{
  "titulo": "Ley del Instituto Electoral y de Participación Ciudadana para el Estado de Coahuila",
  "Contenido": "COAHUILA.\nEL C. ENRIQUE MARTÍNEZ Y MARTÍNEZ, GOBERNADOR CONSTITUCIONAL DEL ESTADO\nINDEPENDIENTE, LIBRE Y SOBERANO DE COAHUILA DE ZARAGOZA, A SUS HABITANTES\nSABED:\nQUE EL CONGRESO DEL ESTADO INDEPENDIENTE, LIBRE Y SOBERANO DE COAHUILA DE\nZARAGOZA,\nDECRETA:\nNÚMERO 172.LEY DEL INSTITUTO ELECTORAL Y DE PARTICIPACIÓN CIUDADANA\nPARA EL ESTADO DE COAHUILA DE ZARAGOZA\nTÍTULO PRIMERO\nPRINCIPIOS FUNDAMENTALES\nCAPÍTULO PRIMERO\nBASES GENERALES\nArtículo 1°. Esta ley es de orden público y de observancia obligatoria en todo el régimen interior del estado, en materia de organización y funcionamiento del Instituto Electoral y de Participación Ciudadana de Coahuila.\nPara los efectos de esta ley, el Instituto Electoral y de Participación Ciudadana de Coahuila se denominará como el Instituto.\nArtículo 2°. El Instituto es un organismo público autónomo, independiente en sus decisiones y funcionamiento y profesional en su desempeño, dotado de personalidad jurídica y patrimonio propio.\nArtículo 3°. El Instituto, en el ámbito de su competencia, tendrá por objeto:\nI. Contribuir al desarrollo de la vida democrática y al fortalecimiento de las convicciones humanistas, sociales y democráticas del estado constitucional de derecho.\nII. Promover, fomentar y preservar el fortalecimiento democrático del sistema de partidos políticos en el estado.\nIII. Promover, fomentar y preservar el ejercicio de los derechos político-electorales de los ciudadanos y vigilar el cumplimiento de sus deberes.\nIV. Garantizar la celebración libre, auténtica y periódica de las elecciones para renovar a los integrantes de los poderes legislativo y ejecutivo, así como de los Ayuntamientos del estado.\nV. Velar por la libertad, autenticidad y efectividad del sufragio popular.\nVI. Llevar a cabo la promoción del voto y coadyuvar a la difusión de la cultura democrática.\nVII. Promover, fomentar y preservar la participación ciudadana.\nArtículo 4°. El Instituto, dentro del régimen interior del estado, se encargará de la preparación, organización, desarrollo, vigilancia y validez de los procesos electorales, de los procedimientos del plebiscito, del referendo, de la iniciativa popular y de la salvaguarda del sistema de partidos políticos, en los términos de las disposiciones aplicables.\nCAPÍTULO SEGUNDO\nEL INSTITUTO COMO ORGANISMO PÚBLICO AUTÓNOMO\nArtículo 5°. El Instituto, dentro del régimen interior del estado, es un organismo público autónomo, en los\nArtículo 6°. La autonomía constitucional del Instituto se basa en los principios de esencialidad, permanencia, independencia, imparcialidad, profesionalismo, transparencia, responsabilidad y sujeción al estado humanista, social y democrático de derecho.\nArtículo 7°. La autonomía del Instituto se expresa en la facultad de resolver con libertad los asuntos de su competencia, sin interferencia de otros poderes u otros organismos públicos autónomos, salvo los medios de control que establezca la Constitución, esta ley y demás disposiciones aplicables.\nArtículo 8°. Para el desarrollo de sus funciones, el Instituto contará con autonomía política, jurídica, administrativa, financiera y presupuestal, en los términos que establece la Constitución Política del\nEstado, esta ley y demás disposiciones aplicables.\nSECCIÓN PRIMERA\nLA AUTONOMÍA POLÍTICA\nArtículo 9°. El Instituto es un organismo autónomo frente a cualquier órgano del gobierno federal, estatal y municipal.\nLa competencia del Instituto se ejercerá por sus órganos conforme a esta ley y su reglamentación y no podrá ser vulnerada o restringida por los gobiernos federal, estatal o municipal.\n(REFORMADO, P.O. 27 DE JUNIO DE 2008)\nArtículo 10. El Instituto es el depositario de la autoridad electoral dentro del régimen interior del estado, responsable del ejercicio de la función estatal de preparar, organizar, desarrollar, vigilar y validar los procesos electorales, los procedimientos del plebiscito, del referendo, de la iniciativa popular y la salvaguarda del sistema de partidos políticos, en los términos de las disposiciones aplicables.\nArtículo 11. El Instituto, en la esfera de su competencia, mantendrá con los gobiernos federal, estatal y municipal y con los organismos públicos autónomos, una relación de respeto y de colaboración mutua para el desarrollo democrático de la entidad.\nPara el desempeño de sus funciones, el Instituto contará con el apoyo, el auxilio y la colaboración de las autoridades federales, estatales y municipales y de los organismos públicos autónomos, bajo los disposiciones aplicables.\nArtículo 12. El Instituto podrá promover controversias constitucionales y acciones de inconstitucionalidad aplicables.\nSECCIÓN SEGUNDA\nLA AUTONOMÍA JURÍDICA Y ADMINISTRATIVA\nArtículo 13. El Instituto, a través del Consejo General, tiene la facultad de establecer la estructura, forma y modalidades de su organización interna, en los términos que establece esta ley en atención a las disponibilidades de su presupuesto de egresos.\nArtículo 14. El Instituto, a través del Consejo General, tiene la facultad de expedir los reglamentos, acuerdos, circulares o cualquier otra disposición general que sea necesaria para el desempeño de sus funciones.\nArtículo 15. El Instituto mediante convenio que celebre con el Instituto Federal Electoral u otra entidad pública federal, estatal o municipal, podrá asumir las funciones o servicios que, en materia electoral o de participación ciudadana, le sean transferidas o delegadas, según su capacidad administrativa y financiera.\nLa transferencia o la delegación de funciones o servicios deberá programarse de manera gradual, a efecto de que el Instituto pueda asumir con responsabilidad la función o servicio de que se trate.\nSECCIÓN TERCERA\nLA AUTONOMÍA FINANCIERA Y PRESUPUESTAL\nArtículo 16. El patrimonio del Instituto estará constituido por:\nI. Los ingresos que perciba conforme a la partida que establezca su presupuesto anual de egresos, así como los que perciba por los servicios que preste en cumplimiento de su objeto o que le correspondan por cualquier otro título legal.\nII. Los bienes muebles e inmuebles y demás ingresos que los gobiernos federal, estatal y municipal le aporten para la realización de su objeto.\nIII. Los subsidios y aportaciones permanentes, periódicas o eventuales, que reciba de los gobiernos federal, estatal y municipal y, en general, los que obtenga de instituciones públicas, privadas o de particulares.\nIV. Las donaciones, herencias y legados que se hicieren a su favor.\nV. Todos los demás bienes o ingresos que adquiera por cualquier otro medio legal.\nArtículo 17. El Instituto elaborará su propio proyecto de presupuesto de egresos y lo remitirá al Ejecutivo del Estado, a fin de que éste lo envíe en su oportunidad al Congreso del Estado, para su estudio, discusión y, en su caso, aprobación. El proyecto de presupuesto de egresos del Instituto no podrá ser para el cumplimiento de su objeto.\nArtículo 18. El Instituto contará con los recursos humanos, financieros y materiales que autorice el presupuesto de egresos correspondiente.\nArtículo 19. El Instituto administrará su patrimonio conforme a las bases siguientes:\nI. Los recursos que integran el patrimonio serán ejercidos en forma directa por los órganos del\nInstituto; o bien, por quien ellos autoricen, conforme a la ley y su reglamento.\nII. El Congreso del Estado revisará y fiscalizará la cuenta pública del Instituto, en los términos de las disposiciones aplicables.\nIII. El ejercicio presupuestal del Instituto deberá ajustarse a los principios de honestidad, legalidad, optimización de recursos, racionalidad e interés público y social.\nIV. El Instituto manejará prudentemente su patrimonio conforme a la ley. En todo caso, el Instituto requerirá el acuerdo de las dos terceras partes de los miembros del Consejo General, para dictar resoluciones que afecten el patrimonio inmobiliario o para celebrar actos o convenios que comprometan al Instituto por un plazo mayor al período de su encargo. El convenio siempre será por un tiempo determinado y con un objeto preciso.\nV. El Instituto podrá celebrar acuerdos con la dependencia del Poder Ejecutivo del Estado que corresponda, para que ésta coadyuve, total o parcialmente, en las funciones relacionadas con la administración, control y fiscalización de su patrimonio.\n(REFORMADA, P.O. 2 DE AGOSTO DE 2007)\nVI. En todo lo relativo a la administración, control y fiscalización de su patrimonio, el Instituto deberá observar las disposiciones aplicables a los órganos del gobierno del estado, según la materia de que se trate, siempre y cuando dichas disposiciones no contravengan los principios rectores de la función electoral.\nArtículo 20. El Instituto gozará respecto de su patrimonio, de las franquicias, exenciones y demás prerrogativas concedidas a los fondos y bienes del estado.\nSECCIÓN CUARTA\nLOS LÍMITES DE LA AUTONOMÍA DEL INSTITUTO\nArtículo 21. Todas las funciones y actividades del Instituto se regirán por los principios de constitucionalidad, legalidad, certeza, independencia, imparcialidad y objetividad.\nArtículo 22. El Instituto se sujetará a los medios de control siguientes:\nI. La controversia constitucional local que ejerza el Pleno del Tribunal Superior de Justicia del Estado de Coahuila.\nIII. El control de revisión y fiscalización que ejerza el Congreso del Estado de Coahuila, a través de la\nAuditoría Superior del Estado.\nArtículo 23. El Instituto, a través de su consejero presidente, deberá rendir un informe por escrito ante el\nCongreso del Estado sobre los trabajos realizados por el Instituto, a más tardar el quince de diciembre de cada año.\nTÍTULO SEGUNDO\nCAPÍTULO PRIMERO\nLA ESTRUCTURA DEL INSTITUTO\nArtículo 24. Para el ejercicio de sus funciones, el Instituto contará con órganos directivos, ejecutivos, técnicos y de vigilancia, en los términos que establece esta ley y la reglamentación que realice el Consejo\nGeneral.\nArtículo 25. Los órganos directivos del Instituto son:\nI. El Consejo General.\nII. La Presidencia del Consejo General.\nIII. Las Comisiones del Consejo General.\nArtículo 26. Los órganos ejecutivos del Instituto son:\nI. La Junta General Ejecutiva.\nII. Los Comités Distritales Electorales.\nIII. Los Comités Municipales Electorales.\nIV. Las Mesas Directivas de Casilla.\nArtículo 27. Los órganos técnicos del Instituto son:\nI. La Dirección General.\nII. La Secretaría Técnica.\nArtículo 28. Los órganos de vigilancia del Instituto son:\nI. La Comisión de Vigilancia, Evaluación y Disciplina.\nII. La Comisión de Contraloría y de Fiscalización.\nArtículo 29. En cada uno de sus órganos, el Instituto contará, para el desempeño de sus funciones, con el apoyo de funcionarios integrados en un cuerpo denominado Servicio Profesional Electoral.\nEl Servicio Profesional Electoral es la base del funcionamiento del Instituto.\nCAPÍTULO SEGUNDO\nLOS ÓRGANOS DIRECTIVOS DEL INSTITUTO\nSECCIÓN PRIMERA\nEL CONSEJO GENERAL\nAPARTADO PRIMERO\nBASES GENERALES\nArtículo 30. El Consejo General es el órgano superior de dirección del Instituto.\nArtículo 31. El Consejo General del Instituto tiene por objeto:\nI. Vigilar el cumplimiento de las disposiciones constitucionales y legales en materia electoral y de participación y organización ciudadana.\nII. Garantizar que los órganos del Instituto cumplan con los principios de constitucionalidad, legalidad, certeza, independencia, imparcialidad y objetividad.\nAPARTADO SEGUNDO\nLA INTEGRACIÓN DEL CONSEJO GENERAL\nArtículo 32. El Consejo General se integrará por cinco consejeros electorales, por un representante de cada partido político, por el Director General y por el Secretario Técnico. Con excepción de los consejeros, los demás podrán concurrir a las sesiones del Consejo General, con voz pero sin voto.\nArtículo 33. Cada partido político tendrá derecho a designar un representante propietario y a un suplente para las sesiones del Consejo General.\nEn todo caso, los representantes de los partidos políticos que sean designados fungirán como consejeros representantes ante el Consejo General.\nLos partidos políticos podrán sustituir en todo tiempo a sus representantes. Para tal efecto, comunicarán con toda oportunidad a través de su representante acreditado ante el Instituto, el aviso correspondiente al consejero presidente.\nAPARTADO TERCERO\nLA DESIGNACIÓN DE LOS CONSEJEROS ELECTORALES\n(REFORMADO, P.O. 2 DE AGOSTO DE 2007)\nArtículo 34. La designación de los consejeros electorales, propietarios y suplentes, se sujetará al procedimiento siguiente:\nI. El Consejo General del Instituto, a más tardar noventa días naturales antes de concluir el periodo constitucional del cargo de consejero electoral, emitirá una convocatoria pública, para que cualquier ciudadano coahuilense, pueda inscribirse dentro del plazo de diez días naturales, a fin que pueda ser examinado el cumplimiento de los requisitos exigidos en la presente ley, para ocupar el cargo de consejero electoral, por conducto del propio Instituto Electoral.\nII. Concluido el plazo para el registro de los aspirantes al cargo de consejero electoral, el Instituto\nElectoral, dentro de los siguientes diez días naturales, emitirá un dictamen que deberá ser aprobado, por las dos terceras partes de los integrantes del Consejo General, en el que señale el número de aspirantes registrados, y establezca quienes cumplieron con los requisitos exigidos en la presente Ley, mismos que continuarán con el procedimiento de selección.\nIII. Los aspirantes que hayan acreditado los requisitos legales, deberán sujetarse a un examen teórico y práctico por escrito, de conocimientos en materia electoral, siendo aplicado conjuntamente por dos instituciones de educación superior del Estado, una pública y otra privada, en los días y horas señalados por el Consejo General del Instituto, que en todo momento coordinará y vigilará lo relativo al procedimiento de aplicación del referido examen, el cual deberá ser efectuado, dentro de los diez días naturales siguientes.\nIV. Conocidos los resultados, el Instituto deberá remitir al Congreso del Estado, los expedientes de los aspirantes que hubieren acreditado los exámenes de que habla la fracción anterior, a fin de que este órgano legislativo dentro de los siguientes veinte días naturales, contados a partir de la fecha en que le sean enviados los expedientes, para que los convoque a comparecer en audiencia pública ante el Pleno del propio Congreso ó ante la Comisión que éste designe para tal efecto.\nV. Concluido el período de audiencias, los grupos parlamentarios de los diferentes partidos representados en el Congreso del Estado, podrán formular sus propuestas del listado de aquellos aspirantes que hayan cumplido con cada uno de los requisitos establecidos en las fracciones anteriores, o en su caso propondrán la ratificación de alguno de los Consejeros Electorales que terminan su periodo, ante una Comisión plural del Congreso del Estado.\nVI. La Comisión plural realizará el dictamen correspondiente y lo presentará al Pleno del Congreso del\nEstado para su discusión y en su caso aprobación.\nVII. Las dos terceras partes de los miembros del Congreso del Estado, aprobarán o rechazarán las designaciones de los consejeros electorales.\nArtículo 35. Para ser designado consejero electoral, propietario o suplente, se deberán cumplir los requisitos siguientes:\n(REFORMADA, P.O. 2 DE AGOSTO DE 2007)\nI. Ser ciudadano mexicano por nacimiento y coahuilense, en pleno ejercicio de sus derechos políticos y civiles, mayor de 27 años de edad el día de su designación.\nII. Estar inscrito en el registro federal de electores y contar con credencial para votar.\n(REFORMADA, P.O. 2 DE AGOSTO DE 2007)\nIII. Poseer al día del registro de aspirantes a ocupar el cargo, título profesional o de formación equivalente y tener conocimientos en la materia político-electoral.\n(REFORMADA, P.O. 2 DE AGOSTO DE 2007)\nIV. No haber desempeñado en ningún caso, un cargo de elección popular federal, estatal o municipal.\nV. No desempeñar un cargo o comisión en cualquiera de los órganos del Instituto Federal Electoral u otro órgano electoral de entidades federativas, diferente al Instituto.\nVI. No haber sido en ningún momento, dirigente de un comité directivo, ejecutivo o equivalente de un partido político a nivel nacional, estatal o municipal, ni representante del mismo ante ningún organismo electoral en el país.\nVII. No tener antecedentes, en ningún caso de una militancia activa, pública y notoria en algún partido político.\nVIII. Gozar de buena reputación y no haber sido condenado por delito doloso que amerite pena de prisión de más de un año; pero si se tratare de robo, fraude, falsificación, abuso de confianza u otro que lastime la buena fama en concepto público, inhabilitará para el cargo cualquiera que haya sido la pena.\nIX. Tener residencia en el estado durante los últimos tres años, salvo el caso de ausencia por desempeño de cargo público al servicio de la federación, del estado o del municipio.\nX. No haber sido Secretario de Estado, ni Procurador General de Justicia del Estado o Subsecretario en la Administración Pública Federal, Estatal o Municipal.\nArtículo 36. Los consejeros electorales, propietarios y suplentes, rendirán la protesta de ley ante el designación.\n(ADICIONADO, P.O. 2 DE AGOSTO DE 2007)\nLos Consejeros Electorales propietarios podrán ser ratificados por el Congreso del Estado, por una sola ocasión, para el periodo inmediato posterior a aquel en que se hayan desempeñado como tales.\nArtículo 37. Los consejeros electorales en funciones, recibirán una remuneración adecuada e irrenunciable por el desempeño de su cargo, la cual no podrá ser disminuida durante su encargo.\nAPARTADO CUARTO\nEL FUNCIONAMIENTO DEL CONSEJO GENERAL\nArtículo 38. El Consejo General celebrará sesiones ordinarias por lo menos una vez al mes, sin perjuicio de celebrar, en cualquier tiempo, las sesiones extraordinarias que sean necesarias para la eficaz marcha del Instituto, previa convocatoria del consejero presidente o de al menos tres de los consejeros electorales.\nArtículo 39. Las sesiones del Consejo General se sujetarán a las reglas siguientes:\nI. Serán válidas cuando se integren con la mitad más uno del total de los consejeros electorales, siempre que esté presente su presidente o quien legalmente deba suplirlo.\nII. Podrán concurrir, con voz pero sin voto, el Director General, el Secretario Técnico y los consejeros representantes de los partidos políticos.\nIII. De toda sesión se levantará el acta respectiva a través del Secretario Técnico. Las actas deberán contener una síntesis del asunto a tratar y el punto acordado. Las actas se resguardarán en el archivo del Instituto por conducto de la Secretaría Técnica.\nIV. El Secretario Técnico al inicio de cada sesión leerá el acta de la sesión anterior para su aprobación. La misma deberá ser autorizada con las firmas del consejero presidente o de quien legalmente deba suplirlo y del propio Secretario Técnico.\nV. Se dará curso a los asuntos listados en el orden del día o de aquellos que requieran la intervención del Consejo General.\nVI. El consejero presidente o quien legalmente deba suplirlo, presidirá la sesión, dirigirá los debates, declarará cerrada la discusión cuando así lo estime y, finalmente, someterá a votación los asuntos correspondientes.\nVII. Las votaciones del Consejo General se tomarán por mayoría de votos de los miembros presentes.\nEn caso de empate, el consejero presidente o quien legalmente deba suplirlo, tendrá voto de calidad.\nVIII. El consejero presidente del Consejo General por sí o a través del Secretario Técnico, deberá ejecutar los acuerdos sin demora. El Consejo General podrá corregir, subsanar o modificar el acuerdo ejecutado cuando advierta un error esencial en el acta que se somete a su aprobación.\nArtículo 40. El Consejo General expedirá los acuerdos necesarios para el debido funcionamiento de los órganos del Instituto.\nAPARTADO QUINTO\nLAS FACULTADES DEL CONSEJO GENERAL\nArtículo 41. Las atribuciones concedidas al Instituto en esta u otras leyes residen originalmente en el\nConsejo General. Los demás órganos del Instituto creados por esta ley o su reglamento, podrán ejercer esas u otras facultades en los casos siguientes:\nI. Cuando esta u otras leyes les otorguen expresamente las atribuciones.\nII. Cuando por acuerdo del Consejo General se deleguen las atribuciones para el mejor funcionamiento del Instituto.\nArtículo 42. El Consejo General tendrá las atribuciones siguientes:\nI. Vigilar el cumplimiento de las disposiciones constitucionales y legales en materia electoral y de participación y organización ciudadana; así como dictar las normas y previsiones destinadas a hacer efectivas tales disposiciones.\n(REFORMADA, P.O. 2 DE AGOSTO DE 2007)\nII. Promover de manera permanente la educación cívica y la participación de los ciudadanos en los procesos electorales, así mismo desarrollar un programa de difusión para los niños y jóvenes del sistema educativo público y privado del Estado para dar a conocer la importancia de elegir a nuestros representantes populares.\nIII. Celebrar convenios de apoyo y colaboración con autoridades federales, estatales o municipales, así como con el Instituto Federal Electoral.\nIV. Establecer la estructura administrativa de los órganos del Instituto.\n(REFORMADA, P.O. 2 DE AGOSTO DE 2007)\nV. Establecer y regular la integración, organización, funcionamiento y atribuciones de las Comisiones del Instituto y demás comisiones o subcomisiones que establezca esta ley o que cree el Consejo\nGeneral para el debido funcionamiento del Instituto, con el número de miembros que para cada caso se determine.\nVI. Expedir los reglamentos interiores, circulares y lineamientos generales necesarios para el funcionamiento del Instituto y sus órganos.\nVII. Formular y aprobar el estatuto del Servicio Profesional Electoral.\nIX. Dirimir cualquier tipo de conflicto competencial entre los órganos del Instituto, resolviendo en definitiva.\nX. Preparar, organizar, desarrollar y validar los procesos electorales, plebiscitarios, de referendo e iniciativa popular, en los términos de la ley de la materia.\nXI. Aprobar el proyecto de presupuesto anual de egresos del Instituto, a efecto de que el consejero presidente lo envíe al Ejecutivo del Estado para los efectos correspondientes.\nXII. Acreditar a los partidos políticos nacionales que, una vez satisfechos los requisitos que establece la ley de la materia, soliciten la inscripción de su registro.\nXIII. Resolver, en los términos de la ley aplicable, el otorgamiento o pérdida del registro de los partidos políticos y de las asociaciones políticas estatales.\nPara el efecto del otorgamiento del registro, contará con una comisión de verificación para el registro de partidos políticos estatales, integrada por tres consejeros electorales designados por la mayoría de los miembros del Consejo General.\nLa comisión revisará que los partidos solicitantes cumplan con los requisitos que establezca la ley correspondiente.\nXIV. Resolver sobre los convenios de coalición. Para este efecto, contará con una comisión de verificación para el registro de coaliciones, integrada por tres consejeros electorales. La comisión revisará que los partidos solicitantes cumplan con los requisitos que establece la ley de la materia.\nXV. (DEROGADA, P.O. 2 DE AGOSTO DE 2007)\n(REFORMADA, P.O. 2 DE AGOSTO DE 2007)\nXVI. Regular los mecanismos para que los partidos políticos puedan acceder en forma equitativa a los medios de comunicación social y realizar las gestiones necesarias a fin de que estos ofrezcan tarifas iguales a los participantes en un proceso electoral local.\nXVII. Propiciar condiciones de equidad en la competencia electoral.\nXVIII. (DEROGADA, P.O. 2 DE AGOSTO DE 2007)\nXIX. Monitorear el comportamiento de los medios de comunicación durante los procesos electorales.\nXX. Registrar los nombramientos de los representantes que las dirigencias estatales de los partidos políticos hayan designado para integrar el Instituto y los comités distritales y municipales electorales, así como los de sus dirigentes federales, estatales y municipales.\nXXI. Proveer lo necesario para que lo relativo a las prerrogativas de los partidos políticos se ejerzan con apego a la ley, así como fijar topes al gasto que puedan hacer éstos en sus campañas electorales en los términos de las disposiciones aplicables.\nXXII. Verificar y, en su caso, aprobar la aplicación que del financiamiento otorgado realicen los partidos políticos. Para tal efecto, el Instituto contará con una Comisión de Contraloría y de Fiscalización que estará integrada y tendrá las facultades que establece esta ley.\nXXIII. Expedir los lineamientos que estime necesarios para reglamentar la fiscalización en el uso y aplicación de los recursos recibidos por los partidos políticos.\nXXIV. Designar a las personas que integrarán los comités distritales y municipales electorales. importancia requieran difusión. La integración de los comités distritales y municipales electorales deberá darse a conocer a través del órgano informativo.\nXXVI. Cuidar el debido funcionamiento de los comités distritales y municipales electorales.\nXXVII.Proporcionar a los órganos electorales la documentación y el material electoral necesarios para el desarrollo de las jornadas electorales.\nXXVIII. Resolver sobre el número de casillas extraordinarias que se instalarán en el estado, observando las prevenciones que señale esta misma ley.\nXXIX. Designar, en los casos previstos por la ley aplicable, a los funcionarios que integrarán las mesas directivas de casilla.\nXXX. Resolver sobre el proyecto de material electoral y aprobar su elaboración.\nXXXI. Integrar y distribuir en los términos de la ley de la materia, los paquetes de material electoral para cada casilla.\nXXXII.Recibir las solicitudes de registro de los candidatos a Gobernador del Estado y resolver sobre ellas en los términos de la ley aplicable.\nXXXIII. Recibir y resolver supletoriamente las solicitudes de registro de candidatos a diputados o integrantes de los Ayuntamientos.\nXXXIV. Hacer públicos los resultados preliminares del proceso electoral.\nXXXV. Realizar el cómputo estatal de la elección de Gobernador, declarar la validez de la elección, entregar la constancia de mayoría correspondiente y declarar formalmente electo al Gobernador\nConstitucional del Estado de Coahuila.\nXXXVI. Realizar el cómputo estatal para la elección de diputados de representación proporcional, hacer la asignación correspondiente y entregar las constancias respectivas.\n(REFORMADA, P.O. 2 DE AGOSTO DE 2007)\nXXXVII. Dictaminar sobre cualesquiera de los hechos relacionados con el proceso electoral y, de manera especial, sobre los que denuncien los partidos políticos y que se consideren contrarios a la ley.\n(REFORMADA, P.O. 2 DE AGOSTO DE 2007)\nXXXVIII. Expedir la reglamentación necesaria para regular la propaganda de los partidos políticos, a fin de evitar contaminación visual y la afectación del entorno urbano y del medio ambiente.\nXXXIX. Supervisar, vigilar y auditar en cualquier tiempo el origen, el ejercicio y el destino de los recursos de los partidos políticos y de los candidatos.\nXL. Propiciar condiciones de legalidad, certidumbre y transparencia a los observadores electorales.\nXLI. Organizar y promover debates incluyentes entre los candidatos que por medio del partido político que los postulen lo soliciten, conforme lo establezca el reglamento que para tal efecto apruebe el propio Consejo General.\nXLII. Preparar, organizar o validar las elecciones internas de los partidos políticos, a solicitud por cuenta con la capacidad y condiciones para acceder a tal solicitud.\nXLIII. Organizar y validar las elecciones de las organizaciones y asociaciones de la comunidad, cuando convenios correspondientes.\nXLIV. Resolver los casos no previstos en la ley aplicable.\nXLV. Las demás que le confiera esta ley u otras disposiciones legales aplicables.\nArtículo 43. Los consejeros electorales tendrán las siguientes atribuciones:\nI. Velar por la autenticidad y efectividad del sufragio.\nII. Promover, supervisar y participar en los programas de formación cívica y capacitación electoral.\nIII. Orientar a los ciudadanos en el ejercicio de sus derechos y en el cumplimiento de sus deberes en materia político electoral.\nIV. Desempeñar las tareas que el propio Instituto les encomiende.\nV. Formar parte de las comisiones y subcomisiones que acuerde el Consejo General.\nVI. Las demás que esta ley u otras disposiciones aplicables les confieran.\nAPARTADO SEXTO\nLA FUNCIÓN PÚBLICA DE LOS CONSEJEROS ELECTORALES\nArtículo 44. Los consejeros electorales desempeñan una función pública. En todo caso, la función de los consejeros electorales se sujetará a los principios de autonomía, independencia, legalidad, excelencia, profesionalismo, imparcialidad, objetividad, probidad y honestidad.\nArtículo 45. Durante el desempeño de su función, los consejeros electorales del Consejo General no podrán ocupar ningún otro empleo, cargo o comisión oficial, excepción hecha en los que actúen en representación del Consejo General y de los que desempeñen en forma honorífica o de fe pública o en asociaciones docentes, científicas, culturales, de investigación o de beneficencia.\nArtículo 46. Los consejeros electorales no podrán utilizar en beneficio propio o de terceros, la información confidencial de que dispongan en razón de su cargo, ni tampoco podrán divulgarla sin autorización del Consejo General.\nArtículo 47. Los consejeros electorales estarán sujetos al régimen de responsabilidades de los reglamentaria y de esta ley.\nAPARTADO SÉPTIMO\nEL RÉGIMEN DE AUSENCIAS DEL CONSEJO GENERAL\nArtículo 48. En caso de ausencia temporal o definitiva de algún consejero electoral propietario, el consejero presidente llamará al consejero electoral suplente que corresponda, según el orden de prelación en que fueron designados por el Congreso del Estado, para que desempeñe la función en forma temporal o definitiva, según se trate. separación provisional de su cargo, previo permiso o licencia del Consejo General. Por ausencia pueda seguir ejerciendo su función, por renuncia, remoción definitiva del cargo, ausencia definitiva o cualquier otra causa grave justificada.\nArtículo 49. Para suplir las ausencias temporales o definitivas de los representantes propietarios de los partidos políticos, el consejero presidente llamará al correspondiente suplente.\nArtículo 50. Las ausencias temporales del consejero presidente las suplirá el consejero electoral propietario que designe el propio presidente.\nArtículo 51. Se considerará ausencia definitiva la inasistencia consecutiva y, sin causa justificada, de disposiciones legales.\nSECCIÓN SEGUNDA\nLA PRESIDENCIA DEL CONSEJO GENERAL\nArtículo 52. Los consejeros electorales propietarios nombrarán por voto secreto y por mayoría de votos al presidente del Consejo General, que lo será también del Instituto durante todo el tiempo que dure su encargo como consejero electoral. Sólo en el caso de ausencia definitiva del presidente, los consejeros electorales nombrarán de nueva cuenta y de entre ellos mismos, a quien deba sustituirlo. En este último caso, el consejero presidente durará en su encargo el tiempo que reste de su período como consejero electoral.\nLa designación del consejero presidente se comunicará de inmediato al Congreso del Estado para su conocimiento.\nArtículo 53. La Presidencia del Consejo General tendrá las atribuciones siguientes:\nI. Representar legalmente al Instituto.\nII. Velar por la unidad y cohesión de las actividades de los órganos del Instituto.\nIII. Establecer los vínculos necesarios entre el Instituto y el Instituto Federal Electoral y las demás autoridades federales, estatales y municipales, para lograr su apoyo, colaboración y auxilio, en sus respectivos ámbitos de competencia.\nIV. Convocar y conducir las sesiones del Consejo General.\nV. Instruir los asuntos del Consejo General hasta ponerlos en estado de resolución.\nVI. Vigilar el cumplimiento de los acuerdos adoptados por el propio Consejo General.\nVII. Proponer al Consejo General el nombramiento del Director General y del Secretario Técnico del\nInstituto.\nVIII. Proponer anualmente al Consejo General el anteproyecto de presupuesto de egresos del Instituto para su aprobación. por el Consejo General, en los términos de la ley de la materia.\nX. Ejercer las partidas presupuestales aprobadas.\nXI. Ejercer, previo acuerdo del Consejo General, actos de dominio.\nXII. Rendir los informes ante las autoridades competentes, en representación del Consejo General o del Instituto.\nXIII. Otorgar poderes generales y especiales para actos de administración y pleitos y cobranzas, de conformidad con la ley.\nXIV. Presidir la Junta General Ejecutiva e informar al Consejo General de los trabajos de la misma.\nXV. Emitir los acuerdos necesarios para el funcionamiento interno de la presidencia.\nXVI. Nombrar y remover libremente al personal de confianza y de base adscrito a la propia presidencia, conforme a las disposiciones aplicables.\nXVII. Las demás que le confiera esta ley u otras disposiciones aplicables.\nSECCIÓN TERCERA\nLAS COMISIONES DEL CONSEJO GENERAL\nAPARTADO PRIMERO\nBASES GENERALES\nArtículo 54. Las Comisiones del Consejo General son:\nI. La Comisión de Administración.\nII. La Comisión de Asuntos Jurídicos.\nIII. La Comisión de Organización y Capacitación.\nIV. La Comisión de Participación Ciudadana.\n(REFORMADO, P.O. 2 DE AGOSTO DE 2007)\nEstos órganos directivos y las demás comisiones que se prevean en esta ley u otras disposiciones aplicables o que sean creadas por el Consejo General para la eficaz marcha del Instituto, funcionarán con el apoyo de las direcciones del Instituto.\nArtículo 55. El objeto de las comisiones radica en la función dictaminadora de los asuntos de su competencia, a efecto de someter su proyecto de dictamen al Consejo General para que éste decida lo que proceda. pueda resolver en definitiva los asuntos de su competencia conforme a las disposiciones aplicables, sin necesidad de la aprobación del Consejo General.\nArtículo 56. Las comisiones del Instituto tendrán la competencia y las atribuciones que les otorga esta ley u otras disposiciones aplicables.\nEl Consejo General podrá delegar funciones a las comisiones.\nArtículo 57. Cada comisión estará integrada por tres consejeros electorales. De entre ellos, elegirán a un presidente de la Comisión, que coordinará los trabajos de la misma.\nArtículo 58. Las comisiones del Consejo General para realizar el desahogo de sus funciones contarán con el apoyo de las direcciones del Instituto, según la comisión de la cual se trate.\nAPARTADO SEGUNDO\nLA COMISIÓN DE ADMINISTRACIÓN\nArtículo 59. La Comisión de Administración se encargará de supervisar el manejo de los recursos financieros, humanos y técnicos del Instituto, cuidando en todo momento la correcta administración y ejercicio del presupuesto de egresos correspondiente.\nLas facultades de la Comisión de Administración se llevarán a cabo por conducto de la Dirección de\nAdministración en los términos de las disposiciones aplicables.\nArtículo 60. La Comisión de Administración tendrá las atribuciones siguientes:\nI. Aplicar las políticas, normas y procedimientos para la administración de los recursos financieros y materiales establecidas por el Consejo General.\nII. Informar al Consejo General de los bienes muebles e inmuebles que se requieran para el desempeño de las funciones del Instituto.\nIII. Vigilar la conservación de los equipamientos y de las instalaciones que se hayan asignado al\nInstituto.\nIV. Suministrar los recursos materiales que sean requeridos para el correcto funcionamiento del\nInstituto.\nV. Dirigir las labores del personal administrativo del Instituto.\nVI. Llevar el libro de registro de proveedores del material necesario para la función electoral.\nVII. Organizar, dirigir y controlar la administración de los recursos materiales y financieros, así como la prestación de los servicios generales en el Instituto.\nVIII. Cumplir las disposiciones que para la aplicación del presupuesto financiero, estipulen los ordenamientos aplicables.\nIX. Establecer y operar los sistemas administrativos para el ejercicio y control presupuestal.\nX. Elaborar el proyecto del manual de organización y operación del personal del Instituto, a fin de someterlo a la consideración del Consejo General.\nXI. Conocer y atender las necesidades administrativas del Instituto.\nXII. Presentar al consejero presidente un informe trimestral de su actuación y un informe anual respecto al ejercicio presupuestal del Instituto.\nXIII. Elaborar las convocatorias públicas, licitaciones y concursos para la adquisición de bienes y servicios en los términos que establezca la ley aplicable y demás disposiciones aplicables.\nXIV. Cumplir y hacer cumplir los acuerdos del Consejo General que se refieran a asuntos de su competencia.\nXV. Las demás que le confiera esta ley, otras disposiciones aplicables o el Consejo General.\nAPARTADO TERCERO\nLA COMISIÓN DE ASUNTOS JURÍDICOS\nArtículo 61. La Comisión de Asuntos Jurídicos se encargará de supervisar las cuestiones legales relacionadas con el funcionamiento del Instituto.\nAsuntos Jurídicos en los términos de las disposiciones aplicables.\nArtículo 62. La Comisión de Asuntos Jurídicos tendrá las atribuciones siguientes:\nI. Realizar y emitir los dictámenes jurídicos que le solicite el Consejo General, las comisiones o cualquier otro órgano del Instituto.\nII. Resolver las consultas jurídicas respecto de los asuntos que se le encomienden.\nIII. Compilar y sistematizar los criterios de resolución que emitan los órganos del Instituto, el Poder\nJudicial del Estado, el Instituto Federal Electoral, el Poder Judicial de la Federación u otras autoridades con relación a la materia electoral o de participación ciudadana.\nIV. Integrar el archivo de las actuaciones del Instituto ante los tribunales.\nV. Auxiliar al Consejo General en la interpretación de las disposiciones legales.\nVI. Formular y revisar los formatos de actas, boletas, cédulas de registro y demás documentos que se utilicen en los procesos electorales.\nVII. Integrar las comisiones y subcomisiones que se le encomienden.\nVIII. Formular los informes justificados que las autoridades competentes soliciten al Instituto.\nIX. Promover las actuaciones e interponer los recursos legales que correspondan, ante los órganos competentes.\nX. Auxiliar al Consejo General en el puntual cumplimiento de las resoluciones de los tribunales y de las autoridades electorales competentes.\nXI. Presentar al consejero presidente un informe trimestral de su actuación.\nXII. Cumplir y hacer cumplir los acuerdos del Instituto que se refieran a los asuntos de su competencia.\nXIII. Las demás que le confiera esta ley, otras disposiciones aplicables o el Consejo General.\nAPARTADO CUARTO\nLA COMISIÓN DE ORGANIZACIÓN Y CAPACITACIÓN\nArtículo 63. La Comisión de Organización y Capacitación se encargará de supervisar la organización, casilla, a fin de promover el adecuado funcionamiento del proceso electoral, así como de la capacitación permanente de los ciudadanos que participarán como funcionarios, con la finalidad de que desempeñen correctamente su encomienda durante el desarrollo de la jornada electoral.\nDirección de Organización y Capacitación en los términos de las disposiciones aplicables.\nArtículo 64. La Comisión de Organización y Capacitación tendrá las atribuciones siguientes:\nI. Colaborar en la integración, insaculación de ciudadanos y funcionamiento de las mesas directivas de casilla.\nII. Elaborar los proyectos de formatos de la documentación y material electoral.\nIII. Proveer lo necesario para la impresión y distribución de la documentación electoral.\nIV. Recabar de los comités distritales y municipales electorales copias de las actas de las sesiones que celebren y demás documentos relacionados con el proceso electoral, en los términos de las disposiciones aplicables.\nV. Llevar la estadística de las elecciones.\nVI. Coadyuvar en las tareas del Consejo General a efecto de que la documentación electoral esté debidamente integrada y de que sea recibida oportunamente por los comités distritales y municipales electorales, para el eficaz desarrollo de la jornada electoral.\nVII. Revisar que la conformación de los distritos electorales cumpla con los requisitos legales y, en su caso, proponer al Director General las modificaciones necesarias.\nVIII. Conformar e integrar los paquetes electorales y hacerse responsable de su entrega, así como del resto del material electoral dentro del proceso.\nIX. Proveer lo necesario para desarrollar el programa de los resultados preliminares de la elección.\nX. Realizar lo conducente al registro y acreditación de los observadores electorales del proceso.\nXI. Recabar la documentación electoral y los paquetes de votación de los respectivos comités en la etapa posterior a las elecciones conducentes.\nXII. Elaborar y proponer al Consejo General los programas de capacitación electoral a ciudadanos, que serán desarrollados por los comités municipales.\nXIII. Supervisar y apoyar a los comités municipales en la aplicación de los programas de capacitación electoral a ciudadanos.\nXIV. Diseñar, proponer y preparar el material didáctico y los instructivos electorales, así como los programas de promoción del voto y de capacitación del Instituto.\nXV. Promover ante los ciudadanos, en el ámbito de su competencia, el ejercicio de sus derechos y el cumplimiento de sus deberes electorales.\nXVI. Llevar el registro de los capacitadores que participen en los programas de capacitación electoral a ciudadanos, así como realizar la evaluación de su desempeño.\nXVII. Asesorar a los integrantes de los comités distritales y municipales electorales sobre el contenido, apoyo didáctico y aplicación de los programas de capacitación electoral.\nXVIII. Presentar al consejero presidente un informe trimestral de su actuación.\nXIX. Cumplir y hacer cumplir los acuerdos del Instituto que se refieran a los asuntos de su competencia.\nXX. Elaborar y ejecutar el programa de educación cívica dirigido a los diferentes niveles de educación del estado.\nXX. Las demás que le confiera esta ley, otras disposiciones aplicables o el Consejo General.\nAPARTADO QUINTO\nLA COMISIÓN DE PARTICIPACIÓN CIUDADANA\n(REFORMADO, P.O. 2 DE AGOSTO DE 2007)\nArtículo 65. La Comisión de Participación Ciudadana se encargará de supervisar la instrumentación de los procedimientos del plebiscito, referendo, iniciativa popular e integración, vigilancia y certificación de los Consejos de Participación Ciudadana, en los términos de las disposiciones aplicables.\nLos trabajos operativos se realizarán por los miembros del Instituto designados por la Dirección General.\nArtículo 66. La Comisión de Participación Ciudadana tendrá las atribuciones siguientes:\nI. Elaborar el Programa de Participación Ciudadana, para presentarlo a su discusión y, en su caso, aprobación al Consejo General.\nII. Conocer, estudiar y dictaminar toda solicitud de plebiscito y referendo para que el Consejo General resuelva sobre su procedencia.\n(REFORMADA, P.O. 27 DE JUNIO DE 2008)\nIII. Validar el porcentaje ciudadano del plebiscito y referendo.\nIV. Instrumentar los procedimientos del plebiscito, referendo y de integración, vigilancia y certificación de los Consejos de Participación Ciudadana, en los términos de las disposiciones aplicables.\nV. Presentar al consejero presidente un informe trimestral de su actuación.\nVI. Cumplir y hacer cumplir los acuerdos del Instituto que se refieran a asuntos de su competencia.\nVII. Las demás que le confiera esta ley, otras disposiciones aplicables o el Consejo General.\nCAPÍTULO TERCERO\nLOS ÓRGANOS EJECUTIVOS DEL INSTITUTO\nSECCIÓN PRIMERA\nLA JUNTA GENERAL EJECUTIVA\nArtículo 67. La Junta General Ejecutiva del Instituto será presidida por el consejero presidente del\nConsejo General y se integrará por el Director General y el Secretario Técnico, así como los directores de área del Instituto.\nArtículo 68. La Junta General Ejecutiva tendrá las siguientes atribuciones:\nI. Proponer a la aprobación del Consejo General las políticas generales, los programas y los procedimientos administrativos del Instituto.\nII. Proponer al Consejo General el Programa de Capacitación Electoral a ciudadanos que hayan resultado insaculados, así como los materiales didácticos que se ocuparán para la capacitación.\nIII. Proponer al Consejo General programas de educación cívica en materia electoral.\nIV. Supervisar, vigilar y evaluar el desempeño del Servicio Profesional Electoral.\nV. Supervisar, vigilar y evaluar el cumplimiento de los programas de capacitación electoral y educación cívica del Instituto.\nVI. Integrar los expedientes relativos a las faltas administrativas de los partidos políticos y del personal del Instituto y, en su caso, los correspondientes a la imposición de sanciones, a efecto de someterlos al Consejo General en los términos de las disposiciones aplicables.\nVII. Supervisar el cumplimiento de las normas aplicables a los partidos políticos y sus prerrogativas.\nVIII. Elaborar las listas de los candidatos a ocupar los cargos de consejeros distritales o municipales, según corresponda, en los comités distritales y municipales electorales, y someterlos a la consideración del Consejo General para que éste proceda a su designación.\nIX. Sustanciar en los términos de las disposiciones aplicables, el procedimiento de pérdida de registro del partido político, en los casos en que se encuentre en los supuestos previstos en la ley de la materia. La sustanciación se tramitará hasta el estado de resolución. Dicha resolución será dictada por el Consejo General del Instituto.\nX. Las demás que le atribuya esta ley u otras disposiciones aplicables, o bien, las que le asigne el\nConsejo General o su consejero presidente.\nSECCIÓN SEGUNDA\nLOS COMITÉS DISTRITALES, MUNICIPALES Y LAS MESAS DE CASILLAS\nAPARTADO PRIMERO\nBASES GENERALES\nArtículo 69. El Estado, los ciudadanos y los partidos políticos son corresponsables de la preparación, la organización, el desarrollo y la vigilancia del proceso electoral, desconcentrándose algunas de las funciones inherentes al proceso electoral, según se establece en la presente ley, a través de los órganos siguientes:\nI. Comités Distritales Electorales.\nII. Comités Municipales Electorales.\nIII. Mesas Directivas de Casilla.\nAPARTADO SEGUNDO\nLOS COMITÉS DISTRITALES ELECTORALES\nArtículo 70. Los comités distritales electorales son órganos encargados de la preparación, organización, desarrollo y vigilancia del proceso electoral para la elección de diputados del Congreso del Estado, dentro de sus respectivos distritos, conforme a lo estipulado en esta ley y demás disposiciones aplicables.\nArtículo 71. En cada uno de los distritos electorales en que se divida el estado, funcionará un comité distrital electoral, con residencia en la cabecera del distrito correspondiente.\nLos comités distritales electorales podrán contar, para su auxilio, con delegados municipales los que serán suficientes para cubrir las necesidades que por el número de electores y la configuración del distrito se presenten.\nArtículo 72. Los comités distritales electorales se integrarán con un presidente, un secretario y tres consejeros distritales electorales designados por el Consejo General del Instituto y por un representante de cada uno de los partidos políticos en los términos que establezca la ley aplicable.\nPor cada miembro propietario habrá un suplente. Todos los integrantes de los comités distritales electorales, con excepción de los representantes de partido, tendrán derecho a voz y voto. Los representantes de los partidos políticos únicamente tendrán derecho a voz.\nArtículo 73. Para ser presidente, secretario y consejero distrital electoral de un comité distrital electoral, se requiere:\nI. Ser ciudadano mexicano por nacimiento, en pleno ejercicio de sus derechos políticos y civiles.\nII. Ser originario o con residencia no menor de un año en el estado.\nIII. No desempeñar o haber desempeñado cargos de elección popular, en los últimos dos años anteriores a su designación.\nIV. No ser funcionario público federal, estatal o municipal, exceptuando aquellos que realicen actividades docentes o de investigación. Ni haber sido funcionario de primer nivel durante el último año anterior a la fecha de su nombramiento.\nV. No formar parte ni haber formado parte en los últimos cinco años de algún órgano de dirección de los partidos políticos a nivel nacional, estatal, distrital o municipal.\nVI. Tener un modo honesto de vivir, ser de reconocida probidad y contar con conocimientos para el desempeño adecuado de sus funciones.\nArtículo 74. Los comités distritales electorales sesionarán cuando se cuente con la presencia de la mayoría de sus integrantes, con derecho a voto, entre los cuales deberá estar presente su presidente. De no existir quórum, se citará nuevamente y la sesión se celebrará con quienes asistan, debiendo estar presentes, en todo caso, el presidente, el secretario y un consejero distrital electoral o su suplente.\nLas decisiones se tomarán por mayoría de votos. En caso de empate, el voto del presidente será de calidad.\nArtículo 75. Los comités distritales electorales tendrán las atribuciones siguientes:\nI. Observar la ley en lo relativo a sus funciones y cumplir con los acuerdos que dicte el Consejo General.\nII. Intervenir, dentro de sus respectivos distritos en la preparación, organización, desarrollo y vigilancia del proceso electoral.\nIII. Recibir y resolver las solicitudes de registro de candidatos a diputados que sean presentadas por los diversos partidos políticos.\nIV. Resolver sobre las peticiones que le sometan los ciudadanos, los candidatos y los partidos políticos relativas a la integración y funcionamiento de las mesas directivas de casilla, al desarrollo del proceso electoral y demás asuntos de su competencia.\nV. Realizar el cómputo distrital para la elección de diputados de mayoría relativa.\nVI. Declarar la validez de las elecciones.\nVII. Expedir y entregar la correspondiente constancia de mayoría, informando inmediatamente de todas sus actuaciones al Consejo General.\nVIII. Declarar formalmente electos a los diputados del Congreso del Estado.\nIX. Enviar la documentación del cómputo distrital al Instituto, para que éste a su vez, realice el cómputo estatal correspondiente.\nX. Remitir al Instituto copia certificada por el secretario, de las actas de las sesiones que celebre e informar sobre el desarrollo de sus funciones.\n(REFORMADA, P.O. 2 DE AGOSTO DE 2007)\nXI. Designar al personal técnico, auxiliar, administrativo y manual que sea necesario para el desempeño de sus funciones, previa consulta con la Dirección General.\nXII. Auxiliar a los comités municipales electorales de su jurisdicción en el proceso de capacitación y selección de funcionarios de las mesas directivas de casilla.\nXIII. Las demás que le confiera esta ley, otras disposiciones aplicables o el Consejo General.\nAPARTADO TERCERO\nLOS COMITÉS MUNICIPALES ELECTORALES\nArtículo 76. Los comités municipales electorales son los órganos encargados de la organización, preparación, desarrollo y vigilancia, dentro de su circunscripción, de los procesos electorales para la elección de gobernador e integrantes de los ayuntamientos.\nArtículo 77. Los comités municipales electorales se integrarán por un presidente, un secretario y tres consejeros municipales electorales, designados por el Consejo General del Instituto y por un representante de cada uno de los partidos políticos en los términos que establezca la ley de la materia.\nPor cada miembro propietario habrá un suplente. Los integrantes de los comités municipales electorales tendrán derecho a participar con voz y voto, con excepción de los representantes de los partidos, que sólo tendrán derecho a voz.\nArtículo 78. Los Ayuntamientos podrán proporcionar a los comités municipales electorales, los recursos económicos, materiales y humanos necesarios para el desarrollo de los procesos electorales en la medida de sus posibilidades.\nArtículo 79. Para ser presidente, secretario y consejero ciudadano de un comité municipal electoral, se requiere:\nI. Ser ciudadano mexicano por nacimiento, en pleno ejercicio de sus derechos políticos y civiles.\nII. Ser originario o con residencia no menor de tres años en el estado.\nIII. No desempeñar o haber desempeñado cargos de elección popular, en los últimos dos años anteriores a su designación.\nIV. No ser funcionario público federal, estatal o municipal, exceptuando aquellos que realicen actividades docentes o de investigación. Ni haber sido funcionario de primer nivel durante el último año anterior a la fecha de su nombramiento.\nV. No haber formado parte en los últimos dos años de algún órgano de dirección de los partidos políticos a nivel nacional, estatal, distrital o municipal.\nVI. Tener un modo honesto de vivir y contar con conocimientos para el desempeño adecuado de sus funciones.\nArtículo 80. Los comités municipales electorales sesionarán cuando cuenten con la asistencia de la mayoría de sus integrantes con derecho a voto, entre los cuales deberá estar presente su presidente. De no existir quórum, se citará nuevamente y la sesión se celebrará con quienes asistan, debiendo estar presentes, en todo caso, su presidente, el secretario y un consejero o su suplente.\nArtículo 81. Los comités municipales electorales tendrán las atribuciones siguientes:\nI. Observar la ley y los acuerdos que dicte el Consejo General en el ámbito de su competencia.\nII. Intervenir dentro de su jurisdicción en la preparación, organización, desarrollo y vigilancia de los procesos electorales de gobernador y Ayuntamientos.\n(REFORMADA, P.O. 2 DE AGOSTO DE 2007)\nIII. Ejecutar un programa de capacitación electoral a ciudadanos que servirá para designar a los funcionarios de las mesas directivas de casilla, bajo los lineamientos que para tal efecto emita el\nConsejo General.\nIV. Participar en la designación de funcionarios de casilla en los términos que establezca la ley correspondiente.\nV. Registrar los candidatos para integrar el ayuntamiento de su jurisdicción en los términos de las disposiciones aplicables.\nVI. Registrar a los representantes de partido o coalición ante las mesas directivas de casilla.\nVII. Seleccionar los lugares en que habrán de ubicarse las casillas en cada una de las secciones de su municipio.\nVIII. Remitir al Consejo General copia de las actas de cada una de las sesiones que celebre e informar sobre el desarrollo del proceso electoral.\nIX. Designar al personal técnico, auxiliar, administrativo y manual que sea necesario para el desempeño de sus funciones, previa consulta con la Dirección General.\nX. Realizar el cómputo municipal de la votación para Gobernador del Estado y remitir al Instituto los resultados de la misma.\nXI. Realizar el cómputo municipal de la elección de Ayuntamientos; declarar la validez de la elección; expedir y entregar la constancia de mayoría respectiva, así como las constancias de asignación que inmediato los resultados al Instituto.\nXII. Declarar formalmente electos a los miembros del Ayuntamiento respectivo.\nXIII. Coadyuvar con los comités distritales electorales de su jurisdicción, en el ejercicio de sus atribuciones.\nXIV. Entregar a los presidentes de las mesas directivas de casilla, el material y la documentación necesaria para el debido cumplimiento de sus funciones.\nXV. Las demás que les confiera esta ley u otras disposiciones aplicables, o el Consejo General.\nAPARTADO CUARTO\nLAS MESAS DIRECTIVAS DE CASILLA\nArtículo 82. Las mesas directivas de casilla, son los órganos electorales integrados por ciudadanos, facultados para recibir la votación y realizar el escrutinio y cómputo en cada una de las secciones electorales en que se divida la entidad.\nLas mesas directivas de casilla deberán, durante la jornada electoral, respetar y hacer respetar la libre emisión y efectividad del voto, garantizar su secreto y asegurar la autenticidad del escrutinio y cómputo.\nArtículo 83. Las mesas directivas de casilla se integrarán con un presidente, un secretario técnico, un escrutador y un suplente, quien entrará en función de cualquiera de los otros funcionarios propietarios en los casos previstos por la ley correspondiente.\nEl Instituto, en coordinación con los comités distritales y municipales electorales será el responsable de la designación de los funcionarios de las mesas directivas de casilla y de la ubicación de las mismas.\nArtículo 84. Las personas a quienes corresponda asistir a los cursos de capacitación para aspirantes a funcionarios de las mesas directivas de casilla, así como los que hayan sido seleccionados como funcionarios cuando fueren trabajadores o funcionarios, tendrán derecho a que sus patrones les concedan los permisos con goce de sueldo y demás prestaciones salariales, correspondientes a los días de trabajo en que hayan tenido que asistir a capacitarse, así como el del día de la jornada electoral cuando les hubiese correspondido trabajar. autoridades competentes, toda irregularidad o violación a los derechos del ciudadano que cometa su patrón con motivo de sus obligaciones político-electorales.\nArtículo 85. Para ser integrante de la mesa directiva de casilla se requiere:\nI. Ser ciudadano residente en la sección electoral que comprenda la casilla. En el caso del secretario técnico preferentemente se buscará que cumpla con este requisito.\nII. Estar inscrito en el registro federal de electores y contar con credencial para votar.\nIII. Estar en ejercicio de sus derechos civiles y políticos.\nIV. Saber leer y escribir y tener un modo honesto de vivir.\nV. Haber participado en los cursos de capacitación electoral a ciudadanos impartidos por los órganos electorales.\nVI. No ser servidor público de confianza con mando superior, ni tener cargo de dirección partidista.\nVII. Los secretarios técnicos tendrán que ser personas que no hayan militado en un partido político ni hayan sido representantes de aquellos ante cualquier órgano electoral.\nArtículo 86. Las mesas directivas de casilla tendrán las atribuciones siguientes:\nI. Instalar y clausurar la casilla en los términos previstos por las disposiciones aplicables.\nII. Recibir los resultados de la votación.\nIII. Efectuar el escrutinio y cómputo de la votación.\nIV. Permanecer en la casilla desde su instalación hasta la conclusión de las labores que la ley les señala.\nV. Formular el acta que de fe de la instalación, cierre, escrutinio, cómputo y formación del paquete electoral.\nVI. Integrar los paquetes electorales respectivos con la documentación correspondiente a cada elección para hacerlos llegar, según corresponda, a los comités distritales o municipales electorales.\nVII. Las demás que les confiera esta ley u otras disposiciones aplicables.\nArtículo 87. Los integrantes de las mesas directivas de casilla tienen las atribuciones siguientes:\nI. El presidente:\n1. Presidir los trabajos de la mesa directiva de casilla y velar por el cumplimiento de las disposiciones contenidas en la ley, a lo largo del desarrollo de la jornada electoral, así como de los acuerdos que para el efecto haya tomado el Instituto.\n2. Recibir de los comités distritales y municipales electorales, la documentación y elementos necesarios para el funcionamiento de la casilla y conservarlos bajo su responsabilidad hasta la instalación de la misma.\n3. Identificar a los electores por medio de su credencial para votar.\n4. Mantener el orden en la casilla electoral y en sus inmediaciones, inclusive con el auxilio de la fuerza pública si fuese necesario.\n5. Suspender la votación en caso de alteración del orden, cuando existan circunstancias o seguridad personal de los electores, de los representantes de los partidos o de los miembros de la mesa directiva, ordenando al secretario técnico levantar el acta en la cual haga constar los hechos.\n6. Retirar de la casilla a cualquier individuo que incurra en la alteración del orden, impida la libre emisión del sufragio, viole el secreto del voto, realice actos que afecten la autenticidad y certeza del escrutinio y cómputo, intimide o ejerza violencia sobre los miembros de la mesa directiva, los representantes de los partidos o los electores.\n7. Vigilar que el proceso de escrutinio y cómputo se realice de la manera prescrita por la ley, ante los representantes de los partidos políticos presentes.\n8. Turnar, una vez concluidas las labores de la casilla electoral, la documentación y los expedientes respectivos, al comité distrital o municipal electoral o al delegado municipal, según sea el caso.\n9. Fijar en un lugar visible al exterior de la casilla los resultados del cómputo de cada una de las elecciones.\n10. Las demás que le confiera esta ley u otras disposiciones aplicables.\nII. El secretario técnico:\n1. Levantar durante la jornada electoral las actas que ordene la ley y distribuirlas en los términos que la misma establezca.\n2. Recibir los nombramientos de los representantes de los partidos políticos ante la casilla, verificando que hayan sido debidamente registrados ante la autoridad electoral correspondiente.\n3. Contar antes del inicio de la votación y ante los representantes de los partidos políticos que se encuentren presentes, las boletas electorales recibidas y anotar su número en el acta de instalación.\n4. Comprobar que el nombre del elector figure en la lista nominal correspondiente.\n5. Enumerar las boletas sobrantes, inutilizándolas por medio de dos rayas diagonales.\n6. Auxiliar al escrutador en la realización del cómputo y el escrutinio de los votos contenidos en las urnas, respecto a cada elección.\n7. Integrar el paquete de votación.\n8. Auxiliar al presidente en todas las labores de la casilla.\n9. Verificar que el paquete de votación se haya recibido en el comité distrital o municipal que corresponda.\n10. Recabar la copia del acta que contenga los resultados, a fin de remitirla al centro de información de resultados preliminares.\n11. Las demás que le confiera esta ley u otras disposiciones aplicables.\nIII. El escrutador:\n1. Contar la cantidad de boletas depositadas en la urna y el número de ciudadanos inscritos en la lista nominal de electores.\n2. Contar el número de votos emitidos en favor de cada candidato a gobernador, fórmula de diputados o planilla de Ayuntamiento.\n3. Auxiliar al presidente y al secretario técnico en las actividades que éstos le encomienden.\n4. Las demás que le confiera esta ley u otras disposiciones aplicables.\nArtículo 88. Los integrantes de las mesas directivas de casilla, deberán cumplir y hacer cumplir la emanen, las normas contenidas en la ley aplicable y los acuerdos del Instituto y desempeñar leal y patrióticamente la función que se les ha encomendado.\nArtículo 89. Los partidos políticos nacionales y estatales y, en su caso, las coaliciones, podrán registrar representantes ante las mesas directivas de casilla, así como representantes generales, en los términos establecidos en la ley de la materia.\nCAPÍTULO CUARTO\nLOS ÓRGANOS TÉCNICOS DEL INSTITUTO\nSECCIÓN PRIMERA\nLA DIRECCIÓN GENERAL\nArtículo 90. El titular de la Dirección General será nombrado y removido libremente por el voto de las dos terceras partes de los miembros del Consejo General del Instituto, a propuesta del consejero presidente.\nArtículo 91. La Dirección General tendrá las facultades siguientes:\nI. Asistir y participar con voz, pero sin voto en las sesiones del Consejo General.\nII. Cumplir y hacer cumplir los acuerdos del Consejo General.\nIII. Someter al conocimiento y, en su caso, a la aprobación del Consejo General o a la Junta General\nEjecutiva, informes periódicos sobre los asuntos de su competencia.\nIV. Ejecutar e implementar las providencias necesarias para la atención de aquellos asuntos del Instituto que, por su naturaleza o urgencia, así lo requieran. Cuando se trate de asuntos que correspondan a la competencia del Consejo General, lo hará del conocimiento inmediato del consejero presidente para que lo instruya al respecto.\nV. Proponer al Consejo General, previo acuerdo con el consejero presidente, la estructura de las comisiones y demás órganos administrativos del Instituto, conforme a las necesidades del servicio y los recursos presupuestales autorizados.\nVI. Coordinar el funcionamiento técnico de los órganos del Instituto y supervisar el adecuado desarrollo de sus actividades.\nVII. Formular y presentar, previo acuerdo con el consejero presidente, a la aprobación del Consejo\nGeneral, el proyecto del estatuto que regirá a los integrantes del Servicio Profesional Electoral.\nVIII. Cumplir y hacer cumplir el estatuto correspondiente, así como las normas y procedimientos del\nServicio Profesional Electoral.\nIX. Llevar a cabo los programas de reclutamiento, selección, formación y desarrollo del personal profesional del Instituto.\nX. Aplicar las políticas, normas y procedimientos para la administración de los recursos humanos, financieros y materiales del Instituto.\nXI. Fijar, previo acuerdo con el consejero presidente, las directrices que le permitan a cada órgano del\nInstituto, el cumplimiento de las funciones y atribuciones que les están conferidas de conformidad con lo establecido por el reglamento interior del Instituto.\nXII. Proveer a los órganos del Instituto de los elementos necesarios para el cumplimiento de sus funciones.\nXIII. Apoyar la integración, instalación y funcionamiento de los comités distritales y municipales electorales y demás órganos del Instituto.\nXIV. Supervisar la aplicación del Programa de Capacitación Electoral aplicado por los comités distritales y municipales electorales, y una vez autorizado, hacerse cargo del cumplimiento de dicho programa.\nXV. Entregar a los partidos políticos las prerrogativas a que tengan derecho.\nXVI. Formular y someter a la aprobación del Consejo General el proyecto de topes de gastos de campaña para los partidos políticos, correspondientes a las elecciones de Gobernador del Estado, diputados e integrantes de los Ayuntamientos.\nXVII. Proponer al Consejo General mecanismos para la difusión inmediata de los resultados preliminares de las elecciones; debiendo formular para tal efecto, el procedimiento respectivo para concesionar, en su caso, dicho servicio.\nXVIII. Aprobar la metodología de las empresas que pretendan realizar encuestas o estudios con el fin de conocer las tendencias electorales el día de la jornada electoral en que se realicen. Los resultados sólo podrán ser difundidos después de las veinte horas del día de la jornada electoral.\nXIX. Dar cuenta al Consejo General del Instituto de los informes que sobre el proceso electoral reciba de los comités distritales y municipales electorales.\nXX. Recibir, para efectos de información y estadística electoral, copias de los expedientes de todas las elecciones.\nXXI. Integrar los expedientes con la documentación necesaria, a fin de que el Consejo General efectúe los cómputos que conforme a la ley aplicable deba realizar y para la asignación de diputados por el principio de representación proporcional.\nXXII. Elaborar y dar a conocer la estadística electoral por sección, distrito, municipio y estado, una vez concluido el proceso electoral.\nXXIII. Elaborar y someter a la aprobación del Consejo General, por conducto del consejero presidente, el proyecto de convocatoria para las diversas elecciones.\nXIV. Elaborar y someter a la aprobación del Consejo General, cuando sea necesario, el proyecto de calendario para elecciones extraordinarias, de acuerdo con la convocatoria respectiva.\nXV. Elaborar, de conformidad con las disposiciones aplicables, el proyecto del presupuesto anual de egresos del Instituto, a fin de que el consejero presidente, una vez que lo haya autorizado el\nConsejo General, lo presente al Ejecutivo del Estado, para que éste lo someta a la consideración y, en su caso, aprobación del Congreso del Estado.\nXVI. Las demás que le confiera esta ley u otras disposiciones aplicables.\nSECCIÓN SEGUNDA\nLA SECRETARÍA TÉCNICA\nArtículo 92. El titular de la Secretaría Técnica será nombrado y removido libremente por el voto de las dos terceras partes de los miembros del Consejo General, a propuesta del consejero presidente.\nArtículo 93. La Secretaría Técnica tendrá las atribuciones siguientes:\nI. Asistir y participar con voz, pero sin voto en las sesiones celebradas por el Consejo General.\nII. Ejecutar, cumplir y verificar el cumplimiento de los acuerdos del Consejo General informando de ello al consejero presidente.\nIII. Elaborar el orden del día de las sesiones del Consejo General.\nIV. Declarar la existencia del quórum legal necesario para sesionar.\nV. Dar fe de lo actuado en las sesiones y levantar el acta correspondiente.\nVI. Dar cuenta de la correspondencia recibida y despachada por el Instituto.\nVII. Firmar junto con el consejero presidente del Instituto, todos los acuerdos y resoluciones que emita el\nConsejo General.\nVIII. Notificar a los partidos políticos y a los demás órganos electorales, los acuerdos y resoluciones del\nConsejo General.\nIX. Informar al Consejo General sobre el cumplimiento de los acuerdos que haya dictado.\nX. Llevar el archivo del Instituto.\nXI. Apoyar a los comités distritales y municipales electorales en el desarrollo de sus funciones y recabar copias certificadas de las actas de sus sesiones y demás documentos relacionados con el proceso electoral.\nXII. Llevar el libro de registro de partidos y asociaciones políticas estatales, así como de los convenios de coalición.\nXIII. Llevar el registro de los representantes de los partidos políticos acreditados ante los órganos electorales, así como de sus dirigencias estatales y nacionales.\nXIV. Expedir los documentos que acrediten la personalidad de los representantes electorales.\nXV. Expedir, previa autorización del consejero presidente, copias certificadas de las constancias que obren en los archivos del Instituto.\nXVI. Proveer lo necesario a fin de que se hagan oportunamente las publicaciones que ordena la ley correspondiente u otras disposiciones aplicables, así como las que disponga el Consejo General.\nXVII. Auxiliar al consejero presidente, a las comisiones y al Director General, en el despacho de los asuntos a su cargo.\nXVIII. Elaborar los proyectos de dictámenes que la ley aplicable, el Consejo General o las comisiones le encomienden.\nXIX. Someter a la aprobación del Consejo General los formatos de la documentación electoral.\nXX. Recibir y tramitar en los términos de las disposiciones aplicables, los medios de impugnación que se interpongan en contra de los actos o resoluciones que emita el Instituto.\nXXI. Tramitar y dar causa, a las promociones quejas o recursos presentados ante el Instituto en los términos establecidos en la ley de la materia.\nXXII. Informar al Consejo General de las resoluciones que le competan, dictadas por los organismos judiciales electorales.\nXXIII. Las demás que le confiera esta ley u otras disposiciones aplicables.\nCAPÍTULO QUINTO\nLOS ÓRGANOS DE VIGILANCIA DEL INSTITUTO\nSECCIÓN PRIMERA\nLA COMISIÓN DE VIGILANCIA Y DISCIPLINA\nArtículo 94. La Comisión de Vigilancia, Evaluación y Disciplina es el órgano de control interno del\nInstituto encargado de inspeccionar, supervisar y sancionar la función electoral de todo el personal del\nInstituto.\nSe integrará por tres consejeros electorales propietarios y por el Director General. De entre ellos elegirán a un presidente, que coordinará los trabajos de la comisión.\n(ADICIONADO, P.O. 2 DE AGOSTO DE 2007)\nLos trabajos operativos se realizarán por los miembros del Instituto designados por la Dirección General.\nArtículo 95. La Comisión de Vigilancia, Evaluación y Disciplina tendrá las atribuciones siguientes:\nI. Dictar las medidas necesarias para supervisar y corregir la función electoral.\nII. Ordenar y practicar visitas ordinarias y extraordinarias a los órganos del Instituto, para verificar el debido cumplimiento de sus funciones.\nIII. Proponer al Consejo General los criterios de evaluación de la función electoral para su discusión y, en su caso, aprobación.\nIV. Aplicar los criterios de evaluación de la función electoral al personal del Instituto, para medir su desempeño conforme a los principios que rigen la función electoral.\nV. Conocer, tramitar y, en su caso, resolver los procedimientos disciplinarios en los términos de las disposiciones aplicables.\nArtículo 96. La Comisión de Contraloría y de Fiscalización tendrá a su cargo la vigilancia, fiscalización y control de los ingresos, gastos, recursos y obligaciones del Instituto, de los partidos políticos, así como la aplicación de las políticas, criterios y lineamientos generales establecidos por el Consejo General.\nSe integrará por tres consejeros electorales propietarios y por el Director General. De entre ellos elegirán a un presidente, que coordinará los trabajos de la comisión.\nGeneral.\nArtículo 97. La Comisión de Contraloría y de Fiscalización tendrá las atribuciones siguientes:\nI. Definir y establecer lineamientos, con bases técnicas, para la presentación de los informes del financiamiento, así como para su empleo y aplicación.\nII. Definir y establecer lineamientos para que los partidos políticos lleven el registro de sus ingresos y egresos, así como definir y determinar la documentación comprobatoria que deberán utilizar para informar sobre el manejo de sus recursos.\nIII. Vigilar que los recursos que, con cargo al financiamiento, ejerzan los partidos políticos, se apliquen estricta e invariablemente a las actividades señaladas en la ley aplicable.\nIV. Solicitar a los partidos políticos, cuando lo considere conveniente, que rindan informe detallado respecto de sus ingresos y egresos.\nV. Revisar los informes que los partidos políticos presenten sobre el origen y destino de sus recursos anuales y de campaña, según corresponda.\nVI. Ordenar y practicar directamente o a través de despachos especializados y en los términos de los acuerdos del Consejo General, auditorias a las finanzas de los partidos políticos.\nVII. Ordenar en cualquier tiempo visitas de auditoria y de verificación a los partidos políticos con el fin de corroborar el cumplimiento de sus obligaciones y la veracidad de sus informes.\nVIII. Presentar al Consejo General, los dictámenes que formulen respecto de las auditorias y verificaciones practicadas.\nIX. Informar al Consejo General de las irregularidades en que hubieren incurrido los partidos políticos derivadas del manejo de sus recursos; el incumplimiento en su obligación de informar sobre la aplicación de los mismos y, en su caso, de las sanciones que a su juicio procedan.\nX. Proporcionar a los partidos políticos la orientación y asesoría necesarias para el cumplimiento de las obligaciones consignadas en esta ley y demás disposiciones aplicables.\nXI. Ejecutar y vigilar el cumplimiento de las disposiciones establecidas en el manual de políticas y procedimientos correspondiente.\nXII. Efectuar comprobaciones y conciliaciones de la contabilidad y los estados financieros del Instituto.\nXIII. Reportar por escrito al consejero presidente, cualquier irregularidad que observe.\nXIV. Realizar todo tipo de revisiones e inspecciones a los diversos órganos del Instituto.\nXV. Vigilar el cumplimiento de los convenios y contratos que celebre el Instituto.\nXVI. Intervenir, para efectos de verificación y control, en los contratos que emanen de la celebración de convocatorias y licitaciones\nXVII. Vigilar el cumplimiento de los contratos a que se refiere la fracción anterior.\nXVIII. Intervenir, para efectos de verificación y control, en los actos de entrega y recepción de los activos que conforman el patrimonio del Instituto.\nXIX. Establecer y dictar las normas generales para la realización de auditorias, inspecciones y evaluaciones del Instituto.\nXX. Vigilar el cumplimiento de las normas de control y fiscalización del Instituto.\nXXI. Presentar al consejero presidente un informe trimestral de su actuación.\nXXII. Cumplir y hacer cumplir los acuerdos del Consejo General que se refieran a los asuntos de su competencia.\nXXIII. Vigilar, controlar y supervisar los ingresos y egresos de los partidos políticos conforme a los lineamientos y normas establecidas.\nXXIV. Las demás que le confiera esta ley u otras disposiciones aplicables.\nTÍTULO TERCERO\nEL SERVICIO PROFESIONAL ELECTORAL\nCAPÍTULO ÚNICO\nBASES FUNDAMENTALES\nArtículo 98. El cuerpo del Servicio Profesional Electoral se integrará por dos áreas: la correspondiente a la función directiva y la relativa a la función técnica.\nEl área de la función directiva contará con el personal necesario para cubrir los cargos cuyas atribuciones versen sobre dirección, mando y supervisión.\nEl área técnica contará con el personal necesario para cubrir los puestos y realizar las actividades de naturaleza técnica-administrativa.\nArtículo 99. El ingreso al Servicio Profesional Electoral procederá cuando el aspirante cumpla y acredite los requisitos personales, académicos, de buena reputación y de imparcialidad que, para cada área funcional, señale el estatuto correspondiente, siempre que haya cumplido con los cursos de formación y capacitación respectivos y realice las prácticas en los órganos del Instituto.\nAsimismo, serán vías de acceso al Servicio Profesional Electoral el examen o el concurso, según lo señalen las normas estatutarias.\nArtículo 100. El estatuto del Servicio Profesional Electoral deberá establecer las normas para:\nI. Definir la integración, organización y atribución del Comité del Servicio Profesional Electoral, que será el órgano que instrumentará el modelo y el Servicio Profesional Electoral.\nII. Definir los niveles o rangos de cada área y los cargos o puestos a los que dé acceso.\nIII. Integrar el catálogo estatal de cargos y puestos.\nIV. Determinar las bases para el reclutamiento y la selección de los funcionarios y técnicos que accederán a las áreas.\nV. Otorgar la titularidad en un nivel o rango de un área y para el nombramiento en un cargo o puesto.\nVI. Precisar los mecanismos para la formación y capacitación profesional y los métodos para la evaluación del rendimiento.\nVII. Determinar los sistemas de ascensos y de movimientos a los cargos o puestos.\nVIII. Precisar los mecanismos para la aplicación de sanciones administrativas o remociones. Los ascensos se otorgarán sobre las bases del mérito y rendimiento.\nIX. Contratar personal temporal de apoyo.\nX. Definir la permanencia de las funciones electorales con relación a puestos o cargos.\nXI. Establecer los mecanismos y previsiones que garanticen la imparcialidad del personal que forme parte del Servicio Profesional Electoral.\nXII. Señalar las demás necesarias para la organización y el buen funcionamiento del Instituto.\nArtículo 101. El estatuto del Servicio Profesional Electoral deberá contener, además de las normas para la organización de las áreas de dicho cuerpo, las relativas a las ramas de empleados administrativos y de trabajadores auxiliares.\nEl estatuto fijará también las normas para su composición, ascensos, movimientos, sanciones administrativas y demás condiciones generales de trabajo.\nArtículo 102. Por la naturaleza de la función que tiene encomendada el Instituto, todo su personal hará prevalecer la lealtad a la Constitución Federal, a la particular del Estado, a las leyes que de ellas emanen y al propio Instituto, por encima de cualquier interés particular.\nTÍTULO CUARTO\nLA RESPONSABILIDAD DE LOS SERVIDORES\nPÚBLICOS DE LA FUNCIÓN ELECTORAL\nCAPÍTULO PRIMERO\nDISPOSICIONES GENERALES\nArtículo 103. Para los efectos de las responsabilidades a que alude este título, se reputarán como servidores públicos de la función electoral; a los consejeros electorales propietarios del Consejo General del Instituto; al Director General, el Secretario Técnico y, en general, a toda persona que desempeñe un empleo, cargo o comisión de cualquier naturaleza dentro del Instituto.\nArtículo 104. Los servidores públicos de la función electoral podrán ser sancionados cuando incurran en responsabilidad, de conformidad con las prevenciones siguientes:\nI. Se impondrá a los consejeros electorales propietarios, mediante juicio político, las sanciones de destitución e inhabilitación para desempeñar funciones, empleos, cargos o comisiones de cualquier naturaleza en el servicio público estatal o municipal, cuando en el ejercicio de sus funciones de su buen desempeño. legislación penal.\nIII. Se aplicarán sanciones administrativas por los actos u omisiones que afecten la legalidad, honradez, lealtad, imparcialidad y eficiencia, que deban observar en el desempeño de su empleo, cargo o comisión.\nLos procedimientos para la aplicación de las sanciones mencionadas serán autónomos en su desarrollo, sin que puedan imponer dos veces, por una sola conducta, sanciones de la misma naturaleza.\nArtículo 105. Todo ciudadano o persona moral, por conducto de sus órganos de representación, bajo su más estricta responsabilidad y mediante la presentación de elementos de prueba, podrá formular denuncia por escrito ante quien corresponda, respecto de las conductas a que se refiere el artículo anterior.\nCAPÍTULO SEGUNDO\nEL JUICIO POLÍTICO\nArtículo 106. Son sujetos de juicio político los consejeros electorales propietarios del Consejo General del Instituto.\nArtículo 107. Corresponde al Congreso del Estado, instruir el procedimiento relativo al juicio político, por materia, así como imponer, en su caso, las sanciones aplicables de acuerdo con la ley.\nArtículo 108. El procedimiento de juicio político sólo podrá iniciarse durante el período en que el servidor público desempeñe su cargo y dentro del año siguiente al que se separe, por cualquier causa, del ejercicio de sus funciones.\nLas sanciones correspondientes se aplicarán en un período no mayor de un año, a partir de iniciado el procedimiento.\nCAPÍTULO TERCERO\nLA DECLARACIÓN DE PROCEDENCIA EN MATERIA\nDE RESPONSABILIDAD PENAL\nArtículo 109. Para proceder penalmente en contra de los consejeros electorales propietarios del Consejo\nGeneral del Instituto, por la comisión de delitos durante el tiempo de su encargo, el Congreso del Estado deberá declarar, mediante resolución de las dos terceras partes del total de sus miembros, si ha lugar o no a proceder contra el inculpado, sujetándose a la garantía de audiencia.\nArtículo 110. Si el Congreso del Estado declara que ha lugar a proceder, el inculpado quedará a disposición del Pleno del Tribunal Superior de Justicia, el cual fallará en definitiva, previas las formalidades esenciales del procedimiento y con audiencia del inculpado, del Ministerio Público y del acusador, si lo hubiere.\nCAPÍTULO CUARTO\nLA RESPONSABILIDAD ADMINISTRATIVA\nSECCIÓN PRIMERA\nLOS SUJETOS\nArtículo 111. Son sujetos de responsabilidad administrativa todos los miembros del Instituto, cualquiera que sea su jerarquía. que establece esta ley; pero en todo caso, la sanción de destitución o inhabilitación de su cargo, se hará disposiciones aplicables.\nArtículo 112. La acción disciplinaria prescribe en tres años, contados desde el día siguiente a aquél en que se hubiere cometido la falta, o a partir del momento en que hubiese cesado, si fuere de carácter continuado.\nLa iniciación del procedimiento interrumpe la prescripción.\nSECCIÓN SEGUNDA\nLAS FALTAS ADMINISTRATIVAS\nArtículo 113. Se consideran como faltas de los consejeros electorales en su actuación relacionadas con el Consejo General, las siguientes:\nI. Dejar de asistir a las sesiones sin causa justificada.\nII. Desintegrar sin motivo justificado, el quórum del Consejo General, una vez iniciados los trabajos en cada sesión.\nIII. Violar las normas que regulan su actuación.\nArtículo 114. Para determinar la responsabilidad administrativa de los consejeros electorales propietarios, del Director General, del Secretario Técnico y de todo funcionario del Instituto de confianza o de base, se aplicará las faltas administrativas que establece la ley de la materia para todo funcionario o servidor público del estado y de los municipios.\nSECCIÓN TERCERA\nLAS SANCIONES\nArtículo 115. Las sanciones aplicables a las faltas administrativas consistirán en:\nI. Apercibimiento.\nII. Amonestación.\nIII. Multa.\nIV. Suspensión.\nV. Destitución del cargo.\nVI. Inhabilitación temporal para desempeñar empleo, cargo o comisión en la función electoral.\nArtículo 116. El apercibimiento consiste en la prevención verbal o escrita que se haga al servidor público, en el sentido de que de incurrir en nueva falta, se le aplicarán una o más de las sanciones previstas en el artículo anterior, según el caso.\nArtículo 117. La amonestación consiste en la reprensión que se haga al infractor, por la falta cometida.\nArtículo 118. La multa consiste en la sanción pecuniaria impuesta al infractor en favor del Instituto, la cual no podrá ser inferior al valor de diez días de sueldo, ni exceder al de un mes, debiendo hacerse efectiva mediante descuento en nómina, de cuotas iguales, no superiores a la quinta parte del sueldo mensual, o a través del procedimiento de ejecución forzosa, con la intervención de la autoridad competente.\nArtículo 119. La suspensión consiste en la separación temporal, que no podrá exceder de tres meses, del cargo, empleo o comisión, privando al servidor público del derecho a percibir remuneración, o cualesquiera otras prestaciones económicas a que tenga derecho.\nArtículo 120. La destitución consiste en la pérdida definitiva del cargo, empleo o comisión.\nArtículo 121. La inhabilitación implica la incapacidad temporal, hasta por diez años para obtener y ejercer cargo, empleo o comisión en el estado o en los municipios de la entidad.\nArtículo 122. Las sanciones administrativas se impondrán, tomando en cuenta:\nI. La gravedad y modalidad de la falta en que se haya incurrido.\nII. El grado de participación.\nIII. Las circunstancias socio-económicas del infractor.\nIV. Los motivos determinantes y los medios de ejecución.\nV. La antigüedad en el servicio.\nVI. La reincidencia.\nVII. El monto del beneficio obtenido y el daño o perjuicio económico derivados de la falta.\nArtículo 123. Las sanciones impuestas se anotarán en la hoja de servicios del servidor público, a cuyo efecto deberá enviarse copia autorizada de la resolución relativa a la Presidencia del Consejo General del\nInstituto.\nArtículo 124. Para la aplicación de las sanciones a que se hace referencia en los artículos anteriores, se observarán las siguientes reglas:\nI. El apercibimiento se aplicará por la primera falta cometida, cuando ésta sea levísima.\nII. La amonestación se aplicará sólo en tratándose de faltas leves.\nIII. Después de dos amonestaciones, la nueva sanción será de multa.\nIV. La triple sanción por faltas leves o la comisión de una falta grave, motivará la suspensión del cargo, empleo o comisión.\nV. La destitución se aplicará, como primera sanción, en caso de faltas muy graves, o después de dos sanciones de suspensión.\nVI. La inhabilitación sólo será aplicable por resolución de la autoridad competente, con arreglo a las leyes aplicables.\nCuando la destitución del cargo, empleo o comisión, afecte a un servidor público de base, se demandará la terminación de su contrato ante quien corresponda por la Presidencia del Consejo General, a solicitud de la autoridad que aplicó la sanción.\nSECCIÓN CUARTA\nArtículo 125. La jurisdicción disciplinaria se ejercerá:\nI. Por el Consejo General, cuando se trate de quejas en contra de los consejeros electorales.\nII. Por la Comisión de Vigilancia, Evaluación y Disciplina cuando se trate de quejas en contra del\nDirector General, el Secretario Técnico y demás personal del Instituto.\nArtículo 126. Contra el presunto autor de alguna de las faltas adminstrativas, se procederá de oficio o en virtud de queja presentada por escrito, ante la autoridad que corresponda, en los términos del artículo anterior.\nLas quejas anónimas no producirán efecto alguno.\nArtículo 127. Si los hechos materia de la queja fueren además, constitutivos de responsabilidad penal o civil, se ordenará ponerlos en conocimiento de la autoridad competente, acompañándole copia autorizada de lo necesario.\nLa existencia de un juicio político o penal sobre los mismos hechos, no dará lugar a la suspensión de la jurisdicción disciplinaria.\nArtículo 128. Las sanciones administrativas se impondrán con sujeción al siguiente procedimiento:\nI. En el auto inicial del proceso disciplinario, se ordenará correr traslado al infractor, con copia de la queja, para que informe lo que corresponda por escrito dentro del término de cinco días, señalándose en el propio auto el lugar, el día y la hora para la celebración de una audiencia de pruebas y alegatos, que se celebrará a más tardar dentro del término de quince días.\nII. Las pruebas deberán ofrecerse y rendirse durante la audiencia; debiéndose preparar con toda anticipación para su desahogo.\nIII. Al concluir la audiencia o dentro de los ocho días hábiles siguientes, se resolverá la queja administrativa.\nIV. En cualquier estado del procedimiento, el instructor podrá ordenar el desahogo de las pruebas para mejor proveer.\nV. En cualquier momento, antes o después de la iniciación del proceso disciplinario, se podrá acordar la suspensión temporal del presunto autor en su cargo, empleo o comisión, si a juicio del instructor así conviniere para el desarrollo de la investigación. La suspensión temporal no prejuzga sobre la determinación final que se tome. Si el servidor público temporalmente suspendido no resultare responsable de la falta que se le haya imputado, será restituido en el goce de sus derechos, y se le cubrirán las percepciones que debió recibir durante el plazo de la suspensión.\nArtículo 129. Se levantará acta circunstanciada de las diligencias que se practiquen, misma que suscribirán quienes en ellas intervengan.\nArtículo 130. Para el cumplimiento de las atribuciones que les confiere esta ley, el Consejo General o la\nComisión de Vigilancia, Evaluación y Disciplina, podrán emplear los siguientes medios de apremio:\nI. Sanción económica de hasta veinte veces el salario mínimo diario vigente en la capital del estado.\nII. Auxilio de la fuerza pública.\nSi existiere resistencia al mandamiento de la autoridad se estará a lo dispuesto en la legislación penal.\nTÍTULO QUINTO\nDISPOSICIONES FINALES\nCAPÍTULO PRIMERO\nLAS RELACIONES DE TRABAJO\nArtículo 131. Las relaciones laborales entre el Instituto y sus trabajadores se regirán por el Estatuto\nJurídico para los Trabajadores al Servicio del Estado, así como, en lo conducente, por la Ley de\nPensiones y Otros Beneficios Sociales para los Trabajadores al Servicio del Estado y el Estatuto del\nServicio Profesional Electoral.\nSerán considerados personal de confianza dentro del Instituto: el Director General, el Secretario Técnico y, en general, quienes realicen funciones de dirección, de vigilancia, de fiscalización y de administración.\nCAPÍTULO SEGUNDO\nLA EQUIDAD Y GÉNERO\nArtículo 132. Si por exigencias de construcción gramatical, enumeración, orden u otra circunstancia el texto legal contenido en esta ley usa el género masculino, el mismo deberá ser interpretado en sentido igualitario para hombres y mujeres, de modo que éstas y aquéllos puedan adquirir toda clase de derechos y contraer igualmente toda clase de deberes jurídicos.\nPRIMERO. La presente ley entrará en vigor el día de la publicación de este Decreto en el Periódico\nSEGUNDO. Una vez designados los consejeros electorales conforme al Decreto de Reforma a la tomarán los acuerdos necesarios para el debido funcionamiento del Instituto.\nTERCERO. El Instituto de acuerdo con esta ley, deberá emitir su reglamento interior, dentro de un plazo de 90 días naturales, contado a partir de la fecha en que se celebre la sesión de inicio de su funcionamiento.\nCUARTO. Por esta única vez y para la designación de los consejeros electorales, propietarios y suplentes, que iniciarán el funcionamiento del Instituto Electoral y de Participación Ciudadana de\nCoahuila, el Congreso del Estado podrá emitir convocatoria pública para que cualquier ciudadano pueda inscribirse dentro del plazo de 10 días naturales, para que su perfil sea tomado en cuenta por la comisión plural, comisión que presentará un dictamen que contendrá una lista de candidatos a ocupar los cargos de consejeros electorales. Dentro de esa lista, el Pleno del Congreso del Estado designará a los\n171 por el cual se aprueban las reformas a la Constitución Política Local en materia Político Electoral y de\nParticipación Ciudadana, que aparece publicada en el Periódico Oficial 82 número extraordinario del día\n13 de octubre del 2001.\nPor lo tanto, para la designación de los consejeros electorales, propietario y suplentes, que iniciarán el funcionamiento del Instituto Electoral y de Participación Ciudadana de Coahuila, no será aplicable el procedimiento previsto en el artículo 34 de la presente ley; pero en todo caso y en lo subsecuente, las designaciones de los consejeros electorales se deberá realizar conforme a dicho procedimiento.\nQUINTO. Se derogan todas las disposiciones legales o reglamentarias que se opongan a esta ley.\nDADO en el Salón de Sesiones del Congreso del Estado, en la Ciudad de Saltillo, Coahuila, a los trece días del mes de octubre del año dos mil uno.\nDIPUTADO PRESIDENTE.\nLUIS ROBERTO JIMÉNEZ GUTIÉRREZ.\nDIPUTADO SECRETARIO. DIPUTADO SECRETARIO.\nERNESTO FRANCISCO VALDÉS CEPEDA. HÉCTOR HERNÁNDEZ CORTINAS.\nIMPRIMASE, COMUNIQUESE Y OBSERVESE.\nEL GOBERNADOR DEL ESTADO\nLIC. ENRIQUE MARTINEZ Y MARTINEZ\nEL SECRETARIO DE GOBIERNO\nLIC. JOSE JESÚS RAUL SIFUENTES GUERRERO\nN. DE E. A CONTINUACION SE TRANSCRIBEN LOS ARTICULOS TRANSITORIOS DE LOS DECRETOS DE REFORMAS A LA\nPRESENTE LEY.\nARTÍCULO UNICO. El presente decreto entrará en vigor al día siguiente de su publicación en el Periódico Oficial del Gobierno del\nEstado.\nARTÍCULO SEGUNDO. El periodo de cuatro años para los integrantes del Congreso del Estado será aplicable a partir de la renovación a realizarse en el año 2013. En consecuencia y por única ocasión, los diputados electos en el proceso electoral a celebrarse en el año 2008, correspondiente a la Quincuagésima Octava Legislatura, durarán en su encargo el período comprendido\nSEGUNDO. Se derogan las disposiciones legales, administrativas y reglamentarias que se opongan al presente decreto.\nSEGUNDO. Se derogan todas las disposiciones legales y reglamentarias que se opongan al presente Decreto.",
  "ordenamiento": "REGLAMENTO",
  "jurisdiccion": "COAHUILA",
  "fuente_oficial": "DIARIO OFICIAL DE LA FEDERACION",
  "Fecha de Publicación": "16 de noviembre de 2001",
  "ULTIMA REFORMA PUBLICADA": "27 DE JUNIO DE 2008",
  "es_escaneado": false,
  "tiene_tablas": true,
  "materia": [
    "electoral",
    "participación ciudadana"
  ]
}