{
  "titulo": "Ley del Registro Civil para el Estado de Coahuila de Zaragoza",
  "Contenido": "EL C. ENRIQUE MARTÍNEZ Y MARTÍNEZ, GOBERNADOR CONSTITUCIONAL DEL ESTADO\nINDEPENDIENTE, LIBRE Y SOBERANO DE COAHUILA DE ZARAGOZA, A SUS HABITANTES\nSABED:\nQUE EL CONGRESO DEL ESTADO INDEPENDIENTE, LIBRE Y SOBERANO DE COAHUILA\nDE ZARAGOZA;\nDECRETA:\nNÚMERO 64.LEY DEL REGISTRO CIVIL PARA EL ESTADO\nDE COAHUILA DE ZARAGOZA\nTÍTULO PRIMERO\nOBJETO DE LA LEY\nCAPÍTULO ÚNICO\nDISPOSICIONES GENERALES\nARTÍCULO 1°. Esta ley es de orden público y de observancia obligatoria en el régimen interno del\nEstado de Coahuila de Zaragoza. Su objeto consiste en reglamentar la organización y funcionamiento del Registro Civil.\nARTÍCULO 2°. El Registro Civil es un órgano de la Secretaría de Gobierno cuya naturaleza se define en su Reglamento Interior. Su función es de interés público. Su objeto consiste en hacer constar de manera auténtica, todos los actos y hechos relacionados con el estado civil de las personas físicas, mediante la intervención de personas dotadas de fe pública, denominados\nOficiales del Registro Civil o, en su caso, Oficiales del Registro Civil Adjuntos, a través de un sistema de publicidad.\nLa coordinación, supervisión y evaluación del Registro Civil corresponderá a la Secretaría de\nGobierno, por conducto de la Subsecretaría o unidad administrativa que se señale en el\nReglamento Interior de la Secretaría de Gobierno o conforme lo instruya el titular de la misma.\nARTÍCULO 3°. El Registro Civil es público. Tendrán acceso a él todas las personas interesadas en mismas.\nLa Dirección del Registro Civil promoverá ante la comunidad, a través de las campañas de difusión que estime convenientes, el registro y la trascendencia de la formalización de los actos o hechos jurídicos relativos al estado civil de las personas. De igual forma, difundirá información sobre la trascendencia de la formalización, a través de su registro, de esos actos o hechos jurídicos.\nTambién difundirá, por medios idóneos, sobre la naturaleza de los servicios que presta, los procedimientos correspondientes y el monto de los derechos que deberán cubrirse por los mismos.\nARTÍCULO 4°. La certificación será el medio de publicidad de las actas, asientos y documentos, que se encuentren en los archivos del Registro Civil.\nLas certificaciones podrán ser positivas o negativas. Serán positivas cuando reproduzcan literalmente o en extracto, un acta, asiento o documento, seguidas de una fórmula que determine la concordancia entre aquéllas y éstos. Serán negativas cuando, con base en los datos contenidos en los libros o en los índices, se limiten a indicar la inexistencia de un asiento o de un documento relativo a un hecho o acto determinado.\nEn toda certificación se incluirá el lugar y la fecha de su emisión; el nombre y la firma del servidor público que tiene encomendada la función de autenticar y el sello de la oficina correspondiente.\nARTÍCULO 5°. Toda persona podrá solicitar y obtener a su costa copia certificada de las actas, asientos, documentos y apuntes relacionados con ellas, existentes en los libros, índices y apéndices correspondientes.\nARTÍCULO 6°. Las copias certificadas y las certificaciones serán autenticadas por la Dirección del\nRegistro Civil, conforme al sistema de asignación previsto en esta ley, cuando se trate de actas, asientos, documentos o apuntes que obren en el Archivo General del Registro Civil. En este caso, el sistema de asignación incluirá al Director, al Subdirector Jurídico, al Oficial Mayor, a los\nRegistradores y a los que el titular de la Secretaría de Gobierno autorice por medio de acuerdo administrativo que se publique en el Periódico Oficial del Gobierno del Estado.\nLa autenticación de los hechos y actos que hayan sido registrados en las Oficialías del Registro\nCivil, se realizará por los propios Oficiales del Registro Civil o, en su caso, por los Oficiales\nAdjuntos en cuyas oficialías consten los hechos o actos registrados.\nARTÍCULO 7°. El Director del Registro Civil establecerá, mediante disposiciones de carácter general o particular, un sistema de asignación mediante el cual se ejercerá la función de autenticación.\nEl sistema de asignación deberá, por lo menos, contemplar:\nI. El orden cronológico y/o turno en el que intervendrán los servidores a quienes, conforme el artículo que antecede, se les otorga la facultad de autenticación.\nII. El período de tiempo durante el cual se ejercerá la atribución de autenticar.\nSin perjuicio de lo anterior, el Director podrá variar el orden y el tiempo previamente establecido, a efecto de garantizar la continuidad, eficiencia y eficacia en el cumplimiento de la atribución correspondiente.\nPara los efectos anteriores, el Director será responsable de realizar o, en su caso, vigilar la realización de los cambios respectivos en el sistema interior de autenticación, a efecto de que puedan ejercer tal función los titulares de las unidades administrativas facultadas para ello.\nARTÍCULO 8°. La certificación podrá autentificarse con firma autógrafa o electrónica. medios electrónicos, la autorización del funcionario competente, según el sistema que implemente la Dirección. La Dirección deberá utilizar mecanismos confiables para evitar la falsificación de documentos.\nARTÍCULO 9°. La facultad para autenticar las copias certificadas y/o las certificaciones, corresponderá de manera exclusiva a quienes esta ley les otorgue dicha facultad, la cual no podrán delegar en persona alguna.\nARTÍCULO 10. Las copias certificadas y las certificaciones emitidas por los servidores públicos tendrán el mismo valor jurídico y probatorio que las suscritas en forma autógrafa.\nARTÍCULO 11. El estado civil de las personas sólo se comprueba con las constancias relativas del\nRegistro Civil, salvo lo dispuesto en los artículos 149, 183, 187, 192, 454 y 455 del Código Civil para el Estado de Coahuila.\nLas copias certificadas y las certificaciones tendrán el carácter de documentos públicos. Cuando la certificación no apareciere conforme con el asiento a que se refiere, se estará a lo que de éste resulte, sin perjuicio de la responsabilidad que proceda.\nARTÍCULO 12. Para establecer el estado civil adquirido por los coahuilenses fuera del territorio del\nEstado, pero dentro de la República Mexicana, se observará lo dispuesto en la fracción IV, del artículo 121 de la Constitución Política de los Estados Unidos Mexicanos.\nARTÍCULO 13. Para establecer el estado civil adquirido por los coahuilenses fuera de la República\nMexicana, se observará lo dispuesto en el artículo 159 del Código Civil para el Estado de Coahuila y demás disposiciones aplicables.\nARTÍCULO 14. Los Oficiales del Registro Civil que intervengan, en el ámbito de su competencia, en actos o hechos del estado civil de extranjeros, se sujetarán a las siguientes prescripciones:\nI. No celebrarán ningún acto del estado civil en que intervenga algún extranjero sin la comprobación previa, por parte de éste, de su legal estancia en el país. Tratándose de matrimonios de extranjeros con mexicanos deberán exigir, además, el permiso previo emitido por la Secretaría de Gobernación. Una vez verificado ese acto, los Oficiales darán aviso de ello a esa dependencia federal.\nII. Las actas de nacimiento, de reconocimiento de hijos y de defunción, deberán levantarse en los términos señalados por el Código Civil para el Estado de Coahuila y, cuando los extranjeros que intervengan no acrediten su estancia legal en el país, tomarán nota de su nombre, ocupación y domicilio y darán aviso a la dependencia competente del gobierno federal.\nIII. Al hacer la inscripción de actas de adopción, tutela, divorcio u otros actos o anotaciones que se realicen por mandato judicial, se cerciorarán si ante la autoridad judicial correspondiente, los extranjeros comprobaron su legal estancia en el país y, en caso contrario, darán aviso a la autoridad a que se refiere la fracción anterior.\nIV. En caso de emancipación por efecto de matrimonio, se cerciorarán de que el mismo se celebró con permiso de la dependencia federal competente y, en caso contrario, con los datos correspondientes se dará el mismo aviso a que se refiere la fracción primera.\nTÍTULO SEGUNDO\nLA ORGANIZACIÓN Y EL FUNCIONAMIENTO\nDEL REGISTRO CIVIL\nCAPÍTULO PRIMERO\nDISPOSICIONES GENERALES\nARTÍCULO 15. El Registro Civil contará con una Dirección, a la que corresponderá la organización, dirección, vigilancia y administración de las oficinas del Registro Civil y de las unidades administrativas adscritas a ella. Dicha Dirección también estará a cargo de la coordinación, vigilancia, control y supervisión de las oficialías.\nLa Dirección del Registro Civil tendrá su sede en la capital del Estado.\nARTÍCULO 16. El mando superior de la Dirección estará a cargo de un Director o de una Directora, quien deberá ejercer las atribuciones que le otorguen esta ley u otras disposiciones aplicables. En el desempeño de las funciones a su cargo, el Director o la Directora se podrá auxiliar de los\nCivil.\nARTÍCULO 17. Las atribuciones que correspondan a cada unidad administrativa, así como las facultades y obligaciones de los titulares de las mismas, se determinarán en el Reglamento del\nRegistro Civil. correspondiente Presupuesto de Egresos en el Estado.\nEl titular de la Dirección establecerá las acciones y mecanismos que aseguren la profesionalización del personal adscrito a la misma, así como de los Oficiales del Registro Civil y de los correspondientes aspirantes.\nARTÍCULO 18. El Registro Civil estará integrado por las Oficialías del Registro Civil que determine el Ejecutivo del Estado, las cuales tendrán las circunscripciones territoriales que se señalen por aquél, a través de la Secretaría de Gobierno.\nEl acuerdo del titular del Ejecutivo del Estado que contenga la determinación del número de la\nOficialía y su respectiva competencia territorial, deberá ser publicado en el Periódico Oficial del\nGobierno del Estado.\nARTÍCULO 19. El Director o la Directora supervisará y vigilará que sean realizados, en los términos de las disposiciones aplicables, los registros cuyos derechos hubieren sido objeto de estímulos o subsidios fiscales mediante resolución de carácter general emitida por el Ejecutivo del\nEstado, así como de aquellos cuyos derechos exima de pago en atención a los programas de asistencia social y demás que se implementen por las instancias competentes en beneficio de los grupos o sectores más vulnerables en la entidad y de aquellos que implemente la propia Dirección.\nARTÍCULO 20. La Dirección del Registro Civil, para el cumplimiento de su objeto, contará con un\nComité de Calidad de carácter permanente. Dicho Comité tendrá por objeto analizar y evaluar la calidad de los servicios del Registro Civil y las oficialías y, en su caso, proponer medidas correctivas y preventivas que coadyuven a una mejor prestación del servicio dentro de la\nInstitución.\nLa organización, integración, atribuciones y funcionamiento del Comité de Calidad, se determinarán en el Reglamento Interior del Registro Civil.\nCAPÍTULO SEGUNDO\nLOS OFICIALES DEL REGISTRO CIVIL\nSECCIÓN PRIMERA\nBASES GENERALES\nARTÍCULO 21. Para el cumplimiento de su objeto, el Registro Civil se auxiliará de las personas que, en los términos de esta ley u otras disposiciones aplicables, sean designadas como Oficiales del Registro Civil. oficialía o, en su caso, de adjuntos a ellas.\nARTÍCULO 22. Para ser Oficial del Registro Civil se requiere:\nI. Ser ciudadano mexicano en pleno goce y ejercicio de sus derechos.\nII. No ser ni haber sido ministro de algún culto religioso.\nIII. Ser de reconocida probidad y honradez.\nIV. De preferencia, tener título oficial de Licenciado en Derecho o de Profesor y contar con conocimientos en la materia de Derecho Registral Civil.\nV. No haber sido condenado por delito intencional que merezca pena privativa de libertad.\nVI. Acreditar los exámenes o pruebas de aptitud que correspondan.\nVII. Los demás que, para asegurar la profesionalización del servicio, determine el titular del del Estado.\nEl titular del Ejecutivo podrá dispensar la presentación de los exámenes de mérito o pruebas de aptitud, cuando a su juicio, existan elementos suficientes que acrediten la capacidad y profesionalismo del aspirante a oficial del Registro Civil.\nARTÍCULO 23. Los Oficiales del Registro Civil serán nombrados y removidos libremente por el\nGobernador del Estado, en los términos previstos por esta ley y demás disposiciones aplicables.\nEl titular de la Dirección determinará el número de Oficiales que deberán fungir como\nCoordinadores y Visitadores.\nARTÍCULO 24. Los aspirantes a Oficiales del Registro Civil, deberán presentar por escrito la solicitud para el examen correspondiente ante la Dirección, la cual dictaminará sobre su procedencia, notificando, en todo caso, al interesado.\nEn el caso de que la petición fuese rechazada, se notificará al interesado por escrito, debiendo establecer claramente, las causas y los motivos de la negativa.\nDe todo trámite se dará cuenta al Ejecutivo del Estado, por conducto de la Secretaría de Gobierno.\nARTÍCULO 25. Declarada la procedencia de la solicitud, la Dirección señalará día y hora para que se celebre el examen correspondiente. La propia Dirección notificará al interesado y a los integrantes del jurado dicha circunstancia con, cuando menos, quince días hábiles de anticipación.\nEl examen deberá presentarse en la hora y lugar que señale la Dirección.\nARTÍCULO 26. El jurado que aplicará el examen estará integrado por el Director, quien lo presidirá; por el Coordinador del Registro Civil de la región correspondiente, y por un representante de la\nARTÍCULO 27. No podrán formar parte del jurado, aquellas personas que tengan parentesco por consanguinidad, afinidad o civil, sin limitación de grado en línea recta ascendente o descendente y dentro del cuarto grado en línea colateral, con el solicitante.\nLos miembros del jurado que concurran en algunos de los impedimentos señalados, deberán excusarse de intervenir en el examen. En caso contrario, el examen será declarado nulo.\nARTÍCULO 28. El examen constará de dos etapas, una práctica que consistirá en la redacción de un asentamiento de registro, mismo que se asignará por sorteo y, otra teórica que se integrará por una sesión de preguntas y respuestas de los distintos temas que comprende la materia registral.\nEn todo caso, el contenido del examen se instrumentara por la Dirección.\nARTÍCULO 29. El jurado levantará el acta relativa al examen, la cual será firmada por todos aquellos que hayan intervenido en el mismo. En ella deberá quedar asentado fehacientemente el resultado del examen, así como la circunstancia de si fue o no otorgada la calidad de aspirante.\nGobierno.\nARTÍCULO 30. La Secretaría de Gobierno podrá enviar semestralmente al Ejecutivo del Estado, la lista de aspirantes a Oficiales del Registro Civil que cumplan con los requisitos señalados en esta ley. Esta lista se constituirá en la de reserva a que se refiere esta ley.\nARTÍCULO 31. El titular del Ejecutivo podrá, en el Reglamento Interior del Registro Civil, determinar la creación de un Comité de Apoyo y Opinión que tenga por objeto instrumentar los mecanismos necesarios para apoyar la profesionalización de la función registral, así como participar, en los términos que acuerde, en la evaluación de los aspirantes a fungir como Oficiales, titulares y adjuntos, del Registro Civil.\nARTÍCULO 32. Los Oficiales del Registro Civil no tendrán ninguna relación laboral con el Gobierno del Estado. Ellos deberán hacerse cargo de todos los gastos de su oficina, incluyendo los correspondientes a la encuadernación de sus libros.\nEl personal de las Oficialías del Registro Civil se regirá por el contrato de trabajo que celebren con el Oficial correspondiente, sin ninguna responsabilidad o vinculación laboral para el Gobierno del\nEstado.\nARTÍCULO 33. Los honorarios que habrán de percibir los Oficiales por su intervención en cada hecho o acto del estado civil, serán los que autorice la Secretaría de Gobierno, por conducto de la\nDirección del Registro Civil.\nLa tarifa autorizada oficialmente, deberá colocarse a la vista de los interesados en las Oficinas del\nRegistro Civil.\nARTÍCULO 34. Son facultades de los Oficiales del Registro Civil, ya sean titulares o adjuntos, las siguientes:\nI. Dar fe pública de los hechos y actos jurídicos vinculados al estado civil de las personas.\nII. Ejercer ordinariamente las atribuciones u obligaciones inherentes a su cargo conforme a esta ley, el Reglamento Interior del Registro Civil y demás disposiciones aplicables.\nEn términos generales, los Oficiales del Registro Civil tendrán las facultades, obligaciones y prohibiciones previstas en esta ley, en el Reglamento Interior del Registro Civil, en el Código Civil para el Estado de Coahuila y demás disposiciones aplicables.\nARTÍCULO 35. Los Oficiales del Registro Civil, titulares y adjuntos, tendrán las obligaciones siguientes:\nI. Rendir la protesta de ley y, una vez presentada, tomar posesión de su encargo.\nII. Asentar en las actas que se establecen en esta ley u otras disposiciones aplicables, los actos y hechos jurídicos que correspondan.\nIII. Asistir con puntualidad y estar al frente del despacho de su oficina durante las horas que señale la Secretaría de Gobierno, por conducto de la Dirección, sin perjuicio de que puedan actuar en horas extraordinarias, a petición de los interesados, o bien, en casos urgentes.\nIV. Vigilar el exacto cumplimiento de las disposiciones contenidas en el Código Civil para el\nEstado de Coahuila, de esta ley y demás disposiciones aplicables.\nV. Expedir las certificaciones que se les soliciten sobre datos o constancias que obren en los libros del Registro Civil bajo su responsabilidad. planteadas, los Oficiales del Registro Civil tomen conocimiento de que no aparecen registrados datos que determinen la filiación paterna o materna del solicitante, procederán a orientarle sobre los procedimientos voluntarios para la determinación de la paternidad y maternidad o, en su caso, los procedimientos judiciales mediante los cuales pueden obtenerse.\n(ADICIONADO, P.O. 17 DE AGOSTO DE 2004)\nEn todos los casos en que un menor aparezca inscrito como hijo de padre o de madre desconocidos, el Oficial del Registro Civil lo pondrá en conocimiento de la Procuraduría de la\nDefensa del Menor y la Familia, para los efectos que se precisan en el párrafo precedente.\nVI. Autenticar las copias certificadas y las certificaciones, cuando se trate de actos registrados en sus oficialías, en los términos de las disposiciones aplicables.\nVII. Enterar a las autoridades que correspondan, los derechos que se causen por los servicios públicos que presten, de acuerdo con las tarifas y sistemas señalados por las disposiciones fiscales vigentes y en los términos de la Ley de Hacienda del Estado.\nVIII. Realizar los registros cuyos derechos hubieren sido objeto de estímulos o subsidios fiscales mediante resolución de carácter general emitida por el Ejecutivo del Estado en los términos de las disposiciones aplicables, así como realizar los registros cuyos derechos hubieren sido eximidos de pago por la Dirección en atención a los programas de asistencia social y demás que se implementen por las instancias competentes en beneficio de los grupos o sectores más vulnerables en la entidad, así como de aquellos que implemente la propia Dirección.\nIX. Devolver a Recaudación de Rentas, dentro de los primeros diez días de cada mes, las formas de expedición de copias certificadas del mes inmediato anterior que se deterioren, manchen o inutilicen por cualquier causa.\nX. Comunicar por escrito a la Dirección, las anotaciones que hayan sido asentadas en los libros del archivo de esa oficina.\nXI. Conservar bajo su responsabilidad los libros, legajos, apéndices y demás documentos que utilicen para la función que se les ha encomendado, organizando su archivo de acuerdo con las bases que se señalan en esta ley, el Reglamento Interior del Registro Civil u otras disposiciones aplicables.\nXII. Remitir mensualmente a la Dirección las copias de los ejemplares que correspondan al\nArchivo General, mismas que deberán ir debidamente sellados y firmados por el Oficial y las personas que hubieren intervenido en el acto.\nXIII. Rendir por escrito a las autoridades judiciales y administrativas, todos los informes que les sean solicitados o resulten necesarios y expedir, sin costo alguno, los certificados que les soliciten.\nXIV. Permitir el examen de los libros a la persona que lo solicite, siempre que dicho examen se realice dentro de la oficina y en horas hábiles.\nXV. Consultar con la Dirección, todas las dudas que surjan y que no estén resueltas por el\nXVI. Cumplir con los requerimientos de infraestructura, equipamiento, capacitación de recursos humanos e identidad, previamente determinados en el Manual de Identidad para Oficialías del Registro Civil en el Estado.\nXVII. Las demás que les confiera esta ley, el Reglamento Interior del Registro Civil u otras disposiciones aplicables.\nEn los casos de las fracciones VIII, IX y XIII, los Oficiales del Registro Civil, tendrán derecho a que se les restituyan las formas empleadas o inutilizadas.\nARTÍCULO 36. En el ejercicio de sus funciones, los Oficiales del Registro Civil, deberán guardar la discreción y prudencia que corresponde a la importancia de su cargo. Deberán desempeñar sus funciones con probidad, honestidad, eficiencia, eficacia y legalidad, tratando con cortesía a cuantas personas ocurran ante ellos.\nARTÍCULO 37. Los Oficiales del Registro Civil estarán investidos de fe pública plena para certificar los hechos y actos del estado civil de las personas. La validez de dichas certificaciones sólo podrá impugnarse en juicio, debiéndose cumplir con las formalidades esenciales del procedimiento.\nARTÍCULO 38. Los Oficiales del Registro Civil serán los únicos responsables de los hechos y actos pasados ante ellos y no podrán delegar, en ningún caso y bajo ninguna circunstancia, sus funciones en persona alguna.\nARTÍCULO 39. Los Oficiales del Registro Civil serán responsables de las formas que para los asentamientos de actas y la expedición de las copias certificadas, se les proporcionen en los términos de las disposiciones aplicables.\nARTÍCULO 40. Los Oficiales del Registro Civil velarán por la concordancia del registro y la realidad. Deberán promover la práctica de los asientos que deban hacerse y no se hayan asentado y procurarán, por todos los medios a su alcance, que la expresión registral del hecho o del acto, sea reflejo fiel de todas las circunstancias que deban constar en el asiento.\nARTÍCULO 41. Los Oficiales del Registro Civil entregarán al interesado, un duplicado del acta que se asiente a fin de que, en todo tiempo y con los datos que en ella consten, se encuentre en posibilidad de solicitar a la propia Oficialía o a la Dirección, ulteriores copias certificadas de dicha acta.\nARTÍCULO 42. Los horarios en que deberán prestar sus servicios los Oficiales del Registro Civil podrán ampliarse, previo acuerdo del titular de la Dirección, en los casos que, a su juicio así se requiera, así como en aquellos otros previstos en las disposiciones legales aplicables.\nEl registro de los hechos y actos del estado civil, así como las anotaciones y la expedición de formas y constancias relativas a los hechos y actos del estado civil, causarán los derechos que establezca la Ley de Hacienda del Estado, la Ley de Ingresos y demás disposiciones aplicables.\nSECCIÓN SEGUNDA\nLAS LICENCIAS Y PERMISOS A LOS OFICIALES\nDEL REGISTRO CIVIL\nARTÍCULO 43. Los Oficiales del Registro Civil titulares podrán solicitar al Ejecutivo del Estado, por conducto de la Secretaría de Gobierno, licencia para separarse temporalmente de la función que tienen encomendada.\nPara tal efecto, deberán presentar a la Secretaría de Gobierno un escrito de solicitud de licencia en el que manifestarán las causas y el plazo por los que se solicita.\nAdemás, deberán mencionar, en su caso, la propuesta de la persona que, como Oficial Adjunto podrá sustituirles por el tiempo que dure la licencia. En este caso, deberán preferentemente señalar alguna persona de las que aparezcan en la lista de reserva correspondiente.\nARTÍCULO 44. El Secretario de Gobierno otorgará o negará la licencia tomando en consideración las causas que motivan la solicitud.\nARTÍCULO 45. El Oficial del Registro Civil a quién se hubiere otorgado licencia para separarse temporalmente de su cargo, deberá comunicar al Secretario de Gobierno su reincorporación a la función que desempeñaba en la Oficialía del Registro Civil respectiva.\nEn todo caso, dicho comunicado deberá realizarse, por lo menos, con treinta días de anticipación a la fecha en que reanudará las actividades inherentes a la función.\nARTÍCULO 46. El Oficial del Registro Civil a quién se le haya concedido licencia para separarse temporalmente de su función, deberá hacer del conocimiento del Secretario de Gobierno su imposibilidad definitiva para reincorporarse a la misma, independientemente de las causas que le motiven para ello, a fin de que se proceda conforme a lo previsto en esta ley, en el Reglamento\nInterior del Registro Civil y en las demás disposiciones aplicables.\nARTÍCULO 47. El titular de la Dirección podrá otorgar permisos a los Oficiales del Registro Civil para separarse de su función hasta por quince días, siempre que, a juicio del propio titular, existiere causa justificada para ello. Cuando la ausencia fuere por más de quince días, se atenderá a las previsiones contenidas en los artículos anteriores.\nEn esos casos, la solicitud de permiso deberá presentarse por escrito ante la Dirección.\nSECCCIÓN TERCERA\nLOS OFICIALES ADJUNTOS\nARTÍCULO 48. Para suplir las ausencias temporales de más de quince días de los Oficiales del\nRegistro Civil, el Ejecutivo del Estado, a través del Secretario de Gobierno, nombrará a los\nOficiales Adjuntos que deberán suplir a aquéllos durante su ausencia. Los Oficiales Adjuntos y todas aquéllas que resulten aplicables a los oficiales sustituidos.\nSe regirán en todo caso por lo previsto en el artículo 32 de esta ley.\nARTÍCULO 50. La designación de los Oficiales Adjuntos podrá realizarse:\nI. De entre aquellas personas que conformen la lista de reserva que, para tal efecto, integre la\nDirección en los términos previstos por esta ley u otras disposiciones aplicables.\nGobierno, sin acudir a la lista de reserva que se hubiere integrado. sustituido.\nSi la designación se realizare de entre las personas que figuran en la lista de reserva, deberá considerarse a aquellas personas con mayor antigüedad y que radiquen en el municipio en que se desempeñe el Oficial al que habrán de sustituir. Si no aparecieren registrados aspirantes cuyo domicilio se ubique en el municipio respectivo, se podrá realizar la designación de entre aquéllos mayor antigüedad en la lista.\nARTÍCULO 51. La lista de reserva se integrará con aquellas personas que hayan obtenido la calidad de aspirante a Oficial del Registro Civil.\nEsta lista de reserva se hará del conocimiento de los oficiales del Registro Civil para el efecto de que, en su caso, de entre las personas que en ella figuren, realicen la propuesta de quien habrá de sustituirles con motivo de ausencia temporal en sus funciones.\nARTÍCULO 52. La Dirección podrá, con la periodicidad que estime conveniente y según al número de aspirantes a Oficiales, convocar a la ciudadanía con el fin de que las personas interesadas, una vez satisfechos los requisitos que esta ley u otras disposiciones señalen, obtengan tal calidad.\nARTÍCULO 53. La convocatoria que emita la Dirección deberá atender a los principios de oportunidad y generalidad. En ella se precisará sucintamente sobre la función que legalmente corresponde a los Oficiales del Registro Civil; sus derechos y obligaciones; los requisitos que deberán satisfacer los aspirantes, así como los documentos que deberán presentar para comprobar el cumplimiento de tales requisitos y el lugar, día y hora en que deberán presentar la solicitud y la documentación correspondiente.\nARTÍCULO 54. La Dirección analizará y revisará cada solicitud, así como la documentación que a la misma se acompañe, a fin de verificar que se cumplan los requisitos correspondientes.\nDesechará de plano aquellas solicitudes notoriamente improcedentes, así como aquéllas de las que se desprenda el incumplimiento de algún requisito.\nTÍTULO TERCERO\nLOS LIBROS Y LAS ACTAS DEL REGISTRO CIVIL\nCAPÍTULO PRIMERO\nDISPOSICIONES GENERALES\nARTÍCULO 55. Las actas del Registro Civil se recopilarán en ocho libros que se llevarán por quintuplicado. Las formas respectivas podrán constar por escrito o en medios magnéticos o electrónicos. En ellas se estampará la firma autógrafa o electrónica.\nLos libros deberán contener:\nI. El primero, actas de nacimiento.\nII. El segundo, actas de reconocimiento.\nIII. El tercero, actas de adopción semiplena y tutela, así como, las inscripciones de las ejecutorias que declaren el estado de interdicción.\nIV. El cuarto, actas de matrimonio.\nV. El quinto, actas de divorcio.\nVI. El sexto, actas de defunción e inscripción de las ejecutorias que declaren la ausencia o la presunción de muerte, así como las que declaren la pérdida o limitación de la capacidad legal para administrar bienes.\nVII.- El Séptimo, actas del pacto civil de solidaridad.\nVIII.- El Octavo, actas de disolución o terminación de los pactos civiles de solidaridad.\nARTÍCULO 56. Toda acta deberá asentarse en los cinco ejemplares del registro y en ellos, deberán constar las firmas autógrafas, facsimilares o electrónicas del Oficial del Registro Civil y de los comparecientes, cuando así corresponda.\n(REFORMADO, P.O. 12 DE ENERO DE 2007\nARTÍCULO 57. Las actas del Registro Civil sólo se asentarán en las formas siguientes: nacimiento, reconocimiento de hijos, adopción semiplena, matrimonio, defunción, divorcio, registro de pacto civil de solidaridad y terminación del mismo, de inscripción de las sentencias ejecutoriadas que declaren la ausencia, la presunción de muerte, la tutela y la pérdida o limitación de la capacidad legal para administrar bienes.\n(FE DE ERRATAS, P.O. 19 DE ENERO DE 2007\nEn caso de adopción plena sólo se asentará acta de nacimiento. Tratándose de emancipación por efecto de matrimonio, no se formará acta separada, sino que el Oficial del Registro Civil realizará las anotaciones correspondientes en las respectivas actas de nacimiento del cónyuge o de los cónyuges emancipados, expresándose esa circunstancia y la fecha en que el matrimonio se celebró, así como el número y la foja del acta relativa.\nARTÍCULO 58. Los Oficiales deberán llenar las formas autorizadas con los datos exigidos por el\nCódigo Civil para el Estado de Coahuila, esta ley u otras disposiciones aplicables, cubriendo con rayas horizontales los espacios sobrantes.\nARTÍCULO 59. Ninguna autoridad podrá ordenar, cualquiera que sea su categoría y/o competencia, que se extraigan de las oficinas del Registro Civil los libros, apéndices y demás documentos que le pertenezcan y obren bajo su responsabilidad. Se exceptúan de esta regla, el\nGobernador del Estado, el Secretario de Gobierno, el Director del Registro Civil o por mandato de autoridad judicial competente.\nLos Oficiales del Registro Civil, salvo las excepciones a que se refiere el párrafo que antecede, no obedecerán las órdenes que se libren para tal efecto, debiendo únicamente remitir bajo su estricta responsabilidad los apéndices y demás documentos al taller en donde deban ser encuadernados y otorgar copia cuando se les solicite por autoridad competente.\nARTÍCULO 60. Además de los ocho libros quintuplicados a que se refiere el artículo 55 de esta ley, los Oficiales del Registro Civil formarán los apéndices que sean necesarios, con los apuntes y correspondientes, foliándose progresivamente y anotando en cada documento el número del acta respectiva y el sello de la Oficialía.\nARTÍCULO 61. En toda acta del Registro Civil se hará constar el año, mes, día y, en su caso, hora en que se presenten los interesados. Se tomará razón detallada de los documentos que se exhiban y se asentarán los nombres, la edad, la profesión, el domicilio y la nacionalidad de los que en ellas sean mencionados en cuanto fuere posible. Deberán contener, además, la Clave Única de Registro de Población.\nARTÍCULO 62. En las actas del registro civil no podrá asentarse, ni siquiera por vía de nota o advertencia, ninguna anotación distinta de lo que deba ser declarado para el acto preciso a que\nEstado de Coahuila.\nARTÍCULO 63. Los libros del Registro Civil se formarán anualmente con los ejemplares que correspondan a cada registro, y no deberán superar doscientas hojas por cada tomo. Todas las hojas deberán ir foliadas, selladas y firmadas por los Oficiales del Registro Civil. Las páginas epígrafes: primer apellido, segundo apellido, nombre, número y página de cada inscripción principal o, en su caso, el número del folio que corresponda.\nARTÍCULO 64. Mensualmente se remitirán a la Dirección del Registro Civil los ejemplares que correspondan al Archivo General, mismos que deberán ir debidamente sellados y firmados por el\nOficial del Registro Civil.\nARTÍCULO 65. Se enviarán de igual forma a la Dirección, las copias que correspondan a la dependencia federal competente en la materia, a fin de que aquélla las remita a esa dependencia federal.\nARTÍCULO 66. Las anotaciones que, en los términos de esta ley deban realizar la Dirección y los\nOficiales, se realizarán al margen izquierdo del acta o en la parte posterior de la misma.\nARTÍCULO 67. Las inscripciones que se realicen fuera del plazo, conforme lo dispuesto por el\nCódigo Civil para el Estado de Coahuila y demás disposiciones aplicables, sólo se efectuarán mediante la presentación del certificado de inexistencia correspondiente.\nARTÍCULO 68. Los testigos que intervengan en el asentamiento de las actas del Registro Civil deberán demostrar, a satisfacción del Oficial, ser mayores de edad. Los testigos serán en el número que, para cada acto o hecho del Registro Civil, determine el Código Civil para el Estado de\nCoahuila. Se preferirá a aquéllos que designen los comparecientes, aún cuando sean parientes de los mismos.\nARTÍCULO 69. Asentado el hecho o acto y extendida el acta, ésta será leída a los interesados por el Oficial del Registro Civil. El acta deberá ser firmada por los comparecientes y si alguno de ellos no puede o no sabe firmar, lo hará otra persona a su ruego y se imprimirá la huella digital del interesado que no firmó. También se hará constar que el acta fue leída y que los interesados quedaron conformes con su contenido.\nARTÍCULO 70. Si alguno de los interesados quisiere imponerse por sí mismo del tenor del acta, quedará facultado para hacerlo y si no pudiere leer, la persona que designe de entre los presentes, la leerá a su ruego.\nARTÍCULO 71. Si un acto comenzado se entorpeciere por cualquier motivo, se inutilizará el acta marcándola con dos líneas transversales, debiéndose expresar, la causa que suspendió el acto. En estos casos, el oficial del Registro Civil deberá firmar el Acta y, en su caso, los comparecientes al acto. En caso de negativa de éstos, el Oficial asentará la causa de la misma.\nARTÍCULO 72. En todo asentamiento se observarán las prevenciones siguientes:\nI. Las actas constarán en idioma español. Se numerarán ordinariamente, valiéndose de números arábigos, utilizando al efecto cinco dígitos.\nII. Las fechas se anotarán con números arábigos utilizando dos dígitos, tanto para el mes como para el día. En el caso de los años, éstos se anotarán completos con cuatro dígitos. De igual manera se procederá con la hora.\nIII. En ningún caso se emplearán abreviaturas.\nIV. No se harán raspaduras, ni se permitirá borrar lo escrito. Cuando sea necesario testar alguna palabra o frase, se pasará por ella una línea delgada de manera tal que pueda leerse lo escrito.\nV. Antes de autorizar el acta se salvará con toda claridad lo entrerrenglonado y testado.\nEn el supuesto previsto por el artículo 467 de Código Civil para el Estado de Coahuila, la testadura se hará por completo, de modo que las palabras o frases correspondientes queden absolutamente ilegibles, advirtiéndose al final del acta la causa por la que se ha procedido en esta forma.\nCAPÍTULO SEGUNDO\nLOS LIBROS DE LAS ACTAS DE NACIMIENTO\nY DE RECONOCIMIENTO DE HIJOS\nARTÍCULO 73. Los Oficiales del Registro Civil deberán registrar solamente los nacimientos que se hayan efectuado dentro de su jurisdicción, salvo las excepciones autorizadas por el o la titular de la\nDirección, en los términos de las disposiciones jurídicas aplicables.\nARTÍCULO 74. Para efectuar un registro de nacimiento, se deben cumplir con los requisitos siguientes:\nI. Presentar, los interesados, el certificado de nacimiento del menor emitido por la institución de salud en la que el mismo hubiere nacido.\n(ADICIONADO, P.O. 25 DE NOVIEMBRE DE 2005)\nEn caso de que el alumbramiento se hubiere presentado en un lugar diferente a una institución de salud, deberá procederse conforme a lo establecido por el artículo 163 del\nCódigo Civil de Coahuila.\nII. Tener domicilio dentro de la jurisdicción de la oficina del Registro Civil de que se trate, lo que demostrará a satisfacción del Oficial, conforme a los lineamientos establecidos en el Código\nCivil para el Estado de Coahuila.\n(ADICIONADO, P.O. 17 DE AGOSTO DE 2004)\nSi después de registrado el nacimiento fuere emitida un resolución judicial mediante la cual se determine la paternidad o maternidad; los oficiales del Registro Civil procederán a realizar las anotaciones que correspondan en las actas respectivas, conforme a dicha resolución.\nARTÍCULO 75. En toda acta de nacimiento se asentará la huella digital del pulgar de la mano derecha del niño o niña presentado o presentada. La misma obligación tendrán los mayores que\nCódigo Procesal Civil para el Estado de Coahuila.\nARTÍCULO 76. Sólo en casos de extrema necesidad debidamente justificada a juicio de los mismos o del titular de la Dirección, los Oficiales del Registro Civil estarán obligados a acudir al lugar en donde el recién nacido se encuentre, para el efecto de levantar el acta correspondiente.\nARTÍCULO 77. De acuerdo con el artículo 166 del Código Civil para el Estado de Coahuila, antes de asentar el acta de nacimiento de un hijo habido dentro del matrimonio, en el libro correspondiente, los Oficiales del Registro Civil deberán cerciorarse de que los comparecientes que manifiestan ser los padres están casados entre sí. Lo anterior podrá ser corroborado mediante la exhibición de la copia certificada del acta de matrimonio correspondiente; o bien, mediante la compulsa del libro correspondiente, en el caso de que el matrimonio se haya efectuado en la misma Oficialía en que se registra el nacimiento.\nARTÍCULO 78. No se expresará en el acta correspondiente que el hijo es adulterino o incestuoso, en los casos a que se refieren los artículos 169 y 171 del Código Civil. Tampoco se expresará que su filiación fue decretada mediante resolución firme dictada por la autoridad judicial competente, en los casos a que se refiere el artículo 481 del citado ordenamiento.\n(REFORMADO P.O. 28 DE DICIEMBRE DE 2007)\nARTÍCULO 79. En el caso de los menores expósitos a que se refiere el artículo 172 bis del Código\nCivil, el Oficial del Registro Civil, recibirá los documentos y la investigación integrada por la\nProcuraduría de la Familia respecto del menor expósito a fin de que se expida el acta respectiva.\n(REFORMADO P.O. 28 DE DICIEMBRE DE 2007)\nARTÍCULO 80. Para la expedición de las actas que el Oficial del Registro Civil levante en estos casos, deberá sujetarse a lo establecido en el artículo 174 del Código Civil del Estado de Coahuila.\nARTÍCULO 81. (DEROGADO P.O. 28 DE DICIEMBRE DE 2007)\nARTÍCULO 82. Si al dar aviso de un nacimiento se comunicara también la muerte del recién nacido, se extenderán dos actas, una de nacimiento y otra de defunción, en los términos de la presente ley y del Código Civil para el Estado de Coahuila.\nARTÍCULO 83. Si después de registrado el nacimiento, el padre, la madre o ambos pretendieren el reconocimiento de un hijo nacido fuera de matrimonio, aquéllos deberán satisfacer los requisitos exigidos por el artículo 181 del Código Civil para el Estado de Coahuila.\nEl Oficial del Registro Civil deberá orientar a los interesados respecto de los requisitos que deberán cubrir para que se realice el reconocimiento.\nARTÍCULO 84. Si el reconocimiento se hiciere en oficina distinta de aquella en la que se levantó el acta de nacimiento, el Oficial del Registro Civil que autorice el acta de reconocimiento remitirá copia de ésta al encargado de la oficina que haya registrado el nacimiento y a la Dirección, para efecto de que se haga la anotación en el acta respectiva.\nCAPÍTULO TERCERO\nLOS LIBROS DE LAS ACTAS DE ADOPCIÓN Y DE TUTELA\nARTÍCULO 85. Las actas de adopción semiplena se asentarán con arreglo a lo dispuesto en la\nSección Cuarta, Capítulo X, Título Segundo del Libro Primero del Código Civil para el Estado de\nCoahuila.\nARTÍCULO 86. Extendida el acta de adopción semiplena, se anotará la de nacimiento del adoptado y se archivará copia de las diligencias relativas, poniéndole el mismo número del acta de adopción y observándose en lo conducente, lo dispuesto por el artículo 84 de esta ley.\nEn los casos de adopción plena, se cancelará el acta de nacimiento del adoptado, si es que existe y, en su lugar, se levantará acta de nacimiento que contendrá los datos del adoptado, de los padres adoptivos y de los ascendientes de éstos, así como de los testigos de ese acto. A partir del levantamiento del acta de nacimiento, no se publicará ni se expedirá ninguna otra que revele el origen del adoptado ni su condición de tal, observándose, en todo caso, lo previsto en el párrafo tercero del artículo 189 del Código Civil para el Estado de Coahuila.\nARTÍCULO 87. Las copias certificadas de las diligencias judiciales y demás documentos relativos pasarán a formar parte del apéndice que corresponda.\nARTÍCULO 88. El juez que resuelva que una adopción semiplena queda sin efectos, deberá remitir copia certificada por duplicado de su resolución, al Oficial de Registro Civil que corresponda, asimismo, deberá remitir una copia a la Dirección, con el fin de que se proceda a cancelar el acta de adopción y las anotaciones respectivas en los términos de esta ley.\nEl plazo para enviar las copias a que se refiere el párrafo anterior, será de ocho días contados a partir de la fecha de la emisión correspondiente.\nARTÍCULO 89. Las actas de tutela se asentarán con arreglo a lo dispuesto en la Sección Quinta,\nCapítulo X, Título Segundo, del Libro Primero del Código Civil para el Estado de Coahuila.\nARTÍCULO 90. Una vez asentada el acta de tutela, se procederá a efectuar la anotación en el acta de nacimiento del sujeto a tutela, observándose lo dispuesto en el artículo 84 de esta ley.\nARTÍCULO 91. Cuando un juez resuelva que una tutela queda sin efectos por haber desaparecido la incapacidad que le dio origen; o bien, porque el sujeto a ella, entró a la patria potestad por reconocimiento o adopción, deberá remitir inmediatamente copia certificada por duplicado de su resolución al Oficial del Registro Civil que corresponda y una copia a la Dirección, para que se proceda a cancelar el acta de tutela y la anotación marginal a que se refiere el artículo que antecede.\nCAPÍTULO CUARTO\nEL LIBRO DE LAS ACTAS DE MATRIMONIO\nARTÍCULO 92. La celebración del matrimonio se sujetará a las formalidades y solemnidades que establece el Código Civil para el Estado de Coahuila.\nARTÍCULO 93. Toda persona que pretenda contraer matrimonio, independientemente de su edad, deberá satisfacer lo previsto en el artículo 197 del Código Civil para el Estado de Coahuila.\nARTÍCULO 94. Los Oficiales del Registro Civil proporcionarán a quienes pretendan contraer matrimonio, las formas de solicitudes de matrimonio, sin perjuicio de la libertad que tienen los interesados de formular este documento de manera distinta y de acuerdo con sus circunstancias particulares.\nARTÍCULO 95. Cuando alguno o ambos contrayentes sean extranjeros, se deberá cumplir con lo dispuesto por el artículo 68 de la Ley General de Población y el artículo 14 de la presente ley.\nARTÍCULO 96. Las personas menores de edad que pretendan contraer matrimonio bajo el régimen de sociedad conyugal, deberán presentar las capitulaciones matrimoniales previamente aprobadas por las personas cuyo consentimiento sea necesario para la celebración del matrimonio.\nSi por el contenido de las capitulaciones matrimoniales, éstas deben constar en escritura pública, se acompañará testimonio de ésta.\nSi el matrimonio se desea celebrar bajo el régimen de sociedad conyugal, pero no se presentan las capitulaciones matrimoniales, el mismo, por disposición de ley, se entenderá celebrado bajo el régimen de separación de bienes.\nARTÍCULO 97. Si alguno de los pretendientes hubiere estado bajo tutela por padecer alguno de los estados de incapacidad a que se refiere la fracción II del artículo 48 del Código Civil para el\nEstado de Coahuila, se deberá acompañar a la solicitud, la resolución del juicio que haya declarado la cesación de la tutela por haber desaparecido la causa que la motivó.\nARTÍCULO 98. El Oficial del Registro Civil tendrá la obligación de anotar en las actas de nacimiento de los contrayentes, la razón de que han contraído matrimonio. Si el nacimiento se hubiera asentado en una oficina distinta a aquélla en que se levantó el acta de matrimonio, el\nOficial que autoriza el mismo, remitirá copia del acta relativa, al encargado de la oficina que haya\nARTÍCULO 99. En caso de que se declare la nulidad del matrimonio, el Oficial del Registro Civil tendrá la obligación de hacer la anotación correspondiente en las actas de matrimonio.\nCAPÍTULO QUINTO\nEL LIBRO DE LAS ACTAS DE DIVORCIO\nARTÍCULO 100. Las actas de divorcio se levantarán de acuerdo con las disposiciones relativas del\nCódigo Civil para el Estado de Coahuila.\nARTÍCULO 101. De acuerdo con el artículo 213 del Código Civil, el juez que decrete un divorcio, deberá remitir inmediatamente a la Dirección y al Oficial del Registro Civil que corresponda, una copia certificada de la sentencia y de los datos de identificación de las actas de nacimiento y de matrimonio de los divorciados.\nARTÍCULO 102. El juez que resuelva que un divorcio queda sin efectos, deberá remitir copia certificada de su resolución al Oficial del Registro Civil que corresponda y a la Dirección, en los términos del artículo anterior, para que se proceda a cancelar el acta de divorcio y las anotaciones marginales correspondientes.\nARTÍCULO 103. La copia certificada a que se refieren los dos artículos anteriores y los demás documentos relativos, pasarán a formar parte del apéndice que corresponda.\nCAPÍTULO SEXTO\nEL LIBRO DE LAS ACTAS DE DEFUNCIÓN\nARTÍCULO 104. Las actas de defunción se asentarán de conformidad con las disposiciones de la\nSección Novena, Capítulo X, Título Segundo, del Libro Primero del Código Civil para el Estado de\nCoahuila. Las inscripciones deberán realizarse dentro de los 180 días de ocurrido el deceso.\nTratándose del registro fuera del plazo al que se refiere el párrafo que antecede, se deberá acompañar el certificado de inexistencia que corresponda.\nARTÍCULO 105. No se podrá realizar ninguna inhumación o cremación sin autorización por escrito que otorgue el Oficial del Registro Civil, quien deberá asegurarse plenamente del fallecimiento de la persona, mediante certificado emitido por médico legalmente autorizado para ello. Tampoco fallecimiento, excepto en los casos en que se ordene lo contrario por autoridad competente para ello.\nARTÍCULO 106. Para tener por comprobado el fallecimiento de una persona, el Oficial del Registro\nCivil exigirá que se le presente el certificado médico de defunción, en el que consten las generales que se conocieren del difunto, el lugar o domicilio en que haya ocurrido el deceso, la hora del fallecimiento y las causas de éste.\nARTÍCULO 107. Cualquier persona o autoridad que tenga conocimiento de una defunción, deberá informarlo al Oficial del Registro Civil que corresponda.\nARTÍCULO 108. En el acta de defunción se asentarán los datos que el Oficial del Registro Civil adquiera del certificado médico. El acta de defunción será firmada por el declarante y dos testigos de identidad del fallecido. Para tal efecto, se consideran testigos preferentes de identidad del fallecido, sus parientes, si los hay o, en su defecto, sus vecinos.\nARTÍCULO 109. Cuando por circunstancias especiales así valoradas por el Oficial del Registro\nCivil, no pueda presentarse el certificado médico de defunción, aquél ordenará oficiosamente que algún médico legista de la Procuraduría de Justicia del Estado, o cualquier otro de la localidad con cargo o sin cargo oficial o, en último caso, los prácticos, expida gratuitamente el certificado médico de defunción correspondiente.\nARTÍCULO 110. Cuando el Oficial del Registro Civil sospeche que la muerte fue violenta, dará parte al Ministerio Público, debiéndole comunicar todos los informes que tenga, esto con el fin de que proceda a la averiguación conforme a derecho.\nCuando dicha institución averigüe un fallecimiento, dará parte al Oficial del Registro Civil para que asiente el acta respectiva. Si se ignora el nombre del difunto, se asentarán las señas de éste, las de los vestidos y objetos que con él se hubieren encontrado y, en general, todo lo que pueda conducir a identificar a la persona; y siempre que se adquieran mayores datos, se comunicarán al\nOficial del Registro Civil para que los anote en el acta correspondiente.\nARTÍCULO 111. En los casos de inundación, terremoto, naufragio, incendio o cualquier otro siniestro, desastre, catástrofe y/o calamidad pública en que no sea fácil y/o posible reconocer el cadáver, se formará el acta con los datos que ministren los que lo recogieron, expresando, en cuanto fuere posible, las señas del mismo y de los vestidos u objetos que con él se hayan encontrado.\nARTÍCULO 112. En las actas de nacimiento y, en su caso, en las de matrimonio se anotarán los datos relativos a la identificación del acta de defunción.\nARTÍCULO 113. Para cumplir con la disposición del artículo anterior, el Oficial que tenga conocimiento del fallecimiento enviará a la Dirección y al Oficial u Oficiales que correspondan, copia certificada del acta relativa.\nARTÍCULO 114. La Dirección y los Oficiales respectivos deberán facilitar a las autoridades en materia electoral el acceso a sus archivos, a fin de coadyuvar en las funciones que a ellas correspondan conforme a la legislación aplicable.\nCAPÍTULO SÉPTIMO\nLAS ACTAS QUE DECLAREN LA AUSENCIA, LA PRESUNCIÓN\nDE MUERTE O LA INCAPACIDAD LEGAL PARA\nADMINISTRAR BIENES\nARTÍCULO 115. Los Oficiales del Registro Civil, al recibir de la autoridad judicial, copia certificada de la ejecutoria que declare la incapacidad legal para administrar bienes, la ausencia o la presunción de muerte, en los términos del Código Civil para el Estado, tendrán la obligación de levantar el acta correspondiente, insertando en la misma, la parte resolutiva de la sentencia judicial que se les comunica, efectuando, además, la anotación marginal relativa en el acta de nacimiento correspondiente.\nLa autoridad judicial deberá enviar copia certificada por duplicado de su resolución, al Oficial que corresponda y remitir una copia a la Dirección para que efectúen, el primero, el acta y los apéndices y, ambos, la anotación marginal en el acta de nacimiento.\nARTÍCULO 116. Cuando se recobre la capacidad legal para administrar bienes o se presente la persona declarada ausente o cuya muerte se presumía, la autoridad que corresponda y/o, en su cancele el acta relativa y la anotación que se hubiere hecho en el acta de nacimiento respectiva.\nCAPÍTULO VIII\nArtículo 116-1.- La celebración del pacto civil de solidaridad se sujetará a las formalidades y solemnidades que establece el Código Civil para el Estado de Coahuila.\nArtículo 116-2.- Los Oficiales del Registro Civil proporcionarán a quienes pretendan contraer pactos civiles de solidaridad, las formas de solicitudes de pacto civil, sin perjuicio de la libertad que tienen los interesados de formular este documento de manera distinta y de acuerdo con sus circunstancias particulares.\nArtículo 116-3.- Si alguno de los pretendientes hubiere estado bajo tutela por padecer alguno de los estados de incapacidad a que se refiere la fracción II del artículo 48 del Código Civil para el\nEstado de Coahuila, se deberá acompañar a la solicitud, la resolución del juicio que haya declarado la cesación de la tutela por haber desaparecido la causa que la motivó.\nArtículo 116-4.- El Oficial del Registro Civil tendrá la obligación de anotar en las actas de nacimiento de los contratantes, la razón de que han celebrado pacto civil de solidaridad. Si el nacimiento se hubiera asentado en una oficina distinta a aquélla en que se levantó el acta de pacto civil de solidaridad, el Oficial que autoriza el mismo, remitirá copia del acta relativa, al encargado de la oficina que haya registrado el nacimiento y a la Dirección, para que realice la anotación marginal correspondiente.\nArtículo 116-5.- En caso de que se declare la nulidad del pacto civil de solidaridad, el Oficial del\nRegistro Civil tendrá la obligación de hacer la anotación correspondiente en las actas de pacto civil.\n(ADICIONADO, P.O. 12 DE ENERO DE 2007\nCAPÍTULO IX\nEL LIBRO DE LAS TERMINACIONES DE LOS PACTOS CIVILES DE SOLIDARIDAD\nArtículo 116-6.- Las actas de terminación de pactos civiles de solidaridad se levantarán de acuerdo con las disposiciones relativas del Código Civil para el Estado de Coahuila.\nArtículo 116-7.- La copia certificada a que se refieren el artículo anterior y los demás documentos relativos, pasarán a formar parte del apéndice que corresponda.\nTÍTULO CUARTO\nLAS ANOTACIONES Y RECTIFICACIONES DE LAS\nACTAS DEL REGISTRO CIVIL\nCAPÍTULO PRIMERO\nLAS ANOTACIONES\nARTÍCULO 117. Toda acta del Registro Civil relativa a otra ya asentada, podrá anotarse a petición de los interesados. expresamente la ley, y se insertará en todos los testimonios que se expidan.\nARTÍCULO 118. Cuando habiéndose remitido el libro original respectivo a la Dirección y tuviere que hacerse al margen alguna anotación de las previstas en el artículo anterior, se librará oficio a la dependencia mencionada para que efectúe la anotación correspondiente.\nARTÍCULO 119. Si concluida y firmada un acta se hubiere dejado de asentar algún dato, el Oficial hará al margen la anotación correspondiente, firmándola en unión de los que intervinieron en el acto, siempre que con dicha anotación no se contradiga la esencia del acto registrado.\nCAPÍTULO SEGUNDO\nLA RECTIFICACIÓN Y ACLARACIÓN DE LAS ACTAS\nDEL REGISTRO CIVIL\nSECCIÓN PRIMERA\nDISPOSICIONES GENERALES\nARTÍCULO 120. La rectificación o aclaración de un acta del Registro Civil, únicamente procederá en los casos y en los términos señalados por los artículos 234 y 235 del Código Civil para el\nEstado de Coahuila, siempre que se cumplan las formalidades previstas en los mismos.\nARTÍCULO 121. Las resoluciones que concedan o nieguen la rectificación, motivarán la anotación del acta correspondiente en los términos del artículo 238 del Código Civil para el Estado de\nCoahuila.\nARTÍCULO 122. El juez que conozca de un juicio de rectificación deberá solicitar un informe a la\nDirección a efecto de que le proporcione una copia certificada del acta que se pretenda rectificar, obtenida de los libros duplicados que obren en su archivo general y manifieste si ante esa dependencia se ha registrado solicitud de rectificación.\nSECCIÓN SEGUNDA\nEL PROCEDIMIENTO DE ACLARACIÓN ANTE LA\nDIRECCIÓN DEL REGISTRO CIVIL\nARTÍCULO 123. Procederá la solicitud de aclaración de actas ante la Dirección en los casos previstos por el artículo 235 del Código Civil para el Estado de Coahuila, siempre y cuando se fundamente en errores cuya evidencia resulte de la confrontación con los documentos en cuya virtud se ha practicado la inscripción; o bien, cuando el error quede establecido por las demás circunstancias de la inscripción, o de otra u otras inscripciones que hagan fe del acto o hecho correspondiente. aclaración hasta la citación para resolución.\nARTÍCULO 124. Los requisitos para iniciar el trámite de aclaración serán:\nI. La comparecencia personal del interesado o, en su caso, del mandatario especial cuyo otorgante ante notario público. Tratándose de menores de edad deberá comparecer quien ejerza la patria potestad o tutela.\nII. El llenado de la forma de solicitud proporcionada al compareciente por la Dirección, previa presentación de identificación oficial con fotografía.\nIII. Cubrir el pago de los derechos que correspondan.\nARTÍCULO 125. La solicitud de aclaración contendrá:\nI. El nombre completo del solicitante y demás generales que estime necesarios solicitar la\nDirección.\nII. El documento que presenta para identificarse.\nIII. Los datos de identificación del acta que se pretende modificar.\nIV. Los hechos en que el solicitante funde su pretensión numerándolos y narrándolos sucintamente, con claridad y precisión.\nV. Los documentos probatorios que demuestren el error en el asentamiento, en los términos de esta ley u otras disposiciones aplicables.\nVI. La firma o huella digital del solicitante.\nARTÍCULO 126. La Dirección resolverá dentro del término de ocho días hábiles, los expedientes que ante ella se sustanciaron. Dentro de los diez días hábiles contados a partir de su recepción, resolverá sobre aquellos que se instruyeron ante los Oficiales Coordinadores.\nARTÍCULO 127. A efecto de mejor proveer, la Dirección queda facultada para allegarse de los documentos probatorios que estime convenientes.\nCon testimonio de la resolución se ordenará que se hagan las anotaciones correspondientes en el original de la Oficialía en que se halle el asiento a que aquélla se refiere y en el duplicado de la\nDirección.\nARTÍCULO 128. La Dirección, a petición de parte legítima, previa comprobación, procederá a hacer la aclaración de un acta en los casos siguientes:\nI. Cuando se trate de meras discrepancias entre el libro duplicado y el original.\nII. El uso de abreviaturas o guarismos no permitidos, el empleo de idioma distinto al español, la difícil legibilidad de caracteres, el error mecanográfico u ortográfico, así como la defectuosa expresión de conceptos cuando por el contexto de la inscripción o de otras inscripciones no haya duda de su contenido.\nIII. Cuando se trate de adicionar asientos ya extendidos y firmados de datos o circunstancias plenamente demostrados, correspondientes a los mismos y que dejaron de consignarse, al practicar el asiento, por desconocimiento de tales datos o por negligencia del Oficial del\nRegistro Civil.\nIV. La indicación equivocada de sexo, cuando no haya duda sobre la identidad del nacido por las demás circunstancias de la inscripción.\nV. Cuando se trate de errores cuya evidencia resulte de la confrontación con otra u otras inscripciones que hagan fe del hecho correspondiente.\nARTÍCULO 129. Cuando la Dirección tenga conocimiento de una duplicidad de asientos, en la misma o en diversas Oficialías en la entidad, ordenará la cancelación del asiento de más reciente fecha y, en su caso, el traslado de los asientos marginales al más antiguo.\nARTÍCULO 130. En todo lo no previsto en esta sección, se aplicarán supletoriamente las disposiciones conducentes del Código Procesal Civil para el Estado.\nTÍTULO QUINTO\nLAS RESPONSABILIDADES Y SANCIONES\nCAPÍTULO ÚNICO\nBASES GENERALES\nARTÍCULO 131. Las sanciones señaladas en este apartado se aplicarán sin perjuicio de la responsabilidad que determine el Código Civil para el Estado de Coahuila u otras leyes, para el caso de faltarse al cumplimiento de sus preceptos.\nARTÍCULO 132. A los funcionarios del Registro Civil, así como a los Oficiales, cuando realicen actos contrarios a las disposiciones jurídicas vigentes en el Estado, a los acuerdos administrativos dictados por autoridades competentes con arreglo a esta ley o a otras disposiciones aplicables, así como a instrucciones giradas por la Dirección, en el ámbito de su competencia, se les podrá aplicar las siguientes sanciones:\nI. Amonestación.\nII. Multa.\nIII. Suspensión temporal del cargo.\nIV. Destitución o inhabilitación.\nLas multas que imponga la Dirección se considerarán, para todos los efectos legales a que haya lugar, como créditos fiscales.\nARTÍCULO 133. Las sanciones a que se refiere esta ley, se impondrán tomando en consideración lo siguiente:\nI. La gravedad de la infracción en que se incurra.\nII. El monto del beneficio, daño o perjuicio económico derivado del incumplimiento de las obligaciones a cargo del infractor, con motivo de su encargo.\nIII. Las condiciones personales y socioeconómicas del infractor.\nIV. Los medios de ejecución de que se valió el infractor.\nV. La calidad de reincidente del infractor.\nVI. La antigüedad en el encargo.\nEn el caso de sanciones por beneficios obtenidos y/o daños y perjuicios causados por el incumplimiento de las obligaciones a que se refieren los artículos 35,36,38 y demás relativos de esta ley, se aplicarán dos tantos del lucro obtenido y de los daños y perjuicios causados.\nPara los efectos de esta ley, se entenderá por reincidencia, la comisión de las infracciones previstas en la misma en dos o más ocasiones, en un plazo de un año.\nLa dirección hará uso de las medidas legales necesarias, incluyendo el auxilio de la fuerza pública para hacer cumplir sus determinaciones.\nARTÍCULO 134. Las amonestaciones, en los casos que procedan y las sanciones económicas a los Oficiales del Registro Civil, serán impuestas por el Director o la Directora del Registro Civil y para su cobro se recurrirá en caso necesario, por constituirse en créditos fiscales, al procedimiento económico coactivo previsto por la ley correspondiente.\nEn estos casos, el Director o la Directora ordenará que se practique una investigación, de cuyo acto de que se trate, dictará resolución, oyendo previamente en defensa al Oficial. por el titular del Ejecutivo, previo cumplimiento del procedimiento previsto en esta ley. cualquier Oficial del Registro Civil durante la tramitación del procedimiento, en forma precautoria.\nARTÍCULO 135. Las sanciones administrativas aplicables a los Subdirectores, al Oficial Mayor, a los Registradores, a los Visitadores Generales y a los Jefes de Departamento se determinarán y aplicarán por el titular de la Dirección, en los términos de las disposiciones aplicables.\nARTÍCULO 136. Las sanciones aplicables al Director o a la Directora del Registro Civil se aplicarán por el titular del Ejecutivo, conforme a lo siguiente:\nI. Se mandará practicar una investigación a cargo de la Secretaría de Gobierno.\nII. El resultado de la investigación se hará del conocimiento del Director o de la Directora a efecto de que prepare su defensa.\nIII. La Secretaría de Gobierno instruirá el procedimiento correspondiente y en él oirá personalmente al Director o a la Directora del Registro Civil, concediéndole el término de veinte días hábiles para que aporte las pruebas que estime pertinentes para su defensa.\nIV. La Secretaría de Gobierno celebrará una audiencia, dentro de los 10 días siguientes al vencimiento del término a que se refiere la fracción que antecede, en la que se deshogarán las pruebas ofrecidas y admitidas. Desahogada la audiencia, se presentará un proyecto al titular del Ejecutivo para su resolución definitiva.\nARTÍCULO 137. El Oficial del Registro Civil, que sin motivo justificado retarde la celebración de un matrimonio, se hará acreedor a una multa equivalente a treinta días de salario mínimo general vigente en el Estado y, en caso de reincidencia, será destituido de su cargo.\nARTÍCULO 138. Los Oficiales que autoricen actas o asienten hechos del estado civil fuera de la circunscripción territorial que les corresponda, o cobren honorarios superiores a los autorizados en la tarifa oficial, serán sancionados con una multa de cinco a cincuenta días de salario mínimo general vigente en el Estado y, en caso de reincidencia, con la suspensión temporal o remoción del cargo, según la gravedad del caso.\nARTÍCULO 139. Son causas de destitución de los Oficiales del Registro Civil, las siguientes:\nI. Las infracciones a los artículos 146, 210 y 468 del Código Civil para el Estado de Coahuila, así como a los artículos 56, 57, 58 y 59 de la presente ley.\nII. Cuando incurran en la omisión o variación de los datos contenidos en las actas o certificaciones de las mismas, así como en la falsificación de actas o la inserción en ellas de circunstancias o declaraciones prohibidas por la ley.\nIII. Cuando sean condenados por sentencia que cause ejecutoria, por la comisión de delito intencional.\nIV. Cuando se haga pública o notoria su mala conducta.\nV. Cuando se haga un uso inadecuado del sistema informático implementado en la Dirección o en las Oficialías, o del equipo de cómputo.\nARTÍCULO 140. Tratándose de actos u omisiones de los Oficiales del Registro Civil, que por su gravedad pudieran motivar la suspensión o remoción del cargo, antes de dictar resolución sobre el particular, se seguirá el siguiente procedimiento:\nI. La Secretaría de Gobierno designará un visitador especial que practicará la investigación que corresponda y con el resultado de la misma, se dará vista a la Dirección para que ésta emita su opinión en un plazo no mayor de diez días hábiles contados a partir de la recepción del informe que resulte de la investigación.\nII. La opinión que emita la Dirección se remitirá al titular de la Secretaría de Gobierno. Recibida esa opinión, el Secretario de Gobierno o la persona que en su representación designe para tal efecto, oirá personalmente al Oficial de que se trate, concediéndole el término de quince días hábiles para que aporte pruebas en su defensa y fenecido dicho plazo, se integrará el expediente relativo, en vista del cual, el titular del Ejecutivo dictará la resolución definitiva que corresponda.\nIII. La substanciación del procedimiento señalado, en ningún caso podrá exceder del término de dos meses.\nARTÍCULO 141. Son causas de destitución del Director o de la Directora de los Subdirectores, del\nOficial Mayor, de los Registradores y el Jefe del Departamento del Archivo General de la Dirección, las que se mencionan en las fracciones II, III, IV y V del artículo 138 de esta ley.\nLos Visitadores Generales y los Jefes de departamento adscritos a la Dirección igualmente serán removidos de su cargo si incurren en los supuestos contenidos en las referidas fracciones III, IV y\nTambién habrá lugar a la destitución del Director o de la Directora cuando teniendo conocimiento de alguna irregularidad, no informe al Gobernador, por conducto de la Secretaría de Gobierno, de las faltas cometidas por los Oficiales del Registro Civil y por los Registradores, cuando ameriten su destitución.\nARTÍCULO 142. Las infracciones al Código Civil para el Estado de Coahuila y a esta ley, que no tengan señalada sanción especial, se castigarán con una multa de tres a cincuenta días de salario mínimo general vigente en la entidad, a juicio de la Dirección que la impondrá.\nTRANSITORIOS\nPRIMERO. Esta ley entrará en vigor el día siguiente al de su publicación en el Periódico Oficial del\nSEGUNDO. Se abroga la Ley Reglamentaria del Registro Civil para el Estado de Coahuila, 1975; y se derogan todas las disposiciones que se opongan al presente decreto.\nTERCERO. El titular del Ejecutivo dentro del plazo de 90 días hábiles siguientes a la entrada en vigor de esta ley, podrá expedir las adecuaciones que resulten necesarias al Reglamento Interior de ser necesario.\nPara tal efecto, el titular de la Dirección del Registro Civil procederá a elaborar un anteproyecto de reformas para someterlo a la consideración del Ejecutivo, por conducto de la Secretaría de\nGobierno.\nCUARTO. Cuando una ley, reglamento, decreto u otras disposiciones jurídicas o administrativas aludan a la Dirección Estatal del Registro Civil, se entenderá la referencia a la Dirección del\nRegistro Civil prevista en esta ley.\nQUINTO. La Dirección del Registro Civil diseñará y elaborará un programa permanente de profesionalización de los oficiales del Registro Civil, con el objeto de garantizar la certeza y seguridad de los actos regístrales conforme a derecho.\nEste programa deberá implementarse y ejecutarse por la Dirección y deberá comprender todas aquellas acciones para garantizar, con base en los objetivos que resulten necesarios, la actualización de los oficiales del Registro Civil, la mejora en la prestación de los servicios a su cargo y la mayor eficiencia y eficacia en el desempeño de sus funciones.\nCorresponderá a la Dirección del Registro Civil establecer los mecanismos para supervisar y evaluar los resultados del programa.\nDADO en el Salón de Sesiones del Congreso del Estado, en la Ciudad de Saltillo, Coahuila, a los veinticuatro días del mes de junio del año dos mil tres.\nDIPUTADA PRESIDENTA.\nLATIFFE ELOÍSA BURCIAGA NEME.\nDIPUTADO SECRETARIO. DIPUTADO SECRETARIO.\nFRANCISCO ORTIZ DEL CAMPO. MIGUEL FELIPE MERY AYUP.\nN. DE E. A CONTINUACION SE TRANSCRIBEN LOS ARTICULOS TRANSITORIOS DE LOS DECRETOS\nDE REFORMAS A LA PRESENTE LEY.\nPRIMERO. El presente decreto entrará en vigor sesenta días hábiles siguientes de su publicación en el\nSEGUNDO. Los artículos del Código Civil y del Código Procesal Civil en los que se autorizan las pruebas periciales biológicas para la determinación de la paternidad y la maternidad, así como la presunción que se genera en perjuicio de quienes no otorgan su consentimiento para someterse a dichas pruebas, entrarán en los que se practiquen y que las Dependencias Oficiales competentes estén en condiciones de realizarlas, con el máximo grado de confiabilidad.\nPRIMERO. El presente decreto entrará en vigor al día siguiente de su publicación en el Periódico Oficial del\nEstado.\nSEGUNDO. Se deroga cualquier otra disposición que se oponga al presente decreto.\nÚNICO.- Esta reforma entrará en vigor al día siguiente de su publicación en el Periódico Oficial del Estado.\nPRIMERO.- Este Decreto entrará en vigor al día siguiente de su publicación en el periódico Oficial del\nGobierno Estado.\nSEGUNDO.- Dentro de los cuarenta y cinco días a la fecha de publicación de este Decreto se expedirán, por conducto del Ejecutivo del Estado, las adecuaciones reglamentarias que sean necesarias para la ejecución cabal de este Decreto, especialmente, las que regule el registro del pacto civil de solidaridad.\nTERCERO.- Publíquese el presente Decreto, al igual que la exposición de motivos, en el Periódico Oficial del\nPRIMERO.- Este Decreto entrará en vigor al día siguiente de su publicación en el Periódico Oficial del\nSEGUNDO.- Se derogan todas las disposiciones legales que se opongan al presente Decreto.",
  "ordenamiento": "REGLAMENTO",
  "jurisdiccion": "COAHUILA",
  "fuente_oficial": "DIARIO OFICIAL DE LA FEDERACION",
  "Fecha de Publicación": "25 de julio de 2003",
  "ULTIMA REFORMA PUBLICADA": "28 DE DICIEMBRE DE 2007",
  "es_escaneado": false,
  "tiene_tablas": false,
  "materia": [
    "civil",
    "registral"
  ]
}