{
  "titulo": "Ley DE FOMENTO A LA COMPETITIVIDAD y DESARROLLO ECONÓMICO PARA EL ESTADO DE BAJA CALIFORNIA",
  "Contenido": "ECONÓMICO PARA EL ESTADO DE BAJA CALIFORNIA\nPublicado en el Periódico Oficial No. 27,\nCAPÍTULO I\nDISPOSICIONES GENERALES\nArtículo 1.- Las disposiciones de esta Ley son de observancia general en el Estado de\nBaja California, y tiene por objeto fomentar la competitividad y el desarrollo económico del Estado, a través de una Política de Desarrollo Empresarial sustentada en las Vocaciones Regionales, así como en el otorgamiento de Estímulos a la inversión privada.\nArtículo 2.- La aplicación de la presente Ley corresponde al Ejecutivo del Estado, por conducto de las Secretarías de Economía Sustentable y Turismo y de Hacienda, así como a los\nAyuntamientos dentro del ámbito de sus respectivas competencias, en coordinación con el sector privado.\nPárrafo Reformado\nPara efectos de lo previsto en el párrafo anterior, las Secretarías de Economía Sustentable y Turismo y de Hacienda, se coordinarán con las demás Dependencias del Estado y Entidades\nParaestatales, cuyas atribuciones incidan en el cumplimiento del objeto de esta Ley.\nPárrafo Reformado\nLas Secretarías a que se refiere el artículo anterior dentro de sus respectivos ámbitos de competencia, se encuentran facultadas para interpretar esta Ley y su Reglamento, así como para emitir las disposiciones de carácter general que resulten necesarias para su adecuado cumplimiento, mismas que deberán publicarse en el Periódico Oficial del Estado.\nArtículo Reformado\nArtículo 3.- Para efectos de esta Ley se entiende por:\nI. Cadena Productiva: Cada una de las etapas del proceso de producción empresarial de un bien o servicio que abarca desde la obtención de sus insumos originarios, su transformación a producto, distribución y consumo;\nII. Comité: El Comité Consultivo de Fomento a la Competitividad y Desarrollo Económico de Baja California.\nIII. Consejo: El Consejo Estatal Empresarial, que opera como órgano del sector privado;\nIV. Empresa: La persona física o moral legalmente constituida, cuyo objeto sea llevar a mercado;\nDe igual forma, se entenderá por Empresa:\nLey de Fomento a la Competitividad y Página 1\na) Las personas morales nacionales que conjuntamente aporten sus servicios de manera complementaria entre sí, para consolidar un mismo proyecto de inversión en Baja California, dediquen.\nb) La persona moral nacional que sea contratada por una empresa extranjera que requiere de la conjunción de esfuerzos y servicios para ejecutar un proyecto de inversión en Baja\nCalifornia. La empresa contratada deberá prestar por lo menos los siguientes servicios: contratación de personal, administración de recursos humanos y materiales, servicios contables, pago de nomina y operación de tráfico y aduanas.\nEl reglamento de la presente Ley establecerá los mecanismos para la debida aplicación de los beneficios fiscales relativos a las empresas señaladas en los incisos anteriores.\nV. Estímulos: Apoyos que se otorgan en los términos de esta Ley y las disposiciones fiscales de carácter estatal;\nVI. FOINFRA: El Fondo de Infraestructura Pública para el Fomento a la Inversión privada;\nVII. Fomento a la Competitividad: Acciones tendientes a propiciar la calidad del ambiente económico e institucional para el desarrollo sostenible y sustentable de las actividades privadas y el aumento de la productividad; y a nivel Empresa, la capacidad para mantener y fortalecer su rentabilidad;\nVIII. Fomento al Desarrollo Económico: Acciones económicas, jurídicas, sociales, comerciales, de capacitación o tecnológicas que contribuyan al progreso de las Empresas;\nIX. Ley: La Ley de Fomento a la Competitividad y Desarrollo Económico para el Estado de\nBaja California;\nX. MIPYMES: La micro, pequeña y mediana Empresa, de conformidad con la estratificación establecida por la legislación vigente y que se encuentren legalmente constituidas;\nXI. PDE: La Política de Desarrollo Empresarial del Estado;\nXII. Persona Adulta Mayor: Persona de 60 años de edad o más, que lo haga constar con los documentos públicos correspondientes;\nXIII. Persona Egresada de Albergue, Casa Hogar o Institución de Asistencia Social para Niñas, Niños y Adolescentes: Toda persona que, al cumplir su mayoría de edad, se le expida constancia de haber concluido su estancia en un albergue, casa hogar o institución de asistencia social para niña, niño y adolescente, pública o privada que se encuentre debidamente registrada ante las autoridades competentes en el Estado, susceptible de ser contratada por una empresa;\nFracción Reformada\nXIV. Persona Productiva con Discapacidad: Toda persona que, como consecuencia de una o más deficiencias físicas, psíquicas o sensoriales, congénitas o adquiridas, permanentes o temporales, independientemente de la causa que las hubiera originado, vea limitada su capacidad educativa, laboral o de integración social, y dicha limitación sea reconocida por una institución pública competente, susceptible de ser contratada por una empresa;\nLey de Fomento a la Competitividad y Página 2\nFracción Adicionada, recorriéndose las subsecuentes\nFracción Reformada\nXV. Proyecto de Inversión: La inversión privada destinada a la instalación de una nueva\nEmpresa, y de aquellos que sean destinados para el desarrollo tecnológico que generen valor agregado en productos, procesos, materiales y/o servicios, de conformidad con la siguiente clasificación:\nPárrafo de la Fracción Reformado\na) Inversión Nueva: La que se destina a la instalación de una empresa para iniciar operaciones productivas en el Estado;\nb) Derogado.\nInciso Derogado\nc) Inversión en Tecnología: Inversiones cuyo modelo de negocios se basa en el conocimiento científico y tecnológico, que destinan un porcentaje de sus ventas anuales a la investigación y/o el desarrollo experimental, y se clasifican a su vez en:\n1. Bienes de Capital: Las orientadas al diseño, procesamiento y/o manufactura de nuevos productos, servicios de alta tecnología o la implementación de procesos de producción innovadores que incrementan su capacidad, reduzcan tiempos y/o ahorren energía.\n2. Capital Humano: Las orientadas en desarrollar, atraer y lograr la permanencia del capital humano altamente calificado, capaz de realizar acciones encaminadas a la investigación y desarrollo tecnológico y científico de productos o servicios.\n3. Recursos Materiales: Todos aquellos bienes que utiliza una empresa para la consecución de sus fines.\nFracción Reformada\nXVI. Reglamento: El Reglamento de la Ley de Fomento a la Competitividad y Desarrollo\nEconómico para el Estado de Baja California;\nXVII. RETE: El Registro Estatal de Trámites Empresariales en el que se inscriben los trámites y servicios a cargo de las dependencias y entidades, sujetos a un proceso de mejora regulatoria;\nXVIII. UMA: Unidad de Medida y Actualización Vigente;\nFracción Reformada\nXIX. Secretaría: La Secretaría de Economía Sustentable y Turismo;\nFracción Reformada\nXX.- Ventanilla Única: Las oficinas de la Secretaría, para la recepción de las solicitudes de las empresas interesadas en obtener estímulos,\nXXI.- Vocaciones regionales: Los sectores productivos con potencial de crecimiento que tiene cada región del Estado, las que se identifican como:\na) Vocaciones Razonables: Actividades productivas cuya participación en el valor del producto interno bruto del Estado sobrepasa a la media nacional.\nLey de Fomento a la Competitividad y Página 3\nb) Vocaciones por Impulsar: Actividades productivas con amplio potencial de desarrollo, nacional y mayor a 1%;\nInciso Reformado\nc) Vocaciones por Incubar: Actividades productivas con amplio potencial de desarrollo y de incipiente proceso de explotación, cuya participación en el valor del producto interno bruto del\nEstado resulta igual o menor a 1%;\nInciso Reformado\nFracción Reformada\nXXII.- IEMBC: Instituto del Emprendimiento de Baja California.\nFracción Adicionada\nArtículo Reformado\nArtículo 4.- Las acciones que deriven de la presente Ley y que implementen las autoridades estatales señaladas en el artículo 2, en coordinación con el sector privado, deberán:\nI. Establecer:\na) Los lineamientos básicos de la política económica que coadyuven en la definición de estrategias y programas específicos de fomento, alineados a la PDE y orientados a fortalecer la posición competitiva del Estado;\nb) Las bases que aseguren la congruencia de las políticas estatales de fomento y desarrollo con los instrumentos vigentes a nivel federal y municipal en la materia, así como con las tendencias internacionales;\nc) Los instrumentos que aseguren la congruencia de las políticas de fomento a la competitividad y desarrollo económico, con las políticas hacendarías y financieras del Estado, y\nd) Las demás acciones que sean necesarias para el cumplimiento del objeto y fines propuestos en la Ley.\nII. Promover:\na) El desarrollo económico equilibrado, armónico y sustentable del Estado, a través de la atracción de Proyectos de Inversión y el fortalecimiento de las inversiones existentes;\nb) El impulso a la creación de Empresas regionales mediante la promoción de la cultura emprendedora;\nc) Un marco jurídico que aliente y consolide la inversión;\nd) La incorporación al mercado laboral de personas adultas mayores, Madres Solteras, Personas Productivas con Discapacidad, Personas egresadas de albergues, casa hogar o institución de asistencia social para niñas, niños y adolescentes, así como el reconocimiento de aquellas empresas que participen en los programas que para tal efecto se establezcan;\nInciso Reformado\ne) La generación de nuevas fuentes de empleo formales y la conservación de los existentes;\nLey de Fomento a la Competitividad y Página 4\nf) El desarrollo de infraestructura, servicios y demás condiciones necesarias que propicien la atracción de Proyectos de Inversión en la Entidad;\ng) La competitividad de las Empresas regionales en los mercados nacionales e internacionales;\nh) Las actividades productivas que generen mayor valor agregado en los productos y servicios de las Empresas;\ni) La reactivación económica de las zonas con menor nivel de desarrollo económico en el\nEstado, con base en los Estímulos a las personas físicas o morales que realicen inversión nueva en esas zonas;\nj) La cultura emprendedora y las oportunidades de desarrollo productivo con potencial en el Estado;\nk) La creación de esquemas de asociación e integración que fortalezcan la posición competitiva de la MIPYMES en el Estado, especialmente su encadenamiento eficiente y rentable con las grandes Empresas y con proveedores en el Estado;\nl) La articulación de los programas, instrumentos, productos, herramientas y acciones para elevar la competitividad de las Empresas;\nm) La mejora regulatoria, para crear un entorno altamente favorable y competitivo para impulsar las actividades económicas;\nn) La participación de las Empresas en eventos nacionales e internacionales que permitan difundir las oportunidades de negocio e inversión que ofrece el Estado; ñ) El uso de tecnologías de información y de comunicación para incrementar las oportunidades de negocio de las Empresas;\no) El acceso de las Empresas al financiamiento, multiplicando los canales y productos financieros existentes y fortaleciendo la capacidad de gestión del empresario ante el sistema financiero;\np) La elaboración de programas de capacitación, investigación y desarrollo tecnológico que atiendan las necesidades específicas de las Empresas, con base en una mayor vinculación entre los sectores educativos y productivos en el Estado;\nq) La coordinación de acciones entre la Administración Pública Federal, Estatal y\nMunicipal, con el sector privado, para impulsar el desarrollo empresarial en sus diversas manifestaciones;\nr) La utilización de tecnología limpia que incluya equipos, dispositivos, mecanismos, técnicas o sistemas, que aplicados a una fuente o proceso generador de contaminantes, reduzcan, minimicen o eliminen, su grado de peligrosidad y contaminación, con otras tecnologías usuales;\ns) La preservación y restauración del equilibrio ecológico, así como la prevención del deterioro ambiental, de manera que sea compatible la obtención de beneficios económicos y las actividades de la sociedad, con la preservación de los ecosistemas; y, Ley de Fomento a la Competitividad y Página 5\nt) El fortalecimiento a las microempresas de reciente creación, a través de la gestión de apoyos y estímulos que las consoliden; y,\nu) Las demás acciones que sean necesarias para el cumplimiento del objeto y fines propuestos en la Ley.\nFracción Reformada\nArtículo Reformado\nArtículo 5.- El Ejecutivo del Estado y los Ayuntamientos, acordarán las bases de coordinación para la realización de acciones conjuntas en materia de fomento a la competitividad y el desarrollo económico, mismas que deberán estar alineadas a la PDE, así como a los programas estatales y municipales en la materia.\nCAPÍTULO II\nDE LA POLÍTICA DE DESARROLLO EMPRESARIAL\nArtículo 6.- La PDE es el instrumento que contiene el conjunto de guías para encauzar y dar seguimiento al rumbo empresarial, con el objeto de fomentar su competitividad y desarrollo económico a través del fortalecimiento y promoción de las Vocaciones Regionales, con base en la asignación de prioridades y la generación de criterios de selectividad, para detectar y aprovechar al máximo las inversiones productivas presentes y futuras en las regiones de la Entidad. Las guías que contenga la PDE, deberán ser congruentes con los objetivos del Plan Estatal de Desarrollo.\nAsimismo, mediante la PDE se buscará preferentemente:\nI. Elevar el nivel de calidad de vida en el Estado;\nII. Garantizar el comportamiento ético en las Empresas mediante la promoción de valores;\nIII. Rediseñar la cadena de valor;\nIV. Desarrollar un encadenamiento productivo; y\nV. Incrementar el valor agregado de los productos.\nArtículo 7.- La Secretaría para asegurar el cumplimiento de la PDE, podrá auxiliarse de las siguientes instancias:\nI. El Consejo;\nII. Los organismos y cámaras empresariales y de promoción económica de cada Municipio;\nIII. Las Universidades y Centros de Investigación en el Estado;\nIV. Autoridades, empresarios y agrupaciones con representatividad y responsabilidad en el desarrollo de la planta laboral, y\nV. Las demás instituciones públicas y privadas relacionadas con la materia.\nArtículo 8.- Para la elaboración, difusión y actualización de la PDE el Comité considerará las propuestas del Consejo, determinando los mecanismos necesarios para evaluar sus avances\nLey de Fomento a la Competitividad y Página 6 conjuntamente con los sectores público y privado de cada municipio, implementando en su caso,\nCAPÍTULO III\nDE LOS ESTÍMULOS\nArtículo 9.- Los Estímulos que se otorguen conforme a las disposiciones de esta Ley serán:\nI.- No Fiscales.\na) De Gestión. Que consistirá en la intervención de la Secretaría ante instancias\nFederales, Estatales y Municipales para:\n1. Coadyuvar en la gestión de trámites para la constitución, establecimiento y funcionamiento de actividades empresariales, y\n2. La obtención de asesoría para la solución de las problemáticas que inhiben la competitividad de las Empresas y afecten su operación.\nb) De Desarrollo Empresarial. Que consistirá en apoyos directos a las MIPYMES a través de los programas de fomento enfocados a la:\n1. Formación de emprendedores;\n2. Capacitación y adiestramiento;\n3. Consultoría especializada;\n4. Acceso al financiamiento;\n5. Articulación de los programas, instrumentos, productos, herramientas y acciones para elevar su competitividad;\nNumeral Reformado\n6. Información estadística, sectorial y económica para la toma de decisiones; y, Numeral Reformado\n7. Asesoría y orientación en los actos y trámites para la regularización de las empresas, conforme a los programas de regularización de empresas que para ello emita el Ejecutivo del\nEstado.\nNumeral Adicionado\nInciso Reformado\nc) De Acceso a Mercados. Que consistirá en la intervención de la Secretaría en coordinación con las instancias competentes, para estimular la participación de Empresas, especialmente de MIPYMES, en los mercados externos, mediante las siguientes acciones:\n1. Apoyar mediante asistencia técnica a las Empresas que cuenten con potencial exportador;\n2. Apoyar la participación de Empresas en ferias y eventos nacionales e internacionales para promocionar productos, y\nLey de Fomento a la Competitividad y Página 7\n3. Establecer programas específicos por sectores y grupos de Empresas para promover exportaciones.\nd) De Infraestructura Pública. Que consistirá en la canalización de recursos del\nFOINFRA, para el apoyo en la realización de obras de infraestructura pública que faciliten el establecimiento y funcionamiento de las Empresas.\nFracción Reformada\nII.- Fiscales. Los previstos en las disposiciones fiscales aplicables.\nArtículo Reformado\nCAPÍTULO IV\nDE LAS ACTIVIDADES OBJETO DE ESTÍMULOS\nArtículo 10.- Podrán ser objeto de Estímulos fiscales en los términos de las disposiciones aplicables, las Empresas que:\nI. Realicen un Proyecto de Inversión;\nII. Operen sistemas para el tratamiento de aguas residuales y las reutilicen totalmente, siempre que su descarga final no se realice en el sistema de alcantarillado; o,\nIII. Contraten Personas Adultas Mayores, Madres Solteras, Personas Productivas con\nDiscapacidad y/o Personas egresadas de albergues, casa hogar o institución de asistencia social para niñas, niños y adolescentes.\nFracción Reformada\nIV.- Implementen proyectos de consumo y uso de energías renovables no contaminantes, aplicadas al consumo de energía proveniente de fuentes renovables no contaminantes, desarrollo de auditorías de eficiencia energética, así como las demás relacionadas con este tipo de proyectos; y\nV. Tengan contratados de 1 a 10 empleados.\nArtículo Reformado\nArtículo 11.- Adicionalmente, podrán ser objeto de los Estímulos no fiscales, las MIPYMES y Empresas que:\nI. Requieran orientación para realizar trámites ante los diversos órdenes de gobierno;\nII. Inviertan en la capacitación de recursos humanos y que se vinculen con las instituciones educativas públicas o privadas alineadas a la PDE;\nIII. Se integren a Cadenas Productivas, agrupamientos empresariales y/o a los programas y lineamientos que establezca la Secretaría para mejorar su productividad y competitividad;\nIV. Contribuyan al avance de la calidad en los procesos de producción, distribución, mercadeo y servicio al cliente y que promuevan la cultura de la calidad en el Estado;\nV. Inviertan y/o participen en programas destinados a impulsar el desarrollo de proveedores ubicados en el Estado;\nLey de Fomento a la Competitividad y Página 8\nVI. Promuevan e inviertan en esquemas y programas de investigación para modernizar y desarrollar tecnología;\nVII. Sustituyan importaciones mediante el consumo de insumos, componentes, servicios o productos que se generen en el Estado;\nVIII. Sean identificadas con posibilidades de participar exitosamente en los mercados de exportación, incluyendo aquellas que en forma complementaria importen insumos indirectamente para la producción de bienes en el Estado;\nIX. Sean identificadas como estratégicas o necesitadas de apoyos especiales, incluyendo obras de infraestructura; y,\nX. Inviertan en proyectos que contribuyan al mejoramiento y conservación del medio ambiente, así como en sistemas de eficiencia energética a través de la implementación de fuentes de energía renovable no contaminante.\nArtículo Reformado\nCAPÍTULO V\nDE LOS ESTÍMULOS FISCALES A LOS\nPROYECTOS DE INVERSIÓN\nArtículo 12.- Los Estímulos fiscales a los Proyectos de Inversión, se orientarán al impuesto sobre remuneraciones al trabajo personal y a los derechos de conexión al sistema de agua potable y alcantarillado sanitario, sin perjuicio de que dichos Estímulos puedan comprender otras contribuciones, según se establezca en las disposiciones fiscales de carácter estatal.\nArtículo 13.- Para el otorgamiento de los Estímulos fiscales a que se refiere el artículo anterior se observarán los términos, porcentajes y períodos previstos en las disposiciones fiscales aplicables, así como los siguientes rubros y esquemas de puntuación:\nI. Generación de Empleos\nEsquema 1. Número de empleos directos a generar, a partir de la implementación del\nProyecto de Inversión:\n1 punto\n3 puntos\nc) De 51 a 250 empleos\n6 puntos\nd) De 251 a 500 empleos\n9 puntos\nLey de Fomento a la Competitividad y Página 9\ne) Más de 500 empleos 12 puntos\nEsquema 2. Número de empleos indirectos a generar por Empresas nuevas que se establezcan en el Estado, como consecuencia directa del Proyecto de Inversión:\n1 punto\nb) De 51 a 250 empleos\n2 puntos\nc) De 251 a 500 empleos\n3 puntos\nd) De 501 a 750 empleos\n4 puntos\ne) Más de 750 empleos\n5 puntos\nEsquema 3. Estudiantes de carreras técnicas y de ingeniería de instituciones técnicas o de educación superior, licenciatura afines de administración de empresas con autorización o reconocimiento de validez oficial de estudios, integrados en los procesos de producción de la\nEmpresa, en virtud del instrumento escrito que revista formalidad y corresponsabilidad entre la empresa y la institución:\n2 puntos\n3 puntos\nc) Más de 15 a 25 estudiantes\n4 puntos\nd) Mas de 25 estudiantes\n5 puntos\nEsquema 4. Contratación de Personas Adultas Mayores, Madres Solteras, Personas\nProductivas con Discapacidad y/o Personas egresadas de albergue, casa hogar o institución de asistencia social para niñas, niños y adolescentes, que representen:\nPárrafo Reformado\nLey de Fomento a la Competitividad y Página 10\na) Al menos el 5% del total del personal\n1 puntos\nb) Entre 6 y 10% del total del personal\n2 puntos\nc) Más del 10% del total del personal\n6 puntos\nEsquema Reformado\nEsquema 5. Derogado\nEsquema Derogado\nFracción Reformada\nII. Nivel Salarial de los Nuevos Empleos\nEsquema 1. De 11 a 50 empleos directos a generar con un sueldo promedio diario de:\na) Entre 3 y 5 UMA\n1 punto\nInciso Reformado\nb) Entre 6 y 7 UMA\n2 puntos\nInciso Reformado\nc) Entre 8 y 10 UMA 3 puntos\nInciso Reformado\nd) Entre 11 y 15 UMA\n4 puntos\nInciso Reformado\ne) Más de 15 UMA\n5 puntos\nInciso Reformado\nEsquema 2. De 51 a 250 empleos directos a generar con un sueldo promedio diario de:\na) Entre 3 y 5 UMA\n2 puntos\nInciso Reformado\nb) Entre 6 y 7 UMA 4 puntos\nInciso Reformado\nLey de Fomento a la Competitividad y Página 11\n6 puntos\nc) Entre 8 y 10 UMA\nInciso Reformado\nd) Entre 11 y 15 UMA 8 puntos\nInciso Reformado\ne) Más de 15 UMA\n10 puntos\nInciso Reformado\nEsquema 3. Más de 250 empleos directos a generar con un sueldo promedio diario de:\na) Entre 3 y 5 UMA 3 puntos\nInciso Reformado\nb) Entre 6 y 7 UMA 6 puntos\nInciso Reformado\nc) Entre 8 y 10 UMA 9 puntos\nInciso Reformado\nd) Entre 11 y 15 UMA 12 puntos\nInciso Reformado\ne) Más de 15 UMA 15 puntos\nInciso Reformado\nFracción Reformada\nIII. Monto y Origen de la Inversión\nEsquema 1. Inversión Nueva, cuyo monto en moneda nacional sea equivalente a:\nPárrafo Reformado\na) 250 mil dólares o menos 1 punto\nb) Más de 250 mil y hasta 1 millón de dólares\n2 puntos\nc) Más de 1 y hasta 5 millones de dólares\n4 puntos\nLey de Fomento a la Competitividad y Página 12\nd) Más de 5 y hasta 50 millones de dólares\n6 puntos\ne) Más de 50 y hasta 100 millones de dólares\n8 puntos\nf) Más de 100 millones de dólares\n10 puntos\nEsquema 2. Cuando el origen de la inversión sea:\na) 100 % extranjera 2 puntos\nb) Mayor del 50 % extranjera pero menor al 4 puntos porcentaje señalado en el inciso anterior\nc) 50 % extranjera y 50 % nacional o local 5 puntos\nd) Mayor del 50 % nacional o local 6 puntos\ne) 100 % Local 7 puntos\nPara efectos de esta fracción, se entenderá por dólares la moneda de los Estados Unidos de América. Su equivalencia en Moneda Nacional, se determinará conforme al tipo de cambio vigente al momento de presentar la solicitud de Estímulos fiscales.\nFracción Reformada\nIV. Inversión en Tecnología\nEsquema 1. Cuando su monto represente por lo menos:\na) 1.0% del valor de sus ventas anuales. 3 puntos\nb) 2.5% del valor de sus ventas anuales 5 puntos\nc) 5.0% del valor de sus ventas anuales 7 puntos\nd) 7.0% del valor de sus ventas anuales 8 puntos\ne) 10% del valor de sus ventas anuales 10 puntos\nLey de Fomento a la Competitividad y Página 13\nV. Proveeduría\nEsquema 1. La adquisición de insumos a Empresas instaladas en el Estado y/o el país, incluyendo aquellas que incorporen a sus procesos, productos fabricados en el estado cuando:\na) Entre 10 y 25% del valor de sus adquisiciones 3 puntos se efectúen en el Estado, en otras entidades federativas del país o en la Ciudad de México.\nb) Entre 26 y 50% del valor de sus adquisiciones 5 puntos se efectúen en el Estado, en otras entidades federativas del país o en la Ciudad de México.\nc) Más del 51% del valor de sus adquisiciones se 6 puntos efectúen en el Estado, en otras entidades federativas del país o en la Ciudad de México.\nd) Entre 75 y 90% del valor de sus adquisiciones 7 puntos se efectúen en el Estado\ne) Más de 90% del valor de sus adquisiciones se 8 puntos efectúen en el Estado\nEn este rubro, se excluye la compra de energía eléctrica, agua, gas, telecomunicaciones y combustóleo.\nVI. Diversificación de Mercados\nEsquema 1. Las Empresas que a través de procesos de elaboración, producción, transformación, reparación o industrialización, generen productos cuya distribución en mercados distintos al Estatal representen en su producción total anual:\na) Entre 10 y 33%, en mercados del país o 2 puntos extranjeros\nb) Más del 33 y hasta 66%, en mercados del 3 puntos país\nLey de Fomento a la Competitividad y Página 14\nc) Más del 33 y hasta 66%, en mercados 4 puntos extranjeros\nd) Más del 66%, en mercados del país 5 puntos\ne) Más del 66%, en mercados extranjeros 6 puntos\nVII.- Prestaciones Laborales\nEsquema 1.- Por la prestación de beneficios laborales otorgados por la misma empresa sin costo alguno para el trabajador:\na) Por servicio de comedor 1 punto\nb) Por servicio de transporte público o privado 1 punto\nc) Por servicio de guardería 1 punto\nVIII. Empleo de Tecnología Limpia en el Proceso Productivo.\nEsquema 1. Por implementar programas que les permitan reciclar cuando menos el 50% de los residuos que resulten de sus procesos productivos, 2 puntos.\nIX. Implementación de Fuentes de Energías Renovables No Contaminantes.\nEsquema 1.- Por el ahorro total del consumo de energía.\na).- Más del 60% en ahorro de energía. 8 Puntos\nb).- Entre 51 y 60% en ahorro de energía. 6 Puntos\nc).- Entre 31 y 50% en ahorro de energía. 4 Puntos\nd).- Entre 21 y 30% en ahorro de energía. 2 Puntos\ne).- Entre 10 y 20% en ahorro de energía. 1 Punto\nLey de Fomento a la Competitividad y Página 15\nLa Comisión Estatal de Energía, coadyuvará con la Secretaría de Economía Sustentable y\nEnergía.\nPárrafo Reformado\nEl plazo para que la Empresa cumpla con los supuestos previstos en las fracciones I, II y\nIII, será de 2 años, contado a partir de que se determine la procedencia de la solicitud de\nEstímulos fiscales.\nEl período para tomar como referencia el promedio de los conceptos previstos en las fracciones IV, V y VI, será de un año, contado a partir de que la Empresa empiece a recibir el\nEstímulo fiscal.\nPara efectos de este artículo en ningún caso se podrá acumular la puntuación prevista en dos o más incisos de un mismo esquema.\nLa empresa que presente un proyecto de inversión para establecerlo fuera de la cabecera municipal, obtendrá 15 puntos adicionales de los que pudiera obtener por los rubros comprendidos de la fracción I a la VI, del presente artículo.\nArtículo Reformado\nCAPÍTULO VI\nDE LA OBTENCIÓN Y EXTINCIÓN DE LOS ESTÍMULOS\nArtículo 14.- Las Empresas interesadas en obtener los Estímulos previstos en esta Ley, deberán presentar la solicitud con los requisitos que se establezcan en el Reglamento, ante la ventanilla única que se establezca para tal efecto.\nArtículo 15.- La Secretaría contará con un plazo máximo de 20 días hábiles para determinar en su caso, la procedencia de la solicitud de Estímulos no fiscales, contados a partir de que la referida solicitud se encuentre debidamente requisitada.\nLa Secretaría de Hacienda, resolverá las solicitudes de Estímulos fiscales conforme a lo previsto en las disposiciones fiscales aplicables.\nPárrafo Reformado\nArtículo Reformado\nArtículo 16.- En cualquier tiempo, la Secretaría y/o la Secretaría de Hacienda, podrán particulares que sirvieron de base para el otorgamiento de los Estímulos.\nPárrafo Reformado\nPara los efectos del párrafo anterior, la Secretaría y/o la Secretaría de Hacienda, podrán auxiliarse de las demás Dependencias del Estado y Entidades Paraestatales.\nPárrafo Reformado\nLey de Fomento a la Competitividad y Página 16\nLas Empresas estarán obligadas a presentar la información que le sea requerida, en un término no mayor a 5 días hábiles, contados a partir de dicho requerimiento. Asimismo estarán caso.\nArtículo Reformado\nArtículo 17.- Los Estímulos quedarán sin efectos en los siguientes casos:\nI. Cuando cumplan el término de su vigencia;\nII. Cuando la Empresa deje de situarse dentro de los supuestos previstos por las disposiciones que sirvieron de sustento para su otorgamiento;\nIII. Cuando el interesado renuncie a los mismos de manera expresa y por escrito, o\nIV. Por cancelación.\nArtículo 18.- Procede la cancelación de los Estímulos, cuando la Empresa:\nI. Aporte información falsa para su obtención;\nII. Suspenda sus actividades durante seis meses sin causa justificada;\nIII. Los destine a una finalidad diversa para la que se le otorgaron;\nIV. Incumpla los requisitos y las condiciones generales y particulares que sirvieron de base para su otorgamiento;\nV. No se encuentre al corriente de sus obligaciones fiscales.\nVI. Los transfiera por cualquier medio; o\nVII. Simule acciones para hacerse acreedor a los mismos.\nCuando se cancele un Estímulo fiscal, se procederá a la determinación y cobro íntegro de la diferencia de las contribuciones que correspondan a partir de la fecha en que se presente la causa que dio origen a la cancelación, incluyendo sus accesorios, en los términos de las disposiciones aplicables.\nArtículo 19.- La cancelación de Estímulos se sujetará a lo siguiente:\nI. Se notificará a la Empresa el inicio del procedimiento de cancelación y la causa que motiva el mismo;\nII. La Empresa contará con 5 días hábiles para manifestar lo que a su derecho convenga, aportando en su caso los elementos que estime pertinentes, los cuales deberán estar relacionados con el hecho que se pretende probar; y\nIII. Transcurrido dicho plazo, la autoridad que otorgó el Estímulo resolverá lo conducente.\nCAPÍTULO VII\nDEL FOINFRA\nLey de Fomento a la Competitividad y Página 17\nArtículo 20.- El FOINFRA tendrá como objeto la canalización de recursos para apoyar la\nInversión.\nArtículo 21.- El FOINFRA se integrará con los recursos que para tal efecto se determinen correspondiente.\nPara la aplicación de los recursos que integran el FOINFRA, se deberá sujetar a lo previsto en la Ley de Presupuesto y Ejercicio del Gasto Público del Estado de Baja California y demás disposiciones legales aplicables.\nArtículo Reformado\nArtículo 22.- Para el funcionamiento del FOINFRA, el Comité establecerá las reglas de operación, procurando impactar en los 5 municipios del Estado, así como el mayor rendimiento de los recursos disponibles a través de la mezcla de recursos con otras instancias.\nArtículo Reformado\nCAPÍTULO VII BIS\nDEL FONDO DE FOMENTO PARA EL DESARROLLO ECONÓMICO\nDE MUJERES Y JÓVENES\nArtículo 22 BIS.- El Poder Ejecutivo del Estado en término de las disposiciones que resulten aplicables, creará un Fondo de Fomento para el Desarrollo Económico que tendrá por objeto financiar proyectos de inversión emprendidos por jóvenes y mujeres, principalmente, por madres solteras, mediante el otorgamiento de microcréditos.\nArtículo Reformado\nArtículo 22 TER.- El Fondo de Fomento para el Desarrollo Económico de Mujeres y\nJóvenes, contará con el patrimonio que se establezca en su instrumento de creación.\nSe buscará que el Fondo de Fomento para el Desarrollo Económico de Mujeres y Jóvenes, sea autosuficiente a partir de la inversión y reinversión de sus recursos.\nArtículo Reformado\nArtículo 22 QUARTER.- Los requisitos, montos, el procedimiento para el otorgamiento de\nDesarrollo Económico de Mujeres y Jóvenes, se establecerán en su instrumento de creación.\nArtículo Reformado\nCAPÍTULO VIII\nDE LA MEJORA REGULATORIA\nArtículo 23.- La mejora regulatoria es un proceso corresponsable de las Dependencias del\nEstado y Entidades Paraestatales, así como de los Ayuntamientos y del sector privado, que tiene como fin impulsar la simplificación, desregulación, perfeccionamiento, eficacia y modernización de\nLey de Fomento a la Competitividad y Página 18 las leyes, reglamentos, procedimientos y demás disposiciones que impacten la actividad empresarial, así como la atracción y realización de Proyectos de Inversión.\nArtículo 24.- El Comité se apoyará en un órgano de trabajo para la formulación de las propuestas en materia de mejora regulatoria, mismas que buscarán reducir los tiempos o costos derivados de las disposiciones a que se refiere el artículo anterior.\nArtículo 25.- El órgano de trabajo estará integrado por:\nI. Un representante de la Secretaría;\nII. Un representante de la Secretaría de Planeación y Finanzas;\nIII. El Secretario Técnico del Comité, y\nIV. Un representante designado de común acuerdo por los Consejos Coordinadores\nEmpresariales Municipales.\nArtículo 26.- El órgano de trabajo en la formulación de las propuestas que turne para aprobación del Comité, deberá considerar por lo menos el impacto que pueden tener en:\na) La creación o modificación de derechos, prestaciones y obligaciones para los particulares;\nb) El establecimiento de nuevos trámites, y\nc) La modificación de los trámites existentes.\nArtículo 27.- El órgano de trabajo, tendrá por lo menos las siguientes atribuciones:\nI. Analizar las leyes, reglamentos, procedimientos y demás disposiciones que impacten la actividad empresarial, así como la atracción y realización de Proyectos de Inversión la normatividad\nII. Formular propuestas de mejora regulatoria;\nIII. Someter a la aprobación del Comité las propuestas;\nIV. Elaborar los proyectos, que en materia de mejora regulatoria, le encomiende el Comité,\nV. Las demás que le otorgue el Comité.\nArtículo 28.- Las propuestas que emita el órgano de trabajo en materia de mejora regulatoria, contendrán por lo menos lo siguiente:\nI. La descripción del asunto turnado;\nII. Análisis de la propuesta, incluyendo los instrumentos y/o razonamientos que sirvan de fundamentación y motivación; y,\nIII. El sentido del dictamen.\nLey de Fomento a la Competitividad y Página 19\nArtículo 29.- Las propuestas aprobadas por el Comité, serán remitidas como proyectos a las autoridades correspondientes, a efecto de que determinen su viabilidad y procedencia jurídica, para en su caso impulsar su implementación.\nArtículo 30.- Las Dependencias del Estado y Entidades Paraestatales cuyas atribuciones\nInversión, instruirán a un servidor público con nivel mínimo de Director o su equivalente, como responsable de analizar los proyectos a que se refiere el artículo anterior. Esto, sin perjuicio de las acciones que dentro de su ámbito competencial deban realizar en materia de mejora regulatoria.\nCAPÍTULO IX\nDEL COMITÉ\nArtículo 31.- El Comité es un órgano consultivo en materia de fomento a la competitividad, desarrollo económico, mejora regulatoria, estímulos y encargado de la PDE, contando para tal efecto con las atribuciones a que se refiere la presente Ley.\nArtículo Reformado\nArtículo 32.- El Comité se integrará con:\nI. Un Presidente que será el Titular de la Secretaría;\nII. Un Secretario, que será nombrado por el Titular de la Secretaría, y\nIII. Los siguientes vocales:\na) El Titular de la Secretaría de Hacienda;\nInciso Reformado\nb) El Titular de la Secretaría del Trabajo y Previsión Social;\nc) El Titular de la Secretaría de Integración y Bienestar Social;\nInciso Reformado\nd) El Presidente del Ayuntamiento de cada Municipio;\ne) El Presidente del Consejo Coordinador Empresarial, de cada Municipio;\nf) El Presidente del Consejo; y\ng) Dos representantes de las instituciones de educación superior, uno del sector público y otro del privado, designados por el titular de la Secretaría, de entre las propuestas que las mismas le presenten.\nFracción Reformada\nCuando así se considere necesario, el Presidente podrá invitar a aquellas personas o autoridades relacionadas con alguno de los asuntos comprendidos en el orden del día, para que participen en las sesiones con derecho voz, pero sin voto.\nArtículo Reformado\nLey de Fomento a la Competitividad y Página 20\nArtículo 33.- Los cargos de los integrantes del Comité serán honoríficos, por lo que no percibirán retribución, emolumento o compensación alguna por su desempeño. Reforma\nLos vocales previstos en la fracción III, incisos e), f) y g), del artículo anterior, desempeñaran dicha función hasta en tanto no sea designado un nuevo representante.\nArtículo 34.- Los integrantes del Comité designarán por escrito a un suplente con funciones de propietario para que cubra sus ausencias temporales. La designación del suplente, siempre deberá recaer en una misma persona.\nArtículo 35.- Para el debido cumplimiento de sus funciones, el Comité contará con un secretario técnico, que será nombrado y removido libremente por el Presidente.\nEl secretario técnico no será tomado en cuenta para efectos del quórum, pero podrá participar en las sesiones del Comité con derecho a voz pero sin voto.\nArtículo 36.- El Comité celebrará sesiones ordinarias por lo menos una vez cada 2 meses, y de manera extraordinaria, cuando así lo determine el Presidente, o la mayoría de sus integrantes.\nArtículo 37.- Para que las sesiones del Comité sean válidas, será necesaria la asistencia de cuando menos la mitad más uno de sus integrantes si se trata de primera convocatoria. Las decisiones del Comité se tomarán por mayoría de votos y en caso de empate, el Presidente tendrá voto de calidad.\nLa elaboración de las convocatorias, se realizará en los términos que establezca el\nReglamento.\nArtículo 38.- Las convocatorias para las sesiones podrán notificarse personalmente o bien mediante oficio, fax o correo electrónico, dejando constancia del mismo y del resultado de la notificación.\nArtículo 39.- La organización y demás normas de funcionamiento del Comité, se sujetarán a las disposiciones previstas en el Reglamento.\nArtículo 40.- El Comité tendrá las siguientes atribuciones:\nI. Elaborar, actualizar y difundir la PDE, así como los demás asuntos relacionados con la misma;\nII. Analizar y opinar las solicitudes que en su caso le turne la Secretaría o la Secretaría de\nHacienda según corresponda, para la obtención de Estímulos señalados en la Ley;\nFracción Reformada\nIII. Impulsar la simplificación, desregulación, perfeccionamiento, eficacia y modernización del marco jurídico estatal y municipal que impacte la actividad empresarial, así como la atracción y realización de Proyectos de Inversión;\nLey de Fomento a la Competitividad y Página 21\nIV. Crear el órgano de trabajo en materia de mejora regulatoria;\nV. Aprobar las propuestas que le turne el órgano de trabajo en materia de mejora regulatoria;\nVI. Definir la información que quedará inscrita en el RETE, así como el procedimiento para su publicación y actualización, promoviendo que las autoridades municipales cuenten con un instrumento similar;\nVII. Promover el uso de tecnologías de la información para la difusión y gestión de trámites empresariales;\nVIII. Fomentar y favorecer la celebración de acuerdos interinstitucionales en materia de mejora regulatoria, así como convenios y demás actos jurídicos necesarios para cumplir sus objetivos;\nIX. Promover, organizar y participar en foros, seminarios y demás actividades orientadas a impulsar el proceso de mejora regulatoria en el Estado;\nFracción Reformada\nX. Estudiar, proponer y evaluar en el ámbito estatal, regional y municipal, medidas de apoyo para el desarrollo de la competitividad de las cadenas productivas y de las MIPYMES a través del análisis de las propuestas surgidas del sector público y de los Sectores privado, social y del conocimiento;\nFracción Reformada\nXI.- Desarrollará el objeto y funciones establecidas al Consejo Estatal para el Desarrollo de la Competitividad de la Micro, Pequeña y Mediana Empresa, previsto en el Capítulo Quinto de la\nLey para el Desarrollo de la Competitividad de la Micro, Pequeña y Mediana Empresa; y,\nFracción Adicionada, recorriéndose la subsecuente\nXII.- Las demás que establezca el Reglamento y otras disposiciones aplicables.\nSin perjuicio de lo anterior, el Comité podrá crear órganos de trabajo para auxiliarse en el cumplimiento de sus atribuciones. El Reglamento establecerá la organización y funcionamiento de los órganos de trabajo del Comité.\nArtículo Reformado\nArtículo 41.- El Comité elaborará y llevará el control del RETE, que compilará y\nDependencias del Estado y Entidades Paraestatales; que de manera enunciativa y no limitativa contendrá la siguiente información:\nI. Nombre del trámite o servicio;\nII. Fundamentación jurídica y fecha de inicio de su vigencia;\nIII. Casos en los que debe o puede realizar el trámite o solicitar el servicio;\nIV. Requisitos para el trámite o prestación del servicio;\nLey de Fomento a la Competitividad y Página 22\nV. Indicación de que el trámite debe iniciarse o el servicio solicitarse mediante escrito simple o formato oficial; servicio;\nVII. Plazos de la autoridad responsable para resolver el trámite o la solicitud del servicio;\nVIII. Monto de los derechos, contribuciones, cuotas, tarifas, aprovechamientos y demás cobros aplicables, así como su fundamento jurídico;\nIX. Seguimiento de los permisos, licencias, autorizaciones, registros y demás resoluciones que se emitan, así como la duración del servicio;\nX. Criterios y procedimientos para resolver el trámite o prestar el servicio;\nXI. Unidades administrativas ante las que se puede iniciar el trámite o solicitar el servicio;\nXII. Horario de atención al público;\nXIII. Dirección, números de teléfono y correo electrónico en caso de que la autoridad que preste servicio lo estime necesario; y,\nXIV. La demás información que se prevea en el Reglamento o que la Dependencia del\nEstado o Entidad Paraestatal considere que pueda ser de utilidad para los interesados.\nArtículo 42.- La veracidad del contenido de la información que se remita al Comité para su inscripción y publicación en el RETE, corresponde a las Dependencias del Estado y Entidades\nParaestatales que correspondan.\nCAPÍTULO X\nDEL FOMENTO A LA COMPETITIVIDAD Y\nEL DESARROLLO ECONÓMICO EN EL ÁMBITO MUNICIPAL\nDenominación Modificada\nArtículo 43.- La Secretaría formulará la política de desarrollo para la competitividad de las\nMIPYMES, tomando en cuenta la participación de los sectores privado, social y del conocimiento, y considerando los objetivos y políticas del Consejo Nacional para la Competitividad de la Micro, Pequeña y Mediana Empresa.\nArtículo Reformado\nArtículo 44.- Para la planeación y ejecución de la política de desarrollo para la competitividad de las MIPYMES, la Secretaría en coordinación con las entidades y dependencias estatales que corresponda, deberá atender los siguientes criterios:\nI. Propiciar la participación y toma de decisiones de los Municipios y respetar los lineamientos de la política nacional en la materia;\nLey de Fomento a la Competitividad y Página 23\nII. Procurar esquemas de apoyo a las MIPYMES a través de la concurrencia de recursos de la Federación, del Estado y de los Municipios, así como de los sectores privado, social y del conocimiento;\nIII. Enfocar los esfuerzos de acuerdo con las necesidades, el potencial y las vocaciones regionales y municipales;\nIV. Contener objetivos a corto, mediano y largo plazo;\nV. Contener propuestas de mejora y simplificación normativa en materia de desarrollo y apoyo a las MIPYMES;\nVI. Enfocar estrategias y proyectos de modernización, innovación y desarrollo tecnológico para las MIPYMES;\nVII. Propiciar nuevos instrumentos de apoyo a las MIPYMES considerando las tendencias internacionales y el comportamiento de las entidades federativas;\nFracción Reformada\nVIII. Contar con mecanismos de medición de avances para evaluar el impacto de las políticas de apoyo a las MIPYMES; y,\nFracción Reformada\nIX. Promover que las dependencias y entidades de la Administración Pública Estatal realicen la planeación de sus adquisiciones de bienes, contratación de servicios y realización de obra pública para destinarlas a las MIPYMES de manera gradual, hasta alcanzar un mínimo del\n35%, conforme a la reglamentación aplicable.\nFracción Adicionada\nArtículo Reformado\nArtículo 45.- Para la ejecución de la política y las acciones contenidas en el artículo anterior, deberá considerarse que los programas sectoriales en materia de fomento a la competitividad y desarrollo económico, contemplen lo siguiente:\nI. La definición de los sectores prioritarios para el desarrollo económico;\nII. Las líneas estratégicas para el desarrollo empresarial;\nIII. Los mecanismos y esquemas mediante los cuales se ejecutarán las líneas estratégicas;\nIV. Los criterios, mecanismos y procedimientos para dar seguimiento, a la evolución y desempeño de las MIPYMES;\nV. Las medidas para procurar un entorno favorable para la creación, desarrollo y crecimiento con calidad de las MIPYMES considerando las necesidades, el potencial y vocación de cada región;\nLey de Fomento a la Competitividad y Página 24\nVI. Los mecanismos para evaluar de manera conjunta con la Federación y los Municipios, los resultados de los convenios de coordinación para formular nuevas acciones.\nVII. La homologación de la normativa y trámites en la materia;\nVIII. El desarrollo de un sistema de información y consulta para la planeación sobre los sectores productivos y cadenas productivas; y\nIX. Los apoyos y estímulos previstos en los artículos 9 incisos b) y c) y 11 de esta Ley.\nArtículo Adicionado\nArtículo 46.- Siempre que las condiciones económicas del Estado lo permitan, en el\nPresupuesto de Egresos del Estado se destinarán apoyos económicos a las MIPYMES, procurando que los mismos no sean inferiores, en términos reales, a los previstos en el presupuesto autorizado en el ejercicio fiscal anterior.\nArtículo Adicionado\nCAPÍTULO XI\nDEL FOMENTO A LA COMPETITIVIDAD Y\nEL DESARROLLO ECONÓMICO EN EL ÁMBITO MUNICIPAL\nCapítulo Adicionado\nArtículo 47.- Los Ayuntamientos en el ámbito de sus competencias, dictarán la normatividad que deberá regir esta materia, señalando de conformidad con las siguientes bases:\nI. Las autoridades responsables, régimen de actuación y los procedimientos para fomentar la competitividad y el desarrollo económico en el municipio;\nII. Las disposiciones en materia de mejora regulatoria y autoridades responsables de la misma;\nIII. En su caso, los esquemas necesarios para estimular e incentivar a las Empresas, y las autoridades u organismos facultados para gestionarlos, otorgando los Estímulos que procedan, de conformidad con las actividades sujetas a fomento económico, según lo determine dicho orden de\nGobierno;\nIV. Las medidas para una promoción coordinada de las acciones de fomento para la competitividad de las MIPYMES, desarrollando las propuestas y la concurrencia de programas y proyectos que consideren las necesidades, el potencial y las vocaciones regionales en el ámbito municipal;\nV. Los medios de defensa que los particulares podrán hacer valer contra sus resoluciones y el procedimiento a observar; y\nVI. Las demás disposiciones que consideren necesarias para lograr el cumplimiento del objeto de la Ley.\nArtículo Adicionado\nCAPÍTULO XII\nDEL RECURSO\nCapítulo Adicionado\nLey de Fomento a la Competitividad y Página 25\nArtículo 48.- Los afectados por la cancelación de un Estímulo no fiscal u otros actos definitivos derivados de la aplicación de la presente Ley, diversos de los relacionados con los\nEstímulos fiscales, podrán interponer el recurso de revocación previsto en la Ley del\nProcedimiento para los Actos de la Administración Pública del Estado de Baja California.\nLos actos relacionados con los estímulos fiscales, podrán ser combatidos a través de los medios de defensa previstos en las disposiciones fiscales aplicables.\nArtículo Adicionado\nCAPÍTULO XIII\nDEL INSTITUTO DEL EMPRENDIMIENTO DE BAJA CALIFORNIA\nCapítulo Adicionado\nArtículo 49.- El Instituto del Emprendimiento de Baja California, IEMBC, es una plataforma de la administración pública centralizada perteneciente a la Secretaría de Economía e Innovación, con el propósito instrumentar una Política de Emprendimiento para Baja California, mismo que deberá diseñar, ejecutar y coordinar programas que fomenten la productividad empresarial, así como de apoyo incluyente a personas emprendedoras y MIPYMES en el Estado, impulsando su diseño, formalización, innovación, competitividad y proyección en los mercados estatales, nacionales e internacionales para aumentar su contribución al desarrollo económico y bienestar social.\nPara el desarrollo de proyectos de emprendimiento, el IEMBC operará con una ventanilla de atención ciudadana a través de la plataforma digital que para tal efecto se establezca.\nEl IEMBC promoverá la integración de una red de instituciones y organizaciones de fomento al emprendimiento como un espacio plural de expresión para la ciudadanía que apoya a las personas emprendedoras.\nArtículo Adicionado\nArtículo 50.- Para el cumplimiento de su objeto, y conforme a lo señalado en el\nReglamento Interno de la Secretaría, el IEMBC tendrá los fines siguientes:\nI. Impulsar la creación de nuevas empresas y el fortalecimiento de las que se encuentran en operación, brindando información, orientación y asesoría;\nII. Fungir como un enlace entre las personas emprendedoras y las instancias de apoyo;\nIII. Desarrollar los programas que promuevan el emprendimiento de nuevos negocios y el apoyo a los ya existentes, brindando información, orientación, asesoría mediante el uso de aplicaciones tecnológicas, así como asistencia técnica, financiamiento, enlace a instancias de apoyo, gestoría de trámites ante diversos entes públicos, fomento a integración a cadenas productivas y exportación, a red de incubadoras y aceleradoras y acceso a red de las y los mentores;\nIV. El Instituto del Emprendimiento de Baja California, podrá establecer vínculos de colaboración, a través de convenios o acuerdos de colaboración, con las dependencias\nLey de Fomento a la Competitividad y Página 26 gubernamentales, incubadoras, organismos empresariales y educativos, dedicados al fortalecimiento de los procesos de incubación y desarrollo empresarial en el Estado;\nV. Incorporar nuevas herramientas tecnológicas para el impulso y fortalecimiento de nuevas empresas y de las que ya se encuentran en funcionamiento;\nVI. Realizar, fomentar y participar en actividades que den como resultado el surgimiento de nuevas empresas y fortalezcan las que se encuentran en operación, tales como foros, cursos de capacitación, asistencia técnica, exposiciones especializadas, misiones comerciales, encuentros de negocios dentro del ámbito nacional e internacional;\nVII. Impulsar y promover políticas públicas, en favor del emprendimiento, desarrollo y fortalecimiento, con perspectiva de género, interculturalidad, juventudes e inclusión;\nVIII. Orientar a las y los nuevos emprendedores, en materia normativa, para iniciar sus proyectos, a través de acciones enfocadas a la formalidad de las actividades económicas e integración de las empresas a la economía formal;\nIX. Las demás que se establezcan en los distintos ordenamientos aplicables a esta materia.\nArtículo Adicionado\nArtículo 51.- El IEMBC funcionará con los recursos con los que cuenta la Secretaría.\nArtículo Adicionado\nArtículo 52.- El Titular de la Secretaría designará a la persona encargada de la operación del IEMBC, quien, a su vez, realizará las acciones necesarias para su implementación y quien tendrá las facultades y obligaciones previstas en las disposiciones jurídicas aplicables.\nArtículo Adicionado\nArtículo 53.- La operación del IEMBC se sujetará a las mismas disposiciones y revisiones del Órgano Interno de Control de la Secretaría.\nArtículo Adicionado\nARTÍCULO PRIMERO.- La presente Ley entrará en vigor al día siguiente de su publicación en el Periódico Oficial del Estado.\nARTÍCULO SEGUNDO.- Se abrogan la Ley de Fomento Económico para el Estado de Baja\nARTÍCULO TERCERO.- El Titular de la Secretaría deberá convocar en un plazo máximo de 30 días, a los miembros del Comité, contados a partir de la publicación de la Presente Ley, a efecto de que celebren la sesión de instalación de dicho órgano. Asimismo para tales efectos y\nLey de Fomento a la Competitividad y Página 27 dentro del referido plazo, deberá designar a los dos representantes de las instituciones de educación superior.\nARTÍCULO CUARTO.- El Ejecutivo del Estado en un término no mayor de 60 días contados a partir de la entrada en vigor de la presente Ley, deberá expedir el Reglamento.\nARTÍCULO QUINTO.- Hasta en tanto se expida el Reglamento la Secretaría y la Secretaría de Planeación y Finanzas, podrán emitir las disposiciones de carácter general que consideren necesarias para la aplicación de la Ley.\nARTÍCULO SEXTO.- Hasta en tanto se expida el Reglamento, el Comité acordará las medidas tendientes a regular su funcionamiento y el de sus órganos de trabajo.\nDADO.- En el Salón de Sesiones “Lic. Benito Juárez García” del Honorable Poder\nLegislativo, en la Ciudad de Mexicali, Baja California, a los diecinueve días del mes de mayo del año dos mil cinco.\nDIP. ABRAHAM CORREA ACEVEDO\nPRESIDENTE\n(RÚBRICA)\nDIP. GILBERTO DANIEL GONZALEZ SOLIS\nSECRETARIO\n(RÚBRICA)\nDE CONFORMIDAD CON LO DISPUESTO POR LA FRACCION I DEL ARTICULO 49 DE\nLA CONSTITUCION POLITICA DEL ESTADO, IMPRIMASE Y PUBLIQUESE.\nMEXICALI, BAJA CALIFORNIA, A LOS TRES DIAS DEL MES DE JUNIO DEL AÑO DOS\nMIL CINCO.\nGOBERNADOR DEL ESTADO\nEUGENIO ELORDUY WALTHER\n(RÚBRICA)\nSECRETARIO GENERAL DE GOBIERNO\nBERNARDO H. MARTINEZ AGUIRRE\n(RÚBRICA)\nLey de Fomento a la Competitividad y Página 28\nARTÍCULO 2.- Fue reformado por Decreto No. 40, publicado en el Periódico Oficial No. siendo Gobernadora Constitucional la C. Marina del Pilar Ávila Olmeda 2021-2027;\nARTÍCULO 3.- Fue reformado por Decreto No. 255, publicado en el Periódico Oficial No.\nGobernador Constitucional el C. José Guadalupe Osuna Millán 2007-2013; fue reformado por\nDecreto No. 409, publicado en el Periódico Oficial No. 37, de fecha 27 de agosto de 2010,\nSección II, Tomo CXVII, expedido por la H. XIX Legislatura, Siendo Gobernador Constitucional el\nC. José Guadalupe Osuna Millán 2007-2013; fue reformado por Decreto No. 151, publicado en el\nPeriódico Oficial No. 50, de fecha 10 de noviembre de 2017, Sección VI, TOMO CXXIV; expedido por la H. XXII Legislatura, siendo Gobernador constitucional el C. Francisco Arturo Vega de\nLamadrid 2013-2019; fue reformado por Decreto No. 281, publicado en el Periódico Oficial No. 55, de fecha 30 de noviembre de 2018, Tomo CXXV, Sección IV, expedido por la Honorable\nLegislatura XXII, siendo Gobernador Constitucional el C. Francisco Arturo Vega de Lamadrid\n2013-2019; fue reformado por Decreto No. 280, publicado en el Periódico Oficial No. 4, de fecha\n18 de enero de 2019, Sección II, Tomo CXXVI; expedido por la H. XXII Legislatura, siendo\nGobernador constitucional el C. Francisco Arturo Vega de Lamadrid 2013-2019; fue reformado por\nDecreto No. 40, publicado en el Periódico Oficial No. 108, de fecha 30 de diciembre de 2021, Tomo CXXVIII, expedida por la H. XXIV Legislatura, siendo Gobernadora Constitucional la C.\nMarina del Pilar Ávila Olmeda 2021-2027; fue reformado por Decreto No. 118, publicado en el\nPeriódico Oficial No. 49, de fecha 29 de julio de 2022, Tomo CXXIX, expedida por la H. XXIV\nLegislatura, siendo Gobernadora Constitucional la C. Marina del Pilar Ávila Olmeda 2021-2027; fue reformado por Decreto No. 361, publicado en el periódico oficial No. 72, Índice, de fecha 22 de diciembre de 2023, Tomo CXXX, expedido por la H. XXIV Legislatura, siendo Gobernadora\nConstitucional la C. Marina del Pilar Ávila Olmeda 2021-2027;\nARTÍCULO 4.- Fue reformado por Decreto No. 255, publicado en el Periódico Oficial No.\n39, de fecha 28 de agosto de 2009, Tomo CXVI, expedida por la H. XIX Legislatura, siendo\nGobernador Constitucional el C. José Guadalupe Osuna Millán 2007-2013; fue reformado por\nDecreto No. 409, publicado en el Periódico Oficial No. 37, de fecha 27 de agosto de 2010,\nSección II, Tomo CXVII, expedido por la H. XIX Legislatura, Siendo Gobernador Constitucional el\nC. José Guadalupe Osuna Millán 2007-2013; fue reformado por Decreto No. 151, publicado en el por la H. XXII Legislatura, siendo Gobernador constitucional el C. Francisco Arturo Vega de\nLamadrid 2013-2019; fue reformado por Decreto No. 280, publicado en el Periódico Oficial No. 4, siendo Gobernador constitucional el C. Francisco Arturo Vega de Lamadrid 2013-2019; fue reformado por Decreto No. 40, publicado en el Periódico Oficial No. 108, de fecha 30 de diciembre de 2021, Tomo CXXVIII, expedida por la H. XXIV Legislatura, siendo Gobernadora Constitucional la C. Marina del Pilar Ávila Olmeda 2021-2027;\nLey de Fomento a la Competitividad y Página 29\nARTÍCULO 9.- Fue reformado por Decreto No. 203, publicado en el Periódico Oficial No. 8, Gobernadora Constitucional la C. Marina del Pilar Ávila Olmeda 2021-2027;\nARTÍCULO 10.- Fue reformado por Decreto No. 194, publicado en el Periódico Oficial No.\nGobernador Constitucional el C. José Guadalupe Osuna Millán 2007-2013; fue reformado por\nDecreto No. 151, publicado en el Periódico Oficial No. 50, de fecha 10 de noviembre de 2017,\nSección VI, TOMO CXXIV; expedido por la H. XXII Legislatura, siendo Gobernador constitucional el C. Francisco Arturo Vega de Lamadrid 2013-2019; fue reformado por Decreto No. 280, publicado en el Periódico Oficial No. 4, de fecha 18 de enero de 2019, Sección II, Tomo CXXVI; expedido por la H. XXII Legislatura, siendo Gobernador constitucional el C. Francisco Arturo Vega de Lamadrid 2013-2019; fue reformado por Decreto No. 40, publicado en el Periódico Oficial No.\n108, de fecha 30 de diciembre de 2021, Tomo CXXVIII, expedida por la H. XXIV Legislatura, siendo Gobernadora Constitucional la C. Marina del Pilar Ávila Olmeda 2021-2027;\nARTÍCULO 11.- Fue reformado por Decreto No. 194, publicado en el Periódico Oficial No.\n24, de fecha 25 de mayo de 2012, Tomo CXIX, expedida por la H. XX Legislatura, siendo\nGobernador Constitucional el C. José Guadalupe Osuna Millán 2007-2013;\nARTÍCULO 13.- Fue reformado por Decreto No. 356, publicado en el Periódico Oficial No.\n36, de fecha 31 de agosto de 2007, Índice, Tomo CXIV, expedida por la H. XVIII Legislatura, siendo Gobernador Constitucional el C. Eugenio Elorduy Walther 2001-2007; fue reformado por\nDecreto No. 255, publicado en el Periódico Oficial No. 39, de fecha 28 de agosto de 2009, Índice, Tomo CXVI, expedida por la H. XIX Legislatura, siendo Gobernador Constitucional el C. José\nGuadalupe Osuna Millán 2007-2013; fue reformado por Decreto No. 409, publicado en el\nPeriódico Oficial No. 37, de fecha 27 de agosto de 2010, Sección II, Tomo CXVII, expedido por la\nH. XIX Legislatura, Siendo Gobernador Constitucional el C. José Guadalupe Osuna Millán 20072013; fue reformado por Decreto No. 194, publicado en el Periódico Oficial No. 24, de fecha 25 de mayo de 2012, Índice, Tomo CXIX, expedida por la H. XX Legislatura, siendo Gobernador\nConstitucional el C. José Guadalupe Osuna Millán 2007-2013; fue reformado por Decreto No. 152, publicado en el Periódico Oficial No. 50, de fecha 10 de noviembre de 2017, Sección III, TOMO\nCXXIV; expedido por la H. XXII Legislatura, siendo Gobernador constitucional el C. Francisco\nArturo Vega de Lamadrid 2013-2019; fue reformado por Decreto No. 151, publicado en el\nPeriódico Oficial No. 50, de fecha 10 de noviembre de 2017, Sección VI, TOMO CXXIV; expedido por la H. XXII Legislatura, siendo Gobernador Constitucional el C. Francisco Arturo Vega de\nLamadrid 2013-2019; fue reformado por Decreto No. 281, publicado en el Periódico Oficial No. 55, Legislatura XXII, siendo Gobernador Constitucional el C. Francisco Arturo Vega de Lamadrid\n2013-2019; fue reformado por Decreto No. 280, publicado en el Periódico Oficial No. 4, de fecha\nGobernador Constitucional el C. Francisco Arturo Vega de Lamadrid 2013-2019; fue reformado\nNúmero Especial, Tomo CXXVIII, expedida por la H. XXIV Legislatura, siendo Gobernadora\nConstitucional la C. Marina del Pilar Ávila Olmeda 2021-2027; fue reformado por Decreto No. 361, Ley de Fomento a la Competitividad y Página 30 expedido por la H. XXIV Legislatura, siendo Gobernadora Constitucional la C. Marina del Pilar\nÁvila Olmeda 2021-2027;\nARTÍCULO 15.- Fue reformado por Decreto No. 40, publicado en el Periódico Oficial No. siendo Gobernadora Constitucional la C. Marina del Pilar Ávila Olmeda 2021-2027;\nARTÍCULO 16.- Fue reformado por Decreto No. 40, publicado en el Periódico Oficial No.\n108, de fecha 30 de diciembre de 2021, Tomo CXXVIII, expedida por la H. XXIV Legislatura, siendo Gobernadora Constitucional la C. Marina del Pilar Ávila Olmeda 2021-2027;\nARTÍCULO 21.- Fue reformado por Decreto No. 315, publicado en el Periódico Oficial No.\n9, de fecha 15 de febrero de 2013, Sección I, Tomo CXX, expedido por la Honorable XX\nLegislatura, siendo Gobernador Constitucional el C. Lic. José Guadalupe Osuna Millán, 20072013;\nFue adicionado este Capítulo mediante Decreto No. 478, publicado en el Periódico Oficial No. 29, de fecha 28 de junio de 2013, Tomo CXX; expedido por la H. XX Legislatura, siendo Gobernador\nConstitucional el C. José Guadalupe Osuna Millán 2007-2013;\nCAPÍTULO VII BIS\nDEL FONDO DE FOMENTO PARA EL DESARROLLO ECONÓMICO\nDE MUJERES Y JÓVENES\nARTÍCULO 22 BIS.- Fue adicionado por Decreto No. 478, publicado en el Periódico Oficial\nNo. 29, de fecha 28 de junio de 2013, Tomo CXX; expedido por la H. XX Legislatura, siendo\nGobernador Constitucional el C. José Guadalupe Osuna Millán 2007-2013;\nARTÍCULO 22 TER.- Fue adicionado por Decreto No. 478, publicado en el Periódico Oficial\nNo. 29, de fecha 28 de junio de 2013, Tomo CXX; expedido por la H. XX Legislatura, siendo\nGobernador Constitucional el C. José Guadalupe Osuna Millán 2007-2013;\nARTÍCULO 22 QUARTER.- Fue adicionado por Decreto No. 478, publicado en el Periódico siendo Gobernador Constitucional el C. José Guadalupe Osuna Millán 2007-2013;\nARTÍCULO 25.- Fue reformado por Decreto No. 40, publicado en el Periódico Oficial No. siendo Gobernadora Constitucional la C. Marina del Pilar Ávila Olmeda 2021-2027;\nARTÍCULO 31.- Fue reformado por Decreto No. 275, publicado en el Periódico Oficial No. siendo Gobernador constitucional el C. Francisco Arturo Vega de Lamadrid 2013-2019;\nLey de Fomento a la Competitividad y Página 31\nARTÍCULO 32.- Fue reformado por Decreto No. 275, publicado en el Periódico Oficial No. siendo Gobernador constitucional el C. Francisco Arturo Vega de Lamadrid 2013-2019; fue reformado por Decreto No. 40, publicado en el Periódico Oficial No. 108, de fecha 30 de diciembre de 2021, Tomo CXXVIII, expedida por la H. XXIV Legislatura, siendo Gobernadora Constitucional la C. Marina del Pilar Ávila Olmeda 2021-2027;\nARTÍCULO 33.- Fue reformado por Decreto No. 275, publicado en el Periódico Oficial No.\n30, de fecha 26 de junio de 2015, Sección III, TOMO CXX; expedido por la H. XX Legislatura, siendo Gobernador constitucional el C. Francisco Arturo Vega de Lamadrid 2013-2019;\nARTÍCULO 40.- Fue reformado por Decreto No. 275, publicado en el Periódico Oficial No.\n30, de fecha 26 de junio de 2015, Sección III, TOMO CXX; expedido por la H. XX Legislatura, siendo Gobernador constitucional el C. Francisco Arturo Vega de Lamadrid 2013-2019; fue reformado por Decreto No. 40, publicado en el Periódico Oficial No. 108, de fecha 30 de diciembre de 2021, Tomo CXXVIII, expedida por la H. XXIV Legislatura, siendo Gobernadora Constitucional la C. Marina del Pilar Ávila Olmeda 2021-2027; fue reformado por Decreto No. 203, publicado en el Periódico Oficial No. 8, de fecha 10 de febrero de 2023, Tomo CXXX, expedida por la H. XXIV\nLegislatura, siendo Gobernadora Constitucional la C. Marina del Pilar Ávila Olmeda 2021-2027;\nCAPÍTULO X\nDEL FOMENTO A LA COMPETITIVIDAD Y\nEL DESARROLLO ECONÓMICO EN EL ÁMBITO MUNICIPAL\nFue modificada la denominación de este Capítulo por Decreto No. 275, publicado en el Periódico\nOficial No. 30, de fecha 26 de junio de 2015, Sección III, TOMO CXX; expedido por la H. XX\nLegislatura, siendo Gobernador constitucional el C. Francisco Arturo Vega de Lamadrid\n2013-2019;\nCAPÍTULO X\nDE LA POLÍTICA DE DESARROLLO PARA LA COMPETITIVIDAD DE LA MICRO, PEQUEÑA\nY MEDIANA EMPRESA\nARTÍCULO 43.- Fue reformado por Decreto No. 275, publicado en el Periódico Oficial No.\n30, de fecha 26 de junio de 2015, Sección III, TOMO CXX; expedido por la H. XX Legislatura, siendo Gobernador constitucional el C. Francisco Arturo Vega de Lamadrid 2013-2019;\nARTÍCULO 44.- Fue reformado por Decreto No. 275, publicado en el Periódico Oficial No. siendo Gobernador constitucional el C. Francisco Arturo Vega de Lamadrid 2013-2019; fue reformado por Decreto No. 203, publicado en el Periódico Oficial No. 8, de fecha 10 de febrero de\n2023, Tomo CXXX, expedida por la H. XXIV Legislatura, siendo Gobernadora Constitucional la C.\nMarina del Pilar Ávila Olmeda 2021-2027;\nARTÍCULO 45.- Fue adicionado por Decreto No. 275, publicado en el Periódico Oficial No. siendo Gobernador constitucional el C. Francisco Arturo Vega de Lamadrid 2013-2019;\nLey de Fomento a la Competitividad y Página 32\nARTÍCULO 46.- Fue adicionado por Decreto No. 275, publicado en el Periódico Oficial No. siendo Gobernador constitucional el C. Francisco Arturo Vega de Lamadrid 2013-2019;\nFue adicionado este Capítulo mediante Decreto No. 275, publicado en el Periódico Oficial No. 30, Gobernador constitucional el C. Francisco Arturo Vega de Lamadrid 2013-2019;\nCAPÍTULO XI\nDEL FOMENTO A LA COMPETITIVIDAD Y\nEL DESARROLLO ECONÓMICO EN EL ÁMBITO MUNICIPAL\nARTÍCULO 47.- Fue adicionado por Decreto No. 275, publicado en el Periódico Oficial No.\n30, de fecha 26 de junio de 2015, Sección III, TOMO CXX; expedido por la H. XX Legislatura, siendo Gobernador constitucional el C. Francisco Arturo Vega de Lamadrid 2013-2019;\nFue adicionado este Capítulo mediante Decreto No. 275, publicado en el Periódico Oficial No. 30, de fecha 26 de junio de 2015, Sección III, TOMO CXX; expedido por la H. XX Legislatura, siendo\nGobernador constitucional el C. Francisco Arturo Vega de Lamadrid\n2013-2019;\nCAPÍTULO XII\nDEL RECURSO\nARTÍCULO 48.- Fue adicionado por Decreto No. 275, publicado en el Periódico Oficial No.\n30, de fecha 26 de junio de 2015, Sección III, TOMO CXX; expedido por la H. XX Legislatura, siendo Gobernador constitucional el C. Francisco Arturo Vega de Lamadrid 2013-2019;\nFue adicionado este Capítulo por Decreto No. 118, publicado en el Periódico Oficial No. 49, de fecha 29 de julio de 2022, Tomo CXXIX, expedida por la H. XXIV Legislatura, siendo\nGobernadora Constitucional la C. Marina del Pilar Ávila Olmeda 2021-2027;\nCAPÍTULO XIII\nDEL INSTITUTO DEL EMPRENDIMIENTO DE BAJA CALIFORNIA\nARTÍCULO 49.- Fue adicionado por Decreto No. 118, publicado en el Periódico Oficial No.\nGobernadora Constitucional la C. Marina del Pilar Ávila Olmeda 2021-2027;\nARTÍCULO 50.- Fue adicionado por Decreto No. 118, publicado en el Periódico Oficial No.\nGobernadora Constitucional la C. Marina del Pilar Ávila Olmeda 2021-2027;\nARTÍCULO 51.- Fue adicionado por Decreto No. 118, publicado en el Periódico Oficial No.\nGobernadora Constitucional la C. Marina del Pilar Ávila Olmeda 2021-2027;\nLey de Fomento a la Competitividad y Página 33\nARTÍCULO 52.- Fue adicionado por Decreto No. 118, publicado en el Periódico Oficial No.\nGobernadora Constitucional la C. Marina del Pilar Ávila Olmeda 2021-2027;\nARTÍCULO 53.- Fue adicionado por Decreto No. 118, publicado en el Periódico Oficial No.\nGobernadora Constitucional la C. Marina del Pilar Ávila Olmeda 2021-2027;\nLey de Fomento a la Competitividad y Página 34\nARTICULO SEGUNDO TRANSITORIO DEL DECRETO NO. 356, POR EL QUE SE\nREFORMAA EL ARTÍCULO 13, PUBLICADO EN EL PERIODICO OFICIAL No. 36, DE FECHA 31\nGOBERNADOR CONSTITUCIONAL EL C. EUGENIO ELORDUY WALTHER 2001-2007.\nTRANSITORIOS\nARTÍCULO PRIMERO.- Las presentes reformas entrarán en vigor al día siguiente de su publicación en el Periódico Oficial del Estado de Baja California.\nARTÍCULO SEGUNDO.- Durante el ejercicio fiscal del año 2007, se aplicará el porcentaje de 80% (ochenta por ciento), para la exención del impuesto sobre remuneraciones al trabajo personal, que prevé el artículo 181 que se adiciona a la Ley de Hacienda del Estado de Baja\nCalifornia.\nARTÍCULO TERCERO.- Se condona a los contribuyentes a que se refiere el artículo 181 que se adiciona a la Ley de Hacienda del Estado de Baja California, del pago del impuesto sobre remuneraciones al trabajo personal causado desde el primero de enero de 2007 hasta la entrada en vigor de este Decreto, en el porcentaje previsto en el artículo que antecede.\nARTÍCULO CUARTO.- Se deroga el artículo segundo transitorio del Decreto número 185, publicado en el Periódico Oficial del Estado, el día 24 de febrero de 2006.”\nDADO.- En el Salón de Sesiones “Lic. Benito Juárez García”, en la Ciudad de Mexicali, Baja California”, a los doce días del mes de julio del año dos mil siete.\nDIP. MANUEL PONS AGÚNDEZ\nPRESIDENTE\n(RÚBRICA)\nDIP. ELÍAS LÓPEZ MENDOZA\nSECRETARIO\n(RÚBRICA)\nDE CONFORMIDAD CON LO DISPUESTO POR LA FRACCION I DEL ARTICULO 49 DE\nLA CONSTITUCION POLITICA DEL ESTADO, IMPRIMASE Y PUBLIQUESE.\nMEXICALI, BAJA CALIFORNIA, A TRECE DE AGOSTO DEL AÑO DOS MIL SIETE.\nGOBERNADOR DEL ESTADO.\nEUGENIO ELORDUY WALTHER\n(RÚBRICA)\nLey de Fomento a la Competitividad y Página 35\nSECRETARIO GENERAL DE GOBIERNO\nBERNARDO H. MARTINEZ AGUIRRE\n(RÚBRICA)\nARTÍCULO UNICO TRANSITORIO DEL DECRETO NO. 255, POR EL QUE SE APRUEBA\nLA ADICIÓN DE LA FRACCIÓN VII AL ARTÍCULO 13, PUBLICADO EN EL PERIÓDICO OFICIAL\nNo. 39, DE FECHA 28 DE AGOSTO DE 2009, TOMO CXVI, EXPEDIDO POR LA H. XIX\nLEGISLATURA, SIENDO GOBERNADOR CONSTITUCIONAL EL C. JOSÉ GUADALUPE\nOSUNA MILLÁN 2007-2013.\nÚNICO.- Las presentes reformas entrarán en vigor al día siguiente de su publicación en el\nPeriódico Oficial del Estado de Baja California.\nDADO en el Salón de Sesiones “Lic. Benito Juárez García” del H. Poder Legislativo del\nEstado de Baja California, en la Ciudad de Mexicali, B.C., a los dieciséis días del mes de julio de dos mil nueve.\nDIP. ENRIQUE MÉNDEZ JUÁREZ\nPRESIDENTE\n(RÚBRICA)\nDIP. GLORIA MARÍA LOZA GALVÁN\nSECRETARIA\n(RÚBRICA)\nDE CONFORMIDAD CON LO DISPUESTO POR LA FRACCIÓN I DEL ARTÍCULO 49 DE\nMEXICALI, BAJA CALIFORNIA, A LOS DOCE DIAS DEL MES DE AGOSTO DEL AÑO\nDOS MIL NUEVE.\nGOBERNADOR DEL ESTADO\nJOSE GUADALUPE OSUNA MILLAN\n(RÚBRICA)\nSECRETARIO GENERAL DE GOBIERNO\nJOSE FRANCISCO BLAKE MORA\n(RÚBRICA)\nARTÍCULO PRIMERO TRANSITORIO DEL DECRETO NO. 409, POR EL QUE SE\nADICIONAN LOS INCISOS A) Y B) A LA FRACCIÓN IV, Y SE MODIFICA EL NUMERAL 1 DEL\nINCISO C) DE LA FRACCIÓN XIV, AMBAS DEL ARTÍCULO 3, SE MODIFICA Y SE ADICIONA\nLOS INCISOS T) Y U) DE LA FRACCIÓN II DEL ARTÍCULO 4, Y SE ADICIONA UNA FRACCIÓN\nLey de Fomento a la Competitividad y Página 36\nVIII AL ARTÍCULO 13, PUBLICADO EN EL PERIÓDICO OFICIAL No. 37, DE FECHA 27 DE\nSIENDO GOBERNADOR CONSTITUCIONAL EL C. JOSÉ GUADALUPE OSUNA MILLÁN 2007-\n2013.\nARTÍCULOS TRANSITORIOS.\nPRIMERO.- La presente reforma entrará en vigor al día siguiente de su publicación en el\nPeriódico Oficial del Estado de Baja California.\nSEGUNDO.- El Ejecutivo del Estado dentro de los noventa días siguientes a la entrada en vigor de estas Reformas, deberá expedir las disposiciones reglamentarias correspondientes.\nDADO en el Salón de Sesiones “Lic. Benito Juárez García” del H. Poder Legislativo del\nEstado de Baja California, en la Ciudad de Mexicali, B.C., a los dieciséis días del mes de agosto del año dos mil diez.\nDIP. JUAN MANUEL GASTÉLUM BUENROSTRO\nPRESIDENTE\n(RÚBRICA)\nDIP. CARLOS ALONSO ANGULO RENTERIA\nSECRETARIO\n(RÚBRICA)\nDE CONFORMIDAD CON LO DISPUESTO POR LA FRACCIÓN I DEL ARTÍCULO 49 DE\nMEXICALI, BAJA CALIFORNIA, A LOS VEINTICUATRO DÍAS DEL MES DE AGOSTO\nDEL AÑO DOS MIL DIEZ.\nJOSE GUADALUPE OSUNA MILLAN\nGOBERNADOR DEL ESTADO\n(RÚBRICA)\nCUAUHTEMOC CARDONA BENAVIDEZ\nSECRETARIO GENERAL DE GOBIERNO\n(RÚBRICA)\nARTÍCULO ÚNICO TRANSITORIO DEL DECRETO No. 194, POR EL QUE SE\nLA FRACCIÓN X DEL ARTÍCULO 11, Y SE ADICIONA LA FRACCIÓN IX AL ARTÍCULO 13,\nPUBLICADO EN EL PERIÓDICO OFICIAL No. 24, TOMO CXIX, DE FECHA 25 DE MAYO DE\nLey de Fomento a la Competitividad y Página 37\n2012, EXPEDIDO POR LA H. XX LEGISLATURA, SIENDO GOBERNADOR CONSTITUCIONAL\nEL C. JOSÉ GUADALUPE OSUNA MILLÁN 2007-2013.\nARTÍCULOS TRANSITORIOS\nPRIMERO.- El presente decreto entrará en vigor, al día siguiente de su publicación en el\nPeriódico Oficial del Estado.\nSEGUNDO.- El Ejecutivo del Estado en un término no mayor de 60 días contados a partir de la entrada en vigor del presente Decreto, deberá modificar el Reglamento de la Ley de\nFomento a la Competitividad y Desarrollo Económico para el Estado de Baja California.\nTERCERO.- La Secretaria de Desarrollo Económico del Estado, así como la Comisión\nEstatal de Energía, adecuarán las normatividades interiores correspondientes a efecto de materializar los procedimientos objetos de esta reforma, en un plazo que no excederá de noventa días naturales siguientes a la entrada en vigor de esta reforma.\nDADO en el Salón de Sesiones “Lic. Benito Juárez García” del H. Poder Legislativo del\nEstado de Baja California, en la Ciudad de Mexicali, B.C., a los diecisiete días del mes de abril del año dos mil doce.\nDIP. DAVID JORGE LOZANO PÉREZ\nPRESIDENTE\n(RÚBRICA)\nDIP. ALFONSO GARZÓN ZATARAIN\nSECRE TARIO\n(RÚBRICA)\nDE CONFORMIDAD CON LO DISPUESTO POR LA FRACCIÓN I DEL ARTÍCULO 49 DE\nMEXICALI, BAJA CALIFORNIA, A LOS TREINTA DÍAS DEL MES DE ABRIL DEL AÑO\nDOS MIL DOCE.\nJOSÉ GUADALUPE OSUNA MILLÁN\nGOBERNADOR DEL ESTADO\n(RÚBRICA)\nCUAUHTEMOC CARDONA BENAVIDES\nLey de Fomento a la Competitividad y Página 38\nSECRETARIO GENERAL DE GOBIERNO\n(RÚBRICA)\nARTÍCULO SEGUNDO TRANSITORIO DEL DECRETO No. 315, POR EL QUE SE\nREFORMA EL PÁRRAFO SEGUNDO DEL ARTÍCULO 21, PUBLICADO EN EL PERIÓDICO\nPOR LA H. XX LEGISLATURA, SIENDO GOBERNADOR CONSTITUCIONAL EL C. JOSÉ\nGUADALUPE OSUNA MILLÁN 2007-2013.\nARTÍCULO TRANSITORIO\nÚNICO.- Las presentes reformas entrarán en vigor al día siguiente de su publicación en el\nPeriódico Oficial del Estado.\nDADO en el Salón de Sesiones “Lic. Benito Juárez García” del H. Poder Legislativo del\nEstado de Baja California, en la Ciudad de Mexicali, B.C., a los quince días del mes de enero del año dos mil trece.\nDIP. ELISA ROSANA SOTO AGÜERO\nVICEPRESIDENTE\n(RÚBRICA)\nDIP. FAUSTO ZÁRATE ZEPEDA\nSECRETARIO\n(RÚBRICA)\nDE CONFORMIDAD CON LO DISPUESTO POR LA FRACCIÓN I DEL ARTÍCULO 49 DE\nMEXICALI, BAJA CALIFORNIA, A LOS VEINTICINCO DÍAS DEL MES DE ENERO DEL\nAÑO DOS MIL TRECE.\nJOSÉ GUADALUPE OSUNA MILLÁN\nGOBERNADOR DEL ESTADO\n(RÚBRICA)\nFRANCISCO ANTONIO GARCÍA BURGOS\nSECRETARIO GENERAL DE GOBIERNO\n(RÚBRICA)\nARTÍCULO UNICO TRANSITORIO DEL DECRETO No. 478, POR EL QUE SE ADICIONA\nEL CAPÍTULO VII BIS, ASÍ COMO LOS ARTÍCULOS 22 BIS, 22 TER Y 22 QUARTER;\nLey de Fomento a la Competitividad y Página 39\nCXX; EXPEDIDO POR LA H. XX LEGISLATURA, SIENDO GOBERNADOR CONSTITUCIONAL\nEL C. JOSÉ GUADALUPE OSUNA MILLÁN 2007-2013.\nTRANSITORIOS\nARTÍCULO PRIMERO.- Las presentes reformas entrarán en vigor el día primero de Enero de 2014.\nARTÍCULO SEGUNDO.- En un término no mayor al de seis meses contados a partir de la entrada en vigor de las presentes reformas, el Poder Ejecutivo del Estado constituirá el Fondo a que se refiere el artículo 22 Bis de este ordenamiento, de conformidad con la Ley de las Entidades\nParaestatales del Estado de Baja California y demás disposiciones que resulten aplicables.\nDADO en el Salón de Sesiones “Lic. Benito Juárez García” del H. Poder Legislativo del\nEstado de Baja California, en la Ciudad de Mexicali, B.C., a los veintiocho días del mes de mayo del año dos mil trece.\nDIP. JULIO FELIPE GARCÍA MUÑOZ\nPRESIDENTE\n(RÚBRICA)\nDIP. MARCO ANTONIO VIZCARRA CALDERÓN\nSECRETARIO\n(RÚBRICA)\nDE CONFORMIDAD CON LO DISPUESTO POR LA FRACCION I DEL ARTÍCULO 49 DE\nMEXICALI, BAJA CALIFORNIA, A LOS DIEZ DÍAS DEL MES DE JUNIO DEL AÑO DOS\nMIL TRECE.\nGOBERNADOR DEL ESTADO\nJOSE GUADALUPE OSUNA MILLAN\n(RÚBRICA)\nSECRETARIO GENERAL DE GOBIERNO\nCUAUHTEMOC CARDONA BENAVIDES\n(RÚBRICA)\nARTÍCULO UNICO TRANSITORIO DEL DECRETO No. 275, POR EL QUE SE\nREFORMAN LOS ARTÍCULOS 31, 32, 33 Y 40; SE ADICIONA UN NUEVO CAPÍTULO\nTITULADO “DE LA POLÍTICA DE DESARROLLO PARA LA COMPETITIVIDAD DE LA MICRO,\nPEQUEÑA Y MEDIANA EMPRESA”, COMPUESTO POR LOS ARTÍCULOS 43, 44, 45, Y 46; Y\nLey de Fomento a la Competitividad y Página 40\nEL TEXTO VIGENTE DEL LOS NUMERALES 43 Y 44 PASA A FORMAR PARTE DE LOS\nARTÍCULOS 47 Y 48; PUBLICADO EN EL PERIÓDICO OFICIAL No. 30, DE FECHA 26 DE\nGOBERNADOR CONSTITUCIONAL EL C. FRANCISCO ARTURO VEGA DE LAMADRID 2013-\n2019.\nARTÍCULOS TRANSITORIOS\nPRIMERO.- El presente Decreto entrará en vigor al día siguiente de su publicación en el\nPeriódico Oficial del Estado de Baja California.\nSEGUNDO.- A partir de la entrada en vigor del presente Decreto, se derogan todas aquellas disposiciones que se opongan a lo establecido en el mismo.\nTERCERO.- El Reglamento de esta Ley, deberá actualizarse en un plazo no mayor a 90 días, contados a partir de la entrada en vigor del presente Decreto.\nCUARTO.- Los Reglamentos Municipales deberán actualizarse en un plazo que no exceda de los 90 días, contados a partir de la entrada en vigor del presente Decreto.\nQUINTO.- Dentro de los 180 días posteriores a la entrada en vigor del presente Decreto, deberán actualizarse los planes y programas respectivos.\nSEXTO.- El Comité Consultivo de Fomento a la Competitividad y Desarrollo Económico de\nBaja California, además de las atribuciones contenidas por esta ley, asumirá el carácter de un\nConsejo Estatal para la Competitividad de la Micro, Pequeña y Mediana Empresa, llevando a cabo el objeto y las funciones encomendadas, por el titular de la Secretaría de Desarrollo Económico del Estado adoptará las medidas administrativas a que haya lugar para tales efectos.\nDADO en el Salón de Sesiones “Lic. Benito Juárez García” del H. Poder Legislativo del\nEstado de Baja California, en la Ciudad de Mexicali, B.C., a los 21 días del mes de mayo del año dos mil quince.\nDIP. FCO. ALCIBÍADES GARCÍA LIZARDI\nPRESIDENTE\n(RÚBRICA)\nDIP. ROSALBA LÓPEZ REGALADO\nSECRETARIA\n(RÚBRICA)\nDE CONFORMIDAD CON LO DISPUESTO POR LA FRACCION I DEL ARTÍCULO 49 DE\nLey de Fomento a la Competitividad y Página 41\nMEXICALI, BAJA CALIFORNIA, A LOS DOS DÍAS DEL MES DE JUNIO DEL AÑO DOS\nMIL QUINCE.\nFRANCISCO ARTURO VEGA DE LAMADRID\nGOBERNADOR DEL ESTADO\n(RÚBRICA)\nFRANCISCO RUEDA GÓMEZ\nSECRETARIO GENERAL DE GOBIERNO\n(RÚBRICA)\nARTÍCULO ÚNICO TRANSITORIO DEL DECRETO No. 152, POR EL QUE SE REFORMA\nLA FRACCIÓN I DEL ARTÍCULO 13; PUBLICADO EN EL PERIÓDICO OFICIAL No. 50, DE\nFECHA 10 DE NOVIEMBRE DEL 2017, SECCIÓN III, TOMO CXXIV; EXPEDIDO POR LA H. XXII\nLEGISLATURA, SIENDO GOBERNADOR CONSTITUCIONAL EL C. FRANCISCO ARTURO\nVEGA DE LAMADRID 2013-2019.\nARTÍCULOS TRANSITORIOS\nPRIMERO.- La presente reforma entrará en vigor al día siguiente de su publicación en el\nPeriódico Oficial del Estado.\nSEGUNDO.- El Ejecutivo del Estado deberá realizar las modificaciones necesarias a sus reglamentos a más tardar sesenta días naturales contados a partir de la publicación de la presente reforma.\nDADO en el Salón de Sesiones “Lic. Benito Juárez García” del H. Poder Legislativo del\nEstado de Baja California, en la Ciudad de Mexicali, B.C., a los doce días del mes de octubre del año dos mil diecisiete.\nDIP. EDGAR BENJAMÍN GÓMEZ MACÍAS\nPRESIDENTE\n(RÚBRICA)\nDIP. EVA MAÍA VÁSQUEZ HERNÁNDEZ\nSECRETARIA\n(RÚBRICA)\nDE CONFORMIDAD CON LO DISPUESTO POR LA FRACCIÓN I DEL ARTÍCULO 49 DE\nMEXICALI, BAJA CALIFORNIA, A LOS VEINTITRÉS DÍAS DE OCTUBRE DEL AÑO DOS\nMIL DIECISIETE.\nLey de Fomento a la Competitividad y Página 42\nFRANCISCO ARTURO VEGA DE LAMADRID\nGOBERNADOR DEL ESTADO\n(RÚBRICA)\nFRANCISCO RUEDA GÓMEZ\nSECRETARIO GENERAL DE GOBIERNO\n(RÚBRICA)\nARTÍCULO ÚNICO TRANSITORIO DEL DECRETO No. 151, POR EL QUE SE REFORMA\nA LOS ARTÍCULOS 3, 4, 10 Y 13; PUBLICADO EN EL PERIÓDICO OFICIAL No. 50, DE FECHA\n10 DE NOVIEMBRE DEL 2017, SECCIÓN VI, TOMO CXXIV; EXPEDIDO POR LA H. XXII\nLEGISLATURA, SIENDO GOBERNADOR CONSTITUCIONAL EL C. FRANCISCO ARTURO\nVEGA DE LAMADRID 2013-2019.\nDADO en el Salón de Sesiones “Lic. Benito Juárez García” del H. Poder Legislativo del\nEstado de Baja California, en la Ciudad de Mexicali, B.C., a los doce días del mes de octubre del año dos mil diecisiete.\nDIP. EDGAR BENJAMÍN GÓMEZ MACÍAS\nPRESIDENTE\n(RÚBRICA)\nDIP. EVA MAÍA VÁSQUEZ HERNÁNDEZ\nSECRETARIA\n(RÚBRICA)\nDE CONFORMIDAD CON LO DISPUESTO POR LA FRACCIÓN I DEL ARTÍCULO 49 DE\nMEXICALI, BAJA CALIFORNIA, A LOS VEINTITRÉS DÍAS DE OCTUBRE DEL AÑO DOS\nMIL DIECISIETE.\nFRANCISCO ARTURO VEGA DE LAMADRID\nGOBERNADOR DEL ESTADO\n(RÚBRICA)\nFRANCISCO RUEDA GÓMEZ\nSECRETARIO GENERAL DE GOBIERNO\n(RÚBRICA)\nARTÍCULO OCTAVO TRANSITORIO DEL DECRETO No. 281, POR EL QUE SE\nREFORMAN LOS ARTÍCULOS 3 Y 13, PUBLICADO EN EL PERIÓDICO OFICIAL No. 55, Ley de Fomento a la Competitividad y Página 43\nXXII LEGISLATURA, SIENDO GOBERNADOR CONSTITUCIONAL EL C. FRANCISCO ARTURO\nVEDA DE LAMADRID 2013-2019.\nARTÍCULOS TRANSITORIOS\nARTÍCULO PRIMERO.- El presente decreto entrará en vigor al día siguiente al de su publicación en el Periódico Oficial del Estado de Baja California.\nARTÍCULO SEGUNDO.- El valor diario de la Unidad de Medida y Actualización a la fecha de entrada en vigor, se tomará el valor publicado en el Diario Oficial de la Federación por el\nINEGI. El valor de la Unidad de Medida y Actualización a la fecha de entrada en vigor del presente\nDecreto, será producto de multiplicar el valor referido en el párrafo anterior por 30.4. Por su parte, el valor anual será el producto de multiplicar el valor inicial mensual por 12.\nARTÍCULO TERCERO. - Todas las menciones al salario mínimo como unidad de cuenta, índice, base, medida o referencia para determinar la cuantía de las obligaciones, sanciones, multas administrativas, conceptos de pago y montos de referencia, se entenderán referidas a la\nUnidad de Medida y Actualización.\nDADO en el Salón de Sesiones “Lic. Benito Juárez García” del H. Poder Legislativo del\nEstado de Baja California, en la Ciudad de Mexicali, B.C., a los veinticinco días del mes de octubre del año dos mil dieciocho.\nDIP. ROCÍO LÓPEZ GOROSAVE\nPRESIDENTA\n(RÚBRICA)\nDIP. MÓNICA HERNÁNDEZ ÁLVAREZ\nSECRETARIA\n(RÚBRICA)\nDE CONFORMIDAD CON LO DISPUESTO POR LA FRACCIÓN I DEL ARTÍCULO 49 DE\nMEXICALI, BAJA CALIFORNIA, A LOS TREINTA DÍAS DEL MES DE NOVIEMBRE DEL\nAÑO DOS MIL DIECIOCHO.\nFRANCISCO ARTURO VEGA DE LAMADRID\nGOBERNADOR DEL ESTADO\n(RÚBRICA)\nFRANCISCO RUEDA GÓMEZ\nSECRETARIO GENERAL DE GOBIERNO\n(RÚBRICA)\nLey de Fomento a la Competitividad y Página 44\nARTÍCULO PRIMERA TRANSITORIO DEL DECRETO No. 280, POR EL QUE SE\nREFORMA A LOS ARTÍCULOS 3, 4, 10 Y 13; PUBLICADO EN EL PERIÓDICO OFICIAL No. 4,\nDE FECHA 18 DE ENERO DEL 2019, SECCIÓN II, TOMO CXXVI; EXPEDIDO POR LA H. XXII\nLEGISLATURA, SIENDO GOBERNADOR CONSTITUCIONAL EL C. FRANCISCO ARTURO\nVEGA DE LAMADRID 2013-2019.\nARTÍCULO TRANSITORIO\nÚNICO.- Las presentes reformas entrarán en vigor al día siguiente de su publicación en el\nPeriódico Oficial del Estado.\nDADO en el Salón de Sesiones “Lic. Benito Juárez García” del H. Poder Legislativo del\nEstado de Baja California, en la Ciudad de Mexicali, B.C., a los veinticinco días del mes de octubre del año dos mil dieciocho.\nDIP. ROCÍO LÓPEZ GOROSAVE\nPRESIDENTA\n(RÚBRICA)\nDIP. MÓNICA HERNÁNDEZ ÁLVAREZ\nSECRETARIA\n(RÚBRICA)\nDE CONFORMIDAD CON LO DISPUESTO POR LA FRACCIÓN I DEL ARTÍCULO 49 DE\nMEXICALI, BAJA CALIFORNIA, A LOS CATORCE DÍAS DEL MES DE DICIEMBRE DEL\nAÑO DOS MIL DIECIOCHO.\nFRANCISCO ARTURO VEGA DE LAMADRID\nGOBERNADOR DEL ESTADO\n(RÚBRICA)\nFRANCISCO RUEDA GÓMEZ\nSECRETARIO GENERAL DE GOBIERNO\n(RÚBRICA)\nARTÍCULO ÚNICO TRANSITORIO DEL DECRETO No. 40, POR EL QUE SE REFORMA\nA LOS ARTÍCULOS 2, 3, 4, 10, 13, 15, 16, 25, 32 Y 40; PUBLICADO EN EL PERIÓDICO\nLey de Fomento a la Competitividad y Página 45\nCXXVIII; EXPEDIDO POR LA H. XXIV LEGISLATURA, SIENDO GOBERNADORA\nCONSTITUCIONAL LA C. MARINA DEL PILAR ÁVILA OLMEDA 2021-2027.\nTRANSITORIO\nÚNICO.- Las presentes reformas entrarán en vigor al día siguiente de su publicación en el\nPeriódico Oficial del Estado.\nDADO en Sesión Ordinaria de la XXIV Legislatura en la Ciudad de Mexicali, B.C., a los dieciocho días del mes de noviembre del año dos mil veintiuno.\nDIP. JUAN MANUEL MOLINA GARCÍA\nPRESIDENTE\n(RÚBRICA)\nDIP. ARACELI GERALDO NÚÑEZ\nSECRETARIA\n(RÚBRICA)\nDE CONFORMIDAD CON LO DISPUESTO POR LA FRACCIÓN I DEL ARTÍCULO 49 DE LA\nIMPRÍMASE Y PUBLÍQUESE.\nMEXICALI, BAJA CALIFORNIA A LOS VEINTIÚN DÍAS DEL MES DE DICIEMBRE DEL\nAÑO DOS MIL VEINTIUNO.\nMARINA DEL PILAR ÁVILA OLMEDA\nGOBERNADORA DEL ESTADO\nDE BAJA CALIFORNIA\n(RÚBRICA)\nCATALINO ZAVALA MÁRQUEZ\nSECRETARIO GENERAL DE GOBIERNO\n(RÚBRICA)\nARTÍCULO ÚNICO TRANSITORIO DEL DECRETO No. 118, POR EL QUE SE REFORMA\nEL ARTÍCULO 3, ASÍ COMO LA ADICIÓN DE UN CAPÍTULO XIII DENOMINADO DEL\nARTÍCULOS DE NUEVA CREACIÓN 49, 50, 51, 52 y 53; PUBLICADO EN EL PERIÓDICO\nLey de Fomento a la Competitividad y Página 46\nPOR LA H. XXIV LEGISLATURA, SIENDO GOBERNADORA CONSTITUCIONAL LA C. MARINA\nDEL PILAR ÁVILA OLMEDA 2021-2027.\nTRANSITORIOS\nÚNICO.- La presente reforma entrará en vigor al día siguiente de su publicación en el\nPeriódico Oficial del Estado de Baja California.\nDADO en Sesión Ordinaria de la XXIV Legislatura en la Ciudad de Mexicali, B.C., a los siete días del mes de julio del año dos mil veintidós.\nDIP. JULIA ANDREA GONZÁLEZ QUIROZ\nPRESIDENTA\n(RÚBRICA)\nDIP. CLAUDIA JOSEFINA AGATÓN MUÑIZ\nPROSECRETARIA\n(RÚBRICA)\nDE CONFORMIDAD CON LO DISPUESTO POR LA FRACCIÓN I DEL ARTÍCULO 49 DE\nIMPRÍMASE Y PUBLÍQUESE.\nMEXICALI, BAJA CALIFORNIA A LOS TRECE DÍAS DEL MES DE JULIO DEL AÑO DOS\nMIL VEINTIDÓS.\nMARINA DEL PILAR ÁVILA OLMEDA\nGOBERNADORA DEL ESTADO\nDE BAJA CALIFORNIA\n(RÚBRICA)\nCATALINO ZAVALA MÁRQUEZ\nSECRETARIO GENERAL DE GOBIERNO\nDEL ESTADO DE BAJA CALIFORNIA\n(RÚBRICA)\nARTÍCULO ÚNICO TRANSITORIO DEL DECRETO No. 203, POR EL QUE SE\nREFORMAN LOS ARTÍCULOS 9, 40 Y 44; PUBLICADO EN EL PERIÓDICO OFICIAL No. 8, DE\nLEGISLATURA, SIENDO GOBERNADORA CONSTITUCIONAL LA C. MARINA DEL PILAR\nÁVILA OLMEDA 2021-2027.\nTRANSITORIOS\nLey de Fomento a la Competitividad y Página 47\nPRIMERO.- El presente decreto entrará en vigor a partir del día siguiente de su publicación en el Periódico Oficial del Estado.\nSEGUNDO.- Para efectos de los programas de regularización de empresas previstos en el presente Decreto, el Ejecutivo del Estado podrá celebrar convenios de colaboración administrativa con los Ayuntamientos para otorgar asesoría y orientación en: cumplimiento de obligaciones en materia tributaria, ambiental, protección civil, del trabajo, entre otras relativas a las empresas.\nDADO en Sesión Ordinaria de la XXIV Legislatura en la Ciudad de Mexicali, B.C., a los veintiséis días del mes de enero del año dos mil veintitrés.\nDIP. MARÍA DEL ROCÍO ADAME MUÑOZ\nPRESIDENTA\n(RÚBRICA)\nDIP. DUNNIA MONTSERRAT MURILLO LÓPEZ\nPROSECRETARIA\n(RÚBRICA)\nDE CONFORMIDAD CON LO DISPUESTO POR LA FRACCIÓN I DEL ARTÍCULO 49 DE\nIMPRÍMASE Y PUBLÍQUESE.\nMEXICALI, BAJA CALIFORNIA A LOS VEINTISIETE DÍAS DEL MES DE ENERO DEL\nAÑO DOS MIL VEINTITRÉS.\nMARINA DEL PILAR ÁVILA OLMEDA\nGOBERNADORA DEL ESTADO\nDE BAJA CALIFORNIA\n(RÚBRICA)\nCATALINO ZAVALA MÁRQUEZ\nSECRETARIO GENERAL DE GOBIERNO\nDEL ESTADO DE BAJA CALIFORNIA\n(RÚBRICA)\nARTÍCULO SEGUNDO TRANSITORIO DEL DECRETO No. 361, POR EL QUE SE\nREFORMAN LOS ARTÍCULOS 3, FRACCIÓN XV, 13 FRACCIÓN III; PUBLICADO EN EL\nEXPEDIDO POR LA H. XXIV LEGISLATURA, SIENDO GOBERNADORA CONSTITUCIONAL LA\nC. MARINA DEL PILAR ÁVILA OLMEDA 2021-2027.\nTRANSITORIOS\nLey de Fomento a la Competitividad y Página 48\nPRIMERO. La presente reforma entrará en vigor el día primero de enero del año dos mil veinticuatro.\nSEGUNDO. Las solicitudes de estímulo fiscales presentadas en ventanilla única de la procedentes, deberán ser tramitadas y remitidas en un plazo máximo de 20 días hábiles a partir de la entrada en vigor de la presente reforma, a la Secretaría de Hacienda para la emisión de la resolución correspondiente, conforme a lo previsto en las disposiciones fiscales aplicables.\nTERCERO. Las solicitudes en trámite por estímulos fiscales regulados por la presente Ley que hayan sido presentadas antes de la publicación de la presente reforma, se deberá dar trámite y resolver, de conformidad con los ordenamientos vigentes al momento de su presentación en ventanilla única de la Secretaría de Economía e Innovación.\nCUARTO. La Secretaría de Economía e Innovación, actualizará los formatos necesarios para las solicitudes de estímulos fiscales que se presenten a partir de la entrada en vigor de la presente reforma.\nDADO en Sesión Ordinaria de la XXIV Legislatura en la Ciudad de Mexicali, B.C., a los diecinueve días del mes de diciembre del año dos mil veintitrés.\nDIP. ARACELI GERALDO NÚÑEZ\nPRESIDENTA\n(RÚBRICA)\nDIP. MANUEL GUERRERO LUNA\nSECRETARIO\n(RÚBRICA)\nLey de Fomento a la Competitividad y Página 49",
  "ordenamiento": "REGLAMENTO",
  "jurisdiccion": "BAJA CALIFORNIA",
  "fuente_oficial": "Periódico Oficial",
  "FECHA PER OFIC": "2023/12/22",
  "ESTATUS": "VIGENTE",
  "TOMO": "TOMO_VII",
  "URL": "https://www.congresobc.gob.mx/Documentos/ProcesoParlamentario/Leyes/TOMO_VII/20231222_LEYFOMCOMPETI.PDF",
  "es_escaneado": false,
  "tiene_tablas": true,
  "materia": [
    "ambiental",
    "urbanismo",
    "infraestructura"
  ]
}