{
  "titulo": "Ley DEL PROCEDIMIENTO PARA LOS ACTOS DE LA ADMINISTRACIÓN PÚBLICA DEL ESTADO DE BAJA CALIFORNIA",
  "Contenido": ".\n.\nActualización Legislativa. Ultima reforma P.O. No. 53, Secc. I, 20-Nov-2015\nLEY DEL PROCEDIMIENTO PARA LOS ACTOS DE LA\nADMINISTRACIÓN PÚBLICA DEL ESTADO DE\nBAJA CALIFORNIA\nPublicado en el Periódico Oficial No. 1, de fecha 02 de\nEnero del 2004, Tomo CXI\nTÍTULO PRIMERO I\nDEL ÁMBITO DE APLICACIÓN\nCAPITULO I\nDE LAS DISPOSICIONES GENERALES\nARTÍCULO 1.- Las disposiciones de esta Ley son de orden e interés públicos, y se aplicarán a los actos, procedimientos y resoluciones de la\nAdministración Pública Centralizada y Paraestatal del Poder Ejecutivo del\nEstado de Baja California.\nQuedan excluidos de la aplicación de ésta Ley, los actos, procedimientos y resoluciones relacionados con las materias siguientes: de carácter estrictamente financiero, fiscal y judicial; seguridad pública, salud, educación, laboral, electoral, participación ciudadana y registral; así como actuaciones de: Ministerio Público en ejercicio de sus funciones legales, de la Dirección de Control y Evaluación Gubernamental del Poder\nEjecutivo en lo relativo a la determinación de responsabilidades de los servidores públicos y, de la Comisión Estatal de los Derechos Humanos en cuanto a las denuncias que reciba y recomendaciones que formule.\nArtículo Reformado\nARTÍCULO 2.- Para los efectos de la presente Ley, se entenderá por:\nI.- Administración Pública: La Administración Pública Estatal\nCentralizada y Paraestatal que conduce el Gobernador del Estado, conforme al\nCalifornia;\nII.- Acto administrativo: Toda actuación o declaración, externa que expresa una decisión de una autoridad administrativa competente, en ejercicio de la potestad pública, que tiene por objeto, crear, transmitir, modificar o interés general o el interés legítimo de los particulares;\nIII.- Autoridad: Dependencia, Entidad o Servidor Público, así como las administrativos que afectan la esfera jurídica del particular, susceptibles de ser\n.\n.\nActualización Legislativa. Ultima reforma P.O. No. 53, Secc. I, 20-Nov-2015 aplicados mediante el uso de las vías de apremio, sanción, uso de la fuerza pública o bien a través de otras autoridades;\nIV.- Interesado: Particular que tiene un interés legítimo respecto de un acto administrativo por ostentar un derecho legalmente tutelado;\nV.- Interés legítimo: Derecho de los particulares vinculado con el interés público y protegido por el orden jurídico, que les confiere la facultad para activar la actuación pública administrativa, respecto de alguna pretensión en particular;\nVI.- Procedimiento Administrativo: Conjunto de requisitos y formalidades jurídicas que regulan todo acto administrativo;\nVII.- Resolución Administrativa: Determinación que corresponde a un procedimiento, de manera expresa o presuntiva en caso del silencio de la autoridad, que decide todas las pretensiones planteadas por el interesado o previstas por la Ley; y\nVIII.- Ley: Ley del Procedimiento para los Actos de la Administración\nPública del Estado de Baja California.\nARTÍCULO 3.- Esta Ley se aplicará supletoriamente a las diversas leyes administrativas. El Código de Procedimientos Civiles para el Estado de Baja\nCalifornia se aplicará supletoriamente a esta Ley, en lo conducente.\nLos servidores de la Administración Pública, de conformidad con el principio de legalidad, deberán abstenerse de realizar prácticas que impliquen actos administrativos contrarios a las garantías constitucionales y a las disposiciones previstas en esta Ley. La inobservancia de lo anterior, será sancionada conforme a la Ley de Responsabilidades de los Servidores\nPúblicos del Estado de Baja California.\nCAPÍTULO II\nDE LA ADMINISTRACIÓN PÚBLICA Y LOS PARTICULARES\nARTÍCULO 4.- En sus relaciones con la Administración Pública, los particulares, tendrán los derechos siguientes:\nI.- Conocer, en cualquier momento, el estado que guardan los legítimo, y obtener copias certificadas de los documentos contenidos en ellos, en términos de la fracción X del artículo 5 de esta Ley;\nII.- Ser informados respecto de la identificación de la autoridad ante la que trámite el asunto de su interés;\nIII.- Obtener constancias de recepción respecto de los documentos que presenten para su tramitación;\n.\n.\nActualización Legislativa. Ultima reforma P.O. No. 53, Secc. I, 20-Nov-2015\nIV.- Aportar las pruebas que estimen pertinentes y formular alegatos, y\nV.- Obtener información y orientación de los requisitos jurídicos o técnicos que las normas impongan a las solicitudes o actuaciones que sea su interés realizar.\nARTÍCULO 5.- La Administración Pública, en sus relaciones con los particulares, tendrá las obligaciones siguientes:\nI.- Hacer constar en los citatorios en que se ordene la comparecencia de los interesados el lugar, fecha, hora y objeto de la misma, así como los efectos jurídicos que se producirán por el hecho de no atenderla;\nII.- Requerir informes, documentos y otros datos durante la realización de verificaciones y visitas domiciliarias, en los casos previstos por esta Ley o en otros ordenamientos jurídicos;\nIII.- Guardar absoluta reserva en lo concerniente a las declaraciones y datos suministrados por los interesados o por terceros con ellos relacionados, así como de aquella información que corresponda en los términos de las leyes respectivas. Dicha reserva no será aplicable en los casos en que deba ser suministrada a los servidores encargados de la administración o defensa de los intereses públicos, ni cuando sea solicitada por autoridades en el ejercicio de sus respectivas competencias;\nIV.- Hacer del conocimiento de los interesados, cuando así lo soliciten, el estado de la tramitación de los asuntos en que participen;\nV.- Recibir las pruebas y alegatos que presenten los interesados;\nVI.- Informar y orientar a todo interesado sobre el ejercicio de sus derechos y el cumplimiento de sus obligaciones;\nVII.- Anotar en las copias de los documentos que se presenten junto con los originales, la constancia de recepción de los mismos;\nVIII.- Facilitar el acceso a sus registros y archivos en los términos previstos en esta y otras Leyes;\nIX.- Dictar resolución expresa sobre cuanta petición le formulen, así como en los procedimientos iniciados de oficio, cuya instrucción y resolución afecte a terceros, debiendo dictarla dentro del plazo fijado por esta ley, y\nX.- Proporcionar a los interesados en todo momento la información sobre los procedimientos y el estado en que se encuentran, así como el acceso formen. Asimismo, se les podrán expedir a su costa y siempre que así lo soliciten, copias y certificaciones de los documentos que obren en los expedientes, previo pago de los derechos que correspondan.\n.\n.\nActualización Legislativa. Ultima reforma P.O. No. 53, Secc. I, 20-Nov-2015\nTÍTULO SEGUNDO\nDEL RÉGIMEN JURÍDICO DE LOS ACTOS ADMINISTRATIVOS\nCAPÍTULO I\nDE LOS REQUISITOS DE VALIDEZ DEL ACTO ADMINISTRATIVO\nARTÍCULO 6.- Para que el acto administrativo sea válido requiere:\nI.- Ser expedido por autoridad en ejercicio de su potestad pública. En caso de que dicha autoridad fuere colegiada, deberá reunir las formalidades que la Ley respectiva ordene para emitirlo;\nII.- Estar debidamente fundado y motivado;\nIII.- Tener por objeto el cumplimiento de la materia del mismo, previamente establecida; siendo posible de determinar o determinable; preciso en cuanto a las circunstancias de tiempo, modo, lugar y, previsto por una norma jurídica;\nIV.- Cumplir con la finalidad de interés público regulado por las normas en que se sustenta, sin que puedan perseguirse otros fines distintos;\nV.- Ser expedido sujetándose a las disposiciones relativas al procedimiento administrativo previsto en esta Ley y con las formalidades que requiera conforme a la Ley o disposición de orden público materia del acto;\nVI.- Ser expedido sin que medie error sobre el objeto, causa o motivo, o sobre el fin del acto;\nVII.- Ser expedido, sin que medie dolo o violencia en su emisión;\nVIII.- Tratándose de actos administrativos que deban notificarse, deberá hacerse mención de la oficina en que se encuentra y de la posibilidad de ser consultado el expediente respetivo por el interesado;\nIX.- Tratándose de actos administrativos recurribles, deberá hacerse mención de los recursos que procedan, y\nX.- Ser expedido señalando lugar y fecha de emisión.\nARTÍCULO 7.- Son requisitos de forma del acto administrativo los siguientes:\nI.- Identificación de la autoridad que lo emite;\nII.- Tratándose de actos administrativos individualizados, contener el nombre del promovente o interesado a quien vaya dirigido, asentarse en la\n.\n.\nActualización Legislativa. Ultima reforma P.O. No. 53, Secc. I, 20-Nov-2015 notificación la oficina en que pueda ser consultado el expediente respectivo y el nombre y cargo de quien lo resguarda;\nIII.- En el caso de actos administrativos que por disposición legal deban ser notificados personalmente, se hará mención de esta circunstancia en ellos;\nIV.- Tratándose de actos administrativos recurribles, deberá mencionarse el término con que se cuenta para interponer el recurso respectivo, así como la autoridad ante la cual deba ser presentado, y\nV.- Que sea expedido sin que medie error respecto a la referencia específica de identificación del expediente, documento o nombre completo del destinatario.\nCAPITULO II\nDE LA EFICACIA DEL ACTO ADMINISTRATIVO\nARTÍCULO 8.- El acto administrativo será válido hasta en tanto no se haya declarado lo contrario por autoridad administrativa o jurisdiccional competente, según sea el caso.\nARTÍCULO 9.- El acto administrativo válido, será eficaz y exigible a partir del día hábil siguiente a la notificación legalmente efectuada.\nSe exceptúa de lo dispuesto en el párrafo anterior, el acto administrativo por el cual se disponga la condición de ser otorgado y exigible por el interesado ante la autoridad que lo emita, desde la fecha en que se dictó o aquella que tenga señalada para iniciar su vigencia. En los casos en virtud de los cuales se tengan que otorgar garantías económicas, afianzar o realizar actos de inspección, investigación o vigilancia conforme a las disposiciones de orden público que procedan, los cuales serán exigibles a partir de la fecha en que la\nAdministración Pública los efectúe.\nARTÍCULO 10.- Si el acto administrativo requiere aprobación de autoridad distinta de la que lo emita, de conformidad a las disposiciones legales aplicables, no tendrá eficacia sino hasta en tanto aquella se produzca.\nCAPÍTULO III\nDE LA EJECUCIÓN DEL ACTO ADMINISTRATIVO\nARTÍCULO 11.- El acto administrativo válido será ejecutado cuando el de obtener su cumplimiento mediante el uso de medios de ejecución forzosa.\nARTÍCULO 12.- La ejecución forzosa de los actos emitidos por la\nAdministración Pública, se realizará respetando siempre el principio de proporcionalidad y por los medios siguientes:\n.\n.\nActualización Legislativa. Ultima reforma P.O. No. 53, Secc. I, 20-Nov-2015\nI.- Apremio sobre el patrimonio;\nII.- Ejecución subsidiaria;\nIII.- Multa, y\nIV.- Actos que se ejerzan sobre la persona.\nTratándose de las fracciones I, III y IV, se estará a lo que establezcan las disposiciones legales aplicables. Si hubiere varios medios de ejecución previstos por la norma aplicable, se elegirán primero los que no restrinjan la libertad individual.\nLa ejecución subsidiaria tiene lugar cuando se trate de actos que por no ser personalísimos puedan ser realizados por sujeto distinto del obligado. En este caso la administración, realizará el acto por sí o a través de las personas que determine a costa, del obligado.\nARTÍCULO 13.- El acto que ordene la clausura de un local o establecimiento, podrá ser ejecutado por la autoridad competente, mediante el auxilio de la fuerza pública, previo cumplimiento del procedimiento establecido en los ordenamientos legales aplicables o, en su defecto, de lo previsto en esta\nLey.\nCAPÍTULO IV\nDE LA NULIDAD DE LOS ACTOS ADMINISTRATIVOS\nARTÍCULO 14.- Está afectado de nulidad absoluta, el acto administrativo que no reúna los elementos de validez establecidos en el artículo\n6 de esta Ley.\nEl acto administrativo afectado de nulidad absoluta que produzca efectos provisionales, retroactivamente dejarán de tenerlos, cuando se decrete por resolución administrativa o judicial y, por ser de orden público, no es susceptible de ser convalidado; pudiendo invocarse la nulidad por todo interesado a efecto de demandar la reparación del daño ocasionado, según sea el caso.\nARTÍCULO 15.- Está afectado de nulidad relativa, el acto administrativo que no reúna los requisitos de forma establecidos en el artículo 7 de esta Ley; la omisión por la autoridad emisora, hasta en tanto no sea declarada su suspensión por autoridad competente. relativa, podrá subsanar las omisiones en los requisitos de forma, convalidando y otorgando plena eficacia del mismo. El acto que sea subsanado producirá efectos retroactivos a la fecha de su expedición, siempre y cuando este acto no\n.\n.\nActualización Legislativa. Ultima reforma P.O. No. 53, Secc. I, 20-Nov-2015 vaya en perjuicio del interesado mismo, que podrá hacer valer en su beneficio, por la vía que corresponda, las circunstancias de nulidad que se hubieren subsanado.\nARTÍCULO 16.- La nulidad absoluta o relativa puede ser invocada por el interesado o tercero perjudicado, a través del recurso de revocación que establece esta Ley.\nARTÍCULO 17.- Todo acto administrativo dictado legalmente y que sea favorable al interesado debe ser cumplido en todo momento. Siendo necesario para su revocación, el cumplimiento del debido procedimiento que corresponda y sólo mediante la declaración de autoridad competente.\nCAPÍTULO V\nDE LA EXTINCIÓN DEL ACTO ADMINISTRATIVO\nARTÍCULO 18.- El acto administrativo se extingue de pleno derecho, por las causas siguientes:\nI.- Cumplimiento de su finalidad;\nII.- Expiración del plazo;\nIII.- Cuando el acto administrativo esté sujeto a una condición o término suspensivo y estos no sean realizados dentro del plazo señalado en el propio acto;\nIV.- Actualización de la condición resolutoria;\nV.- Renuncia del interesado, cuando el acto hubiere sido dictado en exclusivo beneficio de éste y no sea en perjuicio del interés público o de terceros;\nVI.- Revocación determinada, de conformidad con las disposiciones de esta Ley;\nVII.- Conclusión de su vigencia;\nVIII.- Prescripción, y\nIX.- Nulidad, declarada en la resolución dentro del procedimiento jurisdiccional.\nTÍTULO TERCERO\nDEL PROCEDIMIENTO ADMINISTRATIVO\nCAPÍTULO I\n.\n.\nActualización Legislativa. Ultima reforma P.O. No. 53, Secc. I, 20-Nov-2015\nDE LAS DISPOSICIONES GENERALES\nARTÍCULO 19.- El procedimiento administrativo servirá para asegurar el mejor cumplimiento de los fines de la Administración Pública, así como para garantizar los derechos e intereses legítimos de los particulares, de conformidad con lo preceptuado por los ordenamientos jurídicos aplicables.\nLa actuación administrativa en el procedimiento se desarrollará con arreglo a los principios de economía, celeridad, eficacia, legalidad, publicidad y buena fe.\nARTÍCULO 20.- Las disposiciones de este Título se aplicarán a los actos que dicte la Administración Pública ante los interesados, cuando los actos jurídicos que inicien, integren o concluyan el procedimiento administrativo produzcan efectos en la esfera jurídica de estos.\nEl incumplimiento de las disposiciones de esta Ley, dará lugar a la responsabilidad del servidor público, en los términos de la Ley de\nResponsabilidades de los Servidores Públicos del Estado de Baja California.\nARTÍCULO 21.- Las manifestaciones, informes o declaraciones rendidas por los interesados a la autoridad competente, se presumirán ciertas salvo prueba en contrario, aún cuando estén sujetas al control y verificación de la autoridad. Si los informes o declaraciones proporcionados por el particular resultan falsos, se aplicarán las sanciones administrativas correspondientes, sin perjuicio de las penas en que incurran aquéllos que se conduzcan con falsedad ante la autoridad de conformidad con el Código Penal para el Estado de Baja California. La actuación administrativa de la autoridad y la de los interesados se sujetará al principio de buena fe.\nARTÍCULO 22.- La Administración Publica, no podrá exigir más formalidades que las expresamente previstas en esta Ley o el ordenamiento especial aplicable al acto de que se trate.\nLas autoridades podrán ordenar, de oficio o a petición de parte, procedimiento administrativo para el solo efecto de ser corregidas, sin que ello implique que puedan revocar sus propias resoluciones.\nARTÍCULO 23.- Salvo que las leyes especiales establezcan un plazo menor, no podrá exceder de sesenta días hábiles el tiempo para que la autoridad administrativa resuelva lo que corresponda. Transcurrido el plazo sin que se notifique la resolución, el interesado podrá considerar que la autoridad previsto en esta Ley.\n.\n.\nActualización Legislativa. Ultima reforma P.O. No. 53, Secc. I, 20-Nov-2015\nARTÍCULO 24.- Para documentar el procedimiento administrativo deberá utilizarse el medio escrito, salvo disposición en contrario; así como los elementos incorporables a un sistema de archivo y reproducción que garantice su conservación y recuperación completa y fidedigna.\nARTÍCULO 25.- En las actuaciones se deben escribir con número y letra las fechas y cantidades. No deben emplearse abreviaturas ni enmendar las frases equivocadas, los errores deben salvarse con toda precisión sobreponiendo una línea delgada de forma tal que permita la lectura.\nARTÍCULO 26.- Toda promoción debe contener la firma autógrafa y excepcionalmente cualquier otro medio que identifique fehacientemente al interesado que la formule, requisito sin el cual no se le dará curso.\nLa autoridad administrativa, en el caso de que la firma sea ilegible o distinta a las de otras promociones, puede llamar al interesado, otorgándole un plazo de tres días hábiles, para que en su presencia ratifique la firma y el contenido de la promoción.\nSi el interesado niega la firma o el contenido del escrito, o se rehúsa a contestar o no comparece, se desechará de plano la promoción.\nCAPÍTULO II\nDE LOS INTERESADOS\nARTÍCULO 27.- Se considera interesados en el procedimiento administrativo, quienes promuevan como titulares de derechos o intereses legítimos o aquéllos cuyos intereses legítimos puedan resultarles directamente afectados por la decisión que en el mismo se adopte.\nEl interesado deberá adjuntar a su escrito los documentos que acrediten su personalidad e interés legítimo, así como los que en cada caso sean requeridos en los ordenamientos especiales aplicables al acto de que se trate.\nARTÍCULO 28.- Los interesados en el procedimiento administrativo pueden actuar por sí mismos, o por medio de representante o apoderado.\nLa representación, se debe acreditar mediante carta poder firmada ante dos testigos y ratificada ante la autoridad que deba conocer del asunto, o en su caso, mediante escritura pública, cuando el interesado sea una persona moral.\nARTÍCULO 29.- Sin perjuicio de lo dispuesto en el artículo anterior, el documentos, así como para realizar los trámites y las gestiones necesarias para la substanciación del procedimiento administrativo. La autorización para oír y recibir notificaciones, también faculta al autorizado para interponer el recurso previsto en esta Ley.\n.\n.\nActualización Legislativa. Ultima reforma P.O. No. 53, Secc. I, 20-Nov-2015\nARTÍCULO 30.- Cuando en un procedimiento existan varios interesados, las actuaciones se entenderán con el representante común, que al efecto haya sido asignado; y en su defecto, con el que figure en primer término.\nLos interesados pueden revocar en cualquier etapa del procedimiento, la designación del representante común nombrando a otro, lo que se hará saber a la autoridad administrativa ante la que se promueve.\nARTÍCULO 31.- La personalidad y legitimación de las partes deberá analizarse de oficio por la autoridad que conozca del asunto.\nARTÍCULO 32.- Si durante la tramitación de un procedimiento administrativo, se advierte la existencia de un tercero cuyo interés jurídico directo puede afectarse y que hasta ese momento no haya comparecido, se le notificará la tramitación para que alegue lo que en derecho le corresponda.\nCAPÍTULO III\nDE LOS IMPEDIMENTOS, EXCUSAS Y RECUSACIONES\nARTÍCULO 33.- Todo servidor público estará impedido para intervenir o conocer de un procedimiento administrativo, en los casos siguientes:\nI.- Tenga interés directo o indirecto en el asunto de que se trate o en otro semejante, cuya resolución pudiera influir en la de aquél;\nII.- Sea administrador o accionista de la sociedad o persona moral interesada en el procedimiento administrativo;\nIII.- Tenga un litigio de cualquier naturaleza con o contra los interesados, sin haber transcurrido un año de haberse resuelto;\nIV.- Tenga interés directo o indirecto en el asunto de que se trate su cónyuge, sus parientes consanguíneos en línea recta sin limitación de grados, colaterales dentro del cuarto grado o los afines dentro del segundo;\nV.- Sea él mismo, su cónyuge o alguno de sus descendientes, heredero, legatario, donante, donatario, socio, acreedor, deudor, fiador, fiado, arrendador, arrendatario o dependiente de alguna de las partes, o administrador actual de sus bienes;\nVI.- Siga él mismo, su cónyuge o alguno de sus parientes consanguíneos en la línea recta, sin limitación de grados, de los colaterales dentro del segundo, o de los afines en el primero, en contra alguna de las partes, o no haya pasado un año de haber seguido, un juicio civil o una causa penal, como acusadores, querellantes o denunciantes, o se hayan constituido parte civil en causa penal seguida contra cualquiera de ellas;\n.\n.\nActualización Legislativa. Ultima reforma P.O. No. 53, Secc. I, 20-Nov-2015\nVII.- Haya sido denunciado o acusado por alguna de las partes o sus representantes o abogados, o a su cónyuge, o se hayan constituido parte civil en causa penal seguida en su contra;\nVIII.- Tenga parentesco de consanguinidad dentro del cuarto grado o de afinidad dentro del segundo con cualquiera de los interesados, con los administradores o accionistas de las personas morales interesadas o con los asesores, representantes, abogados o personas autorizadas que intervengan en el procedimiento;\nIX.- Intervenga como perito o como testigo en el procedimiento administrativo;\nX.- Tenga alguna relación de amistad estrecha, agradecimiento o compromiso por anteriores actividades laborales con las personas físicas o morales interesadas directamente en el asunto o, en su caso, enemistad manifiesta;\nXI.- Sea tutor o curador de alguno de los interesados y no hayan transcurrido tres años de haber ejercido dicho encargo, o\nXII.- Por cualquier otra causa prevista en los ordenamientos jurídicos aplicables.\nARTÍCULO 34.- El servidor público que se encuentre en alguno de los supuestos que señala el artículo anterior, se excusará de intervenir en el procedimiento sin demora, y lo comunicará a su superior jerárquico inmediato o al titular de la autoridad, quien resolverá lo conducente dentro de los tres días hábiles siguientes.\nARTÍCULO 35.- En el caso de que se declare procedente la excusa planteada, el superior jerárquico inmediato o el titular de la autoridad, en su caso, designará al servidor público que conocerá del asunto, quien habrá de tener la misma jerarquía del impedido.\nSi no existiera servidor público de igual jerarquía al impedido, el superior jerárquico inmediato o el titular de la autoridad, substanciará y resolverá el asunto.\nARTÍCULO 36.- Cuando el superior jerárquico inmediato o el titular de la autoridad, tenga conocimiento que alguno de sus subalternos se encuentra en alguno de los supuestos que establece el artículo 33 de esta Ley, ordenará que se abstenga de intervenir en el procedimiento.\nARTÍCULO 37.- Cuando el servidor público no se abstenga de intervenir en un asunto, a pesar de encontrarse en alguno de los supuestos que establece el artículo 33 de ésta Ley, y sin perjuicio de la responsabilidad en que haya incurrido, el interesado podrá promover la recusación en cualquier\n.\n.\nActualización Legislativa. Ultima reforma P.O. No. 53, Secc. I, 20-Nov-2015 momento de la secuela del procedimiento administrativo, siempre que no se haya emitido la resolución correspondiente.\nEl particular interesado tendrá 1a posibilidad de alegar la recusación al interponer el recurso de revocación en contra de la resolución que ponga fin al procedimiento.\nARTÍCULO 38.- La recusación deberá plantearse por escrito ante el superior jerárquico inmediato del servidor público que se recusa o al titular de la autoridad a la que pertenece. En este escrito se expresará la causa o causas en que se funde el impedimento, debiéndose ofrecer en el mismo los medios probatorios pertinentes, excepto la confesional a cargo de la autoridad y las que sean contrarias a la moral, el derecho o las buenas costumbres.\nAl día siguiente de la presentación del escrito en los términos del párrafo anterior, el servidor público que se recusa será emplazado para que en el plazo de dos días haga las manifestaciones que estime pertinentes. Transcurrido este plazo, haya o no producido el servidor público su informe, el superior jerárquico inmediato o el titular de la autoridad, señalará la fecha de la audiencia para desahogar pruebas, recibir alegatos y pronunciar la resolución, la que deberá emitirse en un plazo de siete días.\nARTÍCULO 39.- En el caso de que la recusación sea procedente y fundada, la resolución respectiva señalará el servidor público que deba sustituir al recusado en el conocimiento y substanciación del procedimiento administrativo.\nARTÍCULO 40.- En el caso de que se declare improcedente la excusa planteada, el superior jerárquico inmediato o el titular de la autoridad, devolverá el expediente para que el servidor público continúe conociendo del mismo.\nDeclarada improcedente o no probada la causa de recusación que se hubiere alegado, el recusante no podrá volver a hacer alguna otra causa de recusación en ese procedimiento, a menos que sea superveniente o que en su defecto, se haya cambiado de servidor público, en cuyo caso podrá hacer valer la causal de impedimento respecto a éste.\nARTÍCULO 41.- La intervención del servidor público que se encuentre en alguno de los supuestos del artículo 33 de esta Ley, no implicará la invalidez de los actos administrativos en que haya intervenido, cuando estos sean favorables al particular, pero en todo caso dará lugar a responsabilidad administrativa, en los términos de esta Ley o de las normas aplicables.\nARTÍCULO 42.- En los casos en que se esté conociendo de algún impedimento, el procedimiento en el cual se haya presentado la excusa o la recusación, se suspenderá hasta en tanto se resuelve sobre ellas.\n.\n.\nActualización Legislativa. Ultima reforma P.O. No. 53, Secc. I, 20-Nov-2015\nARTÍCULO 43.- Contra las resoluciones pronunciadas en materia de impedimentos, excusas y recusaciones no procederá recurso alguno.\nCAPITULO IV\nDE LAS ACTUACIONES Y LOS PLAZOS\nARTÍCULO 44.- Las actuaciones y promociones se practicarán en días y horas hábiles. No son días hábiles los sábados, domingos, aquellos que se señalen en el calendario oficial correspondiente y en los que por cualquier motivo se suspendan actividades en la Administración Pública.\nSe entiende por horas hábiles las comprendidas entre las ocho y las diecisiete horas.\nARTÍCULO 45.- Las autoridades podrán habilitar días y horas inhábiles, Cuando hubiere causa justificada que lo exija. En el Acuerdo que al efecto se expida, se expresará la causa de la habilitación y las diligencias que habrán de practicarse, el cual se notificará personalmente a los interesados.\nARTICULO 46.- Cuando por cualquier circunstancia no se lleve a cabo una actuación o diligencia en el día y hora señalados, las autoridades harán constar la razón por la que no se practicó.\nARTÍCULO 47.- Las diligencias que se inicien en días y horas hábiles, pueden, continuarse hasta su fin sin interrupción y sin necesidad de habilitación expresa.\nARTÍCULO 48.- Para la fijación y cómputo de los plazos y términos se observará lo previsto en esta Ley.\nPara la práctica de las notificaciones, citaciones emplazamientos, requerimientos, visitas de inspección o verificación e informes, a falta de administrativas, se harán en tres días hábiles.\nARTÍCULO 49.- Los plazos comenzarán a correr a partir del día siguiente a aquel en que surta efectos la notificación del acto.\nARTÍCULO 50.- Los plazos y términos serán perentorios. Una vez derecho que dentro de ellos debió ejercitarse.\nARTÍCULO 51.- En los plazos establecidos por períodos se computarán todos los días; cuando se fijen por mes o por año, se entenderá que el plazo\n.\n.\nActualización Legislativa. Ultima reforma P.O. No. 53, Secc. I, 20-Nov-2015 concluye el mismo número del día del mes o año del calendario que corresponda, respectivamente; cuando no exista el mismo número de día en el mes de calendario correspondiente, el término será el primer día hábil del siguiente mes de calendario.\nSi el último día del plazo o la fecha determinada son inhábiles o las oficinas ante las que se vaya a hacer el trámite permanecen cerradas durante el horario normal de labores, se prorrogará el plazo hasta el siguiente día hábil.\nCAPITULO V\nDE LAS NOTIFICACIONES\nARTÍCULO 52.- Las notificaciones se harán: personalmente, por correo certificado, por edictos y por estrados.\nCuando el acto que se pretende notificar al interesado, no imponga una carga procedimental o un deber o derecho, este podrá ser notificado por mensajería, telegrama ó telefax, u otro medio electrónico.\nARTÍCULO 53.- Toda notificación deberá contener un extracto del acto, así como el fundamento legal en que se apoye y el recurso administrativo que proceda.\nARTÍCULO 54.- Se notificarán personalmente a los interesados:\nI.- La primera notificación en el asunto;\nII.- La resolución definitiva y las interlocutorias que se dicten en el procedimiento;\nIII.- El requerimiento de un acto a la parte que deba cumplirlo;\nIV.- Cuando se trate de caso urgente y así lo califique la autoridad;\nV.- La primera resolución que se dicte cuando por cualquier motivo se hubiere dejado de actuar durante más de dos meses, y\nVI.- En los demás casos que lo disponga la Ley.\nARTICULO 55.- Las notificaciones personales se practicaran en el domicilio que para tal efecto designe el interesado, o en el último domicilio que trate o, bien mediante comparecencia del interesado a la oficina administrativa de que se trate.\n.\n.\nActualización Legislativa. Ultima reforma P.O. No. 53, Secc. I, 20-Nov-2015\nARTÍCULO 56.- La primera notificación deberá hacerse de manera personal, en el domicilio que haya sido designado para tal efecto, al interesado notificador dejará citatorio con cualquier persona mayor de edad que se encuentre en el domicilio, para que el interesado le espere a hora fija del día siguiente que se indique en el citatorio. Si el domicilio se encontrare cerrado y nadie respondiera al llamado del notificador para atender la diligencia, el citatorio se dejará con el vecino más próximo.\nSi a pesar del citatorio a que se refiere el párrafo anterior, el interesado no espera al notificador en la fecha y hora indicados, deberá practicarse la notificación con cualquier persona mayor de edad que se encuentre en el domicilio y de negarse ésta a recibirla o en caso de encontrarse cerrado el domicilio, se realizará por cédula que se fijará en Lugar visible del domicilio.\nDe estas diligencias, el notificador asentará en el expediente, razón por escrito.\nARTÍCULO 57.- Si el interesado o, su representante legal, se encuentra presente a la primera búsqueda, el notificado procederá a entender con éste la notificación, entregándole cédula de notificación personal que contenga la trascripción de la resolución que se notifique.\nEn todo caso y antes de proceder a practicar la notificación, el notificador deberá cerciorarse de la identidad y domicilio del interesado, debiendo levantar razón, anotando las circunstancias que hayan llevado a tal dercioramiento, recabando la firma huella digital de la persona con quien se entienda la diligencia o bien, la anotación de que no quiso, no pudo o se negó a firma, lo que se hará constar en el acta citada, sin que estas circunstancias afecten la validez de dicha acta y de la propia notificación.\nARTÍCULO 58.- Con excepción de la primera notificación personal y si no se encuentra en el domicilio al interesado o a su representante legal, las ulteriores notificaciones personales serán practicadas sin necesidad de que se entregue citatorio, con cualquier persona mayor de edad que se encuentre en el domicilio.\nARTÍCULO 59.- Las notificaciones deberán practicarse por la persona efectuarse en días y horas hábiles, salvo lo dispuesto por el artículo 45 de esta\nLey, con una anticipación de cuarenta y ocho horas, por lo menos, al momento en que deba efectuarse la actuación o diligencia que se notifique.\nARTÍCULO 60.- Procede la notificación por correo certificado cuando:\nI.- Se trate de citar a peritos, testigos o terceros que no constituyan parte por disposición expresa de la Ley;\n.\n.\nActualización Legislativa. Ultima reforma P.O. No. 53, Secc. I, 20-Nov-2015\nII.- Cuando se trate de actuaciones de trámite, y\nIII.- En los demás casos previstos en la Ley.\nLa notificación por correo certificado se hará a costa del promovente, siendo requisito indispensable recabar y exhibir ante la autoridad competente, el acuse de recibo que corresponda.\nARTÍCULO 61.- Procede la notificación por edictos cuando:\nI.- Se trate de personas inciertas o que hayan desaparecido;\nII.- Se desconozca el domicilio del interesado;\nIII.- El interesado que haya de notificarse se encuentre en el extranjero sin haber dejado representante legal, y\nIV.- En los demás casos previstos por la Ley.\nLas notificaciones por edictos se efectuarán mediante publicaciones que contendrán un resumen dé las actuaciones por noticiar. Dichas publicaciones se harán por tres veces, de tires en tres días, en el Periódico Oficial del Estado y en un diario de los de mayor circulación en la entidad, advirtiendo a| citado y siempre que se trate de primera citación, que deberá presentarse a la oficina de la autoridad correspondiente en un plazo no menor de cinco ni mayor de quince días hábiles, a partir de la fecha de la última publicación.\nARTÍCULO 62.- Procede la notificación por estrados cuando no se haya señalado domicilio o bien cuando el señalado resultare falso.\nAl efecto se fijará a la vista del público una lista dentro de las instalaciones de que se trate, debiendo ser autorizada con firma y sello; no deberá contener alteraciones o entrerrenglonados ni repetición de números y contendrá el nombre de las partes, el número de expediente y un extracto de la resolución.\nAdicionalmente, todos los acuerdos, resoluciones definitivas e interlocutorias que dicte la autoridad dentro del procedimiento administrativo, deberán publicarse en la lista a que se refiere este artículo.\nARTÍCULO 63.- Las notificaciones surtirán sus efectos:\nI.- Las personales, a partir del día hábil siguiente a la fecha en que fueren practicadas;\nII.- Las que se efectúen por correo certificado, desde el día hábil siguiente a la fecha que se consigne en el acuse de recibo respectivo;\n.\n.\nActualización Legislativa. Ultima reforma P.O. No. 53, Secc. I, 20-Nov-2015\nIII.- Las que se hagan por edictos, desde el día hábil posterior al de la última publicación, y\nIV.- El día hábil siguiente en que el interesado o su representante se haga sabedor de la notificación omitida o irregular. Las notificaciones irregulares se convalidan cuando el interesado se manifieste sabedor del contenido del documento que se notifica.\nARTÍCULO 64.- Las notificaciones o citaciones serán nulas cuando no se verifiquen en la forma prevista por esta Ley. La nulidad se tramitará siguiendo las reglas establecidas en el artículo 65 de esta Ley e interponiéndose el recurso de revocación. Se concederá plazo probatorio solamente cuando la irregularidad no se derive de datos que aparezcan en el expediente. La resolución que declare nula la notificación o citación, determinará el alcance de la nulidad respecto de las demás actuaciones del procedimiento. La autoridad sancionará a los servidores públicos o a los interesados que aparezcan como responsables de la irregularidad.\nARTÍCULO 65.- Cuando se alegue que un acto o resolución no fue notificado o que lo fue ilegalmente, el interesado podrá hacer valer el recurso de revocación previsto en esta Ley y en lo conducente observar las reglas siguientes:\nI.- Si el interesado afirma conocer el acto administrativo materia de notificación, la impugnación contra la misma se hará valer mediante la interposición del recurso de revocación, en el que manifestará la fecha en que lo conoció. En caso de que también impugne el acto, los agravios se expresarán en el citado recurso, conjuntamente con los que se formulen contra la notificación.\nII.- Si el interesado niega conocer el acto, lo manifestará al interponer el recurso de revocación ante la autoridades competente para notificar dicho acto.\nLa autoridad dará a conocer al interesado, el acto junto con la notificación que del mismo se hubiera practicado, para lo cual éste señalará en el escrito de interposición del recurso de revocación, el domicilio en que se le deba dar a conocer y el nombre de la persona autorizada para recibirlo, en su caso. Si no hace señalamiento de domicilio, la autoridad le dará a conocer el acto por estrados. aquél en que la autoridad se lo haya dado a conocer, para ampliar el recurso de revocación, impugnando el acto y su notificación, o cualquiera de ellos, según sea el caso.\nIII.- La autoridad competente para resolver el recurso de revocación, estudiará los agravios expresados contra la notificación, previamente al examen de la impugnación que, en su caso, se haya hecho del acto administrativo, debiendo resolver el recurso dentro de los cuarenta y cinco días siguientes a la fecha de su interposición.\n.\n.\nActualización Legislativa. Ultima reforma P.O. No. 53, Secc. I, 20-Nov-2015\nIV.- Si se resuelve que no hubo notificación o que fue ilegal, se tendrá al recurrente como sabedor del acto o resolución desde la fecha en que manifestó conocerlo, o en que se le dio a conocer en los términos de la fracción II de este artículo, quedando sin efectos todo lo actuado con base en aquella y se procederá, en su caso, al estudio de la impugnación que se hubiese formulado contra dicho acto, y\nV.- Si se resuelve que la notificación fue legalmente practicada y, como consecuencia de ello, la impugnación contra el acto se interpuso extemporáneamente, se desechará el recurso.\nCAPÍTULO VI\nDE LA INICIACIÓN Y TRAMITACIÓN DEL PROCEDIMIENTO\nADMINISTRATIVO\nARTÍCULO 66.- El procedimiento administrativo puede iniciarse de oficio\nEl procedimiento de oficio puede iniciar por acuerdo de la autoridad competente o denuncia de particulares.\nCuando el procedimiento administrativo inicie a petición de parto y la Ley de la materia no señale los requisitos específicos, el escrito inicial deberá cumplir con los siguientes:\nI.- La autoridad a la que se dirige;\nII.- El nombre, denominación o razón social del interesado y, en su caso, nombre del representante legal, agregándose los documentos que acrediten la personería, así como la designación de la persona o personas autorizadas para oír y recibir notificaciones y documentos;\nIII.- El domicilio para recibir notificaciones;\nIV.- La petición que se formula;\nV.- La descripción clara y sucinta de los hechos y razones en los que se apoye la petición;\nVI.- Las documentales necesarias para la tramitación del asunto de que se trate y,\nVII.- El lugar, fecha y firma del interesado o, en su caso, la de su representante o apoderado legal.\nEl procedimiento a petición de parte, debe ser promovido por interesado que puede ser persona física o jurídica, pública o privada, que invoco un derecho subjetivo o un interés legítimo.\n.\n.\nActualización Legislativa. Ultima reforma P.O. No. 53, Secc. I, 20-Nov-2015\nARTÍCULO 67.- Cuando el escrito inicial no contenga los requisitos o no se acompañe de los documentos previstos en el artículo anterior, la autoridad prevendrá por escrito y por una sola vez al interesado o, en su caso, a su representante o apoderado legal, para que dentro del plazo de cinco días siguientes al en que surta efectos la notificación de dicha prevención, subsánela falta. En el supuesto de que en el plazo señalado no se cumpla con la prevención, la autoridad resolverá que se tiene por no presentada la solicitud.\nContra el desechamiento o la negativa de dar trámite a las solicitudes o promociones, procederá el recurso de revocación.\nARTÍCULO 68.- Los escritos iniciales deberán presentarse en las unidades receptoras de documentos de la autoridad; las subsecuentes promociones, en el caso de que el interesado resida en lugar distinto de aquellas, podrá enviarlas vía correo registrado con acuse de recibo, siempre que el envío se efectúe desde el lugar en que resida el interesado.\nARTÍCULO 69.- Cuando un escrito sea presentado ante una autoridad incompetente, dicha autoridad deberá rechazar la promoción de plano, indicando al promovente ante quien debe presentarlo.\nARTÍCULO 70.- Los escritos que se reciban vía correo registrado con acuse de recibo, se considerarán presentados en la fecha que los reciba la autoridad competente, salvo que se trate del desahogo de requerimientos o de promociones sujetas a termino, en cuyo caso se tendrá como fecha de presentación aquélla en que se depositen en la oficina de correos.\nARTÍCULO 71.- En ningún caso se podrán rechazar los escritos que se presenten en las unidades receptoras de documentos de las autoridades competentes. Será causa de responsabilidad administrativa para el servidor público de la autoridad competente, la negativa a recibir las promociones de los particulares.\nARTÍCULO 72.- Para el adecuado control de los asuntos que se substancien a través de procedimientos administrativos, se establecerá un sistema de identificación de los expedientes que comprenda, entre otros datos, los relativos al número progresivo, al año y la clave de la materia que corresponda, mismos que deberán ser registrados en un Libro de Gobierno que para tal efecto deberá crearse. Asimismo, se deberán agregar al expediente las constancias de notificación, los acuses de recibo y todos los documentos aportados como pruebas, así como aquellos en que consten las diligencias practicadas en el procedimiento.\n.\n.\nActualización Legislativa. Ultima reforma P.O. No. 53, Secc. I, 20-Nov-2015\nARTICULO 73.- En el despacho de los asuntos se deberá observar un orden riguroso en la tramitación de los expedientes de la misma naturaleza, que únicamente podrán modificarse cuando exista causa de orden público debidamente fundada y motivada, de la que quede constancia en el expediente. El incumplimiento de esta disposición será causa de responsabilidad para el servidor público que conozca del procedimiento.\nARTÍCULO 74.- Iniciado el procedimiento, la autoridad, a fin de asegurar la eficacia de la resolución que pudiera recaer, podrá adoptar las medidas provisionales establecidas en ésta Ley u otras normas aplicables, siempre que existieren elementos suficientes.\nARTICULO 75.- En las promociones, actuaciones o resoluciones del procedimiento administrativo podrán utilizarse formas impresas autorizadas previamente y publicadas en el Periódico Oficial del Estado, las cuales serán distribuidas gratuitamente por las autoridades. En caso de no existir formas, autorizadas, las promociones se presentarán en escrito libre.\nARTÍCULO 76.- Cuando así lo establezcan las normas aplicables o se considere conveniente, la autoridad que conozca del procedimiento administrativo solicitará de las demás autoridades, informes u opiniones necesarios para resolver el asunto, citándose el precepto normativo que así lo establezca o motivando, en su caso, la conveniencia de solicitarlos.\nLos informes u opiniones solicitados a que se refiere el párrafo anterior, podrán ser obligatorios o facultativos, vinculantes o no. Salvo disposición legal en contrario, los informes y opiniones serán facultativos y no vinculantes para la autoridad que los solicitó y deberán incorporarse al expediente.\nEl servidor público al que se le solicite un informe u opinión, deberá emitirlo dentro del plazo de diez días, salvo disposición que establezca otro plazo. Si transcurrido dicho plazo, no se recibiese el informe u opinión, cuando se trate de aquellos de carácter obligatorio o vinculante, se entenderá que no existe objeción a las pretensiones del interesado.\nARTÍCULO 77.- Con el escrito inicial se deberán ofrecer documentales, siempre que la naturaleza del asunto así lo exija y lo prescriban las normas.\nCuando en los ordenamientos jurídicos aplicables, no esté detallado expresamente el debido proceso legal, se seguirá el procedimiento administrativo que se establece en esta Ley. iniciación del procedimiento, sobre la admisión o desechamiento de las documentales acompañadas. En caso de desechamiento se le notificara personalmente al interesado, dentro de los diez días hábiles siguientes al en que se haya decretado el desechamiento.\n.\n.\nActualización Legislativa. Ultima reforma P.O. No. 53, Secc. I, 20-Nov-2015\nContra el desechamiento de documentales no procederá recurso alguno, sin perjuicio de que esta circunstancia se pueda alegar al impugnarse la resolución administrativa.\nCAPÍTULO VII\nDE LA TERMINACIÓN DEL PROCEDIMIENTO ADMINISTRATIVO\nARTÍCULO 78.- Ponen fin al procedimiento administrativo:\nI.- La resolución definitiva;\nII.- El desistimiento;\nIII.- La imposibilidad material de continuarlo por causas supervenientes;\nIV.- La configuración de la positiva ficta, y\nV.- La declaración de la caducidad, cuando se trate se procedimientos administrativos iniciados por el interesado y que requieran impulso. La autoridad, podrá citar la caducidad del asunto y darlo por terminado, si transcurridos tres meses, no se ha producido actuación del interesado.\nARTÍCULO 79:- La resolución que ponga fin al procedimiento contendrá:\nI.- Lugar y fecha de emisión;\nII.- El nombre de la persona a la que se dirija; cuando éste se ignore, se señalarán los datos suficientes para su identificación;\nIII.- La decisión de todas las cuestiones planteadas o previstas por las normas, en su caso;\nIV.- Los fundamentos y motivos que la sustente;\nV.- Los puntos decisorios, y\nVI.- El nombre, cargo y firma autógrafa de la autoridad que la emita;\nARTÍCULO 80.- Los actos administrativos serán ejecutados por las autoridades en términos de Ley; salvó en los casos en que se otorgue legalmente la suspensión. Para la ejecución de los actos, la autoridad deberá notificar a los interesados el mandamiento que la autorice.\nARTÍCULO 81.- Todo interesado podrá desistirse del procedimiento administrativo que promueva cuando sólo afecte a sus intereses. En caso que existan varios interesados, el desistimiento sólo operará respecto de quien lo hubiese formulado.\n.\n.\nActualización Legislativa. Ultima reforma P.O. No. 53, Secc. I, 20-Nov-2015\nARTÍCULO 82.- El desistimiento deberá ser presentado por escrito, ya sea por el interesado, su representante legal o su apoderado con facultades para ello; y para que produzca efectos jurídicos tendrá que ser ratificado por comparecencia ante la autoridad que conozca del procedimiento, dentro de los tres días hábiles siguientes a su presentación.\nARTÍCULO 83.- Cuando se trate de autorizaciones, licencias o permisos, las autoridades deberán resolver el procedimiento administrativo correspondiente, en los términos previstos por las normas aplicables; y sólo que éstos no contemplen un plazo específico, deberá resolverse dentro de los cuarenta y cinco días hábiles siguientes, contados a partir de la presentación de la solicitud.\nEn estos casos, si la autoridad no emite su resolución dentro de los plazos establecidos, habiendo el interesado cumplido los requisitos que escriben las normas aplicables, el silencio se entenderá como negativa ficta.\nARTÍCULO 84.- Las resoluciones definitivas decidirán no sólo las cuestiones planteadas por las partes, sino también las derivadas del expediente.\nCuando se trate de cuestiones conexas que no hubieran sido planteadas, las autoridades podrán pronunciarse sobre ellas, previa vista a los interesados por el plazo de cinco días para que formulen lo que a su derecho convenga y aporten, en su caso, los medios de prueba que consideren oportunos.\nARTÍCULO 85.- La resolución que recaiga al procedimiento administrativo promovido por el interesado, en ningún caso agravara su situación inicial.\nARTÍCULO 86.- Las resoluciones dictadas en el procedimiento administrativo, expresarán los recursos o medios de defensa que procedan contra las mismas.\nARTÍCULO 87.- Las autoridades en ningún caso podrán dejar en estado de resolución los expedientes bajo pretexto de silencio, oscuridad o insuficiencia de los preceptos legales invocados por los interesados.\nARTÍCULO 88.- Las autoridades no podrán variar ni modificar sus resoluciones después de dictadas y firmadas. No obstante, cuando se trate de precisar algún concepto o suplir alguna emisión, lo podrán hacer de oficio, dentro del día hábil siguiente a la notificación correspondiente, o a petición de parte interesada por escrito presentado dentro del mismo plazo, devolviéndose\n.\n.\nActualización Legislativa. Ultima reforma P.O. No. 53, Secc. I, 20-Nov-2015 lo que se estime procedente dentro del día siguiente a la presentación del escrito.\nARTÍCULO 89.- Al hacer la aclaración, las autoridades, no podrán modificar los elementos esenciales de la resolución, ni variar su sustancia. El acuerdo que decida la aclaración de una resolución, se considerará parte integrante de ésta. Se tendrá como fecha de notificación de la resolución, la del acuerdo que decida la aclaración de la misma.\nTÍTULO CUARTO\nDE LAS VISITAS DE INSPECCIÓN Y VERIFICACIÓN\nCAPÍTULO ÚNICO\nARTÍCULO 90.- La autoridad, para comprobar el cumplimiento de las disposiciones legales y reglamentarias, de carácter administrativo podrá llevar a cabo visitas de inspección y verificación, mismas que podrán ser ordinarias y extraordinarias; las primeras se efectuarán en días y horas hábiles, y las segundas en cualquier tiempo.\nARTÍCULO 91.- Los inspectores y verificadores, para practicar visitas, deberán estar provistos de orden escrita con firma autógrafa expedida por la autoridad competente, en la que deberá precisarse el nombre de la persona respecto de la cual se ordena la visita, el lugar o zona que ha de verificarse o inspeccionarse, el objeto de la visita, el alcance que deba tener y las disposiciones legales que lo fundamenten.\nARTÍCULO 92.- Los propietarios, responsables, encargados u ocupantes de establecimientos objeto de inspección o verificación estarán obligados a permitir el acceso y dar facilidades e informes a los inspectores y verificadores para el desarrollo de su labor.\nARTÍCULO 93.- Al iniciar la visita, el inspector o verificador deberá exhibir credencial vigente con fotografía, expedida por la autoridad competente que lo acredite para desempeñar dicha función, así como la orden expresa a la que se refiere el artículo 91 de esta Ley, de la que deberá dejar copia al propietario, responsable, encargado u ocupante del establecimiento.\nARTÍCULO 94.- De toda visita de inspección y verificación se levantará acta circunstanciada, en presencia de dos testigos propuestos por la persona se hubiere negado a proponerlos. diligencia, aunque se hubiere negado a firmar, lo que no afectará la validez de\n.\n.\nActualización Legislativa. Ultima reforma P.O. No. 53, Secc. I, 20-Nov-2015 la diligencia ni del documento de que se trate, siempre y cuando el inspector o verificador haga constar tal circunstancia en la propia acta.\nARTÍCULO 95.- En las actas se hará constar:\nI.- Nombre, denominación o razón social del visitado;\nII.- Hora, día, mes y año en que inicie y concluya la diligencia;\nIII.- Calle y número, población o colonia, teléfono u otra forma de comunicación disponible, municipio o delegación en que se encuentre ubicado el lugar en que se practique la visita, y el código postal;\nIV.- Número y fecha del oficio de comisión que la motivo;\nV.- Nombre y cargo de la persona con quien se entendió la diligencia;\nVI.- Nombre y domicilio de las personas que fungieron como testigos;\nVII.- Datos relativos a la actuación;\nVIII.- Declaración de quien conoce de la diligencia de que se trate, si quisiera hacerla, y\nIX.- Nombre y firma de quienes intervinieron en la diligencia incluyendo los de quien o quienes la hubieren llevado a cabo. Si se negaren a firmar la persona señalada para recibir la diligencia de que se trate o su representante legal, ello no afectará la validez del acta, debiendo el inspector o verificador asentar la razón relativa e informando de esta circunstancia a quienes se nieguen a firmar.\nARTÍCULO 96.- Los particulares a quienes se haya levantado acta de inspección o verificación podrán formular objeciones al acto de la diligencia y ofrecer pruebas en relación a los hechos contenidos en ella, o bien, por escrito, hacer uso de ese derecho dentro del término de cinco días siguientes a la fecha en que se hubiere levantado.\nARTÍCULO 97.- Las autoridades podrán, de conformidad con las disposiciones aplicables, inspeccionar y verificar bienes, personas y vehículos legales, para lo cual se deberán cumplir, en lo conducente, las formalidades previstas para las visitas de inspección y verificación.\nTÍTULO QUINTO\nDEL RECURSO DE REVOCACIÓN\nCAPÍTULO ÚNICO\n.\n.\nActualización Legislativa. Ultima reforma P.O. No. 53, Secc. I, 20-Nov-2015\nARTÍCULO 98.- Los interesados afectados por los actos o resoluciones de las autoridades, así como por los dictados en el procedimiento de ejecución o por actos recurribles que no hayan sido notificados o que se hayan notificado sin apego a lo dispuesto en esta Ley, podrán interponer el recurso de revocación previsto en este Título.\nARTÍCULO 99.- El plazo para interponer el recurso de revocación será de quince días hábiles, contados a partir del día siguiente a aquel en que surta sus efectos la notificación de la resolución que se recurra, o de que el recurrente tenga conocimiento de dicha resolución.\nEn el caso de que se impugne un acto que no haya sido notificado o que lo haya sido en contravención a lo dispuesto en esta Ley, se observarán las reglas establecidas en el artículo 65 de esta Ley.\nARTÍCULO 100.-El recurso de revocación deberá presentarse ante la autoridad que emitió el acto o resolución.\nARTÍCULO 101.- En el escrito de interposición del recurso de revocación, el interesado deberá cumplir con los requisitos previstos en el artículo 66 de esta Ley, señalando además:\nI.- La autoridad a quien se dirige;\nII.- El nombre del recurrente, y en su caso, de quien promueve en su nombre; del tercero perjudicado si lo hubiere, así como el domicilio que señale para oír y recibir notificaciones y documentos;\nIII.- El acto o resolución administrativa que impugna, así como la fecha en que le fue notificada o, en su caso, la declaratoria bajo protesta de decir verdad de la fecha en que tuvo conocimiento del acto o resolución;\nIV.- La autoridad emisora del acto o resolución que recurre;\nV.- La descripción de los hechos que son antecedentes del acto o resolución que recurre;\nVI.- Los agravios que le causan y los argumentos de derecho que se hagan valer en contra del acto o resolución recurridas, y\nVII.- Las pruebas que se ofrezcan relacionándolas con los hechos que se mencionen.\nARTÍCULO 102.- Con el escrito de interposición del recurso de revocación se deberán acompañar:\n.\n.\nActualización Legislativa. Ultima reforma P.O. No. 53, Secc. I, 20-Nov-2015\nI.- Los documentos que acrediten la personería del promovente, cual lo actúe a nombre de otro o de persona moral;\nII.- El documento en que conste el acto o la resolución recurrida, cuando dicha actuación haya sido por escrito;\nIII.- La constancias de notificación del acto impugnado, o la última publicación si la notificación hubiese sido por edictos, excepto cuando el recurrente declare bajo protesta de decir verdad que no se le notificó o que no la recibió, y\nIV.- Las pruebas que se ofrezcan o la constancia documental en donde se asiente que se solicitó ante la autoridad correspondiente, con tres días de anticipación, los documentos públicos necesarios para acompañar al recurso.\nARTÍCULO 103.- A fin de que las partes puedan rendir sus pruebas, los servidores de la autoridad tienen la obligación de expedir las copias de los documentos que les soliciten los interesados; si no se cumpliera con esta obligación, el recurrente solicitará a la autoridad ante la que impugna que requiera a los omisos.\nCuando sin causa justificada la autoridad requerida no expida las copias de las documentales requeridas para probar los actos reclamados y, siempre y cuando los documentos solicitados hubieran sido identificados con toda precisión, tanto en sus características como en su contenido, se presumirán ciertos los hechos que se pretendan probar con esos documentos, sin perjuicio de las responsabilidades en que incurra el servidor público responsable.\nARTÍCULO 104.- En caso de que el recurrente no cumpliera con alguno de los requisitos anteriores o no acompañe los documentos que se señalan en los dos artículos precedentes, la autoridad que conozca del recurso, deberá prevenirlo por escrito por una sola vez para que en un plazo de cinco días subsecuentes a la notificación personal, subsane la omisión. Si transcurrido este plazo el recurrente no desahoga en sus términos la prevención, el recurso se tendrá por no interpuesto. interesado, o por quien deba hacerlo, se tendrá por no interpuesto.\nARTÍCULO 105.- El interesado podrá solicitar por escrito la suspensión de la ejecución del acto o de la resolución recurrida, en cualquier momento hasta antes de que se resuelva el recurso. dentro de los cinco días siguientes a la solicitud.\n.\n.\nActualización Legislativa. Ultima reforma P.O. No. 53, Secc. I, 20-Nov-2015\nARTÍCULO 106.- La autoridad que conozca del recurso, al resolver sobre la solicitud de suspensión deberá señalar, en su caso, las garantías necesarias para cubrir los daños y perjuicios que pudieran ocasionarse con dicha medida.\nEn los casos que proceda la suspensión, pero su otorgamiento pueda ocasionar daños o perjuicios a terceros, el interesado deberá otorgar garantía bastante para reparar el daño e indemnizar los perjuicios que pudieran ocasionarse con dicha medida;\nARTÍCULO 107.- No se otorgará la suspensión en aquellos casos en que se cause perjuicio al interés social, se contravengan disposiciones de orden público o se deje sin materia el procedimiento.\nARTÍCULO 108.- La suspensión tendrá como efecto que las cosas se mantengan en el estado en que se encuentran, en tanto se pronuncia la resolución del recurso. Dicha suspensión podrá revocarse si se modifican las condiciones bajo las cuales se otorgó.\nARTÍCULO 109.- Una vez recibido el recurso la autoridad procederá de la manera siguiente:\nI.- Requerir al servidor público que autorizó o emitió el acto recurrido, para que en un plazo no mayor de tres días entregue un informe del acto recurrido y, en su caso, presente las pruebas que se relacionen con el acto impugnado, y\nII.- Emitir acuerdo sobre la admisión, prevención o desechamiento del recurso, en un plazo no mayor de cinco días siguientes contados a partir de la recepción del informe. Dicho acuerdo, deberá notificarse personalmente al recurrente.\nARTÍCULO 110.- Se desechará por improcedente el recurso cuando se interponga en contra de actos o resoluciones:\nI.- Que no afecten el interés jurídico o legítimo del recurrente;\nII.- Que sean dictadas en recursos administrativos o en cumplimiento de éstas o de resoluciones ejecutivas;\nIII.- Cuando tratándose de lo previsto por la fracción II del artículo 65 de ésta Ley, no se ampliase el recurso administrativo o si en la ampliación no se expresare agravio alguno;\nIV.- Que sean revocados por la autoridad;\n.\n.\nActualización Legislativa. Ultima reforma P.O. No. 53, Secc. I, 20-Nov-2015\nV.- Que sean materia de otro recurso que se encuentre pendiente de resolución y que haya sido promovido por el mismo recurrente por el propio acto impugnado;\nVI.- Que sean consumadas de modo irreparable;\nVII.- Que se hayan consentido, entendiéndose por esto, aquellos respecto de los cuales no se interpuso el recurso de revocación dentro del plazo establecido por esta Ley;\nVIII.- Que sean conexas a otro que haya sido impugnado por algún recurso o medio de impugnación diferente, o\nIX.- Cuando el recurso sea interpuesto fuera del término previsto por esta Ley.\nARTÍCULO 111.- Será sobreseído el recurso cuando:\nI.- El promovente se desista expresamente;\nII.- El recurrente fallezca durante el procedimiento, si el acto o resolución impugnado sólo afecta a su persona;\nIII.- Durante el procedimiento sobrevenga alguna de las causas de improcedencia a que se refiere el artículo anterior;\nIV.- Hayan cesado los efectos del acta impugnado;\nV.- Falte el objeto o materia del acto; o\nVI.- No se aprobare la existencia del acto impugnado.\nARTÍCULO 112.- La autoridad deberá resolver el recurso de revocación dentro de los cuarenta y cinco días siguientes a la fecha de su interposición o partir de aquel en que se hubiera desahogado la prevención a que se refiere el artículo 104 de esta Ley. Ante el silencio de la autoridad, se entenderá por negado el acto reclamado que se impugna.\nEn el caso del párrafo anterior, el recurrente podrá esperar la resolución párrafo precedente, sin perjuicio de las responsabilidades en que incurran los servidores públicos en los términos de la Ley de la materia.\nARTÍCULO 113.- La resolución del recurso se fundará en derecho y examinará todos y cada uno de los agravios hechos valor por el recurrente, teniendo la autoridad la facultad de invocar hechos notorios; pero cuando uno de los agravios sea suficiente para desvirtuar la validez del acto impugnado, bastará con el examen de dicho punto.\n.\n.\nActualización Legislativa. Ultima reforma P.O. No. 53, Secc. I, 20-Nov-2015\nLa autoridad, examinará en su conjunto los agravios, así como los demás razonamientos del recurrente, a fin de resolver la cuestión efectivamente planteada, pero sin cambiar los hechos expuestos en el recurso.\nSi la resolución ordena realizar un determinado acto o iniciar la reposición del procedimiento, deberá cumplirse dentro de un plazo de quince días contados a partir de que se notifique al recurrente dicha resolución.\nARTÍCULO 114.- Las resoluciones que pongan fin al recurso de revocación podrán:\nI.- Declararlo improcedente o sobreerlo;\nII.- Confirmar el acto impugnado;\nIII.- Declarar la nulidad del acto impugnado o revocarlo, o\nIV.- Modificar el acto impugnado, u ordenar o dictar uno nuevo que lo sustituya, cuando el recurso interpuesto sea total o parcialmente resulto a favor del recurrente; u ordenar la reposición del procedimiento administrativo.\nARTÍCULO 115.- No se podrán anular, revocar o modificar los actos o resoluciones administrativas con argumentos que no haya hecho valer el recurrente.\nARTÍCULO 116.- Contra la resolución que recaiga al recurso de revocación procede su impugnación ante el Tribunal de lo Contencioso\nAdministrativo del Estado de Baja California.\nTÍTULO SEXTO\nCAPÍTULO ÚNICO\nARTÍCULO 117.- El incumplimiento a los preceptos contenidos en esta\nLey, será sancionado, según corresponda; por la autoridad competente. reglamentos respectivos, y podrán consistir en;\nI.- Amonestación con apercibimiento;\nII.- Multa;\n.\n.\nActualización Legislativa. Ultima reforma P.O. No. 53, Secc. I, 20-Nov-2015\nIII.- Arresto hasta por 36 horas;\nIV.- Clausura temporal o permanente, parcial o total, y\nV.- Las demás que señalen las leyes o reglamentos.\nARTÍCULO 118.- Sin perjuicio de lo establecido en los ordenamientos jurídicos aplicables, en caso de reincidencia, se duplicará la sanción impuesta por la infracción anterior, sin que su monto exceda del doble del máximo.\nARTÍCULO 119.- Para la imposición de sanciones, salvo las determinadas por la autoridad como urgentes para preservar el interés público, deberá de iniciarse el procedimiento administrativo correspondiente, otorgando oportunidad para que el interesado exponga lo que a su derecho convenga y, en su caso, aporte las pruebas con que cuente.\nARTÍCULO 120.- Las sanciones administrativas podrán imponerse en más de una de las modalidades previstas en el artículo 117 de esta Ley, salvo el arresto.\nARTÍCULO 121.- Incurren en responsabilidad administrativa en términos de la Ley de Responsabilidades de los Servidores Públicos del Estado de Baja\nCalifornia, los encargados de resolver los procedimientos administrativos, que no emiten la resolución definitiva en los plazos previstos en esta Ley o en las especiales que correspondan.\nARTÍCULO 122.- Una vez oído al infractor y desahogadas las pruebas ofrecidas y admitidas, se procederá, dentro de los diez días siguientes, a dictar por escrito la resolución que proceda, la cual será notificada en forma personal o por correo certificado.\nARTÍCULO 123.- La autoridad administrativa fundará y motivará su resolución, considerando para su individualización:\nI.- La gravedad de la infracción en que se incurra;\nII.- Los antecedentes del infractor;\nIII.- Las condiciones socioeconómicas del infractor;\nIV.- La reincidencia en el incumplimiento de obligaciones, en su caso;\nV.- El monto del beneficio, daño o perjuicio económico, derivado del incumplimiento de obligaciones, si lo hubiere,.\n.\nActualización Legislativa. Ultima reforma P.O. No. 53, Secc. I, 20-Nov-2015\nVI.- Los daños que se hubieren producido al interés público o pudieran producirse, y\nVII.- El carácter doloso o no de la acción u omisión constitutiva de la infracción.\nARTÍCULO 124.- Las autoridades competentes harán uso de las medidas necesarias, incluyendo el auxilio de la fuerza pública, para lograr la ejecución de las sanciones que procedan.\nARTÍCULO 125.- Cuando en una misma acta se hagan constar diversas infracciones, en la resolución respectiva, las multas se determinarán separadamente así como el monto total de todas ellas.\nCuando en una misma acta se comprenda a dos o más infractores, a cada uno de ellos se le impondrá la sanción que corresponda.\nARTÍCULO 126.- Las sanciones por infracciones administrativas se impondrán sin perjuicio de las penas que correspondan a los delitos en que, en su caso, incurran los infractores.\nARTÍCULO 127.- La facultad de la autoridad para imponer sanciones administrativas, y en su caso las sanciones impuestas, prescriben en tres años.\nLos términos de la prescripción serán continuos y contarán desde el día en que se cometió la falta o infracción administrativa si fuere consumada, o desde que cesen sus efectos si fuete continúa y, en su caso, a partir de la fecha del acto de autoridad mediante el cual se impuso la sanción.\nLa tramitación de la declaración de prescripción de la sanción por parte de los interesados, no constituirá recurso, ni suspenderá el plazo para la interposición de este; y tampoco suspenderá la ejecución del acto, La autoridad, en beneficio del infractor, podrá decretar de oficio la prescripción de la sanción.\nARTÍCULO 128.- Cuando el infractor impugnare el acto de la autoridad administrativa que impuso la sanción, se interrumpirá la prescripción hasta en tanto la resolución definitiva que se dicte no admita ulterior recurso.\nARTÍCULO PRIMERO.- La presente Ley entrará en vigor al día siguiente de su publicación en el Periódico Oficial del Estado.\n.\n.\nActualización Legislativa. Ultima reforma P.O. No. 53, Secc. I, 20-Nov-2015\nARTÍCULO SEGUNDO.- Los recursos administrativos que se hubieren interpuesto o hechos valer antes de la vigencia de esta Ley, se seguirán tramitando en los términos de las disposiciones legales anteriores hasta su conclusión.\nHonorable Poder Legislativo, en la Ciudad de Mexicali, Baja California, a los quince días del mes de abril del año del dos mil tres.\nDIP. LAURA SANCHEZ MEDRANO\nPRESIDENTA\n(RÚBRICA)\nDIP. MARIA ROSALBA MARTIN NAVARRO\nPROSECRETARIA\n(RÚBRICA)\nDE CONFORMIDAD CON LO DISPUESTO POR LA FRACCÍON I DEL\nY PUBLIQUESE.\nMEXICALI, BAJA CALIFORNIA, A LOS VEINTITRÉS DÍAS DEL MES DE\nJULIO DEL AÑO DOS MIL TRES.\nEUGENIO ELORDUY WALTHER\nGOBERNADOR DEL ESTADO\n(RÚBRICA)\nBERNARDO H. MARTINEZ AGUIRRE\nSECRETARIO GENERAL DE GOBIERNO\n(RÚBRICA)\n.\n.\nActualización Legislativa. Ultima reforma P.O. No. 53, Secc. I, 20-Nov-2015\nARTÍCULO 1.- Fue reformado por Decreto No. 207, publicado en el por la H. XIX Legislatura, siendo Gobernador Constitucional el C. José\nGuadalupe Osuna Millán 2007-2013; fue reformado mediante Decreto No. 359, Tomo CXXII, Sección I, expedido por la H. XXI Legislatura, siendo Gobernador\nConstitucional el C. Francisco Arturo Vega de Lamadrid 2013-2019;\n.\n.\nActualización Legislativa. Ultima reforma P.O. No. 53, Secc. I, 20-Nov-2015\nARTICULO TERCERO TRANSITORIO DEL DECRETO No. 207, POR\nEL QUE SE APRUEBA LA REFORMA AL ARTICULO 1RO, PUBLICADO EN\nEL PERIODICO OFICIAL NO. 12, DE FECHA 06 DE MARZO DE 2009, TOMO\nCXVI, EXPEDIDO POR LA H. XIX LEGISLATURA, SIENDO GOBERNADOR\nCONSTITUCIONAL EL C. JOSE GUADALUPE OSUNA MILLAN 2007-2013.\nTRANSITORIOS\nARTÍCULO PRIMERO.- La presente reforma entrará en vigor al día siguiente de su publicación en el Periódico Oficial del Estado.\nARTÍCULO SEGUNDO.- Se derogan en lo conducente, todas las disposiciones normativas que se opongan a la presente reforma.\nDADO en el Salón de Sesiones “Lic. Benito Juárez García” del H. Poder\nLegislativo del Estado de Baja California, en la Ciudad de Mexicali, B.C., a los veintidós días del mes de enero del año dos mil nueve.\nDIP. GINA ANDREA CRUZ BLACKLEDGE\nPRESIDENTA\n(RÚBRICA)\nDIP. JUAN MANUEL MOLINA GARCÍA\nSECRETARIO\n(RÚBRICA)\nDE CONFORMIDAD CON LO DISPUESTO POR LA FRACCION I DEL\nARTICULO 49 DE LA CONSTITUCION POLITICA DEL ESTADO, IMPRIMASE\nY PUBLIQUESE.\nMEXICALI, BAJA CALIFORNIA, A LOS DIECISÉIS DIAS DEL MES DE\nFEBRERO DEL AÑO DOS MIL NUEVE.\nGOBERNADOR DEL ESTADO\nJOSE GUADALUPE OSUNA MILLAN\n(RÚBRICA)\nSECRETARIO GENERAL DE GOBIERNO\nJOSE FRANCISCO BLAKE MORA\n(RÚBRICA)\nARTÍCULO DECIMO TRANSITORIO DEL DECRETO No. 359, POR EL\nQUE SE REFORMA EL ARTÍCULO 15, PUBLICADO EN EL PERIÓDICO\nOFICIAL No. 53, SECCIÓN I, TOMO CXXII, DE FECHA 20 DE NOVIEMBRE\nDE 2015, EXPEDIDO POR LA H. XXI LEGISLATURA, SIENDO\nGOBERNADOR CONSTITUCIONAL EL C. FRANCISCO ARTURO VEGA DE\nLA MADRID 2013-2019.\n.\n.\nActualización Legislativa. Ultima reforma P.O. No. 53, Secc. I, 20-Nov-2015\nÚNICO.- La presente reforma entrará en vigor al día siguiente de su publicación en el Periódico Oficial del Estado de Baja California.\nDADO en el Salón de Sesiones “Lic. Benito Juárez García” del H. Poder\nLegislativo del Estado de Baja California, en la Ciudad de Mexicali, B.C., a los veintidós días del mes de octubre del año dos mil quince.\nDIP. IRMA MARTÍNEZ MANRÍQUEZ\nPRESIDENTA\n(RÚBRICA)\nDIP. MARIO OSUNA JIMÉNEZ\nSECRETARIO\n(RÚBRICA)\nDE CONFORMIDAD CON LO DISPUESTO POR LA FRACCIÓN I DEL\nY PUBLÍQUESE.\nMEXICALI, BAJA CALIFORNIA, A LOS TREINTA DÍAS DEL MES\nDE OCTUBRE DEL AÑO DOS MIL QUINCE.\nFRANCISCO ARTURO VEGA DE LAMADRID\nGOBERNADOR DEL ESTADO\n(RÚBRICA)\nFRANCISCO RUEDA GÓMEZ\nSECRETARIO GENERAL DE GOBIERNO\n(RÚBRICA)",
  "ordenamiento": "REGLAMENTO",
  "jurisdiccion": "BAJA CALIFORNIA",
  "fuente_oficial": "Periódico Oficial",
  "FECHA PER OFIC": "2015/11/20",
  "ESTATUS": "VIGENTE",
  "TOMO": "TOMO_I",
  "URL": "https://www.congresobc.gob.mx/Documentos/ProcesoParlamentario/Leyes/TOMO_I/LEYACTOSADMON_20NOV2015.PDF",
  "es_escaneado": false,
  "tiene_tablas": false,
  "materia": [
    "administrativo",
    "legislativo",
    "gobernanza"
  ]
}