{
  "titulo": "Ley DE EJERCICIO DE LAS PROFESIONES PARA EL ESTADO DE BAJA CALIFORNIA",
  "Contenido": "LEY DE EJERCICIO DE LAS PROFESIONES PARA EL\nESTADO DE BAJA CALIFORNIA\nPublicado en el Periódico Oficial No. 39,\nCAPITULO I\nDISPOSICIONES GENERALES\nARTICULO 1.- Esta Ley es reglamentaria del Artículo 5º de la Constitución Política de los Estados Unidos Mexicanos, en lo relativo al ejercicio profesional en el Estado de Baja\nCalifornia; sus disposiciones son de orden público, interés social y de observancia general.\nARTICULO 2.- La presente Ley tiene por objeto:\nI.- Determinar cuales son las profesiones que necesitan título para su ejercicio;\nII.- Establecer las autoridades competentes en materia de profesiones y los organismos auxiliares que intervienen en cumplimiento de la Ley;\nIII.- Normar el registro de las asociaciones de profesionistas, así como su intervención en las actividades previstas en la Ley;\nIV.- Fijar las condiciones y requisitos para la prestación del servicio social profesional;\nV.- Determinar los derechos y obligaciones de los profesionistas, y,\nVI.- Establecer las infracciones y sanciones por incumplimiento a los preceptos establecidos en esta Ley y su Reglamento.\nArtículo Reformado\nARTICULO 3.- Para los efectos de esta Ley se entiende por;\nI.- Asociaciones de Profesionistas.- Las agrupaciones de profesionistas registradas ante el Departamento en los términos de esta Ley;\nII.- Cédula Personal con efectos de patente para el ejercicio profesional.- Es el\nGeneral de Profesiones dependiente de la Secretaría de Educación Pública;\nIII.- Registro Profesional Estatal.- Es el documento expedido por el Departamento de\nProfesiones dependiente de la Secretaría de Educación, el cual otorga autorización para ejercer en el Estado;\nFracción Reformada\nLey de Ejercicio de las Profesiones para el Estado de Baja California. Página 1\nIV.- Departamento.- El Departamento de Profesiones del Estado;\nV.- Ejercicio Profesional.- La realización habitual a título oneroso o gratuito, de todo acto o la prestación de cualquier servicio propio de cada profesión, aunque sólo se trate de simple consulta, o la ostentación del carácter de profesionista por medio de tarjetas, anuncios, placas, insignias o de cualquier otro medio. No se considerará ejercicio profesional los actos realizados en casos graves con propósito de auxilio inmediato;\nVI.- Ley.- La Ley de Ejercicio de las Profesiones para el Estado de Baja California;\nVII.- Nivel Educativo Superior.- Los estudios encaminados a obtener los grados de licenciatura, maestría y doctorado, así como los cursos de actualización y especialización posteriores a la licenciatura;\nVIII.- Pasante.- Persona que ha cumplido con los planes y programas relativos a la\nLicenciatura, Especialidad, Maestría o Doctorado, impartido por una institución de educación superior y no cuente con Título profesional;\nIX.- Profesionista.- La persona física que cuente con Título en algún grado del nivel educativo superior;\nX.- Reglamento.- El Reglamento que derive de la presente Ley;\nXI.- Reincidencia.- Se considera reincidente al infractor que cometa dos o más infracciones a la presente Ley o su Reglamento;\nXII.- Servicio Social.- Se entiende por servicio social, la actividad de carácter temporal, y gratuito, el cual podrá ser remunerado en los términos de las disposiciones que se dicten, mismo que presentarán y ejecutarán los profesionistas y los estudiantes en los sectores públicos, privados o sociales, en interés de la Sociedad y del Estado;\nFracción Reformada\nXIII.- Título Profesional.- El documento expedido por instituciones del Estado o descentralizadas, y por instituciones particulares que tengan reconocimiento de validez oficial de estudios, a favor de la persona que haya concluido los estudios correspondientes; y,\nXIV.- Autorización Provisional.- El documento expedido a los pasantes por el\nDepartamento de Profesiones, por el que se les autoriza a ejercer una profesión en el\nEstado, en tanto el Título, diploma o grado se encuentra en trámite de registro y expedición de cédula.\nArtículo Reformado\nARTICULO 4.- La aplicación y vigilancia de esta Ley corresponde al Ejecutivo del\nEstado, por conducto de la Secretaría de Educación, a través del Departamento de\nProfesiones.\nArtículo Reformado\nLey de Ejercicio de las Profesiones para el Estado de Baja California. Página 2\nARTICULO 5.- Las autoridades estatales y municipales están obligadas a proporcionar al Departamento, los datos, informes y documentos que se les soliciten, con relación a la materia regulada por esta Ley.\nARTICULO 6.- En lo no previsto por la presente Ley o su Reglamento, tratándose de procedimientos arbitrales, se aplicará supletoriamente lo dispuesto por el Código de\nProcedimientos Civiles para el Estado de Baja California.\nARTICULO 7.- En caso de conflicto entre los intereses particulares de los profesionistas y los de la sociedad, la presente Ley se interpretará siempre a favor de las exigencias de esta última, si no hubiere precepto expreso para resolverlo.\nCAPITULO II\nDEL DEPARTAMENTO DE PROFESIONES\nARTICULO 8.- El Departamento contará con un Titular y con los recursos humanos, materiales y financieros necesarios para el adecuado desempeño de sus atribuciones.\nARTICULO 9.- El Departamento tendrá las siguientes atribuciones:\nI.- Ser el órgano de relación entre el Ejecutivo del Estado y las asociaciones de profesionistas y los profesionistas mismos, en todo lo referente al ejercicio de las profesiones, la aplicación y cumplimiento de esta Ley;\nII.- Vigilar el ejercicio profesional en los términos de esta Ley y su Reglamento;\nIII.- Registrar la Cédula Personal con efectos de patente para el ejercicio profesional, así como la del nivel de Técnico Superior Universitario;\nIV.- Difundir anualmente a través del Periódico Oficial del Estado y otro periódico de los de mayor circulación, la lista de profesionistas, pasantes y asociaciones de profesionistas que fueron registrados, así como la lista de personas que cuenten con documentos apócrifos en materia de profesiones;\nV.- Realizar las investigaciones necesarias para comprobar la legitimidad de los documentos que respalden los trámites de los particulares ante el Departamento;\nVI.- Elaborar, organizar y actualizar permanentemente, el padrón de profesionistas en el Estado, formando un expediente para cada profesionista que se integrará con los documentos y anotaciones que especifique el Reglamento.\nVII.- Para tal efecto, el Departamento contará con el apoyo que corresponda, de las asociaciones de profesionistas, de las autoridades federales, estatales y municipales, así como las instituciones de educación superior públicas y privadas.\nVIII.- Expedir a los profesionistas su Registro Profesional Estatal para el ejercicio profesional en el Estado y para su identidad en todas sus actividades profesionales;\nLey de Ejercicio de las Profesiones para el Estado de Baja California. Página 3\nIX.- Requerir a las Asociaciones de Profesionistas registrados ante el departamento para la prestación de Servicios Social Profesional, mediante convocatoria que emita;\nFracción Reformada\nX.- Publicar en el Periódico Oficial del Estado y en los diarios de mayor circulación en el mismo; las resoluciones de registro de Títulos profesionales y las denegatorias de inscripción de los mismos, así como las que emita respecto de suspensiones o cancelaciones del registro para el ejercicio profesional;\nXI.- Derogada;\nFracción Derogada\nXII.- Registrar a las asociaciones de profesionistas en los términos de la presente Ley y su Reglamento, vigilando el funcionamiento de las mismas;\nXIII.- Registrar a las asociaciones de profesionistas en los términos de la presente Ley y su Reglamento, vigilando el funcionamiento de los mismos;\nXIV.- Promover y difundir los programas relativos a la prestación del servicio social profesional en los términos de esta Ley y su Reglamento;\nXV.- Llevar el Registro Estatal de Profesiones, así como publicar mediante la página de internet del Departamento, un listado de los profesionistas, pasantes y asociaciones de profesionistas que fueron registrados, así como la lista de personas que cuenten con documentos apócrifos en materia de profesiones;\nXVI.- Publicar anualmente en el Periódico Oficial del Estado, el listado de instituciones de instituciones de educación superior públicas y privadas, debidamente registradas o reconocidas por las autoridades competentes;\nXVII.- Otorgar autorización provisional a los pasantes para ejercer una profesión;\nXVIII.- Gestionar ante la Secretaría de Educación Pública, el trámite para la expedición de la cédula personal, previo pago de los derechos correspondientes;\nXIX.- Gestionar ante la Secretaría de Educación Pública, el trámite para la expedición de la Cédula Personal con efectos de patente para el ejercicio profesional, previo pago de los derechos correspondientes;\nXX.- Publicar en su página institucional, y en el Periódico Oficial del Estado, el calendario de actividades del Servicio Social Profesional de las Asociaciones de\nProfesionistas registradas ante el departamento;\nFracción Reformada\nXXI.- Publicar en su página institucional, el listado de Profesionistas y Asociaciones profesionistas que cumplan con el Servicio Social Profesional, previsto por esta Ley y su\nReglamento, así como entregar los reconocimientos respectivos;\nFracción Reformada\nXXII.- Registrar a los Consejos de Certificación que se constituyan en el Estado; así esta Ley y su Reglamento;\nLey de Ejercicio de las Profesiones para el Estado de Baja California. Página 4\nXXIII.- En el ámbito de su competencia, ejecutar las penas que ordenen las autoridades correspondientes, referentes a suspensión o privación del derecho a ejercer la profesión; y\nXXIV.- Las demás que contemple esta Ley y su Reglamento.\nArtículo Reformado\nCAPITULO III\nDE LAS PROFESIONES QUE REQUIEREN TITULO PARA SU EJERCICIO\nARTICULO 10.- Todas las profesiones que requieren Título profesional para su ejercicio en el Estado de Baja California, deberán sujetarse a las disposiciones de esta Ley y su Reglamento.\nARTICULO 11.- Las profesiones que necesitan Título para su ejercicio en el Estado de Baja California y en sus diversas ramas y especialidades son las siguientes:\nI. Antropología;\nII. Arquitectura;\nIII. Biólogo;\nIV. Cirujano Dentista;\nV. Contador Público;\nVI. Físico;\nVII. Geología;\nVIII. Ingeniero Agrónomo;\nIX. Ingeniero Agrónomo Zootecnista;\nX. Ingeniería en Bioquímica;\nXI. Ingeniería Cibernética Electrónica;\nXII. Ingeniería Civil;\nXIII. Ingeniería Electromecánica;\nXIV. Ingeniería Electrónica;\nXV. Ingeniería en Eléctrica;\nXVI. Ingeniería en Computación;\nXVII. Ingeniería en Ciencias Computacionales;\nXVIII. Ingeniería en Ciencias Computacionales y Telecomunicaciones;\nLey de Ejercicio de las Profesiones para el Estado de Baja California. Página 5\nXIX. Ingeniería en Diseño Gráfico;\nXX. Ingeniería en Diseño Gráfico Digital;\nXXI. Ingeniería Industrial;\nXXII. Ingeniería Industrial y de Sistemas;\nXXIII. Ingeniería en Informática Corporativa;\nXXIV. Ingeniería Mecánica;\nXXV. Ingeniería en Manufactura;\nXXVI. Ingeniería en Sistemas Computacionales;\nXXVII. Ingeniería en Sistemas Electrónicos;\nXXVIII. Ingeniería en Telecomunicaciones;\nXXIX. Ingeniería Química;\nXXX. Ingeniería Química Fármaco bióloga;\nXXXI. Ingeniería Química Industrial;\nXXXII. Licenciatura en Artes Visuales;\nXXXIII. Licenciatura en Administración;\nXXXIV. Licenciatura en Administración de Empresas;\nXXXV. Licenciatura en Administración Empresarial;\nXXXVI. Licenciatura en Administración Financiera;\nXXXVII. Licenciatura en Administración Hotelera;\nXXXVIII. Licenciatura en Administración de Mercadotecnia;\nXXXIX. Licenciatura en Administración de Organizaciones;\nXL. Licenciatura en Administración para la Calidad;\nXLI. Licenciatura en Administración Pública y Ciencias Políticas;\nXLII. Licenciatura en Auditoría Interna;\nXLIII. Licenciatura en Ciencias;\nXLIV. Licenciatura en Ciencias de la Comunicación;\nXLV. Licenciatura en Ciencias de la Educación;\nXLVI. Licenciado en Educación Preescolar;\nLey de Ejercicio de las Profesiones para el Estado de Baja California. Página 6\nXLVII. Licenciado en Educación Primaria;\nXLVIII. Licenciatura en Ciencias Empresariales;\nXLIX. Licenciatura en Comercio Exterior y Legislación Aduanera;\nL. Licenciatura en Comercio Exterior y Aduanas;\nLI. Licenciatura en Comercio Internacional;\nLII. Licenciatura en Comercio Internacional y Aduanas;\nLIII. Licenciatura en Contador Público Internacional;\nLIV. Licenciatura en Contaduría;\nLV. Licenciatura en Contaduría Fiscal Pública;\nLVI. Licenciatura en Contaduría y Finanzas;\nLVII. Licenciatura en Contaduría-Auditoría;\nLVIII. Licenciatura en Comunicación y Publicidad;\nLIX. Licenciatura en Danza;\nLX. Licenciatura en Derecho;\nLXI. Licenciatura en Derecho Corporativo;\nLXII. Licenciatura en Derecho Corporativo Internacional;\nLXIII. Licenciatura en Deporte;\nLXIV. Licenciatura en Desarrollos Turísticos;\nLXV. Licenciatura en Dirección de Asistencia Social;\nLXVI. Licenciatura en Diseño Gráfico Electrónico;\nLXVII. Licenciatura en Diseño de Modas;\nLXVIII. Licenciatura en Diseño;\nLXIX. Licenciatura en Docencia del idioma inglés;\nLXX. Licenciatura en Economía;\nLXXI. Licenciatura en Economía y Finanzas;\nLXXII. Licenciatura en Educación;\nLXXIII. Licenciatura en Educación Familiar y Desarrollo Humano;\nLXXIV. Licenciatura en Enfermería;\nLey de Ejercicio de las Profesiones para el Estado de Baja California. Página 7\nLXXV. Licenciatura en Etnología;\nLXXVI. Licenciatura en Filosofía;\nLXXVII. Licenciatura en Historia;\nLXXVIII. Licenciatura en Hotelería;\nLXXIX. Licenciatura en Informática;\nLXXX. Licenciatura en Informática Administrativa;\nLXXXI. Licenciatura en Medicina;\nLXXXII. Licenciatura en Mercadotecnia;\nLXXXIII. Licenciatura en Optometría;\nLXXXIV. Licenciatura en Periodismo;\nLXXXV. Licenciatura en Planeación y Desarrollo Urbano;\nLXXXVI. Licenciatura en Ingeniería Comercial;\nLXXXVII. Licenciatura en Ingeniería de Alimentos;\nLXXXVIII. Licenciatura en Lengua y Literatura de Hispanoamérica;\nLXXXIX. Licenciatura en Negocios Internacionales;\nXC. Licenciatura en Matemáticas Aplicadas;\nXCI. Licenciatura en Psicología;\nXCII. Licenciatura en Psicología Familiar;\nXCIII. Licenciatura en Psicología Organizacional;\nXCIV. Licenciatura en Psicología Clínica;\nXCV. Licenciatura en Psicología Educativa;\nXCVI. Licenciatura en Psicología Organizacional;\nXCVII. Licenciatura en Relaciones Internacionales;\nXCVIII. Licenciatura en Sistemas Computacionales;\nXCIX. Licenciatura en Sistemas Computacionales y Administrativos;\nC. Licenciatura en Sociología;\nCI. Licenciatura en Traducción del idioma Inglés;\nCII. Licenciatura en Turismo;\nLey de Ejercicio de las Profesiones para el Estado de Baja California. Página 8\nCIII. Licenciatura en Telecomunicaciones y Redes de Información;\nCIV. Licenciatura en Trabajo Social;\nCV. Licenciatura en Traducción;\nCVI. Licenciatura en Nutriología;\nCVII. Medicina General;\nCVIII. Médico Cirujano y Partero;\nCIX. Médico Veterinario Zootecnista;\nCX. Oceanólogo; y\nCXI. Odontólogo.\nLas demás profesiones que se publiquen en el Periódico Oficial del Estado por el\nDepartamento de Profesiones.\nArtículo Reformado\nCAPITULO IV\nDE LA INSCRIPCION DE LAS INSTITUCIONES\nDE EDUCACION SUPERIOR\nARTICULO 12.- Las instituciones de educación superior establecidas en el Estado, están obligadas a inscribirse ante el Departamento, el cual expedirá constancia respectiva en los términos que establezca el Reglamento.\nARTICULO 13.- Las instituciones de educación superior deberán proporcionar al\nDepartamento, la siguiente información:\nI.- Los planes, programas y cursos que impartan;\nII.- Relación de personas que hayan concluido los estudios profesionales en los niveles de educación superior; y,\nIII.- Relación de personas a quienes se les haya expedido Título Profesional; y,\nIV.- La relación de grados por área y nivel académico de las diferentes profesiones.\nArtículo Reformado\nCAPÍTULO V\nEJERCICIO PROFESIONAL Y EXPEDICIÓN DEL\nREGISTRO PROFESIONAL ESTATAL\nARTICULO 14.- Para obtener el registro de la Cédula Personal con efecto de patente para el ejercicio profesional, el interesado deberá exhibir ante el Departamento:\nLey de Ejercicio de las Profesiones para el Estado de Baja California. Página 9\nI.- Título profesional original y dos copias simples para su cotejo;\nII.- Cédula personal con efectos de patente para el ejercicio profesional y dos copias simples para su cotejo; y,\nFracción Reformada\nIII.- La certificación vigente en caso de profesiones o especialidades que así lo requieran para el ejercicio profesional.\nFracción Derogada\nFracción Adicionada\nArtículo Reformado\nARTICULO 15.- Una vez registrada la Cédula con efecto de patente para el ejercicio profesional, se expedirá autorización escrita a través de un Registro Profesional Estatal para ejercer la profesión en el nivel educativo que corresponda.\nArtículo Reformado\nARTICULO 16.- Los Títulos expedidos en el extranjero a favor de mexicanos o de extranjeros, serán reconocidos en el Estado de Baja California y registrados ante la Dirección General de Profesiones, con sujeción a lo previsto en los Tratados\nInternacionales de que México sea parte.\nArtículo Reformado\nCAPITULO VI\nDEL EJERCICIO PROFESIONAL\nARTICULO 17.- Para ejercer una profesión, se requiere:\nI.- Poseer Título profesional legalmente expedido;\nII.- Estar inscrito en el Registro Estatal de Profesiones y contar con un registro profesional estatal; y,\nIII.- Derogada.\nFracción Derogada\nArtículo Reformado\nARTICULO 18.- Toda persona a la que se le haya expedido Título Profesional dentro del plazo de dos años, deberá tramitar su Registro Profesional Estatal, previo pago de los derechos correspondientes. en el Departamento, si desean ejercer profesionalmente en el Estado; siempre que la entidad federativa de que se trate, de acuerdo con lo establecido en el artículo 121 fracción\nV de la Constitución Política de los Estados Unidos Mexicanos.\nPárrafo Adicionado, recorriéndose el subsecuente\nLey de Ejercicio de las Profesiones para el Estado de Baja California. Página 10\nEl trámite podrá realizarse en forma personal, o por conducto de las instituciones de educación superior, o bien por la Asociación correspondiente.\nArtículo Reformado\nARTICULO 19.- La y los pasantes para ejercer en el Estado, requieren de autorización provisional expedida por el Departamento por un período de dos años, la cual podrá ser prorrogada por un año más.\nPárrafo Reformado\nEl Departamento, previo la expedición de la autorización provisional, deberá cerciorarse que el pasante está bajo el consejo y dirección de un profesionista debidamente registrado ante éste.\nPara otorgar autorización provisional a las y los pasantes para ejercer una profesión se requiere satisfacer los siguientes requisitos:\nPárrafo Reformado\nI.- Haber concluido los planes y programas relativos a la Licenciatura, Especialidad, Maestría, o Doctorado, y tener en trámite la expedición de su Título o cédula profesional, según corresponda;\nFracción Reformada\nII.- Constancia de buena conducta expedida por la institución de educación superior de donde egresó;\nIII.- No tener más de dos años de terminados los estudios de su carrera profesional;\nFracción Reformada\nIV.- Tener un promedio de calificaciones no inferior a ocho.\nEn ningún caso procederá la autorización provisional para el ejercicio de las especialidades médicas.\nPárrafo Adicionado\nArtículo Reformado\nARTICULO 20.- Derogado.\nArtículo Derogado\nARTICULO 21.- Queda estrictamente prohibido:\nI.- A los profesionistas autorizados, respaldar o revalidar con su firma, escritos, gestiones o servicios relacionados con algún acto profesional, por persona que no cuente con autorización del Departamento;\nII.- A las y los profesionistas responsables del funcionamiento de hospitales, clínicas, boticas, farmacias, laboratorios y en cualquier otro establecimiento público o privado, permitir\nLey de Ejercicio de las Profesiones para el Estado de Baja California. Página 11 cédula profesional, registro profesional estatal o en su caso la autorización provisional expedida por el Departamento.\nPárrafo de Fracción Reformado rama de salud correspondiente, a efecto de que avalen el ejercicio profesional del personal médico que bajo cualquier modalidad presten sus servicios en dichos establecimientos.\nPárrafo de Fracción Adicionado\nFracción Reformada\nIII.- A los particulares que no cuenten con Cédula profesional con efecto de patente para el ejercicio profesional o en su caso autorización expedida por el Departamento, prestar servicios profesionales y de especialidad en materia de salud en hospitales, clínicas, boticas, farmacias, laboratorios y cualquier otro establecimiento público o privado, así como proporcionar por su cuenta dichos servicios a la población en general; y,\nFracción Derogada\nFracción Reformada\nIV.- Las demás que establezca el Reglamento.\nArtículo Reformado\nCAPITULO VII\nDERECHOS Y OBLIGACIONES\nDEL PROFESIONISTA\nARTICULO 22.- Son derechos del profesionista:\nI.- Percibir la justa remuneración Por sus servicios profesionales de común acuerdo con el cliente:\nII.- Ser parte de las asociaciones de profesionistas en los términos de esta Ley;\nIII.- Los demás que se encuentren previstos en la presente Ley y su Reglamento.\nArtículo Reformado\nARTICULO 23.- Son obligaciones del profesionista:\nI.- Observar legalidad, honestidad y ética en la prestación de los servicios profesionales,\nII.- Aplicar sus conocimientos profesionales al servicio del cliente o empleador;\nIII.- Guardar el secreto profesional respecto a la información de que disponga, salvo los informes que deban rendirse ante las autoridades competentes, en los términos de las disposiciones legales aplicables;\nIV.- Señalar en su publicidad o papelería particular, su nombre completo, profesión que ejerce, así como cualquier otro estudio de nivel educativo superior en su caso y\nLey de Ejercicio de las Profesiones para el Estado de Baja California. Página 12 especialidad, y número de registro de su Registro Profesional Estatal o autorización respectiva;\nFracción Reformada\nV.- Cumplir con la prestación del Servicio Social Profesional, conforme a los lineamientos de esta Ley y su Reglamento;\nFracción Reformada\nVI.- Exhibir su Título profesional, cédula profesional, registro profesional estatal o en su caso la autorización provisional expedida por el Departamento que acredite estudios de nivel educativo superior, en lugar visible del establecimiento en que habitualmente ejerce la profesión.\nPárrafo de Fracción Reformado\nTratándose de especialistas estos deberán exhibir la certificación vigente de la rama de salud correspondiente.\nPárrafo de Fracción Adicionado\nFracción Reformada\nVII.- Informar al Departamento, el domicilio del establecimiento en que habitualmente ejerce la profesión;\nVIII.- Dar aviso al Departamento dentro de los treinta días hábiles siguientes del cambio de domicilio del establecimiento donde ejercia su profesión;\nIX.- Cumplir con la prestación de los servicios profesionales en los términos convenidos con el cliente; y,\nX.- Las demás que se desprendan de esta Ley y su Reglamento.\nArtículo Reformado\nCAPITULO VIII\nDEL SERVICIO SOCIAL DE PROFESIONISTAS Y ESTUDIANTES\nARTICULO 24.- El Departamento promoverá la prestación del servicio social profesional en el Estado, y contará para ello con el apoyo de las demás dependencias y entidades del Gobierno del Estado, así como del Gobierno Federal y de los municipios.\nAsociación de Profesionistas a que pertenezca, conforme a los acuerdos o convenios que celebre con la dependencia, entidad u orden de gobierno que corresponda.\nArtículo Reformado\nARTICULO 25.- El servicio social profesional se prestará en comunidades de escasos recursos, en instituciones públicas o privadas, en Asociación de Profesionistas, o en asociaciones civiles que tengan por objeto el cuidado y protección del medio ambiente, o el apoyo y asistencia a la comunidad a través de asesorías, consultas, aportación de datos, ejecución de actos propios de su profesión.\nLey de Ejercicio de las Profesiones para el Estado de Baja California. Página 13\nAdemás, se fomentará que el servicio social que se lleve a cabo en el Estado sea inclusivo, con las personas que presenten alguna condición de discapacidad o alguna situación de vulnerabilidad.\nPárrafo Adicionado\nArtículo Reformado\nARTICULO 26.- Las Asociaciones de Profesionistas y sus afiliados, así como aquellos profesionistas independientes que hayan prestado servicio social profesional en atención a los acuerdos o convenios celebrados con alguna dependencia o entidad de gobierno, recibirán de éstas una constancia de reconocimiento.\nCuando las asociaciones de Profesionistas realicen servicio social profesional en cumplimiento a su Plan de Trabajo en beneficio de comunidades vulnerables, dicha acción será reconocida mediante constancia otorgada por el departamento.\nPárrafo Adicionado\nArtículo Reformado\nARTICULO 27.- El servicio social de los estudiantes, quedará al cuidado y responsabilidad de las instituciones de Educación Superior, conforme a sus planes de estudio.\nArtículo Reformado\nARTICULO 28.- Todos los estudiantes de las profesiones a que se refiere esta Ley, deberán prestar su servicio social.\nArtículo Reformado\nARTICULO 29.- El departamento, publicará en su página institucional, y en el\nPeriódico Oficial del estado, el calendario de actividades del Servicio Social Profesional de las Asociaciones de Profesionistas el primer bimestre del año.\nEl Departamento de manera anual en coordinación con las Asociaciones de\nProfesionistas, promoverá y ofrecerá el otorgamiento de Servicio Social Profesional a la sociedad, por las asociaciones registradas ante el departamento.\nPárrafo Adicionado\nArtículo Reformado\nARTICULO 30.- Durante el mes de enero de cada año, las asociaciones de profesionistas deberán proporcionar al Departamento:\nI.- Lista de los afiliados que hayan consentido en prestar su servicio social profesional;\nII.- Lista de los afiliados que en el año inmediato anterior prestaron servicio social profesional; y,\nIII.- El programa anual para el ejercicio del servicio social profesional, especificando las acciones profesionales que se pretenden ejecutar.\nArtículo Reformado\nLey de Ejercicio de las Profesiones para el Estado de Baja California. Página 14\nARTICULO 31.- El Departamento en el mes de enero, realizará convocatoria a los\nProfesionistas y Asociaciones profesionistas, para prestar servicio social profesional anual a la sociedad, promovido el Departamento en coordinación con las Asociaciones de\nProfesionistas.\nArtículo Adicionado\nCAPITULO IX\nDE LAS ASOCIACIONES DE PROFESIONISTAS\nARTICULO 32.- Los profesionistas de una misma rama podrán organizarse y constituírse en el Estado, para el ejercicio de sus derechos y defensa de sus intereses de carácter profesional, en los términos de la presente Ley y su Reglamento.\nARTICULO 33.- Las asociaciones de profesionistas que cumplan con los requisitos previstos en la presente Ley, podrán utilizar en su denominación la expresión “Asociación”, incluyendo en la misma la profesión, y en su caso, la especialidad a que pertenezcan.\nLa denominación de una asociación de profesionistas deberá ser distinta a la de cualquier otra de la misma profesión o especialidad en su caso.\nArtículo Reformado\nARTICULO 34.- Las asociaciones de profesionistas para obtener su registro ante el\nDepartamento, deberán cumplir con lo siguiente:\nI.- Estar constituida como Asociación Civil, en los términos del Código Civil para el\nEstado de Baja California;\nII.- Solicitud por escrito dirigida al Departamento;\nIII.- Contar con un mínimo de 30 asociados debidamente registrados como profesionistas ante el Departamento;\nIV.- Testimonio de la escritura pública de protocolización del acta constitutiva y de sus\nEstatutos y copia simple de ambos documentos; y,\nV.- Relación de sus asociados indicando su domicilio.\nVI.- Presentar ante el Departamento un Código de ética que lo regule.\nTratándose de profesiones en los cuales por su novedad o especialización no se puedan reunir 30 profesionistas, el Departamento previa evaluación podrá otorgar el registro correspondiente.\nArtículo Reformado\nARTICULO 35.- Durante el primer bimestre de cada año, las asociaciones de profesionistas deberán presentar al Departamento, una relación de los profesionistas activos y de los titulares de los órganos directivos. Asimismo, deberán dar aviso de los cambios de sus órganos directivos y domicilio, dentro de los treinta días naturales siguientes a que ello acontezca.\nArtículo Reformado\nLey de Ejercicio de las Profesiones para el Estado de Baja California. Página 15\nARTICULO 36.- Las asociaciones de profesionistas que dejen de tener el mínimo de párrafo del artículo 34, el Departamento les concederá el plazo de un año para que lo completen. El registro será cancelado en el caso de que en el plazo señalado no cumplan con dicho requisito.\nArtículo Reformado\nARTICULO 37.- Las asociaciones de profesionistas en el ejercicio de su función deberán:\nI.- Vigilar que el ejercicio profesional de sus asociados se realice apegado a la ética profesional, denunciando ante el Departamento las violaciones que se cometan a la presente\nLey y a su Reglamento;\nII.- Fomentar la superación profesional de sus asociados;\nIII.- Promover entre sus asociados la prestación del servicio social profesional;\nIV.- Llevar el registro de los trabajos anualmente desempeñados por sus asociados en la práctica del servicio social profesional y de aquellos otros que en forma destacada realicen;\nV.- Proponer a las autoridades judiciales y administrativas, listas de peritos profesionales, cuyos servicios puedan ser preferidos por aquellas, en virtud de sus características o desempeño profesional;\nVI.- Recomendar al Departamento, las comunidades o instituciones que a su juicio requieren con mayor urgencia de la atención de un profesionista, para los efectos de la prestación del servicio social;\nVII.- Nombrar un representante ante el Departamento y las demás autoridades federales, estatales o municipales cuando sea solicitado;\nVIII.- Depositar ante el Departamento un ejemplar de sus Estatutos o Reglamentos;\nIX.- Actuar como cuerpos consultores del poder público dentro de sus respectivas ramas;\nX.- Dar aviso al Departamento, de las bajas de sus asociados;\nXI.- Gestionar el registro de los Títulos profesionales de sus miembros y la expedición de los registros profesionales estatales respectivas;\nXII.- Integrar un expediente de cada uno de sus asociados que contenga la documentación que acuerde la propia asociación de profesionistas;\nXIII.- Presentar anualmente ante el Departamento un proyecto anual de trabajo;\nXIV.- Ofrecer pláticas, cursos y talleres, con la finalidad de ofrecer a sus asociados y a la comunidad en general, educación continua;\nXV.- Elaborar su respectivo Código de ética que lo regule; y, Ley de Ejercicio de las Profesiones para el Estado de Baja California. Página 16\nXVI.- Los demás que esta Ley y su reglamento les confieran.\nArtículo Reformado\nARTICULO 38.- El Departamento, vigilará y supervisará el cumplimiento del Servicio\nSocial Profesional, a que se hayan comprometido las Asociaciones de Profesionistas en sus programas de trabajo, así como la realización de un evento anual en el que se brinde\nServicio Social Profesional, promovido por el Departamento.\nArtículo Adicionado\nARTICULO 39.- Las asociaciones de profesionistas elaborarán sus propios lineamientos de ética profesional, que orientarán la conducta de los profesionistas en sus relaciones con la sociedad, las instituciones, sus asociados, sus clientes, superiores, subordinados y colegas.\nEstos lineamientos regularán su desempeño profesional, ajustándolo a los más elevados valores humanos, científicos y morales, y constituirán un compromiso social de los profesionistas con la sociedad.\nArtículo Reformado\nCAPITULO X\nDEL ARBITRAJE\nARTICULO 40.- En los casos de controversia en materia de obligaciones relativas a la prestación de servicios profesionales, las partes podrán acudir ante los órganos jurisdiccionales competentes o someterse al arbitraje en los términos de esta Ley, excepto en aquellas profesiones que cuenten con un ordenamiento legal para dirimirlas.\nARTICULO 41.- El Departamento fungirá como árbitro, para lo cual deberá desahogar el procedimiento a que se refiere el Reglamento, en el cual deberá contemplarse el derecho de audiencia y defensa a las partes; el desahogo y valoración de las pruebas; y la emisión del laudo debidamente fundado y motivado.\nARTICULO 42.- Derogado.\nArtículo Derogado\nARTICULO 43.- Derogado.\nArtículo Derogado\nARTICULO 44.- Los laudos arbitrales emitidos por el Departamento, tendrán fuerza de cosa juzgada y traerán aparejada ejecución.\nARTICULO 45.- Derogado.\nArtículo Derogado\nARTICULO 46.- Derogado.\nArtículo Derogado\nCAPITULO XI\nDE LA VIGILANCIA E INSPECCION\nLey de Ejercicio de las Profesiones para el Estado de Baja California. Página 17\nARTICULO 47.- Corresponde al Departamento por conducto de las personas a quienes autorice, la práctica de las visitas de inspección, vigilancia y supervisión de las actividades, respecto del exacto cumplimiento de esta Ley y su Reglamento por parte de los profesionistas, pasantes y Asociaciones de Profesionistas.\nArtículo Reformado\nARTICULO 48.- La orden de visita de inspección que emita el Departamento, constará por escrito y deberá contener los siguientes datos:\nI.- Autoridad que la emite;\nII.- Nombre y firma autógrafa del funcionario competente;\nIII.- Nombre del profesionista, pasante o asociación de profesionista sujeto a visita de inspección;\nIV.- Lugar o lugares donde se practicará la visita de inspección;\nV.- Lugar y fecha en que habrá de verificarse la visita de inspección;\nVI.- Expresar el objeto o propósito de la visita de inspección y fundamento legal; y\nVII.- Nombre de la persona comisionada y autorizada para efectuar la visita de inspección.\nArtículo Reformado\nARTICULO 49.- Los profesionistas, pasantes y asociaciones de profesionistas están obligados a permitir el acceso y facilitar las visitas de inspección.\nArtículo Reformado\nARTICULO 50.- De toda visita de inspección se levantará acta circunstanciada, conforme al procedimiento que establezca el Reglamento de la presente Ley.\nDel acta levantada deberá dejarse copia al visitado o con quien se practique la visita de inspección.\nArtículo Reformado\nARTICULO 51.- El Departamento tendrá la más amplia facultad para ordenar la práctica de inspección para constatar la autenticidad de la información que se le haya proporcionado, para investigar el cumplimiento a la Ley y, en general, para allegarse toda clase de datos y elementos de juicio para el mejor cumplimiento de su cometido.\nArtículo Reformado\nARTICULO 52.- Si del resultado de la diligencia de visita de inspección se\nReglamento, se le hará saber al visitado que cuenta con un plazo de quince días hábiles para subsanar las mismas; en caso de incumplimiento se deberá imponer la sanción que corresponda.\nArtículo Reformado\nLey de Ejercicio de las Profesiones para el Estado de Baja California. Página 18\nCAPITULO XII\nDE LAS INFRACCIONES Y SANCIONES\nARTICULO 53.- Las sanciones por las infracciones a esta Ley, serán determinadas por el Departamento en los términos a que se refiere el presente capítulo, sin perjuicio de aquellas que por violación a otros ordenamientos correspondan.\nARTICULO 54.- El Departamento podrá imponer al infractor las siguientes sanciones:\nI.- Multa;\nII.- Suspensión temporal para el ejercicio de la profesión;\nIII.- Suspensión temporal del registro de la asociación de profesionistas;\nIV.- Derogada.\nFracción Derogada\nV.- Cancelación del registro de la asociación de profesionistas; y\nVI.- Derogada.\nFracción Derogada\nArtículo Reformado\nARTICULO 55.- El Departamento para sancionar al infractor deberá tomar en consideración:\nI.- La gravedad de la infracción;\nII.- Las condiciones económicas del infractor; y,\nIII.- La reincidencia.\nARTICULO 56.- Se impondrá multa:\nI.- A quien ejerza una profesión sin poseer título legalmente expedido, ni cuente con el\nRegistro correspondiente;\nII.- A quien se le haya expedido el Título profesional y que dentro del término de dos años esté ejerciendo su profesión y no cuente con su registro profesional estatal;\nIII.- A quien no señale en su publicidad o papelería particular, su nombre completo, profesión que ejerce y cualquier otro estudio de nivel educativo superior en su caso, y número de su Registro Profesional Estatal o autorización respectiva;\nIV.- A quien no exhiba el Título, constancia o certificado que acredite sus estudios de nivel educativo; en lugar visible del establecimiento en que actualmente ejerce su profesión;\nV.- A quien no informe al Departamento, del domicilio del establecimiento en que habitualmente ejerce su profesión;\nVI.- A quien no de aviso al Departamento dentro del término de treinta días hábiles siguientes, del cambio de domicilio del establecimiento donde ejerza su profesión;\nLey de Ejercicio de las Profesiones para el Estado de Baja California. Página 19\nVII.- A quien no cumpla con la prestación de los servicios profesionales en los términos convenidos con el cliente;\nVIII.- A la asociación de profesionistas que no presente al Departamento dentro del primer bimestre de cada año, la relación de los profesionistas activos, o que no de aviso del cambio de los titulares de los órganos directivos o de su domicilio, en los términos de la presente Ley;\nIX.- A las asociaciones de profesionistas que no proporcionen al Departamento durante el mes de enero de cada año su proyecto anual de trabajo, así como un programa para el ejercicio del servicio social;\nX.- A la asociación de profesionistas cuando no deposite ante el Departamento un ejemplar de sus estatutos o reglamentos;\nXI.- A quien no exhiba título profesional, cédula profesional, registro profesional estatal o en su caso la autorización provisional para ejercer la Profesión, así como la certificación vigente en la rama de salud correspondiente para el ejercicio de las profesiones o especialidades que correspondan;\nFracción Derogada\nFracción Adicionada\nXII.- Al profesionista, pasante o asociación de profesionistas que no permita el acceso a quienes realicen las visitas de inspección; y,\nXIII.- A la asociación de profesionistas que no dé aviso al Departamento de las bajas de sus asociados.\nArtículo Reformado\nARTICULO 56 BIS.- Se consideran infracciones leves aquellas previstas en las fracciones II, III, IV, V, VI, VIII, X y XIII del artículo 56 de la Ley, y de las cuales se aplicarán multa de 5 a 150 veces la unidad de medida y actualización vigente.\nPárrafo Reformado\nSe consideran infracciones graves las previstas en las fracciones I, VII, XI y XII del artículo 56 de la presente Ley, las cuales se aplicarán multa de 150 a 300 veces la unidad de medida y actualización vigente.\nPárrafo Reformado\nArtículo Reformado\nARTICULO 57.- Se impondrá suspensión temporal del registro de una asociación de profesionistas hasta por seis meses, cuando:\nI.- No presenten al Departamento durante el mes de enero de cada año, la relación de los profesionistas activos, así como del cambio de los titulares de los órganos directivos, dentro de los treinta días a que acontezca la modificación;\nII.- Cuando no den aviso al Departamento de las bajas de sus asociados; y,\nIII.- Las demás que determine el reglamento.\nArtículo Reformado\nLey de Ejercicio de las Profesiones para el Estado de Baja California. Página 20\nARTICULO 58.- Se impondrá al profesionista, la suspensión temporal del ejercicio de la profesión hasta por dos años, cuando:\nI.- Los profesionistas autorizados, respalden o revaliden con su firma, escritos, gestiones o servicios relacionados con algún acto profesional, a persona que no cuente con autorización del Departamento;\nII.- Derogado.\nFracción Derogada\nIII.- No guarde el secreto profesional respecto a la información de que disponga, con excepción de los informes que deban rendirse ante las autoridades competentes, en los términos de las disposiciones legales aplicables;\nIV.- Reincida en los supuestos previstos por el Artículo 56 Bis segundo párrafo de la presente Ley; y,\nV.- Incurra en lo previsto en la fracción II del artículo 21 de esta Ley.\nArtículo Reformado\nARTICULO 59.- Derogado.\nArtículo Derogado\nARTICULO 60.- Se impondrá la cancelación del registro de la asociación de profesionistas cuando:\nI.- Deje de tener el mínimo de integrantes que la Ley prevé, en el supuesto de que haya transcurrido el año que para tal efecto el Departamento concedió y no hubieren cumplido; y,\nII.- Presente ante el Departamento documentos apócrifos para su inscripción y registro.\nIII.- Derogada.\nFracción Derogada\nArtículo Reformado\nARTICULO 61.- El Departamento para imponer las sanciones previstas en esta Ley, deberá notificar al infractor los hechos u omisiones por los cuales se le imputa la infracción y en su caso, anexando copia certificada del acta circunstanciada levantada en la inspección, de la notificación, comparezca ofreciendo por escrito las pruebas y alegatos que considere para su defensa, apercibido que de no hacerlo perderá el derecho y se impondrá la sanción que corresponda.\nEl Departamento, dentro de los ocho días hábiles siguientes a la recepción del escrito de ofrecimiento de pruebas y alegatos del infractor, deberá desahogar y valorar las pruebas admitidas y resolver sobre la existencia o inexistencia de la infracción, notificando al infractor la resolución definitiva.\nArtículo Reformado\nLey de Ejercicio de las Profesiones para el Estado de Baja California. Página 21\nARTICULO 62.- Derogado.\nArtículo Derogado\nCAPITULO XIII\nDEL RECURSO ADMINISTRATIVO\nARTICULO 63.- Los actos, acuerdos o resoluciones que dicte el Departamento en aplicación de esta Ley y su Reglamento, podrán ser impugnados por parte interesada, mediante la interposición del recurso de revocación.\nArtículo Reformado\nARTICULO 64.- El recurso de revocación se interpondrá ante la autoridad que emitió el acto impugnado dentro de los cinco días hábiles siguientes a aquél en que haya surtido efectos la notificación del mismo.\nCuando el infractor resida fuera de la Capital del Estado, se tendrán por hechas en tiempo las promociones si deposita los escritos relativos, dentro de los términos legales anteriormente señalados, en la oficina de correos o telégrafos que corresponda al lugar de su residencia.\nArtículo Reformado\nARTICULO 65.- El escrito de interposición del recurso deberá satisfacer los siguientes requisitos:\nI.- El nombre, la denominación o razón social y el domicilio del promovente y en su caso, el número de registro estatal de profesiones;\nII.- Señalar la autoridad a la que se dirige la promoción;\nIII.- El domicilio para oír y recibir notificaciones y el nombre de la persona autorizada para recibirlas;\nIV.- La resolución o el acto que se impugna;\nV.- Los agravios que le cause la resolución o el acto impugnado;\nVI.- Las pruebas y los hechos controvertidos de que se trate;\nVII.- Estar firmada por el interesado.\nA falta de cumplimiento de cualquiera de los requisitos a que se refiere este artículo, se tendrá por no presentado el recurso.\nArtículo Reformado\nARTÍCULO 66.- El Departamento dentro del plazo de quince días hábiles contados a partir de la presentación del recurso de revocación, deberá resolver sobre la admisión o rechazo del mismo.\nLey de Ejercicio de las Profesiones para el Estado de Baja California. Página 22\nEn caso de que el recurso resultare improcedente, se deberá notificar al infractor la resolución correspondiente, de lo contrario se citará al recurrente dentro de los quince días hábiles siguientes a la fecha del auto de admisión del recurso, a una audiencia para desahogar las pruebas admitidas y producir alegatos. días hábiles siguientes a la celebración de la misma, debiendo notificar la resolución definitiva al interesado.\nArtículo Reformado\nCAPÍTULO XIV\nDE LA CERTIFICACIÓN DE PROFESIONISTAS\nARTÍCULO 67.- Las asociaciones de profesionistas de una misma rama profesional, podrán constituir en el Estado un Consejo de Certificación, que se integrará cuando menos con la mitad más una de éstas debidamente registradas en el Departamento.\nLas asociaciones que obtengan la representatividad mínima que se menciona en el párrafo anterior, se denominarán “Consejo de Certificación de...”, indicándose la rama o especialidad profesional que corresponda.\nArtículo Reformado\nARTÍCULO 68.- Los Consejos de Certificación tendrán por objeto hacer constar que un profesionista debidamente registrado cuenta con los conocimientos, habilidades o destrezas propias de su profesión.\nArtículo Reformado\nARTÍCULO 69.- Los Consejos de Certificación podrán expedir para dicho efecto, una constancia de certificación al profesionista que apruebe satisfactoriamente el procedimiento respectivo.\nCada Consejo establecerá en sus estatutos los métodos, técnicas y criterios de evaluación aplicables a su propia certificación.\nArtículo Reformado\nARTÍCULO 70.- La certificación tendrá el carácter de voluntaria, y su vigencia la determinará cada Consejo, pero en ningún caso será menor de un año, ni mayor de cinco.\nArtículo Reformado\nARTÍCULO 71.- El reglamento establecerá las bases generales de organización y funcionamiento de los Consejos de Certificación, quienes deberán de considerarlas al momento de elaborar sus estatutos, así como los derechos y obligaciones de los profesionistas certificados.\nArtículo Reformado\nLey de Ejercicio de las Profesiones para el Estado de Baja California. Página 23\nARTICULO PRIMERO.- La presente Ley entrará en vigor a partir del día siguiente al\nARTICULO SEGUNDO.- A partir de la iniciación de su vigencia, queda abrogada la\nLey Reglamentaria del Ejercicio Profesional para el Estado de Baja California, publicada en el Periódico Oficial del Estado, de fecha 10 de junio de 1957, así como las reformas y adiciones surgidas desde el momento de su promulgación.\nARTICULO TERCERO.- En un término de ciento ochenta días posteriores a la entrada en vigor de esta Ley, se modificará el Reglamento de la Ley Reglamentaria del\nEjercicio Profesional para el Estado de Baja California publicado en el Periódico Oficial del\nEstado con fecha 20 de noviembre de 1957; modificándose además los ordenamientos jurídicos correlativos a la misma, en todo lo que se opongan o contradigan con ésta.\nARTICULO CUARTO.- Hasta en tanto se modifique el Reglamento correspondiente a la presente Ley, se aplicará en lo conducente el Reglamento vigente.\nARTICULO QUINTO.- A los Colegios de Profesionistas que a la fecha de entrada en vigor de esta Ley, se encuentren debidamente reconocidos, autorizados y registrados ante el\nDepartamento de Profesiones, se les seguirá respetando su registro, autorización y reconocimiento.\nARTICULO SEXTO.- Los Títulos profesionales que con anterioridad a esta Ley hubieran sido legalmente expedidos y registrados en el Departamento de Profesiones surtirán todos sus efectos, respetándose su registro, autorización y reconocimiento.\nARTICULO SEPTIMO.- Se concede a las personas que no tengan Título legalmente expedido, un plazo de dos años a partir de la vigencia de esta Ley, para que regularicen su situación ajustándose a los términos de la misma.\nARTICULO OCTAVO.- Se concede a los profesionistas un plazo de seis meses contados a partir de la entrada en vigor de la presente Ley, a efecto de que adecuen su papelería y publicidad particular en los términos que establece este ordenamiento.\nDADO en el Salón de Sesiones “Lic. Benito Juárez García” del Honorable Poder\nLegislativo, en la Ciudad de Mexicali, Baja California, a los quince días del mes de agosto del año dos mil dos.\nDIP. JESUS ALEJANDRO RUIZ URIBE\nPRESIDENTE\nLey de Ejercicio de las Profesiones para el Estado de Baja California. Página 24\nDIP. LAURA SANCHEZ MEDRANO\nSECRETARIA\n(RÚBRICA)\nDE CONFORMIDAD CON LO DISPUESTO POR LA FRACCION I DEL ARTICULO 49\nDE LA CONSTITUCION POLITICA DEL ESTADO, MANDO SE IMPRIMA Y PUBLIQUE.\nMEXICALI, BAJA CALIFORNIA, A LOS VEINTITRES DIAS DEL MES DE AGOSTO\nDEL AÑO DOS MIL DOS.\nGOBERNADOR DEL ESTADO\nEUGENIO ELORDUY WALTHER\nSECRETARIO GENERAL DE GOBIERNO\nBERNARDO BORBON VILCHES\nLey de Ejercicio de las Profesiones para el Estado de Baja California. Página 25\nARTICULO 2.- Fue reformado por Decreto No. 206, publicado en el Periódico Oficial\nLegislatura, siendo Gobernador Constitucional el C. Lic. Eugenio Elorduy Walther, 20012007;\nARTICULO 3.- Fue reformado por Decreto No. 238, publicado en el Periódico Oficial\nNo. 24, de fecha 18 de mayo de 2018, Tomo CXXV, Sección II, expedido por la Honorable\nXXII Legislatura, siendo Gobernador Constitucional el C. Francisco Arturo Vega de\nLamadrid, 2013-2019; fue reformado por Decreto No. 229, publicado en el Periódico Oficial\nNo. 30, Índice, Tomo CXXX, de fecha 26 de mayo de 2023, expedido por la H. XXIV\nLegislatura, siendo Gobernadora Constitucional la C. Marina del Pilar Ávila Olmeda 20212027;\nARTICULO 4.- Fue reformado por Decreto No. 229, publicado en el Periódico Oficial\nNo. 30, Índice, Tomo CXXX, de fecha 26 de mayo de 2023, expedido por la H. XXIV\nLegislatura, siendo Gobernadora Constitucional la C. Marina del Pilar Ávila Olmeda 20212027;\nARTICULO 9.- Fue reformado por Decreto No. 206, publicado en el Periódico Oficial\nNo. 33, de fecha 11 de agosto de 2006, Tomo CXIII, expedido por la Honorable XVIII\nLegislatura, siendo Gobernador Constitucional el C. Lic. Eugenio Elorduy Walther, 20012007;\nARTICULO 11.- Fue reformado por Decreto No. 206, publicado en el Periódico Oficial\nNo. 33, de fecha 11 de agosto de 2006, Tomo CXIII, expedido por la Honorable XVIII\nLegislatura, siendo Gobernador Constitucional el C. Lic. Eugenio Elorduy Walther, 20012007;\nARTICULO 13.- Fue reformado por Decreto No. 206, publicado en el Periódico Oficial\nNo. 33, de fecha 11 de agosto de 2006, Tomo CXIII, expedido por la Honorable XVIII\nLegislatura, siendo Gobernador Constitucional el C. Lic. Eugenio Elorduy Walther, 20012007;\nFue modificada su denominación mediante Decreto No. 206, publicado en el Periódico\nOficial No. 33, de fecha 11 de agosto de 2006, Tomo CXIII, expedido por la Honorable XVIII\nLegislatura, siendo Gobernador Constitucional el C. Lic. Eugenio Elorduy Walther, 20012007;\nCAPÍTULO V\nEJERCICIO PROFESIONAL Y EXPEDICIÓN DEL\nREGISTRO PROFESIONAL ESTATAL\nARTICULO 14.- Fue reformado por Decreto No. 206, publicado en el Periódico Oficial\nLegislatura, siendo Gobernador Constitucional el C. Lic. Eugenio Elorduy Walther, 2001Ley de Ejercicio de las Profesiones para el Estado de Baja California. Página 26\n2007; fue reformado por Decreto No. 229, publicado en el Periódico Oficial No. 30, Índice, Gobernadora Constitucional la C. Marina del Pilar Ávila Olmeda 2021-2027;\nARTICULO 15.- Fue reformado por Decreto No. 206, publicado en el Periódico Oficial\nLegislatura, siendo Gobernador Constitucional el C. Lic. Eugenio Elorduy Walther, 20012007;\nARTICULO 16.- Fue reformado por Decreto No. 206, publicado en el Periódico Oficial\nNo. 33, de fecha 11 de agosto de 2006, Tomo CXIII, expedido por la Honorable XVIII\nLegislatura, siendo Gobernador Constitucional el C. Lic. Eugenio Elorduy Walther, 20012007;\nARTICULO 17.- Fue reformado por Decreto No. 206, publicado en el Periódico Oficial\nNo. 33, de fecha 11 de agosto de 2006, Tomo CXIII, expedido por la Honorable XVIII\nLegislatura, siendo Gobernador Constitucional el C. Lic. Eugenio Elorduy Walther, 20012007;\nARTICULO 18.- Fue reformado por Decreto No. 206, publicado en el Periódico Oficial\nNo. 33, de fecha 11 de agosto de 2006, Tomo CXIII, expedido por la Honorable XVIII\nLegislatura, siendo Gobernador Constitucional el C. Lic. Eugenio Elorduy Walther, 20012007; reformado por Decreto No. 229, publicado en el Periódico Oficial No. 30, Índice, Tomo\nCXXX, de fecha 26 de mayo de 2023, expedido por la H. XXIV Legislatura, siendo\nGobernadora Constitucional la C. Marina del Pilar Ávila Olmeda 2021-2027;\nARTICULO 19.- Fue reformado por Decreto No. 206, publicado en el Periódico Oficial\nNo. 33, de fecha 11 de agosto de 2006, Tomo CXIII, expedido por la Honorable XVIII\nLegislatura, siendo Gobernador Constitucional el C. Lic. Eugenio Elorduy Walther, 20012007; reformado por Decreto No. 229, publicado en el Periódico Oficial No. 30, Índice, Tomo\nCXXX, de fecha 26 de mayo de 2023, expedido por la H. XXIV Legislatura, siendo\nGobernadora Constitucional la C. Marina del Pilar Ávila Olmeda 2021-2027; fue reformado por Decreto No. 89, publicado en el Periódico Oficial No. 29, Sección I, de fecha 09 de mayo de 2025, Tomo CXXXII; expedido por la H. XXV Legislatura, siendo Gobernadora\nConstitucional la C. Marina del Pilar Ávila Olmeda, 2021-2027;\nARTICULO 20.- Fue derogado por Decreto No. 206, publicado en el Periódico Oficial\nLegislatura, siendo Gobernador Constitucional el C. Lic. Eugenio Elorduy Walther, 20012007;\nARTICULO 21.- Fue reformado por Decreto No. 206, publicado en el Periódico Oficial\nLegislatura, siendo Gobernador Constitucional el C. Lic. Eugenio Elorduy Walther, 20012007; reformado por Decreto No. 229, publicado en el Periódico Oficial No. 30, Índice, Tomo\nLey de Ejercicio de las Profesiones para el Estado de Baja California. Página 27\nGobernadora Constitucional la C. Marina del Pilar Ávila Olmeda 2021-2027;\nARTICULO 22.- Fue reformado por Decreto No. 206, publicado en el Periódico Oficial\nLegislatura, siendo Gobernador Constitucional el C. Lic. Eugenio Elorduy Walther, 20012007;\nARTICULO 23.- Fue reformado por Decreto No. 206, publicado en el Periódico Oficial\nNo. 33, de fecha 11 de agosto de 2006, Tomo CXIII, expedido por la Honorable XVIII\nLegislatura, siendo Gobernador Constitucional el C. Lic. Eugenio Elorduy Walther, 20012007; reformado por Decreto No. 229, publicado en el Periódico Oficial No. 30, Índice, Tomo\nCXXX, de fecha 26 de mayo de 2023, expedido por la H. XXIV Legislatura, siendo\nGobernadora Constitucional la C. Marina del Pilar Ávila Olmeda 2021-2027;\nARTICULO 24.- Fue reformado por Decreto No. 206, publicado en el Periódico Oficial\nNo. 33, de fecha 11 de agosto de 2006, Tomo CXIII, expedido por la Honorable XVIII\nLegislatura, siendo Gobernador Constitucional el C. Lic. Eugenio Elorduy Walther, 20012007;\nARTICULO 25.- Fue reformado por Decreto No. 206, publicado en el Periódico Oficial\nNo. 33, de fecha 11 de agosto de 2006, Tomo CXIII, expedido por la Honorable XVIII\nLegislatura, siendo Gobernador Constitucional el C. Lic. Eugenio Elorduy Walther, 20012007; fue reformado por Decreto No. 197, publicado en el Periódico Oficial No. 15, de fecha\n12 de marzo de 2021, Tomo CXXVIII, expedido por la Honorable XXIII Legislatura, siendo\nGobernador Constitucional el C. Jaime Bonilla Valdez, 2019-2021; fue reformado por\nDecreto No. 92, publicado en el Periódico Oficial No. 30, Sección III, Tomo CXXIX, de fecha\n09 de mayo de 2022, expedido por la H. XXIV Legislatura, siendo Gobernadora\nConstitucional la C. Marina del Pilar Ávila Olmeda 2021-2027;\nARTICULO 26.- Fue reformado por Decreto No. 238, publicado en el Periódico Oficial\nNo. 24, de fecha 18 de mayo de 2018, Tomo CXXV, expedido por la Honorable XXII\nLegislatura, siendo Gobernador Constitucional el C. Francisco Arturo Vega de Lamadrid, 2013-2019;\nARTICULO 27.- Fue reformado por Decreto No. 206, publicado en el Periódico Oficial\nLegislatura, siendo Gobernador Constitucional el C. Lic. Eugenio Elorduy Walther, 20012007;\nARTICULO 28.- Fue reformado por Decreto No. 206, publicado en el Periódico Oficial\nLegislatura, siendo Gobernador Constitucional el C. Lic. Eugenio Elorduy Walther, 20012007;\nLey de Ejercicio de las Profesiones para el Estado de Baja California. Página 28\nARTICULO 29.- Fue reformado por Decreto No. 206, publicado en el Periódico Oficial\nLegislatura, siendo Gobernador Constitucional el C. Lic. Eugenio Elorduy Walther, 20012007;\nARTICULO 30.- Fue reformado por Decreto No. 206, publicado en el Periódico Oficial\nNo. 33, de fecha 11 de agosto de 2006, Tomo CXIII, expedido por la Honorable XVIII\nLegislatura, siendo Gobernador Constitucional el C. Lic. Eugenio Elorduy Walther, 20012007;\nARTICULO 31.- Fue reformado por Decreto No. 206, publicado en el Periódico Oficial\nNo. 33, de fecha 11 de agosto de 2006, Tomo CXIII, expedido por la Honorable XVIII\nLegislatura, siendo Gobernador Constitucional el C. Lic. Eugenio Elorduy Walther, 20012007;\nARTICULO 33.- Fue reformado por Decreto No. 206, publicado en el Periódico Oficial\nNo. 33, de fecha 11 de agosto de 2006, Tomo CXIII, expedido por la Honorable XVIII\nLegislatura, siendo Gobernador Constitucional el C. Lic. Eugenio Elorduy Walther, 20012007;\nARTICULO 34.- Fue reformado por Decreto No. 206, publicado en el Periódico Oficial\nNo. 33, de fecha 11 de agosto de 2006, Tomo CXIII, expedido por la Honorable XVIII\nLegislatura, siendo Gobernador Constitucional el C. Lic. Eugenio Elorduy Walther, 20012007;\nARTICULO 35.- Fue reformado por Decreto No. 206, publicado en el Periódico Oficial\nNo. 33, de fecha 11 de agosto de 2006, Tomo CXIII, expedido por la Honorable XVIII\nLegislatura, siendo Gobernador Constitucional el C. Lic. Eugenio Elorduy Walther, 20012007;\nARTICULO 36.- Fue reformado por Decreto No. 206, publicado en el Periódico Oficial\nLegislatura, siendo Gobernador Constitucional el C. Lic. Eugenio Elorduy Walther, 20012007;\nARTICULO 37.- Fue reformado por Decreto No. 206, publicado en el Periódico Oficial\nLegislatura, siendo Gobernador Constitucional el C. Lic. Eugenio Elorduy Walther, 20012007; fue modificado mediante fe de erratas publicada en el Periódico Oficial No. 39, de\nGobierno, siendo Gobernador Constitucional el C. Lic. Eugenio Elorduy Walther, 2001-2007;\nLey de Ejercicio de las Profesiones para el Estado de Baja California. Página 29\nARTICULO 38.- Fue derogado por Decreto No. 206, publicado en el Periódico Oficial\nLegislatura, siendo Gobernador Constitucional el C. Lic. Eugenio Elorduy Walther, 20012007;\nARTICULO 39.- Fue reformado por Decreto No. 206, publicado en el Periódico Oficial\nNo. 33, de fecha 11 de agosto de 2006, Tomo CXIII, expedido por la Honorable XVIII\nLegislatura, siendo Gobernador Constitucional el C. Lic. Eugenio Elorduy Walther, 20012007;\nARTICULO 42.- Fue derogado por Decreto No. 206, publicado en el Periódico Oficial\nNo. 33, de fecha 11 de agosto de 2006, Tomo CXIII, expedido por la Honorable XVIII\nLegislatura, siendo Gobernador Constitucional el C. Lic. Eugenio Elorduy Walther, 20012007;\nARTICULO 43.- Fue derogado por Decreto No. 206, publicado en el Periódico Oficial\nNo. 33, de fecha 11 de agosto de 2006, Tomo CXIII, expedido por la Honorable XVIII\nLegislatura, siendo Gobernador Constitucional el C. Lic. Eugenio Elorduy Walther, 20012007;\nARTICULO 45.- Fue derogado por Decreto No. 206, publicado en el Periódico Oficial\nNo. 33, de fecha 11 de agosto de 2006, Tomo CXIII, expedido por la Honorable XVIII\nLegislatura, siendo Gobernador Constitucional el C. Lic. Eugenio Elorduy Walther, 20012007;\nARTICULO 46.- Fue derogado por Decreto No. 206, publicado en el Periódico Oficial\nNo. 33, de fecha 11 de agosto de 2006, Tomo CXIII, expedido por la Honorable XVIII\nLegislatura, siendo Gobernador Constitucional el C. Lic. Eugenio Elorduy Walther, 20012007;\nCAPITULO XI\nDE LA VIGILANCIA E INSPECCION\nARTICULO 47.- Fue reformado por Decreto No. 206, publicado en el Periódico Oficial\nLegislatura, siendo Gobernador Constitucional el C. Lic. Eugenio Elorduy Walther, 20012007;\nARTICULO 48.- Fue reformado por Decreto No. 206, publicado en el Periódico Oficial\nLegislatura, siendo Gobernador Constitucional el C. Lic. Eugenio Elorduy Walther, 20012007;\nLey de Ejercicio de las Profesiones para el Estado de Baja California. Página 30\nARTICULO 49.- Fue reformado por Decreto No. 206, publicado en el Periódico Oficial\nLegislatura, siendo Gobernador Constitucional el C. Lic. Eugenio Elorduy Walther, 20012007;\nARTICULO 50.- Fue reformado por Decreto No. 206, publicado en el Periódico Oficial\nNo. 33, de fecha 11 de agosto de 2006, Tomo CXIII, expedido por la Honorable XVIII\nLegislatura, siendo Gobernador Constitucional el C. Lic. Eugenio Elorduy Walther, 20012007;\nARTICULO 51.- Fue reformado por Decreto No. 206, publicado en el Periódico Oficial\nNo. 33, de fecha 11 de agosto de 2006, Tomo CXIII, expedido por la Honorable XVIII\nLegislatura, siendo Gobernador Constitucional el C. Lic. Eugenio Elorduy Walther, 20012007;\nARTICULO 52.- Fue reformado por Decreto No. 206, publicado en el Periódico Oficial\nNo. 33, de fecha 11 de agosto de 2006, Tomo CXIII, expedido por la Honorable XVIII\nLegislatura, siendo Gobernador Constitucional el C. Lic. Eugenio Elorduy Walther, 20012007;\nARTICULO 54.- Fue reformado por Decreto No. 206, publicado en el Periódico Oficial\nNo. 33, de fecha 11 de agosto de 2006, Tomo CXIII, expedido por la Honorable XVIII\nLegislatura, siendo Gobernador Constitucional el C. Lic. Eugenio Elorduy Walther, 20012007;\nARTICULO 56.- Fue reformado por Decreto No. 206, publicado en el Periódico Oficial\nNo. 33, de fecha 11 de agosto de 2006, Tomo CXIII, expedido por la Honorable XVIII\nLegislatura, siendo Gobernador Constitucional el C. Lic. Eugenio Elorduy Walther, 20012007; reformado por Decreto No. 229, publicado en el Periódico Oficial No. 30, Índice, Tomo\nCXXX, de fecha 26 de mayo de 2023, expedido por la H. XXIV Legislatura, siendo\nGobernadora Constitucional la C. Marina del Pilar Ávila Olmeda 2021-2027;\nARTICULO 56 BIS.- Fue adicionado por Decreto No. 206, publicado en el Periódico\nLegislatura, siendo Gobernador Constitucional el C. Lic. Eugenio Elorduy Walther, 20012007; reformado por Decreto No. 229, publicado en el Periódico Oficial No. 30, Índice, Tomo\nGobernadora Constitucional la C. Marina del Pilar Ávila Olmeda 2021-2027;\nARTICULO 57.- Fue reformado por Decreto No. 206, publicado en el Periódico Oficial\nLegislatura, siendo Gobernador Constitucional el C. Lic. Eugenio Elorduy Walther, 20012007;\nLey de Ejercicio de las Profesiones para el Estado de Baja California. Página 31\nARTICULO 58.- Fue reformado por Decreto No. 206, publicado en el Periódico Oficial\nLegislatura, siendo Gobernador Constitucional el C. Lic. Eugenio Elorduy Walther, 20012007;\nARTICULO 59.- Fue derogado por Decreto No. 206, publicado en el Periódico Oficial\nNo. 33, de fecha 11 de agosto de 2006, Tomo CXIII, expedido por la Honorable XVIII\nLegislatura, siendo Gobernador Constitucional el C. Lic. Eugenio Elorduy Walther, 20012007;\nARTICULO 60.- Fue reformado por Decreto No. 206, publicado en el Periódico Oficial\nNo. 33, de fecha 11 de agosto de 2006, Tomo CXIII, expedido por la Honorable XVIII\nLegislatura, siendo Gobernador Constitucional el C. Lic. Eugenio Elorduy Walther, 20012007;\nARTICULO 61.- Fue reformado por Decreto No. 206, publicado en el Periódico Oficial\nNo. 33, de fecha 11 de agosto de 2006, Tomo CXIII, expedido por la Honorable XVIII\nLegislatura, siendo Gobernador Constitucional el C. Lic. Eugenio Elorduy Walther, 20012007;\nARTICULO 62.- Fue derogado por Decreto No. 206, publicado en el Periódico Oficial\nNo. 33, de fecha 11 de agosto de 2006, Tomo CXIII, expedido por la Honorable XVIII\nLegislatura, siendo Gobernador Constitucional el C. Lic. Eugenio Elorduy Walther, 20012007;\nARTICULO 63.- Fue reformado por Decreto No. 206, publicado en el Periódico Oficial\nNo. 33, de fecha 11 de agosto de 2006, Tomo CXIII, expedido por la Honorable XVIII\nLegislatura, siendo Gobernador Constitucional el C. Lic. Eugenio Elorduy Walther, 20012007;\nARTICULO 64.- Fue adicionado por Decreto No. 206, publicado en el Periódico Oficial\nNo. 33, de fecha 11 de agosto de 2006, Tomo CXIII, expedido por la Honorable XVIII\nLegislatura, siendo Gobernador Constitucional el C. Lic. Eugenio Elorduy Walther, 20012007;\nARTICULO 65.- Fue adicionado por Decreto No. 206, publicado en el Periódico Oficial\nLegislatura, siendo Gobernador Constitucional el C. Lic. Eugenio Elorduy Walther, 20012007;\nARTICULO 66.- Fue adicionado por Decreto No. 206, publicado en el Periódico Oficial\nLegislatura, siendo Gobernador Constitucional el C. Lic. Eugenio Elorduy Walther, 20012007;\nLey de Ejercicio de las Profesiones para el Estado de Baja California. Página 32\nFue adicionado por Decreto No. 206, publicado en el Periódico Oficial No. 33, de fecha 11 de\nGobernador Constitucional el C. Lic. Eugenio Elorduy Walther, 2001-2007;\nCAPÍTULO XIV\nDE LA CERTIFICACIÓN DE PROFESIONISTAS\nARTICULO 67.- Fue adicionado por Decreto No. 206, publicado en el Periódico Oficial\nNo. 33, de fecha 11 de agosto de 2006, Tomo CXIII, expedido por la Honorable XVIII\nLegislatura, siendo Gobernador Constitucional el C. Lic. Eugenio Elorduy Walther, 20012007;\nARTICULO 68.- Fue adicionado por Decreto No. 206, publicado en el Periódico Oficial\nNo. 33, de fecha 11 de agosto de 2006, Tomo CXIII, expedido por la Honorable XVIII\nLegislatura, siendo Gobernador Constitucional el C. Lic. Eugenio Elorduy Walther, 20012007;\nARTICULO 69.- Fue adicionado por Decreto No. 206, publicado en el Periódico Oficial\nNo. 33, de fecha 11 de agosto de 2006, Tomo CXIII, expedido por la Honorable XVIII\nLegislatura, siendo Gobernador Constitucional el C. Lic. Eugenio Elorduy Walther, 20012007;\nARTICULO 70.- Fue adicionado por Decreto No. 206, publicado en el Periódico Oficial\nLegislatura, siendo Gobernador Constitucional el C. Lic. Eugenio Elorduy Walther, 20012007;\nARTICULO 71.- Fue adicionado por Decreto No. 206, publicado en el Periódico Oficial\nLegislatura, siendo Gobernador Constitucional el C. Lic. Eugenio Elorduy Walther, 20012007;\nLey de Ejercicio de las Profesiones para el Estado de Baja California. Página 33\nARTICULO UNICO TRANSITORIO DEL DECRETO No. 206, PUBLICADO EN EL\nQUE SE REFORMAN LOS ARTÍCULOS 2, 3, 9, 11, 13, 14, 15, 16,17,18, 19, 20, 21, 22, 23, 24, 25, 26, 27, 28, 29, 30, 31, 33, 34, 35, 36, 37, 38, 39, 42, 43, 45, 46, 47, 48, 49, 50, 51,\n52, 54, 56, 57, 58, 59, 60, 61, 62, 63, 64, 65, 66, ASIMISMO LA ADICION DEL ARTÍCULO\n56 BIS, Y EL CAPÍTULO XIV DENOMINADO “DE LA CERTIFICACIÓN DE LOS\nPROFESIONISTAS” ADICIONANDO LOS ARTÍCULOS 67, 68, 69, 70 Y 71, EXPEDIDO\nPOR LA H. XVIII LEGISLATURA, SIENDO GOBERNADOR CONSTITUCIONAL EL C.\nEUGENIO ELORDUY WALTHER 2001-2007.\nARTÍCULOS TRANSITORIOS\nARTÍCULO PRIMERO.- Las presentes reformas entrarán en vigor al día siguiente de su publicación en el Periódico Oficial del Estado.\nARTÍCULO SEGUNDO.- Entradas en vigor las presentes reformas, el Ejecutivo del\nEstado contará con 60 días naturales para la realización de las reformas y adecuaciones a el Reglamento de la Ley.\nARTÍCULO TERCERO.- Los Registros Profesionales Estatales que con anterioridad con la reforma a esta Ley hubieren sido legalmente expedidas y registradas en el\nDepartamento de Profesiones, con esa denominación o la que se haya utilizado en su momento y aquellas que se encuentren en trámite a la entrada en vigor a las presentes reformas, seguirán surtiendo sus efectos.\nARTÍCULO CUARTO.- El Departamento de Profesiones tendrá 120 días naturales a partir de la entrada en vigor de la presente reforma, para que haga las adecuaciones administrativas necesarias.\nDADO en el Salón de Sesiones “Lic. Benito Juárez García” del Honorable Poder\nLegislativo, en la Ciudad de Mexicali, Baja California, al primer día del mes de junio del año dos mil seis.\nDIP. RENE ADRIAN MENDIVIL ACOSTA\nPRESIDENTE\nDIP. CARLOS ALBERTO ASTORGA OTHON\nSECRETARIA\nDE CONFORMIDAD CON LO DISPUESTO POR LA FRACCION I DEL ARTICULO 49\nDE LA CONSTITUCION POLITICA DEL ESTADO, MANDO SE IMPRIMA Y PUBLIQUE.\nLey de Ejercicio de las Profesiones para el Estado de Baja California. Página 34\nMEXICALI, BAJA CALIFORNIA, A LOS VEINTICINCO DIAS DEL MES DE JULIO\nDEL AÑO DOS MIL DOS.\nGOBERNADOR DEL ESTADO\nEUGENIO ELORDUY WALTHER\n(RÚBRICA)\nSECRETARIO GENERAL DE GOBIERNO\nBERNARDO H. MARTINEZ AGUIRRE\n(RÚBRICA)\nFUE MODIFICADO MEDIANTE FE DE ERRATAS PUBLICADA EN EL PERIÓDICO\nOFICIAL NO. 39, DE FECHA 22 DE SEPTIEMBRE DE 2006, TOMO CXIII, EXPEDIDA POR\nLA SECRETARÍA GENERAL DE GOBIERNO, SIENDO GOBERNADOR CONSTITUCIONAL\nEL C. LIC. EUGENIO ELORDUY WALTHER, 2001-2007;\nSECRETARIO GENERAL DE GOBIERNO\nBERNARDO H. MARTINEZ AGUIRRE\n(RÚBRICA)\nARTÍCULO ÚNICO TRANSITORIO DEL DECRETO No. 238, POR EL QUE SE\nREFORMA A LOS ARTÍCULOS 9, 23, 26, 29, 31 Y 38, PUBLICADO EN EL PERIÓDICO\nOFICIAL No. 24, SECCIÓN I, TOMO CXXV, DE FECHA 18 DE MAYO DE 2018, EXPEDIDO\nPOR LA H. XXII LEGISLATURA, SIENDO GOBERNADOR CONSTITUCIONAL EL C.\nFRANCISCO ARTURO VEGA DE LAMADRID 2013-2019.\nARTÍCULO TRANSITORIO\nARTÍCULO PRIMERO.- Las presentes reformas entrarán en vigor al día siguiente de su publicación en el Periódico Oficial del Estado.\nARTÍCULO SEGUNDO.- El Ejecutivo del Estado, dentro de los 180 días naturales siguientes a la entrada en vigor de la presente reforma, realizará las modificaciones\nCalifornia, así como hacer las adecuaciones administrativas necesarios para el cumplimiento de la presente reforma.\nARTÍCULO TERCERO.- La Secretaría de Educación y Bienestar Social y el\nDepartamento de Profesiones, realizarán las previsiones presupuestales y programáticas necesarias para el cumplimiento de la presente reforma.\nLey de Ejercicio de las Profesiones para el Estado de Baja California. Página 35 del Estado de Baja California, en la Ciudad de Mexicali, B.C., a los veintiséis días del mes de abril del año dos mil dieciocho.\nDIP. MARCO A. CORONA BOLAÑOS CACHO\nPRESIDENTE\n(RÚBRICA)\nDIP. VICTORIA BENTLEY DUARTE\nSECRETARIA\n(RÚBRICA)\nDE CONFORMIDAD CON LO DISPUESTO POR LA FRACCIÓN I DEL ARTÍCULO 49\nMEXICALI, BAJA CALIFORNIA, A LOS ONCE DÍAS DEL MES DE MAYO DEL AÑO DOS\nMIL DIECIOCHO.\nFRANCISCO ARTURO VEGA DE LAMADRID\nGOBERNADOR DEL ESTADO\n(RÚBRICA)\nFRANCISCO RUEDA GÓMEZ\nSECRETARIO GENERAL DE GOBIERNO\n(RÚBRICA)\nARTÍCULO ÚNICO TRANSITORIO DEL DECRETO No. 240, POR EL QUE SE\nREFORMA A LA FRACCIÓN XII DEL ARTÍCULO 3, PUBLICADO EN EL PERIÓDICO\nEXPEDIDO POR LA H. XXII LEGISLATURA, SIENDO GOBERNADOR CONSTITUCIONAL\nEL C. FRANCISCO ARTURO VEGA DE LAMADRID 2013-2019.\nARTÍCULO TRANSITORIO\nARTÍCULO PRIMERO.- La presente reforma entrará en vigor al día siguiente de su publicación en el Periódico Oficial del Estado. del Estado de Baja California, en la Ciudad de Mexicali, B.C., a los veintiséis días del mes de abril del año dos mil dieciocho.\nLey de Ejercicio de las Profesiones para el Estado de Baja California. Página 36\nDIP. MARCO A. CORONA BOLAÑOS CACHO\nPRESIDENTE\n(RÚBRICA)\nDIP. VICTORIA BENTLEY DUARTE\nSECRETARIA\n(RÚBRICA)\nDE CONFORMIDAD CON LO DISPUESTO POR LA FRACCIÓN I DEL ARTÍCULO 49\nMEXICALI, BAJA CALIFORNIA, A LOS ONCE DÍAS DEL MES DE MAYO DEL AÑO\nDOS MIL DIECIOCHO.\nFRANCISCO ARTURO VEGA DE LAMADRID\nGOBERNADOR DEL ESTADO\n(RÚBRICA)\nFRANCISCO RUEDA GÓMEZ\nSECRETARIO GENERAL DE GOBIERNO\n(RÚBRICA)\nARTÍCULO ÚNICO TRANSITORIO DEL DECRETO No. 197, POR EL QUE SE\nREFORMA EL ARTÍCULO 25, PUBLICADO EN EL PERIÓDICO OFICIAL No. 15, SECCIÓN\nIII, TOMO CXXVIII, DE FECHA 12 DE MARZO DE 2021, EXPEDIDO POR LA H. XXIII\nLEGISLATURA, SIENDO GOBERNADOR CONSTITUCIONAL EL C. JAIME BONILLA\nVALDEZ.\nARTÍCULO TRANSITORIO\nÚNICO.- La presente reforma entrará en vigor al día siguiente de su publicación en el\nPeriódico Oficial del Estado.\nDADO en Sesión Ordinaria Virtual en la Ciudad de Mexicali, B.C., a los diez días del mes de febrero del año dos mil veintiuno.\nDIP. EVA GRICELDA RODRÍGUEZ\nPRESIDENTA\nLey de Ejercicio de las Profesiones para el Estado de Baja California. Página 37\nDIP. MARÍA LUISA VILLALOBOS ÁVILA\nSECRETARIA\n(RÚBRICA)\nDE CONFORMIDAD CON LO DISPUESTO POR LA FRACCIÓN I DEL ARTÍCULO 49\nCALIFORNIA, IMPRÍMASE Y PUBLÍQUESE.\nMEXICALI, BAJA CALIFORNIA, A LOS QUINCE DÍAS DEL MES DE FEBRERO DEL AÑO\nDOS MIL VEINTIUNO.\nJAIME BONILLA VALDEZ\nGOBERNADOR DEL ESTADO\n(RÚBRICA)\nAMADOR RODRÍGUEZ LOZANO\nSECRETARIO GENERAL DE GOBIERNO\n(RÚBRICA)\nARTÍCULO ÚNICO TRANSITORIO DEL DECRETO No. 92, POR EL QUE SE\nAPRUEBA LA REFORMA AL ARTÍCULO 25; PUBLICADO EN EL PERIÓDICO OFICIAL No.\n30, SECCIÓN III, TOMO CXXIX, DE FECHA 09 DE MAYO DE 2022, EXPEDIDO POR LA H.\nXXIV LEGISLATURA, SIENDO GOBERNADORA CONSTITUCIONAL LA C. MARINA DEL\nPILAR ÁVILA OLMEDA 2021 – 2027.\nTRANSITORIO\nÚNICO.- La presente reforma entrará en vigor al día siguiente de su publicación en el\nPeriódico Oficial del Estado.\nDADO en Sesión Ordinaria de la XXIV Legislatura en la Ciudad de Mexicali, B.C., a los veintiún días del mes de abril del año dos mil veintidós.\nDIP. JULIA ANDREA GONZÁLEZ QUIROZ\nPRESIDENTA\nDIP. MANUEL GUERRERO LUNA\nSECRETARIO\nLey de Ejercicio de las Profesiones para el Estado de Baja California. Página 38\nDE CONFORMIDAD CON LO DISPUESTO POR LA FRACCIÓN I DEL ARTÍCULO 49\nCALIFORNIA, IMPRÍMASE Y PUBLÍQUESE.\nMEXICALI, BAJA CALIFORNIA, A LOS VEINTICINCO DÍAS DEL MES DE ABRIL\nDEL AÑO DOS MIL VEINTIDÓS.\nMARINA DEL PILAR ÁVILA OLMEDA\nGOBERNADORA DEL ESTADO\nDE BAJA CALIFORNIA\n(RÚBRICA)\nCATALINO ZAVALA MÁRQUEZ\nSECRETARIO GENERAL DE GOBIERNO\nDEL ESTADO DE BAJA CALIFORNIA\n(RÚBRICA)\nARTÍCULO SEGUNDO TRANSITORIO DEL DECRETO No. 229, POR EL QUE SE\nAPRUEBA LA REFORMA A LOS ARTÍCULOS 3, 4, 14, 18, 19, 21, 23, 56 y 56 BIS;\nPUBLICADO EN EL PERIÓDICO OFICIAL No. 30, ÍNDICE, TOMO CXXX, DE FECHA 26\nDE MAYO DE 2023, EXPEDIDO POR LA H. XXIV LEGISLATURA, SIENDO\nGOBERNADORA CONSTITUCIONAL LA C. MARINA DEL PILAR ÁVILA OLMEDA 2021 –\n2027.\nTRANSITORIOS\nPRIMERO.- Las presentes reformas entrarán en vigor al día siguiente de su publicación en el Periódico Oficial del Estado de Baja California.\nSEGUNDO.- Las y los profesionistas que ejerzan en Baja California, y cuyo Título profesional haya sido expedido en otra entidad federativa, en caso de no contar con su\nRegistro Profesional Estatal, tendrán un plazo de dos meses para solicitarlo.\nDADO en Sesión Extraordinaria de la XXIV Legislatura en la Ciudad de Mexicali, B.C., a los veintiocho días del mes de abril del año dos mil veintitrés.\nDIP. MANUEL GUERRERO LUNA\nPRESIDENTE\nDIP. ALEJANDRA MARÍA ANG HERNÁNDEZ\nSECRETARIA\nLey de Ejercicio de las Profesiones para el Estado de Baja California. Página 39\nDE CONFORMIDAD CON LO DISPUESTO POR LA FRACCIÓN I DEL ARTÍCULO 49\nCALIFORNIA, IMPRÍMASE Y PUBLÍQUESE.\nMEXICALI, BAJA CALIFORNIA, A LOS OCHO DÍAS DEL MES DE MAYO DEL AÑO\nDOS MIL VEINTITRÉS.\nMARINA DEL PILAR ÁVILA OLMEDA\nGOBERNADORA DEL ESTADO\nDE BAJA CALIFORNIA\n(RÚBRICA)\nCATALINO ZAVALA MÁRQUEZ\nSECRETARIO GENERAL DE GOBIERNO\nDEL ESTADO DE BAJA CALIFORNIA\n(RÚBRICA)\nARTÍCULO ÚNICO TRANSITORIO DEL DECRETO No. 89, POR EL QUE SE\nAPRUEBA LA REFORMA AL ARTÍCULO 19; PUBLICADO EN EL PERIÓDICO OFICIAL No.\n29, SECCIÓN I, DE FECHA 09 DE MAYO DE 2025, TOMO CXXXII; EXPEDIDO POR LA H.\nXXV LEGISLATURA, SIENDO GOBERNADORA CONSTITUCIONAL LA C. MARINA DEL\nPILAR ÁVILA OLMEDA 2021-2027.\nARTICULO TRANSITORIO\nÚNICO. El presente Decreto entrará en vigor el día siguiente al de su publicación en el\nPeriódico Oficial del Estado de Baja California.\nDADO en Sesión Ordinaria de la XXV Legislatura en la Ciudad de Mexicali, B.C., a los veinticuatro días del mes de abril del año dos mil veinticinco.\nDIP. MICHELLE ALEJANDRA TEJEDA MEDINA\nPRESIDENTA\nDIP. NORMA ANGELICA PEÑALOZA ESCOBEDO\nSECRETARIA\nDE CONFORMIDAD CON LO DISPUESTO POR LA FRACCIÓN I DEL ARTÍCULO 49\nCALIFORNIA, IMPRÍMASE Y PUBLÍQUESE.\nLey de Ejercicio de las Profesiones para el Estado de Baja California. Página 40\nMEXICALI, BAJA CALIFORNIA, A LOS 25 DÍAS DEL MES DE ABRIL DEL AÑO DOS\nMIL VEINTICINCO.\nMARINA DEL PILAR ÁVILA OLMEDA\nGOBERNADORA DEL ESTADO\nDE BAJA CALIFORNIA\nALFREDO ÁLVAREZ CÁRDENAS\nSECRETARIO GENERAL DE GOBIERNO\nDEL ESTADO DE BAJA CALIFORNIA\nLey de Ejercicio de las Profesiones para el Estado de Baja California. Página 41",
  "ordenamiento": "REGLAMENTO",
  "jurisdiccion": "BAJA CALIFORNIA",
  "fuente_oficial": "Periódico Oficial",
  "FECHA PER OFIC": "2025/05/09",
  "ESTATUS": "VIGENTE",
  "TOMO": "TOMO_VI",
  "URL": "https://www.congresobc.gob.mx/Documentos/ProcesoParlamentario/Leyes/TOMO_VI/20250509_LEYEPROFE.PDF",
  "es_escaneado": false,
  "tiene_tablas": false,
  "materia": [
    "social",
    "salud",
    "educación",
    "cultura"
  ]
}