{
  "titulo": "Ley ORGÁNICA DEL PODER JUDICIAL DEL ESTADO DE BAJA CALIFORNIA",
  "Contenido": "BAJA CALIFORNIA\nTomo CII\nTITULO PRIMERO\nDEL PODER JUDICIAL DEL ESTADO\nCAPITULO I\nDISPOSICIONES GENERALES\nARTÍCULO 1.- Corresponde a los Tribunales de Justicia del Fuero Común del Estado de Baja California, dentro de los términos que establece la Constitución General de la civiles, penales, laborales, de extinción de dominio, familiares y de justicia para adolescentes, que sean de su conocimiento, así como los casos en que las demás leyes les concedan jurisdicción.\nPárrafo Reformado\nLa facultad a que se refiere el párrafo anterior se ejerce:\nI.- Por el Tribunal Superior de Justicia, actuando en Pleno o en Salas.\nII.- Por los Jueces de Primera Instancia en Materia Civil.\nIII.- Por los Jueces de Primera Instancia de lo Familiar.\nIV.- Por los Jueces de Primera Instancia del Ramo Penal.\nV.- Por el Juez de Primera Instancia en materia de extinción de dominio.\nVI.- Por los Jueces de Primera Instancia de Jurisdicción Mixta.\nVII.- Por los Jueces de Primera Instancia Especializados para Adolescentes.\nVIII.- Por los Jueces de Paz.\nIX.- Por los Jueces en materia Laboral.\nFracción Reformada\nX.- Por las y los Jueces Especializados en Violencia Familiar contra las Mujeres.\nFracción Adicionada, recorriéndose las subsecuentes\nXI.- Por las y los Jueces Especializados en materia Hipotecaria.\nFracción Adicionada, recorriéndose las subsecuentes\nXII.- Por el Consejo de la Judicatura del Estado de Baja California.\nXIII.- Por los y las demás Servidores Públicos y auxiliares de la administración de\nJusticia en los términos que establezca esta Ley, los Códigos de Procedimientos y Leyes correspondientes.\nArtículo Reformado\nI.- El Tribunal Superior de Justicia, actuando en Pleno o en Salas;\nII.- Los Juzgados de Primera Instancia en Materia Civil;\nIII.- Los Juzgados de primera Instancia en Materia Familiar;\nIV.- Los Juzgados de Primera Instancia del Ramo Penal;\nV.- El Juzgado de Primera Instancia en materia de extinción de dominio;\nVI.- Los Juzgados de Primera Instancia Especializados para Adolescentes;\nFracción Reformada\nVII.- Los Juzgados de Paz;\nFracción Reformada\nVIII.- Los Tribunales en materia Laboral;\nFracción Adicionada\nFracción Reformada\nIX.- Los Juzgados Especializados en Violencia Familiar contra las Mujeres;\nFracción Adicionada\nFracción Reformada\nX.- Los Juzgados Especializados en Materia Hipotecaria; y,\nFracción Adicionada\nXI.- Los Juzgados Itinerantes.\nFracción Adicionada\nLos órganos del Poder Judicial del Estado, funcionarán de modo permanente e ininterrumpido durante cada año de actividades. El Consejo de la Judicatura dictará las medidas correspondientes para la organización permanente de las actividades de los juzgados de conformidad con el Título Decimoprimero de esta Ley.\nCon independencia de lo dispuesto en el párrafo anterior, el Consejo de la Judicatura aquellas comunidades que considere pertinentes.\nPárrafo Adicionado\nArtículo Reformado\nARTICULO 3.- En lo no previsto por el presente ordenamiento legal, será\nCalifornia, con excepción a lo dispuesto por el Título Decimocuarto de esta Ley.\nArtículo Reformado\nARTICULO 4.- Son auxiliares de la administración de Justicia:\nII.- Las Oficialías del Registro Civil.\nIII.- Los peritos médicos legistas.\nIV.- Los intérpretes oficiales y demás peritos en los ramos que se les encomienden.\nV.- Los síndicos e interventores de concursos y quiebras.\nVI.- Los albaceas e interventores de sucesiones, los tutores, curadores y notarios, en las funciones que les encomienda el Código de Procedimientos Civiles.\nVII.- Los depositarios e interventores.\nVIII.- Los Presidentes municipales, los delegados municipales, los jefes y agentes de los cuerpos policiacos del Estado y Municipales.\nIX.- Todos los demás a quienes las leyes les confieran este cargo.\nLos auxiliares comprendidos en las fracciones de la III a VII de este artículo, están obligados a cumplir las órdenes de las autoridades y servidores de la administración de justicia. El Ejecutivo del Estado, facilitará a los tribunales del Estado, los medios necesarios para el ejercicio de sus funciones.\nTITULO SEGUNDO\nDE LA DIVISION TERRITORIAL\nCAPITULO I\nDE LOS PARTIDOS JUDICIALES\nARTICULO 5.- El Estado de Baja California, para los efectos de esta Ley, se divide en los siguientes partidos judiciales:\nI.- En el de Mexicali, con la comprensión política administrativa del Municipio de ese nombre.\nII.- El de Tijuana, con la comprensión política administrativa del Municipio de ese nombre, así como el del Municipio de Playas de Rosarito.\nIII.- El de Ensenada, con la comprensión política administrativa del Municipio de ese nombre.\nIV.- El de Tecate, con la comprensión política administrativa del Municipio de ese nombre.\nV.- El de Playas de Rosarito, con la comprensión política administrativa del Municipio de ese nombre.\nVI.- El de San Quintín, con la comprensión política administrativa del Municipio de ese nombre.\nFracción Adicionada\nVII. El de San Felipe, con la comprensión política administrativa del Municipio de ese nombre.\nFracción Adicionada\nVIII. Los Partidos Judiciales que determine el Consejo de la Judicatura del Estado, para la mejor administración de justicia, conforme al presupuesto de egresos respectivo.\nFracción Recorrida\nArtículo Reformado\nARTICULO 6.- Las cabeceras de los partidos judiciales del Estado, serán, respectivamente, las ciudades de Mexicali, Tijuana, Ensenada, Tecate, Playas de Rosarito, San Quintín y San Felipe.\nArtículo Reformado\nTITULO TERCERO\nDE LAS DESIGNACIONES, CONDICIONES Y PROHIBICIONES\nPARA EJERCER FUNCIONES JUDICIALES\nCAPITULO I\nDE LOS NOMBRAMIENTOS\nARTICULO 7.- Los nombramientos de los Magistrados del Tribunal Superior de\nJusticia, se harán en forma y términos que previene el Artículo 58 de la Constitución Política del Estado y rendirán la protesta de Ley ante el Congreso o la Comisión Permanente, en su caso.\nArtículo Reformado\nARTICULO 8.- Los Jueces, Secretario General de Acuerdos, Secretarios de Estudio y\nCuenta, Secretarios Auxiliares y Actuarios del Tribunal Superior de Justicia, así como los\nSecretarios de Acuerdos y Actuarios de los Juzgados, serán designados en los términos que aplicables.\nLos demás servidores públicos del Tribunal Superior de Justicia, Juzgados y otros\nArtículo Reformado\nARTICULO 9.- Las designaciones o nombramientos de servidores públicos del Poder anterior, serán realizados por los órganos o servidores públicos a quienes la Constitución y esta Ley confieran la facultad de realizar los nombramientos o designaciones definitivos.\nTratándose de los Jueces se aplicará lo dispuesto en el párrafo anterior, salvo los supuestos especiales contenidos en otros artículos de esta Ley.\nArtículo Reformado\nARTICULO 10.- Derogado.\nArtículo Derogado\nARTICULO 11.- Los servidores Públicos a que se refieren los tres artículos precedentes, rendirán protesta de ley ante el Consejo de la Judicatura en Pleno o ante la\nComisión respectiva, firmando el acta circunstanciada de su aceptación que el interesado haga del cargo o empleo que se le confiere, protestando guardar y hacer guardar la que de ellas emanen, con toda honradez y lealtad.\nARTICULO 12.- Derogado.\nArticulo Derogado\nCAPITULO II\nDE LAS CONDICIONES\nARTICULO 13.- Los empleados del Poder Judicial deberán reunir al día de la designación los siguientes requisitos:\nSer mexicano en pleno uso de sus derechos civiles y políticos; mayores de dieciocho años; de buena conducta; tener la capacidad necesaria para el desempeño del cargo a juicio del Consejo de la Judicatura del Estado; y no ser parientes en los grados a que se refiere el\nArtículo 18 de ésta Ley, del titular de la oficina donde vayan a prestar sus servicios.\nARTICULO 14.- Toda persona que fuere nombrada para desempeñar algún cargo o empleo en el Poder Judicial del Estado, deberán la Protesta conforme a la Ley, y comenzar a ejercer las funciones que le correspondan, dentro de los cinco días hábiles siguientes al de la fecha de su nombramiento. Si no se presentare, el nombramiento se tendrá por no hecho y se procederá a hacer una nueva designación.\nARTICULO 15.- Los magistrados, jueces y demás servidores y empleados de la\nAdministración de Justicia, tienen derecho a ser jubilados en los términos que dispongan las leyes respectivas.\nARTICULO 16.- El retiro de los Jueces, Secretarios de Acuerdos y Actuarios, así como demás servidores y empleados judiciales, se producirá al cumplir setenta años o por padecer incapacidad física o mental que le impidan desempeñar el cargo.\nCAPITULO III\nDE LAS PROHIBICIONES, INCOMPATIBILIDADES\nE INCAPACIDADES. particular. Con excepción de los Magistrados Supernumerarios, mientras no sean llamados para cubrir una falta temporal o absoluta.\nAdministración de Justicia.\nArtículo Reformado\nARTICULO 18.- Ningún nombramiento para empleado de la Administración de\nJusticia o auxiliar de ésta, podrá recaer en los casos a que se refiera el reglamento y en ascendientes, descendientes, cónyuges o colaterales dentro del cuarto grado por consanguinidad o segundo por afinidad de los Consejeros al Consejo de la Judicatura y magistrados del Tribunal, excepto en los casos de los servidores públicos que ya se encuentran laborando dentro del Poder Judicial con anterioridad a la designación del\nConcejero de la Judicatura. La inobservancia de esta disposición es motivo de responsabilidad de quien o quienes aprueban la designación, procediéndose a la remoción inmediata respecto del servidor público indebidamente designado.\nARTICULO 19.- Ningún servidor de la Administración de Justicia podrá desempeñar otro puesto oficial, ni ser notario, corredor, comisionista, apoderado judicial, tutor, curador, albacea, síndico, depositario, administrador, interventor en concurso, árbitro o arbitrador, ni ejercer la abogacía sino en causa propia.\nARTICULO 20.- No podrá recaer ningún nombramiento de la Administración de\nJusticia en individuos ciegos, sordomudos o con enfermedades transmisibles que constituyan un peligro para la salubridad y dificulten gravemente el desempeño de las funciones respectivas.\nTITULO CUARTO\nDE LA ORGANIZACION\nDE LOS TRIBUNALES\nCAPITULO I\nDEL TRIBUNAL SUPERIOR\nARTICULO 21.- El Tribunal Superior de Justicia, estará integrado por trece\nMagistrados Numerarios como mínimo y tres Supernumerarios. Funcionará en Pleno o en colegiadas.\nAdemás contará con una Sala Unitaria Especializada para Adolescentes.\nArtículo Reformado\nARTICULO 22.- Uno de los Magistrados Numerarios será el Presidente del Tribunal\nSuperior de Justicia, quien también lo será del Consejo de la Judicatura del Estado.\nArtículo Reformado\nArtículo Reformado\nARTICULO 24.- Para ser Secretario General de Acuerdos, Secretario de Estudio y\nCuenta, o Secretario Auxiliar del Tribunal Superior de Justicia, se requiere:\nI.- Ser ciudadano en pleno ejercicio de sus derechos políticos y civiles.\nII.- Tener residencia mínima de cinco años en el Estado, anteriores al día de la designación.\nIII.- Poseer al día de la designación, con antiguedad mínima de cinco años, Título profesional de Licenciado en Derecho.\nIV.- Tener más de treinta y menos de sesenta y cinco años de edad, al día de su designación.\nV.- Tener práctica profesional suficiente a juicio del Consejo de la Judicatura del\nEstado.\nVI.- Gozar de buena reputación y no haber sido condenado por delito que amerite pena corporal de más de un año de prisión; pero si se tratare de robo, fraude, falsificación, abuso de confianza u otro que lastime seriamente la buena fama en el concepto público, inhabilitará para el cargo, cualquiera que haya sido la pena.\nArtículo Reformado\nARTICULO 25.- Para ser Actuario del Tribunal Superior de Justicia se requiere:\nI.- Ser ciudadano Mexicano en pleno ejercicio de sus derechos políticos y civiles.\nII.- Tener residencia mínima de cinco años en el Estado, anteriores al día de la designación.\nIII.- Poseer al día de la designación, Título profesional de Licenciado en Derecho, excepto cuando sean prestadores de servicio social.\nIV.- Gozar de buena reputación y no haber sido condenado por delito que amerite pena corporal de más de un año de prisión; pero si se tratare de robo, fraude, falsificación, abuso de confianza u otro que lastime seriamente la buena fama en el concepto público, inhabilitará para el cargo, cualquiera que haya sido la pena.\nArtículo Reformado\nARTICULO 26.- Los demás empleados deberán llenar los requisitos a que se refiere el artículo 13 de este ordenamiento.\nARTÍCULO 27.- El personal del Tribunal Superior de Justicia se compondrá:\nI.- De una Secretaria General de Acuerdos, una Secretaria General de Acuerdos\nAdjunto, y de las y los Secretarios Auxiliares que sean necesarios, mismos que ejercerán en el cargo en la adscripción que determine el Pleno del Tribunal Superior de Justicia; las y los competencia de la Presidencia y del Tribunal en Pleno; autorizar, certificar y dar fe de las actuaciones en que intervengan, documentos y correspondencia oficial; practicar las diligencias que se ordenen en los negocios cuyo conocimiento corresponda al Pleno; de imponerse diariamente de la correspondencia que se reciba, dando cuenta a la presidencia; poner constancia del día y hora en que se presenten o reciban las promociones, en su original y copia, turnándola en su caso, a la Sala correspondiente; distribuir, organizar y vigilar bajo su responsabilidad las labores de las y los empleados de la Secretaría y demás que señalen las leyes.\nFracción Reformada\nII.- De los Secretarios de Estudio y Cuenta, y Secretarios Auxiliares adscritos a cada\nSala.\nIII.- De un coordinador administrativo de la Actuaría, que será preferentemente un secretario auxiliar y los actuarios necesarios para el desarrollo eficaz de su actividad, y demás personal necesario para el cumplimiento de sus atribuciones, y demás personal que para el buen desempeño de sus funciones autorice el presupuesto de egresos.\nArtículo Reformado\nARTICULO 28.- El Pleno del Tribunal Superior de Justicia, estará formado por los magistrados que integren las Salas y por el que designe para presidir, en los términos del artículo 38 de esta ley.\nCAPITULO II\nDEL TRIBUNAL EN PLENO\nARTÍCULO 29.- Son facultades del Tribunal Superior de Justicia en Pleno:\nI.- Elegir de entre sus miembros al Presidente del Tribunal, en los términos que esta\nLey determina.\nII.- Calificar en cada caso, las excusas o impedimentos que sus miembros presenten para conocer de determinado negocio en Pleno o en Salas.\nIII.- Dar al Congreso, al Ejecutivo del Estado y al Consejo de la Judicatura, los informes que pidieren, relativos a la Administración de Justicia.\nIV.- Ordenar, por conducto del Presidente del Tribunal, se haga la consignación que corresponda al Ministerio Público, de los jueces o empleados de la administración de justicia, por delitos comunes o responsabilidades oficiales en que incurran.\nV.- Exigir al Presidente del Tribunal el fiel cumplimiento de sus obligaciones y la responsabilidad en que incurran de acuerdo con la Ley, en el ejercicio de sus funciones.\nVI.- Informar al Ejecutivo o al Congreso del Estado, emitiendo su opinión en los casos de indulto, rehabilitación y demás que las leyes determinen previos los trámites y con los requisitos que ellas establezcan.\nVII.- Imponer correcciones disciplinarias a los litigantes cuando sean irrespetuosos en las promociones que formulen ante el Tribunal.\nVIII.- Proponer iniciativas de leyes y decretos, en asuntos relacionados con la organización y funcionamiento de la Administración de Justicia.\nIX.- Resolver en el caso de discrepancia de criterios jurídicos entre dos o más salas, fijando tesis obligatoria para el Pleno y Salas del Tribunal Superior, así como Juzgados dependientes de éste.\nX.- Invitar a sus sesiones cuando lo estime conveniente al Consejo de la Judicatura.\nXI.- Dictar las disposiciones necesarias para regular el turno de los asuntos de la competencia de las Salas y Juzgados. demás leyes relativas.\nXIII.- Iniciar Leyes de Decretos ante al Congreso del Estado, en asuntos relacionados con la organización y funcionamiento de la Administración de Justicia.\nXIV.- Instrumentar y reglamentar como es que el Poder Judicial y sus órganos jurisdiccionales suministrarán, intercambiarán, sistematizarán, consultarán, analizarán y actualizarán, la información que se genere sobre el incumplimiento de las obligaciones alimentarias en el ámbito de sus competencias utilizando los sistemas e instrumentos tecnológicos del Sistema Nacional DIF para integrar el Registro Nacional de Obligaciones\nAlimentarias.\nFracción Adicionada, recorriéndose la subsecuente\nXV.- Las demás que se establezcan en la Constitución local, esta Ley y demás ordenamientos.\nFracción Adicionada\nArtículo Reformado\nARTICULO 30.- Para que funcione el Tribunal en Pleno, se requiere de la concurrencia de la mayoría de los magistrados propietarios y la del Secretario General o de quien haga sus veces conforme a la Ley.\nARTICULO 31.- Las sesiones del Tribunal serán fijadas en el calendario anual que se apruebe a propuesta del Presidente o de los Magistrados, mismas que se celebrarán semanalmente el día y la hora preestablecido en la agenda, previa convocatoria del\nPresidente en la que determinará si son de carácter público o privado.\nSe podrá sesionar fuera de calendario, para tratar y resolver únicamente aquellos asuntos de carácter urgente o extraordinario, previa convocatoria del Presidente por iniciativa propia o de los Magistrados.\nArtículo Reformado\nARTICULO 32.- En las sesiones privadas en las que deban tomarse acuerdos reservados, desempeñará las funciones de Secretario el Magistrado que elija el Pleno.\nArtículo Reformado\nARTÍCULO 32 BIS.- El Pleno del Tribunal Superior de Justicia deberá reunirse por electrónicos de los que disponga el Poder Judicial del Estado, previa convocatoria del\nPresidente.\nArtículo Reformado\nCAPITULO III\nDE LAS VISITAS A LOS CENTROS DE\nREADAPTACION\nARTICULO 33.- El Pleno del Consejo de la Judicatura del Estado designará a la\nComisión que acompañada de los Jueces penales y un representante de la Dirección de\nPrevención y Readaptación Social, visiten los Centros de Custodia y Readaptación Social en el Estado.\nARTICULO 34.- Las visitas se practicarán sin previo aviso a los alcaides o directores de los establecimientos respectivos.\nARTICULO 35.- Las visitas tendrán por objeto:\nI.- Enterarse de la situación de higiene y seguridad de los establecimientos.\nII.- Verificar el tratamiento que reciben los indiciados, procesados y reos.\nIII.- De la conducta de los servidores públicos encargados de los establecimientos.\nIV.- De la asistencia que reciben los procesados por parte de los defensores de oficio.\nV.- De la atención que reciben por parte de las autoridades judiciales encargadas de sus procesos.\nVI.- Las demás observaciones que permitan mejorar el sistema penitenciario.\nARTICULO 36.- Al practicarse la visita, la Comisión del Consejo de la Judicatura del en la que se hará constar todo lo que ocurra durante ella, así como las quejas y reclamaciones que presenten los internos y las explicaciones de los encargados del Centro.\nARTICULO 37.- Las actas a que se refiere el artículo anterior, serán sometidas a la\nCAPITULO IV\nDEL PRESIDENTE DEL TRIBUNAL\nSUPERIOR DE JUSTICIA\nARTICULO 38.- El Presidente del Tribunal Superior de Justicia, será nombrado por el\nPleno entre los Magistrados Numerarios, en votación secreta y escrutinio público, y en la primera sesión que se celebre durante el mes de noviembre de cada año. Durará en su cargo tres años y podrá ser reelecto para un periodo consecutivo por una sola ocasión.\nEl Magistrado que habiendo sido reelecto cumpliera con el término de tres años, pasado un periodo de tres años posterior a aquel momento, podrá volver a ser electo\nPresidente del Tribunal Superior de Justicia en términos del párrafo anterior. El Presidente del Tribunal Superior de Justicia, será nombrado por el Pleno entre los Magistrados\nNumerarios, en votación secreta y escrutinio público, y en la primera sesión que se celebre durante el mes de noviembre de cada año. Durará en su cargo tres años y podrá ser reelecto para un periodo consecutivo por una sola ocasión.\nEl Magistrado que habiendo sido reelecto cumpliera con el término de tres años, pasado un periodo de tres años posterior a aquel momento, podrá volver a ser electo\nPresidente del Tribunal Superior de Justicia en términos del párrafo anterior.\nArtículo Reformado\nARTICULO 39.- Corresponde al Presidente del Tribunal Superior:\nI.- Vigilar que la Administración de Justicia sea pronta, completa e imparcial para cuyo efecto, dictará las providencias que fueren necesarias y oportunas.\nII.- Representar al Tribunal Superior en los actos oficiales.\nIII.- Dar cuenta al Pleno de los actos que lleve a cabo en el ejercicio de sus funciones.\nIV.- Vigilar la publicación del Boletín Judicial.\nV.- Tramitar, auxiliado por el Secretario General de Acuerdos, todos los asuntos de la competencia del Pleno, hasta ponerlos en estado de resolución.\nVI.- Distribuir los asuntos a cada una de las Salas, así como designar en los negocios civiles al magistrado ponente, a quien corresponda formular el proyecto de resolución, como mejor convenga a la buena marcha del Tribunal, por riguroso turno.\nVII.- Llevar la correspondencia del Tribunal Superior.\nVIII.- Comunicar al Consejo de la Judicatura las faltas temporales y absolutas de los magistrados.\nIX.- Poner en conocimiento del Pleno del Consejo de la Judicatura las faltas atribuciones.\nX.- Remitir al Juez correspondiente los exhortos, rogatorias, suplicatorias, requisitorias y despachos, de acuerdo con el turno que al efecto se lleve.\nXI.- Conceder diariamente audiencia al público.\nXII.- Llevar el turno de los Magistrados Propietarios que se excusen de conocer de alguno de los negocios de su competencia, o sean recusados, para hacer las designaciones de suplencia.\nXIII.- Rendir informe anual ante el Pleno del Tribunal Superior de Justicia y ante el\nPleno del Consejo de la Judicatura sobre las actividades desarrolladas por el Poder Judicial, relativas a la administración de justicia.\nXIV.- Presidir la Comisión Interinstitucional a que hace referencia el artículo 9 de la\nLey que establece las Bases de Operación de la Justicia Terapéutica para el Estado de Baja\nCalifornia.\nFracción Adicionada\nArtículo Reformado\nARTICULO 40.- Las providencias y acuerdos del Presidente pueden reclamarse ante el Pleno, por parte interesada, dentro del término de tres días, siempre que se presente por escrito con expresión del agravio que considere la causa.\nARTICULO 41.- Cuando se trate de conocer de las correcciones disciplinarias que haya impuesto el Presidente del Tribunal, o de exigir, en su caso, las responsabilidades que procedan, presidirá la sesión respectiva del Pleno el Magistrado que al efecto resulte electo mediante procedimiento de insaculación.\nARTICULO 42.- En caso de que el Presidente estime dudoso o transcendental un trámite de su competencia, lo someterá a la consideración del Pleno para que éste resuelva lo que proceda.\nARTICULO 43.- El Presidente del Tribunal Superior tendrá a su cargo la policía de los edificios que custodien el Tribunal y Juzgados, dictará las medidas adecuadas a su conservación e higiene. Para este efecto, los edificios, sus consejerías, servidumbre y mobiliario estarán a su disposición en los términos que fije el reglamento. Esta facultad se despachen en el edificio, para conservar el orden en sus respectivos locales.\nARTICULO 44.- El Presidente del Tribunal Superior de Justicia es Presidente del\nTribunal en Pleno, y como tal, tendrá las siguientes obligaciones:\nI.- Presidir las sesiones que celebre el Tribunal en Pleno.\nII.- Dirigir los debates y conservar el orden durante las audiencias y sesiones.\nIII.- Llevar la correspondencia del Tribunal en Pleno.\nIV.- Convocar a sesiones extraordinarias cada vez que lo crea conveniente o lo pida alguno de los magistrados.\nV.- Proponer al Pleno los acuerdos que juzgue conducentes para la mejor impartición de justicia.\nVI.- Ejercer las atribuciones que le asigne el Reglamento Interior del Tribunal Superior de Justicia.\nVII.- Firmar, en unión de los magistrados asistentes y del secretario, las correspondientes actas, haciendo constar en ellas las deliberaciones del Pleno y los\nAcuerdos que éste dicte en los negocios de su competencia, cuidando de su despacho y ejecución.\nVIII.- Dar cuenta al Pleno con las demandas de responsabilidad civil, presentadas en contra de los Magistrados del Tribunal Superior de Justicia.\nIX.- Turnar a la sala que corresponda, para los efectos que señala el Código de\nProcedimientos Civiles, el expediente que se haya formado con motivo de competencia suscitada entre los funcionarios precisados por la propia Ley adjetiva, en lo que se refiere a la cuantía del negocio.\nX.- Turnar a la sala que corresponda, para los efectos a que hubiere lugar, los expedientes a que se refiere el artículo 166 del Código de Procedimientos Civiles.\nXI.- Compilar las ejecutorias sobresalientes pronunciadas por el Pleno y las Salas para que se publiquen por el Consejo de la Judicatura del Estado.\nXII.- Convocar a sesión extraordinaria del Pleno a solicitud de Consejo de la\nJudicatura.\nArtículo Reformado\nCAPITULO V\nDE LAS SALAS DE TRIBUNAL\nARTÍCULO 45.- Las Salas del Tribunal Superior de Justicia del Estado podrán ser\nColegiadas o Unitarias; las primeras integradas por lo menos con tres Magistrados y las segundas integradas por un Magistrado, designadas por número ordinario.\nLas sesiones de las salas del Tribunal serán públicas por regla general y por excepción privadas solo en los casos que así lo determine la ley.\nCuando por caso fortuito o causas de fuerza mayor, sea imposible llevar a cabo las sesiones en forma presencial, las Salas Colegiadas podrán sesionar a través de las\nPárrafo Adicionado\nTratándose de los supuestos señalados en el párrafo anterior, que imposibiliten a las y los Magistrados reunirse a sesionar de manera presencial, por haberse decretado una medida de seguridad por la autoridad competente, la presidencia de la Sala respectiva, podrán convocar a sesión virtual, con el propósito de evitar poner en riesgo la salud del personal jurisdiccional, así como del público en general.\nPárrafo Adicionado\nArtículo Reformado\nARTICULO 46.- Los magistrados del Tribunal desempeñarán por turno semanario, el cargo de Semanero de acuerdo con las leyes.\nARTICULO 47.- Las resoluciones de las Salas Colegiadas se tomarán por unanimidad o mayoría de votos de los Magistrados que la integran, quienes no podrán abstenerse de votar sino, cuando tengan impedimento legal; si no hubiese mayoría en la votación de algún asunto, se entenderá desechado el proyecto, debiendo pasarse el asunto a otro Magistrado de la Sala para que presente nuevo proyecto de resolución en un término que no excederá de 30 días. Si a pesar de lo previsto en el párrafo anterior, no hubiese mayoría en la votación se pasará el asunto a la Sala que corresponda según la materia para que resuelva. En las\nSalas Unitarias, las resoluciones se tomarán por decisión del Magistrado integrante.\nArtículo Reformado\nARTICULO 48.- Corresponde a los magistrados semaneros:\nI.- Llevar la correspondencia de la sala, autorizándola con su firma.\nII.- Presidir las sesiones de la sala, cuidar el orden y policía de la misma y dirigir los debates.\nIII.- Dirigir la discusión de los negocios sometidos al conocimiento de la sala y ponerlos a votación cuando la Sala declare terminado el debate.\nIV.- Dar a la Secretaría General de Acuerdos los puntos que comprendan las disposiciones relativas votadas y aprobadas.\nV.- Vigilar que los secretarios y demás empleados de la sala cumplan con sus deberes respectivos, imponiéndoles las correcciones disciplinarias procedentes.\nVI.- En cada sala se formará una lista de asuntos que deban verse en la sesión, la cual se fijará a más tardar el día hábil anterior en lugar visible y surtirá los efectos de notificación del auto en que se cite para resolver.\nLos asuntos se fallarán en el orden en que se listen. Si no pudieran despacharse en la audiencia todos los asuntos listados, los restantes figurarán en la siguiente en primer lugar, sin perjuicio de que las salas acuerden que se altere el orden de la lista, que se retire algún asunto o que se aplace la vista del mismo, cuando exista causa justificada.\nNingún aplazamiento excederá del término de treinta días hábiles.\nVII.- El día señalado para la sesión, el Secretario de Estudio y Cuenta dará lectura al discusión el asunto suficientemente discutido, a juicio de los magistrados, se procederá a la votación y acto continuo, el Magistrado semanero declarará el resultado de ésta. El\nMagistrado que no estuviere conforme con el sentido de la resolución, deberá formular su voto particular expresando los fundamentos del mismo, y la resolución que estime débil dictarse.\nVIII.- Toda resolución que pronuncien las salas deberán ser firmadas por el magistrado semanero, por el Secretario General de Acuerdos que dará fé y por los magistrados que estuvieren conformes con la misma, dentro de los cinco días siguientes a la aprobación del proyecto, siempre que se hubiere aprobado sin adiciones ni reformas. y reformas propuestas en la sesión, procederá a redactar la resolución con base a los términos de la discusión.\nSi el proyecto del Magistrado ponente fue aprobado sin adiciones ni reformas, se tendrá como sentencia definitiva y se firmará dentro de los tres días siguientes.\nARTICULO 49.- Cuando un Magistrado estuviere impedido a conocer de un negocio o se excuse; aceptada que sea ésta o calificada de procedente el impedimento, o faltare accidentalmente, o esté ausente por un término no mayor de quince días hábiles, será suplido por el Magistrado que de la Sala correspondiente designe el Presidente del Tribunal.\nCuando la excusa o impedimento afecte a dos o más de los Magistrados de la Sala, conocerá del negocio la Sala que corresponda según la materia.\nTratándose del Magistrado de la Sala Unitaria Especializada en Justicia para\nAdolescentes, en los supuestos que se señalan en el párrafo primero de este artículo, será suplido por el Secretario de Estudio y Cuenta de la propia Sala.\nArtículo Reformado\nARTICULO 50.- Las Salas conocerán:\nI.- De los Recursos de Apelación, de responsabilidad y queja, en su caso, que se interpongan en Asuntos Civiles, de lo familiar y de extinción de dominio contra las resoluciones dictadas en esa materia por los Jueces de Primera y Única Instancia del\nEstado.\nII.- De las apelaciones y denegadas apelaciones que se interpongan en materia penal, en contra de las resoluciones dictadas por los jueces de Primera y Única Instancia del\nEstado, así como de los recursos de nulidad y revisión en los términos de las disposiciones normativas aplicables. De igual forma de los recursos de revocación sobre aspectos de mero trámite que deban resolver las salas.\nIII.- De las revisiones oficiosas en materia civil y de lo familiar que prevengan las leyes.\nIV.- Los recursos que se interpongan en materia de Justicia para Adolescentes, contra\nAdolescentes, de conformidad con la Ley especial en la materia.\nV.- De las competencias que se susciten en materia civil, penal o para Adolescentes entre las autoridades judiciales del Fuero Común.\nVI.- De los impedimentos y recusaciones de las autoridades judiciales del Fuero\nComún del Estado, tanto en materia civil, familiar, de extinción de dominio, del ramo penal y para Adolescentes.\nVII.- De las contiendas de acumulación que susciten en materia penal, entre las autoridades que expresa la fracción anterior, y\nVIII.- De los demás asuntos que determinen las leyes.\nArtículo Reformado\nARTÍCULO 51.- Para el desempeño de los asuntos que tiene encomendados cada\nSala, tendrá las y los secretarios de estudio y cuenta necesarios para el ejercicio de sus atribuciones, atendiendo la viabilidad presupuestal, los cuales serán removidos libremente por el Pleno del Tribunal Superior de Justicia, a solicitud del Magistrado o Magistrada con que se encuentre adscrito la o el secretario en cuestión; así como la planta de empleados que fije el presupuesto de egresos respectivo.\nArtículo Reformado\nTITULO QUINTO\nDE LA ORGANIZACION DE LOS JUZGADOS DEL PODER JUDICIAL DEPENDIENTES\nDEL TRIBUNAL SUPERIOR\nCAPITULO I\nDISPOSICIONES GENERALES\nARTICULO 52.- Son Jueces de Única Instancia, para los efectos que prescribe la\nConstitución General de la República y demás leyes secundarias:\nPárrafo Reformado\nI.- Los Jueces de Paz, en las resoluciones dictadas en materia Civil o Penal, en contra de los cuales no procede ningún recurso ordinario, y\nFracción Adicionada\nII.- Los Jueces en materia laboral, en contra de cuyas resoluciones y sentencias no procede recurso o medio de defensa ordinario alguno.\nFracción Adicionada\nArtículo Reformado\nARTÍCULO 53.- Son Jueces de Primera Instancia:\nI.- Los de Primera Instancia Civil.\nII.- Los de Primera Instancia de los Familiar.\nIII.- Los de Primera Instancia Penal.\nIV.- El de Primera Instancia en materia de extinción de dominio.\nV.- Los de Primera Instancia Especializados para Adolescentes.\nVI.- Los mixtos de Primer Instancia.\nVII.- Los de Paz en materia penal, en las causas en que proceda la apelación y denegada apelación.\nVIII.- Los de Control.\nIX.- Los de Control para Adolescentes.\nX.- Los de competencia mixta especializados en Violencia Familiar contra las Mujeres.\nFracción Adicionada\nX.- Los de Primera Instancia especializados en Materia Hipotecaria.\nFracción Adicionada\nArtículo Reformado\nARTICULO 54.- En el Partido Judicial de Mexicali, habrá cuando menos cuatro\nJuzgados de Primera Instancia Civil, dos Juzgados de Primera Instancia de lo Familiar, cinco\nJuzgados de Primera Instancia Penal y cuatro Juzgados de Paz, distribuidos de la siguiente manera: Uno Civil y uno Penal en la Ciudad de Mexicali, uno Mixto en Guadalupe Victoria y otro Mixto en San Felipe. Además contará con un Juzgado de Primera Instancia\nEspecializado para Adolescentes y uno en materia de extinción de dominio.\nTratándose del Juzgado de Primera Instancia en materia de extinción de dominio, además de la competencia territorial que le corresponde al Partido Judicial de Mexicali, conocerá de lo que conforme a esta ley y a la Ley de Extinción de Dominio del Estado de\nBaja California le corresponda, dentro de las competencias territoriales de los partidos judiciales de los restantes municipios de la entidad.\nArtículo Reformado\nARTICULO 55.- En el Partido Judicial de Tijuana, habrá cuando menos cinco Juzgados de Primera Instancia Civil, dos Juzgados de Primera Instancia de lo Familiar, siete Juzgados de Primera Instancia Penal y tres Juzgados de Paz, uno Civil, dos Penales. Además contará con un Juzgado de Primera Instancia Especializado para Adolescentes.\nArtículo Reformado\nTratándose del Juzgado de Primera Instancia Especializado para Adolescentes además de la competencia territorial que le corresponde al Partido Judicial de Tijuana, conocerá de las conductas tipificadas como delito que cometan los adolescentes dentro de las competencias territoriales de los partidos judiciales de Tecate y Playas de Rosarito.\nARTÍCULO 56.- En el Partido Judicial de Ensenada, habrá cuando menos cuatro\nJuzgados de Primera Instancia Civil, cuatro Juzgados de Primera Instancia Penal distribuidos de la siguiente manera: Uno Civil y uno Penal en San Quintín. Además contará con un Juzgado de Paz, dos Juzgados de Primera Instancia de lo Familiar y un Juzgado de\nPrimera Instancia Especializado para Adolescentes.\nArtículo Reformado\nARTÍCULO 57.- En el Partido Judicial de Tecate habrá cuando menos un Juzgado de\nPrimera Instancia de lo Familiar, un Juzgado Mixto de Primera Instancia en el ramo o ramos que determine el Pleno del Consejo de la Judicatura y un Mixto de Paz.\nArtículo Reformado\nARTICULO 57 BIS.- En el Partido Judicial de Playas de Rosarito, habrá cuando menos un Juzgado Mixto de Primera Instancia, en el ramo o ramos que determine el Pleno del Consejo de la Judicatura y un Mixto de Paz.\nArtículo Reformado\nARTICULO 58.- Cuando en un Partido Judicial haya dos o más Juzgados de la misma categoría y ramo, estarán numerados progresivamente y recibirán los asuntos de su competencia de acuerdo con el procedimiento que autorice el Pleno del Consejo de la\nJudicatura del Estado.\nARTÍCULO 58 BIS.- El Pleno del Consejo de la Judicatura atendiendo a la viabilidad presupuestal correspondiente, podrá establecer los Juzgados Especializados en materia\nHipotecaria en aquellas demarcaciones territoriales que considere pertinentes, fijando su competencia para conocer de los asuntos presentados en los diversos municipios del\nEstado.\nArtículo Adicionado\nARTICULO 59.- Los Jueces de Primera Instancia, Jueces en materia Laboral y\nJueces de Paz deberán residir en el partido judicial que les corresponda durante su encargo.\nArtículo Reformado\nARTICULO 60.- Los Servidores Públicos del Poder Judicial del Estado que deberán protestar al aceptar el cargo, serán únicamente los que se refieren en el presente artículo y en la forma siguiente:\nI.- Los Magistrados y Consejeros al Consejo de la Judicatura, en la forma prevenida\nII.- Los Jueces cualquiera que sea su categoría, ante el Pleno del Tribunal Superior de\nJusticia.\nIII.- El Secretario General de Acuerdos, Secretarios Auxiliares, Secretarios de Estudio y Cuenta, y Actuarios del Tribunal Superior de Justicia, ante el Pleno de este último.\nIV.- Los Secretarios de Acuerdos y Actuarios de los Juzgados, ante el Juez al que sean adscritos.\nArtículo Reformado rendirá ante quien corresponda en los términos siguientes:\n\"Protestáis guardar y hacer guardar la Constitución Política de los Estados Unidos y patrióticamente el cargo de (el que se confiere al interesado) que se os ha conferido; y cumplir fielmente los deberes que dicho carga impone, mirando en todo por el bien y prosperidad de la Unión y del Estado de Baja California?”. El interesado responderá: \"Sí, protesto\". La autoridad que tome la protesta añadirá: \"Si no lo hicieres así, la Nación y el\nEstado de Baja California os lo demanden\".\nARTICULO 62.- De toda protesta y aceptación del cargo de los servidores públicos se remitirá al Consejo de la Judicatura.\nARTICULO 63.- Los nombramientos de jueces serán hechos, preferentemente de entre aquellas personas que presten o hubieren prestado sus servicios con eficacia y probidad en la Administración de Justicia, o que, sin haber laborado en el Poder Judicial, lo merezcan por su honorabilidad, competencia y antecedentes profesionales.\nARTICULO 64.- Para ser Juez, se requiere cumplir con los requisitos que señala la\nArtículo Reformado\nARTICULO 65.- Para ser Secretario de Acuerdos de Juzgado se requiere:\nI.- Ser mexicano en pleno ejercicio de sus derechos civiles y políticos;\nII.- Tener título de abogado o Licenciado en Derecho y cédula profesional;\nIII.- Tener por lo menos veinticinco años y no más de sesenta y cinco años de edad, al día de la designación;\nIV.- Tener práctica profesional mínima de tres años para desempeñar el cargo, y\nV.- Gozar de buena reputación y no haber sido condenado por un delito intencional que amerite pena corporal de más de un año de prisión, pero si se trata de robo, fraude, falsificación, abuso de confianza u otro que lesione la buena fama en el concepto público, lo inhabilitará para el cargo cualquiera que haya sido la pena.\nArtículo Reformado\nARTICULO 66.- Para ser Actuario de Juzgado, se requiere:\nI.- Ser mexicano en pleno ejercicio de sus derechos civiles y políticos.\nII.- Tener título de abogado o Licenciado en Derecho y cédula profesional.\nIII.- Tener por lo menos veintidós años y no más de sesenta y cinco años de edad, al día de la designación. Tener por lo menos veintidós años y no más de sesenta y cinco años de edad, al día de la designación.\nArtículo Reformado\nIV.- Gozar de buena reputación y no haber sido condenado por un delito intencional que amerite pena corporal de más de un año de prisión, pero si se trata de robo, fraude, falsificación, abuso de confianza u otro que lesione la buena fama en el concepto público, lo inhabilitará para el cargo cualquiera que haya sido la pena.\nARTICULO 67.- Los jueces cualquiera que sea su categoría, darán cuenta trámite y de los valores, multas, y cauciones que hubieren hecho efectivas. del Juez responsable, a petición del Pleno del Tribunal.\nARTICULO 68.- Para el mejor desempeño de sus labores, cada uno de los Juzgados de los diversos Partidos Judiciales en los que se divide el Estado, contarán con un Juez, el número de Secretarios de Acuerdos, Actuarios y el personal que determine el Pleno del\nConsejo de la Judicatura del Estado de acuerdo con el presupuesto de egresos.\nARTÍCULO 69.- Las y Los jueces de lo Civil, de lo Familiar, de lo Penal, de lo Laboral, Mixtos de Primera Instancia, Especializados para Adolescentes, Especializados en Violencia\nFamiliar contra las Mujeres, Especializados en Materia Hipotecaria o de Paz, cuando sean varios en el mismo partido judicial, se identificarán por numeración progresiva y conocerán de los negocios jurídicos que, por Ley sean de su competencia.\nArtículo Reformado\nARTICULO 70.- Cuando dentro de la jurisdicción territorial de un Juzgado Mixto de\nPrimera Instancia, no hubiere juzgados de Paz, conocerán también de los negocios jurídicos que de acuerdo con la Ley son de la competencia de estos juzgados.\nARTICULO 71.- Los períodos de designación y de ratificación de los Jueces, serán\nLos períodos a que se refiere el presente artículo se iniciarán del día primero de diciembre del año correspondiente.\nArtículo Reformado\nARTICULO 72.- Son facultades y obligaciones de los jueces cualquiera que sea su categoría:\nI.- Dar cuenta mensual al Tribunal Superior tanto de las diligencias que se le hubieran encomendado, como del movimiento de negocios habidos en sus respectivos Juzgados, incluyendo informe sobre negocios citados para sentencia, sin que ésta se haya dictado.\nII.- Practicar las diligencias que el Pleno del Tribunal o las Salas del mismo, les soliciten; así como las que le soliciten los jueces del Estado, los Tribunales de la Federación, los Jueces de otras entidades Federativas, a títulos a auxilio judicial.\nIII.- Acordar y sentenciar oportuna, fundada, motivadamente y con perspectiva de género los negocios sometidos a su conocimiento, con sujeción a las normas aplicables a cada caso.\nFracción Reformada\nIV.- Excusarse en los casos previstos por la ley.\nV.- Diligenciar los exhortos que reciban de otras autoridades, dentro de los tres días siguientes a su recepción, siempre y cuando se ajusten a la ley; en caso contrario, devolverlos de inmediato con las observaciones pertinentes, pero si la autoridad requirente insistiere, se practicará la diligencia dejando constancia de las objeciones del juez requerido, salvo que se trate de una violación flagrante a las garantías constitucionales.\nVI.- Cuidar el orden y la disciplina en el juzgado imponiendo las sanciones que el caso amerite.\nVII.- Presidir las audiencias, resolviendo sin demora las cuestiones que así lo requieran con estricto apego a la ley.\nVIII.- Imponer sanciones a los Secretarios, Actuarios y personal adscrito en los términos de esta ley.\nIX.- Las demás que les confieran las leyes.\nArtículo Reformado\nCAPITULO II\nDE LA ORGANIZACION DE LOS\nJUZGADOS CIVILES\nARTICULO 73.- Los jueces de Primera Instancia Civil conocerán:\nI.- De los negocios jurídicos de jurisdicción voluntaria, cuyo conocimiento no corresponda a los jueces de Primera Instancia de lo Familiar.\nII.- De los juicios contenciosos que versen sobre la propiedad o demás derechos reales sobre inmuebles, siempre que el valor de estos exceda de 1000 días de salario mínimo general vigente en el Estado.\nIII.- De los demás negocios jurídicos de jurisdicción contenciosa común y concurrente, cuya cuantía sea igual a la cantidad indicada en la fracción anterior.\nIV.- De los asuntos judiciales de jurisdicción común o concurrente, relativos a concursos, suspensiones de pago y quiebras, cualquiera que sea su monto.\nV.- De los interdictos.\nVI.- De las diligencias preliminares de consignación, cuando el valor de la cosa o la cantidad que se ofrezca exceda a 1000 días del salario mínimo general, debiéndose estar a lo que dispone el Código de Procedimientos Civiles, en los casos de prestaciones periódicas, excepto en los asuntos de derecho familiar.\nVII.- De los juicios sucesorios cualquiera que sea su cuantía.\nVIII.- De las órdenes de protección, exceptuando los asuntos de derecho familiar;\nIX.- De los demás asuntos que les encomienden las leyes.\nArtículo Reformado\nARTICULO 74.- Cuando en un juzgado de primera Instancia o de paz haya más de un secretario, el Juez determinará el que tendrá el carácter de primer secretario de acuerdos, acuerdo con las instrucciones y determinaciones del Juez, y suplirá las faltas temporales de este último, que no excedan de dos meses, debiendo dar cuenta al Pleno del Tribunal y del\nConsejo de la Judicatura.\nARTICULO 75.- Son atribuciones y obligaciones de los secretarios de acuerdos:\nI.- Recibir los escritos, exceptuando los iniciales de demanda, donde no exista\nOficialía de Partes, que les presenten en su domicilio después de haberse terminado las labores del juzgado, asentado con letra, al calce, la razón de la fecha y hora de la presentación, expresando las fojas que contengan y los documentos que se acompañan.\nAsimismo, deban poner razón idéntica en la copia cuando se exhiba y la firma de quien la recibe.\nII.- Recibir los escritos, donde no exista oficialía de partes que les presenten durante las horas hábiles del juzgado y en las oficinas del mismo, anotando la hora y fecha de presentación y anexos que se acompañan y la misma razón en la copia si la hubiere para el interesado.\nIII.- Dar cuenta a sus jueces, al reanudar labores al día siguiente, de los escritos recibidos fuera del horario regular de labores del juzgado.\nIV.- Dar cuenta diariamente a sus jueces, bajo su responsabilidad y dentro de las veinticuatro horas siguientes a la presentación, con todos los escritos y promociones en los negocios de la competencia de aquéllos, así como de los oficios y demás documentos que se reciban en el juzgado.\nV.- Autorizar con su firma los despachos, exhortos, actos, diligencias, autos y toda clase de resoluciones que se expidan, asiente, practiquen o se dicten por el juez.\nVI.- Asentar en los expedientes las certificaciones relativas a términos de prueba y las demás razones que expresa la ley o el juez las ordene.\nVII.- Asistir a las diligencias de prueba que debe recibir el juez de acuerdo con el\nCódigo de Procedimientos Civiles.\nVIII.- Expedir las copias autorizadas y certificadas que la ley determine o deban darse a las partes en virtud de Decreto Judicial.\nIX.- Cuidar de que los expedientes sean debidamente foliados al agregarse cada una de las hojas, sellando por sí mismos las actuaciones, oficios y demás instrumentos que lo requieran, rubricando aquéllas en el centro del escrito.\nX.- Guardar en el secreto del Juzgado, los pliegos, valores o documentos cuando así lo disponga la ley, o el Juez.\nXI.- Inventariar o conservar en su poder los expedientes mientras no se remitan al\nArchivo Judicial o al Superior en su caso y entregarlos con las formalidades legales, cuando deba tener lugar la remisión.\nXII.- Proporcionar a los interesados los expedientes en los que fueren partes y que soliciten para informarse del estado de los mismos, para tomar apuntes o para cualquier otro efecto legal, siempre que no estén en poder de los Actuarios y que sea en su presencia, sin extraer las actuaciones de la oficina.\nXIII.- Entregar a las partes, previo conocimiento, los expedientes, en los casos en que lo disponga la ley.\nXIV.- Notificar en el Juzgado, personalmente a las partes, en los juicios o asuntos que se ventilen ante él, en los términos del artículo 123 y demás relativos del Código de\nProcedimientos Civiles.\nXV.- Remitir los expedientes al archivo judicial, al substituto legal de éste, o a la superioridad, previo conocimiento y control en sus respectivos casos.\nXVI.- Ordenar y vigilar que se despachen sin demora los asuntos y correspondencia del juzgado, ya sea que se refiera a negocios judiciales del mismo o al desahogo de los oficios que se manden librar en las determinaciones respectivas, dictadas en los expedientes.\nXVII.- Estarán investidos de fé pública en las actuaciones que realicen en el ejercicio de sus funciones, debiendo consignar en las mismas su nombre completo.\nXVIII.- Distribuir diariamente entre los actuarios por riguroso orden los asuntos que se encuentran pendiente de notificación o ejecución.\nXIX.- Desempeñar todas las funciones que la ley determine, las que autorice expresamente el pleno del Tribunal, los reglamentos interiores.\nXX.- Certificar, autorizar y dar fé de las actuaciones judiciales en que intervengan.\nXXI.- Acompañar al Juez en las diligencias de prueba que se desahoguen fuera del local del juzgado.\nARTICULO 76.- El primer secretario de acuerdos, además de las atribuciones que determina el artículo anterior, tendrá las siguientes:\nI.- Substituir al juez en sus faltas temporales, en los términos de ésta ley.\nII.- Distribuir diaria y equitativamente entre él y los demás secretarios de acuerdos que hubiere, por riguroso turno, los asuntos que se inicien en el juzgado de que dependen, donde no exista oficialía de partes común.\nIII.- Tener a su cargo, bajo su responsabilidad, los libros pertenecientes a la oficina designando de entre los empleados subalternos de la misma, al que deba llevarlos.\nIV.- Conservar en su poder el sello del juzgado.\nV.- Cuidar y vigilar que el archivo se lleve apropiadamente.\nVI.- Ejercer por si mismo o por conducto de los empleados subalternos, la vigilancia que sea necesaria en la oficina, para conservación, y guarda de los expedientes.\nVII.- Los demás que le confieren las leyes y los reglamentos.\nARTICULO 77.- Los Actuarios tendrán las siguientes atribuciones y obligaciones:\nI.- Recibir de los secretarios de acuerdos los expedientes de notificaciones personales o de diligencias que deban llevarse a cabo fuera del propio juzgado, firmando de recibido en el libro respectivo.\nII.- Hacer oportunamente y en los términos de ley las notificaciones personales y practicar las diligencias decretadas por los jueces, devolviendo los expedientes, previas las anotaciones correspondientes en el libro respectivo.\nIII.- Llevar un libro en el que asienten diariamente las diligencias y notificaciones que lleven a cabo fuera de local de la oficina en que presten sus servicios, con expresión, de la fecha en que reciba el expediente y la en que lo devuelva.\nIV.- Devolver debidamente diligenciados dentro de los tres días siguientes a la fecha en que se les turnen los expedientes. El incumplimiento de esta disposición trae como consecuencia, la primera vez amonestación; la segunda, suspensión de tres días; y la tercera remoción del cargo.\nSi la diligencia trae aparejada embargo o ejecución deberá devolver el expediente el mismo día en que se practique con el levantamiento del acta respectiva, en caso de inobservancia se aplicarán las sanciones a que se refiere el párrafo anterior, sin perjuicio de las consecuencias procesales que ocasionare.\nV.- Estarán investidos de fé pública en las actuaciones que realicen en el ejercicio de sus funciones, estableciéndose en ellas el nombre completo de quien las practique, la inobservancia de esta obligación será sancionada en los términos de la fracción anterior.\nCAPITULO III\nDE LA ORGANIZACION DE LOS\nJUZGADOS DE LO FAMILIAR\nARTICULO 78.- Los jueces de Primera Instancia de lo Familiar conocerán:\nI.- De los negocios jurídicos de jurisdicción voluntaria relacionados con el Derecho\nFamiliar.\nII.- De los juicios contenciosos relativos al matrimonio, a la ilicitud o nulidad del matrimonio y al divorcio, incluyendo los que se refieren al régimen de bienes en el legítima, natural o adoptiva; de los que tengan por objeto cuestiones derivadas de la patria potestad, estado de interdicción y tutela y las cuestiones de ausencia y presunción de muerte; de los que se refieran a cualquier cuestión relacionada con el patrimonio de familia, como su constitución, disminución, extinción, afectación o modificación en cualquier forma.\nIII.- De los asuntos judiciales concernientes a otras acciones relativas al estado civil, a la capacidad de las personas y las derivadas del parentesco.\nIV.- De las diligencias de consignación en todo lo relativo al Derecho Familiar.\nV.- De las diligencias de exhortos, suplicatorias, requisitorias y despachos, relacionados con el Derecho Familiar.\nVI.- De las cuestiones relativas a los asuntos que afecten en sus derechos de persona a los menores e incapacitados así como, en general, todas las cuestiones familiares que reclamen la intervención judicial.\nVII.- De la expedición de las órdenes de protección de naturaleza familiar.\nLos Juzgados de Primera Instancia de lo Familiar en el ámbito de su competencia funcionarán de manera ininterrumpida a lo largo del año no existiendo días ni horas inhábiles, para lo cual se establecerán guardias durante los periodos vacacionales, igual situación aplicará cuando se trate de aquellos de jurisdicción mixta.\nPárrafo Adicionado\nArtículo Reformado\nARTICULO 79.- En los juzgados de lo familiar se llevará un registro en que conste los discernimientos que se hicieren de los cargos de tutor o curador.\nARTICULO 80.- Los secretarios de acuerdos y actuarios de los juzgados de lo familiar deberá reunir los mismos requisitos que la presente ley señala a los secretarios de acuerdos y actuarios de los juzgados de lo civil y las mismas atribuciones que la propia ley señala.\nCAPITULO IV\nDE LA ORGANIZACION DE LOS\nJUZGADOS DE LO PENAL\nARTICULO 81.- Los jueces de lo Penal tendrán las siguientes atribuciones:\nI.- Conocer de todos los asuntos de carácter penal que no estén encomendados por esta Ley a la jurisdicción de los jueces de Paz.\nII.- Designar al personal que durante los periodos vacacionales deban quedar de guardia.\nIII.- Informar de inmediato y en su caso dar intervención a las autoridades sanitarias competentes, para los efectos del tratamiento que corresponda, tan pronto identifique que una persona relacionada con un procedimiento es farmacodependiente.\nIV.- Desempeñarse con el carácter de Juez de Ejecución en aquellos asuntos penales aplicables.\nV.- Las demás que les confieren las leyes.\nArtículo Reformado\nARTICULO 81 BIS.- Los Jueces de Control, los Jueces Especializados en Ejecución de Sentencia y los Jueces de control Especializados en Adolescentes, ejercerán las\nTerapéutica para el Estado de Baja California.\nPárrafo Reformado\nPara el nuevo sistema de justicia penal, se contará con el número de Jueces de\nControl que sean indispensables para la adecuada aplicación del citado sistema y de conformidad con la disponibilidad presupuestal.\nLos Jueces de Control estarán investidos de fe pública para constancia y certificación de sus actos.\nEn cada uno de los partidos judiciales en el Estado, de acuerdo a la disponibilidad presupuestal y las necesidades del servicio, se contará por lo menos con un Juez\nEspecializado en Ejecución de Sentencia que ejercerá las facultades que determinen las disposiciones normativas aplicables.\nArtículo Reformado\nARTICULO 81 TER.- Los Tribunales de Juicio Oral o de enjuiciamiento serán unitarios y estarán presididos por un Juez de Garantía o de Control, que no deberá haber conocido del asunto en las etapas previas al juicio oral que deba resolver.\nLos Tribunales de Juicio Oral tendrán las atribuciones que determinen las disposiciones normativas aplicables.\nEl Juez del Tribunal de Juicio Oral estará investido de fe pública para constancia y certificación de sus actos.\nArtículo Reformado\nARTICULO 81 QUATER.- Los Jueces de Control nombrarán entre ellos a un Juez\nCoordinador, el cual tendrá como atribuciones sugerir algunas de las siguientes acciones al administrador judicial:\nI.- La programación del número de audiencias por día.\nII.- Las mejoras a los inmuebles e infraestructura que estén bajo custodia del administrador judicial.\nIII.- Las medidas para hacer más eficiente el modelo de gestión administrativa.\nIV.- El orden de guardias de los Jueces de Control.\nV.- Las mejoras en la labor que presta el personal administrativo.\nControl con el objeto de analizar entre otros aspectos, temas relativos a la actividad jurisdiccional y homologar en lo posible sus criterios de aplicación de la ley.\nArtículo Reformado\nARTICULO 81 QUINQUES.- Las vacaciones de los Jueces de Control, serán establecidas por periodos de acuerdo a las necesidades del servicio, por los órganos competentes a través de un sorteo y previa citación a los Jueces. Los Jueces tendrán derecho a estar presentes en la realización del sorteo. personal suficiente para ejercer adecuadamente sus atribuciones, personal que estará adscrito y a cargo del administrador judicial.\nEl Administrador Judicial contará con notificadores encargados de practicar las diligencias que ordenen los Jueces de Control y Tribunales de Enjuiciamiento, para lo cual estarán investidos de fe pública en las actuaciones que realicen.\nLos notificadores contaran además, con las facultades y obligaciones que señale el reglamento respectivo.\nArtículo Reformado\nARTICULO 82.- Son obligaciones de los secretarios de acuerdos de los Juzgados de lo Penal:\nI.- Llevar personalmente los procesos que se les encomienden.\nII.- Dar cuenta diariamente al Juez y acordar con él, los escritos y promociones de las partes, así como los oficios que se dirijan al Juzgado.\nIII.- Hacer las notificaciones a las partes y proporcionar los expedientes a los interesados para cualquier efecto legal siempre que sean en la oficina.\nIV.- Autorizar las providencias, despachos, autos y sentencias que se dicten, expidan o practiquen escribiendo su nombre completo y firma, en los asuntos del Juzgado, y expedir las copias autorizadas en virtud de resolución judicial o que la ley determine.\nV.- Las demás que les impongan las leyes.\nARTICULO 83.- El primero secretario de acuerdos de lo penal tendrá además, las siguientes atribuciones:\nI.- Substituir al Juez en sus faltas temporales que no excedan de dos meses en los términos que señale esta ley.\nII.- Distribuir diariamente entre él y los demás secretarios, las consignaciones que se hagan al Juzgado.\nIII.- Llevar los libros del Juzgado o con intervención de alguno de los empleados de la oficina.\nIV.- Dirigir las labores interiores de la oficina, de acuerdo con las instrucciones y determinaciones del Juez, dando cuenta de las faltas que se cometan para que el Juez obre de acuerdo con sus facultades.\nARTICULO 84.- El Actuario tendrá las siguientes obligaciones:\nI.- Recibir de los secretarios de Acuerdos de lo penal los expedientes de notificaciones personales o de diligencias que deban llevarse a cabo fuera del Juzgado, firmando en el libro correspondiente.\nII.- Hacer las notificaciones personales y practicar las diligencias que ordene el Juez dentro de los tres días, devolviendo los expedientes debidamente diligenciados previas las notificaciones en el Libro respectivo, el que contendrá la fecha en que se reciba el expediente y la devolución del mismo.\nIII.- Suplir al Secretario de Acuerdos respectivo, en los casos y términos que señala esta ley.\nIV.- Cuidar que los procesados que disfrutan del beneficio de libertad provisional bajo caución, cumplan con la obligación de firmar semanalmente el Libro de Registro respectivo, dando cuenta inmediata al Juez de todos los casos de incumplimiento de dicha obligación, para los efectos legales correspondientes, y.\nV.- El incumplimiento de las obligaciones señaladas por el presente artículo será motivo de la aplicación de las sanciones previstas en la fracción IV del artículo 77 de esta ley.\nVI.- Las demás sanciones que la ley determine.\nCAPITULO V\nDE LA ORGANIZACION DE LOS JUZGADOS\nMIXTOS DE PRIMERA INSTANCIA\nARTICULO 85.- Los Jueces Mixtos de Primera Instancia tendrán la competencia por cuantía y por materia, así como las facultades y obligaciones que esta ley señala a los jueces de Primera Instancia Civil, Familiar y Penal cuando dentro de su jurisdicción territorial no hubiere Juzgados Mixtos de Paz, conocerán también de los negocios jurídicos que de acuerdo con la presente ley son de la competencia de dichos Juzgados.\nARTICULO 86.- Los secretarios de acuerdos y actuarios tendrán el conjunto de facultades y obligaciones que, por disposición de ésta y de las demás leyes, tienen los secretarios de acuerdos y actuarios de los Juzgados de lo Civil y de lo Penal.\nCAPITULO VI\nDE LA ORGANIZACION DE LOS JUZGADOS DE PAZ\nY JURISDICCION MIXTA DE PAZ\nARTICULO 87.- Para el despacho de los negocios jurídicos, los Juzgados de Paz, Consejo de la Judicatura. En caso de ser Mixtos, habrá cuando menos dos secretarios de\nAcuerdos, adscritos al ramo penal y otro al ramo civil.\nARTICULO 88.- Los jueces civiles de Paz conocerán de los juicios contenciosos que a 1000 días de salario mínimo general, a excepción de los interdictos; de los demás negocios de jurisdicción contenciosa, común y concurrente, cuyo monto no exceda la cantidad antes mencionada; de las diligencias preliminares de consignación, cuando el valor de la cosa o cantidad que se ofrezca no pase de la suma señalada con anterioridad, debiéndose estar a lo dispuesto en el Código de Procedimientos Civiles en los casos de prestaciones periódicas; de la diligenciación de exhortos y despachos, y de los demás asuntos que les encomiendan las leyes.\nArtículo Reformado\nARTICULO 89.- Los jueces penales de Paz conocerán de los delitos que tengan como sanción, apercibimiento, caución de no ofender, multa cuyo máximo sea de cuarenta días de salario mínimo, prisión cuyo máximo sea de un año o ambas; de la diligenciación de exhortos y despachos y de los demás que les encomienden las leyes.\nARTICULO 90.- Los jueces Paz de Jurisdicción mixta conocerán:\nI.- En los asuntos civiles, de los juicios contenciosos que versen sobre la propiedad y demás derechos reales sobre inmuebles, cuyo monto no exceda al equivalente de 1000 días de salario mínimo general, a excepción de los interdictos; de los demás negocios de jurisdicción contenciosa, común o concurrente, cuyo monto no exceda de la cantidad antes mencionada; de las diligencias preliminares de consignación, cuando el valor de las cosas o la cantidad que se ofrezca no pase de la suma señalada con anterioridad, debiéndose estar a lo dispuesto en el Código de Procedimientos Civiles en los casos de prestaciones periódicas; de la diligenciación de exhortos y despachos y de los demás asuntos que les encomienden las leyes.\nII.- En el ramo Penal, de los delitos que tengan como sanción, apercibimiento, caución de no ofender, multa cuyo máximo sea de cuarenta días de salario mínimo, prisión cuyo máximo sea de un año o ambas, de la diligenciación de exhortos y despachos y de los demás asuntos que les encomienden las leyes.\nArtículo Reformado\nCAPÍTULO VII\nESPECIALIZADOS PARA ADOLESCENTES\nARTÍCULO 90 BIS.- Los Jueces de Primera Instancia Especializados para Adolescentes, tendrán las siguientes atribuciones y obligaciones:\nI. Conocer de las conductas tipificadas como delito por las leyes estatales atribuidas a adolescentes, desahogando los procedimientos respectivos para emitir las resoluciones que procedan;\nII. Determinar las medidas de orientación, protección o tratamiento, de conformidad con de Baja California, así como vigilar la ejecución de las mismas;\nIII. Proteger los derechos y garantías del adolescente sometido a procedimiento, así como los de la víctima u ofendido;\nIV. Ordenar la detención preventiva, en los casos en que sea legalmente procedente de conformidad con la Ley de la materia;\nV. Promover los Medios de Justicia Alternativa señalados en la Ley de la materia, siempre que procedan jurídicamente, y sancionar los convenios entre las partes;\nVI. Designar al personal que durante los periodos vacacionales deba quedar de guardia,\nVII. Las demás que le confiera esta Ley, y la Ley de la materia.\nArtículo Reformado\nARTÍCULO 90 TER.- Los Jueces de Control para adolescentes ejercerán las facultades que determine la Ley Nacional del Sistema Integral de Justicia Penal para Adolescentes y otras disposiciones normativas aplicables.\nSe contará en los partidos judiciales de Mexicali, Tijuana y Ensenada con el número de Jueces de Control para Adolescentes que sean necesarios para la adecuada aplicación del sistema de justicia para adolescentes. Los Jueces de Control del partido judicial de\nTijuana conocerán de los hechos que la ley señale como delito cuya comisión o participación se le atribuya a adolescentes y se hayan cometido en los municipios de Tecate y Playas de\nRosarito.\nLos Jueces de Control para Adolescentes estarán investidos de fe pública para constancia y certificación de sus actos y les será aplicable lo dispuesto en los artículos 81\nQUATER, 81 QUINQUES de esta Ley. Contarán con el apoyo del administrador judicial en términos de lo dispuesto por el artículo 197 BIS 2 de esta Ley.\nEl Tribunal de Enjuiciamiento especializado en justicia para adolescentes se integrará por un Juez de Control para adolescentes que no haya conocido del asunto en las etapas previas al juicio oral que deba resolver. aplicables. El Tribunal de Enjuiciamiento del partido judicial de Tijuana tendrá competencia en los municipios de Tecate y Playas de Rosarito.\nEl Juez del Tribunal de Enjuiciamiento, estará investido de fe pública para constancia y certificación de los actos del Tribunal.\nLos partidos judiciales de Mexicali, Tijuana y Ensenada, contarán cada uno con un\nJuez de Ejecución especializado en el sistema integral de justicia para adolescentes. El Juez\nTecate y Playas de Rosarito.\nEl Magistrado de la Sala Unitaria Especializada en Justicia para Adolescentes, para Adolescentes y la Ley de Justicia para Adolescentes del Estado de Baja California.\nAdemás, estará investido de fe pública para constancia y certificación de sus actos que se deriven de la aplicación de ambos ordenamientos jurídicos.\nArtículo Reformado\nARTÍCULO 90 QUATER.- Son obligaciones de los Secretarios de Acuerdos de los\nJuzgados de Primera Instancia Especializados para Adolescentes:\nI.- Dar cuenta diariamente al Juez y acordar con él, los escritos y promociones de las partes, así como los oficios que se dirijan al Juzgado;\nII.- Efectuar las notificaciones a las partes y proporcionar los expedientes a los interesados para cualquier efecto legal, siempre que sean en la oficina;\nIII.- Autorizar las providencias, celebración de audiencias, despachos de autos y resoluciones que se dicten, expidan o practiquen, escribiendo su nombre completo y firma en los asuntos del Juzgado y expedir las copias autorizadas en virtud de resolución judicial o cuando la Ley lo determine, y\nIV.- Las demás que les impongan las leyes.\nEl Primer Secretario de Acuerdos tendrá además, las siguientes atribuciones: a.- Sustituir al Juez en sus faltas temporales que no excedan de dos meses, en los términos que señale esta Ley; b.- Distribuir diariamente entre él y los demás Secretarios, las remisiones que se hagan al\nJuzgado; c.- Llevar los libros del Juzgado, pudiendo ser con intervención de alguno de los miembros de la oficina, y d.- Dirigir las labores interiores de la oficina, de acuerdo con las instrucciones y determinaciones del Juez, dando cuenta de las faltas que se cometan para que el Juez obre de acuerdo a sus facultades.\nArtículo Reformado\nARTÍCULO 90 QUINQUIES.- El Actuario tendrá las siguientes obligaciones:\nI. Recibir de los Secretarios de Acuerdos los expedientes de notificaciones personales o de diligencias que deban llevarse a cabo fuera del Juzgado, firmando en el libro correspondiente;\nII. Hacer las notificaciones personales y practicar las diligencias que ordene el Juez dentro de los tres días, devolviendo los expedientes debidamente diligenciados, previas anotaciones en el libro respectivo, el que contendrá la fecha en que se reciba el expediente y la devolución del mismo;\nIII. Suplir al Secretario de Acuerdos respectivo, en los casos y términos que señale esta Ley, y\nIV. Las demás que le impongan las leyes.\nArtículo Reformado\nCAPÍTULO VIII\nDE LA ORGANIZACIÓN DEL JUZGADO DE\nPRIMERA INSTANCIA EN MATERIA DE\nEXTINCIÓN DE DOMINIO\nARTÍCULO 90 SEXIES.- El juzgado en materia de extinción de dominio conocerá:\nArtículo Reformado\nI.- De los procedimientos de extinción dominio establecidos en la Ley de la materia;\nII.- De las medidas cautelares en materia de extinción de dominio;\nIII.- De la diligenciación de los exhortos, rogatorias, suplicatorias, requisitorias y despachos, en la materia, y\nIV.- De las demás diligencias, acuerdos, y actividades que les encomiende la Ley de\nExtinción de Dominio para el Estado y demás legislación vigente.\nCAPITULO IX\nDE LA ORGANIZACIÓN DE LOS TRIBUNALES EN MATERIA LABORAL\nCapítulo Adicionado\nARTÍCULO 90 SEPTIES.- En cada municipio del Estado habrá al menos un Tribunal en materia Laboral.\nLos Jueces en Materia Laboral, tendrán las siguientes atribuciones y obligaciones:\nI. Resolver en única instancia, las diferencias o los conflictos entre trabajadores y patrones, cuya competencia no corresponda al ámbito federal;\nII. Substanciar todo proceso, procedimiento o vía bajo su competencia en materia laboral en términos de lo previsto por la Ley Federal del Trabajo;\nIII. Dictar sus sentencias y resoluciones observando los principios de legalidad, imparcialidad, transparencia, autonomía e independencia; y,\nIV. Las demás previstas en la Constitución Política de los Estados Unidos Mexicanos, la Ley Federal del Trabajo y demás disposiciones aplicables.\nPara la designación y duración en el cargo de los jueces laborales, se observará lo\nCalifornia, y demás disposiciones legales y reglamentarias aplicables.\nArtículo Adicionado\nARTÍCULO 90 OCTIES.- Los Tribunales Laborales contarán con los Jueces, Secretarios Instructores, Actuarios y auxiliares administrativos que sean necesarios para la prestación del servicio y de conformidad con la disponibilidad presupuestal.\nLos Secretarios Instructores, así como los Actuarios, tendrán el conjunto de facultades y obligaciones que por disposición de esta Ley, tiene el personal jurisdiccional de la misma categoría, así como las que señale la Ley Federal del Trabajo.\nPara ser designado Secretario Instructor, deberá cumplirse con los mismos requisitos que establece esta Ley para Secretarios de Acuerdos y lo que establezca la convocatoria respectiva.\nArtículo Adicionado\nARTÍCULO 90 NONIES.- El primer Secretario de Acuerdos, además de las atribuciones que determina el artículo anterior, tendrá las siguientes:\nI. Substituir al juez en sus faltas temporales, en los términos de esta Ley.\nII. Distribuir diaria y equitativamente entre él y los demás Secretarios de Acuerdos que hubiere, por riguroso turno, los asuntos que se inicien en el juzgado de que dependen, donde no exista oficialía de partes común.\nIII. Tener a su cargo, bajo su responsabilidad, los libros pertenecientes a la oficina designando de entre los empleados subalternos de la misma, al que deba llevarlos.\nIV. Conservar en su poder el sello del juzgado.\nV. Cuidar y vigilar que el archivo se lleve apropiadamente.\nVI. Ejercer por sí mismo o por conducto de los empleados subalternos, la vigilancia que sea necesaria en la oficina, para conservación, y guarda de los expedientes.\nVII. Los demás que le confieren las leyes y los reglamentos.\nArtículo Adicionado\nCAPÍTULO X\nFAMILIAR CONTRA LAS MUJERES\nCapítulo Adicionado\nARTÍCULO 90 DECIES.- Las y los Jueces especializados en violencia familiar contra las mujeres, tendrán las siguientes atribuciones y obligaciones:\nEn materia penal:\nI. Conocerán de las etapas de investigación e intermedia del procedimiento penal del sistema acusatorio y oral regulado por el Código Nacional de Procedimientos Penales, respecto de los delitos contenidos en el Código Penal para el Estado de Baja California.\na) Delitos contra la vida, la salud personal y dignidad humana contenidos en el Titulo\nPrimero, Sección Primera, Libro Segundo Parte Especial del Código Penal para el Estado de\nBaja California;\nb) Delitos contra la libertad y seguridad de las personas contenidos en el Titulo\nSegundo, Sección Primera, Libro Segundo Parte Especial del Código Penal para el Estado de Baja California;\nc) Delitos contra la intimidad y la imagen del Código Penal para el Estado de Baja\nCalifornia;\nd) Delitos contra la libertad y seguridad sexual de las personas contenidos en el Titulo\nCuarto, Sección Primera, Libro Segundo Parte Especial del Código Penal para el Estado de\nBaja California;\ne) Delitos contra el patrimonio contenidos en el Titulo Sexto, Sección Primera, Libro\nSegundo Parte Especial del Código Penal para el Estado de Baja California;\nf) Delitos contra la familia contenidos en el Titulo Primero, Sección Segunda, Libro\nSegundo Parte Especial del Código Penal para el Estado de Baja California; y,\ng) Delitos contra el libre desarrollo de la personalidad contenidos en el Titulo Cuarto,\nSección Tercera, Libro Segundo Parte Especial del Código Penal para el Estado de Baja\nCalifornia.\nConocerán de dichos delitos siempre y cuando sean cometidos en el ámbito familiar contra la mujer con quien la persona agresora tenga una relación de pareja o ex pareja, cónyuge o ex cónyuge, concubina o ex concubina, respecto a quien tenga o haya tenido relación de pareja o de hecho, o bien sea pariente consanguíneo en línea recta ascendente o descendente sin limitación de grado o pariente colateral consanguíneo o por afinidad hasta cuarto grado, así como contra el adoptante, adoptado o adoptada, o en contra de los parientes por consanguinidad o afinidad hasta el cuarto grado de las personas nombradas, al igual que contra cualquier otra mujer, en su caso sus hijos e hijas, que estén sujetos a la custodia, guarda, protección, educación o cuidado del sujeto activo.\nII. Resolver sobre las medidas cautelares o de protección de conformidad con el\nCódigo Nacional de Procedimientos Penales, así como cualquier medida tendiente a nacional e internacional, siempre que se trate de aquellos en que figuren como víctimas las personas referidas en la fracción I, segundo párrafo del presente artículo y se juzguen los delitos señalados en el mismo.\nIII. Atenderán y resolverán en ambas etapas las salidas alternas o la forma de terminación anticipada de conformidad con el Código Nacional de Procedimientos Penales.\nIV. Sobreseerán las causas a su cargo cuando se actualicen cualquiera de las hipótesis contenidas en el Código Nacional de Procedimientos Penales.\nEn materia familiar:\nI. Conocer y resolver hasta su conclusión, las controversias del orden familiar a que se refiera el Código de Procedimientos aplicable en la materia, siempre que versen sobre actos o hechos constitutivos de violencia familiar a través de los cuales se vulnere la integridad física o psicológica de la mujer con quien la persona presunta agresora o probable responsable tenga una relación de pareja o ex pareja, cónyuge o ex cónyuge, concubina o ex concubina, respecto a quien tenga o haya tenido relación de pareja o de hecho, o bien sea pariente consanguíneo en línea recta ascendente o descendente sin limitación de grado o pariente colateral consanguíneo o por afinidad hasta cuarto grado, así como contra el adoptante, adoptado o adoptada, o en contra de los parientes por consanguinidad o afinidad hasta el cuarto grado de las personas nombradas, al igual que contra cualquier otra mujer, en su caso sus hijos e hijas, que estén sujetos a la custodia, guarda, protección, educación o cuidado del presunto agresor o probable responsable.\nFracción Reformada\nII. Emitir las órdenes de protección reguladas tanto en la Ley General de Acceso de las Mujeres a una Vida Libre de Violencia, como en la Ley de Acceso de las Mujeres a una\nVida Libre de Violencia para el Estado de Baja California.\nIII. Dictar las medidas cautelares o de protección contenidas en la legislación nacional e Internacional, ya sea que las mujeres víctimas de violencia las reclamen por su propio derecho o en representación de sus hijos e hijas, siempre que se trate de actos cometidos por los sujetos a que se refiere la fracción I, en materia familiar del presente artículo.\nArtículo Adicionado\nArtículo Reformado\nCAPÍTULO XI\nEN MATERIA HIPOTECARIA\nCapítulo Adicionado\nDenominación Modificada\nARTÍCULO 90 UNDECIES.- Los Juzgados Especializados en Materia Hipotecaria conocerán:\nPárrafo Reformado\nI. De los juicios especiales hipotecarios establecidos en el Código de Procedimientos aplicable;\nFracción Adicionada\nII. De los juicios contenciosos que versen sobre acciones hipotecarias, siempre que el valor de estos exceda el valor de 2000 veces la unidad de medida y actualización;\nFracción Adicionada\nIII. De los juicios sumarios que se promuevan con motivo de las acciones hipotecarias que tengan como finalidad constituir, ampliar y registrar una hipoteca;\nFracción Adicionada\nIV. De los juicios ejecutivos que se promuevan en relación a una acción hipotecaria;\nFracción Adicionada\nV. De las diligencias de exhortos, suplicatorias, requisitorias y despachos relacionados con algún procedimiento hipotecario; y,\nFracción Adicionada\nVI. De los demás asuntos que les encomienden las leyes.\nFracción Adicionada\nArtículo Adicionado\nArtículo Reformado\nCAPÍTULO XII\nDE LAS CENTRALES DE ACTUARIOS\nCapítulo Adicionado, trasladándose la denominación anterior del Capítulo XI a este Capítulo XII\nARTÍCULO 90 DUODECIES.- En los Partidos Judiciales en que existan dos o más juzgados de la misma materia, podrán crearse Centrales de Actuarios, cuando las necesidades del servicio así lo ameriten, a juicio del Consejo de la Judicatura.\nLas Centrales de Actuarios serán los órganos encargados de llevar el control de las diligencias cuya realización ordenen las autoridades jurisdiccionales a cargo de las y los actuarios del Poder Judicial del Estado, fuera de la sede judicial, debiendo turnárseles de forma aleatoria. Las Centrales de Actuarios funcionarán conforme a las bases de organización y funcionamiento que sean establecidas en el reglamento y lineamientos que al efecto emita el Consejo de la Judicatura.\nArtículo Adicionado\nArtículo Reformado, trasladándose el texto anterior del Artículo 90 UNDOCIES a este Artículo 90 DUODECIES\nARTÍCULO 90 TERDECIES.- Cada Central de Actuarios estará a cargo de una coordinación, quien contará con las y los Secretarios Actuarios y el personal administrativo necesario para el cumplimiento de sus funciones, de conformidad con la viabilidad presupuestal. Para ser coordinadora o coordinador de la Central de Actuarios se requiere:\nI.- Contar con ciudanía mexicana en pleno ejercicio de sus derechos;\nII.- Tener cuando menos, treinta años cumplidos al día de la designación;\nIII.- Gozar de buena reputación;\nIV.- Licenciatura en Derecho, con título y cédula profesional con antigüedad de cinco años; y,\nV.- Acreditar la experiencia y capacidad indispensables para el desempeño del cargo.\nArtículo Adicionado, trasladándose el texto anterior del Artículo 90 DUODECIES a este Artículo 90 TERDECIES\nTITULO SEXTO\nDEL PROCEDIMIENTO PARA SUPLIR LAS\nFALTAS DE LOS SERVIDORES PUBLICOS DE LA\nADMINISTRACION DE JUSTICIA\nCAPITULO I\nDE LOS MAGISTRADOS\nARTICULO 91.- Las faltas temporales de los Magistrados del Tribunal Superior de\nJusticia en las diversas funciones que las leyes les encomiende, se suplirán:\nI.- Las del Presidente del Tribunal Superior serán suplidas por el Magistrado\nNumerario que elija el Pleno del mismo Tribunal.\nII.- Las de los Magistrados Numerarios cuando no pasen de dos meses, por el\nMagistrado Supernumerario que acuerde el Pleno del Tribunal Superior de Justicia.\nIII.- Las de los Magistrados Numerarios por más de dos meses, por un Magistrado\nSupernumerario atendiendo el orden de prelación que haya establecido el Congreso del\nEstado.\nArtículo Reformado\nARTICULO 92.- La falta absoluta de un Magistrado Numerario, será cubierta por un\nMagistrado Supernumerario atendiendo el orden de prelación que haya establecido el\nCongreso del Estado, hasta en tanto el propio Congreso realice el nuevo nombramiento en\nArtículo Reformado\nARTICULO 93.- Las faltas temporales del Magistrado de la Sala Unitaria\nEspecializada en Justicia para Adolescentes, se suplirán por el Secretario de Estudio y\nCuenta de esta Sala.\nEn el caso de las faltas absolutas del Magistrado de la Sala Unitaria, se estará a lo\nArtículo Reformado\nCAPITULO II\nDE LOS JUECES, SECRETARIOS\nACTUARIOS Y EMPLEADOS\nARTICULO 94.- Los jueces serán suplidos automáticamente en sus faltas temporales\nAcuerdos si lo hubiere; o en su defecto, por quien designe el Juez, haciéndolo del conocimiento del Consejo de la Judicatura y del Pleno del Tribunal Superior de Justicia.\nARTICULO 95.- Las faltas temporales de los jueces, por más de dos meses, serán cubiertas por la persona que nombre el Pleno del Consejo de la Judicatura conforme a lo dispuesto en el Título Octavo, de esta ley.\nARTÍCULO 95 BIS.- Las faltas temporales de los Jueces de Control serán cubiertas por la persona que nombre el Pleno del Tribunal Superior de Justicia del Estado conforme a lo dispuesto en el Título Octavo, de esta ley.\nArtículo Reformado\nARTICULO 96.- Las faltas temporales del Secretario General de Acuerdos, las de los\nSecretarios Auxiliares, la de los Secretarios de Estudio y Cuenta y las del Actuario del\nTribunal Superior cuando no excedan de quince días serán cubiertas por el Secretario que designe el Presidente del propio Tribunal. Pero cuando excedan de ése término y no pases de dos meses por que designe el Pleno del Consejo de la Judicatura.\nARTICULO 97.- Las faltas de los secretarios de Juzgados, que no excedan de dos meses, serán cubiertas por los que le siguen en su orden dentro del mismo Juzgado; o en su defecto, por el actuario correspondiente.\nARTICULO 98.- Cuando las ausencias sean mayores de un mes al tiempo excedente le será pagado a los funcionarios suplentes conforme al sueldo correspondiente al del substituído.\nARTICULO 99.- Las faltas temporales de los demás empleados se suplirán, cuando así lo determine el Pleno del Consejo de la Judicatura por medio de nombramientos que en los designados tendrán el carácter de interinos.\nARTICULO 100.- Las faltas absolutas de los Jueces, Secretarios y demás servidores públicos de la Administración de Justicia, serán cubiertas mediante nuevas designaciones o demás disposiciones normativas aplicables.\nArtículo Reformado\nTITULO SEPTIMO\nDE LOS IMPEDIMENTOS EN LA ADMINISTRACION\nDE JUSTICIA\nCAPITULO I\nDE LA SUBSTITUCION EN CASOS DE\nRECUSACION Y EXCUSAS\nARTICULO 101.- Si un magistrado dejare de conocer algún asunto por excusa o recusación, conocerá de éste el Magistrado de otra Sala a quien corresponda de acuerdo con el turno y en caso de impedimento conocerá de éste el magistrado propietario de otra\nSala que con anterioridad se haya excusado o haya sido recusado en otro negocio, a quien corresponda el turno que deberá llevar el Presidente del Tribunal. Cuando no existiera magistrado en semejantes condiciones, entonces el Presidente del Tribunal designaré, por riguroso turno, al magistrado que deba hacer la sustitución, y si aún subsistiera impedimento se procederá a nombrar por insaculación a un magistrado de los restantes, procediéndose a resolver el asunto, por lo que no podrá ser recusado o removido por impedimento sino en los casos que expresamente previenen las fracciones, II, III, IV, V, VIII; IX, X, XI, XIII, XIV y XV del artículo 171 del Código de Procedimientos Civiles para el Estado de Baja California, y las fracciones II, III, VII, IX, X, XI, XII, XIII y XIV del artículo 18 Código de Procedimientos\nPenales para la Entidad, caso en el cual deberá procederse a nueva insaculación.\nCuando los magistrados que integren una Sala estuvieren impedidos para conocer de un negocio, pasará éste al conocimiento de la Sala que le siga en número; si se tratase e la última Sala, será substituida por la que en el orden numérico corresponda.\nSi el impedimento para conocer de un asunto lo tuviere la totalidad de los magistrados de dos Salas, en la forma señalada en el párrafo anterior y derivare de recusación o excusas hechas valer de cualquier forma por parte interesada, conocerá la Sala siguiente por la que en número le corresponda y para ese único efecto se integrará mediante procedimiento de insaculación de los seis magistrados restantes, para resolver el asunto, por no aplicárseles impedimento alguno y por lo tanto no siendo removidos por recusación o excusa, a menos que se encontrare alguno de ellos en los casos de excepción previstos en el párrafo primero de este artículo, caso en el cual deberá procederse a nueva insaculación.\nCuando el Tribunal en Pleno, advierta que las recusaciones o excusas se hubiesen hecho valer por cualquier medio de los magistrados integrantes de dos de sus Salas, con el único propósito de retrasar la solución de un asunto o la suspensión del mismo se le consignará al Ministerio Público.\nEn los casos en que los Consejeros de la Judicatura estuvieren impedidos para conocer de un asunto, será sustituido por el Consejero que para tal efecto designe el\nCongreso del Estado o el que corresponda como consejero suplente insaculado.\nARTICULO 102.- Si un Juez de lo Civil, de Extinción de Dominio, de lo Penal, en materia Laboral, o Mixto de Primera Instancia, deja de conocer por impedimento, recusación o excusa, conocerá el asunto el que le sigue en número, si lo hubiera de igual categoría o o en aquel partido no hubiere otro Juez, conocerá el que sigue en razón de la distancia, según la forma indicada.\nPárrafo Reformado\nSi un Juez de lo Familiar, o el que conozca de los asuntos de lo familiar deja de conocer por impedimento recusación o excusa, conocerá del asunto el Juez de Primera\nInstancia de lo familiar que siga en número del mismo partido Judicial si lo hubiere, si no, conocerá del asunto el Juez de Primera Instancia Civil del mismo Partido Judicial; si hubiere varios, conocerán por turno, y si estos también tuvieren impedimento o en aquel Partido no hubiere otro Juez de Primera Instancia Civil, conocerá el Juez de lo Familiar que siga en razón de la distancia según la forma indicada.\nEn caso de recusación sin causa promovida ante el Juzgado de primera Instancia del partido judicial de Tecate, conocerán del asunto, sucesivamente por turno, los jueces del partido judicial de Tijuana.\nEn todos los casos en que según esta Ley debe suplir a un Juez el que le sigue en número, si el que faltare fuere último, será substituido por el que en orden numérico sea el primero y así sucesivamente.\nArtículo Reformado\nARTICULO 103.- En los casos de impedimento por recusación o excusas de los jueces de Paz, conocerá del negocio el secretario, que a su vez actuará con testigos de asistencia.\nTITULO OCTAVO\nDE LAS LICENCIAS DE LOS SERVIDORES PUBLICOS EN LA\nADMINISTRACION DE JUSTICIA\nCAPITULO I\nDE LAS CAUSAS Y SU PROCEDENCIA\nARTICULO 104.- Los Servidores de la Administración de justicia tendrán derecho a que se les conceda licencia para separarse de sus labores, con goce de sueldo o sin él, por causa justificada debidamente acreditada y siempre que no se interrumpan o deteriore el buen funcionamiento de las labores de los Tribunales a juicio del Consejo de la Judicatura o por enfermedad que les impida trabajar, previa comprobación en éste último caso, con certificado que deberá extender un Médico Legista o de Institución Oficial, en los siguientes términos:\nI) Cuando tengan de seis meses a un año de servicio se les concederá licencia hasta por quince días con goce de sueldo íntegro; hasta quince días mes con goce de medio sueldo, y hasta treinta días mes sin sueldo.\nII) Cuando tenga de uno a cinco años de servicio se les concederá la licencia hasta por treinta días con goce de sueldo íntegro, hasta por treinta días más con goce de medio sueldo, y hasta por sesenta días más sin sueldo.\nIII) Cuando tengan más de cinco pero menos de diez años de servicio, se les concederá licencia hasta por cuarenta y cinco días más con goce de sueldo íntegro, hasta goce de sueldo.\nIV) Cuando tengan diez o más años de servicio, se les concederá licencia hasta por sesenta días con goce de sueldo íntegro, hasta por sesenta días más con goce de medio sueldo y hasta por ciento veinte días más sin goce de sueldo.\nARTICULO 105.- Los cómputos a que se refiere el artículo anterior deben hacerse por servicios continuos, o cuando de existir una interrupción en la prestación de servicios, ésta no sea mayor de seis meses.\nARTICULO 106.- Las licencias antes referidas, podrán disfrutarse de manera continua o discontinua, una sola vez cada año, contando a partir del momento en que el servidor de que se trate haya tomado posesión de su cargo.\nARTICULO 107.- Los servidores del Poder Judicial que tengan mas de dos años de servicios continuos podrán obtener licencias sin goce de sueldo para separarse de sus cargos por causas que no sean las de enfermedad, hasta por seis meses cada año.\nARTICULO 108.- Las mujeres disfrutarán de licencias con goce de sueldo íntegro durante el último mes del embarazo y hasta dos meses después el alumbramiento. Al escrito de solicitud correspondiente, la interesada acompañará certificado suscrito por un médico legista y por otro con título legalmente expedido; sin este requisito la licencia se concederá sin goce de sueldo.\nARTICULO 109.- Los servidores del Poder Judicial que por imposibilidad física o por otro motivo justificado no pudieren presentarse al desempeño de sus labores por un término menor de veinticuatro horas, deberán dar aviso, con expresión del motivo del impedimento, al superior jerárquico inmediato. Dichos avisos deberán ser por escrito, o en casos urgentes por la vía telegráfica o telefónica.\nARTICULO 110.- Quienes dejaren de asistir a sus labores por el término a que se refiere el artículo anterior, sin dar el aviso respectivo y sin causa justificada, por la primera vez se les deducirá un día de haber o sueldo, por la segunda dos días de haber o sueldo, y por la tercera serán destituídos de su cargo. labores, por más de tres días, sin la licencia correspondiente y sin causa justificada que haya impedido solicitarla, serán considerados como posibles responsables del delito de abandono de funciones y se les consignará al Ministerio Público.\nTITULO NOVENO\nDE LAS VACACIONES\nCAPITULO I\nDE SUS PERIODOS períodos de vacaciones en el año, de quince días cada uno y con goce de sueldo íntegro.\nPara tener derecho a esta prerrogativa, se necesita haber prestado servicios por más de seis meses consecutivos.\nARTICULO 112.- Las fechas de las vacaciones a que se refiere el artículo anterior serán fijadas por el Consejo de la Judicatura del Estado, por acuerdo en pleno; dichos períodos vacacionales no deberán ser consecutivos y el mismo pleno acordará lo necesario, para que durante ése tiempo, no se entorpezcan las labores del Poder Judicial.\nARTICULO 113.- Cuando los interesados no pudieren hacer uso de sus vacaciones en los períodos que señale el Consejo de la Judicatura del Estado, disfrutarán de ellas durante los quince días siguientes a la fecha en que haya desaparecido la causa que impidió el disfrute de dicho descanso previa autorización del Presidente del mismo Consejo.\nARTICULO 114.- Fuera de los períodos de vacaciones y de los días de asueto que señala el calendario oficial, los Servidores de la Administración de Justicia, solo dejarán de laborar los días que el Pleno del Consejo de la Judicatura del Estado lo estime pertinente.\nTITULO DECIMO\nDE LAS RESPONSABILIDAD DE LOS SERVIDORES PUBLICOS\nDE LA ADMINISTRACION DE JUSTICIA\nCAPITULO I\nDISPOSICIONES GENERALES\nARTICULO 115.- Para los efectos de las responsabilidades a que alude éste Título, se reputará como servidores públicos de la administración de justicia a los Magistrados del\nTribunal Superior de Justicia, a los Consejos de la Judicatura del Estado, a los Jueces de\nPrimera Instancia, y en general, a toda persona que desempeñe un empleo cargo y comisión de cualquier naturaleza dentro del Poder Judicial.\nARTICULO 116.- Los servidores públicos de la Administración de Justicia podrán ser sancionados cuando incurran en responsabilidad, de conformidad con las prevenciones siguientes:\nI.- Se les impondrá, mediante juicio político, las sanciones de destitución e inhabilitación para desempeñar funciones, empleos, cargos o comisiones de cualquier naturaleza en el servicio público, cuando en el ejercicio de sus funciones de los intereses públicos fundamentales, o de su buen desempeño.\nII.- Se aplicarán sanciones administrativas por los actos u omisiones que afecten la legalidad, honradez, lealtad, imparcialidad y eficiencia, que deban observar en el desempeño de su empleo, cargo o comisión. autónomos en su desarrollo, sin que puedan imponerse dos veces, por una sola conducta, sanciones de la misma naturaleza.\nARTICULO 117.- Todo ciudadano o persona moral, por conducto de sus órganos de representación, bajo su más estricta responsabilidad y mediante la presentación de elementos de prueba, podrá formular denuncia por escrito y debidamente firmada y ratificada ante quien corresponda, respecto de las conductas a que se refiere el artículo anterior.\nCAPITULO II\nDEL JUICIO POLITICO\nARTICULO 118.- Son sujetos de Juicio Político; el Presidente del Tribunal Superior del Justicia, los Magistrados, los Jueces y los miembros del Consejo de la Judicatura del\nEstado.\nARTICULO 119.- Corresponde al Congreso del Estado, instruir el procedimiento relativo al juicio político por las causas y con las formalidades establecidas por la Ley de\nResponsabilidades de los Servidores Públicos, así como imponer en su caso, las sanciones que juzgue aplicables de acuerdo con la misma ley.\nARTICULO 120.- El procedimiento de juicio político sólo podrá iniciarse durante el período en que el servidor público desempeña su cargo y dentro del año siguiente al en que se separe, por cualquier causa, del ejercicio de sus funciones.\nCAPITULO III\nDE LA DECLARACION DE PROCEDENCIA EN MATERIA\nDE RESPONSABILIDAD PENAL\nARTICULO 121.- Para proceder penalmente contra los Magistrados del Tribunal\nSuperior de Justicia o los Consejeros de la Judicatura del Estado, por la comisión de delitos durante el tiempo de su encargo, el Congreso del Estado, mediante resolución tomada por mayoría calificada de miembros presentes en sesión, deberá declarar si ha lugar o no a proceder contra el inculpado.\nARTICULO 122.- La responsabilidad derivada de delitos cometidos por los\nMagistrados, Jueces y Consejeros de la Judicatura durante el tiempo de su encargo será exigible de acuerdo con los plazos de prescripción consignados en el Código Penal, los cuales nunca podrán ser inferiores a tres años. No correrá término alguno de prescripción en tanto el Magistrado o Consejero de la Judicatura se encuentre en el desempeño de su cargo.\nCAPITULO IV\nDE LA RESPONSABILIDAD Y FALTAS\nADMINISTRATIVAS\nARTICULO 123.- Son sujetos de responsabilidad administrativa todos los miembros\nARTICULO 124.- La acción disciplinaria y la sanción que corresponda, procede aún en los casos de renuncia o abandono del cargo.\nARTICULO 125.- La acción disciplinaria prescribe en un año, contado desde el día siguiente a aquél en que se hubiere cometido la falta, o a partir del momento en que hubiese cesado, si fuere de carácter continuo, La iniciación del procedimiento interrumpe la prescripción.\nARTICULO 126.- Se consideran como faltas de los Magistrados y Consejeros del\nConsejo de la Judicatura del Estado las siguientes:\nI.- Dejar de asistir a las sesiones sin causa justificada.\nII.- Desintegrar sin motivo justificado, el quórum de los Plenos, una vez iniciados.\nARTICULO 127.- Las faltas administrativas de los magistrados y jueces, serán:\nI.- No dictar, sin causa justificada, las resoluciones que procedan en los negocios jurídicos de su conocimiento, dentro de los términos señalados por la Ley.\nII.- Dictar resoluciones o efectuar trámites notoriamente innecesarios, que tiendan a dilatar el procedimiento.\nIII.- Actuar en negocios jurídicos en que estuvieren impedidos, conociendo la causa del impedimento, salvo en el caso previsto por el artículo 101 de esta ley.\nIV.- Hacer declaración de rebeldía en perjuicio de alguna de las partes, sin cerciorarse de su legal emplazamiento, o antes de que expire el término establecido por la Ley.\nV.- No recibir las pruebas admitidas a las partes.\nVI.- Impedir que las partes hagan uso de los recursos establecidos por la Ley.\nVII.- Admitir fianzas o contrafianzas en los casos que prescriban las leyes, de personas que no acrediten su solvencia y libertad de gravámenes de los bienes que sirvan para ello.\nVIII.- Hacer en sus resoluciones calificaciones ofensivas o calumniosas, en perjuicio de las personas que intervienen en el proceso.\nIX.- Hacer constar falsamente en una diligencia judicial hechos no acaecidos o dejar de mencionar los ocurridos.\nX.- Asesorar a las partes en asuntos de su conocimiento o del conocimiento de otras autoridades judiciales.\nXI.- Dejar de asistir, sin causa justificada, a los actos o diligencias que requieran su presencia.\nXII.- No observar en el trato con sus subalternos y público asistente la debida consideración.\nXIII.- Emitir opiniones anticipadas sobre las resoluciones en asuntos de su\nXIV.- No asistir puntualmente al inicio de labores en donde desempeñen su función.\nXV.- No consignar su nombre completo en la actuación o resolución judicial que dictare.\nARTICULO 128.- Son faltas administrativas de los secretarios:\nI.- No dar cuenta al juez dentro de las veinticuatro horas, con los documentos oficiales, asi como con las promociones de las partes.\nII.- No asentar al calce de los escritos a que se refiere la fracción anterior, la razón de recibo correspondiente.\nIII.- No asentar en autos dentro del término legal, las certificaciones y constancias que procedan por disposiciones de la Ley o por mandato judicial.\nIV.- Actuar en los negocios jurídicos en que estuvieren impedidos.\nV.- No formular el proyecto de resolución que se les hubiere encomendado, en el término fijado para ello.\nVI.- Obrar con negligencia en la custodia de los expedientes y documentos de su dependencia, propiciando el deterioro, destrucción, ocultamiento, substracción o pérdida.\nVII.- No practicar los actos necesarios para la celebración de las audiencias en las fechas señaladas.\nVIII.- No hacer entrega oportuna a los actuarios de los expedientes que requieran notificación personal o estén pendientes de diligenciación, cuando deba actuarse fuera del\nJuzgado.\nIX.- No hacer a las partes las notificaciones personales que procedan, cuando ocurran al Juzgado o Tribunal.\nX.- No mostrar a las partes, sin motivo justificado, los expedientes que les soliciten, o facilitarlos a quienes no cuenten con la debida autorización.\nXI.- Proporcionar información telefónica, por escrito, o por cualquier otro medio a los interesados sobre el estado de los autos.\nXII.- No consignar en las actuaciones judiciales su nombre completo y firmarlos.\nARTICULO 129.- Son faltas de los actuarios:\nI.- No hacer, con la debida oportunidad y sin causa justificada, las notificaciones personales que procedan, ni llevar a cabo las diligencias que se les encomienden, cuando deba efectuarse fuera del Juzgado o Tribunal.\nII.- Redactar indebidamente las notificaciones, emplazamientos, embargos o diligencias de cualquier género que hayan realizado u omitieren poner su nombre completo.\nIII.- Dar preferencia a algún litigante con perjuicio de otro, por cualquier motivo.\nIV.- Practicar notificaciones, citaciones o emplazamientos por cédula o instructivo, en lugar distinto al designado en autos, o sin cerciorarse, cuando proceda, de que el interesado tiene su domicilio en el lugar donde se lleve a cabo la diligencia, salvo lo establecido en el\nCódigo de Procedimientos respectivos.\nV.- Practicar embargos, aseguramientos, retención de bienes o lanzamientos, de personas o corporaciones, que no estén mencionadas concretamente en la resolución que se cumplimenta, o cuando en el acto de la diligencia, se le haga ver que esos bienes son ajenos, en cuyo caso deberá agregar a los autos la documentación que se le presente y dar cuenta al Juez.\nVI.- No levantar el acta relativa a la diligencia que practique, en el lugar y momento en que ésta se efectúe.\nVII.- Recibir gratificaciones de las partes con motivo de las diligencias en que actúen.\nARTICULO 130.- Son faltas Administrativas de los Servidores Públicos de base:\nI.- No observar el debido respeto y subordinación hacia sus superiores jerárquicos inmediatos o mediatos.\nII.- Incumplir las disposiciones que sus superiores jerárquicos dicten en el ejercicio de sus atribuciones.\nIII.- Dejar de cumplir con diligencia las instrucciones, requerimientos o trabajos que les sean encomendados.\nIV.- Recibir gratificaciones de cualquier índole.\nV.- Utilizar material y equipo en trabajos ajenos a la oficina.\nARTICULO 131.- Constituyen faltas administrativas comunes a todos los servidores públicos de la Administración de Justicia:\nI.- Incumplir, con la mayor diligencia el trabajo que le sea encomendado, o realizar actos u omisiones que hagan deficiente su labor.\nII.- No asistir puntualmente al desempeño de sus funciones.\nIII.- Dejar de asistir sin motivo justificado al despacho de su oficina o cerrarla limitando indebidamente las horas de trabajo.\nIV.- Autorizar a un subordinado a no asistir a sus labores sin causa justificada, así como otorgarle indebidamente permisos, licencias o comisiones con goce parcial o total de sueldo, cuando las necesidades del servicio público no lo requieran.\nV.- No atender con la debida corrección a los litigantes y al público en general.\nVI.- Solicitar o recibir dádivas, préstamos, regalos y obtener toda clase de percepciones provenientes, directa o indirectamente, de alguna de las partes o de sus representantes o intermediarios, en negocio sometido a su conocimiento, o en el que haya de intervenir.\nVII.- Obtener o tratar de obtener por el desempeño de su función, beneficios adicionales a las prestaciones que le sean cubiertas con cargo al Erario Público.\nVIII.- Influir, directa o indirectamente, en el nombramiento, promociones, suspensión, remoción, cese o sanción de cualquier servidor público de la Administración de Justicia, ya sea por interés personal, familiar o de negocios, o porque con ello pretenda derivar alguna ventaja o beneficio para sí o para un tercero.\nIX.- Abstenerse de cumplir las comisiones que legalmente se le confieran o retardar injustificadamente su ejecución.\nX.- No presentar con oportunidad y veracidad la declaración sobre la situación patrimonial, ante la autoridad correspondiente, en los términos que señala la Ley de\nResponsabilidades.\nXI.- No informar a su superior jerárquico o al titular de su dependencia de todo acto y omisión de los servidores públicos sujetos a su dirección, que puedan implicar inobservancia de las obligaciones propias del cargo.\nXII.- Expedir nombramiento en favor de quien se encuentra inhabilitado por resolución firme de autoridad competente, teniendo conocimiento de ello.\nXIII.- Desempeñar algún otro empleo, cargo o comisión oficial o particular, que la Ley prohiba.\nXIV.- Ejercer funciones de un empleo, cargo o comisión cuando haya concluído el período para el cual se le designe, o haber cesado, por alguna otra causa, en el ejercicio de sus funciones.\nXV.- Desempeñar su labor en estado de embriaguez hacer uso indebido de estupefacientes; practicar juegos prohibidos, u observar, en general un comportamiento inmoral, en el lugar en que le tocare desempeñarse.\nXVI.- Dar el uso inadecuado al equipo de cómputo, electrónico o de cualquier otro que se le facilitare para el desarrollo de sus labores, o que existe en el lugar de su trabajo.\nXVII.- Recibir de las partes de un juicio o sus abogados, dinero por concepto de pago de derechos de certificación de copias o copias simples, las cuales deberán pagarse en la caja de la unidad administrativa respectiva, presentando el recibo en el juzgado donde se esté tramitando el asunto.\nXVIII.- Todo incumplimiento de los deberes propios del cargo.\nArtículo Reformado\nCAPITULO V\nDE LAS SANCIONES Y SU APLICACION\nARTICULO 132.- Las sanciones aplicables a las faltas administrativas consistirán en:\nI.- Apercibimiento.\nII.- Amonestación.\nIII.- Multa.\nIV.- Suspensión.\nV.- Destitución del cargo.\nVI.- Inhabilitación temporal para desempeñar empleo, cargo o comisión en el Poder\nJudicial del Estado.\nARTICULO 133.- El apercibimiento consiste en la prevención verbal o escrita que se haga al servidor público, en el sentido de que de incurrir en una nueva falta, se le aplicará una o más de las sanciones previstas en el artículo anterior, según el caso.\nARTICULO 134.- La amonestación consiste en la reprensión verbal o escrita que se haga al infractor por falta cometida.\nARTICULO 135.- La sanción pecuniaria impuesta al infractor en favor del Fondo para el Mejoramiento de la Administración de Justicia, no podrá ser inferior a un día de sueldo, ni exceder al de un mes, debiendo hacerse efectiva mediante descuento en nómina, de cuotas iguales, no superiores a la quinta parte del sueldo mensual, o a través del procedimiento económico coactivo, con intervención de la autoridad competente.\nARTICULO 136.- La suspensión consiste en la separación temporal, que no podrá exceder de tres meses, del cargo, empleo o comisión, privando al servidor público del derecho a percibir remuneración, o cualquiera otras prestaciones económicas a que tenga derecho, salvo el caso a que se refiere el artículo 150 de esta ley.\nARTICULO 137.- La destitución consiste en la pérdida definitiva del cargo empleo o comisión.\nARTICULO 138.- La inhabilitación implica la incapacidad temporal, hasta por tres años para obtener y ejercer cargo, empleo o comisión.\nARTICULO 139.- Las sanciones administrativas se impondrán, tomando en cuenta:\nI.- La gravedad y modalidad de la falta en que se haya incurrido.\nII.- El grado de participación.\nIII.- Las circunstancias socio-económicas del infractor.\nIV.- Los motivos determinantes y los medios de ejecución.\nV.- La antigüedad en el servicio.\nVI.- La reincidencia.\nVII.- El monto del beneficio, daño o perjuicio económico derivados de la falta.\nARTICULO 140.- Las sanciones impuestas se anotarán en la hoja de servicios del servidor público a cuyo efecto deberá enviarse copia autorizada de la resolución al Consejo de la Judicatura del Estado.\nARTICULO 141.- Para la aplicación de las sanciones a que se hace referencia en los artículos anteriores, se observarán las siguientes reglas:\nI.- El apercibimiento se aplicará por la primera falta cometida, cuando ésta sea leve.\nII.- La amonestación se aplicará sólo tratándose de la acumulación de dos faltas leves cometidas en un plazo de treinta días.\nIII.- Después de dos amonestaciones la nueva sanción será de multa que no excederá del haber de un día de salario.\nIV.- La triple sanción por faltas leves, o la comisión de una falta grave, motivará la suspensión del cargo, empleo o comisión.\nV.- La destitución se aplicará, como primera sanción, en caso de faltas graves, o después de dos sanciones de suspensión.\nVI.- La inhabilitación sólo será aplicable por resolución jurisdiccional, que dictará el órgano que corresponda, con arreglo a las leyes aplicables.\nCuando la destitución del cargo, empleo o comisión, afecte a un servidor público de base, se procederá a la terminación de su contrato ante quien corresponda por el Consejo de la Judicatura del Estado.\nARTICULO 142.- La potestad disciplinaria se ejercerá:\nI.- Por los secretarios de Acuerdos cuando se trate de quejas en contra de sus subalternos, y la falta sólo amerite como sanción, apercibimiento o amonestación.\nII.- Por el Presidente del Tribunal Superior de Justicia, Magistrados y jueces, cuando se trate de quejas en contra de los secretarios, independientemente de la sanción que les corresponda por la falta cometida y en contra de los demás servidores públicos, cuando deba aplicárseles a personas diversas de las que se refiere la fracción anterior.\nIII.- Por el Pleno del Consejo de la Judicatura del Estado, cuando se trate de quejas en contra de los funcionarios a que se refiere la fracción anterior.\nIV.- Por el Pleno del Consejo de la Judicatura, cuando se trate de quejas en contra de su Presidente o uno de sus Consejeros.\nV.- Por el Consejo de la Judicatura del Estado cuando lo prevea la Ley.\nARTICULO 143.- Contra el presunto autor de alguna de las faltas previstas en el capítulo IV de este título, se procederá de oficio o en virtud de queja presentada por escrito, ante el Consejo de la Judicatura.\nLas quejas anónimas, o aquéllas que no sean ratificadas, no producirán efecto alguno.\nCuando las quejas se promuevan respecto a los Titulares de los Juzgados de Primera\nInstancia, en materia Laboral, Mixtos o de Paz, de un Partido Judicial distinto al de la residencia del Consejo de la Judicatura, se presentarán directamente ante éste o la Oficialía de Partes y la ratificación correspondiente, deberá hacerla ante el Juez que en número de orden le suceda o bien el que designe el propio Consejo de la Judicatura o por medio de la autoridad que al efecto señalare.\nPárrafo Reformado\nEn los casos en que al estarse llevando a cabo una visita de inspección por medio del\nConsejero o la autoridad que se ha designado, se presentará una queja, se ratificará ante la presencia del servidor público que la reciba.\nArtículo Reformado\nARTICULO 144.- Todos los servidores públicos tienen la obligación de respetar y hacer respetar el derecho a la formulación de quejas, y de evitar que, con motivo de éstas, se originen molestias indebidas al quejoso.\nIncurre en responsabilidad el servidor público que por sí, o por interpósita persona, empleando cualquier medio, impida la presentación de alguna queja, o que con motivo de ésta, realice cualquier acto u omisión que lesione injustamente los intereses de quien la formule.\nARTICULO 145.- El Presidente del Consejo de la Judicatura del Estado, a petición de parte interesada formulará excitativas a las autoridad que omitan o retarden la iniciación o el trámite de un procedimiento disciplinario.\nARTICULO 146.- Si los hechos materia de la queja fueren además constitutivos de responsabilidad política o penal, se ordenará ponerlos en conocimiento de la autoridad competente, acompañándole copia autorizada de lo necesario.\nARTICULO 147.- Las sanciones administrativas a que se refiere éste capítulo se impondrán con sujeción al siguiente procedimiento:\nI.- En el auto inicial del proceso disciplinario, se ordenará correr traslado al infractor, con copia de la queja o el acta correspondiente, para que informe por escrito dentro del término de cinco días, señalándose lugar, día y hora, para la celebración de una audiencia de pruebas y alegatos, a mas tardar dentro del término de quince días después de recibido el informe.\nII.- Las pruebas deberán ofrecerse y rendirse durante la audiencia; en la que podrá recibirse únicamente las pruebas documental o de inspección ocular que ofrezcan las partes, las que se recibirán desde luego, anunciándose con cinco días de anticipación para la debida preparación de su desahogo. Tratándose de documentales que la parte interesada manifieste la imposibilidad para obtenerlas o no las tuviere a su disposición, designará el archivo o lugar en que se encuentren los originales, salvo que se trate de aquellas que existan en un archivo público del que puedan pedir y obtener copias autorizadas de ellos.\nIII.- En cualquier estado del procedimiento, el Consejo de la Judicatura podrá interrogar libremente al denunciante y al denunciado y practicar careos entre ambos.\nIV.- En cualquier tiempo antes de fallarse, podrá el Consejo de la Judicatura decretar medidas para mejor proveer.\nV.- Abierta la audiencia se procederá a recibir, por su orden las pruebas y los alegatos por escrito, esto último sin perjuicio de que los interesados puedan alegar verbalmente, sin que sus alegaciones se hagan constar en autos.\nVI.- Al concluir la audiencia, y dentro de los ocho días hábiles siguientes, se resolverá sobre la procedencia de la queja, imponiendo al infractor, en su caso, las sanciones administrativas correspondientes, notificándosele personalmente la resolución dentro de las veinticuatro horas siguientes, y dándola a conocer, mediante oficio al Presidente del Consejo de la Judicatura del Estado; para los efectos legales que hubiere lugar.\nVII.- En cualquier momento, antes o después de la iniciación del proceso disciplinario, se podrá acordar la suspensión temporal del presunto autor en su cargo, empleo o comisión, si a juicio del Presidente del Consejo de la Judicatura, conviniere para el desarrollo de la investigación. La suspensión temporal no prejuzga sobre la determinación final que se tome.\nSi el servidor público temporalmente suspendido, no resultare responsable de la falta que se le haya imputado, será restituido en el goce de sus derechos, y se le cubrirá las percepciones que debió recibir durante la suspensión.\nARTICULO 148.- Se levantará acta circunstanciada de las diligencias que se practiquen, misma que suscribirán quienes en ellas intervengan.\nARTICULO 149.- Las resoluciones dictadas por las autoridades que sustancien el mismo como una vez fallado.\nARTICULO 150.- La suspensión temporal a que alude la fracción VII del artículo 147 de esta ley, no deberá exceder del plazo de tres meses, salvo que a juicio del Presidente del pruebas, de la investigación, o de la naturaleza propia de la infracción que haya motivado la iniciación del procedimiento disciplinario.\nARTICULO 151.- Entre tanto, se substancia el procedimiento disciplinario y una vez suspendido temporalmente al presunto infractor, deberá proveerse a quien en forma interina deberá suplirlo, a menos que durante el tiempo en que se desahoga este procedimiento, hubiese expirado el período para el que fue nombrado el presunto infractor, caso en el que podrá hacerse nombramiento definitivo. Si se declarara improcedente o infundada la queja a la fecha en que ya se hubiese hecho una designación definitiva, se le cubrirán las percepciones que debió recibir durante la suspensión hasta la fecha en que concluya el período para el que hubiera sido nombrado.\nARTICULO 152.- La ejecución de las sanciones administrativas impuestas en resolución firme, se llevará a cabo de inmediato en sus términos, pero tratándose de los servidores públicos de base, la restitución se sujetará a lo previsto por la Ley del Servicio\nCivil.\nARTICULO 153.- Si el presunto autor confesare la responsabilidad, se procederá de inmediato a dictar resolución, a no ser que quien conoce el procedimiento, disponga la recepción de pruebas para robustecer la veracidad de la confesión. En caso de que se acepte la plena validez probatoria de la confesión, se impondrá al infractor un tercio de la sanción aplicable, si es de naturaleza económica, y siempre deberá restituir lo que hubiere percibido con motivo de la infracción. Quedará al arbitrio prudencial de quien resuelva, dispensar al infractor de la suspensión y separación o inhabilitación.\nARTICULO 154.- Para el cumplimiento de las atribuciones que les confiere esta ley, las autoridades a que se refiere el artículo 2, podrán aplicar los siguientes medios de apremio:\nI.- Sanción económica hasta de veinte veces el salario mínimo diario vigente en el\nEstado.\nII.- Auxilio de la fuerza pública.\nSi existiere resistencia al mandamiento legítimo de autoridad se estará a lo dispuesto en las prevenciones que establezca la Legislación Penal.\nTÍTULO DÉCIMO PRIMERO\nDE LOS ÓRGANOS ADMINISTRATIVOS DEL PODER\nJUDICIAL DEL ESTADO\nCAPITULO I\nDEL CONSEJO DE LA JUDICATURA DEL ESTADO DE\nBAJA CALIFORNIA.\nSU INTEGRACION Y FUNCIONAMIENTO\nARTICULO 155.- La Administración, Vigilancia, Disciplina y Carrera Judicial del Poder\nJudicial del Estado, estará a cargo del Consejo de la Judicatura de la Entidad, en los\nEl Consejo de la Judicatura del Estado velará, en todo momento, por la autonomía de miembros de éste último.\nARTICULO 156.- El Consejo de la Judicatura, se integrará por siete Consejeros, en los términos de las fracciones I, II, III, IV y V del artículo 64 de la Constitución Local y funcionará en Pleno o a través de Comisiones, además contará con un Secretario General.\nEl Consejo de la Judicatura entrará en funciones el día 1 de diciembre del año en que corresponda realizar las designaciones de nuevos Consejeros. Para tal efecto el Tribunal\nSuperior de Justicia, el Congreso del Estado y el Gobernador del Estado efectuarán las designaciones directas con la debida anticipación.\nLos Magistrados del Tribunal Superior de Justicia así como el Juez que desempeñen el cargo de Consejeros no recibirán por esta función, compensación, estímulos o cualquier otra prestación en dinero o en especie adicional a la que reciban como titulares de sus respectivos órganos jurisdiccionales.\nArtículo Reformado\nARTICULO 157.- El Pleno del Consejo de la Judicatura, aprobará durante la primera sesión del año a propuesta de su Presidente, su calendario anual de actividades colegiadas.\nArtículo Reformado\nARTICULO 158.- El Consejo de la Judicatura del Estado, estará presidido por el presidente del Tribunal Superior de Justicia, quien también lo será del Consejo y ejercerá las atribuciones que le confiere ésta Ley.\nARTICULO 159.- Las resoluciones del Consejo de la Judicatura del Estado y de sus organismos auxiliares constarán en acta. Las notificaciones y, en su caso, la ejecución de sus resoluciones deberá realizarse por conducto de los órganos del propio Consejo de la\nJudicatura del Estado, o de la autoridad que actúe en auxilio de éste.\nCuando el Pleno del Consejo de la Judicatura del Estado, estime que sus reglamentos, acuerdos, resoluciones o de sus organismos auxiliares pudieran resultar de interés general, deberá ordenar su publicación en el Periódico Oficial del Estado.\nARTÍCULO 160.- El Consejo de la Judicatura del Estado, sesionará de acuerdo al calendario anual de actividades colegiadas aprobado, mismas que se celebrarán semanalmente el día y hora preestablecidos en la agenda, previa convocatoria del\nPresidente.\nSe podrá sesionar fuera de calendario, para tratar y resolver únicamente aquellos asuntos de carácter urgente, previa convocatoria del Presidente por iniciativa propia o a solicitud de alguno de los Consejeros. convocado conforme al calendario anual de actividades colegiadas aprobado, así como a las sesiones que haya convocado fuera del mismo, será designado previa verificación del cumplimiento del quórum y por mayoría simple de los miembros presentes, un Consejero quien se encargará de presidir la reunión, dirigir los debates y conservar el orden durante el transcurso de la sesión.\nArtículo Reformado\nARTÍCULO 161.- El Pleno se integrará con siete Consejeros; bastará la presencia de la mayoría de sus integrantes para sesionar.\nEl Pleno del Consejo de la Judicatura podrá reunirse de forma presencial o a través de las plataformas y medios electrónicos de los que disponga el Poder Judicial del Estado, previa convocatoria del Presidente.\nPárrafo Adicionado\nArtículo Reformado\nARTICULO 162.- Las sesiones aprobadas en el calendario anual de actividades colegiadas aprobadas por el Consejo de la Judicatura, serán públicas y excepcionalmente privadas.\nEl Consejo deberá otorgar el espacio y demás condiciones necesarias para garantizar la publicidad y el acceso al público a las sesiones, además serán transmitidas por el portal oficial de internet del Poder Judicial del Estado de Baja California.\nArtículo Reformado\nARTICULO 163.- Las resoluciones del Pleno del Consejo de la Judicatura del Estado, se tomarán por el voto de la mayoría de los Consejeros presentes, los Consejeros no podrán abstenerse de votar sino cuando tengan impedimento legal. En caso de empate, el\nPresidente tendrá voto de calidad.\nEl Pleno del Consejo de la Judicatura del Estado calificará los impedimentos de sus miembros que hubieran sido planteados en asuntos de su competencia, y si el impedido fuera el Presidente, será substituido por el Magistrado que el Pleno del Tribunal Superior de\nJusticia designe, absteniéndose de intervenir el Presidente impedido. Asumirá la presidencia del Consejo de la Judicatura con motivo de impedimento o excusa, el Consejero que por turno le corresponda, quien en su caso empate, tendrá voto de calidad.\nArtículo Reformado\nCAPITULO II\nDE LAS UNIDADES DE APOYO\nARTICULO 164.- El Consejo de la Judicatura del Estado contará con aquellas atribuciones y que autorice el presupuesto de egresos.\nARTICULO 165.- El Consejo de la Judicatura determinará la distribución de las funciones que deben desempeñar las Unidades Administrativas.\nARTICULO 166.- Para el mejor desempeño de las funciones asignadas a las correspondiente.\nARTICULO 167.- Los titulares de las unidades administrativas deberán tener título profesional expedido en alguna materia afín a las atribuciones conferidas, experiencia mínima de tres años, gozar de buena reputación y no haber sido condenado por delito intencional con sanción privativa de libertad mayor de un año.\nCAPITULO III\nDE SUS ATRIBUCIONES\nARTÍCULO 168.- Son atribuciones del Consejo de la Judicatura del Estado.\nI.- Establecer las unidades administrativas que estime convenientes para el adecuado funcionamiento del Consejo de la Judicatura del Estado y designar a los consejeros que deban integrarlas.\nII.- Expedir los reglamentos interiores en materia administrativa, de carrera judicial, de escalafón, régimen disciplinario y todos aquellos acuerdos generales que fueren necesarios para el adecuado ejercicio de sus atribuciones en términos del artículo 65 de la Constitución\n294 de esta ley.\nFracción Reformada\nIII.- Fijar las bases, convocar y realizar el procedimiento para cubrir las respectivas vacantes al Consejo de la Judicatura del Estado, entre ellos jueces, magistrados en términos por falta grave con motivo de una queja administrativa.\nIV.- Determinar el número y, los límites territoriales de los partidos judiciales en que se divide el Estado.\nV.- Determinar el número y, en su caso, especialización por materia de las Salas del\nTribunal Superior de Justicia.\nVI.- Determinar el número y, límites territoriales y, en su caso, especialización por materia, de los juzgados de primera instancia y de paz.\nVII.- Derogada\nVIII.- Acordar las renuncias que presenten los magistrados, jueces, secretarios,\nIX.- Acordar la destitución del personal señalado en la fracción anterior.\nX.- Suspender en sus cargos a los magistrados y jueces a solicitud de la autoridad judicial que conozca del procedimiento penal que se siga en su contra. En éstos casos, la resolución que se dicte deberá comunicarse a la autoridad que la hubiere solicitado.\nEstado, constituye un requisito previo indispensable para su aprehensión y, enjuiciamiento. precepto, se procederá en términos del artículo 94 de la Constitución del Estado y los referentes del Código Punitivo Estatal. El Consejo de la Judicatura del Estado determinará si el juez o magistrado debe continuar percibiendo una remuneración y, en su caso, el monto de ella durante el tiempo en que se encuentre suspendido.\nXI.- Suspender en sus funciones a los magistrados y jueces que aparecieren involucrados en la comisión de un delito, y formular denuncia o querella contra ellos en los casos en que proceda.\nXII.- Recibir y resolver sobre las quejas administrativas relativas a demoras, excusas faltas en el despacho de los negocios o asuntos que tramiten ante el Tribunal Superior de\nJusticia, juzgados y dependencias a su cargo, solicitando los informes necesarios y realizar investigaciones, funciones que podrán delegarse a través de la correspondiente comisión; y sobre la responsabilidad de servidores públicos en términos de lo que dispone ésta ley, incluyendo aquellas que se refieran a la violación de los impedimentos previstos por el miembros de la administración de justicia.\nXIII.- Formular anualmente el proyecto del presupuesto de egresos del Poder Judicial y someterlo al Ejecutivo del Estado para su remisión y aprobación en su caso por el\nCongreso del Estado.\nXIV.- Solicitar al Tribunal Superior de Justicia sesione en forma extraordinaria cuando el interés del asunto así lo amerite.\nFracción Reformada\nXV.- Nombrar a las personas titulares de los órganos auxiliares del Poder Judicial, resolver sobre sus renuncias y licencias, removerlos libremente o suspenderlos en los términos que determinen las leyes y los acuerdos correspondientes, y formular denuncia o querella en los casos en que proceda.\nFracción Reformada\nXVI.- Nombrar, a su Secretario General así como conocer de su licencia, remoción, suspensión o renuncia.\nXVII.- Emitir las bases mediante acuerdos generales, para las adquisiciones, arrendamientos y enajenaciones de todo tipo de bienes, prestaciones de servicios de presupuesto de egresos.\nXVIII.- Dictar las bases generales de organización y funcionamiento de sus órganos auxiliares.\nXIX.- Establecer las disposiciones generales necesarias para el ingreso, estímulos, capacitación, ascensos y promociones por escalafón y remoción del personal administrativo de los Tribunales.\nXX.- Cambiar la residencia de los juzgados.\nXXI.- Conceder licencias en los términos previstos en ésta ley.\nXXII.- Designar, al representante del Poder Judicial del Estado ante el Consejo de la\nJudicatura Federal, del Distrito Federal o de otros Estados, cuando convoquen a intercambio de intenciones o congresos.\nXXIII.- Apercibir, amonestar e imponer multas hasta de treinta días del importe del salario mínimo general en la zona al día de cometerse la falta a aquellas personas que falten el respeto a algún órgano o miembro del Poder Judicial del Estado en promociones que hagan ante el Consejo de la Judicatura del Estado.\nXXIV.- Formar anualmente una lista con los nombres de las personas que puedan fungir como peritos ante los órganos del Poder Judicial del Estado, como Auxiliares de la\nAdministración de Justicia; ordenándolas por ramas y especialidades judiciales.\nXXV.- Ejercer el presupuesto de egresos del Poder Judicial del Estado, relativo a la administración de justicia.\nXXVI.- Supervisar el funcionamiento de los Organos Auxiliares del Consejo de la\nJudicatura del Estado.\nXXVII.- Remitir los informes que solicite el Poder Ejecutivo y Legislativo.\nXXVIII.- Fijar los períodos vacacionales de los magistrados, jueces y en general de los empleados del Poder Judicial.\nXXIX.- Administrar los bienes muebles e inmuebles del Poder Judicial, cuidando su mantenimiento, conservación, acondicionamiento, y la distribución de las oficinas judiciales en sus diversos departamentos.\nXXX.- Fijar las bases de la política informática y de información estadística que permitan conocer y planear el desarrollo del Poder Judicial.\nXXXI.- Investigar y determinar las responsabilidades y sanciones a los servidores públicos y empleados del propio Consejo, magistrados, jueces y órganos auxiliares, en los términos y mediante los procedimientos establecidos en la Ley, los reglamentos y acuerdos generales que dicte el Consejo en materia disciplinaria.\nXXXII.- Realizar visitas extraordinarias o integrar comités de investigación, cuando\nJusticia.\nXXXIII.- Dictar las medidas que exijan el buen servicio y la disciplina en las oficinas de los Juzgados y órganos auxiliares del Consejo de la Judicatura del Estado.\nXXXIV.- Autorizar el nombramiento y remoción de los empleados de la administración de justicia.\nPárrafo Reformado juzgados de primera instancia, su remoción deberá ser propuesta por la persona titular del órgano al que se encuentre adscrito.\nPárrafo Adicionado\nFracción Reformada\nXXXV.- Crear las unidades administrativas que el presupuesto de egresos autorice, asignándoles sus atribuciones.\nXXXVI.- Practicar periódicamente visitas a las Salas del Tribunal Superior de Justicia y juzgados para observar la conducta y desempeño del personal, recibiendo las quejas que hubiere contra ellos y ejercer las atribuciones que señala esta ley.\nXXXVII.- Dar trámite a las iniciativas de leyes y decretos ante la Legislatura del\nEstado en asuntos relacionados con la organización y funcionamiento de la administración de justicia.\nXXXVIII.- Solicitar la celebración de sesiones al Tribunal Superior de Justicia, cuando lo estime pertinente.\nXXXIX.- Expedir la convocatoria y desarrollar el proceso de selección de las personas que aspiren a ocupar los cargos que se mencionan en las fracciones XL, XLI y XLII, de este artículo, para la elaboración de las listas de personas que deben ser consideradas para ocupar dichos cargos.\nXL.- Remitir al Congreso del Estado, la lista de las personas que deben ser consideradas para ocupar las vacantes en el cargo de Magistrado del Tribunal Superior de\nJusticia del Estado.\nXLI.- Remitir al Pleno del Tribunal Superior de Justicia, la lista de las personas que deben ser consideradas para ocupar las vacantes en los cargos de Jueces, Secretario\nGeneral de Acuerdos, Secretarios de Estudio y Cuenta, Secretarios Auxiliares y Actuarios del Tribunal Superior de Justicia del Estado. ordenamientos jurídicos le confieran.\nArtículo Reformado\nARTICULO 169.- El Consejo de la Judicatura así como el Tribunal Superior de\nJusticia por medio de su Presidente, mediante oficio podrán otorgar poder para pleitos y autoridades administrativas, judiciales y laborales, ya sea que intervengan como actores, demandados, coadyuvantes o terceristas, limitándose el mandato al asunto específico que se señalaren.\nARTICULO 170.- El Pleno del Consejo de la Judicatura, contará con los Servidores\nPúblicos y personal de apoyo que establece ésta ley.\nARTICULO 171.- El Consejo de la Judicatura residirá en la capital del Estado de Baja\nCalifornia.\nCAPITULO IV\nDE SU PRESIDENTE\nARTICULO 172.- Son atribuciones del Presidente del Consejo de la Judicatura del\nEstado las siguientes:\nI.- Representar al Consejo de la Judicatura del Estado de Baja California.\nII.- Presidir el Pleno, dirigir los debates y conservar el orden en las sesiones.\nIII.- Dar cuenta al Pleno del Consejo de la Judicatura de los nombramientos que el organismo autorice respecto de los titulares de los Organos Auxiliares del propio Consejo.\nIV.- Vigilar el funcionamiento de los Organos Auxiliares del Consejo de la Judicatura.\nV.- Otorgar licencias para separar de sus labores en los términos previstos por ésta\nLey, y permisos económicos hasta por ocho días con goce de sueldo o sin él, a los\nMagistrados, Jueces y empleados de la administración de justicia.\nVI.- Firmar las resoluciones y acuerdos del Pleno del Consejo de la Judicatura del\nEstado.\nVII.- Las demás que determine esta ley y los correspondientes reglamentos y acuerdos generales.\nArtículo Reformado\nCAPITULO V\nDEL SECRETARIO GENERAL DEL\nCONSEJO DE LA JUDICATURA\nARTICULO 173.- El Secretario General del Consejo de la Judicatura del Estado tendrá las siguientes atribuciones:\nI.- Tramitar los asuntos del Consejo de la Judicatura del Estado y turnar los expedientes entre sus integrantes para su atención.\nII.- Despechar la correspondencia oficial del Consejo. que la ley exija este requisito.\nIV.- Registrar las cédulas de abogados, los permisos y las autorizaciones expedidas por la Dirección de Profesiones del Estado. De las listas de registros que se irán formando, Justicia, con el objeto de que estos no permitan el ejercicio de la profesión a las personas que no se encuentren autorizadas.\nV.- Certificar, autorizar y dar fe de las actuaciones del Consejo de la Judicatura, y extender constancias de las mismas, cuando fueren solicitadas y autorizadas por el\nPresidente del Consejo.\nVI.- Coordinar las funciones de los titulares de las unidades administrativas del\nConsejo de la Judicatura.\nVII.- Llevar el turno de los Consejeros que por casos de impedimento o excusa.\nVIII.- Llevar el control y lista de los auxiliares de la administración de justicia.\nIX.- Las demás que le asignen las leyes y reglamentos.\nARTICULO 174.- El Secretario General del Consejo de la Judicatura deberá reunir los requisitos que señala el artículo 24 de esta ley.\nCAPITULO VI\nDE LOS ORGANOS AUXILIARES\nDEL CONSEJO DE LA JUDICATURA\nARTICULO 175.- Para su adecuado funcionamiento, el Consejo de la Judicatura del\nEstado contará cuando menos con las siguientes unidades administrativas:\nI.- El Instituto de la Judicatura;\nII.- El Archivo Judicial y de Notarios;\nIII.- El Boletín Judicial;\nIV.- La Contraloría;\nV.- La Oficialía de Partes;\nVI.- El Centro Estatal de Justicia Alternativa, y\nVII.- El Administrador Judicial.\nArtículo Reformado\nCAPITULO VII\nDEL INSTITUTO DE LA JUDICATURA\nARTICULO 176.- El Instituto de la Judicatura es la unidad administrativa del Consejo de la Judicatura del Estado en materia de investigación, formación, capacitación y pertenecer a éste. El funcionamiento y atribuciones del Instituto de la Judicatura se regirán respectivo. párrafo anterior.\nARTICULO 177.- El Instituto de la Judicatura contará con un director y el personal necesario para el desempeño de la función.\nARTICULO 178.- El Instituto de la Judicatura cumplirá con los planes y programas que autorice el Consejo de la Judicatura del Estado.\nARTICULO 179.- Los programas que imparta el Instituto de la Judicatura tendrán como objeto lograr que los integrantes del Poder Judicial del Estado o quienes aspiren a ingresar a éste, fortalezcan los conocimientos y habilidades necesarios para el adecuado desempeño de la función judicial. Para ello, el Instituto de la Judicatura establecerá los programas y cursos tendientes a:\nI.- Desarrollar el conocimiento práctico de los trámites, diligencias y actuaciones que forman parte de los procedimientos y asuntos de la competencia del Poder Judicial del\nEstado.\nII.- Perfeccionar las habilidades técnicas en materia de preparación y ejecución de actuaciones judiciales.\nIII.- Reforzar, actualizar y profundizar los conocimientos respecto del ordenamiento jurídico positivo, doctrina y jurisprudencia.\nIV.- Proporcionar y desarrollar técnicas de análisis, argumentación e interpretación que permitan valorar correctamente las pruebas y evidencias aportadas en los procedimientos, así como formular adecuadamente las actuaciones y resoluciones judiciales.\nV.- Difundir las técnicas de organización en la función jurisdiccional, coordinando la biblioteca judicial y supervisando la revista de información judicial.\nVI.- Contribuir al desarrollo de la vocación de servicio así como al ejercicio de los valores y principios éticos inherentes a la función judicial, implementando los exámenes y concursos de méritos conforme al reglamento de la materia.\nVII.- Promover intercambios académicos con instituciones de educación superior.\nARTICULO 180.- El Instituto de la Judicatura llevará acabo cursos de preparación judicial, con excepción a la de los magistrados.\nARTICULO 181.- El Instituto de la Judicatura, contará con un área de investigación, la\nCAPITULO VIII\nDEL ARCHIVO JUDICIAL\nARTICULO 182.- El Consejo de la Judicatura del Estado, tendrá bajo su cargo el archivo judicial. Y el pleno o la comisión respectiva dictará las medidas que estime convenientes y la práctica de visitas cada vez que lo juzgue pertinente.\nARTICULO 183.- Deberán depositarse en el Archivo Judicial:\nI.- Todos los expedientes y tocas del orden civil y penal, concluídos por las\nAutoridades Judiciales del Estado.\nII.- Los expedientes y tocas que, aún cuando no estén concluídos, hayan dejado de tramitarse por más de un año.\nIII.- Cualesquiera otros expedientes concluídos que conforme a la ley, deban formarse por las autoridades judiciales y cuya remisión o entrega no haya de hacerse a oficina determinada o a los particulares interesados respectivamente.\nIV.- Los demás documentos que las leyes y reglamentos determinen.\nV.- La documentación que remita el Consejo de la Judicatura.\nVI.- En su caso, los expedientes concluidos que remita el Tribunal de Justicia\nElectoral del Estado.\nArtículo Reformado\nARTICULO 184.- Por ningún motivo se extraerá expediente alguno del Archivo\nJudicial, a no ser por orden escrita de la autoridad que lo haya remitido a la oficina, de quien legalmente la substituya, o de cualquiera otra que tenga competencia, insertando en el oficio relativo la determinación que motiva el pedimento, llevándose un riguroso control de entrada y salida de los expedientes por persona legalmente autorizada para ello.\nARTICULO 185.- Solo mediante decreto se expedirá copia autorizada de los documentos o expedientes depositados en dicha oficina.\nARTICULO 186.- Después de diez años de concluído un juicio, el expediente que depositado en el archivo judicial, podrán microfilmarse o captarse por cualquier medio aportado por la tecnología, siempre que pueda ser reproducido en papel. Las reproducciones tendrán el mismo valor legal que los originales, debiendo cumplirse los requisitos siguientes:\nI.- El encargado del Archivo al efectuar la microfilmación o captación deberá certificar obran en el expediente respectivo.\nII.- Consignar, el inicio y al final de la microfilmación o captación, la fecha en que se realiza la misma.\nIII.- Realizar la microfilmación o captación por duplicado a efecto de que uno de los que garantice su indestructibilidad.\nIV.- Relacionar al anverso y al reverso de los documentos, cuando la microfilmación o captación no se haga con equipo que capte simultáneamente las dos caras de dichos documentos y estos contengan anotaciones al reverso. Se destruirán las constancias procesales y documentos originales que hayan sido captados conforme a lo dispuesto anteriormente.\nCAPITULO IX\nDEL BOLETIN JUDICIAL\nARTICULO 187.- En la Ciudad de Mexicali, se editará el \"Boletín Judicial\" que será el órgano oficial de difusión del Poder Judicial del Estado; tendrá por objeto publicar las listas de Acuerdos dictados en materia civil y de lo familiar por los correspondientes Juzgados del\nEstado, por el Tribunal Superior de Justicia y del Consejo de la Judicatura así como los\nEdictos y Avisos Judiciales a que se refiere el Capítulo V del Título Segundo, del Código de\nProcedimientos Civiles.\nARTICULO 188.- El Boletín Judicial se publicará diariamente con excepción de sábados, domingos, días de fiestas nacionales, o cuando por cualquier otra causa se suspendan las labores en el Tribunal Superior de Justicia.\nARTICULO 189.- La edición y publicación del Boletín Judicial estará a cargo del\nTribunal Superior de Justicia y su administración corresponderá al Consejo de la Judicatura.\nCAPITULO X\nDE LAS VISITAS DE INSPECCION Y EVALUACION\nARTICULO 190.- El Consejo de la Judicatura del Estado es competente para inspeccionar el funcionamiento del tribunal, sus Salas, y juzgados para supervisar las conductas de los integrantes de estos órganos, a fin de que la administración de justicia sea pronta, expedita y conforme a la ley.\nARTICULO 191.- Las funciones que en ésta ley confiere al Consejo de la Judicatura serán ejercitadas por si o por los visitadores que designe.\nLos visitadores deberán satisfacer los siguientes requisitos: ser mayor de treinta y cinco años, gozar de buena reputación, no tener condena por delito con pena privativa de libertad mayor de un año, título de licenciado en derecho, legalmente expedido y práctica profesional de cuando menos diez años; su designación se hará por el propio consejo.\nEl Consejo de la Judicatura del Estado establecerá mediante acuerdos generales, los visitados para efectos de lo que se dispone en esta ley en materia de responsabilidad. que emita el Consejo de la Judicatura del Estado. órgano jurisdiccional, de la visita de inspección que vayan a practicar a fin de que proceda a fijar el correspondiente aviso en los estrados del órgano con una anticipación mínima de cinco días, para el efecto de que las personas interesadas puedan manifestar sus quejas o denuncias.\nARTICULO 193.- Los visitadores tomando en cuenta las particularidades de cada órgano realizarán, además de lo que específicamente determine el Consejo de la Judicatura del Estado, lo siguiente:\nI.- Pedir la lista del personal para comprobar su asistencia.\nII.- Verificar que los valores estén debidamente guardados, ya sea en la caja de seguridad del órgano visitado, o en la unidad o institución que el Consejo de la Judicatura hubiere señalado.\nIII.- Comprobarán si se encuentra debidamente asegurados los instrumentos y objetos de delito.\nIV.- Revisarán los libros de Gobierno a fin de determinar si se encuentran en orden y contiene los datos requeridos.\nV.- Harán constar el número de asuntos penales y civiles que hayan ingresado al órgano visitado durante el tiempo que comprenda la visita y determinarán si los procesados que disfrutan de libertad caucional han cumplido con la obligación de presentarse en los plazos fijados, y si en algún proceso en suspenso transcurrió el término de prescripción de la acción penal.\nVI.- Examinarán los expedientes formados con motivos de las causas penales y civiles que se estime conveniente a fin de verificar que se lleven con arreglo a la ley; si las resoluciones y acuerdos han sido dictados y cumplidos oportunamente si las notificaciones y diligencias se efectuarón en los plazos legales; si los exhortos y despachos han sido diligenciados y si se han observado los términos Constitucionales. sentencia, recomendará que ésta se pronuncie a la brevedad posible. En cada uno de los expedientes revisados, se pondrá la constancia respectiva.\nVII.- De toda visita de inspección deberá levantarse acta circunstanciada en la cual se hará constar el desarrollo de la misma, las quejas o denuncias presentadas en contra de los titulares y demás servidores del órgano de que se trate, las manifestaciones que respecto de la visita o del contenido del acta, quisieran realizar los propios titulares o servidores del órgano y la firma del juez o magistrado que corresponda y la del visitador.\nConsejo de la Judicatura, a fin de que determine lo que corresponda.\nARTICULO 194.- El Consejo de la Judicatura del Estado cuando tenga conocimiento que a juicio del propio Consejo amerite inmediata inspección, podrá llevarla a cabo por sí o por el visitador que designe sin que previamente se hubiese dado el aviso a que se refiere el artículo 209 de esta ley.\nCAPITULO XI\nDE LA CONTRALORIA DEL PODER JUDICIAL\nARTICULO 195.- La Contraloría es el órgano dependiente y auxiliar del Consejo de la\nJudicatura, en cuanto a practicar auditorías y la aplicación de las disposiciones relativas al\nRegistro Patrimonial y Responsabilidades Administrativas de los Servidores Públicos del\nPoder Judicial y como tal tendrá las siguientes atribuciones:\nI.- Verificar el cumplimiento de las normas de control de las Unidades Administrativas del Poder Judicial;\nII.- Comprobar el cumplimiento, por parte de las Unidades Administrativas del Poder\nJudicial, de las obligaciones derivadas de las disposiciones en materia de planeación, presupuestación, ingresos, financiamiento, inversión, patrimonio y fondos y valores de la propiedad o al cuidado de las mismas;\nIII.- Inspeccionar y vigilar directamente que las Unidades Administrativas del Poder\nJudicial, cumplan con las normas y disposiciones en materia de registro y contabilidad, contratación y pago de personal, contratación de servicios, obra pública, adquisiciones, arrendamientos, conservación, uso, destino, afectación, enajenación y baja de bienes muebles e inmuebles, almacenes y demás activos y recursos materiales;\nIV.- Realizar auditorías a las Unidades Administrativas del Poder Judicial con el objeto de promover la eficiencia de sus procedimientos y verificar el cumplimiento de los objetivos contenidos en sus programas;\nV.- Establecer y mantener coordinación e intercambiar información y documentación con la Contaduría Mayor de Hacienda del Congreso del Estado, sobre las normas, los libros o documentos justificatorios del ingreso y del gasto;\nVI.- Recibir y Registrar las declaraciones patrimoniales que deban presentar los pertinentes de conformidad con las leyes, reglamentos y acuerdos generales que emita el\nConsejo de la Judicatura;\nVII.- Recibir del Congreso del Estado, los pliegos de observaciones y su aprobación;\nVIII.- Recibir quejas y denuncias de la ciudadanía por el incumplimiento de las obligaciones de los servidores públicos mencionados en el artículo 115 de esta Ley, y\nLas demás que determinen las leyes, los reglamentos y acuerdos generales correspondientes.\nArtículo Reformado\nARTICULO 196.- Tienen obligación de presentar declaración de situación patrimonial bajo protesta de decir verdad: Magistrados del Tribunal Superior de Justicia, Jueces, Secretarios y Actuarios, Consejeros de la Judicatura, Secretarios Generales de Acuerdos, los Titulares de las Unidades Administrativas, Visitadores, Jefes de Departamento, y todos aquellos que por acuerdo determine el Consejo de la Judicatura, en los plazos siguientes:\nI.- Dentro de los sesenta días naturales siguientes a la toma de posesión;\nII.- Dentro de los treinta días naturales siguientes a la conclusión del encargo; y\nIII.- Durante el mes de mayo de cada año deberá presentarse la declaración de situación patrimonial, acompañada de una copia de la declaración anual presentada por personas físicas para los efectos de la Ley de Impuesto Sobre la Renta, salvo que en ese mismo año se hubiese presentado la declaración a que se refiere la Fracción I.\nSi transcurrido el plazo a que hace referencia la Fracción I, no se hubiese presentado la declaración correspondiente, sin causa justificada, quedará sin efecto el nombramiento respectivo. Lo mismo ocurrirá cuando se omita la declaración contemplada en la Fracción III.\nArtículo Reformado\nCAPITULO XII\nDE LA OFICIALIA DE PARTES\nARTICULO 197.- Las Oficialías de Partes para el Tribunal Superior de Justicia y para los Juzgados de Primera Instancia y Juzgados en materia Laboral, se establecerán por acuerdo del Pleno de la Judicatura del Estado, según las necesidades de cada partido judicial.\nPárrafo Reformado\nTendrán las siguientes atribuciones:\nI.- Recibir el escrito por el cual se inicia un procedimiento, mismo que deberá turnar al\nJuzgado que corresponda, para que se avoque a su conocimiento.\nII.- Recibir los escritos posteriores al inicial, si se presentaren fuera de las horas de labores del Tribunal Superior de Justicia, Juzgados de Primera Instancia, en materia Laboral y de Paz donde los hubiere, mismos que deberán turnarse a quienes se dirijan.\nFracción Reformada\nIII.- Fuera de la capital del Estado recibir promociones que deben presentarse al hábiles siguientes a su presentación.\nIV.- Las que para el mejor desempeño de la administración de justicia le señalare el\nConsejo de la Judicatura.\nArtículo Reformado\nCAPÍTULO XIII\nDEL CENTRO ESTATAL DE JUSTICIA ALTERNATIVA\nARTÍCULO 197 BIS.- El Centro Estatal de Justicia Alternativa será el órgano auxiliar del Consejo de la Judicatura del Estado, que tendrá a su cargo la prestación de los siguientes servicios:\nI.- Instrumentar y operar servicios de mediación y conciliación extrajudicial, en los asuntos susceptibles de transacción cuyo conocimiento está encomendado por la Ley a los tribunales del Poder Judicial del Estado, y en materia penal tramitar los mecanismos de mediación, conciliación y de junta restaurativa en los términos que señala el Código Nacional de Procedimientos Penales y la Ley Nacional de Mecanismos Alternativas de Solución de\nControversias Penales;\nII.- Substanciar procedimientos de mediación y conciliación que pongan fin a las controversias judiciales, a petición expresa de parte interesada en los términos de la Ley de la materia;\nIII.- Promover la mediación y la conciliación como alternativas de prevención y solución de controversias, y\nIV.- Instrumentar y substanciar procedimientos de conciliación respecto de controversias que se encuentren planteadas ante los Tribunales Laborales del Poder Judicial del Estado, siempre y cuando, siendo viables de resolverse en dicha vía alterna, así lo soliciten las partes.\nFracción Adicionada\nV.- Las demás que establezcan los ordenamientos legales.\nFracción Recorrida\nSalvo en la materia penal, los servicios a que aluden las fracciones anteriores también la Ley de la materia.\nArtículo Reformado\nARTÍCULO 197 BIS-1.- El Centro Estatal de Justicia Alternativa estará a cargo de un\nDirector, y funcionará en los términos que determine el Consejo de la Judicatura del Estado de conformidad con la Ley de la materia.\nCAPÍTULO XIV\nDE LA ADMINISTRACIÓN JUDICIAL\nARTICULO 197 BIS-2.- El administrador judicial estará adscrito a la Presidencia del\nConsejo de la Judicatura y ejercerá las siguientes facultades:\nI.- Dirigir las labores administrativas, para que las audiencias que presidan los Jueces de Control; Jueces de Control para Adolescentes; los Tribunales Unitarios de Enjuiciamiento y los Jueces de Ejecución se desarrollen adecuadamente.\nII.- Realizar las actividades administrativas que sean necesarias, para la buena marcha del despacho y las audiencias que presidan los Jueces de Control; Jueces de\nControl para Adolescentes; los Tribunales Unitarios de Enjuiciamiento y los Jueces de\nEjecución.\nIII.- Supervisar las funciones del personal que tenga adscrito y a su cargo y evaluar su desempeño.\nIV.- Distribuir el despacho judicial y las audiencias a los Jueces de Control; Jueces de\nControl para Adolescentes; Tribunales Unitarios de Enjuiciamiento y Jueces de Ejecución, cuando proceda, conforme a un procedimiento objetivo, aleatorio y general, procurando una correcta programación de las audiencias de acuerdo al sistema informático.\nV.- Establecer el orden de guardias de los Jueces de Control y los Jueces de Control para Adolescentes.\nVI.- Verificar que se cumpla con el abastecimiento de material de trabajo a las áreas de su competencia, de conformidad a lo requerido mensualmente por el Juez coordinador de los Jueces de Control.\nVII.- Implementar y dar cumplimiento a las políticas y directrices generales que dicte el\nPresidente del Consejo de la Judicatura, en materia de selección de personal, evaluación, administración de recursos materiales y humanos, de diseño y análisis de información estadística y demás,\nVIII.- Informar las necesidades presupuestarias anuales y turnarlas a la unidad administrativa del Consejo de la Judicatura.\nIX.- Dar cuenta semestralmente al Presidente del Consejo de la Judicatura, del estado que guarda la gestión administrativa del nuevo sistema de justicia penal.\nX.- Tener bajo su custodia las salas de audiencia, así como los bienes asignados a las mismas, debiendo poner de inmediato en conocimiento del Presidente del Consejo, cualquier deterioro que sufran.\nXI.- Custodiar los bienes y valores que se encuentren a disposición de los Jueces de\nControl; Jueces de Control para Adolescentes y de los Tribunales Unitarios de\nEnjuiciamiento con motivo de la tramitación de los asuntos sometidos a su conocimiento.\nXII.- Entregar y recibir bajo inventario los bienes y valores a que se refieren las\nXIII.- Asignar, conforme a las disposiciones que expida el Presidente del Consejo de la Judicatura, a uno o varios Jueces de Control y Jueces de Control para adolescentes a las unidades judiciales donde deban ejercer su jurisdicción.\nXIV.- Convocar a las partes para que concurran a audiencia en aquellos casos en que necesaria una valoración judicial previa, respecto a la necesidad de celebrarla;\nXV.- Las demás que determinen las disposiciones legales.\nArtículo Reformado\nARTICULO 197 BIS-3.- Podrá contarse con más de un administrador judicial, cuando lo justifique la necesidad de prestar un adecuado apoyo a los Jueces de Control y a los\nTribunales Unitarios de Enjuiciamiento y se cuente con la disponibilidad presupuestal.\nEl Consejo de la Judicatura determinará la adscripción del administrador judicial o administradores judiciales.\nArtículo Reformado\nARTÍCULO 197 BIS-4.- Para ser administrador judicial se requiere:\nI.- Ser mexicano en pleno ejercicio de sus derechos civiles y políticos;\nII.- Tener edad mínima de treinta y cinco años;\nIII.- Tener título profesional de Licenciatura en Derecho, Sistemas Computacionales, Administración, Ingeniero Industrial o carrera afín;\nFracción Reformada\nIV.- Tener un mínimo de ocho años de experiencia profesional dentro de los cuales tres con experiencia en nivel de dirección o gerencial en instituciones públicas o empresas privadas, respectivamente;\nV.- Tener residencia mínima de cinco años en el Estado, anteriores al día de su nombramiento, y\nVI.- Gozar de buena reputación y no haber sido condenado por delito intencional que amerite pena corporal de más de un año de prisión, pero si se trata de robo, fraude, falsificación, abuso de confianza u otro que lesione la buena fama en el concepto público, lo inhabilitará para el cargo cualquiera que haya sido la pena.\nArtículo Reformado\nARTICULO 197 BIS-5.- El administrador judicial será considerado para efectos atribuciones, en particular de apoyo a los Jueces de Control y Tribunales Unitarios de\nEnjuiciamiento.\nArtículo Reformado\nCAPÍTULO XIV\nDenominación Modificada\nARTÍCULO 197 TER.- Los Centros de Convivencia Familiar Supervisada son órganos operativa, que tiene por objeto facilitar la convivencia paterno filial en aquellos casos que, a juicio de las personas titulares de los Juzgados de lo Familiar y de los Juzgados\nEspecializados en Violencia Familiar Contra las Mujeres, ésta no puede realizarse de manera libre o se ponga en riesgo el interés superior del menor; así como realizar los dictámenes y evaluaciones psicosociales que le sean requeridos por los órganos jurisdiccionales antes mencionados, pudiendo emitirlas recomendaciones que considere necesarias para proteger y garantizar el goce de los derechos humanos de sus evaluados.\nPárrafo Reformado\nLos servicios de los Centros de Convivencia Familiar Supervisada, se otorgarán de forma gratuita en sus instalaciones o en aquellas que se designen para tales efectos.\nLos Centros de Convivencia Familiar Supervisada propios del Poder Judicial serán administrados y vigilados por el Consejo de la Judicatura de Baja California, el cual expedirá las bases para su organización y funcionamiento, incluyendo aquellos que por diversas asociaciones o patronatos presten sus instalaciones para tales efectos.\nLos Centros de Convivencia Familiar Supervisada contarán con un Titular y el personal necesario para el cumplimiento de sus funciones, ya sea propio del Poder Judicial o aquellos que éste acreditaré para tales efectos. Deberá igualmente, contar con Secretarios\nAuxiliares que sean necesarios para dar fe de actos.\nPara ser Titular del Centro de Convivencia Familiar Supervisada se deberán reunir los requisitos señalados por las fracciones I, III, IV y V del artículo 65 de esta Ley, además deberá poseer título con antigüedad de cinco años a nivel licenciatura en: Pedagogía, Psicología, Sociología, Trabajo Social o su equivalente, y acreditar la experiencia y capacidad indispensables para el desempeño del cargo.\nArtículo Reformado\nTITULO DECIMOSEGUNDO\nDE LA CARRERA JUDICIAL EN LA ADMINISTRACION\nDE JUSTICIA\nCAPITULO I\nDE LAS DESIGNACIONES\nARTICULO 198.- El ingreso y la promoción de los Servidores Públicos de carácter a que se refiere el presente Título, la cual se regirá por los principios de excelencia, profesionalismo, objetividad, imparcialidad, independencia y antigüedad, en su caso.\nARTICULO 199.- La Carrera Judicial está integrada por las siguientes categorías:\nI.- Magistrado.\nII.- Juez.\nIII.- Secretario General de Acuerdos del Tribunal Superior de Justicia.\nIV.- Secretario Auxiliar del Tribunal Superior de Justicia.\nV.- Secretario de Estudio y Cuenta adscrito a cada Magistrado que integre Sala.\nVI.- Secretario de Acuerdos y Secretario instructor.\nFracción Reformada\nVII.- Actuarios y Notificadores del Poder Judicial del Estado.\nArtículo Reformado\nARTICULO 200.- El Consejo de la Judicatura del Estado establecerá, de acuerdo con su presupuesto y mediante disposiciones generales, un sistema de estímulos para aquellas personas comprendidas en las categorías señaladas en el artículo anterior. Dicho sistema podrá incluir estímulos económicos y tomará en cuenta el desempeño en el ejercicio de su función, los cursos realizados dentro del Instituto de la Judicatura, la antigüedad, grado académico, arraigo y los demás que el propio Consejo estime necesarios.\nCAPITULO II\nDEL INGRESO PROMOCION Y ASCENSO\nARTICULO 201.- Las designaciones que deban hacerse en la Categoría de\nMagistrado deberán ser cubiertas mediante concurso de mérito y previa convocatoria pública hecha por una vez en el Boletín Judicial y en uno de los periódicos de mayor circulación en que se contengan las bases que el Consejo de la Judicatura fije, la de Juez por oposición.\nPrevia a la designación de magistrados el Consejo de la Judicatura deberá escuchar la opinión de las agrupaciones profesionales de abogados de esta Entidad que se encuentren registrados en el Departamento de Profesiones del Estado, así como de las\nFacultades y Escuelas de Derecho de la Entidad.\n216 de esta ley, se hará mediante examen de aptitud que realice el Consejo de la\nJudicatura.\nEl Consejo de la Judicatura tendrá la facultad de obtener y verificar, en todo momento, la información que los aspirantes le hubieren proporcionado.\nARTICULO 202.- Los concursos para el ingreso a la categoría de Juez, Secretario y\nActuario, se sujetarán al siguiente procedimiento:\nI.- El Consejo de la Judicatura del Estado emitirá una convocatoria que deberá ser\nEntidad. En la convocatoria, se deberá especificar que el concurso se trata de oposición.\nLa convocatoria señalará las categorías y número de vacantes sujetas a concurso, el lugar, día y hora en que se llevarán a cabo los exámenes, lugar de inscripción y plazo que se correspondiente y demás elementos que estime necesarios.\nII.- Los aspirantes para las categorías a que se refiere el párrafo primero de este artículo deberán resolver por escrito un cuestionario cuyo contenido versará sobre materias que se relacionen con la función de la plaza para la que se concursa.\nIII.- Al llevar a cabo su evaluación, el jurado del Consejo de la Judicatura tomará en consideración los cursos que haya realizado el sustentante en la antigüedad en el Poder\nJudicial, o en el desempeño libre de la profesión el grado académico, su prestigio profesional y los cursos de actualización y especialización que haya acreditado, en términos del reglamento.\nARTICULO 203.- La celebración y organización de los exámenes de oposición a que se refiere el artículo anterior se sujetarán a las disposiciones que el Consejo de la Judicatura fije en el reglamento respectivo.\nARTICULO 204.- El jurado encargado de los concursos de oposición se integrará por tres elementos:\nI.- Un Consejero del Consejo de la Judicatura del Estado, quien lo presidirá.\nII.- Un Consejero del Consejo de la Judicatura quien hará las veces de Secretario.\nIII.- Un Magistrado del Tribunal Superior de Justicia que determine el Pleno del mismo.\nPor cada miembro titular se nombrará un suplente designado en los términos que señale el reglamento correspondiente.\nCAPITULO III\nDE LA ADSCRIPCION Y RATIFICACION\nARTICULO 205.- Corresponde al Pleno del Consejo de la Judicatura del Estado, Artículo Reformado\nARTICULO 206.- En aquellos casos en que para la primera adscripción de Jueces, Secretarios y Actuarios haya varias plazas vacantes, el Consejo de la Judicatura del Estado, tomar en consideración, de conformidad con el acuerdo respectivo los siguientes elementos:\nI.- La calificación obtenida en el concurso de oposición.\nII.- Los cursos que haya realizado en el Instituto de la Judicatura.\nV.- El grado académico que comprende el nivel de estudios con que cuente el de manera fehaciente.\nARTICULO 207.- Para la ratificación y reelección de Magistrados y Jueces, a que se\nJudicatura, tomará en consideración, de conformidad con el reglamento respectivo, los siguientes elementos:\nI.- El desempeño que haya tenido en el ejercicio de su función.\nII.- Los resultados de las visitas de inspección.\nIII.- En el grado académico que comprende el nivel de estudios con que cuente el servidor público así como los diversos cursos de actualización y especialización acreditados de manera fehaciente.\nIV.- No haber sido sancionado por falta grave, con motivo de una queja de carácter administrativa.\nArtículo Reformado\nTITULO DECIMOTERCERO\nDE LOS AUXILIARES DE LA ADMINISTRACION DE JUSTICIA\nCAPITULO I\nDEL SERVICIO MEDICO FORENSE\nARTÍCULO 208.- El Servicio Médico Forense para la Administración de Justicia del\nEstado, será desempeñado por los médicos de hospitales, por los médicos municipales, por los de centros de Readaptación Social y por peritos médicos legistas.\nArtículo Reformado\nARTÍCULO 209.- Son obligaciones de los médicos de hospital:\nI.- Reconocer a los lesionados y enfermos que se reciban en el establecimiento y encargarse de la curación de ellos, expidiendo sin demora cuando proceda, los certificados correspondientes.\nII.- Extender los certificados de clasificación de lesiones.\nIII.- Practicar la autopsia de los cadáveres de las personas que, hallándose a disposición de las autoridades judiciales, fallezcan en el hospital y extender el Certificado respectivo, expresando con toda exactitud cual haya sido la causa de la muerte, poniendo en todo la mayor atención y escrupulosidad a fin de facilitar las averiguaciones.\nIV.- Rendir con toda oportunidad los informes que les pidan los Tribunales.\nV.- Las demás que les encomienden las leyes.\nArtículo Reformado\nARTÍCULO 210.- Los médicos municipales estarán a las órdenes inmediatas del delegado o agente del Ministerio Público a que se les adscriba, pero deberán rendir todos los informes que les pidan los jueces del ramo penal, en lo relativo al servicio que en cada caso hayan desempeñado.\nArtículo Reformado\nARTÍCULO 211.- Son obligaciones de los médicos municipales:\nI.- Proceder con oportunidad al reconocimiento y curación de los heridos que se reciban en la sección médica que esté a su cargo.\nII.- Asistir a las diligencias de fe de cadáveres y a todas las otras que a juicio de\nMinisterio Público que sean necesarias o útiles sus servicios.\nIII.- Redactar el parte médico legal, las actas de descripción de lesiones o heridas que se extiendan en las delegaciones o agencias del Ministerio Público y expedir las certificaciones médico legales conducentes a la comprobación del delito.\nIV.- Recoger y entregar al Ministerio Público los objetos y sustancias que puedan servir para el esclarecimiento del hecho de que se trate e indicar las precauciones con que deban ser guardados o remitidos a quien corresponda.\nV.- Describir exactamente en los certificados de lesiones, las alteraciones que hubieren sido necesario hacer con motivo de la curación.\nVI.- Hacer en el certificado de lesiones la clasificación provisional o definitiva de ellas.\nVII.- Las demás que le correspondan según las leyes o reglamentos.\nArtículo Reformado\nARTÍCULO 212.- Los médicos de los centros de readaptación social deberán asistir a correspondientes; proporcionarán los primeros auxilios en los casos de lesiones que ocurran en la prisión e intervendrán en cualquier diligencia judicial que ahí se practique, cuando para ello fueren requeridos por los Jueces o por el Ministerio Público.\nArtículo Reformado\nARTÍCULO 213.- Habrá cuando menos cuatro peritos médicos legistas por cada uno de los partidos judiciales de Mexicali y Tijuana, y dos para los de Ensenada y Tecate, los cuales dependerán administrativamente del Consejo de la Judicatura del Estado.\nArtículo Reformado\nARTÍCULO 214.- El Consejo de la Judicatura del Estado tendrá las siguientes atribuciones:\nI.- Cuidar de que el Servicio Médico Forense se desempeñe eficaz y cumplidamente en todo el Estado.\nII.- Distribuir el trabajo en forma equitativa.\nIII.- Convocar a junta, cuando lo estime pertinente, a los peritos médicos con objeto de estudiar los casos graves.\nIV.- Girar las instrucciones necesarias para el desempeño de los trabajos encomendados a cada uno.\nV.- Las demás que fijen las leyes y reglamentos respectivos.\nArtículo Reformado\nARTÍCULO 215.- Para desempeñar el cargo de perito médico legista se requiere:\nI.- Ser mexicano, en ejercicio de los derechos civiles y políticos.\nII.- No tener más de sesenta y cinco años de edad, ni menos de veinticinco el día de su designación.\nIII.- Tener título de Médico Cirujano expedido por autoridad o corporación debidamente facultado para ello y registrada ante autoridad competente.\nIV.- Poseer los conocimientos necesarios en la materia.\nV.- No haber sido sentenciado por delito intencional.\nArtículo Reformado\nARTÍCULO 216.- Los peritos médicos legistas serán nombrados por el Consejo de la iguales.\nArtículo Reformado\nARTÍCULO 217.- Son obligaciones de los médicos legistas:\nI.- Reconocer a los heridos expidiendo sin demora cuando proceda los certificados correspondientes.\nII.- Extender los certificados de clasificación definitiva de lesiones que les soliciten las autoridades.\nIII.- Practicar la autopsia de personas que se hallen a disposición de las autoridades judiciales cuando el fallecimiento ocurra en lugar distinto al hospital, extendiendo el certificado respectivo, en el que expresarán con toda exactitud la causa de la muerte.\nIV.- Rendir los informes que les soliciten los tribunales, con la debida oportunidad, dictámenes respectivos.\nV.- Calzar con su firma y nombre completo, los certificados y constancias que expidan.\nVI.- Las demás que les encomienden las leyes.\nArtículo Reformado\nCAPITULO II\nDE LOS SINDICOS DE CONCURSO\nARTICULO 218.- Los Síndicos de Concurso, serán designados por los jueces de lo civil en los términos establecidos por el Código de Procedimientos Civiles, dentro de las personas comprendidas en la lista que para tal efecto será enviada por el Consejo de la\nJudicatura.\nARTICULO 219.- La lista a que se refiere el artículo anterior, será resultado de una selección que el Consejo de la Judicatura del Estado en Pleno o en comisión llevará a cabo entre los aspirantes a las sindicaturas.\nARTICULO 220.- Para ser Síndico se requiere:\nI.- Ser mexicano en pleno uso y goce de todos sus derechos.\nII.- Tener título de licenciado en derecho debidamente registrado.\nIII.- Acreditar cuando menos dos años en el ejercicio de la profesión.\nIV.- Ser de notoria honradez y no haber sido condenado por delito intencional.\nV.- No encontrarse comprendido dentro de los casos previstos por el artículo 17 de esta ley.\nArtículo Reformado\nCAPITULO III\nDE LOS INTERVENTORES DE CONCURSO\nARTICULO 221.- Los interventores de concurso, al igual que los síndicos, desempeñan una función pública y quedan sujetos a las determinaciones de esta ley, sin perjuicio de las demás disposiciones relativas.\nARTICULO 222.- Los interventores serán nombrados por los acreedores, en cualquier tiempo, por mayoría de votos en términos del Código de Procedimientos Civiles, de la lista\nEstado.\nARTICULO 223.- Las atribuciones del interventor serán:\nI.- Exigir mensualmente la presentación de las cuentas de administración del síndico al juez, dentro de los cinco primeros días de cada mes.\nII.- Vigilar la conducta del síndico, dando cuentas al juez de las irregularidades que notare y de todos los actos que pudieran afectar a los intereses y derechos de la masa.\nARTICULO 224.- Serán causas de la remoción del interventor, no prestar vigilancia necesaria a todos los casos que están encomendados al síndico, y dar aviso al juez de las faltas u omisiones en que éste hubiere incurrido sin perjuicio de las penas y responsabilidades a que se hubiere hecho acreedor.\nCAPITULO IV\nDE LOS ALBACEAS, TUTORES Y CURADORES\nARTICULO 225.- Los albaceas, tutores y curadores, ya sean provisionales o definitivos, designados por los jueces del Estado, deberán llenar todos los requisitos establecidos en este título para los síndicos e interventores, en aquello que sea compatible con su carácter y función, del mismo modo, los depositarios y en particular a todos aquellos que actúen en los juicios como auxiliares, por ese sólo hecho les serán aplicables las reglas establecidas especialmente en éste título y en todas las demás de la presente Ley en lo que fuere compatible para los efectos de su designación de sus atribuciones y responsabilidades.\nCAPITULO V\nDE LOS NOTARIOS\nARTICULO 226.- En los casos en que conforme al artículo 68 del Código de\nProcedimientos Civiles, los litigantes designen a un notario que desempeñe las funciones de secretario, estará éste obligado a cumplir con todas las disposiciones que esta ley prescribe para dichos funcionarios únicamente en relación con el negocio en que intervenga y sujeto a las sanciones establecidas en el Capítulo de Responsabilidades, por las faltas o delitos oficiales en que incurra en el desempeño del cargo. En la inteligencia en que no es preciso desahoguen y dicten diligencias, acuerdos y resoluciones en dicho negocio.\nCAPITULO VI\nDE LOS PERITOS\nARTICULO 227.- El peritaje en los asuntos que se presenten ante las Autoridades\nJudiciales del Estado es una función pública y en esa virtud, los profesionales, los técnicos simplemente prácticos en cualquier materia científica, arte y oficio, están obligados en forma gratuita a rendir el dictamen que se les solicite. su nombramiento de auxiliar a la administración de justicia.\nARTICULO 228.- Para ser perito se requiere: ser ciudadano mexicano, tener antecedentes de honestidad, conocimiento en la ciencia, arte u oficio sobre lo que vaya a versar el peritaje.\nARTICULO 229.- Los peritaje que deban versar sobre materia relativas a profesiones, deberán encomendarse a personas autorizadas con título, si no fuere posible encontrarlas en la localidad de que se trate o las que estuvieren impedidas para ejercer el cargo, podrán designarse prácticos en la materia sobre la que vaya versar dicho peritaje.\nARTICULO 230.- Solo en casos precisos cuando no hubiere en la localidad ciudadanos mexicanos suficientemente idóneos para el peritaje respectivo, podrá dispensarse el requisito de nacionalidad, pero las personas que se designen, al protestar cumplir su encargo, deberán someterse expresamente a las leyes mexicanas, para todos los efectos legales del peritaje que vayan a desempeñar.\nARTICULO 231.- En los asuntos de orden penal cuando no estuvieren designados especialmente por la ley los individuos que deban ejercer las funciones de que se trata, se ocurrirá de preferencia a los profesores del ramo en las escuelas públicas, ya sean primarias, superiores o profesionales, o a los funcionarios y empleados de carácter técnico en los establecimientos o corporaciones dependientes del Gobierno del Estado, contadores, ingenieros, militares de servicio en la plaza, armeros, ensayadores, mecánicos de taller y oficiales y demás especialidades que desempeñen cargos públicos.\nARTICULO 232.- En los asuntos de orden civil, el Consejo de la Judicatura del Estado formará anualmente, en el mes de enero, una lista de las diversas personas que puedan ejercer las funciones de que se trata, según los diversos ramos del conocimiento humano, de los cuales deberán designar las autoridades judiciales, a aquellas personas que pueden desempeñar el cargo respectivo, y solo en caso de que no existiera lista de peritos, o que los listados estuvieren impedidos para ejercer el cargo, los jueces podrán nombrarlos libremente.\nARTICULO 233.- Los Peritos Intérpretes están obligados a traducir clara y fielmente los interrogatorios, declaraciones, actuaciones, resoluciones y documentos que al efecto se les encomienden, guardando en todo caso el secreto debido.\nARTICULO 234.- En los asuntos civiles o penales, las partes interesadas podran nombrar libremente los peritos que les convengan.\nARTICULO 235.- Los honorarios de los peritos designados por el juez, sin solicitud de ninguno de los interesados, de acuerdo con las disposiciones del Código de Procedimientos\nCiviles, serán cubiertos por ambas partes por mitad, sin perjuicio de lo que disponga la sentencia definitiva respecto a la condenación de costas.\nARTICULO 236.- Siempre que alguna persona no hable el idioma español y tenga que ser examinado en juicio civil o criminal, se le proveerá de interprete en los términos del\nCódigo de Procedimientos Civiles y Penales.\nCAPITULO VII\nDE LOS PRESTADORES DEL SERVICIO SOCIAL\nADSCRITOS AL PODER JUDICIAL\nARTICULO 237.- Se entiende por prestador del servicio social, el estudiante o egresado de las Instituciones de Enseñanza Superior que con ese carácter sean asignadas al Poder Judicial para la prestación de sus servicios social obligatorio, en base a los lineamientos legales e internos de dichas instituciones y previa suscripción del convenio respectivo con el Consejo de la Judicatura del Estado.\nARTICULO 238.- Los prestadores del servicio social, adscritos a las diversas dependencias del Poder Judicial, estarán a cargo del Secretario General del Consejo de la\nJudicatura del Estado, quien les ordenará, vigilará y asignará sus actividades, conforme a los programas que para el efecto se elaboren.\nARTICULO 239.- El Presidente del Consejo de la Judicatura del Estado, firmará los convenios necesarios con las Instituciones Educativas, a fin de que se asignen prestadores de servicio social de diferentes disciplinas a los programas que previamente sean elaborados en función a las necesidades del Tribunal, Consejo de la Judicatura y Juzgados de Primera Instancia, Mixtos y de Paz.\nARTICULO 240.- Los estudiantes de las Instituciones de Educación superior, prestarán el servicio social con carácter temporal.\nARTICULO 241.- El Consejo de la Judicatura del Estado dictará las medidas áreas de competencia, en base al Reglamento Interior de Prestadores de Servicio Social, ARTICULO 242.- Los prestadores del servicio social desempeñarán función de servicio.\nARTICULO 243.- Los encargados de cada programa elaborarán reportes mensuales prestación, a través de los informes necesarios.\nTITULO DECIMO CUARTO\nDEL TRIBUNAL ELECTRONICO\nDenominación Modificada\nCAPITULO UNICO\nARTICULO 244.- El Tribunal electrónico es el sistema integral de procesamiento de información, de forma electrónica o digital que permita la substanciación de asuntos jurisdiccionales ante el Poder Judicial del Estado, de conformidad con las leyes aplicables de la materia, así como con el Reglamento que para tales efectos expida el Pleno del Consejo de la Judicatura.\nEl objeto del Tribunal Electrónico es constituirse en una herramienta tecnológica que contribuya a que la impartición de justicia se preste con mayor celeridad, eficacia, eficiencia, seguridad y transparencia en beneficio de los justiciables.\nArtículo Reformado\nARTICULO 245.- El sistema del Tribunal Electrónico tendrá como principales funciones, las siguientes:\nI.- La formación y utilización del expediente electrónico en los procesos jurisdiccionales;\nII.- Facilitar la consulta vía internet de los expedientes electrónicos;\nIII.- La recepción electrónica de promociones y documentos en los procesos jurisdiccionales;\nIV.- Efectuar notificaciones electrónicas dentro de los procesos jurisdiccionales;\nV.- Fungir como medio procesal e institucional entre las Autoridades jurisdiccionales.\nArtículo Reformado\nARTICULO 246.- Derogado.\nArtículo Derogado\nCAPITULO II\nDE SU INTEGRACION, FUNCIONAMIENTO Y ATRIBUCIONES\nARTICULO 247.- Derogado.\nArtículo Derogado\nARTICULO 248.- Derogado.\nArtículo Derogado\nSECCIÓN PRIMERA\nDEL PLENO\nARTICULO 249.- Derogado.\nArtículo Derogado\nARTICULO 250.- Derogado.\nArtículo Derogado\nARTICULO 251.- Derogado.\nArtículo Derogado\nSECCIÓN SEGUNDA\nDE LAS SALAS\nARTÍCULO 251 BIS.- Derogado.\nArtículo Derogado\nARTÍCULO 251 TER.- Derogado.\nArtículo Derogado\nARTÍCULO 251 QUATER.- Derogado.\nArtículo Derogado\nARTÍCULO 251 QUINQUES.- Derogado.\nArtículo Derogado\nARTÍCULO 251 SEXIES.- Derogado.\nArtículo Derogado\nARTÍCULO 251 SEPTIES.- Derogado.\nArtículo Derogado\nCAPITULO III\nDEL PRESIDENTE DEL TRIBUNAL DE JUSTICIA\nELECTORAL Y SUS ATRIBUCIONES\nARTICULO 252.- Derogado.\nArtículo Derogado\nARTICULO 253.- Derogado.\nArtículo Derogado\nCAPITULO IV\nDE LOS MAGISTRADOS ELECTORALES\nY SUS ATRIBUCIONES\nARTICULO 254.- Derogado.\nArtículo Derogado\nARTICULO 255.- Derogado.\nArtículo Derogado\nARTICULO 256.- Derogado.\nArtículo Derogado\nARTICULO 257.- Derogado.\nArtículo Derogado\nCAPITULO V\nDEL SECRETARIO GENERAL DEL TRIBUNAL DE JUSTICIA\nELECTORAL Y SUS ATRIBUCIONES.\nARTICULO 258.- Derogado.\nArtículo Derogado\nCAPITULO VI\nDE LA COMISION DE ADMINISTRACION, INTEGRACION,\nFUNCIONAMIENTO Y ATRIBUCIONES\nARTICULO 259.- Derogado.\nArtículo Derogado\nARTICULO 260.- Derogado.\nArtículo Derogado\nARTICULO 261.- Derogado.\nArtículo Derogado\nARTICULO 262.- Derogado.\nArtículo Derogado\nARTICULO 263.- Derogado.\nArtículo Derogado\nCAPITULO VII\nJUSTICIA ELECTORAL Y SUS ATRIBUCIONES\nARTICULO 264.- Derogado.\nArtículo Derogado\nCAPITULO VIII\nDE LA FISCALIZACION DEL TRIBUNAL DE JUSTICIA\nARTICULO 265.- Derogado.\nArtículo Derogado\nARTICULO 266.- Derogado.\nArtículo Derogado\nCAPITULO IX\nDE LOS REQUISITOS PARA OCUPAR CARGOS EN EL\nTRIBUNAL DE JUSTICIA ELECTORAL\nARTICULO 267.- Derogado.\nArtículo Derogado\nARTICULO 268.- Derogado.\nArtículo Derogado\nARTICULO 269.- Derogado.\nArtículo Derogado\nARTICULO 270.- Derogado.\nArtículo Derogado\nARTICULO 271.- Derogado.\nArtículo Derogado\nARTICULO 272.- Derogado.\nArtículo Derogado\nCAPITULO X\nDE LAS RESPONSABILIDADES, IMPEDIMENTOS\nY EXCUSAS\nARTICULO 273.- Derogado.\nArtículo Derogado\nARTICULO 274.- Derogado.\nArtículo Derogado\nCAPITULO XI\nDE LAS RELACIONES DE TRABAJO DE LOS\nSERVIDORES PUBLICOS\nARTICULO 275.- Derogado.\nArtículo Derogado\nARTICULO 276.- Derogado.\nArtículo Derogado\nARTICULO 277.- Derogado.\nArtículo Derogado\nCAPITULO XII\nDE LAS RENUNCIAS, AUSENCIAS Y LICENCIAS\nARTICULO 278.- Derogado.\nArtículo Derogado\nARTÍCULO 279.- Derogado.\nArtículo Derogado\nARTICULO 280.- Derogado.\nArtículo Derogado\nARTICULO 281.- Derogado.\nArtículo Derogado\nARTÍCULO 282.- Derogado.\nArtículo Derogado\nARTÍCULO 283.- Derogado.\nArtículo Derogado\nARTICULO 284.- Derogado.\nArtículo Derogado\nARTÍCULO 285.- Derogado.\nArtículo Derogado\nARTÍCULO 286.- Derogado.\nArtículo Derogado\nCAPITULO XIII\nDEL ARCHIVO JURISDICCIONAL\nARTÍCULO 287.- Derogado.\nArtículo Derogado\nARTÍCULO 288.- Derogado.\nArtículo Derogado\nCAPITULO XIV\nDE LOS CRITERIOS OBLIGATORIOS\nARTÍCULO 289.- Derogado.\nArtículo Derogado\nCAPITULO XV\nDE LA PROTESTA CONSTITUCIONAL\nARTÍCULO 290.- Derogado.\nArtículo Derogado\nCAPITULO XVI\nDE LOS SERVIDORES DEL TRIBUNAL DE JUSTICIA ELECTORAL\nDEL PODER JUDICIAL DEL ESTADO\nARTICULO 291.- Derogado.\nArtículo Derogado\nARTICULO 292.- Derogado.\nArtículo Derogado\nTÍTULO DÉCIMO QUINTO\nTítulo Adicionado\nCAPÍTULO ÚNICO\nDEL HABER DE RETIRO\nCapítulo Adicionado\nARTÍCULO 293.- Al retirarse del cargo los Magistrados Numerarios tendrán derecho a un haber de retiro, el cual tendrá carácter intransferible, en ningún caso y bajo ninguna circunstancia, podrá exceder del término de siete años contados a partir del día siguiente al último día en que hayan fungido, mismo que no será mayor al salario establecido para el cargo de juez de primera instancia, y que no podrá incrementarse más allá de los términos inflacionarios. El Consejo de la Judicatura, expedirá el Reglamento del haber de retiro, donde se determine el esquema, cuantía, temporalidad y condiciones para su entrega, el cual deberá ser aprobado por las dos terceras partes de sus integrantes.\nEn el Reglamento de Haber de Retiro, deberá contemplarse un Fondo para el otorgamiento de este, en el que, mediante estudios de índole actuarial contable, a solicitud y aportaciones económicas por parte de los magistrados para cubrir el Haber de Retiro. manera voluntaria. Tendrán derecho a un haber por retiro en forma proporcional al tiempo en que ejercieron sus funciones en términos del reglamento respectivo.\nEl Magistrado que haya sido removido de su cargo, en términos de lo dispuesto por el de Baja California, no tendrá derecho al haber por retiro.\nArtículo Adicionado\nARTÍCULO 294.- Las y los Jueces del Poder Judicial al retirarse del cargo tendrán derecho a recibir una prestación periódica y temporal que garantice su independencia y autonomía en la función judicial, el cual tendrá carácter de intransferible en vida, y será equivalente por lo menos al cincuenta por ciento de la remuneración que perciban las y los jueces en activo, por un periodo máximo de nueve años, contados a partir del día siguiente al de la fecha de su retiro. Las y los jueces tendrán derecho a esta remuneración cuando se retiren del cargo con motivo de alguno de los siguientes supuestos:\nI.- Haber cumplido los setenta años de edad; ll.- Haber desempeñado el cargo por un periodo de por lo menos quince años en el ejercicio del cargo; o, Ill.- Que les haya sobrevenido una incapacidad física o mental que les impida continuar en el desempeño de su función.\nLas y los jueces que soliciten su retiro voluntario, antes de haber cumplido quince años en el ejercicio del cargo o bien que no hubieren sido ratificados en el mismo conforme accederán a la prestación a que hace referencia este artículo, por el plazo proporcional que corresponda a sus aportaciones, en los términos que disponga el reglamento respectivo.\nLas y los jueces que hayan sido removidos de su cargo, en términos de lo dispuesto\nSoberano de Baja California o por resolución judicial, no tendrán derecho a la prestación regulada en el presente artículo, sin embargo, podrán solicitar la devolución de las aportaciones que hubieren efectuado durante el ejercicio de su función; exceptuando las cantidades destinadas a la administración del fondo correspondiente. prestación regulada en el presente artículo, donde se determinen los conceptos, esquemas, cuantía, términos y condiciones para su entrega o transferencia a beneficiarios, el cual deberá ser aprobado por las dos terceras partes de sus integrantes.\nEl Reglamento deberá contemplar la creación de un fondo en el que, mediante estudios de índole actuarial, se establezcan los plazos y montos de aportaciones económicas que les corresponden a las y los Jueces, así como los esquemas de lineamientos que sean necesarios para garantizar el otorgamiento de esta prestación.\nArtículo Adicionado\nSentencia de Controversia Constitucional 35/2020\nArtículo Reformado\nPRIMERO.- La presente Ley, entrará en vigor al día siguiente de su publicación, en el\nPeriódico Oficial del Estado de Baja California.\nSEGUNDO.- Se faculta al Consejo de la Judicatura del Estado para dictar en el ámbito de sus atribuciones, todas las medidas que sean necesarias para la efectividad e inmediato cumplimiento de esta Ley.\nTERCERO.- Hasta en tanto el Consejo de la Judicatura del Estado no hubiere nombrado a su Secretario General, sus sesiones serán asistidas por el Secretario General del Tribunal Superior de Justicia.\nCUARTO.- El Consejo de la Judicatura del Estado, establecerá el mecanismo de transferencia de las funciones administrativas y recursos que tiene el Tribunal Superior de\nJusticia, la unidad de apoyo administrativo y órganos auxiliares en favor del mismo Consejo.\nQUINTO.- Los recursos administrativos que se hubieren interpuesto o hechos valer bajo la vigencia de la Ley Orgánica que se abroga, seguirán tramitándose en los términos previstos por la misma hasta su conclusión.\nSEXTO.- Para la integración del Pleno del Consejo de la Judicatura a que se refiere el\nCalifornia, publicada en el Periódico Oficial del Estado de fecha 25 de septiembre de 1995, bastará la asistencia de tres de sus integrantes.\nSEPTIMO.- Para la designación de los magistrados que deban entrar en funciones el las agrupaciones profesionales de abogados a que se refiere el artículo 201 de esta ley.\nOCTAVO.- El Fondo para la Administración de Justicia del Estado de Baja California a que se refiere la ley de ese mismo nombre publicada en el Periódico Oficial de esta Entidad, NOVENO.- Los Secretarios de Acuerdos recibirán en sus domicilios las promociones de los Juzgados, hasta en tanto las Oficialías de Partes respectivas se habiliten para que cumplan con las obligaciones impuestas en las fracciones II y III del artículo 197 de esta ley.\nDECIMO.- Los asuntos que por cuantía se encuentran en trámite en los Juzgados de abroga.\nEstado serán respetados íntegramente.\nDECIMO SEGUNDO.- Queda abrogada la Ley Orgánica del Poder Judicial del Estado de Baja California, publicada en el Periódico Oficial del Estado el día treinta y uno de marzo de 1989 y sus reformas, adiciones y derogaciones a que se refiere la fé de erratas publicada en el Periódico Oficial de fecha veinte de julio de 1989 y decreto número 29 publicado en el\nPeriódico Oficial de fecha veinte de noviembre de 1990.\nCiudad de Mexicali, Baja California a los veintinueve días del mes de Septiembre del mil novecientos noventa y cinco.\nFCO. JAVIER REYNOSO NUÑO,\nDIPUTADO PRESIDENTE.\nRÚBRICA.\nFCO. JAVIER ZEPEDA VILLASEÑOR,\nDIPUTADO SECRETARIO.\nRÚBRICA.\nDE CONFORMIDAD CON LO DISPUESTO POR LA FRACCION I DEL ARTICULO 49\nDE LA CONSTITUCION POLITICA DEL ESTADO, MANDO SE IMPRIMA, PUBLIQUE,\nOBSERVE Y SE LE DE EL DEBIDO CUMPLIMIENTO.\nMEXICALI, BAJA CALIFORNIA, A TRES DE OCTUBRE DE MIL NOVECIENTOS\nNOVENTA Y CINCO.\nEL GOBERNADOR CONSTITUCIONAL DEL ESTADO,\nLIC. ERNESTO RUFFO APPEL.\nRÚBRICA.\nEL SECRETARIO GENERAL DE GOBIERNO,\nLIC. RODOLFO VALDEZ GUTIERREZ\nRÚBRICA.\nARTICULO 1.- Fue reformado por Decreto No. 141, publicado en el Periódico Oficial\nLegislatura, siendo Gobernador Constitucional del Estado, el C. Lic. Héctor Terán Terán, 1995-2001; Fue reformado por Decreto No. 187, publicado en el Periódico Oficial No. 35, de\nConstitucional, siendo Gobernador del Estado el Lic. Héctor Terán Terán, 1995-2001; fue reformado por Decreto No. 247, publicado en el Periódico Oficial No. 45 de fecha 27 de octubre de 2006, Tomo CXIII, expedido por la H. XVIII Legislatura siendo Gobernador\nConstitucional el C. Eugenio Elorduy Walter 2001-2007, fue reformado por Decreto No. 236, publicado en el Periódico Oficial No. 33, de fecha 27 de julio de 2012, Tomo CXIX, Sección\nII, expedido por la H. XX Legislatura, siendo Gobernador Constitucional el C. José\nGuadalupe Osuna Millán 2007-2013; fue reformado por Decreto No. 290, publicado en el\nPeriódico Oficial No. 28, de fecha 12 de junio de 2015, Sección II, Tomo CXXII, expedido por la H. XXI Legislatura, siendo Gobernador Constitucional el C. Francisco Arturo Vega de\nLamadrid 2013-2019; fue reformado por Decreto No. 21, publicado en el Periódico Oficial\nNo. 88, de fecha 27 de octubre de 2021, Número Especial, Tomo CXXVIII, expedido por la\nH. XXIV Legislatura, siendo Gobernador Constitucional el C. Jaime Bonilla Valdez 20192021; fue reformado por Decreto No. 122, publicado en el Periódico Oficial No. 54, de fecha\n02 de septiembre de 2022, Sección IV, Tomo CXXIX, expedido por la H. XXIV Legislatura, siendo Gobernadora Constitucional la C. Marina del Pilar Ávila Olmeda 2021-2027; fue reformado por Decreto No. 329, publicado en el Periódico Oficial No. 66, de fecha 29 de noviembre de 2023, Número Especial, Tomo CXXX, expedido por la H. XXIV Legislatura, siendo Gobernadora Constitucional la C. Marina del Pilar Ávila Olmeda 2021-2027;\nARTICULO 2.- Fue reformado por Decreto No. 141, publicado en el Periódico Oficial\nNo. 18, Sección I, de fecha 4 de mayo de 1998, Tomo CV, expedido por la H. XV\nLegislatura, siendo Gobernador Constitucional del Estado, el C. Lic. Héctor Terán Terán, 1995-2001; Fue reformado por Decreto No. 187, publicado en el Periódico Oficial No. 35, de fecha 28 de agosto de 1998, Sección I, Tomo CV, expedido por la H. XV Legislatura\nConstitucional, siendo Gobernador del Estado el Lic. Héctor Terán Terán, 1995-2001; fue reformado por Decreto No. 247, publicado en el Periódico Oficial No. 45 de fecha 27 de octubre de 2006, Tomo CXIII, expedido por la H. XVIII Legislatura siendo Gobernador\nConstitucional el C. Eugenio Elorduy Walter 2001-2007, fue reformado por Decreto No. 157, publicado en el Periódico Oficial No. 57 de fecha 19 de noviembre de 2008, Tomo CXV, expedido por la H. XIX Legislatura siendo Gobernador Constitucional el C. José Guadalupe\nOsuna Millán 2007-2013, fue reformado por Decreto No. 236, publicado en el Periódico\nLegislatura, siendo Gobernador Constitucional el C. José Guadalupe Osuna Millán 20072013; fue reformado por Decreto No. 290, publicado en el Periódico Oficial No. 28, de fecha\nGobernador Constitucional el C. Francisco Arturo Vega de Lamadrid 2013-2019; fue reformado por Decreto No. 21, publicado en el Periódico Oficial No. 88, de fecha 27 de siendo Gobernador Constitucional el C. Jaime Bonilla Valdez 2019-2021; fue reformado por\nDecreto No. 122, publicado en el Periódico Oficial No. 54, de fecha 02 de septiembre de\n2022, Sección IV, Tomo CXXIX, expedido por la H. XXIV Legislatura, siendo Gobernadora\nConstitucional la C. Marina del Pilar Ávila Olmeda 2021-2027; fue reformado por Decreto No.\nEspecial, Tomo CXXX, expedido por la H. XXIV Legislatura, siendo Gobernadora\nConstitucional la C. Marina del Pilar Ávila Olmeda 2021-2027;\nARTICULO 3.- Fue reformado por Decreto No. 141, publicado en el Periódico Oficial\nNo. 18, Sección I, de fecha 4 de mayo de 1998, Tomo CV, expedido por la H. XV\nLegislatura, siendo Gobernador Constitucional del Estado, el C. Lic. Héctor Terán Terán, 1995-2001;\nARTICULO 5.- Fue reformado por Decreto No. 384, Publicado en el Periódico Oficial\nNo. 29, de fecha 02 de julio de 2010, Tomo CXVII, expedido por la H. XIX Legislatura, siendo\nGobernador Constitucional el C. José Guadalupe Osuna Millán 2007-2013; fue reformado por Decreto No. 21, publicado en el Periódico Oficial No. 88, de fecha 27 de octubre de\n2021, Número Especial, Tomo CXXVIII, expedido por la H. XXIV Legislatura, siendo\nGobernador Constitucional el C. Jaime Bonilla Valdez 2019-2021;\nARTICULO 6.- Fue reformado por Decreto No. 384, Publicado en el Periódico Oficial\nNo. 29, de fecha 02 de julio de 2010, Tomo CXVII, expedido por la H. XIX Legislatura, siendo\nGobernador Constitucional el C. José Guadalupe Osuna Millán 2007-2013; fue reformado por Decreto No. 21, publicado en el Periódico Oficial No. 88, de fecha 27 de octubre de\n2021, Número Especial, Tomo CXXVIII, expedido por la H. XXIV Legislatura, siendo\nGobernador Constitucional el C. Jaime Bonilla Valdez 2019-2021;\nARTICULO 7.- Fue reformado por Decreto No. 141, publicado en el Periódico Oficial\nNo. 18, Sección I, de fecha 4 de mayo de 1998, Tomo CV, expedido por la H. XV\nLegislatura, siendo Gobernador Constitucional del Estado, el C. Lic. Héctor Terán Terán, 1995-2001;\nARTICULO 8.- Fue reformado por Decreto No. 144, publicado en el Periódico Oficial\nNo. 56, Sección I, de fecha 14 de noviembre de 2008, Tomo CXV, expedido por la H. XIX\nLegislatura, siendo Gobernador Constitucional del Estado, el C. Lic. José Guadalupe Osuna\nMillán, 2007-2013;\nARTICULO 9.- Fue reformado por Decreto No. 144, publicado en el Periódico Oficial\nLegislatura, siendo Gobernador Constitucional del Estado, el C. Lic. José Guadalupe Osuna\nMillán, 2007-2013;\nARTICULO 10.- Fue derogado por Decreto No. 144, publicado en el Periódico Oficial\nLegislatura, siendo Gobernador Constitucional del Estado, el C. Lic. José Guadalupe Osuna\nMillán, 2007-2013;\nARTICULO 12.- Fue derogado por Decreto No. 144, publicado en el Periódico Oficial\nLegislatura, siendo Gobernador Constitucional del Estado, el C. Lic. José Guadalupe Osuna\nMillán, 2007-2013;\nARTICULO 17.- Fue reformado por Decreto No. 227, publicado en el Periódico Oficial\nNo. 20, de fecha 24 de abril de 2009, Tomo CXVI, expedido por la H. XIX Legislatura, siendo\nGobernador Constitucional del Estado, el C. Lic. José Guadalupe Osuna Millán, 2007-2013;\nARTICULO 21.- Fue reformado por Decreto No. 141, publicado en el Periódico Oficial\nNo. 18, Sección I, de fecha 4 de mayo de 1998, Tomo CV, expedido por la H. XV\nLegislatura, siendo Gobernador Constitucional del Estado, el C. Lic. Héctor Terán Terán, 1995-2001; Fue reformado por Decreto No. 187, publicado en el Periódico Oficial No. 35, de fecha 28 de agosto de 1998, Tomo CV, Sección I, expedido por la H. XV Legislatura\nConstitucional, siendo Gobernador del Estado el Lic. Héctor Terán Terán, 1995-2001; fue reformado por Decreto No. 247, publicado en el Periódico Oficial No. 45 de fecha 27 de octubre de 2006, Tomo CXIII, expedido por la H. XVIII Legislatura siendo Gobernador\nConstitucional el C. Eugenio Elorduy Walter 2001-2007, Fue reformado por Decreto No. 384, Publicado en el Periódico Oficial No. 29, de fecha 02 de julio de 2010, Tomo CXVII, expedido por la H. XIX Legislatura, siendo Gobernador Constitucional el C. José Guadalupe Osuna\nMillán 2007-2013;\nARTICULO 22.- Fue reformado por Decreto No. 384, Publicado en el Periódico Oficial\nNo. 29, de fecha 02 de julio de 2010, Tomo CXVII, expedido por la H. XIX Legislatura, siendo\nGobernador Constitucional el C. José Guadalupe Osuna Millán 2007-2013;\nARTICULO 23.- Fue reformado por Decreto No. 141, publicado en el Periódico Oficial\nNo. 18, Sección I, de fecha 4 de mayo de 1998, Tomo CV, expedido por la H. XV\nLegislatura, siendo Gobernador Constitucional del Estado, el C. Lic. Héctor Terán Terán, 1995-2001; fue reformado por Decreto No. 247, publicado en el Periódico Oficial No. 45 de fecha 27 de octubre de 2006, Tomo CXIII, expedido por la H. XVIII Legislatura siendo\nGobernador Constitucional el C. Eugenio Elorduy Walter 2001-2007, fue reformado por\nDecreto No. 144, publicado en el Periódico Oficial No. 56, Sección I, de fecha 14 de\nConstitucional del Estado, el C. Lic. José Guadalupe Osuna Millán, 2007-2013;\nARTICULO 24.- Fue reformado por Decreto No. 141, publicado en el Periódico Oficial\nLegislatura, siendo Gobernador Constitucional del Estado, el C. Lic. Héctor Terán Terán, 1995-2001; fue reformado mediante Decreto No. 359, publicado en el Periódico Oficial No.\n57, Tomo CXIX, expedido por la H. XX Legislatura, siendo Gobernador Constitucional el C.\nJosé Guadalupe Osuna Millán 2007-2013;\nARTICULO 25.- Fue reformado por Decreto No. 141, publicado en el Periódico Oficial\nLegislatura, siendo Gobernador Constitucional del Estado, el C. Lic. Héctor Terán Terán, 1995-2001; fue reformado mediante Decreto No. 359, publicado en el Periódico Oficial No.\n57, Tomo CXIX, expedido por la H. XX Legislatura, siendo Gobernador Constitucional el C.\nJosé Guadalupe Osuna Millán 2007-2013;\nARTICULO 27.- Fue reformado por Decreto No. 122, publicado en el Periódico Oficial\nNo. 54, de fecha 02 de septiembre de 2022, Sección IV, Tomo CXXIX, expedido por la H.\nXXIV Legislatura, siendo Gobernadora Constitucional la C. Marina del Pilar Ávila Olmeda\n2021-2027;\nARTICULO 29.- Fue reformado por Decreto No. 141, publicado en el Periódico Oficial\nNo. 18, Sección I, de fecha 4 de mayo de 1998, Tomo CV, expedido por la H. XV\nLegislatura, siendo Gobernador Constitucional del Estado, el C. Lic. Héctor Terán Terán, 1995-2001; fue reformado por Decreto No. 122, publicado en el Periódico Oficial No. 54, de fecha 02 de septiembre de 2022, Sección IV, Tomo CXXIX, expedido por la H. XXIV\nLegislatura, siendo Gobernadora Constitucional la C. Marina del Pilar Ávila Olmeda 20212027; fue reformado por Decreto No. 405, publicado en el Periódico Oficial No. 18, de fecha\n05 de abril de 2024, Índice, Tomo CXXXI, expedido por la H. XXIV Legislatura, siendo\nGobernadora Constitucional la C. Marina del Pilar Ávila Olmeda 2021-2027\nARTICULO 31.- Fue reformado por Decreto No. 187, publicado en el Periódico Oficial\nNo. 35, de fecha 28 de agosto de 1998, Sección I, Tomo CV, expedido por la H. XV\nLegislatura Constitucional, siendo Gobernador del Estado el Lic. Héctor Terán Terán, 19952001;\nARTICULO 32.- Fue reformado por Decreto No. 487, publicado en el Periódico Oficial\nNo. 32, Tomo CXX, de fecha 19 de julio de 2013, expedido por la H. XX Legislatura, siendo\nGobernador Constitucional el C. José Guadalupe Osuna Millán 2007-2013;\nARTICULO 32 BIS.- Fue adicionado por Decreto No. 122, publicado en el Periódico\nOficial No. 54, de fecha 02 de septiembre de 2022, Sección IV, Tomo CXXIX, expedido por la H. XXIV Legislatura, siendo Gobernadora Constitucional la C. Marina del Pilar Ávila\nOlmeda 2021-2027;\nARTICULO 38.- Fue reformado por Decreto No. 384, Publicado en el Periódico Oficial\nGobernador Constitucional el C. José Guadalupe Osuna Millán 2007-2013;\nARTICULO 39.- Fue reformado por Decreto No. 141, publicado en el Periódico Oficial\nLegislatura, siendo Gobernador Constitucional del Estado, el C. Lic. Héctor Terán Terán, 1995-2001; fue reformado por Decreto No. 237, publicado en el Periódico Oficial No. 34, de siendo Gobernador Constitucional el C. Francisco Arturo Vega de Lamadrid 2013-2019;\nARTICULO 44.- Fue reformado por Decreto No. 141, publicado en el Periódico Oficial\nLegislatura, siendo Gobernador Constitucional del Estado, el C. Lic. Héctor Terán Terán, 1995-2001;\nARTICULO 45.- Fue reformado por Decreto No. 247, publicado en el Periódico Oficial\nNo. 45 de fecha 27 de octubre de 2006, Tomo CXIII, expedido por la H. XVIII Legislatura siendo Gobernador Constitucional el C. Eugenio Elorduy Walter 2001-2007; fue reformado por Decreto No. 487, publicado en el Periódico Oficial No. 32, Tomo CXX, de fecha 19 de julio de 2013, expedido por la H. XX Legislatura, siendo Gobernador Constitucional el C.\nJosé Guadalupe Osuna Millán 2007-2013; fue reformado por Decreto No. 122, publicado en el Periódico Oficial No. 54, de fecha 02 de septiembre de 2022, Sección IV, Tomo CXXIX, expedido por la H. XXIV Legislatura, siendo Gobernadora Constitucional la C. Marina del\nPilar Ávila Olmeda 2021-2027;\nARTICULO 47.- Fue reformado por Decreto No. 247, publicado en el Periódico Oficial\nNo. 45 de fecha 27 de octubre de 2006, Tomo CXIII, expedido por la H. XVIII Legislatura siendo Gobernador Constitucional el C. Eugenio Elorduy Walter 2001-2007, ARTICULO 49.- Fue reformado por Decreto No. 247, publicado en el Periódico Oficial\nNo. 45 de fecha 27 de octubre de 2006, Tomo CXIII, expedido por la H. XVIII Legislatura siendo Gobernador Constitucional el C. Eugenio Elorduy Walter 2001-2007, ARTICULO 50.- Fue reformado por Decreto No. 247, publicado en el Periódico Oficial\nNo. 45 de fecha 27 de octubre de 2006, Tomo CXIII, expedido por la H. XVIII Legislatura siendo Gobernador Constitucional el C. Eugenio Elorduy Walter 2001-2007, Fue reformado por Decreto No. 384, Publicado en el Periódico Oficial No. 29, de fecha 02 de julio de 2010, Tomo CXVII, expedido por la H. XIX Legislatura, siendo Gobernador Constitucional el C.\nJosé Guadalupe Osuna Millán 2007-2013; Fue reformado por Decreto No. 236, publicado en el Periódico Oficial No. 33, de fecha 27 de julio de 2012, Tomo CXIX, Sección II, expedido por la H. XX Legislatura, siendo Gobernador Constitucional el C. José Guadalupe Osuna\nMillán 2007-2013;\nARTICULO 51.- Fue reformado por Decreto No. 122, publicado en el Periódico Oficial\nXXIV Legislatura, siendo Gobernadora Constitucional la C. Marina del Pilar Ávila Olmeda\n2021-2027;\nARTICULO 52.- Fue reformado por Decreto No. 21, publicado en el Periódico Oficial\nH. XXIV Legislatura, siendo Gobernador Constitucional el C. Jaime Bonilla Valdez 20192021;\nARTICULO 53.- Fue reformado por Decreto No. 247, publicado en el Periódico Oficial siendo Gobernador Constitucional el C. Eugenio Elorduy Walter 2001-2007, fue reformado por Decreto No. 144, publicado en el Periódico Oficial No. 56, Sección I, de fecha 14 de\nConstitucional del Estado, el C. Lic. José Guadalupe Osuna Millán, 2007-2013; Fue reformado por Decreto No. 384, Publicado en el Periódico Oficial No. 29, de fecha 02 de julio de 2010, Tomo CXVII, expedido por la H. XIX Legislatura, siendo Gobernador Constitucional el C. José Guadalupe Osuna Millán 2007-2013; Fue reformado por Decreto No. 236, publicado en el Periódico Oficial No. 33, de fecha 27 de julio de 2012, Tomo CXIX, Sección\nII, expedido por la H. XX Legislatura, siendo Gobernador Constitucional el C. José\nGuadalupe Osuna Millán 2007-2013; fue reformado por Decreto No. 494, publicado en el\nPeriódico Oficial No. 28, Sección I, Tomo CXXIII, de fecha 17 de junio de 2016, expedido por la H. XXI Legislatura, siendo Gobernador Constitucional el C. Francisco Arturo Vega de\nLamadrid 20013-2016; fue reformado por Decreto No. 122, publicado en el Periódico Oficial\nNo. 54, de fecha 02 de septiembre de 2022, Sección IV, Tomo CXXIX, expedido por la H.\nXXIV Legislatura, siendo Gobernadora Constitucional la C. Marina del Pilar Ávila Olmeda\n2021-2027; fue reformado por Decreto No. 329, publicado en el Periódico Oficial No. 66, de fecha 29 de noviembre de 2023, Número Especial, Tomo CXXX, expedido por la H. XXIV\nLegislatura, siendo Gobernadora Constitucional la C. Marina del Pilar Ávila Olmeda 20212027;\nARTICULO 54.- Fue reformado por Decreto No. 247, publicado en el Periódico Oficial\nNo. 45 de fecha 27 de octubre de 2006, Tomo CXIII, expedido por la H. XVIII Legislatura siendo Gobernador Constitucional el C. Eugenio Elorduy Walter 2001-2007, Fue reformado por Decreto No. 236, publicado en el Periódico Oficial No. 33, de fecha 27 de julio de 2012, Tomo CXIX, Sección II, expedido por la H. XX Legislatura, siendo Gobernador Constitucional el C. José Guadalupe Osuna Millán 2007-2013;\nARTICULO 55.- Fue reformado por Decreto No. 247, publicado en el Periódico Oficial\nNo. 45 de fecha 27 de octubre de 2006, Tomo CXIII, expedido por la H. XVIII Legislatura siendo Gobernador Constitucional el C. Eugenio Elorduy Walter 2001-2007, Fue reformado por Decreto No. 384, Publicado en el Periódico Oficial No. 29, de fecha 02 de julio de 2010, Tomo CXVII, expedido por la H. XIX Legislatura, siendo Gobernador Constitucional el C.\nJosé Guadalupe Osuna Millán 2007-2013;\nARTICULO 56.- Fue reformado por Decreto No. 247, publicado en el Periódico Oficial siendo Gobernador Constitucional el C. Eugenio Elorduy Walter 2001-2007, fue reformado mediante Decreto No. 306, publicado en el Periódico Oficial No. 47, Tomo CXIX, Sección I, Constitucional el C. José Guadalupe Osuna Millán 2007-2013;\nARTÍCULO 57.- Fue reformado por Decreto No. 199, publicado en el Periódico Oficial\nLegislatura, siendo Gobernadora Constitucional la C. Marina del Pilar Ávila Olmeda 20212027;\nARTICULO 57 BIS.- Fue reformado por Decreto No. 384, Publicado en el Periódico siendo Gobernador Constitucional el C. José Guadalupe Osuna Millán 2007-2013;\nARTICULO 58 BIS.- Fue adicionado por Decreto No. 329, publicado en el Periódico\nOficial No. 66, de fecha 29 de noviembre de 2023, Número Especial, Tomo CXXX, expedido por la H. XXIV Legislatura, siendo Gobernadora Constitucional la C. Marina del Pilar Ávila\nOlmeda 2021-2027;\nARTICULO 59.- Fue reformado por Decreto No. 21, publicado en el Periódico Oficial\nNo. 88, de fecha 27 de octubre de 2021, Número Especial, Tomo CXXVIII, expedido por la\nH. XXIV Legislatura, siendo Gobernador Constitucional el C. Jaime Bonilla Valdez 20192021;\nARTICULO 60.- Fue reformado por Decreto No. 144, publicado en el Periódico Oficial\nNo. 56, Sección I, de fecha 14 de noviembre de 2008, Tomo CXV, expedido por la H. XIX\nLegislatura, siendo Gobernador Constitucional del Estado, el C. Lic. José Guadalupe Osuna\nMillán, 2007-2013;\nARTICULO 64.- Fue reformado por Decreto No. 141, publicado en el Periódico Oficial\nNo. 18, Sección I, de fecha 4 de mayo de 1998, Tomo CV, expedido por la H. XV\nLegislatura, siendo Gobernador Constitucional del Estado, el C. Lic. Héctor Terán Terán, 1995-2001; fue reformado por Decreto No. 247, publicado en el Periódico Oficial No. 45 de fecha 27 de octubre de 2006, Tomo CXIII, expedido por la H. XVIII Legislatura siendo\nGobernador Constitucional el C. Eugenio Elorduy Walter 2001-2007, fue reformado por\nDecreto No. 144, publicado en el Periódico Oficial No. 56, Sección I, de fecha 14 de noviembre de 2008, Tomo CXV, expedido por la H. XIX Legislatura, siendo Gobernador\nConstitucional del Estado, el C. Lic. José Guadalupe Osuna Millán, 2007-2013;\nARTICULO 65.- Fue reformado por Decreto No. 384, Publicado en el Periódico Oficial\nNo. 29, de fecha 02 de julio de 2010, Tomo CXVII, expedido por la H. XIX Legislatura, siendo\nGobernador Constitucional el C. José Guadalupe Osuna Millán 2007-2013; fue reformado mediante Decreto No. 359, publicado en el Periódico Oficial No. 57, Tomo CXIX, expedido por la H. XX Legislatura, siendo Gobernador Constitucional el C. José Guadalupe Osuna\nMillán 2007-2013;\nARTICULO 66.- Fue reformado por Decreto No. 384, Publicado en el Periódico Oficial\nGobernador Constitucional el C. José Guadalupe Osuna Millán 2007-2013; fue reformado mediante Decreto No. 359, publicado en el Periódico Oficial No. 57, Tomo CXIX, expedido por la H. XX Legislatura, siendo Gobernador Constitucional el C. José Guadalupe Osuna\nMillán 2007-2013;\nARTICULO 69.- Fue reformado por Decreto No. 247, publicado en el Periódico Oficial siendo Gobernador Constitucional el C. Eugenio Elorduy Walter 2001-2007; fue reformado por Decreto No. 21, publicado en el Periódico Oficial No. 88, de fecha 27 de octubre de\n2021, Número Especial, Tomo CXXVIII, expedido por la H. XXIV Legislatura, siendo\nGobernador Constitucional el C. Jaime Bonilla Valdez 2019-2021; fue reformado por Decreto\nNo. 122, publicado en el Periódico Oficial No. 54, de fecha 02 de septiembre de 2022,\nSección IV, Tomo CXXIX, expedido por la H. XXIV Legislatura, siendo Gobernadora\nConstitucional la C. Marina del Pilar Ávila Olmeda 2021-2027; fue reformado por Decreto No.\n329, publicado en el Periódico Oficial No. 66, de fecha 29 de noviembre de 2023, Número\nEspecial, Tomo CXXX, expedido por la H. XXIV Legislatura, siendo Gobernadora\nConstitucional la C. Marina del Pilar Ávila Olmeda 2021-2027;\nARTICULO 71.- Fue reformado por Decreto No. 144, publicado en el Periódico Oficial\nNo. 56, Sección I, de fecha 14 de noviembre de 2008, Tomo CXV, expedido por la H. XIX\nLegislatura, siendo Gobernador Constitucional del Estado, el C. Lic. José Guadalupe Osuna\nMillán, 2007-2013;\nARTICULO 72.- Fue reformado por Decreto No. 377, publicado en el Periódico Oficial\nNo. 7, de fecha 09 de febrero de 2024, Índice, Tomo CXXXI, expedido por la H. XXIV\nLegislatura, siendo Gobernadora Constitucional la C. Marina del Pilar Ávila Olmeda, 20212027;\nARTICULO 73.- Fue reformado por Decreto No. 214, publicado en el Periódico Oficial\nNo. 10 de fecha 27 de febrero de 2009, Tomo CXVI, expedido por la H. XIX Legislatura siendo Gobernador Constitucional el C. José Guadalupe Osuna Millán 2007-2013, fue reformado mediante Decreto No. 410, publicado en el Periódico Oficial No. 58, de fecha 18 de diciembre de 2015, Sección IV, Tomo CXXII; expedido por la H. XXI Legislatura, siendo\nGobernador constitucional el C. Francisco Arturo Vega de Lamadrid 2013-2019;\nARTICULO 78.- Fue reformado por Decreto No. 214, publicado en el Periódico Oficial\nNo. 10 de fecha 27 de febrero de 2009, Tomo CXVI, expedido por la H. XIX Legislatura siendo Gobernador Constitucional el C. José Guadalupe Osuna Millán 2007-2013, fue reformado por Decreto No. 223, publicado en el Periódico Oficial No. 22, de fecha 21 de abril de 2023, Sección I, Tomo CXXX, expedido por la H. XXIV Legislatura siendo Gobernadora\nConstitucional la C. Marina del Pilar Ávila Olmeda 2021-2024;\nARTICULO 81.- Fue reformado por Decreto No. 214, publicado en el Periódico Oficial siendo Gobernador Constitucional el C. José Guadalupe Osuna Millán 2007-2013, fue reformado por Decreto No. 446, publicado en el Periódico Oficial No. 44, de fecha 15 de\nGobernador Constitucional el C. José Guadalupe Osuna Millán 2007-2013; fue reformado mediante Decreto No. 82, publicado en el Periódico Oficial No. 31, de fecha 01 de julio de\n2011, Tomo CXVIII, Sección II, expedido por la H. XX Legislatura, siendo Gobernador\nConstitucional el C. José Guadalupe Osuna Millán 2007-2013;\nARTICULO 81 BIS.- Fue adicionado por Decreto No. 144, publicado en el Periódico\nXIX Legislatura, siendo Gobernador Constitucional del Estado, el C. Lic. José Guadalupe\nOsuna Millán, 2007-2013; fue reformado por Decreto No. 440, publicado en el Periódico\nOficial No. 44, de fecha 15 de octubre de 2010, Tomo CXVII, Sección II, expedido por la H.\nXIX Legislatura, siendo Gobernador Constitucional el C. José Guadalupe Osuna Millán 20072013; fue reformado mediante Decreto No. 82, publicado en el Periódico Oficial No. 31, de fecha 01 de julio de 2011, Tomo CXVIII, Sección II, expedido por la H. XX Legislatura, siendo Gobernador Constitucional el C. José Guadalupe Osuna Millán 2007-2013; fue reformado por Decreto No. 246, publicado en el Periódico Oficial No. 24, de fecha 22 de mayo de 2015, Sección I, Tomo CXXII, expedido por la H. XXI Legislatura, siendo\nGobernador Constitucional el C. Francisco Arturo Vega de Lamadrid 2013-2019; fue reformado por Decreto No. 237, publicado en el Periódico Oficial No. 34, de fecha 20 de julio de 2018, Sección IV, Tomo CXXV, expedido por la H. XXII Legislatura, siendo Gobernador\nConstitucional el C. Francisco Arturo Vega de Lamadrid 2013-2019;\nARTICULO 81 TER.- Publicado en el Periódico Oficial No. 29, de fecha 02 de julio de\n2010, Tomo CXVII, expedido por la H. XIX Legislatura, siendo Gobernador Constitucional el\nC. José Guadalupe Osuna Millán 2007-2013; fue reformado por Decreto No. 440, publicado en el Periódico Oficial No. 44, de fecha 15 de octubre de 2010, Tomo CXVII, Sección II, expedido por la H. XIX Legislatura, siendo Gobernador Constitucional el C. José Guadalupe\nOsuna Millán 2007-2013; fue reformado por Decreto No. 246, publicado en el Periódico\nOficial No. 24, de fecha 22 de mayo de 2015, Sección I, Tomo CXXII, expedido por la H. XXI\nLegislatura, siendo Gobernador Constitucional el C. Francisco Arturo Vega de Lamadrid\n2013-2019; fue reformado por Decreto No. 494, publicado en el Periódico Oficial No. 28,\nSección I, Tomo CXXIII, de fecha 17 de junio de 2016, expedido por la H. XXI Legislatura, siendo Gobernador Constitucional el C. Francisco Arturo Vega de Lamadrid 20013-2016;\nARTICULO 81 QUARTER.- Publicado en el Periódico Oficial No. 29, de fecha 02 de julio de 2010, Tomo CXVII, expedido por la H. XIX Legislatura, siendo Gobernador\nConstitucional el C. José Guadalupe Osuna Millán 2007-2013; fue reformado por Decreto\nNo. 246, publicado en el Periódico Oficial No. 24, de fecha 22 de mayo de 2015, Sección I, Tomo CXXII, expedido por la H. XXI Legislatura, siendo Gobernador Constitucional el C.\nFrancisco Arturo Vega de Lamadrid 2013-2019; fue reformado por Decreto No. 246, CXXII, expedido por la H. XXI Legislatura, siendo Gobernador Constitucional el C. Francisco\nArturo Vega de Lamadrid 2013-2019;\nARTICULO 81 QUINQUES.- Publicado en el Periódico Oficial No. 29, de fecha 02 de\nConstitucional el C. José Guadalupe Osuna Millán 2007-2013; fue reformado por Decreto\nCXIX, expedido por la H. XX Legislatura, siendo Gobernador Constitucional el C. José\nGuadalupe Osuna Millán 2007-2013; fue reformado por Decreto No. 246, publicado en el la H. XXI Legislatura, siendo Gobernador Constitucional el C. Francisco Arturo Vega de\nLamadrid 2013-2019;\nARTICULO 88.- Fue reformado mediante Decreto No. 410, publicado en el Periódico\nOficial No. 58, de fecha 18 de diciembre de 2015, Sección IV, Tomo CXXII; expedido por la\nH. XXI Legislatura, siendo Gobernador constitucional el C. Francisco Arturo Vega de\nLamadrid 2013-2019;\nARTICULO 90.- Fue reformado mediante Decreto No. 410, publicado en el Periódico\nOficial No. 58, de fecha 18 de diciembre de 2015, Sección IV, Tomo CXXII; expedido por la\nH. XXI Legislatura, siendo Gobernador constitucional el C. Francisco Arturo Vega de\nLamadrid 2013-2019;\nFue adicionado este capítulo por Decreto No. 247, publicado en el Periódico Oficial\nNo. 45 de fecha 27 de octubre de 2006, Tomo CXIII, expedido por la H. XVIII Legislatura siendo Gobernador Constitucional el C. Eugenio Elorduy Walter 2001-2007,\nCAPÍTULO VII\nDE LA ORGANIZACIÓN DE LOS JUZGADOS DE PRIMERA INSTANCIA\nESPECIALIZADOS PARA ADOLESCENTES\nARTICULO 90 BIS.- Fue adicionado por Decreto No. 247, publicado en el Periódico\nOficial No. 45 de fecha 27 de octubre de 2006, Tomo CXIII, expedido por la H. XVIII\nLegislatura siendo Gobernador Constitucional el C. Eugenio Elorduy Walter 2001-2007, ARTICULO 90 TER.- Fue adicionado por Decreto No. 247, publicado en el Periódico\nOficial No. 45 de fecha 27 de octubre de 2006, Tomo CXIII, expedido por la H. XVIII\nLegislatura siendo Gobernador Constitucional el C. Eugenio Elorduy Walter 2001-2007, fue reformado por Decreto No. 494, publicado en el Periódico Oficial No. 28, Sección I, Tomo\nCXXIII, de fecha 17 de junio de 2016, expedido por la H. XXI Legislatura, siendo Gobernador\nConstitucional el C. Francisco Arturo Vega de Lamadrid 20013-2016;\nARTICULO 90 QUATER.- Fue adicionado por Decreto No. 247, publicado en el\nXVIII Legislatura siendo Gobernador Constitucional el C. Eugenio Elorduy Walter 2001-2007, fue reformado por Decreto No. 494, publicado en el Periódico Oficial No. 28, Sección I, Tomo\nConstitucional el C. Francisco Arturo Vega de Lamadrid 20013-2016;\nARTICULO 90 QUINQUIES.- Fue adicionado por Decreto No. 247, publicado en el\nXVIII Legislatura siendo Gobernador Constitucional el C. Eugenio Elorduy Walter 2001-2007, Fue adicionado este Capítulo mediante Decreto No. 236, publicado en el Periódico Oficial\nLegislatura, siendo Gobernador Constitucional el C. José Guadalupe Osuna Millán 20072013;\nCAPÍTULO VIII\nDE LA ORGANIZACIÓN DEL JUZGADO DE\nPRIMERA INSTANCIA EN MATERIA DE\nEXTINCIÓN DE DOMINIO\nARTICULO 90 SEXIES.- Fue adicionado por Decreto No. 236, publicado en el\nPeriódico Oficial No. 33, de fecha 27 de julio de 2012, Tomo CXIX, Sección II, expedido por la H. XX Legislatura, siendo Gobernador Constitucional el C. José Guadalupe Osuna Millán\n2007-2013;\nFue Adicionado el Capítulo por Decreto No. 21, publicado en el Periódico Oficial No. 88, de fecha 27 de octubre de 2021, Número Especial, Tomo CXXVIII, expedido por la H. XXIV\nLegislatura, siendo Gobernador Constitucional el C. Jaime Bonilla Valdez 2019-2021;\nCAPITULO IX\nDE LA ORGANIZACIÓN DE LOS TRIBUNALES EN MATERIA LABORAL\nARTICULO 90 SEPTIES.- Fue adicionado por Decreto No. 21, publicado en el\nPeriódico Oficial No. 88, de fecha 27 de octubre de 2021, Número Especial, Tomo CXXVIII, expedido por la H. XXIV Legislatura, siendo Gobernador Constitucional el C. Jaime Bonilla\nValdez 2019-2021;\nARTICULO 90 OCTIES.- Fue adicionado por Decreto No. 21, publicado en el\nPeriódico Oficial No. 88, de fecha 27 de octubre de 2021, Número Especial, Tomo CXXVIII, expedido por la H. XXIV Legislatura, siendo Gobernador Constitucional el C. Jaime Bonilla\nValdez 2019-2021;\nARTICULO 90 NONIES.- Fue adicionado por Decreto No. 21, publicado en el\nPeriódico Oficial No. 88, de fecha 27 de octubre de 2021, Número Especial, Tomo CXXVIII, expedido por la H. XXIV Legislatura, siendo Gobernador Constitucional el C. Jaime Bonilla\nValdez 2019-2021;\nFue adicionado este Capítulo por Decreto No. 122, publicado en el Periódico Oficial\nXXIV Legislatura, siendo Gobernadora Constitucional la C. Marina del Pilar Ávila Olmeda\n2021-2027;\nCAPÍTULO X\nFAMILIAR CONTRA LAS MUJERES\nARTÍCULO 90 DECIES.- Fue adicionado por Decreto No. 122, publicado en el expedido por la H. XXIV Legislatura, siendo Gobernadora Constitucional la C. Marina del\nPilar Ávila Olmeda 2021-2027; fue reformado por Decreto No. 349, publicado en el Periódico por la H. XXIV Legislatura, siendo Gobernadora Constitucional la C. Marina del Pilar Ávila\nOlmeda 2021-2027;\nFue adicionado este Capítulo por Decreto No. 122, publicado en el Periódico Oficial\nNo. 54, de fecha 02 de septiembre de 2022, Sección IV, Tomo CXXIX, expedido por la H.\nXXIV Legislatura, siendo Gobernadora Constitucional la C. Marina del Pilar Ávila Olmeda\n2021-2027;\nCAPÍTULO XI\nDE LAS CENTRALES DE ACTUARIOS\nFue modificada la denominación de este Capítulo por Decreto No. 329, publicado en el\nPeriódico Oficial No. 66, de fecha 29 de noviembre de 2023, Número Especial, Tomo CXXX, expedido por la H. XXIV Legislatura, siendo Gobernadora Constitucional la C. Marina del\nPilar Ávila Olmeda 2021-2027;\nCAPÍTULO XI\nDE LA ORGANIZACIÓN DE LOS JUZGADOS ESPECIALIZADOS\nEN MATERIA HIPOTECARIA\nARTÍCULO 90 UNDECIES.- Fue adicionado por Decreto No. 122, publicado en el\nPeriódico Oficial No. 54, de fecha 02 de septiembre de 2022, Sección IV, Tomo CXXIX, expedido por la H. XXIV Legislatura, siendo Gobernadora Constitucional la C. Marina del\nPilar Ávila Olmeda 2021-2027; fue reformado por Decreto No. 329, publicado en el Periódico\nOficial No. 66, de fecha 29 de noviembre de 2023, Número Especial, Tomo CXXX, expedido por la H. XXIV Legislatura, siendo Gobernadora Constitucional la C. Marina del Pilar Ávila\nOlmeda 2021-2027;\nFue adicionado este Capítulo trasladándose a éste el texto del Capítulo que se antepone, mediante el Decreto No. 329, publicado en el Periódico Oficial No. 66, de fecha 29 siendo Gobernadora Constitucional la C. Marina del Pilar Ávila Olmeda 2021-2027;\nCAPÍTULO XII\nDE LAS CENTRALES DE ACTUARIOS\nARTÍCULO 90 DODECIES.- Fue adicionado por Decreto No. 122, publicado en el expedido por la H. XXIV Legislatura, siendo Gobernadora Constitucional la C. Marina del\nPilar Ávila Olmeda 2021-2027; fue reformado este artículo trasladándose a éste el texto del artículo que se antepone, mediante el Decreto No. 329, publicado en el Periódico Oficial No.\nXXIV Legislatura, siendo Gobernadora Constitucional la C. Marina del Pilar Ávila Olmeda\n2021-2027;\nARTÍCULO 90 TERDECIES.- Fue adicionado este artículo trasladándose a éste el texto del artículo que se antepone, mediante el Decreto No. 329, publicado en el Periódico\nOficial No. 66, de fecha 29 de noviembre de 2023, Número Especial, Tomo CXXX, expedido por la H. XXIV Legislatura, siendo Gobernadora Constitucional la C. Marina del Pilar Ávila\nOlmeda 2021-2027;\nARTICULO 91.- Fue reformado por Decreto No. 141, publicado en el Periódico Oficial\nNo. 18, Sección I, de fecha 4 de mayo de 1998, Tomo CV, expedido por la H. XV\nLegislatura, siendo Gobernador Constitucional del Estado, el C. Lic. Héctor Terán Terán, 1995-2001; fue reformado por Decreto No. 384, Publicado en el Periódico Oficial No. 29, de fecha 02 de julio de 2010, Tomo CXVII, expedido por la H. XIX Legislatura, siendo\nGobernador Constitucional el C. José Guadalupe Osuna Millán 2007-2013;\nARTICULO 92.- Fue reformado por Decreto No. 141, publicado en el Periódico Oficial\nNo. 18, Sección I, de fecha 4 de mayo de 1998, Tomo CV, expedido por la H. XV\nLegislatura, siendo Gobernador Constitucional del Estado, el C. Lic. Héctor Terán Terán, 1995-2001; Fue reformado por Decreto No. 384, Publicado en el Periódico Oficial No. 29, de fecha 02 de julio de 2010, Tomo CXVII, expedido por la H. XIX Legislatura, siendo\nGobernador Constitucional el C. José Guadalupe Osuna Millán 2007-2013;\nARTICULO 93.- Fue reformado por Decreto No. 141, publicado en el Periódico Oficial\nNo. 18, Sección I, de fecha 4 de mayo de 1998, Tomo CV, expedido por la H. XV\nLegislatura, siendo Gobernador Constitucional del Estado, el C. Lic. Héctor Terán Terán, 1995-2001; Fue reformado por Decreto No. 384, Publicado en el Periódico Oficial No. 29, de fecha 02 de julio de 2010, Tomo CXVII, expedido por la H. XIX Legislatura, siendo\nGobernador Constitucional el C. José Guadalupe Osuna Millán 2007-2013;\nARTICULO 95 BIS.- Fue reformado por Decreto No. 440, publicado en el Periódico\nOficial No. 44, de fecha 15 de octubre de 2010, Tomo CXVII, Sección II, expedido por la H.\nXIX Legislatura, siendo Gobernador Constitucional el C. José Guadalupe Osuna Millán 20072013; fue reformado por Decreto No. 494, publicado en el Periódico Oficial No. 28, Sección I, Gobernador Constitucional el C. Francisco Arturo Vega de Lamadrid 20013-2016;\nARTICULO 100.- Fue reformado por Decreto No. 144, publicado en el Periódico\nXIX Legislatura, siendo Gobernador Constitucional del Estado, el C. Lic. José Guadalupe\nOsuna Millán, 2007-2013;\nARTICULO 102.- Fue reformado por Decreto No. 236, publicado en el Periódico\nLegislatura, siendo Gobernador Constitucional el C. José Guadalupe Osuna Millán 20072013; fue reformado por Decreto No. 21, publicado en el Periódico Oficial No. 88, de fecha\nLegislatura, siendo Gobernador Constitucional el C. Jaime Bonilla Valdez 2019-2021;\nARTICULO 131.- Fue reformado por Decreto No. 315, publicado en el Periódico\nOficial No. 42, de fecha 04 de septiembre de 2015, Sección II, Tomo CXXII, expedido por la\nH. XXI Legislatura, siendo Gobernador Constitucional el C. Francisco Arturo Vega de\nLamadrid 2013-2019;\nARTICULO 143.- Fue reformado por Decreto No. 21, publicado en el Periódico Oficial\nNo. 88, de fecha 27 de octubre de 2021, Número Especial, Tomo CXXVIII, expedido por la\nH. XXIV Legislatura, siendo Gobernador Constitucional el C. Jaime Bonilla Valdez 20192021;\nFue reformada la denominación del Título Séptimo por Decreto No. 141, publicado en el\nPeriódico Oficial No. 18, Sección I, de fecha 4 de mayo de 1998, Tomo CV, expedido por la\nH. XV Legislatura, siendo Gobernador Constitucional del Estado, el C. Lic. Héctor Terán\nTerán, 1995-2001;\nTITULO SEPTIMO\nDE LOS IMPEDIMENTOS EN LA ADMINISTRACION\nDE JUSTICIA\nFue reformada la denominación del Título Octavo por Decreto No. 141, publicado en el\nPeriódico Oficial No. 18, Sección I, de fecha 4 de mayo de 1998, Tomo CV, expedido por la\nH. XV Legislatura, siendo Gobernador Constitucional del Estado, el C. Lic. Héctor Terán\nTerán, 1995-2001;\nTITULO OCTAVO\nDE LAS LICENCIAS DE LOS SERVIDORES PUBLICOS EN LA\nADMINISTRACION DE JUSTICIA\nARTICULO 156.- Fue reformado por Decreto No. 141, publicado en el Periódico\nOficial No. 18, Sección I, de fecha 4 de mayo de 1998, Tomo CV, expedido por la H. XV\nLegislatura, siendo Gobernador Constitucional del Estado, el C. Lic. Héctor Terán Terán, 1995-2001; fue reformado por Decreto No. 126, publicado en el Periódico Oficial No. 48 de\nGobernador Constitucional el C.. Eugenio Elorduy Walter 2001-2007, Se adiciona un párrafo por Decreto No. 141, publicado en el Periódico Oficial No. 54 de fecha 29 de noviembre de\n2005, Tomo CXII, expedido por la H. XVIII Legislatura siendo Gobernador Constitucional el\nC. Eugenio Elorduy Walter 2001-2007; fue reformado por Decreto No. 450, Publicado en el por la H. XIX Legislatura, siendo Gobernador Constitucional el C. José Guadalupe Osuna\nMillán 2007-2013;\nARTICULO 157.- Fue reformado por Decreto No. 187, publicado en el Periódico\nLegislatura Constitucional, siendo Gobernador del Estado el Lic. Héctor Terán Terán, 19952001; fue reformado por Decreto No. 126, publicado en el Periódico Oficial No. 48 de fecha\nGobernador Constitucional el C. Eugenio Elorduy Walter 2001-2007, Fue reformado por\nDecreto No. 203, publicado en el Periódico Oficial No. 25 de fecha 16 de junio de 2006, Tomo CXIII, expedido por la H. XVIII Legislatura siendo Gobernador Constitucional el C.\nEugenio Elorduy Walter 2001-2007; fue reformado por Decreto No. 450, Publicado en el\nPeriódico Oficial No. 44, de fecha 15 de octubre de 2010, Tomo CXVII, Sección II, expedido por la H. XIX Legislatura, siendo Gobernador Constitucional el C. José Guadalupe Osuna\nMillán 2007-2013;\nARTICULO 160.- Fue reformado por Decreto No. 187, publicado en el Periódico\nOficial No. 35, de fecha 28 de agosto de 1998, Sección I, Tomo CV, expedido por la H. XV\nLegislatura Constitucional, siendo Gobernador del Estado el Lic. Héctor Terán Terán, 19952001; Fue reformado por Decreto No. 203, publicado en el Periódico Oficial No. 25 de fecha\n16 de junio de 2006, Tomo CXIII, expedido por la H. XVIII Legislatura siendo Gobernador\nConstitucional el C. Eugenio Elorduy Walter 2001-2007, ARTICULO 161.- Fue reformado por Decreto No. 141, publicado en el Periódico\nOficial No. 18, Sección I, de fecha 4 de mayo de 1998, Tomo CV, expedido por la H. XV\nLegislatura, siendo Gobernador Constitucional del Estado, el C. Lic. Héctor Terán Terán, 1995-2001; Fue reformado por Decreto No. 126, publicado en el Periódico Oficial No. 48 de fecha 01 de noviembre de 2005, Tomo CXII, expedido por la H. XVIII Legislatura siendo\nGobernador Constitucional el C. Eugenio Elorduy Walter 2001-2007, fue reformado por\nDecreto No. 122, publicado en el Periódico Oficial No. 54, de fecha 02 de septiembre de\n2022, Sección IV, Tomo CXXIX, expedido por la H. XXIV Legislatura, siendo Gobernadora\nConstitucional la C. Marina del Pilar Ávila Olmeda 2021-2027;\nARTICULO 162.- Fue reformado por Decreto No. 187, publicado en el Periódico\nOficial No. 35, de fecha 28 de agosto de 1998, Sección I, Tomo CV, expedido por la H. XV\nLegislatura Constitucional, siendo Gobernador del Estado el Lic. Héctor Terán Terán, 19952001; fue reformado por Decreto No. 577, publicado en el Periódico Oficial No. 44, Sección siendo Gobernador Constitucional el C. Francisco Arturo Vega de Lamadrid 20013-2016;\nARTICULO 163.- Fue reformado por Decreto No. 203, publicado en el Periódico siendo Gobernador Constitucional el C. Eugenio Elorduy Walter 2001-2007, ARTICULO 168.- Fue reformado por Decreto No. 141, publicado en el Periódico\nLegislatura, siendo Gobernador Constitucional del Estado, el C. Lic. Héctor Terán Terán, 1995-2001; Fue reformado por Decreto No. 126, publicado en el Periódico Oficial No. 48 de\nGobernador Constitucional el C. Eugenio Elorduy Walter 2001-2007, fue reformado por\nDecreto No. 144, publicado en el Periódico Oficial No. 56, Sección I, de fecha 14 de\nConstitucional del Estado, el C. Lic. José Guadalupe Osuna Millán, 2007-2013; Fue reformado por Decreto No. 384, Publicado en el Periódico Oficial No. 29, de fecha 02 de julio de 2010, Tomo CXVII, expedido por la H. XIX Legislatura, siendo Gobernador Constitucional el C. José Guadalupe Osuna Millán 2007-2013; fue reformado por Decreto No. 340, publicado en el Periódico Oficial No. 53, Sección III, Tomo CXIX, expedido por la H. XX\nLegislatura, siendo Gobernador Constitucional el C. José Guadalupe Osuna Millán 20072013; fue reformado por Decreto No. 408, publicado en el Periódico Oficial No. 5, Sección I, Tomo CXX, de fecha 25 de enero de 2013, expedido por la H. XX Legislatura, siendo\nGobernador Constitucional el C. José Guadalupe Osuna Millán 2007-2013; fue reformado por Decreto No. 290, publicado en el Periódico Oficial No. 28, de fecha 12 de junio de 2015,\nSección II, Tomo CXXII, expedido por la H. XXI Legislatura, siendo Gobernador\nConstitucional el C. Francisco Arturo Vega de Lamadrid 2013-2019; fue reformado por\nDecreto No. 334, publicado en el Periódico Oficial No. 17, de fecha 12 de abril de 2019, Índice, Tomo CXXVI, expedido por la H. XXII Legislatura, siendo Gobernador Constitucional el C. Francisco Arturo Vega de Lamadrid 2013-2019; fue reformado por Decreto No. 122, publicado en el Periódico Oficial No. 54, de fecha 02 de septiembre de 2022, Sección IV, Tomo CXXIX, expedido por la H. XXIV Legislatura, siendo Gobernadora Constitucional la C.\nMarina del Pilar Ávila Olmeda 2021-2027; fue reformado por Decreto No. 293, publicado en el Periódico Oficial No. 55, Índice, de fecha 25 de septiembre de 2023, Tomo CXXX, expedido por la H. XXIV Legislatura, siendo Gobernadora Constitucional la C. Marina del\nPilar Ávila Olmeda 2021-2027;\nARTICULO 172.- Fue reformado por Decreto No. 141, publicado en el Periódico\nOficial No. 18, Sección I, de fecha 4 de mayo de 1998, Tomo CV, expedido por la H. XV\nLegislatura, siendo Gobernador Constitucional del Estado, el C. Lic. Héctor Terán Terán, 1995-2001;\nFue adicionado este Título por Decreto No. 422, publicado en el Periódico Oficial No. 43,\nSección I, de fecha 19 de octubre de 2007, Tomo CXIV, expedido por la H. XVIII Legislatura, siendo Gobernador Constitucional del Estado, del Estado el C. Lic. Eugenio Elorduy Walther\n2001-2007;\nTÍTULO DÉCIMO PRIMERO\nDE LOS ÓRGANOS ADMINISTRATIVOS DEL PODER\nJUDICIAL DEL ESTADO\nCAPITULO VI\nDE LOS ORGANOS AUXILIARES\nDEL CONSEJO DE LA JUDICATURA\nARTICULO 175.- Fue reformado por Decreto No. 85, publicado en el Periódico Oficial\nLegislatura, siendo Gobernador Constitucional del Estado, del Estado el C. Lic. Héctor Terán\nTerán 1995-2001; fue reformado por Decreto No. 422, publicado en el Periódico Oficial No.\nLegislatura, siendo Gobernador Constitucional del Estado, del Estado el C. Lic. Eugenio\nElorduy Walther 2001-2007; Fue reformado por Decreto No. 384, Publicado en el Periódico\nOficial No. 29, de fecha 02 de julio de 2010, Tomo CXVII, expedido por la H. XIX Legislatura, siendo Gobernador Constitucional el C. José Guadalupe Osuna Millán 2007-2013;\nARTICULO 183.- Fue reformado por Decreto No. 141, publicado en el Periódico\nOficial No. 18, Sección I, de fecha 4 de mayo de 1998, Tomo CV, expedido por la H. XV\nLegislatura, siendo Gobernador Constitucional del Estado, el C. Lic. Héctor Terán Terán, 1995-2001; fue reformado por Decreto No. 290, publicado en el Periódico Oficial No. 28, de fecha 12 de junio de 2015, Sección II, Tomo CXXII, expedido por la H. XXI Legislatura, siendo Gobernador Constitucional el C. Francisco Arturo Vega de Lamadrid 2013-2019;\nARTICULO 195.- Fue reformado por Decreto No. 85, publicado en el Periódico Oficial\nNo. 21, Sección I, de fecha 23 de mayo de 1997, Tomo CIV, expedido por la H. XV\nLegislatura, siendo Gobernador Constitucional del Estado el C. Lic. Héctor Terán Terán, 1995-2001;\nARTICULO 196.- Fue reformado por Decreto No. 85, publicado en el Periódico Oficial\nNo. 21, Sección I, de fecha 23 de mayo de 1997, Tomo CIV, expedido por la H. XV\nLegislatura, siendo Gobernador Constitucional del Estado el C. Lic. Héctor Terán Terán, 1995-2001;\nARTICULO 197.- Fue reformado por Decreto No. 21, publicado en el Periódico Oficial\nNo. 88, de fecha 27 de octubre de 2021, Número Especial, Tomo CXXVIII, expedido por la\nH. XXIV Legislatura, siendo Gobernador Constitucional el C. Jaime Bonilla Valdez 20192021;\nFue adicionado este Capítulo por Decreto No. 422, publicado en el Periódico Oficial\nNo. 43, Sección I, de fecha 19 de octubre de 2007, Tomo CXIV, expedido por la H. XVIII\nLegislatura, siendo Gobernador Constitucional del Estado, del Estado el C. Lic. Eugenio\nElorduy Walther 2001-2007; Fue modificada su denominación por Decreto No. 384, por la H. XIX Legislatura, siendo Gobernador Constitucional el C. José Guadalupe Osuna\nMillán 2007-2013;\nCAPÍTULO XIII\nDEL ADMINISTRADOR JUDICIAL\nSección I, Tomo CXXII, expedido por la H. XXI Legislatura, siendo Gobernador\nConstitucional el C. Francisco Arturo Vega de Lamadrid 2013-2019;\nCAPÍTULO XIII\nDEL CENTRO ESTATAL DE JUSTICIA ALTERNATIVA\nARTÍCULO 197 BIS.- Fue reformado por Decreto No. 560, publicado en el Periódico\nH. XXI Legislatura, siendo Gobernador Constitucional el C. Francisco Arturo Vega de\nLamadrid 20013-2016; fue reformado por Decreto No. 21, publicado en el Periódico Oficial\nNo. 88, de fecha 27 de octubre de 2021, Número Especial, Tomo CXXVIII, expedido por la\nH. XXIV Legislatura, siendo Gobernador Constitucional el C. Jaime Bonilla Valdez 20192021;\nFue adicionado este Capítulo por Decreto No. 246, de fecha 22 de mayo de 2015, Sección I, Tomo CXXII, expedido por la H. XXI Legislatura, siendo Gobernador Constitucional el C.\nFrancisco Arturo Vega de Lamadrid 2013-2019;\nCAPÍTULO XIV\nDE LA ADMINISTRACIÓN JUDICIAL\nARTICULO 197 BIS2.- Fue reformado por Decreto No. 384, Publicado en el Periódico\nOficial No. 29, de fecha 02 de julio de 2010, Tomo CXVII, expedido por la H. XIX Legislatura, siendo Gobernador Constitucional el C. José Guadalupe Osuna Millán 2007-2013; fue reformado por Decreto No. 440, publicado en el Periódico Oficial No. 44, de fecha 15 de octubre de 2010, Tomo CXVII, Sección II, expedido por la H. XIX Legislatura, siendo\nGobernador Constitucional el C. José Guadalupe Osuna Millán 2007-2013; fue reformado mediante Decreto No. 82, publicado en el Periódico Oficial No. 31, de fecha 01 de julio de\n2011, Tomo CXVIII, Sección II, expedido por la H. XX Legislatura, siendo Gobernador\nConstitucional el C. José Guadalupe Osuna Millán 2007-2013; fue reformado por Decreto\nNo. 286, publicado en el Periódico Oficial No. 43, de fecha 28 de septiembre de 2012, Tomo\nCXIX, expedido por la H. XX Legislatura, siendo Gobernador Constitucional el C. José\nGuadalupe Osuna Millán 2007-2013; fue reformado por Decreto No. 246, publicado en el\nPeriódico Oficial No. 24, de fecha 22 de mayo de 2015, Sección I, Tomo CXXII, expedido por la H. XXI Legislatura, siendo Gobernador Constitucional el C. Francisco Arturo Vega de\nLamadrid 2013-2019; fue reformado por Decreto No. 494, publicado en el Periódico Oficial\nNo. 28, Sección I, Tomo CXXIII, de fecha 17 de junio de 2016, expedido por la H. XXI\nLegislatura, siendo Gobernador Constitucional el C. Francisco Arturo Vega de Lamadrid\n20013-2016;\nARTICULO 197 BIS3.- Fue reformado por Decreto No. 384, Publicado en el Periódico siendo Gobernador Constitucional el C. José Guadalupe Osuna Millán 2007-2013; fue reformado por Decreto No. 246, publicado en el Periódico Oficial No. 24, de fecha 22 de\nGobernador Constitucional el C. Francisco Arturo Vega de Lamadrid 2013-2019; fue reformado por Decreto No. 494, publicado en el Periódico Oficial No. 28, Sección I, Tomo\nConstitucional el C. Francisco Arturo Vega de Lamadrid 20013-2016;\nARTICULO 197 BIS4.- Fue reformado por Decreto No. 384, Publicado en el Periódico siendo Gobernador Constitucional el C. José Guadalupe Osuna Millán 2007-2013; fue reformado por Decreto No. 122, publicado en el Periódico Oficial No. 54, de fecha 02 de septiembre de 2022, Sección IV, Tomo CXXIX, expedido por la H. XXIV Legislatura, siendo\nGobernadora Constitucional la C. Marina del Pilar Ávila Olmeda 2021-2027;\nARTICULO 197 BIS5.- Fue reformado por Decreto No. 384, Publicado en el Periódico\nOficial No. 29, de fecha 02 de julio de 2010, Tomo CXVII, expedido por la H. XIX Legislatura, siendo Gobernador Constitucional el C. José Guadalupe Osuna Millán 2007-2013; fue reformado por Decreto No. 246, publicado en el Periódico Oficial No. 24, de fecha 22 de mayo de 2015, Sección I, Tomo CXXII, expedido por la H. XXI Legislatura, siendo\nGobernador Constitucional el C. Francisco Arturo Vega de Lamadrid 2013-2019; fue reformado por Decreto No. 494, publicado en el Periódico Oficial No. 28, Sección I, Tomo\nCXXIII, de fecha 17 de junio de 2016, expedido por la H. XXI Legislatura, siendo Gobernador\nConstitucional el C. Francisco Arturo Vega de Lamadrid 20013-2016;\nFue adicionado este Capítulo por Decreto No. 590, publicado en el Periódico Oficial No. 47,\nSección I, de fecha 25 de octubre de 2013, Tomo CXX, expedido por la H. XX Legislatura, siendo Gobernador Constitucional del Estado, del Estado el C. Lic. José Guadalupe Millán\n2007-2013;\nCAPÍTULO XIV\nDE LOS CENTROS E INSTALACIONES DE CONVIVENCIA FAMILIAR SUPERVISADA\nFue modificada por Decreto No. 120, publicado en el Periódico Oficial No. 41, de fecha 08 de septiembre de 2017, Sección III, Tomo CXXIV, expedido por la H. XXII\nLegislatura, siendo Gobernador Constitucional el C. Francisco Arturo Vega de Lamadrid\n2013-2019;\nCAPÍTULO XIV\nDEL CENTRO DE CONVIVENCIA FAMILIAR SUPERVISADA\nARTICULO 197 TER.- Fue adicionado por Decreto No. 590, publicado en el Periódico\nLegislatura, siendo Gobernador Constitucional del Estado, del Estado el C. Lic. José\nGuadalupe Millán 2007-2013; fue reformado por Decreto No. 120, publicado en el Periódico\nH. XXII Legislatura, siendo Gobernador Constitucional el C. Francisco Arturo Vega de\nLamadrid 2013-2019; fue reformado por Decreto No. 122, publicado en el Periódico Oficial\nXXIV Legislatura, siendo Gobernadora Constitucional la C. Marina del Pilar Ávila Olmeda\n2021-2027;\nARTICULO 199.- Fue reformado por Decreto No. 246, publicado en el Periódico\nLegislatura, siendo Gobernador Constitucional el C. Francisco Arturo Vega de Lamadrid\n2013-2019; fue reformado por Decreto No. 21, publicado en el Periódico Oficial No. 88, de fecha 27 de octubre de 2021, Número Especial, Tomo CXXVIII, expedido por la H. XXIV\nLegislatura, siendo Gobernador Constitucional el C. Jaime Bonilla Valdez 2019-2021;\nARTICULO 205.- Fue reformado por Decreto No. 384, Publicado en el Periódico\nOficial No. 29, de fecha 02 de julio de 2010, Tomo CXVII, expedido por la H. XIX Legislatura, siendo Gobernador Constitucional el C. José Guadalupe Osuna Millán 2007-2013;\nARTICULO 207.- Fue reformado por Decreto No. 141, publicado en el Periódico\nOficial No. 18, Sección I, de fecha 4 de mayo de 1998, Tomo CV, expedido por la H. XV\nLegislatura, siendo Gobernador Constitucional del Estado, el C. Lic. Héctor Terán Terán, 1995-2001;\nARTICULO 208.- Fue derogado por Decreto No. 340, publicado en el Periódico Oficial\nNo. 53, Sección III, Tomo CXIX, expedido por la H. XX Legislatura, siendo Gobernador\nConstitucional el C. José Guadalupe Osuna Millán 2007-2013; fue reformado por Decreto\nNo. 408, publicado en el Periódico Oficial No. 5, Sección I, Tomo CXX, de fecha 25 de enero de 2013, expedido por la H. XX Legislatura, siendo Gobernador Constitucional el C. José\nGuadalupe Osuna Millán 2007-2013;\nARTICULO 209.- Fue derogado por Decreto No. 340, publicado en el Periódico Oficial\nNo. 53, Sección III, Tomo CXIX, expedido por la H. XX Legislatura, siendo Gobernador\nConstitucional el C. José Guadalupe Osuna Millán 2007-2013; fue reformado por Decreto\nNo. 408, publicado en el Periódico Oficial No. 5, Sección I, Tomo CXX, de fecha 25 de enero de 2013, expedido por la H. XX Legislatura, siendo Gobernador Constitucional el C. José\nGuadalupe Osuna Millán 2007-2013;\nARTICULO 210.- Fue derogado por Decreto No. 340, publicado en el Periódico Oficial\nNo. 53, Sección III, Tomo CXIX, expedido por la H. XX Legislatura, siendo Gobernador\nConstitucional el C. José Guadalupe Osuna Millán 2007-2013; fue reformado por Decreto\nNo. 408, publicado en el Periódico Oficial No. 5, Sección I, Tomo CXX, de fecha 25 de enero de 2013, expedido por la H. XX Legislatura, siendo Gobernador Constitucional el C. José\nGuadalupe Osuna Millán 2007-2013;\nARTICULO 211.- Fue derogado por Decreto No. 340, publicado en el Periódico Oficial\nNo. 53, Sección III, Tomo CXIX, expedido por la H. XX Legislatura, siendo Gobernador\nConstitucional el C. José Guadalupe Osuna Millán 2007-2013; fue reformado por Decreto\nNo. 408, publicado en el Periódico Oficial No. 5, Sección I, Tomo CXX, de fecha 25 de enero de 2013, expedido por la H. XX Legislatura, siendo Gobernador Constitucional el C. José\nGuadalupe Osuna Millán 2007-2013;\nARTICULO 212.- Fue derogado por Decreto No. 340, publicado en el Periódico Oficial\nNo. 53, Sección III, Tomo CXIX, expedido por la H. XX Legislatura, siendo Gobernador\nConstitucional el C. José Guadalupe Osuna Millán 2007-2013; fue reformado por Decreto\nNo. 408, publicado en el Periódico Oficial No. 5, Sección I, Tomo CXX, de fecha 25 de enero de 2013, expedido por la H. XX Legislatura, siendo Gobernador Constitucional el C. José\nGuadalupe Osuna Millán 2007-2013;\nARTICULO 213.- Fue derogado por Decreto No. 340, publicado en el Periódico Oficial\nNo. 53, Sección III, Tomo CXIX, expedido por la H. XX Legislatura, siendo Gobernador\nConstitucional el C. José Guadalupe Osuna Millán 2007-2013; fue reformado por Decreto\nNo. 408, publicado en el Periódico Oficial No. 5, Sección I, Tomo CXX, de fecha 25 de enero de 2013, expedido por la H. XX Legislatura, siendo Gobernador Constitucional el C. José\nGuadalupe Osuna Millán 2007-2013;\nARTICULO 214.- Fue derogado por Decreto No. 340, publicado en el Periódico Oficial\nNo. 53, Sección III, Tomo CXIX, expedido por la H. XX Legislatura, siendo Gobernador\nConstitucional el C. José Guadalupe Osuna Millán 2007-2013; fue reformado por Decreto\nNo. 408, publicado en el Periódico Oficial No. 5, Sección I, Tomo CXX, de fecha 25 de enero de 2013, expedido por la H. XX Legislatura, siendo Gobernador Constitucional el C. José\nGuadalupe Osuna Millán 2007-2013;\nARTICULO 215.- Fue derogado por Decreto No. 340, publicado en el Periódico Oficial\nNo. 53, Sección III, Tomo CXIX, expedido por la H. XX Legislatura, siendo Gobernador\nConstitucional el C. José Guadalupe Osuna Millán 2007-2013; fue reformado mediante\nDecreto No. 359, publicado en el Periódico Oficial No. 57, Tomo CXIX, expedido por la H. XX\nLegislatura, siendo Gobernador Constitucional el C. José Guadalupe Osuna Millán 20072013; fue reformado por Decreto No. 408, publicado en el Periódico Oficial No. 5, Sección I, Tomo CXX, de fecha 25 de enero de 2013, expedido por la H. XX Legislatura, siendo\nGobernador Constitucional el C. José Guadalupe Osuna Millán 2007-2013;\nARTICULO 216.- Fue derogado por Decreto No. 340, publicado en el Periódico Oficial\nNo. 53, Sección III, Tomo CXIX, expedido por la H. XX Legislatura, siendo Gobernador\nConstitucional el C. José Guadalupe Osuna Millán 2007-2013; fue reformado por Decreto\nNo. 408, publicado en el Periódico Oficial No. 5, Sección I, Tomo CXX, de fecha 25 de enero de 2013, expedido por la H. XX Legislatura, siendo Gobernador Constitucional el C. José\nGuadalupe Osuna Millán 2007-2013;\nARTICULO 217.- Fue derogado por Decreto No. 340, publicado en el Periódico Oficial\nNo. 53, Sección III, Tomo CXIX, expedido por la H. XX Legislatura, siendo Gobernador\nConstitucional el C. José Guadalupe Osuna Millán 2007-2013; fue reformado por Decreto\nNo. 408, publicado en el Periódico Oficial No. 5, Sección I, Tomo CXX, de fecha 25 de enero de 2013, expedido por la H. XX Legislatura, siendo Gobernador Constitucional el C. José\nGuadalupe Osuna Millán 2007-2013;\nARTICULO 220.- Fue reformado mediante Decreto No. 359, publicado en el Periódico\nOficial No. 57, Tomo CXIX, expedido por la H. XX Legislatura, siendo Gobernador\nConstitucional el C. José Guadalupe Osuna Millán 2007-2013;\nFue adicionado el Título Decimocuarto por Decreto No. 141, publicado en el Periódico Oficial\nLegislatura, siendo Gobernador Constitucional del Estado, el C. Lic. Héctor Terán Terán, 1995-2001;\nTITULO DECIMOCUARTO\nDEL TRIBUNAL DE JUSTICIA ELECTORAL DEL\nPODER JUDICIAL DEL ESTADO\nCAPITULO I\nDE SU NATURALEZA\nFue modificada la denominación de este Título por Decreto No. 494, publicado en el\nPeriódico Oficial No. 28, Sección I, Tomo CXXIII, de fecha 17 de junio de 2016, expedido por la H. XXI Legislatura, siendo Gobernador Constitucional el C. Francisco Arturo Vega de\nLamadrid 20013-2016;\nTITULO DECIMO CUARTO\nDEL TRIBUNAL ELECTRONICO\nCAPITULO UNICO\nARTICULO 244.- Fue adicionado por Decreto No. 141, publicado en el Periódico\nOficial No. 18, Sección I, de fecha 4 de mayo de 1998, Tomo CV, expedido por la H. XV\nLegislatura, siendo Gobernador Constitucional del Estado, el C. Lic. Héctor Terán Terán, 1995-2001; fue derogado por Decreto No. 290, publicado en el Periódico Oficial No. 28, de fecha 12 de junio de 2015, Sección II, Tomo CXXII, expedido por la H. XXI Legislatura, siendo Gobernador Constitucional el C. Francisco Arturo Vega de Lamadrid 2013-2019; fue derogado por Decreto No. 290, publicado en el Periódico Oficial No. 28, de fecha 12 de junio de 2015, Sección II, Tomo CXXII, expedido por la H. XXI Legislatura, siendo Gobernador\nConstitucional el C. Francisco Arturo Vega de Lamadrid 2013-2019; fue reformado por\nDecreto No. 494, publicado en el Periódico Oficial No. 28, Sección I, Tomo CXXIII, de fecha\n17 de junio de 2016, expedido por la H. XXI Legislatura, siendo Gobernador Constitucional el\nC. Francisco Arturo Vega de Lamadrid 20013-2016;\nARTICULO 245.- Fue reformado por Decreto No. 157, publicado en el Periódico\nLegislatura siendo Gobernador Constitucional el C. José Guadalupe Osuna Millán 20072013, fue derogado por Decreto No. 290, publicado en el Periódico Oficial No. 28, de fecha\nGobernador Constitucional el C. Francisco Arturo Vega de Lamadrid 2013-2019; fue reformado por Decreto No. 494, publicado en el Periódico Oficial No. 28, Sección I, Tomo\nConstitucional el C. Francisco Arturo Vega de Lamadrid 20013-2016;\nARTICULO 246.- Fue adicionado por Decreto No. 141, publicado en el Periódico\nLegislatura, siendo Gobernador Constitucional del Estado, el C. Lic. Héctor Terán Terán, 1995-2001; fue derogado por Decreto No. 290, publicado en el Periódico Oficial No. 28, de siendo Gobernador Constitucional el C. Francisco Arturo Vega de Lamadrid 2013-2019;\nFue adicionado el Capítulo II, por Decreto No. 141, publicado en el Periódico Oficial No. 18,\nSección I, de fecha 4 de mayo de 1998, Tomo CV, expedido por la H. XV Legislatura, siendo\nGobernador Constitucional del Estado, el C. Lic. Héctor Terán Terán, 1995-2001;\nCAPITULO II\nDE SU INTEGRACION, FUNCIONAMIENTO Y ATRIBUCIONES\nARTICULO 247.- Fue adicionado por Decreto No. 141, publicado en el Periódico\nOficial No. 18, Sección I, de fecha 4 de mayo de 1998, Tomo CV, expedido por la H. XV\nLegislatura, siendo Gobernador Constitucional del Estado, el C. Lic. Héctor Terán Terán, 1995-2001; fue reformado por Decreto No. 157, publicado en el Periódico Oficial No. 57 de fecha 19 de noviembre de 2008, Tomo CXV, expedido por la H. XIX Legislatura siendo\nGobernador Constitucional el C. José Guadalupe Osuna Millán 2007-2013, fue derogado por\nDecreto No. 290, publicado en el Periódico Oficial No. 28, de fecha 12 de junio de 2015,\nSección II, Tomo CXXII, expedido por la H. XXI Legislatura, siendo Gobernador\nConstitucional el C. Francisco Arturo Vega de Lamadrid 2013-2019;\nARTICULO 248.- Fue adicionado por Decreto No. 141, publicado en el Periódico\nOficial No. 18, Sección I, de fecha 4 de mayo de 1998, Tomo CV, expedido por la H. XV\nLegislatura, siendo Gobernador Constitucional del Estado, el C. Lic. Héctor Terán Terán, 1995-2001; fue reformado por Decreto No. 157, publicado en el Periódico Oficial No. 57 de fecha 19 de noviembre de 2008, Tomo CXV, Número Especial, expedido por la H. XIX\nLegislatura siendo Gobernador Constitucional el C. José Guadalupe Osuna Millán 20072013, fue derogado por Decreto No. 290, publicado en el Periódico Oficial No. 28, de fecha\n12 de junio de 2015, Sección II, Tomo CXXII, expedido por la H. XXI Legislatura, siendo\nGobernador Constitucional el C. Francisco Arturo Vega de Lamadrid 2013-2019;\nFue adicionada la Sección Primera, por Decreto No. 157, publicado en el Periódico Oficial\nH. XIX Legislatura, siendo Gobernador Constitucional del Estado, el C. José Guadalupe\nOsuna Millán, 2007-2013;\nSECCIÓN PRIMERA\nDEL PLENO\nARTICULO 249.- Fue adicionado por Decreto No. 141, publicado en el Periódico\nLegislatura, siendo Gobernador Constitucional del Estado, el C. Lic. Héctor Terán Terán, 1995-2001; fue reformado por Decreto No. 239, publicado en el Periódico Oficial de fecha 14\nGobernador Constitucional el C. Eugenio Elorduy, 2001-2007; fue reformado por Decreto No.\nNúmero Especial, expedido por la H. XIX Legislatura siendo Gobernador Constitucional el C.\nJosé Guadalupe Osuna Millán 2007-2013, fue derogado por Decreto No. 290, publicado en el Periódico Oficial No. 28, de fecha 12 de junio de 2015, Sección II, Tomo CXXII, expedido por la H. XXI Legislatura, siendo Gobernador Constitucional el C. Francisco Arturo Vega de\nLamadrid 2013-2019;\nARTICULO 250.- Fue adicionado por Decreto No. 141, publicado en el Periódico\nOficial No. 18, Sección I, de fecha 4 de mayo de 1998, Tomo CV, expedido por la H. XV\nLegislatura, siendo Gobernador Constitucional del Estado, el C. Lic. Héctor Terán Terán, 1995-2001; fue reformado por Decreto No. 157, publicado en el Periódico Oficial No. 57 de fecha 19 de noviembre de 2008, Tomo CXV, Número Especial, expedido por la H. XIX\nLegislatura siendo Gobernador Constitucional el C. José Guadalupe Osuna Millán 20072013, fue derogado por Decreto No. 290, publicado en el Periódico Oficial No. 28, de fecha\n12 de junio de 2015, Sección II, Tomo CXXII, expedido por la H. XXI Legislatura, siendo\nGobernador Constitucional el C. Francisco Arturo Vega de Lamadrid 2013-2019;\nARTICULO 251.- Fue adicionado por Decreto No. 141, publicado en el Periódico\nOficial No. 18, Sección I, de fecha 4 de mayo de 1998, Tomo CV, expedido por la H. XV\nLegislatura, siendo Gobernador Constitucional del Estado, el C. Lic. Héctor Terán Terán, 1995-2001; fue reformado por Decreto No. 157, publicado en el Periódico Oficial No. 57 de fecha 19 de noviembre de 2008, Tomo CXV, Número Especial, expedido por la H. XIX\nLegislatura siendo Gobernador Constitucional el C. José Guadalupe Osuna Millán 20072013, fue derogado por Decreto No. 290, publicado en el Periódico Oficial No. 28, de fecha\n12 de junio de 2015, Sección II, Tomo CXXII, expedido por la H. XXI Legislatura, siendo\nGobernador Constitucional el C. Francisco Arturo Vega de Lamadrid 2013-2019;\nARTICULO 251 BIS.- Fue derogado por Decreto No. 290, publicado en el Periódico\nOficial No. 28, de fecha 12 de junio de 2015, Sección II, Tomo CXXII, expedido por la H. XXI\nLegislatura, siendo Gobernador Constitucional el C. Francisco Arturo Vega de Lamadrid\n2013-2019;\nARTÍCULO 251 TER.- Fue derogado por Decreto No. 290, publicado en el Periódico\nLegislatura, siendo Gobernador Constitucional el C. Francisco Arturo Vega de Lamadrid\n2013-2019;\nARTÍCULO 251 QUATER.- Fue derogado por Decreto No. 290, publicado en el la H. XXI Legislatura, siendo Gobernador Constitucional el C. Francisco Arturo Vega de\nLamadrid 2013-2019;\nARTÍCULO 251 QUINQUES.- Fue derogado por Decreto No. 290, publicado en el la H. XXI Legislatura, siendo Gobernador Constitucional el C. Francisco Arturo Vega de\nLamadrid 2013-2019;\nARTÍCULO 251 SEXIES.- Fue derogado por Decreto No. 290, publicado en el\nPeriódico Oficial No. 28, de fecha 12 de junio de 2015, Sección II, Tomo CXXII, expedido por la H. XXI Legislatura, siendo Gobernador Constitucional el C. Francisco Arturo Vega de\nLamadrid 2013-2019;\nARTÍCULO 251 SEPTIES.- Fue derogado por Decreto No. 290, publicado en el\nPeriódico Oficial No. 28, de fecha 12 de junio de 2015, Sección II, Tomo CXXII, expedido por la H. XXI Legislatura, siendo Gobernador Constitucional el C. Francisco Arturo Vega de\nLamadrid 2013-2019;\nFue adicionada la Sección Segunda, por Decreto No. 157, publicado en el Periódico Oficial\nNo. 57, Número Especial, de fecha 19 de noviembre de 20088, Tomo CXV, expedido por la\nH. XIX Legislatura, siendo Gobernador Constitucional del Estado, el C. José Guadalupe\nOsuna Millán, 2007-2013;\nSECCIÓN SEGUNDA\nDE LAS SALAS\nFue adicionado Capítulo III por Decreto No. 141, publicado en el Periódico Oficial No. 18,\nSección I, de fecha 4 de mayo de 1998, Tomo CV, expedido por la H. XV Legislatura, siendo\nGobernador Constitucional del Estado, el C. Lic. Héctor Terán Terán, 1995-2001;\nCAPITULO III\nDEL PRESIDENTE DEL TRIBUNAL DE JUSTICIA\nELECTORAL Y SUS ATRIBUCIONES\nARTICULO 252.- Fue adicionado por Decreto No. 141, publicado en el Periódico\nOficial No. 18, Sección I, de fecha 4 de mayo de 1998, Tomo CV, expedido por la H. XV\nLegislatura, siendo Gobernador Constitucional del Estado, el C. Lic. Héctor Terán Terán, 1995-2001; fue derogado por Decreto No. 290, publicado en el Periódico Oficial No. 28, de fecha 12 de junio de 2015, Sección II, Tomo CXXII, expedido por la H. XXI Legislatura, siendo Gobernador Constitucional el C. Francisco Arturo Vega de Lamadrid 2013-2019;\nARTICULO 253.- Fue adicionado por Decreto No. 141, publicado en el Periódico\nLegislatura, siendo Gobernador Constitucional del Estado, el C. Lic. Héctor Terán Terán, 1995-2001; fue reformado por Decreto No. 157, publicado en el Periódico Oficial No. 57 de\nLegislatura siendo Gobernador Constitucional el C. José Guadalupe Osuna Millán 20072013; fue reformado por Decreto No. 450, Publicado en el Periódico Oficial No. 44, de fecha\nGobernador Constitucional el C. José Guadalupe Osuna Millán 2007-2013; fue derogado por\nSección II, Tomo CXXII, expedido por la H. XXI Legislatura, siendo Gobernador\nConstitucional el C. Francisco Arturo Vega de Lamadrid 2013-2019;\nFue adicionado el Capítulo IV, por Decreto No. 141, publicado en el Periódico Oficial\nLegislatura, siendo Gobernador Constitucional del Estado, el C. Lic. Héctor Terán Terán, 1995-2001;\nCAPITULO IV\nDE LOS MAGISTRADOS ELECTORALES\nY SUS ATRIBUCIONES\nARTICULO 254.- Fue adicionado por Decreto No. 141, publicado en el Periódico\nOficial No. 18, Sección I, de fecha 4 de mayo de 1998, Tomo CV, expedido por la H. XV\nLegislatura, siendo Gobernador Constitucional del Estado, el C. Lic. Héctor Terán Terán, 1995-2001; fue reformado por Decreto No. 212, publicado en el Periódico Oficial No. 47, de fecha 17 de octubre de 2003, Tomo CX, expedido por la H. XVII Legislatura, siendo\nGobernador Constitucional el C. Eugenio Elorduy Walther 2001-2007; Fe de Erratas publicada en el Periódico Oficial No. 51, de fecha 7 de noviembre de 2003, Tomo CX, expedida por la H. XVII Legislatura, siendo Gobernador Constitucional el C. Eugenio Elorduy\nWalter 2001-2007; fue derogado por Decreto No. 290, publicado en el Periódico Oficial No.\n28, de fecha 12 de junio de 2015, Sección II, Tomo CXXII, expedido por la H. XXI\nLegislatura, siendo Gobernador Constitucional el C. Francisco Arturo Vega de Lamadrid\n2013-2019;\nARTICULO 255.- Fue adicionado por Decreto No. 141, publicado en el Periódico\nOficial No. 18, Sección I, de fecha 4 de mayo de 1998, Tomo CV, expedido por la H. XV\nLegislatura, siendo Gobernador Constitucional del Estado, el C. Lic. Héctor Terán Terán, 1995-2001; fue reformado por Decreto No. 115, publicado en el Periódico Oficial No. 02, de fecha 10 de enero de 2003, Tomo CX, expedido por la H. XVII Legislatura, siendo\nGobernador Constitucional el C. Eugenio Elorduy Walther; fue reformado por Decreto No.\n212, publicado en el Periódico Oficial No. 47, de fecha 17 de octubre de 2003, Tomo CX, expedido por la H. XVII Legislatura, siendo Gobernador Constitucional el C. Eugenio Elorduy\nWalther 2001-2007; Fue derogado por Decreto No. 290, publicado en el Periódico Oficial No.\n28, de fecha 12 de junio de 2015, Sección II, Tomo CXXII, expedido por la H. XXI\nLegislatura, siendo Gobernador Constitucional el C. Francisco Arturo Vega de Lamadrid\n2013-2019;\nARTICULO 256.- Fue adicionado por Decreto No. 141, publicado en el Periódico\nLegislatura, siendo Gobernador Constitucional del Estado, el C. Lic. Héctor Terán Terán, 1995-2001; fue reformado por Decreto No. 115, publicado en el Periódico Oficial No. 02, de\nGobernador Constitucional el C. Eugenio Elorduy Walther; fue derogado por Decreto No.\nCXXII, expedido por la H. XXI Legislatura, siendo Gobernador Constitucional el C. Francisco\nArturo Vega de Lamadrid 2013-2019;\nARTICULO 257.- Fue adicionado por Decreto No. 141, publicado en el Periódico\nLegislatura, siendo Gobernador Constitucional del Estado, el C. Lic. Héctor Terán Terán, 1995-2001; fue reformado por Decreto No. 157, publicado en el Periódico Oficial No. 57 de fecha 19 de noviembre de 2008, Tomo CXV, Número Especial, expedido por la H. XIX\nLegislatura siendo Gobernador Constitucional el C. José Guadalupe Osuna Millán 20072013, fue derogado por Decreto No. 290, publicado en el Periódico Oficial No. 28, de fecha\n12 de junio de 2015, Sección II, Tomo CXXII, expedido por la H. XXI Legislatura, siendo\nGobernador Constitucional el C. Francisco Arturo Vega de Lamadrid 2013-2019;\nFue adicionado el Capítulo V, por Decreto No. 141, publicado en el Periódico Oficial No. 18,\nSección I, de fecha 4 de mayo de 1998, Tomo CV, expedido por la H. XV Legislatura, siendo\nGobernador Constitucional del Estado, el C. Lic. Héctor Terán Terán, 1995-2001;\nCAPITULO V\nDEL SECRETARIO GENERAL DEL TRIBUNAL DE JUSTICIA\nELECTORAL Y SUS ATRIBUCIONES.\nARTICULO 258.- Fue adicionado por Decreto No. 141, publicado en el Periódico\nOficial No. 18, Sección I, de fecha 4 de mayo de 1998, Tomo CV, expedido por la H. XV\nLegislatura, siendo Gobernador Constitucional del Estado, el C. Lic. Héctor Terán Terán, 1995-2001; Fue reformado por Decreto No. 157, publicado en el Periódico Oficial No. 57 de fecha 19 de noviembre de 2008, Tomo CXV, Número Especial, expedido por la H. XIX\nLegislatura siendo Gobernador Constitucional el C. José Guadalupe Osuna Millán 20072013, fue reformado por Decreto No. 293, publicado en el Periódico Oficial No. 48, de fecha\n30 de octubre de 2009, Tomo CXVI, expedido por la H. XIX Legislatura, siendo Gobernador\nConstitucional el C. Eugenio Elorduy Walther 2001-2007; fue derogado por Decreto No. 290, publicado en el Periódico Oficial No. 28, de fecha 12 de junio de 2015, Sección II, Tomo\nCXXII, expedido por la H. XXI Legislatura, siendo Gobernador Constitucional el C. Francisco\nArturo Vega de Lamadrid 2013-2019;\nFue adicionado el Capítulo VI, por Decreto No. 141, publicado en el Periódico Oficial No. 18,\nSección I, de fecha 4 de mayo de 1998, Tomo CV, expedido por la H. XV Legislatura, siendo\nGobernador Constitucional del Estado, el C. Lic. Héctor Terán Terán, 1995-2001;\nCAPITULO VI\nDE LA COMISION DE ADMINISTRACION, INTEGRACION,\nFUNCIONAMIENTO Y ATRIBUCIONES\nARTICULO 259.- Fue adicionado por Decreto No. 141, publicado en el Periódico\nLegislatura, siendo Gobernador Constitucional del Estado, el C. Lic. Héctor Terán Terán, 1995-2001; fue derogado por Decreto No. 290, publicado en el Periódico Oficial No. 28, de siendo Gobernador Constitucional el C. Francisco Arturo Vega de Lamadrid 2013-2019;\nARTICULO 260.- Fue adicionado por Decreto No. 141, publicado en el Periódico\nLegislatura, siendo Gobernador Constitucional del Estado, el C. Lic. Héctor Terán Terán, 1995-2001; fue derogado por Decreto No. 290, publicado en el Periódico Oficial No. 28, de fecha 12 de junio de 2015, Sección II, Tomo CXXII, expedido por la H. XXI Legislatura, siendo Gobernador Constitucional el C. Francisco Arturo Vega de Lamadrid 2013-2019;\nARTICULO 261.- Fue adicionado por Decreto No. 141, publicado en el Periódico\nOficial No. 18, Sección I, de fecha 4 de mayo de 1998, Tomo CV, expedido por la H. XV\nLegislatura, siendo Gobernador Constitucional del Estado, el C. Lic. Héctor Terán Terán, 1995-2001; fue derogado por Decreto No. 290, publicado en el Periódico Oficial No. 28, de fecha 12 de junio de 2015, Sección II, Tomo CXXII, expedido por la H. XXI Legislatura, siendo Gobernador Constitucional el C. Francisco Arturo Vega de Lamadrid 2013-2019;\nARTICULO 262.- Fue adicionado por Decreto No. 141, publicado en el Periódico\nOficial No. 18, Sección I, de fecha 4 de mayo de 1998, Tomo CV, expedido por la H. XV\nLegislatura, siendo Gobernador Constitucional del Estado, el C. Lic. Héctor Terán Terán, 1995-2001; fue derogado por Decreto No. 290, publicado en el Periódico Oficial No. 28, de fecha 12 de junio de 2015, Sección II, Tomo CXXII, expedido por la H. XXI Legislatura, siendo Gobernador Constitucional el C. Francisco Arturo Vega de Lamadrid 2013-2019;\nARTICULO 263.- Fue adicionado por Decreto No. 141, publicado en el Periódico\nOficial No. 18, Sección I, de fecha 4 de mayo de 1998, Tomo CV, expedido por la H. XV\nLegislatura, siendo Gobernador Constitucional del Estado, el C. Lic. Héctor Terán Terán, 1995-2001; fue derogado por Decreto No. 290, publicado en el Periódico Oficial No. 28, de fecha 12 de junio de 2015, Sección II, Tomo CXXII, expedido por la H. XXI Legislatura, siendo Gobernador Constitucional el C. Francisco Arturo Vega de Lamadrid 2013-2019;\nFue adicionado el Capítulo VII, por Decreto No. 141, publicado en el Periódico Oficial\nNo. 18, Sección I, de fecha 4 de mayo de 1998, Tomo CV, expedido por la H. XV\nLegislatura, siendo Gobernador Constitucional del Estado, el C. Lic. Héctor Terán Terán, 1995-2001;\nCAPITULO VII\nJUSTICIA ELECTORAL Y SUS ATRIBUCIONES\nARTICULO 264.- Fue adicionado por Decreto No. 141, publicado en el Periódico\nLegislatura, siendo Gobernador Constitucional del Estado, el C. Lic. Héctor Terán Terán, 1995-2001; fue derogado por Decreto No. 290, publicado en el Periódico Oficial No. 28, de siendo Gobernador Constitucional el C. Francisco Arturo Vega de Lamadrid 2013-2019;\nFue adicionado el Capítulo VIII, por Decreto No. 141, publicado en el Periódico Oficial No. siendo Gobernador Constitucional del Estado, el C. Lic. Héctor Terán Terán, 1995-2001;\nCAPITULO VIII\nDE LA FISCALIZACION DEL TRIBUNAL DE JUSTICIA\nELECTORAL DEL PODER JUDICIAL DEL ESTADO\nARTICULO 265.- Fue adicionado por Decreto No. 141, publicado en el Periódico\nOficial No. 18, Sección I, de fecha 4 de mayo de 1998, Tomo CV, expedido por la H. XV\nLegislatura, siendo Gobernador Constitucional del Estado, el C. Lic. Héctor Terán Terán, 1995-2001; fue derogado por Decreto No. 290, publicado en el Periódico Oficial No. 28, de fecha 12 de junio de 2015, Sección II, Tomo CXXII, expedido por la H. XXI Legislatura, siendo Gobernador Constitucional el C. Francisco Arturo Vega de Lamadrid 2013-2019;\nARTICULO 266.- Fue adicionado por Decreto No. 141, publicado en el Periódico\nOficial No. 18, Sección I, de fecha 4 de mayo de 1998, Tomo CV, expedido por la H. XV\nLegislatura, siendo Gobernador Constitucional del Estado, el C. Lic. Héctor Terán Terán, 1995-2001; fue derogado por Decreto No. 290, publicado en el Periódico Oficial No. 28, de fecha 12 de junio de 2015, Sección II, Tomo CXXII, expedido por la H. XXI Legislatura, siendo Gobernador Constitucional el C. Francisco Arturo Vega de Lamadrid 2013-2019;\nFue adicionado el Capítulo IX, por Decreto No. 141, publicado en el Periódico Oficial\nNo. 18, Sección I, de fecha 4 de mayo de 1998, Tomo CV, expedido por la H. XV\nLegislatura, siendo Gobernador Constitucional del Estado, el C. Lic. Héctor Terán Terán, 1995-2001;\nCAPITULO IX\nDE LOS REQUISITOS PARA OCUPAR CARGOS EN EL\nTRIBUNAL DE JUSTICIA ELECTORAL\nARTICULO 267.- Fue adicionado por Decreto No. 141, publicado en el Periódico\nOficial No. 18, Sección I, de fecha 4 de mayo de 1998, Tomo CV, expedido por la H. XV\nLegislatura, siendo Gobernador Constitucional del Estado, el C. Lic. Héctor Terán Terán, 1995-2001; fue reformado por Decreto No. 157, publicado en el Periódico Oficial No. 57 de fecha 19 de noviembre de 2008, Tomo CXV, Número Especial, expedido por la H. XIX\nLegislatura siendo Gobernador Constitucional el C. José Guadalupe Osuna Millán 20072013, fue derogado por Decreto No. 290, publicado en el Periódico Oficial No. 28, de fecha\nGobernador Constitucional el C. Francisco Arturo Vega de Lamadrid 2013-2019;\nARTICULO 268.- Fue adicionado por Decreto No. 141, publicado en el Periódico\nLegislatura, siendo Gobernador Constitucional del Estado, el C. Lic. Héctor Terán Terán, 1995-2001; fue reformado por Decreto No. 157, publicado en el Periódico Oficial No. 57 de\nLegislatura siendo Gobernador Constitucional el C. José Guadalupe Osuna Millán 20072013, fue reformado por Decreto No. 293, publicado en el Periódico Oficial No. 48, de fecha\nConstitucional el C. Eugenio Elorduy Walther 2001-2007; fue derogado por Decreto No. 290, CXXII, expedido por la H. XXI Legislatura, siendo Gobernador Constitucional el C. Francisco\nArturo Vega de Lamadrid 2013-2019;\nARTICULO 269.- Fue adicionado por Decreto No. 141, publicado en el Periódico\nOficial No. 18, Sección I, de fecha 4 de mayo de 1998, Tomo CV, expedido por la H. XV\nLegislatura, siendo Gobernador Constitucional del Estado, el C. Lic. Héctor Terán Terán, 1995-2001; fue reformado por Decreto No. 157, publicado en el Periódico Oficial No. 57 de fecha 19 de noviembre de 2008, Tomo CXV, Número Especial, expedido por la H. XIX\nLegislatura siendo Gobernador Constitucional el C. José Guadalupe Osuna Millán 20072013, fue derogado por Decreto No. 290, publicado en el Periódico Oficial No. 28, de fecha\n12 de junio de 2015, Sección II, Tomo CXXII, expedido por la H. XXI Legislatura, siendo\nGobernador Constitucional el C. Francisco Arturo Vega de Lamadrid 2013-2019;\nARTICULO 270.- Fue adicionado por Decreto No. 141, publicado en el Periódico\nOficial No. 18, Sección I, de fecha 4 de mayo de 1998, Tomo CV, expedido por la H. XV\nLegislatura, siendo Gobernador Constitucional del Estado, el C. Lic. Héctor Terán Terán, 1995-2001; fue reformado por Decreto No. 157, publicado en el Periódico Oficial No. 57 de fecha 19 de noviembre de 2008, Tomo CXV, Número Especial, expedido por la H. XIX\nLegislatura siendo Gobernador Constitucional el C. José Guadalupe Osuna Millán 20072013, fue derogado por Decreto No. 290, publicado en el Periódico Oficial No. 28, de fecha\n12 de junio de 2015, Sección II, Tomo CXXII, expedido por la H. XXI Legislatura, siendo\nGobernador Constitucional el C. Francisco Arturo Vega de Lamadrid 2013-2019;\nARTICULO 271.- Fue adicionado por Decreto No. 141, publicado en el Periódico\nOficial No. 18, Sección I, de fecha 4 de mayo de 1998, Tomo CV, expedido por la H. XV\nLegislatura, siendo Gobernador Constitucional del Estado, el C. Lic. Héctor Terán Terán, 1995-2001; fue reformado por Decreto No. 157, publicado en el Periódico Oficial No. 57 de fecha 19 de noviembre de 2008, Tomo CXV, Número Especial, expedido por la H. XIX\nLegislatura siendo Gobernador Constitucional el C. José Guadalupe Osuna Millán 20072013, fue derogado por Decreto No. 290, publicado en el Periódico Oficial No. 28, de fecha\nGobernador Constitucional el C. Francisco Arturo Vega de Lamadrid 2013-2019;\nARTICULO 272.- Fue adicionado por Decreto No. 141, publicado en el Periódico\nLegislatura, siendo Gobernador Constitucional el C. Lic. Héctor Terán Terán, 1995-2001; fue derogado por Decreto No. 290, publicado en el Periódico Oficial No. 28, de fecha 12 de junio de 2015, Sección II, Tomo CXXII, expedido por la H. XXI Legislatura, siendo Gobernador\nConstitucional el C. Francisco Arturo Vega de Lamadrid 2013-2019;\nFue adicionado el Capítulo X, por Decreto No. 141, publicado en el Periódico Oficial No. 18, Gobernador Constitucional del Estado, el C. Lic. Héctor Terán Terán, 1995-2001;\nCAPITULO X\nDE LAS RESPONSABILIDADES, IMPEDIMENTOS\nY EXCUSAS\nARTICULO 273.- Fue adicionado por Decreto No. 141, publicado en el Periódico\nOficial No. 18, Sección I, de fecha 4 de mayo de 1998, Tomo CV, expedido por la H. XV\nLegislatura, siendo Gobernador Constitucional del Estado, el C. Lic. Héctor Terán Terán, 1995-2001; fue derogado por Decreto No. 290, publicado en el Periódico Oficial No. 28, de fecha 12 de junio de 2015, Sección II, Tomo CXXII, expedido por la H. XXI Legislatura, siendo Gobernador Constitucional el C. Francisco Arturo Vega de Lamadrid 2013-2019;\nARTICULO 274.- Fue adicionado por Decreto No. 141, publicado en el Periódico\nOficial No. 18, Sección I, de fecha 4 de mayo de 1998, Tomo CV, expedido por la H. XV\nLegislatura, siendo Gobernador Constitucional del Estado, el C. Lic. Héctor Terán Terán, 1995-2001; fue reformado por Decreto No. 157, publicado en el Periódico Oficial No. 57 de fecha 19 de noviembre de 2008, Tomo CXV, Número Especial, expedido por la H. XIX\nLegislatura siendo Gobernador Constitucional el C. José Guadalupe Osuna Millán 20072013, fue derogado por Decreto No. 290, publicado en el Periódico Oficial No. 28, de fecha\n12 de junio de 2015, Sección II, Tomo CXXII, expedido por la H. XXI Legislatura, siendo\nGobernador Constitucional el C. Francisco Arturo Vega de Lamadrid 2013-2019;\nFue adicionado el Capítulo XI, por Decreto No. 141, publicado en el Periódico Oficial No. 18,\nSección I, de fecha 4 de mayo de 1998, Tomo CV, expedido por la H. XV Legislatura, siendo\nGobernador Constitucional del Estado, el C. Lic. Héctor Terán Terán, 1995-2001;\nCAPITULO XI\nDE LAS RELACIONES DE TRABAJO DE LOS\nSERVIDORES PUBLICOS\nARTICULO 275.- Fue adicionado por Decreto No. 141, publicado en el Periódico\nOficial No. 18, Sección I, de fecha 4 de mayo de 1998, Tomo CV, expedido por la H. XV\nLegislatura, siendo Gobernador Constitucional del Estado, el C. Lic. Héctor Terán Terán, 1995-2001; fue derogado por Decreto No. 290, publicado en el Periódico Oficial No. 28, de siendo Gobernador Constitucional el C. Francisco Arturo Vega de Lamadrid 2013-2019;\nARTICULO 276.- Fue adicionado por Decreto No. 141, publicado en el Periódico\nLegislatura, siendo Gobernador Constitucional del Estado, el C. Lic. Héctor Terán Terán, 1995-2001; fue derogado por Decreto No. 290, publicado en el Periódico Oficial No. 28, de siendo Gobernador Constitucional el C. Francisco Arturo Vega de Lamadrid 2013-2019;\nARTICULO 277.- Fue adicionado por Decreto No. 141, publicado en el Periódico\nLegislatura, siendo Gobernador Constitucional del Estado, el C. Lic. Héctor Terán Terán, 1995-2001; fue derogado por Decreto No. 290, publicado en el Periódico Oficial No. 28, de siendo Gobernador Constitucional el C. Francisco Arturo Vega de Lamadrid 2013-2019;\nFue adicionado el Capítulo XII, por Decreto No. 141, publicado en el Periódico Oficial\nNo. 18, Sección I, de fecha 4 de mayo de 1998, Tomo CV, expedido por la H. XV\nLegislatura, siendo Gobernador Constitucional del Estado, el C. Lic. Héctor Terán Terán, 1995-2001;\nCAPITULO XII\nDE LAS RENUNCIAS, AUSENCIAS Y LICENCIAS\nARTICULO 278.- Fue adicionado por Decreto No. 141, publicado en el Periódico\nOficial No. 18, Sección I, de fecha 4 de mayo de 1998, Tomo CV, expedido por la H. XV\nLegislatura, siendo Gobernador Constitucional del Estado, el C. Lic. Héctor Terán Terán, 1995-2001; fue derogado por Decreto No. 290, publicado en el Periódico Oficial No. 28, de fecha 12 de junio de 2015, Sección II, Tomo CXXII, expedido por la H. XXI Legislatura, siendo Gobernador Constitucional el C. Francisco Arturo Vega de Lamadrid 2013-2019;\nARTICULO 279.- Fue adicionado por Decreto No. 141, publicado en el Periódico\nOficial No. 18, Sección I, de fecha 4 de mayo de 1998, Tomo CV, expedido por la H. XV\nLegislatura, siendo Gobernador Constitucional del Estado, el C. Lic. Héctor Terán Terán, 1995-2001; fue derogado por Decreto No. 290, publicado en el Periódico Oficial No. 28, de fecha 12 de junio de 2015, Sección II, Tomo CXXII, expedido por la H. XXI Legislatura, siendo Gobernador Constitucional el C. Francisco Arturo Vega de Lamadrid 2013-2019;\nARTICULO 280.- Fue adicionado por Decreto No. 141, publicado en el Periódico\nOficial No. 18, Sección I, de fecha 4 de mayo de 1998, Tomo CV, expedido por la H. XV\nLegislatura, siendo Gobernador Constitucional del Estado, el C. Lic. Héctor Terán, 19952001; fue derogado por Decreto No. 290, publicado en el Periódico Oficial No. 28, de fecha\n12 de junio de 2015, Sección II, Tomo CXXII, expedido por la H. XXI Legislatura, siendo\nGobernador Constitucional el C. Francisco Arturo Vega de Lamadrid 2013-2019;\nARTICULO 281.- Fue adicionado por Decreto No. 141, publicado en el Periódico\nLegislatura, siendo Gobernador Constitucional del Estado, el C. Lic. Héctor Terán, 19952001; fue derogado por Decreto No. 290, publicado en el Periódico Oficial No. 28, de fecha\nGobernador Constitucional el C. Francisco Arturo Vega de Lamadrid 2013-2019;\nARTICULO 282.- Fue adicionado por Decreto No. 141, publicado en el Periódico\nLegislatura, siendo Gobernador Constitucional del Estado, el C. Lic. Héctor Terán, 19952001; fue derogado por Decreto No. 290, publicado en el Periódico Oficial No. 28, de fecha\nGobernador Constitucional el C. Francisco Arturo Vega de Lamadrid 2013-2019;\nARTICULO 283.- Fue adicionado por Decreto No. 141, publicado en el Periódico\nOficial No. 18, Sección I, de fecha 4 de mayo de 1998, Tomo CV, expedido por la H. XV\nLegislatura, siendo Gobernador Constitucional del Estado, el C. Lic. Héctor Terán, 19952001; fue derogado por Decreto No. 290, publicado en el Periódico Oficial No. 28, de fecha\n12 de junio de 2015, Sección II, Tomo CXXII, expedido por la H. XXI Legislatura, siendo\nGobernador Constitucional el C. Francisco Arturo Vega de Lamadrid 2013-2019;\nARTICULO 284.- Fue adicionado por Decreto No. 141, publicado en el Periódico\nOficial No. 18, Sección I, de fecha 4 de mayo de 1998, Tomo CV, expedido por la H. XV\nLegislatura, siendo Gobernador Constitucional del Estado, el C. Lic. Héctor Terán, 19952001; fue derogado por Decreto No. 290, publicado en el Periódico Oficial No. 28, de fecha\n12 de junio de 2015, Sección II, Tomo CXXII, expedido por la H. XXI Legislatura, siendo\nGobernador Constitucional el C. Francisco Arturo Vega de Lamadrid 2013-2019;\nARTICULO 285.- Fue adicionado por Decreto No. 141, publicado en el Periódico\nOficial No. 18, Sección I, de fecha 4 de mayo de 1998, Tomo CV, expedido por la H. XV\nLegislatura, siendo Gobernador Constitucional del Estado, el C. Lic. Héctor Terán, 19952001; fue derogado por Decreto No. 290, publicado en el Periódico Oficial No. 28, de fecha\n12 de junio de 2015, Sección II, Tomo CXXII, expedido por la H. XXI Legislatura, siendo\nGobernador Constitucional el C. Francisco Arturo Vega de Lamadrid 2013-2019;\nARTICULO 286.- Fue adicionado por Decreto No. 141, publicado en el Periódico\nOficial No. 18, Sección I, de fecha 4 de mayo de 1998, Tomo CV, expedido por la H. XV\nLegislatura, siendo Gobernador Constitucional del Estado, el C. Lic. Héctor Terán, 19952001; fue derogado por Decreto No. 290, publicado en el Periódico Oficial No. 28, de fecha\n12 de junio de 2015, Sección II, Tomo CXXII, expedido por la H. XXI Legislatura, siendo\nGobernador Constitucional el C. Francisco Arturo Vega de Lamadrid 2013-2019;\nFue adicionado el Capítulo XIII, por Decreto No. 141, publicado en el Periódico Oficial\nNo. 18, Sección I, de fecha 4 de mayo de 1998, Tomo CV, expedido por la H. XV\nLegislatura, siendo Gobernador Constitucional del Estado, el C. Lic. Héctor Terán, 19952001;\nCAPITULO XIII\nDEL ARCHIVO JURISDICCIONAL\nARTICULO 287.- Fue adicionado por Decreto No. 141, publicado en el Periódico\nLegislatura, siendo Gobernador Constitucional del Estado, el C. Lic. Héctor Terán, 19952001; fue derogado por Decreto No. 290, publicado en el Periódico Oficial No. 28, de fecha\nGobernador Constitucional el C. Francisco Arturo Vega de Lamadrid 2013-2019;\nARTICULO 288.- Fue adicionado por Decreto No. 141, publicado en el Periódico\nLegislatura, siendo Gobernador Constitucional del Estado, el C. Lic. Héctor Terán, 19952001; fue derogado por Decreto No. 290, publicado en el Periódico Oficial No. 28, de fecha\nGobernador Constitucional el C. Francisco Arturo Vega de Lamadrid 2013-2019;\nFue adicionado el Capítulo XIV, por Decreto No. 141, publicado en el Periódico Oficial No.\n18, Sección I, de fecha 4 de mayo de 1998, Tomo CV, expedido por la H. XV Legislatura, siendo Gobernador Constitucional del Estado, el C. Lic. Héctor Terán, 1995-2001;\nCAPITULO XIV\nDE LOS CRITERIOS OBLIGATORIOS\nARTICULO 289.- Fue adicionado por Decreto No. 141, publicado en el Periódico\nOficial No. 18, Sección I, de fecha 4 de mayo de 1998, Tomo CV, expedido por la H. XV\nLegislatura, siendo Gobernador Constitucional del Estado, el C. Lic. Héctor Terán, 19952001; fue derogado por Decreto No. 290, publicado en el Periódico Oficial No. 28, de fecha\n12 de junio de 2015, Sección II, Tomo CXXII, expedido por la H. XXI Legislatura, siendo\nGobernador Constitucional el C. Francisco Arturo Vega de Lamadrid 2013-2019;\nFue adicionado el Capítulo XV, por Decreto No. 141, publicado en el Periódico Oficial No.\n18, Sección I, de fecha 4 de mayo de 1998, Tomo CV, expedido por la H. XV Legislatura, siendo Gobernador Constitucional del Estado, el C. Lic. Héctor Terán, 1995-2001;\nCAPITULO XV\nDE LA PROTESTA CONSTITUCIONAL\nARTICULO 290.- Fue adicionado por Decreto No. 141, publicado en el Periódico\nOficial No. 18, Sección I, de fecha 4 de mayo de 1998, Tomo CV, expedido por la H. XV\nLegislatura, siendo Gobernador Constitucional del Estado, el C. Lic. Héctor Terán, 19952001; fue derogado por Decreto No. 290, publicado en el Periódico Oficial No. 28, de fecha\n12 de junio de 2015, Sección II, Tomo CXXII, expedido por la H. XXI Legislatura, siendo\nGobernador Constitucional el C. Francisco Arturo Vega de Lamadrid 2013-2019;\nFue adicionado el Capítulo XVI, por Decreto No. 141, publicado en el Periódico Oficial No.\n18, Sección I, de fecha 4 de mayo de 1998, Tomo CV, expedido por la H. XV Legislatura, siendo Gobernador Constitucional del Estado, el C. Lic. Héctor Terán Terán, 1995-2001;\nCAPITULO XVI\nARTICULO 291.- Fue adicionado por Decreto No. 141, publicado en el Periódico\nLegislatura, siendo Gobernador Constitucional del Estado, el C. Lic. Héctor Terán Terán, 1995-2001; fue derogado por Decreto No. 290, publicado en el Periódico Oficial No. 28, de siendo Gobernador Constitucional el C. Francisco Arturo Vega de Lamadrid 2013-2019;\nARTICULO 292.-Fue adicionado por Decreto No. 141, publicado en el Periódico\nLegislatura, siendo Gobernador Constitucional del Estado, el C. Lic. Héctor Terán Terán, 1995-2001; fue derogado por Decreto No. 290, publicado en el Periódico Oficial No. 28, de fecha 12 de junio de 2015, Sección II, Tomo CXXII, expedido por la H. XXI Legislatura, siendo Gobernador Constitucional el C. Francisco Arturo Vega de Lamadrid 2013-2019;\nFue adicionado por Decreto No. 334, publicado en el Periódico Oficial No. 17, de fecha 12 de abril de 2019, Índice, Tomo CXXVI, expedido por la H. XXII Legislatura, siendo\nGobernador Constitucional el C. Francisco Arturo Vega de Lamadrid 2013-2019;\nTÍTULO DÉCIMO QUINTO\nFue adicionado por Decreto No. 334, publicado en el Periódico Oficial No. 17, de fecha 12 de abril de 2019, Índice, Tomo CXXVI, expedido por la H. XXII Legislatura, siendo\nGobernador Constitucional el C. Francisco Arturo Vega de Lamadrid 2013-2019;\nCAPÍTULO ÚNICO\nDEL HABER DE RETIRO\nARTÍCULO 293.- Fue adicionado por Decreto No. 334, publicado en el Periódico\nOficial No. 17, de fecha 12 de abril de 2019, Índice, Tomo CXXVI, expedido por la H. XXII\nLegislatura, siendo Gobernador Constitucional el C. Francisco Arturo Vega de Lamadrid\n2013-2019;\nARTÍCULO 294.- Fue adicionado por Decreto No. 03, publicado en el Periódico Oficial\nNo. 61, de fecha 13 de diciembre de 2019, Sección III, Tomo CXXVI, expedido por la H.\nXXIII Legislatura, siendo Gobernador Constitucional el C. Jaime Bonilla Valdez 2019-2021; fue invalidado este artículo por Sentencia de Controversia Constitucional 35/2020, notificada al Congreso del Estado el día 17 de noviembre de 2022, mediante la cual se declara la invalidez del decreto 03 por el que se reformó la Ley Orgánica del Poder Judicial del Estado de Baja California para crear un artículo 294, publicado en el Periódico Oficial del Estado el\n2021; fue reformado por Decreto No. 293, publicado en el Periódico Oficial No. 55, Índice, de\nGobernadora Constitucional la C. Marina del Pilar Ávila Olmeda 2021-2027;\nARTICULO SEXTO TRANSITORIO.- Fue reformado por Decreto No. 440, publicado expedido por la H. XIX Legislatura, siendo Gobernador Constitucional el C. José Guadalupe\nOsuna Millán 2007-2013;\nARTÍCULOS TRANSITORIOS DEL DECRETO No. 85, POR EL QUE SE\nREFORMAN Y ADICIONAN LOS ARTÍCULOS 175, 195 Y 196 DEL CAPÍTULO XI, TÍTULO\nBAJA CALIFORNIA, PUBLICADO EN EL PERIÓDICO OFICIAL No. 21, SECCION I, DE\nSIENDO GOBERNADOR CONSTITUCIONAL DEL ESTADO EL C. LIC. HÉCTOR TERAN\nTERAN, 1995-2001.\nARTÍCULOS TRANSITORIOS\nPRIMERO.- El Presente decreto entrará en vigor el día siguiente de su publicación en el Periódico Oficial, Organo del Gobierno del Estado de Baja California.\nSEGUNDO.- Se deroga la fracción VI del artículo 72 de la Ley de Responsabilidades de los Servidores Públicos del Estado de Baja California, así como todas las disposiciones vigentes que se opongan y contravengan el contenido del presente decreto.\nTERCERO.- El Consejo de la Judicatura y la Dirección de Control y Evaluación\nGubernamental, en un plazo no mayor de 30 días, contados a partir de la fecha de publicación del presente decreto, establecerán los mecanismos y plazos para que le sean entregados a la Contraloría del Poder Judicial, los expedientes con las declaraciones de\nSituación Patrimonial de los servidores públicos obligados del Poder Judicial del Estado, así como, las reglas de coordinación en materia de inhabilitación.\nCUARTO.- La Unidad Administrativa denominada Contraloría del Poder Judicial empezará a ejercer sus funciones una vez que se incluya en el presupuesto que corresponda en los términos de ley.\nLegislativo, en la Ciudad de Mexicali, Baja California, a los quince días del mes de mayo de mil novecientos noventa y siete.\nLIC. SALVADOR MORALES RIUBI\nDIPUTADO PRESIDENTE\nRÚBRICA\nING. MIGUEL ANGEL BARRAZA CHIQUETE\nDIPUTADO SECRETARIO\nRÚBRICA\nMEXICALI, BAJA CALIFORNIA, A LOS VEINTIUN DÍAS DEL MES DE MAYO DE\nMIL NOVECIENTOS NOVENTA Y SIETE.\nEL GOBERNADOR CONSTITUCIONAL DEL ESTADO.\nHÉCTOR TERAN TERAN\nRÚBRICA\nEL SECRETARIO GENERAL DE GOBIERNO.\nLIC. RODOLFO VALDEZ GUTIERREZ\nRÚBRICA.\nARTICULOS TRANSITORIOS DEL DECRETO No. 141, POR EL QUE SE\nREFORMAN LOS ARTICULOS 1, 2, 3, 7, 21, 23, 24, 25, 29, 39, 44, 64, 91, 92, 93, 156, 161,\n168, 172, 183, 207, SE ADICIONA EL TITULO DECIMO CUARTO, CAPITULO I,\nARTICULOS 244, 245, 246, CAPITULO II, ARTICULOS 247, 248, 249, 250, 251, CAPITULO\nIII, ARTICULOS 252, 253, CAPITULO IV, ARTICULOS 254, 255, 256, 257, CAPITULO V,\nARTICULOS 258, CAPITULO VI, ARTICULOS 259, 260, 261, 262, 263, CAPITULO VII,\nARTICULO 264, CAPITULO VIII, ARTICULOS 265, 266, CAPITULO IX, ARTICULOS 267,\n268, 269, 270, 271, 272, CAPITULO X, ARTICULOS 273, 274, CAPITULO XI, ARTICULOS\n275, 276, 277, CAPITULO XII, ARTICULOS 278, 279, 280, 281, 282, 283, 284, 285, 286,\nCAPITULO XIII, ARTICULOS 287, 288, CAPITULO XIV, ARTICULO 289, CAPITULO XV,\nARTICULO 290, CAPITULO XVI, ARTICULOS 291, 292 Y SE MODIFICAN LAS\nDENOMINACIONES DE LOS TITULOS SEPTIMO, OCTAVO Y DECIMOSEGUNDO,\nPUBLICADO EN EL PERIODICO OFICIAL No. 18, SECCION I, DE FECHA 4 DE MAYO DE\n1998, TOMO CV, EXPEDIDO POR LA H. XV LEGISLATURA, SIENDO GOBERNADOR\nCONSTITUCIONAL DEL ESTADO, EL C. LIC. HECTOR TERAN TERAN, 1995-2001.\nARTÍCULOS TRANSITORIOS\nPRIMERO.- Las reformas a esta Ley, entrarán en vigor el día de la publicación del presente Decreto en el Periódico Oficial, Organo del Gobierno del Estado.\nSEGUNDO.- Por esta ocasión, la incorporación del Presidente del Tribunal de Justicia\nElectoral al Consejo de la Judicatura del Estado, contemplada en las reformas efectuadas a después de concluido el proceso electoral de 1998.\nTERCERO.- El Consejo de la Judicatura del Estado designará a los dos comisionados a que se refiere el Artículo 259 de esta Ley, en un plazo de quince días naturales a partir de la instalación del Tribunal de Justicia Electoral.\nCUARTO.- La Comisión de Administración del Tribunal de Justicia Electoral del Poder\nJudicial, deberá quedar integrada para que ejerza sus funciones, a más tardar la última\nQUINTO.- En tanto se integra la Comisión de Administración y ejerza sus facultades, medidas que competan a dicha Comisión.\nSEXTO.- El personal Jurídico que presta actualmente sus servicios en el Tribunal de\nJusticia Electoral, continuará en sus cargos, a excepción de los jueces instructores; de la misma forma seguirá prestando sus servicios el actual personal administrativo, estando sujetos al régimen laboral establecido en el presente Decreto.\nSEPTIMO.- Las unidades y órganos con que actualmente cuenta el Tribunal de\nJusticia Electoral, seguirán funcionando hasta en tanto se integra el Tribunal Electoral del conforme a los preceptos que se establecen en el presente Decreto.\nOCTAVO.- Las fracciones XXIX del Artículo 253 y IX del Artículo 262 de esta Ley, entrarán en vigor para el ejercicio presupuestal de 1999. Para el ejercicio de 1998, de conformidad con las leyes de la materia, el Tribunal de Justicia Electoral, presentará y aplicará el presupuesto que se programe para el Tribunal de Justicia Electoral del Poder\nJudicial del Estado, con las modificaciones que se requieran para su nueva estructura y funciones.\nNOVENO.- La totalidad de los bienes muebles e inmuebles destinados al Tribunal de\nJusticia Electoral, quedarán destinados al Tribunal de Justicia Electoral del Poder Judicial del\nEstado, a fin de garantizar su adecuado funcionamiento.\nDECIMO.- Si a la entrada en vigor de este Decreto se encuentra en trámite algún medio de impugnación ante el Tribunal de Justicia Electoral, será resuelto conforme a las normas vigentes al momento de su interposición.\nDECIMO PRIMERO.- El Reglamento Interior del Tribunal de Justicia Electoral del\nPoder Judicial del Estado, deberá ser expedido a más tardar el día último del mes de Marzo de 1998.\nLegislativo, en la Ciudad de Mexicali, Baja California, a los veintinueve días del mes de enero de mil novecientos noventa y ocho.\nLIC. JAVIER JULIAN CASTAÑEDA POMPOSO\nDIPUTADO PRESIDENTE\n(RÚBRICA)\nPROFR. ROGELIO APPEL CHACON\nDIPUTADO SECRETARIO\n(RÚBRICA)\nDE CONFORMIDAD CON LO DISPUESTO POR LA FRACCIÓN I DEL ARTÍCULO 49\nDE LA CONSTITUCIÓN POLITICA DEL ESTADO, MANDO SE IMPRÍMA Y PUBLÍQUE.\nMEXICALI, BAJA CALIFORNIA, A LOS DIECISIETE DÍAS DEL MES DE ABRIL DE\nMIL NOVECIENTOS NOVENTA Y OCHO.\nEL GOBERNADOR CONSTITUCIONAL DEL ESTADO.\nHÉCTOR TERAN TERAN\n(RÚBRICA).\nEL SECRETARIO GENERAL DE GOBIERNO\nRODOLFO VALDEZ GUTIERREZ\n(RÚBRICA).\nARTÍCULOS TRANSITORIOS DEL DECRETO No. 187, MEDIANTE EL CUAL SE\nREFORMAN LOS ARTÍCULOS 1, 2, 21, 31, 157, 160 Y 162, PUBLICADO EN EL\nPERIÓDICO OFICIAL No. 35, SECCIÓN I, DE FECHA 28 DE AGOSTO DE MIL\nNOVECIENTOS NOVENTA Y OCHO, EXPEDIDO POR LA H. XV LEGISLATURA\nCONSTITUCIONAL, SIENDO GOBERNADOR DEL ESTADO EL LIC. HÉCTOR TERAN\nTERAN, 1995-2001.\nARTICULO PRIMERO.- Las presentes reformas entrarán en vigor al día siguiente de su publicación en el Periódico Oficial del Estado.\nARTICULO SEGUNDO.- En un plazo de treinta días siguientes a la entrada en vigor, el Poder Judicial del Estado, deberá adecuar el marco jurídico interior reglamentario de su órganos jurisdiccionales y administrativos.\nARTICULO TERCERO.- El Poder Judicial del Estado de Baja California, dictará las medidas correspondientes para la organización permanente e ininterrumpida de los juzgados, en un plazo que no exceda de ciento ochenta días contados a partir de la entrada en vigor de la presente adición.\nARTICULO CUARTO.- El Poder Judicial del Estado de Baja California, dictará las medidas correspondientes para la organización permanente e ininterrumpida de los juzgados, en un plazo que no exceda de ciento veinte días, contados a partir del vencimiento del plazo establecido en el Artículo Transitorio Tercero del Decreto No. 13 de fecha 4 de diciembre de 1998.\nDADO en el Salón de Sesiones Lic. Benito Juárez García del Honorable Poder\nLegislativo, en la Ciudad de Mexicali, Baja California, a los veintitrés días del mes de julio de mil novecientos noventa y ocho.\nM.V.Z. JOSE MANUEL SALCEDO SAÑUDO\nDIPUTADO PRESIDENTE\n(RÚBRICA).\nC.P. JUAN PABLO VALENZUELA GARCIA\nDIPUTADO SECRETARIO\n(RÚBRICA).\nDE CONFORMIDAD CON LO DISPUESTO POR LA FRACCIÓN I DEL ARTÍCULO 49\nMEXICALI, BAJA CALIFORNIA, A LOS CINCO DÍAS DEL MES DE AGOSTO DE MIL\nNOVECIENTOS NOVENTA Y OCHO.\nEL GOBERNADOR CONSTITUCIONAL DEL ESTADO.\nHÉCTOR TERAN TERAN.\n(RÚBRICA).\nEL SECRETARIO GENERAL DE GOBIERNO.\nRODOLFO VALDEZ GUTIERREZ.\n(RÚBRICA).\nARTÍCULO TRANSITORIO DEL DECRETO No. 13, POR EL CUAL SE REFORMAN\nLOS ARTÍCULOS TRANSITORIOS DEL DECRETO No. 187, ADICIONANDOSE UN\nARTÍCULO TERCERO, PUBLICADO EN EL PERIÓDICO OFICIAL No. 49, DE FECHA 04\nDE DICIEMBRE DE 1998, TOMO CV, EXPEDIDO POR LA HONORABLE XVI\nLEGISLATURA, SIENDO GOBERNADOR CONSTITUCIONAL EL C. LIC. ALEJANDRO\nGONZALEZ ALCOCER; OCTUBRE DE 1998-2001.\nUNICO.- La presente adición entrará en vigor el día de su publicación en el Periódico\nOficial del Estado.\nLegislativo, en la Ciudad de Mexicali, Baja California, a los veintiséis días del mes de noviembre de mil novecientos noventa y ocho.\nLIC. EDGAR FERNANDEZ BUSTAMANTE\nDIPUTADO PRESIDENTE\nRÚBRICA\nDR. EFREN MACIAS LEZAMA\nDIPUTADO SECRETARIO\nRÚBRICA\nDE CONFORMIDAD CON LO DISPUESTO POR LA FRACCIÓN I DEL ARTÍCULO 49\nDE LA CONSTITUCION POLÍTICA DEL ESTADO, MANDO SE IMPRÍMA Y PUBLÍQUE.\nMEXICALI, BAJA CALIFORNIA, A LOS CUATRO DÍAS DEL MES DE DICIEMBRE\nDE MIL NOVECIENTOS NOVENTAY OCHO.\nEL GOBERNADOR CONSTITUCIONAL DEL ESTADO.\nLIC. ALEJANDRO GONZALEZ ALCOCER\nRÚBRICA\nEL SECRETARIO GENERAL DE GOBIERNO\nC.P. JORGE RAMOS\nRÚBRICA\nARTÍCULO ÚNICO TRANSITORIO DEL DECRETO No. 90, POR EL QUE SE\nADICIONA UN ARTÍCULO CUARTO TRANSITORIO AL DECRETO No. 187, PUBLICADO\nCVI, EXPEDIDO POR LA H. XVI LEGISLATURA, SIENDO GOBERNADOR\nCONSTITUCIONAL EL C. LIC. ALEJANDRO GONZALEZ ALCOCER 7 DE OCTUBRE DE\n1998-2001.\nUNICO.- El presente Decreto entrará en vigor el día de su publicación en el Periódico\nOficial del Estado de Baja California.\nDADO.- En el Salón de Sesiones “Lic. Benito Juárez García”, del Honorable Poder\nLegislativo, en la Ciudad de Mexicali, Baja California, a los doce días del mes de agosto de mil novecientos noventa y nueve.\nING. MANUEL A. RAMOS RUBIO\nDIPUTADO PRESIDENTE\nRÚBRICA\nC. ALEJANDRO PEDRIN MARQUEZ\nDIPUTADO SECRETARIO\nRÚBRICA\nDE CONFORMIDAD CON LO DISPUESTO POR LA FRACCIÓN I DEL ARTÍCULO 49\nDE LA CONSTITUCION POLÍTICA DEL ESTADO, MANDO SE IMPRÍMA Y PUBLÍQUE.\nMEXICALI, BAJA CALIFORNIA, AL PRIMER DÍA DEL MES DE SEPTIEMBRE DE\nMIL NOVECIENTOS NOVENTA Y NUEVE.\nEL GOBERNADOR CONSTITUCIONAL DEL ESTADO\nLIC. ALEJANDRO GONZALEZ ALCOCER\nRÚBRICA\nEL SECRETARIO GENERAL DE GOBIERNO\nC.P. JORGE RAMOS\nRÚBRICA\nARTÍCULO SEGUNDO TRANSITORIO DEL DECRETO NO. 115, POR EL QUE SE\nREFORMAN LOS ARTÍCULOS 255 Y 256, PUBLICADO EN EL PERIÓDICO OFICIAL NO.\nLEGISLATURA, SIENDO GOBERNADOR CONSTITUCIONAL EL C. EUGENIO ELORDUY\nWALTHER 2001-2007.\nUNICO.- Las presentes reformas entrarán en vigor al día siguiente de su publicación en el Periódico Oficial del Estado de Baja California.\nDADO en el Salón de Sesiones “Lic. Benito Juárez García” del Honorable Poder\nLegislativo en la Ciudad de Mexicali, Capital del Estado de Baja California a los cinco días del mes de septiembre del año dos mil dos.\nDIP. MARIA ROSALBA MARTIN NAVARRO\nPRESIDENTA\nRÚBRICA\nDIP. JUAN MANUEL SALAZAR CASTRO\nSECRETARIO\nRÚBRICA\nDE CONFORMIDAD CON LO DISPUESTO POR LA FRACCIÓN I DEL ARTÍCULO 49\nDE LA CONSTITUCION POLÍTICA DEL ESTADO, MANDO SE IMPRÍMA Y PUBLÍQUE.\nMEXICALI, BAJA CALIFORNIA, A LOS VEINTISIETE DÍAS DEL MES DE\nDICIEMBRE DEL AÑO DOS MIL DOS.\nGOBERNADOR DEL ESTADO\nEUGENIO ELORDUY WALTHER.\nRÚBRICA\nSECRETARIO GENERAL DE GOBIERNO\nBERNARDO H. MARTINEZ AGUIRRE.\nRÚBRICA\nARTÍCULO ÚNICO TRANSITORIO DEL DECRETO NO. 212, PUBLICADO EN EL\nPERIÓDICO OFICIAL NO. 47, DE FECHA 17 DE OCTUBRE DE 2003, TOMO CX, POR EL\nQUE SE REFORMA LOS ARTÍCULOS 254 Y 255, EXPEDIDO POR LA H. XVII\nLEGISLATURA, SIENDO GOBERNADOR CONSTICUIONAL EL C. EUGENIO ELORDUY\nWALTHER 2001-2007.\nUNICO.- Las presentes reformas entrarán en vigor al día siguiente al de su publicación en el Periódico Oficial del Estado de Baja California.\nDADO.- En el Salón de Sesiones “Lic. Benito Juárez García”del Honorable Poder\nLegislativo, en la Ciudad de Mexicali, Baja California, a los diecisiete días del mes de septiembre del año dos mil tres.\nDIP. HECTOR EDGARDO SUAREZ CORDOVA\nPRESIDENTE\nRÚBRICA\nDIP. RAQUEL AVILES MUÑOZ\nSECRETARIO\nRÚBRICA\nDE CONFORMIDAD CON LO DISPUESTO POR LA FRACCIÓN I DEL ARTÍCULO 49\nDE LA CONSTITUCION POLÍTICA DEL ESTADO, MANDO SE IMPRÍMASE Y\nPUBLÍQUESE.\nMEXICALI, BAJA CALIFORNIA, A LOS VEINTITRES DÍAS DEL MES DE\nSEPTIEMBRE DEL AÑO DOS MIL TRES.\nGOBERNADOR DEL ESTADO\nEUGENIO ELORDUY WALTHER.\nRÚBRICA\nSECRETARIO GENERAL DE GOBIERNO\nBERNARDO H. MARTINEZ AGUIRRE.\nRÚBRICA\nFE DE ERRATAS AL DECRETO NO. 212, RELATIVO A LA REFORMA A LOS\nARTÍCULOS 254 Y 255, PUBLICADO EN EL PERIÓDICO OFICIAL NO. 51, DE FECHA 07\nDE NOVIEMBRE DE 2003, TOMO CX, EXPEDIDA POR LA H. XVII LEGISLATURA,\nSIENDO GOBERNADOR CONSTITUCIONAL EL C. EUGENIO ELORDUY WALTHER 2001-\n2007.\nATENTAMENTE\nSUFRAGIO EFECTIVO. NO REELECCION\nMexicali, Baja California, a 27 de octubre del 2003.\nDIP. LEOPOLDO MORAN DIAZ\nPRESIDENTE\nRÚBRICA\nDIP. EVERARDO RAMOS GARCIA\nSECRETARIO\nRÚBRICA\nARTÍCULO ÚNICO TRANSITORIO DEL DECRETO NO. 239, POR EL QUE SE\nREFORMA EL ARTÍCULO 249, PUBLICADO EN EL PERIÓDICO OFICIAL NO. 52, DE\nFECHA 14 DE NOVIEMBRE DE 2003, SECCIÓN II, TOMO CX, EXPEDIDO POR LA H. XVII\nLEGISLATURA, SIENDO GOBERNADOR CONSTITUCIONAL EL C. EUGENIO ELORDUY\nWALTHER 2001-2007.\nPRIMERO.- Las presentes reformas y adiciones entraran en vigor el día de su plazo de 15 días, contados a partir de la entrada en vigor de la presente reforma, a efecto de que realice las adecuaciones correspondientes, a su reglamento interior.\nDADO.- En el Salón de Sesiones “Lic. Benito Juárez García” del Honorable Poder\nLegislativo, en la Ciudad de Mexicali, Baja California, a los trece días del mes de noviembre del año dos mil tres.\nDIP. LEOPOLDO MORAN DIAZ\nPRESIDENTE\nRUBRICA\nDIP. EVERARDO RAMOS GARCIA\nSECRETARIO\nRUBRICA\nDE CONFORMIDAD CON LO DISPUESTO POR EL FRACCION I DEL ARTICULO 49\nDE LA CONSTITUCION POLITICA DEL ESTADO, IMPRIMASE Y PUBLIQUESE.\nMEXICALI, BAJA CALIFORNIA, A LOS CATORCE DIAS DEL MES DE NOVIEMBRE\nDEL AÑO DOS MIL TRES.\nGOBERNADOR DEL ESTADO\nEUGENIO ELORDUY WALTHER\nRÚBRICA\nSECRETARIO GENERAL DE GOBIERNO\nBERNARDO H. MARTINEZ AGUIRRE\nRÚBRICA\nARTÍCULO ÚNICO TRANSITORIO DEL DECRETO NO. 126, POR EL QUE SE\nREFORMAN LOS ARTÍCULOS 156, 157, 161 Y 168, PUBLICADO EN EL PERIÓDICO\nOFICIAL NO. 48, DE FECHA 01 DE NOVIEMBRE DE 2005, TOMO CXII, EXPEDIDO POR\nLA H. XVIII LEGISLATURA, SIENDO GOBERNADOR CONSTITUCIONAL EL C. EUGENIO\nELORDUY WALTHER 2001-2007.\nARTÍCULOS TRANSITORIOS\nPRIMERO.- La presente reforma entrará en vigor el día de su publicación en el\nPeriódico Oficial del Estado de Baja California.\nSEGUNDO.- Hasta en tanto, se realicen las designaciones de los Consejeros de la\nJusticia, bastará con la presencia de dos Consejeros para sesionar.\nTERCERO.- El Pleno del Tribunal Superior de Justicia deberá publicar la convocatoria a que se refiere la fracción 1 del artículo 157 objeto de las presentes reformas, dentro de los tres días siguientes a la entrada en vigor del presente decreto.\nDADO.- En el salón de Sesiones “Lic. Benito Juárez García” del Honorable Poder\nLegislativo, en la Ciudad de Mexicali, Baja California, al primer día del mes de noviembre del año dos mil cinco.\nDIP. ELVIRA LUNA PINEDA\nPRESIDENTA\n(RÚBRICA)\nDIP. ELÍAS LÓPEZ MENDOZA\nSECRETARIO.\n(RÚBRICA)\nDE CONFORMIDAD CON LO DISPUESTO POR LA FRACCIÓN I DEL ARTÍCULO 49\nMEXICALI, BAJA CALIFORNIA, AL PRIMER DÍA DEL MES DE NOVIEMBRE DEL\nAÑO DOS MIL CINCO.\nGOBERNADOR DEL ESTADO\nEUGENIO ELORDUY WALTER\n(Rúbrica)\nSECRETARIO GENERAL DE GOBIERNO\nBERNARDO H. MARTINEZ AGUIRRE.\n(Rúbrica)\nARTÍCULO ÚNICO TRANSITORIO DEL DECRETO NO. 141, POR EL QUE SE\nADICIONA UN PARRAFO AL ARTÍCULO 156, PUBLICADO EN EL PERIÓDICO OFICIAL\nNO. 54, DE FECHA 29 DE NOVIEMBRE DE 2005, TOMO CXII, EXPEDIDO POR LA H.\nXVIII LEGISLATURA, SIENDO GOBERNADOR CONSTITUCIONAL EL C. EUGENIO\nELORDUY WALTHER 2001-2007.\nPRIMERO.- El presente Decreto entrará en vigor el día de su publicación en el\nPeriódico Oficial del Estado.\nSEGUNDO.- La presente reforma será aplicable a los Consejeros de la Judicatura que sustituyan a los que actualmente se encuentren en funciones.\nDADO en el Salón de Sesiones “Lic. Benito Juárez García” del H. Poder\nLegislativo del Estado de Baja California, en la Ciudad de Mexicali, B.C., a los veinticuatro días del mes de noviembre de dos mil cinco.\nDIP. ELVIRA LUNA PINEDA\nPRESIDENTA\n(RÚBRICA)\nDIP. ELÍAS LÓPEZ MENDOZA\nSECRETARIO.\n(RÚBRICA)\nDE CONFORMIDAD CON LO DISPUESTO POR LA FRACCIÓN I DEL ARTÍCULO 49\nMEXICALI, BAJA CALIFORNIA, A LOS VEINTICINCO DÍAS DEL MES DE\nNOVIEMBRE DEL AÑO DOS MIL CINCO.\nGOBERNADOR DEL ESTADO\nEUGENIO ELORDUY WALTER\n(RÚBRICA)\nSECRETARIO GENERAL DE GOBIERNO\nBERNARDO H. MARTINEZ AGUIRRE.\n(RÚBRICA)\nARTÍCULO ÚNICO TRANSITORIO DEL DECRETO NO. 203, POR EL QUE SE\nREFORMAN LOS ARTÍCULOS 157, 160 Y 163, PUBLICADO EN EL PERIÓDICO OFICIAL\nNO. 25, DE FECHA 16 DE JUNIO DE 2006, TOMO CXIII, EXPEDIDO POR LA H. XVIII\nLEGISLATURA, SIENDO GOBERNADOR CONSTITUCIONAL EL C. EUGENIO ELORDUY\nWALTHER 2001-2007.\nUNICO.- Las presentes reformas entrarán en vigor el día siguiente de su publicación en el Periódico Oficial del Estado de Baja California a los Consejeros de la\nJudicatura que sustituyan a los que actualmente se encuentren en funciones.\nDADO en el Salón de Sesiones “Lic. Benito Juárez García” del Honorable Poder\nLegislativo, en la Ciudad de Mexicali, Baja California, a los dieciocho días del mes de mayo del año dos mil seis.\nDIP. RENÉ ADRIÁN MENDÍVIL ACOSTA\nPRESIDENTE\n(RÚBRICA)\nDIP. CARLOS ALBERTO ASTORGA OTHÓN\nSECRETARIO.\n(RÚBRICA)\nDE CONFORMIDAD CON LO DISPUESTO POR LA FRACCIÓN I DEL ARTÍCULO 49\nMEXICALI, BAJA CALIFORNIA, A LOS VEINTINUEVE DÍAS DEL MES DE MAYO\nDEL AÑO DOS MIL SEIS.\nGOBERNADOR DEL ESTADO\nEUGENIO ELORDUY WALTER\n(RÚBRICA)\nSECRETARIO GENERAL DE GOBIERNO\nBERNARDO H. MARTINEZ AGUIRRE.\n(RÚBRICA)\nARTÍCULO PRIMERO TRANSITORIO DEL DECRETO NO. 247, POR EL QUE SE\nREFORMAN LOS ARTÍCULOS 1, 2, 21, 23, 45, 47, 49, 50, 53, 54, 55, 56, 64, 69 Y SE\nADICIONA EL CAPÍTULO VII, DEL TÍTULO QUINTO DENOMINADO “DE LA\nORGANIZACIÓN DE LOS JUZGADOS DEL PODER JUDICIAL DEPENDIENTES DEL\nTRIBUNAL SUPERIOR”, ASÍ COMO LOS ARTÍCULOS 90 BIS, 90 TER, 90 QUATER, Y 90\nQUINQUIES, PUBLICADO EN EL PERIÓDICO OFICIAL NO. 45, DE FECHA 27 DE\nOCTUBRE DE 2006, TOMO CXIII, EXPEDIDO POR LA H. XVIII LEGISLATURA, SIENDO\nGOBERNADOR CONSTITUCIONAL EL C. EUGENIO ELORDUY WALTHER 2001-2007.\nTRANSITORIO\nUNICO.- Las presentes reformas entrarán en vigor a partir del primero de marzo del año dos mil siete, previa publicación en el Periódico Oficial del Estado.\nDADO en el Salón Casino del Centro Social, Cívico y Cultura Riviera de la Ciudad de\nEnsenada, Baja California, a los doce días del mes de septiembre del año dos mil seis.\nDIP. JORGE NÚÑEZ VERDUGO\nPRESIDENTE\n(RÚBRICA)\nDIP. CARLOS ENRIQUE JIMÉNEZ RUIZ\nSECRETARIO.\n(RÚBRICA)\nDE CONFORMIDAD CON LO DISPUESTO POR LA FRACCIÓN I DEL ARTÍCULO 49\nMEXICALI, BAJA CALIFORNIA, A LOS DIECISIETE DÍAS DEL MES DE OCTUBRE\nDEL AÑO DOS MIL SEIS.\nGOBERNADOR DEL ESTADO\nEUGENIO ELORDUY WALTER\n(RÚBRICA)\nSECRETARIO GENERAL DE GOBIERNO\nBERNARDO H. MARTINEZ AGUIRRE.\n(RÚBRICA)\nARTÍCULO SEGUNDO TRANSITORIO DEL DECRETO NO. 422, POR EL QUE\nREFORMA EL ARTÍCULO 175, SE ADICIONA UN CAPÍTULO XIII AL TÍTULO\nDECIMOPRIMERO, ASÍ COMO LOS ARTÍCULOS 197 BIS Y 197 BIS-1, PUBLICADO EN\nEL PERIÓDICO OFICIAL NO. 43, DE FECHA 19 DE OCTUBRE DE 2007, SECCIÓN I,\nTOMO CXIV, EXPEDIDO POR LA H. XVIII LEGISLATURA, SIENDO GOBERNADOR\nCONSTITUCIONAL EL C. EUGENIO ELORDUY WALTHER 2001-2007.\nTRANSITORIO\nUNICO.- La presente reforma entrará en vigor dieciocho meses después de su publicación en el Periódico Oficial del Estado.\nDADO en la Sala de Comisiones “Dr. Francisco Dueñas Montes” del H. Poder\nLegislativo de Baja California en la ciudad de Mexicali, Baja California, el día veinticinco septiembre de dos mil siete.\nDIP. RAÚL LÓPEZ MORENO\nPRESIDENTE\n(RÚBRICA)\nDIP. ABRAHAM CORREA ACEVEDO\nSECRETARIO\n(RÚBRICA)\nDE CONFORMIDAD CON LO DISPUESTO POR LA FRACCIÓN I DEL ARTÍCULO 49\nMEXICALI, BAJA CALIFORNIA, AL PRIMER DÍA DEL MES DE OCTUBRE DEL AÑO\nDOS MIL SIETE.\nGOBERNADOR DEL ESTADO\nEUGENIO ELORDUY WALTER\n(RÚBRICA)\nSECRETARIO GENERAL DE GOBIERNO\nBERNARDO H. MARTINEZ AGUIRRE.\n(RÚBRICA)\nARTÍCULO TRANSITORIO DEL DECRETO NO. 144, POR EL QUE REFORMAN\nLOS ARTÍCULOS 8, 9, 10, 12, 23, 53, 60, 64, 71, 81 BIS, 100 Y 168, PUBLICADO EN EL\nTOMO CXV, EXPEDIDO POR LA H. XIX LEGISLATURA, SIENDO GOBERNADOR\nCONSTITUCIONAL EL C. JOSÉ GUADALUPE OSUNA MILLÁN 2007-2013.\nARTÍCULOS TRANSITORIOS\nPRIMERO.- La presente reforma entrará en vigor al día siguiente de su publicación en el Periódico Oficial del Estado, con excepción en lo dispuesto en el siguiente artículo tercero transitorio.\nSEGUNDO.- Los Jueces Penales en funciones del Partido Judicial de Mexicali, podrán ser readscritos como Jueces del nuevo sistema de justicia penal, siempre y cuando cubran las etapas que se señalan en los incisos c) y f) del artículo cuarto transitorio.\nTERCERO.- Las reformas a los artículos 53 fracción VII y 81 BIS, entrarán en vigor en la misma fecha en que alcance vigencia el primer párrafo del artículo primero transitorio del Código de Procedimientos Penales, publicado el día 19 de octubre de 2007 en el\nPeriódico Oficial del Estado.\nLos efectos de las designaciones de los Jueces del nuevo sistema de justicia penal, se materializarán en la fecha que se señala en la disposición transitoria a la que hace mención el párrafo anterior.\nHasta en tanto surtan sus efectos jurídicos las citadas designaciones, las personas nombradas como Jueces para el nuevo sistema, seguirán recibiendo la remuneración que les correspondía antes de su designación.\nCUARTO.- Para la integración por parte del Consejo de la Judicatura, de la lista que aspirantes en el Partido Judicial de Mexicali, a los cargos de Jueces a los que alude la reforma al artículo 53 fracción VII, deberán observarse como mínimo las siguientes etapas:\na).- Publicación de la convocatoria.\nb).- Revisión de los requisitos que se establezcan en la Convocatoria.\nc).- Capacitación básica.\nd).- Examen teórico de conocimientos básicos.\ne).- Evaluación psicométrica.\nf).- Capacitación avanzada y especializada, así como la evaluación respectiva.\ng).- Entrevista pública.\nh).- Evaluación de méritos.\ni).- Elaboración y remisión de la lista de aspirantes al Tribunal Superior de Justicia del\nEstado.\nLa convocatoria a la que hace mención el inciso a), y los nombres de los aspirantes que vayan superando cada una de la etapas que se señalan en los incisos b), c), d), e), f),\ng), h) e i), deberán ser publicados en el Boletín Judicial del Estado en los términos de la citada convocatoria.\nDentro de los requisitos que se establezcan en la convocatoria que deben cumplir los aspirantes al cargo de Juez, se deberán establecer los que señala el artículo 62 de la\nEn la convocatoria dentro de la etapa que señala el inciso g), deberá precisarse que será valorada la integridad profesional, presentación, seguridad, habilidad de comunicación, madurez, y objetividad de los aspirantes.\nDe igual forma, en la convocatoria dentro de la etapa que señala el inciso h), deberá precisarse que será valorada la preparación académica, experiencia profesional y prestigio profesional de los aspirantes, por lo que deberán solicitarse la opinión de colegios y barras de abogados.\nEl desarrollo de las disposiciones normativas que se contienen en los artículos transitorios, así como los aspectos no previstos por estos y que sean necesarios para alcanzar los fines del concurso, se establecerán en la convocatoria que expida el Consejo de la Judicatura.\nQUINTO.- Los aspirantes del Poder Judicial del Estado que accedan a la etapa de capacitación avanzada y especializada, así como los Jueces que sean readscritos al nuevo sistema, serán separados provisionalmente de sus funciones con goce de sueldo, únicamente durante el tiempo en el que se impartan las citadas capacitaciones.\nSEXTO.- Los aspirantes que aparezcan en la lista que remita el Consejo de la\nJueces, integrarán una reserva de personas dentro de la cual el Tribunal deberá realizar, en justifique la necesidad de contar con Jueces adicionales, las designaciones correspondientes. Reforma\nLa citada reserva, tendrá vigencia de 2 años contados a partir de la fecha en que se de Mexicali. del Estado de Baja California, en la Ciudad de Mexicali, B.C., a los veintitrés días del mes de octubre del año dos mil ocho.\nDIP. GINA ANDREA CRUZ BLACKLEDGE\nPRESIDENTA\n(RÚBRICA)\nDIP. JUAN MANUEL MOLINA GARCÍA\nSECRETARIO\n(RÚBRICA)\nDE CONFORMIDAD CON LO DISPUESTO POR LA FRACCIÓN I DEL ARTÍCULO 49\nMEXICALI, BAJA CALIFORNIA, A LOS DOCE DÍAS DEL MES DE NOVIEMBRE DEL\nAÑO DOS MIL SIETE.\nGOBERNADOR DEL ESTADO\nJOSÉ GUADALUPE OSUNA MILLÁN\n(RÚBRICA)\nSECRETARIO GENERAL DE GOBIERNO\nJOSÉ FRANCISCO BLAKE MORA\n(RÚBRICA)\nARTÍCULO SEGUNDO TRANSITORIO DEL DECRETO NO. 157, POR EL QUE\nREFORMAN LOS ARTÍCULOS 2, 245, 247 AL 251, 253, 257, 258, 267 AL 271 Y 274, SE\nADICIONAN DOS SECCIONES AL CAPÍTULO SEGUNDO DEL TÍTULO DÉCIMO\nCUARTO, QUE COMPRENDEN LA SECCIÓN PRIMERA LOS ARTÍCULOS 249 AL 251, Y\nLA SECCIÓN SEGUNDA LOS ARTÍCULOS 251 BIS, 251 TER, 251 QUATER, 251\nQUINQUES, 251 SEXIES Y 251 SEPTIES QUE SE ADICIONAN, DE FECHA 14 DE\nLEGISLATURA, SIENDO GOBERNADOR CONSTITUCIONAL EL C. JOSÉ GUADALUPE\nOSUNA MILLÁN 2007-2013.\nARTÍCULOS TRANSITORIOS\nPRIMERO.- Las presentes reformas entrarán en vigor el día siguiente al de su publicación en el Periódico Oficial del Estado. conformidad a sus atribuciones, deberá adecuar su reglamentación interna, a más tardar en\nTERCERO.- Quienes se encuentren ejerciendo el cargo de Secretario General y\nSecretarios al momento de la entrada en vigor del presente Decreto, pasarán a ser el\nSecretario General de Acuerdos y los Secretarios de Estudio y Cuenta a que se refiere la presente reforma, según corresponda, conservando sus derechos laborales adquiridos.\nCUARTO.- Se derogan todas las disposiciones que se opongan al presente Decreto.\nDADO en el Salón de Sesiones “Lic. Benito Juárez García” del H. Poder Legislativo, en la Ciudad de Mexicali, Capital del Estado de Baja California, a los dieciocho días del mes de noviembre del año dos mil ocho.\nDIP. GINA ANDREA CRUZ BLACKLEDGE\nPRESIDENTA\n(RÚBRICA)\nDIP. JUAN MANUEL MOLINA GARCÍA\nSECRETARIO\n(RÚBRICA)\nDE CONFORMIDAD CON LO DISPUESTO POR LA FRACCIÓN I DEL ARTÍCULO 49\nMEXICALI, BAJA CALIFORNIA, A LOS DOCE DÍAS DEL MES DE NOVIEMBRE DEL\nAÑO DOS MIL SIETE.\nGOBERNADOR DEL ESTADO\nJOSÉ GUADALUPE OSUNA MILLÁN\n(RÚBRICA)\nSECRETARIO GENERAL DE GOBIERNO\nJOSÉ FRANCISCO BLAKE MORA\n(RÚBRICA)\nARTÍCULO PRIMERO TRANSITORIO DEL DECRETO NO. 214 POR EL QUE\nSECCIÓN I, TOMO CXVI, EXPEDIDO POR LA H. XIX LEGISLATURA, SIENDO\nGOBERNADOR CONSTITUCIONAL EL C. JOSÉ GUADALUPE OSUNA MILLÁN 2007-\n2013.\nARTÍCULO TRANSITORIO\nÚNICO.- Las presentes reformas entrarán en vigor, una vez que sean publicadas en restricción.\nDADO en el Salón de Sesiones “Lic. Benito Juárez García” del H. Poder Legislativo del Estado de Baja California, en la Ciudad de Mexicali, B.C., a los veintinueve días del mes de enero del año dos mil nueve.\nDIP. GINA ANDREA CRUZ BLACKLEDGE\nPRESIDENTA\n(RÚBRICA)\nDIP. JUAN MANUEL MOLINA GARCÍA\nSECRETARIO\n(RÚBRICA)\nDE CONFORMIDAD CON LO DISPUESTO POR LA FRACCIÓN I DEL ARTÍCULO 49\nMEXICALI, BAJA CALIFORNIA, A LOS VEINTITRÉS DÍAS DEL MES DE FEBRERO\nDEL AÑO DOS MIL NUEVE.\nGOBERNADOR DEL ESTADO\nJOSÉ GUADALUPE OSUNA MILLÁN\n(RÚBRICA)\nSECRETARIO GENERAL DE GOBIERNO\nJOSÉ FRANCISCO BLAKE MORA\n(RÚBRICA)\nARTÍCULO SEGUNDO TRANSITORIO DEL DECRETO NO. 227, POR EL QUE SE\nREFORMA EL ARTÍCULO 17, PUBLICADO EN EL PERIÓDICO OFICIAL NO. 20, DE\nSIENDO GOBERNADOR CONSTITUCIONAL EL C. JOSÉ GUADALUPE OSUNA MILLÁN\n2007-2013.\nARTÍCULOS TRANSITORIOS\nPRIMERO.- Aprobada que sea esta Iniciativa de reforma por esta Honorable\nAsamblea, envíese esta a los Ayuntamientos del Estado, con copia de las actas de los debates que hubiere provocado, en cumplimiento a lo previsto por el artículo 112 de la\nSEGUNDO.- Aprobado la iniciativa de reforma por los Ayuntamientos del Estado, pronúnciese la Declaratoria en los términos establecidos por el artículo 112 de la\nTERCERO.- La presente reforma entrará en vigor al día siguiente de su publicación en el Periódico Oficial del Estado, previo cumplimiento del procedimiento que prescribe el\nCUARTO.- La reforma al primer párrafo del artículo 17 de la Ley Orgánica del Poder\nJudicial del Estado de Baja California, entrará en vigor una vez cobre vigencia la reforma al en los artículos transitorios antes citados.\nDADO en el Salón de Sesiones “Lic. Benito Juárez García” del H. Poder Legislativo del\nEstado de Baja California, en la Ciudad de Mexicali, B. C., a los veinticinco días del mes de marzo del año dos mil nueve.\nDIP. ADRIANA GUADALUPE SÁNCHEZ MARTÍNEZ\nPRESIDENTA\n(RÚBRICA)\nDIP. CARLOS ALONSO ANGULO RENTERÍA\nSECRETARIO\n(RÚBRICA)\nDE CONFORMIDAD CON LO DISPUESTO POR LA FRACCIÓN I DEL ARTÍCULO 49\nMEXICALI, BAJA CALIFORNIA, A LOS SIETE DÍAS DEL MES DE ABRIL DEL AÑO\nDOS MIL NUEVE.\nGOBERNADOR DEL ESTADO\nJOSÉ GUADALUPE OSUNA MILLÁN\n(RÚBRICA)\nSECRETARIO GENERAL DE GOBIERNO\nJOSÉ FRANCISCO BLAKE MORA\n(RÚBRICA)\nARTÍCULO SEGUNDO TRANSITORIO DEL DECRETO No. 293, POR EL QUE SE\nREFORMAN LOS ARTÍCULOS 258 Y 268 AMBOS EN SU FRACCIÓN III, PUBLICADO EN\nEXPEDIDO POR LA H. XIX LEGISLATURA, SIENDO GOBERNADOR CONSTITUCIONAL\nEL C. JOSÉ GUADALUPE OSUNA MILLÁN 2007-2013.\nARTÍCULOS TRANSITORIOS\nPRIMERO.- Las presentes reformas entrarán en vigor el día siguiente al de su publicación en el Periódico Oficial del Estado de Baja California.\nSEGUNDO.- El Consejo General del Instituto Electoral, dentro de los sesenta días naturales siguientes a su entrada en vigor del presente decreto, deberá adecuar las disposiciones reglamentarias correspondientes.\nTERCERO.- El Consejo General del Instituto Electoral, en la siguiente sesión pública que celebre, después de la entrada en vigor del presente decreto, deberá integrar la\nComisión de Fiscalización de los Recursos de los Partidos Políticos.\nCUARTO.- El Reglamento Interior de la Contraloría General, deberá emitirse dentro de los sesenta días naturales siguientes a la entrada en vigor del presente Decreto.\nQUINTO.- A partir del 2010, en ningún caso, la dieta de los consejeros presidentes de los consejos electorales podrá ser mayor al cinco porciento del que señale la ley para los consejeros electorales, según corresponda.\nÚNICO: Las presentes reformas entrarán en vigor el día siguiente al de su publicación en el Periódico Oficial del Estado.\nDADO en el Salón de Sesiones “Lic. Benito Juárez García” del H. Poder Legislativo del Estado de Baja California, en la Ciudad de Mexicali, B.C., a los treinta días del mes de octubre de dos mil nueve.\nDIP. ANTONIO RICARDO CANO JIMÉNEZ\nPRESIDENTE\n(RÚBRICA)\nDIP. RUBÉN ERNESTO ARMENTA ZANABIA\nSECRETARIO\n(RÚBRICA)\nDE CONFORMIDAD CON LO DISPUESTO POR LA FRACCIÓN I DEL ARTÍCULO 49\nMEXICALI, BAJA CALIFORNIA, A LOS TREINTA DÍAS DEL MES DE OCTUBRE\nDEL AÑO DOS MIL NUEVE.\nJOSÉ GUADALUPE OSUNA MILLÁN\nGOBERNADOR DEL ESTADO.\n(RÚBRICA)\nJOSÉ FRANCISCO BLACKE MORA\nSECRETARIO GENERAL DE GOBIERNO\n(RÚBRICA)\nARTÍCULO TRANSITORIO DEL DECRETO No. 384, POR EL QUE SE REFORMAN\nDIVERSOS ARTÍCULOS, PUBLICADO EN EL PERIÓDICO OFICIAL No. 29, SECCIÓN I,\nDE FECHA 02 DE JULIO DE 2010, TOMO CXVII, EXPEDIDO POR LA H. XIX\nLEGISLATURA, SIENDO GOBERNADOR CONSTITUCIONAL EL C. JOSÉ GUADALUPE\nOSUNA MILLÁN 2007-2013.\nTRANSITORIOS\nARTICULO PRIMERO.- Las presentes reformas entrarán en vigor al día siguiente de su publicación en el Periódico Oficial del Estado, salvo lo dispuesto en el artículo noveno transitorio.\nARTICULO SEGUNDO.- Lo dispuesto en el Artículo 168 fracción XV párrafo segundo, será aplicable para el nombramiento o nombramientos de administrador judicial, que se realicen con posterioridad a la entrada en vigor de este Decreto.\nBajo la actual integración del Consejo, deberá entenderse por mayoría calificada a por lo menos cinco Consejeros de la Judicatura. En caso que con posterioridad a la entrada en vigor de este Decreto cambiara el número de integrantes del Consejo, si el resultado de la operación aritmética de las dos terceras partes arrojara un número fraccionado, se entenderá que la citada mayoría se alcanza cuando voten en el mismo sentido los\nConsejeros que representen el número entero inmediato superior a dicha fracción.\nARTICULO TERCERO.- Los nombramientos realizados del personal adscrito al administrador o administradores judiciales surtirán sus efectos jurídicos desde el momento en que lo haya determinado o vaya a determinar el Consejo de la Judicatura.\nARTICULO CUARTO.- Suplirán a los jueces penales del sistema tradicional del\nPartido Judicial Mexicali que sean readscritos al nuevo sistema de justicia penal, los primeros secretarios de acuerdos del juzgado respectivo. En caso de que no hubiera un primer secretario o este no aceptara la citada suplencia, el Pleno del Tribunal Superior de el juzgado respectivo, la persona que ejercerá la suplencia.\nARTICULO QUINTO.- Para las faltas temporales de secretarios de acuerdos de los juzgados penales del sistema tradicional del Partido Judicial de Mexicali, que se actualicen con posterioridad a la entrada en vigor de este Decreto y que no excedan de dos meses, se estará a lo dispuesto por el Artículo 97 de esta Ley. sistema tradicional del Partido Judicial de Mexicali, que se actualicen con posterioridad a la entrada en vigor de este Decreto y que excedan de dos meses, el Tribunal Superior de\nJusticia del Estado realizará las suplencias respectivas, dentro de las personas que cumplan con los requisitos que señala la ley y que, preferentemente sean servidores públicos que laboren en el juzgado donde se actualice este supuesto o formen parte de la lista elaborada por el Consejo de la Judicatura que señale nombres de personas aptas para ocupar el cargo.\nPara las faltas absolutas de secretarios de acuerdos de los juzgados penales del sistema tradicional del Partido Judicial de Mexicali, que se actualicen con posterioridad a la entrada en vigor de este Decreto se estará a lo dispuesto en el párrafo anterior.\nARTICULO SEXTO.- En el caso de faltas temporales o absolutas de actuarios de los juzgados penales del sistema tradicional del Partido Judicial de Mexicali, que se actualicen con posterioridad a la entrada en vigor de este Decreto, el Tribunal Superior de Justicia del\nEstado realizará las suplencias respectivas, dentro de las personas que cumplan con los requisitos que señala la ley y formen parte de la lista elaborada por el Consejo de la\nJudicatura que señale nombres de personas aptas para ocupar el cargo.\nARTICULO SEPTIMO.- En el supuesto de faltas temporales o absolutas de servidores públicos distintos a los señalados en los tres artículos transitorios anteriores de los juzgados penales del sistema tradicional del Partido Judicial de Mexicali, que se actualicen con posterioridad a la entrada en vigor de este Decreto, el Consejo de la Judicatura realizará las suplencias respectivas dentro de las personas que cumplan con los requisitos que señala la ley.\nARTICULO OCTAVO.- En todos los casos, los nombramientos que se realicen conforme a lo dispuesto por los artículos transitorios cuarto, quinto, sexto y séptimo tendrán el carácter de interinos y por ende por tiempo determinado. artículos transitorios anteriores, sus nuevos nombramientos seguirán conservando la interino.\nCuando la suplencia exceda del término de un mes, se estará a lo dispuesto en el\nArtículo 98 de esta Ley.\nARTICULO NOVENO.- Las reglas establecidas en los artículos transitorios cuarto, quinto, sexto, séptimo y octavo, entrarán en vigor en los partidos judiciales de Ensenada, Tijuana, Tecate y Playas de Rosarito un mes antes de que empiece a aplicarse el nuevo en el Periódico Oficial del Estado.\nDADO en el Salón de Sesiones “Lic. Benito Juárez García” del H. Poder\nLegislativo del Estado de Baja California, en la Ciudad de Mexicali, B.C., a los quince días del mes de junio de dos mil diez.\nDIP. OSCAR R. MARTÍNEZ GARZA\nPRESIDENTE\nRÚBRICA\nDIP. JUAN MANUEL MOLINA GARCÍA\nSECRETARIO\nRÚBRICA\nDE CONFORMIDAD CON LO DISPUESTO POR LA FRACCIÓN I DEL\nPUBLÍQUESE.\nMEXICALI, BAJA CALIFORNIA, A LOS VEINTIOCHO DÍAS DEL MES DE JUNIO\nDEL AÑO DOS MIL DIEZ.\nGOBERNADOR DEL ESTADO.\nJOSÉ GUADALUPE OSUNA MILLÁN.\nRÚBRICA\nSECRETARIO GRENERAL DE GOBIERNO\nJOSÉ FRANCISCO BLAKE MORA\nRÚBRICA\nARTÍCULO SEGUNDO TRANSITORIO DEL DECRETO No. 440, POR EL QUE SE\nAPRUEBA LA ADICIÓN DE UN ARTÍCULO 95 BIS Y SE REFORMAN LOS ARTÍCULOS 81\nBIS, 81 TER Y 197 BIS-2, PUBLICADO EN EL PERIÓDICO OFICIAL No. 44, DE FECHA 15\nLEGISLATURA, SIENDO GOBERNADOR CONSTITUCIONAL EL C. JOSÉ GUADALUPE\nOSUNA MILLÁN 2007-2013\nTRANSITORIOS:\nPrimero.- La presente adición y las reformas entrarán en vigor al día siguiente de su publicación en el Periódico Oficial del Estado de Baja California.\nSegundo.- Hasta en tanto este vigente el periodo de la reserva a que se refiere el artículo sexto transitorio del Decreto No. 144 publicado en el Periódico Oficial del Estado de reserva.\nDADO en el salón de sesiones “Lic. Benito Juárez García” del H. Poder Legislativo del\nEstado de Baja California, en la ciudad de Mexicali, B.C., a los veinticuatro días del mes de septiembre del año dos mil diez.\nDIP. JUAN MANUEL GASTÉLUM BUENROSTRO\nPRESIDENTE\nRÚBRICA\nDIP. CARLOS ALONSO ANGULO RENTERIA\nSECRETARIO\nRÚBRICA\nDE CONFORMIDAD CON LO DISPUESTO POR LA FRACCIÓN I DEL ARTÍCULO 49\nMEXICALI, BAJA CALIFORNIA, AL PRIMER DÍA DEL MES DE OCTUBRE DEL AÑO\nDOS MIL DIEZ.\nGOBERNADOR DEL ESTADO\nJOSÉ GUADALUPE OSUNA MILLÁN\nRÚBRICA\nSECRERTARIO GENERAL\nCUAUHTÉMOC CARDONA BENAVIDES\nRÚBRICA\nARTÍCULO TERCERO TRANSITORIO DEL DECRETO No. 440, POR EL QUE SE\nNÚMERO 144 PUBLICADO EN EL PERIÓDICO OFICIAL DEL ESTADO DE FECHA 14 DE\nLEGISLATURA, SIENDO GOBERNADOR CONSTITUCIONAL EL C. JOSE GUADALUPE\nOSUNA MILLAN 2007-2013\nDADO EN EL SALÓN DE SESIONES “LIC. BENITO JUÁREZ GARCÍA” DEL H.\nMEXICALI, B.C., A LOS VEINTICUATRO DÍAS DEL MES DE SEPTIEMBRE DEL AÑO DOS\nMIL DIEZ.\nDIP. JUAN MANUEL GASTÉLUM BUENROSTRO\nPRESIDENTE\nRÚBRICA\nDIP. CARLOS ALONSO ANGULO RENTERIA\nSECRETARIO\nRÚBRICA\nDE CONFORMIDAD CON LO DISPUESTO POR LA FRACCIÓN I DEL ARTÍCULO 49\nMEXICALI, BAJA CALIFORNIA, AL PRIMER DÍA DEL MES DE OCTUBRE DEL AÑO\nDOS MIL DIEZ.\nGOBERNADOR DEL ESTADO\nJOSÉ GUADALUPE OSUNA MILLÁN\nRÚBRICA\nSECRERTARIO GENERAL\nCUAUHTÉMOC CARDONA BENAVIDES\nRÚBRICA\nARTÍCULO CUARTO TRANSITORIO DEL DECRETO No. 446, POR EL QUE SE\nREFORMA EL ARTÍCULO 81, PUBLICADO EN EL PERIÓDICO OFICIAL No. 44, TOMO\nCXVII, SECCIÓN III, DE FECHA 15 DE OCTUBRE DE 2010, EXPEDIDO POR LA H. XIX\nLEGISLATURA, SIENDO GOBERNADOR CONSTITUCIONAL EL C. JOSÉ GUADALUPE\nOSUNA MILLÁN 2007-2013.\nUNICO.- Las presentes reformas entrarán en vigor al día siguiente de su publicación en el\nPeriódico Oficial del Estado.” del Estado de Baja California, en la Ciudad de Mexicali, B.C., a los veinticuatro días del mes de septiembre del año dos mil diez.\nDIP. JUAN MANUEL GASTÉLUM BUENROSTRO\nPRESIDENTE\n(RÚBRICA)\nDIP. CARLOS ALONSO ANGULO RENTERIA\nSECRETARIO\n(RÚBRICA)\nDE CONFORMIDAD CON LO DISPUESTO POR LA FRACCION I DEL ARTÍCULO 49\nMEXICALI, BAJA CALIFORNIA, AL PRIMER DÍA DEL MES DE OCTUBRE DEL AÑO\nDOS MIL DIEZ.\nGOBERNADOR DEL ESTADO\nJOSÉ GUADALUPE OSUNA MILLÁN\n(RÚBRICA)\nSECRETARIO GENERAL DE GOBIERNO\nCUAUHTÉMOC CARDONA BENAVIDES\n(RÚBRICA)\nARTÍCULO ÚNICO TRANSITORIO DEL DECRETO No. 450, POR EL QUE SE\nREFORMAN LOS ARTÍCULOS 156 Y 157 Y SE DEROGA LA FRACCIÓN XIII DEL\nARTÍCULO 253, PUBLICADO EN EL PERIÓDICO OFICIAL No. 44, TOMO CXVII, SECCIÓN\nIII, DE FECHA 15 DE OCTUBRE DE 2010, EXPEDIDO POR LA H. XIX LEGISLATURA,\nSIENDO GOBERNADOR CONSTITUCIONAL EL C. JOSÉ GUADALUPE OSUNA MILLÁN\n2007-2013.\nARTÍCULO TRANSITORIO:\nUNICO.- Las presentes reformas entrarán en vigor al día siguiente de su publicación en el Periódico Oficial del Estado.” del Estado de Baja California, en la Ciudad de Mexicali, B.C., a los veinticuatro días del mes de septiembre del año dos mil diez.\nDIP. JUAN MANUEL GASTÉLUM BUENROSTRO\nPRESIDENTE\n(RÚBRICA)\nDIP. CARLOS ALONSO ANGULO RENTERIA\nSECRETARIO\n(RÚBRICA)\nDE CONFORMIDAD CON LO DISPUESTO POR LA FRACCION I DEL ARTÍCULO 49\nMEXICALI, BAJA CALIFORNIA, AL PRIMER DÍA DEL MES DE OCTUBRE DEL AÑO\nDOS MIL DIEZ.\nGOBERNADOR DEL ESTADO\nJOSÉ GUADALUPE OSUNA MILLÁN\n(RÚBRICA)\nSECRETARIO GENERAL DE GOBIERNO\nCUAUHTÉMOC CARDONA BENAVIDES\n(RÚBRICA)\nARTÍCULO SEGUNDO TRANSITORIO DEL DECRETO NO. 82, POR EL QUE SE\nREFORMAN ARTÍCULOS 81, 81 BIS y 197 BIS-2, PUBLICADO EN EL PERIÓDICO\nOFICIAL NO. 31, TOMO CXVIII, SECCIÓN II, DE FECHA 01 DE JULIO DE 2011,\nEXPEDIDO POR LA H. XX LEGISLATURA, SIENDO GOBERNADOR CONSTITUCIONAL\nEL C. JOSÉ GUADALUPE OSUNA MILLÁN 2007-2013.\nARTÍCULOS TRANSITORIOS\nPRIMERO.- Las presentes reformas entrarán en vigor el día de su publicación en el\nPeriódico Oficial del Estado.\nSEGUNDO.- Los jueces penales de primera instancia ejercerán las facultades y observarán las obligaciones que la Ley de Ejecución de Penas y Medidas Judiciales para el\nEstado señala para el Juez de Ejecución, en todo aquello que sea compatible con las disposiciones normativas que se contienen en el Código de Procedimientos Penales para el\nEstado de Baja California publicado en el Periódico Oficial del Estado de fecha 20 de agosto de 1989 o en su caso, conforme a las disposiciones normativas anteriores a este Código. del Estado de Baja California, en la Ciudad de Mexicali, B.C., a los veintinueve días del mes de junio del año dos mil once.\nLIC. CARLOS MURGUÍA MEJÍA\nDIPUTADO PRESIDENTE\n(RÚBRICA)\nLIC. VIRGINIA NORIEGA RÍOS\nDIPUTADA SECRETARIA\n(RÚBRICA)\nDE CONFORMIDAD CON LO DISPUESTO POR LA FRACCION I DEL ARTÍCULO 49\nMEXICALI, BAJA CALIFORNIA, A LOS TREINTA DÍAS DEL MES DE JUNIO DEL\nAÑO DOS MIL ONCE.\nGOBERNADOR DEL ESTADO\nJOSÉ GUADALUPE OSUNA MILLÁN\n(RÚBRICA)\nSECRETARIO GENERAL DE GOBIERNO\nCUAUHTÉMOC CARDONA BENAVIDES\n(RÚBRICA)\nARTÍCULO CUARTO TRANSITORIO DEL DECRETO NO. 236, POR EL QUE SE\nAPRUEBAN LAS REFORMAS A LOS ARTÍCULOS 1, 2, 50, 53, 54, 102, Y SE ADICIONA\nUN CAPÍTULO VIII DENOMINADO “DE LA ORGNIZACIÓN DE LOS JUZGADOS DE\nPRIMERA INSTANCIA EN MATERIA DE EXTINCIÓN DE DOMINIO” AL TÍTULO QUINTO,\nQUE COMPRENDERÁ EL ARTÍCULO 90 SEXIES, PUBLICADO EN EL PERIÓDICO\nOFICIAL NO. 33, TOMO CXIX, DE FECHA 27 DE JULIO DE 2012, SECCIÓN II,\nEXPEDIDO POR LA H. XX LEGISLATURA, SIENDO GOBERNADOR CONSTITUCIONAL\nEL C. JOSÉ GUADALUPE OSUNA MILLÁN 2007-2013.\nARTÍCULO TRANSITORIO\nPRIMERO: El presente Decreto entrará en vigor a los noventa días posteriores de su publicación en el Periódico Oficial del Estado de Baja California.\nSEGUNDO: En tanto el Ejecutivo estatal realice las adecuaciones a la reglamentación correspondiente, a fin de dar el debido cumplimiento a las disposiciones de este ordenamiento, serán competentes para conocer sobre los delitos previstos en el artículo 4 párrafo primero de esta ley y ejercer la acción de extinción de dominio, las áreas o unidades\nGeneral de Justicia del Estado, de conformidad con los acuerdos que para tal efecto emita el\nProcurador. a su estructura interna, a fin de dar cumplimiento en el ámbito de su competencia a lo establecido en esta ley, serán competentes para conocer del procedimiento de extinción de dominio los juzgados de lo civil, de conformidad con los acuerdos que para tal efecto determine el Consejo de la Judicatura. del Estado de Baja California, en la Ciudad de Mexicali, B.C., a los veintiséis días del mes de junio del año dos mil doce.\nDIP. ALFONSO GARZÓN ZATARAIN\nPRESIDENTE\n(RÚBRICA)\nDIP. FAUSTO ZÁRATE ZEPEDA\nSECRETARIO\n(RÚBRICA)\nDE CONFORMIDAD CON LO DISPUESTO POR LA FRACCIÓN I DEL ARTÍCULO 49\nMEXICALI, BAJA CALIFORNIA, A LOS DIECISEIS DÍAS DEL MES DE JULIO DEL\nAÑO DOS MIL DOCE.\nJOSÉ GUADALUPE OSUNA MILLÁN\nGOBERNADOR DEL ESTADO\n(RÚBRICA)\nFRANCISCO ANTONIO GARCÍA BURGOS\nSECRETARIO GENERAL DE GOBIERNO\n(RÚBRICA)\nARTÍCULO TERCERO TRANSITORIO DEL DECRETO NO. 286, POR EL QUE SE\nREFORMAN LOS ARTÍCULOS 81 QUINQUES Y 197 BIS-2, PUBLICADO EN EL\nPERIÓDICO OFICIAL NO. 43, TOMO CXIX, DE FECHA 28 DE SEPTIEMBRE DE 2012,\nEXPEDIDO POR LA H. XX LEGISLATURA, SIENDO GOBERNADOR CONSTITUCIONAL\nEL C. JOSÉ GUADALUPE OSUNA MILLÁN 2007-2013.\nARTÍCULO TRANSITORIO\nÚNICO.- La presente reforma entrará en vigor al día siguiente de su publicación en el\nPeriódico Oficial del Estado. del Estado de Baja California, en la Ciudad de Mexicali, B.C., a los cuatro días del mes de septiembre del año dos mil doce.\nDIP. ALFONSO GARZÓN ZATARAIN\nPRESIDENTE\n(RÚBRICA)\nDIP. FAUSTO ZÁRATE ZEPEDA\nSECRETARIO\n(RÚBRICA)\nDE CONFORMIDAD CON LO DISPUESTO POR LA FRACCIÓN I DEL ARTÍCULO 49\nMEXICALI, BAJA CALIFORNIA, A LOS ONCE DÍAS DEL MES DE SEPTIEMBRE\nDEL AÑO DOS MIL DOCE.\nJOSÉ GUADALUPE OSUNA MILLÁN\nGOBERNADOR DEL ESTADO\n(RÚBRICA)\nFRANCISCO ANTONIO GARCÍA BURGOS\nSECRETARIO GENERAL DE GOBIERNO\n(RÚBRICA)\nARTÍCULO UNICO TRANSITORIO DEL DECRETO No. 306, POR EL QUE SE\nREFORMA EL ARTÍCULO 56, PUBLICADO EN EL PERIÓDICO OFICIAL No. 47, TOMO\nCXIX, SECCION I, DE FECHA 19 DE OCTUBRE DE 2012, EXPEDIDO POR LA H. XX\nLEGISLATURA, SIENDO GOBERNADOR CONSTITUCIONAL EL C. JOSÉ GUADALUPE\nOSUNA MILLÁN 2007-2013.\nARTÍCULO TRANSITORIO\nPRIMERO.- Las presentes reformas entrarán en vigor al día siguiente de su publicación en el Periódico Oficial del Estado de Baja California.\nSEGUNDO.- Las erogaciones que deban realizarse a fin de dar cumplimiento a las presentes reformas, se sujetarán a los recursos aprobados para tal fin por el Congreso del\nEstado, en el presupuesto de egresos asignado al Poder Judicial para el ejercicio fiscal\n2013. del Estado de Baja California, en la Ciudad de Mexicali, B.C., a los dieciocho días del mes de septiembre del año dos mil doce.\nDIP. ALFONSO GARZÓN ZATARAIN\nPRESIDENTE\n(RÚBRICA)\nDIP. FAUSTO ZÁRATE ZEPEDA\nSECRETARIO\n(RÚBRICA)\nDE CONFORMIDAD CON LO DISPUESTO POR LA FRACCIÓN I DEL ARTÍCULO 49\nMEXICALI, BAJA CALIFORNIA, A LOS DIECISIETE DÍAS DEL MES DE OCTUBRE DEL\nAÑO DOS MIL DOCE.\nJOSÉ GUADALUPE OSUNA MILLÁN\nGOBERNADOR DEL ESTADO\n(RÚBRICA)\nFRANCISCO ANTONIO GARCÍA BURGOS\nSECRETARIO GENERAL DE GOBIERNO\n(RÚBRICA)\nARTÍCULO SEGUNDO TRANSITORIO DEL DECRETO NO. 340, POR EL QUE SE\nREFORMA EL ARTICULO 168, ASÍ COMO LA DEROGACIÓN DE LOS ARTÍCULOS 208,\n209, 210, 211, 212, 213, 214, 215, 216 y 217; PUBLICADA EN EL PERIÓDICO OFICIAL\nNO. 53, DE FECHA 30 DE NOVIEMBRE DE 2012, SECCION III, TOMO CXIX; EXPEDIDO\nPOR LA H. XX LEGISLATURA, SIENDO GOBERNADOR CONSTITUCIONAL EL C. JOSÉ\nGUADALUPE OSUNA MILLÁN 2007-2013.\nARTÍCULO TRANSITORIO\nÚNICO.- El presente Decreto entrará en vigor al día siguiente de su publicación en el\nPeriódico Oficial del Estado de Baja California.\nDADO en el Salón de Sesiones “Lic. Benito Juárez García” del H. Poder Legislativo del Estado de Baja California, en la Ciudad de Mexicali, B.C., a los treinta y un días del mes de octubre del año dos mil doce.\nDIP. CLAUDIA JOSEFINA AGATÓN MUÑÍZ\nPRESIDENTA\n(RÚBRICA)\nDIP. FAUSTO ZÁRATE ZEPEDA\nSECRETARIO\n(RÚBRICA)\nDE CONFORMIDAD CON LO DISPUESTO POR LA FRACCION I DEL ARTÍCULO 49\nMEXICALI, BAJA CALIFORNIA, A LOS DOCE DÍAS DEL MES DE NOVIEMBRE DEL\nAÑO DOS MIL DOCE.\nJOSÉ GUADALUPE OSUNA MILLÁN\nGOBERNADOR DEL ESTADO\n(RÚBRICA)\nFRANCISCO ANTONIO GARCÍA BURGOS\nSECRETARIO GENERAL DE GOBIERNO\n(RÚBRICA)\nARTÍCULO TERCERO TRANSITORIO DEL DECRETO NO. 359, POR EL QUE SE\nREFORMAN LOS ARTÍCULOS 24, FRACCIÓN PRIMERA, 25 FRACCIÓN PRIMERA, 65\nFRACCIÓN PRIMERA, 66 FRACCIÓN PRIMERA, 215 FRACCIÓN PRIMERA Y 220\nFRACCIÓN PRIMERA; PUBLICADA EN EL PERIÓDICO OFICIAL NO. 53, DE FECHA 30\nDE NOVIEMBRE DE 2012, SECCION III, TOMO CXIX; EXPEDIDO POR LA H. XX\nLEGISLATURA, SIENDO GOBERNADOR CONSTITUCIONAL EL C. JOSÉ GUADALUPE\nOSUNA MILLÁN 2007-2013.\nARTÍCULO TRANSITORIO\nÚNICO.- Las presentes reformas entrarán en vigor al día siguiente de su publicación en el Periódico Oficial del Estado de Baja California.\nDADO en el Salón de Sesiones “Lic. Benito Juárez García” del H. Poder Legislativo del Estado de Baja California, en la Ciudad de Mexicali, B.C., a los veintiún días del mes de noviembre del año dos mil doce.\nDIP. CLAUDIA JOSEFINA AGATÓN MUÑÍZ\nPRESIDENTA\n(RÚBRICA)\nDIP. FAUSTO ZÁRATE ZEPEDA\nSECRETARIO\n(RÚBRICA)\nDE CONFORMIDAD CON LO DISPUESTO POR LA FRACCION I DEL ARTÍCULO 49\nMEXICALI, BAJA CALIFORNIA, A LOS CUATRO DÍAS DEL MES DE DICIEMBRE\nDEL AÑO DOS MIL DOCE.\nJOSÉ GUADALUPE OSUNA MILLÁN\nGOBERNADOR DEL ESTADO\n(RÚBRICA)\nFRANCISCO ANTONIO GARCÍA BURGOS\nSECRETARIO GENERAL DE GOBIERNO\n(RÚBRICA)\nARTÍCULO SEGUNDO TRANSITORIO DEL DECRETO NO. 408, POR EL QUE SE\nREFORMAN LOS ARTÍCULOS 168, 208, 209, 210, 211, 212, 213, 214, 215, 216 y 217,\nPUBLICADO EN EL PERIÓDICO OFICIAL NO. 5, SECCIÓN I, TOMO CXX, DE FECHA 25\nDE ENERO DE 2013, EXPEDIDO POR LA H. XX LEGISLATURA, SIENDO GOBERNADOR\nCONSTITUCIONAL EL C. JOSÉ GUADALUPE OSUNA MILLÁN 2007-2013;\nARTÍCULOS TRANSITORIOS\nPRIMERO.- El presente Decreto entrará en vigor el día de su publicación en el\nPeriódico Oficial del Estado de Baja California.\nSEGUNDO.- Los dictámenes, certificaciones y constancias periciales y demás actuaciones que se hayan realizado con anterioridad a la abrogación de la presente Ley en auxilio y apoyo técnico del Instituto de Ciencias Forenses del Estado, tendrán plena validez jurídica.\nDADO en el Salón de Sesiones “Lic. Benito Juárez García” del H. Poder Legislativo del Estado de Baja California, en la Ciudad de Mexicali, B.C., a los veinticuatro días del mes de enero del año dos mil trece.\nDIP. CLAUDIA JOSEFINA AGATÓN MUÑÍZ\nPRESIDENTA\n(RÚBRICA)\nDIP. FAUSTO ZÁRATE ZEPEDA\nSECRETARIO\n(RÚBRICA)\nDE CONFORMIDAD CON LO DISPUESTO POR LA FRACCION I DEL ARTÍCULO 49\nMEXICALI, BAJA CALIFORNIA, A LOS VEINTICUATRO DÍAS DEL MES DE ENERO\nDEL AÑO DOS MIL TRECE.\nJOSÉ GUADALUPE OSUNA MILLÁN\nGOBERNADOR DEL ESTADO\n(RÚBRICA)\nFRANCISCO ANTONIO GARCÍA BURGOS\nSECRETARIO GENERAL DE GOBIERNO\n(RÚBRICA)\nARTÍCULO UNICO TRANSITORIO DEL DECRETO No. 487, POR EL QUE SE\nREFORMAN LOS ARTÍCULOS 32 y 45, PUBLICADO EN EL PERIÓDICO OFICIAL No. 32,\nTOMO CXX, DE FECHA 19 DE JULIO DE 2013, EXPEDIDO POR LA H. XX LEGISLATURA,\nSIENDO GOBERNADOR CONSTITUCIONAL EL C. JOSÉ GUADALUPE OSUNA MILLÁN\n2007-2013;\nARTÍCULO TRANSITORIO\nÚNICO.-Las presentes reformas entrarán en vigor el día siguiente de su publicación en el Periódico Oficial de Estado de Baja California.\nDADO en el Salón de Sesiones “Lic. Benito Juárez García” del H. Poder Legislativo del Estado de Baja California, en la Ciudad de Mexicali, B.C., a los diecinueve días del mes de junio del año dos mil trece.\nDIP. GREGORIO CARRANZA HERNÁNDEZ\nPRESIDENTE\n(RÚBRICA)\nDIP. MARCO ANTONIO VIZCARRA CALDERÓN\nSECRETARIO\n(RÚBRICA)\nDE CONFORMIDAD CON LO DISPUESTO POR LA FRACCION I DEL ARTÍCULO 49\nMEXICALI, BAJA CALIFORNIA, A LOS VEINTICINCO DÍAS DEL MES DE JUNIO\nDEL AÑO DOS MIL TRECE.\nJOSÉ GUADALUPE OSUNA MILLÁN\nGOBERNADOR DEL ESTADO\n(RÚBRICA)\nFRANCISCO ANTONIO GARCÍA BURGOS\nSECRETARIO GENERAL DE GOBIERNO\n(RÚBRICA)\nARTÍCULO UNICO TRANSITORIO DEL DECRETO No. 590, POR EL QUE SE\nADICIONA EL CAPÍTULO XIV AL TÍTULO DÉCIMO PRIMERO, CON LA DENOMINACIÓN\n“DEL CENTRO DE CONVIVENCIA FAMILIAR SUPERVISADA”, ASÍ COMO LA ADICIÓN\nDEL NUMERAL 197 TER, PUBLICADO EN EL PERIÓDICO OFICIAL No. 47, TOMO CXX,\nLEGISLATURA, SIENDO GOBERNADOR CONSTITUCIONAL EL C. JOSÉ GUADALUPE\nOSUNA MILLÁN 2007-2013;\nARTÍCULOS TRANSITORIOS\nPRIMERO.- El presente Decreto entrará en vigor el día 01 de enero de 2015.\nSEGUNDO.- El Pleno del Consejo de la Judicatura Estatal, deberá tomar las medidas presupuestales necesarias para que el Centro de Convivencia Familiar Supervisada entre en funciones.\nTERCERO.- Las unidades de apoyo, comenzarán a funcionar en el orden y fechas que determine el Pleno del Consejo de la Judicatura Estatal, conforme a las posibilidades presupuestales y necesidades del servicio.\nDADO en el Salón de Sesiones “Lic. Benito Juárez García” del H. Poder Legislativo del Estado de Baja California, en la Ciudad de Mexicali, B.C., a los veinticinco días del mes de septiembre del año dos mil trece.\nDIP. GREGORIO CARRANZA HERNÁNDEZ\nPRESIDENTE\n(RÚBRICA)\nDIP. MARCO ANTONIO VIZCARRA CALDERÓN\nSECRETARIO\n(RÚBRICA)\nDE CONFORMIDAD CON LO DISPUESTO POR LA FRACCION I DEL ARTÍCULO 49\nMEXICALI, BAJA CALIFORNIA, A LOS TREINTA DÍAS DEL MES DE SEPTIEMBRE\nDEL AÑO DOS MIL TRECE.\nJOSÉ GUADALUPE OSUNA MILLÁN\nGOBERNADOR DEL ESTADO\n(RÚBRICA)\nFRANCISCO ANTONIO GARCÍA BURGOS\nSECRETARIO GENERAL DE GOBIERNO\n(RÚBRICA)\nARTÍCULO SEPTIMO TRANSITORIO DEL DECRETO No. 246, POR EL QUE SE\nREFORMAN LOS ARTÍCULOS 81 BIS, 81 TER, 81 QUATER, 81 QUINQUIES, 197 BIS-2,\n197 BIS-3, 197 BIS-5 Y 199; SE MODIFICA LA DENOMINACIÓN DEL CAPÍTULO XIII DEL\nTÍTULO DÉCIMO PARA LLAMARSE “DEL CENTRO ESTATAL DE JUSTICIA\nALTERNATIVA”; Y SE ADICIONA EL CAPÍTULO XIV “DE LA ADMINISTRACIÓN JUDICIAL”\nDENTRO DEL TÍTULO DÉCIMO, QUE SE INTEGRARÁ CON LOS NUMERALES 197 BIS-2\nAL 197 BIS-5, PUBLICADO EN EL PERIÓDICO OFICIAL No. 24, SECCION I, TOMO CXXII,\nDE FECHA 22 DE MAYO DE 2015, EXPEDIDO POR LA H. XXI LEGISLATURA, SIENDO\nGOBERNADOR CONSTITUCIONAL EL C. FRANCISCO ARTURO VEDA DE LAMADRID\n2013-2019.\nARTÍCULOS TRANSITORIOS\nPRIMERO.- Publíquense las presentes reformas en el Periódico Oficial del Estado de\nBaja California.\nSEGUNDO.- Las presentes reformas entrarán en vigor de manera gradual, en las fechas en que inicie vigencia el Código Nacional de Procedimientos Penales, de conformidad con las Declaratorias que emita el Poder Legislativo del Estado en los términos del artículo segundo transitorio del mencionado Código Nacional. Lo anterior, sin perjuicio de lo siguiente:\n1.- Las reformas a la Ley de Atención y Protección a la Víctima o el Ofendido del\nDelito para el Estado de Baja California, y la reforma a los artículos 19, 22 y 23 de la Ley\nOrgánica de la Administración Pública del Estado, entrarán en vigor al día siguiente de su publicación en el Periódico Oficial del Estado.\n2.- Las reformas a la Ley Orgánica de la Defensoría Pública del Estado de Baja\nCalifornia, entrarán en vigor al día siguiente de su publicación en el Periódico Oficial del\nEstado, y su cumplimiento estará sujeto a la disponibilidad presupuestal.\n3.- Las reformas a la Ley del Sistema Integral de Justicia para Adolescentes del\nEstado de Baja California, entrarán en vigor al momento en que inicie vigencia dicha Ley conforme a su artículo transitorio primero.\n4.- Las reformas a la Ley Contra la Delincuencia Organizada para el Estado de Baja\nCalifornia, iniciarán vigencia a los noventa días después de su publicación en el Periódico\nOficial del Estado.\nTERCERO.- Las menciones que en otras leyes, ordenamientos reglamentarios o acuerdos se haga respecto a la Subprocuraduría contra la Delincuencia Organizada, se\nGeneral de Justicia del Estado.\nCUARTO.- Quienes se encuentren ejerciendo el cargo de Juez de Garantía en el\nPartido Judicial de Mexicali, al momento de la entrada en vigor del presente Decreto conforme al transitorio segundo, pasarán a ejercer el cargo de Juez de Control a que se refiere la presente reforma, conservando sus derechos adquiridos por el periodo que fueron designados.\nLos jueces de control del Partido Judicial de Mexicali, fungirán como jueces de\nQUINTO.- La designación de los jueces de ejecución a que se refiere este Decreto, será de conformidad con la gradualidad prevista en el primer párrafo del artículo segundo transitorio de la presente reforma.\nHasta en tanto no se realice el nombramiento de jueces de ejecución en cada partido judicial, según sea el caso, los jueces de garantía, control o de primer instancia atendiendo la naturaleza del proceso penal que dio lugar a la sentencia, continuarán conociendo y resolviendo los procedimientos competencia de los jueces de ejecución.\nDADO en el Salón de Sesiones “Lic. Benito Juárez García” del H. Poder Legislativo del Estado de Baja California, en la Ciudad de Mexicali, B.C., a los veintitrés días del mes de abril del año dos mil quince.\nDIP. FCO. ALCIBÍADES GARCÍA LIZARDI\nPRESIDENTE\n(RUBRICA)\nDIP. ROSALBA LÓPEZ REGALADO\nSECRETARIA\n(RUBRICA)\nDE CONFORMIDAD CON LO DISPUESTO POR LA FRACCION I DEL ARTÍCULO 49\nMEXICALI, BAJA CALIFORNIA, A LOS CINCO DÍAS DEL MES DE MAYO DEL AÑO DOS\nMIL QUINCE.\nFRANCISCO ARTURO VEGA DE LAMADRID\nGOBERNADOR DEL ESTADO\n(RÚBRICA)\nFRANCISCO RUEDA GOMEZ\nSECRETARIO GENERAL DE GOBIERNO\n(RÚBRICA)\nARTÍCULO SEGUNDO TRANSITORIO DEL DECRETO No. 290, POR EL QUE SE\nREFORMAN LOS ARTÍCULOS 1, 2, 168 Y 183, ASÍ COMO LA DEROGACIÓN DEL TÍTULO\nDECIMOCUARTO CON SUS RESPECTIVOS CAPÍTULOS Y ARTÍCULOS DEL 244 AL 292,\nPUBLICADO EN EL PERIÓDICO OFICIAL No. 24, SECCION I, TOMO CXXII, DE FECHA 22\nCONSTITUCIONAL EL C. FRANCISCO ARTURO VEDA DE LAMADRID 2013-2019.\nARTÍCULO TRANSITORIOS\nÚNICO.- El presente Decreto entrará en vigor al día siguiente de su publicación en el\nPeriódico Oficial del Estado de Baja California. del Estado de Baja California, en la Ciudad de Mexicali, B.C., a los once del mes de junio del año dos mil quince.\nDIP. JULIO CÉSAR VÁZQUEZ CASTILLO\nPRESIDENTE\n(RUBRICA)\nDIP. RODOLFO OLIMPO HERNÁNDEZ BOJÓRQUEZ\nSECRETARIO\n(RUBRICA)\nDE CONFORMIDAD CON LO DISPUESTO POR LA FRACCION I DEL ARTÍCULO 49\nMEXICALI, BAJA CALIFORNIA, A LOS DOCE DÍAS DEL MES DE JUNIO DEL AÑO DOS\nMIL QUINCE.\nFRANCISCO ARTURO VEGA DE LAMADRID\nGOBERNADOR DEL ESTADO\n(RÚBRICA)\nFRANCISCO RUEDA GOMEZ\nSECRETARIO GENERAL DE GOBIERNO\n(RÚBRICA)\nARTÍCULO UNICO TRANSITORIO DEL DECRETO No. 315, POR EL QUE SE\nREFORMA LA FRACCIÓN XVII, RECORRIENDOSE EL ORDEN DE LA FRACCIÓN PARA\nADICIONAR LA FRACCIÓN XVIII AL ARTÍCULO 131, PUBLICADO EN EL PERIÓDICO\nEXPEDIDO POR LA H. XXI LEGISLATURA, SIENDO GOBERNADOR CONSTITUCIONAL\nEL C. FRANCISCO ARTURO VEGA DE LAMADRID 2013-2019.\nARTÍCULO TRANSITORIOS\nPRIMERO: El presente decreto entrará en vigor al día siguiente a su publicación en el\nPeriódico Oficial del Estado de Baja California.\nSEGUNDO: Se derogan todas las disposiciones que contravengan el presente\nDecreto. del Estado de Baja California, en la Ciudad de Mexicali, B.C., a los seis del mes de agosto del año dos mil quince.\nDIP. JULIO CÉSAR VÁZQUEZ CASTILLO\nPRESIDENTE\n(RUBRICA)\nDIP. RODOLFO OLIMPO HERNÁNDEZ BOJÓRQUEZ\nSECRETARIO\n(RUBRICA)\nDE CONFORMIDAD CON LO DISPUESTO POR LA FRACCION I DEL ARTÍCULO 49\nMEXICALI, BAJA CALIFORNIA, A LOS TRECE DÍAS DEL MES DE AGOSTO DEL AÑO\nDOS MIL QUINCE.\nFRANCISCO ARTURO VEGA DE LAMADRID\nGOBERNADOR DEL ESTADO\n(RÚBRICA)\nFRANCISCO RUEDA GOMEZ\nSECRETARIO GENERAL DE GOBIERNO\n(RÚBRICA)\nARTÍCULO UNICO TRANSITORIO DEL DECRETO No. 410, POR EL QUE SE\nREFORMAN LOS ARTÍCULOS 73 FRACCIONES II Y VI, 88 Y 90 FRACCIÓN I,\nPUBLICADO EN EL PERIÓDICO OFICIAL No. 58, SECCION IV, TOMO CXXII, DE FECHA\nGOBERNADOR CONSTITUCIONAL EL C. FRANCISCO ARTURO VEGA DE LAMADRID\n2013-2019.\nARTÍCULOS TRANSITORIOS\nPRIMERO.- La presente reforma entrará en vigor al día siguiente de su publicación en el Periódico Oficial del Estado de Baja California.\nSEGUNDO.- Las adecuaciones a las disposiciones reglamentarias correspondientes, deberán emitirse a más tardar dentro de los 150 días siguientes a partir de la publicación de las presentes reformas.\nTERCERO.- Se derogan todas aquellas disposiciones que se opongan al presente\nDecreto y continúan vigentes los actos, resoluciones, acuerdos y demás disposiciones de carácter general emitidas con fundamento en la Ley que se reforma. del Estado de Baja California, en la Ciudad de Mexicali, B.C., a los tres días del mes de diciembre del año dos mil quince.\nDIP. IRMA MARTÍNEZ MANRÍQUEZ\nPRESIDENTA\n(RUBRICA)\nDIP. MARIO OSUNA JIMÉNEZ\nSECRETARIO\n(RUBRICA)\nDE CONFORMIDAD CON LO DISPUESTO POR LA FRACCION I DEL ARTÍCULO 49\nMEXICALI, BAJA CALIFORNIA, A LOS NUEVE DÍAS DEL MES DE DICIEMBRE DEL\nAÑO DOS MIL QUINCE.\nFRANCISCO ARTURO VEGA DE LAMADRID\nGOBERNADOR DEL ESTADO\n(RÚBRICA)\nFRANCISCO RUEDA GOMEZ\nSECRETARIO GENERAL DE GOBIERNO\n(RÚBRICA)\nARTÍCULO PRIMERO TRANSITORIO DEL DECRETO No. 494, POR EL QUE SE\nREFORMAN LOS ARTÍCULOS 53, 81 TER, 90 TER, 90 QUATER, 95 BIS; 197-BIS-2; 197BIS-3, 197-BIS-5, 244 y 245, PUBLICADO EN EL PERIÓDICO OFICIAL No. 28, SECCION I,\nLEGISLATURA, SIENDO GOBERNADOR CONSTITUCIONAL EL C. FRANCISCO ARTURO\nVEGA DE LAMADRID 2013-2019.\nARTICULOS TRANSITORIOS\nSEGUNDO.- Conforme a lo dispuesto por el artículo cuarto transitorio de las reformas a\n2015 y el párrafo segundo del artículo décimo quinto transitorio de la Ley Nacional del\nSistema Integral de Justicia Penal para Adolescentes, el Congreso del Estado deberá fiscal sujeto a la viabilidad presupuestal correspondiente. A efecto de que cuente con los\nNacional del Sistema Integral de Justicia Penal para Adolescentes, así como para capacitación, adecuación y equipamiento de los espacios físicos.\nDe igual forma, los presupuestos de egresos del Poder Judicial del Estado para los ejercicios subsecuentes, deberán contener los recursos necesarios para la adecuada operación del sistema integral de justicia para adolescentes.\nTERCERO.- Una vez que entre en vigor la Ley Nacional del Sistema Integral de Justicia\nPenal para Adolescentes y hasta en tanto son nombrados Jueces de Control para\nAdolescentes, serán competentes para conocer del modelo acusatorio contenido en la Ley\nNacional, los Jueces de Control a los que alude el artículo 53, fracción VIII de esta Ley\nOrgánica.\nLos Jueces de Control deberán participar en los cursos de capacitación que con posterioridad a estas reformas, desarrolle el Consejo de la Judicatura.\nLos cursos de especialización en justicia para adolescentes que con anticipación a estas reformas haya instrumentado el Consejo de la Judicatura, tendrán plena validez para acreditar la especialización en la materia.\nCUARTO.- Los Jueces de Primera Instancia Especializados para Adolescentes que se señalan en la fracción V del artículo 53 de esta Ley Orgánica, fungirán como Jueces de\nControl para Adolescentes y ejercerán las facultades que establece la Ley Nacional del\nSistema Integral de Justicia Penal para Adolescentes y otras disposiciones normativas aplicables.\nQUINTO.- Hasta en tanto, no sean nombrados los Jueces de Ejecución del Sistema\nIntegral de Justicia Penal para Adolescentes, serán competentes para conocer en materia de ejecución en términos de la Ley Nacional y esta Ley, los Jueces que se señalan en los artículos tercero y cuarto transitorios de estas reformas.\nEn caso que sean nombrados Jueces de Control para Adolescentes, también serán competentes en materia de ejecución, en tanto se nombren Jueces de la materia.\nSEXTO.- De acuerdo a lo dispuesto por el artículo tercero transitorio de las reformas a la\n2015, los procedimientos de justicia para adolescentes y la ejecución de las medidas sancionadoras, iniciados con anterioridad a la entrada en vigor de la Ley Nacional, serán procedimientos y ejecución de medidas sancionadoras.\nSEPTIMO.- Los procesos jurisdiccionales en los que ya se encuentre integrado el\nTribunal de Juicio Oral o de enjuiciamiento para adultos de manera colegiada, así continuarán hasta ser culminados.\nOCTAVO.- El reglamento al que hace referencia el artículo 244 de este Decreto, deberá expedirse en un plazo de 15 días siguientes a la entrada en vigor de esta reforma. del Estado de Baja California, en la Ciudad de Mexicali, B.C., a los dieciséis días del mes de junio del año dos mil dieciséis.\nDIP. MÓNICA BEDOYA SERNA\nPRESIDENTA\n(RUBRICA)\nDIP. ROSA ISELA PERALTA CASILLAS\nSECRETARIA\n(RUBRICA)\nDE CONFORMIDAD CON LO DISPUESTO POR LA FRACCION I DEL ARTÍCULO 49\nMEXICALI, BAJA CALIFORNIA, A LOS DIECISÉIS DÍAS DEL MES DE JUNIO DEL\nAÑO DOS MIL DIECISÉIS.\nFRANCISCO RUEDA GÓMEZ\nSECRETARIO GENERAL DE GOBIERNO\nEn suplencia por ausencia del Gobernador del\nEstado, con fundamento en los artículos 45 y 52\n(RÚBRICA)\nLORETO QUINTERO QUINTERO\nOFICIAL MAYOR DE GOBIERNO\nEn suplencia por ausencia del Gobernador del\nEstado, con fundamento en el artículo 54\n(RÚBRICA)\nARTÍCULO UNICO TRANSITORIO DEL DECRETO No. 560, POR EL QUE SE\nREFORMA EL ARTÍCULO 197 BIS, PUBLICADO EN EL PERIÓDICO OFICIAL No. 43,\nLA H. XXI LEGISLATURA, SIENDO GOBERNADOR CONSTITUCIONAL EL C.\nFRANCISCO ARTURO VEGA DE LAMADRID 2013-2019.\nTRANSITORIOS\nPRIMERO.- El presente decreto entrará en vigor en los mismos términos y plazos en\nControversias Penales de conformidad con lo que establece su artículo primero transitorio. artículos segundo, tercero, cuarto y quinto transitorios de la Ley Nacional de Mecanismos\nAlternativos de Solución de Controversias Penales.\nDADO en el Salón de Sesiones “Lic. Benito Juárez García” del H. Poder Legislativo del Estado de Baja California, en la Ciudad de Mexicali, B.C., a los veinticinco días del mes de agosto del año dos mil dieciséis.\nDIP. MÓNICA BEDOYA SERNA\nPRESIDENTA\n(RUBRICA)\nDIP. ROSA ISELA PERALTA CASILLAS\nSECRETARIA\n(RUBRICA)\nDE CONFORMIDAD CON LO DISPUESTO POR LA FRACCION I DEL ARTÍCULO 49\nMEXICALI, BAJA CALIFORNIA, A LOS CINCO DÍAS DEL MES DE SEPTIEMBRE DEL AÑO\nDOS MIL DIECISÉIS.\nFRANCISCO ARTURO VEGA DE LAMADRID\nGOBERNADOR DEL ESTADO\n(RÚBRICA)\nFRANCISCO RUEDA GOMEZ\nSECRETARIO GENERAL DE GOBIERNO\n(RÚBRICA)\nARTÍCULO UNICO TRANSITORIO DEL DECRETO No. 577, POR EL QUE SE\nREFORMA EL ARTÍCULO 162, PUBLICADO EN EL PERIÓDICO OFICIAL No. 44,\nLA H. XXI LEGISLATURA, SIENDO GOBERNADOR CONSTITUCIONAL EL C.\nFRANCISCO ARTURO VEGA DE LAMADRID 2013-2019.\nTRANSITORIO\nÚNICO.- La presente reforma entrará en vigor al día siguiente de su publicación en el\nPeriódico Oficial del Estado. del Estado de Baja California, en la Ciudad de Mexicali, B.C., al primer día del mes de septiembre del año dos mil dieciséis.\nDIP. MÓNICA BEDOYA SERNA\nPRESIDENTA\n(RUBRICA)\nDIP. ROSA ISELA PERALTA CASILLAS\nSECRETARIA\n(RUBRICA)\nDE CONFORMIDAD CON LO DISPUESTO POR LA FRACCION I DEL ARTÍCULO 49\nMEXICALI, BAJA CALIFORNIA, A LOS NUEVE DÍAS DEL MES DE SEPTIEMBRE DEL\nAÑO DOS MIL DIECISÉIS.\nFRANCISCO ARTURO VEGA DE LAMADRID\nGOBERNADOR DEL ESTADO\n(RÚBRICA)\nFRANCISCO RUEDA GOMEZ\nSECRETARIO GENERAL DE GOBIERNO\n(RÚBRICA)\nARTÍCULO UNICO TRANSITORIO DEL DECRETO No. 120, POR EL QUE SE\nADECUA LA DENOMINACIÓN DEL CAPÍTULO XIV AL TÍTULO UNDÉCIMO; ASÍ COMO\nREFORMA EL ARTÍCULO 197 TER, PUBLICADO EN EL PERIÓDICO OFICIAL No. 41,\nLA H. XXII LEGISLATURA, SIENDO GOBERNADOR CONSTITUCIONAL EL C.\nFRANCISCO ARTURO VEGA DE LAMADRID 2013-2019.\nTRANSITORIO\nPRIMERO.- El presente Decreto entrará en vigor al día siguiente al de su publicación en el\nPeriódico Oficial del Estado de Baja California. deberá contemplar en su presupuesto anual, los recursos necesarios para la creación o en su caso mantenimiento de los Centros de Convivencia Familiar Supervisada. los Jueces de lo Familiar, ponderando el interés superior del menor, en instalaciones particulares, asociaciones o patronatos, debiendo observar las bases de organización y funcionamiento y, solicitar si así se requiere de la ampliación presupuestal correspondiente.\nCUARTO. - El Poder Judicial podrá acreditar al personal que preste sus servicios en los\nCentros de Convivencia Familiar Supervisada que no sean propios del Poder Judicial.\nQUINTO.- Se autoriza al Poder Judicial para que a través de los Jueces de lo Familiar del\nPartido Judicial de Mexicali, se acuerden convivencias familiares supervisadas dentro de las instalaciones especializadas del Centro de Atención a la Violencia Intrafamiliar en Mexicali, Asociación Civil, una vez que ésta cuente con la Sala de Convivencia Familiar Supervisada que al efecto se establezca conforme a las bases del presente Decreto, debiendo acreditar a su personal para el cumplimiento del mismo.\nSEXTO. – Los gastos de operación y funcionamiento de la Sala de Convivencia Familiar\nSupervisada del Centro de Atención a la Violencia Intrafamiliar en Mexicali, Asociación Civil, se programarán anualmente en el Presupuesto de Egresos del Estado.\nDADO en el Salón de Sesiones “Lic. Benito Juárez García” del H. Poder Legislativo del\nEstado de Baja California, en la Ciudad de Mexicali, B.C., a los veinticuatro días del mes de agosto del año dos mil diecisiete.\nDIP. EDGAR BENJAMÍN GÓMEZ MACÍAS\nPRESIDENTE\n(RÚBRICA)\nDIP. EVA MARÍA VÁSQUEZ HERNÁNDEZ\nSECRETARIA\n(RÚBRICA)\nDE CONFORMIDAD CON LO DISPUESTO POR LA FRACCION I DEL ARTÍCULO 49\nMEXICALI, BAJA CALIFORNIA, A LOS VEINTIOCHO DÍAS DE AGOSTO DEL AÑO DOS\nMIL DIECISIETE.\nFRANCISCO ARTURO VEGA DE LAMADRID\nGOBERNADOR DEL ESTADO\n(RÚBRICA)\nFRANCISCO RUEDA GÓMEZ\nSECRETARIO GENERAL DE GOBIERNO\n(RÚBRICA)\nARTÍCULO SEGUNDO TRANSITORIO DEL DECRETO No. 237, POR EL QUE SE\nREFORMAN LOS ARTÍCULOS 39 Y 81 BIS, PUBLICADO EN EL PERIÓDICO OFICIAL No.\nXXII LEGISLATURA, SIENDO GOBERNADOR CONSTITUCIONAL EL C. FRANCISCO\nARTURO VEGA DE LAMADRID 2013-2019.\nTRANSITORIO\nÚNICO.- La presente reforma entrará en vigor a los 180 días posteriores a la publicación del presente Decreto en el Periódico Oficial del Estado.\nDADO en el Salón de Sesiones “Lic. Benito Juárez García” del H. Poder Legislativo del Estado de Baja California, en la Ciudad de Mexicali, B.C., a los veintiséis días del mes de abril del año dos mil dieciocho.\nDIP. MARCO ANTONIO CORONA BOLAÑOS CACHO\nPRESIDENTE\n(RUBRICA)\nDIP. VICTORIA BENTLEY DUARTE\nSECRETARIA\n(RUBRICA)\nDE CONFORMIDAD CON LO DISPUESTO POR LA FRACCION I DEL ARTÍCULO 49\nMEXICALI, BAJA CALIFORNIA, A LOS NUEVE DÍAS DEL MES DE SEPTIEMBRE DEL\nAÑO DOS MIL DIECISÉIS.\nFRANCISCO ARTURO VEGA DE LAMADRID\nGOBERNADOR DEL ESTADO\n(RÚBRICA)\nFRANCISCO RUEDA GÓMEZ\nSECRETARIO GENERAL DE GOBIERNO\n(RÚBRICA)\nARTÍCULO ÚNICO TRANSITORIO DEL DECRETO No. 334, POR EL QUE SE\nREFORMA AL ARTÍCULO 168 FRACCIÓN II, ASÍ COMO LA ADICIÓN DEL TÍTULO\nDÉCIMO QUINTO, CAPÍTULO ÚNICO, DENOMINADO ´´DEL HABER DEL RETIRO´´ QUE\nCONTIENE EL ARTÍCULO 293, PUBLICADO EN EL PERIÓDICO OFICIAL No. 17, ÍNDICE,\nLEGISLATURA, SIENDO GOBERNADOR CONSTITUCIONAL EL C. FRANCISCO ARTURO\nVEGA DE LAMADRID 2013-2019.\nTRANSITORIO\nPRIMERO.- El presente Decreto, entrará en vigor a partir del 1 de junio de 2019, mismo que deberá publicarse en el Periódico Oficial del Estado.\nSEGUNDO.- Los Magistrados que se retiraron de su cargo, conforme lo previsto en el párrafo sexto inciso a) del artículo 58 de la Constitución Estatal, y que, mediante orden judicial, se les reconozca el Derecho al Haber de retiro, gozarán del mismo, conforme lo dispone el presente Decreto. Así mismo, el Poder Judicial del Estado, tomará las previsiones presupuestales para pagar el haber de retiro a que se refiere el presente transitorio.\nTERCERO.- El Consejo de la Judicatura, deberá expedir el Reglamento relativo al\nHaber de Retiro, dentro de un término de 90 días posteriores a la entrada en vigor de la presente reforma.\nCUARTO.- Los Magistrados Numerarios, que hayan sido nombrados, previa a la entrada en vigor del presente Decreto tendrán derechos a un haber de retiro de hasta 12 años en los términos dispuestos en la presente reforma y el reglamento correspondiente.\nQUINTO.- El plan a que hace referencia el Contrato No. 140898-2 de Fidecomiso\nMagistrados Numerarios del H. Tribunal Superior de Justicia del Estado de Baja California, sujetarse, para su ejecución, al Reglamento a que hace referencia el 293 de la Ley Orgánica del Estado de Baja California, en la Ciudad de Mexicali, B.C., a los veintiocho días del mes de marzo del año dos mil diecinueve.\nDIP. CARLOS ALBERTO TORRES TORRES\nPRESIDENTE\n(RÚBRICA)\nDIP. MARÍA TRINIDAD VACA CHACÓN\nSECRETARIA\n(RÚBRICA)\nDE CONFORMIDAD CON LO DISPUESTO POR LA FRACCIÓN I DEL ARTÍCULO 49\nMEXICALI, BAJA CALIFORNIA, A LOS VEINTINUEVE DÍAS DEL MES DE MARZO DEL\nAÑO DOS MIL DIECINUEVE.\nFRANCISCO ARTURO VEGA DE LAMADRID\nGOBERNADOR DEL ESTADO\n(RÚBRICA)\nFRANCISCO RUEDA GÓMEZ\nSECRETARIO GENERAL DE GOBIERNO\n(RÚBRICA)\nARTÍCULO ÚNICO TRANSITORIO DEL DECRETO No. 03, POR EL QUE SE\nREFORMA PARA CREAR UN ARTÍCULO 294, PUBLICADO EN EL PERIÓDICO OFICIAL\nNo. 61, SECCIÓN III, TOMO CXXVI, DE FECHA 13 DE DICIEMBRE DE 2019, EXPEDIDO\nPOR LA H. XXIII LEGISLATURA, SIENDO GOBERNADOR CONSTITUCIONAL EL C.\nJAIME BONILLA VALDEZ 2019-2021.\nTRANSITORIO\nPRIMERO.- La presente reforma entrará en vigor al día siguiente de su publicación en el Periódico Oficial del Estado de Baja California.\nSEGUNDO.- El Consejo de la Judicatura, deberá expedir el Reglamento relativo al\nHaber de Retiro, dentro de un término de 60 días posteriores a la entrada en vigor de la presente reforma.\nTERCERO.- La expedición de la Reglamentación deberá establecer el monto de las compensar las aportaciones de los años en que no lo hubieren hecho.\nDADO en el Salón de Sesiones “Lic. Benito Juárez García” del H. Poder Legislativo del Estado de Baja California, en la Ciudad de Mexicali, B.C., a los tres días del mes de octubre del año dos mil diecinueve.\nDIP. CATALINO ZAVALA MÁRQUEZ\nPRESIDENTE\n(RÚBRICA)\nDIP. ARACELI GERALDO NÚÑEZ\nSECRETARIA\n(RÚBRICA)\nDE CONFORMIDAD CON LO DISPUESTO POR LA FRACCIÓN I DEL ARTÍCULO 49\nMEXICALI, BAJA CALIFORNIA, A LOS SEIS DÍAS DEL MES DE NOVIEMBRE DEL AÑO\nDOS MIL DIECINUEVE.\nJAIME BONILLA VALDEZ\nGOBERNADOR DEL ESTADO\n(RÚBRICA)\nAMADOR RODRÍGUEZ LOZANO\nSECRETARIO GENERAL DE GOBIERNO\n(RÚBRICA)\nARTÍCULO PRIMERO TRANSITORIO DEL DECRETO No. 21, POR EL QUE SE\nREFORMAN LOS ARTÍCULOS 1, 2, 5, 6, 52, 59, 69, 102, 143, 197, 197 BIS Y 199; LA\nADICIÓN DE UN CAPÍTULO IX AL TÍTULO QUINTO DENOMINADO “DE LA\nORGANIZACIÓN DE LOS TRIBUNALES EN MATERIA LABORAL”, ASÍ COMO ADICIÓN\nDE LOS ARTÍCULOS 90 SEPTIES, 90 OCTIES Y 90 NONIES, PUBLICADO EN EL\nPERIÓDICO OFICIAL NO. 88, NÚMERO ESPECIAL, TOMO CXXVIII, DE FECHA 27 DE\nGOBERNADOR CONSTITUCIONAL EL C. JAIME BONILLA VALDEZ 2019-2021.\nTRANSITORIO\nPRIMERO. La presente reforma entrará en vigor al día siguiente al de su publicación en el Periódico Oficial del Estado.\nSEGUNDO. La operación del sistema de justicia laboral en el Estado de Baja\nFederación de fecha 1 de mayo de 2019, en el que se reforman, adicionan y derogan diversas disposiciones de la Ley Federal del Trabajo, de la Ley Orgánica del Poder Judicial de la Federación, de la Ley Federal de la Defensoría Pública, de la Ley del Instituto del\nFondo Nacional de la Vivienda para los Trabajadores y de la Ley del Seguro Social, en materia de Justicia Laboral, Libertad Sindical y Negociación Colectiva.\nTERCERO. La Implementación del Nuevo Sistema Laboral estará a cargo de la\nComisión Interinstitucional Estatal para la Implementación del Sistema de Justicia Laboral, en los términos de las disposiciones legales aplicables.\nCUARTO. El Sistema de Justicia Laboral entrará en vigor conforme a la declaratoria que realice el Congreso del Estado, previa solicitud por parte de la Comisión\nInterinstitucional Estatal para la Implementación del Sistema de Justicia Laboral, y sea publicada en el Periódico Oficial del Estado de Baja California.\nLos Tribunales en Materia Laboral iniciarán sus labores a partir de la Declaratoria que emita el Congreso del Estado y una vez que se hayan realizado las modificaciones presupuestales respectivas.\nQUINTO. La implementación del Sistema de Justicia Laboral en el municipio de San\nFelipe, Baja California, será posterior al primero de enero de 2022, en atención al Decreto\n246 emitido por esta Soberanía, debiendo mediar solicitud por parte de la Comisión\nInterinstitucional y declaratoria emitida el Congreso del Estado.\nDADO en Sesión Ordinaria Virtual de la XXIV Legislatura en la Ciudad de Mexicali, B.C., a los siete días del mes de octubre del año dos mil veintiuno.\nDIP. JUAN MANUEL MOLINA GARCÍA\nPRESIDENTE\n(RÚBRICA)\nDIP. ARACELI GERALDO NÚÑEZ\nSECRETARIA\n(RÚBRICA)\nDE CONFORMIDAD CON LO DISPUESTO POR LA FRACCIÓN I DEL ARTÍCULO 49\nCALIFORNIA, IMPRÍMASE Y PUBLÍQUESE.\nMEXICALI, BAJA CALIFORNIA, A LOS OCHO DÍAS DEL MES DE OCTUBRE DEL AÑO\nDOS MIL VEINTIUNO.\nJAIME BONILLA VALDEZ\nGOBERNADOR DEL ESTADO\n(RÚBRICA)\nAMADOR RODRÍGUEZ LOZANO\nSECRETARIO GENERAL DE GOBIERNO\n(RÚBRICA)\nARTÍCULO ÚNICO TRANSITORIO DEL DECRETO No. 122, POR EL QUE SE\nAPRUEBA LA REFORMA A LOS ARTÍCULOS 1, 2, 27, 29, 45, 51, 53, 69, 161, 168, 197\nBIS-4 Y 197 TER; LA ADICIÓN DE UN CAPÍTULO X Y XI DENOMINADOS “DE LA\nORGANIZACIÓN DE LOS JUZGADOS ESPECIALIZADOS EN VIOLENCIA FAMILIAR\nCONTRA LAS MUJERES” Y “DE LAS CENTRALES DE ACTUARIOS” AL TÍTULO QUINTO,\nCOMO TAMBIÉN LA ADICIÓN DE LOS ARTÍCULOS DE NUEVA CREACIÓN 32 BIS, 90\nDECIES, 90 UNDECIES Y 90 DODECIES; PUBLICADO EN EL PERIÓDICO OFICIAL NO.\n54, SECCIÓN IV, TOMO CXXIX, DE FECHA 02 DE SEPTIEMBRE DE 2022, EXPEDIDO\nPOR LA H. XXIV LEGISLATURA, SIENDO GOBERNADORA CONSTITUCIONAL LA C.\nMARINA DEL PILAR ÁVILA OLMEDA 2021-2027.\nTRANSITORIOS\nPRIMERO. La reforma a los artículos entrará en vigor al día siguiente de su publicación en el\nPeriódico Oficial del Estado. correspondiente, a efecto de que cuente con los recursos adicionales y suficientes para la creación de los Juzgados Especializados en Violencia Familiar contra las Mujeres.\nTERCERO. Las reformas a los artículos 1, 2, 53, 69 y 90 DECIES de la Ley Orgánica del\nViolencia Familiar contra las Mujeres, entrarán en vigor a partir de la Declaratoria que emita el Congreso del Estado, una vez que se hayan realizado las modificaciones presupuestales respectivas.\nSe cumplieron las condiciones establecidas en este Artículo Transitorio Tercero, por lo que entraron en vigor las reformas hechas por este Decreto No. 122 a los artículos 1, 2, 53, 69 y 90 DECIES de la Declaratoria, para realizar las gestiones administrativas necesarias para poner en funcionamiento los Juzgados Especializados en Violencia Familiar contra las Mujeres, así como los diversos cambios estructurales derivados del presente decreto.\nQUINTO. Las Centrales de Actuario, comenzarán a funcionar en el orden y fechas que determine el Pleno del Consejo de la Judicatura Estatal, conforme a las posibilidades presupuestales y necesidades del servicio.\nSEXTO. El Consejo de la Judicatura deberá expedir el Reglamento de las Centrales de\nActuarios, dentro de un término de 60 días posteriores a la entrada en vigor de la presente reforma.\nSÉPTIMO. Las presentes reformas no afectarán los derechos adquiridos y demás prestaciones reconocidas a los trabajadores con anterioridad al presente Decreto.\nDADO en Sesión Ordinaria de la XXIV Legislatura en la Ciudad de Mexicali, B.C., a los veinticinco días del mes de agosto del año dos mil veintidós.\nDIP. ALEJANDRA MARÍA ANG HERNÁNDEZ\nPRESIDENTA\n(RÚBRICA)\nDIP. DUNNIA MONTSERRAT MURILLO LÓPEZ\nSECRETARIA\n(RÚBRICA)\nDE CONFORMIDAD CON LO DISPUESTO POR LA FRACCIÓN I DEL ARTÍCULO 49\nCALIFORNIA, IMPRÍMASE Y PUBLÍQUESE.\nMEXICALI, BAJA CALIFORNIA, A LOS TREINTA Y UN DÍAS DEL MES DE AGOSTO DEL\nAÑO DOS MIL VEINTIDÓS.\nMARINA DEL PILAR ÁVILA OLMEDA\nGOBERNADORA DEL ESTADO\nDE BAJA CALIFORNIA\n(RÚBRICA)\nCATALINO ZAVALA MÁRQUEZ\nSECRETARIO GENERAL DE GOBIERNO\nDEL ESTADO DE BAJA CALIFORNIA\n(RÚBRICA)\nSENTENCIA DE CONTROVERSIA CONSTITUCIONAL 35/2020, NOTIFICADA AL\nDE CONFORMIDAD A SU PUNTO RESOLUTIVO SEGUNDO, SE DECLARA LA\nINVALIDEZ DEL DECRETO 03 POR EL QUE SE REFORMÓ LA LEY ORGÁNICA DEL\nPODER JUDICIAL DEL ESTADO DE BAJA CALIFORNIA PARA CREAR UN ARTÍCULO\n294, PUBLICADO EN EL PERIÓDICO OFICIAL DEL ESTADO EL 13 DE DICIEMBRE DE\n2019; SIENDO GOBERNADOR CONSTITUCIONAL EL C. JAIME BONILLA VALDEZ 2019-\n2021.\nARTÍCULO ÚNICO TRANSITORIO DEL DECRETO No. 199, POR EL QUE SE\nAPRUEBA LA REFORMA AL ARTÍCULO 57; PUBLICADO EN EL PERIÓDICO OFICIAL\nNO. 6, ÍNDICE, TOMO CXXX, DE FECHA 27 DE ENERO DE 2023, EXPEDIDO POR LA H.\nXXIV LEGISLATURA, SIENDO GOBERNADORA CONSTITUCIONAL LA C. MARINA DEL\nPILAR ÁVILA OLMEDA 2021-2027.\nTRANSITORIOS\nÚNICO. La presente reforma entrará en vigor al siguiente día de su publicación en el\nPeriódico Oficial del Estado.\nDADO en Sesión Ordinaria de la XXIV Legislatura en la Ciudad de Mexicali, B.C., a los doce días del mes de enero del año dos mil veintitrés.\nDIP. MARÍA DEL ROCÍO ADAME MUÑOZ\nPRESIDENTA\n(RÚBRICA)\nDIP. DUNNIA MONTSERRAT MURILLO LÓPEZ\nSECRETARIA\n(RÚBRICA)\nDE CONFORMIDAD CON LO DISPUESTO POR LA FRACCIÓN I DEL ARTÍCULO 49\nCALIFORNIA, IMPRÍMASE Y PUBLÍQUESE.\nMEXICALI, BAJA CALIFORNIA, A LOS TRECE DÍAS DEL MES DE enero DEL AÑO DOS\nMIL VEINTITRÉS.\nMARINA DEL PILAR ÁVILA OLMEDA\nGOBERNADORA DEL ESTADO\nDE BAJA CALIFORNIA\n(RÚBRICA)\nCATALINO ZAVALA MÁRQUEZ\nSECRETARIO GENERAL DE GOBIERNO\nDEL ESTADO DE BAJA CALIFORNIA\n(RÚBRICA)\nARTÍCULO CUARTO TRANSITORIO DEL DECRETO No. 223, POR EL QUE SE\nAPRUEBA LA REFORMA AL ARTÍCULO 78; PUBLICADO EN EL PERIÓDICO OFICIAL No.\n22, DE FECHA 21 DE ABRIL DE 2023, SECCIÓN I, TOMO CXXX, EXPEDIDO POR LA H.\nXXIV LEGISLATURA, SIENDO GOBERNADORA CONSTITUCIONAL LA C. MARINA DEL\nPILAR ÁVILA OLMEDA 2021-2027.\nTRANSITORIO\nÚNICO.- La presente reforma entrará en vigor al día siguiente de su publicación en el\nPeriódico Oficial del Estado.\nDADO en Sesión de Clausura de la H. XXIV Legislatura Constitucional del Estado, en la\nCiudad de Mexicali, B.C., a los treinta y un días del mes de marzo del año dos mil veintitrés.\nDIP. MARÍA DEL ROCÍO ADAME MUÑOZ\nPRESIDENTA\n(RÚBRICA)\nDIP. DUNNIA MONTSERRAT MURILLO LÓPEZ\nSECRETARIA\n(RÚBRICA)\nDE CONFORMIDAD CON LO DISPUESTO POR LA FRACCIÓN I DEL ARTÍCULO 49 DE\nCALIFORNIA, IMPRÍMASE Y PUBLÍQUESE.\nMEXICALI, BAJA CALIFORNIA, A LOS CINCO DÍAS DEL MES DE ABRIL DEL AÑO\nDOS MIL VEINTITRÉS.\nMARINA DEL PILAR ÁVILA OLMEDA\nGOBERNADORA DEL ESTADO\nDE BAJA CALIFORNIA\n(RÚBRICA)\nCATALINO ZAVALA MÁRQUEZ\nSECRETARIO GENERAL DE GOBIERNO\nDEL ESTADO DE BAJA CALIFORNIA\n(RÚBRICA)\nARTÍCULO ÚNICO TRANSITORIO DEL DECRETO No. 293, POR EL QUE SE\nAPRUEBA LA REFORMA A LOS ARTÍCULOS 168 Y 294; PUBLICADO EN EL PERIÓDICO\nOFICIAL No. 55, ÍNDICE, DE FECHA 25 DE SEPTIEMBRE DE 2023, TOMO CXXX,\nEXPEDIDO POR LA H. XXIV LEGISLATURA, SIENDO GOBERNADORA\nCONSTITUCIONAL LA C. MARINA DEL PILAR ÁVILA OLMEDA 2021-2027.\nARTICULOS TRANSITORIOS\nPRIMERO.- La presente reforma entrará en vigor al día siguiente de su publicación en el\nPeriódico Oficial del Estado de Baja California.\nSEGUNDO.- El Consejo de la Judicatura deberá expedir el Reglamento de la prestación periódica y temporal que garantice la independencia y autonomía en la función judicial, de las y los Jueces del Poder Judicial del Estado a que se refiere el presente Decreto, dentro de un plazo no mayor a 90 días posteriores a la entrada en vigor de la presente reforma.\nDADO en Sesión Ordinaria de la XXIV Legislatura en la Ciudad de Mexicali, B.C., a los siete días del mes de septiembre del año dos mil veintitrés.\nDIP. MANUEL GUERRERO LUNA\nPRESIDENTE\n(RÚBRICA)\nDIP. DUNNIA MONTSERRAT MURILLO LÓPEZ\nSECRETARIA\n(RÚBRICA)\nDE CONFORMIDAD CON LO DISPUESTO POR LA FRACCIÓN I DEL ARTÍCULO 49 DE\nCALIFORNIA, IMPRÍMASE Y PUBLÍQUESE.\nMEXICALI, BAJA CALIFORNIA, A LOS ONCE DÍAS DEL MES DE SEPTIEMBRE\nDEL AÑO DOS MIL VEINTITRÉS.\nMARINA DEL PILAR ÁVILA OLMEDA\nGOBERNADORA DEL ESTADO\nDE BAJA CALIFORNIA\n(RÚBRICA)\nCATALINO ZAVALA MÁRQUEZ\nSECRETARIO GENERAL DE GOBIERNO\nDEL ESTADO DE BAJA CALIFORNIA\n(RÚBRICA)\nARTÍCULO ÚNICO TRANSITORIO DEL DECRETO No. 329, POR EL QUE SE\nAPRUEBA LA REFORMA A LOS ARTÍCULOS 1, 2, 53, 69, 90 UNDECIES Y 90\nDUODECIES, ASÍ COMO LA DENOMINACIÓN DEL CAPÍTULO XI DEL TÍTULO QUINTO\nPARA LLAMARSE “DE LA ORGANIZACIÓN DE LOS JUZGADOS ESPECIALIZADOS EN\nMATERIA HIPOTECARIA”, TRASLADÁNDOSE AL MISMO TÍTULO LA DENOMINACIÓN Y\nCONTENIDO DE DICHO CAPÍTULO A UN CAPÍTULO XII IDENTIFICADO COMO\n“CENTRALES DE ACTUARIOS”; Y QUE ADICIONA LOS ARTÍCULOS 58 BIS Y 90\nTERDECIES; PUBLICADO EN EL PERIÓDICO OFICIAL No. 66, NÚMERO ESPECIAL, DE\nFECHA 29 DE NOVIEMBRE DE 2023, TOMO CXXX, EXPEDIDO POR LA H. XXIV\nLEGISLATURA, SIENDO GOBERNADORA CONSTITUCIONAL LA C. MARINA DEL PILAR\nÁVILA OLMEDA 2021-2027.\nTRANSITORIOS\nPRIMERO.- Las presentes reformas entrarán en vigor al día siguiente de su publicación en el Periódico Oficial del Estado de Baja California, con salvedad de lo dispuesto en los siguientes artículos transitorios.\nSEGUNDO.- Las reformas relativas a los Juzgados de Primera Instancia Especializados en\nMateria Hipotecaria entraran en vigor a los 90 días naturales, contados a partir de la publicación de las presentes reformas.\nTERCERO.- Durante el Plazo a que se refiere el artículo segundo transitorio, el Poder\nJudicial deberá realizar las acciones siguientes:\nI. Efectuar las adecuaciones presupuestales necesarias;\nII. Llevar a cabo las gestiones administrativas que estime pertinentes para reclutar y creación; y,\nIII. Concretar las modificaciones reglamentarias, acciones administrativas y demás que resulten imprescindibles.\nCUARTO.- La implementación y funcionamiento de los Juzgados de Primera Instancia\nEspecializados en Materia Hipotecaria y de los Juzgados Itinerantes, estará sujeta a la\nQUINTO.- Los asuntos en materia hipotecaria presentados con anterioridad a la entrada en vigor de las presentes reformas, se seguirán sustanciando hasta su conclusión conforme a las disposiciones vigentes al momento de su inicio, en los Juzgados que los conocieron en su primer momento.\nSEXTO.- Las presentes reformas no afectaran los derechos adquiridos y demás con anterioridad a la entrada en vigor de las mismas.\nDADO en Sesión Ordinaria de la XXIV Legislatura en la Ciudad de Mexicali, B.C., a los dieciséis días del mes de noviembre del año dos mil veintitrés.\nDIP. MANUEL GUERRERO LUNA\nPRESIDENTE\n(RÚBRICA)\nDIP. DUNNIA MONTSERRAT MURILLO LÓPEZ\nSECRETARIA\n(RÚBRICA)\nDE CONFORMIDAD CON LO DISPUESTO POR LA FRACCIÓN I DEL ARTÍCULO 49 DE\nCALIFORNIA, IMPRÍMASE Y PUBLÍQUESE.\nMEXICALI, BAJA CALIFORNIA, A LOS VEINTITRÉS DÍAS DEL MES DE\nNOVIEMBRE DEL AÑO DOS MIL VEINTITRÉS.\nMARINA DEL PILAR ÁVILA OLMEDA\nGOBERNADORA DEL ESTADO\nDE BAJA CALIFORNIA\n(RÚBRICA)\nCATALINO ZAVALA MÁRQUEZ\nSECRETARIO GENERAL DE GOBIERNO\nDEL ESTADO DE BAJA CALIFORNIA\n(RÚBRICA)\nARTÍCULO PRIMERO TRANSITORIO DEL DECRETO NO. 349, POR EL QUE\nREFORMAN LOS ARTÍCULOS 1, 3, 4, 8, 44, 54, 60, 69, 73, 75, 88, 90, 90 DECIES, 101,\n102, 187, 197, 218, 222, 226, 235, 236, 245 Y 246; ASÍ COMO LA DENOMINACIÓN DEL\nCAPÍTULO XII, DEL TÍTULO QUINTO, PARA DENOMINARSE “DEL MODELO DE\nGESTIÓN Y DE LAS CENTRALES DE ACTUARIOS” Y LOS ARTÍCULOS 90 DUODECIES\nY 90 TERDECIES; SE ADICIONAN LOS ARTÍCULOS 73 BIS, 78 BIS Y 90\nQUATERDECIES; Y SE DEROGAN LOS ARTÍCULOS 55, 56, 57 Y 57 BIS; PUBLICADO EN\nCXXXI, EXPEDIDO POR LA H. XXIV LEGISLATURA, SIENDO GOBERNADORA\nCONSTITUCIONAL LA C. MARINA DEL PILAR ÁVILA OLMEDA 2021-2027.\nARTÍCULOS TRANSITORIOS\nPrimero.- Las presentes reformas entrarán en vigor el día en que entre en vigor en el Estado el Código Nacional de Procedimientos Civiles y Familiares, de conformidad con la declaratoria que para tal efecto, emita el Congreso del Estado, con la salvedad prevista en el artículo Segundo Transitorio.\nSegundo.- La reforma al artículo 90 Decies entrará en vigor en los términos del artículo\nTercero Transitorio del Decreto 122, publicado en el Periódico Oficial del Estado de Baja\nCalifornia, el 02 de septiembre del año 2022.\nSe cumplió la condición establecida en este Artículo Transitorio Segundo, por lo que entró en vigor la reforma hecha en este Decreto 349 al artículo 90 DECIES\nTercero.- Sin perjuicio de la entrada en vigor del Código Nacional de Procedimientos Civiles y Familiares, y de conformidad con los transitorios Primero y Segundo de las presentes reformas, el Código de Procedimientos Civiles para el Estado de Baja California, publicado en el Periódico Oficial No. 21, de fecha 26 de mayo de 1995, seguirá siendo supletorio de las leyes u ordenamientos estatales que así lo dispongan y que regulen procedimientos distintos a los de naturaleza civil o familiar.\nCuarto.- De conformidad con la viabilidad presupuestal con que cuente el Poder Judicial, deberá realizar las acciones siguientes:\nI. Efectuar las adecuaciones presupuestales necesarias;\nII. Llevar a cabo las gestiones administrativas que estime pertinentes para capacitar a las personas servidoras públicas, y\nIII. Concretar las modificaciones reglamentarias, acciones administrativas y demás que resulten imprescindibles.\nQuinto.- Las presentes reformas no afectarán las relaciones laborales, burocráticas o de servicios personales; ni los derechos adquiridos o demás prestaciones, que con anterioridad a su entrada en vigor, gozaban los servidores públicos o prestadores de servicios del Poder\nJudicial del Estado.\nSexto.- El ejercicio de las atribuciones que con la vigencia de las presentes reformas competerán a las personas Jueces de Primera Instancia Civil o Familiar, en relación con la aplicación del Código Nacional de Procedimientos Civiles y Familiares en el Estado, no afectará sus nombramientos, la duración o periodo de ejercicio de su encargo, ni los decreto.\nDADO en Sesión Extraordinaria de la XXIV Legislatura en la Ciudad de Mexicali, B.C., a los cuatro días del mes de diciembre del año dos mil veintitrés.\nDIP. ARACELI GERALDO NÚÑEZ\nPRESIDENTA\n(RÚBRICA)\nDIP. MANUEL GUERRERO LUNA\nSECRETARIO\n(RÚBRICA)\nDE CONFORMIDAD CON LO DISPUESTO POR LA FRACCIÓN I DEL ARTÍCULO 49\nCALIFORNIA, IMPRÍMASE Y PUBLÍQUESE.\nMEXICALI, BAJA CALIFORNIA, A LOS CUATRO DÍAS DEL MES DE DICIEMBRE\nDEL AÑO DOS MIL VEINTITRÉS.\nMARINA DEL PILAR ÁVILA OLMEDA\nGOBERNADORA DEL ESTADO\nDE BAJA CALIFORNIA\n(RÚBRICA)\nALFREDO ÁLVAREZ CÁRDENAS\nSECRETARIO GENERAL DE GOBIERNO\nDEL ESTADO DE BAJA CALIFORNIA\n(RÚBRICA)\nARTÍCULO TERCERO TRANSITORIO DEL DECRETO No. 377, POR EL QUE SE\nAPRUEBA LA REFORMA AL ARTÍCULO 72; PUBLICADO EN EL PERIÓDICO OFICIAL No.\n7, DE FECHA 09 DE FEBRERO DE 2024, ÍNDICE, TOMO CXXXI, EXPEDIDO POR LA H.\nXXIV LEGISLATURA, SIENDO GOBERNADORA CONSTITUCIONAL LA C. MARINA DEL\nPILAR ÁVILA OLMEDA 2021-2027.\nTRANSITORIOS\nÚNICO.- La presente reforma entrará en vigor al día siguiente de su publicación en el\nPeriódico Oficial del Estado.\nDADO en Sesión Ordinaria de la XXIV Legislatura en la Ciudad de Mexicali, B.C., a los veinticinco días del mes de enero del año dos mil veinticuatro.\nDIP. ARACELI GERALDO NÚÑEZ\nPRESIDENTA\n(RÚBRICA)\nDIP. MANUEL GUERRERO LUNA\nSECRETARIO\n(RÚBRICA)\nDE CONFORMIDAD CON LO DISPUESTO POR LA FRACCIÓN I DEL ARTÍCULO 49 DE\nCALIFORNIA, IMPRÍMASE Y PUBLÍQUESE.\nMEXICALI, BAJA CALIFORNIA, A LOS VEINTINUEVE DÍAS DEL MES DE ENERO\nDEL AÑO DOS MIL VEINTICUATRO.\nMARINA DEL PILAR ÁVILA OLMEDA\nGOBERNADORA DEL ESTADO\nDE BAJA CALIFORNIA\n(RÚBRICA)\nALFREDO ÁLVAREZ CÁRDENAS\nSECRETARIO GENERAL DE GOBIERNO\nDEL ESTADO DE BAJA CALIFORNIA\n(RÚBRICA)\nARTÍCULO TERCERO TRANSITORIO DEL DECRETO No. 405, POR EL QUE SE\nAPRUEBA LA REFORMA AL ARTÍCULO 29; PUBLICADO EN EL PERIÓDICO OFICIAL No.\n18, DE FECHA 05 DE ABRIL DE 2024, ÍNDICE, TOMO CXXXI, EXPEDIDO POR LA H.\nXXIV LEGISLATURA, SIENDO GOBERNADORA CONSTITUCIONAL LA C. MARINA DEL\nPILAR ÁVILA OLMEDA 2021-2027.\nTRANSITORIOS:\nÚNICO. El presente decreto entrará en vigor al día siguiente de su publicación en el\nPeriódico Oficial del Estado de Baja California.\nDADO en Sesión Extraordinaria de la XXIV Legislatura en la Ciudad de Mexicali, B.C., a los ocho días del mes de marzo del año dos mil veinticuatro.\nDIP. ARACELI GERALDO NÚÑEZ\nPRESIDENTA\n(RÚBRICA)\nDIP. MANUEL GUERRERO LUNA\nSECRETARIO\n(RÚBRICA)\nDE CONFORMIDAD CON LO DISPUESTO POR LA FRACCIÓN I DEL ARTÍCULO 49\nCALIFORNIA, IMPRÍMASE Y PUBLÍQUESE.\nMEXICALI, BAJA CALIFORNIA, A LOS QUINCE DÍAS DEL MES DE MARZO DEL\nAÑO DOS MIL VEINTICUATRO.\nMARINA DEL PILAR ÁVILA OLMEDA\nGOBERNADORA DEL ESTADO\nDE BAJA CALIFORNIA\n(RÚBRICA)\nALFREDO ÁLVAREZ CÁRDENAS\nSECRETARIO GENERAL DE GOBIERNO\nDEL ESTADO DE BAJA CALIFORNIA\n(RÚBRICA)\nARTÍCULO ÚNICO LA HONORABLE XXV LEGISLATURA CONSTITUCIONAL DEL\nESTADO DE BAJA CALIFORNIA, CON FUNDAMENTO EN EL TRANSITORIO TERCERO\nDEL DECRETO NÚMERO 122 PUBLICADO EN EL PERIÓDICO OFICIAL DEL ESTADO\nCON FECHA 2 DE SEPTIEMBRE DE 2022, POR EL QUE SE REFORMAN LOS\nARTÍCULOS 1, 2, 53, 69 Y 90 DECIES DE LA LEY ORGÁNICA DEL PODER JUDICIAL DEL\nESTADO DE BAJA CALIFORNIA, EN ATENCIÓN A LA SOLICITUD REALIZADA DE\nEMITIR LA DECLARATORIA CORRESPONDIENTE, POR PARTE DEL MAGISTRADO\nALEJANDRO ISAAC FRAGOZO LÓPEZ, EN SU CARÁCTER DE PRESIDENTE DEL\nTRIBUNAL SUPERIOR DE JUSTICIA Y DEL CONSEJO DE LA JUDICATURA DEL\nESTADO, DECLARA QUE EN BAJA CALIFORNIA, HAN ENTRADO EN VIGOR, LOS\nJUZGADOS ESPECIALIZADOS EN VIOLENCIA FAMILIAR CONTRA LAS MUJERES. LO\nANTERIOR DEBIDO A QUE EL PODER JUDICIAL DEL ESTADO, SE ENCUENTRA\nPLENAMENTE PREPARADO PARA SU IMPLEMENTACIÓN, CONTANDO CON LA\nINFRAESTRUCTURA NECESARIA, ESPACIOS ADECUADOS, REQUERIMIENTOS\nTÉCNICOS, PERSONAL CAPACITADO, ASÍ COMO JUECES ESPECIALIZADOS\nNOMBRADOS PARA DESEMPEÑAR ESTAS FUNCIONES. PUBLICADO EN EL\nCXXXI, EXPEDIDA POR LA H. XXV LEGISLATURA, SIENDO GOBERNADORA\nCONSTITUCIONAL LA C. MARINA DEL PILAR ÁVILA OLMEDA 2021-2027.\nÚNICO.- LA PRESENTE DECLARATORIA ENTRARÁ EN VIGOR EL DÍA DE SU\nPUBLICACIÓN EN EL PERIÓDICO OFICIAL DEL ESTADO.\nDADO en Sesión Extraordinaria de la XXIV Legislatura en la Ciudad de Mexicali, B.C., a los cuatro días del mes de octubre del año dos mil veinticuatro.\nDIP. DUNNIA MONTSERRAT MURILLO LÓPEZ\nPRESIDENTA\n(RÚBRICA)\nDIP. ALEJANDRA MARÍA ANG HERNÁNDEZ\nSECRETARIA\n(RÚBRICA)\nDE CONFORMIDAD CON LO DISPUESTO POR LA FRACCIÓN I DEL ARTÍCULO 49\nCALIFORNIA, IMPRÍMASE Y PUBLÍQUESE.\nMEXICALI, BAJA CALIFORNIA, A LOS NUEVE DÍAS DEL MES DE OCTUBRE DEL\nAÑO DOS MIL VEINTICUATRO.\nMARINA DEL PILAR ÁVILA OLMEDA\nGOBERNADORA DEL ESTADO\nDE BAJA CALIFORNIA\n(RÚBRICA)\nALFREDO ÁLVAREZ CÁRDENAS\nSECRETARIO GENERAL DE GOBIERNO\nDEL ESTADO DE BAJA CALIFORNIA\n(RÚBRICA)",
  "ordenamiento": "REGLAMENTO",
  "jurisdiccion": "BAJA CALIFORNIA",
  "fuente_oficial": "Periódico Oficial",
  "FECHA PER OFIC": "2024/10/11",
  "ESTATUS": "VIGENTE",
  "TOMO": "TOMO_I",
  "URL": "https://www.congresobc.gob.mx/Documentos/ProcesoParlamentario/Leyes/TOMO_I/20241011_LEYORPJE.PDF",
  "es_escaneado": false,
  "tiene_tablas": true,
  "materia": [
    "administrativo",
    "legislativo",
    "gobernanza"
  ]
}