{
  "titulo": "Ley DE PROTECCIÓN DE DATOS PERSONALES PARA EL SECTOR PÚBLICO DEL ESTADO DE BAJA CALIFORNIA",
  "Contenido": ".\nActualización Legislativa.\nLEY DE PROTECCIÓN DE DATOS PERSONALES PARA EL SECTOR\nPÚBLICO DEL ESTADO DE BAJA CALIFORNIA\nPublicada en el Periódico Oficial No. 56, Número Especial, de fecha 16 de septiembre de 2025, Tomo CXXXII.\nTÍTULO PRIMERO\nDISPOSICIONES GENERALES\nCapítulo Único\nDel Objeto de la Ley\nARTÍCULO 1.- La presente Ley es de orden público y tiene por objeto desarrollar las bases, principios y procedimientos para garantizar el derecho que tiene toda persona a la protección de datos personales, en posesión de responsables del sector público estatal y municipal, establecidas en la Ley General de Protección de Datos Personales en Posesión de\nSujetos Obligados y el apartado C fracciones III y IV del artículo 7 de la Constitución Política\nARTÍCULO 2.- La presente Ley tiene por objeto:\nI. Desarrollar las bases, principios y procedimientos para garantizar el derecho que tiene toda persona a la protección de sus datos personales, en posesión de responsables del sector público estatal y municipal;\nII. Desarrollar las bases mínimas y condiciones homogéneas que regirán el tratamiento de los datos personales y el ejercicio de los derechos de acceso, rectificación, cancelación y oposición, mediante procedimientos sencillos y expeditos previstos en la Ley General;\nIII. Garantizar la observancia de los principios de protección de datos personales previstos en la presente Ley y demás disposiciones que resulten aplicables en la materia;\nIV. Proteger los datos personales en posesión de cualquier autoridad, entidad, órgano y organismo de los Poderes Ejecutivo, Legislativo y Judicial, órganos autónomos, fideicomisos y fondos públicos, del Estado y los municipios, con la finalidad de regular su debido tratamiento;\nV. Garantizar que toda persona pueda ejercer el derecho a la protección de los datos personales;\nVI. Promover, fomentar y difundir una cultura de protección de datos personales;\nLey de Protección de Datos Personales para el Sector Público Página 1\n.\nActualización Legislativa.\nVII. Establecer los mecanismos para garantizar el cumplimiento y la efectiva aplicación de las medidas de apremio que correspondan para aquellas conductas que contravengan las disposiciones previstas en esta Ley; y,\nVIII. Instrumentar la Política Estatal en materia de protección de datos personales en posesión de responsables del sector público en concordancia con la política nacional.\nARTÍCULO 3.- Para los efectos de la presente Ley se entenderá por:\nI. Autoridades Garantes: Transparencia para el Pueblo, el Órgano de Control y\nDisciplina del Poder Judicial del Estado, la Contraloría Interna del Poder Legislativo del\nEstado, los órganos internos de control o equivalentes de los Órganos Constitucionales\nAutónomos del Estado;\nII. Áreas: Instancias de los responsables previstos en los respectivos reglamentos internos, estatutos orgánicos o instrumentos equivalentes, que cuentan o puedan contar, dar tratamiento, y ser responsables o encargadas de los datos personales;\nIII. Aviso de privacidad: Documento a disposición de la persona titular de la información de forma física, electrónica o en cualquier formato generado por el responsable, a partir del momento en el cual se recaben sus datos personales, con el objeto de informarle los propósitos del tratamiento de los mismos;\nIV. Bases de datos: Conjunto ordenado de datos personales referentes a una persona identificada o identificable, condicionados a criterios determinados, con independencia de la forma o modalidad de su creación, tipo de soporte, procesamiento, almacenamiento y organización;\nV. Bloqueo: Identificación y conservación de datos personales una vez cumplida la finalidad para la cual fueron recabados, con el único propósito de determinar posibles responsabilidades en relación con su tratamiento, hasta el plazo de prescripción legal o contractual de éstas. Durante dicho periodo, los datos personales no podrán ser objeto de tratamiento y transcurrido éste, se procederá a su cancelación en la base de datos que corresponda;\nVI. Comité de Transparencia: Instancia a la que hace referencia el artículo 32 de la\nLey de Transparencia, Acceso a la Información Pública y Apertura Institucional para el Estado de Baja California;\nVII. Cómputo en la nube: Modelo de provisión externa de servicios de cómputo bajo demanda, que implica el suministro de infraestructura, plataforma o programa informático, distribuido de modo flexible, mediante procedimientos virtuales, en recursos compartidos dinámicamente;\nLey de Protección de Datos Personales para el Sector Público Página 2\n.\nActualización Legislativa.\nVIII. Consentimiento: Manifestación de la voluntad libre, específica e informada de la persona titular de los datos mediante la cual se efectúa el tratamiento de los mismos;\nIX. Datos personales: Cualquier información concerniente a una persona identificada o identificable. Se considera que una persona es identificable cuando su identidad pueda determinarse directa o indirectamente a través de cualquier información;\nX. Datos personales sensibles: Aquellos que se refieran a la esfera más íntima de su titular, o cuya utilización indebida pueda dar origen a discriminación o conlleve un riesgo grave para éste. De manera enunciativa, más no limitativa, se consideran sensibles los datos personales que puedan revelar aspectos como origen racial o étnico, estado de salud presente o futuro, información genética, creencias religiosas, filosóficas y morales, opiniones políticas y preferencia sexual;\nXI. Derechos ARCO: Derechos de acceso, rectificación, cancelación y oposición al tratamiento de datos personales;\nXII. Días: Días hábiles;\nXIII. Disociación: Procedimiento mediante el cual los datos personales no pueden asociarse a la persona titular ni permitir, por su estructura, contenido o grado de desagregación, la identificación de la misma;\nXIV. Documento de seguridad: Instrumento que describe y da cuenta de manera general sobre las medidas de seguridad técnicas, físicas y administrativas adoptadas por el responsable para garantizar la confidencialidad, integridad y disponibilidad de los datos personales que posee;\nXV. Evaluación de impacto en la protección de datos personales: Documento mediante el cual los responsables que pretendan poner en operación o modificar políticas públicas, programas, sistemas o plataformas informáticas, aplicaciones electrónicas o cualquier otra tecnología que implique el tratamiento intensivo o relevante de datos personales, valoran los impactos reales respecto de determinado tratamiento de datos personales, a efecto de identificar y mitigar posibles riesgos relacionados con los principios, deberes y derechos de las personas titulares, así como los deberes de los responsables y las personas encargadas, previstos en las disposiciones jurídicas aplicables;\nXVI. Fuentes de acceso público: Aquellas bases de datos, sistemas o archivos que por una norma limitativa y sin más exigencia que, en su caso, el pago de una contraprestación, tarifa o contribución. No se considerará fuente de acceso público cuando la información contenida en la misma sea obtenida o tenga una procedencia ilícita, conforme a las disposiciones establecidas por la presente Ley y demás disposiciones jurídicas aplicables;\nLey de Protección de Datos Personales para el Sector Público Página 3\n.\nActualización Legislativa.\nXVII. Ley: Ley de Protección de Datos Personales para el Sector Público del Estado de\nBaja California;\nXVIII. Ley General: Ley General de Protección de Datos Personales en Posesión de\nSujetos Obligados;\nXIX. Medidas compensatorias: Mecanismos alternos para dar a conocer a las personas titulares el aviso de privacidad, a través de su difusión por medios masivos de comunicación u otros de amplio alcance;\nXX. Medidas de seguridad: Conjunto de acciones, actividades, controles o mecanismos administrativos, técnicos y físicos que permitan proteger los datos personales;\nXXI. Medidas de seguridad administrativas: Políticas y procedimientos para la gestión, soporte y revisión de la seguridad de la información a nivel organizacional, la identificación, clasificación y borrado seguro de la información, así como la sensibilización y capacitación del personal, en materia de protección de datos personales;\nXXII. Medidas de seguridad físicas: Conjunto de acciones y mecanismos para proteger el entorno físico de los datos personales y de los recursos involucrados en su tratamiento. De manera enunciativa más no limitativa, se deben considerar las siguientes actividades:\na) Prevenir el acceso no autorizado al perímetro de la organización, sus instalaciones físicas, áreas críticas, recursos e información;\nb) Prevenir el daño o interferencia a las instalaciones físicas, áreas críticas de la organización, recursos e información;\nc) Proteger los recursos móviles, portátiles y cualquier soporte físico o electrónico que pueda salir de la organización; y,\nd) Proveer a los equipos que contienen o almacenan datos personales de un mantenimiento eficaz, que asegure su disponibilidad e integridad.\nXXIII. Medidas de seguridad técnicas: Conjunto de acciones y mecanismos que se los datos personales y los recursos involucrados en su tratamiento. De manera enunciativa más no limitativa, se deben considerar las siguientes actividades: recursos, sea por usuarios identificados y autorizados;\nb) Generar un esquema de privilegios para que el usuario lleve a cabo las actividades que requiere con motivo de sus funciones;\nLey de Protección de Datos Personales para el Sector Público Página 4\n.\nActualización Legislativa.\nc) Revisar la configuración de seguridad en la adquisición, operación, desarrollo y mantenimiento del software y hardware; y,\nd) Gestionar las comunicaciones, operaciones y medios de almacenamiento de los recursos informáticos en el tratamiento de datos personales.\nXXIV. Persona Encargada: Persona física o jurídica, pública o privada, ajena a la organización de la persona responsable, que sola o conjuntamente con otras trate datos personales a nombre y por cuenta de la persona responsable;\nXXV. Persona Titular: Sujeto a quien corresponden los datos personales;\nXXVI. Plataforma Nacional: Plataforma Nacional de Transparencia a que hace referencia el artículo 44 de la Ley General de Transparencia y Acceso a la Información\nPública;\nXXVII. Remisión: Toda comunicación de datos personales realizada exclusivamente entre el responsable y la persona encargada, dentro o fuera del territorio mexicano;\nXXVIII. Responsable: Cualquier autoridad, entidad, órgano y organismo de los poderes Ejecutivo, Legislativo y Judicial, órganos autónomos, fideicomisos y fondos públicos, en el ámbito estatal y municipal;\nXXIX. Secretaría: Secretaría Anticorrupción y Buen Gobierno del Estado de Baja\nCalifornia;\nXXX. Supresión: Baja archivística de los datos personales conforme a las disposiciones jurídicas aplicables en materia de archivos, que resulte en la eliminación, borrado o destrucción de los datos personales bajo las medidas de seguridad previamente establecidas por el responsable;\nXXXI. Transparencia para el Pueblo: Órgano Administrativo Desconcentrado de la\nSecretaría Anticorrupción y Buen Gobierno del Estado de Baja California.\nXXXII. Transferencia: Toda comunicación de datos personales dentro o fuera del territorio mexicano, realizada a persona distinta de la titular, del responsable o de la persona encargada;\nXXXIII. Tratamiento: Cualquier operación o conjunto de operaciones efectuadas mediante procedimientos manuales o automatizados aplicados a los datos personales, relacionadas con la obtención, uso, registro, organización, conservación, elaboración, utilización, comunicación, difusión, almacenamiento, posesión, acceso, manejo, aprovechamiento, divulgación, transferencia o disposición de datos personales; y, Ley de Protección de Datos Personales para el Sector Público Página 5\n.\nActualización Legislativa.\nXXXIV. Unidad de Transparencia: Instancia a la que hace referencia el artículo 34 de la Ley de Transparencia, Acceso a la Información Pública y Apertura Institucional para el\nEstado de Baja California.\nARTÍCULO 4.- La presente Ley será aplicable a cualquier tratamiento de datos personales que obren en soportes físicos o electrónicos, con independencia de la forma o modalidad de su creación, tipo de soporte, procesamiento, almacenamiento y organización.\nARTÍCULO 5.- Para los efectos de la presente Ley, se considerarán como fuentes de acceso público:\nI. Las páginas de internet o medios remotos o locales de comunicación electrónica, óptica y de otra tecnología, siempre que el sitio donde se encuentren los datos personales esté concebido para facilitar información al público y esté abierto a la consulta general;\nII. Los directorios telefónicos en términos de la normativa específica;\nIII. Los diarios, gacetas o boletines oficiales, de acuerdo con las disposiciones jurídicas correspondientes;\nIV. Los medios de comunicación social; y,\nV. Los registros públicos conforme a las disposiciones que les resulten aplicables.\nPara que los supuestos enumerados en el presente artículo sean considerados fuentes de acceso público será necesario que su consulta pueda ser realizada por cualquier persona no impedida por una norma limitativa, o sin más exigencia que, en su caso, el pago de una contraprestación, derecho o tarifa.\nNo se considerará una fuente de acceso público cuando la información contenida en la misma sea o tenga una procedencia ilícita.\nARTÍCULO 6.- El Estado garantizará la privacidad de los individuos y deberá velar porque terceras personas no incurran en conductas que puedan afectarla arbitrariamente. de seguridad nacional, en términos de la ley en la materia, disposiciones de orden público, seguridad y salud públicas o para proteger los derechos de terceros.\nARTÍCULO 7.- Por regla general no podrán tratarse datos personales sensibles, salvo que se cuente con el consentimiento expreso de la persona titular o, en su defecto, se trate de los casos establecidos en el artículo 15 de esta Ley.\nLey de Protección de Datos Personales para el Sector Público Página 6\n.\nActualización Legislativa.\nEn el tratamiento de datos personales de menores de edad se deberá privilegiar el interés superior de la niña, el niño y el adolescente, en términos de las disposiciones jurídicas aplicables.\nARTÍCULO 8.- La aplicación e interpretación de la presente Ley se realizará conforme a lo dispuesto en la Constitución Política de los Estados Unidos Mexicanos, Constitución que el Estado Mexicano sea parte, la Ley General, así como las resoluciones y sentencias vinculantes que emitan los órganos nacionales e internacionales especializados, favoreciendo en todo tiempo el derecho a la privacidad, la protección de datos personales y a las personas la protección más amplia.\nPara el caso de la interpretación, se podrán tomar en cuenta los criterios, determinaciones y opiniones de los organismos nacionales e internacionales, en materia de protección de datos personales.\nARTÍCULO 9.- A falta de disposición expresa en la presente Ley, se aplicarán de manera supletoria las disposiciones de la Ley General, del Código adjetivo civil correspondiente y de la Ley del Procedimiento para los Actos de la Administración Pública del\nEstado de Baja California.\nTÍTULO SEGUNDO\nPRINCIPIOS Y DEBERES\nCapítulo I\nDe los Principios\nARTÍCULO 10.- El responsable deberá observar los principios de licitud, finalidad, lealtad, consentimiento, calidad, proporcionalidad, información y responsabilidad en el tratamiento de datos personales.\nEl tratamiento de datos personales por parte del responsable deberá sujetarse a las facultades o atribuciones que la normatividad aplicable le confiera.\nARTÍCULO 11.- Todo tratamiento de datos personales que efectúe el responsable deberá estar justificado por finalidades concretas, lícitas, explícitas y legítimas, relacionadas con las atribuciones que la normatividad aplicable les confiera. establecidas en el aviso de privacidad, siempre y cuando cuente con atribuciones conferidas en la Ley y medie el consentimiento de la persona titular, salvo que sea una persona reportada como desaparecida, en los términos previstos en la presente Ley y demás disposiciones que resulten aplicables en la materia.\nLey de Protección de Datos Personales para el Sector Público Página 7\n.\nActualización Legislativa.\nARTÍCULO 12.- El responsable no deberá obtener y tratar datos personales a través de medios engañosos o fraudulentos, y deberá privilegiar la protección de los intereses de la persona titular y la expectativa razonable de privacidad.\nARTÍCULO 13.- Cuando no se actualicen algunas de las causales de excepción previstas en el artículo 15 de la presente Ley, el responsable deberá contar con el consentimiento previo de la persona titular para el tratamiento de los datos personales, el cual deberá otorgarse de forma:\nI. Libre: Sin que medie error, mala fe, violencia o dolo que puedan afectar la manifestación de voluntad de la persona titular;\nII. Específica: Referida a finalidades concretas, lícitas, explícitas y legítimas que justifiquen el tratamiento; e,\nIII. Informada: Que la persona titular tenga conocimiento del aviso de privacidad previo al tratamiento a que serán sometidos sus datos personales.\nEn la obtención del consentimiento de personas menores de edad o que se encuentren en estado de interdicción, incapacidad declarada o que estén sujetas a una representación, conforme a las disposiciones jurídicas aplicables, se estará a lo dispuesto en la legislación civil que resulte aplicable.\nARTÍCULO 14.- El consentimiento podrá manifestarse de forma expresa o tácita. Se deberá entender que el consentimiento es expreso cuando la voluntad de la persona titular se manifieste verbalmente, por escrito, por medios electrónicos, ópticos, signos inequívocos o por cualquier otra tecnología.\nEl consentimiento será tácito cuando habiéndose puesto a disposición de la persona titular el aviso de privacidad, éste no manifieste su voluntad en sentido contrario.\nPor regla general será válido el consentimiento tácito, salvo que la ley o las expresamente. consentimiento expreso y por escrito de la persona titular para su tratamiento, a través de su establezca, salvo en los casos previstos en el artículo 15 de esta Ley.\nARTÍCULO 15.- El responsable no estará obligado a recabar el consentimiento de la persona titular para el tratamiento de sus datos personales en los siguientes casos:\nLey de Protección de Datos Personales para el Sector Público Página 8\n.\nActualización Legislativa.\nI. Cuando una legislación aplicable así lo disponga, debiendo dichos supuestos ser acordes con las bases, principios y disposiciones establecidos en esta Ley, la Ley General y, en ningún caso, podrán contravenirlas;\nII. Cuando las transferencias que se realicen entre responsables, sean sobre datos personales que se utilicen para el ejercicio de facultades propias, compatibles o análogas con la finalidad que motivó el tratamiento de los datos personales;\nIII. Cuando exista una orden judicial, resolución o mandato fundado y motivado de autoridad competente;\nIV. Para el reconocimiento o defensa de derechos de la persona titular ante autoridad competente;\nV. Cuando los datos personales se requieran para ejercer un derecho o cumplir obligaciones derivadas de una relación jurídica entre la persona titular y el responsable;\nVI. Cuando exista una situación de emergencia que potencialmente pueda dañar a un individuo en su persona o en sus bienes;\nVII. Cuando los datos personales sean necesarios para efectuar un tratamiento para la prevención, diagnóstico o la prestación de asistencia sanitaria;\nVIII. Cuando los datos personales figuren en fuentes de acceso público;\nIX. Cuando los datos personales se sometan a un procedimiento previo de disociación; o,\nX. Cuando la persona titular de los datos personales sea una persona reportada como desaparecida en los términos de las disposiciones jurídicas en la materia.\nARTÍCULO 16.- El responsable deberá adoptar las medidas necesarias para mantener exactos, completos, correctos y actualizados los datos personales en su posesión, a fin de que no se altere la veracidad de éstos. contrario. las disposiciones que resulten aplicables, deberán ser suprimidos, previo bloqueo en su caso, y una vez que concluya el plazo de conservación de los mismos.\nLey de Protección de Datos Personales para el Sector Público Página 9\n.\nActualización Legislativa.\nLos plazos de conservación de los datos personales no deberán exceder aquéllos que sean necesarios para el cumplimiento de las finalidades que justificaron su tratamiento, y deberán atender a las disposiciones aplicables en la materia de que se trate y considerar los aspectos administrativos, contables, fiscales, jurídicos e históricos de los datos personales.\nARTÍCULO 17.- El responsable deberá establecer y documentar los procedimientos para la conservación y, en su caso, bloqueo y supresión de los datos personales que lleve a cabo, en los cuales se incluyan los periodos de conservación de los mismos de conformidad con lo dispuesto en el artículo anterior de la presente Ley.\nEn los procedimientos a que se refiere el párrafo anterior, el responsable deberá incluir mecanismos que le permitan cumplir con los plazos fijados para la supresión de los datos personales, así como para realizar una revisión periódica sobre la necesidad de conservar los datos personales.\nARTÍCULO 18.- El responsable sólo deberá tratar los datos personales que resulten adecuados, relevantes y estrictamente necesarios para la finalidad que justifica su tratamiento.\nEn el tratamiento de datos personales de menores de edad, el responsable deberá privilegiar el interés superior de las niñas, niños y adolescentes, en términos de las disposiciones previstas en la Ley para la Protección y Defensa de los Derechos de Niñas, Niños y Adolescentes del Estado de Baja California y demás ordenamientos que resulten aplicables.\nARTÍCULO 19.- El responsable deberá informar a la persona titular, a través del aviso de privacidad, la existencia y características principales del tratamiento al que serán sometidos sus datos personales, a fin de que pueda tomar decisiones informadas al respecto.\nEl aviso de privacidad deberá ser difundido por los medios electrónicos y físicos con que cuente el responsable. Asimismo, deberá ponerse a disposición en su modalidad simplificada.\nPara que el aviso de privacidad cumpla de manera eficiente con su función de informar, deberá estar redactado y estructurado de manera clara y sencilla.\nCuando resulte imposible dar a conocer a la persona titular el aviso de privacidad, de manera directa o ello exija esfuerzos desproporcionados, el responsable podrá instrumentar efecto emitan las Autoridades Garantes.\nEn el aviso de privacidad se evitará:\nI. Usar frases inexactas, ambiguas o vagas;\nLey de Protección de Datos Personales para el Sector Público Página 10\n.\nActualización Legislativa.\nII. Incluir textos o formatos que induzcan a la persona titular a elegir una opción en específico;\nIII. Marcar previamente casillas, en caso de que éstas se incluyan para que la persona titular otorgue su consentimiento; y,\nIV. Remitir a textos o documentos que no estén disponibles para la persona titular.\nARTÍCULO 20.- El aviso de privacidad deberá contener, al menos, la siguiente información:\nI. La denominación y el domicilio del responsable;\nII. Los datos personales que serán sometidos a tratamiento, identificando aquéllos que son sensibles;\nIII. El fundamento legal que faculta al responsable para llevar a cabo el tratamiento;\nIV. Las finalidades del tratamiento para las cuales se obtienen los datos personales, distinguiendo aquéllas que requieren el consentimiento de la persona titular;\nV. Los mecanismos, medios y procedimientos disponibles para ejercer los derechos\nARCO;\nVI. El domicilio de la Unidad de Transparencia;\nVII. Cuando se realicen transferencias de datos personales que requieran consentimiento, se deberá informar:\na) Las autoridades, poderes, entidades, órganos y organismos gubernamentales de los tres órdenes de gobierno y las personas físicas o morales a las que se transfieren los datos personales; y,\nb) Las finalidades de estas transferencias.\nVIII. Los mecanismos y medios disponibles para que la persona titular, en su caso, transferencias de datos personales que requieren el consentimiento de la persona titular; y,\nIX. Los medios a través de los cuales el responsable comunicará a las personas titulares los cambios al aviso de privacidad.\nLey de Protección de Datos Personales para el Sector Público Página 11\n.\nActualización Legislativa. sus datos personales para las finalidades o transferencias que requieran su consentimiento, previo a que ocurra dicho tratamiento.\nARTÍCULO 21.- El aviso de privacidad en su modalidad simplificada deberá contener la información a que se refieren las fracciones I, IV, VII y VIII del artículo anterior y señalar el sitio donde se podrá consultar el aviso de privacidad integral.\nLa puesta a disposición del aviso de privacidad a que refiere este artículo no exime al responsable de su obligación de proveer los mecanismos para que la persona titular pueda conocer el contenido integral del aviso de privacidad.\nARTÍCULO 22.- El responsable deberá implementar los mecanismos previstos en el artículo 23 de la presente Ley para acreditar el cumplimiento de los principios, deberes y obligaciones establecidos en la misma y rendir cuentas sobre el tratamiento de datos personales en su posesión a la persona titular y a las Autoridades Garantes. En este caso, deberá observar la Constitución Política de los Estados Unidos Mexicanos, Constitución que el Estado mexicano sea parte; en lo que no se contraponga con la normativa mexicana podrá valerse de estándares o mejores prácticas nacionales o internacionales para tales fines.\nARTÍCULO 23.- Entre los mecanismos que deberá adoptar el responsable para cumplir con el principio de responsabilidad establecido en la presente Ley están, al menos, los siguientes:\nI. Destinar recursos autorizados para tal fin para la instrumentación de programas y políticas de protección de datos personales;\nII. Elaborar políticas y programas de protección de datos personales, obligatorios y exigibles al interior de la organización del responsable;\nIII. Poner en práctica un programa de capacitación y actualización del personal sobre las obligaciones y demás deberes en materia de protección de datos personales;\nIV. Revisar periódicamente las políticas y programas de seguridad de datos personales para determinar las modificaciones que se requieran;\nV. Establecer un sistema de supervisión y vigilancia interna y/o externa, incluyendo auditorías, para comprobar el cumplimiento de las políticas de protección de datos personales;\nVI. Establecer procedimientos para recibir y responder dudas y quejas de las personas titulares;\nVII. Diseñar, desarrollar e implementar políticas públicas, programas, servicios, sistemas o plataformas informáticas, aplicaciones electrónicas o cualquier otra tecnología que\nLey de Protección de Datos Personales para el Sector Público Página 12\n.\nActualización Legislativa. implique el tratamiento de datos personales, de conformidad con las disposiciones previstas en la presente Ley y las demás que resulten aplicables en la materia; y,\nVIII. Garantizar que sus políticas públicas, programas, servicios, sistemas o plataformas informáticas, aplicaciones electrónicas o cualquier otra tecnología que implique el tratamiento de datos personales, cumplan por defecto con las obligaciones previstas en la presente Ley y las demás que resulten aplicables en la materia.\nCapítulo II\nDe los Deberes\nARTÍCULO 24.- Con independencia del tipo de sistema en el que se encuentren los datos personales o el tipo de tratamiento que se efectúe, el responsable deberá establecer y mantener las medidas de seguridad de carácter administrativo, físico y técnico para la protección de los datos personales contra daño, pérdida, alteración, destrucción o su uso, acceso o tratamiento no autorizado, así como garantizar su confidencialidad, integridad y disponibilidad.\nARTÍCULO 25.- Las medidas de seguridad adoptadas por el responsable deberán considerar:\nI. El riesgo inherente a los datos personales tratados;\nII. La sensibilidad de los datos personales tratados;\nIII. El desarrollo tecnológico;\nIV. Las posibles consecuencias de una vulneración para las personas titulares;\nV. Las transferencias de datos personales que se realicen;\nVI. El número de personas titulares;\nVII. Las vulneraciones previas ocurridas en los sistemas de tratamiento; y,\nVIII. El riesgo por el valor potencial cuantitativo o cualitativo que pudieran tener los datos personales tratados para una tercera persona no autorizada para su posesión.\nARTÍCULO 26.- Para establecer y mantener las medidas de seguridad para la protección de los datos personales, el responsable deberá realizar, al menos, las siguientes actividades interrelacionadas:\nI. Crear políticas internas para la gestión y tratamiento de los datos personales que personales, es decir, su obtención, uso y posterior supresión;\nLey de Protección de Datos Personales para el Sector Público Página 13\n.\nActualización Legislativa.\nII. Definir las funciones y obligaciones del personal involucrado en el tratamiento de datos personales;\nIII. Elaborar un inventario de datos personales y de los sistemas de tratamiento;\nIV. Realizar un análisis de riesgo de los datos personales, considerando las amenazas y vulnerabilidades existentes para los datos personales y los recursos involucrados en su tratamiento, como pueden ser, de manera enunciativa más no limitativa, hardware, software, personal del responsable, entre otros;\nV. Realizar un análisis de brecha, comparando las medidas de seguridad existentes contra las faltantes en la organización del responsable;\nVI. Elaborar un plan de trabajo para la implementación de las medidas de seguridad faltantes, así como las medidas para el cumplimiento cotidiano de las políticas de gestión y tratamiento de los datos personales;\nVII. Monitorear y revisar de manera periódica las medidas de seguridad implementadas, así como las amenazas y vulneraciones a las que están sujetos los datos personales; y,\nVIII. Diseñar y aplicar diferentes niveles de capacitación del personal bajo su mando, dependiendo de sus roles y responsabilidades respecto del tratamiento de los datos personales.\nARTÍCULO 27.- Las acciones relacionadas con las medidas de seguridad para el tratamiento de los datos personales deberán estar documentadas y contenidas en un sistema de gestión.\nSe entenderá por sistema de gestión al conjunto de elementos y actividades interrelacionadas para establecer, implementar, operar, monitorear, revisar, mantener y mejorar el tratamiento y seguridad de los datos personales, de conformidad con lo previsto en la presente Ley, la Ley General y las demás disposiciones jurídicas que le resulten aplicables en la materia.\nARTÍCULO 28.- El responsable deberá elaborar un documento de seguridad que contenga, al menos, lo siguiente:\nI. El inventario de datos personales y de los sistemas de tratamiento;\nII. Las funciones y obligaciones de las personas que traten datos personales;\nIII. El análisis de riesgos;\nIV. El análisis de brecha;\nLey de Protección de Datos Personales para el Sector Público Página 14\n.\nActualización Legislativa.\nV. El plan de trabajo;\nVI. Los mecanismos de monitoreo y revisión de las medidas de seguridad; y,\nVII. El programa general de capacitación.\nARTÍCULO 29.- El responsable deberá actualizar el documento de seguridad cuando ocurran los siguientes eventos:\nI. Se produzcan modificaciones sustanciales al tratamiento de datos personales que deriven en un cambio en el nivel de riesgo;\nII. Como resultado de un proceso de mejora continua, derivado del monitoreo y revisión del sistema de gestión;\nIII. Como resultado de un proceso de mejora para mitigar el impacto de una vulneración a la seguridad ocurrida; y,\nIV. Implementación de acciones correctivas y preventivas ante una vulneración de seguridad.\nARTÍCULO 30.- En caso de que ocurra una vulneración a la seguridad, el responsable deberá analizar las causas por las cuales se presentó e implementar en su plan de trabajo las acciones preventivas y correctivas para adecuar las medidas de seguridad y el tratamiento de los datos personales si fuese el caso a efecto de evitar que la vulneración se repita.\nARTÍCULO 31.- Además de las que señalen las leyes respectivas y la normatividad aplicable, se considerarán como vulneraciones de seguridad, en cualquier fase del tratamiento de datos, al menos, las siguientes:\nI. La pérdida o destrucción no autorizada;\nII. El robo, extravío o copia no autorizada;\nIII. El uso, acceso o tratamiento no autorizado; o,\nIV. El daño, la alteración o modificación no autorizada.\nARTÍCULO 32.- El responsable deberá llevar una bitácora de las vulneraciones a la seguridad en la que se describa ésta, la fecha en la que ocurrió, el motivo de ésta y las acciones correctivas implementadas de forma inmediata y definitiva.\nARTÍCULO 33.- El responsable deberá informar sin dilación alguna a la persona titular derechos patrimoniales o morales, en cuanto se confirme que ocurrió la vulneración y que el\nLey de Protección de Datos Personales para el Sector Público Página 15\n.\nActualización Legislativa. responsable haya empezado a tomar las acciones encaminadas a detonar un proceso de revisión exhaustiva de la magnitud de la afectación, a fin de que las personas titulares afectadas puedan tomar las medidas correspondientes para la defensa de sus derechos.\nARTÍCULO 34.- El responsable deberá informar a la persona titular al menos lo siguiente:\nI. La naturaleza del incidente;\nII. Los datos personales comprometidos;\nIII. Las recomendaciones acerca de las medidas que la persona titular pueda adoptar para proteger sus intereses;\nIV. Las acciones correctivas realizadas de forma inmediata; y,\nV. Los medios donde puede obtener más información al respecto.\nARTÍCULO 35.- El responsable deberá establecer controles o mecanismos que tengan por objeto que todas aquellas personas que intervengan en cualquier fase del tratamiento de los datos personales, guarden confidencialidad respecto de estos, obligación que subsistirá aún después de finalizar sus relaciones con el mismo.\nLo anterior, sin menoscabo de lo establecido en las disposiciones de acceso a la información pública.\nTÍTULO TERCERO\nDERECHOS DE LAS PERSONAS TITULARES Y SU EJERCICIO\nCapítulo I\nDe los Derechos de Acceso, Rectificación, Cancelación y Oposición\nARTÍCULO 36.- En todo momento la persona titular o su representante podrán solicitar al responsable, el acceso, rectificación, cancelación u oposición al tratamiento de los datos personales que le conciernen, de conformidad con lo establecido en el presente Título. El ejercicio de cualquiera de los derechos ARCO no es requisito previo, ni impide el ejercicio de otro.\nARTÍCULO 37.- La persona titular tendrá derecho de acceder a sus datos personales que obren en posesión del responsable, así como conocer la información relacionada con las condiciones y generalidades de su tratamiento.\nARTÍCULO 38.- La persona titular tendrá derecho a solicitar al responsable la rectificación o corrección de sus datos personales, cuando éstos resulten ser inexactos, incompletos o no se encuentren actualizados.\nLey de Protección de Datos Personales para el Sector Público Página 16\n.\nActualización Legislativa.\nARTÍCULO 39.- La persona titular tendrá derecho a solicitar la cancelación de sus datos personales de los archivos, registros, expedientes y sistemas del responsable, a fin de que los mismos ya no estén en su posesión y dejen de ser tratados por este último.\nARTÍCULO 40.- La persona titular podrá oponerse al tratamiento de sus datos personales o exigir que se cese en el mismo, cuando:\nI. Aun siendo lícito el tratamiento, el mismo debe cesar para evitar que su persistencia le cause un daño o perjuicio; y,\nII. Sus datos personales sean objeto de un tratamiento automatizado, el cual le produzca efectos jurídicos no deseados o afecte de manera significativa sus intereses, derechos o libertades, y estén destinados a evaluar, sin intervención humana, determinados aspectos personales de la misma o analizar o predecir, en particular, su rendimiento profesional, situación económica, estado de salud, preferencias sexuales, fiabilidad o comportamiento.\nCapítulo II\nDel Ejercicio de los Derechos de Acceso, Rectificación, Cancelación y Oposición\nARTÍCULO 41.- La recepción y trámite de las solicitudes para el ejercicio de los derechos ARCO que se formulen a los responsables se sujetará al procedimiento establecido en esta Ley, la Ley General y demás disposiciones que resulten aplicables en la materia.\nARTÍCULO 42.- Para el ejercicio de los derechos ARCO será necesario acreditar la identidad de la persona titular y, en su caso, la identidad y personalidad con la que actúe el representante. El ejercicio de los derechos ARCO por persona distinta a su titular o a su representante, será posible, excepcionalmente, en aquellos supuestos previstos por disposición legal o, en su caso, por mandato judicial.\nEn el ejercicio de los derechos ARCO de personas menores de edad o que se encuentren en estado de interdicción, incapacidad o que estén sujetas a una representación, de conformidad con las leyes civiles, se estará a lo dispuesto en la misma legislación.\nTratándose de datos personales concernientes a personas fallecidas, la persona que acredite tener un interés jurídico, de conformidad con las leyes aplicables, podrá ejercer los derechos que le confiere el presente Capítulo, siempre que la persona titular de los derechos judicial para dicho efecto.\nEn la acreditación de la persona titular o su representación, el responsable deberá seguir las siguientes reglas:\nI. La persona titular podrá acreditar su identidad a través de los siguientes medios:\nLey de Protección de Datos Personales para el Sector Público Página 17\n.\nActualización Legislativa.\na) Identificación oficial;\nb) Instrumentos electrónicos o mecanismos de autenticación permitidos por otras disposiciones legales o reglamentarias que permitan su identificación fehacientemente; o,\nc) Aquellos mecanismos establecidos por el responsable de manera previa, siempre y cuando permitan de forma inequívoca la acreditación de la identidad de la persona titular.\nII. Cuando la persona titular ejerza sus derechos ARCO a través de su representante, éste deberá acreditar su identidad y personalidad presentando ante el responsable:\na) Copia simple de la identificación oficial de la persona titular;\nb) Identificación oficial de quien represente a la persona titular; e,\nc) Instrumento público, o carta poder simple firmada ante dos testigos, o declaración en comparecencia personal de la persona titular.\nARTÍCULO 43.- El ejercicio de los derechos ARCO es gratuito, sólo podrán realizarse cobros para recuperar los costos de reproducción, certificación o envío, conforme a la normatividad que resulte aplicable.\nPara efectos de acceso a datos personales, las leyes que establezcan los costos de reproducción y certificación deberán considerar en su determinación que los montos permitan o faciliten el ejercicio de este derecho.\nCuando la persona titular proporcione el medio magnético, electrónico o el mecanismo necesario para reproducir los datos personales, los mismos deberán ser entregados sin costo a ésta.\nLa información deberá ser entregada sin costo, cuando implique la entrega de no más de veinte hojas simples. Las Unidades de Transparencia podrán exceptuar el pago de reproducción y envío atendiendo a las circunstancias socioeconómicas de la persona titular. de los derechos ARCO algún servicio o medio que implique un costo a la persona titular.\nARTÍCULO 44.- El responsable deberá establecer procedimientos sencillos que permitan el ejercicio de los derechos ARCO, cuyo plazo de respuesta no deberá exceder de veinte días contados a partir del día siguiente a la recepción de la solicitud. diez días cuando así lo justifiquen las circunstancias, siempre y cuando se le notifique a la persona titular dentro del plazo de respuesta.\nLey de Protección de Datos Personales para el Sector Público Página 18\n.\nActualización Legislativa.\nEn caso de resultar procedente el ejercicio de los derechos ARCO, el responsable deberá hacerlo efectivo en un plazo que no podrá exceder de quince días contados a partir del día siguiente en que se haya notificado la respuesta a la persona titular.\nARTÍCULO 45.- En la solicitud para el ejercicio de los derechos ARCO no podrán imponerse mayores requisitos que los siguientes:\nI. El nombre de la persona titular y su domicilio o cualquier otro medio para recibir notificaciones;\nII. Los documentos que acrediten la identidad de la persona titular y, en su caso, la personalidad e identidad de su representante;\nIII. De ser posible, el área responsable que trata los datos personales y ante la cual se presenta la solicitud;\nIV. La descripción clara y precisa de los datos personales respecto de los que se busca ejercer alguno de los derechos ARCO, salvo que se trate del derecho de acceso;\nV. La descripción del derecho ARCO que se pretende ejercer, o bien, lo que solicita la persona titular; y,\nVI. Cualquier otro elemento o documento que facilite la localización de los datos personales, en su caso.\nTratándose de una solicitud de acceso a datos personales, la persona titular deberá señalar la modalidad en la que prefiere que éstos se reproduzcan. El responsable deberá atender la solicitud en la modalidad requerida por la persona titular, salvo que exista una imposibilidad física o jurídica que lo limite a reproducir los datos personales en dicha modalidad, en este caso deberá ofrecer otras modalidades de entrega de los datos personales fundando y motivando dicha actuación.\nEn caso de que la solicitud de protección de datos no satisfaga alguno de los requisitos a que se refiere este artículo, y las Autoridades Garantes no cuenten con elementos para subsanarla, se prevendrá a la persona titular de los datos dentro de los cinco días siguientes a la presentación de la solicitud de ejercicio de los derechos ARCO, por una sola ocasión, para al de la notificación. solicitud de ejercicio de los derechos ARCO.\nLa prevención tendrá el efecto de interrumpir el plazo que tienen los responsables, para resolver la solicitud de ejercicio de los derechos ARCO.\nLey de Protección de Datos Personales para el Sector Público Página 19\n.\nActualización Legislativa.\nCon relación a una solicitud de cancelación, la persona titular deberá señalar las causas que la motiven a solicitar la supresión de sus datos personales en los archivos, registros o bases de datos del responsable.\nEn el caso de la solicitud de oposición, la persona titular deberá manifestar las causas legítimas o la situación específica que la llevan a solicitar el cese en el tratamiento, así como el daño o perjuicio que le causaría la persistencia del tratamiento o, en su caso, las finalidades específicas respecto de las cuales requiere ejercer el derecho de oposición.\nLas solicitudes para el ejercicio de los derechos ARCO deberán presentarse ante la\nUnidad de Transparencia del responsable competente, a través de escrito libre, formatos, medios electrónicos o cualquier otro medio que al efecto establezcan las Autoridades\nGarantes, en el ámbito de sus respectivas competencias.\nEl responsable deberá dar trámite a toda solicitud para el ejercicio de los derechos\nARCO y entregar el acuse de recibo que corresponda.\nLas Autoridades Garantes, según su ámbito de competencia, podrán establecer formularios, sistemas y otros métodos simplificados para facilitar a las personas titulares el ejercicio de los derechos ARCO.\nLos medios y procedimientos habilitados por el responsable para atender las solicitudes para el ejercicio de los derechos ARCO deberán ser de fácil acceso y con la mayor cobertura posible considerando el perfil de las personas titulares y la forma en que mantienen contacto cotidiano o común con el responsable.\nARTÍCULO 46.- Cuando el responsable no sea competente para atender la solicitud para el ejercicio de los derechos ARCO, deberá hacer del conocimiento de la persona titular dicha situación dentro de los tres días siguientes a la presentación de la solicitud y, en caso de poderlo determinar, orientarlo hacia el responsable competente.\nEn caso de que el responsable declare inexistencia de los datos personales en sus archivos, registros, sistemas o expediente, dicha declaración deberá constar en una resolución del Comité de Transparencia que confirme la inexistencia de los datos personales.\nEn caso de que el responsable advierta que la solicitud para el ejercicio de los derechos ARCO corresponda a un derecho diferente de los previstos en la presente Ley, deberá reconducir la vía haciéndolo del conocimiento a la persona titular.\nARTÍCULO 47.- Cuando las disposiciones aplicables a determinados tratamientos de de los derechos ARCO, el responsable deberá informar a la persona titular sobre la existencia del mismo, en un plazo no mayor a cinco días siguientes a la presentación de la solicitud para el ejercicio de los derechos ARCO, a efecto de que este último decida si ejerce sus derechos a través del trámite específico, o bien, por medio del procedimiento que el responsable haya\nLey de Protección de Datos Personales para el Sector Público Página 20\n.\nActualización Legislativa. institucionalizado para la atención de solicitudes para el ejercicio de los derechos ARCO conforme a las disposiciones establecidas en este Capítulo.\nARTÍCULO 48.- Las únicas causas en las que el ejercicio de los derechos ARCO no serán procedentes son:\nI. Cuando la persona titular o su representante no estén debidamente acreditadas para ello;\nII. Cuando los datos personales no se encuentren en posesión del responsable;\nIII. Cuando exista un impedimento legal;\nIV. Cuando se lesionen los derechos de un tercero;\nV. Cuando se obstaculicen actuaciones judiciales o administrativas;\nVI. Cuando exista una resolución de autoridad competente que restrinja el acceso a los datos personales o no permita la rectificación, cancelación u oposición de los mismos;\nVII. Cuando la cancelación u oposición haya sido previamente realizada;\nVIII. Cuando el responsable no sea competente;\nIX. Cuando sean necesarios para proteger intereses jurídicamente tutelados de la persona titular;\nX. Cuando sean necesarios para dar cumplimiento a obligaciones legalmente adquiridas por la persona titular;\nXI. Cuando en función de sus atribuciones legales el uso cotidiano, resguardo y manejo sean necesarios y proporcionales para mantener la integridad, estabilidad y permanencia del\nEstado mexicano; o,\nXII. Cuando los datos personales sean parte de la información que las entidades éste, en cumplimiento a requerimientos de dicha información sobre sus operaciones, organización y actividades.\nEn todos los casos anteriores, el responsable deberá informar a la persona titular el motivo de su determinación, en el plazo de hasta veinte días a los que se refiere el primer párrafo del artículo 44 de la presente Ley, y por el mismo medio en que se llevó a cabo la solicitud, acompañando en su caso, las pruebas que resulten pertinentes.\nLey de Protección de Datos Personales para el Sector Público Página 21\n.\nActualización Legislativa.\nARTÍCULO 49.- Contra la negativa de dar trámite a toda solicitud para el ejercicio de los derechos ARCO o por falta de respuesta del responsable, procederá la interposición del recurso de revisión a que se refiere el artículo 84 de la presente Ley.\nCapítulo III\nDe la Portabilidad de los Datos\nARTÍCULO 50.- Cuando se traten datos personales por vía electrónica en un formato estructurado y comúnmente utilizado, la persona titular tendrá derecho a obtener del responsable una copia de los datos objeto de tratamiento en un formato electrónico estructurado y comúnmente utilizado que le permita seguir utilizándolos.\nCuando la persona titular haya facilitado los datos personales y el tratamiento se base en el consentimiento o en un contrato, tendrá derecho a transmitir dichos datos personales y cualquier otra información que haya facilitado y que se conserve en un sistema de tratamiento automatizado a otro sistema en un formato electrónico comúnmente utilizado, sin impedimentos por parte del responsable del tratamiento de quien se retiren los datos personales.\nTÍTULO CUARTO\nRELACIÓN DEL RESPONSABLE Y LA PERSONA ENCARGADA\nCapítulo Único\nResponsable y Persona Encargada\nARTÍCULO 51.- La persona encargada deberá realizar las actividades de tratamiento de los datos personales sin ostentar poder alguno de decisión sobre el alcance y contenido del mismo, así como limitar sus actuaciones a los términos fijados por el responsable.\nARTÍCULO 52.- La relación entre el responsable y la persona encargada deberá estar formalizada mediante contrato o cualquier otro instrumento jurídico que decida el responsable, de conformidad con las disposiciones jurídicas aplicables, y que permita acreditar su existencia, alcance y contenido.\nEn el contrato o instrumento jurídico que decida el responsable se deberán prever, al menos, las siguientes cláusulas generales relacionadas con los servicios que preste la persona encargada:\nI. Realizar el tratamiento de los datos personales conforme a las instrucciones del responsable;\nLey de Protección de Datos Personales para el Sector Público Página 22\n.\nActualización Legislativa.\nII. Abstenerse de tratar los datos personales para finalidades distintas a las instruidas por el responsable;\nIII. Implementar las medidas de seguridad conforme a los instrumentos jurídicos aplicables;\nIV. Informar al responsable cuando ocurra una vulneración a los datos personales que trata por sus instrucciones;\nV. Guardar confidencialidad respecto de los datos personales tratados;\nVI. Suprimir o devolver los datos personales objeto de tratamiento una vez cumplida la relación jurídica con el responsable, siempre y cuando no exista una previsión legal que exija la conservación de los datos personales; y,\nVII. Abstenerse de transferir los datos personales salvo en el caso de que el responsable así lo determine, o la comunicación derive de una subcontratación, o por mandato expreso de la autoridad competente.\nLos acuerdos entre el responsable y la persona encargada relacionados con el tratamiento de datos personales no deberán contravenir la presente Ley y demás disposiciones aplicables, así como lo establecido en el aviso de privacidad correspondiente.\nARTÍCULO 53.- Cuando la persona encargada incumpla las instrucciones del responsable y decida por sí misma sobre el tratamiento de los datos personales, asumirá el carácter de responsable y las consecuencias legales correspondientes conforme a la legislación en la materia que le resulte aplicable.\nARTÍCULO 54.- La persona encargada podrá, a su vez, subcontratar servicios que impliquen el tratamiento de datos personales por cuenta del responsable, siempre y cuando medie la autorización expresa de este último, en este caso, la persona subcontratada asumirá el carácter de persona encargada en los términos de la presente Ley y demás disposiciones que resulten aplicables en la materia.\nCuando el contrato o el instrumento jurídico mediante el cual se haya formalizado la cabo a su vez las subcontrataciones de servicios, la autorización a la que refiere el párrafo anterior se entenderá como otorgada a través de lo estipulado en estos.\nARTÍCULO 55.- Una vez obtenida la autorización expresa del responsable, la persona un contrato o cualquier otro instrumento jurídico que decida, de conformidad con la normatividad que le resulte aplicable, y permita acreditar la existencia, alcance y contenido de la prestación del servicio en términos de lo previsto en el presente Capítulo.\nLey de Protección de Datos Personales para el Sector Público Página 23\n.\nActualización Legislativa.\nARTÍCULO 56.- El responsable podrá contratar o adherirse a servicios, aplicaciones e infraestructura en el cómputo en la nube, y otras materias que impliquen el tratamiento de datos personales, siempre y cuando la persona proveedora externa garantice políticas de protección de datos personales equivalentes a los principios y deberes establecidos en la presente Ley y demás disposiciones que resulten aplicables en la materia.\nEn su caso, el responsable deberá delimitar el tratamiento de los datos personales por parte de la persona proveedora externa a través de cláusulas contractuales u otros instrumentos jurídicos.\nARTÍCULO 57.- Para el tratamiento de datos personales en servicios, aplicaciones e infraestructura de cómputo en la nube y otras materias, en los que el responsable se adhiera a los mismos mediante condiciones o cláusulas generales de contratación, sólo podrá utilizar aquellos servicios en los que la persona proveedora:\nI. Cumpla, al menos, con lo siguiente:\na) Tener y aplicar políticas de protección de datos personales afines a los principios y deberes que correspondan conforme a lo previsto en la presente Ley y demás disposiciones jurídicas aplicables;\nb) Transparentar las subcontrataciones que involucren la información sobre la que se presta el servicio;\nc) Abstenerse de incluir condiciones en la prestación del servicio que le autoricen o permitan asumir la titularidad o propiedad de la información sobre la que preste el servicio; y,\nd) Guardar confidencialidad respecto de los datos personales sobre los que se preste el servicio.\nII. Cuente con mecanismos, al menos, para:\na) Dar a conocer cambios en sus políticas de privacidad o condiciones del servicio que presta;\nb) Permitir al responsable limitar el tipo de tratamiento de los datos personales sobre los que se presta el servicio;\nc) Establecer y mantener medidas de seguridad para la protección de los datos personales sobre los que se preste el servicio;\nd) Garantizar la supresión de los datos personales una vez que haya concluido el servicio prestado al responsable y que este último haya podido recuperarlos; y, Ley de Protección de Datos Personales para el Sector Público Página 24\n.\nActualización Legislativa.\ne) Impedir el acceso a los datos personales a personas que no cuenten con privilegios de acceso, o bien, en caso de que sea a solicitud fundada y motivada de autoridad competente, informar de ese hecho al responsable.\nEn cualquier caso, el responsable no podrá adherirse a servicios que no garanticen la debida protección de los datos personales, conforme a la presente Ley y demás disposiciones que resulten aplicables en la materia.\nTÍTULO QUINTO\nCOMUNICACIONES DE DATOS PERSONALES\nCapítulo Único\nDe las Transferencias y Remisiones de Datos Personales\nARTÍCULO 58.- Toda transferencia de datos personales se encuentra sujeta al consentimiento de la persona titular, salvo las excepciones previstas en los artículos 15, 59 y\n63 de esta Ley.\nARTÍCULO 59.- Toda transferencia deberá formalizarse mediante la suscripción de cláusulas contractuales, convenios de colaboración o cualquier otro instrumento jurídico, de conformidad con la normatividad que le resulte aplicable al responsable, que permita demostrar el alcance del tratamiento de los datos personales, así como las obligaciones y responsabilidades asumidas por las partes.\nLo dispuesto en el párrafo anterior no será aplicable en los siguientes casos:\nI. Cuando la transferencia sea nacional y se realice entre responsables en virtud del cumplimiento de una disposición legal o en el ejercicio de atribuciones expresamente conferidas a éstos; o,\nII. Cuando la transferencia sea internacional y se encuentre prevista en una ley o tratado suscrito y ratificado por México, o bien, se realice a petición de una autoridad extranjera u organismo internacional competente en su carácter de receptor, siempre y que dieron origen al tratamiento del responsable transferente.\nARTÍCULO 60.- Cuando la transferencia sea nacional, el receptor de los datos personales deberá tratar los datos personales, comprometiéndose a garantizar su transferente.\nLey de Protección de Datos Personales para el Sector Público Página 25\n.\nActualización Legislativa.\nARTÍCULO 61.- El responsable sólo podrá transferir o hacer remisión de datos personales fuera del territorio nacional cuando el tercero receptor o la persona encargada se obligue a proteger los datos personales conforme a los principios y deberes que establece la presente Ley y las disposiciones que resulten aplicables en la materia.\nARTÍCULO 62.- En toda transferencia de datos personales, el responsable deberá comunicar al receptor de los datos personales el aviso de privacidad conforme al cual se tratan los datos personales frente a la persona titular.\nARTÍCULO 63.- El responsable podrá realizar transferencias de datos personales sin necesidad de requerir el consentimiento de la persona titular, en los siguientes supuestos:\nI. Cuando la transferencia esté prevista en esta Ley u otras leyes, convenios o tratados internacionales de los que el Estado Mexicano es parte;\nII. Cuando la transferencia se realice entre responsables, siempre y cuando los datos personales se utilicen para el ejercicio de facultades propias, compatibles o análogas con la finalidad que motivó el tratamiento de los datos personales;\nIII. Cuando la transferencia sea legalmente exigida para la investigación y persecución de los delitos, así como la procuración o administración de justicia;\nIV. Cuando la transferencia sea precisa para el reconocimiento, ejercicio o defensa de un derecho ante autoridad competente, siempre y cuando medie el requerimiento de esta última;\nV. Cuando la transferencia sea necesaria para la prevención o el diagnóstico médico, la prestación de asistencia sanitaria, tratamiento médico o la gestión de servicios sanitarios, siempre y cuando dichos fines sean acreditados;\nVI. Cuando la transferencia sea precisa para el mantenimiento o cumplimiento de una relación jurídica entre el responsable y la persona titular;\nVII. Cuando la transferencia sea necesaria por virtud de un contrato celebrado o por celebrar en interés de la persona titular, por el responsable y un tercero;\nVIII. Cuando se trate de los casos en los que el responsable no esté obligado a personales, conforme a lo dispuesto en el artículo 15 de la presente Ley; o,\nIX. Cuando la transferencia sea necesaria por razones de seguridad nacional.\nCapítulo.\nLey de Protección de Datos Personales para el Sector Público Página 26\n.\nActualización Legislativa.\nARTÍCULO 64.- Las remisiones nacionales e internacionales de datos personales que se realicen entre el responsable y la persona encargada no requerirán ser informadas a la persona titular, ni contar con su consentimiento.\nTÍTULO SEXTO\nACCIONES PREVENTIVAS EN MATERIA DE PROTECCIÓN\nDE DATOS PERSONALES\nCapítulo I\nDe las Mejores Prácticas\nARTÍCULO 65.- Para el cumplimiento de las obligaciones previstas en la presente Ley, el responsable podrá desarrollar o adoptar, en lo individual o en acuerdo con otros responsables, encargados u organizaciones, esquemas de mejores prácticas que tengan por objeto:\nI. Elevar el nivel de protección de los datos personales;\nII. Armonizar el tratamiento de datos personales en un sector específico;\nIII. Facilitar el ejercicio de los derechos ARCO por parte de las personas titulares;\nIV. Facilitar las transferencias de datos personales;\nV. Complementar las disposiciones previstas en la normatividad que resulte aplicable en materia de protección de datos personales; y,\nVI. Demostrar ante las Autoridades Garantes, el cumplimiento de la normatividad que resulte aplicable en materia de protección de datos personales.\nARTÍCULO 66.- Todo esquema de mejores prácticas que busque la validación o reconocimiento por parte de las Autoridades Garantes deberá:\nI. Cumplir con los criterios y parámetros que para tal efecto emitan las\nAutoridades Garantes que corresponda según su ámbito de competencia; y,\nII. Ser notificado ante las Autoridades Garantes de conformidad con el procedimiento establecido en los parámetros señalados en la fracción anterior, a fin de que sean evaluados y, en su caso, validados o reconocidos e inscritos en el registro al que refiere el último párrafo de este artículo.\nLas Autoridades Garantes, según su ámbito de competencia, deberán emitir las reglas\nLey de Protección de Datos Personales para el Sector Público Página 27\n.\nActualización Legislativa. prácticas validados o reconocidos. Las Autoridades Garantes podrán inscribir los esquemas de mejores prácticas que hayan reconocido o validado en el registro administrado por la\nSecretaría, de acuerdo con las reglas que fije esta última.\nARTÍCULO 67.- Cuando el responsable pretenda poner en operación o modificar políticas públicas, sistemas o plataformas informáticas, aplicaciones electrónicas o cualquier otra tecnología que a su juicio y de conformidad con esta Ley impliquen el tratamiento intensivo o relevante de datos personales, deberá realizar una evaluación de impacto en la protección de datos personales, y presentarla ante las Autoridades Garantes, las cuales podrán emitir recomendaciones no vinculantes especializadas en la materia de protección de datos personales.\nEl contenido de la evaluación de impacto en la protección de datos personales deberá determinarse por las Autoridades Garantes.\nARTÍCULO 68.- Para efectos de esta Ley se considerará que se está en presencia de un tratamiento intensivo o relevante de datos personales cuando:\nI. Existan riesgos inherentes a los datos personales a tratar;\nII. Se traten datos personales sensibles; y,\nIII. Se efectúen o pretendan efectuar transferencias de datos personales.\nARTÍCULO 69.- Las Autoridades Garantes podrán emitir criterios adicionales con sustento en parámetros objetivos que determinen que se está en presencia de un tratamiento intensivo o relevante de datos personales, de conformidad con lo dispuesto en el artículo anterior, en función de:\nI. El número de personas titulares;\nII. El público objetivo;\nIII. El desarrollo de la tecnología utilizada; y,\nIV. La relevancia del tratamiento de datos personales en atención al impacto social o económico del mismo, o bien, del interés público que se persigue.\nARTÍCULO 70.- Los responsables que realicen una evaluación de impacto en la protección de datos personales, deberán presentarla ante las Autoridades Garantes treinta públicas, sistemas o plataformas informáticas, aplicaciones electrónicas o cualquier otra tecnología, a efecto de que emitan las recomendaciones no vinculantes correspondientes.\nLey de Protección de Datos Personales para el Sector Público Página 28\n.\nActualización Legislativa.\nARTÍCULO 71.- Las Autoridades Garantes deberán emitir, de ser el caso, recomendaciones no vinculantes sobre la evaluación de impacto en la protección de datos personales presentada por el responsable.\nEl plazo para la emisión de las recomendaciones a que se refiere el párrafo anterior será dentro de los treinta días siguientes contados a partir del día siguiente a la presentación de la evaluación de impacto en la protección de datos personales.\nARTÍCULO 72.- Cuando a juicio del sujeto obligado se puedan comprometer los efectos que se pretenden lograr con la posible puesta en operación o modificación de políticas públicas, sistemas o plataformas informáticas, aplicaciones electrónicas o cualquier otra tecnología que implique el tratamiento intensivo o relevante de datos personales o se trate de situaciones de emergencia o urgencia, no será necesario realizar la evaluación de impacto en la protección de datos personales.\nCapítulo II\nDe las Bases de Datos en Posesión de Instancias de\nSeguridad, Procuración y Administración de Justicia\nARTÍCULO 73.- La obtención y tratamiento de datos personales, en términos de lo que dispone esta Ley, por parte de los responsables competentes en instancias de seguridad, procuración y administración de justicia, está limitada a aquellos supuestos y categorías de datos que resulten necesarios y proporcionales para el ejercicio de las funciones en materia de seguridad nacional, seguridad pública, o para la prevención o persecución de los delitos.\nDeberán ser almacenados en las bases de datos establecidas para tal efecto.\nLas autoridades que accedan y almacenen los datos personales que se recaben por los particulares en cumplimiento de las disposiciones legales correspondientes, deberán cumplir con las disposiciones señaladas en el presente Capítulo.\nARTÍCULO 74.- En el tratamiento de datos personales, así como en el uso de las bases de datos para su almacenamiento, que realicen los responsables competentes de las instancias de seguridad, procuración y administración de justicia deberán cumplir con los principios establecidos en el Título Segundo de la presente Ley.\nLas comunicaciones privadas son inviolables; únicamente se podrá autorizar la los Estados Unidos Mexicanos, la Ley General y las demás leyes aplicables.\nARTÍCULO 75.- Los responsables de las bases de datos a que se refiere este Capítulo deberán establecer medidas de seguridad de nivel alto, para garantizar la integridad, disponibilidad y confidencialidad de la información, que permitan proteger los datos\nLey de Protección de Datos Personales para el Sector Público Página 29\n.\nActualización Legislativa. personales contra daño, pérdida, alteración, destrucción o el uso, acceso o tratamiento no autorizado.\nTÍTULO SÉPTIMO\nRESPONSABLES EN MATERIA DE PROTECCIÓN DE DATOS PERSONALES\nEN POSESIÓN DE LOS RESPONSABLES\nCapítulo I\nComité de Transparencia\nARTÍCULO 76.- Cada responsable contará con un Comité de Transparencia, el cual se integrará y funcionará conforme a lo dispuesto en la Ley de Transparencia, Acceso a la\nInformación Pública y Apertura Institucional del Estado, la presente Ley y demás disposiciones jurídicas aplicables.\nEl Comité de Transparencia será la autoridad máxima en materia de protección de datos personales.\nARTÍCULO 77.- Para los efectos de la presente Ley y sin perjuicio de otras atribuciones que le sean conferidas en la normatividad que le resulte aplicable, el Comité de\nTransparencia tendrá las siguientes funciones:\nI. Coordinar, supervisar y realizar las acciones necesarias para garantizar el derecho a la protección de los datos personales en la organización del responsable, de conformidad con lo previsto en la presente Ley y demás disposiciones aplicables en la materia;\nII. Instituir, en su caso, procedimientos internos para asegurar la mayor eficiencia en la gestión de las solicitudes para el ejercicio de los derechos ARCO;\nIII. Confirmar, modificar o revocar las determinaciones en las que se declare la inexistencia de los datos personales, o se niegue por cualquier causa el ejercicio de alguno de los derechos ARCO;\nIV. Establecer y supervisar la aplicación de criterios específicos que resulten en la materia;\nV. Supervisar, en coordinación con las áreas o unidades administrativas competentes, el cumplimiento de las medidas, controles y acciones previstas en el documento de seguridad;\nVI. Dar seguimiento y cumplimiento a las resoluciones emitidas por las Autoridades\nGarantes, según corresponda;\nLey de Protección de Datos Personales para el Sector Público Página 30\n.\nActualización Legislativa.\nVII. Establecer programas de capacitación y actualización para las personas servidoras públicas en materia de protección de datos personales; y,\nVIII. Dar vista al órgano interno de control o instancia equivalente en aquellos casos en que tenga conocimiento, en el ejercicio de sus atribuciones, de una presunta irregularidad respecto de determinado tratamiento de datos personales; particularmente en casos relacionados con la declaración de inexistencia que realicen.\nCapítulo II\nDe la Unidad de Transparencia\nARTÍCULO 78.- Cada responsable contará con una Unidad de Transparencia que se integrará y funcionará conforme a lo dispuesto en la Ley de Transparencia, Acceso a la\nInformación Pública y Apertura Institucional del Estado, que tendrá además las siguientes funciones:\nI. Auxiliar y orientar a la persona titular que lo requiera con relación al ejercicio del derecho a la protección de datos personales;\nII. Gestionar las solicitudes para el ejercicio de los derechos ARCO;\nIII. Establecer mecanismos para asegurar que los datos personales solo se entreguen a la persona titular o su representante debidamente acreditados;\nIV. Informar a la persona titular o su representante el monto de los costos a cubrir por la reproducción y envío de los datos personales, con base en lo establecido en las disposiciones jurídicas aplicables;\nV. Proponer al Comité de Transparencia los procedimientos internos que aseguren y fortalezcan mayor eficiencia en la gestión de las solicitudes para el ejercicio de los derechos\nARCO;\nVI. Aplicar instrumentos de evaluación de calidad sobre la gestión de las solicitudes para el ejercicio de los derechos ARCO; y,\nVII. Asesorar a las áreas adscritas al responsable en materia de protección de datos personales. tratamientos de datos personales relevantes o intensivos, podrán designar a un oficial de protección de datos personales, especializado en la materia, quien realizará las atribuciones mencionadas en este artículo y formará parte de la Unidad de Transparencia.\nLey de Protección de Datos Personales para el Sector Público Página 31\n.\nActualización Legislativa.\nLos responsables promoverán acuerdos con instituciones públicas especializadas que pudieran auxiliarles a la recepción, trámite y entrega de las respuestas a solicitudes de información, en la lengua indígena, braille o cualquier formato accesible correspondiente, en forma más eficiente.\nARTÍCULO 79.- El responsable procurará que las personas con algún tipo de discapacidad o grupos de atención prioritaria puedan ejercer, en igualdad de circunstancias, su derecho a la protección de datos personales.\nTÍTULO OCTAVO\nAUTORIDADES GARANTES\nCapítulo I\nDe las Autoridades Garantes\nARTÍCULO 80.- En la integración, procedimiento de designación, funcionamiento y competencia de las Autoridades Garantes se estará a lo dispuesto por la Ley de\nTransparencia, Acceso a la Información Pública y Apertura Institucional para el Estado de\nBaja California y demás disposiciones jurídicas aplicables.\nLa Transparencia para el Pueblo, conocerá de los recursos de revisión y denuncias en materia de protección de datos personales de los municipios del Estado.\nARTÍCULO 81.- Las Autoridades Garantes tendrán para los efectos de la presente Ley y sin perjuicio de otras atribuciones que tenga conferidas conforme a las disposiciones jurídicas que les resulte aplicable, las siguientes atribuciones:\nI. Conocer, sustanciar y resolver, en el ámbito de sus respectivas competencias, de los recursos de revisión interpuestos por las personas titulares, en términos de lo dispuesto en la presente Ley y demás disposiciones jurídicas aplicables;\nII. Promover y difundir el ejercicio del derecho a la protección de datos personales;\nIII. Coordinarse con las autoridades competentes para que las solicitudes para el indígenas, sean atendidos en la misma lengua;\nIV. Garantizar, en el ámbito de sus respectivas competencias, condiciones de prioritaria puedan ejercer, en igualdad de circunstancias, su derecho a la protección de datos personales;\nV. Elaborar y publicar estudios e investigaciones para difundir y ampliar el conocimiento sobre la materia de la presente Ley;\nLey de Protección de Datos Personales para el Sector Público Página 32\n.\nActualización Legislativa.\nVI. Hacer del conocimiento de las autoridades competentes la probable responsabilidad derivada del incumplimiento de las obligaciones previstas en la presente\nLey y en las demás disposiciones jurídicas aplicables en la materia;\nVII. Vigilar, en el ámbito de sus respectivas competencias, el cumplimiento de la presente Ley y demás disposiciones jurídicas que resulten aplicables;\nVIII. Llevar a cabo acciones y actividades que promuevan el conocimiento del derecho a la protección de datos personales, así como de sus prerrogativas;\nIX. Emitir, en su caso, las recomendaciones no vinculantes correspondientes a la evaluación de impacto en la protección de datos personales que le sean presentadas.\nX. Garantizar el ejercicio del derecho a la protección de datos personales en posesión de los responsables;\nXI. Interpretar la presente Ley en el ámbito administrativo;\nXII. Conocer, sustanciar y resolver los procedimientos de verificación;\nXIII. Establecer y ejecutar las medidas de apremio previstas en términos de lo dispuesto por la presente Ley y demás disposiciones que resulten aplicables en la materia;\nXIV. Denunciar ante las autoridades competentes las presuntas infracciones a la presente Ley y, en su caso, aportar las pruebas con las que cuente;\nXV. Proporcionar apoyo técnico a los responsables para el cumplimiento de las obligaciones establecidas en la presente Ley;\nXVI. Divulgar y emitir recomendaciones, estándares y mejores prácticas en las materias reguladas por la presente Ley;\nXVII. Administrar el registro de esquemas de mejores prácticas a que se refiere la presente Ley y emitir sus reglas de operación;\nXVIII. Emitir disposiciones generales para el desarrollo del procedimiento de verificación;\nXIX. Realizar las evaluaciones correspondientes a los esquemas de mejores prácticas que les sean notificados, a fin de resolver sobre la procedencia de su prácticas, así como promover la adopción de los mismos;\nLey de Protección de Datos Personales para el Sector Público Página 33\n.\nActualización Legislativa.\nXX. Emitir, en el ámbito de su competencia, las disposiciones administrativas de carácter general para el debido cumplimiento de los principios, deberes y obligaciones que establece la presente Ley, así como para el ejercicio de los derechos de las personas titulares;\nXXI. Celebrar convenios con los responsables para desarrollar programas que tengan por objeto homologar tratamientos de datos personales en sectores específicos, elevar la protección de los datos personales y realizar cualquier mejora a las prácticas en la materia;\nXXII. Celebrar convenios con las Autoridades Garantes y responsables que coadyuven al cumplimiento de los objetivos previstos en la presente Ley y demás disposiciones aplicables en la materia, y\nXXIII. Definir y desarrollar el sistema de certificación en materia de protección de datos personales, de conformidad con lo que se establezca en los parámetros a que se refiere la presente Ley;\nXXIV. Diseñar y aplicar indicadores y criterios para evaluar el desempeño de los responsables respecto al cumplimiento de la presente Ley y demás disposiciones que resulten aplicables en la materia;\nXXV. Promover la capacitación y actualización en materia de protección de datos personales entre los responsables;\nXXVI. Emitir lineamientos generales para el debido tratamiento de los datos personales;\nXXVII. Emitir lineamientos para homologar el ejercicio de los derechos ARCO;\nXXVIII. Emitir criterios generales de interpretación para garantizar el derecho a la protección de datos personales;\nXXIX. Cooperar con otras autoridades de supervisión y organismos nacionales e internacionales, a efecto de coadyuvar en materia de protección de datos personales, de jurídicas aplicables;\nXXX. Promover e impulsar el ejercicio y tutela del derecho a la protección de datos personales a través de la implementación y administración de la Plataforma Nacional;\nXXXI. Cooperar con otras autoridades nacionales o internacionales para combatir conductas relacionadas con el tratamiento indebido de datos personales;\nLey de Protección de Datos Personales para el Sector Público Página 34\n.\nActualización Legislativa.\nXXXII. Diseñar, vigilar y, en su caso, operar el sistema de buenas prácticas en materia de protección de datos personales, así como el sistema de certificación en la materia, a través de disposiciones de carácter general que emita para tales fines; y,\nXXXIII. Las demás que le confiera la presente Ley y demás ordenamientos aplicables.\nCapítulo II\nDe la Coordinación y Promoción del\nDerecho a la Protección de Datos Personales\nARTÍCULO 82.- Los responsables deberán colaborar con las Autoridades Garantes, según corresponda, para capacitar y actualizar de forma permanente a todas las personas servidoras públicas que tengan adscritas en materia de protección de datos personales, a través de la impartición de cursos, seminarios, talleres y cualquier otra forma de enseñanza y entrenamiento que se considere pertinente.\nARTÍCULO 83.- Las Autoridades Garantes, en el ámbito de sus respectivas competencias, deberán:\nI. Promover que en los programas y planes de estudio, libros y materiales que se utilicen en las instituciones educativas de todos los niveles y modalidades del Estado, se incluyan contenidos sobre el derecho a la protección de datos personales, así como una cultura sobre el ejercicio y respeto de éste;\nII. Impulsar en conjunto con instituciones de educación superior, la integración de centros de investigación, difusión y docencia sobre el derecho a la protección de datos personales que promuevan el conocimiento sobre este tema y coadyuven con las Autoridades\nGarantes en sus tareas sustantivas; y,\nIII. Fomentar la creación de espacios de participación social y ciudadana que estimulen el intercambio de ideas entre la sociedad, los órganos de representación ciudadana y los responsables.\nTÍTULO NOVENO\nDEL PROCEDIMIENTO DE IMPUGNACIÓN\nCapítulo I\nDel Recurso de Revisión\nARTÍCULO 84.- La persona titular o su representante podrá interponer un recurso de revisión ante las Autoridades Garantes, según corresponda, o bien, ante la Unidad de\nLey de Protección de Datos Personales para el Sector Público Página 35\n.\nActualización Legislativa.\nTransparencia que haya conocido de la solicitud para el ejercicio de los derechos ARCO dentro de un plazo que no podrá exceder de quince días contados a partir de la notificación de la respuesta, a través de los siguientes medios:\nI. Por escrito libre en el domicilio de las Autoridades Garantes, según corresponda, o en las oficinas habilitadas que al efecto establezcan;\nII. Por correo certificado con acuse de recibo;\nIII. Por formatos que al efecto emitan las Autoridades Garantes, según corresponda;\nIV. Por los medios electrónicos que para tal fin se autoricen; o,\nV. Cualquier otro medio que al efecto establezca las Autoridades Garantes, según corresponda.\nSe presumirá que la persona titular acepta que las notificaciones le sean efectuadas por el mismo conducto que presentó su escrito, salvo que acredite haber señalado uno distinto para recibir notificaciones.\nARTÍCULO 85.- La persona titular podrá acreditar su identidad a través de cualquiera de los siguientes medios:\nI. Identificación oficial;\nII. Firma electrónica avanzada o del instrumento electrónico que lo sustituya; o,\nIII. Mecanismos de autenticación autorizados por las Autoridades Garantes, según corresponda, mediante acuerdo publicado en el Periódico Oficial del Estado.\nEl uso de la firma electrónica avanzada o del instrumento electrónico que lo sustituya eximirá de la presentación de la copia del documento de identificación.\nARTÍCULO 86.- Cuando la persona titular actúe mediante un representante, este deberá acreditar su personalidad en los siguientes términos:\nI. Si se trata de una persona física, a través de carta poder simple suscrita ante dos testigos anexando copia de las identificaciones de los suscriptores, o instrumento público, o\nAutoridades Garantes; y,\nII. Si se trata de una persona moral, mediante instrumento público.\nLey de Protección de Datos Personales para el Sector Público Página 36\n.\nActualización Legislativa.\nARTÍCULO 87.- La interposición del recurso de revisión relacionado con datos personales de personas fallecidas, podrá realizarla la persona que acredite tener un interés jurídico o legítimo.\nARTÍCULO 88.- En la sustanciación de los recursos de revisión, las notificaciones que emitan las Autoridades Garantes, surtirán efectos el mismo día en que se practiquen.\nLas notificaciones podrán efectuarse:\nI. Personalmente en los siguientes casos:\na) Se trate de la primera notificación;\nb) Se trate del requerimiento de un acto a la parte que deba cumplirlo;\nc) Se trate de la solicitud de informes o documentos;\nd) Se trate de la resolución que ponga fin al procedimiento de que se trate; y,\ne) En los demás casos que disponga la ley.\nII. Por correo certificado con acuse de recibo o medios digitales o sistemas autorizados por las Autoridades Garantes, mediante acuerdo publicado en el Periódico Oficial del Estado, cuando se trate de requerimientos, emplazamientos, solicitudes de informes o documentos y resoluciones que puedan ser impugnadas;\nIII. Por correo postal ordinario o por correo electrónico ordinario cuando se trate de actos distintos de los señalados en las fracciones anteriores; o,\nIV. Por estrados, cuando la persona a quien deba notificarse no sea localizable en su domicilio, se ignore este o el de su representante.\nARTÍCULO 89.- El cómputo de los plazos señalados en el presente Título comenzará a correspondiente.\nConcluidos los plazos fijados a las partes, se tendrá por perdido el derecho que dentro de ellos debió ejercitarse, sin necesidad de acuse de rebeldía por parte de la Autoridad\nGarante.\nARTÍCULO 90.- La persona titular, el responsable o cualquier autoridad deberá atender los requerimientos de información en los plazos y términos que las Autoridades Garantes, según corresponda, establezcan.\nLey de Protección de Datos Personales para el Sector Público Página 37\n.\nActualización Legislativa.\nARTÍCULO 91.- Cuando la persona titular, el responsable o cualquier autoridad se niegue a atender o cumplimentar los requerimientos, solicitudes de información y documentación, emplazamientos, citaciones o diligencias notificadas por las Autoridades\nGarantes, o facilitar la práctica de las diligencias que hayan sido ordenadas, o entorpezca sus actuaciones, según corresponda, tendrán por perdido su derecho para hacerlo valer en algún otro momento del procedimiento y las Autoridades Garantes, tendrán por ciertos los hechos materia del procedimiento y resolverán con los elementos que dispongan.\nARTÍCULO 92. En la sustanciación de los recursos de revisión, las partes podrán ofrecer las siguientes pruebas:\nI. La documental pública;\nII. La documental privada;\nIII. La inspección;\nIV. La pericial;\nV. La testimonial;\nVI. La confesional, excepto tratándose de autoridades;\nVII. Las imágenes fotográficas, páginas electrónicas, escritos y demás elementos aportados por la ciencia y tecnología; y,\nVIII. La presuncional legal y humana.\nLas Autoridades Garantes, podrán allegarse de los medios de prueba que consideren necesarios, sin más limitación que las establecidas en la legislación aplicable.\nARTÍCULO 93.- Transcurrido el plazo previsto en el artículo 44 de la presente Ley para dar respuesta a una solicitud para el ejercicio de los derechos ARCO sin que se haya emitido ésta, la persona titular o, en su caso, su representante podrá interponer el recurso de revisión dentro de los quince días siguientes a aquel en que haya vencido el plazo para dar respuesta.\nARTÍCULO 94.- El recurso de revisión procederá en los siguientes supuestos:\nI. Se clasifiquen como confidenciales los datos personales sin que se cumplan las características señaladas en las disposiciones jurídicas aplicables;\nII. Se declare la inexistencia de los datos personales;\nIII. Se declare la incompetencia por el responsable;\nIV. Se entreguen datos personales incompletos;\nLey de Protección de Datos Personales para el Sector Público Página 38\n.\nActualización Legislativa.\nV. Se entreguen datos personales que no correspondan con lo solicitado;\nVI. Se niegue el acceso, rectificación, cancelación u oposición de datos personales;\nVII. No se dé respuesta a una solicitud para el ejercicio de los derechos ARCO dentro de los plazos establecidos en la presente Ley y demás disposiciones aplicables en la materia;\nVIII. Se entregue o ponga a disposición datos personales en una modalidad o formato distinto al solicitado, o en un formato incomprensible;\nIX. La persona titular se inconforme con los costos de reproducción, envío o tiempos de entrega de los datos personales;\nX. Se obstaculice el ejercicio de los derechos ARCO, a pesar de que fue notificada la procedencia de los mismos;\nXI. No se dé trámite a una solicitud para el ejercicio de los derechos ARCO; y,\nXII. En los demás casos que disponga la legislación aplicable.\nARTÍCULO 95. Los únicos requisitos exigibles en el escrito de interposición del recurso de revisión serán los siguientes:\nI. El área responsable ante quien se presentó la solicitud para el ejercicio de los derechos ARCO;\nII. El nombre de la persona titular que recurre o su representante y, en su caso, del tercero interesado, así como el domicilio o medio que señale para recibir notificaciones;\nIII. La fecha en que fue notificada la respuesta a la persona titular, o bien, en caso de falta de respuesta la fecha de la presentación de la solicitud para el ejercicio de los derechos ARCO;\nIV. El acto que se recurre y los puntos petitorios, así como las razones o motivos de inconformidad;\nV. En su caso, copia de la respuesta que se impugna y de la notificación correspondiente; y,\nVI. Los documentos que acrediten la identidad de la persona titular y, en su caso, la personalidad e identidad de su representante. considere la persona titular procedentes someter a juicio de las Autoridades Garantes.\nLey de Protección de Datos Personales para el Sector Público Página 39\n.\nActualización Legislativa.\nEn ningún caso será necesario que la persona titular ratifique el recurso de revisión interpuesto.\nARTÍCULO 96.- Una vez admitido el recurso de revisión las Autoridades Garantes podrán buscar una conciliación entre la persona titular y el responsable.\nDe llegar a un acuerdo, este se hará constar por escrito y tendrá efectos vinculantes. El recurso de revisión quedará sin materia y las Autoridades Garantes, deberán verificar el cumplimiento del acuerdo respectivo.\nARTÍCULO 97.- Admitido el recurso de revisión y sin perjuicio de lo dispuesto por el artículo 58 de la presente Ley, las Autoridades Garantes promoverán la conciliación entre las partes, de conformidad con el siguiente procedimiento:\nI. Requerirá a las partes que manifiesten, por cualquier medio, su voluntad de conciliar, en un plazo no mayor a siete días, contados a partir de la notificación de dicho acuerdo, mismo que contendrá un resumen del recurso de revisión y de la respuesta del responsable si la hubiere, señalando los elementos comunes y los puntos de controversia.\nLa conciliación podrá celebrarse presencialmente, por medios remotos, electrónicos o por cualquier otro medio que determine, según corresponda. En cualquier caso, la conciliación habrá de hacerse constar por el medio que permita acreditar su existencia.\nQueda exceptuada de la etapa de conciliación, cuando la persona titular sea menor de edad y se haya vulnerado alguno de los derechos contemplados en la Ley General de los\nDerechos de Niñas, Niños y Adolescentes y demás disposiciones jurídicas aplicables, salvo que cuente con representación legal debidamente acreditada.\nII. Recibida la manifestación de la voluntad de conciliar por ambas partes, la Autoridad\nGarante señalará el lugar o medio, día y hora para la celebración de una audiencia de conciliación en la que se procurará avenir los intereses entre la persona titular y el responsable, la cual deberá realizarse dentro de los diez días siguientes en que se reciba la manifestación antes mencionada.\nLas Autoridades Garantes en su calidad de conciliadoras podrán, en todo momento en la etapa de conciliación, requerir a las partes que presenten en un plazo máximo de cinco días, los elementos de convicción que estime necesarios para la conciliación. partes la audiencia por una ocasión. En caso de que se suspenda la audiencia, la conciliadora señalará día y hora para su reanudación dentro de los cinco días siguientes.\nDe toda audiencia de conciliación se levantará el acta respectiva, en la que conste el resultado de la misma. En caso de que el responsable o la persona titular o sus respectivos\nLey de Protección de Datos Personales para el Sector Público Página 40\n.\nActualización Legislativa. representantes no firmen el acta, ello no afectará su validez, debiéndose hacer constar dicha negativa.\nIII. Si alguna de las partes no acude a la audiencia de conciliación y justifica su ausencia en un plazo de tres días, será convocada a una segunda audiencia de conciliación, en el plazo de cinco días. En caso de que no acuda a esta última, se continuará con el recurso de revisión. Cuando alguna de las partes no acuda a la audiencia de conciliación sin justificación alguna, se continuará con el procedimiento.\nIV. De no existir acuerdo en la audiencia de conciliación, se continuará con el recurso de revisión.\nV. De llegar a un acuerdo, este se hará constar por escrito y tendrá efectos vinculantes.\nEl recurso de revisión quedará sin materia y las Autoridades Garantes, deberán verificar el cumplimiento del acuerdo respectivo.\nVI. El cumplimiento del acuerdo dará por concluida la sustanciación del recurso de revisión, en caso contrario, la Autoridad Garante reanudará el procedimiento.\nARTÍCULO 98.- Las Autoridades Garantes resolverán el recurso de revisión en un plazo que no podrá exceder de cuarenta días, el cual podrá ampliarse hasta por veinte días por una sola vez.\nEl plazo a que se refiere el párrafo anterior será suspendido durante el periodo de cumplimiento del acuerdo de conciliación.\nARTÍCULO 99.- Durante el procedimiento a que se refiere el presente Capítulo, las\nAutoridades Garantes deberán aplicar la suplencia de la queja a favor de la persona titular, siempre y cuando no altere el contenido original del recurso de revisión, ni modifique los hechos o peticiones expuestas en el mismo, así como garantizar que las partes puedan presentar los argumentos y constancias que funden y motiven sus pretensiones.\nARTÍCULO 100.- Si en el escrito de interposición del recurso de revisión la persona titular no cumple con alguno de los requisitos previstos en el artículo 95 de la presente Ley y las Autoridades Garantes no cuenten con elementos para subsanarlos, estas últimas deberán requerir a la persona titular, por una sola ocasión, la información que subsane las omisiones en un plazo que no podrá exceder de cinco días, contados a partir del día siguiente de la presentación del escrito.\nLa persona titular contará con un plazo que no podrá exceder de cinco días, contados a partir del día siguiente al de la notificación de la prevención, para subsanar las omisiones, con el apercibimiento de que, en caso de no cumplir con el requerimiento, se desechará el recurso de revisión.\nLey de Protección de Datos Personales para el Sector Público Página 41\n.\nActualización Legislativa.\nLa prevención tendrá el efecto de interrumpir el plazo que tienen las Autoridades\nGarantes para resolver el recurso, por lo que comenzará a computarse a partir del día siguiente a su desahogo.\nARTÍCULO 101.- Las resoluciones de las Autoridades Garantes podrán:\nI. Sobreseer o desechar el recurso de revisión por improcedente;\nII. Confirmar la respuesta del responsable;\nIII. Revocar o modificar la respuesta del responsable; o,\nIV. Ordenar la entrega de los datos personales, en caso de omisión del responsable.\nLas resoluciones establecerán, en su caso, los plazos y términos para su cumplimiento y los procedimientos para asegurar su ejecución. Los responsables deberán informar a las\nAutoridades Garantes el cumplimiento de sus resoluciones.\nAnte la falta de resolución por parte de las Autoridades Garantes, se entenderá confirmada la respuesta del responsable.\nCuando las Autoridades Garantes determinen durante la sustanciación del recurso de revisión que se pudo haber incurrido en una probable responsabilidad por el incumplimiento a las obligaciones previstas en la presente Ley y demás disposiciones jurídicas aplicables en la materia, deberán hacerlo del conocimiento del órgano interno de control o de la instancia competente para que ésta inicie, en su caso, el procedimiento de responsabilidad respectivo.\nARTÍCULO 102.- El recurso de revisión podrá ser desechado por improcedente cuando:\nI. Sea extemporáneo por haber transcurrido el plazo establecido en el artículo 84 de la presente Ley;\nII. La persona titular o su representante no acrediten debidamente su identidad y personalidad de este último;\nIII. Las Autoridades Garantes hayan resuelto anteriormente en definitiva sobre la materia del mismo;\nIV. No se actualice alguna de las causales del recurso de revisión previstas en el artículo 94 de la presente Ley;\nV. Se esté tramitando ante los tribunales competentes algún recurso o medio de defensa interpuesto por la persona recurrente o, en su caso, por el tercero interesado, en contra del acto recurrido ante las Autoridades Garantes;\nLey de Protección de Datos Personales para el Sector Público Página 42\n.\nActualización Legislativa.\nVI. La persona recurrente modifique o amplíe su petición en el recurso de revisión, únicamente respecto de los nuevos contenidos; o,\nVII. La persona recurrente no acredite interés jurídico.\nEl desechamiento no implica la preclusión del derecho de la persona titular para interponer ante las Autoridades Garantes, un nuevo recurso de revisión.\nARTÍCULO 103.- El recurso de revisión solo podrá ser sobreseído cuando:\nI. La persona recurrente se desista expresamente;\nII. La persona recurrente fallezca;\nIII. Una vez admitido se actualice alguna causal de improcedencia en los términos de la presente Ley;\nIV. El responsable modifique o revoque su respuesta de tal manera que el mismo quede sin materia; o,\nV. Quede sin materia.\nARTÍCULO 104.- Las Autoridades Garantes deberán notificar a las partes y publicar las resoluciones, en versión pública, a más tardar al tercer día siguiente de su emisión.\nARTÍCULO 105.- Las resoluciones de las Autoridades Garantes serán vinculantes, definitivas e inatacables para los responsables.\nLas personas titulares podrán impugnar dichas resoluciones ante los jueces y tribunales especializados en materia de datos personales establecidos por el Poder Judicial de la Federación mediante el juicio de amparo.\nCapítulo II\nDe los Criterios de Interpretación\nARTÍCULO 106.- Una vez que hayan causado ejecutoria las resoluciones dictadas con motivo de los recursos que se sometan a su competencia, las Autoridades Garantes podrán los mismos.\nARTÍCULO 107.- Los criterios se compondrán de un rubro, un texto y el precedente o precedentes que, en su caso, hayan originado su emisión.\nLey de Protección de Datos Personales para el Sector Público Página 43\n.\nActualización Legislativa.\nTodo criterio que emitan las Autoridades Garantes, deberá contener una clave de control para su debida identificación.\nTÍTULO DÉCIMO\nFACULTAD DE VERIFICACIÓN\nCapítulo Único\nFacultad de Verificación de las Autoridades Garantes\nARTÍCULO 108.- Las Autoridades Garantes tendrán la atribución de vigilar y verificar el cumplimiento de las disposiciones contenidas en la presente Ley y demás ordenamientos que se deriven de ésta.\nEn el ejercicio de las funciones de vigilancia y verificación, las Autoridades Garantes estarán obligadas a guardar confidencialidad sobre la información a la que tengan acceso en virtud de la verificación correspondiente.\nEl responsable no podrá negar el acceso a la documentación solicitada con motivo de una verificación, o a sus bases de datos personales, ni podrá invocar la reserva o la confidencialidad de la información.\nARTÍCULO 109.- La verificación podrá iniciarse:\nI. De oficio cuando las Autoridades Garantes cuenten con indicios que hagan presumir fundada y motivada la existencia de violaciones a las leyes correspondientes; o,\nII. Por denuncia de la persona titular cuando considere que ha sido afectada por actos del responsable que puedan ser contrarios a lo dispuesto por la presente Ley y demás disposiciones jurídicas aplicables o, en su caso, por cualquier persona cuando tenga conocimiento de presuntos incumplimientos a las obligaciones previstas en la presente Ley y demás disposiciones aplicables en la materia.\nEl derecho a presentar una denuncia precluye en el término de un año contado a partir del día siguiente en que se realicen los hechos u omisiones materia de la misma. Cuando los hechos u omisiones sean de tracto sucesivo, el término empezará a contar a partir del día hábil siguiente al último hecho realizado. recurso de revisión previstos en la presente Ley.\nPrevio a la verificación respectiva, las Autoridades Garantes podrán desarrollar investigaciones previas, con el fin de contar con elementos para fundar y motivar el acuerdo de inicio respectivo.\nARTÍCULO 110.- Para la presentación de una denuncia no podrán solicitarse mayores requisitos que los que a continuación se describen:\nLey de Protección de Datos Personales para el Sector Público Página 44\n.\nActualización Legislativa.\nI. El nombre de la persona que denuncia o, en su caso, de su representante;\nII. El domicilio o medio para recibir notificaciones de la persona que denuncia;\nIII. La relación de hechos en que se basa la denuncia y los elementos con los que cuente para probar su dicho;\nIV. El responsable denunciado y su domicilio o, en su caso, los datos para su identificación y/o ubicación; y,\nV. La firma de la persona denunciante o, en su caso, de su representante. En caso de no saber firmar, bastará la huella digital.\nLa denuncia podrá presentarse por escrito libre o a través de los formatos, medios electrónicos o cualquier otro medio que al efecto establezcan las Autoridades Garantes.\nUna vez recibida la denuncia, las Autoridades Garantes deberán acusar recibo de la misma. El acuerdo correspondiente se notificará a la persona denunciante.\nARTÍCULO 111.- La verificación iniciará mediante una orden escrita que funde y motive la procedencia de la actuación por parte de las Autoridades Garantes, la cual tiene por objeto requerir al responsable la documentación e información necesaria vinculada con la presunta violación y/o realizar visitas a las oficinas o instalaciones del responsable o, en su caso, en el lugar donde estén ubicadas las bases de datos personales respectivas.\nPara la verificación en instancias de seguridad pública, se requerirá en la resolución una fundamentación y motivación reforzada de la causa del procedimiento, debiéndose asegurar la información sólo para uso exclusivo de la autoridad y para los fines establecidos en el artículo 112 de la presente Ley.\nEl procedimiento de verificación deberá tener una duración máxima de cincuenta días.\nLas Autoridades Garantes podrán ordenar medidas cautelares, si del desahogo de la verificación advierten un daño inminente o irreparable en materia de protección de datos personales, siempre y cuando no impidan el cumplimiento de las funciones ni el aseguramiento de bases de datos de los responsables.\nGarantes.\nARTÍCULO 112.- El procedimiento de verificación concluirá con la resolución que emitan las Autoridades Garantes correspondientes, en las cuales se establecerán las medidas que deberá adoptar el responsable en el plazo que la misma determine.\nLey de Protección de Datos Personales para el Sector Público Página 45\n.\nActualización Legislativa.\nARTÍCULO 113.- Los responsables podrán voluntariamente someterse a la realización de auditorías por parte de las Autoridades Garantes, que tengan por objeto verificar la adaptación, adecuación y eficacia de los controles, medidas y mecanismos implementados para el cumplimiento de la presente Ley y demás disposiciones jurídicas aplicables.\nEl informe de auditoría deberá dictaminar sobre la adecuación de las medidas y controles implementados por el responsable, identificar sus deficiencias, así como proponer acciones correctivas complementarias, o bien, recomendaciones que en su caso correspondan.\nTÍTULO DÉCIMO PRIMERO\nMEDIDAS DE APREMIO Y RESPONSABILIDADES\nCapítulo I\nDe las Medidas de Apremio\nARTÍCULO 114.- Para el cumplimiento de las resoluciones emitidas por las\nAutoridades Garantes, según corresponda, se deberá observar lo dispuesto en el Capítulo II del Título Séptimo de la Ley de Transparencia, Acceso a la Información Pública y Apertura\nInstitucional para el Estado de Baja California.\nARTÍCULO 115.- Las Autoridades Garantes podrán imponer las siguientes medidas de apremio para asegurar el cumplimiento de sus determinaciones:\nI. La amonestación pública; o,\nII. La multa, equivalente a la cantidad de ciento cincuenta hasta mil quinientas veces el valor diario de la Unidad de Medida y Actualización.\nEl incumplimiento de los responsables será difundido en los portales de obligaciones de transparencia de las Autoridades Garantes y considerados en las evaluaciones que realicen éstas. obligaciones materia de la Ley General y esta Ley, deberán denunciar los hechos ante la autoridad competente. Las medidas de apremio de carácter económico no podrán ser cubiertas con recursos públicos.\nARTÍCULO 116.- Si a pesar de la ejecución de las medidas de apremio previstas en el artículo anterior no se cumpliere con la resolución, se requerirá el cumplimiento a la persona superior jerárquica, para que, en el plazo de cinco días lo obligue a cumplir sin demora.\nLey de Protección de Datos Personales para el Sector Público Página 46\n.\nActualización Legislativa.\nDe persistir el incumplimiento, se aplicarán sobre la persona superior jerárquica, las medidas de apremio establecidas en el artículo anterior.\nTranscurrido el plazo, sin que se haya dado cumplimiento, se dará vista a la autoridad competente en materia de responsabilidades.\nARTÍCULO 117.- Las medidas de apremio a que se refiere el presente Capítulo deberán ser aplicadas por las Autoridades Garantes, por sí mismas o con el apoyo de la autoridad competente.\nARTÍCULO 118.- Las multas que fijen las Autoridades Garantes se harán efectivas por la Secretaría de Hacienda u homólogos en sus respectivos poderes y ámbitos de competencia, a través del procedimiento que las leyes aplicables establezcan, según corresponda, a través de los procedimientos establecidos en las disposiciones jurídicas aplicables.\nARTÍCULO 119.- Para calificar las medidas de apremio establecidas en el presente\nCapítulo, las Autoridades Garantes deben considerar:\nI. La gravedad de la falta del responsable, determinada por elementos tales como el daño causado; los indicios de intencionalidad; la duración del incumplimiento de las determinaciones de las Autoridades Garantes y la afectación al ejercicio de sus atribuciones;\nII. La condición económica del infractor; y,\nIII. La reincidencia.\nLas Autoridades Garantes establecerán mediante lineamientos de carácter general, las atribuciones de las áreas encargadas de calificar la gravedad de la falta de observancia a sus determinaciones y de la notificación y ejecución de las medidas de apremio que apliquen e implementen, conforme a los elementos desarrollados en este Capítulo.\nARTÍCULO 120.- En caso de reincidencia, las Autoridades Garantes podrán imponer una multa dentro del ámbito de su competencia equivalente hasta el doble de la que se hubiera determinado. sancionada, cometa otra del mismo tipo o naturaleza.\nARTÍCULO 121.- Las medidas de apremio deberán aplicarse e implementarse en un plazo máximo de quince días, contados a partir de que sea notificada la medida de apremio a la persona infractora.\nARTÍCULO 122.- La amonestación pública será impuesta por las Autoridades Garantes y será ejecutada por la persona superior jerárquica inmediata de la persona infractora.\nLey de Protección de Datos Personales para el Sector Público Página 47\n.\nActualización Legislativa.\nARTÍCULO 123.- Las Autoridades Garantes podrán requerir a la persona infractora la información necesaria para determinar su condición económica, apercibida, de que en caso de no proporcionar la misma, las multas se cuantificarán con base en los elementos que se tengan a disposición, entendidos como los que se encuentren en los registros públicos, los que contengan medios de información o sus propias páginas de internet y, en general, cualquiera que evidencie su condición, quedando facultadas las Autoridades Garantes para requerir aquella documentación que se considere indispensable para tal efecto a las autoridades competentes.\nARTÍCULO 124.- En contra de la imposición de medidas de apremio procede el recurso correspondiente ante el Tribunal Estatal de Justicia Administrativa.\nCapítulo II\nDe las Sanciones\nARTÍCULO 125.- Serán causas de sanción por incumplimiento de las obligaciones establecidas en la materia de la presente Ley, las siguientes:\nI. Actuar con negligencia, dolo o mala fe durante la sustanciación de las solicitudes para el ejercicio de los derechos ARCO;\nII. Incumplir los plazos de atención previstos en la presente Ley para responder las solicitudes para el ejercicio de los derechos ARCO o para hacer efectivo el derecho de que se trate;\nIII. Usar, sustraer, divulgar, ocultar, alterar, mutilar, destruir o inutilizar, total o parcialmente y de manera indebida datos personales, que se encuentren bajo su custodia o a los cuales tengan acceso o conocimiento con motivo de su empleo, cargo o comisión;\nIV. Dar tratamiento, de manera intencional, a los datos personales en contravención a los principios y deberes establecidos en la presente Ley;\nV. No contar con el aviso de privacidad, o bien, omitir en el mismo alguno de los elementos a que refiere el artículo 20 de la presente Ley, según sea el caso, y demás disposiciones que resulten aplicables en la materia;\nVI. Clasificar como confidencial, con dolo o negligencia, datos personales sin que se cumplan las características señaladas en las leyes que resulten aplicables. La sanción sólo procederá cuando exista una resolución previa, que haya quedado firme, respecto del criterio de clasificación de los datos personales;\nVII. Incumplir el deber de confidencialidad establecido en el artículo 35 de la presente Ley;\nLey de Protección de Datos Personales para el Sector Público Página 48\n.\nActualización Legislativa.\nVIII. No establecer las medidas de seguridad previstas en los artículos 24, 25 y 27 de la presente Ley;\nIX. Presentar vulneraciones a los datos personales por la falta de implementación de medidas de seguridad;\nX. Llevar a cabo la transferencia de datos personales, en contravención a lo previsto en la Ley;\nXI. Obstruir los actos de verificación de la autoridad;\nXII. Crear bases de datos en contravención a lo que dispone el artículo 5 de la Ley;\nXIII. No acatar las resoluciones emitidas por las Autoridades Garantes; y,\nXIV. Omitir la entrega del informe anual y demás informes a que se refiere el artículo\n33, fracción VI de la Ley de Transparencia, Acceso a la Información Pública y Apertura\nInstitucional para el Estado de Baja California, o bien, entregar el mismo de manera extemporánea.\nPara efectos de su sanción administrativa, las causas de responsabilidad previstas en las fracciones I, II, IV, VI, X, XII, y XIV, así como la reincidencia en las conductas previstas en el resto de las fracciones de este artículo, tendrán el carácter que la Ley General establezca.\nLas sanciones de carácter económico no podrán ser cubiertas con recursos públicos.\nARTÍCULO 126.- Para las conductas a que se refiere el artículo anterior se dará vista a la autoridad competente para que imponga o ejecute la sanción.\nARTÍCULO 127.- Las responsabilidades que resulten de los procedimientos administrativos correspondientes, derivados de la violación a lo dispuesto por el artículo 125 de esta Ley, son independientes de las del orden civil, penal o de cualquier otro tipo que se puedan derivar de los mismos hechos.\nDichas responsabilidades se determinarán, en forma autónoma, a través de los procedimientos previstos en las leyes aplicables y las sanciones que, en su caso, se impongan por las autoridades competentes, también se ejecutarán de manera independiente. consideren pertinentes, en los términos de las leyes aplicables.\nARTÍCULO 128.- En el caso de probables infracciones relacionadas con fideicomisos o fondos públicos, las Autoridades Garantes competentes deberán dar vista al órgano interno\nLey de Protección de Datos Personales para el Sector Público Página 49\n.\nActualización Legislativa. de control o equivalente del sujeto obligado correspondiente con el fin de que instrumente los procedimientos administrativos a que haya lugar.\nARTÍCULO 129.- En aquellos casos en que la persona presunta infractora tenga la calidad de persona servidora pública, la Autoridad Garante respectiva deberá remitir a la autoridad competente, junto con la denuncia correspondiente, un expediente que contenga todos los elementos que sustenten la presunta responsabilidad administrativa.\nLa autoridad que conozca del asunto deberá informar de la conclusión del procedimiento y, en su caso, de la ejecución de la sanción a la Autoridad Garante que corresponda.\nA efecto de sustanciar el procedimiento citado en este artículo, la Autoridad Garante que corresponda deberá elaborar lo siguiente:\nI. Denuncia dirigida a la contraloría, órgano interno de control o equivalente, con la descripción precisa de los actos u omisiones que, a su consideración, repercuten en la adecuada aplicación de la presente Ley y que pudieran constituir una posible responsabilidad; y,\nII. Expediente que contenga todos aquellos elementos de prueba que considere pertinentes para sustentar la existencia de la posible responsabilidad, y que acrediten el nexo causal existente entre los hechos controvertidos y las pruebas presentadas.\nLa denuncia y el expediente deberán remitirse a la contraloría, órgano interno de control o equivalente dentro de los quince días siguientes a partir de que la Autoridad Garante correspondiente tenga conocimiento de los hechos.\nARTÍCULO 130.- Las Autoridades Garantes deberán denunciar el incumplimiento de las determinaciones que éstas emitan y que impliquen la presunta comisión de un delito ante la autoridad competente.\nTRANSITORIOS\nPRIMERO.- El presente Decreto entrará en vigor a los quince días de su publicación en\nSEGUNDO.- Se abroga la Ley de Protección de Datos Personales en Posesión de\nSujetos Obligados para el Estado de Baja California, publicada en el Periódico Oficial del\nTERCERO.- Las menciones, atribuciones o funciones contenidas en otras leyes, reglamentos y en general, en cualquier disposición normativa, respecto al Instituto de\nTransparencia, Acceso a la Información Pública y Protección de Datos Personales del Estado\nLey de Protección de Datos Personales para el Sector Público Página 50\n.\nActualización Legislativa. de Baja California, se entenderán hechas o conferidas a los entes públicos que adquieren tales atribuciones o funciones, según corresponda al ámbito de su competencia.\nCUARTO.- Los registros, padrones y sistemas informáticos con los que cuenta el\nInstituto de Transparencia, Acceso a la Información Pública y Protección de Datos Personales del Estado de Baja California, incluso los que ya no se utilicen, pero contengan registros históricos, incluida su documentación y titularidad, serán transferidos a la Secretaría\nAnticorrupción y Buen Gobierno del Estado.\nQUINTO.- Los procedimientos iniciados con anterioridad a la entrada en vigor de este\nDecreto ante el Instituto de Transparencia, Acceso a la Información Pública y Protección de\nDatos Personales del Estado de Baja California, en materia de protección de datos personales, se sustanciarán ante el Órgano Desconcentrado de la Secretaría Anticorrupción y\nBuen Gobierno, denominado Transparencia para el Pueblo conforme a las disposiciones aplicables vigentes al momento de su inicio.\nLa defensa legal ante autoridades administrativas, jurisdiccionales y judiciales de los actos administrativos y jurídicos emitidos por el Instituto de Transparencia, Acceso a la\nInformación Pública y Protección de Datos Personales del Estado de Baja California, en materia de protección de datos personales, se llevará a cabo por Transparencia para el\nPueblo.\nTransparencia para el Pueblo podrá remitir a la Autoridad Garante competente aquellos asuntos que se mencionan en los párrafos anteriores, que le corresponda conforme al ámbito de sus atribuciones para su atención.\nSEXTO.- La persona titular del Poder Ejecutivo del Estado deberá expedir el\nReglamento Interno de Transparencia para el Pueblo dentro de los noventa días naturales siguientes a la entrada en vigor del presente Decreto. Para tal efecto, deberá emplear los recursos humanos con los que cuente el área competente, así como aquellos que le sean asignados en razón de las funciones que asuma como Autoridad Garante, conforme a las necesidades de mejora y modernización de la gestión pública.\nSÉPTIMO.- Los expedientes y archivos que a la entrada en vigor del presente Decreto estén a cargo del Instituto de Transparencia, Acceso a la Información Pública y Protección de\nDatos Personales del Estado de Baja California, para el ejercicio de sus facultades sustantivas, competencias o funciones, de conformidad con la Ley General de Archivos y demás disposiciones jurídicas aplicables, serán transferidos a la Secretaría Anticorrupción y presente Decreto. mencionan en el párrafo anterior, podrá transferirlos a la Autoridad Garante correspondiente.\nLey de Protección de Datos Personales para el Sector Público Página 51\n.\nActualización Legislativa.\nOCTAVO.- El Órgano de Control y Disciplina del Poder Judicial, los Órganos Internos de Control de los Órganos Constitucionales Autónomos y la Contraloría Interna del Poder\nLegislativo del Estado, en un plazo máximo de sesenta días naturales contados a partir de la entrada en vigor del presente Decreto, deberán realizar las adecuaciones necesarias a su normativa interna para dar cumplimiento a lo dispuesto en este instrumento.\nNOVENO.- Se suspenden por un plazo de noventa días naturales contados a partir de la entrada en vigor de este Decreto todos y cada uno de los trámites, procedimientos y demás medios de impugnación, establecidos en este instrumento y demás normativa aplicable, con excepción de la recepción y atención de las solicitudes de acceso, rectificación, cancelación, oposición o portabilidad que se tramitan a través de la Plataforma Nacional de Transparencia.\nDADO en Sesión Ordinaria de la XXV Legislatura en la Ciudad de Mexicali, B.C., a los once días del mes de septiembre del año dos mil veinticinco.\nDIP. JAIME EDUARDO CANTÓN ROCHA\nPRESIDENTE\n(RÚBICA)\nDIP. MICHELLE ALEJANDRA TEJEDA MEDINA\nSECRETARIA\n(RÚBICA)\nDE CONFORMIDAD CON LO DISPUESTO POR LA FRACCIÓN I DEL ARTÍCULO 49\nCALIFORNIA, IMPRÍMASE Y PUBLÍQUESE.\nMEXICALI, BAJA CALIFORNIA, A LOS 12 DÍAS DEL MES DE SEPTIEMBRE DEL\nAÑO DOS MIL VEINTICINCO.\nMARINA DEL PILAR ÁVILA OLMEDA\nGOBERNADORA DEL ESTADO\nDE BAJA CALIFORNIA\n(RÚBRICA)\nALFREDO ÁLVAREZ CÁRDENAS\nSECRETARIO GENERAL DE GOBIERNO\nDEL ESTADO DE BAJA CALIFORNIA\n(RÚBRICA)\nLey de Protección de Datos Personales para el Sector Público Página 52",
  "ordenamiento": "REGLAMENTO",
  "jurisdiccion": "BAJA CALIFORNIA",
  "fuente_oficial": "Periódico Oficial",
  "FECHA PER OFIC": "2025/09/16",
  "ESTATUS": "VIGENTE",
  "TOMO": "TOMO_I",
  "URL": "https://www.congresobc.gob.mx/Documentos/ProcesoParlamentario/Leyes/TOMO_I/20250916_LEYDATOSPERSONALES.PDF",
  "es_escaneado": false,
  "tiene_tablas": false,
  "materia": [
    "administrativo",
    "legislativo",
    "gobernanza"
  ]
}