{
  "titulo": "Ley DE VÍCTIMAS PARA EL ESTADO DE BAJA CALIFORNIA",
  "Contenido": "Publicada en el Periódico Oficial No. 49, Tomo CXXV,\nTÍTULO PRIMERO\nDISPOSICIONES GENERALES\nCAPÍTULO I\nAPLICACIÓN, OBJETO E INTERPRETACIÓN\nARTÍCULO 1.- La presente Ley es de orden público, de interés social y observancia general en el territorio del Estado de Baja California, conforme a lo dispuesto por los artículos 1º, párrafo tercero, 17, 20 y 73 XXXIX-X de la Constitución Política de los Estados\nUnidos Mexicanos, Tratados Internacionales celebrados y ratificados por el Estado\nMexicano, Ley General de Víctimas y otros ordenamientos en materia de víctimas.\nLa presente Ley obliga, a las autoridades estatales y municipales, así como a cualquiera de sus oficinas, dependencias, organismos o instituciones que velen por la protección de las víctimas, a proporcionar ayuda, asistencia o reparación que corresponda.\nLas autoridades de todos los ámbitos de gobierno deberán actuar conforme a los principios y criterios establecidos en esta Ley, así como brindar atención inmediata en especial en materias de salud, educación y asistencia social, en caso contrario quedarán sujetas a las responsabilidades administrativas, civiles o penales a que haya lugar.\nARTÍCULO 2.- La reparación a la víctima comprende las medidas de restitución, rehabilitación, compensación, satisfacción y garantías de no repetición, en la dimensión que corresponda. Cada una de estas medidas será implementada a favor de la víctima teniendo en cuenta la gravedad y magnitud del hecho victimizante cometido o la gravedad y magnitud de la violación de sus derechos, así como las circunstancias y características del hecho victimizante.\nARTÍCULO 3.- El objeto de esta Ley es:\nI.- Reconocer y garantizar los derechos de las víctimas del delito y de violaciones a sus derechos humanos, en especial el derecho a la asistencia, protección, atención, verdad, justicia, reparación, debida diligencia y todos los demás derechos consagrados en la celebrados y ratificados por el Estado Mexicano, en la Ley General de Víctimas, en la jurídicos que reconozcan derechos humanos;\nLey de Víctimas para el Estado de Baja California. Página 1\nII.- Establecer y coordinar las acciones y medidas necesarias para promover, respetar, proteger, garantizar y permitir el ejercicio efectivo de los derechos de las víctimas; municipales, en el ámbito de sus respectivas competencias cumplan con sus obligaciones de prevenir, investigar, sancionar y lograr la reparación;\nIII.- Garantizar un efectivo ejercicio del derecho de las víctimas a la justicia en estricto cumplimiento de las reglas del debido proceso;\nIV.- Establecer los deberes y obligaciones específicos a cargo de las autoridades estatales y municipales y de todo aquel que intervenga en los procedimientos relacionados con las víctimas, y\nV.- Establecer las sanciones respecto al incumplimiento por acción o por omisión de cualquiera de sus disposiciones.\nARTÍCULO 4.- Esta Ley se interpretará de conformidad con la Constitución Federal, los Tratados Internacionales celebrados y ratificados por el Estado Mexicano y la Ley\nGeneral, favoreciendo en todo tiempo la protección más amplia de los derechos de las personas.\nCAPÍTULO II\nCONCEPTO, PRINCIPIOS Y DEFINICIONES\nARTÍCULO 5.- Conforme a lo dispuesto en la Ley General, se denominarán víctimas directas aquellas personas físicas que hayan sufrido algún daño o menoscabo económico, físico, mental, o en general cualquiera puesta en peligro o lesión a sus bienes jurídicos o derechos como consecuencia de la comisión de un delito o violaciones a sus derechos humanos reconocidos en la Constitución Federal y en los Tratados Internacionales celebrados y ratificados por el Estado Mexicano. víctima directa que tengan una relación inmediata con ella. derechos o la comisión de un delito. derechos, en los términos establecidos en la Ley General, con independencia de que se identifique, aprehenda, o condene al responsable del daño o de que la víctima participe en algún procedimiento judicial o administrativo.\nLey de Víctimas para el Estado de Baja California. Página 2\nAsí mismo, son víctimas los grupos, comunidades u organizaciones sociales que hubieran sido afectadas en sus derechos, intereses o bienes jurídicos, materia de la presente Ley.\nARTÍCULO 6.- Los mecanismos, medidas y procedimientos establecidos en esta\nLey, serán diseñados, implementados y evaluados aplicando los siguientes principios:\nI.- Buena fe. - Se presumirá la buena fe de las víctimas. Los servidores públicos que intervengan con motivo del ejercicio de derechos de las víctimas no deberán criminalizarla o responsabilizarla por su situación de víctima y deberán brindarle los servicios de ayuda, atención y asistencia desde el momento en que lo requiera, así como respetar y permitir el ejercicio efectivo de sus derechos.\nII.- Complementariedad. - Los mecanismos, medidas y procedimientos contemplados en esta Ley, en especial los relacionados con la de asistencia, ayuda, protección, atención y reparación a las víctimas, deberán realizarse de manera armónica, eficaz y eficiente entendiéndose siempre como complementarias y no excluyentes.\nLas reparaciones que deriven de esta Ley deben ser complementarias para alcanzar la integralidad que busca la reparación de la víctima.\nIII.- Debida diligencia. - El Estado deberá realizar todas las actuaciones necesarias dentro de un tiempo razonable para lograr el objeto de esta Ley, en especial la prevención, ayuda, atención, asistencia, derecho a la verdad, justicia y reparación a fin de que la víctima sea tratada y considerada como sujeto titular de derecho.\nEl Estado deberá remover los obstáculos que impidan el acceso real y efectivo de las víctimas a las medidas reguladas por esta Ley y por la presente Ley, y realizar prioritariamente acciones encaminadas al fortalecimiento de sus derechos, contribuir a su recuperación como sujetos en ejercicio pleno de sus derechos y deberes, así como evaluar permanentemente el impacto de las acciones que se implementen a favor de las víctimas.\nIV.- Dignidad. - La dignidad humana es un valor, principio y derecho fundamental base y condición de todos los demás, sin importar edad, etapa de desarrollo, lugar de residencia, capacidad física e intelectual. Implica la comprensión de la persona como titular y los particulares.\nEn virtud de la dignidad humana de la víctima, todas las autoridades del Estado están obligadas en todo momento a respetar su autonomía, a considerarla y tratarla como fin de su actuación. Igualmente, todas las autoridades del Estado están obligadas a garantizar que no se vea disminuido el mínimo existencial al que la víctima tiene derecho, ni sea afectado el núcleo esencial de sus derechos.\nLey de Víctimas para el Estado de Baja California. Página 3\nEn cualquier caso, toda norma, institución o acto que se desprenda de la presente\nConstitución y los Tratados Internacionales celebrados y ratificados por el Estado Mexicano, aplicando siempre la norma más benéfica para la persona.\nV.- Enfoque diferencial y especializado. - Esta Ley reconoce la existencia de grupos de población con características particulares o con mayor situación de vulnerabilidad, en consecuencia, se reconoce que ciertos daños requieren de una atención especializada que responda a las particularidades y grado de vulnerabilidad de las víctimas.\nLas autoridades estatales y municipales que deban aplicar esta Ley ofrecerán garantías especiales y medidas de protección a los grupos expuestos a un mayor riesgo de violación de sus derechos, como niñas y niños, jóvenes, mujeres, adultos mayores, personas en situación de discapacidad, migrantes, miembros de pueblos indígenas, periodistas y personas en situación de desplazamiento interno. En todo momento se reconocerá el interés superior del menor.\nEste principio incluye la adopción de medidas que respondan a la atención de dichas particularidades y grado de vulnerabilidad, reconociendo igualmente que ciertos daños sufridos por su gravedad requieren de un tratamiento especializado para dar respuesta a su rehabilitación y reintegración a la sociedad.\nVI.- Enfoque transformador. - Las autoridades que deban aplicar la presente Ley realizarán, los esfuerzos necesarios encaminados a que las medidas de ayuda, protección, atención, asistencia y reparación a las que tienen derecho las víctimas contribuyan a la eliminación de los esquemas de discriminación y marginación que pudieron ser la causa de los hechos victimizantes.\nVII.- Gratuidad. - Todas las acciones, mecanismos, procedimientos y cualquier otro trámite que implique el derecho de acceso a la justicia y demás derechos reconocidos en esta Ley, serán gratuitos para la víctima.\nVIII.- Igualdad y no discriminación.- En el ejercicio de los derechos y garantías de las víctimas y en todos los procedimientos a los que se refiere la presente Ley, las autoridades se conducirán sin distinción, exclusión o restricción, ejercida por razón de sexo, raza, color, orígenes étnicos, sociales, nacionales, lengua, religión, opiniones políticas, ideológicas, sin importar edad, etapa de desarrollo, lugar de residencia, capacidad física e intelectual o de cualquier otro tipo, edad, estado civil, condiciones de salud, patrimonio y personas. Toda garantía o mecanismo especial deberá fundarse en razones de enfoque diferencial.\nLey de Víctimas para el Estado de Baja California. Página 4\nIX.- Interés superior de la niñez. - El interés superior de la niñez deberá ser involucre niñas, niños y adolescentes. Cuando se presenten diferentes interpretaciones, se elegirá la que satisfaga de manera más efectiva este principio rector.\nCuando se tome una decisión que afecte a niñas, niños y adolescentes, en lo individual o colectivo, se deberán evaluar y ponderar las posibles repercusiones a fin de salvaguardar su interés superior y sus garantías procesales.\nX.- Indivisibilidad e interdependencia. - Todos los derechos contemplados en esta\nLey se encuentran interrelacionados entre sí. No se puede garantizar el goce y ejercicio de los mismos sin que a la vez se garantice el resto de los derechos. La violación de un derecho pondrá en riesgo el ejercicio de otros.\nPara garantizar la asistencia, atención, ayuda y reparación del daño a las víctimas se realizará de forma multidisciplinaria y especializada.\nXI.- Máxima protección. - Toda autoridad estatal y municipal debe velar por la aplicación más amplia de medidas de protección a la dignidad, libertad, seguridad y demás derechos de las víctimas del delito y de violaciones a los derechos humanos.\nLas autoridades adoptarán en todo momento, medidas para garantizar la seguridad, protección, bienestar físico y psicológico e intimidad de las víctimas.\nXII.- Mínimo existencial. - Constituye una garantía fundada en la dignidad humana como presupuesto del Estado democrático y consiste en la obligación del Estado de proporcionar a la víctima y a su núcleo familiar un lugar en el que se les preste la atención adecuada para que superen su condición y se asegure su subsistencia con la debida dignidad que debe ser reconocida a las personas en cada momento de su existencia.\nXIII.- No criminalización. - Las autoridades no deberán agravar el sufrimiento de la hechos que denuncie. víctimas al crimen organizado o su vinculación con alguna actividad delictiva.\nXIV.- Participación conjunta. - Para superar la vulnerabilidad de las víctimas, el\nEstado deberá implementar medidas de ayuda, atención, asistencia y reparación con el apoyo y colaboración de la sociedad civil y el sector privado.\nLey de Víctimas para el Estado de Baja California. Página 5 lograr superar su condición de vulnerabilidad, atendiendo al contexto, siempre y cuando las medidas no impliquen un detrimento a sus derechos.\nXV.- Progresividad y no regresividad. - Las autoridades que deben aplicar la los derechos reconocidos en la misma y no podrán retroceder o supeditar los derechos, estándares o niveles de cumplimiento alcanzados.\nXVI.- Publicidad. - Todas las acciones, mecanismos y procedimientos deberán ser públicos, siempre que esto no vulnere los derechos humanos de las víctimas o las garantías para su protección.\nEl Estado deberá implementar mecanismos de difusión eficaces a fin de brindar información y orientación a las víctimas acerca de los derechos, garantías y recursos, así como acciones, mecanismos y procedimientos con los que cuenta, los cuales deberán ser dirigidos a las víctimas y publicitarse de forma clara\nXVII.- Rendición de cuentas. - Las autoridades y funcionarios encargados de la implementación de la Ley, así como de los programas que esta Ley regula, estarán sujetos a mecanismos efectivos de rendición de cuentas y de evaluación que contemplen la participación de la sociedad civil, particularmente de víctimas y organizaciones civiles en la materia.\nXVIII.- Transparencia. - Todas las acciones, mecanismos y procedimientos que lleve a cabo el Estado en ejercicio de sus obligaciones para con las víctimas, deberán instrumentarse de manera que garanticen el acceso a la información, así como el seguimiento y control correspondientes.\nLas autoridades deberán contar con mecanismos efectivos de rendición de cuentas derechos de las víctimas.\nXIX.- Trato preferente. - Todas las autoridades en el ámbito de sus competencias tienen la obligación de garantizar el trato digno y preferente a las víctimas, y\nXX.- Victimización secundaria. - Las características y condiciones particulares de la víctima no podrán ser motivo para negarle su calidad. El Estado tampoco podrá exigir por la conducta de los servidores públicos.\nLey de Víctimas para el Estado de Baja California. Página 6\nARTÍCULO 7.- Para los efectos de esta Ley, se estará a las definiciones de conceptos que se contienen en la Ley General, así como las siguientes:\nI.- Asesor Jurídico: Asesor Jurídico de Atención a Víctimas en el Estado de Baja\nCalifornia;\nII.-Asesoría Jurídica: Asesoría Jurídica Estatal de Atención a Víctimas;\nIII.-Comisión Ejecutiva Estatal: Comisión Ejecutiva Estatal de Atención Integral a\nVíctimas;\nIV.- Compensación: Erogación económica a que la víctima tenga derecho en los términos de esta Ley;\nV.- Daño: Muerte o lesiones corporales, daños o perjuicios morales y materiales, salvo a los bienes de propiedad de la persona responsable de los daños; pérdidas de ingresos directamente derivadas de un interés económico; pérdidas de ingresos directamente derivadas del uso del medio ambiente incurridas como resultado de un deterioro significativo del medio ambiente, teniendo en cuenta los ahorros y los costos; costo de las medidas de restablecimiento, limitado al costo de las medidas efectivamente adoptadas o que vayan a adoptarse; y costo de las medidas preventivas, incluidas cualesquiera pérdidas o daños causados por esas medidas, en la medida en que los daños deriven o resulten;\nVI.- Delito: Acto u omisión que sancionan las leyes penales;\nVII.- Fondo Estatal: Fondo Estatal de Ayuda, Asistencia y Reparación Integral;\nVIII.- Hecho victimizante: Actos u omisiones que dañan, menoscaban o ponen en peligro los bienes jurídicos o derechos de una persona convirtiéndola en víctima. Éstos\nIX.-Ley General: Ley General de Víctimas;\nX.- Ley: Ley de Atención a Víctimas para el Estado de Baja California;\nXI.- Programa Estatal: Programa Estatal de Atención Integral a Víctimas;\nXII.- Registro Estatal: Registro Estatal de Víctimas;\nCalifornia;\nLey de Víctimas para el Estado de Baja California. Página 7\nXIV.- Sistema Estatal: Sistema Estatal de Atención a Víctimas;\nXV.- Víctima directa: persona física que haya sufrido algún daño o menoscabo económico, físico, mental, emocional, o en general cualquiera puesta en peligro o lesión a sus bienes jurídicos o derechos como consecuencia de la comisión de un delito, o por la estatales o por violaciones a sus derechos humanos reconocidos en la Constitución cometidos por servidor público en el ejercicio de sus funciones o atribuciones o un particular que ejerza funciones públicas y en los Tratados Internacionales celebrados y ratificados por el Estado Mexicano, también lo son los grupos, comunidades u organizaciones sociales que hubieran sido afectadas en sus derechos, intereses o bienes jurídicos colectivos como resultado de la comisión de un delito o la violación de derechos;\nXVI.- Víctima indirecta: los familiares o aquellas personas físicas a cargo de la víctima directa que tengan una relación inmediata con ella;\nXVII.- Víctima potencial: Las personas físicas cuya integridad física o derechos peligren por prestar asistencia a la víctima ya sea por impedir o detener la violación de derechos o la comisión de un delito, y\nXVIII.- Violación de derechos humanos: Todo acto u omisión que afecte los derechos humanos reconocidos en la Constitución o en los Tratados Internacionales celebrados y ratificados por el Estado Mexicano, cuando el agente sea servidor público en el ejercicio de sus funciones o atribuciones o un particular que ejerza funciones públicas.\nTambién se considera violación de derechos humanos cuando la acción u omisión referida sea realizada por un particular instigado o autorizado, explícita o implícitamente por un servidor público, o cuando actúe con aquiescencia o colaboración de un servidor público.\nTÍTULO SEGUNDO\nDE LOS DERECHOS DE LAS VÍCTIMAS\nCAPÍTULO I\nARTÍCULO 8.- Conforme a la presente Ley y la Ley General, las víctimas tendrán, entre otros, los siguientes derechos:\nI.- A una investigación pronta y eficaz que lleve, en su caso, a la identificación y humanos, y a su reparación;\nLey de Víctimas para el Estado de Baja California. Página 8\nII.- A ser reparadas por el Estado de manera integral, adecuada, y efectiva por el derechos humanos y por los daños que esas violaciones les causaron;\nIII.- A conocer la verdad de lo ocurrido acerca de los hechos en que le fueron violados sus derechos humanos a que se refiere la fracción VIII del artículo 7 de esta Ley para lo cual la autoridad deberá informar los resultados de las investigaciones;\nIV.- A qué se le brinde protección y se salvaguarde su vida y su integridad corporal, en tratándose de la comisión de delitos en materia de delincuencia organizada.\nV.- A ser tratadas con humanidad y respeto de su dignidad y sus derechos humanos por parte de los servidores públicos y, en general, por el personal de las instituciones públicas responsables del cumplimiento de esta Ley, así como por parte de los particulares que cuenten con convenios para brindar servicios a las víctimas;\nVI.- A solicitar y a recibir ayuda, asistencia y atención en forma oportuna, rápida, equitativa, gratuita y efectiva por personal especializado en atención al daño sufrido desde la comisión del hecho victimizante, con independencia del lugar en donde ella se encuentre, así como a que esa ayuda, asistencia y atención no dé lugar, en ningún caso, a una nueva afectación;\nVII.- A la verdad, a la justicia y a la reparación a través de recursos y procedimientos accesibles, apropiados, suficientes, rápidos y eficaces;\nVIII.- A la protección del Estado, incluido el bienestar físico y psicológico y la seguridad del entorno con respeto a la dignidad y privacidad de la víctima, con independencia de que se encuentren dentro un procedimiento penal o de cualquier otra índole. Lo anterior incluye el derecho a la protección de su intimidad contra injerencias ilegítimas, así como derecho a contar con medidas de protección eficaces cuando su vida o integridad personal o libertad personal sean amenazadas o se hallen en riesgo en razón de su condición de víctima y/o del ejercicio de sus derechos; medios de acceso a los procedimientos, mecanismos y medidas que se establecen en la presente Ley;\nX.- A solicitar, acceder y recibir, en forma clara y precisa, toda la información oficial necesaria para lograr el pleno ejercicio de cada uno de sus derechos;\nXI.- A obtener en forma oportuna, rápida y efectiva todos los documentos que requiera para el ejercicio de sus derechos, entre éstos, los documentos de identificación y las visas;\nLey de Víctimas para el Estado de Baja California. Página 9\nXII.- A conocer el estado de los procesos judiciales y administrativos en los que tenga un interés como interviniente;\nXIII.- A ser efectivamente escuchada por la autoridad respectiva cuando se encuentre presente en la audiencia, diligencia o en cualquier otra actuación y antes de que la autoridad se pronuncie;\nXIV.- A ser notificada de las resoluciones relativas a las solicitudes de ingreso al\nRegistro Estatal y de medidas de ayuda, de asistencia y reparación que se dicten;\nXV.- A que el consulado de su país de origen sea inmediatamente notificado conforme a las normas internacionales que protegen el derecho a la asistencia consular, cuando se trate de víctimas extranjeras;\nXVI.- A la reunificación familiar cuando por razón del tipo de victimización su núcleo familiar se haya dividido;\nXVII.- A retornar a su lugar de origen o a reubicarse en condiciones de voluntariedad, seguridad y dignidad;\nXVIII.- A acudir y a participar en escenarios de diálogo institucional;\nXIX.- A ser beneficiaria de las acciones afirmativas y programas sociales públicos para proteger y garantizar sus derechos;\nXX.- A participar en la formulación, implementación y seguimiento de la política pública de prevención, ayuda, atención, asistencia y reparación;\nXXI.- A que las políticas públicas que son implementadas con base en la presente\nLey tengan un enfoque transversal, particularmente en atención a la infancia, los adultos mayores y población indígena;\nXXII.- A no ser discriminadas ni limitadas en sus derechos;\nXXIII.- A recibir tratamiento especializado que le permita su rehabilitación física y psicológica con la finalidad de lograr su reintegración a la sociedad;\nXXIV.- A acceder a los mecanismos de justicia disponibles para determinar la responsabilidad en la comisión del delito o de la violación de los derechos humanos;\nXXV.- A tomar decisiones informadas sobre las vías de acceso a la justicia o mecanismos alternativos;\nLey de Víctimas para el Estado de Baja California. Página 10\nXXVI.- A una investigación pronta y efectiva que lleve a la identificación, captura, procesamiento y sanción de manera adecuada de todos los responsables del daño, al\nXXVII.- A participar activamente en la búsqueda de la verdad de los hechos y en los mecanismos de acceso a la justicia que estén a su disposición, conforme a los procedimientos establecidos en la ley de la materia;\nXXVIII.- A expresar libremente sus opiniones e intereses ante las autoridades e instancias correspondientes y a que éstas, en su caso, sean consideradas en las decisiones que afecten sus intereses;\nXXIX.- Derecho a ejercer los recursos legales en contra de las decisiones que afecten sus intereses y el ejercicio de sus derechos;\nXXX.- A que se les otorgue, en los casos que procedan, la ayuda provisional;\nXXXI.- A recibir gratuitamente la asistencia de un intérprete o traductor de su lengua, en caso de que no comprendan el idioma español o tenga discapacidad auditiva, verbal o visual;\nXXXII.- A trabajar con otras víctimas para la defensa de sus derechos, incluida su reincorporación a la sociedad;\nXXXIII.- A participar en espacios donde se proporcione apoyo individual o colectivo que le permita relacionarse con otras víctimas,\nXXXIV.- Toda comparecencia ante el órgano investigador, el juez o tribunal, organismo público de protección de los derechos humanos, o ante cualquiera otra autoridad o perito que requiera la presencia de la Víctima, se considerará justificada para los efectos laborales y escolares, teniendo ella derecho a gozar del total de los emolumentos a que se refiere la Ley Federal del Trabajo; y\nXXXV.- Los demás señalados por la Constitución Federal, los Tratados\nInternacionales celebrados y ratificados por el Estado Mexicano, la Ley General y cualquier otra disposición aplicable en la materia o legislación especial.\nCAPÍTULO II\nDE LOS DERECHOS DE AYUDA, ASISTENCIA Y ATENCIÓN\nLey de Víctimas para el Estado de Baja California. Página 11\nARTÍCULO 9.- Las víctimas recibirán ayuda provisional, oportuna y rápida de para atender y garantizar la satisfacción de sus necesidades de alimentación, aseo personal, manejo de abastecimientos, atención médica y psicológica de emergencia, transporte de emergencia y alojamiento transitorio en condiciones dignas y seguras, a partir del momento de la comisión del delito o de la violación de los derechos o en el momento en el que las autoridades tengan conocimiento del delito o de la violación de derechos. Las medidas de ayuda provisional se brindarán garantizando siempre un enfoque transversal de género y diferencial, y durante el tiempo que sea necesario para garantizar que la víctima supere las condiciones de necesidad inmediata.\nLas víctimas de delitos o de violaciones de derechos contra la libertad y la integridad, recibirán ayuda médica y psicológica especializada de emergencia en los términos de la presente Ley.\nLos servidores públicos deberán brindar información clara, precisa y accesible a las víctimas y sus familiares, sobre cada una de las garantías, mecanismos y procedimientos que permiten el acceso oportuno, rápido y efectivo a las medidas de ayuda contempladas en la presente Ley.\nLas medidas de ayuda, asistencia, atención y demás establecidas en la Ley General, se brindarán exclusivamente por las instituciones públicas el gobierno Federal, de las entidades federativas, de la Ciudad de México y municipios, a través de los programas, mecanismos y servicios con que cuenten, salvo en los casos urgentes o de extrema necesidad en los que se podrá recurrir a instituciones privadas.\nPárrafo Reformado\nLa Comisión Ejecutiva Estatal, en el ámbito de su competencia, deberá otorgar, con cargo al Fondo Estatal, los Recursos de Ayuda que requiera la víctima para garantizar que supere las condiciones de necesidad que tengan relación con el hecho victimizante. La\nComisión Ejecutiva Estatal requerirá a la víctima en un plazo de treinta días, los comprobantes del gasto que se hayan generado con motivo del otorgamiento de dichas medidas.\nLas y los menores, personas con discapacidad, y mayores de edad quienes género, recibirá ayuda psicológica especializada de emergencia en los términos de la presente Ley.\nPárrafo Adicionado ayuda inmediata, la Comisión Ejecutiva Estatal deberá solicitarlos a la Comisión Ejecutiva, conforme a lo previsto en el artículo 8 de la Ley General.\nArtículo Reformado\nLey de Víctimas para el Estado de Baja California. Página 12 través del conjunto integrado de mecanismos, procedimientos, programas, medidas y recursos de orden político, económico, social, cultural, entre otros, a cargo del Estado. Entre estas medidas, las víctimas contarán con asistencia médica especializada incluyendo la psiquiátrica, psicológica, traumatológica y tanatológica.\nEl costo o las erogaciones en que incurra el Estado en la prestación de los servicios de atención y asistencia, en ningún caso serán descontados de la compensación a que tuvieran derecho las víctimas.\nCAPÍTULO III\nDEL DERECHO DE ACCESO A LA JUSTICIA\nARTÍCULO 11.- Las víctimas tienen derecho a un recurso judicial adecuado y efectivo, ante las autoridades independientes, imparciales y competentes, que les garantice el ejercicio de su derecho a conocer la verdad, a que se realice con la debida diligencia una investigación inmediata y exhaustiva del delito o de las violaciones de derechos humanos sufridas por ellas; a que los autores de los delitos y de las violaciones de derechos, con el respeto al debido proceso, sean enjuiciados y sancionados; y a obtener una reparación por los daños sufridos.\nLas víctimas tendrán acceso a los mecanismos de justicia de los cuales disponga el\nEstado, incluidos los procedimientos judiciales y administrativos. La legislación en la materia que regule su intervención en los diferentes procedimientos deberá facilitar su participación.\nCAPÍTULO IV\nDE LOS DERECHOS DE LAS VÍCTIMAS EN EL PROCESO PENAL\nARTÍCULO 12.- Las víctimas gozarán de los siguientes derechos:\nI.- A ser informadas de manera clara, precisa y accesible de sus derechos por el\nMinisterio Público o la primera autoridad con la que tenga contacto o que conozca del hecho delictivo, tan pronto éste ocurra;\nII.- A que se les repare el daño en forma expedita, proporcional y justa. En los casos responsable de dicha reparación. Si la víctima o su Asesor Jurídico no solicitaran la reparación del daño, el Ministerio Público está obligado a hacerlo;\nIII.- A coadyuvar con el Ministerio Público; a que se les reciban todos los datos o elementos de prueba con los que cuenten, tanto en la investigación como en el proceso, a que se desahoguen las diligencias correspondientes, y a intervenir en el juicio como partes\nLey de Víctimas para el Estado de Baja California. Página 13 menores a los del imputado. Asimismo, tendrán derecho a que se les otorguen todas las facilidades para la presentación de denuncias o querellas;\nIV.- A ser asesoradas y representadas dentro de la investigación y el proceso por un\nAsesor Jurídico. En los casos en que no quieran o no puedan contratar un abogado, les será proporcionado por el Estado, de acuerdo al procedimiento que determine esta Ley y su\nReglamento.\nV.- A impugnar ante la autoridad judicial las omisiones del Ministerio Público en la investigación de los delitos, así como las resoluciones de reserva, no ejercicio, desistimiento de la acción penal o suspensión del procedimiento, con independencia de que se haya reparado o no el daño;\nVI.- A comparecer en la fase de la investigación o al juicio y a que sean adoptadas medidas para minimizar las molestias causadas, proteger su intimidad, identidad y otros datos personales;\nVII.- A que se garantice su seguridad, así como la de sus familiares y la de los testigos en su favor contra todo acto de amenaza, intimidación o represalia;\nVIII.- A rendir o ampliar sus declaraciones sin ser identificados dentro de la audiencia, teniendo la obligación el juez de resguardar sus datos personales y, si lo solicitan, hacerlo por medios electrónicos;\nIX.- A obtener copia simple gratuita y de inmediato de las diligencias en las que intervengan;\nX.- A solicitar medidas precautorias o cautelares para la seguridad y protección de las víctimas, ofendidos y testigos de cargo, para la investigación y persecución de los probables responsables del delito y para el aseguramiento de bienes para la reparación del daño;\nXI.- A que se les informe sobre la realización de las audiencias donde se vaya a\nXII.- A que se les notifique toda resolución que pueda afectar sus derechos y a impugnar dicha resolución, y\nXIII.- En los casos que impliquen graves violaciones a los derechos humanos, a solicitar la intervención de expertos independientes, a fin de que colaboren con las autoridades competentes en la investigación de los hechos y la realización de peritajes.\nLa Comisión Ejecutiva Estatal, podrá cubrir los gastos que se originen con motivo de\nLey de Víctimas para el Estado de Baja California. Página 14 la contratación de expertos independientes o peritos a que se refiere el párrafo anterior, con cargo al Fondo estatal. internacionales, cuando no se cuente con personal nacional capacitado en la materia.\nARTÍCULO 13.- Cuando el imputado se sustraiga de la acción de la justicia, deje de presentarse ante la autoridad jurisdiccional competente que conozca de su caso los días que se hubieran señalado para tal efecto u omita comunicar a la autoridad jurisdiccional competente los cambios de domicilio que tuviere o se ausentase del lugar del juicio de autorización de la autoridad jurisdiccional competente, esta última ordenará, sin demora alguna, que entregue la suma que garantiza la reparación a la víctima, dejando constancia en el expediente del pago definitivo de la cantidad depositada, lo que no implica que se haya efectuado la reparación correspondiente.\nEn los casos en que la garantía fuese hecha por hipoteca o prenda, la autoridad jurisdiccional competente remitirá dichos bienes a la autoridad fiscal correspondiente para su cobro, el cual deberá entregarse sin dilación a la víctima. En los mismos términos los fiadores están obligados a pagar en forma inmediata la reparación del daño, aplicándose para su cobro, en todo caso, el procedimiento económico coactivo que las leyes fiscales señalen.\nARTÍCULO 14.- Las víctimas tienen derecho a intervenir en el proceso penal y deberán ser reconocidas como sujetos procesales en el mismo, pero si no se apersonaran en el mismo, serán representadas por un Asesor Jurídico o en su caso por el Ministerio\nPúblico, y serán notificadas personalmente de todos los actos y resoluciones que pongan fin al proceso, de los recursos interpuestos ya sean ordinarios o extraordinarios, así como de las modificaciones en las medidas cautelares que se hayan adoptado por la existencia de un riesgo para su seguridad, vida o integridad física o modificaciones a la sentencia.\nARTÍCULO 15.- Las víctimas tienen derecho a que se les explique el alcance y naturaleza del caso, y en caso de aceptar su realización a ser acompañadas en todo momento por su Asesor Jurídico o la persona que consideren.\nARTÍCULO 16.- Toda comparecencia ante el órgano investigador, el juez o tribunal, o ante cualquiera otra autoridad o perito que requiera la presencia de la víctima, se considerará justificada para los efectos laborales y escolares, teniendo ella derecho a gozar del total de los emolumentos correspondientes.\nARTÍCULO 17.- Las víctimas tendrán derecho a optar por la solución de conflictos conforme a las reglas de la justicia alternativa, a través de instituciones como la conciliación\nLey de Víctimas para el Estado de Baja California. Página 15 y la mediación, a fin de facilitar la reparación del daño y la reconciliación de las partes y las medidas de no repetición. través de los medios idóneos, que la víctima está en condiciones de tomar esa decisión. El optado por alguna de las vías de solución alterna de conflictos, notificando en todo caso a las instancias de protección a la mujer a fin de que se cercioren que la víctima tuvo la asesoría requerida para la toma de dicha decisión. Se sancionará a los servidores públicos que conduzcan a las víctimas a tomar estas decisiones sin que éstas estén conscientes de las consecuencias que conlleva.\nCAPÍTULO V\nDEL DERECHO A LA VERDAD\nARTÍCULO 18.- Las víctimas y la sociedad en general tienen el derecho imprescriptible de conocer los hechos constitutivos del delito y de las violaciones a derechos humanos de que fueron objeto, la identidad de los responsables, las circunstancias que hayan propiciado su comisión, así como tener acceso a la justicia en condiciones de igualdad.\nARTÍCULO 19.- Las víctimas tienen el derecho imprescriptible a conocer la verdad y a recibir información específica sobre las violaciones de derechos o los delitos que las afectaron directamente, incluidas las circunstancias en que ocurrieron los hechos y, en los casos de personas desaparecidas, ausentes, no localizadas, extraviadas o fallecidas, a conocer su destino o paradero o el de sus restos.\nToda víctima que haya sido reportada como desaparecida tiene derecho a que las autoridades competentes inicien de manera eficaz y urgente las acciones para lograr su localización y, en su caso, su oportuno rescate.\nARTÍCULO 20.- Las víctimas y la sociedad tienen derecho a conocer la verdad histórica de los hechos. afectados. Las víctimas deberán decidir libremente su participación y tener la información suficiente sobre las implicaciones de cada uno de estos mecanismos. de las víctimas de hechos históricos locales, proveyendo en términos de la legislación aplicable, la información o expedientes que se encuentren en sus archivos, cuando con fines\nLey de Víctimas para el Estado de Baja California. Página 16 reconstruir la verdad histórica las víctimas o titulares de ese derecho lo soliciten. El ejercicio víctimas o terceras personas, por lo que será necesario que otorguen el consentimiento para su difusión en los términos de la Ley de la materia.\nARTÍCULO 21.- El Estado, a través de las autoridades respectivas, tiene la obligación de iniciar, de inmediato y tan pronto como se haga de su conocimiento, todas las diligencias a su alcance para determinar el paradero de las personas desaparecidas. Toda víctima de desaparición tiene derecho a que las autoridades desplieguen las acciones pertinentes para su protección con el objetivo de preservar, al máximo posible, su vida y su integridad física y psicológica.\nEsta obligación, incluye la realización de las exhumaciones de cementerios, fosas clandestinas o de otros sitios en los que se encuentren o se tengan razones fundadas para creer que se encuentran cuerpos u osamentas de las víctimas. Las exhumaciones deberán realizarse con la debida diligencia y competencia y conforme a las normas y protocolos internacionales sobre la materia, buscando garantizar siempre la correcta ubicación, recuperación y posterior identificación de los cuerpos u osamentas bajo estándares científicos reconocidos internacionalmente.\nLos familiares de las víctimas tienen el derecho a estar presentes en las exhumaciones, por sí y/o a través de sus asesores jurídicos; a ser informadas sobre los protocolos y procedimientos que serán aplicados; y a designar peritos independientes, acreditados ante organismo nacional o internacional de protección a los derechos humanos, que contribuyan al mejor desarrollo de las mismas.\nLa Comisión Ejecutiva podrá cubrir los costos de los exámenes a que se refiere el párrafo anterior, con cargo al Fondo Estatal.\nUna vez plenamente identificados y realizadas las pruebas técnicas y científicas a las que está obligado el Estado y que han sido referidas en esta Ley, en el Código Nacional de Procedimientos Penales y la legislación aplicable, la entrega de los cuerpos u osamentas de las víctimas a sus familiares, deberá hacerse respetando plenamente su dignidad y sus tradiciones religiosas y culturales.\nEn caso necesario, a efecto de garantizar las investigaciones, la autoridad deberá notificar a los familiares la obligación de no cremar los restos, hasta en tanto haya una sentencia ejecutoriada. Las autoridades ministeriales tampoco podrán autorizar ni procesar ninguna solicitud de gobierno extranjero para la cremación de cadáveres, identificados o sin identificar, hasta en tanto no haya sentencia ejecutoriada.\nLey de Víctimas para el Estado de Baja California. Página 17\nCon independencia de los derechos previstos en esta Ley, el reconocimiento de la desaparición se sujetarán a lo que dispongan las leyes en la materia, a fin de que las ausente para salvaguardar los intereses esenciales del núcleo familiar.\nARTÍCULO 22.- Para garantizar el ejercicio pleno de este derecho de las víctimas, sus familiares y la sociedad, el Estado podrá generar mecanismos para la investigación independiente, imparcial y competente, que cumpla, entre otros, con los siguientes objetivos:\nI.- El esclarecimiento histórico preciso de las violaciones de derechos humanos, la dignificación de las víctimas;\nII.- La determinación de la responsabilidad individual o institucional de los hechos;\nIII.- La contribución a la superación de la impunidad mediante la recomendación de formulación de políticas de investigación, y\nIV.- La recomendación de las reparaciones, reformas institucionales y otras políticas necesarias para superar las condiciones que facilitaron o permitieron las violaciones de derechos.\nPara el cumplimiento de estos objetivos, deberán realizarse consultas que incluyan la participación y la opinión de las víctimas, grupos de víctimas y de sus familiares.\nARTÍCULO 23.- Las organizaciones de la sociedad civil, tales como asociaciones profesionales, organizaciones no gubernamentales e instituciones académicas, deberán proporcionar a la autoridad competente, los resultados que arrojen sus investigaciones de violaciones a los derechos humanos, con el fin de contribuir con la búsqueda y conocimiento de la verdad. Las autoridades competentes deberán dar las garantías necesarias para que esta actividad se pueda realizar de forma libre e independiente.\nARTÍCULO 24.- Toda persona tendrá derecho a saber si sus datos personales se encuentran en los archivos estatales y, en ese caso, después de ejercer su derecho de consulta, a impugnar la legitimidad de las informaciones y contenidos que le conciernan ejerciendo el derecho que corresponda. La autoridad garantizará que el documento solicite el primero. Para casos de personas fallecidas, este derecho podrá ser ejercido por aplicable.\nLey de Víctimas para el Estado de Baja California. Página 18\nCAPÍTULO VI\nDEL DERECHO A LA REPARACIÓN\nARTÍCULO 25.- Las víctimas tienen derecho a ser reparadas por el daño que han violaciones de derechos humanos que han sufrido, conforme a lo previsto en esta Ley y su\nReglamento.\nARTÍCULO 26.- De conformidad con lo dispuesto en la presente Ley, la reparación busca devolver a la víctima a la situación anterior a la comisión del delito o a la violación de sus derechos.\nARTÍCULO 27.- Para los efectos de la presente Ley, la reparación integral comprenderá:\nI.- La restitución busca devolver a la víctima a la situación anterior a la comisión del delito o a la violación de sus derechos humanos;\nII.- La rehabilitación busca facilitar a la víctima hacer frente a los efectos sufridos por causa del hecho punible o de las violaciones de derechos humanos;\nIII.- La compensación ha de otorgarse a la víctima de forma apropiada y proporcional a la gravedad del hecho punible cometido o de la violación de derechos humanos sufrida y teniendo en cuenta las circunstancias de cada caso. Ésta se otorgará por todos los perjuicios, sufrimientos y pérdidas económicamente evaluables que sean consecuencia del delito o de la violación de derechos humanos;\nIV.- La satisfacción busca reconocer y restablecer la dignidad de las víctimas;\nV.- Las medidas de no repetición buscan que el hecho punible o la violación de derechos sufrida por la víctima no vuelva a ocurrir;\nVI.- Para los efectos de la presente Ley, la reparación colectiva se entenderá como un derecho del que son titulares los grupos, comunidades u organizaciones sociales que hayan colectivos, o cuando el daño comporte un impacto colectivo. La restitución de los derechos reconozca la afectación en la capacidad institucional de garantizar el goce, la protección y la promoción de los derechos en las comunidades, grupos y pueblos afectados. dignificación de los sujetos colectivos victimizados; la reconstrucción del proyecto de vida\nLey de Víctimas para el Estado de Baja California. Página 19 colectivo, y el tejido social y cultural; la recuperación psicosocial de las poblaciones y grupos derechos humanos en las comunidades y colectivos afectados. con cargo al Fondo Estatal.\nTÍTULO TERCERO\nDE LAS MEDIDAS DE AYUDA Y ASESORÍA\nCAPÍTULO I\nMEDIDAS DE AYUDA INMEDIATA\nARTÍCULO 28.- La gravedad del daño sufrido por las víctimas será el eje que determinará prioridad en su asistencia, en la prestación de servicios y en la implementación de acciones dentro de las instituciones encargadas de brindarles atención y tratamiento.\nLos servicios a que se refiere la presente Ley tomarán en cuenta si la víctima pertenece a un grupo en condiciones de vulnerabilidad, sus características y necesidades especiales, particularmente tratándose de los grupos expuestos a un mayor riesgo de violación de sus derechos, como niñas, niños y adolescentes, mujeres, adultos mayores, personas con discapacidad, migrantes, indígenas, personas defensoras de derechos humanos, periodistas y personas en situación de desplazamiento interno.\nARTÍCULO 29.- Las instituciones hospitalarias públicas tienen la obligación de dar atención de emergencia de manera inmediata a las víctimas que lo requieran, con independencia de su capacidad socioeconómica o nacionalidad y sin exigir condición previa para su admisión.\nARTÍCULO 30.- Los servicios de emergencia médica, odontológica, quirúrgica y hospitalaria consistirán en:\nI.- Hospitalización;\nII.- Material médico quirúrgico, incluidas prótesis y demás instrumentos, que la persona requiera para su movilidad, conforme al dictamen dado por el médico especialista en la materia;\nIII.- Medicamentos;\nIV.- Honorarios médicos, en caso de que el sistema de salud más accesible para la víctima no cuente con los servicios que ella requiere de manera inmediata;\nLey de Víctimas para el Estado de Baja California. Página 20\nV.- Servicios de análisis médicos, laboratorios e imágenes diagnósticas;\nVI.- Transporte y ambulancia;\nVII.- Servicios de atención mental en los casos en que, como consecuencia de la comisión del delito o de la violación a sus derechos humanos, la persona quede gravemente afectada psicológica y/o psiquiátricamente;\nFracción Reformada\nVIII.- Servicios odontológicos reconstructivos por los daños causados como consecuencia del delito o la violación a los derechos humanos; y,\nFracción Reformada\nIX.- Brindar a las víctimas de delito de violencia sexual, los servicios de anticoncepción de emergencia y de interrupción legal del embarazo, con absoluto respeto a la voluntad de la víctima, así como de la profilaxis post exposición para Virus de\nInmunodeficiencia Humana, además de aquellos que contemplen y prevean la Ley General y esta Ley, con absoluto respeto a los derechos humanos y a la voluntad de las víctimas; asimismo, se le realizará a la víctima la práctica periódica de exámenes y tratamiento especializado, durante el tiempo necesario para su total recuperación y conforme al diagnóstico y tratamiento médico recomendado; en particular, se considerará prioritario para su tratamiento el seguimiento de eventuales contagios de enfermedades de transmisión sexual y del Virus de Inmunodeficiencia Humana.\nFracción Adicionada\nEn caso de que la institución médica a la que acude o es enviada la víctima no cuente con lo señalado en las fracciones II y III y sus gastos hayan sido cubiertos por la víctima o en el caso de la fracción IV, el Ejecutivo o los municipios, según corresponda, los reembolsarán de manera completa e inmediata, de conformidad con lo que establezcan las normas reglamentarias aplicables.\nArtículo Reformado\nARTÍCULO 31.- El Ejecutivo y los municipios donde se haya cometido el hecho victimizante apoyarán a las víctimas indirectas con los gastos funerarios que deban cubrirse por el fallecimiento de la víctima directa cuando la causa de la muerte sea homicidio. Estos gastos incluirán los de transporte, cuando el fallecimiento se haya producido en un lugar lugar.\nARTÍCULO 32.- El Ejecutivo, a través de sus organismos, dependencias y entidades de salud pública, otorgarán el carnet que identifique a las víctimas ante el sistema de salud, con el fin de garantizar la asistencia y atención urgentes para efectos reparadores. prioridad a las víctimas de daños graves a la salud e integridad personal. No obstante, Ley de Víctimas para el Estado de Baja California. Página 21 ser atendidas de manera prioritaria.\nARTÍCULO 33.- A toda víctima de violación sexual, o cualquier otra conducta que afecte su integridad física o psicológica, se le brindará los servicios de anticoncepción de emergencia y de interrupción legal del embarazo, así como de la profilaxis post exposición para Virus de Inmunodeficiencia Humana, se le realizará con respeto a sus derechos humanos, enfoque transversal de género, diferencial y especializado, que garantice a la víctima superar las secuelas de la victimización; así como la práctica periódica de exámenes y tratamiento especializado, durante el tiempo necesario para su total recuperación y conforme al diagnóstico y tratamiento médico recomendado; en particular, se considerará prioritario para su tratamiento el seguimiento de eventuales contagios de enfermedades de transmisión sexual y del Virus de Inmunodeficiencia Humana.\nPárrafo Reformado\nLas instituciones públicas del Estado que brinden servicios, asistencia y atención a las víctimas, dispondrán de personal capacitado en el tratamiento de la violencia sexual, servicios de anticoncepción de emergencia y de interrupción voluntaria del embarazo de forma gratuita.\nPárrafo Reformado\nArtículo Reformado\nARTÍCULO 34.- El Ejecutivo, a través de sus organismos, dependencias y entidades de salud pública, así como aquellos municipios que cuenten con la infraestructura y la capacidad de prestación de servicios, definirán los procedimientos para garantizar de manera gratuita los servicios de asistencia médica preoperatoria, postoperatoria, quirúrgica, hospitalaria y odontológica a que hubiese lugar de acuerdo al concepto médico y valoración, que permita atender lesiones transitorias y permanentes y las demás afectaciones de la salud física y psicológica que tengan relación causal directa con las conductas.\nARTÍCULO 35.- En caso de que la institución médica a la que acude o es enviada la víctima no cumpla con lo señalado en los artículos anteriores y sus gastos hayan sido cubiertos por la víctima, la autoridad competente se los reembolsará de manera completa y expedita, teniendo dichas autoridades, el derecho de repetir contra los responsables. Las reembolso a que se refiere este artículo.\nCAPÍTULO II\nARTÍCULO 36.- El Sistema para el Desarrollo Integral de la Familia y su correlativo en los municipios, así como las instituciones de las que dependen las casas de refugio y acogida que existan y brinden estos servicios en el ámbito federal, estatal, o municipal, Ley de Víctimas para el Estado de Baja California. Página 22 por causa del delito cometido contra ellas o de la violación de sus derechos humanos. El garantizar que la víctima supere las condiciones de emergencia y pueda retornar libremente en condiciones seguras y dignas a su hogar.\nCAPÍTULO III\nMEDIDAS EN MATERIA DE TRASLADO\nARTÍCULO 37.- Cuando la víctima se encuentre en un lugar distinto al de su lugar de residencia y desee regresar al mismo, las autoridades competentes de los diversos órdenes de gobierno, pagarán los gastos correspondientes, garantizando, en todos los casos, que el medio de transporte usado por la víctima para su regreso es el más seguro y el que le cause menos trauma de acuerdo con sus condiciones.\nEste derecho comprenderá, además, los gastos comprobables de transporte que se le ocasionen a la víctima para trasladarse al lugar del juicio o para asistir a su tratamiento, cuando ésta resida en un lugar distinto al del enjuiciamiento o atención. Las normas reglamentarias aplicables establecerán el procedimiento, requisitos y monto de gasto que podrá ser autorizado.\nLos recursos que se ejerzan por este concepto, se reclamarán al responsable del delito por concepto de reparación del daño.\nCAPÍTULO IV\nMEDIDAS EN MATERIA DE PROTECCIÓN\nARTÍCULO 38.- Cuando la víctima se encuentre amenazada en su integridad personal o en su vida o existan razones fundadas para pensar que estos derechos están en riesgo, en razón del delito o de la violación de derechos humanos sufrida, las autoridades del orden estatal o municipal de acuerdo con sus competencias y capacidades, adoptarán con carácter inmediato, las medidas que sean necesarias para evitar que la víctima sufra alguna lesión o daño. procedimientos previstos en la presente Ley, sin perjuicio de las previstas en otras disposiciones legales, se podrán solicitar y decretar, las siguientes:\nI.- Salvaguarda de la integridad personal en los aspectos físico, psicológico, patrimonial o familiar;\nLey de Víctimas para el Estado de Baja California. Página 23\nII.- Mecanismos para el traslado de la persona protegida;\nIII.- Vigilancia y custodia policial a cargo de las instituciones policiales del Estado o municipios;\nIV.- Uso y entrega de dispositivos de comunicación como mecanismo de alerta a las autoridades en caso de emergencia;\nV.- Auxilio para la reubicación del domicilio personal o del lugar de trabajo o estudios, y\nVI.- Las demás que se consideren necesarias para garantizar la seguridad e integridad de la persona protegida, de conformidad con la valoración de las circunstancias del caso en concreto.\nARTÍCULO 39.- Las medidas de protección a las víctimas se deberán implementar con base en los siguientes principios:\nI.- Principio de protección: Considera primordial la protección de la vida, la integridad física, la libertad y la seguridad de las personas;\nII.- Principio de necesidad y proporcionalidad: Las medidas de protección deben responder al nivel de riesgo o peligro en que se encuentre la persona destinataria, y deben ser aplicadas en cuanto sean necesarias para garantizar su seguridad o reducir los riesgos existentes;\nIII.- Principio de confidencialidad: Toda la información y actividad administrativa o jurisdiccional relacionada con el ámbito de protección de las personas, debe ser reservada para los fines de la investigación o del proceso respectivo, y\nIV.- Principio de oportunidad y eficacia: Las medidas deben ser oportunas, específicas, adecuadas y eficientes para la protección de la víctima y deben ser otorgadas e implementadas a partir del momento y durante el tiempo que garanticen su objetivo.\nV.- Voluntariedad: El interesado deberá expresar su voluntad por escrito de acogerse a las medidas, obligándose a cumplir con todas las disposiciones que se establezcan por la autoridad que las otorgue, pudiendo solicitar en cualquier momento su retiro, y\nVI.- Temporalidad: Las medidas estarán sujetas a un periodo determinado, durante el cual la autoridad realizara la evaluación periódica para determinar si continúan, tomando en cuenta la existencia o no de los factores o circunstancias que motivaron su aplicación.\nLey de Víctimas para el Estado de Baja California. Página 24\nSerán sancionadas administrativa, civil o penalmente, de conformidad con las leyes aplicables, los servidores públicos estatales o municipales que contribuyan a poner en riesgo la seguridad de las víctimas, ya sea a través de intimidación, represalias, amenazas directas, comisión del delito o con un tercero implicado que amenace o dañe la integridad física o moral de una víctima.\nARTICULO 40.- Para determinar la viabilidad y proporcionalidad de las medidas de protección se deberá tomar en cuenta como mínimo lo siguiente:\nI.- La condición de vulnerabilidad de la persona a proteger;\nII.- La situación de riesgo grave o de peligro inminente;\nIII.- La importancia de los hechos que motivan el procedimiento penal;\nIV.- La trascendencia e idoneidad del testimonio y, en general, el rol que desempeñe en el procedimiento la persona a proteger;\nV.- La pertenencia de la persona a un grupo en condición de especial vulnerabilidad;\nVI.- La capacidad y disposición de la persona para adaptarse a la medida de protección;\nVII.- La capacidad de agente generador del riesgo de causar un daño a la persona a proteger;\nVIII.- Las circunstancias propias de los hechos victimizantes, como atentados contra la vida, la integridad, la seguridad o la libertad de las víctimas, independientemente de que se conozca la identidad de los posibles perpetradores, y\nIX.- Las demás circunstancias cuyo análisis se considere necesario para ponderar la necesidad de otorgamiento de la medida.\nCAPÍTULO V\nMEDIDAS EN MATERIA DE ASESORÍA JURÍDICA\nARTÍCULO 41.- Las autoridades estatales y municipales brindarán de inmediato a judiciales, administrativos o de otro tipo a los cuales ellas tienen derecho para la mejor defensa de sus intereses y satisfacción de sus necesidades, así como sobre el conjunto de\nLey de Víctimas para el Estado de Baja California. Página 25 derechos de los que son titulares en su condición de víctima. La Comisión Estatal garantizará lo dispuesto en el presente artículo a través de la Asesoría Jurídica.\nARTÍCULO 42.- La información y asesoría deberán brindarse en forma gratuita y por profesionales conocedores de los derechos de las víctimas, garantizándoles a ellas siempre sus derechos.\nTÍTULO CUARTO\nMEDIDAS DE ASISTENCIA Y ATENCIÓN\nCAPÍTULO I\nDISPOSICIONES GENERALES\nARTÍCULO 43.- Las autoridades competentes garantizarán que el acceso de las víctimas al Registro se haga de manera efectiva, rápida y diferencial, con el fin de permitirles disfrutar de las medidas de asistencia y atención establecidas en la presente Ley.\nLa información tendrá carácter público y en ningún caso incluirá datos personales.\nConforme a los lineamientos desarrollados por la Comisión Ejecutiva, las secretarías, dependencias, organismos y entidades del orden estatal del sector salud, educación, desarrollo social y las demás obligadas, así como aquellos municipios que cuenten con la infraestructura y la capacidad de prestación de servicios, en el marco de sus competencias y fundamentos legales de actuación, deberán tener en cuenta las principales afectaciones y consecuencias del hecho victimizante, respetando siempre los principios generales establecidos en la presente Ley y en particular el enfoque diferencial para los grupos expuestos a un mayor riesgo de violación de sus derechos, como niñas, niños y adolescentes, mujeres, adultos mayores, personas con discapacidad, migrantes, indígenas, personas defensoras de derechos humanos, periodistas y personas en situación de desplazamiento interno.\nARTÍCULO 44.- Todas las medidas de asistencia, atención, protección o servicios se refiere esta Ley, serán gratuitos y éstas recibirán un trato digno con independencia de su capacidad socio-económica y sin exigir condición previa para su admisión a éstos que las establecidas en la presente Ley\nARTÍCULO 45.- El Estado, a través de sus organismos descentralizados, está obligado a prestar servicios educativos para que gratuitamente, cualquier víctima o sus hijos menores de edad, en igualdad efectiva de condiciones de acceso y permanencia en los servicios educativos que el resto de la población, pueda cursar la educación preescolar, la primaria y la secundaria\nLey de Víctimas para el Estado de Baja California. Página 26\nARTÍCULO 46. La víctima o sus familiares tendrán el derecho de recibir becas completas de estudio en instituciones públicas, como mínimo hasta la educación media superior para sí o los dependientes que lo requieran.\nCAPÍTULO II\nMEDIDAS ECONÓMICAS Y DE DESARROLLO\nARTÍCULO 47.- El Estado en sus distintos órdenes, tendrá la obligación de garantizar que toda víctima reciba los beneficios del desarrollo social conforme a sus necesidades, particularmente para atender a las víctimas que hayan sufrido daños graves como consecuencia del hecho victimizante.\nARTÍCULO 48.- Son derechos para el desarrollo social, la educación, la salud, la alimentación, la vivienda, el disfrute de un medio ambiente sano, el trabajo y la seguridad social y los relativos a la no discriminación en los términos de la Constitución Política de los\nEstados Unidos Mexicanos y de los Tratados Internacionales celebrados y ratificados por el\nEstado Mexicano.\nCAPÍTULO III\nMEDIDAS DE ATENCIÓN Y ASISTENCIA EN MATERIA DE PROCURACIÓN Y\nADMINISTRACIÓN DE JUSTICIA\nARTÍCULO 49.- Las medidas de atención y asistencia en materia de procuración y administración de justicia serán permanentes y comprenden, como mínimo:\nI.- La asistencia a la víctima durante cualquier procedimiento administrativo relacionado con su condición de víctima;\nII.- La asistencia a la víctima en el proceso penal durante la etapa de investigación;\nIII.- La asistencia a la víctima durante el juicio, y\nIV.- La asistencia a la víctima durante la etapa posterior al juicio. legal y asesoría que dé a la víctima el Asesor Jurídico.\nTÍTULO QUINTO\nMEDIDAS DE REPARACIÓN\nCAPÍTULO I\nMEDIDAS DE RESTITUCIÓN\nLey de Víctimas para el Estado de Baja California. Página 27\nARTÍCULO 50.- Las víctimas tendrán derecho a la restitución en sus derechos conculcados, así como en sus bienes y propiedades si hubieren sido despojadas de ellos.\nLas medidas de restitución comprenden, según corresponda:\nI.- Restablecimiento de la libertad, en caso de secuestro o desaparición forzada;\nII.- Restablecimiento de los derechos jurídicos;\nIII.- Restablecimiento de la identidad;\nIV.- Restablecimiento de la vida y unidad familiar;\nV.- Restablecimiento de la ciudadanía y de los derechos políticos;\nVI.- Regreso digno y seguro al lugar de residencia;\nVII.- Reintegración en el empleo, y\nVIII.- Devolución de todos los bienes o valores de su propiedad que hayan sido incautados o recuperados por las autoridades incluyendo sus frutos y accesorios, y si no fuese posible, el pago de su valor actualizado. Si se trata de bienes fungibles, el juez podrá condenar a la entrega de un objeto igual al que fuese materia de delito sin necesidad de recurrir a prueba pericial.\nEn los casos en que una autoridad judicial competente revoque una sentencia condenatoria, se eliminarán los registros de los respectivos antecedentes penales.\nCAPÍTULO II\nMEDIDAS DE REHABILITACIÓN\nARTÍCULO 51.- Las medidas de rehabilitación incluyen, entre otras y según proceda, las siguientes:\nI.- Atención médica, psicológica y psiquiátrica especializadas;\nII.- Servicios y asesoría jurídicos tendientes a facilitar el ejercicio de los derechos de\nIII.- Servicios sociales orientados a garantizar el pleno restablecimiento de los derechos de la víctima en su condición de persona y ciudadana;\nLey de Víctimas para el Estado de Baja California. Página 28\nIV.- Programas de educación orientados a la capacitación y formación de las proyecto de vida;\nV.- Programas de capacitación laboral orientados a lograr la plena reintegración de la víctima a la sociedad y la realización de su proyecto de vida, y\nVI.- Todas aquellas medidas tendientes a reintegrar a la víctima a la sociedad, incluido su grupo, o comunidad.\nCAPÍTULO III\nMEDIDAS DE COMPENSACIÓN\nARTÍCULO 52.- Las medidas de compensación previstas en la presente Ley, se otorgarán en los términos previstos en dicho ordenamiento, su reglamento y demás disposiciones normativas aplicables.\nARTÍCULO 53.- La Comisión Ejecutiva correspondiente ordenará la compensación subsidiaria cuando la víctima, que no haya sido reparada, exhiba ante ella todos los elementos a su alcance que lo demuestren y presente ante la Comisión sus alegatos. La víctima podrá presentar entre otros:\nI.- Las constancias del agente del ministerio público que competa de la que se desprenda que las circunstancias de hecho hacen imposible la consignación del presunto delincuente ante la autoridad jurisdiccional y por lo tanto hacen imposible el ejercicio de la acción penal;\nII.- La sentencia firme de la autoridad judicial competente, en la que se señalen los conceptos a reparar, y la reparación obtenida de donde se desprendan los conceptos que el sentenciado no tuvo la capacidad de reparar, y\nIII.- La resolución emitida por autoridad competente u organismo público de reparación del daño, de la persona directamente responsable de satisfacer dicha reparación.\nARTÍCULO 54.- La compensación subsidiaria a favor de las víctimas de delitos, se cubrirá con cargo al Fondo Estatal en términos de esta Ley, la Ley General, sus\nReglamentos y demás disposiciones respectivas.\nARTÍCULO 55.- El Estado, a través de la Comisión Ejecutiva Estatal, tendrá la cometió.\nLey de Víctimas para el Estado de Baja California. Página 29\nARTÍCULO 56.- La obtención de la compensación subsidiaria no extingue el derecho de la víctima a exigir reparación de cualquier otra naturaleza.\nCAPÍTULO IV\nMEDIDAS DE SATISFACCIÓN\nARTÍCULO 57.- Las medidas de satisfacción comprenden, entre otras y según corresponda:\nI.- La verificación de los hechos y la revelación pública y completa de la verdad, en la medida en que esa revelación no provoque más daños o amenace la seguridad y los intereses de la víctima, de sus familiares, de los testigos o de personas que han intervenido para ayudar a la víctima o para impedir que se produzcan nuevos delitos o nuevas violaciones de derechos humanos a la víctima;\nII.- La búsqueda de las personas desaparecidas y de los cuerpos u osamentas de las personas asesinadas, así como la ayuda para recuperarlos, identificarlos y volver a inhumarlos según el deseo explícito o presunto de la víctima o las prácticas culturales de su familia y comunidad;\nIII.- Una declaración oficial o decisión judicial que restablezca la dignidad, la reputación y los derechos de la víctima y de las personas estrechamente vinculadas a ella;\nIV.- Una disculpa pública de parte del Estado, los autores y otras personas involucradas en el hecho punible o en la violación de los derechos, que incluya el reconocimiento de los hechos y la aceptación de responsabilidades;\nV.- La aplicación de sanciones judiciales o administrativas a los responsables de las violaciones de derechos humanos, y\nVI.- La realización de actividades educativas, pedagógicas y culturales dirigidas a la reconstrucción de la memoria sobre las condiciones que generaron el daño a la víctima.\nCAPÍTULO V\nMEDIDAS DE NO REPETICIÓN\nARTÍCULO 58.- Las medidas de no repetición son aquéllas que se adoptan con el contribuir a prevenir o evitar la repetición de actos de la misma naturaleza. Estas consistirán en las siguientes:\nLey de Víctimas para el Estado de Baja California. Página 30\nI.- El ejercicio de un control efectivo por las autoridades civiles de las fuerzas armadas y de seguridad;\nII.- La garantía de que todos los procedimientos penales y administrativos se ajusten a las normas nacionales e internacionales relativas a la competencia, independencia e\nIII.- El fortalecimiento de la independencia del Poder Judicial;\nIV.- La limitación en la participación en el gobierno y en las instituciones políticas de los dirigentes políticos que hayan planeado, instigado, ordenado o cometido graves violaciones de los derechos humanos;\nV.- La exclusión en la participación en el gobierno o en las fuerzas de seguridad de los militares, agentes de inteligencia y otro personal de seguridad declarados responsables de planear, instigar, ordenar o cometer graves violaciones de los derechos humanos;\nVI.- La protección de los profesionales del derecho, la salud y la información;\nVII.- La protección de los defensores de los derechos humanos;\nVIII.- La educación, de modo prioritario y permanente, de todos los sectores de la sociedad respecto de los derechos humanos y la capacitación en esta materia de los funcionarios encargados de hacer cumplir la ley, así como de las fuerzas armadas y de seguridad;\nIX.- La promoción de la observancia de los códigos de conducta y de las normas éticas, en particular los definidos en normas internacionales de derechos humanos y de protección a los derechos humanos, por los funcionarios públicos incluido el personal de las fuerzas armadas, de seguridad y los establecimientos penitenciarios;\nX.- La promoción de mecanismos destinados a prevenir, vigilar y resolver por medios pacíficos los conflictos sociales, y\nXI.- La revisión y reforma de las leyes, normas u ordenamientos legales que humanos o las permitan.\nARTÍCULO 59.- Se entienden como medidas que buscan garantizar la no repetición de los delitos ni de las violaciones a derechos humanos, las siguientes:\nI.- Supervisión de la autoridad;\nLey de Víctimas para el Estado de Baja California. Página 31\nII.- Prohibición de ir a un lugar determinado u obligación de residir en él, en caso de existir peligro inminente para la víctima;\nIII.- Caución de no ofender;\nIV.- La asistencia a cursos de capacitación sobre derechos humanos, y\nV.- La asistencia a tratamiento de deshabituación o desintoxicación dictada por un juez y sólo en caso de que la adicción hubiera sido la causa de la comisión del delito o hecho victimizante.\nARTÍCULO 60.- Se entiende por supervisión de la autoridad, la consistente en la observación y orientación de los sentenciados, ejercidas por personal especializado, con la finalidad de coadyuvar a la protección de la víctima y la comunidad.\nEsta medida se establecerá cuando la privación de la libertad sea sustituida por otra sanción, sea reducida la pena privativa de libertad o se conceda la suspensión condicional de la pena.\nARTÍCULO 61.- El juez en la sentencia exigirá una garantía de no ofender que se hará efectiva si el acusado violase las disposiciones del artículo anterior, o de alguna forma reincidiera en los actos de molestia a la víctima. Esta garantía no deberá ser inferior a la de la multa aplicable y podrá ser otorgada en cualquiera de las formas autorizadas por las leyes.\nARTÍCULO 62.- Cuando el sujeto haya sido sentenciado por delitos o violación a los derechos humanos cometidos bajo el influjo o debido al abuso de sustancias alcohólicas, estupefacientes, psicotrópicos u otras similares o de tipo tóxico, independientemente de la pena que corresponda, sólo si el juez así lo ordena, se aplicarán cursos y tratamientos para evitar su reincidencia y fomentar su deshabituación o desintoxicación.\nTÍTULO SEXTO\nDEL SISTEMA ESTATAL\nDE ATENCIÓN A VÍCTIMAS\nCAPÍTULO I\nNATURALEZA, OBJETO Y ATRIBUCIONES\nARTÍCULO 63.- El Sistema Estatal de Atención a Víctimas será la instancia superior proponer, establecer y supervisar las directrices, servicios, planes, programas, proyectos, estrategias institucionales e interinstitucionales, y demás acciones que se implementen para\nLey de Víctimas para el Estado de Baja California. Página 32 las víctimas en los ámbitos local y municipal. estatales y municipales, organismos autónomos, y demás organizaciones públicas o privadas, encargadas de la protección, ayuda, asistencia, atención, defensa de los derechos humanos, acceso a la justicia, a la verdad y a la reparación de las víctimas, a que se refiere el Capítulo II del presente Título.\nEl Sistema Estatal tiene por objeto la coordinación de instrumentos, políticas, servicios y acciones entre las instituciones y organismos ya existentes y los creados por esta\nLey.\nPara la operación del Sistema Estatal y el cumplimiento de sus atribuciones, contará con la Comisión Ejecutiva Estatal, quien conocerá y resolverá los asuntos de su competencia, de conformidad con las disposiciones aplicables.\nLa Comisión Ejecutiva Estatal tiene la obligación de atender a las víctimas de delitos del fuero común o de violaciones a derechos humanos cometidos por servidores públicos del orden estatal o municipal en el ejercicio de sus funciones o atribuciones o por un particular que ejerza funciones públicas en los supuestos a que se refiere la fracción XVIII del artículo\n7 de esta Ley.\nLas víctimas podrán acudir directamente a la Comisión Ejecutiva Federal cuando no reciba respuesta de los servidores públicos competentes dentro de los treinta días naturales siguientes o cuando la atención se hubiere prestado de forma deficiente o se hubiere negado.\nARTÍCULO 64.- El Sistema Local se coordinará con el Sistema Nacional, por conducto de la Comisión Ejecutiva, con el fin de instrumentar y articular las políticas públicas de carácter nacional, para la adecuada atención y protección de las víctimas.\nMunicipios, en el ámbito de sus respectivas competencias, así como los sectores social y privado, deberán coordinarse para establecer los mecanismos de organización, supervisión, evaluación y control de los servicios en materia de protección, ayuda, asistencia y atención, acceso a la justicia, a la verdad y reparación a víctimas, previstos en esta Ley y en la Ley\nGeneral.\nARTÍCULO 65.- Para el cumplimiento de su objeto, el Sistema Estatal tendrá las siguientes atribuciones:\nLey de Víctimas para el Estado de Baja California. Página 33\nI.- Tener la representatividad del Estado ante el Sistema Nacional de atención a\nVíctimas, y ser el enlace oficial en el seguimiento y consecución del objeto y fines del mismo; locales;\nII.- Promover la coordinación y colaboración entre las instituciones, entidades públicas estatales y municipales, organismos autónomos encargados de la protección, ayuda, asistencia, atención, defensa de los derechos humanos, acceso a la justicia, a la verdad y a la reparación de las víctimas;\nIII.- Formular propuestas para la elaboración del Programa Estatal y demás instrumentos programáticos relacionados con la protección, ayuda, asistencia, atención, defensa de los derechos humanos, acceso a la justicia, a la verdad y a la reparación de las víctimas;\nIV.- Analizar y evaluar los resultados que arrojen las evaluaciones que se realicen a la Comisión Ejecutiva Estatal;\nV.- Recomendar propuestas de reformas legales y reglamentarias en materia de atención a víctimas;\nVI.- Integrar los comités que sean necesarios para el desempeño de sus funciones en estricto apego a la presente Ley;\nVII.- Dar seguimiento y promoción a la estrategia de supervisión y acompañamiento que busca el desarrollo profesional y la especialización conjunta de los miembros de las instituciones de atención a víctimas;\nVIII.- Fomentar la participación de la comunidad en las actividades de atención a víctimas;\nIX.- Fijar criterios de cooperación y coordinación para la atención médica, psicológica y jurídica de víctimas del delito, así como de gestoría de trabajo social respecto de las mismas;\nXI.- Dar seguimiento a la aplicación de las políticas públicas y estrategias de coordinación en materia de combate a la corrupción y de atención a víctimas;\nXII.- Expedir sus reglas de organización y funcionamiento; y\nXIII.- Las demás que le otorga esta Ley y otras disposiciones aplicables.\nLey de Víctimas para el Estado de Baja California. Página 34\nCAPÍTULO II\nINTEGRACIÓN DEL SISTEMA ESTATAL\nDE ATENCIÓN A VÍCTIMAS\nARTÍCULO 66.- El Sistema Estatal estará integrado por las instituciones, entidades, organismos y demás participantes, aquí enumerados:\nI. Poder Ejecutivo: a. La persona titular del Poder Ejecutivo, quien lo presidirá;\nInciso Reformado b. La persona titular de la Secretaría General de Gobierno;\nInciso Reformado c. La persona titular de la Secretaría de Seguridad Ciudadana; y,\nInciso Reformado d. La persona titular de la Dirección General del Sistema Integral de la Familia DIF del Estado.\nInciso Reformado\nFracción Reformada\nII. Poder Legislativo: a. La persona titular de la Presidencia de la Comisión de Justicia; y,\nInciso Reformado b. La persona titular de la Presidencia de la Comisión de Derechos Humanos.\nInciso Reformado\nFracción Reformada\nIII. Poder Judicial: a. La o el Magistrado Presidente del Tribunal Superior de Justicia y del Consejo de la Judicatura del Estado.\nInciso Reformado\nFracción Reformada\nIV. Organismos Públicos: a. La persona titular de la Presidencia de la Comisión Estatal de Derechos\nHumanos.\nInciso Reformado\nFracción Reformada\nV. La persona titular de la Comisión Ejecutiva Estatal.\nFracción Reformada\nLey de Víctimas para el Estado de Baja California. Página 35\nVI. La persona titular de la Fiscalía General del Estado de Baja California;\nFracción Adicionada\nVII. La persona que tenga la representación por cada uno de los Municipios del Estado.\nFracción Reformada\nEl Sistema Estatal contará con una Secretaría Técnica, que tendrá la obligación de dar seguimiento a los acuerdos adoptados por esté.\nPárrafo Reformado\nEl carácter de miembro del Sistema Estatal, será honorífico.\nArtículo Reformado\nARTÍCULO 67.- Los integrantes del Sistema Estatal se reunirán en Pleno por lo menos una vez cada tres meses por convocatoria de su Presidente y en forma extraordinaria, cuando los integrantes del Sistema Estatal así lo determinen. Los integrantes tienen obligación de comparecer a las sesiones.\nEl titular de la Comisión Ejecutiva auxiliara al Presidente del Sistema en la elaboración del orden del día, así como en todo lo necesario para su desahogo.\nEl quórum para las reuniones del Sistema Estatal se conformará con la mitad más uno de sus integrantes. Los acuerdos se tomarán por la mayoría de los integrantes presentes con derecho a voto. En caso de empate el Presidente tendrá voto de calidad.\nCorresponderá al Presidente del Sistema Estatal la facultad de promover en todo tiempo la efectiva coordinación y funcionamiento del mismo. Los integrantes del propio\nSistema Estatal podrán formular propuestas de acuerdos que permitan su mejor funcionamiento.\nEl Presidente del Sistema Estatal será suplido en sus ausencias por el Secretario\nGeneral de Gobierno. Los demás integrantes del Sistema Estatal deberán asistir o enviar a un representante.\nTendrán el carácter de invitados a las sesiones del Sistema Estatal, las instituciones u organizaciones privadas o sociales, o las demás instituciones nacionales o extranjeras, El Reglamento establecerá el mecanismo de invitación correspondiente. Los invitados acudirán a las reuniones con derecho a voz, pero sin voto.\nCAPITULO III\nDEL CONSEJO CONSULTIVO DE LA\nCOMISIÓN EJECUTIVA DE ATENCIÓN A VICTIMAS\nLey de Víctimas para el Estado de Baja California. Página 36\nARTICULO 68.- Con el propósito de garantizar la participación ciudadana en la vigilancia y evaluación de las políticas públicas, así como el funcionamiento de los órganos y autoridades responsables en materia de atención a víctimas en el marco de esta Ley, se crea al Consejo Consultivo, como órgano de apoyo, consulta y opinión.\nARTÍCULO 69.- El Consejo Consultivo estará integrado por cinco ciudadanos que tendrán el carácter de honorifico, elegidos por el Congreso del Estado a propuesta de organizaciones de la sociedad civil o académicas, quienes duraran en su cargo por un periodo de dos años, pero podrán ser reelectos hasta por otro periodo igual.\nLa Comisión Ejecutiva deberá garantizar las condiciones necesarias para que el\nConsejo Consultivo pueda sesionar.\nARTÍCULO 70.- Para la designación de los consejeros, el Congreso Local expedirá una convocatoria que deberá ser publicada en un diario de mayor circulación en el Estado y en el portal de internet del Congreso. En la convocatoria se establecerán las etapas de las que constará el proceso de designación y señalarse con claridad los requisitos y la forma de acreditarlos, así como los plazos lugares y horarios de presentación de solicitudes y demás documentos.\nLa comisión correspondiente, elaborará, aprobará y presentará ante el Pleno, un dictamen debidamente fundado y motivado que contenga el listado de los interesados y el cumplimiento de los requisitos.\nCon el voto de las dos terceras partes de los miembros presentes, el Congreso nombrará a los consejeros correspondientes, previamente al día en que concluya el período de los consejeros respectivos.\nARTÍCULO 71.- La duración del encargo será de dos años, pero podrán ser propuestos y ratificados para un segundo período igual.\nAnualmente serán sustituidos los dos consejeros de mayor antigüedad en el cargo.\nPara el caso de que existan más de dos consejeros con la misma antigüedad, el Congreso del Estado determinará el orden cronológico que deba seguirse para su sustitución.\nLos consejeros podrán ser ratificados para un segundo periodo, previa petición formal que envíen al Congreso del Estado, en la que manifiesten su interés de ser considerados en el proceso de renovación del Consejo. La solicitud para continuar en el convocatoria respectiva\nLey de Víctimas para el Estado de Baja California. Página 37\nARTÍCULO 72.- El Consejo será presidido por el consejero electo por la mayoría de sus integrantes y durará en su encargo un periodo de dos años. para el efecto expida el propio Consejo.\nARTÍCULO 73.- En caso de ausencia definitiva de cualquier integrante del Consejo, el Presidente de la Comisión Ejecutiva notificará inmediatamente al Congreso del Estado para efecto de proceder a la nueva designación la cual será por un periodo completo.\nARTÍCULO 74.- El Consejo Consultivo tendrá las siguientes atribuciones:\nI.- Opinar sobre el programa anual de trabajo y su cumplimiento.\nII.- Opinar respecto a los lineamientos generales del funcionamiento de la Comisión\nEjecutiva;\nIII.- Opinar respecto al Reglamento Interior de la Comisión Ejecutiva;\nIV.- Opinar respecto a los manuales, protocolos, políticas públicas, convenios y documentos técnicos, operativos y reglamentarios relacionados con la actuación de la\nComisión Ejecutiva.\nV.- Conocer y evaluar el informe anual que elabore y presente la Comisión Ejecutiva.\nVI.- Emitir opiniones y hacer recomendaciones respecto al funcionamiento y actuación de la Comisión Ejecutiva.\nVII.- Solicitar a la Comisión Ejecutiva cualquier información relacionada con el funcionamiento y atribuciones de asuntos atendidos o en trámite de atención.\nVIII.- Conocer y opinar el proyecto de presupuesto de la Comisión para el ejercicio del año siguiente, así como opinar el informe sobre el presupuesto asignado a programas y el ejercicio presupuestal. las sesiones del Sistema Estatal.\nARTÍCULO 75.- El Consejo funcionará conforme a las reglas que para el efecto expida, en sesiones ordinarias y extraordinarias y tomará sus decisiones por mayoría de votos.\nARTÍCULO 76.- Las sesiones ordinarias se verificarán cuando menos una cada dos meses.\nLey de Víctimas para el Estado de Baja California. Página 38 importancia o que deban resolverse de inmediato:\nI.- Por el presidente del Consejo, y\nII.- Mediante convocatoria que formulen por lo menos tres de los consejeros.\nCAPÍTULO IV\nDE LA COMISIÓN EJECUTIVA ESTATAL\nDE ATENCIÓN A VÍCTIMAS\nSECCIÓN I\nNATURALEZA JURÍDICA\nARTÍCULO 77.- El Sistema Estatal contará con una Comisión Ejecutiva Estatal de\nAtención a Víctimas, que conocerá y resolverá los asuntos de su competencia, de conformidad con la presente Ley y sus disposiciones reglamentarias aplicables.\nARTÍCULO 78.- La Comisión Ejecutiva Estatal es el órgano operativo del Sistema\nEstatal con personalidad jurídica y patrimonio propios; con autonomía técnica y de gestión, integrante del Sistema Nacional de Atención a Víctimas, encargada de atender a las víctimas de delitos del fuero común o de violaciones a derechos fundamentales cometidos por servidores públicos del orden estatal o municipal en el ejercicio de sus funciones o atribuciones o por un particular que ejerza funciones públicas en los supuestos a que se refiere la fracción XVIII del artículo 7 de esta Ley, de las gestiones necesarias para acceder al Fondo al Fondo Estatal, así como de la ejecución de las funciones, acciones, planes y programas previstos en esta Ley y en la Ley General. El Poder Ejecutivo del Estado reglamentará sus atribuciones y funcionamiento.\nDe la Comisión Ejecutiva Estatal depende el Fondo Estatal, la Asesoría Jurídica y el\nRegistro Estatal, que se establecen a fin de garantizar el acceso efectivo de las víctimas a los derechos, garantías, mecanismos, procedimientos y servicios que establece esta Ley.\nARTÍCULO 79.- La Comisión Ejecutiva Estatal cuenta con una Junta de Gobierno y un Comisionado Ejecutivo para su administración, así como con un Consejo Consultivo,\nARTÍCULO 80.- La organización y funcionamiento de la Junta de Gobierno se regirá por lo dispuesto en esta Ley y las demás disposiciones aplicables, estará integrada de la siguiente manera:\nI.- Un representante de las siguientes secretarías del Estado:\nLey de Víctimas para el Estado de Baja California. Página 39\na) General de Gobierno quien la presidirá;\nb) De Hacienda;\nInciso Reformado\nc) De Educación;\nInciso Reformado\nd) Salud;\nFracción Reformada\nII.- Tres representantes del Consejo Consultivo, designados por ésta, y\nLas y los integrantes referidos en la fracción I del párrafo anterior, serán las personas titulares de cada Institución y sus suplentes tendrán el nivel de Subsecretaría, Dirección o su equivalente. En sus decisiones los integrantes tendrán derecho a voz y voto.\nLa Junta de Gobierno contará con una Secretaría Técnica, que estará a cargo de la o el Comisionado Ejecutivo.\nPárrafo Reformado\nArtículo Reformado\nARTÍCULO 81.- La Junta de Gobierno celebrará sesiones ordinarias por lo menos cuatro veces al año y las extraordinarias que propondrá su Presidente, el Comisionado\nEjecutivo o al menos 5 de sus integrantes.\nARTÍCULO 82.- La Junta de Gobierno sesionará válidamente con la asistencia de la mayoría de sus integrantes, siempre que esté presente el Presidente de la Junta de\nGobierno. Los acuerdos se adoptarán por mayoría de votos de los miembros presentes.\nARTÍCULO 83.- La Junta de Gobierno tendrá exclusivamente las siguientes atribuciones:\nI.- Aprobar y modificar su reglamento de sesiones, con base en la propuesta que presente el Comisionado Ejecutivo;\nII.- Aprobar las disposiciones normativas que el Comisionado Ejecutivo someta a su consideración en términos de la Ley y el Reglamento;\nIII.- Definir los criterios, prioridades y metas de la Comisión Ejecutiva Estatal que proponga el Comisionado Ejecutivo;\nIV.- Conocer de los convenios y acuerdos de colaboración, coordinación y concertación que celebre la Comisión Ejecutiva de acuerdo con esta Ley, y\nLey de Víctimas para el Estado de Baja California. Página 40\nV.- Aquellas que por su naturaleza jurídica le correspondan. recursos de ayuda y la reparación del daño que la Comisión Ejecutiva otorgue a las víctimas.\nSECCIÓN II\nINTEGRACIÓN\nARTÍCULO 84.- La Comisión Ejecutiva Estatal estará a cargo de un Comisionado\nEjecutivo elegido por el voto de las dos terceras partes de los miembros presentes del\nCongreso del Estado, de la terna que enviará el Ejecutivo Estatal, previa consulta pública a las organizaciones de la sociedad civil especializadas en la materia.\nARTÍCULO 85.- Para ser comisionado se requiere:\nI.- Ser ciudadana o ciudadano mexicano y contar por lo menos con treinta años de edad al día de la designación;\nFracción Reformada\nII.- No haber sido condenado por la comisión de un delito doloso o inhabilitado como servidor público;\nIII.- Haberse desempeñado destacadamente en actividades profesionales, de servicio público, en sociedad civil o académicas relacionadas con la materia de esta Ley por lo menos en los dos años previos a su designación;\nIV.- Contar con Título Profesional o acreditar experiencia, cuando menos de tres años y gozar de reconocimiento público por su participación activa y aportes al conocimiento en temas relacionados con la atención integral a víctimas;\nFracción Reformada\nV.- No haber ocupado cargo público ni haber desempeñado cargo de dirección nacional o estatal en algún partido político, dentro de los dos años previos a su designación.\nEn la elección del comisionado, deberá garantizarse el respeto a los principios que dan marco a esta Ley. reelección. Durante el mismo no podrá tener ningún otro empleo, cargo o comisión, salvo en instituciones docentes, científicas o de beneficencia.\nArtículo Reformado\nLey de Víctimas para el Estado de Baja California. Página 41\nARTÍCULO 86.- El Comisionado Ejecutivo Estatal para el desarrollo de las\nEstatal, la Asesoría Jurídica y el Registro Estatal de Víctimas.\nSECCIÓN III\nFUNCIONES Y FACULTADES\nARTÍCULO 87.- La Comisión Ejecutiva Estatal tendrá las siguientes funciones y facultades:\nI.- Ejecutar y dar seguimiento a los acuerdos y resoluciones adoptadas por el\nSistema Nacional y el Sistema Estatal;\nII.- Garantizar el acceso a los servicios multidisciplinarios y especializados que el\nEstado proporcionará a las víctimas de delitos o por violación a sus derechos humanos, para lograr su reincorporación a la vida social;\nIII.- Participar en la elaboración del Programa de Atención Integral a Víctimas, previsto en la Ley General y elaborar anualmente un proyecto de Programa Estatal con el objeto de crear, reorientar, dirigir, planear, coordinar, ejecutar y supervisar las políticas públicas en materia de atención a víctimas, y proponerlo para su aprobación al Sistema\nEstatal;\nIV.- Proponer al Sistema Estatal políticas públicas de prevención de delitos y violaciones a derechos humanos, así como de atención, asistencia, protección, acceso a la justicia, a la verdad y reparación a las víctimas u ofendidos de acuerdo con los principios establecidos en esta Ley y en la Ley General;\nV.- Instrumentar los mecanismos, medidas, acciones, mejoras y demás políticas acordadas por el Sistema Estatal;\nVI.- Implementar el mecanismo de seguimiento y evaluación de las obligaciones derivadas de esta Ley y de la Ley General, que le sean propuestos por los Sistemas\nNacional y Estatal;\nVII.- Proponer al Sistema Estatal las medidas legales necesarias para la protección inmediata de las víctimas cuando su vida o su integridad se encuentre en riesgo;\nVIII.- Coordinarse con las instituciones competentes para la atención de una problemática específica, de acuerdo con los principios establecidos en esta Ley, así como los de coordinación, concurrencia y subsidiariedad;\nLey de Víctimas para el Estado de Baja California. Página 42\nIX.- Establecer mecanismos para la capacitación, formación, actualización y especialización de funcionarios públicos o dependientes de las instituciones, de conformidad con lo dispuesto en esta Ley;\nX.- Realizar las acciones necesarias para la adecuada operación del Registro Estatal y de la Asesoría Jurídica;\nXI.- Remitir la información al Registro Nacional de Víctimas, conforme a los lineamientos fijados por la Comisión Ejecutiva y cuidando la confidencialidad de la información;\nXII.- Rendir un Informe al Sistema Estatal sobre los avances del Programa Estatal;\nXIII.- Realizar las gestiones necesarias ante la Comisión Ejecutiva Nacional para que las víctimas puedan acceder al Fondo previsto en la Ley General, así como administrar y vigilar el adecuado ejercicio del Fondo Estatal y emitir las recomendaciones pertinentes a fin de garantizar su óptimo y eficaz funcionamiento, con base en los principios de publicidad, transparencia y rendición de cuentas;\nXIV.- Solicitar al órgano competente se apliquen las medidas disciplinarias y sanciones correspondientes;\nXV.- Hacer recomendaciones al Sistema Estatal, mismo que deberá dar respuesta oportuna a aquéllas;\nXVI.- Nombrar a los titulares del Fondo Estatal, la Asesoría Jurídica y del Registro\nEstatal;\nXVII.- Emitir opinión sobre el proyecto de Reglamento de la presente Ley y sus reformas y adiciones;\nXVIII.- Formular propuestas de políticas públicas de prevención de violaciones a derechos humanos, atención, asistencia, protección, acceso a la justicia, a la verdad y reparación a las víctimas de acuerdo con los principios establecidos en esta Ley;\nXIX.- Difundir las medidas, lineamientos o directrices de carácter obligatorio emitidas por la Comisión Ejecutiva, con la finalidad de facilitar condiciones dignas, integrales y efectivas para la atención y asistencia de las víctimas, que permitan su recuperación y reparación;\nXX.- Promover la coordinación interinstitucional de las dependencias, instituciones y\nLey de Víctimas para el Estado de Baja California. Página 43 integrantes y especialmente de las áreas, instituciones, grupos de víctimas u organizaciones que se requieran para el tratamiento de una problemática específica, de acuerdo con los principios establecidos en esta Ley y los de coordinación, concurrencia, subsidiariedad, complementariedad y delegación;\nXXI.- Establecer las medidas determinadas por la Comisión Ejecutiva para garantizar la reparación, efectiva y eficaz de las víctimas que hayan sufrido un daño como consecuencia de la comisión de un delito o de la violación de sus derechos humanos;\nXXII.- Proponer al Sistema Estatal las directrices o lineamientos que faciliten el acceso efectivo de las víctimas a la verdad y a la justicia;\nXXIII.- Emitir los lineamientos para la canalización oportuna y eficaz de los recursos humanos, técnicos, administrativos y económicos que sean necesarios para el cumplimiento de las acciones, planes, proyectos y programas de atención, asistencia, acceso a la justicia, a la verdad y reparación de las víctimas en el Estado y los Municipios;\nXXIV.- Consolidar y dar seguimiento al manejo de la plataforma para integrar, desarrollar y consolidar la información sobre las víctimas para retroalimentar a la federación con información de lo local a fin de orientar políticas, programas, planes y demás acciones a favor de las víctimas para la prevención del delito y de violaciones a los derechos humanos, atención, asistencia, acceso a la verdad, justicia y reparación con el fin de llevar a cabo el monitoreo, seguimiento y evaluación del cumplimiento de las políticas, acciones y responsabilidades establecidas en esta Ley.\nXXV.- Dictar los lineamientos para la transmisión de información de las instituciones que forman parte del Sistema Estatal, cuidando la confidencialidad de la información, pero permitiendo que pueda haber un seguimiento y revisión de los casos que lo lleguen a requerir;\nXXVI.- Adoptar las acciones necesarias para garantizar el ingreso de las víctimas al\nRegistro Estatal, así como al Registro Nacional;\nXXVII.- Coadyuvar en la difusión de los protocolos generales de actuación para la prevención, atención e investigación de delitos o violaciones a los derechos humanos;\nXXVIII.- Dar seguimiento y monitoreo al cumplimiento de las autoridades del y demás acciones, a lo establecido en los protocolos, siendo responsable de la homologación y adaptación a nivel estatal, velando porque contengan el mínimo de procedimientos y garantías que los protocolos generales establezcan para las víctimas;\nLey de Víctimas para el Estado de Baja California. Página 44\nXXIX.- En casos de graves violaciones a derechos humanos o delitos graves cometidos contra un grupo de víctimas, proponer al Sistema Estatal los programas integrales emergentes de ayuda, atención, asistencia, protección, acceso a justicia, a la verdad y reparación;\nXXX.- Crear y coordinar los comités especiales de atención a víctimas de delitos o violaciones de derechos humanos que requieran prevención, atención e investigación con una perspectiva integral tales como en los casos de desaparición de personas, extravío, ausencia o no localización de personas, trata de personas, tráfico de personas y secuestro, a fin de que además de las acciones, propuestas, planes o programas que se deriven para un grupo de víctimas específicas, se guarde una integralidad respecto al tratamiento de las víctimas y reparación, con cargo a su presupuesto autorizado;\nXXXI.- Apoyar a la Comisión Ejecutiva Nacional en la realización de diagnósticos regionales que permitan evaluar las problemáticas concretas que enfrentan las víctimas en términos de prevención del delito o de violaciones a los derechos humanos, atención, asistencia, acceso a la justicia, derecho a la verdad y reparación;\nXXXII.- Generar diagnósticos específicos sobre las necesidades locales en materia de capacitación, recursos humanos y materiales que se requieran para garantizar un estándar mínimo de atención digna a las víctimas cuando requieran acciones de ayuda, apoyo, asistencia o acceso a la justicia, a la verdad y a la reparación de tal manera que sea disponible y efectiva;\nXXXIII.- Brindar apoyo a las organizaciones de la sociedad civil que se dedican a la ayuda, atención y asistencia a favor de las víctimas, priorizando aquéllas que se encuentran en lugares donde las condiciones de acceso a la ayuda, asistencia, atención y reparación es difícil debido a las condiciones precarias de desarrollo y marginación;\nXXXIV.- Implementar los mecanismos de control, con la participación de la sociedad civil, que permitan supervisar y evaluar las acciones, programas, planes y políticas públicas en materia de víctimas. La supervisión deberá ser permanente y los comités u órganos específicos que se instauren al respecto, deberán emitir recomendaciones que deberán ser respondidas por las instituciones correspondientes;\nXXXV.- Recibir y evaluar los informes rendidos por el titular del Fondo Estatal, de la\nAsesoría Jurídica, así como el Programa y emitir las recomendaciones pertinentes a fin de garantizar un óptimo y eficaz funcionamiento, siguiendo los principios de publicidad y transparencia;\nXXXVI.- Requerir a las autoridades competentes la obtención urgente de medidas de protección de las víctimas cuando su vida o su integridad física se encuentre en riesgo, así como su inclusión al programa de protección de victimas dentro del procedimiento penal.\nLey de Víctimas para el Estado de Baja California. Página 45\nXXXVII.- Impulsar actividades de investigación especializada en justicia restaurativa, derecho a la verdad, derecho a la reparación y de cualquier otro tema que contribuya a la realización plena y progresiva de los derechos de las víctimas.\nXXXVIII.- Fomentar actividades educativas y culturales encaminadas a fortalecer los derechos humanos, para lo cual podrá coordinarse con organizaciones del sector público, social o privado.\nXXXIX.- Las demás que se deriven de la presente Ley y de la Ley General.\nARTÍCULO 88.- La Comisión Ejecutiva Estatal podrá celebrar convenios de coordinación, colaboración y concertación con las entidades, dependencias e instituciones estatales, así como con las entidades e instituciones federales, incluidos los organismos autónomos de protección de los derechos humanos que sean necesarios para el cumplimiento de los fines del Sistema.\nARTÍCULO 89.- El Comisionado tendrá las siguientes facultades:\nI.- Administrar, representar legalmente y dirigir el cumplimiento de las atribuciones de la Comisión Estatal Ejecutiva;\nII.- Convocar y dar seguimiento a las sesiones que realice la Junta de Gobierno;\nIII.- Crear los lineamientos, mecanismos, instrumentos e indicadores para el seguimiento y vigilancia de las funciones de la Comisión Estatal, acorde a lo previsto en la presente Ley;\nIV.- Notificar a los integrantes del Sistema Estatal los acuerdos asumidos y dar seguimiento a los mismos;\nV.- Coordinar las funciones del Registro Estatal, conforme a los lineamientos, mecanismos, instrumentos e indicadores emitidos por el Registro Nacional de Víctimas; funciones encomendadas a la Comisión Ejecutiva Estatal, al Registro Estatal y al Fondo\nEstatal;\nVII.- Coordinar las acciones para el cumplimiento de las funciones de la Comisión\nEjecutiva Estatal;\nVIII.- Garantizar el registro de las víctimas que acudan directamente ante la\nComisión Ejecutiva Estatal a solicitar su inscripción en el Registro Estatal, así como los\nLey de Víctimas para el Estado de Baja California. Página 46 servicios de ayuda, asistencia, atención, acceso a la justicia, acceso a la verdad y reparación que soliciten a través de las instancias competentes, dando seguimiento hasta la etapa final para garantizar el cumplimiento eficaz de las funciones de las instituciones;\nIX.- Suscribir los convenios de colaboración que se requieran para el cumplimiento de sus funciones;\nX.- Realizar los programas operativos anuales y los requerimientos presupuestales anuales que corresponda a la Comisión Ejecutiva Estatal;\nXI.- Aplicar las medidas que sean necesarias para garantizar que las funciones de la\nComisión Ejecutiva Estatal se realicen de manera adecuada, eficiente, oportuna, expedita y articulada;\nXII.- Recabar información que pueda mejorar la gestión y desempeño de la Comisión\nEjecutiva Estatal;\nXIII.- Determinar a propuesta del Comité Interdisciplinario Evaluador, los Recursos de Ayuda y la reparación que la Comisión Ejecutiva otorgue a las víctimas. Para lo cual, el\nComisionado Ejecutivo se podrá apoyar de la asesoría del Consejo Consultivo, y\nXIV.- Las demás que se requiera para el eficaz cumplimiento de las funciones de la\nComisión Ejecutiva Estatal.\nARTÍCULO 90.- La Comisión Ejecutiva Estatal implementará el Programa\nInstitucional Estatal, el cual establecerá las directrices y lineamientos para la ejecución de los servicios y prestaciones relacionados con los derechos a la ayuda inmediata, la asistencia y la atención de las víctimas.\nARTÍCULO 91.- En los casos de graves violaciones a los derechos humanos o delitos cometidos contra un grupo de víctimas, las organizaciones no gubernamentales, el\nEjecutivo y Legislativo, los municipios, o cualquier otra institución pública o privada que tenga entre sus fines la defensa de los derechos humanos, podrán proponer al Sistema\nEstatal el establecimiento de programas emergentes de ayuda, atención, asistencia, protección, acceso a la justicia, acceso a la verdad y reparación de las víctimas. atención especial de determinada situación o grupos de víctimas.\nARTÍCULO 92.- La Comisión Ejecutiva Estatal podrá también contar con la asesoría de grupos de expertos en temas específicos, solicitar opiniones de organismos estatales, nacionales o internacionales públicos de derechos humanos, instituciones u organizaciones\nLey de Víctimas para el Estado de Baja California. Página 47 relacionada con la atención, asistencia, justicia; verdad y reparación a las víctimas. Los recursos destinados para tal efecto deberán ser públicos, monitoreables y de fácil acceso para la sociedad civil.\nSe deberá procurar en todo momento, además de la especialización técnica y científica, el aporte de los grupos de víctimas y organizaciones de base que trabajen directamente con víctimas.\nSECCIÓN IV\nDE LA ATENCIÓN INTEGRAL\nDE PRIMER CONTACTO\nARTÍCULO 93.- En la prestación de los servicios de primer contacto con la población y las víctimas, la Comisión Estatal brindara orientación sobre los derechos, procedimientos, servicios y mecanismos de garantía contemplados en esta Ley, así como los servicios urgentes de ayuda inmediata, asistencia, acompañamiento y atención en materia psicosocial, médica y de trabajo social.\nARTÍCULO 94.- La Comisión deberá establecer los mecanismos de coordinación con los Ayuntamientos del Estado, a efecto de que se cuente en cada Municipio de la entidad con la prestación de servicios de atención inmediata en casos urgentes.\nARTÍCULO 95.- La prestación de servicios de primer contacto consistirá en:\nI.- Recibir y escuchar a cualquier persona que manifieste haber sido víctima de algún delito o violación de sus derechos humanos, aplicando siempre el principio de buena fe, y proporcionarle la atención adecuada al caso que presente. Si la persona quejosa ha sido afectada por algún hecho ilícito del fuero común y no ha presentado denuncia, se le deberá acompañar ante el Ministerio Público para que éste inicie la investigación procedente; si el delito fuere de competencia federal, se turnará a la autoridad competente; si no existiera delito o violación de derechos humanos, se asesorará a la persona para que reciba la atención de la dependencia correspondiente y, si existiera duda en el caso, se turnará al Comité interdisciplinario Evaluador para su análisis y dictamen.\nII.- Asegurarse de que todas las víctimas de delitos fuero común que sean ingresadas en el Registro Estatal de Víctimas, se les ofrezcan de manera gratuita los servicios y atenciones que prestan las autoridades del Sistema Estatal, conforme a las particularidades de cada caso.\nIII.- Tramitar ante las autoridades judiciales y administrativas correspondientes, las medidas de protección, ayuda, asistencia y atención que sean pertinentes para la salvaguarda de los derechos de las víctimas, y\nLey de Víctimas para el Estado de Baja California. Página 48\nIV.- Vigilar que se cumplan las medidas de ayuda, asistencia y atención contempladas en esta Ley y en la Ley General de Víctimas.\nARTÍCULO 96.- En materia de ayuda, asistencia y atención médica, la prestación de sistema, lo siguiente:\nI.- Diagnósticos médicos de urgencia;\nII.- Suministro de medicamentos para control de urgencias;\nIII.- Traslado de emergencia para hospitalización;\nIV.- Exámenes médicos en casos de personas que hayan sido víctimas de delitos sexuales;\nV.- Solicitar reportes sobre el estado médico de la víctima y la interpretación de los resultados, y\nVI.- Gestionar la atención médica requerida no disponible en dependencias estatales para que se otorgue en otras instituciones.\nARTÍCULO 97.- En materia de ayuda, asistencia y atención psicológica, la prestación de servicios de primer contacto, brindara directamente o a través de las autoridades del sistema, lo siguiente:\nI.- Atención psicológica de contención en situaciones de crisis o emergencia;\nII.- Terapia psicológica a las víctimas directas e indirectas por el tiempo que se requiera;\nIII.- Canalización de la víctima para su atención psiquiátrica, de acuerdo con la gravedad del caso;\nIV.- Acompañamientos psicosociales durante procesos administrativos o judiciales, y\nV.- Las que se señalen en el reglamento y protocolos aplicables.\nARTÍCULO 98.- En materia de ayuda, asistencia y orientación social, la prestación sistema, lo siguiente:\nLey de Víctimas para el Estado de Baja California. Página 49\nI.- Orientación para diseñar y desarrollar conjuntamente estrategias de desarrollo personalizadas,\nII.- Apoyo en la gestión y canalización a las instituciones competentes para cada una de las necesidades y requerimientos de la víctima;\nIII.- Orientación para ingresar al Registro Estatal de Víctimas y recibir la atención de la Asesoría Jurídica o ser atendida por cualquiera otra institución;\nIV.- Información para que se proporcionen las medidas de ayuda y asistencia inmediatas en materias económica, de protección, traslados de emergencia, alojamiento temporal en albergues para víctimas, apoyos para gastos funerarios de emergencia, para ingreso y permanencia en los servicios educativos y las demás que requieran las víctimas en los términos de esta Ley;\nV.- Acompañamientos a víctimas ante instituciones que puedan contribuir a la atención de sus casos, y\nVI.- Las que se señalen en el reglamento y ordenamientos aplicables.\nARTÍCULO 99.- Los servicios médicos, psicológicos y de trabajo social que se brinden por parte de los servicios de primer contacto a las víctimas en atención de urgencias, no sustituirán los derechos y medidas de atención, ayuda y asistencia que establece esta Ley y la Ley General.\nSECCIÓN V\nDEL COMITÉ INTERDISCIPLINARIO EVALUADOR\nARTÍCULO 100.- El Comité Interdisciplinario Evaluador es el área técnica de la víctimas en el Registro Estatal y de elaborar opiniones de reparación, para que sean aprobados por la Comisión Ejecutiva.\nARTÍCULO 101.- Son atribuciones del Comité Interdisciplinario Evaluador:\nI.- Solicitar el esclarecimiento de aspectos dudosos en las solicitudes de inscripción de víctimas al Registro.\nII.- Solicitar información complementaria a las Instituciones del Sistema Estatal, información que se incorporará al Registro.\nLey de Víctimas para el Estado de Baja California. Página 50\nIII.- Elaborar los dictámenes de ingreso al Registro y emitir las constancias respectivas.\nIV.- Elaborar la opinión en caso de cancelación del registro de alguna víctima.\nV.- Analizar las solicitudes de inscripción, la información de las declaraciones y el expediente de la víctima respecto del hecho victimizante, y remitirla a los titulares de la\nAsesoría Jurídica y el Registro para que adopten las acciones conducentes por cuanto a medidas de apoyo y reparación.\nVI.- Emitir el proyecto de dictamen sobre la procedencia o no, de las compensaciones subsidiaria a las víctimas.\nCAPÍTULO V\nREGISTRO ESTATAL DE VÍCTIMAS\nSECCIÓN I\nDEL REGISTRO ESTATAL DE VÍCTIMAS EN GENERAL\nARTÍCULO 102.- El Registro Estatal es el mecanismo administrativo y técnico que soporta todo el proceso de ingreso y registro de las víctimas del delito y de violaciones de derechos humanos al Sistema Estatal, creado en esta Ley.\nEl Registro Estatal constituye un soporte fundamental para garantizar que las víctimas tengan un acceso oportuno y efectivo a las medidas de ayuda, asistencia, atención, acceso a la justicia y reparación previstas en esta Ley.\nEI Registro será una unidad administrativa de la Comisión Ejecutiva Estatal y contará con un titular designado por Comisionado Ejecutivo. de víctimas, a nivel estatal, e inscribir los datos de las víctimas del delito y de violaciones a derechos humanos y retroalimentar el del orden federal.\nARTÍCULO 103.- El Registro Estatal será integrado por las siguientes fuentes:\nI.- Las solicitudes de ingreso hechas directamente por las víctimas del delito y de violaciones de derechos humanos, a través de su representante legal o de algún familiar o persona de confianza ante la Comisión Ejecutiva Estatal;\nII.- Las solicitudes de ingreso que presenten cualquiera de las autoridades y particulares señalados en el Artículo 105 de esta Ley.\nLey de Víctimas para el Estado de Baja California. Página 51\nCuando la víctima sea mayor de 12 años podrá solicitar su ingreso al registro por sí correspondientes.\nIII.- Los registros de víctimas existentes al momento de la entrada en vigor de la presente Ley, que se encuentren en cualquier institución o entidad del ámbito estatal o municipal, así como de la Comisión Estatal de Derechos Humanos del Estado en aquellos casos en donde se hayan dictado recomendaciones, medidas precautorias o bien se hayan celebrado acuerdos de conciliación.\nLas entidades e instituciones generadoras y usuarias de la información sobre las víctimas y que posean actualmente registros de víctimas, pondrán a disposición del Registro\nEstatal la información que generan y administran, de conformidad con lo establecido en los ordenamientos que regulan el manejo de datos personales, para lo cual se suscribirán los respectivos acuerdos de confidencialidad para el uso de la información.\nARTÍCULO 104.- Las solicitudes de ingreso se realizarán de manera personal y directa por la víctima, o a través de representante, y en forma totalmente gratuita ante la\nComisión Ejecutiva Estatal. Las solicitudes derivadas de delitos federales o de violaciones donde participen autoridades federales, serán remitidas a la Comisión Ejecutiva del Sistema\nNacional.\nLa información que acompaña la incorporación de datos al registro se consignará en el formato único de declaración diseñado por la Comisión Ejecutiva en los términos previstos en la Ley General.\nLa solicitud de inscripción de la víctima no implica de oficio su ingreso al Registro\nEstatal. Para acceder a las medidas de atención, asistencia y reparación previstos en esta\nLey, deberá realizarse el ingreso y valoración conforme a lo dispuesto en la presente Ley. directa por la víctima, o a través de representante que, además de cumplir con las disposiciones aplicables, esté debidamente inscrito en el padrón de representantes que al disposiciones reglamentarias correspondientes.\nARTÍCULO 105.- Conforme a la Ley General, para inscribir datos de la víctima en el\nRegistro Estatal se deberá, como mínimo, tener la siguiente información:\nI.- Los datos de identificación de cada una de las víctimas que solicitan su ingreso o en cuyo nombre se solicita el ingreso. En caso que la víctima por cuestiones de seguridad\nLey de Víctimas para el Estado de Baja California. Página 52 solicite que sus datos personales no sean públicos, se deberá asegurar la confidencialidad de sus datos. En caso de que se cuente con ella, se deberá mostrar una identificación oficial;\nII.- En su caso, el nombre completo, cargo y firma del servidor público de la entidad dependencia;\nIII.- La firma y huella dactilar de la persona que solicita el registro; en los casos que la persona manifieste no poder o no saber firmar, se tomará como válida la huella dactilar;\nIV.- Las circunstancias de modo, tiempo y lugar previas, durante y posteriores a la ocurrencia de los hechos victimizantes;\nV.- El funcionario que recabe la declaración la asentará en forma textual, completa y detallada en los términos que sea emitida;\nVI.- Los datos de contacto de la persona que solicita el registro, y\nVII.- La información del parentesco o relación afectiva con la víctima de la persona que solicita el registro, cuando no es la víctima quien lo hace. En caso que el ingreso lo solicite un servidor público deberá detallarse nombre, cargo y dependencia o institución a la que pertenece.\nEn el caso de faltar información, la Comisión Ejecutiva Estatal pedirá a la entidad que tramitó inicialmente la inscripción de datos, que complemente dicha información en el plazo máximo de diez días hábiles. Lo anterior no afecta, en ningún sentido, la garantía de los derechos de las víctimas que solicitaron en forma directa al Registro Estatal o en cuyo nombre el ingreso fue solicitado.\nARTÍCULO 106.- Será responsabilidad de las entidades e instituciones competentes para atender debidamente las solicitudes de ingreso al Registro Estatal:\nI.- Garantizar que los solicitantes sean atendidos de manera preferencial y orientadas de forma digna y respetuosa;\nII.- Para las solicitudes de ingreso en el Registro Estatal tomadas en forma directa, diligenciar correctamente, en su totalidad y de manera legible, el formato único de declaración diseñado conforme a la presente Ley;\nIII.- Disponer de los medios tecnológicos y administrativos necesarios para la toma de la declaración, de acuerdo con los parámetros determinados en los términos previstos en la presente Ley y en Ley General;\nLey de Víctimas para el Estado de Baja California. Página 53\nIV.- Remitir el original de las declaraciones tomadas en forma directa, el siguiente día hábil a la toma de la declaración a la Comisión Ejecutiva Estatal;\nV.- Orientar a la persona que solicite el ingreso sobre el trámite y efectos de la diligencia;\nVI.- Recabar la información necesaria sobre las circunstancias de tiempo, modo y lugar que generaron el hecho victimizante, así como su caracterización socioeconómica, con el propósito de contar con información precisa que facilite su valoración, de conformidad con el principio de participación conjunta consagrado en esta Ley;\nVII.- Indagar las razones por las cuales no se llevó a cabo con anterioridad la solicitud de registro;\nVIII.- Verificar los requisitos mínimos de legibilidad en los documentos aportados por el declarante y relacionar el número de folios que se adjunten con la declaración;\nIX.- Garantizar la confidencialidad, reserva y seguridad de la información y abstenerse de hacer uso de la información contenida en la solicitud de registro o del proceso de diligenciamiento para obtener provecho para sí o para terceros, o por cualquier uso ajeno a lo previsto en esta Ley, la Ley General y a las relativas a la Protección de Datos\nPersonales;\nX.- Entregar una copia o recibo o constancia de su solicitud de registro a las víctimas\nXI.- Cumplir con las demás obligaciones que determine la Comisión Ejecutiva\nEstatal.\nBajo ninguna circunstancia la autoridad podrá negarse a recibir la solicitud de registro a las víctimas a que se refiere la presente Ley.\nARTÍCULO 107.- Presentada la solicitud, deberá ingresarse la misma al Registro\nEstatal, y se procederá a la valoración de la información recogida en el formato único junto con la documentación remitida que acompañe dicho formato.\nPara mejor proveer, la Comisión Ejecutiva Estatal podrá solicitar la información que consideren necesaria a cualquiera de las autoridades del orden federal, local y municipal, las que estarán en el deber de suministrarla en un plazo que no supere los diez días hábiles.\nEjecutiva Estatal. En caso de hechos probados o de naturaleza pública deberá aplicarse el principio de buena fe a que hace referencia esta Ley y la Ley General.\nLey de Víctimas para el Estado de Baja California. Página 54 anteriores, no suspende, en ningún caso, las medidas de ayuda de emergencia a las que tiene derecho la víctima.\nNo se requerirá la valoración de los hechos de la declaración cuando:\nI.- Exista sentencia condenatoria o resolución por parte de la autoridad jurisdiccional o administrativa competente;\nII.- Exista una determinación de la Comisión Nacional de los Derechos Humanos o de la Comisión Estatal de Derechos Humanos del Estado, incluidas recomendaciones, conciliaciones o medidas precautorias;\nIII.- La víctima haya sido reconocida como tal por el Ministerio Público, por una autoridad judicial, o por un organismo público de derechos humanos, aun cuando no se haya dictado sentencia o resolución;\nIV.- Cuando la víctima cuente con informe que le reconozca tal carácter emitido por algún mecanismo internacional de protección de derechos humanos al que México le reconozca competencia, y\nV.- Cuando la autoridad responsable de la violación a los derechos humanos le reconozca tal carácter.\nARTÍCULO 108.- Se podrá cancelar la inscripción en el Registro Estatal cuando, después de realizada la valoración contemplada en el Artículo 107, incluido haber escuchado a la víctima o a quien haya solicitado la inscripción, la Comisión Ejecutiva Estatal encuentre que la solicitud de registro es contraria a la verdad respecto de los hechos victimizante de tal forma que sea posible deducir que la persona no es víctima.\nLa decisión que cancela el ingreso en el Registro Estatal deberá ser fundada y motivada. Deberá notificarse personalmente y por escrito a la víctima o a su representante legal, con el fin de que la víctima pueda interponer, si lo desea, recurso de reconsideración de la decisión ante la Comisión Ejecutiva Estatal para que ésta sea aclarada, modificada, presente Ley.\nLa notificación se hará en forma directa. En el caso de no existir otro medio más dirección, al número de fax o al correo electrónico que figuren en el formato único de declaración o en los demás sistemas de información, a fin de que comparezca a la diligencia de notificación personal.\nLey de Víctimas para el Estado de Baja California. Página 55\nARTÍCULO 109.- La información sistematizada en el Registro Estatal incluirá:\nI.- El relato del hecho victimizante, como quedó registrado en el formato único de declaración. El relato inicial se actualizará en la medida en que se avance en la respectiva\nII.- La descripción del daño sufrido;\nIII.- La identificación del lugar y la fecha en donde se produjo el hecho victimizante;\nIV.- La identificación de la víctima o víctimas del hecho victimizante;\nV.- La identificación de la persona o entidad que solicitó el registro de la víctima, cuando no sea ella quien lo solicite directamente;\nVI.- La identificación y descripción detallada de las medidas de ayuda y de atención que efectivamente hayan sido garantizadas a la víctima;\nVII.- La identificación y descripción detallada de las medidas de reparación que, en su caso, hayan sido otorgadas a la víctima, y\nVIII.- La identificación y descripción detallada de las medidas de protección que, en su caso, se hayan brindado a la víctima.\nARTÍCULO 110.- La Comisión Ejecutiva Estatal elaborará un plan de divulgación, capacitación y actualización sobre el procedimiento para la recepción de la declaración y su trámite hasta la decisión de inclusión o no en el Registro Estatal. Las entidades encargadas de recibir y tramitar la inscripción de datos en el Registro garantizarán la implementación de este plan en los respectivos órdenes estatal y municipal.\nSECCIÓN II\nINGRESO DE LA VÍCTIMA AL REGISTRO ESTATAL\nARTÍCULO 111.- El ingreso de la víctima al Registro Estatal se hará por la denuncia, la queja, o la noticia de hechos que podrá realizar la propia víctima, la autoridad, la Comisión hechos, aportando los elementos que tengan.\nARTÍCULO 112.- Todo servidor público del Estado y sus municipios que tenga contacto con la víctima, estará obligado a orientarla para llenar el formato único de registro.\nEl Ministerio Público, los defensores públicos, los asesores jurídicos de las víctimas y la\nLey de Víctimas para el Estado de Baja California. Página 56 único de registro.\nPárrafo Reformado\nCuando los servidores públicos competentes no se encuentren accesibles, disponibles o se nieguen a auxiliar a la víctima en el llenado del formato único, la víctima o su representante podrán acudir a cualquier otra autoridad estatal o municipal, las cuales tendrán el deber de apoyarla, entre las cuales, en forma enunciativa y no limitativa, se señalan las siguientes:\nI.- Fiscalía General del Estado de Baja California;\nFracción Reformada\nII.- La Comisión Estatal de Derechos Humanos del Estado;\nIII.- El Sistema Estatal para el Desarrollo Integral de la Familia del Estado;\nIV.- Las instituciones de salud y educación, ya sean públicas o privadas;\nV.- Los Institutos de Mujeres;\nVI.- Los Albergues;\nVII.- La Defensoría Pública, y\nVIII.- Los Síndicos municipales que corresponda.\nArtículo Reformado\nARTÍCULO 113.- Una vez recibida la denuncia o queja la autoridad inmediata deberá ponerla en conocimiento del Registro Estatal, en un término que no excederá de veinticuatro horas, a fin de que se lleve a cabo el registro.\nEn el caso de las personas que se encuentren bajo custodia del Estado, las autoridades que estén a cargo de los centros de readaptación social, estarán obligados de recibir la denuncia y queja mencionada en el párrafo anterior.\nARTÍCULO 114.- Cuando un servidor público, en especial los que tienen la obligación de tomar la denuncia de la víctima sin ser autoridad ministerial o judicial, tenga conocimiento de un hecho de violación a los derechos humanos, como: tortura, tratos crueles, inhumanos o degradantes, detención arbitraria, desaparición forzada, ejecución arbitraria, violencia sexual, deberá denunciarlo de inmediato.\nARTÍCULO 115.- El reconocimiento de la calidad de víctima, para efectos de esta\nLey, se realiza por las determinaciones de cualquiera de las siguientes autoridades:\nLey de Víctimas para el Estado de Baja California. Página 57\nI.- El juzgador penal, mediante sentencia ejecutoriada;\nII.- El juzgador penal o de paz que tiene conocimiento de la causa;\nIII.- El juzgador en materia de amparo, civil o familiar que tenga los elementos para acreditar que el sujeto es víctima;\nIV.- Los organismos públicos de protección de derechos humanos;\nV.- Los organismos internacionales de protección de derechos humanos a los que\nMéxico les reconozca competencia;\nVI.- La autoridad responsable de la violación a los derechos humanos que le reconozca tal carácter;\nVII.- La Comisión Estatal Ejecutiva; y\nVIII.- El Ministerio Público.\nEl reconocimiento de la calidad de víctima tendrá como efecto que la víctima pueda acceder a los recursos del Fondo Estatal y a la reparación de conformidad con lo previsto en la presente Ley, en la Ley General y demás disposiciones reglamentarias.\nARTÍCULO 116.- El reconocimiento de la calidad de víctima tendrá como efecto:\nI.- El acceso a los derechos, garantías, acciones, mecanismos y procedimientos, en los términos de esta Ley, la Ley General y las disposiciones reglamentarias, y\nII.- En el caso de lesiones graves, delitos contra la libertad y seguridad sexual, violencia familiar, trata de personas, secuestro, tortura, tratos crueles, inhumanos o degradantes, desaparición, privación de la libertad y todos aquellos que impidan a la víctima por la naturaleza del daño atender adecuadamente la defensa de sus derechos; que el juez de la causa o la autoridad responsable del procedimiento, de inmediato, suspendan todos caducidad, así como todos los efectos que de éstos se deriven, en tanto su condición no sea superada, siempre que se justifique la imposibilidad de la víctima de ejercer adecuadamente sus derechos en dichos juicios y procedimientos.\nAl reconocerse su calidad de víctima, ésta podrá acceder a los recursos del Fondo sus disposiciones reglamentarias.\nLey de Víctimas para el Estado de Baja California. Página 58\nTÍTULO SÉPTIMO\nDE LA DISTRIBUCIÓN DE COMPETENCIAS\nCAPÍTULO I\nDE LAS AUTORIDADES EN GENERAL\nARTÍCULO 117.- Los distintos órdenes de gobierno, coadyuvarán para el cumplimiento de los objetivos de esta Ley, de conformidad con las competencias previstas en la Ley General.\nARTÍCULO 118.- Las autoridades responsables de implementar y dar cumplimiento a las disposiciones de la presente Ley son:\nI.- En el ámbito estatal:\na) Poder Ejecutivo del Estado;\nInciso Reformado\nb) La Comisión Ejecutiva Estatal;\nc) La Secretaría General de Gobierno;\nd) La Secretaría de Salud;\nInciso Reformado\ne) La Secretaría de Seguridad Ciudadana;\nInciso Reformado\nf) La Secretaría de Educación;\nInciso Reformado\ng) La Secretaría de Bienestar;\nInciso Reformado\nh) El Sistema Estatal para el Desarrollo Integral de la Familia, e\nInciso Reformado\ni) El Instituto de la Mujer.\nFracción Reformada\nII.- En el ámbito municipal:\na) Los Ayuntamientos;\nb) Las Presidencias Municipales;\nInciso Reformado\nLey de Víctimas para el Estado de Baja California. Página 59\nc) Los Síndicos Municipales;\nd) Los Sistemas Municipales para el Desarrollo Integral de la Familia, y\ne) Las instituciones de seguridad pública municipales.\nFracción Reformada\nIV.- La Comisión Estatal de Derechos Humanos.\nV.- Fiscalía General del Estado.\nFracción Adicionada\nDe igual manera, se regirán por esta Ley las actividades de las instituciones, organismos o asociaciones privadas o sociales, cuyas actividades impliquen velar por la protección de las víctimas, al proporcionarles servicios de ayuda, asistencia o reparación.\nArtículo Reformado\nCAPÍTULO II\nDEL PODER EJECUTIVO DEL ESTADO\nSECCÍON I\nDE LAS FACULTADES DEL PODER EJECUTIVO DEL ESTADO\nARTÍCULO 119.- Conforme a esta Ley y la Ley General, corresponde al Gobernador del Estado:\nI.- Instrumentar y articular sus políticas públicas en concordancia con la política nacional integral, para la adecuada atención y protección a las víctimas;\nII.- Ejercer sus facultades reglamentarias para la aplicación de la presente Ley;\nIII.- Coadyuvar en la adopción y consolidación del Sistema Nacional y presidir el\nSistema Estatal;\nIV.- Participar en la elaboración del Programa Nacional y del Programa Estatal;\nV.- Fortalecer e impulsar la creación de las instituciones públicas y privadas que prestan atención a las víctimas;\nLey de Víctimas para el Estado de Baja California. Página 60 atención, educación, capacitación, investigación y cultura de los derechos humanos de las víctimas de acuerdo con el Programa;\nVII.- Impulsar programas locales para el adelanto y desarrollo de las mujeres y mejorar su calidad de vida;\nVIII.- Impulsar la creación de refugios para las víctimas conforme al modelo de atención diseñado por el Sistema Nacional;\nIX.- Promover programas de información a la población en la materia;\nX.- Impulsar programas reeducativos integrales de los imputados;\nXI.- Difundir por todos los medios de comunicación el contenido de esta Ley;\nXII.- Rendir ante el Sistema un informe anual sobre los avances de los programas locales;\nXIII.- Revisar y evaluar la eficacia de las acciones, las políticas públicas, los programas estatales, con base en los resultados de las investigaciones que al efecto se realicen;\nXIV.- Impulsar la participación de las organizaciones privadas dedicadas a la promoción y defensa de los derechos humanos, en la ejecución de los programas estatales;\nXV.- Recibir de las organizaciones privadas, las propuestas y recomendaciones sobre atención y protección de las víctimas, a fin de mejorar los mecanismos en la materia;\nXVI.- Proporcionar a las instancias encargadas de realizar estadísticas, la información necesaria para la elaboración de éstas;\nXVII.- Impulsar reformas, en el ámbito de su competencia, para el cumplimiento de los objetivos de la presente Ley, y\nXVIII.- Celebrar convenios de cooperación, coordinación y concertación en la materia, y aplicables a la materia, que les conceda la Ley General u otros ordenamientos legales.\nSECCIÓN II\nLey de Víctimas para el Estado de Baja California. Página 61\nARTÍCULO 120.- Corresponde a la Secretaría General de Gobierno, en lo concerniente a la aplicación de esta Ley, el ejercicio de las atribuciones siguientes: necesario para el cumplimiento de la presente Ley;\nII.- Coadyuvar en la ejecución de las medidas precautorias o cautelares decretadas conforme a la presente Ley, en todo aquello que se relacione con el ámbito de su competencia, garantizando la confidencialidad y reserva de esta información;\nIII.- Coordinar la participación de las instituciones de asistencia privada o social cuyos fines se relacionen con el auxilio, ayuda o asistencia de la víctima u ofendido del delito;\nIV.- Resolver cualquier conflicto de competencia que se presente entre las dependencias u organismos del Poder Ejecutivo del Estado, con motivo de la aplicación de la presente Ley;\nV.- Otorgar a la autoridad judicial, dentro de su competencia, el auxilio que le soliciten para el debido ejercicio de las funciones inherentes a la presente Ley, y\nVI.- Las demás que señalen esta Ley y otras disposiciones legales aplicables en la materia.\nSECCIÓN III\nFACULTADES DEL MINISTERIO PÚBLICO\nARTÍCULO 121.- Corresponde al Ministerio Público, además de los deberes establecidos en el presente ordenamiento, lo siguiente:\nI.- Informar a la víctima, desde el momento en que se presente o comparezca ante él, los derechos que le otorga la Constitución y los Tratados Internacionales celebrados y ratificados por el Estado Mexicano, el código penal y procesal penal respectivo y las demás disposiciones aplicables, así como el alcance de esos derechos, debiendo dejar constancia escrita de la lectura y explicación realizada;\nII.- Vigilar el cumplimiento de los deberes consagrados en esta Ley, en especial el deber legal de búsqueda e identificación de víctimas desaparecidas;\nIII.- Solicitar el embargo precautorio de los bienes susceptibles de aplicarse a la reparación del daño sufrido por la víctima, así como el ejercicio de otros derechos;\nLey de Víctimas para el Estado de Baja California. Página 62\nIV.- Solicitar las medidas cautelares o de protección necesarias para la protección de la víctima, sus familiares y/o sus bienes, cuando sea necesario;\nV.- Solicitar las pruebas conducentes a fin de acreditar, determinar y cuantificar el daño de la víctima, especificando lo relativo a daño moral y daño material;\nVI.- Dirigir los estudios patrimoniales e investigaciones pertinentes a fin de determinar la existencia de bienes susceptibles de extinción de dominio;\nVII.- Solicitar la reparación del daño;\nVIII.- Informar sobre las medidas alternativas de resolución de conflictos que ofrece la Ley a través de instituciones como la conciliación y la mediación, y a garantizar que la opción y ejercicio de las mismas se realice con pleno conocimiento y absoluta voluntariedad;\nIX.- Cuando los bienes asegurados sean puestos bajo la custodia de la víctima o le sean devueltos, deberá informar claramente a ésta los alcances de dicha situación, y las consecuencias que acarrea para el proceso;\nX.- Cuando se entregue a la víctima el cuerpo o restos humanos del familiar o personas cercanas, y no haya causado ejecutoria, le deberán informar que pesa sobre ella el deber de no someter los mismos a cremación. Dicho deber sólo puede ser impuesto a la víctima en aras de hacer efectivo su derecho a la verdad y a la justicia, y\nXI.- Las demás acciones que establezcan las disposiciones jurídicas aplicables en materia de atención integral a víctimas y reparación.\nSECCIÓN IV\nFACULTADES DE LA SECRETARÍA DE SEGURIDAD CIUDADANA\nDenominación Modificada\nARTÍCULO 122.- Corresponde a la Secretaría de Seguridad Ciudadana del Estado, en lo concerniente a la aplicación de esta Ley, el ejercicio de las atribuciones siguientes:\nPárrafo Reformado\nI.- Proporcionar a la víctima del delito, información sobre las instituciones públicas o privadas de seguridad que puedan proporcionarle atención;\nII.- Auxiliar con la fuerza pública a la autoridad judicial para el cumplimiento de la presente Ley;\nLey de Víctimas para el Estado de Baja California. Página 63\nIII.- Proporcionar custodia y protección a la víctima del delito y demás personas que intervienen en el procedimiento penal, en términos de lo dispuesto por la presente Ley y demás ordenamientos legales aplicables;\nIV.- Coordinar a la policía estatal y brindar apoyo a las corporaciones de policía municipal, en el cumplimiento de sus deberes en materia de asistencia, atención y protección de la víctima del delito, y demás personas que intervienen en el procedimiento penal; en términos de lo previsto por esta Ley y demás ordenamientos legales aplicables en la materia;\nV.- Ordenar que se cumplan las medidas de protección que se decreten a favor de personas privadas de su libertad que se encuentren internas en instituciones del Sistema\nEstatal Penitenciario, independientemente de la situación procesal en la que estos se encuentren; lo anterior, sin perjuicio de que las autoridades penitenciarias adopten las medidas adicionales que resulten procedentes en términos de la normatividad aplicable para garantizar la debida protección de la persona;\nFracción Reformada\nVI.- Promover la formación y especialización de los servidores públicos adscritos a las corporaciones policiacas del Estado y municipios, en el conocimiento de sus deberes en relación con la víctima u ofendido del delito, así como de las demás personas que intervienen en el procedimiento penal;\nVII.- Convenir con los Ayuntamientos todo lo necesario para la coordinación intermunicipal de sus funciones en materia de asistencia, atención y protección de la víctima del delito y demás personas que intervienen en el procedimiento penal, y\nVIII.- Las demás que señale esta Ley y otras disposiciones legales aplicables en la materia.\nArtículo Reformado\nSECCIÓN V\nFACULTADES DE LA SECRETARÍA DE SALUD\nARTÍCULO 123.- Corresponde a la Secretaría de Salud, en lo concerniente a la aplicación de esta Ley, el ejercicio de las atribuciones siguientes:\nI.- Proporcionar a la víctima del delito los servicios de atención de emergencia médica, odontológica, quirúrgica y hospitalaria, en términos de lo dispuesto por la presente\nLey y demás ordenamientos legales aplicables;\nII.- Otorgar a la víctima del delito el tratamiento psicológico especializado que requieran como apoyo para el restablecimiento de su integridad emocional;\nLey de Víctimas para el Estado de Baja California. Página 64\nIII.- Promover y coordinar la participación de las instituciones de salud del sector público, privado o social, en la prestación de servicios a la víctima u ofendido del delito, en términos de la normatividad aplicable;\nIV.- Coordinar y vigilar las acciones a cargo de las instituciones, entidades y organismos del sector salud en la Entidad, en todo lo concerniente a la atención y asistencia a víctimas del delito;\nV.- Impulsar la suscripción de acuerdos o convenios dentro del ámbito de salud, con instituciones privadas y sociales, para facilitar el acceso de las víctimas del delito a los servicios prestados por éstas, en términos de la normatividad aplicable;\nVI.- Otorgar a la víctima del delito el carnet que lo identifique como derechohabiente de los servicios de salud en el Estado, en el caso de que éstos no cuenten con la prestación de los servicios por otra institución, a fin de que se le proporcione la atención y servicios que requiera para atender a las consecuencias que el hecho delictivo haya provocado en su salud física o mental;\nVII.- Proporcionar a la víctima del delito la información y asesoría que requieran para conocer sus derechos en lo relacionado con el ámbito de su competencia, así como los servicios que puedan recibir, los requisitos y procedimientos para obtenerlos, y\nVIII.- Las demás que señale esta Ley y otras disposiciones legales aplicables en la materia.\nSECCIÓN VI\nFACULTADES DE LA SECRETARÍA DE EDUCACIÓN\nDenominación Modificada\nARTÍCULO 124.- Corresponde a la Secretaria de Educación, en lo concerniente a la aplicación de esta Ley, el ejercicio de las atribuciones siguientes:\nPárrafo Reformado\nI.- Promover la incorporación de contenidos temáticos con perspectiva de los derechos de la víctima del delito, en los programas de educación de su competencia;\nII.- Proporcionar a la víctima las facilidades necesarias para que acceda a los servicios educativos de los niveles preescolar, primaria y secundarias en instituciones del sector público del Estado, cuando a consecuencia del delito se haya visto en la necesidad de interrumpir sus estudios;\nIII.- Exentar a la víctima del delito de los costos académicos en las instituciones públicas de educación preescolar, primaria y secundaria a cargo del Estado, por el tiempo\nLey de Víctimas para el Estado de Baja California. Página 65 estrictamente necesario para que pueda superar los efectos del delito, en los casos en que como consecuencia del delito la víctima haya perdido su capacidad económica para ello;\nIV.- Solicitar la colaboración de las instituciones particulares que cuenten con autorización o con reconocimiento de validez oficial de estudios de preescolar, primaria y secundaria, para que presten gratuitamente sus servicios a la víctima del delito o sus hijos menores de edad, en términos de lo legalmente procedente;\nV.- Entregar paquetes escolares y uniformes a los niños, niñas y adolescentes que tengan el carácter de víctimas del delito, para garantizar su participación en el sistema educativo bajo condiciones dignas, por el tiempo estrictamente necesario para que superen las consecuencias del delito, en los casos en que como consecuencia del delito la víctima haya perdido su capacidad económica para ello;\nVI.- Gestionar ante la Secretaría de Educación Pública lo conducente para que la víctima del delito o sus hijos menores de edad, tengan acceso a los libros de texto gratuitos y demás materiales educativos complementarios que ésta proporcione;\nVII.- Establecer apoyos para que las víctimas puedan participar en procesos de selección, admisión y matrícula en programas académicos ofrecidos por instituciones públicas del sistema educativo del Estado, incluyendo la posibilidad de exentarles del pago de formulario de inscripción y derechos de grado, en los casos en que como consecuencia del delito la víctima haya perdido su capacidad económica para ello, y\nVIII.- Las demás que señale esta Ley y otras disposiciones legales aplicables en la materia.\nArtículo Reformado\nSECCIÓN VII\nFACULTADES DE LA SECRETARÍA DE BIENESTAR\nDenominación Modificada\nARTÍCULO 125.- Corresponde a la Secretaría de Bienestar en lo concerniente a la aplicación de esta Ley, el ejercicio de las atribuciones siguientes:\nPárrafo Reformado\nI.- Proporcionar a la víctima las facilidades necesarias para que pueda acceder a los beneficios de los programas de desarrollo social con los que cuente la Dependencia, consecuencia del hecho victimizante;\nII.- Proporcionar a la víctima información sobre las reglas de acceso, operación, recursos y cobertura de los programas institucionales con los que cuente, proporcionándole la asesoría y facilidades a su alcance para propiciar su incorporación a los mismos, y\nLey de Víctimas para el Estado de Baja California. Página 66\nIII.- Las demás que señale esta Ley y otras disposiciones legales aplicables en la materia.\nArtículo Reformado\nSECCIÓN VIII\nFACULTADES DEL SISTEMA ESTATAL PARA EL\nDESARROLLO INTEGRAL DE LA FAMILIA\nARTÍCULO 126.- Corresponde al Sistema Estatal para el Desarrollo Integral de la\nFamilia, en lo concerniente a la aplicación de esta Ley, el ejercicio de las atribuciones siguientes:\nI.- Proporcionar a la víctima del delito alojamiento y alimentación en condiciones de seguridad y dignidad, cuando ésta, como consecuencia del delito, se encuentre en especial condición de vulnerabilidad, amenazada o desplazada de su lugar de residencia.\nEstos servicios se brindarán solamente durante el tiempo que sea estrictamente necesario para garantizar que la víctima supere las condiciones de emergencia y pueda retornar libremente a su hogar en condiciones seguras;\nII.- Velar por la seguridad e integridad de las víctimas que se encuentren alojados en los refugios a su cargo;\nIII.- Impulsar la creación de refugios para la víctima, conforme al modelo de atención que para tal efecto se diseñe;\nIV.- Canalizar a la víctima hacia las instituciones que puedan prestarle ayuda, atención y protección especializada, en los casos en que no cuente con la posibilidad de brindarle directamente los servicios legalmente a su cargo;\nV.- Proporcionar a la víctima la atención necesaria para su recuperación física y psicológica, durante el tiempo de su alojamiento;\nVI.- Implementar programas y acciones destinadas a la prevención y erradicación de la violencia familiar, especialmente la ejercida contra niñas, niños, jóvenes, mujeres, indígenas, adultos mayores, y\nVII.- Las demás que señale esta Ley y otras disposiciones legales aplicables en la materia.\nSECCIÓN IX\nFACULTADES DEL INSTITUTO DE LA MUJER\nLey de Víctimas para el Estado de Baja California. Página 67\nARTÍCULO 127.- Corresponde al Instituto de la Mujer del Estado, en lo concerniente a la aplicación de esta Ley, el ejercicio de las atribuciones siguientes:\nI.- Otorgar, en el ámbito de su competencia, medidas especiales de protección para mujeres que hayan sido víctimas del delito, bajo un enfoque diferencial que atienda a su condición de integrantes de un grupo expuesto a un mayor riesgo;\nII.- Promover programas y acciones para la prevención de delitos sexuales cometidos contra una mujer;\nIII.- Contar con refugios para albergar en los casos necesarios a las mujeres víctimas del delito, conforme al modelo de atención que se diseñe, por el tiempo estrictamente necesario para superar la condición de urgencia;\nIV.- Canalizar a las mujeres víctimas del delito hacia las instituciones que puedan prestarle ayuda, atención y protección especializada, cuando no cuente con la posibilidad de brindarle directamente los servicios a su cargo;\nV.- Proporcionar a las mujeres víctimas del delito, la atención necesaria para su recuperación física y psicológica, durante el tiempo de su alojamiento;\nVI.- Recibir la declaración de mujeres que hayan sido víctimas del delito, en los casos en que el Ministerio Público no se encuentre accesible, disponible o se haya negado a recibírselas, en los términos establecidos por esta Ley y la Ley General;\nVII.- Impulsar programas para el adelanto y desarrollo de las mujeres víctimas del delito, que ayuden a mejorar su calidad de vida, y\nVIII.- Las demás que señale esta Ley y otras disposiciones legales aplicables en la materia.\nCAPÍTULO III\nDE LOS MUNICIPIOS\nSECCIÓN I\nFACULTADES DE LOS MUNICIPIOS\nARTÍCULO 128.- Corresponde a los municipios, de conformidad con esta Ley y la\nLey General, las atribuciones siguientes:\nI.- Instrumentar y articular, en concordancia con la política nacional y estatal, la política municipal, para la adecuada atención y protección a las víctimas;\nLey de Víctimas para el Estado de Baja California. Página 68 consolidación del Sistema Nacional y del Sistema Estatal; personas que atienden a víctimas;\nIV.- Ejecutar las acciones necesarias para el cumplimiento del Programa previsto en la Ley General y los programas previstos en esta Ley;\nV.- Apoyar la creación de programas de reeducación integral para los imputados;\nVI.- Apoyar la creación de refugios seguros para las víctimas;\nVII.- Participar y coadyuvar en la protección y atención a las víctimas;\nVIII.- Celebrar convenios de cooperación, coordinación y concertación en la materia,\nIX.- Las demás aplicables a la materia, que les conceda la Ley General u otros ordenamientos legales aplicables.\nSECCIÓN II\nFACULTADES DE LOS AYUNTAMIENTOS\nARTÍCULO 129.- Corresponde a los Ayuntamientos, en el ámbito de sus respectivas competencias, el cumplimiento de las siguientes atribuciones:\nI.- Impulsar la creación de políticas públicas destinadas a la atención y protección de la víctima u ofendido del delito, que sean acordes con la política nacional y estatal;\nII.- Incorporar dentro del bando de policía y gobierno, reglamentos, circulares y disposiciones administrativas de observancia general, las disposiciones necesarias para garantizar el respeto a los derechos de la víctima del delito, así como el cumplimiento de los deberes a cargo de la autoridad municipal en la materia;\nIII.- Ordenar las acciones procedentes para el cumplimiento de la presente Ley, del\nPrograma Estatal y de las demás disposiciones legales aplicables en la materia;\nIV.- Autorizar la celebración de convenios de cooperación, coordinación y concertación con las autoridades federales, estatales y municipales en lo concerniente a la atención, asistencia y protección de la víctima del delito, así como de las demás personas que intervienen en el procedimiento penal, y\nLey de Víctimas para el Estado de Baja California. Página 69\nV.- Las demás que les señale la Ley General de Víctimas, esta Ley y otras disposiciones legales aplicables en la materia.\nSECCIÓN III\nFACULTADES DE LOS PRESIDENTES MUNICIPALES\nARTÍCULO 130.- Corresponde a los Presidentes Municipales, en el ámbito de su competencia, el cumplimiento de las siguientes atribuciones:\nI.- Dar publicidad a las disposiciones de la presente Ley y demás ordenamientos legales aplicables en la materia, en todo aquello que resulte de observancia general dentro del ámbito municipal;\nII.- Cumplir y hacer cumplir a los servidores públicos municipales las disposiciones de la Ley General, de la presente Ley y de las demás disposiciones legales aplicables en la materia;\nIII.- Celebrar a nombre y por acuerdo del Ayuntamiento, los convenios de cooperación, coordinación y concertación para el mejor desempeño de las funciones y cumplimiento de las obligaciones que la Ley General, la presente Ley y las demás disposiciones legales aplicables en la materia;\nIV.- Vigilar y verificar la actuación de las dependencias y entidades municipales en lo relativo al correcto y oportuno ejercicio de sus funciones, así como del cumplimiento de los deberes que le impone la Ley General, la presente Ley y de las demás disposiciones legales aplicables en la materia;\nV.- Ordenar las acciones necesarias para el cumplimiento del Programa Estatal;\nVI.- Ordenar lo necesario para coadyuvar en las acciones de asistencia, protección y atención a la víctima del delito, y\nVII.- Las demás que señale la Ley General, esta Ley y otras disposiciones legales aplicables en la materia.\nSECCIÓN IV\nFACULTADES DE LOS SÍNDICOS MUNICIPALES\nARTÍCULO 131.- Corresponde a los Síndicos Municipales, dentro del ámbito de sus respectivas competencias, el cumplimiento de las siguientes atribuciones:\nI.- Recibir la declaración de la víctima del delito, en los casos en que el Ministerio\nPúblico no se encuentre accesible, disponible o se haya negado a recibírselas, debiendo\nLey de Víctimas para el Estado de Baja California. Página 70 recabar la narración de los hechos, detalles y elementos de prueba con los que cuente la víctima, haciéndolos constar en el formato único de declaración y dando cuenta de ello a la autoridad ministerial más inmediata, en los términos previstos por la Ley General, esta Ley y las demás disposiciones legales aplicables, y\nII.- Las demás que señale la Ley General, esta Ley y otras disposiciones legales y reglamentarias aplicables.\nSECCIÓN V\nDE LOS SISTEMAS MUNICIPALES PARA EL DESARROLLO\nINTREGRAL DE LA FAMILIA\nARTÍCULO 132.- Corresponde a los Sistemas Municipales para el Desarrollo\nIntegral de la Familia, en lo concerniente a la aplicación de esta Ley, el ejercicio de las atribuciones siguientes:\nI.- Coadyuvar con el Sistema Estatal para el Desarrollo Integral de la Familia, en el cumplimiento de las funciones inherentes a proporcionar a la víctima del delito alojamiento y alimentación, cuando ésta, como consecuencia del delito, se encuentre en especial condición de vulnerabilidad, amenazada o desplazada de su lugar de residencia; por el tiempo estrictamente necesario para garantizar que pueda superar las condiciones de emergencia y retornar libremente a su hogar en condiciones seguras;\nII.- Velar por la seguridad e integridad de las víctimas que se encuentren alojadas en los refugios a su cargo;\nIII.- Canalizar a la víctima hacia las instituciones que puedan prestarle ayuda, atención y protección especializada, en los casos en que no cuente con la posibilidad de brindarle directamente los servicios legalmente a su cargo;\nIV.- Proporcionar a la víctima la atención necesaria para su recuperación física y psicológica;\nV.- Implementar programas y acciones destinadas a la prevención y erradicación de la violencia familiar, especialmente la ejercida contra niñas, niños, jóvenes, mujeres, indígenas, adultos mayores que son víctimas del delito, y\nVI.- Las demás que le señale esta Ley y otras disposiciones legales aplicables en la materia.\nSECCIÓN VI\nFACULTADES DE LAS INSTITUCIONES DE\nSEGURIDAD PÚBLICA MUNICIPALES\nLey de Víctimas para el Estado de Baja California. Página 71\nARTÍCULO 133.- Corresponde a las instituciones de Seguridad Pública Municipal, en lo concerniente a la aplicación de esta Ley, el ejercicio de las atribuciones siguientes:\nI.- Proporcionar información a la víctima del delito, sobre sus derechos, requisitos y procedimientos para su ejercicio;\nII.- Auxiliar con la fuerza pública a la autoridad ministerial y judicial para el cumplimiento de las órdenes de protección y demás medidas y determinaciones que dicten en términos de la presente Ley;\nIII.- Proporcionar custodia y protección a la víctima del delito y demás personas que intervienen en el procedimiento penal, en términos de lo dispuesto por la presente Ley y demás ordenamientos legales aplicables;\nIV.- Coordinarse con la Secretaría de Seguridad Ciudadana del Estado para brindar apoyo a la víctima del delito y demás personas que intervienen en el procedimiento penal, en lo relativo a su asistencia, atención y protección;\nFracción Reformada\nV.- Promover la formación y especialización de los servidores públicos adscritos a sus corporaciones, en el conocimiento de sus deberes con relación a la asistencia, atención y protección de la víctima del delito, así como de las demás personas que intervienen en el procedimiento penal, y\nVI.- Las demás que señale esta Ley y otras disposiciones legales aplicables en la materia.\nArtículo Reformado\nCAPÍTULO IV\nDE LOS SERVIDORES PÚBLICOS\nARTÍCULO 134.- Todos los servidores públicos, desde el primer momento en que tengan contacto con la víctima, en el ejercicio de sus funciones y conforme al ámbito de su competencia, tendrán los siguientes deberes:\nI.- Identificarse oficialmente ante la víctima, detallando nombre y cargo que detentan;\nII.- Desarrollar con la debida diligencia las atribuciones reconocidas en esta Ley, en cumplimiento de los principios establecidos en la Ley General;\nIII.- Garantizar que se respeten y apliquen las normas e instrumentos internacionales de derechos humanos;\nLey de Víctimas para el Estado de Baja California. Página 72\nIV.- Tratar a la víctima con humanidad y respeto a su dignidad y sus derechos humanos;\nV.- Brindar atención especial a las víctimas para que los procedimientos reparación no generen un nuevo daño, violación, o amenaza a la seguridad y los intereses de la víctima, familiares, testigos o personas que hayan intervenido para ayudar a la víctima o impedir nuevas violaciones;\nVI.- Evitar todo trato o conducta que implique victimización secundaria o incriminación de la víctima;\nVII.- Brindar a la víctima orientación e información clara, precisa y accesible sobre sus derechos, garantías y recursos, así como sobre los mecanismos, acciones y procedimientos que se establecen o reconocen en esta Ley y en la Ley General;\nVIII.- Entregar en forma oportuna, rápida y efectiva, todos los documentos que requiera para el ejercicio de sus derechos;\nIX.- No obstaculizar ni condicionar el acceso de la víctima a la justicia y la verdad, así como a los mecanismos, medidas y procedimientos establecidos por la Ley General y esta Ley;\nX.- Presentar ante el Ministerio Público, o en su caso, ante la Comisión Estatal de\nDerechos Humanos del Estado, las denuncias y quejas que en cumplimiento de esta Ley reciban;\nXI.- Ingresar a la víctima al Registro Estatal, cuando así lo imponga su competencia;\nXII.- Aportar a la autoridad correspondiente los documentos, indicios o pruebas que obren en su poder, cuando éstos le sean requeridos o se relacionen con la denuncia, queja o solicitud que la víctima haya presentado;\nXIII.- Investigar o verificar los hechos denunciados o revelados, procurando no vulnerar más los derechos de las víctimas;\nXIV.- Garantizar que la víctima tenga un ejercicio libre de todo derecho y garantía, así como de mecanismos, procedimientos y acciones contempladas en esta Ley y la Ley\nGeneral;\nXV.- Realizar de oficio las acciones tendientes a la búsqueda de personas desaparecidas, extraviadas, ausentes o no localizadas, así como la identificación de personas, cadáveres o restos encontrados;\nLey de Víctimas para el Estado de Baja California. Página 73\nXVI.- Prestar ayuda para restablecer el paradero de las víctimas, recuperarlos, identificarlos y en su caso, inhumarlos según el deseo explícito o presunto de la víctima o las tradiciones o prácticas culturales de su familia y comunidad;\nXVII.- Adoptar o solicitar a la autoridad competente, de forma inmediata y específica, o evidenciada;\nXVIII.- Permitir el acceso a lugares, documentos, expedientes, conceder entrevistas y demás solicitudes que les requieran los organismos públicos de defensa de los derechos humanos, cuando éstas sean realizadas en el ámbito de su competencia y con el objeto de investigar presuntas violaciones a derechos humanos;\nXIX.- Abstenerse de solicitar o recibir por parte de las víctimas o sus representantes, gratificaciones monetarias o en especie, dádivas, favores o ventajas de cualquier índole, y\nXX.- Dar vista a la autoridad ministerial sobre la comisión de cualquier hecho que pudiera constituir la comisión de un delito o violación de derechos, siempre que éste se persiga de oficio. La vista en ningún caso condicionará, limitará o suspenderá la ayuda o servicios a los que la víctima tenga derecho.\nEl incumplimiento de los deberes aquí señalados en esta Ley para los servidores públicos, será sancionado con la responsabilidad administrativa o penal correspondiente.\nCAPÍTULO V\nDEL PODER JUDICIAL DEL ESTADO\nARTÍCULO 135.- Corresponde a los integrantes del Poder Judicial del Estado en el ámbito de su competencia:\nI.- Garantizar los derechos de las víctimas en estricta aplicación de la Constitución y los Tratados Internacionales celebrados y ratificados por el Estado Mexicano;\nII.- Dictar las medidas correctivas necesarias a fin de evitar que continúen las violaciones de derechos humanos o comisión de ciertos ilícitos;\nIII.- Imponer las sanciones disciplinarias pertinentes;\nIV.- Resolver expedita y diligentemente las solicitudes que ante ellos se presenten;\nV.- Dictar las medidas precautorias necesarias para garantizar la seguridad de las víctimas, y sus bienes jurídicos;\nLey de Víctimas para el Estado de Baja California. Página 74\nVI.- Garantizar que la opción y ejercicio de las medidas alternativas de resolución de conflictos se realice en respeto de los principios que sustentan la justicia restaurativa, en especial, la voluntariedad;\nVII.- Velar por que se notifique a la víctima cuando estén de por medio sus intereses y derechos, aunque no se encuentre legitimada procesalmente su coadyuvancia;\nVIII.- Permitir participar a la víctima en los actos y procedimientos no jurisdiccionales que solicite, incluso cuando no se encuentre legitimada procesalmente su coadyuvancia;\nIX.- Escuchar a la víctima antes de dictar sentencia, así como antes de resolver cualquier acto o medida que repercuta o se vincule con sus derechos o intereses;\nX.- Cuando los bienes asegurados sean puestos bajo la custodia de la víctima o le sean devueltos, deberá informar claramente a ésta los alcances de dicha situación, y las consecuencias que acarrea para el proceso, y\nXI.- Las demás acciones que dispongan las disposiciones jurídicas aplicables en materia de atención a víctimas de delito y reparación.\nCAPÍTULO VI\nDEL ASESOR JURÍDICO DE LAS VÍCTIMAS\nARTÍCULO 136.- Corresponde al Asesor Jurídico de las Víctimas:\nI. Procurar hacer efectivos cada uno de los derechos y garantías de la víctima, en especial el derecho a la protección, la verdad, la justicia y a la reparación. Por lo que podrá contar con servicios de atención médica y psicológica, trabajo social y aquellas que considere necesarias para cumplir con el objetivo de esta fracción;\nII. Brindar a la víctima información clara, accesible y oportuna sobre los derechos, garantías, mecanismos y procedimientos que reconoce esta Ley;\nIII. Tramitar, supervisar o, cuando se requiera, implementar las medidas de ayuda inmediata, ayuda, asistencia, atención y rehabilitación previstas en la presente Ley;\nIV. Asesorar y asistir a las víctimas en todo acto o procedimiento ante la autoridad;\nV. Formular denuncias o querellas; y,\nVI. Representar a la víctima en todo procedimiento jurisdiccional o administrativo derivado de un hecho victimizante.\nLey de Víctimas para el Estado de Baja California. Página 75\nCAPÍTULO VII\nDE LA COMISIÓN ESTATAL DE DERECHOS HUMANOS\nARTÍCULO 137.- Además de los deberes establecidos para todo servidor público, competencia, y en estricta aplicación de la Constitución y los Tratados Internacionales celebrados y ratificados por el Estado Mexicano, deberán:\nI.- Recibir las quejas por presuntas violaciones a derechos humanos;\nII.- Recibir las denuncias por presuntos hechos delictivos y remitir las mismas al\nMinisterio Público;\nIII.- Investigar las presuntas violaciones a derechos humanos;\nIV.- Respetar, en el marco de sus investigaciones, los protocolos internacionales para documentación de casos de presuntas violaciones de derechos de las víctimas;\nV.- Solicitar, cuando sea conducente, medidas cautelares necesarias para garantizar la seguridad de las víctimas, familiares o bienes jurídicos;\nVI.- Dar seguimiento a las solicitudes que plantee ante la autoridad ejecutiva o judicial; en caso de advertir omisiones o incumplimientos por la autoridad o particular, denunciar las mismas por las vías pertinentes;\nVII.- Recomendar las reparaciones a favor de las víctimas de violaciones a los derechos humanos con base en los estándares y elementos establecidos en la Ley General y esta Ley.\nCAPÍTULO VIII\nDE LAS POLICÍAS\nARTÍCULO 138.- Además de los deberes establecidos para todo servidor público, municipales, y en general de las disposiciones respectivas contempladas en otros ordenamientos, a los miembros de las policías de los órdenes de gobierno estatal y municipal, en el ámbito de su competencia, les corresponde:\nPárrafo Reformado\nI.- Informar a la víctima, desde el momento en que se presente o comparezca ante él, los derechos que le otorga la Constitución y los Tratados Internacionales celebrados y ratificados por el Estado Mexicano, la legislación penal y las demás disposiciones aplicables, Ley de Víctimas para el Estado de Baja California. Página 76 así como el alcance de esos derechos, debiendo dejar constancia escrita de la lectura y explicación realizada;\nII.- Permitir la participación de la víctima y su defensor en procedimientos encaminados a la procuración de justicia, así como el ejercicio de su coadyuvancia;\nIII.- Facilitar el acceso de la víctima a la investigación, con el objeto de respetar su derecho a la verdad;\nIV.- Colaborar con los tribunales de justicia, el ministerio público, las fiscalías, contralorías y demás autoridades en todas las actuaciones policiales requeridas;\nFracción Reformada\nV.- Remitir los datos de prueba e informes respectivos, con debida diligencia;\nVI.- Respetar las mejores prácticas y los estándares mínimos de derecho internacional de los derechos humanos, y\nVII.- Mantener actualizados los registros en cumplimiento de esta Ley y de la Ley\nGeneral.\nArtículo Reformado\nCAPÍTULO IX\nDE LA VÍCTIMA\nARTÍCULO 139.- A la víctima corresponde:\nI.- Actuar de buena fe, así como conducirse con honestidad;\nII.- Cooperar con las autoridades que buscan el respeto de su derecho a la justicia y a la verdad, siempre que no implique un riesgo para su persona, familia o bienes jurídicos;\nIII.- Conservar los bienes objeto de aseguramiento cuando éstos le hayan sido devueltos o puestos bajo su custodia, así como no cremar los cuerpos de familiares a ellos entregados, cuando la autoridad así se lo solicite, y por el lapso que se determine necesario,\nIV.- Cuando tenga acceso a información reservada, respetar y guardar la confidencialidad de la misma.\nTÍTULO OCTAVO\nDEL FONDO ESTATAL DE AYUDA, ASISTENCIA\nY REPARACIÓN INTEGRAL\nLey de Víctimas para el Estado de Baja California. Página 77\nCAPÍTULO I\nOBJETO E INTEGRACIÓN\nARTÍCULO 140.- El Fondo tiene por objeto brindar los Recursos de Ayuda y la humanos, siguiendo criterios de transparencia, oportunidad, eficiencia y rendición de cuentas. El Fondo estatal se conformará con los recursos que destine el Estado para dicho fin.\nARTÍCULO 141.- El fondo estatal deberá estar constituido por la cantidad que resulte de aplicar el factor poblacional que corresponda al estado, a la suma de las asignaciones anuales que corresponda aportar a cada entidad federativa a su fondo estatal de conformidad con el primer párrafo del artículo 157 Ter de la Ley General.\nEl factor poblacional a que se refiere el párrafo anterior será equivalente a la cantidad porcentual que corresponda a la población del estado con respecto del total nacional, de acuerdo con el último censo o conteo de población que publique el Instituto Nacional de\nEstadística y Geografía.\nLa aportación anual del Estado se deberá efectuar, siempre y cuando, el patrimonio del Fondo estatal al inicio del ejercicio sea inferior al monto de aportación que corresponda al Estado de conformidad al presente artículo. Dicha aportación se deberá efectuar a más tardar al 31 de marzo de cada ejercicio.\nARTÍCULO 142.- De los recursos que constituyan el patrimonio del Fondo estatal, se deberá mantener una reserva del 20% para cubrir los reintegros que, en su caso, deban realizarse al Fondo, de acuerdo con lo establecido por esta Ley.\nARTÍCULO 143.- La constitución de cada Fondo estatal será con independencia de la existencia de otros ya establecidos para la atención a víctimas. La aplicación de recursos establecidos en otros mecanismos a favor de las víctimas y los de esta Ley, se hará de manera complementaria, a fin de evitar su duplicidad.\nCAPÍTULO II\nDE LA ADMINISTRACIÓN\nARTÍCULO 144.- El Fondo Estatal será administrado por la Comisión Ejecutiva\nEstatal siguiendo criterios de transparencia, oportunidad, eficiencia y rendición de cuentas.\nLey de Víctimas para el Estado de Baja California. Página 78\nARTÍCULO 145.- La Comisión Ejecutiva Estatal deberá emitir las reglas de operación para el funcionamiento del Fondo, las cuales se regirán por lo establecido en esta\nLey.\nARTÍCULO 146.- El titular de la Comisión Ejecutiva, con el apoyo del servidor público designado por éste deberá:\nI.- Administrar cautelosamente los recursos que lo conforman a fin de permitir el cumplimiento efectivo del objeto de esta Ley;\nII.- Gestionar lo pertinente para que los recursos ingresen oportunamente al Fondo\nEstatal;\nIII.- Presentar trimestralmente informes y rendición de cuentas ante la Junta de\nGobierno, y\nIV.- Realizar las previsiones necesarias a fin de procurar la solvencia del Fondo\nEstatal.\nARTÍCULO 147.- Los recursos del Fondo Estatal se aplicarán también para otorgar a la víctima apoyos en los términos de esta Ley y conforme al Reglamento respectivo.\nLa Comisión Ejecutiva Estatal determinará el apoyo o asistencia que corresponda otorgar a la víctima de los recursos del Fondo Estatal, incluida la compensación, previa opinión que al respecto emita el Comité interdisciplinario evaluador, en los términos, límites y condiciones que determine esta Ley, el Reglamento y demás disposiciones normativas aplicables.\nEl Estado se subrogará en los derechos de las víctimas para cobrar el importe que por concepto de compensación haya erogado en su favor con cargo al Fondo. Para tal efecto, se aportarán al Estado los elementos de prueba necesarios para el ejercicio de los derechos derivados de la subrogación. en el párrafo anterior, en los momentos procesales oportunos, a fin de garantizar que sean valorados por el juzgador al momento de dictar sentencia, misma que deberá prever de reparación del daño y el monto correspondiente a dicha subrogación, en los casos en que así proceda.\nEn el caso de las compensaciones por error judicial, éstas se cubrirán con cargo al\nLey de Víctimas para el Estado de Baja California. Página 79 subrogación del monto de la reparación conforme a las disposiciones aplicables, sin perjuicio de que dicho cobro pueda reclamarse por la víctima en la vía civil, para cobrar la reparación del daño del sentenciado o de quien esté obligado a cubrirla, en términos de las disposiciones que resulten aplicables.\nEl Reglamento precisará el funcionamiento, procedimiento, alcance y criterios específicos de asignación de recursos del Fondo Estatal.\nCAPÍTULO III\nDEL PROCEDIMIENTO\nARTÍCULO 148.- Para acceder a los recursos del Fondo Estatal, la víctima deberá presentar su solicitud ante la Comisión Ejecutiva Estatal, de conformidad con lo señalado por esta Ley y su Reglamento.\nQuien reciba la solicitud la remitirá a la Comisión Ejecutiva Estatal en un plazo que no podrá exceder los dos días hábiles.\nLas determinaciones de la Comisión Ejecutiva Estatal respecto a cualquier tipo de pago, compensación o reparación del daño tendrán el carácter de resoluciones administrativas definitivas.\nEl Reglamento precisará el alcance y criterios específicos para la determinación de la afectación a las víctimas del delito y de violación de derechos humanos, los extremos probatorios de su petición y en su caso las reglas para la cuantificación de la reparación que en su caso proceda.\nARTÍCULO 149.- En cuanto reciba una solicitud, la Comisión Ejecutiva Estatal lo turnará, para la integración del expediente que servirá de base para la propuesta que el determinar el apoyo o ayuda que requiera la víctima.\nARTÍCULO 150.- El Comité interdisciplinario evaluador deberá integrar dicho expediente en un plazo no mayor de cuatro días, el cual deberá contener como mínimo:\nI.- Los documentos presentados por la víctima;\nII.- Descripción del daño o daños que haya sufrido la víctima;\nIII.- Detalle de las necesidades que requiera la víctima para enfrentar las consecuencias del delito o de la violación a sus derechos humanos, y\nLey de Víctimas para el Estado de Baja California. Página 80\nIV.- En caso de contar con ello, relación de partes médicos o psicológicos donde violación a los derechos humanos.\nARTÍCULO 151.- En el caso de la solicitud de ayuda o apoyo deberá agregarse, además:\nI.- Estudio de trabajo social elaborado por el Comité interdisciplinario evaluador en el que se haga una relación de las condiciones de victimización que enfrenta la víctima y las necesidades que requiere satisfacer para enfrentar las secuelas de la victimización;\nII.- Dictamen médico donde se especifique las afectaciones sufridas, las secuelas y el tratamiento, prótesis y demás necesidades que requiere la persona para su recuperación;\nIII.- Dictamen psicológico en caso de que la víctima requiera atención a la salud mental donde se especifique las necesidades que requieren ser cubiertas para la recuperación de la víctima, y\nIV.- Propuesta de resolución que se propone adopte la Comisión Ejecutiva Estatal donde se justifique y argumente jurídicamente la necesidad de dicha ayuda.\nLa víctima sólo estará obligada a entregar la información, documentación y pruebas que obren en su poder. Es responsabilidad del Comité lograr la integración de la carpeta respectiva.\nARTÍCULO 152.- Recibida la solicitud, ésta pasará a evaluación del comité interdisciplinario evaluador para que integre la carpeta con los documentos señalados en el artículo anterior, analice, valore y concrete las medidas que se otorgarán en cada caso. otorgamiento de la ayuda. mayor a veinte días hábiles y resolver con base a su dictamen la procedencia de la solicitud.\nARTÍCULO 153.- Las solicitudes para acceder a los recursos del Fondo Estatal en materia de reparación serán procedentes siempre que la víctima:\nI.- Cuente con sentencia ejecutoria en la que se indique que sufrió el daño por dichos ilícitos, así como el monto a pagar y/o otras formas de reparación;\nII.- No haya alcanzado el pago total de los daños que se le causaron;\nLey de Víctimas para el Estado de Baja California. Página 81\nIII.- No haya recibido la reparación del daño por cualquier otra vía, lo que podrá acreditarse con el oficio del juez de la causa penal o con otro medio fehaciente, y\nIV.- Presente solicitud de asistencia, ayuda o reparación, siempre y cuando dicha en esta Ley y su Reglamento.\nARTÍCULO 154.- Las solicitudes que se presenten en términos de este Capítulo se atenderán considerando:\nI.- La condición socioeconómica de la víctima;\nII.- La repercusión del daño en la vida familiar;\nIII.- La imposibilidad de trabajar como consecuencia del daño;\nIV.- El número y la edad de los dependientes económicos, y\nV.- Los recursos disponibles en el Fondo Estatal.\nCAPÍTULO IV\nDE LA REPARACIÓN\nARTÍCULO 155.- Si el Estado no pudiese hacer efectiva total o parcialmente la orden de compensación, establecida por mandato judicial o por acuerdo de la Comisión\nEjecutiva Estatal, deberá justificar la razón y tomar las medidas suficientes para cobrar su valor, o gestionar lo pertinente ante otras instancias a fin de lograr que se concrete la reparación de la víctima.\nARTÍCULO 156.- Cuando parte del daño sufrido se explique a consecuencia del actuar u omitir de la víctima, dicha conducta podrá ser tenida en cuenta al momento de determinar la indemnización.\nARTÍCULO 157.- Cuando el daño haya sido causado por más de un agente y no sea posible identificar la exacta participación de cada uno de ellos, se establecerá una responsabilidad subsidiaria frente a la víctima, y se distribuirá el monto del pago de la\nEjecutiva Estatal.\nARTÍCULO 158.- Las medidas de ayuda y asistencia podrán ser de diversa índole, en cumplimiento de las disposiciones de esta Ley y su Reglamento. La reparación deberá\nLey de Víctimas para el Estado de Baja California. Página 82 cubrirse mediante moneda nacional, con la excepción de que se podrá pagar en especie de acuerdo a la resolución dictada por la Comisión Ejecutiva Estatal.\nARTÍCULO 159.- La Comisión Ejecutiva Estatal tendrá facultades para cubrir las necesidades en términos de asistencia, ayuda y reparación, a través de los programas gubernamentales federales, estatales o municipales con que se cuente.\nARTÍCULO 160.- Cuando proceda el pago de la reparación, el Fondo Estatal registrará el fallo judicial que lo motivó y el monto de la indemnización, que será de consulta pública.\nTÍTULO NOVENO\nDE LA CAPACITACIÓN, FORMACIÓN, ACTUALIZACIÓN\nY ESPECIALIZACIÓN\nCAPITULO ÚNICO\nDE LA CAPACITACIÓN, FORMACIÓN, ACTUALIZACIÓN\nY ESPECIALIZACIÓN EN GENERAL\nARTÍCULO 161.- Los integrantes del Sistema Estatal que tengan contacto con la víctima en cumplimento de medidas de atención, asistencia, ayuda, apoyo, reparación o cualquier mecanismo de acceso a la justicia, deberán incluir dentro de sus programas contenidos temáticos sobre los principios, derechos, mecanismos, acciones y procedimientos reconocidos por la Ley General y esta Ley; así como las disposiciones específicas de derechos humanos contenidos en la Constitución, en los Tratados\nInternacionales celebrados y ratificados por el Estado Mexicano, protocolos específicos y demás instrumentos del derecho internacional de los derechos humanos.\nDichas entidades deberán diseñar e implementar un sistema de seguimiento que logre medir el impacto de la capacitación en los miembros de sus respectivas dependencias.\nA dicho efecto deberá tenerse en cuenta, entre otros aspectos, las denuncias y quejas hechas contra dichos servidores, las sanciones impuestas, las entrevistas y sondeos directos practicados a las víctimas.\nARTÍCULO 162.- Como parte de la asistencia, atención y reparación, se brindará a las víctimas formación, capacitación y orientación ocupacional.\nLa formación y capacitación se realizará con enfoque diferencial y transformador. Se ofrecerá a la víctima programas en virtud de su interés, condición y contexto, atendiendo a la utilidad de dicha capacitación o formación. El objeto es brindar a la víctima herramientas idóneas que ayuden a hacer efectiva la atención y la reparación, así como favorecer el fortalecimiento y resiliencia de la víctima.\nLey de Víctimas para el Estado de Baja California. Página 83\nAsimismo, deberá brindarse a la víctima orientación ocupacional específica que le permita optar sobre los programas, planes y rutas de capacitación y formación más idóneos conforme su interés, condición y contexto. distintos órdenes de gobierno, mismos que deberán ser coherentes con los principios rectores, derechos y garantías detallados en la Ley General.\nTÍTULO DÉCIMO\nDE LA ASESORÍA JURÍDICA ESTATAL\nDE ATENCIÓN A VÍCTIMAS\nCAPÍTULO ÚNICO\nARTÍCULO 163.- La Comisión Ejecutiva Estatal contará con la Asesoría Jurídica\nEstatal de Atención a Víctimas, área especializada en asesoría jurídica para víctimas, con independencia técnica y operativa, encargada de cumplir con las funciones que le otorga la\nLey.\nLa Asesoría Jurídica gozará de independencia técnica y operativa.\nARTÍCULO 164.- La Asesoría Jurídica estará integrada por asesores jurídicos de atención a víctimas, peritos y profesionistas técnicos de diversas disciplinas que se requieran para la defensa de los derechos de las víctimas.\nContará con un Titular y las unidades administrativas que se requieran para el desempeño de sus funciones, en los términos que señale el reglamento respectivo.\nARTÍCULO 165.- La Asesoría Jurídica tiene las siguientes funciones:\nI.- Coordinar el servicio de Asesoría Jurídica para Víctimas en asuntos del fuero común, a fin de garantizar los derechos de las víctimas contenidos en esta Ley, en los\nTratados Internacionales celebrados y ratificados por el Estado Mexicano, y demás disposiciones aplicables, así como coordinarse con la Asesoría Jurídica Federal;\nII.- Coordinar el servicio de representación y asesoría jurídica de las víctimas en materia penal, civil, laboral, familiar, administrativa y de derechos humanos del fuero común, a fin de garantizar el acceso a la justicia, a la verdad y la reparación;\nIII.- Seleccionar y capacitar a los servidores públicos de su adscripción;\nIV.- Designar por cada Unidad Investigadora del Ministerio Público, por cada del Estado, cuando menos a un Asesor Jurídico y al personal de auxilio necesario;\nLey de Víctimas para el Estado de Baja California. Página 84\nV.- Celebrar convenios de coordinación con todos aquellos que pueden coadyuvar en la defensa de los derechos de las víctimas, y\nVI.- Las demás que se requiera para la defensa de los derechos de las víctimas.\nARTÍCULO 166.- La víctima tendrá derecho a nombrar un Asesor Jurídico el cual elegirá libremente desde el momento de su ingreso al Registro Estatal. En caso de no contar con abogado particular, la Comisión Ejecutiva Estatal deberá nombrarle uno a través de la\nAsesoría Jurídica.\nLa víctima tendrá el derecho de que su abogado comparezca a todos los actos en los que ésta sea requerida.\nEl servicio de la Asesoría Jurídica será gratuito y se prestará a todas las víctimas que deseen o pueden contratar a un abogado particular y en especial a:\nI.- Las personas que estén desempleadas y no perciban ingresos;\nII.- Los trabajadores jubilados o pensionados, así como sus cónyuges;\nIII.- Los trabajadores eventuales o subempleados;\nIV.- Los indígenas, y\nV.- Las personas que por cualquier razón social o económica tengan la necesidad de estos servicios.\nARTÍCULO 167.- El Asesor Jurídico Estatal de Atención a Víctimas tendrá las funciones siguientes:\nI.- Asistir y asesorar a la víctima desde el primer momento en que tenga contacto con la autoridad;\nII.- Representar a la víctima de manera integral en todos los procedimientos y juicios en los que sea parte, para lo cual deberá realizar todas las acciones legales tendientes a su defensa, incluyendo las que correspondan en materia de derechos humanos tanto en el ámbito nacional como internacional;\nIII.- Proporcionar a la víctima de forma clara, accesible, oportuna y detallada la información y la asesoría legal que requiera, sea esta en materia penal, civil, familiar, laboral y administrativa;\nLey de Víctimas para el Estado de Baja California. Página 85\nIV.- Informar a la víctima, respecto al sentido y alcance de las medidas de protección, ayuda, asistencia, atención y reparación, y en su caso, tramitarlas ante las autoridades judiciales y administrativas;\nV.- Dar el seguimiento a todos los trámites de medidas de protección, ayuda, asistencia y atención, que sean necesarias para garantizar la integridad física y psíquica de las víctimas, así como su plena recuperación;\nVI.- Informar y asesorar a los familiares de la víctima o a las personas que ésta decida, sobre los servicios con que cuenta el Estado para brindarle ayuda, asistencia, asesoría, representación legal y demás derechos establecidos en esta Ley, en la Ley\nGeneral, en los Tratados Internacionales celebrados y ratificados por el Estado Mexicano, y demás leyes aplicables;\nVII.- Llevar un registro puntual de las acciones realizadas y formar un expediente del caso;\nVIII.- Tramitar y entregar copias de su expediente a la víctima, en caso de que ésta las requiera;\nIX.- Vigilar la efectiva protección y goce de los derechos de las víctimas, en las actuaciones del Ministerio Público en cada una de las etapas del procedimiento penal, y en su caso; suplir sus deficiencias ante la autoridad jurisdiccional correspondiente cuando considere que no se vela efectivamente por la tutela de los derechos de las víctimas, y\nX.- Las demás que se requieran para la defensa integral de los derechos de las víctimas.\nARTÍCULO 168.- Para ingresar y permanecer como Asesor Jurídico se requiere:\nI.- Ser mexicano o extranjero con calidad migratoria de inmigrado en ejercicio de sus derechos políticos y civiles;\nII.- Ser licenciado en derecho, con cédula profesional expedida por la autoridad competente;\nIII.- Aprobar los exámenes de ingreso correspondientes, y\nIV.- No haber sido condenado por delito doloso con sanción privativa de libertad mayor de un año.\nLey de Víctimas para el Estado de Baja California. Página 86\nARTÍCULO 169.- El Asesor Jurídico será asignado inmediatamente por la Comisión alguna institución, organismo de derechos humanos u organización de la sociedad civil.\nARTÍCULO 170.- El servicio civil de carrera para los Asesores Jurídicos, comprende la selección, ingreso, adscripción, permanencia, promoción, capacitación, prestaciones, estímulos y sanciones. Este servicio civil de carrera se regirá por las disposiciones establecidas en las disposiciones reglamentarias aplicables.\nARTÍCULO 171.- El Titular, los Asesores Jurídicos y el personal técnico de la\nAsesoría Jurídica serán considerados servidores públicos de confianza.\nARTÍCULO 172.- El Titular de la Asesoría Jurídica, será designado por el titular de la\nComisión Ejecutiva Estatal.\nARTÍCULO 173.- El Titular de la Asesoría Jurídica deberá reunir para su designación, los requisitos siguientes:\nI.- Ser ciudadano mexicano y estar en pleno ejercicio de sus derechos;\nII.- Contar con título y cédula profesional de licenciado en derecho, así como experiencia mínima de tres años en el ejercicio de la abogacía, relacionada especialmente, con las materias afines a sus funciones, y\nIII.- Gozar de buena reputación, prestigio profesional y no haber sido condenado por delito doloso con sanción privativa de libertad mayor de un año. Empero, si se tratare de ilícitos como el robo, fraude, falsificación, abuso de confianza u otro que lesione seriamente la reputación de la persona en el concepto público, inhabilitará a ésta para ocupar el cargo cualquiera que haya sido la penalidad impuesta.\nARTÍCULO 174.- El Titular de la Asesoría Jurídica tendrá las atribuciones siguientes:\nI.- Organizar, dirigir, evaluar y controlar los servicios de Asesoría Jurídica que se presten, así como sus unidades administrativas;\nII.- Conocer de las quejas que se presenten contra los Asesores Jurídicos y, en su caso, investigar la probable responsabilidad de los empleados de la Asesoría Jurídica;\nIII.- Vigilar que se cumplan todas y cada una de las obligaciones impuestas a los\nAsesores Jurídicos; determinando, si han incurrido en alguna causal de responsabilidad por parte de éstos o de los empleados de la Asesoría Jurídica;\nLey de Víctimas para el Estado de Baja California. Página 87\nIV.- Proponer las políticas que estime convenientes para la mayor eficacia de la defensa de los derechos e intereses de las víctimas;\nV.- Proponer a la Comisión Ejecutiva Estatal, las sanciones y correcciones disciplinarias que se deban imponer a los Asesores Jurídicos;\nVI.- Promover y fortalecer las relaciones con la Asesoría Jurídica Federal y demás instituciones públicas, sociales y privadas que por la naturaleza de sus funciones, puedan colaborar al cumplimiento de sus atribuciones;\nVII.- Proponer el proyecto de Plan Anual de Capacitación y Estímulos de la Asesoría\nJurídica, así como un programa de difusión de sus servicios;\nVIII.- Elaborar un informe anual de labores sobre las actividades integrales desarrolladas por todos y cada uno de los Asesores Jurídicos, el cual deberá ser publicado;\nIX.- Elaborar la propuesta de anteproyecto de presupuesto; y\nX.- Las demás que sean necesarias para cumplir con el objeto de esta Ley.\nTÍTULO DÉCIMO PRIMERO\nDE LA PROTECCION A VICTIMAS DEL DELITO Y\nVIOLACIONES A DERECHOS HUMANOS\nCAPITULO I\nDISPOSICIONES GENERALES\nARTÍCULO 175.- Las medidas de protección referidas en el Título Tercero, Capítulo\nIV, de la presente Ley, se otorgarán cuando exista una situación de riesgo grave o peligro inminente, derivado de la participación directa o indirecta de la persona a proteger en los términos de la presente Ley.\nARTÍCULO 176.- La información y documentación relacionada con las personas protegidas se clasifica como reservada y confidencial, en los términos de lo dispuesto por la\nLey de la materia. Los servidores públicos que participen en los procedimientos de otorgamiento de las medidas de protección, así como las personas que estén o hayan estado sujetos a las mismas, están obligadas a no revelar información relacionada con éstas, apercibidos de las consecuencias legales que correspondan en caso de incumplimiento; la misma obligación tendrán los servidores públicos que participen en la aplicación de la presente Ley. protegidas, ya sea a través de intimidación, represalias, amenazas, negligencia o cuando\nLey de Víctimas para el Estado de Baja California. Página 88 del delito o con un tercero implicado, serán sancionados de conformidad con las leyes aplicables al caso en concreto.\nARTÍCULO 177.- Para lograr los objetivos de las medidas de protección, el Fiscal\nGeneral podrá celebrar acuerdos, convenios y demás instrumentos jurídicos con personas físicas o morales, así como con autoridades federales y de los gobiernos de las entidades federativas y Municipios, organismos públicos autónomos o constitucionales, así como con organismos de los sectores social y privado e incluso internacionales, que resulten adecuados para otorgar la protección de las personas o establecer las medidas necesarias para su ejecución.\nPárrafo Reformado\nEn el caso de que se requiera de la contratación o adquisición de servicios con particulares, deberá garantizarse que se respeten los criterios de reserva y confidencialidad respecto de los antecedentes personales, médicos o laborales de la persona protegida, por lo que los proveedores de dichos servicios no podrán, bajo ningún caso, tener acceso a información que posibilite por cualquier medio su identificación.\nArtículo Reformado\nARTICULOS TRANSITORIOS\nPRIMERO. - La presente Ley entrará en vigor al día siguiente de su publicación en el\nPeriódico Oficial del Estado.\nSEGUNDO. - Se abroga la Ley de Atención y Protección a la Víctima o el Ofendido del Delito para el Estado de Baja California, publicada en el Periódico Oficial No. 39, de fecha 22 de agosto de 2003, Tomo CX.\nTERCERO. - Se derogan todas las disposiciones legales que se opongan a la presente Ley.\nCUARTO. - En un plazo de 180 días contados a partir de la entrada en vigor de la\nLey, el Ejecutivo del Estado y los Ayuntamientos deberán emitir o adecuar las disposiciones las disposiciones de esta Ley.\nQUINTO. - El Sistema Estatal de Atención a Víctimas deberá instalarse dentro de treinta días contados a partir del nombramiento del Comisionado Ejecutivo Estatal.\nArtículo Transitorio Reformado\nSEXTO. - La Procuraduría General de Justicia del Estado y demás dependencias o entidades del Ejecutivo del Estado, que ejercen funciones encomendadas de la Ley que se\nLey de Víctimas para el Estado de Baja California. Página 89 abroga, deberán transferir los recursos humanos, materiales y financieros a la Comisión\nEjecutiva Estatal para el inicio de sus operaciones. de lo previsto en el párrafo anterior.\nLa Dirección de Atención a Víctimas y Testigos de la Procuraduría General de\nJusticia del Estado y demás instancias de procuración de justicia y atención a víctimas, continuarán funcionando hasta en tanto se vayan desahogando todos los procedimientos penales ya iniciados, y asumirán las funciones que esta Ley le encomienda a la Comisión\nEjecutiva Estatal.\nSÉPTIMO. - En la transferencia del personal de la Dirección de Atención a Víctimas y Testigos de la Procuraduría General de Justicia del Estado y demás instancias de procuración de justicia y atención a víctimas a la Comisión Ejecutiva Estatal, deberán ser respetados sus derechos laborales.\nLa Comisión Ejecutiva organizará al personal que reciba en transferencia considerando sus funciones de conformidad con su perfil y experiencia, a fin de hacer más eficiente el ejercicio de sus atribuciones.\nLas presentes reformas no afectarán los derechos adquiridos y demás prestaciones reconocidas a los trabajadores de base con anterioridad a la entrada en vigor de la presente\nLey, por lo que serán reasignados en relación a sus funciones y experiencia.\nOCTAVO. - Todas las Instituciones a que se refiere esta Ley, deberán establecer los programas tendientes a capacitar a su personal a efecto de dar cumplimiento a la misma, de conformidad con las normas constitucionales y legales aplicables y con la disponibilidad presupuestal.\nNOVENO. - Los registros de víctimas existentes al momento de la entrada en vigor municipal, así como en la Comisión Estatal de Derechos Humanos, deberán ser remitidos a la Comisión Ejecutiva Estatal de Atención a Víctimas, en un plazo de treinta días siguientes a la conformación de la misma.\nDÉCIMO. - Dentro de los 90 días siguientes a la entrada en vigor del presente víctimas, expertos y organizaciones de la sociedad civil especializadas en la materia, remitirá\nEstatal.\nLey de Víctimas para el Estado de Baja California. Página 90 consulta pública a colectivos de víctimas, expertos y organizaciones de la sociedad civil especializadas en la materia, para los mismos fines, dentro de los 60 días siguientes, hasta en tanto se remita dicha propuesta.\nEl Titular del Poder Ejecutivo Estatal deberá remitir la propuesta al Congreso del\nEstado, el cual una vez recibida, contará con un plazo de 45 días para que proceda a su nombramiento.\nArtículo Transitorio Reformado\nDÉCIMO PRIMERO. - Por única ocasión, para la designación de los miembros del\nConsejo Consultivo, el Comisionado Ejecutivo dentro de los 30 días siguientes a su nombramiento enviará propuestas de integrantes al Congreso del Estado, el cual los elegirá dentro de los 60 días posteriores.\nDÉCIMO SEGUNDO. - Dentro de los diez días siguientes de constituirse el Consejo\nConsultivo, deberá instalarse la Junta de Gobierno.\nDÉCIMO TERCERO. - Los recursos del Fondo General de Reparaciones a las\nVíctimas u Ofendidos que dispone la Ley de Atención y Protección a la Victima o el Ofendido del Delito para el Estado que se abroga, serán transferidos al Fondo Estatal de Ayuda, Asistencia y Reparación Integral que regula la Ley que se expide con el presente Decreto. El\nTitular del Poder Ejecutivo del Estado adoptará las medidas administrativas pertinentes para estos efectos.\nDÉCIMO CUARTO. - El Ejecutivo del Estado deberá hacer las previsiones presupuestales para la operación de la presente Ley dentro del ejercicio fiscal subsecuente a su entrada en vigor y a la designación del Comisionado Ejecutivo Estatal. del Estado de Baja California, en la Ciudad de Mexicali, B.C., a los veintisiete días del mes de septiembre del año dos mil dieciocho.\nDIP. ROCÍO LÓPEZ GOROSAVE\nPRESIDENTA DE LA MESA DIRECTIVA\n(RÚBRICA)\nDIP. MÓNICA HERNÁNDEZ ÁLVAREZ\nSECRETARIA DE LA MESA DIRECTIVA\n(RÚBRICA)\nLey de Víctimas para el Estado de Baja California. Página 91\nMEXICALI, BAJA CALIFORNIA, A LOS VEINTINUEVE DÍAS DEL MES DE\nOCTUBRE DEL AÑO DOS MIL DIECIOCHO.\nFRANCISCO ARTURO VEGA DE LAMADRID\nGOBERNADOR DEL ESTADO\n(RÚBRICA)\nFRANCISCO RUEDA GÓMEZ\nSECRETARIO GENERAL DE GOBIERNO\n(RÚBRICA)\nLey de Víctimas para el Estado de Baja California. Página 92\nARTÍCULO 9.- Fue reformado por Decreto No. 377, publicado en el Periódico Oficial\nLegislatura, siendo Gobernadora Constitucional la C. Marina del Pilar Ávila Olmeda, 20212027;\nARTÍCULO 30.- Fue reformado por Decreto No. 36, publicado en el Periódico Oficial\nNo. 93, Sección II, Tomo CXXVIII, de fecha 12 de noviembre de 2021, expedido por la H.\nXXIV Legislatura, siendo Gobernadora Constitucional la C. Marina del Pilar Ávila Olmeda\n2021-2027;\nARTÍCULO 33.- Fue reformado por Decreto No. 36, publicado en el Periódico Oficial\nNo. 93, Sección II, Tomo CXXVIII, de fecha 12 de noviembre de 2021, expedido por la H.\nXXIV Legislatura, siendo Gobernadora Constitucional la C. Marina del Pilar Ávila Olmeda\n2021-2027;\nARTÍCULO 66.- Fue reformado por Decreto No. 145, publicado en el Periódico Oficial\nNo. 60, Sección II, Tomo CXXIX, de fecha 17 de octubre de 2022, expedido por la H. XXIV\nLegislatura, siendo Gobernadora Constitucional la C. Marina del Pilar Ávila Olmeda 20212027; Fe de Erratas a la publicación del Resolutivo Único del Decreto No. 145, publicado en el Periódico Oficial No. 60, Sección II, de fecha 17 de octubre de 2022, publicada en el\nPeriódico Oficial No. 70, Sección III, de fecha 02 de diciembre, Tomo CXXIX, siendo\nGobernadora Constitucional la C. Marina del Pilar Ávila Olmeda 2021-2027;\nARTÍCULO 80.- Fue reformado por Decreto No. 145, publicado en el Periódico Oficial\nNo. 60, Sección II, Tomo CXXIX, de fecha 17 de octubre de 2022, expedido por la H. XXIV\nLegislatura, siendo Gobernadora Constitucional la C. Marina del Pilar Ávila Olmeda 20212027;\nARTÍCULO 85.- Fue reformado mediante Decreto No. 322, publicado en el Periódico\nOficial No. 14, de fecha 22 de marzo de 2019, Tomo CXXVI, Sección III, expedido por la H.\nXXII Legislatura, siendo Gobernador Constitucional el C. Francisco Arturo Vega de Lamadrid\n2013-2019;\nARTÍCULO 112.- Fue reformado por Decreto No. 145, publicado en el Periódico\nXXIV Legislatura, siendo Gobernadora Constitucional la C. Marina del Pilar Ávila Olmeda\n2021-2027;\nARTÍCULO 118.- Fue reformado por Decreto No. 145, publicado en el Periódico\nXXIV Legislatura, siendo Gobernadora Constitucional la C. Marina del Pilar Ávila Olmeda\n2021-2027;\nLey de Víctimas para el Estado de Baja California. Página 93\nFue modificada la denominación de este Capítulo por Decreto No. 388, publicado en\nLegislatura, siendo Gobernadora Constitucional la C. Marina del Pilar Ávila Olmeda 20212027;\nSECCIÓN IV\nFACULTADES DE LA SECRETARÍA DE SEGURIDAD CIUDADANA\nARTÍCULO 122.- Fue reformado por Decreto No. 388, publicado en el Periódico\nOficial No. 14, Índice, de fecha 15 de marzo de 2024, expedido por la H. XXIV Legislatura, siendo Gobernadora Constitucional la C. Marina del Pilar Ávila Olmeda 2021-2027;\nFue modificada la denominación de este Capítulo por Decreto No. 388, publicado en el Periódico Oficial No. 14, Índice, de fecha 15 de marzo de 2024, expedido por la H. XXIV\nLegislatura, siendo Gobernadora Constitucional la C. Marina del Pilar Ávila Olmeda 20212027;\nSECCIÓN VI\nFACULTADES DE LA SECRETARÍA DE EDUCACIÓN\nARTÍCULO 124.- Fue reformado por Decreto No. 388, publicado en el Periódico\nOficial No. 14, Índice, de fecha 15 de marzo de 2024, expedido por la H. XXIV Legislatura, siendo Gobernadora Constitucional la C. Marina del Pilar Ávila Olmeda 2021-2027;\nFue modificada la denominación de este Capítulo por Decreto No. 388, publicado en el Periódico Oficial No. 14, Índice, de fecha 15 de marzo de 2024, expedido por la H. XXIV\nLegislatura, siendo Gobernadora Constitucional la C. Marina del Pilar Ávila Olmeda 20212027;\nSECCIÓN VII\nFACULTADES DE LA SECRETARÍA DE BIENESTAR\nARTÍCULO 125.- Fue reformado por Decreto No. 388, publicado en el Periódico\nOficial No. 14, Índice, de fecha 15 de marzo de 2024, expedido por la H. XXIV Legislatura, siendo Gobernadora Constitucional la C. Marina del Pilar Ávila Olmeda 2021-2027;\nARTÍCULO 133.- Fue reformado por Decreto No. 388, publicado en el Periódico siendo Gobernadora Constitucional la C. Marina del Pilar Ávila Olmeda 2021-2027;\nARTÍCULO 138.- Fue reformado por Decreto No. 145, publicado en el Periódico\nXXIV Legislatura, siendo Gobernadora Constitucional la C. Marina del Pilar Ávila Olmeda\n2021-2027;\nARTÍCULO 177.- Fue reformado por Decreto No. 145, publicado en el Periódico\nLey de Víctimas para el Estado de Baja California. Página 94\nXXIV Legislatura, siendo Gobernadora Constitucional la C. Marina del Pilar Ávila Olmeda\n2021-2027;\nARTÍCULO TRANSITORIO QUINTO.- Fue reformado este Artículo Transitorio del\nDecreto No. 270, mediante Decreto No. 324, publicado en el Periódico Oficial No. 14, de siendo Gobernador Constitucional el C. Francisco Arturo Vega de Lamadrid 2013-2019;\nARTÍCULO TRANSITORIO DÉCIMO.- Fue reformado este Artículo Transitorio del\nDecreto No. 270, mediante Decreto No. 324, publicado en el Periódico Oficial No. 14, de siendo Gobernador Constitucional el C. Francisco Arturo Vega de Lamadrid 2013-2019;\nLey de Víctimas para el Estado de Baja California. Página 95\nARTÍCULO ÚNICO TRANSITORIO DEL DECRETO No. 322, POR EL QUE SE\nAPRUEBA LA REFORMA AL ARTÍCULO 85, PUBLICADO EN EL PERIÓDICO OFICIAL No.\nH. XXII LEGISLATURA, SIENDO GOBERNADOR CONSTITUCIONAL EL C. FRANCISCO\nARTURO VEGA DE LAMADRID 2013-2019.\nARTÍCULO TRANSITORIO\nÚNICO.- La presente reforma entrará en vigor al día siguiente de su publicación en el\nPeriódico Oficial del Estado.\nDADO en el Salón de Sesiones “Lic. Benito Juárez García” del H. Poder Legislativo del Estado de Baja California, en la Ciudad de Mexicali, B.C., a los catorce días del mes de febrero del año dos mil diecinueve.\nDIP. CARLOS ALBERTO TORRES TORRES\nPRESIDENTE\n(RÚBRICA)\nDIP. MARÍA TRINIDAD VACA CHACÓN\nSECRETARIA\n(RÚBRICA)\nDE CONFORMIDAD CON LO DISPUESTO POR LA FRACCIÓN I DEL ARTÍCULO 49\nMEXICALI, BAJA CALIFORNIA, A LOS VEINTIDOS Y UN DÍAS DEL MES DE\nMARZO DEL AÑO DOS MIL DIECINUEVE.\nFRANCISCO ARTURO VEGA DE LAMADRID\nGOBERNADOR DEL ESTADO\n(RÚBRICA)\nFRANCISCO RUEDA GÓMEZ\nSECRETARIO GENERAL DE GOBIERNO\n(RÚBRICA)\nLey de Víctimas para el Estado de Baja California. Página 96\nARTÍCULO ÚNICO TRANSITORIO DEL DECRETO No. 324, POR EL QUE SE\nNÚMERO 270 QUE CREA LA LEY DE VÍCTIMAS PARA EL ESTADO DE BAJA\nCALIDORNIA, PUBLICADO EN EL PERIÓDICO OFICIAL No. 14, SECCIÓN III, TOMO\nSIENDO GOBERNADOR CONSTITUCIONAL EL C. FRANCISCO ARTURO VEGA DE\nLAMADRID 2013-2019.\nARTÍCULO TRANSITORIO\nÚNICO.- La presente reforma entrará en vigor al día siguiente de su publicación en el\nPeriódico Oficial del Estado.\nDADO en el Salón de Sesiones “Lic. Benito Juárez García” del H. Poder Legislativo del Estado de Baja California, en la Ciudad de Mexicali, B.C., a los catorce días del mes de febrero del año dos mil diecinueve.\nDIP. CARLOS ALBERTO TORRES TORRES\nPRESIDENTE\n(RÚBRICA)\nDIP. MARÍA TRINIDAD VACA CHACÓN\nSECRETARIA\n(RÚBRICA)\nDE CONFORMIDAD CON LO DISPUESTO POR LA FRACCIÓN I DEL ARTÍCULO 49\nMEXICALI, BAJA CALIFORNIA, A LOS VEINTIDOS Y UN DÍAS DEL MES DE\nMARZO DEL AÑO DOS MIL DIECINUEVE.\nFRANCISCO ARTURO VEGA DE LAMADRID\nGOBERNADOR DEL ESTADO\n(RÚBRICA)\nFRANCISCO RUEDA GÓMEZ\nSECRETARIO GENERAL DE GOBIERNO\n(RÚBRICA)\nLey de Víctimas para el Estado de Baja California. Página 97\nARTÍCULO SEGUNDO TRANSITORIO DEL DECRETO No. 36, POR EL QUE SE\nAPRUEBA LA REFORMA A LOS ARTÍCULOS 30 Y 33; PUBLICADO EN EL PERIÓDICO\nEXPEDIDO POR LA H. XXIV LEGISLATURA, SIENDO GOBERNADORA\nCONSTITUCIONAL LA C. MARINA DEL PILAR ÁVILA OLMEDA 2021-2027.\nTRANSITORIOS\nÚNICO.- La presente reforma entrará en vigor al día siguiente de su publicación en el\nPeriódico Oficial el Estado.\nDADO en Sesión Extraordinaria Virtual de la XXIV Legislatura en la Ciudad de\nMexicali, B.C., a los veintinueve días del mes de octubre del año dos mil veintiuno.\nDIP. JUAN MANUEL MOLINA GARCÍA\nPRESIDENTE\n(RÚBRICA)\nDIP. ARACELI GERALDO NÚÑEZ\nSECRETARIA\n(RÚBRICA)\nDE CONFORMIDAD CON LO DISPUESTO POR LA FRACCIÓN I DEL ARTÍCULO 49\nCALIFORNIA, IMPRÍMASE Y PUBLÍQUESE.\nMEXICALI, BAJA CALIFORNIA, A LOS DOCE DÍAS DEL MES DE NOVIEMBRE DEL AÑO\nDOS MIL VEINTIUNO.\nMARINA DEL PILAR ÁVILA OLMEDA\nGOBERNADORA CONSTITUCIONAL\nDE BAJA CALIFORNIA\n(RÚBRICA)\nCATALINO ZAVALA MÁRQUEZ\nSECRETARIO GENERAL DE GOBIERNO\nDEL ESTADO DE BAJA CALIFORNIA\n(RÚBRICA)\nLey de Víctimas para el Estado de Baja California. Página 98\nARTÍCULO ÚNICO TRANSITORIO DEL DECRETO No. 145, POR EL QUE SE\nAPRUEBA LA REFORMA A LOS ARTÍCULOS 66, 80, 112, 118, 138 Y 177; PUBLICADO\nEN EL PERIÓDICO OFICIAL No. 60, SECCIÓN II, TOMO CXXIX, DE FECHA 17 DE\nGOBERNADORA CONSTITUCIONAL LA C. MARINA DEL PILAR ÁVILA OLMEDA 2021-\n2027.\nTRANSITORIOS\nÚNICO.- La presente reforma entrará en vigor al día siguiente de su publicación en el\nPeriódico Oficial el Estado.\nDADO en Sesión Ordinaria de la XXIV Legislatura en la Ciudad de Mexicali, B.C., a los veintinueve días del mes de septiembre del año dos mil veintidós.\nDIP. ALEJANDRA MARÍA ANG HERNÁNDEZ\nPRESIDENTA\n(RÚBRICA)\nDIP. DUNNIA MONTSERRAT MURILLO LÓPEZ\nSECRETARIA\n(RÚBRICA)\nDE CONFORMIDAD CON LO DISPUESTO POR LA FRACCIÓN I DEL ARTÍCULO 49\nCALIFORNIA, IMPRÍMASE Y PUBLÍQUESE.\nMEXICALI, BAJA CALIFORNIA, A LOS TRES DÍAS DEL MES DE OCTUBRE DEL AÑO\nDOS MIL VEINTIDÓS.\nMARINA DEL PILAR ÁVILA OLMEDA\nGOBERNADORA DEL ESTADO\nDE BAJA CALIFORNIA\n(RÚBRICA)\nCATALINO ZAVALA MÁRQUEZ\nSECRETARIO GENERAL DE GOBIERNO\nDEL ESTADO DE BAJA CALIFORNIA\n(RÚBRICA)\nLey de Víctimas para el Estado de Baja California. Página 99\nNo. 145, PUBLICADO EN EL PERIÓDICO OFICIAL No. 60, SECCIÓN II, DE FECHA 17 DE\nSIENDO GOBERNADORA CONSTITUCIONAL LA C. MARINA DEL PILAR ÁVILA OLMEDA\n2021-2027.\nATENTAMENTE\nMEXICALI, B.C., A 08 DE NOVIEMBRE DE 2022.\nPOR LA MESA DIRECTIVA\nDIP. ALEJANDRA MARÍA ANG HERNÁNDEZ\nPRESIDENTA\n(RÚBRICA)\nDIP. DUNNIA MONTSERRAT MURILLO LÓPEZ\nSECRETARIA\n(RÚBRICA)\nDE CONFORMIDAD CON LO DISPUESTO POR LA FRACCIÓN I DEL ARTÍCULO 49\nCALIFORNIA, IMPRÍMASE Y PUBLÍQUESE.\nMEXICALI, BAJA CALIFORNIA, A LOS DIECISÉIS DÍAS DEL MES DE NOVIEMBRE DEL\nAÑO DOS MIL VEINTIDÓS.\nMARINA DEL PILAR ÁVILA OLMEDA\nGOBERNADORA DEL ESTADO\nDE BAJA CALIFORNIA\n(RÚBRICA)\nCATALINO ZAVALA MÁRQUEZ\nSECRETARIO GENERAL DE GOBIERNO\nDEL ESTADO DE BAJA CALIFORNIA\n(RÚBRICA)\nLey de Víctimas para el Estado de Baja California. Página 100\nARTÍCULO CUARTO TRANSITORIO DEL DECRETO No. 377, POR EL QUE SE\nAPRUEBA LA REFORMA AL ARTÍCULO 9; PUBLICADO EN EL PERIÓDICO OFICIAL No.\nXXIV LEGISLATURA, SIENDO GOBERNADORA CONSTITUCIONAL LA C. MARINA DEL\nPILAR ÁVILA OLMEDA 2021-2027.\nTRANSITORIOS\nÚNICO.- La presente reforma entrará en vigor al día siguiente de su publicación en el\nPeriódico Oficial del Estado.\nDADO en Sesión Ordinaria de la XXIV Legislatura en la Ciudad de Mexicali, B.C., a los veinticinco días del mes de enero del año dos mil veinticuatro.\nDIP. ARACELI GERALDO NÚÑEZ\nPRESIDENTA\n(RÚBRICA)\nDIP. MANUEL GUERRERO LUNA\nSECRETARIO\n(RÚBRICA)\nDE CONFORMIDAD CON LO DISPUESTO POR LA FRACCIÓN I DEL ARTÍCULO 49 DE\nCALIFORNIA, IMPRÍMASE Y PUBLÍQUESE.\nMEXICALI, BAJA CALIFORNIA, A LOS VEINTINUEVE DÍAS DEL MES DE ENERO\nDEL AÑO DOS MIL VEINTICUATRO.\nMARINA DEL PILAR ÁVILA OLMEDA\nGOBERNADORA DEL ESTADO\nDE BAJA CALIFORNIA\n(RÚBRICA)\nALFREDO ÁLVAREZ CÁRDENAS\nSECRETARIO GENERAL DE GOBIERNO\nDEL ESTADO DE BAJA CALIFORNIA\n(RÚBRICA)\nLey de Víctimas para el Estado de Baja California. Página 101\nARTÍCULO ÚNICO TRANSITORIO DEL DECRETO No. 388, POR EL QUE SE\nAPRUEBA LA REFORMA A LOS ARTÍCULOS 122, 124, 125 Y 133 FRACCIÓN IV;\nPUBLICADO EN EL PERIÓDICO OFICIAL No. 14, ÍNDICE, DE FECHA 15 DE MARZO DE\n2024, EXPEDIDO POR LA H. XXIV LEGISLATURA, SIENDO GOBERNADORA\nCONSTITUCIONAL LA C. MARINA DEL PILAR ÁVILA OLMEDA 2021-2027.\nTRANSITORIO\nÚNICO.- La presente reforma entrará en vigor al día siguiente de su publicación en el\nPeriódico Oficial del Estado de Baja California.\nDADO en Sesión Extraordinaria de la XXIV Legislatura en la Ciudad de Mexicali, B.C., a los nueve días del mes de febrero del año dos mil veinticuatro.\nDIP. ARACELI GERALDO NÚÑEZ\nPRESIDENTA\n(RÚBRICA)\nDIP. MANUEL GUERRERO LUNA\nSECRETARIO\n(RÚBRICA)\nDE CONFORMIDAD CON LO DISPUESTO POR LA FRACCIÓN I DEL ARTÍCULO 49 DE\nCALIFORNIA, IMPRÍMASE Y PUBLÍQUESE.\nMEXICALI, BAJA CALIFORNIA, A LOS CUATRO DÍAS DEL MES DE MARZO DEL\nAÑO DOS MIL VEINTICUATRO.\nMARINA DEL PILAR ÁVILA OLMEDA\nGOBERNADORA DEL ESTADO\nDE BAJA CALIFORNIA\n(RÚBRICA)\nALFREDO ÁLVAREZ CÁRDENAS\nSECRETARIO GENERAL DE GOBIERNO\nDEL ESTADO DE BAJA CALIFORNIA\n(RÚBRICA)\nLey de Víctimas para el Estado de Baja California. Página 102",
  "ordenamiento": "REGLAMENTO",
  "jurisdiccion": "BAJA CALIFORNIA",
  "fuente_oficial": "Periódico Oficial",
  "FECHA PER OFIC": "2024/03/15",
  "ESTATUS": "VIGENTE",
  "TOMO": "TOMO_VI",
  "URL": "https://www.congresobc.gob.mx/Documentos/ProcesoParlamentario/Leyes/TOMO_VI/20240315_LEYVICTIMAS.PDF",
  "es_escaneado": false,
  "tiene_tablas": true,
  "materia": [
    "social",
    "salud",
    "educación",
    "cultura"
  ]
}