{
  "titulo": "Ley DE PROTECCIÓN y DEFENSA DE LOS DERECHOS DE LOS MENORES y LA FAMILIA EN EL ESTADO DE BAJA CALIFOR",
  "Contenido": "DECRETO No. 239 EXPEDIDO POR LA H. XXI LEGISLATURA, PUBLICADO EN EL PERIÓDICO\nLEY, SALVO POR LO QUE REFIERE A LA ESTRUCTURA ORGÁNICA Y ATRIBUCIONES DE\nLA PROCURADURÍA PARA LA DEFENSA DE LOS MENORES Y LA FAMILIA EN EL ESTADO,\nLAS CUALES CORRESPONDERÁN A LA PROCURADURÍA DE PROTECCIÓN DE NIÑAS,\nNIÑOS Y ADOLESCENTES DEL ESTADO, EN TANTO NO CONTRAVENGAN A LA LEY PARA\nLA PROTECCIÓN Y DEFENSA DE LOS DERECHOS DE NIÑAS, NIÑOS Y ADOLESCENTES\nDEL ESTADO DE BAJA CALIFORNIA, HASTA EN TANTO SE EXPIDA SU LEGISLACIÓN\nORGÁNICA.\nLEY DE PROTECCIÓN Y DEFENSA DE LOS DERECHOS DE LOS\nMENORES Y LA FAMILIA EN EL ESTADO DE BAJA CALIFORNIA\nPublicada en el Periódico Oficial No. 31, de fecha 4 de julio de 2008, Tomo CXV\nTÍTULO PRIMERO\nDE LOS DERECHOS DEL MENOR\nCAPÍTULO I\nDISPOSICIONES GENERALES\nARTÍCULO 1.- Las disposiciones de esta ley son de orden público e interés general y tiene por objeto establecer los derechos mínimos de los menores en el Estado de Baja California, mismos que deberán de ser considerados por todas las autoridades judiciales, administrativas o de cualquier otra índole para la emisión de sus acuerdos o resoluciones, tomando en cuenta siempre el interés superior del Menor y la Familia.\nARTÍCULO 2.- La Procuraduría, dependiente del Sistema, será la autoridad administrativa responsable de promover y proteger los derechos del menor consagrados en la Constitución Política de los Estados Unidos Mexicanos, en la Convención Sobre los disposiciones legales aplicables, vigilando que en las actuaciones, acuerdos o superior del menor y su reintegración familiar.\nArtículo Reformado\nARTÍCULO 3.- Serán sujetos de esta ley los menores que se encuentren en estado de vulnerabilidad y la Familia.\nARTÍCULO 4.- Para los efectos de esta Ley, se entiende por:\nI.- Acreedor alimentario: Aquella persona que es sujeta de derecho a una pensión alimenticia generada por parentesco o por disposición de la Ley.\nII.- Consejo: El consejo de adopciones encargado de apoyar y asesorar a la procuraduría, para la definición de políticas y acciones en materia de adopción de menores y hogares substitutos.\nIII.- Director: El Director del Sistema Estatal para el Desarrollo Integral de la\nFamilia de Baja California.\nIV.- Familia: El grupo fundamental de la sociedad y medio natural para el crecimiento y el bienestar de todos sus miembros.\nV.- Ley: Ley para la Protección y Defensa de los Menores y la Familia en el Estado de Baja California.\nVI.- Menor(es): Toda persona menor de dieciocho años de edad.\nVII.- Plan social: Es el programa diseñado por la Procuraduría, que deberán cumplir los padres, familiares o quienes ejerzan la patria potestad del menor en estado de vulnerabilidad, para efectos de lograr su reintegración familiar.\nVIII.- Procurador: El Procurador para la Defensa de los Menores y la Familia en el\nEstado.\nIX.- Procuraduría: La Procuraduría para la Defensa de los Menores y la Familia en el Estado.\nX.- Reglamento: El Reglamento de la Ley para la Protección y Defensa de los\nMenores y la Familia en el Estado de Baja California.\nXI.- Sistema: El Sistema Estatal para el Desarrollo Integral de la Familia de Baja\nCalifornia.\nXII.- Subprocurador: El titular de la Subprocuraduría para la Defensa de los\nMenores y la Familia.\nXIII.- Subprocuraduría: Subprocuraduría para Defensa de los Menores y la\nFamilia.\nXIV. Vulnerabilidad: Cualquier conducta o circunstancia que afecte o ponga en riesgo la seguridad, la salud, la moralidad, la tranquilidad, el bienestar o el desarrollo significado del hecho, aun cuando esos hechos o conductas no cayeren bajo la sanción de la ley penal.\nArtículo Reformado\nCAPÍTULO II\nDE LOS DERECHOS MÍNIMOS DEL MENOR\nARTÍCULO 5 Todo menor tiene derecho a una vida digna y decorosa que comprenderá:\nI.- Una identidad, que se compone de nacionalidad, nombre y filiación de conformidad con lo establecido por las leyes correspondientes;\nII.- Ser tratado sin discriminación alguna en razón a su raza, lengua, costumbres, capacidades diferentes, condiciones físicas o mentales y de salud;\nIII.- Una educación que desarrolle íntegramente su personalidad, en los términos que establecen las leyes relativas;\nIV.- La salud. Para salvaguardar este derecho, el Estado y los municipios deberán brindar el servicio y la atención médica, hospitalaria y de medicación en las instituciones de asistencia social que tengan para tal efecto. El servicio será gratuito cuando el menor sea derechohabiente de alguna institución de seguridad social o la situación socioeconómica de quienes lo tengan bajo su cuidado, no les permita solventarlo;\nV.- Ser protegido en contra de cualquier forma de explotación, agresión o maltrato, actos u omisiones que puedan afectar su salud física o mental y su normal desarrollo, tales como, el uso de drogas y enervantes, secuestro, pornografía, corrupción de menores y trata de personas. Las normas establecerán las formas de prever y evitar estas conductas. Enunciativamente, se les protegerá cuando se vean afectados por el descuido, la negligencia, el abandono, el abuso emocional, físico y sexual.\nPara efectos de lo anterior, el Estado y los municipios en el ámbito de su competencia, deberán establecer programas tendientes a la prevención, detección y denuncia de abusos en contra de menores, así como de apoyo a favor de las víctimas y sus familiares;\nVI.- Ser protegido de toda solicitud que de manera directa, vía informática, audiovisual, virtual, de imágenes o sonidos propios, o de terceros menores de edad con contenido sexual o erótico, no educativo, explícito o no, reales o simuladas, que atenten contra su sano desarrollo.\nPara garantizar lo anterior, el Estado y los municipios dentro de su esfera competencial, establecerán programas enfocados a la prevención, detección y denuncia de abusos en contra de menores, así como de apoyo a favor de las víctimas y sus familiares;\nVII.- Ser protegido mediante la restricción de acceso a sitios de Internet con contenido sexual no educativo, a fin de evitar que sean objeto de las solicitudes que señala la fracción anterior y que puedan ser utilizadas para fines sexuales.\nEl Estado y los municipios como garantes de este derecho de los menores, dispondrán que los equipos de cómputo que se utilicen en las oficinas públicas, los centros educativos oficiales, así como en las instituciones particulares con autorización o reconocimiento oficial de validez de estudios, cuenten inexcusablemente con las contenido sexual o erótico, no educativo;\nVIII.- Ser protegido en contra de la pornografía impresa que se publicita de manera abierta y sin la cubierta necesaria, dejándola a la vista y alcance de los menores sin restricción alguna, en los distintos lugares dedicados a su comercialización, venta y distribución de este tipo de producciones, que de igual manera atentan contra el sano desarrollo de los menores.\nPara asegurar lo anterior, el Estado y los municipios en el ámbito de sus respectivas competencias, deberán formular los programas necesarios para prevenir, detectar y atender las denuncias de este tipo de abusos en contra de menores, dictando al efecto, las medidas que estime pertinentes;\nIX.- Recibir cuidados, educación y asistencia especiales y adecuados en los casos de discapacidad física o mental, o con algún tipo de trastorno del desarrollo, de acuerdo a los recursos de sus padres o demás personas que los tengan a su cargo y, en su caso, del Estado o municipio correspondiente que le permitan un desarrollo integral;\nX.- La libre expresión de sus ideas y opinión en todos los asuntos que lo afecten o beneficien, cuyo ejercicio se efectuará conforme a la evolución de sus facultades edad y madurez;\nXI.- El descanso y acceso a actividades recreativas y culturales propias de su edad;\nXII.- Recibir alimentos de quienes tienen el deber de otorgárselos;\nXIII.- Su integración a un núcleo familiar;\nXIV.- Recibir particularmente de quienes ejerzan la patria potestad, tutela o custodia un trato digno y humano, para desarrollarse en un ambiente de afecto, seguridad moral y material y en general gozar de las condiciones necesarias para su estabilidad emocional y adecuado desarrollo físico y mental, que lo preparen para una vida independiente en sociedad;\nXV.- Contar con la protección legal y cuidados especiales que requiera, tanto antes como después de su nacimiento, que lo coloquen en igualdad de oportunidades, con el objeto de lograr su pleno desarrollo;\nXVI.- Recibir del Estado la protección y tutela en los casos en que peligren, se vean afectados sus derechos o se encuentre en estado de vulnerabilidad; y,\nXVII.- Gozar de todos los derechos y garantías consagradas en la Constitución\nPolítica de los Estados Unidos Mexicanos, así como las demás leyes estatales y federales.\nArtículo Reformado\nARTÍCULO 6.- La Procuraduría, así como todas las autoridades administrativas o judiciales del Estado, velarán por el respeto a los derechos del menor, y especialmente, que no sea separado de quien ejerza su legal custodia, excepto en los supuestos siguientes:\nI.- Cuando dicha separación sea por mandamiento de autoridad competente; y\nII.- En los casos de separación preventiva determinada por la Procuraduría, en los términos de la presente Ley.\nCAPÍTULO III\nDE LA TUTELA PÚBLICA DEL MENOR\nEXPÓSITO Y ABANDONADO\nARTÍCULO 7.- Serán sujetos de la tutela pública los menores expósitos o abandonados.\nARTÍCULO 8.- La tutela pública será la ejercida por el Sistema, por conducto de la\nProcuraduría, sobre el menor, hasta en tanto no se resuelva su situación jurídica por la autoridad jurisdiccional competente.\nARTÍCULO 9.- El ejercicio de la tutela quedará sujeto, en cuanto a la guarda, educación y protección de los menores, a las modalidades que le impriman las resoluciones que se dicten de acuerdo con la presente Ley y el Código Civil.\nTÍTULO SEGUNDO\nDE LA PROTECCIÓN, SEGURIDAD JURÍDICA\nY RESGUARDO DEL MENOR\nCAPÍTULO I\nDE LA PROTECCIÓN Y SEGURIDAD\nJURÍDICA DEL MENOR\nARTÍCULO 10.- La Procuraduría es la institución facultada para realizar las indagatorias tendientes a dar seguimiento a las denuncias recibidas respecto de todo tipo de situaciones que pongan en estado de vulnerabilidad a los menores, y en su caso, ponerlos bajo resguardo en los términos y con las condiciones de la presente Ley, en tanto se resuelve su situación en definitiva por la autoridad jurisdiccional; así como para imponer las sanciones establecidas en la presente Ley.\nLo anterior sin perjuicio de las funciones indagatorias del Ministerio Público, con motivo de la presunta comisión de un delito cometido en contra de los menores, en cuyo caso la calidad de coadyuvante del menor dentro de la averiguación previa o juicio respectivo.\nARTÍCULO 11.- La Procuraduría podrá solicitar de la autoridad judicial competente, California.\nDe igual forma, solicitará a la autoridad, la pérdida de la patria potestad, cuando en seguimiento de una adopción de un menor en los términos establecidos en el segundo párrafo del artículo 398 del Código Civil para el Estado de Baja California, detecte anomalías o el hecho de que la adopción resulto en perjuicio del menor, por las causas previstas en las fracciones III, IV, V y VI del artículo 441 del referido Código; o cuando él o los adoptantes hayan ejecutado conductas tipificadas en la legislación penal como delitos que conlleven aparejada la pérdida o suspensión de la patria potestad.\nArtículo Reformado\nARTÍCULO 12.- Toda persona, autoridad o institución que tenga conocimiento del posible estado de vulnerabilidad de un menor, inclusive, respecto de personas que no tengan la capacidad para comprender el significado del hecho y personas con capacidades diferentes y adultos mayores de sesenta años de edad, que se encuentren en desamparo, marginación o sujetos a maltrato, deberá de hacerlo del conocimiento de la Procuraduría, a través del procedimiento de denuncia contemplado en la presente Ley.\nLa Procuraduría recibirá en todo momento las denuncias referidas en el párrafo anterior, iniciando el procedimiento respectivo, en los términos de la presente Ley.\nArtículo Reformado\nARTÍCULO 13.- La Procuraduría protegerá y promoverá los derechos de los menores y procurará su equidad y seguridad jurídica en las relaciones en que por cualquier motivo participen, emitiendo los acuerdos necesarios para garantizar dicha protección; en los que deberá solicitar la calificación de la medida a la Autoridad\nJurisdiccional, Ministerio Público o autoridad política del lugar que corresponda, cuando así lo prevea la presente Ley.\nSimultáneamente al procedimiento interno que se inicie para brindar atención y protección a las personas adultas mayores en situación vulnerable, la Procuraduría además, en caso de proceder, solicitará judicialmente los alimentos a sus hijos o demás familiares que legalmente les corresponda dicha obligación.\nArtículo Reformado\nARTÍCULO 14.- La Procuraduría, en coordinación con las autoridades federales, estatales y municipales, en el ámbito de sus respectivas competencias, promoverá la implementación de programas, mecanismos y protocolos de seguridad que tengan por objeto la búsqueda inmediata de menores de edad desaparecidos, para lo cual podrán atender este tipo de casos y darles la difusión necesaria, a fin de facilitar su localización.\nArtículo Reformado\nCAPÍTULO II\nDEL RESGUARDO DE LOS MENORES\nARTÍCULO 15.- Cuando por cualquier motivo la Procuraduría tenga conocimiento de que un menor se encuentre en estado de vulnerabilidad, deberá protegerlo y en su caso, custodiarlo o ubicarlo en un albergue temporal, casa hogar, hogar sustituto y hogar voluntario, siguiendo los procedimientos previstos en la presente Ley.\nArtículo Reformado\nARTÍCULO 16.- Los albergues temporales, casas hogar y hogares substitutos, deberán cumplir con los requisitos establecidos en la legislación aplicable.\nPor albergue temporal se entenderá el establecimiento dependiente de la\nProcuraduría, para la atención temporal del menor en situación de vulnerabilidad.\nLos albergues temporales deberán contar con instalaciones y programas adecuados para recibir y atender a menores remitidos por el Ministerio Público cuando hayan sido sujetos del procedimiento previsto por la Ley de Justicia para Adolescentes y puestos en libertad conforme a dicho ordenamiento.\nPor casa hogar se entenderá el establecimiento de asistencia privada que atiende al menor en situación de vulnerabilidad.\nPor hogar voluntario se entenderá el espacio temporal ofrecido por una persona o familia, propuesta por la Procuraduría para tener la custodia temporal de uno o más menores, bajo la estricta vigilancia de la Procuraduría, mientras esta determine la reintegración inmediata del menor a su medio familiar o, bien, la no reintegración temporal por existir condiciones nocivas para el menor.\nArtículo Reformado\nARTÍCULO 17.- El Sistema a propuesta de la Procuraduría, remitirá anualmente al\nTitular del Ejecutivo, una propuesta de apoyos fiscales y financieros para los albergues o casas hogar, que tengan bajo su cuidado a menores puestos a disposición de la\nProcuraduría.\nTÍTULO TERCERO\nDE LA PROCURADURÍA\nCAPÍTULO I\nDEL OBJETO Y ATRIBUCIONES\nARTÍCULO 18.- La Procuraduría es el órgano especializado del Sistema, dotado de autonomía técnica y operativa con funciones de autoridad administrativa, encargado de prestar organizada y permanentemente los servicios de asistencia jurídica al menor y a la familia, así como vigilar el cumplimiento de las disposiciones legales que contemplen las obligaciones de quienes ejercen la patria potestad o tutela sobre los menores.\nARTÍCULO 19.- La Procuraduría tendrá legitimación procesal para ejercer ante los tribunales competentes, acciones tendientes a la protección del menor y la familia, en aquellos casos previstos por la legislación aplicable.\nARTÍCULO 20.- La Procuraduría para proteger eficazmente los derechos del menor y la familia, podrá recibir en todo momento, por conducto de las diversas autoridades judiciales o administrativas competentes, a cualquier menor presuntamente víctima de la comisión de algún delito, infracción o en estado de vulnerabilidad, o bien\nAdolescentes; dichas autoridades, deberán remitir a la Procuraduría, al momento de poner a su disposición al menor, la documentación que se señala en el artículo 38 de la presente Ley.\nArtículo Reformado\nARTÍCULO 21.- La Procuraduría tendrá las siguientes atribuciones:\nI.- Turnar al Ministerio Público los casos que se hagan de su conocimiento relacionados con delitos presuntamente cometidos en contra de menores;\nII.- Realizar todas las diligencias jurídicas necesarias para regularizar la situación de menores en estado de vulnerabilidad, incluyendo aquellas en las que se encuentren relacionadas las Autoridades Municipales, Estatales, Federales o en su caso autoridades de otro país, en las cuales se solicitará la cooperación internacional;\nIII.- Prestar asesoría jurídica, orientación social y psicológica a la familia, para mantener la estabilidad familiar; promoviendo la colaboración y participación de otras instancias públicas o privadas, nacionales o extranjeras, a efecto de dar una atención integral a quienes soliciten su intervención;\nIV.- Presentar denuncia y coadyuvar ante el Ministerio Público, en todos aquellos casos que se tenga la presunción de la comisión de un delito en perjuicio de menores;\nV.- Definir, elaborar y vigilar el cumplimiento de los planes sociales;\nVI.- Hacer del conocimiento del Ministerio Público todos aquellos casos que importen el ejercicio de acciones en los términos de la legislación civil, para la salvaguarda de los intereses de los menores y la familia, para efecto de que las deduzcan ante las autoridades judiciales competentes;\nVII.- Denunciar ante las autoridades competentes, toda violación a las normas que protegen los intereses del menor y la familia;\nVIII.- Coadyuvar con las autoridades educativas para que los menores concurran a las instituciones educativas a recibir educación básica exhortando a sus representantes legales o guardadores, para que los inscriban y los hagan asistir;\nIX.- Gestionar ante las autoridades correspondientes becas educativas a favor de los menores en estado de vulnerabilidad que se encuentren a su disposición, para que prosigan sus estudios y alcancen su pleno desarrollo;\nX.- Realizar todas las diligencias necesarias del área de Trabajo Social, para armónico de acuerdo a su edad y necesidades especiales, sugiriendo en su caso, un plan social para tal efecto;\nXI.- Ordenar que se realicen todas las diligencias que sean necesarias por el área de Psicología, con la finalidad de dictaminar el estado psicológico del menor y de quienes lo tienen o tenían bajo su cuidado, a efecto de determinar el plan social a seguir para la viabilidad de su reintegración al ambiente del cual provisionalmente fueron separados;\nXII.- Fomentar la creación de brigadas para la detección y prevención de problemas sociales que afecten al menor como violencia familiar, maltrato físico, sexual, psicológico o verbal, omisión de cuidados, corrupción, explotación laboral o sexual;\nXIII.- Difundir por los medios más eficaces, el conocimiento de la presente ley, a efecto de lograr su plena observancia;\nXIV.- Levantar acta circunstanciada de las actuaciones que, en el cumplimiento de la presente Ley, se realicen por la Procuraduría, a través de las subprocuradurías o coordinaciones;\nXV.- Velar porque los menores abandonados, víctimas de la violencia familiar o en estado de vulnerabilidad, obtengan provisional o definitivamente un hogar seguro;\nXVI.- Elaborar, publicar pesquisas y en su caso, publicar oficios de localización de familiares de los menores abandonados o expósitos puestos a su disposición, así como la de realizar las acciones necesarias para constatar el abandono de los menores;\nXVII.- Emitir dictámenes o resoluciones que en su caso, respalden una solicitud ante la Autoridad Jurisdiccional, Ministerio Público o Autoridad política del lugar que corresponda, respecto de la separación cautelar o temporal de los menores u otros incapaces que se encuentren en estado de vulnerabilidad a efecto de proteger su integridad física y psico-emocional, en tanto se resuelve jurisdiccionalmente su situación definitiva;\nXVIII.- Realizar las acciones necesarias para brindar atención y protección integral a los menores u otros incapaces que realicen actividades de riesgo en la calle o lugares públicos, o sean objeto de explotación laboral o sexual, o inducidos a realizar actividades de corrupción;\nXIX.- Gestionar en su caso, ante el Oficial del Registro Civil de los distintos ayuntamientos del estado, la elaboración del acta de nacimiento de los menores expósitos o abandonados;\nXX.- Solicitar a otras instancias públicas o privadas ya sean federales, estatales o municipales inclusive extranjeras, diversas peticiones, documentos, estudios sociales, valoraciones psicológicas, comparecencias documentadas de personas y demás que sean necesarias para la debida integración de los expedientes administrativos a su cargo;\nXXI.- Solicitar a la autoridad, la pérdida de la patria potestad, cuando en párrafo del artículo 398 del Código Civil para el Estado de Baja California, detecte anomalías o el hecho de que la adopción resultó en perjuicio del menor, por las causas previstas en las fracciones III, IV, V y VI del artículo 441 del referido Código; o cuando él o que conlleven aparejada la pérdida o suspensión de la patria potestad; y\nXXII.- Las demás contempladas en otras disposiciones legales que sean aplicables para el cumplimiento de su objetivo.\nArtículo Reformado\nARTICULO 21 BIS.- La Procuraduría, llevará a cabo el registro de las adopciones que se promuevan ante los juzgados de la Entidad, con el objeto de conservar la información correspondiente a los orígenes del menor adoptado, incluyendo la identidad de sus progenitores, su historia médica y de su familia, debiendo además, conservar los datos de identificación del proceso, incluyendo el tribunal que autorizó la adopción; así como la información correspondiente de los padres adoptivos.\nArtículo Reformado\nLa información obtenida, tendrá el carácter de confidencial y, sólo será proporcionada a las autoridades, en los siguientes supuestos:\nI.- Cuando el adoptado mayor de edad desee conocer sus antecedentes familiares; si fuere menor de edad se requerirá el consentimiento del o de los adoptantes;\nII.- Para cumplir los fines del artículo 403 del Código Civil para el Estado de Baja\nCalifornia;\nCuando sea solicitada vía oficio por las diversas autoridades administrativas competentes en el tema de adopciones, con el único fin de llevar a cabo su registro, control y estadística.\nCAPÍTULO II\nDE LA ESTRUCTURA\nARTÍCULO 22.- El titular de la Procuraduría será el Procurador, quien para el ejercicio de sus atribuciones, funciones y despacho, se auxiliará de las siguientes áreas y servidores públicos:\nI.- La Subprocuraduría Estatal;\nII.- Las Subprocuradurías asignadas a cada Municipio del Estado;\nIII.- Coordinación de Adopciones;\nIV.- Coordinación de Asistencia Privada;\nV.- Coordinación de Albergues y Módulos temporales; y,\nVI. Las demás que sean necesarias para el cumplimiento de sus atribuciones que señalen la presente Ley y demás disposiciones legales aplicables.\nProcurador.\nPara ocupar el cargo de cualquiera de las Coordinaciones antes señaladas, se deberán cumplir con los requisitos previstos en las fracciones I, III, IV, V, VI y VII del artículo 24 de la presente Ley.\nArtículo Reformado\nARTÍCULO 23.- Los titulares de las áreas señaladas en el artículo anterior, serán nombrados y/o removidos por el Director a propuesta del Procurador; y tratándose del\nProcurador será nombrado y removido por el Director y ratificado por la Junta de Gobierno del Sistema.\nARTÍCULO 24.- Para ocupar el cargo de Procurador o Subprocurador, se requiere:\nI.- Ser ciudadano mexicano por nacimiento y estar en pleno goce y ejercicio de sus derechos políticos y civiles;\nII.- Tener Título de Licenciado en Derecho con una antigüedad mínima al día de la designación de tres años, debidamente expedido por una institución legalmente facultada para ello; y contar con cedula profesional Federal y Estatal;\nIII.- Tener una reconocida solvencia moral y social;\nIV.- No haber sido condenado por delito intencional, que amerite pena corporal de más de un año de prisión, pero si se tratare de robo, fraude, falsificación, abuso de confianza, lesiones, o cualquier delito cometido en contra de menores, cualquiera que haya sido la pena, no calificará para dicho cargo;\nV.- Tener residencia en el Estado durante los cinco años anteriores al día de la designación;\nVI.- Tener vocación y conocimiento sobre la problemática de los menores y la familia; y,\nVII.- Tener cuando menos treinta años cumplidos el día de la designación.\nEl Procurador residirá en la Capital del Estado, y en el desempeño de sus funciones, realizará cuantas visitas estime necesarias a las distintas dependencias de la\nProcuraduría.\nARTÍCULO 25.- El Procurador tendrá las facultades y obligaciones siguientes:\nI.- Acordar en forma periódica con el Director, el despacho general de los asuntos de su competencia, así como proponer lo que se estime conveniente para mejorar el servicio;\nII.- Emitir a sus colaboradores las instrucciones generales y especiales que estime convenientes para la unidad de criterio y acción a favor de los menores y la familia, para el mejor cumplimiento de sus funciones;\nIII.- Proponer al Director los anteproyectos de ley, reglamentos, decretos, acuerdos, convenios, acciones y mecanismos, relativos a los asuntos de su competencia;\nIV.- Poner en conocimiento del Consejo de la Judicatura, del Procurador General de Justicia del Estado, del Secretario de Seguridad Pública del Estado y de los titulares de las distintas dependencias, las irregularidades que se adviertan y que perjudiquen los derechos fundamentales de los menores, con la finalidad de que se adopten las medidas pertinentes, considerando siempre el interés superior del menor y la familia;\nV.- Ejecutar en la esfera de su competencia, las facultades, obligaciones y atribuciones señaladas por las disposiciones legales aplicables;\nVI.- Conceder audiencias al público que lo solicite, para tratar asuntos de su competencia;\nVII.- Dictar las medidas necesarias para unificar las actuaciones de las\nSubprocuradurías y demás áreas de la Procuraduría;\nVIII.- Designar en caso de ausencia, falta o excusa de uno de los servidores públicos, la persona que temporalmente desempeñe las funciones inherentes al cargo;\nIX.- Imponer a sus subalternos las correcciones disciplinarias necesarias por faltas en que incurran en el desempeño de sus funciones, de conformidad con la Ley aplicable;\nX.- Rendir al Director los informes que éste pida o el mismo estime necesarios sobre los asuntos de su competencia;\nXI.- Llevar el control administrativo y del personal de su dependencia a efecto de supervisar y evaluar el desempeño de las labores del personal bajo su cargo;\nXII.- Vigilar y procurar la integración o en su caso, la reintegración familiar de los menores, siempre y cuando esto sea posible conforme al interés superior del menor y la familia;\nXIII.- Expedir copias certificadas de sus resoluciones;\nXIV.- Delegar a los Subprocuradores las atribuciones que sean necesarias para correcto desempeño de sus funciones; y,\nXV.- Fe pública, para efecto de dar cumplimiento al artículo 394 BIS fracción V segundo párrafo.\nXVI.- Las demás que le sean encomendadas por el Director y las señaladas en otras disposiciones legales aplicables.\nArtículo Reformado\nARTICULO 25 BIS.- El Subprocurador Estatal tendrá las facultades y obligaciones siguientes:\nI. Constituirse como coadyuvante del Procurador en el control administrativo de las\nSubprocuradurías, sus Delegaciones y demás Coordinaciones de Áreas, así como del personal bajo su responsabilidad, a efecto, de supervisar y evaluar el desempeño de sus labores encomendadas;\nII. Informar permanentemente al Procurador las actividades realizadas, en las\nSubprocuradurías del Estado, sus Delegaciones y demás Coordinaciones, y que con anterioridad le hubieren sido encomendadas;\nIII. Constituirse en un enlace de comunicación, coordinación y ejecución de acciones entre el Procurador, Subprocuradores y Coordinadores de Áreas;\nIV. Llevar a cabo la supervisión y evaluación permanente de los expedientes más relevantes que se integran en cada una de las Subprocuradurías del Estado y sus\nDelegaciones, así como definir la política en su conducción, de manera conjunta con el\nSubprocurador responsable del mismo; lo anterior, con apego estricto a derecho y tomando siempre en consideración el interés del menor y la familia;\nV. A ser informado por conducto de los Subprocuradores responsables, sobre los proyectos de determinación correspondientes a los expedientes más relevantes a cargo de la Subprocuraduría que representan, ha efecto de que su opinión o recomendación debidamente fundamentada en ley sea tomada en consideración, privilegiando siempre el interés superior del menor y la familia;\nVI. Supervisar y evaluar el cumplimiento de los acuerdos y compromisos asumidos entre los padres o las personas responsables del cuidado de los menores y el personal profesional de las distintas áreas que conforman cada una de las subprocuradurías y sus delegaciones, plasmados en las mismas determinaciones;\nVII. Brindar asesoría a los Subprocuradores, Coordinadores de Áreas y demás empleados que conforman las distintas áreas pertenecientes a las Subprocuradurías y\nDelegaciones en el Estado, cuando así lo considere necesario, o en su caso, se lo soliciten;\nVIII. Investigar de oficio o por medio de denuncia, las presuntas irregularidades funciones, y en caso de responsabilidad, promover lo conducente;\nIX. Actuar en representación del Procurador cuando le sea asignada alguna comisión especial; y\nX. Las demás que le sean encomendadas por el Procurador y Director General del\nSistema Estatal para el Desarrollo Integral de la Familia.\nArtículo Adicionado\nARTÍCULO 26.- Operarán bajo el régimen de desconcentración, pero directamente subordinadas al Procurador, las siguientes Subprocuradurías:\nI.- Subprocuraduría para la Defensa del Menor y la Familia en Mexicali, que comprenderá el Municipio de Mexicali;\nII.- Subprocuraduría para la Defensa del Menor y la Familia en Tijuana, que comprenderá el Municipio de Tijuana;\nIII.- Subprocuraduría para la Defensa del Menor y la Familia en Tecate, que comprenderá el Municipio de Tecate;\nIV.- Subprocuraduría para la Defensa del Menor y la Familia en Ensenada, que comprenderá el Municipio de Ensenada; y,\nV.- Subprocuraduría para la Defensa del Menor y la Familia en Playas de Rosarito, que comprenderá el Municipio de Playas de Rosarito.\nVI.- Delegación de la Subprocuraduría para la Defensa del Menor y la Familia en el\nPoblado de San Felipe, perteneciente al Municipio de Mexicali;\nVII.- Delegación de la Subprocuraduría para la Defensa del Menor y la Familia en el\nPoblado de San Quintín, perteneciente al Municipio de Ensenada.\nDe conformidad a las necesidades del servicio, el Director a propuesta del\nProcurador podrá establecer otras delegaciones de la Procuraduría en poblaciones de la entidad donde se requieran, de acuerdo a las disponibilidades presupuestales.\nArtículo Reformado\nARTÍCULO 27.- Por cada Subprocuraduría, habrá un Subprocurador que tendrá las siguientes atribuciones:\nI.- Representar al Procurador en el Municipio de adscripción;\nII.- Auxiliar al Procurador en las funciones que le sean conferidas;\nIII.- Acordar con el Procurador los asuntos relacionados con la Subprocuraduría de conducto del Subprocurador Estatal;\nIV.- Someter a la aprobación del Procurador directamente o por conducto del\nSubprocurador Estatal, los estudios y proyectos de trascendencia que se elaboren en el área de su responsabilidad;\nV.- Conceder audiencias al público que lo solicite para tratar asuntos del área de su competencia;\nVI.- Informar mensualmente al Procurador de los asuntos de su competencia;\nVII.- Mantener informado al Procurador del estado que guardan los asuntos que por su importancia y trascendencia requieran de su atención personal; pudiéndolo hacer a través del Subprocurador Estatal; y,\nVIII.- Transmitir al personal a su cargo, las instrucciones generales y especiales para el cumplimiento de sus atribuciones y funciones; y,\nIX.- Las demás que le sean encomendadas legalmente por el Procurador, o estén señaladas en las disposiciones legales aplicables.\nArtículo Reformado\nARTÍCULO 28.- Las Subprocuradurías para el desempeño de sus funciones, contarán con las siguientes áreas:\nI.- Área Jurídica;\nII.- Área de Psicología;\nIII.- Área de Trabajo Social;\nIV.- Área de Recepción y Canalización; y,\nV.- Las demás que sean necesarias para el cumplimiento de las atribuciones de las\nSubprocuradurías.\nARTÍCULO 29.- El Área Jurídica, tendrá las siguientes facultades:\nI.- Otorgar asesoría al público que así lo solicite;\nII.- Integrar debidamente los expedientes a su cargo tanto física como electrónicamente;\nIII.- Promover y gestionar los tramites judiciales y administrativos que sean necesarios para regularizar la situación jurídica de los menores que se encuentren bajo tutela de la Procuraduría;\nIV.- Visitar semanalmente los albergues temporales para conocer personalmente a los menores bajo tutela de la Procuraduría;\nV.- Ordenar al área de trabajo social, las investigaciones e informes que requiera ante la Procuraduría;\nVI.- Ordenar al área de Psicología, los estudios y dictámenes necesarios para la\nProcuraduría;\nVII.- Por conducto de la Procuraduría presentar denuncias ante el Ministerio\nPúblico de los hechos presuntamente constitutivos de delitos en perjuicio de menores, del hecho, de los cuales tengan conocimiento en el ejercicio de sus funciones;\nVIII.- Por conducto del Procurador o Subprocurador o Delegado en su caso, solicitar cuando sea necesario, el apoyo o auxilio de los cuerpos de seguridad pública, estatales o municipales, para el ejercicio de sus funciones;\nIX.- Ordenar la comparecencia, mediante citatorios, de las personas involucradas en las denuncias que se presenten ante la Procuraduría;\nX.- Concluidas las actuaciones del día y agregados los documentos recibidos, vigilar que estos sean foliados y que el sello de la Procuraduría esté colocado en el fondo del expediente físico, de manera que abarque las dos caras;\nXI.- Ser coadyuvante del Ministerio Público y aportar las pruebas con que cuente, cuando en el ejercicio de sus funciones haya tenido conocimiento de hechos presuntamente constitutivos de un delito en contra de menores;\nXII.- Autorizar las diligencias y actuaciones que se practiquen;\nXIII.- Apoyar a la Coordinación de Asistencia a Acreedores Alimentarios en la solicitud de aseguramiento de alimentos a favor del acreedor alimentario solicitante; y,\nXIV. Las demás que le sean encomendadas legalmente por el Procurador o el\nSubprocurador en su caso, o le señalen las disposiciones legales aplicables.\nARTÍCULO 30.- El Área Jurídica se conforma con los agentes procuradores necesarios para atención de las atribuciones de la Procuraduría, quienes deberán contar con título de licenciado en derecho.\nARTÍCULO 31.- Compete al área de Psicología, lo siguiente:\nI.- Atender a las personas que lo soliciten;\nII.- Otorgar entrevistas, terapias, consultas, aplicar exámenes y pruebas psicológicas, emitir dictámenes mismos que deberán contener un diagnóstico y las familia; así como realizar todas aquellas diligencias necesarias para la atención de los menores bajo tutela de la Procuraduría, así como a sus padres o las personas que los hayan tenido bajo su cuidado cuando se considere necesario;\nIII.- Atender a los solicitantes de adopción, realizar el estudio psicológico correspondiente y emitir dictamen al respecto;\nIV.- Proponer las medidas que sean necesarias cuando el interés superior del\nMenor y la Familia, así lo requiera;\nV.- Cuando lo considere necesario, el Área de Psicología solicitará al\nSubprocurador, las canalizaciones correspondientes con la finalidad de que los menores o sus familiares reciban la atención especializada; y,\nVI.- En general, todas aquellas que le sean encomendadas legalmente por el\nProcurador, el Subprocurador o por el Área Jurídica, o en su caso, cuando así lo establezcan las disposiciones legales aplicables.\nARTÍCULO 32.- El Área de Psicología se conformará con los psicólogos necesarios para atención de las atribuciones de la Procuraduría, quienes deberán contar con el título de licenciado en psicología.\nARTÍCULO 33.- Compete al Área de Trabajo Social, lo siguiente:\nI.- Atender de manera inmediata las denuncias recibidas por la Procuraduría, y en las que se encuentren en riesgo la seguridad, integridad o dignidad del Menor y la Familia;\nII.- Realizar las investigaciones que sean necesarias en atención a la fracción anterior, levantando los informes detallados correspondientes;\nIII.- Informar al área jurídica las actividades desarrolladas;\nIV.- Por conducto de la Procuraduría, denunciar ante el Ministerio Público los hechos de los que tuviere conocimiento, en los cuales se puedan afectar los derechos fundamentales del Menor y la Familia;\nV.- Elaborar los estudios necesarios para la debida y oportuna integración de los expedientes, mismos que deberán contener un diagnóstico y las recomendaciones necesarias para mejorar las condiciones sociales del menor y la familia; y dar seguimiento a las denuncias recibidas;\nVI.- Atender a los solicitantes de adopción, realizar el estudio socioeconómico correspondiente y emitir dictamen al respecto; y,\nVII.- En general, todas aquellas actividades que le sean encomendadas legalmente por el Procurador, el Subprocurador o por el Área Jurídica, o en su caso, cuando así lo establezcan las disposiciones legales aplicables.\nARTÍCULO 34.- El área de Trabajo Social se conformará con el personal necesario para la atención de las atribuciones de la procuraduría.\nARTÍCULO 35.- La Coordinación de Adopciones tendrá las siguientes atribuciones:\nI.- Acordar con el Procurador, y en su caso con los Subprocuradores, los requisitos menor;\nII.- Revisar los expedientes de aquellos menores que pueden ser viables para ser considerados en hogar substituto o en vías de adopción;\nIII.- Recibir a los solicitantes de adopción, asesorándolos sobre los trámites administrativos necesarios para lograr legalmente la adopción de un menor;\nIV.- Dar seguimiento a los solicitantes de adopción presentados en la Procuraduría o Subprocuraduría;\nV.- Vigilar la debida integración de los expedientes de los solicitantes de adopción;\nVI.- Proponer al Procurador aquellos expedientes de solicitantes de adopción que se encuentren completos y debidamente integrados para ser considerados por el Consejo;\nVII.- Promover ante el Sistema Nacional para el Desarrollo Integral de la Familia, así como los Sistemas Estatales para el Desarrollo Integral de la Familia, la recepción de menores bajo la disposición del Sistema, y que por su situación especial resulta difícil colocarlo en hogar sustituto con personas residentes de esta entidad;\nVIII.- Recibir las solicitudes de ciudadanos nacionales residentes en otras entidades federativas del país; y,\nIX.- Las demás que le sean encomendadas legalmente por el Procurador, o en su caso, le señalen las disposiciones legales aplicables.\nArtículo Reformado\nARTICULO 35 BIS.- La Coordinación de Adopciones, del Sistema, será el área encargada de dar trámite y seguimiento a las solicitudes de adopción que se reciban del\nSistema Nacional para el Desarrollo Integral de la Familia o la Consultoría Jurídica de la\nSecretaría de Relaciones Exteriores, provenientes de las autoridades centrales designadas por los países que han ratificado la Convención sobre la Protección de\nMenores y la Cooperación en Materia de Adopción Internacional.\nLa Coordinación de Adopciones, también se encargará de mantener contacto permanente e intercambio de información y documentación con dichas autoridades centrales, antes de iniciar los trámites legales de adopción, durante su seguimiento ante el\nJuez de conocimiento, y hasta que concluya la aplicación de la Convención, en los términos establecidos en la misma.\nArtículo Adicionado\nARTICULO 35 TER.- La Coordinación de Adopciones en el cumplimiento de sus funciones deberá cumplir con las siguientes directrices:\nI.- Agotar el principio de subsidiaridad, al constatar que, después de examinar adecuadamente las posibilidades de colocación del menor en el país, la adopción internacional responde al interés superior del propio menor;\nII.- Cerciorarse de que no existe o habrá contacto alguno entre los futuros padres adoptivos y los padres del menor u otras personas que tengan la guarda de este, hasta que se hayan cumplido las condiciones del artículo 387 fracción VII, incisos a) al e) del lugar entre familiares;\nIII.- Gestionar el informe de compatibilidad de la adopción que expedirá el\nProcurador, relativo a un menor adoptado por ciudadanos extranjeros radicados en otro país, bajo los términos establecidos en el artículo 16 de la Convención sobre la Protección de Menores y la Cooperación en Materia de Adopción Internacional;\nIV.- Cerciorarse que el Sistema, por conducto de la Procuraduría, en su carácter de\nAutoridad Central en la aplicación de la Convención sobre la Protección de Menores y la\nCooperación en Materia de Adopción Internacional, sólo podrá confiar al menor a los futuros padres adoptivos si se ha corroborado por lo menos de lo siguiente:\na).- Se ha asegurado de que los futuros padres adoptivos han manifestado su acuerdo con la adopción que se intenta;\nb).- Que la Autoridad Central del Estado de Recepción de los solicitantes radicados en el extranjero, ha aprobado la decisión anterior;\nc).- Que el Sistema, y la Autoridad Central del Estado de recepción, están de acuerdo en que la autoridad judicial de esta Entidad Federativa y del país continúen con el procedimiento de adopción;\nd).- Se ha constatado que los futuros padres adoptivos son adecuados y aptos para adoptar y que el menor ha sido o será autorizado para entrar y residir permanentemente en el Estado de Recepción de los solicitantes radicados en el extranjero,\nV.- Que la adopción que se promueve, obedece al interés superior del propio menor,\nVI.- Tomar las medidas necesarias para que el menor adoptado, reciba la autorización de salida del país, así como la entrada y residencia en el estado de recepción; esto último con la cooperación de la Autoridad Central del país de origen de los adoptantes residentes en el extranjero;\nVII.- Prohibir el desplazamiento del menor adoptado al país de origen de los solicitantes, si no se han observado las exigencias anteriores, debiéndose además asegurar que su desplazamiento se realizará con toda seguridad, en condiciones adecuadas y, siempre en compañía de los padres adoptivos;\nVIII.-Recibir las solicitudes de ciudadanos nacionales residentes en otras entidades federativas del país.\nArtículo Adicionado\nARTÍCULO 36.- Compete a la Coordinación de Asistencia Privada, lo siguiente:\nI.- Supervisar permanentemente la atención y cuidados que las instituciones públicas o privadas brindan a los menores que reciben en sus establecimientos;\nII.- Realizar las recomendaciones que estimen convenientes a las instituciones privadas o casas hogar para mejorar las condiciones de cuidados de los menores;\nIII.- Contar con un padrón actualizado de los menores que se encuentren en instituciones privadas de asistencia o casas hogar;\nIV.- Vigilar la debida integración de los expedientes de los menores puestos a disposición de la Procuraduría, que se encuentren en casas hogar;\nV.- Por conducto de la Procuraduría, presentar denuncias ante el Ministerio\nPúblico, por actos u omisiones que pudieran constituir delitos que se adviertan en el funcionamiento de las instituciones privadas o casas hogar;\nVI.- Proponer a las Subprocuradurías, la revisión de expedientes de los menores que tengan más de dos años a disposición de la Procuraduría y se encuentran en casas hogar para lograr su reintegración;\nVII.- Promover ante las instituciones privadas o casas hogar, la implementación de acciones tendientes a la capacitación y reintegración social y laboral de los menores para ofrecerles una opción de desarrollo y autosuficiencia al salir de la institución;\nVIII.- Atender las solicitudes de reubicación de menores, que considere necesarias como resultado de las supervisiones que realice, o a petición de la Coordinación de\nAlbergues Temporales o de las Subprocuradurías; y,\nIX.- En general, todas aquellas que le sean encomendadas legalmente por el\nProcurador, o en su caso, le señalen las disposiciones legales aplicables.\nARTÍCULO 37.- Compete a la Coordinación de Albergues Temporales, lo siguiente:\nI.- Someter a consideración del Procurador, la organización interna de las unidades a su cargo;\nII.- Proponer al Procurador los lineamientos de operación y atención de los albergues y módulos de recepción y atención a menores migrantes y repatriados;\nIII.- Gestionar de forma inmediata, los trámites necesarios para la atención médica u condición así lo requiera; y\nIV.- Informar de manera inmediata al Procurador de cualquier situación que se presente en la unidad a su cargo, y que requiera la atención y conocimiento personal de éste;\nV.- Autorizar el ingreso a los Albergues de los menores remitidos por la\nSubprocuradurías, Ministerio Público o cualquier autoridad competente, siempre y cuando se cumplan con los requisitos previstos por esta Ley para tal efecto;\nVI.- Transmitir al personal a su cargo, las instrucciones generales y especiales para el cumplimiento de sus atribuciones y funciones;\nVII.- Tomar todas las medidas necesarias para garantizar el bienestar de los recepción y atención menores migrantes y repatriados, informado de éstas al Procurador;\nVIII.- Llevar un control y seguimiento de los expedientes de los menores que se encuentren en los albergues temporales, debiendo informar al Procurador los casos que requieran una especial atención;\nIX.- Planear y coordinar las actividades inherentes a su cargo en las que debe predominar el interés superior de los menores y la familia;\nX.- Solicitar a las Subprocuradurías, la reubicación de menores a casas hogar o instituciones de asistencia privada cuando su atención así lo requiera, y,\nXI.- En general todas aquellas que legalmente le sean encomendadas por el\nProcurador, o le señalen las disposiciones legales aplicables.\nARTÍCULO 37 BIS.- Compete a la Coordinación de Asistencia a Acreedores\nAlimentarios, lo siguiente:\nI. Otorgar asesoría, a quienes lo soliciten, sobre el derecho de pensión alimenticia;\nII. Orientar a los acreedores alimentarios sobre como solicitar la pensión alimenticia, y en el caso que sea necesario, coadyuvarlo para poder hacer la presentación de dicha solicitud ante la autoridad correspondiente;\nIII. Integrar debidamente los expedientes a su cargo tanto física como electrónicamente;\nIV. Canalizar apropiadamente al acreedor alimentario a la Defensoría Pública en el alimenticia;\nV. Al tener conocimiento de la comisión de un delito a raíz del incumplimiento del pago de pensión alimenticia a un acreedor alimentario, inmediatamente hacerle del conocimiento al Ministerio Público para que se proceda debidamente;\nVI. Por medio de las áreas jurídicas de las Subprocuradurías, solicitar a la que lo haya gestionado, aportando lo necesario para que se pueda realizar dicha acción;\nVII. Promover el derecho de pensión alimenticia, mediante campañas informativas permanentes; y\nVIII. Mantener una base de datos de acreedores alimentarios asistidos y darle seguimiento oportuno a cada uno de los casos atendidos.\nArtículo Adicionado\nARTÍCULO 38.- Para que pueda ser autorizado el ingreso de un menor a un albergue temporal, la autoridad que solicite dicho ingreso, deberá de remitir cuando menos el oficio mediante el cual sea puesto a disposición de la Procuraduría; el cual, deberá especificar los efectos de la medida, una breve narración del motivo del ingreso, los generales del menor, incluyendo los nombres de sus familiares, tratándose de menores víctimas de delitos, o menores que hayan sido sujetos a proceso conforme a la\nLey de Justicia para Adolescentes, deberá acompañarse copia de las valoraciones médicas y los estudios practicados por el Ministerio Público.\nArtículo Reformado\nARTÍCULO 39.- Al ingresar un menor a un albergue temporal, se deberá integrar un expediente que contendrá los requisitos fijados en el Reglamento.\nTÍTULO CUARTO\nDE LOS PROCEDIMIENTOS\nCAPÍTULO I\nDEL PROCEDIMIENTO DE PROTECCIÓN Y RESGUARDO DE MENORES EN\nESTADO DE VULNERABILIDAD\nARTÍCULO 40.- Toda persona que tenga conocimiento de que algún menor se encuentre en estado de vulnerabilidad, está obligada a denunciarlo ante la Procuraduría, en forma escrita, personal, telefónica o electrónica, proporcionando si fuera posible, la información siguiente:\nI.- Nombre y domicilio del denunciante;\nII.- Domicilio o descripción del lugar donde ocurre el hecho que denuncia;\nIII.- Descripción del hecho denunciado; y,\nIV.- El nombre y domicilio del menor en estado de vulnerabilidad.\nLa Procuraduría, podrá recibir denuncias anónimas, en cuyo caso tendrá la hecho.\nARTÍCULO 41.- La Procuraduría, al recibir una denuncia, ordenará por medio del\nÁrea Jurídica, el inicio de una investigación, misma que estará a cargo del Área de\nTrabajo Social.\nSi de la investigación resulta que el menor se encuentra en situación de peligro, la\nProcuraduría podrá trasladarlo a un albergue temporal; en cuyo caso, deberá informar dentro de las cuarenta y ocho horas siguientes de la decisión dictada, al Ministerio Público o al Juez competente o bien, a la autoridad política del lugar que corresponda, para que califique la medida preventiva adoptada y en su caso, inicien las actuaciones necesarias, en el ámbito de su competencia, para determinar la situación legal del menor.\nAunado a lo anterior, la Procuraduría llevará a cabo las diligencias y actuaciones necesarias para proteger y salvaguardar los derechos fundamentales del menor.\nUna vez que todas las áreas de la Procuraduría hayan realizado sus investigaciones, estudios, pruebas, dictámenes y en general, todas las diligencias necesarias, la Procuraduría recomendará a la autoridad que tenga bajo su disposición al menor, la reintegración inmediata del menor a su medio familiar o, bien, la no reintegración temporal por existir condiciones nocivas para el menor.\nEn el último supuesto a que se refiere el párrafo anterior, la Procuraduría recomendará también el cumplimiento de un Plan Social y su duración, así como la ubicación del menor en una institución pública, privada u hogar voluntario con la finalidad de que reciba las atenciones e instrucciones adecuadas a su edad y nivel de madurez, en tanto, la autoridad competente determine su reintegración.\nEl tiempo que en el menor deba estar ubicado en las instalaciones señaladas en el párrafo anterior, será determinado, con base a las consideraciones individuales de cada caso, por la autoridad competente a propuesta de la Procuraduría.\nSi la autoridad competente aplica las medidas a que se refiere el párrafo anterior, la\nProcuraduría vigilará sobre su cumplimiento; y de persistir las condiciones nocivas para el menor en su entorno familiar, solicitará se resuelva sobre la custodia del menor a la\nAutoridad Jurisdiccional, y se de vista a la Representación Social, a efecto de que se inicien las gestiones necesarias para determinar su situación jurídica definitiva.\nSi de las investigaciones realizadas por la Procuraduría, no se consideró necesaria la separación preventiva de algún menor, pero a su juicio existen indicios de la posible comisión de algún delito, se hará del conocimiento inmediato del Ministerio Público.\nArtículo Reformado\nARTÍCULO 42.- Cuando se trate de menores puestos a disposición de la\nProcuraduría por autoridad competente, se seguirá en lo que resulte aplicable, el procedimiento previsto en el artículo anterior.\nARTÍCULO 43.- Las determinaciones de la Procuraduría deberán ser notificadas\nAdministración Pública del Estado de Baja California.\nCAPÍTULO II\nARTÍCULO 44.- La Procuraduría en ejercicio de las atribuciones conferidas por la legislación civil, promoverá el inicio del trámite de asignación en hogar sustituto en vías de adopción, de menores expósitos y abandonados.\nARTÍCULO 45.- La Procuraduría notificará en los términos del artículo 43 de la presente Ley, la resolución de inicio del trámite a que se refiere el artículo anterior, para efecto de que quienes se crean con derecho a reclamar al menor, comparezcan dentro de un plazo de cinco días hábiles contados a partir del día siguiente de la publicación, para efecto de que comparezcan personalmente ante la Procuraduría a manifestar lo que a su derecho convenga respecto a dicha asignación.\nLa Procuraduría en un término de nueve días hábiles, y tomando en consideración los estudios, dictámenes, declaraciones y demás pruebas obrantes en el expediente del menor, resolverá sobre la procedencia de las manifestaciones formuladas por la parte interesada; y en caso de estimarse fundadas, se le indicará al solicitante el plan social y demás condiciones que deberá cumplir para lograr la reintegración del menor. En caso de resultar infundadas aquellas, el menor será puesto a consideración del Consejo para su asignación a un hogar sustituto en vías de adopción, conforme al procedimiento fijado en su Decreto de creación.\nLa autoridad Judicial podrá autorizar que la estancia de menores en hogares sustitutos sea hasta por un periodo de noventa días, mismos que podrán ser prorrogables.\nCAPÍTULO III\nDE LA CONCILIACIÓN\nARTÍCULO 46.- La Procuraduría a través de las Subprocuradurías, podrá auxiliar a las familias a resolver sus diferencias mediante el presente procedimiento de conciliación.\nARTÍCULO 47.- No podrán estar sujetas a este procedimiento las controversias sobre acciones o derechos de carácter civil irrenunciables o aquellas acciones que constituyan un delito, que se persigan de oficio o pudieran poner al menor en estado de vulnerabilidad.\nARTÍCULO 48.- Antes de iniciar el procedimiento conciliatorio, se les informará a las partes el contenido y alcance de esta Ley, de los derechos que les asisten y de los procedimientos administrativos, civiles o penales que existan en la materia, así como de reincidencia.\nARTÍCULO 49.- El procedimiento conciliatorio se iniciará a petición de una de las partes o ambas. Para acudir a él, se requerirá, notificación personal previa.\nARTÍCULO 50.- La Procuraduría señalará día y hora para la celebración de una de audiencia de conciliación en la que se procurará avenir los intereses de las partes, procurando siempre el interés superior del Menor y la Familia, la cual no deberá de exceder de cinco días hábiles siguientes a la fecha de notificación.\nARTÍCULO 51.- En caso de que cualquiera de las partes en conciliación no se presente a la audiencia, se les impondrá medida de apremio y se citará a una segunda audiencia, en un plazo no mayor de diez días. dentro de los siguientes diez días hábiles justificación fehaciente de su inasistencia, se tendrá por desistido de la reclamación y no podrá presentar otra ante la Procuraduría por los mismos hechos.\nSi la contraparte no asiste, se le tendrá por inconforme con la conciliación, dándose por concluido el procedimiento.\nARTÍCULO 52.- La Procuraduría podrá en todo momento requerir a las partes los elementos de convicción que estime necesarios para la conciliación, así como para el ejercicio de las atribuciones que a la Procuraduría le confiere la Ley. Asimismo, podrá acordar la práctica de diligencias que permitan acreditar los hechos constitutivos de la denuncia. Las partes podrán aportar las pruebas que estimen necesarias para acreditar su dicho.\nARTÍCULO 53.- El conciliador podrá suspender la audiencia de conciliación cuando lo estime pertinente o a instancia de ambas partes, a efecto de que valoren y acepten las propuestas de conciliación, por una sola ocasión.\nEn caso de que se suspenda la audiencia, el conciliador señalará día y hora para su reanudación, dentro de los quince días siguientes, donde en su caso, podrá emitir un acuerdo de trámite que ordene un estudio de trabajo social y psicológico.\nDe toda audiencia se levantará el acta respectiva, debiendo ser firmada y ratificada por las partes y validada por el Subprocurador o Procurador en su caso.\nARTÍCULO 54.- Si el conflicto se resolviera mediante la conciliación y existiera un litigio en relación con el mismo asunto, se le remitirá al Juez de la causa el convenio correspondiente para los efectos legales a que haya lugar.\nARTÍCULO 55.- Como parte del convenio que se celebre, se establecerá la obligación de las partes de asistir a terapia familiar y el cumplimiento del plan social que en su caso, les fuere asignado.\nARTÍCULO 56.- En todos los casos en que se trate o afecte a menores, antes de convenir las partes sobre su situación, se deberá hacer del conocimiento del Ministerio\nPúblico o de la Autoridad Jurisdiccional, a efecto de que intervengan en lo que corresponda.\nARTÍCULO 57.- Los convenios celebrados ante la Procuraduría traen aparejada ejecución, por lo que el interesado podrá promover su cumplimiento ante los tribunales competentes en juicio ejecutivo.\nARTÍCULO 58.- El convenio celebrado deberá contener lo siguiente:\nI.- Lugar y fecha de emisión;\nII.- Nombre de la autoridad ante quien se celebra;\nIII.- Nombre y domicilio de las partes;\nIV.- El tipo de convenio de que se trate;\nV.- Las cláusulas que especifiquen el convenio;\nVI.- La firma de las partes celebrantes, y su ratificación.\nEl convenio surtirá sus efectos legales desde el momento que sea ratificado por las partes ante la Procuraduría.\nCAPÍTULO IV\nDE LAS INFRACCIONES Y SANCIONES.\nARTÍCULO 59.- Se consideran Infracciones:\nI.- El no asistir, sin causa justificada a los citatorios emitidos por la Procuraduría a través de las subprocuradurías;\nII.- El incumplimiento de la obligación que tienen los jefes, directores o administradores de centros de reclusión, y de cualquier casa hogar, hospital e inclusa, de hacer del conocimiento de la Procuraduría de los menores abandonados o expuestos en ellas.\nARTÍCULO 60.- Las sanciones aplicables para las infracciones descritas en el artículo anterior, atendiendo a su gravedad que podrán consistir en alguna o algunas de las siguientes:\nI.- Amonestación por escrito;\nII.- Multa de diez a ochenta días de salario mínimo general vigente en la capital del\nEstado al momento de cometerse la infracción;\nSi el infractor fuese jornalero, obrero o trabajador asalariado, la multa será equivalente a un día de su jornal o ingreso diario;\nIII.- Arresto administrativo hasta por treinta y seis horas.\nARTÍCULO 61.- Para que pueda ser aplicada una sanción de las señaladas en el artículo anterior, deberá existir constancia de que se ha comprobado y documentado el hecho que se atribuye.\nARTÍCULO 62.- En todo lo no previsto en la presente Ley, se deberá aplicar supletoriamente el Código de Procedimientos Civiles para el Estado de Baja California.\nARTÍCULOS TRANSITORIOS\nPRIMERO.- La presente Ley entrará en vigor al día siguiente de su publicación en el Periódico Oficial del Estado.\nSEGUNDO.- Se abroga la Ley de Protección y Defensa de los Derechos de las\nPersonas Menores de Dieciocho Años de Edad y la Familia en el Estado de Baja\nCalifornia, Publicada en el Periódico Oficial No. 43, de fecha 15 de Octubre de 1999.\nTERCERO.- Los asuntos que se encuentren en trámite ante la Procuraduría, serán substanciados conforme al procedimiento previsto en la Ley anterior.\nCUARTO.- En todos los ordenamientos en que se haga alusión a las personas menores de dieciocho años de edad, se entenderá referida a los menores, en los términos de la presente Ley.\nQUINTO.- En todos los ordenamientos en que se haga alusión a la Procuraduría para la Defensa de las Personas Menores de Dieciocho Años de Edad y la Familia en el\nEstado, se entenderá referida a la Procuraduría para la Defensa de los Menores y la\nFamilia en el Estado, en los términos de la presente Ley.\nDADO en el Salón de Sesiones “Lic. Benito Juárez García” del H. Poder Legislativo del Estado de Baja California, en la Ciudad de Mexicali, B.C., a los veintidós días del mes de mayo del año dos mil ocho.\nDIP. JOSÉ ALFREDO FERREIRO VELAZCO\nPRESIDENTE\n(RÚBRICA)\nDIP. JUAN MANUEL GASTÉLUM BUENROSTRO\nSECRETARIO\n(RÚBRICA)\nDE CONFORMIDAD CON LO DISPUESTO POR LA FRACCIÓN I DEL ARTICULO\nORGANICA DE LA ADMINISTRACIÓN PUBLICA DEL ESTADO DE BAJA CALIFORNIA,\nIMPRIMASE Y PUBLÍQUE.\nMEXICALI, BAJA CALIFORNIA, A LOS NUEVE DIAS DEL MES DE JUNIO DEL\nAÑO DOS MIL OCHO.\nGOBERNADOR DEL ESTADO.\nJOSE GUADALUPE OSUNA MILLAN\n(RÚBRICA)\nSECRETARIO GENERAL DE GOBIERNO\nJOSE FRANCISCO BLAKE MORA\n(RÚBRICA)\nSECRETARIO DE DESARROLLO SOCIAL\nCARLOS ARMANDO REYNOSO NUÑO\nPARA SU CONOCIMIENTO EN TERMINOS DEL ARTICULO 9\nDE LA LEY ORGANICA DE LA ADMINISTRACION PUBLICA DEL ESTADO.\n(RÚBRICA)\nArtículo 2.- Fue reformado por Decreto No. 563, publicado en el Periódico Oficial\nLegislatura, siendo Gobernador Constitucional el C. José Guadalupe Osuna Millán 200720013;\nArtículo 4.- Fue reformado por Decreto No. 202, publicado en el Periódico Oficial\nNo. 25, Tomo CXIX, de fecha 01 de junio de 2012, expedido por la H. XX Legislatura, siendo Gobernador Constitucional el C. José Guadalupe Osuna Millán 2007-20013; fue reformado por Decreto No. 403, publicado en el Periódico Oficial No. 5, Sección III, Tomo\nCXX, de fecha 25 de enero de 2013, expedido por la H. XX Legislatura, siendo\nGobernador Constitucional el C. José Guadalupe Osuna Millán 2007-20013;\nArtículo 5.- Fue reformado por Decreto No. 302, publicado en el Periódico Oficial\nNo. 51, de fecha 13 de noviembre de 2009, Tomo CXVI, expedido por la H. XIX\nLegislatura, siendo Gobernador Constitucional el C. José Guadalupe Osuna Millán 20072013; fue reformado por Decreto No. 109, publicado en el Periódico Oficial No. 51, de fecha 28 de octubre de 2011, Tomo CXVIII, Sección II, expedido por la H. XX Legislatura, siendo Gobernador Constitucional el C. José Guadalupe Osuna Millán 2007-2013; fue reformado por Decreto No. 314, publicado en el Periódico Oficial No. 52, de fecha 23 de noviembre de 2012, Sección I, Tomo CXIX; expedido por la H. XX Legislatura, siendo\nGobernador Constitucional el C. José Guadalupe Osuna Millán; 2007-2013;\nArtículo 11.- Fue reformado por Decreto No. 512, publicado en el Periódico Oficial\nNo. 40, de fecha 13 septiembre de 2013, Sección I, Tomo CXX, expedido por la H. XX\nLegislatura, siendo Gobernador Constitucional el C. José Guadalupe Osuna Millán 20072013;\nArtículo 12.- Fue reformado por Decreto No. 202, publicado en el Periódico Oficial\nNo. 25, Tomo CXIX, de fecha 01 de junio de 2012, expedido por la H. XX Legislatura, siendo Gobernador Constitucional el C. José Guadalupe Osuna Millán 2007-2013; fue reformado por Decreto No. 109, publicado en el Periódico Oficial No. 51, de fecha 28 de octubre de 2011, Tomo CXVIII, Sección II, expedido por la H. XX Legislatura, siendo\nGobernador Constitucional el C. José Guadalupe Osuna Millán 2007-2013;\nArtículo 13.- Fue reformado por Decreto No. 109, publicado en el Periódico Oficial\nNo. 51, de fecha 28 de octubre de 2011, Tomo CXVIII, Sección II, expedido por la H. XX\nLegislatura, siendo Gobernador Constitucional el C. José Guadalupe Osuna Millán 20072013; fue reformado por Decreto No. 512, publicado en el Periódico Oficial No. 40, de siendo Gobernador Constitucional el C. José Guadalupe Osuna Millán 2007-2013;\nArtículo 14.- Fue reformado por Decreto No. 109, publicado en el Periódico Oficial\nLegislatura, siendo Gobernador Constitucional el C. José Guadalupe Osuna Millán 20072013;\nArtículo 15.- Fue reformado por Decreto No. 512, publicado en el Periódico Oficial\nLegislatura, siendo Gobernador Constitucional el C. José Guadalupe Osuna Millán 20072013;\nArtículo 16.- Fue reformado por Decreto No. 480, publicado en el Periódico Oficial siendo Gobernador Constitucional el C. José Guadalupe Osuna Millán 2007-2013; fue reformado por Decreto No. 512, publicado en el Periódico Oficial No. 40, de fecha 13 septiembre de 2013, Sección I, Tomo CXX, expedido por la H. XX Legislatura, siendo\nGobernador Constitucional el C. José Guadalupe Osuna Millán 2007-2013;\nArtículo 20.- Fue reformado por Decreto No. 480, publicado en el Periódico Oficial\nNo. 29, Tomo CXX, de fecha 28 de junio de 2013, expedido por la H. XX Legislatura, siendo Gobernador Constitucional el C. José Guadalupe Osuna Millán 2007-2013;\nArtículo 21.- Fue reformado por Decreto No. 403, publicado en el Periódico Oficial\nNo. 5, Sección III, Tomo CXX, de fecha 25 de enero de 2013, expedido por la H. XX\nLegislatura, siendo Gobernador Constitucional el C. José Guadalupe Osuna Millán 20072013; fue reformado por Decreto No. 512, publicado en el Periódico Oficial No. 40, de fecha 13 septiembre de 2013, Sección I, Tomo CXX, expedido por la H. XX Legislatura, siendo Gobernador Constitucional el C. José Guadalupe Osuna Millán 2007-2013;\nArtículo 21 BIS.- Fue adicionado por Decreto No. 512, publicado en el Periódico\nOficial No. 40, de fecha 13 septiembre de 2013, Sección I, Tomo CXX, expedido por la H.\nXX Legislatura, siendo Gobernador Constitucional el C. José Guadalupe Osuna Millán\n2007-2013;\nArtículo 22.- Fue reformado por Decreto No. 202, publicado en el Periódico Oficial\nNo. 25, Tomo CXIX, de fecha 01 de junio de 2012, expedido por la H. XX Legislatura, siendo Gobernador Constitucional el C. José Guadalupe Osuna Millán 2007-2013; fue reformado por Decreto No. 403, publicado en el Periódico Oficial No. 5, Sección III, Tomo\nCXX, de fecha 25 de enero de 2013, expedido por la H. XX Legislatura, siendo\nGobernador Constitucional el C. José Guadalupe Osuna Millán 2007-2013; fue reformado por Decreto No. 512, publicado en el Periódico Oficial No. 40, de fecha 13 septiembre de\n2013, Sección I, Tomo CXX, expedido por la H. XX Legislatura, siendo Gobernador\nConstitucional el C. José Guadalupe Osuna Millán 2007-2013;\nArtículo 25.- Fue reformado por Decreto No. 512, publicado en el Periódico Oficial\nNo. 40, de fecha 13 septiembre de 2013, Sección I, Tomo CXX, expedido por la H. XX\nLegislatura, siendo Gobernador Constitucional el C. José Guadalupe Osuna Millán 20072013;\nArtículo 25 BIS.- Fue adicionado por Decreto No. 512, publicado en el Periódico\nXX Legislatura, siendo Gobernador Constitucional el C. José Guadalupe Osuna Millán\n2007-2013;\nArtículo 26.- Fue reformado por Decreto No. 512, publicado en el Periódico Oficial\nLegislatura, siendo Gobernador Constitucional el C. José Guadalupe Osuna Millán 20072013;\nArtículo 27.- Fue reformado por Decreto No. 512, publicado en el Periódico Oficial\nLegislatura, siendo Gobernador Constitucional el C. José Guadalupe Osuna Millán 20072013;\nArtículo 29.- Fue reformado por Decreto No. 403, publicado en el Periódico Oficial\nNo. 5, Sección III, Tomo CXX, de fecha 25 de enero de 2013, expedido por la H. XX\nLegislatura, siendo Gobernador Constitucional el C. José Guadalupe Osuna Millán 20072013;\nArtículo 35.- Fue reformado por Decreto No. 512, publicado en el Periódico Oficial\nNo. 40, de fecha 13 septiembre de 2013, Sección I, Tomo CXX, expedido por la H. XX\nLegislatura, siendo Gobernador Constitucional el C. José Guadalupe Osuna Millán 20072013;\nArtículo 35 BIS.- Fue adicionado por Decreto No. 512, publicado en el Periódico\nOficial No. 40, de fecha 13 septiembre de 2013, Sección I, Tomo CXX, expedido por la H.\nXX Legislatura, siendo Gobernador Constitucional el C. José Guadalupe Osuna Millán\n2007-2013;\nArtículo 35 TER.- Fue adicionado por Decreto No. 512, publicado en el Periódico\nOficial No. 40, de fecha 13 septiembre de 2013, Sección I, Tomo CXX, expedido por la H.\nXX Legislatura, siendo Gobernador Constitucional el C. José Guadalupe Osuna Millán\n2007-2013;\nArtículo 37 BIS- Fue adicionado por Decreto No. 403, publicado en el Periódico\nOficial No. 5, Sección III, Tomo CXX, de fecha 25 de enero de 2013, expedido por la H.\nXX Legislatura, siendo Gobernador Constitucional el C. José Guadalupe Osuna Millán\n2007-2013;\nArtículo 38.- Fue reformado por Decreto No. 480, publicado en el Periódico Oficial siendo Gobernador Constitucional el C. José Guadalupe Osuna Millán 2007-2013;\nArtículo 41.- Fue reformado por Decreto No. 512, publicado en el Periódico Oficial\nLegislatura, siendo Gobernador Constitucional el C. José Guadalupe Osuna Millán 20072013;\nARTICULO SEGUNDO TRANSITORIO DEL DECRETO No. 302, POR EL QUE SE\nREFORMA LA FRACCIÓN FRACCIÓN VI DEL ARTÍCULO 5, PUBLICADO EN EL\nPERIODICO OFICIAL No. 51, SECCION II, TOMO CXVI, EXPEDIDO POR LA H. XIX\nLEGISLATURA, SIENDO GOBERNADOR CONSTITUCIONAL EL C. JOSE GUADALUPE\nOSUNA MILLAN 2007-2013.\nARTÍCULO TRANSITORIO:\nÚNICO.- Las presentes reformas entrarán en vigor al día siguiente de su publicación en el Periódico Oficial del Estado de Baja California.\nDADO en el Salón de Sesiones “Lic. Benito Juárez García” del H. Poder Legislativo del Estado de Baja California, en la Ciudad de Mexicali, B.C., a los doce días del mes de noviembre de dos mil nueve.\nDIP. ANTONIO RICARDO CANO JIMÉNEZ\n(RÚBRICA)\nDIP. RUBÉN ERNESTO ARMENTA ZANABIA\n(RÚBRICA)\nDE CONFORMIDAD CON LO DISPUESTO POR LA FRACCION I DEL ARTÍCULO\nMEXICALI, BAJA CALIFORNIA, A LOS VEINTISEIS DIAS DEL MES DE\nOCTUBRE DEL AÑO DOS MIL NUEVE.\nGOBERNADOR DEL ESTADO\nJOSE GUADALUPE OSUNA MILLAN\n(RÚBRICA)\nSECRETARIO GENERAL DE GOBIERNO\nJOSE FRANCISCO BLAKE MORA\n(RÚBRICA)\nARTICULO UNICO TRANSITORIO DEL DECRETO NO. 109, POR EL QUE SE\nAPRUEBA LA REFORMA A LOS ARTÍCULOS 5, 12, 13 Y 14, PUBLICADO EN EL\nSECCION II, EXPEDIDO POR LA H. XX LEGISLATURA, SIENDO GOBERNADOR\nCONSTITUCIONAL EL C. JOSE GUADALUPE OSUNA MILLAN 2007-2013.\nARTÍCULO TRANSITORIO\nPRIMERO.- Las presentes reformas entrarán en vigor al día siguiente de su publicación en el Periódico Oficial del Estado de Baja California. del Estado de Baja California, en la Ciudad de Mexicali, B.C., a los treinta días del mes de septiembre del año dos mil once.\nDIP. CARLOS MURGUÍA MEJÍA\nDIPUTADO PRESIDENTE\n(RÚBRICA)\nDIP. VIRGINIA NORIEGA RÍOS\nDIPUTADA SECRETARIA\n(RÚBRICA)\nDE CONFORMIDAD CON LO DISPUESTO POR LA FRACCION I DEL ARTÍCULO\nMEXICALI, BAJA CALIFORNIA, A LOS SEIS DÍAS DEL MES DE OCTUBRE DEL\nAÑO DOS MIL ONCE.\nGOBERNADOR DEL ESTADO\nJOSE GUADALUPE OSUNA MILLAN\n(RÚBRICA)\nSECRETARIO GENERAL DE GOBIERNO\nCUAUHTEMOC CARDONA BENAVIDES\n(RÚBRICA)\nARTÍCULO ÚNICO TRANSITORIO DEL DECRETO No. 202, POR EL QUE SE\nAPRUEBAN LAS REFORMAS A LOS ARTÍCULOS 4, 12, Y 21, PUBLICADO EN EL\nPERIÓDICO OFICIAL No. 25, TOMO CXIX, DE FECHA 01 DE JUNIO DE 2012,\nEXPEDIDO POR LA H. XX LEGISLATURA, SIENDO GOBERNADOR\nCONSTITUCIONAL EL C. JOSE GUADALUPE OSUNA MILLAN 2007-2013.\nARTÍCULO TRANSITORIO\nÚNICO.- Las presentes reformas entrarán en vigor a los sesenta días siguientes de su publicación en el Periódico Oficial del Estado de Baja California. del Estado de Baja California, en la Ciudad de Mexicali, B.C., a los tres días del mes de mayo del año dos mil doce.\nDIP. DAVID JORGE LOZANO PÉREZ\nDIPUTADO PRESIDENTE\n(RÚBRICA)\nDIP. ALFONSO GARZÓN ZATARAIN\nDIPUTADO SECRETARIO\n(RÚBRICA)\nMEXICALI, BAJA CALIFORNIA, A LOS QUINCE DÍAS DEL MES DE MAYO DEL\nAÑO DOS MIL DOCE.\nGOBERNADOR DEL ESTADO\nJOSÉ GUADALUPE OSUNA MILLÁN\n(RÚBRICA)\nSECRETARIO GENERAL DE GOBIERNO\nCUAUHTEMOC CARDONA BENAVIDES\n(RÚBRICA)\nARTÍCULO PRIMERO TRANSITORIO DEL DECRETO NO. 314, POR EL QUE SE\nAPRUEBA LA REFORMA AL ARTÍCULO 5, FRACCIONES V, VI, VII Y VIII,\nRECORRIÉNDOSE PARA PASAR A LAS FRACCIONES IX, X, XI, XII, XIII, XIV, XV, XVI\nY XVII; DE FECHA 23 DE NOVIEMBRE DE 2012, SECCIÓN I, TOMO CXIX; EXPEDIDO\nPOR LA H. XX LEGISLATURA, SIENDO GOBERNADOR CONSTITUCIONAL EL C.\nJOSE GUADALUPE OSUNA MILLÁN 2007-2013.\nARTÍCULOS TRANSITORIOS\nPRIMERO.- La presente reforma entrará en vigor a partir del día siguiente al de su publicación en el Periódico Oficial del Estado.\nSEGUNDO.- El Congreso del Estado realizará las adecuaciones presupuestales necesarias para dar cumplimiento efectivo a las presentes Reformas de Ley.\nDADO en el Salón de Sesiones “Lic. Benito Juárez García” del H. Poder Legislativo del Estado de Baja California, en la Ciudad de Mexicali, B.C., a los veinticinco días del mes de septiembre del año dos mil doce.\nDIP. ALFONSO GARZÓN ZATARAIN\nDIPUTADO\n(RÚBRICA)\nDIP. FAUSTO ZÁRATE ZEPEDA\nDIPUTADO SECRETARIO\n(RÚBRICA)\nMEXICALI, BAJA CALIFORNIA, A DÍA PRIMERO DEL MES DE NOVIEMBRE DEL\nAÑO DOS MIL DOCE.\nGOBERNADOR DEL ESTADO\nJOSÉ GUADALUPE OSUNA MILLÁN\n(RÚBRICA)\nSECRETARIO GENERAL DE GOBIERNO\nFRANCISCO ANTONIO GARCÍA BURGOS\n(RÚBRICA)\nARTÍCULO SEGUNDO TRANSITORIO DEL DECRETO No. 403, POR EL QUE SE\nREFORMAN LOS ARTÍCULOS 4, 21, 22, 29 Y LA ADICIÓN DE UN ARTÍCULO 37 BIS,\nPUBLICADO EN EL PERIÓDICO OFICIAL NO. 5, SECCIÓN III, TOMO CXX, DE FECHA\n25 DE ENERO DE 2013, EXPEDIDO POR LA H. XX LEGISLATURA, SIENDO\nGOBERNADOR CONSTITUCIONAL EL C. JOSÉ GUADALUPE OSUNA MILLÁN 20072013;\nARTÍCULOS TRANSITORIOS\nPRIMERO.- Las presentes reformas entrarán en vigor al día siguiente de su publicación en el Periódico Oficial del Estado.\nSEGUNDO.- Se concede un plazo de 60 días, a partir de la entrada en vigor del presente Decreto, para que se realicen las adecuaciones reglamentarias y materiales para su cumplimiento.\nDADO en el Salón de Sesiones “Lic. Benito Juárez García” del H. Poder Legislativo del Estado de Baja California, en la Ciudad de Mexicali, B.C., a los veintisiete días del mes de diciembre del año dos mil doce.\nDIP. CLAUDIA JOSEFINA AGATÓN MUÑÍZ\nPRESIDENTE\n(RÚBRICA)\nDIP. MARCO ANTONIO VIZCARRA CALDERÓN\nPROSECRETARIO\n(RÚBRICA)\nMEXICALI, BAJA CALIFORNIA, A LOS CATORCE DÍAS DEL MES DE ENERO\nDEL AÑO DOS MIL TRECE.\nJOSÉ GUADALUPE OSUNA MILLÁN\nGOBERNADOR DEL ESTADO\n(RÚBRICA)\nFRANCISCO ANTONIO GARCÍA BURGOS\nSECRETARIO GENERAL DE GOBIERNO\n(RÚBRICA)\nARTÍCULO UNICO TRANSITORIO DEL DECRETO No. 480, POR EL QUE SE\nREFORMAN LOS ARTÍCULOS 16, 20 Y 38, PUBLICADO EN EL PERIÓDICO OFICIAL\nNo. 29, TOMO CXX, DE FECHA 28 DE JUNIO DE 2013, EXPEDIDO POR LA H. XX\nLEGISLATURA, SIENDO GOBERNADOR CONSTITUCIONAL EL C. JOSÉ\nGUADALUPE OSUNA MILLÁN 2007-2013;\nARTÍCULO TRANSITORIO\nÚNICO: Las presentes reformas entrarán en vigor al día siguiente de su publicación en el Periódico Oficial del Estado de Baja California.\nDADO en el Salón de Sesiones “Lic. Benito Juárez García” del H. Poder\nLegislativo del Estado de Baja California, en la Ciudad de Mexicali, B.C., a los veintiocho días del mes de mayo del año dos mil trece.\nDIP. JULIO FELIPE GARCÍA MUÑOZ\nPRESIDENTE\n(RÚBRICA)\nDIP. MARCO ANTONIO VIZCARRA CALDERÓN\nSECRETARIO\n(RÚBRICA)\nDE CONFORMIDAD CON LO DISPUESTO POR LA FRACCION I DEL ARTÍCULO\nMEXICALI, BAJA CALIFORNIA, A LOS CUATRO DÍAS DEL MES DE JUNIO DEL\nAÑO DOS MIL TRECE.\nGOBERNADOR DEL ESTADO\nJOSE GUADALUPE OSUNA MILLAN\n(RÚBRICA)\nSECRETARIO GENERAL DE GOBIERNO\nCUAUHTEMOC CARDONA BENAVIDES\n(RÚBRICA)\nARTÍCULO CUARTO TRANSITORIO DEL DECRETO No. 512, POR EL QUE SE\nREFORMAN 11, 13, 15, 16, 21, 22, 25, 26, 27, 35 Y 41 A LA ADICIÓN DE LOS\nARTÍCULOS 21 BIS, 25 BIS, 35 BIS Y 35 TER, PUBLICADO EN EL PERIÓDICO\nEXPEDIDO POR LA H. XX LEGISLATURA, SIENDO GOBERNADOR\nCONSTITUCIONAL EL C. JOSÉ GUADALUPE OSUNA MILLÁN 2007-2013.\nARTÍCULOS TRANSITORIOS\nPrimero.- Las presentes reformas entrarán en vigor a los noventa días posteriores a la publicación del presente decreto en el Periódico Oficial del Estado.\nSegundo.- El Poder Ejecutivo del Estado, deberá publicar las disposiciones reglamentarias para el cumplimiento de las presentes reformas dentro de los noventa días posteriores a la publicación del presente decreto en el Periódico Oficial del Estado.\nDADO en el Salón de Sesiones “Lic. Benito Juárez García” del H. Poder Legislativo del Estado de Baja California, en la Ciudad de Mexicali, B.C., a los dieciséis días del mes de agosto del año dos mil trece.\nDIP. GREGORIO CARRANZA HERNÁNDEZ\nPRESIDENTE\n(RÚBRICA)\nDIP. MARCO ANTONIO VIZCARRA CALDERÓN\nSECRETARIO\n(RÚBRICA)\nDE CONFORMIDAD CON LO DISPUESTO POR LA FRACCIÓN I DEL ARTÍCULO\nMEXICALI, BAJA CALIFORNIA, A LOS SEIS DÍAS DEL MES DE SEPTIEMBRE\nDEL AÑO DOS MIL TRECE.\nJOSÉ GUADALUPE OSUNA MILLÁN\nGOBERNADOR DEL ESTADO\n(RÚBRICA)\nFRANCISCO ANTONIO GARCÍA BURGOS\nSECRETARIO GENERAL DE GOBIERNO\n(RÚBRICA)\nARTÍCULO UNICO TRANSITORIO DEL DECRETO No. 563, POR EL QUE SE\nREFORMA EL ARTÍCULO 2, PUBLICADO EN EL PERIÓDICO OFICIAL No. 43,\nH. XX LEGISLATURA, SIENDO GOBERNADOR CONSTITUCIONAL EL C. JOSÉ\nGUADALUPE OSUNA MILLÁN 2007-2013;\nARTÍCULOS TRANSITORIOS\nPRIMERO.- El presente Decreto entrará en vigor al día siguiente de su publicación en el Periódico Oficial del Estado. para los efectos de publicación en el Periódico Oficial del Estado de Baja California. del Estado de Baja California, en la Ciudad de Mexicali, B.C., a los trece días del mes de septiembre del año dos mil trece.\nDIP. GREGORIO CARRANZA HERNÁNDEZ\nPRESIDENTE\n(RÚBRICA)\nDIP. MARCO ANTONIO VIZCARRA CALDERÓN\nSECRETARIO\n(RÚBRICA)\nDE CONFORMIDAD CON LO DISPUESTO POR LA FRACCION I DEL ARTÍCULO\nMEXICALI, BAJA CALIFORNIA, A LOS VEINTISIETE DÍAS DEL MES DE\nSEPTIEMBRE DEL AÑO DOS MIL TRECE.\nJOSÉ GUADALUPE OSUNA MILLÁN\nGOBERNADOR DEL ESTADO\n(RÚBRICA)\nFRANCISCO ANTONIO GARCÍA BURGOS\nSECRETARIO GENERAL DE GOBIERNO\n(RÚBRICA)",
  "ordenamiento": "REGLAMENTO",
  "jurisdiccion": "BAJA CALIFORNIA",
  "fuente_oficial": "Periódico Oficial",
  "FECHA PER OFIC": "2015/04/17",
  "ESTATUS": "VIGENTE",
  "TOMO": "TOMO_VI",
  "URL": "https://www.congresobc.gob.mx/Documentos/ProcesoParlamentario/Leyes/TOMO_VI/20150417_LEYPROMENORES.PDF",
  "es_escaneado": false,
  "tiene_tablas": true,
  "materia": [
    "social",
    "salud",
    "educación",
    "cultura"
  ]
}