{
  "titulo": "Ley DE ESTÍMULO FISCAL A LA CREACIÓN y EXPRESIÓN ARTÍSTICA PARA BAJA CALIFORNIA",
  "Contenido": "PARA BAJA CALIFORNIA\nPublicada en el Periódico Oficial No. 04,\nCAPÍTULO PRIMERO\nDISPOSICIONES GENERALES\nARTÍCULO 1.- Esta Ley es de orden público e interés social, de observancia general en el Estado de Baja California y tiene por objeto regular la promoción, fomento y financiamiento de proyectos culturales y artísticos por parte del sector privado a través de la figura del mecenazgo.\nARTÍCULO 2.- El mecenazgo es el financiamiento total o parcial que realiza una persona física o moral sin fines de lucro, para la investigación, creación, producción, desarrollo o ejecución de proyectos artísticos o culturales, a cambio de un incentivo en la exención de Impuestos Sobre Remuneraciones al Trabajo Personal, en los términos y condiciones que fije el presente instrumento y la Ley de Hacienda del Estado de Baja\nCalifornia.\nARTÍCULO 3.- La presente Ley promueve:\nI. Los derechos humanos de todas las personas al acceso a la cultura.\nII. La gestión cultural.\nIII. La expresión cultural.\nIV. La vocación artística y creativa en Baja California.\nV. La concurrencia activa entre el sector privado, comunidad artística y gobierno a través del principio de colaboración.\nVI. La instrumentación de políticas públicas transversales en materia de arte y cultura.\nARTÍCULO 4.- Las disciplinas sujetas a financiamiento a través del mecenazgo son las siguientes:\nI. Literatura.\nII. Música.\nLey de Estímulo Fiscal a la Creación y Expresión Artística para Baja California. Página 1\nIII. Dramática.\nIV. Danza.\nV. Pictórica o de dibujo.\nVI. Escultórica y de carácter plástico.\nVII. Caricatura e historietas.\nVIII. Arquitectónica.\nIX. Arte digital.\nX. Guion cinematográfico.\nXI. Fotografía.\nXII. Compilaciones, colecciones de obras como enciclopedias o antologías.\nXIII. Restauración y mantenimiento de bienes públicos con valor histórico y cultural.\nXIV. Promoción y difusión a través de exposiciones, foros y presentaciones.\nCAPÍTULO SEGUNDO\nLAS AUTORIDADES\nARTÍCULO 5.- Son autoridades encargadas de aplicar la presente Ley:\nI. El Ejecutivo del Estado, por conducto del Instituto de Cultura de Baja California; y\nCAPÍTULO TERCERO\nLOS SUJETOS\nARTÍCULO 6.- Beneficiarios: Son las personas físicas o morales que sin fines de lucro, en calidad de artistas o creadores, presenten proyectos culturales mencionados en el artículo 4 de la presente Ley.\nARTÍCULO 7.- Para ser beneficiario de mecenazgos es necesario:\nI. Contar con residencia comprobada en el Estado de Baja California.\nLey de Estímulo Fiscal a la Creación y Expresión Artística para Baja California. Página 2\nII. Desarrollar actividades culturales a las que hace referencia la presente Ley.\nIII. Ser contribuyente activo en los términos de la Ley de Hacienda del Estado de Baja\nCalifornia.\nIV. Contar con muestras, soportes o portafolios de trabajo que demuestre la trascendencia del proyecto que se busca financiar.\nV. Las demás que se establezca la autoridad cultural en términos del reglamento y de las reglas de operación.\nEl interesado, solo podrá concursar con un proyecto, ya sea de forma individual o colectiva, debiendo elegir una disciplina mencionada en esta Ley.\nARTÍCULO 8.- Patrocinadores: Son las personas físicas o morales contribuyentes del Impuesto Sobre Remuneraciones al Trabajo Personal, que decidan financiar con recursos económicos o materiales, los proyectos culturales previamente aprobados por el\nInstituto de Cultura de Baja California.\nARTÍCULO 9.- Para ser patrocinadores de mecenazgo es necesario:\nI. Ser contribuyente activo en los términos de la Ley de Hacienda del Estado de Baja\nCalifornia.\nII. Estar al corriente de impuestos y obligaciones fiscales.\nIII.- Cumplir con todos los requisitos que fije la autoridad cultural y hacendaria en los términos del reglamento y de las reglas de operación.\nCAPÍTULO CUARTO\nLOS INCENTIVOS FISCALES\nARTÍCULO 10.- Las personas físicas o morales que decidan financiar proyectos artísticos o culturales podrán deducir hasta un 80% de su aportación, contra el pago del\nImpuesto Sobre Remuneraciones al Trabajo Personal.\nARTÍCULO 11.- El monto por acreditarse en ningún caso podrá exceder del 10% de del contribuyente.\nCalifornia, establecerá anualmente un presupuesto y cálculos de recursos financieros que podrán ser desgravados, de acuerdo con la viabilidad financiera disponible.\nLey de Estímulo Fiscal a la Creación y Expresión Artística para Baja California. Página 3\nARTÍCULO 13.- El reglamento establecerá los procesos, formalidades y requisitos para el cumplimiento de esta Ley.\nCAPÍTULO QUINTO\nLOS PATROCINIOS CULTURALES\nARTÍCULO 14.- El financiamiento de proyectos culturales o artísticos que realicen las personas físicas o morales en términos de la presente Ley, podrá ser a través de recursos financieros o en especie.\nARTÍCULO 15.- El monto anual de financiamiento se sujetará a los siguientes topes máximos:\nI. Procesos de creación: Hasta la suma de quinientos mil pesos anuales por proyecto.\nII. Proyectos de producción: Hasta la suma de un millón de pesos anuales por proyecto.\nARTÍCULO 16.- Las personas físicas o morales que deseen financiar proyectos culturales o artísticos, podrán elegir libremente entre aquellos que previamente hayan sido aprobados por el Instituto de Cultura de Baja California.\nARTÍCULO 17.- Es condición del incentivo que las actividades que se beneficien del mecenazgo en los términos de la presente Ley, tengan carácter público.\nARTÍCULO 18.- Un artista, creador o gestor cultural solo podrá beneficiarse del mecenazgo hasta en dos procesos consecutivos.\nARTÍCULO 19.- Con independencia del financiamiento que pudieran beneficiarse actividades culturales o artísticas en los términos de la presente Ley, los artistas o creadores, conservarán sus derechos de autor mismos que son reconocidos y protegidos por la Ley Federal del Derecho de Autor.\nCAPÍTULO SEXTO\nDEL COMITÉ TÉCNICO DICTAMINADOR\nARTÍCULO 20.- El Instituto de Cultura de Baja California contará con un Comité\nTécnico Dictaminador, que fungirá como un órgano auxiliar para la evaluación de proyectos culturales y artísticos sujetos a concurso de financiamiento a través del mecenazgo. disciplinas señaladas en esta Ley.\nLey de Estímulo Fiscal a la Creación y Expresión Artística para Baja California. Página 4\nARTÍCULO 21.- Los integrantes del Comité Técnico Dictaminador, serán designados libremente por el Director del Instituto de Cultura de Baja California, sus cargos serán compensación alguna.\nARTÍCULO 22.- Los principios rectores en el proceso de evaluación del Comité\nTécnico Dictaminador, respecto a los proyectos culturales y artísticos susceptibles a financiamiento serán:\nI. La calidad.\nII. Originalidad.\nIII. Viabilidad técnica y financiera del proyecto.\nIV. El impacto social.\nV. El interés cultural para la sociedad de Baja California.\nCAPÍTULO SÉPTIMO\nDEL INSTITUTO DE CULTURA\nARTÍCULO 23.- El Instituto de Cultura de Baja California, además de las atribuciones que le confiere su propia norma, contará con las siguientes facultades:\nI. Emitir las convocatorias para concurso de financiamiento de proyectos artísticos o culturales a través del mecenazgo.\nII. En coordinación con la Secretaría de Planeación y Finanzas del Gobierno del\nEstado, establecer los requisitos y trámites que deberán cumplir los interesados para hacerse acreedores del estímulo fiscal, así como los procedimientos a seguir para la entrega del patrocinio al beneficiario.\nIII. Poner a disposición de los particulares la información pública en los términos de la\nIV. En coordinación con la Secretaría de Planeación y Finanzas del Gobierno del\nEstado, establecer un sistema para el control de rendición de cuentas que deberán presentar los beneficiarios y patrocinadores.\nV. Establecer los lineamientos técnicos y operativos que habrá de seguir el Comité\nTécnico Dictaminador.\nLey de Estímulo Fiscal a la Creación y Expresión Artística para Baja California. Página 5\nVI. Vigilar que los proyectos aprobados y en general todo el proceso, se sujete a lo establecido en la presente Ley, su reglamento y reglas de operación.\nVII. Aprobar, observar o rechazar los informes de avances de los proyectos de rendición de cuentas.\nVIII. Dar vista a las autoridades competentes cuando se adviertan hechos con apariencia de delitos.\nCAPÍTULO OCTAVO\nDISPOSICIONES FINALES\nARTÍCULO 24.- Los beneficiarios de mecenazgo deberán utilizar los recursos obtenidos estrictamente para los fines y propósitos que fueron destinados.\nARTÍCULO 25.- Los contribuyentes que otorguen patrocinio para el financiamiento de proyectos artísticos o culturales, solo podrán recibir del artista o creador, reconocimientos, pero en ningún caso contraprestaciones de carácter económicas.\nARTÍCULO 26.- Los recursos de financiamiento para proyectos artísticos o culturales por medio de mecenazgo tendrán el carácter de inembargables.\nPRIMERO.- El presente decreto entrará en vigor a partir del día siguiente de su publicación en el Periódico Oficial del Estado de Baja California.\nSEGUNDO.- El Poder Ejecutivo del Estado de Baja California dentro de los 120 días naturales siguientes, contados a partir de la publicación de esta Ley deberá expedir el reglamento correspondiente.\nTERCERO.- El Comité Técnico Dictaminador al que alude el Capítulo Sexto de esta\nLey, deberá quedar conformado a más tardar 60 días naturales, contados a partir de la creación del Reglamento al que hace referencia la disposición transitoria segunda.\nCUARTO.- Para efectos de dar cumplimiento a lo dispuesto por el artículo 22 fracción\nII de la presente Ley, el Instituto de Cultura de Baja California, emitirá los Lineamientos para la aplicación del estímulo fiscal, pudiendo apoyarse con la Secretaría de Planeación y\nFinanzas del Estado de Baja California, en un plazo no mayor de 120 días naturales, Ley de Estímulo Fiscal a la Creación y Expresión Artística para Baja California, en concordancia a lo dispuesto por el Artículo 12 de la referida Ley.\nLey de Estímulo Fiscal a la Creación y Expresión Artística para Baja California. Página 6 del Estado de Baja California, en la Ciudad de Mexicali, B.C., a los veintisiete días del mes de diciembre del año dos mil dieciocho.\nDIP. CARLOS ALBERTO TORRES TORRES\nPRESIDENTE\n(RÚBRICA)\nDIP. MARÍA TRINIDAD VACA CHACÓN\nSECRETARIA\n(RÚBRICA)\nDE CONFORMIDAD CON LO DISPUESTO POR LA FRACCIÓN I DEL ARTÍCULO 49\nMEXICALI, BAJA CALIFORNIA, A LOS DIECIOCHO DÍAS DEL MES DE ENERO\nDEL AÑO DOS MIL DIECINUEVE.\nFRANCISCO ARTURO VEGA DE LAMADRID\nGOBERNADOR DEL ESTADO\nFRANCISCO RUEDA GÓMEZ\nSECRETARIO GENERAL DE GOBIERNO\nLey de Estímulo Fiscal a la Creación y Expresión Artística para Baja California. Página 7",
  "ordenamiento": "REGLAMENTO",
  "jurisdiccion": "BAJA CALIFORNIA",
  "fuente_oficial": "Periódico Oficial",
  "FECHA PER OFIC": "2019/01/18",
  "ESTATUS": "VIGENTE",
  "TOMO": "TOMO_II",
  "URL": "https://www.congresobc.gob.mx/Documentos/ProcesoParlamentario/Leyes/TOMO_II/18012019_LEYEST%C3%8DMFISCART%C3%8DS.PDF",
  "es_escaneado": false,
  "tiene_tablas": false,
  "materia": [
    "financiero",
    "fiscal",
    "económico"
  ]
}