{
  "titulo": "Ley DE INGRESOS DEL MUNICIPIO DE MEXICALI, BAJA CALIFORNIA PARA EL EJERCICIO FISCAL 2025",
  "Contenido": "BAJA CALIFORNIA, EN USO DE LAS FACULTADES QUE LE CONFIERE EL ARTÍCULO\nSOBERANO DE BAJA CALIFORNIA, TIENE A BIEN APROBAR LA SIGUIENTE:\nLEY DE INGRESOS DEL MUNICIPIO\nDE MEXICALI, BAJA CALIFORNIA\nPARA EL EJERCICIO FISCAL 2025\nTÍTULO PRIMERO\nDISPOSICIONES PRELIMINARES\nCAPÍTULO ÚNICO\nDE LOS INGRESOS\nARTÍCULO 1.- La presente Ley es de orden público y de interés social, y tiene por objeto establecer los ingresos que percibirá la Hacienda\nPública del Municipio de Mexicali, Estado de Baja California durante el ejercicio fiscal del 1o. de enero al 31 de diciembre del 2025, y serán los que se obtengan por los siguientes conceptos en cantidades estimadas que a continuación se enumeran:\n1 IMPUESTOS $1,537,214,081.90\n1 IMPUESTOS SOBRE LOS INGRESOS $ 25,770,798.79\n01 Impuestos sobre Asistencia a\nDiversiones y Espectáculos Públicos $ 9,916,937.74\n02 Impuesto a Centros de Apuestas, Apuestas Remotas, Salas de Sorteos de $ 15,853,861.05\nNúmeros y/o Casinos\n2 IMPUESTOS SOBRE EL PATRIMONIO $ 744,688,339.79\n01 Impuesto Predial $ 744,688,339.79\n02 Impuesto sobre la Plusvalía $ 0.00\n3 IMPUESTOS SOBRE LA PRODUCCIÓN, EL\nCONSUMO Y LAS TRANSACCIONES $ 415,541,502.28\n01 Impuesto sobre Adquisición de Inmuebles $ 415,541,502.28\n4 IMPUESTOS AL COMERCIO EXTERIOR\n5 IMPUESTOS SOBRE NÓMINAS Y ASIMILABLES\n6 IMPUESTOS ECOLÓGICOS\n7 ACCESORIOS DE IMPUESTOS $ 30,040,391.17\n01 Accesorios de Impuestos $ 30,040,391.17\n8 OTROS IMPUESTOS $ 166,186,350.95\n01 Impuesto para el Mantenimiento y\nConservación de las Vías Públicas $ 166,186,350.95\n9 IMPUESTOS NO COMPRENDIDOS EN LA LEY DE\nINGRESOS VIGENTE, CAUSADOS EN\nEJERCICIOS FISCALES ANTERIORES\nPENDIENTES DE LIQUIDACIÓN O PAGO $ 168,986,698.92\n01 Impuestos causados en ejercicios anteriores pendientes de liquidación o\nPago $ 168,986,698.92\n2 CUOTAS Y APORTACIONES DE SEGURIDAD SOCIAL $ 7,932,896.79\n1 APORTACIONES PARA FONDOS DE VIVIENDA\n2 CUOTAS PARA LA SEGURIDAD SOCIAL\n3 CUOTAS DE AHORRO PARA EL RETIRO\n4 OTRAS CUOTAS Y APORTACIONES PARA LA\nSEGURIDAD SOCIAL $ 7,932,896.79\n01 Otras Cuotas y Aportaciones de\nRecuperación de Servicios Médicos $ 7,932,896.79\n5 ACCESORIOS DE CUOTAS Y APORTACIONES DE\nSEGURIDAD SOCIAL\n3 CONTRIBUCIONES DE MEJORAS $ 0.00\n1 CONTRIBUCIONES DE MEJORAS POR OBRAS\nPÚBLICAS\n01 Aportaciones de Particulares para Obras\nPúblicas Municipales\n9 CONTRIBUCIONES DE MEJORAS NO\nCOMPRENDIDAS EN LA LEY DE INGRESOS\nVIGENTE, CAUSADAS EN EJERCICIOS\nFISCALES ANTERIORES PENDIENTES DE\nLIQUIDACIÓN O PAGO\n01 Aportaciones de Particulares para Obras\nPúblicas Municipales de Ejercicios\nAnteriores\n4 DERECHOS $ 575,049,585.08\n1 DERECHOS POR EL USO, GOCE,\nAPROVECHAMIENTO O EXPLOTACIÓN DE BIENES\nDE DOMINIO PÚBLICO $ 2,867,505.80\n01 Explotación o Arrendamiento de Bienes\nMuebles e Inmuebles Propiedad del\nGobierno Municipal. $ 2,867,505.80\n02 Del Piso. $ 0.00\n3 DERECHOS POR PRESTACIÓN DE SERVICIOS $ 565,081,919.93\n01 Exención de derechos a Asociaciones\nCiviles sin fines de lucro -$ 1,341,955.32\n02 Derecho por servicio de Alumbrado\nPúblico $ 126,973,718.68\n03 Servicios que presta el Registro Civil $ 54,753,457.07\n04 Por la autorización del Uso u Ocupación de Vías Públicas para ejercer el comercio o la prestación de servicios, por Comerciantes Ambulantes, con\nPuestos Semifijos o Mercados Sobre\nRuedas. $ 11,090,878.97\n05 Por la autorización de la Venta, Almacenaje o Consumo Público de Bebidas\nAlcohólicas $ 60,643,632.00\n06 Por la autorización del funcionamiento de Máquinas Electrónicas, Electromecánicas, Mecánicas, Musicales, Digitales, Videojuegos y cualquier tecnología similar $ 31,828,451.41\n07 Por la autorización de la Instalación de Máquinas Expendedoras de alimentos, bebidas, productos y similares $ 656,092.44\n08 Por la autorización para la Realización de Eventos, Espectáculos Públicos y de\nDiversión $ 3,095,353.78\n09 Establecimientos para Eventos Sociales y Fiestas $ 3,419,845.01\n10 Estacionamiento de Vehículos en la Vía\nPública y Estacionamientos Públicos $ 40,126,093.09\n11 Servicios que presta Oficialía Mayor $ 2,754,415.93\n12 Servicios que presta el Departamento de\nServicios Médicos Municipales $ 4,066,727.38\n13 Servicios que presta la Dirección de\nSeguridad Pública Municipal $ 11,349,796.01\n14 Servicios que presta la Dirección del\nHeroico Cuerpo de Bomberos $ 33,836,276.55\n15 Servicios que presta el Departamento de\nControl Urbano $ 78,180,495.05\n16 Servicios que presta el Departamento de\nFraccionamientos $ 15,883,305.47\n17 Servicios que presta el Departamento de\nIngeniería de Tránsito $ 4,029,312.70\n18 Servicios que presta el Departamento de\nCatastro Municipal $ 38,107,027.78\n19 Servicios que presta la Dirección de\nProtección al Ambiente $ 10,478,859.26\n20 Servicios que presta la Dirección de\nServicios Públicos Municipales $ 8,537,641.37\n21 Servicios que presta la Dirección de\nObras Públicas $ 8,497,727.59\n22 Expedición de Certificados, Títulos o copias de Documentos $ 10,253,125.33\n23 Unidad Municipal de Protección Civil $ 6,906,271.73\n24 Centro Histórico $ 400,258.00\n4 OTROS DERECHOS\n5 ACCESORIOS DE DERECHOS $ 4,483,264.28\n01 Accesorios de Derechos $ 4,483,264.28\n9 DERECHOS NO COMPRENDIDOS EN LA LEY DE\nINGRESOS VIGENTE, CAUSADOS EN\nEJERCICIOS FISCALES ANTERIORES\nPENDIENTES DE LIQUIDACIÓN O PAGO $ 2,097,337.50\n01 Derechos causados en Ejercicios\nAnteriores pendientes de liquidación o\nPago $ 2,097,337.50\n5 PRODUCTOS $ 97,020,281.24\n1 PRODUCTOS $ 97,020,281.24\n01 Productos $ 93,682,374.69\n02 Enajenación de Bienes Muebles e\nInmuebles Propiedad del Gobierno\nMunicipal. $ 3,337,906.55\n03 Bienes Mostrencos. $ 0.00\n04 Explotación o Arrendamiento de Bienes\nMuebles e Inmuebles de Dominio Privado\nPropiedad del Gobierno Municipal $ 0.00\n9 PRODUCTOS NO COMPRENDIDOS EN LA LEY DE\nINGRESOS VIGENTE, CAUSADOS EN\nEJERCICIOS FISCALES ANTERIORES\nPENDIENTES DE LIQUIDACIÓN O PAGO $ 0.00\n01 Productos causados en Ejercicios\nAnteriores pendientes de liquidación o\nPago $ 0.00\n6 APROVECHAMIENTOS $ 177,877,194.58\n1 APROVECHAMIENTOS $ 167,903,485.40\n01 Multas $ 132,843,249.04\n02 Otras Actividades del Gobierno\nMunicipal que no correspondan a sus\nFunciones Propias de Derecho Público. $ 2,895,821.36\n03 Reintegros e Indemnizaciones $ 0.00\n04 Donaciones, Cesiones, Herencias y\nLegados a Favor del Municipio $ 897,584.26\n05 Otros Aprovechamientos $ 31,266,830.74\n2 APROVECHAMIENTOS PATRIMONIALES $ 0.00\n3 ACCESORIOS DE APROVECHAMIENTOS $ 2,251,783.13\n01 Accesorios de Aprovechamientos $ 2,251,783.13\n9 APROVECHAMIENTOS NO COMPRENDIDOS EN LA\nLEY DE INGRESOS VIGENTE, CAUSADOS EN\nEJERCICIOS FISCALES ANTERIORES\nPENDIENTES DE LIQUIDACIÓN O PAGO $ 7,721,926.05\n01 Aprovechamientos causados en Ejercicios\nAnteriores pendientes de liquidación o\nPago $ 7,721,926.05\n7 INGRESOS POR VENTA DE BIENES, PRESTACIÓN DE\nSERVICIOS Y OTROS INGRESOS.\n1 INGRESOS POR VENTA DE BIENES Y\nPRESTACIÓN DE SERVICIOS DE\nINSTITUCIONES PÚBLICAS DE SEGURIDAD\nSOCIAL.\n2 INGRESOS POR VENTA DE BIENES Y\nPRESTACIÓN DE SERVICIOS DE EMPRESAS\nPRODUCTIVAS DEL ESTADO.\n3 INGRESOS POR VENTA DE BIENES Y\nPRESTACIÓN DE SERVICIOS DE ENTIDADES\nPARAESTATALES Y FIDEICOMISOS NO\nEMPRESARIALES Y NO FINANCIEROS.\n4 INGRESOS POR VENTA DE BIENES Y\nPRESTACIÓN DE SERVICIOS DE ENTIDADES\nPARAESTATALES EMPRESARIALES NO\nFINANCIERAS CON PARTICIPACIÓN ESTATAL\nMAYORITARIA.\n5 INGRESOS POR VENTA DE BIENES Y\nPRESTACIÓN DE SERVICIOS DE ENTIDADES\nPARAESTATALES EMPRESARIALES\nFINANCIERAS MONETARIAS CON\nPARTICIPACIÓN ESTATAL MAYORITARIA.\n6 INGRESOS POR VENTA DE BIENES Y\nPRESTACIÓN DE SERVICIOS DE ENTIDADES\nPARAESTATALES EMPRESARIALES\nFINANCIERAS NO MONETARIAS CON\nPARTICIPACIÓN ESTATAL MAYORITARIA.\n7 INGRESOS POR VENTA DE BIENES Y\nPRESTACIÓN DE SERVICIOS DE FIDEICOMISOS\nFINANCIEROS PÚBLICOS CON PARTICIPACIÓN\nESTATAL MAYORITARIA.\n8 INGRESOS POR VENTA DE BIENES Y\nPRESTACIÓN DE SERVICIOS DE LOS PODERES\nLEGISLATIVO Y JUDICIAL, Y DE LOS\nÓRGANOS AUTÓNOMOS.\n9 OTROS INGRESOS\n8 PARTICIPACIONES, APORTACIONES, CONVENIOS,\nINCENTIVOS DERIVADOS DE LA COLABORACIÓN\nFISCAL Y FONDOS DISTINTOS DE APORTACIONES $3,790,905,961.41\n1 PARTICIPACIONES $2,728,075,078.41\n01 Participaciones de Contribuciones\nFederales $2,398,361,941.93\n02 Participaciones de Contribuciones\nEstatales $ 329,713,136.48\n2 APORTACIONES $1,062,830,883.00\n01 Aportaciones Federales del Ramo 33 $1,062,830,883.00\n02 Otras Aportaciones $ 0.00\n3 CONVENIOS\n01 Otros Ingresos por Convenios Federales $ 0.00\n02 Otros Ingresos por Convenios Estatales $ 0.00\n4 INCENTIVOS DERIVADOS DE LA COLABORACIÓN\nFISCAL\n5 FONDOS DISTINTOS DE APORTACIONES\n9 TRANSFERENCIAS, ASIGNACIONES, SUBSIDIOS Y\nSUBVENCIONES, Y PENSIONES Y JUBILACIONES $ 0.00\n1 TRANSFERENCIAS Y ASIGNACIONES\n3 SUBSIDIOS Y SUBVENCIONES $ 0.00\n01 Subsidios y Subvenciones $ 0.00\n5 PENSIONES Y JUBILACIONES\n7 TRANSFERENCIAS DEL FONDO MEXICANO DEL\nPETRÓLEO PARA LA ESTABILIZACIÓN Y EL\nDESARROLLO\n0 INGRESOS DERIVADOS DE FINANCIAMIENTOS\n1 ENDEUDAMIENTO INTERNO\n2 ENDEUDAMIENTO EXTERNO\n3 FINANCIAMIENTO INTERNO\nTOTAL DE INGRESOS $6,200,000,001.00\nTÍTULO SEGUNDO\n1 IMPUESTOS\nCAPÍTULO I\n1 IMPUESTOS SOBRE LOS INGRESOS\n01 IMPUESTO SOBRE ASISTENCIA A DIVERSIONES\nY ESPECTÁCULOS PÚBLICOS\nARTÍCULO 2.- Son sujetos de este impuesto, los asistentes a juegos permitidos, espectáculos públicos y centros nocturnos de diversión, así como a las funciones de obras de teatro y circo. No se considerarán objeto de este impuesto, espectáculos públicos presentados en restaurantes, bares, cabarets, salones de fiesta o baile y centros nocturnos, cuando se acredite previamente a la celebración del evento que los ingresos por dichos espectáculos, serán acumulados a los\nHistórico de Mexicali.\nARTÍCULO 3.- El impuesto sobre asistencia a diversiones y espectáculos públicos se calculará aplicando la tasa del 5% sobre la cuota o boleto de entrada, precio de admisión o asistencia a diversiones y espectáculos públicos.\nPara la determinación de este impuesto, en los casos en que para un sección, zona o ubicación, se considerará como base gravable el del costo mayor. generadores de esta contribución, los organizadores de los juegos permitidos y espectáculos, deberán solicitar el permiso correspondiente y garantizar, en su carácter de responsables solidarios con el causante, el crédito fiscal estimado por la Tesorería\nMunicipal, mediante depósito en efectivo, que no será inferior al impuesto correspondiente a un día de actividades, ni superior al que pudiera corresponder también estimativamente a tres días.\nPara la intervención de dicho evento se requerirá la presencia de personal designado por la Recaudación de Rentas Municipal, quien causará los honorarios que determine la Autoridad fiscal, y que oscilará de entre 8.00 a 12.00 Unidad de Medida y Actualización vigente por interventor a cargo del promotor u organizador del evento.\nNo se pagará este impuesto, tratándose de eventos realizados por\nPartidos Políticos, siempre y cuando se acredite fehacientemente a través de contrato o declaración de impuestos, 5 días hábiles previos al evento, organizado por el “Partido Político”.\nTratándose de espectáculos realizados por Organismos no lucrativos que brinden servicios y asistencia médica de manera gratuita a enfermos que padezcan cáncer en etapa terminal, debidamente registrados ante institución oficial que para tales efectos señale la Ley de la materia, Municipal, en caso de no contar con ella causarán el impuesto a una tasa del 2.5%.\nMunicipal de Arte y Cultura de Mexicali, Baja California., que sean el reglamento de dicho instituto, gravarán este impuesto a tasa cero previa autorización del Presidente Municipal.\nTratándose de eventos y/o espectáculos que tengan por objeto impulsar el impuesto a una tasa del 2.5% o en su caso podrán exentar el pago\nPresidente Municipal. no lucrativos, debidamente constituidas que tengan por objeto allegarse recursos para el cumplimiento de sus fines, causarán el impuesto a una tasa del 2.5%.\nLos organizadores de los eventos a que se refiere el párrafo anterior podrán exentar el pago hasta en un cien por ciento de este impuesto previa solicitud y autorización del Presidente Municipal.\nSerá obligatorio tratándose de Partidos Políticos, Asociaciones\nCiviles, así como de las organizaciones anteriormente mencionadas en este artículo, que deberán de contar con un representante previamente acreditado ante la Recaudación de Rentas Municipal, para la verificación de la apertura de los accesos del lugar donde se llevará a cabo el evento, así como para la firma del acta de liquidación y el pago a los Interventores comisionados por parte del Ayuntamiento de Mexicali del espectáculo o evento realizado y para el cual se hubiere aprobado la exención del impuesto. En el caso de no encontrarse ningún representante por parte de los organizadores del evento, el\nInterventor Municipal procederá a cancelar la exención del impuesto, cobrando lo estipulado en este artículo.\nEl ingreso que se recaude por concepto del impuesto sobre asistencia a diversiones y espectáculos públicos, se destinarán a la promoción y prestación de servicios de asistencia de la comunidad y de los grupos vulnerables, a la promoción del sano desarrollo físico, mental y social de la niñez, a través del Desarrollo Integral de la Familia.\nARTÍCULO 4.- Los organizadores o empresarios de los espectáculos públicos, juegos permitidos, centros de diversión y funciones de obras de teatro o circo, serán solidariamente responsables del pago de este impuesto, debiendo retener al momento de pagar el asistente el boleto de celebrarse éste, previa liquidación o comprobación del ingreso al interventor municipal, en el caso en que sea intervenido el evento, o en su defecto, en la Recaudación Municipal el día hábil siguiente al de la celebración del evento.\nEn casos excepcionales, el titular de la Recaudación de Rentas causado, ante la oficina recaudadora al siguiente día hábil de aquel en que se celebre el evento.\n02 IMPUESTO A CENTROS DE APUESTAS, APUESTAS REMOTAS,\nSALAS DE SORTEOS, DE NÚMEROS Y/O CASINOS\nARTÍCULO 5.- Son sujetos de este impuesto los permisionarios que, proceden de los juegos con apuestas y/o habilidades o destrezas, que otorguen premios en efectivo o en especie al amparo de un permiso federal otorgado por la Secretaría de Gobernación o de una resolución judicial que haya causado estado, registrados y reconocidos en la página oficial de la citada Secretaría de Gobernación, pagarán este impuesto de acuerdo a lo siguiente:\nLos permisionarios y organizadores de juegos con apuestas permitidas y/o habilidades o destrezas, calcularán este impuesto aplicando la tasa del 3.0% al valor nominal de los billetes, boletos, apuestas y demás comprobantes que permitan la participación o la apuesta, deduciéndose a dicha base gravable el valor del premio efectivamente pagado o entregado a los participantes dentro de los primeros quince días de cada mes.\n2 IMPUESTOS SOBRE EL PATRIMONIO\n01 IMPUESTO PREDIAL\nARTÍCULO 6.-El Impuesto Predial se causará de acuerdo a lo que se establece en la Ley de Hacienda Municipal y la Ley del Catastro\nInmobiliario, ambas del Estado de Baja California, así como en lo de Mexicali, Baja California, y de conformidad con la Tabla de Valores\nUnitarios de Suelo(Valores Catastrales), aprobada por el Congreso del\nEstado para el Municipio de Mexicali, Baja California, y no podrá ser menor a 2.00 veces la Unidad de medida y actualización vigente.\nUnitarios de Suelo (Valores Catastrales), por el número de metros cuadrados que corresponda a la superficie de cada predio, aplicándole las siguientes:\nI.- Predios Baldíos, Predios no edificados o que teniendo construcciones en proceso, Predios en receso, Predios en estado ruinoso que presente condiciones de inseguridad y se encuentre improductivo................................. 9.00 al millar\nII.- Predios Comerciales ubicados en plazas y corredores, en zona valle y predios industriales................................. 6.00 al millar\nIII.- Predios Habitacionales:\na).- En uso exclusivo en el que habite el propietario o en uso o goce de terceras personas............................... 3. 0 0 a l millar\nb).- Cuando el predio sea habitado exclusivamente por su propietario y/o cónyuge, y esté registrado a su nombre, siendo éste pensionado, jubilado, persona con discapacidad o persona mayor de sesenta años que acredite esta condición con identificación oficial expedida por Institución Pública, en la que se especifique el domicilio del predio a pagar gozará de un descuento del 50% de la tasa precisada en esta fracción.\nCuando se aplique el beneficio de este inciso, el impuesto predial resultante, no podrá ser menor a 2 veces la Unidad de medida y actualización vigente.\nIV.- Predios de asociaciones, sociedades u organizaciones de productores que realicen actividades agropecuarias y pesqueras........ 3.00 veces\nUnidad de\nMedida y\nActualización\nV.- Predios de asociaciones y sociedades que su actividad principal sea realizar programas asistenciales con fines no lucrativos, predios la Charrería; siempre y cuando encuentren debidamente constituidas registradas, reconocidas por la autoridad correspondiente, y que los predios se encuentren a nombre de éstas; para la obtención del beneficio deberá cubrirse anualmente durante los tres primeros meses del año.......................................... 5.00 veces\nUnidad de\nMedida y\nActualización\nVI.- Predios sociales, religiosos, educativos, de organizaciones sindicales, de agrupaciones debidamente constituidas y reconocidas por la autoridad correspondiente.................... 6.00 al millar\nLos predios Educativos que se encuentren debidamente adscritos ante la Secretaría de Educación Pública, podrán acceder de una disminución de un valor de 1.50 al millar.\nVII.- Predios ubicados en zonas habitacionales, para uso industrial, comercial o mixto....... 6. 00 al millar\nVIII.- Predios ubicados en las Zonas Urbanas de los\nEjidos o Poblados Rurales en uso habitacional exclusivamente.................. 3.00 al millar\nIX.- Predios de reserva territorial............... 3.00 al millar\na).- Que tengan factibilidad de servicios y no cuenten con los mismos a pie de terreno o que cuenten con los servicios básicos a pie de terreno............... 6.00 al millar\nX.- Predios dedicados permanentemente a fines:\nAgrícolas, ganaderos, forestal, acuícola, de extracción de pétreos, arenosos y cerril....................................... 3.00 al millar\nXI.- Predios ubicados en zonas urbanas de los ejidos o poblados rurales que no estén destinados a la explotación agropecuaria o a uso habitacional, pagarán el Impuesto\nPredial, de acuerdo a la tasa establecida para el uso y destino del suelo.\nXII.- Predios de propiedad de particulares que se encuentren destinados a un servicio público a cargo del Gobierno Municipal, que se encuentren en proceso o sean destinados para ser donados a favor del Municipio, previa calificación que realice la Autoridad\nFiscal competente........................... 0.00 al millar\nLos predios de Dominio Público, propiedad de la Federación, del Estado o de los Municipios, estarán exentos de pago de conformidad con lo estipulado en el Artículo 75 BIS A Fracción IX de la Ley de Hacienda\nMunicipal del Estado de Baja California, con las excepciones que el mismo establece.\nLos predios urbanos ocupados por asentamientos irregulares y que se encuentren en proceso de regularización por Organismo Oficial Federal o Estatal, siempre que estén destinados total y exclusivamente para habitación de sus propietarios previa opinión favorable de los organismos, pagarán de acuerdo a la tasa establecida para dicho uso.\nLos predios públicos que sean utilizados por entidades paraestatales o por particulares, bajo cualquier título, o la proporción de los mismos que sean utilizados para fines administrativos y no operativos, o propósitos distintos a los de su objeto público conforme a lo señalado en el Artículo 115 de la Constitución Política de los Estados\nUnidos Mexicanos, pagarán el Impuesto Predial de acuerdo al valor, uso\nMunicipal. artículo 6, se establece la siguiente sobre tasa del impuesto predial:\na).- Sobre tasa en apoyo a Seguridad Pública, del 2.00 al millar sobre la base del citado impuesto. descuentos siguientes:\nI.- Descuento del 1.52 al millar de la sobre tasa, respecto a las tasas establecidas en las fracciones III, VIII, IX excepto el inciso a) y la fracción X.\nII.- Descuento del 1.04 al millar de la sobre tasa, respecto a las fracciones II, VI, VII y IX únicamente el inciso a).\nPara efectos de este artículo se entiende por:\n1).- Predio.- A la porción de terreno, con o sin construcción, limitada por un perímetro, comprendida dentro del\nMunicipio, que constituya una sola propiedad, copropiedad, posesión o usufructo.\n2).- Predio urbano.- Los existentes dentro del límite de la mancha urbana, zonas de transición y de las manchas urbanas de los poblados, que cuenten con acción o acciones de urbanización, con excepción de los predios dedicados permanentemente a fines agrícolas, o los que estén ubicados en las zonas rústicas y contengan construcciones que no se destinen a fines agrícolas, ganaderos, mineros o forestales.\n3).- Predio suburbano.- Es aquel que se encuentra dentro del límite de la mancha urbana que no ha recibido alguna acción de urbanización, pero que por su ubicación y características es factible de recibirlas. Dentro de esta categoría se consideran las reservas territoriales, que son áreas de un centro de población que serán utilizadas para su futuro crecimiento y se integrarán al sistema de suelo para el desarrollo urbano y la vivienda.\n4).- Predio rústico.- Los predios que no estén comprendidos dentro de los números anteriores 2) y 3).\n5).- Predio no edificado o baldío.- Al que encuadre en cualquiera de los siguientes supuestos:\na).- Al predio urbano que no tenga construcciones y se encuentre improductivo.\nb).- Al predio urbano que teniendo construcciones en proceso, en receso o en estado ruinoso, presente condiciones de inseguridad y se encuentre improductivo.\nc).- Al predio urbano que teniendo construcciones no habitadas por el propietario, al hacerse el avalúo de éstas, resulten con valor inferior al cincuenta por ciento del valor del terreno, en zonas que cuenten como mínimo con servicios de agua, electricidad y drenaje.\nd).- Al predio que teniendo construcciones, éstas sean de carácter provisional, los materiales usados sean de además se encuentre improductivo.\nPara efectos de lo dispuesto en los incisos anteriores, se entiende que un predio es improductivo cuando, siendo urbano, no sea utilizado con fines habitacionales, educativos, para la realización de actividades comerciales, industriales, de equipamiento o servicios y carezca de equipamiento y mantenimiento adecuado a su uso.\nNo se consideran predios no edificados o baldíos, los que sean utilizados con fines habitacionales, educativos, comerciales, industriales, de prestación de servicios, cuyas áreas constituyan jardines ornamentales o se aprovechen en la realización de actividades deportivas, siempre y cuando cuenten con la infraestructura, equipamiento e instalaciones necesarias para dicho objeto.\n6).- Predio edificado.- Todos aquellos predios urbanos que no estén especificados en el numeral anterior.\n7).- Predio habitacional.- Todos aquellos dedicados exclusivamente para habitación.\n8).- Predio industrial.- Los que se encuentren comprendidos dentro de una zona declarada expresamente como zona industrial en los programas de desarrollo urbano de población, así como los ocupados exclusivamente para la indicada.\n9).- Predio comercial.- Todos aquellos que se dediquen total o parcialmente a giros comercial, así como actividades u oficinas administrativas gubernamentales.\n10).- Predio público.- Aquellos propiedad o posesión de la\nFederación, Estado o Municipio que con base en la Ley aplicable, sean considerados en dominio público.\n11).- Predio educativo.- Los que estén dedicados exclusivamente educativos.\n12).- Predio social.- Todos aquellos de propiedad o posesión desarrollo de actividades de beneficencia.\n13).- Predios de agrupaciones.- Los que sea propiedad o posesión de organizaciones sindicales, ejidales, sociedades o asociaciones civiles u otras similares.\n14).- Vía pública.- Todo espacio de uso común que se encuentre destinado o que de hecho se utilice, al libre tránsito de personas, bienes o servicios, a alojar redes de infraestructura urbana a dar acceso, iluminación, ventilación y asoleamiento a los predios que lo delimitan.\nEste espacio está limitado por la superficie engendrada por la generatriz vertical que sigue el alineamiento oficial o el lindero de dicha vía pública.\nARTÍCULO 7.- El Impuesto Predial se causará y deberá cubrirse anualmente durante los dos primeros meses del año, excepto cuando exceda de cuatro veces la Unidad de Medida y Actualización vigente, que podrá ser cubierto bimestralmente durante los meses de Febrero, Abril, Junio, Agosto, Octubre y Diciembre.\nARTÍCULO 8.- Los contribuyentes que acudan a efectuar el pago del importe anual del Impuesto Predial del presente ejercicio fiscal, cuando éste se realice en una sola exhibición durante los meses de\nEnero, Febrero y Marzo, del año en curso, gozarán de un descuento del\n15%, 10% y 5% respectivamente, únicamente respecto del importe total a pagar por concepto del Impuesto Predial, por lo que no se incluye el descuento en la sobre tasa referida en el artículo 6 de esta Ley.\nLos propietarios de predios urbanos baldíos o no edificados, que la Dirección de Administración Urbana, gozarán de hasta un 50% de ejercicios anteriores pendientes de liquidación o pago, siempre y anterior. El descuento que otorga el certificado podrá aplicarse en forma bimestral.\nLas bases del Certificado de Mejoramiento a la Imagen Urbana, se encuentran establecidas en el Artículo 42, apartado “B” de esta Ley. casa habitación, cuyo valor catastral no exceda de $500,000 pesos, y que los contribuyentes realicen el pago durante los meses de enero, gozarán de un descuento del 3% (tres por ciento) adicional a cualquier otro estímulo fiscal aplicable.\n02 IMPUESTO SOBRE LA PLUSVALÍA\n3 IMPUESTOS SOBRE LA PRODUCCIÓN, EL CONSUMO Y LAS TRANSACCIONES\n01 IMPUESTO SOBRE ADQUISICIÓN DE INMUEBLES\nARTÍCULO 9.- El Impuesto sobre Adquisición de Inmuebles a cargo de los contribuyentes, se determinará, causará y pagará aplicando la tasa que a continuación se establece, sobre la base gravable que se determine conforme al artículo 75-Bis B de la Ley de Hacienda Municipal del\nEstado de Baja California:\nTARIFA\nRango Límite inferior Límite superior Cuota fija Tasa marginal\n1 0.01 800,000.00 0 1.50%\n2 800,000.01 1,500,000.00 12,000 2.00%\n3 1,500,000.01 2,300,000.00 26,000 2.50%\n4 2,300,000.01 3,100,000.00 46,000 3.00%\n5 3,100,000.01 4,000,000.00 70,000 3.50%\n6 4,000,000.01 5,000,000.00 101,500 4.00%\n7 5,000,000.01 6,400,000.00 141,500 4.50%\n8 6,400,000.01 En adelante 204,500 5.00%\nPara el cálculo del Impuesto sobre Adquisición de Inmuebles, la base los límites del recuadro; a la base del impuesto se le disminuirá el límite, se multiplicará por la tasa aplicable sobre el excedente del límite inferior, al resultado se le sumará la cuota fija que corresponda y el importe de dicha operación será el impuesto a pagar; lo anterior, conforme a la siguiente fórmula:\nImpuesto sobre Adquisición de Inmuebles = ((BI-LI) x T)+ CF\nEn donde:\nBI = Base del Impuesto\nLI = Límite inferior correspondiente\nT = Tasa para aplicarse sobre excedente del límite inferior correspondiente.\nCF = Cuota fija correspondiente\nLa tarifa establecida en el presente artículo es aplicable para la determinación del impuesto sobre Adquisición de Inmuebles, respecto a los bienes inmuebles ubicados en Mexicali y su Valle por lo que en estos supuestos, no serán aplicables las deducciones ni la tasa que se encuentran establecidas en las fracciones III y IV del artículo 75Bis B, de la Ley de Hacienda Municipal del Estado de Baja California.\nPor lo tanto, cualquier disposición emitida con anterioridad que se oponga a la presente disposición, no surtirá efecto alguno en el\nMunicipio de Mexicali en tanto se encuentre vigente la misma. del o los inmuebles de que se trate, por causas imputables al\nMunicipal, se llevará a cabo la devolución del pago efectuado siempre que no sean causas imputables a la autoridad municipal, con una sanción de 2 a 5 Unidades de Medida y Actualización vigente.\nLos contribuyentes al realizar el pago de este impuesto, no deberán presentar adeudo de Impuesto Predial del año en curso.\n4 IMPUESTOS AL COMERCIO EXTERIOR\n5 IMPUESTOS SOBRE NÓMINAS Y ASIMILABLES\n6 IMPUESTOS ECOLÓGICOS\nCAPÍTULO II\n7 ACCESORIOS DE IMPUESTOS\n01 ACCESORIOS DE IMPUESTOS\nARTÍCULO 10.- Son los ingresos que se perciben por concepto de recargos, sanciones, gastos de ejecución, indemnizaciones, entre otros, asociados a los impuestos, cuando éstos no se cubran oportunamente, de conformidad con lo siguiente:\nI.- Recargos por mora: Cuando no se paguen las contribuciones dentro de los plazos señalados en las disposiciones fiscales o no se cubran las parcialidades en los plazos convenidos, se pagarán recargos por mora a la tasa del 2% mensual.\nII.- Recargos por financiamiento: Cuando se conceda prórroga para el pago de créditos fiscales o para que los mismos sean cubiertos en parcialidades, se causarán recargos por financiamiento sobre el saldo insoluto a la tasa del 1.5% mensual.\nIII.- Sanciones: Las multas derivadas del incumplimiento en el pago de contribuciones en la forma, fecha y términos que establezcan en esta Ley y en las disposiciones fiscales respectivas.\nIV.- Gastos de Ejecución: Cuando las autoridades fiscales la recuperación de los créditos fiscales que correspondan, se estará a lo establecido en el \"Capítulo VIII. De los\nGastos de Ejecución\" de la Ley de Hacienda Municipal del\nEstado de Baja California.\nV.- Otros: Todos aquellos que se encuentren asociados o establecidos en las leyes fiscales.\nCAPÍTULO III\n8 OTROS IMPUESTOS\n01 IMPUESTO PARA MANTENIMIENTO Y CONSERVACIÓN\nDE LAS VÍAS PÚBLICAS\nARTÍCULO 11.- Son sujetos de este impuesto, las personas que soliciten la Legislatura Estatal respectiva.\nARTÍCULO 12.- Este impuesto se enterará previamente a la expedición o tarifa:\nUNIDAD DE MEDIDA Y\nACTUALIZACIÓN VIGENTE\nI.- Vehículos de uso particular................. 7.00 veces\nII.- Camiones de uso particular.................. 12.00 veces\nIII.- Vehículos de transporte público de pasajeros 10.00 veces\nIV.- Camiones de transporte público de pasajeros o carga..................................... 14.00 veces\nCAPÍTULO IV\n9 IMPUESTOS NO COMPRENDIDOS EN LA LEY DE INGRESOS VIGENTE CAUSADOS\nEN EJERCICIOS FISCALES ANTERIORES PENDIENTES DE LIQUIDACIÓN O PAGO.\n01 IMPUESTOS CAUSADOS EN EJERCICIOS ANTERIORES PENDIENTES DE\nLIQUIDACIÓN O PAGO\nARTÍCULO 13.- Los Impuestos no pagados en el ejercicio fiscal en que anteriores, aplicando en cuanto al fondo, las leyes vigentes a la fecha del Estado de Baja California o en su caso, el procedimiento judicial que corresponda.\nEn el caso del Impuesto Predial, cuando el Consejo del Catastro anterioridad, el nuevo valor se aplicará retroactivamente al Impuesto pendiente de pago.\nTÍTULO TERCERO\n2 CUOTAS Y APORTACIONES DE SEGURIDAD SOCIAL\nCAPÍTULO I\n1 APORTACIONES PARA FONDOS DE VIVIENDA\n2 CUOTAS PARA LA SEGURIDAD SOCIAL\n3 CUOTAS DE AHORRO PARA EL RETIRO\n4 OTRAS CUOTAS Y APORTACIONES PARA LA SEGURIDAD SOCIAL.\n01 OTRAS CUOTAS Y APORTACIONES DE RECUPERACIÓN DE SERVICIOS MÉDICOS\nARTÍCULO 14. - Los empleados municipales, los empleados de las\nParamunicipales o aquellos organismos de participación municipal que a través de convenio con sus empleados tengan servicios de seguridad equivalente al 5% de su salario neto como aportación de recuperación de servicios médicos municipales.\n5 ACCESORIOS DE CUOTAS Y APORTACIONES DE SEGURIDAD SOCIAL\nTÍTULO CUARTO\n3 CONTRIBUCIONES DE MEJORAS\nCAPÍTULO I\n1 CONTRIBUCIONES DE MEJORAS POR OBRAS PÚBLICAS\n01 APORTACIONES DE PARTICULARES PARA OBRAS PÚBLICAS MUNICIPALES\nARTÍCULO 15.- El Gobierno Municipal, por conducto del Consejo de\nUrbanización Municipal de Mexicali (CUMM), obtendrá ingresos por contribuciones de mejoras, conforme a lo que establece la Ley de\nUrbanización del Estado de Baja California y su Reglamento, obras que realice el Consejo, en proporción a la superficie de los mismos.\nCAPÍTULO II\n9 CONTRIBUCIONES DE MEJORAS NO COMPRENDIDAS EN LA LEY DE INGRESOS\nVIGENTE, CAUSADAS EN EJERCICIOS FISCALES ANTERIORES PENDIENTES DE\nLIQUIDACIÓN O PAGO\n01 APORTACIONES DE PARTICULARES PARA OBRAS PÚBLICAS MUNICIPALES DE\nEJERCICIOS ANTERIORES\nARTÍCULO 16.- Las Contribuciones de Mejoras no pagadas en el ejercicio fiscal en que se causaron se cobrarán como pagos extemporáneos de ejercicios fiscales anteriores, aplicando en cuanto al fondo, las leyes vigentes a la fecha en que se generaron y en cuanto a la forma mediante el procedimiento administrativo de ejecución que establece la Ley de\nHacienda Municipal del Estado de Baja California o en su caso, el procedimiento judicial que corresponda.\nTÍTULO QUINTO\n4 DERECHOS\nCAPÍTULO I\n1 DERECHOS POR EL USO, GOCE, APROVECHAMIENTO O EXPLOTACIÓN DE BIENES\nDEL DOMINIO PÚBLICO\n01 EXPLOTACIÓN O ARRENDAMIENTO DE BIENES MUEBLES E INMUEBLES\nPROPIEDAD DEL GOBIERNO MUNICIPAL\nARTÍCULO 17.- La renta de los bienes muebles e inmuebles de dominio público propiedad del Municipio de Mexicali, así como los que tiene a subarrendar, serán fijados en cada caso por la Comisión Municipal de días de cada mes.\n02 DEL PISO\nARTÍCULO 18.- Las personas físicas o morales que previa autorización de la autoridad municipal correspondiente hagan uso del piso, de instalaciones subterráneas o aéreas, o en las vías públicas, o en el de actividades comerciales.\nPor construcción de tuberías tendido de cables, fibras ópticas o similares y conducciones aéreas de uso público y privado, sean eléctricas, telefónicas, telecomunicaciones, de transportación de gas domiciliario o industrial y otros, pagarán por metro lineal:\nUNIDAD DE MEDIDA Y\nACTUALIZACIÓN VIGENTE\nI.- Casetas telefónicas, registros para distribuidores telefónicos, sobre el nivel de banqueta, diariamente, por cada una; debiendo realizar el pago anual dentro de los primeros 60 días del ejercicio fiscal.......................................... 1.21 veces\nII.- Instalación de postes o similar en vía pública.... 1.21 veces\nIII.- Instalaciones de infraestructura, por metro lineal, anualmente:\na).- Líneas subterráneas de:\n1).- Telefonía.............................. 0.10 veces\n2).- Transmisión de datos................... 0.10 veces\n3).- Transmisión de señales de televisión por cable.................................. 0.10 veces\n4).- Distribución de gas.................... 0.10 veces\n5).- Energía eléctrica...................... 0.10 veces\nb).- Líneas visibles o aéreas de:\n1).- Telefonía.............................. 0.90 veces\n2).- Transmisión de datos................... 0.90 veces\n3).- Transmisión de señales de televisión por cable.................................. 0.90 veces\n4).- Energía eléctrica...................... 0.90 veces\nCualquier otra instalación permanente en la vía pública, pagará lo que corresponda de acuerdo con la autorización que emita el Ayuntamiento.\nPor uso de las vías públicas y/o del equipamiento urbano público y/o de las áreas verdes municipales, para la explotación de la imagen urbana, pagarán por estructura o instalación:\na).- Anuncio publicitario o propaganda; debiendo realizar el pago anual dentro de los primeros\n60 días del ejercicio fiscal............... 60.00 veces\nCAPÍTULO II\n3 DERECHOS POR LA PRESTACIÓN DE SERVICIOS\n01 EXENCIÓN DE DERECHOS A ASOCIACIONES CIVILES SIN FINES DE LUCRO\nARTÍCULO 19.- Se autorizó a las instituciones de asistencia social como Asilos, Estancias Infantiles, Casas Hogar, Centros de Atención a\nMigrantes y Centros de Rehabilitación, previo estudio socio económico, siguientes:\nI.- Factibilidad de Uso de Suelo;\nII.- Dictamen de Uso de Suelo;\nIII.- Acceso vial;\nIV.- Certificación de Deslinde;\nV.- Licencia de Construcción;\nVI.- Terminación de Obra;\nVII.- Inspección de Bomberos;\nVIII.- Plan de Contingencia;\nIX.- Certificación de Dispositivos de Seguridad;\nX.- Licencia Ambiental;\nXI.- Programa Interno de Protección Civil;\nXII.- Inspecciones de Protección Civil;\nXIII.- Capacitaciones de Protección Civil; y\nXIV.- Todos los demás trámites que garanticen la Seguridad de los\nCentros de Asistencia Social.\nEn virtud de lo anterior, y siguiendo la misma línea de acción tendiente a lograr la regularización total de los Centros de Asistencia\nSocial, es que se establecen exenciones en los trámites relacionados que no se encontraban previstos en Leyes de Ingresos anteriores.\n02 DERECHO POR SERVICIO DE ALUMBRADO PÚBLICO\nARTÍCULO 20.- En materia de Derechos por Servicio de Alumbrado Público, se aplicarán las siguientes disposiciones:\nI.- Es objeto de este derecho, la prestación del servicio de alumbrado público. Se entiende por servicio de alumbrado público, el servicio de iluminación directo o indirecto que las autoridades municipales otorgan a través de la red de alumbrado público y alumbrado ornamental, en espacios públicos y vialidades como calles, avenidas, bulevares, caminos vecinales, plazas, parques, jardines y otros lugares de uso común del\nMunicipio de Mexicali.\nII.- Son sujetos de este derecho, los beneficiarios del servicio de alumbrado público a que se refiere el párrafo anterior, en el Municipio de Mexicali.\nIII.- La base de este derecho es el costo anual globalizado del servicio de alumbrado público erogado por el Municipio.\nIV.- El derecho por el servicio de alumbrado público se causará\n00/100 moneda nacional.\nV.- El pago del Derecho de Alumbrado Público deberá realizarse dentro de los primeros 10 días siguientes al mes en que se cause, en las oficinas recaudadoras municipales y demás instancias o establecimientos autorizados para tal efecto.\nEl citado plazo y forma de cobro, podrá modificarse o ampliarse en beneficio de los contribuyentes, cuando existan acuerdos o convenios entre el Municipio con otras instancias públicas o privadas, que permitan simplificar el entero de la contribución.\nVI.- Los ingresos que se perciban por el derecho establecido en este artículo, se destinarán prioritariamente al pago de conceptos que se requieran para el debido otorgamiento del servicio, operación y mantenimiento del alumbrado público que proporciona el Municipio.\n03 SERVICIOS QUE PRESTA EL REGISTRO CIVIL\nARTÍCULO 21.- Los derechos por servicios que preste el Registro Civil, serán pagados por los usuarios, sujetándose a la siguiente tarifa:\nUNIDAD DE MEDIDA Y\nACTUALIZACIÓN VIGENTE\nI.- NACIMIENTOS\na).- Registro en horas hábiles dentro de la oficina menores de cinco años................................. EXENTO\nb).- Registro en Institución de Salud por enfermedad infantil o maternal............................. EXENTO\nc).- Registro en horas inhábiles dentro de la oficina........................ 3.96 veces\nd).- Registro a domicilio en horas hábiles.. 21.73 veces\ne).- Registro a domicilio en horas 46.30 veces inhábiles...........................\nf).- Registro de nacimiento dentro del\nPrograma “Jornadas del Registro\nCivil” aún fuera del término de cinco años.................................. EXENTO\nII.- MATRIMONIOS\na).- Solicitud, trámite y celebración en horas hábiles dentro de la oficina...... 6.61 veces\nb).- Solicitud, trámite y celebración en horas inhábiles dentro de la oficina.... 10.58 veces\nc).- Solicitud, trámite y celebración en días inhábiles dentro de la oficina........ 12.60 veces\nd).- Solicitud, trámite y celebración a domicilio en horas hábiles............. 52.92 veces\ne).- Solicitud, trámite y celebración a domicilio en horas inhábiles........... 66.15 veces\nf).- Solicitud, trámite y celebración a domicilio en días inhábiles............ 79.38 veces\ng).- Solicitud, trámite y celebración fuera de la oficina, pero en lugar asignado por la oficialía....................... 26.46 veces\nh).- Anotación de cambio de régimen matrimonial, registro o modificación a las capitulaciones matrimoniales....... 16.54 veces\ni).- Costo adicional por servicio de celebración urgente, dentro o fuera de la oficina............................. 16.54 veces\nj).- Formatos oficiales para contraer matrimonio, siendo estos: Solicitud para contraer matrimonio, formato para certificado médico prenupcial y contrato de régimen matrimonial........ 3.31 veces\nk).- Constancia de asistencia a pláticas prematrimoniales...................... 2.64 veces\nl).- Celebración de matrimonio dentro del programa de “Matrimonios Colectivos”... EXENTO\nm).- Dentro del Programa \"Matrimonios\nColectivos\" los formatos oficiales para contraer matrimonio, siendo estos:\nSolicitud para contraer matrimonio, formato para certificado médico prenupcial y contrato de régimen matrimonial........................... EXENTO\nn).- Dentro del Programa \"Matrimonios\nColectivos\" la constancia de asistencia a pláticas prematrimoniales............ EXENTO\nEn caso de cancelación del servicio solicitado, en los incisos a), b),\nc), d), e), f) y g) previstos en esta fracción, se llevará a cabo la devolución del 50% del pago efectuado, siempre y cuando se solicite hasta 5 días anteriores a la fecha en que se llevaría a cabo el matrimonio.\nTratándose de matrimonios en los cuales intervengan personas con capacidades diferentes, problemas motrices, enfermedades terminales, Registro Civil, la celebración del matrimonio a domicilio o\nInstituciones de Salud, será exento de pago. ordenadas por la autoridad competente, no sea posible efectuarse el matrimonio en la fecha agendada, procederá la devolución del 100% de en los incisos a), b), c), d), e), f), g), j) y k) de esta fracción, Municipal, y siempre que la solicitud se realice antes de la fecha en que se celebraría el matrimonio.\nIII.- DEFUNCIONES\na).- Servicio, registro y expedición de\nOrden de Inhumación y/o cremación en horas hábiles.......................... 5.29 veces\nb).- Registro y expedición de Orden de\nInhumación y/o cremación en horas inhábiles............................. 5.98 veces\nc).- Registro y expedición de Orden de\nInhumación y/o cremación en día inhábil. 5.98 veces\nd).- Por servicios que preste el Registro\nCivil a panteones particulares en horas hábiles.............................. 9.26 veces\ne).- Por servicios que preste el Registro\nCivil a panteones particulares en día inhábil.............................. 10.73 veces\nf).- Por servicios que preste el Registro\nCivil a panteones particulares en horas inhábiles....... 11.90 veces\ng).- Servicio, registro y expedición de Orden de Traslado de cadáver dentro de\nTerritorio Nacional.................... 6.61 veces\nh).- Servicio, registro y expedición de Orden de Traslado de cadáver dentro de\nTerritorio Nacional en día inhábil..... 8.82 veces\ni).- Servicio, registro y expedición de Orden de Traslado de cadáver fuera de\nTerritorio Nacional.................... 13.23 veces\nj).- Servicio, registro y expedición de Orden de Traslado de cadáver fuera de\nTerritorio Nacional en día inhábil..... 14.49 veces\nk).- Orden de Exhumación.................... 7.93 veces\nl).- Servicio y registro de defunción por\nPresunción de Muerte................... 5.29 veces competente, los derechos que comprenden los incisos a), b), c), d),\ne), f), g), h), i) y j) de esta fracción, y los accesorios que se causen por dichos conceptos, quedarán exentos de pago en el tiempo permanezca vigente la emergencia y en los casos en que la defunción sea asociada directamente con dicha emergencia sanitaria.\nIV.- DIVORCIOS\na).- Administrativo......................... 39.69 veces\nb).- Inscripción de sentencia de divorcio o nulidad de matrimonio proveniente de\nJuzgado................................ 19.84 veces\nc).- Campañas especiales de inscripción de sentencia de divorcio o nulidad de matrimonio proveniente de Juzgado local. 9.92 veces\nV.- ADOPCIONES\na).- Inscripción de Sentencia de Adopción proveniente de Juzgado....... 13.23 veces\nb).- Campañas especiales de inscripción colectiva de Sentencia de Adopción proveniente de Juzgado.................. EXENTO\nVI.- RECONOCIMIENTO DE HIJOS\na).- Registro de reconocimiento............. 6.61 veces\nb).- Reconocimiento dentro del programa\n“Jornadas del Registro Civil”........... EXENTO\nVII.- Inscripción de constancias referentes a\nHechos o actos del Registro Civil ocurridos en el Extranjero, con participación de\nMexicanos................................... 19.84 veces\na).- Programa de inscripción colectiva de constancias referentes a hechos o actos del Registro Civil ocurridos en el\nExtranjero, con participación de\nMexicanos.............................. 9.92 veces\nPor servicio extraordinario de los trámites de las fracciones IV, V, VI y VII, se cobrará.............. 3.96 veces\na).- Copias fotostáticas no certificadas, por hoja................................... 1.32 veces\nb).- Recepción y trámite para anotación marginal de rectificación de acta salvo a aquellos errores imputables a la dependencia............................ 5.29 veces\nc).- Corrección de acta, cuando el error haya sido detectado por el ciudadano antes del día 5 del mes siguiente en que llevo a cabo su registro...................... 1.99 veces\nd).- Campañas especiales relativas al Estado\nCivil de las personas................... EXENTO\ne).- Recepción, trámite y anotación marginal de cancelación de acta por duplicidad... 5.29 veces\nf).- Otras anotaciones marginales........... 2.64 veces\ng).- Certificados y constancias............. 2.64 veces\n1).- Por Expedición de Certificación de\nApéndices de Asentamientos.\n2).- Otros.\nh).- Por solicitud y envío de actas que obran en las Oficialías del Registro Civil del territorio nacional vía servicio de mensajería, independientemente del costo por derechos estipulado en cada\nEstado................................. 3.31 veces\ni).- Constancia de inexistencia............. 2.64 veces\nj).- Por expedición de acta certificada, extracto y/o digitalizada de los hechos y actos civiles asentados en las\nOficialías del Registro Civil del\nMunicipio de Mexicali................... 2.20 veces\nk).- Expedición de extracto de acta de nacimiento a menores de 12 años, nacidos en el Municipio de Mexicali, Baja California, dentro del “Programa\nNiño Mexicalense”...................... EXENTO\nl).- Por trámite de solicitud de constancias referentes a hechos o actos del registro civil solicitados desde el extranjero... 19.84 veces\nm).- Por la expedición de la primera copia certificada de acta de nacimiento a la persona que acuda a registrarse por primera vez............................ EXENTO\nn).- Por el servicio de la expedición de acta digitalizada Estatales e Interestatales a través del sistema electrónico de la dirección del Registro Civil de Gobierno del Estado............................. 1.89 veces\nPor la expedición de documentos subsecuentes al primero, señalados en el inciso j), se cobrará el 50% del costo normal del servicio.\nLos pensionados, jubilados, personas con discapacidad y las personas mayores de sesenta años, pagarán el 50% de la tarifa, únicamente tratándose de documentos que estén a su nombre, debiendo comprobar su\nInstitución Pública, únicamente en los trámites comprendidos en la fracción VIII, inciso a), b), e), f), h), i), j) y l).\nTratándose de personas en situación de calle mayores de 60 años y las personas con discapacidad, estarán exentos de pago, previa solicitud o en su caso, estudio socioeconómico y certificado médico que acredite tal condición, únicamente en los trámites comprendidos en fracción\nVIII, inciso j).\nDe igual manera, se exenta del pago de los derechos por la expedición de acta certificada, extracto, y/o digitalizada de los hechos y actos civiles asentados en las Oficialías del Registro Civil del Municipio de Mexicali, contenido en la fracción VIII del inciso j), a menores de edad nacidos en el Municipio de Mexicali, Baja California; en estado de vulnerabilidad, o en su caso, que se encuentren a cargo de\nAsociaciones Civiles cuyo objeto sea la prestación de servicios de asistencia social, trámite que deberá realizarse por conducto de\nDesarrollo Integral de la Familia de Mexicali (DIF Municipal), debiendo acreditar ante esa autoridad que el menor se encuentra bajo su resguardo.\nPara los efectos del presente artículo, se entiende por horas hábiles, las transcurridas de 8:00 a 15:00 horas y por días hábiles de lunes a viernes, siempre y cuando no se trate de un día inhábil decretado oficialmente.\nEn caso de existir circunstancias de emergencia sanitaria en el\nMunicipio, se entenderán por horas hábiles las transcurridas de 8:00 a 17:00 horas.\n04 POR LA AUTORIZACIÓN DEL USO U OCUPACIÓN DE VÍAS PÚBLICAS PARA\nEJERCER EL COMERCIO O LA PRESTACIÓN DE SERVICIOS, POR COMERCIANTES\nAMBULANTES, CON PUESTOS SEMIFIJOS O MERCADOS SOBRE RUEDAS\nARTÍCULO 22.- Por la expedición o revalidación de permisos para el uso prestación de servicios en los términos del reglamento de la materia, se pagarán conforme lo siguiente:\nUNIDAD DE MEDIDA Y\nACTUALIZACIÓN VIGENTE\nI.- Permisos Ordinarios (Anuales):\na).- Aseadores de calzado ambulante.......... 5.29 veces\nb).- Aseadores de calzado semifijos.......... 10.58 veces\nc).- Fotógrafos ambulantes................... 9.26 veces\nd).- Músicos ambulantes...................... 9.26 veces\ne).- Vendedores ambulantes................... 13.23 veces\nf).- Puestos semifijos....................... 33.07 veces\ng).- Extensión de espacio de puesto semifijo. 33.07 veces\nh).- Puestos semifijos periódicos y revistas. 10.58 veces\ni).- Comerciante en mercado sobre ruedas, por la superficie especificada en el\nReglamento Municipal de 1 a 3 días de la semana.................................. 18.52 veces\nj).- Extensión de espacio de 1 a 3 metros en mercado sobre ruedas de 1 a 3 días de la semana.................................. 9.26 veces\nk).- Extensión de espacio de 3 a 6 metros en mercado sobre ruedas de 1 a 3 días de la semana.................................. 18.52 veces\nl).- Comerciante en mercado sobre ruedas, por la superficie especificada en el\nReglamento Municipal de 4 a 7 días de la semana.................................. 34.39 veces\nm).- Extensión de espacio de 1 a 3 metros en mercado sobre ruedas de 4 a 7 días de la semana.................................. 17.20 veces\nn).- Extensión de espacio de 3 a 6 metros en mercado sobre ruedas de 4 a 7 días de la semana.................................. 34.39 veces ñ).- Ambulantes con vehículo................. 32.00 veces por vehículo\no).- Vendedor con vehículo Food Truck......... 45.00 veces por vehículo\np).- Aquellos permisos que se otorguen a institución municipal de asistencia social y/o fideicomiso y/o patronato autorizado, para operar dentro de la circunscripción territorial delimitada por el Decreto que declara como “Área\nParcial de reactivación Comercial y de\nUso Turístico Intensivo”................ EXENTO\nLas tarifas anteriores se cobrarán proporcionalmente al número de meses del ejercicio fiscal del que se trate, pendientes de transcurrir a partir de la fecha en que se expida el permiso.\nII.- Permisos Extraordinarios (de 1 a 30 días naturales):\nUNIDAD DE MEDIDA Y\nACTUALIZACIÓN VIGENTE\na).- Ambulante............................... 3.96 veces\nb).- Músicos ambulantes hasta tres integrantes............................. 3.96 veces\n1.- 4 o más integrantes............. 1.32 veces por cada uno\nc).- Semifijos............................... 6.61 veces\nd).- Extensión de espacios de puesto semifijo 6.61 veces\ne).- Mercado sobre ruedas.................... 1.32 veces\nf).- Ambulantes con vehículo................. 6.32 veces por vehículo\ng).- Permiso Especial para la ocupación de la vía pública para el desarrollo de actividades sociales u otro tipo de actividades............................. EXENTO\nh).- Por la expedición de permisos para auxiliares de oferentes titulares, que cuente con certificado médico expedido por Servicios Médicos Municipales....... 1.40 veces\ni).- Vendedor con vehículo Food Truck........ 8.32 veces por vehículo\nIII.- Permisos Extraordinarios (de 1 a 180 días naturales):\na).- Por la expedición de permisos para auxiliares de oferentes titulares, que cuente con certificado médico expedido por Servicios Médicos Municipales....... 8.40 veces\nIV.- Otros Servicios:\na).- Constancias de permisionario............ 2.64 veces\nb).- Reposición de constancia de permisionario........................... 3.96 veces\nc).- Certificado de no adeudo................ EXENTO\nd).- Modificaciones, reposiciones o cambios a permisos ordinarios..................... 3.96 veces\nPara los residentes de la zona rural se aplicará el 75% de las tarifas del presente artículo. registrados ante el DIF Municipal, siempre y cuando cumplan con el\nReglamento para el Ejercicio del Comercio, o de Otras Actividades en la Vía o Bienes Públicos del Municipio de Mexicali. pensionados, jubilados o mayores de 60 años, estarán exentos por los cuando sea para revalidación y únicamente en los meses de enero, febrero y marzo. Para permisos nuevos tramitados en los meses de enero a diciembre el descuento será del 50%, para aquellas personas que revaliden en los meses de abril a diciembre, el descuento será del\n50%.\nLas personas que acrediten con documentación oficial ser pensionado, jubilado o mayores de 60 años, tendrán el 50% de descuento en permisos extraordinarios.\nAquellas personas con discapacidad y que cuenten con autorización vigente a su nombre, estarán exentos por los conceptos de derechos a que hace referencia este artículo.\nEn el caso de madres autónomas trabajadoras, padres autónomos trabajadores y madres, padres o tutores de un hijo con discapacidad, cubrirán el 50% por concepto de derechos a que se refiere este artículo, siempre y cuando así lo acrediten ante el Departamento de\nComercio Ambulante, conforme a los requisitos que se expidan.\nEn lo referente al párrafo anterior, los padres solteros deberán acreditar tener la guarda y custodia de sus hijos, para acceder al citado beneficio.\nSe otorgará descuento del 25% a jóvenes estudiantes de entre 16 y 25 la institución donde estudie, constancia de estudios y/o boleta, lo anterior con previa autorización por escrito de su padre, madre o tutor, en los casos de menores de edad.\nEstos beneficios se aplicarán a un solo permiso, por lo que en el caso de que la persona contara con más de uno, a éste(os) se aplicará la tarifa señalada en las fracciones anteriores, según corresponda.\nLas personas que revaliden sus permisos, en los meses de enero, febrero y marzo del año en curso, ante el Departamento de Comercio Ambulante como lo marca el artículo 30 del Reglamento para el Ejercicio del\nComercio, o de otras Actividades en la Vía o Bienes Públicos del\nMunicipio de Mexicali y que conforme a la Ley de Ingresos, gozarán de un descuento por pronto pago del 15%, 10% y 5% respectivamente. La falta de pago dentro del plazo establecido, no causará los recargos que establece la presente Ley.\nComercio, o de Otras Actividades en la Vía o Bienes Públicos del\nMunicipio de Mexicali, Baja California se impondrá una sanción, derivada del 5% adicional al valor del permiso que corresponda, de acuerdo a lo establecido en las fracciones I y II del presente artículo.\n05 POR LA AUTORIZACIÓN DE LA VENTA, ALMACENAJE O CONSUMO PÚBLICO DE\nBEBIDAS ALCOHÓLICAS.\nARTÍCULO 23.- Por la recepción, análisis y revisión de solicitudes de permisos nuevos para la operación de establecimientos con venta, almacenaje o consumo de bebidas alcohólicas o alcohol, cambio de giro, cambio de permisionario, cambio de nombre o denominación y cambio de domicilio, así como la emisión de permisos y certificados que por dichos conceptos y similares, se expidan de conformidad con el reglamento de la materia, estarán sujetos a la siguiente tarifa:\nUNIDAD DE MEDIDA Y\nACTUALIZACIÓN VIGENTE\nI.- Certificado de distancias..................... 48.95 veces\nII.- Constancia de cumplimiento de las condiciones del permiso................................... 1.65 veces\nIII.- Dictamen de factibilidad...................... 25.13 veces\nIV.- Inspección de condiciones del local........... 25.13 veces\nV.- Dictamen de Procedencia para la autorización de permisos nuevos, cambio de giro y cambio de domicilio, para operar, el solicitante, dependiendo del giro autorizado por los derechos y obligaciones que adquiera:\nUNIDAD DE MEDIDA Y\nACTUALIZACIÓN VIGENTE\na).- Abarrotes............................... 132.30 veces\nb).- Fonda o Lonchería...................... 132.30 veces\nc).- Restaurante............................. 198.45 veces\nd).- Mercado................................. 132.30 veces\ne).- Supermercado............................ 793.80 veces\nf).- Billar.................................. 248.72 veces\ng).- Tienda de Autoservicio.................. 330.75 veces\nh).- Agencia y Subagencia.................... 330.75 veces\ni).- Expendio................................ 496.12 veces\nj).- Restaurante Bar......................... 578.15 veces\nk).- Bar Turístico........................... 496.12 veces\nl).- Licorería............................... 578.15 veces\nm).- Café Cantante........................... 992.25 veces\nn).- Hotel................................... 529.20 veces ñ).- Discoteca............................... 992.25 veces\no).- Bodega.................................. 330.75 veces\np).- Bar Terraza............................. 826.87 veces\nq).- Centro de Espectáculos.................. 661.50 veces\nr).- Microcervecería........................ 132.30 veces\ns).- Sala de Degustación para la venta de cerveza artesanal....................... 1 32.30 veces\nt).- Boutique de cerveza artesanal........... 132.30 veces\nu).- Depósito................................ 320.75 veces\nv).- Centro de Apuestas...................... 472.50 veces\nVI.- Expedición de Permiso provisional y autorización para la venta de bebidas alcohólicas, cuando el solicitante reúna las condiciones establecidas en el Artículo 52 del Reglamento de la materia, se cobrará 504.00 veces la Unidad de Medida y\nActualización Vigente.\nVII.- Expedición del permiso eventual para la venta de bebidas alcohólicas:\nUNIDAD DE MEDIDA Y\nEVENTO\nACTUALIZACIÓN VIGENTE\na).- Kermeses y posadas...................... 21.16 veces\nb).- Eventos de centros escolares............ 13.23 veces\nc).- Degustación de bebidas alcohólicas y obsequios de bebidas alcohólicas, por establecimiento de 1 a 30 días dentro del mismo mes........................... 50.40 veces\nd).- Contingencias de autos de carreras o exhibición de autos o tractocamiones.... 92.61 veces\ne).- Eventos de lucha libre semi profesional.. 74.08 veces\nf).- Eventos de lucha libre profesional....... 145.00 veces\ng).- Charreadas, rodeo o jaripeo............. 82.02 veces\nh).- Corrida de toros, rejoneo o novillada... 129.65 veces\ni).- Carreras y arrancones de autos, tractocamiones, motocicletas y cualquier otro vehículo de motor.................. 148.17 veces\nj).- Funciones de box no profesional o amateurs................................ 95.25 veces\nk).- Funciones de box semi profesional....... 145.00 veces\nl).- Funciones de box profesional............ 402.19 veces\nm).- Baile popular........................... 267.24 veces\nn).- Peleas de gallos y carreras de Caballos. 330.75 veces ñ).- Ferias o festejos populares............. 190.51 veces\no).- Conciertos musicales masivos............ 661.50 veces\np).- Pasarelas, eventos de modelaje.......... 58.21 veces\nq).- Eventos de música de rock locales....... 124.36 veces\nr).- Muestras gastronómicas y exposiciones generales............................... 50.27 veces\ns).- Cena baile.............................. 95.25 veces\nt).- Torneos deportivos o trasmisión, reproducción y/o difusión digital de eventos deportivos (voleibol, basquetbol béisbol, fútbol, etc.).................. 74.08 veces\nu).- Obras de teatro......................... 50.27 veces\nv).- Aniversario e Inauguraciones de eventos. 63.50 veces\nw).- Eventos o bailes en salones o centro nocturnos............................... 166.69 veces\nx).- Verbena popular......................... 124.36 veces\ny).- Bailes o Espectáculos Eróticos.......... 330.75 veces\nz).- Contingencias, exhibición o espectáculos de motocicletas y bicicletas............ 63.50 veces aa).- Eventos de música de grupos locales generales............................... 50.27 veces bb).- Transmisión, reproducción y/o difusión mediante plataformas digitales de eventos virtuales............................... 58.80 veces cc).- Funciones de artes marciales mixtas semi profesional............................. 145.00 veces dd).- Funciones de artes marciales profesionales........................... 402.19 veces ee).- Presentación de comediantes, conferencistas, o los demás del género... 95.25 veces\nLos eventos promovidos por juntas de mejoramiento, por asociaciones religiosas constituidas legalmente y por asociaciones civiles con fines no lucrativos y que tengan por objeto allegarse de recursos para el cumplimiento de sus fines, así como aquellos estarán...................................... EXENTOS\nVIII.- Los derechos por expedición de permisos nuevos, una vez que se autoricen, se pagarán conforme a la siguiente tarifa, Procedencia:\nUNIDAD DE MEDIDA Y\nACTUALIZACIÓN VIGENTE\na).- Abarrotes.............................. 2,646.00 veces\nb).- Fonda o Lonchería....................... 3,024.00 veces\nc).- Restaurante............................ 3,276.00 veces\nd).- Mercado................................ 10,080.00 veces\ne).- Supermercado........................... 12,600.00 veces\nf).- Billar................................. 9,450.00 veces\ng).- Tienda de Autoservicio................. 13,860.00 veces\nh).- Agencia y Subagencia................... 4,788.00 veces\ni).- Expendio............................... 7,182.00 veces\nj).- Restaurante Bar........................ 18,900.00 veces\nk).- Bar Turístico.......................... 18,900.00 veces\nl).- Licorería.............................. 8,946.00 veces\nm).- Café Cantante.......................... 31,500.00 veces\nn).- Hotel.................................. 31,500.00 veces ñ).- Discoteca.............................. 31,500.00 veces\no).- Bodega................................. 4,788.00 veces\np).- Bar Terraza............................ 18,900.00 veces\nq).- Centro de Espectáculos.................. 12,600.00 veces\nr).- Microcervecería........................ 378.00 veces\ns).- Sala de Degustación para la venta de cerveza artesanal...................... 378.00 veces\nt).- Boutique de cerveza artesanal.......... 378.00 veces\nu).- Depósito.............................. 4,788.00 veces\nv).- Centro de Apuestas.................... 31,500.00 veces\nw).- Restaurante para la venta y almacenaje de vinos de mesa exclusivamente de producción nacional................... EXENTO\nx).- Aquellos permisos que se otorguen a entidades paramunicipales enfocadas a parques temáticos................... EXENTO\nIX.- Derechos por revalidación anual de permisos\nUNIDAD DE MEDIDA y\nACTUALIZACIÓN VIGENTE\na).- Abarrotes............................... 34.77 veces\nb).- Fonda o Lonchería....................... 87.69 veces\nc).- Restaurante............................. 101.30 veces\nd).- Mercado................................. 181.44 veces\ne).- Supermercado............................ 279.72 veces\nf).- Billar.................................. 189.00 veces\ng).- Tienda de Autoservicio.................. 189.00 veces\nh).- Agencia y Subagencia.................... 140.61 veces\ni).- Expendio................................ 170.85 veces\nj).- Restaurante Bar......................... 300.88 veces\nk).- Bar Turístico........................... 349.27 veces\nl).- Licorería............................... 181.44 veces\nm).- Café Cantante........................... 420.33 veces\nn).- Hotel/Motel............................. 210.16 veces ñ).- Discoteca............................... 359.85 veces\no).- Bodega.................................. 130.03 veces\np).- Bar Terraza............................. 300.58 veces\nq).- Centro de Espectáculos.................. 220.75 veces\nr).- Microcervecería........................ 101.30 veces\ns).- Sala de Degustación para la venta de cerveza artesanal....................... 1 01.30 veces\nt).- Boutique de cerveza artesanal........... 101.30 veces\nu).- Centro de Apuestas...................... 472.50 veces\nv).- Depósito................................ 140.61 veces\nw).- Restaurante para la venta y almacenaje de vinos de mesa exclusivamente de producción nacional.................... 40.61 veces\nAdicional a la revalidación anual de permisos permanentes, los alcohólicas en envase abierto enumerados en los incisos c), f), i),\nj), k), m), n), ñ), p), q), r), s) y w) de esta fracción IX, causarán derechos por la cantidad equivalente a 12.60 veces la Unidad de Medida y Actualización vigente, por concepto de apoyo a las campañas y relacionados con el consumo inmoderado de bebidas alcohólicas, así control de seguridad en los establecimientos. por mes y giros.\nJunio:\nBar Terraza, Bar turístico, Café cantante y Discoteca.\nJulio:\nBillar, Bodega, Expendio, Licorería y Motel.\nAgosto:\nAgencia y Subagencia, Autoservicio, Mercado, Supermercado y abarrotes.\nSeptiembre:\nRestaurant, Restaurant Bar, Restaurant para la Venta y Almacenaje de\nVinos de Mesa exclusivamente de producción nacional, Fonda o Lonchería, Hotel, Centro de Espectáculos, Microcervecería, Sala de Degustación para la venta exclusiva de Cerveza Artesanal y Boutique de Cerveza\nArtesanal.\nDe cada año de lo contrario se procederá a lo establecido en el párrafo siguiente:\nQuienes no revaliden sus permisos en forma oportuna o quienes lo hagan fuera de los plazos establecidos conforme a esta Ley de Ingresos causarán una sanción económica, dependiendo de los servicios adicionales con los que cuente el permiso original independientemente de las sanciones administrativas a que tuviese lugar, no procederá sanción alguna cuando se haya presentado y otorgado prórroga para la revalidación de permisos por parte de la Tesorería Municipal, las prórrogas o plazos otorgados serán por única vez y no podrán exceder de 90 días naturales.\nLa sanción aplicable será de acuerdo al siguiente tabulador:\nUNIDAD DE MEDIDA Y\nACTUALIZACIÓN VIGENTE\na).- Abarrotes............................... 33.39 veces\nb).- Fonda o Lonchería....................... 66.15 veces\nc).- Restaurante............................. 66.15 veces\nd).- Mercado................................. 99.22 veces\ne).- Supermercado............................ 132.30 veces\nf).- Billar.................................. 98.91 veces\ng).- Tienda de Autoservicio.................. 98.91 veces\nh).- Agencia y Subagencia.................... 66.15 veces\ni).- Expendio................................ 99.22 veces\nj).- Restaurante Bar......................... 132.30 veces\nk).- Bar Turístico........................... 165.37 veces\nl).- Licorería............................... 99.22 veces\nm).- Café Cantante........................... 198.45 veces\nn).- Hotel/Motel............................. 99.22 veces ñ).- Discoteca............................... 165.37 veces\no).- Bodega.................................. 66.15 veces\np).- Bar Terraza............................. 132.30 veces\nq).- Centro de Espectáculos.................. 132.30 veces\nr).- Microcervecería........................ 66.15 veces\ns).- Sala de Degustación para la venta de cerveza artesanal....................... 66.15 veces\nt).- Boutique de cerveza artesanal........... 66.15 veces\nu).- Centro de Apuestas...................... 157.50 veces\nv).- Depósito................................ 66.15 veces\nX.- La expedición de autorización de cambios o modificación al permiso pagará los siguientes derechos, disminuyéndose de éstos el pago realizado por el Dictamen de Procedencia, dependiendo del giro autorizado por los derechos y obligaciones que adquiera:\na).- Cambio de giro comercial de manera ascendente, se cobrará la diferencia entre las tarifas de los permisos nuevos de los giros que se modifican.\nb).- Por cambio de giro comercial de manera descendente, se de este artículo, relativa al Dictamen de Procedencia del giro que prevalece.\nc).- Por el cambio de nombre comercial se pagará 10% sobre el valor del permiso.\nd).- 30% Sobre el valor del permiso por cambio de domicilio.\ne).- 50% Sobre el valor del permiso por cambio de propietario.\nf).- Operadores Diversos..................... 63.00 veces\nEl cambio de propietario por muerte de su titular, se reducirá 50% del costo previsto en este inciso, siempre y cuando exista testamento que los herederos, en ambos casos, sean familiares descendientes, ascendientes, cónyuge, concubina o concubinario o que tengan cesión de recta hasta el segundo grado.\nXI.- Derechos por otorgamiento de servicios adicionales\nUNIDAD DE MEDIDA Y\nACTUALIZACIÓN VIGENTE\na).- Áreas adicionales de servicio, tales como albercas, jardines, patios, salones o instalaciones para eventos.............. 912.87 veces\nb).- Música grabada.......................... 541.10 veces\nc).- Música en vivo.......................... 799.09 veces\nd).- Baile................................... 760.72 veces\ne).- Espectáculo artístico................... 1,065.01 veces\nf).- Mesas de billar......................... 608.58 veces\ng).- Boliche................................. 912.87 veces\nh).- Bailes Eróticos......................... 1,141.74 veces\nXII.- Derechos por revalidación anual de servicios adicionales\na).- Áreas adicionales de servicio, tales como albercas, jardines, patios, salones o instalaciones para eventos.............. 46.30 veces\nb).- Música grabada.......................... 30.42 veces\nc).- Música en vivo.......................... 41.01 veces\nd).- Espectáculo artístico................... 66.15 veces\ne).- Servibar................................ 46.30 veces\nf).- Mesas de billar......................... 34.39 veces\ng).- Servicio en su auto..................... 91.28 veces\nh).- Bailes Eróticos......................... 91.28 veces\ni).- Boliche................................. 76.73 veces\nj).- Baile................................... 41.01 veces\nXIII.- Recepción, análisis y evaluación de la de alcohol.................................... 30.42 veces\nXIV.- Evaluación y dictamen sobre la procedencia de ampliación al plazo para inicio de operaciones. 13.23 veces\nXV.- Autorización de suspensión del uso del permiso. 39.69 veces\nXVI.- Derechos por otorgamiento de horario extraordinario, por cada hora que se otorgue... 29.10 veces\nAdemás se adiciona al pago de la fracción anterior el cobro de 48.00 veces UMA para fortalecer la campaña y/o capacitación de prevención de accidentes relacionados con el consumo de bebidas alcohólicas.\nXVII.- Expedición de certificación de los permisos para exhibición en establecimientos........... 5.04 veces\nXVIII. Expedición de certificación de los permisos por robo, destrucción o extravío................... 63.00 veces\nLos contribuyentes al realizar el pago de este derecho, deberán presentar el certificado de no adeudo municipal. Salvo que se demuestre un bien inmueble en arrendamiento. autorización de venta, almacenaje o consumo público de bebidas particularidades inherentes a cada giro, así como de sus respectivas restricciones y características, de acuerdo con lo estipulado en la Ley para la Venta, Almacenaje y Consumo Público de\nReglamento para la Venta, Almacenaje y Consumo Público de Bebidas\nAlcohólicas para el Municipio de Mexicali, Baja California.\n06 POR LA AUTORIZACIÓN DEL FUNCIONAMIENTO DE MÁQUINAS ELECTRÓNICAS,\nELECTROMECÁNICAS, MECÁNICAS, MUSICALES, DIGITALES, VIDEOJUEGOS Y\nCUALQUIER TECNOLOGÍA SIMILAR.\nARTÍCULO 24.- Para la apertura, cambio de domicilio o de propietario, cambio o incremento de aparatos y revalidación de máquinas electrónicas, electromecánicas, mecánicas, musicales, digitales, videojuegos y cualquier tecnología similar, que operen mediante la inserción de billete, moneda, ficha, tarjeta, banda magnética o cualquier otro medio de cobro integrado a la máquina, así como la renta de las mismas, como rocolas y karaokes entre otros, deberá entregarse y analizarse la documentación necesaria, previo al pago de derechos que se causen conforme a la tabla siguiente:\nUNIDAD DE MEDIDA Y\nACTUALIZACIÓN VIGENTE\nI.- Apertura de establecimiento hasta diez aparatos 33.07 veces\nII.- Apertura de establecimiento mayor de diez aparatos...................................... 66.15 veces\nIII.- Expedición por primera vez de calcomanía por aparato....................................... 3.96 veces\nIV.- Cambio de domicilio........................... 39.69 veces\nV.- Cambio de propietario......................... 39.69 veces\nVI.- Cambio o incremento, por aparato.............. 6.61 veces\nVII.- Multa por no exhibir la calcomanía que expide la autoridad municipal........................ 10.50 veces\nVIII.- Por revalidación anual, por aparato........... 5.29 veces de este artículo, deberá realizarse a más tardar en el mes de marzo de cada año. electrónicas, electromecánicas, mecánicas, musicales, digitales, de un billete, moneda, ficha, tarjeta, banda magnética o cualquier otro medio de cobro integrado a la máquina, así como los propietarios y/o poseedores de los bienes inmuebles donde se instalen, serán solidariamente responsables del pago de los impuestos, derechos y/o multas que se originen con motivo de dichos aparatos que tengan instalados en esta municipalidad.\nCENTROS DE APUESTAS, APUESTAS REMOTAS, SALAS DE SORTEOS DE NÚMEROS Y/O\nCASINOS.\nIX.- Las máquinas de azar o con combinaciones de azar y destreza, con premios en efectivo o en especie que cuenten con autorización de la Secretaría de Gobernación, pagarán derechos de instalación o explotación conforme a la siguiente tabla:\na).- Apertura del establecimiento............ 2,646.00 veces\nb).- Expedición por primera vez de calcomanía por máquina y mesas de juego.............. 50.40 veces\nc).- Cambio de domicilio..................... 1,890.00 veces\nd).- Cambio de propietario................... 1,890.00 veces\ne).- Cambio de nombre comercial.............. 1,890.00 veces\nf).- Revalidación trimestral por máquina y mesas de juego........................... 31.50 veces\ng).- Incremento por aparato y mesa de juego.. 50.40 veces\nh).- Revalidación anual de licencia de operación/ocupación por establecimiento.\n1,008.00 veces\ni).- Aportación para programas preventivos para la ludopatía, trimestral por máquina por unidad de aparato similar y mesa de juego autorizado............................... 1.89 veces\nLudopatía una cuota de 500.00 UMAS.\nj).- Permiso de operación por horario ampliado, anual................................... 1,984.50 veces\nRespecto al inciso f), de la fracción IX del presente artículo, los derechos se causarán y deberán cubrirse trimestralmente, siendo la fecha de vencimiento el último día de cada trimestre.\nAsí mismo; la calcomanía correspondiente al ejercicio fiscal en curso, será renovada por la autoridad siempre y cuando el obligado se encuentre al corriente en el pago de los derechos causados conforme a este artículo.\n07 POR LA AUTORIZACIÓN DE LA INSTALACIÓN DE MÁQUINAS EXPENDEDORAS DE\nALIMENTOS, BEBIDAS, PRODUCTOS Y SIMILARES.\nARTÍCULO 25.- Para la apertura o inicio de actividades, cambio de domicilio o de propietario, la revalidación o el incremento de máquinas expendedoras de alimentos, bebidas, productos y similares, deberá derechos que se causen, conforme a la tabla siguiente:\nUNIDAD DE MEDIDA Y\nACTUALIZACIÓN VIGENTE\nI.- Máquinas consideradas consolas expendedoras:\na).- Apertura por aparato o incremento....... 13.23 veces\nb).- Para la revalidación anual de permiso... 6.61 veces\nc).- Cambio de domicilio..................... 26.46 veces\nd).- Cambio de propietario................... 26.46 veces\ne).- Expedición por primera vez de calcomanía por aparato............................. 3.96 veces\nII.- Módulos conformados por cabezales:\na).- Apertura o incremento por aparato....... 6.61 veces\nIII.- Para la revalidación anual del permiso:\na).- Los aparatos que estén conformados por módulo de 1 hasta 4 cabezales monederos. 1.99 veces\nb).- Los aparatos que estén conformados por módulo de 5 hasta 10 cabezales monederos 3.31 veces\nA partir de la onceava pagará cada uno.. 1.32 veces\nc).- Los aparatos considerados consola expendedora............................. 6.61 veces\nd).- Multa por no exhibir la calcomanía que expida la autoridad..................... 10.50 veces\nPara cambio de domicilio o de propietario, se aplicarán los incisos\nIV.- Requisitos:\nPara la autorización de las máquinas expendedoras de alimentos, bebidas, productos y similares, el solicitante deberá cumplir con los requisitos que a continuación se señalan:\n1.- Solicitud dirigida al Recaudador de Rentas Municipal.\n2.- Inscripción en el Registro Federal de contribuyentes.\n3.- Identificación oficial con fotografía del propietario, y en el identificación del representante legal.\n4.- Documento que acredite la legal propiedad o posesión de las máquinas, especificando la marca, modelo y serie.\n5.- Documento que acredite la legal estancia en el país en caso de que la máquina sea extranjera.\n6.- Fotografía de la máquina a registrar.\n7.- La anuencia del propietario del inmueble donde se instalará la máquina. realizarse a más tardar en el mes de abril de cada año. expendedoras de alimentos, bebidas, productos y similares, así como los propietarios y/o poseedores de los bienes inmuebles donde se instalen, serán solidariamente responsables del pago de los impuestos, derechos y/o multas que se originen con motivo de dichas máquinas que tengan instaladas en esta municipalidad.\n08 POR LA AUTORIZACIÓN PARA LA REALIZACIÓN DE EVENTOS, ESPECTÁCULOS\nPÚBLICOS Y DE DIVERSIÓN\nARTÍCULO 26.- Las personas físicas o morales que soliciten permisos para la realización de eventos, espectáculos públicos y de diversión deberán entregar la documentación necesaria, previo el pago de los derechos que se causen de acuerdo a la siguiente tarifa:\nUNIDAD DE MEDIDA Y\nACTUALIZACIÓN VIGENTE\nI.- Circos:\na).- Por semana.............................. 37.80 veces\nb).- Por día................................. 5.39 veces\nII.- Juegos mecánicos, por semana:\na).- Zona urbana............................. 37.80 veces\nb).- Zona Valle.............................. 31.50 veces\nIII.- Pasarelas, eventos de modelaje:\na).- Con fines de lucro...................... 31.75 veces\nb).- Sin fines de lucro...................... 13.23 veces\nIV.- Desfiles relativos a centros educativos por a sus actividades académicas.................... EXENTOS\nV.- Charreadas, Exposiciones, Ferias y otros\na).- Por semana.............................. 37.80 veces\nb).- Por día................................. 5.39 veces\nVI.- Funciones:\na).- Box o lucha libre\n1).- Con fines de lucro................. 34.39 veces\n2).- Sin fines de lucro................. 23.81 veces\nb).- Obras de teatro\n1).- Con fines de lucro................. 21.16 veces\n2).- Sin fines de lucro................. EXENTO\nc).- Circuito cerrado......................... 23.81 veces\nd).- Otros.................................... 13.23 veces\nVII.- Los propietarios de los lugares de alquiler para la realización de eventos:\na).- Fiestas o bailes en salones que se alquilen para tal fin, sin fines de lucro........... 6.61 veces\nb).- Fiestas o bailes en jardines de alquiler sin fines de lucro...................... 3.31 veces\nVIII.- Espectáculos masivos:\na).- Corrida de toros........................ 33.07 veces\nb).- Presentación de artistas, cantantes y otros 33.07 veces\nc).- Fiestas o bailes, sin fines de especulación 13.23 veces\nd).- Fiestas o bailes en salones que se alquilen para tal fin, sin fines de especulación.... 6.61 veces\ne).- Bailes populares........................ 33.07 veces\nf).- Carreras de vehículos................... 33.07 veces\ng).- Peleas de Gallos........................ 39.69 veces\n1).- Dictamen de no inconveniente...... 26.46 veces\nh).- Carrera de Caballos..................... 39.69 veces\n1).- Dictamen de no inconveniente...... 26.46 veces\ni).- Eventos Deportivos (Basquetbol, Softbol, Futbol y otros).\n1).- Por Temporada............ 37.80 veces\n2).- Por juego................ 13.23 veces\nj).- Otros................................... 15.87 veces\nk).- Multa por anunciarse o promocionarse sin permiso correspondiente................. 50.00 a\n500.00 veces\nl).- Será sancionado como responsable solidario la persona física o moral que permita la promoción de eventos y venta de entradas\n(boletos) al espectáculo o evento, sin contar con la autorización o permiso expedido por el Ayuntamiento.............. 50.00 a\n500.00 veces\nm).- La persona física o moral propietaria de las estructuras para la colocación de\nAnuncios Espectaculares o Carteleras, tendrá la obligación de solicitar el documento de la Autorización o Permiso que expida el Ayuntamiento al arrendatario, para la colocación de propaganda o publicidad, debido a que si el arrendador no cuenta con el documento de la\nAutorización o permiso que expidió el\nAyuntamiento, se hará acreedor a una sanción de............................... 50.00 a\n500.00 veces\nn).- Tratándose de espectáculos realizados por\nOrganismo no lucrativos que brinden servicios y asistencia médica de manera gratuita a enfermos que padezcan cáncer en etapa terminal, debidamente registrados ante institución oficial que para tales efectos señale la Ley de la materia....... EXENTO\nEl permiso deberá solicitarse 48 horas antes del evento, en caso contrario se cobrará el doble de la tarifa correspondiente.\n09 ESTABLECIMIENTOS PARA EVENTOS SOCIALES Y FIESTAS\nARTÍCULO 27.- Las personas físicas o morales que soliciten permiso para el funcionamiento de establecimientos para eventos sociales y fiestas, deberán entregar la documentación necesaria, para su análisis en la Secretaría del Ayuntamiento, previo al pago de derechos que se causen conforme a la siguiente tarifa:\nUNIDAD DE MEDIDA Y\nACTUALIZACIÓN VIGENTE\nI.- Inspección de Factibilidad..................... 26.46 veces\nII.- Apertura\nEn zona habitacional:\na).- Establecimiento abierto con horario de\n11:00 horas a 22:00 horas................ 85.99 veces\nb).- Establecimiento mixto con horario de\n11:00 horas a 24:00 horas................ 171.99 veces\nc).- Establecimiento cerrado con horario de\n11:00 horas a 24:00 horas................ 343.98 veces\nEn zona comercial:\na).- Establecimiento abierto con horario de\n11:00 horas a 2:00 horas................. 171.99 veces\nb).- Establecimiento mixto con horario de\n11:00 horas a 2:00 horas................. 264.60 veces\nc).- Establecimiento cerrado con horario de\n11:00 horas a 2:00 horas................. 529.20 veces\nd).- Multa por operar sin el permiso 50.00 a correspondiente.......................... 250.00 veces\nUNIDAD DE MEDIDA Y\nACTUALIZACIÓN VIGENTE\nZONA ZONA\nHABITACIONAL COMERCIAL\nIII.- Cambio de propietario............ 52.92 veces 66.15 veces\nIV.- Cambio de nombre comercial....... 26.46 veces 39.69 veces\nV.- La revalidación anual del permiso, deberá realizarse a más tardar en el mes de marzo de cada año, de acuerdo con la siguiente tarifa:\nZona Habitacional:\na).- Establecimiento abierto con horario de\n11:00 horas a 22:00 horas................ 46.30 veces\nb).- Establecimiento mixto con horario de\n11:00 horas a 24:00 horas................ 85.99 veces\nc).- Establecimiento cerrado con horario de\n11:00 horas a 24:00 horas................ 171.99 veces\nEn zona comercial:\na).- Establecimiento abierto con horario de\n11:00 horas a 2:00 horas................. 85.99 veces\nb).- Establecimiento mixto con horario de\n11:00 horas a 2:00 horas................. 132.30 veces\nc).- Establecimiento cerrado con horario de\n11:00 horas a 2:00 horas................. 264.60 veces\nPara la revalidación anual del permiso el permisionario deberá entregar la documentación necesaria y el no adeudo municipal, además se les impondrá una sanción económica de 10 a 75 veces la Unidad de Medida y\nActualización vigente, a quienes no revaliden sus permisos en forma oportuna o quiénes lo hagan fuera de los plazos establecidos conforme a esta Ley.\nVI.- Expedición de certificado de los permisos para exhibición en el establecimiento.............. 4.00 veces\nVII.- Expedición de certificado de los permisos por robo, destrucción o extravío.................. 20.00 veces\n10 ESTACIONAMIENTO DE VEHÍCULOS EN LA VÍA PÚBLICA Y\nESTACIONAMIENTOS PÚBLICOS\nARTÍCULO 28.- Las personas físicas o morales que ocupen la vía pública con vehículos, pagarán derechos por el uso de la misma conforme a lo siguiente:\nI.- Con señalamiento de cordones de color amarillo, para sitio exclusivo de estacionamiento de vehículos, dentro de los primeros veinte días de cada mes, por metro lineal diariamente:\nUNIDAD DE MEDIDA Y\nACTUALIZACIÓN VIGENTE\nPRIMERA Y OTRAS ZONAS\nSEGUNDA COMERCIALES\nSECCIÓN,\nCENTRO CÍVICO\na).- Batería.................... 0.16 veces 0.10 veces\nb).- Cordón..................... 0.075 veces 0.05 veces\nc).- Zonas exclusivas de taxis, por vehículo, una cuota de\n7.50 veces la Unidad de Medida y Actualización vigente por mes.\nd).- Zonas exclusivas de taxis en las Delegaciones Municipales del Valle de Mexicali, por vehículo, una cuota de 3.70 veces la Unidad de Medida y Actualización vigente por mes.\nEl estacionamiento en cordón amarillo no podrá ser utilizado para otra actividad diferente al uso exclusivo de estacionamiento sin obtener ningún lucro de ello, lo contrario resultaría en la cancelación del permiso, independientemente de las sanciones correspondientes.\nII.- Por el derecho de estacionarse en uso exclusivo para personas con discapacidad, quedará EXENTO.\nPara otorgarse la identificación necesaria para el uso de estos estacionamientos, se estará al procedimiento que establece el\nReglamento respectivo.\nIII.- Por el servicio de estacionamiento en la vía pública en los lugares, en donde se hayan instalado dispositivos para el control de estacionamiento en la vía pública, la tarifa será la siguiente:\nA).- Por cada 15 minutos o fracción de quince minutos la cantidad de 0.0334 veces.\nB).- Los domingos y días festivos de descanso obligatorio que marca la Ley Federal del Trabajo, el estacionamiento será gratuito.\nC).- Dentro del horario de 20:01 a 7:59 horas del día siguiente, el estacionamiento será gratuito. pública, dentro del perímetro controlado por parquímetros o dispositivos de control de estacionamiento en la vía pública, acuerdo con la normatividad vigente y aplicable:\nUNIDAD DE MEDIDA Y\nACTUALIZACIÓN VIGENTE\na).- Particulares, por cajón para un vehículo, anual...................................... 487.00 veces\nb).- Comercial para realizar maniobras de carga y descarga, por cajón para un vehículo, anual. 487.00 veces\nc).- Autorización para ocupar la vía pública como terminal para el servicio de transporte público de carga o pasajeros, por cajón para un vehículo, anual......................... 487.00 veces\nEstán exentos del pago de los derechos por estacionamiento en la vía pública en las zonas que se encuentren controladas por dispositivos electrónicos identificados como parquímetros, las personas avecinadas o residentes del lugar de ubicación de los citados dispositivos, siempre y cuando hayan cumplido con los requisitos que para efecto establece el Reglamento de\nEstacionamientos del Municipio de Mexicali, Baja California.\nIV.- Por el estacionamiento de vehículos en zonas de tiempo limitado y no reguladas por equipos o terminales de control de estacionamiento colocados en la vía pública, comúnmente denominados parquímetros:\na).- Por el derecho de estacionarse en zonas de tiempo limitado, hasta por un máximo de dos horas consecutivas, para vehículos con placas nacionales, fronterizas y extranjeras, una cuota de 1.25 veces la Unidad de Medida y Actualización vigente por año.\nEl pago del derecho antes referido es obligatorio, para todo propietario por cada vehículo de su propiedad, excepto tratándose de personas con discapacidad, únicamente por un solo vehículo de su propiedad, y siempre y cuando demuestren que hayan cubierto la cuota anual para estacionamiento exclusivo para personas con discapacidad.\nUNIDAD DE MEDIDA Y\nACTUALIZACIÓN VIGENTE\n- Por infracción al excederse de dos horas consecutivas, si se liquida dentro de los 5 días siguientes........................................ 0.53 veces\nUnidad de\nMedida y\nActualización vigente.\n- Por infracción al excederse de dos horas consecutivas si se liquida después de los 5 días siguientes........................................ 1.05 veces\nUnidad de\nMedida y\nActualización vigente.\nb).- Las personas cuyos vehículos estén contemplados en el\nInciso anterior, podrán obtener calcomanías o en su caso, comprobantes de pago, por el derecho de estacionarse por más de dos horas y sin límite de tiempo, para vehículos con placas nacionales y fronterizas, con una cuota de\n12.60 veces la Unidad de Medida y Actualización vigente por año o proporcionalmente al número de meses pendientes de transcurrir desde la fecha en que se solicite el servicio.\nEl entero de los derechos a que se refiere ésta fracción, tendrá como los derechos por expedición de placas y tarjeta de circulación, conforme a las Leyes y disposiciones relativas que correspondan, en los módulos que al efecto instale el Ayuntamiento.\nV.- Estacionamientos Públicos. meses del año:\nPor permiso anual:\nUNIDAD DE MEDIDA Y\nACTUALIZACIÓN VIGENTE\na).- De 1 a 40 cajones de estacionamiento... 69.45 veces\nb).- De 41 a 100 cajones de estacionamiento... 116.68 veces\nc).- De 101 a 180 cajones de estacionamiento... 166.69 veces\nd).- De 181 a 280 cajones de estacionamiento... 216.97 veces\ne).- De 281 a 400 cajones de estacionamiento... 265.92 veces\nf).- De más a 400 cajones de estacionamiento... 317.52 veces\nPor las sanciones a este artículo, incluyendo a aquellos que señalen un espacio como estacionamiento exclusivo, sin contar con la autorización respectiva, se causará una sanción económica de 40 veces la Unidad de Medida y Actualización Vigente; si se liquida dentro de los quince días siguientes de haberse causado la infracción, gozará de un 50% de descuento.\n11 SERVICIOS QUE PRESTA OFICIALÍA MAYOR\nARTÍCULO 29.- Por los servicios que preste Oficialía Mayor en cuanto a la regularización de bienes inmuebles y/o de terrenos excedentes de la vía pública, se pagará conforme a lo siguiente:\nUNIDAD DE MEDIDA Y\nACTUALIZACIÓN VIGENTE\nI.- Por atención, análisis, integración y determinación de expediente que contiene la petición de venta de él o los excedentes y/o él o los terrenos de la vía pública a regular...... 18.90 veces\nII.- Por expedición de Contrato de compraventa de bienes inmuebles y/o terrenos excedentes de la vía pública.................................... 25.20 veces\nARTÍCULO 30.- Los derechos por el Servicio del Departamento de\nDepósitos Vehiculares, deberán cubrirse de acuerdo con las siguientes tarifas:\nI.- MANIOBRAS DE SALVAMENTO:\nLos derechos por maniobras de salvamento, deberán cubrirse de acuerdo con la siguiente tarifa:\nUNIDAD DE MEDIDA Y\nACTUALIZACIÓN VIGENTE\na).- Automóviles, Pick Up y Camionetas......... 5.23 veces\nb).- Camiones Urbanos de Pasajeros............. 16.25 veces\nc).- Autobuses de Pasajeros.................... 18.88 veces\nd).- Camiones de Carga......................... 21.50 veces\ne).- Tractocamiones............................ 24.13 veces\nf).- Remolques................................. 24.13 veces\ng).- Tractocamiones con Remolque............... 29.38 veces\nh).- Motocicletas.............................. 1.03 veces\nPara efectos de este artículo se entiende por maniobras de salvamento al conjunto en general de maniobras mecánicas necesarias para el rescate de vehículos imposibilitados para circular, hasta dejarlos en condiciones de arrastre o traslado, como es el caso de vehículos mal estacionados, volcados, accidentados fuera de la carpeta asfáltica, dentro de un canal o barranco, entre otros.\nPor lo que se cobrará una sola cuota por vehículo.\nII.- ARRASTRE DE VEHÍCULOS:\nLos derechos por el arrastre de vehículos deberán cubrirse de acuerdo con la siguiente tarifa:\nUNIDAD DE MEDIDA Y\nACTUALIZACIÓN VIGENTE\na).- Automóviles, Pick Up y Camionetas......... 10.40 veces\nb).- Camiones Urbanos de Pasajeros............. 17.80 veces\nc).- Autobuses de Pasajeros.................... 24.10 veces\nd).- Camiones de Carga:\nSin carga................................. 30.40 veces\nCon carga................................. 37.75 veces\ne).- Tractocamiones sin Remolque............... 35.65 veces\nf).- Remolques................................. 35.65 veces\ng).- Tractocamiones con Remolque............... 62.95 veces\nh).- Motocicletas.............................. 7.30 veces\ni).- Bicicletas................................ 1.55 veces población, se incrementará en 0.25 veces la Unidad de Medida y\nActualización vigente por kilómetro recorrido.\nIII.- SERVICIOS A DOMICILIO: con la tarifa de arrastre y maniobras de salvamento.\nIV.- MANIOBRAS INCONCLUSAS DE GRÚA:\nNo se pagarán los derechos por servicios de salvamento, arrastre y almacenaje en caso de maniobras inconclusas de grúa, cualquiera que sea la causa, de los siguientes vehículos: automóviles, camionetas, pick up, camiones de pasajeros (microbús), remolques (trailers) y autobuses de pasajeros, remolque de tractocamiones de tres o más cajas.\nV.- ALMACENAJE DE VEHÍCULOS\na).- Derechos:\nLos derechos por almacenaje de vehículos causarán, después de las primeras 24 horas una cuota de:\nPor cada 24 horas o fracción:\nUNIDAD DE MEDIDA Y\nACTUALIZACIÓN VIGENTE\n1).- Automóviles, Pick Up y Camionetas......... 0.58 veces\n2).- Camiones Urbanos de Pasajeros............. 1.32 veces\n3).- Autobuses de Pasajeros.................... 1.32 veces\n4).- Camiones de Carga......................... 1.32 veces\n5).- Tractocamiones............................ 1.32 veces\n6).- Remolques (trailers)...................... 1.32 veces\n7).- Tractocamiones con Remolque............... 1.84 veces\n8).- Motocicletas.............................. 0.45 veces\n9).- B icicletas................................ 0.14 veces\n10).- Otros..................................... 0.79 veces\nb).- Exención: oficiales de Autoridad Competente, se exentará del pago de los derechos de maniobras de salvamento, arrastre y almacenaje de vehículos, siempre y cuando el robo sea reportado dentro de las primeras 72 horas subsecuentes al hecho.\nc).- Generalidades:\nPara la Zona Rural, se reducirá el 50% de las tarifas previstas por este artículo, con excepción de los servicios que se presten en las\nDelegaciones de González Ortega y Progreso.\nd).- Tiempo:\nTratándose de vehículos retenidos por concepto de infracción, se le concederá al infractor un plazo de veinticuatro horas para que retire su vehículo sin cobro por los servicios de traslado y resguardo, desde su presentación ante el juez calificador para que realice las gestiones necesarias para cubrir la o las multas.\n12 SERVICIOS QUE PRESTA EL DEPARTAMENTO DE SERVICIOS MÉDICOS\nMUNICIPALES\nARTÍCULO 31.- Los servicios proporcionados por Servicios Médicos\nMunicipales, se pagarán de acuerdo a la siguiente tarifa:\nUNIDAD DE MEDIDA Y\nACTUALIZACIÓN VIGENTE\nI.- Expedición de certificados prenupciales........ 3.31 veces\nII.- Consultas médicas............. de 0.00 veces a 2.64 veces\nEl rango se aplicará de acuerdo con estudio socioeconómico.\nIII.- Servicios en el Centro de Atención de Enfermedades de\nTransmisión Sexual (C.A.E.T.S).\na).- Servicios o procedimientos de consulta vigente.................................. EXENTO\nb).- Servicios o procedimientos de consulta vencida.................................. 1.32 veces un 50% a aquellas personas que acrediten su insolvencia económica en el estudio socioeconómico que se les practique.\nIV.- Expedición de tarjeta de salud:\na).- Primera vez.............................. EXENTO\nb).- Reposición por extravío, mutilación o daño a la tarjeta........................ 1.85 veces\nV.- Credencial de identificación para personas con discapacidad............................... EXENTO\nVI.- Expedición de tarjetón para uso de estacionamiento en personas con discapacidad temporal...................................... EXENTO\nVII.- Expedición de tarjetón para uso de estacionamiento en personas con discapacidad permanente.................................... E XENTO\nVIII.- Por reposición por extravío, mutilación o daño al tarjetón para uso de estacionamiento en personas con discapacidad..................... 1. 0 0 vez\nIX.- Certificado de Esencia Psicofisiológica médico legal......................................... 3.31 veces\nNo se causará este derecho, cuando el certificado sea expedido en favor de alguna persona que hubiere sido detenida y puesta a disposición de la autoridad competente, en los casos en que de Tránsito Municipal y/o Bando de Policía y Gobierno del\nMunicipio de Mexicali.\nX.- Certificado de Esencia Psicofisiológica médico legal con aplicación de alcoholímetro E/E...... 6.61 veces\nXI.- Servicio de ambulancia en zona urbana por solicitud particular.......................... 15.87 veces\nXII.- Servicio de ambulancia en eventos particulares por hora...................................... 13.23 veces\nXIII.- Certificado de discapacidad................... EXENTO\nXIV.- Certificado de salud......................... 1.32 veces\nXV.- Otros servicios médicos...................... 3.31 a\n13.23 veces\nXVI.- Atención Médica:\na).- Atención de heridas sin sutura.......... 1.32 veces\nb).- Atención de Heridas sin sutura de hasta\n3cms................................... 3.96 veces\nc).- Herida-Sutura de 3.1 a 10 cms........... 10.58 veces\nd).- Electrofulguración de verrugas vulgares. 7.28 veces\ne).- Electrofulguración de condilomas........ 8.60 veces\nf).- Electrofulguración de úlceras cervicales 11.25 veces\nXVII.- Multa del módulo.............................. 5.00 veces\nARTÍCULO 32.- Los servicios proporcionados por el Centro Municipal de\nControl Animal, se pagarán de acuerdo a la siguiente tarifa:\nI.- Servicios:\nUNIDAD DE MEDIDA Y\nACTUALIZACIÓN VIGENTE\na).- Consulta................................. 1.99 veces\nb).- Esterilización quirúrgica................ 3.96 veces\nc).- Campaña de esterilización quirúrgica..... EXENTO\nHasta dos veces por año.\nd).- Desahucio Humanitario.................... 2.77 veces\ne).- Desparasitado............................ 1.99 veces\nf).- Vacuna contra el moquillo................ 3.31 veces\ng).- Enucleación.............................. 10.58 veces\nh).- Reparación de hernias.................... 6.61 veces\ni).- Reparación de heridas.................... 4.63 veces\nj).- Prolapso Vaginal......................... 10.58 veces\nk).- Mastectomía.............................. 8.60 veces\nl).- Emisión de microprocesador de identificación de mascota................ 5.29 veces\nSe exentará el pago, solo aquellos microprocesadores de identificación de mascota que se hayan adquirido a través de organizaciones auxiliares legalmente constituidos.\nm).- Emisión placa de identificación.......... 3.31 veces\nn).- Servicio de cremación para perros........ 1.32 veces\nII.- Se pagarán las siguientes cuotas de acuerdo a la captura y posterior devolución del animal, adicionales a las cuotas de los servicios que se hubieren requerido por el animal o que exija el Reglamento respectivo.\nUNIDAD DE MEDIDA Y\nACTUALIZACIÓN VIGENTE\na).- Captura (Devolución)..................... 4.80 veces\nSe otorgará el 50% de descuento en el pago de este derecho:\n1.- A aquellas personas que no sean reincidentes y acrediten cuenten con las vacunas.\n2.- Cuando la devolución se realice para la adopción de la mascota.\n3.- Donación por Asociación Protectora de Animales. legalmente constituido cuando:\n1.- Le sea entregado un animal con la finalidad de que se le encuentre un hogar definitivo.\n2.- Se tenga convenio vigente con Servicios Médicos\nMunicipales.\n3.- No se le haya prestado ningún servicio de los mencionados en la fracción I del presente artículo.\n13 SERVICIOS QUE PRESTA LA DIRECCIÓN DE SEGURIDAD PÚBLICA MUNICIPAL\nARTÍCULO 33.- Los derechos por servicios que se soliciten a la\nDirección de Seguridad Pública se cobrarán:\nUNIDAD DE MEDIDA Y\nACTUALIZACIÓN VIGENTE\nI.- Por servicio permanente de vigilancia policíaca, por elemento por turno de ocho horas, al solicitarse el servicio............. 17.01 veces\nSe entenderá por servicio permanente de vigilancia policíaca cuando se contrate por un término igual o mayor a seis meses de manera continua, para lo cual se deberá celebrar un contrato entre el Municipio y el solicitante, donde se establezcan los derechos y obligaciones para ambas partes, así mismo el pago de las bonificaciones en faltas, como retardos de los elementos, tendrá que ser dentro de los primeros seis meses en que ocurrieron las faltas.\nII.- Por servicio eventual de vigilancia policíaca, por elemento por turno de ocho horas al solicitarse el servicio por organismos paramunicipales............................... 13.23 veces\nIII.- Por servicio eventual de vigilancia policíaca, por elemento por turno de ocho horas al solicitarse el servicio....................... 26.46 veces discontinua, con total independencia del evento que se trate.\nIV.- Por servicio en apoyo en cortejos fúnebres, por elemento.................................. 7.28 veces\nV.- Por impartición de curso de manejo por persona. 13.23 veces\nVI.- Por ratificación de peritajes de accidentes de tránsito...................................... 2.64 veces\nVII.- Las personas físicas o morales que se dediquen a la instalación de alarmas comerciales e industriales, así como a los servicios de la opinión de la Dirección de Seguridad\nPública Municipal debiendo cubrir las siguientes tarifas:\na).- Por la opinión para la apertura o inicio de actividades.......................... 132.30 veces\nb).- Por revalidación anual.................. 66.15 veces\nLa expedición o revalidación del documento a que se refiere esta fracción, se establece para las empresas que inicien actividades o ya estén operando, y deberán solicitarse a más tardar en el mes de marzo de cada año.\nVIII.- Por revisión física mecánica anual:\na).- Automóviles particulares por unidad...... EXENTO\nb).- Por el incumplimiento a la revisión mecánica a cargo de particulares......... 4.20 veces\nARTÍCULO 34.- Los derechos por alimentación de detenidos estén o no a disposición de la autoridad investigadora o judicial local o federal, que hayan ingresado a separos, por la comisión de algún ilícito o estén compurgando una sanción administrativa, impuesta por el Juez\nCalificador, se pagarán 1.89 veces la Unidad de Medida y Actualización vigente en la entidad por día. Siempre y cuando se proporcione la alimentación antes mencionada.\nARTÍCULO 35.- Los derechos por traslado de detenidos a disposición de otras autoridades sean federales o estatales, y lo requieran para la práctica de diligencias ordenadas conforme a las leyes, serán los siguientes:\nUNIDAD DE MEDIDA Y\nACTUALIZACIÓN VIGENTE\nI.- Cuando el traslado se realice dentro de la misma mancha urbana de la Ciudad, se pagará por detenido.................................. 5.29 veces\nII.- Cuando el traslado se realice de la Ciudad a cualquier Delegación Municipal del Valle de\nMexicali B.C., o del Valle a la Ciudad, se pagarán por detenido....................... 1 5. 87 veces\nARTÍCULO 36.- La entrega de citatorios y notificaciones que expida cualquier autoridad para ser entregadas a las personas dentro de la municipalidad, así como la localización, búsqueda de personas y apoyo en diligencias, que soliciten las autoridades diversas de las municipales, causarán los siguientes derechos:\nUNIDAD DE MEDIDA Y\nACTUALIZACIÓN VIGENTE\nI.- La entrega de citatorios y diversas notificaciones que se realicen dentro de la mancha urbana de la Ciudad se pagarán......... 2.64 veces\nII.- La entrega de citatorios y diversas notificaciones que se realicen fuera de la mancha urbana de la Ciudad se pagarán......... 5.29 veces\nIII.- La búsqueda o localización de personas y/o domicilios se pagará, por quien lo solicite.. 5.29 veces\nIV.- Apoyo en diligencias ordenadas por autoridad judicial, administrativa o laboral por elemento diario............................... 3.96 veces\n14 SERVICIOS QUE PRESTA LA DIRECCIÓN DEL HEROICO CUERPO DE\nBOMBEROS\nARTÍCULO 37.- Los servicios que presta la Dirección del Heroico Cuerpo sectores públicos y privados, se causarán conforme a la siguiente tarifa:\nA.- PROYECTOS DE CONSTRUCCIÓN\nI.- Revisión y autorización de sistemas contra incendios y dispositivos de seguridad en proyectos de construcción:\nUNIDAD DE MEDIDA Y\nACTUALIZACIÓN VIGENTE\nCONSTRUCCIÓN REGULARIZACIÓN\na).- Casa-habitación por m² de construcción................. 0.063 veces 0.075 veces\nb).- Comercial por m² de construcción................. 0.10 veces 0.11 veces\nc).- Industrial, naves de inventario, almacenes, bodegas por m² de construcción........ 0.26 veces 0.40 veces\nd).- Administrativo/Oficinas por m² de construcción.............. 0.13 veces 0.16 veces\ne).- Giro mercantil tales como: bancos, casas de empeño y/o giros similares, por m2 de construcción................. 0.16 veces 0.18 veces\nf).- Clínicas, hospitales, laboratorios y/o giros similares, por m2 de construcción................. 0.11 veces 0.12 veces\ng).- Estaciones de servicio, estaciones de carburación, estaciones de autoconsumo y/o giros similares, por giro.... 264.60 veces 396.90 veces\nh).- Estacionamientos por m2 de terreno................... 0.088 veces 0.10 veces\ni).- Instalaciones: Estaciones y\nSub-Estaciones eléctricas, torres y antenas de telefonía, carteleras y espectaculares, antenas de radio y/o giros similares, por giro.......... 198.45 veces 211.68 veces\nj).- Barda, fachada y remodelaciones por m2 de construcción:\nCasa-Habitación.............. 0.025 veces 0.037 veces\nComercial.................... 0.063 veces 0.075 veces\nMercantil.................... 0.11 veces 0.13 veces\nIndustrial................... 0.13 veces 0.16 veces\nk).- Las microempresas por m² que ingresen por trámite S.A.R.E\n(Sistema de Apertura Rápida de\nEmpresas) de hasta 100 m²..... 13.23 veces\nII.- Por la asesoría de anteproyectos de sistemas contra incendios y dispositivos de seguridad.\na).- Proyecto Comercial........................ 13.23 veces\nb).- Proyecto Industrial....................... 13.23 veces\nB.- INSPECCIÓN DE DISPOSITIVOS DE SEGURIDAD EN EDIFICIOS EXISTENTES,\nI.- Establecimientos en general no especificados en otros rubros de hasta de 30 m² de superficie. 2.64 veces\nII.- Giro de servicio como: estéticas, estacionamientos, autolavado, lavanderías, planchadurías, peluquerías, consultorios, sastrerías, renta de internet, clínicas, hospitales, sanatorios, bancos, casas de cambio, oficinas administrativas, salas de entretenimiento, como salas cinematográficas, salas de teatro y demás giros similares por m2:\na).- Hasta 80 m2.............................. 5.29 veces\nb).- De 81 hasta 150 m2........................ 10.58 veces\nc).- De 151 a 300 m2........................... 19.84 veces\nd).- De 301 a 500 m2........................... 31.74 veces\ne).- De 501 a 1,000 m2......................... 52.92 veces\nf).- De 1,001 m2 en adelante.................... 105.84 veces\nIII.- Giros de reunión pública como templos, salones religiosos y giros similares........... 10.58 veces\nIV.- Salones y parques para fiestas/eventos (hasta con 1 alberca)................................ 19.84 veces\nV.- Giros comerciales como:\nAbarrotes, mercados, supermercados, tortillerías, centros comerciales, venta de autos, refaccionarias, librerías, dulcerías y demás establecimientos dedicados a la compra-venta de artículos por m² de construcción:\na).- Hasta 50 m²................................ 5.29 veces\nb).- De 51 a 100 m²............................. 10.58 veces\nc).- De 101 a 200 m²............................ 15.87 veces\nd).- De 201 a 300 m²............................ 21.16 veces\ne).- De 301 a 400 m²............................ 31.74 veces\nf).- De 401 a 500 m²............................ 39.69 veces\ng).- De 501 a 1,000 m².......................... 52.92 veces\nh).- De 1,001 a 2,000 m²........................ 66.15 veces\ni).- De 2,001 a 3,000 m²........................ 92.61 veces\nj).- De 3,001 m² en adelante.................... 105.84 veces\nTiendas de autoservicio, expendios, licorerías y giros similares por cada sucursal............. 39.66 veces\nVI.- Restaurante, Restaurante Bar, Cantinas, Bar, Video-Bar, Karaoke, Café Cantante, Bar Terraza, Discotecas y giros similares:\na).- Hasta 50 m²................................ 10.58 veces\nb).- De 51 hasta 150 m²......................... 33.07 veces\nc).- De 151 a 500 m²............................ 52.92 veces\nd).- De 501 m² en adelante...................... 105.84 veces\nVII.- Tiendas departamentales, Centros de Espectáculos, Centros/Parques recreativos con dos o más albercas, Clubes Deportivos por giro............ 105.84 veces\na).- Revisión de alberca....................... 13.23 veces\nVIII. Moteles:\na).- Hasta 10 habitaciones...................... 19.84 veces\nb).- De 11 a 20 habitaciones.................... 26.46 veces\nc).- De 21 habitaciones en adelante............. 33.07 veces\nd).- Moteles con alberca, adicional al pago correspondiente por el número de habitaciones............................... 19.84 veces\nIX.- Hoteles:\na).- Hasta 30 habitaciones...................... 39.69 veces\nb).- De 31 habitaciones en adelante............. 52.92 veces\nc).- De tres niveles o más...................... 105.84 veces\nd).- Hoteles con alberca, adicional al pago correspondiente por el número de habitaciones............................... 26.46 veces\nX.- Edificios Educativos Públicos................... 2.64 veces\nXI.- Edificios Educativos Privados / Estancias\nInfantiles/Asilos, Centros de asistencia social y giros similares:\na).- Hasta 10 aulas............................. 18.52 veces\nb).- De 11 aulas en adelante.................... 33.07 veces\nXII.- En empresas dedicadas al reciclaje en general, tarimeras y centros de transferencia............. 6 6.15 veces\nXIII. Chatarreras, en empresas dedicadas a la desmantelación de vehículos (Yonkes)............ 26.46 veces\nXIV.- Otros giros no especificados.................... 13.23 veces\nXV.- Verificaciones a solicitud:\na).- Establecimientos de hasta 300 m²........... 2.64 veces\nb).- Establecimientos de 301 m² hasta 500 m².... 5.28 veces\nc).- Establecimientos de 501 m² hasta 1000 m²... 8.92 veces\nd).- Establecimientos de 1001 m² hasta 2000 m².. 11.56 veces\ne).- De 2001 m² en adelante..................... 1 4. 2 0 veces\nEDIFICIOS INDUSTRIALES/ALMACENES:\nXVI.- Industria/almacenes/bodegas/naves de inventario/ empacadoras:\na).- Hasta 1,000 m²............................ 33.07 veces\nb).- De 1,001 m² hasta 2,000 m²................. 66.15 veces\nc).- De 2,001 hasta 4,500 m².................... 132.30 veces\nd).- De 4,501 m² hasta 10,000 m²................ 330.75 veces\ne).- De 10,001 m² en adelante.................. 396.90 veces\nGIROS DE ALTO RIESGO:\nXVII. Industria generadora de electricidad, distribuidoras de gases comprimidos y criogénicos, combustibles y lubricantes, oxígenos y acetilenos, polvorines, plantas de almacenamiento de gas, licuado de petróleo y natural licuado y depósitos de combustibles y lubricantes y demás establecimientos de alto riesgo.......................................... 264.60 veces\nXVIII Estación de distribución de Gas L.P. u otros gases licuados. (Almacenamiento de hasta 10,000 litros)......................................... 132.30 veces\nXIX.- Planta de distribución de Gas L.P. u otros gases licuados (Almacenamiento hasta 5,000 litros).... 66.15 veces\nXX.- Estaciones de gasolina/estaciones de autoconsumo\n(Hasta 4 dispensarios).......................... 6 6.15 veces\nXXI.- Estaciones de gasolina/estaciones de autoconsumo\n(Mayor de 4 dispensarios)....................... 132.30 veces\nCENTROS DE APUESTAS, APUESTAS REMOTAS, SALAS DE SORTEOS DE NÚMEROS Y/O\nCASINOS.\nXXII. Inspección anual................................ 264.60 veces\nXXIII Dictamen de operación/permiso de ocupación....... 264.60 veces del Heroico Cuerpo de Bomberos a que se refiere este apartado, sólo dará lugar al cobro de derechos, tratándose de la primera inspección, específico, en el caso de incumplimiento de los dispositivos de seguridad correspondientes.\nC.- ANÁLISIS DE FACTIBILIDAD PARA LA PRESTACIÓN DE SERVICIOS DE\nBOMBEROS EN PROYECTOS DE DESARROLLOS URBANOS:\nI.- Desarrollo habitacional:\na).- Hasta 5,000 m²............................. 66.15 veces\nb).- Mayor de 5,001 m².......................... 132.30 veces\nII.- Desarrollo industrial y comercial............... 132.30 veces\nIII.- Cambio de régimen de propiedad, cambio de razón social.......................................... 26.46 veces\nD.- CERTIFICACIÓN DE DAÑOS EN BIENES SINIESTRADOS:\nI.- Casa habitación................................. 13.23 veces\nII.- Comercio........................................ 66.15 veces\nIII.- Industria....................................... 132.30 veces\nIV.- Agrícola........................................ 66.15 veces\nV.- Vehículos particulares.......................... 6.61 veces\nVI.- Vehículos comerciales........................... 13.23 veces\nQuedan exceptuados del pago de este derecho, aquellas casas habitación que no se encuentren aseguradas al ocurrir el siniestro.\nE.- EXPEDICIÓN DE CERTIFICACIÓN DE EQUIPO Y DISPOSITIVOS DE\nSEGURIDAD:\nI.- Vivienda........................................ 3.96 veces\nII.- Comercio y de servicios......................... 13.23 veces\nIII.- Industria....................................... 19.84 veces\nIV.- Certificación de sistemas hidráulicos contra incendios/Sistemas de detección de incendios\n/iluminación y demás sistemas de conformidad con el Reglamento de prevención de incendios, para el Municipio de Mexicali........................ 66.15 veces\nV.- Comercios dedicados a la venta, renta y mantenimiento de extintores, empresas dedicadas a la venta de sistemas contra incendio......... 6 6.15 veces\nF.- REVISIÓN DE LAS CONDICIONES DE SEGURIDAD EN LAS INSTALACIONES\nTEMPORALES:\nI.- Circos......................................... 26.46 veces\nII.- Juegos mecánicos por aparato mecánico revisado 1.32 veces\nIII.- Exposiciones, ferias, kermeses y otros no especificados.................................. 13.23 veces\nIV.- Bailes populares............................... 39.69 veces\nV.- Eventos masivos de más de 1,000 personas....... 52.92 veces\nVI.- Eventos deportivos y culturales................ 19.84 veces\nG.- SERVICIOS ESPECIALES:\nCURSO:\nI.- Cursos de orientación en caso de sismo, incendios, evacuación de inmuebles............. 13.23 veces\nII.- Formación de brigadas y combate a incendios.... 39.66 veces\nIII.- Primeros auxilios.............................. 39.66 veces\nIV.- Manejo de extintores........................... 21.16 veces\nV.- Uso y manejo de mangueras contra incendios..... 66.15 veces\nVI.- Supervisión de simulacros...................... 13.23 veces\nVII.- Prevención de incendios........................1 39.69 veces\nVIII. Bombero infantil............................... 13.23 veces\nIX.- Rescate acuático (guardavidas)................. 66.15 veces\nX.- Soporte vital básico (resucitación cardiopulmonar con el uso del desfibrilador externo automático). 66.15 veces\nXI.- Materiales peligrosos nivel reconocimiento..... 66.15 veces\nXII.- Seguridad en alturas............................ 66.15 veces\nXIII.- Seguridad en espacios confinados................ 66.15 veces\nXIV.- Otros cursos no especificados................... 13.23 veces\nQuedan exentas del cobro del numeral G de este artículo, asociaciones sin fines de lucro.\nUSO DE EQUIPO POR EVENTO:\nXV.- Máquina extinguidora por hora................... 1 4.18 veces\nXVI.- Máquina de iluminación........................... 9.92 veces\nXVII.- Máquina escala por hora.......................... 9.92 veces\nXVIII. Ambulancia en caso de eventos deportivos o sociales....................................... 25.20 veces\nXIX.- Por servicios de supervisión contratados para cubrir eventos públicos o privados, por bombero 6.61 veces\nREVISIÓN DE EXPLOSIVOS:\nXX.- Revisión de polvorines o permisos de explosivos 1 3 2.30 veces\nXXI.- Centros de distribución al menudeo............. 132.30 veces\nXII.- Revisión de castillos pirotécnicos............. 13.23 veces\nH.- REVISIÓN DE DOCUMENTACIÓN.\nI.- Revisión de Plan de contingencias contra incendios hasta en 2 ocasiones................. 42.00 veces\nII.- Reingreso a revisión por tercera ocasión....... 21.00 veces\nIII. Análisis de riesgos............................ 26.46 veces\nIV.- Expedición de oficio de terminación de obra.... 13.23 veces\nV.- Certificado de ocupación máxima................ 13.23 veces\nVI.- Por solicitud por cada prórroga............... 5.29 veces\nI.- TRÁMITES INGRESADOS POR EL SISTEMA DE APERTURA RÁPIDA DE\nEMPRESAS (SARE).\nI.- Por concepto de Inspección certificación....... 19.84 veces\nLos servicios a que hace referencia este artículo, cuando se trate de escuelas públicas de nivel básico, quedaran exentas de pago.\n15 SERVICIOS QUE PRESTA EL DEPARTAMENTO DE CONTROL URBANO\nARTÍCULO 38.- Los servicios que presta esta oficina, por Licencias de\nConstrucción se pagarán conforme a lo siguiente:\nI.- REVISIÓN DE SOLICITUDES Y EXPEDICIÓN DE LICENCIAS DE EDIFICACIÓN,\nAMPLIACIÓN, REMODELACIÓN, DEMOLICIÓN DE INMUEBLES,\nINSTALACIONES, ANUNCIOS Y OTROS permisos o licencias, deberán ser cubiertos por los solicitantes, de acuerdo con la siguiente tarifa:\nPara construcción, reconstrucción, ampliación, remodelación y otras construcciones de edificios habitacionales, comerciales e industriales, de acuerdo a la siguiente tabla:\nUNIDAD DE MEDIDA Y\nACTUALIZACIÓN VIGENTE\n1.- Casa habitación y vivienda de interés social unifamiliares, multifamiliar horizontal, multifamiliar vertical y módulos prefabricados, tratándose de cualquier tipo de inmuebles.\na).- Para vivienda nueva y ampliaciones hasta\n40 m² propiedad de particulares, en fraccionamientos y colonias pagará.......... 7.83 veces\nb).- Para vivienda nueva y ampliaciones de 40 m² a 60 m² propiedad de particulares, en fraccionamientos y colonias pagará.......... 18.79 veces\nc).- Para vivienda nueva y ampliaciones de 60 m² a 120 m², propiedad de particulares, en fraccionamientos y colonias se pagará....... 37.58 veces\nd).- Para vivienda nueva y ampliación mayor a\n120 m², propiedad de particulares, en fraccionamientos y colonias pagará por el total, por metro cuadrado................... 0.40 veces\ne).- Las viviendas particulares mayores a 60 m2 que se inicien sin licencia de construcción, pagarán 50% por regularización adicional al costo de la licencia........................\n2.- Para la instalación de cada módulo prefabricado, de uso provisional:\na).- Para uso comercial y de servicios, por unidad incluye el retiro........................... 24.20 veces\n3.- Para comercio y servicios hasta 100 m² de móvil............................................ 81.44 veces\nPor cada 100 m² o fracción subsecuente........... 46.99 veces\n4.- Para industria hasta de 100 m² de construcción incluyendo prefabricado tipo casa móvil.......... 62.65 veces\nPor cada 100 m² o fracción subsecuente........... 62.65 veces\n5.- Estacionamiento y patios de maniobras para industria, comercio y servicios con necesidad:\na).- Hasta 40 cajones de estacionamiento......... 17.22 veces\nb).- De 41 a 100 cajones de estacionamiento...... 31.32 veces\nc).- Anden de carga y descarga por unidad........ 27.72 veces\nd).- Por cada cajón subsecuente.................. 0.31 veces\ne).- Patio de maniobras por m²................... 7.60 veces\n6.- Bardas, cercos y fachadas:\nHasta 50 metros lineales......................... 10.96 veces\nPor cada 10 metros lineales subsecuentes......... 10.96 veces\n7.- Movimiento de tierras por los primeros 1,000 m² o fracción......................................... 20.35 veces\nPor cada 1,000 m² adicionales o fracción......... 2.34 veces\n8.- Prórroga de licencia de edificación:\na).- Para habitacionales, en todos los rangos de superficie por cada vivienda................ 7.83 veces\nb).- Por edificación comercial y servicio........ 15.66 veces\nc).- Por edificación industrial.................. 31.32 veces\nd).- Por barda................................... 7.83 veces\n9.- Terminación de obra y autorización de ocupación:\na).- Para viviendas con superficie de\nb).- Para habitacionales mayores de 60 m² de superficie por cada vivienda................ 9.39 veces\nc).- Comercial y de servicios.................... 2 3.49 veces\nd).- Industrial por cada edificación............. 54.82 veces\n10.- Para instalaciones y/o estructuras no habitables, por cada unidad que requiera de análisis en materia de construcción, se pagarán derechos de acuerdo a la siguiente tabla:\na).- Hasta 20 m² de superficie en construcción... 40.71 veces\nb).- Por cada 10 m² o fracción en construcción subsecuente................................. 4.68 veces\nc).- Por cada unidad de cisternas, fosas, tanques, silos y otros.............................. 3 1.32 veces\nd).- Por la instalación de Paneles Solares por cada módulo................................. 7.00 veces\ne).- Por instalación de antenas con desplante desde nivel de piso y/o sobre una edificación a partir de los 5 metros.................... 60.00 veces\nf).- Por instalación de tuberías para hidrocarburos o acueductos y líneas de alta tensión y comunicación por cada 10 metros lineales............................. 7. 0 0 v e ces\ng).- Por instalación de torres de alta tensión eléctricas en todas las modalidades......... 8 0. 0 0 v eces\nEn uso habitacional y generador de área sombreada para estacionamiento y andadores será EXENTO.\n11.- Para la demolición parcial o total de tarifa:\na).- Por cada 10 m² en uso de suelo habitacional.. 8.19 veces\nb).- Por cada 10 m² en uso de suelo comercial, de servicio e industrial.................... 16.37 veces\nc).- Demolición de cordón para modificación, por metro lineal................................ 0.62 veces\nd).- Demolición de banquetas para modificación, por metro cuadrado.......................... 0.46 veces\ne).- Por cada 10 metros lineales de demolición de barda.................................... 8.19 veces\nf).- Demolición para reposición o construcción de banqueta y cordones de vía pública.......... E X ENTO\ng).- Demolición de cualquier tipo de edificación en estado de abandono para mejorar las condiciones del predio..................... EXENTO\n12.- Por expedición de Factibilidad de Licencia de\nConstrucción para las siguientes edificaciones:\na).- Habitacionales.............................. 12.52 veces\nb).- Comerciales y de servicios.................. 2 3.49 veces\nc).- Industrial.................................. 31.32 veces\n13.- Por la autorización de licencia incluida la revisión de proyectos obras para la instalación de líneas y estructuras de servicios subterráneos o aéreos sobre la vía pública:\na).- Por canalización que incluya una o más tuberías, cuya suma de diámetros sea menor a\n9 cm por cada 10 metros lineales o fracción 1.56 veces\nb).- Por canalización que incluya una o más tuberías, cuya suma de diámetros sea mayor a\n9 cm por cada 10 metros lineales o fracción 3.13 veces\nc).- Por reparación o sustitución de línea subterránea con circuitos de una o mas cableados, sin modificar canalización por cada 10 metros lineales o fracción.......... 0.78 veces\nd).- Para instalaciones aéreas, con circuitos de uno o más cableados en la misma trayectoria, por cada 10 metros lineales o fracción... 3.13 veces\ne).- Para estructuras subterráneas como registros, cajas de válvulas, etc. por m².............. 4.69 veces\nf).- Para estructuras fijas y semifijas, sobre y / o empotradas en la vía pública como módulos, registros, transformadores, postería, semáforos, señalizaciones verticales y horizontales, con excepción de anuncios publicitarios. f.1).- Hasta 2.00 m²........................ 3.91 veces f.2).- Por cada m² o fracción adicional..... 2.34 veces f.3).- Por unidad........................... 11.00 veces\ng).- Prórroga de licencia para la instalación de líneas aéreas y subterráneas sobre la vía pública..................................... 1 5.66 veces\nh).- Terminación de obra licencia instalación de líneas aéreas y subterráneas sobre la vía pública..................................... 2 3.49 veces\n14.- Registro de Peritos Responsable Proyectista y/o director de obra:\na).- P or alta inicial........................... 22.60 veces\nb).- Por revalidación........................... 11.30 veces\n15.- Por modificación de licencia habitacional, comercial, de servicios e industrial............ 12.43 veces\nEn caso de remodelación de interiores sin afectar estructura, donde de la edificación, se cobrará el 50% de la tarifa anterior.\nEn caso de regularización de cualquier tipo de trámite o autorización, se incrementará en un 50% de las tarifas fijadas en la presente fracción.\nPor la evaluación de anteproyectos arquitectónicos, previa a la expedición del permiso o licencia, se cobrará 12.60 veces la Unidad de Medida y Actualización vigente. para un mismo trámite, siendo esto imputable al propietario, se cobrará adicionalmente el 50% de la tarifa anterior. a equipamientos y servicios, incluyendo redes y urbanizaciones que se construyan en predios propiedad del Gobierno Municipal, estarán exentos del pago de los derechos a que se refiere esta fracción.\nII.- POR ANÁLISIS DE SOLICITUDES Y EMISIÓN DE DECLARATORIA PARA\nCONSTITUIR REGÍMENES DE PROPIEDAD EN CONDOMINIO DE INMUEBLES\nA).- Por análisis de anteproyectos de conjuntos habitacionales, comerciales, industriales o mixtos, únicos, que estarán bajo el régimen de propiedad en condominio, se pagará:\nUNIDAD DE MEDIDA Y\nACTUALIZACIÓN VIGENTE\n1.- Por conjunto hasta de 10 unidades........... 39.15 veces\n2.- Por cada unidad que exceda de las diez primeras.................................... 5. 4 8 veces\nB).- Por análisis de anteproyectos de conjuntos habitacionales, comerciales, industriales o mixtos, que se utilizarán en forma múltiple en predios uniformes y que conformen un solo conjunto inmobiliario, se pagará por el primero las mismas cuotas del inciso anterior, y el 10% de éstas para las subsecuentes.\nC).- Por análisis y dictamen de factibilidad de conversión al habitacionales, comerciales, industriales o mixtos ya construidos se pagará:\n1.- Por conjuntos habitacionales hasta de\n10 unidades................................. 39.15 veces\n2.- Por cada unidad habitacional que exceda de las diez primeras........................... 5.48 veces\n3.- Por Centros Comerciales, urbanos o sub urbanos hasta de 5 unidades................. 7 0. 48 veces\n4.- Por cada unidad comercial que exceda de las cinco primeras.............................. 6. 2 6 veces\n5.- Por cada unidad industrial hasta 1,000 m²... 2 0.35 veces\n6.- Por cada m² o fracción subsecuente de los 1000 m² por unidad............................... 0. 071 veces\nD).- Por la emisión de la declaratoria para la constitución del régimen de propiedad en condominio de inmuebles, se pagará por cada lote, departamento, vivienda, casa o local comercial en la forma siguiente:\n1.- Por cada unidad habitacional............ 15.66 veces\n2.- Por cada unidad comercial............... 36.01 veces\n3.- Por cada unidad industrial de hasta 1,000 m² 70.48 veces\n4.- Por cada m² o fracción subsecuente.......... 0.085 veces\nE).- Por verificación y certificación de memorias descriptivas de departamentos, viviendas, casas o locales, pertenecientes a condominios, se pagará por la primera revisión en la forma siguiente:\n1.- Por cada conjunto hasta de 5 unidades....... 54.82 veces\n2.- Por cada unidad excedente................... 10.17 veces\nEn el caso de revisiones subsecuentes, se pagará el 50% de la cuota prevista para la primera revisión, siempre y cuando se trate de observaciones de la autoridad.\nF).- Por emisión de constancia de traslación de dominio.......................................... 62.65 veces\nG).- Por constancia para cancelación de fianza en condominios...................................... 31.32 veces\n“A” y “B”, se hará previa notificación del Departamento de Control\nUrbano del Municipio, una vez determinados los lotes o unidades resultantes. monto total de estos derechos en un plazo de 20 días a partir de la fecha de su notificación, se suspenderá el trámite correspondiente.\nARTÍCULO 39.- Los servicios que presta esta oficina, por Uso del Suelo se pagarán conforme a lo siguiente:\nI.- POR ANÁLISIS Y EMISIÓN DE DICTAMEN O CONSTANCIA DE USO DEL SUELO:\nUNIDAD DE MEDIDA Y\nACTUALIZACIÓN VIGENTE\n1.- Vivienda:\na).- Multifamiliar\nHasta 3 viviendas........................... 12.52 veces\nDe 4 a 6 viviendas.......................... 21.92 veces\nPor cada vivienda adicional................. 4.69 veces\nb).- Mixto\nVivienda con uso comercial de baja escala... 21.92 veces\n2.- En equipamiento y servicios, por superficie del predio:\na).- Comercio:\n- Abasto y almacenaje; depósitos de productos básicos, de materiales de construcción, maquinaria, vehículos y otros; llevar dentro de un predio.\nHasta 5,000 m² de superficie............... 42.28 veces\nPor cada 1,000 m² subsecuentes, se pagará la cuota anterior más.......................... 4.69 veces\n- Artículos, servicios comerciales, estéticas, lavanderías, planchadurías, limpiadurías, alquiler de vehículos y equipo, sastrerías y vestimenta de alquiler, boutique de cerveza artesanal, venta de alimentos, etc.\nHasta 500 m² de superficie................. 46.99 veces\nDe 501 m² a 2,500 m² de superficie.......... 62.65 veces\nDe 2,501 m² hasta 5,000 m² de superficie.... 78.31 veces\nMayor de 5,001 m² de superficie............. 109.63 veces\nTramites ingresados a través del Sistema de\nApertura Rápida de Empresas (SARE), hasta\n100 m² de superficie........................ 31.32 veces\nb).- Educación y Cultura:\n- Preescolar, elemental, media básica, media superior, superior, academias y escuelas técnicas:\n(Incluye escuelas particulares)\nHasta 500 m² de superficie de terreno...... 31.32 veces\nDe 501 m² hasta 1,000 m² de superficie de terreno..................................... 62.65 veces\nPor cada 100 m² subsecuentes, o fracción pagará la cuota anterior más................ 6.26 veces\nc).- Salud y Servicios Asistenciales:\n- Hospitales, centros médicos y de especialidades:\nHasta 5,000 m² de superficie............... 78.31 veces\nMayor de 5,000 m² hasta 10,000 m² de superficie................................... 109.63 veces\nPor cada 1,000 m² subsecuentes se pagará la cuota anterior más.......................... 3.13 veces\n- Clínicas, consultorios, servicios médicos forenses, laboratorios médicos y guarderías:\nHasta 500 m² de superficie................. 46.99 veces\nMayor de 501 m² hasta 2,500 m² de superficie. 62.65 veces\nMayor de 2,501 m² hasta 5,000 m² de\nSuperficie.................................. 78.31 veces\nMayor de 5,001 m² de superficie........... 109.63 veces\nd).- Deportes y Recreación:\n- Centros deportivos y entretenimiento: estadios, lienzos charros, campos de tiro, boliche y juegos de mesa o electrónicos:\nHasta 5,000 m².............................. 26.62 veces\nMayor de 5,000 m² hasta 10,000 m²........... 31.32 veces\nPor cada 1,000 m² subsecuentes se pagará la cuota anterior más.......................... 3.13 veces\n- Canchas deportivas, albercas, salones de ejercicio y acondicionamiento físico:\nHasta 2,500 m².............................. 18.01 veces\nMayor de 2,500 m² hasta 5,000 m²............ 26.62 veces\nPor cada 1,000 m² subsecuentes se pagará la cuota anterior más.......................... 3.13 veces\ne).- Servicios Administrativos:\nHasta 500 m²................................ 46.99 veces\nMayor de 501 m² hasta 2,500 m².............. 62.65 veces\nMayor de 2,501 m² hasta 5,000 m² de superficie.................................. 78.31 veces\nMayor de 5,001 m² de superficie............. 109.63 veces\nf).- Seguridad y Bienestar:\n- Defensa, reclusorios, unidades de rescate y basureros:\nHasta 5,000 m².............................. 31.32 veces\nMayor de 5,000 m² hasta 10,000 m²........... 39.15 veces\nPor cada 1,000 m² que exceda los 10,000 m² pagará la cuota anterior más................ 3.13 veces\ng).- Turismo:\n- Alojamiento: hoteles, moteles, casas de huéspedes y estacionamiento para casas rodantes y vehículos para acampar:\nHasta 5,000 m².............................. 39.15 veces\nMayor de 5,000 m² hasta 10,000 m²........... 43.84 veces\nPor cada 1,000 m² subsecuentes se pagará la cuota anterior más.......................... 4.69 veces\nh).- Servicios Mortuorios:\n- Crematorios, velatorios, agencias de inhumaciones y funerarias:\nHasta 1,000 m².............................. 20.43 veces\nMayor de 1,000 m² hasta 5,000 m²............ 39.15 veces\nPor cada 1,000 m² subsecuentes se pagará la cuota anterior más.......................... 3.13 veces\ni).- Comunicaciones y Transportes:\n- Transporte: Estaciones y sitios de transporte público\n(autobuses y taxis), estacionamientos públicos, estacionamientos privados, terminales de transporte foráneo, encierro de transporte de carga, de vehículos de alquiler y base para radio taxis:\nHasta 5,000 m².............................. 32.88 veces\nMayor de 5,000 m² hasta 10,000 m²........... 37.58 veces\nPor cada 1,000 m² subsecuentes se pagará la cuota anterior más.......................... 3.13 veces\n- Comunicaciones: estaciones de radio, televisión, telefonía y concentradoras:\nHasta 2,500 m².............................. 20.35 veces\nMayor de 2,500 m² hasta 5,000 m²............ 28.18 veces\nMayor de 5,000 m² hasta 10,000 m²........... 32.88 veces\nPor cada 1,000 m² subsecuentes se pagará la cuota anterior más.......................... 3.13 veces\nj).- Diversión y Espectáculos:\n- Auditorios, teatros, cines, exposiciones, y sitios de diversiones:\nHasta 10,000 m²............................. 46.99 veces\nPor cada 1,000 m² subsecuentes se pagará la cuota anterior más.......................... 4.69 veces\n- Centros de apuestas, apuestas remotas, salas de sorteos de números y/o casinos, Libro Foráneo y similares:\nHasta 3,000 m² de superficie................ 783.09 veces\nDe 3,001 m² de terreno en adelante.......... 1,174.64 veces\n- Centros Sociales: Jardines para fiestas, salones para banquetes, salones de baile, centros nocturnos, cantinas, café cantante, bares y billares, sala de degustación de cerveza artesanal:\nHasta 1,000 m².............................. 86.14 veces\nDe 1,001 m² hasta 2,500 m² de terreno....... 109.63 veces\nPor cada 500 m² subsecuente, o fracción se pagará la cuota anterior más................ 9.39 veces\nk).- Especial:\n- Estación o distribución de gas, gasolineras, almacén de hidrocarburos y estaciones de carburación:\nHasta 5,000 m².............................. 86.14 veces\nPor cada 1,000 m² subsecuentes se pagará la cuota anterior más.......................... 4.69 veces\n3.- En industria, por superficie del predio:\na).- Extractiva: Explotación de minas o bancos de materiales de construcción:\nHasta 2 hectáreas de predio................. 78.31 veces\nPor cada hectárea subsecuente se pagará la cuota anterior más.......................... 4. 69 veces\nb).- Transformación: Fundición de minerales metálicos, fertilizantes, hules y plásticos, petróleos y derivados, papel madera, bloqueras y ladrilleras, alimenticia, bebidas y tabaco, pigmentos, pinturas colorantes y derivados, vidrios, cerámica y derivados:\nHasta 10,000 m² de predio.................. 78.31 veces\nPor cada 2,000 m² subsecuentes se pagará la cuota anterior más.......................... 4.69 veces\nc).- Manufacturera: Máquinas y herramientas, textiles e industrias de cueros, de la madera, productos de papel, ensamble de aparatos eléctricos o electrónicos, maquiladoras de otros tipos:\nHasta 10,000 m² de predio.................. 70.48 veces\nPor cada 2,000 m² subsecuentes se pagará la cuota anterior más.......................... 4.69 veces\nd).- Agroindustria: Envases y empaques, forrajes y otras.\nCualquier superficie........................ 78.31 veces\ne).- Micro Industria: Imprentas, talleres de serigrafía, taller de torno y soldadura, taller de herrería, elaboración de frituras, taller de carrocería y pintura, elaboración de cerveza artesanal.\nHasta 500 m² de superficie.................. 26.62 veces\nMayor de 500 hasta 1,000 m²................. 40.71 veces\nMayor de 1,000 m²........................... 54.82 veces\n4.- Infraestructura, por superficie del predio:\n- Instalaciones: Plantas, estaciones y subestaciones, torres y antenas, antenas de telefonía celular, carteleras espectaculares, carteleras electrónicas, depósitos, antenas de radio, telefonía, cárcamos y bombas, ramales, tuberías, generación de energía mediante paneles solares, generación eólica, generación de energía mediante turbinas y otros:\nPor elemento en cada predio...................... 164.45 veces\nTratándose de antenas, torres, antenas de telefonía celular o de radio comunicación así como carteleras electrónicas realizarán una revalidación anual si se determina uso temporal.. 234.93 veces por unidad\n5.- En otros usos:\na).- Actividades agropecuarias, cauces y cuerpo de agua:\nPor cualquier superficie.................... 46.99 veces\nb).- Casetas fitosanitarias, centros de pesaje, viveros, pistas para fumigadores, pistas para carreras de vehículos:\nHasta 1,000 m² de superficie................ 39.15 veces\nDe 1,001 hasta 2,500 m²..................... 46.99 veces\nDe 2,501 hasta 5,000 m²..................... 54.82 veces\nMayor de 5,000 m²........................... 70.48 veces\nDesmanteladoras (yonques), recicladoras..... 93.97 veces\n6.- Permiso temporal de uso de suelo para plantas generadoras de energía eléctrica:\nPor cualquier superficie................... 78.31 veces\nEn cualquier caso anterior, por regularización de uso de suelo, se adicionará un 50% de las tarifas anteriores.\nAlbergues, centros de tratamiento psiquiátrico, centros de rehabilitación física y orfanatos o casas de cuna, quedarán exentos de pago.\nDictámenes en predios propiedad del Gobierno Municipal, estarán exentos del pago de los derechos a que se refiere esta fracción.\n7.- Cobro por cambio de propietario y/o posesionario en el dictamen o constancia de uso de suelo...... 20.00 veces\nII.- POR FACTIBILIDAD DE USO DEL SUELO.\n1.- Para construcciones en uso o desuso y para predios a desarrollar a solicitud del interesado:\nUNIDAD DE MEDIDA Y\nACTUALIZACIÓN VIGENTE\nVivienda:\na).- Multifamiliar\nPor cada vivienda........................... 2.34 veces\nb).- Mixto\nVivienda con uso comercial de baja escala... 10.96 veces\n2.- En equipamiento y servicios, por superficie del predio:\na).- Comercio:\n- Abasto y almacenaje; depósitos de productos básicos, de materiales de construcción, maquinaria, vehículos y otros; llevar dentro de un predio.\nPor predio.................................. 20.35 veces\n- Artículos, servicios comerciales, estéticas, lavanderías, planchadurías, limpiadurías, alquiler de vehículos y equipo, sastrerías y vestimenta de alquiler, etc.\nPor predio.................................. 31.32 veces\nb).- Educación y Cultura:\n- Preescolar, elemental, media básica, media superior, superior, academias y escuelas técnicas:\nPor predio.................................. 15.66 veces\nc).- Salud y Servicios Asistenciales:\n- Hospitales, centros médicos y de especialidades:\nPor predio.................................. 24.27 veces\n- Clínicas, consultorios, servicios médicos forenses, laboratorios médicos y guarderías:\nPor predio.................................. 19.57 veces\nd).- Deportes y Recreación:\n- Centros deportivos y entretenimiento: estadios, lienzos charros, campos de tiro, boliche y juegos de mesa o electrónicos:\nPor predio.................................. 15.66 veces\n- Canchas deportivas, albercas, salones de ejercicio y acondicionamiento físico:\nPor predio.................................. 13.31 veces\ne).- Servicios Administrativos:\nPor predio.................................. 11.74 veces\nf).- Seguridad y Bienestar:\n- Defensa, reclusorios, unidades de rescate y basureros:\nPor predio.................................. 15.66 veces\ng).- Turismo:\n- Alojamiento: hoteles, moteles, casas de huéspedes y estacionamiento para casas rodantes y vehículos para acampar:\nPor predio.................................. 21.92 veces\nh).- Servicios Mortuorios:\n- Crematorios, velatorios, agencias de inhumaciones y funerarias:\nPor predio.................................. 19.57 veces\ni).- Comunicaciones y Transportes:\n- Transporte: Estaciones y sitios de transporte público\n(autobuses y taxis), estacionamientos públicos, estacionamientos privados, terminales de transporte foráneo, estacionamiento y encierro de transporte de carga y de vehículos de alquiler:\nPor predio.................................. 16.44 veces\n- Comunicaciones: Estaciones de radio, televisión, telefonía y concentradoras:\nPor predio.................................. 16.44 veces\nj).- Diversión y Espectáculos:\n- Auditorios, teatros, cines, exposiciones, y sitios de diversiones:\nPor predio.................................. 23.49 veces\n- Centros de apuestas, apuestas remotas, salas de sorteos de números y/o casinos, Libro Foráneo y similares:\nHasta 3,000 m² de superficie................ 391.55 veces\nDe 3,001 m² de terreno en adelante.......... 548.16 veces\n- Centros Sociales: Jardines para fiestas, salones para banquetes, salones de baile, centros nocturnos, cantinas, café cantante, bares y billares:\nPor predio.................................. 39.15 veces\nk).- Especial:\n- Estación o distribución de gas, gasolineras, almacén de hidrocarburos y estaciones de carburación:\nPor predio................................. 313.24 veces\n3.- En industria, por superficie del predio:\na).- Extractiva: Explotación de minas o bancos de materiales de construcción:\nPor predio.................................. 23.49 veces\nb).- Transformación: Fundición de minerales metálicos, fertilizantes, hules y plásticos, petróleos y derivados, papel madera, bloqueras y ladrilleras, alimenticia, bebidas y tabaco, pigmentos, pinturas colorantes y derivados, vidrios, cerámica y derivados:\nPor predio.................................. 23.49 veces\nc).- Manufacturera: Máquinas y herramientas, textiles e industrias de cueros, de la madera, productos de papel, ensamble de aparatos eléctricos o electrónicos, maquiladoras de otros tipos:\nPor predio.................................. 23.49 veces\nd).- Agroindustria: Envases y empaques, forrajes y otras.\nCualquier superficie........................ 15.66 veces\ne).- Micro Industria: Imprentas, talleres de serigrafía, taller de torno y soldadura, taller de herrería, elaboración de frituras, taller de carrocería y pintura.\nHasta 500 m² de superficie.................. 9.39 veces\nMayor de 500 hasta 1,000 m²................. 10.96 veces\nMayor de 1,000 m²........................... 15.66 veces\n4.- Infraestructura, por superficie del predio:\n- Instalaciones: Plantas, estaciones y subestaciones, torres y antenas, antenas de telefonía, carteleras espectaculares, carteleras electrónicas, depósitos, antenas de radio, telefonía, cárcamos y bombas:\nHasta 1,000 m² de superficie................ 16.63 veces\nMayor de 1,000 m² de superficie............. 23.49 veces\n- En otros usos:\na).- Actividades agropecuarias, cauces y cuerpo de agua:\nPor cualquier superficie.................... 1 8.79 veces\nb).- Casetas fitosanitarias, centros de pesaje, viveros, pistas para fumigadores, pistas para carreras de vehículos:\nPor predio.................................. 23.49 veces\n5.- Reconsideraciones de uso de suelo.\nPara cualquier uso de suelo................. 12.52 veces\n6.- Permisos temporales de uso de suelo.\na).- Instalaciones temporales destinadas a eventos públicos como circos, espectáculos, convenciones, exposiciones, carpas, casas muestras, árboles de navidad, juguetería, regalos y similares:\nPor predio.................................. 23.49 veces\n7.- Anuencia de Uso de Suelo:\nPor trámite................................. 13.86 veces\n8.- Congruencia de Uso por cualquier superficie...... 46.99 veces\n9.- Previo a la apertura, regularización, ampliación, remodelación o instalación de módulos prefabricados de un giro comercial, industrial y de servicio, el Departamento de Control Urbano, realizará la revisión de las condiciones físicas para las actividades, validando la apertura del establecimiento, fijando horarios según la actividad solicitada; se emitirá la Licencia de Operaciones anual para los giros comerciales, industriales y de servicios.\na).- Para Usos Comerciales y de Servicios......... EXENTO\nb).- Para Uso Industrial......................... EXENTO\nc).- Revalidación anual:\n1.- Para Usos Comerciales y de Servicios..... EXENTO\n2.- Para Uso Industrial...................... EXENTO\n10.- Copia Certificada:\na).- Copia de documentos, por la primer hoja...... 1.56 veces\nb).- Por cada hoja subsecuente................... 0.40 veces\n11.- Inspección para constancia uso de suelo.......... 23.49 veces\nIII.- INSTALACIONES DE INFRAESTRUCTURA URBANA: de infraestructura urbana, se regirán bajo el supuesto del denominado Del Piso, de esta ley.\nARTÍCULO 40.- Los servicios que presta esta oficina, por concepto de\nImagen Urbana, se pagarán conforme a lo siguiente:\nI.- PARA RÓTULOS E INSTALACIÓN DE ESTRUCTURAS DE ANUNCIOS CON\nVISIBILIDAD DIRECTA HACIA EL EXTERIOR, SE PAGARÁN DERECHOS DE\nACUERDO A LA SIGUIENTE TABLA, EN LA CUAL LAS SUPERFICIES SE\nCONSIDERAN LAS CARAS EXPUESTAS DEL ANUNCIO:\na).- Establecimientos de giro comercial y de servicios en propiedad privada, excepto plazas comerciales y predios con varios locales, que cuenten con un solo anuncio, clasificado como denominativo, instalado en azotea, pared, ventana o puerta, etc., que no excedan de 3 m² (incluyendo los ingresados a través del Sistema de Apertura Rápida de\nEmpresas (SARE))............................ EXENTO\nb).- Establecimientos de giro comercial y de\nServicios que se ingresen a través del\nSistema de Apertura Rápida de Empresas\n(SARE), que cuenten con un solo anuncio que no exceda de 3 m².......................... EXENTO\nc).- Hasta 15 m² de superficie.............. 56.38 veces\nd).- Mayor de 15 m²........................... 92.55 veces\nII.- ESTABLECIMIENTO DE MOBILIARIO URBANO Y PUBLICITARIO CON\nVISIBILIDAD HACIA EL EXTERIOR. incluyendo plazas comerciales, se determinará de acuerdo a las cuotas o tarifas siguientes:\nPor la autorización para la construcción y/o instalación de anuncios por cara expuesta, se pagarán las siguientes cuotas vigente:\n1.- Pantalla electrónica y/o digital o electromecánica, pantalla en vehículos o sin movimiento, incluyendo instalación..... 284.76 veces\n2.- Espectacular unipolar y anuncio mayor a\n15 m², o en azotea incluye instalación..... 500.00 veces\n3.- Unipolar mediano/directorio, torre, hasta\n15 m², por cara, sobre poste o azotea, incluye instalación........................ 121.02 veces\n4.- Unipolar pequeño........................... 49.83 veces\n5.- Valla publicitaria hasta 15 m² por unidad, incluye instalación........................ 58.87 veces\n6.- Electrónicos, incluye instalación.......... 50.40 veces\n7.- Por cada m² excedente...................... 58.87 veces\nIII.- POR PERMISO TEMPORAL PARA LA COLOCACIÓN DE ANUNCIO CON\nVISIBILIDAD DIRECTA HACIA EL EXTERIOR, EXCEPTUANDO LA\nPROPAGANDA POLÍTICA, SE PAGARÁ LO SIGUIENTE:\nUNIDAD DE MEDIDA Y\nACTUALIZACIÓN VIGENTE\n1).- Anuncios tipo caballete, bandera, banderín o estandarte, hasta 4 m² por ambas caras, colocados en estructuras de cualquier tipo de material por un período de 3 meses..... 23.49 veces por cada uno\n2).- Por cada cartel promocional de hasta 1.50 m²:\na).- Vigencia hasta 90 días................ 7.83 veces\n3).- Rótulo tipo manta o lona en vía pública o en propiedad privada por un período de 15 días hasta 90 días:\na).- Por cada 20 m² o fracción de superficie........................... 2 3.49 veces\n4).- Rótulo tipo manta o lona en propiedad privada por un período de 365 días:\na).- Por cada 20 m² o fracción de superficie 67.80 veces\n5).- Promoción en elementos y/o estructuras inflables luminosos o sin iluminación en propiedad privada o en vehículos:\na).- Vigencia por cada 15 días............ 1 5.66 veces\n6).- Por instalación de teléfono público colocado en vía pública, existente o nuevo, por unidad................................ 24.24 veces\n7).- Para anuncio ambulante conducido por persona por anuncio, por día............... 24.24 veces\n8).- Licencias nuevas para rótulos en cobertizos publicitarios, mobiliario urbano, figuras cilíndricas y en vehículos móviles, con o sin iluminación con vigencia hasta un año:\na).- Rótulo por anuncio:\n1.- Ajeno a la razón social del\nEstablecimiento hasta 3 m² por anuncio. 7.83 veces\n2.- Excedente de 3 m² por cada metro cuadrado............................. 1.56 veces\n3.- Igual a la razón social hasta 3 m²... EXENTO\n4.- Igual a la razón social de 3 m² en adelante por metro cuadrado.......... 4. 6 9 v e ces\nb).- Rótulo con iluminación..................... 4.69 veces por m²\nc).- Anuncio electrónico o electromecánico, LED por m²..................................... 1 2.52 veces\nd).- Instalación de cobertizo publicitario y/o mobiliario urbano (banca publicitaria, bote de basura o buzón con publicidad, etc.).... 18.79 veces por unidad\ne).- Torrete en techo de camión o taxi.......... 4.69 veces por unidad\nf).- Rótulo en vehículos o autobuses excepto aquellos de distintivo oficial............. 31.32 veces por unidad\ng).- Anuncios electrónicos y rótulos electrónicos con o sin movimiento en vehículos con vigencia de tres meses..................... 31.32 veces por unidad\nIV.- LA REVALIDACIÓN DEL PERMISO PARA ANUNCIOS Y SIMILARES,\nCONSTRUIDOS EN PROPIEDAD PRIVADA, CON VISIBILIDAD DIRECTA HACIA\nEL EXTERIOR, INCLUYENDO PLAZAS COMERCIALES CONSIDERANDO LA\nSUPERFICIE DE CADA CARA EXPUESTA, SE PAGARÁN DERECHOS DE ACUERDO\nCON LA SIGUIENTE TARIFA:\na).- Anuncio adosado, toldo, rótulo, etc. por m² 1.56 veces\nb).- Anuncio en pantalla electrónica o electromecánica con o sin movimiento....... 500.00 veces\nc).- Torrete en techo de camión o taxi por unidad. 4.69 veces\nd).- Anuncio electrónico y con movimiento en vehículos por unidad....................... 31.32 veces\ne).- Espectacular............................... 75.60 veces luminosos, en propiedad privada con superficie de hasta 3 m².\nSe condona el 100% del cobro del derecho establecido en está fracción pintados no luminosos, que cuenten con un solo anuncio de hasta 3 m2, construidos en propiedad privada, comprendidos desde el ejercicio fiscal de 2020 a 2024, siempre y cuando cubran los derechos correspondientes al ejercicio fiscal de 2025.\nLas instituciones educativas públicas, culturales, asociaciones civiles y religiosas dedicadas a la beneficencia pública, estarán exentas del pago de este derecho.\nV.- POR ANÁLISIS Y EMISIÓN DE FACTIBILIDAD DE OPINIONES TÉCNICAS\nCONSTRUIDA EN PROPIEDAD PRIVADA.\nPor cada anuncio o estructura.................... 17.09 veces de cada año, en meses subsecuentes se cobrará el 50% adicional.\nAl instalar cualquier tipo de anuncio o estructura permanente con fines de publicidad en un predio su tasa automáticamente cambiará a tasa comercial.\nLos derechos del ejercicio fiscal 2024, correspondientes a este artículo de Imagen Urbana podrán ser aplicables a los rezagos de ejercicios fiscales anteriores.\nVI.- GENERALIDADES:\nA).- Copiado de documento, por cada hoja.......... 1.56 veces\nB).- Constancia de documento..................... 6.26 veces\nC).- Certificación de documento.................. 4.69 veces\nD).- Inspección ocular, a solicitud del interesado................................. 6.26 veces\nARTÍCULO 41.- Las personas físicas o morales que presten los servicios de publicidad, así como los propietarios y/o poseedores de los bienes donde se instalen anuncios, serán solidariamente responsables del pago de los impuestos, derechos y/o multas que se originen con motivo de los anuncios que tengan instalados en esta municipalidad.\nARTÍCULO 42.- El Certificado de Mejoramiento de la Imagen Urbana, es que se hace constar el estado físico de un predio urbano, que cuenten con tasa de baldío o no edificado; conforme el Reglamento del Catastro\nInmobiliario para el Municipio de Mexicali, Baja California y en base al Artículo 6, Fracción I de la presente Ley de Ingresos. mismo, tendrán derecho a los siguientes descuentos en el pago anual del Impuesto Predial.\nA).- Predios con tasa de Baldíos o no Edificados:\nI.- Los predios baldíos o no edificados deberán: estar sin uso, libres de basura, maleza, escombro, cascajo o cualquier otro residuo, desecho o desperdicio............ 20 %\nII.- Contar con guarniciones y banquetas en buen estado que permitan el libre tránsito peatonal.................................. 1 0 %\nIII.- Tener en sus colindancias barda, cerco de malla ciclónica, estructura metálica o similar debidamente rigidizados, con elementos estructurales uniformes. Libre de graffiti en muros propios o ajenos.... 10 %\nIV.- Contar con áreas verdes en buenas condiciones al frente del predio sin que obstruyan el tránsito peatonal............ 5 %\nTOTAL 45 %\nB).- Bases para el otorgamiento del Certificado de Mejoramiento de la\nImagen Urbana:\nI.- Acreditar ser propietario o poseedor de un inmueble edificado.\nII.- Al momento de inscribirse para adquirir el Certificado de\nMejoramiento de la Imagen Urbana, pagar la cuota correspondiente, en base a la siguiente tabla:\nCOSTO DEL CERTIFICADO\nVALOR CATASTRAL VECES LA UNIDAD DE\nDE A MEDIDA Y ACTUALIZACIÓN\nVIGENTE\n$ 0 $ 37,200 0.25\n37,201 93,000 0.50\n93,001 186,000 1.50\n186,001 279,000 2.50\n279,001 372,000 4.00\n372,001 558,000 6.00\n558,001 774,000 8.00\n774,001 1,116,000 12.00\n1’116,001 2’232,000 20.00\n2’232,001 5’208,000 55.00\n5’208,001 8’928,000 90.00\n8’928,001 En adelante 100.00\n16 SERVICIOS QUE PRESTA EL DEPARTAMENTO DE FRACCIONAMIENTOS\nARTÍCULO 43.- Los servicios que presta esta oficina, por concepto de\nFraccionamientos, se pagarán conforme a lo siguiente:\nI.- POR ANÁLISIS DE DESARROLLOS URBANOS:\nPor análisis de uso de suelo para acciones de urbanización por superficie de predio:\nA).- Por análisis de predios a urbanizar, incorporar o reincorporar al área urbana, revisión de restricciones existentes y de los del suelo:\nUNIDAD DE MEDIDA Y\nACTUALIZACIÓN VIGENTE\n1.- Por emisión de Dictamen de Uso de Suelo:\na).- Hasta 3 hectáreas..................... 71.19 veces\nb).- Por cada hectárea o fracción adicional 7.12 veces promovidas por Organismos Gubernamentales pagarán un 50% de la tarifa anterior.\nPara predios con superficie menor a 1.00 hectárea, que no sean desarrollados como fraccionamientos, el monto a pagar deberá calcularse conforme al artículo 39 de esta Ley.\n2.- Por emisión de Factibilidad de Uso de Suelo:\na).- En terrenos de hasta 3 has. dentro del límite del centro de población de\nMexicali.............................. 56.95 veces\nb).- En terrenos de hasta 3 has. fuera del límite del centro de población de\nMexicali.............................. 75.60 veces\nHectárea o fracción adicional......... 7.12 veces\n3.- Por Gestión en Autorización de Cambio de Uso de Suelo, se deberá cubrir:\na).- Por documento......................... 50.00 veces\n4.- Por realización de inspección y elaboración de dictamen técnico, se deberá cubrir previo al inicio del trámite:\na).- Encaminado a la desincorporación de los bienes del dominio público........ 10.96 veces\nb).- Encaminado a la obtención de dictamen técnico para la asignación en comodato de un bien del dominio público........ 12.52 veces\nc).- Dictamen técnico encaminado a la certificación de datos sobre la ubicación, medidas y colindancias de un bien del dominio privado........... 14.09 veces\n5.- Por emisión de dictamen de congruencia:\nEn terrenos ubicados dentro del centro de población de la cabecera municipal.......... 117.46 veces\nEn terrenos ubicados dentro de los centros de población de los poblados................ 156.62 veces\n6.- Por ratificación de dictamen de uso de suelo, que haya sido emitido en un periodo mayor de un año:\nPor cada vez................................ 15.66 veces\nB).- Por análisis de anteproyectos de lotificación para acciones de\nUrbanización en sus diversas modalidades, consistentes en el\nAnálisis de la distribución de los usos y destinos del suelo, estructuración del desarrollo, integración vial al contexto urbano, así como por la modificación o revalidación de los mismos, se cobrará por la superficie total para cualquier tipo de desarrollo y uso en la forma siguiente:\n1.- Por análisis de anteproyecto de lotificación en Acciones de Urbanización:\nUNIDAD DE MEDIDA Y\nACTUALIZACIÓN VIGENTE\na).- En terrenos dentro de los centros de población:\nHasta 5 hectáreas..................... 85.43 veces\nPor cada hectárea o fracción adicional 8.54 veces\nb).- En terrenos fuera de los centros de población:\nHasta 5 hectáreas..................... 121.02 veces\nPor cada hectárea o fracción adicional 8.54 veces\n25% las tarifas de la presente fracción.\nLas acciones de urbanización por objetivo social, las colonias y fraccionamientos populares, con urbanización mínima promovida por\nOrganismos Gubernamentales pagarán un 50% de las tarifas anteriores.\nPor la tercera revisión se cobrará el 50% de la tarifa y por la cuarta revisión en adelante se cobrará el 25%.\nC).- Por análisis de proyectos ejecutivos nuevos o modificaciones de la geometría de ejes de vías públicas, manzanas y lotificación de Acciones de Urbanización en sus diversas modalidades, se pagará dentro o fuera de los centros de población, de la forma siguiente:\n1.- Para acciones de urbanización nuevas, modificaciones y regularización:\nHasta 5 hectáreas..................... 128.14 veces\nPor cada hectárea o fracción adicional 17.08 veces\nLas acciones de urbanización por objetivo social, las colonias y fraccionamientos populares, con urbanización mínima promovida por los\nOrganismos Gubernamentales pagarán un 50% de las tarifas anteriores.\nEn revisiones subsecuentes a la segunda se cobrará el 50% de la tarifa anterior.\nD).- Por análisis de anteproyectos de infraestructura urbana para acciones de urbanización, consistente en inspección al terreno a desarrollar, análisis de la ubicación de los servicios públicos en las vías públicas resultantes, en servidumbres de paso establecidas, integración de la infraestructura a instalar a los públicos de alumbrado público, equipamiento de áreas verdes e instalación de hidrante, en cualquier modalidad de acciones de urbanización, incluyendo la incorporación o reincorporación municipal:\nHasta 5 hectáreas................................ 75.60 veces\nPor cada hectárea o fracción adicional........... 1.89 veces\nLas acciones de urbanización por objetivo social, las colonias y fraccionamientos populares, con urbanización mínima promovidas por\nOrganismos Gubernamentales pagarán un 50% de las tarifas anteriores.\n25% de las tarifas fijadas en los incisos C) y D).\nEn revisiones subsecuentes a la segunda se cobrará el 50% de la tarifa anterior.\nE).- Modificación de predios urbanos y suburbanos:\n1.- Por relotificación, subdivisión o fusión de predios urbanos:\nPor inspección ocular y análisis para visto bueno de cada solicitud:\na).- Ubicados dentro del área urbana\n(ciudad)............................. 6.26 veces\nPor cada lote resultantes de la modificación......................... 3.13 veces\nb).- Ubicados fuera del área urbana (zonas suburbanas)........................... 9.39 veces\nPor cada lote resultante de la\nModificación.......................... 3.13 veces\n2.- Por análisis, expedición de autorización y certificación de la memoria descriptiva resultante por subdivisión, relotificación o fusión de predios urbanos:\na).- En lotes baldíos:\nHasta 5 lotes resultantes por subdivisión, relotificación o fusión por cada uno.......................... 10.68 veces\nPor cada lote resultante por subdivisión, relotificación o fusión adicional............................. 3.13 veces\nb).- En lotes construidos:\nHasta 5 lotes resultantes por subdivisión, relotificación o fusión por cada uno.......................... 14.24 veces\nPor cada lote resultante por subdivisión, relotificación o fusión adicional............................. 3.13 veces\nF).- Por subdivisión o fusión de lotes rústicos y análisis para visto bueno:\n1.- Por inspección ocular de cada solicitud:\na).- Ubicados dentro del centro de población............................. 10.68 veces\nPor cada lote resultante de la modificación. 3.13 veces\nb).- Ubicados fuera del centro de población 13.53 veces\nPor cada lote resultante de la modificación. 3.13 veces\n2.- Por análisis, expedición de autorización y certificación de la memoria descriptiva, por cada lote resultante........................ 3 7.73 veces\nG).- Por certificación de memorias descriptivas:\n1.- Por verificación y certificación de memorias descriptivas modificaciones, se pagará por cada revisión en la forma siguiente:\na).- Hasta 50 lotes........................ 28.48 veces\nb).- Por cada lote adicional a 50.......... 0.42 veces\n2.- Por validación a la modificación de la memoria descriptible y del Comercio, propiedad de instituciones gubernamentales certificado por catastro municipal:\nPor cada lote............................... 9.97 veces\nH).- Por constancia de cumplimiento de requisitos para traslación de de dominio en desarrollos urbanos:\nDe 1 a 50 lotes solicitados................. 99.67 veces\nPor cada lote adicional..................... 2.14 veces\nI).- Emisión de respuestas y constancias a solicitud de personas distintas a los propietarios, relativas a las acciones de urbanización autorizadas o en proceso de autorización:\nPor cada vez................................ 23.49 veces\nJ).- Por acta de recepción de fraccionamientos para su mantenimiento por etapa o completo:\nPor cada vez................................ 78.31 veces\nK).- Por copia simple o certificada de documento o plano:\n1.- Por copia simple de documento:\na).- Hasta 10 hojas....................... 0.45 veces\nb).- Por cada hoja adicional............... 0.080 veces\n2.- Por copia certificada de documento:\na).- Hasta 10 hojas........................ 2.14 veces\nb).- Por cada hoja adicional............... 0.42 veces\n3.- Por certificación de copias de planos...... 4.27 veces\nL).- Por revisión del presupuesto de urbanización para pago de derechos, notificación y modificación del monto de la fianza y por constancia de reducción y/o cancelación de fianza de desarrollos urbanos y/o acciones de urbanización por documento:\nHasta 5 hectáreas........................... 31.32 veces\nPor cada hectárea adicional................. 7.12 veces\nM).- Visto bueno para que el desarrollador provisionalmente municipio:\nPor cada vez................................ 7.83 veces\nN).- Por elaboración de dictamen técnico e integración de expediente al municipio mediante el pago por su valor comercial, por obras de infraestructura y/o obras de edificación se deben pagar previo a su envío a Cabildo:\nPor cada vez................................ 31.32 veces\nÑ).- Por integración de expediente, formulación de dictamen y trámite para opinión de la Acción de Urbanización solicitada:\nPor cada vez................................ 85.43 veces\nO).- Por elaboración de Acuerdo de Autorización de Acciones de\nUrbanización, o modificaciones a éstas, se cobrará:\nHasta 3 hectáreas........................... 85.43 veces\nPor cada hectárea o fracción adicional...... 4.27 veces\nP).- Por emisión de respuesta y constancias relativas al cumplimiento realización de estas acciones, se cobrará:\nPor cada vez................................ 9.39 veces\nEl pago de los derechos a que se refieren a los incisos del “A” al “O” notificación del Departamento de Fraccionamientos del Municipio.\n17 SERVICIOS QUE PRESTA EL DEPARTAMENTO DE INGENIERÍA DE TRÁNSITO\nARTÍCULO 44.- Los servicios que presta el Departamento de Ingeniería de Tránsito, se causarán conforme a lo siguiente:\nI.- Por expedición de lineamientos viales para el desarrollo urbano y obras de infraestructura, se pagará por la superficie total registrada del predio:\nUNIDAD DE MEDIDA Y\nACTUALIZACIÓN VIGENTE\na).- Menor de 1 hectárea......................... 31.39 veces\nb).- Mayor de 1 ha. Hasta 3 ha................... 62.78 veces\nc).- Mayor de 3 ha. Hasta 5 ha................... 94.17 veces\nd).- Por hectárea adicional de 5 ha. además de la cuota anterior se agrega.................... 8.96 veces\ne).- Por ratificación y actualización de lineamientos viales emitidos en un período mayor de un año............................. 31.39 veces\nf).- Por emisión de constancia de no lineamientos viales...................................... 23.91 veces\ng).- Por análisis de estudios relacionados para la modificación de lineamientos viales despachados................................. 91.67 veces\nh).- Cuando la expedición de lineamientos viales corresponda a un trámite de subdivisión, certificación de deslinde edificación u obras de infraestructura, se pagará el 50% de los derechos enunciados en los incisos que anteceden, según corresponda.\nII.- Por análisis de accesos vehiculares se pagará en relación a los siguiente:\na).- Por emisión de factibilidad de acceso vehicular por predio:\n1).- Lotes habitacionales de aprovechamiento comercial.............................. 8. 96 veces\n2).- Lotes comerciales y de servicio con área de estacionamiento privado........ 1 1.96 veces\n3).- Naves industriales, centros de abasto y almacenaje, andenes de carga y descarga, o cualquier uso similar...... 1 7. 93 veces\n4).- Estaciones de servicio, de carburación o cualquier uso similar............... 3 2. 88 veces\nb).- Por análisis y elaboración de dictamen de proyectos de acceso vehicular a:\n1).- Lotes habitacionales de aprovechamiento comercial.............................. 17.93 veces\n2).- Lotes comerciales y de servicio con área de estacionamiento privado, se pagará de la siguiente manera:\n2.1).- Hasta 10 cajones........................ 23.91 veces\n2.2).- De 11 a 20 cajones................... 47.83 veces\n2.3).- De 21 a 30 cajones................... 71.76 veces\n2.4).- Por cada cajón de estacionamiento\n3).- Naves industriales, centros de abasto y almacenaje, andenes de carga y descarga, o cualquier uso similar...... 3 5. 88 veces\n3.1).- Por cada cajón de estacionamiento, además de la cuota anterior.......... 2.25 veces\n4).- Estaciones de servicio, de carburación o cualquier uso similar................ 65.78 veces\n4.1).- Por cada cajón de estacionamiento además de la cuota anterior.......... 2.25 veces\n5).- Revisión y análisis de estudio de impacto vial........................ 23.28 veces\nc).- Por modificaciones a proyectos de acceso vehicular a:\n1).- Lotes habitacionales de aprovechamiento comercial............. 8.96 veces\n2).- Lotes comerciales y de servicio con área de estacionamiento privado, se pagará de la siguiente manera:\n2.1).- Hasta 10 cajones................... 11.96 veces\n2.2).- De 11 a 20 cajones................. 23.91 veces\n2.3).- De 21 a 30 cajones................. 35.88 veces\n2.4).- Por cada cajón de estacionamiento adicional además de la cuota anterior 1. 1 2 v e c e s\n3).- Naves industriales, centros de abasto y almacenaje, andenes de carga y descarga, o cualquier uso similar...... 1 7. 93 veces\n3.1).- Por cada cajón de estacionamiento, además de la cuota anterior.......... 1.12 veces\n4).- Estaciones de servicio, de carburación o cualquier uso similar................ 32.88 veces\n4.1).- Por cada cajón de estacionamiento además de la cuota anterior.......... 1.12 veces\nd).- En caso de tratarse de edificaciones existentes o regularizaciones, a la cuota respectiva se le agregará el\n50%.\ne).- Por cada revisión subsecuente de un mismo trámite, siendo esto imputable al propietario, se cobrará por cada una el\n50% de la tarifa inicial.\nIII.- Por análisis y autorización de proyectos de señalamiento vial, se pagará de la forma siguiente:\na).- A fraccionamientos de cualquier tipo se pagará de la siguiente manera:\n1).- Hasta de 5 hectáreas.................. 71.76 veces\n2).- De 5 hasta 10 hectáreas............... 83.71 veces\n3).- De 10 hasta 20 hectáreas.............. 94.17 veces\n4).- De 20 hasta 40 hectáreas.............. 107.64veces\n5).- Por cada 5 hectáreas o fracción excedente por hectárea adicional....... 4.47 veces\nb).- Por análisis y elaboración de dictamen de señalamiento vial extra y dispositivos reductores de velocidad (topes) a escuelas particulares de cualquier nivel educativo y/o empresas privadas........................... 8.96 veces\nc).- Por análisis y elaboración de dictamen para la instalación de dispositivos reductores de velocidad (topes) a empresas y/o particulares 17.93 veces\nIV.- Por la opinión técnica del uso de la vía pública a empresas, escuelas o particulares en las siguientes modalidades:\na).- Para el cierre parcial y temporal de vialidades y/o andador peatonal (banqueta):\n1).- Eventos públicos....................... 22.42 veces\n2).- Eventos privados....................... 10.46 veces\n3).- Eventos deportivos:\n- Con fines de lucro................... 14.95 veces\n- Sin fines de lucro................... EXENTO\n4).- Eventos Religiosos, Educativos, Culturales, etc:\n- Con fines de lucro................... 10.46 veces\n- Sin fines de lucro................... 1.42 veces\nb).- Por emisión de opinión técnica para habilitar estacionamientos exclusivos....... 10.46 veces\n1).- Por emisión de opinión técnica para habilitar estacionamiento exclusivo en azul................................... 14.95 veces\nc).- Para carga y descarga o eventos especiales con horario establecido con un máximo de 5 horas por día............................... 8.96 veces\n- Por cada hora adicional................ 2.07 veces\nd).- Por cierre parcial (1 carril) de vialidad con horario establecido con un máximo de 5 horas por día............................... 1 0.38 veces\n1).- Por cierre parcial (1 carril) de vialidad por hora adicional hasta 23 horas................................. 2.07 veces\n2).- Por cierre parcial (1 carril) por 24 horas................................. 49.89 veces\ne).- Por cierre total de la vialidad con horario establecido con un máximo de 5.00 horas al día......................................... 62.87 veces\nV.- Por análisis y autorización de rutas de carga con transporte pesado dentro de la ciudad:\na).- Carga de 17 hasta 25 toneladas vigencia sesenta días sin un horario establecido:\n1).- A empresas con flota vehicular hasta de tres camiones...................... 14.95 veces\n2).- A empresas con flota vehicular hasta de diez camiones...................... 29.90 veces\n3).- A empresas con flota vehicular hasta veinte camiones....................... 59.80 veces\n4).- A empresas con flota vehicular mayor de veinte camiones, por cada vehículo adicional............................. 2. 2 5 veces\nb).- Carga mayor de 25 toneladas vigencia sesenta días:\n1).- A empresas con flota vehicular hasta de tres camiones...................... 29.90 veces\n2).- A empresas con flota vehicular hasta de diez camiones...................... 67.27 veces\n3).- A empresas con flota vehicular hasta veinte camiones....................... 89.70 veces\n4).- A empresas con flota vehicular mayor de veinte camiones, por cada vehículo adicional............................. 1 0. 4 6 veces\nc).- Ruta de carga de camiones pesados con vigencia de un día con horario establecido.. 7.47 veces\nd).- Vehículos de carga hasta de 25 toneladas:\n1).- Carga especial o con exceso de dimensiones por única vez y vigencia de horario nocturno................... 29.90 veces\n2).- Por cada tonelada adicional........... 4.47 veces\ne).- Para el tránsito de unidades foráneas sin ruta especifica determinada, se cobrará por unidad por día.............................. 44.85 veces\nVI.- Generalidades:\na).- Por definición de secciones viales para acciones de urbanización y/o instalación de infraestructura, por cada una............... 8.96 veces\nb).- Por análisis y autorización de rutas de infraestructura urbana por kilómetro o fracción, en vía pública................... 23.91 veces\nc).- Por análisis y autorización de proyectos de infraestructura urbana por kilómetro o fracción, en vía pública.................... 31.39 veces\nd).- Por análisis de proyectos de semaforización presentados por empresas o particulares..... 32.88 veces\ne).- Por análisis y factibilidad de proyectos geométricos y/o de señalamiento para integración vial............................ 23.91 veces\nf).- Por análisis y aprobación de proyectos geométricos y/o de señalamiento para integración vial............................ 47.83 veces\ng).- Por elaboración de aforos vehiculares dentro de la estructura vial de la ciudad (por estación, por día).......................... 23.91 veces\nh).- Por expedición de copias fotostáticas de aforos vehiculares (por estación, por día).. 5.98 veces\ni).- Por la emisión de factibilidad u opinión técnica a empresas y/o particulares de conceptos no previstos en esta Ley.......... 10.46 veces\nj).- Por expedición de copias fotostáticas de autorizaciones expedidas por el Departamento de Ingeniería de Tránsito.................... 5.82 veces\n1.- Copia de documentos la primera hoja.................................. 1. 0 0 veces\n2.- Por cada hoja subsecuente............. 0. 2 0 veces\nk).- Copia certificada y copia en formato digital sin incluir dispositivo:\n1.- Copia de documentos la primera hoja..... 1.56 veces\n2.- Por cada hoja subsecuente.............. 0. 4 0 veces\n3.- Por archivo digital de lineamiento vial. 4. 0 0 veces\n18 SERVICIOS QUE PRESTA EL DEPARTAMENTO DE CATASTRO MUNICIPAL\nARTÍCULO 45.- Los servicios que presta esta oficina, se pagarán conforme a la siguiente tarifa:\nUNIDAD DE MEDIDA Y\nACTUALIZACIÓN VIGENTE\nA.- POR EXPEDICIÓN DE DOCUMENTOS Y MODIFICACIÓN AL PADRÓN CATASTRAL:\nI.- Corrección de datos catastrales:\na).- Cambio de propietario.................. 2.50 veces\nb).- Cambio de valor unitario o superficie.. 2.00 veces\nc).- Cambio de tasa......................... EXENTO\nII.- Certificado catastral para constancia de libertad de gravámenes, por predio......... 5.00 veces\nIII.- Análisis de información:\na).- Para determinar la ubicación y/o superficie resultante previo a deslinde de un predio con clave de colonia urbana que no se encuentre catastrado y/o regularizado........... 9.00 veces\nb).- Para determinar la ubicación y/o superficie resultante previo a deslinde de un predio con clave rústica que no se encuentre catastrado y/o regularizado por cada\n20 hectáreas.......................... 20.00 veces\nc).- Revisión de la superficie asignadas en base a Indiviso de las unidades resultantes de un condominio, por unidad................................ 2.00 veces\nd).- Revisión de la superficie asignadas de la lotificación de los predios resultantes de nuevos desarrollos, por unidad................................ 1.50 veces\nIV.- Copias de documentos:\na).- Copia Simple, primera hoja............ 0.50 veces\nb).- Por hoja adicional.................... 0.080 veces\nV.- Por ampliación de vigencia de acta de deslinde o levantamiento certificado en original, hasta un año después de su fecha de despacho, por cada uno de los predios a certificar por única ocasión y que no exceda los 6 meses de su vencimiento.... 8.00 veces\nVI.- Certificación de documentos:\na).- Primera hoja.......................... 4.80 veces\nb).- Hoja adicional........................ 0.80 veces\nVII.- Cédula única catastral y Registral......... 5.00 veces\nVIII.- Constancia de registro catastral........... 10.00 veces\nIX.- Expedición de carta de no registro........... 1.50 veces\nX.- Certificación de copias de planos.......... 8.00 veces\nXI.- Valuación:\na).- Revisión de Avalúo Rústico fuera del área urbana, elaborado por perito valuador adscrito al padrón............ 9.20 veces\nb).- Certificación de avalúo elaborado por\nPerito Valuador Registrado en el\nPadrón Municipal...................... 7.40 veces\nc).- Avalúo de la Comisión Municipal de\nValuación solicitado por personas físicas o morales..................... 19.00 veces más el 1.05 al millar sobre el valor de avalúo\nd).- Inspección para análisis de valor catastral y/o tasa por predio a solicitud:\n1.- Dentro de los límites de la zona urbana........................... 4.20 veces\n2.- Fuera de la zona urbana de la\nCiudad de Mexicali dentro del límite de un centro de población. 6. 3 0 veces\n3.- Fuera de la zona urbana de la\nCiudad de Mexicali por cada kilómetro recorrido fuera del límite de un centro de población. 0.50 veces\nXII.- Elaboración y/o revisión de memoria descriptiva, por predio................ 2.31 veces\nXIII.- Análisis y ratificación de firmas de documento privado.......................... 16.58 veces\n2191, del capítulo VIII de la forma del contrato de Compra-Venta del Código Civil para el Estado de Baja California.\nXIV.- Constancia de no deslinde................. 7.40 veces del pago de los derechos a que se refiere este apartado.\nB.- ASIGNACIÓN DE CLAVE CATASTRAL:\nI.- En el registro de fraccionamientos, colonias regularizadas o modificaciones de predios, por cada clave:\nNo. de Predios UNIDAD DE MEDIDA Y\nPor cada uno ACTUALIZACIÓN VIGENTE\na).- De 1 a 100 claves catastrales......... 4.60 veces\nb).- De 101 en adelante.................... 3.50 veces\nII.- Asignación de clave catastral individual:\na).- Por cada predio urbano................. 5.00 veces\nb).- Por cada predio rústico.............. 8.00 veces\nIII.- Por el registro y otorgamiento de clave definitiva en el padrón, derivado de una resolución judicial........................ 8.00 veces\nIV.- Análisis para la asignación de claves catastrales en el proyecto de la modificación de predios.................... 3. 0 0 veces\nV.- Análisis técnico, documental y determinación de clave catastral provisional por trámite:\na).- Por cada predio...................... 1 5. 0 0 veces\nb).- Para predios con clave rústica hasta\nC.- NOMENCLATURA Y NÚMEROS OFICIALES:\nI.- Análisis y revisión de anteproyectos y autorización de proyectos de nomenclatura para nuevos desarrollos de fraccionamientos o condominios, con superficie hasta 5 has.\na).- Para Fraccionamientos menor o igual a\n5 has................................ 27.63 veces\nb).- Por Régimen en Condominio............ 32.24 veces\nc).- Por hectárea adicional o fracción.... 3.50 veces\nII.- Individuales:\na).- Por asignación y expedición de número oficial para predios con clave rústica 5.20 veces\nb).- Por asignación y expedición de número oficial para predios con clave de colonia urbana........................ 2.76 veces\nIII.- Fraccionamientos:\na).- Por asignación y autorización de números oficiales de proyectos para nuevos desarrollos de fraccionamientos o condominios:\n1.- Por autorización y asignación de números oficiales en plano de\nNuevos Fraccionamientos.......... 20.00 veces\n2.- Por Autorización y Asignación de números oficiales en proyecto de régimen en condominio............. 30.00 veces\nb).- Por expedición de boleta de número oficial\n1.- Por cada boleta expedida de número oficial................... 2. 3 1 veces\nc).- Por expedición de certificación de alineamiento:\n1.- Por cada certificado de alineamiento..................... 4.60 veces\nD.- SERVICIOS DE CARTOGRAFÍA Y PROCESOS:\nUNIDAD DE MEDIDA Y\nACTUALIZACIÓN VIGENTE\nI.- Cartografía digital de la ciudad de Mexicali escala\n1:1000, a nivel predio:\na).- Por el primer kilómetro cuadrado...... 72.76 veces\nb).- Por kilómetro cuadrado adicional...... 6.61 veces\nII.- Catálogo general de colonias formato digital.................................... 12.60 veces\nE.- POR TRABAJOS TÉCNICOS:\nI.- Perito deslindador autorizado por el Departamento de\nCatastro:\na).- Solicitud y aplicación de examen para ingresar al padrón de peritos deslindadores......................... 25.20 veces\nb).- Registro de perito deslindador........ 19.84 veces\nc).- Revalidación anual de peritos deslindadores......................... 19.84 veces\nII.- Referencias de ejes de fraccionamientos:\na).- Revisión en campo de ejes de fraccionamiento para proceso de entrega recepción..................... 5 2.92 veces\nb).- Por cada revisión en campo adicional.. 13.23 veces\nc).- Por análisis y colocación física de referencia de ejes dentro del límite de centro de población por intersección... 18.90 veces\nIII.- Deslinde de predios:\n1.- Elaboración de deslinde y levantamientos en zonas urbanas control comprobados:\nSUPERFICIE EN HECTÁREAS\nUNIDAD DE MEDIDA Y\nACTUALIZACIÓN VIGENTE\nMAYOR DE: HASTA: PARA DESLINDE: PARA LEVANTAMIENTO:\n1.00 500.00 M² 28.12 veces 22.50 veces\n500.01 1,000.00 M² 39.65 veces 31.72 veces\n1,000.01 2,000.00 M² 47.45 veces 37.96 veces\n2,000.01 4,000.00 M² 66.76 veces 53.41 veces\n4,000.01 6,000.00 M² 88.93 veces 71.15 veces\n6,000.01 8,000.00 M² 110.38 veces 88.31 veces\n8,000.01 10,000.00 M² 131.85 veces 105.48 veces\nSUPERFICIE EN HECTÁREAS\nUNIDAD DE MEDIDA Y\nACTUALIZACIÓN VIGENTE\nMAYOR DE: HASTA: PARA DESLINDE: PARA LEVANTAMIENTO:\n1-00-00 5-00-00 177.31 veces 141.85 veces\n5-00-00 10-00-00 241.62 veces 193.30 veces\n10-00-00 15-00-00 313.16 veces 250.53 veces\n15-00-00 20-00-00 384.68 veces 307.75 veces\n20-00-00 30-00-00 491.66 veces 393.33 veces\n30-00-00 40-00-00 635.01 veces 508.01 veces\na).- En caso de que durante la verificación física de un levantamiento o deslinde no se presente el perito deslindador responsable, se cobrará un costo adicional por..................................... 1 0.00 veces\nb).- En caso de que durante la verificación física de un levantamiento o deslinde no se encuentren los puntos o ligas que delimitan el predio en cuestión, se cobrará un costo adicional por.......... 1 0.00 veces\nc).- El procedimiento de certificación de deslinde tendrá como máximo dos revisiones por parte del analista, a partir de la tercera corrección se cobrará al perito firmante un adicional por cada revisión... 1 0.00 veces\n2.- En las zonas urbanas irregulares o carentes de puntos de control y ejes físicos definidos, se les incrementará 25% a las cuotas del punto número 1.\n3.- Para predios ubicados fuera de la zona urbana pero dentro de los límites del centro de población de Mexicali se les aplicarán los mismos valores del número anterior.\n4.- Los predios cuya superficie excede de las 150-00-00 hectáreas pagarán los derechos de deslinde de acuerdo al presupuesto que al efecto realice el Departamento de\nCatastro Municipal, el que en todo caso será equivalente al costo del servicio y previa solicitud del interesado.\n5.- A los predios ubicados dentro de los límites de centros de población que no sean cabecera municipal, además de las cuotas anteriores se les acumulará 0.40 veces la Unidad de la ciudad.\n6.- Para terrenos semicerriles o lomeríos, los cuales para uniformes menores de 30 grados, tendrán las cuotas anteriores un incremento de 40%, los terrenos cerriles, pendientes mayores de 30 grados, tendrán un aumento del 75% a las cuotas establecidas.\nIV.- Levantamiento de predios, se pagará el 25% más del costo de los deslindes, de acuerdo a los rangos establecidos en los incisos anteriores.\nCatastro Municipal, el que en todo caso, será equivalente al costo del servicio y previa solicitud del interesado.\n2.- A los predios ubicados fuera del centro de población de\nMexicali, además de las cuotas anteriores se les acumulará\n0.37 veces la Unidad de Medida y Actualización vigente para cada kilómetro fuera de la ciudad.\n3.- Para terrenos semicerriles o lomeríos, los cuales para efectos fiscales se considerarán aquellos de pendientes uniformes menores de 30 grados tendrán las cuotas anteriores un incremento de 40%, los terrenos cerriles, considerándose para efecto aquellos con cambios bruscos de pendientes mayores de 30 grados, tendrán un aumento del 75% a las cuotas establecidas.\n4.- En zonas urbanas o suburbanas irregulares o fuera de los límites de los centros de población donde no exista la totalidad de los ejes físicos y puntos de control definidos, que requieran análisis extraordinarios se cobrará un 50% adicional a las cuotas anteriores de deslindes.\n5.- Los trabajos de levantamiento, deslinde o estudio, cálculo y verificación física de planos para efectos de certificación catastral de predios ubicados en lugares causarán una cuota adicional, equivalente a los gastos de transporte, alojamiento y alimentación del personal que se utilice.\nV.- Verificación física de deslinde de predio, para colocación de con vigencia menor a 3 años a solicitud del interesado, se pagará un 50% del costo de los deslindes o levantamiento, de acuerdo a los rangos establecidos en los incisos anteriores.\nVI.- Certificación de deslindes y/o levantamiento para el estudio, Catastro Municipal, se pagará de acuerdo a lo que causen por el servicio de deslindes o levantamiento de los predios, de conformidad con la siguiente tabla:\n1.- Hasta 10,000 m².............................. 35.00 %\n2.- Mayor de 1 hasta 20 hectáreas................ 30.00 %\n3.- Mayor de 20 hectáreas........................ 27.50 %\n4.- Los predios cuya superficie excede de los 150-00-00 Has, pagarán los derechos de certificación de acuerdo al presupuesto que para tal efecto realice el Departamento de\nCatastro Municipal.\nEn caso de no realizarse el o los servicios previstos en el presente artículo, por causas imputables al solicitante y se compruebe por parte del Departamento de Catastro, se llevará a cabo la devolución del 25% del pago efectuado.\nVII.- En la certificación de deslindes urbanos, que se requiera en carácter de urgente se cobrará tres veces el valor que se especifica en el Artículo 45, inciso E, fracción III.\nVIII.- Verificación física de deslinde de predio para certificación a partir de la segunda revisión en campo.\na). Dentro de los límites de la zona urbana...... 6.61 veces\nb). Fuera de la zona urbana de la Ciudad de\nMexicali, dentro del límite de un centro de población.................................... 7.93 veces\nc). Fuera de la zona urbana de la Ciudad de\nMexicali, por cada kilómetro recorrido fuera del límite de un centro de población......... 0.40 veces\n19 SERVICIOS QUE PRESTA LA DIRECCIÓN DE PROTECCIÓN AL AMBIENTE\nARTÍCULO 46.- Los servicios que presta esta Dirección en materia\nAmbiental se pagarán conforme a lo siguiente:\nI.- Por la recepción y evaluación de documentos para resolver respecto a la licencia ambiental municipal:\nUNIDAD DE MEDIDA Y\nACTUALIZACIÓN VIGENTE\na).- Por la recepción y evaluación de la solicitud de naves industriales y/o fraccionamientos, por hectárea................................ 75.00 veces\nb).- En caso de construcción de centro de acopio:\n1).- Residuos sólidos urbanos............... 126.00 veces\n2).- Residuos de manejo especial............ 189.00 veces\nc).- Para la operación de centro de acopio, separación o aprovechamiento de residuos sólidos urbanos:\n1).- Primera vez........................... 132.30 veces\n2).- Revalidación anual.................... 66.00 veces\nd).- Para la construcción de comercios y/o servicios con una superficie de:\n1).- Hasta 150 m²........................... 18.90 veces\n2).- Mayor a 151 m² y hasta 500 m².......... 33.00 veces\n3).- Mayor a 501 m² y hasta 1,000 m²........ 48.00 veces\n4).- Mayor a 1,001 m² y hasta 2,000 m²..... 60.00 veces\n5).- Mayor a 2,001 m2...................... 87.00 veces\ne).- Para actividades comerciales y/o de servicios:\n1).- Con superficie de construcción hasta\n100 m²:\n1.1).- Primera vez........................ 12.60 veces\n1.2).- Revalidación anual................. 4.00 veces\n2).- Con superficie de construcción mayor a\n101 m² y hasta 500 m²:\n2.1).- Primera vez........................ 25.20 veces\n2.2).- Revalidación anual................. 7.56 veces\n3).- Con superficie de construcción mayor de\n501 m² y hasta 1,000 m²:\n3.1).- Primera vez........................ 45.36 veces\n3.2).- Revalidación anual................. 13.36 veces\n4).- Con superficie de construcción mayor a\n1,001 m²:\n4.1).- Primera vez........................ 60.48 veces\n4.2).- Revalidación anual................. 22.68 veces\nf).- Por licencia ambiental para comercios o servicios ingresada por el sistema de apertura rápida hasta 100 m² de superficie de construcción.................. 1 2. 60 veces\ng).- Por la recepción y evaluación de la solicitud de la licencia ambiental para el aprovechamiento de materiales pétreos, por hectárea................................... 208.00 veces\n1).- Revalidación anual por hectárea........ 104.00 veces\nh).- Por recepción, análisis, y en su caso registro del Plan de Residuos de Manejo Especial de pequeños generadores, vigencia anual........ 75.00 veces\nII.- Otros Dictámenes y Servicios en Materia Ambiental:\na).- Por la emisión de dictámenes técnicos y de factibilidad ambiental:\nEn todos los casos.......................... 39.69 veces\nb).- Por la emisión de autorizaciones para la recolección y transporte de:\n1).- Residuos sólidos urbanos, No-peligrosos o de manejo especial:\nNeumáticos usados, de la construcción o demolición, por cada vehículo anual.... 26.46 veces\n2).- Aguas residuales, por cada vehículo anual.................................. 13.23 veces\nc).- Por permiso para la remoción y/o trasplante de árboles y otras plantas:\nPor cada organismo vegetativo............... 6.61 veces\nSe exime el pago en caso de solicitud o permiso por remoción de troncos de árboles secos.\nSe exime del pago cuando se considere dentro del programa de rehabilitación de adopción de espacios públicos.\nd).- Copia de documentos por expediente por fojas:\nDe 26 a 50.................................. 2.64 veces\nDe 51 en adelante........................... 3.96 veces\ne).- Por la recepción y evaluación de solicitudes de prórrogas................... 2.64 veces\nf).- Por la autorización ambiental para la utilización de equipos de perifoneo en unidades móviles hasta 30 días.............. 6.61 veces\ng).- Por autorización ambiental para la utilización de equipo de sonido en establecimientos comerciales y de servicios:\nPor 30 días................................. 63.00 veces\nh).- Por la autorización ambiental anual para la utilización de anuncios luminosos de fuentes fijas en establecimientos comerciales y de servicios................................... 2 2.36 veces\ni).- Por autorización ambiental para la utilización de anuncios luminosos en unidades móviles hasta por 6 meses.......... 1 3.23 veces\nj).- Por dictamen relativo a áreas verdes dentro de fraccionamientos habitacionales e industriales:\n1).- De 1 a 10 hectáreas................... 37.80 veces\n2).- De 11 a 50 hectáreas.................. 89.76 veces\n3).- De 51 en adelante...................... 141.72 veces\nk).- Por dictamen relativo a la arborización de estacionamientos mayores a 9 cajones........ 37.80 veces\nl).- Por el estudio y evaluación de factibilidad para formar parte del padrón de prestadores de servicios ambientales.................. 6.30 veces\nm).- Por la inscripción al padrón de prestadores de servicios ambientales................. 10.08 veces\nn).- Por la evaluación para permanecer inscrito en el padrón de prestadores de servicios ambientales................................ 3.78 veces ñ).- Por la recepción, evaluación y dictamen de los estudios técnicos justificativo y manifiesto de impacto ambiental para determinar la factibilidad del cambio de uso de suelo fuera del centro de población de\nMexicali con base en el Programa de\nOrdenamiento Ecológico local, se deberá cubrir las siguientes cuotas:\n1).- De 1 a 5 hectáreas.................... 36.00 veces\n2).- De más de 5 hectáreas hasta 10 hectáreas 56.00 veces\n3).- De más de 10 hectáreas hasta 15 hectáreas 75.00 veces\n4).- De más de 15 hectáreas en adelante.... 95.00 veces\no).- De la recepción, evaluación y resolución del manifiesto de impacto ambiental para determinar la compatibilidad de la actividad promovida con el Programa de Ordenamiento\nEcológico Local, se deberán cubrir las siguientes cuotas:\n1).- De 1 a 5 hectáreas.................... 61.00 veces\n2).- De más de 5 hectáreas hasta 10 hectáreas 123.00 veces\n3).- De más de 10 hectáreas hasta 15 hectáreas 185.00 veces\n4).- De más de 15 hectáreas en adelante.... 248.00 veces\n20 SERVICIOS QUE PRESTA LA DIRECCIÓN DE SERVICIOS PÚBLICOS\nMUNICIPALES\nARTÍCULO 47.- Los derechos por estos servicios, se pagarán conforme a lo siguiente:\nPANTEONES MUNICIPALES\nUNIDAD DE MEDIDA Y\nACTUALIZACIÓN VIGENTE\nI.- Exhumaciones.................................. 10.58 veces\nII.- Inhumaciones de restos humanos................. 2.46 veces\nIII.- Inhumaciones a perpetuidad, en hora hábil...... 39.69 veces\nIV.- Inhumaciones a perpetuidad en hora inhábil..... 52.92 veces\nV.- Apertura de fosa............................... 13.23 veces\nVI.- Permiso para instalación o remodelación de lápidas...................................... 2.46 veces refiere este artículo, las personas físicas, jurídicas o unidades económicas, que presten los servicios.\nRECOLECCIÓN DE BASURA\nARTÍCULO 48.- Los derechos por el servicio de recolección de basura en recipientes comunales o que tengan carácter extraordinario, que preste el Ayuntamiento a giros comerciales, industriales o de servicio, la ubicación, superficie del terreno, periodicidad del servicio y otros elementos que impacten en el costo del mismo. enajenación de bienes propios del Ayuntamiento de Mexicali, consistente en materia de Reciclaje que deberá ser separado del resto del contenido recolectado, conforme lo establezca el reglamento correspondiente para la enajenación de bienes muebles.\nSERVICIOS DE LIMPIEZA, TAPIADO Y DEMOLICIÓN\nARTÍCULO 49.- Los derechos por los servicios de limpieza, tapiado o demolición en domicilios particulares, predios baldíos, comercios y otros, serán fijados en cada caso por la Autoridad Municipal dependiendo de la ubicación y superficie del terreno, periodicidad de servicio y otros elementos que impacten en el costo del mismo, se otorgará hasta un 50% de descuento a todos los adeudos que tengan un retraso en el pago por este concepto por el presente ejercicio y rezagos.\nSERVICIOS POR UTILIZACIÓN DEL SITIO DE DISPOSICIÓN FINAL DE RESIDUOS\nSÓLIDOS MUNICIPALES\nARTÍCULO 50.- Los servicios por utilización del sitio de disposición final de residuos sólidos municipales, se pagarán conforme a lo siguiente:\nI.- ESTACIÓN DE TRANSFERENCIA DE LA CIUDAD\nUNIDAD DE MEDIDA Y\nACTUALIZACIÓN VIGENTE\na).- Particulares que en forma esporádica y por sus propios medios depositan residuos de su propiedad, excepto escombro, siempre que no exceda de camión de 1½ toneladas y de tres metros de longitud.......................... EXENTO\nb).- Residuo sólido urbano por tonelada.......... 2.46 veces\nc).- Residuo sólido urbano voluminoso, o diferente al doméstico por tonelada......... 2.46 veces\nII.- ESTACIÓN DE TRANSFERENCIA DEL VALLE Y RELLENO SANITARIO\nUNIDAD DE MEDIDA Y\nACTUALIZACIÓN VIGENTE\na).- Pick-up (con o sin redilas) con basura doméstica por cada ocasión................. EXENTO\nb).- Pick-up (con o sin redilas) con basura comercial por cada ocasión................. 1.99 veces\nc).- Camión de una tonelada por cada ocasión.. 2.44 veces\nd).- Camión cerrado o de redilas hasta 6 mts. de largo por cada ocasión..................... 5.29 veces\ne).- Particulares, que en forma esporádica y por sus propios medios depositan desechos de su propiedad, excepto escombro, siempre que no exceda de camión de 1½ toneladas........... EXENTO\nIII.- RELLENO SANITARIO\na).- Particulares, que en forma esporádica y por sus propios medios depositan residuos de su propiedad, excepto escombro, siempre que no exceda de camión de 1½ toneladas y de tres metros de longitud......................... E X ENTO\nb).- Residuo sólido urbano por tonelada......... 1.99 veces\nc).- Residuo sólido urbano, voluminoso o diferente al doméstico por tonelada........ 2.46 veces\n21 SERVICIOS QUE PRESTA LA DIRECCIÓN DE OBRAS PÚBLICAS\nARTÍCULO 51.- Servicios por Supervisión, Licencias de Autorización, Obras de Señalamiento Vial, Constancias de Cumplimiento y\nUrbanización.\nI.- SERVICIOS POR URBANIZACIÓN en campo que incluya la topografía, infraestructura e instalaciones, estructura de pavimentos, geometría y otros, en la ejecución de obras de urbanización de terrenos que serán destinados a vías públicas, se pagará sobre el importe total de los presupuestos presentados al\nDepartamento de Control Urbano, el 2%.\nLos presupuestos presentados se revisarán conforme al tabulador de precios unitarios de infraestructura de la Secretaría de\nInfraestructura y Desarrollo Urbano del Gobierno del Estado de Baja\nCalifornia.\nLas colonias populares con urbanización mínima promovidas por\nOrganismos Gubernamentales, pagarán un 50% de la tarifa anterior.\nA los urbanizadores y/o promotores inmobiliarios que promuevan fraccionamientos para construcción de vivienda tipo interés social en donde construyan como mínimo un 25% viviendas tipo económicas del total de los lotes habitacionales que esté desarrollando en el municipio de\nMexicali, les será devuelta la cantidad que resulte de multiplicar el número de viviendas económicas inscritas en el Registro Público de la\nPropiedad y de Comercio del Estado a favor de terceros adquirientes por $ 1,104.00 pesos Moneda Nacional.\nEsta devolución será aplicable como máximo hasta cubrir la cantidad total de los derechos de urbanización calculados. valor no exceda los 55,000 UDIS.\nPrevia devolución de la cantidad antes señalada los urbanizadores y/o como mínimo la cantidad de $ 800.00 pesos Moneda Nacional. Dichos de edificaciones de la Dirección de Obras Públicas Municipales.\nII.- SERVICIOS POR OBRA\nUNIDAD DE MEDIDA Y\nACTUALIZACIÓN VIGENTE pública, para la ejecución de obras públicas o privadas se cobrará conforme a la siguiente tarifa:\na).- De piso, vía pública en lugar no pavimentado, por metro cuadrado o fracción. 1.32 veces\nb).- De calles revestidas de grava conformada, por metro cuadrado o fracción.............. 3.31 veces\nc).- De concreto hidráulico o asfáltico, por metro cuadrado o fracción.................. 5. 2 9 v eces\nd).- De guarniciones y banquetas de concreto, por metro lineal o fracción............... 1.32 veces\ne).- De banquetas de concreto, por metro cuadrado o fracción.................................. 3.31 veces\nEn cualquiera de los casos previstos en los incisos a), b), c), d) y\ne) estarán exentas las Dependencias pertenecientes a los Municipios, cuando la acción resulte para fines administrativos y propósitos de objeto público, así mismo estarán exentos los particulares cuando la obra tenga por objeto mejorar la imagen urbana o reponer el pavimento.\nPúblicas.\nCuando la ruptura de la banqueta y/o vialidad tenga como propósito su reposición sin modificar su trazo y estructura, así como mejorar la imagen urbana, se considera EXENTO. Sin que lo anterior libere al correspondiente ante la Dirección de Obras Públicas.\nPara el otorgamiento de las exenciones previstas en esta fracción, deberá contarse con la validación de la Dirección de Obras Públicas.\nEn caso de no realizar el trámite, este no se considerará exento de incisos f) y g) de esta fracción.\nEn cualquiera de los casos previstos en los incisos anteriores, cuando instalación aérea por una subterránea, se considerará EXENTO. Sin que oportunamente el trámite correspondiente ante la Dirección de Obras\nPúblicas.\nEn caso de no realizar el trámite, este no se considerará exento de cobro y se hará acreedor a cualesquiera de las multas señaladas en los incisos f) y g) de esta fracción.\nf).- Multa del 150% del valor de la licencia o permiso a quien cometa la infracción de romper piso, calles revestidas de grava conformada, pavimento de concreto hidráulico o asfaltico, guarnición y banquetas de concreto de la vía pública sin haber realizado el trámite y pago correspondiente ante la Dirección de Obras\nPúblicas Municipales para el otorgamiento de la licencia o permiso de ruptura.\nLa multa señalada en la fracción f) se cobrará en base al valor de la licencia o permiso y su cobro es adicional al pago del derecho por la expedición de la licencia de autorización por romper, piso, calles revestidas de grava conformada, pavimento de concreto hidráulico o asfaltico, guarnición y banquetas de concreto de la vía pública.\ng).- Multa del 150% del valor de la licencia o alterar o modificar el pavimento, guarnición o banqueta en la vía pública en las colonias o fraccionamientos destinadas a rampas vehiculares construidas por los ciudadanos para el acceso de un segundo vehículo a la vivienda, sin haber realizado el trámite ante la Dirección de Obras Públicas Municipales para otorgar la licencia o permiso de ruptura, alteración o modificación.\nLa multa señalada en la fracción g) se cobrará en base al valor de la licencia o permiso y la expedición de la licencia de autorización por romper, alterar o modificar el pavimento, guarnición o banqueta de la vía pública en las colonias o fraccionamientos, destinadas a rampas vehiculares.\nIII.- SERVICIOS DE MANTENIMIENTO A VIALIDADES\nPor la construcción de topes o retiro de los mismos con cargo a los solicitantes, así como instalación de altos de discos a giros comerciales y escuelas privadas, que cuenten con autorización de la\nDirección de Administración Urbana, tarifa:\na).- Construcción de topes a base de carpeta asfáltica.\nUnidad de medida: metros lineales.......... 15.87 veces\nb).- Construcción de topes a base de boyas metálicas.\nUnidad de medida: metros lineales.......... 22.65 veces\nc).- Retiro de topes.\nUnidad de medida: metros lineales.......... 7.93 veces\nd).- Instalación de altos de disco.\nUnidad de medida: pieza.................... 32.42 veces\nIV.- IMPLEMENTACIÓN DE CRUCES PEATONALES, ZONAS COMERCIALES Y ESCUELAS\nPRIVADAS. comerciales y escuelas privadas, que cuenten con autorización de la\nDirección de Administración Urbana, tarifa:\na).- En cruces peatonales.\nUnidad de medida: metros cuadrados......... 1.99 veces\nb).- En cordones.\nUnidad de medida: metros lineales.......... 1.32 veces\nc).- En líneas de pavimento.\nUnidad de medida: metros lineales.......... 0.20 veces\nV.- SERVICIOS POR EXPEDICIÓN DE CONSTANCIAS DE URBANIZACIÓN\nPor la expedición de “constancia de terminación de obra y liberación de garantías” se pagará de acuerdo a la siguiente tarifa:\na).- Para fraccionamientos dentro del centro de población.................................. 66.15 veces\nb).- Para fraccionamientos fuera del centro de población.................................. 92.61 veces\nVI.-POR CONSTANCIA DE CUMPLIMIENTO DE REQUISITOS PARA TRASLACIÓN DE\nDOMINIO EN DESARROLLOS URBANOS\na).- De 1 a 50 lotes solicitados................ 66.15 veces\nb).- Por cada lote adicional.................... 1.38 veces\nDe ser necesario una segunda revisión, se deberá cubrir el 50% de los antes dispuesto según rango.\nVII.- POR EL ALTA EN EL PADRÓN DE CONTRATISTAS Y PROVEEDORES CON\nVIGENCIA ANUAL, A QUIEN LO SOLICITE:\na).- Por el alta o renovación anual............. 7.35 veces\nVIII.- BASES DE LICITACIÓN PARA OBRA PÚBLICA:\na).- Expedición de bases para licitación Pública.. 20.00 veces\nb).- Expedición de bases para invitación simplificada a cuando menos tres contratistas 1 0. 00 veces las bases de licitación podrán entregarse gratuitamente.\n22 EXPEDICIÓN DE CERTIFICADOS, TÍTULOS O COPIAS DE DOCUMENTOS\nARTÍCULO 52.- Los certificados, copias certificadas, legalización de\nDependencias Municipales, de los cuales no exista tarifa específica en otro apartado de esta Ley, se pagarán conforme a la siguiente tarifa:\nUNIDAD DE MEDIDA Y\nACTUALIZACIÓN VIGENTE\nI.- Certificación en general por documento.......... 1.32 veces\nII.- Tratándose de certificación de expedientes, por cada hoja....................................... 0.209 veces\nIII.- Expedición de títulos de propiedad o contratos de compraventa.................................. 19.84 veces\nIV.- Certificado de residencia....................... 1.32 veces\nV.- Carta de residencia para obtener la tarjeta del\nINAPAM.......................................... EXENTO\nVI.- Expedición de Certificado de Vecindad........... 6.61 veces\nVII.- Certificado de Arraigo.......................... 6.61 veces\nVIII.- Certificación de firmas de Constitución de\nSociedades Cooperativas......................... 13.23 veces\na).- Copia adicional de la Certificación........ 3. 9 6 veces\nb).- Certificación de actas de asambleas........ 6.61 veces\nIX.- Constancia de Origen............................ 6.61 veces\nX.- Formato de declaración para el pago del Impuesto\nSobre Adquisición de Inmuebles de 1 a 10 formas. 0.18 vez c/u\na).- De 11 a 50 formas.......................... 0.17 vez c/u\nb).- De 51 a 100 formas......................... 0.16 vez c/u\nc).- De 101 en adelante......................... 0.15 vez c/u\nXI.- Registro peritos valuadores, pago único......... 19.84 veces\nXII.- Revalidación anual de peritos valuadores........ 19.84 veces\nXIII.- Por revisión de avalúo por clave Catastral...... 5. 29 veces\nXIV.- Copia:\na).- Fotostática simple......................... 0.0209 veces\nb).- Por copia digital.......................... 0.0209 veces\nSe entenderá por copia digital la que conste en archivo digital o sistema de cómputo.\nc).- Por copia simple o digitalizada que requiera testarse.......................... 0. 2 2 veces\nd).- Cuando implique la entrega de no más de veinte hojas.............................. E X E N TO\nXV.- Emisión de estados de cuenta del Impuesto Predial:\na).- De 1 a 10.................................. EXENTO\nb).- De 11 en adelante.......................... 0.018 vez c/u\nXVI.- Por servicio del cobro y entrega a domicilio del recibo de pago del impuesto predial (hasta dos trámites en un mismo domicilio)................. 1.32 veces\nXVII.- Certificado de no adeudo para licitaciones y proveedores del Ayuntamiento.................... 1.99 veces\nXVIII. Certificado de no adeudo para revalidación de\n- permisos por establecimiento.................... 1.99 veces\nXIX.- Certificado de no adeudo para revalidación del\nPermiso de alcoholes y establecimientos para eventos sociales................................ 1.99 veces\nXX.- Certificado de no adeudo para revalidación vehicular....................................... EXENTO\nXXI.- Expedición de Constancia de Presentación de la\nDeclaración de Situación Patrimonial y de con la presentación de la Declaración Fiscal. 6.61 veces\nXXII.- Bases de Licitación para adquisiciones, arrendamientos o servicios:\na).- Expedición de bases para licitación local o regional.................................. 1 5. 0 0 veces\nb).- Expedición de bases para licitación nacional.................................... 3 0. 0 0 veces\nEn casos excepcionales se podrá establecer en la convocatoria que las bases de licitación podrán entregarse gratuitamente.\n23 UNIDAD MUNICIPAL DE PROTECCIÓN CIVIL\nARTÍCULO 53.- Los servicios que presta la Unidad Municipal de\nProtección Civil a los inmuebles e instalaciones fijas y móviles de las dependencias, entidades, instituciones, organismos, industrias o empresas, pertenecientes a los sectores público, privado y social, se pagarán conforme a la siguiente tarifa:\nI.- Por la elaboración y/o asesoría de programas específicos en materia de Protección Civil:\nUNIDAD DE MEDIDA Y\nACTUALIZACIÓN VIGENTE\na).- Asesoría para elaboración de programa interno de Protección Civil por m² de construcción:\nHasta 90 m²................................. 132.30 veces\nDe 91 a 500 m².............................. 198.45 veces\nDe 501 a 1,000 m²........................... 396.90 veces\nDe 1,001 m² en adelante..................... 793.80 veces\nb).- Elaboración de análisis de vulnerabilidad y riesgo:\n1.- Revisión para la aprobación de estudios de análisis de riesgos para la licencia de construcción:\nHasta 90 m²................................. 65.52 veces\nDe 91 a 500 m².............................. 132.30 veces\nDe 501 a 1,000 m²........................... 264.60 veces\nDe 1,001 m² en adelante..................... 529.20 veces\n2.- Elaboración de Dictamen de Estabilidad\nEstructural:\nHasta 90 m²................................. 81.90 veces\nDe 91 a 500 m².............................. 138.60 veces\nDe 501 a 1,000 m²........................... 270.60 veces\nDe 1,001 m² en adelante..................... 567.00 veces\n3.- Para uso y ocupación.\nFijos por m² de construcción:\nHasta 90 m²................................. 105.84 veces\nDe 91 a 500 m².............................. 198.45 veces\nDe 501 a 1,000 m²........................... 330.75 veces\nDe 1,001 m² en adelante..................... 661.50 veces\nc).- Dictamen de factibilidad en materia de\nProtección Civil............................ 132.30 veces\nPara los servicios a que se refiere esta fracción, en población fuera de la zona urbana pagarán 10 veces la Unidad de Medida y Actualización vigente adicional hasta cien kilómetros, después de cien kilómetros pagará 15 veces la Unidad de Medida y Actualización vigente adicionales.\nII.- Por revisión y autorización de programas específicos en materia de Protección Civil:\nUNIDAD DE MEDIDA Y\nACTUALIZACIÓN VIGENTE\na).- Eventos temporales masivos:\nHasta 300 personas.......................... 13.86 veces\nDe 301 a 500 personas....................... 26.46 veces\nDe 501 a 1,000 personas..................... 52.92 veces\nDe 1,001 a 3,000 personas................... 79.38 veces\nDe 3,001 a 6,000 personas................... 105.84 veces\nDe 6,001 en adelante........................ 132.30 veces\nb).- Programa interno de Protección Civil:\n1.- Por primera revisión:\nHasta 120 m²................................ 44.10 veces\nDe 121 a 500 m²............................. 73.08 veces\nDe 501 a 1,000 m²........................... 146.16 veces\nDe 1,001 m² en adelante..................... 291.06 veces\n2.- Por segunda revisión........................ 7.56 veces\n3.- Por tercera revisión........................ 7.56 veces\nEdificios de Gobierno Municipal, escuelas públicas y casas hogar, quedan exentos del cobro de derechos por este rubro.\nIII.- Multas por incumplir o no contar con el programa interno de\nProtección Civil: sanción del 30% por el incumplimiento al Programa Interno de Protección legislación en materia, en caso de reincidencia se aplicará una sanción por el 100% del mismo con independencia de la suspensión parcial o total que pudiera aplicarse.\nIV.- Servicios de Capacitación:\nCursos que se Imparten.\nUNIDAD DE MEDIDA Y\nACTUALIZACIÓN VIGENTE\na).- Nivel básico en primeros auxilios para el primer respondiente:\n1.- Hasta 25 personas...................... 26.46 veces\n2.- De 26 hasta 50 personas................ 46.30 veces\n3.- De 51 hasta 100 personas............... 66.15 veces\nb).- Búsqueda y rescate:\n1.- Hasta 25 personas...................... 26.46 veces\n2.- De 26 hasta 50 personas................ 46.30 veces\n3.- De 51 hasta 100 personas............... 66.15 veces\nc).- Rutas de evacuación y señalización:\n1.- Hasta 25 personas...................... 26.46 veces\n2.- De 26 hasta 50 personas................ 46.30 veces\n3.- De 51 hasta 100 personas............... 66.15 veces\nd).- Formación de unidades internas de Protección\nCivil...................................... 66.15 veces\ne).- Elaboración de programas internos de\nProtección Civil............................ 66.15 veces\nf).- Elaboración de análisis de riesgo........... 66.15 veces\ng).- Otros no especificados...................... 13.23 veces\nEn el caso de los tres primeros cursos que se menciona, el cupo máximo será de 100 personas.\nQuedan exentas del cobro, escuelas públicas y casas hogar; así mismo como los que encuadren en el supuesto del artículo 19 de la presente\nLey.\nV.- Asistencia y evaluación presencial en un\nSimulacro:....................................... 12.60 veces\nQuedan exentas del cobro las escuelas públicas y casas hogar; así mismo como los que encuadren en el supuesto del artículo 19 de la presente\nLey.\nVI.- Otros Servicios:\nUNIDAD DE MEDIDA Y\nACTUALIZACIÓN VIGENTE\na).- Otros servicios no especificados....... 13.23 veces\n24 CENTRO HISTÓRICO\nARTÍCULO 54.- Los servicios que presta el Museo Wok y Centro Histórico, se pagarán conforme a las siguientes tarifas:\nTARIFA\nMONEDA NACIONAL\nI.- Museo Wok:\na).- Entrada al Museo.............................. $ 25.00 M.N.\nb).- Recorridos guiados en el Museo................ $ 40.00 M.N.\nc).- Recorridos guiados para escuelas públicas por persona....................................... $ 35.00 M.N.\nd).- Recorridos guiados para escuelas privadas por persona....................................... $ 50.00 M.N.\ne).- Entrada a festivales al Museo................. $ 150.00 M.N.\nf).- Presentaciones artísticas en el Museo.......... $ 110.00 M.N.\ng).- Inscripción a cursos de pintura china.......... $ 725.00 M.N.\nh).- Paquete de cursos de pintura china............. $2,400.00M.N.\ni).- Inscripción a cursos de idioma chino........... $ 725.00 M.N.\nj).- Paquetes de cursos de idioma chino............. $2,400.00M.N.\nk).- Renta de vestíbulo del Museo Wok............... $1,590.00M.N.\nl).- Renta de sótano del Museo Wok.................. $3,180.00M.N.\nm).- Renta de galería temporal Museo Wok............ $1,060.00M.N.\nn).- Renta de espacios en colectivo Museo Wok mensual $ 106.00 a\n$ 530.00 M.N.\nII.- Centro Histórico:\n1).- Renta de Carretas Chinas por 7 días........... $ 250.00 M.N.\nDeberá de contar con los permisos necesarios vigentes, requeridos por la Dirección de\nComercio Ambulante.\nCAPÍTULO III\n4 OTROS DERECHOS\nCAPÍTULO IV\n5 ACCESORIOS DE DERECHOS\n01 ACCESORIOS DE DERECHOS\nARTÍCULO 55.- Son los ingresos que se perciben por concepto de recargos, sanciones, gastos de ejecución, indemnizaciones, entre otros, asociados a los derechos, cuando éstos no se cubran oportunamente, de conformidad con lo siguiente:\nI.- Recargos por mora: Cuando no se paguen las contribuciones dentro de los plazos señalados en las disposiciones fiscales o no se cubran las parcialidades en los plazos convenidos, se pagarán recargos por mora a la tasa del 2% mensual.\nII.- Recargos por financiamiento: Cuando se conceda prórroga para el pago de créditos fiscales o para que los mismos sean cubiertos en parcialidades, se causarán recargos por financiamiento sobre el saldo insoluto a la tasa del 1.5% mensual.\nIII.- Sanciones: Las multas derivadas del incumplimiento en el pago de contribuciones en la forma, fecha y términos que establezcan en esta Ley y en las disposiciones fiscales respectivas.\nIV.- Gastos de Ejecución: Cuando las autoridades fiscales la recuperación de los créditos fiscales que correspondan, se estará a lo establecido en el \"Capítulo VIII. De los\nGastos de Ejecución\" de la Ley de Hacienda Municipal del\nEstado de Baja California.\nV.- Otros: Todos aquellos que se encuentren asociados o establecidos en las leyes fiscales.\nCAPÍTULO V\n9 DERECHOS NO COMPRENDIDOS EN LA LEY DE INGRESOS VIGENTE, CAUSADOS\nEN EJERCICIOS FISCALES ANTERIORES PENDIENTES\nDE LIQUIDACIÓN O PAGO\n01 DERECHOS CAUSADOS EN EJERCICIOS ANTERIORES PENDIENTES DE\nLIQUIDACIÓN O PAGO\nARTÍCULO 56.- Los Derechos no pagados en el ejercicio fiscal en que anteriores, aplicando en cuanto al fondo, las leyes vigentes a la fecha en que se generaron y en cuanto a la forma mediante el procedimiento administrativo de ejecución que establece la Ley de Hacienda Municipal del Estado de Baja California o en su caso, el procedimiento judicial que corresponda.\nTÍTULO SEXTO\n5 PRODUCTOS\n1 PRODUCTOS\n01 PRODUCTOS\nARTÍCULO 57.- El Ayuntamiento podrá cobrar los intereses generados o causados por sus cuentas bancarias.\n02 ENAJENACIÓN DE BIENES MUEBLES E INMUEBLES PROPIEDAD DEL\nGOBIERNO MUNICIPAL\nARTÍCULO 58.- El Ayuntamiento podrá disponer de Bienes Muebles e fortalecer las finanzas municipales, para ponerlos en venta con pago de contrato, mismo que no podrá exceder los 5 años, con el\nOficialía Mayor Municipal.\nValuación o en su defecto el valor fiscal, cuando el primero resulte inferior al segundo.\n03 BIENES MOSTRENCOS no tener dueño aparente, de acuerdo al procedimiento establecido en el Código Civil de Baja California, después de una investigación y cumplido el plazo fijado para su reclamo, si no aparece el dueño legítimo, el Municipio percibirá ingresos por concepto de la venta de bienes mostrencos en subasta pública tales como:\nI.- Bienes muebles\nII.-Otros\n04 EXPLOTACIÓN O ARRENDAMIENTO DE BIENES MUEBLES E INMUEBLES\nDE DOMINIO PRIVADO PROPIEDAD DEL GOBIERNO MUNICIPAL\nARTÍCULO 59.- La renta de los bienes muebles e inmuebles de dominio privado propiedad del Municipio de Mexicali, así como los que tiene a subarrendar, serán fijados en cada caso por la Comisión Municipal de\nValuación y cuyo pago deberá efectuarse dentro de los primeros cinco días de cada mes.\n9 PRODUCTOS NO COMPRENDIDOS EN LA LEY DE INGRESOS VIGENTE, CAUSADOS\nEN EJERCICIOS FISCALES ANTERIORES PENDIENTES DE LIQUIDACIÓN O PAGO\n01 PRODUCTOS CAUSADOS EN EJERCICIOS ANTERIORES PENDIENTES DE\nLIQUIDACIÓN O PAGO\nARTÍCULO 60.- Los Productos no pagados en el ejercicio fiscal en que anteriores, aplicando en cuanto al fondo, las leyes vigentes a la fecha del Estado de Baja California o en su caso, el procedimiento judicial que corresponda.\nTÍTULO SÉPTIMO\n6 APROVECHAMIENTOS\nCAPÍTULO I\n1 APROVECHAMIENTOS\n01 MULTAS\nARTÍCULO 61.- Las que se contemplan en los reglamentos municipales y las que deriven por el incumplimiento de las disposiciones fiscales, asimismo la autoridad municipal, al hacer efectiva la sanción impuesta por las diversas dependencias municipales, por violaciones a los reglamentos emitidos por el Ayuntamiento, y al hacer efectivas dichas infracciones mediante el procedimiento administrativo de ejecución podrá apegarse a lo establecido por el Artículo 88 de la Ley de Hacienda\nMunicipal del Estado de Baja California.\n02 OTRAS ACTIVIDADES DEL GOBIERNO MUNICIPAL QUE NO CORRESPONDAN A\nSUS FUNCIONES PROPIAS DE DERECHO PÚBLICO\nARTÍCULO 62.- Las personas físicas que hagan uso de los sanitarios públicos propiedad del Ayuntamiento, ubicados en el Centro Histórico de Mexicali, pagarán una tarifa de $5.00 M.N. por usuario.\n03 REINTEGROS E INDEMNIZACIONES\n04 DONACIONES, CESIONES, HERENCIAS Y LEGADOS A FAVOR DEL MUNICIPIO\n05 OTROS APROVECHAMIENTOS\nCAPÍTULO II\n2 APROVECHAMIENTOS PATRIMONIALES\nCAPÍTULO III\n3 ACCESORIOS DE APROVECHAMIENTOS\n01 ACCESORIOS DE APROVECHAMIENTOS\nARTÍCULO 63.- Son los ingresos que se perciben por concepto de recargos, sanciones, gastos de ejecución, indemnizaciones, entre otros, asociados a los aprovechamientos, cuando éstos no se cubran oportunamente, de conformidad con lo siguiente:\nI.- Recargos por mora: Cuando no se paguen las contribuciones o no se cubran las parcialidades en los plazos convenidos, se pagarán recargos por mora a la tasa del 2% mensual.\nII.- Recargos por financiamiento: Cuando se conceda prórroga para el pago de créditos fiscales o para que los mismos sean cubiertos en parcialidades, se causarán recargos por financiamiento sobre el saldo insoluto a la tasa del 1.5% mensual.\nIII.- Sanciones: Las multas derivadas del incumplimiento en el pago de contribuciones en la forma, fecha y términos que establezcan en esta Ley y en las disposiciones fiscales respectivas.\nIV.- Gastos de Ejecución: Cuando las autoridades fiscales instauren el Procedimiento Administrativo de Ejecución para la recuperación de los créditos fiscales que correspondan, se estará a lo establecido en el \"Capítulo VIII. De los\nGastos de Ejecución\" de la Ley de Hacienda Municipal del\nEstado de Baja California.\nV.- Otros: Todos aquellos que se encuentren asociados o establecidos en las leyes fiscales.\nCAPÍTULO IV\n9 APROVECHAMIENTOS NO COMPRENDIDOS EN LA LEY DE INGRESOS VIGENTE,\nO PAGO\n01 APROVECHAMIENTOS CAUSADOS EN EJERCICIOS ANTERIORES\nPENDIENTES DE LIQUIDACIÓN O PAGO\nARTÍCULO 64.- Los Aprovechamientos no pagados en el ejercicio fiscal fiscales anteriores, aplicando en cuanto al fondo, las leyes vigentes\nHacienda Municipal del Estado de Baja California o en su caso, el procedimiento judicial que corresponda.\nTÍTULO OCTAVO\n7 INGRESOS POR VENTA DE BIENES, PRESTACIÓN DE SERVICIOS\nY OTROS INGRESOS\nCAPÍTULO I\n1 INGRESOS POR VENTA DE BIENES Y PRESTACIÓN DE SERVICIOS\nDE INSTITUCIONES PÚBLICAS DE SEGURIDAD SOCIAL.\n2 INGRESOS POR VENTA DE BIENES Y PRESTACIÓN DE SERVICIOS\nDE EMPRESAS PRODUCTIVAS DEL ESTADO.\n3 INGRESOS POR VENTA DE BIENES Y PRESTACIÓN DE SERVICIOS\nDE ENTIDADES PARAESTATALES Y FIDEICOMISOS NO\nEMPRESARIALES Y NO FINANCIEROS.\n4 INGRESOS POR VENTA DE BIENES Y PRESTACIÓN DE SERVICIOS\nDE ENTIDADES PARAESTATALES EMPRESARIALES NO\nFINANCIERAS CON PARTICIPACIÓN ESTATAL MAYORITARIA.\n5 INGRESOS POR VENTA DE BIENES Y PRESTACIÓN DE SERVICIOS\nMONETARIAS CON PARTICIPACIÓN ESTATAL MAYORITARIA.\n6 INGRESOS POR VENTA DE BIENES Y PRESTACIÓN DE SERVICIOS\nNO MONETARIAS CON PARTICIPACIÓN ESTATAL MAYORITARIA.\n7 INGRESOS POR VENTA DE BIENES Y PRESTACIÓN DE SERVICIOS\nESTATAL MAYORITARIA.\n8 INGRESOS POR VENTA DE BIENES Y PRESTACIÓN DE SERVICIOS\nDE LOS PODERES LEGISLATIVO Y JUDICIAL, Y DE LOS\nÓRGANOS AUTÓNOMOS.\nCAPÍTULO II\n9 OTROS INGRESOS\nARTÍCULO 65.- Ninguna contribución podrá recaudarse si no está prevista en la presente Ley de Ingresos Municipal.\nDESARROLLO HUMANO INTEGRAL - CENTENARIO\nARTÍCULO 66.- Los servicios que presta el Patronato del Centro de\nDesarrollo Humano Integral - Centenario, se cobrarán conforme a lo siguiente:\nI.- Los ingresos por conceptos son:\nTARIFA\nMONEDA NACIONAL\nPrecio de entrada y servicios\na).- Entrada:\n1.- Entrada niños hasta 3 años, adulto mayor y personas con discapacidad, presentando tarjeta INAPAM o cualquier identificación vigente que lo acredite, así como al acompañante mayor de edad de un menor de edad el día que asista al curso inscrito...................... EXENTO\n2.- Entrada general mayor de 3 años........ $ 10.00 M.N.\n3.- Entrada a grupos mediante convenios, acreditados previamente y no transferibles......................... $ 5.00 M.N.\n4.- Entrada solo por el día 30 de abril en conmemoración del “Día de la Niña y el\nNiño” de los menores de 12 años, EXENTO acompañados por un adulto..............\n5.- Estacionamiento por día:\na).- De 0 a 20 minutos................ EXENTO\nb).- De 21 minutos en adelante........ $ 12.00 M.N.\n6.- Tarjeta de 30 pases estacionamiento... $ 130.00 M.N.\n7.- Boleto de estacionamiento extraviado.. $ 58.00 M.N.\n8.- Boleto de estacionamiento en eventos especiales........................... $ 30.00 M.N.\n9.- Boleto de estacionamiento camiones por día................................... $ 60.00 M.N.\nb).- Membresías:\n1.- Membresía con 12 entradas............. $ 84.00 M.N.\n2.- Membresía con 24 entradas............. $ 155.00 M.N.\n3.- Gimnasio.............................. $ 350.00 M.N.\n4.- Gimnasio por sesión................... $ 45.00 M.N.\n5.- Gimnasio con instructor............... $ 450.00 M.N.\n6.- Gimnasio por sesión con instructor.... $ 100.00 M.N.\n7.- Membresía individual alberca-gimnasio\n(mensual) 1 hora de alberca por día..... $ 835.00 M.N.\nc).- Albercas:\n1.- Alberca por una hora.................. $ 34.00 M.N.\n2.- Acuatlón por persona (incluye entrada al parque)............................ $ 334.00 M.N.\n3.- Alberca pase individual no transferible\n15 horas (incluye entrada)............ $ 418.00 M.N.\n4.- Alberca pase individual no transferible\n30 horas (incluye entrada)............. $ 668.00 M.N.\n5.- Paquete Alberca Grupos con convenio por persona 2 horas........................ $ 45.00 M.N.\n6.- Paquete Fin de Semana (Chapoteadero) por persona, por 4 horas, mínimo 20 personas.............................. $ 67.00 M.N.\nNota: La alberca no es de uso exclusivo\nComo requisito obligatorio para acceso a albercas, deberá presentar certificado médico.\nd).- Servicios:\n1.- Atención nutricional sesión........... $ 250.00 M.N.\n2.- Evaluación psicológica individual, niños o adultos....................... $ 350.00 M.N.\n3.- Sesión atención psicológica individual. $ 300.00 M.N.\n4.- Sesión atención psicológica pareja.... $ 400.00 M.N.\n5.- Sesión atención psicológica familiar.. $ 450.00 M.N.\n6.- Taller Psicológico Comunitario o\nEmpresarial, por persona, por hora..... $ 200.00 M.N.\n(30 a 50 personas)\n7.- Test y/o evaluaciones en niños o adultos por cada prueba........................ $ 668.00 M.N.\n8.- Paquete de tres test y/o evaluaciones.. $1,558.00M.N.\nTodo servicio, deberá cubrirse en su totalidad al momento de agendar la cita en ventanilla.\ne).- Asesoría escolar:\n1.- Asesoría individual, por sesión en todos los niveles escolares........ $ 250.00 M.N.\n2.- Escuela para adultos, por sesión...... $ 250.00 M.N.\nf).- Renta de palapas y mobiliario:\n1.- Palapas o Kiosco por 6 horas.......... $ 840.00 M.N.\n(Incluye cuota de recuperación por el servicio de limpieza y energía eléctrica)\n2.- Cuota de recuperación por uso de agua potable............................... $ 105.00 M.N.\n(Únicamente en albercas, brincolinas y otras actividades acuáticas)\n3.- Sillas (c/u).......................... $ 12.00 M.N.\n4.- Mesas (c/u)........................... $ 34.00 M.N.\ng).- Renta de canchas:\n1.- Renta de cancha Basquetbol al aire libre, por hora:\nRegular............................... $ 111.00 M.N.\nGrupos con convenio................... $ 89.00 M.N.\n2.- Renta de cancha de Fútbol Americano por tres horas (De día):\nRegular............................... $ 557.00 M.N.\nGrupos con convenio.................... $ 445.00 M.N.\n3.- Renta de cancha de Fútbol Americano por tres horas (De noche):\nRegular............................... $ 835.00 M.N.\nGrupos con convenio.................... $ 668.00 M.N.\n4.- Renta de cancha de Fútbol Soccer por dos horas (De día):\nRegular............................... $ 445.00 M.N.\nGrupos con convenio.................... $ 334.00 M.N.\n5.- Renta de cancha de Fútbol Soccer por dos horas (De noche):\nRegular............................... $ 668.00 M.N.\nGrupos con convenio.................... $ 556.00 M.N.\nPor cada hora adicional de los puntos\n6.- Renta de cancha de Voleibol al aire libre, por hora (De día):\nRegular............................... $ 111.00 M.N.\nGrupos con convenio................... $ 89.00 M.N.\n7.- Renta de cancha de Voleibol al aire libre, por hora (De noche):\nRegular............................... $ 223.00 M.N.\nGrupos con convenio................... $ 167.00 M.N.\n8.- Renta de cancha de Frontón, por hora (De día)\nRegular............................... $ 150.00 M.N.\nGrupo con convenio................... $ 128.00 M.N.\n9.- Renta de cancha de Frontón, por hora (De noche)\nRegular............................... $ 250.00 M.N.\nGrupo con convenio.................... $ 228.00 M.N.\n10.- Renta de cancha de Fútbol Rápido por hora (De día):\nRegular............................... $ 334.00 M.N.\nGrupos con convenio.................... $ 278.00 M.N.\n11.- Renta de cancha de Fútbol Rápido por hora (De noche):\nRegular............................... $ 445.00 M.N.\nGrupos con convenio.................... $ 334.00 M.N.\n12.- Renta de cancha de usos múltiples al aire libre, por día (máximo 5 horas):\nRegular............................... $ 779.00 M.N.\nGrupos con convenio.................... $ 557.00 M.N.\n13.- Renta de cancha de usos múltiples techada, máximo 5 horas, sin uso de energía eléctrica:\nRegular............................... $ 4,463.00 M.N.\nSector Empresarial.................... $ 5,565.00 M.N.\nSector Educativo...................... $ 3,339.00 M.N.\n14.- Renta de cancha de usos múltiples techada, máximo 5 horas, con uso de energía eléctrica:\nRegular............................... $ 6,678.00 M.N.\nSector Empresarial.................... $ 8,904.00 M.N.\nSector Educativo...................... $ 4,452.00 M.N.\n15.- Renta de campo de Softbol por dos horas\n(De día):\nRegular............................... $ 334.00 M.N.\nGrupos con convenio................... $ 278.00 M.N.\n16.- Renta de campo de Softbol por dos horas(De noche):\nRegular............................... $ 557.00 M.N.\nGrupos con convenio................... $ 445.00 M.N.\nPara efectos de este inciso se considera horario de noche en:\n- Verano a partir de las 19:00 horas\n- Invierno a partir de las 17:00 horas\nh).- Renta de infraestructura:\n1.- Renta de concesión “A” mensual......... $5,565.00 M.N.\n(Se requiere un mes de depósito)\n2.- Renta de concesión \"B\" y \"C\" mensual... $4,452.00 M.N.\n(Se requiere un mes de depósito)\n3.- Renta de salón de usos múltiples por hora (capacidad máxima 40 personas).... $ 3 34.00 M.N.\n4.- Renta de sala audiovisual por hora:\n(No incluye proyector)\nRegular............................... $ 445.00 M.N.\nGrupos con convenio.................... $ 334.00 M.N.\n5.- Renta de sala audiovisual, máximo 8 horas: (No incluye proyector)\nRegular............................... $2,226.00 M.N.\nGrupos con convenio................... $1,113.00 M.N.\n6.- Renta de Brincolina Acuática en evento organizado en las instalaciones por 5 horas................................. $ 557.00 M.N.\n7.- Renta de Brincolina en evento organizado en las instalaciones por\n5 horas............................... $ 501.00 M.N.\n8.- Renta de Sonido (Bocina y tripie) en evento organizado dentro de las instalaciones por día.................. $ 501.00 M.N.\n9.- Otros arrendamientos mensual.......... $10,000.00 a\n$30,000.00 M.N.\n(De acuerdo a los m² solicitados y se requiere un mes de depósito)\ni).- Renta de espacios a vendedores ambulantes:\n1.- Autorización a vendedores ambulantes con puestos móviles, en giros tales como: nieves de garrafa, paleteros, botana a granel, algodoneros, etc., por día............................... $ 111.00 M.N.\n2.- Autorización a vendedores ambulantes puestos semifijos (Instalados con mobiliario, tales como: mesa, carpa, sombrilla o cualquier similar) por día................................... $ 390.00 M.N.\n3.- Autorización a toma de fotografías con fines lucrativos, por día.............. $ 390.00 M.N.\n4.- Renta mensual de espacio por máquina expendedora de productos............... $ 1,002.00 M.N.\n5.- Renta mensual de espacio por mesa de juego................................. $ 278.00 M.N.\nj).- Renta de espacios publicitarios:\n1.- Renta mensual de espacio publicitario.\na) Menor o igual a 1.8 x 1.5 mts...... $ 557.00 M.N.\n2.- Renta de espacio publicitario de 2.0 x\n1.8 mts, ubicado sobre Bulevar Lázaro\nCárdenas:\na) Mensual............................ $ 1,113.00 M.N.\nb) Semestral.......................... $ 5,565.00 M.N.\nc) Anual.............................. $11,130.00 M.N.\n3.- Renta de espacio publicitario de 3.0 x\n1.8 mts, ubicado sobre Bulevar Lázaro\nCárdenas:\na) Mensual............................ $ 2,226.00 M.N.\nb) Semestral.......................... $11,130.00 M.N.\nc) Anual.............................. $22,260.00 M.N.\n4.- Renta de espacio publicitario de 3.0 x\n2.4 mts y 3.0 x 3.0 mts, ubicado sobre\nBulevar Lázaro Cárdenas:\na) Mensual............................ $ 3,339.00 M.N.\nb) Semestral.......................... $16,695.00 M.N.\nc) Anual.............................. $31,164.00 M.N.\n5.- Renta de espacio publicitario de 5.0 x\n3.7 mts., ubicado dentro del estacionamiento del Centro Desarrollo\nHumano Integral:\na) Mensual............................ $ 4,200.00 M.N.\nb) Semestral.......................... $16,800.00 M.N.\nc) Anual.............................. $31,500.00 M.N.\nk).- Renta de estacionamiento para eventos:\n1.- Renta de estacionamiento “Car Show”/ eventos varios:\na) Cualquier zona del estacionamiento hasta por 5 horas.................... $4,500.00 a\n$7,790.00 M.N.\nb) Cualquier zona del estacionamiento renta mensual........................ $15,000.00 a\n$25,000.00 M.N\nCon uso de energía eléctrica se cobrará además................................ $ 1,113.00 M.N.\nLos costos serán fijados en el contrato previa autorización del Director del\nCentro de Desarrollo Humano Integral\nCentenario y se deberá tomar en cuenta la zona solicitada, completa y/o parcial, el mes y periodo en que se llevará a cabo la renta.\n2.- Renta de espacio 2x2 mts. para Bazar\nCentenario o eventos varios:\na) 1 día.............................. $ 53.00 M.N.\nb) 2 días (consecutivos).............. $ 74.00 M.N.\nCon uso de energía eléctrica se cobrará además................................ $1,113.00 M.N.\n3.- Renta de estacionamiento para clases de manejo:\na) 1 hora............................. $ 223.00 M.N.\nb) 2 horas............................ $ 390.00 M.N.\nEl área de estacionamiento para las clases de manejo será la zona oriente pegado a la lateral y delimitado por personal del CDHI.\n*La renta mensual de los bienes inmuebles propiedad del Centro de\nDesarrollo Humano Integral, será fijada de acuerdo al contrato o convenio que se celebre, dependiendo de la superficie ocupada y de su localización.\nl).- Cursos (costo mensual):\n1.- Acondicionamiento Físico.............. $ 400.00 M.N.\n2.- Animación deportiva................... $ 400.00 M.N.\n3.- Artes Marciales Chinas (Kung Fu, Wu\nShu, Tai Chi)......................... $ 400.00 M.N.\n4.- Artes Marciales Chinas por sesión\n(Kung Fu, Wu Shu, Tai Chi)............ $ 100.00 M.N.\n5.- Artes marciales mixtas................ $ 400.00 M.N.\n6.- Artes marciales mixtas por sesión..... $ 100.00 M.N.\n7.- Baile de Salón........................ $ 400.00 M.N.\n8.- Ballet por sesión..................... $ 100.00 M.N.\n9.- Ballet................................ $ 400.00 M.N.\n10.- Baloncesto............................ $ 400.00 M.N.\n11.- Banda de Guerra*\na) Femenil............................ $ 668.00 M.N.\nb) Mixto.............................. $ 668.00 M.N.\nc) Varonil............................ $ 668.00 M.N.\n12.- Banda de Guerra curso intensivo\n(Dos semanas)\na) Femenil............................ $ 445.00 M.N.\nb) Mixto.............................. $ 445.00 M.N.\nc) Varonil............................ $ 445.00 M.N.\n13.- Banda de Guerra sesión individual..... $ 167.00 M.N.\n14.- Béisbol............................... $ 400.00 M.N.\n15.- Belleza............................... $ 445.00 M.N.\n16.- Box................................... $ 400.00 M.N.\n17.- Campo de entrenamiento (Bootcamp)..... $ 400.00 M.N.\n18.- Canto................................. $ 400.00 M.N.\n19.- Computación........................... $ 400.00 M.N.\n20.- Corte y confección.................... $ 550.00 M.N.\n21.- Danza Folklórica..................... $ 400.00 M.N.\n22.- Danzas Polinesias por sesión.......... $ 100.00 M.N.\n23.- Danzas Polinesias..................... $ 400.00 M.N.\n24.- Dibujo................................ $ 400.00 M.N.\n25.- Dibujo por sesión..................... $ 100.00 M.N.\n26.- Dibujo Digital........................ $ 445.00 M.N.\n27.- Diplomado............................. $3,896.00 M.N.\n28.- Escolta*\na) Femenil........................... $ 668.00 M.N.\nb) Mixto............................. $ 668.00 M.N.\nc) Varonil........................... $ 668.00 M.N.\n29.- Escolta curso intensivo (Dos semanas)\na) Femenil........................... $ 445.00 M.N.\nb) Mixto............................. $ 445.00 M.N.\nc) Varonil........................... $ 445.00 M.N.\n30.- Escolta sesión individual............. $ 167.00 M.N.\n31.- Esgrima............................... $ 400.00 M.N.\n32.- Fútbol................................ $ 400.00 M.N.\n33.- Fútbol Americano...................... $ 400.00 M.N.\n34.- Fútbol Banderitas..................... $ 400.00 M.N.\n35.- Guitarra.............................. $ 400.00 M.N.\n36- Guitarra por sesión................... $ 100.00 M.N.\n37.- Hip Hop............................... $ 400.00 M.N.\n38.- Jazz.................................. $ 400.00 M.N.\n39.- Jazz por sesión....................... $ 100.00 M.N.\n40.- Karate................................ $ 400.00 M.N.\n41.- Karate por sesión................... $ 100.00 M.N.\n42.- Kick Boxing........................... $ 400.00 M.N.\n43.- Kick Boxing por sesión................ $ 100.00 M.N.\n44.- Manualidades.......................... $ 400.00 M.N.\n45.- Manualidades por sesión: $ 100.00 M.N.\n46.- Modelaje y Expresión Corporal......... $ 557.00 M.N.\n47.- Pintura............................... $ 400.00 M.N.\n48.- Pintura por sesión.................... $ 100.00 M.N.\n49.- Rumba (Ritmos latinos)................ $ 400.00 M.N.\n50.- Salsa................................. $ 400.00 M.N.\n51.- Taekwondo............................. $ 400.00 M.N.\n52.- Teatro................................ $ 400.00 M.N.\n53.- Tiro con Arco......................... $ 700.00 M.N.\n54.- Uñas acrílicas........................ $ 445.00 M.N.\n55.- Voleibol.............................. $ 400.00 M.N.\n56.- Yoga.................................. $ 400.00 M.N.\n57.- Zumba................................. $ 400.00 M.N.\n58.- Zumba por sesión...................... $ 100.00 M.N.\n59.- Ciclismo BMX.......................... $ 750.00 M.N.\n60.- Otros cursos.......................... $ 334.00 a\n$1,670.00 M.N.\n61.- Costo de sesión por curso............ $ 100.00 M.N.\nm).- Cursos de Albercas:\n1.- Acuaerobics........................... $ 668.00 M.N.\n2.- Matronatación......................... $ 890.00 M.N.\n3.- Natación.............................. $1,000.00 M.N.\n(Principiante, intermedio y avanzado)\nEs necesario presentar Certificado Médico, de cualquier institución pública o privada, especificando que la persona es apta para desarrollar actividades acuáticas.\n* Por los cursos de los incisos k) y l) se otorga a Instituciones y empresas el 50% de descuento por 10 elementos inscritos.\nTodos los cursos son mensuales, la inscripción se cobra los primeros cinco días de cada mes, únicamente para usuarios de nuevo ingreso se realiza cobro proporcional.\nn).- Programas Vacacionales:\n1.- Programa Vacacional de Verano por participante, (horario 8:00 a.m. a\n13:00 p.m.) incluye camiseta.......... $1,350.00 M.N.\n2.- Camiseta adicional para el\nParticipante inscrito en el Programa\nVacacional............................ $ 130.00 M.N. ñ).- Otros:\n1.- Arbitraje de Baloncesto por equipo por juego:\na) Abierta, Liga o Copa............... $ 334.00 M.N.\nb) Infantil........................... $ 278.00 M.N.\nc) Escolar............................ $ 223.00 M.N.\n2.- Arbitraje de Fútbol y Voleibol por equipo por juego:\na) Abierta, Liga o Copa............... $ 223.00 M.N.\nb) Infantil........................... $ 167.00 M.N\nc) Escolar............................ $ 140.00 M.N.\n3.- Inscripción carrera atlética\na) 2 km, 5 km y 10 km................ $ 278.00 M.N.\n4.- Inscripción paseo ciclista............ $ 22.00 M.N.\n5.- Inscripción torneos categoría Abierta\nNovatos............................... $ 557.00 M.N.\n6.- Inscripción torneos Escolar/Infantil.. $ 445.00 M.N.\n7.- Inscripciones y arbitrajes otros...... $ 340.00 a\n$1,670.00 M.N.\n8.- Pintado de cancha de Fútbol y Softbol. $ 111.00 M.N.\n9.- Organización-Logística de eventos, festivales o torneos, por evento:\na) Regular............................ $ 3,340.00 a\n$8,904.00 M.N.\n(El costo inicial será definido por el número de personas a ingresar, siendo el mínimo 30 personas)\nb) Sector empresarial o escolar....... $10,000.00 a\n25,000.00 M.N.\n(El costo inicial será definido por el número de personas a ingresar, siendo el mínimo de ingresar 50 personas)\n10.- Organización de Rally Deportivo:\n(Por niño o adulto)\na) Escolar:\n1) De 5 a 8 estaciones............. $ 34.00 a\n$ 56.00 M.N.\n2) De 10 a 15 estaciones........... $ 78.00 a\n$ 111.00 M.N.\nb) Sector Empresarial:\n1) De 5 a 8 estaciones............. $ 78.00 a\n$ 111.00 M.N.\n2) De 10 a 15 estaciones........... $ 111.00 a\n$167.00 M.N.\n11.- Reposición de credencial para cursos o tarjetas de entrada de estacionamiento y alberca por persona. $ 56.00 M.N.\n12.- Tarjetones (no incluyen la entrada del jugador).............................. $ 56.00 M.N.\n13.- Eventos especiales boleto por persona. $ 34.00 a\n$557.00 M.N.\n14.- Venta de artículos varios............. $ 2.00 a\n$ 557.00 M.N.\no).- Paquete Fiestas por seis horas:\n1.- Paquete Fiesta, incluye:\nPalapa, 3 mesas, 30 sillas, brincolina $1,447.00M.N.\np).- Centro de conocimiento centenario:\n1.- Copia e impresión tamaño carta en blanco y negro (precio por hoja)...... $ 2.00 M.N.\n2.- Copia e impresión tamaño oficio en blanco y negro (precio por hoja)...... $ 3.00 M.N.\n1.- EMPLEADOS DE CONFIANZA, EVENTUALES, ASIMILADOS Y COMISIONADOS\nDEL CENTRO DE DESARROLLO HUMANO INTEGRAL CENTENARIO.\na).- Se les otorga acceso gratuito y descuento del 20% en cursos permanentes, 20% en cursos temporales como: Plan vacacional y natación, 20% de descuento en todos los demás servicios (renta de infraestructura, etc.). Para ellos y su familia (esposo (a) e hijos). Excepto servicio de atención psicológica y nutricional.\n2.- EMPLEADOS DE LOS TRES NIVELES DE GOBIERNO CON IDENTIFICACIÓN\nVIGENTE.\na).- Descuento del 10% en cursos para ellos y sus familias, incluye: esposo (a) e hijos y descuento del 20% a partir del segundo curso a una misma persona.\n3.- POBLACIÓN EN GENERAL.\na).- Familiar inscrito en algún curso, (esposo(a) e hijos) descuento del 10% a partir del segundo integrante de la familia inscrito y descuento del 20% a partir del tercer curso.\nb).- Personas con necesidades de rehabilitación, 100% de y alberca, presentando su solicitud por escrito acompañada de una copia del diagnóstico médico emitido por una institución de salud pública o privada.\nDeben de acompañarse de un instructor, médico o persona certificada para asistirlos en su rehabilitación.\nc).- Personas con discapacidad descuento del 50% en cursos que se oferten en CDHI Centenario presentando credencial vigente.\nd).- Personas Adultos Mayores, descuento del 50% en cursos y horas de alberca presentando su credencial de INAPAM. No transferible, SUJETO A SANCIÓN.\ne).- Descuento del 50% en la renta de cancha usos múltiples a dependencias municipales, estatales, escuelas, etc., siempre y cuando esta sea solicitada mediante escrito de acuerdo a la necesidad y/o solvencia económica del solicitante. SUJETO A REVISIÓN.\nf).- Cualquier otro descuento que no figure en los ya mencionados, deberá ser autorizado por la dirección de la entidad.\n4.- POLÍTICA GENERAL DE PROMOCIONES Y DESCUENTOS.\na).- Se establece de forma permanente 2 x 1 a usuarios de nuevo ingreso en gimnasio o en cursos a un mismo usuario, en los meses de enero, febrero, septiembre, noviembre y diciembre, por ser temporada baja, en aquellos cursos que tengan solo 5 o menos usuarios inscritos, siempre que el instructor este de acuerdo.\nb).- Al iniciar un nuevo curso se podrá otorgar promoción del\n2x1 a usuarios o en cursos a un mismo usuario siempre que el instructor este de acuerdo.\nNota: Todos estos descuentos no son acumulativos a otras promociones.\nII.- Otros Servicios:\nEl Patronato del Centro de Desarrollo Humano Integral – Centenario, Municipal, así como de personas físicas y morales, subsidios, aportaciones, subvenciones y donativos en efectivo y/o en especie.\nSe cobrarán Derechos de conformidad al presupuesto que al efecto realice el Centro de Desarrollo Humano Integral - Centenario, los que en todo caso serán proporcionales al costo del servicio. Los ingresos que por concepto de derechos, transferencias, asignaciones y ayudas sociales que se perciban, pasarán a formar parte del patrimonio del Centro de Desarrollo Humano Integral – Centenario.\nSERVICIOS QUE PRESTA EL INSTITUTO MUNICIPAL DE ARTE Y\nCULTURA DE MEXICALI\nARTÍCULO 67.- Los servicios que presta el Instituto Municipal de Arte y Cultura, se cobrarán por persona conforme a lo siguiente:\nI.- Venta de Bienes y Prestación de Servicios:\nTARIFA\nMONEDA NACIONAL\na).- Casa de la Cultura:\n1.- Inscripción a cursos regular............. $1,113.00 M.N.\n2.- Inscripción a clases individuales de piano, violín, chelo y trompeta.................. $ 1, 6 7 0.00 M.N.\n3.- Inscripción a cursos de verano (taller individual)............................... $ 813.00 M.N.\n4.- Paquete de curso de verano (varias disciplinas).............................. $1,670.00 M.N.\n5.- Extensión de horario en paquete de curso de verano................................. $ 3 9 0.00 M.N.\n6.- Inscripción a clases individuales en línea de piano y cuerdas........................ $1,670.00 M.N.\n7.- Inscripción a cursos en línea.............. $ 390.00 M.N.\n8.- Inscripción a talleres intensivos........ $ 223.00 a\n$1,113.00 M.N.\n9.- Recorridos escolares para escuelas públicas\n(por persona)............................. $ 39.00 M.N.\n10.- Recorridos escolares para escuelas particulares (por persona)................ $ 67.00 M.N.\n11.- Boleto para evento artístico (obras de teatro, danza, música, literatura u otra rama del arte)............................ $ 2.00 a\n$ 557.00 M.N.\n12.- Autorización para sesión de fotografías... $ 525.00 M.N.\n13.- Renta de Marquesina para entidades de gobierno y asociaciones no lucrativas...... EXENTO\n14.- Renta de bastidor en las rejas para entidades de gobierno y asociaciones no lucrativas................................ EXENTO\n15.- Renta de Galerías Rufino Tamayo\n(por 3 horas de evento)................... $1,670.00 M.N.\n16.- Renta de Anfiteatro (por 3 horas de evento)................................... $4,931.00 M.N.\n17.- Renta de Teatro Salvador Caldera (por 3 horas de evento).......................... $9,906.00 M.N.\n18.- Renta de marquesina costo mensual......... $ 1,113.00 a\n$3,339.00 M.N.\n19.- Renta de bastidor en las rejas costo mensual.. $ 557.00 a\n$1,113.00 M.N.\n20.- Renta de espacio comercial costo por día... $ 140.00 M.N.\nb).- CREA Cultura:\n1.- Inscripción a cursos regular............... $ 813.00 M.N.\n2.- Inscripción a clases individuales de piano, violín, chelo y trompeta................... $ 1, 6 7 0.00 M.N.\n3.- Inscripción en paquete de curso de verano\n(varias disciplinas)...................... $1,447.00 M.N.\n4.- Extensión de horario en paquete de curso de verano................................. $ 334.00 M.N.\n5.- Inscripción a cursos en línea.............. $ 390.00 M.N.\n6.- Inscripción a talleres intensivos........ $ 223.00 a\n$1,113.00 M.N.\n7.- Boleto para evento artístico (obra de teatro, danza, música, literatura u otra rama del arte)............................ $ 2.00 a\n$ 557.00 M.N.\n8.- Renta de parque infantil (por 3 horas de evento)................................... $1,035.00 M.N.\n9.- Renta de Teatro Benito Juárez\n(por 3 horas de evento)................... $ 5, 1 2 0.00 M.N.\n10.- Recorridos escolares para escuelas públicas\n(por persona)............................. $ 3 9.00 M.N.\n11.- Recorridos escolares para escuelas particulares (por persona)................ $ 6 7. 00 M.N.\n12.- Renta de espacio comercial costo por día.. $ 140.00 M.N.\nc).- Meyibó Centro del Saber:\n1.- Inscripción a curso regular................ $ 813.00 M.N.\nDescuento del 50% a personas con discapacidad.\n2.- Inscripción en paquete de curso de verano (varias disciplinas)............... $ 813.00 M.N.\n3.- Extensión de horario en paquete de curso de verano.................................... $ 334.00 M.N.\n4.- Inscripción a cursos en línea............. $ 390.00 M.N.\n5.- Inscripción talleres intensivos........... $ 223.00 a\n$1,113.00 M.N.\n6.- Expedición de credencial individual Meyibó por 6 meses............................... $ 390.00 M.N.\n7.- Expedición de credencial de grupo escolar, familiar o empresas (por 6 meses)......... $ 273.00 M.N.\n8.- Expedición de pasaporte diario............ $ 28.00 M.N.\n9.- Copia fotostática simple................. $ 3.00 M.N.\n10.- Reposición de credencial.................. $ 50.00 M.N.\n11.- Material de apoyo en cursos.............. $ 50.00 M.N.\n12.- Material de talleres...................... $ 123.00 M.N.\n13.- Recorridos escolares para escuelas públicas (por persona).................... $ 39.00 M.N.\n14.- Expedición de credencial \"Club de Video\nJuegos Meyibó\" acceso a torneos en PC\nGamer y juegos en línea por 3 meses........ $ 390.00 M.N.\n15.- Expedición de credencial \"Club Meyibó\" acceso al club de ciencias, efectos audiovisuales, matemáticas, animación y diseño digital, por 3 meses................ $ 390.00 M.N.\n16.- Expedición de credencial \"Club Meyibó\" todo incluido, por 3 meses................ $ 668.00 M.N.\n17.- Boleto para evento artístico (obra de teatro, danza, música, literatura u otra rama del arte)..................... $ 2.00 a\n$ 557.00 M.N.\n18.- Renta de Salón de usos múltiples Sala “A” y “B” juntos (precio por hora)............ $1,335.00 M.N.\n19.- Renta de Salón de usos múltiples Sala “A”\n(precio por hora)......................... $ 801.00 M.N.\n20.- Renta de Salón de usos múltiples Sala “B” $ 779.00 M.N.\n(precio por hora).........................\n21.- Renta de Jardín (precio por 3 horas)..... $ 1,035.00 M.N.\n22.- *Renta de Sala de cómputo digital (por 3 horas de evento).......................... $ 4,230.00 M.N.\n23.- *Renta de Sala de cómputo PC Gamer (por 3 horas de evento).......................... $ 2,671.00 M.N.\n24.- Renta de Bastidor en las rejas de Meyibó\nCentro del Saber (Costo mensual).......... $ 525.00 a\n$1,050.00 M.N.\n25.- Renta de Bastidor en las rejas para asociaciones no lucrativas (costo\n26.- Renta de Espacio comercial costo por día.. $ 140.00 M.N.\n27.- Recorridos Escolares para escuelas particulares (por persona)............... $ 67.00 M.N.\nd).- Zona Valle (Km 57, Ciudad Coahuila, Km 43\nGuadalupe Victoria, Los Algodones y Ciudad\nMorelos) y Progreso:\n1.- Inscripción de curso regular.............. $ 368.00 M.N.\n2.- Inscripción en Paquete de curso de verano\n(varias disciplinas)...................... $ 701.00 M.N.\n3.- Extensión de horario en paquete de curso de verano.................................... $ 223.00 M.N.\n4.- Inscripción a talleres intensivos.......... $ 223.00 a\n$1,113.00 M.N.\n5.- Inscripción a cursos en línea............. $ 278.00 M.N.\n6.- Boleto para evento artístico (obra de teatro, danza, música, literatura u otra rama del arte)..................... $ 2.00 a\n$ 557.00 M.N.\n7.- Renta de Salón de usos múltiples......... $ 3,339.00 M.N.\n8.- Renta de Salón de usos múltiples Centro\nCultural Progreso (3 horas de evento)..... $ 5, 1 2 0.00 M.N.\n9.- Renta de espacio comercial costo por día.................................... $ 140.00 M.N.\nSe podrán otorgar descuentos en la renta de los espacios culturales en las diversas modalidades de descuento desde el 50% hasta el 100% según establecido en el Reglamento para el Arrendamiento y Uso de Espacios\nCulturales con los que cuenta el Instituto Municipal de Arte y Cultura de Mexicali vigente. Excepto los incisos a) numeral 18, 19 y 20; b) numeral 12; c) numeral 24 y 26 y d) numeral 8.\nEn apoyo a los artistas de la localidad y con el fin de contribuir al fomento de la cultura se establece la modalidad de porcentaje que va desde un 30% hasta un 70% según lo establecido en el Reglamento para el\nInstituto Municipal de Arte y Cultura de Mexicali vigente.\nMexicali vigente. Excepto las inscripciones de cursos en línea y el inciso C numeral 2.\nII.- Venta de artículos promocionales: y artísticos, tales como: camisetas, tazas, plumas, libretas, portavasos, gorras, artesanías, cuadros, libros y todo lo que conlleve a la venta de accesorios, mismos que se ajustarán al precio de lista aprobado por la Junta de Gobierno.\nIII.- Otros Servicios: realice el Instituto Municipal de Arte y Cultura de Mexicali, los que en todo caso serán proporcionales al costo del servicio y estos sean autorizados a través de la Junta de Gobierno.\nLos ingresos que por concepto de derechos, transferencias, asignaciones y ayudas sociales que se perciban, pasarán a formar parte del patrimonio del Instituto Municipal de Arte y Cultura de Mexicali.\nSERVICIOS QUE PRESTA EL BOSQUE Y ZOOLÓGICO\nDE LA CIUDAD DE MEXICALI\nARTÍCULO 68.- Los servicios que presta el Bosque y Zoológico de la\nCiudad de Mexicali, se cobrarán conforme a lo siguiente:\nI.- Los ingresos por conceptos son:\nTARIFA\nMONEDA NACIONAL\nPrecio de entrada y servicios\na).- Entrada:\n1.- Entrada niños, hasta 3 años............ EXENTO\n2.- Entrada niños, 4 a 12 años............. $ 20.00 M.N.\n3.- Entrada adultos....................... $ 25.00 M.N.\n4.- Entrada adulto mayor presentando\nTarjeta de INAPAM o cualquier identificación vigente que lo acredite. EXENTO\n5.- Entrada para personas con discapacidad. EXENTO\n6.- Entrada para estudiantes de cualquier nivel escolar presentando su credencial vigente............................... $ 13.00 M.N.\n7.- Entrada solo por el día 30 de abril en conmemoración del “Día de la Niña y el\nNiño” de los menores de 12 años acompañados por un adulto............. EXENTO\n8.- Zoo Tarjeta Mujer.................... $ 159.00 M.N.\n9.- Entrada de martes a jueves para niños pertenecientes a los albergues y asociaciones civiles sin fines de lucro que se encuentren debidamente registradas ante DIF Municipal, cuyo objeto sea el de proveer o suplir todas las necesidades básicas a menores que carezcan de padres ya sea por abandono o por muerte, requiere solicitud previa EXENTO\nb).- Estacionamientos:\n1.- Estacionamiento en horario hábil...... $ 19.00 M.N.\n2.- Estacionamiento en eventos privados, por unidad............................ $ 43.00 M.N.\n3.- Estacionamiento en eventos masivos.... $ 70.00 M.N.\n4.- Estacionamiento en eventos área VIP.. $235.00 M.N.\nc).- Servicios y atracciones:\n1.- Brazalete atracciones fin de semana\n(Tren, carrusel, tobogán de costales, granjita y lanchas)................... $ 70.00 M.N.\n2.- Carrusel.............................. $ 25.00 M.N.\n3.- Tren.................................. $ 30.00 M.N.\n4.- Tobogán de costales................... $ 23.00 M.N.\n5.- Lanchas............................... $ 23.00 M.N.\n6.- Barco................................. $ 40.00 M.N.\n7.- Tirolesa.............................. $ 83.00 M.N.\n8.- Tirolesa en días de promoción 2x1..... $ 8 3.00 M.N.\n9.- Granjita/Mini Zoo..................... $ 15.00 M.N.\n10.- Granjita/Mini Zoo Fiestas del sol..... $ 30.00 M.N.\n11.- Revisión física para ingresar al\nParque Acuático....................... EXENTO\n12.- Parque Acuático, por día.............. $ 63.00 M.N.\n13.- Parque Acuático 2 x 1 de martes a viernes durante los meses de junio a septiembre $ 63.00 M.N.\n14.- Parque Acuático(Niños hasta de 3 años) EXENTO\n15.- Fotografías con ejemplares del\nZoológico............................. $ 59.00 M.N.\n16.- Permiso para toma de fotografías con fines lucrativos por sesión........... $472.00 M.N.\n17.- Renta de espacio para llevar a cabo ceremonia de matrimonio civil, por evento................................ $413.00 M.N.\n18.- Renta de mobiliario para llevar a cabo ceremonia de matrimonio civil, incluye\n1 mesa, 1 mantel y 20 sillas.......... $413.00 M.N.\n19.- Permiso de pesca (Incluye acceso y el permiso por un día (Horario de 6:00 am a 7:00 pm)............................ $ 105.00 M.N.\n20.- Membresía de pesca(Incluye acceso y el permiso de pesca valido por un semestre (Horario de 6:00am a 7:00pm). $708.00 M.N.\n21.- Permiso de pesca dentro del lago por un día incluye acceso y permiso por día (Horario de 6:00am a 7:00pm), en lancha sin motor...................... $236.00 M.N.\n22.- Permiso de pesca dentro del lago por mes, incluye acceso y permiso por día\n(Horario de 6:00am a 7:00 pm), en lancha sin motor...................... $2,360.00 M.N.\n23.- Renta de Barco (Por hora fuera de horario normal)....................... $1,299.00 M.N.\n24.- Atracciones temporada BAJA de junio a septiembre y de diciembre a enero, 2x1 en carrusel (para niños menores de 11 años) tobogán de costales y lanchas.\n25.- Aviario Interactivo................... $ 13.00 M.N.\nd).- Paquetes Empresarial, Escolar, Familiar y Organizaciones sin Fines de lucro.\nEmpresarial y organizaciones sin fines de lucro:\n1.- Paquete Plata (Incluye entrada, una vuelta en tren, 3 deslizadas en el tobogán de costales, un vaso de alimento para animales de la granjita y un área para evento).......................... $ 75.00 M.N.\n2.- Paquete Oro (Incluye entrada, una vuelta en tren, 3 deslizadas en el tobogán de costales, un vaso de alimento para animales de la granjita, un recorrido en lancha y un área para evento)............................... $ 95.00 M.N.\n3.- Paquete Acuático (Incluye entrada, área para evento y acceso al parque acuático\n(hasta por 4 horas).................... $ 56.00 M.N.\n4.- Paquete Diamante (Incluye una entrada, una vuelta en tren, 3 deslizadas tobogán de costales, un recorrido en lancha, un paseo en el carrusel, (niños menores de\n11 años), área para evento y un acceso al parque acuático (hasta por 4 horas) o una entrada al Safari............... $154.00 M.N.\n5.- Paquete Tren (Incluye entrada, una vuelta en el tren).................... $ 48.00 M.N.\n6.- Paquete Interactivo (Incluye entrada, una vuelta en el tren y un vaso de alimento para animales de la granjita) $ 59.00 M.N.\n7.- Paquete Granjita (Incluye entrada, un vaso de alimento)..................... $ 29.00 M.N.\n8.- Paquete Asistencia Social (Incluye entrada, una vuelta en el tren y un vaso de alimento para animales de la granjita)............................. $ 30.00 M.N.\n9.- Safari en el Bosque de la Ciudad, recorrido guiado por los alrededores del Bosque y Zoológico en auto........ $154.00 M.N.\n10.- Reservación de entrada a Safari en el\nBosque de la Ciudad................... $ 59.00 M.N.\n11.- Entrada de un vehículo al Safari en el\nBosque de la Ciudad, en caso de un festejo, siempre y cuando venga acompañado de una caravana mínima de 8 vehículos, los cuales pagarán precio\n12.- Paquete Carrusel (Incluye entrada, una vuelta en el carrusel a niños menores de 11 años) $ 35.00 M.N.\nEscolar:\n1.- Paquete Escolar 1 Ecopaquete (Incluye entrada, una vuelta en el tren y la\nGranjita Interactiva (niños menores de\n11 años) y 3 deslizadas en el tobogán de costales).......................... $ 45.00 M.N.\n* Promoción 2x1 en este paquete para escuelas de educación especial y casas hogar.\n** Una vez por año este paquete será totalmente gratis para dos escuelas de bajos recursos, las cuales serán seleccionadas de acuerdo a los resultados de la valuación de su situación económica.\n2.- Paquete Escolar 2 atracciones (Incluye entrada, una vuelta en el tren, 3 deslizadas en el tobogán costales, un recorrido en lanchas de pedales y un vaso de alimento para los animales de la granjita).......................... $ 67.00 M.N.\n3.- Paquete Escolar 3 Acuático (Incluye entrada, 3 deslizadas en el tobogán de costales y un acceso al área acuática\n(sujeto a disponibilidad)............ $ 56.00 M.N.\n4.- Paquete Escolar 4 V.I.P. (Incluye entrada, paquete #2 y paquete#3) o entrada al Safari..................... $111.00 M.N.\n5.- Paquete Escolar 5 Econozoo\na).- Escuelas Pre-escolar y primarias.\n(Incluye entrada, una vuelta en tren, o 3 deslizadas en el tobogán de costales)..................... $ 27.00 M.N.\nb).- Secundarias y preparatorias.\n(Incluye entrada, una vuelta en tren, 3 deslizadas en el tobogán de costales o un recorrido en lanchas)......................... $ 27.00 M.N.\nc).- Escuelas Pre-escolar y primarias.\n(Incluye entrada, una vuelta en tren, 3 deslizadas en el tobogán de costales y un vaso para alimentar animales de la granjita)........................ $ 27.00 M.N.\n* Para escuelas del Valle de Mexicali, zonas foráneas, turnos vespertinos, grupos vulnerables y escuelas de bajos recursos, el costo será de........... $ 27.00 M.N.\n6.- Paquete Escolar 6 (Incluye entrada, un recorrido completo en tirolesa y una vuelta en el tren para nivel secundaria, preparatoria y universidad)............ $ 100.00 M.N.\n7.- Tirolesa a precio especial, en la compra de uno de los paquetes\n8.- Paquete Escolar econopaquete 2 (Incluye entrada, una vuelta en tren, una vuelta en el carrusel y 3 deslizadas en el tobogán de costales).................. $ 55.00 M.N.\nFamiliar:\n1.- Paquete Entrada, incluye dos accesos para adultos y dos accesos para niños. $ 74.00 M.N.\n2.- Paquete Atracciones, incluye dos accesos para adultos, dos accesos para niños, una vuelta en tren, un vaso de alimento para los animales,3 deslizadas en el tobogán de costales y un recorrido en lancha............................. $ 320.00 M.N.\ne).- Palapas:\n1.- Palapas chicas (Pai-Pai, Cachanilla, Sta. Lucia, Sta. Cruz, Pereira, José\nIsabel, Sta. María, Rubí y Pagoda) de día................................... $ 767.00 M.N.\n2.- Palapas grandes (Cucapah, Persal, Vizcarra, Marycruz, Sta. Mónica y\nFMM) de día........................... $ 1,534.00 M.N.\n3.- Palapa Persal (En horario Nocturno de\n7:00 p.m. a 2 a.m.).................. $ 7,550.00 M.N.\n4.- Palapa Vizcarra y Maricruz (En Horario nocturno de 7:00 p.m. a 2:00 a.m.).... $ 6,135.00 M.N.\n5.- Palapa Pagoda (En horario nocturno de\n7:00 p.m. a 2:00 a.m.)................ $ 1,770.00 M.N.\nf).- Muelles:\n1.- Muelle Proconsa (De día).............. $ 1,180.00 M.N.\n2.- Muelle San José (De día).............. $ 737.00 M.N.\n3.- Muelle Terraza del Lago (De día)...... $ 1,180.00 M.N.\n4.- Muelle Terraza del Lago (Cena una pareja) de noche...................... $ 590.00 M.N.\n5.- Muelle Terraza del Lago, mensual para establecimiento de negocio en temporada............................. $ 5,899.00 M.N.\n6.- Muelle San José(En horario Nocturno de\n7:00 p.m. a 2:00 a.m.)................ $ 1,180.00 M.N.\n7.- Muelle Proconsa(En horario nocturno de\n7:00 p.m. a 2:00 a.m.)................ $ 4,011.00 M.N.\n8.- Muelle Terraza del Lago (En Horario nocturno de 7:00 p.m. a 2:00 a.m.).... $ 9,910.00 M.N.\ng).- Teatro:\n1.- Teatro al aire libre (En cualquier horario).............................. $ 7,079.00 M.N.\nh).- Renta de Estacionamiento:\n1.- Estacionamiento San Marcos y el contiguo al Centenario (En horario nocturno de 7:00 p.m. a 2:00 a.m.).... $11,798.00M.N.\n2.- Estacionamiento eje central (Zoológico a cualquier hora)..................... $11,798.00M.N.\ni).- Áreas verdes:\n1.- Área verde eje central de lunes a jueves (En el día).................... $ 1 1, 7 9 8.00M.N.\n2.- Área verde eje central de viernes a domingo (En el día)................... $13,568.00M.N.\n3.- Área verde eje central de lunes a jueves(En horario nocturno de 7:00p.m. a 2:00 a.m.).......................... $14,748.00 M.N.\n4.- Área verde eje central de viernes a domingo (En horario nocturno de 7:00 p.m. a 2:00 a.m.).................... $17,697.00 M.N.\n5.- Área verde circundante al teatro al aire libre (sección A)................ $ 8,258.00 M.N.\n6.- Área verde contigua al redondel\n¨sección B¨........................... $ 5,899.00 M.N.\n7.- Área verde contigua al cocodrilario\n¨sección C¨........................... $ 3,539.00 M.N.\nj).- Plaza Centenario:\n1.- Renta de la explanada en la Plaza\nCentenario............................ $ 2,950.00 M.N.\n2.- Renta de la explanada en la Plaza\nCentenario a instituciones de Gobierno de lucro.............................. E XENTO\nk).- Campamentos:\n1.- Área verde para campamento, hasta 10 personas.............................. $ 1,180.00 M.N.\n2.- Área verde para campamento, de 11 a 50 personas.............................. $ 1,770.00 M.N.\n3.- Área verde para campamento, de 51 a\n100 personas.......................... $ 2,950.00 M.N.\nPor cada persona adicional............\n(aplica solo en el punto 3.) $ 23.00 M.N.\nl).- Cursos:\n1.- Curso de Verano curso completo........ $1,770.00 M.N.\n2.- Curso de Verano (1 semana)............ $ 885.00 M.N.\n3.- Curso de Verano (2 semanas)........... $1,180.00 M.N.\n4.- Curso de Verano (Segundo hermano obtiene 20% de descuento en curso completo)............................. $1,416.00 M.N.\n5.- Curso de Verano (3 Hermanos – en curso completo, 2 pagan cuota normal y el tercero cubre el 50%).\n6.- Curso de Verano (Hijos de empleados del patronato, 20% de descuento, en curso completo).\n7.- Curso de Verano para hijos de empleados\nFederal en curso completo, tendrán un\n15% de descuento.\nm).- Locales Comerciales:\n1.- Renta de espacio comercial ambulante\n(Diariamente)......................... $ 473.00 M.N.\n2.- Renta de espacio comercial con estructura fija, semifija – ambulante en andadores (Mensual)................ $ 2,360.00 M.N.\n3.- Puesto Redondel (Meses de febrero, marzo, abril, mayo, junio y julio) pago por mes............................... $3,893.00 M.N.\n4.- Puesto Redondel (Meses de agosto, septiembre, octubre, noviembre, diciembre y enero) pago por mes....... $3,539.00 M.N.\n5.- Locales plaza de la comida 1, 2, 3 y 4\n(Meses de febrero, marzo, abril, mayo, junio y julio) pago por mes........... $2,596.00 M.N.\n6.- Locales plaza de la comida 1, 2, 3 y 4\n(Meses de agosto, septiembre, octubre, noviembre, diciembre y enero) pago por mes................................... $2,360.00 M.N.\n7.- Locales ubicados en andadores, frente al área acuática, a su ingreso y dentro de la misma, así como de la Cabaña del\nBosque en los meses de febrero, marzo, abril, mayo, junio y julio, por cada uno................................... $ 2,596.00 M.N.\n8.- Locales ubicados en andadores, frente al área acuática, a su ingreso y dentro de la misma, así como de la Cabaña del\nBosque en los meses de agosto, septiembre, octubre, noviembre, diciembre y enero, por cada uno....... $ 2,360.00 M.N.\nn).- Paquetes Piñatas:\n1.- Paquete Carrusel:\nIncluye palapa chica, entrada gratis y derecho a todas las atracciones para el cumpleañero, 30 entradas para niño y/o adulto, 20 pases para el carrusel para niños menores de 11 años; cada persona adicional pagará el precio de entrada correspondiente, adulto y/o niño....... $ 1,416.00 M.N.\n2.- Paquete Tobogán de Costales:\nIncluye palapa grande, entrada gratis y derecho a todas las atracciones para el cumpleañero, 30 entradas para niño y/o adulto, 20 pases para el tobogán para niños menores de 11 años; cada persona adicional pagará el precio de entrada correspondiente, adulto y/o niño....... $ 2,065.00 M.N.\n3.- Paquete Diviertas:\na).- Palapa chica y atracciones, incluye entrada gratis y derecho a todas las atracciones para el cumpleañero, 30 entradas para niño y/o adulto, y 30 paquetes de atracciones ya sea niño o adulto que incluye paseo en: tren, 1 vaso de alimento para animales de la granjita, 3 deslizadas al tobogán de costales y un recorrido en lancha, por cada persona adicional pagará el precio de entrada y en su caso precio de paquete de atracciones correspondiente\n(adulto y/o niño)...................... $ 2,950.00 M.N.\n4.- Paquete Emociones:\na).- Palapa grande y atracciones, incluye entrada gratis y derecho a todas las atracciones para el cumpleañero, 30 entradas para niño y/o adulto y 30 paquetes de atracciones ya sea niño o adulto que incluye paseo en: tren, 1 vaso de alimento para animales de la granjita, 3 deslizadas al tobogán de costales y un recorrido en lancha, por cada persona adicional pagará el precio de entrada y en su caso precio de paquete de atracciones correspondiente\n(adulto y/o niño)...................... $ 3,539.00 M.N.\n5.- Paquete Chapuzón:\na).- Palapa chica y acuático incluye entrada gratis y derecho a todas las atracciones para el cumpleañero, 30 entradas para niño y/o adulto, y 30 accesos al área acuática (sujeto a disponibilidad)..... $ 2,360.00 M.N.\n6.- Paquete Refresques:\na).- Palapa chica y acuático incluye entrada gratis y derecho a todas las atracciones para el cumpleañero, 50 entradas para niño y/o adulto, y 50 accesos al área acuática (sujeto a disponibilidad)..... $ 3,776.00 M.N.\n7.- Paquete Granjita:\nIncluye palapa chica, entrada gratis y derecho a todas la atracciones para el cumpleañero, 30 entradas para niño y/o adulto, 20 pases para la granjita cada persona adicional pagará el precio de entrada correspondiente, adulto y/o niño................................. $ 1,336.00 M.N. ñ).- Cortesías:\n1.- Promoción por difusión en medios de comunicación:\nAdulto (1 acceso al parque)........... EXENTO\nNiños (1 acceso al parque)........... EXENTO\nCarrusel (1 paseo).................... EXENTO\nTren (1 vuelta)....................... EXENTO\nTobogán de costales (3 deslizadas).... EXENTO\nLanchas (1 recorrido)................. EXENTO\nÁrea Acuática (1 acceso).............. EXENTO\nCurso de Verano (1 acceso)........... EXENTO\n2.- Festejos por fechas especiales:\nDía del niño (1 acceso a niños de 3 a\n11 años).............................. EXENTO\nDía de las madres (1 acceso adulto madre de familia).................... EXENTO\nDía de la familia (2x1 a la Familia en adultos y/o niños)................... EXENTO\nReferente al ciudadano del medio ambiente (acceso con referencia al evento).............................. EXENTO\nCurso de Verano (1 acceso)........... EXENTO\n3.- Un día al año la entrada para niños de 4 a 12 años....................... E X ENTO\nDía seleccionado por el Patronato.\no).- Otros Servicios:\n1.- Sala audiovisual (Sin refrigeración).. $ 943.00 M.N.\n2.- Sala audiovisual (Con refrigeración).. $2,360.00 M.N.\n3.- Renta de carteleras (Para empresas y eventos) mensual...................... $4,130.00 M.N.\n4.- Descuento para empleados del\nAyuntamiento, Gobierno del Estado y del\nPatronato del Bosque y Zoológico de la\nCiudad de Mexicali (Renta de palapas o espacio para eventos particulares) 15% de descuento por evento.\n5.- Cuota de recuperación por el uso de energía eléctrica (Aparatos de sonido, inflables, lámparas, aparatos eléctricos y/o electrónicos).......... $177.00 M.N.\nII.- Parque Ecológico Laguna México:\na).- Entrada:\n1.- Entrada General.................... EXENTO\nIII.- Otros Servicios: realice el Bosque y Zoológico de la Ciudad de Mexicali, los que en todo caso serán proporcionales al costo del servicio. Los ingresos que por concepto de venta de diversos productos, derechos, transferencias, asignaciones, ayudas sociales y donaciones que se perciban, pasarán a\nMexicali.\nSERVICIOS QUE PRESTA EL PATRONATO DEL PARQUE\nVICENTE GUERRERO DE LA CIUDAD DE MEXICALI\nARTÍCULO 69.- Los servicios que presta por el uso de inmobiliario e instalación de los parques asignados al Patronato Parque Vicente\nGuerrero de la Ciudad de Mexicali, se cobrarán conforme a lo siguiente:\nI.- Los ingresos por conceptos son:\nTARIFA\nMONEDA NACIONAL\nA).- PARQUE VICENTE GUERRERO:\n1.- Entradas:\na).- Niña y niño menor de 9 años y adulto mayor presentando la tarjeta de INAPAM o cualquier identificación vigente que lo acredite, usuarios del bazar y las personas con discapacidad quedaran..... EXENTO\nSi el bazar se instala en fecha que exista un evento dentro del parque, el costo del boleto de entrada para los usuarios será de $ 10.00 M.N.\nb).- Boleto entrada, 10 años en adelante... $ 10.00 M.N.\nc).- Boleto festivales adulto (día del niño\nHalloween, navideño, ferias, etc.).... $ 40.00 M.N.\nd).- Boleto festival niño mayor de 3 años y menor de 12 (Halloween, navideño, ferias, etc.)......................... $ 20.00 M.N.\n2.- Estacionamiento por día:\na).- Estacionamiento por vehículo......... $ 21.00 M.N.\nb).- Estacionamiento por vehículo en eventos vespertinos y nocturnos..... $ 56.00 M.N.\nc).- Estacionamiento por camión por día.... $ 56.00 M.N.\nd).- Estacionamiento para usuarios del\nBazar, cuando no se lleve a cabo otro evento en el parque.................. $ 11.00 M.N.\ne).- Estacionamiento exclusivo para usuarios de la cancha de futbol rápido $ 11.00 M.N.\nf).- Estacionamiento VIP................... $100.00 M.N.\n3.- Renta de instalaciones y otros servicios:\na).- Palapa de la 01 a la 13 y de 15 a la 19 $ 668.00 M.N.\nb).- Palapa número 14 y 20................. $1,836.00 M.N.\nc).- Áreas verdes........................1) $1,590.00 M.N.\n2) $2,650.00 M.N.\n3) $5,300.00 M.N.\nd).- Área verde anexa al vagón...........1) $2,500.00 M.N.\n2) $3,750.00 M.N.\n3) $7,500.00 M.N.\ne).- Área del vagón.....................1) $2,000.00 M.N.\n2) $4,000.00 M.N.\n3) $6,000.00 M.N.\nf).- Macro Plaza.........................1) $ 8,000.00 M.N\n2) $13,250.00 M.N.\n3) $26,500.00 M.N.\ng).- Plaza del Sol.......................1) $ 5,500.00 M.N\n2) $ 8,000.00 M.N.\n3) $15,900.00 M.N.\nh).- Salón las misiones..................1) $2,300.00 M.N.\n2) $3,180.00 M.N.\n3) $6,360.00 M.N.\ni).- Cafetería frente a Salón las Misiones\n(cuota mensual)..................... $2,600.00 M.N.\nj).- Isla de las Estrellas...............1) $5,300.00 M.N.\n2) $7,420.00 M.N.\n3) $10,600.00 M.N\nk).- Kiosco..............................1) $1,500.00 M.N.\n2) $2,100.00 M.N.\n3) $2,915.00 M.N.\nl).- Deposito por concepto de limpieza en renta de palapas...................... $ 500.00 M.N.\nLos sujetos que renten las instalaciones se le aplicarán los costos de la siguiente manera:\nSe aplicará el costo 1) a las Dependencias y Entidades de la\nAdministración Pública Municipal, Estatal, y Federal; órganos autónomos que realicen eventos sin fines de lucro; cuando se trate de eventos de menos de 900 personas y sean promotores que busquen el desarrollo del entretenimiento en la Ciudad, eventos especiales para beneficio social, eventos culturales sin fines de lucro y eventos sociales.\nSe aplicará el costo 2) a Asociaciones civiles y organismos sin fines de lucro legalmente constituidas, instituciones educativas públicas, niñez y las juventudes; cuando se trate de eventos de 901 a 1600 personas\nCiudad, actividades recreativas sin fines de lucro, eventos religiosos e instituciones educativas privadas.\nSe aplicará el costo 3) a todos aquellos que no se encuentren dentro de los sujetos mencionados anteriormente.\nm).- Arrendamiento de terreno por m2 en estacionamientos principal y noroeste y en áreas del interior del parque\n(zona urbana, plaza central, sección para mascotas, zona del antiguo palenque), mensual................... $55.00 a\n$75.00 M.N.\nn).- Arrendamiento de terreno por m2 en área noroeste del parque,cuota mensual $ 9.00 a\n$ 75.00 M.N. ñ).- Arrendamiento de espacio por m2 en interior del parque (zona urbana, plaza central, sección para mascotas, zona del antiguo palenque), mensual.. $ 280.00 M.N.\n4.- Renta de espacios publicitario, atracciones, cursos y otros:\na).- Valla Publicitaria atrás de cancha de futbol (Blvd. López Mateos), renta mensual............................... $ 1,050.00 M.N.\nb).- Valla Publicitaria en estacionamiento noroeste(Calz. Milton Castellanos) renta mensual......................... $3,339.00 M.N.\nc).- Valla Publicitaria en cerco perimetral en calles Cristóbal Garcilaso y Alfonso\nEsquer, renta mensual................. $1,050.00 M.N.\nd).- Valla publicitaria en estacionamiento principal (Calle Alfonso Esquer), renta mensual............................... $3,339.00 M.N.\ne).- Estacionamiento por cajón por día para renta de espacio para eventos especiales, exposiciones, juegos o ferias.\nDe septiembre a mayo.................. $ 25.00 M.N.\nDe junio a agosto.................... $ 13.00 M.N.\nLa cuota establecida se cobrará por evento o actividad, entendiéndose que no exceda de un periodo de 30 días naturales cuando se trate de arrendamiento.\nf).- Cuota de recuperación por el uso de energía eléctrica por evento (Rockolas, inflables, abanicos, aparatos eléctricos)........................... $ 179.00 M.N.\ng).- Cuota de recuperación por el uso de agua potable en chapoteaderos de palapas............................... $ 150.00 M.N.\nh).- Cuota de recuperación por el uso de agua potable para brincolinas acuáticas y albercas............................ $ 200.00 M.N.\ni).- Boleto tren recreativo, una vuelta al perímetro del parque.................. $ 12.00 M.N.\nj).- Uso de cuatriciclos (media hora)...... $ 34.00 M.N.\nk).- Uso de brincolina (20 minutos)......... $ 35.00 M.N.\nl).- Renta de brincolina por evento (5 horas máximo)............................... $ 600.00 M.N.\nm).- Tobogán (4 vueltas)................... $ 17.00 M.N.\nn).- Pulsera (Incluye entrada y boletos para el tren recreativo, el tobogán y los cuadriciclos)..................... $ 55.00 M.N. ñ).- Paquete escolar (Incluye entrada y boletos para el tren recreativo, el tobogán y los cuadriciclos)........... $ 50.00 M.N.\no).- Autorización a vendedores ambulantes por día, espacio de 3x3 mts (Puestos chicos/móviles):\nDe septiembre a mayo............... $ 250.00 M.N.\nDe junio a agosto $ 120.00 M.N.\np).- Autorización a vendedores ambulantes por día, espacios hasta 6 x 6 mts\n(puestos fijos):\nDe septiembre a mayo............... $ 450.00 M.N.\nDe junio a agosto $ 240.00 M.N.\nq).- Autorización a vendedores ambulantes por día en eventos vespertinos masivos:\nDe 3x3 mts........................... $ 570.00 M.N.\nDe 6x6 mts........................... $ 1,113.00 M.N.\nr).- Autorización a vendedores ambulantes por día en eventos nocturnos masivos:\nDe 3x3 mts........................... $1,113.00 M.N.\nDe 6x6 mts........................... $2,226.00 M.N.\ns).- Por venta para consumo inmediato de bebidas alcohólicas “cerveza” en el interior de las instalaciones, se reintegrará al Patronato por cada unidad vendida de lata o media de vidrio de 355 ml**:\nSi el precio de venta es de $25.00 $ 4.00 M.N.\nSi el precio de venta es de $30.00 $ 5.00 M.N.\nSi el precio de venta es de $35.00 $ 6.00 M.N.\nY así sucesivamente por cada aumento de 5.00 en el precio de venta se aumentara el costo en $1.00 M.N.\n**En el caso de venta de la denominada “caguama”, esta equivaldrá a tres unidades, y la venta de la denominada\n“caguamón” equivaldrá a cuatro unidades; el mismo contenga se hará la conversión a unidades de 355 ml.\nt).- Por venta para consumo inmediato de bebidas alcohólicas exceptuando la\n“cerveza” en el interior de las instalaciones, se reintegrará al patronato por el espacio rentado:\nPlaza del Sol........................ $ 2,100.00 M.N.\nMacroplaza........................... $ 4,200.00 M.N.\nu).- Inscripción a curso de verano*......... $ 890.00 M.N.\nv).- Chapoteadero:\nPersonas con discapacidad............. EXENTO\nNiños de 4 a 15 años (todo el día).... $ 34.00 M.N.\nAdultos (todo el día)................. $ 44.00 M.N.\nw).- Renta de área de Chapoteadero......... $ 7,350.00 a\n$10,500.00 M.N.\nx).- Camisetas............................ $ 200.00 M.N.\ny).- Gorras.............................. $ 350.00 M.N.\nz).- Llaveros............................ $ 70.00 M.N. aa).- Tazas............................... $ 120.00 M.N. bb).- Peluches............................ $ 150.00 M.N. cc).- Termos.............................. $ 170.00 M.N. dd).- Renta de cancha de futbol soccer:\n1.- Futbol rápido por hora (sin luz)...... $ 150.00 M.N.\n2.- Futbol rápido por hora (con luz)...... $ 170.00 M.N.\n3.- Publicidad al interior de la cancha:\n(cobro mensual)\nZona perimetral 2.4 x 1.2 mts......... $1,113.00 a\n$2,226.00 M.N.\nZona de esquina 2.4 x 2.4 mts......... $1,113.00 a\n$2,783.00 M.N.\nZona frontal de 4.80 x 3.66 mts....... $1,670.00 a\n$3,339.00 M.N. más de dos hijos, al tercero y subsiguiente se les otorgará un descuento del 30%. Hijas e hijos de empleadas y empleados del Ayuntamiento tendrán un 20% de descuento.\nB).- PARQUE CRI - CRI:\n1.- Palapa 00 El ratón vaquero................. $ 610.00 M.N.\n2.- Palapa 01 La marcha de las letras, 02 El\nChorrito, 03 Negrito Sandia, 04 La patita, 05\nBombón Primero, 06 Caminito de la Escuela y\n07 Di Por qué............................ $ 489.00 M.N.\n3.- Palapa 08 CRI-CRI.......................... $1,110.00 M.N.\n(Incluye área verde)\n4.- Cuota de recuperación por el uso de energía eléctrica por evento (Rockolas, inflables, abanicos, aparatos eléctricos)............. $ 179.00 M.N.\n5.- Kiosco Los Cochinitos dormilones........... $ 1,500.00 M.N.\n6.- Uso de todo el parque, cualquier día de lunes a viernes:\nDe septiembre a mayo..................... $ 9,350.00 M.N.\nDe junio a agosto....................... $ 7,000.00 M.N.\n7.- Uso de todo el parque, cualquier día de sábado o domingo:\nDe septiembre a mayo..................... $11,350.00 M.N\nDe junio a agosto....................... $ 8,000.00 M.N\n8.- Renta mensual de Cafetería Barquito de Nuez. $ 1,836.00 M.N.\n9.- Renta del área norte o sur del parque, cualquier día:\nDe septiembre a mayo..................... $3,895.00 M.N.\nDe junio a agosto....................... $2,300.00 M.N.\n10.- Renta del Salón de Usos Múltiples.......... $ 2,000.00 M.N. cerco perimetral (Av. Brasil, Rio Mocorito y\nAv. Argentina) cuota mensual............... $3,000.00 M.N.\n12.- Renta mensual de anexo a Cafetería......... $ 800.00 M.N.\n13.- Autorización a vendedores ambulantes por día, espacio de 3x3 mts (puestos chicos/ móviles):\nDe septiembre a mayo..................... $ 250.00 M.N.\nDe junio a agosto........................ $ 120.00 M.N.\n14.- Depósito por concepto de limpieza en renta de palapas................................. $ 500.00 M.N.\n15.- Cuota de recuperación por uso de agua potable para brincolinas acuáticas y albercas....... $ 200.00 M.N.\nC).- PARQUE VILLA AVENTURA:\n1.- Uso de todo el parque, cualquier día de lunes a viernes, por doce horas............ $ 4,897.00 M.N.\n2.- Uso de todo el parque, cualquier día de sábado a domingo,.......................... $ 6,122.00 M.N.\n4.- Cafetería.................................. $ 1,691.00 M.N.\n5.- Cuota de recuperación por el uso de energía eléctrica por evento (Rocolas, inflables, abanicos, aparatos eléctricos)............. $ 179.00 M.N.\nII.- Otros Servicios:\nEl Patronato del Parque Vicente Guerrero de la Ciudad de Mexicali, Estatal y Municipal, así como de Personas Físicas y Morales, subsidios, aportaciones, subvenciones, donativos en numerario, servicios, especie y bienes muebles.\nMexicali, los que en todo caso serán proporcionales al costo del servicio. Los ingresos que por concepto de derechos, transferencias, asignaciones y ayudas sociales que se perciban, pasarán a formar parte del patrimonio del Parque Vicente Guerrero de la Ciudad de Mexicali.\nSERVICIOS QUE PRESTA EL INSTITUTO MUNICIPAL\nDEL DEPORTE Y LA CULTURA FÍSICA DE MEXICALI\nARTÍCULO 70.- Los servicios que presta el Instituto Municipal del\nDeporte y la Cultura Física, se cobrarán conforme a lo siguiente:\nI.- Arrendamiento de espacios deportivos:\nTARIFA\nMONEDA NACIONAL\na).- Gimnasios:\n1.- Espectáculo Musical................... $ 1 2, 0 0 0. 00 M.N.\n2.- Función de Deportiva.................. $11,000.00 M.N.\n3.- Evento Social......................... $10,000.00 M.N.\n4.- Otros................................. $ 9,000.00 M.N.\n5.- Entrada General...................... $ 12.00 M.N.\nb).- Canchas de Fútbol Soccer:\n1.- Campo de Fútbol Soccer por día (6 horas máximo por día)................. $ 1,350.00 M.N.\n2.- Campo de Futbol Soccer por partido.... $ 280.00 M.N.\n3.- Campo de Futbol Soccer por hora....... $ 170.00 M.N.\n4.- Renta por 4 días al mes(6 horas al día)............................. $ 2,200.00 M.N.\n5.- Otros Eventos Deportivo y Culturales\n(Really, Premiaciones, Escolares, Religiosos)........................... $ 1,150.00 M.N.\nc).- Canchas de Béisbol/Softbol:\n1.- Campo de Béisbol o Softbol por día (6 horas máximo por día)................. $ 1,350.00 M.N.\n2.- Campo de Béisbol o Softbol por partido $ 280.00 M.N.\n3.- Campo de Béisbol o Softbol por hora... $ 170.00 M.N.\n4.- Renta por 4 días al mes (6 horas al día)................................. $ 2,200.00 M.N.\n5.- Otros Eventos Deportivo y Culturales\n(Really, Premiaciones, Escolares, Religiosos)........................... $ 1,150.00 M.N.\nd).- Canchas de usos múltiples (Basquetbol, Voleibol y otros espacios deportivos):\n1.- Campo de usos múltiples por día....... $ 850.00 M.N.\n(6 horas máximo por día)\n2.- Campo de usos múltiples por partido... $ 280.00 M.N.\n3.- Campo de usos múltiples por hora...... $ 280.00 M.N.\n4.- Renta por 4 días al mes (6 horas al día)................................. $ 2,200.00 M.N.\n5.- Otros Eventos Deportivo y Culturales\n(Really, Premiaciones, Escolares, Religiosos)........................... $ 1,150.00 M.N.\ne).- Albercas (arrendamiento únicamente de la mitad de la alberca):\n1.- Alberca por día (4 horas máximo por día).................................. $ 1,350.00 M.N.\n2.- Alberca por hora...................... $ 170.00 M.N.\n3.- Otros, costo diario................... $ 560.00 a\n$ 1,150.00 M.N.\nf).- Otros Arrendamientos:\n1.- Material deportivo por evento (vallas, balones, cronómetros, otros, etc.) por cada uno.............................. $ 60.00 M.N.\nII.- Renta de Otros espacios distintos a los deportivos:\nTARIFA\nMONEDA NACIONAL\na).- Por la renta de espacios comerciales\n(alimentos, dulces, otros, etc.):\nMensual:................................... $ 1,200.00 a\n$ 4,500.00 M.N.\nPor día:................................... $ 225.00 M.N.\nb).- Por la renta de espectaculares:\nAnual:..................................... $63,600.00 a\n$89,040.00 M.N.\nMensual:................................... $ 8,480.00 M.N.\nc).- Renta de espacios publicitarios:\nMensual:................................... $2,000.00 M.N.\nd).- Renta de espacios para feria y eventos:\nMensual:.................................. $10,800.00M.N.\nPor día:.................................. $ 500.00 M.N.\nIII.- Entrada a instalaciones deportivas:\na).- Entrada a Unidades Deportivas:\nNecaxa, Campo anexo Necaxa, Industrial, Alamitos, Baja California, Centro Recreativo\nMunicipal, Cóndor, Independencia, Nacozari, Nacionalista, División del Norte, Atlético del Rey, 18 de Marzo, Carbajal, Robledo, Valle Dorado, Infonavit Cucapah, Hidalgo Sur y Ciudad Morelos.\nTARIFA\nMONEDA NACIONAL\n1.- Entrada General mayor de 12 años...... $ 12.00 M.N.\n2.- Entrada a menor de 12 años............ EXENTO\n3.- Entrada adulto mayor presentando tarjeta INAPAM o cualquier identificación vigente que lo acredite EXENTO\n4.- Entrada a Persona con discapacidad... EXENTO\nb).- Polideportivo:\nTARIFA\nMONEDA NACIONAL\n1.- Entrada Niños, hasta 12 años.......... EXENTO\n2.- Entrada adultos....................... $ 8.00 M.N.\n3.- Entrada adulto mayor presentando tarjeta INAPAM o cualquier identificación vigente que lo acredite. EXENTO\n4.- Entrada a personas con discapacidad... EXENTO\nc).- Ingreso a albercas:\n1.- Admisión general...................... $ 20.00 M.N.\n2.- Entrada adulto mayor presentando tarjeta INAPAM o cualquier\nIV.- Programas y Cursos:\nTARIFA\nMONEDA NACIONAL\n1.- Programa Vacacional de Verano impartido en las instalaciones del\nInstituto, por participante:\n1).- Primer niño...................... $ 900.00 M.N.\n2).- Segundo hermano en adelante...... $ 700.00 M.N.\n2.- Curso de natación (por participante por mes).............................. $ 500.00 M.N.\n3.- Cursos diversos en instalaciones deportivas del Instituto por persona.. $ 500.00 M.N.\nV.- Otros Servicios:\n1.- Inscripción al Medio Maratón por persona.. $290.00 M.N.\n2.- Impresión de números para carreras........ $ 10.00 M.N.\n3.- Servicio de traslado............ $2,616.00 a $5,272.00M.N\n* Habrá descuentos para personas discapacitadas, de la tercera edad, apoyo institucional, programas de tipo institucional, por intercambio de servicios, según lo establece el reglamento de becas del instituto.\nMexicali, los que en todo caso serán proporcionales al costo del servicio. Los ingresos que por concepto de derechos, transferencias, asignaciones y ayudas sociales que se perciban, pasarán a formar parte de Mexicali.\nSERVICIOS QUE PRESTA LA COMISIÓN DE\nDESARROLLO INDUSTRIAL DE MEXICALI\nARTÍCULO 71.- Los servicios que presta la Comisión de Desarrollo\nIndustrial de Mexicali, se cobrarán conforme a lo siguiente:\nI.- Grupos de empresas que sean Desarrolladores Industriales\n(Parques Industriales), pagarán lo siguiente:\nTARIFA\nMONEDA NACIONAL\na).- Cuota de Inscripción....................... $10,000.00M.N.\nb).- Desarrolladores Industriales (Parques\nIndustriales) cuota mensual en el rango..... $ 6,938.00 a\n$43,876.00M.N.\nEn rango menor a quienes incorporen 1 parque industrial.\nEn rango medio a quienes incorporen 2 parques industriales.\nEn rango mayor a quienes incorporen 3 parques industriales o más.\nII.- Empresas de Servicios o Subcontrato, pagarán conforme a la siguiente clasificación:\na).- Cuota de Inscripción....................... $ 4,505.00 a\n$13,780.00M.N.\nEn rango menor a quienes se incorporen como MIPYME. subcontrato.\nb).- Empresas de Servicio o Subcontrato, ubicadas en México o en los Estados Unidos de\nNorteamérica, cuota mensual de........... $ 1,400.00 a\n$ 9,500.00M.N. interesadas en pertenecer en una red de contactos.\nEn un segundo rango Empresas MIPYME.\nEn un tercer rango Hoteles, Servicios de logística y demás proveedores no esenciales. ubicados en México o en los Estados Unidos de Norteamérica, tales como: Empresas de consultoría y administración para la instalación de empresas extranjeras en México, Agentes\nAduanales, Contadores, Abogados, Contract Manufacturing, entre otros.\nEn un quinto rango Empresas Constructoras, Servicios y\nProveedores esporádicos.\nLos sujetos que realicen los pagos referidos en la Fracción I, inciso\nb) y Fracción II inciso b), podrán gozar de un descuento por pago anticipado equivalente a una mensualidad, siempre y cuando realicen el pago anual en una sola exhibición durante el mes de enero y no cuenten con adeudos en ejercicios anteriores.\nLos sujetos que se incorporen a la Fracción I, inciso b), así como a la Fracción II, inciso b), podrán exentar el pago del inciso a) de las citadas fracciones, siempre y cuando realicen el pago total de los meses correspondientes desde su incorporación hasta el mes de diciembre del ejercicio en curso, debiendo ser este en una sola exhibición durante el mes de su incorporación.\nLos Grupos de Empresas que se incorporen a dos o más de los conceptos establecidos en las fracciones I inciso b) y II inciso b), pagarán el inciso y/o concepto de mayor valor a su precio completo y podrán gozar de un descuento del 50% en el resto de los incisos y/o conceptos que se incorporen.\nIII.- Otros Servicios: realice la Comisión de Desarrollo Industrial de Mexicali, los que en todo caso serán proporcionales al costo del servicio. Los ingresos que por concepto de derechos, transferencias, asignaciones y ayudas sociales que se perciban, pasarán a formar parte del patrimonio de la\nComisión de Desarrollo Industrial de Mexicali.\nSERVICIOS QUE PRESTA EL PATRONATO DE LAS\nFIESTAS DEL SOL DE LA CIUDAD DE MEXICALI\nARTÍCULO 72.- Los servicios que presta el Patronato de las Fiestas del\nSol de la Ciudad de Mexicali, se cobrarán conforme a lo siguiente:\nTARIFA\nMONEDA NACIONAL\nI.- Los ingresos por concepto de entradas a las Fiestas del Sol:\na).- Entrada Adulto............................. $ 60.00 M.N.\nb).- Entrada menor de 12 años................... EXENTO\nc).- Entrada Adulto Mayor presentando tarjeta de\nINAPAM o cualquier identificación vigente que lo acredite............................ EXENTO\nd).- Entrada para personas con discapacidad..... EXENTO\ne).- Entrada para los que cumplan años en el periodo de las Fiestas del Sol, únicamente el día del cumpleaños...................... EXENTO\nf).- Entrada los días Lunes únicamente durante las fiestas del sol........................ EXENTO\ng).- Boleto Zona VIP de las Islas de las\nEstrellas, durante las fiestas del sol de $250.00 M.N.acuerdo a la calidad del Artista........... $3,500.00 M.N\nEl rango se aplicará por el nivel de trayectoria del Artista.\nh).- Boleto Zona VIP de las islas de las estrellas, durante las fiestas del sol de personas con discapacidad y un acompañante.. EXENTO\nII.- Estacionamiento:\na).- Estacionamiento Exclusivo (VIP)............ $ 100.00 M.N.\nb).- Estacionamiento durante Fiestas del Sol.... $ 50.00 M.N.\nc).- Estacionamiento en evento artístico........ $ 50.00 M.N.\nd).- Estacionamiento general en eventos con fines no lucrativos (Religiosos, culturales, escolares, etc.)........................... $ 30.00 M.N.\ne).- Estacionamiento general fuera del periodo\nFiestas del Sol, por cajón por día se cobrará de................................. $ 20.00 M.N.\nf).- Estacionamiento general fuera del periodo\nFiestas del Sol, renta del espacio para módulos de venta........................... $ 3,000.00 M.N.\nIII.- Renta de Módulos para Fiestas del Sol:\na).- Zona #1: (Isla de las Estrellas):\n1).- Venta de cerveza, licor y alimentos........ $ 4 9,250.00 $68,500.00 M.N.\n2).- Venta de cerveza y alimentos............... $50,000.00 $58,700.00 M.N.\n3).- Con venta de alimentos..................... $40,000.00 $49,000.00 M.N.\n4).- Por espacio adicional tipo terraza, se pagará un 20% adicional por un segundo nivel y un\n15% más por un tercer nivel y subsecuentes, más el costo del módulo\nb).- Zona #2: (La Terraza)\n1).- Venta de cerveza, licor y alimentos........ $ 4 0,000.00 $44,000.00 M.N.\n2).- Con venta de alimentos..................... $20,000.00 $24,000.00 M.N.\nc).- Zona # 3: (Las Palmeras)................... $25,000.00 $26,500.00 M.N.\nd).- Zona #4: (Asphalt City)\n1).- Venta de cerveza y alimentos............... $20,000.00 $24,500.00 M.N.\n2).- Con venta de alimentos..................... $15,000.00 $22,000.00 M.N.\ne).- Zona #5: (Zona Comercial).................. $20,000.00 $24,500.00 M.N.\nf).- Zona #6: (Aztlán)\n1).- Venta de cerveza y alimentos............... $20,000.00 $25,000.00 M.N.\ng).- Zona #7: (Plaza Infantil)..................... $15,000.00 $22,000.00 M.N.\nh).- Zona #8 (Hacienda del Norte)................. $20,000.00 $24,500.00 M.N.\ni).- Estructura K............................... $20,000.00 $60,000.00 M.N.\nj).- Zona #9: (Pabellón Artesanal)\n1).- Acreditando ser Artesanos.................. $ 7,000.00 $10,000.00 M.N.\n2).- Sin acreditación de ser Artesanos.......... $20,000.00 $24,500.00 M.N.\nk).- Zona #10: (Plaza Valle)\n1).- Lineal..................................... $ 1 5, 000.00 $22,000.00 M.N.\n2).- Esquina, con venta de licor, cerveza y alimentos.................................. $20,000.00 $24,500.00 M.N.\nl).- Espacio para comerciante hasta 1.25 mts cuota diaria............................... $ 400.00 $ 600.00 M.N.\nm).- Área para expendedores de comida rápida en unidades denominadas “Camión o carreta de comida”..................................... $ 1,000.00 $10,000.00 M.N.\nn).- Artesanos en cualquier área con acreditación............................... $ 7,000.00 $10,000.00 M.N. ñ) Zona #11: (Pabellón Off Road)\n1).- Por todo el periodo de la feria.......... $18,000.00 M.N.\n2).- Barra de cerveza y bebida............... $100,000.00 M.N.\no) Zona #12: (Premium Juegos Mecánicos) $40,000.00 M.N.\nEn todos los incisos de esta fracción se pagará la cuota mínima si se cubre el costo total a más tardar el 30 de abril, a partir del 01 de mayo aplicará la cuota máxima.\nIV.- Los ingresos por concepto de entrada a la Villa Navideña:\na).- Entrada Adulto $ 20.00 M.N.\nb).- Entrada Adulto Mayor presentando tarjeta de\nINAPAM o cualquier identificación vigente que lo acredite............................ EXENTO\nc).- Entrada para personas con discapacidad.... EXENTO\nd).- Entrada para los que cumplan años en el periodo de la Villa Navideña, únicamente el día del cumpleaños......................... EXENTO\ne).- Entrada menor de 12 años.................... EXENTO\nf).- Por el uso de la pista de hielo............ $ 30.00 M.N.\nV.- Renta de Módulos para Villa Navideña:\na).- Zona #1:................................... $20,000.00 $24,500.00 M.N.\nb).- Zona #2:................................... $15,000.00 $22,000.00 M.N.\nc).- Zona #3:................................... $15,000.00 $19,500.00 M.N.\nd).- Zona #4:................................... $20,000.00 $24,500.00 M.N.\ne).- Artesanos en cualquier área con acreditación............................... $ 7,000.00 $10,000.00 M.N.\nf).- Espacio para comerciante hasta 1.25 mts cuota diaria Villa Navideña................ $ 200.00 $ 400.00 M.N.\ng).- Área para expendedores de comida rápida en unidades denominadas “Camión o carreta de de Comida”................................. $ 1,000.00 $10,000.00 M.N.\nEn todos los incisos de esta fracción se pagará la cuota mínima si se cubre el costo total a más tardar el 30 de noviembre, a partir del 01 de diciembre aplicará la cuota máxima.\nEn caso que algún espacio o Módulo no se rentará este espacio podrá utilizarse por Módulos Institucionales, Asociaciones Civiles sin fines de lucro, etc. En estos casos el costo del Módulo será EXENTO.\nVI.- Por la Renta del Palenque FEX durante las\nFiestas del Sol........................... $1’000,000.00 $1’500,000.00M.N más tardar el 30 de abril, a partir del 01 de mayo aplicará la cuota máxima.\nVII.- Por la Renta de Instalaciones del Patronato\nFiestas del Sol: (En periodos distintos a las fechas de Fiestas del Sol)\na).- Palenque FEX............................... $37,000.00 M.N.\nb).- Por servicio adicional de aire acondicionado en las instalaciones del Palenque FEX a solicitud expresa del arrendatario, se cubrirá previo al evento.................... $ 6,000.00 M.N.\nc).- Dentro del Palenque del FEX, fuera del periodo Fiestas del Sol, renta del espacio para módulos de venta...................... $ 3,000.00 M.N.\nd).- Plaza Calafia.............................. $36,000.00 M.N\ne).- Dentro de la Plaza Calafia, renta del espacio para módulos de venta.............. $ 3,000.00 M.N.\nf).- Zona #1.................................... $31,000.00 M.N\ng).- Dentro del área de la Isla de las\nEstrellas y fuera del periodo Fiestas del\nSol renta del espacio para módulos de venta $ 3,000.00 M.N.\nh).- Carpa Fex.................................. $17,000.00 M.N.\ni).- Dentro del área de la Carpa Fex y fuera del periodo Fiestas del Sol, renta del espacio para módulos de venta...................... $ 3,000.00 M.N.\nj).- Jardín del Fex............................. $20,000.00 M.N.\nEn eventos con fines no lucrativos, religiosos, escolares, etc. En los de hasta $37,000.00 M.N.\nVIII.- Por la Renta de las Instalaciones para Eventos\nMasivos: (En periodos distintos a las fechas de\nFiestas del Sol)\na).- Zona #11 Área de Juegos Mecánicos.......... $31,000.00 M.N.\nb).- Dentro del área de juegos mecánicos y fuera del periodo Fiestas del Sol, la renta del espacio para módulos de venta......... $ 3,000.00 M.N.\nc).- Estacionamiento Sur........................ $10,500.00 M.N.\nd).- Zona #6…................................. $15,000.00 M.N.\n(Incluye módulos y escenario)\ne).- Zona #7.................................... $15,000.00 M.N.\nf).- Zona #8…................................. $15,000.00 M.N.\ng).- En la realización de cualquier evento a facultad expresa del Patronato, se aplicará mantenimiento en cualquier espacio del FEX, por cuota de mantenimiento y limpieza, dependiendo del tamaño del evento.......... $14,300.00 M.N.\nIX.- Por la Renta de las Instalaciones para Publicidad:\na).- Valla Publicitaria, para Entidades No\nLucrativas el costo será................... EXENTO\nb).- Valla Publicitaria, renta mensual.......... $ 2,000.00 M.N.\nc).- Renta de Marquesina fuera de Fiestas del\nSol, costo mensual......................... $ 2,250.00 M.N.\nd).- Renta de Marquesina: Fiestas del Sol tarifa diaria..................................... $1,000.00 M.N.\ne).- Renta de Marquesina, para Entidades No\nLucrativas el costo será................... EXENTO\nf).- Por venta de publicidad digital Fex TV “El\nPod Cast” por bimestre:\n1.- Portada............................... $25,000.00 M.N.\n2.- Por plana............................. $16,000.00 M.N.\n3.- Por media plana....................... $ 8,000.00 M.N.\n4.- Por un cuarto de plana................ $ 4,000.00 M.N.\n5.- Por contraportada..................... $25,000.00 M.N\ng).- Venta de publicidad en eventos del Fex o\nPlaza Calafia:\n1.- Por engomado en silla, por día........ $ 30.00 M.N.\n2.- Letrero luminoso o lona, anual........ $30,000.00 M.N\n3.- Por permiso de volanteo, por evento... $ 1,500.00 M.N.\nX.- Por concepto de Derecho de venta de productos:\na).- Venta de lata y media de vidrio de cerveza de 355 mililitros, en periodo Fiestas del\nSol, por cada unidad vendida se reintegrará al Patronato............................... $ 5.50 $ 7.00 M.N.\nSe pagará la cuota mínima si se contrata renta de espacio a más tardar el 30 de abril, a partir del 01 de mayo aplicará la cuota máxima.\nb).- Venta de lata y media de vidrio de cerveza de 355 mililitros, en periodo fuera de\nFiestas del Sol y en el Palenque dentro del periodo de fiestas del sol:\n1.- Con precio de venta por unidad a valor de $ 25 m.n. reintegrará al Patronato el importe proporcional por cada unidad vendida de............................. $ 3.30 M.N.\n2.- Con precio de venta por unidad a valor de $ 30 m.n. reintegrará al Patronato el importe proporcional por cada unidad vendida de............................. $ 4.30 M.N.\n3.- Con precio de venta por unidad a valor de\n$ 35 m.n. reintegrará al Patronato el importe proporcional por cada unidad vendida de.... $ 5.30 M.N.\n$ 40.00 M.N. y por cada $ 5.00 M.N. adicionales sucesivamente en su precio de venta, se reintegrará al patronato por cada unidad la cantidad de $1.00\nM.N.\n4.- En eventos masivos en caso de que el promotor requiera el derecho a venta de bebidas alcohólicas, exceptuando la denominada “cerveza” deberá cubrir una cuota que varía según la magnitud del evento de acuerdo a lo siguiente:\na).- De 1 a 1,000 personas............. $ 4,000.00 M.N.\nb).- De 1,001 a 3,000 personas......... $ 8,000.00 M.N.\nc).- De 3,001 a 5,300 personas......... $12,000.00 M.N\nd).- De 5,301 a 10,000 personas........ $16,000.00 M.N\ne).- De 10,001 personas en adelante.... $22,000.00 M.N\nc).- Venta de bote de Refresco de 355 mililitros, en periodo Fiestas del Sol por cada unidad vendida se reintegrará al Patronato......... $ 0.90 $ 4.10 M.N.\nSe pagará la cuota mínima si se contrata renta de espacio a más tardar el 30 de abril, a partir del 01 de mayo aplicará la cuota máxima.\nd).- Venta de bote de Refresco de 355 mililitros, en periodo fuera de Fiestas del Sol:\n1.- Con precio de venta por unidad a valor de\n$ 20 m.n. reintegrará al Patronato el importe proporcional por cada unidad vendida de..... $ 2.10 M.N.\n2.- Con precio de venta por unidad a valor de\n$ 25 m.n. reintegrará al Patronato el importe proporcional por cada unidad vendida de..... $ 3.10 M.N.\n3.- Con precio de venta por unidad a valor de\n$ 30 m.n. reintegrará al Patronato el importe proporcional por cada unidad vendida de..... $ 4.10 M.N.\ne).- Venta de botella de Agua de 600 mililitros, en periodo Fiestas del Sol por cada unidad vendida se reintegrará al Patronato........ $ 0.90 $ 4.10 M.N. a más tardar el 30 de abril, a partir del 01 de mayo aplicará la cuota máxima.\nf).- Venta de botella de Agua de 600 mililitros en periodo fuera de Fiestas del Sol:\n1.- Con precio de venta por unidad a valor de $ 20 m.n. reintegrará al Patronato el importe proporcional por cada unidad vendida de............................. $ 2.10 M.N.\n2.- Con precio de venta por unidad a valor de $ 25 m.n. reintegrará al Patronato el importe proporcional por cada unidad vendida de............................. $ 3.10 M.N.\n3.- Con precio de venta por unidad a valor de $ 30 m.n. reintegrará al Patronato el importe proporcional por cada unidad vendida de............................. $ 4.10 M.N.\ng).- Venta directa de bebidas por parte del\nPatronato de las Fiestas del Sol de la\nCiudad de Mexicali, por cada unidad vendida en cualquier presentación:\n1.- Refresco........................... $ 30.00 M.N.\n2.- Agua embotellada................... $ 30.00 M.N.\nXI.- Otros Servicios:\na).- Venta del nombre del Palenque del FEX, el Consejo Directivo del\nPatronato de las Fiestas del Sol de la Ciudad de Mexicali, B.C., propuestas económicas de los interesados.\nb).- Venta del nombre de la Carpa del FEX, el Consejo Directivo del\nPatronato de las Fiestas del Sol de la Ciudad de Mexicali, B.C., propuestas económicas de los interesados.\nMorales subsidios, aportaciones, subvenciones, donativos en especie y bienes muebles.\nEl Consejo Directivo del Patronato de las Fiestas del Sol de la Ciudad de Mexicali, B.C., podrá autorizar cualquier otro tipo de ingreso y este pertenecerá al mismo Patronato.\nSe cobrarán Derechos de conformidad al presupuesto que al efecto realice el Patronato de las Fiestas del Sol de la Ciudad de Mexicali, los que en todo caso serán proporcionales al costo del servicio. Los ingresos que por concepto de derechos, transferencias, asignaciones y ayudas sociales que se perciban, pasarán a formar parte del patrimonio del Patronato de las Fiestas del Sol de la Ciudad de Mexicali.\nSERVICIOS QUE PRESTA EL PATRONATO DEL\nCENTRO RECREATIVO JUVENTUD 2000 DE LA CIUDAD DE MEXICALI\nARTÍCULO 73.- Los servicios que presta el Patronato del Centro\nRecreativo Juventud 2000 de la Ciudad de Mexicali, se cobrarán conforme a lo siguiente:\nTARIFA\nMONEDA NACIONAL\nI.- Los ingresos por concepto de entrada:\na).- Entrada Niños, hasta 12 años............... EXENTO\nb).- Entrada General............................ $ 12.00 M.N.\nc).- Entrada adulto mayor presentando tarjeta de\nINAPAM o cualquier identificación vigente que lo acredite............................ EXENTO\nd).- Entrada para personas con discapacidad..... EXENTO\ne).- Membresía Individual mensual (entrada)..... $ 150.00 M.N.\nf).- Membresía Individual mensual (entrada y estacionamiento)........................... $ 300.00 M.N.\ng).- Entrada gratis a alumnos destacados en las disciplinas deportivas que se imparten en el\nCentro, previo estudio socioeconómico.\nNo se cobrará entrada al Parque a aquellas adquiera una membresía para uso de las instalaciones.\nII.- Estacionamiento:\na).- Estacionamiento General.................... $ 12.00 M.N.\nb).- Boleto de estacionamiento extraviado....... $ 60.00 M.N.\nc).- Boleto de estacionamiento a usuarios de eventos especiales........................ $ 60.00 M.N.\nIII.- Curso Mensual:\nInscripción............................................ EXENTO\na).- Costo por curso, disciplina o clases individuales que requieran asistencia de un instructor, con excepción de los incisos\nb), c) y d)................................ $ 350.00 a\n$ 585.00 M.N.\nb).- Steel Combat+steel jump+gym................ $ 467.00 M.N.\nc).- Steel Combat+gym o Steel Combat-Rumba...... $ 410.00 M.N.\nd).- Rumba+gym.................................. $ 410.00 M.N.\ne).- Membresía curso extraviada................. $ 60.00 M.N.\nPor cada cinco mensualidades pagadas de manera consecutiva, la sexta será de forma gratuita, a solicitud del usuario.\nIV.- Renta de Palapas por evento:\na).- Palapa..................................... $ 350.00 M.N.\nDurante horario 8:00 horas a 15:00 horas o 15:00 horas a 21:00 horas\nb).- Depósito por concepto de limpieza en la renta de la Palapa......................... $ 175.00 M.N.\nc).- Renta de mobiliario por día................ $ 60.00 a\n$ 550.00 M.N.\nd).- Acceso al Parque con:\n1).- Rockola o bocina...................... $ 175.00 M.N.\n2).- Brincolina............................ $ 467.00 M.N.\nV.- Renta de Canchas:\na).- Futbol rápido por hora..................... $ 350.00 M.N.\nb).- Soccer por dos horas pasto sintético para la realización de juegos, sin energía eléctrica y sujeto a disponibilidad........ $ 585.00 M.N.\nc).- Soccer por dos horas pasto sintético para la realización de juegos, con energía eléctrica y sujeto a disponibilidad........ $ 818.00 M.N.\nd).- Usos múltiples sin luz por hora para la realización de juegos deportivos o recreativos................................ $ 467.00 M.N.\ne).- Usos múltiples con luz por hora para la realización de juegos deportivos o recreativos................................ $ 585.00 M.N.\nf).- Usos múltiples para la realización de cualquier evento, duración máxima 6 horas.. $ 8,820.00 M.N.\ng).- Usos múltiples para la realización de evento de carácter social y/o escolar, duración máxima 6 horas.................... $ 6,615.00 M.N.\nh).- Softbol por dos horas para la realización de juegos con energía eléctrica y sujeto a disponibilidad............................. $ 467.00 M.N.\ni).- Softbol campo completo para entrenamientos, con o sin energía eléctrica, por hora y sujeto a disponibilidad.................... $ 117.00 M.N.\nj).- Renta de cancha de Basquetbol al aire libre por hora................................... $ 117.00 M.N.\nk).- Renta de cancha de Basquetbol para evento\n(6 horas máximo y sujeto a disponibilidad.. $ 935.00 M.N.\nl).- Renta de mitad cancha de soccer para\nEntrenamientos(máximo 2 horas)............. $ 585.00 M.N.\nm).- Renta de cuarto cancha y/o cabeceras para entrenamientos(máximo 2 horas)............. $ 292.00 M.N.\nn).- Caja de bateo por ficha (15 bolas)......... $ 25.00 M.N. ñ).- Renta de salón de usos múltiples por hora capacidad máxima 50 personas............... $ 117.00 M.N.\no).- Depósito de limpieza de canchas........... $ 552.00 a\n$ 1,655.00 M.N.\np).- Renta de canchas de Voleibol de playa, por hora....................................... $ 120.00 M.N.\nq).- Renta de espacios para módulos de caja de bateo, por mes............................. $ 5,000.00 a\n$ 8,000.00 M.N.\nEl espacio de módulos es por concesión y el rango se aplicará al número de espacios que el concesionario utilice, el mínimo se a partir de un paquete de 3 espacios en adelante.\nVI.- Renta de equipo deportivo:\na).- Balones por hora, por balón................ $ 25.00 M.N.\nb).- Red de Voleibol, por hora................... $ 65.00 M.N.\nc).- Ring de box, por evento.................... $ 6,320.00 M.N.\nd).- Bats, guantes, pelotas y bases por hora cada uno................................... $ 38.00 M.N.\nVII.- Membresías de Gimnasio(Mensual):\na).- Público en general mensual................. $ 370.00 M.N.\nb).- Público en general semestral............... $ 1,600.00 M.N.\nc).- Público en general anual................... $ 2,250.00 M.N.\nd).- Adulto mayor presentando tarjeta de INAPAM o cualquier identificación vigente que lo acredite................................... EXENTO\ne).- Gym por un día individual.................. $ 38.00 M.N.\nf).- Membresía Grupal (máximo 5 personas) por mes........................................ $ 1,500.00 M.N.\ng).- Usuario inscrito en cualquier disciplina enumerada en la fracción III de este artículo siempre y cuando este al corriente en sus mensualidades, por mes.............. $ 200.00 M.N.\nh).- Membresía individual en el gimnasio para empleados de los 3 niveles de Gobierno y paraestatales, por mes..................... $ 270.00 M.N.\nEl uso del gimnasio en cualquier modalidad estará limitado a dos horas como máximo por usuario cuando este declarada una contingencia.\nVIII.- Albercas:\na).- Acceso a la alberca por una hora (No incluye revisión física y entrada)......... $ 40.00 M.N.\nb).- Revisión física............................ $ 10.00 M.N.\nc).- Inscripción a curso de natación............ $ 60.00 M.N.\nd).- Curso de natación:\n1)Clases de Natación $ 1,200.00 M.N.\n2)Aquafitness $ 1,200.00 M.N.\ne).- Membresía individual alberca (mensual)..... $ 600.00 M.N.\nf).- Membresía individual alberca - gimnasio\n(mensual)................................. $ 800.00 M.N.\ng).- Membresía Familiar Mensual Alberca (máximo\n5 personas) 3 horas diarias en un horario de Martes a Viernes de 7 a 13 horas, Sábado y Domingo cualquier hora.................... $ 1,500.00 M.N.\nh).- Membresía Familiar Mensual AlbercaGimnasio (máximo 5 personas) 3 horas diarias en un horario de Martes a Viernes de 7 a 13 horas, Sábado y Domingo cualquier hora....................................... $ 1,950.00 M.N.\ni).- Paquete Escolar de alberca, incluye 2 horas y revisión médica en un horario de Martes a\nViernes de 7 a 13 horas.................... $ 60.00 M.N.\nj).- Alberca para grupo 2 horas de alberca, revisión física y entrada hasta 40 personas en horario de Martes a Domingo de 7 a 13 horas................................. $ 1,920.00 M.N.\nk).- Paquete fiesta fin de semana (5 horas de alberca, revisión física, entrada para 30 a\n40 personas y palapa)...................... $ 4,200.00 M.N.\nNota: la alberca no es de uso exclusivo.\nIX.- Torneos en cualquier disciplina:\na).- Inscripción a torneo de liga............... $ 950.00 M.N.\nb).- Inscripción a torneo en fin de semana...... $ 715.00 M.N.\nc).- Inscripción a torneo en cancha de usos múltiples.................................. $ 540.00 M.N.\nd).- Inscripción a torneo de copa............... $ 360.00 M.N.\ne).- Inscripción a torneo relámpago............. $ 180.00 M.N.\n(solo 1 día)\nf).- Inscripción a torneo cuadrangular.......... $ 120.00 M.N.\ng).- Tarjetón individual para torneo, siempre que sea requerido.......................... $ 30.00 M.N.\nh).- Arbitraje general.......................... $ 180.00 M.N.\nX.- Programa vacacional:\na).- Curso de verano completo por niño.......... $ 1,100.00 M.N.\n(En horario de 8:00 a 13:00 horas)\nb).- Curso de verano completo en el pago de un segundo hermano............................ $ 920.00 M.N.\n(En horario de 8:00 a 13:00 horas)\nc).- Curso de verano completo en el pago del tercer hermano o más....................... $ 610.00 M.N.\n(En horario de 8:00 a 13:00 horas)\nd).- Curso de verano completo por niño con horario extendido de 8:00 a 15:00 horas.... $ 1,550.00 M.N.\ne).- Curso de verano completo por niño para hijos de trabajadores de los tres niveles de Gobierno,(Federal, Estatal y Municipal).\n(En horario de 8:00 a 13:00 horas) $ 920.00 M.N.\nf).- Curso de verano completo por niño para apoyo a asociaciones civiles no lucrativas.\n(En horario de 8:00 a 13:00 horas) $ 550.00 M.N.\ng).- Cursos de verano completo por niño para hijos de trabajadores del Patronato del Centro\nRecreativo Juventud 2000 (En horarios de\n8:00 a 13:00 horas)......................... $ 550.00 M.N. seleccionados como talento deportivo, gozarán de 1 mes gratis en la disciplina correspondiente.\nXI.- Reposición de Credencial:\na).- Membresía-Curso............................ $ 60.00 M.N.\nXII.- Renta de local y espacios comerciales (Mensual):\na).- Local A.................................... $ 8,800.00 M.N.\nb).- Local B.................................... $ 4,700.00 M.N.\nc).- Local C.................................... $ 6,350.00 M.N.\nd).- Local D.................................... $ 3,700.00 M.N.\ne).- Local E.................................... $21,050.00 M.N.\nf).- Local F en plaza principal ubicado frente al ingreso al Salón de Box................. $ 4,100.00 M.N.\ng).- Espacio Fotográfico........................ $ 1,100.00 M.N.\nh).- Espacio abierto en plaza principal ubicado frente a las oficinas de vinculación....... $ 4,100.00 M.N.\ni).- Zona de Food Trucks, por vehículo.......... $ 8,800.00 M.N.\nj).- Zona Anáhuac, por metro cuadrado........... $ 200.00 a\n$ 500.00 M.N.\nSe cobrará una tasa del 1.47% de interés moratorio por pago tardío después del día 10 de cada mes, con excepción de solicitud de prórroga siempre y cuando sea dentro del mismo mes y antes del vencimiento.\nXIII.- Renta de otros espacios (cuota diaria):\na).- Renta para espacio a vendedor ambulante para eventos dentro del Parque............. $ 120.00 M.N.\nb).- Renta de espacio para módulo comercial de 4 metros por 3 metros en la zona del bazar estacionamiento............................ $ 120.00 a\n$ 160.00 M.N.\nc).- Renta de espacio por día para módulo de comida de 3 metros por 2 metros dentro de las instalaciones......................... $ 120.00 M.N.\nXIV.- Descuentos por fechas especiales:\na).- Día de la niña y el niño (1 acceso de adulto acompañando a una niña o niño de 3 a 12 años)...................................... EXENTO\nb).- Día de las madres (1 acceso adulto madre de familia)................................... EXENTO\nc).- Día de la familia (2x1 a la familia)....... EXENTO\nd).- Adultos y niños acceso al parque, gimnasio y alberca en las jornadas que se lleven a cabo.............................. EXENTO\ne).- Día del padre (1 acceso adulto padre de familia)................................... EXENTO\nf).- Otros..................................... EXENTO\nXV.- Renta de espacios publicitarios:\na).- Valla publicitaria (3 mts x 1.80 mts) ubicada sobre blvd. Anáhuac renta mensual, por mes................................... $ 1,100.00 M.N.\nb).- Renta de marquesina ubicada en la entrada principal del parque, por mes...... $ 1,100.00 M.N.\nc).- Renta de espacio publicitario en las tablas\n(1.22 mts x 2.44 mts) de las canchas de fútbol rápido, por mes..................... $ 550.00 M.N.\nd).- Renta de espacio publicitario en barda perimetral (1.22 mts x 2.44 mts) del campo de sóftbol, por mes........................ $ 550.00 M.N.\ne).- Renta de espacio publicitario de 2x1 mts en cerco perimetral del campo de fútbol soccer y/o americano, por mes.............. $ 550.00 M.N.\nf).- Renta de espacio publicitario de 2x1 mts en acceso principal, explanada y cancha de usos múltiples, por mes................. $1,650.00 M.N.\ng).- Renta de espacio publicitario de 2x1 mts en salón de usos múltiples, gimnasio y salón de box, por mes................... $1,100.00 M.N.\nSe aplicará tarifa especial por la contratación de dos o más incisos.\nXVI.- Paquete publicitario:\na).- Publicidad en calendario anual de actividades..............................de $ 5,565.00 a\n$ 7,791.00 M.N.\nb).- Publicidad dinámica en pantalla, por mes\n.........................................de $ 4,452.00 a\n$ 7,791.00 M.N.\nc).- Valla publicitaria (3 mts x 1.80 mts):\n1).- Mes................................... $ 1,125.00 M.N.\n2).- Semestre.............................. $ 6,750.00 M.N.\n3).- Anual................................. $15,500.00 M.N.\nSe aplicará tarifa especial por la contratación de dos o más incisos.\nXVII.- Organización y logística de eventos:\na).- Sector educativo.........................de $ 1,200.00 a\n$ 4,800.00 M.N.\nb).- Sector privado (empresas)................de $ 4,800.00 a\n$12,000.00 M.N.\nXVIII.- Servicios:\na).- Atención nutricional....................... $ 111.00 M.N.\nb).- Consulta psicológica individual............ $ 222.00 M.N.\nc).- Consulta psicológica de pareja............. $ 333.00 M.N.\nd).- Consulta psicológica familiar.............. $ 333.00 M.N.\ne).- Otros servicios especiales...............de $ 111.00 a\n$ 700.00 M.N.\nf).- Servicio de quiropráctico.................. $ 167.00 M.N.\nXIX.- Inscripción a eventos:\na).- Carrera atlética Aniversario Juventud 2000\n2 km....................................... $ 60.00 M.N.\nb).- Carrera atlética Aniversario Juventud 2000\n5 km....................................... $ 180.00 M.N.\nc).- Carrera de botargas........................ $ 40.00 M.N.\nd).- Carrera con obstáculos 1.5 KM.............. $ 180.00 M.N.\ne).- Carrera con obstáculos 3 KM................ $ 300.00 M.N.\nf).- Otros....................................de $ 60.00 a\n$ 360.00 M.N.\ng).- Eventos Especiales......................... $ 360.00 a\n$ 1,100.00 M.N.\nXX.- Venta de ropa y recuerdos:\na).- Venta de pantalón deportivo..............de $ 111.00 a\n$ 600.00 M.N.\nb).- Venta de camisetas.......................de $ 56.00 a\n$ 300.00 M.N.\nc).- Venta de chamarras.......................de $ 334.00 a\n$ 700.00 M.N.\nd).- Venta de conjuntos deportivos............de $ 445.00 a\n$ 1,400.00 M.N.\ne).- Venta de cubrebocas......................de $ 56.00 a\n$ 223.00 M.N.\nf).- Venta de cilindros/ánforas de plástico...de $ 56.00 a\n$ 150.00 M.N.\ng).- Venta de lentes de protección para nadar.de $ 56.00 a\n$ 300.00 M.N.\nh).- Venta de toallas de baño.................de $ 56.00 a\n$ 250.00 M.N.\ni).- Otros....................................de $ 22.00 a\n$ 1,500.00 M.N.\nXXI.- Otros Servicios:\nEl Patronato del Centro Recreativo Juventud 2000 está autorizado para\nFísicas y Morales, subsidios, aportaciones, subvenciones, donaciones.\nSe cobrarán Derechos de conformidad al presupuesto que al efecto realice el Patronato del Centro Recreativo Juventud 2000 de la Ciudad de Mexicali, los que en todo caso serán proporcionales al costo del servicio. Los ingresos que por concepto de derechos, transferencias, asignaciones y ayudas sociales que se perciban, pasarán a formar parte del Patronato del Centro Recreativo Juventud 2000 de la Ciudad de\nMexicali.\nSERVICIOS QUE PRESTA EL COMITÉ DE TURISMO Y CONVENCIONES DEL\nMUNICIPIO DE MEXICALI\nARTÍCULO 74.- Los servicios que presta el Comité de Turismo y\nConvenciones del Municipio de Mexicali, se cobrarán conforme a lo siguiente:\nTARIFA\nMONEDA NACIONAL\nI.- Cuota anual de apoyo promoción turística........ $ 2,756.00 M.N.\nII.- Cuota de renta mensual de pantalla:\na).- Cuota de apoyo a la promoción turística mensual $ 2,756.00 M.N.\nb).- Cuota de renta mensual......................... $ 3,500.00 M.N.\nIII.- Patrocinador de Expo, Ferias y Convenciones:\na).- Patrocinador Diamante...................... $53,000.00 M.N.\nb).- Patrocinador Oro........................... $31,800.00 M.N.\nc).- Patrocinador Plata........................... $21,200.00 M.N.\nd).- Patrocinador Bronce........................ $10,600.00 M.N.\nIV.- Renta de espacios para Expo, Ferias y\nConvenciones:\na).- Estand tipo pasillo por evento............. $ 2,120.00 M.N.\nb).- Estand de 3x3 metros por evento............ $ 2,650.00 M.N.\nc).- Estand de alimentos por evento............. $ 3,180.00 M.N.\nd).- Estand para la venta de bebidas con grado de alcohol por evento...................... $ 6,000.00 M.N.\nV.- Membresía Revista digital Visit Mexicali anual:\na).- Contraportada.............................. $ 5,300.00 M.N.\nb).- Portada interior o contraportada interior.. $ 4,770.00 M.N.\nc).- Plana completa............................. $ 4,240.00 M.N.\nd).- 1/2 de Plana............................... $ 2,385.00 M.N.\ne).- 1/4 de Plana............................... $ 1,325.00 M.N.\nf).- 1/8 de Plana............................... $ 795.00 M.N.\ng).- Datos sencillos............................ $ 530.00 M.N.\nVI.- Mapa Turístico:\na).- Logo tamaño grande......................... $ 5,300.00 M.N.\nb).- Logo tamaño chico.......................... $ 2,120.00 M.N.\nVII.- Renta de espacios instalaciones COTUCO:\na).- Oficina superior 21m2 por mes.......... $ 7,420.00 M.N.\nb).- Sala de Juntas 50 m2 2 horas............. $ 1,060.00 M.N.\nc).- Fachada superior (López Mateos)por mes..... $ 5,300.00 M.N.\nd).- Salón Audiovisual por día..................\n(Incluye personal de staff, tres micrófonos, dos luces, una cámara, edición de fotos, audio y videos de lo grabado) $10,600.00 M.N.\ne).- Fachada noche (Lateral)por mes............. $ 5,300.00 M.N.\nf).- Estacionamiento y vigilancia por evento.... $ 1,590.00 M.N.\nSe exentarán de los cobros incluidos en esta fracción a las Dependencias Municipales.\nVIII.- Venta de mercancía:\na).- Camisetas.................................. $ 265.00 M.N.\nb).- Polos...................................... $ 318.00 M.N.\nc).- Chamarras.................................. $ 742.00 M.N.\nd).- Llaveros................................... $ 106.00 M.N.\ne).- Tazas...................................... $ 127.00 M.N.\nf).- Vasos...................................... $ 127.00 M.N.\ng).- Cuadros, pinturas, óleos, bocetos, dibujos, etc......................................de $ 106.00 a\n$ 5,300.00 M.N.\nEl precio se fijará de acuerdo al tipo de bien.\nh).- Gorras..................................... $ 265.00 M.N.\ni).- Bolsas de viaje............................ $ 150.00 M.N.\nj).- Botella reutilizable....................... $ 120.00 M.N.\nIX.- Publicidad en Redes Sociales:\na).- De 3 a 5 menciones por mes................. $ 530.00 M.N.\nb).- De 3 a 5 logos por mes...................de $ 530.00 a\n2,120.00 M.N.\nc).- De 3 a 5 menciones con logo por mes........ $ 530.00 M.N.\nd).- Logo de fondo en los programas por mes..... $ 5,300.00 M.N.\nX.- Talleres, capacitaciones y certificaciones:\n(Incluye certificación y taller por persona)\nEl costo se fijará de acuerdo a la duración del taller o capacitación.\na).- Con maestros locales.....................de $ 424.00 a\n$ 1,590.00 M.N.\nb).- Con maestro nacionales...................de $ 848.00 a\n$ 3,710.00 M.N.\nc).- Capacitación del idioma Inglés enfocado al turismo por mes............................ $ 1,500.00 M.N.\nXI.- Sorteos:\na).- Costo del boleto.........................de $ 53.00 a\n530.00 M.N.\nXII.- Cuota para la promoción y conservación de recursos turísticos del Municipio de Mexicali por filmación de película........................... $ 3,500.00 M.N.\nXIII.- Otros Servicios: realice el Comité de Turismo y Convenciones del Municipio de Mexicali, los que en todo caso serán proporcionales al costo del servicio. Los ingresos que por concepto de derechos, transferencias, asignaciones, donativos y ayudas sociales que se perciban, pasarán a formar parte\nMexicali.\nMEXICALI\nARTÍCULO 75.- Los servicios que presta el Consejo de Urbanización\nMunicipal de Mexicali, se cobrarán conforme a lo siguiente:\nUNIDAD DE MEDIDA Y\nACTUALIZACIÓN VIGENTE\nI.- Verificación del certificado de no adeudo\n(Libertad de gravamen) por parte del Consejo de Urbanización Municipal de Mexicali se pagará.. 3.50 veces\nII.- Emisión de carta de confirmación de inclusión en el Programa de Obra del Organismo de determinada obra de urbanización a efectuarse.............. 2.62 veces\nIII.- Carta de cancelación de Gravamen ante Registro\nPúblico de la propiedad........................ 2.62 veces\nIV.- Servicios de expedición, grabación y/o envío de documentos e información solicitada al Consejo de Urbanización, serán pagados de acuerdo a lo siguiente:\na).- Copia Fotostática......................... 0.0174 veces\nb).- Copia certificada......................... 1.10 veces\nc).- Copia digital de expedientes por cada 20 páginas................................... 0.19 veces\nV.- Otros Servicios: que se realizaron. realice el Consejo de Urbanización Municipal de Mexicali, los que en todo caso serán proporcionales al costo del servicio. Los ingresos que por concepto de derechos, transferencias, asignaciones y ayudas sociales que se perciban, pasarán a formar parte del patrimonio del\nConsejo de Urbanización Municipal de Mexicali.\n02 SERVICIOS QUE PRESTA EL INSTITUTO MUNICIPAL DE INVESTIGACIÓN Y\nPLANEACIÓN URBANA DE MEXICALI\nARTÍCULO 76.- Los servicios que presta este Organismo Paramunicipal, causarán derechos los cuales se cobrarán, conforme a la siguiente tarifa:\nI.- Por Factibilidad de uso de suelo, se pagará por predio:\nUNIDAD DE MEDIDA Y\nACTUALIZACIÓN VIGENTE\na).- Dentro del área urbana de Mexicali........ 12.60 veces\nb).- Fuera del área urbana y dentro del límite de centro de población PDUCP de Mexicali.. 20.16 veces\nc).- Fuera del límite del centro de la población de Mexicali..................... 25.20 veces\nII.- Por emisión de Dictamen técnico de uso de suelo, se pagará por predio:\na).- Dentro del área urbana de Mexicali........ 35.00 veces\nb).- Fuera del área urbana y dentro del limite del centro de población PDUCP de Mexicali. 40.00 veces\nc).- Fuera del límite del centro de la población de Mexicali.................... 50.40 veces\nIII.- Por análisis y emisión de dictamen técnico de congruencia de estructura vial:\na).- Dentro del área urbana indicado en el\nPrograma de Desarrollo Urbano de Centro de\nPoblación de Mexicali..................... 35.00 veces\nb).- Fuera del área urbana y dentro de los límites del Centro de Población indicando en el Programa de Desarrollo Urbano de\nCentro de Población de Mexicali........... 40.32 veces\nIV.- A solicitud de la Dirección de Administración Urbana o a petición del interesado, por análisis de estudio de a los indicados en la fracción V de este artículo, con validez de hasta dos revisiones, se pagará por dictamen:\na).- Dentro del límite de expansión del área urbana:\n1.- Hasta 400 m2.......................... 100.00 veces\n2.- De 401 m2 hasta 15,000 m2............. 140.00 veces\n3.- Adicional, cada 1000 m2............... 10.00 veces\nb).- Fuera del límite de expansión del área urbana:\n1.- Hasta 3 hectáreas.................... 200.00 veces\n2.- Cada hectárea o fracción adicional.... 10.08 veces\nc).- Dentro del límite de expansión urbana para plantas, estaciones y subestaciones de energía hidrocarburos, manejo de residuos peligrosos y otros usos especiales:\n1.- Hasta 400 m2.......................... 200.00 veces\n2.- De 401 m2 hasta 15,000 m2............. 250.00 veces\n3.- Adicional, cada 1000 m2............... 10.00 veces\nd).- Fuera del límite de expansión urbana para plantas, estaciones y subestaciones de energía, hidrocarburos y manejo de residuos peligrosos y otros usos especiales.\n1.- Hasta 10 hectáreas.................... 300.00 veces\n2.- Por cada hectárea o fracción adicional. 10.00 veces\nPor revisión adicional se cobrará el 50% del valor del trámite de acuerdo al inciso aplicable.\nV.- Por análisis de desarrollos urbanos habitacionales, comerciales, industriales, mixtos y equipamiento urbano, de\n20,000 m2 o más, con validez de hasta dos revisiones:\nUNIDAD DE MEDIDA Y\nACTUALIZACIÓN VIGENTE\na).- Por análisis de estudio de justificación y emisión de dictamen de cambio de uso del suelo, con validez de hasta dos revisiones, se pagará:\n1.- Por cada metro cuadrado de superficie..... 0.010 veces\nb).- Por análisis de Integración Urbana de predios ubicados fuera del área urbana con objeto de urbanizar, incorporar o reincorporar, revisión de restricciones existentes y de los programas de desarrollo urbano y distribución de usos y destinos del suelo y emisión del dictamen:\n1.- Por cada metro cuadrado de superficie..... 0.010 veces\nVI.- Por revisión de estudios de impacto urbano y emisión de dictamen; con validez de hasta dos revisiones:\na).- Dentro del límite del área urbana:\n1.- Hasta 10,000 m2........................ 150.00 veces\n2.- Adicional, cada 1,000 m2............... 10.00 veces\nb).- Fuera del área urbana y dentro del limite del centro de población:\n1.- Hasta 10 hectáreas........................ 180.00 veces\n2.- Cada hectárea adicional o fracción........ 10.00 veces\nc).- Fuera del límite del centro de la población:\n1.- Hasta 10 hectáreas........................ 200.00 veces\n2.- Cada hectárea adicional o fracción........ 10.00 veces\nd).- Dentro del límite de expansión para plantas, estaciones y subestaciones de energía, hidrocarburos y manejo de residuos peligrosos y otros usos especiales.\n1.- Hasta 1 hectáreas........................ 200.00 veces\n2.- Cada hectárea adicional o fracción........ 5.00 veces\ne).- Fuera del límite de expansión urbana para plantas, estaciones y subestaciones de energía, hidrocarburos y manejo de residuos peligrosos y otros usos especiales.\n1.- Hasta 10 hectáreas........................ 250.00 veces\n2.- Cada hectárea adicional o fracción........ 10.00 veces\nPor revisión adicional se cobrará el 50% del valor de trámite de acuerdo al inciso aplicable.\nVII.- Por la elaboración y Actualización de:\nUNIDAD DE MEDIDA Y\nACTUALIZACIÓN VIGENTE\nDESDE HASTA\na).- Planes, Programas, Estudios o Proyectos\nTécnicos................................... 1,000.00 a\n140,000.00 veces\nLos conceptos a los que se refiere el presente artículo, son los de suelo y el crecimiento de los asentamientos.\nVIII.- Por revisión y análisis de Planes, Programas y Estudio de\nDesarrollo Urbano, con validez de hasta dos revisiones:\na).- Hasta 1,000 hectáreas del área de estudio, por cada hectárea......................... 2.52 veces\nb).- Por cada hectárea adicional y fracción del área de estudio........................... 0.63 veces\nPor revisión adicional se cobrará el 50% del valor de trámite de acuerdo al inciso aplicable.\nIX.- Planos digitales en formato PDF o JPG:\n1.- Plano base temático o existente de la\nCiudad de Mexicali, o Matriz de\nCompatibilidad de Usos de Suelo:\n96 dpi (7,680 x 4,032 pxs)........... 5.04 veces\n150 dpi (12,000 x 6,300 pxs).......... 11.34 veces\n180 dpi (14,400 x 7,560 pxs).......... 16.38 veces\n2.- Plano base temático o existente del\nValle de Mexicali:\n96 dpi (6,048 x 6,048 pxs)........... 6.30 veces\n150 dpi (9,450 x 9,450 pxs)........... 8.82 veces\n180 dpi (11,340 x 11,340 pxs)......... 18.90 veces\n3.- Capas temáticas:\n3.1.- Capa adicional existente que se quiera agregar al mapa base o temático seleccionado.......... 5.04 veces\nNOTA: El costo del plano temático lo integra el costo del plano base, ya sea de la Ciudad de Mexicali o el Valle, más el costo de cada desee agregar.\n4.- Capas de Ciudad de Mexicali y Valle:\nAUTOCAD (DWG), ARCGIS (SHP), MAPINFO\n(TAB) Y GOOGLE EARTH (KMZ).\n4.1.- Elementos por capa:\n26 a 50............................. 9.36 veces\n76 a 100............................ 18.72 veces\n126 a 150............................ 28.08 veces\n176 a 200............................ 37.44 veces\n226 a 250............................ 50.82 veces\n276 a 300............................ 56.17 veces\n326 a 350............................ 65.53 veces\n376 a 400............................ 74.89 veces\n426 a 450............................ 84.25 veces\n476 a 500............................ 93.63 veces\n501 en adelante (cada elemento tendrá un costo de $ 5.00 m.n.)\n4.2.- Campo extra individual.......... 10.08 veces\nNOTA: Cada elemento contiene un solo campo a selección del interesado, siempre y cuando este se encuentre en la base de datos del elemento.\nEn caso de no contar con los elementos o los campos requeridos, se hará una cotización de acuerdo a la fracción VI para generarlos.\nX.- Planos Impresos de la Ciudad de Mexicali y Valle:\n1.- Planos Impresos en papel Bond:\n1.1.- Plano base o temático existente de la Ciudad de Mexicali, o\nMatriz de Compatibilidad de Uso de Suelo:\n11\" x 17\".................... 1.26 veces\n24\" x 42\".................... 6.30 veces\n36\" x 62\".................... 13.86 veces\n42\" x 80\".................... 21.42 veces\n1.2.- Plano base o temático existente del Valle de Mexicali:\n24\" x 24\".................... 5.04 veces\n36\" x 36\".................... 8.82 veces\n42\" x 42\".................... 11.34 veces\n2.- Planos Impresos en papel fotográfico\n(Glossy):\n2.1.- Plano base o temático existente de la Ciudad de Mexicali, o\nMatriz de Compatibilidad de Uso de Suelo:\n24\" x 42\".................... 7.56 veces\n36\" x 62\".................... 15.12 veces\n42\" x 80\".................... 22.68 veces\n2.2.- Plano base o temático existente del Valle de Mexicali:\n24\" x 24\".................... 7.56 veces\n36\" x 36\".................... 11.34 veces\n42\" x 42\".................... 13.86 veces\n3.- Planos Impresos en Papel Fotográfico\n(Glossy) y montados en foambord o\nCanvas:\n3.1.- Plano base o temático existente de la Ciudad de Mexicali, o\nMatriz de Compatibilidad de Uso de Suelo:\n24\" x 42\".................... 13.86 veces\n36\" x 62\".................... 28.98 veces\n42\" x 80\".................... 44.10 veces\n3.2.- Plano base o temático existente del Valle de Mexicali:\n24\" x 24\".................... 15.12 veces\n36\" x 36\".................... 17.64 veces\n42\" x 42\".................... 22.68 veces\nXI.- Por Servicios de asesoría, capacitación e Impartición de\nTalleres:\nUNIDAD DE MEDIDA Y\nACTUALIZACIÓN VIGENTE\nDESDE HASTA\na).- De 1 hasta 15 horas............. 18.90 veces 56.70veces\nb).- De 16 hasta 30 horas............ 57.96 veces 94.50veces\nc).- De 31 horas en adelante......... 3.15 veces cada hora\nNOTA: Se aplicarán descuentos a Instituciones Educativas y\nDependencias u Organismos relacionados con el ramo.\nXII.- Otros Servicios:\nSe cobrarán derechos de conformidad al presupuesto que al efecto realice el Instituto Municipal de Investigación y Planeación Urbana de Mexicali, los que en todo caso serán proporcionales al costo del servicio. Los ingresos que por concepto de derechos, transferencias, asignaciones y ayudas sociales que se perciban, pasarán a formar parte\nUrbana de Mexicali.\nSEGURIDAD PÚBLICA\nARTÍCULO 77.- Los ingresos, transferencias, asignaciones, subsidios y percibirán cuando lo decrete y exhiba, conforme a su reglamento interior, y pasarán a formar parte del patrimonio del Patronato\nEscuadrón Juvenil Deportivo de Seguridad Pública.\nLA FAMILIA DE MEXICALI\nARTÍCULO 78.- Los servicios que presta el Patronato del Desarrollo\nIntegral de la Familia de Mexicali, se cobrarán conforme a lo siguiente:\nTARIFA\nMONEDA NACIONAL\nI.- Oficinas Generales:\na).- Consulta Médica, Primera Vez.........Desde $ 0.00 M.N.\nHasta $50.00 M.N.\nb).- Sutura sencilla por punto.................. $ 45.00 M.N.\nc).- Sutura Subdérmica......................... $ 75.00 M.N.\nd).- Retiro de sutura aplicación medicamento TM, consulta de seguimiento.................... $ 35.00 M.N.\ne).- Curación.................................. $ 85.00 M.N.\nf).- Retiro de Sonda Foley..................... $ 85.00 M.N.\ng).- Aplicación de medicamento TM.............. $ 35.00 M.N.\nh).- Aplicación de medicamento IV.............. $ 55.00 M.N.\ni).- Canalización con obturador................ $ 160.00 M.N.\nj).- Retiro de implante subdérmico............. $ 160.00 M.N.\nk).- Canalización con obturador, retiro de implante subdérmico, retiro de DIU........ $ 160.00 M.N.\nl).- Consulta de seguimiento................... $ 35.00 M.N.\nm).- Toma de presión arterial.................. $ 20.00 M.N.\nn).- Toma de glucosa capilar................... $ 25.00 M.N. ñ).- Certificado Médico........................ $ 30.00 M.N.\no).- Certificado Médico Prenupcial............. $ 150.00 M.N.\np).- Consulta Psicológica, primera vez......... $ 50.00 M.N.\nq).- Terapia Seguimiento del Adulto............ $ 55.00 M.N.\nr).- Terapia FR Pareja......................... $ 105.00 M.N.\ns).- Terapia Infantil.......................... $ 55.00 M.N.\nt).- Servicio Dental, primera vez.............. $ 50.00 M.N.\nu).- Limpieza Dental........................... $ 105.00 M.N.\nv).- Extracción Sencilla....................... $ 140.00 M.N.\nw).- Extracción Muelas del Juicio.............. $ 210.00 M.N.\nx).- Resinas Dentales.......................... $ 130.00 M.N.\ny).- Amalgamas Dentales........................ $ 150.00 M.N.\nz).- Consulta de seguimiento................... $ 35.00 M.N. aa).- Terapia de lenguaje, primera vez.......... EXENTO bb).- Terapia Seguimiento del Adulto............ $ 55.00 M.N. cc).- Terapia Infantil de Seguimiento........... $ 35.00 M.N.\nAdemás de los subsidios, aportaciones, subvenciones y bienes que los\nGobiernos Federal, Estatal y Municipal, y otras entidades otorguen.\nLas aportaciones, donaciones, legados y demás liberalidades que reciba de personas físicas y morales.\nII.- Casa del Abuelo:\na).- Cuota diaria por usuario.................. $ 170.00 M.N.\nb).- Cuota diaria por matrimonio............... $ 330.00 M.N.\nc).- Arrendamiento de jardín................... $ 4,200.00 M.N.\nd).- Terapia Física Externa................... $ 200.00 M.N.\ne).- Renta de carteleras(Empresas y Eventos)... $4,000.00 M.N.\nSe otorgarán hasta 10 becas para los usuarios con hasta un 50% de descuento.\nLa atención de terapia física externa deberá presentarse con una valoración e informe por parte del ortopedista tratante.\nIII.- Estancia Infantil Hermosillo:\na).- Cuota semanal por niño.................... $ 215.00 M.N.\nb).- Cuota semanal por dos hermanos............ $ 315.00 M.N.\nc).- Cuota semanal por niño hijo de empleada... $ 115.00 M.N.\nd).- Cuota semanal por traslado estancia a escuela................................... $ 45.00 M.N.\nIV.- Estancia Infantil Jiquilpan:\na).- Cuota semanal por niño.................... $ 180.00 M.N.\nb).- Cuota semanal por dos hermanos............ $ 250.00 M.N.\nc).- Cuota semanal por niño hijo de empleada... $ 115.00 M.N.\nd).- Cuota semanal por traslado estancia a escuela................................... $ 45.00 M.N.\nV.- Centro de Desarrollo Comunitario Melchor Ocampo:\na).- Cuota de inscripción por curso............ $ 70.00 M.N.\nb).- Cuota semanal por taller por participante dependiendo del curso..................... $ 60.00 a\n$ 115.00 M.N.\nc).- Por disposición de consultorio para asesoría Psicológica, por sesión.......... $ 100.00 M.N.\nd).- Consulta Médica.......................... $ 60.00 M.N.\nc).- Cuota Semanal por Curso de Verano.......... $ 150.00 M.N.\nVI.- WA-KIÑUL:\na).- Cuota de inscripción por curso............ $ 60.00 M.N.\nb).- Cuota diaria por terapia.................. $ 0.00 a\n$ 45.00 M.N.\nEn base a estudio socioeconómico.\nVII.- Centro de día Madre Teresa:\na).- Cuota mensual en base a estudio\nSocioeconómico, incluye transporte........ Hasta\n$ 450.00 M.N.\nb).- Programa vacacional en base a estudio socioeconómico, por participante.......... Hasta\n$ 1,150.00 M.N.\nVIII. Centro de Desarrollo Comunitario Santa Isabel:\na).- Cuota de inscripción a cursos semestral... $ 67.00 M.N.\nb).- Cuota semanal por taller por participante dependiendo del curso................Desde $ 22.00 M.N.\nHasta $ 67.00 M.N.\nc).- Curso de verano por usuario............... $ 67.00 M.N.\nd).- Asesoría Psicológica por sesión en base a estudio socioeconómico.................... $ 34.00 M.N.\nIX.- Casa de la Alegría:\na).- Cuota de inscripción a cursos............. EXENTO\nb).- Cuota semanal por taller................. EXENTO\nc).- Cuota diaria por acceso al centro......... EXENTO\nX.- Centro de Desarrollo Comunitario Esperanza Agrícola:\na).- Cuota semestral de inscripción a cursos.. $ 60.00 M.N.\nb).- Cuota Semanal por taller.............Desde $ 80.00 M.N.\nHasta $ 100.00 M.N.\nc).- Curso de verano por usuario..........Desde $ 80.00 M.N.\nHasta $ 100.00 M.N.\nd).- Asesoría Psicológica por sesión en base a estudio socioeconómico................... $ 150.00 M.N.\nXI.- Otros Servicios:\nSe cobrarán Derechos de conformidad al presupuesto que al efecto realice el Patronato Desarrollo Integral de la Familia de Mexicali, los que en todo caso serán proporcionales al costo del servicio. Los ingresos que por concepto de derechos, transferencias, asignaciones y ayudas sociales que se perciban, pasarán a formar parte del patrimonio del Patronato Desarrollo Integral de la Familia de Mexicali. establece el presente artículo, estarán sujetos a condonación total o parcial, siempre y cuando medie la autorización de la autoridad municipal, previo estudio socio-económico.\nARTÍCULO 79.- Los servicios que presta Bienestar Social Municipal, se cobrarán conforme a lo siguiente:\nTARIFA\nMONEDA NACIONAL\nI.- Renta de Auditorio Río Nuevo (4 horas)..........\nTemporada de Temporada de\nInvierno Verano\n(Nov-Abr) (May-Oct)\na).- Organismos empresariales y profesionales (empresas privadas y colegios). $ 2,330.00 M.N.$ 3,450.00 M.N.\nb).- Organismos de Gobierno $ 1,750.00 M.N.$ 2,330.00 M.N.\nc).- Instituciones Educativas\nPrivadas $ 2,330.00 M.N.$ 3,450.00 M.N.\nd).- Sociedades y Asociaciones\nCiviles..................... $ 1,870.00 M.N.$ 2,330.00 M.N.\ne).- Renta de auditorio por ensayo\nPrevia disponibilidad por hora....................... $ 420.00 M.N.$ 630.00 M.N.\nPor hora extra se descontará del precio estipulado que corresponda $ 105.00 M.N. por cada hora. aplicar un descuento del 50% en el cobro de las cuotas por la renta del Auditorio Río Nuevo, previo estudio socioeconómico en cada caso.\nMunicipales e Instituciones Educativas Públicas, con autorización previa del Director.\nII.- Renta de mobiliario en Auditorio Río Nuevo:\na).- Renta de sonido........................... $ 465.00 M.N.\nb).- Renta de medios audiovisuales.............. $ 930.00 M.N.\n(Sonido, micrófono, proyector, pódium)\nc).- Renta de medios audiovisuales y de mobiliario (4 mesas y 10 sillas)............ $1,165.00 M.N.\nd).- Renta de espacio para fotógrafo por evento.. $ 580.00 M.N.\ne).- Renta para eventos de entretenimiento:\nTemporada de invierno (Nov-Abr)............ $4,090.00 M.N.\nTemporada de verano (May-Oct).............. $5,840.00 M.N.\nMunicipales e Instituciones Educativas Públicas, con autorización previa del Director.\nIII.- Renta de Campo Deportivo Francisco Villa:\na).- Renta del campo Francisco Villa para Futbol\nSoccer:\n1.- Renta del campo para entrenamiento de día por hora (8:00 a 19:00 horas).............. $ 175.00 M.N.\n2.- Renta del campo para entrenamiento de noche por hora (19:00 a 22:15 horas)..................................... $ 230.00 M.N.\n3.- Renta del campo por partido de día (8:00 a\n19:00 horas).............................. $ 290.00 M.N.\n4.- Renta del campo por partido de noche (19:00 a 22:15 horas)............................. $ 350.00 M.N.\nb).- Renta del campo Francisco Villa para Futbol\nAmericano y Banderitas:\n1.- Renta del campo para entrenamiento de día por hora (8:00 a 19:00 horas)............... $ 230.00 M.N.\n2.- Renta del campo para entrenamiento de noche por hora (19:00 a 22:15 horas).............. $ 290.00 M.N.\n3.- Renta del campo por partido de día (8:00 a\n19:00 horas)............................... $ 350.00 M.N.\n4.- Renta del campo por partido de noche (19:00 a 22:15 horas).............................. $ 405.00 M.N.\nc).- Fracción de hora no contemplada previamente..... $ 230.00 M.N.\nd).- Renta de espacio para publicidad por mes (fuera del cerco perimetral).......................... $ 230.00 M.N.\ne).- Renta para eventos especiales:\n1.- Organismos empresariales y profesionales\n(Empresas privadas y colegios).............. $2,920.00 M.N.\n2.- Organismos de Gobierno..................... $1,780.00 M.N.\n3.- Instituciones educativas privadas.......... $2,920.00 M.N.\n4.- Sociedades y asociaciones civiles.......... $2,335.00 M.N.\nf).- Renta de espacio exterior para publicidad por mes\n(5.6 mts x 3.4 mts) Río Nuevo e Independencia.... $5,250.00 M.N.\nEl Director del organismo tiene la facultad de aplicar un descuento del 50% en el cobro de las cuotas por la renta del Campo Francisco Villa y en la renta del espacio exterior para publicidad previo estudio socioeconómico en cada caso. eventos especiales.\nIV.- Acceso Campo Deportivo Francisco Villa:\n1.- Entrada de niños hasta 3 años.............. EXENTO\n2.- Entrada para personas con discapacidad..... EXENTO\n3.- Entrada adulto mayor presentando tarjeta de\nINAPAM o cualquier identificación vigente que lo acredite............................ EXENTO\n4.- Entrada general mayor de 3 años............ $ 17.50 M.N.\n5.- Carnet mensual para entrenamiento.......... $ 70.00 M.N.\n6.- Carnet anual para entrenamiento........... $ 680.00 M.N.\nV.- Cuota por cursos y talleres impartidos en los\nCentros de Desarrollo Humano Integral........ $ 19.00 M.N.\na).- Deportivo por semana y por usuario......... $ 90.00 M.N.\nb).- Cultural por semana y por usuario.......... $ 90.00 M.N.\nc).- De oficios por semana y por usuario........ $ 120.00 M.N.\nd).- Educativo por semana y por usuario a excepción de INEA.......................... $ 90.00 M.N.\ne).- Servicios de atención psicológica y nutricional por semana y por usuario....... $ 145.00 M.N.\nVI.- Plan Vacacional en cualquier Centro de Desarrollo\nHumano Integral de BISOM por alumno:\na).- Plan vacacional en cualquier Centro por alumno, por diez días................. $ 365.00 M.N.\nb).- En caso de inscribirse en el plan vacacional un segundo hermano.............. $ 180.00 M.N.\nc).- En caso de inscribir a un tercer hermano o más en el plan vacacional.................. $ 90.00 M.N. por cada uno\nSe exentará del cobro anterior a las personas en situación vulnerable previo estudio socioeconómico y con autorización del Director.\nVII.- Renta de campo deportivo Los Santorales:\na).- Renta del campo deportivo juego (2 horas) sin energía eléctrica, pasto sintético..... $ 115.00 M.N.\nb).- Renta del campo deportivo juego (2 horas) con energía eléctrica, pasto sintético...... $ 230.00 M.N.\nc).- Entrada al campo deportivo por día......... $ 12.50 M.N.\nd).- Entrada niños hasta 3 años................. EXENTO\ne).- Entrada para personas con discapacidad presentando credencial..................... EXENTO\nf).- Entrada adulto mayor presentando tarjeta de\nINAPAM o cualquier identificación vigente que lo acredite............................ EXENTO\ng).- Carnet mensual para entrenamiento.......... $ 58.00 M.N.\nh).- Carnet anual para entrenamiento...........$ $ 525.00 M.N.\nEl Director del organismo tiene la facultad de aplicar un descuento del 50% en el cobro de las cuotas por la renta del Campo Deportivo Santorales previo estudio socioeconómico en cada caso.\nEl Director tiene la facultad de exentar el cobro de la entrada al campo en eventos especiales.\nVIII. Acceso al estacionamiento de Río Nuevo:\na).- En el periodo Fiestas del Sol y Villa\nNavideña............................ $ 58.00 M.N.\nb).- Cualquier otro evento masivo............... $ 58.00 M.N.\nc).- En periodo distinto a las Fiestas del Sol y\nVilla Navideña........................... EXENTO\nVilla, así como al personal que labora en BISOM e\nIMDECUF, durante el periodo de Fiestas del Sol, estará EXENTO.\nIX.- Renta mensual del espacio para máquinas expendedoras será el equivalente al 10% de la venta mensual total.\nX.- Renta de Espacio (cuota diaria):\na).- Renta para espacio a vendedor ambulante para eventos en exterior de BISOM........ $ 52.00 M.N.\nb).- Renta de espacio para modulo comercial de\n3 mts x 3 mts en la zona de bazar......... $ 105.00 M.N.\nc).- Renta de espacio por día para módulo de comida de 3 mts x 3 mts en la zona del bazar.................................... $ 105.00 M.N.\nXI.- Otros Servicios:\nSe cobrarán Derechos de conformidad al presupuesto que al efecto realice Bienestar Social Municipal de la Ciudad de Mexicali, los que en todo caso serán proporcionales al costo del servicio. Los ingresos que por concepto de derechos, transferencias, asignaciones y ayudas sociales que se perciban, pasarán a formar parte del patrimonio de\nBienestar Social Municipal de la Ciudad de Mexicali.\nINGRESOS DEL COMITÉ DE PLANEACIÓN PARA EL DESARROLLO\nDEL MUNICIPIO DE MEXICALI\nARTÍCULO 80.- Los ingresos, participaciones, transferencias, asignaciones, subsidios, donativos y otras ayudas que reciba este organismo descentralizado se percibirán cuando lo decrete y exhiba, conforme a su reglamento interior, y pasarán a formar parte del patrimonio del Comité de Planeación para el Desarrollo del Municipio de Mexicali, Baja California.\nINGRESOS DEL PATRONATO D.A.R.E.\nDE LA CIUDAD MEXICALI\n(EDUCACIÓN PREVENTIVA CONTRA EL CONSUMO DE DROGAS Y VIOLENCIA)\nARTÍCULO 81.- Los ingresos, participaciones, aportaciones, transferencias, asignaciones, subsidios, donativos y otras ayudas que y exhiba, conforme a su reglamento interior, y pasarán a formar parte del patrimonio del Patronato D.A.R.E. de Mexicali, Baja California.\nSERVICIOS QUE PRESTA EL FIDEICOMISO PARA EL\nDESARROLLO URBANO DE MEXICALI\nARTÍCULO 82.- Los servicios que presta el Fideicomiso para el\nDesarrollo Urbano de Mexicali, se cobrarán conforme a lo siguiente:\nI.- Venta y cobranza de Bienes Inmuebles:\na).- Pago por concepto de compraventa de Bienes\nInmuebles y sus derivados (parcialidades, pago inicial de adendum) con un anticipo o pago inicial de al menos el 10% del valor de la propiedad pagado hasta en tres exhibiciones, así como las mensualidades que le correspondan de acuerdo a la tabla de amortización o abonos que den a las mismas.\nb).- Por concepto de anticipo de clientes en el apartado de un predio habitacional sin la posibilidad de que el promitente comprador ocupe el inmueble, se cobrará al menos 10% del precio de pre-venta correspondiente.\nII.- Por expedición de documentos:\na).- Por expedición de Títulos de Propiedad, cuando se trate de bienes de uso habitacional.............................. $ 7 0 7.00 M.N.\nTratándose de personas en situación vulnerable: personas mayores de\n60 años, personas viudas mayores de 50 años, personas con discapacidad, jubilados y pensionados, entre otros, cuando se trate de bienes inmuebles de uso habitacional se le cobrará el 50% de la tarifa.\nb).- Por expedición de Títulos de Propiedad, cuando se trate de bienes de uso de suelo distinto al habitacional.................. $3,000.00 M.N.\nc).- Por expedición de Cesión de Derechos en bienes inmuebles de uso habitacional...... $ 7 0 7.00 M.N.\nd).- Por expedición de Carta Finiquito, respecto de bienes inmuebles de uso habitacional.............................. $ 3 5 0.00 M.N.\ne).- Por expedición de Carta Finiquito, cuando se trate de bienes de uso de suelo distinto al habitacional.................. $ 350.00 M.N.\nTratándose de personas en situación vulnerable: personas mayores de\n60 años, personas viudas mayores de 50 años, personas con discapacidad, jubilados y pensionados, entre otros, cuando se trate de bienes inmuebles de uso habitacional se le cobrará el 50% de la tarifa.\nf).- Por expedición de Cesión de Derechos en bienes inmuebles de uso de suelo distinto\nIII.- Intereses:\na).- Interés por Financiamiento:\n1.- Pago realizado por concepto de la Tasa de\nInterés Interbancaria de Equilibrio (TIIE) y en su caso hasta cinco puntos, aplicable al financiamiento de la operación en predios de uso diferente al habitacional.\nb).- Interés Moratorio:\n1.- Bienes Inmuebles de uso habitacional:\nEl pago realizado que se deriva del incumplimiento de las obligaciones será el equivalente a la Tasa del Costo\nPorcentual Promedio (CPP) que emite el\n2.- Bienes Inmuebles de uso distinto al habitacional:\nPago realizado que se deriva del incumplimiento de las obligaciones será el equivalente a la Tasa de Interés\nInterbancaria de Equilibrio (TITE) multiplicado por dos.\nIV.- Gastos de cobranza:\na).- Por generación de gastos de cobranza a domicilio de bienes inmuebles de uso habitacional.............................. $ 234.00 M.N.\nTratándose de personas en situación vulnerable: personas mayores de 60 años, personas viudas mayores de 50 años, personas con discapacidad, jubilados y pensionados, entre otros, cuando se trate de bienes inmuebles de uso habitacional se le cobrará el 50% de la tarifa.\nb).- Por generación de gastos de cobranza a domicilio en bienes inmuebles de uso distinto al habitacional se cobrará el 5% sobre el valor de la deuda requerida.\nV.- Bases de Licitación:\na).- El costo será fijado considerando una una cantidad equivalente a la décima parte del costo estimado para la publicación de la convocatoria correspondiente.\nVI.- Programa de Regularización de Titulación de\nVivienda.\nDichos programas de regularización (ya sean federales, estatales, municipales y/o en convenio con la Sociedad Civil), podrán incluir la exención parcial o total de los trámites relacionados con los mismos.\nVII.- Gestoría de trámites con terceros para la\nTitulación de Vivienda:\na).- El costo por la firma del Delegado\nFiduciario en el contrato de transmisión de propiedad en los inmuebles de uso de habitacional.............................. $ 580.00 M.N.\nb).- El costo de los documentos que se requieren para la inscripción ante el Registro\nPúblico de la Propiedad y de Comercio de los contratos de transmisión de propiedad en los inmuebles de uso de suelo habitacional.............................. $ 7,500.00 M.N.\nVIII.- Ingresos por arrendamiento:\na).- Por el arrendamiento de terreno, un importe no menor al setenta y cinco porciento (75%) en base al valor avalúo para arrendamiento.\nb).- Por el arrendamiento de espacios y locales para oficinas y comercio, un importe no menor al setenta y cinco por ciento (75%) en base al valor avalúo para arrendamiento de este tipo..............................\nIX.- Otros Servicios:\na).- Servicios de obras:\nParalelo a la compraventa o apartado de un predio habitacional se podrá cobrar 5% o más del precio correspondiente por concepto de instalación de servicios de obra complementaria tales como, pavimentación, construcción, instalaciones hidráulicas, eléctricas, y/o equipamiento habitacional entre otros necesarios y contratados para ocupar dicho predio.\nb).- Comisión por administración y/o comercialización:\nDado el caso de la consignación de inmuebles, muebles o subrogación de servicios, por concepto de administración y/o comercialización se cobrará al menos el\n3% del valor de la operación comercial, pagaderos a más tardar al momento de realizarse el cobro por el consignante o por algún tercero. realice el Fideicomiso para el Desarrollo Urbano de Mexicali, los que en todo caso serán proporcionales al costo del servicio. Los ingresos que por concepto de derechos, transferencias, asignaciones y ayudas sociales que se perciban, pasarán a formar parte del patrimonio del\nFideicomiso para el Desarrollo Urbano de Mexicali.\nPARA LA SEGURIDAD PÚBLICA\nARTÍCULO 83.- Los ingresos, participaciones, transferencias, asignaciones, subsidios, donativos y otras ayudas que reciba este organismo descentralizado se percibirán cuando lo decrete y exhiba, conforme a su reglamento interior, y pasarán a formar parte del patrimonio del Patronato Denominado Alianza Empresarial para la\nSeguridad Pública.\nINGRESOS DEL INSTITUTO DE LA MUJER PARA EL MUNICIPIO\nDE MEXICALI, BAJA CALIFORNIA\nARTÍCULO 84.- Los ingresos, participaciones, transferencias, asignaciones, subsidios, donativos y otras ayudas que reciba este organismo descentralizado se percibirán cuando lo decrete y exhiba, conforme a su reglamento interior, y pasarán a formar parte del patrimonio del Instituto de la Mujer para el Municipio de Mexicali, Baja California.\nSERVICIOS QUE PRESTA EL INSTITUTO MUNICIPAL DE LA JUVENTUD\nDE MEXICALI, BAJA CALIFORNIA\nARTÍCULO 85.- Los servicios que presta el Instituto Municipal de la\nJuventud de Mexicali, Baja California, se cobrará conforme a lo siguiente:\nTARIFA\nMONEDA NACIONAL\nI.- Eventos culturales, sociales y deportivos.\na).- Inscripción............................... $ 0.00 a\n$ 250.00 M.N.\nb).- Entrada general a eventos:\n1.- Adultos................................. $ 30.00 M.N.\n2.- Niños hasta 11 años...................... $ 15.00 M.N.\nII.- Asesorías para el desarrollo integral de las juventudes:\n1.- Por sesión............................... $ 100.00 M.N.\nIII.- Otros servicios:\nEl Instituto Municipal de la Juventud de Mexicali, Baja California así como personas físicas y morales, subsidios, aportaciones, subvenciones, donativos en especie y bienes muebles.\nSe cobrarán Derechos de conformidad al presupuesto que al efecto realice el Instituto Municipal de la Juventud de Mexicali, Baja\nCalifornia los que en todo caso serán proporcionales al costo del servicio. Los ingresos que por concepto de derechos transferencias, asignaciones, donaciones y ayudas sociales que se perciban, pasarán a formar parte del patrimonio del Instituto Municipal de la Juventud de\nMexicali, Baja California.\nTÍTULO NOVENO\n8 PARTICIPACIONES, APORTACIONES, CONVENIOS, INCENTIVOS DERIVADOS DE\nCAPÍTULO I\n1 PARTICIPACIONES\n01 PARTICIPACIONES DE CONTRIBUCIONES FEDERALES\n02 PARTICIPACIONES DE CONTRIBUCIONES ESTATALES\nObras.\nII.- Por Otros Impuestos o Ingresos del Estado, que señalen las Leyes, Acuerdos o Convenios que las Regulen.\nCAPÍTULO II\n2 APORTACIONES\n01 APORTACIONES FEDERALES DEL RAMO 33\nI.- Fondo de Aportaciones para la Infraestructura Social Municipal.\nII.- Fondo de Aportaciones para el Fortalecimiento de los Municipios.\n02 OTRAS APORTACIONES\nI.- Fondo de Desarrollo Regional Sustentable de Estados y Municipios\nMineros.\nCAPÍTULO III\n3 CONVENIOS\n01 OTROS INGRESOS POR CONVENIOS FEDERALES\n02 OTROS INGRESOS POR CONVENIOS ESTATALES\nI.- Convenio de Colaboración Administrativa en Materia Fiscal Federal\nCalifornia y el Ayuntamiento del Municipio de Mexicali.\nII.- Convenio de Colaboración para la Administración de Multas\nBaja California y al Ayuntamiento de Mexicali.\n4 INCENTIVOS DERIVADOS DE LA COLABORACIÓN FISCAL\n5 FONDOS DISTINTOS DE APORTACIONES\nTÍTULO DÉCIMO\n9 TRANSFERENCIAS, ASIGNACIONES, SUBSIDIOS Y SUBVENCIONES,\nY PENSIONES Y JUBILACIONES\nCAPÍTULO I\n1 TRANSFERENCIAS Y ASIGNACIONES\n3 SUBSIDIOS Y SUBVENCIONES\n01 SUBSIDIOS Y SUBVENCIONES\n5 PENSIONES Y JUBILACIONES\n7 TRANSFERENCIAS DEL FONDO MEXICANO DEL PETRÓLEO PARA LA\nESTABILIZACIÓN Y EL DESAROLLO\nTÍTULO DECIMOPRIMERO\n0 INGRESOS DERIVADOS DE FINANCIAMIENTOS\nCAPÍTULO I\n1 ENDEUDAMIENTO INTERNO\n1.- Créditos otorgados al municipio\nDeuda Pública.\nLa Deuda Pública Municipal, se constituye por las obligaciones derivadas de las operaciones de financiamiento.\nCAPÍTULO II\n2 ENDEUDAMIENTO EXTERNO\n1.- Otros créditos otorgados al municipio.\nTÍTULO DECIMOSEGUNDO\nDISPOSICIONES GENERALES\nARTÍCULO 86.- Las participaciones de impuestos federales y estatales que perciba el Municipio, serán las que fijen las Leyes, Convenios\nFederales y Estatales respectivas.\nARTÍCULO 87.- La validez de las licencias, así como permisos otorgados por el Municipio, está condicionada al exacto cumplimiento de los ordenamientos legales aplicables.\nARTÍCULO 88.- Los gravámenes que prevé la presente Ley, no serán motivo de exención, condonación o modificación por parte de las autoridades municipales, salvo por autorización expresa del Congreso del Estado, con excepción de los Recargos, que podrán condonarse total o parcialmente, conforme al Artículo 110 de la Ley de Hacienda Municipal del Estado de Baja California.\nARTÍCULO 89.- Las personas físicas o morales, que para expender sus mercancías lo hagan a través de vendedores ambulantes, agentes de venta, comisionistas, repartidores, concesionarios ambulantes o cualquier otro nombre que se le dé al expendedor, serán solidariamente responsables del pago de los Impuestos, Derechos y/o Multas que se originen con motivo de las actividades que ejerzan para lo cual se constituirán en retenedores de los Créditos Fiscales, debiendo enterarlos a la Recaudación de Rentas Municipal, dentro de los plazos que fijen las Leyes Fiscales.\nARTÍCULO 90.- Son cuotas de cooperación los ingresos que perciba el\nConsejo de Urbanización Municipal de Mexicali, a cargo de los propietarios y/o poseedores de los predios que se beneficien de manera directa por obras de urbanización, de acuerdo a las bases y\nCalifornia.\nARTÍCULO 91.- El cheque recibido por las autoridades fiscales que sea presentado en tiempo y no sea pagado, dará lugar al cobro del monto de éste, y se exigirá independientemente de los demás conceptos a que se refiere este artículo. Para tal efecto, la Recaudación de Rentas\nMunicipal requerirá al librador del cheque para que, dentro de un plazo de tres días, efectúe el pago junto con la mencionada indemnización del 20%, o bien, acredite fehacientemente, con las pruebas documentales procedentes, que se realizó el pago o que dicho pago no se realizó por causas exclusivamente imputables a la institución de crédito.\nTranscurrido el plazo señalado sin que se obtenga el pago o se demuestre cualquiera de los extremos antes señalados, la autoridad fiscal requerirá y cobrará el monto del cheque, la indemnización mencionada y los demás accesorios que correspondan, mediante el procedimiento administrativo de ejecución, sin perjuicio de la responsabilidad que en su caso procediere.\n3 FINANCIAMIENTO INTERNO\nARTÍCULO PRIMERO.- La presente Ley entrará en vigor el día primero de\nEnero del año dos mil veinticinco.\nARTÍCULO SEGUNDO.- Las contribuciones cuyo cobro haya quedado suspendido con base a los acuerdos celebrados con el Gobierno Federal y las Leyes Fiscales de la Federación, en caso de reformas o modificaciones a estas disposiciones, que permitan el cobro de dichas suspensión de cada contribución.\nARTÍCULO TERCERO.- La Unidad de Medida y Actualización aplicable en todos los conceptos que marca la presente Ley, será la última publicada\nARTÍCULO CUARTO.- Será el Ayuntamiento quien reglamentará el uso de los rangos en los derechos por cobrar, de acuerdo al tabulador que para dicho efecto aprueben.\nARTÍCULO QUINTO.- Los beneficios a pensionados, jubilados, personas propietarios de varios inmuebles.\nARTÍCULO SEXTO.- La Tesorería Municipal proporcionará a las sociedades las Sociedades de Información Crediticia, la información de los establecen.\nARTÍCULO SÉPTIMO. - En caso de que durante el presente ejercicio fiscal, las dependencias a que se refiere esta Ley, sufrieran alguna modificación en sus funciones o cambiaran su denominación, los servicios previstos para ser prestados por dichas dependencias, se entenderán por referidos y prestados por las que las sustituyan, dando lugar al pago de los derechos que señala ésta.\nARTÍCULO OCTAVO. - La Ley que se abroga, seguirá vigente respecto de las obras que se ejecutaron o estén en proceso de ejecución al entrar en vigor la presente Ley.\nARTÍCULO NOVENO. - Serán homogéneos en su valor unitario de suelo, los predios que colinden con aquellos ubicados en corredores comerciales e industriales y que sirvan o se utilicen para los mismos fines, sin importar las características del mismo.\nARTÍCULO DECIMO. - La presente Ley de Ingresos se encontrará disponible\nARTÍCULO DECIMOPRIMERO. - En el cobro establecido en el artículo 3, las entidades paramunicipales podrán causar una tasa del 2.5%; siempre cuente con anuencia de la Secretaría del Ayuntamiento.\nARTÍCULO DECIMOSEGUNDO. - En el caso de los cobros establecidos en el artículo 23 fracción VII, artículo 26 y el artículo 37 numeral F, las entidades paramunicipales podrán quedar exentas; siempre y cuando la anuencia de la Secretaría del Ayuntamiento.\nARTÍCULO DECIMOTERCERO.-Tratándose de adquisiciones de inmuebles que\nCalifornia (INDIVI) o con el Instituto Nacional del Suelo Sustentable\n(INSUS), y las que se realicen a través de cualquier dependencia oficial que promueva desarrollos habitacionales de interés social y popular, pagarán por concepto del impuesto sobre Adquisición de\nInmueble, el equivalente a dos Unidades de Medida y Actualización vigente.\nARTÍCULO DECIMOCUARTO.- Se implementará un programa para otorgar una póliza de seguro de daños para casa-habitación a las primeras cincuenta mil personas físicas que realicen el pago del impuesto predial de aquellos predios con tasa de casa-habitación.\nARTÍCULO DECIMOQUINTO. - A partir de la fecha de entrada en vigor de la presente Ley, todas las referencias que se realicen a la Tabla de\nValores Catastrales Unitarios en esta ley y en otros ordenamientos relacionados, se entenderán referidas a la Tabla de Valores Unitarios de Suelo (Valores Catastrales).\nARTÍCULO DECIMOSEXTO.- Se exenta a las personas físicas y morales inscritas en el Programa Estatal de Vivienda 2022-2027, del pago de derechos que se causen por: factibilidades, dictámenes, certificados, autorizaciones, licencias y en general, por trámites relacionados con la construcción de vivienda social, exclusivamente para los proyectos\nTitular de la Secretaría de Infraestructura, Desarrollo Urbano y\nReordenación Territorial del Estado de Baja California (SIDURT), y se actualizaciones posteriores, así como del Programa de Vivienda para\nDesarrollo Agrario, Territorial y Urbano (SEDATU), Instituto Nacional del Suelo Sustentable (INSUS), Comisión Nacional de Vivienda (CONAVI), (INFONAVIT), Instituto de Seguridad y Servicios Sociales de los\nTrabajadores del Estado (ISSSTE) y el Fondo de la Vivienda del\nEstado (FOVISSSTE), en conjunto con la Entidad Federativa y sus\nMunicipios.\nLas contribuciones a exentar se enuncian a continuación:\n1. Factibilidad de uso del suelo;\n2. Constancia de libertad de gravamen;\n3. Dictamen de uso del suelo;\n4. Manifiesto de impacto ambiental;\n5. Movimiento de tierras;\n6. Certificación de deslinde catastral;\n7. Licencia de Construcción;\n8. Régimen de Propiedad en Condominio;\n9. Autorización de Fraccionamiento;\n10. Asignación y expedición de número oficial;\n11. Constancia de terminación de obra;\n12. Cambio de propietario, e\n13. Impuesto sobre adquisición de bienes inmuebles.\nArtículo Transitorio Adicionado a los veinte días del mes de diciembre del dos mil veinticuatro.\nC. EVELYN SÁNCHEZ SÁNCHEZ\nDIPUTADA PRESIDENTA\nC. MICHELLE ALEJANDRA TEJEDA MEDINA\nDIPUTADA SECRETARIA\nARTÍCULO DECIMOSEXTO TRANSITORIO.- Fue adicionado mediante el Decreto No. 117, expedido por la H. XXV Legislatura, siendo Gobernadora Constitucional la C. Marina del Pilar\nÁvila Olmeda 2021-2027;\nARTÍCULO ÚNICO TRANSITORIO DEL DECRETO No. 117, POR EL QUE SE\nTRANSITORIO; PUBLICADO EN EL PERIÓDICO OFICIAL No. 42, SECCIÓN I, DE FECHA\nGOBERNADORA CONSTITUCIONAL LA C. MARINA DEL PILAR ÁVILA OLMEDA 2021-\n2027.\nARTÍCULOS TRANSITORIOS\nARTÍCULO PRIMERO: La presente reforma entrará en vigor al día siguiente de su publicación en el Periódico Oficial del Estado de Baja California.\nARTÍCULO SEGUNDO: Notifíquese a la Presidenta Municipal del H. XXV Ayuntamiento de\nMexicali, Baja California.\nARTÍCULO TERCERO: Remítase la presente Iniciativa al Poder Ejecutivo del Estado de Baja\nCalifornia, pasa su publicación en el Periódico Oficial del Estado de Baja California\nDADO en Sesión Ordinaria de la XXV Legislatura en la Ciudad de Mexicali, B.C., a los tres días del mes de julio del año dos mil veinticinco.\nDIP. MICHELLE ALEJANDRA TEJEDA MEDINA\nPRESIDENTA\n(RÚBICA)\nDIP. NORMA ANGELICA PEÑALOZA ESCOBEDO\nSECRETARIA\n(RÚBICA)\nDE CONFORMIDAD CON LO DISPUESTO POR LA FRACCIÓN I DEL ARTÍCULO 49\nCALIFORNIA, IMPRÍMASE Y PUBLÍQUESE.\nMEXICALI, BAJA CALIFORNIA, A LOS 4 DÍAS DEL MES DE JULIO DEL AÑO DOS\nMIL VEINTICINCO.\nMARINA DEL PILAR ÁVILA OLMEDA\nGOBERNADORA DEL ESTADO\nDE BAJA CALIFORNIA\n(RÚBRICA)\nALFREDO ÁLVAREZ CÁRDENAS\nSECRETARIO GENERAL DE GOBIERNO\nDEL ESTADO DE BAJA CALIFORNIA\n(RÚBRICA)",
  "ordenamiento": "REGLAMENTO",
  "jurisdiccion": "BAJA CALIFORNIA",
  "fuente_oficial": "Periódico Oficial",
  "FECHA PER OFIC": "2025/07/18",
  "ESTATUS": "VIGENTE",
  "TOMO": "TOMO_II",
  "URL": "https://www.congresobc.gob.mx/Documentos/ProcesoParlamentario/Leyes/TOMO_II/20250718_LEYINGRESOMEXICALI2025.PDF",
  "es_escaneado": false,
  "tiene_tablas": true,
  "materia": [
    "financiero",
    "fiscal",
    "económico"
  ]
}