{
  "titulo": "Ley DE PREVENCIÓN, MITIGACIÓN y ADAPTACIÓN DEL CAMBIO CLIMÁTICO PARA EL ESTADO DE BAJA CALIFORNIA",
  "Contenido": ".\nActualización Legislativa.\nÚltima Reforma P.O. No. 40, Índice, 16/Ago/2024\nLEY DE PREVENCIÓN, MITIGACIÓN Y ADAPTACIÓN DEL CAMBIO\nCLIMÁTICO PARA EL ESTADO DE BAJA CALIFORNIA\nPublicado en el Periódico Oficial No. 25, de fecha 01 de junio de 2012, Tomo CXIX\nCAPÍTULO I\nDISPOSICIONES GENERALES\nArtículo 1. La presente Ley es de orden público e interés social; sus disposiciones son de observancia obligatoria en el territorio del Estado de Baja California y tienen por objeto establecer la concurrencia del Estado y de los Municipios en la formulación e instrumentación de la política estatal y municipal de cambio climático para prevenir y mitigar sus efectos adversos con el fin de proteger a la población y coadyuvar al desarrollo sustentable.\nEn lo no previsto por esta Ley, se aplicarán de manera supletoria y complementaria los ordenamientos estatales en materia ambiental.\nArtículo Reformado\nArtículo 2. Son objetivos específicos de esta Ley:\nI. Definir los criterios para la formulación de la política estatal y municipal de cambio climático;\nII. Desarrollar indicadores en materia de prevención, adaptación y mitigación ante el cambio climático y evaluar de manera periódica los resultados de las acciones realizadas.\nIII. Establecer las bases de coordinación institucional entre las dependencias del\nGobierno del Estado, los Municipios y el Gobierno Federal en materia de vulnerabilidad, riesgo, prevención, adaptación y mitigación ante el cambio climático.\nIV. Instrumentar la participación solidaria de la sociedad en materia de prevención adaptación y mitigación ante el cambio climático.\nV. Contribuir a frenar los procesos de deterioro ambiental en las áreas más vulnerables de la entidad, tales como: la conservación de la biodiversidad, la protección y aprovechamiento sustentable de ecosistemas, la conservación de suelos y el resguardo de los recursos hidrológicos.\nVI. Promover políticas de conservación que permitan efectuar la restauración de áreas degradadas y la conservación y manejo sustentable de los ecosistemas del Estado.\nVII. Identificar temas prioritarios para el desarrollo de la Estrategia Estatal de Acción\nClimática.\nVIII. Contribuir como Estado, al cumplimiento de las obligaciones internacionales de\nMéxico en materia de cambio climático.\nLey de Prevención, Mitigación y Adaptación del Página 1\n.\nActualización Legislativa.\nÚltima Reforma P.O. No. 40, Índice, 16/Ago/2024\nIX. Impulsar el Programa de Acción ante el Cambio Climático del Estado.\nX. Garantizar el derecho a un medio ambiente sano, la equidad intergeneracional y el desarrollo sostenible ante el cambio climático.\nFracción Adicionada\nArtículo Reformado\nArtículo 3. Para los efectos de esta Ley, se entenderá por:\nI. Adaptación: Medida encaminada a reducir la vulnerabilidad de los sistemas naturales y humanos ante los efectos del cambio climático.\nII. Atlas de Riesgos: Colección de mapas a escala con características topográficas, de uso del suelo, hidrología, vías de comunicación, equipamiento e información adicional del\nEstado y de sus municipios, en que se encuentren sobrepuestas zonas, áreas y regiones que indiquen el riesgo potencial que amenaza la población del Estado de Baja California ante los efectos del cambio climático, así como sus bienes y los servicios estratégicos y entorno.\nIII. Calentamiento Global: Es el incremento a largo plazo en la temperatura promedio de la atmósfera. Se debe a la emisión de gases de efecto invernadero que se desprenden por actividades del hombre.\nIV. Cambio Climático: Variación del clima atribuido directa o indirectamente a la actividad humana que altera la composición de la atmósfera y que se suma a la variabilidad natural del clima observada durante períodos de tiempo comparables.\nV. Consejo: Al Consejo para el Cambio Climático del Estado de Baja California.\nVI. Efectos adversos del cambio climático: Variaciones bruscas en el medio ambiente resultantes del cambio climático, que tienen efectos nocivos significativos en la composición, capacidad de recuperación, productividad de los ecosistemas, en la salud y bienestar humano y en el funcionamiento de los sistemas socioeconómicos.\nVII. Emisión: Liberación de gases de efecto invernadero, o sus precursores, en la atmósfera, en un área y en un espacio de tiempo específicos.\nVIII. Estado: Estado de Baja California.\nIX. Estrategia Estatal: Estrategia Estatal de Cambio Climático. Documento que precisa posibilidades e intervalos de reducción de emisores de gases de efecto invernadero, propone los estudios para definir metas de prevención, mitigación y necesidades de adaptación.\nX. Fuentes Emisoras: Organización, establecimiento o instalación, pública o privada, en donde se realizan actividades industriales, comerciales, agropecuarias, de servicios o aprovechamiento de recursos naturales que generan emisiones.\nXI. Gases de Efecto Invernadero: Componentes gaseosos de la atmósfera, que\nKyoto: Dióxido de carbono\nLey de Prevención, Mitigación y Adaptación del Página 2\n.\nActualización Legislativa.\nÚltima Reforma P.O. No. 40, Índice, 16/Ago/2024\n(CO2), metano (CH4), óxido nitroso (N2O), hidrofluorocarbonos (HFC), perfluorocarbonos (PFC) y hexafluoruro de azufre (SF6).\nXII. GEI.- Gases de Efecto Invernadero: Componentes gaseosos de la atmósfera, que absorben y remiten radiación infrarroja y que están incluidos en el Anexo A del Protocolo de\nKioto:\n• Dióxido de carbono (CO2), • Metano (CH4), • Óxido nitroso (N2O), • Hidrofluorocarbonos (HFC), • Perfluorocarbonos (PFC) y\n• Hexafluoruro de azufre (SF6).\nXIII. Ley: Ley de Prevención, Mitigación y Adaptación del Cambio Climático para\nEstado de Baja California.\nXIV. Mecanismo para un Desarrollo Limpio: Mecanismo establecido en el Protocolo de Kyoto a través del cual se financian proyectos de reducción o de captura de gases de efecto invernadero.\nXV. Mitigación: Medida ambiental destinada a reducir las emisiones de gases de efecto invernadero o incrementar su captura.\nXVI. Plan: Plan de Acción Climática del Estado de Baja California. Documento que contempla, en concordancia con su marco estatal de planeación, en forma ordenada y coherente, estrategias, políticas, directrices y tácticas en tiempo y espacio, así como los instrumentos, mecanismos y acciones relacionadas al cambio climático en el ámbito estatal.\nXVII. Protocolo de Kyoto: Tratado internacional ligado a la Convención Marco que establece compromisos legalmente vinculantes, mecanismos y medidas para limitar o reducir las emisiones de gases de efecto invernadero.\nXVIII. Reducciones Certificadas de Emisiones: Disminución de emisiones de gases de efecto invernadero a la atmósfera expresados en toneladas de bióxido de carbono equivalente logradas por alguna actividad o proyecto y que han sido certificadas por alguna entidad autorizada para dichos efectos.\nXIX. Registro: Registro Estatal de Emisiones. Instrumento de registro a cargo de la de reducción de emisiones, así como las transacciones de reducciones certificadas y de permisos de emisión.\nXX. Secretaría: la Secretaría de Protección al Ambiente del Estado de Baja\nCalifornia.\nXXI. Sistema: Sistema Estatal para el Cambio Climático. Es el conjunto de instancias\nLey de Prevención, Mitigación y Adaptación del Página 3\n.\nActualización Legislativa.\nÚltima Reforma P.O. No. 40, Índice, 16/Ago/2024\nEstatal para la prevención y adaptación al cambio climático a través de planes, programas, estrategias y coordinación entre los distintos órdenes de gobierno.\nXXII. Sumidero: Cualquier proceso, actividad o mecanismo que absorbe de la atmósfera un gas de efecto invernadero, uno de sus precursores o un aerosol.\nXXIII. Toneladas de bióxido de carbono equivalentes (CO2e): Unidad de medida de los Gases Efecto Invernadero expresada en toneladas de bióxido de carbono que tendrían el efecto invernadero equivalente. Se asumirán las equivalencias adoptadas por la\nConvención Marco de las Naciones Unidas sobre Cambio Climático, y\nXXIV. Vulnerabilidad: Incapacidad de un sistema climático, hidrológico o humano para enfrentar los efectos del cambio climático, en los aspectos sociales, económicos, culturales, biológicos, sanitarios y ambientales.\nCAPÍTULO II\nDE LAS AUTORIDADES\nArtículo 4. Son autoridades competentes para la aplicación de la presente Ley:\nI. El Gobernador del Estado.\nII. La Secretaría.\nIII. Los Gobiernos Municipales.\nArtículo 5. Las autoridades establecidas por esta Ley así como las dependencias y entidades de la Administración Pública Estatal y los Gobiernos Municipales, en sus respectivos ámbitos de competencia, incorporarán políticas y estrategias en materia de cambio climático dentro de sus planes y programas de desarrollo, para que en forma articulada y coordinada se lleven a cabo las medidas de prevención, adaptación y mitigación para enfrentar el cambio climático, con la participación de la sociedad en general.\nArtículo 6. Para el desarrollo de los objetivos de esta Ley, se implementará en el\nEstado, un Consejo de Cambio Climático como Órgano Técnico Colegiado con carácter permanente, y que tendrá por objeto la definición de la Estrategia Estatal para la prevención, mitigación y adaptación al cambio climático, a través de planes y programas; así como establecer la coordinación entre el Gobierno Estatal y de los Municipios.\nArtículo 7. El Consejo será presidido por el Gobernador del Estado y estará integrada por los titulares de las dependencias y entidades siguientes:\nI. El Secretario de Protección al Ambiente, quien suplirá en sus ausencias al\nGobernador;\nII. El Director de Protección Civil;\nIII. El Secretario de Infraestructura y Desarrollo Urbano;\nIV. El Secretario de Desarrollo Económico;\nLey de Prevención, Mitigación y Adaptación del Página 4\n.\nActualización Legislativa.\nÚltima Reforma P.O. No. 40, Índice, 16/Ago/2024\nV. El Secretario de Educación y Bienestar Social;\nVI. El Secretario de Salud;\nVII. El Secretario de Desarrollo Social;\nVIII. El Secretario de Pesca;\nIX. El Secretario de Turismo;\nX. Un representante de la Universidad Autónoma de Baja California;\nXI. Un representante del sector industrial;\nXII. Un representante de la Comisión Estatal de Agua; y\nXIII. El Subsecretario de Protección al Ambiente, quien fungirá como Secretario\nTécnico.\nEl Consejo funcionará con base en lo que disponga su Reglamento Interior, y sus integrantes ejercerán su labor de manera honorífica.\nArtículo 8. El Consejo podrá convocar a otras dependencias y entidades gubernamentales, e invitar a representantes del Poder Judicial, del Congreso del Estado, de los Ayuntamientos del Estado de Baja California, de los Organismos Constitucionales\nAutónomos, y de Organismos o Instituciones de la Sociedad, a participar en sus trabajos cuando se aborden temas relacionados con el ámbito de su competencia u objeto.\nEn los términos del Reglamento que al efecto se expida, al Consejo se integrarán miembros provenientes de la sociedad civil, organismos privados y académicos con experiencia en temas de cambio climático, quienes serán designados por el Presidente del\nConsejo a propuesta de sus integrantes, debiendo garantizarse el equilibrio en la representación.\nArtículo Reformado\nArtículo 9. El Consejo celebrará sesiones ordinarias por lo menos dos veces al año; pudiendo reunirse además en sesiones extraordinarias a convocatoria de su Presidente, o a petición de cualquiera de sus miembros.\nArtículo 10. Son atribuciones del Consejo:\nI. Formular y evaluar las políticas, planes, estrategias, acciones y metas de cambio climático para el Estado, proponiendo en su caso las medidas y recomendaciones necesarias para fortalecer o reorientar los avances logrados, en cumplimiento a los fines de esta Ley.\nII. Gestionar la coordinación y homologación de programas, medidas y acciones de prevención, adaptación y mitigación al cambio climático por parte de las Dependencias y\nEntidades de la Administración Pública Estatal, así como con los programas creados por el\nMunicipales.\nLey de Prevención, Mitigación y Adaptación del Página 5\n.\nActualización Legislativa.\nÚltima Reforma P.O. No. 40, Índice, 16/Ago/2024\nIII. Elaborar y actualizar de manera permanente el Atlas de Riesgos en materia de cambio climático, así como los demás estudios y diagnósticos que se consideren necesarios para el cumplimiento de las disposiciones de esta Ley.\nIV. Definir y coordinar la realización de las acciones para el diseño e instrumentación del Programa de Acción ante el cambio climático y la Estrategia Estatal de Acción Climática, así como las medidas de mitigación y adaptación.\nV. Establecer metas e indicadores de efectividad e impacto de las acciones de su competencia.\nVI. Llevar a cabo la implementación, monitoreo, seguimiento y evaluación del\nPrograma y la Estrategia Estatal de Acción Climática.\nVII. Aprobar las reglas de operación del Fondo Ambiental del Estado.\nVIII. Establecer las bases técnicas y jurídicas que se requieran para fomentar la participación de empresas, con prioridad en el sector de industrial, en las acciones de\nPrevención, Mitigación y Adaptación al Cambio Climático.\nIX. Promover, difundir y en su caso, aprobar proyectos de reducción o captura de emisiones, en términos del mercado, del Protocolo de Kyoto, así como de otros instrumentos firmados y ratificados por el Gobierno Federal que estén orientados al mismo objetivo.\nX. Proponer la implementación de estímulos para promover inversiones y cambios de conducta en actividades industriales, comerciales y de servicios, que generan emisiones de efecto invernadero, así como para otorgar incentivos a quienes realicen acciones para la protección, preservación o restauración del equilibrio climático, y a quienes se apeguen a los\nProgramas estatales de eficiencia energética, de energías renovables y sustentabilidad energética.\nXI. Analizar el desarrollo e integración de un marco jurídico estatal congruente con la política pública en materia de cambio climático a nivel nacional.\nXII. Convocar a otras dependencias y entidades gubernamentales e invitar a representantes del Poder Judicial, del Congreso del Estado, de los Ayuntamientos del\nEstado de Baja California, de los Organismos Constitucionales Autónomos, y de otras\nEntidades Federativas, a participar en sus trabajos cuando se aborden temas relacionados en el ámbito de su competencia.\nXIII. Establecer las normas técnicas ambientales estatales en materia de cambio climático, y las medidas de vigilancia para su cumplimiento en la materia.\nXIV. Las demás que sean necesarias para el cumplimiento de sus fines, conforme a las bases y disposiciones de esta Ley.\nArtículo Reformado\nCAPÍTULO III\nMUNICIPAL DE CAMBIO CLIMÁTICO\nDenominación Modificada\nLey de Prevención, Mitigación y Adaptación del Página 6\n.\nActualización Legislativa.\nÚltima Reforma P.O. No. 40, Índice, 16/Ago/2024\nArtículo 10 BIS.- Son principios rectores de la política estatal de cambio climático:\nI. Compromiso: obligación del Estado con el desarrollo económico, social y humano, como una forma de reducir la vulnerabilidad de sectores desprotegidos ante los efectos adversos del cambio climático;\nII. Conservación: acción y efecto de conservar los ecosistemas y su biodiversidad, dando prioridad a las zonas forestales del Estado, fundamentales para reducir la vulnerabilidad social y ambiental ante los efectos adversos del cambio climático;\nIII. Corresponsabilidad: responsabilidad compartida del gobierno con la sociedad, en la realización de acciones para la mitigación y adaptación a los efectos adversos causados por el cambio climático;\nIV. Prevención: medio más eficaz para evitar los daños al medio ambiente y preservar el equilibrio ecológico ante los efectos del cambio climático;\nV. Responsabilidad ambiental: obligación para quien realice obras o actividades que afecten o puedan afectar al medio ambiente de, prevenir, minimizar, mitigar, reparar, restaurar y, en última instancia, compensar los daños que cause;\nVI. Transparencia y acceso a la información: herramienta para facilitar y fomentar la concientización de la población, poniendo a su disposición la información relativa al cambio climático, y proporcionando acceso efectivo a los procedimientos judiciales y administrativos pertinentes, atendiendo a las disposiciones jurídicas aplicables, y\nVII. Transversalidad: enfoque de coordinación, cooperación y articulación en el diseño, ejecución e instrumentación de los programas y la política pública entre todas las dependencias y los distintos niveles de gobierno, a fin de cumplir con los objetivos de la presente Ley.\nArtículo Adicionado\nArtículo 11. Los habitantes del Estado deberán participar, de manera ordenada y activa, en la mitigación y prevención de la vulnerabilidad ante el cambio climático. Para el cumplimiento de los objetivos establecidos en esta Ley, la política estatal y municipal de cambio climático, los programas sectoriales y la Estrategia Estatal deberán fijar metas y objetivos específicos de mitigación y adaptación, e indicadores de sustentabilidad de las acciones.\nArtículo Reformado\nArtículo 12. En la definición de los objetivos y metas de adaptación, las autoridades del cambio climático, mapas de riesgo, desarrollo de capacidades de adaptación y demás estudios para hacer frente al cambio climático.\nArtículo 13. Quienes realicen programas de investigación y de desarrollo tecnológico y social deberán considerar temas relacionados al cambio climático, así como la creación de fondos concurrentes para financiar la realización de proyectos relativos.\nLey de Prevención, Mitigación y Adaptación del Página 7\n.\nActualización Legislativa.\nÚltima Reforma P.O. No. 40, Índice, 16/Ago/2024\nArtículo 14. Para enfrentar los retos del cambio climático, la política estatal y municipal de cambio climático atenderá de manera prioritaria las necesidades de adaptación en el corto, mediano y largo plazos, conforme a las directrices siguientes:\nI. En materia de protección civil, en los mapas de riesgo, se considerarán los escenarios de vulnerabilidad;\nII. En materia de seguridad agroalimentaria, se impulsará la investigación de posibles escenarios climáticos, para ubicar cultivos prioritarios o señalar la oportunidad de cambio de cultivos, proponer la reconversión productiva sustentable o del método de beneficiarlos;\nIII. Se implementará un Plan Estatal de Ordenamiento Ecológico Territorial y\nDesarrollo Urbano que considere los efectos del cambio climático;\nIV. En toda inversión para infraestructura estatal o municipal, se estimarán los efectos del cambio climático ante futuros fenómenos hidrológicos y meteorológicos extremos, para propiciar la reubicación de asentamientos humanos alejándolos de zonas de riesgo; y\nV. En el monitoreo y pronóstico climático, se incluirán modelos de escenarios ante el cambio climático y la alerta temprana de sus efectos.\nArtículo Reformado\nArtículo 15. En materia de mitigación de gases efecto invernadero, deberán considerarse las directrices siguientes:\nI. La preservación y aumento de sumideros de carbono:\na) Alcanzar una tasa neta de deforestación cero;\nb) Reconvertir las tierras agropecuarias degradadas a sistemas agroforestales de manejo sustentable, de conservación o para la producción de bioenergéticos;\nc) Mejorar la cobertura vegetal en todos los terrenos ganaderos;\nd) Incorporar los ecosistemas forestales a esquemas de pago de servicios ambientales, áreas naturales protegidas, unidades de manejo para la conservación de la vida silvestre o de manejo forestal;\ne) Fortalecer la infraestructura para el combate de incendios forestales; y\nf) Impulsar la certificación de los aprovechamientos forestales.\nII. En centros urbanos de más de cincuenta mil habitantes, la sistematización del manejo de residuos sólidos a fin de que no generen emisiones de metano;\nIII. En todos los centros urbanos, las unidades de transporte público deberán cumplir los estándares de emisión, sujetándose a los programas de verificación vehicular o los concesionarios podrán optar por otros sistemas de transporte colectivo más eficientes; y\nIV. El Estado, conforme a las normas federales de la materia, procurará la generación de energía eléctrica para sus instalaciones, con la utilización de fuentes no contaminantes, como el viento, la luz solar, la biomasa y el oleaje marino.\nLey de Prevención, Mitigación y Adaptación del Página 8\n.\nActualización Legislativa.\nÚltima Reforma P.O. No. 40, Índice, 16/Ago/2024\nCAPÍTULO IV\nDE LA COORDINACIÓN DEL ESTADO Y SUS MUNICIPIOS\nArtículo 16. El Gobierno del Estado realizará las acciones y medidas necesarias para la prevención, mitigación y adaptación al cambio climático, en coordinación con los municipios.\nArtículo 17. Corresponde a las dependencias y entidades del Poder Ejecutivo, en el ámbito de sus respectivas competencias:\nI. Formular y ejecutar las medidas de prevención, adaptación al cambio climático y mitigación de sus efectos;\nII. Proponer al titular del Ejecutivo proyectos de normas y reglamentos en materia de prevención, mitigación y adaptación ante los efectos del cambio climático;\nIII. Vigilar el cumplimiento de la Estrategia Estatal;\nIV. Promover la participación social, conforme a lo dispuesto en esta Ley;\nV. Coordinar con los Municipios la definición de lineamientos y directrices dispuestos en esta Ley;\nVI. Convenir con los sectores social y privado la realización de acciones e inversiones concertadas para mitigación y adaptación al cambio climático;\nVII. Elaborar, en coordinación con los Ayuntamientos, un reporte sobre medidas tomadas para mejorar el ahorro y la eficiencia energética en sus instalaciones y áreas de incumbencia administrativa, así como elaborar sus metas a mediano y corto plazos en este sentido; y\nVIII. Las demás que les señalen esta Ley y otras disposiciones jurídicas.\nArtículo 18. Corresponden a los Municipios, en el ámbito de sus respectivas jurisdicciones, las atribuciones siguientes:\nI. Formular, aprobar y administrar los planes o programas municipales de cambio climático y los demás que de éstos se deriven, así como evaluar y vigilar su cumplimiento, de conformidad con la legislación aplicable;\nII. Promover y realizar acciones e inversiones para la conservación, mejoramiento y previstas en materia de prevención, adaptación y mitigación del cambio climático;\nIII. Celebrar con el Estado, con otros Municipios de la Entidad o con los particulares, previstos en la Estrategia Estatal;\nIV. Promover la participación de la sociedad para el cumplimiento de los objetivos de esta Ley, mediante acciones de sensibilización y corresponsabilidad ciudadana en materia de prevención, adaptación y mitigación del cambio climático;\nLey de Prevención, Mitigación y Adaptación del Página 9\n.\nActualización Legislativa.\nÚltima Reforma P.O. No. 40, Índice, 16/Ago/2024\nV. Difundir permanentemente la aplicación de los planes o programas de desarrollo urbano municipal, donde se prevenga la exposición de los pobladores a riesgos ambientales;\nVI. Promover que los concesionarios y permisionarios de transporte público y privado de pasajeros o de carga, en el reemplazo de sus unidades, adquieran vehículos híbridos, eléctricos o que usen gas biocombustibles, para disminuir los Gases de Efecto Invernadero;\nFracción Adicionada recorriéndose la subsecuente\nVII. Las demás que les señalen esta Ley y otras disposiciones jurídicas aplicables.\nArtículo Reformado\nArtículo 19. Para la prevención, mitigación y adaptación de los efectos del cambio climático, la Secretaría, propondrá la política estatal y municipal de cambio climático así como la Estrategia Estatal al Consejo, que estará facultado para:\nI. Promover la orientación del Plan Estatal de Desarrollo con visión integral y sustentable en cumplimiento de la presente Ley;\nII. Coordinarse con el Comité Estatal de Planeación del Desarrollo Integral\nSustentable, en la integración anual del presupuesto de egresos, en lo concerniente a su objeto;\nIII. Coordinar entre las distintas dependencias y entidades estatales la instrumentación de medidas de prevención y control de emergencias y contingencias causadas por los efectos adversos del cambio climático;\nIV. Formular y adoptar políticas, estrategias y acciones necesarias para el cumplimiento de sus fines;\nV. Diseñar e implementar un Programa de Modelación del Clima y un Sistema de\nInformación Climática;\nVI. Incorporar en los instrumentos de la política ambiental, como el ordenamiento ecológico y la evaluación del impacto ambiental, los criterios de mitigación y adaptación ante los impactos adversos previsibles del cambio climático;\nVII. Realizar la valoración económica de los costos asociados al cambio climático y los beneficios derivados de las acciones para enfrentarlo;\nVIII. Generar capacidades para contabilizar las emisiones de gases de efecto invernadero y plantear planes de reducción de los mismos;\nIX. Identificar oportunidades, evaluar y, en su caso, aprobar proyectos de reducción de emisiones y captura de gases de efecto invernadero en el Estado, en términos del\nProtocolo de Kyoto, así como de otros instrumentos tendientes al mismo objetivo;\nX. Impulsar el desarrollo de proyectos de investigación de interés estatal, en relación con el cambio climático;\nLey de Prevención, Mitigación y Adaptación del Página 10\n.\nActualización Legislativa.\nÚltima Reforma P.O. No. 40, Índice, 16/Ago/2024\nXI. Promover el desarrollo y registro de proyectos de reducción y de captura de emisiones de gases de efecto invernadero, en términos de las disposiciones jurídicas aplicables; y\nXII. Las demás que le confieran las disposiciones legales y reglamentarias aplicables.\nArtículo Reformado\nArtículo 20. La Secretaría coordinará las acciones de las dependencias y entidades de la Administración Pública Estatal, relativas a la formulación e instrumentación de las políticas estatales para la mitigación de emisiones de gases de efecto invernadero, y la adaptación a los efectos del cambio climático.\nArtículo 21. La Secretaría será responsable de elaborar y publicar un reporte anual sobre los niveles de emisiones de los gases de efecto invernadero en el Estado, así como de las acciones realizadas en el año por el gobierno estatal en materia de prevención, adaptación y mitigación del cambio climático.\nArtículo 22. La Secretaría apoyará y asesorará a los Municipios que lo soliciten, en la formulación, ejecución y operación de sus programas de atención al cambio climático.\nArtículo 23. La Secretaría será responsable de administrar la información de los programas de monitoreo de la calidad del aire, agua y suelo, proporcionada por los organismos competentes, cuando corresponda.\nArtículo 24. La Secretaría será la encargada de crear y presidir comités y subcomités operativos formados por representantes de las dependencias, servicios y demás organismos competentes, para el estudio, consulta, análisis, comunicación y coordinación en materia de cambio climático.\nCAPÍTULO V\nDE LOS INSTRUMENTOS DE LA ESTRATEGIA ESTATAL\nArtículo 25. Para el ejercicio de las atribuciones previstas en el Plan Estatal de\nDesarrollo y los programas sectoriales, se fijarán objetivos, metas, prioridades, asignación de recursos, responsabilidades y tiempos de ejecución sobre las acciones de adaptación al cambio climático y mitigación de sus efectos, basándose en la Estrategia Estatal.\nArtículo 26. Los objetivos, metas y prioridades para fomentar, promover, regular, restringir, orientar, prohibir y, en general, para inducir las acciones para la adaptación al cambio climático y la mitigación de sus efectos estarán contenidas en la Estrategia Estatal.\nArtículo 27. La Estrategia Estatal es el instrumento rector de la política estatal y municipal de cambio climático, que precisará las posibilidades e intervalos de reducción de emisores de gases de efecto invernadero, los estudios necesarios para definir metas de mitigación y las necesidades del Estado para construir capacidades de adaptación. Su actualización es responsabilidad de las autoridades señaladas por esta Ley.\nArtículo Reformado\nLey de Prevención, Mitigación y Adaptación del Página 11\n.\nActualización Legislativa.\nÚltima Reforma P.O. No. 40, Índice, 16/Ago/2024\nArtículo 28. El Ejecutivo del Estado se coordinará con los Municipios, con pleno respeto a las atribuciones constitucionales de éstos, para que los programas estatales de acción ante el cambio climático fijen objetivos, metas, estrategias, prioridades, responsabilidades y tiempos de ejecución comunes sobre las acciones de adaptación al cambio climático y mitigación de sus efectos, en concordancia con la Estrategia Estatal.\nCAPÍTULO VI\nREGISTRO ESTATAL DE EMISIONES\nArtículo 29. Corresponderá a la Secretaría el funcionamiento del Registro Estatal de\nEmisiones.\nArtículo 30. La Secretaría establecerá las metodologías y procedimientos para calcular, validar y certificar las emisiones, las reducciones o capturas de gases efecto invernadero de proyectos o fuentes emisoras inscritas en el Registro Estatal de Emisiones.\nArtículo 31. Los reportes de emisiones y proyectos de reducción de emisiones del\nRegistro, deberán de estar certificados y validados por organismos autorizados por la\nSecretaría.\nArtículo 32. El Registro Estatal de Emisiones operará con independencia de otros registros internacionales o nacionales con objetivos similares, buscando la compatibilidad del mismo con metodologías y criterios internacionales, y en su caso, utilizando los adoptados por la Convención Marco y su Protocolo de Kyoto.\nArtículo 33. La información del Registro Estatal de Emisiones será pública y podrá ser consultada y actualizada a través del portal de la Secretaria.\nArtículo 34. Para el correcto funcionamiento y seguimiento del Sistema de Emisiones de Carbono, el Consejo establecerá un sistema de auditoría al Registro Estatal de Emisiones y podrá emitir recomendaciones o solicitudes expresas a las metodologías usadas y procedimientos del Registro.\nCAPÍTULO VII\nDE LA OBLIGACIÓN DE REPORTAR EMISIONES\nArtículo 35. Las fuentes emisoras ubicadas en el Estado, públicas y privadas, están obligadas a reportar sus emisiones a la Secretaría, de acuerdo a las disposiciones de esta\nLey y demás ordenamientos que de ella se deriven.\nCuando se trate de fuentes emisoras de competencia federal, el reporte se solicitará a través de la autoridad competente.\nCAPÍTULO VIII\nDE LA ADAPTACIÓN\nLey de Prevención, Mitigación y Adaptación del Página 12\n.\nActualización Legislativa.\nÚltima Reforma P.O. No. 40, Índice, 16/Ago/2024\nArtículo 36. Para enfrentar los retos de la adaptación, se observarán los siguientes criterios:\nI. Corregir o aminorar los desequilibrios generados por el cambio climático, que deterioren la calidad de vida de la población o que tengan un impacto negativo en el desarrollo de los ecosistemas;\nII. Considerar los escenarios actuales y futuros de cambio climático en la planeación territorial, evitando los impactos negativos en la calidad de vida de la población, la infraestructura, las diferentes actividades productivas y de servicios, los asentamientos humanos y los recursos naturales;\nFracción Reformada\nIII. Establecer y considerar umbrales de riesgo aceptable, derivados de la variabilidad climática actual y esperada, en los instrumentos de planeación territorial, para garantizar la seguridad alimentaria, la protección civil, la conservación de la biodiversidad y la productividad;\nFracción Reformada\nIV.- Fomentar la investigación y el estudio en materia de adaptación en la Entidad; y,\nFracción Adicionada\nV.- Prevenir riesgos en materia de salud asociados con el cambio climático.\nFracción Adicionada\nArtículo Reformado\nArtículo 37. Los criterios para la adaptación al cambio climático se considerarán en:\nI. El establecimiento de usos, reservas y destinos de los planes de desarrollo urbano;\nII. El establecimiento de centros de población o asentamientos humanos, así como en las acciones de mejoramiento y conservación de los mismos;\nIII. El manejo, protección, conservación y restauración de los ecosistemas, recursos forestales y suelos;\nIV. El establecimiento de los ordenamientos ecológicos territoriales;\nV. La protección, el aprovechamiento sustentable o rehabilitación de playas, costas, terrenos ganados al mar y cualquier otro depósito que se forme con aguas marítimas, para uso turístico, industrial, agrícola, acuícola o de conservación;\nVI. La construcción de infraestructura y la protección de zonas inundables y zonas áridas;\nVII. El establecimiento y conservación de los espacios y áreas naturales protegidas;\nVIII. La complementación del Atlas Estatal de Riesgos;\nIX. La elaboración y aplicación de las reglas de operación de programas de subsidio y proyectos de inversión;\nLey de Prevención, Mitigación y Adaptación del Página 13\n.\nActualización Legislativa.\nÚltima Reforma P.O. No. 40, Índice, 16/Ago/2024\nX. Los programas de conservación y aprovechamiento sustentable de la biodiversidad;\nXI. Los programas de protección civil;\nXII. Los programas en materia de asentamientos humanos y desarrollo urbano;\nXIII. Los programas de desarrollo turístico;\nXIV. Los programas de salud; y\nXV. El otorgamiento de licencias y permisos en materia de evaluación de impacto ambiental, aprovechamiento de recursos naturales, así como autorizaciones en materia de cambio de uso del suelo.\nArtículo 38. Las dependencias y entidades de la Administración Pública Estatal, los\nMunicipios y la sociedad en general llevarán a cabo las políticas y acciones de la Estrategia\nEstatal, atendiendo de manera prioritaria lo siguiente:\nI. La protección de la vida humana y la infraestructura;\nII. La prevención y atención a riesgos climáticos;\nIII. El reforzamiento de los programas de prevención y vigilancia epidemiológica;\nIV. El impulso y el aprovechamiento sustentable de las fuentes superficiales y subterráneas de agua, promoviendo entre otras acciones la tecnificación de la superficie de riego, la producción bajo condiciones de prácticas de agricultura sustentable o agricultura protegida cuando sea viable y prácticas sustentables de ganadería, silvicultura, pesca y acuacultura;\nV. La identificación de medidas de gestión para la adaptación de especies prioritarias, indicadoras y particularmente vulnerables al cambio climático;\nVI. La elaboración de diagnósticos de la vulnerabilidad ante los cambios climáticos esperados;\nVII. El intercambio y migración de las especies de flora y fauna silvestres, terrestres o acuáticas dentro de un mismo ecosistema o entre éstos; y\nVIII. La implementación de un sistema tarifario por el uso de agua, que incorpore el pago por los servicios ambientales hidrológicos de los ecosistemas, a fin de destinar su producto a la conservación de los mismos; y\nIX. Identificación e implementación de medidas de manejo y gestión que favorezcan la migración, intercambio genético y la adaptación natural de la biodiversidad, especies de flora y fauna prioritarias, indicadoras y particularmente vulnerables al cambio climático, a través del mantenimiento e incremento de la cobertura vegetal nativa terrestre, acuática y riparia del Estado, promoviendo la conectividad entre los ecosistemas.\nArtículo Reformado\nCAPÍTULO IX\nDE LA MITIGACIÓN\nLey de Prevención, Mitigación y Adaptación del Página 14\n.\nActualización Legislativa.\nÚltima Reforma P.O. No. 40, Índice, 16/Ago/2024\nArtículo 39. Para la mitigación de los efectos nocivos del cambio climático, la prevención y el control de la contaminación de la atmósfera por gases de efecto invernadero y de otras partículas con las mismas consecuencias, se observarán los lineamientos siguientes:\nI. En todos los asentamientos humanos, la calidad del aire será de acuerdo a las normas oficiales;\nII. Se promoverán patrones de producción y consumo que disminuyan las emisiones;\nIII. Se apoyará e impulsará a las empresas de los sectores social y privado para que reduzcan sus emisiones;\nIV. Se promoverán prácticas de eficiencia energética, la sustitución del uso de combustibles fósiles por fuentes renovables de energía y la transferencia e innovación de tecnologías limpias;\nV. Se reforzarán los programas para evitar la deforestación y degradación de los ecosistemas naturales; y\nVI. Se monitoreará, verificará e informará de las acciones de mitigación emprendidas.\nCAPÍTULO X\nFONDO PARA EL CAMBIO CLIMÁTICO\nArtículo 40. De conformidad con las disponibilidades presupuestales, el Estado y sus\nMunicipios podrán crear Fondos para el Cambio Climático, con el objeto de captar y canalizar recursos económicos para acciones de prevención, mitigación y adaptación al cambio climático. El Fondo dará prioridad a los proyectos y acciones relacionadas con adaptación.\nArtículo 41. El Fondo es el agente financiero del Orden de Gobierno Estatal o\nMunicipal respectivo, para la contratación de recursos provenientes de organismos financieros estatales, en su caso, nacionales e internacionales, a fin de financiar proyectos de cambio climático.\nArtículo 42. El patrimonio del Fondo se constituirá por:\nII. Los recursos que anualmente señale el Presupuesto de Egresos del Estado y\nMunicipios;\nIII. Las contribuciones por emisiones de gases de efecto invernadero, así como sanciones por exceder los permisos de emisión autorizados que se desprendan de esta Ley;\nIV. Las aportaciones que efectúen los sectores público, privado y social;\nV. Las donaciones de personas físicas o morales, mismas que serán deducibles de impuestos, en términos de Ley;\nLey de Prevención, Mitigación y Adaptación del Página 15\n.\nActualización Legislativa.\nÚltima Reforma P.O. No. 40, Índice, 16/Ago/2024\nVI. Las aportaciones que en su caso efectúen gobiernos de otros países u organismos internacionales; y\nVII. Las sanciones pecuniarias administrativas que se apliquen con motivo de esta\nLey.\nArtículo 43. Los recursos del Fondo se destinarán a:\nI. Desarrollo e implementación de proyectos de mitigación de gases de efecto invernadero y de adaptación conforme a las prioridades de los planes y programas;\nII. Programas, planes y acciones para reducir la vulnerabilidad frente al cambio climático en materia de atención y protección a grupos y zonas vulnerables, uso del suelo, infraestructura y otros aspectos que se consideren estratégicos;\nIII. Estudios y evaluaciones en materia de cambio climático que requiera el Sistema\nNacional;\nIV. Proyectos de investigación, de innovación y desarrollo tecnológico en la materia, conforme al establecido en la Estrategia Nacional.\nV. Programas de educación, concientización y difusión de una cultura de mitigación y adaptación; y\nVI. Otros proyectos y acciones en concordancia a las metas establecidas en los planes y programas, así como las definidas en las reglas de operación del Fondo.\nArtículo 44. El Fondo podrá complementar o transferir recursos, a otros fondos con objetivos concurrentes, previo acuerdo del Consejo.\nArtículo 45. El Fondo contará con un Comité Técnico presidido por un representante de la Secretaría de Planeación y Finanzas, e integrado por representantes de las\nSecretarías de Protección al Ambiente; Desarrollo Social; Energía; Desarrollo Económico;\nFomento Agropecuario; Secretaria General de Gobierno y Turismo.\nArtículo 46. El Comité Técnico aprobará las operaciones que se realicen con cargo al\nFondo, en los términos de esta Ley, de las reglas de operación y del contrato de fideicomiso respectivos.\nArtículo 47. El Fondo se sujetará a los mecanismos de control, auditoría, evaluación\nConsejo, asimismo aprobará en su caso las reglas de operación del Fondo.\nCAPÍTULO XI\nDE LAS RESPONSABILIDADES Y SANCIONES\nArtículo 48. La Secretaría será el órgano competente para realizar actos de fiscalización, inspección y vigilancia en las fuentes emisoras sujetas a reporte, para verificar\nLey de Prevención, Mitigación y Adaptación del Página 16\n.\nActualización Legislativa.\nÚltima Reforma P.O. No. 40, Índice, 16/Ago/2024 la información proporcionada, así como su entrega en tiempo y forma, de acuerdo con las disposiciones reglamentarias que de esta Ley se deriven.\nArtículo 49. Cuando del procedimiento de inspección se desprendan infracciones a esta Ley en materia de los reportes de emisiones, la Secretaría procederá conforme a lo establecido en esta Ley y la Ley de Protección al Ambiente para el Estado de Baja\nCalifornia.\nArtículo 50. Las fuentes emisoras que sean sujetas de procedimientos de fiscalización para proporcionar informes, datos o documentos, tendrán la obligación de hacerlo dentro de un plazo no mayor a quince días hábiles, contados a partir del día siguiente al de la fecha de su requerimiento.\nEn caso de no atender lo requerido por la autoridad en el plazo señalado, se harán acreedoras a las sanciones administrativas establecidas en esta Ley y en la Ley de\nProtección al Ambiente para el Estado de Baja California.\nArtículo 51. Los servidores públicos sujetos de esta Ley se harán acreedores a las sanciones administrativas aplicables por las normas y reglamentos vigentes en sus respectivas materias, para el caso de incumplimiento de sus deberes y responsabilidades, y corresponderá la determinación de dichas sanciones a la autoridad o autoridades competentes en los siguientes casos:\nI. Por negligencia, cuando no se registre en tiempo la información proporcionada por las fuentes emisoras sujetas a reporte de emisiones; y\nII. Por negligencia, dolo o mala fe, cuando se altere total o parcialmente la información, se cometan inexactitudes u omisiones en la captura de la información y que por ello se causen daños o perjuicios al interés de terceros.\nArtículo 52. Los servidores públicos a que se refiere el presente capítulo serán responsables del manejo de la información a que tengan acceso con motivo de la operación de los registros y, en su caso, serán sancionados conforme a las disposiciones de la normatividad relativa a la Transparencia y Acceso a la Información Pública.\nArtículo 53. Los servidores públicos encargados de la aplicación y vigilancia del caso de incumplimiento de sus disposiciones, de acuerdo con lo dispuesto en la Ley de\nResponsabilidades de los Servidores Públicos del Estado y demás leyes aplicables, sin perjuicio de la responsabilidad civil y penal a que haya lugar.\nArtículo 54. La inspección y vigilancia se llevará a cabo por personal autorizado, para el Estado de Baja California.\nLey de Prevención, Mitigación y Adaptación del Página 17\n.\nActualización Legislativa.\nÚltima Reforma P.O. No. 40, Índice, 16/Ago/2024\nArtículo 55. Las dependencias y servidores públicos, bajo su más estricta responsabilidad y mediante la presentación de elementos de prueba, podrán denunciar ante el Consejo, conductas que contravengan las disposiciones de la presente Ley.\nEl Consejo, previo análisis de las pruebas presentadas, determinará si la denuncia hecha es procedente, en cuyo caso, informará por escrito a la dependencia u orden de gobierno correspondiente, a la que pertenezca el servidor público de la infracción cometida.\nEl órgano interno de control de la dependencia, o la Contraloría del orden de gobierno correspondiente, será el encargado de determinar e imponer la sanción. Previamente a la imposición de una sanción, se concederá audiencia al servidor público infractor para que alegue lo que a su derecho convenga.\nEn caso de la presunta comisión de delitos, la Comisión dará parte al Ministerio\nPúblico.\nLas sanciones administrativas se impondrán tomando en cuenta la gravedad de la infracción en que se incurra. El Consejo proporcionará los elementos técnicos que permitan determinar la gravedad y consecuencias de la infracción.\nARTÍCULOS TRANSITORIOS\nPRIMERO. La presente Ley entrará en vigor a al día siguiente al de su publicación en el Periódico Oficial del Estado de Baja California.\nSEGUNDO. El Ejecutivo del Estado, en el ámbito de sus atribuciones, expedirá las disposiciones reglamentarias de esta Ley, en un plazo que no excederá de los noventa días naturales siguientes a su publicación en el Periódico Oficial del Estado de Baja California.\nTERCERO. El Consejo deberá integrarse e instalarse dentro de los noventa días naturales de la entrada en vigor del presente Decreto.\nDADO en el Salón de Sesiones “Lic. Benito Juárez García” del H. Poder Legislativo del Estado de Baja California, en la Ciudad de Mexicali, B.C., a los tres días del mes de mayo del año dos mil doce.\nDIP. DAVID JORGE LOZANO PÉREZ\nPRESIDENTE\n(RÚBRICA)\nDIP. ALFONSO GARZÓN ZATARAIN\nSECRETARIO\n(RÚBRICA)\nDE CONFORMIDAD CON LO DISPUESTO POR LA FRACCIÓN I DEL ARTÍCULO 49\nLey de Prevención, Mitigación y Adaptación del Página 18\n.\nActualización Legislativa.\nÚltima Reforma P.O. No. 40, Índice, 16/Ago/2024\nMEXICALI, BAJA CALIFORNIA, A LOS QUINCE DÍAS DEL MES DE MAYO DEL\nAÑO DOS MIL DOCE.\nJOSÉ GUADALUPE OSUNA MILLÁN\nGOBERNADOR DEL ESTADO\n(RÚBRICA)\nCUAUHTÉMOC CARDONA BENAVIDES\nSECRETARIO GENERAL DE GOBIERNO\n(RÚBRICA)\nLey de Prevención, Mitigación y Adaptación del Página 19\n.\nActualización Legislativa.\nÚltima Reforma P.O. No. 40, Índice, 16/Ago/2024\nArtículo 1.- Fue reformado por Decreto No. 459, publicado en el Periódico Oficial No.\n13, Sección IV, Tomo CXXIII, de fecha 11 de marzo de 2016, expedido por la H. XXI\nLegislatura, siendo Gobernador Constitucional el C. Francisco Arturo Vega de Lamadrid\n2013-2019;\nArtículo 2.- Fue reformado por Decreto No. 459, publicado en el Periódico Oficial No.\n13, Sección IV, Tomo CXXIII, de fecha 11 de marzo de 2016, expedido por la H. XXI\nLegislatura, siendo Gobernador Constitucional el C. Francisco Arturo Vega de Lamadrid\n2013-2019; fue reformado mediante Decreto No. 290, publicado en el Periódico Oficial No.\n55, Índice, de fecha 25 de septiembre de 2023, Tomo CXXX, expedido por la H. XXIV\nLegislatura, siendo Gobernadora Constitucional la C. Marina del Pilar Ávila Olmeda 20212027;\nArtículo 8.- Fue reformado por Decreto No. 223, publicado en el Periódico Oficial No.\n15, Sección II, Tomo CXXII, de fecha 27 de marzo de 2015, expedido por la H. XXI\nLegislatura, siendo gobernador constitucional el C. Francisco Arturo Vega de Lamadrid 20132019;\nArtículo 10.- Fue reformado por Decreto No. 223, publicado en el Periódico Oficial No.\n15, Sección II, Tomo CXXII, de fecha 27 de marzo de 2015, expedido por la H. XXI\nLegislatura, siendo gobernador constitucional el C. Francisco Arturo Vega de Lamadrid 20132019;\nCAPÍTULO III\nDE LOS CRITERIOS GENERALES PARA LA DEFINICIÓN DE POLÍTICAS DE\nMITIGACIÓN Y ADAPTACIÓN\nFue modificada la denominación de este Capítulo por Decreto No. 459, publicado en el\nPeriódico Oficial No. 13, Sección IV, Tomo CXXIII, de fecha 11 de marzo de 2016, expedido por la H. XXI Legislatura, siendo Gobernador Constitucional el C. Francisco Arturo Vega de\nLamadrid 2013-2019;\nCAPÍTULO III\nDE LOS CRITERIOS GENERALES PARA LA DEFINICIÓN DE LA POLÍTICA ESTATAL Y\nMUNICIPAL DE CAMBIO CLIMÁTICO\nArtículo 10 BIS.- Fue adicionado por Decreto No. 459, publicado en el Periódico\nXXI Legislatura, siendo Gobernador Constitucional el C. Francisco Arturo Vega de Lamadrid\n2013-2019;\nArtículo 11.- Fue reformado por Decreto No. 459, publicado en el Periódico Oficial No.\nLegislatura, siendo Gobernador Constitucional el C. Francisco Arturo Vega de Lamadrid\n2013-2019;\nLey de Prevención, Mitigación y Adaptación del Página 20\n.\nActualización Legislativa.\nÚltima Reforma P.O. No. 40, Índice, 16/Ago/2024\nArtículo 14.- Fue reformado por Decreto No. 223, publicado en el Periódico Oficial No.\n15, Sección II, Tomo CXXII, de fecha 27 de marzo de 2015, expedido por la H. XXI\nLegislatura, siendo gobernador constitucional el C. Francisco Arturo Vega de Lamadrid 20132019; fue reformado por Decreto No. 459, publicado en el Periódico Oficial No. 13, Sección\nIV, Tomo CXXIII, de fecha 11 de marzo de 2016, expedido por la H. XXI Legislatura, siendo\nGobernador Constitucional el C. Francisco Arturo Vega de Lamadrid 2013-2019;\nArtículo 18.- Fue reformado por Decreto No. 277, publicado en el Periódico Oficial No.\n55, Sección III, Tomo CXXV, de fecha 30 de noviembre de 2018, expedido por la H. XXII\nLegislatura, siendo Gobernador Constitucional el C. Francisco Arturo Vega de Lamadrid\n2013-2019;\nArtículo 19.- Fue reformado por Decreto No. 459, publicado en el Periódico Oficial No.\n13, Sección IV, Tomo CXXIII, de fecha 11 de marzo de 2016, expedido por la H. XXI\nLegislatura, siendo Gobernador Constitucional el C. Francisco Arturo Vega de Lamadrid\n2013-2019;\nArtículo 27.- Fue reformado por Decreto No. 459, publicado en el Periódico Oficial No.\n13, Sección IV, Tomo CXXIII, de fecha 11 de marzo de 2016, expedido por la H. XXI\nLegislatura, siendo Gobernador Constitucional el C. Francisco Arturo Vega de Lamadrid\n2013-2019;\nArtículo 36.- Fue reformado mediante Decreto No. 454, publicado en el Periódico\nLegislatura, siendo Gobernadora Constitucional la C. Marina del Pilar Ávila Olmeda 20212027;\nArtículo 38.- Fue reformado por Decreto No. 458, publicado en el Periódico Oficial\nLegislatura, siendo Gobernador Constitucional el C. Francisco Arturo Vega de Lamadrid\n2013-2019;\nLey de Prevención, Mitigación y Adaptación del Página 21\n.\nActualización Legislativa.\nÚltima Reforma P.O. No. 40, Índice, 16/Ago/2024\nARTÍCULO TERCERO TRANSITORIO DEL DECRETO No. 223, POR EL QUE SE\nREFORMAN LOS ARTÍCULOS 8, 10 Y 14, PUBLICADO EN EL PERIÓDICO OFICIAL No.\n15, SECCIÓN II, TOMO CXXII, DE FECHA 27 DE MARZO DE 2015, EXPEDIDO POR LA H.\nXXI LEGISLATURA, SIENDO GOBERNADOR CONSTITUCIONAL EL C. FRANCISCO\nARTURO VEGA DE LAMADRID 2013-2019;\nARTÍCULO TRANSITORIO\nÚNICO.- El presente Decreto entrará en vigor al día siguiente de su publicación en el\nPeriódico Oficial del Estado.\nDADO en el Salón de Sesiones “Lic. Benito Juárez García” del H. Poder Legislativo del Estado de Baja California, en la Ciudad de Mexicali, B.C., a los veintiséis días del mes de febrero del año dos mil quince.\nDIP. FCO. ALCIBIADES GARCÍA LIZARDÍ\nPRESIDENTE\n(RÚBRICA)\nDIP. ROSALBA LÓPEZ REGALADO\nSECRETARIO\n(RÚBRICA)\nDE CONFORMIDAD CON LO DISPUESTO POR LA FRACCION I DEL ARTÍCULO 49\nMEXICALI, BAJA CALIFORNIA, A LOS SEIS DÍAS DEL MES DE MARZO DEL AÑO\nDOS MIL QUINCE.\nFRANCISCO ARTURO VEGA DE LAMADRID\nGOBERNADOR DEL ESTADO\n(RÚBRICA)\nFRANCISCO RUEDA\nSECRETARIO GENERAL DE GOBIERNO\n(RUBRICA)\nARTÍCULO SEGUNDO TRANSITORIO DEL DECRETO No. 458, POR EL QUE SE\nREFORMA EL ARTÍCULO 38; PUBLICADO EN EL PERIÓDICO OFICIAL No. 14, SECCIÓN\nLEGISLATURA, SIENDO GOBERNADOR CONSTITUCIONAL EL C. FRANCISCO ARTURO\nVEGA DE LAMADRID 2013-2019.\nARTÍCULO TRANSITORIO\nLey de Prevención, Mitigación y Adaptación del Página 22\n.\nActualización Legislativa.\nÚltima Reforma P.O. No. 40, Índice, 16/Ago/2024\nÚNICO: La presente reforma al artículo 38 de la Ley de Prevención, Mitigación y\nAdaptación del Cambio Climático para el Estado de Baja California, entrará en vigor al día siguiente al de su publicación en el Periódico Oficial del Estado.\nDADO en el Salón de Sesiones “Lic. Benito Juárez García” del H. Poder Legislativo del Estado de Baja California, en la Ciudad de Mexicali, B.C., a los veinticinco días del mes de febrero del año dos mil dieciséis.\nDIP. RODOLFO OLIMPO HERNÁNDEZ BOJÓRQUEZ\nPRESIDENTE\n(RUBRICA)\nDIP. ARMANDO REYES LEDESMA\nSECRETARIO\n(RUBRICA)\nDE CONFORMIDAD CON LO DISPUESTO POR LA FRACCION I DEL ARTÍCULO 49\nMEXICALI, BAJA CALIFORNIA, A LOS NUEVE DÍAS DEL MES DE MARZO DEL AÑO DOS\nMIL DIECISÉIS.\nFRANCISCO ARTURO VEGA DE LAMADRID\nGOBERNADOR DEL ESTADO\n(RÚBRICA)\nFRANCISCO RUEDA GOMEZ\nSECRETARIO GENERAL DE GOBIERNO\n(RÚBRICA)\nARTÍCULO UNICO TRANSITORIO DEL DECRETO No. 459, POR EL QUE SE\nREFORMAN LOS ARTÍCULOS 1, 2 FRACCIÓN I, LA DENOMINACIÓN DEL CAPÍTULO III\nY LA CREACIÓN DE UN ARTÍCULO 10 BIS, LOS ARTÍCULOS 11, 14, 19, Y 27;\nPUBLICADO EN EL PERIÓDICO OFICIAL No. 13, SECCION IV, TOMO CXXIII, DE FECHA\n11 DE MARZO DE 2016, EXPEDIDO POR LA H. XXI LEGISLATURA, SIENDO\nGOBERNADOR CONSTITUCIONAL EL C. FRANCISCO ARTURO VEGA DE LAMADRID\n2013-2019.\nARTÍCULOS TRANSITORIOS\nÚNICO: El presente Decreto entrará en vigor al día siguiente de su publicación en el\nPeriódico Oficial del Estado de Baja California. del Estado de Baja California, en la Ciudad de Mexicali, B.C., a los veinticinco días del mes de febrero del año dos mil dieciséis.\nLey de Prevención, Mitigación y Adaptación del Página 23\n.\nActualización Legislativa.\nÚltima Reforma P.O. No. 40, Índice, 16/Ago/2024\nDIP. RODOLFO OLIMPO HERNÁNDEZ BOJÓRQUEZ\nPRESIDENTE\n(RUBRICA)\nDIP. ARMANDO REYES LEDESMA\nSECRETARIO\n(RUBRICA)\nDE CONFORMIDAD CON LO DISPUESTO POR LA FRACCION I DEL ARTÍCULO 49\nMEXICALI, BAJA CALIFORNIA, A LOS NUEVE DÍAS DEL MES DE MARZO DEL AÑO DOS\nMIL DIECISÉIS.\nFRANCISCO ARTURO VEGA DE LAMADRID\nGOBERNADOR DEL ESTADO\n(RÚBRICA)\nFRANCISCO RUEDA GOMEZ\nSECRETARIO GENERAL DE GOBIERNO\n(RÚBRICA)\nARTÍCULO ÚNICO TRANSITORIO DEL DECRETO No. 277, POR EL QUE SE\nREFORMA EL ARTÍCULO 18; PUBLICADO EN EL PERIÓDICO OFICIAL No. 55, SECCIÓN\nIII, TOMO CXXV, DE FECHA 30 DE NOVIEMBRE DE 2018, EXPEDIDO POR LA H. XXII\nLEGISLATURA, SIENDO GOBERNADOR CONSTITUCIONAL EL C. FRANCISCO ARTURO\nVEGA DE LAMADRID 2013-2019.\nARTÍCULOS TRANSITORIOS\nÚNICO: El presente Decreto entrará en vigor al día siguiente de su publicación en el\nPeriódico Oficial del Estado de Baja California.\nDADO en el Salón de Sesiones “Lic. Benito Juárez García” del H. Poder Legislativo del Estado de Baja California, en la Ciudad de Mexicali, B.C., a los veinticinco días del mes de octubre del año dos mil dieciocho.\nDIP. ROCÍO LÓPEZ GOROSAVE\nPRESIDENTA\n(RÚBRICA)\nDIP. MÒNICA HERNÁNDEZ ÁLVAREZ\nSECRETARIA\n(RÚBRICA)\nLey de Prevención, Mitigación y Adaptación del Página 24\n.\nActualización Legislativa.\nÚltima Reforma P.O. No. 40, Índice, 16/Ago/2024\nDE CONFORMIDAD CON LO DISPUESTO POR LA FRACCION I DEL ARTÍCULO 49\nMEXICALI, BAJA CALIFORNIA, A LOS TREINTA DÍAS DEL MES DE NOVIEMBRE DEL\nAÑO DOS MIL DIECIOCHO.\nFRANCISCO ARTURO VEGA DE LAMADRID\nGOBERNADOR DEL ESTADO\n(RÚBRICA)\nFRANCISCO RUEDA GÓMEZ\nSECRETARIO GENERAL DE GOBIERNO\n(RÚBRICA)\nARTÍCULO ÚNICO TRANSITORIO DEL DECRETO No. 290, POR EL QUE SE\nAPRUEBA LA ADICIÓN DE LA FRACCIÓN X AL ARTÍCULO 2; PUBLICADO EN EL\nPERIÓDICO OFICIAL No. 55, ÍNDICE, DE FECHA 25 DE SEPTIEMBRE DE 2023, TOMO\nCXXX, EXPEDIDO POR LA H. XXIV LEGISLATURA, SIENDO GOBERNADORA\nCONSTITUCIONAL LA C. MARINA DEL PILAR ÁVILA OLMEDA 2021 – 2027.\nTRANSITORIOS\nÚNICO.- EI presente Decreto entrará en vigor al día siguiente de su publicación en el\nPeriódico Oficial del Estado de Baja California.\nDADO en Sesión Ordinaria de la XXIV Legislatura en la Ciudad de Mexicali, B.C., a los siete días del mes de septiembre del año dos mil veintitrés.\nDIP. MANUEL GUERRERO LUNA\nPRESIDENTE\n(RÚBRICA)\nDIP. DUNNIA MONTSERRAT MURILLO LÓPEZ\nSECRETARIA\n(RÚBRICA)\nDE CONFORMIDAD CON LO DISPUESTO POR LA FRACCION I DEL ARTÍCULO 49\nCALIFORNIA, IMPRÍMASE Y PUBLÍQUESE.\nMEXICALI, BAJA CALIFORNIA, A LOS ONCE DÍAS DEL MES DE SEPTIEMBRE\nDEL AÑO DOS MIL VEINTITRÉS.\nLey de Prevención, Mitigación y Adaptación del Página 25\n.\nActualización Legislativa.\nÚltima Reforma P.O. No. 40, Índice, 16/Ago/2024\nMARINA DEL PILAR ÁVILA OLMEDA\nGOBERNADORA DEL ESTADO\nDE BAJA CALIFORNIA\n(RÚBRICA)\nCATALINO ZAVALA MÁRQUEZ\nSECRETARIO GENERAL DE GOBIERNO\nDEL ESTADO DE BAJA CALIFORNIA\n(RÚBRICA)\nARTÍCULO ÚNICO TRANSITORIO DEL DECRETO No. 454, POR EL QUE SE\nAPRUEBA LA REFORMA AL ARTÍCULO 36; PUBLICADO EN EL PERIÓDICO OFICIAL No.\n40, ÍNDICE, DE FECHA 16 DE AGOSTO DE 2024, TOMO CXXXI, EXPEDIDO POR LA H.\nXXIV LEGISLATURA, SIENDO GOBERNADORA CONSTITUCIONAL LA C. MARINA DEL\nPILAR ÁVILA OLMEDA 2021-2027.\nARTÍCULO TRANSITORIO\nÚNICO.- La presente reforma de Ley entrará en vigor al día siguiente de su publicación en el periódico oficial del Estado de Baja California.\nDADO en Sesión Ordinaria de la XXIV Legislatura en la Ciudad de Mexicali, B.C., a los veinticinco días del mes de julio del año dos mil veinticuatro.\nDIP. RAMÓN VÁZQUEZ VALADEZ\nPRESIDENTE\n(RÚBRICA)\nDIP. MANUEL GUERRERO LUNA\nSECRETARIO\n(RÚBRICA)\nDE CONFORMIDAD CON LO DISPUESTO POR LA FRACCIÓN I DEL ARTÍCULO 49\nCALIFORNIA, IMPRÍMASE Y PUBLÍQUESE.\nMEXICALI, BAJA CALIFORNIA, AL DÍA PRIMERO DEL MES DE AGOSTO DEL AÑO\nDOS MIL VEINTICUATRO.\nMARINA DEL PILAR ÁVILA OLMEDA\nGOBERNADORA DEL ESTADO\nDE BAJA CALIFORNIA\n(RÚBRICA)\nLey de Prevención, Mitigación y Adaptación del Página 26\n.\nActualización Legislativa.\nALFREDO ÁLVAREZ CÁRDENAS\nSECRETARIO GENERAL DE GOBIERNO\nDEL ESTADO DE BAJA CALIFORNIA\n(RÚBRICA)\nLey de Prevención, Mitigación y Adaptación del Página 27",
  "ordenamiento": "REGLAMENTO",
  "jurisdiccion": "BAJA CALIFORNIA",
  "fuente_oficial": "Periódico Oficial",
  "FECHA PER OFIC": "2024/08/16",
  "ESTATUS": "VIGENTE",
  "TOMO": "TOMO_VII",
  "URL": "https://www.congresobc.gob.mx/Documentos/ProcesoParlamentario/Leyes/TOMO_VII/20240816_LEYCAMCLIM.PDF",
  "es_escaneado": false,
  "tiene_tablas": false,
  "materia": [
    "ambiental",
    "urbanismo",
    "infraestructura"
  ]
}