{
  "titulo": "Ley DE RESPONSABILIDADES ADMINISTRATIVAS DEL ESTADO DE BAJA CALIFORNIA",
  "Contenido": "LEY DE RESPONSABILIDADES ADMINISTRATIVAS\nDEL ESTADO DE BAJA CALIFORNIA\nPublicado en el Periódico Oficial No. 36,\nLIBRO PRIMERO\nDISPOSICIONES SUSTANTIVAS\nTÍTULO PRIMERO\nCapítulo I\nObjeto, ámbito de aplicación y sujetos de la ley\nArtículo 1. La presente Ley es de orden público y de observancia general en el\nEstado de Baja California, y tiene por objeto reglamentar el Título Octavo de la Constitución establecer las responsabilidades administrativas de los Servidores Públicos, sus obligaciones, las sanciones aplicables por los actos u omisiones en que estos incurran y las que correspondan a los particulares vinculados con faltas administrativas graves, así como los procedimientos para su aplicación.\nArtículo 2. Son objeto de la presente Ley:\nI. Establecer los principios y obligaciones que rigen la actuación de los\nServidores Públicos;\nII. Establecer las faltas administrativas graves y no graves de los Servidores\nPúblicos, las sanciones aplicables a las mismas, así como los procedimientos para su aplicación y las facultades de las autoridades competentes para tal efecto;\nIII. Establecer las sanciones por la comisión de faltas de particulares, así como los efecto;\nIV. Determinar los mecanismos para la prevención, corrección e investigación de responsabilidades administrativas, y\nV. Crear las bases para que todo Ente Público establezca políticas eficaces de ética pública y responsabilidad en el servicio público.\nArtículo 3. Para efectos de esta Ley se entenderá por:\nI. Auditoría Superior: La Auditoría Superior del Estado;\nLey de Responsabilidades Administrativas del Estado de Baja California. Página 1\nII. Autoridad investigadora: La Secretaria de la Contraloría y Transparencia\nGubernamental del Estado, los Órganos internos de control, la Auditoría Superior del Estado y las Sindicaturas Municipales, así como las unidades de responsabilidades de las que deriven de una ley Estatal que apliquen, administren, reciban, manejen o ejecuten fondos públicos, encargadas de la investigación de Faltas administrativas;\nIII. Autoridad substanciadora: La Secretaria de la Contraloría y Transparencia\nGubernamental del Estado, los Órganos internos de control, la Auditoría Superior y las\nSindicaturas Municipales, así como las unidades de responsabilidades que, en el ámbito de su competencia, dirigen y conducen el procedimiento de responsabilidades administrativas desde la admisión del Informe de presunta responsabilidad administrativa y hasta la conclusión de la audiencia inicial. La función de la Autoridad substanciadora, en ningún caso podrá ser ejercida por una Autoridad investigadora;\nIV. Autoridad resolutora: Tratándose de Faltas administrativas no graves lo será la unidad de responsabilidades administrativas o el servidor público asignado en los Órganos internos de control. Para las Faltas administrativas graves, así como para las Faltas de particulares, lo será la Sala Especializada en materia de Responsabilidades Administrativas y Combate a la Corrupción del Tribunal Estatal de Justicia Administrativa;\nV. Comité Coordinador: La instancia a la que hace referencia el artículo 95 de la coordinación y eficacia del Sistema Estatal;\nVI. Conflicto de Interés: La posible afectación del desempeño imparcial y objetivo de las funciones de los Servidores Públicos en razón de intereses personales, familiares o de negocios;\nCalifornia;\nVIII. Declarante: El Servidor Público obligado a presentar declaración de situación patrimonial, de intereses y fiscal, en los términos de esta Ley;\nIX. Denunciante: La persona física o moral, o el Servidor Público que acude ante las Autoridades investigadoras a que se refiere la presente Ley, con el fin de denunciar actos u omisiones que pudieran constituir o vincularse con Faltas administrativas, en términos de los artículos 91 y 93 de esta Ley;\nX. Ente público: Los Poderes Legislativo y Judicial, los organismos constitucionales autónomos, así como aquellos que las leyes del Estado les confieren autonomía, las dependencias y entidades de la Administración Pública Estatal; los\nLey de Responsabilidades Administrativas del Estado de Baja California. Página 2 municipios y sus dependencias y entidades; la Procuraduría General de Justicia del Estado y las fiscalías; los órganos jurisdiccionales que no formen parte de los poderes judiciales; las empresas productivas del Estado, incluyendo aquellas que deriven de una ley Estatal que apliquen, administren, reciban, manejen o ejecuten fondos públicos, así como cualquier otro de los tres órdenes de gobierno;\nXI. Entidades: Los organismos públicos descentralizados, las empresas de participación estatal mayoritaria y los fideicomisos públicos que tengan el carácter de entidad paraestatal a que se refieren la Ley Orgánica de la Administración Pública del Estado de\nBaja California, la Ley de las Entidades Paraestatales del Estado de Baja California y demás aplicables;\nXII. Auditoría Superior del Estado: El órgano a que hace referencia el Título\nXIII. Expediente de presunta responsabilidad administrativa: El expediente derivado de la investigación que las Autoridades Investigadoras realizan en sede administrativa, al tener conocimiento de un acto u omisión posiblemente constitutivo de\nFaltas administrativas;\nXIV. Faltas administrativas: Las Faltas administrativas graves, las Faltas administrativas no graves; así como las Faltas de particulares, conforme a lo dispuesto en esta Ley;\nXV. Falta administrativa no grave: Las faltas administrativas de los Servidores\nPúblicos en los términos de la presente Ley, cuya sanción corresponde a las Secretarías y a los Órganos internos de control;\nXVI. Falta administrativa grave: Las faltas administrativas de los Servidores\nPúblicos catalogadas como graves en los términos de la presente Ley, cuya sanción corresponde al Tribunal Estatal de Justicia Administrativa;\nXVII. Faltas de particulares: Los actos de personas físicas o morales privadas que\nTítulo Tercero de esta Ley, cuya sanción corresponde al Tribunal en los términos de la misma;\nXVIII. Informe de Presunta Responsabilidad Administrativa: El instrumento en el faltas señaladas en la presente Ley, exponiendo de forma documentada con las pruebas y fundamentos, los motivos y presunta responsabilidad del Servidor Público o de un particular en la comisión de Faltas administrativas;\nLey de Responsabilidades Administrativas del Estado de Baja California. Página 3\nXIX. Magistrados: Los Titulares integrantes del Pleno del Tribunal Estatal de\nAdministrativas y Combate a la Corrupción, competentes en materia de responsabilidades administrativas;\nXX. Órganos constitucionales autónomos: Organismos a los que la Constitución otorga expresamente autonomía técnica y de gestión, personalidad jurídica y patrimonio propio; incluidos aquellos creados con tal carácter por las leyes del Estado;\nXXI. Órganos internos de control: Las unidades administrativas a cargo de promover, evaluar y fortalecer el buen funcionamiento del control interno en los entes públicos; la Secretaria responsable del control interno de Ejecutivo del Estado, las\nSindicaturas Municipales, así como aquellas otras instancias de los Órganos constitucionales autónomos que, conforme a sus respectivas leyes, sean competentes para aplicar las leyes en materia de responsabilidades de Servidores Públicos; incluyendo aquellas que tengan a su cargo las funciones de Contraloría Interna;\nXXII. Plataforma Digital Estatal: La plataforma a que se refiere la Ley del Sistema\nEstatal Anticorrupción, que contará con los sistemas que establece la referida ley, así como los contenidos previstos en la presente Ley;\nXXIII. Sala Especializada: La Sala Especializada en materia de Responsabilidades\nAdministrativas y Combate a la Corrupción del Tribunal Estatal de Justicia Administrativa;\nXXIV. Secretaría: La Secretaria de la Contraloría y Transparencia Gubernamental del\nEstado;\nXXV. Sindicatura: Las Sindicaturas Municipales correspondientes a los\nAyuntamientos del Estado de Baja California;\nXXVI. Servidores Públicos: cualquier persona que se ubique en alguno de los\nSoberano de Baja California;\nXXVII. Sistema Estatal Anticorrupción: La instancia de coordinación entre las autoridades de competentes en la prevención, detección y sanción de responsabilidades administrativas y hechos de corrupción, así como en la fiscalización y control de recursos públicos; y\nXXVIII. Tribunal: El Tribunal Estatal de Justicia Administrativa.\nArtículo 4. Son sujetos de esta Ley:\nI. Los Servidores Públicos;\nLey de Responsabilidades Administrativas del Estado de Baja California. Página 4\nII. Aquellas personas que habiendo fungido como Servidores Públicos se ubiquen en los supuestos a que se refiere la presente Ley; y\nIII. Los particulares vinculados con faltas administrativas graves.\nArtículo 5. No se considerarán Servidores Públicos los consejeros independientes de cuyas leyes de creación se prevea expresamente, sin perjuicio de las responsabilidades que establecen las leyes que los regulan.\nTampoco tendrán el carácter de Servidores Públicos los consejeros independientes que, en su caso, integren los órganos de gobierno de entidades de la Administración Pública del Estado que realicen actividades comerciales, conforme a lo establecido en la Ley de las\nEntidades Paraestatales del Estado de Baja California, quienes podrán ser contratados como consejeros, siempre y cuando:\nI. No tengan una relación laboral con las entidades;\nII. No tengan un empleo, cargo o comisión en cualquier otro Ente público, ni en entes privados con los que tenga Conflicto de Interés;\nIII. Las demás actividades profesionales que realicen les permitan contar con el tiempo suficiente para desempeñar su encargo como consejero;\nIV. El monto de los honorarios que se cubran por su participación en los órganos de gobierno no sean superiores a los que se paguen en empresas que realicen actividades similares en la República Mexicana; y\nV. Cuenten, al menos, con los mismos deberes de diligencia y lealtad aplicables a los consejeros independientes de las empresas productivas del Estado. En todo caso, serán responsables por los daños y perjuicios que llegaren a causar a la entidad, derivados de los actos, hechos u omisiones en que incurran, incluyendo el incumplimiento a dichos deberes.\nCapítulo II\nArtículo 6. Todos los entes públicos están obligados a crear y mantener condiciones conjunto, y la actuación ética y responsable de cada servidor público.\nArtículo 7. Los Servidores Públicos observarán en el desempeño de su empleo, cargo o comisión, los principios de respeto a la dignidad de las personas, disciplina, legalidad, objetividad, profesionalismo, honradez, lealtad, imparcialidad, integridad, rendición\nLey de Responsabilidades Administrativas del Estado de Baja California. Página 5 de cuentas, eficacia y eficiencia que rigen el servicio público. Para la efectiva aplicación de dichos principios, los Servidores Públicos observarán las siguientes directrices:\nI. Actuar conforme a lo que las leyes, reglamentos y demás disposiciones jurídicas les atribuyen a su empleo, cargo o comisión, por lo que deben conocer y cumplir las disposiciones que regulan el ejercicio de sus funciones, facultades y atribuciones;\nII. Conducirse con rectitud sin utilizar su empleo, cargo o comisión para obtener o pretender obtener algún beneficio, provecho o ventaja personal o a favor de terceros, ni buscar o aceptar compensaciones, prestaciones, dádivas, obsequios o regalos de cualquier persona u organización;\nIII. Satisfacer el interés superior de las necesidades colectivas por encima de intereses particulares, personales o ajenos al interés general y bienestar de la población;\nIV. Dar a las personas en general el mismo trato, por lo que no concederán privilegios o preferencias a organizaciones o personas, ni permitirán que influencias, intereses o prejuicios indebidos afecten su compromiso para tomar decisiones o ejercer sus funciones de manera objetiva;\nV. Actuar conforme a una cultura de servicio orientada al logro de resultados, procurando en todo momento un mejor desempeño de sus funciones a fin de alcanzar las metas institucionales según sus responsabilidades;\nVI. Administrar los recursos públicos que estén bajo su responsabilidad, sujetándose a los principios de eficiencia, eficacia, economía, transparencia y honradez para satisfacer los objetivos a los que estén destinados;\nVII. Promover, respetar, proteger y garantizar los derechos humanos establecidos en la Constitución;\nVIII. Corresponder a la confianza que la sociedad les ha conferido; tendrán una vocación absoluta de servicio a la sociedad, y preservarán el interés superior de las necesidades colectivas por encima de intereses particulares, personales o ajenos al interés general;\nIX. Evitar y dar cuenta de los intereses que puedan entrar en conflicto con el desempeño responsable y objetivo de sus facultades y obligaciones; y\nX. Abstenerse de realizar cualquier trato o promesa privada que comprometa al\nEstado.\nCapítulo III\nLey de Responsabilidades Administrativas del Estado de Baja California. Página 6\nArtículo 8. Las autoridades del Estado y Municipios concurrirán en el cumplimiento del objeto y los objetivos de esta Ley. entre las autoridades competentes.\nArtículo 9. En el ámbito de su competencia, serán autoridades facultadas para aplicar la presente Ley:\nI. La Secretaria de la Contraloría y Transparencia Gubernamental del Estado;\nII. Los Órganos internos de control;\nIII. La Auditoría Superior del Estado;\nIV. El Tribunal Estatal de Justicia Administrativa;\nV. Tratándose de las responsabilidades administrativas de los Servidores Públicos de los poderes judiciales, serán competentes para investigar e imponer las sanciones que correspondan, el Tribunal Superior de Justicia y el Consejo de la Judicatura del Estado, conforme al régimen establecido por la Constitución. Lo anterior, sin perjuicio de las atribuciones de la Auditoría Superior del Estado, en materia de fiscalización sobre el manejo, la custodia y aplicación de recursos públicos;\nVI. Las Sindicaturas Municipales; y\nVII. Las unidades de responsabilidades de las empresas productivas del Estado, de conformidad con las leyes que las regulan. Para tal efecto, contarán exclusivamente con las siguientes atribuciones:\na) Las que esta Ley prevé para las autoridades investigadoras y substanciadoras;\nb) Las necesarias para imponer sanciones por faltas administrativas no graves, y\nc) Las relacionadas con la Plataforma Digital Estatal, en los términos previstos en esta Ley.\nVIII. Las autoridades previstas en este Artículo, en el ámbito de sus competencias, ley;\nArtículo 10. La Secretaría y los órganos internos de control, tendrán a su cargo, en el ámbito de su competencia, la investigación, substanciación y calificación de las faltas administrativas.\nLey de Responsabilidades Administrativas del Estado de Baja California. Página 7 administrativas no graves, la Secretaría, Sindicatura y los órganos internos de control serán competentes para iniciar, substanciar y resolver los procedimientos de responsabilidad administrativa en los términos previstos en esta Ley. existencia de Faltas administrativas, así como la presunta responsabilidad del infractor, deberán elaborar el Informe de Presunta Responsabilidad Administrativa y presentarlo a la\nAutoridad substanciadora para que proceda en los términos previstos en esta Ley.\nAdemás de las atribuciones señaladas con anterioridad, los Órganos internos de control serán competentes para:\nI. Implementar los mecanismos internos que prevengan actos u omisiones que pudieran constituir responsabilidades administrativas, en los términos establecidos por el\nSistema Estatal Anticorrupción;\nII. Revisar el ingreso, egreso, manejo, custodia y aplicación de recursos públicos, según corresponda en el ámbito de su competencia;\nFracción Reformada\nIII. Presentar denuncias por hechos que las leyes señalen como delitos ante la\nFiscalía Especializada en Combate a la Corrupción; y,\nFracción Reformada\nIV. Capacitar anualmente a las personas servidoras públicas de los entes gubernamentales, en materia anticorrupción y de responsabilidades administrativas.\nFracción Adicionada\nArtículo Reformado\nArtículo 11. La Auditoría Superior será competente para investigar y substanciar el procedimiento por las faltas administrativas graves.\nEn caso de que la Auditoría Superior detecte posibles faltas administrativas no graves darán cuenta de ello a los Órganos internos de control, según corresponda, para que continúen la investigación respectiva y promuevan las acciones que procedan.\nEn los casos en que, derivado de sus investigaciones, acontezca la presunta comisión de delitos, presentarán las denuncias correspondientes ante el Ministerio Público competente.\nArtículo 12. El Tribunal, además de las facultades y atribuciones conferidas en su legislación orgánica y demás normatividad aplicable, estará facultado para resolver la particulares, conforme a los procedimientos previstos en esta Ley.\nLey de Responsabilidades Administrativas del Estado de Baja California. Página 8\nArtículo 13. Cuando las Autoridades investigadoras determinen que de los actos u como no graves por el mismo servidor público, por lo que hace a las Faltas administrativas graves substanciarán el procedimiento en los términos previstos en esta Ley, a fin de que sea el Tribunal el que imponga la sanción que corresponda a dicha falta. Si el Tribunal determina que se cometieron tanto faltas administrativas graves, como faltas administrativas no graves, al graduar la sanción que proceda tomará en cuenta la comisión de éstas últimas.\nArtículo 14. Cuando los actos u omisiones de los Servidores Públicos materia de denuncias, queden comprendidos en más de uno de los casos sujetos a sanción y previstos en el artículo 92 de la Constitución, los procedimientos respectivos se desarrollarán en forma autónoma según su naturaleza y por la vía procesal que corresponda, debiendo las autoridades a que alude el artículo 9 de esta Ley turnar las denuncias a quien deba conocer de ellas. No podrán imponerse dos veces por una sola conducta sanciones de la misma naturaleza.\nLa atribución del Tribunal para imponer sanciones a particulares en términos de esta\nLey, no limita las facultades de otras autoridades para imponer sanciones administrativas a particulares, conforme a la legislación aplicable.\nTÍTULO SEGUNDO\nMECANISMOS DE PREVENCIÓN E INSTRUMENTOS DE RENDICIÓN DE CUENTAS\nCapítulo I\nMecanismos Generales de Prevención\nArtículo 15. Para prevenir la comisión de faltas administrativas y hechos de corrupción, la Secretaría y los Órganos internos de control, considerando las funciones que a cada una de ellas les corresponden y previo diagnóstico que al efecto realicen, podrán implementar acciones para orientar el criterio que en situaciones específicas deberán observar los Servidores Públicos en el desempeño de sus empleos, cargos o comisiones, en coordinación con el Sistema Estatal Anticorrupción.\nEn la implementación de las acciones referidas, los Órganos internos de control de la\nSecretaría, en sus respectivos ámbitos de competencia. En los Órganos constitucionales autónomos, los Órganos internos de control respectivos, emitirán los lineamientos señalados. En los Municipios se atenderá a los Lineamientos de la Sindicatura competente.\nArtículo 16. Los Servidores Públicos deberán observar el código de ética que al efecto sea emitido por la Secretaría o los Órganos internos de control, conforme a los lineamientos que emita el Sistema Estatal Anticorrupción, para que en su actuación impere\nLey de Responsabilidades Administrativas del Estado de Baja California. Página 9 desempeño.\nEl código de ética a que se refiere el párrafo anterior, deberá hacerse del conocimiento de los Servidores Públicos de la dependencia o entidad de que se trate, así como garantizar y brindar la máxima publicidad.\nArtículo 17. Los Órganos internos de control deberán evaluar anualmente el resultado de las acciones específicas que hayan implementado conforme a este Capítulo y proponer, en su caso, las modificaciones que resulten procedentes, informando de ello a la\nSecretaría en los términos que ésta establezca.\nArtículo 18. Los Órganos internos de control deberán cumplir las recomendaciones que haga el Comité Coordinador del Sistema Estatal Anticorrupción a las autoridades, con el objeto de adoptar las medidas necesarias para el fortalecimiento institucional en su desempeño y control interno y con ello la prevención de Faltas administrativas y hechos de corrupción. Deberán informar a dicho órgano de la atención que se dé a éstas y, en su caso, sus avances y resultados.\nArtículo 19. Los entes públicos deberán implementar los mecanismos de coordinación que, en términos de la Ley del Sistema Estatal Anticorrupción, determine el\nComité Coordinador del Sistema Estatal Anticorrupción e informar a dicho órgano de los avances y resultados que estos tengan, a través de sus Órganos internos de control.\nArtículo 20. Para la selección de los integrantes de los Órganos internos de control se deberán observar, además de los requisitos establecidos para su nombramiento, un sistema que garantice la igualdad de oportunidades en el acceso a la función pública con base en el mérito y los mecanismos más adecuados y eficientes para su adecuada profesionalización, atrayendo a los mejores candidatos para ocupar los puestos a través de procedimientos transparentes, objetivos y equitativos. Los titulares de los Órganos internos de control de los Órganos constitucionales autónomos, así como de las unidades especializadas que los conformen, serán nombrados en términos de la Constitución y leyes respectivas.\nArtículo 21. La Secretaría y Sindicaturas podrán suscribir convenios de colaboración con las personas físicas o morales que participen en contrataciones públicas, así como con las cámaras empresariales u organizaciones industriales o de comercio, con la finalidad de el desarrollo de una cultura ética en su organización.\nArtículo 22. En el diseño y supervisión de los mecanismos a que se refiere el artículo anterior, se considerarán las mejores prácticas internacionales sobre controles, ética e integridad en los negocios, además de incluir medidas que inhiban la práctica de conductas\nLey de Responsabilidades Administrativas del Estado de Baja California. Página 10 irregulares, que orienten a los socios, directivos y empleados de las empresas sobre el protección a denunciantes.\nArtículo 23. El Comité Coordinador del Sistema Estatal Anticorrupción deberá generación de políticas públicas dirigidas al combate a las distintas conductas que constituyen Faltas administrativas.\nCapítulo II\nDe la integridad de las personas morales\nArtículo 24. Las personas morales serán sancionadas en los términos de esta Ley cuando los actos vinculados con faltas administrativas graves sean realizados por personas físicas que actúen a su nombre o representación de la persona moral y pretendan obtener mediante tales conductas beneficios para dicha persona moral.\nArtículo 25. En la determinación de la responsabilidad de las personas morales a que se refiere la presente Ley, se valorará si cuentan con una política de integridad. Para los efectos de esta Ley, se considerará una política de integridad aquella que cuenta con, al menos, los siguientes elementos:\nI. Un manual de organización y procedimientos que sea claro y completo, en el que se delimiten las funciones y responsabilidades de cada una de sus áreas, y que especifique claramente las distintas cadenas de mando y de liderazgo en toda la estructura, incluyendo a su vez el control interno de sus operaciones y su correspondiente registro contable;\nII. Un código de conducta debidamente publicado y socializado entre todos los miembros de la organización, que cuente con sistemas y mecanismos de aplicación real;\nIII. Sistemas adecuados y eficaces de control, vigilancia y auditoría, que examinen de manera constante y periódica el cumplimiento de los estándares de integridad en toda la organización;\nIV. Sistemas adecuados de denuncia, tanto al interior de la organización como hacia las autoridades competentes, así como procesos disciplinarios y consecuencias legislación mexicana;\nV. Sistemas y procesos adecuados de entrenamiento y capacitación respecto de las medidas de integridad que contiene este artículo;\nVI. Políticas de recursos humanos tendientes a evitar la incorporación de personas que puedan generar un riesgo a la integridad de la corporación. Estas políticas en ningún\nLey de Responsabilidades Administrativas del Estado de Baja California. Página 11 caso autorizarán la discriminación de persona alguna motivada por origen étnico o nacional, el género, la edad, las discapacidades, la condición social, las condiciones de salud, la religión, las opiniones, las preferencias sexuales, el estado civil o cualquier otra que atente de las personas; y\nVII. Mecanismos que aseguren en todo momento la transparencia y publicidad de sus intereses.\nCapítulo III\nDe los instrumentos de rendición de cuentas\nSección Primera\nDel sistema de evolución patrimonial, de declaración de intereses y constancia de presentación de declaración fiscal\nArtículo 26. La Secretaría Ejecutiva del Sistema Estatal Anticorrupción, llevará el sistema de evolución patrimonial, de declaración de intereses y constancia de presentación de declaración fiscal, a través de la Plataforma Digital Estatal que al efecto se establezca, de conformidad con lo previsto en la Ley del Sistema Estatal Anticorrupción, así como las bases, principios y lineamientos que apruebe el Comité Coordinador del Sistema Estatal\nAnticorrupción.\nArtículo 27. La información prevista en el sistema de evolución patrimonial, de declaración de intereses y de constancias de presentación de declaración fiscal se almacenará en la Plataforma Digital Estatal que contendrá la información que para efectos de las funciones del Sistema Estatal Anticorrupción, generen los entes públicos facultados para la fiscalización y control de recursos públicos y la prevención, control, detección, sanción y disuasión de faltas administrativas y hechos de corrupción, de conformidad con lo establecido en la Ley del Sistema Estatal Anticorrupción.\nLa Plataforma Digital Estatal contará además con los sistemas de información específicos que estipula la Ley del Sistema Estatal Anticorrupción.\nEn el sistema de evolución patrimonial, de declaración de intereses y de constancias de presentación de la declaración fiscal de la Plataforma Digital Nacional, se inscribirán los patrimonial y de intereses. De igual forma, se inscribirá la constancia que para efectos de esta Ley emita la autoridad fiscal, sobre la presentación de la declaración anual de impuestos.\nPlataforma Digital Estatal se inscribirán y se harán públicas, de conformidad con lo dispuesto transparencia, las constancias de sanciones o de inhabilitación que se encuentren firmes en\nLey de Responsabilidades Administrativas del Estado de Baja California. Página 12 vinculados con faltas graves en términos de esta Ley, así como la anotación de aquellas abstenciones que hayan realizado las autoridades investigadoras o el Tribunal, en términos de los artículos 77 y 80 de esta Ley.\nLos entes públicos, previo al nombramiento, designación o contratación de quienes pretendan ingresar al servicio público, consultarán el Sistema Nacional de Servidores\nPúblicos y particulares sancionados de la Plataforma digital Estatal, con el fin de verificar si existen inhabilitaciones de dichas personas.\nArtículo 28. La información relacionada con las declaraciones de situación patrimonial y de intereses, podrá ser solicitada y utilizada por el Ministerio Público, el\nTribunal o las autoridades judiciales en el ejercicio de sus respectivas atribuciones, el\nServidor Público interesado o bien, cuando las Autoridades investigadoras, substanciadoras o resolutoras lo requieran con motivo de la investigación o la resolución de procedimientos de responsabilidades administrativas.\nArtículo 29. Las declaraciones patrimoniales y de intereses serán públicas salvo los rubros cuya publicidad pueda afectar la vida privada o los datos personales protegidos por la\nConstitución. Para tal efecto, el Comité Coordinador, a propuesta del Comité de\nParticipación Ciudadana, emitirá los formatos respectivos, garantizando que los rubros que pudieran afectar los derechos aludidos queden en resguardo de las autoridades competentes.\nArtículo 30. La Secretaría, Sindicatura y los Órganos internos de control, según sea el caso, deberán realizar una verificación aleatoria de las declaraciones patrimoniales que obren en el sistema de evolución patrimonial, de declaración de intereses y constancia de presentación de declaración fiscal, así como de la evolución del patrimonio de los Servidores\nPúblicos. De no existir ninguna anomalía expedirán la certificación correspondiente, la cual se anotará en dicho sistema. En caso contrario, iniciarán la investigación que corresponda.\nArtículo 31. La Secretaría, Sindicaturas, así como los Órganos internos de control de los entes públicos, según corresponda, serán responsables de inscribir y mantener actualizada en el sistema de evolución patrimonial, de declaración de intereses y constancia de presentación de declaración fiscal, la información correspondiente a los Declarantes a su cargo. Asimismo, verificarán la situación o posible actualización de algún Conflicto de\nInterés, según la información proporcionada, llevarán el seguimiento de la evolución y la verificación de la situación patrimonial de dichos Declarantes, en los términos de la presente\nLey. Para tales efectos, la Secretaría y Sindicatura según se trate podrán firmar convenios con las distintas autoridades que tengan a su disposición datos, información o documentos que puedan servir para verificar la información declarada por los Servidores Públicos.\nSección Segunda\nLey de Responsabilidades Administrativas del Estado de Baja California. Página 13\nArtículo 32. Estarán obligados a presentar las declaraciones de situación patrimonial y de intereses, bajo protesta de decir verdad y ante la Secretaría, Sindicaturas o su respectivo Órgano interno de control, todos los Servidores Públicos, en los términos previstos en la presente Ley. Asimismo, deberán presentar su declaración fiscal anual, en los términos que disponga la legislación de la materia.\nSección tercera\nPlazos y mecanismos de registro al sistema de evolución patrimonial, de declaración de intereses y constancia de presentación de declaración fiscal\nArtículo 33. La declaración de situación patrimonial deberá presentarse en los siguientes plazos:\nI. Declaración inicial, dentro de los sesenta días naturales siguientes a la toma de posesión con motivo del:\na) Ingreso al servicio público por primera vez;\nb) Reingreso al servicio público después de sesenta días naturales de la conclusión de su último encargo;\nII. Declaración de modificación patrimonial, durante el mes de mayo de cada año;\nIII. Declaración de conclusión del encargo, dentro de los sesenta días naturales siguientes a la conclusión.\nEn el caso de cambio de dependencia o entidad en el mismo orden de gobierno, únicamente se dará aviso de dicha situación y no será necesario presentar la declaración de conclusión.\nLa Secretaría, Sindicaturas o los Órganos internos de control, según corresponda, podrán solicitar a los Servidores Públicos una copia de la declaración del Impuesto Sobre la\nRenta del año que corresponda, si éstos estuvieren obligados a presentarla o, en su caso, de la constancia de percepciones y retenciones que les hubieren emitido alguno de los entes públicos, la cual deberá ser remitida en un plazo de tres días hábiles a partir de la fecha en que se reciba la solicitud.\nSi transcurridos los plazos a que se refieren las fracciones I, II y III de este artículo, no se hubiese presentado la declaración correspondiente, sin causa justificada, se iniciará dicha obligación. siguientes a la fecha en que hubiere notificado el requerimiento al Declarante, la Secretaría, Ley de Responsabilidades Administrativas del Estado de Baja California. Página 14\nSindicaturas o los Órganos internos de control, según corresponda, declararán que el nombramiento o contrato ha quedado sin efectos, debiendo notificar lo anterior al titular del\nEnte público correspondiente para separar del cargo al servidor público. La autoridad que cargo, en su caso justificar y fundar la temporalidad de la medida.\nEl incumplimiento por no separar del cargo al servidor público por parte del titular de alguno de los entes públicos, será causa de responsabilidad administrativa en los términos de esta Ley.\nPara el caso de omisión, sin causa justificada, en la presentación de la declaración a que se refiere la fracción III de este artículo, se inhabilitará al infractor de tres meses a un año.\nPara la imposición de las sanciones a que se refiere este artículo deberá sustanciarse el procedimiento de responsabilidad administrativa por faltas administrativas previsto en el\nTítulo Segundo del Libro Segundo de esta Ley.\nArtículo 34. Las declaraciones de situación patrimonial deberán ser presentadas a través de medios electrónicos, empleándose medios de identificación electrónica. En el caso de autoridades que no cuenten con las tecnologías de la información y comunicación necesarias para cumplir lo anterior, podrán emplearse formatos impresos, siendo responsabilidad de los Órganos internos de control, Sindicatura y la Secretaría verificar que dichos formatos sean digitalizados e incluir la información que corresponda en el sistema de evolución patrimonial y de declaración de intereses.\nLas Secretarías tendrán a su cargo el sistema de certificación de los medios de identificación electrónica que utilicen los Servidores Públicos, y llevarán el control de dichos medios.\nAsimismo, el Comité Coordinador, a propuesta del Comité de Participación\nCiudadana, emitirá las normas y los formatos impresos; de medios magnéticos y electrónicos, bajo los cuales los Declarantes deberán presentar las declaraciones de situación patrimonial, así como los manuales e instructivos, observando lo dispuesto por el artículo 29 de esta Ley, debiendo garantizar su accesibilidad. disposiciones del presente Título, son documentos públicos aquellos que emita la Secretaría para ser presentados como medios de prueba, en los cuales se contenga la información que patrimonial de los Servidores Públicos.\nLey de Responsabilidades Administrativas del Estado de Baja California. Página 15 legislación en materia de transparencia, acceso a la información pública y protección de datos personales.\nArtículo 35. En la declaración inicial y de conclusión del encargo se manifestarán los bienes inmuebles, con la fecha y valor de adquisición. modificaciones al patrimonio, con fecha y valor de adquisición. En todo caso se indicará el medio por el que se hizo la adquisición.\nArtículo 36. La Secretaría, Sindicaturas y los Órganos internos de control, estarán facultadas para llevar a cabo investigaciones o auditorías para verificar la evolución del patrimonio de los Declarantes.\nArtículo 37. En los casos en que la declaración de situación patrimonial del\nDeclarante refleje un incremento en su patrimonio que no sea explicable o justificable en virtud de su remuneración como servidor público, la Secretaría, Sindicaturas y los Órganos internos de control inmediatamente solicitarán sea aclarado el origen de dicho enriquecimiento. De no justificarse la procedencia de dicho enriquecimiento, la Secretaría, Sindicaturas y los Órganos internos de control procederán a integrar el expediente correspondiente para darle trámite conforme a lo establecido en esta Ley, y formularán, en su caso, la denuncia correspondiente ante el Ministerio Público.\nArtículo 38. Los Declarantes estarán obligados a proporcionar a la Secretaría, Sindicaturas y los Órganos internos de control, la información que se requiera para verificar la evolución de su situación patrimonial, incluyendo la de sus cónyuges, concubinas o concubinarios y dependientes económicos directos.\nSólo los titulares de la Secretaría, Sindicaturas o los Servidores Públicos en quien deleguen esta facultad podrán solicitar a las autoridades competentes, en los términos de las disposiciones aplicables, la información en materia fiscal, o la relacionada con operaciones de depósito, ahorro, administración o inversión de recursos monetarios.\nArtículo 39. Para los efectos de la presente Ley y de la legislación penal, se conduzcan como dueños, los que reciban o de los que dispongan su cónyuge, concubina o concubinario y sus dependientes económicos directos, salvo que se acredite que éstos los obtuvieron por sí mismos.\nArtículo 40. En caso de que los Servidores Públicos, sin haberlo solicitado, reciban uso de cualquier bien, con motivo del ejercicio de sus funciones, deberán informarlo inmediatamente a la Secretaría, Sindicaturas o al Órgano interno de control. En el caso de recepción de bienes, los Servidores Públicos procederán a poner los mismos a disposición\nLey de Responsabilidades Administrativas del Estado de Baja California. Página 16 públicos.\nArtículo 41. La Secretaría, Sindicaturas y los Órganos internos de control, según corresponda, tendrán la potestad de formular la denuncia al Ministerio Público, en su caso, procedencia lícita del incremento notoriamente desproporcionado de éste, representado por sus bienes, o de aquéllos sobre los que se conduzca como dueño, durante el tiempo de su empleo, cargo o comisión.\nArtículo 42. Cuando las Autoridades investigadoras, en el ámbito de sus competencias, llegaren a formular denuncias ante el Ministerio Público correspondiente, éstas serán coadyuvantes del mismo en el procedimiento penal respectivo.\nSección cuarta\nRégimen de los servidores públicos que participan en contrataciones públicas\nArtículo 43. La Plataforma Digital Estatal incluirá, en un sistema específico, los nombres y adscripción de los Servidores Públicos que intervengan en procedimientos para contrataciones públicas, ya sea en la tramitación, atención y resolución para la adjudicación de un contrato, otorgamiento de una concesión, licencia, permiso o autorización y sus prórrogas, así como la enajenación de bienes muebles y aquellos que dictaminan en materia de avalúos, el cual será actualizado quincenalmente.\nLos formatos y mecanismos para registrar la información serán determinados por el\nComité Coordinador.\nLa información a que se refiere el presente artículo deberá ser puesta a disposición de todo público a través de un portal de Internet.\nSección quinta\nDel protocolo de actuación en contrataciones\nArtículo 44. El Comité Coordinador expedirá el protocolo de actuación que la\nSecretaría, Sindicaturas y los Órganos internos de control implementarán.\nCapítulo y, en su caso, aplicarán los formatos que se utilizarán para que los particulares formulen un manifiesto de vínculos o relaciones de negocios, personales o familiares, así como de posibles Conflictos de Interés, bajo el principio de máxima publicidad y en los términos de la normatividad aplicable en materia de transparencia.\nLey de Responsabilidades Administrativas del Estado de Baja California. Página 17\nCapítulo incluirá la relación de particulares, personas físicas y morales, que se encuentren administrativos diversos a los previstos por esta Ley.\nArtículo 45. La Secretaría, Sindicaturas o los Órganos internos de control deberán supervisar la ejecución de los procedimientos de contratación pública por parte de los contratantes para garantizar que se lleva a cabo en los términos de las disposiciones en la materia, llevando a cabo las verificaciones procedentes si descubren anomalías.\nSección sexta\nDe la declaración de intereses\nArtículo 46. Se encuentran obligados a presentar declaración de intereses todos los\nServidores Públicos que deban presentar la declaración patrimonial en términos de esta Ley.\nAl efecto, la Secretaría, Sindicaturas y los Órganos internos de control se encargarán de que las declaraciones sean integradas al sistema de evolución patrimonial, de declaración de intereses y constancia de presentación de declaración fiscal.\nArtículo 47. Para efectos del artículo anterior habrá Conflicto de Interés en los casos a los que se refiere la fracción VI del artículo 3 de esta Ley.\nLa declaración de intereses tendrá por objeto informar y determinar el conjunto de intereses de un servidor público a fin de delimitar cuándo éstos entran en conflicto con su función.\nArtículo 48. El Comité Coordinador, a propuesta del Comité de Participación\nCiudadana, expedirá las normas y los formatos impresos, de medios magnéticos y electrónicos, bajo los cuales los Declarantes deberán presentar la declaración de intereses, así como los manuales e instructivos, observando lo dispuesto por el artículo 29 de esta Ley.\nLa declaración de intereses deberá presentarse en los plazos a que se refiere el artículo 33 de esta Ley y de la misma manera le serán aplicables los procedimientos establecidos en dicho artículo para el incumplimiento de dichos plazos. También deberá presentar la declaración en cualquier momento en que el servidor público, en el ejercicio de sus funciones, considere que se puede actualizar un posible Conflicto de Interés.\nTÍTULO TERCERO\nCapítulo I\nLey de Responsabilidades Administrativas del Estado de Baja California. Página 18\nArtículo 49. Incurrirá en Falta administrativa no grave el servidor público cuyos actos u omisiones incumplan o transgredan lo contenido en las obligaciones siguientes:\nI.….Cumplir con las recomendaciones vinculatorias emitidas por el Comité\nCoordinador del Sistema Estatal Anticorrupción, así como cumplir con sus funciones, atribuciones y comisiones encomendadas, observando en su desempeño disciplina y respeto, tanto a los demás Servidores Públicos como a los particulares con los que llegare a tratar, en los términos que se establezcan en el código de ética a que se refiere el artículo 16 de esta Ley;\nII. Denunciar los actos u omisiones que en ejercicio de sus funciones llegare a advertir, que puedan constituir Faltas administrativas, en términos del artículo 93 de la presente Ley;\nIII. Atender las instrucciones de sus superiores, siempre que éstas sean acordes con las disposiciones relacionadas con el servicio público.\nEn caso de recibir instrucción o encomienda contraria a dichas disposiciones, deberá denunciar esta circunstancia en términos del artículo 93 de la presente Ley;\nIV. Presentar en tiempo y forma las declaraciones de situación patrimonial y de intereses, en los términos establecidos por esta Ley;\nV. Registrar, integrar, custodiar y cuidar la documentación e información que por razón de su empleo, cargo o comisión, tenga bajo su responsabilidad, e impedir o evitar su uso, divulgación, sustracción, destrucción, ocultamiento o inutilización indebidos;\nVI. Supervisar que los Servidores Públicos sujetos a su dirección, cumplan con las disposiciones de este artículo;\nVII. Rendir cuentas sobre el ejercicio de las funciones, en términos de las normas aplicables;\nVIII. Colaborar en los procedimientos judiciales y administrativos en los que sea parte;\nIX. Cerciorarse, antes de la celebración de contratos de adquisiciones, arrendamientos o para la enajenación de todo tipo de bienes, prestación de servicios de cualquier naturaleza o la contratación de obra pública o servicios relacionados con ésta, que el particular manifieste bajo protesta de decir verdad que no desempeña empleo, cargo o comisión en el servicio público o, en su caso, que a pesar de desempeñarlo, con la formalización del contrato correspondiente no se actualiza un Conflicto de Interés. Las\nÓrgano interno de control, previo a la celebración del acto en cuestión. En caso de que el\nLey de Responsabilidades Administrativas del Estado de Baja California. Página 19 contratista sea persona moral, dichas manifestaciones deberán presentarse respecto a los socios o accionistas que ejerzan control sobre la sociedad, y una sociedad cuando sean administradores o formen parte del consejo de administración, o bien conjunta o separadamente, directa o indirectamente, mantengan la titularidad de derechos que permitan ejercer el voto respecto de más del cincuenta por ciento del capital, tengan poder decisorio en sus asambleas, estén en posibilidades de nombrar a la mayoría de los miembros de su órgano de administración o por cualquier otro medio tengan facultades de tomar las decisiones fundamentales de dichas personas morales.\nArtículo 50. También se considerará falta administrativa no grave, los daños y perjuicios que, de manera culposa o negligente y sin incurrir en alguna de las faltas administrativas graves señaladas en el Capítulo siguiente, cause un servidor público a la\nHacienda Pública o al patrimonio de un Ente público.\nLos entes públicos o los particulares que, en términos de este artículo, hayan recibido recursos públicos sin tener derecho a los mismos, deberán reintegrar los mismos a la\nHacienda Pública o al patrimonio del Ente público afectado en un plazo no mayor a 90 días, contados a partir de la notificación correspondiente de la Auditoría Superior del Estado o de la Autoridad resolutora.\nEn caso de que no se realice el reintegro de los recursos señalados en el párrafo anterior, estos serán considerados créditos fiscales, por lo que la autoridad competente, Secretaria de Planeación y Finanzas del Poder Ejecutivo del Estado, en su caso el Servicio de Administración Tributaria, deberán ejecutar el cobro de los mismos en términos de las disposiciones jurídicas aplicables.\nLa Autoridad resolutora podrá abstenerse de imponer la sanción que corresponda conforme al artículo 75 de esta Ley, cuando el daño o perjuicio a la Hacienda Pública o al patrimonio de los entes públicos no exceda de dos mil veces el valor diario de la Unidad de\nMedida y Actualización y el daño haya sido resarcido o recuperado.\nCapítulo II\nArtículo 51. Las conductas previstas en el presente Capítulo constituyen faltas administrativas graves de los Servidores Públicos, por lo que deberán abstenerse de realizarlas, mediante cualquier acto u omisión.\nArtículo 52. Incurrirá en cohecho el servidor público que exija, acepte, obtenga o pretenda obtener, por sí o a través de terceros, con motivo de sus funciones, cualquier beneficio no comprendido en su remuneración como servidor público, que podría consistir en dinero; valores; bienes muebles o inmuebles, incluso mediante enajenación en precio\nLey de Responsabilidades Administrativas del Estado de Baja California. Página 20 notoriamente inferior al que se tenga en el mercado; donaciones; servicios; empleos y demás beneficios indebidos para sí o para su cónyuge, parientes consanguíneos, parientes civiles o para terceros con los que tenga relaciones profesionales, laborales o de negocios, o formen parte.\nArtículo 53. Cometerá peculado el servidor público que autorice, solicite o realice actos para el uso o apropiación para sí o para las personas a las que se refiere el artículo anterior, de recursos públicos, sean materiales, humanos, financieros, incluyendo la asignación de plazas de base o planta, sin fundamento jurídico o en contraposición a las normas aplicables.\nArtículo Reformado\nArtículo 54. Será responsable de desvío de recursos públicos el servidor público que autorice, solicite o realice actos para la asignación o desvío de recursos públicos, sean materiales, humanos o financieros, sin fundamento jurídico o en contraposición a las normas aplicables.\nEn ningún caso los servidores públicos podrán realizar contratación alguna de las previstas en la Ley de Adquisiciones, Arrendamientos y Servicios para el Estado de Baja\nCalifornia, tres meses antes de que concluya el periodo de gobierno de la administración correspondiente, salvo que exista autorización expresa del Congreso del Estado.\nPárrafo Adicionado\nArtículo Reformado\nArtículo 55. Incurrirá en utilización indebida de información el servidor público que adquiera para sí o para las personas a que se refiere el artículo 52 de esta Ley, bienes inmuebles, muebles y valores que pudieren incrementar su valor o, en general, que mejoren sus condiciones, así como obtener cualquier ventaja o beneficio privado, como resultado de información privilegiada de la cual haya tenido conocimiento.\nArtículo 56. Para efectos del artículo anterior, se considera información privilegiada la que obtenga el servidor público con motivo de sus funciones y que no sea del dominio público. servidor público se haya retirado del empleo, cargo o comisión, hasta por un plazo de un año.\nArtículo 57. Incurrirá en abuso de funciones la persona servidora o servidor público que ejerza atribuciones que no tenga conferidas o se valga de las que tenga, para realizar o inducir actos u omisiones arbitrarios, para generar un beneficio para sí o para las personas a las que se refiere el artículo 52 de esta Ley o para causar perjuicio a alguna persona o al servicio público.\nPárrafo Reformado\nLey de Responsabilidades Administrativas del Estado de Baja California. Página 21\nDe igual manera, se considerará abuso de funciones, cuando el funcionario que, estando obligado, por omisión, negligencia o con conocimiento de causa, no entere las cuotas de aportación de seguridad social a la entidad correspondiente, en los términos legalmente establecidos. Así como cuando realiza por sí o a través de un tercero, alguna de las conductas descritas en el artículo 11 TER, de la Ley de Acceso de las Mujeres a una\nVida Libre de Violencia para el Estado de Baja California.\nPárrafo Reformado\nArtículo Reformado\nArtículo 58. Incurre en actuación bajo Conflicto de Interés el servidor público que intervenga por motivo de su empleo, cargo o comisión en cualquier forma, en la atención, tramitación o resolución de asuntos en los que tenga Conflicto de Interés o impedimento legal.\nAl tener conocimiento de los asuntos mencionados en el párrafo anterior, el servidor público informará tal situación al jefe inmediato o al órgano que determine las disposiciones aplicables de los entes públicos, solicitando sea excusado de participar en cualquier forma en la atención, tramitación o resolución de los mismos.\nSerá obligación del jefe inmediato determinar y comunicarle al servidor público, a más tardar 48 horas antes del plazo establecido para atender el asunto en cuestión, los casos en que no sea posible abstenerse de intervenir en los asuntos, así como establecer instrucciones por escrito para la atención, tramitación o resolución imparcial y objetiva de dichos asuntos.\nArtículo 59. Será responsable de contratación indebida el servidor público que autorice cualquier tipo de contratación, así como la selección, nombramiento o designación, de quien se encuentre impedido por disposición legal o inhabilitado por resolución de autoridad competente para ocupar un empleo, cargo o comisión en el servicio público o inhabilitado para realizar contrataciones con los entes públicos, siempre que en el caso de las inhabilitaciones, al momento de la autorización, éstas se encuentren inscritas en el\nSistema Nacional de Servidores Públicos y particulares sancionados de la Plataforma Digital\nNacional.\nArtículo 60. Incurrirá en enriquecimiento oculto u ocultamiento de Conflicto de Interés situación patrimonial o de intereses, que tenga como fin ocultar, respectivamente, el justificable, o un Conflicto de Interés.\nArtículo 61. Cometerá tráfico de influencias el servidor público que utilice la posición que su empleo, cargo o comisión le confiere para inducir a que otro servidor público efectúe, retrase u omita realizar algún acto de su competencia, para generar cualquier beneficio, Ley de Responsabilidades Administrativas del Estado de Baja California. Página 22 provecho o ventaja para sí o para alguna de las personas a que se refiere el artículo 52 de esta Ley.\nArtículo 62. Será responsable de encubrimiento el servidor público que cuando en el administrativas, realice deliberadamente alguna conducta para su ocultamiento.\nArtículo 62 BIS. El servidor público que no entregue, incumpla, retrase, oculte, destruya, altere, deforme, inutilice total o parcialmente la información pública que de acuerdo a la Ley de Entrega y Recepción de los Asuntos y Recursos Públicos para el Estado de Baja\nCalifornia, esté obligado a proporcionar, en los plazos, términos y formas previstas en la legislación.\nArtículo Adicionado\nArtículo 63. Cometerá desacato el servidor público que, tratándose de requerimientos o resoluciones de autoridades fiscalizadoras, de control interno, judiciales, electorales o en materia de defensa de los derechos humanos o cualquier otra competente, proporcione información falsa, así como no dé respuesta alguna, retrase deliberadamente y sin justificación la entrega de la información, a pesar de que le hayan sido impuestas medidas de apremio conforme a las disposiciones aplicables.\nArtículo 63 BIS. Será responsable de atentar contra el desarrollo urbano y los asentamientos humanos, la persona servidora o servidor público que, contraviniendo el Atlas de Riesgos o los planes o programas de desarrollo urbano expedidos en términos de las leyes aplicables, expida licencia, permiso, autorización, constancia o dictamen para realizar cualquier tipo de construcción, obra de infraestructura, equipamiento urbano, acción de urbanización o asentamientos humanos.\nArtículo Adicionado\nArtículo 63 TER.- La persona servidora pública que incumpla o retrase la entrega de los Informes de Avance de Gestión de la Entidad Fiscalizada, en los plazos, términos y formas previstas en la legislación; o en su caso, oculte, destruya, altere, deforme, inutilice total o parcialmente la información y documentación que integra estos informes.\nAsimismo, la persona servidora pública que incumpla o retrase la entrega de la\nCuenta Pública de la Entidad Fiscalizada, en los plazos, términos y formas previstas en la legislación; o en su caso, oculte, destruya, altere, deforme, inutilice total o parcialmente la información y documentación que integra la Cuenta Pública.\nArtículo Adicionado\nArtículo 64. Los Servidores Públicos responsables de la investigación, substanciación y resolución de las Faltas administrativas incurrirán en obstrucción de la justicia cuando:\nLey de Responsabilidades Administrativas del Estado de Baja California. Página 23\nI. Realicen cualquier acto que simule conductas no graves durante la disposiciones aplicables;\nII. No inicien el procedimiento correspondiente ante la autoridad competente, dentro del plazo de treinta días naturales, a partir de que tengan conocimiento de cualquier conducta que pudiera constituir una Falta administrativa grave, Faltas de particulares o un acto de corrupción; y\nIII. Revelen la identidad de un denunciante anónimo protegido bajo los preceptos establecidos en esta Ley.\nPara efectos de la fracción anterior, los Servidores Públicos que denuncien una falta administrativa grave o faltas de particulares, o sean testigos en el procedimiento, podrán solicitar medidas de protección que resulten razonables. La solicitud deberá ser evaluada y atendida de manera oportuna por el Ente público donde presta sus servicios el denunciante.\nCapítulo III\nDe los actos de particulares vinculados con faltas administrativas graves\nArtículo 65. Los actos de particulares previstos en el presente Capítulo se consideran vinculados a faltas administrativas graves, por lo que su comisión será sancionada en términos de esta Ley.\nArtículo 66. Incurrirá en soborno el particular que prometa, ofrezca o entregue cualquier beneficio indebido a que se refiere el artículo 52 de esta Ley a uno o varios\nServidores Públicos, directamente o a través de terceros, a cambio de que dichos Servidores\nPúblicos realicen o se abstengan de realizar un acto relacionado con sus funciones o con las de otro servidor público, o bien, abusen de su influencia real o supuesta, con el propósito de obtener o mantener, para sí mismo o para un tercero, un beneficio o ventaja, con independencia de la aceptación o recepción del beneficio o del resultado obtenido.\nArtículo 67. Incurrirá en participación ilícita en procedimientos administrativos el municipales, no obstante que por disposición de ley o resolución de autoridad competente se encuentren impedido o inhabilitado para ello.\nTambién se considera participación ilícita en procedimientos administrativos, cuando un particular intervenga en nombre propio, pero en interés de otra u otras personas que se\nEstado o municipales, con la finalidad de que ésta o éstas últimas obtengan, total o parcialmente, los beneficios derivados de dichos procedimientos. Ambos particulares serán sancionados en términos de esta Ley.\nLey de Responsabilidades Administrativas del Estado de Baja California. Página 24\nArtículo 68. Incurrirá en tráfico de influencias para inducir a la autoridad el particular que use su influencia, poder económico o político, real o ficticio, sobre cualquier servidor público, con el propósito de obtener para sí o para un tercero un beneficio o ventaja, o para causar perjuicio a alguna persona o al servicio público, con independencia de la aceptación del servidor o de los Servidores Públicos o del resultado obtenido.\nArtículo 69. Será responsable de utilización de información falsa el particular que presente documentación o información falsa o alterada, o simulen el cumplimiento de requisitos o reglas establecidos en los procedimientos administrativos, con el propósito de lograr una autorización, un beneficio, una ventaja o de perjudicar a persona alguna.\nAsimismo, incurrirán en obstrucción de facultades de investigación el particular que, teniendo información vinculada con una investigación de Faltas administrativas, proporcione información falsa, retrase deliberada e injustificadamente la entrega de la misma, o no dé respuesta alguna a los requerimientos o resoluciones de autoridades investigadoras, substanciadoras o resolutoras, siempre y cuando le hayan sido impuestas previamente medidas de apremio conforme a las disposiciones aplicables.\nArtículo 70. Incurrirá en colusión el particular que ejecute con uno o más sujetos particulares, en materia de contrataciones públicas, acciones que impliquen o tengan por objeto o efecto obtener un beneficio o ventaja indebidos en las contrataciones públicas.\nTambién se considerará colusión cuando los particulares acuerden o celebren contratos, convenios, arreglos o combinaciones entre competidores, cuyo objeto o efecto sea obtener un beneficio indebido u ocasionar un daño a la Hacienda Pública o al patrimonio de los entes públicos.\nCuando la infracción se hubiere realizado a través de algún intermediario con el propósito de que el particular obtenga algún beneficio o ventaja en la contratación pública de que se trate, ambos serán sancionados en términos de esta Ley.\nLas faltas referidas en el presente artículo resultarán aplicables además respecto de transacciones comerciales internacionales. En estos supuestos la Secretaría será la autoridad competente para realizar las investigaciones que correspondan y podrá solicitar a las autoridades competentes la opinión técnica referida en el párrafo anterior, así como a un procedimientos a que se refiere esta Ley, en los términos previstos en los instrumentos internacionales de los que ambos estados sean parte y demás ordenamientos aplicables. internacionales, los actos y procedimientos relacionados con la contratación, ejecución y cumplimiento de contratos en materia de adquisiciones, arrendamientos, servicios de cualquier naturaleza, obra pública y servicios relacionados con la misma; los actos y procedimientos relativos al otorgamiento y prórroga de permisos o concesiones, así como\nLey de Responsabilidades Administrativas del Estado de Baja California. Página 25 cualquier otra autorización o trámite relacionados con dichas transacciones, que lleve a cabo participación de un servidor público extranjero y en cuyo desarrollo participen, de manera directa o indirecta, personas físicas o morales de nacionalidad mexicana.\nArtículo 71. Será responsable por el uso indebido de recursos públicos el particular que realice actos mediante los cuales se apropie, haga uso indebido o desvíe del objeto para el que estén previstos los recursos públicos, sean materiales, humanos o financieros, cuando por cualquier circunstancia maneje, reciba, administre o tenga acceso a estos recursos.\nTambién se considera uso indebido de recursos públicos la omisión de rendir cuentas que comprueben el destino que se otorgó a dichos recursos.\nArtículo 72. Será responsable de contratación indebida de ex servidores públicos el particular que contrate a quien haya sido servidor público durante el año previo, que posea información privilegiada que directamente haya adquirido con motivo de su empleo, cargo o comisión en el servicio público, y directamente permita que el contratante se beneficie en el mercado o se coloque en situación ventajosa frente a sus competidores. En este supuesto también será sancionado el ex servidor público contratado.\nCapítulo IV\nDe las Faltas de particulares en situación especial\nArtículo 73. Se consideran faltas de particulares en situación especial, aquéllas realizadas por candidatos a cargos de elección popular, miembros de equipos de campaña electoral o de transición entre administraciones del sector público, y líderes de sindicatos del sector público, que impliquen exigir, solicitar, aceptar, recibir o pretender recibir alguno de los beneficios a que se refiere el artículo 52 de esta Ley, ya sea para sí, para su campaña electoral o para alguna de las personas a las que se refiere el citado artículo, a cambio de otorgar u ofrecer una ventaja indebida en el futuro en caso de obtener el carácter de\nServidor Público.\nCapítulo, incluidos los directivos y empleados de los sindicatos, podrán ser sancionados cuando incurran en las conductas a que se refiere el Capítulo anterior.\nCapítulo V\nArtículo 74. Para el caso de faltas administrativas no graves, las facultades de la\nSecretaría, Sindicaturas, o de los Órganos internos de control para imponer las sanciones prescribirán en tres años, contados a partir del día siguiente al que se hubieren cometido las infracciones, o a partir del momento en que hubieren cesado.\nLey de Responsabilidades Administrativas del Estado de Baja California. Página 26\nCuando se trate de faltas administrativas graves o faltas de particulares, el plazo de prescripción será de siete años, contados en los mismos términos del párrafo anterior. del artículo 100 de esta Ley. originados con motivo de la admisión del citado informe, y como consecuencia de ello se produjera la caducidad de la instancia, la prescripción se reanudará desde el día en que se admitió el Informe de Presunta Responsabilidad Administrativa.\nEn ningún caso, en los procedimientos de responsabilidad administrativa podrá dejar de actuarse por más de seis meses sin causa justificada; en caso de actualizarse dicha inactividad, se decretará, a solicitud del presunto infractor, la caducidad de la instancia.\nLos plazos a los que se refiere el presente artículo se computarán en días naturales.\nTÍTULO CUARTO\nSANCIONES\nCapítulo I\nSanciones por faltas administrativas no graves\nArtículo 75. En los casos de responsabilidades administrativas distintas a las que son competencia del Tribunal, la Secretaría, Sindicaturas o los Órganos internos de control impondrán las sanciones administrativas siguientes:\nI. Amonestación pública o privada;\nII. Suspensión del empleo, cargo o comisión;\nIII. Destitución de su empleo, cargo o comisión; y\nIV. Inhabilitación temporal para desempeñar empleos, cargos o comisiones en el servicio público y para participar en adquisiciones, arrendamientos, servicios u obras públicas.\nLa Secretaría, Sindicaturas y los Órganos internos de control podrán imponer una o más de las sanciones administrativas señaladas en este artículo, siempre y cuando sean compatibles entre ellas y de acuerdo a la trascendencia de la falta administrativa no grave.\nLa suspensión del empleo, cargo o comisión que se imponga podrá ser de uno a treinta días naturales.\nLey de Responsabilidades Administrativas del Estado de Baja California. Página 27\nEn caso de que se imponga como sanción la inhabilitación temporal, ésta no será menor de tres meses ni podrá exceder de un año.\nArtículo 76. Para la imposición de las sanciones a que se refiere el artículo anterior se deberán considerar los elementos del empleo, cargo o comisión que desempeñaba el servidor público cuando incurrió en la falta, así como los siguientes:\nI. El nivel jerárquico y los antecedentes del infractor, entre ellos, la antigüedad en el servicio;\nII. Las condiciones exteriores y los medios de ejecución; y\nIII. La reincidencia en el incumplimiento de obligaciones.\nEn caso de reincidencia de faltas administrativas no graves, la sanción que imponga el Órgano interno de control no podrá ser igual o menor a la impuesta con anterioridad.\nSe considerará reincidente al que habiendo incurrido en una infracción que haya sido sancionada y hubiere causado ejecutoria, cometa otra del mismo tipo.\nArtículo 77. Corresponde a la Secretaría, Sindicaturas o a los Órganos internos de control imponer las sanciones por Faltas administrativas no graves, y ejecutarlas. Los\nÓrganos internos de control podrán abstenerse de imponer la sanción que corresponda siempre que el servidor público:\nI. No haya sido sancionado previamente por la misma Falta administrativa no grave; y\nII. No haya actuado de forma dolosa.\nLa Secretaría, Sindicaturas o los órganos internos de control dejarán constancia de la no imposición de la sanción a que se refiere el párrafo anterior.\nCapítulo II\nArtículo 78. Las sanciones administrativas que imponga el Tribunal a los Servidores\nPúblicos, derivado de los procedimientos por la comisión de faltas administrativas graves, consistirán en:\nI. Suspensión del empleo, cargo o comisión;\nII. Destitución del empleo, cargo o comisión;\nLey de Responsabilidades Administrativas del Estado de Baja California. Página 28\nIII. Sanción económica; y\nIV. Inhabilitación temporal para desempeñar empleos, cargos o comisiones en el servicio público y para participar en adquisiciones, arrendamientos, servicios u obras públicas.\nA juicio del Tribunal, podrán ser impuestas al infractor una o más de las sanciones señaladas, siempre y cuando sean compatibles entre ellas y de acuerdo a la gravedad de la\nFalta administrativa grave.\nLa suspensión del empleo, cargo o comisión que se imponga podrá ser de treinta a noventa días naturales.\nEn caso de que se determine la inhabilitación, ésta será de uno hasta diez años si el monto de la afectación de la falta administrativa grave no excede de doscientas veces el valor diario de la Unidad de Medida y Actualización, y de diez a veinte años si dicho monto excede de dicho límite. Cuando no se cause daños o perjuicios, ni exista beneficio o lucro alguno, se podrán imponer de tres meses a un año de inhabilitación.\nArtículo 79. En el caso de que la falta administrativa grave cometida por el servidor público le genere beneficios económicos, a sí mismo o a cualquiera de las personas a que se refiere el artículo 52 de esta Ley, se le impondrá sanción económica que podrá alcanzar hasta dos tantos de los beneficios obtenidos. En ningún caso la sanción económica que se imponga podrá ser menor o igual al monto de los beneficios económicos obtenidos. Lo anterior, sin perjuicio de la imposición de las sanciones a que se refiere el artículo anterior.\nEl Tribunal determinará el pago de una indemnización cuando, la falta administrativa grave a que se refiere el párrafo anterior provocó daños y perjuicios a la Hacienda Pública\nEstatal o municipal, o al patrimonio de los entes públicos. En dichos casos, el servidor público estará obligado a reparar la totalidad de los daños y perjuicios causados y las personas que, en su caso, también hayan obtenido un beneficio indebido, serán solidariamente responsables.\nArtículo 80. Para la imposición de las sanciones a que se refiere el artículo 78 de esta Ley se deberán considerar los elementos del empleo, cargo o comisión que desempeñaba el servidor público cuando incurrió en la falta, así como los siguientes:\nI. Los daños y perjuicios patrimoniales causados por los actos u omisiones;\nII. El nivel jerárquico y los antecedentes del infractor, entre ellos la antigüedad en el servicio;\nIII. Las circunstancias socioeconómicas del servidor público;\nIV. Las condiciones exteriores y los medios de ejecución;\nLey de Responsabilidades Administrativas del Estado de Baja California. Página 29\nV. La reincidencia en el incumplimiento de obligaciones; y\nVI. El monto del beneficio derivado de la infracción que haya obtenido el responsable.\nCapítulo III\nSanciones por Faltas de particulares\nArtículo 81. Las sanciones administrativas que deban imponerse por Faltas de particulares por comisión de alguna de las conductas previstas en los Capítulos III y IV del\nTítulo Tercero de esta Ley, consistirán en:\nI. Tratándose de personas físicas:\na) Sanción económica que podrá alcanzar hasta dos tantos de los beneficios obtenidos o, en caso de no haberlos obtenido, por el equivalente a la cantidad de cien hasta ciento cincuenta mil veces el valor diario de la Unidad de Medida y Actualización;\nb) Inhabilitación temporal para participar en adquisiciones, arrendamientos, servicios u obras públicas, según corresponda, por un periodo que no será menor de tres meses ni mayor de ocho años;\nc) Indemnización por los daños y perjuicios ocasionados a la Hacienda Pública\nEstatal o municipal, o al patrimonio de los entes públicos.\nII. Tratándose de personas morales:\na) Sanción económica que podrá alcanzar hasta dos tantos de los beneficios obtenidos, en caso de no haberlos obtenido, por el equivalente a la cantidad de mil hasta un millón quinientas mil veces el valor diario de la Unidad de Medida y Actualización;\nb) Inhabilitación temporal para participar en adquisiciones, arrendamientos, servicios u obras públicas, por un periodo que no será menor de tres meses ni mayor de diez años;\nc) La suspensión de actividades, por un periodo que no será menor de tres meses ni mayor de tres años, la cual consistirá en detener, diferir o privar temporalmente a los particulares de sus actividades comerciales, económicas, contractuales o de negocios por estar vinculados a faltas administrativas graves previstas en esta Ley;\nd) Disolución de la sociedad respectiva, la cual consistirá en la pérdida de la capacidad legal de una persona moral, para el cumplimiento del fin por el que fue creada\nLey de Responsabilidades Administrativas del Estado de Baja California. Página 30 por orden jurisdiccional y como consecuencia de la comisión, vinculación, participación y relación con una Falta administrativa grave prevista en esta Ley;\ne) Indemnización por los daños y perjuicios ocasionados a la Hacienda Pública\nEstatal o Municipal, o al patrimonio de los entes públicos.\nPara la imposición de sanciones a las personas morales deberá observarse además, lo previsto en los artículos 24 y 25 de esta Ley.\nLas sanciones previstas en los incisos c) y d) de esta fracción, sólo serán procedentes cuando la sociedad obtenga un beneficio económico y se acredite participación de sus órganos de administración, de vigilancia o de sus socios, o en aquellos casos que se advierta que la sociedad es utilizada de manera sistemática para vincularse con faltas administrativas graves.\nA juicio del Tribunal, podrán ser impuestas al infractor una o más de las sanciones señaladas, siempre que sean compatibles entre ellas y de acuerdo a la gravedad de las\nFaltas de particulares.\nSe considerará como atenuante en la imposición de sanciones a personas morales cuando los órganos de administración, representación, vigilancia o los socios de las personas morales denuncien o colaboren en las investigaciones proporcionando la información y los elementos que posean, resarzan los daños que se hubieren causado.\nSe considera como agravante para la imposición de sanciones a las personas morales, el hecho de que los órganos de administración, representación, vigilancia o los socios de las mismas, que conozcan presuntos actos de corrupción de personas físicas que pertenecen a aquellas no los denuncien.\nArtículo 82. Para la imposición de las sanciones por Faltas de particulares se deberán considerar los siguientes elementos:\nI. El grado de participación del o los sujetos en la Falta de particulares;\nII. La reincidencia en la comisión de las infracciones previstas en esta Ley;\nIII. La capacidad económica del infractor;\nIV. El daño o puesta en peligro del adecuado desarrollo de la actividad administrativa del Estado; y\nV. El monto del beneficio, lucro, o del daño o perjuicio derivado de la infracción, cuando éstos se hubieren causado.\nLey de Responsabilidades Administrativas del Estado de Baja California. Página 31\nArtículo 83. El fincamiento de responsabilidad administrativa por la comisión de participación de un servidor público.\nLas personas morales serán sancionadas por la comisión de faltas de particulares, las personas físicas que actúen a nombre o representación de la persona moral o en beneficio de ella.\nCapítulo IV\nDisposiciones comunes para la imposición de sanciones por faltas administrativas graves y Faltas de particulares\nArtículo 84. Para la imposición de las sanciones por faltas administrativas graves y faltas de particulares, se observarán las siguientes reglas:\nI. La suspensión o la destitución del puesto de los Servidores Públicos, serán impuestas por el Tribunal y ejecutadas por el titular o servidor público competente del Ente público correspondiente;\nII. La inhabilitación temporal para desempeñar un empleo, cargo o comisión en el servicio público, y para participar en adquisiciones, arrendamientos, servicios u obras públicas, será impuesta por el Tribunal y ejecutada en los términos de la resolución dictada;\nIII. Las sanciones económicas serán impuestas por el Tribunal y ejecutadas por la\nSecretaria de Planeación y Finanzas del Poder Ejecutivo del Estado en términos del Código\nFiscal del Estado o por la autoridad competente de la entidad federativa correspondiente.\nArtículo 85. En los casos de sanción económica, el Tribunal ordenará a los responsables el pago que corresponda y, en el caso de daños y perjuicios que afecten a la\nHacienda Pública Estatal o Municipal, o al patrimonio de los entes públicos, adicionalmente el pago de las indemnizaciones correspondientes. Dichas sanciones económicas tendrán el carácter de créditos fiscales. públicos afectados.\nArtículo 86. El monto de la sanción económica impuesta se actualizará, para efectos de su pago, en la forma y términos que establece el Código Fiscal del Estado, en tratándose de contribuciones y aprovechamientos, o de la legislación aplicable en el ámbito local.\nLey de Responsabilidades Administrativas del Estado de Baja California. Página 32\nArtículo 87. Cuando el servidor público o los particulares presuntamente responsables de estar vinculados con una Falta administrativa grave, desaparezcan o exista riesgo inminente de que oculten, enajenen o dilapiden sus bienes a juicio del Tribunal, se autoridad competente en el ámbito local, en cualquier fase del procedimiento proceda al embargo precautorio de sus bienes, a fin de garantizar el cobro de las sanciones económicas que llegaren a imponerse con motivo de la infracción cometida. Impuesta la sanción económica, el embargo precautorio se convertirá en definitivo y se procederá en los términos de la legislación aplicable.\nArtículo 88. La persona que haya realizado alguna de las Faltas administrativas graves o Faltas de particulares, o bien, se encuentre participando en su realización, podrá confesar su responsabilidad con el objeto de acogerse al beneficio de reducción de sanciones que se establece en el artículo siguiente. Esta confesión se podrá hacer ante la\nAutoridad investigadora.\nArtículo 89. La aplicación del beneficio a que hace referencia el artículo anterior, tendrá por efecto una reducción de entre el cincuenta y el setenta por ciento del monto de las sanciones que se impongan al responsable, y de hasta el total, tratándose de la inhabilitación temporal para participar en adquisiciones, arrendamientos, servicios u obras públicas, por Faltas de particulares. Para su procedencia será necesario que adicionalmente se cumplan los siguientes requisitos:\nI. Que no se haya notificado a ninguno de los presuntos infractores el inicio del procedimiento de responsabilidad administrativa;\nII. Que la persona que pretende acogerse a este beneficio, sea de entre los sujetos involucrados en la infracción, la primera en aportar los elementos de convicción suficientes que, a juicio de las autoridades competentes, permitan comprobar la existencia de la infracción y la responsabilidad de quien la cometió;\nIII. Que la persona que pretende acogerse al beneficio coopere en forma plena y continua con la autoridad competente que lleve a cabo la investigación y, en su caso, con la que substancie y resuelva el procedimiento de responsabilidad administrativa; y\nIV. Que la persona interesada en obtener el beneficio, suspenda, en el momento en el que la autoridad se lo solicite, su participación en la infracción.\nAdemás de los requisitos señalados, para la aplicación del beneficio al que se refiere este artículo, se constatará por las autoridades competentes, la veracidad de la confesión realizada.\nEn su caso, las personas que sean los segundos o ulteriores en aportar elementos de convicción suficientes y cumplan con el resto de los requisitos anteriormente establecidos, Ley de Responsabilidades Administrativas del Estado de Baja California. Página 33 podrán obtener una reducción de la sanción aplicable de hasta el cincuenta por ciento, cuando aporten elementos de convicción en la investigación, adicionales a los que ya tenga la Autoridad Investigadora. Para determinar el monto de la reducción se tomará en convicción presentados.\nEl procedimiento de solicitud de reducción de sanciones establecido en este artículo podrá coordinarse y aplicarse supletoriamente con el procedimiento de solicitud de reducción de sanciones establecido en el artículo 103 de la Ley Federal de Competencia Económica cuando así convenga a las Autoridades Investigadoras correspondientes.\nEl Comité Coordinador podrá recomendar mecanismos de coordinación efectiva a efecto de permitir el intercambio de información entre autoridades administrativas, autoridades investigadoras de órganos del Estado y Autoridades Investigadoras dentro de su ámbito de competencia.\nSi el presunto infractor confiesa su responsabilidad sobre los actos que se le imputan una vez iniciado el procedimiento de responsabilidad administrativa a que se refiere esta\nLey, le aplicará una reducción de hasta treinta por ciento del monto de la sanción aplicable y, en su caso, una reducción de hasta el treinta por ciento del tiempo de inhabilitación que corresponda.\nLIBRO SEGUNDO\nDISPOSICIONES ADJETIVAS\nTÍTULO PRIMERO\nDE LA INVESTIGACIÓN Y CALIFICACIÓN DE LAS FALTAS GRAVES Y NO GRAVES\nCapítulo I\nInicio de la investigación\nArtículo 90. En el curso de toda investigación deberán observarse los principios de legalidad, imparcialidad, objetividad, congruencia, verdad material y respeto a los derechos humanos. Las autoridades competentes serán responsables de la oportunidad, exhaustividad y eficiencia en la investigación, la integralidad de los datos y documentos, así como el resguardo del expediente en su conjunto.\nIgualmente, incorporarán a sus investigaciones, las técnicas, tecnologías y métodos de investigación que observen las mejores prácticas internacionales.\nLas autoridades investigadoras, de conformidad con las leyes de la materia, deberán investigación, compartir las mejores prácticas internacionales, y combatir de manera efectiva la corrupción.\nLey de Responsabilidades Administrativas del Estado de Baja California. Página 34\nArtículo 91. La investigación por la presunta responsabilidad de Faltas administrativas iniciará de oficio, por denuncia o derivado de las auditorías practicadas por parte de las autoridades competentes o, en su caso, de auditores externos.\nLas denuncias podrán ser anónimas. En su caso, las autoridades investigadoras presuntas infracciones.\nArtículo 92. Las autoridades investigadoras establecerán áreas de fácil acceso, para que cualquier interesado pueda presentar denuncias por presuntas Faltas administrativas, de conformidad con los criterios establecidos en la presente Ley.\nArtículo 93. La denuncia deberá contener los datos o indicios que permitan advertir la presunta responsabilidad administrativa por la comisión de Faltas administrativas, y podrán ser presentadas de manera electrónica a través de los mecanismos que para tal efecto establezcan las Autoridades investigadoras, lo anterior sin menoscabo de la plataforma digital que determine, para tal efecto, el Sistema Estatal Anticorrupción.\nCapítulo II\nDe la Investigación\nArtículo 94. Para el cumplimiento de sus atribuciones, las Autoridades investigadoras llevarán de oficio las auditorías o investigaciones debidamente fundadas y motivadas respecto de las conductas de los Servidores Públicos y particulares que puedan constituir responsabilidades administrativas en el ámbito de su competencia. Lo anterior sin menoscabo de las investigaciones que se deriven de las denuncias a que se hace referencia en el Capítulo anterior.\nArtículo 95. Las autoridades investigadoras tendrán acceso a la información necesaria para el esclarecimiento de los hechos, con inclusión de aquélla que las disposiciones legales en la materia consideren con carácter de reservada o confidencial, siempre que esté relacionada con la comisión de infracciones a que se refiere esta Ley, con la obligación de mantener la misma reserva o secrecía, conforme a lo que determinen las leyes.\nPara el cumplimiento de las atribuciones de las autoridades investigadoras, durante el desarrollo de investigaciones por faltas administrativas graves, no les serán oponibles las disposiciones dirigidas a proteger la secrecía de la información en materia fiscal bursátil, fiduciario o la relacionada con operaciones de depósito, administración, ahorro e inversión de recursos monetarios. Esta información conservará su calidad en los expedientes correspondientes, para lo cual se celebrarán convenios de colaboración con las autoridades correspondientes.\nLey de Responsabilidades Administrativas del Estado de Baja California. Página 35\nPara efectos de lo previsto en el párrafo anterior, se observará lo dispuesto en el artículo 38 de esta Ley.\nLas autoridades encargadas de la investigación, por conducto de su titular, podrán ordenar la práctica de visitas de verificación, las cuales se sujetarán a lo previsto en la Ley\nFederal de Procedimiento Administrativo, en aplicación supletoria.\nArtículo 96. Las personas físicas o morales, públicas o privadas, que sean sujetos de investigación por presuntas irregularidades cometidas en el ejercicio de sus funciones, deberán atender los requerimientos que, debidamente fundados y motivados, les formulen las autoridades investigadoras.\nLa Autoridad investigadora otorgará un plazo de cinco hasta quince días hábiles para la atención de sus requerimientos, sin perjuicio de poder ampliarlo por causas debidamente justificadas, cuando así lo soliciten los interesados. Esta ampliación no podrá exceder en ningún caso la mitad del plazo previsto originalmente.\nLos entes públicos a los que se les formule requerimiento de información, tendrán la obligación de proporcionarla en el mismo plazo a que se refiere el párrafo anterior, contado a partir de que la notificación surta sus efectos.\nCuando los entes públicos, derivado de la complejidad de la información solicitada, requieran de un plazo mayor para su atención, deberán solicitar la prórroga debidamente justificada ante la Autoridad investigadora; de concederse la prórroga en los términos solicitados, el plazo que se otorgue será improrrogable. Esta ampliación no podrá exceder en ningún caso la mitad del plazo previsto originalmente.\nAdemás de las atribuciones a las que se refiere la presente Ley, durante la investigación las autoridades investigadoras podrán solicitar información o documentación a cualquier persona física o moral con el objeto de esclarecer los hechos relacionados con la comisión de presuntas Faltas administrativas.\nArtículo 97. Las autoridades investigadoras podrán hacer uso de las siguientes medidas para hacer cumplir sus determinaciones:\nI. Multa hasta por la cantidad equivalente de cien a ciento cincuenta veces el valor diario de la Unidad de Medida y Actualización, la cual podrá duplicarse o triplicarse en cada ocasión, hasta alcanzar dos mil veces el valor diario de la Unidad de Medida y\nActualización, en caso de renuencia al cumplimiento del mandato respectivo;\nII. Solicitar el auxilio de la fuerza pública de cualquier orden de gobierno, los que deberán de atender de inmediato el requerimiento de la autoridad; o\nIII. Arresto hasta por treinta y seis horas.\nLey de Responsabilidades Administrativas del Estado de Baja California. Página 36\nArtículo 98. La Auditoría Superior, investigará y, en su caso substanciarán en los términos que determina esta Ley, los procedimientos de responsabilidad administrativa correspondientes. Asimismo, en los casos que procedan, presentarán la denuncia correspondiente ante el Ministerio Público competente.\nArtículo 99. En caso de que la Auditoría Superior tenga conocimiento de la presunta comisión de Faltas administrativas distintas a las señaladas en el artículo anterior, darán vista a la Secretaría, Sindicaturas o a los Órganos internos de control que correspondan, a efecto de que procedan a realizar la investigación correspondiente.\nCapítulo III\nDe la calificación de Faltas administrativas\nArtículo 100. Concluidas las diligencias de investigación, las autoridades investigadoras procederán al análisis de los hechos, así como de la información recabada, a efecto de determinar la existencia o inexistencia de actos u omisiones que la ley señale como falta administrativa y, en su caso, calificarla como grave o no grave.\nUna vez calificada la conducta en los términos del párrafo anterior, se incluirá la misma en el Informe de Presunta Responsabilidad Administrativa y este se presentará ante la autoridad substanciadora a efecto de iniciar el procedimiento de responsabilidad administrativa.\nSi no se encontraren elementos suficientes para demostrar la existencia de la infracción y la presunta responsabilidad del infractor, se emitirá un acuerdo de conclusión y archivo del expediente, sin perjuicio de que pueda abrirse nuevamente la investigación si se presentan nuevos indicios o pruebas y no hubiere prescrito la facultad para sancionar. Dicha determinación, en su caso, se notificará a los Servidores Públicos y particulares sujetos a la investigación, así como a los denunciantes cuando éstos fueren identificables, dentro los diez días hábiles siguientes a su emisión.\nArtículo 101. Las autoridades substanciadoras, o en su caso, las resolutoras se o de imponer sanciones administrativas a un servidor público, según sea el caso, cuando de procedimiento referido, adviertan que no existe daño ni perjuicio a la Hacienda Pública\nEstatal o Municipal, o al patrimonio de los entes públicos y que se actualiza alguna de las siguientes hipótesis:\nI. Que la actuación del servidor público, en la atención, trámite o resolución de asuntos a su cargo, esté referida a una cuestión de criterio o arbitrio opinable o debatible, en la que válidamente puedan sustentarse diversas soluciones, siempre que la conducta o\nLey de Responsabilidades Administrativas del Estado de Baja California. Página 37 que tomó en cuenta el servidor público en la decisión que adoptó; o\nII. Que el acto u omisión fue corregido o subsanado de manera espontánea por el servidor público o implique error manifiesto y en cualquiera de estos supuestos, los efectos que, en su caso, se hubieren producido, desaparecieron.\nLa autoridad investigadora o el denunciante, podrán impugnar la abstención, en los términos de lo dispuesto por el siguiente Capítulo.\nCapítulo IV\nImpugnación de la calificación de faltas no graves\nArtículo 102. La calificación de los hechos como faltas administrativas no graves que realicen las Autoridades investigadoras, será notificada al Denunciante, cuando este fuere identificable. Además de establecer la calificación que se le haya dado a la presunta falta, la notificación también contendrá de manera expresa la forma en que el notificado podrá acceder al Expediente de presunta responsabilidad administrativa.\nLa calificación y la abstención a que se refiere el artículo 101, podrán ser impugnadas, en su caso, por el Denunciante, mediante el recurso de inconformidad conforme al presente\nCapítulo. La presentación del recurso tendrá como efecto que no se inicie el procedimiento de responsabilidad administrativa hasta en tanto este sea resuelto.\nArtículo 103. El plazo para la presentación del recurso será de cinco días hábiles, contados a partir de la notificación de la resolución impugnada.\nArtículo 104. El escrito de impugnación deberá presentarse ante la Autoridad investigadora que hubiere hecho la calificación de la falta administrativa como no grave, debiendo expresar los motivos por los que se estime indebida dicha calificación.\nInterpuesto el recurso, la autoridad investigadora deberá correr traslado, adjuntando el expediente integrado y un informe en el que justifique la calificación impugnada a la Sala\nEspecializada.\nArtículo 105. En caso de que el escrito por el que se interponga el recurso de inconformidad fuera obscuro o irregular, la Sala Especializada requerirá al promovente para que subsane las deficiencias o realice las aclaraciones que corresponda, para lo cual le concederán un término de cinco días hábiles. De no subsanar las deficiencias o aclaraciones en el plazo antes señalado el recurso se tendrá por no presentado.\nArtículo 106. En caso de que la Sala Especializada tenga por subsanadas las deficiencias o por aclarado el escrito por el que se interponga el recurso de inconformidad; o bien, cuando el escrito cumpla con los requisitos señalados en el artículo 109 de esta Ley, Ley de Responsabilidades Administrativas del Estado de Baja California. Página 38 días hábiles manifieste lo que a su derecho convenga.\nArtículo 107. Una vez subsanadas las deficiencias o aclaraciones o si no existieren, días hábiles.\nArtículo 108. El recurso será resuelto tomando en consideración la investigación que conste en el Expediente de presunta responsabilidad administrativa y los elementos que aporten el Denunciante o el presunto infractor. Contra la resolución que se dicte no procederá recurso alguno.\nArtículo 109. El escrito por el cual se interponga el recurso de inconformidad deberá contener los siguientes requisitos:\nI. Nombre y domicilio del recurrente;\nII. La fecha en que se le notificó la calificación en términos de este Capítulo;\nIII. Las razones y fundamentos por los que, a juicio del recurrente, la calificación del acto es indebida; y\nIV. Firma autógrafa del recurrente. La omisión de este requisito dará lugar a que no se tenga por presentado el recurso, por lo que en este caso no será aplicable lo dispuesto en el artículo 105 de esta Ley.\nAsimismo, el recurrente acompañará su escrito con las pruebas que estime pertinentes para sostener las razones y fundamentos expresados en el recurso de inconformidad. La satisfacción de este requisito no será necesaria si los argumentos contra la calificación de los hechos versan solo sobre aspectos de derecho.\nArtículo 110. La resolución del recurso consistirá en:\nI. Confirmar la calificación o abstención; o\nII. Dejar sin efectos la calificación o abstención, para lo cual la autoridad encargada para resolver el recurso, estará facultada para recalificar el acto u omisión; o bien ordenar se inicie el procedimiento correspondiente.\nTÍTULO SEGUNDO\nCapítulo I\nLey de Responsabilidades Administrativas del Estado de Baja California. Página 39\nSección Primera\nPrincipios, interrupción de la prescripción, partes y autorizaciones\nArtículo 111. En los procedimientos de responsabilidad administrativa deberán observarse los principios de legalidad, presunción de inocencia, imparcialidad, objetividad, congruencia, exhaustividad, verdad material y respeto a los derechos humanos.\nArtículo 112. El procedimiento de responsabilidad administrativa dará inicio cuando las autoridades substanciadoras, en el ámbito de su competencia, admitan el Informe de\nPresunta Responsabilidad Administrativa.\nArtículo 113. La admisión del Informe de Presunta Responsabilidad Administrativa interrumpirá los plazos de prescripción señalados en el artículo 74 de esta Ley y fijará la materia del procedimiento de responsabilidad administrativa.\nArtículo 114. En caso de que con posterioridad a la admisión del informe las autoridades investigadoras adviertan la probable comisión de cualquier otra falta administrativa imputable a la misma persona señalada como presunto responsable, deberán elaborar un diverso Informe de Presunta Responsabilidad Administrativa y promover el respectivo procedimiento de responsabilidad administrativa por separado, sin perjuicio de que, en el momento procesal oportuno, puedan solicitar su acumulación.\nArtículo 115. La autoridad a quien se encomiende la substanciación y, en su caso, resolución del procedimiento de responsabilidad administrativa, deberá ser distinto de aquél o aquellos encargados de la investigación. Para tal efecto, la Secretaría, Sindicaturas, los\nÓrganos internos de control, la Auditoría Superior, así como las unidades de responsabilidades de las empresas productivas del Estado, contarán con la estructura orgánica necesaria para realizar las funciones correspondientes a las autoridades investigadoras y substanciadoras, y garantizarán la independencia entre ambas en el ejercicio de sus funciones.\nArtículo 116. Son partes en el procedimiento de responsabilidad administrativa:\nI. La Autoridad investigadora;\nII. El servidor público señalado como presunto responsable de la Falta administrativa grave o no grave;\nIII. El particular, sea persona física o moral, señalado como presunto responsable en la comisión de Faltas de particulares; y\nIV. Los terceros, que son todos aquellos a quienes pueda afectar la resolución que se dicte en el procedimiento de responsabilidad administrativa, incluido el denunciante.\nLey de Responsabilidades Administrativas del Estado de Baja California. Página 40\nArtículo 117. Las partes señaladas en las fracciones II, III y IV del artículo anterior podrán autorizar para oír notificaciones en su nombre, a una o varias personas con capacidad legal, quienes quedarán facultadas para interponer los recursos que procedan, ofrecer e intervenir en el desahogo de pruebas, alegar en las audiencias, pedir se dicte realizar cualquier acto que resulte ser necesario para la defensa de los derechos del autorizante, pero no podrá substituir o delegar dichas facultades en un tercero.\nLas personas autorizadas conforme a la primera parte de este párrafo, deberán acreditar encontrarse legalmente autorizadas para ejercer la profesión de abogado o licenciado en derecho, debiendo proporcionar los datos correspondientes en el escrito en que se otorgue dicha autorización y mostrar la cédula profesional o carta de pasante para la práctica de la abogacía en las diligencias de prueba en que intervengan, en el entendido que el autorizado que no cumpla con lo anterior, perderá la facultad a que se refiere este artículo en perjuicio de la parte que lo hubiere designado, y únicamente tendrá las que se indican en el penúltimo párrafo de este artículo.\nLas personas autorizadas en los términos de este artículo, serán responsables de los daños y perjuicios que causen ante el que los autorice, de acuerdo a las disposiciones aplicables del Código Civil del Estado, relativas al mandato y las demás conexas. Los autorizados podrán renunciar a dicha calidad, mediante escrito presentado a la autoridad resolutora, haciendo saber las causas de la renuncia.\nLas partes podrán designar personas solamente autorizadas para oír notificaciones e imponerse de los autos, a cualquiera con capacidad legal, quien no gozará de las demás facultades a que se refieren los párrafos anteriores.\nLas partes deberán señalar expresamente el alcance de las autorizaciones que concedan. El acuerdo donde se resuelvan las autorizaciones se deberá expresar con toda claridad el alcance con el que se reconoce la autorización otorgada.\nTratándose de personas morales estas deberán comparecer en todo momento a través de sus representantes legales, o por las personas que estos designen, pudiendo, asimismo, designar autorizados en términos de este artículo.\nArtículo 118. En lo que no se oponga a lo dispuesto en el procedimiento de responsabilidad administrativa, será de aplicación supletoria lo dispuesto en la Ley del conforme la materia y según corresponda.\nArtículo 119. En los procedimientos de responsabilidad administrativa se estimarán como días hábiles todos los del año, con excepción de aquellos días que, por virtud de ley, algún decreto o disposición administrativa, se determine como inhábil, durante los que no se\nLey de Responsabilidades Administrativas del Estado de Baja California. Página 41 practicará actuación alguna. Serán horas hábiles las que medien entre las 9:00 y las 18:00 horas. Las autoridades substanciadoras o resolución del asunto, podrán habilitar días y horas inhábiles para la práctica de aquellas diligencias que, a su juicio, lo requieran.\nSección Segunda\nMedios de apremio\nArtículo 120. Las autoridades substanciadoras o resolutoras, podrán hacer uso de los siguientes medios de apremio para hacer cumplir sus determinaciones:\nI. Multa de cien a ciento cincuenta veces el valor diario de la Unidad de Medida y\nActualización, la cual podrá duplicarse o triplicarse en cada ocasión, hasta alcanzar dos mil veces el valor diario de la Unidad de Medida y Actualización, en caso de renuencia al cumplimiento del mandato respectivo;\nII. Arresto hasta por treinta y seis horas; y\nIII. Solicitar el auxilio de la fuerza pública de cualquier orden de gobierno, los que deberán de atender de inmediato el requerimiento de la autoridad.\nArtículo 121. Las medidas de apremio podrán ser decretadas sin seguir rigurosamente el orden en que han sido enlistadas en el artículo que antecede, o bien, decretar la aplicación de más de una de ellas, para lo cual la autoridad deberá ponderar las circunstancias del caso.\nArtículo 122. En caso de que pese a la aplicación de las medidas de apremio no se logre el cumplimiento de las determinaciones ordenadas, se dará vista a la autoridad penal competente para que proceda en los términos de la legislación aplicable.\nSección Tercera\nMedidas cautelares\nArtículo 123. Las autoridades investigadoras podrán solicitar a la autoridad substanciadora o resolutora, que decrete aquellas medidas cautelares que:\nI. Eviten el ocultamiento o destrucción de pruebas;\nII. Impidan la continuación de los efectos perjudiciales de la presunta falta administrativa;\nIII. Eviten la obstaculización del adecuado desarrollo del procedimiento de responsabilidad administrativa;\nLey de Responsabilidades Administrativas del Estado de Baja California. Página 42\nIV. Eviten un daño irreparable a la Hacienda Pública Estatal o Municipal o al patrimonio de los entes públicos. al interés social o se contravengan disposiciones de orden público.\nArtículo 124. Podrán ser decretadas como medidas cautelares las siguientes:\nI. Suspensión temporal del servidor público señalado como presuntamente responsable del empleo, cargo o comisión que desempeñe. Dicha suspensión no prejuzgará ni será indicio de la responsabilidad que se le impute, lo cual se hará constar en la resolución en la que se decrete. Mientras dure la suspensión temporal se deberán decretar, al mismo tiempo, las medidas necesarias que le garanticen al presunto responsable mantener su mínimo vital y de sus dependientes económicos; así como aquellas que impidan que se le presente públicamente como responsable de la comisión de la falta que se le imputa. En el supuesto de que el servidor público suspendido temporalmente no resultare responsable de los actos que se le imputan, la dependencia o entidad donde preste sus servicios lo restituirán en el goce de sus derechos y le cubrirán las percepciones que debió recibir durante el tiempo en que se halló suspendido;\nII. Exhibición de documentos originales relacionados directamente con la presunta\nFalta administrativa;\nIII. Apercibimiento de multa de cien y hasta ciento cincuenta Unidades de Medida y Actualización, para conminar a los presuntos responsables y testigos, a presentarse el día y hora que se señalen para el desahogo de pruebas a su cargo, así como para señalar un domicilio para practicar cualquier notificación personal relacionada con la substanciación y resolución del procedimiento de responsabilidad administrativa;\nIV. Embargo precautorio de bienes; aseguramiento o intervención precautoria de negociaciones. Al respecto será aplicable de forma supletoria el Código Fiscal del Estado;\nV. Las que sean necesarias para evitar un daño irreparable a la Hacienda Pública\nEstatal o Municipal, o al patrimonio de los entes públicos, para lo cual las autoridades resolutoras del asunto, podrán solicitar el auxilio y colaboración de cualquier autoridad del país.\nArtículo 125. El otorgamiento de medidas cautelares se tramitará de manera incidental. El escrito en el que se soliciten se deberá señalar las pruebas cuyo ocultamiento o destrucción se pretende impedir; los efectos perjudiciales que produce la presunta falta administrativa; los actos que obstaculizan el adecuado desarrollo del procedimiento de responsabilidad administrativa; o bien, el daño irreparable a la Hacienda Pública Estatal o\nMunicipal, al patrimonio de los entes públicos, expresando los motivos por los cuales se solicitan las medidas cautelares y donde se justifique su pertinencia. En cualquier caso, se\nLey de Responsabilidades Administrativas del Estado de Baja California. Página 43 cautelares, para que, en su caso, se les dé vista del incidente respectivo.\nArtículo 126. Con el escrito por el que se soliciten las medidas cautelares se dará vista a todos aquellos que serán directamente afectados con las mismas, para que en un término de cinco días hábiles manifiesten lo que a su derecho convenga. Si la autoridad que conozca del incidente lo estima necesario, en el acuerdo de admisión podrá conceder provisionalmente las medidas cautelares solicitadas.\nArtículo 127. Transcurrido el plazo señalado en el artículo anterior la Autoridad resolutora dictará la resolución interlocutoria que corresponda dentro de los cinco días hábiles siguientes. En contra de dicha determinación no procederá recurso alguno.\nArtículo 128. Las medidas cautelares que tengan por objeto impedir daños a la\nHacienda Pública Estatal o Municipal, o bien, al patrimonio de los entes públicos sólo se suspenderán cuando el presunto responsable otorgue garantía suficiente de la reparación del daño y los perjuicios ocasionados.\nArtículo 129. Se podrá solicitar la suspensión de las medidas cautelares en cualquier momento del procedimiento, debiéndose justificar las razones por las que se estime innecesario que éstas continúen, para lo cual se deberá seguir el procedimiento incidental descrito en esta sección. Contra la resolución que niegue la suspensión de las medidas cautelares no procederá recurso alguno.\nSección Cuarta\nDe las pruebas\nArtículo 130. Para conocer la verdad de los hechos las autoridades resolutoras podrán valerse de cualquier persona o documento, ya sea que pertenezca a las partes o a terceros, sin más limitación que la de que las pruebas hayan sido obtenidas lícitamente, y con pleno respeto a los derechos humanos, solo estará excluida la confesional a cargo de las partes por absolución de posiciones.\nArtículo 131. Las pruebas serán valoradas atendiendo a las reglas de la lógica, la sana crítica y de la experiencia.\nArtículo 132. Las autoridades resolutoras recibirán por sí mismas las declaraciones de testigos y peritos, y presidirán todos los actos de prueba bajo su más estricta responsabilidad.\nArtículo 133. Las documentales emitidas por las autoridades en ejercicio de sus veracidad de los hechos a los que se refieran, salvo prueba en contrario.\nLey de Responsabilidades Administrativas del Estado de Baja California. Página 44\nArtículo 134. Las documentales privadas, las testimoniales, las inspecciones y las periciales y demás medios de prueba lícitos que se ofrezcan por las partes, solo harán guarden entre sí, de forma tal que generen convicción sobre la veracidad de los hechos.\nArtículo 135. Toda persona señalada como responsable de una falta administrativa tiene derecho a que se presuma su inocencia hasta que no se demuestre, más allá de toda duda razonable, su culpabilidad. Las autoridades investigadoras tendrán la carga de la prueba para demostrar la veracidad sobre los hechos que demuestren la existencia de tales faltas, así como la responsabilidad de aquellos a quienes se imputen las mismas. Quienes sean señalados como presuntos responsables de una falta administrativa no estarán obligados a confesar su responsabilidad, ni a declarar en su contra, por lo que su silencio no deberá ser considerado como prueba o indicio de su responsabilidad en la comisión de los hechos que se le imputan.\nArtículo 136. Las pruebas deberán ofrecerse en los plazos señalados en esta Ley.\nLas que se ofrezcan fuera de ellos no serán admitidas salvo que se trate de pruebas supervenientes, entendiéndose por tales, aquellas que se hayan producido con posterioridad al vencimiento del plazo para ofrecer pruebas; o las que se hayan producido antes, siempre que el que las ofrezca manifieste bajo protesta de decir verdad que no tuvo la posibilidad de conocer su existencia.\nArtículo 137. De toda prueba superveniente se dará vista a las partes por un término de tres días para que manifiesten lo que a su derecho convenga.\nArtículo 138. Los hechos notorios no serán objeto de prueba, pudiendo la autoridad que resuelva el asunto referirse a ellos aun cuando las partes no los hubieren mencionado.\nArtículo 139. En caso de que cualquiera de las partes hubiere solicitado la expedición de un documento o informe que obre en poder de cualquier persona o Ente público, y no se haya expedido sin causa justificada, la Autoridad resolutora del asunto ordenará que se expida la misma, para lo cual podrá hacer uso de los medios de apremio previstos en esta\nLey.\nArtículo 140. Cualquier persona, aun cuando no sea parte en el procedimiento, tiene de la verdad, por lo que deberán exhibir cualquier documento o cosa, o rendir su testimonio en el momento en que sea requerida para ello. Estarán exentos de tal obligación los ascendientes, descendientes, cónyuges y personas que tengan la obligación de mantener el secreto profesional, en los casos en que se trate de probar contra la parte con la que estén relacionados.\nLey de Responsabilidades Administrativas del Estado de Baja California. Página 45\nArtículo 141. El derecho nacional no requiere ser probado. El derecho extranjero podrá ser objeto de prueba en cuanto su existencia, validez, contenido y alcance, para lo conducto de la Secretaría de Relaciones Exteriores, sin perjuicio de las pruebas que al respecto puedan ofrecer las partes.\nArtículo 142. Las autoridades resolutoras del asunto podrán ordenar la realización de diligencias para mejor proveer, sin que por ello se entienda abierta de nuevo la investigación, disponiendo la práctica o ampliación de cualquier diligencia probatoria, siempre que resulte pertinente para el conocimiento de los hechos relacionados con la existencia de la Falta administrativa y la responsabilidad de quien la hubiera cometido. Con las pruebas que se alleguen al procedimiento derivadas de diligencias para mejor proveer se dará vista a las partes por el término de tres días para que manifiesten lo que a su derecho convenga, pudiendo ser objetadas en cuanto a su alcance y valor probatorio en la vía incidental.\nArtículo 143. Cuando la preparación o desahogo de las pruebas deba tener lugar fuera del ámbito jurisdiccional de la Autoridad resolutora del asunto, podrá solicitar, mediante exhorto o carta rogatoria, la colaboración de las autoridades competentes del lugar.\nTratándose de cartas rogatorias se estará a lo dispuesto en los tratados y convenciones de los que México sea parte.\nSección Quinta\nDe las pruebas en particular\nArtículo 144. La prueba testimonial estará a cargo de todo aquél que tenga conocimiento de los hechos que las partes deban probar, quienes, por ese hecho, se encuentran obligados a rendir testimonio.\nArtículo 145. Las partes podrán ofrecer los testigos que consideren necesarios para acreditar los hechos que deban demostrar. La Autoridad resolutora podrá limitar el número de testigos si considera que su testimonio se refiere a los mismos hechos, para lo cual, en el acuerdo donde así lo determine, deberá motivar dicha resolución.\nArtículo 146. La presentación de los testigos será responsabilidad de la parte que los ofrezca. Solo serán citados por la Autoridad resolutora cuando su oferente manifieste que está imposibilitado para hacer que se presenten, en cuyo caso, se dispondrá la citación del testigo mediante la aplicación de los medios de apremio señalados en esta Ley.\nArtículo 147. Quienes por motivos de edad o salud no pudieran presentarse a rendir su testimonio ante la Autoridad resolutora, se les tomará su testificación en su domicilio o en el lugar donde se encuentren, pudiendo asistir las partes a dicha diligencia.\nArtículo 148. Los representantes de elección popular; magistrados y jueces del Poder\nJudicial del Estado, los consejeros del Consejo de la Judicatura del Estado, los Servidores\nLey de Responsabilidades Administrativas del Estado de Baja California. Página 46\nPúblicos que sean ratificados o nombrados con la intervención del Congreso del Estado, los\nGobiernos Municipales, los titulares de los organismos a los que la Constitución les otorgue autonomía, rendirán su declaración por oficio, para lo cual les serán enviadas por escrito las preguntas y repreguntas correspondientes.\nArtículo 149. Con excepción de lo dispuesto en el artículo anterior, las preguntas que se dirijan a los testigos se formularán verbal y directamente por las partes o por quienes se encuentren autorizadas para hacerlo.\nArtículo 150. La parte que haya ofrecido la prueba será la primera que interrogará al testigo, siguiendo las demás partes en el orden que determine la Autoridad resolutora del asunto.\nArtículo 151. La Autoridad resolutora podrá interrogar libremente a los testigos, con la finalidad de esclarecer la verdad de los hechos.\nArtículo 152. Las preguntas y repreguntas que se formulen a los testigos, deben referirse a la Falta administrativa que se imputa a los presuntos responsables y a los hechos que les consten directamente a los testigos. Deberán expresarse en términos claros y no ser insidiosas, ni contener en ellas la respuesta. Aquellas preguntas que no satisfagan estos requisitos serán desechadas, aunque se asentarán textualmente en el acta respectiva.\nArtículo 153. Antes de rendir su testimonio, a los testigos se les tomará la protesta para conducirse con verdad, y serán apercibidos de las penas en que incurren aquellos que declaran con falsedad ante autoridad distinta a la judicial. Se hará constar su nombre, domicilio, nacionalidad, lugar de residencia, ocupación y domicilio, si es pariente por consanguinidad o afinidad de alguna de las partes, si mantiene con alguna de ellas relaciones de amistad o de negocios, o bien, si tiene alguna enemistad o animadversión hacia cualquiera de las partes. Al terminar de testificar, los testigos deberán manifestar la razón de su dicho, es decir, el por qué saben y les consta lo que manifestaron en su testificación.\nArtículo 154. Los testigos serán interrogados por separado, debiendo la Autoridad resolutora tomar las medidas pertinentes para evitar que entre ellos se comuniquen. Los testigos ofrecidos por una de las partes se rendirán el mismo día, sin excepción, para lo cual se podrán habilitar días y horas inhábiles. De la misma forma se procederá con los testigos de las demás partes, hasta que todos los llamados a rendir su testimonio sean examinados por las partes y la Autoridad resolutora del asunto.\nArtículo 155. Cuando el testigo desconozca el idioma español, o no lo sepa leer, la\nAutoridad resolutora del asunto designará un traductor, debiendo, en estos casos, asentar la declaración del absolvente en español, así como en la lengua o dialecto del absolvente, para lo cual se deberá auxiliar del traductor que dicha autoridad haya designado. Tratándose de\nLey de Responsabilidades Administrativas del Estado de Baja California. Página 47 personas que presenten alguna discapacidad visual, auditiva o de locución se deberá los procedimientos de responsabilidad administrativa en que intervengan.\nArtículo 156. Las preguntas que se formulen a los testigos, así como sus correspondientes respuestas, se harán constar literalmente en el acta respectiva. Deberán firmar dicha acta las partes y los testigos, pudiendo previamente leer la misma, o bien, solicitar que les sea leída por el funcionario que designe la Autoridad resolutora del asunto.\nPara las personas que presenten alguna discapacidad visual, auditiva o de locución, se adoptarán las medidas pertinentes para que puedan acceder a la información contenida en el acta antes de firmarla o imprimir su huella digital. En caso de que las partes no pudieran o quisieran firmar el acta o imprimir su huella digital, la firmará la autoridad que deba resolver el asunto haciendo constar tal circunstancia.\nArtículo 157. Los testigos podrán ser tachados por las partes en la vía incidental en los términos previstos en esta Ley.\nArtículo 158. Son pruebas documentales todas aquellas en la que conste información de manera escrita, visual o auditiva, sin importar el material, formato o dispositivo en la que esté plasmada o consignada. La Autoridad resolutora del asunto podrá solicitar a las partes que aporten los instrumentos tecnológicos necesarios para la apreciación de los documentos ofrecidos cuando éstos no estén a su disposición. En caso de que las partes no cuenten con tales instrumentos, dicha autoridad podrá solicitar la colaboración del Ministerio Público, o bien, de las instituciones públicas de educación superior, para que le permitan el acceso al instrumental tecnológico necesario para la apreciación de las pruebas documentales.\nArtículo 159. Son documentos públicos, todos aquellos que sean expedidos por los servidores públicos en el ejercicio de sus funciones. Son documentos privados los que no cumplan con la condición anterior.\nArtículo 160. Los documentos que consten en un idioma extranjero o en cualquier lengua o dialecto, deberán ser traducidos en idioma español castellano. Para tal efecto, la ella misma. Las objeciones que presenten las partes a la traducción se tramitarán y resolverán en la vía incidental.\nArtículo 161. Los documentos privados se presentarán en original, y, cuando formen parte de un expediente o legajo, se exhibirán para que se compulse la parte que señalen los interesados.\nArtículo 162. Podrá pedirse el cotejo de firmas, letras o huellas digitales, siempre que se niegue o se ponga en duda la autenticidad de un documento público o privado. La\nLey de Responsabilidades Administrativas del Estado de Baja California. Página 48 el cotejo, o bien, pedirá a la Autoridad resolutora que cite al autor de la firma, letras o huella digital, para que en su presencia estampe aquellas necesarias para el cotejo.\nArtículo 163. Se considerarán indubitables para el cotejo:\nI. Los documentos que las partes reconozcan como tales, de común acuerdo;\nII. Los documentos privados cuya letra o firma haya sido reconocida ante la\nAutoridad resolutora del asunto, por aquél a quien se atribuya la dudosa;\nIII. Los documentos cuya letra, firma o huella digital haya sido declarada en la vía judicial como propia de aquél a quien se atribuya la dudosa, salvo que dicha declaración se haya hecho en rebeldía; y\nIV. Las letras, firmas o huellas digitales que haya sido puestas en presencia de la\nAutoridad resolutora en actuaciones propias del procedimiento de responsabilidad, por la parte cuya firma, letra o huella digital se trate de comprobar.\nArtículo 164. La Autoridad substanciadora o resolutora podrá solicitar la colaboración del ministerio público, para determinar la autenticidad de cualquier documento que sea cuestionado por las partes.\nArtículo 165. Se reconoce como prueba la información generada o comunicada que conste en medios electrónicos, ópticos o en cualquier otra tecnología.\nPara valorar la fuerza probatoria de la información a que se refiere el párrafo anterior, se estimará primordialmente la fiabilidad del método en que haya sido generada, comunicada, recibida o archivada y, en su caso, si es posible atribuir a las personas obligadas el contenido de la información relativa y ser accesible para su ulterior consulta.\nCuando la ley requiera que un documento sea conservado y presentado en su forma original, ese requisito quedará satisfecho si se acredita que la información generada, comunicada, recibida o archivada por medios electrónicos, ópticos o de cualquier otra tecnología, se ha mantenido íntegra e inalterada a partir del momento en que se generó por primera vez en su forma definitiva y ésta pueda ser accesible para su ulterior consulta.\nArtículo 166. Las partes podrán objetar el alcance y valor probatorio de los en la vía incidental prevista en esta Ley.\nArtículo 167. La prueba pericial tendrá lugar cuando para determinar la verdad de los hechos sea necesario contar con los conocimientos especiales de una ciencia, arte, técnica, oficio, industria o profesión.\nLey de Responsabilidades Administrativas del Estado de Baja California. Página 49\nArtículo 168. Quienes sean propuestos como peritos deberán tener título en la ciencia, arte, técnica, oficio, industria o profesión a que pertenezca la cuestión sobre la que han de rendir parecer, siempre que la ley exija dicho título para su ejercicio. En caso contrario, podrán ser autorizados por la autoridad resolutora para actuar como peritos, sobre la cuestión.\nArtículo 169. Las partes ofrecerán sus peritos indicando expresamente la ciencia, arte, técnica, oficio, industria o profesión sobre la que deberá practicarse la prueba, así como los puntos y las cuestiones sobre las que versará la prueba.\nArtículo 170. En el acuerdo en que se resuelva la admisión de la prueba, se requerirá al oferente para que presente a su perito el día y hora que se señale por la Autoridad resolutora del asunto, a fin de que acepte y proteste desempeñar su cargo de conformidad con la ley. En caso de no hacerlo, se tendrá por no ofrecida la prueba.\nArtículo 171. Al admitir la prueba pericial, la Autoridad resolutora del asunto dará vista a las demás partes por el término de tres días para que propongan la ampliación de otros puntos y cuestiones para que el perito determine.\nArtículo 172. En caso de que el perito haya aceptado y protestado su cargo, la\nAutoridad resolutora del asunto fijará prudentemente un plazo para que el perito presente el dictamen correspondiente. En caso de no presentarse dicho dictamen, la prueba se declarará desierta.\nArtículo 173. Las demás partes del procedimiento administrativo, podrán a su vez designar un perito para que se pronuncie sobre los aspectos cuestionados por el oferente de la prueba, así como por los ampliados por las demás partes, debiéndose proceder en los términos descritos en el artículo 169 de esta Ley.\nArtículo 174. Presentados los dictámenes por parte de los peritos, la autoridad resolutora convocará a los mismos a una audiencia donde las partes y la autoridad misma, podrán solicitarles las aclaraciones y explicaciones que estimen conducentes.\nArtículo 175. Las partes absolverán los costos de los honorarios de los peritos que ofrezcan.\nArtículo 176. De considerarlo pertinente, la Autoridad resolutora del asunto podrá solicitar la colaboración del Ministerio Público, o bien, de instituciones públicas de educación superior, para que, a través de peritos en la ciencia, arte, técnica, industria, oficio o profesión adscritos a tales instituciones, emitan su dictamen sobre aquellas cuestiones o puntos controvertidos por las partes en el desahogo de la prueba pericial, o sobre aquellos aspectos que estime necesarios para el esclarecimiento de los hechos.\nLey de Responsabilidades Administrativas del Estado de Baja California. Página 50\nArtículo 177. La inspección en el procedimiento de responsabilidad administrativa, estará a cargo de la Autoridad resolutora, y procederá cuando así sea solicitada por cualquiera de las partes, o bien, cuando de oficio lo estime conducente dicha autoridad para el esclarecimiento de los hechos, siempre que no se requieran conocimientos especiales para la apreciación de los objetos, cosas, lugares o hechos que se pretendan observar mediante la inspección.\nArtículo 178. Al ofrecer la prueba de inspección, su oferente deberá precisar los objetos, cosas, lugares o hechos que pretendan ser observados mediante la intervención de la Autoridad resolutora del asunto.\nArtículo 179. Antes de admitir la prueba de inspección, la autoridad resolutora dará vista a las demás partes para que manifiesten lo que a su derecho convenga y, en su caso, propongan la ampliación de los objetos, cosas, lugares o hechos que serán materia de la inspección.\nArtículo 180. Para el desahogo de la prueba de inspección, la autoridad resolutora citará a las partes en el lugar donde se llevará a cabo esta, quienes podrán acudir para hacer las observaciones que estimen oportunas.\nArtículo 181. De la inspección realizada se levantará un acta que deberá ser firmada por quienes en ella intervinieron. En caso de no querer hacerlo, o estar impedidos para ello, la Autoridad resolutora del asunto firmará el acta respectiva haciendo constar tal circunstancia.\nSección Sexta\nDe los incidentes\nArtículo 182. Aquellos incidentes que no tengan señalado una tramitación especial se promoverán mediante un escrito de cada parte, y tres días para resolver. En caso de que se ofrezcan pruebas, se hará en el escrito de presentación respectivo. Si tales pruebas no tienen relación con los hechos controvertidos en el incidente, o bien, si la materia del incidente solo versa sobre puntos de derecho, la Autoridad substanciadora o resolutora del asunto, según sea el caso, desechará las pruebas ofrecidas. En caso de admitir las pruebas donde se recibirán las pruebas, se escucharán los alegatos de las partes y se les citará para oír la resolución que corresponda.\nArtículo 183. Cuando los incidentes tengan por objeto tachar testigos, o bien, objetar pruebas en cuanto su alcance y valor probatorio, será necesario que quien promueva el incidente señale con precisión las razones que tiene para ello, así como las pruebas que sustenten sus afirmaciones. En caso de no hacerlo así, el incidente será desechado de plano.\nLey de Responsabilidades Administrativas del Estado de Baja California. Página 51\nArtículo 184. Los incidentes que tengan por objeto reclamar la nulidad del emplazamiento, interrumpirán la continuación del procedimiento.\nSección Séptima\nDe la acumulación\nArtículo 185. La acumulación será procedente:\nI. Cuando a dos o más personas se les atribuya la comisión de una o más Faltas administrativas que se encuentren relacionadas entre sí con la finalidad de facilitar la ejecución o asegurar la consumación de cualquiera de ellas;\nII. Cuando se trate de procedimientos de responsabilidad administrativa donde se imputen dos a más Faltas administrativas a la misma persona, siempre que se encuentren relacionadas entre sí, con la finalidad de facilitar la ejecución o asegurar la consumación de cualquiera de ellas.\nArtículo 186. Cuando sea procedente la acumulación, será competente para conocer del asunto aquella Autoridad substanciadora que tenga conocimiento de la falta cuya sanción sea mayor. Si la falta administrativa amerita la misma sanción, será competente la autoridad encargada de substanciar el asunto que primero haya admitido el Informe de\nPresunta Responsabilidad Administrativa.\nSección Octava\nDe las notificaciones\nArtículo 187. Las notificaciones se tendrán por hechas a partir del día hábil siguiente en que surtan sus efectos.\nArtículo 188. Las notificaciones podrán ser hechas a las partes personalmente o por los estrados de la Autoridad substanciadora o, en su caso, de la resolutora.\nArtículo 189. Las notificaciones personales surtirán sus efectos al día hábil siguiente en que se realicen. Las autoridades substanciadoras o resolutoras del asunto, según corresponda, podrán solicitar mediante exhorto, la colaboración de la Secretaría, Sindicaturas, Órganos internos de control, o del Tribunal, para realizar las notificaciones lugares que se hallen fuera de su jurisdicción.\nArtículo 190. Las notificaciones por estrados surtirán sus efectos dentro de los tres días hábiles siguientes en que sean colocados en los lugares destinados para tal efecto. La\nAutoridad substanciadora o resolutora del asunto, deberá certificar el día y hora en que hayan sido colocados los acuerdos en los estrados respectivos.\nLey de Responsabilidades Administrativas del Estado de Baja California. Página 52\nArtículo 191. Cuando las leyes orgánicas del Tribunal dispongan la notificación electrónica, se aplicará lo que al respecto se establezca en ellas.\nArtículo 192. Cuando las notificaciones deban realizarse en el extranjero, las rogatoria, para lo cual deberá estarse a lo dispuesto en las convenciones o instrumentos internacionales de los que México sea parte.\nArtículo 193. Serán notificados personalmente:\nI. El emplazamiento al presunto o presuntos responsables para que comparezca al procedimiento de responsabilidad administrativa. Para que el emplazamiento se entienda realizado se les deberá entregar copia certificada del Informe de Presunta Responsabilidad\nAdministrativa y del acuerdo por el que se admite; de las constancias del Expediente de presunta Responsabilidad Administrativa integrado en la investigación, así como de las demás constancias y pruebas que hayan aportado u ofrecido las autoridades investigadoras para sustentar el Informe de Presunta Responsabilidad Administrativa;\nII. El acuerdo de admisión del Informe de Presunta Responsabilidad\nAdministrativa;\nIII. El acuerdo por el que se ordene la citación a la audiencia inicial del procedimiento de responsabilidad administrativa;\nIV. En el caso de faltas administrativas graves, el acuerdo por el que remiten las constancias originales del expediente del procedimiento de responsabilidad administrativa al\nTribunal encargado de resolver el asunto;\nV. Los acuerdos por lo que se aperciba a las partes o terceros, con la imposición de medidas de apremio;\nVI. La resolución definitiva que se pronuncie en el procedimiento de responsabilidad administrativa; y\nVII. Las demás que así se determinen en la ley, o que las autoridades de sus resoluciones.\nSección Novena\nArtículo 194. El Informe de Presunta Responsabilidad Administrativa será emitido por las Autoridades investigadoras, el cual deberá contener los siguientes elementos:\nLey de Responsabilidades Administrativas del Estado de Baja California. Página 53\nI. El nombre de la Autoridad investigadora;\nII. El domicilio de la Autoridad investigadora para oír y recibir notificaciones;\nIII. El nombre o nombres de los funcionarios que podrán imponerse de los autos del expediente de responsabilidad administrativa por parte de la Autoridad investigadora, precisando el alcance que tendrá la autorización otorgada;\nIV. El nombre y domicilio del servidor público a quien se señale como presunto responsable, así como el Ente público al que se encuentre adscrito y el cargo que ahí desempeñe. En caso de que los presuntos responsables sean particulares, se deberá señalar su nombre o razón social, así como el domicilio donde podrán ser emplazados;\nV. La narración lógica y cronológica de los hechos que dieron lugar a la comisión de la presunta Falta administrativa;\nVI. La infracción que se imputa al señalado como presunto responsable, señalando con claridad las razones por las que se considera que ha cometido la falta;\nVII. Las pruebas que se ofrecerán en el procedimiento de responsabilidad administrativa, para acreditar la comisión de la Falta administrativa, y la responsabilidad que se atribuye al señalado como presunto responsable, debiéndose exhibir las pruebas documentales que obren en su poder, o bien, aquellas que, no estándolo, se acredite con el acuse de recibo correspondiente debidamente sellado, que las solicitó con la debida oportunidad;\nVIII. La solicitud de medidas cautelares, de ser el caso; y\nIX. Firma autógrafa de Autoridad investigadora.\nArtículo 195. En caso de que la Autoridad substanciadora advierta que el Informe de\nPresunta Responsabilidad Administrativa adolece de alguno o algunos de los requisitos señalados en el artículo anterior, o que la narración de los hechos fuere obscura o imprecisa, prevendrá a la Autoridad investigadora para que los subsane en un término de tres días. En caso de no hacerlo se tendrá por no presentado dicho informe, sin perjuicio de que la la Falta administrativa en cuestión no hubiera prescrito.\nSección Décima\nDe la improcedencia y el sobreseimiento\nArtículo 196. Son causas de improcedencia del procedimiento de responsabilidad administrativa, las siguientes:\nLey de Responsabilidades Administrativas del Estado de Baja California. Página 54\nI. Cuando la falta administrativa haya prescrito;\nII. Cuando los hechos o las conductas materia del procedimiento no fueran de competencia de las autoridades substanciadoras o resolutoras del asunto. En este caso, mediante oficio, el asunto se deberá hacer del conocimiento a la autoridad que se estime competente;\nIII. Cuando las faltas administrativas que se imputen al presunto responsable ya hubieran sido objeto de una resolución que haya causado ejecutoria pronunciada por las autoridades resolutoras del asunto, siempre que el señalado como presunto responsable sea el mismo en ambos casos;\nIV. Cuando de los hechos que se refieran en el Informe de Presunta\nResponsabilidad Administrativa, no se advierta la comisión de Faltas administrativas; y\nV. Cuando se omita acompañar el Informe de Presunta Responsabilidad\nAdministrativa.\nArtículo 197. Procederá el sobreseimiento en los casos siguientes:\nI. Cuando se actualice o sobrevenga cualquiera de las causas de improcedencia previstas en esta Ley;\nII. Cuando por virtud de una reforma legislativa, la Falta administrativa que se imputa al presunto responsable haya quedado derogada; o\nIII. Cuando el señalado como presunto responsable muera durante el procedimiento de responsabilidad administrativa.\nCuando las partes tengan conocimiento de alguna causa de sobreseimiento, la comunicarán de inmediato a la Autoridad substanciadora o resolutora, según corresponda, y de ser posible, acompañarán las constancias que la acrediten.\nSección Décimo Primera\nDe las audiencias\nArtículo 198. Las audiencias que se realicen en el procedimiento de responsabilidad administrativa, se llevarán de acuerdo con las siguientes reglas:\nI. Serán públicas;\nII. No se permitirá la interrupción de la audiencia por parte de persona alguna, sea por los que intervengan en ella o ajenos a la misma. La autoridad a cargo de la dirección de apremio que se prevén en esta Ley, e incluso estará facultado para ordenar el desalojo de\nLey de Responsabilidades Administrativas del Estado de Baja California. Página 55 las personas ajenas al procedimiento del local donde se desarrolle la audiencia, cuando a su juicio resulte conveniente para el normal desarrollo y continuación de la misma, para lo cual podrá solicitar el auxilio de la fuerza pública, debiendo hacer constar en el acta respectiva los motivos que tuvo para ello;\nIII. Quienes actúen como secretarios, bajo la responsabilidad de la autoridad encargada de la dirección de la audiencia, deberán hacer constar el día, lugar y hora en que principie la audiencia, la hora en la que termine, así como el nombre de las partes, peritos y testigos y personas que hubieren intervenido en la misma, dejando constancia de los incidentes que se hubieren desarrollado durante la audiencia.\nArtículo 199. Las autoridades substanciadoras o resolutoras del asunto tienen el deber de mantener el buen orden y de exigir que se les guarde el respeto y la consideración debidos, por lo que tomarán, de oficio o a petición de parte, todas las medidas necesarias establecidas en la ley, tendientes a prevenir o a sancionar cualquier acto contrario al respeto debido hacia ellas y al que han de guardarse las partes entre sí, así como las faltas de decoro y probidad, pudiendo requerir el auxilio de la fuerza pública.\nCuando la infracción llegare a tipificar un delito, se procederá contra quienes lo cometieren, con arreglo a lo dispuesto en la legislación penal.\nSección Décimo Segunda\nDe las actuaciones y resoluciones\nArtículo 200. Los expedientes se formarán por las autoridades substanciadoras o, en su caso, resolutoras del asunto con la colaboración de las partes, terceros y quienes intervengan en los procedimientos conforme a las siguientes reglas:\nI. Todos los escritos que se presenten deberán estar escritos en idioma español o lengua nacional y estar firmados o contener su huella digital, por quienes intervengan en ellos. En caso de que no supieren o pudieren firmar bastará que se estampe la huella digital, o bien, podrán pedir que firme otra persona a su ruego y a su nombre debiéndose señalar tal circunstancia. En este último caso se requerirá que el autor de la promoción comparezca personalmente ante la Autoridad substanciadora o resolutora, según sea el caso, a ratificar su escrito dentro de los tres días siguientes, de no comparecer se tendrá por no presentado dicho escrito;\nII. Los documentos redactados en idioma extranjero, se acompañarán con su debida traducción, de la cual se dará vista a las partes para que manifiesten lo que a su derecho convenga;\nIII. En toda actuación las cantidades y fechas se escribirán con letra, y no se emplearán abreviaturas, ni se rasparán las frases equivocadas, sobre las que solo se pondrá precisión el error cometido. Lo anterior no será aplicable cuando las actuaciones se realicen\nLey de Responsabilidades Administrativas del Estado de Baja California. Página 56 mediante el uso de equipos de cómputo, pero será responsabilidad de la Autoridad substanciadora o resolutora, que en las actuaciones se haga constar fehacientemente lo acontecido durante ellas;\nIV. Todas las constancias del expediente deberán ser foliadas, selladas y rubricadas en orden progresivo; y\nV. Las actuaciones serán autorizadas por las autoridades substanciadoras o resolutoras, y, en su caso, por el secretario a quien corresponda certificar o dar fe del acto cuando así se determine de conformidad con las leyes correspondientes.\nArtículo 201. Las actuaciones serán nulas cuando les falte alguno de sus requisitos esenciales, de manera que quede sin defensa cualquiera de las partes. No podrá reclamar la nulidad la parte que hubiere dado lugar a ella.\nArtículo 202. Las resoluciones serán:\nI. Acuerdos, cuando se trate de aquellas sobre simples resoluciones de trámite;\nII. Autos provisionales, los que se refieren a determinaciones que se ejecuten provisionalmente;\nIII. Autos preparatorios, que son resoluciones por las que se prepara el conocimiento y decisión del asunto, se ordena la admisión, la preparación de pruebas o su desahogo;\nIV. Sentencias interlocutorias, que son aquellas que resuelven un incidente; y\nV. Sentencias definitivas, que son las que resuelven el fondo del procedimiento de responsabilidad administrativa.\nArtículo 203. Las resoluciones deben ser firmadas de forma autógrafa por la autoridad que la emita, y, de ser el caso, por el secretario correspondiente en los términos que se dispongan en las leyes.\nArtículo 204. Los acuerdos, autos y sentencias no podrán modificarse después de haberse firmado, pero las autoridades que los emitan sí podrán aclarar algún concepto cuando éstos sean obscuros o imprecisos, sin alterar su esencia. Las aclaraciones podrán realizarse de oficio, o a petición de alguna de las partes las que deberán promoverse dentro de los tres días hábiles siguientes a que se tenga por hecha la notificación de la resolución, siguientes.\nLey de Responsabilidades Administrativas del Estado de Baja California. Página 57\nArtículo 205. Toda resolución deberá ser clara, precisa y congruente con las promociones de las partes, resolviendo sobre lo que en ellas hubieren pedido. Se deberá utilizar un lenguaje sencillo y claro, debiendo evitar las transcripciones innecesarias.\nArtículo 206. Las resoluciones se considerarán que han quedado firmes, cuando transcurridos los plazos previstos en esta Ley, no se haya interpuesto en su contra recurso alguno; o bien, desde su emisión, cuando no proceda contra ellas recurso o medio ordinario de defensa.\nArtículo 207. Las sentencias definitivas deberán contener lo siguiente:\nI. Lugar, fecha y Autoridad resolutora correspondiente;\nII. Los motivos y fundamentos que sostengan la competencia de la Autoridad resolutora;\nIII. Los antecedentes del caso;\nIV. La fijación clara y precisa de los hechos controvertidos por las partes;\nV. La valoración de las pruebas admitidas y desahogadas;\nVI. Las consideraciones lógico jurídicas que sirven de sustento para la emisión de la resolución. En el caso de que se hayan ocasionado daños y perjuicios a la Hacienda\nPública Estatal o Municipal o al patrimonio de los entes públicos, se deberá señalar la existencia de la relación de causalidad entre la conducta calificada como Falta administrativa grave o Falta de particulares y la lesión producida; la valoración del daño o perjuicio causado; así como la determinación del monto de la indemnización, explicitando los criterios utilizados para su cuantificación;\nVII. El relativo a la existencia o inexistencia de los hechos que la ley señale como\nFalta administrativa grave o Falta de particulares y, en su caso, la responsabilidad plena del servidor público o particular vinculado con dichas faltas. Cuando derivado del conocimiento del asunto, la Autoridad resolutora advierta la probable comisión de Faltas administrativas, imputables a otra u otras personas, podrá ordenar en su fallo que las autoridades investigadoras inicien la investigación correspondiente;\nVIII. La determinación de la sanción para el servidor público que haya sido administrativa grave;\nIX. La existencia o inexistencia que en términos de esta Ley constituyen Faltas administrativas; y\nLey de Responsabilidades Administrativas del Estado de Baja California. Página 58\nX. Los puntos resolutivos, donde deberá precisarse la forma en que deberá cumplirse la resolución.\nCapítulo II\nÓrganos internos de control\nArtículo 208. En los asuntos relacionados con Faltas administrativas no graves, se deberá proceder en los términos siguientes:\nI. La Autoridad investigadora deberá presentar ante la Autoridad substanciadora el Informe de Presunta Responsabilidad Administrativa, la cual, dentro de los tres días siguientes se pronunciará sobre su admisión, pudiendo prevenir a la Autoridad investigadora para que subsane las omisiones que advierta, o que aclare los hechos narrados en el informe;\nII. En el caso de que la Autoridad substanciadora admita el Informe de Presunta\nResponsabilidad Administrativa, ordenará el emplazamiento del presunto responsable, debiendo citarlo para que comparezca personalmente a la celebración de la audiencia inicial, señalando con precisión el día, lugar y hora en que tendrá lugar dicha audiencia, así como la autoridad ante la que se llevará a cabo. Del mismo modo, le hará saber el derecho que tiene de no declarar contra de sí mismo ni a declararse culpable; de defenderse personalmente o ser asistido por un defensor perito en la materia y que, de no contar con un defensor, le será nombrado un defensor público;\nIII. Entre la fecha del emplazamiento y la de la audiencia inicial deberá mediar un plazo no menor de diez ni mayor de quince días hábiles. El diferimiento de la audiencia sólo podrá otorgarse por causas de caso fortuito o de fuerza mayor debidamente justificadas, o en aquellos casos en que se nombre;\nIV. Previo a la celebración de la audiencia inicial, la Autoridad substanciadora deberá citar a las demás partes que deban concurrir al procedimiento, cuando menos con setenta y dos horas de anticipación;\nV. El día y hora señalado para la audiencia inicial el presunto responsable rendirá su declaración por escrito o verbalmente, y deberá ofrecer las pruebas que estime necesarias para su defensa. En caso de tratarse de pruebas documentales, deberá exhibir todas las que tenga en su poder, o las que no estándolo, conste que las solicitó mediante el acuse de recibo correspondiente. Tratándose de documentos que obren en poder de terceros y que no pudo conseguirlos por obrar en archivos privados, deberá señalar el archivo donde se encuentren o la persona que los tenga a su cuidado para que, en su caso, le sean requeridos en los términos previstos en esta Ley;\nLey de Responsabilidades Administrativas del Estado de Baja California. Página 59\nVI. Los terceros llamados al procedimiento de responsabilidad administrativa, a más tardar durante la audiencia inicial, podrán manifestar por escrito o verbalmente lo que a su derecho convenga y ofrecer las pruebas que estimen conducentes, debiendo exhibir las documentales que obren en su poder, o las que no estándolo, conste que las solicitaron mediante el acuse de recibo correspondiente. Tratándose de documentos que obren en poder de terceros y que no pudieron conseguirlos por obrar en archivos privados, deberán señalar el archivo donde se encuentren o la persona que los tenga a su cuidado para que, en su caso, le sean requeridos;\nVII. Una vez que las partes hayan manifestado durante la audiencia inicial lo que a su derecho convenga y ofrecido sus respectivas pruebas, la Autoridad substanciadora declarará cerrada la audiencia inicial, después de ello las partes no podrán ofrecer más pruebas, salvo aquellas que sean supervenientes;\nVIII. Dentro de los quince días hábiles siguientes al cierre de la audiencia inicial, la\nAutoridad substanciadora deberá emitir el acuerdo de admisión de pruebas que corresponda, donde deberá ordenar las diligencias necesarias para su preparación y desahogo;\nIX. Concluido el desahogo de las pruebas ofrecidas por las partes, y si no existieran diligencias pendientes para mejor proveer o más pruebas que desahogar, la\nAutoridad substanciadora declarará abierto el periodo de alegatos por un término de cinco días hábiles comunes para las partes;\nX. Una vez trascurrido el periodo de alegatos, la Autoridad resolutora del asunto, de oficio, declarará cerrada la instrucción y citará a las partes para oír la resolución que corresponda, la cual deberá dictarse en un plazo no mayor a treinta días hábiles, el cual podrá ampliarse por una sola vez por otros treinta días hábiles más, cuando la complejidad del asunto así lo requiera, debiendo expresar los motivos para ello;\nXI. La resolución, deberá notificarse personalmente al presunto responsable. En su caso, se notificará a los denunciantes únicamente para su conocimiento, y al jefe inmediato o al titular de la dependencia o entidad, para los efectos de su ejecución, en un plazo no mayor de diez días hábiles.\nCapítulo III corresponda al Tribunal\nArtículo 209. En los asuntos relacionados con faltas administrativas graves o faltas de particulares, se deberá proceder de conformidad con el procedimiento previsto en este artículo.\nLey de Responsabilidades Administrativas del Estado de Baja California. Página 60\nVII del artículo anterior, luego de lo cual procederán conforme a lo dispuesto en las siguientes fracciones:\nI. A más tardar dentro de los tres días hábiles siguientes de haber concluido la audiencia inicial, la Autoridad substanciadora deberá, bajo su responsabilidad, enviar a la\nSala Especializada competente los autos originales del expediente, así como notificar a las partes de la fecha de su envío, indicando el domicilio del Tribunal encargado de la resolución del asunto;\nII. Cuando la Sala Especializada reciba el expediente, bajo su más estricta responsabilidad, deberá verificar que la falta descrita en el Informe de Presunta\nResponsabilidad Administrativa sea de las consideradas como graves. En caso de no serlo, fundando y motivando debidamente su resolución, enviará el expediente respectivo a la\nAutoridad substanciadora que corresponda para que continúe el procedimiento en términos de lo dispuesto en el artículo anterior.\nDe igual forma, de advertir la Sala Especializada que los hechos descritos por la\nAutoridad investigadora en el Informe de Presunta Responsabilidad Administrativa corresponden a la descripción de una falta grave diversa, le ordenará a ésta realice la reclasificación que corresponda, pudiendo señalar las directrices que considere pertinentes para su debida presentación, para lo cual le concederá un plazo de tres días hábiles. En caso de que la Autoridad investigadora se niegue a hacer la reclasificación, bajo su más estricta responsabilidad así lo hará saber la Sala Especializada fundando y motivando su proceder. En este caso, la Sala Especializada continuará con el procedimiento de responsabilidad administrativa.\nUna vez que el Tribunal haya decidido que el asunto corresponde a su competencia y, en su caso, se haya solventado la reclasificación, deberá notificar personalmente a las partes sobre la recepción del expediente.\nCuando conste en autos que las partes han quedado notificadas, dictará dentro de los quince días hábiles siguientes el acuerdo de admisión de pruebas que corresponda, donde deberá ordenar las diligencias necesarias para su preparación y desahogo;\nIII. Concluido el desahogo de las pruebas ofrecidas por las partes, y si no comunes para las partes;\nIV. Una vez trascurrido el periodo de alegatos, la Sala Especializada, de oficio, declarará cerrada la instrucción y citará a las partes para oír la resolución que corresponda, la cual deberá dictarse en un plazo no mayor a treinta días hábiles, el cual podrá ampliarse\nLey de Responsabilidades Administrativas del Estado de Baja California. Página 61 por una sola vez por otros treinta días hábiles más, cuando la complejidad del asunto así lo requiera debiendo expresar los motivos para ello; y\nV. La resolución, deberá notificarse personalmente al presunto responsable. En su caso, se notificará a los denunciantes únicamente para su conocimiento, y al jefe inmediato o al titular de la dependencia o entidad, para los efectos de su ejecución, en un plazo no mayor de diez días hábiles.\nSección Primera\nDe la revocación\nArtículo 210. Los Servidores Públicos que resulten responsables por la comisión de faltas administrativas no graves en los términos de las resoluciones administrativas que se dicten conforme a lo dispuesto en el presente Título por la Secretaría, Sindicaturas o los\nÓrganos internos de control, podrán interponer el recurso de revocación ante la autoridad que emitió la resolución dentro de los quince días hábiles siguientes a la fecha en que surta efectos la notificación respectiva.\nLas resoluciones que se dicten en el recurso de revocación serán impugnables ante la\nSala Especializada, vía el juicio administrativo correspondiente.\nArtículo 211. La tramitación del recurso de revocación se sujetará a las normas siguientes:\nI. Se iniciará mediante escrito en el que deberán expresarse los agravios que a juicio del Servidor Público le cause la resolución, así como el ofrecimiento de las pruebas que considere necesario rendir;\nII. La autoridad acordará sobre la prevención, admisión o desechamiento del recurso en un término de tres días hábiles; en caso de admitirse, tendrá que acordar sobre las pruebas ofrecidas, desechando de plano las que no fuesen idóneas para desvirtuar los hechos en que se base la resolución;\nIII. Si el escrito de interposición del recurso de revocación no cumple con alguno elementos para subsanarlos se prevendrá al recurrente, por una sola ocasión, con el objeto contados a partir del día siguiente de la notificación de la prevención, con el apercibimiento de que, de no cumplir, se desechará el recurso de revocación. resolver el recurso, por lo que comenzará a computarse a partir del día siguiente a su desahogo; y\nLey de Responsabilidades Administrativas del Estado de Baja California. Página 62\nIV. Desahogadas las pruebas, si las hubiere, la Secretaría, Sindicaturas, el titular del Órgano interno de control o el servidor público en quien delegue esta facultad, dictará resolución dentro de los treinta días hábiles siguientes, notificándolo al interesado en un plazo no mayor de setenta y dos horas.\nArtículo 212. La interposición del recurso suspenderá la ejecución de la resolución recurrida, si concurren los siguientes requisitos:\nI. Que la solicite el recurrente; y\nII. Que no se siga perjuicio al interés social ni se contravengan disposiciones de orden público.\nEn los casos en que sea procedente la suspensión, pero pueda ocasionar daño o perjuicio a tercero y la misma se conceda, el quejoso deberá otorgar garantía bastante para reparar el daño e indemnizar los perjuicios que con aquélla se causaren si no obtuviere resolución favorable.\nCuando con la suspensión puedan afectarse derechos del tercero interesado que no sean estimables en dinero, la autoridad que resuelva el recurso fijará discrecionalmente el importe de la garantía.\nLa autoridad deberá de acordar en un plazo no mayor de veinticuatro horas respecto a la suspensión que solicite el recurrente.\nSección Segunda\nDe la Reclamación\nArtículo 213. El recurso de reclamación procederá en contra de las resoluciones de las autoridades substanciadoras o resolutoras que admitan, desechen o tengan por no presentado el Informe de Presunta Responsabilidad Administrativa, la contestación o alguna prueba; las que decreten o nieguen el sobreseimiento del procedimiento de responsabilidad administrativa antes del cierre de instrucción; y aquéllas que admitan o rechacen la intervención del tercero interesado.\nArtículo 214. La reclamación se interpondrá ante la Autoridad substanciadora o resolutora, según corresponda, que haya dictado el auto recurrido, dentro de los cinco días hábiles siguientes a aquél en que surta efectos la notificación de que se trate.\nInterpuesto el recurso, se ordenará correr traslado a la contraparte por el término de tres días hábiles para que exprese lo que a su derecho convenga, sin más trámite, se dará cuenta a la autoridad substanciadora o resolutora, según sea el caso, para que resuelva en el término de cinco días hábiles.\nLey de Responsabilidades Administrativas del Estado de Baja California. Página 63 emitido el auto recurrido.\nLa resolución de la reclamación no admitirá recurso legal alguno.\nSección Tercera\nDe la Apelación\nArtículo 215. Las resoluciones emitidas por la sala especializada, podrán ser impugnadas por las partes, mediante el recurso de apelación, ante el Pleno del Tribunal\nEstatal de Justicia Administrativa, conforme a los medios que determine la Ley del Tribunal\nEstatal de Justicia Administrativa.\nEl recurso de apelación se promoverá mediante escrito ante la Sala Especializada que emitió la resolución, dentro de los quince días hábiles siguientes a aquél en que surta sus efectos la notificación de la resolución que se recurre.\nEn el escrito deberán formularse los agravios que consideren las partes se les hayan causado, exhibiéndose una copia del mismo para el expediente y una para cada una de las partes.\nArtículo 216. Procederá el recurso de apelación contra las resoluciones siguientes:\nI. La que determine imponer sanciones por la comisión de Faltas administrativas graves o Faltas de particulares; y\nII. La que determine que no existe responsabilidad administrativa por parte de los presuntos infractores, ya sean Servidores Públicos o particulares.\nArtículo 217. El Pleno del Tribunal deberá resolver en el plazo de tres días hábiles si admite el recurso, o lo desecha por encontrar motivo manifiesto e indudable de improcedencia. requisitos establecidos en el artículo 215 de esta Ley, se señalará al promovente en un plazo que no excederá de tres días hábiles, para que subsane las omisiones o corrija los defectos precisados en la providencia relativa.\nEl Tribunal, dará vista a las partes para que, en el término de tres días hábiles, manifiesten lo que a su derecho convenga; vencido este término se procederá a resolver con los elementos que obren en autos.\nArtículo 218. El Pleno del Tribunal procederá al estudio de los conceptos de apelación, atendiendo a su prelación lógica. En todos los casos, se privilegiará el estudio de\nLey de Responsabilidades Administrativas del Estado de Baja California. Página 64 los conceptos de apelación de fondo por encima de los de procedimiento y forma, a menos que invertir el orden dé la certeza de la inocencia del servidor público o del particular, o de ambos; o que en el caso de que el recurrente sea la Autoridad Investigadora, las violaciones de forma hayan impedido conocer con certeza la responsabilidad de los involucrados. derivarse el sobreseimiento del procedimiento de responsabilidad administrativa, la inocencia del recurrente, o la determinación de culpabilidad respecto de alguna conducta, se le dará preferencia al estudio de aquéllas aún de oficio.\nArtículo 219. En el caso de ser revocada la sentencia o de que su modificación así lo disponga, cuando el recurrente sea el servidor público o el particular, se ordenará al Ente público en el que se preste o haya prestado sus servicios, lo restituya de inmediato en el goce de los derechos de que hubiese sido privado por la ejecución de las sanciones impugnadas, en los términos de la sentencia respectiva, sin perjuicio de lo que establecen otras leyes.\nSe exceptúan del párrafo anterior, los Agentes del Ministerio Público, peritos oficiales y miembros de las instituciones policiales; casos en los que la Procuraduría General de\nJusticia del Estado, y las instituciones o corporaciones policiales del Estado y Municipios, sólo estarán obligadas a pagar la indemnización y demás prestaciones a que tengan derecho, sin que en ningún caso proceda la reincorporación al servicio, en los términos previstos en el apartado B, fracción XIII, del artículo 123 de la Constitución.\nSección Cuarta\nDe la Revisión\nArtículo 220. Las resoluciones definitivas que emita el Pleno del Tribunal Estatal de\nJusticia Administrativa, podrán ser impugnadas por la Secretaría, Sindicaturas, los Órganos internos de control de los entes públicos o la Auditoría Superior, interponiendo el recurso de revisión, mediante escrito que se presente ante el propio Tribunal, dentro de los diez días hábiles siguientes a aquél en que surta sus efectos la notificación respectiva.\nAmparo, Reglamentaria de los Artículos 103 y 107 de la Constitución Política de los Estados\nUnidos Mexicanos. En contra de la resolución dictada por el Tribunal Colegiado de Circuito no procederá juicio ni recurso alguno.\nArtículo 221. Las sentencias definitivas que emita el Tribunal podrán ser impugnadas por la Secretaría, Sindicaturas, los Órganos internos del control, en los términos que lo prevean la Ley que rige al Tribunal Estatal de Justicia Administrativa del Estado.\nCapítulo IV\nDe la Ejecución\nLey de Responsabilidades Administrativas del Estado de Baja California. Página 65\nSección Primera\nArtículo 222. La ejecución de las sanciones por faltas administrativas no graves se llevará a cabo de inmediato, una vez que sean impuestas por la Secretaría, Sindicaturas o los Órganos internos de control, y conforme se disponga en la resolución respectiva.\nArtículo 223. Tratándose de los Servidores Públicos de base, la suspensión y la destitución se ejecutarán por el titular del Ente público correspondiente.\nSección Segunda\nCumplimiento y ejecución de sanciones por Faltas administrativas graves y Faltas de particulares\nArtículo 224. Las sanciones económicas impuestas por la Sala Especializada constituirán créditos fiscales a favor de la Hacienda Pública Estatal o Municipal, o del patrimonio de los entes públicos, según corresponda. Dichos créditos fiscales se harán efectivos mediante el procedimiento administrativo de ejecución, por la Secretaria de\nPlaneación y Finanzas del Poder Ejecutivo del Estado, a la que será notificada la resolución emitida por la Sala Especializada.\nArtículo 225. Cuando haya causado ejecutoria una sentencia en la que se determine la plena responsabilidad de un servidor público por faltas administrativas graves, la Sala\nEspecializada, sin que sea necesario que medie petición de parte y sin demora alguna, girará oficio por el que comunicará la sentencia respectiva, así como los puntos resolutivos de esta para su cumplimiento, de conformidad con las siguientes reglas:\nI. Cuando el servidor público haya sido suspendido, destituido o inhabilitado, se dará vista a su superior jerárquico y a la Secretaría; y\nII. Cuando se haya impuesto una indemnización y/o sanción económica al responsable, se dará vista a la Secretaria de Planeación y Finanzas del Poder Ejecutivo del\nEstado.\nEn el oficio respectivo, la Sala Especializada prevendrá a las autoridades señaladas para que informen, dentro del término de diez días, sobre el cumplimiento que den a la sentencia en los casos a que se refiere la fracción I de este artículo. En el caso de la fracción corresponda.\nArtículo 226. Cuando haya causado ejecutoria una sentencia en la que se determine la comisión de Faltas de particulares, la Sala Especializada, sin que sea necesario que\nLey de Responsabilidades Administrativas del Estado de Baja California. Página 66 medie petición de parte y sin demora alguna, girará oficio por el que comunicará la sentencia respectiva, así como los puntos resolutivos de esta para su cumplimiento, de conformidad con las siguientes reglas:\nI. Cuando el particular haya sido inhabilitado para participar con cualquier carácter en adquisiciones, arrendamientos, servicios u obras públicas, la Sala Especializada ordenará su publicación en el Periódico Oficial del Estado de Baja California; y\nII. Cuando se haya impuesto una indemnización y/o sanción económica al responsable, se dará vista a la autoridad municipal o estatal competente, según sea el caso.\nArtículo 227. Cuando el particular tenga carácter de persona moral, sin perjuicio de lo establecido en el artículo que antecede, la Sala Especializada girará oficio por el que comunicará la sentencia respectiva, así como los puntos resolutivos de ésta para su cumplimiento, de conformidad con las siguientes reglas:\nI. Cuando se decrete la suspensión de actividades de la sociedad respectiva, se dará vista a la Secretaria de Planeación y Finanzas del Poder Ejecutivo del Estado y al\nServicio de Administración Tributaria, se inscribirá en el Registro Público de la Propiedad y del Comercio y se hará publicar un extracto de la sentencia que decrete esta medida, en el\nPeriódico Oficial del Estado y en uno de los diarios de mayor circulación en la localidad donde tenga su domicilio fiscal el particular; y\nII. Cuando se decrete la disolución de la sociedad respectiva, los responsables procederán de conformidad con la Ley General de Sociedades Mercantiles en materia de disolución y liquidación de las sociedades, o en su caso, conforme el Código Civil del\nEstado, según corresponda, y las demás disposiciones aplicables.\nArtículo 228. Cuando haya causado ejecutoria una sentencia en la que se determine que no existe una falta administrativa grave o Faltas de particulares, la Sala Especializada, sin que sea necesario que medie petición de parte y sin demora alguna, girará oficio por el que comunicará la sentencia respectiva, así como los puntos resolutivos de ésta para su cumplimiento. En los casos en que haya decretado la suspensión del servidor público en su empleo, cargo o comisión, ordenará la restitución inmediata del mismo.\nArtículo 229. El incumplimiento de las medidas cautelares previstas en el artículo 123 de la presente Ley por parte del jefe inmediato, del titular del Ente público correspondiente o de cualquier otra autoridad obligada a cumplir con dicha disposición, será causa de responsabilidad administrativa en los términos de la Ley. incidente, podrá modificar o revocar la resolución que haya decretado o negado las medidas cautelares, cuando ocurra un hecho superveniente que lo justifique.\nLey de Responsabilidades Administrativas del Estado de Baja California. Página 67\nTRANSITORIOS\nPrimero. La presente Ley entrará en vigor con fecha primero de enero del año dos mil dieciocho, sin perjuicio de lo previsto en los transitorios siguientes.\nSegundo. Hasta en tanto el Comité Coordinador del Sistema Estatal Anticorrupción determina los formatos para la presentación de las declaraciones patrimonial y de intereses, los servidores públicos de todos los órdenes de gobierno presentarán sus declaraciones en los formatos aplicables antes de la entrada en vigor de esta Ley.\nTercero. En tanto se aplican plenos efectos a las normas materia del Sistema Estatal\nAnticorrupción, las referencias de ésta Ley en cuanto a los Órganos cuya denominación se modifican se entenderán bajo las siguientes referencias normativas:\na) Director o Dirección de Control y Evaluación Gubernamental o Contraloría del\nEstado, se refiere al titular o a la secretaria responsable del Control Interno del Ejecutivo del Estado.\nb) Dirección de Contraloría, Unidad de Contraloría Interna, Contralor Interno, unidad de responsabilidades se refiere a Órgano Interno de Control:\nc) Tribunal de lo Contencioso Administrativo del Estado de Baja California, se refiere al Tribunal Estatal de Justicia Administrativa.\nCuarto. El cumplimiento de las obligaciones previstas en la presente Ley de\nResponsabilidades Administrativas, una vez que ésta entre en plenitud de aplicación, serán exigibles, en lo que resulte aplicable, hasta en tanto el Comité Coordinador del Sistema\nEstatal Anticorrupción, de conformidad con la ley de la materia, emita los lineamientos, criterios y demás resoluciones conducentes de su competencia.\nQuinto. Los procedimientos administrativos iniciados por las autoridades estatales y municipales con anterioridad a la entrada en vigor de la presente Ley de Responsabilidades\nAdministrativas, serán concluidos conforme a las disposiciones aplicables vigentes a su inicio.\nSexto. A la fecha de entrada en vigor de la presente Ley, todas las menciones a la en las leyes del Estado, así como en cualquier disposición jurídica, se entenderán referidas a la Ley de Responsabilidades Administrativas de Baja California.\nSéptimo. Con la entrada en vigor de la Ley de Responsabilidades Administrativas de\nEstado de Baja California.\nLey de Responsabilidades Administrativas del Estado de Baja California. Página 68\nOctavo. Los asuntos iniciados antes de la entrada en vigor de la presente Ley\nPúblicos del Estado de Baja California que se abroga.\nNoveno. Los Entes Públicos previstos por esta Ley realizarán las adecuaciones administrativas, así como la gestión de modificaciones reglamentarias, programáticas, presupuestales y de políticas públicas a efecto de desarrollar sus atribuciones conforme a las premisas de este nuevo ordenamiento.\nDécimo. En tanto se expide una ley especial lo referente al Juicio Político y\nDeclaración de Procedencia; continuará en vigor en lo precedente el Título Segundo, denominado del Juicio Político y Declaración de Procedencia, en sus capítulos I, II, III y IV de la Ley de Responsabilidades de los Servidores Públicos del Estado de Baja California.\nDADO en el Salón de Sesiones “Lic. Benito Juárez García” del H. Poder Legislativo del Estado de Baja California, en la Ciudad de Mexicali, B.C., a los dieciocho días del mes de julio del año dos mil diecisiete\nDIP. JOB MONTOYA GAXIOLA\nPRESIDENTE\n(RÚBRICA)\nDIP. IRAÍS MARÍA VÁZQUEZ AGUIAR\nSECRETARIA\n(RÚBRICA)\nDE CONFORMIDAD CON LO DISPUESTO POR LA FRACCIÓN I DEL ARTÍCULO 49\nMEXICALI, BAJA CALIFORNIA, A LOS VEINTISIETE DÍAS DEL MES DE JULIO DEL AÑO\nDOS MIL DIECISIETE.\nFRANCISCO ARTURO VEGA DE LAMADRID\nGOBERNADOR DEL ESTADO\n(RÚBRICA)\nFRANCISCO RUEDA GÓMEZ\nSECRETARIO GENERAL DE GOBIERNO\n(RÚBRICA)\nLey de Responsabilidades Administrativas del Estado de Baja California. Página 69\nARTÍCULO 10.- Fue mediante Decreto No. 79, publicado en el Periódico Oficial No. 22, siendo Gobernadora Constitucional la C. Marina del Pilar Ávila Olmeda 2021-2027;\nARTÍCULO 53.- Fue reformado por Decreto No. 01, publicado en el Periódico Oficial\nLegislatura, siendo Gobernador Constitucional el C. Francisco Arturo Vega de Lamadrid\n2013-2019;\nARTÍCULO 54.- Fue reformado por Decreto No. 01, publicado en el Periódico Oficial\nNo. 44, Sección VII, Tomo CXXVI, de fecha 11 de octubre de 2019, expedido por la H. XXIII\nLegislatura, siendo Gobernador Constitucional el C. Francisco Arturo Vega de Lamadrid\n2013-2019;\nARTÍCULO 57.- Fue reformado por Decreto No. 102, publicado en el Periódico Oficial\nNo. 54, de fecha 02 de septiembre de 2020, Tomo CXXVII, NÚMERO ESPECIAL, expedido por la H. XXIII Legislatura, siendo Gobernador Constitucional el C. Jaime Bonilla Valdez, 2019-2021;\nARTÍCULO 62 BIS.- Fue reformado por Decreto No. 01, publicado en el Periódico\nOficial No. 44, Sección VII, Tomo CXXVI, de fecha 11 de octubre de 2019, expedido por la\nH. XXIII Legislatura, siendo Gobernador Constitucional el C. Francisco Arturo Vega de\nLamadrid 2013-2019;\nARTÍCULO 63 BIS.- Fue adicionado mediante Decreto No. 254, publicado en el la H. XXIV Legislatura, siendo Gobernadora Constitucional la C. Marina del Pilar Ávila\nOlmeda 2021-2027;\nARTÍCULO 63 TER.- Fue adicionado por Decreto No. 310, publicado en el Periódico\nH. XXIV Legislatura, siendo Gobernadora Constitucional la C. Marina del Pilar Ávila Olmeda\n2021-2027;\nLey de Responsabilidades Administrativas del Estado de Baja California. Página 70\nARTÍCULO SEGUNDO TRANSITORIO DEL DECRETO No. 01, POR EL QUE SE\nAPRUEBA LA REFORMA AL ARTÍCULO 53, LA ADICIÓN DE UN SEGUNDO PÁRRAFO AL\nARTÍCULO 54, ASÍ COMO ADICIÓN DE UN ARTÍCULOS 62 BIS; PUBLICADO EN EL\nPERIÓDICO OFICIAL No. 44, SECCIÓN VII, TOMO CXXVI, DE FECHA 11 DE OCTUBRE\nDE 2019, EXPEDIDO POR LA H. XXIII LEGISLATURA, SIENDO GOBERNADOR\nCONSTITUCIONAL EL C. FRANCISCO ARTURO VEGA DE LAMADRID 2013-2019.\nTRANSITORIOS\nÚNICO.- La presente reforma entrará en vigor al día siguiente de su publicación en el\nPeriódico Oficial del Estado.\nDADO en el Salón de Sesiones “Lic. Benito Juárez García” del H. Poder Legislativo del\nEstado de Baja California, en la Ciudad de Mexicali, B.C., a veintinueve días del mes de agosto del año dos mil diecinueve.\nDIP. CATALINO ZAVALA MÁRQUEZ\nPRESIDENTE\n(RÚBRICA)\nDIP. ARACELI GERALDO NÚÑEZ\nSECRETARIA\n(RÚBRICA)\nARTÍCULO QUINTO TRANSITORIO DEL DECRETO No. 102, POR EL QUE SE\nREFORMA EL ARTÍCULO 57; PUBLICADO EN EL PERIÓDICO OFICIAL No. 54, NÚMERO\nESPECIAL, TOMO CXXVII, DE FECHA 02 DE SEPTIEMBRE DE 2020, EXPEDIDO POR LA\nH. XXIII LEGISLATURA, SIENDO GOBERNADOR CONSTITUCIONAL EL C. JAIME\nBONILLA VALDEZ 2019-2021.\nARTÍCULOS TRANSITORIOS\nÚNICO.- La presente reforma entrará en vigor al día siguiente de su publicación en el\nPeriódico Oficial del Estado.\nDADO en Sesión Ordinaria Virtual, en la Ciudad de Mexicali, B.C., a los veintiséis días del mes de agosto del año dos mil veinte.\nDIP. JULIO CÉSAR VÁZQUEZ CASTILLO\nPRESIDENTE\n(RÚBRICA)\nDIP. EVA GRICELDA RODRÍGUEZ\nSECRETARIA\n(RÚBRICA)\nDE CONFORMIDAD CON LO DISPUESTO POR LA FRACCIÓN I DEL ARTÍCULO 49\nLey de Responsabilidades Administrativas del Estado de Baja California. Página 71\nMEXICALI, BAJA CALIFORNIA, A LOS VEINTIOCHO DÍAS DEL MES DE AGOSTO DEL\nAÑO DOS MIL VEINTE.\nJAIME BONILLA VALDEZ\nGOBERNADOR DEL ESTADO\n(RÚBRICA)\nAMADOR RODRÍGUEZ LOZANO\nSECRETARIO GENERAL DE GOBIERNO\n(RÚBRICA)\nARTÍCULO SEGUNDO TRANSITORIO DEL DECRETO No. 254, POR EL QUE SE\nADICIONA UN ARTÍCULO 63 BIS; PUBLICADO EN EL PERIÓDICO OFICIAL No. 45,\nSECCIÓN I, TOMO CXXX, DE FECHA 28 DE JULIO DE 2023, EXPEDIDO POR LA H. XXIV\nLEGISLATURA, SIENDO GOBERNADORA CONSTITUCIONAL LA C. MARINA DEL PILAR\nÁVILA OLMEDA 2021-2027.\nTRANSITORIOS\nÚNICO. La presente reforma entrará en vigor al día siguiente de su publicación en el\nPeriódico Oficial del Estado.\nDADO en Sesión Ordinaria de la XXIV Legislatura en la Ciudad de Mexicali, B.C., a los seis días del mes de julio del año dos mil veintitrés.\nDIP. MANUEL GUERRERO LUNA\nPRESIDENTE\n(RÚBRICA)\nDIP. ALEJANDRA MARÍA ANG HERNÁNDEZ\nSECRETARIA\n(RÚBRICA)\nDE CONFORMIDAD CON LO DISPUESTO POR LA FRACCIÓN I DEL ARTÍCULO 49\nCALIFORNIA, IMPRÍMASE Y PUBLÍQUESE.\nMEXICALI, BAJA CALIFORNIA, A LOS ONCE DÍAS DEL MES DE JULIO DEL AÑO\nDOS MIL VEINTITRÉS.\nMARINA DEL PILAR ÁVILA OLMEDA\nGOBERNADORA DEL ESTADO\nDE BAJA CALIFORNIA\nLey de Responsabilidades Administrativas del Estado de Baja California. Página 72\n(RÚBRICA)\nCATALINO ZAVALA MÁRQUEZ\nSECRETARIO GENERAL DE GOBIERNO\nDEL ESTADO DE BAJA CALIFORNIA\n(RÚBRICA)\nARTÍCULO QUINTO TRANSITORIO DEL DECRETO No. 310, POR EL QUE SE\nAPRUEBA LA ADICIÓN DEL ARTÍCULO 63 TER; PUBLICADO EN EL PERIÓDICO\nOFICIAL No. 62, DE FECHA 06 DE NOVIEMBRE DE 2023, SECCIÓN I, TOMO CXXX,\nEXPEDIDO POR LA H. XXIV LEGISLATURA, SIENDO GOBERNADORA\nCONSTITUCIONAL LA C. MARINA DEL PILAR ÁVILA OLMEDA 2021-2027.\nTRANSITORIO\nÚNICO.- La presente adición entrará en vigor al día siguiente de su publicación en el\nPeriódico Oficial del Estado de Baja California.\nDADO en Sesión Ordinaria de la XXIV Legislatura en la Ciudad de Mexicali, B.C., a los diecinueve días del mes de octubre del año dos mil veintitrés.\nDIP. MANUEL GUERRERO LUNA\nPRESIDENTE\n(RÚBRICA)\nDIP. DUNNIA MONTSERRAT MURILLO LÓPEZ\nSECRETARIA\n(RÚBRICA)\nDE CONFORMIDAD CON LO DISPUESTO POR LA FRACCIÓN I DEL ARTÍCULO 49\nCALIFORNIA, IMPRÍMASE Y PUBLÍQUESE.\nMEXICALI, BAJA CALIFORNIA, A LOS VEINTE DÍAS DEL MES DE OCTUBRE DEL\nAÑO DOS MIL VEINTITRÉS.\nMARINA DEL PILAR ÁVILA OLMEDA\nGOBERNADORA DEL ESTADO\nDE BAJA CALIFORNIA\n(RÚBRICA)\nCATALINO ZAVALA MÁRQUEZ\nSECRETARIO GENERAL DE GOBIERNO\nDEL ESTADO DE BAJA CALIFORNIA\n(RÚBRICA)\nLey de Responsabilidades Administrativas del Estado de Baja California. Página 73\nARTÍCULO ÚNICO TRANSITORIO DEL DECRETO No. 79, POR EL QUE SE APRUEBA LA\nREFORMA AL ARTÍCULO 10, PUBLICADO EN EL PERIÓDICO OFICIAL No. 22, ÍNDICE,\nLEGISLATURA, SIENDO GOBERNADORA CONSTITUCIONAL LA C. MARINA DEL PILAR\nÁVILA OLMEDA 2021-2027.\nTRANSITORIO\nÚNICO.- La presente reforma entrará en vigor al día siguiente de su publicación en el\nPeriódico Oficial del Estado.\nDADO en Sesión Ordinaria de la XXV Legislatura en la Ciudad de Tijuana, B.C., a los veintisiete días del mes de marzo del año dos mil veinticinco.\nDIP. EVELYN SÁNCHEZ SÁNCHEZ\nPRESIDENTA\n(RÚBRICA)\nDIP. MICHELLE ALEJANDRA TEJEDA MEDINA\nSECRETARIA\n(RÚBRICA)\nDE CONFORMIDAD CON LO DISPUESTO POR LA FRACCIÓN I DEL ARTÍCULO 49\nCALIFORNIA, IMPRÍMASE Y PUBLÍQUESE.\nMEXICALI, BAJA CALIFORNIA, A LOS 31 DÍAS DEL MES DE MARZO DEL AÑO\nDOS MIL VEINTICUATRO.\nMARINA DEL PILAR ÁVILA OLMEDA\nGOBERNADORA DEL ESTADO\nDE BAJA CALIFORNIA\n(RÚBRICA)\nALFREDO ÁLVAREZ CÁRDENAS\nSECRETARIO GENERAL DE GOBIERNO\nDEL ESTADO DE BAJA CALIFORNIA\n(RÚBRICA)\nLey de Responsabilidades Administrativas del Estado de Baja California. Página 74",
  "ordenamiento": "REGLAMENTO",
  "jurisdiccion": "BAJA CALIFORNIA",
  "fuente_oficial": "Periódico Oficial",
  "FECHA PER OFIC": "2025/04/11",
  "ESTATUS": "VIGENTE",
  "TOMO": "TOMO_I",
  "URL": "https://www.congresobc.gob.mx/Documentos/ProcesoParlamentario/Leyes/TOMO_I/20250411_LEYRESPADMTRA.PDF",
  "es_escaneado": false,
  "tiene_tablas": false,
  "materia": [
    "administrativo",
    "legislativo",
    "gobernanza"
  ]
}