{
  "titulo": "Ley DE PROTECCIÓN AL AMBIENTE PARA EL ESTADO DE BAJA CALIFORNIA",
  "Contenido": "LEY DE PROTECCIÓN AL AMBIENTE PARA EL ESTADO\nDE BAJA CALIFORNIA\nPublicado en el Periódico Oficial No. 53,\nTITULO PRIMERO\nDISPOSICIONES GENERALES\nCAPÍTULO I\nNormas Preliminares\nARTICULO 1.- La presente Ley es reglamentaria de las disposiciones de la desarrollo sustentable, prevención, preservación y restauración del equilibrio ecológico, así como la protección al ambiente del territorio del Estado. Sus disposiciones son de orden público e interés social y tienen por objeto establecer las bases para:\nI. Garantizar el derecho de toda persona a gozar de un ambiente adecuado para su desarrollo, salud y bienestar y vigilar el cumplimiento del deber que tiene toda persona de proteger el ambiente;\nII. Establecer un sistema de gestión ambiental estatal;\nIII. Definir los principios mediante los cuales se habrá de formular, conducir y evaluar la política ambiental en el Estado, así como los instrumentos y los procedimientos para su aplicación, apoyándose en la solidaridad colectiva;\nIV. Aprovechar en forma sustentable los recursos naturales e incrementar la calidad de vida de la población;\nV. Preservar y restaurar el equilibrio ecológico, así como prevenir el deterioro ambiental y de la vida silvestre, de manera que sea compatible la obtención de beneficios económicos y las actividades de la sociedad con la preservación de los ecosistemas.\nVI. Preservar y proteger la biodiversidad, establecer, regular y administrar las áreas naturales protegidas de competencia del Estado, así como manejar y vigilar las que se asuman por convenio con la Federación.\nVII. Prevenir y controlar la contaminación del aire, agua, atmósfera y suelo en las áreas que no sean competencia de la Federación;\nVIII. Coordinar y concertar, entre las distintas dependencias y organismos de la administración pública federal, estatal y municipal en las acciones de protección al ambiente;\nLey de Protección al Ambiente para el Estado de Baja California. Página 1\nIX. Garantizar la participación corresponsable de las personas y los grupos sociales organizados, en las materias que regula la presente Ley,\nX. Definir las medidas de control y de seguridad para garantizar el cumplimiento y la aplicación de esta Ley y de las disposiciones que de ella se deriven, así como para la imposición de las sanciones administrativas que correspondan; y\nXI. Establecer las bases para garantizar el acceso de la sociedad a la información ambiental, que permita a los ciudadanos conocer la situación ambiental que guarda el estado y para asegurar su participación corresponsable en la protección del ambiente, la vida silvestre y la preservación del equilibrio ecológico.\nXII. - Establecer las bases y principios mediante los cuales se habrán de conducir y evaluar a las instituciones públicas Estatales y Municipales en materia de cuidado ambiental.\nArtículo Reformado\nARTICULO 2.- Para los efectos de esta Ley, se estará a las definiciones de conceptos que se contienen en la Ley General del Equilibrio Ecológico y la Protección al\nAmbiente, Ley General de Prevención y Gestión Integral de Residuos, Ley General de Vida\nSilvestre, la Ley de Aguas Nacionales, la Ley General de Desarrollo Forestal Sustentable y la Ley de Desarrollo Urbano del Estado de Baja California, y sus Reglamentos, así como las siguientes:\nI. AGUAS RESIDUALES.- Las aguas de composición variada provenientes de las descargas de usos municipales, comerciales, de servicios, agrícolas, pecuarios, domésticos, incluyendo fraccionamientos y en general cualquier otro uso, así como la mezcla de ellas.\nII. ÁREA VERDE URBANA: Bien inmueble del dominio público municipal ubicado dentro de los límites de los centros de población, ocupado predominantemente por vegetación, destinado al uso, disfrute o aprovechamiento colectivo y de acceso generalizado y libre tránsito;\nFracción Adicionada, recorriéndose las subsecuentes\nIII. AUDITORIA AMBIENTAL: Examen metodológico, de carácter voluntario de las responsables del funcionamiento y operaciones de una empresa, respecto de la contaminación y el riesgo que generan, así como el grado de cumplimiento de la operación e ingeniería aplicables, con el objeto de definir las medidas preventivas y correctivas necesarias para proteger el ambiente;\nIV. AUTORREGULACION: Proceso voluntario a través del cual los particulares buscan mejorar su desempeño ambiental, respetando la legislación y normatividad vigente en la materia, y se comprometen a superar o cumplir mayores niveles, metas o beneficios en materia de protección ambiental;\nLey de Protección al Ambiente para el Estado de Baja California. Página 2\nV. CENTROS DE VERIFICACIÓN: Centros de verificación de emisiones contaminantes a la atmósfera de automotores en circulación;\nVI. COMBUSTIBLES FÓSILES: Materiales comburentes de origen orgánico que incluyen los hidrocarburos, el gas natural y el carbón;\nVII. CONSEJO: Al Consejo Estatal de Protección al Ambiente del Estado de Baja\nCalifornia;\nVIII. CONSERVACIÓN: Conjunto de políticas y medidas orientadas a mantener la diversidad genética y la calidad de vida, incluido el uso no destructivo de los elementos naturales, con el propósito de permitir la continuidad de los procesos evolutivos que les dieron origen;\nIX. CONTAMINACION LUMINICA: Emisión de flujo luminoso en la atmosfera de fuentes artificiales nocturnas, en intensidades, direcciones, rangos espectrales u horarios innecesarios para la realización de las actividades previstas en la zona en que se instala la fuente;\nFracción Reformada\nX. CONTINGENCIA AMBIENTAL: Situación de riesgo, derivada de actividades humanas o fenómenos naturales, que puede poner en peligro la integridad de uno o varios ecosistemas, declarada por las autoridades competentes cuando se presenta o se prevé con base en objetivos o en el monitoreo de la contaminación ambiental;\nXI. EMERGENCIA ECOLÓGICA: Situación derivada de actividades humanas o fenómenos naturales que al afectar severamente a sus elementos, pone en peligro a uno o varios ecosistemas, declarada por las autoridades competentes cuando se presenta o se prevé con base en objetivos o en el monitoreo de la contaminación ambiental;\nXII. EUTROFICACIÓN: Proceso de fertilización acelerada en lagos, arroyos y esteros, generado por un enriquecimiento de nutrientes que produce alga, lama y plantas que deterioran el ambiente acuático;\nXIII. FUENTE FIJA: Es toda instalación establecida en un solo lugar, que tenga como finalidad desarrollar operaciones o procesos industriales, comerciales, de servicios o actividades que generen o puedan generar emisiones contaminantes a la atmósfera;\nXIV. FUENTE MÓVIL: Unidad sujeta a movimiento que genera y emite contaminantes a la atmósfera;\nXV. INVERNADERO (EFECTO DE): Propiedad de la atmósfera de dejar entrar de una manera fácil la radiación solar, pero que a la vez dificulta la salida del calor. Este de hidrocarburos y otras actividades humanas;\nLey de Protección al Ambiente para el Estado de Baja California. Página 3\nXVI. LEY: Ley de Protección al Ambiente para el Estado de Baja California;\nXVII. LEY GENERAL: Ley General del Equilibrio Ecológico y la Protección al\nAmbiente;\nXVIII. MEJOR TECNOLOGÍA DISPONIBLE: El conjunto de equipos, dispositivos, mecanismos, técnicas o sistemas, que aplicados a una fuente o proceso generador de contaminantes, logra la mayor reducción, minimización o eliminación de dichos contaminantes, o reduce su grado de peligrosidad, comparada con otras tecnologías usuales. Se entiende asimismo, que su implementación es técnicamente factible, que es posible su adquisición en el mercado regional, y que su costo es razonablemente comparable a tecnologías usuales, tradicionales o análogas;\nXIX. QUEMA: Combustión controlada o no, de cualquier sustancia o material;\nXX. RECICLAJE: Método de tratamiento que consiste en la transformación de los residuos con fines productivos;\nXXI. SECRETARÍA: Secretaría de Medio Ambiente y Desarrollo Sustentable, y\nFracción Reformada\nXXII. VIDA SILVESTRE: Los organismos que subsisten sujetos a los procesos de evolución natural y que se desarrollan libremente en su hábitat, incluyendo sus poblaciones menores e individuos que se encuentran bajo el control del hombre, así como ferales.\nArtículo Reformado\nARTICULO 3.- Para los efectos de la presente Ley, se consideran de utilidad pública:\nI. El ordenamiento ecológico del estado, y de los municipios;\nII. El establecimiento, regulación, administración y vigilancia de las áreas naturales protegidas de competencia estatal y municipal;\nIII. Las zonas de preservación y restauración del equilibrio ecológico de competencia estatal y municipal, que sean avaladas por el Consejo Estatal de Protección al Ambiente y se\nIV. La preservación y protección de la biodiversidad en zonas o bienes de recursos genéticos.\nV. El establecimiento de zonas de amortiguamiento, con motivo de la presencia de actividades consideradas como riesgosas;\nVI. El establecimiento de sitios de confinamiento y disposición final de residuos sólidos urbanos y residuos de manejo especial;\nLey de Protección al Ambiente para el Estado de Baja California. Página 4\nVII. Los fondos ambientales.\nVIII. La conservación del hábitat natural en que se desarrolla la vida silvestre, y\nIX. El establecimiento y conservación de parques urbanos y áreas verdes estatales y municipales localizadas en los centros de población.\nArtículo Reformado\nARTICULO 4.- La Ley General, sus reglamentos y normas oficiales mexicanas, así como las disposiciones contenidas en otras leyes relacionadas con la materia que regula este ordenamiento, que emita la Federación, serán de aplicación supletoria de la presente\nLey, en los casos no previstos en la misma.\nCAPÍTULO II\nDe las Autoridades Ambientales\nARTICULO 5.- Son autoridades en materia ambiental del estado;\nI. El Gobernador del Estado;\nII. La Secretaría;\nIII. El Consejo Estatal de Protección al Ambiente;\nIV. Los Ayuntamientos;\nV. En su caso, los organismos públicos de competencia estatal o municipal que administren el agua.\nEstas autoridades ejercerán sus facultades de conformidad con lo que dispone esta\nLey, lo que establezcan otros ordenamientos legales y en su caso, con lo que establezcan los acuerdos o convenios de coordinación que en términos de las leyes aplicables se celebren entre el Ejecutivo del Estado, la Federación y los Municipios, conjunta o separadamente.\nARTICULO 6.- Para la aplicación de la presente Ley, el Ejecutivo del Estado contará\nCalifornia, con funciones de autoridad en todo lo relativo a la prevención, preservación y restauración del equilibrio ecológico y protección al ambiente.\nArtículo Reformado\nARTICULO 7.- La Persona Titular de la Secretaría, será nombrada por la Persona\nTitular del Ejecutivo del Estado, debiendo reunir, además de los requisitos a que se refiere la\nPárrafo Reformado\nLey de Protección al Ambiente para el Estado de Baja California. Página 5\nI. Contar con estudios relacionados con la materia ambiental;\nII. Tener experiencia en la administración o coordinación de acciones relativas a la materia ambiental.\nArtículo Reformado\nARTICULO 8.- Corresponde a la Secretaría, el ejercicio de las siguientes atribuciones:\nI. Proponer, conducir y evaluar la política ambiental en el estado, así como los planes y programas que de esta se deriven, en congruencia con lo establecido por la Federación y los criterios formulados por el Consejo Estatal de Protección al Ambiente;\nII. Proponer, ejecutar y evaluar el programa estatal de protección al ambiente;\nIII. Hacer efectivas las obligaciones establecidas en la Ley General, la presente Ley, y disposiciones que de éstas emanen, en el ámbito de su competencia, y en su caso, hacer uso de los medios de apremio;\nIV. Aplicar los instrumentos de política ambiental previstos en esta Ley, preservar y restaurar el equilibrio ecológico y proteger el ambiente en bienes y zonas de su jurisdicción;\nV. Promover la creación de instrumentos económicos que incentiven el cumplimiento de los objetivos de la política ambiental;\nVI. Promover la creación de un fondo para la investigación científica y tecnológica de aquellos asuntos que en materia ambiental se consideren de interés para el estado, en coordinación con las autoridades y dependencias correspondientes;\nVII. Promover convenios de coordinación administrativa con otros estados, y en su caso, con el Gobierno de la Ciudad de México con el propósito de atender y resolver problemas ambientales comunes y ejercer las atribuciones a que se refiere esta Ley, a través de las instancias que al efecto se determinen, atendiendo a lo dispuesto en las leyes locales que resulten aplicables;\nFracción Reformada\nVIII. Promover acuerdos o convenios de coordinación y descentralización con los municipios, con el objeto de que estos asuman las funciones y atribuciones contenidas en la acciones conjuntas orientadas a dar cumplimiento a las disposiciones de esta Ley;\nIX. Promover convenios mediante los cuales se obtengan recursos materiales y económicos para realizar investigaciones pertinentes a la problemática ambiental del estado;\nLey de Protección al Ambiente para el Estado de Baja California. Página 6\nX. Ejercer las funciones que le transfiera la Federación al Estado en materia ambiental, en los términos que establezcan los convenios o acuerdos de coordinación o descentralización correspondientes;\nXI. Emitir recomendaciones a las autoridades federales, estatales y municipales, con el propósito de promover el cumplimiento de la legislación ambiental;\nXII. Coordinar la participación de las dependencias y entidades de la administración pública estatal, en las acciones de cultura ambiental, de prevención y control del deterioro ambiental, preservación, protección y restauración del ambiente en el territorio del estado, así como celebrar con éstas los acuerdos que sean necesarios con el propósito de dar cumplimiento a la presente Ley;\nXIII. Participar en coordinación con la Federación, en asuntos que afecten el equilibrio ecológico o el ambiente de dos o más entidades federativas;\nXIV. Participar en los asuntos que afecten el equilibrio ecológico o el ambiente de dos o más municipios del estado, tomando en cuenta los convenios ya existentes entre éstos;\nXV. Participar conforme a las políticas y programas de protección civil, en las contingencias ambientales y emergencias ecológicas, cuando se afecten zonas de dos o más municipios de la entidad, o bien cuando por su magnitud o repercusiones así se requiera;\nXVI. Formular y ejecutar los programas de ordenamiento ecológico regionales y los planes y programas que de éstos se deriven, en coordinación con los municipios de la entidad y la participación de la sociedad;\nXVII. Evaluar las manifestaciones de impacto ambiental de su competencia, y en su caso, autorizar condicionalmente o negar la realización de planes, programas, proyectos, obras y actividades y suspender temporalmente aquellos que se realicen sin contar con la autorización correspondiente;\nXVIII. Promover y realizar acciones relacionadas con la protección, preservación y restauración del ambiente, entre los diferentes sectores de la comunidad, a fin de desarrollar en la población una mayor cultura ambiental y promover el mejor conocimiento de esta ley;\nXIX. Promover y realizar programas para el desarrollo de técnicas y procedimientos que permitan prevenir, controlar y abatir el deterioro ambiental, propiciar el aprovechamiento sustentable de los recursos naturales y la conservación de los ecosistemas, con instituciones de educación superior, centros de investigación e instituciones públicas;\nXX. Promover la creación de normas ambientales estatales;\nLey de Protección al Ambiente para el Estado de Baja California. Página 7\nXXI. Otorgar y revocar los permisos, licencias y en general las autorizaciones derivadas de la presente Ley y solicitar la cancelación o revocación del permiso, licencia, autorización o concesión a la autoridad otorgante, cuando esta sea distinta a la Secretaría;\nXXII. Promover la participación de la sociedad en materia ambiental;\nXXIII. Conducir la política estatal de información y difusión en materia ambiental;\nXXIV. Ordenar la realización de visitas de inspección para verificar el cumplimiento de los preceptos de esta Ley, sus reglamentos, normas ambientales estatales y las disposiciones y condicionante que en materia ambiental se impongan;\nXXV. Aplicar las sanciones administrativas correspondientes por infracciones a esta\nLey y sus reglamentos;\nXXVI. Ordenar, cuando exista violación flagrante, daños o presencia inminente de desequilibrio ecológico que afecte la salud pública o al ambiente, las medidas de seguridad previstas en esta Ley;\nXXVII. Emitir las resoluciones que pongan fin al procedimiento de inspección y vigilancia, así como cualquier resolución que sea necesaria, de conformidad con la Ley, durante el procedimiento;\nXXVIII. Admitir y resolver los recursos de revocación que se interpongan con motivo de la aplicación de la presente Ley;\nXXIX. Expedir, previo pago del derecho que se fije en la Ley de Ingresos del Estado, las copias certificadas que le sean solicitadas en los términos de esta Ley;\nXXX. Integrar el padrón de las personas físicas o morales que lo soliciten en su carácter de prestador de servicios profesionales especializados, en la preservación y restauración ecológica;\nXXXI. Promover consulta pública en materia ambiental. En el caso de plebiscitos o referéndum, se atendrá a lo establecido en la ley y reglamentos respectivos;\nXXXII. Ejercer todas aquellas acciones tendientes a la preservación y restauración del equilibrio ecológico, así como la prevención y control de la contaminación del aire, agua y suelo que no sean de competencia federal; y\nXXXIII. Prevenir, regular y controlar la contaminación a la atmósfera generada por la emisión de ruido, vibraciones, energía térmica, lumínica, radiaciones electromagnéticas y olores perjudiciales al equilibrio ecológico o al ambiente, proveniente de fuentes fijas que funcionen como establecimientos industriales, así como, en su caso, de fuentes móviles que no sean de competencia Federal;\nLey de Protección al Ambiente para el Estado de Baja California. Página 8\nXXXIV. La Secretaría propondrá los derechos que correspondan al aprovechamiento\nFederación, y\nXXXV. Instrumentar, ejecutar y evaluar programas, proyectos, políticas, servicios y en la materia;\nXXXVI. Coordinarse con la Secretaría de Salud del Estado para elaborar, dar seguimiento y hacer público, los estudios epidemiológicos relacionados con la calidad del aire;\nFracción Reformada\nXXXVII. Identificar, delimitar y establecer corredores biológicos, así como diseñar y proponer las estrategias para su implementación;\nFracción Reformada\nXXXVIII. Formular los Criterios y Normas de Producción Sustentable que tendrán por objeto establecer y describir los criterios y buenas prácticas de producción sustentable que las y los fabricantes de bolsas de plástico deban implementar en sus procesos, operaciones y productos;\nFracción Adicionada\nFracción Reformada\nXXXIX. Garantizar la protección de las plantas nativas;\nFracción Adicionada\nXL. La formulación, evaluación, aplicación y vigilancia de programas de siembra y distribución de árboles, plantas tradicionales y plantas medicinales en zonas marginadas y zonas indígenas, de conformidad con lo que establezca la Secretaría para alcanzar el objetivo del programa; y,\nFracción Adicionada\nXLI. Las demás que conforme a la legislación local y federal aplicable le correspondan.\nFracción Recorrida\nArtículo Reformado\nARTÍCULO 9.- Corresponde a los municipios, el ejercicio de las siguientes atribuciones:\nI. Formular, conducir y evaluar la política ambiental en su jurisdicción territorial, en el ámbito de su competencia, en congruencia con la legislación aplicable;\nII. Formular, ejecutar y evaluar el programa municipal de protección al ambiente;\nIII. Aplicar los instrumentos de política ambiental previstos en la ley;\nLey de Protección al Ambiente para el Estado de Baja California. Página 9\nIV. Preservar y restaurar el equilibrio ecológico y proteger el ambiente en bienes y zonas de su jurisdicción, en materias de su competencia;\nV. Ejercer las funciones que le transfieran la Federación y el estado en materia ambiental, en los términos que establezca la ley y los convenios o acuerdos de coordinación y descentralización correspondientes;\nVI. Formular y expedir los programas de ordenamiento ecológico del municipio, así como el control y cambio de uso de suelo que se establezcan en dichos programas, conforme lo dispone la Ley General y esta Ley;\nVII. Coordinarse con la Secretaría en la formulación de los programas de\nOrdenamiento Ecológico Regionales que los involucren;\nVIII. Evaluar y otorgar la licencia para aquellos casos que esta ley determina, así como participar en la evaluación del impacto ambiental de obras o actividades de competencia estatal, cuando las mismas se realicen en el ámbito de su circunscripción territorial, a solicitud expresa de la autoridad estatal, o por convenio;\nIX. Emitir los reglamentos y bandos municipales para proveer el cumplimiento de la presente Ley en las materias de su competencia, así como para establecer las sanciones correspondientes;\nX. Crear la unidad de gestión ambiental a que se refiere esta ley;\nXI. Proponer ante la legislatura local, iniciativas de leyes o decretos en materia ambiental y participar en el análisis que de las mismas realice la comisión de dictamen correspondiente;\nXII. Sujetar a los establecimientos mercantiles o de servicios, a los requerimientos que consideren pertinentes en materia de prevención y control de la contaminación atmosférica, del agua y del suelo, en los bandos o reglamentos que expidan;\nXIII. Regular la realización de eventos públicos y en su caso, establecer restricciones para efectos de protección al ambiente o conservación ecológica de los ecosistemas, zonas o bienes de jurisdicción municipal;\nXIV. Formular y conducir la política municipal de información y difusión en materia ambiental;\nXV. Promover la participación de la sociedad en materia ambiental;\nXVI. Crear y administrar zonas de preservación ecológica de los centros de población, áreas verdes urbanas, parques urbanos, jardines públicos y demás áreas análogas previstas en esta ley;\nFracción Reformada\nLey de Protección al Ambiente para el Estado de Baja California. Página 10\nXVII. Otorgar y revocar los permisos, licencias, concesiones y en general las autorizaciones derivadas de la presente Ley, que sean de su competencia y solicitar la cancelación o revocación del permiso, licencia, autorización o concesión a la autoridad otorgante, cuando esta sea distinta a la municipal;\nXVIII. Aplicar las disposiciones jurídicas en materia de prevención y control de la contaminación de las aguas que se descarguen a los sistemas de drenaje y alcantarillado de los centros de población, así como de las aguas nacionales que tengan asignadas, con la participación que conforme a ésta, y otras leyes le corresponda al Estado;\nXIX. Aplicar las disposiciones jurídicas en materia de prevención y control de la contaminación atmosférica generada por fuentes fijas que funcionen como establecimientos mercantiles o de servicios, obras o actividades que realicen las dependencias o entidades de la administración pública municipal, quemas dentro de la zona urbana, quemas agropecuarias, así como de emisiones de contaminantes provenientes de fuentes móviles de competencia municipal con la participación que de acuerdo con la presente Ley, corresponda al Ejecutivo del Estado;\nXX. Aplicar las disposiciones jurídicas relativas a la prevención y control de la contaminación por ruido, vibraciones, energía térmica, radiaciones electromagnéticas y lumínicas y olores perjudiciales para el equilibrio ecológico y el ambiente, proveniente de fuentes fijas que funcionen como establecimientos mercantiles o de servicios, así como la vigilancia del cumplimiento de las disposiciones que, en su caso, resulten aplicables a las fuentes móviles excepto las de competencia federal y estatal;\nXXI. Aplicar las disposiciones jurídicas relativas a la prevención y control de los efectos sobre el ambiente ocasionados por la generación, transporte, almacenamiento, tratamiento y disposición final de los residuos sólidos urbanos de conformidad con lo dispuesto por la Ley General y la presente Ley;\nXXII. Ordenar la realización de visitas de inspección para verificar el cumplimiento de la presente Ley, en las materias que sean de su competencia;\nXXIII. Aplicar las sanciones administrativas y medidas técnicas correspondientes por infracciones a esta Ley y sus reglamentos;\nXXIV. Ordenar, cuando exista riesgo inminente de desequilibrio ecológico o contaminación que afecte la salud pública, las medidas de seguridad previstas en esta Ley;\nXXV. Emitir las resoluciones que pongan fin al procedimiento de inspección y vigilancia, así como cualquier resolución que sea necesaria, de conformidad con la Ley, durante el procedimiento;\nXXVI. Admitir y resolver los recursos de revisión que se interpongan con motivo de la aplicación de la presente Ley;\nLey de Protección al Ambiente para el Estado de Baja California. Página 11\nXXVII. Otorgar, en el ámbito de su competencia, concesiones a personas físicas o morales, para la prestación de los servicios públicos especializados en la preservación y restauración del equilibrio ecológico, así como en la conservación del ambiente;\nXXVIII. Promover y participar en la elaboración y celebración de convenios o acuerdos de coordinación que se lleven a cabo entre el Ejecutivo del Estado y la Federación, con el objeto de que los municipios asuman el ejercicio de las funciones que señalan la Ley\nGeneral y esta Ley;\nXXIX. Celebrar convenios o acuerdos de coordinación con otros municipios, el\nEjecutivo del Estado y la Federación, con el objeto de que asuman el ejercicio de las funciones y atribuciones que señalan la Ley General y esta Ley y los reglamentos municipales;\nXXX. Emitir recomendaciones a las autoridades federales y estatales, con el propósito de promover el cumplimiento de la legislación ambiental;\nXXXI. Coordinar la participación de las dependencias y entidades de la administración pública municipal, en las acciones de cultura ambiental, de prevención y control de deterioro ambiental, preservación, protección y restauración del ambiente en su jurisdicción territorial, así como celebrar con estas los acuerdos que sean necesarios con el propósito de dar cumplimiento a la presente Ley;\nXXXII. Participar en la atención de los asuntos que afecten el equilibrio ecológico de dos o más municipios y que generen efectos ambientales en su circunscripción territorial;\nXXXIII. Participar en la atención de contingencias ambientales y emergencias ecológicas conforme a las políticas y programas de protección civil que al efecto se establezcan;\nXXXIV. Promover y realizar acciones relacionadas con la protección, preservación y restauración del ambiente, que permita la incorporación de los diferentes sectores de la comunidad, a fin de desarrollar en la población, una mayor cultura ambiental, así como difundir el contenido de esta ley y promover su conocimiento;\nXXXV. Promover y realizar programas para el desarrollo de técnicas y procedimientos que permitan prevenir, controlar y abatir el deterioro ambiental, propiciar el aprovechamiento sustentable de los recursos naturales y la conservación de los ecosistemas, con instituciones de educación superior, centros de investigación científica y tecnológica y el sector privado;\nXXXVI. Requerir a los responsables de empresas de competencia municipal, la generación de contaminantes;\nXXXVII. Regular y aplicar las disposiciones jurídicas relativas a la prevención y control de la contaminación generada por fuentes móviles, así mismo, para los sistemas de\nLey de Protección al Ambiente para el Estado de Baja California. Página 12 identificar los que, dentro de su competencia, puedan ser sujetos a planes de manejo; y,\nFracción Reformada\nXXXVIII.- Los demás asuntos que en la materia les concedan la Ley General, esta\nLey, otros ordenamientos legales y reglamentos aplicables.\nArtículo Reformado\nARTÍCULO 10.- A fin de garantizar un medio ambiente adecuado para el desarrollo, bienestar y elevamiento de la calidad de vida de la población, el Estado y los municipios promoverán el desarrollo ambientalmente planificado e incorporarán la dimensión ambiental en los programas y actividades de sus dependencias y organismos.\nLos Poderes Legislativo, Ejecutivo y Judicial del Estado, las dependencias y organismos de los gobiernos Municipales, y los Órganos constitucionales autónomos deberán de contar en sus oficinas e instalaciones con contenedores especiales para el reciclaje de las distintas clases de desperdicios.\nEl recurso financiero que se recaude del proceso de reciclado se destinará a la integración de los fondos ambientales previstos en esta Ley.\nArtículo Reformado\nARTÍCULO 11.- Los organismos públicos de competencia estatal o municipal que administren el agua, podrán asumir las facultades a que se refiere la Ley General, además de aquellas a que se refiere esta ley y que tenga como propósito regular el aprovechamiento sustentable de las aguas de jurisdicción estatal y municipal y prevenir y controlar la contaminación de las mismas, para lo cual deberán celebrar los acuerdos o convenios de coordinación en la materia que correspondan.\nARTÍCULO 12.- Los convenios de coordinación que se celebren entre el Ejecutivo del\nEstado y la Federación o con los municipios, además de las bases a que se refiere la Ley\nGeneral, deberán ajustarse a las siguientes:\nI. Ser congruente su propósito, con las disposiciones del Plan Estatal de Desarrollo y la política ambiental del estado;\nII. Procurar que en los mismos se establezcan condiciones que faciliten el proceso la administración pública estatal y municipal; y\nIII. Las demás que tengan por objeto dar cumplimiento a lo dispuesto en la presente\nLey.\nCAPÍTULO III\nPolítica Ambiental\nARTÍCULO 13.- Se consideran instrumentos de la política ambiental estatal: la planeación ambiental, el fondo ambiental, la evaluación del impacto ambiental, la\nLey de Protección al Ambiente para el Estado de Baja California. Página 13 investigación y educación ambiental, el ordenamiento ecológico, instrumentos económicos, la regulación de los asentamientos humanos, las normas ambientales estatales y la autoregulación y las auditorías ambientales.\nARTÍCULO 14.- Para la formulación, evaluación y ejecución de la política ambiental y sus instrumentos previstos en esta Ley, y en las demás disposiciones en materia de prevención, preservación y restauración del equilibrio ecológico y protección al ambiente en el territorio del estado, además de los que establece la Ley General, se observarán los siguientes principios:\nI. Los ecosistemas son patrimonio común de la sociedad y de su equilibrio dependen la vida y las posibilidades productivas del estado;\nII. Los ecosistemas y sus elementos deben ser aprovechados asegurando una productividad sustentable, compatible con su equilibrio e integridad;\nIII. Toda persona tiene derecho a disfrutar de un ambiente adecuado para su desarrollo, salud y bienestar, así como el deber de conservarlo. Las autoridades en los términos de ésta y otras leyes, tomarán las medidas para garantizar su cumplimiento;\nIV. Las autoridades y la sociedad deben asumir la responsabilidad de la protección ambiental y la preservación del equilibrio ecológico;\nV. Quien realice obras o actividades que afecten o puedan afectar al ambiente, esta obligado a prevenir, minimizar o reparar los daños que cause, así como a asumir los costos que dicha afectación implique;\nVI. Las autoridades de la materia, deben asegurarse de que se incentive a quienes protejan el ambiente y aprovechen de manera sustentable los recursos naturales;\nVII. La responsabilidad respecto al equilibrio ecológico, comprende tanto las condiciones presentes como las que determinarán la calidad de vida de las futuras generaciones;\nVIII. La prevención de las causas que los generan, es el medio más eficaz para evitar los desequilibrios ecológicos;\nIX. El aprovechamiento de los recursos naturales renovables debe realizarse de manera que se asegure el mantenimiento de su diversidad y renovabilidad;\nX. Los recursos naturales no renovables deben utilizarse de modo que se evite el peligro de su agotamiento y la generación de efectos ecológicos adversos;\nXI. La coordinación entre las dependencias y entidades de la administración pública y entre los distintos niveles de gobierno y la concertación con la sociedad, son indispensables para la eficacia de las acciones ecológicas;\nLey de Protección al Ambiente para el Estado de Baja California. Página 14\nXII. El sujeto principal de la concertación ecológica, es no solamente el individuo, sino también los grupos y organizaciones sociales. El propósito de la concertación de naturaleza;\nXIII. En el ejercicio de las atribuciones que las leyes confieren al estado para regular, promover, restringir, prohibir, orientar, y en general, inducir las acciones de los particulares en los campos económico y social, se consideraran los criterios de preservación y restauración del equilibrio ecológico y protección al ambiente;\nXIV. La prevención y el control de la contaminación ambiental y el adecuado aprovechamiento de los elementos naturales, son factores fundamentales para elevar la calidad de vida de la población;\nXV. Es interés del estado que las actividades que se lleven a cabo dentro de su territorio, no afecten el equilibrio ecológico de otras entidades federativas;\nXVI. Es interés del estado alcanzar el desarrollo sustentable y propiciar la erradicación de la pobreza;\nXVII. Se tendrá como meta ambiental, la fijación de límites de generación emisión y descargas de contaminantes cada vez más exigentes y adecuados para el bienestar, tomando como base la utilización materias primas menos contaminantes y tecnologías más limpias;\nXVIII. Las autoridades promoverán la formación de un mercado de materiales y residuos reutilizables y reciclables; y\nXIX. El principio de subsidiariedad, que permita a las estructuras municipales desarrollar plenamente sus atribuciones y asegure la participación corresponsable de las comunidades localizadas en las demarcaciones interiores de su territorio.\nCAPÍTULO IV\nInstrumentos de política ambiental\nSECCION I\nPlaneación ambiental\nARTÍCULO 15.- En la planeación del desarrollo estatal y municipal deberá incorporarse lo ambiental como una de sus dimensiones, considerar los principios e instrumentos de la política ambiental, la educación ambiental, los programas de aplicables sobre la materia. administración pública estatal y municipal, así como en el ejercicio de las atribuciones que\nLey de Protección al Ambiente para el Estado de Baja California. Página 15 las leyes confieran al gobierno estatal y los municipios para regular, promover, restringir, prohibir, orientar, y en general, inducir las acciones de los particulares en los campos económico y social, se observarán los lineamientos de política ambiental establecidos el presente Ley.\nEn la formulación, ejecución y evaluación de la política ambiental se considerará la participación de los tres niveles de gobierno y los distintos sectores de la sociedad.\nArtículo Reformado\nARTÍCULO 15 BIS.- Los Poderes Legislativo, Judicial y Ejecutivo, así como los\nMunicipios del Estado de Baja California, expedirán sus manuales de sistemas de manejo ambiental, que tendrán por objeto ser una herramienta que guíe a la optimización de los recursos materiales y energéticos que se utilizan en sus actividades administrativas y operativas diarias, con el fin de reducir costos ambientales y financieros.\nArtículo Reformado\nARTÍCULO 16.- La entidad pública responsable de la planeación del estado, participará en planeación ambiental, en los términos que establezca la legislación aplicable, particularmente en lo que se refiere a:\nI. Asistir al Ejecutivo del Estado y al Consejo Estatal de Protección al Ambiente en materia de planeación ambiental;\nII. Coordinar la participación de los tres niveles de gobierno y de la sociedad en la elaboración de programas ambientales, conjuntamente con la Secretaría;\nIII. Colaborar en la instrumentación de los planes y programas de ordenamiento ecológico estatal, regionales y municipales;\nIV. Promover programas de difusión y educación ambiental, en coordinación con la\nSecretaría;\nV. Fomentar la creación, restauración y mantenimiento de áreas naturales protegidas de competencia estatal y municipal;\nVI. Dar seguimiento a los programas que en materia ambiental elabore el Ejecutivo del Estado, en coordinación con el Consejo Estatal de Protección al Ambiente;\nVII. Emitir su opinión a las autoridades competentes respecto de problemas relativos al objeto de la presente ley; y\nVIII. Promover consultas en materia ambiental, a solicitud o en coordinación con las autoridades ambientales.\nLey de Protección al Ambiente para el Estado de Baja California. Página 16\nARTÍCULO 17.- Para apoyar y orientar las acciones que realiza el Ejecutivo del\nEstado en cumplimiento del objeto de la presente Ley, se crea el Consejo, como un órgano normativo y de equilibrio entre sociedad y gobierno. El Consejo es la autoridad estatal estado, así como promover la coordinación entre el estado y los municipios en la participación de la sociedad en la solución.\nARTÍCULO 18.- El Consejo, quedará integrado de la siguiente forma:\nI. La Persona Titular del Poder Ejecutivo del Estado, que fungirá como presidente;\nFracción Reformada\nII. La Persona Titular de la Secretaría, que fungirá como secretario;\nFracción Reformada\nIII. La Persona Titular de la Secretaría de Hacienda;\nFracción Reformada\nIV. La Persona Titular de la Secretaría de Educación\nFracción Reformada\nV. La Persona Titular de la Secretaría de Economía e Innovación;\nFracción Reformada\nVI. La Persona Titular de la Secretaría de Turismo;\nFracción Reformada\nVII. La Persona Titular de la Secretaría de Agricultura y Desarrollo Rural;\nFracción Reformada\nVIII. La Persona Titular de la Secretaría de Pesca y Acuacultura;\nFracción Reformada\nIX. La o el Presidente de la Comisión del Congreso del Estado responsable de la materia ambiental,\nFracción Reformada\nX. Una persona ciudadana por cada uno de los municipios, electos mediante procedimientos participativos y transparentes; y,\nFracción Reformada\nXI. La Persona Titular del área de Protección al Ambiente de cada uno de los gobiernos municipales.\nFracción Reformada honoríficos. Los apoyos que sus integrantes ciudadanas y ciudadanos deban recibir para el mejor ejercicio de sus funciones, serán establecidos en el reglamento.\nPárrafo Reformado\nArtículo Reformado\nLey de Protección al Ambiente para el Estado de Baja California. Página 17\nARTÍCULO 19.- El Consejo, sesionará en forma ordinaria cada dos meses y, extraordinariamente, cuantas veces sea necesario, a juicio de su Presidente, quien emitirá la convocatoria respectiva. de sesiones. Si el Consejo deja de sesionar en las fechas acordadas, cualquiera de sus integrantes podrá solicitar al presidente emita la convocatoria que corresponda.\nEl quórum para celebrar sesiones legalmente válidas, se establece a partir de la asistencia de la mayoría de sus integrantes, pero deberá incluir la presencia del Presidente o su suplente. Las sesiones del Consejo serán públicas pero sólo sus titulares asistirán con voz.\nPor acuerdo previo del Consejo o decisión de su presidente, se podrá invitar a las sesiones que lo ameriten, a funcionarios de las dependencias de los gobiernos federal, estatal y municipal y representantes de sectores de la sociedad, que tengan relación directa o indirecta con los asuntos que se vayan a tratar. Los invitados asistirán únicamente con voz y para intervenir únicamente en los asuntos para los que fueron convocados.\nArtículo Reformado\nARTÍCULO 20.- Las resoluciones del Consejo se tomarán preferentemente por consenso, y en caso de que no produzca, en orden de prelación: a) Por las dos terceras partes de los asistentes y b) por mayoría simple. De cada sesión se levantará acta circunstanciada, la cual deberá ser firmada por quien haya presidido la misma, así como por el Secretario Técnico.\nARTÍCULO 21.- La designación o elección de los miembros ciudadanos del Consejo, así como su integración, operación y funcionamiento, se determinará conforme a lo que establezca su reglamento. Su elección, en el ámbito social, educativo o profesional en que de procedencia, se hará democráticamente, estando sujeto su desempeño a la evaluación correspondiente y debiendo rendir cuentas a sus representados. ambiental, en cualesquiera de sus ámbitos y durarán en su cargo durante un período de tres años, pudiendo ser reelectos para un período inmediato posterior, cubriendo lo que establece el párrafo anterior y lo que determine su reglamento.\nARTÍCULO 22.- Son funciones del Consejo:\nI. Formular y aprobar su reglamento;\nLey de Protección al Ambiente para el Estado de Baja California. Página 18\nII. Proponer, revisar y evaluar la política ambiental del estado con el propósito de ambiente adecuado para su bienestar y desarrollo;\nIII. Participar en materia de planeación del desarrollo, en coordinación con la instancia de planeación del estado y otras instancias locales y nacionales, a afecto de verificar que el desarrollo promovido en el estado, sea ambientalmente planificado y se avance en el territorio del estado por la senda del desarrollo sustentable;\nIV. Revisar y aprobar los planes generales y específicos y los programas que estipula la presente ley;\nV. Fortalecer la participación de los ciudadanos y sus organizaciones en el diseño de la política ambiental y en el ejercicio de la protección ambiental y de la conservación de los recursos naturales;\nVI. Diseñar, en coordinación con la Secretaría y los municipios, una estrategia que permita incorporar la dimensión ambiental en las distintas esferas de la administración pública, contribuyendo a normar con un enfoque ambiental integral en cada una de las instancias involucradas en la gestión ambiental;\nVII. Aprobar, dar seguimiento y evaluar el cumplimiento de los objetivos de política ambiental del estado contenidos en el Plan Estatal de Desarrollo y los planes y programas ambientales, vigilando su vigencia y cumplimiento conforme a los términos establecidos;\nVIII. Emitir criterios en materia de política ambiental, en el mediano y largo plazo;\nIX. Establecer los lineamientos para la elaboración de planes y programas que conforme a la política ambiental del estado deba elaborar y ejecutar la Secretaría;\nX. Promover y fomentar la participación ciudadana en la formulación, evaluación y ejecución de programas ambientales;\nXI. Definir las bases y dar seguimiento de los convenios, acuerdos, reglamentos y formatos que la Secretaría desee establecer;\nXII. Emitir opinión sobre la declaratoria y dar seguimiento a programas de manejo de áreas naturales protegidas;\nXIII. Dar seguimiento a la aplicación de los instrumentos económicos que la\nSecretaría proponga para incentivar el cumplimiento de la política ambiental;\nXIV. Emitir opinión y avalar las normas ambientales estatales que la Secretaría proponga;\nLey de Protección al Ambiente para el Estado de Baja California. Página 19\nXV. Proponer el Programa Estatal de Protección al Ambiente y demás planes y programas derivados de esta ley;\nXVI. Fomentar la cultura y educación ambiental en la sociedad, incorporando en esta tarea a las instituciones educativas y organismos no gubernamentales, mediante la promoción de la cooperación entre ellos y las instituciones públicas;\nXVII. Revisar, emitir opinión y proponer los acuerdos y convenios que en materia de descentralización de la política ambiental celebre el Ejecutivo del Estado con la Federación, otras entidades federativas o los municipios del Estado;\nXVIII. Ser parte coadyuvante con el organismo responsable de la instrumentación de plebiscitos promovidos por los ciudadanos, el Ejecutivo y el Congreso sobre aquellos proyectos de envergadura tal que supongan un gran impacto ambiental o una utilización masiva de recursos naturales, o bien se proyecten realizar en áreas naturales protegidas;\nXIX. Ser parte coadyuvante con el organismo responsable de la instrumentación de referéndum respecto de reformas, creación o derogación de artículos de la Constitución ambientales y la conservación de los recursos naturales; y\nXX. Las demás que conforme a esta Ley y sus reglamentos le correspondan.\nARTÍCULO 23.- Las resoluciones adoptadas por el Consejo, serán notificadas a las autoridades que por materia correspondan para efecto de que, dentro del ámbito de su competencia, adopten las medidas para implementarlas. Estas autoridades, deberán notificar al Consejo, con debida oportunidad, de las acciones que se programen para ejecutar tales resoluciones.\nARTÍCULO 24.- La Secretaría, en coordinación con los municipios, elaborará y pondrá en ejecución los planes y programas ambientales del estado, los cuales serán considerados como los documentos básicos de la política ambiental en el estado.\nLa Secretaría, a más tardar el 31 de octubre de cada año, elaborará y presentará para su aprobación al Consejo, el Programa Estatal de Protección al Ambiente, que incluirá un informe del estado que guarda el ambiente, debiéndose hacer de conformidad con los ambiental general.\nARTÍCULO 25.- Derogado.\nArtículo Derogado\nSECCION II\nOrdenamiento ecológico\nLey de Protección al Ambiente para el Estado de Baja California. Página 20\nARTÍCULO 26.- Los programas de ordenamiento ecológico a que se refiere la asentamientos humanos, así como para el aprovechamiento sustentable de los recursos naturales de que se trate. Para ello deberán considerar los atributos físicos, bióticos y socioeconómicos del territorio de que se trate, debiendo especificar los lineamientos y directrices para su ejecución, seguimiento, evaluación y modificación.\nCada cuatro años, la Secretaría deberá presentar al Consejo, para su aprobación, una actualización al Programa de Ordenamiento Ecológico del Estado, el cual contendrá los cambios o modificaciones presentados en el ambiente estatal, de acuerdo a los parámetros caracterizados en el programa de ordenamiento vigente o los que deriven de posteriores investigaciones.\nARTÍCULO 27.- En la formulación de los programas de ordenamiento ecológico se considerarán los siguientes criterios:\nI. La naturaleza y características de los ecosistemas existentes;\nII. La vocación de cada zona, en función de sus elementos naturales, la distribución de la población y las actividades económicas predominantes;\nIII. Los desequilibrios existentes en los ecosistemas por efecto de los asentamientos humanos, de las actividades económicas o de otras actividades humanas o fenómenos naturales;\nIV. El equilibrio que debe existir entre los asentamientos humanos y sus condiciones ambientales, y\nV. El impacto ambiental de nuevos asentamientos humanos, vías de comunicación y demás obras y actividades.\nVI. Las zonas prioritarias para la conservación, corredores biológicos y áreas naturales protegidas federales, estatales y municipales.\nArtículo Reformado\nARTÍCULO 28.- El ordenamiento ecológico del estado se llevará a cabo conforme a lo dispuesto en la Ley General y esta Ley, a través de los programas de ordenamiento ecológico correspondientes:\nI. Regionales: que comprendan la entidad federativa o una parte de ésta; y\nII. Locales: que involucran la totalidad o una parte de un municipio.\nARTÍCULO 29.- Los programas de ordenamiento ecológico deberán ser considerados en:\nLey de Protección al Ambiente para el Estado de Baja California. Página 21\nI. Los programas de desarrollo urbano estatal y municipal, así como en los programas de vivienda que formulen las autoridades estatales y municipales;\nII. Autorizaciones en materia de impacto ambiental y en general en el establecimiento de actividades productivas;\nIII. La fundación de nuevos centros de población;\nIV. El aprovechamiento de los recursos naturales en el estado;\nV. La creación de áreas naturales protegidas de competencia estatal y municipal, zonas prioritarias para la conservación y corredores biológicos; y\nVI. La expansión o apertura de zonas agrícolas o de uso pecuario y en general en los cambios de uso de suelo fuera de los centros de población.\nArtículo Reformado\nARTÍCULO 30.- Corresponde a la Secretaría, en coordinación con los municipios, la elaboración y revisión de los programas de ordenamiento ecológico regionales, conforme a los principios de la política ambiental previstos en esta Ley.\nARTÍCULO 31.- Corresponde al Ejecutivo del Estado la expedición de los programas de ordenamiento ecológico regionales y los planes y programas estatales que de ellos se deriven.\nLos municipios formularán y expedirán los programas de ordenamiento ecológico locales, y podrán promover y convenir su participación en la formulación de los programas ordenamientos ecológicos regionales y de otros que consideren convenientes cuando involucren su territorio.\nARTÍCULO 32.- En la elaboración y revisión de los programas de ordenamiento ecológico deberá garantizarse la participación de la sociedad, previo a su expedición.\nARTÍCULO 33.- Una vez aprobados los programas de ordenamiento ecológico, la autoridad competente, ordenará su publicación en el Periódico Oficial del Gobierno del\nEstado.\nARTÍCULO 34.- Los programas de ordenamiento ecológico regional y los planes y programas derivados del mismo, deberán ser revisados y en su caso, actualizados cada cuatro años.\nLey de Protección al Ambiente para el Estado de Baja California. Página 22\nARTÍCULO 35.- Los programas de ordenamiento ecológico vigentes, se harán del el aprovechamiento de recursos naturales de competencia federal.\nSECCION III\nInstrumentos económicos\nARTÍCULO 36.- El estado y los municipios, en el ámbito de sus respectivas competencias y conforme a lo dispuesto en la Ley General, diseñarán, desarrollarán y aplicarán instrumentos económicos que incentiven el cumplimiento de los objetivos de la política ambiental.\nARTÍCULO 37.- Se consideran instrumentos económicos:\nI. Los mecanismos normativos y administrativos de carácter económico, fiscales, financieros y de mercado que establece la Ley General; y\nII. Los demás que al efecto propongan y desarrollen el estado y los municipios en el ámbito de sus competencias.\nARTÍCULO 38.- Se considerarán prioritarias, para efectos de la aplicación de instrumentos económicos, las actividades relacionadas con:\nI. El aprovechamiento sustentable del agua, y la prevención de su contaminación, en términos de lo señalado en las Normas Oficiales Mexicanas aplicables y las normas ambientales del Estado;\nII. La investigación, desarrollo, incorporación y utilización de mecanismos, equipos y tecnologías que tengan por objeto evitar, reducir o controlar la contaminación o deterioro ambiental, así como el uso eficiente de energía y recursos naturales;\nIII. El establecimiento y reubicación de instalaciones industriales, comerciales y de servicios en áreas ambientales adecuadas;\nIV. El establecimiento, manejo, conservación, mejoramiento y vigilancia de áreas naturales protegidas y áreas verdes urbanas;\nFracción Reformada\nV. La investigación e incorporación de sistemas de ahorro de energía y de uso de fuentes de energía más eficientes y menos contaminantes;\nVI. La fabricación, instalación y mantenimiento de equipos de control y tratamiento de residuos, aguas residuales y en general, de contaminantes de la atmósfera, agua y suelo;\nLey de Protección al Ambiente para el Estado de Baja California. Página 23\nVII. La sustitución o eliminación de sustancias que afecten o puedan llegar a afectar la salud y al ambiente;\nVIII. El saneamiento y restauración ambiental voluntario, cuando quien lo realice no haya sido responsable de la contaminación o deterioro;\nIX. Las actividades de reciclaje de residuos de manejo especial y residuos sólidos urbanos;\nX. La incorporación y utilización de mecanismos, equipos y tecnologías que tengan por objeto, evitar, reducir o controlar la contaminación lumínica; y\nXI. En general, aquellas acciones relacionadas con la preservación y restauración del equilibrio ecológico y la protección al ambiente.\nArtículo Reformado\nSECCION IV\nDel fondo ambiental\nARTÍCULO 39.- Los ingresos que se obtengan de las multas por infracciones a lo dispuesto en la Ley General, esta Ley, sus reglamentos y demás disposiciones que de ellos se deriven, así como los que se perciban por concepto del otorgamiento de permisos, autorizaciones, concesiones y licencias en materia ambiental, indemnizaciones que reciba el\nGobierno del Estado por daños al ambiente, herencias, aportaciones o donativos, así como rendimientos financieros, conforme lo determinen en los ordenamientos aplicables, se destinarán a la integración de fondos ambientales en los ámbitos que corresponda.\nLos recursos de los fondos ambientales serán aplicados a:\nI. La realización de acciones de preservación de la biodiversidad y el equilibrio ecológico, así como aquellas de protección y restauración ambiental;\nII. La administración de las áreas naturales en que se generen dichos ingresos;\nIII. El desarrollo de programas vinculados con la inspección y la vigilancia en las materias a que se refiere esta Ley;\nIV. El desarrollo de programas de educación e investigación en materia ambiental; y\nV. Restauración de sitios contaminados.\nVI. El desarrollo y adquisición de nuevas tecnologías en materia de prevención y mitigación de contaminación ambiental;\nVII. La promoción de la participación de grupos y organizaciones sociales y empresariales, instituciones académicas y de investigación; y\nLey de Protección al Ambiente para el Estado de Baja California. Página 24\nVIII. El establecimiento, manejo, conservación, mejoramiento y equipamiento de áreas verdes urbanas y el fortalecimiento de los programas ambientales en los municipios.\nFracción Reformada\nIX. A la protección de las áreas que fungen como zonas de recarga, de provisión, de almacenamiento, corredores biológicos, de belleza escénica y conservación de germoplasma estratégicas definidas por la Secretaría;\nX. A la adquisición de terrenos situados en áreas naturales protegidas estatales, especialmente en las zonas núcleo de las mismas o en sitios estratégicos para la conservación de la biodiversidad;\nTodo lo relacionado con la integración, administración y gasto de los recursos constitutivos de dichos fondos serán establecidos en el reglamento respectivo, el cual será aprobado por el Consejo, o en su caso los reglamentos municipales.\nArtículo Reformado\nSECCIÓN V\nRegulación ambiental de los asentamientos humanos\nARTÍCULO 40.- Para contribuir al logro de los objetivos de la política ambiental, la planeación del desarrollo urbano y la vivienda, se deberán considerar los criterios que establece la Ley General, así como los siguientes:\nI. En las áreas que se determinen como aptas para uso industrial, próximas a zonas habitacionales, se promoverá la instalación de industrias de bajo impacto y riesgo y aquellas que utilicen la mejor tecnología disponible, materia prima y combustibles que generen menor contaminación, previendo la instalación y operación de dispositivos y sistemas de control de alta eficiencia; y\nII. En la determinación de usos de suelo que definan los programas de desarrollo urbano respectivos, se considerarán las condiciones topográficas, climatológicas y meteorológicas, para asegurar la adecuada dispersión de contaminantes.\nSECCIÓN VI\nEvaluación del impacto ambiental\nARTÍCULO 41.- La evaluación del impacto ambiental es el procedimiento a través del planes y programas de desarrollo de alcance regional, así como de las obras y actividades que se refiere este capítulo, a fin de evitar o reducir al mínimo sus efectos negativos sobre el ambiente. El procedimiento de evaluación del impacto ambiental se inicia mediante la presentación del documento denominado manifestación de impacto ambiental.\nLey de Protección al Ambiente para el Estado de Baja California. Página 25\nARTÍCULO 42.- Se requiere previamente la evaluación y autorización de la Secretaría en materia de impacto ambiental, en los siguientes casos:\nI. Los planes y programas regionales, estatales y municipales, en materia de desarrollo urbano, turístico, de vivienda, agropecuarios, sectoriales de industria, de centros de población, así como aquellos que en general promuevan las actividades económicas o prevean el aprovechamiento masivo de los recursos naturales del estado;\nII. Obras o actividades que pretendan realizarse fuera de los límites de los centros de población, así como aquellas que se ubiquen dentro de áreas naturales protegidas de competencia estatal o municipal, así como las que establezcan los programas de ordenamiento ecológico regionales y locales;\nIII. Las obras y actividades de carácter público o privado, destinadas a la prestación de un servicio público;\nIV. Vías estatales de comunicación, incluidos los caminos rurales;\nV. Zonas, fraccionamientos y parques industriales, incluidas las plantas agroindustriales;\nVI. La prestación de servicios a terceros que tengan por objeto la operación de sistemas de almacenamiento, reuso, reciclaje, incineración, acopio, recolección, transporte, tratamiento, y disposición final de residuos de manejo especial, así como la construcción y operación de los sistemas mencionados;\nVII. Aquellas obras y actividades que no estando expresamente reservadas a la\nFederación en los términos de la Ley General, causen o puedan causar desequilibrios ecológicos, rebasen los límites y condiciones establecidos en las disposiciones jurídicas referidas a la preservación del equilibrio ecológico y la protección al ambiente;\nVIII. Actividades consideradas riesgosas en los términos de esta ley y las que se establezcan en los listados de actividades riesgosas;\nFracción Reformada\nIX. La instalación y operación por parte del generador de residuos industriales de sistemas para el almacenamiento, reuso, recuperación, reciclaje, incineración, tratamiento, confinamiento, o disposición final fuera de la instalación donde se generan dichos residuos;\nFracción Reformada\nX. - Exploración, explotación, extracción y aprovechamiento de materiales o sustancias no reservadas a la Federación, fuera de los centros de población;\nFracción Reformada\nXI. - construcción y operación de rellenos sanitarios y centros de transferencia;\nFracción Reformada\nLey de Protección al Ambiente para el Estado de Baja California. Página 26\nXII. - Para la construcción, operación, funcionamiento o establecimiento de cualquier giro comercial, industrial o de servicios que produzcan impactos ambientales significativos sobre el medio ambiente en zonas agrícolas, ganaderas o pesqueras, que no sean de competencia federal; y,\nFracción Adicionada, recorriéndose la subsecuente\nXIII. - Las que se determinen en los reglamentos, normas ambientales estatales.\nCuando la solicitud de autorización sea en zonas agrícolas, ganaderas o pesqueras y contravenga el Programa de Ordenamiento Ecológico del Estado, la planeación urbana estatal o municipal, no se otorgará la autorización correspondiente.\nPárrafo Adicionado\nLa Secretaría y los Municipios, podrán celebrar convenios de colaboración a fin de que las propias unidades de gestión ambiental municipales realicen las evaluaciones de impacto ambiental y emitan las autorizaciones, cuando las obras o actividades de que se refiere el presente artículo no sean altamente riesgosas, no causen impactos al ambiente o impliquen un uso masivo de recursos naturales de la zona, en los términos de la presente ley.\nPárrafo Reformado\nArtículo Reformado\nARTÍCULO 43.- Se requiere previamente la evaluación y otorgamiento de la licencia ambiental por la autoridad municipal en los siguientes casos:\nI. Obras o actividades comerciales y de servicios que pretendan realizarse dentro del centro de población;\nII. Fraccionamientos industriales y habitacionales que pretenden ubicarse dentro del centro de población;\nIII. Centrales de abastos;\nIV. Aprovechamiento de minerales o sustancias no reservados a la Federación, que constituyan depósitos de naturaleza semejante a los componentes de los terrenos, tales como rocas o productos de su desintegración, para la fabricación de materiales para la construcción u ornato;\nV. La recolección, transporte, almacenamiento, reuso, recuperación y reciclaje de residuos sólidos urbanos; y\nVI. Obras y actividades que estando reservadas a la Federación o al estado se descentralicen a favor del municipio a través del convenio respectivo. actividades de competencia estatal, en aquellos casos que por su ubicación, dimensiones o\nLey de Protección al Ambiente para el Estado de Baja California. Página 27 encuentran expresamente señalados en esta ley.\nEn estos casos la participación en la evaluación de impacto ambiental, se podrá efectuar dentro de los procedimientos de autorización de uso del suelo, construcciones, de ellos se deriven dichos ordenamientos preverán lo necesario a fin de hacer compatible la política ambiental con el desarrollo urbano y evitar la duplicidad innecesaria de procedimientos administrativos en la materia.\nARTÍCULO 44.- Para obtener autorización en materia de impacto ambiental, los interesados, previo a la publicación de cualquier plan o programa o al inicio de cualquier obra o actividad, deberán presentar ante la autoridad competente una manifestación de impacto ambiental, la cual deberá contener, por lo menos, una descripción de los posibles efectos en los ecosistemas que pudieren ser afectados por los planes, programas, obras o actividad de que se trate, considerando el conjunto de los elementos que conforman dichos ecosistemas, así como las medidas preventivas de mitigación y las demás necesarias para evitar y reducir al mínimo los efectos negativos sobre el ambiente.\nCuando se trate de obras y actividades consideradas riesgosas en los términos de esta ley, la manifestación deberá incluir el estudio de riesgo correspondiente.\nSi después de la presentación de una manifestación de impacto ambiental y antes de realizar modificaciones a los planes y programas, obras o actividades respectivas, los interesados deberán hacerlas del conocimiento de la Autoridad, a fin de que ésta, les notifique si es necesaria la presentación de información adicional para evaluar los efectos al ambiente que pudiesen ocasionar tales modificaciones, en los términos de lo dispuesto en esta ley.\nAsimismo, si la información presentada en la manifestación de Impacto Ambiental no contempla los elementos técnicos necesarios que permitan a esta Autoridad determinar los posibles impactos por el desarrollo de la actividad solicitada, se requerirá la presentación de información adicional para evaluar los efectos al ambiente que pudiesen ocasionar las obras o actividades del proyecto respectivo.\nLos contenidos, características y las modalidades de las manifestaciones de impacto ambiental, los estudios de riesgo, serán establecidos por el reglamento de la presente Ley.\nARTÍCULO 45.- Las obras y actividades, que por su ubicación, dimensiones, ambiente, no causen desequilibrios ecológicos, ni rebasen los límites y condiciones y la protección al ambiente, no estarán sujetas a la presentación de la manifestación de impacto ambiental. En estos casos, el responsable de la obra o actividad deberá presentar el\nLey de Protección al Ambiente para el Estado de Baja California. Página 28 documento denominado informe preventivo, de manera previa al inicio de actividades, especialmente cuando:\nI. Existan Normas Oficiales Mexicanas o Ambientales Estatales u otras disposiciones que regulen las emisiones a la atmósfera, las descargas de aguas, manejo y disposición de residuos sólidos urbanos y de manejo especial, el aprovechamiento de los recursos naturales y en general todos los impactos ambientales relevantes que puedan producir las obras y actividades;\nII. Las obras y actividades de que se traten estén expresamente previstas en los planes y programas estatales de desarrollo y planes y programas de desarrollo urbano del centro de población y que hayan sido evaluados y aprobados por la Secretaría; y\nIII. Cuando se trate de instalaciones de obras y actividades expresamente previstas ubicadas en parques industriales o zonas autorizadas en términos de la Ley General y la presente Ley.\nLos formatos con sus contenidos y características del informe preventivo y el listado de las obras y actividades, que requieran de la presentación de un informe preventivo deberán ser analizados y aprobados por el Consejo Estatal de Protección al Ambiente y publicados el Periódico Oficial del Estado.\nUna vez recibido el informe preventivo, la autoridad competente en un plazo no mayor de diez días hábiles, comunicará a los interesados si procede o no la presentación de una manifestación de impacto ambiental, así como la modalidad y plazo para hacerlo.\nTranscurrido el plazo señalado, sin que la autoridad emita la comunicación correspondiente, se entenderá que no es necesaria la presentación de una manifestación de impacto ambiental.\nSi después de la presentación de un informe preventivo y antes de realizar modificaciones a los planes y programas, obras o actividades respectivas, los interesados deberán hacerlas del conocimiento de la Autoridad, a fin de que ésta, les notifique si es pudiesen ocasionar tales modificaciones, en los términos de lo dispuesto en la presente Ley.\nQuedan exentas del trámite de evaluación de impacto ambiental, las obras o actividades que se determinen en los reglamentos y normas ambientales estatales.\nARTÍCULO 46.- Una vez evaluada la manifestación de impacto ambiental, la autoridad competente emitirá, debidamente fundada y motivada, la resolución correspondiente, en la que podrá:\nI. Autorizar los planes, programas y las obras o actividades de que se trate, en los términos solicitados;\nLey de Protección al Ambiente para el Estado de Baja California. Página 29\nII. Autorizar de manera condicionada los planes y programas, así como la realización de la obra o actividad que correspondan, sujetándose a la modificación del proyecto o al establecimiento de medidas adicionales de prevención y mitigación, a fin de que se eviten, la ejecución del proyecto, así como en caso de accidentes;\nIII. Negar la autorización solicitada, cuando:\na) Se contraponga con lo establecido en esta Ley, sus reglamentos, las normas oficiales mexicanas, las normas ambientales estatales y demás disposiciones legales aplicables;\nb) La obra o actividad de que se trate pueda propiciar que una o más especies sean declaradas como amenazadas o en peligro de extinción, o cuando se afecte significativamente a una de dichas especies; y\nc) Exista falsedad en la información proporcionada por los promoventes, respecto de los impactos ambientales de la obra o actividad de que se trate.\nARTÍCULO 47.- La autoridad ambiental competente, a solicitud del promovente integrará a la autorización en materia de impacto ambiental, los demás permisos, licencias y autorizaciones de su competencia, que se requieran para la implementación o realización de los planes, programas, obras o actividades propuestas. Asimismo, deberá exigir el otorgamiento de garantías respecto del cumplimiento de las condicionantes establecidas en la autorización, en aquellos casos expresamente señalados en el reglamento de la ley, cuando durante la realización u operación de las obras y actividades puedan producirse daños graves a los ecosistemas o al ambiente.\nCuando se trate de personas físicas o morales que desempeñen actividades que representen un factor de riesgo potencial para la calidad del ambiente, la autoridad ambiental les requerirá un seguro de responsabilidad civil por daños ambientales.\nARTÍCULO 48.- La Secretaría notificará al municipio correspondiente, que ha recibido manifestación de impacto ambiental, cuando las obras, actividades o programas pretendan realizarse en el ámbito de su circunscripción territorial y que por su ubicación, dimensiones, características o alcances produzcan impactos ambientales significativos, a fin de que éste convenios o acuerdos existentes entre las partes, que lleguen ha realizarse entre ellas, tratándose en especial de los siguientes casos:\nI. Los planes y programas regionales, estatales y municipales en materia de desarrollo urbano, turístico, de vivienda, agropecuarios, sectoriales de industria, de centros de población, así como aquellos que en general promuevan las actividades económicas o prevean el aprovechamiento masivo de los recursos naturales del estado;\nLey de Protección al Ambiente para el Estado de Baja California. Página 30\nII. Obras o actividades dentro de las áreas naturales protegidas de competencia estatal; y\nIII. Actividades consideradas riesgosas en los términos de esta ley.\nEl municipio correspondiente, solicitará la resolución de impacto ambiental que emita la Secretaría, para considerarla como un requisito dentro de los procedimientos de autorización de uso del suelo, construcción, fraccionamiento u otros, excepto en los casos que establezca la presente Ley, exista convenio o acuerdo para que el municipio evalúe y autorice las obras y acciones comprendidas en estas actividades.\nARTÍCULO 49.- La autorización que en materia de impacto ambiental emita la\nSecretaría, no obligará en forma alguna a la autoridad municipal para expedir las autorizaciones que le corresponda en el ámbito de su competencia.\nARTÍCULO 50.- Una vez que la autoridad competente reciba una manifestación de impacto ambiental e integre el expediente respectivo, la pondrá a disposición del público para su consulta, en los términos del reglamento correspondiente.\nEl promovente podrá solicitar que se mantenga en reserva la información que haya sido integrada al expediente, si es comprobable, que de hacerse pública pudiera afectar derechos de propiedad industrial y la confidencialidad de la información comercial que aporte el interesado.\nLa autoridad competente, por la solicitud de cualquier persona de la comunidad de que se trate, podrá llevar a cabo una consulta pública conforme a las bases que se establezcan en el reglamento, sólo en:\nI. Aquellos que prevean el aprovechamiento masivo de los recursos naturales del estado;\nII. Obras o actividades que pretendan realizarse dentro de áreas naturales protegidas de competencia estatal;\nIII. Sitios para disposición final de residuos sólidos urbanos y manejo especial;\nIV. Plantas de tratamientos de aguas residuales destinadas a la prestación de un servicio publico;\nV. Las actividades consideradas riesgosas; y\nVI. Las demás señaladas en el reglamento.\nEl resultado de la consulta pública no tendrá efecto vinculatorio.\nLey de Protección al Ambiente para el Estado de Baja California. Página 31\nARTÍCULO 51.- Al realizar la evaluación del impacto ambiental, la autoridad competente, se ajustará, entre otros aspectos, a los programas de ordenamiento ecológico regional, así como la declaratoria de áreas naturales protegidas y las demás disposiciones jurídicas que resulten aplicables.\nARTÍCULO 52.- Los responsables de la realización de los planes y programas, obras o actividades reguladas en esta sección, deberán sujetarse a las condiciones y limitaciones que señale la autorización respectiva.\nARTÍCULO 53.- Las personas que presten servicios de impacto ambiental, serán responsables ante la autoridad competente, de los informes preventivos, manifestaciones de impacto ambiental y estudios de riesgo que elaboren. Los prestadores de servicios de impacto ambiental, declararán bajo protesta de decir verdad, que para la obtención de los resultados contenidos en dichos documentos se incorporan las mejores técnicas y metodologías existentes, así como la información y medidas de prevención y mitigación sean las más confiables y efectivas.\nAsimismo, los informes preventivos, las manifestaciones de impacto ambiental y los estudios de riesgo, podrán ser presentados por los interesados, instituciones de investigación, colegios o asociaciones profesionales, en este caso, la responsabilidad respecto del contenido del documento corresponderá a quienes lo suscriban.\nEl padrón se constituirá en los términos señalados en el artículo 60, de esta Ley y su reglamento, por las personas físicas o morales que lo soliciten a la Secretaría, en su carácter de prestadores de servicios profesionales especializados, en la preservación y restauración ecológica.\nSECCIÓN VII\nNormas ambientales Estatales\nARTÍCULO 54.- El Ejecutivo del Estado, previo análisis y justificación técnica de la\nSecretaría, emitirá normas ambientales estatales, mediante las cuales se regularán las actividades económicas y establecerán las condiciones de operación de aquellas actividades y procesos que representen un riesgo de impacto al ambiente, de desequilibrio ecológico, de ecológico, la prevención de la contaminación, contingencias ambientales y emergencias ecológicas.\nLa expedición y actualización de las normas ambientales estatales, se sujetará al procedimiento establecido en el reglamento que al efecto se expida. De no existir en el país, deberá contarse con la referencia a la norma o normas internacionales equiparables, preferentemente de orden mundial. Cualquier caso de excepción, será analizado por el\nConsejo, quien emitirá la resolución procedente.\nLey de Protección al Ambiente para el Estado de Baja California. Página 32\nARTÍCULO 55.- En la formulación de normas ambientales estatales deberá características de cada proceso productivo o actividad sujeta a regulación, sin que ello implique el uso obligatorio de tecnologías o equipos específicos.\nARTÍCULO 56.- Las normas ambientales estatales son de cumplimiento obligatorio en el territorio del estado y señalarán su ámbito de validez, vigencia y gradualidad en su aplicación.\nARTÍCULO 57.- Los particulares podrán proponer la creación de normas ambientales estatales, en los términos señalados en el reglamento que al efecto se expida.\nARTÍCULO 58.- Las autoridades estatales y municipales que expidan actos que tengan injerencia en las normas ambientales estatales, deberán tomarlas como referencia en sus determinaciones. Igualmente, tratándose de controversias de carácter civil, mercantil o administrativo de jurisdicción estatal y municipal.\nSECCION VIII\nAutorregulación y auditorias ambientales\nARTÍCULO 59.- La Secretaría fomentará programas de autorregulación y auditoria ambiental y promoverá la aplicación de instrumentos económicos a quienes participen en dichos programas. El desarrollo de la auditoria ambiental es de carácter estrictamente voluntario y no limita las facultades que esta ley confiere a la autoridad en materia de inspección y vigilancia.\nARTÍCULO 60.- La Secretaría convocará a los profesionistas y laboratorios que operen en el estado en el área ambiental, de prevención y control de la contaminación para integrar un padrón de:\nI. Auditores ambientales, los cuales apoyarán a los empresarios obligados al cumplimiento de las disposiciones de la presente Ley, a solicitud de éstos;\nII. Prestadores de servicio, quienes prestarán el servicio de realizar las empresarios;\nIII. Laboratorios ambientales y de peritos en monitoreo, los cuales auxiliarán en la realización de los monitoreos y análisis;\nLos requisitos y condiciones para formar parte de estos padrones, así como las funciones de los profesionales a que se refiere el presente artículo, se establecerán en los reglamentos correspondientes.\nSECCION IX\nInvestigación y educación ambiental\nLey de Protección al Ambiente para el Estado de Baja California. Página 33\nARTÍCULO 61.- Las autoridades ambientales estatales y municipales, en el ámbito de su competencia, así como las instituciones que integran el sistema educativo estatal, en su caso, promoverán:\nI. Que las instituciones de educación de todos los niveles incorporen en sus programas de enseñanza temas o materias de contenido ambiental;\nII. El fortalecimiento de una cultura ambiental de participación corresponsable de la sociedad;\nIII. El adiestramiento en y para el trabajo en materia de protección al ambiente y restauración del equilibrio ecológico, con apego a lo que establece esta ley;\nIV. La incorporación de contenidos ambientales en los programas con la Secretaría del Trabajo y de las comisiones de seguridad e higiene; y\nV. La formación de especialistas, la investigación y el desarrollo tecnológico en materia ambiental, que permita prevenir, controlar y abatir la contaminación, propiciar el aprovechamiento sustentable de los recursos y proteger los ecosistemas.\nARTÍCULO 62.- La Secretaría y las dependencias y organismos competentes en materia de ciencia y tecnología en el estado, se coordinarán para promover la creación de un sistema estatal de certificación, con el propósito de establecer y adoptar normas, indicadores y criterios de calidad ambiental en:\nI. Capacitación y formación de especialistas e instructores;\nII. La elaboración de bienes y productos; y\nIII. Desarrollo científico y tecnológico.\nTÍTULO SEGUNDO\nÁREAS NATURALES PROTEGIDAS\nCAPÍTULO I\nDisposiciones generales\nARTÍCULO 63.- Las zonas del territorio del estado, terrestres y acuáticas, en las que el ambiente original no ha sido significativamente alterado por la actividad del ser humano, que requiere ser preservado o restaurado, quedarán sujetas al régimen previsto en esta ley y los demás ordenamientos aplicables.\nLos propietarios, poseedores o titulares de los derechos sobre tierras, aguas y modalidades que de conformidad con la presente Ley, establezcan los decretos por los que\nLey de Protección al Ambiente para el Estado de Baja California. Página 34 se constituyan dichas áreas, así como a las demás previsiones contenidas en el programa de manejo y en los programas de ordenamiento ecológico que correspondan.\nARTÍCULO 64.- La designación de áreas naturales protegidas tiene como propósito, sustentable y la cultura ambiental, de conformidad con lo establecido en esta ley y la Ley\nGeneral.\nCAPÍTULO II\nTipos y características de las Áreas Naturales Protegidas\nARTÍCULO 65.- Se considerarán áreas naturales protegidas de competencia estatal:\nI. Reservas estatales;\nII. Parques estatales; y\nIII. Monumentos naturales estatales.\nARTÍCULO 66.- Las reservas estatales se constituirán en áreas biogeográficas relevantes, representativas de uno o más ecosistemas no alterados significativamente por la acción del ser humano o que requieran ser preservadas o restauradas, en las cuales habiten especies representativas de la biodiversidad estatal, incluyendo a las consideradas endémicas, amenazadas o en peligro de extinción.\nARTÍCULO 67.- En las reservas estatales podrá determinarse la existencia de la superficie mejor conservada o no alterada, que aloje ecosistemas o fenómenos naturales de especial importancia, o especies de flora y fauna que requieran protección especial y que será denominada zona núcleo. En ella podrá autorizarse la realización de actividades de preservación de los ecosistemas y sus elementos, de investigación científica y educación ecológica y limitarse o prohibirse aprovechamientos que alteren los ecosistemas.\nEn las reservas estatales se considera prioritario apoyar la conservación de germoplasma de las especies nativas. Para la cual se dará facilidad a las instituciones de investigación científica del estado y del país que investiguen o pretendan establecer banco de germoplasma de plantas nativas de Baja California.\nPárrafo Adicionado\nArtículo Reformado\nARTÍCULO 68.- En las reservas estatales deberá determinarse la superficie que proteja la zona núcleo del impacto exterior, que será denominada de amortiguamiento, en la ahí habiten, al momento de la expedición de la declaratoria respectiva o con su participación, que sean estrictamente compatibles con los objetivos, criterios y programas de aprovechamiento sustentable, en los términos del decreto respectivo y del programa de\nLey de Protección al Ambiente para el Estado de Baja California. Página 35 manejo que se expida, considerando las previsiones de los programas de ordenamiento ecológico que resulten aplicables.\nARTÍCULO 69.- En las zonas núcleo de las reservas estatales no se permitirá:\nI. Verter o descargar cualquier tipo de contaminantes así como desarrollar cualquier actividad contaminante;\nII. Interrumpir, rellenar, desecar o desviar los flujos hidráulicos estatales o concesionados al estado; y\nIII. Ejecutar acciones que contravengan lo dispuesto por esta ley, la declaratoria respectiva y las demás disposiciones que de ellas se deriven.\nARTÍCULO 70.- Tratándose de representaciones biogeográficas, los parques estatales se constituirán, de uno o más ecosistemas que se signifiquen por su belleza escénica, su valor científico, educativo, histórico, de recreo, por la existencia de flora y fauna, por su aptitud para el desarrollo del turismo o bien por otras razones análogas de interés general.\nEn los parques estatales sólo podrá permitirse la realización de actividades relacionadas con la preservación, protección y aprovechamiento sustentable de los recursos naturales, el incremento de su flora y fauna y en general, con la preservación de los ecosistemas y sus elementos, así como con la investigación, recreación regulada, turismo, y educación ecológica. En el otorgamiento de dichas autorizaciones se dará preferencia a quienes ahí habiten en el momento de la expedición de la declaratoria respectiva.\nARTÍCULO 71.- Corresponderá a la Secretaría, la promoción y elaboración de recomendaciones y coordinación con autoridades federales, con el propósito de hacer efectivas las disposiciones que regulen y limiten las actividades dentro de las áreas naturales protegidas de competencia estatal, tales como: actividades cinegéticas, de aprovechamiento de sus recursos naturales, de investigación y educación ecológica, de la preservación de los ecosistemas y de sus elementos, recreación y turismo, con el propósito de compatibilizar los regímenes de protección correspondiente.\nARTÍCULO 72.- Los monumentos naturales estatales se establecerán en áreas que contengan uno o varios elementos naturales, consistentes en lugares u objetos naturales, que por su carácter único o excepcional, interés estético, valor histórico o científico se resuelva incorporar a un régimen de protección absoluta. En los monumentos naturales únicamente podrá permitirse la realización de actividades relacionadas con su preservación, investigación científica, recreación y educación.\nARTÍCULO 73.- Se consideran áreas naturales protegidas de competencia municipal, declarados como tales por acuerdo del ayuntamiento.\nLey de Protección al Ambiente para el Estado de Baja California. Página 36\nAsimismo, los municipios, durante el proceso de planeación del desarrollo urbano para la ampliación de los centros de población, deberán identificar las zonas que por las características de sus ecosistemas, sean susceptibles de declararse como áreas naturales protegidas de competencia municipal, conforme lo establezca el programa de ordenamiento ecológico municipal.\nCAPÍTULO III\nDeclaratorias para el establecimiento de Áreas Naturales Protegidas\nARTÍCULO 74.- Las áreas naturales protegidas de competencia estatal se establecerán mediante decreto que expida el titular del Ejecutivo, conforme a lo que establecen la Ley General y esta ley.\nARTÍCULO 75.- Previamente a la expedición de las declaratorias para el establecimiento de las áreas naturales protegidas de competencia estatal, se deberán realizar los estudios que lo justifiquen, los cuales deberán ser puestos a disposición del público, en los términos del reglamento correspondiente. Asimismo la Secretaría deberá solicitar la opinión de:\nI. El Consejo Estatal de Protección al Ambiente;\nII. Los municipios en cuya circunscripción territorial se localice el área natural de que se trate;\nIII. Las dependencias del Ejecutivo del Estado que deban intervenir, de conformidad con sus atribuciones;\nIV. La entidad pública responsable de la planeación en el estado; y\nV. Las comunidades que habiten la zona sujeta a declaratoria.\nTratándose de las áreas naturales protegidas municipales, los municipios, deberán propios reglamentos.\nARTÍCULO 76.- Cualquier persona o grupo de la sociedad podrá proponer la mediante la fundamentación correspondiente.\nARTÍCULO 77.- Las declaratorias para el establecimiento de las áreas naturales protegidas que establece esta ley, sin perjuicio de lo dispuesto por otras leyes, contendrán:\nLey de Protección al Ambiente para el Estado de Baja California. Página 37\nI. La delimitación precisa del área, señalando la superficie, ubicación geográfica, dentro del municipio correspondiente o bien el deslinde del predio, descripción y zonificación del uso actual y en su caso, la zonificación propuesta;\nII. Las modalidades que se impongan al derecho de la propiedad y las modalidades a que se sujetará el uso o aprovechamiento de los recursos naturales sujetos a protección;\nIII. La descripción de actividades que podrán llevarse a cabo en el área correspondiente y las modalidades y limitaciones a que se sujetarán;\nIV. La causa de utilidad pública que, en su caso, fundamente la expropiación de terrenos, para que el estado adquiera su dominio, cuando al establecerse un área natural protegida se requiera dicha resolución;\nV. Cuando proceda, los lineamientos generales para la administración el establecimiento de órganos colegiados representativos, la creación de fondos o fideicomisos y la elaboración del programa de manejo del área;\nVI. Los lineamientos para la realización de acciones de preservación, restauración y aprovechamiento sustentable de los recursos naturales dentro de las áreas naturales protegidas, para su administración y vigilancia, así como para la elaboración de las reglas administrativas a que se sujetarán las actividades dentro del área respectiva, conforme a lo dispuesto en ésta y otras leyes aplicables; y\nVII. Los términos en que las autoridades municipales habrán de participar en la administración y regulación del área de que se trate.\nARTÍCULO 78.- Las declaratorias deberán publicarse en el Periódico Oficial del\nEstado y al menos en uno de los diarios de mayor circulación en la entidad. Se notificarán previamente a los propietarios o poseedores de los predios afectados, en forma personal cuando se conocieren sus domicilios, en caso contrario, se hará una segunda publicación, la que surtirá efectos de notificación personal. Las declaratorias se inscribirán en el Registro\nPúblico de la Propiedad y del Comercio.\nARTÍCULO 79.- Una vez establecida un área natural protegida, solo podrá ser modificada su extensión y en su caso, los usos del suelo permitidos, o cualquiera de sus disposiciones, por la autoridad que la haya establecido, siguiendo las mismas formalidades previstas en esta Ley.\nARTÍCULO 80.- El Ejecutivo del Estado y los ayuntamientos, a través de las dependencias competentes, realizará prioritariamente los programas de regularización de la tenencia de la tierra en las áreas naturales protegidas, con el objeto de proporcionar seguridad jurídica a los propietarios o poseedores de los predios en ellas comprendidas.\nLey de Protección al Ambiente para el Estado de Baja California. Página 38\nARTÍCULO 81.- En el otorgamiento o expedición de permisos, licencias, concesiones o en general de autorizaciones a que se sujetaren la exploración, explotación o autoridades distintas a las ambientales, se observarán las disposiciones de la presente Ley, de las leyes en que se fundamenten las declaratorias de creación correspondiente, así como las prevenciones de las propias declaratorias y los programas de manejo.\nEl solicitante deberá en tales casos demostrar ante la autoridad competente, su capacidad técnica y económica para llevar a cabo la exploración, explotación o aprovechamiento de que se trate, sin causar deterioro al equilibrio ecológico.\nLa autoridad competente, tomando como base los estudios técnicos y socioeconómicos practicados, podrá solicitar al otorgante la cancelación o revocación del permiso, licencia, concesión o autorización correspondiente, cuando la exploración, explotación o aprovechamiento de recursos ocasione o pueda ocasionar deterioro al equilibrio ecológico, o daños graves a los recursos naturales.\nARTÍCULO 82.- La autoridad competente, en coordinación con las Secretarías de\nPlaneación y Finanzas y de Desarrollo Económico, así como con los órganos equivalentes de los municipios, en el ámbito de sus respectivas competencias:\nI. Promoverán las inversiones públicas y privadas para el establecimiento y manejo de las áreas naturales protegidas;\nII. Establecerán o en su caso promoverán la utilización de mecanismos para captar recursos y financiar o apoyar el manejo de las áreas naturales protegidas; y\nIII. Establecerán los incentivos económicos y los estímulos fiscales para las personas, y las organizaciones sociales, públicas o privadas, que participen en la administración y vigilancia de las áreas naturales protegidas, así como para quienes aporten recursos para tales fines o destinen sus predios a acciones de preservación.\nCAPÍTULO IV\nProgramas de manejo\nARTÍCULO 83.- La elaboración de los programas de manejo de las áreas naturales protegidas que se establezcan, estarán a cargo de la entidad competente que hubiere propuesto la declaratoria del área de que se trate. Dichos programas deberán elaborarse dentro de los plazos que para tal efecto señalen las propias declaratorias.\nARTÍCULO 84.- El programa de manejo a que se refiere el artículo anterior deberá contener, al menos, lo siguiente:\nLey de Protección al Ambiente para el Estado de Baja California. Página 39\nI. La descripción de las características físicas, biológicas, sociales, económicas y culturales del área natural protegida, en el contexto nacional, regional, local y municipal, así respectiva;\nII. Las acciones a realizar a corto, mediano y largo plazo, estableciendo su vinculación con el Plan Estatal de Desarrollo, así como con los programas sectoriales correspondientes incluyendo los de ordenamiento ecológico. Dichas acciones comprenderán, entre otras, las siguientes: investigación y educación ambiental; protección y aprovechamiento sustentable de los recursos naturales; la flora y la fauna; para el desarrollo de actividades recreativas y turísticas; obras de infraestructura y demás actividades productivas; de financiamiento para la administración del área; de prevención y control de contingencias ambientales, emergencias ecológicas y de vigilancia, y las demás que por las características propias del área natural protegida se requieran;\nIII. La forma en que se organizará la administración del área y los mecanismos de participación de los individuos y comunidades asentadas en la misma;\nIV. Los objetivos específicos del área natural protegida;\nV. La referencia a las normas oficiales mexicanas y normas ambientales estatales aplicables a todas y cada una de las áreas a que esté sujeta el área natural protegida;\nVI. En su caso, las reglas de carácter administrativo a que se sujetarán las actividades que se desarrollen en el área natural protegida de que se trate;\nVII. Los inventarios biológicos existentes y los que se prevean realizar; y\nVIII. Un sistema de vigilancia y cuidado de la zona.\nSe deberá publicar en el Periódico Oficial del Estado un resumen del programa de manejo respectivo y un plano de localización del área.\nARTÍCULO 85.- Corresponde al Ejecutivo del Estado, por conducto de la Secretaría la vigilancia de las áreas naturales protegidas de competencia estatal en coordinación con autoridades federales competentes, y cuando proceda, su administración y manejo, en los términos de esta ley y la Ley General.\nARTÍCULO 86.- Corresponde a los municipios la vigilancia de las áreas naturales protegidas de competencia municipal, en coordinación con las autoridades competentes y cuando proceda, su administración y manejo, en los términos de esta ley y la Ley General.\nARTÍCULO 87.- El Ejecutivo del Estado y los municipios, según corresponda, una vez que se cuente con el programa de manejo respectivo, podrán otorgar la administración de las áreas naturales protegidas a que se refiere este capítulo a los municipios, así como a ejidos, comunidades agrarias, grupos y organizaciones sociales y empresariales, Ley de Protección al Ambiente para el Estado de Baja California. Página 40 morales interesadas, siempre y cuando no sean terrenos privados.\nPara tal efecto, se deberán suscribir los acuerdos o convenios que conforme a la legislación aplicable procedan. administrar las áreas naturales protegidas, estarán obligados a sujetarse a las previsiones contenidas en la presente Ley, los reglamentos, normas oficiales mexicanas y normas ambientales estatales, o municipales en su caso, que se expidan en la materia, así como a cumplir los decretos por los que se establezcan dichas áreas y los programas de manejo respectivos.\nARTÍCULO 88.- Todos los actos, convenios y contratos relativos a la propiedad, posesión o cualquier derecho relacionado con bienes inmuebles ubicados en las áreas naturales protegidas deberán contener referencias de la declaratoria correspondiente y de sus datos de inscripción en el registro público de la propiedad y del comercio. Los notarios y cualesquiera otros fedatarios públicos, harán constar tal circunstancia al autorizar las escrituras públicas, actos, convenios y contratos en los que intervengan.\nSerá nulo todo acto, convenio o contrato que contravenga lo establecido en la mencionada declaratoria.\nCAPÍTULO V\nRegistro Estatal de Areas Naturales Protegidas\nARTÍCULO 89.- La autoridad competente integrará el Registro Estatal de Areas\nNaturales Protegidas, el cual consistirá en la inscripción de los decretos mediante los cuales se declaren las áreas naturales protegidas de competencia estatal y municipal y los instrumentos que los modifiquen. Dicho registro podrá ser consultado por cualquier persona que así lo solicite y deberá ser integrado al sistema estatal de información ambiental.\nTÍTULO TERCERO\nCAPÍTULO I\nARTÍCULO 90.- Para el aprovechamiento sustentable de las aguas de competencia estatal, así como el uso adecuado del agua que se utiliza en los centros de población, se considerarán los criterios establecidos en la Ley General, así como los siguientes:\nI. El agua debe ser aprovechada y distribuida con eficiencia y equidad;\nII. El agua residual debe recibir tratamiento para prevenir la afectación del ambiente y sus ecosistemas.\nLey de Protección al Ambiente para el Estado de Baja California. Página 41\nIII. El reuso y aprovechamiento de las aguas residuales tratadas, es una forma eficiente de utilizar y preservar el recurso.\nARTÍCULO 91.- Los criterios para el aprovechamiento sustentable del agua, serán considerados en:\nI. La formulación e integración de planes y programas relacionados con el aprovechamiento del agua;\nII. El otorgamiento de concesiones, permisos, y en general toda clase de autorizaciones para el aprovechamiento de los recursos naturales no reservados a la\nFederación, que afecten o puedan llegar a afectar el ciclo hidrológico, así como en su revocación;\nIII. El otorgamiento de autorizaciones para la desviación, extracción o derivación de aguas de propiedad estatal, así como su revocación;\nIV. La operación y administración de los sistemas de agua potable y alcantarillado que sirven a los centros de población;\nV. Los programas estatales de desarrollo urbano y vivienda, y\nVI. El diseño y ubicación de conjuntos habitacionales, turísticos e industriales;\nVII. La formulación de los programas de ordenamiento ecológico.\nARTÍCULO 92.- Con el propósito de asegurar la disponibilidad del agua y abatir los niveles de desperdicio, las autoridades competentes promoverán el ahorro y uso eficiente del agua, el tratamiento y reuso de aguas residuales.\nARTÍCULO 93.- El Ejecutivo del Estado realizará las acciones necesarias para evitar o, en su caso, controlar procesos de eutroficación, salinización o cualquier otro proceso de degradación de las aguas de competencia estatal.\nARTÍCULO 94.- La construcción de nuevos sistemas de abastecimiento de agua para el tratamiento de las aguas residuales o su incorporación a los existentes.\nARTÍCULO 95.- Los organismos operadores de agua y alcantarillado en coordinación con las autoridades competentes, estimularán la participación de la sociedad a través de la acrediten que practican el uso más eficiente del agua.\nLey de Protección al Ambiente para el Estado de Baja California. Página 42\nARTÍCULO 96.- Los parques urbanos y demás áreas verdes de propiedad pública tratada.\nARTÍCULO 97.- Los usuarios que declaren falsamente contar con instalaciones de tratamiento de aguas grises o no informen la suspensión de su funcionamiento, serán objeto de las sanciones que para su efecto contemplen los reglamentos municipales.\nCAPÍTULO II\nPreservación y aprovechamiento sustentable del suelo\nARTÍCULO 98.- Para la preservación, protección y aprovechamiento sustentable del suelo, se considerarán los criterios establecidos en la Ley General, así como los siguientes:\nI. La acumulación o depósito de residuos constituye una fuente de contaminación que altera los procesos biológicos, físicos y químicos de los suelos; y\nII. Deben evitarse prácticas que provoquen riesgos o problemas de salud, causen alteraciones en el suelo y perjudiquen su aprovechamiento, uso y explotación. Asimismo, deberá evitarse la realización de obras y actividades en zonas con pendientes pronunciadas o que presenten fenómenos de erosión o degradación del suelo, que las pongan en riesgo y afecten a la población y los recursos naturales.\nARTÍCULO 99.- Los criterios anteriores serán considerados en:\nI. Los apoyos a las actividades agrícolas que otorguen las dependencias del ejecutivo estatal y municipal, de manera directa o indirecta, para que promuevan la progresiva incorporación de cultivos compatibles con la preservación del equilibrio ecológico y la restauración de los ecosistemas;\nII. La fundación de centros de población y la radicación de asentamientos humanos y desarrollos urbanos;\nIII. El establecimiento de usos, reservas y destinos, en los planes de desarrollo urbano, así como en las acciones de restauración y conservación de los centros de población;\nIV. Las disposiciones, programas y lineamientos técnicos para la conservación, protección y restauración de los suelos, en las actividades agropecuarias, forestales e hidráulicas;\nLey de Protección al Ambiente para el Estado de Baja California. Página 43\nV. Las actividades de exploración, explotación, extracción y aprovechamiento de materiales o sustancias, no reservadas a la Federación, así como las excavaciones y todas aquellas acciones que alteren los recursos y la vegetación forestal;\nVI. El otorgamiento de concesiones, permisos y en general toda clase de autorizaciones en materia de impacto ambiental, de manejo de residuos sólidos y de usos de suelo fuera de los centros de población, así como su revocación; y\nVII. La formulación de los programas de ordenamiento ecológico.\nCAPÍTULO III\nPreservación y Aprovechamiento de los Elementos y Recursos Naturales\nSECCIÓN I\nZONAS DE RESTAURACIÓN\nARTÍCULO 100.- En aquellas áreas que presenten procesos de degradación o desertificación o graves desequilibrios ecológicos, la Secretaría, promoverá ante las autoridades federales competentes, la declaratoria para el establecimiento de zonas de restauración ecológica, en los términos de la Ley General.\nArtículo Reformado\nARTÍCULO 101.- Derogado.\nArtículo Derogado\nSECCIÓN II\nENERGÍA\nSección Adicionada\nARTÍCULO 102.- La Secretaría, en coordinación con los ayuntamientos promoverán la celebración de acuerdos y convenios para el establecimiento de programas que permitan el ahorro de energía y su utilización eficiente y fomentar el uso de fuentes de energía menos contaminantes, conforme a los principios establecidos en la presente Ley.\nARTÍCULO 103.- La Secretaría en coordinación con los municipios y demás dependencias buscarán estimular en la población el uso de energía alternativa, fomentando la utilización de todas aquellas fuentes que representen un menor impacto al medio ambiente, tales como la energía solar, eólica, hidráulica, geotérmica y la generada por la combustión o digestión de materia orgánica.\nARTÍCULO 104.- La Secretaría, en coordinación con los municipios y organismos competencia en materia de ciencia y tecnología, presentarán un reporte bienal a la sociedad y al Consejo, en el que informe de manera detallada los avances que existan en la aplicación de energía alternativa en la entidad. Dicho reporte deber incluir:\nI. El grado de aprovechamiento que se haga de cada una de las energías alternativas la energía consumida en el estado;\nLey de Protección al Ambiente para el Estado de Baja California. Página 44\nII. Los obstáculos existentes, de orden científico, económico o social que a su juicio cada una de las fuentes de energía alternativa contempladas;\nIII. Los resultados de investigaciones llevadas a cabo en el estado, en otras partes energía alternativa, y que sean de interés para el avance de la utilización de otras formas de energía en la entidad;\nIV. Previo a la elaboración del reporte, con apoyo de los fondos ambientales, se auspiciará la organización de por lo menos un seminario estatal sobre energía y energía alternativa, convocando para dicho evento a los científicos de la disciplina y al público en general, y deber incluir en el reporte las ponencias y testimonios presentados.\nARTÍCULO 105.- La Secretaría llevará un registro de las fuentes emisoras de energía radioactiva en el estado, cualquiera que sea su uso o aplicación.\nARTÍCULO 106.- El uso de la energía nuclear con el fin de generar energía eléctrica deberá considerarse una opción poco deseable en el Estado, cuya aplicación se realizara solo después de haber agotado todas las demás fuentes de que se dispone para producirla.\nSECCIÓN III\nVIDA SILVESTRE\nARTICULO 106 BIS.- Para la preservación y aprovechamiento sustentable de la vida silvestre y su hábitat, la Secretaria tendrá las siguientes:\nI.- La formulación y conducción de la política estatal sobre la conservación y aprovechamiento sustentable de la vida silvestre la que, en todo caso, deberá ser congruente con los lineamientos de la política nacional en la materia;\nII.- La regulación para el manejo, control y remediación de los problemas asociados a ejemplares y poblaciones ferales, así como la aplicación de las disposiciones en la materia, dentro de su ámbito territorial;\nIII.- La compilación de la información sobre los usos y formas de aprovechamiento de ejemplares, partes y derivados de la vida silvestre con fines de subsistencia por parte de las integración a los procesos de desarrollo sustentable en los términos de esta Ley;\nIV.- El apoyo, asesoría técnica y capacitación a las comunidades rurales para el silvestre, la elaboración de planes de manejo, el desarrollo de estudios de poblaciones y la solicitud de autorizaciones;\nLey de Protección al Ambiente para el Estado de Baja California. Página 45\nV.- La conducción de la política estatal de información y difusión en materia de vida silvestre; la integración, seguimiento y actualización del Sistema Estatal de Información\nInformación sobre la Vida Silvestre, en el ámbito de su jurisdicción territorial;\nVI.- La creación y administración del registro estatal de las organizaciones relacionadas con la conservación y aprovechamiento sustentable de la vida silvestre;\nVII.- La creación y administración del registro estatal de los prestadores de servicios vinculados a la transformación, tratamiento, preparación, aprovechamiento y comercialización de ejemplares, partes y derivados de la vida silvestre, así como la supervisión de sus actividades;\nVIII.- La creación y administración del padrón estatal de mascotas de especies silvestres y aves de presa;\nIX.- La coordinación de la participación social en las actividades que incumben a las autoridades estatales, y\nX.- La emisión de recomendaciones previo a los estudios correspondientes a las autoridades competentes en materia de vida silvestre, con el propósito de promover el cumplimiento de la legislación en materia de conservación y aprovechamiento sustentable.\nPara el ejercicio de estas atribuciones, se estará a lo dispuesto en las disposiciones reglamentarias.\nArtículo Reformado\nARTICULO 106 BIS 1.- Para la preservación, conservación y aprovechamiento sustentable de la vida silvestre y su hábitat, la Secretaría y los Municipios en su demarcación territorial, previo los estudios correspondientes podrán promover ante autoridades federales correspondientes:\nI.- El establecimiento o modificación de vedas;\nII.- La declaración de especies endémicas, amenazadas, sujetas a protección especial, en peligro de extinción, o probablemente extinta en el medio silvestre,\nIII.- La creación de áreas de refugio para protección de las especies acuáticas;\nIV.- La modificación o renovación de concesiones, permisos y en general, de toda clase de autorizaciones para el aprovechamiento, posesión, administración, conservación, repoblación, propaganda y desarrollo de la flora y fauna silvestre, y\nV.- La emisión de normas ambientales en materia de vida silvestre, las cuales deberán de ser congruentes con los lineamientos de la política nacional en la materia, con el\nLey de Protección al Ambiente para el Estado de Baja California. Página 46 aprovechamiento sustentable;\nVI.- Listas, catálogos y demás información prioritaria relativa a las especies y localizada dentro del Estado, señalando el nombre científico y nombre común más utilizado de las mismas; y\nVII.- La celebración de convenios para garantizar la congruencia y propósitos en la acción de los distintos órganos de gobierno y asumir las funciones y facultades de la federación en los términos de la Ley General de Vida Silvestre.\nArtículo Reformado\nARTICULO 106 BIS 2.- El aprovechamiento de los recursos naturales en áreas que sean el hábitat de especies de flora o fauna silvestres, especialmente de las endémicas, amenazadas sujetas a protección especial, en peligro de extinción o probablemente extinta en el medio silvestre, deberá hacerse de manera que no se alteren las condiciones necesarias para la subsistencia, desarrollo y evolución de dichas especies.\nArtículo Reformado\nLa Secretaría deberá promover y apoyar el manejo de la flora y fauna silvestre, con base en el conocimiento biológico tradicional, información técnica, científica y económica, con el propósito de hacer un aprovechamiento sustentable de las especies.\nARTÍCULO 106 BIS 3.- Queda prohibido en el Estado el establecimiento de espectáculos circenses públicos o privados, fijos o itinerantes, en los que se utilicen ejemplares vivos de fauna silvestre.\nArtículo Reformado\nSECCIÓN IV\nCORREDORES BIOLÓGICOS\nARTÍCULO 106 BIS 4.- Un corredor biológico es un territorio que proporciona conectividad entre paisajes, ecosistemas y hábitat, sean éstos naturales o modificados, asegurando el mantenimiento de la diversidad biológica y los procesos ecológicos entre éstos.\nARTÍCULO 106 BIS 5.- Corresponde a la Secretaría, la identificación, delimitación y flujo genético, y evitar el aislamiento de las especies entre áreas prioritarias para la conservación.\nARTÍCULO 106 BIS 6.- Los objetivos de los Corredores Biológicos son:\nI.- Mantener y generar la conectividad ecológica territorial entre áreas naturales prioritarias por su riqueza biológica, brindando un conjunto de bienes y servicios ambientales a la sociedad de la región, Ley de Protección al Ambiente para el Estado de Baja California. Página 47\nII.- Fortalecer las capacidades locales en el uso sustentable de los recursos naturales aprovecharlos, y\nIII.- Servir como instrumento para que los recursos del gobierno apoyen a las\nARTÍCULO 106 BIS 7.- Los Corredores Biológicos tendrán por componentes de la estrategia:\nI. El diseño y monitoreo de corredores biológicos: Se refiere a aspectos de ordenamiento espacial y ecológico, y a la definición detallada de prioridades para la conservación y uso sustentable de los recursos con la participación de la comunidad,\nII. La coordinación interinstitucional y reorientación de políticas públicas: Lograr una coordinación interinstitucional y alineación de políticas públicas secretariales y sectoriales de las dependencias y entidades de la Administración Pública Estatal y municipales, y demás actores estratégicos, a partir de la integración de criterios de conservación de la biodiversidad, ordenamiento ecológico y uso sustentable de los recursos naturales.\nIII. Conservación y restauración: Conservar y restaurar la biodiversidad del Estado, a través de acciones que permitan generar la conectividad entre poblaciones y comunidades de especies de flora y fauna nativa.\nIV. El uso sustentable: Se refiere al desarrollo de nuevas cadenas de valor no convencional con un enfoque integral que promueva prácticas de uso racional y sustentable de la biodiversidad; y\nV. La administración y coordinación: Se refiere a la estructura prevista para la implementación de los corredores biológicos.\nARTÍCULO 106 BIS 8.- Las líneas estratégicas a aplicar en los Corredores\nBiológicos, son las siguientes:\nI.- Conservación;\nII.- Servicios Ambientales;\nIII.- Aprovechamiento de la Vida Silvestre;\nIV.- Monitoreo y evaluación;\nV.- Producción forestal nativa y recuperación de cobertura forestal;\nVI.- Ecoturismo;\nVII.- Economía Ambiental;\nLey de Protección al Ambiente para el Estado de Baja California. Página 48\nVIII.- Diversificación y reconversión productiva;\nIX.- Producción Sostenible’;\nX.- Aprovechamiento Forestal, y\nXI.- Las demás que favorezcan al cumplimiento de los objetivos de los corredores biológicos.\nARTÍCULO 106 BIS 9.- Los criterios que la Secretaría deberá de seguir, para establecer los corredores biológicos en el Estado, son los siguientes:\nI.- Alta biodiversidad;\nII.- Alta endemicidad;\nIII.- Presencia de especies emblemáticas, prioritarias, en riesgo y particularmente vulnerables al cambio climático;\nIV.- Comunidades climax;\nV.- Hábitats únicos;\nVI.- Buen estado de conservación;\nVII.- Ausencia de caminos y asentamientos humanos;\nVIII.- Uso alternativo de recursos;\nIX.- Amenazas y vulnerabilidad;\nX.- Presencia de proyectos de conservación;\nXI.- Fenómenos biológicos importantes;\nXII.- Áreas importantes para especies migratorias;\nXIII.- Fuentes de cuerpos de agua, y\nXIV.- Las demás que favorezcan al cumplimiento de los objetivos de los corredores biológicos.\nCAPÍTULO IV\nÁreas Verdes Urbanas y las acciones necesarias a fin de crear, conservar, mejorar e incrementar el número y\nLey de Protección al Ambiente para el Estado de Baja California. Página 49 social de sus habitantes.\nPárrafo Reformado conservación, mejoramiento y crecimiento, para lo cual las políticas y acciones a que se refiere el párrafo anterior se planearán y gestionarán con base en los siguientes objetivos:\nPárrafo Reformado\nI. El incremento progresivo y la prohibición de la disminución del número y la superficie de las áreas verdes urbanas.\nFracción Adicionada\nII. El mejoramiento de la localización, equipamiento, conservación y mantenimiento de las áreas verdes urbanas.\nFracción Adicionada\nIII. La participación de la sociedad en el diseño, construcción, equipamiento, conservación y mantenimiento de las áreas verdes urbanas.\nFracción Adicionada\nIV. La recuperación de espacios públicos en desuso para ser destinados a áreas verdes urbanas.\nFracción Adicionada\nV. El establecimiento de estímulos para que los particulares destinen Inmuebles a áreas verdes.\nFracción Adicionada\nVI. El diseño y gestión de las políticas públicas en materia de áreas verdes urbanas usarán como referencia parámetros Internacionales.\nFracción Adicionada\nArtículo Adicionado\nArtículo Reformado\nARTÍCULO 106 TER 1.- El Estado y los municipios podrán celebrar convenios con los vecinos y los sectores social y productivo para los objetivos a que se refiere el artículo anterior.\nArtículo Adicionado\nArtículo Reformado\nARTÍCULO 106 TER 2.- Las Los espacios públicos destinados a áreas verdes urbanas no podrán ser destinados a otro uso, ni su superficie podrá ser disminuida.\nPárrafo Reformado para área verde urbana se inscribirá en el Registro Público de la Propiedad.\nPárrafo Adicionado\nArtículo Adicionado\nArtículo Reformado\nLey de Protección al Ambiente para el Estado de Baja California. Página 50\nARTÍCULO 106 TER 3.- La Secretaría y los municipios llevarán dentro de sus respectivos ámbitos de competencia, un inventario de Áreas Verdes con la finalidad de conocer, preservar e incrementar dichas áreas.\nEl inventario a que se refiere el párrafo anterior, deberá contener cuando menos la siguiente información:\nI.- Ubicación y superficie del Área Verde,\nII.- Tipo de Área Verde,\nIII.- Especies de flora y fauna que la conforman,\nIV.- A que ente de gobierno pertenece; y\nV.- Zonas en las cuales se considera próximamente establecer nuevas áreas verdes.\nEl inventario que lleven los municipios lo harán del conocimiento de la Secretaría para su integración en un inventario general de Áreas Verdes, y además proporcionaran anualmente las actualizaciones correspondientes. Dicho inventario formará parte del sistema estatal de información ambiental.\nArtículo Adicionado\nTÍTULO CUARTO\nPROTECCIÓN AL AMBIENTE\nCAPÍTULO I\nDisposiciones generales\nARTÍCULO 107.- Las disposiciones contenidas en este título, serán aplicables a la prevención y control de la contaminación atmosférica, de las aguas y del suelo, en aquellas materias que de conformidad con la Ley General, no son consideradas de jurisdicción federal.\nEn todas las descargas de contaminantes a la atmósfera, el agua y los suelos, deberán ser observadas las previsiones de la Ley General, esta ley, sus disposiciones reglamentarias, así como las normas oficiales mexicanas y normas ambientales estatales que al efecto se expidan.\nARTÍCULO 108.- La Secretaría, en los términos que señale el reglamento correspondiente, establecerá un Registro de Emisiones y Transferencia de Contaminantes, complementario al de la Federación, el cual contendrá el inventario de emisiones a la atmósfera, el registro de descargas de aguas residuales y el inventario de materiales y realicen en el Estado. Este registro será la base para la creación de un sistema consolidado\nLey de Protección al Ambiente para el Estado de Baja California. Página 51 contaminantes en el Estado.\nLas personas responsables de los establecimientos industriales, comerciales y de servicios, de competencia Estatal y Municipal, están obligadas a proporcionar datos y\nContaminantes.\nPárrafo Reformado\nEI Registro de Emisiones y Transferencia de Contaminantes se deberá integrar con datos desagregados por sustancia y por fuente, anexando nombre y dirección de los establecimientos sujetos a registro.\nLa Secretaría determinará la periodicidad en la que deberá actualizarse el inventario de emisiones y será responsable de que la información se difunda de forma accesible a toda la población.\nPárrafo Adicionado\nArtículo Reformado\nARTÍCULO 109.- En aquellos casos en que para la operación y funcionamiento de establecimientos industriales, comerciales o de servicios que requieran obtener diversos permisos, licencias o autorizaciones que deban ser otorgados por una autoridad ambiental competente los interesados podrán optar por integrar dichas autorizaciones en un solo trámite que se denominará Licencia Ambiental Única, en los términos que señalen los reglamentos que al efecto se expidan.\nLa actualización de la base de datos del Registro de Emisiones y Transferencia de\nContaminantes, será a través de la cédula de operación anual; instrumento mediante el cual los sujetos a que refiere el segundo párrafo del artículo 108, están obligados a proporcionar datos y documentos necesarios para integrarlo, conforme a los requisitos y tiempos que prevea el reglamento correspondiente.\nArtículo Reformado\nCAPÍTULO II\nSECCIÓN I\nCriterios ambientales\nARTÍCULO 110.- Para la prevención, protección y mejoramiento de la calidad de la atmósfera se considerarán los siguientes criterios:\nI. La calidad del aire debe ser satisfactoria; y\nLey de Protección al Ambiente para el Estado de Baja California. Página 52\nII. Las emisiones de contaminantes a la atmósfera, sean de fuentes fijas o móviles, deberán ser reducidas y controladas, para asegurar una calidad del aire satisfactoria para el bienestar de la población y el mantenimiento del equilibrio ecológico.\nARTÍCULO 111.- Los criterios anteriores serán considerados en:\nI. La expedición de normas ambientales estatales, para la prevención y control de la contaminación de la atmósfera;\nII. La formulación y revisión del Programa de Ordenamiento Ecológico para el estado y los planes y programas que de él deriven;\nIII. Los programas de ordenamiento territorial;\nIV. La clasificación de áreas o zonas atmosféricas, de acuerdo a su capacidad de asimilación o dilución y la carga de contaminantes que éstas puedan recibir, en concordancia con la clasificación que realice la federación;\nV. El otorgamiento de todo tipo de autorizaciones, licencias, registros o permisos para emitir contaminantes a la atmósfera; y\nVI. El diseño de indicadores de calidad ambiental.\nArtículo 111 BIS.- El Poder Ejecutivo y los Municipios, en el ámbito de sus respectivas competencias, elaborarán y promoverán la implementación de instrumentos económicos para quienes:\nI. Reconviertan los procesos productivos con el objeto de prevenir y controlar la contaminación atmosférica, principalmente en la zona rural;\nII. Provean o adquieran equipo o tecnología que contribuya a reducir y controlar las emisiones de contaminantes o de gases de efecto invernadero a la atmósfera;\nIII. Incorporen en sus procesos productivos el uso de energías renovables;\nIV. Preserven zonas forestales de conformidad con las disposiciones de la Ley\nGeneral de Desarrollo Forestal Sustentable y demás disposiciones legales aplicables;\nV. Realicen actividades de conservación de la cubierta forestal y de reforestación, de conformidad con las disposiciones legales aplicables;\nVI. Favorezcan la conservación del uso de suelo silvícola;\nVII. Reduzcan o sustituyan el uso de sustancias agotadoras de la capa de ozono en sus procesos productivos; y\nLey de Protección al Ambiente para el Estado de Baja California. Página 53\nVIII. Realicen las demás actividades que al efecto se determinen como prioritarias y tengan por objeto mejorar la prevención y control de la contaminación atmosférica.\nArtículo Adicionado\nSECCIÓN II\nFacultades\nARTÍCULO 112.- Para prevenir, controlar, reducir o evitar la contaminación de la atmósfera, la Secretaría tendrá las siguientes facultades:\nI. Promover y apoyar técnicamente a los municipios que lo soliciten en la formulación y aplicación de programas de gestión de calidad del aire e indicadores ambientales que tengan por objeto el cumplimiento de la normatividad aplicable, así como elaborar un\nPrograma Estatal de Gestión de Calidad del Aire;\nII. Requerir a los responsables de fuentes emisoras de competencia estatal, el cumplimiento de las normas ambientales estatales, de conformidad con esta ley, la Ley\nGeneral y sus reglamentos;\nIII. Otorgar la licencia correspondiente, de conformidad con esta Ley, la Ley General y sus reglamentos, a los responsables de fuentes emisoras de competencia estatal;\nIV. Establecer los límites máximos permisibles de emisión de contaminantes a los responsables de fuentes emisoras de competencia estatal, conforme al reglamento respectivo;\nV. Requerir a los responsables de la operación de fuentes generadoras de contaminantes, el uso y la aplicación de la mejor tecnología disponible, con el propósito de reducir y controlar sus emisiones a la atmósfera;\nVI. Integrar y mantener actualizado el inventario de fuentes de emisiones contaminantes a la atmósfera proveniente de fuentes emisoras de competencia estatal y coordinarse con la Federación y los municipios para la integración de los inventarios correspondientes;\nVII. Promover y apoyar técnicamente a los gobiernos municipales que lo soliciten para el establecimiento de sistemas de monitoreo de la calidad del aire, así como calendarización y control de quemas agropecuarias;\nVIII. Establecer y operar centros de verificación;\nIX. Proponer el monto de las tarifas que deberán cubrirse por los servicios de verificación de emisiones de automotores en circulación;\nX. Llevar un registro de los centros de verificación y mantener actualizado los resultados obtenidos;Aplicar las normas oficiales mexicanas y normas ambientales estatales para la protección de la atmósfera, en las materias y supuestos de su competencia.\nLey de Protección al Ambiente para el Estado de Baja California. Página 54\nXI. Entregar a los propietarios o poseedores de vehículos automotores, cuando proceda, el documento que acredite que dicha fuente no rebasa los límites máximos permisibles de emisión, conforme a las normas oficiales mexicanas y normas estatales, en su caso;\nXII. Proponer el establecimiento de normas ambientales estatales con el propósito de regular las emisiones del transporte y las medidas de tránsito y en su caso, la suspensión de la circulación vehicular, en casos graves de contaminación;\nXIII. Tomar las medidas preventivas necesarias y los instrumentos de prevención y control para evitar contingencias ambientales por contaminación atmosférica;\nXIV. Requerir la instalación de equipos o sistemas de control de emisiones a quienes realicen actividades que las generen;\nXV. Aplicar las normas oficiales mexicanas y normas ambientales estatales para la protección de la atmósfera, en las materias y supuestos de su competencia;\nXVI. Ordenar la clausura temporal, parcial o total, de los puntos de ventas de cohetes, petardos y otros artificios pirotécnicos, cuando conforme a los sistemas de monitoreo de la calidad del aire los niveles de AQI sean superiores a 101 puntos, o su caso equivalente conforme al sistema de mediación que en su caso se utilice.\nLos establecimientos mercantiles que corresponda, de forma inmediata deberán atender las medidas preventivas que se le requieran; y\nXVII.- Las demás que tengan por objeto dar cumplimiento a lo dispuesto en la presente Ley.\nArtículo Reformado\nARTÍCULO 113.- Para prevenir, controlar, reducir o evitar la contaminación de la atmósfera, los municipios, en el ámbito de su circunscripción territorial, tendrán las siguientes facultades:\nI. Aplicar los criterios generales para la protección a la atmósfera en los programas y planes de desarrollo urbano de su competencia, definiendo las zonas en que sea permitida la instalación de obras y actividades generadoras de emisiones;\nII. Requerir a los responsables de la operación de fuentes contaminantes, y quemas agropecuarias, la aplicación de la mejor tecnología disponible, con el propósito de reducir y controlar sus emisiones a la atmósfera;\nIII. Proponer al Estado el establecimiento de normas ambientales estatales con el de contaminación;\nLey de Protección al Ambiente para el Estado de Baja California. Página 55\nIV. Requerir a los responsables de la operación de fuentes contaminantes, la aplicación de la mejor tecnología disponible, con el propósito de reducir y controlar sus emisiones a la atmósfera;\nV. Integrar y mantener actualizado el inventario de emisiones contaminantes a la atmósfera provenientes de fuentes emisoras de competencia municipal;\nVI. Establecer y operar sistemas de monitoreo de calidad del aire;\nVII. Tomar las medidas preventivas necesarias para evitar contingencias ambientales por contaminación atmosférica, en coordinación con la Secretaría;\nVIII. Aplicar las normas oficiales mexicanas y normas ambientales estatales para la protección de la atmósfera, en materias de su competencia;\nFracción Reformada\nIX. Requerir la instalación de equipos o sistemas de control de emisiones a quienes realicen actividades que las generen.\nX. Requerir y aplicar las sanciones respectivas a los particulares responsables de quemas dentro de las zona urbana;\nFracción Reformada\nXI. Expedir autorización para la quema en terrenos de uso agropecuario, de conformidad a lo que establecen las normas oficiales mexicanas;\nFracción Adicionada\nXII. Vigilar, que los usuarios con autorización para realizar quemas en terrenos de uso agropecuario, cumplan con lo dispuesto por las normas oficiales mexicanas;\nFracción Adicionada\nXIII. Tomar las medidas preventivas necesarias para que los usuarios con autorización de quema en terrenos de uso agropecuario, no realicen las quemas de forma simultánea; y,\nFracción Adicionada\nXIV. Realizar, en coordinación con las autoridades federales y estatales competentes, la preparación de la tierra de uso agropecuario, así como el contenido de lo regulado por las normas oficiales mexicanas.\nFracción Adicionada\nArtículo Reformado\nARTÍCULO 113 BIS.- Los Ayuntamientos, conforme a la periodicidad que señalen sus reglamentos deberán emitir un calendario de quemas agropecuarias.\nLey de Protección al Ambiente para el Estado de Baja California. Página 56\nPara la elaboración del calendario, los Ayuntamientos deberán coordinarse con las autoridades estatales y federales especializadas en materia.\nDicho calendario deberá publicarse en el Periódico Oficial del Estado, y en otros medios de difusión que se consideren convenientes.\nArtículo Adicionado\nARTÍCULO 113 TER.- Las quemas agrícolas deberán autorizarse considerando los parámetros climáticos, estacionales, regionales, de preservación del suelo, flora y fauna, así como técnicos para prevenir el riesgo de propagación del fuego y resguardar la salud y seguridad pública.\nArtículo Adicionado\nSECCIÓN III\nControl de emisiones proveniente de fuentes fijas\nARTÍCULO 114.- Queda prohibido emitir contaminantes a la atmósfera que rebasen los niveles máximos permisibles de emisión establecidos en las normas aplicables\nARTÍCULO 115.- Los responsables de fuentes fijas, emisoras de contaminantes a la atmósfera de competencia estatal, en los términos del reglamento correspondiente deberán:\nI. Tramitar ante la Secretaría y, en su caso, obtener la autorización correspondiente que ésta emita y anualmente revalidar su vigencia;\nII. Instalar equipos o sistemas de control de emisiones y realizar monitoreos de las mismas, para mantenerlas por debajo de los niveles máximos permisibles para cada uno de los contaminantes emitidos a la atmósfera, de acuerdo a lo señalado en las normas oficiales mexicanas, normas ambientales estatales y demás disposiciones legales aplicables;\nIII. Llevar y mantener actualizada, bitácora de sus procesos industriales y una de operación y mantenimiento de los equipos utilizados para el control de las emisiones de acuerdo a los formatos emitidos por la Secretaría;\nIV. Instalar y mantener una plataforma y un puerto de muestreo en las chimeneas o puntos de emisión;\nV. Aplicar la mejor tecnología disponible para reducir y controlar sus emisiones y mantenimiento del equilibrio ecológico; y caso de descompostura o falla de los equipos de control de emisiones, susceptibles de generar una contingencia ambiental.\nLey de Protección al Ambiente para el Estado de Baja California. Página 57\nPara los efectos de lo dispuesto en este capítulo, se entiende por fuente fija de competencia estatal, a los establecimientos industriales que no son definidos como fuentes fijas de jurisdicción federal, conforme al Capítulo II, Título Cuarto de la Ley General.\nARTÍCULO 116.- Los municipios, a través de los bandos de policía o reglamentos que al efecto expidan, podrán sujetar a los establecimientos comerciales y de servicios, a los requerimientos que considere pertinentes en materia de emisión de contaminantes a la atmósfera.\nSECCIÓN IV\nDe los centros de verificación\nARTÍCULO 117.- Queda prohibido la circulación de automotores que emitan contaminantes, cuyos niveles de emisión a la atmósfera rebasen los máximos permisibles establecidos en las normas aplicables.\nLa autoridad correspondiente podrá limitar la circulación de vehículos automotores en el Estado, incluyendo los que cuenten con placas expedidas por otra entidades federativas o en el extranjero, para prevenir y reducir las emisiones contaminantes, conforme a lo previsto por el Programa de Verificación Vehicular que expida la Secretaría, y en su caso, los reglamentos municipales que se emitan al respecto.\nArtículo Reformado\nARTÍCULO 118.- Los propietarios o poseedores de vehículos automotores en circulación deberán someter sus unidades a la verificación de emisores contaminantes en los centros de verificación, dentro del periodo que le corresponda en los términos del\nPrograma de Verificación Vehicular, así como obtener la constancia de verificación de emisores en la que se señale que se cumple con los límites máximos permisibles que establezca dicho Programa, las normas oficiales mexicanas y demás aplicables, y revalidarla anualmente.\nEn su caso, los propietarios o poseedores de vehículos automotores deberán reparar los sistemas de emisores de contaminantes de éstos y sustituir los equipos y dispositivos que no funcionen adecuadamente en aquellos, en los términos que determine el Programa de Verificación Vehicular. verificación dentro del periodo que le corresponda, de acuerdo al calendario establecido en el Programa de Verificación Vehicular, deberá trasladarse en un término de treinta días determinadas, exclusivamente, conforme a los reglamentos municipales en materia de tránsito, que en su caso se emitan.\nArtículo Reformado\nLey de Protección al Ambiente para el Estado de Baja California. Página 58\nARTÍCULO 118 BIS.- Los vehículos con una antigüedad mínima de 40 años, de carrocería conserven sus características de originalidad y de operación hasta en un 95%, establecidos en el Programa que emita la Secretaría.\nArtículo Reformado\n(Nota aclaratoria: De conformidad con lo establecido por la Controversia Constitucional\n58/2013, publicada en el Periódico Oficial Número 45, Sección II, de fecha 25 de septiembre del 2015, solo serán aplicables en los municipios de Mexicali, Tecate, Playas de Rosarito y\nEnsenada).\nARTÍCULO 119.- Las constancias a que se refiere el artículo anterior, serán emitidas por los centros de verificación establecidos por la Secretaría o por los particulares que obtengan la correspondiente concesión, en los términos de esta Ley, el Programa de verificación Vehicular y disposiciones reglamentarias correspondientes.\nEn todo caso, corresponde a la Secretaría, vigilar el adecuado funcionamiento de los centros de verificación.\nArtículo Reformado\nARTÍCULO 119 BIS.- Será revocada la concesión a los centros de verificación que falseen pruebas con la finalidad de modificar los resultados para lograr la aprobación de emisiones, como ocurre tratándose de:\nI. Alterar el equipo o la toma de la muestra,\nII. Verificar un vehículo para aprobar otro,\nIII. Capturar la información de identidad de un vehículo que no corresponda al que realmente efectuó la prueba, o\nIV: Usar cualquier dispositivo o sistema no autorizado por la Secretaría.\nArticulo Adicionado\nARTÍCULO 119 BIS 1.- Quienes entreguen documentos que acrediten la aprobación de verificaciones de vehículos automotores, sin contar con la concesión correspondiente, aplicables.\nArtículo Adicionado\nARTÍCULO 119 BIS 2.- Los centros de verificación deberán obtener y mantener vigente en el Estado, para garantizar el cumplimiento de las obligaciones y condiciones establecidas en esta Ley, su reglamento, el Programa de Verificación Vehicular, la concesión y circulares correspondientes.\nArtículo Adicionado\nLey de Protección al Ambiente para el Estado de Baja California. Página 59\nARTÍCULO 119 BIS 3.- La concesión sólo podrá darse por terminada cuando:\nI. La Secretaría modifique las condiciones conforme a las que deberá prestarse el servicio,\nII. Concluya el término de la concesión, o\nIII. En los casos de revocación previstos en el artículo 119 bis de la presente Ley.\nPara efectos de la fracción primera de este artículo, la Secretaría publicará en el\nPeriódico Oficial del Estado y en un diario de circulación local, las nuevas condiciones que se deberán cumplir para que las concesiones sean revalidadas, con sesenta días naturales de anticipación, como mínimo, a la fecha prevista para que dichas condiciones entren en vigor.\nArtículo Adicionado\nARTÍCULO 119 BIS 4.- Los centros de verificación están obligados a:\nI. Operar conforme a los sistemas, procedimientos, instalaciones, equipos, plazos y condiciones establecidos en esta Ley, las normas oficiales mexicanas, normas ambientales estatales, el Programa de Verificación Vehicular y demás normatividad correspondiente;\nII. Contar con personal debidamente acreditado por la Secretaría;\nIII. Mantener sus instalaciones y equipos calibrados en las condiciones requeridas por la Secretaría, observando los requisitos que fije la misma para la debida prestación del servicio de verificación vehicular;\nIV. Destinar exclusivamente sus establecimientos respectivos a la verificación de emisiones contaminantes, sin efectuar en ellos reparaciones mecánicas, venta de refacciones automotrices o cualquier otra actividad comercial o industrial;\nV. Abstenerse de recibir documentación reportada como robada, falsificada o notoriamente alterada como soporte de las verificaciones vehiculares;\nVI. Llevar un registro con la información de las verificaciones efectuadas y remitir a la\nSecretaría los datos obtenidos en los términos fijados por ésta;\nVII. Dar aviso inmediato a la Secretaría cuando dejen de prestar el servicio de verificación vehicular o los equipos e instalaciones no funcionen debidamente, en cuyo caso se abstendrán de realizar verificaciones hasta en tanto los mismos funcionen correctamente;\nVIII. Conservar en depósito y manejar debidamente los documentos que reciban de la\nSecretaría para acreditar la aprobación de la verificación vehicular, hasta que éstos sean entregados al interesado y, en su caso, adheridos a la fuente emisora de contaminantes;\nIX. Dar aviso inmediato a la Secretaría y presentar las denuncias correspondientes, Ley de Protección al Ambiente para el Estado de Baja California. Página 60 la verificación vehicular;\nX. Enviar a la Secretaría, en los términos establecidos por ésta, la documentación e información requerida para la supervisión y control de la verificación;\nXI. Mantener durante las horas de funcionamiento a un responsable técnico y recibir las verificaciones administrativas que ordene la Secretaría en cualquier momento;\nXII. Contar con los elementos distintivos determinados por la Secretaría;\nXIII. Cobrar las tarifas autorizadas conforme a la normatividad aplicable, por la prestación del servicio de verificación vehicular;\nXIV. Mantener en vigor la fianza correspondiente durante la vigencia de la concesión para prestar el servicio de verificación vehicular;\nXV. Corroborar que el equipo y programa de cómputo que se le instale para proporcionar el servicio de verificación vehicular, sea la versión autorizada por la Secretaría, de lo contrario abstenerse de proporcionar el servicio; y\nXVI. Las demás que determine la Secretaría para garantizar el correcto funcionamiento de los centros de verificación.\nArtículo Adicionado\nSECCIÓN V\nPrevención y control de la contaminación lumínica\nARTÍCULO 120.- Para la prevención y control de la contaminación lumínica la\nSecretaría, tendrá las siguientes facultades:\nI.- Promover la creación y ejecución del Programa para la Prevención y Control de la\nContaminación Lumínica, en apego a lo dispuesto en esta Ley, en la Ley General y las\nNormas Oficiales Mexicanas;\nII.- Promover la realización de estudios y proyectos destinados a prevenir y controlar la contaminación lumínica en los municipios de la entidad;\nIII.- Apoyar a los Municipios en la elaboración y aplicación de sus reglamentos, comerciales y de servicios a los requerimientos que consideren pertinentes en la materia;\nIV.- Promover campañas y actividades de capacitación, difusión y sensibilización sobre la importancia de prevenir la contaminación lumínica; y\nLey de Protección al Ambiente para el Estado de Baja California. Página 61\nV.- Promover convenios de colaboración con organismos e instituciones de investigación local, nacional e internacional, interesadas en la preservación de la calidad de la atmósfera.\nArtículo Reformado\nARTÍCULO 121.- En materia de prevención y control de la contaminación lumínica, los municipios tendrán las siguientes facultades:\nI.- Participar en la elaboración del Programa para la Prevención y Control de la\nContaminación Lumínica, en apego a lo dispuesto en esta Ley, en la Ley General y las\nNormas Oficiales Mexicanas;\nII.- Promover las disposiciones de protección ambiental para evitar la contaminación lumínica, en el ámbito de su competencia, en particular;\na) La regulación de los establecimientos mercantiles o de servicios;\nb) En materia de alumbrado público;\nc) En materia de edificaciones;\nd) En materia de imagen urbana, y\ne) En general aquellas que pudieran generar contaminación lumínica.\nIII.- Integrar y mantener actualizado el inventario de luminarias y coordinarse con el gobierno estatal para la integración del inventario en el Estado;\nIV.- Promover campañas y actividades de capacitación, difusión y sensibilización sobre la importancia de prevenir la contaminación lumínica; y\nV.- Promover convenios de colaboración con organismos e instituciones de investigación local, nacional e internacional, interesadas en la preservación de la calidad de la atmósfera.\nArtículo Reformado\nCAPÍTULO III\nPrevención y control de la contaminación del agua.\nSección I\nCriterios ambientales.\nARTÍCULO 122.- Para la prevención y control de la contaminación del agua se considerarán los criterios establecidos en la Ley General.\nLey de Protección al Ambiente para el Estado de Baja California. Página 62\nARTÍCULO 123.- Los criterios para la prevención y control de la contaminación del agua deberán considerarse en:\nI. La expedición de normas ambientales estatales para el uso, tratamiento y disposición de aguas residuales, para evitar riesgos y daños a la salud pública y al ambiente;\nII. El otorgamiento de concesiones, permisos, licencias, y en general toda clase de autorizaciones para el aprovechamiento sustentable del agua y las descargas de agua residual;\nIII. El diseño y operación de sistemas de agua potable, alcantarillado y tratamiento de agua residual; y\nIV. La restricción o suspensión de explotaciones y aprovechamientos en casos de contaminación de las fuentes de abastecimiento.\nARTÍCULO. 124.- Las disposiciones contenidas en el presente capítulo, son aplicables a las descargas de aguas residuales que se viertan a los cuerpos de aguas nacionales asignadas al estado, a las aguas que en los términos de la Constitución Política de los Estados Unidos Mexicanos sean de jurisdicción local y a los sistemas de drenaje y alcantarillado de los centros de población.\nSECCIÓN II\nFacultades\nARTÍCULO 125.- En materia de prevención y control de la contaminación del agua, la\nSecretaría tendrá las siguientes facultades:\nI. Prevenir y controlar las descargas de aguas residuales a cuerpos receptores de competencia estatal;\nII. Requerir a quienes generen descargas de aguas residuales a cuerpos receptores, mexicanas y las normas ambientales estatales;\nIII. Integrar el registro y otorgar la licencia correspondiente, de conformidad con esta ley, la Ley General y sus reglamentos, a los generadores de descargas de aguas residuales a cuerpos receptores de competencia estatal;\nIV. Requerir a quienes generen descargas de aguas residuales, la aplicación de la mejor tecnología disponible, con el propósito de reducir la generación de contaminantes;\nV. Integrar y mantener actualizado el registro de descargas de aguas residuales a\nLey de Protección al Ambiente para el Estado de Baja California. Página 63 municipal para la integración de los registros nacional, estatal y municipales de descargas de aguas residuales;\nVI. Tomar las medidas preventivas necesarias para evitar contingencias ambientales por contaminación del agua; y\nVII. Requerir a quienes generen descargas y no cumplan con las normas oficiales mexicanas o normas ambientales estatales, la instalación de equipos o sistemas de tratamiento de aguas residuales.\nPara los efectos de lo dispuesto en este capítulo, se considerarán cuerpos receptores de competencia estatal, las aguas nacionales asignadas al estado, las aguas que en términos del artículo 27 constitucional, sean consideradas de jurisdicción local y los sistemas de drenaje y alcantarillado de centros de población, por lo que se refiere a descargas de aguas residuales de obras y actividades industriales.\nARTÍCULO 126.- En materia de prevención y control de la contaminación del agua, los municipios, por si mismos, o por conducto de los organismos públicos municipales que administren los sistemas de agua y alcantarillado, tendrán las siguientes facultades:\nI. Prevenir y controlar la contaminación de las descargas de aguas residuales a cuerpos receptores de competencia municipal;\nII. Requerir, y en su caso autorizar, a quienes generen descargas de aguas residuales a cuerpos receptores, el cumplimiento de los límites máximos permisibles que establezcan las normas aplicables;\nIII. Requerir a quienes generen descargas de aguas residuales, la aplicación de la mejor tecnología disponible, con el propósito de reducir la generación de contaminantes y volumen de descarga, así como fomentar su reuso;\nIV. Integrar y mantener actualizado el registro municipal de descargas de aguas residuales; y\nV. Requerir a quienes generen descargas y no cumplan con las normas oficiales mexicanas o normas ambientales estatales, la instalación de los equipos o sistemas de tratamiento de aguas residuales. municipales administradores de los sistemas de agua y alcantarillado, y los sistemas de drenaje y alcantarillado de los centros de población, por lo que se refiere a descargas de aguas residuales provenientes de obras y actividades comerciales y de servicios.\nSección III\nLey de Protección al Ambiente para el Estado de Baja California. Página 64\nControl de descargas de aguas residuales\nARTÍCULO 127.- No podrán descargarse aguas residuales provenientes de usos públicos urbanos y las de usos industriales o agropecuarios, en los sistemas de drenaje y jurisdicción estatal o municipal, en los casos que generen o puedan generar:\nI. Contaminación de los cuerpos receptores;\nII. Interferencias en los procesos de tratamiento o depuración de las aguas; y\nIII. Trastornos, alteraciones o impedimentos en los aprovechamientos, en el funcionamiento y en la capacidad de los sistemas hidráulicos y de drenaje y alcantarillado, así como en aquellos de tratamiento de aguas residuales y de riego agrícola.\nARTÍCULO. 128.- No podrán descargarse o infiltrarse en cualquier cuerpo o corriente de agua de jurisdicción estatal o municipal o en el suelo, aguas residuales que contengan contaminantes, sin el previo tratamiento y sin contar con el permiso de descarga de la\nSecretaría, los municipios o los organismos municipales administradores de los sistemas de agua y alcantarillado, según corresponda.\nARTÍCULO 129.- Se exceptúan de la obligación de contar con el permiso a que se refiere el artículo anterior, a los responsables de las descargas a los sistemas de drenaje y alcantarillado provenientes de los siguientes usos:\nI. Domésticos;\nII. Servicios sanitarios o análogos a los domésticos; y\nIII. Aquellos que determinen las normas ambientales aplicables y los reglamentos correspondientes.\nARTÍCULO 130.- Los responsables de la generación de descargas de aguas residuales de competencia estatal y municipal, están obligados a:\nI. Tramitar y obtener el permiso de descarga de aguas residuales y anualmente revalidar su vigencia;\nII. Dar Tratamiento a sus descargas y mantenerlas por debajo de los niveles aplicables;\nIII. Aplicar la mejor tecnología disponible para reducir la generación de contaminantes y el volumen de descarga, así como facilitar su reuso;\nLey de Protección al Ambiente para el Estado de Baja California. Página 65\nIV. En el caso de fallas o descomposturas de los equipos de control de la contaminación del agua, de inmediato realizar las actividades y obras para su restauración y dar aviso a la Secretaría; y\nV. Mantener en el predio un acceso fácil y permanente al punto de descarga de las aguas residuales para su monitoreo.\nVI. Llevar y mantener actualizada, una bitácora de operación y mantenimiento del equipo utilizado para tratamiento y control de la descarga de aguas residuales.\nARTÍCULO 131.- Los municipios, en los bandos de policía o reglamentos que al efecto se expidan, podrán sujetar a los establecimientos comerciales y de servicios a los requerimientos que consideren pertinentes en materia de descarga de aguas residuales.\nARTÍCULO 132.- Para conocer la calidad de las aguas, se establecerá un sistema estatal de monitoreo, que será llevado a cabo, en el ámbito de su competencia, por las dependencias estatales, municipales y los organismos públicos que tengan a su cargo la administración, distribución y operación de los sistemas de agua, drenaje y alcantarillado.\nCAPÍTULO IV\nPrevención y control de la contaminación del suelo\nSECCIÓN I\nCriterios ambientales\nARTÍCULO 133.- Para la prevención y control de la contaminación del suelo, se considerarán los criterios establecidos en la Ley General.\nARTÍCULO 134.- Los criterios para la prevención y control de la contaminación del suelo deberán considerarse en:\nI. La expedición de normas ambientales estatales y municipales, para el funcionamiento de los sistemas de recolección transporte, almacenamiento, manejo, tratamiento, reciclaje, confinamiento y disposición final de residuos no peligrosos, así como para evitar la contaminación del suelo, para evitar riesgos y daños al ambiente;\nII. La ordenación y regulación del desarrollo urbano, del turístico, industrial y agropecuario; y\nIII. El otorgamiento de concesiones, permisos, y en general toda clase de autorizaciones que al efecto se otorguen con relación a la generación, recolección, transporte, almacenamiento, manejo, tratamiento y disposición final de residuos no peligrosos.\nLey de Protección al Ambiente para el Estado de Baja California. Página 66\nSECCIÓN II\nFacultades\nARTÍCULO 135.- Para la prevención y control de la contaminación del suelo, la\nSecretaría, en las materias de su competencia, tendrá las siguientes facultades:\nI. Promover las acciones necesarias para evitar la contaminación del suelo;\nII. Tomar las medidas preventivas necesarias para evitar contingencias ambientales por contaminación del suelo;\nIII. Promover la realización de las obras y actividades de regeneración y rehabilitación para la restauración de los suelos contaminados, así mismo para los que presentan fenómenos de erosión o degradación;\nIV. Requerir a quienes generen contaminación del suelo el cumplimiento de las normas aplicables en materia de almacenamiento reuso, recuperación, reciclaje, incineración, tratamiento, confinamiento y disposición final de residuos de manejo especial y de lenta degradación;\nV. Integrar y mantener actualizado el inventario de generación de residuos de competencia estatal y coordinarse con los gobiernos federal y municipal para la integración del inventario de generación de residuos;\nVI. Requerir, a quienes produzcan contaminación del suelo, para que lleven a cabo las acciones necesarias para recuperar y restablecer las condiciones del mismo, para que este pueda ser destinado a alguna de las actividades previstas en el programa de desarrollo urbano o de ordenamiento ecológico que resulte aplicable para el predio o zona respectiva; y\nVII. Autorizar las actividades relacionadas con la exploración, explotación, extracción y aprovechamiento de los minerales o sustancias no reservadas a la federación y requerir la restauración y reforestación de las áreas utilizadas, una vez concluidos los trabajos respectivos.\nEn el caso de que sea el Ayuntamiento quien opere el sistema de recolección, estación de transferencia, transporte, almacenamiento, manejo, tratamiento de un sitio de disposición final de residuos sólidos urbanos, será la Secretaría quien lo regulará y requerirá para el cumplimiento de la Ley General, esta Ley y la normatividad aplicable.\nARTÍCULO 136.- En materia de prevención y control de la contaminación del suelo, los municipios tendrán las siguientes facultades:\nI. Operar el sistema de manejo de residuos sólidos urbanos;\nII. Promover normas ambientales estatales para evitar la contaminación del suelo;\nLey de Protección al Ambiente para el Estado de Baja California. Página 67\nIII. Tomar las medidas preventivas necesarias para evitar contingencias ambientales por contaminación del suelo;\nIV. Autorizar las actividades de recolección, transporte, almacenamiento, segregación, aprovechamiento y manejo de los residuos sólidos urbanos;\nV. Requerir y aplicar las disposiciones jurídicas relativas a la prevención y control de la contaminación del ambiente, a los responsables de la generación, recolección, almacenamiento, manejo, transporte y reciclaje de residuos sólidos urbanos, conforme a las normas aplicables y demás condicionantes que se les establezcan;\nVI. Requerir y aplicar las disposiciones jurídicas a quienes generen y provoquen la contaminación del suelo, el cumplimiento de las normas aplicables y demás condicionantes que se les establezcan, en materia de manejo, recolección, transporte, almacenamiento, reuso, recuperación y reciclaje de residuos sólidos urbanos;\nVII. Integrar y mantener actualizado el inventario de generación de residuos sólidos urbanos y coordinarse con el Gobierno Estatal para la integración del inventario de generación de residuos en el Estado, y\nVIII. Expedir en sus bandos de policía o reglamentos los requerimientos que considere pertinentes para sujetar los responsables a que se refieren las fracciones III y IV de este artículo, en materia de prevención y control de la contaminación del suelo.\nIX. Requerir y aplicar las sanciones respectivas a los particulares que provoquen la contaminación del suelo con tiras clandestinas de los residuos sólidos urbanos en lugares no destinados para ello.\nArtículo Reformado\nARTÍCULO 137.- Derogado.\nArtículo Derogado\nARTÍCULO 138.- Quienes realicen proyectos obras o actividades que contaminen o puedan contaminar los suelos o desarrollen actividades, relacionadas con la exploración, explotación, extracción y aprovechamiento de materiales o sustancias no reservadas a la federación, están obligados a:\nI. Implementar prácticas y aplicar tecnologías que eviten los impactos ambientales negativos a que se refiere el artículo anterior;\nII. Cumplir con las normas oficiales mexicanas y normas ambientales estatales que al efecto se expidan;\nIII. Restaurar y reforestar las áreas utilizadas una vez concluidos los trabajos respectivos, de acuerdo con los principios y criterios expedidos por la Secretaría o los municipios; y\nLey de Protección al Ambiente para el Estado de Baja California. Página 68\nIV. Tramitar y obtener las autorizaciones correspondientes a que se refiere esta ley; y (sic)\nARTÍCULO 139.- Derogado.\nArtículo Derogado\nARTÍCULO 140.- Las autoridades que tengan a su cargo la promoción y el fomento de las actividades agropecuarias, vigilarán y regularán que en la aplicación y empleo de plaguicidas, fertilizantes o sustancias tóxicas, no se provoque contaminación del suelo y así evitar daños a los seres humanos, al ambiente, cultivos y áreas circunvecinas.\nARTÍCULO 141.- Para la protección del Estado de Baja California y sus habitantes queda prohibida el obsequio, venta o entrega al consumidor final de bolsas de plástico en supermercados, tiendas de autoservicio o conveniencia, mercados, comercios de giros diversos y en general cualquier tipo de unidad comercial que sean elaboradas con polietileno de baja densidad, polietileno lineal, polietileno de alta densidad, polipropileno, polímero de plástico y cualquier otro de sus derivados, así como cualquier bolsa que no cumpla con las normas oficiales mexicanas que determinen los criterios en materia de eficiencia ambiental y tecnológica, y en materia de generación, manejo y disposición final.\nPárrafo Reformado\nQuedan exentas de la restricción del párrafo anterior aquellas bolsas que hayan sido producidas incorporando un porcentaje mínimo de treinta por ciento (30%) de material reciclado y que la fabricación de dichas bolsas de plástico sea con materiales y procesos de tecnología que permitan su ágil degradación.\nPárrafo Reformado\nEntre los Criterios y Normas de Producción Sustentable que formule la Secretaría para la fabricación de bolsas de plástico, se comprenderá:\nPárrafo Reformado\n1. Conservación de recursos naturales y no renovables;\n2. Minimización de las emisiones y la generación de residuos;\n3. Procesos de fabricación atóxicos, y\n4. Los demás que la Secretaría determine para favorecer la producción sustentable de las bolsas de plástico. mayor al de diez años.\nLey de Protección al Ambiente para el Estado de Baja California. Página 69 incompatible con el reciclaje, se procurará que éstas tengan un fin de vida menor al de cinco años.\nArtículo Reformado\nARTÍCULO 141 BIS.- La Secretaría, en coordinación con Municipios, diseñará y realizará campañas permanentes de información para concientizar y sensibilizar a la población sobre los peligros y efectos nocivos que, para el medio ambiente, representa el uso de popotes y utensilios de plástico, con objeto de desincentivar su utilización en el hogar y en restaurantes, bares y todo tipo de establecimientos en los que se comercialice y/o se ofrezcan alimentos y bebidas.\nArtículo Adicionado\nARTÍCULO 141 TER.- Los establecimiento en los que se comercialice y/o se ofrezcan alimentos y bebidas, dentro del territorio del Estado, deberán prescindir de proporcionar popotes, utensilios y agitadores de plástivo para el consumo de sus productos, salvo que el usuario lo solicite.\nArtículo Adicionado\nSECCION III\nDerogada\nSección Derogada\nARTÍCULO 142.- Derogado.\nArtículo Derogado\nARTÍCULO 143.- Derogado.\nArtículo Derogado\nARTÍCULO 144.- Derogado.\nArtículo Derogado\nARTÍCULO 145.- Derogado.\nArtículo Derogado\nARTÍCULO 146.- Derogado.\nArtículo Derogado\nARTÍCULO 147.- Derogado.\nArtículo Derogado\nARTÍCULO 148.- Derogado.\nArtículo Derogado\nARTÍCULO 149.- Derogado.\nArtículo Derogado\nLey de Protección al Ambiente para el Estado de Baja California. Página 70\nSECCION IV\nManejo, Almacenameinto y Tránsito de Materiales y Residuos Peligrosos\nARTÍCULO 150.- Para la protección de los habitantes, con motivo de la operación de sistemas destinados al manejo de materiales y residuos peligrosos, los reglamentos de esta ley y las normas ambientales estatales, podrán establecer medidas o restricciones complementarias a las que emita la Federación en los siguientes aspectos:\nI. Características de las edificaciones que alberguen a dichas instalaciones y las franjas de aislamiento, o áreas de amortiguación que se deben guardar en los usos habitacionales;\nII. Tránsito dentro de zonas urbanas y centros de población; y\nIII. Aquellas necesarias para evitar o prevenir contingencias ambientales y emergencias ecológicas.\nLa vigilancia y aplicación de dichas medidas o restricciones corresponderá a la\nSecretaría o municipios de acuerdo a la distribución de competencias que establece la presente Ley.\nARTÍCULO 151.- Los municipios establecerán en los planes o programas de desarrollo urbano las zonas donde se permitirá, condicionará o prohibirá el establecimiento de las obras y actividades riesgosas y las altamente riesgosas, así como aquellas dedicadas al almacenamiento, reciclaje, tratamiento de materiales y residuos peligrosos, en los términos de lo dispuesto por la Ley General y esta Ley\nARTÍCULO 152.- Requieren autorización de la Secretaría en materia de impacto ambiental, previo al inicio de la construcción y operación, de las instalaciones para el tratamiento, reciclaje, recuperación, incineración, confinamiento o disposición final de residuos peligrosos, cuando también en ellas se pretenda tratar, reciclar, recuperar, incinerar, confinar o disponer residuos no peligrosos.\nSECCION V\nActividades Riesgosas\nARTÍCULO 153.- Los reglamentos de esta Ley y las normas ambientales estatales establecerán la clasificación de las actividades que deban considerarse riesgosas, en virtud de las características de peligrosidad y riesgo, que éstas representen para el equilibrio ecológico y el ambiente, de los materiales que se manejen o generen en los establecimientos industriales, comerciales o de servicios, considerando los volúmenes de manejo y ubicación del establecimiento.\nPara el establecimiento de esta clasificación, se deberá considerar previamente la opinión de las autoridades competentes.\nLey de Protección al Ambiente para el Estado de Baja California. Página 71\nARTÍCULO 154.- Para evitar y reducir los riesgos ambientales con motivo de la realización de actividades riesgosas, corresponde a la Secretaría:\nI. Evaluar, y en su caso, aprobar los estudios de riesgo ambiental, así como los programas para la prevención de accidentes y el de atención a contingencias;\nII. Promover ante responsables de la realización de las actividades riesgosas, la aplicación de la mejor tecnología disponible para evitar y minimizar los riesgos ambientales;\nIII. Tomar las medidas preventivas necesarias para evitar contingencias ambientales; y\nIV. Requerir a las personas físicas o morales un seguro de responsabilidad civil por daños ambientales.\nARTÍCULO 155.- Corresponde a los municipios vigilar que en la determinación de los usos del suelo se especifiquen las zonas en las que se permita el establecimiento de las actividades consideradas altamente riesgosas, así como las riesgosas, tomando en consideración:\nI. Las condiciones topográficas, meteorológicas, climatológicas, geológicas y sísmicas de las zonas;\nII. Su ubicación o proximidad a centros de población, previendo las tendencias de expansión y la creación de asentamientos;\nIII. Los impactos probables de un posible evento extraordinario de la industria, comercio o servicio de que se trate, sobre los centros de población y sobre los recursos naturales;\nIV. La compatibilidad con otras actividades de las zonas;\nV. La infraestructura existente y necesaria para la atención de emergencias ecológicas; y\nVI. La infraestructura para la dotación de servicios básicos.\nARTÍCULO 156.- Corresponde a los municipios establecer restricciones a los usos altamente riesgosas y establecer en los programas de desarrollo urbano, las prohibiciones a los usos habitacionales, comerciales u otros que pongan en riesgo a la población. Asimismo, intermedias de salvaguarda.\nARTÍCULO 157.- Los responsables de la realización de actividades riesgosas están obligados a:\nLey de Protección al Ambiente para el Estado de Baja California. Página 72\nI. Cumplir con las disposiciones previstas en esta ley, sus reglamentos y las normas aplicables;\nII. Tramitar, y en su caso, obtener autorización del estudio de riesgo ambiental y los programas para la prevención de accidentes y atención a contingencias, y presentarlos ante la autoridad competente;\nIII. Ubicarse en las zonas determinadas por el municipio como aptas para la instalación de actividades riesgosas, y en su caso, garantizar el establecimiento de la zona intermedia de salvaguarda;\nIV. Aplicar la mejor tecnología disponible para evitar y minimizar los riesgos ambientales;\nV. Dar aviso inmediato a la Secretaría, los cuerpos de bomberos y las unidades de protección civil, en caso accidentes que puedan ocasionar una contingencia ambiental o una emergencia ecológica; y\nVI. Cumplir con las condiciones de operación que le establezca la Secretaría, e instalar equipos o sistemas de seguridad.\nTÍTULO QUINTO\nPARTICIPACIÓN CIUDADANA\nCAPÍTULO I\nParticipación Ciudadana\nARTÍCULO 158.- El gobierno estatal, a través de la Secretaría, y los municipios deberán promover la participación corresponsable de la sociedad en la planeación, ejecución, evaluación y vigilancia de la política ambiental.\nARTÍCULO 159.- Para los efectos del artículo anterior, el Ejecutivo Estatal y los municipios:\nI. Convocarán, en el ámbito del sistema estatal de planeación democrática, al sector social, privado, instituciones académicas, grupos y organizaciones sociales, y demás personas interesadas, para que manifiesten sus opiniones y propuestas;\nII. Alentarán el uso de instrumentos de participación ciudadana en materia ambiental, como el plebiscito, referéndum e iniciativa ciudadana, cuyas reglas se sujetarán a la ley en la materia;\nIII. Celebrarán convenios con los diferentes sectores de la sociedad y personas interesadas, para el establecimiento, administración, manejo, conservación, mejoramiento y equipamiento de áreas naturales protegidas y áreas verdes urbanas, aprovechamiento\nLey de Protección al Ambiente para el Estado de Baja California. Página 73 sustentable de los recursos naturales, acciones de protección al ambiente y la realización de estudios e investigación en la materia;\nFracción Reformada\nIV. Celebrarán convenios con los medios de comunicación masiva para la difusión, al ambiente;\nV. Promoverán el establecimiento de reconocimientos a los esfuerzos más destacados de la sociedad para preservar y restaurar el equilibrio ecológico y proteger el ambiente;\nVI. Impulsarán el fortalecimiento de la cultura ambiental, a través de la realización de acciones conjuntas con la comunidad para la preservación y restauración del ambiente, el aprovechamiento racional de los recursos naturales y el correcto manejo de los residuos.\nPara ello podrán, en forma coordinada, celebrar convenios con las comunidades urbanas y rurales, así como con diversas organizaciones sociales; y\nVII. Concertarán acciones e inversiones con los sectores social y privado, instituciones académicas, grupos y organizaciones sociales, y demás personas interesadas, en favor de la preservación y restauración del equilibrio ecológico y la protección al ambiente.\nArtículo Reformado\nCAPÍTULO II\nInformación Ambiental\nARTÍCULO 160.- Toda persona tendrá derecho a que las autoridades ambientales pongan a su disposición la información ambiental que les soliciten, en los términos previstos por esta ley y sus reglamentos.\nPara los efectos de lo dispuesto en esta Ley, se considerará información ambiental, cualquier información escrita, visual o en forma de base de datos, de que dispongan las autoridades ambientales en materia de agua, aire, suelo, flora, fauna y recursos naturales de jurisdicción estatal y municipal, así como sobre las actividades o medidas que les afecten o puedan afectarlos.\nEn su caso los gastos que se generen, correrán por cuenta del solicitante y de la Ley de Ingresos del estado.\nToda petición de información ambiental deberá presentarse por escrito, especificando claramente la información que se solicita y los motivos de la petición. Los solicitantes deberán identificarse indicando su nombre o razón social y domicilio.\nLey de Protección al Ambiente para el Estado de Baja California. Página 74\nARTÍCULO 161.- La Secretaría, en coordinación con los municipios, desarrollará un sistema estatal de información ambiental, vinculado al sistema nacional de información ambiental y de recursos naturales, que tendrá por objeto registrar, organizar, actualizar y difundir la información ambiental estatal, por los diferentes medios, incluidos los electrónicos. Los aspectos de integración y operación, del sistema de información ambiental, serán establecidos en el reglamento.\nEn dicho sistema se integrarán, entre otros aspectos, información relativa a los inventarios de recursos naturales existentes en el Estado, de los Mecanismos y resultados obtenidos del monitoreo de la calidad del aire, del agua y del suelo, al ordenamiento ecológico del estado, así como la información relativa a emisiones atmosféricas, descargas de aguas residuales y residuos no peligrosos, y la correspondiente a los registros, programas y acciones que se realicen para la preservación del equilibrio ecológico y la protección del ambiente.\nARTÍCULO 162.- La Secretaría y los municipios elaboraran y publicarán cada dos años un diagnóstico de la situación general existente en la entidad en materia ambiental, el cual se integrará al sistema estatal de información ambiental.\nARTÍCULO 163.- La Secretaría editará la revista ambiental en la que se publicarán las disposiciones jurídicas, normas ambientales estatales, decretos, reglamentos, acuerdos, registros y demás actos administrativos, así como información de interés general en materia ambiental que se publiquen por los gobiernos federal, estatal y municipales, o documentos internacionales en materia ambiental de interés para la entidad, independientemente de su publicación en el Periódico Oficial del estado o en otros órganos de difusión.\nIgualmente, en dicha revista ambiental, se publicará la información oficial relacionada con las áreas naturales protegidas y la preservación y el aprovechamiento sustentable de los recursos naturales de jurisdicción estatal.\nARTÍCULO 164.- La autoridad ambiental deberá responder por escrito a los la fecha de recepción de la petición respectiva.\nEn caso que la autoridad conteste negativamente la solicitud, deberá señalar las razones que motivaron tal determinación. capítulo, podrán ser impugnados mediante la interposición del recurso correspondiente, de conformidad con lo dispuesto en esta Ley y disposiciones reglamentarias.\nLey de Protección al Ambiente para el Estado de Baja California. Página 75\nARTÍCULO 165.- Quien reciba información ambiental de las autoridades competentes, en los términos del presente capítulo, será responsable de su adecuada manejo.\nARTÍCULO 166.- La Secretaría o los municipios denegarán la información solicitada cuando:\nI. Se considere por disposición legal que la información es confidencial y que por su propia naturaleza su difusión afecte o pueda afectar la seguridad de la entidad o municipios;\nII. Se trate de información relativa a asuntos que son materia de procedimientos judiciales o de inspección y vigilancia, pendientes de resolución;\nIII. Se trate de información aportada por terceros cuando los mismos no estén obligados por disposición legal a proporcionarla;\nIV. Se trate de información sobre inventarios e insumos y tecnología de proceso, incluyendo la descripción del mismo; y\nV. Se utilice con fines de lucro o publicidad.\nEn todo caso, la Secretaría y las autoridades municipales informarán a la población acerca de los riesgos potenciales que generen diversos establecimientos, las formas de prevenirlos y en su caso, como enfrentarlos.\nCAPÍTULO III\nDenuncia\nARTÍCULO 167.- Toda persona, física o moral, podrá denunciar ante las autoridades ambientales, cualquier hecho, acto u omisión que produzca o pueda producir desequilibrios ecológicos, daños al ambiente, a los recursos naturales o contravenga las disposiciones de la presente Ley y demás ordenamientos en la materia. municipal en materia ambiental, la denuncia se podrá formular ante cualquier autoridad la autoridad municipal en materia ambiental.\nARTICULO 168.- Cuando la denuncia haya sido presentada ante una autoridad municipal distinta de la ambiental y resulta ser del orden municipal o estatal, deberá ser\nSecretaría, según sea el caso, dentro de los tres días hábiles contados a partir de la fecha de recepción.\nLey de Protección al Ambiente para el Estado de Baja California. Página 76 orden federal, se declinará para su atención o trámite a la Procuraduría Federal de\nProtección al Ambiente, dentro de los tres días hábiles contados a partir de la fecha de recepción. Cuando la persona denunciante solicite guardar secreto respecto de su identidad, por razones de seguridad e interés particular, la autoridad procederá a reservar sus datos, de conformidad con lo dispuesto en la Ley de Transparencia y Acceso a la Información\nPública para el Estado de Baja California.\nParrafo Reformado\nArtículo Reformado\nARTÍCULO 169.- Al recibir la denuncia ciudadana, la autoridad ambiental acusará recibo y le asignará un número de expediente, haciendo la anotación respectiva en el libro de registro.\nCuando se presenten dos o más denuncias respecto de los mismos hechos, actos u omisiones, deberá acordarse su acumulación en un sólo expediente, prevaleciendo el primer número de expediente asignado. El contenido del acuerdo respectivo deberá notificarse a los denunciantes.\nUna vez admitida la denuncia, la autoridad la atenderá mediante el procedimiento administrativo de inspección y vigilancia, asimismo efectuará las diligencias necesarias con el propósito de determinar la existencia de los hechos, acciones u omisiones constitutivos de la denuncia, así como el cumplimiento de la legislación ambiental vigente.\nPárrafo Reformado\nSi de las diligencias a que se refiere el párrafo anterior, se desprende que el asunto no es competencia de la autoridad que haya recibido la denuncia, dentro de un plazo no mayor a diez días hábiles, lo turnará a la autoridad que estime competente, notificándole de tal hecho a la persona denunciante, mediante acuerdo debidamente fundado y motivado.\nPárrafo Adicionado\nEn el caso de autoridad ambiental municipal, para el seguimiento de la denuncia ciudadana deberá estarse al procedimiento establecido en el reglamento que al efecto se expida.\nPárrafo Adicionado\nArtículo Reformado\nARTÍCULO 170.- La autoridad ambiental en el ámbito de sus atribuciones, está facultada para iniciar las acciones que procedan, ante las autoridades judiciales competentes, cuando conozca de actos, hechos u omisiones que constituyan violaciones a la legislación administrativa o penal.\nSi del resultado de las investigaciones realizadas por la autoridad ambiental, se desprende que se trata de actos, hechos u omisiones en que hubieren incurrido autoridades federales, estatales o municipales, emitirá las recomendaciones necesarias para promover ante estas u otras, la ejecución de las acciones procedentes.\nLey de Protección al Ambiente para el Estado de Baja California. Página 77\nARTÍCULO 171.- La denuncia deberá presentarse por escrito y contener al menos:\nI. El nombre o razón social, domicilio, correo electrónico y teléfono en su caso;\nFracción Reformada\nII. Los actos, hechos u omisiones denunciados;\nIII. Los datos que permitirán identificar al presunto infractor o localizar la fuente de contaminación; y\nIV. Las pruebas que en su caso ofrezca el denunciante.\nAsimismo, podrá formularse verbalmente, por vía telefónica o medios electrónicos la denuncia, en cuyo caso el denunciante deberá ratificarla por escrito, cumpliendo con los requisitos establecidos en el presente artículo, en un término de tres días hábiles siguientes a la formulación de la denuncia, sin perjuicio de que la Secretaría o la autoridad municipal competente investiguen de oficio los hechos constitutivos de la denuncia.\nArtículo Reformado\nARTÍCULO 172.- Los expedientes de denuncia que se encuentren en trámite podrán concluirse, en los siguientes casos:\nI. Por incompetencia para conocer de la denuncia planteada;\nII. Por haberse dictado la recomendación correspondiente;\nIII. Cuando no existan contravenciones a la normatividad ambiental;\nIV. Por falta de interés del denunciante en los términos de este capítulo;\nV. Por haberse dictado anteriormente acuerdo de acumulación de expedientes;\nVI. Por haberse solucionado la denuncia mediante conciliación entre las partes;\nVII. Por la emisión de una resolución derivada del procedimiento de inspección;\nVIII. Por desistimiento del denunciante;\nIX. Por desaparecer o extinguirse los actos, hechos u omisiones materia de la denuncia; y\nX. Las demás que se establezcan en el reglamento que al efecto se expida.\nARTÍCULO 173.- No se admitirán denuncias notoriamente improcedentes e infundadas. Aquellas en las que se advierta mala fe o inexistencia de petición, lo cual se notificará al denunciante.\nLey de Protección al Ambiente para el Estado de Baja California. Página 78\nARTÍCULO 174.- Las autoridades y servidores públicos involucrados en asuntos de la competencia de la autoridad ambiental, o que por razón de sus funciones o actividades puedan proporcionar información pertinente, deberán cumplir en sus términos con las peticiones que dicha autoridad les formule en tal sentido. documentación que se estime con carácter de reservado, conforme a lo dispuesto por la legislación aplicable, lo comunicarán a la autoridad ambiental. En este supuesto, dicha autoridad deberá manejar la información proporcionada bajo la más estricta confidencialidad.\nARTÍCULO 175.- Cuando una denuncia no implique violaciones a la normatividad ambiental, ni afecte cuestiones de orden público e interés social, la autoridad ambiental podrá sujetar la misma a un procedimiento de conciliación. En todo caso, se escuchará a las partes involucradas.\nTÍTULO SEXTO\nMEDIDAS DE CONTROL, DE SEGURIDAD Y SANCIONES\nCAPÍTULO I\nDe la inspección y vigilancia\nARTÍCULO 176.- Las autoridades ambientales a que se refiere el Capítulo II, del\nTítulo Primero de esta Ley, de conformidad con la distribución de competencias que en la misma se establece, podrán realizar actos de inspección y vigilancia del cumplimiento de las disposiciones contenidas en la Ley General, el presente ordenamiento, así como de las que de ellas se deriven.\nARTÍCULO 177.- Las autoridades competentes podrán realizar, por conducto de personal debidamente autorizado, visitas de inspección para verificar el cumplimiento de la\nLey General y esta ley.\nDicho personal, al realizar las visitas de inspección, deberá contar con el documento oficial que lo acredite o autorice a practicar la inspección, así como la orden escrita debidamente fundada y motivada, expedida por la autoridad competente en la que se precisará el lugar o la zona que habrá de inspeccionarse, el objeto de la diligencia y el alcance de esta. ejecución que le sean ordenados.\nARTÍCULO 178.- El personal autorizado, al iniciar la inspección, se identificará debidamente ante la persona propietaria, ante la o el representante o persona apoderada legal, o bien ante la persona encargada y/o responsable de las actividades del lugar o zona\nLey de Protección al Ambiente para el Estado de Baja California. Página 79 donde habrá de inspeccionarse. La inspección se realizará con la persona con quien se entienda la diligencia, a quien se exhibirá la orden respectiva y le entregará copia de la misma con firma autógrafa, requiriéndola para que en el acto designe a dos testigos.\nPárrafo Reformado\nEn caso de negativa o de que los designados no acepten fungir como testigos, el personal autorizado podrá designarlos, haciendo constar esta situación en el acta administrativa que al efecto se levante, sin que esta circunstancia invalide los efectos de la inspección.\nArtículo Reformado\nARTÍCULO 179.- La persona con quien se entienda la diligencia estará obligada a permitir al personal autorizado el acceso al lugar o lugares sujetos a inspección, en los términos previstos en la orden escrita a que se refiere este capítulo, así como proporcionar toda clase de información que conduzca a la verificación del cumplimiento de la Ley General y de esta Ley y demás disposiciones aplicables con excepción de lo relativo a derechos de propiedad industrial que sean confidenciales conforme a la ley, debiendo la autoridad mantener absoluta reserva si así lo solicita el interesado, salvo caso de requerimiento judicial.\nARTÍCULO 180- La autoridad competente podrá solicitar el auxilio de la fuerza pública para efectuar la visita de inspección, cuando alguna o algunas personas obstaculicen o se opongan a la práctica de la diligencia, independientemente de las sanciones a que haya lugar.\nARTÍCULO 181.- De toda visita de inspección se levantará acta, en la que se harán constar en forma circunstanciada los hechos u omisiones, que se hubiesen detectado durante la diligencia, así como los elementos constitutivos de la intencionalidad o negligencia de los mismos.\nConcluida la inspección, se dará oportunidad a la persona con la que se entendió la diligencia para que en el mismo acto formule sus observaciones con relación a los hechos u omisiones, así como los elementos constitutivos de la intencionalidad o negligencia, hábiles siguientes a la fecha en que se haya practicado la diligencia. diligencia, por los testigos y el personal autorizado, quien entregará copia del acta al interesado. acta, o se negare el interesado a aceptar copia de la misma, dichas circunstancias se asentarán en ella, sin que esto afecte su validez.\nLey de Protección al Ambiente para el Estado de Baja California. Página 80\nARTÍCULO 182.- Recibida el acta de inspección por la autoridad ordenadora y una vez transcurrido el plazo a que se refiere el segundo párrafo del artículo anterior, dentro de motivado, para que la persona interesada implemente de inmediato las medidas correctivas necesarias para cumplir con las disposiciones jurídicas aplicables, así como con los permisos, licencias, autorizaciones o concesiones respectivas, señalando los plazos que corresponda para su cumplimiento, procediendo a su notificación para que en el término de diez días hábiles manifieste lo que a su derecho convenga.\nArtículo Reformado\nARTÍCULO 183.- Transcurrido el término a que se refiere el artículo anterior y dentro de los veinte días hábiles siguientes, la autoridad emitirá la resolución administrativa correspondiente, debidamente fundada y motivada, misma que se notificará al interesado, y en la cual se señalarán o en su caso ratificarán o adicionarán, las medidas que deberán llevarse a cabo para corregir las deficiencias o irregularidades observadas, el plazo otorgado al infractor para subsanarlas y las sanciones a que se hubiere hecho acreedor conforme a las disposiciones aplicables.\nARTÍCULO 184.- Dentro de los cinco días hábiles siguientes al vencimiento del plazo otorgado al infractor para subsanar las deficiencias e irregularidades observadas, éste deberá comunicar por escrito y en forma detallada a la autoridad ordenadora, haber dado cumplimiento a las medidas ordenadas en los términos del requerimiento o resolución respectiva.\nCAPÍTULO II\nMedidas de seguridad\nARTÍCULO 185.- De existir riesgo inminente de desequilibrio ecológico o casos de contaminación con repercusiones peligrosas para los ecosistemas, sus componentes o para la salud pública, la autoridad competente, fundada y motivadamente, podrá ordenar alguna o algunas de las siguientes medidas de seguridad sin necesidad de cumplir con los plazos a que se refiere el capítulo anterior:\nI. La neutralización o cualquier acción análoga que impida que las sustancias contaminantes generen los afectos previstos en el primer párrafo de este artículo;\nII. El aseguramiento precautorio de bienes, equipo, maquinaria, vehículos, imposición de las medidas de seguridad; y,\nFracción Reformada\nIII. La clausura temporal, parcial o total, de las fuentes contaminantes, así como de supuestos a que se refiere el primer párrafo de este artículo;\nLey de Protección al Ambiente para el Estado de Baja California. Página 81 las acciones anteriores.\nArtículo Reformado\nARTÍCULO 186.- Cuando la autoridad ordene alguna de las medidas de seguridad previstas en esta Ley, indicará al interesado, cuando proceda, las acciones que debe llevar a cabo para subsanar las irregularidades que motivaron la imposición de dichas medidas, así como los plazos para su realización, a fin de que una vez cumplidas éstas, se ordene el retiro de la medida de seguridad impuesta.\nCAPÍTULO III\nSanciones administrativas\nARTÍCULO 187.- Las violaciones a los preceptos de la Ley General, esta Ley, sus reglamentos, normas oficiales mexicanas, normas ambientales estatales y demás disposiciones aplicables, serán sancionadas administrativamente por la autoridad, con una o más de las siguientes sanciones: Reforma\nI. Amonestación;\nII. Multa por el equivalente de doscientas a veinte mil unidades de medida y actualización vigente al momento de imponer la sanción;\nFracción Reformada\nLas multas aplicables, serán determinadas en un tabulador de multas, de conformidad con las disposiciones previstas en el reglamento correspondiente;\nIII. Clausura temporal o definitiva, parcial o total, cuando se incurra en cualquiera de los siguientes casos:\na) Cuando el infractor no hubiere cumplido en los plazos y condiciones impuestos por la autoridad, con las medidas correctivas, de urgente aplicación o de seguridad ordenadas;\nb) En los casos de reincidencia cuando las infracciones generen efectos negativos al ambiente.\nIV. Reparar el daño causado, en los siguientes términos:\na).- Restaurar el área afectada;\nb).- Llevar a cabo las acciones de compensación que se requieran a efecto de que se restituya un área equivalente a la afectada, en el sitio más próximo posible a ésta, y\nc).- En caso de que el daño realizado sea irreparable, el responsable deberá pagar una compensación económica que deberá destinarse al fondo ambiental correspondiente.\nLey de Protección al Ambiente para el Estado de Baja California. Página 82 previstas en el reglamento respectivo.\nV. Reparar daños físicamente causados al medio ambiente en agua, aire o suelo dentro y fuera de su empresa, independientemente de las sanciones de los delitos contra el medio ambiente;\nFracción Reformada\nVI. Arresto administrativo hasta por treinta y seis horas; y,\nVII. Suspensión o revocación de las autorizaciones, permisos, licencias, cédulas, registros o resoluciones correspondientes.\nFracción Adicionada\nArtículo Reformado\nARTÍCULO 188.- Para la imposición de las sanciones por infracciones a esta ley, se tomará en cuenta:\nI. La gravedad de la infracción, considerando los siguientes criterios: impacto a la salud pública, generación de desequilibrios ecológicos, impacto al ambiente y los niveles en que se hubieran rebasado los límites establecidos en las normas oficiales mexicanas y las normas ambientales estatales;\nII. Las condiciones económicas del infractor.\nARTÍCULO 189.- Cuando se trate de segunda o posterior inspección para verificar el cumplimiento de un requerimiento o requerimientos anteriores y del acta correspondiente se desprenda que no se ha dado cumplimiento a las medidas previamente ordenadas, la autoridad competente podrá imponer además de la sanción o sanciones que procedan conforme al presente capítulo, una multa adicional que no exceda de los límites máximos señalados.\nPara el caso de reincidencia, la sanción podrá ser hasta por dos veces el monto de la multa inicialmente impuesta, sin exceder del doble del máximo permitido, así como la clausura definitiva. impliquen infracciones a un mismo precepto, en un período de dos años, contados a partir de la fecha en que se levante el acta en que se hizo constar la primera infracción, siempre que esta no hubiese sido desvirtuada.\nARTÍCULO 190.- En el caso en que el infractor realice las medidas correctivas o las de urgente aplicación, o subsane las irregularidades en que hubiere incurrido, previamente a\nLey de Protección al Ambiente para el Estado de Baja California. Página 83 de medidas correctivas o de urgente aplicación, la autoridad podrá considerar tal situación como atenuante de la infracción cometida.\nAl dictar la resolución que ponga fin al procedimiento de inspección y vigilancia, o al resolver sobre el recurso correspondiente interpuesto, y siempre que el particular lo solicite dentro del plazo a que se refiere el párrafo anterior, la autoridad podrá, fundando y motivando su resolución, otorgar al infractor la opción para pagar la multa o realizar inversiones equivalentes en adquisición, instalación de equipo o tecnología de protección ambiental, siempre y cuando ésta no tenga relación directa con el motivo de la sanción o sus obligaciones de ley y se garanticen las obligaciones del infractor y no se trate de riesgo inminente de desequilibrio ecológico, o de casos de contaminación con repercusiones peligrosas al ambiente.\nARTÍCULO 191.- Cuando proceda como sanción la clausura temporal o definitiva, total o parcial, el personal comisionado para ejecutarla, procederá a levantar acta circunstanciada de la diligencia.\nEn los casos en que se imponga como sanción la clausura temporal, la autoridad ambiental deberá indicar al infractor las medidas correctivas y las acciones que deba llevar a cabo para subsanar las irregularidades que motivaron dicha sanción, así como los plazos para su realización.\nARTÍCULO 191 BIS.- La Secretaría y los Municipios podrán revocar las autorizaciones, permisos, licencias, cédulas o resoluciones, que haya emitido en los siguientes casos:\nI.- Cuando la autorización, permiso o licencia se hubiera otorgado considerando información falsa proporcionada por el autorizado;\nII.- Cuando una vez emitida la autorización, licencia o permiso surjan causas supervenientes que modifiquen significativamente las condiciones ambientales bajo las cuales fueron otorgadas;\nFracción Reformada\nIII.- Cuando el autorizado no haya iniciado actividades en el término de un año, a partir de la fecha en que le fue notificada la autorización, licencia o permiso;\nFracción Reformada\nIV.- Cuando se incumpla con las condicionantes establecidas por esta la autoridad competente, en los plazos que le fueron establecidos; y,\nFracción Adicionada\nV.- Por las violaciones a los preceptos de esta Ley, sus reglamentos y las disposiciones que de ella emanen, previo dictamen de la autoridad en inspección y vigilancia.\nFracción Adicionada\nLey de Protección al Ambiente para el Estado de Baja California. Página 84\nAntes de emitir fundada y motivadamente la resolución respectiva, la Secretaría dará vista a la persona interesada.\nPárrafo Reformado\nArtículo Reformado\nCAPÍTULO IV\nDel Recurso Administrativo\nARTÍCULO 192.- Las resoluciones dictadas por autoridades Estatales ambientales en los procedimientos administrativos con motivo de la aplicación de la Ley General, esta ley, sus reglamentos y disposiciones que de ellas emanen, podrán ser impugnadas por los afectados, a través del recurso de revocación previsto en la Ley del Procedimiento para los\nActos de la Administración Pública del Estado de Baja California, y tratándose de las dictadas por los Municipios mediante el recurso de revisión con base en las reglas establecidas en la presente Ley, dentro de los quince días hábiles siguientes a la fecha de su notificación.\nARTÍCULO 193.- El escrito de interposición del recurso de revisión deberá expresar lo siguiente:\nI. El nombre del recurrente y del tercero perjudicado si lo hubiere, así como el lugar que señale para efectos de notificaciones. En caso de no señalar domicilio, las notificaciones que deban hacerse al promovente, se fijarán en sitio visible del local de las oficinas de la autoridad ambiental que hubiere emitido el acto recurrido, aún las de carácter personal;\nII. El acto que se recurre y fecha en que se le notificó o tuvo conocimiento del mismo;\nIII. Los conceptos de impugnación, entendidos como los razonamientos que haga valer el impugnante, en los que señalará la parte de la resolución que le cause perjuicio y su relación con los preceptos de la presente Ley, la Ley General, sus reglamentos, normas oficiales mexicanas, normas ambientales estatales y demás disposiciones que de ellas emanen, con lo cual pretenda demostrar la ilegalidad del acto que controvierte;\nIV. Copia de la resolución que se impugna y de la notificación correspondiente, exhibiendo dicho documento como justificativo del recurso. Tratándose de actos que por no haberse resuelto en tiempo se entiendan negados, deberá acompañarse el escrito de alguna;\nV. La mención de la autoridad que haya dictado la resolución u ordenado el acto;\nVI. Las pruebas que ofrezca que tengan relación inmediata y directa con la resolución o acto impugnado, señalando el objeto de la prueba, debiendo acompañar las documentales con que cuente, incluidas las que acrediten su personalidad cuando actúen en\nLey de Protección al Ambiente para el Estado de Baja California. Página 85 nombre de otro o de personas morales. Quedan exceptuadas la confesión de autoridades, al derecho; y\nVII. En su caso, el recurrente podrá autorizar a las personas que considere para que a su nombre reciban notificaciones, quienes además, una vez autorizadas, podrán hacer las promociones de trámite respectivas.\nARTÍCULO 194.- Las pruebas deberán ser ofrecidas relacionándolas con cada uno de los puntos controvertidos; de no hacerse dicha relación en forma precisa, estas serán desechadas de plano.\nARTÍCULO 195.- Cuando con la interposición del recurso de revisión, el promovente solicite la suspensión del acto recurrido, la autoridad revisora podrá ordenar la suspensión, siempre y cuando:\nI. Sea procedente el recurso;\nII. No se siga perjuicio al interés social o se contravengan disposiciones de orden público;\nIII. No se ocasionen daños o perjuicios a terceros, a menos que se garanticen estos para el caso de no obtener resolución favorable; y\nIV. Tratándose de multas, el recurrente garantice el interés fiscal.\nARTÍCULO 196.- El recurso de revisión se tendrá por no interpuesto y se desechará cuando:\nI. Se presente fuera de plazo;\nII. No acredite la personalidad del recurrente;\nIII. No aparezca suscrito por quien deba hacerlo, a menos que se firme antes del vencimiento del plazo para interponerlo; y\nIV. No se exhiba copia de la resolución recurrida.\nARTÍCULO 197.- El recurso de revisión es improcedente:\nI. Contra actos que no afecten los intereses jurídicos del promovente;\nII. Contra actos consumados de modo irreparable; y\nLey de Protección al Ambiente para el Estado de Baja California. Página 86\nIII. Contra actos consentidos expresamente.\nARTÍCULO 198.- Procede el sobreseimiento del recurso de revisión:\nI. Cuando el promovente se desista expresamente del recurso;\nII. Cuando durante el procedimiento sobrevenga alguna de las causas de improcedencia a que se refiere el artículo anterior; y\nIII. Cuando hayan cesado los efectos del acto recurrido.\nARTÍCULO 199.- La autoridad revisora al resolver el recurso podrá:\nI. Desecharlo por improcedente o sobreseerlo;\nII. Confirmar el acto impugnado; o\nIII. Modificar u ordenar la modificación del acto impugnado o dictar u ordenar expedir uno nuevo que lo sustituya, cuando el recurso interpuesto sea total o parcialmente resulto a favor del recurrente.\nARTÍCULO 200.- La resolución del recurso se fundará en derecho y examinará todos y cada uno de los razonamientos lógico jurídicos hechos valer por el recurrente, teniendo la autoridad revisora la facultad de invocar hechos notorios. Cuando uno de éstos sea suficiente para desvirtuar la validez del acto impugnado bastará con el examen de dicho punto.\nLa autoridad revisora, en beneficio del recurrente, podrá corregir los errores que advierta en la cita de los preceptos que se consideren violados y examinar en su conjunto los razonamientos expuestos por el recurrente, a fin de resolver la cuestión planteada, pero sin cambiar los hechos expuestos en el recurso. reposición del procedimiento, la autoridad que haya emitido la resolución impugnada deberá cumplimentarla en un plazo que no exceda de dos meses.\nARTÍCULO 201.- La oposición a los actos de trámite en un procedimiento administrativo deberá alegarse con los interesados durante dicho procedimiento, para su consideración, en la resolución que resuelva sobre el mismo.\nLa falta de oposición durante el procedimiento a tales actos de trámite, dará como consecuencia que sea innecesario su estudio por parte de la autoridad revisora, en caso de que se expresen en los conceptos de impugnación.\nLey de Protección al Ambiente para el Estado de Baja California. Página 87\nARTÍCULO 202.- La resolución que resuelva respecto del recurso de revisión interpuesto deberá notificarse al afectado, bien sea en lo personal o por conducto de su representante o apoderado legal, debiendo asentar razón en la cédula correspondiente.\nCuando el recurrente no señale domicilio para oír y recibir notificaciones, ésta deberá hacerse al promovente, fijándola en sitio visible del local de las oficinas de la autoridad revisora, así como en las oficinas de la autoridad que emitió la resolución impugnada, en una lista expresando solamente el nombre y apellido del interesado y asentando tal circunstancia en los autos del mismo.\nARTÍCULO 203.- Tratándose de obras o actividades que contravengan las disposiciones de esta Ley, los programas de ordenamiento ecológico, las declaratorias de áreas naturales protegidas o los reglamentos, las normas oficiales mexicanas o las normas ambientales estatales, las personas físicas y morales de las comunidades afectadas, tendrán derecho a impugnar los actos administrativos correspondientes, siempre que demuestren en el procedimiento que dichas obras o actividades originen o puedan originar un daño a los recursos naturales, el ambiente o salud pública. Para tal efecto, deberán interponer el recurso administrativo de revisión a que se refiere este capítulo.\nARTÍCULO 204.- En caso de que se expidan licencias, permisos, autorizaciones o concesiones contraviniendo esta Ley, serán nulas y no producirán efecto legal alguno. Dicha nulidad podrá ser exigida por medio del recurso a que se refiere el presente capítulo.\nTÍTULO QUINTO\nPARTICIPACIÓN CIUDADANA\nCAPÍTULO V\n“DE LAS REGLAS DE LAS NOTIFICACIONES”\nCapítulo Adicionado\nARTÍCULO 204 BIS.- Las notificaciones de los actos administrativos dictados con motivo de la aplicación de esta Ley, se realizarán:\nI.- Personalmente o por correo certificado con acuse de recibo, cuando se trate de emplazamientos, resoluciones administrativas y de conclusión; sin perjuicio de que la de la Secretaría, si las personas a quienes deba notificarse se presentan en las mismas y siempre que consienta recibirlas. En este último caso, se asentará la razón correspondiente.\nII.- Por estrados, colocados en las unidades administrativas del Municipio que corresponda, cuando la persona a quien deba notificarse no pueda ser ubicada después de iniciadas las facultades de inspección, vigilancia o verificación a las que se refiere el ubicada la autoridad ordenadora, así como los demás casos contemplados en la Ley del\nProcedimiento para los Actos de la Administración Pública del Estado de Baja California; y\nLey de Protección al Ambiente para el Estado de Baja California. Página 88\nIII.- Por edictos, cuando se desconozca el domicilio del interesado o, en su caso, cuando la persona a quien deba notificarse haya desaparecido, se trate de personas inciertas, se ignore su domicilio o se encuentre en el extranjero sin haber dejado representante legal o autorizado para tales efectos.\nTratándose de actos distintos a los señalados en la fracción I de este artículo, las notificaciones podrán realizarse por correo ordinario, mensajería, telegrama o previa solicitud por escrito del interesado, a través de telefax, medios de comunicación electrónica u otro similar o en las oficinas de las unidades administrativas, a más tardar dentro del término de cinco días hábiles siguientes contados a partir del día en que se dicten los actos que han de notificarse. Lo anterior, sin perjuicio de que la autoridad ordenadora lo haga por estrados, dentro del término de diez días hábiles contados a partir del día en que se dicten los actos que han de notificarse, el cual se fijará en lugar visible de las oficinas de las Unidades\nAdministrativas de la Secretaría.\nSi los interesados, sus representantes legales o las personas autorizadas por ellos, no ocurren a las oficinas de las unidades administrativas de la Secretaría, a notificarse dentro del término señalado en el párrafo anterior, las notificaciones se tendrán por hechas y surtirán sus efectos al día siguiente al de su fijación en los estrados de las oficinas de la\nSecretaría.\nDe toda notificación por estrados, se agregará al expediente un tanto de aquél, asentándose la razón correspondiente.\nIV.- Por instructivo, solamente en el caso previsto en el cuarto párrafo del artículo 204 bis 1 de la presente Ley.\nArtículo Adicionado\nARTÍCULO 204 BIS 1.- Las notificaciones personales se harán en el domicilio del interesado o en el último domicilio que la persona a quien se deba notificar haya señalado en la población donde se encuentre la unidad administrativa de la Secretaría, o bien, personalmente en el recinto oficial de ésta, cuando comparezcan voluntariamente a recibirlas.\nEn los dos primeros casos, el notificador deberá cerciorarse que se trata del domicilio del interesado o del designado para esos efectos y deberá entregar el original del acto que se notifique y copia de la constancia de notificación respectiva; así como, señalar la fecha y hora en que la notificación se efectúa, recabando el nombre y firma de la persona con quien se entienda la diligencia. Si ésta se niega, se hará constar en el acta de notificación, sin que ello afecte su validez.\nLas notificaciones personales, se entenderán con la persona que deba ser notificada, o su representante legal; a falta de ambos, el notificador dejará citatorio con cualquier persona que se encuentre en el domicilio, para que el interesado espere a una hora fija del día hábil siguiente. Si el domicilio se encontrare cerrado, el citatorio se dejará en un lugar visible del mismo o con el vecino más inmediato.\nLey de Protección al Ambiente para el Estado de Baja California. Página 89\nSi la persona a que haya de notificarse no atendiere el citatorio, la notificación se diligencia y, de negarse esta a recibirla o en su caso, de encontrarse cerrado el domicilio, se realizará por instructivo que se fijará en un lugar visible del domicilio, o con el vecino más cercano, lo que se hará constar en el acta de notificación, sin que ello afecte su validez.\nTratándose de las facultades de inspección y vigilancia, la Secretaría se encuentra facultada para proceder a efectuar la visita correspondiente, sin previo citatorio al interesado.\nDe las diligencias en que conste la notificación, el notificador tomará razón por escrito.\nArtículo Adicionado\nARTÍCULO 204 BIS 2.- Las notificaciones por edictos se realizarán haciendo publicaciones que contendrán un resumen de los actos por notificar. Dichas publicaciones deberán efectuarse por dos días consecutivos en el Periódico Oficial del\nEstado y en uno de los periódicos o diarios de mayor circulación en el Estado.\nArtículo Adicionado\nARTÍCULO 204 BIS 3.- Las notificaciones personales surtirán sus efectos el día en que hubieren sido realizadas. Los plazos empezarán a correr a partir del día hábil siguiente a aquel en que haya surtido efectos la notificación.\nSe tendrá como fecha de notificación por correo certificado, la que conste en el acuse de recibo.\nEn las notificaciones por edictos se tendrá como fecha de notificación la de la última publicación en el Periódico Oficial del Estado y en los periódicos o diarios de mayor circulación del Estado.\nLas notificaciones por estrados surtirán sus efectos al día siguiente al de la fijación del mismo en las oficinas de la unidad administrativa de la Secretaría.\nArtículo Adicionado\nARTÍCULO 204 BIS 4.- Toda notificación deberá efectuarse en un plazo máximo de quince días hábiles, contados a partir de la emisión de la resolución o acto que se notifique, y deberá contener el texto íntegro del acto, así como el fundamento legal en que se apoye con la indicación de si es o no definitivo en la vía administrativa, y en su caso, la expresión del recurso administrativo que contra la misma proceda, órgano ante el cual hubiera de presentarse y plazo para su interposición.\nArtículo Adicionado\nCAPÍTULO VI\nDe los delitos ambientales\nLey de Protección al Ambiente para el Estado de Baja California. Página 90\nARTÍCULO 205.- En aquellos casos en que, como resultado del ejercicio de sus atribuciones, la autoridad ambiental tenga conocimiento de actos u omisiones que pudieran constituir delitos conforme a lo previsto en la legislación penal aplicable, formulará ante el\nMinisterio Público la denuncia correspondiente. a los delitos ambientales previstos en el Código Penal vigente en el estado.\nARTÍCULO 206.- La autoridad ambiental proporcionará, en las materias de su competencia, los dictámenes técnicos o periciales que le soliciten el Ministerio Público o las autoridades judiciales, con motivo de las denuncias presentadas por la comisión de delitos en contra del ambiente.\nIgualmente, la autoridad ambiental proporcionará los dictámenes técnicos o periciales que le soliciten, con motivo de los juicios contencioso administrativos que se ventilen ante dicho tribunal.\nCAPÍTULO VII\nResponsabilidad por el daño ambiental\nARTÍCULO 207.- Sin perjuicio de las sanciones penales o administrativas que procedan, toda persona que contamine, deteriore el ambiente, o afecte los recursos naturales de competencia estatal o municipal, será responsable y estará obligada a reparar los daños causados, de conformidad con la legislación civil aplicable.\nEl término para demandar la responsabilidad ambiental, será de cinco años contados a partir del momento en que se tenga conocimiento del hecho, acto u omisión correspondiente.\nARTÍCULO 208.- Cuando por infracción a las disposiciones de la Ley General, esta\nLey y sus disposiciones reglamentarias se ocasionen daños o perjuicios, los interesados podrán solicitar a la autoridad ambiental, la formulación de un dictamen técnico al respecto, el cual tendrá el valor de medio de convicción, en caso de que éste se presente en juicio.\nTRANSITORIOS:\nARTÍCULO PRIMERO: La presente Ley entrará en vigor al día siguiente de su publicación en el Periódico Oficial del estado de Baja California.\nARTÍCULO SEGUNDO: Se abroga la Ley del Equilibrio Ecológico y Protección al\nAmbiente del Estado de Baja California, publicada en el Periódico Oficial del Estado de Baja que se opongan a la presente Ley.\nLey de Protección al Ambiente para el Estado de Baja California. Página 91\nARTÍCULO TERCERO: Hasta en tanto se expidan las disposiciones reglamentarias de esta ley, seguirán en vigor las que han regido hasta ahora, en lo que no la contravenga.\nAmbiente del Estado de Baja California se entienden hechas en lo aplicable, a la presenta ley.\nARTÍCULO CUARTO: Los procedimientos y recursos administrativos relacionados con la materia de esta Ley, que se hubieren iniciado bajo la vigencia de la Ley del Equilibrio\nEcológico y Protección al Ambiente del Estado de Baja California, se tramitarán y resolverán conforme a las disposiciones de dicha ley que se abroga.\nARTÍCULO QUINTO: Los municipios deberán adecuar sus reglamentos, ordenanzas, bandos de policía y gobierno, y demás disposiciones derivadas de la presente Ley, debiéndolos expedir dentro de los trescientos sesenta y cinco días naturales siguientes a la entrada en vigor de este ordenamiento.\nEn el caso de los municipios que no cuenten con disposiciones reglamentarias a que se refiere el párrafo anterior ni con la unidad de gestión ambiental a través de la cual presten los servicios administrativos y técnicos ambientales, la Secretaría aplicará temporalmente las disposiciones que en la materia les correspondan.\nArtículo Reformado\nARTÍCULO SEXTO: Hasta en tanto se expidan sus reformas, seguirán aplicándose los Planes vigentes en el Estado de Baja California, publicados en el Periódico Oficial del\nGobierno del Estado de fecha 8 de septiembre de 1995.\nARTÍCULO SÉPTIMO.- Las bases de estos planes y programas a que se refiere el artículo 25 de la presente Ley, se establecerán en el programa de ordenamiento ecológico de acuerdo con los plazos y formas que se establezcan en el reglamento respectivo, pero su elaboración y puesta en vigor no podrá exceder de 360 días naturales.\nARTÍCULO OCTAVO: En lo relativo a la regulación, vigilancia y sanciones de descargas de aguas residuales a los sistemas de alcantarillado sanitario pasarán a formar parte de las funciones del área ecológica municipal, una vez que forme parte de la administración pública municipal, el organismo operador de dichos sistemas.\nARTÍCULO NOVENO: Los reglamentos de esta Ley deberán ser expedidas dentro de los doscientos diez días hábiles siguientes a la entrada en vigor de este ordenamiento.\nARTÍCULO DÉCIMO: Hasta en tanto no se decrete la creación de la Secretaría, la\nDirección General de Ecología, continuará aplicando la presente Ley.\nARTÍCULO DÉCIMO PRIMERO: El Consejo emitirá la convocatoria para constituir el\nConsejo Consultivo, a más tardar ciento veinte días naturales después de que entre en vigor la presente Ley.\nLey de Protección al Ambiente para el Estado de Baja California. Página 92\nARTICULO DECIMO SEGUNDO: Hasta en tanto no se integre el Consejo Estatal de\nProtección al Ambiente, seguirá en funciones el Consejo Estatal de Ecología.\nARTICULO DECIMO TERCERO: Las dependencias y entidades de la Administración disposiciones se relacionen con el objeto de la presente Ley, ajustarán su ejercicio a los criterios que para preservar el equilibrio ecológico, aprovechar sustentablemente los recursos naturales y proteger el ambiente, se incluyen en ella, así como las disposiciones de los reglamentos, normas ambientales y programas de ordenamiento ecológico y demás normatividad que de la misma se derive.\nDADO en la Sala de Sesiones “Lic. Benito Juárez García” del H. Poder Legislativo, en la Ciudad de Mexicali, Baja California, a los veintisiete días del mes de septiembre del año dos mil uno.\nDIP. SERGIO GOMEZ MORA\nPRESIDENTE\n(RÚBRICA)\nDIP. GILBERTO FLORES MUÑOZ\nSECRETARIO\n(RÚBRICA)\nDE CONFORMIDAD CON LO DISPUESTO POR LA FRACCION I DEL ARTICULO\n49 DE LA CONSTITUCION POLITICA DEL ESTADO, MANDO SE IMPRIMA Y PUBLIQUE.\nMEXICALI, BAJA CALIFORNIA, A LOS DIECISEIS DIAS DEL MES DE NOVIEMBRE\nDEL AÑO DOS MIL UNO.\nEL GOBERNADOR DEL ESTADO\nEUGENIO ELORDUY WALTHER\n(RÚBRICA)\nEL SECRETARIO GENERAL DE GOBIERNO\nBERNARDO BORBON VILCHES\n(RÚBRICA)\nLey de Protección al Ambiente para el Estado de Baja California. Página 93\nARTICULO QUINTO.- Fue reformado por Decreto No. 63, publicado en el Periódico\nConstitucional, siendo Gobernador del Estado el C. Lic. Eugenio Elorduy Walther, 20012007;\nARTÍCULO 1.- Fue reformado por Decreto No. 339, publicado en el Periódico Oficial\nNo. 01, de fecha 14 de enero de 2010, Tomo CXVII, expedido por la Honorable XIX\nLegislatura Constitucional, siendo Gobernador del Estado el C. Lic. José Guadalupe Osuna\nMillán, 2007-2013; fue reformado por Decreto No. 445, publicado en el Periódico Oficial No.\n45, de fecha 22 de octubre de 2010, Tomo CXVII, Sección I, expedido por la H. XIX\nLegislatura, siendo Gobernador Constitucional el C. José Guadalupe Osuna Millán 20072013; fue reformado mediante Decreto No. 318, publicado en el Periódico Oficial No. 48, de fecha 26 de octubre de 2012, Tomo CXIX, expedido por la H. XX Legislatura, siendo\nGobernador Constitucional el C. José Guadalupe Osuna Millán 2007-20013;\nARTÍCULO 2.- Fue reformado por Decreto No. 339, publicado en el Periódico Oficial\nNo. 01, de fecha 14 de enero de 2010, Tomo CXVII, expedido por la Honorable XIX\nLegislatura Constitucional, siendo Gobernador del Estado el C. Lic. José Guadalupe Osuna\nMillán, 2007-2013; Fue reformado por Decreto No. 341, publicado en el Periódico Oficial No.\n2, de fecha 05 de enero de 2010, expedido por la Honorable XIX Legislatura, siendo\nGobernador Constitucional el C. José Guadalupe Osuna Millan 2007-2013; fue reformado por Decreto No. 445, publicado en el Periódico Oficial No. 45, de fecha 22 de octubre de\n2010, Tomo CXVII, Sección I, expedido por la H. XIX Legislatura, siendo Gobernador\nConstitucional el C. José Guadalupe Osuna Millán 2007-2013; fue reformado por Decreto\nNo. 510, publicado en el Periódico Oficial No. 39, de fecha 06 de septiembre de 2013, Tomo\nCXX, expedido por la H. XIX Legislatura, siendo Gobernador Constitucional el C. José\nGuadalupe Osuna Millán 2007-2013; fue reformado por Decreto No. 66, publicado en el\nPeriódico Oficial No. 39, Sección II, de fecha 01 de agosto de 2014, Tomo CXXI, expedido por la H. XXI Legislatura, siendo Gobernador Constitucional el C. Francisco Arturo Vega de\nLamadrid 2013-2019; fue reformado por Decreto No. 67, publicado en el Periódico Oficial\nNo. 39, Sección II, de fecha 01 de agosto de 2014, Tomo CXXI, expedido por la H. XXI\nLegislatura, siendo Gobernador Constitucional el C. Francisco Arturo Vega de Lamadrid\n2013-2019; fue reformado por Decreto No. 172, publicado en el Periódico Oficial No. 10, Índice, de fecha 12 de febrero de 2021, Tomo CXXVIII, expedido por la H. XXIII Legislatura, siendo Gobernador Constitucional el C. Jaime Bonilla Valdez 2019-2021; fue reformado por\nDecreto No. 129, publicado en el Periódico Oficial No. 56, Sección III, de fecha 19 de\nConstitucional la C. Marina del Pilar Ávila Olmeda 2021-2027;\nARTÍCULO 3.- Fue reformado por Decreto No. 445, publicado en el Periódico Oficial\nLegislatura, siendo Gobernador Constitucional el C. José Guadalupe Osuna Millán 20072013; fue reformado mediante Decreto No. 491, publicado en el Periódico Oficial No. 34, de siendo Gobernador Constitucional el C. José Guadalupe Osuna Millán 2007-20013;\nLey de Protección al Ambiente para el Estado de Baja California. Página 94\nARTÍCULO 6.- Fue reformado por Decreto No. 333, publicado en el Periódico Oficial\nLegislatura, siendo Gobernadora Constitucional la C. Marina del Pilar Ávila Olmeda 20212027;\nARTÍCULO 7.- Fue reformado por Decreto No. 333, publicado en el Periódico Oficial\nNo. 70, Sección I, de fecha 08 de diciembre de 2023, Tomo CXXX, expedido por la H. XXIV\nLegislatura, siendo Gobernadora Constitucional la C. Marina del Pilar Ávila Olmeda 20212027;\nARTÍCULO 8.- Fue reformado por Decreto No. 339, publicado en el Periódico Oficial\nNo. 01, de fecha 14 de enero de 2010, Tomo CXVII, expedido por la Honorable XIX\nLegislatura Constitucional, siendo Gobernador del Estado el C. Lic. José Guadalupe Osuna\nMillán, 2007-2013; Fue reformado por Decreto No. 341, publicado en el Periódico Oficial No.\n2, de fecha 05 de enero de 2010, expedido por la Honorable XIX Legislatura, siendo\nGobernador Constitucional el C. José Guadalupe Osuna Millan 2007-2013; fue reformado por Decreto No. 445, publicado en el Periódico Oficial No. 45, de fecha 22 de octubre de\n2010, Tomo CXVII, Sección I, expedido por la H. XIX Legislatura, siendo Gobernador\nConstitucional el C. José Guadalupe Osuna Millán 2007-2013; fue reformado mediante\nDecreto No. 436, publicado en el Periódico Oficial No. 18, de fecha 12 de abril de 2013,\nSección II, Tomo CXX, expedido por la H. XX Legislatura, siendo Gobernador Constitucional el C. José Guadalupe Osuna Millán 2007-20013; fue reformado por Decreto No. 276, publicado en el Periódico Oficial No. 10, Sección III, Tomo CXXVI, de fecha 22 de febrero de\n2019, expedido por la H. XXII Legislatura, siendo Gobernador Constitucional el C. Francisco\nArturo Vega de Lamadrid 20013-2016; fue reformado por Decreto No. 333, publicado en el\nPeriódico Oficial No. 70, Sección I, de fecha 08 de diciembre de 2023, Tomo CXXX, expedido por la H. XXIV Legislatura, siendo Gobernadora Constitucional la C. Marina del\nPilar Ávila Olmeda 2021-2027; fue reformado por Decreto No. 453, publicado en el Periódico\nOficial No. 40, Índice, de fecha 16 de agosto de 2024, Tomo CXXXI, expedido por la H. XXIV\nLegislatura, siendo Gobernadora Constitucional la C. Marina del Pilar Ávila Olmeda 20212027;\nARTÍCULO 9.- Fue reformado por Decreto No. 66, publicado en el Periódico Oficial\nNo. 39, Sección II, de fecha 01 de agosto de 2014, Tomo CXXI, expedido por la H. XXI\nLegislatura, siendo Gobernador Constitucional el C. Francisco Arturo Vega de Lamadrid\n2013-2019; fue reformado por Decreto No. 129, publicado en el Periódico Oficial No. 56, Legislatura, siendo Gobernadora Constitucional la C. Marina del Pilar Ávila Olmeda 20212027; fue reformado por Decreto No. 456, publicado en el Periódico Oficial No. 40, Índice, de\nGobernadora Constitucional la C. Marina del Pilar Ávila Olmeda 2021-2027;\nARTÍCULO 10.- Fue reformado mediante Decreto No. 318, publicado en el Periódico\nLegislatura, siendo Gobernador Constitucional el C. José Guadalupe Osuna Millán 2007Ley de Protección al Ambiente para el Estado de Baja California. Página 95\n20013; fue reformado por Decreto No. 66, publicado en el Periódico Oficial No. 39, Sección\nGobernador Constitucional el C. Francisco Arturo Vega de Lamadrid 2013-2019;\nARTÍCULO 15.- Fue reformado por Decreto No. 383, Publicado en el Periódico Oficial\nGobernador Constitucional el C. José Guadalupe Osuna Millán 2007-20013;\nARTÍCULO 15 BIS.- Fue adicionado mediante Decreto No. 328, publicado en el\nPeriódico Oficial No. 47, Tomo CXXII, Sección II, de fecha 09 de octubre de 2015, expedido por la H. XXI Legislatura, siendo Gobernador Constitucional el C. Francisco Arturo Vega de\nLamadrid 2013-2019.\nARTÍCULO 18.- Fue reformado por Decreto No. 145, publicado en el Periódico Oficial\nNo. 56, Sección I, de fecha 14 de noviembre de 2008, Tomo CXV, expedido por la H. XIX\nLegislatura, siendo Gobernador Constitucional del Estado, el C. Lic. José Guadalupe Osuna\nMillán, 2007-2013; fue reformado mediante Decreto No. 398, publicado en el Periódico\nOficial No. 4, de fecha 18 de enero de 2013, Tomo CXX, expedido por la H. XX Legislatura, siendo Gobernador Constitucional el C. José Guadalupe Osuna Millán 2007-20013; fue reformado por Decreto No. 333, publicado en el Periódico Oficial No. 70, Sección I, de fecha\n08 de diciembre de 2023, Tomo CXXX, expedido por la H. XXIV Legislatura, siendo\nGobernadora Constitucional la C. Marina del Pilar Ávila Olmeda 2021-2027;\nARTÍCULO 19.- Fue adicionado mediante Decreto No. 150, publicado en el Periódico\nOficial No. 50, Tomo CXXIV, Sección III, de fecha 10 de noviembre de 2017, expedido por la\nH. XXII Legislatura, siendo Gobernador Constitucional el C. Francisco Arturo Vega de\nLamadrid 2013-2019.\nARTÍCULO 25.- Fue derogado mediante Decreto No. 60, publicado en el Periódico\nOficial No. 30, Tomo CXV, de fecha 27 de junio de 2008, expedido por la H. XIX Legislatura, siendo Gobernador Constitucional el C. José Guadalupe Osuna Millán 2007-2013.\nARTÍCULO 27.- Fue reformado por Decreto No. 458, publicado en el Periódico Oficial\nNo. 14, Sección V, Tomo CXXIII, de fecha 18 de marzo de 2016, expedido por la H. XXI\nLegislatura, siendo Gobernador Constitucional el C. Francisco Arturo Vega de Lamadrid\n20013-2016;\nARTÍCULO 29.- Fue reformado por Decreto No. 458, publicado en el Periódico Oficial\nLegislatura, siendo Gobernador Constitucional el C. Francisco Arturo Vega de Lamadrid\n20013-2016;\nARTÍCULO 38.- Fue reformado por Decreto No. 339, publicado en el Periódico Oficial\nLegislatura Constitucional, siendo Gobernador del Estado el C. Lic. José Guadalupe Osuna\nMillán, 2007-2013; fue reformado por Decreto No. 66, publicado en el Periódico Oficial No.\nLey de Protección al Ambiente para el Estado de Baja California. Página 96\nLegislatura, siendo Gobernador Constitucional el C. Francisco Arturo Vega de Lamadrid\n2013-2019; fue reformado por Decreto No. 129, publicado en el Periódico Oficial No. 56, Legislatura, siendo Gobernadora Constitucional la C. Marina del Pilar Ávila Olmeda 20212027;\nARTÍCULO 39.- Fue reformado mediante Decreto No. 318, publicado en el Periódico\nOficial No. 48, de fecha 26 de octubre de 2012, Tomo CXIX, expedido por la H. XX\nLegislatura, siendo Gobernador Constitucional el C. José Guadalupe Osuna Millán 200720013; fue reformado mediante Decreto No. 455, publicado en el Periódico Oficial No. 24, de fecha 24 de mayo de 2013, Sección I, Tomo CXX, expedido por la H. XX Legislatura, siendo\nGobernador Constitucional el C. José Guadalupe Osuna Millán 2007-20013; Fue reformado por Decreto No. 458, publicado en el Periódico Oficial No. 14, Sección V, Tomo CXXIII, de fecha 18 de marzo de 2016, expedido por la H. XXI Legislatura, siendo Gobernador\nConstitucional el C. Francisco Arturo Vega de Lamadrid 20013-2016; fue reformado por\nDecreto No. 129, publicado en el Periódico Oficial No. 56, Sección III, de fecha 19 de septiembre de 2022, Tomo CXXIX, expedido por la H. XXIV Legislatura, siendo Gobernadora\nConstitucional la C. Marina del Pilar Ávila Olmeda 2021-2027;\nARTÍCULO 42.- Fue reformado por Decreto No. 387, publicado en el Periódico\nOficial No. 40, de fecha 28 de septiembre de 2007, expedido por la Honorable XVIII\nLegislatura Constitucional, siendo Gobernador del Estado el C. Lic. Eugenio Elorduy\nWalther, 2001-2007; fue reformado por Decreto No. 431, publicado en el Periódico Oficial\nNo. 44, de fecha 15 de octubre de 2010, Tomo CXVII, expedido por la H. XIX Legislatura, siendo Gobernador Constitucional el C. José Guadalupe Osuna Millán 2007-2013; fue reformado por Decreto No. 281, publicado en el Periódico Oficial No. 51, de fecha 23 de julio de 2021, Tomo CXXVIII, expedido por la H. XXIII Legislatura, siendo Gobernador\nConstitucional el C. Jaime Bonilla Valdez 2019-2021;\nARTICULO 67.- Fue reformado por Decreto No. 255, publicado en el Periódico\nLegislatura, siendo Gobernador Constitucional el C. Francisco Arturo Vega de Lamadrid\n2013-2019;\nFue adicionado este Capitulo por Decreto No. 445, publicado en el Periódico Oficial No. 45, siendo Gobernador Constitucional el C. José Guadalupe Osuna Millán 2007-2013;\nCAPÍTULO III\nSECCIÓN I\nLey de Protección al Ambiente para el Estado de Baja California. Página 97\nZONAS DE RESTAURACIÓN\nARTICULO 100.- Fue reformado por Decreto No. 445, publicado en el Periódico\nXIX Legislatura, siendo Gobernador Constitucional el C. José Guadalupe Osuna Millán\n2007-2013;\nARTICULO 101.- Fue derogado por Decreto No. 445, publicado en el Periódico Oficial\nNo. 45, de fecha 22 de octubre de 2010, Tomo CXVII, Sección I, expedido por la H. XIX\nLegislatura, siendo Gobernador Constitucional el C. José Guadalupe Osuna Millán 20072013;\nFue adicionada esta Sección II mediante Decreto No. 445, publicado en el Periódico Oficial\nNo. 45, de fecha 22 de octubre de 2010, Tomo CXVII, Sección I, expedido por la H. XIX\nLegislatura, siendo Gobernador Constitucional el C. José Guadalupe Osuna Millán 20072013;\nSECCION II\nENERGÍA\nFue adicionada esta Sección mediante Decreto No. 445, publicado en el Periódico Oficial\nNo. 45, de fecha 22 de octubre de 2010, Tomo CXVII, Sección I, expedido por la H. XIX\nLegislatura, siendo Gobernador Constitucional el C. José Guadalupe Osuna Millán\n2007-2013;\nSECCION III\nVIDA SILVESTRE\nARTICULO 106 BIS.- Fue adicionado por Decreto No. 445, publicado en el Periódico\nOficial No. 45, de fecha 22 de octubre de 2010, Tomo CXVII, Sección I, expedido por la H.\nXIX Legislatura, siendo Gobernador Constitucional el C. José Guadalupe Osuna Millán\n2007-2013;\nARTICULO 106 BIS 1.- Fue adicionado por Decreto No. 445, publicado en el por la H. XIX Legislatura, siendo Gobernador Constitucional el C. José Guadalupe Osuna\nMillán 2007-2013; fue reformado por Decreto No. 627, publicado en el Periódico Oficial No.\nLegislatura, siendo Gobernador Constitucional el C. Francisco Arturo Vega de Lamadrid\n2013-2019;\nARTICULO 106 BIS 2.- Fue adicionado por Decreto No. 445, publicado en el\nLey de Protección al Ambiente para el Estado de Baja California. Página 98 por la H. XIX Legislatura, siendo Gobernador Constitucional el C. José Guadalupe Osuna\nMillán 2007-2013;\nARTICULO 106 BIS 3.- Fue adicionado por Decreto No. 251, publicado en el\nLegislatura, siendo Gobernador Constitucional el C. Francisco Arturo Vega de Lamadrid\n2013-2019;\nFue adicionada esta Sección IV por Decreto No. 458, publicado en el Periódico\nOficial No. 14, Sección V, Tomo CXXIII, de fecha 18 de marzo de 2016, expedido por la H.\nXXI Legislatura, siendo Gobernador Constitucional el C. Francisco Arturo Vega de Lamadrid\n20013-2016;\nSECCIÓN IV\nCORREDORES BIOLÓGICOS\nFue adicionado este Capítulo mediante Decreto No. 67, publicado en el Periódico Oficial\nNo. 39, Sección II, de fecha 01 de agosto de 2014, Tomo CXXI, expedido por la H. XXI\nLegislatura, siendo Gobernador Constitucional el C. Francisco Arturo Vega de Lamadrid\n2013-2019;\nCAPÍTULO IV\nÁreas Verdes Urbanas\nARTÍCULO 106 TER.- Fue adicionado por Decreto No. 67, publicado en el Periódico\nXXI Legislatura, siendo Gobernador Constitucional el C. Francisco Arturo Vega de Lamadrid\n2013-2019; fue reformado por Decreto No. 129, publicado en el Periódico Oficial No. 56, Legislatura, siendo Gobernadora Constitucional la C. Marina del Pilar Ávila Olmeda 20212027;\nARTÍCULO 106 TER 1.- Fue adicionado por Decreto No. 67, publicado en el por la H. XXI Legislatura, siendo Gobernador Constitucional el C. Francisco Arturo Vega de\nLey de Protección al Ambiente para el Estado de Baja California. Página 99\nLamadrid 2013-2019; fue reformado por Decreto No. 129, publicado en el Periódico Oficial\nXXIV Legislatura, siendo Gobernadora Constitucional la C. Marina del Pilar Ávila Olmeda\n2021-2027;\nARTÍCULO 106 TER 2.- Fue adicionado por Decreto No. 67, publicado en el\nPeriódico Oficial No. 39, Sección II, de fecha 01 de agosto de 2014, Tomo CXXI, expedido por la H. XXI Legislatura, siendo Gobernador Constitucional el C. Francisco Arturo Vega de\nLamadrid 2013-2019; fue reformado por Decreto No. 129, publicado en el Periódico Oficial\nNo. 56, Sección III, de fecha 19 de septiembre de 2022, Tomo CXXIX, expedido por la H.\nXXIV Legislatura, siendo Gobernadora Constitucional la C. Marina del Pilar Ávila Olmeda\n2021-2027;\nARTÍCULO 106 TER 3.- Fue adicionado por Decreto No. 67, publicado en el\nPeriódico Oficial No. 39, Sección II, de fecha 01 de agosto de 2014, Tomo CXXI, expedido por la H. XXI Legislatura, siendo Gobernador Constitucional el C. Francisco Arturo Vega de\nLamadrid 2013-2019;\nARTICULO 108.- Fue reformado por Decreto No. 431, publicado en el Periódico\nOficial No. 44, de fecha 15 de octubre de 2010, Tomo CXVII, expedido por la H. XIX\nLegislatura, siendo Gobernador Constitucional el C. José Guadalupe Osuna Millán 20072013; fue reformado por Decreto No. 111, publicado en el Periódico Oficial No. 39. Índice, de fecha 27 de junio de 2025, Tomo CXXXII, expedido por la H. XXV Legislatura, siendo\nGobernadora Constitucional la C. Marina del Pilar Ávila Olmeda 2021-2027;\nARTICULO 109.- Fue reformado por Decreto No. 431, publicado en el Periódico\nOficial No. 44, de fecha 15 de octubre de 2010, Tomo CXVII, expedido por la H. XIX\nLegislatura, siendo Gobernador Constitucional el C. José Guadalupe Osuna Millán 20072013;\nARTÍCULO 111 BIS.- Fue adicionado mediante Decreto No. 509, publicado en el\nPeriódico Oficial No. 34, de fecha 29 de julio de 2016, Tomo CXXIII, Sección VI, expedido por la H. XXI Legislatura, siendo Gobernador Constitucional el C. Francisco Arturo Vega de\nLamadrid 2013-2019;\nARTÍCULO 112.- Fue reformado por Decreto No. 341, publicado en el Periódico siendo Gobernador Constitucional el C. José Guadalupe Osuna Millan 2007-2013; fue reformado por Decreto No. 66, publicado en el Periódico Oficial No. 39, Sección II, de fecha\nConstitucional el C. Francisco Arturo Vega de Lamadrid 2013-2019; fue reformado mediante\nTomo CXXIII, Sección VI, expedido por la H. XXI Legislatura, siendo Gobernador\nConstitucional el C. Francisco Arturo Vega de Lamadrid 2013-2019; fue reformado mediante\nLey de Protección al Ambiente para el Estado de Baja California. Página 100\nTomo CXXV, Sección VII, expedido por la H. XXII Legislatura, siendo Gobernador\nConstitucional el C. Francisco Arturo Vega de Lamadrid 2013-2019;\nARTÍCULO 113.- Fue reformado por Decreto No. 341, publicado en el Periódico siendo Gobernador Constitucional el C. José Guadalupe Osuna Millán 2007-2013; fue reformado por Decreto No. 66, publicado en el Periódico Oficial No. 39, Sección II, de fecha\n01 de agosto de 2014, Tomo CXXI, expedido por la H. XXI Legislatura, siendo Gobernador\nConstitucional el C. Francisco Arturo Vega de Lamadrid 2013-2019; fue adicionado mediante\nDecreto No. 149, publicado en el Periódico Oficial No. 50, Tomo CXXIV, Sección III, de fecha\n10 de noviembre de 2017, expedido por la H. XXII Legislatura, siendo Gobernador\nConstitucional el C. Francisco Arturo Vega de Lamadrid 2013-2019. fue reformado por\nDecreto No. 202, publicado en el Periódico Oficial No. 8, Índice, de fecha 10 de febrero de\n2023, Tomo CXXX, expedido por la H. XXIV Legislatura, siendo Gobernadora Constitucional la C. Marina del Pilar Ávila Olmeda 2021-2027;\nARTÍCULO 113 BIS.- Fue adicionado por Decreto No. 202, publicado en el Periódico\nOficial No. 8, Índice, de fecha 10 de febrero de 2023, Tomo CXXX, expedido por la H. XXIV\nLegislatura, siendo Gobernadora Constitucional la C. Marina del Pilar Ávila Olmeda 20212027;\nARTÍCULO 113 TER.- Fue adicionado por Decreto No. 202, publicado en el Periódico\nOficial No. 8, Índice, de fecha 10 de febrero de 2023, Tomo CXXX, expedido por la H. XXIV\nLegislatura, siendo Gobernadora Constitucional la C. Marina del Pilar Ávila Olmeda 20212027;\nFue modificada la denominación de esta sección por Decreto No. 341, publicado en el\nPeriódico Oficial No. 02, de fecha 05 de enero de 2010, Tomo CXVII, expedido por la\nHonorable XIX, Legislatura Constitucional, siendo Gobernador del Estado el C. Lic. José\nGuadalupe Osuna Millán, 2007-2013;\nSECCIÓN IV\nDe los centros de verificación\nARTÍCULO 117.- Fue reformado por Decreto No. 341, publicado en el Periódico siendo Gobernador Constitucional el C. José Guadalupe Osuna Millán 2007-2013;\nARTÍCULO 118.- Fue reformado por Decreto No. 341, publicado en el Periódico siendo Gobernador Constitucional el C. José Guadalupe Osuna Millán 2007-2013; fue reformado mediante Decreto No. 263, publicado en el Periódico Oficial No. 6, Tomo CXX, de\nLey de Protección al Ambiente para el Estado de Baja California. Página 101\nConstitucional el C. José Guadalupe Osuna Millán 2007-2013; fue reformado mediante\nDecreto No. 28, publicado en el Periódico Oficial No. 60, Sección VIII, Tomo CXX, de fecha\nConstitucional el C. Francisco Arturo Vega de la Madrid 2013-2019;\nARTÍCULO 118 BIS.- Fue adicionado mediante Decreto No. 263, publicado en el\nPeriódico Oficial No. 6, Tomo CXX, de fecha 01 de febrero de 2013, expedido por la H. XX\nLegislatura, siendo Gobernador Constitucional el C. José Guadalupe Osuna Millán 20072013;\nARTÍCULO 119.- Fue reformado por Decreto No. 341, publicado en el Periódico\nOficial No. 2, de fecha 05 de enero de 2010, expedido por la Honorable XIX Legislatura, siendo Gobernador Constitucional el C. José Guadalupe Osuna Millán 2007-2013;\nARTÍCULO 119 BIS.- Fue adicionado por Decreto No. 341, publicado en el Periódico\nOficial No. 2, de fecha 05 de enero de 2010, expedido por la Honorable XIX Legislatura, siendo Gobernador Constitucional el C. José Guadalupe Osuna Millán 2007-2013;\nARTÍCULO 119 BIS 1.- Fue adicionado por Decreto No. 341, publicado en el\nPeriódico Oficial No. 2, de fecha 05 de enero de 2010, expedido por la Honorable XIX\nLegislatura, siendo Gobernador Constitucional el C. José Guadalupe Osuna Millán 20072013;\nARTÍCULO 119 BIS 2.- Fue adicionado por Decreto No. 341, publicado en el\nPeriódico Oficial No. 2, de fecha 05 de enero de 2010, expedido por la Honorable XIX\nLegislatura, siendo Gobernador Constitucional el C. José Guadalupe Osuna Millán 20072013;\nARTÍCULO 119 BIS 3.- Fue adicionado por Decreto No. 341, publicado en el\nPeriódico Oficial No. 2, de fecha 05 de enero de 2010, expedido por la Honorable XIX\nLegislatura, siendo Gobernador Constitucional el C. José Guadalupe Osuna Millán 20072013;\nARTÍCULO 119 BIS 4.- Fue adicionado por Decreto No. 341, publicado en el\nLegislatura, siendo Gobernador Constitucional el C. José Guadalupe Osuna Millán 20072013;\nFue modificada la denominación de esta sección por Decreto No. 339, publicado en el\nHonorable XIX, Legislatura Constitucional, siendo Gobernador del Estado el C. Lic. José\nGuadalupe Osuna Millán, 2007-2013;\nSECCIÓN V\nLey de Protección al Ambiente para el Estado de Baja California. Página 102\nARTÍCULO 120.- Fue derogado por Decreto No. 387, publicado en el Periódico Oficial\nConstitucional, siendo Gobernador del Estado el C. Lic. Eugenio Elorduy Walther, 20012007; fue reformado por Decreto No. 339, publicado en el Periódico Oficial No. 01, de fecha\n14 de enero de 2010, Tomo CXVII, expedido por la Honorable XIX Legislatura\nConstitucional, siendo Gobernador del Estado el C. Lic. José Guadalupe Osuna Millán, 2007-2013;\nARTÍCULO 121.- Fue derogado por Decreto No. 387, publicado en el Periódico Oficial\nNo. 40, de fecha 28 de septiembre de 2007, expedido por la Honorable XVIII Legislatura\nConstitucional, siendo Gobernador del Estado el C. Lic. Eugenio Elorduy Walther, 20012007; fue reformado por Decreto No. 339, publicado en el Periódico Oficial No. 01, de fecha\n14 de enero de 2010, Tomo CXVII, expedido por la Honorable XIX Legislatura\nConstitucional, siendo Gobernador del Estado el C. Lic. José Guadalupe Osuna Millán, 2007-2013;\nARTÍCULO 136.- Fue adicionado mediante Decreto No. 149, publicado en el\nPeriódico Oficial No. 50, Tomo CXXIV, Sección III, de fecha 10 de noviembre de 2017, expedido por la H. XXII Legislatura, siendo Gobernador Constitucional el C. Francisco Arturo\nVega de Lamadrid 2013-2019.\nARTÍCULO 137.- Fue derogado por Decreto No. 387, publicado en el Periódico Oficial\nNo. 40, de fecha 28 de septiembre de 2007, expedido por la Honorable XVIII Legislatura\nConstitucional, siendo Gobernador del Estado el C. Lic. Eugenio Elorduy Walther, 20012007;\nARTÍCULO 139.- Fue derogado por Decreto No. 387, publicado en el Periódico Oficial\nNo. 40, de fecha 28 de septiembre de 2007, expedido por la Honorable XVIII Legislatura\nConstitucional, siendo Gobernador del Estado el C. Lic. Eugenio Elorduy Walther, 20012007;\nARTÍCULO 141.- Fue derogado por Decreto No. 387, publicado en el Periódico Oficial\nNo. 40, de fecha 28 de septiembre de 2007, expedido por la Honorable XVIII Legislatura\nConstitucional, siendo Gobernador del Estado el C. Lic. Eugenio Elorduy Walther, 20012007; Fue derogado por Decreto No. 340, publicado en el Periódico Oficial No. 59, de fecha\nGobernador del Estado el C. Lic. José Guadalupe Osuna Millán, 2007-2013; fue reformado por Decreto No. 457, publicado en el Periódico Oficial No. 13, Sección IV, Tomo CXXIII, de\nConstitucional el C. Francisco Arturo Vega de Lamadrid 20013-2016; fue reformado por\nDecreto No. 276, publicado en el Periódico Oficial No. 10, Sección III, Tomo CXXVI, de fecha\nConstitucional el C. Francisco Arturo Vega de Lamadrid 20013-2016;\nLey de Protección al Ambiente para el Estado de Baja California. Página 103\nARTICULO 141 BIS.- Fue reformado por Decreto No. 254, publicado en el Periódico\nLegislatura, siendo Gobernador Constitucional el C. Francisco Arturo Vega de Lamadrid\n2013-2019;\nARTICULO 141 TER.- Fue reformado por Decreto No. 254, publicado en el Periódico\nOficial No. 7, de fecha 01 de febrero de 2019, Tomo CXXVI, expedido por la H. XXII\nLegislatura, siendo Gobernador Constitucional el C. Francisco Arturo Vega de Lamadrid\n2013-2019;\nFue derogada esta sección por Decreto No. 387, publicado en el Periódico Oficial No. 40, de fecha 28 de septiembre de 2007, expedido por la Honorable XVIII Legislatura Constitucional, siendo Gobernador del Estado el C. Lic. Eugenio Elorduy Walther, 2001-2007;\nSECCION III\nDerogada\nARTÍCULO 142.- Fue derogado por Decreto No. 387, publicado en el Periódico Oficial\nNo. 40, de fecha 28 de septiembre de 2007, expedido por la Honorable XVIII Legislatura\nConstitucional, siendo Gobernador del Estado el C. Lic. Eugenio Elorduy Walther, 20012007;\nARTÍCULO 143.- Fue derogado por Decreto No. 387, publicado en el Periódico Oficial\nNo. 40, de fecha 28 de septiembre de 2007, expedido por la Honorable XVIII Legislatura\nConstitucional, siendo Gobernador del Estado el C. Lic. Eugenio Elorduy Walther, 20012007;\nARTÍCULO 144.- Fue derogado por Decreto No. 387, publicado en el Periódico Oficial\nNo. 40, de fecha 28 de septiembre de 2007, expedido por la Honorable XVIII Legislatura\nConstitucional, siendo Gobernador del Estado el C. Lic. Eugenio Elorduy Walther, 20012007;\nARTÍCULO 145.- Fue derogado por Decreto No. 387, publicado en el Periódico Oficial\nConstitucional, siendo Gobernador del Estado el C. Lic. Eugenio Elorduy Walther, 20012007;\nARTÍCULO 146.- Fue derogado por Decreto No. 387, publicado en el Periódico Oficial\nConstitucional, siendo Gobernador del Estado el C. Lic. Eugenio Elorduy Walther, 20012007;\nARTÍCULO 147.- Fue derogado por Decreto No. 387, publicado en el Periódico Oficial\nLey de Protección al Ambiente para el Estado de Baja California. Página 104\nConstitucional, siendo Gobernador del Estado el C. Lic. Eugenio Elorduy Walther, 20012007;\nARTÍCULO 148.- Fue derogado por Decreto No. 387, publicado en el Periódico Oficial\nConstitucional, siendo Gobernador del Estado el C. Lic. Eugenio Elorduy Walther, 20012007;\nARTÍCULO 149.- Fue derogado por Decreto No. 387, publicado en el Periódico Oficial\nNo. 40, de fecha 28 de septiembre de 2007, expedido por la Honorable XVIII Legislatura\nConstitucional, siendo Gobernador del Estado el C. Lic. Eugenio Elorduy Walther, 20012007;\nARTICULO 159.- Fue reformado por Decreto No. 129, publicado en el Periódico\nOficial No. 56, Sección III, de fecha 19 de septiembre de 2022, Tomo CXXIX, expedido por la\nH. XXIV Legislatura, siendo Gobernadora Constitucional la C. Marina del Pilar Ávila Olmeda\n2021-2027;\nARTICULO 168.- Fue reformado por Decreto No. 220, publicado en el Periódico\nOficial No. 16, Índice, de fecha 31 de marzo de 2023, Tomo CXXX, expedido por la H. XXIV\nLegislatura, siendo Gobernadora Constitucional la C. Marina del Pilar Ávila Olmeda 20212027;\nARTICULO 169.- Fue reformado por Decreto No. 220, publicado en el Periódico\nOficial No. 16, Índice, de fecha 31 de marzo de 2023, Tomo CXXX, expedido por la H. XXIV\nLegislatura, siendo Gobernadora Constitucional la C. Marina del Pilar Ávila Olmeda 20212027;\nARTICULO 171.- Fue reformado por Decreto No. 220, publicado en el Periódico\nOficial No. 16, Índice, de fecha 31 de marzo de 2023, Tomo CXXX, expedido por la H. XXIV\nLegislatura, siendo Gobernadora Constitucional la C. Marina del Pilar Ávila Olmeda 20212027;\nARTICULO 178.- Fue reformado por Decreto No. 220, publicado en el Periódico\nLegislatura, siendo Gobernadora Constitucional la C. Marina del Pilar Ávila Olmeda 20212027;\nARTICULO 182.- Fue reformado por Decreto No. 431, publicado en el Periódico\nLegislatura, siendo Gobernador Constitucional el C. José Guadalupe Osuna Millán 20072013; fue reformado por Decreto No. 220, publicado en el Periódico Oficial No. 16, Índice, de\nGobernadora Constitucional la C. Marina del Pilar Ávila Olmeda 2021-2027;\nLey de Protección al Ambiente para el Estado de Baja California. Página 105\nARTICULO 185.- Fue reformado por Decreto No. 220, publicado en el Periódico\nLegislatura, siendo Gobernadora Constitucional la C. Marina del Pilar Ávila Olmeda 20212027;\nARTICULO 187.- Fue reformado por Decreto No. 67, publicado en el Periódico Oficial\nNo. 39, Sección II, de fecha 01 de agosto de 2014, Tomo CXXI, expedido por la H. XXI\nLegislatura, siendo Gobernador Constitucional el C. Francisco Arturo Vega de Lamadrid\n2013-2019; fue reformado por Decreto No. 220, publicado en el Periódico Oficial No. 16, Índice, de fecha 31 de marzo de 2023, Tomo CXXX, expedido por la H. XXIV Legislatura, siendo Gobernadora Constitucional la C. Marina del Pilar Ávila Olmeda 2021-2027;\nARTICULO 191 BIS.- Fue reformado por Decreto No. 220, publicado en el Periódico\nOficial No. 16, Índice, de fecha 31 de marzo de 2023, Tomo CXXX, expedido por la H. XXIV\nLegislatura, siendo Gobernadora Constitucional la C. Marina del Pilar Ávila Olmeda 20212027;\nFue adicionado este Capítulo por Decreto No. 438, publicado en el Periódico Oficial No. 44, de fecha 15 de octubre de 2010, Tomo CXVII, expedido por la H. XIX Legislatura, siendo\nGobernador Constitucional el C. José Guadalupe Osuna Millán 2007-2013;\nTÍTULO QUINTO\nPARTICIPACIÓN CIUDADANA\nCAPÍTULO V\n“DE LAS REGLAS DE LAS NOTIFICACIONES”\nARTÍCULO 204 BIS.- Fue adicionado este Capítulo por Decreto No. 438, publicado en el Periódico Oficial No. 44, de fecha 15 de octubre de 2010, Tomo CXVII, expedido por la\nH. XIX Legislatura, siendo Gobernador Constitucional el C. José Guadalupe Osuna Millán\n2007-2013;\nARTÍCULO 204 BIS 1.- Fue adicionado este Capítulo por Decreto No. 438, expedido por la H. XIX Legislatura, siendo Gobernador Constitucional el C. José Guadalupe\nOsuna Millán 2007-2013;\nARTÍCULO 204 BIS 2.- Fue adicionado este Capítulo por Decreto No. 438, expedido por la H. XIX Legislatura, siendo Gobernador Constitucional el C. José Guadalupe\nOsuna Millán 2007-2013;\nLey de Protección al Ambiente para el Estado de Baja California. Página 106\nARTÍCULO 204 BIS 3.- Fue adicionado este Capítulo por Decreto No. 438, expedido por la H. XIX Legislatura, siendo Gobernador Constitucional el C. José Guadalupe\nOsuna Millán 2007-2013;\nARTÍCULO 204 BIS 4.- Fue adicionado este Capítulo por Decreto No. 438, publicado\nH. XIX Legislatura, siendo Gobernador Constitucional el C. José Guadalupe Osuna Millán\n2007-2013;\nTRANSITORIO TERCERO.- Fue adicionado mediante Decreto No. 38, publicado en por la H. XXI Legislatura, siendo Gobernador Constitucional el C. Francisco Arturo Vega de la Madrid 2013-2019;\nLey de Protección al Ambiente para el Estado de Baja California. Página 107\nARTICULO SEGUNDO TRANSITORIO DEL DECRETO No. 63, DONDE SE\nREFORMA EL ARTICULO QUINTO TRANSITORIO, PUBLICADO EN EL PERIODICO\nHONORABLE XVII LEGISLATURA CONSTITUCIONAL, SIENDO GOBERNADOR DEL\nESTADO EL C. LIC. EUGENIO ELORDUY WALTHER, 2001-2007.\nUNICO.- Las presentes reformas entrarán en vigor el día siguiente al de su publicación en el Periódico Oficial del Estado de Baja California.\nDADO en el Salón de Sesiones “Lic. Benito Juárez García” del Honorable Poder\nLegislativo, en la Ciudad de Mexicali, Baja California, a los trece días del mes de junio del año dos mil dos.\nDIP. JESUS ALEJANDRO RUIZ URIBE\nPRESIDENTE\n(RÚBRICA).\nDIP. MARIA ROSALBA MARTIN NAVARRO\nPROSECRETARIA\n(RÚBRICA).\nDE CONFORMIDAD CON LO DISPUESTO DISPUESTO POR LA FRACCION I DEL\nARTICULO 49 DE LA CONSTITUCION POLITICA DEL ESTADO, MANDO SE IMPRIMA Y\nPUBLIQUE.\nMEXICALI, BAJA CALIFORNIA, A LOS VEINTIUN DIAS DEL MES DE JUNIO DEL AÑO\nDOS MIL DOS.\nGOBERNADOR DEL ESTADO.\nEUGENIO ELORDUY WALTHER.\n(RÚBRICA).\nSECRETARIO GENERAL DE GOBIERNO\nBERNARDO BORBON VILCHES.\n(RÚBRICA).\nARTICULO UNICO TRANSITORIO DEL DECRETO NO. 60, QUE REFORMA LOS\nARTÍCULOS 2, 3, 8, 9, 38, 39, 42, 43, 44, 45, 50, 53, 125, 130, 135, 136, 161, 164, 171, 178,\n187, 190, 192 Y DENOMINACIÓN DEL CAPÍTULO IV DEL TÍTULO SEXTO, ADICIÓN DEL\nARTÍCULO 191 BIS, ASÍ COMO DEROGACIÓN DEL ARTÍCULO 25, PUBLICADO EN EL\nLey de Protección al Ambiente para el Estado de Baja California. Página 108\nPOR LA H. XIX LEGISLATURA, SIENDO GOBERNADOR CONSTITUCIONAL EL C. JOSÉ\nGUADALUPE OSUNA MILLÁN 2007-2013.\nARTICULOS TRANSITORIOS\nUNICO.- Las presentes reformas entrarán en vigor al día siguiente de su publicación en el Periódico Oficial del Estado.\nDADO en el Salón de Sesiones “Lic. Benito Juárez García” del H. Poder Legislativo del Estado de Baja California, en la Ciudad de Mexicali, B.C., a los ocho días del mes de mayo del año dos mil ocho.\nDIP. JOSÉ ALFREDO FERREIRO VELAZCO\nPRESIDENTE\n(RÚBRICA)\nDIP. JUAN MANUEL GASTÉLUM BUENROSTRO\nSECRETARIO\n(RÚBRICA)\nDE CONFORMIDAD CON LO DISPUESTO POR LA FRACCION I DEL ARTICULO\n49 DE LA CONSTITUCION POLITICA DEL ESTADO, Y ARTICULO 9 DE LA LEY\nORGANICA DE LA ADMINISTRACION PUBLICA DEL ESTADO DE BAJA CALIFORNIA,\nIMPRIMASE Y PUBLÍQUE.\nMEXICALI, BAJA CALIFORNIA, A LOS TREINTA DIAS DEL MES DE MAYO DEL\nAÑO DOS MIL OCHO.\nGOBERNADOR DEL ESTADO.\nJOSÉ GUADALUPE OSUNA MILLÁN\n(RÚBRICA)\nSECRETARIO GENERAL DE GOBIERNO\nJOSE FRANCISCO BLAKE MORA\n(RÚBRICA)\nSECRETARIO DE PROTECCION AL AMBIENTE\nSOCRATESBASTIDA HERNANDEZ\n(RÚBRICA)\nLey de Protección al Ambiente para el Estado de Baja California. Página 109\nARTICULO PRIMERO TRANSITORIO DEL DECRETO No. 387, DONDE SE\nREFORMA EL ARTICULO 42, LA DEROGACIÓN DE LOS ARTÍCULOS 120, 121, 137, 139,\n141, 142, 143, 144, 145, 146, 147, 148 Y 149, ASÍ COMO LA DENOMINACIÓN DE LA\nSECCIÓN III “RESIDUOS INDUSTRIALES Y RESIDUOS SÓLIDOS MUNICIPALES”,\nPUBLICADO EN EL PERIODICO OFICIAL No. 40, DE FECHA 28 DE SEPTIEMBRE DE\n2007, TOMO CXIV, EXPEDIDO POR LA HONORABLE XVIII LEGISLATURA\nCONSTITUCIONAL, SIENDO GOBERNADOR DEL ESTADO EL C. LIC. EUGENIO\nELORDUY WALTHER, 2001-2007.\nDADO En el Salón de Sesiones “Lic. Benito Juárez García”, en la Ciudad de Mexicali, Baja California”, a los veintinueve días del mes de agosto del año dos mil siete.\nDIP. RAÚL LÓPEZ MORENO\nPRESIDENTE\n(RÚBRICA)\nDIP. ABRAHAM CORREA ACEVEDO\nSECRETARIO\n(RÚBRICA)\nDE CONFORMIDAD CON LO DISPUESTO DISPUESTO POR LA FRACCION I DEL\nARTICULO 49 DE LA CONSTITUCION POLITICA DEL ESTADO, MANDO SE IMPRIMA Y\nPUBLIQUE.\nMEXICALI, BAJA CALIFORNIA, A LOS DOCE DIAS DEL MES DE SEPTIEMBRE\nDEL AÑO DOS MIL SIETE.\nGOBERNADOR DEL ESTADO.\nEUGENIO ELORDUY WALTHER.\n(RÚBRICA)\nSECRETARIO GENERAL DE GOBIERNO\nBERNARDO H. MARTÍNEZ AGUIRRE\n(RÚBRICA)\nARTICULO TRANSITORIO DEL DECRETO No. 145, DONDE SE REFORMA A LAS\nARTÍCULO 18, PUBLICADO EN EL PERIODICO OFICIAL No. 56, DE FECHA 14 DE\nLEGISLATURA CONSTITUCIONAL, SIENDO GOBERNADOR DEL ESTADO EL C. LIC.\nJOSÉ GUADALUPE OSUNA MILLÁN, 2007-2013.\nLey de Protección al Ambiente para el Estado de Baja California. Página 110 del Estado de Baja California, en la Ciudad de Mexicali, B.C., a los veintitrés días del mes de octubre del año dos mil ocho.\nDIP. GINA ANDREA CRUZ BLACKLEDGE\nPRESIDENTA\n(RÚBRICA)\nDIP. JUAN MANUEL MOLINA GARCÍA\nSECRETARIO\n(RÚBRICA)\nDE CONFORMIDAD CON LO DISPUESTO DISPUESTO POR LA FRACCION I DEL\nARTICULO 49 DE LA CONSTITUCION POLITICA DEL ESTADO, MANDO SE IMPRIMA Y\nPUBLIQUE.\nMEXICALI, BAJA CALIFORNIA, A LOS SIETE DIAS DEL MES DE NOVIEMBRE DEL\nAÑO DOS MIL OCHO.\nJOSÉ GUADALUPE OSUNA MILLÁN\nGOBERNADOR DEL ESTADO.\n(RÚBRICA)\nJOSÉ FRANCISCO BLAKE MORA\nSECRETARIO GENERAL DE GOBIERNO\n(RÚBRICA)\nARTICULO PRIMERO TRANSITORIO DEL DECRETO No. 340, POR EL QUE SE\nAPRUEBA LA REFORMA AL ARTÍCULO 141, DE FECHA 31 DE DICIEMBRE DE 2009,\nTOMO CXVI, SECCION IX, EXPEDIDO POR LA H. XIX LEGISLATURA, SIENDO\nGOBERNADOR CONSTITUCIONAL EL C. JOSÉ GUADALUPE OSUNA MILLÁN 2007-\n2013.\nPRIMERO.- En el ámbito territorial del Estado de Baja California, las personas físicas derivados del petróleo, contarán con un plazo de 365 días a efecto de sustituir estos artículos por otros materiales que faciliten su reuso, reciclado o de pronta biodegradación a fin de proteger el medio ambiente. atribuciones, deberá de emitir la normatividad y ajustar su reglamentación en la materia a los fines y objetivos de esta reforma.\nLey de Protección al Ambiente para el Estado de Baja California. Página 111\nTERCERO.- Los municipios del Estado, dentro del ámbito legal de sus competencias, esta reforma.\nCUARTO.- La presente reforma entrará en vigor al día siguiente al de su publicación en el Periódico Oficial del Estado de Baja California.\nDADO en el Salón de Sesiones “Lic. Benito Juárez García” del H. Poder Legislativo del Estado de Baja California, en la ciudad de Mexicali, B.C., a los dieciocho días del mes de diciembre de dos mil nueve.\nDIP. ANTONIO RICARDO CANO JIMÉNEZ\nPRESIDENTE\n(RÚBRICA)\nDIP. RUBÉN ERNESTO ARMENTA ZANABIA\nSECRETARIO\n(RÚBRICA)\nDE CONFORMIDAD CON LO DISPUESTO POR LA FRACCION I DEL ARTICULO\n49 DE LA CONSTITUCION POLITICA DEL ESTADO, IMPRIMASE Y PUBLIQUESE.\nMEXICALI, BAJA CALIFORNIA, A LOS VEINTIDÓS DIAS DEL MES DE DICIEMBRE\nDEL AÑO DOS MIL NUEVE.\nGOBERNADOR DEL ESTADO\nJOSÉ GUADALUPE OSUNA MILLÁN\n(RÚBRICA)\nSECRETARIO GENERAL DE GOBIERNO\nJOSÉ FRANCISCO BLAKE MORA\n(RÚBRICA)\nARTICULO TRANSITORIO DEL DECRETO No. 339, POR EL QUE SE APRUEBA\nLA REFORMA A LOS ARTÍCULOS 1, 2, 8, 38, 120 Y 121, ASÍ COMO EL CAMBIO DE LA\nDENOMINACIÓN DE LA SECCIÓN V, POR EL DE PREVENCIÓN Y CONTROL DE LA\nCONTAMINACIÓN LUMÍNICA, DEL CAPÍTULO II, DEL TITULO CUARTO, DE FECHA 04\nGOBERNADOR CONSTITUCIONAL EL C. JOSÉ GUADALUPE OSUNA MILLÁN 2007-\n2013.\nTRANSITORIOS\nLey de Protección al Ambiente para el Estado de Baja California. Página 112 publicación en el Periódico Oficial de Estado de Baja California.\nARTÍCULO SEGUNDO: Los municipios deberán crear o adecuar sus reglamentos, y demás disposiciones normativas, debiéndolos expedir dentro de los ciento ochenta días naturales siguientes a la entrada en vigor de este ordenamiento.\nDADO en el Salón de Sesiones “Lic. Benito Juárez García” del H. Poder Legislativo del Estado de Baja California, en la ciudad de Mexicali, B.C., a los dieciocho días del mes de diciembre de dos mil nueve.\nDIP. ANTONIO RICARDO CANO JIMÉNEZ\nPRESIDENTE\n(RÚBRICA)\nDIP. RUBÉN ERNESTO ARMENTA ZANABIA\nSECRETARIO\n(RÚBRICA)\nDE CONFORMIDAD CON LO DISPUESTO POR LA FRACCION I DEL ARTICULO\n49 DE LA CONSTITUCION POLITICA DEL ESTADO, IMPRIMASE Y PUBLIQUESE.\nMEXICALI, BAJA CALIFORNIA, A LOS TREINTA DIAS DEL MES DE DICIEMBRE\nDEL AÑO DOS MIL NUEVE.\nGOBERNADOR DEL ESTADO\nJOSÉ GUADALUPE OSUNA MILLÁN\n(RÚBRICA)\nSECRETARIO GENERAL DE GOBIERNO\nJOSÉ FRANCISCO BLAKE MORA\n(RÚBRICA)\nARTICULO SEGUNDO TRANSITORIO DEL DECRETO No. 341, POR EL QUE SE\nREFORMAN LOS ARTÍCULOS 2, 8, 112, 113, 117, 118, 119, Y SE ADICIONAN LOS\nNUMERALES 119 BIS, 119 BIS 1, 119 BIS 2, 119 BIS 3 Y 119 BIS 4, ASÍ COMO TAMBIÉN\nEXPEDIDO POR LA H. XIX LEGISLATURA, SIENDO GOBERNADOR CONSTITUCIONAL\nEL C. JOSÉ GUADALUPE OSUNA MILLÁN 2007-2013.\nTRANSITORIOS\nLey de Protección al Ambiente para el Estado de Baja California. Página 113\nPRIMERO.- El presente Decreto entrará en vigor al día siguiente de su publicación en el Periódico Oficial del Estado.\nSEGUNDO.- El Ejecutivo Estatal y los Municipios deberán expedir las disposiciones legales que deriven del presente Decreto, a partir de su entrada en vigor.\nTERCERO.- Las obligaciones contempladas en el artículo 118 para los propietarios y poseedores de vehículos automotores en circulación, iniciarán hasta que sea publicado en los términos previstos en este Decreto, el Programa de Verificación Vehicular y, en su caso, estén operando los centros de verificación.\nDADO en el Salón de Sesiones “Lic. Benito Juárez García” del H. Poder Legislativo del Estado de Baja California, en la ciudad de Mexicali, B.C., a los dieciocho días del mes de diciembre de dos mil nueve.\nDIP. ANTONIO RICARDO CANO JIMÉNEZ\nPRESIDENTE\n(RÚBRICA)\nDIP. RUBÉN ERNESTO ARMENTA ZANABIA\nSECRETARIO\n(RÚBRICA)\nDE CONFORMIDAD CON LO DISPUESTO POR LA FRACCION I DEL ARTICULO\n49 DE LA CONSTITUCION POLITICA DEL ESTADO, IMPRIMASE Y PUBLIQUESE.\nMEXICALI, BAJA CALIFORNIA, A LOS TREINTA DÍAS DEL MES DE DICIEMBRE\nDEL AÑO DOS MIL NUEVE.\nGOBERNADOR DEL ESTADO\nJOSÉ GUADALUPE OSUNA MILLÁN\n(RÚBRICA)\nSECRETARIO GENERAL DE GOBIERNO\nJOSÉ FRANCISCO BLAKE MORA\n(RÚBRICA)\nARTICULO SEGUNDO TRANSITORIO DEL DECRETO No. 383, POR EL QUE SE\nREFORMA EL ARTICULO 15, PUBLICADO EN EL PERIODICO OFICIAL No. 32, DE\nSIENDO GOBERNADOR CONSTITUCIONAL EL C. JOSÉ GUADALUPE OSUNA MILLÁN\n2007-2013.\nDIP. ÓSCAR R. MARTÍNEZ GARZA\nLey de Protección al Ambiente para el Estado de Baja California. Página 114\nPRESIDENTE\n(RÚBRICA)\nDIP. JUAN MANUEL MOLINA GARCÍA\nSECRETARIO\n(RÚBRICA)\nDE CONFORMIDAD CON LO DISPUESTO POR LA FRACCIÓN I DEL ARTÍCULO 49\nMEXICALI, BAJA CALIFORNIA, A LOS QUINCE DÍAS DEL MES DE JULIO DEL AÑO\nDOS MIL DIEZ.\nGOBERNADOR DEL ESTADO.\nJOSÉ GUADALUPE OSUNA MILLÁN.\n(RÚBRICA)\nOFICIAL MAYOR DE GOBIERNO\nRUTH TRINIDAD HERNÁNDEZ MARTÍNEZ\n(RÚBRICA)\nDe conformidad con lo dispuesto por el artículo 54 de la\nBaja California, firma la Oficial Mayor de Gobierno del Estado\nARTICULO UNICO TRANSITORIO DEL DECRETO No. 438, POR EL QUE SE\nREFORMAN LOS ARTÍCULOS 42, 108, 109 Y 182, ASÍ COMO ADICIÓN DE UN\nCAPÍTULO V DENOMINADO “DE LAS REGLAS DE LAS NOTIFICACIONES” Y\nARTÍCULOS 204 BIS, 204 BIS 1, 204 BIS 2, 204 BIS 3 Y 204 BIS 4, PUBLICADO EN EL\nEXPEDIDO POR LA H. XIX LEGISLATURA, SIENDO GOBERNADOR CONSTITUCIONAL\nEL C. JOSÉ GUADALUPE OSUNA MILLÁN 2007-2013.\nTRANSITORIOS:\nPRIMERO.- El presente Decreto entrará en vigor al día siguiente de su publicación en el Periódico Oficial del Estado de Baja California”.\nSEGUNDO.- El Ejecutivo del Estado expedirá un reglamento dentro de un plazo que no exceda noventa días contados a partir de la entrada en vigor de las presentes reformas.\nLey de Protección al Ambiente para el Estado de Baja California. Página 115\nTERCERO.- La Secretaría junto con los Ayuntamientos del Estado iniciaran mesa de párrafo del artículo 42 de la presente ley. del Estado de Baja California, en la Ciudad de Mexicali, B.C., a los veinticuatro días del mes de septiembre del año dos mil diez.\nDIP. JUAN MANUEL GASTÉLUM BUENROSTRO\n(RÚBRICA)\nDIP. CARLOS ALONSO ANGULO RENTERÍA\n(RÚBRICA)\nDE CONFORMIDAD CON LO DISPUESTO POR LA FRACCION I DEL ARTÍCULO 49\nMEXICALI, BAJA CALIFORNIA, A LOS TREINTA DIAS DEL MES DE SEPTIEMBRE\nDEL AÑO DOS MIL DIEZ.\nGOBERNADOR DEL ESTADO\nJOSÉ GUADALUPE OSUNA MILLÁN\n(RÚBRICA)\nSECRETARIO GENERAL DE GOBIERNO\nCUAUHTEMOC CARDONA BENAVIDES\n(RÚBRICA)\nARTICULO UNICO TRANSITORIO DEL DECRETO No. 445, POR EL QUE SE\nREFORMAN LOS ARTÍCULOS 1, 2, 3, 8, 101, ASÍ COMO SE ADICIONA AL CAPÍTULO\nTERCERO, TRES SECCIONES A INTEGRARSE LA SECCIÓN I CON EL ACTUAL\nARTÍCULO 100 Y LA REFORMA AL 101; LA SECCIÓN II, CON LOS VIGENTES\nARTÍCULOS 102 AL 106; Y LA SECCIÓN III CON LOS NUMERALES 106 BIS, 106 BIS 1 Y\n106 BIS2, PUBLICADO EN EL PERIODICO OFICIAL No. 45, DE FECHA 15 DE OCTUBRE\nDE 2010, TOMO CXVII, SECCION I, EXPEDIDO POR LA H. XIX LEGISLATURA, SIENDO\nGOBERNADOR CONSTITUCIONAL EL C. JOSÉ GUADALUPE OSUNA MILLÁN 2007-\n2013.\nTRANSITORIOS\nLey de Protección al Ambiente para el Estado de Baja California. Página 116 publicación en el Periódico Oficial del Estado de Baja California.\nARTÍCULO SEGUNDO: Los municipios deberán crear o adecuar sus reglamentos, y demás disposiciones normativas, debiéndolos expedir dentro de los ciento ochenta días naturales siguientes a la entrada en vigor de este ordenamiento.\nDADO en el Salón de Sesiones “Lic. Benito Juárez García” del H. Poder Legislativo del Estado de Baja California, en la Ciudad de Mexicali, B.C., a los veinticuatro días del mes de septiembre del año dos mil diez.\nDIP. JUAN MANUEL GASTÉLUM BUENROSTRO\n(RÚBRICA)\nDIP. CARLOS ALONSO ANGULO RENTERÍA\n(RÚBRICA)\nDE CONFORMIDAD CON LO DISPUESTO POR LA FRACCION I DEL ARTÍCULO 49\nMEXICALI, BAJA CALIFORNIA, AL PRIMER DIA DEL MES DE OCTUBRE DEL AÑO\nDOS MIL DIEZ.\nGOBERNADOR DEL ESTADO\nJOSÉ GUADALUPE OSUNA MILLÁN\n(RÚBRICA)\nSECRETARIO GENERAL DE GOBIERNO\nCUAUHTEMOC CARDONA BENAVIDES\n(RÚBRICA)\nARTÍCULO ÚNICO TRANSITORIO DEL DECRETO No. 318, POR EL QUE SE\nREFORMAN LOS ARTÍCULOS 1, 10 y 39, PUBLICADO EN EL PERIÓDICO OFICIAL NO.\nLEGISLATURA, SIENDO GOBERNADOR CONSTITUCIONAL EL C. JOSÉ GUADALUPE\nOSUNA MILLÁN 2007-2013.\nARTÍCULOS TRANSITORIOS\nLey de Protección al Ambiente para el Estado de Baja California. Página 117\nARTÍCULO PRIMERO.- La presente reforma entrará en vigor al día siguiente de su publicación en el Periódico Oficial del Estado de Baja California.\nARTÍCULO SEGUNDO.- El Ejecutivo implementará en un periodo de 90 días, la logística de transporte, inversión en los recipientes de basura y propaganda de la campaña, cuyo costo deberá ser acorde al dinero obtenido por la venta del material reciclable.\nDADO en el Salón de Sesiones “Lic. Benito Juárez García” del H. Poder Legislativo del Estado de Baja California, en la Ciudad de Mexicali, B.C., a los veinticinco días del mes de septiembre del año dos mil doce.\nDIP. ALFONSO GARZÓN ZATARAIN\nPRESIDENTE\n(RÚBRICA)\nDIP. FAUSTO ZÁRATE ZEPEDA\nSECRETARIO\n(RÚBRICA)\nDE CONFORMIDAD CON LO DISPUESTO POR LA FRACCIÓN I DEL ARTÍCULO 49\nMEXICALI, BAJA CALIFORNIA, A LOS TRES DÍAS DEL MES DE OCTUBRE DEL\nAÑO DOS MIL DOCE.\nJOSÉ GUADALUPE OSUNA MILLÁN\nGOBERNADOR DEL ESTADO\n(RÚBRICA)\nFRANCISCO ANTONIO GARCÍA BURGOS\nSECRETARIO GENERAL DE GOBIERNO\n(RÚBRICA)\nARTÍCULO ÚNICO TRANSITORIO DEL DECRETO No. 398, POR EL QUE SE\nREFORMAN LAS FRACCIONES IX, X, Y LA ADICIÓN DE UNA FRACCIÓN XI AL\nARTÍCULO 18, PUBLICADO EN EL PERIÓDICO OFICIAL No. 4, TOMO CXX, DE FECHA\nGOBERNADOR CONSTITUCIONAL EL C. JOSÉ GUADALUPE OSUNA MILLÁN 2007-\n2013.\nARTÍCULO TRANSITORIO\nÚNICO.- El presente decreto entrará en vigor al día siguiente de su publicación en el\nPeriódico Oficial del Estado.\nLey de Protección al Ambiente para el Estado de Baja California. Página 118 del Estado de Baja California, en la Ciudad de Mexicali, B.C., a los veinte días del mes de diciembre del año dos mil doce.\nDIP. CLAUDIA JOSEFINA AGATÓN MUÑÍZ\nPRESIDENTE\n(RÚBRICA)\nDIP. MARCO ANTONIO VIZCARRA CALDERÓN\nPROSECRETARIO\n(RÚBRICA)\nDE CONFORMIDAD CON LO DISPUESTO POR LA FRACCIÓN I DEL ARTÍCULO 49\nMEXICALI, BAJA CALIFORNIA, A LOS VEINTISEIS DÍAS DEL MES DE DICIEMBRE\nDEL AÑO DOS MIL DOCE.\nJOSÉ GUADALUPE OSUNA MILLÁN\nGOBERNADOR DEL ESTADO\n(RÚBRICA)\nFRANCISCO ANTONIO GARCÍA BURGOS\nSECRETARIO GENERAL DE GOBIERNO\n(RÚBRICA)\nARTÍCULO SEGUNDO TRANSITORIO DEL DECRETO No. 263, POR EL QUE SE\nREFORMA EL ARTÍCULO 118, SE ADICIONA EL ARTÍCULO 118 BIS, PUBLICADO EN EL\nPERIÓDICO OFICIAL NO. 6, SECCIÓN I, TOMO CXX, DE FECHA 01 DE FEBRERO DE\n2013, EXPEDIDO POR LA H. XX LEGISLATURA, SIENDO GOBERNADOR\nCONSTITUCIONAL EL C. JOSÉ GUADALUPE OSUNA MILLÁN 2007-2013.\nARTÍCULOS TRANSITORIOS\nPRIMERO.- Los Ayuntamientos contarán con un plazo de 30 días naturales contados verificación vehicular vigente.\nSEGUNDO.- Para el ejercicio fiscal 2013 los automóviles que no hayan obtenido el certificado que acredite haber aprobado la verificación vehicular correspondiente, podrán presentar en su lugar la constancia técnica de verificación.\nLey de Protección al Ambiente para el Estado de Baja California. Página 119\nTERCERO.- Los vehículos registrados o procedentes de otras entidades federativas o del extranjero, no podrán ser sancionados por esta causa, pero están obligados a no rebasar\nMexicanas.\nCUARTO.- El presente Decreto entrará en vigor al día siguiente de su publicación en el Periódico Oficial del Estado.\nDADO en el Salón de Sesiones “Lic. Benito Juárez García” del H. Poder Legislativo del Estado de Baja California, en la Ciudad de Mexicali, B.C., a los quince días del mes de enero del año dos mil trece.\nDIP. ELISA ROSANA SOTO AGÜERO\nPRESIDENTE\n(RÚBRICA)\nDIP. FAUSTO ZÁRATE ZEPEDA\nSECRETARIO\n(RÚBRICA)\nDE CONFORMIDAD CON LO DISPUESTO POR LA FRACCIÓN I DEL ARTÍCULO 49\nMEXICALI, BAJA CALIFORNIA, A LOS CUATRO DÍAS DEL MES DE SEPTIEMBRE\nDEL AÑO DOS MIL DOCE.\nJOSÉ GUADALUPE OSUNA MILLÁN\nGOBERNADOR DEL ESTADO\n(RÚBRICA)\nFRANCISCO ANTONIO GARCÍA BURGOS\nSECRETARIO GENERAL DE GOBIERNO\n(RÚBRICA)\nARTÍCULO SEGUNDO TRANSITORIO DEL DECRETO No. 436, POR EL QUE SE\nREFORMA EL ARTÍCULO 8, PUBLICADO EN EL PERIÓDICO OFICIAL No. 18, TOMO\nLEGISLATURA, SIENDO GOBERNADOR CONSTITUCIONAL EL C. JOSÉ GUADALUPE\nOSUNA MILLÁN 2007-2013.\nARTÍCULOS TRANSITORIOS\nPRIMERO.- La presente reforma entrará en vigor al día siguiente de su publicación en el Periódico Oficial del Estado.\nLey de Protección al Ambiente para el Estado de Baja California. Página 120\nSEGUNDO.- La Secretaría de Protección al Ambiente para el Estado de Baja\nCalifornia tendrá un plazo de 90 días para determinar las reglas de operación bajo las cuales se realizarán dichos estudios. del Estado de Baja California, en la Ciudad de Mexicali, B.C., a los doce días del mes de marzo del año dos mil trece.\nDIP. ALFONSO GARZÓN ZATARAIN\nVICEPRESIDENTE\n(RÚBRICA)\nDIP. MARCO ANTONIO VIZCARRA CALDERÓN\nSECRETARIO\n(RÚBRICA)\nDE CONFORMIDAD CON LO DISPUESTO POR LA FRACCIÓN I DEL ARTÍCULO 49\nMEXICALI, BAJA CALIFORNIA, A LOS VEINTE DÍAS DEL MES DE MARZO DEL\nAÑO DOS MIL TRECE.\nJOSÉ GUADALUPE OSUNA MILLÁN\nGOBERNADOR DEL ESTADO\n(RÚBRICA)\nFRANCISCO ANTONIO GARCÍA BURGOS\nSECRETARIO GENERAL DE GOBIERNO\n(RÚBRICA)\nARTÍCULO SEGUNDO TRANSITORIO DEL DECRETO No. 455, POR EL QUE SE\nREFORMA EL ARTÍCULO 39, PUBLICADO EN EL PERIÓDICO OFICIAL No. 24, TOMO\nLEGISLATURA, SIENDO GOBERNADOR CONSTITUCIONAL EL C. JOSÉ GUADALUPE\nOSUNA MILLÁN 2007-2013.\nARTÍCULOS TRANSITORIOS\nPRIMERO.- El presente decreto entrará en vigor al día siguiente de su publicación en el Periódico Oficial del Estado. ámbito de su competencia, deberán expedir en un plazo no mayor a 60 días el Reglamento\nLey de Protección al Ambiente para el Estado de Baja California. Página 121 de Operación de los Fondos Ambientales establecidos en los artículos 3, 13, 38, 39 y 104 de la Ley de Protección al Ambiente para el Estado de Baja California. del Estado de Baja California, en la Ciudad de Mexicali, B.C., a los veintitrés días del mes de abril del año dos mil trece.\nDIP. ALFONSO GARZÓN ZATARAIN\nVICEPRESIDENTE\n(RÚBRICA)\nDIP. MARCO ANTONIO VIZCARRA CALDERÓN\nSECRETARIO\n(RÚBRICA)\nDE CONFORMIDAD CON LO DISPUESTO POR LA FRACCIÓN I DEL ARTÍCULO 49\nMEXICALI, BAJA CALIFORNIA, A LOS TREINTA DÍAS DEL MES DE ABRIL DEL\nAÑO DOS MIL TRECE.\nJOSÉ GUADALUPE OSUNA MILLÁN\nGOBERNADOR DEL ESTADO\n(RÚBRICA)\nFRANCISCO ANTONIO GARCÍA BURGOS\nSECRETARIO GENERAL DE GOBIERNO\n(RÚBRICA)\nARTÍCULO PRIMERO TRANSITORIO DEL DECRETO No. 491, POR EL QUE SE\nREFORMA EL ARTÍCULO 3 FRACCIÓN VIII Y SE ADICIONA UNA FRACCIÓN IX,\nPUBLICADO EN EL PERIÓDICO OFICIAL No. 34, TOMO CXX, SECCION I, DE FECHA 02\nGOBERNADOR CONSTITUCIONAL EL C. JOSÉ GUADALUPE OSUNA MILLÁN 2007-\n2013.\nARTÍCULO TRANSITORIO\nÚNICO.- La presente reforma entrará en vigor al día siguiente de su publicación en el del Estado de Baja California, en la Ciudad de Mexicali, B.C., a los once días del mes de julio del año dos mil trece.\nLey de Protección al Ambiente para el Estado de Baja California. Página 122\nDIP. GREGORIO CARRANZA HERNÁNDEZ\nPRESIDENTE\n(RÚBRICA)\nDIP. MARCO ANTONIO VIZCARRA CALDERÓN\nSECRETARIO\n(RÚBRICA)\nDE CONFORMIDAD CON LO DISPUESTO POR LA FRACCIÓN I DEL ARTÍCULO 49\nMEXICALI, BAJA CALIFORNIA, A LOS DIECIOCHO DÍAS DEL MES DE JULIO DEL\nAÑO DOS MIL TRECE.\nJOSÉ GUADALUPE OSUNA MILLÁN\nGOBERNADOR DEL ESTADO\n(RÚBRICA)\nFRANCISCO ANTONIO GARCÍA BURGOS\nSECRETARIO GENERAL DE GOBIERNO\n(RÚBRICA)\nARTÍCULO UNICO TRANSITORIO DEL DECRETO No. 510, POR EL QUE SE\nREFORMA EL ARTÍCULO 2, PUBLICADO EN EL PERIÓDICO OFICIAL No. 39, TOMO\nCXX, DE FECHA 06 DE SEPTIEMBRE DE 2013, EXPEDIDO POR LA H. XX\nLEGISLATURA, SIENDO GOBERNADOR CONSTITUCIONAL EL C. JOSÉ GUADALUPE\nOSUNA MILLÁN 2007-2013.\nARTÍCULO TRANSITORIO\nÚNICO.- El presente Decreto entrará en vigor el día de su publicación en el Periódico\nOficial del Estado. del Estado de Baja California, en la Ciudad de Mexicali, B.C., a los seis días del mes de agosto del año dos mil trece.\nDIP. GREGORIO CARRANZA HERNÁNDEZ\nPRESIDENTE\n(RÚBRICA)\nDIP. MARCO ANTONIO VIZCARRA CALDERÓN\nSECRETARIO\nLey de Protección al Ambiente para el Estado de Baja California. Página 123\n(RÚBRICA)\nDE CONFORMIDAD CON LO DISPUESTO POR LA FRACCIÓN I DEL ARTÍCULO 49\nMEXICALI, BAJA CALIFORNIA, A LOS VEINTIDOS DÍAS DEL MES DE AGOSTO\nDEL AÑO DOS MIL TRECE.\nJOSÉ GUADALUPE OSUNA MILLÁN\nGOBERNADOR DEL ESTADO\n(RÚBRICA)\nFRANCISCO ANTONIO GARCÍA BURGOS\nSECRETARIO GENERAL DE GOBIERNO\n(RÚBRICA)\nARTÍCULO SEGUNDO TRANSITORIO DEL DECRETO No. 28, POR EL QUE SE\nREFORMA EL ARTÍCULO 118; PUBLICADO EN EL PERIÓDICO OFICIAL No. 60,\nSECCIÓN VIII, TOMO CXX, DE FECHA 31 DE DICIEMBRE DE 2013, EXPEDIDO POR LA\nH. XXI LEGISLATURA, SIENDO GOBERNADOR CONSTITUCIONAL EL C. FRANCISCO\nARTURO VEGA DE LA MADRID 2013-2019.\nARTÍCULOS TRANSITORIOS\nPRIMERO.- El presente Decreto entrará en vigor el día de su publicación en el\nPeriódico Oficial del Estado.\nSEGUNDO.- No se encontrarán obligados a la realización de la verificación vehicular exigida conforme a la Ley de Protección al Ambiente para el Estado de Baja California, y a la\nLey que Regula los Servicios de Control Vehicular en el Estado de Baja California, los propietarios o poseedores de vehículos con domicilio y registro vehicular en los valles de\nEnsenada, San Felipe, el Valle de Mexicali y Delegaciones Municipales del Municipio de\nTecate, dado que no existen centros de verificación vehicular en dichas localidades.\nTERCERO.- Por esta única ocasión, durante el ejercicio fiscal 2014, los propietarios o obligatoria en términos del Programa de Verificación Vehicular Obligatoria 2014, serán objeto de una multa de cinco salarios mínimos vigentes en la entidad, misma que se hará\nFinanzas del Estado, mediante el Procedimiento Administrativo de Ejecución correspondiente, salvo que dentro de este periodo se expidan las disposiciones reglamentarias municipales correspondientes en los respectivos ámbitos competenciales.\nArtículo Transitorio Reformado\nLey de Protección al Ambiente para el Estado de Baja California. Página 124 del Estado de Baja California, en la Ciudad de Mexicali, B.C., a los veinticuatro días del mes de diciembre del año dos mil trece.\nDIP. CUAUHTÉMOC CARDONA BENAVIDES\nPRESIDENTE\n(RÚBRICA)\nDIP. JOSÉ ALBERTO MARTINEZ CARRILLO\nSECRETARIO\n(RÚBRICA)\nDE CONFORMIDAD CON LO DISPUESTO POR LA FRACCIÓN I DEL ARTÍCULO 49\nMEXICALI, BAJA CALIFORNIA, A LOS VEINTISÉIS DÍAS DEL MES DE DICIEMBRE\nDEL AÑO DOS MIL TRECE.\nFRANCISCO ARTURO VEGA DE LA MADRID\nGOBERNADOR DEL ESTADO\n(RÚBRICA)\nGUILLERMO TREJO DOZAL\nSECRETARIO GENERAL DE GOBIERNO\n(RÚBRICA)\nARTÍCULO SEGUNDO TRANSITORIO DEL DECRETO No. 38, POR EL QUE SE\nADICIONA EL ARTÍCULO TERCERO TRANSITORIO AL DECRETO No. 28; DEL 31 DE\nDICIEMBRE DE 2013, SECCIÓN VIII; PUBLICADO EN EL PERIÓDICO OFICIAL No. 04,\nSECCIÓN I, TOMO CXXI, DE FECHA 24 DE ENERO DE 2014, EXPEDIDO POR LA H. XXI\nLEGISLATURA, SIENDO GOBERNADOR CONSTITUCIONAL EL C. FRANCISCO\nARTURO VEGA DE LA MADRID 2013-2019.\nARTÍCULOS TRANSITORIOS\nPRIMERO: El presente Decreto entrará en vigor el día de su publicación en el\nPeriódico Oficial del Estado.\nSEGUNDO.- A partir de la vigencia del presente Decreto y dentro de los 100 días naturales contado a partir de su publicación, quienes realicen el canje de tarjetas de circulación de vehículos, no les será exigible el requisito a que hace referencia el artículo 29 fracción VII, de la Ley que Regula los Servicios de Control Vehicular en el Estado de Baja\nCalifornia.\nLey de Protección al Ambiente para el Estado de Baja California. Página 125\nTERCERO.- Los propietarios o poseedores de los automóviles que durante el 2012 y\n2013 hubieren realizado la verificación vehicular conforme a los programas respectivos, estarán exentos de acreditar dicho requisito, para el canje de tarjeta de circulación.\nCUARTO.- El Ejecutivo del Estado deberá adoptar de manera inmediata las medidas necesarias para la correcta aplicación del presente Decreto, debiendo en su caso, modificar el Programa de Verificación Vehicular 2014.\nDADO en el Salón de Sesiones “Lic. Benito Juárez García” del H. Poder Legislativo del Estado de Baja California, en la Ciudad de Mexicali, B.C., a los dieciséis días del mes de enero del año dos mil catorce.\nDIP. CUAUHTÉMOC CARDONA BENAVIDES\nPRESIDENTE\n(RÚBRICA)\nDIP. JOSÉ ALBERTO MARTINEZ CARRILLO\nSECRETARIO\n(RÚBRICA)\nDE CONFORMIDAD CON LO DISPUESTO POR LA FRACCIÓN I DEL ARTÍCULO 49\nMEXICALI, BAJA CALIFORNIA, A LOS VEINTE DÍAS DEL MES DE ENERO DEL\nAÑO DOS MIL CATORCE.\nFRANCISCO ARTURO VEGA DE LA MADRID\nGOBERNADOR DEL ESTADO\n(RÚBRICA)\nGUILLERMO TREJO DOZAL\nSECRETARIO GENERAL DE GOBIERNO\n(RÚBRICA)\nARTÍCULO PRIMERO TRANSITORIO DEL DECRETO No. 66, POR EL QUE SE\nREFORMAN LOS ARTICULOS 2, 9, 10, 38, 112 Y 113, PUBLICADO EN EL PERIÓDICO\nEXPEDIDO POR LA H. XXI LEGISLATURA, SIENDO GOBERNADOR CONSTITUCIONAL\nEL C. FRANCISCO ARTURO VEGA DE LA MADRID 2013-2019.\nARTÍCULO TRANSITORIO\nÚNICO.- Las presentes reformas entrarán en vigor el día siguiente al de su publicación en el Periódico Oficial del Estado.\nLey de Protección al Ambiente para el Estado de Baja California. Página 126 del Estado de Baja California, en la Ciudad de Mexicali, B.C., a los diecinueve días del mes de junio del año dos mil catorce.\nDIP. FELIPE DE JESÚS MAYORAL MAYORAL\nPRESIDENTE\n(RÚBRICA)\nDIP. GERARDO ÁLVAREZ HERNÁNDEZ\nSECRETARIO\n(RÚBRICA)\nDE CONFORMIDAD CON LO DISPUESTO POR LA FRACCIÓN I DEL ARTÍCULO 49\nMEXICALI, BAJA CALIFORNIA, A LOS VEINTITRES DÍAS DEL MES DE JULIO DEL\nAÑO DOS MIL CATORCE.\nFRANCISCO ARTURO VEGA DE LA MADRID\nGOBERNADOR DEL ESTADO\n(RÚBRICA)\nGUILLERMO TREJO DOZAL\nSECRETARIO GENERAL DE GOBIERNO\n(RÚBRICA)\nARTÍCULO UNICO TRANSITORIO DEL DECRETO No. 67, POR EL QUE SE\nREFORMA EL ARTÍCULO 2 Y QUE SE ADICIONA UN CAPÍTULO IV, AL TÍTULO\nTERCERO DENOMINADO DE LAS “ÁREAS VERDES URBANAS”, ASÍ COMO LOS\nARTÍCULOS 106 TER, 106 TER 1, 106 TER 2, 106 TER 3 Y LA MODIFICACIÓN DEL\nARTICULO 187 FRACCIÓN IV, PUBLICADO EN EL PERIÓDICO OFICIAL No. 39,\nXXI LEGISLATURA, SIENDO GOBERNADOR CONSTITUCIONAL EL C. FRANCISCO\nARTURO VEGA DE LA MADRID 2013-2019.\nARTÍCULOS TRANSITORIOS\nPRIMERO.- Las presentes reformas entrarán en vigor al día siguiente de su publicación en el Periódico Oficial del Estado.\nSEGUNDO.- En un plazo no mayor al de seis meses contados a partir de la entrada en vigor de las presentes reformas, el Estado y los Ayuntamientos dentro de sus respectivos ámbitos de competencia, deberán emitir las disposiciones reglamentarias correspondientes.\nLey de Protección al Ambiente para el Estado de Baja California. Página 127 del Estado de Baja California, en la Ciudad de Mexicali, B.C., a los diecinueve días del mes de junio del año dos mil catorce.\nDIP. FELIPE DE JESÚS MAYORAL MAYORAL\nPRESIDENTE\n(RÚBRICA)\nDIP. GERARDO ÁLVAREZ HERNÁNDEZ\nSECRETARIO\n(RÚBRICA)\nDE CONFORMIDAD CON LO DISPUESTO POR LA FRACCIÓN I DEL ARTÍCULO 49\nMEXICALI, BAJA CALIFORNIA, A LOS VEINTITRES DÍAS DEL MES DE JULIO DEL\nAÑO DOS MIL CATORCE.\nFRANCISCO ARTURO VEGA DE LA MADRID\nGOBERNADOR DEL ESTADO\n(RÚBRICA)\nGUILLERMO TREJO DOZAL\nSECRETARIO GENERAL DE GOBIERNO\n(RÚBRICA)\nARTÍCULO SEGUNDO TRANSITORIO DEL DECRETO No. 251, POR EL QUE SE\nADICIONA UN ARTÍCULO 106 BIS 3, PUBLICADO EN EL PERIÓDICO OFICIAL No. 28,\nTOMO CXXII, DE FECHA 12 DE JUNIO DE 2015, EXPEDIDO POR LA H. XXI\nLEGISLATURA, SIENDO GOBERNADOR CONSTITUCIONAL EL C. FRANCISCO\nARTURO VEGA DE LAMADRID 2013-2019.\nARTÍCULOS TRANSITORIOS\nPRIMERO.- Las presentes reformas entrarán en vigor el día 08 de julio del año 2015.\nSEGUNDO.- Los Municipios del Estado, a través de sus Ayuntamientos, emitirán las disposiciones reglamentarias correspondientes en un término que no exceda de 180 días naturales, computados a partir de la fecha en que entre en vigor la presente reforma. del Estado de Baja California, en la Ciudad de Mexicali, B.C., a los 07 días del mes de mayo del año dos mil quince.\nLey de Protección al Ambiente para el Estado de Baja California. Página 128\nDIP. FCO. ALCIBÍADES GARCÍA LIZARDI\nPRESIDENTE\n(RÚBRICA)\nDIP. ROSALBA LÓPEZ REGALADO\nSECRETARIA\n(RÚBRICA)\nDE CONFORMIDAD CON LO DISPUESTO POR LA FRACCION I DEL ARTÍCULO 49\nMEXICALI, BAJA CALIFORNIA, A LOS VEINTISIETE DÍAS DEL MES DE MAYO DEL\nAÑO DOS MIL QUINCE.\nFRANCISCO ARTURO VEGA DE LAMADRID\nGOBERNADOR DEL ESTADO\n(RÚBRICA)\nFRANCISCO RUEDA GOMEZ\nSECRETARIO GENERAL DE GOBIERNO\n(RÚBRICA)\nARTÍCULO UNICO TRANSITORIO DEL DECRETO No. 328, POR EL QUE SE\nADICIONA EL ARTÍCULO 15 BIS, PUBLICADO EN EL PERIÓDICO OFICIAL No. 47,\nTOMO CXXII, DE FECHA 09 DE OCTUBRE DE 2015, EXPEDIDO POR LA H. XXI\nLEGISLATURA, SIENDO GOBERNADOR CONSTITUCIONAL EL C. FRANCISCO\nARTURO VEGA DE LAMADRID 2013-2019.\nARTÍCULOS TRANSITORIOS\nPRIMERO.- La presente reforma entrará en vigor al día siguiente de su publicación en el Periódico Oficial del Estado de Baja California.\nSEGUNDO.- Los Poderes Legislativo, Judicial y Ejecutivo, así como los Municipios del Estado, contarán con 120 días contados a partir de la entrada en vigor de la reforma, para expedir sus manuales de sistemas de manejo ambiental. del Estado de Baja California, en la Ciudad de Mexicali, B.C., a los diez días del mes de septiembre del año dos mil quince.\nDIP. JULIO CÉSAR VÁZQUEZ CASTILLO\nPRESIDENTE\n(RÚBRICA)\nLey de Protección al Ambiente para el Estado de Baja California. Página 129\nDIP. RODOLFO OLIMPO HERNÁNDEZ BOJÓRQUEZ\nSECRETARIO\n(RÚBRICA)\nDE CONFORMIDAD CON LO DISPUESTO POR LA FRACCION I DEL ARTÍCULO 49\nMEXICALI, BAJA CALIFORNIA, A LOS DIECISIETE DÍAS DEL MES DE\nSEPTIEMBRE DEL AÑO DOS MIL QUINCE.\nFRANCISCO ARTURO VEGA DE LAMADRID\nGOBERNADOR DEL ESTADO\n(RÚBRICA)\nFRANCISCO RUEDA GOMEZ\nSECRETARIO GENERAL DE GOBIERNO\n(RÚBRICA)\nARTÍCULO UNICO TRANSITORIO DEL DECRETO No. 457, POR EL QUE SE\nREFORMA EL ARTÍCULO 141, PUBLICADO EN EL PERIÓDICO OFICIAL No. 13,\nSECCION IV, TOMO CXXIII, DE FECHA 11 DE MARZO DE 2016, EXPEDIDO POR LA H.\nXXI LEGISLATURA, SIENDO GOBERNADOR CONSTITUCIONAL EL C. FRANCISCO\nARTURO VEGA DE LAMADRID 2013-2019.\nARTÍCULO TRANSITORIO\nUNICO.- La presente reforma entrará en vigor dentro de dieciocho meses, contados a partir del día siguiente de su publicación en el Periódico Oficial del Estado de Baja California.\nDADO en el Salón de Sesiones “Lic. Benito Juárez García” del H. Poder Legislativo del Estado de Baja California, en la Ciudad de Mexicali, B.C., a los veinticinco días del mes de febrero del año dos mil dieciséis.\nDIP. RODOLFO OLIMPO HERNÁNDEZ BOJÓRQUEZ\nPRESIDENTE\n(RÚBRICA)\nDIP. ARMANDO REYES LEDESMA\nSECRETARIO\n(RÚBRICA)\nDE CONFORMIDAD CON LO DISPUESTO POR LA FRACCION I DEL ARTÍCULO 49 DE\nLey de Protección al Ambiente para el Estado de Baja California. Página 130\nMEXICALI, BAJA CALIFORNIA, A LOS NUEVE DÍAS DEL MES DE MARZO DEL\nAÑO DOS MIL DIECISÉIS.\nFRANCISCO ARTURO VEGA DE LAMADRID\nGOBERNADOR DEL ESTADO\n(RÚBRICA)\nFRANCISCO RUEDA GOMEZ\nSECRETARIO GENERAL DE GOBIERNO\n(RÚBRICA)\nARTÍCULO PRIMERO TRANSITORIO DEL DECRETO No. 458, POR EL QUE SE\nREFORMAN LOS ARTÍCULOS 8, 27, 29 Y 39, ASIMISMO SE ADICIONA UNA SECCIÓN IV\nAL TÍTULO TERCERO; PUBLICADO EN EL PERIÓDICO OFICIAL No. 14, SECCION V,\nTOMO CXXIII, DE FECHA 18 DE MARZO DE 2016, EXPEDIDO POR LA H. XXI\nLEGISLATURA, SIENDO GOBERNADOR CONSTITUCIONAL EL C. FRANCISCO\nARTURO VEGA DE LAMADRID 2013-2019.\nARTÍCULO TRANSITORIO\nÚNICO: La presente reforma a los artículos 8, 27, 29 y 39 y la adición de la Sección\nIV denominada Corredores Biológicos al Título Tercero a la Ley de Protección al Ambiente para el Estado de Baja California, entrará en vigor al día siguiente al de su publicación en el\nPeriódico Oficial del Estado.\nDADO en el Salón de Sesiones “Lic. Benito Juárez García” del H. Poder Legislativo del Estado de Baja California, en la Ciudad de Mexicali, B.C., a los veinticinco días del mes de febrero del año dos mil dieciséis.\nDIP. RODOLFO OLIMPO HERNÁNDEZ BOJÓRQUEZ\nPRESIDENTE\n(RÚBRICA)\nDIP. ARMANDO REYES LEDESMA\nSECRETARIO\n(RÚBRICA)\nDE CONFORMIDAD CON LO DISPUESTO POR LA FRACCION I DEL ARTÍCULO 49\nMEXICALI, BAJA CALIFORNIA, A LOS NUEVE DÍAS DEL MES DE MARZO DEL\nAÑO DOS MIL DIECISÉIS.\nFRANCISCO ARTURO VEGA DE LAMADRID\nGOBERNADOR DEL ESTADO\n(RÚBRICA)\nLey de Protección al Ambiente para el Estado de Baja California. Página 131\nFRANCISCO RUEDA GOMEZ\nSECRETARIO GENERAL DE GOBIERNO\n(RÚBRICA)\nARTÍCULO ÚNICO TRANSITORIO DEL DECRETO No. 508, POR EL QUE SE\nREFORMA LA FRACCIÓN XVI Y SE RECORRE LA SIGUIENTE FRACCIÓN XVII, AL\nARTÍCULO 112; PUBLICADO EN EL PERIÓDICO OFICIAL No. 34, SECCIÓN VI, TOMO\nCXXIII, DE FECHA 29 DE JULIO DE 2016, EXPEDIDO POR LA H. XXI LEGISLATURA,\nSIENDO GOBERNADOR CONSTITUCIONAL EL C. FRANCISCO ARTURO VEGA DE\nLAMADRID 2013-2019.\nARTÍCULO TRANSITORIO\nÚNICO.- El presente decreto entrará en vigor el día siguiente de su publicación en el\nPeriódico Oficial del Estado.\nDADO en el Salón de Sesiones “Lic. Benito Juárez García” del H. Poder Legislativo del Estado de Baja California, en la Ciudad de Mexicali, B.C., a los veintitrés días del mes de\nJunio del año dos mil dieciséis.\nDIP. MÓNICA BEDOYA SERNA\nPRESIDENTA\n(RÚBRICA)\nDIP. ROSA ISELA PERALTA CASILLAS\nSECRETARIA\n(RÚBRICA)\nDE CONFORMIDAD CON LO DISPUESTO POR LA FRACCIÓN I DEL ARTÍCULO 49\nMEXICALI, BAJA CALIFORNIA, A LOS SEIS DÍAS DEL MES DE JULIO DEL AÑO\nDOS MIL DIECISÉIS.\nFRANCISCO RUEDA GÓMEZ\nSECRETARIO GENERAL DE GOBIERNO\nEstado, con fundamento en los artículos 45 y 52\n(RÚBRICA)\nLORETO QUINTERO QUINTERO\nOFICIAL MAYOR DE GOBIERNO\nLey de Protección al Ambiente para el Estado de Baja California. Página 132 de Gobierno, con fundamento en los artículos 54 de la\n(RÚBRICA)\nARTÍCULO ÚNICO TRANSITORIO DEL DECRETO No. 509, POR EL QUE SE\nADICIONA EL ARTÍCULO 111 BIS; PUBLICADO EN EL PERIÓDICO OFICIAL No. 34,\nSECCIÓN VI, TOMO CXXIII, DE FECHA 29 DE JULIO DE 2016, EXPEDIDO POR LA H. XXI\nLEGISLATURA, SIENDO GOBERNADOR CONSTITUCIONAL EL C. FRANCISCO\nARTURO VEGA DE LAMADRID 2013-2019.\nARTÍCULO TRANSITORIO\nÚNICO.- El presente Decreto entrará en vigor al día siguiente de su publicación en el\nPeriódico Oficial del Estado de Baja California.\nDADO en el Salón de Sesiones “Lic. Benito Juárez García” del H. Poder Legislativo del Estado de Baja California, en la Ciudad de Mexicali, B.C., a los veintitrés días del mes de\nJunio del año dos mil dieciséis.\nDIP. MÓNICA BEDOYA SERNA\nPRESIDENTA\n(RÚBRICA)\nDIP. ROSA ISELA PERALTA CASILLAS\nSECRETARIA\n(RÚBRICA)\nDE CONFORMIDAD CON LO DISPUESTO POR LA FRACCIÓN I DEL ARTÍCULO 49\nMEXICALI, BAJA CALIFORNIA, A LOS SEIS DÍAS DEL MES DE JULIO DEL AÑO\nDOS MIL DIECISÉIS.\nFRANCISCO RUEDA GÓMEZ\nSECRETARIO GENERAL DE GOBIERNO\nEstado, con fundamento en los artículos 45 y 52\n(RÚBRICA)\nLORETO QUINTERO QUINTERO\nOFICIAL MAYOR DE GOBIERNO\nLey de Protección al Ambiente para el Estado de Baja California. Página 133 de Gobierno, con fundamento en los artículos 54 de la\n(RÚBRICA)\nARTÍCULO ÚNICO TRANSITORIO DEL DECRETO No. 627, POR EL QUE SE\nREFORMA EL ARTÍCULO 106 BIS; PUBLICADO EN EL PERIÓDICO OFICIAL No. 47,\nSECCIÓN V, TOMO CXXIII, DE FECHA 21 DE OCTUBRE DE 2016, EXPEDIDO POR LA H.\nXXI LEGISLATURA, SIENDO GOBERNADOR CONSTITUCIONAL EL C. FRANCISCO\nARTURO VEGA DE LAMADRID 2013-2019.\nARTÍCULO TRANSITORIO\nÚNICO.- La presente reforma entrará en vigor al día siguiente de su publicación en el\nPeriódico Oficial del Estado de Baja California.\nDADO en el Salón de Sesiones “Lic. Benito Juárez García” del H. Poder Legislativo del Estado de Baja California, en la Ciudad de Mexicali, B.C., a los veintitdos días del mes de septiembre del año dos mil dieciséis.\nDIP. MÓNICA BEDOYA SERNA\nPRESIDENTA\n(RÚBRICA)\nDIP. ROSA ISELA PERALTA CASILLAS\nSECRETARIA\n(RÚBRICA)\nDE CONFORMIDAD CON LO DISPUESTO POR LA FRACCIÓN I DEL ARTÍCULO 49\nMEXICALI, BAJA CALIFORNIA, A LOS TRES DÍAS DEL MES DE OCTUBRE DEL\nAÑO DOS MIL DIECISÉIS.\nFRANCISCO ARTURO VEGA DE LAMADRID\nGOBERNADOR DEL ESTADO\n(RÚBRICA)\nFRANCISCO RUEDA GÓMEZ\nSECRETARIO GENERAL DE GOBIERNO\n(RÚBRICA)\nARTÍCULO ÚNICO TRANSITORIO DEL DECRETO No. 149, POR EL QUE SE\nADICIONA UNA FRACCIÓN X AL ARTÍCULO 113 Y UNA FRACCIÓN IX AL ARTÍCULO\n136; PUBLICADO EN EL PERIÓDICO OFICIAL No. 50, SECCIÓN III, TOMO CXXIV, DE\nLey de Protección al Ambiente para el Estado de Baja California. Página 134\nSIENDO GOBERNADOR CONSTITUCIONAL EL C. FRANCISCO ARTURO VEGA DE\nLAMADRID 2013-2019.\nARTÍCULO TRANSITORIO\nPRIMERO.- Las presentes reformas entraran en vigor al día siguiente de su publicación en el Periódico Oficial del Estado.\nSEGUNDO.- Los ayuntamientos tendrán un plazo no mayor de 90 (noventa) días hábiles para la realización de la adecuaciones necesarias de sus reglamentos municipales.\nDADO en el Salón de Sesiones “Lic. Benito Juárez García” del H. Poder Legislativo del Estado de Baja California, en la Ciudad de Mexicali, B.C., a los doce días del mes de octubre del año dos mil diecisiete.\nDIP. EDGAR BENJAMÍN GÓMEZ MACÍAS\nPRESIDENTE\n(RÚBRICA)\nDIP. EVA MARÍA VÁSQUEZ HERNÁNDEZ\nSECRETARIA\n(RÚBRICA)\nDE CONFORMIDAD CON LO DISPUESTO POR LA FRACCIÓN I DEL ARTÍCULO 49\nMEXICALI, BAJA CALIFORNIA, A LOS DIECISIETE DÍAS DE OCTUBRE DEL AÑO DOS\nMIL DIECISIETE.\nFRANCISCO ARTURO VEGA DE LAMADRID\nGOBERNADOR DEL ESTADO\n(RÚBRICA)\nFRANCISCO RUEDA GÓMEZ\nSECRETARIO GENERAL DE GOBIERNO\n(RÚBRICA)\nARTÍCULO ÚNICO TRANSITORIO DEL DECRETO No. 150, POR EL QUE SE\nREFORMA EL ARTÍCULO 19; PUBLICADO EN EL PERIÓDICO OFICIAL No. 50, SECCIÓN\nLEGISLATURA, SIENDO GOBERNADOR CONSTITUCIONAL EL C. FRANCISCO\nARTURO VEGA DE LAMADRID 2013-2019.\nARTÍCULO TRANSITORIO\nLey de Protección al Ambiente para el Estado de Baja California. Página 135\nPRIMERO.- La presente reforma entrará en vigor al día siguiente de su publicación en el Periódico Oficial del Estado.\nSEGUNDO.- El Consejo a que se refiere el presente decreto, deberá aprobar el reforma.\nDADO en el Salón de Sesiones “Lic. Benito Juárez García” del H. Poder Legislativo del Estado de Baja California, en la Ciudad de Mexicali, B.C., a los doce días del mes de octubre del año dos mil diecisiete.\nDIP. EDGAR BENJAMÍN GÓMEZ MACÍAS\nPRESIDENTE\n(RÚBRICA)\nDIP. EVA MARÍA VÁSQUEZ HERNÁNDEZ\nSECRETARIA\n(RÚBRICA)\nDE CONFORMIDAD CON LO DISPUESTO POR LA FRACCIÓN I DEL ARTÍCULO 49\nMEXICALI, BAJA CALIFORNIA, A LOS DIECISIETE DÍAS DE OCTUBRE DEL AÑO\nDOS MIL DIECISIETE.\nFRANCISCO ARTURO VEGA DE LAMADRID\nGOBERNADOR DEL ESTADO\n(RÚBRICA)\nFRANCISCO RUEDA GÓMEZ\nSECRETARIO GENERAL DE GOBIERNO\n(RÚBRICA)\nARTÍCULO ÚNICO TRANSITORIO DEL DECRETO No. 203, POR EL QUE SE\nREFORMA EL ARTÍCULO 112 FRACCIÓN XVI; PUBLICADO EN EL PERIÓDICO OFICIAL\nLA H. XXII LEGISLATURA, SIENDO GOBERNADOR CONSTITUCIONAL EL C.\nFRANCISCO ARTURO VEGA DE LAMADRID 2013-2019.\nARTÍCULO TRANSITORIO\nÚNICO.- Las presentes reformas entrarán en vigor al día siguiente de su publicación en el Periódico Oficial del Estado.\nLey de Protección al Ambiente para el Estado de Baja California. Página 136 del Estado de Baja California, en la Ciudad de Mexicali, B.C., al primer día del mes de marzo del año dos mil dieciocho.\nDIP. MTRO. RAÚL CASTAÑEDA POMPOSO\nPRESIDENTE\n(RÚBRICA)\nDIP. ROCÍO LÓPEZ GOROSAVE\nSECRETARIA\n(RÚBRICA)\nDE CONFORMIDAD CON LO DISPUESTO POR LA FRACCIÓN I DEL ARTÍCULO 49\nMEXICALI, BAJA CALIFORNIA, A LOS DIEZ Y NUEVE DÍAS DEL MES DE ABRIL\nDEL AÑO DOS MIL DIECIOCHO.\nFRANCISCO ARTURO VEGA DE LAMADRID\nGOBERNADOR DEL ESTADO\n(RÚBRICA)\nFRANCISCO RUEDA GÓMEZ\nSECRETARIO GENERAL DE GOBIERNO\n(RÚBRICA)\nARTÍCULO ÚNICO TRANSITORIO DEL DECRETO No. 254, POR EL QUE SE\nADICIONAN LOS ARTÍCULOS 141 BIS Y 141 TER; PUBLICADO EN EL PERIÓDICO\nOFICIAL No. 7, SECCIÓN III, TOMO CXXVI, DE FECHA 01 DE FEBRERO DE 2019,\nEXPEDIDO POR LA H. XXII LEGISLATURA, SIENDO GOBERNADOR CONSTITUCIONAL\nEL C. FRANCISCO ARTURO VEGA DE LAMADRID 2013-2019.\nARTÍCULO TRANSITORIO\nÚNICO.- El presente decreto entrará en vigor a partir del día siguiente de su publicación en el Periódico Oficial del Estado de Baja California. del Estado de Baja California, en la Ciudad de Mexicali, B.C., a los seis día del mes de septiembre del año dos mil dieciocho.\nDIP. ROCÍO LÓPEZ GOROSAVE\nPRESIDENTA\n(RÚBRICA)\nDIP. MÓNICA HERNÁNDEZ ÁLVAREZ\nSECRETARIA\nLey de Protección al Ambiente para el Estado de Baja California. Página 137\n(RÚBRICA)\nDE CONFORMIDAD CON LO DISPUESTO POR LA FRACCIÓN I DEL ARTÍCULO 49\nMEXICALI, BAJA CALIFORNIA, A LOS TREINTA Y UN DÍAS DEL MES DE ENERO\nDEL AÑO DOS MIL DIECINUEVE.\nFRANCISCO ARTURO VEGA DE LAMADRID\nGOBERNADOR DEL ESTADO\n(RÚBRICA)\nFRANCISCO RUEDA GÓMEZ\nSECRETARIO GENERAL DE GOBIERNO\n(RÚBRICA)\nARTÍCULO ÚNICO TRANSITORIO DEL DECRETO No. 255, POR EL QUE SE\nAPRUEBA LA REFORMA DE ADICIÓN AL ARTÍCULO 67; PUBLICADO EN EL PERIÓDICO\nOFICIAL No. 7, SECCIÓN III, TOMO CXXVI, DE FECHA 01 DE FEBRERO DE 2019,\nEXPEDIDO POR LA H. XXII LEGISLATURA, SIENDO GOBERNADOR CONSTITUCIONAL\nEL C. FRANCISCO ARTURO VEGA DE LAMADRID 2013-2019.\nARTÍCULO TRANSITORIO\nÚNICO.- El presente decreto entrará en vigor al día siguiente de su publicación en el\nPeriódico Oficial del Estado de Baja California.\nDADO en el Salón de Sesiones “Lic. Benito Juárez García” del H. Poder Legislativo del Estado de Baja California, en la Ciudad de Mexicali, B.C., a los seis día del mes de septiembre del año dos mil dieciocho.\nDIP. ROCÍO LÓPEZ GOROSAVE\nPRESIDENTA\n(RÚBRICA)\nDIP. MÓNICA HERNÁNDEZ ÁLVAREZ\nSECRETARIA\n(RÚBRICA)\nDE CONFORMIDAD CON LO DISPUESTO POR LA FRACCIÓN I DEL ARTÍCULO 49\nMEXICALI, BAJA CALIFORNIA, A LOS TREINTA Y UN DÍAS DEL MES DE ENERO\nDEL AÑO DOS MIL DIECINUEVE.\nFRANCISCO ARTURO VEGA DE LAMADRID\nLey de Protección al Ambiente para el Estado de Baja California. Página 138\nGOBERNADOR DEL ESTADO\n(RÚBRICA)\nFRANCISCO RUEDA GÓMEZ\nSECRETARIO GENERAL DE GOBIERNO\n(RÚBRICA)\nARTÍCULO ÚNICO TRANSITORIO DEL DECRETO No. 276, POR EL QUE SE\nAPRUEBA LA REFORMA A LOS ARTÍCULOS 8 Y 141; PUBLICADO EN EL PERIÓDICO\nOFICIAL No. 10, SECCIÓN III, TOMO CXXVI, DE FECHA 22 DE FEBRERO DE 2019,\nEXPEDIDO POR LA H. XXII LEGISLATURA, SIENDO GOBERNADOR CONSTITUCIONAL\nEL C. FRANCISCO ARTURO VEGA DE LAMADRID 2013-2019.\nARTÍCULO TRANSITORIO\nPRIMERO.- El presente decreto entrará en vigor a partir del día siguiente de su publicación en el Periódico Oficial del Estado.\nSEGUNDO.- Para la implementación de esta disposición, el Ejecutivo del Estado deberá elaborar las normas, programas y planes correspondientes que deberán establecer los criterios de eficiencia ambiental, tecnológica, económica y social bajo los principios de responsabilidad compartida.\nEstos ordenamientos deberán contener disposiciones aplicables a productores, distribuidores, comerciantes, consumidores, generadores de residuos de estos materiales.\nTERCERO.- Los productores, distribuidores y comerciantes de bolsas de plástico, contarán con trecientos sesenta y cinco días naturales después de la publicación del\nPresente Decreto para dar cumplimiento a lo establecido en el artículo 141 de la Ley de\nProtección al Ambiente para el Estado de Baja California.\nDADO en el Salón de Sesiones “Lic. Benito Juárez García” del H. Poder Legislativo del Estado de Baja California, en la Ciudad de Mexicali, B.C., a los veinticinco día del mes de octubre del año dos mil dieciocho.\nDIP. ROCÍO LÓPEZ GOROSAVE\nPRESIDENTA\n(RÚBRICA)\nDIP. MÓNICA HERNÁNDEZ ÁLVAREZ\nSECRETARIA\n(RÚBRICA)\nDE CONFORMIDAD CON LO DISPUESTO POR LA FRACCIÓN I DEL ARTÍCULO 49\nMEXICALI, BAJA CALIFORNIA, A LOS VEINTIDOS DÍAS DEL MES DE FEBRERO\nDEL AÑO DOS MIL DIECINUEVE.\nLey de Protección al Ambiente para el Estado de Baja California. Página 139\nFRANCISCO ARTURO VEGA DE LAMADRID\nGOBERNADOR DEL ESTADO\n(RÚBRICA)\nFRANCISCO RUEDA GÓMEZ\nSECRETARIO GENERAL DE GOBIERNO\n(RÚBRICA)\nARTÍCULO ÚNICO TRANSITORIO DEL DECRETO No. 172, POR EL QUE SE\nAPRUEBA LA REFORMA AL ARTÍCULO 2; PUBLICADO EN EL PERIÓDICO OFICIAL No.\n10, ÍNDICE, TOMO CXXVIII, DE FECHA 12 DE FEBRERO DE 2021, EXPEDIDO POR LA\nH. XXIII LEGISLATURA, SIENDO GOBERNADOR CONSTITUCIONAL EL C. JAIME\nBONILLA VALDEZ 2019-2021.\nARTÍCULO TRANSITORIO\nPRIMERO.- La presente reforma entrará en vigor al día siguiente de su publicación en el Periódico Oficial del Estado.\nDADO en Sesión Extraordinaria Virtual en la Ciudad de Mexicali, B.C., a los veinticuatro días del mes de noviembre del año dos mil veinte.\nDIP. JULIO CÉSAR VÁZQUEZ CASTILLO\nPRESIDENTE\n(RÚBRICA)\nDIP. EVA GRICELDA RODRÍGUEZ\nSECRETARIA\n(RÚBRICA)\nDE CONFORMIDAD CON LO DISPUESTO POR LA FRACCIÓN I DEL ARTÍCULO 49\nCALIFORNIA, IMPRÍMASE Y PUBLÍQUESE.\nMEXICALI, BAJA CALIFORNIA, A LOS DOS DÍAS DEL MES DE DICIEMBRE DEL\nAÑO DOS MIL VEINTE.\nJAIME BONILLA VALDEZ\nGOBERNADOR DEL ESTADO\n(RÚBRICA)\nAMADOR RODRÍGUEZ LOZANO\nSECRETARIO GENERAL DE GOBIERNO\n(RÚBRICA)\nLey de Protección al Ambiente para el Estado de Baja California. Página 140\nARTÍCULO ÚNICO TRANSITORIO DEL DECRETO No. 281, POR EL QUE SE\nAPRUEBA LA REFORMA AL ARTÍCULO 42; PUBLICADO EN EL PERIÓDICO OFICIAL No.\nH. XXIII LEGISLATURA, SIENDO GOBERNADOR CONSTITUCIONAL EL C. JAIME\nBONILLA VALDEZ 2019-2021.\nARTÍCULO TRANSITORIO\nPRIMERO.- El presente Decreto entrará en vigor al día siguiente de su publicación en el Periódico Oficial del Estado de Baja California.\nDADO en el Salón de Sesiones Benito Juárez García en Sesión Ordinaria de la XXIII\nLegislatura en la Ciudad de Mexicali, B.C., a los veintiún días del mes de julio del año dos mil veintiuno.\nDIP. EVA GRICELDA RODRÍGUEZ\nPRESIDENTA\n(RÚBRICA)\nDIP. MARÍA LUISA VILLALOBOS ÁVILA\nSECRETARIA\n(RÚBRICA)\nDE CONFORMIDAD CON LO DISPUESTO POR LA FRACCIÓN I DEL ARTÍCULO 49\nCALIFORNIA, IMPRÍMASE Y PUBLÍQUESE.\nMEXICALI, BAJA CALIFORNIA, A LOS VEINTITRÉS DÍAS DEL MES DE JULIO DEL\nAÑO DOS MIL VEINTIUNO.\nJAIME BONILLA VALDEZ\nGOBERNADOR DEL ESTADO\n(RÚBRICA)\nAMADOR RODRÍGUEZ LOZANO\nSECRETARIO GENERAL DE GOBIERNO\n(RÚBRICA)\nARTÍCULO PRIMERO TRANSITORIO DEL DECRETO No. 129, POR EL QUE SE\nAPRUEBA LA REFORMA A LOS ARTÍCULOS 2, 9, 38, 39, 106 TER, 106 TER 1, 106 TER 2\nY 159; PUBLICADO EN EL PERIÓDICO OFICIAL No. 56, SECCIÓN III, TOMO CXXIX, DE\nSIENDO GOBERNADORA CONSTITUCIONAL LA C. MARINA DEL PILAR ÁVILA OLMEDA\n2021-2027.\nTRANSITORIOS\nLey de Protección al Ambiente para el Estado de Baja California. Página 141\nPRIMERO.- La presente reforma entrará en vigor al día siguiente de su publicación en el Periódico Oficial del Estado de Baja California.\nSEGUNDO.- El Ejecutivo del Estado y los Ayuntamientos emitirán la reglamentación\nReforma.\nTERCERO.- El Consejo Estatal de Protección al Ambiente ajustará la reglamentación para la integración, administración y gasto de los fondos ambientales a que se refiere el artículo 39 de la Ley de la materia dentro de los tres meses siguientes al inicio de la vigencia de esta Reforma.\nEl Consejo procurará que por lo menos durante tres años, el cincuenta por ciento de los recursos que integran los fondos ambientales se destine a los fines previstos en la fracción VIII del artículo 39 de la Ley de Protección al Ambiente para el Estado de Baja\nCalifornia.\nDADO en Sesión Ordinaria de la XXIV Legislatura en la Ciudad de Mexicali, B.C., a los veinticinco días del mes de agosto del año dos mil veintidós.\nDIP. ALEJANDRA MARÍA ANG HERNÁNDEZ\nPRESIDENTA\n(RÚBRICA)\nDIP. DUNNIA MONTSERRAT MURILLO LÓPEZ\nSECRETARIA\n(RÚBRICA)\nDE CONFORMIDAD CON LO DISPUESTO POR LA FRACCIÓN I DEL ARTÍCULO 49\nCALIFORNIA, IMPRÍMASE Y PUBLÍQUESE.\nMEXICALI, BAJA CALIFORNIA, A LOS CINCO DÍAS DEL MES DE SEPTIEMBRE\nDEL AÑO DOS MIL VEINTIDÓS.\nMARINA DEL PILAR ÁVILA OLMEDA\nGOBERNADORA DEL ESTADO\nDE BAJA CALIFORNIA\n(RÚBRICA)\nCATALINO ZAVALA MÁRQUEZ\nSECRETARIO GENERAL DE GOBIERNO\nDEL ESTADO DE BAJA CALIFORNIA\n(RÚBRICA)\nLey de Protección al Ambiente para el Estado de Baja California. Página 142\nARTÍCULO ÚNICO TRANSITORIO DEL DECRETO No. 202, POR EL QUE SE\nAPRUEBA LA REFORMA AL ARTÍCULO 113 Y LA ADICIÓN DE LOS ARTÍCULOS 113 BIS\nY 113 TER; PUBLICADO EN EL PERIÓDICO OFICIAL No. 8, ÍNDICE, DE FECHA 10 DE\nGOBERNADORA CONSTITUCIONAL LA C. MARINA DEL PILAR ÁVILA OLMEDA 2021-\n2027.\nTRANSITORIOS\nPRIMERO.- Las presentes reformas entrarán en vigor al día siguiente de su publicación en el Periódico Oficial del Estado.\nSEGUNDO.- Los Ayuntamientos, dentro de los noventa días siguientes a la entrada en vigor de las presentes reformas, deberán realizar las adecuaciones reglamentarias pertinentes para su debido cumplimiento.\nDADO en Sesión Ordinaria de la XXIV Legislatura en la Ciudad de Mexicali, B.C., a los veintiséis días del mes de enero del año dos mil veintitrés.\nDIP. MARÍA DEL ROCÍO ADAME MUÑOZ\nPRESIDENTA\n(RÚBRICA)\nDIP. DUNNIA MONTSERRAT MURILLO LÓPEZ\nSECRETARIA\n(RÚBRICA)\nDE CONFORMIDAD CON LO DISPUESTO POR LA FRACCIÓN I DEL ARTÍCULO 49\nCALIFORNIA, IMPRÍMASE Y PUBLÍQUESE.\nMEXICALI, BAJA CALIFORNIA, A LOS VEINTISIETE DÍAS DEL MES DE ENERO\nDEL AÑO DOS MIL VEINTITRÉS.\nMARINA DEL PILAR ÁVILA OLMEDA\nGOBERNADORA DEL ESTADO\nDE BAJA CALIFORNIA\n(RÚBRICA)\nCATALINO ZAVALA MÁRQUEZ\nSECRETARIO GENERAL DE GOBIERNO\nDEL ESTADO DE BAJA CALIFORNIA\n(RÚBRICA)\nLey de Protección al Ambiente para el Estado de Baja California. Página 143\nARTÍCULO ÚNICO TRANSITORIO DEL DECRETO No. 220, POR EL QUE SE\nREFORMAN LOS ARTÍCULOS 168, 169, 171, 178, 182, 185, 187 Y 191 BIS; PUBLICADO\nCXXX, EXPEDIDO POR LA H. XXIV LEGISLATURA, SIENDO GOBERNADORA\nCONSTITUCIONAL LA C. MARINA DEL PILAR ÁVILA OLMEDA 2021-2027.\nTRANSITORIOS\nÚNICO. La presente reforma entrará en vigor al día siguiente al de su publicación en el\nPeriódico Oficial del Estado.\nDADO en Sesión Ordinaria de la XXIV Legislatura en la Ciudad de Mexicali, B.C., a los dieciséis días del mes de marzo del año dos mil veintitrés.\nDIP. MARÍA DEL ROCÍO ADAME MUÑOZ\nPRESIDENTA\n(RÚBRICA)\nDIP. DUNNIA MONTSERRAT MURILLO LÓPEZ\nSECRETARIA\n(RÚBRICA)\nDE CONFORMIDAD CON LO DISPUESTO POR LA FRACCIÓN I DEL ARTÍCULO 49\nCALIFORNIA, IMPRÍMASE Y PUBLÍQUESE.\nMEXICALI, BAJA CALIFORNIA, A LOS DIECISIETE DÍAS DEL MES DE MARZO DEL\nAÑO DOS MIL VEINTITRÉS.\nMARINA DEL PILAR ÁVILA OLMEDA\nGOBERNADORA DEL ESTADO\nDE BAJA CALIFORNIA\n(RÚBRICA)\nCATALINO ZAVALA MÁRQUEZ\nSECRETARIO GENERAL DE GOBIERNO\nDEL ESTADO DE BAJA CALIFORNIA\n(RÚBRICA)\nLey de Protección al Ambiente para el Estado de Baja California. Página 144\nARTÍCULO ÚNICO TRANSITORIO DEL DECRETO No. 333, POR EL QUE SE\nREFORMAN LOS ARTÍCULOS 6, 7, 8 Y 18; PUBLICADO EN EL PERIÓDICO OFICIAL No.\nLA H. XXIV LEGISLATURA, SIENDO GOBERNADORA CONSTITUCIONAL LA C. MARINA\nDEL PILAR ÁVILA OLMEDA 2021-2027.\nTRANSITORIO\nÚNICO. La presente reforma entrará en vigor al día siguiente de su publicación en el\nPeriódico Oficial del Estado de Baja California.\nDADO en Sesión Ordinaria de la XXIV Legislatura en la Ciudad de Mexicali, B.C., a los dieciséis días del mes de noviembre del año dos mil veintitrés.\nDIP. MANUEL GUERRERO LUNA\nPRESIDENTE\n(RÚBRICA)\nDIP. DUNNIA MONTSERRAT MURILLO LÓPEZ\nSECRETARIA\n(RÚBRICA)\nDE CONFORMIDAD CON LO DISPUESTO POR LA FRACCIÓN I DEL ARTÍCULO 49\nCALIFORNIA, IMPRÍMASE Y PUBLÍQUESE.\nMEXICALI, BAJA CALIFORNIA, A LOS VEINTITRÉS DÍAS DEL MES DE NOVIEMBRE\nDEL AÑO DOS MIL VEINTITRÉS.\nMARINA DEL PILAR ÁVILA OLMEDA\nGOBERNADORA DEL ESTADO\nDE BAJA CALIFORNIA\n(RÚBRICA)\nCATALINO ZAVALA MÁRQUEZ\nSECRETARIO GENERAL DE GOBIERNO\nDEL ESTADO DE BAJA CALIFORNIA\n(RÚBRICA)\nLey de Protección al Ambiente para el Estado de Baja California. Página 145\nARTÍCULO ÚNICO TRANSITORIO DEL DECRETO No. 453, POR EL QUE SE\nAPRUEBA LA REFORMA AL ARTÍCULO 8; PUBLICADO EN EL PERIÓDICO OFICIAL No.\nXXIV LEGISLATURA, SIENDO GOBERNADORA CONSTITUCIONAL LA C. MARINA DEL\nPILAR ÁVILA OLMEDA 2021-2027.\nTRANSITORIO\nPRIMERO.- La presente reforma entrará en vigor al día siguiente de su publicación en el\nPeriódico Oficial del Estado de Baja California.\nSEGUNDO.- El Ejecutivo del Estado expedirá las disposiciones reglamentarias correspondientes para la aplicación de la reforma a la presente ley, dentro de los noventa días siguientes a la publicación de este Decreto.\nDADO en Sesión Ordinaria de la XXIV Legislatura en la Ciudad de Mexicali, B.C., a los veinticinco días del mes de julio del año dos mil veinticuatro.\nDIP. RAMÓN VÁZQUEZ VALADEZ\nPRESIDENTE\n(RÚBRICA)\nDIP. MANUEL GUERRERO LUNA\nSECRETARIO\n(RÚBRICA)\nDE CONFORMIDAD CON LO DISPUESTO POR LA FRACCIÓN I DEL ARTÍCULO 49\nCALIFORNIA, IMPRÍMASE Y PUBLÍQUESE.\nMEXICALI, BAJA CALIFORNIA, AL DÍA PRIMERO DEL MES DE AGOSTO DEL AÑO\nDOS MIL VEINTICUATRO.\nMARINA DEL PILAR ÁVILA OLMEDA\nGOBERNADORA DEL ESTADO\nDE BAJA CALIFORNIA\n(RÚBRICA)\nALFREDO ÁLVAREZ CÁRDENAS\nSECRETARIO GENERAL DE GOBIERNO\nDEL ESTADO DE BAJA CALIFORNIA\n(RÚBRICA)\nARTÍCULO ÚNICO TRANSITORIO DEL DECRETO No. 456, POR EL QUE SE\nAPRUEBA LA REFORMA AL ARTÍCULO 9; PUBLICADO EN EL PERIÓDICO OFICIAL No.\nLey de Protección al Ambiente para el Estado de Baja California. Página 146\nXXIV LEGISLATURA, SIENDO GOBERNADORA CONSTITUCIONAL LA C. MARINA DEL\nPILAR ÁVILA OLMEDA 2021-2027.\nTRANSITORIO\nÚnico.- La presente reforma entrará en vigor al día siguiente de su publicación en el\nPeriódico Oficial del Estado de Baja California.\nDADO en Sesión Ordinaria de la XXIV Legislatura en la Ciudad de Mexicali, B.C., a los veinticinco días del mes de julio del año dos mil veinticuatro.\nDIP. RAMÓN VÁZQUEZ VALADEZ\nPRESIDENTE\n(RÚBRICA)\nDIP. MANUEL GUERRERO LUNA\nSECRETARIO\n(RÚBRICA)\nDE CONFORMIDAD CON LO DISPUESTO POR LA FRACCIÓN I DEL ARTÍCULO 49\nCALIFORNIA, IMPRÍMASE Y PUBLÍQUESE.\nMEXICALI, BAJA CALIFORNIA, AL DÍA PRIMERO DEL MES DE AGOSTO DEL AÑO\nDOS MIL VEINTICUATRO.\nMARINA DEL PILAR ÁVILA OLMEDA\nGOBERNADORA DEL ESTADO\nDE BAJA CALIFORNIA\n(RÚBRICA)\nALFREDO ÁLVAREZ CÁRDENAS\nSECRETARIO GENERAL DE GOBIERNO\nDEL ESTADO DE BAJA CALIFORNIA\n(RÚBRICA)\nARTÍCULO ÚNICO TRANSITORIO DEL DECRETO No. 111, POR EL QUE SE\nAPRUEBA LA REFORMA AL ARTÍCULO 108; PUBLICADO EN EL PERIÓDICO OFICIAL\nXXV LEGISLATURA, SIENDO GOBERNADORA CONSTITUCIONAL LA C. MARINA DEL\nPILAR ÁVILA OLMEDA 2021-2027.\nTRANSITORIOS\nLey de Protección al Ambiente para el Estado de Baja California. Página 147\nPRIMERO.- La presente reforma entrará en vigor al día siguiente de su publicación en el\nPeriódico Oficial del Estado.\nSEGUNDO.- A partir de la entrada en vigor de la presente reforma, la Secretaría contará con un plazo de 60 días para establecer la periodicidad a que hace referencia el artículo 108 y a partir de esa fecha iniciar el registro para su actualización permanente.\nDADO en Sesión Ordinaria de la XXV Legislatura en la Ciudad de Mexicali, B.C., a los diecinueve días del mes de junio del año dos mil veinticinco.\nDIP. MICHELLE ALEJANDRA TEJEDA MEDINA\nPRESIDENTA\n(RÚBRICA)\nDIP. NORMA ANGELICA PEÑALOZA ESCOBEDO\nSECRETARIA\n(RÚBRICA)\nDE CONFORMIDAD CON LO DISPUESTO POR LA FRACCIÓN I DEL ARTÍCULO 49\nCALIFORNIA, IMPRÍMASE Y PUBLÍQUESE.\nMEXICALI, BAJA CALIFORNIA, A LOS 20 DÍAS DEL MES DE JUNIO DEL AÑO DOS\nMIL VEINTICINCO.\nMARINA DEL PILAR ÁVILA OLMEDA\nGOBERNADORA DEL ESTADO\nDE BAJA CALIFORNIA\n(RÚBRICA)\nALFREDO ÁLVAREZ CÁRDENAS\nSECRETARIO GENERAL DE GOBIERNO\nDEL ESTADO DE BAJA CALIFORNIA\n(RÚBRICA)\nLey de Protección al Ambiente para el Estado de Baja California. Página 148",
  "ordenamiento": "REGLAMENTO",
  "jurisdiccion": "BAJA CALIFORNIA",
  "fuente_oficial": "Periódico Oficial",
  "FECHA PER OFIC": "2025/06/27",
  "ESTATUS": "VIGENTE",
  "TOMO": "TOMO_VII",
  "URL": "https://www.congresobc.gob.mx/Documentos/ProcesoParlamentario/Leyes/TOMO_VII/20250627_LEYPROAMBIENTE.PDF",
  "es_escaneado": false,
  "tiene_tablas": false,
  "materia": [
    "ambiental",
    "urbanismo",
    "infraestructura"
  ]
}