{
  "titulo": "Ley CONTRA LA DELINCUENCIA ORGANIZADA PARA EL ESTADO DE BAJA CALIFORNIA",
  "Contenido": "ESTADO DE BAJA CALIFORNIA\nPublicado en el Periódico Oficial No. 1,\nCAPÍTULO PRIMERO\nDE LA NATURALEZA, OBJETO Y APLICACIÓN DE LA LEY\nARTÍCULO 1.- La presente Ley tiene por objeto normar la investigación, persecución, procesamiento, sanción y ejecución de las penas, por delitos cometidos por miembros de la delincuencia organizada, sus disposiciones son de orden público y de aplicación en el Estado de Baja California; asimismo, será aplicable para aquellos delitos que cometan los miembros de la delincuencia organizada aun cuando se preparen o cometan en otra Entidad\nFederativa, siempre que sus efectos se produzcan en el Estado.\nARTÍCULO 2.- Para efectos de esta Ley, se entiende por:\nI. Ley: La Ley Contra la Delincuencia Organizada para el Estado de Baja\nCalifornia;\nII. Código Penal: El Código Penal para el Estado de Baja California;\nIII. Código de Procedimientos Penales: El Código de Procedimientos\nPenales para el Estado de Baja California;\nIV. Ley de Ejecución: La Ley de Ejecución de Sanciones y Medidas de\nSeguridad para el Estado de Baja California;\nV. Ley Orgánica: La Ley Orgánica de la Procuraduría General de\nJusticia del Estado de Baja California;\nVI. Miembros de la Delincuencia Organizada: Aquellas personas que, siendo autores o partícipes, desempeñen actividades comprendidas dentro de las funciones de administración, dirección, supervisión o cualquier otra, que organizada, así como de acciones delictivas derivadas de ésta;\nVIl. Ministerio Público: El que pertenece a la subprocuraduría\nMiembros de la Delincuencia Organizada;\nVIII. Subprocuraduría de Investigaciones Especiales: La unidad de la\nOrganizada; y\nIX. Subprocurador: El titular de la Subprocuraduría de Investigaciones\nEspeciales.\nArtículo Reformado\nARTICULO 3.- Son aplicables supletoriamente a esta Ley, las disposiciones del Código Penal, Código de Procedimientos Penales, Ley de comprendidas en leyes especiales.\nAsimismo, es aplicable supletoriamente a esta Ley, la Ley Federal\nContra la Delincuencia Organizada y la Ley Orgánica del Poder Judicial de la\nFederación cuando intervengan autoridades jurisdiccionales federales, en materia de interposición de recursos, solicitud de intervención de comunicaciones, término para su resolución, negativa de la solicitud, características, modalidades, límites, prórroga, tipos de comunicaciones escuchadas o interceptadas, lugares que serán vigilados y período en que se realizarán las intervenciones.\nARTÍCULO 4.- Cuando tres o más personas de manera conjunta acuerden organizarse o se organicen para realizar en forma reiterada o permanente, conductas que por sí o unidas a otras, tengan como fin o resultado cometer alguno o algunos de los delitos siguientes, serán sancionados por ese solo hecho como Miembros de la Delincuencia\nOrganizada:\nI. Homicidio, previsto en los artículos 123 y 147 del Código Penal;\nII. Privación ilegal de la libertad, previsto por el artículo 161 del Código\nPenal;\nIII. Secuestro, previsto por el artículo 164 del Código Penal;\nIV. Fraude genérico, previsto en el artículo 218 del Código Penal;\nV. Robo con violencia, previsto por el artículo 198 y sancionado por el artículo 203 del Código Penal;\nVI. Robo de vehículo, previsto por el Artículo 208-Bis y robo equiparado de vehículo de motor, previsto en el Artículo 208-Ter del Código Penal;\nVII. Asalto, previsto en los artículos 172 y 173 del Código Penal;\nVIII. Tráfico de personas menores de dieciocho años de edad o\n, descrito en el artículo 238 en sus párrafos primero y quinto del Código Penal;\nIX. Lenocinio, previsto en los artículos 264 y 267 del Código Penal;\nX. Falsificación de documentos, previsto por el artículo 259 del Código\nPenal;\nXI. Abigeato, previsto por los artículos 209 y 212 del Código Penal.\nXII.- Pornografía de personas menores de dieciocho años de edad o hecho o persona que no tienen capacidad de resistirlo, establecido en el artículo 262 del Código Penal;\nXIII. Turismo Sexual con personas menores de dieciocho años de edad o personas que no tienen la capacidad de comprender el significado del hecho o persona que no tienen capacidad de resistirlo; previsto en el artículo 262 Ter del Código Penal;\nXIV. DEROGADO.\nFracción Derogada\nXV. Corrupción de personas menores de edad o personas que no tengan la capacidad de comprender el significado del hecho, previsto en el artículo 261 del Código Penal.\nXVI. Extorsión, previsto en los artículos 224 del Código Penal.\nArtículo Reformado\nARTÍCULO 5.- Sin perjuicio de las penas que correspondan por el delito o delitos que se cometan, al Miembro de la Delincuencia Organizada, se le aplicarán las siguientes:\nI. Cuando se trate de servidor público o haya tenido esa calidad dentro de un plazo de tres años anteriores a la comisión del delito. Además, se le impondrá a dicho servidor público la destitución, así como la inhabilitación definitiva para desempeñar cualquier empleo, cargo o comisión públicos, o\nII. A quien no tenga las funciones anteriores, se le impondrá de cinco a diez años de prisión y multa de doscientos hasta mil días.\nARTÍCULO 6.- Las penas a que se refiere el artículo anterior se aumentarán hasta una mitad más, de la que se haya impuesto en los casos siguientes:\nI. Cuando se trate de servidor público. Además, se le impondrá a dicho servidor público la destitución, así como la inhabilitación definitiva para desempeñar cualquier empleo, cargo o comisión públicos, o\nII. Cuando en la comisión del delito o de los delitos a que se refiere esta\nLey, se utilicen uno o varias personas menores de dieciocho años de edad o hecho.\nArtículo Reformado\nARTÍCULO 7.- Los plazos para la prescripción de la pretensión punitiva y de la potestad de ejecutar las penas y medidas de seguridad se duplicarán, respecto a los delitos a que se refiere esta Ley.\nCAPÍTULO SEGUNDO\nARTÍCULO 8.- La Subprocuraduría de Investigaciones Especiales, esta Ley, que se cometan por Miembros de la Delincuencia Organizada, en los términos previstos en la misma y demás leyes aplicables en la materia.\nArtículo Reformado\nARTÍCULO 9.- La Subprocuraduría de Investigaciones Especiales, contará para el desempeño de su función con los servidores públicos necesarios, los cuales deberán reunir el perfil y los requisitos que aseguren un alto nivel profesional, de conformidad con la Ley Orgánica y su reglamento.\nArtículo Reformado\nCAPÍTULO TERCERO\nDEL ARRAIGO DEL INCULPADO\nARTÍCULO 10.- Cuando existan indicios suficientes que acrediten fundadamente que alguien es Miembro de la Delincuencia Organizada, el Juez podrá dictar, a solicitud del Ministerio Público y tomando en cuenta las características del hecho imputado, así como las circunstancias personales del inculpado, el arraigo de éste en el lugar, forma y medios de realización señalados en la solicitud. Corresponde a la Subprocuraduría de\nInvestigaciones Especiales, vigilar que el mandato de la autoridad judicial sea debidamente cumplido.\nEl arraigo se prolongará por el tiempo estrictamente indispensable para la debida integración de la averiguación previa, no pudiendo exceder de noventa días, con el objeto de que el afectado participe en la aclaración de los hechos que se le imputan y pueda abreviarse el tiempo de la medida impuesta.\nArtículo Reformado\nCAPÍTULO CUARTO\nDE LA RESERVA DE LAS ACTUACIONES EN LA AVERIGUACIÓN PREVIA\nY DE LA PROTECCIÓN A LAS PERSONAS\nARTÍCULO 11.- Una vez iniciada la averiguación previa por los delitos a que se refiere esta Ley, únicamente tendrán acceso para consulta de la misma el Ministerio Público y las personas que éste designe, así como el indiciado y su defensor, los cuales tendrán conocimiento únicamente de los hechos imputados, pudiendo en base a la información recibida, presentar las pruebas de descargo que estimen oportunas. proporcione copias de ellas o de los documentos que la integran, se le sujetará al procedimiento de responsabilidad administrativa o penal, según corresponda.\nARTÍCULO 12.- Cuando las personas que declaren con el carácter de testigos, hagan imputaciones directas contra los Miembros de la Delincuencia\nOrganizada y corran peligro o riesgo en su integridad o de su familia, el ejercite la acción penal.\nCAPITULO QUINTO\nDE LAS ÓRDENES DE CATEO Y DE LAS AUTORIZACIONES DE\nINTERVENCIÓN DE COMUNICACIONES\nARTÍCULO 13.- Cuando el Ministerio Público solicite al juez una orden de cateo relacionada con alguno de los delitos previstos por esta Ley, el juzgador resolverá dentro del término de doce horas.\nEn caso de que el juez no resuelva dentro del término citado, el\nMinisterio Público, lo hará del conocimiento al Presidente del Tribunal Superior de Justicia y del Consejo de la Judicatura del Estado, quienes solicitarán al\nJuez la práctica de las diligencias correspondientes con el propósito de acordar oportunamente la orden de cateo solicitada, en caso de que proceda.\nSi el Juez negara la orden de cateo, el Ministerio Público tendrá un término de tres días contados a partir de la notificación del auto para interponer el recurso de apelación ante el mismo, debiendo expresar los motivos de inconformidad que tenga contra la resolución apelada, si no presenta éstos, de oficio se declarará desierto el recurso interpuesto.\nAdmitida la apelación, se remitirán las constancias originales da la solicitud al Tribunal Superior de Justicia, quien a su vez radicará el recurso y dentro de un término de cuarenta y ocho horas pronunciará el fallo correspondiente.\nARTÍCULO 14.- En la averiguación previa, el Procurador General de\nJusticia del Estado, a petición del Subprocurador y en los delitos en que sea procedente, podrá solicitar al Juez de Distrito en turno, la autorización de intervención de comunicaciones privadas.\nLa solicitud de autorización de intervención de comunicaciones privadas, deberá contener:\nI. Los indicios que hagan presumir. fundadamente, que en los delitos investigados participa algún Miembro de la Delincuencia Organizada;\nII. Los preceptos legales que la fundan;\nIII. El razonamiento por el que se considera procedente;\nIV. El objeto y la necesidad de la intervención;\nV. El tipo de comunicaciones, los sujetos y los lugares que serán intervenidos;\nVI. El período durante el cual se llevarán a cabo las intervenciones. El período podrá ser prorrogado, sin que él mismo, incluyendo sus prórrogas, pueda exceder de seis meses; después de dicho plazo, sólo podrán autorizarse acredite nuevos elementos que así lo justifiquen, y\nVIl. En su caso, las instituciones públicas o privadas referentes al ramo de comunicaciones y los modos específicos de colaboración en la intervención de comunicaciones privadas.\nPodrán ser objeto de intervención, las comunicaciones que se realicen en forma oral, escrita, por signos, señales o mediante el empleo de aparatos electrónicos, eléctricos, mecánicos, alámbricos, inalámbricos, sistemas de cómputo o equipos informáticos, así como cualquier otro medio o forma que permita la comunicación entre uno o varios emisores y uno o varios receptores.\nEl auto que niegue la solicitud de autorización de intervención de comunicaciones privadas, podrá ser impugnado mediante el recurso que proceda ante el Tribunal Unitario de Circuito que corresponda.\nARTÍCULO 15.- El Ministerio Público deberá levantar acta circunstanciada de la intervención de comunicaciones privadas que realice, la cuál contendrá:\nI. Fechas de inicio y conclusión de la intervención de comunicaciones privadas;\nII. Un inventario pormenorizado de los documentos, objetos y cintas de audio o video que contengan los sonidos o imágenes captadas durante la misma, y\nIII. La identificación de quienes hayan participado en las diligencias, así como los demás datos que considere relevantes para la investigación.\nLas cintas originales y el duplicado de cada una de ellas, se numerarán progresivamente y contendrán los datos necesarios para su identificación, debiéndose guardar en sobre sellado, siendo responsable de su seguridad, cuidado e integridad, el Ministerio Público.\nARTÍCULO 16.- Al iniciarse el proceso, las cintas así como todas las comunicaciones privadas, serán entregados al juez.\nARTICULO 17.- Durante el proceso, el juez pondrá las cintas a disposición del inculpado, quien podrá escucharlas o verlas durante un período de diez días, bajo la supervisión de la autoridad judicial, quien velará por la integridad de estos elementos probatorios. Al término de este período, el inculpado o su defensor, formularán sus observaciones si las tuvieran y podrá para el proceso. Asimismo, podrá solicitar la transcripción de aquellas grabaciones o, la fijación en impreso de imágenes que considere relevantes para su defensa. términos de la autorización judicial respectiva.\nEl auto que resuelva la destrucción de cintas, la transcripción de grabaciones o la fijación de imágenes, es apelable en efecto suspensivo.\nARTÍCULO 18.- En caso de no ejercicio de la acción penal, y una vez transcurrido el plazo legal para impugnarlo sin que ello suceda, las cintas se pondrán a disposición del Juez de Distrito que autorizó la intervención, quien ordenará su destrucción en presencia del Procurador General de Justicia del\nEstado. Igual procedimiento se aplicará, cuando por reserva de la averiguación previa u otra circunstancia, dicha averiguación no hubiera sido consignada y haya transcurrido el plazo para la prescripción de la acción penal.\nARTÍCULO 19.- Quienes participen en la intervención de las comunicaciones a que se refiere esta Ley, deberán guardar reserva sobre el contenido de las mismas, en caso de que revelen, divulguen o utilicen en forma indebida o en perjuicio de otro la información o imágenes obtenidas en el curso de una intervención de comunicaciones privadas, autorizada o no, serán sancionados con pena de tres a seis años de prisión y de quinientos a mil días multa; si se trata de un servidor público, se impondrá además la destitución e inhabilitación para desempeñar otro empleo, cargo o comisión públicos, por un tiempo igual a la pena, a partir del cumplimiento de la misma,\nARTÍCULO 20.- Cuando un servidor público intervenga comunicaciones privadas sin la autorización judicial correspondiente o, la realice en términos distintos a los autorizados, será sancionado con pena de cuatro a ocho años de prisión y de ochocientos a mil quinientos días multa, así como con la destitución e inhabilitación para desempeñar otro empleo, cargo o comisión públicos, por un tiempo igual a la pena, a partir del cumplimiento de la misma.\nCAPÍTULO SEXTO\nDEL ASEGURAMIENTO Y DECOMISO DE BIENES\nARTÍCULO 21.- Si durante la averiguación previa se acredita que\nMiembro de la Delincuencia Organizada, podrá el Ministerio Público solicitar al juzgado penal en turno o al que corresponda, el aseguramiento de sus bienes, así como aquellos respecto de los cuales se conduzca como dueño, asegurados.\nEl decomiso de bienes podrá realizarse durante el proceso penal, siguiéndose lo dispuesto por los artículos 62, 63 y 64 del Código Penal.\nCAPÍTULO SÉPTIMO\nDE LA COLABORACIÓN EN LA PERSECUCIÓN DE LA\nDELINCUENCIA ORGANIZADA\nARTÍCULO 22.- El Miembro de la Delincuencia Organizada que de la Delincuencia Organizada podrá según el caso, recibir los beneficios siguientes:\nI. Cuando exista una averiguación previa en la que el colaborador esté implicado y aporte medios de prueba para la consignación de otros Miembros de la Delincuencia Organizada, la pena que le corresponda por los delitos cometidos se le reducirá hasta en dos terceras partes;\nII. Cuando aporte elementos de prueba durante el proceso penal que sirvan de base para dictar sentencia a otros Miembros de la Delincuencia\nOrganizada que tengan funciones de administración, dirección o supervisión, la pena que le corresponda por los delitos que cometió el colaborador podrá reducirse hasta la mitad, y\nIII. Cuando después de haber sido sentenciado alguno de los Miembros de la Delincuencia Organizada, aporte elementos de prueba que sean suficientes para dictar una sentencia condenatoria a otros Miembros de la\nDelincuencia Organizada, que tengan funciones de administración, dirección o supervisión podrá otorgársele como beneficio la preliberación, en términos de la Ley de Ejecución.\nARTICULO 23.- Cuando se dicte una orden de aprehensión en contra de alguno de los Miembros de la Delincuencia Organizada, la autoridad podrá ofrecer recompensa a quienes auxilien de manera eficiente en su localización y aprehensión. Para ello, el Procurador General del Justicia del Estado, emitirá el acuerdo correspondiente donde se establecerán los términos y condiciones para tal efecto.\nARTÍCULO 24.- Toda persona que tenga en su poder cualquier documento u objeto que pueda tener el carácter de prueba y que sirva de base para iniciar una averiguación previa en contra de algún Miembro de la\nDelincuencia Organizada, tiene la obligación de entregarlos al Ministerio\nPúblico. De igual forma, se tiene la obligación de entregarlos cuando sea requerido por el Ministerio Público durante la averiguación previa o, por el juzgador durante el proceso.\nCAPÍTULO OCTAVO\nDE LA VALORACIÓN DE LAS PRUEBAS\nARTÍCULO 25.- Las pruebas que se presenten durante la averiguación previa o durante un proceso penal, deberán ser valoradas en términos de lo previsto por el Capítulo IX, del Título Quinto, del Libro Primero del Código de\nProcedimientos Penales.\nLas pruebas desahogadas durante un proceso penal, podrán servir de\nDelincuencia Organizada, e inclusive podrán relacionarse como tales en otros procedimientos relativos a la delincuencia organizada.\nCAPITULO NOVENO\nY MEDIDAS DE SEGURIDAD\nARTÍCULO 26.- Los Miembros de la Delincuencia Organizada que hayan colaborado para la persecución y procesamiento de otros Miembros de la Delincuencia Organizada, deberán ser recluidos ya sea en prisión preventiva o en ejecución de sentencia en centros de reinserción social diferentes a aquellos donde se encuentren los miembros señalados.\nArtículo Reformado\nARTÍCULO 27.- Los sentenciados por delitos a que se refiere esta Ley, no tendrán derecho a que se les conceda la substitución de la pena o la suspensión condicional de la ejecución de la pena, así corno tampoco la libertad preparatoria, preliberación o remisión parcial de la pena. A excepción, de aquellos sentenciados que colaboren con el Ministerio Público en la investigación y persecución de otros Miembros de la Delincuencia Orqanizada, en los términos de esta Ley.\nTRANSITORIO\nARTÍCULO ÚNICO.- La presente Ley entrará en vigor, al día siguiente de su publicación en el Periódico Oficial del Estado de Baja California.\nDADO.- En el Salón de Sesiones \"Lic. Benito Juárez García\" del\nHonorable Poder Legislativo en la Ciudad de Mexicali, Baja California, a los diecinueve días del mes de noviembre del año dos mil tres.\nDIP. LEOPOLDO MORAN DIAZ\nPRESIDENTE\nDIP. ARTURO ALVARADO GONZALEZ\nPROSECRETARIO\nY PUBLÍQUESE.\nMEXICALI, BAJA CALIFORNIA, A LOS CUATRO DIAS DEL MES DE\nDICIEMBRE DEL AÑO DOS MIL TRES.\nGOBERNADOR DEL ESTADO.\nEUGENIO ELORDUY WALTHER\nSECRETARIO GENERAL DE GOBIERNO\nBERNARDO H. MARTINEZ AGUIRRE.\nARTÍCULO 2.- Fue reformado por Decreto No. 246, publicado en el expedido por la H. XXI Legislatura, siendo Gobernador Constitucional el C.\nFrancisco Arturo Vega de Lamadrid 2013-2019;\nARTÍCULO 4.- Fue reformado por Decreto No. 125, publicado en el expedido por la H. XVIII Legislatura, siendo Gobernador Constitucional el C.\nEugenio Elorduy Walther 2001-2007; fue reformado por Decreto No. 191, publicado en el Peródico Oficial No. 7, de fecha 17 de febrero de 2006, Tomo\nCXIII, expedido por la H. XVIII Legislatura, siendo Gobernador Constitucional el\nC. Eugenio Elorduy Walther 2001-2007; fue reformado por Decreto No. 250, publicado en el Periódico Oficial No. 46, de fecha 03 de noviembre de 2006, Tomo CXIII, expedido por la H. XVIII Legislatura, siendo Gobernador\nConstitucional el C. Eugenio Elorduy Walther 2001-2007; fue reformado por\nDecreto No. 330, publicado en el Periódico Oficial No. 20, de fecha 11 de mayo de 2007, Sección I, Tomo CXIV, expedido por la Honorable XVIII Legislatura, siendo Gobernador Constitucional el C. Lic. Eugenio Elorduy Walter 2001-2007;\nFue reformado por Decreto No. 405, publicado en el Periódico Oficial No. 39, de fecha 10 de septiembre de 2010, Tomo CXVII, expedido por la Honorable\nXIX Legislatura, siendo Gobernador Constitucional del Estado, el C. José\nGuadalupe Osuna Millán 2007-2013; fue reformado por Decreto No. 149, publicado en el Periódico Oficial No. 60, de fecha 30 de diciembre de 2011, Tomo CXVIII, Sección I, expedido por la Honorable XX Legislatura, siendo\nGobernador Constitucional el C. Lic. José Guadalupe Osuna Millán, 2007-2013; fue reformado por Decreto No. 489, publicado en el Periódico Oficial No. 32, Tomo CXX, de fecha 19 de julio de 2013, expedido por la H. XX Legislatura, siendo Gobernador Constitucional el C. José Guadalupe Osuna Millán 20072013;\nARTÍCULO 6.- Fue reformado por Decreto No. 125, publicado en el\nPeriódico Oficial No. 51, de fecha 18 de noviembre de 2005, Tomo CXII, expedido por la H. XVIII Legislatura, siendo Gobernador Constitucional el C.\nEugenio Elorduy Walther 2001-2007; Fue reformado por Decreto No. 405, publicado en el Periódico Oficial No. 39, de fecha 10 de septiembre de 2010, Tomo CXVII, expedido por la Honorable XIX Legislatura, siendo Gobernador\nConstitucional del Estado, el C. José Guadalupe Osuna Millán 2007-2013;\nARTÍCULO 8.- Fue reformado por Decreto No. 246, publicado en el expedido por la H. XXI Legislatura, siendo Gobernador Constitucional el C.\nFrancisco Arturo Vega de Lamadrid 2013-2019;\nARTÍCULO 9.- Fue reformado por Decreto No. 246, publicado en el expedido por la H. XXI Legislatura, siendo Gobernador Constitucional el C.\nFrancisco Arturo Vega de Lamadrid 2013-2019;\nARTÍCULO 10.- Fue reformado por Decreto No. 246, publicado en el expedido por la H. XXI Legislatura, siendo Gobernador Constitucional el C.\nFrancisco Arturo Vega de Lamadrid 2013-2019;\nARTÍCULO 26.- Fue reformado por Decreto No. 246, publicado en el expedido por la H. XXI Legislatura, siendo Gobernador Constitucional el C.\nFrancisco Arturo Vega de Lamadrid 2013-2019;\nARTICULO SEXTO TRANSITORIO DEL DECRETO NO. 125, POR EL\nQUE SE APRUEBAN LAS REFORMAS A LOS ARTÍCULOS 4 y 6,\nPUBLICADO EN EL PERIODICO OFICIAL NO. 51, DE FECHA 18 DE\nLEGISLATURA, SIENDO GOBERNADOR CONSTITUCIONAL EL C.\nEUGENIO ELORDUY WALTHER 2001-2007.\nARTICULOS TRANSITORIOS\nPRIMERO.- Las presentes reformas entrarán en vigor el día siguiente de su públicación en el Periódico Oficial del Estado de Baja California.\nSEGUNDO.- Se derogan todas las disposiciones que se opongan a las presentes reformas.\nDADO.- En el Salón de Sesiones “Lic. Benito Juárez García” del\nHonorable Poder Legislativo, en la Ciudad de Mexicali, Baja California, a los tres días del mes de noviembre del año dos mil cinco.\nDIP. ELVIRA LUNA PINEDA\nPRESIDENTA\n(RÚBRICA)\nDIP. ELÍAS LÓPEZ MENDOZA\nSECRETARIO\n(RÚBRICA)\nDE CONFORMIDAD CON LO DISPUESTO POR LA FRACCION I DEL\nARTICULO 49 DE LA CONSTITUCION POLITICA DEL ESTADO, IMPRIMASE\nY PUBLIQUESE.\nMEXICALI, BAJA CALIFORNIA, A LOS ONCE DIAS DEL MES DE\nNOVIEMBRE DEL AÑO DOS MIL CINCO.\nGOBERNADOR DEL ESTADO.\nEUGENIO ELORDUY WALTHER\nSECRETARIO GENERAL DE GOBIERNO\nBERNARDO H. MARTINEZ AGUIRRE\nARTICULO PRIMERO TRANSITORIO DEL DECRETO NO. 191, POR\nEL QUE SE REFORMA EL ARTÍCULO 4, PUBLICADO EN EL PERIODICO\nEXPEDIDO POR LA H. XVIII LEGISLATURA, SIENDO GOBERNADOR\nCONSTITUCIONAL EL C. EUGENIO ELORDUY WALTHER 2001-2007.\nARTÍCULOS TRANSITORIOS\nPRIMERO.- Las presentes reformas entrarán en vigor al día siguiente al de su publicación en el Periódico Oficial del Estado.\nSEGUNDO.- Se derogan todas aquellas disposiciones contrarias a las presentes reformas.\nTERCERO.- Esta nueva legislación podrá aplicarse a hechos surgidos bajo la vigencia de la reforma anterior, en lo que beneficie al responsable del delito, tal y como lo establece el artículo 8 del Código Penal del Estado de Baja\nCalifornia.\nDADO en el Salón de Sesiones “Lic. Benito Juárez García” del\nHonorable Poder Legislativo, en la Ciudad de Mexicali, Baja California, a los catorce días del mes de febrero del año dos mil seis.\nDIP. ABRAHAM CORREA ACEVEDO\nPRESIDENTE\n(RÚBRICA)\nDIP. GILBERTO DANIEL GONZÁLEZ SOLÍS\nSECRETARIO\n(RÚBRICA)\nDE CONFORMIDAD CON LO DISPUESTO POR LA FRACCION I DEL\nARTICULO 49 DE LA CONSTITUCION POLITICA DEL ESTADO, IMPRIMASE\nY PUBLIQUESE.\nMEXICALI, BAJA CALIFORNIA, A LOS DIECISEIS DIAS DEL MES DE\nFEBRERO DEL AÑO DOS MIL SEIS.\nGOBERNADOR DEL ESTADO.\nEUGENIO ELORDUY WALTHER\nSECRETARIO GENERAL DE GOBIERNO\nBERNARDO H. MARTINEZ AGUIRRE\nARTICULO TERCERO TRANSITORIO DEL DECRETO NO. 250, POR\nEL QUE SE REFORMA EL ARTÍCULO 4, PUBLICADO EN EL PERIODICO\nEXPEDIDO POR LA H. XVIII LEGISLATURA, SIENDO GOBERNADOR\nCONSTITUCIONAL EL C. EUGENIO ELORDUY WALTHER 2001-2007.\nARTÍCULO TRANSITORIO\nARTÍCULO ÚNICO.- El presente Decreto entrará en vigor al día siguiente de su publicación en el Periódico Oficial del Estado.\nDADO en el Salón de Sesiones “Lic. Benito Juárez García” del cinco días del mes de octubre del año dos mil seis.\nDIP. RICARDO MAGAÑA MOSQUEDA\nPRESIDENTE\n(RÚBRICA)\nDIP. CARLOS ALBERTO MONTAÑO QUINTANA\nSECRETARIO\n(RÚBRICA)\nDE CONFORMIDAD CON LO DISPUESTO POR LA FRACCION I DEL\nARTICULO 49 DE LA CONSTITUCION POLITICA DEL ESTADO, IMPRIMASE\nY PUBLIQUESE.\nMEXICALI, BAJA CALIFORNIA, A LOS DIECISIETE DIAS DEL MES DE\nOCTUBRE DEL AÑO DOS MIL SEIS.\nGOBERNADOR DEL ESTADO\nEUGENIO ELORDUY WALTHER\n(RÚBRICA)\nSECRETARIO GENERAL DE GOBIERNO\nBERNARDO H. MARTINEZ AGUIRRE\n(RÚBRICA)\nARTICULO TERCERO TRANSITORIO DEL DECRETO NO. 330, POR\nEL QUE SE REFORMA EL ARTICULO 4, PUBLICADO EN EL PERIODICO\nOFICIAL NO. 20, DE FECHA 11 DE MAYO DE 2007, TOMO CXIV, EXPEDIDO\nPOR LA H. XVIII LEGISLATURA, SIENDO GOBERNADOR\nCONSTITUCIONAL EL C. EUGENIO ELORDUY WALTHER 2001-2007.\nARTICULOS TRANSITORIOS\nPRIMERO.- Las presentes reformas entrarán en vigor el día siguiente de su publicación en el Periódico Oficial del Estado de Baja California.\nSEGUNDO.- Se derogan todas las disposiciones que se opongan a la presente reforma.\nDADO.- En el Salón de Sesiones “Lic. Benito Juárez García”, en la\nCiudad de Mexicali, Baja California”, a los quince días del mes de marzo del año dos mil siete.\nDIP. CARLOS ENRIQUE JIMÉNEZ RUIZ\nPRESIDENTE\n(RÚBRICA)\nDIP. GILBERTO DANIEL GONZÁLEZ SOLÍS\nSECRETARIO\n(RÚBRICA)\nDE CONFORMIDAD CON LO DISPUESTO POR LA FRACCION I DEL\nARTICULO 49 DE LA CONSTITUCION POLITICA DEL ESTADO, IMPRIMASE\nY PUBLÍQUESE.\nMEXICALI, BAJA CALIFORNIA, A DOS DIAS DEL MES DE MARZO\nDEL AÑO DOS MIL SIETE.\nGOBERNADOR DEL ESTADO\nEUGENIO ELORDUY WALTHER\n(RÚBRICA)\nSECRETARIO GENERAL DE GOBIERNO\nBERNARDO H. MARTINEZ AGUIRRE\n(RÚBRICA)\nARTICULO PRIMERO TRANSITORIO DEL DECRETO No. 405, POR\nEL QUE SE REFORMAN LOS ARTICULOS 4 Y 6, PUBLICADO EN EL\nPERIODICO OFICIAL No. 39, DE FECHA 10 DE SEPTIEMBRE DE 2010,\nTOMO CXVII, EXPEDIDO POR LA H. XIX LEGISLATURA, SIENDO\nGOBERNADOR CONSTITUCIONAL EL C. JOSE GUADALUPE OSUNA\nMILLAN 2007-2013.\nTRANSITORIO\nÚNICO.- Las presentes reformas entrarán en vigor al día siguiente de su publicación en el Periódico Oficial del Estado.\nDADO en el Salón de Sesiones “Lic. Benito Juárez García” del H. Poder\nLegislativo del Estado de Baja California, en la Ciudad de Mexicali, B.C., a los dieciséis días del mes de agosto del año dos mil diez.\nDIP. JUAN MANUEL GASTÉLUM BUENROSTRO\nPRESIDENTE\nDIP. CARLOS ALONSO ANGULO RENTERIA\nSECRETARIO\nY PUBLÍQUESE.\nMEXICALI, BAJA CALIFORNIA, A LOS TREINTA DÍAS DEL MES DE\nAGOSTO DEL AÑO DOS MIL DIEZ.\nGOBERNADOR DEL ESTADO\nJOSÉ GUADALUPE OSUNA MILLÁN\n(RÚBRICA)\nSECRERTARIO GENERAL\nCUAUHTÉMOC CARDONA BENAVIDES\n(RÚBRICA)\nARTICULO SEGUNDO TRANSITORIO DEL DECRETO No. 149, POR\nEL QUE SE APRUEBA LA REFORMA AL ARTÍCULO 4, PUBLICADO EN EL\nPERIODICO OFICIAL NO. 60, TOMO CXVIII, SECCION I, DE FECHA 30 DE\nDICIEMBRE DE 2011, EXPEDIDO POR LA H. XX LEGISLATURA, SIENDO\nGOBERNADOR CONSTITUCIONAL EL C. JOSE GUADALUPE OSUNA\nMILLAN 2007-2013.\nARTÍCULO TRANSITORIO\nÚNICO.- Las presentes reformas entrarán en vigor el día de su publicación en el Periódico Oficial de Estado de Baja California.\nDADO en el Salón de Sesiones “Lic. Benito Juárez García” del H. Poder\nLegislativo del Estado de Baja California, en la Ciudad de Mexicali, B.C., a los trece días del mes de diciembre del año dos mil once.\nLIC. MÁXIMO GARCÍA LÓPEZ\nDIPUTADO PRESIDENTE\nPROFR. ALFONSO GARZÓN ZATARAIN\nDIPUTADO SECRETARIO\nY PUBLIQUESE.\nMEXICALI, BAJA CALIFORNIA, A LOS VEINTIUN DÍAS DEL MES DE\nDICIEMBRE DEL AÑO DOS MIL ONCE.\nGOBERNADOR DEL ESTADO\nJOSE GUADALUPE OSUNA MILLAN\n(RÚBRICA)\nSECRETARIO GENERAL DE GOBIERNO\nCUAUHTEMOC CARDONA BENAVIDES\n(RÚBRICA)\nARTÍCULO CUARTO TRANSITORIO DEL DECRETO No. 489, POR EL\nQUE SE REFORMA EL ARTICULO 4, PUBLICADO EN EL PERIÓDICO\nOFICIAL No. 32, TOMO CXX, DE FECHA 19 DE JULIO DE 2013, EXPEDIDO\nPOR LA H. XX LEGISLATURA, SIENDO GOBERNADOR CONSTITUCIONAL\nEL C. JOSÉ GUADALUPE OSUNA MILLÁN 2007-2013;\nARTÍCULO TRANSITORIO\nÚNICO. El presente decreto entrará en vigor a los noventa días siguientes a su publicación en el Periódico Oficial del Estado de Baja California.\nDADO en el Salón de Sesiones “Lic. Benito Juárez García” del H. Poder\nLegislativo del Estado de Baja California, en la Ciudad de Mexicali, B.C., a los veintiocho días del mes de junio del año dos mil trece.\nDIP. GREGORIO CARRANZA HERNÁNDEZ\nPRESIDENTE\n(RÚBRICA)\nDIP. MARCO ANTONIO VIZCARRA CALDERÓN\nSECRETARIO\n(RÚBRICA)\nDE CONFORMIDAD CON LO DISPUESTO POR LA FRACCION I DEL\nY PUBLIQUESE.\nMEXICALI, BAJA CALIFORNIA, A LOS DOS DÍAS DEL MES DE JULIO\nDEL AÑO DOS MIL TRECE.\nJOSÉ GUADALUPE OSUNA MILLÁN\nGOBERNADOR DEL ESTADO\nFRANCISCO ANTONIO GARCÍA BURGOS\nSECRETARIO GENERAL DE GOBIERNO\nARTÍCULO QUINTO TRANSITORIO DEL DECRETO No. 246, POR EL\nQUE SE REFORMAN LOS ARTÍCULOS 2, 8, 9, 10 y 26, PUBLICADO EN EL\nPERIÓDICO OFICIAL No. 24, SECCION I, TOMO CXXII, DE FECHA 22 DE\nGOBERNADOR CONSTITUCIONAL EL C. FRANCISCO ARTURO VEDA DE\nLAMADRID 2013-2019.\nARTÍCULOS TRANSITORIOS\nPRIMERO.- Publíquense las presentes reformas en el Periódico Oficial del Estado de Baja California.\nSEGUNDO.- Las presentes reformas entrarán en vigor de manera gradual, en las fechas en que inicie vigencia el Código Nacional de\nProcedimientos Penales, de conformidad con las Declaratorias que emita el\nPoder Legislativo del Estado en los términos del artículo segundo transitorio del mencionado Código Nacional. Lo anterior, sin perjuicio de lo siguiente:\n1.- Las reformas a la Ley de Atención y Protección a la Víctima o el\nOfendido del Delito para el Estado de Baja California, y la reforma a los artículos 19, 22 y 23 de la Ley Orgánica de la Administración Pública del\nEstado, entrarán en vigor al día siguiente de su publicación en el Periódico\nOficial del Estado.\n2.- Las reformas a la Ley Orgánica de la Defensoría Pública del Estado de Baja California, entrarán en vigor al día siguiente de su publicación en el\nPeriódico Oficial del Estado, y su cumplimiento estará sujeto a la disponibilidad presupuestal.\n3.- Las reformas a la Ley del Sistema Integral de Justicia para\nAdolescentes del Estado de Baja California, entrarán en vigor al momento en que inicie vigencia dicha Ley conforme a su artículo transitorio primero.\n4.- Las reformas a la Ley Contra la Delincuencia Organizada para el\nEstado de Baja California, iniciarán vigencia a los noventa días después de su publicación en el Periódico Oficial del Estado.\nTERCERO.- Las menciones que en otras leyes, ordenamientos reglamentarios o acuerdos se haga respecto a la Subprocuraduría contra la\nDelincuencia Organizada, se entenderán hechas a la Subprocuraduría de\nInvestigaciones Especiales de la Procuraduría General de Justicia del Estado.\nCUARTO.- Quienes se encuentren ejerciendo el cargo de Juez de\nGarantía en el Partido Judicial de Mexicali, al momento de la entrada en vigor del presente Decreto conforme al transitorio segundo, pasarán a ejercer el cargo de Juez de Control a que se refiere la presente reforma, conservando sus derechos adquiridos por el periodo que fueron designados.\nLos jueces de control del Partido Judicial de Mexicali, fungirán como\nQUINTO.- La designación de los jueces de ejecución a que se refiere este Decreto, será de conformidad con la gradualidad prevista en el primer párrafo del artículo segundo transitorio de la presente reforma. cada partido judicial, según sea el caso, los jueces de garantía, control o de primer instancia atendiendo la naturaleza del proceso penal que dio lugar a la sentencia, continuarán conociendo y resolviendo los procedimientos competencia de los jueces de ejecución.\nDADO en el Salón de Sesiones “Lic. Benito Juárez García” del H. Poder\nLegislativo del Estado de Baja California, en la Ciudad de Mexicali, B.C., a los veintitrés días del mes de abril del año dos mil quince.\nDIP. FCO. ALCIBÍADES GARCÍA LIZARDI\nPRESIDENTE\n(RÚBRICA)\nDIP. ROSALBA LÓPEZ REGALADO\nSECRETARIA\n(RÚBRICA)\nDE CONFORMIDAD CON LO DISPUESTO POR LA FRACCION I DEL\nY PUBLIQUESE.\nMEXICALI, BAJA CALIFORNIA, A LOS CINCO DÍAS DEL MES DE MAYO DEL\nAÑO DOS MIL QUINCE.\nFRANCISCO ARTURO VEGA DE LAMADRID\nGOBERNADOR DEL ESTADO\nFRANCISCO RUEDA GOMEZ\nSECRETARIO GENERAL DE GOBIERNO",
  "ordenamiento": "REGLAMENTO",
  "jurisdiccion": "BAJA CALIFORNIA",
  "fuente_oficial": "Periódico Oficial",
  "FECHA PER OFIC": "2015/05/22",
  "ESTATUS": "VIGENTE",
  "TOMO": "TOMO_V",
  "URL": "https://www.congresobc.gob.mx/Documentos/ProcesoParlamentario/Leyes/TOMO_V/LEYODELIORG_22MAY2015.PDF",
  "es_escaneado": false,
  "tiene_tablas": true,
  "materia": [
    "penal",
    "seguridad",
    "justicia"
  ]
}