{
  "titulo": "Ley DE INGRESOS DEL ESTADO DE BAJA CALIFORNIA PARA EL EJERCICIO FISCAL DEL 2025",
  "Contenido": "PARA EL EJERCICIO FISCAL DEL AÑO 2025\nÍNDICE GENERAL.\nTÍTULO PRIMERO GENERALIDADES.\nTÍTULO SEGUNDO IMPUESTOS.\n- Capítulo I Impuesto sobre Actividades Mercantiles e\nIndustriales.\n- Capítulo II Impuesto sobre Remuneraciones al Trabajo Personal.\n- Capítulo III Impuesto sobre Diversiones y Espectáculos Públicos.\n- Capítulo IV Impuesto sobre Compraventa y Operaciones Similares.\n- Capítulo V Impuesto sobre Servicios de Hospedaje.\n- Capítulo VI Impuesto Ambiental sobre la Extracción y\nAprovechamiento de Materiales Pétreos.\nTÍTULO TERCERO CONTRIBUCIONES DE MEJORAS.\n- Capítulo Único Contribuciones de Mejoras.\nTÍTULO CUARTO DERECHOS.\n- Capítulo I Servicios de Agua.\n- Capítulo II Servicios de Control Vehicular.\n- Capítulo III Servicios del Instituto de Movilidad Sustentable.\n- Capítulo IV Servicios de la Dirección del Registro Público de la Propiedad y de Comercio.\n- Capítulo V Servicios de la Secretaría de Economía e\nInnovación.\n- Capítulo VI Servicios de la Secretaría de Medio Ambiente y\nDesarrollo Sustentable y la Procuraduría de\nProtección al Ambiente de Baja California.\n- Capítulo VII Legalización de Firmas, Expedición de Certificados y Certificaciones, Estudios de Cumplimiento, Publicaciones y servicios para valuadores y\nServicios de Protección Civil.\n- Capítulo VIII Servicios de la Secretaría de Infraestructura, Desarrollo Urbano y Reordenación Territorial.\n- Capítulo IX Servicios de la Secretaría de Agricultura y\nDesarrollo Rural.\n- Capítulo X Servicios del Instituto para el Desarrollo\nInmobiliario y de la Vivienda para el Estado.\n- Capítulo XI Servicios de la Secretaría de Seguridad Ciudadana.\n- Capítulo XII Registro de Establecimientos.\n- Capítulo XIII Servicios de la Dirección del Archivo General de\nNotarías.\n- Capítulo XIV Servicios de la Secretaría de Salud y del Instituto de Servicios de Salud Pública del Estado de Baja\nCalifornia.\n- Capítulo XV Servicios de la Secretaría de Educación y del\nBaja California.\n- Capítulo XVI Servicios de la Comisión Estatal de Energía.\n- Capítulo XVII Cooperación para Obras y Servicios Públicos.\n- Capítulo XVIII Obras de Urbanización.\nTÍTULO QUINTO CONTRIBUCIONES CAUSADAS EN EJERCICIOS ANTERIORES.\n- Capítulo Único Contribuciones causadas en ejercicios anteriores.\nTÍTULO SEXTO PRODUCTOS.\n- Capítulo I Explotación de Bienes del Estado.\n- Capítulo II Periódico Oficial, Venta de Formas y Otros\nProductos.\n- Capítulo III Almacenamiento y Guarda de Bienes en\nEstablecimientos dependientes del Estado.\n- Capítulo IV Explotación o Aprovechamiento de Establecimientos dependientes del Estado.\n- Capítulo V Ingresos de Organismos Descentralizados y Empresas de Participación Estatal.\n- Capítulo VI Intereses de Valores.\n- Capítulo VII Avalúos.\n- Capítulo VIII Otros.\nTÍTULO SÉPTIMO APROVECHAMIENTOS.\n- Capítulo I Recargos.\n- Capítulo II Donativos e Indemnizaciones.\n- Capítulo III Herencias y Legados a favor de la Hacienda Pública del Estado.\n- Capítulo IV Multas.\n- Capítulo V Reintegros.\n- Capítulo VI Cauciones, Fianzas y Depósitos cuya pérdida se declare por resolución firme.\nPúblicas.\n- Capítulo VIII Otorgamiento y Usufructo de Concesiones.\n- Capítulo IX Otros.\n- Capítulo Único Participaciones y Aportaciones Federales.\nTÍTULO NOVENO INGRESOS EXTRAORDINARIOS.\n- Capítulo Único Ingresos Extraordinarios.\nARTÍCULOS TRANSITORIOS: Primero, Segundo, Tercero, Cuarto, Quinto, Sexto, Séptimo, Octavo, Noveno, Décimo, Decimoprimero, Decimosegundo, Decimotercero, Decimocuarto, Decimoquinto, Decimosexto, Decimoséptimo, Decimoctavo, Decimonoveno, Vigésimo, Vigésimo Primero y Vigésimo\nSegundo.\nTÍTULO PRIMERO\nARTÍCULO 1.- Los ingresos que la Hacienda Pública del Estado percibirá durante el Ejercicio Fiscal comprendido del primero de enero al treinta y uno de diciembre del año dos mil veinticinco, serán los provenientes de los conceptos y en los importes estimados que a continuación se enumeran:\n(pesos)\n1.1 IMPUESTOS SOBRE LOS INGRESOS 871,445,069\n1.1.1 Impuesto sobre Actividades Mercantiles e Industriales 15,217,024\n1.1.2 Impuesto sobre Diversiones y\nEspectáculos Públicos 34,320,866\n1.1.3 Impuesto sobre Servicios de\nHospedaje 443,139,863\n1.1.4 Impuesto por la realización de\nJuegos con Apuestas y Sorteos 198,083,539\n1.1.5 Impuesto Estatal a la Venta Final de Bebidas con contenido Alcohólico 92,194,331\n1.1.6 Impuesto a Casas de Empeño 723,762\n1.1.7 Impuesto a Empresas de Redes de\nTransporte 87,765,684\n1.2 IMPUESTOS SOBRE EL PATRIMONIO 1,964,393,798\n1.2.1 Impuesto sobre Compraventa y\nOperaciones Similares 115,937,153\n1.2.2 Impuesto Estatal Sobre Tenencia o\nUso de Vehículos 301,310,764\n1.2.3 Impuesto a las Erogaciones en Juegos con Apuestas 802,631,010\n1.2.4 Impuesto por la Obtención de Premios 744,514,871\n1.3 IMPUESTOS SOBRE LA PRODUCCIÓN, EL CONSUMO Y LAS\nTRANSACCIONES 0\n1.4 IMPUESTOS AL COMERCIO EXTERIOR 0\n1.5 IMPUESTOS SOBRE NÓMINAS Y ASIMILABLES 12,142,120,147\n1.5.1 Impuesto sobre Remuneraciones al\nTrabajo Personal 12,142,120,147\n1.6 IMPUESTOS ECOLÓGICOS 3,464,671\n1.6.1 Impuesto Ambiental sobre la Extracción y\nAprovechamiento de Materiales Pétreos 3,464,671\n1.6.2 Impuesto Ambiental por la Emisión de\nGases a la Atmósfera 0\n1.7 ACCESORIOS 157,484,480\n1.7.1 Accesorios Impuestos Estatales 157,484,480\n1.8 OTROS IMPUESTOS 0\n1.9 IMPUESTOS NO COMPRENDIDOS EN LA LEY DE\nINGRESOS VIGENTE, CAUSADOS EN EJERCICIOS\nANTERIORES PENDIENTES DE LIQUIDACIÓN O PAGO 15,000,000\n1.9.1 Impuestos no comprendidos en la Ley de\nIngresos vigente, causados en ejercicios anteriores pendientes de liquidación o pago 15,000,000\n2 CUOTAS Y APORTACIONES DE SEGURIDAD SOCIAL 0\n2.1 APORTACIÓN PARA FONDO DE VIVIENDA 0\n2.2 CUOTAS PARA SEGURO SOCIAL 0\n2.3 CUOTAS DE AHORRO PARA EL RETIRO 0\n2.4 OTRAS CUOTAS Y APORTACIONES DE SEGURIDAD SOCIAL 0\n2.5 ACCESORIOS 0\n3 CONTRIBUCIONES DE MEJORAS 23,589,109\n3.1 CONTRIBUCIÓN DE MEJORAS POR OBRAS PÚBLICAS 23,589,109\n3.1.1 Contribuciones de Mejoras PIPCA 21,366,700\n3.1.2 Contribuciones de Mejoras FICOTIRO 2,222,409\n3.1.3 Contribuciones de Mejoras por Obra 0\n4 DERECHOS 3,889,000,674\n4.1 DERECHOS POR EL USO, GOCE, APROVECHAMIENTO O\nEXPLOTACIÓN DE BIENES DEL DOMINIO PÚBLICO 0\n4.2 DERECHOS A LOS HIDROCARBUROS 0\n4.3 DERECHOS POR PRESTACIÓN DE SERVICIOS 3,579,112,307\n4.3.1 Licencias de Conducir 475,180,116\n4.3.2 Placas, Calcomanías, Tarjeta de\nCirculación y Refrendo Servicio\nParticular 2,097,448,050\n4.3.3 Placas, Calcomanías, y Tarjeta de\nCirculación y Refrendo Servicio\nPúblico 0\n4.3.4 Placas, Calcomanías, y Tarjeta de\nCirculación Otros Servicios 148,366,993\n4.3.5 Registro Público de la Propiedad y de Comercio en materia de Propiedad 460,271,503\n4.3.6 Registro Público de la Propiedad y de Comercio en materia de Comercio 28,374,910\n4.3.7 Secretaría de Medio Ambiente y\nDesarrollo Sustentable 31,416,223\n4.3.8 Secretaría General de Gobierno 40,747,815\n4.3.9 Registro Civil del Estado 69,529,343\n4.3.10 Secretaría de Infraestructura, Desarrollo Urbano y Reordenación\nTerritorial 68,449,252\n4.3.11 Secretaría de Agricultura y\nDesarrollo Rural 20,843,124\n4.3.12 Secretaría de Seguridad Ciudadana 94,514,507\n4.3.13 Dirección de Archivo General de\nNotarías 6,777,935\n4.3.14 Secretaría de Salud 0\n4.3.15 Secretaría de Educación 25,029,837\n4.3.16 Secretaría de la Honestidad y la Función Pública 4,267,926\n4.3.19 Secretaría de Economía e Innovación 460,720\n4.3.20 Oficialía Mayor 7,434,054\n4.4 OTROS DERECHOS 0\n4.5 ACCESORIOS 309,888,367\n4.5.1 Multas 139,234,690\n4.5.2 Recargos 898,279\n4.5.3 Gastos de Ejecución 169,755,398\n5 PRODUCTOS 620,174,761\n5.1 PRODUCTOS 620,174,761\n5.1.1 Productos 30,632,988\n5.1.1.1 Venta de Periódico oficial 127,248\n5.1.1.2 Ingreso Aeropuerto 6,057,117\n5.1.1.3 Otros Productos 9,434,408\n5.1.1.4 Venta de Libros 135,050\n5.1.1.5 Poder Judicial 0\n5.1.1.6 Parque Eólico 14,879,165\n5.1.2 Ingresos Financieros Ramo 33 0\n5.1.3 Ingresos Financieros 553,087,370\n5.1.4 Ingresos Financieros por Recursos\nFederales 0\n5.1.5 Ingresos Financieros por Préstamos\nOtorgados 0\n5.1.6 Ingresos Financieros por\nParticipaciones 36,454,403\n5.1.10 Venta de Terrenos 0\n6 APROVECHAMIENTOS 241,926,092\n6.1 APROVECHAMIENTOS 233,529,790\n6.1.4 Multas Estatales 28,598,979\n6.1.5 Indemnizaciones 0\n6.1.6 Reintegros 176,840,143\n6.1.6.1 Reintegros 176,592,315\n6.1.6.2 Reintegros Apoyos Productivos 247,828\n6.1.7 Aprovechamientos provenientes de Obras\nPúblicas 0\n6.1.10 Aprovechamientos por Cheques Devueltos 0\n6.1.13 Otros Aprovechamientos 14,715,065\n6.1.13.1 Capacitación y Certificación de Competencia Laboral 144,700\n6.1.13.2 Otros Aprovechamientos 14,570,366\n6.1.14 Donativos 13,375,602\n6.1.14.1 Donativos 13,375,602\n6.2 APROVECHAMIENTOS PATRIMONIALES 0\n6.2.1 Terrenos 0\n6.3 ACCESORIOS APROVECHAMIENTOS 8,396,302\n6.3.1 Accesorios 0\n6.3.2 Recargos 0\n6.3.3 Gastos de Ejecución 8,396,302\n7 INGRESOS POR VENTA DE BIENES Y SERVICIOS 0\n8 PARTICIPACIONES Y APORTACIONES FEDERALES 66,643,757,977\n8.1 PARTICIPACIONES 39,001,631,872\n8.1.1 Fondo General de Participaciones 29,263,841,879\n8.1.2 Fondo Fomento Municipal 986,621,039\n8.1.3 Fondo de Fiscalización y Recaudación 1,944,397,409\n8.1.4 Fondo de Compensación 0\n8.1.5 Fondo de Extracción de Hidrocarburos 0\n8.1.6 Impuesto Especial sobre Producción y\nServicios 1,029,277,143\n8.1.7 0.136% de la Recaudación Federal\nParticipable 0\n8.1.8 3.17% sobre Extracción de Petróleo 0\n8.1.9 Gasolina y Diésel 1,395,563,700\n8.1.10 Fondo del Impuesto Sobre la Renta 4,381,930,702\n8.1.11 Fondo de Estabilización de los\nIngresos de las Entidades Federativas 0\n8.2 APORTACIONES RAMO 33 24,217,292,748\n8.2.1 Fondo de Aportaciones para la\nNómina Educativa y Gasto Operativo 15,115,098,097\n8.2.1.1 FONE Gastos de Operación 1,216,535,166\n8.2.1.2 FONE Fondo de Compensación 288,710,317\n8.2.1.3 FONE Servicios Personales 13,609,852,614\n8.2.2 Fondo de Aportaciones para los\nServicios de Salud 1,295,564,967\n8.2.2.1 Fondo Aportación Servicios\nSalud 1,295,564,967\n8.2.3 Fondo de Aportaciones para la\nInfraestructura Social 893,937,991\n8.2.3.1 FAIS Social Municipal 785,579,729\n8.2.3.2 FAIS Estatal 108,358,262\n8.2.4 Fondo de Aportaciones para el\nFortalecimiento de los Municipios y de las Demarcaciones Territoriales del Distrito Federal 3,603,721,779\n8.2.4.1 Fondo de Aportación\nFortalecimiento Municipal 3,603,721,779\n8.2.5 Fondo de Aportaciones Múltiples 998,045,581\n8.2.5.1 FAM Educación Básica 385,112,187\n8.2.5.2 FAM Educación Superior 215,722,985\n8.2.5.3 FAM Asistencia Social 370,739,331\n8.2.5.4 FAM Educación Media\nSuperior 26,471,078\n8.2.6 Fondo de Aportaciones para la\nEducación Tecnológica y de Adultos 204,682,544\n8.2.6.1 Fondo de Aportaciones para la Educación Tecnológica 204,682,544\n8.2.7 Fondo de Aportaciones para la\nSeguridad Pública de los Estados y del Distrito Federal 364,390,458\n8.2.7.1 Fondo Aportación Seguridad\nPública 364,390,458\n8.2.8 Fondo de Aportaciones para el\nFortalecimiento de las Entidades\nFederativas 1,741,851,331\n8.2.8.1 Fondo Aportación para\nFortalecimiento Entidades\nFederalizadas 1,741,851,331\n8.3 CONVENIOS 0\n8.3.1 Convenios de Protección Social en Salud 0\n8.3.2 Otros Convenios y Subsidios Federales 0\n8.3.3 Otros Convenios Estatales 0\n8.4 INCENTIVOS DERIVADOS DE LA COLABORACIÓN\nFISCAL 3,424,833,357\n8.4.2 Fondo de Compensación de ISAN 87,245,103\n8.4.3 Impuesto Sobre Automóviles Nuevos 520,530,715\n8.4.4 Fondo de Compensación de REPECOSINTERMEDIOS 46,334,884\n8.4.5 Otros Incentivos Económicos 2,770,722,655\n9 TRANSFERENCIAS, ASIGNACIONES, SUBSIDIOS Y SUBVENCIONES,\nY PENSIONES Y JUBILACIONES 0\n9.1 TRANSFERENCIAS Y ASIGNACIONES 0\n9.1.1 Transferencias de Recurso Estatal 0\n9.1.2 Transferencias de Recurso Federal 0\n9.2 TRANSFERENCIAS AL RESTO DEL SECTOR PÚBLICO 0\n9.3 SUBSIDIOS Y SUBVENCIONES 0\n9.3.1 Subsidios Sector Seguridad 0\n9.3.2 Subsidios Sector Educación 0\n9.3.3 Subsidios Sector Salud 0\n9.3.4 Subsidios Sector Gobierno 0\n9.3.5 Subsidios Sector Turismo 0\n9.3.6 Subsidios Sector Desarrollo Agropecuario 0\n9.3.7 Subsidios Sector Desarrollo Económico 0\n9.3.8 Subsidios Sector Desarrollo Social 0\n9.3.9 Subsidios Sector Infraestructura 0\n9.3.10 Subsidios Sector Cultura 0\n10 INGRESOS DERIVADOS DE FINANCIAMIENTO 0\n10.1 ENDEUDAMIENTO INTERNO 0\n10.1.1 Endeudamiento Interno 0\n10.1.2 Endeudamiento Externo 0\n10.1.3 Financiamiento Interno 0\nENTIDADES DE LA ADMINISTRACIÓN PÚBLICA\nPARAESTATAL 12,666,293,374\nComisión Estatal de Servicios Públicos de Mexicali 3,057,271,988\nComisión Estatal de Servicios Públicos de Tijuana 7,218,501,535\nComisión Estatal de Servicios Públicos de Ensenada 1,352,388,243\nComisión Estatal de Servicios Públicos de Tecate 591,202,901\nJunta de Urbanización del Estado 42,847,083\nInstituto para el Desarrollo Inmobiliario y de la Vivienda para el Estado 158,000,000\nInstituto de Servicios Educativos y\nPedagógicos de Baja California 10,335,000\nInstituto de Movilidad Sustentable del Estado de Baja California 235,746,624\nTOTAL DE INGRESOS DEL PODER EJECUTIVO Y\nENTIDADES PARAESTATALES 99,238,650,152\nTÍTULO SEGUNDO\nCAPÍTULO I\nIMPUESTO SOBRE ACTIVIDADES MERCANTILES E INDUSTRIALES.\nARTÍCULO 2.- El Impuesto sobre Actividades Mercantiles e\nIndustriales se causa con una tasa de..................... 2.0%\nCAPÍTULO II\nIMPUESTO SOBRE REMUNERACIONES AL TRABAJO PERSONAL.\nARTÍCULO 3.- De los ingresos estatales que se obtengan por este impuesto se destinará el 1.5% a un fideicomiso empresarial que tendrá los siguientes objetivos:\na).- Fortalecimiento de empresas instaladas en Baja California mediante instrumentos de financiamiento y asistencia técnica, Baja California, en los términos de las reglas que se emitan para tal efecto.\nb).- Realización de programas de promoción de la inversión y las exportaciones de bienes y servicios. Los gastos que se eroguen de acuerdo a las Reglas de Operación que se emitan para tal efecto.\nc).- Realización de proyectos estratégicos en alineación con la\nPolítica de Desarrollo Empresarial y los Planes Estratégicos\nMunicipales.\nNo se incluyen en dicha recaudación, los ingresos que se obtengan derivados del ejercicio de las facultades de cobro y/o de comprobación por parte de las autoridades fiscales.\nLa Secretaría de Economía e Innovación en coordinación con la\nSecretaría de Hacienda del Estado podrán emitir reglas específicas para la correcta administración y destino de los recursos en comento y los fideicomisos respectivos.\nCon independencia de lo que establezcan otras leyes, se incluye dentro de los sujetos referidos en el artículo 151-15 de la Ley de\nHacienda del Estado de Baja California, a cualquier ente público de\nMunicipal, que realice pagos por concepto de remuneraciones al trabajo personal, prestado dentro del territorio del Estado, bajo su dirección o dependencia de un tercero, incluidos las entidades paraestatales, paramunicipales y organismos autónomos.\nCAPÍTULO III\nIMPUESTO SOBRE DIVERSIONES Y ESPECTÁCULOS PÚBLICOS.\nARTÍCULO 4.- El Impuesto sobre Diversiones y Espectáculos Públicos, se causa conforme a las siguientes\nI.- Obras de Teatro y funciones de circo, por el ingreso bruto espectáculo.......................................... 2.96%\nII.- Espectáculos cómicos, taurinos, audiencias musicales, bailes, eventos de box y lucha, sobre el ingreso bruto percibido por la venta de boletos para entrar al espectáculo....... 5.0%\nIII.- Espectáculos de carpa y aquéllos en que participan deportistas profesionales, sobre el ingreso bruto percibido por la venta de boletos para entrar al espectáculo.......................................... 5.0%\nIV.- Espectáculos en que participen deportistas, músicos y actores no profesionales, así como los realizados por Instituciones\nEducativas y organizaciones que no persigan fines de lucro, sobre el ingreso bruto percibido por la venta de boletos para entrar al espectáculo................................. 5.0%\nV.- Espectáculos de frontón, carreras de caballos, o de galgos, sobre el ingreso bruto percibido por la venta de boletos para entrar al espectáculo................................. 10.0%\nVI.- Otras diversiones y espectáculos públicos, sobre el ingreso bruto percibido por la venta de boletos que importen el derecho de admisión para entrar al espectáculo........................................... 10.0% vendidos aquéllos por los que no se pague la entrada, por tener boletos de cortesía, pases, o por cualquier otro motivo, determinándose como base gravable de éstos, el costo promedio aritmético del valor de los boletos ofrecidos al público.\nPara la determinación del impuesto, en los casos en que para un sección, zona o ubicación, se considerará como base gravable el de costo mayor.\nCAPÍTULO IV\nIMPUESTO SOBRE COMPRAVENTA Y OPERACIONES SIMILARES.\nARTÍCULO 5.- El Impuesto Sobre Compraventa y Operaciones Similares, similares se causa a una tasa de 4.0%, a excepción de los actos por los que deba pagarse el Impuesto al Valor Agregado.\nPara efecto de este impuesto, la base gravable será la que a continuación se establece:\nA. Para vehículos año modelo 2015 y anteriores, la base del valores mínimos a que se refiere la fracción I, del Artículo 146 de la Ley de Hacienda del Estado de Baja California.\nB. Para vehículos año modelo 2016 y posteriores, la base del impuesto, será el resultado de multiplicar el valor total del vehículo contenido en la factura de origen de la agencia, armadora o distribuidora, por el factor de depreciación de acuerdo al año modelo del vehículo, en los siguientes términos:\nAÑOS DE FACTOR DE\nANTIGÜEDAD DEPRECIACIÓN\n0 1.000\n1 0.850\n2 0.725\n3 0.600\n4 0.500\n5 0.400\n6 0.300\n7 0.225\n8 0.150\n9 0.075\nPara los efectos de la depreciación, los años de antigüedad se año modelo al que corresponda el vehículo.\nCAPÍTULO V\nIMPUESTO SOBRE SERVICIOS DE HOSPEDAJE.\nARTÍCULO 6.- El Impuesto sobre Servicios de Hospedaje se causa con una tasa de................................................ 5.0% tasa será del.............................................. 7.0% aplicaciones digitales que actúen como intermediarias, promotoras o facilitadoras se causará con una tasa del................. 5.0% impuesto, serán destinados en un setenta por ciento al fortalecimiento, promoción y difusión de la actividad y sector turístico del Estado. No se incluyen en dicha recaudación, los ingresos que se obtengan derivados del ejercicio de las facultades de cobro o de comprobación por parte de las autoridades fiscales.\nEl ingreso por concepto del setenta por ciento de la recaudación del Impuesto sobre Servicios de Hospedaje, será administrado en un sesenta y cinco por ciento por el Ejecutivo Estatal para proyectos estratégicos de turismo en el Estado, y el treinta y cinco por ciento por el Fideicomiso Público para la Promoción Turística del\nEstado de Baja California, para ser destinado en los términos del mismo. correcto destino de los recursos en comento.\nCAPÍTULO VI\nMATERIALES PÉTREOS.\nARTÍCULO 7.- La cuota a enterar por el Impuesto Ambiental sobre\nExtracción y Aprovechamiento de Materiales pétreos, será de $4.78 pesos por metro cúbico extraído que sea aprovechado.\nTÍTULO TERCERO\nCONTRIBUCIONES DE MEJORAS\nCAPÍTULO ÚNICO de mejoras, conforme a lo que establecen las Leyes y Reglamentos respectivos.\nTÍTULO CUARTO\nDERECHOS POR LA PRESTACIÓN DE LOS SIGUIENTES SERVICIOS PÚBLICOS.\nCAPÍTULO I\nSERVICIOS DE AGUA.\nARTÍCULO 9.- Los derechos por consumo de agua se pagarán mensualmente en la Recaudación Auxiliar de Rentas adscrita a cada uno de los Organismos que presten el servicio, en los establecimientos y en las instituciones bancarias de la localidad autorizados para tal efecto, y están obligados al pago de las cuotas por consumo de agua, todas las personas físicas y morales, particulares, dependencias de los Gobiernos Federal, Estatal y\nMunicipal, así como las Entidades Paraestatales, organismos autónomos, Paramunicipales, Educativas o de Asistencia Pública o\nPrivada, independientemente de que en otras Leyes no sean objeto, sujeto, no causen o estén exentos de dichos derechos. Se otorgará pobreza mayores de 60 años, personas viudas en situación de pobreza mayores de 50 años, o que estando en situación de pobreza, sean el único sostén del hogar con hijos menores de edad, así como, personas con discapacidad, jubilados y pensionados, siempre que éstos no\nUnidad de Medida y Actualización, en los Municipios de Tijuana, Playas de Rosarito, Tecate, Ensenada y San Quintín con exención total del pago de los derechos por consumo de agua, siempre y cuando sus consumos no excedan de 15 m³; se otorgará exención del 50% del crédito fiscal cuando sus consumos mensuales no excedan de 25 m³; y tratándose del consumo excedente de 26 m³ mensuales pagarán por el consumo total de acuerdo a la tarifa normal de Ley. En tanto que, San Felipe, cuando los consumos domésticos de dicho sector de la población no excedan de 30 m³ mensuales se les otorgará exención total del pago; y por el excedente de 30 m³ mensuales pagarán por el consumo total de acuerdo a la tarifa normal de Ley. Este beneficio será únicamente por un domicilio del beneficiario, previo estudio socioeconómico elaborado por el Organismo respectivo y siempre que se cumpla con las reglas generales que para tal efecto determine el citado Organismo.\nLas personas mencionadas en el párrafo anterior, están igualmente obligadas al pago de los derechos de conexión de las redes, tanto de agua como drenaje, salvo las exenciones señaladas en el Título\nIX de la Ley de Hacienda del Estado de Baja California.\nLa falta de pago oportuno de los derechos a que se refiere este\nCapítulo, o la autorización para el pago en parcialidades de los mismos causarán recargos a la tasa que establece el Artículo 37 de la Ley de Ingresos del Estado.\nLos usuarios podrán hacer pagos anticipados a cuenta del consumo de agua de todo el año, durante los meses de enero y febrero del mismo año, en cuyo caso gozarán quienes hagan el pago total aproximado por los servicios obtenidos, de un descuento de 12% en enero y 8.5% en febrero respectivamente, sin que se causen los recargos correspondientes del mes de enero si es pagado en febrero.\nAsimismo, se podrán realizar pagos anticipados a cuenta del consumo de agua por un periodo de por lo menos seis meses, gozando de un\n5.5% de descuento, dicho pago se podrá efectuar a más tardar en el mes de julio.\nLos Centros de Reinserción Social (CERESOS) y las escuelas públicas de educación preescolar, primaria, secundaria, media superior o bachillerato, Sistema para el Desarrollo Integral de la Familia\n(DIF) y las oficinas públicas del Instituto del Deporte y la\nCultura Física de Baja California, pagarán los derechos por consumo\n50%. Se perderá este beneficio cuando se deje de cubrir tres meses consecutivos el pago de los derechos en un mismo ejercicio fiscal. utilicen en los usos propios de la institución, se les disminuirá la vigencia de esta Ley, el equivalente a 35 litros, por educando, docente y personal administrativo con que cuente la institución, por día natural, por mes, en los municipios de Mexicali y San\nFelipe, y de 30 litros en los municipios de Tecate, Tijuana, Playas de Rosarito, Ensenada y San Quintín, por educando, docente y personal administrativo con que cuente la institución, por día natural, por mes, siempre y cuando mantengan en operación dicha planta de tratamiento y presenten ante el Organismo que preste el servicio, en el municipio de que se trate, programas anuales que incluyan acciones concretas tendientes a promover la cultura del cuidado del agua, su uso eficiente y el uso de aguas residuales tratadas, incluso ampliación de la infraestructura en sus propias instalaciones o en la comunidad para riego de áreas verdes y otros usos compatibles. Al excedente de consumo de agua potable se le aplicará la tarifa no doméstica respectiva al municipio donde se ubique. Se entenderá como educando a los alumnos que cuando menos asistan en promedio cuatro horas por día hábil en calendario escolar. Para acceder a este beneficio, los compromisos que asuma la institución pública de educación superior o media superior, deberán quedar plasmados en el instrumento que para tal efecto suscriba con el Organismo que presta el servicio, los cuales deberán revisarse y cumplirse durante la vigencia de esta Ley.\nEn el caso de aquellos usuarios que no requieran de los servicios por consumo de agua, podrán solicitar la suspensión temporal de los mismos, siempre y cuando reúnan los siguientes requisitos: Hacer la petición por escrito, la suspensión sea por un periodo no menor a treinta días, que el inmueble se encuentre deshabitado y no presentar adeudo por contribuciones relativas al servicio de agua.\nEn este caso no se causará la cuota mínima que establece esta Ley, el aparato medidor quedará en resguardo del organismo operador, reanudación de los servicios correspondientes, o bien, haya consumo de agua. No se podrán reinstalar aparatos medidores que cumplieron funcionamiento.\nTratándose de consumos de agua de organismos públicos, poblados de los ejidos y colonias rurales de los municipios del Estado, asociaciones civiles de vecinos, derivados de tomas instaladas para el riego de camellones, parques y jardines públicos, los derechos correspondientes se causarán al 30% del importe de la tarifa respectiva a cargo de los mismos. Para gozar del beneficio se del agua establezca el Organismo operador de agua.\nLos beneficios fiscales mencionados en los párrafos anteriores, serán aplicables siempre y cuando no se tenga el beneficio de otro estímulo fiscal para los servicios prestados por los Organismos operadores de agua.\nLos derechos por consumo de agua que a continuación se expresan para cada uno de los Municipios, se calcularán aplicando la tarifa por metro cúbico consumido que estén previstas en cada uno de los distintos rangos en forma escalonada, es decir, por el excedente de los mismos, de forma tal que el monto a pagar por dicho consumo será la suma de todos y cada uno de los rangos consumidos.\nSe derogan las disposiciones que se establezcan en otras Leyes, reglamentos, acuerdos, circulares o disposiciones administrativas en la parte que contengan exenciones, totales o parciales, beneficios o estímulos fiscales, o consideren a personas como no sujetos de estos derechos, distintas a las comprendidas en las\nEstado.\nSECCIÓN I\nMUNICIPIO DE MEXICALI.\nA).- SERVICIO MEDIDO.\nPrecios al Consumidor (INPC) que corresponda al mes de facturación más un 1% acumulable cada mes. Este último porcentaje, no será aplicable a las tarifas establecidas en los tres primeros rangos de consumo que van desde 0 m³ hasta\n15 m³ para Uso Doméstico.\n1.- Uso doméstico.\na).- Los usuarios que tengan medidor en la Ciudad de consumido, en forma escalonada y por cada uno de los rangos, la siguiente:\n1.- De 0 hasta 5 m³, cuota mínima..... $ 92.17\n2.- Por el excedente de 5 y hasta 10 m³, por cada m³ consumido...................... $ 6.02\n3.- Por el excedente de 10 y hasta 15 m³, por cada m³ consumido...................... $ 8.10\n4.- Por el excedente de 15 y hasta 25 m³, por cada m³ consumido...................... $ 12.89\n5.- Por el excedente de 25 y hasta 30 m³, por cada m³ consumido...................... $ 13.40\n6.- Por el excedente de 30 y hasta 40 m³, por cada m³ consumido...................... $ 16.42\n7.- Por el excedente de 40 y hasta 50 m³, por cada m³ consumido...................... $ 26.60\n8.- Por el excedente de 50 y hasta 60 m³, por cada m³ consumido...................... $ 32.87\n9.- Por el excedente de 60 m³ en adelante, por cada m³ consumido...................... $ 47.53\nb).- Los usuarios que tengan medidor en los poblados\nGuadalupe Victoria, Ciudad Morelos, así como los dichos poblados en administración, operación y mantenimiento, causarán mensualmente por cada metro cúbico consumido, en forma escalonada y por cada uno de los rangos, la siguiente tarifa:\nGPE. VICTORIA\nY CD. MORELOS\n1.- De 0 hasta 5 m³, cuota mínima.... $ 89.14\n2.- Por el excedente de 5 y hasta 10 m³, por cada m³ consumido...................... $ 5.93\n3.- Por el excedente de 10 y hasta 15 m³, por cada m³ consumido...................... $ 6.58\n4.- Por el excedente de 15 y hasta 20 m³, por cada m³ consumido...................... $ 9.48\n5.- Por el excedente de 20 y hasta 25 m³, por cada m³ consumido...................... $ 11.17\n6.- Por el excedente de 25 y hasta 30 m³, por cada m³ consumido...................... $ 11.62\n7.- Por el excedente de 30 y hasta 40 m³, por cada m³ consumido...................... $ 12.11\n8.- Por el excedente de 40 y hasta 50 m³, por cada m³ consumido...................... $ 20.87\n9.- Por el excedente de 50 y hasta 60 m³, por cada m³ consumido...................... $ 20.79\n10.- Por el excedente de 60 y hasta 150 m³, por cada m³ consumido...................... $ 20.79\n11.- Por el excedente de 150 y hasta 300 m³, por cada m³ consumido................. $ 24.68\n12.- Por el excedente de 300 m³ en adelante, por cada m³ consumido................. $ 36.14 durante tres meses consecutivos, en el cuarto pago oportuno gozarán de un descuento del 15% sobre el importe de este último, sin que se interrumpa la comprendan dos ejercicios fiscales. servicio.\nPara continuar gozando de este descuento, además de seguir cumpliendo con lo dispuesto en el párrafo anterior, deberán transcurrir por lo menos tres meses entre la obtención de cada beneficio.\n2.- Uso comercial, industrial, gubernamental y otros no domésticos.\na).- Los usuarios que tengan medidor en la Ciudad de\nMexicali, causarán mensualmente por cada metro cúbico consumido, en forma escalonada y por cada uno de los rangos, la siguiente tarifa:\n1.- De 0 hasta 5 m³, cuota mínima..... $ 588.00\n2.- Por el excedente de 5 y hasta 10 m³, por cada m³ consumido...................... $ 103.95\n3.- Por el excedente de 10 y hasta 15 m³, por cada m³ consumido...................... $ 103.95\n4.- Por el excedente de 15 y hasta 20 m³, por cada m³ consumido......................$ 103.95\n5.- Por el excedente de 20 y hasta 30 m³, por cada m³ consumido...................... $ 103.95\n6.- Por el excedente de 30 y hasta 40 m³, por cada m³ consumido...................... $ 103.95\n7.- Por el excedente de 40 y hasta 50 m³, por cada m³ consumido...................... $ 122.01\n8.- Por el excedente de 50 y hasta 60 m³, por cada m³ consumido..................... $ 122.01\n9.- Por el excedente de 60 y hasta 100 m³, por cada m³ consumido..................... $ 132.77\n10.- Por el excedente de 100 y hasta 500 m³, por cada m³ consumido................. $ 137.51\n11.- Por el excedente de 500 y hasta 10,000 m³, por cada m³ consumido................. $ 137.51\n12.- Por el excedente de 10,000 m³ en adelante, por cada m³ consumido................. $ 162.74\nb).- Los usuarios que tengan medidor, en los Poblados\nGuadalupe Victoria, Ciudad Morelos, así como los ejidos o polos de desarrollo que pertenezcan a dichos poblados en administración, operación y mantenimiento, causarán mensualmente por cada metro cúbico consumido, en forma escalonada y por cada uno de los rangos, la siguiente tarifa:\nGPE. VICTORIA\nY CD. MORELOS\n1.- De 0 hasta 5 m³, cuota mínima......... $ 423.15\n2.- Por el excedente de 5 y hasta 10 m³, por cada m³ consumido............................. $ 18.07\n3.- Por el excedente de 10 y hasta 15 m³, por cada m³ consumido.......................... $ 18.07\n4.- Por el excedente de 15 y hasta 20 m³, por cada m³ consumido.......................... $ 18.07\n5.- Por el excedente de 20 y hasta 30 m³, por cada m³ consumido.......................... $ 19.24\n6.- Por el excedente de 30 y hasta 40 m³, por cada m³ consumido.......................... $ 25.85\n7.- Por el excedente de 40 y hasta 50 m³, por cada m³ consumido.......................... $ 39.14\n8.- Por el excedente de 50 y hasta 60 m³, por cada m³ consumido.......................... $ 48.52\n9.- Por el excedente de 60 y hasta 100 m³, por cada m³ consumido..................... $ 64.66\n10.- Por el excedente de 100 y hasta 500 m³, por cada m³Consumido........................... $ 76.65\n11.- Por el excedente de 500 y hasta 10,000 m³, por cada m³consumido...................... $ 82.80\n12.- Por el excedente de 10,000 m³ en adelante, por cada m³ consumido..................... $ 86.87\nEl 5 por ciento de la tarifa prevista en este numeral se destinará al proyecto Plan de Pluviales en Mexicali, a través del fideicomiso público o instrumento jurídico que para tal efecto determine la Secretaría de Hacienda.\nPara desarrolladores, fraccionadores, centros comerciales u otros no domésticos en donde el organismo determina la instalación de medidor control y cuyas redes aún no se encuentran entregadas al organismo, el desarrollador estará obligado a incluir en los proyectos de cada etapa de construcción la instalación de un medidor control, el cual servirá para registrar la diferencia que existe medidores individuales (la micro medición). estar cubiertos los derechos de uso de agua, derechos por consumo de agua y derechos de conexión; así como contratados los servicios al 100% de la micro medición; reubicación o cancelación del medidor según proceda.\n3.- En aquellos usuarios que por caso fortuito o fuerza mayor siendo ésta comprobada por el Organismo, se estará en lo dispuesto por el Manual de Políticas de Bonificaciones.\n4.- Agua sin potabilizar y puesta en el punto de conexión que determine el Organismo. en el punto de conexión que determine el organismo......................................... $20.68\nLos Organismos Públicos que produzcan agua para consumo humano, causarán mensualmente por cada metro cúbico consumido de aguas sin potabilizar y puesta en el punto de conexión que determine el organismo............ $ 9.35\n5.- El costo de agua por servicio y suministro en tomas fijas para ser distribuidas en camiones cisterna, exclusivamente a usuarios que no cuenten con sistemas de redes de agua potable en sus predios, por cada m³.................................................$38.47\n6.- Aguas residuales tratadas o sin tratar entregadas en planta o fuera de planta a quienes lo soliciten para uso industrial, comercial y agrícola.\na).- Tratada por cada m³ entregada en planta..... $ 6.48\nb).- Tratada por cada m³ entregada en la toma domiciliaria del usuario.....................$ 19.69\nc).- Tratada por cada m³ entregada en planta para uso agrícola.................................... $ 0.18\nd).- Sin tratar por cada m³ entregada en planta o en cualquier punto de la red del sistema de alcantarillado............................. $ 4.49\n7.- Derecho anual de reserva de aguas residuales, tratadas y no tratadas.\na).- Por cada m³............................ $ 0.38\n8.- Recepción y tratamiento de aguas residuales. materia ambiental y los ordenamientos técnicos.\na).- Remover la demanda bioquímica de oxígeno (DBO) por cada Kg............................... $ 27.80\nb).- Remover los sólidos suspendidos totales (SST) por cada Kg............................... $ 40.31\nc).- Remover grasas y aceites (G y A), por cada\nKg.................................... $ 8.56\nd).- Remover demanda química de oxigeno (DQO) por cada\nKg.................................... $ 27.80\ne).- Por cada revisión y verificación de las condiciones de las descargas de aguas residuales a la red de alcantarillado sanitario.............. $ 1,040.36\nf).- Por la recepción y tratamiento de aguas residuales sanitarias procedente de letrinas móviles descargadas mediante camiones cisterna (pipas), por cada m3.........................................$ 27.74\ng).- Recepción y tratamiento de aguas residuales sanitarias vertida por camiones cisterna (pipa), por m³..................................... $ 13.10\nh).- Análisis de laboratorio de los parámetros conforme a\nla NOM-002-SEMARNAT-1996............... $ 9,964.74\ni).- Análisis de laboratorio de parámetros fisicoquímicos básicos en forma individual, por toma de muestreo compuesto.............................. $ 1,994.34\nj).- Análisis de laboratorio de parámetros fisicoquímicos básicos en forma individual, por toma de muestreo simple................................. $ 1,085.27\nAdicionalmente al costo por toma de muestra, por cada parámetro que se solicite:\nPotencial de hidrogeno (ph)............ $ 66.39\nTemperatura............................ $ 132.86\nDemanda bioquímica de oxigeno (DBO5)... $ 934.23\nGrasas y aceites....................... $ 770.39\nSólidos sedimentables.................. $ 319.46\nSólidos suspendidos.................... $ 398.77\nNitrógeno total........................ $ 1,381.40\nFósforo total.......................... $ 442.03\nArsénico............................... $ 745.97\nCadmio................................. $ 511.11\nCianuro................................ $ 718.33\nCobre.................................. $ 511.11\nCromo.................................. $ 511.11\nMercurio............................... $ 745.97\nNíquel................................. $ 511.11\nPlomo.................................. $ 511.11\nZinc................................... $ 511.11\nCromo Hexavalente...................... $ 511.11\nColiformes fecales..................... $ 692.78\nHuevos de Helmintos.................... $ 1,381.40\nMateria flotante....................... $ 317.71\nDemanda química de oxígeno............. $ 971.27\nk).- Por la recepción de lodos estabilizados, residuos peligrosos, por m³.............. $ 609.17\nl).- Por la recepción de lodos sin estabilizar, residuos peligrosos, por m³.............. $ 1,665.58\nm).- Por la recepción de agua residual fuera de norma, proveniente de descargas al sistema de alcantarillado, de procesos productivos de empresas con giros industriales o comerciales, así como de fraccionamientos habitacionales, de conformidad con el artículo 277-B, fracción I, y Octavo Transitorio de la Ley Federal de Derechos, por cada m3....................................... $ 2.00\nn).- Por el permiso para descargar por medio de camiones cisterna aguas residuales sanitarias, de fosas sépticas y/o letrinas móviles, que cumplan con la normatividad, y las viertan en sitios autorizados por el organismo, por cada camión cisterna................................. $ 2,505.46 ñ).- Por la revalidación anual para descargar por medio de camiones cisterna aguas residuales sanitarias, de fosas sépticas y/o letrinas móviles, que cumplan con la normatividad, y las viertan en sitios autorizados por el organismo, por cada camión cisterna................................. $ 2,096.75\no).- Registro de descarga de aguas potencialmente contaminantes............................ $ 5,240.03\np).- Revaluación a los registros de descargas de aguas alcantarillado sanitario................. $ 2,987.50\nq).- Análisis de solicitud de prórroga para presentar alcantarillado sanitario................. $ 1,395.94\nr).- Cambios de razón social, fusiones, transferencias de trámites en general...................... $ 4,191.94\ns).- Por el análisis para reconsideración de residual................................. $ 2,440.11\nt).- Análisis de solicitud de prórroga para dar cumplimiento a condicionantes del permiso de descarga de agua residual............... $ 1,458.75\nu).- Análisis de solicitud de exención al trámite de permiso de descarga de agua residual..... $ 1,458.75\nv).- Constancia y revaluación anual de cumplimiento de aguas de tratamiento residual dentro de su proceso.....................................$ 422.06\nw).- Constancia y revaluación anual de cumplimiento de descarga para usuarios que operen dispositivos de pre tratamiento de aguas residuales, interceptor de grasas, aceites y solidos.................$ 3,214.51\nLa prestación del servicio será en los términos que establezca la Comisión Estatal de Servicios Públicos de\nMexicali.\nB).- TOMAS COMUNALES.\nLos consumos de las cuentas de este tipo de tomas, serán divididos entre el número de usuarios servidos del mismo vigente de acuerdo con la tarifa del punto número uno.\nC).- SERVICIO SIN MEDIDOR.\nPara los usuarios domésticos sin servicio medido, los consumos promedio de la zona, y para los no domésticos, el consumo será correspondiente, con base a las estadísticas de consumo para este tipo de usuarios.\nD).- DERECHOS DE CONEXIÓN AL SISTEMA DE AGUA POTABLE Y\nALCANTARILLADO SANITARIO.\n1.- Para los terrenos habitacionales unifamiliares de\nLey, y cuyo uso sea exclusivamente para casa habitación:\na).- A las redes del sistema de agua potable, por m² de superficie vendible, incluyendo áreas de donación.............................. $ 21.38\nb).- A las redes del sistema de alcantarillado sanitario por m² de superficie vendible, incluyendo áreas de donación.............................. $ 13.30\n2.- Para los terrenos destinados a desarrollos de vivienda de interés social, popular y de nivel medio, definidos de conformidad con el Artículo Quinto Transitorio de esta\nLey, por la incorporación a los sistemas de agua potable y alcantarillado sanitario por cada casa habitación construida o por construir, será de:\na).- Tratándose de vivienda de interés social:\n1).- Por agua potable.................. $ 2,998.94\n2).- Por alcantarillado sanitario...... $ 1,999.29\nb).- Tratándose de vivienda popular y de nivel medio:\n1).- Por agua potable.................. $ 5,021.36\n2).- Por alcantarillado sanitario...... $ 3,347.58\n3.- Para las viviendas unifamiliares, de los poblados de los ejidos y colonias rurales del Municipio de Mexicali, cuyo uso sea exclusivamente para casa habitación, sin tomar en cuenta el tipo o clasificación de la construcción, e sujete:\na).- A las redes del sistema de agua potable.\n...............................................$ 4,890.86\nb).- A las redes del sistema de alcantarillado. $ 2,968.34\n4.- Para terrenos en fraccionamientos residenciales quinto transitorio de esta Ley, y cuyo uso sea exclusivamente para casa habitación:\na).- A las redes del sistema de agua potable, por m² de superficie vendible, incluyendo áreas de donación................................. $ 69.19\nb).- A las redes del sistema de alcantarillado sanitario, por m² de superficie vendible, incluyendo áreas de donación................................... $ 44.20\n5.- Para los terrenos destinados a condominios y departamentos de renta:\na).- A las redes del sistema de agua potable, por m² de terreno................................... $ 41.38\nb).- A las redes del sistema de alcantarillado sanitario, por m² de terreno........................ $ 26.50\nc).- Adicionalmente a los incisos a) y b), por m² de construcción............................. $ 28.57 cálculo, deberá de acreditarse mediante documentación oficial que emita la autoridad municipal competente.\n6.- Para predios destinados a locales, establecimientos y desarrollos comerciales, industriales, de gobierno, turísticos y otros no domésticos, el cobro lo determinará el organismo previo análisis, en función a las necesidades de abasto de agua, infraestructura y capacidad de diseño, de acuerdo a las siguientes tarifas:\na).- A las redes del sistema de agua potable, por litro por segundo......................... $ 1’374,022.95\nb).- A las redes del sistema de alcantarillado sanitario, por litro por segundo............... $ 757,468.91\nc).- En aquellos casos en que no sea posible determinar las necesidades de abasto, capacidad de diseño e infraestructura, en la determinación del cobro por obtenido con la dotación para zona industrial, comercial y equipamiento urbano o donación de un litro por segundo por hectárea (l/s/ha)del área bruta a desarrollar; en tanto para la determinación del cobro por concepto de Derechos de Conexión al sistema de alcantarillado sanitario se tomará como base una aportación en gasto medio para zona industrial, comercial y equipamiento urbano y donación de 0.75 litros por segundo por hectárea\n(.75/s/ha)del área bruta a desarrollar.\nA excepción de los destinados a escuelas, parques, jardines y parques deportivos, de carácter públicos, que estarán exentos del pago de estos derechos. También estarán exentos del pago de estos derechos los campos y parques deportivos públicos que pertenezcan a los poblados de colonias agrícolas o ejidos del Valle de Mexicali.\nTratándose de los apartados de este inciso D), los dueños de los fraccionamientos y desarrollos, estarán obligados al pago de los derechos de conexión de agua potable y alcantarillado sanitario, por etapas completas, incluidas\nMunicipio y al Estado. doméstico a no doméstico, el organismo al tener conocimiento, cobrará la diferencia que resulte por el cambio del tipo de servicio, así también de existir derechos de conexión cubiertos con anterioridad, se previamente cubierto. fueron contratados, no siendo estos transferibles a un predio distinto. la reactivación de sus servicios, deberán pagar el costo\nAlcantarillado Sanitario, de no haber sido cubiertos con anterioridad. del organismo se demuestre que sus consumos y necesidad de abasto se han incrementado, están obligados a cubrir la diferencia que resulte del cálculo de los derechos de conexión para agua potable y alcantarillado sanitario, con base a la Ley de Ingresos vigente en la fecha que se determine la diferencia.\nE).- DERECHOS DE USO DE AGUA (DERECHOS DE RIEGO)\nEn los casos en donde el volumen de agua consumida sea mayor al volumen transferido por el concepto de derechos de uso de agua (derechos de riego) el usuario estará obligado a transferir gratuitamente al organismo los volúmenes que garanticen el suministro permanente y continuo del servicio del agua.\nF).- TOMAS Y DESCARGAS NO REGISTRADAS.\n1.- En caso de que sea detectada una toma no registrada instalada en este Municipio, el cobro será de la siguiente manera:\na).- En la detección de tomas no registradas domésticas, se tomará como base para el cobro 250 litros por día y por habitante, considerando hasta 4 habitantes por familia, por un máximo de hasta por 5 años, al 100% de dicha toma. este Artículo 9, como son las personas en situación de pobreza mayores de 60 años, personas viudas en situación de pobreza mayores de 50 años, o que estando en situación de pobreza, sean el único sostén del hogar con hijos menores de edad, así como, personas con discapacidad, jubilados y pensionados que no la Unidad de Medida y Actualización, se tomará como base para el cobro el cálculo contemplado en el párrafo anterior por un período máximo de 6 meses.\nb).- En la detección de tomas no registradas en locales, establecimientos y desarrollos comerciales, turísticos, industriales y gubernamentales, así como otras no domésticas, se tomará como base para el cobro por consumo de agua, el consumo medido promedio del giro correspondiente en base a las estadísticas de consumo para este tipo de servicio, proyectado desde la fecha de instalación de la toma, y si no fuere posible de determinar fecha cierta hasta por un máximo de 10 años, a la tarifa vigente de la Ley de Ingresos del Estado en la fecha en que sea detectada dicha toma.\nLa determinación del período de cobro para los incisos anteriores, se hará basándose en la documentación que presente el usuario con valor legal probatorio y dictamen emitido por el organismo, partiendo de la fecha de interconexión a la red que suministra el servicio de agua potable.\nAsimismo, el cobro deberá realizarse también por los derechos de conexión y obra según corresponda.\n2.- En caso de que sea detectada una descarga no registrada instalada en este Municipio, y que no cuenten con el servicio de agua potable, el cobro será de la siguiente manera:\na).- En la detección de descargas no registradas domésticas, se tomará como base para el cobro 120 litros por día y por habitante, considerando hasta 4 habitantes por familia, por un máximo de hasta por 5 años, al precio en que sea detectada dicha descarga. este Artículo 9, como son las personas en situación de pobreza mayores de 60 años, personas viudas en situación de pobreza mayores de 50 años, o que estando en situación de pobreza, sean el único sostén del hogar con hijos menores de edad, así como, personas con discapacidad, jubilados y pensionados que no obtengan ingresos mayores al equivalente a cinco veces la Unidad de Medida y\nActualización, se tomará como base para el cobro el cálculo contemplado en el párrafo anterior por un período máximo de 6 meses.\nb).- En la detección de descargas no registradas comerciales, gubernamentales, industriales y de desarrollos turísticos, así como otras no domésticas, los cobros serán estimados por el organismo de acuerdo al consumo medido promedio del giro correspondiente en base a las estadísticas de consumo para este tipo de servicio, hasta por un período de 10 años, al 50% de la tarifa de servicio medido vigente en la Ley de Ingresos del Estado en la fecha en que sea detectada dicha descarga.\nLa determinación del período de cobro para los incisos anteriores, se hará basándose en la documentación que presente el usuario con valor legal probatorio y dictamen emitido por el organismo, partiendo de la fecha de interconexión a la red de descargas de agua.\nAsimismo, el cobro deberá realizarse también por los derechos de conexión y obra según corresponda.\nG).- OTROS SERVICIOS:\n1.- Por la expedición de opiniones técnicas y/o de servicios potable, alcantarillado sanitario o alcantarillado pluvial, por cada cuenta asignada por el organismo con vigencia de seis meses:\na).- Para terrenos de uso Residencial......... $ 326.33\nb).- Para terrenos de uso Comercial, Industrial y otros no residenciales......................... $ 664.43\n2.- Por la expedición de dictamen de factibilidad o viabilidad de servicios, tanto por agua potable, alcantarillado sanitario o alcantarillado pluvial, con vigencia de seis meses, por cada servicio y por clave catastral:\na).- Para terrenos de uso residencial, comercial, industrial y turístico................... $ 554.96\nPara la expedición de la factibilidad de servicios de agua potable, alcantarillado sanitario y alcantarillado pluvial deberán estar cubiertos o convenidos los derechos de conexión correspondientes, así como donados los derechos de uso de agua\n(derechos de riego) en los predios solicitados.\nEn los casos en donde la solicitud de factibilidad de servicios correspondiente sea solicitado solo para la subdivisión del predio y no para el permiso de edificación o construcción no causará el pago de los derechos de conexión ni la cesión de los derechos de uso de agua (derechos de riego).\n3.- Por revisión de proyecto para la construcción de redes de agua potable, alcantarillado sanitario y alcantarillado pluvial, en predios hasta de 5,000 m² de superficie, por red........................................... $ 5,215.99\nMás, por cada m² de superficie adicional, por red.. $0.03\n4.- Por revisión de obras de agua potable, alcantarillado sanitario y alcantarillado pluvial, conforme a proyectos autorizados en predios hasta de 5,000 m² de superficie, por red, por mes............................. $ 21,418.12\nMás, por cada m² de superficie adicional, por red, por mes........................................... $ 0.04\n5.- Por hidrante contra incendios instalado del sistema de agua potable, el equivalente a 5 m³ mensuales a la tarifa para uso comercial, industrial, gubernamental y otros no domésticos.\n6.- Por expedición y certificación de documentos, con vigencia de seis meses........................ $ 208.60\n7.- Por expedición de certificados de libertad de gravamen...................................... $ 382.15\n8.- Por localización de toma o descarga por hora. $ 1,103.37\n9.- Instalación de medidor y protección de los mismos, instalación de toma de agua domiciliaria y descarga de drenaje de aguas negras, así como el costo de la introducción de las redes de agua potable y alcantarillado, y otros servicios no contemplados en este capítulo, se pagará el importe de acuerdo con el presupuesto que previamente formule el organismo que preste el servicio.\nEn los casos de usuarios que soliciten la reposición del medidor, el costo de la reposición se pagará de acuerdo al presupuesto que previamente formule el organismo, salvo aquellos casos de medidores que cumplieron su vida útil o que el organismo determine retirarlo por mal funcionamiento del mismo.\nEl costo de la introducción de las redes de agua potable y alcantarillado sanitario, se pagarán de acuerdo a los presta el servicio. Para aquellos usuarios que después de\n12 meses de haber sido ejecutada y notificada la obra y el presupuesto, no hayan contratado, el costo que deberá\nMedida y Actualización, desde la fecha de notificación la fecha de contratación.\n10.- Los propietarios o poseedores de predios que tengan una o el sistema de alcantarillado de aguas negras, se les aplicará el 50% de la tarifa de agua potable aplicable, sobre el volumen vertido a las descargas de aguas negras, operador.\n11.- Por la remoción de reductor en servicio doméstico........................................$ 251.27\n12.- Por tipos de reconexión de servicio de uso comercial, industrial, gubernamental y otros no domésticos:\na).- Reconexión para medidor de 12.6 mm (1/2”) hasta 19 mm\n(3/4”) de diámetro....................$340.25\nb).- Reconexión para medidor desde 25.4 mm(1”)hasta 50.8 mm (2”)de diámetro.......................... $ 543.15\nc).- Reconexión para medidor mayor de 50.8 mm (2”) de\n13.- Por el sondeo de descarga domiciliaria....... $ 913.09\n14.- Por revisión de proyecto para la construcción de plantas de tratamiento y cárcamos de bombeo:\na).- Hasta 10 lps............................. $ 24,352.72\nb).- De 10.1 a 30 lps......................... $ 34,917.88\nc).- Más de 30.1 lps.......................... $ 45,676.49\n15.- Por el trámite de cambio de propietario o poseedor del predio y/o razón social.......................$ 211.15\n16.- En aquellos casos en que el usuario requiera una inspección por parte del Organismo, se realizará el mencionan:\na).- Inspección General para usuarios Domésticos..$176.08\nb).- Inspección General para usuarios Comerciales, Industriales, Gubernamentales y otros No Domésticos\n................................................ $ 263.99\nc).- Por la revisión y detección de fuga interna no usuarios Domésticos............................$ 468.64\nd).- Por la revisión y detección de fuga interna no\nComerciales, Industriales, Gubernamentales y otros No\nDomésticos se cobrará de acuerdo al presupuesto que formule el Organismo.\n17.- En aquellos casos en donde el usuario realizó su depósito en garantía y éste se atrase hasta por tres meses o más, el organismo aplicará el importe correspondiente a los tres meses de depósito en contra de los adeudos existentes; liquidados los adeudos y extinguida la garantía, el organismo podrá dar de baja el servicio hasta en tanto no se garantice de nuevo el consumo conforme a la legislación aplicable.\nSECCIÓN II\nMUNICIPIO DE SAN FELIPE.\nA).- SERVICIO MEDIDO.\nPrecios al Consumidor (INPC) que corresponda al mes de facturación más un 1% acumulable cada mes. Este último porcentaje, no será aplicable a las tarifas establecidas en los tres primeros rangos de consumo que van desde 0 m³ hasta\n15 m³ para Uso Doméstico.\n1.- Uso doméstico. causarán mensualmente por cada metro cúbico consumido, en forma escalonada y por cada uno de los rangos, la siguiente:\n1.- De 0 hasta 5 m³, cuota mínima..... $ 92.17\n2.- Por el excedente de 5 y hasta 10 m³, por cada m³ consumido...................... $ 6.02\n3.- Por el excedente de 10 y hasta 15 m³, por cada m³ consumido...................... $ 8.10\n4.- Por el excedente de 15 y hasta 25 m³, por cada m³ consumido...................... $ 12.89\n5.- Por el excedente de 25 y hasta 30 m³, por cada m³ consumido...................... $ 13.40\n6.- Por el excedente de 30 y hasta 40 m³, por cada m³ consumido..................... $ 16.42\n7.- Por el excedente de 40 y hasta 50 m³, por cada m³ consumido...................... $ 26.60\n8.- Por el excedente de 50 y hasta 60 m³, por cada m³ consumido...................... $ 32.87\n9.- Por el excedente de 60 m³ en adelante, por cada m³ consumido...................... $ 47.53 meses consecutivos, en el cuarto pago oportuno gozarán de un descuento del 15% sobre el importe de este último, sin fiscales. servicio.\nPara continuar gozando de este descuento, además de anterior, deberán transcurrir por lo menos tres meses entre la obtención de cada beneficio.\n2.- Uso comercial, industrial, gubernamental y otros no domésticos.\nFelipe, causarán mensualmente por cada metro cúbico consumido, en forma escalonada y por cada uno de los rangos, la siguiente tarifa:\n1.- De 0 hasta 5 m³, cuota mínima............. $ 423.15\n2.- Por el excedente de 5 y hasta 10 m³, por cada m³ consumido................................. $ 31.52\n3.- Por el excedente de 10 y hasta 15 m³, por cada m³ consumido................................. $ 31.52\n4.- Por el excedente de 15 y hasta 20 m³, por cada m³ consumido................................. $ 31.52\n5.- Por el excedente de 20 y hasta 30 m³, por cada m³ consumido................................. $ 47.52\n6.- Por el excedente de 30 y hasta 40 m³, por cada m³ consumido................................. $ 53.12\n7.- Por el excedente de 40 y hasta 50 m³, por cada m³ consumido................................. $ 61.01\n8.- Por el excedente de 50 y hasta 60 m³, por cada m³ consumido................................. $ 72.67\n9.- Por el excedente de 60 y hasta 100 m³, por cada m³ consumido................................. $ 113.94\n10.- Por el excedente de 100 y hasta 500 m³, por cada m³\nConsumido................................. $ 114.96\n11.- Por el excedente de 500 y hasta 10,000 m³, por cada m³ consumido.............................. $ 115.72\n12.- Por el excedente de 10,000 m³ en adelante, por cada m³consumido............................... $ 138.82\nPara desarrolladores, fraccionadores, centros comerciales encuentran entregadas al organismo, el desarrollador estará obligado a incluir en los proyectos de cada etapa de construcción la instalación de un medidor control, el cual servirá para registrar la diferencia que existe entre el volumen total suministrado al fraccionamiento o desarrollo y el consumo total registrado por los medidores individuales (la micro medición).\nConcluida o entregada la etapa de edificación deberán estar cubiertos los derechos de uso de agua, derechos por consumo de agua y derechos de conexión; así como contratados los servicios al 100% de la micro medición; por lo que el desarrollador deberá solicitar la reubicación o cancelación del medidor según proceda.\n3.- En aquellos usuarios que por caso fortuito o fuerza mayor exista un consumo de agua involuntario en las instalaciones hidráulicas internas y deriven en un siendo ésta comprobada por el Organismo, se estará en lo dispuesto por el Manual de Políticas de Bonificaciones.\n4.- Agua sin potabilizar y puesta en el punto de conexión que determine el Organismo. en el punto de conexión que determine el organismo........................................ $20.69 humano, causarán mensualmente por cada metro cúbico de conexión que determine el organismo........... $ 9.35\n5.- El costo de agua por servicio y suministro en tomas fijas para ser distribuidas en camiones cisterna, redes de agua potable en sus predios, por cada m³ $ 38.47\n6.- Aguas residuales tratadas o sin tratar entregadas en industrial, comercial y agrícola.\na).- Tratada por cada m³ entregada en planta..... $ 6.48\nb).- Tratada por cada m³ entregada en la toma domiciliaria del usuario.....................$ 19.69\nc).- Tratada por cada m³ entregada en planta para uso agrícola.................................... $ 0.18\nd).- Sin tratar por cada m³ entregada en planta o en cualquier punto de la red del sistema de alcantarillado............................. $ 4.49\n7.- Derecho anual de reserva de aguas residuales, tratadas y no tratadas.\na).- Por cada m³............................... $ 0.39\n8.- Recepción y tratamiento de aguas residuales. materia ambiental y los ordenamientos técnicos.\na).- Remover la demanda bioquímica de oxígeno(DBO) por cada Kg.................................. $ 27.80\nb).- Remover los sólidos suspendidos totales(SST) por cada Kg................................. $ 40.31\nc).- Remover grasas y aceites (G y A), por cada\nKg....................................... $ 8.56\nd).- Remover demanda química de oxigeno(DQO) por cada\nKg...................................... $ 27.80\ne).- Por cada revisión y verificación de las condiciones alcantarillado sanitario................. $1,040.36\nf).- Por la recepción y tratamiento de aguas residuales mediante camiones cisterna (pipas), por cada m3.........................................$ 27.74\ng).- Recepción y tratamiento de aguas residuales sanitarias vertida por camiones cisterna (pipa), por m³..................................... $ 13.10\nh).- Análisis de laboratorio de los parámetros conforme a\nla NOM-002-SEMARNAT-1996............... $ 9,964.74\ni).- Análisis de laboratorio de parámetros fisicoquímicos básicos en forma individual, por toma de muestreo compuesto.............................. $ 1,994.34\nj).- Análisis de laboratorio de parámetros fisicoquímicos básicos en forma individual, por toma de muestreo simple................................. $ 1,085.27\nAdicionalmente al costo por toma de muestra, por cada parámetro que se solicite:\nPotencial de hidrogeno (ph).............. $ 66.40\nTemperatura.............................. $ 132.85\nDemanda bioquímica de oxigeno (DBO5)..... $ 934.23\nGrasas y aceites......................... $ 770.39\nSólidos sedimentables.................... $ 319.47\nSólidos suspendidos...................... $ 398.77\nNitrógeno total.......................... $1,381.40\nFósforo total............................ $ 442.03\nArsénico................................. $ 745.97\nCadmio................................... $ 511.11\nCianuro.................................. $ 718.33\nCobre.................................... $ 511.11\nCromo.................................... $ 511.11\nMercurio................................. $ 745.97\nNíquel................................... $ 511.11\nPlomo.................................... $ 511.11\nZinc..................................... $ 511.11\nCromo Hexavalente........................ $ 511.11\nColiformes fecales....................... $ 692.78\nHuevos de Helmintos...................... $1,381.40\nMateria flotante......................... $ 317.71\nDemanda química de oxígeno............... $ 971.28\nk).- Por la recepción de lodos estabilizados, provenientes de plantas de tratamiento de aguas residuales de fraccionamientos habitacionales y de empresas con giros que no utilicen ni contengan residuos peligrosos, por m³.............. $ 609.17\nl).- Por la recepción de lodos sin estabilizar, provenientes de plantas de tratamiento de aguas residuales de fraccionamientos habitacionales y de empresas con giros que no utilicen ni contengan residuos peligrosos, por m³.............. $ 1,665.58\nm).- Por la recepción de agua residual fuera de norma, proveniente de descargas al sistema de alcantarillado, de procesos productivos de empresas con giros industriales o comerciales, así como de\nPlantas de Tratamiento de Aguas Residuales de fraccionamientos habitacionales, de conformidad con el artículo 277-B, fracción I, y Octavo Transitorio de la Ley Federal de Derechos, por cada m3... $ 2.00\nn).- Por el permiso para descargar por medio de camiones cisterna aguas residuales sanitarias, de fosas sépticas y/o letrinas móviles, que cumplan con la normatividad, y las viertan en sitios autorizados por el organismo, por cada camión cisterna................................$ 2,505.46 ñ).- Por la revalidación anual para descargar por medio de camiones cisterna aguas residuales sanitarias, de fosas sépticas y/o letrinas móviles, que cumplan con la normatividad, y las viertan en sitios autorizados por el organismo, por cada camión cisterna................................. $ 2,096.75\no).- Registro de descarga de aguas potencialmente contaminantes............................ $ 5,240.03\np).- Revaluación a los registros de descargas de aguas alcantarillado sanitario................. $ 2,987.50\nq).- Análisis de solicitud de prórroga para presentar potencialmente contaminantes a los sistemas de alcantarillado sanitario................. $ 1,395.94\nr).- Cambios de razón social, fusiones, transferencias de derechos y obligaciones respecto a resoluciones o trámites en general...................... $ 4,191.94\ns).- Por el análisis para reconsideración de condicionantes de permiso de descarga de agua residual................................. $ 2,440.11\nt).- Análisis de solicitud de prórroga para dar cumplimiento a condicionantes del permiso de descarga de agua residual............... $ 1,458.75\nu).- Análisis de solicitud de exención al trámite de permiso de descarga de agua residual..... $ 1,458.75\nv).- Constancia y revaluación anual de cumplimiento de aguas de tratamiento residual dentro de su proceso.....................................$ 422.06\nw).- Constancia y revaluación anual de cumplimiento de pre tratamiento de aguas residuales, interceptor de grasas, aceites y solidos.................$ 3,214.51\nMexicali.\nB).- TOMAS COMUNALES.\nLos consumos de las cuentas de este tipo de tomas, serán vigente de acuerdo con la tarifa del punto número uno.\nC).- SERVICIO SIN MEDIDOR.\nPara los usuarios domésticos sin servicio medido, los consumos serán estimados por el organismo de acuerdo al consumo medido promedio de la zona, y para los no domésticos, el consumo será determinado de acuerdo al consumo medido promedio del giro correspondiente, con base a las estadísticas de consumo para este tipo de usuarios.\nD).- DERECHOS DE CONEXIÓN AL SISTEMA DE AGUA POTABLE Y\nALCANTARILLADO SANITARIO.\n1.- Para los terrenos habitacionales unifamiliares de fraccionamientos y colonias populares definidos de conformidad con el Artículo Quinto Transitorio de esta\nLey, y cuyo uso sea exclusivamente para casa habitación:\na).- A las redes del sistema de agua potable, por m² de superficie vendible, incluyendo áreas de donación.............................. $ 21.38\nb).- A las redes del sistema de alcantarillado sanitario por m² de superficie vendible, incluyendo áreas de donación.............................. $ 13.30\n2.- Para los terrenos destinados a desarrollos de vivienda de interés social, popular y de nivel medio, definidos de\nLey, por la incorporación a los sistemas de agua potable construida o por construir, será de:\na).- Tratándose de vivienda de interés social:\n1).- Por agua potable.................. $ 2,998.94\n2).- Por alcantarillado sanitario...... $ 1,999.29\nb).- Tratándose de vivienda popular y de nivel medio:\n1).- Por agua potable.................. $ 5,021.36\n2).- Por alcantarillado sanitario...... $ 3,347.58\n3.- Para terrenos en fraccionamientos residenciales quinto transitorio de esta Ley, y cuyo uso sea exclusivamente para casa habitación:\na).- A las redes del sistema de agua potable, por m² de superficie vendible, incluyendo áreas de donación....................... $ 69.19\nb).- A las redes del sistema de alcantarillado sanitario, por m² de superficie vendible, incluyendo áreas de donación................................ $ 44.20\n4.- Para los terrenos destinados a condominios y departamentos de renta:\na).- A las redes del sistema de agua potable, por m² de terreno................................. $ 41.38\nb).- A las redes del sistema de alcantarillado sanitario, por m² de terreno....................... $ 26.50\nc).- Adicionalmente a los incisos a) y b), por m² de construcción............................. $ 28.57 cálculo, deberá de acreditarse mediante documentación oficial que emita la autoridad municipal competente.\n5.- Para predios destinados a locales, establecimientos y desarrollos comerciales, industriales, de gobierno, turísticos y otros no domésticos, el cobro lo determinará el organismo previo análisis, en función a las necesidades de abasto de agua, infraestructura y capacidad de diseño, de acuerdo a las siguientes tarifas:\na).- A las redes del sistema de agua potable, por litro por segundo......................... $ 1’374,022.95\nb).- A las redes del sistema de alcantarillado sanitario, por litro por segundo............... $ 757,468.91\nc).- En aquellos casos en que no sea posible determinar las necesidades de abasto, capacidad de diseño e infraestructura, en la determinación del cobro por concepto de Derechos de Conexión al sistema de agua potable se tomará como base un gasto medio diario obtenido con la dotación para zona industrial, comercial y equipamiento urbano o donación de un litro por segundo por hectárea (l/s/ha)del área bruta a desarrollar; en tanto para la determinación del cobro por concepto de Derechos de Conexión al sistema de alcantarillado sanitario se tomará como base una aportación en gasto medio para zona industrial, comercial y equipamiento urbano y donación de 0.75 litros por segundo por hectárea\n(.75/s/ha)del área bruta a desarrollar.\nA excepción de los destinados a escuelas, parques, jardines y parques deportivos, de carácter públicos, que estarán exentos del pago de estos derechos.\nTratándose de los apartados de este inciso D), los dueños de los fraccionamientos y desarrollos, estarán obligados al pago de los derechos de conexión de agua potable y alcantarillado sanitario, por etapas completas, incluidas\nMunicipio y al Estado. doméstico a no doméstico, el organismo al tener conocimiento, cobrará la diferencia que resulte por el cambio del tipo de servicio, así también de existir derechos de conexión cubiertos con anterioridad, se previamente cubierto. fueron contratados, no siendo estos transferibles a un predio distinto. la reactivación de sus servicios, deberán pagar el costo\nAlcantarillado Sanitario, de no haber sido cubiertos con anterioridad. del organismo se demuestre que sus consumos y necesidad de abasto se han incrementado, están obligados a cubrir la diferencia que resulte del cálculo de los derechos de conexión para agua potable y alcantarillado sanitario, con base a la Ley de Ingresos vigente en la fecha que se determine la diferencia.\nE).- DERECHOS DE USO DE AGUA (DERECHOS DE RIEGO)\nEn los casos en donde el volumen de agua consumida sea mayor al volumen transferido por el concepto de derechos de uso de agua (derechos de riego) el usuario estará obligado a transferir gratuitamente al organismo los volúmenes que garanticen el suministro permanente y continuo del servicio del agua.\nF).- TOMAS Y DESCARGAS NO REGISTRADAS.\n1.- En caso de que sea detectada una toma no registrada instalada en este Municipio, el cobro será de la siguiente manera:\na).- En la detección de tomas no registradas domésticas, se tomará como base para el cobro 250 litros por día y por habitante, considerando hasta 4 habitantes por familia, por un máximo de hasta por 5 años, al 100% de dicha toma. este Artículo 9, como son las personas en situación de pobreza mayores de 60 años, personas viudas en situación de pobreza mayores de 50 años, o que estando en situación de pobreza, sean el único sostén del hogar con hijos menores de edad, así como, personas con discapacidad, jubilados y pensionados que no la Unidad de Medida y Actualización, se tomará como base para el cobro el cálculo contemplado en el párrafo anterior por un período máximo de 6 meses.\nb).- En la detección de tomas no registradas en locales, establecimientos y desarrollos comerciales, turísticos, industriales y gubernamentales, así como otras no domésticas, se tomará como base para el cobro por consumo de agua, el consumo medido promedio del giro correspondiente en base a las estadísticas de consumo para este tipo de servicio, proyectado desde la fecha de instalación de la toma, y si no fuere posible de determinar fecha cierta hasta por un máximo de 10 años, a la tarifa vigente de la Ley de Ingresos del Estado en la fecha en que sea detectada dicha toma.\nLa determinación del período de cobro para los incisos anteriores, se hará basándose en la documentación que presente el usuario con valor legal probatorio y dictamen emitido por el organismo, partiendo de la fecha de interconexión a la red que suministra el servicio de agua potable.\nAsimismo, el cobro deberá realizarse también por los derechos de conexión y obra según corresponda.\n2.- En caso de que sea detectada una descarga no registrada instalada en este Municipio, y que no cuenten con el servicio de agua potable, el cobro será de la siguiente manera:\na).- En la detección de descargas no registradas domésticas, se tomará como base para el cobro 120 litros por día y por habitante, considerando hasta 4 habitantes por familia, por un máximo de hasta por 5 años, al precio en que sea detectada dicha descarga. este Artículo 9, como son las personas en situación de pobreza mayores de 60 años, personas viudas en situación de pobreza mayores de 50 años, o que estando en situación de pobreza, sean el único sostén del hogar con hijos menores de edad, así como, personas con discapacidad, jubilados y pensionados que no obtengan ingresos mayores al equivalente a cinco veces la Unidad de Medida y\nActualización, se tomará como base para el cobro el cálculo contemplado en el párrafo anterior por un período máximo de 6 meses.\nb).- En la detección de descargas no registradas comerciales, gubernamentales, industriales y de desarrollos turísticos, así como otras no domésticas, los cobros serán estimados por el organismo de acuerdo al consumo medido promedio del giro correspondiente en base a las estadísticas de consumo para este tipo de servicio, hasta por un período de 10 años, al 50% de la tarifa de servicio medido vigente en la Ley de Ingresos del Estado en la fecha en que sea detectada dicha descarga.\nLa determinación del período de cobro para los incisos anteriores, se hará basándose en la documentación que presente el usuario con valor legal probatorio y dictamen emitido por el organismo, partiendo de la fecha de interconexión a la red de descargas de agua.\nAsimismo, el cobro deberá realizarse también por los derechos de conexión y obra según corresponda.\nG).- OTROS SERVICIOS:\n1.- Por la expedición de opiniones técnicas y/o de servicios potable, alcantarillado sanitario o alcantarillado pluvial, por cada cuenta asignada por el organismo con vigencia de seis meses:\na).- Para terrenos de uso Residencial......... $ 326.33\nb).- Para terrenos de uso Comercial, Industrial y otros no residenciales......................... $ 664.43\n2.- Por la expedición de dictamen de factibilidad o viabilidad de servicios, tanto por agua potable, alcantarillado sanitario o alcantarillado pluvial, con vigencia de seis meses, por cada servicio y por clave catastral:\na).- Para terrenos de uso residencial, comercial, industrial y turístico................... $ 554.96\nPara la expedición de la factibilidad de servicios de agua potable, alcantarillado sanitario y alcantarillado pluvial deberán estar cubiertos o convenidos los derechos de conexión correspondientes, así como donados los derechos de uso de agua\n(derechos de riego) en los predios solicitados.\nEn los casos en donde la solicitud de factibilidad de servicios correspondiente sea solicitada solo para la subdivisión del predio y no para el permiso de edificación o construcción no causará el pago de los derechos de conexión ni la cesión de los derechos de uso de agua (derechos de riego).\n3.- Por revisión de proyecto para la construcción de redes de agua potable, alcantarillado sanitario y alcantarillado pluvial, en predios hasta de 5,000 m² de superficie, por red........................................... $ 5,215.99\nMás, por cada m² de superficie adicional, por red.. $0.03\n4.- Por revisión de obras de agua potable, alcantarillado sanitario y alcantarillado pluvial, conforme a proyectos autorizados en predios hasta de 5,000 m² de superficie, por red, por mes............................ $ 20,418.12\nMás, por cada m² de superficie adicional, por red, por mes........................................... $ 0.04\n5.- Por hidrante contra incendios instalado del sistema de agua potable, el equivalente a 5 m³ mensuales a la tarifa para uso comercial, industrial, gubernamental y otros no domésticos.\n6.- Por expedición y certificación de documentos, con vigencia de seis meses........................ $ 208.60\n7.- Por expedición de certificados de libertad de gravamen...................................... $ 382.15\n8.- Por localización de toma o descarga por hora.. $ 1,103.37\n9.- Instalación de medidor y protección de los mismos, instalación de toma de agua domiciliaria y descarga de drenaje de aguas negras, así como el costo de la introducción de las redes de agua potable y alcantarillado, y otros servicios no contemplados en este capítulo, se pagará el importe de acuerdo con el presupuesto que previamente formule el organismo que preste el servicio.\nEn los casos de usuarios que soliciten la reposición del medidor, el costo de la reposición se pagará de acuerdo al presupuesto que previamente formule el organismo, salvo aquellos casos de medidores que cumplieron su vida útil o que el organismo determine retirarlo por mal funcionamiento del mismo.\nEl costo de la introducción de las redes de agua potable y alcantarillado sanitario, se pagará de acuerdo a los presta el servicio. Para aquellos usuarios que después de\n12 meses de haber sido ejecutada y notificada la obra y el presupuesto, no hayan contratado, el costo que deberá\nMedida y Actualización, desde la fecha de notificación la fecha de contratación.\n10.- Los propietarios o poseedores de predios que tengan una o el sistema de alcantarillado de aguas negras, se les aplicará el 50% de la tarifa de agua potable aplicable, sobre el volumen vertido a las descargas de aguas negras, operador.\n11.- Por la remoción de reductor en servicio doméstico........................................ $251.27\n12.- Por tipos de reconexión de servicio de uso comercial, industrial, gubernamental y otros no domésticos:\na).- Reconexión para medidor de 12.6 mm (1/2”) hasta 19 mm\n(3/4”) de diámetro.......................... $ 340.25\nb).- Reconexión para medidor desde 25.4 mm(1”)hasta 50.8 mm (2”)de diámetro.......................... $ 543.15\nc).- Reconexión para medidor mayor de 50.8 mm (2”) de diámetro.................................... $ 656.73\n13.- Por el sondeo de descarga domiciliaria.......... $ 913.09\n14.- Por revisión de proyecto para la construcción de plantas de tratamiento y cárcamos de bombeo:\na).- Hasta 10 lps............................. $ 24,352.72\nb).- De 10.1 a 30 lps......................... $ 34,917.88\nc).- Más de 30.1 lps.......................... $ 45,676.49\n15.- Por el trámite de cambio de propietario o poseedor del predio y/o razón social.........................$ 211.15\n16.- En aquellos casos en que el usuario requiera una inspección por parte del Organismo, se realizará el mencionan:\na).- Inspección General para usuarios Domésticos...$176.08\nb).- Inspección General para usuarios Comerciales, Industriales, Gubernamentales y otros No Domésticos\n................................................ $ 263.99\nc).- Por la revisión y detección de fuga interna no usuarios Domésticos............................ $468.64\nd).- Por la revisión y detección de fuga interna no\nComerciales, Industriales, Gubernamentales y otros No\nDomésticos se cobrará de acuerdo al presupuesto que formule el Organismo.\n17.- En aquellos casos en donde el usuario realizó su depósito en garantía y éste se atrase hasta por tres meses o más, el organismo aplicará el importe correspondiente a los tres meses de depósito en contra de los adeudos existentes; liquidados los adeudos y extinguida la garantía, el organismo podrá dar de baja el servicio hasta en tanto no se garantice de nuevo el consumo conforme a la legislación aplicable.\nSECCIÓN III\nMUNICIPIO DE ENSENADA.\nA).- SERVICIO MEDIDO.\nPrecios al Consumidor (INPC) que corresponda al mes de facturación más un 1% acumulable cada mes. Este último porcentaje, no será aplicable a las tarifas establecidas en los tres primeros rangos de consumo que van desde 0 m³ hasta\n15 m³ para Uso Doméstico.\n1.- Uso doméstico.\na).- Los usuarios que tengan medidor en la Ciudad de\nEnsenada y áreas conurbadas, desarrollos turísticos como: Puerto Salina, Punta Piedra, Bajamar, Las\nOlas, Ejido Úrsulo Galván, así como otros que se desarrollen o incorporen al sistema, causarán mensualmente por cada metro cúbico consumido, en forma escalonada y por cada uno de los rangos, la siguiente\n1).- De 0 hasta 5 m³, cuota mínima....... $ 131.05\n2).- Por el excedente de 5 y hasta 10 m³..$ 30.12\n3).- Por el excedente de 10 y hasta 15 m³.$ 34.31\n4).- Por el excedente de 15 y hasta 20 m³.$ 61.25\n5).- Por el excedente de 20 y hasta 25 m³.$ 93.65\n6).- Por el excedente de 25 y hasta 30 m³.$ 113.13\n7).- Por el excedente de 30 y hasta 40 m³.$ 143.56\n8).- Por el excedente de 40 y hasta 50 m³.$ 154.87\n9).- Por el excedente de 50 y hasta 60 m³.$ 161.88\n10).- Por el excedente de 60 m³........... $ 163.91\nb).- Los usuarios que tengan medidor en los poblados no contemplados en el inciso a), así como los ejidos o polos de desarrollo que pertenezcan a dichos poblados en administración, operación y mantenimiento, causarán mensualmente por cada metro cúbico consumido, en forma escalonada y por cada uno de los rangos, la siguiente\n1).- De 0 hasta 5 m³, cuota mínima...... $ 78.65\n2).- Por el excedente de 5 y hasta 10 m³. $ 18.09\n3).- Por el excedente de 10 y hasta 15 m³.$ 20.54\n4).- Por el excedente de 15 y hasta 20 m³.$ 36.85\n5).- Por el excedente de 20 y hasta 25 m³.$ 55.94\n6).- Por el excedente de 25 y hasta 30 m³.$ 67.88\n7).- Por el excedente de 30 y hasta 40 m³.$ 86.11\n8).- Por el excedente de 40 y hasta 50 m³.$ 93.00\n9).- Por el excedente de 50 y hasta 60 m³.$ 97.13\n10).- Por el excedente de 60 m³........... $ 98.35\nA los usuarios domésticos que efectúen su pago mensual y lo hagan antes de la fecha de vencimiento durante tres meses consecutivos, en el cuarto pago oportuno gozarán de un descuento del 15% sobre el importe de este último; sin que se interrumpa la consecutividad de los pagos mensuales cuando éstos comprendan dos ejercicios fiscales. servicio.\nPara continuar gozando de este descuento, además de anterior, deberán transcurrir por lo menos tres meses entre la obtención de cada beneficio.\n2.- Uso comercial, industrial, gubernamental y otros no domésticos.\na).- Los usuarios que tengan medidor en la Ciudad de\nEnsenada y áreas conurbadas, desarrollos turísticos como: Puerto Salina, Punta Piedra, Bajamar, Las\nOlas, Ejido Úrsulo Galván, así como otros que se desarrollen o incorporen al sistema, causarán mensualmente por cada metro cúbico consumido, en forma escalonada y por cada uno de los rangos, la siguiente\nTARIFA:\n1).- De 0 hasta 5 m³, cuota mínima........ $1,111.00\n2).- Por el excedente de 5 y hasta 10 m³.. $ 131.37\n3).- Por el excedente de 10 y hasta 15 m³. $ 179.21\n4).- Por el excedente de 15 y hasta 20 m³. $ 211.02\n5).- Por el excedente de 20 y hasta 30 m³. $ 247.59\n6).- Por el excedente de 30 y hasta 40 m³. $ 252.25\n7).- Por el excedente de 40 y hasta 50 m³. $ 264.85\n8).- Por el excedente de 50 y hasta 60 m³. $ 280.06\n9).- Por el excedente de 60 y hasta 10,000 m³................................... $ 281.07\n10).- Por el excedente de 10,000 m³ por cada m³................................... $ 185.68\nb).- Los usuarios que tengan medidor en los poblados no contemplados en el inciso a), así como los ejidos o polos de desarrollo que pertenezcan a dichos poblados en administración, operación y mantenimiento, causarán mensualmente por cada metro cúbico consumido, en forma escalonada y por cada uno de los rangos, la siguiente\nTARIFA:\n1).- De 0 hasta 5 m³, cuota mínima......... $ 760.45\n2).- Por el excedente de 5 y hasta 10 m³... $ 77.22\n3).- Por el excedente de 10 y hasta 15 m³.. $ 105.77\n4).- Por el excedente de 15 y hasta 20 m³.. $ 124.53\n5).- Por el excedente de 20 y hasta 30 m³.. $ 146.17\n6).- Por el excedente de 30 y hasta 40 m³.. $ 148.81\n7).- Por el excedente de 40 y hasta 50 m³.. $ 156.15\n8).- Por el excedente de 50 y hasta 60 m³.. $ 159.34\n9).- Por el excedente de 60 y hasta 10,000 m³.................................... $ 167.04\n10).- Por el excedente de 10,000 m³ por cada m³................................... $ 109.48\nPara desarrolladores, fraccionadores, centros comerciales u otros no domésticos en donde el organismo determina la instalación de medidor control y cuyas redes aún no se encuentran entregadas al organismo, el desarrollador estará obligado a incluir en los proyectos de cada etapa de construcción la instalación de un medidor control, el cual servirá para registrar la diferencia que existe entre el volumen total suministrado al fraccionamiento o medidores individuales (la micro medición). estar cubiertos los derechos de consumo de agua; por lo cancelación del medidor según proceda.\n3.- En aquellos usuarios que por caso fortuito o fuerza mayor siendo ésta comprobada por el Organismo, se estará en lo dispuesto por el Manual de Políticas de Bonificaciones.\n4.- El costo de agua entregada en bloque.\na) Por cada m³ para uso doméstico entregada en planta, sin exceder de 1 m³............................. $ 55.73\nb) Entregada a domicilio por cada m³ para uso doméstico................................... $ 116.47\nc) Por cada m³ para uso comercial, industrial, Gubernamental u otro no doméstico, entregado en planta...................................... $ 174.21\n5.- El costo de aguas residuales, a quienes lo soliciten.\na).- Sin tratar por cada m³ entregada en planta.... $ 4.27\nb).- Tratada por cada m³ entregada en planta..... $ 11.75\nc).- Tratada por cada m³ entregada en sitio...... $ 23.64\n6.- Derecho anual de reserva de aguas residuales, tratadas y no tratadas.\na).- Por cada m³................................. $ 0.58\n7.- Recepción y tratamiento de aguas residuales. materia ambiental y los ordenamientos técnicos.\na).- Remover la demanda bioquímica de oxígeno (DBO) por cada Kg.................................. $ 25.25\nb).- Remover los sólidos suspendidos totales (SST) por cada Kg................................. $ 24.71\nc).- Remover grasas y aceites (G y A), por cada\nKg....................................... $ 23.01\nd).- Remover la demanda química de oxígeno (DQO) por cada\nKg...................................... $ 23.84\ne).- Por cada revisión y verificación de las condiciones alcantarillado sanitario................. $ 1,318.16\nf).- Recepción y tratamiento de aguas residuales cisterna (pipa), por m³.................. $ 82.82\ng).- Análisis de laboratorio de los parámetros conforme a\nla NOM-002-SEMARNAT-1996............... $ 13,951.14\nh).- Por recepción y evaluación de la documentación relativa a la firma del contrato de tratamiento conjunto de aguas residuales............ $ 8,438.49\ni).- Reevaluación anual del contrato de pre-tratamiento de aguas residuales................... $ 5,430.61\nj).- Recepción, tratamiento y confinamiento de lodos de plantas de tratamiento de aguas residuales:\nI.- Por recepción y evaluación de la documentación relativa a la firma del contrato de confinamiento de lodos............. $ 8,438.49\nII.- Reevaluación anual del contrato de confinamiento de lodos............. $ 4,811.11\nIII.- Recepción de lodos estabilizados (biosólidos) provenientes de plantas de tratamiento de aguas residuales de fraccionamientos habitacionales, por m3............. $ 852.88\nIV.- Recepción de lodos sin estabilizar provenientes de plantas de tratamiento de aguas residuales de fraccionamientos habitacionales, por m3............ $ 1,705.83\nk).- Por los servicios de toma de muestras y análisis de laboratorio de aguas residuales:\nI.- Por el servicio de muestreo simple de aguas residuales..........................$ 1,169.90\nII.- Por el servicio de muestreo puntual de aguas residuales........................ $ 3,044.91\nIII.- Por el análisis de parámetro:\nPH............................................. $ 134.51\nCloro residual............................. $ 336.37\nDemanda Bioquímica de Oxígeno............. $1,255.86\nDemanda Química de Oxígeno................. $ 903.22\n% de Salinidad............................. $ 134.51\nColiformes Totales......................... $ 807.24\nColiformes Fecales.........................$1,064.71\nConductividad.............................. $ 134.51\nTemperatura................................ $ 179.40\nSólidos Totales............................ $ 252.22\nSólidos Totales Disueltos.................. $ 302.69\nSólidos Totales Volátiles.................. $ 302.69\nSólidos Suspendidos Totales................ $ 538.21\nSólidos Suspendidos Volátiles.............. $ 542.57\nSólidos Sedimentables...................... $ 412.64\nGrasas y Aceites.......................... $1,040.54\nl).- Por la recepción de agua residual fuera de norma, proveniente de descargas al sistema de alcantarillado, de procesos productivos de empresas con giros industriales o comerciales, así como de fraccionamientos habitacionales, de conformidad con el artículo 277-B, fracción I, y Octavo Transitorio de la Ley Federal de Derechos, por cada m3........................................... $ 1.31 de la presente Ley.\nm).- Por la recepción y evaluación de la documentación usuarios no domésticos................... $ 6,639.23\nn).- Por la recepción y evaluación de la documentación usuarios domésticos...................... $ 4,503.11 ñ).- Análisis de solicitud de prórroga para presentar potencialmente contaminantes a los sistemas de alcantarillado sanitario................. $ 1,897.47\no).- Para la entrega del registro estatal de descargas de aguas potencialmente contaminantes....... $ 7,122.66\np).- Por el análisis para reconsideración de condicionantes de permiso de descarga de agua residual................................. $ 3,091.68\nq).- Análisis de solicitud de exención al trámite de permiso de descarga de agua residual..... $ 1,848.26\n8.- Por los servicios de toma de muestras y análisis del laboratorio de agua potable:\na).- Por análisis de agua potable por toma muestra simple.................................... $1,169.90\nb).- Por el análisis del parámetro:\nPH............................................. $ 134.51\nTurbiedad................................. $ 142.30\nColor aparente............................ $ 36.75\n% Salinidad............................... $ 142.77\nDureza Total.............................. $ 142.77\nCloro Residual............................ $ 142.77\nConductividad............................. $ 142.77\nColiformes Totales........................ $ 142.77\nCloruros.................................. $ 142.77\nManganeso................................. $ 142.77\nFierro.................................... $ 134.51\nFlúor..................................... $ 134.51\nAlcalinidad total......................... $ 134.51\nAcidez total.............................. $ 134.51\nTemperatura............................... $ 71.89\nSólidos Disueltos Totales................. $ 134.51\nSulfatos.................................. $ 134.51\nc).- Por expedición de documento de calidad de agua potable.................................... $ 517.32 establezca la Comisión Estatal de Servicios Públicos de\nEnsenada.\nB).- TOMAS COMUNALES.\nA los consumos de las cuentas de este tipo de tomas se le aplicará la tarifa doméstica vigente de acuerdo con el punto número uno.\nLos consumos de las cuentas de este tipo de tomas, serán divididos entre el número de usuarios servidos del mismo medidor y a la resultante se le aplicará la tarifa doméstica vigente de acuerdo con el punto número uno.\nCuando se trate de una re-conexión derivada de una reducción, se cobrará un costo de ejecución en............ $526.66 pesos.\nCuando sea una re-conexión por falta de medidor o destrucción\nAgua Potable en el Estado de Baja California.\nServicio de Agua Potable en el Estado de Baja California. Para todos los demás, estará el Manual de políticas Internas para\nTomas Comunales del Organismo Operador.\nC).- SERVICIO SIN MEDIDOR.\nPara los usuarios domésticos sin servicio medido, los consumos promedio de la zona y para los no domésticos, el consumo será correspondiente, con base a las estadísticas de consumo para este tipo de usuarios.\nD).- DERECHOS DE CONEXIÓN AL SISTEMA DE AGUA POTABLE Y\nALCANTARILLADO SANITARIO:\n1.- Para los terrenos residenciales unifamiliares de fraccionamientos y colonias populares, definidos de conformidad con el Artículo Quinto Transitorio de esta Ley, y cuyo uso sea exclusivamente para casa habitación:\na).- A las redes del sistema de agua potable, por m² de superficie vendible, incluyendo área de donación................................. $ 20.85\nb).- A las redes del sistema de alcantarillado sanitario por m² de superficie vendible, incluyendo área de donación................................. $ 12.98\n1 bis.- Para los terrenos residenciales unifamiliares de fraccionamientos y colonias populares, definidos de conformidad con el Artículo Quinto Transitorio de esta\nLey, y cuyo uso sea exclusivamente para casa habitación ubicados en zona rural:\na).- A las redes del sistema de agua potable, por m² de superficie vendible, incluyendo área de donación................................. $ 10.19\nb).- A las redes del sistema de alcantarillado sanitario por m² de superficie vendible, incluyendo área de donación................................. $ 6.35\n2.- Para los terrenos destinados a desarrollos de vivienda de interés social, popular y de nivel medio, definidos de conformidad con el Artículo Quinto Transitorio de esta Ley, construida o por construir, será de:\na).- Tratándose de vivienda de interés social:\n1).- Por agua potable.................... $ 3,096.91\n2).- Por alcantarillado sanitario......... $ 1,524.03\nb).- Tratándose de vivienda popular y de nivel medio:\n1).- Por agua potable.................... $ 5,297.97\n2).- Por alcantarillado sanitario........ $ 3,263.87\n3.- Para terrenos residenciales unifamiliares y turísticos cuyo uso sea exclusivamente para casa habitación:\na).- A las redes del sistema de agua potable, por m² de superficie vendible, incluyendo áreas de donación.................................. $ 68.55\nb).- A las redes del sistema de alcantarillado sanitario, por m² de superficie vendible, incluyendo áreas de donación.................................. $ 43.10\n3 bis.- Para terrenos residenciales unifamiliares y turísticos cuyo uso sea exclusivamente para casa habitación ubicados en zona rural:\na).- A las redes del sistema de agua potable, por m² de superficie vendible, incluyendo áreas de donación.................................. $ 33.50\nb).- A las redes del sistema de alcantarillado sanitario, por m² de superficie vendible, incluyendo áreas de donación.................................. $ 21.07\n4.- Para los terrenos destinados a desarrollos de vivienda de interés social en condominio, acreditados como tales por la exclusivamente para casa habitación:\na).- A las redes del sistema de agua potable, por m² de terreno.................................... $ 45.77\nb).- A las redes del sistema de alcantarillado sanitario, por m² de terreno......................... $ 30.83\n5.- Para los terrenos destinados a condominios y departamentos de renta:\na).- A las redes del sistema de agua potable, por m² de terreno................................... $ 67.10\nb).- A las redes del sistema de alcantarillado sanitario, por m² de terreno......................... $ 36.15\nc).- Adicionalmente a los incisos a) y b), por m² de construcción.............................. $ 19.62\nLa superficie que servirá como base para realizar este cálculo, deberá de acreditarse mediante documentación oficial que emita la autoridad municipal competente.\n6.- Para terrenos, locales, establecimientos y desarrollos comerciales, industriales, de gobierno, turísticos y otros no domésticos, el cobro lo determinará el organismo previo análisis, en función a las necesidades de abasto de agua, infraestructura y capacidad de diseño, de acuerdo a las siguientes tarifas:\na).- A las redes del sistema de agua potable, por litro por segundo............................... $ 1,035,350.25\nb).- A las redes del sistema de alcantarillado sanitario, por litro por segundo................... $ 738,527.06\nc).- En el caso de escuelas y universidades públicas y privadas, la necesidad de abasto de agua e infraestructura, se determinará considerando 60 litros por alumno por día, de acuerdo a las tarifas de los incisos a) y b) de este numeral.\nd).- En aquellos casos en que no sea posible determinar las necesidades de abasto e infraestructura, la o haya establecido el organismo, previo análisis.\nDe conformidad con los Artículos 21 y 65 del Reglamento de\nFraccionamientos del Estado, tratándose de los apartados de este inciso, los dueños de los fraccionamientos, serán los alcantarillado sanitario, incluidas las áreas destinadas a donación al Municipio y al Estado. doméstico a no doméstico, el organismo al tener conocimiento, cobrará la diferencia que resulte del cálculo del cambio.\nPara aquellos usuarios no domésticos y que previo análisis del organismo se demuestre que sus consumos y necesidad de abasto se han incrementado, están obligados a cubrir la diferencia que resulte del cálculo de los derechos de conexión para agua potable y alcantarillado sanitario, con base a la Ley de Ingresos vigente en la fecha que se determine la diferencia.\nE).- TOMAS Y DESCARGAS NO REGISTRADAS.\n1.- En caso de que sea detectada una toma no registrada instalada en este Municipio, el cobro será de acuerdo a la siguiente manera:\na).- En la detección de tomas domésticas no registradas, se tomará como base para el cobro, lo que resulte de considerar un gasto de 250 litros por día y por habitante, considerando hasta 4 habitantes por familia, por un máximo de hasta por 5 años, a la\nEstado en la fecha en que sea detectada dicha toma. este Artículo 9, como son las personas en situación de pobreza mayores de 60 años, personas viudas en situación de pobreza mayores de 50 años, o que estando en situación de pobreza, sean el único sostén del hogar con hijos menores de edad, así como, personas con discapacidad, jubilados y pensionados que no la Unidad de Medida y Actualización, se tomará como párrafo anterior por un período máximo de 6 meses.\nb).- En la detección de tomas no registradas comerciales, industriales, de desarrollos turísticos, gubernamentales, así como otras no domésticas, se tomará como base para el cobro por consumo de agua, el base a las estadísticas de consumo para este tipo de servicio, proyectado desde la fecha de instalación de la toma, y si no fuere posible determinar fecha cierta hasta por un máximo de 10 años, a la tarifa vigente de la Ley de Ingresos del Estado, en la fecha en que sea detectada dicha toma.\nLa determinación del período para los incisos anteriores, se hará basándose en la documentación que presente el usuario con valor legal probatorio y dictamen emitido por el organismo, partiendo de la fecha de interconexión a la red que suministra el servicio de agua potable.\nAsimismo, el cobro deberá realizarse también por los derechos de conexión y obra según corresponda.\n2.- En caso de que sea detectada una descarga no registrada instalada en este Municipio, y que no cuenten con el servicio de agua potable el cobro será de acuerdo a la siguiente manera:\na).- En la detección de descargas no registradas domésticas, se tomará como base para el cobro 120 litros por día y por habitante, considerando 4 habitantes por familia, por un máximo de hasta por 5 años, a la tarifa doméstica aprobada por la Ley de dicha descarga. de este Artículo 9, como son las personas en situación de pobreza mayores de 60 años, personas viudas en situación de pobreza mayores de 50 años, o que estando en situación de pobreza, sean el único sostén del hogar con hijos menores de edad, así como, personas con discapacidad, jubilados y pensionados que no la Unidad de Medida y Actualización, se tomará como párrafo anterior por un período máximo de 6 meses.\nb).- En la detección de descargas no registradas comerciales, industriales, de desarrollos turísticos, gubernamentales y otras no domésticas, los cobros serán estimados por el organismo de acuerdo al consumo medido promedio del giro correspondiente en base a las estadísticas de consumo para este tipo de servicio, hasta por un período de 10 años, al 40% de la tarifa vigente en la Ley de Ingresos del Estado en la fecha en que sea detectada dicha descarga.\nLa determinación del período de cobro para los incisos anteriores, se hará basándose en la documentación que presente el usuario con valor legal probatorio y dictamen emitido por el organismo, partiendo de la fecha de interconexión a la red que suministra el servicio de descarga de agua.\nAsimismo, el cobro deberá realizarse también por los derechos de conexión y obra según corresponda.\nF).- OTROS SERVICIOS:\n1.- Por la expedición de opiniones técnicas para los servicios de agua potable, alcantarillado sanitario, por cada cuenta asignada por el organismo con vigencia de seis meses:\na).- Para terrenos de uso residencial.......... $ 329.30\nb).- Para terrenos de uso Comercial, Industrial y otros no residenciales............................. $ 670.49\n2.- Por la expedición de constancias de factibilidad de servicios de agua potable y alcantarillado sanitario, con vigencia de seis meses, por servicio y por clave catastral:\na).- Para terrenos de uso doméstico............ $ 396.45\nb).- Para terrenos de uso no doméstico.......... $ 1,161.34 servicios de agua potable y/o alcantarillado sanitario, deberá estar vigente la opinión técnica (inciso anterior) y correspondientes.\n3.- Por la expedición de dictamen de factibilidad de servicios de agua potable, alcantarillado sanitario, con vigencia de seis meses, por servicio y por clave catastral:\na).- Para terrenos de uso residencial.......... $ 396.45\nb).- Para terrenos de uso comercial, industrial, gubernamental y otros no domésticos....... $ 1,161.34\n4.- Por localización de toma o descarga por hora... $ 735.19\n5.- Por revisión de proyecto para la construcción de redes de agua potable y alcantarillado, en predios hasta de 5,000 m² de superficie, por plano....................... $ 4,097.10\nPor cada m² de superficie adicional, por plano.... $ 0.06\n6.- Por hidrante contra incendios instalado del sistema de agua potable, el equivalente a 5 m³ mensuales de la tarifa para uso comercial, industrial, gubernamental y otros no domésticos.\n7.- Por expedición y certificación de documentos, con vigencia de seis meses.................................. $ 203.38\n8.- Por expedición de certificados de libertad de Gravamen para:\na).- Cuentas domésticas........................ $ 205.29\nb).- Cuentas comercial, industrial, gubernamental y otros no domésticos............................. $ 688.22\n9.- Cambios de medidor, reposición de medidor, reparación en marco medidor, costo del aparato y protección de los mismos, instalación de toma de agua domiciliaria y descarga de drenaje de aguas negras, reposición de toma de agua o drenaje, así como el costo de la introducción de las redes de agua potable y alcantarillado, y otros servicios no contemplados en este capítulo, se pagará el importe de organismo que preste el servicio. afecten el funcionamiento del drenaje sanitario del usuario o la red en general, por cumplimiento de la vida útil del material con que fue construida, se determinará por la dependencia el presupuesto según las necesidades del predio.\nPara aquellos usuarios que después de 12 meses de haber sido ejecutada y notificada la obra y el presupuesto, no hayan contratado, el costo que deberá cubrir será aquel que resulte de haber aplicado el porcentaje de incremento que haya tenido la Unidad de Medida y Actualización, desde la fecha de notificación del presupuesto a los beneficiarios de dicha obra hasta la fecha de contratación.\n10.- Los propietarios o poseedores de predios que tengan una o varias fuentes de abastecimiento de agua y que utilicen el sistema de alcantarillado de aguas negras, se les aplicará el 40% de la tarifa de agua potable aplicable, sobre el volumen vertido a las descargas de aguas negras, operador. En los casos en donde no sea posible determinar el volumen vertido a las descargas de aguas negras, el facturado.\n11.- Por la remoción de reductor en servicio a cuentas domésticas................................... $ 158.74\n12.- Por tipos de reconexión de servicio de uso comercial, industrial, gubernamental y otros no domésticos:\na).- Reconexión para medidor de 12.6 mm (1/2”) hasta 19 mm\n(3/4”) de diámetro..............................$ 157.08\nb).- Reconexión para medidor desde 25.4 mm(1”)hasta 50.8 mm\n(2”)de diámetro..................................$ 542.86\nc).- Reconexión para medidor mayor de 50.8 mm (2”) de diámetro.........................................$ 656.57\n13.- Por el sondeo de descarga:\na).- En domicilio.............................. $ 475.33\nb).- En comercio o no domicilio................ $ 963.13\n14.- Por la supresión o baja temporal de la toma de agua que resulte de una solicitud de baja por parte del propietario, por desocupación del inmueble, como resultado de un análisis interno de la cuenta o una inspección................................... $ 19.92\n15.- Por la reactivación del servicio de agua para un domicilio no doméstico (comercio, industria, gobierno) en el cual se haya suprimido o dado de baja temporal por desocupación del inmueble, como resultado de una inspección, análisis o por convenir así a su propietario.................................. $ 360.26\n16.- Por revisión de agua potable, alcantarillado sanitario y pozos de visita conforme a proyecto autorizado:\nCosto unitario por visita...................... $ 739.53\nPor hora adicional............................. $ 246.52\n17.- Por la segunda visita de inspección para verificación de la preparación de instalación de medidor, factibilidad, propietario o poseedor........................ $ 368.11\n18.- Por el trámite de cambio de propietario o poseedor del predio y/o razón social....................... $ 211.15\n19.- Inspección y evaluación para la expedición de la y sólidos..................................... $ 1,947.18\nSECCIÓN IV\nMUNICIPIO DE SAN QUINTÍN.\nA).- SERVICIO MEDIDO.\nPrecios al Consumidor (INPC) que corresponda al mes de facturación más un 1% acumulable cada mes. Este último porcentaje, no será aplicable a las tarifas establecidas en los tres primeros rangos de consumo que van desde 0 m³ hasta\n15 m³ para Uso Doméstico.\n1.- Uso doméstico.\na).- Los usuarios que tengan medidor en el municipio de San\nQuintín y áreas conurbadas, así como otros que se desarrollen o incorporen al sistema, causarán mensualmente por cada metro cúbico consumido, en forma escalonada y por cada uno de los rangos, la siguiente\n1).- De 0 hasta 5 m³, cuota mínima........ $ 74.16\n2).- Por el excedente de 5 y hasta 10 m³.. $ 17.11\n3).- Por el excedente de 10 y hasta 15 m³.. $ 19.40\n4).- Por el excedente de 15 y hasta 20 m³.. $ 34.75\n5).- Por el excedente de 20 y hasta 25 m³.. $ 52.77\n6).- Por el excedente de 25 y hasta 30 m³.. $ 64.05\n7).- Por el excedente de 30 y hasta 40 m³.. $ 81.23\n8).- Por el excedente de 40 y hasta 50 m³.. $ 87.74\n9).- Por el excedente de 50 y hasta 60 m³.. $ 91.62\n10).- Por el excedente de 60 m³............. $ 92.80 consecutivos, en el cuarto pago oportuno gozarán de un descuento del 15% sobre el importe de este último; sin que cuando éstos comprendan dos ejercicios fiscales.\nEste descuento será aplicable siempre y cuando no se tenga el beneficio de otro estímulo fiscal para este servicio.\nPara continuar gozando de este descuento, además de seguir cumpliendo con lo dispuesto en el párrafo anterior, deberán transcurrir por lo menos tres meses entre la obtención de cada beneficio.\n2.- Uso comercial, industrial, gubernamental y otros no domésticos.\na).- Los usuarios que tengan medidor en el municipio de San\nQuintín y áreas conurbadas, así como otros que se desarrollen o incorporen al sistema, causarán mensualmente por cada metro cúbico consumido, en forma escalonada y por cada uno de los rangos, la siguiente\nTARIFA:\n1).- De 0 hasta 5 m³, cuota mínima......... $ 717.41\n2).- Por el excedente de 5 y hasta 10 m³... $ 72.83\n3).- Por el excedente de 10 y hasta 15 m³.. $ 99.76\n4).- Por el excedente de 15 y hasta 20 m³.. $ 117.45\n5).- Por el excedente de 20 y hasta 30 m³.. $ 137.88\n6).- Por el excedente de 30 y hasta 40 m³.. $ 140.40\n7).- Por el excedente de 40 y hasta 50 m³.. $ 147.33\n8).- Por el excedente de 50 y hasta 60 m³.. $ 150.31\n9).- Por el excedente de 60 y hasta 10,000 m³.................................... $ 157.62\n10).- Por el excedente de 10,000 m³ por cada m³................................... $ 102.41\nPara desarrolladores, fraccionadores, centros redes aún no se encuentran entregadas al organismo, el desarrollador estará obligado a incluir en los proyectos de cada etapa de construcción la instalación de un medidor control, el cual servirá para registrar la diferencia que existe entre el volumen total suministrado al fraccionamiento o desarrollo y el consumo total registrado por los medidores individuales\n(la micro medición).\nConcluida o entregada la etapa de edificación deberán estar cubiertos los derechos de consumo de agua; por lo que el desarrollador deberá solicitar la reubicación o cancelación del medidor según proceda.\n3.- En aquellos usuarios que por caso fortuito o fuerza mayor exista un consumo de agua involuntario en las instalaciones por el Organismo, se estará en lo dispuesto por el Manual de Políticas de Bonificaciones.\n4.- El costo de agua entregada en bloque.\na) Por cada m³ para uso doméstico entregada en planta, sin exceder de 1 m³............................. $ 55.73\nb) Entregada a domicilio por cada m³ para uso doméstico................................... $ 116.47\nc) Por cada m³ para uso comercial, industrial, Gubernamental u otro no doméstico, entregado en planta\n............................................ $ 174.21\nB).- TOMAS COMUNALES. número uno.\nLos consumos de las cuentas de este tipo de tomas, serán vigente de acuerdo con el punto número uno.\nCuando se trate de una re-conexión derivada de una reducción, se cobrará un costo de ejecución en............ $526.66 pesos.\nCuando sea una re-conexión por falta de medidor o destrucción se cobrará la reposición del medidor y las sanciones que se apliquen de acuerdo a la Ley que Reglamenta el Servicio de\nAgua Potable en el Estado de Baja California.\nEn el caso de detectar toma clandestina derivada de la toma comunal se sancionará de acuerdo a la Ley que Reglamenta el\nServicio de Agua Potable en el Estado de Baja California. Para todos los demás, estará el Manual de políticas Internas para\nTomas Comunales del Organismo Operador.\nC).- SERVICIO SIN MEDIDOR.\nPara los usuarios domésticos sin servicio medido, los consumos serán estimados por el organismo de acuerdo al consumo medido promedio de la zona y para los no domésticos, el consumo será correspondiente, con base a las estadísticas de consumo para este tipo de usuarios.\nD).- DERECHOS DE CONEXIÓN AL SISTEMA DE AGUA POTABLE Y\nALCANTARILLADO SANITARIO:\n1.- Para los terrenos residenciales unifamiliares de fraccionamientos y colonias populares, definidos de conformidad con el Artículo Quinto Transitorio de esta Ley, y cuyo uso sea exclusivamente para casa habitación:\na).- A las redes del sistema de agua potable, por m² de superficie vendible, incluyendo área de donación................................. $ 10.19\nb).- A las redes del sistema de alcantarillado sanitario por m² de superficie vendible, incluyendo área de donación................................. $ 6.35\n2.- Para los terrenos destinados a desarrollos de vivienda de interés social, popular y de nivel medio, definidos de conformidad con el Artículo Quinto Transitorio de esta Ley, agua potable y alcantarillado por cada casa habitación construida o por construir, será de:\na).- Tratándose de vivienda de interés social:\n1).- Por agua potable.................... $ 3,096.91\n2).- Por alcantarillado sanitario......... $ 1,524.03\nb).- Tratándose de vivienda popular y de nivel medio:\n1).- Por agua potable.................... $ 5,297.97\n2).- Por alcantarillado sanitario........ $ 3,263.87\n3.- Para terrenos residenciales unifamiliares y turísticos cuyo uso sea exclusivamente para casa habitación:\na).- A las redes del sistema de agua potable, por m² de superficie vendible, incluyendo áreas de donación................................... $ 33.50\nb).- A las redes del sistema de alcantarillado sanitario, por m² de superficie vendible, incluyendo áreas de donación.................................. $ 21.07\n4.- Para los terrenos destinados a desarrollos de vivienda de interés social en condominio, acreditados como tales por la casa habitación:\na).- A las redes del sistema de agua potable, por m² de terreno.................................... $ 45.77\nb).- A las redes del sistema de alcantarillado sanitario, por m² de terreno.......................... $ 30.83\n5.- Para los terrenos destinados a condominios y departamentos de renta:\na).- A las redes del sistema de agua potable, por m² de terreno................................... $ 67.10\nb).- A las redes del sistema de alcantarillado sanitario, por m² de terreno......................... $ 36.15\nc).- Adicionalmente a los incisos a) y b), por m² de construcción.............................. $ 19.62\nLa superficie que servirá como base para realizar este cálculo, deberá de acreditarse mediante documentación oficial que emita la autoridad municipal competente.\n6.- Para terrenos, locales, establecimientos y desarrollos comerciales, industriales, de gobierno, turísticos y otros no domésticos, el cobro lo determinará el organismo previo análisis, en función a las necesidades de abasto de agua, infraestructura y capacidad de diseño, de acuerdo a las siguientes tarifas:\na).- A las redes del sistema de agua potable, por litro por segundo................................ $1,035,350.25\nb).- A las redes del sistema de alcantarillado sanitario, por litro por segundo................... $ 738,527.06\nc).- En el caso de escuelas y universidades públicas y privadas, la necesidad de abasto de agua e infraestructura, se determinará considerando 60 litros por alumno por día, de acuerdo a las tarifas de los incisos a) y b) de este numeral.\nd).- En aquellos casos en que no sea posible determinar las necesidades de abasto e infraestructura, la o haya establecido el organismo, previo análisis.\nDe conformidad con los Artículos 21 y 65 del Reglamento de\nFraccionamientos del Estado, tratándose de los apartados de este inciso, los dueños de los fraccionamientos, serán los alcantarillado sanitario, incluidas las áreas destinadas a donación al Municipio y al Estado. doméstico a no doméstico, el organismo al tener conocimiento, cobrará la diferencia que resulte del cálculo del cambio.\nPara aquellos usuarios no domésticos y que previo análisis del organismo se demuestre que sus consumos y necesidad de abasto se han incrementado, están obligados a cubrir la diferencia que resulte del cálculo de los derechos de conexión para agua potable y alcantarillado sanitario, con base a la Ley de Ingresos vigente en la fecha que se determine la diferencia.\nE).- TOMAS Y DESCARGAS NO REGISTRADAS.\n1.- En caso de que sea detectada una toma no registrada instalada en este Municipio, el cobro será de acuerdo a la siguiente manera:\na).- En la detección de tomas domésticas no registradas, se tomará como base para el cobro, lo que resulte de considerar un gasto de 250 litros por día y por habitante, considerando hasta 4 habitantes por familia, por un máximo de hasta por 5 años, a la\nEstado en la fecha en que sea detectada dicha toma. este Artículo 9, como son las personas en situación de pobreza mayores de 60 años, personas viudas en situación de pobreza mayores de 50 años, o que estando en situación de pobreza, sean el único sostén del hogar con hijos menores de edad, así como, personas con discapacidad, jubilados y pensionados que no la Unidad de Medida y Actualización, se tomará como párrafo anterior por un período máximo de 6 meses.\nb).- En la detección de tomas no registradas comerciales, industriales, de desarrollos turísticos, gubernamentales, así como otras no domésticas, se tomará como base para el cobro por consumo de agua, el base a las estadísticas de consumo para este tipo de servicio, proyectado desde la fecha de instalación de la toma, y si no fuere posible determinar fecha cierta hasta por un máximo de 10 años, a la tarifa vigente de la Ley de Ingresos del Estado, en la fecha en que sea detectada dicha toma.\nLa determinación del período para los incisos anteriores, se hará basándose en la documentación que presente el usuario con valor legal probatorio y dictamen emitido por el organismo, partiendo de la fecha de interconexión a la red que suministra el servicio de agua potable.\nAsimismo, el cobro deberá realizarse también por los derechos de conexión y obra según corresponda.\n2.- En caso de que sea detectada una descarga no registrada instalada en este Municipio, y que no cuenten con el servicio de agua potable el cobro será de acuerdo a la siguiente manera:\na).- En la detección de descargas no registradas domésticas, se tomará como base para el cobro 120 litros por día y por habitante, considerando 4 habitantes por familia, por un máximo de hasta por 5 años, a la tarifa doméstica aprobada por la Ley de dicha descarga. de este Artículo 9, como son las personas en situación de pobreza mayores de 60 años, personas viudas en situación de pobreza mayores de 50 años, o que estando en situación de pobreza, sean el único sostén del hogar con hijos menores de edad, así como, personas con discapacidad, jubilados y pensionados que no la Unidad de Medida y Actualización, se tomará como párrafo anterior por un período máximo de 6 meses.\nb).- En la detección de descargas no registradas comerciales, industriales, de desarrollos turísticos, gubernamentales y otras no domésticas, los cobros serán estimados por el organismo de acuerdo al consumo medido promedio del giro correspondiente en base a las estadísticas de consumo para este tipo de servicio, hasta por un período de 10 años, al 40% de la tarifa vigente en la Ley de Ingresos del Estado en la fecha en que sea detectada dicha descarga.\nLa determinación del período de cobro para los incisos anteriores, se hará basándose en la documentación que presente el usuario con valor legal probatorio y dictamen emitido por el organismo, partiendo de la fecha de interconexión a la red que suministra el servicio de descarga de agua.\nAsimismo, el cobro deberá realizarse también por los derechos de conexión y obra según corresponda.\nF).- OTROS SERVICIOS:\n1.- Por la expedición de opiniones técnicas para los servicios de agua potable, alcantarillado sanitario, por cada cuenta asignada por el organismo con vigencia de seis meses:\na).- Para terrenos de uso residencial.......... $ 329.30\nb).- Para terrenos de uso Comercial, Industrial y otros no residenciales............................. $ 670.49\n2.- Por la expedición de constancias de factibilidad de servicios de agua potable y alcantarillado sanitario, con vigencia de seis meses, por servicio y por clave catastral:\na).- Para terrenos de uso doméstico............ $ 396.45\nb).- Para terrenos de uso no doméstico........ $ 1,161.34 servicios de agua potable y/o alcantarillado sanitario, deberá estar vigente la opinión técnica (inciso anterior) y correspondientes.\n3.- Por la expedición de dictamen de factibilidad de servicios de agua potable, alcantarillado sanitario, con vigencia de seis meses, por servicio y por clave catastral:\na).- Para terrenos de uso residencial.......... $ 396.45\nb).- Para terrenos de uso comercial, industrial, gubernamental y otros no domésticos...... $ 1,161.34\n4.- Por localización de toma o descarga por hora... $ 735.19\n5.- Por revisión de proyecto para la construcción de redes de agua potable y alcantarillado, en predios hasta de 5,000 m² de superficie, por plano....................... $ 4,097.10\nPor cada m² de superficie adicional, por plano... $ 0.06\n6.- Por hidrante contra incendios instalado del sistema de agua potable, el equivalente a 5 m³ mensuales de la tarifa para uso comercial, industrial, gubernamental y otros no domésticos.\n7.- Por expedición y certificación de documentos, con vigencia de seis meses.................................. $ 203.38\n8.- Por expedición de certificados de libertad de Gravamen para:\na).- Cuentas domésticas........................ $ 205.29\nb).- Cuentas comercial, industrial, gubernamental y otros no domésticos............................. $ 688.22\n9.- Cambios de medidor, reposición de medidor, reparación en marco medidor, costo del aparato y protección de los mismos, instalación de toma de agua domiciliaria y descarga de drenaje de aguas negras, reposición de toma de agua o drenaje, así como el costo de la introducción de las redes de agua potable y alcantarillado, y otros servicios no contemplados en este capítulo, se pagará el importe de organismo que preste el servicio. afecten el funcionamiento del drenaje sanitario del usuario o la red en general, por cumplimiento de la vida útil del material con que fue construida, se determinará por la dependencia el presupuesto según las necesidades del predio.\nPara aquellos usuarios que después de 12 meses de haber sido ejecutada y notificada la obra y el presupuesto, no hayan contratado, el costo que deberá cubrir será aquel que resulte de haber aplicado el porcentaje de incremento que haya tenido la Unidad de Medida y Actualización, desde la fecha de notificación del presupuesto a los beneficiarios de dicha obra hasta la fecha de contratación.\n10.- Los propietarios o poseedores de predios que tengan una o varias fuentes de abastecimiento de agua y que utilicen el sistema de alcantarillado de aguas negras, se les aplicará el 40% de la tarifa de agua potable aplicable, sobre el volumen vertido a las descargas de aguas negras, restando en su caso el volumen facturado por el organismo operador. En los casos en donde no sea posible determinar el volumen vertido a las descargas de aguas negras, el facturado.\n11.- Por la remoción de reductor en servicio a cuentas domésticas.................................. $ 158.74\n12.- Por tipos de reconexión de servicio de uso comercial, industrial, gubernamental y otros no domésticos:\na).- Reconexión para medidor de 12.6 mm (1/2”) hasta 19 mm\n(3/4”) de diámetro..............................$ 157.08\nb).- Reconexión para medidor desde 25.4 mm(1”)hasta 50.8 mm\n(2”)de diámetro..................................$ 542.86\nc).- Reconexión para medidor mayor de 50.8 mm (2”) de diámetro.........................................$ 656.57\n13.- Por el sondeo de descarga:\na).- En domicilio.............................. $ 475.33\nb).- En comercio o no domicilio................ $ 963.10\n14.- Por la supresión o baja temporal de la toma de agua que resulte de una solicitud de baja por parte del propietario, por desocupación del inmueble, como resultado de un análisis interno de la cuenta o una inspección................................... $ 19.92\n15.- Por la reactivación del servicio de agua para un domicilio no doméstico (comercio, industria, gobierno) en el cual se haya suprimido o dado de baja temporal por desocupación del inmueble, como resultado de una inspección, análisis o por convenir así a su propietario................................. $ 360.26\n16.- Por revisión de agua potable, alcantarillado sanitario y pozos de visita conforme a proyecto autorizado:\nCosto unitario por visita...................... $ 739.52\nPor hora adicional............................. $ 246.52\n17.- Por la segunda visita de inspección para verificación de la preparación de instalación de medidor, factibilidad, propietario o poseedor........................ $ 368.11\n18.- Por el trámite de cambio de propietario o poseedor del predio y/o razón social....................... $ 211.15\n19.- Inspección y evaluación para la expedición de la y sólidos..................................... $ 1,947.18\nSECCIÓN V\nMUNICIPIO DE TIJUANA.\nA).- SERVICIO MEDIDO.\nPrecios al Consumidor (INPC) que corresponda al mes de facturación más un 1% acumulable cada mes. Este último porcentaje, no será aplicable a las tarifas establecidas en los tres primeros rangos de consumo que van desde 0 m³ hasta\n15 m³ para Uso Doméstico.\n1.- Uso doméstico.\nLos usuarios que tengan medidor en el Municipio de Tijuana, causarán mensualmente por cada metro cúbico consumido, en forma escalonada y por cada uno de los rangos, la siguiente\na).- De 0 hasta 5 m³, cuota mínima............ $ 149.30\nb).- Por el excedente de 5 y hasta 10 m³,por cada m³ consumido................................ $ 30.23\nc).- Por el excedente de 10 y hasta 15 m³, por cada m³ consumido................................ $ 30.88\nd).- Por el excedente de 15 y hasta 20 m³, por cada m³ consumido................................ $ 48.65\ne).- Por el excedente de 20 y hasta 25 m³, por cada m³ consumido................................ $ 81.58\nf).- Por el excedente de 25 y hasta 30 m³, por cada m³ consumido................................ $ 84.35\ng).- Por el excedente de 30 y hasta 35 m³, por cada m³ consumido................................ $ 106.60\nh).- Por el excedente de 35 y hasta 40 m³, por cada m³ consumido................................ $ 107.51\ni).- Por el excedente de 40 y hasta 45 m³, por cada m³ consumido................................ $ 121.54\nj).- Por el excedente de 45 y hasta 50 m³, por cada m³ consumido................................ $ 121.97\nk).- Por el excedente de 50 y hasta 60 m³, por cada m³ consumido................................ $ 142.03\nl).- Por el excedente de 60 m³ en adelante, por cada m³ consumido................................ $ 143.05\nA los usuarios domésticos que efectúen su pago mensual y lo hagan antes de la fecha de vencimiento durante tres meses consecutivos, en el cuarto pago oportuno gozarán de un descuento del 15% sobre el importe de este último; sin que se interrumpa la consecutividad de los pagos mensuales cuando éstos comprendan dos ejercicios fiscales.\nEste descuento será aplicable siempre y cuando no se tenga el beneficio de otro estímulo fiscal para este servicio.\nPara continuar gozando de este descuento, además de seguir cumpliendo con lo dispuesto en el párrafo anterior, deberán cada beneficio.\n2.- Uso comercial, industrial, gubernamental y otros no domésticos.\nLos usuarios que tengan medidor en el Municipio de Tijuana, causarán mensualmente por cada metro cúbico consumido, en forma escalonada y por cada uno de los rangos, la siguiente\nTARIFA:\na).- De 0 hasta 5 m³, cuota mínima............ $ 737.82\nb).- Por el excedente de 5 y hasta 15 m³, por cada m³ consumido................................ $ 173.82\nc).- Por el excedente de 15 y hasta 20 m³, por cada m³ consumido................................ $ 183.82\nd).- Por el excedente de 20 y hasta 30 m³, por cada m³ consumido................................ $ 187.15\ne).- Por el excedente de 30 y hasta 40 m³, por cada m³ consumido................................ $ 193.61\nf).- Por el excedente de 40 y hasta 100 m³, por cada m³ consumido................................ $ 201.85\ng).- Por el excedente de 100 y hasta 1,000 m³, por cada m³ consumido................................ $ 205.97\nh).- Por el excedente de 1,000 m³ en adelante, por cada m³ consumido................................ $ 210.00\nPara desarrolladores, fraccionadores, centros comerciales u otros no domésticos en donde el organismo determina la instalación de medidor control y cuyas redes aún no se encuentran entregadas al organismo, el desarrollador estará obligado a incluir en los proyectos de cada etapa de construcción la instalación de un medidor control, el medidores individuales (la micro medición). estar cubiertos los derechos de consumo de agua; así como contratados los servicios al 100% de la micro medición; reubicación o cancelación del medidor según proceda.\n3.- En aquellos usuarios que por caso fortuito o fuerza mayor por el Organismo, se estará en lo dispuesto por el Manual de Políticas de Bonificaciones.\n4.- Aguas residuales en planta o fuera de planta a quienes lo soliciten.\na).- Tratada, por cada m³ entregada en planta..... $ 7.60\nb).- Tratada, por cada m³ entregada en el domicilio del usuario..................................... $ 21.60\nc).- Sin tratar, por cada m³ entregada en planta.. $ 1.34\nd).- Sin tratar, por cada m³ entregada en planta para uso agrícola..................................... $ 1.34\n5.- El costo de agua por servicio y suministro en tomas fijas para ser distribuidas en camiones cisterna, exclusivamente a usuarios que no cuenten con sistemas de redes de agua potable en sus predios, por cada m³............ $ 41.96\n6.- Derecho anual de reserva de aguas residuales, tratadas y no tratadas.\na).- Por cada m³................................. $ 0.48\n7.- Servicios de registro de transporte de agua residual tratada y/o transporte de camión cisterna de fosa séptica.\na).- Establecimiento de recepción de aguas residuales sanitarias domésticas y no domésticas.......$ 3,146.37\nb).- Registro de dotación de agua residual tratada en camión cisterna............................$ 7,217.26\nc).- Revalidación anual de registro dotación de agua residual tratada..........................$ 4,114.83\nd).- Registro de transporte de agua residual tratada.\nIncluye: cubicación de unidad y recepción, análisis de documentos.............................$ 2,202.09\ne).- Revalidación anual del registro de transporte de agua residual tratada. Incluye recepción de documentos y análisis de los mismos, verificación de cubicación de unidades...................................$ 2,256.05\nf).- Por el registro de transporte camión cisterna adicional para recepción de agua residual tratada......................................$ 835.02\ng).- Registro de transporte de camión cisterna para fosa séptica......................................$2,202.09\nh).- Revalidación anual de transporte de camión cisterna para fosa séptica........................$ 2,067.95\ni).- Permiso para descargar domingos del mes......$1,112.87\n8.- Derechos en materia de servicios de saneamiento.\nPor el servicio de tratamiento de aguas residuales para los parámetros que se descarguen en forma excedida de los límites establecidos por la normatividad vigente en materia ambiental y los ordenamientos técnicos.\na).- Remover la demanda química de oxígeno (DQO) por cada Kg.................................. $ 17.11\nb).- Remover la demanda bioquímica de oxígeno (DBO) por cada Kg.................................. $ 17.36\nc).- Remover los sólidos suspendidos totales (SST) por cada Kg.................................. $ 17.78\nd).- Por cada revisión y verificación de las condiciones alcantarillado sanitario................. $ 1,240.19\ne).- Recepción de aguas residuales sanitarias vertida por camiones cisterna (pipa), por m³.......... $ 14.04\nf).- Análisis de laboratorio de los parámetros conforme a\nla NOM-002-SEMARNAT-1996.\nI.- De 6 muestras simples en el mismo día.. $17,982.61\nII.- De 4 muestras simples en el mismo día..$16,214.08\nIII.- De 2 muestras simples en el mismo día.$11,611.76\nIV.- De 1 muestra simple en el mismo día....$ 9,969.81\nV.- Cuando el usuario es responsable del muestreo............................... 16,214.02\ng).- Por recepción y evaluación de la documentación conjunto de aguas residuales.............. $ 7,710.24\nh).- Revaluación anual del contrato de tratamiento conjunto de aguas residuales........................ $ 4,395.90\ni).- Recepción, tratamiento y confinamiento de lodos de plantas de tratamiento de aguas residuales de fraccionamientos habitacionales:\nI.- Por recepción y evaluación de la documentación relativa a la firma del contrato de confinamiento de lodos............................. $ 7,710.24\nII.- Revaluación anual del contrato de confinamiento de lodos............................. $ 4,395.90\nIII.- Recepción de lodos estabilizados (biosólidos) residuales de fraccionamientos habitacionales, por m3................................ $ 740.50\nIV.- Recepción de lodos sin estabilizar provenientes fraccionamientos habitacionales, por m3.$1,481.01\nj).- Por los servicios de toma de muestras y análisis de laboratorio de aguas residuales:\nI.- Por el servicio de muestreo simple de aguas residuales............................. $ 1,068.95\nII.- Por el muestreo simple de parámetros de la NOM001-SEMARNAT-1996.................... $12,485.82\nIII.- Por el análisis del parámetro:\nPH.................................. $ 126.71\nDemanda Bioquímica de Oxígeno....... $ 691.41\nDemanda Química de Oxígeno.......... $ 399.48\nGrasas y aceites.................... $ 583.87\nFósforo Total....................... $ 414.88\nDetergentes......................... $ 583.87\nNitrógeno Total..................... $ 583.87\nNitrógeno Amoniacal................. $ 583.87\nCloro Residual...................... $ 307.35\nColiformes Totales.................. $ 737.58\nColiformes Fecales.................. $ 737.58\nConductividad....................... $ 122.91\nTemperatura......................... $ 61.47\n% Salinidad......................... $ 122.91\nSólidos Totales..................... $ 230.45\nSólidos Totales Disueltos........... $ 276.57\nSólidos Totales Volátiles........... $ 276.57\nSólidos Suspendidos Totales......... $ 276.57\nSólidos Suspendidos Volátiles....... $ 322.58\nSólidos Sedimentables............... $ 184.39\nAluminio............................ $ 599.25\nArsénico............................ $ 599.25\nBario............................... $ 599.25\nBoro................................ $ 599.25\nCadmio.............................. $ 599.25\nCalcio.............................. $ 599.25\nCobre............................... $ 599.25\nCianuro Total....................... $ 149.00\nCromo Hexavalente................... $ 599.25\nCromo Total......................... $ 599.25\nEstaño.............................. $ 599.25\nFierro.............................. $ 599.25\nMagnesio............................ $ 599.25\nMercurio............................ $ 599.25\nNíquel.............................. $ 599.25\nPlata............................... $ 599.25\nPlomo............................... $ 599.25\nPotasio............................. $ 599.25\nSodio............................... $ 599.25\nZinc................................ $ 599.25\nOtros............................... $ 599.25\nk).- Por la recepción de agua residual fuera de norma, proveniente de descargas al sistema de alcantarillado, de procesos productivos de empresas con giros industriales o comerciales, así como de\nPlantas de Tratamiento de Aguas Residuales de fraccionamientos habitacionales, de conformidad con el artículo 277-B, fracción I, y Octavo Transitorio de la Ley Federal de Derechos, por cada m3.. $ 1.19\nl).- Por la recepción y evaluación de la documentación relativa a la solicitud de permiso de descargas de aguas residuales al sistema de alcantarillado a usuarios no domésticos.................... $ 6,066.26\nm).- Por la recepción y evaluación de la documentación relativa a la revaluación del permiso de descargas de aguas residuales al sistema de alcantarillado a usuarios no domésticos.................... $ 3,458.56\nn).- Análisis de solicitud de prórroga para presentar revaluación de los registros de descarga de aguas potencialmente contaminantes a los sistemas de alcantarillado sanitario.................. $ 1,616.06 ñ).- Cambios de razón social, fusiones, transferencias de trámites en general....................... $ 4,852.92\no).- Por el análisis para reconsideración de residual.................................. $ 2,824.86\np).- Por el trámite inicial o revalidación de permiso de servicios:\n1.- Por expedición........................ $ 1,688.77\n2.- Por la revalidación anual............. $ 916.62\nq).- Inspección y evaluación para la expedición de la grasa y sólidos............................$ 2,258.73\nr).- Visita adicional de verificación, para la expedición de constancia atrapa la grasa..............$1,104.37\ns).- Inspección y evaluación para la expedición de la grasa y sólidos, de redimensionamiento y verificación............................... $ 1,276.80\nt).- Evaluación de prórroga para el programa atrapa la grasa........................................$ 309.54\nu).- Inspección y evaluación para la expedición de la revalidación de constancia de cumplimiento de atrapa la grasa.....................................$1,202.03\nv).- Inspección y evaluación para la expedición de exención de constancia programa atrapa la grasa y solidos.....................................$ 1,264.86\nw).- Por emisión de proyecto ejecutivo de interceptor de grasas y aceites, programa atrapa la grasa.......................................$ 326.08\nx).- Por emisión de proyecto ejecutivo de sistemas de retención de sólidos de tortillerías, lavanderías entre otros comercios y servicios...................................$ 276.64\nTijuana.\n9.- Los usuarios que tengan medidor en el Municipio de Tijuana, determine el organismo.......................... $ 59.40\n10.-Por el análisis de muestras de agua potable en laboratorio certificado del organismo, según los parámetros preestablecidos a solicitud del usuario........ $ 1,441.81\nB).- TOMAS COMUNALES.\nLos consumos de las cuentas de este tipo de tomas, serán medidor y a la resultante se le aplicará la tarifa doméstica vigente de acuerdo con el punto número uno.\nC).- SERVICIO SIN MEDIDOR.\nPara los usuarios domésticos sin servicio medido los consumos serán estimados por el organismo de acuerdo al consumo medido promedio de la zona y para los no domésticos, el consumo será determinado de acuerdo al consumo medido promedio del giro correspondiente, con base a las estadísticas de consumo para este tipo de usuarios.\nD).- DERECHOS DE CONEXIÓN AL SISTEMA DE AGUA POTABLE Y\nALCANTARILLADO:\n1.- Para los terrenos residenciales unifamiliares de fraccionamientos y colonias populares, definidos de conformidad con el Artículo Quinto Transitorio de esta Ley, y cuyo uso sea exclusivamente para casa habitación:\na).- A las redes del sistema de agua potable, por m² de superficie vendible incluyendo áreas de donación................................. $ 19.85\nb).- A las redes del sistema de alcantarillado, por m² de superficie vendible incluyendo áreas de donación................................. $ 12.38\n2.- Para los terrenos destinados a desarrollos de vivienda de interés social y popular, definidos de conformidad con el\nArtículo Quinto Transitorio de esta Ley, el derecho a pagar construir, será de:\na).- Tratándose de vivienda de interés social:\n1).- Por agua potable.................... $ 3,972.44\n2).- Por alcantarillado sanitario........ $ 2,750.06\nb).- Tratándose de vivienda popular:\n1).- Por agua potable.................... $ 7,150.39\n2).- Por alcantarillado sanitario........ $ 4,950.11\n3.- Para los terrenos destinados a desarrollos de vivienda de interés social en condominio, acreditados como tales por la\nSecretaría de Infraestructura, Desarrollo Urbano y\nReordenación Territorial y Dirección de Administración\nUrbana del Municipio de Tijuana y cuyo uso sea exclusivamente para casa habitación:\na).- A las redes del sistema de agua potable, por m² de terreno.................................. $ 130.76\nb).- A las redes del sistema de alcantarillado sanitario, por m² de terreno........................ $ 98.29\n4.- Para terrenos residenciales unifamiliares y cuyo uso sea exclusivamente para casa habitación:\na).- A las redes del sistema de agua potable, por m² de superficie vendible, incluyendo áreas de donación................................. $ 156.33\nb).- A las redes del sistema de alcantarillado sanitario por m² de superficie vendible, incluyendo áreas de donación................................. $ 107.87\n5.- Para los terrenos destinados a condominios:\na).- A las redes del sistema de agua potable, por m² de terreno.................................. $ 157.80\nb).- A las redes del sistema de alcantarillado sanitario, por m² de terreno........................ $ 97.76\nc).- Adicionalmente a los incisos a) y b), por m² de construcción............................. $ 130.62 cálculo, deberá de acreditarse mediante documentación oficial que emita la autoridad municipal competente.\n6.- Para predios destinados a locales, establecimientos y desarrollos comerciales, industriales, turísticos, gubernamentales y otros no domésticos, así como los terrenos de propiedad gubernamental destinados a escuelas, parques, jardines y campos deportivos públicos, el cobro lo determinará el organismo previo análisis, en función a las necesidades de abasto de agua, infraestructura y capacidad de diseño, de acuerdo a las siguientes tarifas:\na).- A las redes del sistema de agua potable, por litro por segundo............................... $ 1,297,663,74\nb).- A las redes del sistema de alcantarillado sanitario, por litro por segundo.................. $ 717,499.13\nc).- En aquellos casos en que no sea posible determinar las necesidades de abasto, capacidad de diseño e infraestructura, se tomará como base un gasto medio diario obtenido para zona industrial, comercial y equipamiento urbano o donación de.8 (punto ocho)litros por segundo por hectárea (.8 l/s/ha).\nEn el caso de escuelas y universidades públicas y privadas, la necesidad de abasto de agua e infraestructura, se determinará considerando 60 litros por alumno/día de acuerdo a las tarifas de los incisos a) y b) de este numeral.\nTratándose de los apartados de este inciso D), los dueños de los fraccionamientos y desarrollos, serán los obligados sanitario. doméstico a no doméstico, el organismo al tener conocimiento, cobrará la diferencia que resulte del cálculo del cambio. del organismo se demuestre que sus consumos y necesidad de abasto se han incrementado, están obligados a cubrir la diferencia que resulte del cálculo de los derechos de conexión para agua potable y alcantarillado sanitario, con base a la Ley de Ingresos vigente en la fecha que se determine la diferencia.\nE).- TOMAS Y DESCARGAS NO REGISTRADAS.\n1.- En caso de que sea detectada una toma no registrada instalada en el Municipio de Tijuana, el cobro será de acuerdo a la siguiente manera:\na).- En la detección de tomas no registradas domésticas, se tomará como base para el cobro 230 litros por día y por habitante, considerando hasta 4.1 habitantes por familia, por un máximo de hasta por 5 años, al 100% de la tarifa para uso doméstico aprobada por la Ley de\nIngresos del Estado en la fecha en que sea detectada dicha toma.\nEn la detección de tomas no registradas domésticas a usuarios de los que se señalan en el primer párrafo de este Artículo 9, como son las personas en situación de pobreza mayores de 60 años, personas viudas en situación de pobreza mayores de 50 años, o que estando en situación de pobreza, sean el único sostén del hogar con hijos menores de edad, así como, personas con discapacidad, jubilados y pensionados que no la Unidad de Medida y Actualización, se tomará como párrafo anterior por un período máximo de 6 meses.\nb).- En la detección de tomas no registradas comerciales, industriales, gubernamentales y desarrollos turísticos, así como otras no domésticas, se tomará como base para el cobro por consumo de agua, el servicio, proyectado desde la fecha de instalación de la toma, y si no fuere posible determinar fecha cierta hasta por un máximo de 10 años, a la tarifa vigente de detectada dicha toma.\nLa determinación del período de cobro para los incisos anteriores, se hará basándose en la documentación que presente el usuario con valor legal probatorio y dictamen emitido por el organismo, partiendo de la fecha de interconexión a la red que suministra el servicio de agua potable.\nAsimismo, el cobro deberá realizarse también por los derechos de conexión y obra según corresponda.\n2.- En caso de que sea detectada una descarga no registrada instalada en el Municipio de Tijuana, y que no cuenten con el servicio de agua potable, el cobro será de acuerdo a la siguiente manera:\na).- En la detección de descargas no registradas domésticas, se tomará como base para el cobro 80 litros por día y por habitante, considerando hasta 4.1 habitantes por familia, por un máximo de hasta por 5 años, al 40% de la tarifa aprobada por consumo de agua para uso doméstico por la Ley de Ingresos del Estado en la fecha en que sea detectada dicha descarga. de este Artículo 9, como son las personas en situación de pobreza mayores de 60 años, personas viudas en situación de pobreza mayores de 50 años, o que estando en situación de pobreza, sean el único sostén del hogar con hijos menores de edad, así como, personas con discapacidad, jubilados y pensionados que no la Unidad de Medida y Actualización, se tomará como párrafo anterior por un período máximo de 6 meses.\nb).- En la detección de descargas no registradas comerciales, gubernamentales, industriales y de desarrollos turísticos, así como otras no domésticas, servicio, hasta por un período de 10 años, al 40% de la tarifa de servicio medido vigente en la Ley de\nIngresos del Estado, en la fecha en que sea detectada dicha descarga.\nEn caso de que sea detectada una descarga no registrada instalada en el Municipio de Tijuana, en usuarios registrados para el suministro del servicio de agua potable, el cobro será por los conceptos de derechos de conexión para alcantarillado sanitario, derrama de obra e instalación de descarga.\nLa determinación del período de cobro para los incisos anteriores, se hará basándose en la documentación que presente el usuario con valor legal probatorio y dictamen emitido por el organismo, partiendo de la fecha de interconexión a la red que suministra el servicio de descarga de agua.\nAsimismo, el cobro deberá realizarse también por los derechos de conexión y obra según corresponda.\nF).- OTROS SERVICIOS.\n1.- Por la expedición de opiniones técnicas para los servicios de agua potable, alcantarillado sanitario y plantas de tratamiento de aguas residuales, con vigencia de seis meses.\na).- Para terrenos de uso doméstico............. $ 354.57\nb).- Para terrenos de uso Comercial, Industrial y otros no domésticos................................ $ 720.63\nc).- Para los sistemas de tratamiento (PTAR).....$ 1,170.66\nd).- Para la verificación de calidad de agua potable y/o agua residual...............................$ 372.31 potable y alcantarillado sanitario, deberán estar cubiertos o convenidos los derechos de conexión correspondientes.\n2.- Por revisión de proyecto para la construcción de redes de agua potable y alcantarillado, en predios hasta de 5,000 m² de superficie, por plano....................... $ 1,775.17\nMás, por cada m² de superficie adicional, por proyecto....................................... $ 0.05\n3.- Por revisión de proyecto para la construcción de plantas de tratamiento y cárcamos de bombeo:\na).- Hasta 10 lps............................... $22,611.62\nb).- De 10.1 a 30 lps........................... $32,421.43\nc).- Más de 30.1 lps............................ $42,410.85\nA partir de la tercera revisión, para cualquier capacidad de tratamiento..................................$10,450.00 uso de suelo emitido por la autoridad correspondiente.\n4.- Por hidrante contra incendios instalado del sistema de agua potable el equivalente a 5 m³ mensuales a la tarifa para uso comercial, industrial, gubernamental y otros no domésticos.\n5.- Por expedición, y cotejo de expedientes o de documentos:\na).- Por expedición y certificación de documentos, con vigencia de seis meses......................... $193.69\nb).- Expedición de copias simples de expedientes o documentales, por hoja, tamaño carta u oficio por cada lado............................................$ 20.98\nc).- Cotejo de documentos públicos y/o privados.... $408.76\nd).-Por expedición de constancia de existencia o inexistencia de contrato, permiso, autorización o certificación................................. $ 78.98\n6.- Por expedición de certificados de libertad de gravamen.......................................... $401.82\n7.- Cambios de medidor, costo del aparato y protección de los mismos, instalación de toma de agua domiciliaria y descarga de drenaje de aguas negras, así como el costo de la introducción de las redes de agua potable y alcantarillado, y otros servicios no contemplados en este capítulo, se pagará el importe de acuerdo con el presupuesto que previamente formule el organismo que preste el servicio.\nEl costo de la introducción de las redes de agua potable y alcantarillado sanitario, se pagarán de acuerdo a los presupuestos que previamente formule el organismo que presta el servicio. Para aquellos usuarios que después de\n12 meses de haber sido ejecutada y notificada la obra y el presupuesto, no hayan contratado, el costo que deberá cubrir será aquel que resulte de haber aplicado el porcentaje de incremento que haya tenido la Unidad de\nMedida y Actualización, desde la fecha de notificación del presupuesto a los beneficiarios de dicha obra hasta la fecha de contratación.\n8.- Los propietarios o poseedores de predios que tengan una o aguas negras, se les aplicará el 40% de la tarifa de agua potable, sobre el volumen vertido a las descargas de aguas negras, restando en su caso el volumen facturado por el organismo operador.\n9.- Por la inspección interna por fugas no visibles en:\na).- Residencial y comercial.................. $ 1,206.15\nb).- Fraccionamientos, solicitadas por desarrolladores de vivienda.............................. $ 1,660.45\nMás, $2.00 por metro lineal inspeccionado.\nc).- Hoteles, solicitadas por los usuarios de dicho servicio................................ $ 4,568.01\n10.- Por la instalación y/o remoción de reductor en servicio doméstico.................................... $ 261.50\n11.- Por la reconexión de servicio no domestico:\na).- Reconexión para medidor de 12.6 mm (1/2”) hasta 19 mm\n(3/4”) de diámetro......................... $ 1,440.91\nb).- Reconexión para medidor desde 25.4 mm (1”) hasta\n50.08 mm (2”) de diámetro.................. $ 4,488.75\nc).- Reconexión para medidor de 101.4 mm (4”) o de mayor diámetro................................... $ 8,131.56\n12.- Por el sondeo de descarga domiciliaria....... $ 495.58\n13.- Por localización de toma de agua potable o descarga por hora.......................................... $ 489.13\n14.- En aquellos casos en que el usuario requiera una inspección por parte del Organismo, se realizará el mencionan:\na).- Inspección General para usuarios Domésticos...$ 176.08\nb).- Inspección General para usuarios Comerciales, Industriales, Gubernamentales y otros No\nDomésticos...................................$ 263.99\n15.- Por el trámite de cambio de propietario o poseedor del predio y/o razón social............................$ 211.15\nSECCIÓN VI\nMUNICIPIO DE PLAYAS DE ROSARITO.\nA).- SERVICIO MEDIDO.\nPrecios al Consumidor (INPC) que corresponda al mes de facturación más un 1% acumulable cada mes. Este último porcentaje, no será aplicable a las tarifas establecidas en los tres primeros rangos de consumo que van desde 0 m³ hasta\n15 m³ para Uso Doméstico.\n1.- Uso doméstico.\nLos usuarios que tengan medidor en el Municipio de Playas de Rosarito, causarán mensualmente por cada metro cúbico consumido, en forma escalonada y por cada uno de los rangos, la siguiente\na).- De 0 hasta 5 m³, cuota mínima............ $ 149.30\nb).- Por el excedente de 5 y hasta 10 m³, por cada m³ consumido................................ $ 30.23\nc).- Por el excedente de 10 y hasta 15 m³, por cada m³ consumido................................ $ 30.88\nd).- Por el excedente de 15 y hasta 20 m³, por cada m³ consumido................................ $ 48.65\ne).- Por el excedente de 20 y hasta 25 m³, por cada m³ consumido................................ $ 81.58\nf).- Por el excedente de 25 y hasta 30 m³, por cada m³ consumido................................ $ 84.35\ng).- Por el excedente de 30 y hasta 35 m³, por cada m³ consumido................................ $ 106.60\nh).- Por el excedente de 35 y hasta 40 m³, por cada m³ consumido................................ $ 107.51\ni).- Por el excedente de 40 y hasta 45 m³, por cada m³ consumido................................ $ 121.54\nj).- Por el excedente de 45 y hasta 50 m³,por cada m³ consumido................................ $ 121.97\nk).- Por el excedente de 50 y hasta 60 m³, por cada m³ consumido............................... $ 142.03\nl).- Por el excedente de 60 m³ en adelante, por cada m³ consumido............................... $ 143.05\nA los usuarios domésticos que efectúen su pago mensual y lo hagan antes de la fecha de vencimiento durante tres meses consecutivos, en el cuarto pago oportuno gozarán de un descuento del 15% sobre el importe de este último; sin que se interrumpa la consecutividad de los pagos mensuales cuando éstos comprendan dos ejercicios fiscales.\nEste descuento será aplicable siempre y cuando no se tenga el beneficio de otro estímulo fiscal para este servicio.\nPara continuar gozando de este descuento, además de seguir cumpliendo con lo dispuesto en el párrafo anterior, deberán transcurrir por lo menos tres meses entre la obtención de cada beneficio.\n2.- Uso comercial, industrial, gubernamental y otros no domésticos. de Rosarito, causarán mensualmente por cada metro cúbico consumido, en forma escalonada y por cada uno de los rangos, la siguiente\nTARIFA:\na).- De 0 hasta 5 m³, cuota mínima............ $ 737.82\nb).- Por el excedente de 5 y hasta 15 m³, por cada m³ consumido................................ $ 173.82\nc).- Por el excedente de 15 y hasta 20 m³, por cada m³ consumido................................ $ 183.82\nd).- Por el excedente de 20 y hasta 30 m³, por cada m³ consumido................................ $ 187.15\ne).- Por el excedente de 30 y hasta 40 m³, por cada m³ consumido................................ $ 193.61\nf).- Por el excedente de 40 y hasta 100 m³, por cada m³ consumido................................ $ 201.85\ng).- Por el excedente de 100 y hasta 1,000 m³, por cada m³ consumido................................ $ 205.97\nh).- Por el excedente de 1,000 m³ en adelante, por cada m³ consumido................................ $ 210.00\nPara desarrolladores, fraccionadores, centros comerciales u otros no domésticos en donde el organismo determina la instalación de medidor control y cuyas redes aún no se encuentran entregadas al organismo, el desarrollador estará obligado a incluir en los proyectos de cada etapa de construcción la instalación de un medidor control, el cual servirá para registrar la diferencia que existe entre el volumen total suministrado al fraccionamiento o desarrollo y el consumo total registrado por los medidores individuales (la micro medición).\nConcluida o entregada la etapa de edificación deberán estar cubiertos los derechos de consumo de agua; así como contratados los servicios al 100% de la micro medición; reubicación o cancelación del medidor según proceda.\n3.- En aquellos usuarios que por caso fortuito o fuerza mayor por el Organismo, se estará en lo dispuesto por el Manual de Políticas de Bonificaciones.\n4.- Aguas residuales en planta o fuera de planta a quienes lo soliciten.\na).- Tratada, por cada m³ entregada en planta..... $ 7.60\nb).- Tratada, por cada m³ entregada en el domicilio del usuario..................................... $ 21.60\nc).- Sin tratar, por cada m³ entregada en planta.. $ 1.34\nd).- Sin tratar, por cada m³ entregado en planta para uso agrícola..................................... $ 1.34\n5.- El costo de agua por servicio y suministro en tomas fijas para ser distribuidas en camiones cisterna, exclusivamente a usuarios que no cuenten con sistemas de redes de agua potable en sus predios, por cada m³............. $ 41.96\n6.- Derecho anual de reserva de aguas residuales, tratadas y no tratadas.\na).- Por cada m³.............................. $ 0.48\n7.- Servicios de registro de transporte de agua residual tratada y/o transporte de camión cisterna de fosa séptica.\na).- Establecimiento de recepción de aguas residuales sanitarias domésticas y no domésticas.......$ 3,146.37\nb).- Registro dotación de agua residual tratada en camión cisterna....................................$ 7,217.26\nc).- Revalidación anual de registro dotación de agua residual tratada...........................$ 4,114.83\nd).- Registro de transporte de agua residual tratada.\nIncluye: cubicación de unidad y recepción, análisis de documentos..............................$ 2,202.09\ne).- Revalidación anual del registro de transporte de agua residual tratada. Incluye: recepción de documentos y análisis de los mismos, verificación de cubicación de unidades....................................$ 2,256.05\nf).- Por el registro de transporte camión cisterna adicional para recepción de agua residual tratada.......................................$ 835.02\ng).- Registro de transporte de camión cisterna para fosa séptica.....................................$ 2,202.09\nh).- Revalidación anual de transporte de camión cisterna para fosa séptica.........................$ 2,067.95\ni).- Permiso para descargar domingos del mes......$1,112.87\n8.- Derechos en materia de servicios de saneamiento. parámetros que se descarguen en forma excedida de los límites establecidos por la normatividad vigente en materia ambiental y los ordenamientos técnicos.\na).- Remover la demanda química de oxígeno (DQO) por cada Kg.................................. $ 17.11\nb).- Remover la demanda bioquímica de oxígeno (DBO) por cada Kg.................................. $ 17.36\nc).- Remover los sólidos suspendidos totales (SST) por cada Kg.................................. $ 17.78\nd).- Por cada revisión y verificación de las condiciones alcantarillado sanitario................. $ 1,240.19\ne).- Recepción de aguas residuales sanitarias vertida por camiones cisterna (pipa), por m³.......... $ 14.04\nf).- Análisis de laboratorio de los parámetros conforme a\nla NOM-002-SEMARNAT-1996.\nI.- De 6 muestras simples en el mismo día.. $17,982.61\nII.-De 4 muestras simples en el mismo día.. $16,214.08\nIII.-De 2 muestras simples en el mismo día..$11,611.76\nIV.- De 1 muestra simple en el mismo día....$ 9,969.81\nV.- Cuando el usuario es responsable del muestreo............................. $16,214.02\ng).- Por recepción y evaluación de la documentación conjunto de aguas residuales.............. $ 7,710.23\nh).- Revaluación anual del contrato de tratamiento conjunto de aguas residuales.................... $ 4,395.90\ni).- Recepción, tratamiento y confinamiento de lodos de fraccionamientos habitacionales:\nI.- Por recepción y evaluación de la documentación relativa a la firma del contrato de confinamiento de lodos............................ $ 7,710.24\nII.- Revaluación anual del contrato de confinamiento de lodos............................. $ 4,395.90\nIII.- Recepción de lodos estabilizados (biosólidos) provenientes de plantas de tratamiento de aguas residuales de fraccionamientos habitacionales, por m3............................... $ 740.50\nIV.- Recepción de lodos sin estabilizar provenientes fraccionamientos habitacionales, por m3................................... $ 1,481.01\nj).- Por los servicios de toma de muestras y análisis del laboratorio de aguas residuales:\nI.- Por el servicio de muestreo simple de aguas residuales................................ $ 1,068.95\nII.- Por el muestreo simple de parámetros de la NOM001-SEMARNAT-1996.................... $12,485.82\nIII.- Por el análisis del parámetro:\nPH.................................. $ 126.71\nDemanda Bioquímica de Oxígeno....... $ 691.41\nDemanda Química de Oxígeno.......... $ 399.48\nGrasas y aceites.................... $ 583.87\nFósforo Total....................... $ 414.88\nDetergentes......................... $ 583.87\nNitrógeno Total..................... $ 583.87\nNitrógeno Amoniacal................. $ 583.87\nCloro Residual...................... $ 307.35\nColiformes Totales.................. $ 737.58\nColiformes Fecales.................. $ 737.58\nConductividad....................... $ 122.91\nTemperatura......................... $ 61.47\n% Salinidad......................... $ 122.91\nSólidos Totales..................... $ 230.45\nSólidos Totales Disueltos........... $ 276.57\nSólidos Totales Volátiles........... $ 276.57\nSólidos Suspendidos Totales......... $ 276.57\nSólidos Suspendidos Volátiles....... $ 322.58\nSólidos Sedimentables............... $ 184.39\nAluminio............................ $ 599.25\nArsénico............................ $ 599.25\nBario............................... $ 599.25\nBoro................................ $ 599.25\nCadmio.............................. $ 599.25\nCalcio.............................. $ 599.25\nCobre............................... $ 599.25\nCianuro Total....................... $ 149.00\nCromo Hexavalente................... $ 599.25\nCromo Total......................... $ 599.25\nEstaño.............................. $ 599.25\nFierro.............................. $ 599.25\nMagnesio............................ $ 599.25\nMercurio............................ $ 599.25\nNíquel.............................. $ 599.25\nPlata............................... $ 599.25\nPlomo............................... $ 599.25\nPotasio............................. $ 599.25\nSodio............................... $ 599.25\nZinc................................ $ 599.25\nOtros............................... $ 599.25\nk).- Por la recepción de agua residual fuera de norma, proveniente de descargas al sistema de alcantarillado, de procesos productivos de empresas con giros industriales o comerciales, así como de fraccionamientos habitacionales, de conformidad con el artículo 277-B, fracción I, y Octavo Transitorio de la Ley Federal de Derechos, por cada m3.. $ 1.19\nl).- Por la recepción y evaluación de la documentación aguas residuales al sistema de alcantarillado a usuarios no domésticos.................... $ 6,066.26\nm).- Por la recepción y evaluación de la documentación relativa a la revaluación del permiso de descargas de aguas residuales al sistema de alcantarillado a usuarios no domésticos.................... $ 3,458.56\nn).- Análisis de solicitud de prórroga para presentar revaluación de los registros de descarga de aguas potencialmente contaminantes a los sistemas de alcantarillado sanitario.................. $ 1,616.06 ñ).- Cambios de razón social, fusiones, transferencias de derechos y obligaciones respecto a resoluciones o trámites en general....................... $ 4,852.92\no).- Por el análisis para reconsideración de condicionantes de permiso de descarga de agua residual.................................. $ 2,824.86\np).- Por el trámite inicial o revalidación de permiso de servicios:\n1.- Por expedición........................ $ 1,688.77\n2.- Por la revalidación anual............. $ 916.62\nq).- Inspección y evaluación para la expedición de la grasa y sólidos............................$ 2,258.73\nr).- Visita adicional de verificación, para la expedición de constancia atrapa la grasa..............$1,104.37\ns).- Inspección y evaluación para la expedición de la grasa y sólidos, de redimensionamiento y verificación............................... $ 1,276.80\nt).- Evaluación de prórroga para el programa atrapa la grasa........................................$ 309.54\nu).- Inspección y evaluación para la expedición de la la grasa.....................................$1,202.03\nv).- Inspección y evaluación para la expedición de exención de constancia programa atrapa la grasa y solidos.....................................$ 1,264.86\nw).- Por emisión de proyecto ejecutivo de interceptor de grasas y aceites, programa atrapa la grasa.......................................$ 326.08\nx).- Por emisión de proyecto ejecutivo de sistemas de retención de sólidos de tortillerías, lavanderías entre otros comercios y servicios..........$ 276.64\nLa prestación del servicio será en los términos que\nTijuana.\n9.- Los usuarios que tengan medidor en el Municipio de Playas de Rosarito, causarán mensualmente por cada metro cúbico conexión que determine el organismo............. $ 59.40\n10.-Por el análisis de muestras de agua potable en laboratorio certificado del organismo, según los parámetros preestablecidos a solicitud del usuario........ $ 1,441.81\nB).- TOMAS COMUNALES.\nLos consumos de las cuentas de este tipo de tomas, serán vigente de acuerdo con el punto número uno.\nC).- SERVICIO SIN MEDIDOR. promedio de la zona y para los no domésticos, el consumo será correspondiente, con base a las estadísticas de consumo para este tipo de usuarios.\nD).- DERECHOS DE CONEXIÓN AL SISTEMA DE AGUA POTABLE Y\nALCANTARILLADO:\n1.- Para los terrenos residenciales unifamiliares de fraccionamientos y colonias populares, definidos de conformidad con el Artículo Quinto Transitorio de esta Ley, y cuyo uso sea exclusivamente para casa habitación:\na).- A las redes del sistema de agua potable, por m² de superficie vendible incluyendo áreas de donación................................. $ 19.85\nb).- A las redes del sistema de alcantarillado, por m² de superficie vendible incluyendo áreas de donación................................. $ 12.38\n2.- Para los terrenos destinados a desarrollos de vivienda de interés social y popular, definidos de conformidad con el\nArtículo Quinto Transitorio de esta Ley, el derecho a pagar construir, será de:\na).- Tratándose de vivienda de interés social:\n1).- Por agua potable.................... $ 3,972.44\n2).- Por alcantarillado sanitario........ $ 2,750.06\nb).- Tratándose de vivienda popular:\n1).- Por agua potable.................... $ 7,150.39\n2).- Por alcantarillado sanitario........ $ 4,950.11\n3.- Para los terrenos destinados a desarrollos de vivienda de interés social en condominio, acreditados como tales por la exclusivamente para casa habitación:\na).- A las redes del sistema de agua potable, por m² de terreno.................................. $ 130.76\nb).- A las redes del sistema de alcantarillado sanitario, por m² de terreno........................ $ 98.29\n4.- Para terrenos residenciales unifamiliares y cuyo uso sea exclusivamente para casa habitación:\na).- A las redes del sistema de agua potable, por m² de superficie vendible, incluyendo áreas de donación................................. $ 156.33\nb).- A las redes del sistema de alcantarillado sanitario por m² de superficie vendible, incluyendo áreas de donación................................. $ 107.87\n5.- Para los terrenos destinados a condominios:\na).- A las redes del sistema de agua potable, por m² de terreno........................ $ 157.80\nb).- A las redes del sistema de alcantarillado sanitario, por m² de terreno............. $ 97.76\nc).- Adicionalmente a los incisos a) y b), por m² de construcción....................... $ 130.62 cálculo, deberá de acreditarse mediante documentación oficial que emita la autoridad municipal competente.\n6.- Para predios destinados a locales, establecimientos y desarrollos comerciales, industriales, turísticos, gubernamentales y otros no domésticos, así como los terrenos de propiedad gubernamental destinados a escuelas, parques, jardines y campos deportivos públicos, el cobro lo determinará el organismo previo análisis, en función a las necesidades de abasto de agua, infraestructura y capacidad de diseño, de acuerdo a las siguientes tarifas:\na).- A las redes del sistema de agua potable, por litro por segundo............................... $ 1,297,663.74\nb).- A las redes del sistema de alcantarillado sanitario, por litro por segundo....... $ 717,499.13\nc).- En aquellos casos en que no sea posible determinar las necesidades de abasto, capacidad de diseño e infraestructura, se tomará como base un gasto medio diario obtenido para zona industrial, comercial y equipamiento urbano o donación de.8 (punto ocho)litros por segundo por hectárea (.8 l/s/ha).\nEn el caso de escuelas y universidades públicas y privadas, la necesidad de abasto de agua e infraestructura, se determinará considerando 60 litros por alumno/día de acuerdo a las tarifas de los incisos a) y b) de este numeral.\nTratándose de los apartados de este inciso D), los dueños de los fraccionamientos y desarrollos, serán los obligados sanitario. doméstico a no doméstico, el organismo al tener conocimiento, cobrará la diferencia que resulte del cálculo del cambio. abasto se han incrementado, están obligados a cubrir la conexión para agua potable y alcantarillado sanitario, con determine la diferencia.\nE).- TOMAS Y DESCARGAS NO REGISTRADAS.\n1.- En caso de que sea detectada una toma no registrada instalada en el Municipio de Playas de Rosarito, el cobro será de acuerdo a la siguiente manera:\na).- En la detección de tomas no registradas domésticas, se tomará como base para el cobro 230 litros por día y por habitante, considerando hasta 4.1 habitantes por familia, por un máximo de hasta por 5 años, al 100% de la tarifa para uso doméstico aprobada por la Ley de\nIngresos del Estado en la fecha en que sea detectada dicha toma.\nEn la detección de tomas no registradas domésticas a usuarios de los que se señalan en el primer párrafo de este Artículo 9, como son las personas en situación de pobreza mayores de 60 años, personas viudas en situación de pobreza mayores de 50 años, o que estando en situación de pobreza, sean el único sostén del hogar con hijos menores de edad, así como, personas con discapacidad, jubilados y pensionados que no obtengan ingresos mayores al equivalente a cinco veces la Unidad de Medida y Actualización, se tomará como base para el cobro el cálculo contemplado en el párrafo anterior por un período máximo de 6 meses.\nb).- En la detección de tomas no registradas comerciales, industriales, gubernamentales y desarrollos turísticos, así como otras no domésticas, se tomará como base para el cobro por consumo de agua, el servicio, proyectado desde la fecha de instalación de la toma, y si no fuere posible determinar fecha cierta hasta por un máximo de 10 años, a la tarifa vigente de detectada dicha toma. anteriores, se hará basándose en la documentación que emitido por el organismo, partiendo de la fecha de potable.\nAsimismo, el cobro deberá realizarse también por los derechos de conexión y obra según corresponda.\n2.- En caso de que sea detectada una descarga no registrada instalada en el Municipio de Playas de Rosarito, y que no cuenten con el servicio de agua potable, el cobro será de acuerdo a la siguiente manera:\na).- En la detección de descargas no registradas domésticas, se tomará como base para el cobro 80 litros por día y por habitante, considerando hasta 4.1 habitantes por familia, por un máximo de hasta por 5 años, al 40% de la tarifa aprobada por consumo de agua para uso doméstico por la Ley de Ingresos del Estado en la fecha en que sea detectada dicha descarga.\nEn la detección de descargas no registradas domésticas a usuarios de los que se señalan en el primer párrafo de este Artículo 9, como son las personas en situación de pobreza mayores de 60 años, personas viudas en situación de pobreza mayores de 50 años, o que estando en situación de pobreza, sean el único sostén del hogar con hijos menores de edad, así como, personas con discapacidad, jubilados y pensionados que no la Unidad de Medida y Actualización, se tomará como párrafo anterior por un período máximo de 6 meses.\nb).- En la detección de descargas no registradas comerciales, gubernamentales, industriales y de desarrollos turísticos, así como otras no domésticas, servicio, hasta por un período de 10 años, al 40% de\nIngresos del Estado, en la fecha en que sea detectada dicha descarga. instalada en el Municipio de Playas de Rosarito, en agua potable, el cobro será por los conceptos de derechos de conexión para alcantarillado sanitario, derrama de obra e instalación de descarga.\nLa determinación del período de cobro para los incisos anteriores, se hará basándose en la documentación que presente el usuario con valor legal probatorio y dictamen emitido por el organismo, partiendo de la fecha de interconexión a la red que suministra el servicio de descarga de agua.\nAsimismo, el cobro deberá realizarse también por los derechos de conexión y obra según corresponda.\nF).- OTROS SERVICIOS.\n1.- Por la expedición de opiniones técnicas para los servicios de agua potable, alcantarillado sanitario y plantas de tratamiento de aguas residuales, con vigencia de seis meses.\na).- Para terrenos de uso doméstico............. $ 354.57\nb).- Para terrenos de uso Comercial, Industrial y otros no domésticos................................ $ 720.63\nc).- Para los sistemas de tratamiento (PTAR).....$ 1,170.66\nd).- Para la verificación de calidad de agua potable y/o agua residual...............................$ 372.31 potable y alcantarillado sanitario, deberán estar cubiertos o convenidos los derechos de conexión correspondientes.\n2.- Por revisión de proyecto para la construcción de redes de agua potable y alcantarillado, en predios hasta de 5,000 m² de superficie, por plano....................... $ 1,775.17\nMás, por cada m² de superficie adicional, por proyecto\n.................................................$ 0.05\n3.- Por revisión de proyecto para la construcción de plantas de tratamiento y cárcamos de bombeo:\na).- Hasta 10 lps............................... $22,611.62\nb).- De 10.1 a 30 lps........................... $32,421.43\nc).- Más de 30.1 lps............................ $42,410.85\nA partir de la tercera revisión, para cualquier capacidad de tratamiento..................................$10,450.00\nPara la autorización de los proyectos deberá presentarse el uso de suelo emitido por la autoridad correspondiente.\n4.- Por hidrante contra incendios instalado del sistema de agua potable el equivalente a 5 m³ mensuales a la tarifa para uso comercial, industrial, gubernamental y otros no domésticos.\n5.- Por expedición, y cotejo de expedientes o de documentos:\na).-Por expedición y certificación de documentos, con vigencia de seis meses......................... $193.69\nb).-Expedición de copias simples de expedientes o documentales, por hoja, tamaño carta u oficio por cada lado............................................$ 20.98\nc).-Cotejo de documentos públicos y/o privados..... $408.76\nd).-Por expedición de constancia de existencia o inexistencia de contrato, permiso, autorización o certificación................................. $ 78.98\n6.- Por expedición de certificados de libertad de gravamen.......................................... $401.82\n7.- Cambios de medidor, costo del aparato y protección de los mismos, instalación de toma de agua domiciliaria y descarga de drenaje de aguas negras, así como el costo de la introducción de las redes de agua potable y alcantarillado, y otros servicios no contemplados en este capítulo, se pagará el importe de acuerdo con el presupuesto que previamente formule el organismo que preste el servicio.\nEl costo de la introducción de las redes de agua potable y alcantarillado sanitario, se pagarán de acuerdo a los presupuestos que previamente formule el organismo que presta el servicio. Para aquellos usuarios que después de\n12 meses de haber sido ejecutada y notificada la obra y el presupuesto, no hayan contratado, el costo que deberá cubrir será aquel que resulte de haber aplicado el porcentaje de incremento que haya tenido la Unidad de\nMedida y Actualización, desde la fecha de notificación del presupuesto a los beneficiarios de dicha obra hasta la fecha de contratación.\n8.- Los propietarios o poseedores de predios que tengan una o varias fuentes de abastecimiento de agua o líquidos aguas negras, se les aplicará el 40% de la tarifa de agua potable, sobre el volumen vertido a las descargas de aguas negras, restando en su caso el volumen facturado por el organismo operador.\n9.- Por la inspección interna por fugas no visibles en:\na).- Residencial y comercial.................. $ 1,206.15\nb).- Fraccionamientos, solicitadas por desarrolladores de vivienda................................. $ 1,660.45\nMás, $2.00 por metro lineal inspeccionado.\nc).- Hoteles, solicitadas por los usuarios de dicho servicio................................ $ 4,568.01\n10.- Por la instalación y/o remoción de reductor en servicio doméstico.................................... $ 261.50\n11.- Por la reconexión de servicio no domestico:\na).- Reconexión para medidor de 12.6 mm (1/2”) hasta 19 mm\n(3/4”) de diámetro......................... $ 1,440.91\nb).- Reconexión para medidor desde 25.4 mm (1”) hasta\n50.08 mm (2”) de diámetro.................. $ 4,488.75\nc).- Reconexión para medidor de 101.4 mm (4”) o de mayor diámetro................................... $ 8,131.56\n12.- Por el sondeo de descarga domiciliaria....... $ 495.58\n13.- Por localización de toma de agua potable o descarga por hora.......................................... $ 489.13\n14.- En aquellos casos en que el usuario requiera una inspección por parte del Organismo, se realizará el mencionan:\na).- Inspección General para usuarios Domésticos...$ 176.08\nb).- Inspección General para usuarios Comerciales, Industriales, Gubernamentales y otros No\nDomésticos...................................$ 263.99\n15.- Por el trámite de cambio de propietario o poseedor del predio y/o razón social............................$ 211.15\nSECCIÓN VII\nMUNICIPIO DE TECATE.\nA).- SERVICIO MEDIDO.\nPrecios al Consumidor (INPC) que corresponda al mes de facturación más un 1% acumulable cada mes. Este último porcentaje, no será aplicable a las tarifas establecidas en los tres primeros rangos de consumo que van desde 0 m³ hasta\n15 m³ para Uso Doméstico.\n1.- Uso Doméstico.\nLos usuarios que tengan medidor en el Municipio de Tecate, causarán mensualmente por cada metro cúbico consumido, en forma escalonada y por cada uno de los rangos, la siguiente\na).- De 0 hasta 5 m³, cuota mínima............ $ 112.20\nb).- Por el excedente de 5 y hasta 10 m³, por cada m³ consumido................................ $ 22.14\nc).- Por el excedente de 10 y hasta 15 m³, por cada m³ consumido................................ $ 22.60\nd).- Por el excedente de 15 y hasta 20 m³, por cada m³ consumido................................ $ 31.58\ne).- Por el excedente de 20 y hasta 25 m³, por cada m³ consumido................................ $ 43.64\nf).- Por el excedente de 25 y hasta 30 m³, por cada m³ consumido................................ $ 57.29\ng).- Por el excedente de 30 y hasta 40 m³, por cada m³ consumido................................ $ 78.48\nh).- Por el excedente de 40 y hasta 50 m³, por cada m³ consumido................................ $ 101.08\ni).- Por el excedente de 50 y hasta 60 m³, por cada m³ consumido................................ $ 111.82\nj).- Por el excedente de 60 m³ en adelante, por cada m³ consumido................................ $ 119.16 consecutivos, en el cuarto pago oportuno gozarán de un descuento del 15% sobre el importe de este último; sin que se interrumpa la consecutividad de los pagos mensuales cuando éstos comprendan dos ejercicios fiscales.\nEste descuento será aplicable siempre y cuando no se tenga el beneficio de otro estímulo fiscal para este servicio.\nPara continuar gozando de este descuento, además de seguir cumpliendo con lo dispuesto en el párrafo anterior, deberán transcurrir por lo menos tres meses entre la obtención de cada beneficio.\n2.- Uso comercial, industrial, gubernamental y otros no domésticos.\nLos usuarios que tengan medidor en el Municipio de Tecate, causarán mensualmente por cada metro cúbico consumido, en forma escalonada y por cada uno de los rangos, la siguiente\nTARIFA:\na).- De 0 hasta 5 m³, cuota mínima............ $ 855.06\nb).- Por el excedente de 5 y hasta 30 m³, por cada m³ consumido................................ $ 88.93\nc).- Por el excedente de 30 y hasta 100 m³, por cada m³ consumido................................ $ 148.89\nd).- Por el excedente de 100 y hasta 500 m³, por cada m³ consumido................................ $ 150.76\ne).- Por el excedente de 500 y hasta 1,000 m³, por cada m³ consumido................................ $ 151.50\nf).- Por el excedente de 1,000 y hasta 2,000 m³, por cada m³ consumido.................... $ 161.43\ng).- Por el excedente de 2,000 m³, por cada m³ consumido................................ $ 173.11\nPara desarrolladores, fraccionadores, centros comerciales instalación de medidor control y cuyas redes aún no se encuentran entregadas al organismo, el desarrollador estará obligado a incluir en los proyectos de cada etapa de construcción la instalación de un medidor control, el cual servirá para registrar la diferencia que existe entre el volumen total suministrado al fraccionamiento o desarrollo y el consumo total registrado por los medidores individuales (la micro medición).\nConcluida o entregada la etapa de edificación deberán estar cubiertos los derechos de consumo de agua; así como contratados los servicios al 100% de la micro medición; por lo que el desarrollador deberá solicitar la reubicación o cancelación del medidor según proceda.\n3.- En aquellos usuarios que por caso fortuito o fuerza mayor por el Organismo, se estará en lo dispuesto por el Manual de Políticas de Bonificaciones.\n4.- Aguas residuales en planta o fuera de planta a quienes lo soliciten.\na).- Tratada por cada m³ entregada en planta.... $ 7.02\nb).- Tratada por cada m³ entregada en el domicilio................................. $ 16.53\nc).- Sin tratar, por cada m³ entregada en planta.................................... $ 1.46\nd).- Sin tratar, por cada m³ entregada en planta para uso agrícola.................................. $ 0.81\n5.- El costo de agua por servicio y suministro en tomas fijas para ser distribuidas en camiones cisterna, exclusivamente potable en sus predios, por cada m³............. $ 41.91\n6.- Derecho anual de reserva de aguas residuales, tratadas y no tratadas.\na).- Por cada m³............................... $ 0.50\n7.- Recepción y tratamiento de aguas residuales.\nPor el servicio de tratamiento de aguas residuales para los parámetros que se descarguen en forma excedida de los límites establecidos por la normatividad vigente en materia ambiental y los ordenamientos técnicos.\na).- Remover la demanda bioquímica de oxígeno (DBO) por cada Kg.................................. $ 19.39\nb).- Remover los sólidos suspendidos totales (SST) por cada Kg.................................. $ 19.39\nc).- Remover grasas y aceites (G y A), por cada\nKg....................................... $ 19.39\nd).- Por revisión y verificación de la documentación conjunto de aguas residuales............. $ 7,824.80\ne).- Revalidación anual del convenio de tratamiento conjunto de aguas residuales......... $ 4,694.90\nf).- Por administración del convenio de tratamiento conjunto de aguas residuales y análisis de laboratorio de la descarga, mensualmente............................. $ 4,068.90\ng).- Recepción y tratamiento de aguas residuales sanitarias vertida por camiones cisterna (pipa), por m³....................................... $ 55.49\nh).- Análisis de laboratorio de los parámetros conforme a la NOM-002-SEMARNAT-\n1996..................................... $ 7,355.36\ni).- Análisis de laboratorio de parámetros fisicoquímicos básicos en forma individual, por toma de muestreo compuesto................................. $ 2,128.96\nj).- Análisis de laboratorio de parámetros fisicoquímicos básicos en forma individual, por toma de muestreo simple.............. $ 1,158.52\nAdicionalmente al costo por toma de muestra, Por cada parámetro que se solicite:\nPotencial de hidrógeno (pH).............. $ 70.87\nTemperatura.............................. $ 141.82\nDemanda bioquímica de oxígeno............ $ 1,036.85\nDemanda química de oxígeno............... $ 684.39\nGrasas y aceites......................... $ 822.40\nSólidos sedimentables.................... $ 341.03\nSólidos suspendidos...................... $ 425.68\nNitrógeno total.......................... $ 1,474.65\nFósforo total............................ $ 471.86\nArsénico................................. $ 796.33\nCadmio................................... $ 545.61\nCianuro.................................. $ 766.82\nCobre.................................... $ 545.61\nCromo.................................... $ 545.61\nMercurio................................. $ 796.33\nNíquel................................... $ 545.61\nPlomo.................................... $ 545.61\nZinc..................................... $ 545.61\nCromo Hexavalente........................ $ 545.61\nColiformes fecales....................... $ 739.55\nHuevos de Helmintos...................... $ 1,474.65\nMateria flotante......................... $ 339.15\nk).- Por la recepción y evaluación de la documentación usuarios no domésticos................... $ 5,881.05\nl).- Revaluación a los registros de descargas de aguas alcantarillado sanitario................. $ 3,352.98\nm).- Análisis de solicitud de prórroga para presentar revaluación de los registros de descarga de aguas potencialmente contaminantes a los sistemas de alcantarillado sanitario................. $ 1,566.71\nn).- Por el análisis de solicitud de exención al trámite de permiso de descarga de agua residual..... $ 1,555.42\no).- Cambios de razón social, fusiones, transferencias de derechos y obligaciones respecto a resoluciones o trámites en genera....................... $ 4,474.92\np).- Inspección y evaluación para la expedición de la constancia de cumplimiento al programa de atrapa la grasa y sólidos.......................... $ 2,161.00\nq).- Expedición de constancia de cumplimiento al programa de atrapa la grasa y sólidos............. $ 1,560.00\nr).- Inspección y evaluación para la expedición de la de atrapa la grasa y sólidos............. $ 1,150.27\ns).- Inspección y evaluación para la expedición de exención de constancia programa atrapa la grasa y solidos.................................. $ 1,210.39\nTecate.\n8.- Los usuarios que tengan medidor en el Municipio de Tecate, determine el organismo....................... $ 59.44\nB).- TOMAS COMUNALES.\nLos consumos de las cuentas de este tipo de tomas, serán vigente de acuerdo con el punto número uno.\nC).- SERVICIO SIN MEDIDOR.\nPara los usuarios domésticos sin servicio medido, los consumos serán estimados por el organismo de acuerdo al consumo promedio de la zona y para los no domésticos, el consumo será determinado de acuerdo al consumo medido promedio del giro correspondiente, con base a las estadísticas de consumo para este tipo de usuarios.\nD).- DERECHOS DE CONEXIÓN AL SISTEMA DE AGUA POTABLE Y\nALCANTARILLADO SANITARIO:\n1.- Para los terrenos residenciales unifamiliares de fraccionamientos y colonias populares, definidos de conformidad con el Artículo Quinto Transitorio de esta Ley, y cuyo uso sea exclusivamente para casa habitación.\na).- A las redes del sistema de agua potable, por m² de superficie vendible, incluyendo áreas de donación................................. $ 12.95\nb).- A las redes del sistema de alcantarillado sanitario, por m² de superficie vendible, incluyendo áreas de donación................................. $ 6.81\n2.- Para los terrenos destinados a desarrollos de vivienda de interés social y popular, definidos de conformidad con el\nArtículo Quinto Transitorio de esta Ley, el derecho a pagar construir, será de:\na).- Tratándose de vivienda de interés social:\n1).- Por agua potable.................... $ 2,836.61\n2).- Por alcantarillado sanitario........ $ 1,397.16\nb).- Tratándose de vivienda popular:\n1).- Por agua potable.................... $ 4,747.54\n2).- Por alcantarillado sanitario........ $ 2,338.31\n3.- Para terrenos residenciales unifamiliares y cuyo uso sea exclusivamente para casa habitación:\na).- A las redes del sistema de agua potable, por m² de superficie vendible, incluyendo áreas de donación................................. $ 69.26\nb).- A las redes del sistema de alcantarillado sanitario, por m² de superficie vendible, incluyendo áreas de donación................................. $ 38.04\n4.- Para los terrenos destinados a condominios:\na).- A las redes del sistema de agua potable, por m² de terreno.................................. $ 65.44\nb).- A las redes del sistema de alcantarillado sanitario, por m² de terreno........................ $ 35.94\nc).- Adicionalmente a los incisos a) y b), por m² de construcción............................. $ 17.99 que emita la autoridad municipal competente.\n5.- Para predios destinados a locales, establecimientos y desarrollos comerciales, industriales, turísticos, gubernamentales y otros no domésticos, así como los terrenos de propiedad gubernamental destinados a escuelas, parques, jardines y campos deportivos públicos, el cobro lo determinará el organismo previo análisis, en función de las necesidades de abasto de agua potable, capacidad de diseño e infraestructura, de acuerdo a lo siguiente:\na).- A las redes del sistema de agua potable, por litro por segundo............................... $ 1,004,021.98\nb).- A las redes del sistema de alcantarillado sanitario, por litro por segundo................... $ 543,127.36\nc).- En aquellos casos en que no sea posible determinar las necesidades de abasto, capacidad de diseño e infraestructura, se tomará como base una dotación en gasto medio diario obtenido con la dotación para zona industrial, comercial y equipamiento urbano o donación de.8 (punto ocho)litros por segundo por hectárea (.8 l/s/ha)en zona urbana y.64 (punto sesenta y cuatro) litros por segundo por hectárea (.64 l/s/ha) en zona rural.\nd).- En aquellos casos en que no sea posible determinar las necesidades de abasto, capacidad de diseño infraestructura, se tomará como base una aportación en gasto medio diario para zona industrial, comercial y equipamiento urbano o donación de.64 (punto sesenta y cuatro) litros por segundo por hectárea (.64 l/s/ha) en zona urbana y.51 (punto cincuenta y uno) litros por segundo por hectárea (.51 l/s/ha) en zona rural.\nEn el caso de escuelas y universidades públicas y privadas, la necesidad de abasto de agua e infraestructura, se determinará considerando 60 litros por alumno/día de acuerdo a las tarifas de los incisos a) y b) de este numeral.\nTratándose de los apartados de este inciso D), los dueños de los fraccionamientos y desarrollos, serán los obligados sanitario. doméstico a no doméstico, el organismo al tener conocimiento, cobrará la diferencia que resulte del cálculo del cambio. abasto se han incrementado, están obligados a cubrir la conexión para agua potable y alcantarillado sanitario, con que se determine la diferencia.\nE).- TOMAS Y DESCARGAS NO REGISTRADAS.\n1.- En caso de que sea detectada una toma no registrada instalada en este Municipio, el cobro será de acuerdo a la siguiente manera:\na).- En la detección de tomas domésticas no registradas, se tomará como base para el cobro 250 litros por día y por habitante, considerando hasta 4.1 habitantes por familia, por un máximo de hasta por 5 años, al 100% de la tarifa para uso doméstico aprobada por la Ley de\nIngresos del Estado en la fecha en que sea detectada dicha toma.\nEn la detección de tomas no registradas domésticas a usuarios de los que se señalan en el primer párrafo de este Artículo 9, como son las personas en situación de pobreza mayores de 60 años, personas viudas en situación de pobreza mayores de 50 años, o que estando en situación de pobreza, sean el único sostén del hogar con hijos menores de edad, así como, personas con discapacidad, jubilados y pensionados que no la Unidad de Medida y Actualización, se tomará como párrafo anterior por un período máximo de 6 meses.\nb).- En la detección de tomas no registradas comerciales, industriales, gubernamentales y desarrollos turísticos, así como otras no domésticas, se tomará como base para el cobro por consumo de agua, el servicio, proyectado desde la fecha de instalación de la toma, y si no fuere posible determinar fecha cierta hasta por un máximo de 10 años, a la tarifa vigente de detectada dicha toma. anteriores, se hará basándose en la documentación que emitido por el organismo, partiendo de la fecha de interconexión a la red que suministra el servicio de agua potable.\nAsimismo, el cobro deberá realizarse también por los derechos de conexión y obra según corresponda.\n2.- En caso de que sea detectada una descarga no registrada instalada en este Municipio, y que no cuenten con el servicio de agua potable, el cobro será de acuerdo a la siguiente manera:\na).- En la detección de descargas no registradas domésticas, se tomará como base para el cobro 100 litros por día y por habitante, considerando hasta 4.1 habitantes por familia, por un máximo de hasta por 5 años, al 40% de la tarifa de servicio medido aprobada por consumo de agua para uso doméstico por la Ley de\nIngresos del Estado en la fecha en que sea detectada dicha descarga.\nEn la detección de descargas no registradas domésticas a usuarios de los que se señalan en el primer párrafo de este Artículo 9, como son las personas en situación de pobreza mayores de 60 años, personas viudas en situación de pobreza mayores de 50 años, o que estando en situación de pobreza, sean el único sostén del hogar con hijos menores de edad, así como, personas con discapacidad, jubilados y pensionados que no la Unidad de Medida y Actualización, se tomará como párrafo anterior por un período máximo de 6 meses.\nb).- En la detección de descargas no registradas comerciales, gubernamentales, industriales y desarrollos turísticos, así como otras no domésticas, servicio, hasta por un período de 10 años, al 40% de\nIngresos del Estado, en la fecha en que sea detectada dicha descarga.\nEn caso de que sea detectada una descarga no registrada instalada en el Municipio de Tecate, en usuarios registrados para el suministro del servicio de agua potable, el cobro será por los conceptos de derechos de conexión para alcantarillado sanitario, derrama de obra e instalación de descarga.\nLa determinación del período de cobro para los incisos anteriores, se hará basándose en la documentación que presente el usuario con valor legal probatorio y dictamen emitido por el organismo, partiendo de la fecha de interconexión a la red que suministra el servicio de descarga de agua.\nAsimismo, el cobro deberá realizarse también por los derechos de conexión y obra según corresponda.\nF).- OTROS SERVICIOS.\n1.- Por la expedición de opiniones técnicas para los servicios de agua potable, alcantarillado sanitario y plantas de tratamiento de aguas residuales (PTAR), por cada cuenta asignada por el organismo con vigencia de seis meses:\na).- Para terrenos de uso residencial.......... $ 387.16\nb).- Para terrenos de uso Comercial, Industrial y otros no residenciales............................. $ 748.39\nc).- Para los sistemas de tratamiento (PTAR)... $ 1,114.91\n2.- Por la expedición de constancias de factibilidad de servicios de agua potable y alcantarillado sanitario, con vigencia de seis meses:\na).- Para terrenos de uso Residencial............$ 387.16\nb).- Para terrenos de uso Comercial e Industrial.$ 748.39 potable y alcantarillado sanitario, deberán estar cubiertos o convenidos los derechos de conexión correspondientes.\n3.- Por revisión de proyecto para la construcción de redes de agua potable y alcantarillado, en predios hasta de 5,000 m² de superficie, por plano........................ $ 2,007.02\nMás, por cada m² de superficie adicional, por plano.......................................... $ 0.04\n4.- Por revisión de proyecto para la construcción de plantas de tratamiento y cárcamos de bombeo:\na).- Hasta 10 lps...............................$22,611.62\nb).- De 10.1 a 30 lps...........................$32,421.43\nc).- Más de 30.1 lps............................$42,410.85\nA partir de la tercera revisión, para cualquier capacidad de tratamiento................................ $10,450.00 uso de suelo emitido por la autoridad correspondiente.\n5.- Por hidrante contra incendios instalado del sistema de agua potable, el equivalente a 5 m³ mensuales a la tarifa para uso comercial, industrial, gubernamental y otros no domésticos.\n6.- Por expedición y certificación de documentos, con vigencia de seis meses.................................. $ 201.50\n7.- Por expedición de certificados de libertad de gravamen....................................... $ 476.44\n8.- Por localización de toma o descarga........... $ 1,112.87\n9.- Para la instalación o reposición de medidor y protección de los mismos, instalación de toma de agua domiciliaria y descarga de drenaje de aguas negras, así como el costo de otros servicios no contemplados en este capítulo, se pagará formule el organismo que preste el servicio. alcantarillado sanitario, se pagarán de acuerdo a los presupuestos que previamente formule el organismo que presta el servicio. Para aquellos usuarios que después de\n12 meses de haber sido ejecutada y notificada la obra y el presupuesto, no hayan contratado, el costo que deberá cubrir será aquel que resulte de haber aplicado el porcentaje de incremento que haya tenido la Unidad de\nMedida y Actualización, desde la fecha de notificación del presupuesto a los beneficiarios de dicha obra hasta la fecha de contratación.\n10.- Los propietarios o poseedores de predios que por cualquier motivo utilicen el alcantarillado de aguas negras, sin ser contribuyentes de los derechos de consumo de agua o bien aquellos no domésticos que tengan el servicio suspendido, pagarán:\nEn el primer caso, el 40% del consumo de agua estimado por señala el inciso A), puntos 1 y 2.\nEn el segundo caso, el 40% de su consumo de agua promedio de los últimos 6 meses, a las cuotas que señala el inciso\nA), puntos 1 y 2.\n11.- Por la remoción de reductor en servicio doméstico.................................... $ 459.84\n12.- Por la reconexión del servicio de uso comercial, industrial, gubernamental y otros no domésticos.................................... $ 919.42\n13.- Por la cancelación y remoción de reductor.... $ 459.84\n14.- Por el sondeo de descarga según el tipo de servicio:\na) Domiciliaria.............................. $ 480.91\nb) Comercial, Industrial o Gobierno.......... $ 1,992.41\n15.- Por la revisión de proyecto para la construcción de plantas de tratamiento y cárcamos de bombeo:\na) Hasta 10 lps............................ $ 23,553.69\nb) De 10.1 a 30 lps........................ $ 33,772,19\nc) Más de 30.1 lps......................... $ 44,177.80\n16.- Por la inspección interna por fugas no visibles en:\na) Residencial y comercial................. $ 1,112.87\nb) Fraccionamientos, solicitadas por desarrolladores de vivienda............................... $ 1,532.57\nMás, $2.06 por metro lineal inspeccionado.\nc) Hoteles, solicitadas por los usuarios de dicho servicio................................ $ 4,216.19\n17.- Por revisión de agua potable, alcantarillado sanitario y pozos de visita conforme a proyecto autorizado:\na) Costo unitario por visita.............. $ 708.82\nb) Por hora adicional..................... $ 236.29\n18.- En aquellos casos en que el usuario requiera una inspección por parte del Organismo, se realizará el mencionan:\na).- Inspección General para usuarios\nDomésticos........................................ $176.08\nb).- Inspección General para usuarios Industriales, Gubernamentales y otros No Domésticos........... $ 263.99\nc).- Por la revisión y detección de fuga interna no usuarios Domésticos, Comerciales.................$ 468.64\n19.- Por el trámite de cambio de propietario o poseedor del predio y/o razón social......................... $ 211.15\nCAPÍTULO II\nSERVICIOS DE CONTROL VEHICULAR.\nARTÍCULO 10.- Los servicios a que se refiere el presente Capítulo se cobrarán conforme a las siguientes\nI.- LICENCIAS PARA CONDUCIR:\nLas licencias de conducir tendrán una vigencia de 3 o 5 años, a elección del solicitante, a partir de la fecha de su expedición. Dicho plazo podrá variar, aumentándose de manera proporcional por fracción de año, de acuerdo a la fecha de nacimiento del conductor.\nA).- Por expedición por primera vez:\n1.- De automovilista con vigencia de 3 años.. $ 1,051.46\n2.- De automovilista con vigencia de 5 años.. $ 1,401.95\n3.- De motociclista con vigencia de 3 años... $ 1,051.46\n4.- De motociclista con vigencia de 5 años... $ 1,401.95\n5.- De Chofer \"C\" con vigencia de 3 años..... $ 1,199.82\n6.- De Chofer \"C\" con vigencia de 5 años..... $ 1,599.76\n7.- De Chofer \"A\", \"B\" y \"D\"................. $ 1,978.37\n8.- Licencia para conducir automóviles o motocicletas para menor de 18 años y mayor de 16, hasta por un año...................................... $ 776.48\n9.- Licencia provisional para conducir vehículo de servicio público (pasajeros o carga) por 12 meses, por única vez............................ $ 976.20 de chofer “C”. cuenten con licencia de chofer.\n10.- Licencia provisional de automovilista, motociclista o chofer “C”, nacional o extranjero, hasta por nueve meses.................................... $ 900.75\nB).- Por revalidación de licencia de conducir:\n1.- De automovilista con vigencia de 3 años.. $ 933.29\n2.- De automovilista con vigencia de 5 años.. $ 1,244.39\n3.- De motociclista con vigencia de 3 años... $ 933.29\n4.- De motociclista con vigencia de 5 años... $ 1,244.39\n5.- De Chofer \"C\" con vigencia de 3 años..... $ 1,081.65\n6.- De Chofer \"C\" con vigencia de 5 años..... $ 1,442.20\n7.- De Chofer \"A\", \"B\" y \"D\"................. $ 1,860.20\n8.- Licencia para conducir automóviles o motocicletas para menor de 18 años y mayor de 16, hasta por un año...................................... $ 630.11\nC).- En pagos extemporáneos de licencias de conducir, se siguiente manera:\na).- Hasta un año de vencida, el 25% de su costo.\nb).- Hasta dos años de vencida, el 50% de su costo.\nc).- Hasta tres años de vencida, el 75% de su costo.\nd).- Más de tres años de vencida, el 100% de su costo.\nD).- Por reposición de licencia.................... $ 803.59\nE).- Por baja de licencia de conducir.............. $ 372.69\nConforme a lo establecido en el último párrafo de la fracción\nI, del artículo 10 de la Ley de Ingresos del Estado de Baja\nCalifornia correspondiente al ejercicio fiscal 2021, los ciudadanos a quienes se les haya expedido licencia con vigencia permanente deberán acudir a la oficina de recaudación de rentas, cada cinco años contados a partir de la expedición inicial de la misma a efecto de actualizar los datos y fotografía, sin que por ello pierda la calidad de permanente, debiendo pagar únicamente los derechos que corresponda por la reposición de la licencia respectiva.\nEl ciudadano al que le haya sido expedida licencia con vigencia permanente, gozará de un plazo máximo de tres meses siguientes al cumplimiento de los cinco años que se establece para su actualización correspondiente. Sin embargo, en el caso del plazo concedido, su licencia con vigencia permanente dejará de tener vigencia.\nAsimismo, en el caso de reposición de licencia con vigencia permanente por robo, extravío o cualquier otro supuesto que proceda, no se perderá la citada vigencia, supuesto en el que establecidos en el artículo 10, fracción I, inciso D de la presente Ley.\nII.- PLACAS, CALCOMANÍAS, TARJETAS DE CIRCULACIÓN, Y REFRENDOS:\nA).- Servicio Particular:\n1.- Por el Refrendo de la Tarjeta de Circulación:\na).- Automóviles y camiones particulares.. $ 1,120.27\nb).- Motocicletas........................ $ 1,120.27\nc).- Para demostración................... $ 2,109.48\nd).- Remolques.......................... $ 492.16\n2.- Por canje o refrendo extemporáneo, se pagará un adicional sobre su costo de expedición de la siguiente manera:\na).- Hasta tres meses de su vencimiento, el 50% de su costo.\nb).- Más de tres meses y hasta seis meses de su vencimiento, el 75% de su costo.\nc).- Más de seis meses de su vencimiento, el 100% de su costo.\n3.- Por expedición de Placas:\na).- Automóviles y camiones particulares.. $ 1,828.81\nb).- Motocicletas......................... $ 367.00\nc).- Para demostración................... $ 4,125.60\nd).- Remolques............................ $ 1,325.94\ne).- Para vehículo de persona con discapacidad.............................$ 1,828.81\n4.- Por canje extemporáneo, se pagará un adicional sobre su costo de expedición de la siguiente manera:\na).- Hasta tres meses de su vencimiento, el 50% de su costo.\nb).- Más de tres meses y hasta seis meses de su vencimiento, el 75% de su costo.\nc).- Más de seis meses de su vencimiento, el 100% de su costo.\n5.- Por expedición de tarjeta de circulación por primera vez:\na).- Automóviles y camiones particulares.. $ 1,736.35\nb).- Motocicletas......................... $ 1,736.35\nc).- Para demostración.................. $ 4,149.19\nd).- Remolques............................ $ 1,596.85\n6.- Expedición de constancia de registro de vehículo todo terreno:\na).- Por expedición por primera vez de constancia anual de registro en el padrón vehicular estatal, de vehículos todo terreno cuya circulación no es permitida en poblaciones y caminos del Estado.................. $ 1,119.91\nb).- Por la expedición anual, de la constancia de registro en el padrón vehicular estatal, de vehículos todo terreno.............. $ 762.91\nB).- Servicio Público:\n1.- Por el Refrendo de la Tarjeta de Circulación:\na).- Taxis y autobuses de pasajeros........$ 1,125.04\nb).- Camiones de carga.....................$ 1,517.52\nc).- Motocicletas..........................$ 1,125.04\n2.- Por canje o refrendo extemporáneo, se pagará un adicional sobre su costo de expedición de la siguiente manera:\na).- Hasta tres meses de su vencimiento, el 50% de su costo.\nb).- Más de tres meses y hasta seis meses de su vencimiento, el 75% de su costo.\nc).- Más de seis meses de su vencimiento, el 100% de su costo.\n3.- Por expedición de placas:\na).- Taxis y autobuses de pasajeros....... $ 2,100.92\nb).- Camiones de carga................... $ 2,492.64\nc).- Motocicletas........................ $ 344.33\n4.- Por canje extemporáneo, se pagará un adicional sobre su costo de expedición de la siguiente manera:\na).- Hasta tres meses de su vencimiento, el 50% de su costo.\nb).- Más de tres meses y hasta seis meses de su vencimiento, el 75% de su costo.\nc).- Más de seis meses de su vencimiento, el 100% de su costo.\n5.- Por expedición de tarjeta de circulación por primera vez:\na).- Taxis y autobuses de pasajeros.......$ 2,259.26\nb).- Camiones de carga....................$ 2,259.26\nc).- Motocicletas.........................$ 2,259.26\nC).- Reducción por pronto pago: ejercicio fiscal 2025, se les otorgará una reducción en ejercicio, de acuerdo al siguiente calendario:\n1.- En el mes de enero, gozarán de una reducción del\n12%.\n2.- En el mes de febrero, gozarán de una reducción del\n8.5%.\n3.- En el mes de marzo, gozarán de una reducción del 5%.\nEl citado beneficio aplica para el pago de derechos correspondientes al ejercicio fiscal 2025.\nIII.- OTROS SERVICIOS:\n1.- Por expedición de constancias.................. $ 298.83\n2.- Certificación de documentos expedidos por la Recaudación de Rentas....................... $ 298.83\n3.- Por reposición de tarjetas de circulación...... $ 375.22\n4.- Por reposición de placas de servicio particular $1,392.20\n5.- Por baja del padrón vehicular.................. $ 375.22\n6.- Por reposición de placas de taxis y autobuses de pasajeros........................ $1,704.65\n7.- Por reposición de placas de camiones de carga......................................... $2,154.49\n8.- Por flotillas, en la expedición de calcomanías y tarjetas de circulación, por unidad......................................... $ 202.02\n9.- Por servicio de entrega a domicilio (hasta dos trámites en un mismo domicilio)........................ $ 149.89 mismo, una vez cubiertos dichos gastos, de existir un remanente podrá utilizarse para gasto corriente.\n10.- Por servicio de recaudación en la empresa, por trámite........................................ $ 238.25\n11.- Por servicio de control vehicular en agencias de autos.......................................... $ 238.25\n12.- Por servicio de revisión del vehículo y documentos para altas al padrón vehicular en el domicilio del contribuyente.................................. $ 238.25\n13.- Por expedición por única vez, de permiso de traslado, por\n15 días....................................... $ 1,011.44\n14.- Por los servicios relativos a la verificación física y validación de los documentos del vehículo que amparan la propiedad y legal estancia dentro del territorio del país, al dar de alta y cambio de propietario en el registro vehicular del Estado.................. $ 219.45\n15.- Por los servicios relativos a la validación del registro de vehículos provenientes de otras entidades federativas.................................... $ 219.45\nTratándose del servicio de entrega a domicilio, el recibir la tarjeta de circulación; en los demás casos al momento de solicitar el servicio.\nCAPÍTULO III\nSERVICIOS DEL INSTITUTO DE MOVILIDAD SUSTENTABLE.\nArtículo 11.– Los derechos por los servicios de planeación, operación del transporte, permisos, concesiones y control vehicular, que brinda el Instituto de Movilidad Sustentable del cuotas:\nI.- Por servicios para el mejoramiento de la movilidad sostenible y la accesibilidad, en particular aplicable a prestadores del\nEstado de Baja California.\nVECES UNIDAD DE MEDIDA\nY ACTUALIZACIÓN\nA).- Por recepción, análisis y emisión de Dictamen de\nFactibilidad del servicio de transporte público y privado en cualquiera de sus modalidades, incluye la definición de tipo de transporte, características y dimensiones de los recorridos:\n1.- Por modificación de fracción de ruta menor a 300 metros lineales dentro del límite del centro de población.............................. 43.75 VECES\n2.- Por modificación de fracción de ruta menor a 300 metros lineales fuera del límite del centro de población.............................. 43.75 VECES\n3.- Por ampliación de ruta dentro del límite del centro de población, por cada 1 metro lineal... 0.15 VECES\n4.- Por ampliación de ruta fuera del límite del centro de población, por cada 1 metro lineal..... 0.25 VECES\n5.- Por ruta nueva dentro del límite del centro de población por metro lineal............. 138.12 VECES\n6.- Por ruta nueva fuera del límite del centro de población por metro lineal............. 138.12 VECES\n7.- Dictamen técnico de factibilidad por incremento de parque vehicular otorgada a la concesión. 21.00\nVECES\n8.- Dictamen técnico de factibilidad por incremento de parque vehicular en sitio de taxi, cobro por unidad................................. 2.00 VECES\n9.- Por recepción y análisis de solicitud de Dictamen\nTécnico de factibilidad:\na) Por expedición de concesión........ 27.50 VECES\nb) Por revalidación y/o modificación de\nConcesión......................... 25.00 VECES\n10.- Expedición de autorización de cambio de color en vehículos de transporte masivo o taxi.. 10.00 VECES\n11.- Expedición de autorización de cambio de ruta para vehículos de transporte masivo o taxi... 20.00 VECES\nB).- Por análisis de solicitud y emisión de Opinión Técnica de\nFactibilidad para la ubicación o utilización de sitios exclusivos para el transporte público y otros, incluye la definición de las características geométricas:\n1.- A solicitud del interesado.............. 138.12 VECES\n2.- Por determinación de la autoridad....... 12.50 VECES\n3.- Modificación de las características geométricas............................ 25.00 VECES\nC).- Por análisis de solicitud y emisión de Opinión Técnica de\nFactibilidad para autorización de cierres de circuito, lanzaderas, bases, encierros, terminales, zonas de ascenso y descenso, y zonas de carga y descarga... 138.12\nVECES\nD).- Expedición de Anuencia de Impacto a la Movilidad de zonas de transporte como son cierres de circuito, lanzaderas, bases, encierros, terminales, zonas de ascenso y descenso en lo específico:\n1.- Por análisis de solicitud de ubicación dentro del primer cuadro y corredores comerciales de la ciudad................................... 27.50 VECES\n2.- Por análisis de solicitud de ubicación fuera del primer cuadro y corredores comerciales de la ciudad................................... 27.50 VECES\n3.- Por reubicación dentro del primer cuadro y corredores comerciales de la ciudad................. 27.50 VECES\n4.- Por reubicación fuera del primer cuadro y corredores comerciales de la ciudad................. 27.50 VECES\n5.- Modificación de las características geométricas.............................. 27.50 VECES\nE).- Por análisis y emisión de Dictamen de Capacidad de unidades para el servicio de carga y arrastre, considerando peso, dimensiones y número de ejes por unidad...................................... 10.00 VECES\nF).- Anuencia de Impacto de Proyectos de Movilidad 27.50 VECES\nG).- Anuencia de Impacto de Movilidad de la emisión o modalidades.................................. 27.50 VECES\nH).- Servicios Técnicos de Planeación del Transporte:\n1.- Por copia impresa de la traza de rutas... 25.00 VECES\n2.- Por copia digital en disco magnético de la traza de rutas.................................. 50.00 VECES\n3.- Por digitalización de rutas de transporte en cualquiera de sus modalidades por unidad. 3.00 VECES\nI).- Expedición de Anuencia para el traslado de sustancias peligrosas:\n1.- Para trasladar dentro de los límites del estado, vehículos con residuos peligrosos, sustancias toxicas, gasolina y/o explosivos. Siempre y cuando para el manejo de éstos:\na) Por una semana...................... 30.00 VECES\nb) Por un mes.......................... 55.00 VECES\nc) Por un año.......................... 137.00 VECES\nJ).- Expedición de Anuencia para la modificación de los elementos de identificación de las unidades de transporte público por instalación de publicidad:\n1.- Publicidad gráfica en unidades de transporte público por metro cuadrado, con vigencia de 6 meses.................................... 2.00 VECES\n2.- Publicidad gráfica de programas institucionales de los tres órganos de gobierno en unidades de transporte público por metro cuadrado, con vigencia de 6 meses.............................. Exento\nK).- Expedición de anuencia para la circulación con perifoneo de unidades de transporte:\n1.- Publicidad mediante perifoneo en transporte.15.00\nVECES\n2.- Publicidad de programas institucionales mediante perifoneo en transporte...................... Exento\nL).- Expedición, revalidación y transferencia de permisos para prestar servicio de transporte y otros:\n1.- De alquiler, escolar y carga, por permiso:\na)- De alquiler:\n1) Expedición por permiso........ 120.00 VECES\n2) Revalidación por permiso...... 90.00 VECES\n3) Transferencia de la titularidad entre terceros....................... 90.00 VECES\n4) Transferencia de la titularidad de permiso por defunción.................. 46.24 VECES\n5) Por recepción y análisis de solicitud de\nAnuencia de Impacto a la Movilidad para prestar el servicio de transporte en la configuración de ejecutivo-turístico por un periodo de 30 días por unidad:\na) Por emisión.............. 27.50 VECES\nb) Por revalidación......... 25.00 VECES\nb)- Escolar:\n1) Expedición por permiso.......... 70.00 VECES\n2) Revalidación de permiso........ 50.00 VECES\n3) Transferencia de la titularidad entre terceros........................ 70.00 VECES\n4) Transferencia de la titularidad de permiso por defunción................... 46.24 VECES\nc)- De carga y arrastre:\n1) Expedición por permiso para carga y arrastre........................ 100.00 VECES\n2) Revalidación por permiso para carga y arrastre........................ 90.00 VECES\n3) Transferencia de la titularidad entre terceros........................ 60.00 VECES\n4) Transferencia de la titularidad de permiso por defunción................... 46.24 VECES\n5) Por el servicio de pesaje al transporte público de carga en básculas que para tal efecto habilite el Instituto..... 3.00 VECES\n6) Por recepción y análisis de solicitud de\nAnuencia de Impacto a la Movilidad para prestar el servicio de transporte de carga por un periodo de 30 días por unidad:\na) Por emisión.................... 27.50 VECES\nb) Por revalidación.............. 25.00 VECES\n2.- Modificación de permiso.................. 20.00 VECES\n3.- Reposición de permiso.................... 20.00 VECES\n4.- Concesión de transporte público masivo, de personal y turístico:\na)- Por 1 a 15 años por unidad autorizada:\n1) Expedición de concesión........ 110.00 VECES\n2) Revalidación de concesión...... 110.00 VECES\n3) Modificación de concesión por ampliación de parque vehicular, por unidad.... 110.00 VECES\n4) Activación de parque vehicular por unidad.......................... 110.00 VECES\nb)- De 16 a 30 años por unidad autorizada:\n1) Expedición de concesión.......... 220.00 VECES\n2) Revalidación de concesión........ 220.00 VECES\n3) Modificación de concesión por ampliación de parque vehicular por unidad...... 220.00 VECES\n4) Activación de parque vehicular por unidad........................... 220.00 VECES\n5.- Impresión de permiso estatal en sustitución de permiso municipal por única vez.................... 5.00 VECES\nM).- Servicios de Control Vehicular del Servicio Público de\nTransporte, adicionales a los señalados en el artículo 10 de la presente Ley:\n1.- Anuencia para adquirir taxímetro......... 6.00 VECES\n2.- Constancia de no adeudo.................. 2.00 VECES\n3.- Expedición de autorización temporal para circular sin placas por única vez por 30 días........ 10.00 VECES\n4.- Anuencia para aplicaciones digitales para taxis................................... 20.00 VECES\n5.- Autorización para uso de aplicación digital para taxis.............................. 20.00 VECES\nN.- Expedición de documentos, certificados, constancias, engomados, hologramas y copias:\n1.- Expedición de identificación para operadores de transporte público, privado y Empresas de Redes de\nTransporte (ERT) en todas sus modalidades.............................. 8.00 VECES\n2.- Revalidación de identificación para operadores y conductores de transporte público, privado y\nEmpresas de Redes de Transporte (ERT), en todas sus modalidades, cada año.................... 3.00 VECES\n3.- Reposición de identificación para operadores y conductores de trasporte público, privado y Empresas de Redes de Trasporte (ERT), en todas sus modalidades............................. 2.00 VECES\n4.- Expedición de tarjetón.................. 8.00 VECES\n5.- Expedición de autorización de cambio de color................................... 10.00 VECES\n6.- Expedición de autorización de cambio de ruta.................................... 20.00 VECES\n7.- Expedición de engomado QR, para transporte público, privado, y Empresas de Redes de Transporte, por unidad.................................. 6.00 VECES\n8.- Reposición de engomado QR, para transporte público, privado y Empresas de Redes de Transporte en todas sus modalidades, por unidad............. 6.00 VECES\n9.- Expedición de cartas:\na) Carta de operador sustituto activo con permiso.............................. 2.00 VECES\nb) Carta de operador sustituto con suspensión........................... 4.00 VECES\n10.- Por expedición de copias:\na) Simple por hoja...................... 0.013 VECES\nb) Copia certificada.................... 1.10 VECES\nO).- Por el análisis, revisión, cotejo, digitalización y captura de documentos.\n1.- Cotejo de archivo por hoja.............. 2.00 VECES\n2.- Por el análisis, revisión, digitalización y captura de documentos........................... 6.00 VECES\nP).- Servicios de Control Vehicular de Empresas de Redes de\nTransporte (ERT):\n1.- Autorización de vehículo para operar mediante\nEmpresas de Transporte (ERT) (única vez). 30.00\nVECES\n2.- Autorización para la operación de una Empresa de\nRedes de Transporte (ERT) dentro de los límites territoriales del Estado (vigencia de\n1 año).............................. 2,130.00 VECES\n3.- Renovación de la autorización para la operación de una Empresa de Redes de Transporte (ERT) en los límites territoriales del Estado.... 2,130.00 VECES\n4.- Cancelación de la autorización para la operación de una Empresa de Redes de Transporte (ERT) en los límites territoriales del Estado...... 60.00 VECES\n5.- Autorización para la operación de servicios de entrega de alimentos por medio de aplicaciones digitales dentro de los límites territoriales del\nEstado (vigencia de 1 año)........... 900.00 VECES\n6.- Renovación de la autorización para la operación de servicios de entrega de alimentos por medio de aplicaciones digitales dentro de los límites territoriales del Estado............... 900.00 VECES\n7.- Cancelación de la autorización para la operación de aplicaciones digitales dentro de los límites territoriales del Estado............... 60.00 VECES\n8.- Autorización para la operación de servicios de entrega de bienes y mercancías por medio de aplicaciones digitales dentro de los límites territoriales del Estado (vigencia de 1 año)\n...................................... 900.00 VECES\n9.- Renovación de la autorización para la operación de límites territoriales del\nEstado................................. 900.00 VECES\n10.- Cancelación de la autorización para la operación de límites territoriales del\nEstado.................................. 60.00 VECES\nQ).- Expedición, revalidación y transferencia de permisos para prestar servicio de alquiler de vehículos no motorizados, por ubicación, hasta 100 unidades:\n1.- Análisis, recepción y cotejo de estudios técnicos para elaboración de opinión técnica de factibilidad del servicio de alquiler de vehículos no motorizados, por ubicación............................ 23.00 VECES\n2.- Por análisis de solicitud y emisión de opinión técnica de factibilidad para la ubicación o utilización de espacios exclusivos para el alquiler de vehículos no motorizados, incluye la definición de las características geométricas.......... 23.00 VECES\n3.- Por análisis de solicitud y emisión de opinión técnica de factibilidad para la modificación de para el alquiler de vehículos no motorizados............................. 23.00 VECES\n4.- Expedición por permiso.................. 172.65 VECES\n5.- Revalidación por permiso................ 172.65 VECES\n6.- Transferencia de la titularidad entre terceros con autorización............................ 172.65 VECES\n7.- Transferencia de la titularidad de permiso por defunción............................... 46.24 VECES\n8.- Copia certificada de permiso............ 8.75 VECES\n9.- Modificación de permiso por ampliación de parque vehicular, hasta 100 unidades........... 172.65 VECES\nR).- Por efectuar la revisión físico mecánica de los vehículos todas sus modalidades por unidad.............. 5.00 VECES\nII.- Los Usuarios del Servicio de Transporte Público en las modalidades de taxis libres, taxi ejecutivo y taxi mediante una aplicación digital, que opten por utilizar la aplicación\nEstado de Baja California para acceder a los servicios de taxi, deberán cubrir las siguientes:\nTARIFAS\nA).- Por intervalo recorrido:\n1).- 0 KM - 5 KM.................................... $ 5.49\n2).- 6 KM - 18 KM.................................... $10.97\n3).- 19 KM - 30 KM.................................. $16.46\n4).- 31 KM - 73 KM.................................. $21.95\n5).- 74 KM - 174 KM.................................. $49.38\n6).- 175 KM - 361 KM.................................. $60.35\n7).- MAS DE 362 KM.................................. $65.84\nB).- Por cancelación de viaje:\n1).- Cancelación del chofer después de 5 minutos de haber aceptado el servicio...................................$27.43\n2).- Cancelación del Usuario después de 5 minutos de que el chofer haya aceptado el servicio........................$27.43\nIII.- Los derechos por Arrastre de Vehículos se cobrarán por una final, debiendo cubrirse siempre y cuando la maniobra se realice, de acuerdo con la siguiente:\nVECES UNIDAD DE MEDIDA\nY ACTUALIZACIÓN\nA).- Por arrastre:\n1).- Automóvil, camioneta y pick-up.............. 11.40 VECES\n2).- Camiones de pasajeros..................17.55 VECES\n3).- Camiones de servicio público o particular de carga...\n4).- Auto tractores solos o con remolques, por cada maniobra\n5).- Motocicletas...............................11.40 VECES\n6).- Bicicletas.................................. 1.75 VECES\n7).- En caso de que sean necesarias maniobras especiales, se aplicará lo siguiente:\na) Cuando el vehículo que se va a remolcar no cuenta con\nLlantas y/o se encuentra imposibilitado de rodar, así como en camiones y tractocamiones, desatorado en los frenos de aire, volcaduras, salidas de carretera, utilización en dos o más ocasiones de equipo para arrastre................................... 3.51 VECES\nb) Uso de grúa para vehículo con defensa adaptada a la original............................... 3.51 VECES\nc) Uso de maniobra por parte del operador para retirar dificultad............................... 3.51 VECES\nd) Uso de maniobras con alto grado de dificultad cuando sea necesario retirar el cambio en la transmisión, siendo este de tracción trasera y/o conlleve un alto riesgo para el operador de la grúa................. 3.51 VECES\ne) En caso de volcadura de vehículos ligeros en los\nI. Volcadura en áreas planas y aceras de carril de rodamiento.\nII. Volcadura cuando el vehículo sale del camino y cae en un barranco a menos de 10 metros de distancia del carril de rodamiento.\nIII. Volcadura cuando el vehículo sale del camino y cae en un barranco a más de 10 metros de distancia del carril de rodamiento.\nIV. Volcadura cuando el vehículo cae en un barranco poniéndose en riesgo el patrimonio y seguridad de terceras personas.\nf) En caso de volcadura de vehículos de carga y/o autobuses, en los siguientes casos..........39.48 VECES\nI. Volcadura en áreas planas y aceras de carril de rodamiento.\nII. Volcadura cuando el vehículo sale del camino y cae en un barranco a menos de 10 metros de distancia del carril de rodamiento.\nIII. Volcadura cuando el vehículo sale del camino y cae en un barranco a más de 10 metros de distancia del carril de rodamiento.\nIV. Volcadura cuando el vehículo cae en un barranco terceras personas.\nB).- Maniobras inconclusas de grúa, por el evento de reglamentado, con infracción por escrito, pero no realice el grúa, se pagará las siguientes:\n1).- Automóvil, camioneta y pick-up............... 5.26 VECES\n2).- Camiones de pasajeros...................5.26 VECES\n3).- Remolques (tráiler) y autobuses de pasaje.... 8.77 VECES\n4).- Remolque de tractocamiones de tres o más ejes, con una o más cajas.................................... 8.77 VECES\n5).- Motocicletas.................................. 2.63 VECES\n6).- Bicicletas................................... 1.75 VECES\nIV.- Para efectos de este Capítulo se entenderá por:\nCentro de Población: De acuerdo con la división territorial de los municipios en México, un Centro de Población es una porción de territorio que agrupa el conjunto de áreas urbanizadas, las reservas para el crecimiento de la ciudad y las áreas naturales protegidas, por lo que un solo municipio puede contener uno o varios centros de población, en base a la\nLey General de Asentamientos Humanos, Ordenamiento Territorial y Desarrollo Urbano.\nCAPÍTULO IV\nSERVICIOS DE LA DIRECCIÓN DEL REGISTRO PÚBLICO\nDE LA PROPIEDAD Y DE COMERCIO.\nARTÍCULO 12.- Los servicios que se presten en materia de la\nPropiedad, causarán derechos cada vez y se pagarán previamente por los interesados, con excepción de los solicitados por las\nAutoridades Fiscales de la Federación, Estado y Municipios, y\nOrganismos Descentralizados, los cuales se harán efectivos a través crédito fiscal, debiendo éstas enterarlos a la oficina recaudadora partir de la fecha de su cobro, conforme a la siguiente\nI.- Por el análisis que se realice sobre todo tipo de documento inscripción, anotación o cancelación, emisión de dictamen jurídico, ratificación de firma de documento, por cada vez...................................................$ 379.10\nEn caso de que se requiera un segundo o subsecuente análisis, primer párrafo de esta fracción.\nII.- Por la anotación o cancelación que se realice por el aviso preventivo de notario público relativo a escritura en la que se declare, reconozca, adquiera, transmita, modifique, limite, grave o extinga la propiedad o posesión de bienes raíces o cualquier derecho real sobre los mismos, o por las autoridades establecidas en el Artículo 2878, fracción III, del Código\nCivil para el Estado de Baja California, cada vez... $ 283.40\nIII.-Por la inscripción de documentos públicos o privados, por virtud de los cuales se establezca, declare, reconozca, transmita, modifique o extinga el dominio o la propiedad de bienes muebles e inmuebles, asimismo, la condición resolutoria o suspensiva en los casos de venta de bienes raíces, por cada acto en un mismo documento......................... $11,398.60\nIV.- Por la inscripción de toda clase de gravámenes o contratos de garantía que limiten la propiedad o la posesión ordinaria de inmuebles; actos o contratos, en virtud de los cuales se adquieran, se den en comodato, se arrienden, transmitan, limiten o modifiquen derechos reales de muebles e inmuebles distintos de dominio; contratos de crédito hipotecario incluyendo aquellos cuyo destino sea la adquisición, remodelación, ampliación o construcción de vivienda, sobre el monto del gravamen, garantía o acto de que se trate............................................ $ 11,398.60\nQueda comprendida la inscripción de toda clase de gravámenes, prevista en el primer párrafo de esta fracción, cada providencia precautoria, acta de embargo definitiva o precautoria, reinscripciones, actas complementarias y ampliaciones de embargos. del crédito inscrito, se causarán derechos por la diferencia se reconozca adeudar.\nV.- Por la inscripción de contratos que tengan por objeto la popular, por cada acto y unidad de vivienda........ $ 1,801.92 auxiliares de crédito, destinados para la adquisición o construcción individualizada de los tipos de vivienda señalados en esta fracción, sobre el monto que ampara el capital del crédito que se destine a la compra-venta de dichas viviendas y que así se indique en el acto jurídico.\nVI.- Por la inscripción de la designación, aceptación, discernimiento de albacea y declaración de herederos si consta en el mismo documento............................... $1,243.98\nVII.- Por la inscripción:\nA).- De la constitución del patrimonio familiar..... $1,243.98\nB).- Del otorgamiento de poderes, sustitución, revocación o renuncia de los mismos, por cada acto, contenido en un mismo documento.............................. $ 1,040.65\nC).- De actos, contratos, convenios o resoluciones administrativas por los que se constituye un fraccionamiento, se fusione, se lotifique, se relotifique, se divida o subdivida un inmueble, por cada lote que resulte............................... $ 119.57\nD). De actos, contratos, convenios por los que se extinga o constituye el régimen de propiedad en condominio, que no se destine a interés social, por lote, departamento, despacho o local, que lo integre, cada vez.....$ 1,297.89 para vivienda de interés social, por cada departamento.................................... $ 645.87\nE).- De documentos públicos o privados por los que se constituyan Asociaciones Civiles, Sociedades Civiles y\nAsociaciones Religiosas, o por el aumento de capital:\n- Hasta por la cantidad de $ 50,000.00....... $ 4,281.66\n- Por el excedente de $ 50,000.00......... 5.0 al millar de........................................... $ 65,036.14 inmuebles, se estará además a lo dispuesto por el\nArtículo 12, Fracción III.\nF).- De las Actas de Asamblea, y Juntas Administrativas de\nSociedades y Asociaciones Civiles, cada vez.. $ 1,268.87\nG).- De las inscripciones preventivas de demanda, sentencias, jurisdicciones voluntarias que no impliquen declaración de dominio, embargos, cédulas o demandas de juicio especial hipotecario, rescisiones de contratos, convenios modificatorios que no impliquen aumento al monto del crédito, convenios de extinción de fideicomiso..$1,309.73\nH).- De la inscripción o anotación de contratos o convenios que constituyan, modifiquen, liquiden o disuelvan el régimen de sociedad conyugal, así como las capitulaciones matrimoniales................................. $ 1,309.73\nCuando estos documentos impliquen transmisión de bienes inmuebles, se estará además a lo dispuesto por el\nArtículo 12, Fracción III.\nI).- Por el registro e inscripción de Patente, sello y firma de Notario Titular, de Notario Adscrito o de corredor público, cada vez........................... $ 10,412.80\nJ).- Por el registro e inscripción de Patente de aspirante al ejercicio del notariado, cada vez........... $ 10,263.94\nK).- Por el registro de convenios de asociación o suplencia celebrados entre Notarios Públicos, cada vez.. $ 1,404.11\nVIII.- Por la expedición de:\nA).- Certificado de no Propiedad Municipal........... $ 83.62\nB).- Certificado de no Propiedad Estatal............ $ 316.06\nIX.- Por la expedición de:\nA).- Certificados de inscripción con o sin gravamen, por cada predio, departamento o local, hasta 5 hojas........................................ $ 483.12\nPor el excedente de 5 hojas, por cada hoja... $ 8.03 derivado de un mismo antecedente registral, por cada predio, departamento o local, adicional, en un mismo certificado, por cada uno.................. $ 113.57\nB).- Certificación de partida registral, hasta 15 hojas....................................... $ 520.33\nPor el excedente de 15 hojas, por cada hoja...$ 10.84\nC).- Certificado de no inscripción o no contradicción, por cada predio, departamento o local.......... $ 1,223.46\nD).- Historia registral por un predio, departamento o local, sociedad o asociación civil que involucre:\n- Hasta cinco partidas registrales y/o anotaciones................................ $ 1,278.40\n- De seis a diez partidas registrales y/o anotaciones................................ $ 1,643.65\n- Más de diez partidas registrales y/o anotaciones................................ $ 2,812.36\nE).- Cada copia de imagen registral sin certificar, reportes de anotaciones derivadas de las mismas, así como libro de copias de documentos, por cada hoja..... $ 11.90\nX.- Por el retiro de cada testamento ológrafo y expedición de la respectiva constancia............................. $ 1,567.00\nXI.- Por la ratificación de firma de documento, cada vez.$ 825.25\nXII.-Por la cancelación de partidas, por cada partida... $ 364.77\nXIII.-Por la inscripción, anotación, registro, cancelación o este artículo..................................... $ 1,947.04\nXIV.-Por el servicio de consulta al Sistema de Enlace\nRemoto............................................ $ 6,576.10 de pago.\nXV.- Por el registro de cesión de derechos sobre gravámenes relacionados con créditos:\n- Hasta 10 créditos................................ $ 1,826.27\n- De 11 a 20 créditos.............................. $ 3,652.55\n- Más de 21 créditos............................... $ 5,478.81\nXVI.- Por el servicio de alerta registral de predio o lote, por año:\nA).- Por un predio................................ $ 532.04\nB).- Por hasta 4 predios.......................... $1,064.11\nC).- De 5 a 10 predios........................... $2,021.77\nD).- De 11 a 20 predios.......................... $2,660.22\nPor el excedente de 1 hasta 10 predios, $450.29 por cada 10 predios. pertenecientes a una misma persona física o moral. Cuando se derechos por cada propietario, conforme al tabulador anterior.\nARTÍCULO 13.- Para el cobro de los derechos que establece el artículo anterior, se observarán las siguientes reglas:\nI.- Con base en el valor mayor que resulte entre el de operación contractual, el catastral o el de avalúo certificado por la autoridad catastral que no podrá tener antigüedad mayor de un año a la fecha de presentación, el cual deberá ser practicado por Institución Bancaria o Perito Valuador autorizado.\nII.- Toda transmisión de bienes o derechos reales formalizada en documento público o privado, cuando en ella queden comprendidos varios bienes, se pagarán sobre el valor de cada uno de ellos, conforme a la fracción anterior.\nIII.- Cuando un documento público o privado origine inscripción en las diversas Oficinas Registrales de la Dirección del\nRegistro Público de la Propiedad y de Comercio en razón de la ubicación jurisdiccional de los bienes o garantías reales en el Estado, se causarán los derechos por el análisis del mismo una sola vez, y por inscripción en cada una de las oficinas registrales que se requiera.\nIV.- Cuando se soliciten trámites de certificaciones de bienes inmuebles inscritos en otras Oficinas Registrales de la\nDirección del Registro Público de la Propiedad y de Comercio, aplicará la tarifa que establece el Artículo 12, Fracciones\nVIII y IX de esta Ley.\nV.- Cuando se trate de contratos, demandas o resoluciones judiciales y administrativas que se refieran a prestaciones periódicas, el valor se determinará por la suma de éstas, en caso contrario se tomará como base la cantidad que resulte, haciendo el cómputo por anualidades.\nVI.- Tratándose de los Servicios Tecnológicos de Enlaces Remotos a que se refiere la Fracción XIV del Artículo 12 de esta Ley, y de Comercio a entidades públicas o privadas, éstos se la Propiedad y de Comercio.\nVII.- No se causarán los derechos a que se refiere el Artículo 12 en los siguientes casos:\nA).- Los inmuebles regularizados o enajenados por el\nVivienda para el Estado de Baja California.\nB).- Cuando se trate de inmuebles que adquiera la\nAdministración Pública Centralizada, Federal, Estatal o\nMunicipal.\nC).- Cuando se trate de inmuebles regularizados por la\nTierra, Instituto del Fondo Nacional de la Vivienda para los Trabajadores, Fondo de la Vivienda del Instituto de\nSeguridad y Servicios Sociales de los Trabajadores del\nEstado y cualquier otro organismo público facultado por la Federación, Estado o los Municipios de la entidad.\nD).- Por los informes o certificados que soliciten las autoridades correspondientes para asuntos de carácter penal, laboral o juicios de amparo y aquéllos que provengan de la Defensoría Pública estatal o federal.\nE).- Por la inscripción de contratos de apertura de crédito o convenios judiciales cuyo objeto sea la reestructuración de pasivos derivados de contratos de crédito refaccionario y de habilitación o avío, cuyo destino encuadre en lo dispuesto por el Artículo 15, Fracción\nVIII, Inciso B).\nF).- Por la inscripción, anotación y cancelación de hipoteca, embargos precautorios, decomiso y aseguramientos que se términos de la legislación penal aplicable.\nG).- Por la inscripción, anotación y cancelación de actas de fiscales.\nH).- Por la búsqueda y expedición de información respecto a por las Autoridades Judiciales y Notarios Públicos.\nI).- Cuando se trate de la inscripción por primera vez de de Certificación de Derechos Agrarios.\nJ).- Por los certificados de no propiedad solicitados por el\nVivienda para el Estado de Baja California.\nK).- Para la inscripción, anotación y/o cancelación de:\nI.- Mandamientos o resoluciones judiciales que deriven de juicios de orden familiar en beneficio de las mujeres bajacalifornianas.\nII.- Tratándose de inscripciones de disolución de sociedad conyugal cuando el inmueble objeto de inscripción sea de interés social en beneficio de las mujeres bajacalifornianas.\nVIII.- Los documentos depositados con fecha anterior al 31 de diciembre de 2024, que fueron registrables causarán los derechos de acuerdo a la Ley vigente a la fecha de su depósito.\nIX.- Cuando un mismo título o documento origine dos o más inscripciones en el Registro Público de la Propiedad, los derechos se causarán por cada una de ellas, calculándose separadamente, con su cuota respectiva.\nX.- Cuando en un documento el monto o cantidad sea en dólares, la de curso legal en el país, se cuantificarán los derechos momento de la presentación para su registro, con excepción de dólares, unidades de inversión o cualquier otro tipo de moneda indique el equivalente en moneda de curso legal.\nXI.- El usuario podrá solicitar que los servicios previstos en el inciso B) de la fracción VII, así como aquellos del inciso A) y B) de la fracción IX del artículo anterior sean prestados mediante la modalidad acelerada extraordinaria, en cuyo caso del servicio correspondiente.\nXII.- El usuario podrá solicitar la opción de certificado ésta se encuentre disponible, en cuyo caso el pago será el correspondiente.\nARTÍCULO 14.- Los servicios que se presten en materia del Comercio, causarán derechos cada vez y se pagarán previamente por los interesados, con excepción de los solicitados por las Autoridades\nFiscales de la Federación, Estado y Municipios, los cuales se harán efectivos dentro del Procedimiento Administrativo de Ejecución como parte del crédito fiscal, debiendo éstas enterarlos a la oficina recaudadora correspondiente dentro de los treinta días naturales contados a partir de la fecha de su cobro, conforme a la siguiente\nI.- Por el análisis que se realice sobre todo tipo de documento, sea público o privado, que se presente al Registro para su inscripción, anotación o cancelación, por cada vez............................................ $ 379.10\nEn caso de que se requiera un segundo o subsecuente análisis, primer párrafo de esta fracción.\nII.- Por la inscripción de:\nA).- Matrícula de un comerciante persona física.. $ 1,243.98\nB).- Inscripción de documentos públicos o privados, resoluciones judiciales o administrativas, por virtud de los cuales se establezca, declare, adquiera, transmita, propiedad de buques, aeronaves y en general de bienes mercantiles, sobre el valor mayor que resulte entre el de factura o avalúo certificado, practicado por Institución\nBancaria o Perito Valuador autorizado..... 5.0 al millar\nEn ningún caso el derecho correspondiente excederá de............................... $ 56,275.63\nC).- De los instrumentos públicos en los que se consigne la constitución, escisión, aumento de capital o fusión de sociedades mercantiles, sobre el aumento o el incremento que experimente, incluyendo las Asociaciones en\nParticipación, Sociedades de Producción Rural y\nSociedades Cooperativas:\n- Hasta por la cantidad de $ 50,000.00... $ 4,485.72\n- Por el excedente de $ 50,000.00........ 5.0 al millar\nEn ningún caso el derecho correspondiente excederá de....................................... $ 67,680.62\nCuando estos documentos impliquen transmisión de bienes inmuebles, se estará además a lo dispuesto por el\nArtículo 12, Fracción III.\nD).- Actas de asamblea, cada vez.............. $ 3,115.96\nCuando en dichas actas queden comprendidas el aumento de capital y el otorgamiento de poderes, sustitución o revocación de los mismos, se estará a lo dispuesto por los incisos C) y H) de esta Fracción.\nE).- Del depósito o resguardo de programas de la firma balances bancarios, industriales o comerciales a que se refieren los Artículos 92, 125, fracción VII, 177 y 242\nMercantiles............................. $ 1,243.98\nF).- Anotación o depósito del acta de emisión de bonos y la emisión.............................. 5.0 al millar\nG).- De la disolución o liquidación de sociedades mercantiles constitución de la sociedad, cada acto.... $ 1,243.98\nH).- Del otorgamiento de poderes, sustitución, renuncia o revocación de los mismos, por cada acto contenido en un mismo documento...........................$ 1,243.98\nI).- Por cada acta de embargo definitiva, precautoria, reinscripciones, actas complementarias, ampliaciones de embargos, así como secuestros del orden mercantil, sobre su monto................................. 5.0 al millar\nEn ningún caso el derecho correspondiente excederá de........................................ $ 56,233.07\nEn los casos en los que de un mismo mandamiento de autoridad deriven dos o más actas de embargo, se causarán derechos por una sola vez, respecto al total del adeudo.\nJ).- De declaraciones judiciales de suspensión de pago, sentencias de estado de quiebra........... $ 400.63\nK).- De contratos, convenios o corresponsalía mercantil…................................ $ 1,243.98\nL).- Por la inscripción o anotación de contratos de créditos hipotecarios, refaccionarios, de habilitación o avío, destinados a la adquisición de materias primas y a la realización de actividades industriales y comerciales, así como la consolidación y reestructuración de pasivos concertados con las Instituciones de Crédito, de Seguros, de Fianzas o de cualquier otra índole mercantil, incluyendo apoyo a capital de trabajo, sobre el monto del crédito................................... 3.5 al millar diferencia en el monto del crédito inscrito, se causarán inscrito y la suma de dinero que se reconozca adeudar. de........................................ $ 112,454.21\nM).- El arrendamiento financiero............... 5.0 al millar de........................................ $ 56,233.07\nN).- Del fideicomiso en administración o en garantía.................................. $ 4,072.94\nÑ).- Del fideicomiso traslativo de dominio, sobre el valor autorizado................................ 5.0 al millar\nEn ningún caso el derecho correspondiente excederá de........................................ $ 56,233.07\nIII.- Por el registro relativo a inscripciones principales cuando se refieran a modificaciones de plazo, intereses o garantías, números equivocados o cualquier otra que no constituya renovación de contrato.......................... $ 1,243.98\nEn tratándose de rectificación o modificación de la cuantía, se cobrará por la diferencia de acuerdo al tipo de contrato.\nIV.- Por la ratificación de firma de documento, cada vez............................................ $ 825.25\nV.- Por las inscripciones de fianzas, contrafianzas y obligaciones solidarias con el fiador, para el solo efecto de comprobar la solvencia del fiador, del contrafiador y del obligado solidario, cuando éstos sean sujetos de derecho mercantil, sobre su monto................................. 3.5 al millar de............................................. $ 95,671.57\nVI.- Por la cancelación de partidas, por cada partida........................................ $ 364.77\nVII.- Por expedición de:\nA).- Certificado de no propiedad............... $ 83.62\nB).- Certificados de inscripción con o sin gravamen.................................. $ 263.59\nC).- Certificación de partida registral, hasta 15 hojas..................................... $ 520.33\n- Por el excedente de 15 hojas, por cada hoja..................................... $ 10.84\nD).- Por cada certificado de inscripción o no inscripción en materia de contratos de mandato y sociedades mercantiles............................... $ 520.33\nE).- Historia registral de sociedades mercantiles:\n- Hasta cinco partidas registrales y/o anotaciones............................ $ 1,278.40\n- De seis a diez partidas registrales y/o anotaciones............................ $ 1,643.65\n- Más de diez partidas registrales y/o anotaciones.............................. $ 2,812.36\nF).- Cada copia de imagen registral sin certificar, reportes de anotaciones derivadas de las mismas, así como libro de copias de documentos, por cada hoja...................................... $ 11.90 autoridades estatales, federales, municipales u organismos descentralizados, se causarán derechos conforme a los incisos anteriores.\nVIII.- Por la inscripción, anotación, registro, cancelación o fracciones de este artículo..................... $ 1,947.04\nIX.- Por el registro de cesión de derechos sobre gravámenes relacionados con créditos:\n- Hasta 10 créditos.......................... $ 1,826.27\n- De 11 a 20 créditos........................ $ 3,652.55\n- Más de 21 créditos......................... $ 5,478.81\nARTÍCULO 15.- Para el cobro de los derechos que establece la tarifa del artículo anterior, se observarán las siguientes reglas:\nI.- Con base en el valor mayor que resulte entre el de operación contractual, el fiscal o el de avalúo que no podrá tener antigüedad mayor de un año a la fecha de presentación, el cual deberá ser practicado por Institución Bancaria o Perito\nValuador autorizado.\nII.- Toda transmisión de bienes o derechos reales formalizada en documento público o privado, cuando en ella queden comprendidos varios bienes, se pagarán sobre el valor de cada uno de ellos, conforme a la fracción anterior.\nIII.- Cuando un mismo título o documento origine dos o más inscripciones en el Registro del Comercio, los derechos se causarán por cada una de ellas, calculándose separadamente, con su cuota respectiva.\nIV.- Cuando un documento público o privado origine inscripción en las diversas Oficinas Registrales de la Dirección del\nRegistro Público de la Propiedad y de Comercio en razón de la el Estado, se causarán los derechos por el análisis del mismo una sola vez, y por inscripción en cada una de las oficinas registrales que se requiera.\nV.- Cuando se trate de contratos, demandas o resoluciones periódicas, el valor se determinará por la suma de éstas, en caso contrario se tomará como base la cantidad que resulte, haciendo el cómputo por anualidades.\nVI.- En los contratos mercantiles relativos a buques y aeronaves en los que medie condición suspensiva, resolutoria, reserva inscripción complementaria para su perfeccionamiento, se pagará el total de lo que corresponda, de acuerdo con la disposición aplicable.\nVII.- Respecto de inscripciones relativas a embarcaciones o aeronaves, los derechos se cobrarán con base en el valor mayor que resulte entre el de operación, factura o de avalúo, autorizado.\nVIII.- No se causarán los derechos a que se refiere el artículo anterior:\nA).- Por los informes o certificados que soliciten las autoridades correspondientes para asuntos de carácter penal, laboral, administrativo y juicios de amparo.\nB).- Por la inscripción de contratos de crédito refaccionario y de habilitación o avío, destinados a la adquisición de materias primas y materiales y en el pago de los jornales, salarios y gastos decretados de explotación indispensables para los fines de su actividad, aperos, útiles de labranza, ganado o animales de cría y la realización de plantaciones o cultivos cíclicos o permanentes, compra o instalación de maquinarias de la construcción de obras, materiales para el fomento de la actividad agropecuaria como perforación de pozo profundo y electrificación, así como la pesca o acuacultura, crédito. sólo se refiera a lo que establece este inciso, sino diverso, este último se cobrará de acuerdo a lo establecido en la Fracción II, Inciso L) del Artículo 14 de esta Ley.\nC).- Por la inscripción de contratos de apertura de crédito o de pasivos derivados de contratos de crédito refaccionario y de habilitación o avío, cuyo destino encuadre en lo dispuesto por el Inciso anterior.\nD).- De la inscripción, anotación y cancelación de actas de embargo provenientes de autoridades laborales.\n12 y la fracción I del artículo 14 de esta Ley, se destinará al\nFondo para la Modernización del Registro Público de la Propiedad y de Comercio del Estado, en los términos que se establecen en los artículos 86 y 87 de la Ley del Registro Público de la Propiedad y de Comercio para el Estado de Baja California, y con base a las reglas que determine la Secretaría de Hacienda.\nCAPÍTULO V\nSERVICIOS DE LA SECRETARÍA DE ECONOMÍA E INNOVACIÓN\nARTÍCULO 16.- Por los servicios que presta la Secretaría de\nEconomía e Innovación, se cubrirán las siguientes\nI.- AGENTE PROFESIONAL INMOBILIARIO.\na).- Por el estudio y evaluación de factibilidad de servicios de agentes......................................... $ 4,863.11\nb).- Por la revaluación trianual de agente profesional inmobiliario...................................... $ 3,782.42\nc).- Por la reposición de licencia de agente profesional inmobiliario...................................... $ 270.17\nd).- Por la expedición de Constancias de agentes profesionales inmobiliarios....................... $ 270.17\nCAPÍTULO VI\nCALIFORNIA.\nARTÍCULO 17.- Por los servicios que prestan la Secretaría del Medio al Ambiente de Baja California, se cubrirán las siguientes\nI.- IMPACTO AMBIENTAL. al impacto ambiental.\nA).- Recepción y evaluación del Informe Preventivo. $ 9,144.02\nB).- Recepción y evaluación de la Manifestación del Impacto\nAmbiental:\n1.- En su modalidad general:\na) En su modalidad general que comprenda las actividades señaladas en el artículo 13 fracción I, II, IV, V, VIII, IX, X, XII y XIII del Reglamento de la Ley de\nProtección al Ambiente del Estado de Baja California en materia de Impacto Ambiental......... $ 21,101.60\nb) En su modalidad general que comprenda las actividades señaladas en el artículo 13 fracción III, VII y XI\nAmbiental............................... $ 30,245.62\nc) En su modalidad general que comprenda las actividades señaladas en el artículo 13 fracción VI del\nAmbiental............................... $ 70,338.66\nd) En su modalidad general que comprenda Carreras fuera de Carretera............................ $ 30,245.62\n2.- Modalidad planes y programas............ $ 84,406.40\n3.- Estudios de riesgo...................... $ 13,797.34\nII.- DESCARGAS Y EMISIONES. los registros de emisiones a la atmósfera.\nA).- Recepción y evaluación de emisiones a la atmósfera:\n1.- Registro de emisiones a la atmósfera.... $ 7,286.23\nB).- Revaluación a los registros de emisiones a la atmósfera:\n1.- Registro de emisiones a la atmósfera.... $ 4,154.15\nIII.- PRESTADORES DE SERVICIOS AMBIENTALES.\nPor los servicios que a continuación se señalan con respecto a las personas físicas o morales como prestadores de servicios ambientales:\nA).- Por el estudio y evaluación de factibilidad para prestar servicios ambientales:\n1.- Auditor ambiental....................... $ 7,286.23\n2.- Perito en monitoreo..................... $ 7,286.23\n3.- Prestador de servicios en materia de impacto ambiental............................... $13,509.21\n4.- Laboratorio ambiental................... $15,587.60\nB).- Por la inscripción al padrón de prestador de servicios en materia de Impacto Ambiental, Auditores Ambientales, Laboratorios Ambientales y Peritos en Monitoreo.\na).- Por la inscripción al padrón de prestador de servicios en materia de impacto ambiental.................... $13,509.21\nb).- Por la inscripción al padrón de Auditores\nAmbientales............................. $ 7,286.23\nc).- Por la inscripción al padrón de Laboratorios\nAmbientales............................ $ 15,587.60\nd).- Por la inscripción al padrón de Peritos en\nMonitoreo............................... $ 7,286.23\nC).- Por la evaluación para seguir inscrito en el padrón de prestador de servicios en Materia de Impacto Ambiental, Auditores Ambientales, Laboratorios Ambientales y Peritos en Monitoreo.\na).- Evaluación para seguir inscrito en el padrón de prestador de servicios en materia de impacto ambiental............................... $ 8,105.55\nb).- Evaluación para seguir inscrito en el padrón de auditores ambientales.................. $ 4,371.79\nc).- Evaluación para seguir inscrito en el padrón de laboratorios ambientales............... $ 9,352.51\nd).- Evaluación para seguir inscrito en el padrón de perito en monitoreo..................... $ 4,371.79\nIV.- OTROS SERVICIOS.\na).- Cambios de razón social, fusiones, transferencias de trámites en general......................... $ 5,604.72\nb).- Por el análisis para la reconsideración de condicionantes de autorización y licencia...$ 3,262.47\nc).- Por la evaluación en materia de impacto ambiental por modificaciones a proyectos autorizados...... $ 4,242.65\nd).- El servicio de visitas de verificación a petición de parte, para constatar el cumplimiento de condicionantes en materia de impacto ambiental:\n1.- En sitios ubicados dentro de los centros de población.............................. $ 4,684.06\n2.- En sitios ubicados fuera de los centros de población.............................. $15,613.53\ne).- Análisis de solicitud de prórroga para dar cumplimiento a condicionantes de impacto ambiental, del permiso de emisiones, de descargas de aguas residuales y de residuos de manejo especial.................. $ 1,950.37\nf).- Análisis de solicitud de exención del trámite de registro de emisiones a la atmosfera y/o registro como generador de residuos de manejo especial.................................... $ 1,950.37\ng).- Cotejo de hojas, por hoja................... $ 61.45\nh).- Expedición de copias simples de documentales integradas al expediente, por cada hoja................ $ 13.63\ni).- Análisis de prórroga para presentar la información adicional en materia de impacto ambiental, de riesgo y del registro y/o reevaluación en materia del permiso de emisiones a la atmósfera y en materia de residuos de manejo especial............................. $ 1,877.14\nj).- Cualquier otra certificación o expedición de constancias................................. $ 443.27\nk).- Revaluación de la manifestación del impacto ambiental................................... $13,797.34\nl).- Expedición de constancia de disposición de llantas de parte de la autoridad competente............ $ 970.56\nm).- Están obligados por la recepción y evaluación de la manejo especial en el Estado de Baja California:\nPequeño Generador y Grande Generador......... $ 1,363.18 considera como: a) Gran Generador: Persona física o moral que genere una cantidad igual o superior a 10 equivalente en otra unidad de medida; y b) Pequeño\nGenerador: Persona física o moral que genere una cantidad igual o mayor a cuatrocientos kilogramos y menor a diez toneladas en peso bruto total de residuos al año o su equivalente en otra unidad de medida.\nn).- Están obligadas las personas físicas o morales por la recepción y evaluación de la solicitud para registro para la realización de la actividad, relativa a la prestación del servicio de manejo integral de residuos de manejo especial...........................$ 15,338.27 ñ).- Por la recepción y disposición de llantas o neumáticos de vehículos que se reciba en los centros de acopio de la Secretaría de Medio Ambiente y Desarrollo\nSustentable; por cada llanta o neumático de:\nAutomóvil y motocicleta.................... $ 10.35\nCamiones urbanos y similares................ $ 20.72\nTractocamión u otros........................ $ 20.72\no).- Por recepción y evaluación del Plan de Manejo de\nResiduos de manejo especial................... $3,459.64\np).- Actualización del Plan de Manejo de Residuos de manejo especial.................................... $ 1,911.38\nq).- Recepción y evaluación del reporte anual de Generadores de Residuos de manejo especial.............. $ 1,729.79\nr).- Actualización al Registro como Generador de Residuos de manejo especial en el Estado................ $ 660.46\ns).- Análisis de la solicitud de revalidación de licencia de\nResiduos de manejo especial.................. $ 8,917.58\nt).- Modificaciones a la licencia de prestador para el manejo integral de residuos de manejo especial..... $ 2,110.16\nu).- Recepción y evaluación del informe anual de Prestadores manejo especial.............................. $ 2,461.85\nv).- Reporte de cumplimiento de permisos, licencias y autorizaciones en materia de emisiones al aire, al agua y al suelo y sus transferencias a través de la Cédula de\nOperación Anual Estatal..................... $ 8,442.37\nEl cobro señalado en el inciso s) se realizará por una sola vez.\nCAPÍTULO VII\nLEGALIZACIÓN Y RATIFICACIÓN DE FIRMAS, EXPEDICIÓN DE CERTIFICADOS Y\nCERTIFICACIONES, ESTUDIOS DE CUMPLIMIENTO, PUBLICACIONES, SERVICIOS\nPARA VALUADORES Y SERVICIOS DE PROTECCIÓN CIVIL.\nARTÍCULO 18.- Los derechos de legalización y ratificación de firmas, expedición de certificados y certificaciones, estudios de cumplimiento y revaluación de estudios no comprendidos en otros capítulos de la presente Ley, publicaciones en los Órganos de\nDirección del Registro Civil del Estado, la Secretaría de la\nCivil del Estado, se pagarán conforme lo siguiente:\nI.- Los derechos de legalización y ratificación de firmas, otros capítulos de la presente Ley, así como publicaciones en\nA).- Legalización de firmas de documentos expedidos por servidores públicos estatales y notarios públicos, Recaudación de Rentas del Estado............ $ 156.69\nB).- Expedición de copias certificadas del Periódico Oficial del Estado, por cada hoja................... $ 63.84\nC).- Apostillamiento de documentos expedidos por servidores públicos estatales y notarios públicos...... $ 1,053.90\nD).- Copias certificadas de declaraciones de pago de impuestos que obren en las Recaudaciones de Rentas del\nEstado, por cada hoja....................... $ 301.92\nE).- Certificaciones de no adeudos fiscales que obren en las Recaudaciones de Rentas del Estado, por cada hoja........................................ $ 452.84\nF).- Certificaciones que realicen o certificados que expidan cualquier dependencia, entidad paraestatal o unidad administrativa, del Poder Ejecutivo, del Poder\nLegislativo, Poder Judicial y de los organismos constitucionalmente autónomos, exceptuando las autoridades de trabajo y las que en forma específica se señalan en este artículo, por cada hoja........................................ $ 123.53\nG).- Expedición de copias y certificaciones de documentos judiciales, por cada certificación....... $ 103.22\nH).- Expedición de constancia de antecedentes\nPenales..................................... $ 272.91\nPor la expedición subsecuente a la primera constancia, se cobrará el 50% de su costo; siempre y cuando se solicite en un mismo acto. obligados al pago del mismo, con independencia de lo que establezcan otras Leyes.\nI).- Expedición de duplicado de cédula de registro profesional para ejercer en el\nEstado...................................... $ 574.78\nJ).- Por expedición de copias certificadas o testimonios de por hoja................................... $ 156.69\nK).- Certificaciones que realice o certificados que expida la\nJunta de Urbanización del Estado, por cada hoja...................................... $ 275.29\nL).- Expedición de copias y certificaciones de documentos judiciales generados en medios audiovisuales, del Nuevo\nSistema de Justicia Penal del Estado de Baja California, por cada certificación...................... $ 118.65\nM).- Por publicaciones en el Boletín Judicial del Estado, las siguientes tarifas:\n1.- Por una cuartilla....................... $ 593.23\n2.- Por media cuartilla..................... $ 404.87\n3.- Por un cuarto de cuartilla.............. $ 379.19\nN).- Por el estudio y análisis de la solicitud anual para el\nListado de Padrón de Peritos del Consejo de la de......................................... $ 2,224.60\nÑ).- Certificación de copias digitales de las actuaciones\nJudicial, las siguientes tarifas:\n1.- De 1 hasta 100 hojas......................... $ 98.77\nPor hoja adicional............................ $ 3.00\nII.- Los derechos de estudio de cumplimiento y revaluación de estudio, pagarán las siguientes\nA).- Estudio de cumplimiento, para análisis Jurídico y operación de casas de empeño................ $12,329.00\nB).- Revaluación de estudio de cumplimiento...... $ 6,164.53\nC).- Modificación y reposición de Estudio de cumplimiento................................. $ 2,465.80\nIII.- Por expedición de actas certificadas de constancias que obran en el Archivo de la Dirección del Registro Civil del Estado, rectificación de actas y otros servicios, se cobrarán conforme a la siguiente\nA).- Matrimonios y defunciones................... $ 238.08\nB).- Nacimientos................................. $ 238.08\nC).- Divorcios................................... $ 238.08\nD).- Adopciones y reconocimiento de hijos........ $ 238.08\nE).- Análisis de documentos para rectificación de actas, aun cuando no proceda lo solicitado............. $ 301.92\nF).- Expedición de certificados de inexistencia de actas del estado civil en el Estado.................... $ 464.44\nG).- Expedición de actas del estado civil que obran en las\nMexicana.................................... $ 453.05\nH).- Rectificación de actas del estado civil..... $ 1,448.90\nI).- Otras certificaciones....................... $ 238.08\nJ).- Copia certificada excedente que forme parte de una misma acta........................................ $ 79.36\nK).- Copia certificada de expediente existente en registro civil del Estado, por hoja........................................ $ 79.36\nL).- Trámite de cancelación de acta............... $ 780.71\nM).- Por la entrega a los Municipios de formatos para inscripción de actos del estado civil de las personas, por millar.................................. $ 4,256.00\nN).- Por la expedición de copia simple de las actas señaladas en los incisos A), B), C), D)................ $ 76.32 en los incisos A) a D) se cobrará el 50% de su costo; siempre y cuando se solicite en un mismo acto.\nIV.- Los derechos por los servicios que se prestan por la solicitud de inserciones en el Periódico Oficial del Gobierno del Estado se cobrarán conforme a las siguientes\nA).- Publicación a Organismos Descentralizados, Desconcentrados y Autónomos Federales, Estatales y\nMunicipales, así como a Dependencias Federales y\nMunicipios, por plana........................ $ 3,906.89\nNo se estará obligado al pago de dicha cuota, tratándose de las publicaciones de Acuerdos de Cabildo, Leyes de Ingresos, Tablas de Valores Catastrales, Presupuestos de Egresos, Reglamentos y Estados Financieros de los Ayuntamientos del\nEstado; excepto cuando se trate de Fe de Erratas a las del Estado.\nB).- Publicación a particulares, por plana........ $ 5,650.50\nV.- Por los servicios que se presten por conducto de la Secretaría de la Honestidad y la Función Pública, se pagarán las siguientes\nA).- Por el estudio y evaluación de factibilidad para valuadores................................... $ 1,438.65\nB).- Por el estudio y evaluación de factibilidad para refrendo anual de valuadores................ $ 1,106.66\nC).- Por la expedición de credenciales de valuadores.................................. $ 664.00\nD).- Por la actualización de credenciales de valuadores.................................. $ 199.21\nE).- Por la Expedición de Constancias de No\nInhabilitación.............................. $ 123.53\nVI.- Por los servicios que presta la Coordinación de Protección\nCivil del Estado a giros comerciales, industriales, de servicios, los sectores públicos, privados y sociales que se causarán conforme a las siguientes\nA).- Revisión de programas internos de protección civil:\n1. Revisión hasta en dos ocasiones del programa interno de protección civil, clasificados en el artículo 74, fracción I, de la Ley de Protección Civil y Gestión\nIntegral de Riesgos....................... $ 3,602.30\n2. Revisión hasta en dos ocasiones del programa interno de protección civil, clasificados en el artículo 74, fracción II, de la Ley de Protección Civil y Gestión\nIntegral de Riesgos....................... $ 6,981.20\n3. Revisión hasta en dos ocasiones del programa Interno de protección civil, clasificados en el artículo 74, fracción III, de la Ley de Protección Civil y Gestión\nIntegral de Riesgos........................ $ 5,403.45\n4. Revisión hasta en dos ocasiones del programa interno de protección civil, clasificados en el artículo 74, fracción IV, excepto los considerados en el artículo\n80 de la Ley de Protección Civil y Gestión Integral de\nRiesgos.................................... $ 5,403.45\n5. Revisión hasta en dos ocasiones del programa interno de protección civil, los no clasificados en el artículo 74, de la Ley de Protección Civil y Gestión aplicable................................. $ 5,403.45\nB).- Revisión hasta en dos ocasiones del Programa Interno de\nProtección Civil conforme al artículo 80 de la Ley de\nProtección Civil y Gestión Integral de Riesgos y/o emisión instalaciones abiertas, por cada uno:\n1. Lugares que cuenten con aforo o capacidad mayor a 1,000 hasta 2,000 personas....................... $ 5,806.91\n2. Lugares que cuenten con aforo o capacidad mayor a 2,000 hasta 3,000 personas....................... $ 8,710.36\n3. Lugares que cuenten con aforo o capacidad mayor a 3,000 hasta 4,000 personas....................... $ 11,613.83\n4. Lugares que cuenten con aforo o capacidad mayor a 4,000 hasta 10,000 personas....................... $ 14,517.28\n5. Lugares que cuenten con aforo o capacidad mayor a 10,000 personas o inmuebles públicos de afluencia masiva con construcción mayor a 3,000 metros cuadrados................................... $ 18,872.47\nC).- Revisión hasta en dos ocasiones del Programa Interno de\nProtección Civil conforme al artículo 80 de la Ley de\nProtección Civil y Gestión Integral de Riesgos y/o emisión instalaciones cerradas, por cada uno:\n1. Lugares que cuenten con aforo o capacidad mayor a\n500 hasta 1,000 personas................. $ 4,355.19\n2. Lugares que cuenten con aforo o capacidad mayor a\n1,000 hasta 2,000 personas.............. $ 5,806.91\n3. Lugares que cuenten con aforo o capacidad mayor a\n2,000 hasta 3,000 personas.............. $ 8,710.36\n4. Lugares que cuenten con aforo o capacidad mayor a\n3,000 hasta 4,000 personas.............. $ 11,613.83\n5. Lugares que cuenten con aforo o capacidad mayor a\n4,000 hasta 10,000 personas............. $ 14,517.28\n6. Lugares que cuenten con aforo o capacidad mayor a\n10,000 personas o inmuebles públicos de afluencia masiva con construcción mayor a 3,000 metros cuadrados............................... $ 18,872.47\nSi el inmueble en el que se realizará el evento cuenta con programa interno de protección civil debidamente aprobado por la Coordinación Estatal de Protección Civil, se le otorgará un descuento del 70% del costo de la anuencia.\nD).- Revisión de Simulacros....................... $ 4,328.35\nE).- Agentes consultores capacitadores:\n1.- Por el estudio y evaluación de factibilidad para desempeñarse como agente consultor capacitador.................................. $ 4,355.19\n2.- Por el estudio y evaluación de factibilidad para revalidación como agente consultor capacitador.................................. $ 2,177.59\nCAPÍTULO VIII\nSERVICIOS DE LA SECRETARÍA DE INFRAESTRUCTURA, DESARROLLO URBANO Y\nREORDENACIÓN TERRITORIAL.\nARTÍCULO 19.- Por los servicios que presta la Secretaría de\nInfraestructura, Desarrollo Urbano y Reordenación Territorial, se cubrirán las siguientes\nI.- POR ANÁLISIS DE FACTIBILIDAD Y CONGRUENCIA DE ACCIONES DE\nPROGRAMAS DE DESARROLLO URBANO, O QUE SE UBIQUEN DONDE NO\nEXISTAN ESTOS; Y DE ESTUDIOS URBANOS DE MODIFICACIÓN DE PLANES\nGENERALES.\nA).- Por análisis y emisión de dictamen de terrenos ubicados hasta 5 kilómetros fuera de los centros de población, se pagará por la superficie total del predio estudiado, en la forma siguiente:\n1.- En terrenos de hasta 5 hectáreas......... $ 5,305.60\n2.- Por cada mil metros cuadrados que excedan de 5 hectáreas............................... $ 54.95\n3.- A la cuota máxima del inciso anterior se le acumulará por cada kilómetro en zonas ubicadas más allá de 5 kilómetros fuera de los centros de población............................... $ 73.27\nLos proyectos de fraccionamientos para ser realizados por objetivo social en los términos del Capítulo Octavo del\nTítulo Séptimo de la Ley de Desarrollo Urbano del Estado, pagarán el cincuenta por ciento de esta cuota.\nB).- Por análisis y emisión de dictamen de los estudios y/o establezcan directrices generales se pagará por el predio (hasta dos veces), en la forma siguiente:\n1.- Estudios de predios de hasta 10 hectáreas............................... $ 35,000.00\n2.- Por cada hectárea que excedan de 10 hectáreas.............................. $ 54.95\n3.- A la cuota máxima del inciso anterior se le allá de 5 kilómetros fuera de los centros de población............................... $ 73.27\n4.- Por cada análisis adicional, después de la segunda revisión............................ $ 15,000.00 desarrollo urbano y/o establezcan directrices generales urbanización municipales y/o estatales no pagarán esta cuota.\nII.- POR LINEAMIENTOS VIALES PARA ESTUDIOS Y PROYECTOS DE ACCIONES\nDE URBANIZACIÓN.\nPor la validación de los proyectos viales para la integración a la infraestructura, obras o proyectos de vialidades de competencia estatal, incluyendo la supervisión de la obra, el\n12% sobre el costo de la misma.\nIII.- POR EQUIPAMIENTO ESCOLAR.\nLa cuota correspondiente se causa por cada lote resultante del fraccionamiento, división de copropiedad, relotificación o subdivisión de predios dedicados a uso habitacional, así como por cada departamento, casa o vivienda resultante de la constitución del régimen de propiedad en condominio de inmuebles habitacionales, de acuerdo con la clasificación establecida en esta Ley y en el Reglamento de escolar, anexos e instalaciones complementarias, conforme a\nInfraestructura, Desarrollo Urbano y Reordenación\nTerritorial:\nA).- Fraccionamientos con oferta de suelo y vivienda o interés social…................................... 0.40%\nB).- Fraccionamientos con oferta de suelo y vivienda o tipo popular...................................... 0.60%\nC).- Fraccionamientos o conjuntos habitacionales y edificios multifamiliares de nivel medio.................... 0.80%\nD).- Fraccionamientos, conjuntos habitacionales y edificios multifamiliares de nivel residencial.............. 1.00%\nE).- Fraccionamientos que se realicen por objetivo social en\nLey de Desarrollo Urbano del Estado............... 0.40%\nEl pago por Equipamiento Escolar derivado de la modificación, división de copropiedad, relotificación o subdivisión de lotes en fraccionamientos autorizados, se hará por cada lote que exceda el número original de unidades, de acuerdo con la clasificación determinada por la Secretaría de\nInfraestructura, Desarrollo Urbano y Reordenación Territorial, apoyada en la Tabla de Valores Catastrales Unitarios del\nMunicipio a que corresponda.\nEn el caso de conjuntos habitacionales o edificios multifamiliares para constituirse el régimen de propiedad en condominios, construidos en lotes de fraccionamientos autorizados, el pago se hará por cada vivienda que exceda el número original de lotes, conforme al tipo de unidad que resulte del avalúo respectivo.\nEn los fraccionamientos en los que sólo se ofrezca el suelo urbanizado para uso habitacional, la cuota por Equipamiento\nInfraestructura, Desarrollo Urbano y Reordenación Territorial, vigor.\nLa donación para equipamiento a que se refiere el artículo 175 de la Ley de Desarrollo Urbano del Estado de Baja California, Estado correspondiente, en aquellos casos en los que las características de ubicación y superficie no sean idóneas, ello y se autorice por la Secretaría de Hacienda. En este caso\nEstatal de Avalúos.\nEl pago de los derechos a que se refieren las fracciones I, II y III, lo hará el interesado previa notificación de la\nReordenación Territorial, una vez determinado el costo correspondiente.\nEn el caso de no presentar el comprobante de haber enterado en la Recaudación de Rentas del Estado el monto total de los derechos en un plazo de 20 días hábiles a partir de la fecha de su notificación, ésta quedará sin efecto y se suspenderá el trámite correspondiente.\nIV.- POR SERVICIOS DERIVADOS DEL SISTEMA ESTATAL DE INFORMACIÓN\nGEOGRÁFICA.\nA).- Material Cartográfico Automatizado por Computadora:\n1.- Impresión de planos a color (original ploteado), por cm²:\na).- Planimétrico......................... $ 0.49\nb).- Topográfico (Planimetría y\nAltimetría).......................... $ 0.58\nc).- Topográfico con información adicional (por cada nivel de información)................ $ 0.02\n2.- Impresiones de planos en tinta negra (plano original ploteado), por cm²:\na).- Planimétrico......................... $ 0.03\nb).- Topográfico (Planimetría y Altimetría).\n..................................... $ 0.56\nc).- Topográfico con información adicional (por cada nivel de información)......................... $ 0.02\n3.- Grabación en medio magnético en formato autocad, de planos base de las ciudades y/o localidades:\na).- Hasta un Km.\nPlanimétrico......................... $1,056.81\nTopográfico (Planimetría y\nAltimetría)......................... $1,596.79\nTopográfico con información adicional (por cada nivel de información)......................... $ 539.98\nb).- Por cada kilómetro cuadrado subsecuente o fracción:\nPlanimétrico......................... $ 63.84\nTopográfico.......................... $ 98.70\nTopográfico con información adicional (por cada nivel de información)........................ $ 11.57\n4.- Grabación en medio magnético en formato autocad de planos base de los Municipios y/o el Estado:\na).- Estado............................. $ 8,088.81\nb).- Municipio.......................... $ 5,051.88\n5.- Grabación en medio magnético de imagen de planos de fraccionamientos, por plano............ $ 129.43\n6.- Impresión de planos de fraccionamientos, por cada metro de longitud de papel bond........ $ 323.60\nB).- Vértices Geodésicos:\n1.- Información por vértice (ubicación, coordenadas, descripción)..............................$ 209.02\n2.- El establecimiento de vértices geodésicos en el\nSatélite GPS, estará condicionado al presupuesto que al efecto realice la Secretaría de Infraestructura, Desarrollo Urbano y Reordenación Territorial, características fisiográficas del sitio.\n3.- Liga al Sistema Estatal de Coordenadas, mediante equipo GPS, hasta 10 kilómetros fuera de los límites del centro de población.\na).- Por los primeros dos vértices de desarrollo ligados en:\nMexicali........................... $ 4,250.56\nTijuana............................ $ 9,552.07\nEnsenada........................... $10,614.73\nTecate............................ $ 8,489.56\nPlayas de Rosarito................. $ 9,552.07\nSan Quintín........................ $10,614.73\nSan Felipe......................... $ 4,250.56\nb).- Por cada vértice extra ligado (hasta un máximo de 3):\nMexicali........................... $ 1,056.81\nTijuana............................ $ 2,125.20\nEnsenada........................... $ 2,125.20\nTecate............................. $ 2,125.20\nPlayas de Rosarito................. $ 2,125.20\nSan Quintín........................ $ 2,125.20\nSan Felipe......................... $ 1,056.81\nV.- POR REVISIÓN DE PROYECTOS DE ALCANTARILLADO PLUVIAL Y RASANTES\nDE VÍAS PÚBLICAS:\nA).- Por la revisión de proyecto de alcantarillado pluvial y rasantes de vías públicas en predios de hasta 5 hectáreas.................................... $ 5,602.94\nPor cada hectárea o fracción adicional....... $ 1,120.55\nB).- Por la verificación en campo de la ejecución de obra de alcantarillado pluvial, conforme al proyecto autorizado, por la Secretaría de Infraestructura, Desarrollo Urbano y\nReordenación Territorial, el......................... 2%\nVI.- POR EL ALTA EN EL PADRÓN DE CONTRATISTAS Y PROVEEDORES CON\nVIGENCIA ANUAL, A QUIEN LO SOLICITE:\nA).- Por el alta o su renovación anual............ $ 836.33\nVII.- POR EXPEDICIÓN DE DOCUMENTOS:\nA).- Certificación de copias de planos............ $ 574.78\nB).- Constancias en relación con los desarrollos urbanos...................................... $ 574.78\nC).- Constancias y copias certificadas de documentos, por la primera hoja................................. $ 156.69\nD).- Por hoja adicional........................... $ 40.60\nE).- Copias simples de documentos, por hoja....... $ 23.16\nF).- Catálogo de costos unitarios de edificación o\nInfraestructura.............................. $ 807.90\nVIII.- POR EL MANTENIMIENTO, OPERACIÓN Y CONSERVACIÓN DEL TRAMO\nCARRETERO LA ROSITA-RUMOROSA:\nPor el mantenimiento, operación y conservación del tramo carretero La Rosita-Rumorosa, se aplicará la tarifa que para tal efecto establezca la concesión correspondiente.\nIX.- OTROS SERVICIOS:\nA).- Por servicio consistente en el mantenimiento superficial de pavimentos asfálticos en caliente, mediante proceso de reciclado de un solo paso, se pagará por M²..... $ 67.10\nLa prestación del servicio incluye el equipo, mano de obra, insumos para el funcionamiento de la maquinaria, sea necesario, tendido y compactado, para la integración de otra capa de carpeta asfáltica nueva de 2.5 centímetros de espesor.\nNo incluye el suministro de concreto asfáltico y control de calidad del mismo, protección vial y traslados dentro de la ciudad, renivelación o retiro de instalaciones hidráulicas y de telefonía, retiro de rampas de concreto, extracción de baches y demás elementos extraños dentro de la vialidad.\nLa prestación del servicio será en los términos que establezca la Secretaría de Infraestructura, Desarrollo\nUrbano y Reordenación Territorial.\nCAPÍTULO IX\nSERVICIOS DE LA SECRETARÍA DE AGRICULTURA Y DESARROLLO RURAL.\nARTÍCULO 20.- Por los servicios que presta la Secretaría de\nAgricultura y Desarrollo Rural, se cubrirán las siguientes\nI.- POR LA CLASIFICACIÓN O CERTIFICACIÓN DE GANADO Y CARNES DE\nBOVINO Y CLASIFICACIÓN DE HUEVO EN EL ESTADO.\nA).- Por clasificación de canales de ganado, por canal............................................ $ 17.75\nB).- Por certificación de calidad de carne en cortes, por kilogramo...................................... $ 0.30\nC).- Por la clasificación de huevo para plato, por kilogramo...................................... $ 0.10\nII.- OTROS SERVICIOS.\nA).- Por la expedición de credencial de patente ganadera...................................... $ 557.64\nB).- Por la expedición de duplicado de credencial de patente\nGanadera...................................... $ 375.26\nC).- Por la expedición de duplicado de patente ganadera y comerciante................................... $ 376.97\nD).- Por la expedición de duplicado de Certificado de Registro\nGanadero, Marca de Herrar y Señal de Sangre... $ 691.24\nE).- Por el servicio de báscula.................... $ 76.62\nF).- Por servicios de laboratorio:\n1.- Laboratorios de agua y suelo (ANÁLISIS DE FERTILIDAD Y\nSALINIDAD)................................ $ 2,363.48\n2.- Laboratorio de microbiología (SALMONELLA, E\nCOLI0157:H7, EHEC, MESOFILICOS, COLIFORMES EN CARNE)\n......................................... $ 4,136.08\n3.- Laboratorio de microbiología (SALMONELLA, MESOFILICOS,\nCOLIFORMES Y HONGOS Y LEVADURAS EN LECHE)\n......................................... $ 4,136.08\n4.- Laboratorio de biología molecular (SALMONELLA, E\nCOLI0157:H7, EHEC, MESOFILICOS, COLIFORMES, LISTERIA spp,\nMONOCYTOGENES, HONGOS Y LEVADURAS EN HORTALIZAS).......\n......................................... $ 9,453.91\n5.- Laboratorio de microbiología\n5.1.- Salmonella........................ $ 827.22\n5.2.- Coliformes........................ $ 590.87\n5.3.- Coliformes totales................ $ 590.87\n5.4.- E. coli 0157:H7.................... $ 827.22\n5.5.- Mesofílicos....................... $ 590.87\n5.6.- Hongos y levaduras................ $ 590.87\n5.7.- Estafilococo...................... $ 590.87\n5.8.- Listeria.......................... $ 827.22\n6.- Laboratorios en prueba\n6.1.- Salinidad.......................... $ 822.94\n6.2.- Fertilidad........................ $ 822.94\n6.3.- Agua para riego.................... $ 1,097.25\n6.4.- Calidad de granos de trigo......... $ 329.18\n6.5.- Laboratorio de microbiología\n(SALMONELLA, MESOFILICOS Y COLIFORMES)..$ 1,316.70\nCAPÍTULO X\nSERVICIOS DEL INSTITUTO PARA EL DESARROLLO INMOBILIARIO Y\nDE LA VIVIENDA PARA EL ESTADO.\nARTÍCULO 21.- Por los servicios que presta el Instituto para el\nDesarrollo Inmobiliario y de la Vivienda para el Estado, se cubrirán las siguientes\nI.- POR TRABAJOS TÉCNICOS.\nA).- Para los municipios de Ensenada, Mexicali, San Quintín y\nSan Felipe, se cobrará por metro cuadrado regularizable, cuando se trate de predios ocupados en terrenos cuyo valor catastral sea de $ 1.00 a $325.00 por m2............................................... $ 18.83\nB).- Para los municipios de Ensenada, Mexicali, San Quintín y\nSan Felipe, se cobrará por metro cuadrado regularizable catastral sea de $ 1.00 a $325.00 por m2......... $ 22.60\nC).- Para los municipios de Ensenada, Mexicali, San Quintín y\nSan Felipe, se cobrará por metro cuadrado regularizable sea de $ 325.01 o más por m2.................... $ 24.50\nD).- Para los municipios de Ensenada, Mexicali, San Quintín y\nSan Felipe, se cobrará por metro cuadrado regularizable de $ 325.01 o más por m2........................ $ 28.26\nE).- Para los municipios de Tijuana, Tecate y Playas de Rosarito se cobrará por metro cuadrado regularizable, cuando se sea de $ 1.00 a $ 325.00 por m2.....................$ 24.50\nF).- Para los municipios de Tijuana, Tecate y Playas de Rosarito de predios baldíos en terrenos cuyo valor catastral sea de\n$ 1.00 a $ 325.00 por m2......................... $ 28.26\nG).- Para los municipios de Tijuana, Tecate y Playas de Rosarito se cobrará por metro cuadrado regularizable cuando se trate de predios ocupados cuyo valor catastral sea de $ 325.01 o más por m2...................................... $ 32.04\nH).- Para los municipios de Tijuana, Tecate y Playas de Rosarito se cobrará por metro cuadrado regularizable cuando se trate de predios baldíos cuyo valor catastral sea de $ 325.01 o más por m2...................................... $ 37.68\nII.- POR EXPEDICIÓN DE DOCUMENTOS.\nA).- Por expedición de títulos de propiedad, cuando se trate de predios ocupados en terrenos cuyo valor catastral sea de $ 1.00 a $ 325.00 por m2.................... $ 1,978.58\nB).- Por expedición de títulos de propiedad, a personas en situación de pobreza mayores de 60 años, personas viudas en situación de pobreza mayores de 50 años, personas con discapacidad, jubilados y pensionados, definidos de conformidad con el artículo 172 de la Ley de Hacienda del\nEstado de Baja California, siempre que sus ingresos no excedan de 5 veces el valor diario de la Unidad de Medida y Actualización vigente....................... $ 500.00\nC).- Por expedición de título de propiedad, cuando se trate de predios baldíos en terrenos cuyo valor catastral sea de $\n1.00 a $ 325.00 por m2......................... $ 2,543.79\nD).- Por expedición de título de propiedad, cuando se trate de\n$ 325.01 o más por m2.......................... $ 3,297.64\nE).- Por expedición de título de propiedad, cuando se trate de predios baldíos en terrenos cuyo valor catastral sea de $\n325.01 o más por m2......................... $ 4,616.69\nF).- Cesión de Derechos........................... $ 753.74\nG).- Carta Finiquito o Constancia de Regularización $ 376.88\nH).- Integración de expediente para escrituración para trámites en las notarías..................... $ 3,203.61\nCAPÍTULO XI\nSERVICIOS DE LA SECRETARÍA DE SEGURIDAD CIUDADANA.\nARTÍCULO 22.- Por los servicios que presta la Secretaría de\nSeguridad Ciudadana, se cubrirán las siguientes\nI.- PERSONA FÍSICA O MORAL CON ESTABLECIMIENTO.\nA).- Por el estudio y evaluación de factibilidad para prestar servicios de seguridad privada............... $22,012.24\nB).- Por la revaluación anual..................... $17,609.08\nC).- Por el alta en el padrón de seguridad privada (por agente)...................................... $ 219.80\nD).- Por ampliación del tipo o lugares para la prestación de este servicio................................ $ 13,207.11\nE).- Por el estudio y evaluación de factibilidad por cambio de:\n1.- Domicilio............................... $ 719.68\n2.- Denominación o razón social y nombre comercial............................... $ 719.68\nF).- Por el otorgamiento de código QR de identificación vehicular de seguridad privada............... $ 590.87\nII.- PRESTADOR INDIVIDUAL.\nA).- Por el estudio y evaluación de factibilidad para prestar servicios de seguridad privada............... $ 4,401.97\nB).- Por la revaluación anual..................... $ 3,301.78\nC).- Por la expedición de credenciales de identificación personal..................................... $ 660.59\nD).- Por el alta en el padrón de seguridad privada. $ 219.80\nE).- Por ampliación del tipo o lugares para la prestación de este servicio................................ $ 2,201.58\nF).- Por el estudio y evaluación de factibilidad por cambio de:\n1.- Domicilio............................... $ 719.68\nG).- Por la capacitación otorgada para brindar servicios de alcohólicas en envase abierto................ $ 7,680.75\nIII.- PROTECCIÓN PERSONAL A PARTICULARES.\nUNIDAD DE MEDIDA Y\nACTUALIZACIÓN VIGENTE\nA).- Por servicio de escolta, por día de servicio, por Agente será......................................... 15.6 veces condiciones que establezca el contrato respectivo, pudiendo prestación del servicio en tiempos y horas extraordinarias.\nCAPÍTULO XII\nREGISTRO DE ESTABLECIMIENTOS.\nARTÍCULO 23.- Independientemente de la obligación de hacerlo conforme a otras Leyes o Reglamentos, todas las personas físicas y morales que cuenten con establecimientos comerciales, industriales, agropecuarias, deberán registrarlos o inscribirlos dentro de los diez días siguientes a la fecha en que inicien operaciones, en las oficinas recaudadoras de Rentas del Estado, del lugar en donde realicen parcial o totalmente sus actividades, proporcionando los datos que consignan las formas aprobadas por la Secretaría de\nHacienda, aun cuando conforme a las Leyes respectivas no sean objeto, sujeto, no causen o se encuentren exentos del pago de contribuciones.\nCAPÍTULO XIII\nSERVICIOS DE LA DIRECCIÓN DEL ARCHIVO GENERAL DE NOTARIAS.\nARTÍCULO 24.- Por los servicios que presta la Dirección del Archivo\nGeneral de Notarías, deberán cubrirse las siguientes\na).- Por informes de disposiciones testamentarias..... $ 372.50\nb).- Por revisión y resguardo de aviso de otorgamiento de disposición testamentaria........................ $ 372.50\nc).- Por consulta a los índices de los libros del protocolo en\nNotarías......................................... $ 341.29\nd).- Por la expedición de constancias................. $ 307.17\ne).- Por la expedición de testimonios y copias certificadas, de 1 a\n4 páginas....................................... $ 478.81\nAdicional de 5 en adelante, por página........... $ 31.90\nf).- Por autorización de traslado de Protocolo Notarial resguardado origen........................................... $ 549.35\ng).- Por expedición de copias simples, por página..... $ 15.99\nh).- Por apertura de expediente de práctica notarial... $ 709.24\ni).- Por análisis y estudio de solicitud, y el trámite para la celebración de examen de aspirante al ejercicio del notariado......................................... $ 4,787.27\nj).- Por análisis y estudio de solicitud, y el trámite para la celebración de examen para lograr la titularidad de una notaría........................................... $ 7,978.85\nk).- Por apertura de expediente de aspirante al ejercicio de la función notarial.................................. $ 7,978.85\nl).- Por apertura de expediente de notario adscrito... $ 22,340.82\nm).- Por apertura de expediente como notario titular.. $ 25,532.31\nn).- Por la recepción y resguardo de convenios de asociación y de suplencia........................................ $ 19,149.24 ñ).- Expedición de constancia de patente notarial, titular o adscrito.......................................... $ 2,498.12\no).- Por expedición de constancia de terminación de práctica notarial.......................................... $ 723.18\np).- Expedición bianual de credencial de identificación de Notario titular y adscrito............................... $ 4,847.31\nq).- Renovación de credencial de identificación de Notario titular y adscrito.......................................... $ 2,423.66\nr).- Reposición de credencial de identificación vigente de notario titular y adscrito................................. $ 2,423.66\nLos servicios extraordinarios tendrán un incremento del 100% de su costo regular.\nCAPÍTULO XIV\nSALUD PÚBLICA DEL ESTADO DE BAJA CALIFORNIA.\nARTÍCULO 25.- Por los servicios que prestan la Secretaría de Salud y el Instituto de Salud Pública del Estado de Baja California deberá cubrirse la siguiente\nI.- Por la capacitación otorgada al que realice actividades sanitaria........................................ $ 2,843.67\nCAPÍTULO XV\nSERVICIOS EDUCATIVOS Y PEDAGÓGICOS DE BAJA CALIFORNIA.\nARTÍCULO 26.- Por los servicios que prestan la Secretaría de\nBaja California, deberán cubrirse las siguientes\n1.- Trámite de Registro Profesional Estatal en el nivel licenciatura, especialidad, maestría y doctorado.. $ 1,217.02\n2.- Análisis de solicitud de autorización provisional para ejercer una profesión.................................... $ 468.39\n3.- Expedición de duplicado de registro profesional estatal.......................................... $ 624.54\n4.- Análisis de solicitud por parte de asociaciones de profesionistas................................... $ 7,806.75\n5.- Constancia de antecedentes de profesionistas..... $ 156.17\n6.- Estudio, trámite y resolución de solicitud de autorización a los particulares para impartir educación inicial........................................... $ 29,228.49\n7.- Estudio, trámite y resolución de solicitud, de reconocimiento de validez oficial de estudios a los particulares para impartir educación de formación para el trabajo......................................... $ 29,228.49\n8.- Estudio, trámite y resolución de solicitud, de reconocimiento de validez oficial de estudios de Técnico Superior\nUniversitario, Profesional Asociado, Licenciatura, Especialidad, Maestría y Doctorado................ $ 29,228.49\n9.- Estudio, trámite y resolución de solicitud, de autorización a los particulares para impartir educación preescolar........................................ $ 29,228.49\n10.- Estudio, trámite y resolución de solicitud, de Autorización a particulares para impartir educación primaria......................................... $ 29,228.49\n11.- Estudio, trámite y resolución de solicitud, de autorización a particulares para impartir educación secundaria....................................... $ 29,228.49\n12.- Estudio, trámite y resolución de solicitud, por cambio de particulares..................................... $ 7,307.09\n13.- Estudio, trámite y resolución de solicitud, de cambio de de estudios....................................... $ 4,384.27\n14.- Estudio, trámite y resolución de solicitud, de cambio de representante legal del plantel particular incorporado....................................... $ 1,501.31\n15.- Estudio, trámite y resolución de solicitud, de cambio de director del plantel particular incorporado...... $ 1,501.31\n16.- Estudio, trámite y resolución de solicitud, por cada cambio de docente en escuelas particulares incorporadas...................................... $ 1,501.31\n17.- Estudio, trámite y resolución de solicitud, de cambio de nombre del plantel particular incorporado\n.................................................. $ 1,501.31\n18.- Expedición de duplicados de Certificados de terminación de estudios de educación primaria y secundaria........................................ $ 61.99\n19.- Expedición de revalidaciones de Estudios de Educación\nBásica............................................ $ 61.99\n20.- Equivalencia de Educación Media Superior.......... $ 388.45\n21.- Equivalencia de Educación Superior................ $ 388.45\n22.- Equivalencia de Educación Normal.................. $ 388.45\n23.- Revalidación de Educación Media Superior.......... $ 388.45\n24.- Revalidación de Educación Superior................ $ 1,163.28\n25.- Revalidación de Educación Normal.................. $ 1,163.28\n26.- Dictamen Técnico de Nivel Superior.................$ 1,163.28\n27.- Dictamen Técnico de Educación Normal.............. $ 1,163.28\n28.- Registro a preparatoria abierta (REGISTRO)........ $ 361.59\n29.- Expedición de Credencial (CREDENCIALIZACIÓN)...... $ 154.97\n30.- Expedición de Certificado de terminación completo, Parcial o Duplicado (CERTIFICACIÓN)............... $ 388.79\n31.- Expedición de Constancia de Estudios (CONSTANCIA DE ESTUDIO)\n.................................................. $ 109.90\n32.- Expedición de Historial Académico (HISTORIAL ACADÉMICO)\n.................................................. $ 55.54\n33.- Aplicación de exámenes en Centros de Atención Particulares y\nSociales (APLICACIÓN Y CALIFICACIÓN)............. $ 723.18\n34.- Plática Informativa en Centros de Atención Particulares y\nSociales (INDUCCIÓN PROPEDÉUTICA.................. $ 665.32\n35.- Trámite y envío de documentos fuera del Estado.... $ 665.32\n36.- Registro por Centro de Atención................... $ 5,551.81\n37.- Solicitud de Examen............................... $ 93.34\n38.- Análisis y resolución de modificación a la denominación del registro de la asociación de profesionistas....... $ 1,761.88\n39.- Análisis y resolución de modificación a los estatutos de las asociaciones de profesionistas registradas....... $ 1,637.76\n40.- Por asesoría académica por asignatura a alumnos de\nPreparatoria Abierta.............................. $ 224.53\n41.- Por cambio de plan y programa de estudios con reconocimiento de validez oficial de estudios.... $ 13,957.47\n42.- Por cambios al Reglamento Institucional de Instituciones\nParticulares...................................... $ 2,790.74\n43.- Por expedición de documentos de control escolar de\nEducación básica: Kardex, informe de calificaciones parciales, evaluación histórica, y constancia de estudios.......................................... $ 18.64\n44.- Cotejo de documentos académicos................... $ 8.69\n45.- Certificado de terminación de estudios............ $ 209.00\n46.- Acta de examen profesional........................ $ 261.25\n47.- Título Profesional................................ $ 470.25\n48.- Certificación de documentos académicos (por hoja)..$ 8.28\nCAPÍTULO XVI\nSERVICIOS DE LA COMISIÓN ESTATAL DE ENERGÍA\nARTÍCULO 27.- Por los servicios que presta la Comisión Estatal de\nEnergía, deberán cubrirse las siguientes\nI. Emisión de Dictámenes Técnicos de Congruencia:\na) Capacidad de la central eléctrica en megawatts(MW).\n1.- 0.5 <Cap MW ≤ 10............................ $ 10,450.00\nPor cada MW Adicional............................ $ 1,045.00\nCAPÍTULO XVII\nCOOPERACIÓN PARA OBRAS Y SERVICIOS PÚBLICOS.\nCAPÍTULO XVIII\nOBRAS DE URBANIZACIÓN.\nTÍTULO QUINTO\nCONTRIBUCIONES CAUSADAS EN EJERCICIOS ANTERIORES.\nCAPÍTULO ÚNICO\nARTÍCULO 28.- Las contribuciones causadas en ejercicios anteriores, situaciones jurídicas previstas en las Leyes fiscales.\nTÍTULO SEXTO\nCAPÍTULO I\nEXPLOTACIÓN DE BIENES DEL ESTADO.\nARTÍCULO 29.- Los productos derivados de la explotación de bienes del Estado, provenientes de las ventas o arrendamientos de bienes muebles e inmuebles u otros actos sobre los mismos, se originarán en los contratos que se celebren o en las concesiones que se otorguen al efecto por el Ejecutivo del Estado, en uso de sus atribuciones legales y sobre las bases que en los mismos establezcan.\nCAPÍTULO II\nPERIÓDICO OFICIAL, VENTA DE FORMAS Y OTROS PRODUCTOS.\nARTÍCULO 30.- Los productos del Periódico Oficial del Gobierno del\nEstado, venta de formas, otros productos, así como los relativos al\nI.- SUSCRIPCIONES Y EJEMPLARES:\nA).- Suscripción anual........................... $ 4,193.67\nB).- Ejemplar de la semana....................... $ 70.68\nC).- Ejemplar atrasado del año en curso.......... $ 83.89\nD).- Ejemplar de años anteriores.................. $ 105.43\nE).- Ejemplar de edición especial: Leyes, Reglamentos, etc.......................................... $ 150.96\nF).- Ejemplar de calendario oficial............... $ 119.81\nII.- FORMAS OFICIALES Y COPIAS:\nA).- Por cada forma oficial para efectuar declaraciones de trámite administrativo....................... $ 7.60\nB).- Por copia fotostática simple, sin certificar $ 1.40\nIII.- OTROS PRODUCTOS:\nA).- Pago por derecho de uso de imagen en publicaciones\n(impresas, digitales o cualquier otro medio). $ 263.59\nB).- Por reproducción de fotografías en papel fotográfico:\n1.- En papel fotográfico de 5 x 7........... $ 167.72\n2.- En papel fotográfico de 8 x 10.......... $ 264.35\n3.- En papel fotográfico de 11 X 14..........$ 299.53\n4.- En papel fotográfico de 16 X 20..........$ 371.43\nC).- Por digitalización de imágenes (de originales hasta 8 ½” por 14” más derecho de imagen).............. $ 50.32\nAdministración de Justicia, de acuerdo a las siguientes\nA).- Expedición de copias simples de documentos que obren en\nJudicial del Estado, por cada hoja......... $ 3.00\nB).- Expedición de copias simples de audio y video de de Baja California, por disco compacto...... $ 14.84\nC).- Por el costo de diversos servicios proporcionados por el\nServicio Médico Forense (SEMEFO) de Baja California las siguientes tarifas:\n1.- Visitas guiadas con práctica de necropsia, por grupo o institución que lo solicite.......... $ 4,449.19\nD).- Por suscripción anual en el Boletín Judicial del Estado en su modalidad electrónica................. $ 2,805.20\nCAPÍTULO III\nALMACENAMIENTO Y GUARDA DE BIENES EN\nESTABLECIMIENTOS DEPENDIENTES DEL ESTADO.\nARTÍCULO 31.- Los bienes que por cualquier motivo se encuentren depositados, guardados, secuestrados o simplemente internados en almacenes, depósitos, patios o locales dependientes del Gobierno del Estado, causarán por cada metro cuadrado o fracción de superficie que ocupen, diariamente una cuota de....... $ 14.48\nLas cuotas que señala este artículo, deberán pagarse en la oficina recaudadora correspondiente, por períodos vencidos de diez días. pago para el almacenaje o guarda de los bienes, se cobrará el establece el Código Fiscal del Estado.\nCAPÍTULO IV\nDEPENDIENTES DEL ESTADO.\nARTÍCULO 32.- Los productos líquidos de los establecimientos actividades económicas lucrativas, que no correspondan a las funciones de derecho público, se regirán por las bases generales las mismas bases se disponga.\nCAPÍTULO V\nINGRESOS DE ORGANISMOS DESCENTRALIZADOS Y EMPRESAS DE\nPARTICIPACIÓN ESTATAL.\nARTÍCULO 33.- Los ingresos producidos por organismos descentralizados y empresas de participación estatal, se percibirán cuando lo decreten y exhiban, conforme a sus respectivos regímenes interiores, los organismos y empresas que los produzcan.\nCAPÍTULO VI\nINTERESES DE VALORES.\nARTÍCULO 34.- Los capitales impuestos a réditos, así como toda clase de acciones y valores que formen parte de la Hacienda Pública del Estado y los intereses o productos de los mismos, se regirán por los contratos o actos jurídicos de que se deriven, en caso de que incurra en mora en el pago de los créditos, éstos se harán en caso de que no exista convenio al respecto, por vía judicial. En este caso, por acuerdo del Gobernador del Estado, podrá\nDirección competente en el Estado o abogados particulares, cuyos deudor, más el porcentaje que se estipule en el convenio respectivo.\nCAPÍTULO VII\nARTÍCULO 35.- Todos los avalúos que emita la Secretaría de la\nHonestidad y la Función Pública, por conducto de la Comisión\nEstatal de Avalúos, devengarán honorarios que serán a cargo de las pagarán conforme a la siguiente tarifa:\nI.- Práctica de Avalúos.\na).- Dentro del centro de población. $892.57 pesos (como anticipo) más el 3.00 al millar sobre el valor del bien(al término del trámite)\nb).- Fuera del centro de población. $1,116.66 pesos (como anticipo) más el 3.00 al millar sobre el valor del bien(al término del trámite)\nII.- Actualización de Avalúo (hasta un año después de su fecha de término de vigencia).\na).- Dentro del centro de población. $893.34 pesos (como anticipo) más el 1.50 al millar sobre el valor del bien (al término del trámite)\nb).- Fuera del centro de población. $1,116.66 pesos (como anticipo) más el 1.50 al millar sobre el valor del bien (al término del trámite) que se encuentre vigente.\nCuando el monto que resulte de la aplicación del 3.00 y 1.50 al millar sobre el valor del bien sea inferior a $ 1,601.02 pesos, se cobrará esta cantidad como tarifa por el servicio.\nLa comisión practicará los avalúos de bienes muebles e inmuebles, en las operaciones que se celebren sobre dichos bienes; tales avalúos se realizarán en forma gratuita.\nParamunicipales, los honorarios se reducirán al 50% del arancel.\nTratándose de personas pensionadas, jubiladas, con discapacidad o personas mayores de sesenta años que acrediten esta condición con identificación oficial expedida por institución pública, se otorgará exención del 50% del arancel, previo estudio socioeconómico realizado por la dependencia que presta el servicio.\nCAPÍTULO VIII\nARTÍCULO 36.- Otros productos distintos de los señalados por los artículos anteriores.\nTÍTULO SÉPTIMO\nCAPÍTULO I\nARTÍCULO 37.- Cuando se conceda prórroga para el pago de créditos fiscales o para que los mismos sean cubiertos en parcialidades, se causarán recargos sobre el saldo insoluto a la tasa del 1.5% mensual. parcialidades en los plazos convenidos, se pagarán recargos por concepto de indemnización al fisco estatal a la tasa del 2.25% mensual.\nCAPÍTULO II\nDONATIVOS E INDEMNIZACIONES.\nARTÍCULO 38.- Las cantidades que por concepto de donativo e indemnizaciones perciba el Estado, se sujetarán a las disposiciones resoluciones relativas.\nCAPÍTULO III\nHERENCIAS Y LEGADOS A FAVOR DE LA HACIENDA PÚBLICA\nDEL ESTADO.\nARTÍCULO 39.- Los bienes que obtenga la Hacienda Pública del Estado por concepto de herencias y legados, se sujetarán a las disposiciones de los testadores y, en su caso, se harán efectivos de acuerdo con las Leyes respectivas.\nCAPÍTULO IV\nCAPÍTULO V\nCAPÍTULO VI\nCAUCIONES, FIANZAS Y DEPÓSITOS CUYA PÉRDIDA\nSE DECLARE POR RESOLUCIÓN FIRME.\nCAPÍTULO VII\nPARA OBRAS PÚBLICAS.\nCAPÍTULO VIII\nOTORGAMIENTO Y USUFRUCTOS DE CONCESIONES.\nCAPÍTULO IX\nTÍTULO OCTAVO\nPARTICIPACIONES Y APORTACIONES FEDERALES.\nCAPÍTULO ÚNICO.\nARTÍCULO 40.- Las participaciones y aportaciones que correspondan establezcan las Leyes y reglamentos correspondientes o por los convenios que al efecto se celebren.\nTÍTULO NOVENO\nINGRESOS EXTRAORDINARIOS.\nCAPÍTULO ÚNICO.\nARTÍCULO 41.- Los ingresos extraordinarios son:\nI.- Créditos otorgados al Estado.\nII.- Impuestos Extraordinarios.\nIII.- Derechos Extraordinarios por la prestación de servicios.\nIV.- Expropiaciones.\nV.- Aportaciones Extraordinarias de los Entes Públicos.\nVI.- Otros conceptos.\nPRIMERO.- En caso de que durante el presente ejercicio sea modificado el Artículo 10-A de la Ley de Coordinación Fiscal o la terminación del Convenio que en materia de Derechos, el Estado de\nBaja California ha suscrito con el Ejecutivo Federal, el cobro de los Derechos Estatales, que en base al Decreto No. 30 publicado en suspendidos, en tanto no se hayan efectuado las modificaciones legales correspondientes, se cobrarán conforme a las cuotas de que se trate.\nSEGUNDO.- La suspensión del cobro de los derechos a que se refiere el Decreto mencionado en el artículo que antecede, no libera a los particulares de la obligación de cumplir con todos los requisitos que las Leyes Estatales y Municipales establecen respecto de los servicios que dan origen a la causación de los derechos, cuyo cobro se encuentra suspendido.\nTERCERO.- En caso de que durante la vigencia de la presente ley, alguna de las Dependencias señaladas cambiara de denominación o los servicios sean prestados por otra Dependencia por disposición de\nLey o reglamentaria, se entenderán referidos y prestados por la que la sustituya.\nCUARTO.- Los Acuerdos o decretos que el Ejecutivo del Estado emita en los términos de los Artículos 2 y 35 del Código Fiscal del\nEstado, respecto de la causación de las contribuciones a que se refiere esta Ley y demás disposiciones fiscales estatales, se cobrarán de conformidad con dichos Acuerdos o Decretos.\nQUINTO.- Para efectos de esta Ley se considerará:\nFraccionamientos por Objetivo Social: Aquellos Fraccionamientos y mediante la gestión pública a través de los Ayuntamientos, del\nLey de Desarrollo Urbano del Estado de Baja California.\nFraccionamientos o Colonias Populares: Aquéllos cuyas el Reglamento de Fraccionamientos del Estado de Baja California.\nViviendas de Interés Social: Aquéllas que consistan en el suelo y quince la unidad de medida y actualización elevada al año, vigente en el Estado de Baja California.\nViviendas Populares: Aquéllas que consistan en el suelo y las construcciones adheridas a él y cuyo valor, determinado mediante autorizado, con antigüedad máxima de un año, no exceda de la suma actualización elevada al año, vigente en el Estado de Baja\nCalifornia.\nViviendas de Nivel Medio: Aquéllas que consistan en el suelo y las construcciones adheridas a él y cuyo valor, determinado mediante avalúo practicado por institución bancaria o perito valuador autorizado, con antigüedad máxima de un año, no exceda de la suma que resulte de multiplicar por treinta la unidad de medida y actualización elevada al año, vigente en el Estado de Baja\nCalifornia.\nViviendas de Nivel Residencial: Aquéllas que consistan en el suelo y las construcciones adheridas a él y cuyo valor, determinado mediante avalúo practicado por institución bancaria o perito valuador autorizado, con antigüedad máxima de un año, exceda de la suma que resulte de multiplicar por treinta la unidad de medida y actualización elevada al año, vigente en el Estado de Baja\nCalifornia.\nSEXTO.- En caso de que cualesquiera de los Municipios no esté en condiciones de prestar los servicios que les fueron transferidos por el Estado para su administración, éstos podrán ser prestados por el Ejecutivo Estatal, a través de las Dependencias competentes, ellos, de acuerdo con las disposiciones legales vigentes.\nSÉPTIMO.- Las cuotas y tarifas por los Derechos a que se refiere esta Ley, con excepción de las que se establecen en los Artículos\n10 Fracción III numeral 10; 16 Fracción I, 18 Fracción I Inciso H), III Inciso M) y VI, 19 Fracción III, VI Inciso A), VII Inciso F), y\nIX Inciso A), 20 Fracciones I Inciso A) y C), y II Inciso A), 22, 26 numerales 37, 43 y 44, de esta Ley, se actualizarán mensualmente a partir del mes de febrero, con el factor que se obtenga de\nEstadística y Geografía, o la dependencia federal que en sustitución de ésta lo publique, del último mes inmediato anterior al mes por el cual se hace el ajuste, entre el citado índice del penúltimo mes inmediato anterior al del mismo mes que se actualiza. anterior, sea menor a 1, el factor de actualización que se aplicará será 1.\nPara efectos de la actualización a que se refiere este artículo, se considerarán cuotas y tarifas, sólo aquellas que estén determinadas en cantidad fija.\nOCTAVO.- Durante el Ejercicio Fiscal del año 2025, el Impuesto sobre Actividades Mercantiles e Industriales, se causará a la tasa del 0%, respecto de los ingresos que obtengan los establecimientos, negociaciones o giros mercantiles con motivo de la enajenación de libros, periódicos y revistas.\nNOVENO.- Los ingresos adicionales a los estimados en la proyección de ingresos, de acuerdo al Artículo 64 de la Ley de Presupuesto y\nEjercicio del Gasto Público del Estado de Baja California, deberán programarse y someterse como egresos a la aprobación del Congreso del Estado de Baja California.\nDÉCIMO.- Sin perjuicio de lo establecido en los Artículos 12 y 14 de esta Ley, la Dirección del Registro Público de la Propiedad y de\nComercio durante el ejercicio fiscal del año 2025, y previo al pago de los derechos respectivos, podrá prestar los servicios de inscripción de actos traslativos de dominio o actos por los que se constituya o transmita derechos reales, que hayan sido celebrados a través de documento privado convencional ratificado ante notario, juez de paz, Registro Público de la Propiedad o Catastro Municipal, hasta antes del 26 de septiembre del año 2015 y cuyo valor por 7,000 el importe del salario mínimo general vigente en aquella fecha.\nDECIMOPRIMERO.- Durante el Ejercicio Fiscal del 2025, solo deberán referencia los artículos 7 fracción IX, 17 fracción IV, 18 Bis, 26 fracción IX, 27 fracción VI y 29 fracción VI, de la Ley que Regula los Servicios de Control Vehicular en el Estado de Baja California, quienes realicen trámite de alta y cambios de propietarios, así circulación de vehículos modelos 2008 y posteriores, y aquellos que en el año 2024 hayan tenido la obligación de presentar el seguro de responsabilidad civil.\nDECIMOSEGUNDO.- Las personas físicas y morales que estén obligadas a presentar declaraciones de impuestos estatales, deberán\nGobierno del Estado o mediante declaración que contenga la referencia para pago en ventanilla bancaria.\nAsimismo el trámite de refrendo de tarjeta de circulación, establecido en el artículo 29 de la Ley que Regula los Servicios de\nControl Vehicular en el Estado de Baja California, deberá solicitarse a través del portal de internet del Poder Ejecutivo del\nGobierno del Estado, cumpliendo con los requisitos que para tal efecto establece la citada Ley, debiendo cubrir el pago correspondiente a través de dicho portal o bien mediante referencia para pago en ventanilla bancaria, o Institución y/o establecimiento autorizado para tal efecto por la Secretaría de Hacienda.\nNo se considerarán presentadas las citadas declaraciones, o solicitud de refrendo de tarjeta de circulación cuando se realicen por medios distintos a los señalados en el presente artículo, por lo que se generarán los accesorios correspondientes hasta en tanto se cumpla con la obligación fiscal a través del portal de internet del Poder Ejecutivo del Gobierno del Estado o declaración que contenga la referencia para pago en ventanilla bancaria.\nLa Secretaría de Hacienda diseñará e implementará los mecanismos los relativos al cumplimiento de obligaciones en materia fiscal.\nDECIMOTERCERO.- Las personas físicas y morales que tengan registrados vehículos en el Registro Estatal Vehicular, podrán realizar la baja definitiva de los mismos, cuando hayan dejado de circulación, y por los cuales no se haya cumplido con la obligación de darlos de baja en los términos de la normatividad aplicable. En\nIngresos del Estado de Baja California, excepto los derechos que se en que se lleve a cabo la baja definitiva, así como sus derechos extemporáneos, sin incluir el Impuesto Adicional para la Educación media y Superior y las multas que se hayan generado por tal motivo, respectiva, las contribuciones y accesorios de carácter federal que en su caso se adeuden por los citados vehículos.\nEl vehículo que haya sido dado de baja definitiva que se desee inscribir nuevamente al Registro Estatal Vehicular, podrá hacerse siempre y cuando se cubran las contribuciones que en su momento dejó de pagar por acogerse al presente beneficio.\nDECIMOCUARTO.- Cuando los ciudadanos soliciten el servicio establecido en el artículo 10, fracción I, inciso D de la presente\nLey, se expedirá la licencia de conducir en los términos y vigencias establecidas en la misma.\nDECIMOQUINTO.- El Ejecutivo Estatal por conducto de la Secretaría de Hacienda podrá afectar en garantía y/o como fuente de pago los ingresos que deriven del impuesto sobre remuneraciones al trabajo personal a que se refiere el artículo 3 de la presente Ley, previa autorización expresa de la Legislatura del Estado mediante la cual se determinen las condiciones para ello.\nDECIMOSEXTO.- Los Organismos operadores de agua deberán realizar en el mes de octubre de cada año, un análisis sobre el aumento real en el costo de los insumos y demás conceptos que se requieren para prestar los servicios de agua, a fin de que sirvan de base para las iniciativa de Ley de Ingresos del Estado.\nDECIMOSÉPTIMO.- Se autoriza la recepción de los recursos que se los artículos 18 Fracción I, incisos F), G), L), M), N) y Ñ), y 30 fracción IV incisos A), B), C) y D) de la presente Ley, a través\nBaja California.\nDECIMOCTAVO.- Durante el ejercicio fiscal de 2025, todas las menciones al salario mínimo que se contenga como unidad de cuenta, índice, base, medida o referencia para determinar la cuantía del del Estado, así como en la presente Ley de Ingresos del Estado, se entenderán referidas a la Unidad de Medida y Actualización (UMA) a la propia Constitución y la Ley para Determinar el Valor de la\nUnidad de Medida y Actualización.\nDECIMONOVENO.- El Poder Ejecutivo del Estado por conducto de su\nSecretaría de Hacienda en coordinación con la Secretaría de\nTurismo, deberán realizar las gestiones necesarias a fin de que dentro de un plazo de 60 días naturales siguientes a que entre en vigor esta ley, se lleven a cabo las modificaciones correspondientes dentro del fideicomiso constituido, para actualizar sus reglas de operación que permitan establecer el correcto destino de los recursos que lo integran; acorde a lo establecido en el artículo 6 de la presente Ley.\nVIGÉSIMO.- Las personas físicas o morales que no hayan realizado su trámite de canje o revalidación de sus Tarjetas de Circulación durante el ejercicio fiscal 2024 y/o anteriores, deberán cubrir los derechos por cada ejercicio, los derechos extemporáneos y accesorios, hasta en tanto cumpla con la obligación fiscal del presente ejercicio, de conformidad con lo señalado en el artículo\n29 de la Ley que Regula los Servicios de Control Vehicular en el\nEstado de Baja California, y de acuerdo a las tarifas establecidas en la Ley de Ingresos del Estado de Baja California del ejercicio fiscal correspondientes, según sea el caso.\nVIGÉSIMO PRIMERO.- Se deja sin efectos el Decreto del Poder\nOficial del Estado de Baja California, respecto al plazo indefinido\n24 de la Ley que Regula los Servicios de Control Vehicular en el\nEstado de Baja California, la cual se sujetará a la vigencia establecida en la Norma Oficial Mexicana NOM-001-SCT-2-2016, tal como se establece en el artículo 24 de la Ley que Regula los\nServicios de Control Vehicular en el Estado de Baja California.\nPor lo anterior, el canje de placas de circulación en los trámites por Refrendo para el presente ejercicio fiscal 2025, con las personas físicas o morales de conformidad con el artículo 29 de placas de circulación durante el ejercicio fiscal de 2021 o anteriores, con independencia si es por Servicio Particular o\nPúblico, deberá de realizar el canje de placas de circulación a partir del 01 de julio de 2025, de conformidad con el trámite señalado en el artículo 29 de la Ley que Regula los Servicios de\nControl Vehicular en el Estado de Baja California, debiendo cubrir la tarifa establecida en la presente Ley; según corresponda.\nVIGÉSIMO SEGUNDO.- La presente Ley entrará en vigor el día primero de enero del año dos mil veinticinco.\nDADO: En el salón de sesiones “Lic. Benito Juárez García” del veinte días del mes diciembre de dos mil veinticuatro.\nC. EVELYN SÁNCHEZ SÁNCHEZ\nDIPUTADA PRESIDENTA.\nC. MICHELLE ALEJANDRA TEJEDA MEDINA\nDIPUTADA SECRETARIA.",
  "ordenamiento": "REGLAMENTO",
  "jurisdiccion": "BAJA CALIFORNIA",
  "fuente_oficial": "Periódico Oficial",
  "FECHA PER OFIC": "2024/12/26",
  "ESTATUS": "VIGENTE",
  "TOMO": "TOMO_II",
  "URL": "https://www.congresobc.gob.mx/Documentos/ProcesoParlamentario/Leyes/TOMO_II/20241226_LEYINGRESOESTADO2025.PDF",
  "es_escaneado": false,
  "tiene_tablas": false,
  "materia": [
    "financiero",
    "fiscal",
    "económico"
  ]
}