{
  "titulo": "Ley DE SEGURIDAD ESCOLAR DEL ESTADO DE BAJA CALIFORNIA",
  "Contenido": "LEY DE SEGURIDAD ESCOLAR DEL ESTADO\nDE BAJA CALIFORNIA\nPublicado en el Periódico Oficial No. 45, Tomo CXIX, de fecha 05 de\nCAPÍTULO I\nDISPOSICIONES GENERALES\nArtículo 1.- Las disposiciones de esta Ley son de orden público e interés general.\nLas acciones y programas en materia de seguridad escolar son de carácter obligatorio para las autoridades, organizaciones e instituciones estatales y municipales de los sectores público, privado, social y en general para la comunidad escolar.\nArtículo 2.- La presente Ley tiene por objeto:\nI. Establecer las normas y lineamientos conforme a las cuales se llevarán a cabo las acciones en materia de seguridad escolar;\nII. Procurar la creación de vínculos permanentes entre los diversos elementos que interactúan en el ámbito de la comunidad escolar;\nIII. Regular las acciones, proyectos y programas de corto, mediano y largo plazo, que permitan su seguimiento y evaluación constante en materia de seguridad escolar;\nIV. Impulsar acciones para generar un clima de seguridad en la comunidad escolar que permita fortalecer integralmente una cultura de prevención, y\nV. Fortalecer las políticas públicas nacionales en materia de seguridad escolar.\nArtículo 3.- Para los efectos de esta Ley se entenderá por:\nI. Ayuntamientos: Ayuntamientos del Estado de Baja California;\nII. Centro Escolar: Institución pública o particular donde se imparte educación básica, media superior y superior en el estado de Baja California;\nIII. Comunidad Escolar: Conjunto de personas que comparten espacios educativos, dentro de los cuales se consideran a alumnos, directivos, docentes, personal administrativo y de apoyo, padres de familia, vecinos y autoridades educativas;\nIV. Consejo de Seguridad: Consejo Estatal de Seguridad Ciudadana de\nCalifornia;\nFracción Reformada\nV. Consejo Escolar: Consejo Escolar de Participación Social a que refiere el\nArtículo 68 de la Ley de Educación del Estado de Baja California, así como los análogos creados en las escuelas particulares de educación básica a que refiere el\nArtículo 69 de dicha ley;\nVI. Infraestructura escolar: Muebles e inmuebles destinados a la educación impartida por el Estado o municipios de la entidad y los particulares con autorización o con reconocimiento de validez oficial de estudios, en el marco del sistema educativo estatal, en términos de la Ley de Educación del Estado de Baja California, así como a los servicios e instalaciones necesarios para su correcta operación:\nVII. Ley: Ley de Seguridad Escolar del Estado de Baja California.;\nVIII. Secretaría: Secretaría de Educación del Estado;\nFracción Reformada\nIX. Secretario Ejecutivo: La o el Secretario Ejecutivo del Sistema Estatal de\nSeguridad Ciudadana de conformidad con la Ley del Sistema Estatal de Seguridad\nCiudadana del Estado de Baja California;\nFracción Reformada\nX. Seguridad Escolar: Resguardo de la integridad física y psicosocial de los integrantes de la comunidad escolar, al interior y en el entorno que rodea el centro escolar, derivada del conjunto de acciones preventivas, de seguimiento y de atención ante cualquier situación de riesgo; y\nXI. Situación de riesgo: Circunstancias que conllevan la posibilidad de un hecho violento o peligroso para la comunidad escolar.\nArtículo Reformado\nArtículo 4.- La seguridad escolar es responsabilidad del Ejecutivo Estatal y\nAyuntamientos, de acuerdo a su ámbito de competencia, con la participación de los sectores público, privado y social, en los términos de esta Ley.\nArtículo 5.- Los programas y acciones en materia de seguridad escolar que se deriven de la presente Ley, tenderán principalmente a modificar las actitudes, así de prevención de situaciones de riesgo.\nArtículo 6.- En lo no previsto por la presente Ley será de aplicación supletoria:\nI. Ley de Educación del Estado de Baja California;\nII. Ley del Sistema Estatal de Seguridad Ciudadana de Baja California;\nFracción Reformada\nIII. Ley de Protección Civil y Gestión Integral de Riesgos del Estado de Baja\nCalifornia; y,\nFracción Reformada\nIV. Ley del Régimen Municipal para el Estado de Baja California.\nArtículo Reformado\nCAPÍTULO II\nAUTORIDADES\nArtículo 7.- Son autoridades en materia de seguridad escolar:\nI. Consejo de Seguridad;\nII. Secretaría;\nIII. Secretaría de Seguridad Ciudadana del Estado;\nFracción Reformada\nIV. Secretaría de Salud del Estado;\nV. Dirección Estatal de Protección Civil;\nVI. Secretaría de Bienestar;\nFracción Reformada\nVII. Ayuntamientos;\nVIII. Organismos Públicos Descentralizados de la Administración Pública\nEstatal, sectorizados a la Secretaría, y\nIX. Órganos Municipales de Protección Civil.\nArtículo Reformado\nArtículo 8.- Corresponde al Consejo de Seguridad, en materia de seguridad escolar, el ejercicio de las atribuciones siguientes:\nI. Coordinar y supervisar la ejecución de los programas en materia de seguridad escolar que prevea la presente Ley, y\nII. Apoyar, asesorar y capacitar, a través de las instancias correspondientes, a los consejos escolares.\nArtículo 9.- Corresponde a la Secretaría, en materia de seguridad escolar, el ejercicio de las atribuciones siguientes:\nI. Aplicar, en la esfera de su competencia, esta Ley y vigilar su observancia;\nII. Proponer al titular del Ejecutivo Estatal la celebración de acuerdos y/o convenios con instituciones educativas particulares, organismos no gubernamentales y demás organismos de la sociedad civil, con el propósito de cumplir el objeto de la presente Ley;\nIII. Proponer al Consejo de Seguridad, a través del Secretario Ejecutivo del mismo, la adopción de medidas necesarias para el cabal cumplimiento del objeto de esta Ley;\nIV. Formular y desarrollar acciones en materia de seguridad escolar, coordinándose con el Consejo de Seguridad, demás autoridades en la materia y con la sociedad;\nV. Mantener permanentemente actualizado el directorio estatal y municipal de los centros escolares;\nVI. Supervisar, en coordinación con la Dirección de Protección Civil, la implementación del Programa Interno de Protección Civil en cada centro escolar con base al Programa Escolar de Protección Civil contenido en la presente Ley;\nVII. Proponer, a través del Secretario Ejecutivo, al Consejo de Seguridad que en la toma de decisiones en materia de esta Ley, las autoridades o instancias respectivas consideren las necesidades específicas para cada municipio del Estado.\nVIII. Elaborar el Programa Estatal de Seguridad Escolar de Baja California, y\nIX. Las que conforme a esta ley y otras disposiciones aplicables le correspondan.\nArtículo 10.- La Secretaría de Seguridad Ciudadana, se coordinará con la\nAyuntamientos.\nArtículo Reformado\nArtículo 11.- Corresponde a la Secretaría de Salud en materia de Seguridad\nEscolar, el ejercicio de las atribuciones siguientes:\nI. Proponer al Consejo de Seguridad, a través del Secretario Ejecutivo, las de violencia y consumo, abuso de drogas, problemas en la salud mental, así como del comportamiento con base a la Ley de Salud Pública del Estado;\nFracción Reformada\nII. Dar seguimiento a los alumnos detectados con factores de riesgo para su tratamiento individual y del entorno familiar, con base a la Ley de Salud Pública del\nEstado;\nIII. Generar estadística precisa de los centros escolares atendidos y difundirla para su conocimiento al Consejo de Seguridad y la Secretaría, y\nIV. Las demás atribuciones que conforme a la presente Ley y demás disposiciones legales aplicables le competan.\nArtículo Reformado\nArtículo 12.- Corresponde a la Dirección de Protección Civil, en materia de seguridad escolar, el ejercicio de las atribuciones siguientes:\nI. Expedir el Programa Escolar de Protección Civil del Estado con base a lo previsto en la presente Ley;\nII. Autorizar el Programa Interno de Protección Civil en cada centro escolar con base al Programa Escolar de Protección Civil del Estado;\nIII. Supervisar, en coordinación con la Secretaría, la aplicación del Programa\nInterno de Protección Civil en cada centro escolar;\nIV. Coordinar las actividades que se relacionen con la protección civil en los centros escolares, con el apoyo del resto de las autoridades y con las entidades auxiliares en materia de seguridad escolar previstas en la presente Ley;\nV. Identificar los centros escolares dentro del Atlas Estatal de Riesgo, para casos en que se presente alguna emergencia provocada por factores geológicos, hidrometereológicos, químicos o sanitarios en alguno de ellos, con base a la información que le proporcione la Secretaría;\nVI. Capacitar en materia de protección civil en los centros escolares a través de la Secretaría;\nVII. Practicar las inspecciones técnicas a los centros escolares a fin de vigilar puedan afectar a la comunidad escolar, así como dictar las medidas de seguridad necesarias e imponer las sanciones correspondientes, todo ello conforme a la Ley de Protección Civil del Estado;\nVIII. Invitar y fomentar en la comunidad escolar la cultura de la protección civil, a través de la participación social de la Secretaría, y\nIX. Las demás atribuciones que conforme a la presente Ley y demás disposiciones legales aplicables, le competan.\nArtículo 13.- La Secretaría de Bienestar en materia de Seguridad Escolar, aplicará los programas que le correspondan en materia de bienestar social, a fin de mejorar el entorno social de los centros escolares, en coordinación con las autoridades Estatales y Municipales competentes.\nArtículo 14.- Corresponde a los Ayuntamientos en materia de Seguridad\nEscolar, el ejercicio de las siguientes atribuciones:\nI. Colaborar con el resto de las autoridades en materia de seguridad escolar y entidades auxiliares previstas en la presente Ley para la ejecución de acciones en materia de seguridad escolar;\nII. Aplicar en la comunidad escolar acciones relativas a la prevención del delito y participación social;\nIII. Proveer de infraestructura vial, señalización y limpieza en las calles de los centros escolares; así como tapeado, limpieza o demolición de construcciones abandonadas para garantizar la seguridad de la comunidad escolar;\nIV. Instruir a los Órganos Municipales de Protección Civil y Bomberos a que participen en las acciones que se implementen en materia de seguridad escolar en los centros escolares, dentro del ámbito de su competencia, conforme a la Ley de\nProtección Civil del Estado, y\nV. Las demás que deriven de esta ley y de otras disposiciones aplicables.\nArtículo Reformado\nArtículo 15.- Los Organismos Públicos Descentralizados de la Administración\nPública Estatal, sectorizados a la Secretaría, en sus respectivos ámbitos de competencia, propondrán a ésta, la adopción de cualquier tipo de medida necesaria para el cabal cumplimiento de los objetivos de esta Ley, y en su caso, las aplicarán en beneficio de la comunidad escolar.\nArtículo 16.- Corresponde a los Órganos Municipales de Protección Civil en materia de seguridad escolar, el ejercicio de las atribuciones siguientes:\nI. Promover la capacitación en materia de protección civil y desastres en los centros escolares.\nII. Invitar y fomentar en la comunidad escolar la cultura de la protección civil.\nIII. Participar dentro del ámbito de su competencia en los programas y acciones que en materia de protección civil, se implementen en los centros escolares, y\nIV. Las demás que conforme a esta Ley y otras disposiciones le correspondan.\nCAPÍTULO III\nENTIDADES AUXILIARES Y PERSONAL DIRECTIVO, ADMINISTRATIVO Y DE\nAPOYO\nArtículo 17.- Son entidades auxiliares en materia de seguridad escolar:\nI. Los consejos escolares que operen con arreglo a esta Ley para los fines exclusivos de seguridad escolar;\nII. Los demás integrantes del sector privado y organismos de la sociedad civil que de forma voluntaria decidan auxiliar en materia de seguridad escolar; y\nIII.- La Academia de Seguridad Pública del Estado de Baja California.\nArtículo Reformado\nArtículo 18.- Los consejos escolares son órganos de apoyo de las autoridades encargadas de aplicar la presente Ley que tienen por objeto promover la participación de la comunidad escolar en acciones que contribuyan a lograr la seguridad escolar.\nArtículo 19.- Conforme al Artículo 68 de la Ley de Educación del Estado, en cada centro escolar habrá un consejo escolar, el cual se sujetará a lo previsto en dicha ley y en la presente. Al efecto, deberán operar Consejos análogos en las escuelas particulares de educación básica.\nEn el caso de las instituciones de educación pública que dependan de la autoridad educativa federal, o en el de las universidades autónomas con domicilio en el Estado, el titular del Ejecutivo Estatal por conducto de la Secretaría, podrá\nLey.\nArtículo 20.- Los consejos escolares se integrarán de acuerdo a lo previsto\nSocial en la Educación del Estado.\nArtículo 21.- Además de las establecidas en otros ordenamientos aplicables, corresponde a los consejos escolares, las atribuciones siguientes:\nI. Diseñar y aplicar medidas preventivas que propicien un entorno escolar sano, confiable y seguro para la educación;\nII. Fomentar en la comunidad escolar la cultura de la denuncia ciudadana de aquellas acciones delictivas o contrarias a la legalidad;\nIII. Hacer del conocimiento al Directivo del centro escolar y en su caso, a la riesgo de la comunidad escolar;\nIV. Constituirse en vínculos efectivos de coordinación entre las autoridades en materia de Seguridad Escolar para el cumplimiento de las disposiciones de esta Ley;\nV. Proponer al Directivo del centro escolar correspondiente, gestione ante quien corresponda los recursos para cubrir las necesidades que en materia de seguridad escolar requiera el centro escolar;\nVI. Hacer del conocimiento del Directivo del centro escolar correspondiente, de aquellos estudiantes que requieran algún tratamiento específico de salud o necesidad educativa especial;\nVII. Llevar registro de aquellos establecimientos comerciales y/o negocios en general que a juicio del consejo escolar constituyan una situación de riesgo, así como su difusión entre la comunidad escolar;\nVIII. Proponer al Directivo del centro escolar correspondiente, que otorgue reconocimientos a los miembros de la comunidad escolar y de la sociedad en general, que se distingan por su valor cívico y participación social en bien de las labores preventivas de seguridad escolar, así como a sus propios miembros;\nIX. Gestionar ante la autoridad municipal respectiva la instalación de alumbrado público, de infraestructura vial, de señalización y de limpieza en el perímetro del centro escolar correspondiente;\nX. Solicitar a la autoridad competente, con apego a las disposiciones aplicables, la destrucción de bardas, construcciones e inmuebles en general, así como el tapiado de estas, que por su estado de abandono y condiciones físicas, representen un peligro o sean susceptibles de ser usados para actividades ilícitas en riesgo de la comunidad escolar;\nXI. Promover y difundir entre la comunidad escolar las actividades y capacitaciones que realicen;\nXII. Promover la colaboración en la vigilancia vecinal tendiente a proteger al alumnado del centro escolar que corresponda, así como la infraestructura educativa, especialmente en periodos vacacionales y días inhábiles;\nXIII. Promover la información a la comunidad escolar sobre el uso adecuado integridad física del alumnado y prever su manejo adecuado;\nFracción Reformada\nXIV. Fomentar la política de cero tolerancia al hostigamiento y acoso sexual; y,\nFracción Adicionada, recorriéndose la subsecuente\nXV. Las demás atribuciones que conforme a esta ley y otras disposiciones aplicables le correspondan.\nFracción Reformada\nArtículo 22.- Los consejos escolares para el cumplimiento de la presente Ley, actuarán por conducto de sus respectivos Comités de Seguridad y Protección Civil.\nArtículo 23.- El funcionamiento de los consejos escolares en materia de seguridad escolar se hará conforme a la presente Ley, sin detrimento de las reglas previstas en la Ley de Educación del Estado y demás normatividad aplicable.\nEl funcionamiento de los consejos escolares para efectos de esta Ley, será coordinado por la Secretaría, a través de las Subsecretarías, Coordinaciones\nGenerales, así como de las Delegaciones Municipales respectivas.\nArtículo 24.- Corresponde al Directivo o al encargado de los centros escolares:\nI. Propiciar el respeto a la dignidad de los alumnos y el resto de la comunidad escolar;\nII. Promover el respeto a la propiedad pública y privada;\nIII. Fomentar el compañerismo, los valores, la cultura y el deporte entre alumnos, personal docente, administrativo y de apoyo;\nIV. Implementar, en coordinación con la autoridad del ramo, programas permanentes de concientización, formación e información, que aborden, entre otros, los temas de:\na) Prevención de adicciones;\nb) Prevención contra el acoso escolar (bullying);\nc) Educación sexual y prevención contra la violencia sexual;\nd) Fortalecimiento de valores;\ne) Uso responsable del Servicio de Asistencia Telefónica 066 y de denuncia anónima 089;\nf) Cultura de la legalidad;\ng) Educación vial;\nh) Violencia intrafamiliar;\ni) Prevención a conductas contrarias a la armonía en la comunidad escolar, y\nj) Protección civil.\nV. Contar con un Programa Interno de Protección Civil del centro escolar con\nCivil;\nVI. Canalizar para su atención a las diversas organizaciones e instituciones de los sectores público, privado o social que corresponda, aquellos estudiantes que requieran algún tratamiento específico de salud o necesidad educativa especial, con el consentimiento expreso de sus padres o tutores;\nVII. Vigilar el aspecto sanitario del centro escolar a su cargo;\nVIII. Promover el consumo de alimentos nutritivos;\nLos lineamientos a que deberán sujetarse el expendio y distribución de los alimentos y bebidas preparados y procesados, dentro de toda escuela, serán establecidos por la Secretaría de Educación Pública, mediante disposiciones de carácter general que se publicarán en el Diario Oficial de la Federación, con base en los criterios nutrimentales que para tal efecto determine la Secretaría de Salud\nFederal. Estas disposiciones de carácter general comprenderán las regulaciones que prohíban los alimentos que no favorezcan la salud de los educandos y fomenten aquellos de carácter nutrimental.\nIX. Promover el respeto al entorno y al cuidado del medio ambiente;\nX. Coordinar al interior del centro escolar a su cargo, la revisión del alumnado a fin de detectar cualquier factor de riesgo hacia su persona o a la comunidad escolar, designando en su caso al personal educativo idóneo para dicho propósito;\nXI. Denunciar los hechos presuntamente delictivos o de situación de riesgo cuando tenga conocimiento de estos ante las autoridades competentes;\nXII. Contar con un botiquín de primeros auxilios, y\nXIII. Las demás acciones que conforme a esta Ley y otras disposiciones aplicables le correspondan. instrumento de planeación estratégica de cada centro escolar, de conformidad con el\nCapítulo IV de la Ley de Educación del Estado.\nArtículo Reformado\nArtículo 25.- Corresponde al personal docente, administrativo y de apoyo de los centros escolares:\nI. Propiciar el respeto a la dignidad de los alumnos y el resto de la comunidad escolar;\nII. Promover el respeto a la propiedad pública y privada;\nIII. Fomentar el compañerismo, los valores, la cultura y el deporte en el centro escolar;\nIV. Auxiliar al directivo o responsable del centro escolar, en la implementación de los programas permanentes de concientización, formación e información, que aborden, entre otros, los temas de:\na) Prevención de adicciones;\nb) Prevención contra el acoso escolar (bullying);\nc) Educación sexual y prevención contra la violencia sexual;\nd) Fortalecimiento de valores;\ne) Uso responsable del Servicio de Asistencia Telefónica 066 y de denuncia anónima 089;\nf) Cultura de la legalidad;\ng) Educación vial;\nh) Violencia intrafamiliar;\ni) Prevención a conductas contrarias a la armonía en la comunidad escolar,\nj) Protección civil.\nV. Participar en la elaboración e implementación del Programa Interno de\nProtección Civil;\nVI. Promover la higiene de los alumnos a su cargo;\nVII. Promover el consumo de alimentos nutritivos;\nVIII. Promover el respeto al entorno y al cuidado del medio ambiente;\nIX. Auxiliar al directivo o responsable del centro escolar en la revisión del alumnado a su cargo para detectar cualquier situación de riesgo;\nX. Hacer del conocimiento del directivo o responsable del centro escolar, los conocimiento de estos ante las autoridades competentes, y\nXI. Las demás acciones que conforme a esta Ley y otras disposiciones aplicables le correspondan.\nArtículo 25 BIS.- Corresponde a la Academia de Seguridad Pública del encargadas de aplicar la presente Ley. Para tal efecto, la Academia realizará programas en los que se contemple la participación de sus aspirantes como miembros de las instituciones policiales.\nArtículo Adicionado\nCAPÍTULO IV\nPROGRAMA ESTATAL DE SEGURIDAD ESCOLAR\nArtículo 26.- El Programa Estatal de Seguridad Escolar es el documento emitido por la Secretaría que contiene el conjunto de acciones preventivas, de seguimiento y de atención de la Comunidad Escolar y de su infraestructura educativa, con el objeto de detectar y minimizar los factores de riesgo delictivo, adictivo y de cualquier otra circunstancia que la ponga en peligro.\nAsimismo, en el Programa se deben incluir acciones para prevenir, detectar, atender y erradicar el acoso escolar. Del Programa se deriva el Protocolo para\nPrevenir, Detectar, Atender y Erradicar el acoso escolar, previsto en el artículo 16 de la Ley para Prevenir y Erradicar el Acoso Escolar para el Estado de Baja California.\nLas autoridades señaladas en el artículo 7 de esta Ley y los centros escolares se sujetarán a las disposiciones establecidas en el Programa.\nArtículo Reformado\nArtículo 27.- El Programa Estatal de Seguridad Escolar se revisará anualmente respecto de su contenido y resultados, deberá guardar congruencia con la Ley de Planeación del Estado.\nLa Secretaría implementará y dará seguimiento al Programa Estatal de\nSeguridad Escolar con la participación de las autoridades en materia de seguridad escolar previstas en la presente Ley.\nLa Secretaría informará, por conducto del Secretario Ejecutivo, al Consejo de\nSeguridad, anualmente o cuando sea requerido por éste, sobre los resultados y avances del Programa Estatal de Seguridad Escolar.\nArtículo 28.- El Programa Estatal de Seguridad Escolar deberá atender, por lo menos, los rubros siguientes:\nI. La prevención y tratamiento de adicciones;\nII. La prevención de conductas parasociales, antisociales y cualquier otra situación de riesgo, con particular énfasis en el acoso escolar;\nIII. La vinculación de los integrantes de la comunidad escolar en la implementación del presente programa;\nIV. La atención de infraestructura educativa segura y entorno social de los\nCentros Escolares;\nV. Articular los programas educativos federales en materia de seguridad escolar al Programa Estatal de Seguridad Escolar;\nVI. La participación con los diversos sectores público, privado y social, para los fines del Programa Estatal de Seguridad Escolar, y\nVII. El fomento en la comunidad escolar de una cultura de prevención del delito y autoprotección de cualquier situación de riesgo, así como de la cultura de la legalidad y la denuncia.\nArtículo Reformado\nArtículo 29.- Las autoridades en materia de seguridad escolar previstas en la presente Ley, deberán incorporar el Programa Estatal de Seguridad Escolar en sus respectivos programas anuales de operación.\nCAPÍTULO V\nPROGRAMA ESCOLAR DE PROTECCIÓN CIVIL\nArtículo 30.- El Programa Escolar de Protección Civil es el instrumento rector en materia de protección civil para los centros escolares, cuya expedición estará a cargo de la Dirección de Protección Civil y contiene los subprogramas de prevención, auxilio y recuperación.\nEl Programa Escolar de Protección Civil servirá como base para que en cada centro escolar se cuente con un Programa Interno de Protección Civil, en cuya elaboración participe la comunidad escolar; será autorizado por la Dirección de\nProtección Civil y su aplicación será supervisada por dicha autoridad y la Secretaría.\nArtículo 31.- En el subprograma de prevención se definirán medidas para la comunidad escolar y medio ambiente, siendo como mínimas, las siguientes:\nI. Realizar análisis de riesgos, externos e internos.\nII. Actualizar directorios e inventarios.\nIII. Revisión de normas y señales y equipamiento conforme a la normatividad aplicable.\nIV. Programa de mantenimiento.\nV. Conformar, coordinar y capacitar brigadas.\nVI. Implementar medidas de difusión de acciones.\nVII. Ejercicios y simulacros.\nVIII. Procedimiento de cierre forzoso.\nArtículo Reformado\nArtículo 32.- En el subprograma de auxilio se engloban las acciones que se llevan a cabo en el momento en que se presenta una contingencia, están enfocadas a salvaguardar a la comunidad escolar y se integra de la siguiente forma:\nI. Etapa de alertamiento: a través de la cual se requiere llamar la atención de quienes se encuentran en el centro escolar cuando se detecta la presencia o proximidad de un incidente.\nEn esta etapa se debe definir el nombre y ubicación del responsable y suplentes del Comité de Seguridad Escolar y Protección Civil del Consejo Escolar, así como el establecimiento de un sistema identificable entre toda la población.\nII. Plan de emergencia: que deberá contener actividades y procedimientos específicos para proteger a la comunidad escolar e infraestructura educativa cuando impacte una contingencia.\nSe debe establecer un centro de comando de emergencias, debidamente localizado e intercomunicado que coordine las operaciones.\nIII. La evaluación de daños: que deberá contemplar mecanismos y medidas para determinar la dimensión de la contingencia, la cuantificación de daños humanos y materiales, las necesidades que deben cubrirse y la previsión de eventos secundarios.\nArtículo 33.- El subprograma de recuperación se constituye con una serie de acciones orientadas a la reconstrucción, mejoramiento o reestructuración de los sistemas dañados por la contingencia, se derivan de la revisión y análisis de las quienes hayan sido evacuados o movilizados como resultado de la contingencia, procurando garantizar su regreso a las instalaciones de la manera más segura.\nArtículo 34.- En cada centro escolar operará un Comité de Seguridad Escolar operación del Programa Interno de Protección Civil.\nArtículo 35.- El Comité de Seguridad Escolar y Protección Civil tendrá las funciones siguientes:\nI. Elaborar un diagnóstico de riesgos del centro escolar ajustado a su realidad y entorno.\nII. Actualización de directorios e inventarios.\nIII. Conformación y coordinación de brigadas.\nIV. Recibir o solicitar capacitación.\nV. Revisión periódica de áreas de riesgo.\nVI. Realizar ejercicios y simulacros.\nVII. Revisión de procedimientos.\nArtículo 36.- En caso de que en un mismo edificio se concentren varios niveles educativos, deberá existir un Comité de Seguridad Escolar y Protección Civil por cada uno de ellos.\nEn cada Comité de Seguridad Escolar y Protección Civil existirá, por lo menos, brigadas de: Comunicación, evacuación, primeros auxilios, prevención de incendios, así como búsqueda y rescate.\nLa integración de las brigadas se regirá en los términos específicos de cada\nPrograma Escolar de Protección Civil, atendiendo a las particularidades de cada centro escolar.\nEn el Comité de Seguridad Escolar y Protección Civil participará un brigadista por cada diez personas que asistan al centro escolar.\nCAPÍTULO VI\nPROCEDIMIENTO DE CIERRE FORZOSO\nArtículo 37.- El procedimiento de cierre forzoso, previsto en el Artículo 31 fracción VII de la presente Ley, es aquel destinado a restringir el movimiento en el centro escolar ante una situación de riesgo.\nArtículo 38.- Las condiciones en las cuales debe activarse el procedimiento de cierre forzoso pueden ser cualquiera de las siguientes:\nI. Situaciones que impliquen el uso de armas de fuego, explosivos o de cualquier otro tipo.\nII. Cuando un operativo policial o militar está en acción próxima o en el centro escolar mismo.\nIII. Cuando alguien tome rehenes.\nIV. Cuando se suscite alguna emergencia de sustancias químicas.\nV. Situaciones de fenómenos hidrometereológicos, o\nVI. Cualquier otra situación análoga a las anteriores que igualmente ponga en riesgo a la comunidad escolar.\nArtículo 39.- Cualquier persona que se percate de la situación de riesgo deberá llamar a 911 y/o 089 denuncia anónima y, notificarlo inmediatamente al personal directivo y/o personal docente y, en su caso, obtener la descripción física de la persona sospechosa y las circunstancias de la situación de riesgo.\nArtículo Reformado\nArtículo 40.- Cuando el personal directivo es notificado de una situación de riesgo debe adquirir la mayor cantidad de información detallada acerca de la misma y, de ser posible, confirmarla. Después de haber ponderado la información y confirmado la situación respectiva, el personal directivo inmediatamente deberá implementar el procedimiento de cierre forzoso, enfocándose en mantener la calma.\nAsimismo, en todo momento debe ejercitar sentido común y tener siempre presente que su única prioridad es la seguridad del alumnado y su personal.\nArtículo 41.- Toda entidad gubernamental que, atendiendo a sus funciones, pueda atender alguna situación de riesgo, está facultada para solicitar al personal directivo la activación del procedimiento de cierre forzoso.\nArtículo 42.- Una vez tomada la determinación de activación del procedimiento de cierre forzoso, se procederá de la siguiente manera:\nI. Activar la alarma, la cual debe estar diferenciada atendiendo al tipo de situación de riesgo.\nII. Notificar al Centro de Control, Comando, Comunicación y Computo, dependiente de la Secretaria de Seguridad Ciudadana, proporcionando la información pertinente en forma clara: quien reporta, nombre del centro escolar, dirección, definición de la situación, información de personas lesionadas, rutas principales y alternas de acceso, en general, toda aquella de relevancia para su adecuada atención.\nFracción Reformada\nIII. El personal directivo deberá comunicar de la situación de riesgo a su superior inmediato a la brevedad posible.\nIV. Quienes se encuentren en el centro escolar deberán trasladarse al salón más próximo, permanecer ahí o mantenerse en zona segura al aire libre dentro del centro escolar, según lo amerite la situación. Deben agacharse, cubrirse, alejarse de las paredes, permanecer fuera de la línea de visión exterior, si es posible cerrar cortinas o instalar y/o improvisar barreras visuales.\nV. Si la situación amerita ingresar a espacios cerrados, todas las puertas y ventanas deberán ser cerradas con llave, únicamente se abrirán cuando un alumno o persona que se encuentre dentro del centro escolar busque asilo y seguridad.\nVI. Los alumnos y el personal de que se trate, deberán permanecer callados y apagar todos los dispositivos eléctricos, electrónicos y audio-visuales, siendo el personal directivo el único que utilizará estos medios para contactarse con la autoridad.\nVII. Deberán evaluarse particularmente aquellas situaciones en que los alumnos requieran utilizar el sanitario.\nVIII. El personal docente deberá ser promotor de mantener la calma, así como de administrar primeros auxilios, si las circunstancias lo ameritan.\nIX. En casos muy especiales, como situaciones médicas, el personal directivo deberá coordinarse con las autoridades del puesto de mando exterior para realizar una extracción.\nX. Quienes se encuentren fuera del centro escolar deben alejarse lo más rápido posible hacia alguna zona segura previamente identificada.\nXI. Los padres o tutores que se encuentren en el exterior del centro escolar, no podrán ingresar al área ni recoger a sus hijos hasta que el personal directivo lo indique, previa confirmación de la autoridad a cargo.\nXII. El procedimiento de cierre forzoso permanecerá hasta que la autoridad a cargo declare la zona segura.\nArtículo Reformado\nCAPÍTULO VII\nDENUNCIA Y REVISIONES PERIÓDICAS\nArtículo 43.- Es obligación de la comunidad escolar reportar o hacer de conocimiento del consejo escolar cualquier situación riesgo.\nLas denuncias podrán ser presentadas por escrito o digital. Deberán ser recibidas y enviadas al mismo, por la autoridad escolar correspondiente.\nPárrafo Adicionado\nAsimismo, para tal efecto la autoridad escolar establecerá un buzón digital en\nEstado de Baja California, a fin de recibir cualquier denuncia y dar el trámite correspondiente, así como para brindar atención a víctimas de violencia escolar.\nPárrafo Adicionado\nArtículo Reformado\nArtículo 44.- A su vez, el consejo escolar hará del conocimiento del Directivo que haya lugar.\nArtículo 45.- Cuando se presuma que existen negocios, vendedores o o regale bebidas de graduación alcohólica, estupefacientes, psicotrópicos o sustancias toxicas al alumnado, el consejo escolar o el Directivo denunciarán la situación inmediatamente. Las autoridades competentes deberán solicitar a los responsables la exhibición de los permisos, autorizaciones o licencias requeridos para su operación.\nArtículo 46.- Con el fin de detectar la posesión de estupefacientes, psicotrópicos, armas o demás sustancias u objetos prohibidos en el interior de los centros escolares, la Secretaría autorizará por escrito a las instituciones policiales preventivas locales, la realización de revisiones periódicas a las pertenencias de los alumnos, las cuales se examinarán detalladamente en su presencia.\nSe entiende por objeto prohibido aquél que, en sí mismo o por su uso, representa un riesgo para la comunidad escolar y la infraestructura educativa.\nTratándose de instituciones policiales preventivas federales, se estarán a las disposiciones establecidas vía convenio con la Secretaría.\nEn los centros escolares privados se actuará en los términos del primer párrafo del presente artículo, previa autorización de la autoridad correspondiente de los mismos.\nCAPÍTULO VIII\nREGLAMENTOS INTERIORES DE LOS\nCENTROS ESCOLARES EN MATERIA DE SEGURIDAD ESCOLAR\nArtículo 47.- Los reglamentos interiores de los centros escolares deberán ser acordes a la presente Ley y serán autorizados por la Secretaría, en los cuales se educativo en materia de seguridad escolar.\nArtículo Reformado\nArtículo 48.- Los reglamentos interiores deberán especificar como mínimo lo siguiente:\nI. Derechos y prohibiciones de los alumnos;\nII. Obligaciones de los padres de familia o tutor;\nIII. Obligaciones para el personal directivo, docente, administrativo y de apoyo;\nIV. Enlistar aquellos objetos que se consideren prohibidos o de uso restringidos. En Educación Básica estará prohibido el uso de dispositivos móviles distintos a los autorizados por la Secretaría.\nV. Forma y tiempo en que deberán ser regresados a sus propietarios los alumnos, siempre y cuando éstos sean de uso lícito;\nVI. Los mecanismos alternativos de solución de controversias aplicables entre alumnos, y\nVII. Sanciones a los alumnos.\nArtículo Reformado\nArtículo 49.- Dentro de las prohibiciones de los alumnos a que se hace referencia en el artículo que antecede, cuando menos deberán de establecerse las siguientes:\nI. Faltar al respeto a la comunidad escolar;\nII. Realizar acoso escolar o violencia en contra de algún integrante de la comunidad escolar;\nIII. Introducir y/o consumir bebidas de graduación alcohólica, estupefacientes, psicotrópicos o sustancias toxicas en el centro escolar;\nIV. Presentarse al centro escolar bajo el influjo de estupefacientes, psicotrópicos, substancias tóxicas o debidas de graduación alcohólica;\nV. Fumar en el interior del centro escolar;\nVI. Portar armas blancas o portar o disparar armas de fuego en el centro escolar o su perímetro exterior, independientemente de las sanciones a que hubiera lugar que se deriven de otros ordenamientos legales aplicables;\nVII. Participar, promover, permitir o tolerar cualquier tipo de juegos de azar y juegos con apuestas en el centro escolar;\nVIII. Pintar, modificar, grabar, dibujar o rayar con fines vandálicos paredes, muros, bardas, salones y demás infraestructura educativa;\nIX. Poner en peligro en forma dolosa la seguridad de la comunidad escolar;\nX. Causar daños, incendio, destrucción o deterioro de cualquier tipo en la infraestructura educativa;\nXI. Participar en riñas en el centro escolar o su perímetro exterior;\nXII. Proferir o incitar a otro, a amenazar o coaccionar a algún integrante de la comunidad escolar, y\nXIII. Crear o formar parte de pandillas o cualquier otra agrupación delictiva o contraria a la armonía social.\nArtículo 50.- Dentro de las obligaciones de los padres de familia o tutor, cuando menos deberán de establecerse las siguientes:\nI. Propiciar, inculcar y fomentar el respeto a la dignidad de sus hijos o pupilos, hacia sus compañeros de estudio, personal directivo y docente, y en general hacia la\nComunidad Escolar, como base de la formación de valores en el hogar;\nII. Inculcar y fomentar el estudio, la cultura, la salud y el deporte en sus hijos o pupilos;\nIII. Informar al consejo escolar o en su caso a las autoridades correspondientes, de cualquier situación de riesgo que detecten;\nIV. Asistir y participar en los diversos programas y actividades que se lleven a cabo en el centro escolar en materia de Seguridad Escolar, realizados por las autoridades escolares o el consejo escolar;\nV. Conocer de las acciones en materia de protección civil al interior de los centros escolares establecidas por las autoridades competentes, y en su caso, participar en los cursos, ejercicios, simulacros y demás actividades que permitan reducir riesgos;\nVI. Informar al personal directivo o al consejo escolar sobre cualquier irregularidad en el aspecto sanitario y nutricional de los alimentos ofertados, así como cualquier otra en materia sanitaria en el centro escolar, y\nVII. Dar seguimiento a los programas de prevención, detección y atención de los factores de riesgo adictivo o de cualquier otro que implique una afectación para sus hijos o pupilos con el apoyo de la autoridad competente para tal efecto.\nCAPÍTULO IX\nSANCIONES\nArtículo 51.- El incumplimiento a las disposiciones contenidas en la presente\nLey, relativas a la protección civil, serán sancionadas conforme lo previsto en la Ley de Protección Civil del Estado.\nArtículo 52.- Es atribución exclusiva de la autoridad educativa competente, seguridad escolar de cada centro escolar.\nArtículo 53.- El incumplimiento a las disposiciones contenidas en la presente\nLey por parte del personal directivo, docente, administrativo y de apoyo, serán del Estado de Baja California.\nArtículo Reformado\nTRANSITORIOS\nArtículo Primero.- La presente Ley entrará en vigor al día siguiente de su publicación en el Periódico Oficial del Estado de Baja California.\nArtículo Segundo.- La Secretaría contará con ciento ochenta días, a partir del día siguiente de la publicación de la presente Ley, para expedir el Programa\nEstatal de Seguridad Escolar.\nArtículo Tercero.- Los centros escolares contarán con ciento ochenta días, a partir del día siguiente de la publicación de la presente Ley, para emitir o en su caso adecuar su reglamentación interior en materia de seguridad escolar, conforme a la presente Ley.\nArtículo Cuarto.- La Dirección Estatal de Protección Civil, dependiente de la\nSecretaría General de Gobierno del Estado de Baja California, contará con ciento ochenta días, a partir de la publicación de esta Ley, para expedir el Programa\nEscolar de Protección Civil del Estado de Baja California, conforme a la presente\nLey.\nDADO en el Salón de Sesiones “Lic. Benito Juárez García” del H. Poder\nLegislativo del Estado de Baja California, en la Ciudad de Mexicali, B.C., a los once días del mes de septiembre del año dos mil doce.\nDIP. ALFONSO GARZÓN ZATARAIN\nDIPUTADO PRESIDENTE\nDIP. FAUSTO ZÁRATE ZEPEDA\nDIPUTADO SECRETARIO\nPUBLÍQUESE.\nMEXICALI, BAJA CALIFORNIA, A LOS DIECISIETE DÍAS DEL MES DE\nSEPTIEMBRE DEL AÑO DOS MIL DOCE.\nGOBERNADOR DEL ESTADO\nJOSÉ GUADALUPE OSUNA MILLÁN\nSECRETARIO GENERAL DE GOBIERNO\nFRANCISCO ANTONIO GARCÍA BURGOS\nARTÍCULO 3.- Fue reformado por Decreto No. 235, publicado en el Periódico\nXXIV Legislatura, siendo Gobernadora Constitucional la C. Marina del Pilar Ávila\nOlmeda 2021-2027;\nARTÍCULO 6.- Fue reformado por Decreto No. 235, publicado en el Periódico\nOficial No. 33, de fecha 09 de junio de 2023, Índice, Tomo CXXX, expedido por la H.\nXXIV Legislatura, siendo Gobernadora Constitucional la C. Marina del Pilar Ávila\nOlmeda 2021-2027;\nARTÍCULO 7.- Fue reformado por Decreto No. 235, publicado en el Periódico\nOficial No. 33, de fecha 09 de junio de 2023, Índice, Tomo CXXX, expedido por la H.\nXXIV Legislatura, siendo Gobernadora Constitucional la C. Marina del Pilar Ávila\nOlmeda 2021-2027;\nARTÍCULO 10.- Fue reformado por Decreto No. 235, publicado en el\nPeriódico Oficial No. 33, de fecha 09 de junio de 2023, Índice, Tomo CXXX, expedido por la H. XXIV Legislatura, siendo Gobernadora Constitucional la C. Marina del Pilar Ávila Olmeda 2021-2027;\nARTÍCULO 11.- Fue reformado por Decreto No. 235, publicado en el\nPeriódico Oficial No. 33, de fecha 09 de junio de 2023, Índice, Tomo CXXX, expedido por la H. XXIV Legislatura, siendo Gobernadora Constitucional la C. Marina del Pilar Ávila Olmeda 2021-2027;\nARTÍCULO 13.- Fue reformado por Decreto No. 235, publicado en el\nPeriódico Oficial No. 33, de fecha 09 de junio de 2023, Índice, Tomo CXXX, expedido por la H. XXIV Legislatura, siendo Gobernadora Constitucional la C. Marina del Pilar Ávila Olmeda 2021-2027;\nARTÍCULO 14.- Fue reformado por Decreto No. 235, publicado en el\nPeriódico Oficial No. 33, de fecha 09 de junio de 2023, Índice, Tomo CXXX, expedido por la H. XXIV Legislatura, siendo Gobernadora Constitucional la C. Marina del Pilar Ávila Olmeda 2021-2027;\nARTÍCULO 17.- Fue reformado por Decreto No. 564, publicado en el expedido por la H. XX Legislatura, siendo Gobernador Constitucional el C. José\nGuadalupe Osuna Millán 2007-2013;\nARTÍCULO 21.- Fue reformado mediante Decreto No. 315, publicado en el expedido por la H. XXIV Legislatura, siendo Gobernadora Constitucional la C. Marina del Pilar Ávila Olmeda 2021-2027;\nARTICULO 24.- Fue reformado por Decreto No. 41, publicado en el Periódico expedido por la H. XXI Legislatura, siendo Gobernador Constitucional el C.\nFrancisco Arturo Vega de Lamadrid 2013-2019;\nARTÍCULO 25 BIS.- Fue reformado por Decreto No. 564, publicado en el expedido por la H. XX Legislatura, siendo Gobernador Constitucional el C. José\nGuadalupe Osuna Millán 2007-2013;\nARTICULO 26.- Fue reformado por Decreto No. 85, publicado en el Periódico\nOficial No. 46, de fecha 19 de septiembre de 2014, Sección I, Tomo CXXI, expedido por la H. XXI Legislatura, siendo Gobernador Constitucional el C. Francisco Arturo\nVega de Lamadrid 2013-2019;\nARTICULO 28.- Fue reformado por Decreto No. 85, publicado en el Periódico\nOficial No. 46, de fecha 19 de septiembre de 2014, Sección I, Tomo CXXI, expedido por la H. XXI Legislatura, siendo Gobernador Constitucional el C. Francisco Arturo\nVega de Lamadrid 2013-2019;\nARTÍCULO 31.- Fue modificado por Fe de Erratas, publicada en el Periódico\nOficial No. 55, de fecha 07 de diciembre de 2012, Sección I, Tomo CXIX, expedida por la H. XX Legislatura, siendo Gobernador Constitucional del Estado, el C. José\nGuadalupe Osuna Millán 2007-2013;\nARTÍCULO 39.- Fue reformado por Decreto No. 235, publicado en el\nPeriódico Oficial No. 33, de fecha 09 de junio de 2023, Índice, Tomo CXXX, expedido por la H. XXIV Legislatura, siendo Gobernadora Constitucional la C. Marina del Pilar Ávila Olmeda 2021-2027;\nARTÍCULO 42.- Fue reformado por Decreto No. 235, publicado en el\nPeriódico Oficial No. 33, de fecha 09 de junio de 2023, Índice, Tomo CXXX, expedido por la H. XXIV Legislatura, siendo Gobernadora Constitucional la C. Marina del Pilar Ávila Olmeda 2021-2027;\nARTÍCULO 47.- Fue reformado por Decreto No. 643, publicado en el\nPeriódico Oficial No. 47, Sección IV, Tomo CXXIII, de fecha 21 de octubre de 2016, expedido por la H. XXI Legislatura, siendo gobernador constitucional el C. Francisco\nArturo Vega de Lamadrid 2013-2019;\nARTÍCULO 43.- Fue reformado mediante Decreto No. 315, publicado en el expedido por la H. XXIV Legislatura, siendo Gobernadora Constitucional la C. Marina del Pilar Ávila Olmeda 2021-2027;\nARTÍCULO 48.- Fue reformado por Decreto No. 643, publicado en el expedido por la H. XXI Legislatura, siendo gobernador constitucional el C. Francisco\nArturo Vega de Lamadrid 2013-2019;\nARTÍCULO 21.- Fue reformado mediante Decreto No. 315, publicado en el expedido por la H. XXIV Legislatura, siendo Gobernadora Constitucional la C. Marina del Pilar Ávila Olmeda 2021-2027;\nARTÍCULO 53.- Fue reformado mediante Decreto No. 315, publicado en el expedido por la H. XXIV Legislatura, siendo Gobernadora Constitucional la C. Marina del Pilar Ávila Olmeda 2021-2027;\nFE DE ERRATAS al Decreto Número 292, en su Artículo 31, publicada en el expedida por la H. XX Legislatura, siendo Gobernador Constitucional del Estado, el\nC. José Guadalupe Osuna Millán 2007-2013;\nMexicali, B.C., a los dieciséis días del mes de noviembre del año dos mil doce.\nDIP. CLAUDIA JOSEFINA AGATÓN MUÑIZ\nDIPUTADO PRESIDENTA\n(RÚBRICA)\nDIP. FAUSTO ZÁRATE ZEPEDA\nDIPUTADO SECRETARIO\n(RÚBRICA)\nDE CONFORMIDAD CON LO DISPUESTO POR LA FRACCIÓN I DEL\nPUBLÍQUESE.\nMEXICALI, BAJA CALIFORNIA, A LOS VEINTISÉIS DÍAS DEL MES DE\nNOVIEMBRE DEL AÑO DOS MIL DOCE.\nJOSÉ GUADALUPE OSUNA MILLÁN\nGOBERNADOR DEL ESTADO\n(RÚBRICA)\nFRANCISCO ANTONIO GARCÍA BURGOS\nSECRETARIO GENERAL DE GOBIERNO\n(RÚBRICA)\nARTÍCULO SEGUNDO TRANSITORIO DEL DECRETO No. 564, POR EL\nQUE SE REFORMA A LA FRACCIÓN II Y LA ADICIÓN DE UNA FRACCIÓN III,\nAMBAS AL ARTÍCULO 17; ASÍ COMO LA ADICIÓN DE UN ARTÍCULO 25 BIS,\nPUBLICADO EN EL PERIÓDICO OFICIAL No. 46, SECCIÓN III, TOMO CXX, DE\nSIENDO GOBERNADOR CONSTITUCIONAL EL C. JOSÉ GUADALUPE OSUNA\nMILLÁN 2007-2013;\nARTÍCULO TRANSITORIO\nÚNICO.- Las presentes reformas entrarán en vigor al día siguiente de su publicación en el Periódico Oficial del Estado.\nDADO en el Salón de Sesiones “Lic. Benito Juárez García” del H. Poder\nLegislativo del Estado de Baja California, en la Ciudad de Mexicali, B.C., a los veinte días del mes de septiembre del año dos mil trece.\nDIP. GREGORIO CARRANZA HERNÁNDEZ\nPRESIDENTE\n(RÚBRICA)\nDIP. MARCO ANTONIO VIZCARRA CALDERÓN\nSECRETARIO\n(RÚBRICA)\nDE CONFORMIDAD CON LO DISPUESTO POR LA FRACCION I DEL\nPUBLIQUESE.\nMEXICALI, BAJA CALIFORNIA, A LOS TREINTA DÍAS DEL MES DE\nSEPTIEMBRE DEL AÑO DOS MIL TRECE.\nJOSÉ GUADALUPE OSUNA MILLÁN\nGOBERNADOR DEL ESTADO\n(RÚBRICA)\nFRANCISCO ANTONIO GARCÍA BURGOS\nSECRETARIO GENERAL DE GOBIERNO\n(RÚBRICA)\nARTÍCULO CUARTO TRANSITORIO DEL DECRETO No. 41, POR EL QUE\nSE REFORMA EL ARTÍCULO 24, PUBLICADO EN EL PERIÓDICO OFICIAL No.\n13, TOMO CXXI, NUMERO ESPECIAL, DE FECHA 13 DE MARZO DE 2014,\nEXPEDIDO POR LA H. XXI LEGISLATURA, SIENDO GOBERNADOR\nCONSTITUCIONAL EL C. FRANCISCO ARTURO VEDA DE LAMADRID 2013-2019.\nARTÍCULO TRANSITORIO\nÚNICO.- El presente Decreto entrará en vigor al día siguiente de su publicación en el Periódico Oficial del Estado.\nDADO en el Salón de Sesiones “Lic. Benito Juárez García” del H. Poder\nLegislativo del Estado de Baja California, en la Ciudad de Mexicali, B.C., a los doce días del mes de marzo del año dos mil catorce.\nDIP. RENÉ ADRIÁN MENDÍVIL ACOSTA\nPRESIDENTE\nDIP. MARÍA DEL CARMEN FRÍAS\nSECRETARIA\nPUBLÍQUESE.\nMEXICALI, BAJA CALIFORNIA, A LOS TRECE DÍAS DEL MES DE MARZO\nDEL AÑO DOS MIL CATORCE.\nFRANCISCO ARTURO VEGA DE LAMADRID\nGOBERNADOR DEL ESTADO\n(RÚBRICA)\nGUILLERMO TREJO DOZAL\nSECRETARIO GENERAL DE GOBIERNO\n(RÚBRICA)\nARTÍCULO SEGUNDO TRANSITORIO DEL DECRETO No. 85, POR EL QUE\nSE REFORMAN LOS ARTÍCULOS 26 y 28, PUBLICADO EN EL PERIÓDICO\nOFICIAL No. 46, SECCION I, TOMO CXXI, DE FECHA 19 DE SEPTIEMBRE DE\n2014, EXPEDIDO POR LA H. XXI LEGISLATURA, SIENDO GOBERNADOR\nCONSTITUCIONAL EL C. FRANCISCO ARTURO VEDA DE LAMADRID 2013-2019.\nARTÍCULO TRANSITORIO\nÚNICO.- La presente reforma entrará en vigor a los 30 días hábiles siguientes de su publicación en el Periódico Oficial del Estado.\nDADO en el Salón de Sesiones “Lic. Benito Juárez García” del H. Poder\nLegislativo del Estado de Baja California, en la Ciudad de Mexicali, B.C., a los tres días del mes de julio del año dos mil catorce.\nDIP. FELIPE DE JESÚS MAYORAL MAYORAL\nPRESIDENTE\n(RÚBRICA)\nDIP. GERARDO ÁLVAREZ HERNÁNDEZ\nSECRETARIO\nPUBLÍQUESE.\nMEXICALI, BAJA CALIFORNIA, A LOS VEINTE DÍAS DEL MES DE\nAGOSTO DEL AÑO DOS MIL CATORCE.\nFRANCISCO ARTURO VEGA DE LAMADRID\nGOBERNADOR DEL ESTADO\nFRANCISCO RUEDA GOMEZ\nSECRETARIO GENERAL DE GOBIERNO\n(RÚBRICA)\nARTÍCULO UNICO TRANSITORIO DEL DECRETO No. 643, POR EL QUE\nSE REFORMAN LOS ARTÍCULOS 47 Y 48, PUBLICADO EN EL PERIÓDICO\nOFICIAL No. 47, SECCION IV, TOMO CXXIII, DE FECHA 21 DE OCTUBRE DE\n2016, EXPEDIDO POR LA H. XXI LEGISLATURA, SIENDO GOBERNADOR\nCONSTITUCIONAL EL C. FRANCISCO ARTURO VEGA DE LAMADRID 2013-2019.\nARTÍCULOS TRANSITORIOS\nPRIMERO. El presente Decreto entrará en vigor al día siguiente de su publicación en el Periódico Oficial del Estado de Baja California.\nSEGUNDO. A partir de la entrada en vigor del presente Decreto, el Ejecutivo\nEstatal deberá emitir, en un plazo no mayor ciento ochenta días naturales, las modificaciones a los Reglamentos correspondientes.\nDADO en el Salón de Sesiones “Lic. Benito Juárez García” del H. Poder\nLegislativo del Estado de Baja California, en la Ciudad de Mexicali, B.C., a veintidós días del mes de septiembre del año dos mil dieciséis.\nDIP. MÓNICA BEDOYA SERNA\nPRESIDENTA\n(RÚBRICA)\nDIP. ROSA ISELA PERALTA CASILLAS\nSECRETARIA\n(RÚBRICA)\nDE CONFORMIDAD CON LO DISPUESTO POR LA FRACCION I DEL\nPUBLIQUESE.\nMEXICALI, BAJA CALIFORNIA, A LOS TRES DÍAS DEL MES DE OCTUBRE DEL\nAÑO DOS MIL DIECISÉIS.\nFRANCISCO ARTURO VEGA DE LAMADRID\nGOBERNADOR DEL ESTADO\nFRANCISCO RUEDA GOMEZ\nSECRETARIO GENERAL DE GOBIERNO\nARTÍCULO ÚNICO TRANSITORIO DEL DECRETO No. 235, POR EL QUE\nSE APRUEBAN LAS REFORMAS A LOS ARTÍCULOS 3, 6, 7, 10, 11, 13, 14, 39 Y\n42; PUBLICADO EN EL PERIÓDICO OFICIAL No. 33, ÍNDICE, DE FECHA 09 DE\nSIENDO GOBERNADORA CONSTITUCIONAL LA C. MARINA DEL PILAR ÁVILA\nOLMEDA 2021-2027.\nTRANSITORIOS\nÚNICO. EI presente Decreto entrará en vigor al día siguiente de su publicación en el Periódico Oficial del Estado de Baja California.\nDADO en Sesión Ordinaria de la XXIV Legislatura en la Ciudad de Mexicali, B.C., a los veinticinco días del mes de mayo del año dos mil veintitrés.\nDIP. MANUEL GUERRERO LUNA\nPRESIDENTE\n(RÚBRICA)\nDIP. ALEJANDRA MARÍA ANG HERNÁNDEZ\nSECRETARIA\n(RÚBRICA)\nDE CONFORMIDAD CON LO DISPUESTO POR LA FRACCIÓN I DEL\nSOBERANO DE BAJA CALIFORNIA, IMPRÍMASE Y PUBLÍQUESE.\nMEXICALI, BAJA CALIFORNIA, A LOS TREINTA DÍAS DEL MES DE MAYO DEL\nAÑO DOS MIL VEINTITRÉS.\nMARINA DEL PILAR ÁVILA OLMEDA\nGOBERNADORA DEL ESTADO\nDE BAJA CALIFORNIA\nCATALINO ZAVALA MÁRQUEZ\nSECRETARIO GENERAL DE GOBIERNO\nDEL ESTADO DE BAJA CALIFORNIA\nARTÍCULO ÚNICO TRANSITORIO DEL DECRETO No. 315, POR EL QUE\nSE APRUEBAN LAS REFORMAS A LOS ARTÍCULOS 21, 43, 53; PUBLICADO EN\nSECCIÓN I, TOMO CXXX, EXPEDIDO POR LA H. XXIV LEGISLATURA, SIENDO\nGOBERNADORA CONSTITUCIONAL LA C. MARINA DEL PILAR ÁVILA OLMEDA\n2021-2027.\nTRANSITORIO\nÚNICO.- La presente reforma entrará en vigor al día siguiente de su publicación en el Periódico Oficial del Estado.\nDADO en Sesión Ordinaria de la XXIV Legislatura en la Ciudad de Mexicali, B.C., a los nueve días del mes de noviembre del año dos mil veintitrés.\nDIP. MANUEL GUERRERO LUNA\nPRESIDENTE\n(RÚBRICA)\nDIP. DUNNIA MONTSERRAT MURILLO LÓPEZ\nSECRETARIA\n(RÚBRICA)\nDE CONFORMIDAD CON LO DISPUESTO POR LA FRACCIÓN I DEL\nSOBERANO DE BAJA CALIFORNIA, IMPRÍMASE Y PUBLÍQUESE.\nMEXICALI, BAJA CALIFORNIA, A LOS CATORCE DÍAS DEL MES DE\nNOVIEMBRE DEL AÑO DOS MIL VEINTITRÉS.\nMARINA DEL PILAR ÁVILA OLMEDA\nGOBERNADORA DEL ESTADO\nDE BAJA CALIFORNIA\nCATALINO ZAVALA MÁRQUEZ\nSECRETARIO GENERAL DE GOBIERNO\nDEL ESTADO DE BAJA CALIFORNIA",
  "ordenamiento": "REGLAMENTO",
  "jurisdiccion": "BAJA CALIFORNIA",
  "fuente_oficial": "Periódico Oficial",
  "FECHA PER OFIC": "2023/12/01",
  "ESTATUS": "VIGENTE",
  "TOMO": "TOMO_VI",
  "URL": "https://www.congresobc.gob.mx/Documentos/ProcesoParlamentario/Leyes/TOMO_VI/20231201_LEYSEGESCOLAR.PDF",
  "es_escaneado": false,
  "tiene_tablas": true,
  "materia": [
    "social",
    "salud",
    "educación",
    "cultura"
  ]
}