{
  "titulo": "Ley DE SALUD MENTAL DEL ESTADO DE BAJA CALIFORNIA",
  "Contenido": ".\nActualización Legislativa.\nÚltima Reforma P.O. No.33, Índice, 28-Jun-2024\nLEY DE SALUD MENTAL DEL ESTADO DE BAJA CALIFORNIA\nPublicado en el Periódico Oficial No. 09, de fecha\n23 de febrero de 2018, Sección IV, Tomo CXXV\nCapítulo Primero\nDisposiciones Generales\nArtículo 1.- La presente Ley es de orden público, de interés social y de aplicación general en el Estado de Baja California y tiene por objeto asegurar el derecho a la protección de la salud mental de las personas y población usuaria, y garantizar el pleno goce de los derechos humanos de las personas con trastornos mentales y adicciones, así como regular el acceso y prestación de servicios de salud mental dentro del ambiente comunitario, y su vinculación con los servicios de protección y apoyo social complementarios.\nPárrafo Reformado\nLa salud mental y la prevención de las adicciones tendrán carácter prioritario dentro de las políticas de salud.\nArtículo Reformado\nArtículo 2.- Son objetivos de esta ley:\nI. Regular las bases y modalidades, para garantizar el acceso a los servicios de salud mental a toda la población del Estado de Baja California, con un enfoque de derechos humanos y perspectiva de género;\nII. Establecer los mecanismos adecuados para la promoción, prevención, evaluación, diagnóstico, tratamiento, rehabilitación, reintegración, fomento de la salud mental y demás acciones a realizar por parte de instituciones de salud pública del Estado de Baja California y personas físicas o morales de los sectores social y privado, que coadyuven en la prestación de salud mental; y,\nIII. Definir los mecanismos y lineamientos para promover la participación de la población, en el desarrollo y la ejecución de los programas emitidos por la Secretaría de\nSalud del Estado en materia de salud mental.\nIV. Las demás que le señalen otras leyes y disposiciones aplicables.\nArtículo 3.- Para los efectos de esta Ley, se entiende por salud mental un estado de bienestar físico, mental, emocional y social determinado por la interacción del individuo con la sociedad y vinculado al ejercicio pleno de los derechos humanos; y por adicción a la enfermedad física y psico-emocional que crea una dependencia o necesidad hacia una sustancia, actividad o relación.\nArtículo Reformado\nLey de Salud Mental del Estado de Baja California. Página 1\n.\nActualización Legislativa.\nÚltima Reforma P.O. No.33, Índice, 28-Jun-2024\nArtículo 4. El Gobierno del Estado, las Secretarías e instituciones públicas y sociales en el ámbito de sus respectivas competencias, tienen la obligación de garantizar el cumplimiento del derecho a la salud mental, mediante una política transversal, con respeto a los derechos humanos y con un enfoque de género. Las instituciones privadas que brinden atención a la salud mental están obligadas a cumplir, en el ámbito de su competencia con las disposiciones de esta Ley.\nArtículo 5.- El núcleo familiar desempeña una función esencial en el desarrollo de las potencialidades de las personas con trastornos mentales y adicciones, corresponde a la\nSecretaría de Salud, al Consejo Estatal de Salud Mental del Estado de Baja California y al\nInstituto de Psiquiatría del Estado de Baja California, proporcionar a las personas que integren el núcleo familiar, debida asistencia, asesoría, orientación, capacitación y adiestramiento necesario para tal fin.\nEl propósito último de los servicios de salud mental es la recuperación y el bienestar, el despliegue óptimo de sus potencialidades individuales para la convivencia, el trabajo y la recreación.\nPárrafo Adicionado\nLa recuperación varía de persona a persona, de acuerdo con las preferencias individuales, significa el empoderamiento de la persona para poder tener una vida autónoma, superando o manejando el trauma.\nPárrafo Adicionado\nLa atención a la salud mental deberá brindarse con un enfoque comunitario, de recuperación y con estricto respeto a los derechos humanos de los usuarios de estos servicios, en apego a los principios de interculturalidad, interdisciplinariedad, integralidad, intersectorialidad, perspectiva de género y participación social.\nPárrafo Adicionado\nArtículo Reformado\nArtículo 6.- Para efectos de la presente Ley, se entenderá por:\nI. Acciones para la atención de la salud mental: estrategias necesarias para proporcionar a la persona usuaria una atención integral en salud mental, a través de la promoción, prevención de riesgos, la evaluación, diagnóstico, tratamiento, rehabilitación y seguimiento, en los términos previstos en la presente Ley;\nII. Consejo: Consejo de Salud Mental de Baja California;\nIII. Municipio: órgano político-administrativo de las demarcaciones territoriales;\nIV. Derecho a la salud mental: derecho de toda persona al bienestar psíquico, identidad, dignidad, respeto y un tratamiento integral con el propósito de una óptima\nLey de Salud Mental del Estado de Baja California. Página 2\n.\nActualización Legislativa.\nÚltima Reforma P.O. No.33, Índice, 28-Jun-2024 integración social, para lo cual el Gobierno tiene la obligación de planear, organizar, operar y supervisar el funcionamiento de los servicios a los que se refiere la presente Ley;\nV. Diagnóstico psicológico: informe que resulta del análisis e interpretación de los datos obtenidos en las distintas medidas de evaluación que se aplican a una persona o grupo, con el objetivo de detectar los síntomas que interfieren en su adaptación o que podrían desencadenar algún tipo de alteración, detectar disfunciones mentales, conocer el perfil de habilidades, aptitudes o personalidad, así como ubicar la evolución y constitución de grupos que alteran la estabilidad social, de tal manera que además, puede ser útil en el diagnóstico diferencial de distintos padecimientos, en la selección de personal y en la orientación vocacional;\nVI. Equipo de atención en salud mental: grupo de profesionales para la atención integral en salud mental, conformado por una persona profesional en psiquiatría, una en psicología, una en enfermería y una en trabajo social;\nVII. Espacio físico o presencial: en el que interactúan el psicoterapeuta, el paciente y sus familiares, el cual deberá estar equipado y amueblado adecuadamente, sólo en casos excepcionales, se adaptará de acuerdo a las condiciones posibles;\nVIII. Evaluación psicológica: conjunto de exámenes mentales que realiza el psicólogo, para estudiar el comportamiento humano en su interacción recíproca con el ambiente físico y social para describir, clasificar, predecir y explicar su comportamiento e identificar las variables que conforman la estructura intelectual, emocional, conductual, perceptual, sensorial, familiar, psicoeducativa y neuropsicológica;\nIX. Familiar: persona con parentesco por consanguinidad, afinidad o civil con la persona usuaria de los servicios de salud mental;\nX. Fomento de la salud mental: promoción de acciones encaminadas a mejorar la mental; cargo;\nXII. Infraestructura: conjunto de inmuebles, instalaciones, construcciones, mobiliario y equipo, cuyo objeto sea otorgar los servicios a la población los servicios de salud mental;\nXIII. Ley: Ley de Salud Mental del Estado de Baja California;\nXIV. Ley de Salud: Ley de Salud Pública del Estado de Baja California;\nLey de Salud Mental del Estado de Baja California. Página 3\n.\nActualización Legislativa.\nÚltima Reforma P.O. No.33, Índice, 28-Jun-2024\nXV. Paciente bajo custodia: persona con algún trastorno mental que requiere atención médica hospitalaria encontrándose privada de la libertad o sometida a cualquier forma de detención o prisión, el que tenga la calidad de presentado, indiciado, probable responsable, procesado o sentenciado;\nXVI. Persona usuaria: toda persona que recibe el beneficio de cualquier programa o campaña de promoción de salud mental, de prevención o manejo de trastornos mentales, encaminadas a la preservación de su salud mental y calidad de vida, y\nXVII. Personal de salud: profesionales, especialistas, técnicos, auxiliares y demás trabajadores que laboran en la prestación de los servicios de salud;\nXVIII. Prevención de riesgos en salud mental: conjunto de acciones contenidas en los planes, programas, campañas y proyectos gubernamentales, nacionales e internacionales, con la finalidad de informar y educar a la población en relación a cualquier aspecto vinculado a la salud mental, e intervenir en las comunidades para evitar situaciones de riesgo y dar a conocer procedimientos con el propósito principal de preservar la calidad de vida;\nXIX. Primer nivel de atención: atención otorgada por las Instituciones de Salud del\nEstado, y cualquier otra institución de Gobierno, que preste algún servicio de salud a la población en general;\nXX. Promoción de la Salud Mental: estrategia concreta, concebida como la suma de las acciones de los distintos sectores de la población, las autoridades sanitarias y los prestadores de servicios de salud pública, privada y social, encaminadas al desarrollo de mejores condiciones de salud mental individual y colectiva, priorizando la atención en primer nivel;\nXXI. Psicofarmacoterapia: tratamiento médico psiquiátrico dirigido a determinado trastorno mental, que se apoya en el empleo de medicamentos de diseño específico y con evidencia científica favorable;\nXXII. Psicoterapia: conjunto de métodos y recursos utilizados para el tratamiento psicológico de las personas, mediante los cuales interacciona la persona usuaria y el psicólogo con el propósito de promover la adaptación al entorno, la salud física o psíquica, la integridad de la identidad psicológica, el bienestar de las personas y el mejoramiento de su calidad de vida;\nXXIV. Rehabilitación: conjunto de procedimientos dirigidos a las personas usuarias de los servicios de salud mental, los cuales se ocupan de la evolución del padecimiento y de vida cotidiana. Su objetivo es mejorar la calidad de vida, para que el usuario en salud\nLey de Salud Mental del Estado de Baja California. Página 4\n.\nActualización Legislativa.\nÚltima Reforma P.O. No.33, Índice, 28-Jun-2024 mental, pueda actuar en comunidad tan activamente como sea posible y de manera independiente en su entorno social,\nXXV. Secretaría: Secretaría de Salud del Estado de Baja California;\nXXVI. Instituto: Instituto de Psiquiatría del Estado de Baja California;\nXXVII. Secretaría de Educación: Secretaría de Educación del Estado;\nXXVIII. Segundo nivel de atención: atención hospitalaria y ambulatoria otorgada por las unidades médicas que pertenecen al Sistema de Salud en el Estado;\nXXIX. Tercer nivel de atención: atención hospitalaria y ambulatoria otorgada por las\nUnidades Médicas de Especialidades pertenecientes al sistema de Salud del Estado;\nXXX. Titular de la Secretaría: persona titular de la Secretaría de Salud del Estado;\nXXXI. Trastorno Mental: afectación de la salud mental de una persona debido a la presencia de un comportamiento derivado de un grupo de síntomas identificables en la práctica clínica que en la mayoría de los casos se acompaña de malestar e interfieren en la actividad cotidiana del individuo y su entorno;\nXXXII. Tratamiento: diseño, planeación, instrumentación y conducción de estrategias médicas, farmacológicas y psicológicas encaminadas a restaurar, mejorar o mantener la calidad de vida de la persona que presenta algún trastorno mental;\nXXXIII. Tratamiento mixto: sistema terapéutico que integran los aspectos farmacológico y de reintegración psicosocial sobre el funcionamiento cognitivo, la psicopatología y la calidad de vida de pacientes con diagnóstico de trastorno mental.\nArtículo 7.- Además de los derechos a que se refiere el artículo 31 Bis de la Ley de\nSalud, las personas usuarias de los servicios de salud mental, tendrán derecho:\nPárrafo Reformado\nI. Al acceso oportuno y adecuado a los servicios de salud mental;\nII. A la toma de decisiones relacionadas con su atención y su tratamiento;\nIII. A la atención médica en el momento que lo solicite y, en su caso, a ser atendido en las instancias de salud del segundo y tercer nivel de atención, para completar su proceso de tratamiento y rehabilitación;\nIV. A ser informado sobre las campañas, planes, programas y servicios que proporcione el Gobierno y las instituciones sociales y privadas en materia de salud mental;\nLey de Salud Mental del Estado de Baja California. Página 5\n.\nActualización Legislativa.\nÚltima Reforma P.O. No.33, Índice, 28-Jun-2024\nV. A conservar la confidencialidad de información personal, a una historia clínica de conformidad con lo establecido en las normas oficiales y al anonimato de los participantes en estudios;\nVI. Derogada;\nFracción Derogada\nVII. A que se le apliquen exámenes de valoración, confiables y actualizados que consideren su entorno social o característica a estudiar y a conocer los alcances y las limitaciones de las evaluaciones realizadas\nVIII. A solicitar su diagnóstico diferencial, a recibir atención especializada, a contar con un plan o programa integral de tratamiento para la recuperación de sus funciones cerebrales, habilidades cognitivas, proceso de aprendizaje, así como a la reinserción al ámbito social y productivo, conservando su integridad psicológica, incluyendo a pacientes que hayan estado recluidos en un hospital o pabellón penitenciario psiquiátrico o establecimiento especializado en adiciones;\nIX. A la rehabilitación que le permita la reinserción familiar, laboral y comunitaria;\nX. A la accesibilidad de familiares, en el acompañamiento de las personas usuarias de los servicios de salud mental, salvo que medie contraindicación profesional; y\nXI. A recibir un trato digno y con respeto a sus derechos humanos, por parte de sus familiares y a que estos le proporcionen alimentos y cuidados necesarios para su rehabilitación integral.\nArtículo Reformado\nArtículo 8.- El profesional de salud mental tiene la obligación de estar debidamente acreditado para ejercer sus funciones, lo que incluye al menos, tener a la vista Cédula\nProfesional, Título Profesional, Certificación por un órgano colegiado y en su caso, certificados de especialización expedidos y registrados por las autoridades educativas y administrativas competentes, con la finalidad de que el usuario corrobore que es un especialista en la materia de salud mental.\nArtículo 9.- Todos los prestadores de servicios de salud mental del sector social y privado, participarán y coadyuvarán con las instancias involucradas en el diseño, operación y en general; para tal efecto deberán:\nI.Asistir a las convocatorias que realice la Secretaría;\nII.Coordinarse con la Secretaría para fomentar la suscripción de convenios o acuerdos para beneficio de la sociedad;\nLey de Salud Mental del Estado de Baja California. Página 6\n.\nActualización Legislativa.\nÚltima Reforma P.O. No.33, Índice, 28-Jun-2024\nIII.Participar en la difusión y publicación en los diversos medios de comunicación sobre la importancia de la detección temprana de los trastornos mentales y las alternativas para su atención en los sectores público, social y privado, y\nIV.Llevar a cabo cursos de capacitación para la población en general a efecto de crear condiciones para la detección oportuna de los trastornos mentales, conforme a los lineamientos que dicte la Secretaría.\nCapítulo Segundo\nAtribuciones de la Autoridad\nArtículo 10.- Corresponden a la Secretaría y al Instituto, en el ámbito de su competencia, sin menoscabo de las demás que se encuentren estipuladas en esta Ley y demás ordenamientos legales, las siguientes acciones:\nI. Elaborar el Programa de Salud Mental para el Estado de Baja California, conforme a los lineamientos establecidos en la Ley General de Salud, las Normas Oficiales Mexicanas, en la Ley Estatal de Salud y el presente ordenamiento, fomentando la participación de los sectores social y privado;\nII. Implementar programas en materia de salud mental en todos los niveles de atención;\nIII. Fijar los lineamientos de coordinación para que los municipios, en el ámbito de su competencia, intervengan en la promoción de la salud mental, e incentiven la participación social;\nIV. Suscribir convenios, acuerdos o cualquier instrumento jurídico de coordinación con los Municipios del Estado a efecto de mejorar la atención en materia de salud mental;\nV. Llevar a cabo los convenios de coordinación necesarios con los Municipios del\nEstado y el Instituto, para que, en cada uno de los municipios del Estado, se cuente, mínimamente con un centro ambulatorio de atención primaria que preste atención a la psicoactivas, y de adicciones;\nFracción Reformada\nVI. Implementar estrategias de coordinación y supervisión de índole institucional con los prestadores de servicios de salud mental del sector público, social y privado, con la finalidad de generar convenios y acciones de coordinación para la prevención, diagnóstico oportuno, tratamiento y rehabilitación, además, de garantizar la calidad en la prestación de los servicios de salud mental y adicciones;\nFracción Reformada\nLey de Salud Mental del Estado de Baja California. Página 7\n.\nActualización Legislativa.\nÚltima Reforma P.O. No.33, Índice, 28-Jun-2024\nVII. Brindar, a través de una línea telefónica de ayuda psicológica y de intervención en crisis, atención en tiempo real y contribuir a estabilizar a los pacientes, mientras se canaliza a una terapia psicológica presencial;\nFracción Adicionada, recorriéndose la subsecuente\nFracción Reformada\nVIII. La realización de programas para la prevención del suicidio a causa de trastornos mentales y del comportamiento, preferentemente en niñas, niños y adolescentes; y,\nFracción Adicionada, recorriéndose la subsecuente\nIX. Las demás acciones que contribuyan a la promoción y fomento de la salud mental de la población.\nArtículo Reformado\nArtículo 11.- La Secretaría y el Instituto buscará dar prioridad a la niñez, adolescencia, juventud, mujeres en condiciones de embarazo y puerperio, menopausia, adultos mayores, hombres con afecciones mentales y personas que se encuentran en situación de calle, de emergencia o desastre.\nArtículo 12.- La Secretaría de Educación fomentará y llevará a cabo acciones de coordinación con la Secretaría de Educación Pública Federal, para que en los centros escolares de educación inicial y básica en el sector público, se contemple lo siguiente:\nPárrafo Reformado\nI. Contar con personal capacitado y actualizado en la materia de psicología, pedagogía infantil y educación escolar con el objetivo de identificar un posible trastorno mental que presenten niñas o niños, debiéndolos canalizar a algún centro ambulatorio de atención primaria con servicios de salud mental o centro hospitalario, así como informar a madres y padres de familia o tutores y dar la orientación correspondiente;\nFracción Reformada\nII. Aplicar programas relacionados con salud mental infantil para que sean incorporados en el plan de estudios correspondiente;\nFracción Reformada\nIII. Proporcionar material informativo básico en salud mental a madres y padres de aplicar las medidas preventivas en un primer momento; y,\nFracción Reformada\nIV. Realizar el tamizaje de salud mental por las personas especialistas del sistema educativo, por lo menos una vez en el transcurso del ciclo escolar.\nFracción Adicionada\nLa Secretaría de Educación, deberá coordinarse con las instituciones de educación privada, a efecto de que se apliquen las acciones señaladas en el presente artículo.\nPárrafo Reformado\nLey de Salud Mental del Estado de Baja California. Página 8\n.\nActualización Legislativa.\nÚltima Reforma P.O. No.33, Índice, 28-Jun-2024\nAsimismo, la Secretaría de Educación en coordinación con la Secretaría de Salud, implementará acciones similares a las previstas en las fracciones anteriores, respecto a la salud mental de las y los estudiantes de nivel medio superior.\nPárrafo Adicionado\nPárrafo Reformado\nArtículo Reformado\nArtículo 13.- Para la atención de la salud mental, la Secretaría y el Instituto, en coordinación con los demás Poderes del Estado del Estado, implementará acciones en materia de salud mental, a través de las áreas competentes. Garantizando que todos los internos de los centros de reinserción social de estado sean evaluados para la detección oportuna de una patología psiquiátrica, así como que reciban un tratamiento específico durante su reclusión.\nArtículo 14.- En las Unidades Médicas de los Centros de Detención de Adolescentes, coordinados por la Secretaria y el Instituto, se realizará una valoración psiquiátrica para la detección oportuna de alguna patología psiquiátrica, el tratamiento farmacológico o psicoterapéutico que el menor requiera, dando seguimiento por las áreas competentes de los mismos.\nArtículo 15.- Se implementarán programas para aprovechar los recursos disponibles en los reclusorios preventivos, como son el centro escolar y los diferentes talleres donde la persona usuaria de los servicios de salud mental se encuentre bajo custodia, con la finalidad de que pueda realizar actividades encaminadas a su rehabilitación.\nCapítulo Tercero\nInstituto de Psiquiatría del Estado de Baja California\nArtículo 16.- El Instituto de Psiquiatría del Estado de Baja California, es un órgano aplicables.\nArtículo 17.- Al Instituto, le corresponde:\nI. Elaborar el Plan Estatal de Salud Mental;\nII. Diseñar y evaluar políticas de prevención y atención integral en materia de promoción a la salud mental, educación para la salud mental, atención integral médicopsiquiátrica, rehabilitación integral y participación ciudadana, así como analizar y asesorar los planes y proyectos de las acciones para la atención de la salud mental;\nLey de Salud Mental del Estado de Baja California. Página 9\n.\nActualización Legislativa.\nÚltima Reforma P.O. No.33, Índice, 28-Jun-2024\nIII. La asignación de personal especializado en atención integral para cada uno de los trastornos que requieran atención prioritaria en base al presupuesto asignado;\nIV. Sensibilizar a la sociedad sobre los trastornos mentales y las alternativas para la solución de sus problemas como son terapias, pláticas y orientación en los Módulos de\nAtención en Salud Mental; centros ambulatorios de atención primaria con servicios de atención de salud mental y adicciones; centros hospitalarios; centros de salud y demás espacios para la atención de su problema;\nFracción Reformada\nV. Instalar, administrar y operar la línea telefónica de ayuda psicológica y de intervención en crisis y la página electrónica de Salud Mental, para brindar orientación y canalización, en su caso, las cuales deberán estar disponibles las 24 horas, los 365 días del año;\nVI. Diseñar y ejecutar de manera permanente en los medios de difusión masiva campañas educativas para orientar, motivar e informar a la población sobre el concepto de salud mental, los estigmas imperantes, los diversos trastornos mentales existentes, los síntomas que se presentan, las formas de prevención, y modos de atención, en coordinación con las dependencias e instituciones competentes;\nVII. Dar a conocer las acciones que procuran una vida saludable a través de actividades educativas, recreativas y cívicas;\nVIII. Motivar a la comunidad a la realización de acciones y proyectos que benefician a la salud;\nIX. Apoyar, asesorar, llevar registro, así como vigilancia a Grupos de Autoayuda;\nX. Fortalecer las acciones comunitarias que aseguren los factores de protección;\nXI. Diseñar y llevar a cabo campañas que reduzcan los factores de riesgo, y colaborar en el desarrollo de las mismas;\nXII. Participar en las acciones de atención a personas afectadas en situación de emergencia o desastre en el Estado;\nXIII. Instrumentar acciones de participación en redes sociales de Internet y en medios masivos de comunicación con la finalidad de proporcionar información precisa, objetiva y con base en criterios científicos, enfocada a la detección, la atención y la prevención de algún tipo de trastorno mental que induzca al suicidio;\nXIV. Detectar y manejar de manera oportuna conflictos en la convivencia en el núcleo familiar;\nLey de Salud Mental del Estado de Baja California. Página 10\n.\nActualización Legislativa.\nÚltima Reforma P.O. No.33, Índice, 28-Jun-2024\nXV. Informar acerca de las consecuencias del abandono, el maltrato y explotación de menores;\nXVI. Participar en la elaboración de planes en los que se informe a la comunidad sobre el desarrollo evolutivo y las posibles alteraciones en cada una de las etapas de desarrollo de las personas;\nXVII. Asesorar a los prestadores de servicios de salud mental privados, en la instalación, administración y operación de Módulos Comunitarios de Atención en Salud Mental;\nFracción Reformada\nXVIII. Asesorar en la instalación, administración y operación de las unidades de atención a la salud mental y de las adicciones o unidades de psiquiatría, en los centros ambulatorios de atención primaria y hospitales generales que cuente con este servicio; y,\nFracción Adicionada, recorriéndose la subsecuente\nXIX. Las demás que le otorgue la presente Ley y otras disposiciones legales aplicables.\nArtículo Reformado\nCuarto\nDel Consejo Estatal De Salud Mental\nArtículo 18.- El Consejo Estatal de Salud Mental de Baja California, es un órgano de consulta, análisis y asesoría para el desarrollo de planes, programas y proyectos que en materia de salud mental aplique el Gobierno federal y estatal y será integrado por:\nI. La persona titular del Poder Ejecutivo del Estado, quien lo Presidirá;\nFracción Reformada\nII. La persona titular de la Secretaría de Salud, que asumirá la vicepresidencia;\nFracción Reformada\nIII. La persona titular de la Dirección General del Instituto de Psiquiatría del Estado de\nBaja California, quien fungirá como Secretario Técnico, con voz pero sin voto; y,\nFracción Reformada\nIV. Las personas titulares de las siguientes dependencias del Estado:\nFracción Reformada\na) Secretaría de Seguridad Ciudadana;\nInciso Adicionado\nb) Secretaría de Bienestar;\nInciso Adicionado\nc) Secretaría de Educación; y,\nInciso Adicionado\nLey de Salud Mental del Estado de Baja California. Página 11\n.\nActualización Legislativa.\nÚltima Reforma P.O. No.33, Índice, 28-Jun-2024\nd) Secretaría de Hacienda.\nInciso Adicionado\nLas y los integrantes asistirán a las reuniones del Consejo, los cuales podrán nombrar a una persona suplente quien deberá tener como cargo mínimo un nivel inmediato inferior al de la persona titular.\nPárrafo Reformado\nLa Secretaría invitará a formar parte del Consejo de manera permanente, a una persona representante de los órganos colegiados de los gremios de profesionales de Salud\nMental en el Estado, del Colegio Estatal de Salud Pública, de la Universidad Autónoma de\nBaja California así como de Organizaciones Civiles que tengan amplia y reconocida experiencia en el tema. Las y los integrantes del Consejo tendrán derecho a voz y voto.\nPárrafo Reformado\nSerán invitados permanentes del Consejo, las y los diputados que presidan las\nComisiones de Salud, Justicia, Igualdad de Género y Juventudes, así como las comisiones que se instalen en materia de Derechos Humanos, Atención a Grupos Vulnerables de la\nSociedad y Asuntos de Equidad y Género del Congreso del Estado de Baja California.\nPárrafo Reformado\nA las sesiones podrán asistir como invitados, personas expertas en materia de salud mental, de los sectores público, social y privado que el pleno del Consejo considere para emitir opiniones, aportar información, o apoyar acciones sobre el tema que se defina. El\nReglamento determinará los lineamientos de operación del Consejo.\nArtículo Reformado\nArtículo 19.- Los cargos en el Consejo serán honoríficos. Las facultades, del\nPresidente y demás integrantes, se establecerán en el Reglamento Interno que para tal efecto se expida.\nArtículo 20.- El Consejo tendrá las siguientes atribuciones:\nI. Diseñar y evaluar políticas de prevención y atención integral en materia de promoción a la salud mental, educación para la salud mental, atención integral médicopsiquiátrica, rehabilitación integral y participación ciudadana;\nII. Solicitar a la Secretaría y al Instituto un informe de los avances relacionados con\nPlan Estatal de Salud Mental\nIII. Solicitar en cualquier momento datos relativos a la erogación de los recursos asignados en materia de salud mental y, en su caso, podrá proponer estrategias para optimizar su ejecución, conforme a la realidad social;\nLey de Salud Mental del Estado de Baja California. Página 12\n.\nActualización Legislativa.\nÚltima Reforma P.O. No.33, Índice, 28-Jun-2024\nIV. Suscribir convenios, acuerdos o cualquier instrumento jurídico de coordinación con los Estados y Municipios de la región noroeste del país a efecto de mejorar la atención en materia de salud mental;\nV. Analizar y asesorar los planes y proyectos de las acciones para la atención de la salud mental en el Estado de Baja California, así como la participación ciudadana;\nVI. Funcionar como un organismo de consulta permanente de planes, proyectos y programas encaminados hacia la atención integral de la salud mental;\nVII. Desempeñarse como un organismo de vinculación entre los sectores público, social y privado, en materia de salud mental, para la implementación de estrategias que beneficien a la población, y\nVIII. Las demás que le reconozca la presente Ley y demás disposiciones normativas aplicables.\nCapítulo Quinto\nDel Financiamiento En Salud Mental\nArtículo 21.- La inversión en materia de salud mental constituye una acción de interés social, por ello resulta indispensable el financiamiento de las acciones a que se refiere la presente ley.\nArtículo 22.- Son obligaciones del Gobierno del Estado incluir una partida no menor al\n5% del presupuesto total destinado a la salud, que garantice a la Secretaría y al Instituto cumplir con los objetivos señalados en la presente ley, para ser invertido en la planeación, organización, operación, supervisión y evaluación de la prestación de los servicios en materia de salud mental.\nArtículo 23.- La Secretaría deberá considerar en la erogación del recurso asignado, primaria con servicios de salud mental y de adicciones, a efecto de incrementar la cobertura de los servicios de salud mental en el Estado de Baja California.\nArtículo Reformado\nArtículo 24.- La Secretaría fomentará la aportación de recursos económicos y en especie para la atención de la salud mental por parte de los sectores social y privado.\nCapítulo Sexto\nDe Las Sanciones Y Recurso De Inconformidad\nLey de Salud Mental del Estado de Baja California. Página 13\n.\nActualización Legislativa.\nÚltima Reforma P.O. No.33, Índice, 28-Jun-2024\nArtículo 25.- Las violaciones a los preceptos de esta ley, su reglamento y demás disposiciones legales que de ella emanen, serán sancionadas administrativamente, en el ámbito de su competencia, por:\nPárrafo Reformado\nI. La Secretaría de la Honestidad y Función Pública, órganos de control interno, y por la Sala Especializada en materia de Responsabilidades Administrativas y Combate a la\nCorrupción del Tribunal Estatal de Justicia Administrativa, según corresponda; y,\nFracción Reformada\nII. La Comisión Estatal para la Protección Contra Riesgos Sanitarios (COEPRIS).\nFracción Reformada\nLo anterior, sin menoscabo de las sanciones que establezcan otros ordenamientos jurídicos.\nArtículo Reformado\nArtículo 26.- Las autoridades a que se refiere la fracción I del artículo anterior, son competente, según corresponda, para vigilar y sancionar las acciones u omisiones que cometan los servidores públicos que deriven en incumplimiento del presente ordenamiento, de conformidad con la Ley de Responsabilidades Administrativas del Estado de Baja\nCalifornia.\nArtículo Reformado\nArtículo 27.- La COEPRIS vigilará, regulará y sancionará las contravenciones a las disposiciones señaladas en la presente ley, sólo para el caso de los establecimientos que brindan servicios de salud mental.\nArtículo Reformado\nArtículo 28.- Contra los actos y resoluciones definitivas que deriven de la aplicación de la presente ley, el interesado podrá interponer los recursos previstos en la Ley Estatal para los actos de administración pública del Estado de Baja California.\nARTÍCULOS TRANSITORIOS\nPRIMERO.- La presente Ley entrara en vigor al día siguiente al de su publicación en el Periódico Oficial del Estado de Baja California.\nSEGUNDO.- El reglamento interior a que hace referencia la presente Ley, deberá emitirse en un plazo no mayor a 180 días naturales contados a partir del inicio de la vigencia de la presente Ley.\nTERCERO.- Para el cumplimiento de las facultades conferidas en la presente Ley, deberán preverse los recursos presupuestales necesarios.\nCUARTO.- Para dar debido cumplimiento a lo establecido en el artículo 22 de la presente ley, se estará sujeto a la capacidad presupuestal del Ejecutivo del Estado para el ejercicio fiscal 2018;\nLey de Salud Mental del Estado de Baja California. Página 14\n.\nActualización Legislativa.\nÚltima Reforma P.O. No.33, Índice, 28-Jun-2024 debiendo contemplarse en la planeación presupuestal para los años subsecuentes, a partir del presupuesto de egresos 2019 del Ejecutivo del Estado.\nDADO en el Salón de Sesiones “Lic. Benito Juárez García” del H. Poder Legislativo del\nEstado de Baja California, en la Ciudad de Mexicali, B.C., a los veinticinco días del mes de enero del año dos mil dieciocho.\nDIP. MTRO. RAÚL CASTAÑEDA POMPOSO\nPRESIDENTE\n(RÚBRICA)\nDIP. ROCÍO LÓPEZ GOROSAVE\nSECRETARIA\n(RÚBRICA)\nDE CONFORMIDAD CON LO DISPUESTO POR LA FRACCIÓN I DEL ARTÍCULO 49\nMEXICALI, BAJA CALIFORNIA, A LOS VEINTIUN DÍAS DE FEBRERO DEL AÑO\nDOS MIL DIECIOCHO.\nFRANCISCO ARTURO VEGA DE LAMADRID\nGOBERNADOR DEL ESTADO\n(RÚBRICA)\nFRANCISCO RUEDA GÓMEZ\nSECRETARIO GENERAL DE GOBIERNO\n(RÚBRICA)\nLey de Salud Mental del Estado de Baja California. Página 15\n.\nActualización Legislativa.\nÚltima Reforma P.O. No.33, Índice, 28-Jun-2024\nArtículo 1.- Fue reformado por Decreto No. 380, publicado en el Periódico Oficial No.\n7, de fecha 09 de febrero de 2024, Índice, Tomo CXXXI, expedido por la H. XXIV\nLegislatura, siendo Gobernadora Constitucional la C. Marina del Pilar Ávila Olmeda, 20212027;\nArtículo 3.- Fue reformado por Decreto No. 380, publicado en el Periódico Oficial No.\n7, de fecha 09 de febrero de 2024, Índice, Tomo CXXXI, expedido por la H. XXIV\nLegislatura, siendo Gobernadora Constitucional la C. Marina del Pilar Ávila Olmeda, 20212027;\nArtículo 5.- Fue reformado por Decreto No. 380, publicado en el Periódico Oficial No.\n7, de fecha 09 de febrero de 2024, Índice, Tomo CXXXI, expedido por la H. XXIV\nLegislatura, siendo Gobernadora Constitucional la C. Marina del Pilar Ávila Olmeda, 20212027;\nArtículo 7.- Fue reformado por Decreto No. 380, publicado en el Periódico Oficial No.\n7, de fecha 09 de febrero de 2024, Índice, Tomo CXXXI, expedido por la H. XXIV\nLegislatura, siendo Gobernadora Constitucional la C. Marina del Pilar Ávila Olmeda, 20212027;\nArtículo 10.- Fue reformado por Decreto No. 132, publicado en el Periódico Oficial No.\n56, de fecha 19 de septiembre de 2022, Sección III, TOMO CXXIX; expedido por la H. XXIV\nLegislatura, siendo Gobernadora Constitucional la C. Marina del Pilar Ávila Olmeda 20212027; fue reformado por Decreto No. 306, publicado en el Periódico Oficial No. 62, de fecha\n06 de noviembre de 2023, Índice, Tomo CXXX, expedido por la H. XXIV Legislatura, siendo\nGobernadora Constitucional la C. Marina del Pilar Ávila Olmeda 2021-2027; fue reformado por Decreto No. 380, publicado en el Periódico Oficial No. 7, de fecha 09 de febrero de 2024, Índice, Tomo CXXXI, expedido por la H. XXIV Legislatura, siendo Gobernadora\nConstitucional la C. Marina del Pilar Ávila Olmeda, 2021-2027;\nArtículo 12.- Fue reformado por Decreto No. 308, publicado en el Periódico Oficial No.\n62, de fecha 06 de noviembre de 2023, Índice, Tomo CXXX, expedido por la H. XXIV\nLegislatura, siendo Gobernadora Constitucional la C. Marina del Pilar Ávila Olmeda 20212027; fue reformado por Decreto No. 380, publicado en el Periódico Oficial No. 7, de fecha\nGobernadora Constitucional la C. Marina del Pilar Ávila Olmeda, 2021-2027; fue reformado\nÍndice, Tomo CXXXI, expedido por la H. XXIV Legislatura, siendo Gobernadora\nConstitucional la C. Marina del Pilar Ávila Olmeda, 2021-2027;\nArtículo 17.- Fue reformado por Decreto No. 380, publicado en el Periódico Oficial No.\nLegislatura, siendo Gobernadora Constitucional la C. Marina del Pilar Ávila Olmeda, 20212027;\nLey de Salud Mental del Estado de Baja California. Página 16\n.\nActualización Legislativa.\nÚltima Reforma P.O. No.33, Índice, 28-Jun-2024\nArtículo 18.- Fue reformado por Decreto No. 308, publicado en el Periódico Oficial No.\n62, de fecha 06 de noviembre de 2023, Índice, Tomo CXXX, expedido por la H. XXIV\nLegislatura, siendo Gobernadora Constitucional la C. Marina del Pilar Ávila Olmeda 20212027;\nArtículo 23.- Fue reformado por Decreto No. 380, publicado en el Periódico Oficial No.\n7, de fecha 09 de febrero de 2024, Índice, Tomo CXXXI, expedido por la H. XXIV\nLegislatura, siendo Gobernadora Constitucional la C. Marina del Pilar Ávila Olmeda, 20212027;\nArtículo 25.- Fue reformado por Decreto No. 380, publicado en el Periódico Oficial No.\n7, de fecha 09 de febrero de 2024, Índice, Tomo CXXXI, expedido por la H. XXIV\nLegislatura, siendo Gobernadora Constitucional la C. Marina del Pilar Ávila Olmeda, 20212027;\nArtículo 26.- Fue reformado por Decreto No. 380, publicado en el Periódico Oficial No.\nLegislatura, siendo Gobernadora Constitucional la C. Marina del Pilar Ávila Olmeda, 20212027;\nArtículo 27.- Fue reformado por Decreto No. 380, publicado en el Periódico Oficial No.\nLegislatura, siendo Gobernadora Constitucional la C. Marina del Pilar Ávila Olmeda, 20212027;\nLey de Salud Mental del Estado de Baja California. Página 17\n.\nActualización Legislativa.\nÚltima Reforma P.O. No.33, Índice, 28-Jun-2024\nARTÍCULO PRIMERO TRANSITORIO DEL DECRETO No. 132, POR EL QUE SE\nREFORMA EL ARTÍCULO 10, PUBLICADO EN EL PERIÓDICO OFICIAL No. 56, SECCIÓN\nIII, TOMO CXXIX, DE FECHA 19 DE SEPTIEMBRE DE 2022, EXPEDIDO POR LA H. XXIV\nLEGISLATURA, SIENDO GOBERNADORA CONSTITUCIONAL LA C. MARINA DEL PILAR\nÁVILA OLMEDA 2021-2027.\nTRANSITORIO\nÚNICO. Las presentes reformas entraran en vigor al día siguiente de su publicación en el Periódico Oficial del Estado.\nDADO en Sesión Ordinaria de la XXIV Legislatura en la Ciudad de Mexicali, B.C., a los veinticinco días del mes de agosto del año dos mil veintidós.\nDIP. ALEJANDRA MARÍA ANG HERNÁNDEZ\nPRESIDENTA\n(RÚBRICA)\nDIP. DUNNIA MONTSERRAT MURILLO LÓPEZ\nSECRETARIA\n(RÚBRICA)\nDE CONFORMIDAD CON LO DISPUESTO POR LA FRACCIÓN I DEL ARTÍCULO 49\nCALIFORNIA, IMPRÍMASE Y PUBLÍQUESE.\nMEXICALI, BAJA CALIFORNIA, A LOS CINCO DÍAS DEL MES DE SEPTIEMBRE\nDEL AÑO DOS MIL VEINTIDÓS.\nMARINA DEL PILAR ÁVILA OLMEDA\nGOBERNADORA DEL ESTADO\nDE BAJA CALIFORNIA\n(RÚBRICA)\nCATALINO ZAVALA MÁRQUEZ\nSECRETARIO GENERAL DE GOBIERNO\nDEL ESTADO DE BAJA CALIFORNIA\n(RÚBRICA)\nARTÍCULO ÚNICO TRANSITORIO DEL DECRETO No. 306, POR EL QUE SE\nAPRUEBA LA REFORMA AL ARTÍCULO 10; PUBLICADO EN EL PERIÓDICO OFICIAL No.\nH. XXIV LEGISLATURA, SIENDO GOBERNADORA CONSTITUCIONAL LA C. MARINA\nDEL PILAR ÁVILA OLMEDA 2021-2027.\nLey de Salud Mental del Estado de Baja California. Página 18\n.\nActualización Legislativa.\nÚltima Reforma P.O. No.33, Índice, 28-Jun-2024\nTRANSITORIO\nÚNICO.- El presente decreto entrará en vigor a partir del día siguiente de su publicación en el Periódico Oficial del Estado de Baja California.\nDADO en Sesión Ordinaria de la XXIV Legislatura en la Ciudad de Mexicali, B.C., a los diecinueve días del mes de octubre del año dos mil veintitrés.\nDIP. MANUEL GUERRERO LUNA\nPRESIDENTE\n(RÚBRICA)\nDIP. DUNNIA MONTSERRAT MURILLO LÓPEZ\nSECRETARIA\n(RÚBRICA)\nDE CONFORMIDAD CON LO DISPUESTO POR LA FRACCIÓN I DEL ARTÍCULO 49\nCALIFORNIA, IMPRÍMASE Y PUBLÍQUESE.\nMEXICALI, BAJA CALIFORNIA, A LOS VEINTITRÉS DÍAS DEL MES DE OCTUBRE\nDEL AÑO DOS MIL VEINTITRÉS.\nMARINA DEL PILAR ÁVILA OLMEDA\nGOBERNADORA DEL ESTADO\nDE BAJA CALIFORNIA\n(RÚBRICA)\nCATALINO ZAVALA MÁRQUEZ\nSECRETARIO GENERAL DE GOBIERNO\nDEL ESTADO DE BAJA CALIFORNIA\n(RÚBRICA)\nARTÍCULO PRIMERO TRANSITORIO DEL DECRETO No. 308, POR EL QUE SE\nAPRUEBA LA REFORMA A LOS ARTÍCULOS 12 Y 18; PUBLICADO EN EL PERIÓDICO\nEXPEDIDO POR LA H. XXIV LEGISLATURA, SIENDO GOBERNADORA\nCONSTITUCIONAL LA C. MARINA DEL PILAR ÁVILA OLMEDA 2021-2027.\nTRANSITORIOS\nPRIMERO.- El presente Decreto entrará en vigor al día siguiente de su publicación en el\nPeriódico Oficial del Estado.\nLey de Salud Mental del Estado de Baja California. Página 19\n.\nActualización Legislativa.\nÚltima Reforma P.O. No.33, Índice, 28-Jun-2024\nSEGUNDO.- Las autoridades educativas del Estado en un plazo de seis meses contados a partir de la vigencia del presente Decreto, actualizarán y/o emitirán los programas o protocolos de promoción, prevención y abordaje de la salud mental de los estudiantes.\nDADO en Sesión Ordinaria de la XXIV Legislatura en la Ciudad de Mexicali, B.C., a los diecinueve días del mes de octubre del año dos mil veintitrés.\nDIP. MANUEL GUERRERO LUNA\nPRESIDENTE\n(RÚBRICA)\nDIP. DUNNIA MONTSERRAT MURILLO LÓPEZ\nSECRETARIA\n(RÚBRICA)\nDE CONFORMIDAD CON LO DISPUESTO POR LA FRACCIÓN I DEL ARTÍCULO 49\nCALIFORNIA, IMPRÍMASE Y PUBLÍQUESE.\nMEXICALI, BAJA CALIFORNIA, A LOS VEINTITRÉS DÍAS DEL MES DE OCTUBRE\nDEL AÑO DOS MIL VEINTITRÉS.\nMARINA DEL PILAR ÁVILA OLMEDA\nGOBERNADORA DEL ESTADO\nDE BAJA CALIFORNIA\n(RÚBRICA)\nCATALINO ZAVALA MÁRQUEZ\nSECRETARIO GENERAL DE GOBIERNO\nDEL ESTADO DE BAJA CALIFORNIA\n(RÚBRICA)\nARTÍCULO SEGUNDO TRANSITORIO DEL DECRETO No. 380, POR EL QUE SE\nAPRUEBAN LAS REFORMAS A LOS ARTÍCULOS 1, 3, 5, 7, 10, 12, 17, 23, 25, 26 Y 27;\nÍNDICE, TOMO CXXXI, EXPEDIDO POR LA H. XXIV LEGISLATURA, SIENDO\nGOBERNADORA CONSTITUCIONAL LA C. MARINA DEL PILAR ÁVILA OLMEDA 2021-\n2027.\nTRANSITORIOS:\nPRIMERO.- El presente Decreto entrará en vigor al día siguiente de su publicación en el\nPeriódico Oficial del Estado.\nLey de Salud Mental del Estado de Baja California. Página 20\n.\nActualización Legislativa.\nÚltima Reforma P.O. No.33, Índice, 28-Jun-2024\nSEGUNDO.- Para la ejecución y cumplimiento de las disposiciones contenidas en el presente Decreto, se realizarán de forma gradual y progresiva, considerando los recursos disponibles. Para su cabal cumplimiento, se estará a la actualización de normas y disposiciones reglamentarias a que se refiere el artículo transitorio tercero del DECRETO por el que se reforman, adicionan y derogan diversas disposiciones de la Ley General de Salud, en materia de Salud Mental y Adicciones, publicado el 16 de mayo de 2022 en el Diario\nOficial de la Federación.\nTERCERO.- Para garantizar el acceso y continuidad de la atención de la salud mental y adicciones, el Poder Ejecutivo del Estado deberá implementar un programa para disponer de establecimientos o centros ambulatorios de atención primaria y servicios de psiquiatría en hospitales generales del sector público, en la totalidad de los municipios de la entidad, iniciando preferentemente en el municipio en donde la población requiera mayor servicio en la atención de la salud mental, mediante la creación de un centro ambulatorio o la habilitación de una unidad de psiquiatría en el Hospital General respectivo.\nDADO en Sesión Ordinaria de la XXIV Legislatura en la Ciudad de Mexicali, B.C., a los veinticinco días del mes de enero del año dos mil veinticuatro.\nDIP. ARACELI GERALDO NÚÑEZ\nPRESIDENTA\n(RÚBRICA)\nDIP. MANUEL GUERRERO LUNA\nSECRETARIO\n(RÚBRICA)\nDE CONFORMIDAD CON LO DISPUESTO POR LA FRACCIÓN I DEL ARTÍCULO 49 DE\nCALIFORNIA, IMPRÍMASE Y PUBLÍQUESE.\nMEXICALI, BAJA CALIFORNIA, A LOS VEINTINUEVE DÍAS DEL MES DE ENERO\nDEL AÑO DOS MIL VEINTICUATRO.\nMARINA DEL PILAR ÁVILA OLMEDA\nGOBERNADORA DEL ESTADO\nDE BAJA CALIFORNIA\n(RÚBRICA)\nALFREDO ÁLVAREZ CÁRDENAS\nSECRETARIO GENERAL DE GOBIERNO\nDEL ESTADO DE BAJA CALIFORNIA\n(RÚBRICA)\nLey de Salud Mental del Estado de Baja California. Página 21\n.\nActualización Legislativa.\nÚltima Reforma P.O. No.33, Índice, 28-Jun-2024\nARTÍCULO ÚNICO TRANSITORIO DEL DECRETO No. 437, POR EL QUE SE\nAPRUEBA LA REFORMA AL ARTÍCULO 12; PUBLICADO EN EL PERIÓDICO OFICIAL No.\n33, DE FECHA 28 DE JUNIO DE 2024, ÍNDICE, TOMO CXXXI, EXPEDIDO POR LA H.\nXXIV LEGISLATURA, SIENDO GOBERNADORA CONSTITUCIONAL LA C. MARINA DEL\nPILAR ÁVILA OLMEDA 2021-2027.\nTRANSITORIOS\nPRIMERO.- La presente reforma entrará en vigor al día siguiente al de su publicación en el\nPeriódico Oficial del Estado.\nSEGUNDO.- La aplicación de la presente reforma una vez aprobada, estará sujeta a la disponibilidad presupuestaria con base a la normatividad aplicable.\nDADO en Sesión Ordinaria de la XXIV Legislatura en la Ciudad de Mexicali, B.C., a los veinte días del mes de junio del año dos mil veinticuatro.\nDIP. RAMÓN VÁZQUEZ VALADEZ\nPRESIDENTE\n(RÚBRICA)\nDIP. MANUEL GUERRERO LUNA\nSECRETARIO\n(RÚBRICA)\nDE CONFORMIDAD CON LO DISPUESTO POR LA FRACCIÓN I DEL ARTÍCULO 49 DE\nCALIFORNIA, IMPRÍMASE Y PUBLÍQUESE.\nMEXICALI, BAJA CALIFORNIA, A LOS VEINTICUATRO DÍAS DEL MES DE JUNIO\nDEL AÑO DOS MIL VEINTICUATRO.\nMARINA DEL PILAR ÁVILA OLMEDA\nGOBERNADORA DEL ESTADO\nDE BAJA CALIFORNIA\n(RÚBRICA)\nALFREDO ÁLVAREZ CÁRDENAS\nSECRETARIO GENERAL DE GOBIERNO\nDEL ESTADO DE BAJA CALIFORNIA\n(RÚBRICA)\nLey de Salud Mental del Estado de Baja California. Página 22",
  "ordenamiento": "REGLAMENTO",
  "jurisdiccion": "BAJA CALIFORNIA",
  "fuente_oficial": "Periódico Oficial",
  "FECHA PER OFIC": "2024/06/28",
  "ESTATUS": "VIGENTE",
  "TOMO": "TOMO_VI",
  "URL": "https://www.congresobc.gob.mx/Documentos/ProcesoParlamentario/Leyes/TOMO_VI/20240628_LEYSALMENTAL.PDF",
  "es_escaneado": false,
  "tiene_tablas": false,
  "materia": [
    "social",
    "salud",
    "educación",
    "cultura"
  ]
}