{
  "titulo": "Ley QUE CREA EL CENTRO DE JUSTICIA PARA LAS MUJERES DEL ESTADO DE BAJA CALIFORNIA",
  "Contenido": "DEL ESTADO DE BAJA CALIFORNIA\nPublicado en el Periódico Oficial No. 57, de fecha 11 de diciembre de 2015, Sección I, Tomo CXXII\nCAPÍTULO I\nDE SU NATURALEZA, OBJETO Y DOMICILIO\nARTÍCULO 1. La presente Ley es de orden público, interés social y observancia general en el Estado de Baja California en materia de coordinación y vinculación interinstitucional de las áreas de procuración de justicia, seguridad pública, salud, educación y todas aquellas que de acuerdo a las facultades establecidas en la normatividad local contribuyan a prevenir, sancionar, atender y erradicar la violencia en contra de las mujeres, las adolescentes y las niñas.\nArtículo Reformado\nARTÍCULO 2.- Se crea el Centro de Justicia para las Mujeres del Estado de\nBaja California como un organismo descentralizado de la administración pública del Estado, con personalidad jurídica, patrimonio propio y autonomía de gestión para el cumplimiento de sus fines, el cual contará con la estructura administrativa que determine su reglamentación interior y que se integrará por la representación de las autoridades que se contemplan en esta Ley.\nPárrafo Reformado\nEl Centro de Justicia para las Mujeres del Estado de Baja California, tendrá su domicilio legal en el municipio de Tijuana; y podrán establecerse oficinas o delegaciones en el Estado priorizando los municipios con mayor índice de violencia contra las mujeres, las adolescentes y las niñas.\nPárrafo Adicionado\nArtículo Reformado\nARTÍCULO 3. Para los efectos de esta Ley, se entenderá por:\nI. Centro: Centro de Justicia para las Mujeres del Estado de Baja California;\nFracción Reformada\nII. Junta de Gobierno: Órgano rector del Centro;\nFracción Reformada\nIII. Ley: Ley que Crea el Centro de Justicia para las Mujeres del Estado de\nBaja California;\nFracción Reformada\nIV. Ley Paraestatal: Ley de las Entidades Paraestatales del Estado de Baja\nCalifornia.\nV. Órgano Interno de Control: La unidad administrativa encargada de promover, evaluar y fortalecer el buen funcionamiento del control interno del\nCentro, así como la aplicación de lo dispuesto en la Ley de Responsabilidades\nAdministrativas del Estado de Baja California.\nFracción Adicionada\nArtículo Reformado\nARTÍCULO 4. El Centro es un espacio multidisciplinario e interinstitucional que tiene como objeto brindar, de manera gratuita, atención integral a mujeres víctimas de violencia de género, así como a sus hijas e hijos menores de dieciocho años de edad, desde las perspectivas de género, derechos humanos, intercultural, diferencial e interseccional, mediante la prestación de servicios en un mismo lugar, con la finalidad de promover y garantizar su acceso a la justicia, el ejercicio pleno de sus derechos humanos y su empoderamiento. Asimismo, tendrá por objeto:\nPárrafo Reformado\nI. Brindar un ambiente seguro y confiable para mujeres víctimas de violencia y para sus hijas e hijos;\nII. Contribuir a la reducción de la tasa de violencia contra las mujeres;\nIII. Fomentar la cultura de la no violencia, con la finalidad de reducir la impunidad;\nIV. Evitar la re victimización de las mujeres víctimas de violencia;\nV. Generar estudios, información y estadística sobre la violencia contra las mujeres, sus causas y consecuencias; y\nVI. Consolidar un equipo multidisciplinario profesionalizado y acreditado en el tema de violencia contra las mujeres.\nArtículo Reformado\nARTÍCULO 4 BIS.- El Centro deberá proporcionar o gestionar que por conducto de las autoridades correspondientes se brinden de manera gratuita, como mínimo los siguientes servicios:\nI. Atención médica y psicológica, incluyendo atención terapéutica de contención emocional;\nII. Asesoría y orientación jurídica;\nIII. Representación legal en materias penal, familiar, civil y demás que se requieran, en los términos que dispongan las leyes;\nIV. Gestión de expedición de documentación oficial;\nV. Servicios de albergue temporal o tránsito;\nVI. Servicios de cuidado y atención infantil;\nVII. Servicios de trabajo social;\nVIII. Servicios de protección de seguridad a víctimas en situación de riesgo grave o falta de red de apoyo familiar o comunitario para lo cual se coordinarán con los refugios para víctimas de violencia;\nIX. Acceso a la justicia a través de agencias del Ministerio Público especializadas en violencia contra las mujeres;\nX. Asesoría, capacitación y servicios para el empoderamiento social y económico;\nXI. Gestionar el acceso a servicios educativos;\nXII. Programas de incorporación de las mujeres víctimas de violencia al mercado laboral; y,\nXIII. Los demás servicios que contribuyan al acceso de las mujeres a una vida libre de violencia.\nEl Centro facilitará el acceso a la justicia las 24 horas todos los días del año, y se deberá garantizar que en los servicios que se brinden se cuente con personas intérpretes de lenguas indígenas, así como condiciones de accesibilidad para mujeres con discapacidad, incluidas personas intérpretes de lengua de señas mexicana y asistencia personal en caso de que se requiera.\nLos servicios se proporcionarán con independencia de que exista o no una denuncia por los hechos de violencia.\nArtículo Adicionado\nARTÍCULO 4 TER.- Los servicios que brinde el Centro deberán ejecutarse bajo los principios previstos en el artículo 4 de la Ley General de Acceso de las\nMujeres a una Vida Libre de Violencia.\nArtículo Adicionado\nARTÍCULO 5. Para el cumplimiento de su objeto, el Centro tendrá las siguientes atribuciones:\nI. Coordinar interinstitucionalmente a las autoridades competentes para la debida diligencia y desde la perspectiva de género, así como el ejercicio programas establecidos para ello, realizando las gestiones ante las autoridades competentes;\nFracción Reformada\nII. Procurar el acceso rápido y eficaz a los programas establecidos en las diferentes áreas de la administración pública en beneficio de las mujeres;\nIII. Diseñar y ejecutar acciones, programas y planes de coordinación con las autoridades en materia de prevención, sanción, atención y erradicación de la violencia contra las mujeres, las adolescentes y las niñas;\nFracción Reformada\nIV. Promover entre las autoridades de la administración pública un ejercicio humanizado y solidario ante las mujeres para evitar fenómenos de violencia institucional;\nV. Solicitar los mecanismos de financiamiento con recursos federales a través de los programas, estatales y municipales para mejorar el funcionamiento y equipamiento de sus instalaciones;\nFracción Reformada\nVI. Promover la participación y colaboración de todos los organismos públicos y privados que realizan actividades o tienen funciones afines al Objeto del\nCentro;\nVII. Promover ante las autoridades competentes las órdenes y medidas provisionales necesarias para salvaguardar la integridad de las mujeres, así como la de sus hijas e hijos menores de dieciocho años de edad, incluyendo su solicitud y prórroga;\nFracción Reformada\nVIII. Coadyuvar en el diseño de planes y programas de prevención y educación que impartan las dependencias públicas con la intención de fomentar los valores de la no violencia y el respeto e igualdad de derechos entre mujeres y hombres.\nIX. Diseñar e implementar acciones que eviten la victimización secundaria de las mujeres víctimas de violencia;\nFracción Adicionada\nX. Garantizar a las mujeres información sobre los mecanismos de acceso a la justicia. A las mujeres con discapacidad, se les podrá brindar asistencia temporal, y a las mujeres, adolescentes y niñas sordas, en su caso, teléfonos de emergencias adaptados;\nFracción Adicionada\nXI. Proporcionar orientación y asesoría jurídica, así como representación dieciocho años de edad;\nFracción Adicionada\nXII. Facilitar a las mujeres víctimas de violencia, así como a sus hijas e hijos menores de dieciocho años de edad, el acceso a los servicios de salud, trabajo social y de empoderamiento económico y social;\nFracción Adicionada\nXIII. Asegurar la aplicación de los ajustes de procedimiento para que las mujeres con discapacidad puedan ejercer efectivamente sus derechos;\nFracción Adicionada\nXIV. Gestionar ante autoridades públicas e instituciones privadas los apoyos necesarios para que las mujeres con discapacidad puedan tener acceso a los servicios que proporciona el Centro;\nFracción Adicionada\nXV. Realizar visitas domiciliarias en hogares, instituciones públicas o privadas, donde se encuentren mujeres con discapacidad que probablemente estén siendo víctimas de violencia, así como gestionar los apoyos y medidas de protección necesarias para salvaguardar su integridad personal. Se podrán realizar estas visitas cuando exista información suficiente sobre la ocurrencia de los hechos, incluso mediante denuncia anónima. Las mujeres con discapacidad pueden rehusarse a la entrevista durante estas visitas cuando estén en condiciones de manifestarlo; y,\nFracción Adicionada\nXVI. Las demás que le confieran los ordenamientos legales aplicables, sin perjuicio de las atribuciones que correspondan a otras autoridades en el ámbito de sus competencias.\nFracción Adicionada\nArtículo Reformado\nCAPÍTULO II\nDEL ÓRGANO DE GOBIERNO\nDenominación del Capítulo Modificada\nARTÍCULO 6. El Centro, en concordancia con la Ley Paraestatal estará a cargo de una Junta de Gobierno y de una persona Titular.\nArtículo Reformado\nARTÍCULO 7. La Junta de Gobierno, es el órgano rector del Centro, y estará integrada por la persona titular de las siguientes dependencias, entidades y organismos:\nPárrafo Reformado presidirá;\nII. La Secretaría de Hacienda;\nFracción Reformada\nIII. La Secretaría de Educación;\nFracción Reformada\nIV. La Secretaría de Salud;\nV. La Fiscalía General del Estado;\nFracción Reformada\nVI. La Secretaría de Seguridad Ciudadana;\nFracción Reformada\nVII. La Secretaría de Bienestar;\nFracción Reformada\nVIII. La Dirección del Sistema Estatal para el Desarrollo Integral de la\nFamilia;\nIX. La Dirección General del Instituto Estatal de la Mujer;\nX. Una persona representante de la Administración Pública Municipal; y,\nFracción Reformada\nXI. Una persona representante de la Sociedad Civil.\nFracción Reformada\nEn el caso de la persona representante de la Administración Municipal, lo será del municipio bajacaliforniano en donde se encuentre ubicado el Centro.\nPárrafo Reformado\nPor cada persona integrante de la Junta de Gobierno existirá una suplente debidamente acreditada para ejercer las facultades de la persona titular integrante ante la Junta, y quien tendrá por lo menos el cargo de director de área o su equivalente, salvo la representación a que se refiere la fracción XI de este artículo.\nPárrafo Reformado\nGobierno, teniendo solo derecho a voz en el desarrollo de sus sesiones.\nPárrafo Adicionado\nArtículo Reformado\nARTÍCULO 8. Podrán participar en las sesiones de la Junta de Gobierno solo con derecho a voz en calidad de invitadas:\nPárrafo Reformado\nI. La Presidencia del Tribunal Superior de Justicia;\nFracción Reformada\nII. La Titularidad de la Comisión Estatal de Derechos Humanos, y\nFracción Reformada\nIII. Las y los representantes de organizaciones sociales afines a las actividades del Centro.\nFracción Reformada\nArtículo Reformado\nARTÍCULO 9. Las personas integrantes de la Junta de Gobierno contemplados en las fracciones I a la IX del artículo siete de esta Ley, durarán en su cargo en tanto sean titulares de las Dependencias, entidades u organismos de que se trate. Los cargos serán honoríficos.\nArtículo Reformado\nARTÍCULO 10. Las Sesiones que celebre la Junta de Gobierno, serán ordinarias y extraordinarias. Las primeras se llevarán a cabo cuando menos cuatro veces al año, en forma trimestral, teniendo la persona que preside la Junta de\nGobierno, la facultad de convocar a las demás personas integrantes para la celebración de sesiones.\nPárrafo Reformado\nPara la validez de las sesiones se deberá contar con la mitad más uno de sus integrantes, y las decisiones se tomarán por mayoría de votos, contando con voto de calidad la Persona Titular de la Presidencia.\nPárrafo Reformado\nArtículo Reformado\nARTÍCULO 11. Las reglas de organización de las sesiones de la Junta se regularán por su Reglamento Interno.\nARTÍCULO 12. Corresponde a la Junta de Gobierno:\nI. Establecer las políticas generales y definir las prioridades a las que deberá sujetarse el Centro de Justicia para las Mujeres del Estado de Baja\nCalifornia en congruencia con el Plan estatal de Desarrollo;\nII. Aprobar su presupuesto anual de Ingresos y Egresos del Centro;\nIII. Expedir el Reglamento Interno y aprobar la organización administrativa del Centro;\nIV. Se deroga;\nFracción Derogada\nV. Aprobar anualmente los estados financieros del Centro;\nVI. Aprobar de acuerdo con las leyes y políticas aplicables, las bases y programas generales que regulen los convenios, contratos, pedidos o acuerdos que deba celebrar el Centro con terceros en materia de obra pública, adquisiciones, arrendamientos y prestaciones de servicios;\nVII. Otorgar en favor de la Persona Titular del Centro Poder General para pleitos y cobranzas, actos de administración y dominio, con todas las facultades generales y las especiales que requieran cláusula especial conforme a la Ley;\nFracción Reformada\nVIII. Analizar y aprobar, en su caso, los informes periódicos que rinda la\nPersona Titular del Centro; y,\nFracción Reformada\nIX. Autorizar la creación de los comités o grupos especializados de apoyo institucional.\nArtículo Reformado\nCAPÍTULO III\nDE LA PERSONA TITULAR DEL CENTRO\nDenominación del Capítulo modificada\nARTÍCULO 13. Al frente del Centro estará la Persona Titular del Centro a quien se designará y removerá libremente por la persona Titular del Poder\nEjecutivo del Estado.\nArtículo Reformado\nARTÍCULO 14. Para ocupar la titularidad del Centro, se deberá cumplir con los siguientes requisitos:\nPárrafo Reformado\nI. Estar en pleno goce y ejercicio de sus derechos;\nII. Contar con Título Profesional;\nIII. Ser mayor de treinta años y menor de sesenta y cinco al momento de su designación;\nIV. Acreditar tener una residencia mínima de cinco años en el Estado;\nV. No ser ministra o ministro de ningún culto religioso ni líder partidista;\nFracción Reformada\nVI. No haber obtenido condena por la comisión de ningún delito intencional;\nFracción Reformada\nVII. Tener experiencia comprobable en el ramo de derechos humanos de las mujeres y atención a mujeres víctimas de violencia con perspectiva de género;\nFracción Adicionada\nVIII. No desempeñar ningún otro empleo, cargo, puesto o comisión, con excepción de los honoríficos y los relacionados con la docencia;\nFracción Reformada, recorriéndose su posición\nIX. No haber obtenido condena por sanción relacionada con violencia contra las mujeres en razón de género;\nFracción Adicionada\nX. No contar con inhabilitación para el ejercicio de un cargo público a nivel estatal o federal;\nFracción Adicionada\nXI. No tener sentencia firme por la comisión intencional de cualquiera de los delitos o ilícitos a que se refiere el artículo 38, fracción VII, de la Constitución\nFederal; y,\nFracción Adicionada\nXII. Los demás que establezcan otras disposiciones legales aplicables.\nFracción Adicionada\nArtículo Reformado\nARTÍCULO 15. La Persona Titular del Centro tendrá las siguientes facultades y obligaciones:\nPárrafo Reformado\nI. Ejecutar los acuerdos de la Junta de Gobierno;\nII. Representar legalmente al Centro, con facultades en los términos que apruebe e instruya previamente y por escrito la Junta de Gobierno para ejercer actos de dominio, de administración, para pleitos y cobranzas, incluyendo aquellas de carácter laboral, y para juicios civiles, administrativos, penales y de amparo en que el Centro sea parte, con todas las facultades generales y especiales exceptuando los actos de dominio que tengan por objeto la compra o enajenación de inmuebles;\nFracción Reformada\nIII. Otorgar y revocar poderes generales para pleitos y cobranzas, y poderes especiales a favor de terceras personas;\nIV. Dirigir administrativamente el Centro;\nV. Coordinar las actividades de las dependencias públicas que por colaboración institucional se enfoquen en la prevención, atención, sanción y erradicación de la violencia contra las mujeres, así como coordinar aquellas actividades que realice el personal de las secretarías, dependencias y entidades así como otras instituciones del sector público federal y municipal, y organizaciones de la sociedad civil que, por colaboración interinstitucional, laboren en el Centro;\nFracción Reformada\nVI. Asesorar a las dependencias de la administración pública para que el materia de Justicia para las Mujeres;\nVII. Asesorar a los ciudadanos y organizaciones de la sociedad civil que acudan al Centro de Justicia respecto de los servicios gubernamentales y no gubernamentales disponibles para su atención y tratamiento;\nVIII. Fomentar los valores en los programas educativos apropiados a todos los niveles para contrarrestar prejuicios, costumbres y todo tipo de prácticas de violencia contra las mujeres;\nIX. Establecer procedimientos eficaces que incluyan medidas de protección y acceso efectivo a los procedimientos de procuración de justicia;\nX. Establecer la base de datos en la que se contengan los registros de la atención que se brinda en el Centro;\nFracción Reformada\nXI. Participar, con derecho a voz, pero sin voto, en las reuniones de la Junta de Gobierno;\nFracción Adicionada, recorriéndose las subsecuentes\nXII. Rendir un informe de labores cuando menos una vez al año a la Junta de Gobierno;\nXIII. Elaborar y aplicar el Reglamento Interior del Centro el cual será sometido a la Junta de Gobierno para su aprobación;\nFracción Reformada\nXIV. Elaborar y presentar a la Junta de Gobierno, para su aprobación, el proyecto de presupuesto del Centro, y aplicar los recursos financieros adoptados a los proyectos institucionales;\nFracción Reformada\nXV. Formular y presentar a la Junta de Gobierno los proyectos de planes y programas para el desarrollo de las funciones del Centro;\nXVI. Conducir las relaciones laborales, removiendo y dando por concluida la relación laboral de las personas trabajadoras del Centro, de conformidad con la normatividad aplicable;\nFracción Reformada\nXVII. Elaborar proyectos de convenios de colaboración interinstitucional con dependencias de la administración pública estatal, otras instituciones del sector público federal y municipal, y organizaciones de la sociedad civil;\nFracción Adicionada\nXVIII. Dar seguimiento a los planes y programas de atención a mujeres víctimas de violencia, con la finalidad de evaluar su eficacia y rediseñar las acciones y medidas para avanzar en la erradicación de la violencia contra las mujeres, así como establecer las medidas de protección necesarias y acceso efectivo a los procedimientos de procuración y administración de justicia;\nFracción Adicionada\nXIX. Difundir los servicios que se proporcionan en el Centro a las mujeres víctimas de violencia;\nFracción Adicionada\nXX. Rendir a la persona titular del Poder Ejecutivo de Gobierno del Estado y al Congreso del Estado, un informe anual sobre las actividades realizadas en el\nCentro;\nFracción Adicionada\nXXI. Elaborar los protocolos o manuales para la operación del Centro, conforme a lo previsto en el artículo 59 Septies, fracción VIII de la Ley General de\nAcceso de las Mujeres a una Vida Libre de Violencia;\nFracción Adicionada\nXXII. Remitir al Poder Ejecutivo del Estado, el Reglamento interno del\nCentro aprobado por la Junta de Gobierno, para los efectos que correspondan;\nFracción Adicionada\nXXIII. Expedir copias certificadas de los documentos que obran en sus archivos sobre asuntos que competan al Centro, de conformidad con las disposiciones jurídicas y administrativas aplicables; y,\nFracción Adicionada\nXXIV. Las demás que le asigne la Junta de Gobierno, y que establezcan las\nLeyes y el Reglamento respectivo.\nFracción Recorrida y Reformada\nArtículo Reformado\nCAPÍTULO IV\nDEL PATRIMONIO\nARTÍCULO 16. El patrimonio del Centro estará constituido por:\nPárrafo Reformado\nI. Todos las aportaciones, bienes muebles e inmuebles que obtenga por medio de participaciones, subsidios y apoyos que le otorguen los gobiernos\nFederal, Estatal y en su caso, municipales, para su debida operación;\nII. Los ingresos que obtenga por actividades que fortalezcan su condición patrimonial;\nFracción Reformada\nIII. Los legados y donaciones que sean otorgados en su favor;\nIV. Los fondos derivados de fideicomisos e impuesto especiales, municipales o estatales, que en su caso se le asignen para el impulso y sostenimiento de la finalidad del Centro; y\nV. Los demás ingresos que perciba por cualquier otro título legal.\nArtículo Reformado\nARTÍCULO 17. Los bienes inmuebles que formen parte del patrimonio del\nCentro de Justicia para las Mujeres de Baja California y los que se destinen a su servicio directo, tendrán el carácter de inalienables, imprescriptibles e inembargables por lo que no podrá constituirse sobre ellos ningún gravamen o derecho real.\nCAPÍTULO V\nDE LA VIGILANCIA, RELACIONES LABORALES Y TÉRMINOS DE\nLIQUIDACIÓN Y EXTINCIÓN DEL CENTRO\nARTÍCULO 18. El Control y vigilancia de los recursos y las prácticas de las personas empleadas del Centro estarán a cargo del Órgano Interno de Control.\nPárrafo Reformado\nLa Persona Titular de este órgano será nombrada y removida libremente por la Persona Titular de la Secretaría de la Honestidad y de la Función Pública.\nPárrafo Adicionado\nArtículo Reformado\nARTÍCULO 19. Es labor del Órgano Interno de Control el evaluar, detectar, controlar y sancionar prácticas ilegales de las personas servidoras públicas, dirigiendo su actuación con enfoque de carácter preventivo.\nPárrafo Reformado\nLey de Responsabilidades Administrativas del Estado de Baja California, así como inconformidades generadas en el servicio que se presta en el Centro.\nPárrafo Reformado\nArtículo Reformado\nARTÍCULO 20. La Persona Titular del Órgano Interno de Control asistirá a relacionados con sus atribuciones.\nArtículo Reformado\nARTÍCULO 21. El Centro queda sometido a las normas de contabilidad, presupuesto y gasto público aplicables a la Administración Pública del Estado de\nBaja California.\nARTÍCULO 22. Las relaciones laborales entre el Centro y las personas trabajadoras de éste se regirán por el Apartado “A” del artículo 123 de la\nPárrafo Reformado\nSin perjuicio de lo anterior, el personal adscrito y designado al Centro mantendrá su vínculo jerárquico y laboral con cada una de las dependencias, entidades u organismos de donde en su caso procedan, y deberán ajustar su desempeño a los reglamentos, lineamientos y demás reglas de operación que se emitan para sus funciones dentro del Centro.\nPárrafo Adicionado\nArtículo Reformado\nARTÍCULO 23. Cuando el Centro deje de cumplir con el objeto para el que fue creado o su funcionamiento no resultare conveniente desde el punto de vista del Estado o del Interés Público, la Secretaría General de Gobierno propondrá al\nEjecutivo la disolución, liquidación o extinción de este organismo; en este sentido se considera que opera la extinción de la fuente de trabajo. Asimismo, podrá proponer su fusión, cuando su actividad combinada redunde en un incremento de eficiencia y productividad.\nArtículo Reformado\nARTÍCULO 24.- Todo el personal adscrito y designado a los Centros deberá estar sensibilizado y profesionalizado en atención a víctimas de violencia de género desde la perspectiva de género, y en derechos humanos de las mujeres, además de recibir capacitación permanente para su actualización.\nArtículo Adicionado\nTRANSITORIOS:\nPRIMERO.- La presente Ley será publicada en el Periódico Oficial del forma, iniciará funciones el Centro de Justicia a que se refiere dicha Ley.\nSEGUNDO.- El Ejecutivo del Estado conformará una comisión que deberá integrarse a más tardar en el mes de junio del año 2016 que realizará, con la\n39, fracción II de la Ley de Presupuesto y Ejercicio del Gasto Público del Estado, y inicio de funciones del Centro de Justicia para Mujeres.\nAsimismo, el Ejecutivo del Estado gestionará para los mismos fines, los o fortalecimiento del Centro de Justicia para Mujeres.\nTERCERO.- La Junta de Gobierno expedirá el Reglamento Interno del\nCentro dentro de los tres meses siguientes a la entrada en vigor de esta Ley, mientras tanto, determinará lo necesario para el despacho de los asuntos de su competencia.\nCUARTO.- La primera sesión de la Junta de Gobierno, será convocada y presidida por el C. Gobernador Constitucional del Estado, dentro de los treinta días siguientes a la entrada en vigor de la presente Ley, debiendo celebrarse la subsecuentes en los términos de este ordenamiento.\nQUINTO.- Los titulares de las Dependencias del Ejecutivo en sus respectivas esferas de competencia, proveerán lo necesario, en forma coordinada, para que se realicen las acciones con las que se dé fiel cumplimiento a esta Ley.\nDADO en el Salón de Sesiones “Lic. Benito Juárez García” del H. Poder\nLegislativo del Estado de Baja California, en la Ciudad de Mexicali, B.C., a los tres días del mes de diciembre del año dos mil quince.\nDIP. IRMA MARTÍNEZ MANRÍQUEZ\nPRESIDENTA\n(RÚBRICA)\nDIP. MARIO OSUNA JIMÉNEZ\nSECRETARIO\n(RÚBRICA)\nDE CONFORMIDAD CON LO DISPUESTO POR LA FRACCIÓN I DEL\nPUBLÍQUESE.\nMEXICALI, BAJA CALIFORNIA, A LOS NUEVE DÍAS DEL MES DE\nDICIEMBRE DEL AÑO DOS MIL QUINCE.\nFRANCISCO ARTURO VEGA DE LAMADRID\nGOBERNADOR DEL ESTADO\n(RÚBRICA)\nFRANCISCO RUEDA GÓMEZ\nSECRETARIO GENERAL DE GOBIERNO\n(RÚBRICA)\nARTÍCULO 1.- Fue reformado mediante Decreto No. 294, publicado en el expedido por la H. XXIV Legislatura, siendo Gobernadora Constitucional la C.\nMarina del Pilar Ávila Olmeda 2021-2027;\nARTÍCULO 2.- Fue reformado mediante Decreto No. 294, publicado en el\nPeriódico Oficial No. 57, de fecha 06 de octubre de 2023, Índice, Tomo CXXX, expedido por la H. XXIV Legislatura, siendo Gobernadora Constitucional la C.\nMarina del Pilar Ávila Olmeda 2021-2027;\nARTÍCULO 3.- Fue reformado mediante Decreto No. 294, publicado en el\nPeriódico Oficial No. 57, de fecha 06 de octubre de 2023, Índice, Tomo CXXX, expedido por la H. XXIV Legislatura, siendo Gobernadora Constitucional la C.\nMarina del Pilar Ávila Olmeda 2021-2027;\nARTÍCULO 4.- Fue reformado mediante Decreto No. 294, publicado en el\nPeriódico Oficial No. 57, de fecha 06 de octubre de 2023, Índice, Tomo CXXX, expedido por la H. XXIV Legislatura, siendo Gobernadora Constitucional la C.\nMarina del Pilar Ávila Olmeda 2021-2027;\nARTÍCULO 4 BIS.- Fue adicionado mediante Decreto No. 294, publicado en el\nPeriódico Oficial No. 57, de fecha 06 de octubre de 2023, Índice, Tomo CXXX, expedido por la H. XXIV Legislatura, siendo Gobernadora Constitucional la C.\nMarina del Pilar Ávila Olmeda 2021-2027;\nARTÍCULO 4 TER.- Fue adicionado mediante Decreto No. 294, publicado en el\nPeriódico Oficial No. 57, de fecha 06 de octubre de 2023, Índice, Tomo CXXX, expedido por la H. XXIV Legislatura, siendo Gobernadora Constitucional la C.\nMarina del Pilar Ávila Olmeda 2021-2027;\nARTÍCULO 5.- Fue reformado mediante Decreto No. 294, publicado en el\nPeriódico Oficial No. 57, de fecha 06 de octubre de 2023, Índice, Tomo CXXX, expedido por la H. XXIV Legislatura, siendo Gobernadora Constitucional la C.\nMarina del Pilar Ávila Olmeda 2021-2027;\nFue modificada la denominación de este Capítulo mediante Decreto No. 294, Tomo CXXX, expedido por la H. XXIV Legislatura, siendo Gobernadora\nConstitucional la C. Marina del Pilar Ávila Olmeda 2021-2027;\nCAPÍTULO II\nDEL ÓRGANO DE GOBIERNO\nARTÍCULO 6.- Fue reformado mediante Decreto No. 294, publicado en el expedido por la H. XXIV Legislatura, siendo Gobernadora Constitucional la C.\nMarina del Pilar Ávila Olmeda 2021-2027;\nARTÍCULO 7.- Fue reformado mediante Decreto No. 294, publicado en el expedido por la H. XXIV Legislatura, siendo Gobernadora Constitucional la C.\nMarina del Pilar Ávila Olmeda 2021-2027;\nARTÍCULO 8.- Fue reformado mediante Decreto No. 294, publicado en el\nPeriódico Oficial No. 57, de fecha 06 de octubre de 2023, Índice, Tomo CXXX, expedido por la H. XXIV Legislatura, siendo Gobernadora Constitucional la C.\nMarina del Pilar Ávila Olmeda 2021-2027;\nARTÍCULO 9.- Fue reformado mediante Decreto No. 294, publicado en el\nPeriódico Oficial No. 57, de fecha 06 de octubre de 2023, Índice, Tomo CXXX, expedido por la H. XXIV Legislatura, siendo Gobernadora Constitucional la C.\nMarina del Pilar Ávila Olmeda 2021-2027;\nARTÍCULO 10.- Fue reformado mediante Decreto No. 294, publicado en el\nPeriódico Oficial No. 57, de fecha 06 de octubre de 2023, Índice, Tomo CXXX, expedido por la H. XXIV Legislatura, siendo Gobernadora Constitucional la C.\nMarina del Pilar Ávila Olmeda 2021-2027;\nARTÍCULO 12.- Fue reformado mediante Decreto No. 294, publicado en el\nPeriódico Oficial No. 57, de fecha 06 de octubre de 2023, Índice, Tomo CXXX, expedido por la H. XXIV Legislatura, siendo Gobernadora Constitucional la C.\nMarina del Pilar Ávila Olmeda 2021-2027;\nFue modificada la denominación de este Capítulo mediante Decreto No. 294, publicado en el Periódico Oficial No. 57, de fecha 06 de octubre de 2023, Índice, Tomo CXXX, expedido por la H. XXIV Legislatura, siendo Gobernadora\nConstitucional la C. Marina del Pilar Ávila Olmeda 2021-2027;\nCAPÍTULO III\nDE LA PERSONA TITULAR DEL CENTRO\nARTÍCULO 13.- Fue reformado mediante Decreto No. 294, publicado en el expedido por la H. XXIV Legislatura, siendo Gobernadora Constitucional la C.\nMarina del Pilar Ávila Olmeda 2021-2027;\nARTÍCULO 14.- Fue reformado mediante Decreto No. 294, publicado en el expedido por la H. XXIV Legislatura, siendo Gobernadora Constitucional la C.\nMarina del Pilar Ávila Olmeda 2021-2027;\nARTÍCULO 15.- Fue reformado mediante Decreto No. 294, publicado en el expedido por la H. XXIV Legislatura, siendo Gobernadora Constitucional la C.\nMarina del Pilar Ávila Olmeda 2021-2027;\nARTÍCULO 16.- Fue reformado mediante Decreto No. 294, publicado en el\nPeriódico Oficial No. 57, de fecha 06 de octubre de 2023, Índice, Tomo CXXX, expedido por la H. XXIV Legislatura, siendo Gobernadora Constitucional la C.\nMarina del Pilar Ávila Olmeda 2021-2027;\nARTÍCULO 18.- Fue reformado mediante Decreto No. 294, publicado en el\nPeriódico Oficial No. 57, de fecha 06 de octubre de 2023, Índice, Tomo CXXX, expedido por la H. XXIV Legislatura, siendo Gobernadora Constitucional la C.\nMarina del Pilar Ávila Olmeda 2021-2027;\nARTÍCULO 19.- Fue reformado mediante Decreto No. 294, publicado en el\nPeriódico Oficial No. 57, de fecha 06 de octubre de 2023, Índice, Tomo CXXX, expedido por la H. XXIV Legislatura, siendo Gobernadora Constitucional la C.\nMarina del Pilar Ávila Olmeda 2021-2027;\nARTÍCULO 20.- Fue reformado mediante Decreto No. 294, publicado en el\nPeriódico Oficial No. 57, de fecha 06 de octubre de 2023, Índice, Tomo CXXX, expedido por la H. XXIV Legislatura, siendo Gobernadora Constitucional la C.\nMarina del Pilar Ávila Olmeda 2021-2027;\nARTÍCULO 22.- Fue reformado mediante Decreto No. 294, publicado en el\nPeriódico Oficial No. 57, de fecha 06 de octubre de 2023, Índice, Tomo CXXX, expedido por la H. XXIV Legislatura, siendo Gobernadora Constitucional la C.\nMarina del Pilar Ávila Olmeda 2021-2027;\nARTÍCULO 23.- Fue reformado mediante Decreto No. 294, publicado en el expedido por la H. XXIV Legislatura, siendo Gobernadora Constitucional la C.\nMarina del Pilar Ávila Olmeda 2021-2027;\nARTÍCULO 24.- Fue adicionado mediante Decreto No. 294, publicado en el expedido por la H. XXIV Legislatura, siendo Gobernadora Constitucional la C.\nMarina del Pilar Ávila Olmeda 2021-2027;\nARTÍCULO PRIMERO TRANSITORIO DEL DECRETO No. 294, POR EL\nQUE SE REFORMA A LOS ARTÍCULOS 1, 2, 3, 4, 5, 6, 7, 8, 9, 10, 12, 13, 14, 15,\n16, 18, 19, 20, 22 Y 23, ASÍ COMO LA MODIFICACIÓN EN LA IDENTIFICACIÓN\nDEL CAPÍTULO II PARA DENOMINARSE “DEL ÓRGANO DE GOBIERNO” Y\nDEL CAPÍTULO III PARA DENOMINARSE “DE LA PERSONA TITULAR DEL\nCENTRO” Y SE ADICIONAN LOS ARTÍCULOS 4 BIS, 4 TER Y 24; PUBLICADO\nEN EL PERIÓDICO OFICIAL No. 57, ÍNDICE, DE FECHA 06 DE OCTUBRE DE\n2023, TOMO CXXX, EXPEDIDO POR LA H. XXIV LEGISLATURA, SIENDO\nGOBERNADORA CONSTITUCIONAL LA C. MARINA DEL PILAR ÁVILA\nOLMEDA 2021 – 2027.\nTRANSITORIOS\nPRIMERO.- Las presentes reformas entrarán en vigor al día siguiente de su publicación en el Periódico Oficial del Estado de Baja California.\nSEGUNDO.- La Persona Titular de la Dirección del Centro de Justicia para las\nMujeres del Estado de Baja California en un plazo que no exceda de sesenta días naturales posteriores a la publicación del presente Decreto, deberá llevar a cabo las acciones necesarias para adecuación del Reglamento Interno del Centro a los términos de estas reformas.\nTERCERO.- El cumplimiento e implementación de todas las acciones que deriven de las presentes reformas, estará sujeto a la disponibilidad presupuestal correspondiente para el ejercicio fiscal en el que las mismas entren en vigor y en los subsecuentes, así como a los convenios que el Estado suscriba con el\nGobierno Federal en términos del artículo 59 Nonies de la Ley General de Acceso de las Mujeres a una Vida Libre de Violencia; sin excluir la responsabilidad de las entidades, organismos y dependencias Estatales y Municipales de programar y presupuestar para el ejercicio presupuestal inmediato posterior al inicio de vigencia del presente Decreto, el recurso que se requiera para el cumplimiento de lo dispuesto por éste.\nCUARTO.- Las dependencias, entidades y organismos de la Administración\nPública Estatal involucradas, favorecerán la coordinación de acciones que se cuenta, así como la homologación o creación de protocolos de acción necesarios.\nDADO en Sesión Ordinaria de la XXIV Legislatura en la Ciudad de Mexicali, B.C., a los veintiún días del mes de septiembre del año dos mil veintitrés.\nDIP. MANUEL GUERRERO LUNA\nPRESIDENTE\n(RÚBRICA)\nDIP. DUNNIA MONTSERRAT MURILLO LÓPEZ\nSECRETARIA\n(RÚBRICA)\nSOBERANO DE BAJA CALIFORNIA, IMPRÍMASE Y PUBLÍQUESE.\nMEXICALI, BAJA CALIFORNIA, A LOS VEINTICINCO DÍAS DEL MES DE\nSEPTIEMBRE DEL AÑO DOS MIL VEINTITRÉS.\nMARINA DEL PILAR ÁVILA OLMEDA\nGOBERNADORA DEL ESTADO\nDE BAJA CALIFORNIA\n(RÚBRICA)\nCATALINO ZAVALA MÁRQUEZ\nSECRETARIO GENERAL DE GOBIERNO\nDEL ESTADO DE BAJA CALIFORNIA\n(RÚBRICA)",
  "ordenamiento": "REGLAMENTO",
  "jurisdiccion": "BAJA CALIFORNIA",
  "fuente_oficial": "Periódico Oficial",
  "FECHA PER OFIC": "2023/10/06",
  "ESTATUS": "VIGENTE",
  "TOMO": "TOMO_V",
  "URL": "https://www.congresobc.gob.mx/Documentos/ProcesoParlamentario/Leyes/TOMO_V/20231006_LEYJUSMUJERES.PDF",
  "es_escaneado": false,
  "tiene_tablas": false,
  "materia": [
    "penal",
    "seguridad",
    "justicia"
  ]
}