{
  "titulo": "Ley DEL SERVICIO CIVIL DE LOS TRABAJADORES AL SERVICIO DE LOS PODERES DEL ESTADO y MUNICIPIOS DE BAJ",
  "Contenido": "Denominación Modificada\nPublicada en el Periódico Oficial No. 29,\nTITULO PRIMERO\nDISPOSICIONES GENERALES\nARTICULO 1.- La presente Ley es de orden público y observancia general en el\nEstado de Baja California y tiene por objeto regular las relaciones de trabajo entre las\nAutoridades Públicas y sus trabajadores, acorde a las instituciones jurídicas comprendidas en los artículos 123 apartado B, 116 fracción VI y segundo párrafo de la fracción VIII del artículo 115, todos de la Constitución Política de los Estados Unidos Mexicanos.\nSon Autoridades Públicas Patronales: Los Poderes Legislativo, Judicial y Ejecutivo; los Municipios del Estado de Baja California; el Tribunal de Arbitraje del Estado y las Juntas de Conciliación y Arbitraje del Estado.\nLa relación jurídica de los servidores públicos contemplados en el artículo 123\nApartado B, fracción XIII, de la Constitución Política de los Estados Unidos Mexicanos, se regirán por sus propias leyes.\nArtículo Reformado\nARTICULO 2.- Trabajador es la persona física que presta a las autoridades públicas un trabajo personal subordinado consistente en un servicio material, intelectual, o de ambos géneros, independientemente del grado de preparación técnica requerida, para cada profesión u oficio, en virtud del nombramiento que le fuera expedido o por el hecho de figurar en las listas de raya de los trabajadores permanentes o temporales.\nPara los efectos de esta Ley, no se considerarán trabajadores:\nI.- El Gobernador;\nII.- Los Diputados;\nEstado, y\nIV.- Los Presidentes Municipales, Síndicos Procuradores, Regidores y Consejeros\nMunicipales.\nLos servidores públicos mencionados en las fracciones anteriores, no tendrán derecho a las prestaciones que se contienen en esta Ley.\nArtículo Reformado\nLey del Servicio Civil de los Trabajadores al Servicio de los Poderes Página 1\nARTICULO 3.- La relación de trabajo entre las Autoridades Públicas y sus trabajadores se establecerá mediante nombramiento, contrato o por cualquier otro acto que tenga como consecuencia la prestación de un servicio personal y directo, en forma subordinada, a cambio de la percepción de un salario.\nLas Autoridades Públicas podrán ser representadas en juicio mediante simple oficio, por conducto de sus respectivos titulares, los titulares de sus respectivas oficinas de asuntos jurídicos o por los representantes legales que aquéllos designen para tales fines.\nArtículo Reformado\nARTICULO 4.- Los trabajadores al servicio de las Autoridades Públicas se clasifican en trabajadores de confianza o trabajadores de base. De acuerdo a la duración de la relación de trabajo y a la naturaleza del servicio prestado, se les expedirá alguno de los siguientes nombramientos:\nA) Definitivo: Si la relación se establece por tiempo indefinido para cubrir una plaza definitiva autorizada en el presupuesto de egresos respectivo y de la cual no existe titular.\nB) Interino: Si la relación se establece por un plazo de hasta un año para cubrir una vacante temporal.\nC) Provisional: Si la relación se establece para cubrir una vacante temporal mayor a un año, respecto de una plaza que existe titular.\nD) Por tiempo determinado: Si la relación se establece respecto a una plaza temporal por un plazo previamente definido.\nE) Por obra determinada: Si la relación se establece respecto de una plaza temporal para realizar una labor específica por un plazo indeterminado.\nLos Catálogos Generales de Puestos de cada Autoridad Pública, contendrán la denominación, funciones, descripción y clasificación de los puestos, así como la categoría o rama a la que pertenezcan de acuerdo a su régimen interno. Los Catálogos Generales de\nPuestos deberán publicarse en el Periódico Oficial del Estado.\nLos Presupuestos de Egresos de las Autoridades Públicas, deberán incluir un\nTabulador Anual de Remuneraciones, acorde a los objetivos, funciones, actividades y tareas de los servidores públicos, así como la cantidad, calidad y responsabilidad del trabajo. El\nSoberano de Baja California.\nArtículo Reformado\nJuntas de Conciliación y Arbitraje del Estado, los que se señalan y reúnan las condiciones a que se refiere el Artículo siguiente.\nLey del Servicio Civil de los Trabajadores al Servicio de los Poderes Página 2\nArtículo Reformado\nARTICULO 6.- Son trabajadores de confianza, los que se encuentran comprendidos de manera enunciativa más no limitativa, en la siguiente clasificación: asesores, secretario particular, privado o técnico del Gobernador del Estado, así como personal de seguridad, chóferes y todo servidor público que esté adscrito a la Oficina del\nGobernador del Estado o le preste servicios personales y directos; inclusive aquellos a quienes éste les confiera una comisión especial, temporal, transitoria o definitiva, de conformidad con la normatividad aplicable.\nb) Los titulares de cada una de las dependencias reconocidas en la Ley Orgánica de la Administración Pública del Estado y el personal que realice trabajos personales a los mismos; los subsecretarios, secretarios particulares, privados y adjuntos de los titulares de las Dependencias. Asimismo, el procurador fiscal, subprocurador fiscal, subprocuradores de justicia, delegados y subdelegados, directores, subdirectores, coordinadores, jefes de departamento o de área, todo tipo de asesores, analistas especializados, jefes de las unidades, jefe de transporte terrestre y aéreo; el personal técnico adscrito al área informática de las dependencias; jefe de bienes muebles y almacenes generales, las personas que participan en el procedimiento de adjudicación y contratación de adquisiciones y compras de bienes y servicios, o de obra pública o concesiones de bienes o servicios.\nc) Todo el personal adscrito a la Dirección de Control y Evaluación Gubernamental, incluyendo el de las contralorías internas.\nd) Los presidentes de las Juntas Locales de Conciliación y Arbitraje, los presidentes de las Juntas Especiales y los secretarios generales; todo tipo de secretarios de acuerdos, canalizadores, actuarios, notificadores, ejecutores, procuradores de la defensa del trabajo, funcionarios conciliadores e inspectores del trabajo.\ne) El presidente y los secretarios generales del Tribunal de Arbitraje del Estado; sus secretarios auxiliares, así como el personal de la unidad de actuarios, de la unidad de amparo y ejecuciones, de la unidad de proyección, de la unidad de actividades procesales, de la unidad informática jurídica, de la unidad de archivo y correspondencia y el de la coordinación administrativa.\nf) Los auditores, auxiliares de auditor, cajeros, pagadores, inspectores, visitadores, valuadores, notificadores, promotores, defensores públicos, asesores legales de todo tipo y consultores; oficiales y sub oficiales del Registro Civil; los que realicen labores de contaduría, y de representación legal, así como el Director Estatal de Protección Civil, Emergencias, y los Coordinadores Administrativos de la Coordinación Estatal de Protección\nCivil.\nLey del Servicio Civil de los Trabajadores al Servicio de los Poderes Página 3\ng) Los funcionarios públicos que la Ley General del Sistema Nacional de Seguridad de apoyo; así como aquellos que presten sus servicios a la Secretaría de Seguridad Pública del Estado, Procuraduría General de Justicia del Estado, Centro Estatal de Control y\nConfianza, Centro de Control, Comando, Comunicación y Cómputo del Estado y, en las\nAcademias de Seguridad Pública del Estado.\nh) Todo el personal encargado de la readaptación o reinserción social en los centros penitenciarios o centros de custodia para menores, incluyendo quienes ejercen la profesión de sociólogos, psicólogos, psiquiatras, trabajadores sociales, profesores, médicos e instructores técnicos.\nLa clasificación de los puestos de confianza en cada una de las dependencias, formará parte de su catálogo de puestos.\nII.- En el Poder Judicial: El Secretario General de Acuerdos, Secretario General del\nConsejo, Administrador Judicial, Contralor, Contador General, Oficial Mayor, directores, sub directores, visitadores, jefes de departamento, secretario auxiliar de la Secretaría General, secretario de estudio y cuenta, coordinadores, sub jefes, delegados, secretarios de acuerdos, investigadores, conciliadores, mediadores, asesores, auxiliar del área penal, secretario actuario, analistas, médico legista, químico legista, profesionista especializado, notificador, cajero, auxiliar contable, en almacenes e inventarios, el responsable de autorizar el ingreso o salida de bienes o valores y su destino o la baja y alta en inventarios, guardias de seguridad, personal técnico adscrito al área de informática, así como todos los trabajadores adscritos al nuevo sistema de justicia penal.\nIII.- En el Poder Legislativo:\na) Secretario de Servicios Administrativos;\nb) Secretario de Servicios Parlamentarios;\nc) Auditor Superior;\nd) Sub Auditor;\ne) Contralor;\nf) Directores;\ng) Sub Directores;\nh) Jefe de Departamento;\ni) Sub Jefe de Departamento;\nj) Asesores;\nk) Secretarios técnicos;\nl) Personal adscrito a los módulos de atención ciudadana de los Diputados;\nLey del Servicio Civil de los Trabajadores al Servicio de los Poderes Página 4\nIV.- En los Municipios:\na) Los titulares de cada una de las dependencias reconocidas en la ley del régimen personales a los mismos, directores, subdirectores, oficiales y sub oficiales del registro civil, delegados municipales, jefes de departamento, coordinadores administrativos, subjefes de departamento, jefe de oficina, coordinadores de área, secretarios de delegaciones municipales, todo tipo de asesores y consultores;\nb) El responsable de la adquisición y destino de bienes o servicios, sólo cuando tengan facultades para tomar decisiones sobre las adquisiciones, compras, enajenación o arrendamiento, así como, los que elaboren los documentos técnicos para realizar las compras de bienes o la asignación de los contratos para los servicios públicos;\nc) Aquellos que manejen directamente fondos o valores con la facultad legal para disponer de ellos, o bien, los que sean responsables del resguardo y manejo de documentos o datos de orden confidencial, cuando determinen el ingreso o salida de los mismos, su baja o alta en los inventarios;\nd) Quienes realicen funciones en la procuración y administración de justicia, jueces municipales o calificadores, secretarios de acuerdos, actuarios o notificadores;\ne) Los titulares o responsables de las áreas de bomberos y protección civil;\nf) Quienes realicen funciones de representación legal de los titulares de las instituciones públicas o dependencias, así como en el manejo de recursos, inspectores, notificadores, interventores, ejecutores, cajeros, peritos, analistas especializados, valuadores, los que realicen labores de contaduría, pagadores, secretarios particulares, secretarios privados; los choferes, secretarias, supervisores, encargados de despacho y demás personal operativo adscrito o asignado directamente a los servidores de elección popular y, todo el personal adscrito a las sindicaturas municipales.\ng) También serán considerados de confianza, los trabajadores que la Ley de\nSeguridad Pública del Estado de Baja California denomina elementos de apoyo, y en general quienes presten sus servicios en las Secretarías o Direcciones de Seguridad Pública\nMunicipal, en el Centro Estatal de Control y Confianza, en el Centro de Control, Comando, Comunicación y Cómputo y, en las Academias de Seguridad Pública Municipales. Los miembros de las instituciones policiales y peritos, se regirán por sus propias leyes.\nCon independencia del nombramiento expedido, en todos los casos a que se refiere este artículo, serán considerados trabajadores de confianza los que determinen las leyes especiales y cualquiera que desempeñe las siguientes funciones:\na) Dirección: Los responsables de conducir las actividades de otros trabajadores subordinados a ellos, ya sea en toda una Institución Pública o en alguna de sus dependencias o unidades administrativas, así como aquellas que como consecuencia de su ejercicio confieran la representatividad de la dependencia frente a los trabajadores, o impliquen poder de decisión en el ejercicio del mando a nivel de Subsecretarios, Directores\nLey del Servicio Civil de los Trabajadores al Servicio de los Poderes Página 5\nGenerales, Directores de Área, Adjuntos, Subdirectores, Jefes y Subjefes de Departamento o área, Coordinadores y Asesores;\nb) Administración: Los que tengan por objeto el control, supervisión, manejo y organización de los recursos humanos, así como la definición, asignación, aprobación, suministro, y disposición, de fondos, bienes, valores o recursos materiales propiedad de las\nInstituciones Públicas, sus dependencias y unidades administrativas.\nc) Inspección, auditoria y fiscalización: Los que realicen funciones a efecto de conocer, examinar, verificar, controlar o sancionar las acciones a cargo de las Instituciones\nPúblicas o de sus dependencias o unidades administrativas; con relación al cumplimiento de las normas aplicables.\nd) Vigilancia: Los que se relacionan o que tengan por objeto velar, custodiar, cuidar o preservar las cosas, personas o valores para prevenir una pérdida, daño o perjuicio; asimismo aquellas que se ejerzan como medida de control en la organización y funcionamiento de las Instituciones Públicas, dependencias o unidades administrativas.\ne) Supervisión: Los que en su carácter de superior, se encargan de vigilar y dirigir las actividades de otros. Corresponde a nivel de supervisores, directores, subdirectores, coordinadores de área.\nf) Asesoría o consultoría: Los que efectúen asistencia técnica o profesional que se brinde mediante consejos, opiniones o dictámenes, a las Instituciones Públicas, sus dependencias, unidades administrativas o jefaturas.\ng) Representación: Los que se refieren a aquellos que cuenten con la facultad legal de actuar a nombre de los titulares de las Instituciones Públicas o de sus dependencias.\nArtículo Reformado\nARTICULO 7.- Los trabajadores de confianza no podrán formar parte de los sindicatos de los demás trabajadores de base, ni serán tomados en consideración en los recuentos para determinar la mayoría en casos de huelga o conflictos intergremiales, no pudiendo ser representantes de los trabajadores en los organismos que se integre en virtud de las disposiciones de esta ley.\nARTICULO 8.- Son trabajadores de base los no incluidos en los artículos 5 y 6 que anteceden, siendo por ello inamovibles; adquiriendo el derecho personal a la estabilidad no fueron nombrados, de conformidad con el sistema escalafonario regulado en esta ley, salvo que por disposición legal especial deban sujetarse a un sistema escalafonario diverso.\nArtículo Reformado\nARTICULO 9.- Los trabajadores de nuevo ingreso, que acumulen más de un año efectivo de prestación de servicios, tendrán derecho a solicitar su registro ante la Comisión\nMixta de Escalafón de la Autoridad Pública que corresponda, para ser incorporados al sistema escalafonario y participar en los concursos, ascensos y promociones para la\nLey del Servicio Civil de los Trabajadores al Servicio de los Poderes Página 6 obtención de la base definitiva prevista en el artículo 4 de esta Ley.\nArtículo Reformado\nARTICULO 10.- Todos los trabajadores al servicio de las Autoridades Públicas, deberán ser preferentemente de nacionalidad mexicana.\nArtículo Reformado\nARTICULO 11.- Son irrenunciables los derechos que otorga la presente y las demás leyes laborales aplicables.\nARTICULO 12.- En los casos no previstos por esta ley y sus reglamentos se aplicarán supletoriamente, en el orden siguiente: la Ley Federal de los Trabajadores al Servicio del\nEstado, la jurisprudencia, la Ley Federal del Trabajo, los principios generales de justicia social que deriven del Artículo 123 constitucional, y los principios generales del derecho.\nArtículo Reformado\nARTICULO 13.- En la interpretación y aplicación de las normas de trabajo se deberán tomar en cuenta que estas tienden a conseguir la democracia y justicia social y que el trabajo es un derecho y un deber social; no es artículo de comercio, exige respeto para las libertades y dignidad de quien lo presta y debe efectuarse en condiciones que aseguren la vida y un nivel decoroso para el trabajador, su familia o dependientes económicos que les permitan una constante superación con cultura adecuada.\nARTICULO 14.- Las actuaciones y certificaciones que se hicieren con motivo de la aplicación de la presente ley no causarán impuesto alguno.\nTITULO SEGUNDO\nDERECHOS Y OBLIGACIONES DE LAS AUTORIDADES PUBLICAS Y SUS\nTRABAJADORES\nCAPITULO I\nARTICULO 15.- Los trabajadores de confianza o de base de nuevo ingreso prestan sus servicios en virtud del nombramiento expedido por el funcionario facultado para ello, y sólo podrá ser definitivo, interino, provisional, por tiempo determinado, por obra determinada, sin que dichas modalidades puedan cambiarse.\nPara la expedición de los nombramientos de los trabajadores de base, se tomará en\nPública correspondiente.\nArtículo Reformado\nARTICULO 16.- El señalamiento de un tiempo determinado puede únicamente estipularse en los casos siguientes:\nLey del Servicio Civil de los Trabajadores al Servicio de los Poderes Página 7\nI.- Cuando lo exija la naturaleza del trabajo que se va a prestar.\nII.- Cuando tenga por objeto substituir temporalmente a otro trabajador y\nIII.- En los demás casos previstos por esta ley.\nARTICULO 17.- Si vencido el término que le hubiese fijado subsiste la materia del trabajo, la relación quedará prorrogada por todo el tiempo que perdure dicha circunstancia.\nARTICULO 18.- Los menores de edad que tengan más de 16 años tendrán la capacidad legal para prestar sus servicios en las instituciones de las autoridades públicas, percibir el salario correspondiente y ejercitar las acciones derivadas de la presente ley.\nARTICULO 19.- Serán condiciones nulas y no obligarán a los trabajadores, aun cuando lo admitieran expresamente las que estipulen:\nI.- Una jornada mayor de la permitida por esta ley.\nII.- Las que fijen labores peligrosas e insalubres para las mujeres, y las peligrosas, insalubres o nocturnas para menores de 16 años, exceptuando al personal de hospitales, cárceles, mantenimiento de edificios públicos y establecimientos de beneficencia y asistencia social.\nIII.- Una jornada inhumana por lo notoriamente excesiva o peligrosa, dada la índole del trabajo a juicio del tribunal de arbitraje.\nIV.- Horas extraordinarias y trabajos nocturnos para las mujeres, cuando pongan en peligro su salud.\nV.- Un salario inferior al mínimo general y profesional para la zona económica correspondiente.\nVI.- Un salario que no sea remunerativo a juicio del tribunal de arbitraje, habiendo oído al sindicato correspondiente.\nVII.- Un plazo mayor de una quincena para el pago de los salarios de los trabajadores.\nVIII.- Un salario menor al que se pague a otro trabajador en la misma institución pública o en cualquier otra de las que son objeto de esta ley, por trabajo de igual eficiencia en la misma clase de trabajo o igual jornada, por consideración de edad, sexo o nacionalidad, debiendo prevalecer el principio de: a igual función a igual remuneración.\nIX.- Renuncia por parte del trabajador a cualquiera de los derechos o prerrogativas consignadas en las normas de trabajo.\nARTICULO 20.- Los nombramientos de los trabajadores de confianza o de base deberán contener:\nLey del Servicio Civil de los Trabajadores al Servicio de los Poderes Página 8\nI.- Nombre, nacionalidad, edad, sexo, estado civil y domicilio.\nII.- Categoría y servicios que deban prestarse, los que se determinarán y precisarán de la manera más conveniente para las partes.\nIII.- El carácter del nombramiento: definitivo, interino, provisional, por tiempo determinado o por obra determinada.\nIV.- La duración de la jornada de trabajo.\nV.- El salario y demás prestaciones que deberá percibir el trabajador.\nVI.- La dependencia a la que se encuentra adscrito.\nArtículo Reformado\nARTICULO 21.- El nombramiento aceptado obliga a cumplir con los deberes inherentes al mismo y a las consecuencias que sean conforme a la ley, al uso, a la costumbre y a la buena fe.\nARTICULO 22.- En ningún caso el cambio de funcionarios de las autoridades públicas o de estas, modificará la situación de los trabajadores de base esto es, que no se afectarán los derechos de los mismos y fundamentalmente los de antigüedad e inamobilidad.\nCAPITULO II\nJORNADA DE TRABAJO,\nDESCANSOS Y VACACIONES\nARTICULO 23.- Jornada de trabajo es el tiempo durante el cual el trabajador está a disposición de las autoridades públicas para prestar sus servicios.\nARTICULO 24.- Para los efectos de la presente ley, es jornada diurna la comprendida entre las 6:00 y las 19:00 horas, jornada nocturna la comprendida entre las 19:00 horas y las\n6 horas del día siguiente, se considera jornada mixta la comprendida en el período de la jornada diurna y nocturna, siempre que el período nocturno sea menor de dos horas y media, en caso contrario se reputará como jornada nocturna.\nARTICULO 25.- La duración máxima de las jornadas diurnas, nocturna y mixta será 7, 6 y 6:30 horas respectivamente, cuando por circunstancias especiales o necesidades del servicio deban aumentarse las horas de las jornadas estipuladas en esta Ley, en las condiciones generales de trabajo o preestablecidas, este trabajo será considerado como extraordinario y no podrá exceder de tres horas diarias ni de tres veces en una semana.\nARTICULO 26.- Durante la jornada continua de trabajo, se concederá al trabajador un descanso de treinta minutos por lo menos, debiendo fijarse la hora de dicho lapso por acuerdo del titular de la dependencia correspondiente, tomando en consideración que no se interrumpa la prestación de los servicios en el centro de trabajo de que se trate.\nLey del Servicio Civil de los Trabajadores al Servicio de los Poderes Página 9 horas de reposo o de comidas, el tiempo correspondiente le será computado como tiempo efectivo de la jornada de trabajo. permitido en este Capítulo. Sin embargo, atendiendo a las necesidades del servicio público, la autoridad podrá requerir servicios extraordinarios de los trabajadores, mediante oficio en el que se establecerá la labor a desempeñar, el nombre de su jefe inmediato, los días y horas del servicio requerido. El pago de tiempo extraordinario se liquidará con base en el reporte de actividades que conjuntamente suscriban el trabajador y el jefe inmediato autorizado para tales fines; se cubrirá a más tardar a la siguiente catorcena de aquella en la que se hubiese generado.\nLa prolongación del tiempo extraordinario que exceda de nueve horas a la semana, obliga a la institución pública a pagar al trabajador el tiempo excedente con un 200% más del salario que corresponda a las horas de la jornada estipulada sin perjuicio de las sanciones establecidas en esta ley.\nArtículo Reformado\nARTICULO 27.- Por cada cinco días de trabajo disfrutará el trabajador dos días de descanso por lo menos, con goce del salario íntegro.\nARTICULO 28.- En los reglamentos de esta Ley y en la práctica se procurará que los días de descanso semanarios sean preferentemente los sábados y domingos.\nLos trabajadores que presten sus servicios en sábado o domingo o en ambos días, tendrán derecho al pago de una prima adicional de un 35% por lo menos en base al salario normal de los demás días de trabajo.\nARTICULO 29.- Las mujeres disfrutarán de 30 días de descanso antes de la fecha que aproximadamente se fije del parto y de 60 días después del mismo; pudiendo ampliarse la periodicidad en casos especiales mediante dictámenes médicos, además durante la lactancia tendrán un descanso extraordinario por día de cuando menos una hora para amamantar a sus hijos, estas prerrogativas se conceden independientemente de las vacaciones o demás descansos que se estipulen en la presente Ley; la institución o dependencia debe contar con sala de lactancia.\nPárrafo Reformado naturales con goce de sueldo, posteriores al día en que lo reciban, a fin de garantizar su integración familiar y social.\nLos hombres disfrutarán de un permiso de cinco días laborables, con goce de sueldo íntegro, por el nacimiento de sus hijos y de igual manera en el caso de adopción de un infante. El trabajador deberá comprobar conforme a la legislación aplicable que estos hechos ocurrieron y además deberá acreditar que cohabita con la madre del menor.\nArtículo Reformado\nLey del Servicio Civil de los Trabajadores al Servicio de los Poderes Página 10\nARTÍCULO 29 BIS.- Las mujeres y hombres trabajadores tendrán permiso de un día al año, con goce de sueldo íntegro, para someterse a la realización de exámenes médicos de prevención de cáncer de mama, cervicouterino o de próstata, según sea el caso; para lo salud pública o privada.\nArtículo Adicionado\nARTÍCULO 29 TER.- Las madres, padres o tutores trabajadores tendrán derecho a que se les otorguen permisos para ausentarse de sus labores con el fin de atender asuntos escolares relacionados con sus hijas, hijos o pupilos menores de edad, para facilitar su participación en las actividades de educación y desarrollo de las y los educandos. Dichos permisos se expedirán, previa justificación y a petición de parte de la madre, padre o tutor que tenga a su cargo el ejercicio de la patria potestad, la guarda y custodia del menor, los que no podrán excederse de cuatro permisos durante el año escolar por cada educando menor.\nEn ningún caso se podrá otorgar dicho permiso de manera simultánea a la madre, padre o tutor, así como tampoco podrá exigirse que sea compensada su ausencia laboral.\nArtículo Adicionado\nARTICULO 30.- Son días de descanso obligatorios con goce de salario íntegro los siguientes:\n1.- Primero de Enero.\n2.- El primer lunes de Febrero en conmemoración del 5 de Febrero.\n3.- El tercer lunes de Marzo en conmemoración del 21 de Marzo.\n4.- 1 y 5 de Mayo.\n5.- 16 y 22 de Septiembre.\n6.- 12 y el 27 de Octubre.\n7.- 1 de Noviembre.\n8.- El tercer lunes de Noviembre en conmemoración del 20 de Noviembre.\n9.- 1 de diciembre de cada seis años cuando corresponda a la transmisión del Poder\nEjecutivo Federal.\n10.- 5 y el 25 de Diciembre.\n11.- Los demás que señala el calendario oficial o concedan las autoridades públicas.\nArtículo Reformado\nARTICULO 31.- Los trabajadores no están obligados a prestar sus servicios en los días de descanso obligatorio que señala el precepto anterior, ni en los días semanarios de descanso que se estipulen. Si se quebranta esta disposición las dependencias de las\nLey del Servicio Civil de los Trabajadores al Servicio de los Poderes Página 11 corresponda por el descanso, un 200% más.\nCuando coincidan los supuestos anteriores, la autoridad pública estará obligada a concederle otro día de descanso semanario en la siguiente semana de labores.\nARTICULO 32.- Los trabajadores que tengan más de un año de servicios en las áreas o dependencias de las Autoridades Públicas, tendrán derecho a dos períodos anuales de vacaciones: de diez días hábiles cada uno durante el primer año; de once días semestrales durante el segundo y así sucesivamente hasta llegar a quince días por cada período.\nDespués del sexto año el período semestral de vacaciones se aumentará en dos días por cada cinco años de servicios.\n*Por el 1er Año de Servicios 10 Días por Semestre\nPor el 11vo “ 17 \"\nPor el 16vo “ 19 \"\nPor el 21vo “ 21 \"\nPor el 26vo “ 23 \"\nEn ningún caso las vacaciones podrán compensarse con el pago de salario doble, sin el descanso correspondiente.\nLos trabajadores que hubieren prestado sus servicios de manera discontinua durante el período anual de que se trate, ya sea por la naturaleza transitoria del cargo, por la suspensión de la relación de trabajo, por falta injustificada, por obtener licencia sin goce de sueldo, tendrán derecho a disfrutar vacaciones en proporción al número de días trabajados en ese período. La antigüedad se computa a partir del inicio de la relación de trabajo y es acumulativa, mientras aquélla se encuentre vigente; es la base para determinar los años de vacaciones al trabajador.\nArtículo Reformado\nARTICULO 33.- Los trabajadores además de su salario ordinario tendrán derecho a una prima no menor del 55% sobre los salarios que les corresponda durante el período vacacional.\nLey del Servicio Civil de los Trabajadores al Servicio de los Poderes Página 12\nARTICULO 34.- Si la relación de trabajo termina antes de que se cumpla un año de servicio. El Trabajador tendrá derecho a una remuneración proporcional al tiempo de\nARTICULO 35.- Fuera de las horas de jornada legal, los trabajadores tendrá la facultad de desarrollar las actividades cívicas, sociales, culturales, sindicales y deportivas que fueren compatibles con sus aptitudes, edad y condición física, para lo cual las autoridades públicas concederán las facilidades necesarias.\nCAPITULO III\nDE LOS SALARIOS\nARTICULO 36.- Salario es la retribución que debe pagar la autoridad pública correspondiente a los trabajadores por sus servicios.\nEl salario se integra con lo pagos hechos en efectivo por cuota diaria, gratificaciones, percepciones, quinquenios, habitación, primas, comisiones, complementos, honorarios, participaciones, prestaciones, que se entregue al trabajador por sus servicios.\nARTICULO 37.- El salario debe ser remunerador y nunca menor al fijado como mínimo general y profesional de acuerdo con las leyes y disposiciones de la Comisión\nNacional de Salarios Mínimos.\nARTICULO 38.- La cuantía del salario fijado en los términos del artículo anterior, no podrá ser disminuida en ningún caso, debiendo revisar anualmente el salario, de conformidad con el aumento de las tasas de inflación y las necesidades reales de los trabajadores así como el aumento real del costo de la vida.\nARTICULO 39.- A trabajo igual, desempeñado en el puesto, jornada y condiciones de eficiencia también iguales, deberá corresponder salario igual.\nARTICULO 40.- El salario correspondiente a las distintas categorías de los trabajadores deberá ser uniforme en todas las autoridades públicas.\nARTICULO 41.- Se crearán también partidas para cubrir las asignaciones específicas contenidas en las condiciones generales de trabajo.\nARTICULO 42.- Los pagos se efectuarán precisamente en el lugar en que los electrónico, o en cheques oficiales, debiendo entregarse al trabajador copia del recibo oficial. También deberá entregarse copia del comprobante de la transacción electrónica cuando así se realice y el trabajador lo solicite.\nArtículo Reformado\nLey del Servicio Civil de los Trabajadores al Servicio de los Poderes Página 13\nARTICULO 43.- Los plazos para el pago de los salarios nunca podrán ser mayores de quince días.\nARTICULO 44.- Los trabajadores tendrán derecho a un aguinaldo anual, que deberá pagarse de la siguiente manera: en la primera quincena de diciembre cuarenta días y veinte días durante la primera quincena del mes de enero.\nLos que no hayan cumplido el año de servicio, tendrán derecho a que se les pague la parte proporcional del aguinaldo por el tiempo laborado.\nArtículo Reformado\nARTICULO 45.- Para determinar el monto de las indemnizaciones, pensiones o jubilaciones que deban pagarse al trabajador o a sus beneficiarios, se tomará como base la cuota diaria exclusivamente, correspondiente al día en que nazca el derecho a recibirlas.\nARTICULO 46.- Sólo podrán hacerse retenciones, descuentos o deducciones al salario de los trabajadores, cuando se trate:\nI.- De deudas contraídas con las instituciones públicas por concepto de anticipo de salarios, pagos hechos con exceso, errores o perdidas debidamente compradas imputables al trabajador.\nII.- Del Cobro de cuotas sindicales, cuotas de defunción, para pago de seguro mutual, abono por diversos créditos sindicales, aportación para constitución de cooperativas, tiendas de consumo, cajas de ahorro, seguro de vida, siempre que el trabajador hubiere manifestado previamente y de manera expresa su conformidad.\nIII.- De los descuentos ordenados por las instituciones de seguridad social correspondiente con motivo de las obligaciones de los trabajadores con las mismas que les presten servicios en ese renglón.\nIV.- De descuentos ordenados por la autoridad judicial competente, para cubrir alimentos que fueren exigidos al trabajador.\nV.- Del pago de impuestos consignados en las Leyes Fiscales, Federales y Estatales en atención a la remuneración a su trabajo, el monto total de los descuentos no podrá ser mayor del 30% de la remuneración total, excepto cuando se trate de abonos por créditos sindicales, obligaciones alimenticias o anticipos de salarios concedidos por la Autoridades\nPúblicas. En cuyo caso se estará a lo ordenado por la autoridad judicial, Tratándose de\nArtículo Reformado\nARTICULO 47.- Las horas extraordinarias de trabajo se pagarán con un ciento por sea la máxima fijada en esta Ley.\nARTICULO 48.- El salario no es susceptible de embargo judicial o administrativo, Ley del Servicio Civil de los Trabajadores al Servicio de los Poderes Página 14 salvo lo establecido en el Artículo 46 de ésta Ley.\nARTICULO 49.- Será preferente el pago de salarios a cualquier otra erogación de las autoridades públicas.\nARTICULO 50.- Es nula la cesión de salarios hecha a favor de terceras personas.\nCAPITULO IV\nOBLIGACIONES DE LAS AUTORIDADES PUBLICAS\nARTICULO 51.- Son obligaciones de las Autoridades Públicas a que se refiere el artículo 1 de esta Ley:\nI.- Preferir en igualdad de condiciones, conocimientos, aptitudes y antigüedad. A los trabajadores sindicalizados respecto de quienes no lo estuvieren, a los que con anterioridad hayan prestado satisfactoriamente un servicio, a los que acrediten tener mejores derechos conforme al escalafón.\nPara los efectos del párrafo que antecede, en cada una de las dependencias de las\nInstituciones Públicas, se formarán los escalafones, de acuerdo con las bases establecidas en esta Ley.\nLos funcionarios de las dependencias y de las instituciones públicas nombrarán y removerán libremente a los trabajadores de confianza. Para llevar a cabo la remoción de los trabajadores de confianza, se hará mediante escrito simple, sin que se requiera de procedimiento, notificación o formalidad alguna; salvo aquellas condiciones y requisitos que para el caso de los servidores públicos de carrera llegue a establecer la ley del servicio profesional de carrera que se expida para tal efecto.\nUn trabajador de base: podrá ser ascendido a un puesto de confianza, pero en este caso y mientras conserve esta categoría, quedarán en suspenso todos los derechos y prerrogativas que tuviere conforme a esta Ley como sindicalizado, así como los vínculos con la organización sindical a la cual perteneciere.\nEl trabajador promovido podrá una vez que cese en sus funciones de confianza regresar en todos los casos a su puesto de base.\nLas vacantes de plazas de base definitiva por motivo de jubilación, renuncia o muerte previsto en esta Ley, lo anterior con excepción de los trabajadores pertenecientes a instituciones policiales.\nII.- Cumplir con todos los servicios de higiene y de prevención de accidentes a que están obligados todos los patrones en general, en relación con todas las disposiciones legales vigentes.\nLey del Servicio Civil de los Trabajadores al Servicio de los Poderes Página 15\nIII.- Reinstalar a los trabajadores en las plazas de las cuales los hubieren separado injustificadamente, y hacer el pago de los salarios vencidos y demás prestaciones a que fueren condenados por laudo ejecutoriado.\nEn los casos de supresión de plazas los trabajadores afectados, tendrán derecho a se le indemnice en términos de esta Ley.\nIV.- Asignar partidas suficientes en los presupuestos de egresos correspondientes para pagar indemnizaciones y demás obligaciones económicas a sus trabajadores.\nV.- Proporcionar a los trabajadores los útiles, instrumentos, materiales, y equipo de seguridad suficientes e idóneos para desempeñar el trabajo convenido.\nVI.- Cubrir las aportaciones que fijen:\nLa Ley de Seguridad Social del Estado para que los trabajadores reciban los beneficios de la seguridad social integral.\nA) Proporcionar a los trabajadores habitaciones cómodas, higiénicas y económicas de interés social en propiedad o en arrendamiento, ya sea en forma directa o a través de instituciones creadas exprofeso para resolver el problema habitacional, o bancarias, siempre que prevalezca el interés social.\nVII.- Capacitar a sus trabajadores, mediante el establecimiento de escuelas o institutos en administración pública, incorporados a instituciones oficiales, en las que se impartan los cursos necesarios, para que los trabajadores puedan adquirir los conocimientos adecuados para obtener asensos conforme al escalafón, desarrollar técnicamente sus actividades y mantener la superación de su actitud profesional, para prestar servicios eficientes en la institución pública de que se trate.\nVIII.- Conceder becas a los trabajadores de base, de la institución pública de que se trate para especialización, en materias relacionadas con la administración pública, así como cursos o seminarios en materia sindical en el país o en el extranjero. Estas becas serán con goce de salario integro y comprenderán el pago de colegiaturas, alimentación y gastos de viaje.\nIX.- Conceder becas a los hijos de los trabajadores de base, para cursar los estudios de primaria, secundaria, preparatoria, profesional y de especialización.\nX.- Conceder licencia con goce de sueldos a los trabajadores para el desempeño de por el sindicato para participar en congresos, asambleas, eventos, seminarios, etc.\nBastando para el primer supuesto, que se exhiba ante la autoridad pública correspondiente, el acta de la asamblea donde se llevó a cabo el acta de elección de los\nComités Ejecutivos respectivos, y para los demás casos la notificación por oficio de la comisión sindical de que se trate.\nLey del Servicio Civil de los Trabajadores al Servicio de los Poderes Página 16 escalafonarios, jubilaciones, pensiones y demás derechos a que tuviere el trabajador;\nXI.- Otorgar a los trabajadores el pago de una prima de antigüedad consistente en quince días de salario por cada año de servicios prestados cuando sean separados del empleo independientemente de la justificación o injustificación de la separación, en caso de retiro voluntario para tener derecho al disfrute de esta prestación deberán tener por lo menos tres años de antigüedad del empleo.\nXII.- Hacer las deducciones de los salarios de los trabajadores de las instituciones públicas que le soliciten los sindicatos respectivos o las federaciones de sindicatos estatales y nacionales, siempre que se ajusten a los términos de esta Ley, y a los rendimientos internos que los rijan.\nXIII.- Contribuir al fomento de las actividades deportivas de los trabajadores, proporcionándoles útiles e implementos necesarios para la practica del deporte.\nXIV.- Establecer sistemas de estímulos para los trabajadores por años de servicio, méritos y aportaciones valiosas y útiles para la administración pública en sus respectivos niveles.\nXV.- Proporcionar a los sindicatos y federaciones de sindicatos, las informaciones que soliciten, así como copias simples al personal de base relacionadas con su situación contractual.\nArtículo Reformado\nARTICULO 52.- Queda prohibido a las dependencias de las autoridades públicas y sus funcionarios o titulares:\nI.- Intervenir en cualquier forma en el régimen interno de los sindicatos o de las federaciones de sindicatos, que en capítulo respectivo se mencionan.\nII.- Ejecutar cualquier acto que restrinja a los trabajadores, el derecho a realizar sus funciones normales para las que fueron nombrados, así como el ejercicio de sus derechos sindicales y de los demás que otorga la presente Ley.\nIII.- Hacer propaganda política o religiosa dentro de sus dependencias.\nIV.- Realizar actos de represión, discriminación de cualquier índole, en contra de sus trabajadores, familiares o dependientes económicos.\nArtículo Reformado\nCAPITULO V\nDE LAS OBLIGACIONES DE LOS TRABAJADORES\nLey del Servicio Civil de los Trabajadores al Servicio de los Poderes Página 17\nARTICULO 53.- Son obligaciones de los trabajadores:\nI.- Desempeñar sus labores con la intensidad, cuidado y esmero apropiados, sujetándose a la dirección de sus jefes, a las leyes y reglamentos respectivos.\nII.- Observar buenas costumbres dentro del servicio.\nIII.- Cumplir con las obligaciones que les impongan las condiciones generales de trabajo.\nIV.- Guardar reserva de los asuntos que les lleguen a su conocimiento, con motivo de su trabajo.\nV.- Evitar la ejecución de actos que pongan en peligro su seguridad y la de sus compañeros.\nVI.- Asistir puntualmente a sus labores.\nVII.- Abstenerse de hacer propaganda dentro de los edificios o lugares de trabajo.\nVIII.- Someterse a exámenes médicos periódicamente.\nIX.- Asistir a los institutos de capacitación, cursos, seminarios, etc., para mejorar su preparación y eficiencia.\nTITULO TERCERO\nDE LA SUSPENSION Y DE LA TERMINACION DE LAS RELACIONES LABORALES\nCAPITULO I\nDE LA SUSPENSION\nARTICULO 54.- La suspensión temporal de los efectos del nombramiento de un trabajador, no significa la terminación de la relación laboral.\nARTICULO 55.- Son causas de suspensión temporal de las obligaciones de prestar el servicio y pagar el salario, sin responsabilidad para el trabajador y el patrón:\nI.- La prisión preventiva del trabajador, seguida de sentencia absolutoria o el arresto impuesto por autoridad judicial o administrativa, a menos que el Tribunal de Arbitraje resuelva que debe tener lugar el cese del trabajador.\nII.- Los trabajadores que tengan encomendados el manejo de fondos, valores o bienes, podrán ser suspendidos por los servidores públicos de las autoridades públicas facultados para ello, cuando apareciere alguna irregularidad en su gestión.\nArtículo Reformado\nArtículo 55 BIS.- La suspensión temporal surtirá efectos:\nI.- Tratándose del supuesto a que refiere la fracción I del artículo anterior, desde el\nLey del Servicio Civil de los Trabajadores al Servicio de los Poderes Página 18 administrativa, hasta la fecha en que cause ejecutoria la sentencia que lo absuelva, o termine el arresto.\nII.- En el caso de la fracción II del artículo que antecede, en tanto se efectúa la investigación y se resuelve sobre el caso; si la imputación fuere infundada, se le pagaran al trabajador los salarios que dejó de percibir.\nArtículo Adicionado\nArtículo 55 BIS 1.- El trabajador deberá regresar a su trabajo, en los casos de las fracciones I y II del artículo 55, dentro de los tres días siguientes a la terminación de la causa de la suspensión.\nArtículo Adicionado\nCAPITULO II\nDE LA TERMINACION\nDE LA RELACION LABORAL\nARTICULO 56.- Los trabajadores sólo podrán ser cesados por causa justificada en los términos que exige esta Ley, tratándose de separación injustificada podrán optar por la reinstalación en su trabajo o por la indemnización constitucional, y al pago de las demás prestaciones establecidas, mediante el procedimiento legal para el efecto establecido en los casos de supresión de plazas, los trabajadores afectados tendrán derecho a que se les indemnice constitucionalmente y al pago de veinte días de salario por cada año de servicios prestados a proporción, si así lo manifiesta expresamente, y en caso de indemnización, al pago de una prima de antigüedad consistente en quince días de salario por cada año de servicios prestados, independientemente de las demás prestaciones a que tuviere derecho el trabajador.\nCualquiera que sea la acción que se intente en caso de juicio, la condena al pago de salarios vencidos o caídos, en su caso, no podrá exceder del importe de doce meses de salario.\nArtículo Reformado\nARTICULO 57.- La relación laboral podrá ser objeto de rescisión o terminación, de conformidad con las siguientes disposiciones.\nI.- Son causas de rescisión de la relación laboral:\nA) Imputable a los trabajadores:\n1.- Por abandono del empleo, cargo o comisión sin previa autorización de su superior jerárquico.\n2.- Cuando faltare por más de tres días a sus labores en un período de treinta días naturales, sin causa justificada.\n3.- Cuando el trabajador incurra en faltas de probidad u honradez o en actos de\nLey del Servicio Civil de los Trabajadores al Servicio de los Poderes Página 19 violencia, amagos, injurias o malos tratos, contra sus jefes o compañeros o contra los familiares de unos y otros ya sea dentro o fuera de las horas de servicio.\n4.- Por destruir intencionalmente edificios, instalaciones, obras, maquinaria, instrumentos, materias primas, documentos, información, equipo y demás objetos relacionados con el trabajo.\n5.- Por revelar asuntos secretos o reservados de los que tuviere conocimiento por motivo del trabajo.\n6.- Por comprometer con su imprudencia, descuido o negligencia, la seguridad de la dependencia, oficina o área donde presta sus servicios o de las personas que allí laboren o que estén tramitando algún servicio.\n7.- Por desobedecer sin justificación, las órdenes que reciba de sus superiores, siempre que se trate del trabajo para el que fue nombrado o contratado.\n8.- Por concurrir al trabajo en estado de embriaguez o bajo la influencia de algún narcótico o droga enervante.\n9.- Por incumplimiento al contrato de trabajo.\n10.- La sentencia ejecutoriada que imponga al trabajador una pena de prisión que le impida el cumplimiento de la relación de trabajo.\n11.- La inhabilitación o destitución decretada por el Órgano de Control competente previsto en la Ley de Responsabilidades de los Servidores Públicos del Estado.\n12.-Cometer el trabajador actos inmorales o de hostigamiento o acoso sexual contra cualquier persona en el lugar de trabajo.\n13.- Las análogas a las establecidas en los numerales anteriores, igualmente graves y de consecuencias semejantes.\nLa Autoridad Pública por sí o por conducto del Tribunal de Arbitraje, entregara personalmente el aviso escrito de la fecha y causa o causas de la rescisión. En caso de que el trabajador se negare a recibirlo, la Autoridad dentro de los diez días hábiles siguientes a la fecha de la rescisión, deberá hacerlo del conocimiento al Tribunal de Arbitraje, solicitando su debida notificación al trabajador en el domicilio que al efecto tenga registrado ante la\nAutoridad Pública.\nLa falta de aviso al trabajador de base o al Tribunal del Arbitraje, por si sola bastará para considerar que el despido fue injustificado. rescisión, el trabajador tendrá derecho, además, cualquiera que hubiese sido la acción intentada, a que se le paguen los salarios vencidos computados desde la fecha del despido hasta por un período máximo de doce meses.\nB) Imputable a las Autoridades Públicas:\nLey del Servicio Civil de los Trabajadores al Servicio de los Poderes Página 20\n1.- Incurrir los funcionarios o titulares de las autoridades públicas en faltas de probidad y honradez, actos de violencia, amenazas, injurias, malos tratamientos, hostigamiento y/o acoso sexual u otros análogos en contra del trabajador o de sus familiares.\n2.- Reducir las autoridades públicas los salarios de los trabajadores.\n3.- No pagar los salarios correspondientes en las fechas y lugares a que se refiere esta Ley.\n4.- Sufrir perjuicios causados de manera maliciosa en sus herramientas o útiles de trabajo, el trabajador.\n5.- La existencia de un peligro grave para la seguridad o salud del trabajador o de su familia ya sea por carecer de condiciones higiénicas las dependencias, oficina o taller o porque se incumplan las medidas preventivas y de seguridad e higiene que las leyes establezcan.\n6.- Comprometer con su imprudencia o descuido inexcusables la seguridad de la dependencia, oficina o taller o de las personas que en estos lugares laboran.\n7.- Las análogas a las establecidas en los incisos anteriores y que sean de consecuencias graves y semejantes en perjuicio de los trabajadores.\nII.- Son causas de terminación de la relación laboral:\n1.- Por renuncia en el empleo, cargo o comisión.\n2.- Por muerte del trabajador.\n3.- Por conclusión de la obra o del término estipulado en el contrato.\n4.- Por haberse agotado, cancelado, o extinguido el recurso presupuestal destinado a la obra, servicio o programa gubernamental.\n5.- Por pensión o jubilación solicitada por el trabajador en términos de las disposiciones aplicables.\nArtículo Reformado\nARTICULO 58.- En los casos en que se refiere el apartado B de la fracción I del artículo anterior, las autoridades públicas están obligadas a pagar a sus trabajadores, la indemnización constitucional, el pago de los salarios vencidos hasta por doce meses en su caso, las demás prestaciones que establece esta Ley y además veinte días por cada año de servicios prestados por los mismos o fracción.\nArtículo Reformado\nARTICULO 59.- Sindicato es la Asociación de Trabajadores de las instituciones públicas, constituidas para el estudio, mejoramiento y defensa de sus intereses económicos, políticos, sociales y culturales, orientando invariablemente su acción hacia mejores metas de justicia social.\nLey del Servicio Civil de los Trabajadores al Servicio de los Poderes Página 21\nARTICULO 60.- Todos los trabajadores tendrán derecho a sindicalizarse libremente.\nARTICULO 61.- Las instituciones públicas reconocerán un solo sindicato y en caso de que concurran diversos grupos, la asociación mayoritaria será la titular de la contratación colectiva y de las condiciones generales de trabajo. municipios en que este dividido territorialmente el Estado.\nARTICULO 62.- Para que se constituya un sindicato, se requiere que lo formen 50 trabajadores en activo como mínimo y que cumplan con los requisitos que establece esta\nLey.\nARTICULO 63.- Los sindicatos serán registrados por el tribunal de arbitraje para cuyo efecto se remitirán a este por duplicado los documentos que a continuación se especifican.\nI.- Acta de la asamblea constitutiva autorizada por la directiva del sindicato.\nII.- Estatutos que regirán la vida del sindicato.\nIII.- Lista de los miembros que lo integren debiendo contener: Nombre, estado civil, edad, empleo que desempeñen y salario que perciban.\nIV.- Acta de la sesión o asamblea, en que se haya elegido los cuerpos directivos del sindicato correspondientes.\nEl tribunal de arbitraje al recibir la solicitud del registro comprobará por los medios que estime más prácticos y eficaces la libre voluntad de los trabajadores para constituirse en sindicato: Cumpliendo con este requisito no podrá negar el registro respectivo.\nSi el tribunal de arbitraje no resuelve a los 30 días la solicitud del registro, los peticionarios pueden requerirlo para que dicte resolución concediéndole y si no lo hace dentro de los cinco días siguientes a la presentación del requerimiento se tendrá por hecho el registro, surtiendo todos los efectos legales y estando obligado dicho tribunal, a expedir la constancia de registro dentro de los cinco días siguientes.\nARTICULO 64.- El registro de los sindicatos solo se cancelará en caso de disolución y a petición de parte, no siendo medio de disolución, suspensión o cancelación de su registro la vía administrativa.\nARTICULO 65.- Los trabajadores que por mala conducta, falta de solidaridad o por sindicato al cual pertenezcan, perderán por ese solo hecho, todas las prerrogativas que se establezcan en las condiciones generales de trabajo.\nARTICULO 66.- Derogado;\nArtículo Derogado\nLey del Servicio Civil de los Trabajadores al Servicio de los Poderes Página 22\nARTICULO 67.- Son obligaciones de los sindicatos:\nI.- Proporcionar los informes que en cumplimiento de esta Ley, solicite el tribunal de arbitraje y titulares de las instituciones públicas;\nII.- Comunicar al tribunal de arbitraje dentro de los diez días siguientes a cada elección los cambios que ocurran en su directiva o en sus comités, las altas y bajas de sus miembros y las modificaciones que sufran los ordenamientos jurídicos que rijan su vida social o que estén relacionados con la situación contractual.\nIII.- Facilitar la labor del tribunal de arbitraje en los conflictos que se tramiten ante el mismo, ya sea del sindicato o de sus miembros proporcionando la cooperación que se requiera.\nIV.- Patrocinar y representar a sus miembros ante las autoridades públicas y ante el tribunal de arbitraje por si, o a través de apoderados cuando se solicite, todos los conflictos que surjan entre los miembros del sindicato de no ser solucionados por su comité ejecutivo serán resueltos por el tribunal de arbitraje, así mismo los gastos que origine el funcionamiento del sindicato serán cubiertos por los miembros del mismo.\nTÍTULO CUARTO\nDE LA ORGANIZACIÓN COLECTIVA DE LOS TRABAJADORES, LA\nCONTRATACIÓN Y LAS CONDICIONES GENERALES DE\nTRABAJO\nCAPITULO I\nDE LA ORGANIZACION COLECTIVA\nARTICULO 68.- Los sindicatos pueden formar federaciones y confederaciones, las que se regirán por disposiciones de este Capítulo en lo que les sea aplicable, siempre en apego a lo señalado por el apartado B) del artículo 123 de la Constitución Política de los\nEstados Unidos Mexicanos.\nArtículo Reformado\nARTICULO 69.- Queda prohibido a los sindicatos:\nI.- Hacer propaganda de carácter religioso.\nII.- Ejercer la función de comercio con fines de lucro.\nIII.- Usar la violencia con los trabajadores para obligarlos a que se sindicalicen.\nARTICULO 70.- La directiva de los sindicatos, será responsable ante éstos y respecto de terceras personas en los términos que lo son los mandatarios en derecho común.\nARTICULO 71.-Los actos realizados por las directivas de los sindicatos, obligan civil y\nLey del Servicio Civil de los Trabajadores al Servicio de los Poderes Página 23 laboralmente a éstos, siempre que hayan actuado dentro de sus facultades.\nARTICULO 72.- Los sindicatos podrán disolverse:\nI.- Por el voto de las dos terceras partes de los miembros que lo integran;\nII.- Porque dejen de reunir los requisitos señalados en el artículo 59 de esta Ley.\nIII.- Por fenecer el término fijado en sus estatutos internos.\nARTICULO 73.- Los conflictos que surjan entre los sindicatos, serán resueltos por el tribunal de arbitraje a petición de parte interesada.\nARTICULO 74.- Las remuneraciones que se paguen a los directivos de los sindicatos y en general los gastos que origine el funcionamiento de éstos, será a cargo de su presupuesto, el cuál cubrirán los miembros con cuotas sindicales que se establecerán en sus estatutos internos.\nCAPITULO II\nDE LAS CONDICIONES GENERALES DE TRABAJO\nARTICULO 75.- Las condiciones generales de trabajo, en ningún caso podrán ser inferiores a las fijadas en esta Ley, en la costumbre y demás leyes laborales aplicables, debiendo ser proporcionales a la importancia de los servicios, e iguales para trabajos iguales, sin que se puedan establecer diferencias con motivo de raza nacionalidad, sexo, edad, credo religioso o doctrina Política, salvo las modalidades expresamente consignadas en este ordenamiento.\nARTICULO 76.- Las condiciones generales de trabajo se fijarán por el titular de la autoridad pública respectiva, tomando en cuenta la opinión del sindicato correspondiente a solicitud de éste; serán revisables cada año, su análisis de viabilidad laboral y financiera se deberán de llevar a cabo preferentemente en la última semana del mes de septiembre del año que corresponda, con la finalidad de que los recursos económicos que se aprueben por las autoridades públicas, puedan ser presupuestados y ejercidos a favor de los trabajadores desde el inicio del ejercicio fiscal siguiente. revisará en el mes de octubre.\nArtículo Reformado\nARTICULO 77.- Las condiciones generales de trabajo establecerán:\nI.- Las horas de entrada y salida al trabajo.\nII.- Intensidad, calidad de trabajo y salarios.\nIII.- Los tipos de jornada de trabajo y demás prestaciones socioeconómicas que se\nLey del Servicio Civil de los Trabajadores al Servicio de los Poderes Página 24 estipulen.\nIV.- Medidas de seguridad para la prevención de riesgos profesionales.\nV.- Las fechas y condiciones de descanso de los trabajadores.\nVI.- Conceder licencia a los trabajadores para separarse de sus funciones. profesionales, tendrán derecho a que se le conceda licencia para dejar de concurrir a sus labores, en los siguientes términos:\n1ro.- A los empleados que tengan menos de un año de servicio, se les podrá conceder licencia hasta por quince días con goce de sueldo integro, hasta quince días más con medio sueldo y hasta treinta días más sin sueldo.\n2do.- A los que tengan de uno a cinco años de servicio hasta treinta días con goce de sueldo integro, hasta treinta días más con medio sueldo y hasta sesenta días más sin sueldo.\n3ro.- A los que tengan de cinco a diez años de servicio, hasta cuarenta y cinco días con goce de sueldo integro, hasta cuarenta y cinco días más con medio sueldo y hasta noventa días más sin sueldo.\n4to.- A los que tengan de diez o más de años de servicios, hasta sesenta días con goce de sueldo íntegro, hasta sesenta días más con medio sueldo y hasta ciento veinte días sin sueldo.\nLos cómputos deberán hacerse por servicios continuados o cuando de existir una interrupción en la prestación de dicho servicio. Esta no sea mayor de seis meses.\nPodrán gozar de la franquicia señalada, de manera continua o discontinua, una sola vez cada año, contando a partir del momento en que tomaron posesión de su puesto.\n5to.- Cuando por razones de que un trabajador al servicio del Estado o municipios e instituciones descentralizadas, solicite permiso para no concurrir a sus labores, la licencia se concederá sin goce de sueldo, tomándose en cuenta la antigüedad del mismo, de acuerdo con los siguientes términos:\nA) Los empleados que tengan un año de servicios, hasta sesenta días, sin goce de sueldo,\nB) Los empleados que tengan de un año a cinco de servicios hasta ciento veinte días sin goce de sueldo.\nC) Los que tengan de cinco a diez años hasta ciento ochenta días sin goce de sueldo y de diez en adelante hasta un año sin goce de sueldo.\nD) Las licencias se concederán cuando a juicio del funcionario responsable del área o dependencia, no se lesione el funcionamiento de la oficina ni se afecte la prestación del servicio público. Los interinatos se cubrirán de conformidad con el sistema escalafonario, Ley del Servicio Civil de los Trabajadores al Servicio de los Poderes Página 25\nComisión Mixta de Escalafón quien cubra dicho interinato, para que proceda conforme a la presente ley.\nVII.- Disposiciones disciplinarias y la forma de aplicarlas.\nVIII.- Las demás reglas que fueren convenientes para obtener mayor seguridad, eficiencia y eficacia en el trabajo, pero sin invadir competencia reservada a esta Ley o a disposiciones similares de ordenamientos jurídicos de mayor jerarquía.\nArtículo Reformado\nARTICULO 78.- Las condiciones generales de trabajo deberán depositarse en el tribunal de arbitraje y surtirán efectos a partir de la fecha de su depósito salvo pacto en contrario.\nTITULO QUINTO\nDE LA HUELGA\nCAPITULO UNICO\nARTICULO 79.- Huelga es la suspensión temporal del trabajo, llevada a cabo por una coalición de trabajadores.\nARTICULO 80.- Para los efectos de este capítulo, los sindicatos de trabajadores, son coaliciones permanentes.\nARTICULO 81.- Declaración de huelga, es la manifestación de la mayoría de los trabajadores, de una institución pública o de sus dependencias, para suspender las labores, si los titulares no acceden a sus demandas o peticiones.\nARTICULO 82.- Los trabajadores podrán hacer uso del derecho de huelga respecto de una o varias instituciones públicas o dependencias de las mismas por lo siguiente:\nI.- Por incumplimiento de las condiciones generales de trabajo.\nII.- Por la falta de pago de salarios consecutivos correspondientes a un mes de trabajo, salvo causa de fuerza mayor que calificara el tribunal de arbitraje;\nIII.- Porque la política general del Estado sea contraria a los derechos fundamentales que la Ley concede a los trabajadores del mismo.\nIV.- Por desconocimiento Oficial del tribunal de arbitraje o porque el Estado ponga graves obstáculos para el ejercicio de sus atribuciones.\nV.- Por omitir en los períodos correspondientes la revisión de las condiciones de plazas y salarios.\nLey del Servicio Civil de los Trabajadores al Servicio de los Poderes Página 26\nVI.- Porque el Estado haga presión para frustrar una huelga parcial.\nVII.- Por la negativa sistemática del estado a comparecer ante el tribunal de arbitraje.\nVIII.- Por desobediencia a las resoluciones del tribunal de arbitraje.\nIX.- Apoyar una huelga que tenga por objeto alguno de los enumerados con antelación.\nLa huelga podrá ser general o parcial.\nSerá general cuando se promueva en contra de todos los funcionarios del Estado y esta se podrá emplazar únicamente por los primeros seis supuestos antes referidos.\nLa huelga será parcial, cuando se promueva contra un funcionario o grupo de funcionarios de una unidad burocrática y podrá hacerse valer por los dos últimos supuestos antes enunciados.\nARTICULO 83.- La huelga solo suspende los efectos de los nombramientos de los trabajadores por el tiempo que dure pero sin terminarlos o extinguirlos.\nARTICULO 84.- La huelga deberá limitarse al mero acto de las suspensión del trabajo.\nARTICULO 85.- Los actos de coacción o de violencia física o moral sobre las personas, o de fuerza sobre las cosas cometidas por la mayoría de los trabajadores huelguistas, tendrán como consecuencia la declaración de ilicitud de la huelga.\nARTICULO 86.- Para declarar una huelga se requiere:\nI.- Que tenga por objeto alguno de los supuestos enunciados en el artículo 82 de esta\nLey.\nII.- Que sea declarada por la mayoría de los trabajadores de las instituciones públicas o dependencias respectivas.\nARTICULO 87.- La huelga es legalmente inexistente si:\nI.- La suspensión del trabajo se realiza por un número de trabajadores menor al fijado en el articulo 86 fracción II.\nII.- No ha tenido por objeto alguno de los establecidos en el artículo 82 de esta ley.\nARTICULO 88.- La huelga terminará:\nI.- Por acuerdo entre los trabajadores huelguistas y la autoridad pública correspondiente;\nII.- Si la autoridad pública se allana, en cualquier tiempo a las peticiones contenidas\nLey del Servicio Civil de los Trabajadores al Servicio de los Poderes Página 27 percibir los trabajadores.\nIII.- Por resolución de la asamblea de trabajadores tomada por acuerdo de la mayoría de los mismos.\nIV.- Por declaración de ilegalidad o inexistencia de la huelga.\nV.- Por laudo del tribunal de arbitraje o de la persona o comisión que libremente elijan las partes, si los trabajadores huelguistas someten el conflicto a su decisión.\nARTICULO 89.- El procedimiento de huelga se iniciará mediante la presentación del pliego de peticiones que deberá reunir los requisitos siguientes:\nI.- Se dirigirá por escrito a la institución pública o dependencia y en el se formularán las peticiones, enunciarán el propósito de ir a la huelga si no son satisfechas expresarán concretamente el objeto de la misma y señalarán el día y hora en que suspenderán las labores, o término de pre-huelga.\nII.- Se presentará por duplicado al Tribunal de Arbitraje, con las copias del acta de la asamblea en que se haya acordado declarar la huelga.\nIII.- El aviso para la suspensión de las labores deberá darse por lo menos, con diez días de anticipación.\nIV.- El Presidente del Tribunal de Arbitraje bajo su estricta responsabilidad hará llegar a las instituciones públicas o dependencia la copia del escrito de emplazamiento dentro de las 48 horas siguientes a la de su recibo.\nARTICULO 90.- El tribunal de arbitraje citará a las partes a una audiencia de conciliación, en la que procurará avenirlas sin hacer declaraciones que prejuzguen sobre la existencia o inexistencia justificación o injustificación de la huelga. Esta audiencia solo podrá diferirse a petición de los trabajadores y por una sola vez:\nI.- Si los trabajadores no concurren a la audiencia de conciliación, no correrá el término para la suspensión de las labores.\nII.- El presidente del tribunal podrá emplear los medios de apremio para obligar a la\nIII.- Los efectos del aviso a que se refiere el artículo 89 fracción I de la presente Ley para concurrir a ella.\nARTICULO 91.- Si no se hubiere llegado a un entendimiento entre las partes, los necesarias.\nLey del Servicio Civil de los Trabajadores al Servicio de los Poderes Página 28\nARTICULO 92.- En tanto no se declare ilegal, inexistente o terminado un Estado de huelga, las instituciones públicas, el tribunal de arbitraje y las autoridades civiles y militares, deberán hacer respetar el derecho ejercitado por los trabajadores, dándoles las garantías necesarias y prestándoles el auxilio que les soliciten.\nARTICULO 93.- Los riesgos profesionales que sufran los trabajadores se regirán por la Ley de Seguridad Social del Estado o por la Ley Federal del Trabajo en su caso.\nTITULO SEXTO\nDE LA PRESCRIPCION Y DE LA CADUCIDAD\nDenominación Modificada\nCAPITULO UNICO\nARTICULO 94.- Las acciones que nazcan de esta Ley, de los nombramientos otorgados a favor de los trabajadores, de las condiciones generales de trabajo y demás disposiciones favorables a los trabajadores, prescribirán en un año con excepción de los casos previstos en los siguientes artículos.\nARTICULO 95.- Prescriben:\nI.- En un mes.\nA) Las acciones para pedir la nulidad de un nombramiento hecho por error o en contravención a lo dispuesto por esta Ley, contando dicho plazo a partir de la fecha que sea conocido el error o que se haga de conocimiento general.\nB) Las acciones de los trabajadores para ejercitar el derecho a ocupar la plaza que haya dejado por riesgo profesional o enfermedad, contando el plazo a partir de la fecha que estén en aptitud de volver al trabajo por dictamen médico.\nII.- En cuarenta y cinco días.\nA) El derecho de las Autoridades Públicas para dar por rescindida la relación laboral o aplicar las medidas disciplinarias a sus trabajadores, contando el término desde que sean conocidas las causas justificadas, independientemente de las investigaciones que se realicen con posterioridad.\nIII.- En dos meses.\nA) En caso de despido o suspensión injustificadas las acciones para exigir la reinstalación en el trabajo o la indemnización que la ley concede, contados a partir del momento en que sea notificado el trabajador del despido o suspensión en su caso.\nB) Las acciones relacionadas con el pago de tiempo extraordinario. Se interrumpe la prescripción cuando el trabajador, mediante escrito que acuse de recibido, requiera al jefe inmediato que le hubiere solicitado y autorizado la prestación de servicio extraordinario.\nArtículo Reformado\nLey del Servicio Civil de los Trabajadores al Servicio de los Poderes Página 29\nARTICULO 96.- Prescriben en dos años.\nI.- Las acciones de los trabajadores para demandar indemnizaciones por riesgos de trabajo.\nII.- Las acciones de los beneficiarios de los trabajadores en los casos de muerte por riesgos de trabajo.\nIII.- Las acciones para ejecutar las resoluciones o laudos del tribunal de arbitraje.\nLos plazos para ejecutar las acciones a que se refieren las fracciones anteriores, correrán precisamente desde el momento en que se determine la naturaleza del riesgo, y desde la fecha de la muerte del trabajador o desde que sea ejecutable la resolución dictada por el tribunal de arbitraje.\nARTICULO 97.- La prescripción no puede comenzar ni correr.\nI.- Contra los incapaces mentales.\nII.- Contra los trabajadores incorporados al servicio militar o en tiempos de guerra y que por alguno de los conceptos contenidos en esta ley, se hayan hecho acreedores a indemnización.\nIII.- Durante el tiempo que el trabajador se encuentre privado de su libertad, siempre que haya sido absuelto por sentencia ejecutoriada.\nARTICULO 98.- La prescripción se interrumpe.\nI.- Por la sola presentación de la demanda respectiva ante el Tribunal de Arbitraje del\nEstado. No se interrumpirá la prescripción cuando la demanda correspondiente se presente ante un tribunal o autoridad distinta al Tribunal de Arbitraje del Estado.\nII.- Si el servidor público, expresamente facultado para tales fines por la Autoridad\nPública a cuyo favor corre la prescripción, reconoce el derecho del trabajador, mediante escrito o por hechos indudables.\nArtículo Reformado\nARTICULO 99.- Para los efectos de la prescripción los meses se regularán por el número de días que les corresponda.\nEl primer día se contará completo, aún cuando no lo sea y cuando sea inhábil el hábil siguiente.\nARTÍCULO 99 BIS.- Se tendrá por desistida de la instancia intentada a quien no haga promoción alguna en el término de tres meses naturales, siempre que esa promoción sea necesaria para la continuación del procedimiento. Una vez transcurrido este término, el\nLey del Servicio Civil de los Trabajadores al Servicio de los Poderes Página 30 caducidad, aun cuando el término transcurra, por el desahogo de diligencias que se estén practicando por exhorto.\nArtículo Adicionado\nTITULO SEPTIMO\nDEL TRIBUNAL DE ARBITRAJE, DEL PROCEDIMIENTO\nY DE LOS MEDIOS PROBATORIOS\nCAPÍTULO I\nDEL TRIBUNAL DE ARBITRAJE\nARTICULO 100.- El Tribunal de Arbitraje, será colegiado, y se integrará por:\nI.- Dos representantes de los Poderes del Estado;\nII.- Dos representantes de los Municipios;\nIII.-Cuatro representantes de los trabajadores, entre ellos uno de los trabajadores de la educación; y\nIV.- Un árbitro, fungiendo como tal, el Presidente del Tribunal.\nEl presidente del Tribunal de Arbitraje, será designado por unanimidad de los representantes en sesión formal; en caso de desacuerdo será designado por el Gobernador del Estado.\nLa designación de los Representantes de los Poderes del Estado, se hará por unanimidad de los titulares de los Poderes, y en caso de desacuerdo, por aquel que cuente con el mayor número de juicios en trámite ante el Tribunal de Arbitraje. El representante deberá contar con título de licenciado en Derecho y deberá formar parte de alguno de los\nPoderes del Estado.\nLa designación de los representantes de los municipios, se hará por los presidentes municipales mediante mayoría simple, y en caso de desacuerdo, por aquellos municipios que cuenten con el mayor número de juicios en trámite ante el Tribunal de Arbitraje. Los representantes deberán contar con título de licenciado en Derecho y formar parte de la administración municipal, preferentemente con adscripción a sus respectivas oficinas de asuntos jurídicos. sus estatutos. Los representantes que designen deberán ser trabajadores de base definitiva. encomienda serán remunerados por sus respectivos representados, excepto los representantes de los trabajadores, quienes contarán con licencia con goce de sueldo. El\nTribunal de Arbitraje deberá dotar a los representantes del tribunal, de un espacio físico\nLey del Servicio Civil de los Trabajadores al Servicio de los Poderes Página 31 debidamente acondicionado para el adecuado desempeño de sus funciones.\nAsimismo, se debe enlistar y correr traslado a los integrantes del tribunal de arbitraje, con cinco días naturales de antelación, de los proyectos de resolución de los asuntos a tratar antes de la celebración de la sesión correspondiente, a efecto de que estén en aptitud de conocer y comparecer a la misma a deliberar, emitir y justificar su voto.\nArtículo Reformado\nARTICULO 101.- Las faltas temporales del presidente del tribunal serán cubiertas por el secretario general de acuerdos y de los demás representantes por la persona que designe el organismo que cada uno representa.\nARTICULO 102.- El Presidente del Tribunal de Arbitraje durará en su cargo seis años.\nSólo podrá ser removido por haber cometido delitos graves del orden común, federal o por encontrarse impedido o inhabilitado para desempeñar funciones, cargos o comisiones de cualquier naturaleza en el servicio público; o por unanimidad de los Representantes que integran el pleno del Tribunal de Arbitraje, cuando su conducta, negligencia o incapacidad afecte el adecuado desarrollo de las funciones del Tribunal de Arbitraje. El Presidente deberá ser oportunamente notificado de la imputación y oído en su defensa.\nLos Representantes de las organizaciones de trabajadores y de los Poderes del\nEstado y de los Municipios, podrán ser removidos libremente por quienes los designaron.\nArtículo Reformado\nARTICULO 103.- Para ser representante del tribunal de arbitraje se requiere:\n1.- Ser mexicano en pleno goce de sus derechos.\n2.- Ser mayor de 21 años.\n3.- No haber sido condenado por delitos contra la propiedad, o a sufrir pena mayor de un año de prisión por cualquier otra clase de delitos.\nLos representantes de los trabajadores deberán haber servido a las instituciones públicas como empleados de base, cinco años cuando menos anteriores a la fecha de la designación.\nARTICULO 104.- El Presidente del Tribunal de Arbitraje del Estado deberá reunir los siguientes requisitos:\nI.- Ser mexicano, mayor de veinticinco años y estar en pleno ejercicio de sus derechos civiles y políticos;\nII.- Tener título legalmente expedido de licenciado en derecho;\nIII.- Tener cinco años de ejercicio profesional, posteriores a la fecha de expedición del acreditable en materia laboral;\nLey del Servicio Civil de los Trabajadores al Servicio de los Poderes Página 32\nIV.- Haberse distinguido en estudios de derecho del trabajo y de la seguridad social;\nV.- No pertenecer al estado eclesiástico, y\nVI.- No haber sido condenado por delitos contra la propiedad o sufrir pena mayor de un año de prisión por cualquier otra clase de delitos intencionales.\nArtículo Reformado\nARTICULO 105.- El tribunal contará con un secretario general de acuerdos, los secretarios actuarios y el personal que sea necesario. Los secretarios y actuarios así como los empleados del tribunal estarán sujetos a la presente Ley. Pero los conflictos que se susciten con su relación laboral serán resueltos por la Junta Local de Conciliación y Arbitraje que corresponda según el domicilio de adscripción del trabajador.\nPara los juicios que se presenten en contra de las Instituciones Públicas que tienen jurisdicción en los municipios de Ensenada, Tecate, Tijuana y Playas de Rosarito, el tribunal podrá contar con una Sala Especial en la ciudad de Tijuana Baja California, para su debida tramitación, misma que contará con un Presidente Auxiliar para trámites en la sala Especial, un Secretario Auxiliar del Secretario de Acuerdos, que cuente con fe pública, los secretarios actuarios y el personal que sea necesario.\nArtículo Reformado\nARTICULO 106.- El tribunal nombrará, removerá o suspenderá a sus trabajadores en los términos de esta Ley.\nLos salarios que originen el funcionamiento del tribunal así como los gastos serán cubiertos por el Estado, consignándose en el presupuesto de egresos estatal.\nARTICULO 107.- El tribunal de arbitraje será competente para:\nI.- Resolver conflictos que se susciten entre las Autoridades Públicas y sus trabajadores;\nII.- Resolver los conflictos colectivos que surjan entre las Autoridades Públicas y las organizaciones sindicales de trabajadores a su servicio;\nIII.- Conocer y resolver de los conflictos sindicales o intersindicales.\nIV.- Conocer del registro de los sindicatos y federaciones estatales, y en su caso parte.\nV.- Efectuar el registro de las Condiciones Generales de Trabajo, Reglamentos de\nEscalafón, Reglamentos de las Comisiones Mixtas de Seguridad e Higiene, Estatutos de los\nSindicatos y elección de los cuerpos directivos de los sindicatos.\nVI.- Designar árbitro, cuando exista desacuerdo en la Comisión Mixta de Escalafón.\nVII.- Aprobar su Reglamento Interior de Trabajo, sus Manuales de Organización y su\nLey del Servicio Civil de los Trabajadores al Servicio de los Poderes Página 33\nCatálogo de Puestos.\nArtículo Reformado\nCAPÍTULO II\nDEL PROCEDIMIENTO\nARTICULO 108.- En el procedimiento ante el tribunal de arbitraje no se requiere forma o solemnidad especial en las promociones o intervenciones de las partes.\nARTICULO 109.- La demanda debe contener:\n1.- Nombre y Domicilio del reclamante.\n2.- Nombre y domicilio de la demandada. Cuando la demandada sea la Autoridad\nPública, también se deberá señalar la denominación y ubicación de la dependencia, área o unidad administrativa en la que trabajador preste sus servicios.\nLas demandas en contra de la autoridad pública deberán enderezarse a su nombre y no en contra de los servidores públicos que en ella laboren.\nSerán improcedentes las demandas que no observen lo dispuesto en el párrafo anterior.\nLas Autoridades Públicas deberán proporcionar sus domicilios actuales al Tribunal de\nArbitraje para que elabore y difunda un padrón de domicilios.\n3.- Objeto de la demanda.\n4.- Una relación de los hechos en que se fundamente la demanda.\n5.- La fundamentación del derecho y puntos petitorios en que se condense lo anterior.\n6.- Una copia de la demanda y documentos presentados para el traslado.\nCuando la demanda del trabajador sea incompleta, en cuanto que no comprenda todas las prestaciones que de acuerdo con esta Ley deriven de la acción intentada o procedente, o se estuvieren ejerciendo acciones contradictorias conforme a los hechos expuestos por el trabajador; el Tribunal de Arbitraje, previo a la admisión de la demanda, lo que hubiere incurrido, de no atender el requerimiento, se le tendrá por admitida en su perjuicio en los términos planteados.\nArtículo Reformado\nARTICULO 110.- Son personales las notificaciones siguientes:\nI.- El emplazamiento a juicio y en todo caso en que se trate de la primera notificación.\nII.- El auto del tribunal de arbitraje en el que se haga saber a las partes que se recibió la sentencia de amparo.\nLey del Servicio Civil de los Trabajadores al Servicio de los Poderes Página 34\nIII.- La resolución que ordene la reanudación del procedimiento cuya tramitación estuviese interrumpida por cualquier causa legal, y la que cite a absolver posiciones.\nIV.- La resolución que cite para la audiencia a que se refiere el artículo 117.\nV.- La declaratoria de caducidad, los acuerdos con apercibimiento, la vista en el recurso de revisión y su correspondiente resolución.\nVI.- La resolución de incompetencia dictada por el Tribunal.\nVII.- La resolución que deban conocer los terceros extraños al juicio.\nVIII.- El auto por el que se ordena la reposición de actuaciones.\nIX.- El auto que cite a declarar a las partes o a absolver posiciones.\nX.- El laudo.\nXI.- En casos urgentes o cuando concurran circunstancias especiales a juicio del\nPleno del Tribunal.\nArtículo Reformado\nARTICULO 111.- Las notificaciones personales surtirán sus efectos día y hora en que se practiquen; las que no lo sean, al día siguiente de su publicación.\nARTICULO 112.- Las notificaciones deben hacerse en horas hábiles, con una anticipación de cinco días, por lo menos, del día y hora en que deba tener lugar la diligencia, salvo lo dispuesto en el artículo 117.\nLas notificaciones para desahogo de pruebas a cargo de las partes, se harán en el domicilio procesal señalado en autos, independientemente del lugar que hubiere señalado el oferente para la práctica de la prueba.\nArtículo Reformado\nARTICULO 113.- Las notificaciones hechas al representante de cual quiera de las partes acreditado ante el tribunal surtirán los mismos efectos si se hubiesen hecho a ellas.\nARTICULO 114.- Las audiencias serán públicas, el tribunal podra ordenar, de oficio o negocios, la moral o las buenas costumbres.\nARTICULO 115.- El tribunal dictara las resoluciones dentro de un termino no mayor de veinticuatro horas, salvo disposiciones en contrario de esta Ley.\nARTICULO 116.- Las resoluciones del tribunal deberán firmarse por los representantes que las voten y autorizarse por el secretario. intervengan en ellas y serán autorizadas por el secretario.\nLey del Servicio Civil de los Trabajadores al Servicio de los Poderes Página 35\nToda actuación deberá ser firmada por el secretario, excepción hecha de las diligencias hechas por otros funcionarios.\nARTICULO 117.- Tan pronto se tenga por admitida la primera promoción o demanda en su caso, relativa a un conflicto individual, colectivo de naturaleza jurídica o sindical, el conciliación, demanda y excepciones que deberá efectuarse dentro de los quince días siguientes a la fecha de su admisión, salvo lo dispuesto en el párrafo segundo de este artículo.\nLa notificación de la demanda será personal, corriéndosele a la parte demandada traslado de la misma por lo menos diez días hábiles con anticipación a la celebración de la audiencia indicada en el párrafo anterior, en la cual deberá producir su contestación, sin perjuicio de que la parte demandada pueda presentar por escrito su contestación aun antes del día y hora programados para la celebración de la audiencia por conducto de oficialía de partes del tribunal que conozca del juicio. Cuando el número de actores en una demanda de tipo individual exceda de tres, se ampliará el término para contestar a la demandada, en un día hábil más por cada tres actores adicionales, y así sucesivamente.\nSi el demandado no puede ser notificado en el lugar de residencia del tribunal, se aumentará el término a que se refiere el párrafo anterior a razón de un día por cada 100 kilómetros o fracción.\nEl Tribunal está facultado y obligado a adoptar todas las medidas necesarias para el efecto de resolver los juicios en un término máximo de doce meses a partir de la presentación de la demanda.\nArtículo Reformado\nARTICULO 118.- La audiencia a que se refiere el Artículo anterior se celebrará de conformidad con las normas siguientes:\nI.- El tribunal exhortará a las partes para que procuren un arreglo conciliatorio.\nII.- Si las partes llegan a un convenio se dará por terminado el conflicto, el convenio aprobado por el tribunal, producirá todos los efectos jurídicos inherentes a un laudo.\nIII.- Si no se llega a un convenio se dará por concluido el periodo de conciliación y se pasará demanda y excepciones.\nIV.- El actor expondrá su demanda por escrito o verbalmente por medio de comparecencia, precisando los puntos petitorios y sus fundamentos. Siempre que se las bases para fijarla.\nV.- En la contestación que se efectúe por escrito o verbalmente por medio de comparecencia opondrá el demandado sus excepciones y defensas, debiendo referirse a todos y cada uno de los hechos que comprendan la demanda, afirmándolos, negándolos o\nLey del Servicio Civil de los Trabajadores al Servicio de los Poderes Página 36 sucedieron. Se tendrán por admitidos los hechos sobre los que el demandado no suscitare controversia, salvo prueba en contrario. La negación pura y simple del derecho importa la confesión de los hechos. La confesión de los hechos no entraña la aceptación del derecho.\nVI.- Las partes podran replicar y duplicar bremente.\nVII.- Las audiencias, según corresponda, estarán a cargo de los Secretarios de\nAudiencias, el Secretario General de Acuerdos del Tribunal o el Presidente del Tribunal, quienes resolverán todas las cuestiones que en ellas se susciten.\nArtículo Reformado\nARTÍCULO 118 BIS.- Las partes podrán interponer recurso de revisión, en contra de las siguientes resoluciones o acuerdos:\nI.- Las que versen sobre personalidad.\nII.- Las que versen sobre competencia.\nIII.- Las que versen sobre admisión de pruebas.\nIV.- Las que versen sobre nulidad de actuaciones.\nV.- Las que versen sobre el interés de terceros.\nEl recurso de revisión se interpondrá dentro de las cuarenta y ocho horas siguientes a la notificación de la resolución o acuerdo; se tramitará incidentalmente y suspenderá el curso del proceso hasta en tanto se resuelva aquél. Con su interposición se le dará vista a la parte contraria, para que en plazo de tres días manifieste lo que a sus intereses convenga; desahogada la vista o no, el Pleno del Tribunal de Arbitraje resolverá de plano dentro del plazo de cinco días.\nArtículo Adicionado\nARTICULO 119.- Si no concurren las partes a la audiencia se les tendrá por inconformes con todo arreglo y, según corresponda, por reproducida en vía de demanda o contestación su escrito inicial. Si el demandado no asiste a la audiencia y tampoco rindió su contestación por escrito, se le tendrá por contestada la demanda en sentido afirmativo.\nLas partes, en su primera comparecencia verbal o escrita, deberán señalar domicilio dentro del lugar de residencia del Tribunal de Arbitraje para recibir notificaciones; si no lo hacen, las notificaciones personales se harán por boletín o por estrados, según el caso, en para tales fines.\nArtículo Reformado\nARTICULO 120.- El demandado que no hubiese concurrido a la audiencia a que se refiere el artículo anterior. Solo podrá rendir prueba en contrario para demostrar que no existió el despido, suspensión o separación del actor o que no son ciertos los hechos\nLey del Servicio Civil de los Trabajadores al Servicio de los Poderes Página 37 afirmados en la demanda.\nARTICULO 121.- Si ninguna de las partes concurre a la audiencia, se archivará el expediente hasta nueva promoción.\nARTICULO 122.- Si las partes están conformes con los hechos, y la controversia queda reducida a un punto de derecho, al concluir la audiencia de demanda y excepciones el tribunal oirá los alegatos de las partes y dictará el laudo.\nARTICULO 123.- El tribunal, al concluir la audiencia de demanda y excepciones, salvo lo dispuesto en el artículo anterior señalará día y hora para la celebración de la audiencia de ofrecimiento de pruebas que deberá efectuarse dentro de los diez días siguientes.\nARTICULO 124.- En la audiencia de ofrecimiento de pruebas se observarán las normas siguientes:\nI.- Si ninguna de las partes concurre o resultan mal representadas se les tendrá por perdido su derecho a ofrecer pruebas en el juicio y el tribunal procederá de conformidad con lo dispuesto en el artículo 121.\nII.- Si concurre una o ambas partes, ofrecerán sus pruebas de conformidad con las fracciones siguientes.\nIII.- Las pruebas deben referirse a los hechos contenidos en la demanda y su contestación que no hayan sido confesados por la parte a quien perjudiquen.\nIV.- Las pruebas se ofrecerán acompañadas de los elementos necesarios para su desahogo.\nV.- Las partes están obligadas a aportar todos los elementos de prueba de que dispongan, que pueden contribuir a la comprobación de los hechos o al esclarecimiento de la verdad, salvo aquellos que por imposibilidad física o legal no puedan presentarse, pudiendo en dicho caso solicitar al tribunal que por su conducto sean requeridos los informes correspondientes y la citación de personas así como la certificación de hechos o documentos y en auxilio de peritos.\nVI.- Concluido el ofrecimiento, el tribunal resolverá cuales son las pruebas que admite y desechará las que estime improcedentes, y\nVII.- Dictada la resolución a que se refiere la fracción anterior, no se admitirán nuevas las tachas que se hagan valer en contra de los testigos.\nARTICULO 125.- El Tribunal de Arbitraje, al concluir la audiencia de ofrecimiento de pruebas, y dentro de los diez días siguientes, las calificará y fijará la fecha para el desahogo de aquéllas que hubiere admitido.\nLey del Servicio Civil de los Trabajadores al Servicio de los Poderes Página 38 planteada o resulten inútiles o intrascendentes, expresando el motivo de ello.\nArtículo Reformado\nARTICULO 126.- El actor está obligado a probar los hechos constitutivos de su acción y el demandado sus excepciones; no obstante, corresponderá a la Autoridad Pública probar su dicho cuando exista controversia sobre:\nI.- Fecha de ingreso del trabajador y tipo de nombramiento.\nII.- Antigüedad del trabajador.\nIII.- Faltas de asistencia del trabajador.\nIV.- Causa de rescisión de la relación de trabajo; excepto, cuando se trate de trabajador de confianza.\nV.- Terminación de la relación o contrato de trabajo.\nVI.- Constancia de haber dado aviso por escrito al trabajador de la fecha y causa de su despido; excepto, cuando se trate de trabajador de confianza.\nVII.- El contrato de trabajo.\nVIII.- Duración de la jornada legal de trabajo.\nIX.- Pagos de días de descanso y obligatorios.\nX.- Disfrute y pago de las vacaciones.\nXI.- Pago de las primas dominical, vacacional y de antigüedad.\nXII.- Monto y pago del salario.\nXIII.- Los nombramientos expedidos a los trabajadores.\nLa Autoridad Pública tiene la obligación de exhibir en juicio los documentos antes enlistados, cuando lo hubiere requerido el trabajador y lo apruebe el Tribunal de Arbitraje.\nLos documentos referidos en las fracciones anteriores podrán ser exhibidos en el juicio, en original o en copia certificada.\nLos documentos aludidos en la fracción I, II, III, VII y VIII deberán conservarse mientras dure la relación laboral; los señalados por las fracciones IX al XII durante el último año y un año después de que se extinga la relación laboral. En ningún caso se podrá exigir un período mayor al señalado.\nDe no presentarse el o los documentos mencionados en este Artículo, se presumirán directamente con tales documentos; salvo la prueba en contrario. El Tribunal de Arbitraje los hechos que se pretenden acreditar.\nArtículo Reformado\nLey del Servicio Civil de los Trabajadores al Servicio de los Poderes Página 39\nArtículo 126 BIS.- Son medios de prueba:\nI.- La confesional.\nII.- La declaración de parte.\nIII.- Las documentales.\nIV.- El informe de autoridad.\nV.- La testimonial.\nVI.- La pericial.\nVII.- La inspección.\nVIII.- La presuncional.\nIX.- La instrumental de actuaciones.\nX.- Los elementos aportados por los avances de la ciencia y la tecnología.\nXI.- Todos los medios de prueba que no sean contrarios a la moral y al derecho.\nArtículo Adicionado\nARTICULO 127.- Las partes podrán interrogar libremente a las personas que intervengan en la audiencia de desahogo de pruebas sobre los hechos controvertidos, hacerse mutuamente las preguntas que juzguen convenientes y examinar los documentos y objetos que exhiban.\nARTICULO 128.- Si alguna persona no puede por enfermedad u otras circunstancias especiales, concurrir al local del tribunal para absolver posiciones o contestar un interrogatorio, el tribunal, previa comprobación del hecho podrá trasladarse al local donde aquella se encuentre.\nARTICULO 129.- Al concluir la recepción de las pruebas de oficio, el tribunal concederá a las partes un término de 48 horas para que presenten sus alegatos por escrito.\nARTICULO 130.- Transcurrido el término para la presentación de los alegatos, de dictamen que deberá contener:\nI.- Un extracto de la demanda y la contestación.\nII.- El señalamiento de los hechos controvertidos y de los aceptados por las partes.\nIII.- Una enumeración de las pruebas rendidas y su apreciación en conciencia, señalando los hechos que deban considerarse probados; y\nIV.- Las concluciones que se deduzcan de lo alegado y probado.\nLey del Servicio Civil de los Trabajadores al Servicio de los Poderes Página 40\nARTICULO 131.- El dictamen se agregará al expediente y se entregará una copia a cada uno de los representantes de los trabajadores y de las instituciones públicas.- El representantes o de la negativas de estos a recibirlas.\nARTICULO 132.- El presidente citará para la audiencia de discusión y votación que deberá efectuarse dentro de los diez días siguientes al en que sean entregadas a los representantes las copias del dictamen.\nARTICULO 133.- Los laudos se dictarán a verdad sabida, sin necesidad de sujetarse a reglas sobre estimación de las pruebas, sino apreciando los hechos según los miembros del tribunal lo crean debido en conciencia.\nARTICULO 134.- Todos los términos correrán a partir del día hábil siguiente a aquel en que se haga el emplazamiento citación o notificación y se contaran en ellos el día del vencimiento.\nEn ningún término se contarán los días en que no puedan tener lugar actuaciones ante el tribunal, salvo disposición en contraria.\nTratándose de conflictos de huelga todos los días son hábiles.\nARTICULO 135.- Las actuaciones en el tribunal deben de practicarse en días y horas hábiles bajo pena de nulidad.\nSon días hábiles todos los del año con excepción de los días de vacaciones concedidas al tribunal, los feriados, los sábados y domingos y los de descanso obligatorio.\nARTICULO 136.- Son horas hábiles, las comprendidas entre las siete horas y las diez y nueve horas del día.\nARTICULO 137.- El tribunal puede habilitar los días y horas inhábiles para que se practiquen diligencias, cuando hubiere causa urgente que lo exija o por necesidades del mismo manifestando las diligencias que hayan de practicarse.\nARTICULO 138.- Los miembros del tribunal de arbitraje podrán ser recusados y se podrán excusar con causa legítima.\nARTICULO 139.- Las resoluciones del tribunal de arbitraje no admiten ningún recurso.\nARTICULO 140.- De todas las actuaciones sin excepción, se levantará acta circunstanciada y la firmarán todos los que en ella intervengan, dando fe el secretario.\nARTICULO 141.- Las autoridades civiles y militares están obligadas a prestar auxilio al tribunal de arbitraje, para hacer respetar sus resoluciones cuando fuere requeridas para\nLey del Servicio Civil de los Trabajadores al Servicio de los Poderes Página 41 ello.\nCAPÍTULO III\nDE LOS MEDIOS PROBATORIOS\nCapítulo Adicionado\nSECCIÓN A\nCONFESIONAL\nArtículo 141 BIS.- Cada parte podrá solicitar se cite a su contraparte para que concurra a absolver posiciones.\nArtículo Adicionado\nArtículo 141 BIS 1.- El trabajador podrá solicitar que se cite a absolver posiciones a los servidores públicos que ejerzan funciones de dirección y administración en la Autoridad\nPública, así como a los miembros de la directiva de los sindicatos, cuando los hechos que dieron origen al conflicto les sean propios y se les hayan atribuido en la demanda o contestación, o bien que por razones de sus funciones les deban ser conocidos.\nLos servidores públicos pertenecientes a las Autoridades Públicas, desde jefes de departamento o sus equivalentes hasta los titulares, podrán desahogar la prueba mediante oficio, por el absolvente o por conducto de su representante o apoderado legal.\nArtículo Adicionado\nArtículo 141 BIS 2.- El Tribunal de Arbitraje ordenará se cite a los absolventes, apercibiéndolos de que si no concurren el día y hora señalados, se les tendrá por confesos de las posiciones exhibidas y previamente calificadas de legales.\nArtículo Adicionado\nArtículo 141BIS 3.- En el desahogo de la prueba confesional se observarán las disposiciones siguientes:\nI.- Las posiciones deberán formularse por escrito, y ser exhibidas debidamente firmadas por la parte interesada en el momento del ofrecimiento de pruebas;\nII.- Las posiciones deberán concretarse a los hechos controvertidos; no deberán ser insidiosas o inútiles. Son insidiosas las posiciones que tiendan a ofuscar la inteligencia del que ha de responder, para obtener una confesión contraria a la verdad. Son inútiles aquellas fehaciente que conste en autos o sobre los que no exista controversia;\nIII.- Las posiciones serán calificadas previamente, y cuando no reúnan los requisitos a que se refiere la fracción anterior, el Tribunal las desechará asentando en autos el fundamento y motivo concreto en que apoye su resolución;\nIV.- Si la persona citada para absolver posiciones, no concurre en la fecha y hora señalada, se hará efectivo el apercibimiento a que se refiere el artículo anterior y se le declarará confesa de las posiciones que se hubieren calificado de legales previamente;\nLey del Servicio Civil de los Trabajadores al Servicio de los Poderes Página 42\nV.- Sólo podrán formularse nuevas posiciones libremente, en caso de asistencia del absolvente a la audiencia, y se harán constar textualmente en el acta respectiva;\nVI.- El absolvente bajo protesta de decir verdad, responderá por sí mismo, de palabra, sin la presencia de su asesor o asistencia de persona alguna. No podrá valerse de borrador de respuestas pero se le permitirá que consulte simples notas o apuntes, si el Tribunal, después de tomar conocimiento de ellos, resuelve que son necesarios para auxiliar su memoria;\nVII.- El absolvente contestará categóricamente las posiciones afirmando o negando; pudiendo agregar las explicaciones que juzgue convenientes o las que le pida el Tribunal; las respuestas también se harán constar textualmente en el acta respectiva;\nVIII.- Si el absolvente se niega a responder o sus respuestas son evasivas, el Tribunal de oficio o a instancia de parte, lo apercibirá en el acto de tenerlo por confeso si persiste en ello, debiendo hacer constar en autos tal circunstancia, y de continuar con dicha conducta el absolvente deberá hacerse efectivo el apercibimiento. Se considerará respuesta evasiva las que el declarante se limite a remitirse a su escrito de demanda o de contestación de demanda, según sea el caso, o cualquier conducta semejante tendiente a eludir la respuesta, y\nIX.- El escrito, que contenga las posiciones se mandará agregar a los autos y deberá ser firmado por el absolvente.\nArtículo Adicionado\nArtículo 141BIS 4.- Si la persona que deba absolver posiciones tiene su residencia fuera del lugar donde se encuentre el Tribunal de Arbitraje, éste librará exhorto, acompañando, en sobre cerrado y sellado, el pliego de posiciones previamente calificado; del que deberá sacarse una copia que se guardará en el secreto del Tribunal.\nLa autoridad exhortada recibirá la confesional y la desahogara en los términos del\nArtículo anterior a solicitud del Tribunal exhortante.\nArtículo Adicionado\nArtículo 141 BIS 5.- Se tendrán por confesión expresa y espontánea, las afirmaciones contenidas en las posiciones que formule el articulante.\nArtículo Adicionado\nArtículo 141 BIS 6.- Cuando la persona a quien se señale para absolver posiciones sobre hechos propios, ya no labore para la Autoridad Pública, previa comprobación del hecho, el oferente de la prueba será requerido para que proporcione el domicilio donde deba ser citada. En el supuesto antes señalado, cambiará la naturaleza de la prueba de confesional a testimonial.\nSi la persona citada no concurre el día y hora señalados, el Tribunal lo hará presentar auxiliándose de las distintas instituciones policiales.\nArtículo Adicionado\nArtículo 141 BIS 7.- Se tendrán por confesión expresa y espontánea de las partes, sin\nLey del Servicio Civil de los Trabajadores al Servicio de los Poderes Página 43 necesidad de ser ofrecida como prueba, las manifestaciones contenidas en las constancias y las actuaciones del juicio.\nArtículo Adicionado\nArtículo 141BIS 8.- La confesión realizada en los términos de esta Ley, hará prueba plena.\nArtículo Adicionado\nSECCIÓN B\nDECLARACIÓN DE PARTE\nArtículo 141 BIS 9.- Las partes podrán pedir que la contraparte se presente a declarar sobre los interrogatorios que por anticipado o en el acto de la diligencia se le formulen. Están obligadas a declarar las mismas personas que están obligadas a absolver posiciones.\nCuando se trate de los titulares de las Autoridades Públicas, Dependencias o\nUnidades Administrativas, desde los jefes de departamento o sus equivalentes, la declaración se desahogarán mediante oficio.\nLos interrogatorios podrán formularse libremente, sin más limitación que las preguntas se refieran a los hechos controvertidos.\nArtículo Adicionado\nArtículo 141 BIS 10.- En la prueba de declaración de parte se observarán las disposiciones siguientes:\nI.- Podrá recibirse con independencia de la prueba confesional;\nII.- Cuando la persona no comparezca al desahogo de esta prueba, el Tribunal, deberá usar los medios de apremio autorizados por la Ley para hacerla comparecer, y\nIII.- No procede la confesión ficta en la prueba de declaración de parte, pero si el declarante se niega a responder o sus respuestas son evasivas, el Tribunal de oficio o a instancia de parte, lo apercibirá en el acto de aplicarle cualquiera de las medidas disciplinarias establecidas en esta Ley si persiste en ello, debiendo hacer constar en autos tal apercibimiento. Se considerarán como respuestas evasivas las que el declarante pronuncie limitándose a remitirse a su escrito de demanda o de contestación de demanda, según sea el caso, o cualquier conducta semejante tendiente a eludir la respuesta.\nEn caso de evasivas del declarante, el Tribunal valorará tal conducta procesal al momento de emitir su resolución, presumiendo como ciertos los hechos que se pretenden acreditar y que se desprendan del interrogatorio realizado.\nArtículo Adicionado\nArtículo 141 BIS 11.- Serán aplicables a esta prueba, en lo conducente, las reglas de la prueba confesional.\nArtículo Adicionado\nLey del Servicio Civil de los Trabajadores al Servicio de los Poderes Página 44\nSECCIÓN C\nDOCUMENTALES\nArtículo 141 BIS 12.- Son documentos públicos aquellos cuya formulación o pública, así como los que expidan en ejercicio de sus funciones.\nLos documentos públicos expedidos por las autoridades harán fe en el juicio sin necesidad de legalización.\nArtículo Adicionado\nArtículo 141 BIS 13.- Son documentos privados los que no reúnen las condiciones previstas por el artículo anterior.\nArtículo Adicionado\nArtículo 141 BIS 14.- Los documentos privados se presentarán en originales por la parte oferente; si éstos se objetan en cuanto a contenido y firma se dejarán en autos hasta su perfeccionamiento. Si no son objetados, la oferente podrá solicitar la devolución del original, previa copia certificada en autos.\nArtículo Adicionado\nArtículo 141 BIS 15.- Si el documento privado consiste en copia simple o fotostática se podrá solicitar, en caso de ser objetado, la compulsa o cotejo con el original; para este efecto, la parte oferente deberá precisar el lugar donde el documento original se encuentre.\nArtículo Adicionado\nArtículo 141 BIS 16.- Si el documento original sobre el que deba practicarse el cotejo o compulsa se encuentra en poder de un tercero, éste estará obligado a exhibirlo.\nArtículo Adicionado\nArtículo 141 BIS 17.- Cuando un documento que provenga de tercero ajeno al juicio, resulta impugnado, deberá ser ratificado en su contenido y firma por el suscriptor, para lo cual deberá ser citado personalmente, en los términos del artículo 110 de esta Ley.\nLa contraparte podrá formular las preguntas en relación con los hechos contenidos en el documento.\nArtículo Adicionado\nArtículo 141 BIS 18.- Los interesados presentarán los originales de los documentos privados y, cuando formen parte de un libro, expediente o legajo, exhibirán copia para que se compulse la parte que señalen, indicando el lugar en donde éstos se encuentren.\nArtículo Adicionado\nArtículo 141 BIS 19.- Se reputa autor de un documento privado al que lo suscribe. Se entiende por suscripción, la colocación al pie del escrito de la firma o huella digital que sean idóneas, para identificar a la persona que suscribe. suscriptor cuando sea ratificado en su contenido y firma o huella digital; excepto en los casos en que el contenido no se repute proveniente del autor, circunstancia que deberá justificarse\nLey del Servicio Civil de los Trabajadores al Servicio de los Poderes Página 45 con prueba idónea. será necesaria para otorgarle plena fe al documento, cuando el que suscribió el mismo, es parte en el juicio y no se haya objetado la autenticidad de la firma o huella digital.\nArtículo Adicionado\nArtículo 141 BIS 20.- Cada parte exhibirá los documentos u objetos que ofrezca como prueba para que obren en autos. Si se trata de informes, o copias, que deba expedir alguna autoridad, el Tribunal de Arbitraje deberá solicitarlos directamente.\nArtículo Adicionado\nArtículo 141 BIS 21.- Siempre que uno de los litigantes pida copia o testimonio de un documento, pieza o expediente que obre en las oficinas públicas, la parte contraria tendrá derecho de que, a su costa, se adicione con lo que crea conducente del mismo documento, pieza o expediente.\nArtículo Adicionado\nArtículo 141 BIS 22.- Los documentos existentes en el lugar donde se promueva el juicio, que se encuentren en poder de la contraparte, autoridades o terceros, serán objeto de cotejo o compulsa, a solicitud de la oferente, por conducto del actuario.\nLos documentos existentes en lugar distinto del de la residencia del Tribunal de\nArbitraje, que se encuentren en cualquiera de los supuestos mencionados en el párrafo anterior, se cotejarán o compulsarán a solicitud del oferente, mediante exhorto dirigido a la autoridad que corresponda.\nPara que proceda la compulsa o cotejo, deberá exhibirse en la audiencia de ofrecimiento de pruebas, copia del documento que por este medio deba ser perfeccionado.\nCuando el documento no haya sido perfeccionado, carecerá de valor probatorio.\nArtículo Adicionado\nArtículo 141 BIS 23.- Para que hagan fe en el territorio de Baja California, los documentos procedentes del extranjero deberán presentarse debidamente legalizados conforme a las reglas que establezcan las leyes relativas, y si son en idioma extranjero, deberán acompañarse de su traducción.\nArtículo Adicionado\nArtículo 141 BIS 24.- Las copias hacen presumir la existencia de los originales, conforme a las reglas procedentes; pero si se pone en duda su exactitud, deberá ordenarse su cotejo con los originales de que se tomaron, siempre y cuando así se haya ofrecido.\nArtículo Adicionado\nArtículo 141 BIS 25.- Si se objeta la autenticidad de algún documento en cuanto a contenido, firma o huella digital, las partes podrán ofrecer pruebas con respecto a las objeciones, las que se recibirán, si fueren procedentes, en la audiencia de recepción de pruebas a que se refiere el Artículo 125 de esta Ley.\nArtículo Adicionado\nArtículo 141 BIS 26.- Cuando los documentos públicos contengan declaraciones o\nLey del Servicio Civil de los Trabajadores al Servicio de los Poderes Página 46 manifestaciones hechas por particulares, sólo prueban que las mismas fueron hechas ante la autoridad que expidió el documento. hicieron o asistieron al acto en que fueron hechas y se manifestaron conformes con ellas.\nArtículo Adicionado\nSECCIÓN D\nINFORME DE AUTORIDAD Y DE TERCEROS\nArtículo 141 BIS 27.- Las partes pueden pedir que por conducto del Tribunal de\nArbitraje se solicite que cualquier autoridad, organismo, tercero ajeno al juicio, informe respecto de algún hecho, constancia o documento que obre en sus archivos de los que hayan tenido conocimiento por razón de la función que desempeñen y que se relacione con la materia del litigio.\nTratándose de Autoridad Pública demandada, podrán solicitarse los informes sólo a autoridades diferentes a la dependencia de adscripción de la parte actora.\nArtículo Adicionado\nArtículo 141 BIS 28.- Las autoridades, organismos o terceros requeridos, estarán obligadas a proporcionar al Tribunal de Arbitraje, los informes y datos de que tengan conocimiento en el ejercicio de la función que desempeña que guarden relación con el informe requerido.\nArtículo Adicionado\nArtículo 141 BIS 29.- Recibido el informe por el Tribunal de Arbitraje, éste de oficio o a instancia de parte, podrá disponer que la autoridad, organismo o tercero que lo haya emitido esclarezca o amplíe cualquier punto, que no haya sido informado conforme a lo solicitado.\nArtículo Adicionado\nArtículo 141 BIS 30.- Los informes de las autoridades harán fe cuando se trate de hechos que conozcan por razón de su función, y no estén contradichos por otras pruebas fehacientes que obren en autos.\nLos informes rendidos por terceros que no tengan el carácter de autoridades, deberán ser valorados prudentemente por el Tribunal de Arbitraje, adminiculándolos con las probanzas relacionadas y siempre que no se encuentren contradichas por otras pruebas.\nArtículo Adicionado\nSECCIÓN E\nTESTIMONIAL\nArtículo 141 BIS 31.- La parte que ofrezca prueba testimonial deberá cumplir con los requisitos siguientes:\nI.- Sólo podrán ofrecerse un máximo de tres testigos por cada hecho controvertido\nLey del Servicio Civil de los Trabajadores al Servicio de los Poderes Página 47 que se pretenda probar.\nII.- Indicará los nombres y domicilios de los testigos; cuando exista impedimento para presentar directamente a los testigos, deberá solicitarse al Tribunal de Arbitraje que los cite, señalando la causa o motivo justificados que le impidan presentarlos directamente.\nIII.- Si el testigo radica fuera del lugar de residencia del Tribunal de Arbitraje, el oferente deberá al ofrecer la prueba, acompañar interrogatorio por escrito, al tenor del cual deberá ser examinado el testigo; de no hacerlo, se declarará desierta. Asimismo, exhibirá copias del interrogatorio, que se pondrán a disposición de las demás partes, para que dentro del término de tres días presenten su pliego de repreguntas en sobre cerrado.\nIV.- Cuando a juicio del Tribunal de Arbitraje el testigo sea servidor público desde jefe de departamento o sus equivalentes, deberá rendir su declaración por medio de oficio.\nV.- A quien proporcione domicilio inexacto o inexistente de algún testigo o de comprobarse que se solicitó su citación con el propósito de retardar el procedimiento, se le impondrá al oferente una multa de hasta doce veces el valor diario de la Unidad de Medida y\nActualización vigente, declarándose desierta la prueba respecto de quien haya sido propuesto como testigo.\nFracción Reformada\nVI.- La sustitución de un testigo será procedente cuando se acredite ante el Tribunal de Arbitraje, causa superveniente que le impida acudir al desahogo de la prueba, o cuando se ponga en duda por el oferente su imparcialidad. Debiendo notificarse a la contraparte, por lo menos con cinco días de anticipación a la fecha señalada para el desahogo de la testimonial.\nArtículo Reformado\nArtículo 141 BIS 32.- El Tribunal de Arbitraje, en el caso de la fracción II del artículo anterior, ordenará se cite al testigo para que rinda su declaración, en la hora y día que al efecto se señale, con el apercibimiento de que de no asistir, se le aplicará indistintamente los medios de apremio necesarios para obligarlo a comparecer, además de que podrá ser presentado por conducto de la autoridad pública.\nEn caso de que dejare de concurrir a la audiencia, no obstante haber sido citado legalmente, se le hará efectivo el apercibimiento decretado.\nArtículo Adicionado\nArtículo 141 BIS 33.- En el desahogo de la prueba testimonial se observarán las normas siguientes:\nI.- El oferente de la prueba presentará directamente a sus testigos, salvo lo dispuesto en el Artículo 141 BIS 31, fracción III y IV, y el Tribunal de Arbitraje procederá a recibir su testimonio.\nII.- El testigo deberá identificarse ante el Tribunal de Arbitraje, a menos que las partes en juicio lo reconozcan expresamente. En caso de no comparecer con identificación se\nLey del Servicio Civil de los Trabajadores al Servicio de los Poderes Página 48 declarará desierta en perjuicio del oferente, salvo el caso señalado en la fracción II del artículo 141 BIS 31 de esta Ley, en cuyo caso no se desahogará la prueba hasta en tanto el testigo comparezca debidamente identificado, apercibiéndosele en los términos del artículo\n141 BIS 32.\nIII.- Los testigos serán examinados por separado, en el orden en que fueran ofrecidos.\nLos interrogatorios se formularán oralmente, salvo lo dispuesto en las fracciones III y IV del artículo 141 BIS 31 de esta Ley.\nIV.- Después de tomarle al testigo la protesta de conducirse con verdad y de advertirle de las penas en que incurren los testigos falsos, se hará constar el nombre, edad, estado civil, domicilio, ocupación y lugar en que trabaja y se procederá a tomar su declaración.\nV.- Las partes formularán las preguntas en forma verbal y directa, debiendo tener relación con el asunto de que se trata, estar concebidas en términos claros y precisos, procurando que en una sola no se comprenda más de un hecho y que no lleve implícita la contestación.\nVI.- Primero interrogará el oferente de la prueba y posteriormente las demás partes repreguntarán sobre el cuestionamiento realizado por el oferente. El Tribunal de Arbitraje, cuando lo estime pertinente, examinará directamente al testigo.\nVII.- Las preguntas y respuestas se harán constar en autos, escribiéndose textualmente unas y otras.\nVIII.- Cuando el testigo deje de contestar algún punto o haya incurrido en contradicción, o se haya expresado con ambigüedad, pueden las partes llamar la atención del Tribunal de Arbitraje para que éste, si lo estima conveniente, exija al testigo las aclaraciones pertinentes.\nIX.- Los testigos están obligados a dar la razón de su dicho, y el Tribunal de Arbitraje deberá solicitarla, respecto de las respuestas que no la lleven ya en sí.\nX.- El testigo, enterado de su declaración, firmará al margen de las hojas que la contengan y así se hará constar por el Secretario; si no sabe o no puede leer o firmar la declaración, le será leída por el Secretario e imprimirá su huella digital, en caso de negarse a firmar o a estampar su huella, el Secretario asentará la razón y lo hará constar.\nArtículo Adicionado\nArtículo 141 BIS 34.- Si el testigo no habla el idioma español rendirá su declaración por medio de intérprete, que será nombrado por el Tribunal, el que protestará su fiel desempeño. Cuando el testigo lo pidiere, además de asentarse su declaración en español, deberá escribirse en su propio idioma, por él o por el intérprete.\nArtículo Adicionado\nArtículo 141 BIS 35.- El Tribunal, al girar el exhorto para desahogar la prueba testimonial, acompañará el interrogatorio con las preguntas calificadas, e indicará a la autoridad exhortada, los nombres de las personas que tienen facultad para intervenir en la diligencia, señalándole a la autoridad exhortada que la intervención de las partes que en su\nLey del Servicio Civil de los Trabajadores al Servicio de los Poderes Página 49 caso comparezcan, deberá sujetarse a la facultad de realizar preguntas adicionales dadas por el testigo, así como para hacer las manifestaciones que en derecho correspondan.\nArtículo Adicionado\nArtículo 141 BIS 36.- Las objeciones o tachas a los testigos se formularán oralmente al concluir el desahogo de la prueba, para su apreciación posterior por el Tribunal de\nArbitraje.\nCuando se objetare de falso a un testigo, el Tribunal recibirá dentro de los tres días siguientes al desahogo de la testimonial, las pruebas pertinentes para su posterior apreciación al momento de emitir el laudo.\nArtículo Adicionado\nArtículo 141 BIS 37.- Si la parte oferente así lo ofrece, el testigo singular podrá formar convicción, cuando concurran circunstancias que sean garantía de veracidad que lo hagan insospechable de falsear los hechos sobre los que declara, siempre y cuando:\nI.- Fue el único que se percató de los hechos.\nII.- La declaración no se encuentre en oposición con otras pruebas que obren en autos.\nArtículo Adicionado\nArtículo 141 BIS 38.- La declaración de los testigos será valorada según el prudente arbitrio del Tribunal de Arbitraje, tomando en cuenta las declaraciones rendidas y que las mismas hayan sido uniformes, congruentes, imparciales, verosímiles y de certeza.\nArtículo Adicionado\nSECCIÓN F\nPERICIAL\nArtículo 141 BIS 39.- La prueba pericial versará sobre cuestiones relativas a alguna ciencia, técnica, o arte y deberá ofrecerse indicando la materia sobre la que deba versar, exhibiendo el cuestionario respectivo, con copia para cada una de las partes, señalando el domicilio en donde deba ser citado el perito.\nArtículo Adicionado\nArtículo 141 BIS 40.- Los peritos deben tener conocimiento en la ciencia, técnica, o arte sobre el cual debe versar su dictamen; si la profesión o el arte estuvieren legalmente reglamentados, los peritos deberán acreditar estar autorizados, exhibiendo el título o constancia que conforme a la ley corresponda.\nArtículo Adicionado\nArtículo 141 BIS 41.- El Tribunal de Arbitraje citará a los peritos nombrados por las partes, quienes dentro de los tres días siguientes aceptarán y protestarán de desempeñar su cargo con arreglo a la Ley.\nLey del Servicio Civil de los Trabajadores al Servicio de los Poderes Página 50\nArtículo Adicionado\nArtículo 141 BIS 42.- El Tribunal de Arbitraje nombrará los peritos que correspondan a cada parte, eligiéndolo de la lista autorizada por el Tribunal Superior de Justicia del Estado, en los siguientes casos:\nI.- Si alguna de las partes omitiera hacer el nombramiento de perito.\nII.- Si designándolo las partes, no aceptare el cargo.\nIII.- Cuando, habiendo aceptado el cargo, no rindiere su dictamen dentro del término fijado o en la audiencia respectiva.\nIV.- Cuando el que fue nombrado y aceptó el cargo, lo renunciare posteriormente.\nEn los supuestos establecidos en las fracciones II, III y IV de este Artículo, el Tribunal de Arbitraje designará al perito faltante cuando se omita la designación de uno nuevo, dentro del término de tres días que para tal efecto fue concedido por el Tribunal.\nArtículo Adicionado\nArtículo 141 BIS 43.- El honorario de cada perito será pagado por la parte que lo nombró, o en su defecto, lo hubiere nombrado el Tribunal, y el del tercero, por ambas partes.\nArtículo Adicionado\nArtículo 141 BIS 44.- El Tribunal, una vez confirmada la aceptación del cargo por parte de los peritos, procederá a señalar día y hora para celebración de la audiencia de desahogo, la cual deberá ser en un término no menor a 5 días, ni mayor de 15, dependiendo de la complejidad del peritaje.\nArtículo Adicionado\nArtículo 141 BIS 45.- En el desahogo de la prueba pericial se observarán las disposiciones siguientes:\nI.- Cada parte presentará personalmente a su perito del día de la audiencia, salvo el caso previsto en el artículo 141 BIS 42;\nII.- Los peritos en la audiencia rendirán su dictamen por escrito en el orden en que fueron ofrecidos, a menos que por causa justificada soliciten se señale nueva fecha para rendirlo;\nIII.- Las partes y los miembros del Tribunal podrán hacer a los peritos las preguntas que juzguen conveniente; y a su vez los peritos podrán preguntarse entre sí, debiendo quedar asentadas las preguntas y respuestas en el acta respectiva;\nIV.- El Tribunal, a solicitud de las partes, podrá conceder un término de hasta tres días para que realicen sus objeciones por escrito al dictamen; y\nV.- En caso de existir discrepancia en los dictámenes rendidos por los peritos, el\nTribunal designará un perito tercero, eligiéndolo de la lista autorizada por el Tribunal\nSuperior de Justicia del Estado. Aceptado el cargo por el perito designado, el Tribunal señalará fecha para el desahogo, la cual se desarrollará en los mismos términos antes citados.\nLey del Servicio Civil de los Trabajadores al Servicio de los Poderes Página 51\nArtículo Adicionado\nArtículo 141 BIS 46.- El perito tercero en discordia que designe el Tribunal debe excusarse dentro de las cuarenta y ocho horas siguientes, en que se notifique su nombramiento, siempre que concurra alguna de las causas de excusa señalados por esta\nLey.\nEl Tribunal calificará de plano la excusa y, declarada procedente, se nombrará nuevo perito.\nArtículo Adicionado\nArtículo 141 BIS 47.- El dictamen de peritos será valorizado según el prudente arbitrio del Tribunal.\nArtículo Adicionado\nSECCIÓN G\nINSPECCIÓN\nArtículo 141 BIS 48.- La parte que ofrezca la inspección deberá precisar la materia de la misma; el lugar donde debe practicarse, que en todo caso debe ser el lugar en el que se encuentren los instrumentos materia de la inspección; los documentos, objetos, fotografías, videos, cintas cinematográficas y cualquier otra producción de imágenes, registros dactiloscópicos, fonográficos, biométricos, magnéticos, los sistemas de información electrónica y demás avances de la ciencia y tecnología, que deben ser examinados.\nTambién deberá señalar los períodos que abarcará la inspección tomando en cuenta lo dispuesto por el Artículo 141 BIS 21.\nAl ofrecerse la prueba, deberá hacerse en sentido afirmativo, fijando los hechos o cuestiones que se pretenden acreditar con la misma.\nArtículo Adicionado\nArtículo 141 BIS 49.- Admitida la prueba de inspección por el Tribunal de Arbitraje, deberá señalar día y hora para su desahogo. Si los documentos y objetos obran en poder de la contraparte, el Tribunal de Arbitraje apercibirá a la misma que, en caso de no exhibirlos, se tendrán por ciertos presuntivamente los hechos que se tratan de probar, siempre y cuando se tenga certeza que dichos documentos efectivamente obran en poder de la contraparte o bien, en tratándose de los establecidos en el artículo 141 BIS 21 de esta Ley.\nSi los documentos y objetos a inspeccionar obran en poder de la misma parte que los ofrece, el Tribunal de Arbitraje la apercibirá que, en caso de no exhibirlos, se tendrá por desierta la probanza. Si los documentos y objetos se encuentran en poder de personas ajenas a la controversia se aplicarán los medios de apremio que procedan.\nArtículo Adicionado\nArtículo 141 BIS 50.- En el desahogo de la prueba de inspección se observarán las reglas siguientes:\nI.- El actuario, para el desahogo de la prueba, requerirá se le pongan a la vista los\nLey del Servicio Civil de los Trabajadores al Servicio de los Poderes Página 52 ordenado por el Tribunal.\nII.- Las partes y sus apoderados pueden concurrir a la diligencia de inspección y asentadas en el acta respectiva, aun cuando sean desahogadas por exhorto.\nIII.- De la diligencia se levantará acta circunstanciada, que firmarán los que en ella intervengan y quieran hacerlo, la cual se agregará al expediente.\nArtículo Adicionado\nSECCIÓN H\nPRESUNCIONAL\nArtículo 141 BIS 51.- Presunción es la consecuencia que se deriva de la Ley o que deduce el Tribunal de un hecho conocido para averiguar la verdad de otro desconocido; la primera es legal y la segunda es humana.\nArtículo Adicionado\nArtículo 141 BIS 52.- El que tiene a su favor una presunción legal, sólo está obligado a probar el hecho en que la funda.\nArtículo Adicionado\nArtículo 141 BIS 53.- Las presunciones legales y humanas, admiten prueba en contrario.\nArtículo Adicionado\nArtículo 141 BIS 54.- Las partes al ofrecer la prueba presuncional, indicarán en qué consiste y lo que se acredita con ella.\nArtículo Adicionado\nSECCIÓN I\nINSTRUMENTAL\nArtículo 141 BIS 55.- La instrumental es el conjunto de actuaciones que obren en el expediente, formado con motivo del juicio.\nArtículo Adicionado\nArtículo 141 BIS 56.- El Tribunal estará obligado a tomar en cuenta las actuaciones que obren en el expediente del juicio, salvo las que expresamente hayan sido desechadas por el Tribunal, aunque aún obren en el expediente.\nArtículo Adicionado\nArtículo 141 BIS 57.- La actuaciones ante el Tribunal hacen prueba plena.\nArtículo Adicionado\nSECCIÓN J\nELEMENTOS APORTADOS POR LOS AVANCES\nDE LA CIENCIA O TECNOLOGÍA\nLey del Servicio Civil de los Trabajadores al Servicio de los Poderes Página 53\nArtículo 141 BIS 58.- Las partes podrán ofrecer pruebas consistentes en fotografías, grabaciones de audio y de video, cintas cinematográficas, registros dactiloscópicos, fonográficos, biométricos, magnéticos, sistemas de información electrónica, o las distintas tecnologías de la información y la comunicación, tales como, medios electrónicos ópticos, aquellos medios aportados por los avances de la ciencia, la técnica o el arte, que pueda contribuir para acreditar hechos o circunstancias que tengan relación con el asunto en litigio.\nEn el caso de que las partes ofrezcan las pruebas señaladas en el párrafo anterior, el oferente deberá proporcionar al Tribunal los instrumentos, aparatos o elementos necesarios para que pueda apreciarse el contenido de los registros y reproducirse los sonidos e imágenes, por el tiempo indispensable para su desahogo.\nArtículo Adicionado\nArtículo 141 BIS 59.- El valor probatorio de medios establecidos en este apartado queda a la prudente calificación del Tribunal.\nArtículo Adicionado\nTITULO OCTAVO\nDE LOS MEDIOS DE APREMIO Y DE LA EJECUCION DE LOS LAUDOS\nCAPITULO I\nARTICULO 142.- El tribunal para hacer cumplir sus determinaciones podrá imponer multas hasta por el importe del equivalente a doce días de salarios mínimos.\nARTICULO 143.- Las multas se harán efectivas por las oficinas recaudadoras del\nEstado para lo cual se girará el oficio correspondiente.\nLas oficinas de referencia informarán al tribunal de haber hecho efectiva la multa, especificando los datos que acrediten su cobro.\nCAPITULO II\nARTICULO 144.- La ejecución de los laudos dictados por el tribunal de arbitraje, que la ejecución sea pronta y expedita.\nARTICULO 145.- Cuando se solicite la ejecución de un laudo, el presidente del la parte que obtuvo, se constituya en el domicilio de la parte demandada y la requiera para el cumplimiento, apercibiéndola que de no hacerlo se procederá conforme a lo dispuesto en el artículo anterior.\nLey del Servicio Civil de los Trabajadores al Servicio de los Poderes Página 54\nTITULO NOVENO\nDE LAS CORRECCIONES\nDISCIPLINARIAS Y DE LAS\nSANCIONES\nCAPITULO UNICO\nARTICULO 146.- Las violaciones a las normas de trabajo cometidas por las autoridades públicas, o por los trabajadores se sancionaran de conformidad con las disposiciones de este título, independientemente de la responsabilidad que les corresponda por el incumplimiento de sus obligaciones.\nARTICULO 147.- El tribunal de arbitraje o el presidente impondrán correcciones disciplinarias.\nI.- A las partes y a los particulares que falten al respeto y al orden debidos, durante las actuaciones del tribunal.\nII.- A los empleados del propio tribunal, por faltas que cometan en el desempeño de sus funciones.\nARTICULO 148.- Las correcciones a que aluden el artículo anterior serán:\nI.- Amonestación.\nII.- Multa hasta por el equivalente a seis veces el valor diario de la Unidad de Medida y Actualización vigente.\nFracción Reformada\nIII.- Suspensión de empleo con privación de sueldo hasta por quince días.\nArtículo Reformado\nARTICULO 149.- Las correcciones disciplinarias se impondrán oyendo al interesado y tomando en cuenta las circunstancias en que tuvo lugar la falta cometida.\nARTICULO 150.- Las infracciones a la presente Ley que no tengan establecida otra sanción, se castigarán con multa hasta el equivalente a seis veces el valor diario de la\nUnidad de Medida y Actualización vigente.\nArtículo Reformado\nTITULO DECIMO\nDE LA SEGURIDAD SOCIAL DE LOS TRABAJADORES\nCAPITULO UNICO\nARTICULO 151.- Los derechos de los trabajadores al servicio de las Autoridades\nLey del Servicio Civil de los Trabajadores al Servicio de los Poderes Página 55\nPúblicas, en materia de jubilación, pensiones y de seguridad social en lo integral quedarán\nGobierno y Municipios del Estado de Baja California (ISSSTECALI).\nArtículo Reformado\nARTICULO 152.- Si llegase a ocurrir que los recursos de ISSSTECALI no bastaren para cumplir con las obligaciones a su cargo, se actuará de acuerdo con lo contemplado en las disposiciones legales vigentes.\nTITULO DECIMO PRIMERO\nDE LOS TRABAJADORES DE LA EDUCACION\nTítulo Adicionado\nCAPITULO UNICO\nARTICULO 153.- Los Trabajadores al Servicio de la Educación, se agruparán en su propio Sindicato.\nArtículo Adicionado\nARTICULO 154.- Los Trabajadores al Servicio de la Educación disfrutarán de dos períodos anuales de vacaciones de diez días hábiles a cada uno, conforme al calendario escolar; además de su salario ordinario gozarán de una prima vacacional no menor del 55% sobre los salarios que le correspondan durante dichos períodos.\nAsimismo, los Trabajadores al Servicio de la Educación, que tengan una antigüedad de más de un año, tendrán derecho al pago de una prima vacacional de conformidad con la tabla siguiente.\n1 año, 55% sobre 20 días hábiles.\n2 años, 60.5% sobre 20 días hábiles.\n3 años, 66% sobre 20 días hábiles.\n4 años, 71.5% sobre 20 días hábiles.\n5 años 77% sobre 20 días hábiles.\n6 a 10 años, 82.5% sobre 20 días hábiles.\n11 a 15 años, 93.5% sobre 20 días hábiles.\n16 a 20 años, 104.5% sobre 20 días hábiles.\n21 a 25 años, 115.5% sobre 20 días hábiles.\n26 a 30 años, 126.5% sobre 20 días hábiles.\n31 años en adelante, 137.5% sobre 20 días hábiles.\nArtículo Adicionado\nLey del Servicio Civil de los Trabajadores al Servicio de los Poderes Página 56\nTITULO DECIMO SEGUNDO\nTRABAJADORES TRANSFERIDOS POR LA FEDERACION\nTítulo Adicionado\nCAPITULO UNICO\nARTICULO 155.- Las relaciones laborales entre los Poderes del Estado de Baja\nCalifornia y los Trabajadores que sean transferidos por la Federación hacia el Estado, se regirá de acuerdo a las disposiciones contenidas en:\nI.- Los Acuerdos Nacionales de Descentralización.\nII.- Los Convenios de Coordinación.\nIII.- Los Acuerdos de Coordinación específicos o particulares que se deriven de los diversos Programas de Descentralización del Gobierno Federal o Estatal.\nIV.- Las disposiciones especiales que determinen por los organismos o dependencias que asuman las funciones transferidas de la Federación, cualquiera que sea la forma o estructura legal que adopten.\nV.- Las disposiciones administrativas que se expidan al momento de la transferencia de funciones de la Federación hacia el Estado.\nVI.- Los demás ordenamientos legales que se emitan en virtud de la descentralización.\nArtículo Adicionado\nARTICULO 156.- El Instituto de Servicios de Salud Pública del Estado de Baja\nCalifornia, respetará los derechos laborales señalados en el Artículo 123, Apartado B de la aplicarán y respetarán las Condiciones Generales de Trabajo de la Secretaría de Salud del\nGobierno Federal y sus reformas futuras, así como los Reglamentos elaborados conforme a la normatividad federal aplicable en sus relaciones laborales con los trabajadores provenientes de la Secretaría de Salud. El Instituto procederá a registrarlos ante el Tribunal de Arbitraje del Estado de Baja California, con el propósito de que se apliquen en las controversias que se diriman por ésta autoridad jurisdiccional.\nLos trabajadores al servicio del sector salud continuarán agrupados en su propio\nSindicato. Los asuntos laborales de naturaleza colectiva serán tratados en los términos de los Acuerdos de Descentralización y Coordinación respectivos.\nArtículo Adicionado\nInstituto de Servicios de Salud Pública del Estado de Baja California, continuarán gozando de su actual régimen de seguridad social, que estará a cargo del Instituto de Seguridad y\nServicios Sociales para los Trabajadores del Estado.\nArtículo Adicionado\nLey del Servicio Civil de los Trabajadores al Servicio de los Poderes Página 57\nTÍTULO DÉCIMO TERCERO\nDEL ESCALAFÓN\nTítulo Adicionado\nCAPÍTULO ÚNICO\nDEL ESCALAFÓN\nArtículo 158.- El escalafón es el sistema organizado en las áreas de las Autoridades\nPúblicas, que incluye la lista de trabajadores de base que le estén adscritos, y se estructura con base en los factores escalafonarios que hacen posible el acceso del trabajador a las garantías de estabilidad, ascenso o permuta en el empleo, consagradas la Constitución\nPolítica de los Estados Unidos Mexicanos y demás disposiciones aplicables.\nArtículo Adicionado\nArtículo 159.- Los trabajadores de base con un mínimo de un año acumulativo en la prestación del servicio, tienen derecho a participar en los concursos para ser promovidos a la obtención de la base definitiva. Todos los trabajadores incorporados al sistema de escalafón, tendrán derecho a participar en los concursos y promociones de ascensos, de conformidad con los tabuladores señalados en el Reglamento de Escalafón. En cada\nAutoridad Pública se expedirá un Reglamento de Escalafón.\nCuando no existan disposiciones especiales, las Autoridades Públicas expedirán su reglamento de escalafón atendiendo las bases establecidas en este Capítulo, el cual se formulará, de común acuerdo, por el titular y el o los sindicatos respectivos.\nSon factores escalafonarios:\nI.- Los conocimientos;\nII.- La aptitud;\nIII.- La antigüedad, y\nIV.- La disciplina y puntualidad.\nSe entiende por:\na) Conocimientos: La posesión de los principios teóricos y prácticos que se requieren para el desempeño de una plaza.\nb) Aptitud: La suma de facultades físicas y mentales, la iniciativa, laboriosidad y la eficiencia para llevar a cabo una actividad determinada.\nc) Antigüedad: El tiempo de servicios prestados a la dependencia correspondiente, o a otra distinta cuyas relaciones laborales se rijan por la presente Ley, siempre que el de servicios, o de los efectos de la desconcentración administrativa, aun cuando la reasignación tuviere lugar por voluntad del trabajador.\nArtículo Adicionado\nArtículo 160.- Las vacantes se otorgarán a los trabajadores de la categoría inmediata\nLey del Servicio Civil de los Trabajadores al Servicio de los Poderes Página 58 escalafonarios. fuente de ingresos de su familia o cuando existan varios en esta situación, se preferirá al que demuestre mayor tiempo de servicios prestados dentro de la misma unidad burocrática.\nArtículo Adicionado\nArtículo 161.- Los factores escalafonarios se calificarán por medio de los tabuladores respectivos.\nEl personal de cada Autoridad Pública será clasificado, según sus categorías, en los términos señalados en el Catálogo General de Puestos que les corresponda.\nArtículo Adicionado\nArtículo 162.- En cada Autoridad Publica funcionará una Comisión Mixta de\nEscalafón, integrada con igual número de representantes, tanto de la autoridad como del o los sindicatos que se encuentren registrados, quienes designarán un árbitro que decida los casos de empate. Si no hay acuerdo, la designación lo hará el Pleno del Tribunal de Arbitraje del Estado en un término que no excederá de diez días y de una lista de cuatro candidatos que las partes en conflicto le propongan.\nPara ser árbitro se deberán reunir los requisitos que se exigen para el Presidente del\nTribunal de Arbitraje del Estado. Los árbitros duraran en su encargo tres años pudiendo ser ratificados por la Comisión Mixta de Escalafón correspondiente hasta por otro periodo igual.\nArtículo Adicionado\nArtículo 163.- Los titulares de las Autoridades Públicas, por si o por conducto del servidor público facultado, proporcionarán a las Comisiones Mixtas de Escalafón la información necesaria, medios administrativos y materiales para su eficaz funcionamiento.\nArtículo Adicionado\nArtículo 164.- Las facultades, obligaciones, atribuciones, procedimientos y derechos de las Comisiones Mixtas de Escalafón, quedarán señalados en el Reglamento de\nEscalafón, sin contravenir las disposiciones de esta ley.\nArtículo Adicionado\nArtículo 165.- Los titulares de las Autoridades Públicas, por si o por conducto del servidor público facultado, darán a conocer a las Comisiones Mixtas de Escalafón las baja de una base definitiva, o en su caso se apruebe presupuestalmente la creación de nuevas plazas de base. procederán desde luego a convocar a un concurso, entre los trabajadores de la categoría inmediata inferior, mediante circulares o boletines que se fijaran en lugares visibles de los centro de trabajo correspondientes.\nLas convocatorias señalaran los requisitos para aplicar derechos, plazos para\nLey del Servicio Civil de los Trabajadores al Servicio de los Poderes Página 59\nReglamento de la Comisión Mixta de Escalafón. vacantes sin sujetarse al procedimiento aquí señalado; lo anterior, acorde a los parámetros que se acuerden para tales efectos en el Reglamento de Escalafón, debiendo en todo caso justificar su petición a fin de que sea aprobada por la Comisión Mixta de Escalafón.”\nArtículo Adicionado\nArtículo 166.- En los concursos se procederá por las comisiones a verificar las pruebas a que se sometan los concursantes y a calificar los factores escalafonarios, teniendo en cuenta los documentos constancias o hechos que los comprueben, de acuerdo con la valuación fijada en los Reglamentos.\nLos aspirantes para ocupar las plazas vacantes deberán reunir los requisitos que para esos puestos, señale la normatividad de cada una de las Autoridades Públicas, acorde a los catálogos de puestos correspondientes.\nArtículo Adicionado\nArtículo 167.- La vacante se otorgará al trabajador que habiendo sido aprobado de acuerdo con el Reglamento respectivo obtenga la mejor calificación.\nArtículo Adicionado\nArtículo 168.- Cuando se trate de vacantes temporales que no excedan de seis meses no se moverá el escalafón; el Titular de la Dependencia de que se trate nombrará y removerá libremente al empleado interino que deba cubrirla.\nArtículo Adicionado\nArtículo 169.- Las vacantes temporales mayores de seis meses serán ocupadas por riguroso escalafón; pero los trabajadores ascendidos serán nombrados en todo caso con el carácter de provisionales, de tal modo que si quien disfrute de la licencia reingresare al servicio, automáticamente se correrá en forma inversa el escalafón y el trabajador provisional de la última categoría correspondiente, dejará de prestar sus servicios sin responsabilidad para el titular.\nLas vacantes temporales mayores de seis meses serán las que se originen por licencias otorgadas a un trabajador de base en los términos del presente artículo.\nArtículo Adicionado\nArtículo 170.- El procedimiento para resolver las permutas de empleos, así como las inconformidades de los trabajadores afectados por trámites o movimientos escalafonarios, será previsto en los Reglamentos correspondientes.\nArtículo Adicionado\nARTICULO I.- Esta Ley entrará en vigor al día siguiente de su publicación en el\nPeriódico Oficial del Estado.\nLey del Servicio Civil de los Trabajadores al Servicio de los Poderes Página 60\nARTICULO II.- Se abroga la Ley del Servicio Civil de los Trabajadores al Servicio de conformidad con las disposiciones de esta Ley, dentro de un término de tres meses contados a partir de la fecha de su vigencia.\nARTICULO IV.- Los juicios pendientes ante el tribunal de arbitraje continuarán tramitándose de conformidad con las disposiciones de la Ley del Servicio Civil del 5 de diciembre de 1955, entre tanto se efectúa la reorganización a que se refiere el transitorio que antecede.\nEfectuada la reorganización, los juicios se continuarán tramitando conforme a las disposiciones de esta Ley. El tribunal hará saber a las partes el momento en que la tramitación quedará sometida a los procedimientos establecidos en esta Ley.\nDADA en el salón de sesiones del H. Poder Legislativo en la ciudad de Mexicali, Baja\nCalifornia, a los diecinueve días del mes de septiembre de mil novecientos ochenta y nueve.\nPROFR. ANTONIO SALGADO RUFFO,\nDIPUTADO PRESIDENTE.\n(RÚBRICA)\nMA. BERTHA NAVARRO MELENDEZ,\nDIPUTADO SECRETARIO.\n(RÚBRICA)\nDE CONFORMIDAD CON LO DISPUESTO POR LA FRACCION I DEL ARTICULO 49\nDE LA CONSTITUCION POLITICA DEL ESTADO, MANDO SE IMPRIMA, PUBLIQUE,\nOBSERVE Y SE LE DE EL DEBIDO CUMPLIMIENTO.\nMEXICALI, CAPITAL DEL ESTADO DE BAJA CALIFORNIA, A LOS VEINTISIETE\nDIAS DEL MES DE SEPTIEMBRE DE MIL NOVECIENTOS OCHENTA Y NUEVE.\nEL GOBERNADOR DEL ESTADO,\nING. OSCAR BAYLON CHACON.\n(RÚBRICA)\nEL SECRETARIO GENERAL DE GOBIERNO,\nDR. ARTURO GUERRA FLORES.\n(RÚBRICA)\nLey del Servicio Civil de los Trabajadores al Servicio de los Poderes Página 61\nLOS PODERES DEL ESTADO, MUNICIPIOS E INSTITUCIONES\nDESCENTRALIZADAS DE BAJA CALIFORNIA\nFue modificada la denominación de esta Ley por Decreto No. 52, publicado en el\nLegislatura, siendo Gobernador Constitucional el C. Lic. Francisco Arturo Vega de Lamadrid\n2013-2019; para quedar vigente como sigue:\nLEY DEL SERVICIO CIVIL DE LOS TRABAJADORES AL SERVICIO DE\nLOS PODERES DEL ESTADO Y MUNICIPIOS DE BAJA CALIFORNIA\nARTICULO 1.- Fue reformado por Decreto No. 52, publicado en el Periódico Oficial\nNo. 24, de fecha 08 de mayo de 2014, Número Especial, Tomo CXXI, expedido por la\nHonorable XXI Legislatura, siendo Gobernador Constitucional el C. Lic. Francisco Arturo\nVega de Lamadrid 2013-2019;\nARTICULO 2.- Fue reformado por Decreto No. 230, publicado en el Periódico Oficial\nNo. 35, de fecha 25 de agosto de 2006, Tomo CXIII, expedido por la Honorable XVIII\nLegislatura, siendo Gobernador Constitucional el C. Lic. Eugenio Elorduy Walther, 20012007;\nARTICULO 3.- Fue reformado por Decreto No. 230, publicado en el Periódico Oficial\nNo. 35, de fecha 25 de agosto de 2006, Tomo CXIII, expedido por la Honorable XVIII\nLegislatura, siendo Gobernador Constitucional el C. Lic. Eugenio Elorduy Walther, 20012007; fue reformado por Decreto No. 52, publicado en el Periódico Oficial No. 24, de fecha\n08 de mayo de 2014, Número Especial, Tomo CXXI, expedido por la Honorable XXI\nLegislatura, siendo Gobernador Constitucional el C. Lic. Francisco Arturo Vega de Lamadrid\n2013-2019;\nARTICULO 4.- Fue reformado por Decreto No. 52, publicado en el Periódico Oficial\nNo. 24, de fecha 08 de mayo de 2014, Número Especial, Tomo CXXI, expedido por la\nHonorable XXI Legislatura, siendo Gobernador Constitucional el C. Lic. Francisco Arturo\nVega de Lamadrid 2013-2019;\nARTICULO 5.- Fue reformado por Decreto No. 52, publicado en el Periódico Oficial\nHonorable XXI Legislatura, siendo Gobernador Constitucional el C. Lic. Francisco Arturo\nVega de Lamadrid 2013-2019;\nARTICULO 6.- Fue reformado por Decreto No. 52, publicado en el Periódico Oficial\nHonorable XXI Legislatura, siendo Gobernador Constitucional el C. Lic. Francisco Arturo\nLey del Servicio Civil de los Trabajadores al Servicio de los Poderes Página 62\nVega de Lamadrid 2013-2019;\nARTICULO 8.- Fue reformado por Decreto No. 52, publicado en el Periódico Oficial\nHonorable XXI Legislatura, siendo Gobernador Constitucional el C. Lic. Francisco Arturo\nVega de Lamadrid 2013-2019;\nARTICULO 9.- Fue reformado por Decreto No. 52, publicado en el Periódico Oficial\nNo. 24, de fecha 08 de mayo de 2014, Número Especial, Tomo CXXI, expedido por la\nHonorable XXI Legislatura, siendo Gobernador Constitucional el C. Lic. Francisco Arturo\nVega de Lamadrid 2013-2019;\nARTICULO 10.- Fue reformado por Decreto No. 52, publicado en el Periódico Oficial\nNo. 24, de fecha 08 de mayo de 2014, Número Especial, Tomo CXXI, expedido por la\nHonorable XXI Legislatura, siendo Gobernador Constitucional el C. Lic. Francisco Arturo\nVega de Lamadrid 2013-2019;\nARTICULO 12.- Fue reformado por Decreto No. 52, publicado en el Periódico Oficial\nNo. 24, de fecha 08 de mayo de 2014, Número Especial, Tomo CXXI, expedido por la\nHonorable XXI Legislatura, siendo Gobernador Constitucional el C. Lic. Francisco Arturo\nVega de Lamadrid 2013-2019;\nARTICULO 15.- Fue reformado por Decreto No. 52, publicado en el Periódico Oficial\nNo. 24, de fecha 08 de mayo de 2014, Número Especial, Tomo CXXI, expedido por la\nHonorable XXI Legislatura, siendo Gobernador Constitucional el C. Lic. Francisco Arturo\nVega de Lamadrid 2013-2019;\nARTICULO 20.- Fue reformado por Decreto No. 52, publicado en el Periódico Oficial\nNo. 24, de fecha 08 de mayo de 2014, Número Especial, Tomo CXXI, expedido por la\nHonorable XXI Legislatura, siendo Gobernador Constitucional el C. Lic. Francisco Arturo\nVega de Lamadrid 2013-2019;\nARTICULO 26.- Fue reformado por Decreto No. 52, publicado en el Periódico Oficial\nNo. 24, de fecha 08 de mayo de 2014, Número Especial, Tomo CXXI, expedido por la\nHonorable XXI Legislatura, siendo Gobernador Constitucional el C. Lic. Francisco Arturo\nVega de Lamadrid 2013-2019;\nARTICULO 29.- Fue reformado por Decreto No. 243, publicado en el Periódico Oficial\nXXI Legislatura, siendo Gobernador Constitucional el C. Lic. Francisco Arturo Vega de\nLamadrid 2013-2019; fue reformado por Decreto No. 378, publicado en el Periódico Oficial\nLegislatura, siendo Gobernadora Constitucional la C. Marina del Pilar Ávila Olmeda, 20212027;\nLey del Servicio Civil de los Trabajadores al Servicio de los Poderes Página 63\nARTICULO 29 BIS.- Fue adicionado por Decreto No. 198, publicado en el Periódico\nHonorable XXII Legislatura, siendo Gobernador Constitucional el C. Lic. Francisco Arturo\nVega de Lamadrid 2013-2019;\nARTICULO 29 TER.- Fue adicionado por Decreto No. 390, publicado en el Periódico\nOficial No. 13, de fecha 08 de marzo de 2024, Índice, Tomo CXXXI, expedido por la H. XXIV\nLegislatura, siendo Gobernadora Constitucional la C. Marina del Pilar Ávila Olmeda, 20212027;\nARTICULO 30.- Fue reformado por Decreto No. 205, publicado en el Periódico Oficial\nNo. 27, de fecha 30 de junio de 2006, Tomo CXIII, expedido por la H. XVIII Legislatura, siendo Gobernador Constitucional el C. Lic. Eugenio Elorduy Walther, 2001-2007, Fue reformado por Decreto No. 207, publicado en el Periódico Oficial No. 33, de fecha 11 de agosto de 2006, Tomo CXIII, expedido por la Honorable XVIII Legislatura, siendo\nGobernador Constitucional el C. Lic. Eugenio Elorduy Walther, 2001-2007;\nARTICULO 32.- Fue reformado por Decreto No. 52, publicado en el Periódico Oficial\nNo. 24, de fecha 08 de mayo de 2014, Número Especial, Tomo CXXI, expedido por la\nHonorable XXI Legislatura, siendo Gobernador Constitucional el C. Lic. Francisco Arturo\nVega de Lamadrid 2013-2019;\nARTICULO 42.- Fue reformado por Decreto No. 52, publicado en el Periódico Oficial\nNo. 24, de fecha 08 de mayo de 2014, Número Especial, Tomo CXXI, expedido por la\nHonorable XXI Legislatura, siendo Gobernador Constitucional el C. Lic. Francisco Arturo\nVega de Lamadrid 2013-2019;\nARTICULO 44.- Fue reformado por Decreto No. 329, publicado en el Periódico Oficial\nNo. 37, de fecha 31 de agosto de 2001, Tomo CVIII, expedido por la Honorable XVI\nLegislatura del Estado, siendo Gobernador Constitucional el C. Lic. Alejandro González\nAlcocer, 1998-2001;\nARTICULO 46.- Fue reformado por Decreto No.120, publicado en el Periódico Oficial\nNo.52, de fecha 19 de Diciembre de 1997, Tomo CIV, expedido por la Honorable XV\nLegislatura del Estado, siendo Gobernador Constitucional el C. Lic. Héctor Terán Terán, 1995-2001;\nARTICULO 51.- Fue reformado por Decreto No. 52, publicado en el Periódico Oficial\nHonorable XXI Legislatura, siendo Gobernador Constitucional el C. Lic. Francisco Arturo\nVega de Lamadrid 2013-2019;\nARTICULO 52.- Fue reformado por Decreto No. 52, publicado en el Periódico Oficial\nLey del Servicio Civil de los Trabajadores al Servicio de los Poderes Página 64\nHonorable XXI Legislatura, siendo Gobernador Constitucional el C. Lic. Francisco Arturo\nVega de Lamadrid 2013-2019;\nARTICULO 55.- Fue reformado por Decreto No. 52, publicado en el Periódico Oficial\nHonorable XXI Legislatura, siendo Gobernador Constitucional el C. Lic. Francisco Arturo\nVega de Lamadrid 2013-2019;\nARTICULO 55 BIS.- Fue adicionado por Decreto No. 52, publicado en el Periódico\nOficial No. 24, de fecha 08 de mayo de 2014, Número Especial, Tomo CXXI, expedido por la\nHonorable XXI Legislatura, siendo Gobernador Constitucional el C. Lic. Francisco Arturo\nVega de Lamadrid 2013-2019;\nARTICULO 55 BIS 1.- Fue adicionado por Decreto No. 52, publicado en el Periódico\nOficial No. 24, de fecha 08 de mayo de 2014, Número Especial, Tomo CXXI, expedido por la\nHonorable XXI Legislatura, siendo Gobernador Constitucional el C. Lic. Francisco Arturo\nVega de Lamadrid 2013-2019;\nARTICULO 56.- Fue reformado por Decreto No. 52, publicado en el Periódico Oficial\nNo. 24, de fecha 08 de mayo de 2014, Número Especial, Tomo CXXI, expedido por la\nHonorable XXI Legislatura, siendo Gobernador Constitucional el C. Lic. Francisco Arturo\nVega de Lamadrid 2013-2019;\nARTICULO 57.- Fue reformado por Decreto No. 52, publicado en el Periódico Oficial\nNo. 24, de fecha 08 de mayo de 2014, Número Especial, Tomo CXXI, expedido por la\nHonorable XXI Legislatura, siendo Gobernador Constitucional el C. Lic. Francisco Arturo\nVega de Lamadrid 2013-2019;\nARTICULO 58.- Fue reformado por Decreto No. 52, publicado en el Periódico Oficial\nNo. 24, de fecha 08 de mayo de 2014, Número Especial, Tomo CXXI, expedido por la\nHonorable XXI Legislatura, siendo Gobernador Constitucional el C. Lic. Francisco Arturo\nVega de Lamadrid 2013-2019;\nARTICULO 66.- Fue derogado por Decreto No. 184, publicado en el Periódico Oficial\nNo. 14, de fecha 7 de abril del 2000, Tomo CVII, expedido por la Honorable XVI Legislatura del Estado, siendo Gobernador Constitucional el C. Lic. Alejandro González Alcocer, 19982001;\nARTICULO 68.- Fue reformado por Decreto No. 52, publicado en el Periódico Oficial\nHonorable XXI Legislatura, siendo Gobernador Constitucional el C. Lic. Francisco Arturo\nVega de Lamadrid 2013-2019;\nARTICULO 76.- Fue reformado por Decreto No. 52, publicado en el Periódico Oficial\nLey del Servicio Civil de los Trabajadores al Servicio de los Poderes Página 65\nHonorable XXI Legislatura, siendo Gobernador Constitucional el C. Lic. Francisco Arturo\nVega de Lamadrid 2013-2019;\nARTICULO 77.- Fue reformado por Decreto No. 52, publicado en el Periódico Oficial\nHonorable XXI Legislatura, siendo Gobernador Constitucional el C. Lic. Francisco Arturo\nVega de Lamadrid 2013-2019;\nFue modificada la denominación de este Título mediante Decreto No. 52, publicado en el\nPeriódico Oficial No. 24, de fecha 08 de mayo de 2014, Número Especial, Tomo CXXI, expedido por la Honorable XXI Legislatura, siendo Gobernador Constitucional el C. Lic.\nFrancisco Arturo Vega de Lamadrid 2013-2019;\nTÍTULO SEXTO\nDE LA PRESCRIPCION Y DE LA CADUCIDAD\nCAPÍTULO ÚNICO\nARTICULO 95.- Fue reformado por Decreto No. 52, publicado en el Periódico Oficial\nNo. 24, de fecha 08 de mayo de 2014, Número Especial, Tomo CXXI, expedido por la\nHonorable XXI Legislatura, siendo Gobernador Constitucional el C. Lic. Francisco Arturo\nVega de Lamadrid 2013-2019;\nARTICULO 98.- Fue reformado por Decreto No. 52, publicado en el Periódico Oficial\nNo. 24, de fecha 08 de mayo de 2014, Número Especial, Tomo CXXI, expedido por la\nHonorable XXI Legislatura, siendo Gobernador Constitucional el C. Lic. Francisco Arturo\nVega de Lamadrid 2013-2019;\nARTICULO 99 BIS.- Fue adicionado por Decreto No. 52, publicado en el Periódico\nOficial No. 24, de fecha 08 de mayo de 2014, Número Especial, Tomo CXXI, expedido por la\nHonorable XXI Legislatura, siendo Gobernador Constitucional el C. Lic. Francisco Arturo\nVega de Lamadrid 2013-2019;\nARTICULO 100.- Fue reformado por Decreto No. 52, publicado en el Periódico Oficial\nHonorable XXI Legislatura, siendo Gobernador Constitucional el C. Lic. Francisco Arturo\nVega de Lamadrid 2013-2019;\nARTICULO 102.- Fue reformado por Decreto No. 52, publicado en el Periódico Oficial\nHonorable XXI Legislatura, siendo Gobernador Constitucional el C. Lic. Francisco Arturo\nVega de Lamadrid 2013-2019;\nLey del Servicio Civil de los Trabajadores al Servicio de los Poderes Página 66\nARTICULO 104.- Fue reformado por Decreto No. 52, publicado en el Periódico Oficial\nHonorable XXI Legislatura, siendo Gobernador Constitucional el C. Lic. Francisco Arturo\nVega de Lamadrid 2013-2019;\nARTICULO 105.- Fue reformado por Decreto No. 346, publicado en el Periódico\nOficial No. 51, Tomo CXIX, Sección I, de fecha 16 de noviembre de 2012; expedido por la H.\nXX Legislatura, siendo Gobernador Constitucional el C. José Guadalupe Osuna Milláan\n2007-2013. fue reformado por Decreto No. 52, publicado en el Periódico Oficial No. 24, de fecha 08 de mayo de 2014, Número Especial, Tomo CXXI, expedido por la Honorable XXI\nLegislatura, siendo Gobernador Constitucional el C. Lic. Francisco Arturo Vega de Lamadrid\n2013-2019;\nARTICULO 107.- Fue reformado por Decreto No. 52, publicado en el Periódico Oficial\nNo. 24, de fecha 08 de mayo de 2014, Número Especial, Tomo CXXI, expedido por la\nHonorable XXI Legislatura, siendo Gobernador Constitucional el C. Lic. Francisco Arturo\nVega de Lamadrid 2013-2019;\nARTICULO 109.- Fue reformado por Decreto No. 52, publicado en el Periódico Oficial\nNo. 24, de fecha 08 de mayo de 2014, Número Especial, Tomo CXXI, expedido por la\nHonorable XXI Legislatura, siendo Gobernador Constitucional el C. Lic. Francisco Arturo\nVega de Lamadrid 2013-2019;\nARTICULO 110.- Fue reformado por Decreto No. 52, publicado en el Periódico Oficial\nNo. 24, de fecha 08 de mayo de 2014, Número Especial, Tomo CXXI, expedido por la\nHonorable XXI Legislatura, siendo Gobernador Constitucional el C. Lic. Francisco Arturo\nVega de Lamadrid 2013-2019;\nARTICULO 112.- Fue reformado por Decreto No. 52, publicado en el Periódico Oficial\nNo. 24, de fecha 08 de mayo de 2014, Número Especial, Tomo CXXI, expedido por la\nHonorable XXI Legislatura, siendo Gobernador Constitucional el C. Lic. Francisco Arturo\nVega de Lamadrid 2013-2019;\nARTICULO 117.- Fue reformado por Decreto No. 52, publicado en el Periódico Oficial\nHonorable XXI Legislatura, siendo Gobernador Constitucional el C. Lic. Francisco Arturo\nVega de Lamadrid 2013-2019;\nARTICULO 118.- Fue reformado por Decreto No. 52, publicado en el Periódico Oficial\nHonorable XXI Legislatura, siendo Gobernador Constitucional el C. Lic. Francisco Arturo\nVega de Lamadrid 2013-2019;\nLey del Servicio Civil de los Trabajadores al Servicio de los Poderes Página 67\nARTICULO 118 BIS.- Fue adicionado por Decreto No. 52, publicado en el Periódico\nHonorable XXI Legislatura, siendo Gobernador Constitucional el C. Lic. Francisco Arturo\nVega de Lamadrid 2013-2019;\nARTICULO 119.- Fue reformado por Decreto No. 52, publicado en el Periódico Oficial\nNo. 24, de fecha 08 de mayo de 2014, Número Especial, Tomo CXXI, expedido por la\nHonorable XXI Legislatura, siendo Gobernador Constitucional el C. Lic. Francisco Arturo\nVega de Lamadrid 2013-2019;\nARTICULO 125.- Fue reformado por Decreto No. 52, publicado en el Periódico Oficial\nNo. 24, de fecha 08 de mayo de 2014, Número Especial, Tomo CXXI, expedido por la\nHonorable XXI Legislatura, siendo Gobernador Constitucional el C. Lic. Francisco Arturo\nVega de Lamadrid 2013-2019;\nARTICULO 126.- Fue reformado por Decreto No. 52, publicado en el Periódico Oficial\nNo. 24, de fecha 08 de mayo de 2014, Número Especial, Tomo CXXI, expedido por la\nHonorable XXI Legislatura, siendo Gobernador Constitucional el C. Lic. Francisco Arturo\nVega de Lamadrid 2013-2019;\nARTICULO 126 BIS.- Fue adicionado por Decreto No. 52, publicado en el Periódico\nOficial No. 24, de fecha 08 de mayo de 2014, Número Especial, Tomo CXXI, expedido por la\nHonorable XXI Legislatura, siendo Gobernador Constitucional el C. Lic. Francisco Arturo\nVega de Lamadrid 2013-2019;\nFue adicionado este capítulo mediante Decreto No. 52, publicado en el Periódico Oficial No.\n24, de fecha 08 de mayo de 2014, Número Especial, Tomo CXXI, expedido por la Honorable\nXXI Legislatura, siendo Gobernador Constitucional el C. Lic. Francisco Arturo Vega de\nLamadrid 2013-2019;\nCAPÍTULO III\nDE LOS MEDIOS PROBATORIOS\nSECCIÓN A\nCONFESIONAL\nARTICULO 141 BIS.- Fue adicionado por Decreto No. 52, publicado en el Periódico\nHonorable XXI Legislatura, siendo Gobernador Constitucional el C. Lic. Francisco Arturo\nVega de Lamadrid 2013-2019;\nARTICULO 141 BIS 1.- Fue adicionado por Decreto No. 52, publicado en el Periódico\nHonorable XXI Legislatura, siendo Gobernador Constitucional el C. Lic. Francisco Arturo\nLey del Servicio Civil de los Trabajadores al Servicio de los Poderes Página 68\nVega de Lamadrid 2013-2019;\nARTICULO 141 BIS 2.- Fue adicionado por Decreto No. 52, publicado en el Periódico\nHonorable XXI Legislatura, siendo Gobernador Constitucional el C. Lic. Francisco Arturo\nVega de Lamadrid 2013-2019;\nARTICULO 141 BIS 3.- Fue adicionado por Decreto No. 52, publicado en el Periódico\nOficial No. 24, de fecha 08 de mayo de 2014, Número Especial, Tomo CXXI, expedido por la\nHonorable XXI Legislatura, siendo Gobernador Constitucional el C. Lic. Francisco Arturo\nVega de Lamadrid 2013-2019;\nARTICULO 141BIS 4.- Fue adicionado por Decreto No. 52, publicado en el Periódico\nOficial No. 24, de fecha 08 de mayo de 2014, Número Especial, Tomo CXXI, expedido por la\nHonorable XXI Legislatura, siendo Gobernador Constitucional el C. Lic. Francisco Arturo\nVega de Lamadrid 2013-2019;\nARTICULO 141 BIS 5.- Fue adicionado por Decreto No. 52, publicado en el Periódico\nOficial No. 24, de fecha 08 de mayo de 2014, Número Especial, Tomo CXXI, expedido por la\nHonorable XXI Legislatura, siendo Gobernador Constitucional el C. Lic. Francisco Arturo\nVega de Lamadrid 2013-2019;\nARTICULO 141 BIS 6.- Fue adicionado por Decreto No. 52, publicado en el Periódico\nOficial No. 24, de fecha 08 de mayo de 2014, Número Especial, Tomo CXXI, expedido por la\nHonorable XXI Legislatura, siendo Gobernador Constitucional el C. Lic. Francisco Arturo\nVega de Lamadrid 2013-2019;\nARTICULO 141 BIS 7.- Fue adicionado por Decreto No. 52, publicado en el Periódico\nOficial No. 24, de fecha 08 de mayo de 2014, Número Especial, Tomo CXXI, expedido por la\nHonorable XXI Legislatura, siendo Gobernador Constitucional el C. Lic. Francisco Arturo\nVega de Lamadrid 2013-2019;\nARTICULO 141BIS 8.- Fue adicionado por Decreto No. 52, publicado en el Periódico\nOficial No. 24, de fecha 08 de mayo de 2014, Número Especial, Tomo CXXI, expedido por la\nHonorable XXI Legislatura, siendo Gobernador Constitucional el C. Lic. Francisco Arturo\nVega de Lamadrid 2013-2019;\nSECCIÓN B\nDECLARACIÓN DE PARTE\nARTÍCULO 141 BIS 9.- Fue adicionado por Decreto No. 52, publicado en el Periódico\nHonorable XXI Legislatura, siendo Gobernador Constitucional el C. Lic. Francisco Arturo\nVega de Lamadrid 2013-2019;\nARTÍCULO 141 BIS 10.- Fue adicionado por Decreto No. 52, publicado en el\nLey del Servicio Civil de los Trabajadores al Servicio de los Poderes Página 69 expedido por la Honorable XXI Legislatura, siendo Gobernador Constitucional el C. Lic.\nFrancisco Arturo Vega de Lamadrid 2013-2019;\nARTÍCULO 141 BIS 11.- Fue adicionado por Decreto No. 52, publicado en el expedido por la Honorable XXI Legislatura, siendo Gobernador Constitucional el C. Lic.\nFrancisco Arturo Vega de Lamadrid 2013-2019;\nSECCIÓN C\nDOCUMENTALES\nARTÍCULO 141 BIS 12.- Fue adicionado por Decreto No. 52, publicado en el\nPeriódico Oficial No. 24, de fecha 08 de mayo de 2014, Número Especial, Tomo CXXI, expedido por la Honorable XXI Legislatura, siendo Gobernador Constitucional el C. Lic.\nFrancisco Arturo Vega de Lamadrid 2013-2019;\nARTÍCULO 141 BIS 13.- Fue adicionado por Decreto No. 52, publicado en el\nPeriódico Oficial No. 24, de fecha 08 de mayo de 2014, Número Especial, Tomo CXXI, expedido por la Honorable XXI Legislatura, siendo Gobernador Constitucional el C. Lic.\nFrancisco Arturo Vega de Lamadrid 2013-2019;\nARTÍCULO 141 BIS 14.- Fue adicionado por Decreto No. 52, publicado en el\nPeriódico Oficial No. 24, de fecha 08 de mayo de 2014, Número Especial, Tomo CXXI, expedido por la Honorable XXI Legislatura, siendo Gobernador Constitucional el C. Lic.\nFrancisco Arturo Vega de Lamadrid 2013-2019;\nARTÍCULO 141 BIS 15.- Fue adicionado por Decreto No. 52, publicado en el\nPeriódico Oficial No. 24, de fecha 08 de mayo de 2014, Número Especial, Tomo CXXI, expedido por la Honorable XXI Legislatura, siendo Gobernador Constitucional el C. Lic.\nFrancisco Arturo Vega de Lamadrid 2013-2019;\nARTÍCULO 141 BIS 16.- Fue adicionado por Decreto No. 52, publicado en el\nPeriódico Oficial No. 24, de fecha 08 de mayo de 2014, Número Especial, Tomo CXXI, expedido por la Honorable XXI Legislatura, siendo Gobernador Constitucional el C. Lic.\nFrancisco Arturo Vega de Lamadrid 2013-2019;\nARTÍCULO 141 BIS 17.- Fue adicionado por Decreto No. 52, publicado en el expedido por la Honorable XXI Legislatura, siendo Gobernador Constitucional el C. Lic.\nFrancisco Arturo Vega de Lamadrid 2013-2019;\nARTÍCULO 141 BIS 18.- Fue adicionado por Decreto No. 52, publicado en el expedido por la Honorable XXI Legislatura, siendo Gobernador Constitucional el C. Lic.\nFrancisco Arturo Vega de Lamadrid 2013-2019;\nLey del Servicio Civil de los Trabajadores al Servicio de los Poderes Página 70\nARTÍCULO 141 BIS 19.- Fue adicionado por Decreto No. 52, publicado en el expedido por la Honorable XXI Legislatura, siendo Gobernador Constitucional el C. Lic.\nFrancisco Arturo Vega de Lamadrid 2013-2019;\nARTÍCULO 141 BIS 20.- Fue adicionado por Decreto No. 52, publicado en el\nPeriódico Oficial No. 24, de fecha 08 de mayo de 2014, Número Especial, Tomo CXXI, expedido por la Honorable XXI Legislatura, siendo Gobernador Constitucional el C. Lic.\nFrancisco Arturo Vega de Lamadrid 2013-2019;\nARTÍCULO 141 BIS 21.- Fue adicionado por Decreto No. 52, publicado en el\nPeriódico Oficial No. 24, de fecha 08 de mayo de 2014, Número Especial, Tomo CXXI, expedido por la Honorable XXI Legislatura, siendo Gobernador Constitucional el C. Lic.\nFrancisco Arturo Vega de Lamadrid 2013-2019;\nARTÍCULO 141 BIS 22.- Fue adicionado por Decreto No. 52, publicado en el\nPeriódico Oficial No. 24, de fecha 08 de mayo de 2014, Número Especial, Tomo CXXI, expedido por la Honorable XXI Legislatura, siendo Gobernador Constitucional el C. Lic.\nFrancisco Arturo Vega de Lamadrid 2013-2019;\nARTÍCULO 141 BIS 23.- Fue adicionado por Decreto No. 52, publicado en el\nPeriódico Oficial No. 24, de fecha 08 de mayo de 2014, Número Especial, Tomo CXXI, expedido por la Honorable XXI Legislatura, siendo Gobernador Constitucional el C. Lic.\nFrancisco Arturo Vega de Lamadrid 2013-2019;\nARTÍCULO 141 BIS 24.- Fue adicionado por Decreto No. 52, publicado en el\nPeriódico Oficial No. 24, de fecha 08 de mayo de 2014, Número Especial, Tomo CXXI, expedido por la Honorable XXI Legislatura, siendo Gobernador Constitucional el C. Lic.\nFrancisco Arturo Vega de Lamadrid 2013-2019;\nARTÍCULO 141 BIS 25.- Fue adicionado por Decreto No. 52, publicado en el\nPeriódico Oficial No. 24, de fecha 08 de mayo de 2014, Número Especial, Tomo CXXI, expedido por la Honorable XXI Legislatura, siendo Gobernador Constitucional el C. Lic.\nFrancisco Arturo Vega de Lamadrid 2013-2019;\nARTÍCULO 141 BIS 26.- Fue adicionado por Decreto No. 52, publicado en el expedido por la Honorable XXI Legislatura, siendo Gobernador Constitucional el C. Lic.\nFrancisco Arturo Vega de Lamadrid 2013-2019;\nSECCIÓN D\nINFORME DE AUTORIDAD Y DE TERCEROS\nARTÍCULO 141 BIS 27.- Fue adicionado por Decreto No. 52, publicado en el expedido por la Honorable XXI Legislatura, siendo Gobernador Constitucional el C. Lic.\nLey del Servicio Civil de los Trabajadores al Servicio de los Poderes Página 71\nFrancisco Arturo Vega de Lamadrid 2013-2019;\nARTÍCULO 141 BIS 28.- Fue adicionado por Decreto No. 52, publicado en el expedido por la Honorable XXI Legislatura, siendo Gobernador Constitucional el C. Lic.\nFrancisco Arturo Vega de Lamadrid 2013-2019;\nARTÍCULO 141 BIS 29.- Fue adicionado por Decreto No. 52, publicado en el\nPeriódico Oficial No. 24, de fecha 08 de mayo de 2014, Número Especial, Tomo CXXI, expedido por la Honorable XXI Legislatura, siendo Gobernador Constitucional el C. Lic.\nFrancisco Arturo Vega de Lamadrid 2013-2019;\nARTÍCULO 141 BIS 30.- Fue adicionado por Decreto No. 52, publicado en el\nPeriódico Oficial No. 24, de fecha 08 de mayo de 2014, Número Especial, Tomo CXXI, expedido por la Honorable XXI Legislatura, siendo Gobernador Constitucional el C. Lic.\nFrancisco Arturo Vega de Lamadrid 2013-2019;\nSECCIÓN E\nTESTIMONIAL\nARTÍCULO 141 BIS 31.- Fue adicionado por Decreto No. 52, publicado en el\nPeriódico Oficial No. 24, de fecha 08 de mayo de 2014, Número Especial, Tomo CXXI, expedido por la Honorable XXI Legislatura, siendo Gobernador Constitucional el C. Lic.\nFrancisco Arturo Vega de Lamadrid 2013-2019; fue reformado por Decreto No. 281, publicado en el Periódico Oficial No. 55, de fecha 30 de noviembre de 2018, Tomo CXXV,\nSección IV, expedido por la Honorable Legislatura XXII, siendo Gobernador Constitucional el\nC. Francisco Arturo Vega de Lamadrid 2013-2019;\nARTÍCULO 141 BIS 32.- Fue adicionado por Decreto No. 52, publicado en el\nPeriódico Oficial No. 24, de fecha 08 de mayo de 2014, Número Especial, Tomo CXXI, expedido por la Honorable XXI Legislatura, siendo Gobernador Constitucional el C. Lic.\nFrancisco Arturo Vega de Lamadrid 2013-2019;\nARTÍCULO 141 BIS 33.- Fue adicionado por Decreto No. 52, publicado en el expedido por la Honorable XXI Legislatura, siendo Gobernador Constitucional el C. Lic.\nFrancisco Arturo Vega de Lamadrid 2013-2019;\nARTÍCULO 141 BIS 34.- Fue adicionado por Decreto No. 52, publicado en el expedido por la Honorable XXI Legislatura, siendo Gobernador Constitucional el C. Lic.\nFrancisco Arturo Vega de Lamadrid 2013-2019;\nARTÍCULO 141 BIS 35.- Fue adicionado por Decreto No. 52, publicado en el\nLey del Servicio Civil de los Trabajadores al Servicio de los Poderes Página 72 expedido por la Honorable XXI Legislatura, siendo Gobernador Constitucional el C. Lic.\nFrancisco Arturo Vega de Lamadrid 2013-2019;\nARTÍCULO 141 BIS 36.- Fue adicionado por Decreto No. 52, publicado en el expedido por la Honorable XXI Legislatura, siendo Gobernador Constitucional el C. Lic.\nFrancisco Arturo Vega de Lamadrid 2013-2019;\nARTÍCULO 141 BIS 37.- Fue adicionado por Decreto No. 52, publicado en el\nPeriódico Oficial No. 24, de fecha 08 de mayo de 2014, Número Especial, Tomo CXXI, expedido por la Honorable XXI Legislatura, siendo Gobernador Constitucional el C. Lic.\nFrancisco Arturo Vega de Lamadrid 2013-2019;\nARTÍCULO 141 BIS 38.- Fue adicionado por Decreto No. 52, publicado en el\nPeriódico Oficial No. 24, de fecha 08 de mayo de 2014, Número Especial, Tomo CXXI, expedido por la Honorable XXI Legislatura, siendo Gobernador Constitucional el C. Lic.\nFrancisco Arturo Vega de Lamadrid 2013-2019;\nSECCIÓN F\nPERICIAL\nARTÍCULO 141 BIS 39.- Fue adicionado por Decreto No. 52, publicado en el\nPeriódico Oficial No. 24, de fecha 08 de mayo de 2014, Número Especial, Tomo CXXI, expedido por la Honorable XXI Legislatura, siendo Gobernador Constitucional el C. Lic.\nFrancisco Arturo Vega de Lamadrid 2013-2019;\nARTÍCULO 141 BIS 40.- Fue adicionado por Decreto No. 52, publicado en el\nPeriódico Oficial No. 24, de fecha 08 de mayo de 2014, Número Especial, Tomo CXXI, expedido por la Honorable XXI Legislatura, siendo Gobernador Constitucional el C. Lic.\nFrancisco Arturo Vega de Lamadrid 2013-2019;\nARTÍCULO 141 BIS 41.- Fue adicionado por Decreto No. 52, publicado en el\nPeriódico Oficial No. 24, de fecha 08 de mayo de 2014, Número Especial, Tomo CXXI, expedido por la Honorable XXI Legislatura, siendo Gobernador Constitucional el C. Lic.\nFrancisco Arturo Vega de Lamadrid 2013-2019;\nARTÍCULO 141 BIS 42.- Fue adicionado por Decreto No. 52, publicado en el expedido por la Honorable XXI Legislatura, siendo Gobernador Constitucional el C. Lic.\nFrancisco Arturo Vega de Lamadrid 2013-2019;\nARTÍCULO 141 BIS 43.- Fue adicionado por Decreto No. 52, publicado en el expedido por la Honorable XXI Legislatura, siendo Gobernador Constitucional el C. Lic.\nFrancisco Arturo Vega de Lamadrid 2013-2019;\nLey del Servicio Civil de los Trabajadores al Servicio de los Poderes Página 73\nARTÍCULO 141 BIS 44.- Fue adicionado por Decreto No. 52, publicado en el expedido por la Honorable XXI Legislatura, siendo Gobernador Constitucional el C. Lic.\nFrancisco Arturo Vega de Lamadrid 2013-2019;\nARTÍCULO 141 BIS 45.- Fue adicionado por Decreto No. 52, publicado en el\nPeriódico Oficial No. 24, de fecha 08 de mayo de 2014, Número Especial, Tomo CXXI, expedido por la Honorable XXI Legislatura, siendo Gobernador Constitucional el C. Lic.\nFrancisco Arturo Vega de Lamadrid 2013-2019;\nARTÍCULO 141 BIS 46.- Fue adicionado por Decreto No. 52, publicado en el\nPeriódico Oficial No. 24, de fecha 08 de mayo de 2014, Número Especial, Tomo CXXI, expedido por la Honorable XXI Legislatura, siendo Gobernador Constitucional el C. Lic.\nFrancisco Arturo Vega de Lamadrid 2013-2019;\nARTÍCULO 141 BIS 47.- Fue adicionado por Decreto No. 52, publicado en el\nPeriódico Oficial No. 24, de fecha 08 de mayo de 2014, Número Especial, Tomo CXXI, expedido por la Honorable XXI Legislatura, siendo Gobernador Constitucional el C. Lic.\nFrancisco Arturo Vega de Lamadrid 2013-2019;\nSECCIÓN G\nINSPECCIÓN\nARTÍCULO 141 BIS 48.- Fue adicionado por Decreto No. 52, publicado en el\nPeriódico Oficial No. 24, de fecha 08 de mayo de 2014, Número Especial, Tomo CXXI, expedido por la Honorable XXI Legislatura, siendo Gobernador Constitucional el C. Lic.\nFrancisco Arturo Vega de Lamadrid 2013-2019;\nARTÍCULO 141 BIS 49.- Fue adicionado por Decreto No. 52, publicado en el\nPeriódico Oficial No. 24, de fecha 08 de mayo de 2014, Número Especial, Tomo CXXI, expedido por la Honorable XXI Legislatura, siendo Gobernador Constitucional el C. Lic.\nFrancisco Arturo Vega de Lamadrid 2013-2019;\nARTÍCULO 141 BIS 50.- Fue adicionado por Decreto No. 52, publicado en el expedido por la Honorable XXI Legislatura, siendo Gobernador Constitucional el C. Lic.\nFrancisco Arturo Vega de Lamadrid 2013-2019;\nSECCIÓN H\nPRESUNCIONAL\nARTÍCULO 141 BIS 51.- Fue adicionado por Decreto No. 52, publicado en el\nLey del Servicio Civil de los Trabajadores al Servicio de los Poderes Página 74 expedido por la Honorable XXI Legislatura, siendo Gobernador Constitucional el C. Lic.\nFrancisco Arturo Vega de Lamadrid 2013-2019;\nARTÍCULO 141 BIS 52.- Fue adicionado por Decreto No. 52, publicado en el expedido por la Honorable XXI Legislatura, siendo Gobernador Constitucional el C. Lic.\nFrancisco Arturo Vega de Lamadrid 2013-2019;\nARTÍCULO 141 BIS 53.- Fue adicionado por Decreto No. 52, publicado en el\nPeriódico Oficial No. 24, de fecha 08 de mayo de 2014, Número Especial, Tomo CXXI, expedido por la Honorable XXI Legislatura, siendo Gobernador Constitucional el C. Lic.\nFrancisco Arturo Vega de Lamadrid 2013-2019;\nARTÍCULO 141 BIS 54.- Fue adicionado por Decreto No. 52, publicado en el\nPeriódico Oficial No. 24, de fecha 08 de mayo de 2014, Número Especial, Tomo CXXI, expedido por la Honorable XXI Legislatura, siendo Gobernador Constitucional el C. Lic.\nFrancisco Arturo Vega de Lamadrid 2013-2019;\nSECCIÓN I\nINSTRUMENTAL\nARTÍCULO 141 BIS 55.- Fue adicionado por Decreto No. 52, publicado en el\nPeriódico Oficial No. 24, de fecha 08 de mayo de 2014, Número Especial, Tomo CXXI, expedido por la Honorable XXI Legislatura, siendo Gobernador Constitucional el C. Lic.\nFrancisco Arturo Vega de Lamadrid 2013-2019;\nARTÍCULO 141 BIS 56.- Fue adicionado por Decreto No. 52, publicado en el\nPeriódico Oficial No. 24, de fecha 08 de mayo de 2014, Número Especial, Tomo CXXI, expedido por la Honorable XXI Legislatura, siendo Gobernador Constitucional el C. Lic.\nFrancisco Arturo Vega de Lamadrid 2013-2019;\nARTÍCULO 141 BIS 57.- Fue adicionado por Decreto No. 52, publicado en el\nPeriódico Oficial No. 24, de fecha 08 de mayo de 2014, Número Especial, Tomo CXXI, expedido por la Honorable XXI Legislatura, siendo Gobernador Constitucional el C. Lic.\nFrancisco Arturo Vega de Lamadrid 2013-2019;\nSECCIÓN J\nELEMENTOS APORTADOS POR LOS AVANCES\nDE LA CIENCIA O TECNOLOGÍA\nARTÍCULO 141 BIS 58.- Fue adicionado por Decreto No. 52, publicado en el expedido por la Honorable XXI Legislatura, siendo Gobernador Constitucional el C. Lic.\nLey del Servicio Civil de los Trabajadores al Servicio de los Poderes Página 75\nFrancisco Arturo Vega de Lamadrid 2013-2019;\nARTÍCULO 141 BIS 59.- Fue adicionado por Decreto No. 52, publicado en el expedido por la Honorable XXI Legislatura, siendo Gobernador Constitucional el C. Lic.\nFrancisco Arturo Vega de Lamadrid 2013-2019;\nARTICULO 148.- Fue reformado por Decreto No. 281, publicado en el Periódico\nOficial No. 55, de fecha 30 de noviembre de 2018, Tomo CXXV, Sección IV, expedido por la\nHonorable Legislatura XXII, siendo Gobernador Constitucional el C. Francisco Arturo Vega de Lamadrid 2013-2019;\nARTICULO 150.- Fue reformado por Decreto No. 281, publicado en el Periódico\nOficial No. 55, de fecha 30 de noviembre de 2018, Tomo CXXV, Sección IV, expedido por la\nHonorable Legislatura XXII, siendo Gobernador Constitucional el C. Francisco Arturo Vega de Lamadrid 2013-2019;\nARTICULO 151.- Fue reformado por Decreto No. 12, publicado en el Periódico Oficial\nNo. 40, sección I, de fecha 11 de diciembre de 1992, expedido por la Honorable XIV\nLegislatura, siendo Gobernador Constitucional el C. L.A.E. Ernesto Ruffo Appel, 1989-1995 y estando encargado del Despacho de Gobierno por ministerio de Ley el C. C.P. Fortunato\nÁlvarez Enríquez; fue reformado por Decreto No. 52, publicado en el Periódico Oficial No.\n24, de fecha 08 de mayo de 2014, Número Especial, Tomo CXXI, expedido por la Honorable\nXXI Legislatura, siendo Gobernador Constitucional el C. Lic. Francisco Arturo Vega de\nLamadrid 2013-2019;\nFue adicionado Título Décimo Primero, por Decreto No. 12, publicado en el Periódico\nOficial No. 40, sección I, de fecha 11 de diciembre de 1992, expedido por la Honorable XIV\nLegislatura, siendo Gobernador Constitucional el C. L.A.E. Ernesto Ruffo Appel, 1989-1995 y estando encargado del Despacho de Gobierno por ministerio de Ley el C. C.P. Fortunato\nÁlvarez Enríquez;\nTITULO DECIMO PRIMERO\nDE LOS TRABAJADORES DE LA EDUCACION\nCAPITULO UNICO\nARTICULO 153.- Fue adicionado por Decreto No. 12, publicado en el Periódico Oficial\nLegislatura, siendo Gobernador Constitucional el C. L.A.E. Ernesto Ruffo Appel, 1989-1995 y estando encargado del Despacho de Gobierno por ministerio de Ley el C. C.P. Fortunato\nÁlvarez Enríquez;\nLey del Servicio Civil de los Trabajadores al Servicio de los Poderes Página 76\nARTICULO 154.- Fue adicionado por Decreto No. 12, publicado en el Periódico Oficial\nLegislatura, siendo Gobernador Constitucional el C. L.A.E. Ernesto Ruffo Appel, 1989-1995 y estando encargado del Despacho de Gobierno por ministerio de Ley el C. C.P. Fortunato\nÁlvarez Enríquez;\nFue adicionado el Título Décimo Segundo, Según Decreto No. 147 publicado en el Periódico\nOficial del Estado No. 16, de fecha 17 de abril de 1998, Tomo CV, Expedido por la\nHonorable XV Legislatura, siendo Gobernador Constitucional el C. Lic. Héctor Terán Terán, 1995-2001;\nTITULO DECIMO SEGUNDO\nDE LAS RELACIONES LABORALES ENTRE EL ESTADO Y LOS\nTRABAJADORES TRANSFERIDOS POR LA FEDERACION\nARTICULO 155.- Fue adicionado por Decreto No. 147 publicado en el Periódico\nOficial del Estado No. 16, de fecha 17 de abril de 1998, Tomo CV, Expedido por la\nHonorable XV Legislatura, siendo Gobernador Constitucional el C. Lic. Héctor Terán Terán, 1995-2001;\nARTICULO 156.- Fue adicionado por Decreto No. 147 publicado en el Periódico\nOficial del Estado No. 16, de fecha 17 de abril de 1998, Tomo CV, Expedido por la\nHonorable XV Legislatura, siendo Gobernador Constitucional el C. Lic. Héctor Terán Terán, 1995-2001;\nARTICULO 157.- Fue adicionado por Decreto No. 147 publicado en el Periódico\nOficial del Estado No. 16, de fecha 17 de abril de 1998, Tomo CV, Expedido por la\nHonorable XV Legislatura, siendo Gobernador Constitucional el C. Lic. Héctor Terán Terán, 1995-2001;\nFue adicionado el Título Décimo Tercero, mediante Decreto No. 52, publicado en el expedido por la Honorable XXI Legislatura, siendo Gobernador Constitucional el C. Lic.\nFrancisco Arturo Vega de Lamadrid 2013-2019;\nTÍTULO DÉCIMO TERCERO\nDEL ESCALAFÓN\nCAPÍTULO ÚNICO\nDEL ESCALAFÓN\nARTÍCULO 158.- Fue adicionado por Decreto No. 52, publicado en el Periódico Oficial\nLey del Servicio Civil de los Trabajadores al Servicio de los Poderes Página 77\nHonorable XXI Legislatura, siendo Gobernador Constitucional el C. Lic. Francisco Arturo\nVega de Lamadrid 2013-2019;\nARTÍCULO 159.- Fue adicionado por Decreto No. 52, publicado en el Periódico Oficial\nHonorable XXI Legislatura, siendo Gobernador Constitucional el C. Lic. Francisco Arturo\nVega de Lamadrid 2013-2019;\nARTÍCULO 160.- Fue adicionado por Decreto No. 52, publicado en el Periódico Oficial\nNo. 24, de fecha 08 de mayo de 2014, Número Especial, Tomo CXXI, expedido por la\nHonorable XXI Legislatura, siendo Gobernador Constitucional el C. Lic. Francisco Arturo\nVega de Lamadrid 2013-2019;\nARTÍCULO 161.- Fue adicionado por Decreto No. 52, publicado en el Periódico Oficial\nNo. 24, de fecha 08 de mayo de 2014, Número Especial, Tomo CXXI, expedido por la\nHonorable XXI Legislatura, siendo Gobernador Constitucional el C. Lic. Francisco Arturo\nVega de Lamadrid 2013-2019;\nARTÍCULO 162.- Fue adicionado por Decreto No. 52, publicado en el Periódico Oficial\nNo. 24, de fecha 08 de mayo de 2014, Número Especial, Tomo CXXI, expedido por la\nHonorable XXI Legislatura, siendo Gobernador Constitucional el C. Lic. Francisco Arturo\nVega de Lamadrid 2013-2019;\nARTÍCULO 163.- Fue adicionado por Decreto No. 52, publicado en el Periódico Oficial\nNo. 24, de fecha 08 de mayo de 2014, Número Especial, Tomo CXXI, expedido por la\nHonorable XXI Legislatura, siendo Gobernador Constitucional el C. Lic. Francisco Arturo\nVega de Lamadrid 2013-2019;\nARTÍCULO 164.- Fue adicionado por Decreto No. 52, publicado en el Periódico Oficial\nNo. 24, de fecha 08 de mayo de 2014, Número Especial, Tomo CXXI, expedido por la\nHonorable XXI Legislatura, siendo Gobernador Constitucional el C. Lic. Francisco Arturo\nVega de Lamadrid 2013-2019;\nARTÍCULO 165.- Fue adicionado por Decreto No. 52, publicado en el Periódico\nOficial No. 24, de fecha 08 de mayo de 2014, Número Especial, Tomo CXXI, expedido por la\nHonorable XXI Legislatura, siendo Gobernador Constitucional el C. Lic. Francisco Arturo\nVega de Lamadrid 2013-2019; fue reformado por Decreto No. 61, publicado en el Periódico\nLegislatura, siendo Gobernador Constitucional el C. Francisco Arturo Vega de Lamadrid\n2013-2019;\nARTÍCULO 166.- Fue adicionado por Decreto No. 52, publicado en el Periódico Oficial\nHonorable XXI Legislatura, siendo Gobernador Constitucional el C. Lic. Francisco Arturo\nVega de Lamadrid 2013-2019;\nARTÍCULO 167.- Fue adicionado por Decreto No. 52, publicado en el Periódico Oficial\nLey del Servicio Civil de los Trabajadores al Servicio de los Poderes Página 78\nHonorable XXI Legislatura, siendo Gobernador Constitucional el C. Lic. Francisco Arturo\nVega de Lamadrid 2013-2019;\nARTÍCULO 168.- Fue adicionado por Decreto No. 52, publicado en el Periódico Oficial\nHonorable XXI Legislatura, siendo Gobernador Constitucional el C. Lic. Francisco Arturo\nVega de Lamadrid 2013-2019;\nARTÍCULO 169.- Fue adicionado por Decreto No. 52, publicado en el Periódico Oficial\nNo. 24, de fecha 08 de mayo de 2014, Número Especial, Tomo CXXI, expedido por la\nHonorable XXI Legislatura, siendo Gobernador Constitucional el C. Lic. Francisco Arturo\nVega de Lamadrid 2013-2019;\nARTÍCULO 170.- Fue adicionado por Decreto No. 52, publicado en el Periódico Oficial\nHonorable XXI Legislatura, siendo Gobernador Constitucional el C. Lic. Francisco Arturo\nVega de Lamadrid 2013-2019;\nARTICULO OCTAVO DECRETO No. 52 XXI.- Fue modificado por Decreto No. 61, expedido por la Honorable XXI Legislatura, siendo Gobernador Constitucional el C. Lic.\nFrancisco Arturo Vega de Lamadrid 2013-2019;\nLey del Servicio Civil de los Trabajadores al Servicio de los Poderes Página 79\nARTICULO TRANSITORIO DEL DECRETO NUMERO 12, PUBLICADO EN EL\nPOR EL QUE SE ADICIONAN LOS ARTICULOS 151 Y EL TITULO DECIMO PRIMERO\nCON LOS ARTICULOS 153 Y 154, EXPEDIDO POR LA HONORABLE XIV LEGISLATURA:\nUNICO.- Las presentes adiciones entrarán en vigor al día siguiente de su publicación en el Periódico Oficial, Organo del Gobierno del Estado.\nLegislativo, en la Ciudad de Mexicali, Baja California, a los diez días del mes de Diciembre de 1992.\nLic. José Luis Sabori Granados, Diputado Presidente.\nRúbrica.\nC. Armando Martínez Gámez, Diputado Secretario.\nRúbrica.\nDE CONFORMIDAD CON LO DISPUESTO POR LA FRACCION I DEL ARTICULO 49\nDE LA CONSTITUCION POLITICA DEL ESTADO, MANDO SE IMPRIMA, PUBLIQUE,\nOBSERVE Y SE LE DE EL DEBIDO CUMPLIMIENTO.\nMEXICALI, BAJA CALIFORNIA, A LOS DIEZ DIAS DEL MES DE DICIEMBRE DE\nMIL NOVECIENTOS NOVENTA Y DOS.\nEl Secretario General de Gobierno, encargado del\nDespacho por Ministerio de Ley, C.P. Fortunato Alvarez Enriquez.\nRúbrica.\nEl Oficial Mayor de Gobierno, encargado de la\nSecretaría General de Gobierno por Ministerio de Ley, C. René C. Corella Gil Samaniego.\nRúbrica.\nARTICULO TRANSITORIO DEL DECRETO No.120, POR EL QUE SE REFORMA EL\nARTICULO 46 EN SU FRACCION II DE LA LEY DEL SERVICIO CIVIL DE LOS TRABAJADORES\nAL SERVICIO DEL ESTADO, MUNICIPIOS E INSTITUCIONES DESCENTRALIZADAS DE BAJA\nCALIFORNIA, PUBLICADA EN EL PERIODICO OFICIAL No. 52, DE FECHA 19 DE DICIEMBRE DE\n1997, TOMO CIV, EXPEDIDO POR LA HONORABLE XV LEGISLATURA, SIENDO GOBERNADOR\nCONSTITUCIONAL DEL ESTADO, EL C. LIC. HECTOR TERAN TERAN, 1995-2001.\nUNICO.- El presente Decreto entrará en vigencia a partir del día siguiente de su publicación en el Periódico Oficial del Estado.\nLey del Servicio Civil de los Trabajadores al Servicio de los Poderes Página 80\nLegislativo, en la Ciudad de Mexicali, Baja California, a los trece días del mes de noviembre de mil novecientos noventa y siete.\nLIC. JAVIER JULIAN CASTAÑEDA POMPOSO.\nDIPUTADO PRESIDENTE.\nRUBRICA.\nDIP. ROGELIO APPEL CHACON.\nDIPUTADO SECRETARIO.\nRUBRICA.\nDE CONFORMIDAD CON LO DISPUESTO POR LA FRACCION I DEL ARTICULO 49\nDE LA CONSTITUCION POLITICA DEL ESTADO, MANDO SE IMPRIMA Y PUBLIQUE.\nMEXICALI, BAJA CALIFORNIA, A LOS VEINTICINCO DIAS DEL MES DE\nNOVIEMBRE DE MIL NOVECIENTOS NOVENTA Y SIETE.\nEL GOBERNADOR CONSTITUCIONAL DEL ESTADO.\nLIC. HECTOR TERAN TERAN.\nRUBRICA.\nEL SECRETARIO GENERAL DE GOBIERNO.\nLIC. RODOLFO VALDEZ GUTIERREZ.\nRUBRICA.\nARTICULO TRANSITORIO DEL DECRETO NO. 147, POR EL QUE SE ADICIONA UN\nTITULO DECIMO SEGUNDO A LA LEY DEL SERVICIO CIVIL DE LOS TRABAJADORES AL\nSERVICIO DEL ESTADO, MUNICIPIOS E INSTITUCIONES DESCENTRALIZADAS DE BAJA\nCALIFORNIA, PUBLICADO EN EL PERIODO OFICIAL NO. 16, DE FECHA 17 DE ABRIL DE 1998,\nTOMO: CV, EXPEDIDO POR LA H. XV LEGISLATURA, SIENDO GOBERNADOR\nCONSTITUCIONAL DEL ESTADO, EL C. LIC. HECTOR TERAN TERAN, 1995-2001.\nARTICULO UNICO.- El presente Decreto entrará en vigor al día siguiente de su publicación en el Periódico Oficial del Estado.\nDado en el Salón de Sesiones Lic. Benito Juárez García del Honorable Poder\nLegislativo, en la ciudad de Mexicali, Baja California, a los ocho días del mes de abril de mil novecientos noventa y ocho.\nC. JUAN MENESES JIMENEZ\nDIPUTADO PRESIDENTE\nLey del Servicio Civil de los Trabajadores al Servicio de los Poderes Página 81\nRUBRICA\nC. CESAR BAYLON CHACON\nDIPUTADO SECRETARIO\nRUBRICA\nDE CONFORMIDAD CON LO DISPUESTO POR LA FRACCION I DEL ARTICULO 49 DE LA\nCONSTITUCION POLITICA DEL ESTADO, MANDO SE IMPRIMA Y PUBLIQUE.\nMEXICALI, BAJA CALIFORNIA, A LOS QUINCE DIAS DEL MES DE ABRIL DE MIL\nNOVECIENTOS NOVENTA Y OCHO.\nEL GOBERNADOR CONSTITUCIONAL DEL ESTADO.\nLIC. HECTOR TERAN TERAN.\nRUBRICA.\nEL SECRETARIO GENERAL DE GOBIERNO.\nLIC. RODOLFO VALDEZ GUTIERREZ\nRUBRICA.\nARTICULO UNICO TRANSITORIO DEL DECRETO No. 184, POR EL QUE SE DEROGA EL\nARTICULO 66, PUBLICADO EN EL PERIODICO OFICIAL NO. 14, DE FECHA 7 DE ABRIL DEL\n2000, TOMO CVII, SIENDO GOBERNADOR CONSTITUCIONAL EL C. LIC. ALEJANDRO\nGONZALEZ ALCOCER 1998-2001, EXPEDIDO POR LA H. XVI LEGISLATURA.\nUNICO.- La presente Reforma entrará en vigor al día siguiente de su publicación en el\nPeriódico Oficial Organo del Gobierno del Estado.\nLegislativo, en la Ciudad de Mexicali, Baja California, a los diecisiete días del mes de marzo del año dos mil.\nPROFR. ALEJANDRO BAHENA FLORES\nDIPUTADO PRESIDENTE\nRUBRICA\nDR. EFREN MACIAS LEZAMA\nDIPUTADO SECRETARIO\nRUBRICA\nDe conformidad con lo dispuesto por la Fracción I del Artículo 49 de la Constitución\nMexicali, Baja California, a los veintiocho días del mes de marzo del año dos mil.\nEL GOBERNADOR CONSTITUCIONAL DEL ESTADO\nLIC. ALEJANDRO GONZALEZ ALCOCER\nRUBRICA\nLey del Servicio Civil de los Trabajadores al Servicio de los Poderes Página 82\nEL SECRETARIO GENERAL DE GOBIERNO\nC.P. JORGE RAMOS\nRUBRICA\nARTICULO UNICO TRANSITORIO DEL DECRETO NO. 329, POR EL QUE SE REFORMA\nEL ARTICULO 44, PUBLICADO EN EL PERIODICO OFICIAL NO. 37, DE FECHA 31 DE AGOSTO\nDE 2001, SECCION I, TOMO CVIII, EXPEDIDO POR LA H. XVI LEGISLATURA, SIENDO\nGOBERNADOR CONSTITUCIONAL EL C. LIC. ALEJANDRO GONZALEZ ALCOCER 1998-2001.\nUNICO La presente reforma entrará en vigor al día siguiente al de su publicación en el\nPeriódico Oficial del Gobierno del Estado.\nDADO en el Salón de Seisones \"Lic. Benito Juárez García\" del H. Poder Legislativo, en la ciudad de Mexicali, Baja California, a los ventinueve días del mes de junio del año dos mil uno.\nDIP. GILBERTO FLORES MUÑOZ\nPRESIDENTE\nRUBRICA\nDIP. OLIVIA VILLALAZ BECERRA\nSECRETARIA\nRUBRICA\nDE CONFORMIDAD CON LO DISPUESTO POR LA FRACCION I DEL ARTICULO 49 DE LA\nCONSTITUCION POLITICA DEL ESTADO, MANDO SE IMPRIMA Y PUBLIQUE.\nMEXICALI, BAJA CALIFORNIA, A LOS DOS DIAS DEL MES DE AGOSTO DEL AÑO DOS\nMIL UNO.\nEL GOBERNADOR CONSTITUCIONAL DEL ESTADO.\nLIC. ALEJANDRO GONZALEZ ALCOCER\nRUBRICA\nEL SECRETARIO GENERAL DE GOBIERNO\nC.P. JORGE RAMOS\nRUBRICA.\nARTICULO TRANSITORIO DEL DECRETO NO. 207, POR EL QUE SE REFORMA\nEL ARTICULO 30, PUBLICADO EN EL PERIODICO OFICIAL NO. 27, DE FECHA 30 DE\nGOBERNADOR CONSTITUCIONAL EL C. EUGENIO ELORDUY WALTHER 2001-2007.\nARTICULOS TRANSITORIOS\nLey del Servicio Civil de los Trabajadores al Servicio de los Poderes Página 83\nÚNICO.- La presente reforma, entrará en vigor al día siguiente de su publicación en el\nPeriódico Oficial del Estado de Baja California.\nDADO en el Salón de Sesiones “Lic. Benito Juárez García” del Honorable Poder\nLegislativo, en la Ciudad de Mexicali, Baja California, a los ocho días del mes de junio del año dos mil seis.\nDIP. RENE ADRÍAN MENDIVIL ACOSTA\nPRESIDENTE\n(RÚBRICA)\nDIP. CARLOS ALBERTO ASTORGA OTHÓN\nSECRETARIO\n(RÚBRICA)\nDE CONFORMIDAD CON LO DISPUESTO POR LA FRACCION I DEL ARTICULO 49\nDE LA CONSTITUCION POLITICA DEL ESTADO, IMPRIMASE Y PUBLIQUESE.\nMEXICALI, BAJA CALIFORNIA, A LOS TRECE DIAS DEL MES DE JUNIO DEL AÑO\nDOS MIL SEIS.\nGOBERNADOR DEL ESTADO\nEUGENIO ELORDUY WALTHER\n(RÚBRICA)\nSECRETARIO GENERAL DE GOBIERNO\nBERNARDO H. MARTINEZ AGUIRRE\n(RÚBRICA)\nARTICULO UNICO TRANSITORIO DEL DECRETO No. 217, PUBLICADO EN EL\nQUE SE REFORMA EL ARTÍCULO 30, EXPEDIDO POR LA H. XVIII LEGISLATURA,\nSIENDO GOBERNADOR CONSTITUCIONAL EL C. EUGENIO ELORDUY WALTHER 2001-\n2007.\nARTÍCULOS TRANSITORIOS\nÚNICO.- La presente reforma, entrará en vigor al día siguiente de su publicación en el\nPeriódico Oficial del Estado de Baja California.\nLey del Servicio Civil de los Trabajadores al Servicio de los Poderes Página 84\nDADO en el Salón de Sesiones “Lic. Benito Juárez García” del Honorable Poder\nLegislativo, en la Ciudad de Mexicali, Baja California, a los seis días del mes de julio del año dos mil seis\nDIP. RENE ADRIAN MENDIVIL ACOSTA\nPRESIDENTE\n(RÚBRICA)\nDIP. CARLOS ALBERTO ASTORGA OTHON\nSECRETARIA\n(RÚBRICA)\nDE CONFORMIDAD CON LO DISPUESTO POR LA FRACCION I DEL ARTICULO 49\nDE LA CONSTITUCION POLITICA DEL ESTADO, MANDO SE IMPRIMA Y PUBLIQUE.\nMEXICALI, BAJA CALIFORNIA, A LOS VEINTICINCO DIAS DEL MES DE JULIO\nDEL AÑO DOS MIL DOS.\nGOBERNADOR DEL ESTADO\nEUGENIO ELORDUY WALTHER\n(RÚBRICA)\nSECRETARIO GENERAL DE GOBIERNO\nBERNARDO H. MARTINEZ AGUIRRE\n(RÚBRICA)\nARTICULOS TRANSITORIOS DEL DECRETO No. 230, MEDIANTE EL CUAL SE\nREFORMAN LOS ARTÍCULOS 2 Y 3, PUBLICADO EN EL PERIODICO OFICIAL NO. 35,\nLEGISLATURA, SIENDO GOBERNADOR CONSTITUCIONAL EL C. EUGENIO ELORDUY\nWALTHER 2001-2007.\nTRANSITORIO\nUNICO.- El presente Decreto entrará en vigor el día 1 de enero del año 2007.\nDADO en el Salón de Sesiones “Lic. Benito Juárez García” del Honorable Poder\nLegislativo, en la Ciudad de Mexicali, Baja California, a los veintisiete días del mes de julio del año dos mil seis.\nLey del Servicio Civil de los Trabajadores al Servicio de los Poderes Página 85\nDIP. RENÉ ADRIÁN MENDÍVIL ACOSTA\nPRESIDENTE\n(RÚBRICA)\nDIP. CARLOS ALBERTO ASTORGA OTHÓN\nSECRETARIO\n(RÚBRICA)\nDE CONFORMIDAD CON LO DISPUESTO POR LA FRACCION I DEL ARTICULO 49\nDE LA CONSTITUCION POLITICA DEL ESTADO, IMPRIMASE Y PUBLIQUESE.\nMEXICALI, BAJA CALIFORNIA, A LOS SIETE DIAS DEL MES DE AGOSTO DEL\nAÑO DOS MIL SEIS.\nGOBERNADOR DEL ESTADO.\nEUGENIO ELORDUY WALTHER\n(RÚBRICA)\nSECRETARIO GENERAL DE GOBIERNO\nBERNARDO H. MARTINEZ AGUIRRE\n(RÚBRICA)\nARTÍCULO PRIMERO Y SEGUNDO TRANSITORIO DEL DECRETO No. 346, POR\nEL CUAL SE RATIFICA CONTENIDO DEL DECRETO NO. 320; POR EL QUE SE\nADICIONA UN SEGUNDO PÁRRAFO AL ARTÍCULO 105; PUBLICADO EN EL PERIÓDICO\nOFICIAL NO. 51, TOMO CXIX, SECCIÓN I, DE FECHA 16 DE NOVIEMBRE DE 2012,\nEXPEDIDO POR LA H. XX LEGISLATURA, SIENDO GOBERNADOR CONSTITUCIONAL\nEL C. JOSÉ GUADALUPE OSUNA MILLÁN 2007-2013.\nARTÍCULOS TRANSITORIOS\nPRIMERO.- El presente Decreto entrará en vigor el día de su publicación en el\nPeriódico Oficial del Estado.\nSEGUNDO.- La disposiciones contenidas en la presente reforma, serán aplicables también, a los asuntos que estén en trámite o pendientes por resolverse, en instancias jurisdiccionales. Lo anterior, fundado en el artículo 14 de la Constitución Federal, relativo a los principios de retroactividad de la ley.\nTERCERO.- El Congreso del Estado deberá tomar las medidas presupuestarias\nLey del Servicio Civil de los Trabajadores al Servicio de los Poderes Página 86 en funciones en el año 2013. del Estado de Baja California, en la Ciudad de Mexicali, B.C., a los trece días del mes de noviembre del año dos mil doce.\nDIP. ELISA ROSANA SOTO AGÜERO\nVICEPRESIDENTE\n(RÚBRICA)\nDIP. FAUSTO ZÁRATE ZEPEDA\nSECRETARIO\n(RÚBRICA)\nDE CONFORMIDAD CON LO DISPUESTO POR LA FRACCION I DEL ARTICULO 49\nDE LA CONSTITUCION POLITICA DEL ESTADO, IMPRIMASE Y PUBLIQUESE.\nMEXICALI, BAJA CALIFORNIA, A LOS CATORCE DIAS DEL MES DE NOVIEMBRE\nDEL AÑO DOS MIL DOCE.\nJOSÉ GUADALUPE OSUNA MILLÁN\nGOBERNADOR DEL ESTADO\n(RÚBRICA)\nFRANCISCO ANTONIO GARCÍA BURGOS\nSECRETARIO GENERAL DE GOBIERNO\n(RÚBRICA)\nARTÍCULO UNICO TRANSITORIO DEL DECRETO No. 52, POR EL CUAL SE\nMODIFICA LA DENOMINACIÓN DE LA LEY DEL SERVICIO CIVIL DE LOS\nTRABAJADORES AL SERVICIO DE LOS PODERES DEL ESTADO, MUNICIPIOS E\nINSTITUCIONES DESCENTRALIZADAS DE BAJA CALIFORNIA, PARA QUEDAR COMO\n“LEY DEL SERVICIO CIVIL DE LOS TRABAJADORES AL SERVICIO DE LOS PODERES\nDEL ESTADO Y MUNICIPIOS DE BAJA CALIFORNIA”; Y SE REFORMAN LOS\nARTÍCULOS 1, 3, 4, 5, 6, 8, 9, 10, 12, 15, 20 FRACCIÓN III; 26 TERCER PÁRRAFO, 32, 42,\n51, 52 FRACCIÓN IV, 55, 56, 57, 58, 68, 76, 77, 95, 98, 100, 102, 104, 105, 107, 109, 110,\n112, 117, 118, 119, 125, 126 Y 151, LA ADICIÓN DE LOS ARTÍCULOS 55 BIS Y 55 BIS 1\nAL CAPÍTULO I DEL TÍTULO TERCERO; LOS ARTÍCULOS 99 BIS, 118 BIS, 126 BIS; AL\nTÍTULO SÉPTIMO, EL CAPÍTULO III, DENOMINADO DE LOS MEDIOS PROBATORIOS,\nEL CUAL COMPRENDE LAS SECCIONES A, B, C, D, E, F, G, H, I Y J, ABARCANDO LOS\nARTÍCULOS DEL 141 BIS AL 141 BIS 59, RESPECTIVAMENTE, SE ADICIONA EL TÍTULO\nDÉCIMO TERCERO, DENOMINADO DEL ESCALAFÓN, EL CUAL CONTIENE UN\nCAPÍTULO ÚNICO, DENOMINADO DEL ESCALAFÓN, EN EL QUE SE AGRUPAN LOS\nARTÍCULOS 158 AL 170, ASÍ TAMBIÉN SE MODIFICA LA SECUENCIA NUMÉRICA DEL\nLey del Servicio Civil de los Trabajadores al Servicio de los Poderes Página 87\nTRABAJADORES, LA CONTRATACIÓN Y LAS CONDICIONES GENERALES DE\nTRABAJO, PARA QUEDAR COMO TÍTULO CUARTO, PRESERVANDO LA MISMA\nDENOMINACIÓN, Y QUEDANDO EN ÉL COMPRENDIDO EL CAPÍTULO I, DE LA\nORGANIZACIÓN COLECTIVA Y EL CAPÍTULO II, DE LAS CONDICIONES GENERALES\nDE TRABAJO. SE MODIFICA LA DENOMINACIÓN DEL TÍTULO SEXTO, POR EL DE LA\nPRESCRIPCIÓN Y DE LA CADUCIDAD, Y SE INTEGRA A ÉSTE TÍTULO EL ARTÍCULO\n94. SE MODIFICA LA DENOMINACIÓN DEL TÍTULO SÉPTIMO, PARA QUEDAR: DEL\nTRIBUNAL DE ARBITRAJE, DEL PROCEDIMIENTO Y LAS PRUEBAS, EL CUAL A SU\nVEZ SE DIVIDE EN EL CAPÍTULO I, DENOMINADO DEL TRIBUNAL DE ARBITRAJE, EL\nCAPÍTULO II, DENOMINADO DEL PROCEDIMIENTO ANTE EL TRIBUNAL, Y EL\nCAPÍTULO III, DENOMINADO DE LOS MEDIOS PROBATORIOS; PUBLICADO EN EL\nPERIÓDICO OFICIAL No. 24, NUMERO ESPECIAL, TOMO CXXI, DE FECHA 08 DE MAYO\nDE 2014, EXPEDIDO POR LA H. XXI LEGISLATURA, SIENDO GOBERNADOR\nCONSTITUCIONAL EL C. FRANCISCO ARTURO VEGA DE LAMADRID 2013-2019.\nARTICULOS TRANSITORIOS\nPRIMERO.- Las presentes reformas entrarán en vigor al día siguiente de su publicación en el Periódico Oficial del Estado.\nSEGUNDO.- Por única ocasión las Condiciones Generales de trabajo del Poder\nLegislativo del Estado de Baja California, serán revisadas y acordadas con una vigencia del\n1 de mayo al 31 de diciembre de 2014, mismas que serán sustituidas por las que entren en vigor el 1 de enero de 2015 en los términos del artículo 76 de esta Ley.\nTERCERO.- Las presentes reformas no afectarán los derechos adquiridos y demás prestaciones reconocidas a los trabajadores con anterioridad al presente Decreto.\nCUARTO.- Las autoridades públicas contarán con tres meses a partir de la entrada en vigor del presente decreto, para publicar en el Periódico Oficial del Estado, el Catálogo\nGeneral de Puestos correspondiente, el Tabulador Anual de Remuneraciones de los\nServidores Públicos, así como para la creación de la Comisión Mixta de Escalafón y la expedición de su respectivo Reglamento. En igual plazo, las Autoridades Públicas deberán domiciliario a que se refiere el artículo 109 de esta Ley.\nQUINTO.- Dentro de los tres meses siguientes a la creación de las Comisiones Mixtas de Escalafón se deberán de designar los árbitros a que se refiere el artículo 162 de esta Ley.\nSEXTO.- El Tribunal de Arbitraje del Estado, deberá quedar configurado en su nueva integración, a los treinta días hábiles siguientes a la entrada en vigor del presente decreto.\nSÉPTIMO.- Dentro un año contado a partir de la entrada en vigor del presente\nLey del Servicio Civil de los Trabajadores al Servicio de los Poderes Página 88 decreto, se deberá expedir la Ley del Servicio Profesional de Carrera para la administración estatal centralizada a que se refiere la fracción I del artículo 51 de esta Ley.\nOCTAVO.- Las menciones que en otras leyes se hagan a la Ley del Servicio Civil de los Trabajadores al Servicio de los Poderes del Estado, Municipios e Instituciones\nDescentralizadas, se entenderán hechas a la Ley del Servicio Civil de los Trabajadores al Servicio de los Poderes del Estado y Municipios de Baja California.\nArtículo Transitorio Reformado\nNOVENO.- Se derogan todas aquellas disposiciones que contravengan lo dispuesto en el presente decreto.\nDÉCIMO.- Las vacantes de plazas definitivas que existen hasta la entrada en vigor de la presente ley serán propuestas por el sindicato a la Comisión Mixta de Escalafón de la\nAutoridad Pública que corresponda para que proceda de conformidad con lo previsto en esta\nLey.\nDÉCIMO PRIMERO.- Los trabajadores de base, que en su calidad de elementos de apoyo, ya laboran en las instituciones policiales, no serán considerados trabajadores de confianza y conservarán sus prerrogativas y derechos adquiridos.\nDÉCIMO SEGUNDO.- Las autoridades públicas en reconocimiento al derecho a la vivienda del que gozan sus trabajadores de base; acorde a su factibilidad financiera, procurarán integrar un fondo destinado a su implementación, debiendo llevar a cabo los trabajos técnicos y presupuestarios a más tardar al año 2019.\nDADO en el Salón de Sesiones “Lic. Benito Juárez García” del H. Poder Legislativo del Estado de Baja California, en la Ciudad de Mexicali, B.C., a los seis días del mes de mayo del año dos mil catorce.\nDIP. RENÉ ADRIÁN MENDÍVIL ACOSTA\nPRESIDENTE\n(RÚBRICA)\nDIP. MARÍA DEL CARMEN FRÍAS\nSECRETARIA\n(RÚBRICA)\nDE CONFORMIDAD CON LO DISPUESTO POR LA FRACCION I DEL ARTICULO 49\nDE LA CONSTITUCION POLITICA DEL ESTADO, IMPRIMASE Y PUBLIQUESE.\nMEXICALI, BAJA CALIFORNIA, A LOS OCHO DIAS DEL MES DE MAYO DEL AÑO\nDOS MIL CATORCE.\nFRANCISCO ARTURO VEGA DE LAMADRID\nGOBERNADOR DEL ESTADO\nLey del Servicio Civil de los Trabajadores al Servicio de los Poderes Página 89\n(RÚBRICA)\nLORETO QUINTERO QUINTERO\nOFICIAL MAYOR DE GOBIERNO EN\nSUPLENCIA POR AUSENCIA DEL\nSECRETARIO GENERAL DE GOBIERNO\n(RÚBRICA)\nARTÍCULOS PRIMERO Y SEGUNDO TRANSITORIOS DEL DECRETO No. 61,\nPOR EL QUE SE ADICIONA UN CUARTO PÁRRAFO AL ARTÍCULO 165 Y SE MODIFICA\nEL ARTÍCULO OCTAVO TRANSITORIO DEL DECRETO NÚMERO 52 DE LA XXI\nLEGISLATURA CONSTITUCIONAL DEL ESTADO DE BAJA CALIFORNIA, PUBLICADO EN\nEL PERIÓDICO OFICIAL No. 35, SECCIÓN I, TOMO CXXI, DE FECHA 04 DE JULIO DE\n2014, EXPEDIDO POR LA H. XXI LEGISLATURA, SIENDO GOBERNADOR\nCONSTITUCIONAL EL C. FRANCISCO ARTURO VEDA DE LAMADRID 2013-2019.\nARTÍCULOS TRANSITORIOS\nÚNICO.- Las presentes reformas entrarán en vigor al día siguiente de su publicación en el Periódico Oficial del Estado de Baja California.\nDADO en el Salón de Sesiones “Lic. Benito Juárez García” del H. Poder Legislativo del Estado de Baja California, en la Ciudad de Mexicali, B.C., a los cinco días del mes de junio del año dos mil catorce.\nDIP. FELIPE DE JESÚS MAYORAL MAYORAL\nPRESIDENTE\n(RÚBRICA)\nDIP. GERARDO ÁLVAREZ HERNÁNDEZ\nSECRETARIO\n(RÚBRICA)\nDE CONFORMIDAD CON LO DISPUESTO POR LA FRACCIÓN I DEL ARTÍCULO 49\nMEXICALI, BAJA CALIFORNIA, A LOS DIECISÉIS DÍAS DEL MES DE JUNIO DEL\nAÑO DOS MIL CATORCE.\nFRANCISCO ARTURO VEGA DE LAMADRID\nGOBERNADOR DEL ESTADO\n(RÚBRICA)\nLey del Servicio Civil de los Trabajadores al Servicio de los Poderes Página 90\nFRANCISCO RUEDA GÓMEZ\nSECRETARIO GENERAL DE GOBIERNO\n(RÚBRICA)\nARTÍCULO UNICO TRANSITORIO DEL DECRETO No. 243, POR EL QUE SE\nREFORMA EL ARTÍCULO 29, PUBLICADO EN EL PERIÓDICO OFICIAL No. 25, SECCION\nIV, TOMO CXXII, DE FECHA 29 DE MAYO DE 2015, EXPEDIDO POR LA H. XXI\nLEGISLATURA, SIENDO GOBERNADOR CONSTITUCIONAL EL C. FRANCISCO ARTURO\nVEDA DE LAMADRID 2013-2019.\nARTÍCULO TRANSITORIO\nÚNICO.- La presente reforma entrará en vigor el día siguiente al de su publicación en el Periódico Oficial del Gobierno del Estado.\nDADO en el Salón de Sesiones “Lic. Benito Juárez García” del H. Poder Legislativo del Estado de Baja California, en la Ciudad de Mexicali, B.C., a los veintitrés días del mes de abril del año dos mil quince.\nDIP. FCO. ALCIBÍADES GARCÍA LIZARDI\nPRESIDENTE\n(RÚBRICA)\nDIP. ROSALBA LÓPEZ REGALADO\nSECRETARIA\n(RÚBRICA)\nDE CONFORMIDAD CON LO DISPUESTO POR LA FRACCION I DEL ARTÍCULO 49\nMEXICALI, BAJA CALIFORNIA, A LOS ONCE DÍAS DEL MES DE MAYO DEL AÑO\nDOS MIL QUINCE.\nFRANCISCO ARTURO VEGA DE LAMADRID\nGOBERNADOR DEL ESTADO\n(RÚBRICA)\nFRANCISCO RUEDA GOMEZ\nSECRETARIO GENERAL DE GOBIERNO\n(RÚBRICA)\nLey del Servicio Civil de los Trabajadores al Servicio de los Poderes Página 91\nARTÍCULO ÚNICO TRANSITORIO DEL DECRETO No. 198, POR EL QUE SE\nAPRUEBA LA INICIATIVA DE REFORMA QUE ADICIONA UN ARTÍCULO 29 BIS,\nPUBLICADO EN EL PERIÓDICO OFICIAL No. 10, SECCION II, TOMO CXXV, DE FECHA\nGOBERNADOR CONSTITUCIONAL EL C. FRANCISCO ARTURO VEDA DE LAMADRID\n2013-2019.\nARTÍCULO TRANSITORIO\nÚNICO.- La presente iniciativa entrará en vigor el día siguiente al de su publicación en el Periódico Oficial del Gobierno del Estado.\nDADO en el Salón de Sesiones “Lic. Benito Juárez García” del H. Poder Legislativo del Estado de Baja California, en la Ciudad de Mexicali, B.C., a los veinticinco días del mes de enero del año dos mil dieciocho.\nDIP. MTRO. RAÚL CASTAÑEDA POMPOSO\nPRESIDENTE\n(RÚBRICA)\nDIP. ROCÍO LÓPEZ GOROSAVE\nSECRETARIA\n(RÚBRICA)\nDE CONFORMIDAD CON LO DISPUESTO POR LA FRACCION I DEL ARTÍCULO 49\nMEXICALI, BAJA CALIFORNIA, A LOS DOS DÍAS DEL MES DE MARZO DEL AÑO\nDOS MIL DIECIOCHO.\nFRANCISCO ARTURO VEGA DE LAMADRID\nGOBERNADOR DEL ESTADO\n(RÚBRICA)\nFRANCISCO RUEDA GÓMEZ\nSECRETARIO GENERAL DE GOBIERNO\n(RÚBRICA)\nLey del Servicio Civil de los Trabajadores al Servicio de los Poderes Página 92\nARTÍCULO VIGÉSIMO QUINTA TRANSITORIO DEL DECRETO No. 281, POR EL\nQUE SE REFORMAN LOS ARTÍCULOS 141 BIS 31, 148 Y 150, PUBLICADO EN EL\nPERIÓDICO OFICIAL No. 55, SECCION IV, TOMO CXXV, DE FECHA 30 DE NOVIEMBRE\nDE 2018, EXPEDIDO POR LA H. XXII LEGISLATURA, SIENDO GOBERNADOR\nCONSTITUCIONAL EL C. FRANCISCO ARTURO VEDA DE LAMADRID 2013-2019.\nARTÍCULOS TRANSITORIOS\nARTÍCULO PRIMERO.- El presente decreto entrará en vigor al día siguiente al de su publicación en el Periódico Oficial del Estado de Baja California.\nARTÍCULO SEGUNDO.- El valor diario de la Unidad de Medida y Actualización a la fecha de entrada en vigor, se tomará el valor publicado en el Diario Oficial de la Federación por el INEGI. El valor de la Unidad de Medida y Actualización a la fecha de entrada en vigor del presente Decreto, será producto de multiplicar el valor referido en el párrafo anterior por\n30.4. Por su parte, el valor anual será el producto de multiplicar el valor inicial mensual por\n12.\nARTÍCULO TERCERO. - Todas las menciones al salario mínimo como unidad de cuenta, índice, base, medida o referencia para determinar la cuantía de las obligaciones, sanciones, multas administrativas, conceptos de pago y montos de referencia, se entenderán referidas a la Unidad de Medida y Actualización.\nDADO en el Salón de Sesiones “Lic. Benito Juárez García” del H. Poder Legislativo del Estado de Baja California, en la Ciudad de Mexicali, B.C., a los veinticinco días del mes de octubre del año dos mil dieciocho.\nDIP. ROCÍO LÓPEZ GOROSAVE\nPRESIDENTA\n(RÚBRICA)\nDIP. MÓNICA HERNÁNDEZ ÁLVAREZ\nSECRETARIA\n(RÚBRICA)\nDE CONFORMIDAD CON LO DISPUESTO POR LA FRACCIÓN I DEL ARTÍCULO 49\nMEXICALI, BAJA CALIFORNIA, A LOS TREINTA DÍAS DEL MES DE NOVIEMBRE\nDEL AÑO DOS MIL DIECIOCHO.\nLey del Servicio Civil de los Trabajadores al Servicio de los Poderes Página 93\nFRANCISCO ARTURO VEGA DE LAMADRID\nGOBERNADOR DEL ESTADO\n(RÚBRICA)\nFRANCISCO RUEDA GÓMEZ\nSECRETARIO GENERAL DE GOBIERNO\n(RÚBRICA)\nARTÍCULO ÚNICO TRANSITORIO DEL DECRETO No. 378, POR EL QUE SE\nAPRUEBA LA REFORMA AL ARTÍCULO 29; PUBLICADO EN EL PERIÓDICO OFICIAL No.\n7, DE FECHA 09 DE FEBRERO DE 2024, ÍNDICE, TOMO CXXXI, EXPEDIDO POR LA H.\nXXIV LEGISLATURA, SIENDO GOBERNADORA CONSTITUCIONAL LA C. MARINA DEL\nPILAR ÁVILA OLMEDA 2021-2027.\nTRANSITORIOS\nPRIMERO. EI presente Decreto entrará en vigor al día siguiente de su publicación en el\nPeriódico Oficial del Estado.\nSEGUNDO. Se contará para la instalación de las salas de lactancia, con un plazo de 90 días naturales, siguientes a la publicación de la presente reforma.\nTERCERO. La aplicación del presente Decreto estará sujeta a la disponibilidad presupuestal.\nDADO en Sesión Ordinaria de la XXIV Legislatura en la Ciudad de Mexicali, B.C., a los veinticinco días del mes de enero del año dos mil veinticuatro.\nDIP. ARACELI GERALDO NÚÑEZ\nPRESIDENTA\n(RÚBRICA)\nDIP. MANUEL GUERRERO LUNA\nSECRETARIO\n(RÚBRICA)\nDE CONFORMIDAD CON LO DISPUESTO POR LA FRACCIÓN I DEL ARTÍCULO 49 DE\nCALIFORNIA, IMPRÍMASE Y PUBLÍQUESE.\nLey del Servicio Civil de los Trabajadores al Servicio de los Poderes Página 94\nMEXICALI, BAJA CALIFORNIA, A LOS VEINTINUEVE DÍAS DEL MES DE ENERO\nDEL AÑO DOS MIL VEINTICUATRO.\nMARINA DEL PILAR ÁVILA OLMEDA\nGOBERNADORA DEL ESTADO\nDE BAJA CALIFORNIA\n(RÚBRICA)\nALFREDO ÁLVAREZ CÁRDENAS\nSECRETARIO GENERAL DE GOBIERNO\nDEL ESTADO DE BAJA CALIFORNIA\n(RÚBRICA)\nARTÍCULO ÚNICO TRANSITORIO DEL DECRETO No. 390, POR EL QUE SE\nAPRUEBA LA ADICIÓN DEL ARTÍCULO 29 TER; PUBLICADO EN EL PERIÓDICO\nOFICIAL No. 13, DE FECHA 08 DE MARZO DE 2024, ÍNDICE, TOMO CXXXI, EXPEDIDO\nPOR LA H. XXIV LEGISLATURA, SIENDO GOBERNADORA CONSTITUCIONAL LA C.\nMARINA DEL PILAR ÁVILA OLMEDA 2021-2027.\nTRANSITORIO:\nÚNICO.- La presente reforma entrará en vigor al día siguiente de su publicación en el\nPeriódico Oficial del Estado de Baja California.\nDADO en Sesión Extraordinaria de la XXIV Legislatura en la Ciudad de Mexicali, B.C., a los nueve días del mes de febrero del año dos mil veinticuatro.\nDIP. ARACELI GERALDO NÚÑEZ\nPRESIDENTA\n(RÚBRICA)\nDIP. MANUEL GUERRERO LUNA\nSECRETARIO\n(RÚBRICA)\nDE CONFORMIDAD CON LO DISPUESTO POR LA FRACCIÓN I DEL ARTÍCULO 49 DE\nCALIFORNIA, IMPRÍMASE Y PUBLÍQUESE.\nMEXICALI, BAJA CALIFORNIA, A LOS VEINTE DÍAS DEL MES DE FEBRERO DEL\nAÑO DOS MIL VEINTICUATRO.\nLey del Servicio Civil de los Trabajadores al Servicio de los Poderes Página 95\nMARINA DEL PILAR ÁVILA OLMEDA\nGOBERNADORA DEL ESTADO\nDE BAJA CALIFORNIA\n(RÚBRICA)\nALFREDO ÁLVAREZ CÁRDENAS\nSECRETARIO GENERAL DE GOBIERNO\nDEL ESTADO DE BAJA CALIFORNIA\n(RÚBRICA)\nLey del Servicio Civil de los Trabajadores al Servicio de los Poderes Página 96",
  "ordenamiento": "REGLAMENTO",
  "jurisdiccion": "BAJA CALIFORNIA",
  "fuente_oficial": "Periódico Oficial",
  "FECHA PER OFIC": "2024/03/08",
  "ESTATUS": "VIGENTE",
  "TOMO": "TOMO_I",
  "URL": "https://www.congresobc.gob.mx/Documentos/ProcesoParlamentario/Leyes/TOMO_I/20240308_LEYSERCI.PDF",
  "es_escaneado": false,
  "tiene_tablas": false,
  "materia": [
    "administrativo",
    "legislativo",
    "gobernanza"
  ]
}