{
  "titulo": "Ley DE INGRESOS DEL MUNICIPIO DE PLAYAS DE ROSARITO, BAJA CALIFORNIA PARA EL EJERCICIO FISCAL DEL 20",
  "Contenido": "BAJA CALIFORNIA, EN USO DE LAS FACULTADES QUE LE CONFIERE EL ARTÍCULO\nSOBERANO DE BAJA CALIFORNIA, TIENE A BIEN APROBAR LA SIGUIENTE:\nLEY DE INGRESOS\nDEL MUNICIPIO DE PLAYAS DE ROSARITO, BAJA CALIFORNIA\nPARA EL EJERCICIO FISCAL DEL 2025\nÍNDICE GENERAL\nCAPÍTULO I.- DE LOS INGRESOS\nCAPÍTULO II.- IMPUESTOS\nSECCIÓN PRIMERA. IMPUESTOS SOBRE EL PATRIMONIO\n1.- Impuesto Predial.\n2.- Impuesto sobre Adquisición de Inmuebles.\nSECCIÓN SEGUNDA. IMPUESTOS SOBRE LA PRODUCCIÓN, EL CONSUMO Y LAS\nTRANSACCIONES\n3.- Impuesto sobre Asistencia a Juegos Permitidos y Espectáculos\nPúblicos.\n4.- Impuesto sobre Actividades de Juegos con Apuestas o Sorteos.\nSECCIÓN TERCERA. ACCESORIOS DE IMPUESTOS\n5.- Gastos de Ejecución Sobre Impuestos.\n6.- Recargos Sobre Impuestos.\nSECCIÓN CUARTA. OTROS IMPUESTOS MUNICIPALES\n7.- Impuesto para el Mantenimiento y Conservación de las Vías\nPúblicas.\nSECCIÓN QUINTA. IMPUESTOS CAUSADOS EN EJERCICIOS FISCALES ANTERIORES\nPENDIENTES DE LIQUIDACIÓN O PAGO\n8.- Impuestos Causados en Ejercicios Fiscales Anteriores Pendientes de Liquidación o Pago.\nCAPÍTULO III.- CUOTAS Y APORTACIONES DE SEGURIDAD SOCIAL\n1.- Otras Cuotas y Aportaciones de Recuperación de Servicios\nMédicos.\nCAPÍTULO IV.- CONTRIBUCIONES DE MEJORAS\nSECCIÓN PRIMERA. CONTRIBUCIÓN DE MEJORAS POR OBRAS PÚBLICAS\n1.- Aportaciones de Particulares para Obras Públicas Municipales.\nSECCIÓN SEGUNDA. CONTRIBUCIÓN DE MEJORAS CAUSADAS EN EJERCICIOS\n2.- Aportaciones de Particulares para Obras Públicas Municipales de\nAños Anteriores.\nCAPÍTULO V.- DERECHOS\nSECCIÓN PRIMERA. DERECHOS POR PRESTACIÓN DE SERVICIOS\n1.- Derechos por Servicios que Presta el Registro Civil.\n2.- Derechos por Servicios que Prestan los Panteones Municipales.\n3.- Derechos por los Servicios que Presta la Secretaría de Desarrollo y Servicios Urbanos.\n4.- Derechos por Expedición de Permisos por el Uso u Ocupación de las Vías Públicas por Comerciantes Ambulantes con Puestos Fijos o Semifijos, así como permisos provisionales en propiedad privada.\n5.- Derechos por los Servicios que Presta la Dirección de Catastro.\n6.- Derechos por los Servicios que Presta la Secretaría de Movilidad y Transporte.\n7.- Derechos por Arrastre de Vehículos.\n8.- Derechos por Almacenaje de Vehículos.\n9.- Derechos por Ocupación de la Vía Pública por Estacionamiento de\nVehículos.\n10.- Derechos por la Expedición de Certificados, Títulos, Copias de\nDocumentos y Otros Servicios Administrativos.\n11.- Derechos por Recolección de Basura.\n12.- Derechos por Servicio de Limpia.\n13.- Derechos por Servicios de Vigilancia Policíaca.\n14.- Derechos por Recepción, Análisis y Revisión de Solicitudes, de\nEmisión de Documentos, Permisos y Certificados Referentes a\nInstalaciones para la Venta, Almacenaje o Consumo de Bebidas con\nGraduación Alcohólica, Cambio de Giro, Cambio de Permisionario, Cambio de Domicilio, Cambio de Denominación Comercial y\nTramitación Relativa a la Operación de Giros de Cerveza, Vinos, Licores, Alcoholes y Similares.\n15.- Derechos por Servicios de la Dirección de Salud Municipal.\n16.- Derechos por Servicios que Presta la Dirección de Protección\nCivil y Bomberos.\n17.- Derechos por Recepción y Análisis de Documentos Referentes a la\nRealización de Espectáculos Públicos y de Diversión.\n18.- Derechos por Recepción y Análisis de Documentos Referentes a la\nInstalación de Aparatos Electromecánicos y Videojuegos.\n19.- Derechos por Servicios que Presta la Secretaría de Bienestar\nSocial Municipal.\n20.- Derecho por Alumbrado Público que Presta la Dirección de\nServicios Urbanos.\nSECCIÓN SEGUNDA. OTROS DERECHOS\n21.- Otros Derechos por Otros Servicios que Presta el Ayuntamiento u\nOrganismos Paramunicipales.\nSECCIÓN TERCERA. ACCESORIOS DE DERECHOS\n22.- Gastos de Ejecución Sobre Derechos.\n23.- Recargos Sobre Derechos.\nSECCIÓN CUARTA. DERECHOS CAUSADOS EN EJERCICIOS FISCALES ANTERIORES\nPENDIENTES DE LIQUIDACIÓN O PAGO\n24.- Derechos Causados en Ejercicios Fiscales Anteriores Pendientes de Liquidación o Pago.\nCAPÍTULO VI. - PRODUCTOS\nSECCIÓN PRIMERA. PRODUCTOS\n1.- Suministro de Formas Diversas para Trámites Administrativos.\n2.- Otras Actividades del Gobierno Municipal, que no Correspondan a sus Funciones Propias de Derecho Público.\n3.- Organismos Públicos Descentralizados y/o Paramunicipales.\n4.- Bienes Mostrencos.\n5.- Del Piso.\nSECCIÓN SEGUNDA. PRODUCTOS DE CAPITAL\n6.- Productos Financieros.\n7.- Productos Causados en Ejercicios Fiscales Anteriores Pendientes de Liquidación o Pago.\nCAPÍTULO VII.- APROVECHAMIENTOS\nSECCIÓN PRIMERA. APROVECHAMIENTOS\n1.- Multas.\n2.- Reintegros e Indemnizaciones.\n3.- Donaciones, Cesiones, Herencias y Legados a Favor del Municipio.\na).- Donaciones, Cesiones, Herencias y Legados a Favor de las\nParamunicipales.\n4.- Otorgamiento y Usufructo de Derechos.\n5.- Recuperación Parcial de Primas de Seguros de Vida.\n6.- Otros Aprovechamientos.\n7.- Cauciones, Fianzas y Depósitos cuya Pérdida se Declare por\nResolución Firme.\n8.- Otros Aprovechamientos de Capital.\nSECCIÓN SEGUNDA. APROVECHAMIENTOS PATRIMONIALES\n9.- Contraprestaciones de Concesiones, Explotación o Arrendamiento de Bienes Muebles e Inmuebles Propiedad del Gobierno Municipal.\n10.- Ingresos por Venta de Bienes Patrimoniales.\nSECCIÓN TERCERA. ACCESORIOS DE APROVECHAMIENTOS\n11.- Gastos de Ejecución Sobre Aprovechamientos.\n12.- Recargos Sobre Aprovechamientos.\nSECCIÓN CUARTA. APROVECHAMIENTOS CAUSADOS EN EJERCICIOS FISCALES\nANTERIORES PENDIENTES DE LIQUIDACIÓN O PAGO\n13.- Aprovechamientos Causados en Ejercicios Fiscales Anteriores\nPendientes de Liquidación o Pago.\nCAPÍTULO VIII.- INGRESOS POR VENTAS DE BIENES, PRESTACIÓN DE SERVICIOS\nY OTROS INGRESOS\n1.- Ingresos por Venta de Bienes, Prestación de Servicios Producidos en Establecimientos del Gobierno Municipal y Otros Ingresos.\nCAPÍTULO IX.- PARTICIPACIONES, APORTACIONES, CONVENIOS, INCENTIVOS\nSECCIÓN PRIMERA. PARTICIPACIONES\n1.- Participaciones en Impuestos Federales.\n2.- Participaciones en Impuestos Estatales:\nRealización de Obras.\nb).- Por Otros Impuestos o Ingresos del Estado, que señalen las\nLeyes, Acuerdos o Convenios que las Regulen.\nc).- Por Convenios de los Organismos Públicos Descentralizados y/o Paramunicipales con el Gobierno del Estado para la\nRealización de Obras.\nSECCIÓN SEGUNDA. APORTACIONES\n3.- Aportaciones del Gobierno del Estado o de la Federación para\nObras y Servicios Públicos, o Programas Especiales, incluyendo las que tengan Participación de las Paramunicipales.\n4.- Aportaciones Federales del Ramo 33:\na).- Fondo de Aportaciones para la Infraestructura Social\nMunicipal.\nb).- Fondo de Aportaciones para el Fortalecimiento de los\nMunicipios.\nc).- Las que reciban los Organismos Públicos Descentralizados y/o Paramunicipales de Aportaciones Municipales, Estatales o Federales.\nd).- Otras que reciban el Municipio y los Organismos Públicos\nDescentralizados y/o Paramunicipales.\nSECCIÓN TERCERA. CONVENIOS\n5.- Otros Ingresos por Convenios Federales.\na).- Otros Ingresos por Convenios Federales Efectuados con los\nOrganismos Públicos Descentralizados y/o Paramunicipales.\n6.- Otros Ingresos por Convenios Estatales.\na).- Otros Ingresos por Convenios Estatales Efectuados con los\nOrganismos Públicos Descentralizados y/o Paramunicipales.\n7.- Otros Ingresos por Convenios Municipales.\na).- Otros Ingresos por Convenios Municipales Efectuados con los Organismos Públicos Descentralizados y/o\nParamunicipales.\nSECCIÓN CUARTA. INCENTIVOS DERIVADOS DE LA COLABORACIÓN FISCAL\n8.- Otros Ingresos por Incentivos Derivados de la Colaboración\nFiscal.\nSECCIÓN QUINTA. FONDOS DISTINTOS DE APORTACIONES\n9.- Otros Ingresos por Fondos Distintos de Aportaciones.\nCAPÍTULO X.- TRANSFERENCIAS, ASIGNACIONES, SUBSIDIOS Y SUBVENCIONES\n1.- Transferencias, Asignaciones, Subsidios y Subvenciones que\nOtorgue el Gobierno del Estado.\na).- Transferencias, Asignaciones, Subsidios y Subvenciones que\nOtorgue el Gobierno del Estado al Municipio.\nb).- Transferencias, Asignaciones, Subsidios y Subvenciones que\nOtorgue el Gobierno del Estado a los Organismos Públicos\nDescentralizados y/o Paramunicipales.\n2.- Transferencias, Asignaciones, Subsidios y Subvenciones que\nOtorgue el Gobierno Federal.\na).- Transferencias, Asignaciones, Subsidios y Subvenciones que\nOtorgue el Gobierno Federal al Municipio.\nb).- Transferencias, Asignaciones, Subsidios y Subvenciones que\nOtorgue el Gobierno Federal a los Organismos Públicos\nDescentralizados y/o Paramunicipales.\n3.- Transferencias, Asignaciones, Subsidios y Subvenciones que\nOtorgue el Gobierno Municipal.\na).- Transferencias, Asignaciones, Subsidios y Subvenciones que\nDescentralizados y/o Paramunicipales.\nCAPÍTULO XI.- INGRESOS DERIVADOS DE FINANCIAMIENTOS\nSECCIÓN PRIMERA. ENDEUDAMIENTO INTERNO\n1.- Créditos Otorgados al Municipio.\n2.- Los Provenientes de Bonos y Obligaciones.\n3.- Otros.\nSECCIÓN SEGUNDA. ENDEUDAMIENTO EXTERNO\n4.- Otros Créditos Otorgados al Municipio.\nSECCIÓN TERCERA. FINANCIAMIENTO INTERNO\n5.- Adelanto de Participaciones o Aportaciones Estatales y\nFederales.\nCAPÍTULO XII.- DISPOSICIONES GENERALES\nCAPÍTULO I\nDE LOS INGRESOS\nARTÍCULO 1.- Los Ingresos del Municipio de Playas de Rosarito, Estado de Baja California, durante el Ejercicio Fiscal del 1ro. de enero al\n31 de diciembre del 2025, serán los que se obtengan por los siguientes conceptos de ingresos:\nI.- IMPUESTOS $316,169,000.00\nIMPUESTOS SOBRE EL PATRIMONIO\n1.- Impuesto Predial. $114,000,000.00\n2.- Impuesto sobre Adquisición de Inmuebles. $125,000,000.00\nIMPUESTOS SOBRE LA PRODUCCIÓN, EL CONSUMO Y LAS\nTRANSACCIONES\n3.- Impuesto sobre Asistencia a Juegos\nPermitidos y Espectáculos Públicos. $2,800,000.00\n4.- Impuesto sobre Actividades de Juegos con\nApuestas o Sorteos. $3,800,000.00\nACCESORIOS DE IMPUESTOS\n5.- Gastos de Ejecución Sobre Impuestos. $3,100,000.00\n6.- Recargos Sobre Impuestos. $3,400,000.00\nOTROS IMPUESTOS MUNICIPALES\n7.- Impuesto para el Mantenimiento y\nConservación de las Vías Públicas. $14,000,000.00\nIMPUESTOS CAUSADOS EN EJERCICIOS FISCALES\nANTERIORES PENDIENTES DE LIQUIDACIÓN O PAGO\n8.- Impuestos Causados en Ejercicios Fiscales\nAnteriores Pendientes de Liquidación o\nPago. $50,069,000.00\nII.- CUOTAS Y APORTACIONES DE SEGURIDAD SOCIAL $4,500,000.00\n1.- Otras Cuotas y Aportaciones de Recuperación de Servicios Médicos. $4,500,000.00\nIII.- CONTRIBUCIONES DE MEJORAS $1,300,000.00\nCONTRIBUCIÓN DE MEJORAS POR OBRAS PÚBLICAS\n1.- Aportaciones de Particulares para Obras\nPúblicas Municipales. $0.00\nCONTRIBUCIÓN DE MEJORAS CAUSADAS EN EJERCICIOS\nFISCALES ANTERIORES PENDIENTES DE LIQUIDACIÓN O\nPAGO\n2.- Aportaciones de Particulares para Obras\nPúblicas Municipales de Años Anteriores. $1,300,000.00\nIV.- DERECHOS $193,067,628.00\nDERECHOS POR PRESTACIÓN DE SERVICIOS\n1.- Derechos por Servicios que Presta el\nRegistro Civil. $5,485,000.00\n2.- Derechos por Servicios que Prestan los\nPanteones Municipales. $245,000.00\n3.- Derechos por los Servicios que Presta la\nUrbanos. $57,148,378.00\n4.- Derechos por Expedición de Permisos por el\nUso u Ocupación de las Vías Públicas por\nComerciantes Ambulantes con Puestos Fijos o\nSemifijos, así como permisos provisionales en propiedad privada. $2,300,000.00\n5.- Derechos por los Servicios que Presta la\nDirección de Catastro. $12,730,000.00\n6.- Derechos por los Servicios que Presta la\n7.- Derechos por Arrastre de Vehículos. $1,950,000.00\n8.- Derechos por Almacenaje de Vehículos. $500,000.00\n9.- Derechos por Ocupación de la Vía Pública por Estacionamiento de Vehículos. $3,500,000.00\n10.-Derechos por la Expedición de Certificados, Títulos, Copias de Documentos y Otros\nServicios Administrativos. $7,579,250.00\n11.-Derechos por Recolección de Basura. $5,000,000.00\n12.-Derechos por Servicio de Limpia. $0.00\n13.-Derechos por Servicios de Vigilancia\nPolicíaca. $10,000,000.00\n14.-Derechos por Recepción, Análisis y Revisión de Solicitudes, de Emisión de Documentos, Permisos y Certificados Referentes a\nInstalaciones para la Venta, Almacenaje o\nConsumo de Bebidas con Graduación\nAlcohólica, Cambio de Giro, Cambio de\nPermisionario, Cambio de Domicilio, Cambio de Denominación Comercial y Tramitación\nRelativa a la Operación de Giros de\nCerveza, Vinos, Licores, Alcoholes y\nSimilares. $15,760,000.00\n15.-Derechos por Servicios de la Dirección de\nSalud Municipal. $2,900,000.00\n16.-Derechos por Servicios que Presta la\nDirección de Protección Civil y Bomberos. $14,920,000.00\n17.-Derechos por Recepción y Análisis de\nDocumentos Referentes a la Realización de\nEspectáculos Públicos y de Diversión. $1,510,000.00\n18.-Derechos por Recepción y Análisis de\nDocumentos Referentes a la Instalación de\nAparatos Electromecánicos y Videojuegos. $2,900,000.00\n19.-Derechos por Servicios que Presta la\n20.-Derecho por Alumbrado Público que Presta la\nDirección de Servicios Urbanos. $47,000,000.00\nOTROS DERECHOS\n21.-Otros Derechos por Otros Servicios que\nPresta el Ayuntamiento u Organismos\nParamunicipales. $90,000.00\nACCESORIOS DE DERECHOS\n22.-Gastos de Ejecución Sobre Derechos. $550,000.00\n23.-Recargos Sobre Derechos. $10,000.00\nDERECHOS CAUSADOS EN EJERCICIOS FISCALES\nANTERIORES PENDIENTES DE LIQUIDACIÓN O PAGO\n24.-Derechos Causados en Ejercicios Fiscales\nAnteriores Pendientes de Liquidación o\nPago. $990,000.00\nV.- PRODUCTOS $25,590,000.00\nPRODUCTOS\n1.- Suministro de Formas Diversas para Trámites\nAdministrativos. $80,000.00\n2.- Otras Actividades del Gobierno Municipal, que no Correspondan a sus Funciones Propias de Derecho Público. $25,510,000.00\n3.- Organismos Públicos Descentralizados y/o\nParamunicipales. $0.00\n4.- Bienes Mostrencos. $0.00\n5.- Del Piso. $0.00\nPRODUCTOS DE CAPITAL\n6.- Productos Financieros. $0.00\n7.- Productos Causados en Ejercicios Fiscales\nAnteriores Pendientes de Liquidación o\nPago. $0.00\nVI.- APROVECHAMIENTOS $22,414,000.00\nAPROVECHAMIENTOS\n1.- Multas. $19,405,000.00\n2.- Reintegros e Indemnizaciones. $1,000,000.00\n3.- Donaciones, Cesiones, Herencias y Legados a\nFavor del Municipio. $300,000.00\na).- Donaciones, Cesiones, Herencias y\nLegados a Favor de las\nParamunicipales.\n4.- Otorgamiento y Usufructo de Derechos. $0.00\n5.- Recuperación Parcial de Primas de Seguros de Vida. $0.00\n6.- Otros Aprovechamientos. $73,000.00\n7.- Cauciones, Fianzas y Depósitos cuya Pérdida se Declare por Resolución Firme. $0.00\n8.- Otros Aprovechamientos de Capital. $0.00\nAPROVECHAMIENTOS PATRIMONIALES\n9.- Contraprestaciones de Concesiones, Explotación o Arrendamiento de Bienes\nMuebles e Inmuebles Propiedad del Gobierno\nMunicipal. $0.00\n10.-Ingresos por Venta de Bienes Patrimoniales. $0.00\nACCESORIOS DE APROVECHAMIENTOS\n11.- Gastos de Ejecución Sobre Aprovechamientos. $602,000.00\n12.- Recargos Sobre Aprovechamientos. $1,024,000.00\nAPROVECHAMIENTOS CAUSADOS EN EJERCICIOS\nPAGO\n13.-Aprovechamientos Causados en Ejercicios\nFiscales Anteriores Pendientes de\nLiquidación o Pago. $10,000.00\nVII.- INGRESOS POR VENTAS DE BIENES, PRESTACIÓN\nDE SERVICIOS Y OTROS INGRESOS $0.00\n1.- Ingresos por Venta de Bienes, Prestación de\nServicios Producidos en Establecimientos del Gobierno Municipal y Otros Ingresos. $0.00\nVIII.- PARTICIPACIONES, APORTACIONES,\nCONVENIOS, INCENTIVOS DERIVADOS DE LA\nCOLABORACIÓN FISCAL Y FONDOS DISTINTOS DE\nAPORTACIONES $562,418,778.00\nPARTICIPACIONES\n1.- Participaciones en Impuestos Federales. $348,655,024.00\n2.- Participaciones en Impuestos Estatales: $33,553,823.00\na).- Por Convenios con el Gobierno del\nEstado para la Realización de Obras.\nb).- Por Otros Impuestos o Ingresos del\nEstado, que señalen las Leyes, Acuerdos o Convenios que las Regulen.\nc).- Por Convenios de los Organismos\nPúblicos Descentralizados y/o\nParamunicipales con el Gobierno del\nEstado para la Realización de Obras.\nAPORTACIONES\n3.- Aportaciones del Gobierno del Estado o de la Federación para Obras y Servicios\nPúblicos, o Programas Especiales, incluyendo las que tengan Participación de las Paramunicipales. $0.00\n4.- Aportaciones Federales del Ramo 33:\na).- Fondo de Aportaciones para la\nInfraestructura Social Municipal. $38,651,230.00\nb).- Fondo de Aportaciones para el\nFortalecimiento de los Municipios. $113,811,120.00\nc).- Las que reciban los Organismos\nPúblicos Descentralizados y/o\nParamunicipales de Aportaciones\nMunicipales, Estatales o Federales. $0.00\nd).- Otras que reciban el Municipio y los\nOrganismos Públicos Descentralizados y/o Paramunicipales. $0.00\nCONVENIOS\n5.- Otros Ingresos por Convenios Federales.\na).- Otros Ingresos por Convenios\nFederales Efectuados con los\nOrganismos Públicos Descentralizados y/o Paramunicipales. $0.00\n6.- Otros Ingresos por Convenios Estatales.\na).- Otros Ingresos por Convenios\nEstatales Efectuados con los\nOrganismos Públicos Descentralizados y/o Paramunicipales. $8,992,900.00\n7.- Otros Ingresos por Convenios Municipales.\na).- Otros Ingresos por Convenios\nMunicipales Efectuados con los\nOrganismos Públicos Descentralizados y/o Paramunicipales. $ 0.00\nINCENTIVOS DERIVADOS DE LA COLABORACIÓN FISCAL\n8.- Otros Ingresos por Incentivos Derivados de la Colaboración Fiscal. $18,754,681.00\nFONDOS DISTINTOS DE APORTACIONES\n9.- Otros Ingresos por Fondos Distintos de\nAportaciones. $0.00\nIX.- TRANSFERENCIAS, ASIGNACIONES, SUBSIDIOS Y\nSUBVENCIONES $0.00\n1.- Transferencias, Asignaciones, Subsidios y\nSubvenciones que Otorgue el Gobierno del\nEstado. $0.00\na).- Transferencias, Asignaciones, Subsidios y Subvenciones que Otorgue\nb).- Transferencias, Asignaciones, Subsidios y Subvenciones que Otorgue\nOrganismos Públicos Descentralizados y/o Paramunicipales.\n2.- Transferencias, Asignaciones, Subsidios y\nSubvenciones que Otorgue el Gobierno\nFederal. $0.00\na).- Transferencias, Asignaciones, Subsidios y Subvenciones que Otorgue\nb).- Transferencias, Asignaciones, Subsidios y Subvenciones que Otorgue\nPúblicos Descentralizados y/o\nParamunicipales.\n3.- Transferencias, Asignaciones, Subsidios y\nSubvenciones que Otorgue el Gobierno\nMunicipal. $0.00\na).- Transferencias, Asignaciones, Subsidios y Subvenciones que Otorgue el Gobierno Municipal a los\nOrganismos Públicos Descentralizados y/o Paramunicipales.\nX.- INGRESOS DERIVADOS DE FINANCIAMIENTOS $0.00\nENDEUDAMIENTO INTERNO\n1.- Créditos Otorgados al Municipio. $0.00\n2.- Los Provenientes de Bonos y Obligaciones. $0.00\n3.- Otros. $0.00\nENDEUDAMIENTO EXTERNO\n4.- Otros Créditos Otorgados al Municipio. $0.00\nFINANCIAMIENTO INTERNO\n5.- Adelanto de Participaciones o Aportaciones\nEstatales y Federales. $0.00\nARTÍCULO 2.- Los ingresos ordinarios del Municipio de Playas de\nRosarito, Baja California, se dividen en Impuestos, Cuotas y\nAportaciones de Seguridad Social, Contribuciones de Mejoras, Derechos, Productos y Aprovechamientos previstos en la presente Ley de Ingresos.\nARTÍCULO 3.- Son Contribuciones de Mejoras las establecidas en la Ley públicas.\nLos elementos de las Contribuciones de Mejoras, realizadas bajo el sistema de cooperación, son los siguientes:\nI.- Objeto: El incremento de valor y la mejoría específica de la propiedad, que se originan como consecuencia inmediata y directa de la ejecución de obras por el sistema de cooperación;\nII.- Sujeto Activo: Las autoridades previstas por el Artículo 16, fracciones I, V, VI y VII de la Ley de Urbanización del Estado de Baja California;\nIII.- Sujeto Pasivo: Las personas previstas por los Artículos 2 y 7 de la Ley de Urbanización del Estado de Baja California;\nIV.- Base: Los supuestos previstos en el Artículo 94 de la Ley de\nUrbanización del Estado de Baja California;\nV.- Cuota: La que se determine de conformidad al procedimiento previsto en los Artículos 88 y 93 de la Ley de Urbanización del\nEstado de Baja California;\nVI.- Época de pago: Las Contribuciones de Mejoras serán cubiertas en la fecha y el número de exhibiciones que se determine de conformidad al procedimiento previsto en los Artículos 88 y 93 de la Ley de Urbanización del Estado de Baja California.\nARTÍCULO 4.- El pago de los Derechos que establece esta Ley deberá hacerse por el contribuyente, previamente a la prestación de los servicios, salvo los casos en que expresamente se señale otra época de pago. deban pagarse por anticipado, el servicio no se proporcionará. continuos o porque así se establezca en esta Ley, dejará de prestarse si no se efectúa dicho pago. objeto de cubrir el importe del crédito fiscal adeudado, las autoridades fiscales estarán facultadas para embargar cualquier giro, dichos establecimientos, y retener los ingresos diarios, después de salarios de los trabajadores debidamente registrados con antelación a la intervención del establecimiento. Las sumas obtenidas de los establecimientos intervenidos serán aplicadas diariamente al crédito fiscal adeudado.\nARTÍCULO 5.- El Ejecutivo Municipal dentro de sus facultades discrecionales podrá eximir cualquiera de los pagos de Derechos a que se refiere esta Ley, a personas pensionadas, jubiladas, que acrediten su condición mediante documento expedido por institución pública, así como a personas con discapacidad, o que tengan a su cargo un familiar con alguna discapacidad y residan en el mismo domicilio y además se encuentren registradas como responsables en la credencial oficial con la que se acredite la discapacidad, indigentes, adultas mayores de 60 años, personas indígenas, viudas mayores de 50 años, mujeres jefas de familia de escasos recursos, personas liberadas por amnistías, y las que se encuentren en extrema pobreza y previo estudio socioeconómico, o personas afectadas por un desastre derivado de la naturaleza o antropogénico, o contingencia sanitaria.\nTratándose de extrema pobreza, por incapacidad física, temporal o permanente de los beneficiarios por obras de urbanización, determinada mediante verificación y estudio socioeconómico que se haga al respecto, el Ejecutivo Municipal, podrá congelar el cobro de los adeudos por Contribuciones de Mejoras, previstos en esta Ley, en la medida que resulte necesario, mientras no cambie el mencionado causa. El cobro se hará efectivo cuando se transmita la propiedad a tercero, ya sea por herencia o por cualquier otro concepto.\nAsí mismo, el Ayuntamiento podrá otorgar estímulos fiscales sobre el pago de impuestos, derechos y contribuciones de mejora por obra pública, siempre y cuando estos estímulos no sean mayores al 50% y generación de nuevos empleos en el desarrollo económico del municipio, económica o que sea de impacto para el beneficio de la comunidad.\nCAPÍTULO II\nIMPUESTOS\nSECCIÓN PRIMERA\nIMPUESTOS SOBRE EL PATRIMONIO\n1.- IMPUESTO PREDIAL\nARTÍCULO 6.- El Impuesto Predial, se causará de acuerdo a lo que se establece en la Ley de Hacienda Municipal y Ley del Catastro\nInmobiliario, ambas del Estado de Baja California, así como el\nReglamento del Catastro Inmobiliario para el Municipio de Playas de\nRosarito, Baja California, de conformidad con la Tabla de Valores\nCatastrales Unitarios, elaborada por el Consejo Municipal del\nCatastro Inmobiliario del Municipio de Playas de Rosarito, B. C., y aprobadas por el Congreso del Estado de Baja California para el\nMunicipio de Playas de Rosarito, Baja California.\nEl monto del Impuesto Predial se determinará multiplicando el Valor\nCatastral Unitario, por el número de metros cuadrados que corresponda a la superficie de cada predio, aplicándole las siguientes:\n1.- Predios urbanos construidos, urbanos baldíos, suburbanos construidos, suburbanos baldíos, costeros desarrollados, costeros sin desarrollar, costeros no desarrollados completamente, rurales, rústicos, cerril baldíos, agropecuarios sobre su valor catastral........................... 2.75 puntos al millar\n2.- La tasa general contenida en el numeral anterior se adicionará para predios urbanos destinados a uso industrial, causarán el Impuesto\nPredial adicionado.................. 0.85 puntos al millar a la tasa general\nTratándose de predios rurales, suburbanos, cerril baldíos, parcelas ejidales y predios destinados a la producción agropecuaria, Municipal de Propietarios Rurales de Playas de Rosarito, A.C. o por el Comisariado Ejidal (previa inspección efectuada por Catastro), pagarán de 22.00 a 40.00 veces la Unidad de Medida y Actualización vigente, según la Tabla “C”, que se contempla en el apartado de la\nTabla de Ajustes de la presente Ley de Ingresos del Ejercicio Fiscal\n2025.\nARTÍCULO 7.- La Contribución por concepto del Impuesto Predial anual, se regirá con base a la Tabla de Valores Catastrales Unitarios, aprobados por el Congreso del Estado, y no podrá ser menor a 9.50 veces la Unidad de Medida y Actualización vigente.\nEl Impuesto Predial deberá cubrirse anualmente durante los tres primeros meses del año en curso.\nIndistintamente de lo señalado en el párrafo anterior, la autoridad fiscal podrá autorizar que sea cubierto bimestralmente durante los meses de enero, marzo, mayo, julio, septiembre y noviembre, siempre y cuando sea solicitado por el contribuyente y se trate de personas pensionadas, jubiladas, que acrediten su condición mediante documento expedido por institución pública, así como a personas con discapacidad, o que tengan a su cargo un familiar con alguna acredite la discapacidad, adultas mayores de 60 años, personas indígenas, viudas mayores de 50 años, mujeres jefas de familia de escasos recursos, y las que se encuentren en extrema pobreza y previo estudio socioeconómico.\nARTÍCULO 8.- Los contribuyentes que opten por pagar el Impuesto\nPredial del 2025 durante los primeros tres meses del año gozarán de la reducción de un 10% de descuento en el mes de enero, de un 7% en el mes de febrero y de un 5% en el mes de marzo del monto del Impuesto determinado en lo dispuesto en los Artículos 6 y 7 de la presente\nLey, siempre y cuando se cumpla con el pago total anual en una sola exhibición.\nLos propietarios de predios urbanos baldíos, que adquieran el de descuento en el pago del Impuesto Predial, siempre y cuando no hayan recibido el beneficio a que se refiere el párrafo anterior. El bimestral.\nLas bases del Certificado de Mejoramiento a la Imagen Urbana, se encuentran establecidas en el Artículo 28 de esta Ley.\n2.- IMPUESTO SOBRE ADQUISICIÓN DE INMUEBLES\nARTÍCULO 9.- Es objeto de este impuesto, toda adquisición de inmuebles que se realice dentro del territorio del Municipio de Playas de\nRosarito, Baja California, por cualquiera de los medios establecidos en la Ley de Hacienda Municipal del Estado de Baja California y la presente Ley.\nSon sujetos de este impuesto las personas físicas o morales que adquieran inmuebles consistentes en el suelo o en el suelo y las construcciones adheridas a él, incluyendo los accesorios y las instalaciones especiales que pertenezcan al inmueble, ubicados en el\nMunicipio; la adquisición de derechos reales o posesionarios sobre los bienes inmuebles, al igual que los contemplados en el artículo 75\nBIS B, apartado A de la Ley de Hacienda Municipal del Estado de Baja\nCalifornia. por la cual se adquiera el inmueble por cualquiera de sus formas. establece, sobre la base gravable que se determine de acuerdo a la\nLey de Hacienda Municipal del Estado de Baja California.\nTASA MARGINAL SOBRE\nLÍMITE LÍMITE\nRANGO CUOTA FIJA EXCEDENTE DEL LÍMITE\nINFERIOR SUPERIOR\nINFERIOR\n1 0.01 500,000.00 0.00 1.50%\n2 500,000.01 1,000,000.00 7,500.00 2.00%\n3 1,000,000.01 1,600,000.00 17,500.00 2.50%\n4 1,600,000.01 2,600,000.00 32,500.00 3.00%\n5 2,600,000.01 3,800,000.00 62,500.00 3.50%\n6 3,800,000.01 5,200,000.00 104,500.00 4.00%\n7 5,200,000.01 6,800,000.00 160,500.00 4.50%\n8 6,800,000.01 EN ADELANTE 232,500.00 5.00%\nPara el cálculo de este impuesto, la base del mismo deberá ubicarse en el renglón que le corresponda de entre los límites del recuadro, a la base se le disminuirá el límite inferior del rango que le corresponda y a la diferencia del excedente del límite inferior se le aplicará la tasa marginal que le corresponda; al resultado se le sumará la cuota fija del mismo rango y el importe de dicha operación será el Impuesto Sobre Adquisición de Inmuebles a pagar. Lo anterior, conforme a la siguiente fórmula:\n((BI-LI)*T)+CF = Impuesto Sobre Adquisición de Inmuebles a pagar.\nEn donde:\nBI= Base del Impuesto\nLI= Límite Inferior correspondiente\nT= Tasa marginal sobre excedente del límite inferior correspondiente\nCF= Cuota Fija correspondiente del inmueble referido a la fecha de adquisición, mismo que no deberá\nMunicipio de Playas de Rosarito, Baja California. del ejercicio fiscal 2025, aprobada por el Congreso del Estado.\nSe aplicará a la base gravable la tasa 0%, cuando la adquisición sea por alguno de los siguientes supuestos:\na) Por donación, herencia o legado entre cónyuges.\nb) Por donación, herencia o legado que se realicen de padres a hijos o de hijos a padres.\nc) En las operaciones en que los adquirientes sean asociaciones civiles, o asociaciones religiosas que no persigan fines de lucro, debidamente registradas en el Estado.\nd) Por la adquisición de terrenos a través de títulos de propiedad, expedidos por el Registro Agrario Nacional que obtengan los ejidatarios.\nLa tasa del 0% no será aplicable cuando los donatarios, herederos o legatarios cedan sus derechos sobre los bienes gravables, y cuando los adquirientes a que se refiere el inciso d) cedan sus derechos a personas distintas a las que hacen alusión en dicho inciso.\nLa tarifa establecida en el presente artículo será aplicable a partir del ejercicio fiscal 2025 para la determinación del Impuesto Sobre\nAdquisición de Inmuebles, respecto de los bienes inmuebles ubicados en el Municipio de Playas de Rosarito.\nPor lo tanto, cualquier disposición emitida con anterioridad que se oponga a la presente disposición no surtirá efecto alguno en el\nMunicipio de Playas de Rosarito, en tanto se encuentre vigente la misma.\nPara la revisión y aceptación de este impuesto, el contribuyente deberá presentar la siguiente documentación legible:\n1.- Formato previamente llenado de la declaración de Impuesto Sobre\nAdquisición de Inmuebles.\n2.- Contrato o sentencia donde se adquieren derechos reales o posesorios.\n3.- Identificación de las partes.\n4.- Avalúo vigente.\n5.- Libertad de Gravamen con vigencia al ejercicio fiscal en curso.\n6.- Comprobante de pago del trámite de cambio de propietario emitido por la Autoridad Catastral Municipal.\n7.- Acta de Nacimiento en caso del párrafo séptimo inciso b) de este artículo y en los casos del inciso a), deberá presentar bienes. inmuebles, el dar aviso dentro de los primeros 15 días hábiles después del hecho imponible a la Autoridad Fiscal Municipal, siendo párrafo. que se hacen referencia en la fracción IX del artículo\n75 BIS B de la Ley de Hacienda Municipal del Estado de Baja\nCalifornia de las operaciones y actos por la que se causen los mismos cuando: autoricen actos o contratos de adquisición de propiedad de inmuebles o de derechos reales o posesorios, así como cuando inscriban o realicen anotaciones de escrituras, actos o contratos sin que el causante compruebe que se han cubierto estas contribuciones.\nLa responsabilidad solidaria, consiste en el pago del importe total de las contribuciones mencionadas que indebidamente dejaron de pagar los contribuyentes.\nAsí mismo, tendrán la misma responsabilidad solidaria sobre el\nImpuesto Sobre Adquisición de Inmuebles los enajenantes de inmuebles que omitan dar aviso a la autoridad municipal correspondiente de las operaciones de transmisión de dominio que realicen cuando dichas operaciones no se hayan formalizado ante fedatario público o autoridad competente.\nSi el adquiriente una vez transcurrido el tiempo establecido en la presente Ley para presentar la declaración y al no haberlo hecho en tiempo y forma se entiende que al ser un impuesto autodeterminado fiscales. Por lo tanto, se procederá a la aplicación de una sanción\nInmuebles de conformidad con el artículo 89 fracción I, inciso l) encuentran en el supuesto jurídico.\nSECCIÓN SEGUNDA\nIMPUESTOS SOBRE LA PRODUCCIÓN, EL CONSUMO Y LAS TRANSACCIONES\n3.- IMPUESTO SOBRE ASISTENCIA A JUEGOS PERMITIDOS Y ESPECTÁCULOS\nPÚBLICOS\nARTÍCULO 10.- Son sujetos de este Impuesto, los asistentes a juegos permitidos, espectáculos públicos y centros de diversión, así como funciones de obra de teatro y circo. No se considerarán espectáculos públicos, los presentados en restaurantes, bares, cabarets, salones de fiesta o baile y centros nocturnos, cuando se acredite previamente a la celebración del evento que los ingresos por dichos espectáculos, serán acumulados a los propios del establecimiento.\nTratándose de eventos organizados por Partidos Políticos, por cualquiera de los Organismos Públicos Descentralizados de la\nAdministración Pública Municipal, DIF Estatal u organismos no lucrativos que brinden servicios y asistencia médica de manera gratuita a enfermos que padezcan cáncer en etapa terminal, están obligados a cumplir con el pago del Impuesto a que hace referencia el párrafo primero. La autoridad municipal podrá, si así lo considera hacer la devolución de dicho Impuesto enterado, a solicitud del organizador siempre y cuando le sea emitido recibo o factura fiscal del mismo organizador y demuestre que la totalidad de los ingresos fueron acreditados y acumulados en sus ingresos propios.\nARTÍCULO 11.- Tratándose de juegos permitidos, espectáculos públicos y centros de diversión, juegos mecánicos, obra de teatro, circo, espectáculos taurinos, rodeos y eventos deportivos, el Impuesto Sobre\nAsistencia a Juegos Permitidos y Espectáculos Públicos se calculará aplicando la tasa del 4% sobre el precio de admisión o sobre el importe del consumo mínimo obligatorio (COVER), debiéndolo cobrar el a la entrada del espectáculo público.\nTratándose de eventos de peleas de gallos, variedades y baile erótico, la tasa aplicable será del 7% sobre el precio de admisión o sobre el importe del consumo mínimo obligatorio (COVER), debiéndolo cobrar el a la entrada del espectáculo público. por sociedades de alumnos, comités de vecinos y asociaciones que no persigan fines de lucro, se aplicará un descuento del 50% sobre la tasa que corresponda según lo establecido en este Artículo.\nARTÍCULO 12.- Los organizadores o empresarios de los espectáculos públicos, juegos permitidos o centros de diversión, previamente a la iniciación de los actos generadores del mismo, garantizarán el crédito fiscal estimado por la Tesorería Municipal, mediante fianza mercantil otorgada por compañía afianzadora acreditada en el municipio, que no actividades, ni superior al que pudiera corresponder también estimativamente a tres días, debiéndose estipular el tiempo para hacer efectiva la fianza por la falta de entero del Impuesto causado dentro del término que señala la Ley para ese efecto.\nLos honorarios de los interventores de los eventos a que se refieren los Artículos anteriores, se determinarán discrecionalmente por el\nRecaudador de Rentas Municipal y en ningún caso será inferior a 4.00 veces la Unidad de Medida y Actualización vigente en el Estado.\n4.- IMPUESTO SOBRE ACTIVIDADES DE JUEGOS CON APUESTAS O SORTEOS.\nARTÍCULO 13.- Son sujetos de este Impuesto, los permisionarios que derivado de sus actividades de juegos con apuestas o sorteos, otorguen premios en efectivo o en especie al amparo de un permiso federal otorgado por la Secretaría de Gobernación o de una resolución judicial que haya causado estado, registrados y reconocidos en la página oficial de la citada Secretaría de Gobernación.\nARTÍCULO 14.- El Impuesto sobre Actividades de Juegos con Apuestas o\nSorteos se determinará, por los permisionarios y organizadores de juegos con apuestas permitidas, multiplicando el valor nominal de los billetes, boletos, apuestas y demás comprobantes que permitan la participación o la apuesta, deduciéndose a dicha base gravable el valor del premio efectivamente pagado o entregado a los participantes, los participantes, aplicándole la siguiente:\n1.- Para los organizadores de juegos con apuestas permitidas y/o habilidades o destrezas......................... 3.00 %\nEl pago de este Impuesto se realizará de manera mensual, enterándose en la Recaudación de Rentas Municipal a más tardar el día 17 de cada mes, siguiente a aquel al que corresponda el pago, utilizando para la declaración el formato que expida la Recaudación de Rentas Municipal.\nSECCIÓN TERCERA\nACCESORIOS DE IMPUESTOS\n5.- GASTOS DE EJECUCIÓN SOBRE IMPUESTOS\nARTÍCULO 15.- Los gastos de ejecución se cobrarán a quien se le pago de Impuestos municipales, no satisfechas dentro de los plazos legales, una vez iniciado el Procedimiento Administrativo de\nEjecución que señala la Ley de Hacienda Municipal del Estado de Baja\nCalifornia.\nEn ningún expediente administrativo de ejecución, los gastos serán menores de 2.00 veces la Unidad de Medida y Actualización vigente, ni excederán de 500.00 veces la Unidad de Medida y Actualización vigente por los honorarios del ejecutor o ejecutores que intervengan. Los gastos por impresiones, publicaciones y cualquier otra erogación que, con el carácter de extraordinaria, sea necesaria para el éxito del procedimiento de ejecución, se liquidarán por separado.\n6.- RECARGOS SOBRE IMPUESTOS\nARTÍCULO 16.- La tasa de recargos sobre Impuestos municipales en caso de prórroga será del 1% mensual, y será incrementada a un 2% tratándose de mora. Los recargos se causarán hasta por 5 años.\nSECCIÓN CUARTA\nOTROS IMPUESTOS MUNICIPALES\n7.- IMPUESTO PARA EL MANTENIMIENTO Y CONSERVACIÓN DE LAS VÍAS\nPÚBLICAS\nARTÍCULO 17.- Son sujetos de este Impuesto, los propietarios o poseedores de vehículos de motor, que residan dentro del territorio del municipio de Playas de Rosarito, Baja California, para contribuir en el mantenimiento y conservación de las vías públicas municipales.\nARTÍCULO 18.- El pago de este impuesto se realizará anualmente y se enterará ante las instituciones autorizadas, previo convenio que se celebre con el municipio de Playas de Rosarito, Baja California, al tarjeta de circulación relativa, conforme a la siguiente:\na).- Vehículos de servicio particular 6.00 VECES UNIDAD DE MEDIDA\nY ACTUALIZACIÓN VIGENTE\nb).- Vehículos de servicio público de pasajeros y carga, así como vehículos particulares de carga pesada de más de 2 toneladas.... 11.00 VECES UNIDAD DE MEDIDA\nY ACTUALIZACIÓN VIGENTE\nSECCIÓN QUINTA\nIMPUESTOS CAUSADOS EN EJERCICIOS FISCALES ANTERIORES PENDIENTES DE\nLIQUIDACIÓN O PAGO\n8.- IMPUESTOS CAUSADOS EN EJERCICIOS FISCALES ANTERIORES\nPENDIENTES DE LIQUIDACIÓN O PAGO\nARTÍCULO 19.- Los Impuestos no pagados en el Ejercicio Fiscal en que se causaron, se cobrarán aplicando en cuanto al fondo, las Leyes vigentes a la fecha en que se generaron y en cuanto a la forma mediante el procedimiento administrativo de ejecución que establece la Ley de\nHacienda Municipal del Estado de Baja California, o en su caso, el procedimiento judicial que corresponda.\nCAPÍTULO III\nCUOTAS Y APORTACIONES DE SEGURIDAD SOCIAL\n1.- OTRAS CUOTAS Y APORTACIONES DE RECUPERACIÓN DE SERVICIOS\nMÉDICOS\nARTÍCULO 20.- Los empleados municipales, los empleados de los organismos públicos descentralizados, los empleados de las del municipio u organismo empleador, deberán aportar una cuota equivalente al 4% de su salario bruto como aportación del empleado al\nSeguro de Enfermedades No Profesionales y de Maternidad recibido.\nCuando los empleados del Ayuntamiento, los empleados de los organismos públicos descentralizados, los empleados de las Paramunicipales o de éstos, los servicios de seguridad social a través del Instituto de\nSeguro Social, no estarán obligados a cubrir la aportación a que hace referencia el párrafo primero de este Artículo, debiendo en su lugar realizar las aportaciones contempladas en la Ley del Instituto que corresponda.\nCuando los organismos públicos descentralizados, las Paramunicipales o cualquier otro organismo de participación municipal celebre convenio con el Ayuntamiento, para que sus empleados reciban consultas médicas a través de la Dirección de Salud Municipal, estos organismos deberán de pagar al Ayuntamiento una cuota equivalente al 40% de las aportaciones mensuales retenidas a sus empleados por los servicios convenidos.\nCAPÍTULO IV\nCONTRIBUCIONES DE MEJORAS\nSECCIÓN PRIMERA\nCONTRIBUCIÓN DE MEJORAS POR OBRAS PÚBLICAS\n1.- APORTACIONES DE PARTICULARES PARA OBRAS PÚBLICAS MUNICIPALES\nARTÍCULO 21.- Los propietarios o poseedores de los predios que resulten beneficiados con obras públicas, tales como pavimentación, banquetas y guarniciones, estarán obligados a cubrir el importe total municipal, y se determinará de la siguiente manera:\nI.- Cuando beneficien uniformemente alguna zona y no sea cada propietario, el monto total de las obras será dividido metros lineales que tengan de frente sus predios.\nII.- El costo de las obras que sólo beneficien a determinado predio, se pagarán por el propietario beneficiado. en exhibiciones parciales iguales, previo convenio que celebre con las autoridades, pero el plazo de liquidación total no podrá, en ningún caso, ser mayor de cinco años. desde el siguiente bimestre a aquél en que se inicien las obras, temporal o definitiva de las obras.\nARTÍCULO 22.- Los propietarios o poseedores de los predios que resulten beneficiados con obras públicas, tales como pavimentación, banquetas y guarniciones, estarán obligados a cubrir el importe total o parcial de tales obras de acuerdo a lo convenido con la autoridad municipal o el organismo público descentralizado o Paramunicipal, que realice la obra, y se determinará de la siguiente manera:\nI.- Cuando beneficien uniformemente alguna zona y no sea factible determinar exactamente el beneficio que percibe cada propietario, el monto total de las obras será dividido entre cada uno de ellos proporcionalmente al número de metros lineales que tengan de frente sus predios.\nII.- El costo de las obras que beneficie a determinado predio, se determinará de multiplicar la superficie beneficiada por la cuota o cuotas que por metro cuadrado corresponda. en exhibiciones parciales iguales, previo convenio que celebre con la\nParamunicipal, pero el plazo de liquidación total no podrá en ningún caso ser mayor de cinco años. desde el siguiente bimestre a aquél en que se inicien las obras, temporal o definitiva de las obras.\nSECCIÓN SEGUNDA\nPENDIENTES DE LIQUIDACIÓN O PAGO\n2.- APORTACIONES DE PARTICULARES PARA OBRAS PÚBLICAS MUNICIPALES\nDE AÑOS ANTERIORES\nARTÍCULO 23.- Las Contribuciones de Mejoras no pagadas en el Ejercicio\nFiscal en que se causaron, se cobrarán aplicando en cuanto al fondo, establece la Ley de Hacienda Municipal del Estado de Baja California, o en su caso, el procedimiento judicial que corresponda.\nARTÍCULO 24.- Las Contribuciones de Mejoras no pagadas en el Ejercicio\nFiscal en que se causaron a la Paramunicipal, se cobrarán aplicando en cuanto al fondo, las Leyes vigentes a la fecha en que se generaron y en cuanto a la forma mediante el procedimiento administrativo de ejecución que establece la Ley de Hacienda Municipal del Estado de\nBaja California, o en su caso, el procedimiento judicial que corresponda.\nCAPÍTULO V\nDERECHOS\nSECCIÓN PRIMERA\nDERECHOS POR PRESTACIÓN DE SERVICIOS\n1.- DERECHOS POR SERVICIOS QUE PRESTA EL REGISTRO CIVIL\nARTÍCULO 25.- Los Derechos por servicios que preste el Registro Civil, serán pagados por los usuarios, sujetándose a la siguiente:\nACTUALIZACIÓN VIGENTE\nA.- NACIMIENTOS\na).- Registro............................. EXENTO\nb).- Inscripción de registro ocurrido en el extranjero........................... EXENTO\nc).- Reconocimiento de hijo (acta separada)............................ 5.00 VECES\nd).- Reconocimiento de hijo en la inscripción de registro ocurrido en el extranjero........................... 10.00 VECES\ne).- Por búsqueda de datos o antecedentes. EXENTO\nB.- MATRIMONIOS\na).- Registro o celebración dentro de las oficinas en horas hábiles............ 6.00 VECES\nb).- Registro o celebración dentro de las oficinas en horas extraordinarias.... 10.00 VECES\nc).- Registro o celebración que se verifique fuera de las oficinas en horas hábiles........................ 30.00 VECES\nd).- Registro o celebración que se verifiquen fuera de las oficinas en horas extraordinarias, excepto en día domingo.............................. 55.00 VECES\ne).- Registro o celebración que se verifiquen fuera de las oficinas en día domingo.......................... 60.00 VECES\nf).- Inscripción de registro de matrimonio celebrado en el extranjero........... 20.00 VECES\ng).- Registro o celebración de matrimonios verificados dentro del programa de\n\"Matrimonios Colectivos\" en horas hábiles extraordinarias dentro o fuera del domicilio de las oficinas............................. $ 1.00\nh).- Cambio de régimen matrimonial........ 10.00 VECES\ni).- Registro de Capitulaciones matrimoniales en régimen de separación de bienes............................ 15.20 VECES\nj).- Adicional, a la tarifa contemplada en los incisos a), b), c), d) y e) de este\nApartado, cuando sea solicitado el registro o celebración con 24 horas de anticipación o menos y previa cita................................. 15.00 VECES\nk).- Expedición de inexistencia de registro de matrimonio........................ 3.50 VECES\nEn los supuestos enumerados con los incisos “c”, “d” y “e” de este\nApartado, se causarán honorarios del Oficial del Registro Civil de acuerdo al tabulador contenido en este Artículo. Al Juez del Registro\nCivil se le pagarán los honorarios que procedan de acuerdo a los servicios prestados y montos efectivamente pagados en la Recaudación de Rentas de la Tesorería Municipal, independientemente del sueldo oficial que le corresponda por ser funcionario empleado.\nTABULADOR DE HONORARIOS DEL JUEZ DEL REGISTRO CIVIL\na).- Servicio a domicilio en horas hábiles 3.00 VECES\nb).- Servicio a domicilio en horas inhábiles, excepto en día domingo.... 10.00 VECES\nc).- Servicio a domicilio en día domingo.. 15.00 VECES\nC.- DEFUNCIONES\na).- Registro en las oficinas en horas hábiles.............................. EXENTO\nb).- Registro en las oficinas en horas extraordinarias...................... 2.70 VECES\nc).- Servicios que preste el Registro Civil a Panteones Particulares, por servicio............................. 5.20 VECES\nd).- Inscripción o transcripción de defunción ocurrida en el extranjero.. 16.00 VECES\nD.- DIVORCIOS\na).- Administrativo, tramitado en las oficinas del Registro Civil.......... 30.00 VECES\nb).- Registro de divorcios provenientes de\nJuzgado.............................. 20.00 VECES\nc).- Inscripción de divorcio dictado en el extranjero........................... 30.00 VECES\nE.- ADOPCIONES\na).- Registro............................. 12.70 VECES\nb).- Inscripción de sentencia de adopción dictada en el extranjero............. 17.70 VECES\nF.- EXPEDICIÓN DE ACTAS Y CERTIFICADOS\na).- Expedición de certificados de matrimonio...........................\nb).- Expedición de certificados de divorcio\nc).- Expedición de certificados de defunción............................\nd).- Expedición de certificados de nacimientos..........................\ne).- Certificados prenupciales de salud...\nf).- Actas de reconocimiento..............\ng).- Certificados de adopción.............\nh).- Copia certificada....................\nSujetos a la siguiente tarifa:\n1.- Servicio......................... 2.20 VECES\n2.- Expedición de la primera copia certificada del acta de registro de nacimiento.................... EXENTO\nPor la expedición de documentos subsecuentes al primero, se cobrará el 50% del costo normal del servicio.\nLas personas pensionadas, jubiladas, que acrediten su condición mediante documento expedido por institución pública, así como las personas con discapacidad, o que tengan a su cargo un familiar con encuentren registradas como responsables en la credencial oficial con la que se acredite la discapacidad, indigentes, adultas mayores de 60 años, personas indígenas, viudas mayores de 50 años, mujeres jefas de familia de escasos recursos, personas liberadas por amnistías, y las que se encuentren en extrema pobreza y previo estudio socioeconómico, cubrirán el 50% por concepto de los Derechos a que hace referencia el\nApartado F de este Artículo.\nG.- POR EL TRÁMITE DE TRASLADO DE CADÁVERES\na).- Al extranjero........................ 15.20 VECES\nb).- Fuera del municipio.................. 6.45 VECES\nc).- Dentro del municipio................. 2.70 VECES\nH.- OTROS\na).- Rectificación de actas............... 5.00 VECES\nb).- Por búsqueda de datos o antecedentes. EXENTO\nc).- Otros certificados................... 2.70 VECES\nPor la expedición de documentos subsecuentes al primero, se cobrará el 50% del costo normal del servicio.\nLas personas pensionadas, jubiladas, que acrediten su condición mediante documento expedido por institución pública, así como las personas con discapacidad, o que tengan a su cargo un familiar con la que se acredite la discapacidad, indigentes, adultas mayores de 60 años, personas indígenas, viudas mayores de 50 años, mujeres jefas de familia de escasos recursos, personas liberadas por amnistías, y las que se encuentren en extrema pobreza y previo estudio socioeconómico, cubrirán el 50% por concepto de los Derechos a que hace referencia el\nApartado H de este Artículo.\n2.- DERECHOS POR SERVICIOS QUE PRESTAN LOS PANTEONES MUNICIPALES\nARTÍCULO 26.- Los Derechos por estos servicios, se pagarán con base a la siguiente:\nACTUALIZACIÓN VIGENTE\na).- Servicio de Inhumación.................... 7.70 VECES\nb).- Renta de Espacio (6 años)................. 28.95 VECES\nc).- Permiso de Obra........................... 7.70 VECES\nd).- Refrendo Renta de Espacio 5 años más...... 28.95 VECES\ne).- Exhumaciones.............................. 7.70 VECES\nf).- Servicio de Inhumación a Perpetuidad...... 51.45 VECES\ng).- Servicios de Incineración................. 15.20 VECES\nEn cumplimiento a lo dispuesto en el Artículo 63 fracción VIII de la\nCalifornia, quedan exentas del pago de los derechos a que se refieren los incisos a), e) y f) anteriores de este Artículo, los familiares de búsqueda y localización en términos de dicha Ley, previa comprobación del parentesco. La misma exención se aplicará respecto de los derechos referidos en el Artículo 25, Apartados C, inciso b) y F, inciso c), numeral 1 de esta Ley.\nI.- GENERALES\na).- Son solidariamente responsables del pago de los Derechos a que se refiere este Artículo, las personas físicas, morales o unidades económicas, que presten los servicios.\nb).- Solamente se concederán gratuitamente fosas con temporalidad por acuerdo del C. Presidente Municipal, cuando el occiso y los deudos sean indigentes.\nc).- Por inhumaciones de cadáveres en tiempo extraordinario después de las 17:00 horas o días festivos y domingos en que se cierran los panteones, se pagará el doble de las tarifas establecidas en este Artículo.\n3.- DERECHOS POR LOS SERVICIOS QUE PRESTA LA SECRETARÍA DE\nDESARROLLO Y SERVICIOS URBANOS\nARTÍCULO 27.- Los Derechos por revisión, análisis y verificación de anteproyectos y proyectos para construcción de obra nueva, ampliación, modificación, reparación, demolición, regularización, asentamiento y traslado de oficinas, comercios y casas móviles, instalación, modificación o reparación de mecanismos de transporte electromecánico, factibilidades, peritajes, registros, certificaciones, declaratorias, supervisión, opiniones técnicas y dictámenes, incluyendo fraccionamientos, usos de suelo, anuncios, rótulos y similares, y otros servicios que presta la Secretaría de\nDesarrollo y Servicios Urbanos, deberán ser cubiertos por los solicitantes de acuerdo a la siguiente:\nDIRECCIÓN DE ADMINISTRACIÓN URBANA\nI. DEPARTAMENTO DE LICENCIAS DE CONSTRUCCIÓN\nACTUALIZACIÓN VIGENTE\nA).- Por revisión, análisis y verificación de proyecto, y emisión de habitacionales, comerciales, industriales y otros; se pagarán, previo al inicio de los trámites, hasta dos revisiones de acuerdo a la siguiente tabla:\n1.- Casa habitación y vivienda de interés social unifamiliares, tratándose de inmuebles construidos sin fines de comercialización ni de arrendamiento:\na).- Nueva, hasta 60 M² de construcción.................... 0.10 VECES POR M²\nb).- Nueva, mayor de 60 M² y hasta 200\nM² de superficie de construcción.................... 0.30 VECES POR M²\nc).- Nueva, de más de 200 M² de superficie de construcción...... 0.36 VECES POR M²\nd).- Ampliación de uso habitacional.. 0.30 VECES POR M²\ne).- Construcción de casa habitación en la costa cuando el predio en donde se pretende construir sea colindante con la zona federal marítimo terrestre.............. 0.50 VECES POR M²\nf).- Construcción de casa habitación en la costa dentro de la zona federal marítimo terrestre, siempre y cuando cuente con\nConcesión vigente y/o autorización de la dependencia federal competente en los términos del Reglamento para el\nUso y Aprovechamiento del Mar\nTerritorial, Vías Navegables, Playas, Zona Federal Marítimo\nTerrestre y Terrenos Ganados al\nMar, así como la demás normatividad aplicable.......... 1.00 VEZ POR M²\ng).- Por revisiones subsecuentes en construcciones hasta 60 M²...... 2.70 VECES POR\nREVISIÓN\nh).- Por revisiones subsecuentes en construcciones mayores a 60 M².. 20% DEL VALOR DE\nLA LICENCIA\n2.- Otras edificaciones e instalaciones, nuevas o ampliación:\na).- Habitacionales, unifamiliares y multifamiliares con fines de comercialización y/o arrendamiento, por unidad de vivienda: a.1).- Hasta 60 M²............. 0.37 VECES POR M² a.2).- Más de 60 M²............ 0.44 VECES POR M² a.3).- En la costa cuando el predio donde se pretende construir sea colindante con la zona federal marítimo terrestre...... 1.25 VECES POR M² a.4).- En la costa cuando se pretenda construir dentro de la zona federal marítimo terrestre y cuente con Concesión vigente y/o autorización de la dependencia federal competente en los términos del Reglamento para el Uso y\nAprovechamiento del Mar\nTerritorial, Vías\nNavegables, Playas, Zona\nFederal Marítimo\nTerrestre y Terrenos\nGanados al Mar, así como la demás normatividad aplicable............... 2.00 VECES POR M²\nb).- Hoteles, moteles, comercios, oficinas, salas de espectáculos, centros recreativos, hospitales, baños públicos, estacionamientos públicos, industriales y otros.. 0.44 VECES POR M² b.1).- Cuando el predio en que se pretende construir sea colindante con la zona federal marítimo terrestre............... 1.25 VECES POR M² b.2).- En la costa cuando se pretenda construir dentro de la zona federal marítimo terrestre y cuente con Concesión vigente y/o autorización de la dependencia federal competente en los términos del Reglamento para el Uso y\nAprovechamiento del Mar\nTerritorial, Vías\nNavegables, Playas, Zona\nFederal Marítimo\nTerrestre y Terrenos\nGanados al Mar, así como la demás normatividad aplicable............... 2.00 VECES POR M²\nc).- Para culto religioso e iglesias. 0.21 VECES POR M²\nd).- Cementerios y panteones: d.1).- Superficies de construcción techadas........... 0.21 VECES POR M² d.2).- Superficie total del predio.................. 0.06 VECES POR M²\ne).- Para la educación, cultura, deporte y espectáculos deportivos, recreación y parques de diversiones (superficie de construcción techada y/o graderías) cuando se trata de inversión privada............... 0.30 VECES POR M²\nf).- Para infraestructura especial, distribución de todo tipo de gas, estaciones de servicio y/o carburación, se cobrará por la superficie de construcción del uso especial.................... 7.5 VECES POR M²\ng).- Para todo tipo de firmes de concreto y/o asfalto en propiedad privada con uso comercial, industrial o multifamiliar densidad media o alta: g.1).- Hasta 100 M2............. 0.25 VECES POR M² g.2).- Mayores de 100 M2....... 0.15 VECES POR M²\nh).- Para asentamiento de construcciones móviles: h.1).- Para uso habitacional.... 0.10 VECES POR M² h.2).- Para usos distintos al habitacional............ 0.30 VECES POR M²\ni).- Para carteleras de tipo comerciales y/o espectaculares, por metro cuadrado de cimentación..................... 1.00 VEZ POR M2\nj).- Obra pública, todo tipo de edificación promovida y realizada por cualquiera de los tres órdenes de gobierno........ EXENTO\nk).- Por revisiones subsecuentes..... 20% DEL VALOR DE\nLA LICENCIA\n3.- Edificaciones provisionales o temporales destinadas a circos, espectáculos, convenciones, exposiciones, carpas, casas muestra; nuevas y ampliación, a solicitud del interesado o dependencia de gobierno:\na).- Por cada 200 M² o fracción hasta por 30 días..................... 18.75 VECES\nb).- Por cada día adicional.......... 0.50 VECES\n4.- Cercos, bardas y muros de contención; obra nueva y ampliación:\na).- Cercos de madera, lámina, malla ciclónica y reja metálica....... 0.14 VECES POR ML\nb).- Bardas: b.1).- Hasta 2.50 metros de altura.................. 0.37 VECES POR ML b.2).- Mayores de 2.50 metros de altura.................. 1.25 VECES POR ML b.3).- Cuando el predio donde se pretenda construir sea colindante con la zona federal marítimo terrestre............... 1.87 VECES POR ML b.4).- En la costa cuando se pretenda construir dentro de la zona federal marítimo terrestre y cuente con Concesión vigente y/o autorización de la dependencia federal competente en los términos del Reglamento para el Uso y\nAprovechamiento del Mar\nTerritorial, Vías\nNavegables, Playas, Zona\nFederal Marítimo\nTerrestre y Terrenos\nGanados al Mar, así como la demás normatividad aplicable............... 1.87 VECES POR ML\nc).- Muros de contención: c.1).- Hasta 2.00 metros de altura.................. 1.87 VECES POR ML c.2).- Mayores de 2.00 metros y hasta 5.00 metros de altura.................. 3.12 VECES POR ML c.3).- Mayores de 5.00 metros de altura.................. 5.00 VECES POR ML c.4).- Cuando el predio donde se pretende construir sea colindante con la zona federal marítimo terrestre............... 3.75 VECES POR ML c.5).- En la costa cuando se pretenda construir dentro de la zona federal marítimo terrestre y cuente con Concesión vigente y/o autorización de la dependencia federal competente en los términos del Reglamento para el Uso y\nAprovechamiento del Mar\nTerritorial, Vías\nNavegables, Playas, Zona\nFederal Marítimo\nTerrestre y Terrenos\nGanados al Mar, así como la demás normatividad aplicable............... 3.75 VECES POR ML\n5.- Revisión, análisis y emisión de licencias de construcción:\na).- Por torres autosoportadas\n(Antenas, emisores y receptores) por pieza....................... 156.45 VECES\n6.- Por letrero de obra.................. 3.32 VECES\n7.- Por colocación de plataformas provisionales o permanentes.......... 0.44 VECES POR M²\n8.- Plantas de tratamiento, por M²....... 1.00 VEZ POR M²\n9.- Cisternas, fosas sépticas, por M².... 0.32 VECES POR M²\n10.- Albercas, Jacuzzis, por M²........... 1.00 VEZ POR M²\nB).- Por revisión, análisis y verificación de proyecto y emisión de licencia para modificación y reparación, incluyendo remodelación y reconstrucción de edificios habitacionales, comerciales, industriales, turísticos y otros; se pagará previo al inicio de los trámites, por metro cuadrado de construcción, de acuerdo a la siguiente tabla:\n1.- Para uso habitacional unifamiliar.... 0.14 VECES POR M²\n2.- Para uso de hoteles, moteles, comercios, oficinas, salas de espectáculos, centros de reunión, hospitales, baños públicos, estacionamientos públicos, industriales, multifamiliares y otros................................ 0.21 VECES POR M²\n3.- Para cualquier uso en terrenos colindantes con la zona federal marítimo terrestre................... 0.29 VECES POR M²\n4.- Para cualquier uso en terrenos dentro de la zona federal marítimo terrestre y cuente con autorización de la dependencia federal competente en los términos del Reglamento para el Uso y\nAprovechamiento del Mar Territorial, Vías Navegables, Playas, Zona Federal\nMarítimo Terrestre y Terrenos Ganados al Mar, así como la demás normatividad aplicable............................ 0.50 VECES POR M²\n5.- Para otros usos...................... 0.14 VECES POR M²\nC).- Por revisión, análisis y verificación de proyecto y obra, y construcción, para cualesquiera de los tipos de obra e instalaciones descritos en las fracciones A) y B) inmediatas anteriores de este Artículo, que hayan sido ejecutadas total o parcialmente sin contar con las licencias correspondientes; se pagará previo al inicio del trámite; 50% adicional sobre la tarifa por licencia de construcción normal indicada en la tabla correspondiente de las fracciones A) y B) inmediatas anteriores.\nD).- Por prórroga de licencia de construcción de edificios e instalaciones; incluye revisión de planos y verificación:\n1.- Habitacionales:\na).- Hasta 80 M² de construcción..... 2.70 VECES\nb).- Mayor de 80 M² y hasta 200 M² de construcción.................... 8.95 VECES\nc).- Mayor de 200 M² y hasta 500 M² de construcción.................... 15.20 VECES\nd).- Mayor de 500 M² y hasta 1,000 M² de construcción................. 33.95 VECES\ne).- Mayor de 1,000 M² de construcción.................... 43.95 VECES MÁS\nEL 0.06 POR CADA\nM² EXCEDENTE\n2.- Para uso comercial y/o de servicios\n(hoteles, moteles, oficinas, salas de espectáculo, centros recreativos, hospitales, baños públicos, estacionamientos públicos y otros).\na).- Hasta 100 M² de construcción.... 15.20 VECES\nb).- Mayor de 100 M² y hasta 300 M² de construcción.................... 22.70 VECES\nc).- Mayor de 300 M² y hasta 500 M² de construcción.................... 30.20 VECES\nd).- Mayor de 500 M² y hasta 1,000 M² de construcción................. 43.95 VECES\ne).- Mayor de 1,000 M² de construcción................... 51.45 VECES MÁS\nEL 0.06 POR CADA\nM² EXCEDENTE\nf).- Del predio colindante con zona federal......................... 7.50 VECES más de acuerdo a los incisos “a” al “e” del punto 2.\n3.- Para industrias:\na).- Hasta 500 M² de construcción.... 36.45 VECES\nb).- Mayor de 500 M² y hasta 5,000 M² de construcción................. 43.95 VECES\nc).- Mayor de 5,000 M² de construcción.................... 51.45 VECES MÁS\nEL 0.06 POR CADA\nM² EXCEDENTE\n4.- Para edificios e instalaciones de otros tipos o usos................... 15.20 VECES\n5.- Para cercos y bardas................. 1.45 VECES\n6.- Para muros de contención............. 5.00 VECES\n7.- Para uso habitacional del predio colindante con la zona federal marítimo terrestre:\na).- Hasta 80 M² de construcción..... 5.70 VECES\nb).- Mayor de 80 M² y hasta 500 M² de construcción.................... 22.70 VECES\nc).- Mayor de 500 M² y hasta 1,000 M² de construcción................. 28.95 VECES\nd).- Mayor de 1,000 M² de construcción.................... 58.95 VECES MÁS\nEL 0.06 POR CADA\nM² EXCEDENTE\nE).- Por revisión y verificación de documentos y planos, y emisión de instalaciones; se pagará, previo al inicio de los trámites, de acuerdo a la siguiente tabla:\n1.- En construcciones hasta 100 M²....... 6.45 VECES\n2.- En construcciones mayores de 100 M² y hasta 200 M²......................... 17.50 VECES\n3.- En construcciones mayores de 200 M² y hasta 500 M²......................... 43.75 VECES\n4.- En construcciones mayores de 500 M² se pagará, además de la tarifa del numeral 3 inmediato anterior, por cada metro cuadrado adicional............. 0.44 VECES\n5.- Bardas, cercos o muros de contención hasta 50 ML, por metro lineal........ 0.12 VECES\n6.- Cercos, bardas y muros de contención, mayores de 50 ML..................... 18.95 VECES\n7.- En construcciones colindantes o dentro de la zona federal marítimo terrestre hasta 500 M², siempre y cuando cuente con autorización de la dependencia federal competente en los términos del\nReglamento para el Uso y\nAprovechamiento del Mar Territorial, Vías Navegables, Playas, Zona Federal\nMarítimo Terrestre y Terrenos Ganados al Mar, así como la demás normatividad aplicable............................ 60.00 VECES\n8.- En construcciones colindantes o dentro de la zona federal marítimo terrestre mayores a 500 M², siempre y cuando cuente con autorización de la dependencia federal competente en los términos del Reglamento para el Uso y\nAprovechamiento del Mar Territorial, Vías Navegables, Playas, Zona Federal\nMarítimo Terrestre y Terrenos Ganados al Mar, así como la demás normatividad aplicable, adicional a la tarifa del numeral 7 inmediato anterior, por metro cuadrado adicional............. 0.60 VECES\n9.- Cercos, bardas y muros de contención, colindante o dentro de la zona federal marítimo terrestre, siempre y cuando cuente con autorización de la dependencia federal competente en los términos del Reglamento para el Uso y\nAprovechamiento del Mar Territorial, Vías Navegables, Playas, Zona Federal\nMarítimo Terrestre y Terrenos Ganados al Mar, así como la demás normatividad aplicable, por ML.................... 1.00 VEZ\nF).- Por modificación de proyecto para la obtención de licencia de construcción o certificado de terminación de obra.\n1.- En construcciones menores a 60 M²...... 5.20 VECES\n2.- De 60 M² a 200 M²...................... 10.20 VECES\n3.- De 201 M² a 500 M²..................... 17.39 VECES\n4.- De 501 M² a 1,000 M²................... 50.00 VECES\n5.- Mayores de 1,000 M²................... 75.00 VECES MÁS\nEL 0.01 POR CADA\nM² EXCEDENTE\nG).- Por peritajes y dictámenes técnicos oculares sobre inmuebles; se pagará, previo al inicio de los trámites, de acuerdo con la siguiente tabla:\n1.- Dictamen técnico ocular en edificios en condición ruinosa y/o peligrosa, por cada 100 M² de construcción o fracción (no incluye ensayos de resistencia de materiales, ni de geotécnica y otros).................. 15.20 VECES\n2.- Dictamen técnico ocular en edificios de condición normal, por cada 100 M² de construcción o fracción (no incluye ensayos de resistencia de materiales, geotécnicos y otros)................. 10.20 VECES\n3.- Dictamen técnico ocular sobre el estado físico aparente de edificios, por cada 100 M² de construcción o fracción............................. 7.70 VECES\n4.- Peritaje en bardas y muros de contención, por cada 50 metros lineales o fracción (no incluye ensayos de resistencia de materiales, de geotécnica y otros)............... 6.45 VECES\n5.- Dictamen técnico sobre el estado físico aparente de bardas y muros de contención, por cada 50 metros lineales o fracción.................. 5.20 VECES\n6.- Supervisión de obras en general, a petición de parte a la Secretaría de\nDesarrollo y Servicios Urbanos, semanal o fracción................... 25.20 VECES\n7.- Dictamen técnico de ocupación de inmueble............................. 60.00 VECES\nH).- Por revisión de anteproyecto a solicitud del particular y/o promotor, para la construcción de edificios de todo tipo; se pagará previo al inicio del trámite, de acuerdo con la siguiente tabla:\n1.- Hasta 500 M² de construcción......... 22.70 VECES\n2.- Mayor de 500 M² y hasta 1,000 M² de construcción......................... 36.45 VECES\n3.- Mayores de 1,000 M² de construcción. 43.95 VECES\nI).- Por registros como director de obra, director de proyecto y demás corresponsables; se pagará, previo al inicio del trámite, de acuerdo con la siguiente tabla:\n1.- Registro inicial (alta).............. 50.20 VECES\n2.- Revalidación anual................... 18.95 VECES\n3.- Aviso de cambio de director de obra\na).- Cuando el expediente no se haya despachado...................... 12.70 VECES\nb).- Cuando el expediente se haya despachado a petición del propietario y/o perito.......... 6.45 VECES\n4.- Expedición de credencial oficial de\nDirector de Obra o Perito............ 5.20 VECES\nJ).- Por Ocupación Temporal de la Vía Pública, se pagará previo al inicio del trámite, de acuerdo con la siguiente tabla, por semana o fracción:\n1.- Para depósito de materiales de construcción:\na).- Hasta 50 M² de ocupación........ 17.70 VECES\nPOR SEMANA O FRACCIÓN\nb).- Mayor de 50 M² y hasta 100 M²... 28.95 VECES\nPOR SEMANA O FRACCIÓN\nc).- Por M² adicional de ocupación... 0.36 VECES\nPOR SEMANA O FRACCIÓN\nd).- En zonas con estacionómetros.... 28.95 VECES\nPOR SEMANA O FRACCIÓN\n2.- Para movimientos y maniobras con equipos de carga, izaje y/o montaje, incluyendo la zona o área acordonada para seguridad, por semana o fracción, excepto para el inciso d):\na).- Hasta 50 M² de ocupación........ 6.45 VECES\nPOR SEMANA\nb).- Mayor de 50 M² y hasta 100 M² de ocupación....................... 8.95 VECES\nPOR SEMANA\nc).- Por M² adicional de ocupación... 0.04 VECES\nPOR SEMANA\nd).- En zonas con estacionómetros.... 6.45 VECES\nPOR CAJÓN\nPOR DÍA\ne).- De requerirse los servicios de oficiales de seguridad pública para acordonamiento, se pagarán los Derechos correspondientes de acuerdo a lo dispuesto en el\nArtículo 41 de esta Ley.\nK).- Por certificación de terminación de obra de licencia, autorización y/o instalaciones; se pagará hasta por dos revisiones previo al inicio del trámite, por edificio y/o condominio, de acuerdo con la siguiente tabla:\n1.- Para uso habitacional:\na).- Hasta 60 M² de construcción. a.1).- Sin fines de comercialización......... 2.70 VECES a.2).- Con fines de comercialización......... 5.20 VECES\nb).- Mayor de 60 M² y hasta 90 M² de construcción. b.1).- Sin fines de comercialización......... 7.70 VECES b.2).- Con fines de comercialización......... 10.20 VECES\nc).- Mayor de 90 M² y hasta 500 M² de construcción. c.1).- Sin fines de comercialización......... 15.20 VECES c.2).- Con fines de comercialización......... 17.70 VECES\nd).- Mayores de 500 M² y hasta 1,000\nM² de construcción. d.1).- Sin fines de comercialización......... 28.95 VECES d.2).- Con fines de comercialización......... 31.45 VECES\ne).- Mayores de 1,000 M² de construcción. e.1).- Sin fines de comercialización......... 43.95 VECES\nMÁS EL 0.06 POR\nCADA M² EXCEDENTE e.2).- Con fines de comercialización......... 46.45 VECES\nMÁS EL 0.10 POR\nCADA M² EXCEDENTE\nf).- Colindante con la zona federal marítimo terrestre, adicional a la tarifa que corresponda de los incisos “a” al “e” de este numeral......................... 6.25 VECES\ng).- Dentro de la zona federal marítimo terrestre, siempre y cuando cuente con autorización de la dependencia federal competente en los términos del\nReglamento para el Uso y\nAprovechamiento del Mar\nTerritorial, Vías Navegables, Playas, Zona Federal Marítimo\nTerrestre y Terrenos Ganados al\nMar, así como la demás normatividad aplicable, adicional a la tarifa que corresponda de los incisos “a” al\n“e” de este numeral............. 10.00 VECES\n2.- Para uso comercial y/o de servicios\n(hoteles, moteles, comercios, oficinas, salas de espectáculos, centros de recreación, hospitales, baños públicos, estacionamientos públicos y otros usos):\na).- Hasta 60 M² de construcción..... 13.95 VECES\nb).- Mayor de 60 M² y hasta 100 M² de construcción.................... 20.20 VECES\nc).- Mayor de 100 M² y hasta 500 M² de construcción.................... 26.45 VECES\nd).- Mayor de 500 M² y hasta 1,000 M² de construcción................. 43.95 VECES\ne).- Mayores de 1,000 M² de construcción.................... 51.45 VECES\nMÁS EL 0.06 POR\nPOR CADA M² EXCEDENTE\nf).- Colindantes con la zona federal marítimo terrestre, adicional a la tarifa que corresponda de los incisos “a” al “e” de este numeral......................... 7.50 VECES\ng).- Dentro de la zona federal marítimo terrestre, siempre y cuando cuente con autorización de la dependencia federal competente en los términos del\nReglamento para el Uso y\nAprovechamiento del Mar\nTerritorial, Vías Navegables, Playas, Zona Federal Marítimo\nTerrestre y Terrenos Ganados al\nMar, así como la demás normatividad aplicable, adicional a la tarifa que corresponda de los incisos “a” al\n“e” de este numeral............. 12.00 VECES\n3.- Para uso en educación, cultura, salud, deporte y espectáculos deportivos, recreación y parques de diversiones y otros usos, tratándose de inversión privada:\na).- Hasta 500 M² de construcción.... 15.20 VECES\nb).- Mayor de 500 M² y hasta 1,000 M² de construcción................. 22.70 VECES\nc).- De más de 1,000 M² de construcción.................... 28.95 VECES\nMÁS EL 0.06 POR\nPOR CADA M² EXCEDENTE\n4.- Para uso industrial:\na).- Hasta 100 M² de construcción.... 22.70 VECES\nb).- Mayor de 100 M² y hasta 500 M² de construcción.................... 41.45 VECES\nc).- Mayor de 500 M² y hasta 5,000 M² de construcción................. 56.45 VECES\nd).- Mayor de 5,000 M² de construcción.................... 58.95 VECES\nMÁS EL 0.06 POR\nPOR CADA M² EXCEDENTE\ne).- Colindantes con la zona federal marítimo terrestre, adicional a la tarifa que corresponda de los incisos “a” al “d” de este numeral......................... 20.00 VECES\n5.- Para usos especiales, de acuerdo a lo estipulado en el Programa de\nDesarrollo Urbano del Centro de\nPoblación de Playas de Rosarito o en el Programa de Desarrollo Urbano del\nCentro de Población de Primo Tapia vigentes, según su ubicación:\na).- Hasta 100 M² de construcción.... 25.00 VECES\nb).- Mayor de 100 M² y hasta 500 M² de construcción................. 45.00 VECES\nc).- Mayor de 500 M² y hasta 1,000 M² de construcción................. 60.00 VECES\nd).- Mayor de 1,000 M² de construcción.................... 85.00 VECES\n6.- Para edificaciones ubicadas fuera de la mancha urbana se cobrará, sobre la tarifa anterior, un 10% adicional.\n7.- Por revisiones y/o inspecciones subsecuentes, en construcciones hasta\n60 M²................................ 1.45 VECES\nPOR REVISIÓN\n8.- Por revisiones y/o inspecciones subsecuentes, en construcciones mayores a 60 M²...................... 2.50 VECES\nPOR REVISIÓN\nL).- Por análisis de solicitudes y emisiones de conversiones, anteproyecto, declaratoria y constancia para traslación de dominio, para constituir regímenes de propiedad en condominio de inmuebles; se pagarán de acuerdo a la siguiente tabla y según las condiciones que a continuación se mencionan:\nEl pago de Derechos a que se refiere la fracción L), numerales\n1, 3 y 4, lo efectuará el interesado previamente al inicio del trámite y según notificación de la Secretaría de Desarrollo y\nServicios Urbanos.\nEl pago de los Derechos a que se refiere la fracción L), numerales 2 y 5, lo efectuará el interesado previa notificación de la Secretaría de Desarrollo y Servicios Urbanos, una vez que ésta haya determinado el costo correspondiente a los Derechos mencionados. En el caso de que el interesado no presentare el comprobante de haber entregado en la Recaudación de Rentas\nMunicipal el monto total de los Derechos anteriores en un plazo de 20 días hábiles a partir de la fecha de su notificación, ésta quedará sin efecto y se suspenderá el trámite correspondiente.\n1.- Por análisis y revisión de proyecto tipo Prototipo para la constitución del régimen de propiedad en condominio, sobre conjuntos sin construir, para uso habitacional, comercial, industrial o mixto, que se utilizarán en forma múltiple, y conformen un sólo conjunto inmobiliario.\na).- Por Prototipo menor a 200.00 M² de superficie................... 35.00 VECES\nb).- Por Prototipo mayor a 200.00 M² de superficie................... 45.00 VECES\nc).- Por modificación de Prototipo... 30.00 VECES\n2.- Por análisis y dictamen de factibilidad de conversión al régimen de propiedad en condominio C-1 de inmuebles o conjuntos habitacionales, comerciales, industriales o mixtos, ya construidos:\na).- Localizados dentro o fuera del centro de población: a.1).- Por conjuntos de hasta diez unidades............ 31.45 VECES a.2).- Por cada unidad que exceda de las diez primeras................. 5.00 VECES\n3.- Por análisis y dictamen de factibilidad de anteproyecto C-2 para la constitución de régimen de propiedad en condominio sobre conjuntos sin construir, para uso habitacional, comercial, industrial o mixto, únicos, localizados dentro del centro de población:\na).- Por conjuntos de hasta diez unidades........................ 22.70 VECES\nb).- Por cada unidad que exceda de las diez primeras................... 2.50 VECES\n4.- Por análisis y dictamen de factibilidad de anteproyecto C-2 para la constitución de régimen de propiedad en condominio sobre conjuntos sin construir, para uso habitacional, comercial, industrial o mixto, únicos, localizados fuera del centro de población:\na).- Por conjuntos de hasta diez unidades........................ 28.32 VECES\nb).- Por cada unidad que exceda de las diez primeras................... 3.12 VECES\n5.- Por declaratoria de factibilidad para la constitución del régimen de propiedad en condominio C-3 de inmuebles o conjuntos, por cada vivienda, departamento, casa o local:\na).- Por cada unidad habitacional de tipo: a.1).- Interés social.......... 7.70 VECES a.2).- Nivel medio............. 10.20 VECES a.3).- Nivel residencial....... 12.70 VECES\nb).- Por cada unidad de tipo comercial o industrial.......... 30.20 VECES\nc).- Por cada unidad habitacional en predios colindantes con la zona federal marítimo terrestre...... 31.25 VECES\n6.- Por verificación y certificación de memorias descriptivas de viviendas, departamentos, casas o locales comerciales, pertenecientes a condominios:\na).- Por la primera revisión: a.1).- Por conjuntos de hasta diez unidades........... 22.70 VECES a.2).- Por cada unidad que exceda de las diez primeras................ 2.50 VECES\nb).- Por revisiones subsecuentes: b.1).- Por conjuntos de hasta diez unidades........... 11.45 VECES b.2).- Por cada unidad que exceda de las diez primeras................ 1.25 VECES\n7.- Por constancia de cumplimiento de requisitos para traslación de dominio en condominios C-4:\na).- Por régimen, cada vez........... 25.20 VECES\nb).- Por régimen constituido sobre inmuebles construidos con un proyecto único, en un mismo conjunto inmobiliario y que sea susceptible de expedirse la constancia en un solo documento que incluya varios regímenes: b.1).- Por el primer régimen... 25.20 VECES b.2).- Por cada régimen que exceda de uno........... 2.50 VECES\n8.- Por constancia para cancelación de fianzas en condominios, cada vez..... 31.45 VECES\n9.- Por Certificación de Libros de Actas de Asamblea de Condominios........... 5.20 VECES\n10.- Cobro para modificaciones de Régimen de Condominio:\n10.1).- Por Declaratoria modificada de\nRégimen de Propiedad en\nCondominio de inmuebles o conjuntos ya constituidos, sin afectar áreas comunes ni incrementar la superficie total del inmueble, por cada vivienda, departamento o local comercial modificados o resultantes de la modificación, lo que resulte mayor y cambio de nomenclatura:\na).- Por cada unidad habitacional............. 5.50 VECES\nb).- Por cada unidad turístico en predio colindante con la zona federal marítimo terrestre................ 10.50 VECES\nc).- Por cada unidad comercial o industrial............. 15.50 VECES\n11.- Por cancelación de régimen de condominio:\na).- No inscrito en Registro Público de la Propiedad y del Comercio.. 30.00 VECES\nb).- Inscrito en Registro Público de la Propiedad y del Comercio..... 60.00 VECES\nM).- Por otros conceptos que presta la Dirección de Administración\nUrbana, a solicitud del interesado, se pagará al momento de la solicitud, lo siguiente:\n1.- Por servicios de elaboración de nota aclaratoria no incluida al momento del inicio del trámite.................... 7.07 VECES\n2.- Por certificación de planos de proyectos autorizados o bitácoras de obra, solicitados después del quinto día hábil de despacho de la licencia, se pagará:\na).- Por juego de planos no mayor a diez............................. 6.45 VECES\nb).- Por juego de planos mayor a diez............................. 11.45 VECES\nc).- Por bitácora de obra............. 5.20 VECES\n3.- Por emisión de identificación para placa de control...................... 6.45 VECES\n4.- Por expedición de constancias y copias de documentos:\na).- Copia certificada de documento por foja............................. 1.45 VECES\nb).- Copia simple por foja............ 0.82 VECES\nc).- Copia simple de planos autorizados por pieza........................ 0.82 VECES\n5.- Por búsqueda de documentos............ EXENTO\n6.- Por análisis y emisión de dictamen de no inconveniencia para la fusión de\nClaves Catastrales de predios registrados bajo régimen de propiedad en condominio......................... 12.70 VECES\nLos trámites ingresados al Departamento de Licencias de Construcción sólo permanecerán 90 días calendario, a su vencimiento, éstos se cancelarán y se tendrá que ingresar de nuevo, con el pago de Derechos correspondiente.\nII.- DEPARTAMENTO DE URBANIZACIÓN\nN).- Por análisis y revisión de acciones de urbanización para la introducción de infraestructura, pluviales, subdivisiones, relotificaciones, fusiones, movimientos de tierra y/o fraccionamientos, dentro de los términos del Título Quinto de la\nLey de Desarrollo Urbano del Estado de Baja California; se pagarán, previo al inicio de los trámites, hasta por 2 revisiones del mismo análisis, de acuerdo con la siguiente tabla, salvo por el Registro Agrario Nacional (RAN), el Instituto Nacional de\nSuelo Sustentable (INSUS) y/o por el Instituto para el Desarrollo\n(INDIVI), con excepción de los contemplados en el convenio\nAyuntamiento Municipal de Playas de Rosarito, Baja California:\n1.- Por análisis de anteproyecto de fraccionamientos, según la superficie total de predio:\na).- En predios ubicados dentro o fuera del centro de población: a.1).- Hasta de cinco hectáreas 95.00 VECES a.2).- Por cada hectárea o fracción excedente...... 7.50 VECES\n2.- Por regularización del análisis de anteproyecto de fraccionamientos, para el cual se hayan iniciado actividades relacionadas a la urbanización y/o promoción de venta sin contar con la autorización correspondiente:\na).- En predios ubicados dentro o fuera del centro de población: a.1).- Hasta de cinco hectáreas 125.00 VECES a.2).- Por cada hectárea o fracción excedente...... 11.25 VECES\n3.- Por análisis de proyecto de fraccionamientos habitacionales, comerciales, industriales o mixtos, nuevos o modificaciones a proyectos aprobados que requieran de un nuevo dictamen, según la superficie fraccionada:\na).- Hasta de cinco hectáreas........ 58.95 VECES\nb).- Por cada hectárea o fracción excedente....................... 8.75 VECES\n4.- Por análisis de proyectos de fraccionamientos tipo campestre, nuevos o modificaciones a proyectos aprobados que requieran de un nuevo dictamen, por superficie fraccionada o proyectada:\na).- Hasta cinco hectáreas........... 31.45 VECES\nb).- Por cada hectárea o fracción excedente....................... 6.25 VECES\n5.- Por regularización de Proyecto de\nFraccionamientos habitacionales, comerciales, industriales o mixtos, según la superficie proyectada, que hayan iniciado actividades relacionadas a la urbanización y/o promoción de venta sin contar con la autorización correspondiente:\na).- Hasta cinco hectáreas........... 65.00 VECES\nb).- Por cada hectárea o fracción excedente....................... 10.00 VECES\n6.- Por regularización de Proyecto de\nFraccionamientos tipo campestre, según la superficie proyectada, que hayan iniciado actividades relacionadas a la urbanización y/o promoción de venta sin contar con la autorización correspondiente:\na).- Hasta cinco hectáreas........... 40.00 VECES\nb).- Por cada hectárea o fracción excedente....................... 7.00 VECES\n7.- Por recorrido de inspección en fraccionamientos autorizados, sin concluir acciones de urbanización, con el fin de otorgar prórroga de urbanización o para disminuir fianzas por obras concluidas, se cobrará:\na).- Para fraccionamientos dentro del centro de población............. 73.95 VECES\nb).- Para fraccionamientos fuera del centro de población............. 102.70 VECES\n8.- Por constancia de cumplimiento de requisitos para traslación de dominio en fraccionamientos, cada vez que se solicite............................. 73.95 VECES\n9.- Por constancia de reducción y/o cancelación de fianza, en fraccionamientos, cada vez........... 37.70 VECES\n10.- Por análisis de factibilidad para relotificación, subdivisión y/o fusión............................... 6.45 VECES\n11.- Por realización de inspección y elaboración de Dictamen Técnico:\na).- Encaminado a la desincorporación de bienes públicos.............. EXENTO\n12.- Por relotificación, subdivisión y/o fusión de lotes urbanos y certificación de memoria descriptiva de los mismos, por cada lote fusionado o lote resultante de la subdivisión\n(lo que resulte mayor), se pagará:\na).- En lotes baldíos................ 15.20 VECES\nb).- En lotes construidos............ 17.70 VECES\nc).- En lotes que se encuentren en proceso de regularización por las instituciones de los gobiernos federal y/o estatal que correspondan.................... 0.00 VECES\nd).- Relotificación de manzanas por cada lote resultante............ 6.25 VECES\n13.- Por subdivisión y/o fusión de predios rústicos, que no devengan de un fraccionamiento, por cada lote fusionado o lote resultante de la subdivisión, se pagará:\na).- Dentro de los límites del centro de población.................... 31.45 VECES\nb).- Fuera de los límites del centro de población, para uso agropecuario y otros............ 40.20 VECES\n14.- Por análisis y revisión de proyecto de obras pluviales, áreas verdes y/o alumbrado público, promovido por particulares, según la superficie total del predio. Hasta dos revisiones y/o análisis:\na).- En predios ubicados dentro del centro de población: a.1).- Hasta de cinco hectáreas. 20.82 VECES a.2).- Por cada hectárea o fracción excedente....... 4.37 VECES\nb).- En predios ubicados fuera del centro de población: b.1).- Hasta cinco hectáreas.... 22.70 VECES b.2).- Por cada hectárea o fracción excedente....... 6.25 VECES\nc).- Por revisiones y/o análisis subsecuentes.................... 5.00 VECES\n15.- Por análisis previo de planos correspondientes a anteproyecto o proyecto ejecutivo, bajo la modalidad de fraccionamientos que no reúnan los requisitos para autorización completa de proyecto, sólo una revisión:\na).- En predios ubicados dentro del centro de población: a.1).- Hasta de cinco hectáreas.. 35.82 VECES a.2).- Por cada hectárea o fracción excedente........ 4.37 VECES\nb).- En predios ubicados fuera del centro de población: b.1).- Hasta cinco hectáreas..... 43.95 VECES b.2).- Por cada hectárea o fracción excedente........ 6.25 VECES\n16.- Por análisis, revisión e inspección para la factibilidad de Licencia de\nUrbanización (introducción de redes y/o infraestructura aérea, subterránea o a nivel de piso) en vía pública, se cobrará al inicio del trámite:\na).- Por kilómetro o fracción de línea de redes y/o infraestructura.................. 31.45 VECES\nb).- Por poste o torre................ 12.70 VECES\nc).- Por registro..................... 25.20 VECES\nd).- Por caseta de telefonía pública.. 6.45 VECES\n17.- Por prórroga de licencia de urbanización en la vía pública en el suelo, subsuelo o sobresuelo.......... 37.70 VECES\n18.- Por prórroga de licencia de urbanización de rompimiento de banqueta para la introducción de agua potable y/o drenaje sanitario................. 2.00 VECES\n19.- Por certificación de terminación de obra por introducción de redes y/o infraestructura aérea, subterránea o a nivel de piso en vía pública, o cualquier otra licencia de urbanización, se pagará hasta por dos revisiones, previo al inicio del trámite............................... 200.00 VECES\n20.- Por recorrido de inspección de las dependencias involucradas, y en su caso, elaboración de dictamen de no inconveniencia correspondiente a fraccionamientos finalizados, con el fin de la entrega-recepción parcial o total al Municipio, se cobrará, por cada recorrido:\na).- Por dictamen de no inconveniencia de entrega de alumbrado público.. 20.82 VECES\nb).- Por dictamen de no inconveniencia de entrega de áreas verdes....... 20.82 VECES\nc).- Por dictamen de no inconveniencia de entrega de Ingeniería de\nTránsito......................... 20.82 VECES\nd).- Por dictamen de no inconveniencia de entrega de Ingeniería de\nRehabilitación y Mantenimiento... 20.82 VECES\ne).- Por dictamen de no inconveniencia de entrega del señalamiento vial................ 20.82 VECES\nf).- Por dictamen de no inconveniencia de entrega de pluviales........................ 20.82 VECES\ng).- Por dictamen de no inconveniencia de entrega de polígono envolvente y puntos de control.......................... 20.82 VECES\n21.- Por análisis y revisión de modificación de proyectos de fraccionamientos autorizados y publicados en el\nPeriódico Oficial del Estado y/o autorizados por Convenios de\nRegularización con cualquier ente gubernamental, que requieran un nuevo dictamen, por superficie modificada:\na).- Con superficie de hasta 5 Has.... 145.45 VECES\nb).- Por cada hectárea o fracción..... 16.25 VECES\n22.- Por análisis y emisión de documento de situación legal de un fraccionamiento, se pagará por cada caso............... 2.07 VECES\n23.- Por cambio de Director de Obra o Perito responsable de obras y/o acciones de urbanización.......................... 27.70 VECES\n24.- Por copia simple de planos autorizados por pieza............................. 0.82 VECES\n25.- Por elaboración de nota aclaratoria no incluida en el trámite original....... 6.45 VECES\n26.- Por sancionar contratos de compraventa en predios de fraccionamientos autorizados, por el Programa de\nRegularización de Fraccionamientos y\nAsentamientos Humanos Irregulares en el\nMunicipio de Playas de Rosarito, Baja\nCalifornia, publicado en Periódico\nOficial del Estado el 01 de abril del año 2005, en predios ubicados dentro y fuera del centro de población:\na).- Por regularización de predios dentro de fraccionamientos progresivos y/o colonias populares........................ 50.20 VECES\nb).- Por regularización de predios dentro de fraccionamientos que no son progresivos ni colonias populares........................ 80.20 VECES\nÑ).- DERECHOS POR SUPERVISIÓN DE OBRA EN FRACCIONAMIENTOS, ASÍ COMO\nLAS OBRAS PÚBLICAS O PRIVADAS DE URBANIZACIÓN PARA LA\nINTRODUCCIÓN DE REDES ELÉCTRICAS, REDES DE ALCANTARILLADO\nSANITARIO, REDES DE ALCANTARILLADO PLUVIAL, REDES DE AGUA\nPOTABLE, LÍNEAS DE GAS Y REDES DE TELECOMUNICACIONES, ETC.\na).- Por supervisión de obras de urbanización realizadas esporádicamente con base al proyecto de obras autorizado; se pagará, sobre el importe total de los presupuestos presentados, salvo en los predios que se encuentren en proceso de regularización por el Registro Agrario\nNacional (RAN), el Instituto Nacional de Suelo Sustentable (INSUS) y/o por el Instituto para el Desarrollo\nInmobiliario y de la Vivienda para el\nEstado de Baja California (INDIVI), con excepción de los contemplados en el convenio celebrado entre el\nInstituto para el Desarrollo\nInmobiliario y de la Vivienda para el\nEstado de Baja California y el\nAyuntamiento Municipal de Playas de\nRosarito, Baja\nCalifornia........................... 3.00% a.1).- Por supervisión de obras de urbanización realizadas esporádicamente que no sean en fraccionamientos, se pagará, sobre el importe total de los presupuestos de obra presentados, incluyendo los expedidos por la Comisión\nEstatal de Servicios Públicos para la introducción de los servicios que ellos prestan... 5.00%\nb).- Por obra pública, factibilidades y supervisión de obras de urbanización, promovidas por cualquiera de los tres niveles de gobierno.................. EXENTO\nEl pago de estos Derechos se efectuará una vez aprobado el proyecto correspondiente por la Secretaría de Desarrollo y\nServicios Urbanos, y previamente al otorgamiento de la autorización definitiva. El cálculo del monto de estos Derechos se hará con el carácter de provisional, debiendo revisarse al terminar el desarrollo total, a efecto de que, para fijar el monto definitivo sirva de base la aplicación del porcentaje citado al costo total de las obras declarado para efectos fiscales, este mismo concepto se aplicará en los casos de obras de urbanización en vía pública, concesionada o no a la iniciativa privada y que por su ubicación impacten a la imagen urbana y el buen funcionamiento de la circulación peatonal y vehicular.\nO).- Por certificación de memorias descriptivas, planos y otros de fraccionamientos; se pagarán, previo al inicio de los trámites, de acuerdo con la siguiente tabla, salvo en los predios que se encuentren en proceso de regularización por el Registro Agrario\nNacional (RAN), el Instituto Nacional de Suelo Sustentable\n(INSUS) y/o por el Instituto para el Desarrollo Inmobiliario y de la Vivienda para el Estado de Baja California (INDIVI), con\nPlayas de Rosarito, Baja California:\n1.- Por verificación y certificación de memorias descriptivas de lotes pertenecientes a fraccionamientos autorizados, según la cantidad total de lotes, incluye hasta dos revisiones:\na).- Hasta 100 lotes................. 43.95 VECES\nb).- Por cada lote excedente......... 0.62 VECES\nc).- Predios que se encuentren en proceso de regularización por las instituciones de los gobiernos federal y/o estatal que correspondan.................... 0.00 VECES\nd).- Por revisiones subsecuentes..... 25.20 VECES\n2.- Por certificación de planos correspondientes a relotificación, subdivisión y/o fusión, cada certificación........................ 6.45 VECES\n3.- Copia certificada de relotificación, subdivisión y/o fusión............... 3.07 VECES\n4.- Por rectificación de memorias descriptivas autorizadas previamente e inscritas ante la Dirección de\nRegistro Público de la Propiedad y de\nComercio, salvo el caso de predios a nombre del Registro Agrario Nacional\n(RAN), el Instituto Nacional de Suelo\nSustentable (INSUS) y/o por el\nInstituto para el Desarrollo\nInmobiliario y de la Vivienda para el\nEstado de Baja California (INDIVI), por cada lote........................ 6.45 VECES\n5.- Por aclaración de subdivisión, fusión y/o relotificación................... 6.45 VECES\n6.- Por cancelación de subdivisión, fusión y/o relotificación............ 6.45 VECES\nP).- Por análisis y revisión para la autorización de trabajos de nivelación, limpieza, despalme y/o movimientos de tierra para el mejoramiento y desarrollo de predios; deberán ser cubiertos por el solicitante previo al inicio del trámite, según el volumen en metros cúbicos, de acuerdo con la siguiente tabla, salvo en los\nRegistro Agrario Nacional (RAN), el Instituto Nacional de Suelo\nSustentable (INSUS) y/o por el Instituto para el Desarrollo\n(INDIVI), con excepción de los contemplados en el convenio\nAyuntamiento Municipal de Playas de Rosarito, Baja California:\n1.- Por revisión, análisis de proyecto y licencia para movimiento de tierra, con cortes mayores a 0.30 metros, o rellenos para conformación de plataformas o terraplenes en predios, dentro o fuera del centro de población:\na).- Para volúmenes de hasta 200.00\nM3.............................. 25.00 VECES\nb).- Para volúmenes de 200.01 M3 hasta\n1,000.00 M3..................... 35.00 VECES\nc).- Para volúmenes de 1,000.01 M3 hasta 10,000.00 M3.............. 55.00 VECES\nd).- Por cada M3 de volumen que exceda a 10,000.01 M3 adicionar a la cuota del inciso c)............. 0.0052 VECES/M3\n2.- Por revisión, análisis de proyecto y licencia de nivelación con cortes menores a 0.30 metros, limpieza y despalme en predios, fuera o dentro del centro de población:\na).- Para volúmenes de hasta 200.00\nM³.............................. 15.00 VECES\nb).- Para volúmenes de 200.01 M3 hasta\n1,000.00 M3..................... 20.00 VECES\nc).- Para volúmenes de 1,000.01 M3 hasta 10,000.00 M3.............. 25.00 VECES\nd).- Por cada metro cúbico de volumen que exceda a 10,000.01 M³ adicionar a la cuota del inciso\nc).............................. 0.0040 VECES/M³\n3.- Por revisión, análisis y verificación de proyecto para la emisión de licencia de regularización de movimientos de tierra y/o limpieza y despalme, descritos en el inciso P) numerales 1 y 2 que hayan sido ejecutados total o parcialmente, sin contar con las licencias correspondientes, se pagará previo al inicio del trámite el cincuenta por ciento adicional de los Derechos por trámite normal.\n4.- Por prórroga de licencia para movimiento de tierra y/o nivelación, limpieza y despalme:\na).- Para volúmenes de hasta 200.00\nM³.............................. 10.00 VECES\nb).- Para volúmenes de 200.01 M³ hasta\n1,000.00 M³..................... 15.00 VECES\nc).- Para volúmenes de 1,000.01 M3 hasta 10,000.00 M3.............. 20.00 VECES\nd).- Para volúmenes mayores de\n10,000.00 M³.................... 100.00 VECES\nQ).- Por revisión y verificación de documentos y planos, y emisión de banquetas, arroyos viales o guarniciones; se pagará, previo al inicio de los trámites, de acuerdo a la siguiente tabla:\n1.- Demolición de cordón de banquetas.... 0.62 VECES ML\n2.- Demolición de banquetas.............. 0.80 VECES POR M²\n3.- Demolición de arroyos viales......... 1.00 VEZ POR M²\n4.- Construcción de cordón de banqueta o guarnición, hasta 3 ML............... 2.50 VECES\n5.- Construcción de cordón de banqueta o guarnición, mayor de 3 ML, adicionar al punto 4, por metro lineal o fracción excedente............................ 0.87 VECES\n6.- Construcción de banquetas, de hasta 3\nM²................................... 3.00 VECES\n7.- Construcción de banqueta mayor de 3\nM², adicionar al punto 6, por metro cuadrado o fracción excedente........ 1.00 VEZ\n8.- Construcción de arroyos viales, hasta\n3 M²................................. 4.00 VECES\n9.- Construcción de arroyos viales mayor de 3 M², adicionar al punto 8, por metro cuadrado o fracción excedente............................ 1.25 VECES\nR).- Por análisis y emisión de autorización de ocupación de la vía pública por elementos o mobiliario de los servicios públicos concesionados o no, a la iniciativa privada, así como por el equipamiento del comercio en la vía pública con puestos fijos o semifijos, y que por su ubicación impactan la imagen urbana y el buen funcionamiento de la circulación peatonal, tales como:\n1.- Por análisis y emisión de autorización de ocupación de la vía pública en el piso, en el subpiso y en sobrepiso por elementos o mobiliario, de los servicios públicos concesionados o no a la iniciativa privada; se pagará de acuerdo al tipo de elemento o mobiliario, previo el inicio del trámite.\na).- Para los elementos o mobiliario urbano de los equipos de telecomunicaciones y transmisión de señales de televisión por cable y distribución de gas: a.1).- Por kilómetro o fracción de línea de telecomunicaciones subterránea o aérea y/o transmisión de señales de televisión por cable y distribución de gas\n(anual)................. 75.20 VECES a.2).- Por poste o torre....... 18.95 VECES a.3).- Por registro............ 31.45 VECES a.4).- Por caseta de telefonía pública................. 18.95 VECES\nb).- Para los elementos o mobiliario urbano de los equipos de energía eléctrica: b.1).- Por kilómetro o fracción de línea de energía eléctrica subterránea o aérea................... 37.70 VECES b.2).- Por poste o torre....... 18.95 VECES b.3).- Por registro............ 31.45 VECES\nc).- Para los elementos o mobiliario urbano de los equipos de agua potable y drenaje sanitario: c.1).- Por Km o fracción de línea subterránea....... 37.70 VECES c.2).- Por registro............ 31.45 VECES\n2.- Por análisis y emisión de autorización de ocupación de la vía pública en el piso por equipamiento del comercio en la vía pública con puestos fijos y semifijos; se pagará una cuota anual de acuerdo a la superficie ocupada, previo al inicio del trámite.\na).- Por metro cuadrado o fracción de cobertizo para zonas de ascenso y descenso........................ 25.00 VECES\nb).- Por metro cuadrado o fracción de puesto fijo o semifijo para comercio en la vía pública...... 2.50 VECES\nc).- Por metro cuadrado o fracción de banca........................... 6.25 VECES\nd).- Por metro cuadrado o fracción de bote de basura.................. 2.50 VECES\ne).- Por metro cuadrado o fracción de otro tipo de equipamiento con fines comerciales............... 2.50 VECES\nIII.- DEPARTAMENTO DE USOS DEL SUELO\nS).- Por análisis y emisión de factibilidad de opiniones técnicas, copias simples, copias certificadas, destinos de infraestructura, y/o dictámenes de uso del suelo habitacional, comercial, turístico, industrial, especiales y/o de servicios sobre el predio, que sustente la factibilidad de uso del suelo en el sector en que se ubiquen; incluye el análisis normativo\nCentro de Población, con los Planes y Programas de Desarrollo\nUrbano locales y regionales, y con los Planes y Programas\nParciales y sectoriales de desarrollo urbano en vigor; se pagará de acuerdo con la superficie del predio, previo al inicio del trámite:\n1.- Por análisis y emisión de factibilidad de opinión técnica de uso del suelo en predios para usos comerciales, habitacionales, turísticos, servicios, industriales, de equipamiento y otros usos similares, con vigencia de 6 meses:\na).- Por análisis de predios hasta de\n500 M², a excepción de los que colinden o se encuentren dentro de la zona federal marítimo terrestre........................ 11.45 VECES\nb).- Por análisis de predios mayores de\n500 M² y/o colinden o se encuentren dentro de la zona federal marítimo terrestre, siempre y cuando cuente con autorización de la dependencia federal competente en los términos del Reglamento para el Uso y\nAprovechamiento del Mar\nTerritorial, Vías Navegables, Playas, Zona Federal Marítimo\nTerrestre y Terrenos Ganados al\nMar, así como la demás normatividad aplicable........... 18.95 VECES\n2.- Por análisis y emisión de factibilidad de opinión técnica de uso del suelo en predios de desarrollos habitacionales, desarrollos turísticos, centros comerciales, parques industriales, y otros similares, con vigencia de 6 meses:\n2.a).- Hasta 10,000 M² de superficie................ 43.95 VECES\n2.b).- Mayor de 10,000 M² y hasta\n100,000 M² de superficie.. 51.45 VECES\n2.c).- Mayor de 100,000 M² y hasta\n500,000 M² de superficie................ 58.95 VECES\n2.d).- Mayores de 500,000 M² de superficie................ 66.45 VECES\n2.e).- Por cada kilómetro fuera del límite del centro de población donde se ubique el predio, adicionar a la tarifa indicada en los incisos 2.a), 2.b), 2.c) y\n2.d). inmediatos anteriores................ 0.14 VECES/KM\n3.- Por análisis y revisión para la emisión de dictamen de uso del suelo para factibilidad de edificaciones en predios de uso habitacional dentro y fuera del centro de población se pagará previo a la iniciación de trámites por dictamen:\na).- De terrenos ubicados en el centro de población, dentro de la mancha urbana: a.1).- Para predios con superficie hasta 300 M².. 13.95 VECES a.2).- Para predios con superficie mayor de 300 M² y hasta 500 M²........... 20.20 VECES a.3).- Para predios con superficie mayor de 500 M² y hasta 1,000 M²......... 26.45 VECES\nb).- De terrenos ubicados fuera del centro de población: b.1).- Por predios con superficie hasta 500 M²............. 22.70 VECES b.2).- Por predios con superficie mayor de 500 M² y hasta\n1,000 M²................. 32.70 VECES b.3).- Por cada kilómetro fuera del límite del centro de población donde se ubique el predio, adicionar a la tarifa indicada en los incisos b.1) y b.2) inmediatos anteriores.... 0.14 VECES/KM\n4.- Por análisis y revisión para la emisión de dictamen de uso del suelo para factibilidad en predios, de uso industrial, se pagará de acuerdo con la superficie total del predio, por dictamen:\na).- En industria fuera y dentro del centro de población: a.1).- Hasta 100 M² de predio.. 22.70 VECES a.2).- Mayor de 100 M² y hasta\n500 M² de predio........ 28.95 VECES a.3).- Mayor de 500 M² y hasta\n1,000 M² de predio...... 36.45 VECES a.4).- Mayor de 1,000 M² de predio.................. 43.95 VECES a.5).- Por cada kilómetro fuera del límite del centro de población y/o fuera de la mancha urbana, donde se ubique el predio, adicionar a la tarifa indicada en los incisos a.1), a.2), a.3) y a.4) inmediatos anteriores... 0.14 VECES/KM\n5.- Por análisis y revisión para la emisión de dictamen de uso del suelo para factibilidad por predio de uso comercial, mixto (habitacional y comercial), o equipamiento, se cobrará por superficie del área a utilizar del predio:\na).- En predios de hasta 50 M²....... 13.95 VECES\nb).- En predios mayores de 50 M² y hasta 100 M².................... 20.20 VECES\nc).- En predios mayores de 100 M² y hasta 500 M².................... 22.70 VECES\nd).- En predios mayores de 500 M² y hasta 1,000 M².................. 26.45 VECES\ne).- En predios mayores de 1,000 M² y hasta 5,000 M².................. 36.45 VECES\nf).- En predios mayores de 5,000 M².. 55.20 VECES\ng).- Por cada kilómetro fuera del límite del centro de población y/o fuera de la mancha urbana, donde se ubique el predio, adicionar a la tarifa indicada en los incisos a), b), c), d), e) y\nf), inmediatos anteriores....... 0.14 VECES/KM\n6.- Por análisis de emisión de dictamen sobre uso del suelo para sitio de taxis, autobuses, camiones y similares............................ 21.45 VECES\n7.- Por factibilidad de asentamiento y licencia de traslado de oficinas y casas móviles; se pagará, previo al inicio del trámite................... 0.29 VECES POR M²\n8.- Por análisis de emisión de dictamen de factibilidad de uso de suelo para la instalación de cada estructura para anuncio con fines de comercializar la publicidad y con superficie mayor de\n6.00 M².............................. 31.45 VECES\n9.- Por análisis y revisión para la emisión de dictamen de uso del suelo en predios para la incorporación urbana de desarrollos habitacionales, desarrollos turísticos, centros comerciales, parques industriales, etc.\na).- De predios ubicados dentro y fuera de los límites del centro de población: a.1).- Hasta 10,000 M² de superficie.............. 43.95 VECES a.2).- Mayor de 10,000 M² y hasta 100,000 M² de superficie.............. 51.45 VECES a.3).- Mayor de 100,000 M² y hasta 500,000 M² de superficie.............. 58.95 VECES a.4).- Mayores de 500,000 M² de superficie.............. 66.45 VECES a.5).- Por cada kilómetro fuera del límite del centro de población y/o fuera de la mancha urbana, donde se ubique el predio, adicionar a la tarifa indicada en los incisos a.1), a.2), a.3) y a.4), inmediatos anteriores... 0.14 VECES/KM\n10.- Por análisis y revisión para la emisión de dictamen de uso de suelo y/o destino de infraestructura para factibilidad de predios y/o destinos de ocupación con uso especial, se pagará previo a la iniciación del trámite, por dictamen:\na).- De predios ubicados dentro y fuera de los límites del centro de población: a.1).- Sobre predios con superficie menor a 200\nM²...................... 93.95 VECES a.2).- Sobre predios con superficie mayor a 200\nM²..................... 168.95 VECES a.3).- Para destino de infraestructura mediante insta- laciones subterráneas\n(líneas de gas, cable, etc.) por metro lineal. 0.31 VECES\n11.- Por análisis y revisión para la emisión de dictamen de uso de suelo para centros de apuestas, salas de sorteos de números, apuestas remotas, libro foráneo y/o casinos y similares\n(siempre y cuando no exista moratoria para su expedición):\na).- Sobre predios con superficie hasta de 3,000\nM²........................ 625.20 VECES\nb).- Sobre predios con superficie mayor a 3,000\nM²........................ 937.70 VECES\n12.- Por expedición de copias de documentos (excepto uso especial), siempre y cuando se cuente con el expediente.\na).- Copia certificada de opinión técnica y/o dictamen de uso de suelo, por hoja.................. 6.25 VECES\nb).- Copia simple de opinión técnica y/o dictamen de uso de suelo, por hoja...................... 1.25 VECES\n13.- Por expedición de copias certificadas de uso de suelo especial, por superficie, siempre y cuando se cuente con el expediente.\na).- Predio con superficie menor\na 200 M².................. 50.20 VECES\nb).- Predio con superficie mayor de 200 M²................. 125.20 VECES\nLas solicitudes de cambio de uso de suelo en predios habitacionales, industriales, comerciales, especiales, de servicios, turísticos o mixtos deben presentar opinión técnica y/o Estudio de Impacto Urbano favorable emitido por el Instituto Municipal de Planeación para el\nMunicipio de Playas de Rosarito, Baja California, previo a la iniciación de los trámites y pagará conforme el tabulador del inciso\nS) según el uso y superficie.\nIV.- DEPARTAMENTO DE IMAGEN URBANA\nT).- Por revisión y certificación para el otorgamiento, cambio de domicilio, cambio de propietario, aumento de superficie, aumento de actividad, cambio de actividad, cambio de denominación y comerciales, industriales y de servicios, se causarán Derechos conforme a lo siguiente:\na).- Comercio básico pequeño, hasta 40\nM² de superficie................ 7.90 VECES\nb).- Despachos de profesionistas y oficinas administrativas de 10 M² hasta 60 M²..................... 15.60 VECES\nc).- Despachos de profesionistas y oficinas administrativas con superficie mayor a 60 M²........ 23.81 VECES\nd).- Expendios, abarrotes, loncherías, panaderías, tortillerías, tiendas de ropa, misceláneas, estéticas, papelerías, librerías, vidrierías, florerías, casas de cambio, venta de agua purificada\n(llenado de garrafón), casetas telefónicas, cerrajerías, café internet, curiosidades y artesanías, dulcerías, equipo de comunicación, gimnasios, imprentas, renta de autos, tiendas de segunda, videos, venta de celulares, zapaterías, mueblerías con superficies hasta de 80 M², con excepción de los contemplados en el inciso a).... 25.61 VECES\n(Para estos giros con superficies mayores a 80 M² se tomará la tarifa del inciso e)\ne).- Talleres de servicio, llanteras, lavanderías, laboratorios, ferreterías, refaccionarias, farmacias, venta de alimentos preparados, cafeterías, fruterías, fumigadoras, graneros, veterinarias, autolavados, mercados, estacionamientos públicos, limpiadurías, autoservicios, con superficie mayor de 40 M²....... 33.40 VECES\nf).- Billares, bares, restaurantes, supermercados, sub-agencias, bodegas de distribución, salones para eventos temporales, hospitales, clínicas médicas, bancos, funerarias, teatros, lotes de carros, madererías, máquinas de videojuegos, casas de empeño, discotecas, tiendas departamentales, clubes deportivos, café cantante, centros de espectáculos y salas cinematográficas, con superficie mayor de 40 M².................. 41.26 VECES\ng).- Moteles con ocupación de:\n1.- Hasta 10 habitaciones....... 33.40 VECES\n2.- De 11 habitaciones o más.... 45.01 VECES\nh).- Hoteles con ocupación de:\n1.- Hasta 30 habitaciones....... 48.97 VECES\n2.- De 31 habitaciones o más.... 56.67 VECES\ni).- Edificios educativos con:\n1.- Hasta 5 aulas............... 25.70 VECES\n2.- De 6 aulas o más............ 33.40 VECES\nj).- Giros de riesgo tales como: distribuidoras de gases, combustibles y lubricantes, oxígenos y acetilenos, estaciones de carburación de diesel, polvorines, gasolineras, lubricantes y demás de riesgo... 259.41 VECES\nk).- Yonkes, recicladoras y centros de acopio de material metálico........................ 85.76 VECES\nl).- Edificios industriales:\n1.- Industrial hasta 1,000.00 M²\n(maquiladoras, fábricas, bodegas, almacenes, empacadoras, procesadoras).. 54.96 VECES\n2.- Industrial mayor a 1,000.00\nM² (maquiladoras, fábricas, bodegas, almacenes, empacadoras, procesadoras).. 188.45 VECES\nm).- Centros de apuestas, apuestas remotas, salas de sorteos de números y/o casinos, libro foráneo y similares:\n1.- Hasta 3,000 M² de superficie 875.20 VECES\n2.- De 3,001 M² de terreno en adelante.................... 1,312.70 VECES\nn).- Otros giros no especificados:\n1.- Con superficie menor o igual\na 40 M²..................... 7.90 VECES\n2.- Con superficie mayor de 40 M² hasta 80 M²................. 25.61 VECES\n3.- Con superficie mayor a 80\nM².......................... 33.34 VECES\nU).- Por otros servicios relacionados con la licencia de operación:\na).- Por corrección de documento oficial expedido, derivado por error imputable al solicitante............ 2.07 VECES\nb).- Por tercera y subsecuente inspección, revisión y/o análisis documental para seguimiento de la obtención de la\nLicencia de Operación............... 3.32 VECES\nc).- Por expedición de constancias y copias de documentos:\n1).- Copia certificada de documento por foja....................... 1.45 VECES\n2).- Copia simple por foja.......... 0.10 VECES\nV).- Por revisión, análisis y certificación para el otorgamiento de permisos provisionales de operación para giros comerciales, industriales y de servicios, por única vez, excepto giros de alto riesgo, con venta de alcohol y/o casinos. Con vigencia de noventa días, se causarán Derechos conforme a lo siguiente:\na).- Comercio básico pequeño, hasta\n40 M² de superficie............ 1.49 VECES\nb).- Despachos de profesionistas y oficinas administrativas de 10\nM² hasta 60 M²................. 3.64 VECES\nc).- Despachos de profesionistas y oficinas administrativas con superficie mayor de 60 M²...... 4.57 VECES\nd).- Expendios, abarrotes, loncherías, panaderías, tortillerías, tiendas de ropa, misceláneas, estéticas, papelerías, librerías, vidrierías, florerías, casas de cambio, venta de agua purificada\n(llenado de garrafón), casetas telefónicas, cerrajerías, café internet, curiosidades y artesanías, dulcerías, equipos de comunicación, gimnasios, imprentas, renta de autos, tiendas de segunda, videos, venta de celulares, zapaterías, mueblerías, con superficies hasta 80 M², con excepción de los contemplados en el inciso\na)............................. 4.57 VECES\n(Para estos giros con superficies mayores a 80 M² se tomará la tarifa del inciso e)\ne).- Talleres de servicio, llanteras, lavanderías, laboratorios, ferreterías, refaccionarias, farmacias, venta de alimentos preparados, cafeterías, fruterías, fumigadoras, graneros, veterinarias, autolavados, mercados, estacionamientos públicos, limpiadurías, autoservicios con superficie mayor de 40\nM²............................. 6.45 VECES\nf).- Billares, restaurantes, supermercados, bodegas de distribución, salones para eventos temporales, hospitales, clínicas médicas, bancos, funerarias, teatros, lotes de carros, madererías, casas de empeño, tiendas departamentales, clubes deportivos y salas cinematográficas con superficie mayor de 40 M²................. 8.32 VECES\ng).- Moteles con ocupación de:\n1.- Hasta 10 habitaciones...... 5.82 VECES\n2.- De 11 habitaciones o más... 9.57 VECES\nh).- Hoteles con ocupación de:\n1.- Hasta 30 habitaciones...... 9.57 VECES\n2.- De 31 habitaciones o más... 13.95 VECES\ni).- Edificios educativos con:\n1.- Hasta 5 aulas.............. 4.57 VECES\n2.- De 6 aulas o más........... 6.45 VECES\nj).- Edificios industriales:\n1.- Industrial hasta 1,000.00 M²\n(maquiladoras, fábricas, bodegas, almacenes, empacadoras, procesadoras). 11.45 VECES\n2.- Industrial mayor a 1,000.00\nM² (maquiladoras, fábricas, bodegas, almacenes, empacadoras, procesadoras). 23.32 VECES\nk).- Otros giros no especificados:\n1.- Con superficie menor o igual\na 40 M².................... 3.63 VECES\n2.- Con superficie mayor de 40\nM² hasta 80 M²............. 4.57 VECES\n3.- Con superficie mayor a 80 M² 8.32 VECES\nl).- Venta de árboles y/u ornamentos navideños, ornamentos de temporada especial dentro de propiedad privada, hasta 45 días calendario...................... 20.20 VECES\nW).- Por verificación y certificación de factibilidad para la instalación, revalidación anual y regularización de rótulos, anuncios y similares, exceptuando la propaganda efectuada por partidos políticos; se pagará, previo al inicio del trámite por superficie o cantidad, según se indique, de acuerdo a la siguiente tabla:\n1.- Licencia nueva, cuando la instalación se efectúe una vez que sea emitida esta licencia:\na).- Cartelera no luminosa, o sin iluminación..................... 3.12 VECES POR M²\nO FRACCIÓN\nb).- Cartelera luminosa o con iluminación, excepto pantalla electrónica..................... 5.00 VECES POR M²\nO FRACCIÓN\nc).- Cartelera luminosa tipo pantalla electrónica, incluye torre directorio y pantalla en vehículo, por cara.............. 8.75 VECES POR M²\nO FRACCIÓN\nd).- Rótulo adosado o toldo no luminoso o sin iluminación...... 1.25 VECES POR M²\nO FRACCIÓN\ne).- Rótulo adosado o toldo luminoso o con iluminación (excepto de pantalla electrónica)........... 2.50 VECES POR M²\nO FRACCIÓN\nf).- Rótulo pintado no luminoso o con iluminación, por fachada que no exceda de la tercera parte de la superficie. f.1).- Hasta 2.00 M²............ 1.00 VEZ f.2).- Mayores de 2.00 M² y hasta\n10.00 M²................. 3.00 VECES f.3).- Mayores de 10.00 M²...... 6.00 VECES\ng).- Rótulo adosado electrónico y/o electromecánico, con o sin movimiento, por cada lado....... 6.25 VECES POR M²\nO FRACCIÓN\nh).- Figura cilíndrica no luminosa o sin iluminación................. 7.70 VECES\ni).- Figura cilíndrica luminosa o con iluminación..................... 10.20 VECES\nj).- Torre directorio................ 25.00 VECES\n(excepto de pantalla electrónica) POR UNIDAD\nk).- Valla publicitaria luminosa o con iluminación hasta 12.50 M²...... 5.00 VECES POR M²\nl).- Valla publicitaria no luminosa o sin iluminación hasta 12.50 M².. 3.75 VECES POR M²\nm).- Miniportacartel direccional..... 7.50 VECES POR\nPIEZA\nn).- Banca publicitaria.............. 12.50 VECES POR\nPIEZA ñ).- Cobertizo publicitario.......... 25.00 VECES POR\nPIEZA\no).- Carro de sonido por tres meses.. 15.00 VECES POR\nUNIDAD\np).- Torreta en techo de automóvil, camión o taxi................... 11.25 VECES POR\nUNIDAD\nq).- Rótulo en vehículo excepto de tipo pantalla electrónica o aquéllos de distintivo fiscal... 2.50 VECES POR M²\nr).- Rótulo en caseta telefónica, por caseta.......................... 6.25 VECES\ns).- Publicidad en banderolas, estandartes, pendones o caballetes dentro de propiedad privada, por pieza, por tres meses........................... 10.00 VECES\nt).- Anuncio en tapial hasta 12.50 M² por pieza....................... 37.50 VECES\n2.- Revalidación anual de licencia, antes del 30 de junio, al verificarse que aún se cumplen los requisitos de reglamento; cumpliendo con lo dispuesto en la Ley de Hacienda\nMunicipal del Estado de Baja\nCalifornia:\na).- Cartelera no luminosa o sin iluminación..................... 1.56 VECES POR M²\nO FRACCIÓN\nb).- Cartelera luminosa o con iluminación, excepto pantalla electrónica..................... 2.50 VECES POR M²\nO FRACCIÓN\nc).- Cartelera luminosa tipo pantalla electrónica incluye torre directorio y pantalla en vehículo, por cara.............. 4.37 VECES POR M²\nO FRACCIÓN\nd).- Rótulo adosado o toldo no luminoso o sin iluminación...... 0.62 VECES POR M²\nO FRACCIÓN\ne).- Rótulo adosado o toldo luminoso o con iluminación (excepto de pantalla electrónica)........... 1.25 VECES POR M²\nO FRACCIÓN\nf).- Rótulo pintado no luminoso o con iluminación, por fachada que no exceda de la tercera parte de la superficie. f.1).- Hasta 2.00 M²............ 0.50 VECES f.2).- Mayores de 2.00 M² y hasta\n10.00 M²................. 1.50 VECES f.3).- Mayores de 10.00 M²...... 3.00 VECES\ng).- Rótulo adosado electrónico y/o electromecánico, con o sin movimiento, por cada lado....... 2.50 VECES POR M²\nO FRACCIÓN\nh).- Figura cilíndrica no luminosa o sin iluminación................. 2.50 VECES\ni).- Figura cilíndrica luminosa o con iluminación..................... 5.00 VECES\nj).- Torre directorio................ 22.50 VECES POR\n(excepto de pantalla electrónica) UNIDAD\nk).- Valla publicitaria luminosa o con iluminación hasta 12.50 M²...... 2.50 VECES POR M²\nl).- Valla publicitaria no luminosa o sin iluminación hasta 12.50 M².. 1.87 VECES POR M²\nm).- Miniportacartel direccional..... 3.75 VECES POR\nPIEZA\nn).- Banca publicitaria.............. 6.25 VECES POR\nPIEZA ñ).- Cobertizo publicitario.......... 12.50 VECES POR\nPIEZA\no).- Carro de sonido por tres meses.. 10.00 VECES POR\nUNIDAD\np).- Torreta en techo de automóvil, camión o taxi................... 6.25 VECES POR\nUNIDAD\nq).- Rótulo en vehículo, excepto tipo pantalla electrónica o aquéllos de distintivo fiscal............ 1.25 VECES POR M²\nr).- Rótulo en caseta telefónica, por caseta.......................... 2.50 VECES\ns).- Publicidad en banderolas, estandartes, pendones o caballetes dentro de propiedad privada, por pieza, por tres meses........... 5.00 VECES\nt).- Anuncio en tapial hasta 12.50 M² por pieza....................... 18.95 VECES\n3.- Licencia de regularización, cuando se ha efectuado la instalación sin contar con la licencia correspondiente:\na).- Cartelera no luminosa o sin iluminación..................... 6.25 VECES POR M²\nO FRACCIÓN\nb).- Cartelera luminosa o con iluminación, excepto pantalla electrónica..................... 10.00 VECES POR M²\nO FRACCIÓN\nc).- Cartelera luminosa tipo pantalla electrónica incluye torre directorio y pantalla en vehículo, por cara.............. 17.70 VECES POR M²\nO FRACCIÓN\nd).- Rótulo adosado o toldo no luminoso o sin iluminación...... 2.50 VECES POR M²\nO FRACCIÓN\ne).- Rótulo adosado o toldo luminoso o con iluminación, excepto de pantalla electrónica............ 5.00 VECES POR M²\nO FRACCIÓN\nf).- Rótulo pintado no luminoso o con iluminación, por fachada que no exceda de la tercera parte de la superficie. f.1).- Hasta 2.00 M²............ 2.00 VECES f.2).- Mayores de 2.00 M² y hasta\n10.00 M²................. 4.50 VECES f.3).- Mayores de 10.00 M²...... 9.00 VECES\ng).- Rótulo adosado electrónico y/o electromecánico, con o sin movimiento, por cada lado....... 8.75 VECES POR M²\nO FRACCIÓN\nh).- Figura cilíndrica no luminosa o sin iluminación................. 7.50 VECES\ni).- Figura cilíndrica luminosa o con iluminación..................... 10.00 VECES\nj).- Torre directorio................ 43.75 VECES POR\n(excepto de pantalla electrónica) UNIDAD\nk).- Valla publicitaria luminosa o con iluminación hasta 12.50 M².......\n10.00 VECES POR M²\nl).- Valla publicitaria no luminosa o sin iluminación hasta 12.50 M².. 7.50 VECES POR M²\nm).- Miniportacartel direccional..... 11.25 VECES POR\nPIEZA\nn).- Banca publicitaria.............. 18.75 VECES POR\nPIEZA ñ).- Cobertizo publicitario.......... 37.50 VECES POR\nPIEZA\no).- Carro de sonido por tres meses.. 21.25 VECES POR\nUNIDAD\np).- Torreta en techo de automóvil, camión o taxi................... 17.50 VECES POR\nUNIDAD\nq).- Rótulo en vehículo, excepto tipo pantalla electrónica o aquéllos de distintivo fiscal............ 5.00 VECES POR M²\nr).- Rótulo en caseta telefónica, por caseta.......................... 6.25 VECES\ns).- Publicidad en banderolas, estandartes, pendones o caballetes dentro de propiedad privada, por pieza, por tres meses........... 15.00 VECES\nt).- Anuncio en tapial hasta 12.50 M² por pieza....................... 56.25 VECES\nLa revalidación anual a que hace referencia el numeral 2 de este\nApartado se deberá realizar a más tardar en el mes de junio del\nEjercicio Fiscal que corresponda, como se menciona en el Artículo\n76 de la presente Ley. En el caso de que la revalidación sea extemporánea, se cobrará con los recargos que correspondan de acuerdo a lo que establece el Artículo 54 de esta Ley, y la multa que establezca la Ley de Hacienda Municipal del Estado de Baja\nCalifornia.\nLas personas físicas, morales o unidades económicas que presten los servicios de publicidad, así como los propietarios de los bienes inmuebles donde se instalen anuncios y las sucursales de giros comerciales e industriales y de instituciones de crédito, seguros y fianzas serán solidariamente responsables del pago de señalado en el inciso W).\n4.- Licencia nueva con vigencia de 15 días naturales, cuando la instalación se efectuara una vez que sea emitida esta licencia:\na).- Manta o lona en propiedad privada: a.1).- Por cada M² de superficie 4.37 VECES\nb).- Volantes: b.1).- Vigencia por un período de 15 días naturales.... 5.00 VECES b.2).- Vigencia por un período mayor de 15 días naturales............... 10.00 VECES b.3).- Volantes a beneficio de la comunidad............ EXENTO\nc).- Figura inflable, con publicidad y de duración temporal............ 4.37 VECES\nPOR DÍA\nd).- Carteles promocionales en propiedad privada: d.1).- Vigencia hasta por 15 días.................... 5.00 VECES d.2).- Vigencia mayor de 15 días.................... 10.00 VECES d.3).- A beneficio de la comunidad............... EXENTO\ne).- Anuncio ambulante dirigido por personas incluye botargas....... 3.12 VECES\nPOR DÍA\n5.- Revalidación temporal de licencia, al verificarse que aún cumplan los requisitos de reglamento; vigencia de\n15 días naturales:\na).- Manta o lona en propiedad privada, hasta por 3 períodos adicionales: a.1).- Por cada M² de superficie.............. 2.50 VECES\nb).- Figura inflable, con publicidad y de duración temporal......... 3.12 VECES\nPOR DÍA\n6.- Licencia de regularización con vigencia de 15 días naturales, cuando se ha efectuado la instalación o el reparto sin contar con la licencia correspondiente:\na).- Manta o lona en propiedad privada: a.1).- Por cada M² de superficie.............. 5.62 VECES\nb).- Volantes: b.1).- Vigencia por un período de 15 días naturales.... 7.50 VECES b.2).- Vigencia por un período mayor de 15 días naturales............... 12.50 VECES b.3).- De beneficio a la comunidad............... EXENTO\nc).- Figura inflable, con publicidad y de duración temporal......... 5.62 VECES\nPOR DÍA\nd).- Anuncio ambulante dirigido por personas incluye botargas....... 6.25 VECES\nPOR DÍA\n7.- Por verificación y certificación de factibilidad para la instalación y regularización de aparatos de telefonía en la vía pública, existentes y de nueva instalación:\na).- Licencia para la instalación de teléfono público colocado en la vía pública..................... 12.50 VECES POR\nAPARATO\nb).- Regularización de teléfono público colocado en la vía pública......................... 15.00 VECES POR\nAPARATO\nc).- Por revalidación anual.......... 10.00 VECES POR\nAPARATO\n8.- Por retiro de rótulos, anuncios y similares irregulares, exceptuando la propaganda por partidos políticos o entidades de gobierno, se pagará:\na).- Cartelera luminosa o sin iluminación de 50.00 M² en adelante, incluye desmonte y traslado........................ 1,250.20 VECES\nb).- Cartelera y/o rótulo de cualquier tipo, menor de 50.00\nM².............................. 125.20 VECES\nc).- Bancas publicitarias, cobertizos o elementos de equipamiento urbano en general............... 50.20 VECES\nd).- Casetas telefónicas en vía pública......................... 50.20 VECES\ne).- Retiro de lonas en mal estado... 62.70 VECES\nf).- Almacenaje de estructura por día 1.87 VECES\nV.- DEPARTAMENTO DE VIALIDAD Y TRANSPORTE\nX).- Por análisis y emisión de factibilidad de dictámenes técnicos impactan el sector en que se ubiquen; incluye el análisis de densidades, el análisis normativo y el análisis de congruencia parciales y sectoriales de desarrollo urbano en vigor; tales como:\n1.- Por análisis y emisión de factibilidad de dictamen técnico de integración vial a predios de desarrollos habitacionales, desarrollos turísticos, centros comerciales, parques industriales, etc.; incluye la definición de la ruta, la definición del origen y el destino de la vialidad, la definición de la sección de Derecho de vía con base a los volúmenes de tráfico que deberá absorber la vialidad, la definición de los lineamientos viales en los cruces e intersecciones con otras vialidades existentes o propuestas, etc.; se pagará de acuerdo con la longitud del trazo, previo al inicio del trámite.\nIncluye hasta dos revisiones de proyecto.\na).- De propuestas de vialidades ubicadas dentro o fuera de los límites del centro de población: a.1).- Hasta 2,500 ML de longitud................ 28.95 VECES a.2).- Mayor de 2,500 ML y hasta\n5,000 ML de longitud................ 43.95 VECES a.3).- Mayor de 5,000 ML y hasta\n10,000 ML de longitud................ 58.95 VECES a.4).- Mayores de 10,000 ML de longitud................ 102.50 VECES a.5).- Por cada kilómetro fuera del centro de población. 0.14 VECES\n2.- Por análisis y emisión de factibilidad de dictamen técnico de estructura vial en predios de desarrollos habitacionales y parques industriales, incluye la definición de la sección de Derecho de vía con base a los volúmenes de tráfico que deberá absorber la vialidad, la definición de los lineamientos viales en los cruces e intersecciones con otras vialidades existentes o propuestas, etc.; se pagará de acuerdo con la superficie del predio, previo al inicio del trámite.\na).- De predios ubicados dentro o fuera de los límites del centro de población: a.1).- Hasta 10,000 M² de superficie.............. 37.70 VECES a.2).- Mayor de 10,000 M² y hasta 100,000 M² de superficie.............. 42.70 VECES a.3).- Mayor de 100,000 M² y hasta 500,000 M² de superficie.............. 46.45 VECES a.4).- Mayores de 500,000 M² de superficie.............. 51.45 VECES a.5).- Por cada kilómetro fuera del centro de población. 0.14 VECES\n3.- Por análisis y emisión de dictamen técnico de afectación a predios; se pagará de acuerdo con la superficie del predio, previo al inicio del trámite.\na).- De predios ubicados dentro o fuera de los límites del centro de población: a.1).- Hasta 10,000 M² de superficie.............. 18.95 VECES a.2).- Mayor de 10,000 M² y hasta 100,000 M² de superficie.............. 22.70 VECES a.3).- Mayor de 100,000 M² y hasta 500,000 M² de superficie.............. 23.75 VECES a.4).- Mayores de 500,000 M² de superficie.............. 26.45 VECES a.5).- Por cada kilómetro fuera del centro de población............... 0.14 VECES\n4.- Por análisis y/o revisiones subsecuentes de cualquier inciso de los puntos 1, 2 y 3 inmediatos anteriores, se pagará 20% DEL VALOR\nDEL DICTAMEN TÉCNICO.\nAdicionar estos conceptos a los predios de los que se haya solicitado análisis de acción de urbanización para fraccionamientos a través de la fracción N, licencia de construcción, régimen de condominio, opinión o dictamen de uso del suelo o factibilidad de licencia de operación y que por su de densidades, el análisis normativo y el análisis de programas parciales y sectoriales de desarrollo urbano en vigor.\nY).- Por análisis y revisión para la emisión de factibilidad de estructura vial, en predios para edificación o inmuebles para las que colindan; incluye el análisis normativo; y/o análisis por sitios exclusivos de estacionamiento y/o reductores de velocidad, se pagará previo al inicio del trámite, lo siguiente:\n1.- Por análisis y revisión de proyecto para la emisión de factibilidad de dictamen técnico de integración y estructura vial a predios para edificaciones habitacionales, turísticos, comerciales, industriales, etc. y/o para operación comercial, industrial y/o de servicio.\nIncluye hasta dos revisiones.\na).- De predios ubicados dentro o fuera de los límites del centro de población y/o de la mancha urbana: a.1).- Hasta 200 M² de superficie.............. 15.00 VECES a.2).- Mayor de 200 M² y hasta\n600 M² de superficie.... 20.00 VECES a.3).- Mayor de 600 M² y hasta\n1,000 M² de superficie.. 25.00 VECES a.4).- Mayor de 1,000 M² y hasta\n5,000 M² de superficie.............. 30.00 VECES a.5).- Mayores de 5,000 M² de superficie.............. 45.00 VECES\n2.- Por análisis y/o revisiones subsecuentes de cualquier inciso del punto inmediato anterior, se pagará: 20% DEL VALOR\nDEL DICTAMEN TÉCNICO\n3.- Derechos por análisis, revisión e inspección para la emisión y/o baja de factibilidad de ocupación de la vía pública para estacionamiento de vehículos particulares o de transporte público (línea amarilla, línea blanca, línea azul, línea verde y/o línea roja):\na).- Para transporte público......... 15.00 VECES\nb).- Para uso comercial: b.1).- En zona central.......... 8.00 VECES b.2).- Otras zonas.............. 5.00 VECES\nc).- Para línea azul................. 2.50 VECES\nd).- Para baja o cancelación de línea exclusiva....................... 0.00 VECES\n4.- Por análisis, revisión e inspección para la emisión de factibilidad para la colocación de reductores de velocidad (topes) por pieza.\na).- En zona central................. 6.45 VECES\nb).- Otras zonas..................... 3.95 VECES\n5.- Por análisis, revisión e inspección para la emisión de factibilidad para la colocación de señalamiento vial\n(horizontal y/o vertical), por pieza:\na).- Dentro de la mancha urbana...... 3.95 VECES\nb).- Fuera de la mancha urbana....... 5.95 VECES\n6.- Por análisis, revisión e inspección para la emisión de factibilidad para la colocación de diversos dispositivos de control de tránsito, por pieza:\na).- Dentro de la mancha urbana...... 3.95 VECES\nb).- Fuera de la mancha urbana....... 5.95 VECES\nZ).- Por análisis y emisión de factibilidad de dictamen técnico para pagará de acuerdo con la superficie, previo al inicio del trámite.\na).- Por superficies en secciones de banqueta o circulación peatonal: a.1).- Por cada metro o fracción en el primer cuadro de la ciudad........................ 58.75 VECES a.2).- Por cada metro o fracción fuera del primer cuadro de la ciudad........................ 28.75 VECES\nb).- Por superficies en secciones de arroyo o en circulación vehicular: b.1).- Por cada metro o fracción en el primer cuadro de la ciudad........................ 28.75 VECES b.2).- Por cada metro o fracción fuera del primer cuadro de la ciudad........................ 15.00 VECES\nAA).- Por otros servicios que presta la Secretaría de Desarrollo y\nServicios Urbanos, a solicitud del interesado se pagará al momento de efectuar la solicitud correspondiente:\n1.- Por metro lineal de papel o fracción de copia heliográfica simple de planos de la ciudad......................... 15.00 VECES\n2.- Por certificación de copia heliográfica simple de planos de la ciudad............................... 6.45 VECES\n3.- Por constancias y copias certificadas de documentos\nUrbanos.\na).- Por primera hoja................ 1.45 VECES\nb).- Por hoja adicional.............. 0.10 VECES\n3.1).- Por copias simples de documentos emitidos por la\nServicios Urbanos.\na).- Por primera hoja......... 0.15 VECES\nb).- Por hojas subsecuentes... 0.10 VECES\n4.- Por copia de la Ley de Edificaciones del Estado de Baja California o el\nReglamento de Edificaciones, Desarrollo Urbano y Habitabilidad para el Municipio de Playas de Rosarito, Baja California u otras leyes o reglamentos.\na).- Por cada Ley.................... 6.45 VECES\nb).- Por cada Reglamento............. 6.45 VECES\n5.- Por copia de información digitalizada en disco compacto.................... 51.45 VECES\n6.- Por ejemplar del Programa de\nDesarrollo Urbano del Centro de\nPoblación Playas de Rosarito (PDUCP).\na).- Por carpeta del documento técnico completo, incluyendo todos los planos.......................... 125.20 VECES\nb).- Por cuadernillo del documento técnico en versión abreviada, incluyendo todos los planos en reducción....................... 11.45 VECES\nc).- Copia en disco compacto del programa de desarrollo urbano en versión abreviada............... 51.45 VECES\n7.- Por ejemplar de la carta urbana del centro de población de Playas de\nRosarito............................. 22.70 VECES\n8.- Por ejemplar de un Plan o Programa parcial o sectorial del Centro de\nPoblación Playas de Rosarito, de acuerdo con lo que señalan los\nArtículos 56, 65 y 72 de la Ley de\nDesarrollo Urbano del Estado de Baja\nCalifornia.\na).- Por copia en versión digital de documento técnico............... 43.95 VECES\n9.- Por copia simple de información de los planes parciales para el centro de población, de acuerdo con lo que señala el Artículo 56 de la Ley de\nDesarrollo Urbano del Estado de Baja\nCalifornia.\na).- Por copia simple del ejemplar del documento técnico............... 43.95 VECES\nb).- Por copia en disco compacto del centro de población............. 50.20 VECES\n10.- Por plano impreso:\na).- Por metro lineal o fracción de plano de la ciudad.............. 5.00 VECES\nb).- Por metro lineal o fracción de plano de infraestructura........ 5.00 VECES\nc).- Por metro lineal o fracción de plano de equipamiento........... 5.00 VECES\nd).- Por metro lineal o fracción de plano de usos del suelo......... 5.00 VECES\ne).- Por metro lineal o fracción de plano de vialidades............. 5.00 VECES\n11.- Por información de análisis de estadísticas con base a los datos de los AGEB'S del Censo de INEGI en vigor.\na).- Por análisis estadístico de cada subcomponente socioeconómico.... 5.00 VECES\n12.- Por ejemplar del corredor costero\nTijuana-Rosarito-Ensenada (COCOTREN), y sistema vial metropolitano:\na).- Copia en disco compacto de la versión completa................ 43.95 VECES\n13.- Derechos de Registro como Agente\nInmobiliario Municipal Certificado:\na).- Registro inicial................ 25.20 VECES\nb).- Revalidación anual.............. 12.70 VECES\nc).- Baja de padrón.................. 6.45 VECES\nd).- Expedición de gafete............ 2.70 VECES\n14.- Pago de Derechos por el uso del formato estándar del cuadro de datos para planos de Integración Vial, planos de proyectos ejecutivos y de cualquier otro tipo para solicitar licencias u otras autorizaciones en el\nMunicipio de Playas de Rosarito.\na).- Por trámite ingresado........... 3.95 VECES\nAB).- Por los servicios que presta la Oficialía Conciliadora\nCalificadora Municipal, se pagará previo al inicio del trámite:\na).- Recepción para análisis y dictamen de documentos correspondiente, a efecto de excusarse del pago de cuotas, cuando éstas no sean fijadas en asamblea por mayoría de los condominios o se demuestre que resultan excesivas para el fin que se pretende destinar........ 12.70 VECES\nb).- Por registro de libro de actas.. 5.20 VECES\nc).- Por protocolización del acta constitutiva por modificación... 22.70 VECES\nd).- Por protocolización del reglamento interior del condominio por modificación..... 22.70 VECES\ne).- Por registro ante la Oficialía\nConciliadora y Calificadora\nMunicipal del nombramiento del administrador................... 12.70 VECES\nf).- Por curso de cultura condominal. 37.70 VECES\ng).- Por registro ante la Oficialía\nConciliadora y Calificadora\nMunicipal de cambio de administrador................... 12.70 VECES\nh).- Por la función que tenga que desempeñar como fedatario....... 18.95 VECES\ni).- Cursos de capacitación a administradores, miembros del comité de vigilancia o consejo de administración que se impartirá por lo menos una vez al año............................. 37.70 VECES\nj).- Por certificación del acta constitutiva de la asamblea de condominios..................... 25.20 VECES\nk).- Por recepción y análisis del proyecto de reglamento interior del condominio.................. 25.20 VECES\nl).- Por registro ante la Oficialía\nConciliadora y Calificadora\nMunicipal....................... 25.20 VECES\nSecretaría de Desarrollo y Servicios Urbanos dentro de los 60 días hábiles posteriores a la fecha señalada de entrega, el documento será destruido y deberá ser solicitado nuevamente, en su caso.\nCERTIFICADO DE MEJORAMIENTO DE LA IMAGEN URBANA\nARTÍCULO 28.- Es el documento expedido por la Secretaría de Desarrollo y Servicios Urbanos en el que se hace constar el estado físico de un predio urbano baldío; conforme lo define el Reglamento del Catastro\nInmobiliario para el Municipio de Playas de Rosarito, Baja California y con base al Artículo 8 de la presente Ley de Ingresos.\nLos contribuyentes que adquieran el Certificado de Mejoramiento de la\nImagen Urbana de conformidad con las bases para el otorgamiento del mismo, tendrán derecho a los siguientes descuentos en el pago anual del Impuesto Predial.\nA).- Predios Baldíos:\nI.- Los predios baldíos deberán: estar libres de basura, maleza, escombro, cascajo o cualquier otro residuo, desecho o desperdicio............... 20%\nII.- Contar con guarniciones y banquetas en buen estado que permitan el libre tránsito peatonal o con iluminación dentro del inmueble................. 10%\nIII.- Tener en sus colindancias barda, cerco de malla ciclónica, estructura metálica o similar debidamente rigidizados, con elementos estructurales uniformes, libre de grafiti en muros propios o ajenos.............................. 10%\nIV.- Tener cerco similar a lo anterior en sus colindancias.................... 5%\nTOTAL 45%\nB).- Cuando el predio baldío, se localice dentro de las zonas comerciales o industriales, además de lo anterior, deberá contener:\nI.- Si se ubica en esquina, contar con adecuaciones para personas con discapacidad........................ 5%\nII.- Si se usa como bodega al aire libre para cualquier tipo de material, contar con barda de mampostería, concreto o similar al frente y en sus colindancias, pintada y en buen estado.............................. 5%\nIII.- Contar con árboles al frente del predio con espacio de seis metros entre cada uno...................... 5%\nIV.- En caso de contar con anuncios espectaculares, cumplir con lo dispuesto por el Reglamento de\nPublicidad e Imagen para el Municipio de Playas de Rosarito, Baja\nCalifornia, y en su caso por las normas de la Dirección de\nAdministración Urbana............... 5%\nTOTAL 20%\nImagen Urbana:\nI.- Acreditar ser propietario o poseedor de un inmueble urbano que se encuentre baldío.\nII.- Al momento de inscribirse para adquirir el Certificado de\nMejoramiento de la Imagen Urbana, pagar la cuota correspondiente, con base a la siguiente tabla:\nVALOR CATASTRAL COSTO DEL CERTIFICADO\nVECES LA UNIDAD DE MEDIDA Y\nACTUALIZACIÓN VIGENTE\nDE A\n$ 0 $ 37,200 0.51\n37,201 93,000 0.82\n93,001 186,000 2.07\n186,001 279,000 3.32\n279,001 372,000 5.20\n372,001 558,000 7.70\n558,001 744,000 10.20\n744,001 1’116,000 15.20\n1’116,001 1’488,000 18.95\n1’488,001 1’860,000 25.20\n1’860,001 2’232,000 31.45\n2’232,001 2’604,000 36.45\n2’604,001 2’976,000 40.82\n2’976,001 3’348,000 47.07\n3’348,001 3’720,000 53.32\n3’720,001 4’464,000 59.57\n4’464,001 5’208,000 68.95\n5’208,001 5’902,000 81.25\n5’902,001 6’696,000 90.82\n6’696,001 7’440,000 100.20\n7’440,001 8’164,000 109.57\n8’164,001 8’928,000 112.70\n8’928,001 9’672,000 115.72\n9’672,001 10’416,000 118.95\n10’416,001 11’160,000 122.07\nMÁS DE 11’160,001 125.20\nIII.- En caso de haber cumplido dentro del plazo de 6 meses con los requisitos señalados en los incisos “A” y “B” para obtener el estímulo fiscal correspondiente, la Secretaría de Desarrollo y\nServicios Urbanos realizará una inspección otorgando en su caso, el Certificado de Mejoramiento de la Imagen Urbana.\nARTÍCULO 29.- Derechos por servicios que presta el Departamento de\nGestión Ambiental del Ayuntamiento de Playas de Rosarito.\n1.- Por análisis de evaluaciones de impacto ambiental se pagará previo al inicio del trámite:\n1.1.-Por recepción y análisis de manifiesto de impacto ambiental y emisión de licencia ambiental para la realización de obras de urbanización y/o construcción de desarrollos habitacionales, desarrollos turísticos, centros comerciales, parques industriales, giros comerciales de alto impacto, y otros similares:\na).- Hasta 2,500 M² de superficie..... 180.00 VECES\nb).- Mayor de 2,500 M² y hasta 5,000 M² de superficie.................... 220.00 VECES\nc).- Mayor de 5,000 M² y hasta 10,000\nM² de superficie................. 235.00 VECES\nd).- Mayor de 10,000 M² y hasta 100,000\nM² de superficie................. 280.00 VECES\ne).- Mayores de 100,000 M² de superficie....................... 320.00 VECES\n1.2.-Por recepción y análisis de manifiesto de impacto ambiental y emisión de licencia ambiental para la realización de obras de urbanización y/o construcción de plantas de tratamiento, instalaciones que utilicen recursos naturales (gasolineras, gaseras, gasoductos, oleoductos, etc.)\na).- Hasta 200 M² de superficie....... 50.00 VECES\nb).- Mayor de 200 M² y hasta 400 M² de superficie....................... 75.00 VECES\nc).- Mayor de 400 M² y hasta 600 M² de superficie....................... 110.00 VECES\nd).- Mayor de 600 M² y hasta 1,000 M² de superficie.................... 175.00 VECES\ne).- Mayores de 1,000 M² de superficie 210.00 VECES\nf).- Por kilómetro o fracción de gasoductos u oleoductos.......... 150.00 VECES\n2.- Por recepción y análisis de informe preventivo y emisión de licencia ambiental municipal en predios turísticos, comerciales, industriales, habitacionales y similares:\n2.1.-Por recepción y análisis de informe preventivo y emisión de licencia ambiental municipal para la operación de giros comerciales y/o de servicios\n(excepto los giros enlistados en el punto 2.2 inmediato). Se pagará por metro cuadrado de superficie utilizable para la realización de la actividad, previo al inicio del trámite:\na).- Hasta 40 M² de superficie........ 7.00 VECES\nb).- Mayores de 40 M² y hasta 80 M² de superficie....................... 15.00 VECES\nc).- Mayores de 80 M² hasta 100 M² de superficie....................... 18.00 VECES\nd).- Mayores de 100 M² hasta 200 M² de superficie....................... 30.00 VECES\ne).- Mayores de 200 M² hasta 400 M² de superficie....................... 48.00 VECES\nf).- Mayores de 400 M² hasta 600 M² de superficie....................... 65.00 VECES\ng).- Mayores de 600 M² hasta 1,200 M² de superficie.................... 75.00 VECES\nh).- Mayores de 1,200 M² de superficie 100.00 VECES\n2.2.-Por recepción y análisis de informe preventivo y emisión de licencia ambiental municipal para la operación de giros comerciales y/o de servicios, tales como talleres de reparación de vehículos y/o transporte en todas sus modalidades; lavado y/o detallados de autos, vehículos o transporte, venta de alimentos preparados en todas sus modalidades, lavanderías, tortillerías, llanteras, supermercados o herrerías. Se pagará por metro cuadrado de superficie utilizable para la realización de la actividad, previo al inicio del trámite:\na).- Hasta 50 M² de superficie........ 20.00 VECES\nb).- Mayores de 50 M² hasta 100 M² de superficie....................... 30.00 VECES\nc).- Mayores de 100 M² hasta 250 M² de superficie....................... 40.00 VECES\nd).- Mayores de 250 M² hasta 500 M² de superficie....................... 60.00 VECES\ne).- Mayores de 500 M² hasta 1,000 M² de superficie.................... 80.00 VECES\nf).- Mayores de 1,000 M² de superficie....................... 100.00 VECES\n2.3.-Por recepción y análisis de informe preventivo y emisión de licencia ambiental municipal para la realización de obras de construcción o demolición para usos habitacionales, turísticos, comerciales, industriales, especiales, etc. Se pagará por metro cuadrado de construcción, previo al inicio del trámite:\na).- Hasta 100 M² de superficie....... 17.00 VECES\nb).- Mayores de 100 M² y hasta 300 M² de superficie.................... 38.00 VECES\nc).- Mayores de 300 M² y hasta 500 M² de superficie.................... 73.00 VECES\nd).- Mayores de 500 M² y hasta 750 M² de superficie.................... 87.00 VECES\ne).- Mayores de 750 M² y hasta 1,000 M² de superficie.................... 95.00 VECES\nf).- Mayores de 1,000 M² y hasta 1,200\nM² de superficie................. 110.00 VECES\ng).- Para montaje y/o construcción de antenas de telecomunicaciones por pieza............................ 75.00 VECES\n2.4.-Por recepción y análisis de informe preventivo y emisión de licencia ambiental municipal para la realización de obras de urbanización y/o movimientos de tierra en predios habitacionales, turísticos, comerciales, industriales, etc. Se pagará por metro cúbico de volumen, previo al inicio del trámite:\na).- Hasta 100 M3 de volumen........... 30.00 VECES\nb).- Mayores de 100 M3 y hasta 250 M3 de volumen.......................... 45.00 VECES\nc).- Mayores de 250 M3 y hasta 500 M3 de volumen.......................... 65.00 VECES\nd).- Mayores de 500 M3 y hasta 1,000 M3 de volumen....................... 105.00 VECES\ne).- Mayores de 1,000 M3 y hasta 1,200\nM3 de volumen..................... 150.00 VECES\n3.- Por recepción y análisis para el registro anual en el padrón de prestadores de servicios ambientales, se pagará:\na).- Por registro inicial............. 50.00 VECES\nb).- Por revalidación de registro anual............................ 35.00 VECES\n4.- Por recepción y análisis para el registro anual en el padrón de transportadores de residuos sólidos urbanos, no peligrosos, de origen doméstico y/o comercial, se pagará por unidad de transporte:\na).- Por registro inicial............. 75.00 VECES\nb).- Por revalidación de registro anual............................ 48.00 VECES\n5.- Por recepción y análisis para el registro anual en el padrón de transportadores de aguas residuales domésticas y/o comerciales, se pagará por vehículo:\na).- Por registro inicial............. 75.00 VECES\nb).- Por revalidación de registro anual............................ 48.00 VECES\n6.- Por otros conceptos de servicios ecológicos................................. 56.25 VECES\n7.- Por permiso de poda de árbol. Por árbol.... 2.70 VECES\n8.- Dictamen de afectación y permiso de reubicación o tala de árbol o palmera. Por pieza...................................... 5.20 VECES\n9.- Por multas por infracciones al Reglamento en materia de impacto ambiental:\na).- Las contempladas en el Capítulo\nDécimo Segundo del Reglamento de\nProtección al Ambiente del\nMunicipio de Playas de Rosarito,\nB.C.\n10.- Por recepción y análisis para el registro anual en el padrón de comerciantes de neumáticos, se pagará:\na).- Por registro inicial............. 50.00 VECES\nb).- Por revalidación de registro anual............................ 35.00 VECES\nLa revalidación anual a que hacen referencia los incisos b) de los numerales 3, 4, 5 y 10 de este Artículo se deberá realizar a más tardar en el mes de junio del Ejercicio Fiscal que corresponda, como se menciona en el Artículo 76 de la presente Ley. En el caso de que la revalidación sea extemporánea, se cobrará con los recargos que correspondan de acuerdo a lo que establece el Artículo 54 de esta\nLey, y la multa que establezca la Ley de Hacienda Municipal del Estado de Baja California.\nARTÍCULO 30.- Los propietarios de giros comerciales e industriales o actividad que ejerzan, modificar cordón de banqueta, retiro de de ingreso, deberán tener autorización del Departamento de Ingeniería de Tránsito, así como del Departamento de Estacionómetros y pagar los\nDerechos por este concepto, de acuerdo a la siguiente clasificación:\nA).- Por retiro de aparato estacionómetro:\nI).- Aparato sencillo.................... 70.00 VECES\nII).- Aparato doble....................... 88.00 VECES\nB).- Por modificación del cordón de banqueta por metro lineal para rampa de ingreso... 8.95 VECES\n4.- DERECHOS POR EXPEDICIÓN DE PERMISOS POR EL USO U OCUPACIÓN DE LAS\nSEMIFIJOS, ASÍ COMO PERMISOS PROVISIONALES EN PROPIEDAD PRIVADA\nARTÍCULO 31.- Las Licencias o Permisos por el uso u ocupación de las vías públicas por quienes realicen la actividad de comercio ambulante, puestos fijos, semifijos o mercados sobre ruedas y provisionales en propiedad privada serán pagados anualmente por el Ejercicio Fiscal vigente, por los usuarios previo al cumplimiento con el reglamento respectivo vigente, sujetándose a la siguiente:\nACTUALIZACIÓN VIGENTE\nA).- ANUALMENTE\na).- Vendedores ambulantes................ 15.82 VECES\nb).- Puestos fijos........................ 21.97 VECES\nc).- Puestos semifijos.................... 21.97 VECES\nd).- Mercado sobre ruedas d.1).- Puesto que no exceda de 6 M de frente por 4 M de fondo....... 22.70 VECES d.2).- Puesto que no exceda de 9 M de frente por 4 M de fondo....... 28.75 VECES d.3).- Puesto que no exceda de 12 M de frente por 4 M de fondo....... 35.20 VECES\ne).- Aseador de calzado................... 7.70 VECES\nf).- Músicos ambulantes................... 7.70 VECES\ng).- Voceador............................. EXENTO\nh).- Venta de paletas de hielo............ 12.70 VECES\ni).- Dentro de la zona federal marítimo terrestre debido a que atiende a la temporalidad de la actividad, una vez aprobado por la autoridad federal competente........................... 12.70 VECES\nj).- Renta por unidad de cuatrimotos...... 6.45 VECES\nB).- OCUPACIÓN EVENTUAL, TARIFA SEMANAL\nOCUPACIÓN ACCIDENTAL Y EVENTUAL\na).- Vendedores ambulantes................ 1.45 VECES\nb).- Puestos semifijos.................... 2.70 VECES\nc).- Mercado sobre ruedas................. 2.70 VECES\nC).- PROVISIONALES\nOcupación Eventual, Tarifa Mensual.\na).- Vendedores ambulantes................ 7.70 VECES/MES\nb).- Puestos fijos........................ 12.70 VECES/MES\nc).- Puestos semifijos.................... 10.20 VECES/MES\nd).- Mercado sobre ruedas................. 6.45 VECES/MES\ne).- Aseador de calzado................... 2.70 VECES/MES\nf).- Músicos ambulantes................... 2.70 VECES/MES\ng).- Voceador............................. EXENTO máximo.\nD).- DERECHOS POR EXPEDICIÓN O REPOSICIÓN DE\nIDENTIFICACIÓN DE COMERCIANTE AMBULANTE\na).- Expedición de identificación......... 2.70 VECES\nb).- Reposición........................... 3.95 VECES\nc).- Copia certificada.................... 1.45 VECES\nE).- PERMISO PROVISIONAL EN PROPIEDAD PRIVADA\n(SEMANAL)\nI.- Estacionamientos públicos\na).- Hasta 500.00 M²................. 12.70 VECES\nb).- De 500.01 M² a 1,000.00 M²...... 25.20 VECES\nc).- De 1,000.01 M² a 5,000.00 M².... 37.70 VECES\nd).- De 5,000.01 M² en adelante...... 62.70 VECES\nII.- Otras actividades provisionales\n(mensual)........................... 12.70 VECES\nLas personas pensionadas, jubiladas, que acrediten su condición mediante documento expedido por institución pública, así como las personas con discapacidad, o que tengan a su cargo un familiar con alguna discapacidad y residan en el mismo domicilio y además se encuentren registradas como responsables en la credencial oficial con la que se acredite la discapacidad, indigentes, adultas mayores de\n60 años, personas indígenas, viudas mayores de 50 años, mujeres jefas de familia de escasos recursos, personas liberadas por amnistías, y socioeconómico, cubrirán el 50% por concepto de los Derechos a que hace referencia este Artículo.\n5.- DERECHOS POR LOS SERVICIOS QUE PRESTA LA DIRECCIÓN DE CATASTRO\nARTÍCULO 32.- Los servicios que presta la Dirección de Catastro, se pagarán conforme a la siguiente:\nACTUALIZACIÓN VIGENTE\nA).- POR EXPEDICIÓN DE DOCUMENTOS:\na).- Certificación de copias de planos.... 12.70 VECES\nb).- Copia simple de planos por M²........ 6.45 VECES\nc).- Constancia catastral................. 8.95 VECES\nd).- Copia certificada de documentos por primera página....................... 1.45 VECES\ne).- Por hoja adicional................... 0.10 VECES\nf).- Constancia de no registro en el padrón catastral..................... 5.20 VECES\ng).- Copia certificada de deslinde o levantamiento catastral.............. 12.70 VECES\nh).- Constancia de condición de predio.... 15.20 VECES\ni).- Práctica de avalúos para los efectos estipulados en el Artículo 12, fracción XIII de la Ley del Catastro\nInmobiliario del Estado de Baja\nCalifornia.......................... 37.70 VECES\nj).- Dictámenes periciales de apeo y deslinde de bienes raíces solicitados a través de autoridades competentes: j.1).- Dentro de la mancha urbana.... 43.95 VECES j.2).- Fuera de la mancha urbana..... 56.45 VECES\nk).- Certificación de datos............... 10.20 VECES\nl).- Copia simple de documentos por primera página............................... 1.45 VECES\nm).- Por páginas subsecuentes............. 0.12 VECES\nn).- Copia impresa de plano de centro de población............................ 15.20 VECES ñ).- Copia digitalizada de centro de población............................ 25.20 VECES\no).- Inspección y/o Investigación documental de predios por Catastro... 7.70 VECES\np).- Ratificación de contratos por Catastro\nArtículo 2191 del Código Civil para el\nEstado de Baja California............ 21.25 VECES\nq).- Nomenclatura y asignación de números oficiales............................ 5.00 VECES\nPara la obtención de los documentos de los incisos anteriores, con carácter urgente, en tiempos menores de cuarenta y ocho horas se les incrementará un 200% en el pago de los Derechos normales de los mismos.\nB).- POR TRABAJOS TÉCNICOS:\na).- Deslinde de predios:\n1.- En zonas urbanas donde existan ejes físicos correctos y comprobados así como puntos de control:\n1.1).- Para predios con superficie hasta 180 M² pagará................... 50.20 VECES\n1.2).- Para predios con superficie de 180 M² a 300\nM² pagará la cuota del inciso anterior más...................... 0.027 VECES por cada metro cuadrado excedente de 180 M².\n1.3).- Para predios con superficie de 300 M² a 500\nM² pagará la cuota máxima del inciso anterior más...................... 0.023 VECES por cada metro cuadrado excedente de 300 M².\n1.4).- Para predios con superficie de 500 M² a\n1,000 M² pagará la cuota máxima del inciso anterior más...................... 0.02 VECES por cada metro cuadrado excedente de 500 M².\n1.5).- Para predios con superficie de 1,000 M² a\n2,500 M² pagará la cuota máxima del inciso anterior más...................... 0.012 VECES por cada metro cuadrado excedente de 1,000 M².\n1.6).- Para predios con superficie de 2,500 M² a\n5,000 M² pagará la cuota máxima del inciso anterior más...................... 0.007 VECES por cada metro cuadrado excedente de 2,500 M².\n2.- En las zonas urbanas donde no exista la totalidad de ejes físicos y puntos de control definidos, a las cuotas anteriores se les incrementará un\n25%.\n3.- En las zonas urbanas irregulares o carentes de puntos de control y ejes físicos definitivos, se les incrementará un 50% a las cuotas del punto número 1.\n4.- Para predios ubicados fuera de la zona urbana pero dentro del centro de población de las cabeceras municipales, se les aplicará los mismos valores del número anterior.\n5.- A los predios ubicados fuera de la zona urbana además de las cuotas anteriores, se les acumulará 0.22 VECES por cada kilómetro fuera de la ciudad.\n6.- Para terrenos semicerriles o lomeríos, los cuales para efectos fiscales se consideran, aquéllos de pendientes uniformes menores de 30 grados; tendrán las cuotas anteriores un incremento del 40%; los terrenos cerriles considerándose para el efecto aquéllos con cambios bruscos de pendientes mayores de 30 grados tendrán un aumento del 75% a las cuotas establecidas.\nb).- Levantamiento de predios:\n1).- Para predios con superficie hasta\n180 M² pagará................... 7.70 VECES\n2).- Para predios con superficie de\n180 M² a 300 M² pagará la cuota del inciso anterior, más........ 0.021 VECES por cada metro cuadrado excedente de 180 M².\n3).- Para predios con superficie de\n300 M² a 500 M² pagará la cuota máxima del inciso anterior más............................. 0.018 VECES por cada metro cuadrado excedente de 300 M².\n4).- Para predios con superficie de\n500 M² a 1,000 M² pagará la cuota máxima del inciso anterior más............................. 0.025 VECES por cada metro cuadrado excedente de 500 M².\n5).- Para predios con superficie de\n1,000 M² a 2,500 M² pagará la cuota máxima del inciso anterior más............................. 0.007 VECES por cada metro cuadrado excedente de 1,000 M².\n6).- Para predios con superficie de\n2,500 M² a 5,000 M² pagará la cuota máxima del inciso anterior más............................. 0.004 VECES por cada metro cuadrado excedente de 2,500 M².\n7).- Los predios ubicados fuera de la zona urbana además de las cuotas anteriores, se le acumulará 0.24 veces la Unidad de Medida y\nActualización vigente para cada kilómetro fuera de la ciudad.\n8).- Para terrenos semicerriles o lomeríos, los cuales para efectos fiscales se consideran aquéllos de pendientes uniformes menores de 30 grados, tendrán las cuotas anteriores un aumento del 40%; los terrenos cerriles, considerándose para el efecto, aquéllos con cambios bruscos de pendientes mayores de 30 grados, tendrán aumentos de 75% a las cuotas establecidas.\n9).- Para el estudio, cálculo y verificación física de planos para efectos de certificaciones catastrales, se pagará:\n9.1).- Para predios de 5,000 M²\nMAYOR DE: HASTA:\n075-00-00.01 a 100-00-00.00 Has 190.32 VECES\n100-00-00.01 a 250-00-00.00 Has 197.64 VECES\n250-00-00.01 a 500-00-00.00 Has 226.89 VECES\n500-00-00.01 a 1,000-00-00.00 Has 270.76 VECES\n9.2).- Para predios cuya superficie exceda de\n1,000-00-00.01 Has., se pagarán los Derechos de acuerdo al presupuesto que al efecto realice la\nDirección de Catastro\nMunicipal, el que en todo caso será equivalente al costo del servicio y previa solicitud del interesado. o constancia expedida por las autoridades del ramo, se pagarán el 50% de la tarifa anterior.\n10).- Para la obtención del deslinde y levantamiento de predios o para el estudio, cálculo y verificación física de planos para efectos de certificaciones catastrales con carácter de urgente en tiempos menores de lo que requiere el trabajo normal, se les incrementará un 200% en el pago de los Derechos normales del mismo.\n11).- Los predios cuya superficie exceda de 1,000-00-00.00 Has., pagarán los Derechos de levantamiento, de acuerdo al presupuesto que al efecto realice las Oficinas de Catastro\nMunicipal, el que, en todo caso, será equivalente al costo del servicio y previa solicitud del interesado.\n12).- Vértices geodésicos:\n1.- Información por vértice\n(ubicación, coordenadas, descripción)............... 3.95 VECES\n2.- El establecimiento de vértices geodésicos en el\nMunicipio mediante el\nSistema de Posicionamiento por Satélite GPS, estará condicionado al presupuesto que al efecto realice la Dirección de\nCatastro, tomando en cuenta el lugar del establecimiento y características fisiográficas del sitio.\n3.- Liga al Sistema Municipal de\nCoordenadas, mediante equipo GPS, hasta 10 kilómetros fuera de los límites del centro de población.\na).- Por los primeros dos vértices de desarrollo ligados en:\nPlayas de Rosarito.... 62.70 VECES\nb).- Por cada vértice extra ligado (hasta un máximo de 3) en:\nPlayas de Rosarito.... 13.75 VECES\nc).- Certificación de trabajos:\n1.- Certificación de trabajos de deslinde y levantamiento de predios realizados por peritos con registro vigente ante la\nDirección de Catastro........... 9.57 VECES\n1.a.- A partir de la tercera revisión subsecuente...... 1.45 VECES\n2.- Derechos de liga al sistema oficial de coordenadas para efecto de certificación de trabajos predios menores a\n5,000.00 M²..................... 1.45 VECES\n3.- Derechos de liga al sistema oficial de coordenadas para efecto de certificación de trabajos predios mayores a\n5,000.00 M²..................... 6.45 VECES\n4.- El estudio, cálculo y verificación de planos y trabajos para efecto de certificación, se pagará por adelantado. En caso de no llevarse a cabo la certificación se hará la devolución del 40% del pago solamente.\nC).- OTROS SERVICIOS: la Dirección de Catastro Municipal, el que en todo caso es proporcional al costo del servicio y en su caso, a la contraprestación en especie al que esté obligado el usuario del servicio.\nD).- DERECHOS DE REGISTRO COMO PERITO\nDESLINDADOR:\n1.- Registro inicial (alta).............. 37.70 VECES\n2.- Revalidación anual................... 22.70 VECES\nLa revalidación anual a que hace referencia el numeral 2 de este\nApartado se deberá realizar a más tardar en el mes de febrero del Ejercicio Fiscal que corresponda, como lo establece la fracción V del Artículo 72 del Reglamento del Catastro\nInmobiliario para el Municipio de Playas de Rosarito, Baja\nCalifornia. En el caso de que la revalidación sea extemporánea, se cobrará con los recargos que correspondan de acuerdo a lo que establece el Artículo 54 de esta Ley, y la multa que establezca la Ley de Hacienda Municipal del Estado de Baja California.\nE).- POR ACTUALIZACIÓN Y MODIFICACIÓN DE LA BASE\nDE DATOS POR TERRENO A PETICIÓN DEL\nCONTRIBUYENTE:\n1.- Por solicitud de cambios, rectificaciones, y cualquier servicio solicitado por el contribuyente previo al trámite, con excepción de los señalados en los numerales 2 y 3. 7.00 VECES\n2.- Por el registro inicial de un predio con o sin antecedentes............... 8.00 VECES\n3.- Por cambio o modificación de nombre.. 6.00 VECES\nF).- POR ACCESO A LA PLATAFORMA CARTOGRÁFICA Y ARCHIVO DIGITAL DEL\nCATASTRO VÍA INTERNET:\n1.- Por acceso a la plataforma cartográfica y archivo digital vía internet, anual...................... 25.00 VECES deslindadores con registro municipal vigente, previa solicitud por escrito, en los términos que establezcan los formatos oficiales para tal efecto.\n6.- DERECHOS POR LOS SERVICIOS QUE PRESTA LA SECRETARÍA DE\nMOVILIDAD Y TRANSPORTE\nARTÍCULO 33.- Los servicios que presta la Secretaría de Movilidad y\nTransporte, se pagarán conforme a lo siguiente:\n1.- Por otros servicios que presta la Secretaría de Movilidad y\nTransporte, se pagará conforme a la siguiente:\nACTUALIZACIÓN VIGENTE\na).- Expedición de copias certificadas de documentos........................... 1.45 VECES\nb).- Expedición de Opinión Técnica para\nAutorización de Cierres de Circuitos, Sitios o Zonas de Ascenso y Descenso, a petición de parte.................. 35.00 VECES\nc).- Por habilitación o rehabilitación de\nCierres de Circuitos, Sitios o Zonas de Ascenso y Descenso................ 35.00 VECES\nd).- Por servicios de vigilancia de transporte de carga mediante escolta de un inspector y una unidad, por traslado dentro del Municipio........ 20.00 VECES\ne).- Expedición de permiso para instalación de publicidad en unidades de transporte colectivo. Por unidad..... 8.00 VECES\nf).- Expedición de Predictamen previo a la autorización de permisos y concesiones del servicio público................. 40.00 VECES\ng).- Otros servicios que presta la\nSecretaría de Movilidad y Transporte, causarán Derechos, los cuales se cobrarán de conformidad con los presupuestos que al efecto se realicen por esta dependencia, los que en todo caso serán proporcionales al costo del servicio.\n7.- DERECHOS POR ARRASTRE DE VEHÍCULOS\nARTÍCULO 34.- Los Derechos por arrastre de vehículos se cobrarán por una sola vez desde el lugar del levantamiento hasta su destino final, debiendo cubrirse siempre y cuando la maniobra se realice, de acuerdo con la siguiente:\nACTUALIZACIÓN VIGENTE\n1.- Automóvil tipo sedán.................. 12.00 VECES\n2.- Camioneta tipo vagoneta, pick up menos de una tonelada....................... 21.00 VECES\n3.- Auto-tractores solos o con remolques, camiones de pasajeros o personal, carga general. 1 Tonelada o más............. 35.00 VECES\n4.- Motocicletas, bicicletas, remolques, lanchas, sky acuático y otros......... 8.00 VECES\n5.- Por maniobras de arrastre. Por cada una. (Siempre y cuando el vehículo remolcado se ubique en barrancas o lugares que dificulten su remolque)... 1.00 VEZ\n6.- Por maniobras especiales, de salvamento o volcaduras:\na).- Después de transcurrido el tiempo inicial de 15 minutos, se cobrará el tiempo adicional proporcional al tiempo de maniobra realizada.. 5.00 VECES\nPOR HORA\nb).- Cuando el vehículo que se va a remolcar no cuente con llantas y/o se encuentre imposibilitado de rodar, utilizándose el dolly, así como en el desatorado de frenos de aire en tractocamiones, volcaduras, por salidas de carretera, utilización en dos o más ocasiones por el equipo de arrastre......................... 5.00 VECES\nPOR HORA\n7.- Maniobras inconclusas de grúa, por el evento de presentarse el vehículo grúa al lugar donde exista violación a lo reglamentado, con infracción por escrito, pero no se realice el servicio de remolque por causas no imputables al servicio de grúa, se pagarán por vehículo las cuotas siguientes:\na).- Automóvil tipo sedán............. 3.50 VECES\nb).- Camioneta tipo vagoneta, pick up menos de una tonelada............ 6.00 VECES\nc).- Auto-tractores solos o con remolques, camiones de pasajeros o personal, carga general. 1\nTonelada o más................... 12.00 VECES\nd).- Motocicletas, bicicletas, remolques, lanchas, sky acuático y otros............................ 3.50 VECES\nTratándose de vehículos robados que ingresen al Depósito Municipal, previa comprobación con documentos oficiales de autoridad competente, se exentará del pago de los Derechos por arrastre de vehículos.\n8.- DERECHOS POR ALMACENAJE DE VEHÍCULOS\nARTÍCULO 35.- Los Derechos por almacenaje de vehículos en predios propiedad del Municipio o ajenos causarán una cuota diaria de:\nACTUALIZACIÓN VIGENTE\na).- Automóvil tipo sedán...................... 1.25 VECES\nb).- Camioneta tipo vagoneta, pick up menos de una tonelada.............................. 1.25 VECES\nc).- Auto-tractores solos con remolques, camiones de pasajeros o personal, carga general. 1 Tonelada o más................. 2.00 VECES\nd).- Motocicletas, bicicletas, remolques, lanchas, sky acuático y otros............. 1.25 VECES\nTratándose de vehículos robados que ingresen al Depósito Municipal, previa comprobación con documentos oficiales de autoridad competente, se exentará del pago de los Derechos por almacenaje de vehículos.\n9.- DERECHOS POR OCUPACIÓN DE LA VÍA PÚBLICA POR ESTACIONAMIENTO\nDE VEHÍCULOS\nARTÍCULO 36.- Los propietarios de giros comerciales o industriales o actividad que ejerza, ocupar sitios exclusivos de estacionamiento de vehículos y otros, deberán obtener autorización escrita de la\nPresidencia Municipal, debiendo pagar mensualmente los Derechos por este concepto de acuerdo a la siguiente clasificación:\nA.- PARA ESTACIONAMIENTO DE VEHÍCULOS:\nACTUALIZACIÓN VIGENTE\nI.- Por sitios exclusivos de estacionamiento de vehículos con señalamiento en los cordones de las banquetas DIARIAMENTE por metro lineal.\na).- Zona central de................. 0.04 VECES\nb).- Otras zonas de.................. 0.04 VECES\nc).- Para transporte público sin itinerario fijo................. 0.04 VECES\nII.- Por sitios exclusivos de estacionamiento de vehículos en batería cuando tenga un ángulo menor a 45 grados con relación al cordón de banqueta, DIARIAMENTE por metro lineal:\na).- Zona central.................... 0.04 VECES\nb).- Otras zonas..................... 0.04 VECES\nc).- Para transporte público sin itinerario fijo................. 0.04 VECES\nIII.- Por sitios exclusivos de estacionamiento de vehículos en batería cuando tenga un ángulo mayor a 45 grados con relación al cordón de banqueta, DIARIAMENTE por metro lineal:\na).- Zona central................... 0.04 VECES\nb).- Otras zonas.................... 0.04 VECES\nc).- Para transporte público sin itinerario fijo................. 0.04 VECES\nTratándose de los supuestos previstos en las Fracciones I, II y III de este Artículo, la solicitud y autorización de línea amarilla estará autorizados por el Ayuntamiento.\nACTUALIZACIÓN VIGENTE\nB.- POR OCUPACIÓN TEMPORAL DE LA VÍA PÚBLICA:\nI.- Con cobertizos o casetas en paradas de transporte público................... 3.95 VECES, POR AÑO\nII.- Con bancas publicitarias............. 3.75 VECES POR METRO\nLINEAL, POR AÑO\nC.- POR SEÑALAMIENTOS Y PINTURAS:\nI.- Señalamientos........................ 22.70 VECES, POR AÑO\nII.- Pintura.............................. 15.20 VECES, POR AÑO\nD.- POR RETIRO DE APARATO ESTACIONÓMETRO:\nI.- Aparato sencillo..................... 22.70 VECES, POR AÑO\nII.- Aparato doble........................ 28.95 VECES, POR AÑO\nE.- Derechos por análisis, revisión e inspección para la emisión de factibilidad de ocupación de la vía pública para estacionamiento de vehículos (línea amarilla, línea blanca, línea azul, línea verde y/o línea roja):\na).- Para transporte público.............. 18.95 VECES\nb).- Para uso comercial: b.1).- En zona central............... 10.20 VECES b.2).- Otras zonas................... 5.20 VECES\nF.- POR RAMPAS DE ACCESO: Por cada metro lineal que exceda los seis metros de largo....... 2.50 VECES, POR AÑO\nARTÍCULO 37.- Los propietarios de vehículos que se estacionen en las zonas de la vía pública, cuyo uso del espacio para estacionamiento, esté tarifado por cualquier método, pagarán las siguientes tarifas:\nLas personas con discapacidad como neuromotoras, auditivas, visuales e intelectuales, que sean los propietarios de vehículos que se estacionen en las zonas de vía pública, quedarán exentos de todo pago correspondiente.\na).- Zona Puerto Nuevo (área comercial y restaurantera), zona del Blvd. Benito\nJuárez y calles adyacentes (del Puente\nRene’s a la Colonia Echeverría), pagarán por cada hora $3.00 M.N., o su equivalente en tiempo fraccionado.\nb).- Otras zonas de esta ciudad, distintas al inciso a) del presente Artículo, pagarán\n$8.00 M.N., o su equivalente en tiempo fraccionado.\nc).- Por infracciones a este Artículo, se causará una multa de 4.00 veces la Unidad de Medida y Actualización vigente; si se liquida dentro de los quince días siguientes de haberse causado la infracción, gozará de un 50% de descuento.\nd).- Se colocará al vehículo estacionado en las zonas, cuyo uso del espacio para estacionamiento está tarifado por cualquier método, un mecanismo inmovilizador cuando el usuario incurra en la infracción de acuerdo al presente Artículo o reglamento respectivo, lo cual para el retiro de dicho mecanismo, pagarán el equivalente de 4.00 veces la Unidad de Medida y Actualización vigente.\n10.- DERECHOS POR LA EXPEDICIÓN DE CERTIFICADOS, TÍTULOS,\nARTÍCULO 38.- Los certificados, copias certificadas, legalización de oficinas municipales, dentro del ámbito de su competencia se pagarán de acuerdo a la siguiente:\nACTUALIZACIÓN VIGENTE\na).- Certificados de Libertad de Gravámenes\nFiscales, Certificados de No Adeudo, Certificados de Datos, Constancias\nCatastrales, Constancias de No Adeudo.\n1.- Servicios ordinarios................. 2.70 VECES\n2.- Servicios urgentes (en menos de 48 horas)............................... 7.70 VECES a.1).- Certificado de libertad de gravámenes fiscales (urgentes menos de 48 horas)............ 7.70 VECES a.2).- Certificado de libertad de gravámenes fiscales ordinarios 5.20 VECES a.3).- Certificado de no adeudo en rezago........................ 0.00 VECES\nb).- Copias certificadas de documentos......... 1.45 VECES\nc).- Copias adicionales por certificación de expediente................................ 0.15 VECES\nd).- Certificados de Residencia, Constancias de\nArraigo, Constancia de Antecedentes\nJurídicos, Carta de Antecedentes Penales y legalización de firmas ordinarias......... 3.50 VECES\ne).- Certificados de Residencia, Constancias de\nArraigo, Constancia de Antecedentes\nJurídicos, Carta de Antecedentes Penales y legalización de firmas urgentes........... 7.00 VECES\nf).- Certificados de alineamiento con documentación de oficina.................. 2.70 VECES\ng).- Certificados de alineamiento con inspección técnica........................ 7.70 VECES\nh).- Certificados de número oficial............ 2.70 VECES\ni).- Certificados de obras públicas............ 5.20 VECES\nj).- Certificados de peritaje de tránsito municipal, a solicitud del interesado..... 5.20 VECES\nk).- Copias simples de documentos, por hoja.... 0.15 VECES\nl).- Documento de identificación para estacionamiento en lugares exclusivos de discapacitados............................ 1.45 VECES\nm).- Por la revisión de avalúos fiscales....... 6.00 VECES\nn).- Por ratificación de firmas por el\nSecretario del Ayuntamiento............... 7.70 VECES ñ).- Por registro o revalidación anual de permisos de comercio establecido.......... 3.50 VECES\no).- Por registro inicial y revalidación anual de permisos de yonkes y recicladoras de metales en términos del reglamento........ 25.20 VECES\np).- Expedición de bases de licitación de obras y servicios públicos...................... 50.20 VECES\nq).- Expedición de bases de licitación de adquisición de bienes para el Ayuntamiento 25.20 VECES\nr).- Expedición de bases de licitación de adquisición de arrendamientos y servicios para el Ayuntamiento...................... 12.70 VECES\ns).- Por registro inicial y revalidación anual de proveedores del Ayuntamiento........... 6.45 VECES\nt).- Expedición de carta de trabajo cuando no subsista relación laboral con el interesado o solicitante............................. 2.70 VECES\nu).- Reposición de gafete a empleados.......... 1.45 VECES\nv).- Copias simples o certificadas que soliciten los funcionarios y ex funcionarios de la administración pública municipal y paramunicipales, requeridas para la solventación de cuentas públicas.......... EXENTO\nw).- Por cambio de propietario, cambio de denominación o cualquier otro cambio en el registro de comercio establecido, excepto los avisos de clausura definitiva o temporal: w.1).- Comercio menor de 50 M²............ 5.00 VECES w.2).- Comercio de 51 a 200 M²............ 15.00 VECES w.3).- Comercio mayor de 200 M²........... 30.00 VECES\nx).- Registro de comercio de bajo riesgo menores a 50 M², sin uso de gas ni combustibles\n(miscelánea, bazar de saldos, estética, barbería, peluquería, video, cerrajería, florería, joyería, frutería, agencia de viajes, librería, expendio de pan, venta de teléfonos celulares y accesorios, novedades y regalos, juguetería, papelería, sastrería y costuras, zapatería, abarrotes sin venta de cerveza, paletería y nevería, dulcería, galería de arte, escritorio público, reparación de calzado, venta de CD, artículos deportivos, artículos de decoración, oficinas administrativas, importación, fuente de sodas, café internet, cafetería, waflería, crepería, churrería, despacho contable, óptica, academias, arrendamiento de inmuebles, casas de cambio, electrónicas, despacho jurídico, auto eléctrico, venta de tamales y cocos, estudios de fotografía, venta de gelatinas y pasteles, venta de perfumes, artículos naturistas, venta de productos desechables, tacos varios, elaboración de piñatas, boutique, venta y renta de ropa, llenado de agua purificada, compra y venta de computadoras).......................... 28.95 VECES\ny).- Derechos por registro y revalidación anual de Peritos Valuadores ante la Recaudación de Rentas Municipal: y.1).- Registro inicial (alta)............ 37.70 VECES y.2).- Revalidación anual................. 22.70 VECES\nLos proveedores del Ayuntamiento a que hace referencia el inciso s) del presente Artículo, deberán realizar su revalidación anual a más tardar en el mes de marzo del Ejercicio Fiscal que corresponda.\nLos permisos de operación de bajo riesgo de los que se hace mención en el inciso x) del presente Artículo, deberá de presentar para tal efecto de registro, copia del recibo del Impuesto Predial pagado del año corriente, copia de identificación del propietario, croquis de ubicación del negocio, fotografía del local comercial (interior y exterior), pago de inspección de bomberos y deberán realizar su\nFiscal que corresponda, como se menciona en el Artículo 76 de la presente Ley.\nLa revalidación anual a que hace referencia el inciso y) de este\nEjercicio Fiscal que corresponda, como se menciona en el Artículo 76 de la presente Ley. En el caso de que la revalidación sea extemporánea, se cobrará con los recargos que correspondan de acuerdo a lo que establece el Artículo 54 de esta Ley, y la multa que establezca la Ley de Hacienda Municipal del Estado de Baja California.\n11.- DERECHOS POR RECOLECCIÓN DE BASURA\nARTÍCULO 39.- Los Derechos por los servicios de recolección de basura en recipientes comunales o que tengan carácter extraordinario, que preste el Ayuntamiento a giros comerciales, industriales o de servicio, serán fijados en cada caso por la autoridad municipal, dependiendo de la ubicación, de la superficie y topografía del terreno, periodicidad de servicio y otros elementos que impacten en el costo del mismo.\nEstán exentos los particulares que en forma esporádica y por sus propios medios depositen desechos de su propiedad en el relleno sanitario municipal.\nEl costo por recolección de basura para giros comerciales, industriales o de servicio, será de acuerdo al costo siguiente:\nTABULADOR\nCOSTO POR GIRO\nUNIDAD DE MEDIDA Y\nACTUALIZACIÓN VIGENTE\nGIRO TARIFA ANUAL\n1.- Abarrotes, misceláneas, panaderías, pastelerías, paleterías, papelerías, vidrierías, comisionistas, café Internet, curiosidades y artesanías, dulcerías, decoraciones, puestos de dulces, equipos de comunicación, gimnasios, imprentas, videos, zapaterías, venta de artículos de belleza, venta de artículos para el hogar, regalos y novedades, venta de artículos para fiestas, talabarterías, tapicerías, televisión por cable, estéticas, salas de belleza, barberías y peluquerías, laboratorios, farmacias, renta de tuxedos, seguridad y protección, rayos X, ultrasonidos, reparación de calzado, retacerías, rotulistas, sastrerías: a.- Con superficie menor a 20 M².......... 3.95 VECES b.- Con superficie de 21 a 60 M².......... 5.20 VECES c.- Con superficie de 61 a 100 M²......... 6.45 VECES d.- Con superficie mayor a 100 M²......... 9.57 VECES\n2.- Artículos deportivos, centros de copiado, tiendas de ropa, librerías, casas de cambio, boutiques, venta de agua purificada\n(llenado de garrafón), casetas telefónicas, cerrajerías, bolerías, diseño gráfico, venta de celulares, centros cambiarios, fotografías, venta de discos y casetes, casas de empeño, venta de revistas, editoriales, artesanías de vidrio, alfarerías, perfumerías, telecomunicaciones, mueblerías, joyerías, jugueterías, modistas, venta de hielo, venta de pañales, venta de productos de limpieza, venta de video juegos comerciales, fumigadoras, botánicas: a.- Con superficie menor a 20 M².......... 3.95 VECES b.- Con superficie de 21 a 60 M².......... 3.95 VECES c.- Con superficie de 61 a 100 M²......... 5.20 VECES d.- Con superficie mayor a 100 M²......... 6.45 VECES\n3.- Despachos profesionales, oficinas administrativas, agencias aduanales, agencias de bienes raíces, agencias de mudanzas, agencias de publicidad, agencias de seguros y fianzas, agencias de viajes, bufetes jurídicos, notarías y escritorios públicos, limpiadurías: a.- Con superficie menor a 20 M².......... 5.20 VECES b.- Con superficie de 21 a 60 M².......... 6.45 VECES c.- Con superficie de 61 a 100 M²......... 9.57 VECES d.- Con superficie mayor a 100 M²......... 12.70 VECES\n4.- Academias particulares, escuelas, centros educativos, edificios educativos, colegios particulares, guarderías y jardines de niños particulares: a.- Hasta 6 aulas......................... 12.70 VECES b.- Mayor de 6 aulas...................... 25.20 VECES\n5.- Estacionamientos públicos, guarderías, jardines de niños particulares: a.- Con superficie menor a 60 M².......... 12.70 VECES b.- Con superficie de 61 a 100 M²......... 18.95 VECES c.- Con superficie mayor a 100 M²......... 25.20 VECES\n6.- Lavanderías (lavamáticas), graneros, clínicas veterinarias, autolavados, avícolas, acuarios, forrajearías, tiendas de artículos de segunda y establos: a.- Con superficie menor a 20 M².......... 6.45 VECES b.- Con superficie de 21 a 60 M².......... 9.57 VECES c.- Con superficie de 61 a 100 M²......... 15.82 VECES d.- Con superficie mayor a 100 M²......... 18.95 VECES\n7.- Consultorios médicos, consultorios dentales, clínicas y sanatorios, centros de reducción de peso, nutriólogos, centros de rehabilitación y ópticas: a.- Con superficie menor a 60 M².......... 6.45 VECES b.- Con superficie de 61 a 100 M²......... 12.70 VECES c.- Con superficie mayor a 100 M²......... 18.95 VECES\n8.- Centros de espectáculos, centros recreativos, centros vacacionales, cinemas, discotecas y salones de baile\n(fiestas y espectáculos).................. 41.45 VECES\n9.- Talleres: reparación de bicicletas, reparación de tv y radio, industriales, autoeléctricos, carrocería y pinturas, equipos de oficina, de mofles, de soldadura, mecánicos, para tornear, de servicios automotriz y autoservicios, llanteras, reconstructoras automotriz, servicio de lavado y engrasado, reparación de lavadoras, secadoras, estufas, herrerías, reparación de todo tipo en general y maquinados industriales: a.- Con superficie menor a 20 M².......... 6.45 VECES b.- Con superficie de 21 a 60 M².......... 9.57 VECES c.- Con superficie de 61 a 100 M²......... 15.82 VECES d.- Con superficie mayor a 100 M²......... 20.82 VECES\n10.- Moteles con ocupación hasta de 10 habitaciones.............................. 31.45 VECES\n11.- Moteles con ocupación mayor a 10 habitaciones.............................. 41.45 VECES\n12.- Hoteles con ocupación hasta 30 habitaciones.............................. 41.45 VECES\n13.- Hoteles con ocupación mayor a 30 habitaciones.............................. 56.45 VECES\n14.- Agencias automotriz, arrendadoras de equipo de construcción, compra venta de maquinaria industrial, constructoras, renta de autos, lotes de autos usados, renta de maquinaria, renta y venta de casas móviles, venta de equipos diversos y venta de acumuladores: a.- Con superficie menor a 20 M².......... 12.70 VECES b.- Con superficie de 21 a 60 M².......... 18.95 VECES c.- Con superficie de 61 a 100 M²......... 31.45 VECES d.- Con superficie mayor a 100 M²......... 41.45 VECES\n15.- Restaurantes, loncherías, torterías, taquerías, rosticerías, cafeterías, menuderías y pizzerías: a.- Con superficie menor a 20 M².......... 12.70 VECES b.- Con superficie de 21 a 60 M².......... 18.95 VECES c.- Con superficie de 61 a 100 M²......... 25.20 VECES d.- Con superficie mayor a 100 M²......... 31.45 VECES\n16.- Restaurantes bar, bares, cantinas, billares, pescaderías, venta de mariscos preparados y centros de apuestas y sorteos: a.- Con superficie hasta 60 M²............ 25.20 VECES b.- Con superficie de 61 a 100 M²......... 31.45 VECES c.- Con superficie mayor a 100 M²......... 41.45 VECES\n17.- Fábricas de cerveza, fábricas de dulces, mueblerías, fábricas de productos alimenticios, fábricas de productos metálicos, marmolerías, fábricas de cartón, fábricas de conservas, fábricas de concreto, fábricas de helados, carpinterías, fábricas de muebles, fábricas de productos de barro y cerámica, fábricas de textiles, fábricas de ropa, fábricas de varios productos, fundiciones, fábricas de ladrillos, blocks y mosaicos: a.- Con superficie menor a 20 M².......... 18.95 VECES b.- Con superficie de 21 a 60 M².......... 25.20 VECES c.- Con superficie de 61 a 100 M²......... 41.45 VECES d.- Con superficie mayor a 100 M²......... 56.45 VECES\n18.- Maquilas de: aparatos electrónicos y eléctricos, artículos de piel, componentes electrónicos, productos de limpieza, muebles, plásticos, productos alimenticios, productos de vidrio, productos metálicos, productos de madera, productos textiles, productos de barro y cerámica y productos en general........... 62.70 VECES\n19.- Materiales para la construcción, materiales pétreos, pinturas y barnices, plomería y electricidad, transportistas, bodegas, depósitos y almacén, ferreterías, refaccionarias, refacciones para aparatos domésticos, refacciones para maquinaria pesada, venta de aceites y lubricantes, madererías, servicios de transporte urbano, grúas (servicio de arrastre de vehículos) y transportes foráneos: a.- Con superficie menor a 20 M².......... 12.70 VECES b.- Con superficie de 21 a 60 M².......... 18.95 VECES c.- Con superficie de 61 a 100 M²......... 31.45 VECES d.- Con superficie mayor a 100 M²......... 41.45 VECES\n20.- Tiendas de autoservicio, carnicerías, centros de abasto, distribución y venta de alimentos preparados, comercializadoras, tortillerías, fruterías y verdulerías, licorerías, mercados, supermercados, productos lácteos, expendios de cervezas, funerarias, fumigadoras, gases industriales, gasolineras, recicladoras de basura, yonkes, recolectoras de basura, electrónicos y compraventa de componentes, distribuidoras, distribuidoras de gas doméstico, empacadoras, envasadoras y embotelladoras, florerías, mensajerías y recicladoras: a.- Con superficie menor a 20 M².......... 12.70 VECES b.- Con superficie de 21 a 60 M².......... 18.95 VECES c.- Con superficie de 61 a 100 M²......... 31.45 VECES d.- Con superficie mayor a 100 M²......... 41.45 VECES\n21.- Iglesias e instituciones no lucrativas: a.- Con superficie de 61 a 100 M²......... 6.45 VECES b.- Con superficie mayor a 100 M²......... 41.45 VECES\n22.- Instituciones bancarias, institutos de comunicación y comercio, radiodifusoras: a.- Con superficie menor a 20 M².......... 10.20 VECES b.- Con superficie de 21 a 60 M².......... 12.70 VECES c.- Con superficie de 61 a 100 M²......... 18.95 VECES d.- Con superficie mayor a 100 M²......... 31.45 VECES\n23.- Servicios de instalaciones eléctricas, servicentros, servicios de limpieza, servicios de teléfono, servicios administrativos, servicios de aire acondicionado, servicios de informática, servicios de ingeniería y arquitectura, servicios de plomería y servicios en general: a.- Con superficie menor a 20 M².......... 10.20 VECES b.- Con superficie de 21 a 60 M².......... 12.70 VECES c.- Con superficie de 61 a 100 M²......... 18.95 VECES d.- Con superficie mayor a 100 M²......... 25.20 VECES en el mes de enero serán acreedores a un descuento del 10%, en el mes de febrero del 7% y en el mes de marzo del 5%. pagos a más tardar en el mes de junio, o bien a partir del mes en que inicie el servicio.\nLos giros comerciales no enunciados en el tabulador anterior corresponderá el pago de acuerdo a la tarifa de giros similares.\n12.- DERECHOS POR SERVICIO DE LIMPIA\nARTÍCULO 40.- Los Derechos por servicios de limpia fuera del programa normal que otorgue el municipio, en domicilios particulares, terrenos baldíos, unidades habitacionales y otros, serán fijados en cada caso por la autoridad municipal, dependiendo de la ubicación, superficie y otros elementos que impacten en el costo del mismo. Debiéndose pagar los Derechos correspondientes de acuerdo a la siguiente:\nACTUALIZACIÓN VIGENTE\na).- Limpieza y deshierbe con medios mecánicos (M²)....................... 0.81 VECES\nb).- Limpieza y deshierbe con medios manuales (M²)........................ 0.62 VECES\nc).- Carga y retiro de material producto de la limpieza (basura pesada, escombro, ramas, otros) a un kilómetro (M³).... 10.20 VECES\nd).- Acarreo a km subsecuentes (M³/Km).... 0.31 VECES\ne).- Demolición con medios mecánicos de estructuras (madera, concreto, bloque, otros) carga y acarreo a un kilómetro\n(M³)................................. 16.45 VECES\nf).- Recolección de basura (Ton).......... 9.70 VECES\n13.- DERECHOS POR SERVICIOS DE VIGILANCIA POLICÍACA\nARTÍCULO 41.- Los Derechos por el servicio de vigilancia policíaca que preste el Ayuntamiento a domicilios particulares, giros comerciales e instituciones de servicio u otros que soliciten, así como por servicios de escolta policíaca, se pagarán de acuerdo a la siguiente:\nACTUALIZACIÓN VIGENTE\nA).- SERVICIOS DE VIGILANCIA POLICÍACA EN PUNTOS\nFIJOS\n1).- Por agente comercial armado, por turno de 8 horas, quincenalmente........... 8.95 VECES\n2).- Por vigilancia comunitaria en zonas habitacionales (contratadas por asociaciones) por cada elemento, por turno de 8 horas, quincenalmente previo pago.......................... 7.07 VECES\n3).- Por vigilancia a instituciones gubernamentales, por cada elemento, por turno de 8 horas, quincenalmente. 8.95 VECES\nB).- SERVICIOS EXTRAORDINARIOS Y DE ESCOLTA\nPOLICÍACA\n1).- Escoltas a funerales, por elemento, por servicio, por turno de 6 horas previo pago.......................... 10.20 VECES\n2).- Escolta policíaca para servicios particulares, por elemento, por turno de 8 horas previo pago............... 16.45 VECES\n3).- Otros servicios, por cada elemento, por turno de 6 horas previo pago..... 12.20 VECES\nC).- POR LA RENTA DE EQUIPAMIENTO ADICIONAL\n1).- Por la renta de unidad patrulla con un elemento armado por turno de 8 horas. 25.20 VECES\nD).- DERECHOS POR BÚSQUEDA JUDICIALES O\nADMINISTRATIVAS\n1).- Búsqueda o localización de personas y/o domicilios a solicitud de autoridades judiciales y/o administrativas...................... EXENTO\nTodo servicio por más de 90 días deberá contar con un convenio o contrato suscrito.\n14.- DERECHOS POR RECEPCIÓN, ANÁLISIS Y REVISIÓN DE SOLICITUDES, DE\nEMISIÓN DE DOCUMENTOS, PERMISOS Y CERTIFICADOS REFERENTES A\nINSTALACIONES PARA LA VENTA, ALMACENAJE O CONSUMO DE BEBIDAS CON\nGRADUACIÓN ALCOHÓLICA, CAMBIO DE GIRO, CAMBIO DE PERMISIONARIO,\nCAMBIO DE DOMICILIO, CAMBIO DE DENOMINACIÓN COMERCIAL Y\nTRAMITACIÓN RELATIVA A LA OPERACIÓN DE GIROS DE CERVEZA, VINOS,\nLICORES, ALCOHOLES Y SIMILARES\nARTÍCULO 42.- Por la recepción, análisis y revisión de solicitudes de permisos nuevos para la operación de establecimientos con venta, almacenaje o consumo de bebidas alcohólicas o alcohol, cambio de giro, cambio de permisionario, cambio de nombre o denominación y cambio de domicilio, así como la emisión de permisos y certificados que por dichos conceptos y similares extienda el H. Ayuntamiento, estarán sujetos a la siguiente tarifa:\n1.- Emisión de estudio de impacto social, autorizaciones y opinión técnica, se pagará de acuerdo a la siguiente tarifa:\nUNIDAD DE MEDIDA Y\nACTUALIZACIÓN VIGENTE\n1.1).- Estudio de impacto social.\na).- En envase cerrado............ 31.45 VECES\nb).- En envase abierto............ 37.70 VECES\n1.2).- Autorizaciones.\na).- De cambio de giro y cambio de titular...................... 25.20 VECES\nb).- Cambio de nombre comercial... 12.70 VECES\n1.3).- Opinión Técnica..................... 25.20 VECES\n2.- Por expedición de permisos nuevos, una vez que han sido autorizados, pagarán los siguientes Derechos:\na).- Tienda de abarrotes.................. 1,875.20 VECES\nb).- Loncherías, fondas y coctelerías..... 2,247.39 VECES\nc).- Tienda de autoservicios.............. 5,750.20 VECES\nd).- Billares............................. 2,997.70 VECES\ne).- Agencias, sub-agencias y depósitos... 4,891.45 VECES\nf).- Restaurante.......................... 3,070.20 VECES\ng).- Licorerías........................... 5,811.45 VECES\nh).- Almacén o bodegas.................... 5,326.45 VECES\ni).- Expendios de cerveza y vinos......... 5,783.95 VECES\nj).- Supermercados........................ 5,783.95 VECES\nk).- Restaurante-bar...................... 5,637.70 VECES\nl).- Bar turístico, cantina, discoteca.... 7,639.57 VECES\nm).- Café cantante, cabaret............... 8,855.82 VECES\nn).- Hoteles y moteles.................... 8,475.20 VECES ñ).- Restaurante con venta para consumo únicamente de vinos de mesa de producción nacional.................. 0.00 VECES\no).- Sala de degustación exclusiva de cerveza artesanal.................... 187.70 VECES\np).- Boutique de cerveza artesanal en envase cerrado....................... 62.70 VECES\nq).- Establecimientos destiladores y/o fermentadores........................ 0.00 VECES\nr).- Establecimientos vinícolas........... 0.00 VECES\ns).- Centro de espectáculos............... 6,250.20 VECES\nt).- Centro de apuestas................... 12,500.20 VECES\nu).- Mercado.............................. 5,750.20 VECES\nPara efectos de los servicios adicionales, se otorgará sólo en aquellos giros, que refiere la\nLey de la materia, pagando los siguientes\nDerechos:\na).- Música grabada y aparatos musicales\n(tocadiscos, sinfonolas y aparatos estereofónicos)...................... 275.20 VECES\nb).- Conjuntos musicales.................. 325.20 VECES\nc).- Espectáculos artísticos.............. 437.70 VECES\nd).- Baile................................ 325.20 VECES\ne).- Mesas de billar...................... 275.20 VECES\n3.- Pago de Derechos por otros trámites:\na).- Cambio de domicilio dentro del municipio............................ 5% SOBRE PERMISO\nNUEVO\nb).- Cambio de domicilio de otro municipio 100% SOBRE PERMISO\nNUEVO\nc).- Cambio de propietario excepto los contemplados en el inciso g) de este apartado............................. 10% SOBRE PERMISO\nNUEVO\nd).- Cambio de giro comercial (hacia abajo)............................... 15% SOBRE PERMISO\nNUEVO DEL GIRO\nQUE PREVALECE\ne).- Cambio de giro comercial (hacia arriba).............................. DIFERENCIA ENTRE\nLAS TARIFAS DE LOS\nPERMISOS NUEVOS DE\nLOS GIROS QUE SE\nMODIFICAN\nf).- Por el cambio de nombre comercial, se pagará el 1% sobre el valor del permiso nuevo.\ng).- Cambio de propietario por herencia entre cónyuges o de padres a hijos... 5% SOBRE PERMISO\nNUEVO\nh).- Expedición de permiso temporal....... 10% SOBRE GIRO\nSOLICITADO\n4.- Recepción, análisis y evaluación de solicitudes de modificaciones o ajuste de horario a establecimientos donde se venda o almacenen bebidas con graduación alcohólica o alcohol...................... 26.45 VECES\n5.- Por autorización de permisos para venta y consumo público de bebidas alcohólicas en eventos públicos y privados con fines de lucro, y por eventos privados sin fines de lucro, se cobrará de acuerdo a la capacidad de ocupación por evento conforme a lo siguiente:\nI.- Por autorización de venta para consumo en eventos públicos y privados con fines de lucro por día.\na).- Con capacidad de hasta 150 personas......................... 45.00 VECES\nb).- Con capacidad de 151 a 300 personas......................... 90.00 VECES\nc).- Con capacidad de 301 a 450 personas......................... 135.00 VECES\nd).- Con capacidad de 451 a 600 personas......................... 180.00 VECES\ne).- Con capacidad de 601 a 750 personas......................... 225.00 VECES\nf).- Con capacidad de 751 a 1,000 personas......................... 300.00 VECES\ng).- Con capacidad de 1,001 a 5,000 personas........................ 400.00 VECES\nh).- Con capacidad de 5,001 a 10,000 personas........................ 600.00 VECES\ni).- Con capacidad mayor a 10,000 personas........................ 800.00 veces\nII.- Por autorización de consumo en eventos públicos y privados sin fines de lucro por día.\na).- Con capacidad de hasta 150 personas........................ 10.00 VECES\nb).- Con capacidad de 151 a 300 personas........................ 30.00 VECES\nc).- Con capacidad de 301 a 450 personas........................ 45.00 VECES\nd).- Con capacidad de 451 a 600 personas........................ 60.00 VECES\ne).- Con capacidad de 601 a 750 personas........................ 75.00 VECES\nf).- Con capacidad de 751 a 1,000 personas........................ 90.00 VECES\ng).- Con capacidad mayor a 1,000 personas........................ 150.00 VECES\nIII.- Por autorización de venta para consumo o consumo en eventos organizados por entidades paramunicipales o de gobierno, siempre y cuando estén considerados en sus Programas Operativos\nAnuales............................. EXENTO\n6.- Recepción, análisis y evaluación de solicitudes correspondientes para la venta de bebidas con graduación alcohólica en parques deportivos........................ 7.70 VECES\n7.- Expedición del permiso y autorización de venta de bebidas con graduación alcohólica en ferias................................. 1,312.70 VECES\n8.- Expedición de permiso y autorización en degustación de vinos de mesa de producción nacional y cerveza artesanal, por día..... 12.70 VECES\n9.- Autorización de modificación o ajuste de horario dentro del Ejercicio Fiscal que corresponda............................... 81.45 a 127.43 VECES\n10.- Por los certificados de opinión para la venta eventual de bebidas con graduación alcohólica se cubrirá 12.70 veces la Unidad de Medida y Actualización vigente.\n11.- Horario Extraordinario de operación de los establecimientos que cuentan con permisos para la venta, almacenaje y consumo público de bebidas alcohólicas.\nI.- Por hora extraordinaria en giros comerciales de restaurantes, restaurantes bar, cafés cantantes, discotecas, bares turísticos, espectáculos públicos, bailes públicos, ferias, variedades y diversiones análogas, pagarán de acuerdo a la capacidad de ocupación conforme a lo siguiente:\na).- Con capacidad de hasta 150 personas........................ 12.70 VECES\nb).- Con capacidad de 151 a 300 personas........................ 18.95 VECES\nc).- Con capacidad de 301 a 400 personas........................ 37.70 VECES\nd).- Con capacidad mayor a 400 personas........................ 62.70 VECES\nII.- Por hora extraordinaria en giros comerciales de billar, expendio de cerveza y vinos, licorería, bodega, agencia y sub agencia y depósito, pagarán conforme a lo siguiente:\na).- Por cada hora autorizada........ 12.70 VECES\n12.- Derechos por revalidación anual de permisos y servicios adicionales:\nACTUALIZACIÓN VIGENTE\na).- Café cantante, cabaret............... 112.70 VECES\nb).- Bar turístico, cantina, discoteca.... 93.95 VECES\nc).- Restaurante bar...................... 56.45 VECES\nd).- Supermercado......................... 56.45 VECES\ne).- Expendio de cerveza y vino........... 43.95 VECES\nf).- Almacén o bodega..................... 56.45 VECES\ng).- Licorería............................ 56.45 VECES\nh).- Restaurante.......................... 37.70 VECES\ni).- Agencias, subagencias y depósitos.... 43.95 VECES\nj).- Billares............................. 62.70 VECES\nk).- Tienda de autoservicios.............. 37.70 VECES\nl).- Loncherías, fondas y coctelerías..... 25.20 VECES\nm).- Tienda de abarrotes.................. 25.20 VECES\nn).- Hoteles y moteles.................... 100.20 VECES ñ).- Otros................................ 37.70 VECES\no).- Los servicios adicionales se revalidarán conjuntamente con el permiso de alcohol pagando por cada servicio adicional contratado........ 12.70 VECES\np).- Restaurante con venta para consumo únicamente de vinos de mesa de producción nacional.................. 31.45 VECES\nq).- Sala de degustación exclusiva de cerveza artesanal.................... 31.45 VECES\nr).- Boutique de cerveza artesanal en envase cerrado....................... 31.45 VECES\ns).- Establecimientos destiladores y/o fermentadores........................ 31.45 VECES\nt).- Establecimientos vinícolas........... 31.45 VECES\nu).- Centro de espectáculos............... 125.20 VECES\nv).- Centro de apuestas................... 250.20 VECES\nw).- Mercado.............................. 37.70 VECES\nLos contribuyentes que opten por revalidar los permisos anuales establecidos en el punto 12 de este Artículo, gozarán de un descuento de 10% en el mes de enero y de un 7% de descuento en el mes de febrero sobre la tarifa anual establecida.\nQuienes no revaliden sus permisos en forma oportuna o quienes lo hagan fuera de los plazos establecidos conforme a la Ley de la materia, causarán una sanción económica de 20.00 a 150.00 veces la Unidad de Medida y Actualización Vigente independientemente de las sanciones administrativas a que tuviese lugar. No procederá sanción alguna cuando se haya presentado y otorgado prórroga para la revalidación de permisos. Las prórrogas o plazos otorgados serán por única vez y no podrán exceder de 90 días naturales. Los permisos y las autorizaciones para servicios adicionales deberán ser revalidados y cubiertos los Derechos correspondientes ante la Tesorería Municipal, en el mes de junio de cada año, de lo contrario, se procederá a lo establecido en este párrafo.\nx).- Recepción, análisis y evaluación de solicitud de plazo para revalidación de permiso de alcohol................ 22.70 VECES\n13.- Evaluación y dictamen sobre la procedencia de ampliación al plazo para inicio de operaciones............................... 2.70 VECES\n14.- Recepción de notificaciones respecto de cierre temporal o circunstancial.......... 2.70 VECES\n15.- Expedición de nueva impresión de permisos otorgados................................. 6.45 VECES\nIndependiente de las sanciones administrativas, a que haya lugar, por las infracciones previstas en la Ley para la Venta, Almacenaje y\nConsumo Público de Bebidas Alcohólicas del Estado de Baja California, los infractores serán sancionados con una multa de 3.00 a 500.00 veces la Unidad de Medida y Actualización Vigente.\n15.- DERECHOS POR SERVICIOS DE LA DIRECCIÓN DE SALUD MUNICIPAL\nARTÍCULO 43.- Los servicios proporcionados por la Dirección de Salud\nMunicipal, se pagarán con base a lo siguiente:\nUNIDAD DE MEDIDA Y\nACTUALIZACIÓN VIGENTE\n1.- Consulta médica general................... 0.50 VECES\n2.- Servicios de laboratorio.................. 12.70 VECES\n3.- Consulta de especialista.................. 3.95 VECES\n4.- Registro en la Dirección de Salud\nMunicipal................................. 2.70 VECES\n5.- Expedición o reposición de Tarjeta\nSanitaria de Control del Sector Sexual\n(Tarjeta Sanitaria CSS)................... 4.00 VECES\n6.- Otros (fotos, material médico, etc.)...... 1.00 VEZ\n7.- Certificado médico de esencia a conductores bajo el influjo del alcohol................................... 12.70 VECES\n8.- Consulta sanitaria........................ 2.70 VECES\n9.- Consulta psicológica...................... 2.70 VECES\n10.- Internado por día en hospital psiquiátrico.............................. 15.20 VECES\n11.- Certificados médicos prenupciales......... 2.70 VECES\n12.- Expedición de certificados médicos........ 2.70 VECES\n13.- Expedición o reposición de Tarjeta\nSanitaria de Control del Sector Alimentos\n(Tarjeta Sanitaria CSA)................... 4.00 VECES\n14.- Certificado médico por aliento alcohólico. 7.70 VECES\nNo se causará este Derecho, cuando el certificado sea expedido disposición de la autoridad competente y no se encuentre en estado de ebriedad, ni bajo el influjo de sustancias tóxicas, con aliento alcohólico, que se establece en los numerales 7) y\n14) anteriores; aun cuando hubiere cometido algún tipo de infracción al Reglamento de Orden y Justicia Cívica del Municipio de Playas de Rosarito, Baja California.\n15.- Servicios que presta el Centro de Control\nAnimal:\na).- Vacunación antirrábica............... EXENTO\nb).- Alimentación de animales capturados por día.............................. 1.00 VEZ\nc).- Tratamiento de scabiasis............. EXENTO\nd).- Orquiectomía en caninos: d.1).- Hasta 5 kilos de peso........ 4.00 VECES d.2).- De 5.1 hasta 15 kilos de peso 5.00 VECES d.3).- Más de 15 kilos de peso...... 6.00 VECES\ne).- Ovariectomía en caninas: e.1).- Hasta 5 kilos de peso........ 4.00 VECES e.2).- De 5.1 hasta 15 kilos de peso 5.00 VECES e.3).- Más de 15 kilos de peso...... 6.00 VECES\nf).- Ovariectomía en felinas: f.1).- Hasta 5 kilos de peso........ 4.00 VECES f.2).- Más de 5 kilos de peso....... 5.00 VECES\ng).- Orquiectomía en felinos: g.1).- Hasta 5 kilos de peso........ 4.00 VECES g.2).- Más de 5 kilos de peso....... 5.00 VECES\nh).- Adopción de animales: h.1).- Por particulares............. 3.00 VECES h.2).- Por Organizaciones No\nGubernamentales (ONG) o rescatistas.. 2.50 VECES\ni).- Sacrificio de animales a petición del ciudadano............................ 3.00 VECES\nj).- Recepción de cadáveres caninos o felinos.............................. 3.00 VECES\nk).- Consulta Veterinaria................. 0.50 VECES\nl).- Cédula de Identificación Animal...... 2.70 VECES\nm).- Esterilización contemplada en los incisos d), e), f) y g), de este numeral 15, realizadas en campañas o jornadas asistenciales............... EXENTO\nProtección y Control de Animales Domésticos de Playas de Rosarito, Baja California, se cobrarán de 3.00 a 300.00 veces la Unidad de\n91 al 95 del Reglamento a que se refiere el presente párrafo.\nIndependiente de las sanciones administrativas, a que haya lugar, por\nMunicipio de Playas de Rosarito, Baja California, los infractores serán sancionados con una multa de 20.00 a 1,000.00 veces la Unidad de Medida y Actualización Vigente.\n16.- DERECHOS POR SERVICIOS QUE PRESTA LA DIRECCIÓN DE PROTECCIÓN\nCIVIL Y BOMBEROS\nARTÍCULO 44.- Los servicios que presta la Dirección de Protección\nCivil y Bomberos a giros comerciales, industriales y de los sectores público y privado, se causarán conforme a su materia, de acuerdo a lo siguiente:\nI.- Certificación o regularización de dispositivos de seguridad en edificios existentes, de oficio o a petición de parte:\nACTUALIZACIÓN VIGENTE\n1.- Comercio en pequeño:\na).- Comercio establecido hasta 50 M² de superficie................... 9.00 VECES\nb).- Puestos semifijos con uso de minas de gas.................... 4.00 VECES\nc).- Colectivos. Por puesto con uso de minas de gas.................... 5.00 VECES\n2.- Despachos de profesionistas y giros de servicio............................. 16.00 VECES\n3.- Expendios de sodas y pan, autoservicios, loncherías, panaderías, lavanderías, ferreterías, refaccionarias, tiendas de ropa, farmacias, papelerías, librerías, templos religiosos, abarrotes, carnicerías, bancos, café internet, estéticas, zapaterías, renta películas de video, tiendas de curiosidades, misceláneas, boticas, lotes de autos, joyerías, tiendas de segunda, mueblerías, taquerías, imprentas, gimnasios, fruterías, vidrieras, florerías, spa, veterinarias, graneros y casas de cambio............................... 13.00 VECES\n4.- Restaurantes, mercados, supermercados, bodegas de distribución, salones de renta, salas cinematográficas, culturales y teatros, herrerías, llanteras, laboratorios clínicos, talleres mecánicos, carrocería y pintura, lavado de autos, talleres autoeléctricos, taller de carpintería, yonkes, pizzerías, tapicerías, crematorios y estacionamientos verticales.......... 23.00 VECES\n5.- Clubes deportivos, clínicas y hospitales........................... 32.00 VECES\n6.- Tiendas departamentales.............. 60.00 VECES\n7.- Moteles:\na).- Hasta 10 habitaciones........... 30.00 VECES\nb).- De 11 a 20 habitaciones......... 45.00 VECES\nc).- De 21 habitaciones en adelante.. 75.00 VECES\n8.- Hoteles:\na).- Hasta 30 habitaciones........... 45.00 VECES\nb).- De 31 habitaciones en adelante por habitación.................. 2.70 VECES\n9.- Edificios educativos o de asistencia:\na).- Educativos, hasta 10 aulas...... 20.00 VECES\nb).- Educativos, de 11 aulas en adelante........................ 30.00 VECES\nc).- Guarderías...................... 30.00 VECES\nd).- Asilos.......................... 20.00 VECES\ne).- Casas de retiro................. 20.00 VECES\nf).- Centro de Rehabilitación........ 20.00 VECES\n10.- Condominios: habitacional por unidad. 7.00 VECES\n11.- Giros de alto riesgo:\na).- Distribuidoras de gases, combustibles y lubricantes, oxígenos y acetilenos, polvorines, gasolineras y depósitos de combustibles y lubricantes, ferreterías con venta de minas de gas, madererías, recicladoras, basurero o depósito final de residuos domésticos y comerciales, y otros giros de alto riesgo..................... 200.00 VECES\nb).- Mercados y abarrotes con venta de minas de gas.................... 75.00 VECES\nc).- Centros de apuestas, apuestas remotas, salas de sorteos de números y/o casinos, Dictamen de\nOperación....................... 300.00 VECES\n12.- Eventos por ferias, circos, exposiciones, conciertos y/u otros eventos masivos:\na).- Por evento...................... 25.00 VECES\nb).- Adicional por puesto o módulo con uso de mina de gas.............. 1.50 VECES\n13.- Otros giros no especificados:\na).- Hasta 50 M² de superficie....... 13.00 VECES\nb).- Mayores a 50 M² de superficie... 25.00 VECES\n14.- Edificios Industriales:\na).- Micro-industria De 1 a 25 empleados... 45.00 VECES\nb).- Pequeña industria De 26 a 100 empleados... 75.00 VECES\nc).- Industria mediana De 101 a 250 empleados... 125.00 VECES\nd).- Macro industria De 251 empleados en adelante.... 0.65 VECES\nPOR EMPLEADO\nII.- Análisis de factibilidad para la prestación de servicios de bomberos en proyectos de desarrollos urbanos, mayores a 50 M², con base al uso de suelo:\n1.- Desarrollo habitacional multifamiliar, horizontal o vertical, por metro cuadrado de construcción....... 0.10 VECES\n2.- Desarrollo industrial por metro cuadrado de construcción............. 0.25 VECES\n3.- Desarrollo comercial por metro cuadrado de construcción............. 0.19 VECES\n4.- Desarrollos considerados en numerales anteriores 1, 2 y 3, cuando no sea posible determinar los metros cuadrados de construcción, se cobrará por metro cuadrado utilizable........ 0.05 VECES\n5.- Modificación por cambio de nombre y/o representante legal.................. 20.00 VECES\n6.- Cambio de Régimen de Propiedad por cantidad condominio al momento de la inspección........................... 25.20 VECES\nIII.- Certificación de daños en bienes siniestrados:\n1.- Casas-habitación que no se encuentren aseguradas al ocurrir el siniestro........................... EXENTO\n2.- Casas-habitación que se encuentren aseguradas al ocurrir el siniestro.. 12.70 VECES\n3.- Uso comercial o de servicios que no se encuentren aseguradas al ocurrir el siniestro........................ 12.70 VECES\n4.- Uso comercial o de servicios que se encuentren aseguradas al ocurrir el siniestro........................... 37.70 VECES\n5.- Uso industrial siniestrado.......... 125.20 VECES\nIV.- Revisión de giros comerciales para obtención de autorización para la venta de bebidas alcohólicas:\n1.- Restaurante con venta para consumo únicamente de vinos de mesa de producción nacional, sala de degustación exclusiva de cerveza artesanal, boutique de cerveza artesanal en envase cerrado, establecimientos destiladores y/o fermentadores, establecimientos vinícolas............................ 10.00 VECES\n2.- Tiendas de abarrotes, loncherías, fondas y coctelerías................. 30.00 VECES\n3.- Restaurantes, restaurantes bar, bares turísticos, cantinas, cafés cantantes, cabarets, mercados y tiendas de autoservicios, supermercados, almacén o bodegas de distribución, licorerías, agencias, sub-agencias, depósitos, billares, expendios de cervezas y vinos........ 45.00 VECES\n4.- Discotecas, tiendas departamentales, hoteles, moteles, centros de espectáculos y centros de apuestas... 100.00 VECES\nV.- Certificación de equipo y dispositivos de seguridad:\n1.- Vivienda............................. EXENTO\n2.- Comercio............................. EXENTO\n3.- Industria............................ EXENTO\n4.- Certificación de sistemas hidráulicos contra incendios..................... 62.70 VECES\nVI.- Certificación de empresas dedicadas a mantenimiento, renta y/o venta de extintores portátiles:\n1.- Certificación anual de actividad comercial e instalaciones............ 40.20 VECES\n2.- Suministro anual de etiquetas para verificación de la calidad del agente extintor, por cada etiqueta.......... 0.12 VECES\nVII.- Servicios especiales:\n1.- Certificación de empresas de capacitación a personas físicas o morales en el área de formación de brigadas de primeros auxilios, uso y manejo de extinguidores, uso y manejo de mangueras, materiales peligrosos, sistema de administración de emergencia, previa acreditación de cursos............................... 40.00 VECES\n2.- Pago de Derechos por empresas registradas ante la Subdirección de\nBomberos por otorgar cursos de:\na).- Formación de brigadas contra incendios....................... 22.70 VECES\nb).- Primeros auxilios............... 28.95 VECES\nc).- Manejo de extintores............ 12.70 VECES\nd).- Brigadas de evacuación.......... 12.70 VECES\ne).- Brigadas de búsqueda y rescate.. 12.70 VECES\n3.- Uso de equipo por hora:\na).- Máquina extinguidora............ 43.95 VECES\nb).- Máquina de iluminación.......... 43.95 VECES\nc).- Máquina escala.................. 43.95 VECES\nLos servicios especiales a que hace referencia este inciso, cuando se trate de escuelas públicas, quedarán exentas de pago, la misma institución.\nVIII.- Revisión de explosivos y líquidos flamables:\n1.- Revisión de castillos pirotécnicos... 37.70 VECES\n2.- Revisión de polvorín móvil........... 62.70 VECES\n3.- Revisión de polvorines o permisos de explosivos........................... 73.95 VECES\n4.- Revisión de unidades móviles que transporten líquidos flamables....... 62.70 VECES\nIX.- Revalidación anual de certificación de dispositivos de seguridad en edificios parte:\nPor revalidación anual de certificación de dispositivos de seguridad según giro que corresponda, se cobrará................... 50% SOBRE COSTO\nDE CERTIFICACIÓN\nAÑO EN CURSO\nX.- Por otros servicios en materia de protección civil, se cobrará:\n1.- Análisis de Gestión Integral de\nRiesgos y/o Verificación de Proyectos de Construcción:\na).- Casa-habitación, por M².......... 0.09 VECES\nb).- Habitacionales, unifamiliares y multifamiliares, con fines de comercialización y/o arrendamiento, por M²............ 0.13 VECES\nc).- Comercial, por M²................ 0.16 VECES\nd).- Industrial hasta 2,500 M², por M² 0.21 VECES\ne).- Industrial, más de 2,500 M², por\nM²............................... 0.16 VECES\nf).- Barda, fachada y remodelaciones, por M²........................... 0.09 VECES\n2.- Revisión y certificación de programas internos y programas específicos a petición de parte:\na).- Revisión y certificación de programas internos por primera vez............................. EXENTO\nb).- Revisión y certificación de programas internos\n(revalidación).................. 28.00 VECES\nc).- Revisión de programas específicos..................... 31.45 VECES\nd).- Revisión de programas específicos de más de 1,000 personas........................ 37.70 VECES\ne).- Revisión de programas específicos de más de 10,000 personas........................ 50.20 VECES\n3.- Expedición de Certificado de Aforo, requisito para la expedición y revalidación anual de permisos de alcohol contemplado en el Reglamento que Regula la Venta, Almacenaje y\nConsumo de Bebidas Alcohólicas en el\nMunicipio de Playas de Rosarito, Baja\nCalifornia........................... 20.00 VECES\nARTÍCULO 45.- Los servicios extraordinarios que preste la Dirección de Protección Civil y Bomberos a solicitud de la parte interesada, se pagarán conforme al presupuesto que al efecto formule la Dirección, preste y quedar comprendido de 10.00 a las 100.00 veces la Unidad de\nMedida y Actualización vigente.\n17.- DERECHOS POR RECEPCIÓN Y ANÁLISIS DE DOCUMENTOS REFERENTES A\nARTÍCULO 46.- Para la realización de eventos, espectáculos públicos pago de Derechos que se causen de acuerdo a la siguiente:\nACTUALIZACIÓN VIGENTE\n1.- CIRCOS (por día)\na).- De una pista......................... 5.00 VECES\nb).- De más de una pista.................. 10.00 VECES\n2.- JUEGOS MECÁNICOS (por día)\na).- Zona centro.......................... 10.00 VECES\nb).- Delegaciones......................... 5.00 VECES\n3.- CIERRE DE CALLES (por día)\na).- Eventos públicos..................... 20.00 VECES\nb).- Eventos privados..................... 15.00 VECES\nc).- Carreras atléticas, carreras y paseos ciclistas y otros eventos deportivos: c.1).- Con fines de lucro............ 0.37 VECES\nPOR PARTICIPANTE c.2).- Sin fines de lucro............ 0.01 VECES\nPOR PARTICIPANTE\nd).- Por filmaciones documentales, comerciales, películas y series...... 80.00 VECES\n4.- DESFILES PROMOCIONALES.................... 22.70 VECES\n5.- EXHIBICIÓN DE MODAS Y OTROS............... 22.70 VECES\n6.- FUNCIONES\na).- Box (por día) a.1).- Profesional................... 45.00 VECES a.2).- Amateur....................... 22.70 VECES\nb).- Lucha libre (por día) b.1).- Profesional................... 45.00 VECES b.2).- Amateur....................... 22.70 VECES\nc).- Obras de teatro...................... 18.95 VECES\nd).- Cine................................. 22.70 VECES\ne).- Otros................................ 22.70 VECES\n7.- EVENTOS PARTICULARES\na).- Los eventos privados que hayan pagado lo correspondiente al Artículo 42, numeral 5, Fracción II de la presente\nLey de Ingresos, quedarán exentos del pago por el evento.\n8.- ESPECTÁCULOS MASIVOS\na).- Corrida de toros..................... 28.95 VECES\nb).- Concierto y/o presentación de artistas, cantantes, entretenedores\n(por día)............................ 50.00 VECES\nc).- Bailes en salones.................... 28.95 VECES\nd).- Motocross y carreras de autos........ 28.95 VECES\ne).- Ferias............................... 1,312.70 VECES\nf).- Otros................................ 15.20 VECES\ng).- Tratándose de espectáculos realizados por Organismos no lucrativos que brinden servicios y asistencia médica de manera gratuita a enfermos que padezcan cáncer en etapa terminal, debidamente registrados ante institución oficial que para tales efectos señale la Ley de la materia.............................. 0.00 VECES\nh).- Festival musical por la capacidad de personas (por día) h.1) Con capacidad de hasta 1,000 personas............................. 50.00 VECES h.2) Con capacidad de 1,001 a 2,000 personas............................. 100.00 VECES h.3) Con capacidad de 2,001 a 3,000 personas............................. 150.00 VECES h.4) Con capacidad de 3,001 a 4,000 personas............................. 180.00 VECES h.5) Con capacidad de 4,001 a 5,000 personas............................. 225.00 VECES h.6) Con capacidad de 5,001 a 6,000 personas............................. 300.00 VECES h.7) Con capacidad de 6,001 a 8,000 personas............................. 400.00 VECES h.8) Con capacidad mayor de 8,000 personas............................. 600.00 VECES\ni).- Exposiciones y/o Congresos por la capacidad de personas (por día) i.1) Con capacidad de hasta 1,000 personas............................. 50.00 VECES i.2) Con capacidad de 1,001 a 2,000 personas............................. 100.00 VECES i.3) Con capacidad de 2,001 a 3,000 personas............................. 150.00 VECES i.4) Con capacidad de 3,001 a 4,000 personas............................. 180.00 VECES i.5) Con capacidad de 4,001 a 5,000 personas............................. 225.00 VECES i.6) Con capacidad de 5,001 a 6,000 personas............................. 300.00 VECES i.7) Con capacidad de 6,001 a 8,000 personas............................. 400.00 VECES i.8) Con capacidad mayor de 8,000 personas............................. 600.00 VECES\n9.- FILMACIONES DOCUMENTALES, COMERCIALES,\nPELÍCULAS Y SERIES\na).- Filmaciones Documentales............. 25.00 VECES\nb).- Filmaciones Comerciales.............. 50.00 VECES\nc).- Películas............................ 200.00 VECES\nd).- Series............................... 100.00 VECES\nEn general por la recepción y análisis de documentos de espectáculos y eventos urgentes (en menos de 48 horas), se cobrará el doble de la tarifa.\nCuando los eventos de la vía pública, establecidos en el inciso d) del numeral 3 y los incisos del numeral 9 de este Artículo, sean realizados por producciones estudiantiles con fines académicos, con el aval de la institución educativa correspondiente, se exentarán del pago de la tarifa establecida en los mismos.\n18.- DERECHOS POR RECEPCIÓN Y ANÁLISIS DE DOCUMENTOS REFERENTES A\nARTÍCULO 47.- Para el registro inicial, cambio de domicilio o de propietario o el incremento de aparatos mecánicos, electrónicos, electromecánicos, musicales, digitales, videojuegos y cualquier otra tecnología similar que opere mediante la inserción de billete, moneda, ficha, tarjeta, banda magnética, o cualquier otro medio de cobro integrado a la máquina, incluyendo de manera enunciativa y no limitativa las máquinas expendedoras de bebidas, dulces, alimentos, botanas, golosinas, juguetes, computadoras, goma de mascar, tarjetas de teléfono, mercancías en general, entre otros, dirigidas al público en general, se deberán entregarse y analizarse la documentación necesaria previo el pago de Derechos conforme a la tabla siguiente:\nACTUALIZACIÓN VIGENTE\nPROPIETARIO COMISIONISTA\nDEL APARATO\na).- Cambio de domicilio.............. 43.95 VECES 0.00 VECES\nb).- Cambio de propietario............ 43.95 VECES 0.00 VECES\nc).- Registro inicial, por aparato.... 7.70 VECES 3.95 VECES\nd).- Incremento, por aparato.......... 7.70 VECES 3.95 VECES\ne).- Por verificación anual de aparatos mecánicos, electrónicos, electromecánicos, musicales y videojuegos por aparato que deberá pagarse antes del 30 de junio del\nEjercicio Fiscal correspondiente. 3.95 VECES 2.70 VECES\nf).- Por la recepción de documentos y dictamen de solicitud............ 37.70 VECES\nArtículo, serán responsables solidarios del pago de los Derechos que deban enterarse.\nArtículo, ocasionará la clausura de los aparatos de que se trate.\nCENTROS DE APUESTAS, APUESTAS REMOTAS, SALAS DE SORTEOS DE NÚMEROS\nY/O CASINOS\ng).- Las máquinas de azar o con combinaciones de azar y destreza, con premios en efectivo o en especie que cuenten con autorización de la Secretaría de Gobernación, pagarán los\nDerechos de instalación o explotación conforme a la siguiente tabla:\n1).- Anuencia para apertura, por establecimiento...................... 50,000.00 VECES\n2).- Apertura del establecimiento......... 100,000.00 VECES\n3).- Cambio de domicilio.................. 2,500.20 VECES\n4).- Cambio de propietario................ 2,500.20 VECES\n5).- Registro inicial o incremento por aparato.............................. 75.20 VECES\n6).- Revalidación anual de licencia de operación por establecimiento........ 2,500.20 VECES\n7).- Aportación para programas preventivos para la ludopatía, trimestral por máquina, por unidad de aparato similar autorizado........................... 2.70 VECES\n8).- Permiso de operación por horario ampliado, anual...................... 2,500.20 VECES\nPara el caso del inciso g) numeral 2) de este Artículo, quienes cubran los Derechos correspondientes al Ejercicio Fiscal 2025, anteriores.\n19.- DERECHOS POR SERVICIOS QUE PRESTA LA SECRETARÍA DE BIENESTAR\nSOCIAL MUNICIPAL\nARTÍCULO 48.- Los servicios que presta la Secretaría de Bienestar\nSocial Municipal, se cobrarán conforme a la siguiente:\nACTUALIZACIÓN VIGENTE\na).- Los Derechos municipales por cursos culturales se cobrarán de acuerdo a los convenios que se suscriban con los talleristas por mes....................... 20% DE LA INSCRIPCIÓN Y MENSUALIDAD\nESTABLECIDA\nb).- Los Derechos municipales por impartición de talleres de capacitación y certificación por competencia\n1).- Servicio de proceso de certificación con base a estándares de competencia inscritos en el Registro Nacional de\nEstándares de Competencia............ 16.76 a 49.88 VECES\n2).- Servicio de capacitación a través de cursos de formación continua, procurando la adquisición de conocimientos, habilidades y destrezas............................ 1.03 a 8.48 VECES\n3).- Registro de foros, convenciones y exposiciones en eventos públicos que promuevan............................ 4.89 a 23.95 VECES\n20.- DERECHO POR ALUMBRADO PÚBLICO QUE PRESTA LA DIRECCIÓN DE\nSERVICIOS URBANOS\nARTÍCULO 49.- El Derecho por Alumbrado Público que preste el\nMunicipal otorgado a la comunidad en calles, avenidas, bulevares, caminos vecinales, plazas, parques, jardines y otros lugares de uso común. Entendiéndose por beneficiarios todos los habitantes del\nMunicipio de Playas de Rosarito, Baja California, por lo que pagarán una cuota fija mensual general de acuerdo al costo siguiente:\nUNIDAD DE MEDIDA Y\nACTUALIZACIÓN VIGENTE\n1.- Derecho por Alumbrado Público.............. 0.61 VECES/\nMENSUAL operación, ampliación, rehabilitación, reposición y mantenimiento en la prestación de este servicio, así como los gastos administrativos, servicio, erogado por el Municipio. Lo anterior en cumplimiento a los principios establecidos en el Artículo 31 Fracción IV de la cuenta a los beneficiarios de este servicio en el Municipio.\nEl Ayuntamiento cobrará el Derecho por Alumbrado Público, a través de las oficinas de la Recaudación de Rentas de la Tesorería Municipal, o bien, en los organismos o empresas autorizadas, previo convenio que para el efecto se celebre, quienes expedirán el recibo correspondiente, pudiendo ampliarse la periodicidad y modalidad de su cobro en beneficio de los contribuyentes.\nSECCIÓN SEGUNDA\nOTROS DERECHOS\n21.- OTROS DERECHOS POR OTROS SERVICIOS QUE PRESTA EL AYUNTAMIENTO\nU ORGANISMOS PARAMUNICIPALES\nARTÍCULO 50.- Los servicios que presten las dependencias municipales no enunciados en los Artículos que anteceden de esta Ley, causarán\nDerechos, los cuales se estarán a lo dispuesto en los Artículos 7, 7\nBaja California.\nARTÍCULO 51.- Los servicios que presten los Organismos Públicos\nDescentralizados y/o Paramunicipales, causarán Derechos, los cuales se cobrarán de acuerdo a lo siguiente:\nA.- PROMOTORA DE DESARROLLO URBANO DE PLAYAS DE ROSARITO\nACTUALIZACIÓN VIGENTE\n1.- Certificados de Libertad de Gravámenes\nFiscales, Certificados o Constancias de No\nAdeudo, y Certificados de Datos:\na).- Servicios ordinarios (mayor a 24 horas)............................... 1.25 VECES\nb).- Servicios extraordinarios (menor a 24 horas)............................... 2.50 VECES\nc).- Servicios urgentes................... 3.75 VECES\n2.- Alta y revalidación al padrón de contratistas............................... 13.75 VECES\n3.- Pago de bases de licitaciones para la obra pública:\na).- De $0.00 y hasta $500,000.00 pesos... 6.25 VECES\nb).- Mayor de $500,000.00 y hasta\n$1’000,000.00 pesos.................. 12.50 VECES\nc).- Mayor de $1’000,000.00 y hasta\n$5’000,000.00 pesos.................. 25.00 VECES\nd).- Mayor de $5’000,000.00 pesos......... 75.00 VECES\nB.- COMITÉ DE TURISMO Y CONVENCIONES DE PLAYAS DE ROSARITO\n1).- De los servicios que presta el Comité de\nTurismo y Convenciones, se cobrarán de conformidad al presupuesto realizado.\na).- Únicamente con fines de lucro.\n2).- Los servicios de apoyo que presta el Comité de Turismo y Convenciones a los eventos turísticos realizados en el municipio de\nPlayas de Rosarito se cobrarán de acuerdo a la siguiente:\nACTUALIZACIÓN VIGENTE\na).- Evento deportivo Paseo Ciclista\nRosarito-Ensenada: a.1).- Con fines de lucro por participante.................. Hasta 0.20 VECES\nC.- INSTITUTO MUNICIPAL DEL DEPORTE DE PLAYAS DE ROSARITO de Rosarito, se cobrarán de acuerdo a sus tabuladores conforme a la siguiente:\nACTUALIZACIÓN VIGENTE\na).- Por admisión, inscripción, eventos especiales a unidades deportivas, centro acuático, lienzo charro, centro tenístico de alto rendimiento, clases, arbitraje, se cobrará conforme a lo siguiente: a.1).- Admisión a Centro Acuático Rosarito por día............................ 0.50 a 2.00 VECES a.2).- Admisión a Centro Acuático Rosarito por mes............................ 4.50 a 13.00 VECES a.3).- Inscripción al Centro Acuático..... 1.50 a 3.00 VECES a.4).- Clases de Piso por clase........... 0.15 a 0.30 VECES a.5).- Uso de Gimnasio Centro de\nFortalecimiento de Rosarito, por día................................ 0.30 a 1.10 VECES a.6).- Uso de Gimnasio Centro de\nFortalecimiento de Rosarito, por mes................................ 1.50 a 5.00 VECES a.7).- Inscripción al Centro de\nFortalecimiento de Rosarito........ EXENTO a.8).- Uso de cancha de fútbol 7 por hora............................... 1.50 a 4.50 VECES a.9).- Uso de cancha de fútbol 7 por evento............................. 7.50 a 22.50 VECES a.10).- Admisión a estacionamiento, por vehículo.......................... 0.025 a 1.50 VECES a.11).- Admisión a Unidades Deportivas, por persona....................... EXENTO a.12).- Admisión de Alberca Unidad Deportiva Rosarito niños, por día...... 0.10 a 1.00 VECES a.13).- Admisión de Alberca Unidad Deportiva Rosarito niños, por mes...... 3.00 a 10.00 VECES a.14).- Admisión de Alberca Unidad Deportiva Rosarito adultos, por día... 0.10 a 2.00 VECES a.15).- Admisión de Alberca Unidad Deportiva Rosarito adultos, por mes... 3.00 a 10.00 VECES a.16).- Por uso de Cancha de Raquetbol 1 hora por pareja día Unidad\nRosarito.......................... 0.24 a 1.50 VECES a.17).- Por uso de Cancha de Tenis 1 hora por pareja Unidad Rosarito... EXENTO a.18).- Por uso de Asadores Unidad\nRosarito, por evento.............. EXENTO a.19).- Por uso de Cancha de Tenis Centro\nTenístico de Alto Rendimiento 1 hora, por pareja.................. 0.80 a 3.00 VECES a.20).- Por clase de natación o fisioterapia deportiva por persona\nUnidad Rosarito................... 0.25 a 10.00 VECES a.21).- Por uso mensual de salón de usos múltiples en Centro Tenístico de\nAlto Rendimiento.................. 7.43 a 44.58 VECES a.22).- Por admisión por persona por evento organizado por IMDER al Lienzo\nCharro de Rosarito................ 1.00 a 7.50 VECES a.23).- Por admisión por niño al Plan\nVacacional organizado por IMDER... 1.00 a 15.00 VECES a.24).- Por participar en Carrera Atlética organizado por IMDER por participante...................... 0.80 a 4.00 VECES a.25).- Por evento de Valetodo organizado por IMDER por asistente........... 1.50 a 4.00 VECES a.26).- Por evento de Lucha Libre organizado por IMDER por asistente...... 0.30 a 4.00 VECES a.27).- Por evento de Box Amateur organizado por IMDER por asistente......................... 0.30 a 4.00 VECES a.28).- Por evento de Box organizado por\nIMDER por asistente............... 0.30 a 4.50 VECES a.29).- Por torneo de Basquetbol organizado por IMDER por asistente........... 0.30 a 2.50 VECES a.30).- Por evento de Paseo Ciclista organizado por IMDER por asistente 0.80 a 4.00 VECES a.31).- Por evento de Medio Maratón organizado por IMDER por asistente 1.50 a 4.00 VECES a.32).- Por uso de Auditorio de la Unidad\nDeportiva 1 hora.................. 1.50 a 5.00 VECES a.33).- Por uso de Cancha de Soccer por 1 hora.............................. 1.50 a 5.00 VECES a.34).- Por uso de Cancha de Atletismo por\n1 hora............................ 1.50 a 3.00 VECES a.35).- Por uso de Estadio en Centro\nTenístico de Alto Rendimiento, por evento............................ 55.00 a 250.00 VECES a.36).- Por uso de caballerizas del Lienzo\nCharro Rosarito, mensual.......... 2.00 a 10.00 VECES a.37).- Por uso del Lienzo Charro Rosarito, por hora.......................... 1.00 a 10.00 VECES a.38).- Por uso del Lienzo Charro Rosarito, por evento........................ 100.00 a 300.00\nVECES a.39).- Por uso de corraletas del Lienzo\nCharro Rosarito, mensual.......... 2.00 a 10.00 VECES\nLos Derechos por uso contenidos en el inciso anterior deben cumplir con el objeto y fines del Instituto Municipal del Deporte de Playas de Rosarito, Baja California; para fines distintos deberá aplicarse lo establecido en el Artículo 69 de esta Ley.\nb).- Por copias simples o certificadas de documentos solicitados a la Paramunicipal, se cobrará conforme a lo siguiente: b.1).- Por copia simple de documento...... EXENTO b.2).- Por copia certificada de documento. EXENTO\nc).- Los Derechos por Cursos Deportivos se cobrarán de acuerdo a los según el acuerdo establecido.\nD.- INSTITUTO MUNICIPAL DE ARTE Y CULTURA DE ROSARITO cobrarán de acuerdo a sus tabuladores conforme a la siguiente:\nACTUALIZACIÓN VIGENTE\na).- Por cursos culturales por mes............. 2.00 a 10.00 VECES a.1).- Los derechos municipales por cursos culturales se cobrarán de acuerdo a los convenios que se suscriban con los talleristas por mes........... 100% INSCRIPCIÓN Y\n30% DE LA MENSUALIDAD\nESTABLECIDA\nb).- Por uso de instalaciones: b.1).- Por uso del salón de usos múltiples......................... 30 a 60 VECES b.2).- Por uso de la explanada........... 40 a 80 VECES b.3).- Por uso del salón................. 2 a 15 VECES\nE.- SISTEMA PARA EL DESARROLLO INTEGRAL DE LA FAMILIA\nLos servicios que presta el Sistema para el Desarrollo Integral de la\nFamilia se cobrarán de acuerdo a sus tabuladores conforme a la siguiente:\nACTUALIZACIÓN VIGENTE\na).- Admisión a estacionamiento de la playa.... 0.35 a 1.49 VECES\nb).- Por cursos en centros comunitarios........ 0.22 a 2.41 VECES\nc).- Admisión a baños públicos de la playa..... 0.07 a 0.15 VECES\nd).- Por expedición de tarjetón de discapacitados............................ EXENTO\ne).- Por expedición de engomado de tarjetón de discapacitados............................ EXENTO\nf).- Por servicio de traslado a personas con discapacidad.............................. EXENTO\ng).- Por servicio de guardería en estancias infantiles que presta el DIF.............. 2.97 a 17.83 VECES\nh).- Por certificación de estancias............ 22.29 VECES\ni).- Por constancia de preescolar.............. 0.80 a.92 VECES\nj).- Por copia certificada de documento........ 0.80 a.92 VECES\nk).- Por verificación de estancias infantiles.. 22.29 a 25.21 VECES\nl).- Consulta de terapia física................ 0.70 VECES\nm).- Sesión de terapia física.................. 0.65 a 3.00 VECES\nn).- Sesión psicológica........................ 0.57 a 2.00 VECES ñ).- Constancia de pláticas prematrimoniales... 4.62 VECES\nF.- INSTITUTO MUNICIPAL DE LA MUJER DE PLAYAS DE ROSARITO\nLos servicios que presta el Instituto Municipal de la Mujer de Playas de Rosarito, se cobrarán de acuerdo a la siguiente:\nACTUALIZACIÓN VIGENTE\na).- Por talleres que imparta el Instituto\nMunicipal de la Mujer de Playas de\nRosarito.................................. 1.00 VEZ\nb).- Por conferencias que imparta el Instituto\nMunicipal de la Mujer de Playas de\nRosarito.................................. 0.60 a 2.50 VECES\nc).- Por participar en evento organizado por el\nInstituto Municipal de la Mujer de Playas de Rosarito, Baja California............. 1.50 a 10.00 VECES este Apartado F, estarán sujetos a condonación total o parcial, siempre y cuando medie la autorización de la autoridad municipal, previo estudio socioeconómico.\nG.- INSTITUTO MUNICIPAL DE LA JUVENTUD DE PLAYAS DE ROSARITO\nPlayas de Rosarito, Baja California, se cobrarán de acuerdo a la siguiente:\nACTUALIZACIÓN VIGENTE\na).- Por eventos culturales organizados por el\nInstituto Municipal de la Juventud del\nMunicipio de Playas de Rosarito, Baja\nCalifornia, por participante.............. 1.00 VEZ\nLos Derechos causados por la prestación de los servicios que establece este Apartado G, estarán sujetos a condonación total o parcial, siempre y cuando medie la autorización de la autoridad municipal, previo estudio socioeconómico.\nH.- INSTITUTO MUNICIPAL DE PLANEACIÓN DE PLAYAS DE ROSARITO\nLos servicios que presta el Instituto Municipal de Planeación de\nPlayas de Rosarito, se cobrarán de acuerdo a la siguiente:\nACTUALIZACIÓN VIGENTE\n1.- Por evaluación de estudios de impacto urbano y emisión de dictamen para la implementación, previo al inicio de trámites, hasta por 2 revisiones:\na).- Habitacional, económico (socialpopular), hasta 1,000 M² de construcción......................... 40.00 VECES\nb).- Habitacional, económico (socialpopular) de 1,001 M² hasta 5,000 M² de construcción...................... 133.00 VECES\nc).- Habitacional, económico (socialpopular) más de 5,001 M² de construcción......................... 189.00 VECES\nd).- Habitacional, hasta 1,000 M² de construcción......................... 100.00 VECES\ne).- Habitacional, de 1,001 M² hasta 5,000\nM² de construcción................... 140.00 VECES\nf).- Habitacional, más de 5,001 M² de construcción......................... 201.00 VECES\ng).- Habitacional, turístico hasta 5,000 M² de construcción...................... 168.00 VECES\nh).- Habitacional, turístico más de 5,001\nM² de construcción................... 241.00 VECES\ni).- Mixto hasta 5,000 M² de construcción. 175.00 VECES\nj).- Mixto más de 5,001 M² de construcción 250.00 VECES\nk).- Comercio, servicios y equipamiento hasta 5,000 M² de construcción....... 140.00 VECES\nl).- Comercio, servicios y equipamiento más de 5,001 M² de construcción.......... 201.00 VECES\nm).- Industrial........................... 201.00 VECES\nn).- Especial............................. 455.00 VECES\no).-Infraestructura...................... 325.00 VECES\np).- Usos de suelo en modalidad de fraccionamiento, hasta diez hectáreas............................ 250.00 VECES\nq).- Adicional al inciso inmediato anterior, por hectárea adicional..... 3.00 VECES\n2.- Por evaluación de estudios de impacto urbano y emisión de dictamen para el cambio de uso de suelo, previo al inicio de los trámites, hasta por 2 revisiones:\na).- Industrial........................... 900.00 VECES\nb).- Habitacional, económico (socialpopular)............................. 490.00 VECES\nc).- Habitacional unifamiliar y multifamiliar........................ 510.00 VECES\nd).- Habitacional turístico............... 750.00 VECES\ne).- Mixto................................ 750.00 VECES\nf).- Comercio, servicios y equipamiento... 605.00 VECES\ng).- Especial e infraestructura........... 900.00 VECES\n3.- Por evaluación de estudios de impacto urbano y emisión de dictamen para la densificación, previo al inicio de los trámites, hasta por 2 revisiones:\na).- Habitacional, económica (socialpopular) hasta 5,000 M² de construcción......................... 182.00 VECES\nb).- Habitacional, económica (socialpopular) más de 5,001 M² de construcción......................... 302.00 VECES\nc).- Habitacional, hasta 1,000 M² de construcción......................... 200.00 VECES\nd).- Habitacional, de 1,001 M² hasta 5,000\nM² de construcción.................. 282.00 VECES\ne).- Habitacional, de 5,001 M² hasta\n10,000 M² de construcción........... 402.00 VECES\nf).- Habitacional, más de 10,001 M² de construcción........................ 602.00 VECES\ng).- Habitacional, turístico hasta 5,000 M² de construcción...................... 302.00 VECES\nh).- Habitacional, turístico de 5,001 M² hasta 10,000 M² de construcción..... 402.00 VECES\ni).- Habitacional, turístico más de 10,001\nM² de construcción................... 602.00 VECES\nj).- Mixto hasta 5,000 M² de construcción. 282.00 VECES\nk).- Mixto más de 5,001 M² de construcción 402.00 VECES\nl).- Usos de suelo en modalidad de fraccionamiento, hasta diez hectáreas............................ 602.00 VECES\nm).- Adicional al inciso inmediato anterior, por hectárea adicional..... 3.00 VECES\n4.- Por evaluación de estudios de impacto urbano y emisión de dictamen para intensificación, previo al inicio de trámites, hasta por 2 revisiones:\na).- Industrial........................... 750.00 VECES\nb).- Mixto................................ 450.00 VECES\nc).- Comercio, servicios y equipamiento... 550.00 VECES\nd).- Especial e infraestructura........... 900.00 VECES\n5.- Por elaboración de factibilidad de desarrollo y emisión de dictamen para implementación, previo al inicio de los trámites:\na).- Comercial, mixto, industrial o infraestructura...................... 50.00 VECES\nb).- Habitacional......................... 125.00 VECES\nc).- Fraccionamiento y/o conjunto comercial 125.00 VECES\nd).- Especial............................. 125.00 VECES\n6.- Por elaboración de factibilidad de desarrollo y emisión de dictamen para cambio de uso de suelo, previo al inicio de los trámites:\na).- Comercial, mixto o industrial........ 125.00 VECES\nb).- Habitacional......................... 185.00 VECES\nc).- Fraccionamiento y/o conjunto comercial 185.00 VECES\nd).- Especial............................. 185.00 VECES\n7.- Por emisión de opinión técnica de congruencia con respecto de acciones de urbanización en las zonas de conurbación metropolitana:\na).- Por uso habitacional mixto o turístico, hasta 10,000 M²........... 60.00 VECES\nb).- Por uso industrial, especial o infraestructura urbana, hasta 10,000\nM²................................... 120.00 VECES\nc).- Por uso de comercio, servicios o equipamiento, hasta 10,000 M²........ 70.00 VECES\nd).- Por cada 10,000 M² adicionales en los usos señalados en los incisos a, b y c de este numeral...................... 5.00 VECES\n8.- Por evaluación y emisión de dictamen técnico, por concepto de:\na).- Programa Parcial de Crecimiento...... 500.00 VECES\nb).- Programa Parcial Comunitario......... 500.00 VECES\nc).- Programa Parcial de Desarrollo\nUrbano............................... 900.00 VECES\nd).- Plan Maestro Urbano, hasta 100 hectáreas............................ 450.00 VECES\ne).- Plan Maestro Urbano, mayor a 101 hectáreas............................ 900.00 VECES\nf).- Plan Integral de Mejoramiento\nBarrial.............................. 250.00 VECES\n9.- Por evaluación de estudio de impacto a movilidad y seguridad vial y emisión de dictamen técnico, previo al inicio de trámites, hasta por 2 revisiones:\na).- Para usos de suelo, exceptuando industriales y especiales, a desarrollarse en predios particulares, de hasta 1,000 M² de construcción o hasta 10 viviendas en casos de usos habitacionales y que no implican la creación de nuevas vialidades........ 100.00 VECES\nb).- Para usos de suelo, exceptuando industriales y especiales, a desarrollarse en predios particulares, mayores a 1,000 M² de construcción o de más de 10 viviendas en casos de usos habitacionales y que no implican la creación de nuevas vialidades........................... 145.00 VECES\nc).- Para usos de suelo industriales y especiales, a desarrollarse en predios particulares y que no implican la creación de nuevas vialidades........ 201.00 VECES\nd).- Para acciones de urbanización de hasta\n10 hectáreas, incluyendo fraccionamientos y aquellos usos que implican la creación de nuevas vialidades........................... 201.00 VECES\ne).- Adicional al inciso inmediato anterior, por cada 10 hectáreas adicionales.......................... 5.00 VECES\n10.- Por la emisión de certificado de Derechos adquiridos sobre el uso de suelo, previo a la actualización del Programa de Desarrollo\nUrbano del Centro de Población de Playas de\nRosarito o del Programa de Desarrollo\nUrbano del Centro de Población de Primo\nTapia, para complementar trámites ante la\nDirección de Administración Urbana:\na).- Hasta 10,000 M²...................... 40.00 VECES\nb).- Por cada 10,000 M² adicionales....... 5.00 VECES\n11.- Otros servicios que presta el Instituto\nMunicipal de Planeación de Playas de\nRosarito, Baja California, se cobrará de acuerdo a la siguiente tabla:\na).- Plan o Programa de Desarrollo Urbano versión técnica digitalizado en formato PDF.......................... 25.00 VECES\nb).- Mapa digital de plan o programa...... 15.00 VECES\nc).- Mapa temático CENSO 2020............. 25.00 VECES\nd).- Integración de información socioeconómica y equipamiento urbano 3 variables radio de influencia........ 90.00 VECES\ne).- Por variable adicional socioeconómica y equipamiento urbano................ 22.00 VECES\nf).- Por radio o kilómetro adicional...... 22.00 VECES\ng).- Por emisión de constancia de no ser zona de alto riesgo.................. 50.00 VECES\nh).- Por emisión de constancia de no afectación por declaratoria, moratoria o restricción........................ 30.00 VECES\ni) Por emisión de dictamen de congruencia respecto al sistema vial propuesto en acciones de urbanización, de hasta 10 hectáreas, con los planes y programas de desarrollo urbano del Municipio de\nPlayas de Rosarito................... 20.00 VECES\nj).- Adicional al inciso anterior, por cada\n10 hectáreas......................... 20.00 VECES\nk).- Por plano o mapa digital con hasta tres variables de información de plan o programa de desarrollo urbano........ 25.00 VECES\nl).- Por capa de información adicional.... 03.00 VECES\nm).- Por capa de información en formato kmz o shp................................ 07.00 VECES\nn).- Por factibilidad de desarrollo cuando no se tiene definida una actividad, uso, densidad o intensidad........... 150.00 VECES\no).- Por expedición de copia de documento oficial............................. 1.45 VECES\n12.- Por dictamen de impacto urbano para asentamientos humanos que se encuentran en el programa de regularización............. 201.00 VECES\n13.- Por dictamen de impacto urbano para cambio de uso de tierra común a asentamiento humano.................................... 201.00 VECES\n14.- Inscripción al registro de peritos en desarrollo urbano y peritos en movilidad y seguridad vial............................ 37.00 VECES\n15.- Revalidación anual al registro de peritos en desarrollo urbano y peritos en movilidad y seguridad vial.......................... 18.00 VECES\nPara servicios previstos en los numerales 1, 2, 3, 4, 5, 6, 7, 8 y 9 del presente Artículo, cuando sean solicitados por dependencias de la administración pública federal, estatal o municipal, estarán exentos.\nARTÍCULO 52.- Los servicios que presten los organismos\nLey, causarán Derechos, los cuales se estarán a lo dispuesto en los\nArtículos 7, 7 BIS y demás relativos de la Ley de Hacienda Municipal del Estado de Baja California.\nSECCIÓN TERCERA\nACCESORIOS DE DERECHOS\n22.- GASTOS DE EJECUCIÓN SOBRE DERECHOS\nARTÍCULO 53.- Los gastos de ejecución se cobrarán a quien se le requiera por haber incurrido en incumplimiento de obligaciones del pago de Derechos no satisfechas dentro de los plazos legales, una vez iniciado el Procedimiento Administrativo de Ejecución que señala la\nLey de Hacienda Municipal del Estado de Baja California.\nEn ningún expediente administrativo de ejecución, los gastos serán menores de 2.00 veces la Unidad de Medida y Actualización vigente, ni excederán de 500.00 veces la Unidad de Medida y Actualización vigente por los honorarios del ejecutor o ejecutores que intervengan. Los gastos por impresiones, publicaciones y cualquier otra erogación que, con el carácter de extraordinaria, sea necesaria para el éxito el procedimiento de ejecución, se liquidarán por separado.\n23.- RECARGOS SOBRE DERECHOS\nARTÍCULO 54.- La tasa de recargos en Derechos en caso de prórroga será del 1% mensual, y será incrementada a un 2% tratándose de mora.\nLos recargos se causarán hasta por 5 años.\nSECCIÓN CUARTA\nLIQUIDACIÓN O PAGO\n24.- DERECHOS CAUSADOS EN EJERCICIOS FISCALES ANTERIORES PENDIENTES\nDE LIQUIDACIÓN O PAGO\nARTÍCULO 55.- Los Derechos no pagados en el Ejercicio Fiscal en que se causaron se cobrarán aplicado en cuanto al fondo, las Leyes\nHacienda Municipal del Estado de Baja California o en su caso, el procedimiento judicial que corresponda.\nCAPÍTULO VI\nPRODUCTOS\nSECCIÓN PRIMERA\nPRODUCTOS\n1.- SUMINISTRO DE FORMAS DIVERSAS PARA TRÁMITES ADMINISTRATIVOS\nARTÍCULO 56.- Ingresos obtenidos por el suministro de formas impresas tales como solicitudes que se utilizan en trámites administrativos en las Oficinas Municipales, se pagarán a razón de 0.25 veces la Unidad de Medida y Actualización vigente por forma impresa, en la caja recaudadora de la Tesorería Municipal.\n2.- OTRAS ACTIVIDADES DEL GOBIERNO MUNICIPAL, QUE NO CORRESPONDAN\nA SUS FUNCIONES PROPIAS DE DERECHO PÚBLICO\nARTÍCULO 57.- Las rentas que produzcan los bienes propiedad del\nMunicipio y que sean susceptibles de ser arrendados, se pagarán con base en los contratos de arrendamientos que se celebren con cada uno de los inquilinos y el Ayuntamiento, cubriéndose el importe de la renta mensual los primeros cinco días hábiles del mes correspondiente.\nARTÍCULO 58.- Las gestiones o trámites que se realicen a través de oficinas municipales con dependencias federales o estatales, se cubrirán al momento de su solicitud, y se estará a la siguiente:\nACTUALIZACIÓN VIGENTE\na).- Recepción de documentación para trámite de\nExpedición de Pasaporte Mexicano en la\nOficina Municipal de Enlace.............. 3.00 VECES\nb).- Recepción de documentación para otros trámites en la Oficina Municipal de\nEnlace................................... 5.00 VECES\n3.- ORGANISMOS PÚBLICOS DESCENTRALIZADOS Y/O PARAMUNICIPALES\nARTÍCULO 59.- Los rendimientos producidos por organismos descentralizados y/o paramunicipales, se percibirán cuando lo decreten y se exhiban, conforme a sus respectivos regímenes interiores.\nARTÍCULO 60.- Los productos generados por los rendimientos descentralizados y/o paramunicipales.\nARTÍCULO 61.- Los productos generados por la venta de artículos deportivos, uniformes deportivos y artículos de hidratación por las\nParamunicipales, se pagarán conforme a los tabuladores siguientes:\nACTUALIZACIÓN VIGENTE\na).- Venta de artículos de hidratación, por pieza..................................... 0.10 a 0.60 VECES\nb).- Venta de uniformes deportivos, por pieza.. 2.50 a 15.00 VECES\nc).- Venta de artículos deportivos, por pieza.. 0.25 a 15.00 VECES\nARTÍCULO 62.- Los productos generados por la venta de desayunos, despensas, que brinde el Sistema para el Desarrollo Integral de la\nFamilia, se pagarán conforme a los tabuladores siguientes:\nACTUALIZACIÓN VIGENTE\na).- Venta de alimentos en Estancia Casa del\nAbuelo, por porción....................... 0.15 a 0.45 VECES\nb).- Venta de despensa, por unidad............. 0.00 VECES\nc).- Venta de desayuno frío, por porción....... 0.00 VECES\nd).- Venta de desayuno caliente, por porción... 0.00 VECES\ne).- Renta de autobús de pasajeros por evento.. 29.00 a\n92.00 VECES\n4.- BIENES MOSTRENCOS\nARTÍCULO 63.- Ingresos obtenidos por los bienes mostrencos que se rematen o vendan de acuerdo a las disposiciones relativas, así como la venta de subproductos de ganado sacrificado.\n5.- DEL PISO\nARTÍCULO 64.- Las personas físicas o morales que previa autorización de la autoridad municipal correspondiente hagan uso del piso, de instalaciones subterráneas o áreas en las vías públicas para la realización de actividades comerciales o de prestación de servicios en forma permanente o temporal, pagarán los Productos correspondientes conforme a la siguiente:\nACTUALIZACIÓN VIGENTE\nI.- Casetas telefónicas por cada una, debiendo realizar el pago anualizado dentro de los primeros 2 meses del Ejercicio Fiscal..... 12.00 VECES\nII.- Instalaciones de infraestructura, por metro lineal, anualmente dentro de los primeros dos meses del Ejercicio\nFiscal....................................\na).- Redes subterráneas: a.1).- Telefonía..................... 0.001 VECES a.2).- Transmisión de datos.......... 0.001 VECES a.3).- Transmisión de señales de televisión por cable.......... 0.001 VECES a.4).- Distribución de gas........... 0.001 VECES\nb).- Redes visibles de: b.1).- Telefonía..................... 0.002 VECES b.2).- Transmisión de datos.......... 0.002 VECES b.3).- Transmisión de señales de televisión por cable.......... 0.002 VECES\nSECCIÓN SEGUNDA\nPRODUCTOS DE CAPITAL\n6.- PRODUCTOS FINANCIEROS\n7.- PRODUCTOS CAUSADOS EN EJERCICIOS FISCALES ANTERIORES PENDIENTES\nDE LIQUIDACIÓN O PAGO\nARTÍCULO 65.- Los Productos no pagados en el Ejercicio Fiscal en que se causaron se cobrarán aplicado en cuanto al fondo, las Leyes vigentes a la fecha en que se generaron y en cuanto a la forma mediante el procedimiento administrativo de ejecución que establece la Ley de\nHacienda Municipal del Estado de Baja California o en su caso, el procedimiento judicial que corresponda.\nCAPÍTULO VII\nAPROVECHAMIENTOS\nSECCIÓN PRIMERA\nAPROVECHAMIENTOS\n1.- MULTAS\nARTÍCULO 66.- Las que se contemplan en los reglamentos municipales y las que deriven por el incumplimiento de las disposiciones fiscales, asimismo, la Autoridad Municipal al hacer efectiva la sanción impuesta por las diversas dependencias municipales, por violaciones a los reglamentos emitidos por el Ayuntamiento, y al hacer efectivas dichas infracciones mediante el Procedimiento Administrativo de Ejecución, podrá apegarse a lo establecido por el Artículo 88 de la Ley de\nHacienda Municipal del Estado de Baja California.\n2.- REINTEGROS E INDEMNIZACIONES.\nARTÍCULO 67.- El cheque recibido por las autoridades fiscales que sea presentado en tiempo y no sea pagado, dará lugar al cobro del monto de éste, y se exigirá independientemente de los demás conceptos a que se refiere este Artículo. Para tal efecto, la Recaudación de Rentas\nMunicipal requerirá al librador del cheque para que, dentro de un plazo de tres días, efectúe el pago junto con la mencionada indemnización del 20%, o bien, acredite fehacientemente, con las pruebas documentales procedentes, que se realizó el pago o que dicho pago no se realizó por causas exclusivamente imputables a la institución de crédito.\nTranscurrido el plazo señalado sin que se obtenga el pago o se demuestre cualquiera de los supuestos antes señalados, la autoridad fiscal requerirá y cobrará el monto del cheque, la indemnización señalada y los demás accesorios que correspondan, mediante el procedimiento administrativo de ejecución, sin perjuicio de la responsabilidad que en su caso procediere.\n3.- DONACIONES, CESIONES, HERENCIAS Y LEGADOS A FAVOR DEL MUNICIPIO.\na).- Donaciones, Cesiones, Herencias y Legados a favor de las\nParamunicipales.\n4.- OTORGAMIENTO Y USUFRUCTO DE DERECHOS.\n5.- RECUPERACIÓN PARCIAL DE PRIMAS DE SEGUROS DE VIDA.\n6.- OTROS APROVECHAMIENTOS.\n7.- CAUCIONES, FIANZAS Y DEPÓSITOS CUYA PÉRDIDA SE DECLARE POR\nRESOLUCIÓN FIRME.\n8.- OTROS APROVECHAMIENTOS DE CAPITAL.\nSECCIÓN SEGUNDA\nAPROVECHAMIENTOS PATRIMONIALES\n9.- CONTRAPRESTACIONES DE CONCESIONES, EXPLOTACIÓN O\nGOBIERNO MUNICIPAL\nARTÍCULO 68.- La renta de los módulos o espacios para exhibición, presentación o comercialización de productos o servicios en expos, ferias, fiestas patrias y demás eventos especiales organizados o inmuebles propiedad del Gobierno Municipal, será fijada acorde a la siguiente:\nACTUALIZACIÓN VIGENTE\na).- Los módulos de particulares, ya sea personas físicas o morales, en interiores o en patio central de la Casa Municipal pagarán por día........................... 2.00 VECES\nb).- Los módulos de particulares, ya sea personas físicas o morales en exteriores pagarán por día........................... 20.00 VECES\nc).- Los módulos interiores o exteriores de dependencias municipales u otras entidades de gobierno............................... EXENTO\nd).- Por suministro, colocación, instalación o uso de templetes o entarimados para eventos privados con o sin fines de lucro por día: d.1).- De 1.00 M² hasta 35.00 M²......... 8.00 VECES d.2).- De 35.01 M² hasta 72.00 M²........ 12.00 VECES d.3).- De 72.01 M² en adelante........... 16.00 VECES\nARTÍCULO 69.- La renta de bienes muebles e inmuebles que estén a cargo del Instituto Municipal del Deporte de Playas de Rosarito, Baja\nCalifornia, será fijada en los contratos que se celebren entre ambas partes, por distintos conceptos acorde a sus tabuladores conforme a la siguiente:\nACTUALIZACIÓN VIGENTE\na).- Renta de salón de Centro de\nFortalecimiento de Rosarito cuota mensual............................... 10.00 a 74.50 VECES\nb).- Renta de salón Auditorio de la Unidad\nDeportiva por evento.................. 22.50 a 74.50 VECES\nc).- Renta de Espacio Comercial para cafetería o tienda, pagarán cuota mensual............................... 7.45 a 74.30 VECES\nd).- Renta de Cancha de Fútbol 7 pagarán por evento................................ 12.00 a 70.00 VECES\ne).- Renta de Cancha de Fútbol Soccer pagarán por evento.................... 15.00 a 74.50 VECES\nf).- Renta de Pista de Atletismo pagarán por evento................................ 10.00 a 74.50 VECES\ng).- Renta de Cancha de Tenis, Centro\nTenístico de Alto Rendimiento, mensual............................... 100.00 a 300.00 VECES\nh).- Renta de Lienzo Charro Rosarito, por evento................................ 10.00 a 300.00 VECES\ni).- Renta de Espacio Publicitario en\nExterior pagarán cuota mensual........ 10.00 a 100.00 VECES\nj).- Renta de Espacio del Espectacular pagarán cuota anual................... 179.00 a 400.00 VECES\nk).- Renta de Espacio Publicitario Interior de unidades pagarán cuota mensual..... 3.00 a 60.00 VECES\nl).- Renta de Transporte Servicio Local pagarán por evento.................... 15.00 a 100.00 VECES\nm).- Renta de Transporte Servicio Foráneo pagarán por evento.................... 40.00 a 150.00 VECES\nn).- Renta de Centro Acuático Rosarito, mensual............................... 230.00 a 3,000.00 VECES\nARTÍCULO 70.- La renta de inmuebles por exhibiciones, presentaciones o comercialización de productos o servicios en expos, ferias, fiestas patrias, festivales y demás eventos especiales organizados o coordinados por el Instituto Municipal de Arte y Cultura de Rosarito, forma siguiente:\nACTUALIZACIÓN VIGENTE\na).- Arrendamiento de Foro Interior por día....................................... 8.00 a 30.00 VECES\nb).- Arrendamiento de Foro Exterior por día....................................... 8.00 a 30.00 VECES\nc).- Arrendamiento de Salones por día.......... 7.00 a 8.00 VECES\nd).- Los Módulos de Particulares, sean personas físicas o morales en exteriores pagarán por día....................................... 8.00 a 25.00 VECES\ne).- Los Módulos Interiores o Exteriores, de dependencias municipales.................. EXENTO\nf).- Los Módulos Interiores o Exteriores, de patrocinadores del mismo evento........... EXENTO\n10.- INGRESOS POR VENTA DE BIENES PATRIMONIALES\nARTÍCULO 71.- El Ayuntamiento podrá disponer de bienes patrimoniales municipales, para ponerlos en venta con pago en una sola exhibición o en parcialidades fijas mediante suscripciones de contrato, mismo que no podrá exceder los 5 años, con el financiamiento que para tales efectos sea aprobado en la venta por Cabildo.\nValor Fiscal, cuando el primero resulte inferior al segundo.\nSECCIÓN TERCERA\nACCESORIOS DE APROVECHAMIENTOS\n11.- GASTOS DE EJECUCIÓN SOBRE APROVECHAMIENTOS\nARTÍCULO 72.- Los gastos de ejecución se cobrarán a quien se le fiscales no satisfechas dentro de los plazos legales, una vez iniciado\nHacienda Municipal del Estado de Baja California.\nEn ningún expediente administrativo de ejecución, los gastos serán menores de 2.00 veces la Unidad de Medida y Actualización vigente, ni excederán de 500.00 veces la Unidad de Medida y Actualización vigente por los honorarios del ejecutor o ejecutores que intervengan. Los gastos por impresiones, publicaciones y cualquier otra erogación que, con el carácter de extraordinaria; sea necesaria para el éxito del procedimiento de ejecución, se liquidarán por separado.\n12.- RECARGOS SOBRE APROVECHAMIENTOS\nARTÍCULO 73.- La tasa de recargos en caso de prórroga será del 1% mensual y será incrementada a un 2% tratándose de mora. Los recargos se causarán hasta por 5 años.\nSECCIÓN CUARTA\nAPROVECHAMIENTOS CAUSADOS EN EJERCICIOS FISCALES ANTERIORES\nPENDIENTES DE LIQUIDACIÓN O PAGO\n13.- APROVECHAMIENTOS CAUSADOS EN EJERCICIOS FISCALES ANTERIORES\nPENDIENTES DE LIQUIDACIÓN O PAGO\nARTÍCULO 74.- Los Aprovechamientos no pagados en el Ejercicio Fiscal en que se causaron, se cobrarán aplicando en cuanto al fondo, las caso, el procedimiento judicial que corresponda.\nCAPÍTULO VIII\nINGRESOS POR VENTAS DE BIENES, PRESTACIÓN DE SERVICIOS Y OTROS\nINGRESOS\n1.- INGRESOS POR VENTA DE BIENES, PRESTACIÓN DE SERVICIOS PRODUCIDOS\nCAPÍTULO IX\nPARTICIPACIONES, APORTACIONES, CONVENIOS, INCENTIVOS DERIVADOS DE\nSECCIÓN PRIMERA\nPARTICIPACIONES\n1.- PARTICIPACIONES EN IMPUESTOS FEDERALES\n2.- PARTICIPACIONES EN IMPUESTOS ESTATALES:\na).- Por Convenios con el Gobierno del Estado para la Realización de Obras.\nb).- Por Otros Impuestos o Ingresos del Estado, que señalen las\nLeyes, Acuerdos o Convenios que las Regulen.\nc).- Por Convenios de los Organismos Públicos Descentralizados y/o Paramunicipales con el Gobierno del Estado para la\nRealización de Obras.\nSECCIÓN SEGUNDA\nAPORTACIONES\nY SERVICIOS PÚBLICOS, O PROGRAMAS ESPECIALES, INCLUYENDO LAS QUE\nTENGAN PARTICIPACIÓN DE LAS PARAMUNICIPALES.\n4.- APORTACIONES FEDERALES DEL RAMO 33:\na).- Fondo de Aportaciones para la Infraestructura Social\nMunicipal.\nb).- Fondo de Aportaciones para el Fortalecimiento de los\nMunicipios.\nc).- Las que reciban los Organismos Públicos Descentralizados y/o\nParamunicipales de Aportaciones Municipales, Estatales o\nFederales.\nd).- Otras que reciban el Municipio y los Organismos Públicos\nDescentralizados y/o Paramunicipales.\nSECCIÓN TERCERA\nCONVENIOS\n5.- OTROS INGRESOS POR CONVENIOS FEDERALES\na).- Otros Ingresos por Convenios Federales Efectuados con los\nOrganismos Públicos Descentralizados y/o Paramunicipales.\n6.- OTROS INGRESOS POR CONVENIOS ESTATALES\na).- Otros Ingresos por Convenios Estatales Efectuados con los\nOrganismos Públicos Descentralizados y/o Paramunicipales.\n7.- OTROS INGRESOS POR CONVENIOS MUNICIPALES\na).- Otros Ingresos por Convenios Municipales Efectuados con los\nOrganismos Públicos Descentralizados y/o Paramunicipales.\nSECCIÓN CUARTA\n8.- OTROS INGRESOS POR INCENTIVOS DERIVADOS DE LA COLABORACIÓN FISCAL.\nSECCIÓN QUINTA\nFONDOS DISTINTOS DE APORTACIONES\n9.- OTROS INGRESOS POR FONDOS DISTINTOS DE APORTACIONES.\nCAPÍTULO X\nTRANSFERENCIAS, ASIGNACIONES, SUBSIDIOS Y SUBVENCIONES\n1.- TRANSFERENCIAS, ASIGNACIONES, SUBSIDIOS Y SUBVENCIONES QUE\na).- Transferencias, Asignaciones, Subsidios y Subvenciones que\nb).- Transferencias, Asignaciones, Subsidios y Subvenciones que\nDescentralizados y/o Paramunicipales.\n2.- TRANSFERENCIAS, ASIGNACIONES, SUBSIDIOS Y SUBVENCIONES QUE\na).- Transferencias, Asignaciones, Subsidios y Subvenciones que otorgue el Gobierno Federal al Municipio.\nb).- Transferencias, Asignaciones, Subsidios y Subvenciones que otorgue el Gobierno Federal a los Organismos Públicos\nDescentralizados y/o Paramunicipales.\n3.- TRANSFERENCIAS, ASIGNACIONES, SUBSIDIOS Y SUBVENCIONES QUE\nOTORGUE EL GOBIERNO MUNICIPAL.\na).- Transferencias, Asignaciones, Subsidios y Subvenciones que otorgue el Gobierno Municipal a los Organismos Públicos\nDescentralizados y/o Paramunicipales.\nCAPÍTULO XI\nINGRESOS DERIVADOS DE FINANCIAMIENTOS\nSECCIÓN PRIMERA\nENDEUDAMIENTO INTERNO\n1.- CRÉDITOS OTORGADOS AL MUNICIPIO.\n2.- LOS PROVENIENTES DE BONOS Y OBLIGACIONES.\n3.- OTROS.\nSECCIÓN SEGUNDA\nENDEUDAMIENTO EXTERNO\n4.- OTROS CRÉDITOS OTORGADOS AL MUNICIPIO.\nSECCIÓN TERCERA\nFINANCIAMIENTO INTERNO\n5.- ADELANTO DE PARTICIPACIONES O APORTACIONES ESTATALES Y FEDERALES.\nCAPÍTULO XII\nDISPOSICIONES GENERALES\nARTÍCULO 75.- Las Participaciones de Impuestos Federales y Estatales que perciba el Municipio, serán las que fijen las Leyes, Convenios y\nAcuerdos Federales y Estatales respectivos.\nARTÍCULO 76.- La validez de los permisos y autorizaciones otorgados por el Municipio, están condicionados al exacto cumplimiento de los ordenamientos legales.\nTratándose de revalidaciones de permisos de comercio establecido, éstas deberán llevarse a cabo a más tardar el 30 de junio del Ejercicio\nFiscal corriente, debiendo comprobar que se encuentra al corriente del Impuesto Predial, certificación de bomberos, licencia de anuncios, rótulos y similares, línea amarilla, etc., quien no revalide dentro del plazo establecido se le aplicará la sanción económica prevista en la Ley de Hacienda Municipal del Estado de Baja\nCalifornia.\nARTÍCULO 77.- Los gravámenes que prevé la presente Ley, no serán motivo de exención, condonación o modificación por parte de las autoridades municipales, salvo lo dispuesto en los Artículos 5 y 28 de esta Ley o por autorización expresa del Congreso del Estado. Cuando se trate de bienes de dominio público de la Federación, del Gobierno del Estado o del Municipio estarán exentos. Con excepción de los recargos, que podrán condonarse total o parcialmente conforme al\nArtículo 110 de la Ley de Hacienda Municipal del Estado de Baja\nCalifornia. anterior sean utilizados por entidades paraestatales, Organismos\nPúblicos Descentralizados y/o Paramunicipales o por particulares, bajo cualquier título, para fines administrativos o propósitos distintos a los de su objeto público, los gravámenes que prevé esta\nLey no serán motivo de exención.\nARTÍCULO 78.- Se entiende como fecha de iniciación de operaciones de las personas físicas y de las unidades económicas, aquéllas en que se ingreso. En el caso de personas morales el día de su constitución, fecha en que se obtenga el primer ingreso.\nARTÍCULO 79.- Las personas físicas, morales o unidades económicas que ambulantes, agentes de ventas, comisionistas, repartidores concesionarios o cualquier otro nombre que se le dé al expendedor, será solidariamente responsable del pago de los Impuestos, Derechos o Multas que se originen con motivo de las actividades que ejerzan, para lo cual se constituirán en los retenedores de los Créditos\nFiscales debiendo enterarlos en la Recaudación de Rentas Municipales, dentro de los plazos que fijan las Leyes Fiscales.\nARTÍCULO 80.- Las personas físicas, morales o unidades económicas que presten los servicios de publicidad, así como los propietarios de bienes inmuebles donde se instalen anuncios y las sucursales de giros comerciales e industriales y de instituciones de crédito, seguros y fianzas serán solidariamente responsables del pago de las sanciones que se originen con motivo de los anuncios que tengan instalados en esta municipalidad por violaciones a los reglamentos respectivos.\nARTÍCULO 81.- Los gravámenes fiscales se pagarán con base a la Unidad de Medida y Actualización vigente, al momento de la solicitud de la prestación del servicio público en caso de Derechos y al momento de realizarse el hecho o la situación jurídica, en caso de Impuestos.\nARTÍCULO 82.- Para efectos de esta Ley se considerarán:\nVivienda de Interés Social: Aquélla que consista en el suelo y las construcciones adheridas a él y cuyo valor, determinado mediante avalúo bancario con antigüedad máxima de un año, no exceda de la suma\nActualización vigente elevada al año, en el Estado de Baja California.\nVivienda Popular: Aquélla que consista en el suelo y las construcciones adheridas a él y cuyo valor, determinado mediante avalúo bancario con antigüedad máxima de un año, no exceda de la suma\nActualización vigente elevada al año, en el Estado de Baja California.\nVivienda de Nivel Medio: Aquélla que consista en el suelo y las construcciones adheridas a él y cuyo valor, determinado mediante avalúo bancario con antigüedad máxima de un año, no exceda de la suma\nActualización vigente elevada al año, en el Estado de Baja California.\nVivienda de Nivel Residencial: Aquélla que consista en el suelo y las construcciones adheridas a él y cuyo valor, determinado mediante avalúo bancario con antigüedad máxima de un año, exceda de la suma\nActualización vigente elevada al año, en el Estado de Baja California.\nARTÍCULO 83.- La liquidación de créditos fiscales que arroje fracciones del peso se ajustará para que las que contengan cantidades que incluyan de 1 a 50 centavos, se ajusten a la unidad del peso inmediato inferior y, las que contengan cantidades de 51 a 99 centavos, se ajusten a la unidad del peso inmediata superior.\nARTÍCULO 84.- Las personas pensionadas, jubiladas, que acrediten su condición mediante documento expedido por institución pública, así como las personas con discapacidad, o que tengan a su cargo un familiar con alguna discapacidad y residan en el mismo domicilio y además se encuentren registradas como responsables en la credencial oficial con la que se acredite la discapacidad, indigentes, adultas mayores de 60 años, personas indígenas, viudas mayores de 50 años, mujeres jefas de familia de escasos recursos, personas liberadas por amnistías, y las que se encuentren en extrema pobreza y previo estudio socioeconómico, podrán recibir apoyos de orden social para el pago de sus contribuciones contenidas en esta Ley, con base en la normatividad vigente, así como las reglas generales de operación para el caso expedidas por la Presidencia y la Tesorería Municipal para su aplicación y con base al Presupuesto de Egresos que se apruebe.\nTratándose de personas indigentes, adultas mayores de 60 años, meses de radicar en el Municipio, y las personas con discapacidad las dependencias municipales, siempre y cuando estos vayan destinados para el Desarrollo Integral de la Familia, mismos que deberán ser remitidos a la dependencia solicitante y no a la persona. párrafo de este artículo, podrán contemplar apoyos hasta por el 100% de las contribuciones municipales a pagar incluyendo sus accesorios, descritos, pudiendo ser extensivos estos beneficios a asociaciones religiosas, instituciones de beneficencia pública o privada, asociaciones culturales, instituciones de enseñanza pública y otros contribuyentes que realicen actividades no lucrativas.\nARTÍCULO 85.- Las personas con discapacidad y las personas adultas mayores de 60 años, estarán exentas de pago del Derecho por Alumbrado\nPúblico que presta la Dirección de Servicios Urbanos, a que hace referencia el Artículo 49 de esta Ley, siempre y cuando vivan en el domicilio y tengan registrado el servicio a su nombre.\nARTÍCULO 86. – Los Contribuyentes de Impuesto Predial que durante los meses de enero a marzo del presente ejercicio fiscal validen, rectifiquen y/o actualicen su información ante la Autoridad Fiscal en conceptos de domicilio fiscal, número telefónico y/o correo electrónico, así como el uso que se le da al predio, siempre y cuando llene el Formato de autorización de descuento y que declare en el mismo que el uso del predio sea casa habitación, podrán obtener un descuento del 5% adicional a los descuentos ya establecidos en los respectivos meses de enero, febrero y marzo.\nLa autoridad no podrá otorgar este estímulo fiscal para aquellos predios que el uso no sea casa habitación. En caso de que la autoridad detecte que la información proporcionada por el contribuyente es incorrecta, inexacta o falsa, tendrá la facultad de cobrar diferencias en el impuesto, así como multas y recargos.\nARTÍCULO PRIMERO.- Las contribuciones cuyo cobro haya quedado suspendido con base a los acuerdos celebrados con el Gobierno Federal y las Leyes Fiscales de la Federación, en caso de reformas o modificaciones a estas disposiciones, que permitan el cobro de dichas contribuciones, se cobrará por este ejercicio la tasa que fija la Ley de cada contribución.\nARTÍCULO SEGUNDO.- La inspección de dispositivos de seguridad por la Fracción I del Apartado A del Artículo 44 de esta Ley, sólo dará lugar al cobro de Derechos, tratándose de la primera inspección, sin específico, en el caso de incumplimiento de los dispositivos de seguridad correspondientes.\nARTÍCULO TERCERO.- Será el Ayuntamiento quien reglamentará el uso de los rangos en los Derechos por cobrar, de acuerdo al tabulador que para dicho efecto aprueben.\nARTÍCULO CUARTO.- Los recursos que reciba la Tesorería del\nH. X Ayuntamiento de Playas de Rosarito, Baja California, correspondientes a aportaciones, participaciones u otros conceptos pendientes de enterar por parte de otras instituciones, se ingresarán bajo una partida especial según sea el caso.\nARTÍCULO QUINTO.- El Impuesto Predial se pagará por los últimos cinco años, independientemente que se encuentre requerida, embargada, siempre y cuando el pago se realice en una sola exhibición, pudiendo tener éste beneficio las claves catastrales que se encuentren en proceso judicial (siempre y cuando se desista para obtener este beneficio), el período de vigencia será el Ejercicio Fiscal 2025.\nARTÍCULO SEXTO. - El Ayuntamiento previa propuesta del Titular de la\nTesorería Municipal, mediante Acuerdo de Cabildo podrá autorizar la depuración de su padrón de rezago, una vez que se configure el plazo de prescripción contemplado en la normatividad aplicable vigente.\nARTÍCULO SÉPTIMO. - La presente Ley entrará en vigor el día primero de enero del año dos mil veinticinco.\nARTÍCULO OCTAVO.- Se exenta a las personas físicas y morales inscritas en el Programa Estatal de Vivienda 2022-2027, del pago de derechos que se causen por: factibilidades, dictámenes, certificados, autorizaciones, licencias y en general, por trámites relacionados con la construcción de vivienda social, exclusivamente para los proyectos habitacionales que cuenten con certificado expedido por el Titular de la Secretaría de Infraestructura, Desarrollo Urbano y Reordenación\nTerritorial (SIDURT), y se lleven a cabo en términos de los\nVivienda publicado en el Periódico Oficial del Estado en fecha 21 de la Secretaría de Desarrollo Agrario, Territorial y Urbano (SEDATU), Instituto Nacional del Suelo Sustentable (INSUS), Comisión Nacional de Vivienda (CONAVI), Instituto del Fondo Nacional de la Vivienda para los Trabajadores (INFONAVIT), Instituto de Seguridad y Servicios\nSociales de los Trabajadores del Estado (ISSSTE) y el Fondo de la\nTrabajadores del Estado (FOVISSSTE), en conjunto con la Entidad\nFederativa y sus Municipios.\nLos derechos a exentar se enuncian a continuación:\n1. Factibilidad de uso del suelo\n2. Certificado de libertad de gravamen\n3. Dictamen de uso del suelo\n4. Manifestación de impacto ambiental\n5. Movimiento de tierras\n6. Deslinde catastral\n7. Licencia de Construcción\n8. Régimen de Propiedad en Condominio\n9. Licencia de Fraccionamiento\n10. Certificado de número oficial\n11. Constancia de obra terminada\n12. Cambio de propietario\n13. Impuesto sobre adquisición de bienes inmuebles\nArtículo Transitorio Adicionado a los 20 días del mes de diciembre del dos mil veinticuatro.\nDIP. EVELYN SÁNCHEZ SÁNCHEZ\nDIPUTADA PRESIDENTA\nDIP. MICHELLE ALEJANDRA TEJEDA MEDINA\nDIPUTADA SECRETARIA\nARTÍCULO ÚNICO TRANSITORIO DEL DECRETO No. 73, POR EL QUE SE\nLEY DE INGRESOS DEL MUNICIPIO DE PLAYAS DE ROSARITO, BAJA CALIFORNIA,\nPARA EL EJERCICIO FISCAL 2025; PUBLICADO EN EL PERIÓDICO OFICIAL No. 22,\nLEGISLATURA; SIENDO GOBERNADORA CONSTITUCIONAL LA C. MARINA DEL PILAR\nÁVILA OLMEDA 2021-2027.\nTRANSITORIOS\nPRIMERO: La presente reforma entrará en vigor a partir del día siguiente de su publicación en el Periódico Oficial del Estado de Baja California.\nSEGUNDO: Notifíquese a la Presidenta Municipal del H. X Ayuntamiento de Playas de\nRosarito, Baja California.\nTERCERO: Remítase la presente reforma al Ejecutivo Estatal para efectos de su publicación en el Periódico Oficial del Estado de Baja California.\nDADO en Sesión Ordinaria de la XXV Legislatura en la Ciudad de Tijuana, B.C., a los veintisiete días del mes de marzo del año dos mil veinticinco.\nDIP. EVELYN SÁNCHEZ SÁNCHEZ\nPRESIDENTA\n(RÚBICA)\nDIP. MICHELLE ALEJANDRA TEJEDA MEDINA\nSECRETARIA\n(RÚBICA)\nDE CONFORMIDAD CON LO DISPUESTO POR LA FRACCIÓN I DEL ARTÍCULO\nCALIFORNIA, IMPRÍMASE Y PUBLÍQUESE.\nMEXICALI, BAJA CALIFORNIA, A LOS 31 DÍAS DEL MES DE MARZO DEL AÑO\nDOS MIL VEINTICINCO.\nMARINA DEL PILAR ÁVILA OLMEDA\nGOBERNADORA DEL ESTADO\nDE BAJA CALIFORNIA\n(RÚBRICA)\nALFREDO ÁLVAREZ CÁRDENAS\nSECRETARIO GENERAL DE GOBIERNO\nDEL ESTADO DE BAJA CALIFORNIA\n(RÚBRICA)",
  "ordenamiento": "REGLAMENTO",
  "jurisdiccion": "BAJA CALIFORNIA",
  "fuente_oficial": "Periódico Oficial",
  "FECHA PER OFIC": "2025/04/11",
  "ESTATUS": "VIGENTE",
  "TOMO": "TOMO_II",
  "URL": "https://www.congresobc.gob.mx/Documentos/ProcesoParlamentario/Leyes/TOMO_II/20250411_LEYINGRESOPLAYASDEROSARITO2025.PDF",
  "es_escaneado": false,
  "tiene_tablas": true,
  "materia": [
    "financiero",
    "fiscal",
    "económico"
  ]
}