{
  "titulo": "Ley DE DESARROLLO FORESTAL SUSTENTABLE PARA EL ESTADO DE BAJA CALIFORNIA",
  "Contenido": "BAJA CALIFORNIA\nTomo CXVII, Sección II\nCAPITULO PRIMERO\nDISPOSICIONES GENERALES\nARTÍCULO 1.- La presente Ley es de orden público e interés social, sus disposiciones regirán en todo el Estado de Baja California, y tiene por objeto regular el ejercicio de las atribuciones que en materia forestal le competen al estado y sus municipios bajo el principio de concurrencia previsto en la fracción XXIX-G del artículo 73 de la Constitución Política de los Estados Unidos Mexicanos y la Ley General de Desarrollo Forestal Sustentable.\nARTÍCULO 2.- La presente Ley tiene como objetivos establecer las bases para:\nI.- Diseñar, formular y aplicar la política estatal forestal en coordinación con los principios y criterios definidos por la federación y los municipios;\nII.- Elaborar y ejecutar los planes y programas estatales en materia forestal;\nIII.- Promover la organización, conservación, fomento y mejoramiento de las actividades que incidan al desarrollo forestal sustentable;\nIV.- Impulsar la protección, mantenimiento y restauración de suelos, ecosistemas y recursos forestales así como la ordenación y el manejo forestal;\nV.- Garantizar el aprovechamiento, uso y restauración de los recursos forestales;\nVI.- Brindar el servicio de asistencia técnica integral a los productores forestales;\nVII.- Apoyar la investigación científica y tecnológica aplicada a las actividades forestales;\nVIII.- Establecer las bases para la creación, operación y funcionamiento de mecanismos de participación de los productores y sujetos dedicados a la actividad forestal;\nIX.- Difundir la cultura, educación y capacitación para el manejo sustentable de los recursos forestales;\nX.- Procurar y promover que a las comunidades y pueblos indígenas, se les respete su derecho preferente sobre los recursos forestales en los lugares que ocupen y habiten;\nXI.- Elaborar, monitorear y mantener actualizado el Inventario Estatal Forestal y de\nSuelos;\nXII.- Integrar el Sistema Estatal de Información Forestal e incorporar su contenido al\nSistema Nacional de Información Forestal;\nLey de Desarrollo Forestal Sustentable para el Estado de Baja California. Página 1 artículo 13 de la Ley General de Desarrollo Forestal Sustentable; y\nXIV.- Establecer las infracciones y sanciones correspondientes por incumplimiento o violación a las disposiciones de esta Ley, y sus Reglamentos.\nARTÍCULO 3.- Además de las definiciones contenidas en el artículo 7 de la Ley\nGeneral de Desarrollo Forestal Sustentable, para los efectos de esta Ley, se entenderá por:\nI.- Acahual: Toda aquella vegetación derivada de intervenciones a las áreas arboladas cuya constitución no es leñosa;\nII.- Consejo: El Consejo Estatal Forestal;\nIII.- Cuenca hidrológico-forestal: La unidad de espacio físico de planeación y desarrollo, que comprende el territorio donde se encuentran los ecosistemas forestales y donde el agua fluye por diversos cauces y converge en un cauce común, constituyendo el componente básico de la región forestal, que a su vez se divide en subcuencas y microcuencas;\nIV.- Degradación del suelo: Proceso que describe el fenómeno causado por el hombre, que disminuye la capacidad presente y futura del suelo, para sustentar vida vegetal, animal y humana;\nVI.- Erosión del suelo: Desprendimiento, arrastre y depósito de las partículas del suelo por acción del agua y el viento;\nVII.- Inventario Estatal: El Inventario Estatal Forestal y de Suelos;\nVIII.- Leña: Materia prima maderable proveniente de la vegetación forestal que se utiliza como material combustible y para carbonización, la cual puede ser en rollo o en raja;\nIX.- Ley: La Ley de Desarrollo Forestal Sustentable para el Estado de Baja California;\nX.- Ley General: La Ley General de Desarrollo Forestal Sustentable;\nXI.- Manejo Forestal: El proceso que comprende el conjunto de acciones y procedimientos que tienen por objeto la ordenación, el cultivo, la protección, la conservación, la restauración y el aprovechamiento de los recursos forestales de un ecosistema forestal, recursos existentes en la misma;\nXII.- Ordenación forestal: La organización económica de un área forestal tomando en cuenta sus características silvícola, que implica la división espacial y temporal de las actividades del manejo forestal;\nLey de Desarrollo Forestal Sustentable para el Estado de Baja California. Página 2\nXIII.- Recursos Hídricos: Son los recursos de agua en términos de disponibilidad con que cuenta una región, siendo estos las aguas superficiales y subterráneas donde se incluyan los aspectos relacionados con los componentes del ciclo hidrológico;\nEstado de Baja California;\nXV.- Secretaría: Secretaría de Medio Ambiente y Desarrollo Sustentable;\nFracción Reformada\nXVI.- Sistema Estatal: El Sistema Estatal de Información Forestal;\nXVII.- Veda forestal: Restricción total o parcial del aprovechamiento de recursos forestales en una superficie o para una especie determinada, mediante decreto que expida el titular del Ejecutivo Federal, y\nXVIII.- Zonificación forestal: Es el instrumento en el cual se identifican, agrupan y ordenan los terrenos forestales y preferentemente forestales dentro de las cuencas, subcuencas y micro cuencas hidrológico-forestales, por funciones y subfunciones biológicas, ambientales, socioeconómicas, recreativas, protectoras y restauradoras, con fines de manejo y con el objeto de propiciar una mejor administración y contribuir al desarrollo forestal sustentable.\nArtículo Reformado\nARTÍCULO 4.- Los procedimientos establecidos por esta Ley no alterarán el régimen de propiedad establecido por la legislación de la materia.\nARTÍCULO 5.- En lo no previsto por esta ley, se aplicarán de forma supletoria y en lo conducente, las disposiciones de la Ley General, la Ley General del Equilibrio Ecológico y\nProtección al Ambiente, y la Ley de Protección al Ambiente del Estado.\nDe igual forma se considera supletoria de esta Ley, en lo conducente a los actos, notificaciones, procedimientos y resoluciones relativas a las visitas, operativos de inspecciones, infracciones, sanciones y medios de defensa, la Ley del Procedimiento para los Actos de la Administración Pública del Estado de Baja California.\nCAPÍTULO SEGUNDO\nDE LAS AUTORIDADES EN MATERIA FORESTAL\nARTÍCULO 6.- Son autoridades en materia forestal:\nI.- El Gobernador del Estado;\nII.- La Secretaría, y\nIII.- Los Municipios. conformidad con la distribución de competencias prevista en la Ley General, este\nLey de Desarrollo Forestal Sustentable para el Estado de Baja California. Página 3 ordenamiento y sus respectivos reglamentos, así como los convenios que sobre la materia suscriban.\nARTÍCULO 7.- La Secretaría tendrá las siguientes facultades y atribuciones:\nI.- Proponer, y ejecutar la política forestal en el Estado, en concordancia con la política forestal nacional;\nII.- Representar al sector forestal de la entidad en el Servicio Nacional Forestal;\nIII.- Participar en la elaboración, formulación y aplicación de programas, planes, proyectos forestales o cuencas hidrológico-forestales que no estén expresamente atribuidas a la federación o a los municipios;\nIV.- Establecer el esquema de ventanilla única para la atención eficiente de los usuarios del sector forestal;\nV.- Pr bienes y servicios ambientales de los ecosistemas forestales.\nVI.- Impulsar lomover losa participación directa de los propietarios o poseedores de los recursos forestales en la protección, conservación, restauración, vigilancia, ordenación, aprovechamiento, cultivo, transformación, y comercialización de los mismos;\nVII.- Promover convenios o acuerdos de coordinación y colaboración con el gobierno federal, con el objeto de que el Estado asuma funciones o atribuciones reservadas para la federación en la Ley General, y aquellas que tengan como finalidad la realización de acciones conjuntas en materia forestal;\nVIII.- Fomentar la silvicultura como actividad de desarrollo en la entidad;\nIX.- Colaborar en la prevención, manejo, combate, control y restauración de incendios forestales, así como en campañas contra plagas y enfermedades forestales;\nX.- Llevar a cabo acciones de prevención, capacitación y combate de incendios forestales en congruencia con el programa nacional respectivo;\nXI.- Promover y participar en la restauración de los ecosistemas forestales afectados por incendio;\nXII.- Impulsar programas de mejoramiento genético forestal;\nXIII.- Realizar y supervisar las labores de conservación, protección y restauración de los terrenos estatales forestales;\nXIV.- Elaborar y aplicar programas de reforestación y forestación en zonas protección y mantenimiento de las zonas reforestadas o forestadas;\nXV.- Llevar a cabo acciones de saneamiento de los ecosistemas forestales;\nXVI.- Prestar asesoría y capacitación en prácticas y métodos que conlleven un manejo forestal sustentable;\nLey de Desarrollo Forestal Sustentable para el Estado de Baja California. Página 4\nXVII.- Asesorar y capacitar a los propietarios y poseedores forestales en la elaboración y ejecución de programas de manejo forestal, y de plantaciones forestales comerciales, así como en la diversificación de las actividades forestales;\nXVIII.- Asesorar y orientar a ejidatarios, comuneros, pequeños propietarios, comunidades indígenas y otros productores forestales en el desarrollo de su organización, así como en la creación de empresas sociales forestales, propiciando la integración de cadenas productivas y los sistemas producto del sector;\nXIX.- Brindar atención a los asuntos relacionados con la conservación y mejoramiento del habitat natural de los pueblos y comunidades indígenas.\nXX.- Diseñar, desarrollar y aplicar instrumentos económicos para promover el desarrollo forestal de la entidad;\nXXI.- Promover e invertir en el mejoramiento de la infraestructura en las áreas forestales de la entidad;\nXXII.- Fortalecer y ampliar la participación de la producción forestal en el crecimiento económico estatal;\nXXIII.- Participar en la inspección y vigilancia forestal en la entidad, así como en las acciones de prevención y combate a la extracción ilegal y tala clandestina de los recursos forestales;\nXXIV.- Informar a las autoridades competentes y en su caso denunciar, las infracciones o delitos que se cometan en materia forestal;\nXXV.- Elaborar en el ámbito de su competencia los estudios para el establecimiento, modificación o levantamiento de vedas;\nXXVI.- Presentar estudios para el establecimiento de restricciones a la forestación y reforestación;\nXXVII.- Impulsar las promotorías de desarrollo forestal en los distritos de desarrollo rural de la entidad, y\nXXVIII.- Incorporar un sistema obligatorio de corredores verdes en las principales zonas de generación de contaminación de atmosfera de zonas urbanas de los ayuntamientos.\nXXIX.- Las demás que le atribuyan las leyes, reglamentos, decretos y acuerdos sobre la materia.\nArtículo Reformado\nARTÍCULO 8.- Cuando por razón de la materia y de conformidad con la Ley Orgánica de la Administración Pública del Estado u otras disposiciones similares, se requiera la intervención de otras dependencias, la Secretaría ejercerá sus atribuciones en coordinación con las mismas.\nLey de Desarrollo Forestal Sustentable para el Estado de Baja California. Página 5\nSECCIÓN SEGUNDA\nDE LOS MUNICIPIOS\nARTÍCULO 9.- Corresponde a los Gobiernos de los Municipios, de conformidad con la distribución de competencias previstas en esta ley, la Ley General y los reglamentos de ambas, las siguientes atribuciones:\nI.- Diseñar, formular y aplicar, en concordancia con la política nacional y estatal, la política forestal del municipio;\nII.- Aplicar los criterios de política forestal previstos en esta Ley en las zonas de jurisdicción municipal, en las materias que no estén expresamente reservadas a la\nFederación o a los Estados;\nIII.- Apoyar a la Federación y al Estado en la adopción y consolidación del Servicio\nNacional Forestal;Participar en el ámbito de sus atribuciones, en el establecimiento de sistemas y esquemas de ventanilla única de atención eficiente para los usuarios del sector:\nV.- Coadyuvar con el Estado en la realización y actualización del Inventario Estatal:\nVI.- Participar en coordinación con la federación en la zonificación forestal, comprendiendo las áreas forestales permanentes de su ámbito territorial:\nVII.- Promover programas y proyectos de educación, capacitación, investigación y cultura forestal:\nVIII.- Celebrar acuerdos o convenios de coordinación, cooperación y concertación en materia forestal\nIX.- Expedir, previo a su instalación las licencias o permisos, para el establecimiento de centros de almacenamiento o transformación de materias primas forestales en el ámbito de su competencia,\nX.- Diseñar, desarrollar y aplicar incentivos para promover el desarrollo forestal, de conformidad con esta Ley y los lineamientos de la política forestal del país;Participar y coadyuvar en las acciones de prevención y combate de incendios forestales en coordinación con los gobiernos federal y estatal, y participar en la atención, en general, de las emergencias y contingencias forestales, de acuerdo con los programas de protección civil;\nXII.- Participar en la planeación y ejecución de la reforestación, forestación, restauración de suelos y conservación de los bienes y servicios ambientales forestales;\nXIII.- Desarrollar y apoyar viveros y programas de producción de plantas;\nXIV.- Llevar a cabo, en coordinación con el Estado las acciones de saneamiento en los ecosistemas forestales;\nXV.- Promover la construcción y mantenimiento de la infraestructura en las áreas forestales del Municipio:\nLey de Desarrollo Forestal Sustentable para el Estado de Baja California. Página 6\nXVI.- Promover la participación de organismos públicos, privados y no gubernamentales en proyectos de apoyo directo al desarrollo forestal sustentable;\nXVII.- Participar, de conformidad con los acuerdos y convenios que se celebren con los gobiernos federal y de las entidades federativas, en la vigilancia forestal en el municipio;\nXVIII.- Hacer del conocimiento a las autoridades competentes, y en su caso denunciar, las infracciones, faltas administrativas o delitos que se cometan en materia forestal;\nXIX.- Participar y coadyuvar en los programas integrales de prevención y combate a la extracción ilegal y a la tala clandestina con la federación y el gobierno de la entidad;\nXX.- Regular y vigilar la disposición final de residuos provenientes de la extracción de materias primas forestales, y\nXXI.- Coadyuvar con el Estado en la incorporación de un esquema obligatorio de forestación de corredores verdes en las principales zonas de generación de contaminación de aire en zonas urbanas de los ayuntamientos.\nFracción Adicionada recorriéndose la subsecuente\nXXII.- La atención de los demás asuntos que en materia de desarrollo forestal sustentable les conceda esta Ley u otros ordenamientos.\nArtículo Reformado\nARTÍCULO 10.- Los Municipios, conforme a su reglamentación, podrán promover la integración de Consejos Municipales Forestales, como órganos de consulta, asesoramiento y concertación, en materia de planeación, supervisión, evaluación de las políticas y aprovechamiento, conservación y restauración de los recursos forestales del Municipio.\nCAPÍTULO TERCERO\nDE LA COORDINACIÓN\nARTÍCULO 11.- El Ejecutivo del Estado por conducto de la Secretaría impulsará la celebración de instrumentos, convenios o acuerdos de coordinación con la federación, con el objeto de ejercer, con la participación, en su caso, de los municipios, las funciones delegables en materia forestal conforme a la Ley General, siguientes:\nI.- Impulsar la vinculación interinstitucional en el marco del Servicio Nacional Forestal del sector rural forestal;\nII.- Programar y operar las tareas de prevención, detección y combate de incendios forestales en el Estado, así como los de control de plagas y enfermedades;\nIII.- Inspección y vigilancia forestales;\nIV.- Imponer medidas de seguridad y las sanciones a las infracciones que se cometan en materia forestal;\nLey de Desarrollo Forestal Sustentable para el Estado de Baja California. Página 7\nV.- Requerir la acreditación de la legal procedencia de las materias primas forestales;\nVI.- Otorgar los permisos y avisos para el combate y control de plagas y enfermedades;\nVII.- Recibir los avisos de aprovechamiento de recursos forestales maderables, no maderables, de forestación, y los de plantaciones forestales comerciales;\nVIII.- Autorizar el cambio de uso del suelo de los terrenos de uso forestal;\nIX.- Autorizar el aprovechamiento de los recursos forestales maderables y no maderables y de plantaciones forestales comerciales;\nX.- Dictaminar, autorizar y evaluar los programas de manejo forestal, así como evaluar y asistir a los servicios técnico forestales, o\nXI.- Evaluar el impacto ambiental de las obras o actividades forestales a que se refiere el artículo 28 de la Ley General del Equilibrio Ecológico y la Protección al Medio Ambiente.\nARTÍCULO 12.- El Ejecutivo del Estado y los Ayuntamientos podrán celebrar los instrumentos legales necesarios para el ejercicio de la actividad forestal, a efecto de que estos últimos asuman de forma concurrente con la autoridad estatal las facultades y atribuciones que sean viablemente delegables dentro de su jurisdicción, para mejorar la actividad en el sector, siempre y cuando garantice que cuenta con los recursos humanos capacitados, recursos materiales y financieros y la estructura institucional específica para atender y desarrollar las funciones que asumiría.\nARTÍCULO 13.- La Secretaría preverá en el seguimiento y evaluación de los resultados que se obtengan por la ejecución de los convenios y acuerdos a que se refiere el artículo anterior, intervenga el Consejo Estatal Forestal.\nARTÍCULO 14.- El Ejecutivo del Estado y los gobiernos municipales impulsarán y promoverán en el ámbito de su competencia, el establecimiento del sistema de ventanilla única para la atención del usuario del sector forestal.\nPor medio del sistema de ventanilla única, se brindará una atención eficiente al\nReglamento de esta Ley.\nCAPÍTULO CUARTO\nDEL CONSEJO ESTATAL FORESTAL\nARTÍCULO 15.- El Consejo fungirá como órgano de carácter consultivo, asesoramiento y concertación, en materia de planeación, supervisión, evaluación de las políticas y aprovechamiento, conservación y restauración de los recursos forestales del\nEstado, tendrá como objetivos:\nI.- Contribuir con sus opiniones al desarrollo forestal sustentable en el Estado;\nLey de Desarrollo Forestal Sustentable para el Estado de Baja California. Página 8\nII.- Presentar a las autoridades competentes, propuestas de normas en materia forestal;\nIII.- Emitir opiniones y observaciones técnicas respecto de las solicitudes de autorización de aprovechamiento de recursos forestales maderables o de forestación, en términos de la Ley General.\nIV.- Emitir opinión técnica respecto a la procedencia de cambio de uso de suelos en terrenos forestales, en términos de la Ley General;\nV.- Apoyar en la difusión de medidas de prevención y manejo de plagas y enfermedades, y\nVI.- Participar en labores de conservación y restauración de los recursos forestales y las cuencas hídricas.\nARTÍCULO 16.- El ejercicio de los objetivos del Consejo se realizará por los miembros que lo integran, en apego al Plan Estatal de Desarrollo y de acuerdo a lo establecido en las disposiciones normativas aplicables, sin perjuicio de las revisiones, dictámenes, actos o procedimientos que se deban realizar por las diversas unidades administrativas de las dependencias y entidades de la Administración Pública Estatal.\nARTÍCULO 17.- El Consejo se integrara por:\nI.- El Titular de la Secretaría, quien será su Presidente;\nII.- El Secretario de Fomento Agropecuario;\nIII.- El Secretario de Planeación y Finanzas;\nIV.- El Director de Ecología o su equivalente por cada uno de los Ayuntamientos; o en su defecto, un representante por cada Municipio del Estado;\nV.- Un representante del sector social, designado en ios (sic) términos del\nReglamento respectivo, y\nVI.- Un representante del sector académico, designado en los términos del\nReglamento; y\nVII.- El Presidente de la Comisión del Congreso del Estado responsable de la materia ambiental.\nVIII.- Un representante de la Secretaría de Medio Ambiente y Recursos Naturales;\nIX.- Un representante de la Comisión Nacional Forestal;\nX.- Un representante de la Comisión Nacional de Áreas Naturales Protegidas;\nXI.- Un representante de la Procuraduría Federal de Protección al Ambiente naturaleza de las sesiones y/o los asuntos representen conflicto de interés con sus funciones de gobierno.\nLey de Desarrollo Forestal Sustentable para el Estado de Baja California. Página 9\nEl Consejo contará con un Secretario Técnico designado por el Presidente, de entre el personal de la propia secretaría, quien deberá contar con nivel de Director de Área por lo menos.\nArtículo Reformado\nARTÍCULO 18.- Cada miembro propietario designará un suplente, quien asistirá a las sesiones del Consejo en ausencia del primero, con las facultades que a éste corresponda.\nLos miembros propietarios y suplentes del Consejo serán a título honorífico.\nARTÍCULO 19.- El Consejo, por conducto de su Presidente, podrá invitar a participar en sus sesiones a:\nI.- Titulares de otras dependencias y entidades de la Administración Pública\nFederal, Estatal y Municipal relacionadas con el sector forestal;\nII.- Centros de enseñanzas e instituciones de investigación, y tecnológicos,\nIII.- Representantes del sector organizaciones de la sociedad civil que realice actividades en materia de conservación y restauración forestal;\nIV.- Representantes del sector empresarial en materia de producción forestal o de silvicultura;\nV.- Representantes del sector profesional, prestadores de servicios profesionales a productores;\nVI.- Un representante de la Secretaría de Agricultura, Desarrollo Rural, Pesca y\nAlimentación;\nVII.- Cualquier otro que considere el Consejo.\nLos invitados a las sesiones, en términos del presente artículo participarán en las mismas con voz pero sin voto.\nArtículo Reformado\nAERÍCULO 19 BIS.- La Secretaría promoverá la interacción de este Consejo con los demás Consejos Estatales Forestales.\nArtículo Adicionado\nARTÍCULO 20.- El Consejo, sesionará en forma ordinaria cada tres meses y, extraordinariamente, cuantas veces sea necesario, a juicio de su presidente, quien emitirá la convocatoria respectiva. En la primera sesión del año, se definirá el calendario de sesiones ordinarias. miembros, y tomarán las decisiones por mayoría de votos de los presentes, salvo el referido en la fracción VII del artículo 17 quien solo contará con voz y no se considerará para integrar el quórum legal, en caso de empate quien presida la sesión tendrá voto de calidad.\nArtículo Reformado\nLey de Desarrollo Forestal Sustentable para el Estado de Baja California. Página 10\nARTÍCULO 21.- La organización y funcionamiento del Consejo, además de lo dispuesto en el presente Capítulo, así como las atribuciones y obligaciones de sus miembros, se determinarán en las disposiciones reglamentarias que deriven de esta Ley.\nCAPÍTULO QUINTO\nDEL SERVICIO ESTATAL FORESTAL\nARTÍCULO 22.- El Servicio Estatal Forestal es la instancia de coordinación entre el\nGobierno del Estado y los gobiernos municipales, y de concentración entre dichos niveles de gobierno y los particulares, que tiene por objeto la conjunción de esfuerzos, instancias, instrumentos, políticas, servicios y acciones institucionales para la atención eficiente del sector forestal.\nEl reglamento de la presente ley desarrollará las bases de coordinación, integración y funcionamiento del Servicio Estatal Forestal, procurando la participación de la Comisión\nNacional Forestal.\nARTÍCULO 23.- Para la atención y coordinación de las distintas materias del sector forestal, el Servicio Estatal Forestal contará, al menos, con los grupos de trabajo siguientes:\nI.- Inspección, protección y vigilancia forestal;\nII.- Prevención, control y combate de incendios forestales;\nIII.- Educación, capacitación e investigación, y\nIV.- Asistencia técnica forestal.\nCAPÍTULO SEXTO\nDE LA POLÍTICA ESTATAL EN MATERIA FORESTAL\nARTÍCULO 24.- El desarrollo forestal sustentable se considera un área prioritaria del desarrollo estatal, y por tanto, tendrán ese carácter las actividades públicas o privadas que se le relacionen.\nARTÍCULO 25.- La política estatal en materia forestal deberá promover el fomento y la adecuada planeación de un desarrollo forestal sustentable, entendido éste como un proceso evaluable y medible mediante criterios e indicadores de carácter ambiental, silvícola, recursos forestales sin comprometer el rendimiento, equilibrio e integridad de los ecosistemas forestales, que mejore el ingreso y la calidad de vida de las personas que regiones forestales, diversificando las alternativas productivas y creando fuentes de empleo en el sector.\nLey de Desarrollo Forestal Sustentable para el Estado de Baja California. Página 11\nEn la política que desarrolle el Ejecutivo Estatal, deberán observarse los principios y criterios obligatorios de política forestal, previstos en la Ley General.\nARTÍCULO 26.- Son instrumentos de la política estatal en materia forestal:\nI.- La Planeación del Desarrollo Forestal;\nII.- El Sistema Estatal de Información Forestal, y\nIII.- El inventario Estatal Forestal y de Suelos.\nSECCIÓN PRIMERA\nDE LA PLANEACIÓN DEL DESARROLLO FORESTAL ESTATAL\nARTÍCULO 27.- La planeación del desarrollo forestal en el Estado estará a cargo del\nGobernador a través de la Secretaría y el órgano responsable del proceso de planeación en la entidad, y por los Ayuntamientos en sus respectivas jurisdicciones, en los términos establecidos en la Ley de Planeación para el Estado, esta Ley y demás disposiciones aplicables.\nARTÍCULO 28.- La planeación del desarrollo forestal, como instrumento para el diseño y ejecución de la política forestal, comprenderá la elaboración, aplicación y seguimiento de los programas respectivos, que comprenderán los objetivos, estrategias y líneas de acción prioritarias, tomando en cuenta los criterios e instrumentos de la política nacional forestal y buscando congruencia con los programas nacionales.\nEn la elaboración de la planeación del desarrollo forestal estatal y municipal, deberán tomarse en cuenta a los consejos consultivos en la materia, en los términos de la Ley de\nPlaneación para el Estado.\nARTÍCULO 29.- Los programas que deriven del cumplimiento de esta Ley, tendrán la vigencia que se determine en cada caso, debiendo ser acorde a los plazos previstos en la\nLey de Planeación para el Estado.\nSECCIÓN SEGUNDA\nDEL SISTEMA ESTATAL DE INFORMACIÓN FORESTAL\nARTÍCULO 30.- El Sistema Estatal de Información Forestal tendrá por objeto registrar, integrar, organizar, actualizar y difundir la información relacionada con la materia forestal que sustentable y la cual estará disponible al público para su consulta.\nLa Secretaría integrará el Sistema Estatal, conforme a las normas, criterios, Ley de Desarrollo Forestal Sustentable para el Estado de Baja California. Página 12\nNaturales, y las que dicte la propia Secretaría, para que sea compatible con el Sistema\nNacional de Información Forestal al cual deberá integrar la información.\nARTÍCULO 31.- Los gobiernos municipales proporcionarán a la Secretaría en los términos que prevea el reglamento de esta ley, la información que se recabe en el cumplimiento de sus atribuciones, para que sea integrada al Sistema Estatal.\nARTÍCULO 32.- Mediante el Sistema Estatal, se deberá integrar de forma homogénea toda la información en materia forestal, incluyendo:\nI.- La contenida en el Inventario Estatal;\nII.- La contenida en la Ordenación Forestal;\nIII.- Las evaluaciones de plantaciones forestales comerciales y reforestación con propósitos de restauración y conservación;\nIV.- El uso y conocimiento de los recursos forestales, incluyendo información sobre uso doméstico y tradicional;\nV.- Los acuerdos y convenios en materia forestal;\nVI.- La información económica de la actividad forestal;\nVII.- Las investigaciones y desarrollo tecnológico;\nVIII.- La información sobre el manejo forestal para aprovechamientos maderables y no maderables persistentes y de contingencia;\nIX.- El padrón estatal de productores, aserraderos e industrias de recursos forestales;\nX.- Organizaciones e instituciones de los sectores social y privado, así como de organismos públicos relacionados con este sector;\nXI.- La relacionada con la prevención y combate de incendios forestales;\nXII.- Los programas estatales de sanidad forestal, y\nXIII.- Las demás que la Secretaría considere estratégica para la planeación y evaluación del desarrollo forestal sustentable.\nSECCIÓN TERCERA\nDEL INVENTARIO ESTATAL FORESTAL Y DE SUELOS\nARTICULO 33.- La Secretaría integrará el Inventario Estatal, el cual se deberá bienes y servicios forestales. En el Reglamento de la presente Ley se determinarán los criterios, metodología y procedimientos para su conformación y actualización, debiendo observar los establecidos para el Inventario Nacional Forestal y de Suelos.\nLey de Desarrollo Forestal Sustentable para el Estado de Baja California. Página 13\nARTÍCULO 34.- El Inventario Estatal deberá comprender la siguiente información:\nI.- La superficie y localización de terrenos forestales y preferentemente forestales con que cuenta el Estado y sus municipios, con el propósito de integrar su información estadística y elaborar su cartografía, en sus distintos niveles de ordenación y manejo;\nII.- Los terrenos forestales temporales, su superficie y localización, así como los datos de sus legítimos propietarios;\nIII.- Los tipos de vegetación forestal y de suelos, su localización, formaciones y clases, con tendencia y proyecciones que permitan clasificar y delimitar el estado actual de la degradación, así como las zonas de conservación, protección, restauración y producción forestal, en relación con las cuencas hidrológicas-forestales, las regiones ecológicas, las áreas forestales permanentes y las áreas naturales protegidas;\nIV.- La dinámica de cambio de la vegetación forestal del Estado, que permita conocer y evaluar las tasas de deforestación y de degradación y disturbio, registrando sus causas principales;\nV.- La cuantificación de los recursos forestales, incluyendo la valoración de los bienes y servicios ambientales que generen los ecosistemas forestales, así como los impactos que se ocasionen en los mismos;\nVI.- Los criterios e indicadores de sustentabilidad y degradación de los ecosistemas forestales;\nVII.- Los inventarios sobre la infraestructura forestal existente, y\nVIII.- Los demás datos que señale el Reglamento de esta Ley.\nARTÍCULO 35.- En la formulación del Inventario Estatal, se deberán considerar cuando menos los siguientes criterios:\nI.- La delimitación por cuencas y subcuencas hidrológico-forestales;\nII.- La naturaleza, características, diversidad de los ecosistemas o tipos de vegetación forestales existentes en el Estado;\nIII.- La vocación de los terrenos forestales, y\nIV.- Los desequilibrios existentes en los ecosistemas por efecto de las actividades económicas o de otras actividades humanas o fenómenos naturales.\nCAPÍTULO SÉPTIMO\nARTÍCULO 36.- La Secretaría en coordinación con la Comisión Nacional Forestal, delimitará las Unidades de Manejo Forestal, tomando como base preferentemente las cuencas, subcuencas y microcuencas hidrológico-forestales, con el propósito de lograr una\nLey de Desarrollo Forestal Sustentable para el Estado de Baja California. Página 14 ordenación forestal sustentable, una planeación ordenada de las actividades forestales y el manejo eficiente de los recursos forestales.\nGeneral y en el Reglamento de la presente Ley.\nARTÍCULO 37.- La Secretaría, en coordinación con la Comisión Nacional Forestal, impulsará y promoverá la Certificación del buen manejo forestal y el apoyo a los propietarios forestales, a fin de que éstos puedan obtener dicho certificado y otros beneficios inherentes al mismo.\nLa Certificación del buen manejo forestal, para los efectos de esta Ley, y conforme a la Ley General, es un medio para acreditar el adecuado manejo forestal, mejorar la protección de los ecosistemas forestales y facilitar el acceso a mercados nacionales e internacionales preocupados por el futuro de los recursos forestales.\nARTÍCULO 38.- El derecho real de usufructo forestal, faculta a su titular a sembrar o plantar sobre parte o la totalidad de un terreno ajeno forestal o preferentemente forestal, sin que en ningún caso y mientras subsista el derecho puedan confundirse ambas propiedades, ya que el terreno seguirá perteneciendo al dueño de éste y lo sembrado o plantado será del usufructuario.\nEl derecho real de usufructo forestal deberá constar en escritura pública, teniendo la obligación el Notario Público ante quien se celebre el acto, de dar aviso ai Registro Público de la Propiedad y de Comercio o al Registro Agrario Nacional, según corresponda el régimen de propiedad de que se trate, y al Registro Forestal Nacional en términos del artículo 61 de la Ley General.\nCAPÍTULO OCTAVO\nDE LOS RECURSOS FORESTALES LOCALIZADOS EN LAS COMUNIDADES\nINDÍGENAS\nARTÍCULO 39.- El Ejecutivo Estatal y los gobiernos municipales garantizarán que, los conservación, aprovechamiento y restauración en su caso de dichos recursos.\nARTÍCULO 40.- El Ejecutivo Estatal y los gobiernos municipales promoverán estímulos e incentivos económicos-fiscales para los miembros de los pueblos y restauración de recursos forestales.\nCAPÍTULO NOVENO\nDE LA SANIDAD FORESTAL\nLey de Desarrollo Forestal Sustentable para el Estado de Baja California. Página 15\nARTÍCULO 41.- En los términos de los acuerdos y convenios que celebren los gobiernos Federal y Estatal, y en su caso los gobiernos municipales, se efectuarán acciones en forma coordinada para detectar, diagnosticar, prevenir, combatir y controlar las plagas y enfermedades forestales; promoviendo además la restauración de las áreas afectadas e forestal.\nARTÍCULO 42.- Cuando por motivos de sanidad forestal sea necesario realizar un aprovechamiento o eliminación de la vegetación forestal, deberá implementarse un programa que permita la reforestación, restauración y conservación de suelos, estando obligados los propietarios, poseedores o usufructuarios a restaurar mediante la regeneración natural o artificial, en un plazo no mayor a dos años.\nARTÍCULO 43.- Los ejidatarios, comuneros y demás propietarios o poseedores de terrenos forestales o preferentemente forestales, así como los titulares de autorizaciones de aprovechamiento de recursos forestales, quienes realicen actividades de forestación o plantaciones forestales comerciales y de reforestación, los prestadores de servicios técnicos forestales responsables de los mismos y los responsables de la administración de las áreas naturales protegidas, en forma inmediata a la detección de plagas o enfermedades, estarán obligados a dar aviso de ello a la Secretaría o a las autoridades federales del sector.\nARTÍCULO 44.- Para la aplicación de las medidas sanitarias en los terrenos forestales o preferentemente forestales, se atenderá a la Declaratoria de Emergencia Sanitaria emitida por la autoridad federal competente.\nLa Secretaría promoverá la Declaratoria de Emergencia Sanitaria en los terrenos forestales o preferentemente forestales, cuando:\nI.- El terreno se encuentre invadido de una plaga o enfermedad forestal;\nII.- A pesar de las medidas emprendidas por el propietario o poseedor del terreno la plaga o enfermedad forestal siga extendiéndose; o\nIII.- A pesar de las acciones instauradas en el terreno afectado y después de seis meses, la plaga o enfermedad forestal siga subsistiendo.\nCAPÍTULO DÉCIMO\nDE LA PREVENCIÓN, COMBATE Y CONTROL DE INCENDIOS FORESTALES\nARTÍCULO 45.- La Secretaría realizará acciones de detección y capacitación en el combate y control de incendios forestales, de conformidad con los programas operativos anuales que se elaboren en congruencia con el Programa Nacional, de igual forma apoyará la coordinación con las instancias federales correspondientes en la prevención, control y combate de incendios forestales, así como el cumplimiento de las Normas Oficiales\nMexicanas en la materia y similares, pudiendo en todo caso celebrar convenios y acuerdos de coordinación para dichos efectos.\nLey de Desarrollo Forestal Sustentable para el Estado de Baja California. Página 16\nARTÍCULO 46.- La Secretaría en coordinación con las instancias federales correspondientes, podrá celebrar convenios y acuerdos de colaboración con los ayuntamientos, organizaciones y asociaciones sociales, en las regiones forestales que así se requiera, con la finalidad de constituir agrupaciones de defensa forestal que tendrán como objeto integrar, capacitar y equipar grupos coadyuvantes para difundir programas y acciones de prevención, combate y control de incendios.\nARTÍCULO 47.- La autoridad municipal deberá atender el combate y control de incendios; y en el caso de que los mismos superen su capacidad financiera y operativa de respuesta, acudirá a la instancia estatal correspondiente. Si ésta resultase insuficiente, se procederá a informar a la autoridad federal competente, la cual actuará de acuerdo con los programas y procedimientos respectivos.\nARTÍCULO 48.- Los propietarios y poseedores de los terrenos forestales y preferentemente forestales y sus colindantes, que realicen el aprovechamiento de recursos forestales, la forestación o plantaciones forestales comerciales y reforestación, así como los prestadores de servicios técnicos forestales responsables de los mismos y los encargados de la administración de las áreas naturales protegidas, estarán obligados a ejecutar trabajos para prevenir, combatir y controlar incendios forestales, en los términos de las normas aplicables.\nARTÍCULO 49.- Los propietarios, poseedores, agricultores, o toda aquella persona que realice quemas autorizadas por la autoridad competente en terrenos agropecuarios, deberán dar aviso a la Secretaría o a la autoridad municipal cuando menos con siete días hábiles de anticipación a la quema, en los casos que pudieran afectar los ecosistemas forestales vecinos. De igual forma el interesado deberá dar aviso de la quema a los propietarios y poseedores de los terrenos forestales o preferentemente forestales colindantes, con el objeto de que adopten las precauciones necesarias.\nEl incumplimiento del aviso a que se refiere el párrafo anterior, será sancionado administrativamente por la Secretaría, con independencia de la responsabilidad civil o penal que en su caso pudiera exigirse.\nLa Secretaría y la autoridad municipal promoverán que los productores agrícolas y ganaderos usen alternativas técnicas para la preparación de terreno, control de plagas y eviten el uso del fuego, tales como el aprovechamiento de esquilmos, la incorporación de esquilmos al suelo; labranza mínima, abonos verdes, cultivos de cobertera, control biológico y manejo integrado de plagas, planificación de pastoreo, establecimiento de praderas, tratamiento localizado de pastizales lignificados, entre otros que la innovación científica y tecnología desarrollen.\nArtículo Reformado\nCAPÍTULO DÉCIMO PRIMERO\nDE LA CULTURA, EDUCACIÓN, CAPACITACIÓN Y TECNOLOGÍA FORESTAL\nLey de Desarrollo Forestal Sustentable para el Estado de Baja California. Página 17\nARTÍCULO 50.- La Secretaría, en coordinación con las autoridades competentes, los\nMunicipios, organizaciones e instituciones públicas, privadas y sociales, realizarán en materia de cultura, educación y capacitación forestal las acciones siguientes:\nI.- Participar en las campañas de difusión y eventos especiales orientados al logro sustentable;\nII.- Promover espacios orientados a la cultura, educación y capacitación en materia forestal;\nIII.- Fomentar la divulgación, el uso, respeto y reconocimiento de costumbres, tradiciones y prácticas culturales propias de las comunidades forestales del Estado;\nIV.- Contribuir al diseño, formulación, elaboración y publicación de materiales de comunicación educativa y guías técnicas actualizadas, que reorienten la relación de la sociedad y lo forestal;\nV.- Impulsar la participación de promotores forestales voluntarios;\nVI.- Encabezar programas de capacitación relacionados con la difusión de la cultura de conservación forestal;\nVII.- Realizar campañas de difusión permanentes en redes sociales y medios de comunicación, para informar a la población sobre las medidas de prevención y acciones que deben tomarse para evitar, combatir y reducir los incendios en zonas forestales aunado a desarrollar proyectos de educación ambiental, prevención y de difusión de la cultura para la protección de los recursos forestales;\nFracción Reformada\nVIII.- Impartir en escuelas públicas y privadas educación forestal y acciones de prevención a contingencias ambientales;\nIX.- Emitir recomendaciones a las actualizaciones de los planes de estudios de carreras afines a la materia forestal que le sean solicitados;\nX.- Inducir la formación continua y permanente a los servidores públicos del ramo forestal estatal y municipal;\nXI.- Incentivar y difundir los proyectos que sean aprobados en materia de investigación forestal;\nXII.- Apoyar la transferencia de tecnología para conservar, proteger, restaurar y aprovechar en forma óptima y racional los recursos forestales, y\nXIII.- Las demás que contribuyan al desarrollo forestal sustentable del Estado.\nArtículo Reformado\nCAPÍTULO DÉCIMO SEGUNDO\nLey de Desarrollo Forestal Sustentable para el Estado de Baja California. Página 18\nARTÍCULO 51.- Para verificar y garantizar el cumplimiento de esta Ley y sus disposiciones reglamentarias, la Secretaría por conducto de su personal autorizado, efecto se elabore.\nARTÍCULO 52.- La Secretaría deberá observar en el desarrollo de los procedimientos de inspección, las formalidades que para la materia señala la normatividad aplicable vigente en el Estado, y de conformidad con los acuerdos de coordinación celebrados con la autoridad federal competente en la materia.\nARTÍCULO 53.- Cuando de las visitas u operativos de inspección se determine que existe riesgo inminente de daño o deterioro grave a los ecosistemas forestales, o cuando los actos, hechos u omisiones pudieran dar lugar a la imposición del decomiso como sanción administrativa en los términos de la Ley General, la Secretaría en coordinación con la autoridad federal competente, podrá tomar alguna de las medidas de seguridad previstas en el artículo 161 de la Ley General.\nCAPÍTULO DÉCIMO TERCERO\nDE LAS INFRACCIONES, SANCIONES Y MEDIOS DE DEFENSA\nARTÍCULO 54.- Las infracciones a los preceptos de esta Ley y su reglamento, serán sancionadas administrativamente por la Secretaría, con alguna de las siguientes sanciones:\nI.- Amonestación con apercibimiento, o\nII.- Multa de cien a cinco mil veces el valor diario de la Unidad de Medida y\nActualización vigente.\nFracción Reformada\nArtículo Reformado\nARTÍCULO 55.- Las infracciones a esta ley serán sancionadas por la Secretaría, tomando en consideración la gravedad de la infracción cometida y:\nI.- Los daños que se hubieren producido o puedan producirse, así como el tipo, localización y cantidad del recurso dañado;\nII.- El beneficio directamente obtenido;\nIII.- El carácter intencional o no de la acción u omisión;\nIV.- El grado de participación e intervención en la preparación y realización de la infracción;\nV.- Las condiciones económicas, sociales y culturales del infractor, y\nVI.- La reincidencia.\nLey de Desarrollo Forestal Sustentable para el Estado de Baja California. Página 19\nARTÍCULO 56.- Los interesados afectados por los actos o resoluciones de la\nProcedimiento para los Actos de la Administración Pública del Estado.\nARTÍCULOS TRANSITORIOS\nPRIMERO.- Esta ley entrará en vigor al día siguiente de su publicación en el Periódico\nOficial del Gobierno del Estado.\nSEGUNDO.- El Ejecutivo del Estado dentro de los seis meses siguientes a la entrada en vigor de esta ley, deberá expedir las disposiciones reglamentarias correspondientes.\nTERCERO.- El Consejo Estatal Forestal deberá instalarse dentro de los noventa días siguientes a partir de la entrada en vigor de la presente Ley.\nCUARTO.- El Congreso del Estado deberá adecuar la Ley de Fomento Agropecuario y Forestal del Estado de Baja California, a más tardar dentro de los noventa días siguientes a la entrada en vigor de las presentes reformas.\nQUINTO.- Se derogan las demás Disposiciones que se opongan a la aplicación de la presente Ley.\nDADO en el Salón de Sesiones “Lic. Benito Juárez García” del H. Poder Legislativo del Estado de Baja California, en la Ciudad de Mexicali, B.C., a los veintinueve días del mes de abril del dos mil diez.\nDIP. OSCAR R. MARTÍNEZ GARZA\nPRESIDENTE\n(RÚBRICA)\nDIP. JUAN MANUEL MOLINA GARCÍA\nSECRETARIO\n(RÚBRICA)\nDE CONFORMIDAD CON LO DISPUESTO POR LA FRACCION I DEL ARTÍCULO 49\nMEXICALI, BAJA CALIFORNIA, A LOS TREINTA DIAS DEL MES DE ABRIL DEL\nAÑO DOS MIL DIEZ.\nGOBERNADOR DEL ESTADO\nJOSE GUADALUPE OSUNA MILLAN\n(RÚBRICA)\nLey de Desarrollo Forestal Sustentable para el Estado de Baja California. Página 20\nSECRETARIO GENERAL DE GOBIERNO\nJOSE FRANCISCO BLAKE MORA\n(RUBRICA)\nLey de Desarrollo Forestal Sustentable para el Estado de Baja California. Página 21\nARTÍCULO 3.- Fue reformado por Decreto No. 110, publicado en el Periódico Oficial\nLegislatura, siendo Gobernadora Constitucional la C. Marina del Pilar Ávila Olmeda 20212027;\nARTÍCULO 7.- Fue reformado por Decreto No. 275, publicado en el Periódico Oficial\nNo. 55, Sección III, de fecha 30 de noviembre de 2018, Tomo CXXV, expedido por la H. XXII\nLegislatura, siendo Gobernador Constitucional el C. Francisco Arturo Vega de Lamadrid\n2013-2019;\nARTÍCULO 9.- Fue reformado por Decreto No. 275, publicado en el Periódico Oficial\nNo. 55, Sección III, de fecha 30 de noviembre de 2018, Tomo CXXV, expedido por la H. XXII\nLegislatura, siendo Gobernador Constitucional el C. Francisco Arturo Vega de Lamadrid\n2013-2019;\nARTÍCULO 17.- Fue reformado por Decreto No. 66, publicado en el Periódico Oficial\nNo. 39, Sección II, de fecha 01 de agosto de 2014, Tomo CXXI, expedido por la H. XXI\nLegislatura, siendo Gobernador Constitucional el C. Francisco Arturo Vega de Lamadrid\n2013-2019; fue reformado por Decreto No. 200, publicado en el Periódico Oficial No. 11,\nSección IV, de fecha 09 de marzo de 2018, Tomo CXXV, expedido por la H. XXII Legislatura, siendo Gobernador Constitucional el C. Francisco Arturo Vega de Lamadrid 2013-2019;\nARTÍCULO 19.- Fue reformado por Decreto No. 200, publicado en el Periódico Oficial\nNo. 11, Sección IV, de fecha 09 de marzo de 2018, Tomo CXXV, expedido por la H. XXII\nLegislatura, siendo Gobernador Constitucional el C. Francisco Arturo Vega de Lamadrid\n2013-2019;\nARTÍCULO 19 BIS.- Fue adicionado por Decreto No. 200, publicado en el Periódico\nOficial No. 11, Sección IV, de fecha 09 de marzo de 2018, Tomo CXXV, expedido por la H.\nXXII Legislatura, siendo Gobernador Constitucional el C. Francisco Arturo Vega de Lamadrid\n2013-2019;\nARTÍCULO 20.- Fue reformado por Decreto No. 66, publicado en el Periódico Oficial\nLegislatura, siendo Gobernador Constitucional el C. Francisco Arturo Vega de Lamadrid\n2013-2019;\nARTÍCULO 49.- Fue reformado por Decreto No. 66, publicado en el Periódico Oficial\nLegislatura, siendo Gobernador Constitucional el C. Francisco Arturo Vega de Lamadrid\n2013-2019;\nARTÍCULO 50.- Fue reformado por Decreto No. 110, publicado en el Periódico Oficial\nLey de Desarrollo Forestal Sustentable para el Estado de Baja California. Página 22\nLegislatura, siendo Gobernadora Constitucional la C. Marina del Pilar Ávila Olmeda 20212027;\nARTÍCULO 54.- Fue reformado por Decreto No. 281, publicado en el Periódico Oficial\nLegislatura, siendo Gobernador Constitucional el C. Francisco Arturo Vega de Lamadrid\n2013-2019;\nLey de Desarrollo Forestal Sustentable para el Estado de Baja California. Página 23\nARTÍCULO SEGUNDO TRANSITORIO DEL DECRETO No. 66, POR EL QUE SE\nREFORMAN LOS ARTICULOS 17, 20 y 49, PUBLICADO EN EL PERIÓDICO OFICIAL No.\nH. XXI LEGISLATURA, SIENDO GOBERNADOR CONSTITUCIONAL EL C. FRANCISCO\nARTURO VEGA DE LAMADRID 2013-2019.\nARTÍCULO TRANSITORIO\nÚNICO.- Las presentes reformas entrarán en vigor el día siguiente al de su publicación en el Periódico Oficial del Estado.\nDADO en el Salón de Sesiones “Lic. Benito Juárez García” del H. Poder Legislativo del Estado de Baja California, en la Ciudad de Mexicali, B.C., a los diecinueve días del mes de junio del año dos mil catorce.\nDIP. FELIPE DE JESÚS MAYORAL MAYORAL\nPRESIDENTE\n(RÚBRICA)\nDIP. GERARDO ÁLVAREZ HERNÁNDEZ\nSECRETARIO\n(RÚBRICA)\nDE CONFORMIDAD CON LO DISPUESTO POR LA FRACCIÓN I DEL ARTÍCULO 49\nMEXICALI, BAJA CALIFORNIA, A LOS VEINTITRES DÍAS DEL MES DE JULIO DEL\nAÑO DOS MIL CATORCE.\nFRANCISCO ARTURO VEGA DE LAMADRID\nGOBERNADOR DEL ESTADO\n(RÚBRICA)\nGUILLERMO TREJO DOZAL\nSECRETARIO GENERAL DE GOBIERNO\n(RÚBRICA)\nARTÍCULO ÚNICO TRANSITORIO DEL DECRETO No. 200, POR EL QUE SE\nAPRUEBAN LAS REFORMAS AL ARTÍCULO 19, PUBLICADO EN EL PERIÓDICO\nEXPEDIDO POR LA H. XXII LEGISLATURA, SIENDO GOBERNADOR CONSTITUCIONAL\nEL C. FRANCISCO ARTURO VEGA DE LAMADRID 2013-2019.\nARTÍCULO TRANSITORIO\nLey de Desarrollo Forestal Sustentable para el Estado de Baja California. Página 24\nÚNICO.- La presente reforma entrará en vigor a partir del día siguiente de su publicación en el Periódico Oficial del Estado de Baja California. del Estado de Baja California, en la Ciudad de Mexicali, B.C., a los ocho días del mes de febrero del año dos mil dieciocho.\nDIP. MTRO. RAÚL CASTAÑEDA POMPOSO\nPRESIDENTE\n(RÚBRICA)\nDIP. ROCÍO LÓPEZ GOROSAVE\nSECRETARIA\n(RÚBRICA)\nDE CONFORMIDAD CON LO DISPUESTO POR LA FRACCIÓN I DEL ARTÍCULO 49\nMEXICALI, BAJA CALIFORNIA, A LOS VEINTIDOS DÍAS DEL MES DE FEBRERO\nDEL AÑO DOS MIL DIECIOCHO.\nFRANCISCO ARTURO VEGA DE LAMADRID\nGOBERNADOR DEL ESTADO\n(RÚBRICA)\nFRANCISCO RUEDA GÓMEZ\nSECRETARIO GENERAL DE GOBIERNO\n(RÚBRICA)\nARTÍCULO ÚNICO TRANSITORIO DEL DECRETO No. 200, POR EL QUE SE\nAPRUEBAN LAS REFORMAS AL ARTÍCULO 17, 19 Y 19 BIS, PUBLICADO EN EL\nPERIÓDICO OFICIAL No. 11, SECCIÓN IV, TOMO CXXV, DE FECHA 09 DE MARZO DE\n2018, EXPEDIDO POR LA H. XXII LEGISLATURA, SIENDO GOBERNADOR\nCONSTITUCIONAL EL C. FRANCISCO ARTURO VEGA DE LAMADRID 2013-2019.\nARTÍCULO TRANSITORIO\nÚNICO.- La presente reforma entrará en vigor a partir del día siguiente de su publicación en el Periódico Oficial del Estado de Baja California. del Estado de Baja California, en la Ciudad de Mexicali, B.C., a los ocho días del mes de febrero del año dos mil dieciocho.\nLey de Desarrollo Forestal Sustentable para el Estado de Baja California. Página 25\nDIP. MTRO. RAÚL CASTAÑEDA POMPOSO\nPRESIDENTE\n(RÚBRICA)\nDIP. ROCÍO LÓPEZ GOROSAVE\nSECRETARIA\n(RÚBRICA)\nDE CONFORMIDAD CON LO DISPUESTO POR LA FRACCIÓN I DEL ARTÍCULO 49\nMEXICALI, BAJA CALIFORNIA, A LOS VEINTIDOS DÍAS DEL MES DE FEBRERO\nDEL AÑO DOS MIL DIECIOCHO.\nFRANCISCO ARTURO VEGA DE LAMADRID\nGOBERNADOR DEL ESTADO\n(RÚBRICA)\nFRANCISCO RUEDA GÓMEZ\nSECRETARIO GENERAL DE GOBIERNO\n(RÚBRICA)\nFE DE ERRATAS A LA PUBLICACIÓN DEL RESOLUTIVO ÚNICO DEL DECRETO\nNo. 200 APROBADO POR ESTA LEGISLATURA BAJO EL DICTAMEN 4 DE LA COMISIÓN\nDE MEDIO AMBIENTE Y DESARROLLO SUSTENTABLE Y PUBLICADO EN EL\nPERIÓDICO OFICIAL NÚMERO 11, SECCIÓN IV, DE FECHA 09 DE MARZO DE 2018,\nPUBLICADO EN EL PERIÓDICO OFICIAL No. 24, SECCIÓN I, TOMO CXXV, DE FECHA\n18 DE MAYO DE 2018, EXPEDIDO POR LA H. XXII LEGISLATURA, SIENDO\nGOBERNADOR CONSTITUCIONAL EL C. FRANCISCO ARTURO VEGA DE LAMADRID\n2013-2019.\nARTÍCULO TRANSITORIO\nÚNICO.- La presente reforma entrará en vigor a partir del día siguiente de su publicación en el Periódico Oficial del Estado de Baja California.\nATENTAMENTE\nPOR LA MESA DIRECTIVA\nDIP. MARCO A. CORONA BOLAÑOS CACHO\nPRESIDENTE\n(RÚBRICA)\nLey de Desarrollo Forestal Sustentable para el Estado de Baja California. Página 26\nDIP. VICTORIA BENTLEY DUARTE\nSECRETARIA\n(RÚBRICA)\nDE CONFORMIDAD CON LO DISPUESTO POR LA FRACCIÓN I DEL ARTÍCULO 49\nMEXICALI, BAJA CALIFORNIA, A LOS ONCE DÍAS DEL MES DE MAYO DEL AÑO\nDOS MIL DIECIOCHO.\nFRANCISCO ARTURO VEGA DE LAMADRID\nGOBERNADOR DEL ESTADO\n(RÚBRICA)\nFRANCISCO RUEDA GÓMEZ\nSECRETARIO GENERAL DE GOBIERNO\n(RÚBRICA)\nARTÍCULO ÚNICO TRANSITORIO DEL DECRETO No. 275, POR EL QUE SE\nAPRUEBA LA REFORMA A LOS ARTÍCULOS 7 Y 9, PUBLICADO EN EL PERIÓDICO\nOFICIAL No. 55, SECCIÓN III, TOMO CXXV, DE FECHA 30 DE NOVIEMBRE DE 2018,\nEXPEDIDO POR LA H. XXII LEGISLATURA, SIENDO GOBERNADOR CONSTITUCIONAL\nEL C. FRANCISCO ARTURO VEGA DE LAMADRID 2013-2019.\nARTÍCULO TRANSITORIO\nARTICULO PRIMERO.- Las presentes reformas entrarán en vigor al día siguiente de su publicación en el Periódico Oficial del Estado.\nARTICULO SEGUNDO.- El Ejecutivo Estatal en un lapso que no excederá de 90 días contados a partir de la entrada en vigor de la presente reforma realizará las adecuaciones pertinentes al Reglamento de la Ley de Desarrollo Forestal.\nARTICULO TERCERO.- Remítase las presentes reformas a los ayuntamientos del estado para que un plano que excederá de 90 días contados a partir de la entrada en vigor de la presente reforma, realicen las adecuaciones a los Reglamentos municipales. del Estado de Baja California, en la Ciudad de Mexicali, B.C., a los veinticinco días del mes de octubre del año dos mil dieciocho.\nDIP. ROCÍO LÓPEZ GOROSAVE\nPRESIDENTA\n(RÚBRICA)\nLey de Desarrollo Forestal Sustentable para el Estado de Baja California. Página 27\nDIP. MÓNICA HERNÁNDEZ ÁLVAREZ\nSECRETARIA\n(RÚBRICA)\nDE CONFORMIDAD CON LO DISPUESTO POR LA FRACCIÓN I DEL ARTÍCULO 49\nMEXICALI, BAJA CALIFORNIA, A LOS TREINTA DÍAS DEL MES DE NOVIEMBRE\nDEL AÑO DOS MIL DIECIOCHO.\nFRANCISCO ARTURO VEGA DE LAMADRID\nGOBERNADOR DEL ESTADO\n(RÚBRICA)\nFRANCISCO RUEDA GÓMEZ\nSECRETARIO GENERAL DE GOBIERNO\n(RÚBRICA)\nARTÍCULO VIGÉSIMO PRIMERO TRANSITORIO DEL DECRETO No. 281, POR EL\nQUE SE REFORMA EL ARTÍCULO 54, PUBLICADO EN EL PERIÓDICO OFICIAL No. 55,\nSECCION IV, TOMO CXXV, DE FECHA 30 DE NOVIEMBRE DE 2018, EXPEDIDO POR LA\nH. XXII LEGISLATURA, SIENDO GOBERNADOR CONSTITUCIONAL EL C. FRANCISCO\nARTURO VEDA DE LAMADRID 2013-2019.\nARTÍCULOS TRANSITORIOS\nARTÍCULO PRIMERO.- El presente decreto entrará en vigor al día siguiente al de su publicación en el Periódico Oficial del Estado de Baja California.\nARTÍCULO SEGUNDO.- El valor diario de la Unidad de Medida y Actualización a la fecha de entrada en vigor, se tomará el valor publicado en el Diario Oficial de la Federación por el INEGI. El valor de la Unidad de Medida y Actualización a la fecha de entrada en vigor del presente Decreto, será producto de multiplicar el valor referido en el párrafo anterior por\n30.4. Por su parte, el valor anual será el producto de multiplicar el valor inicial mensual por\n12.\nARTÍCULO TERCERO. - Todas las menciones al salario mínimo como unidad de cuenta, índice, base, medida o referencia para determinar la cuantía de las obligaciones, sanciones, multas administrativas, conceptos de pago y montos de referencia, se entenderán referidas a la Unidad de Medida y Actualización. del Estado de Baja California, en la Ciudad de Mexicali, B.C., a los veinticinco días del mes de octubre del año dos mil dieciocho.\nLey de Desarrollo Forestal Sustentable para el Estado de Baja California. Página 28\nDIP. ROCÍO LÓPEZ GOROSAVE\nPRESIDENTA\n(RÚBRICA)\nDIP. MÓNICA HERNÁNDEZ ÁLVAREZ\nSECRETARIA\n(RÚBRICA)\nDE CONFORMIDAD CON LO DISPUESTO POR LA FRACCIÓN I DEL ARTÍCULO 49\nMEXICALI, BAJA CALIFORNIA, A LOS TREINTA DÍAS DEL MES DE NOVIEMBRE\nDEL AÑO DOS MIL DIECIOCHO.\nFRANCISCO ARTURO VEGA DE LAMADRID\nGOBERNADOR DEL ESTADO\n(RÚBRICA)\nFRANCISCO RUEDA GÓMEZ\nSECRETARIO GENERAL DE GOBIERNO\n(RÚBRICA)\nARTÍCULO ÚNICO TRANSITORIO DEL DECRETO No. 110, POR EL QUE SE\nAPRUEBA LA REFORMA A LOS ARTÍCULOS 3 Y 50; PUBLICADO EN EL PERIÓDICO\nOFICIAL No. 39, ÍNDICE, DE FECHA 27 DE JUNIO DE 2025, TOMO CXXXII; EXPEDIDO\nPOR LA H. XXV LEGISLATURA, SIENDO GOBERNADORA CONSTITUCIONAL LA C.\nMARINA DEL PILAR ÁVILA OLMEDA 2021-2027.\nTRANSITORIO\nÚNICO. El presente decreto entrará en vigor al día siguiente al de su publicación en el\nPeriódico Oficial del Estado.\nDADO en Sesión Ordinaria de la XXV Legislatura en la Ciudad de Mexicali, B.C., a los diecinueve días del mes de junio del año dos mil veinticinco.\nDIP. MICHELLE ALEJANDRA TEJEDA MEDINA\nPRESIDENTA\n(RÚBRICA)\nDIP. NORMA ANGELICA PEÑALOZA ESCOBEDO\nSECRETARIA\n(RÚBRICA)\nLey de Desarrollo Forestal Sustentable para el Estado de Baja California. Página 29\nDE CONFORMIDAD CON LO DISPUESTO POR LA FRACCIÓN I DEL ARTÍCULO 49\nCALIFORNIA, IMPRÍMASE Y PUBLÍQUESE.\nMEXICALI, BAJA CALIFORNIA, A LOS 20 DÍAS DEL MES DE JUNIO DEL AÑO DOS\nMIL VEINTICINCO.\nMARINA DEL PILAR ÁVILA OLMEDA\nGOBERNADORA DEL ESTADO\nDE BAJA CALIFORNIA\n(RÚBRICA)\nALFREDO ÁLVAREZ CÁRDENAS\nSECRETARIO GENERAL DE GOBIERNO\nDEL ESTADO DE BAJA CALIFORNIA\n(RÚBRICA)\nLey de Desarrollo Forestal Sustentable para el Estado de Baja California. Página 30",
  "ordenamiento": "REGLAMENTO",
  "jurisdiccion": "BAJA CALIFORNIA",
  "fuente_oficial": "Periódico Oficial",
  "FECHA PER OFIC": "2025/06/27",
  "ESTATUS": "VIGENTE",
  "TOMO": "TOMO_VII",
  "URL": "https://www.congresobc.gob.mx/Documentos/ProcesoParlamentario/Leyes/TOMO_VII/20250627_LEYFORESTAL.PDF",
  "es_escaneado": false,
  "tiene_tablas": false,
  "materia": [
    "ambiental",
    "urbanismo",
    "infraestructura"
  ]
}