{
  "titulo": "Ley DE CENTROS DE ATENCIÓN, CUIDADO y DESARROLLO INTEGRAL INFANTIL DEL ESTADO DE BAJA CALIFORNIA",
  "Contenido": "LEY DE CENTROS DE ATENCIÓN, CUIDADO Y DESARROLLO INTEGRAL\nINFANTIL DEL ESTADO DE BAJA CALIFORNIA\nPublicada en el Periódico Oficial No. 25, Sección V, Tomo CXXII,\nTÍTULO I\nDISPOSICIONES GENERALES\nCapítulo I\nDe la Naturaleza y Objeto de la Ley\nArtículo 1.- La presente Ley es de orden público, interés social y tiene por objeto desarrollar las bases previstas en la Ley General de Prestación de Servicios para la\nAtención, Cuidado y Desarrollo Integral Infantil, respecto de la regulación de los Centros de\nAtención, Cuidado y Desarrollo Integral Infantil, en el Estado de Baja California y sus\nMunicipios.\nArtículo 2.- Conforme a lo previsto en la Ley General, la presente Ley tiene por objetivos:\nI.- Regular la prestación de servicios social y privado para la atención, cuidado y desarrollo integral infantil;\nII.- Garantizar a las niñas y niños, el acceso a dichos servicios en condiciones de igualdad, calidad, calidez, seguridad y protección adecuadas;\nIII.- Desarrollar la concurrencia entre el Estado y los municipios en la Regulación de los Centros de Atención, Cuidado y Desarrollo Integral Infantil; y\nIV.- Salvaguardar el ejercicio pleno de los derechos de las niñas y niños en los centros para la atención, cuidado y desarrollo integral infantil.\nCapítulo II\nDe los sujetos de la Norma\nArtículo 3.- Corresponde la aplicación de la presente Ley, al Ejecutivo del Estado, por conducto del Sistema para el Desarrollo Integral de la Familia, la Secretaría de Educación y\nAyuntamientos conforme a las dependencias que estos determinen.\nArtículo Reformado\nArtículo 4.- Son sujetos de la presente norma, las dependencias públicas, organismos auxiliares y los particulares que presten los servicios para la atención, cuidado y desarrollo integral infantil.\nLey de Centros de Atención, Cuidado y Página 1\nArtículo 5.- Las dependencias públicas, organismos auxiliares y los particulares que presten los servicios para la atención, cuidado y desarrollo integral infantil, además de cumplir con la normatividad aplicable, deberán observar lo dispuesto en la presente Ley.\nArtículo 6.- Los prestadores del servicio para la atención, cuidado y desarrollo integral infantil, ya sean públicos, sociales o privados deben garantizar la seguridad, calidad e higiene de dicho servicio.\nArtículo 7.- Los prestadores de servicios para la atención, cuidado y desarrollo integral infantil, quedan sujetos a lo dispuesto en la presente Ley y, en su caso, a las disposiciones legales y administrativas aplicables.\nCapítulo III\nDe los parámetros interpretativos\nArtículo 8.- La interpretación de esta Ley, se hará conforme a los criterios previstos en la Ley General, y siempre buscando salvaguardar el interés superior de los menores.\nArtículo 9.- Además de las definiciones previstas en la Ley General, para los efectos de la presente Ley se entenderá por:\nI.- Centros de Atención: A los espacios, cualquiera que sea su denominación de modalidad pública, privada o mixta, donde se prestan servicios para la atención, cuidado y desarrollo integral infantil a niños y niñas desde los cuarenta y tres días de nacido;\nII.- Consejo.- Al Consejo para la Prestación de Servicios de Atención, Cuidado y\nDesarrollo Integral Infantil del Estado de Baja California;\nIII.- Consejo Nacional: Consejo Nacional de Prestación de Servicios para la Atención, Cuidado y Desarrollo Integral Infantil;\nIV.- Desarrollo Integral Infantil: Es el derecho que tienen niñas y niños a formarse física, mental, emocional y socialmente en condiciones de seguridad e igualdad;\nV.- Ley: Ley de Centros de Atención, Cuidado y Desarrollo Integral Infantil del Estado de Baja California;\nVI.- Ley General: Ley General de Prestación de Servicios para la Atención, Cuidado y\nDesarrollo integral infantil;\nVII.- Medidas Precautorias: Aquéllas que con motivo de la prestación de los servicios para la atención, cuidado y desarrollo integral infantil emitan las autoridades competentes, de conformidad con la presente Ley, para salvaguardar y proteger la vida y la integridad de niñas y niños;\nVIII.- Modalidades y Tipos: A las modalidades y tipos del servicio para la atención, cuidado y desarrollo integral infantil que se refiere esta Ley;\nLey de Centros de Atención, Cuidado y Página 2\nIX.- Política Pública: A la política pública para la prestación de Servicios para la\nAtención, Cuidado y Desarrollo Integral Infantil en el Estado de Baja California;\nX.- Prestadores de servicios: Aquellas personas físicas o morales que cuenten con permiso, licencia o autorización, emitido por la autoridad competente, para instalar y operar uno o varios Centros de Atención en cualquier modalidad y tipo;\nXI.- Programa Integral de Supervisión, Acompañamiento, Monitoreo y Evaluación del funcionamiento: Conjunto de acciones para lograr una vigilancia efectiva del cumplimiento de la presente Ley y garantizar el mejoramiento progresivo y fortalecimiento de los servicios para la atención, cuidado y desarrollo integral infantil;\nXII.- Programa Interno de Protección Civil: Al que se instala en los inmuebles correspondientes con el fin de salvaguardar la integridad física de niñas y niños, empleados y de las personas que concurran a ellos;\nXIII.- Registro: Al Registro de Centros de Atención;\nXIV.- Servicios para atención, cuidado y desarrollo integral infantil: Medidas dirigidas a niñas y niños en los Centros de Atención, consistentes en la atención y cuidado para su desarrollo integral infantil; y\nXV.- Usuario: Al padre, la madre, tutor o quienes ejerzan la guarda o custodia del niño o niña.\nXVI.- Modelo de desarrollo integral para niños de 0 a 3 años 11 meses: Modelo desarrollo para su aplicación en la formación inicial o temprana aprobado por el Consejo\nEstatal para su vigencia.\nFracción Adicionada\nArtículo Reformado\nArtículo 10.- La interpretación de la Ley corresponde en lo administrativo a la\nSecretaría de Salud, a la Secretaría de Educación Pública y Bienestar Social y a la\nSecretaría General de Gobierno, en el ámbito de sus respectivas atribuciones, así como a las dependencias que determinen los Ayuntamientos en sus normas reglamentarias.\nTÍTULO II\nDE LOS DERECHOS DE LAS NIÑAS Y NIÑOS\nArtículo 11.- El Estado y los Ayuntamientos, garantizarán en el ámbito de sus competencias, la vigencia y observancia de los derechos garantizados en el presente título y de los reconocidos en los ordenamientos legales.\nArtículo 12.- Los niños y niñas sujetos a la prestación de los servicios de atención, cuidado y desarrollo integral infantil, tendrán derecho:\nI.- A la comprensión y el ejercicio de sus derechos;\nLey de Centros de Atención, Cuidado y Página 3\nII.- A la no discriminación en contra suya o de sus padres tutores;\nIII.- A recibir servicios de calidad y con calidez, por parte de personal apto, suficiente y niñez y en su caso de los indígenas o discapacitados;\nIV.- A un entorno seguro, afectivo y libre de violencia;\nV.- A la atención y promoción de la salud;\nVI.- A participar, ser consultado, expresar libremente sus ideas y opiniones sobre los asuntos que les atañen y que dichas opiniones sean tomadas en cuenta;\nVII.- A recibir la alimentación que les permita tener una nutrición adecuada;\nVIII.- A recibir orientación y educación a través de un modelo de desarrollo integral para niños de 0 a 3 años 11 meses apropiado para su edad y orientado a lograr un desarrollo físico, cognitivo, afectivo y social hasta el máximo de sus posibilidades, así como a la comprensión y el ejercicio de sus derechos pudiendo basarse la misma, en el modelo señalado en la fracción XVI del artículo 9 de esta ley; y\nFracción Reformada\nIX.- Al cuidado y protección contra actos u omisiones que puedan afectar su integridad física o psicológica.\nX.- Al descanso, al juego y al esparcimiento.\nFracción Reformada\nArtículo Reformado\nArtículo 13.- A fin de garantizar el interés superior de la niñez, las niñas y niños tienen derecho a recibir los servicios para la atención, cuidado y desarrollo integral en condiciones de calidad, calidez, seguridad, protección y respeto a sus derechos, identidad e individualidad.\nArtículo 14.- Las niñas y niños son sujetos de los servicios para la atención, cuidado y desarrollo integral, sin discriminación de ningún tipo en los términos de lo dispuesto por el artículo 1° de la Constitución Política de los Estados Unidos Mexicanos.\nTÍTULO III\nDE LA COMPETENCIA ESTATAL Y MUNICIPAL\nCapítulo I\nDisposiciones Comunes\nArtículo 16.- Las disposiciones reglamentarias relativas a la prestación de servicios para la atención, cuidado y desarrollo integral infantil que se emitan por parte de la\nLey de Centros de Atención, Cuidado y Página 4 administración pública estatal y municipal, en el ámbito de sus respectivas competencias, deberán sujetarse a la presente Ley.\nArtículo 17.- Las autoridades estatales y municipales, en el ámbito de su competencia, verificarán que las disposiciones reglamentarias señaladas en el artículo anterior y su cumplimiento, se apeguen a lo dispuesto en las Normas Oficiales Mexicanas aplicables.\nArtículo 18.- Las autoridades estatales y municipales, a través de las instancias correspondientes, ofrecerán la orientación y capacitación necesarias para que los prestadores del servicio cumplan eficazmente con las normas correspondientes.\nAsimismo, llevarán a cabo campañas de prevención y denuncia de irregularidades en las instalaciones y condiciones del servicio de atención, cuidado y desarrollo integral infantil.\nCapítulo II\nDel Ámbito Estatal\nArtículo 19.- La rectoría de los servicios para la atención, cuidado y desarrollo integral infantil corresponde al Estado, que tendrá responsabilidad indeclinable en la autorización, funcionamiento, monitoreo, supervisión y evaluación de dichos servicios.\nArtículo 20.- La prestación de los servicios para la atención, cuidado y desarrollo integral infantil, cuando esté a cargo de las dependencias y entidades estatales o de los municipios, podrá otorgarse por éstas o a través de la personas del sector social o privado, mediante licitación pública, que cuenten con los requisitos y la autorización correspondientes.\nArtículo 21.- Conforme a lo previsto en la Ley General, son atribuciones del Ejecutivo estatal, en materia de Prestación de Servicios de Atención, Cuidado y Desarrollo Integral\nInfantil, las siguientes:\nI.- Asesorar a los gobiernos municipales en la elaboración y ejecución de sus respectivos programas, de acuerdo al Programa Integral de Supervisión, Acompañamiento, Monitoreo y Evaluación del funcionamiento;\nII.- Brindar orientación y capacitación para que los prestadores del servicio de atención, cuidado y desarrollo integral infantil cumplan rigurosamente con la normatividad referida en la fracción anterior;\nIII.- Celebrar convenios de coordinación en la materia con los demás órdenes de gobierno, para alcanzar los fines de la presente Ley;\nIV.- Coadyuvar con el Consejo Nacional;\nLey de Centros de Atención, Cuidado y Página 5\nV.- Coordinar y operar el Registro Estatal a través del Sistema para el Desarrollo\nSocial en el Estado y con la Secretaría de Salud;\nVI.- Decretar las medidas precautorias necesarias a los Centros de Atención;\nVII. Determinar los indicadores que permitan evaluar la aplicación del Programa\nIntegral de Supervisión, Acompañamiento, Monitoreo y Evaluación del funcionamiento a que se refiere la fracción I de este artículo;\nVIII.- Difundir los principios generales de esta Ley entre los usuarios y los prestadores de servicios de atención, cuidado y desarrollo integral infantil, así como la normatividad que establezca los mínimos necesarios para la prestación del servicio en materia de salubridad, infraestructura, equipamiento, seguridad y protección civil;\nIX.- Elaborar, aplicar y evaluar el Programa Integral de Supervisión, Acompañamiento, Monitoreo y Evaluación del funcionamiento, cuyas directrices deberán atender al objeto de la presente Ley, así como a los fines del Consejo;\nX.- Establecer mecanismos eficaces que permitan a niñas y niños con discapacidad recibir atención especializada y disfrutar del Servicio de Atención, Cuidado y Desarrollo\nIntegral Infantil de manera gratuita;\nXI.- Fomentar, realizar y difundir estudios e investigaciones en la materia;\nXII.- Hacer del conocimiento de la autoridad competente toda aquella conducta o hecho que pueda constituir un ilícito;\nXIII.- Imponer las sanciones que correspondan a su ámbito de competencia, por el incumplimiento a las disposiciones de esta Ley;\nXIV.- Organizar el Consejo Estatal, así como promover el cumplimiento de sus objetivos; y\nXV.- Promover y celebrar convenios de concertación con los sectores privado y social, para el impulso, fomento y desarrollo de los fines de la presente Ley.\nSección I\nDe la política pública de prestación de servicios de atención, cuidado y desarrollo integral infantil\nArtículo 22.- Es prioritaria y de interés público la política que se formule, ejecute y evalúe en materia de prestación de los servicios a que se refiere la presente Ley, la cual será determinada por el Consejo siguiendo las bases previstas en la Ley General, y permitirá la coordinación de esfuerzos de los distintos órdenes de gobierno y de los sectores público, social y privado.\nArtículo 23.- La Política Pública deberá velar por el cumplimiento de los siguientes objetivos:\nLey de Centros de Atención, Cuidado y Página 6\nI.- Contribuir al mejoramiento progresivo y al fortalecimiento de los servicios para la atención, cuidado y desarrollo integral infantil;\nII.- Definir criterios estandarizados de calidad y seguridad;\nIII.- Fomentar la equidad de género;\nIV.- Garantizar criterios cuantitativos y cualitativos de los servicios, de conformidad con las prioridades que defina el Consejo, y de los requerimientos y características de los modelos de atención;\nV.- Garantizar el reconocimiento de la dignidad de niñas y niños, a partir de la creación de las condiciones necesarias de respeto, protección y ejercicio pleno de sus derechos;\nVI.- Promover el acceso de niñas y niños con discapacidad, que se encuentren en situación de calle, que habiten en el medio rural, migrantes o jornaleros agrícolas, comunidades indígenas, en situación de riesgo o vulnerabilidad y en general población que habite en zonas marginadas o de extrema pobreza, a los servicios que señala esta Ley, sin importar sus condiciones económicas, físicas, intelectuales o sensoriales; y\nVII.- Promover pautas de convivencia familiar y comunitaria fundadas en el respeto, protección y ejercicio de los derechos de niñas y niños;\nArtículo 24.- De conformidad con lo dispuesto en la Ley General, en el diseño, implementación, monitoreo y evaluación de la Política Estatal y en la aplicación e interpretación de la presente Ley, se deberá atender a los siguientes principios:\nI.- Interés superior de la niñez: que será eje rector para la toma de decisiones de los padres o tutores, directivos y personal de los centros de atención, quienes deberán pensar y actuar privilegiando el bienestar del menor;\nII.- Calidad: los servicios de las estancias infantiles se proveerán de manera eficiente y eficaz, conforme a los estándares y normas oficiales correspondientes y la mejora continua;\nIII.- Desarrollo de niñas y niños: en todos los aspectos de su vida, ya sean físicos, emocionales, psicosociales, cognitivos, sociales, educativos o culturales;\nIV.- Equidad de género;\nV.- No discriminación e igualdad de derechos;\nVI.- Participación de niñas y niños en todos los asuntos que les atañen;\nVII.- Participación, el derecho y obligación de las madres, padres o tutores a colaborar en los objetivos de las estancias infantiles, velando por el debido cuidado de los niños, especialmente en materia de seguridad e higiene;\nLey de Centros de Atención, Cuidado y Página 7\nVIII.- Respeto: en todo momento se debe proteger la dignidad y derechos fundamentales de los niños; y\nIX.- Seguridad: salvaguardar el derecho a la vida, la integridad física y psicológica, promoviendo espacios educativos libres de violencia escolar;\nArtículo 25.- La política pública será evaluada por el Consejo, para conocer el grado de cumplimiento de los principios, objetivos, criterios, lineamientos y directrices a seguir por las dependencias y entidades en la materia, así como medir el impacto de la prestación de los servicios en niñas y niños.\nArtículo 26.- El Consejo llevará a cabo la evaluación a través de uno o varios organismos independientes que podrán ser instituciones de educación superior, de investigación científica u organizaciones no gubernamentales sin fines de lucro.\nSección II\nDel Consejo para la Prestación de Servicios de Atención, Cuidado y Desarrollo Integral\nInfantil de Baja California\nArtículo 27.- El Consejo es una instancia de consulta y coordinación, a través del cual se dará seguimiento continuo a las acciones que tengan por objeto promover mecanismos interinstitucionales, que permitan establecer políticas públicas y estrategias de atención para el cumplimiento de los objetivos de esta Ley.\nArtículo 28.- Son atribuciones del Consejo:\nI.- Elaborar y aprobar su reglamento interno y normas de operación, así como el\nPrograma Integral de Supervisión, Acompañamiento, Monitoreo y Evaluación del\nFuncionamiento;\nFracción Reformada\nII.- Formular, conducir y evaluar la política pública que permita la conjunción de esfuerzos de los distintos órdenes de gobierno y de los sectores público, privado y social en la promoción de condiciones favorables al cuidado y desarrollo integral de niñas y niños, siguiendo los lineamientos fijados por el Consejo Nacional;\nIII.- Impulsar la coordinación interinstitucional, así como la concertación de acciones entre los sectores público, social y privado;\nIV.- Impulsar la investigación y la generación de estudios que contribuyan a la toma de decisiones y la planeación de políticas públicas vinculadas con el objeto de esta ley;\nV.- Impulsar programas conjuntos de capacitación y seguimiento para el personal que labora en los Centros de Atención;\nVI.- Promover ante las instancias competentes la certificación de competencias laborales para el personal que preste sus servicios en los Centros de Atención;\nLey de Centros de Atención, Cuidado y Página 8\nVII.- Promover el diseño y uso de indicadores, así como la implementación de ofrecen;\nVIII.- Promover el monitoreo ciudadano y el acceso a la información de los programas de servicios de atención, cuidado y desarrollo integral infantil, a fin de garantizar la transparencia y el uso eficiente de los recursos públicos;\nIX.- Promover la ampliación de la cobertura y la calidad de los servicios a través de esquemas diversificados y regionalizados;\nX.- Promover la participación de las familias, la sociedad civil, niñas y niños en la observación y acompañamiento de la Política Estatal y de los Servicios;\nXI.- Promover los mecanismos de corresponsabilidad y solidaridad entre la sociedad civil y las diferentes dependencias y entidades que integran el Consejo; y\nXII.- Actuar en coordinación con el Consejo Nacional de Prestación de Servicios para la Atención, Cuidado y Desarrollo Integral Infantil;\nArtículo Reformado\nArtículo 29.- Son objetivos del Consejo:\nI.- Coordinar esfuerzos de las dependencias y entidades que conforman el Consejo, para promover mecanismos que permitan mejorar la calidad de los servicios para la atención, cuidado y desarrollo integral infantil;\nII.- Diseñar políticas públicas, estrategias y acciones coordinadas para asegurar la atención integral a niñas y niños, siguiendo los lineamientos fijados por el Consejo Nacional;\nIII.- Generar y ejecutar acciones de gobierno para ofrecer un servicio de atención, cuidado y desarrollo integral infantil con criterios comunes de calidad, a través del fomento de actividades de capacitación, certificación, supervisión y seguimiento de los servicios;\nIV.- Organizar el sistema de prestación de servicios para la atención, cuidado y desarrollo integral infantil de la entidad correspondiente y coadyuvar con el Consejo\nNacional;\nArtículo 30.- El Consejo se integrará con los Titulares de las siguientes dependencias y entidades de la Administración Pública Estatal:\nI.- El Sistema para el Desarrollo Integral de la Familia de Baja California, quien lo presidirá;\nFracción Reformada\nII.- La Secretaría de Salud;\nFracción Reformada\nLey de Centros de Atención, Cuidado y Página 9\nIII.- La Secretaría de Educación y Bienestar Social;\nFracción Reformada\nIV.- La Secretaría del Trabajo y Previsión Social;\nFracción Reformada\nV.- Un Representante de cada Ayuntamiento;\nFracción Reformada\nVI.- Un Representante del sector social;\nFracción Adicionada\nVII.- Un representante del sector empresarial y;\nFracción Adicionada\nVIII.- La Secretaría General de Gobierno.\nFracción Adicionada\nSerán invitados permanentes a las sesiones del Consejo, el Instituto de la Mujer para el Estado de Baja California, la Comisión Estatal de los Derechos Humanos, las delegaciones del IMSS y del ISSSTE quienes tendrán derecho a voz.\nPárrafo Adicionado\nCuando el Gobernador del Estado asista a sesiones del Consejo, lo presidirá.\nPárrafo Recorrido\nArtículo Reformado\nArtículo 31.- Los titulares podrán designar un suplente, el cual deberá tener, al menos, nivel jerárquico de director o equivalente. El cargo de consejero será honorífico.\nArtículo 32.- Los integrantes del Consejo se reunirán en sesiones ordinarias por lo menos cuatro veces al año, para dar seguimiento a las acciones acordadas entre sus integrantes.\nArtículo 33.- El Consejo podrá sesionar de forma extraordinaria para atender asuntos que merezcan atención inmediata, las cuales serán convocadas por su Presidente a propuesta de cualquiera de los integrantes.\nArtículo 34.- Los integrantes del Consejo intercambiarán y analizarán información y datos referentes a los temas de su competencia, con el fin de cumplir con los objetivos establecidos.\nArtículo 35.- El Gobernador a través del Sistema Integral para el Desarrollo de la\nFamilia de Baja California, podrá integrar al Consejo a los titulares de otras dependencias de atención, cuidado y desarrollo integral infantil, o cuyo ámbito de atribuciones esté vinculado\nLey de Centros de Atención, Cuidado y Página 10 con estos servicios, así como a los representantes de los municipios que presten servicios para la atención, cuidado y desarrollo integral infantil.\nArtículo Reformado\nArtículo 36.- El Consejo contará con una Secretaria Técnica que será responsable de de su Reglamento.\nArtículo 37.- La operación y funcionamiento del Consejo se regularán por las disposiciones de esta ley y su Reglamento.\nArtículo 38.- Con el fin de garantizar el cumplimiento de los servicios a que se refiere esta Ley, en los Centros de Atención se contemplarán las siguientes actividades:\nI.- Alimentación adecuada y suficiente para su nutrición;\nII.- Aplicación del modelo o programa para la formación inicial o temprana apropiado a su edad y orientado al desarrollo biológico, cognoscitivo, psicomotriz, y socioafectivo;\nFracción Reformada\nIII.- Atención médica en caso de urgencia, la cual podrá brindarse en el Centro de\nAtención por personal debidamente certificado o a través de instituciones de salud públicas o privadas;\nIV.- Descanso, esparcimiento, juego y actividades recreativas propias de su edad;\nV.- Enseñanza del lenguaje y comunicación incluyendo, en su caso, lenguas indígenas, sistema braille o señas;\nVI.- Fomento a la comprensión y ejercicio de los derechos de niñas y niños;\nVII.- Fomento al cuidado de la salud;\nVIII.- Información y apoyo a los padres, tutores o quienes tengan la responsabilidad del cuidado o crianza, para fortalecer la comprensión de sus funciones en la educación de niñas y niños;\nIX.- Protección y seguridad; y\nX.- Supervisión e inspección efectiva en materia de salud y protección civil.\nArtículo Reformado\nSección III\nArtículo 39.- El Registro estará a cargo de la Secretaría de Educación y Bienestar\nSocial y tendrá por objeto:\nLey de Centros de Atención, Cuidado y Página 11\nI.- Coadyuvar al cumplimiento de los objetivos de esta Ley y la Ley General, con la ejecución de la política pública y con las actividades del Consejo;\nII.- Concentrar la información de los centros de atención que presten servicios para la atención, cuidado y desarrollo integral infantil en Baja California;\nIII.- Contar con un control estadístico que contribuya a la definición de políticas públicas a que se refiere esta Ley;\nIV.- Facilitar la supervisión de los centros de atención;\nV.- Identificar a los prestadores de servicios para la atención, cuidado y desarrollo integral infantil en cualquiera de sus modalidades y tipos, así como mantener actualizada la información que lo conforma;\nVI.- Revisar que las dependencias y entidades de la administración pública estatal, los\nPoderes Legislativo y Judicial y los órganos constitucionalmente autónomos en el Estado, que brinden directamente servicios para la atención, cuidado y desarrollo integral infantil, inscriban el Centro de Atención en el registro local que corresponda, previa revisión del cumplimiento de requisitos conforme a la modalidad y tipo que se trate y conforme a las leyes locales aplicables;\nArtículo 40.- En todo momento se deberá proteger y garantizar la integridad y el buen uso de los datos personales de prestadores de servicios, empleados y usuarios del servicio;\nArtículo 41.- El Registro Estatal deberá orientarse por los principios de máxima publicidad, transparencia y legalidad, cumpliendo con la normatividad en la materia;\nArtículo 42.- Cuando las autoridades competentes emitan permisos, licencias o autorizaciones a que se refiere esta ley, además de llevar su propio registro, procederán a informar al Registro Estatal dicha emisión. El registro deberá actualizarse cada seis meses.\nArtículo 43.- Los centros de atención deberán informar al Registro Estatal el número de sujetos de atención bajo su responsabilidad y las condiciones de la prestación del servicio en materia educativa, de salud y de protección civil, además de la información que les sea solicitada acorde al objeto de esta ley.\nArtículo 44.- El Registro deberá proporcionar al Registro Nacional la siguiente información:\nI.- Ubicación del Centro de Atención;\nII.- Fecha de inicio de operaciones;\nIII.- Capacidad instalada y, en su caso, ocupada;\nIV.- Modalidad y modelo de atención bajo el cual opera;\nLey de Centros de Atención, Cuidado y Página 12\nV.- Identificación del prestador del servicio, sea persona física o jurídico colectiva;\nVI.- Identificación, en su caso, del representante legal;\nSección IV\nDe las modalidades y tipos\nArtículo 45.- Conforme a lo previsto en la Ley General, los Centros de Atención tendrán la modalidad de públicos, privados y mixtos.\nArtículo 46.- En función de su capacidad instalada, los Centros de Atención se clasifican en:\nTipo 1: Cuando tengan una capacidad instalada para dar servicio hasta a 10 sujetos de atención.\nTipo 2: Con capacidad instalada para dar servicio de 11 hasta 50 sujetos de atención.\nTipo 3: Con capacidad instalada para dar servicio de 51 hasta 100 sujetos de atención.\nTipo 4: Con capacidad instalada para dar servicio a más de 100 sujetos de atención.\nArtículo 47.- Todos los tipos de Centros de Atención, deberán ser administrados por personal profesional o capacitado de acuerdo al tipo de servicio y para determinar si la capacidad de las instalaciones es la adecuada, se considerará la proporción existente entre cada sujeto de atención con la superficie del inmueble y con el número de personal profesional o capacitado, tomando como referente mínimo la normatividad reglamentaria dispuesta para las dependencias y entidades de la administración pública federal, incluyendo los organismos de seguridad social.\nCapítulo III\nDel ámbito municipal\nArtículo 48.- De conformidad con lo previsto en la Ley General, son atribuciones de los municipios en materia de la atención, cuidado y desarrollo integral infantil:\nI.- Celebrar convenios de coordinación en la materia con los demás órdenes de gobierno, para alcanzar los fines de la presente ley;\nII.- Coadyuvar con la prestación de servicios para la atención, cuidado y desarrollo integral infantil, así como en la integración y operación del Registro;\nIII.- Determinar los indicadores que permitan evaluar la aplicación del programa a que se refiere el primer párrafo de la fracción II de este artículo;\nLey de Centros de Atención, Cuidado y Página 13\nIV.- Elaborar, aprobar, ejecutar y evaluar el programa municipal en materia de prestación de servicios de atención, cuidado y desarrollo integral infantil, de conformidad con el objeto de la presente ley. Para tal efecto se considerarán las directrices previstas en el\nPrograma Integral de Supervisión, Acompañamiento, Monitoreo y Evaluación del funcionamiento;\nV.- Fomentar, realizar y difundir estudios e investigaciones en la materia;\nVI.- Formular, conducir y evaluar la política municipal en materia de prestación de servicios para la atención, cuidado y desarrollo integral infantil, en congruencia con la\nPolítica Estatal y Federal en la materia;\nVII.- Hacer del conocimiento de la autoridad competente toda aquella conducta o hecho que pueda constituir un ilícito;\nVIII.- Imponer las sanciones, en el ámbito de su competencia, a las que se refiere la presente ley;\nIX.- Promover y celebrar convenios de concertación con los sectores privado y social, las acciones tendientes a favorecer la prestación de servicios para la atención, cuidado y desarrollo integral infantil, en los términos de la presente ley;\nX.- Verificar en su ámbito de competencia, que la prestación de los servicios cumpla con los estándares de calidad y seguridad que exige el principio del interés superior de la niñez;\nXI.- Vigilar el cumplimiento de esta ley y demás disposiciones aplicables en su ámbito de competencia que se relacionen y deriven de la misma, por parte de los prestadores de servicios para la atención, cuidado y desarrollo integral infantil; y\nXII.- Las demás que les señale esta ley y otras disposiciones legales.\nTÍTULO IV\nDE LAS MEDIDAS DE SALUD, SEGURIDAD Y PROTECCIÓN CIVIL\nArtículo 49.- Los Centros de Atención se sujetarán a las disposiciones de esta Ley y deberán prestar atención física, psicológica, sanitaria, alimentaria y educación inicial.\nEn los Centros de Atención Infantil, se deberán instalar equipos y sistemas tecnológicos para la captación, grabación de imágenes y sonidos como una medida de instalaciones, salvaguardando la integridad de las personas menores de edad en términos de las disposiciones legales aplicables.\nPárrafo Adicionado\nLa captación, grabación de imágenes y sonidos a los que se refiere este artículo, se resguardaran por un periodo de 5 años y se pondrán a disposición inmediata de las autoridades competentes que así lo requieran.\nPárrafo Adicionado\nLey de Centros de Atención, Cuidado y Página 14 ley.\nPárrafo Adicionado\nArtículo Reformado\nArtículo 50.- Los Centros de Atención deberán contar con un seguro que cubra daños derivados por la forma en que operan, y que causen daños físicos o psicológicos al menor, seguro que será determinado conforme a la directriz que se marque en la Política Pública.\nArtículo 51.- Para la prestación del servicio de atención, cuidado y desarrollo integral infantil, se deberá cumplir con lo dispuesto en esta Ley, así como en las disposiciones y ordenamientos jurídicos correspondientes en cuanto a salubridad, infraestructura, equipamiento, seguridad, protección civil y medidas de higiene de los Centros de Atención, en cualquiera de sus modalidades, incluidos los servicios educativos, de descanso, juego y esparcimiento, y otros relacionados con el objeto de esta Ley.\nCapítulo I\nDe la admisión y entrega del niño o niña\nArtículo 52.- El ingreso de niñas y niños a los servicios para la atención, cuidado y desarrollo integral infantil se hará de conformidad con los requisitos previstos en las disposiciones normativas aplicables a cada caso y no se podrá condicionar por discapacidad, origen étnico, religión, preferencias sexuales o situación económica de los menores, padres, madres o tutores legales.\nArtículo 53.- Los Centros de Atención, para admitir a un niño o niña, deberán sujetarse a un contrato de adhesión suscrito con el padre, madre, tutor, o quienes ejerzan la patria potestad o custodia sobre el menor, especificando como mínimo la prestación del servicio, la persona o personas autorizadas para recoger al menor y la tolerancia para su entrada y salida.\nArtículo 54.- Los Centros de Atención del sector público, se regularán conforme con su propio reglamento interno.\nArtículo 55.- Para admitir a un niño o niña en un Centro de Atención se deberán presentar, al menos, los siguientes documentos:\nI.- Acta de nacimiento;\nII.- Certificado médico general;\nIII.- Cartilla de vacunación;\nIV.- Copia de la Clave Única de Registro Poblacional del niño, niña y de los padres;\nLey de Centros de Atención, Cuidado y Página 15\nV.- Acreditar ser tutor legal, tener la patria potestad o custodia del menor en su caso;\nVI.- Identificación oficial de los padres o tutores;\nVII.- Comprobante de domicilio; y\nVIII.- Las fotografías del menor, padres o tutores que dicte la política del Centro de\nAtención para los fines correspondientes.\nArtículo 56.- Los Centros de Atención que presten el servicio de educación especial deberán contar con la infraestructura, servicios, personal capacitado y atención adecuada conforme a la discapacidad de que se trate.\nArtículo 57.- Los niños y niñas sólo serán entregados al usuario o a las personas autorizadas para recogerlos, previa exhibición de la credencial expedida por el Centro de\nAtención.\nCapítulo II\nDe la certificación\nArtículo 58.- Las autoridades establecerán programas de formación, actualización y capacitación en materia educativa, de salud y de protección civil, para lograr la certificación del personal que labore en los Centros de Atención, personal que deberá contar con la aptitud psicológica suficiente, certificada por psicólogo o psiquiatra de la Secretaría de\nSalud, para laborar con menores.\nArtículo 59.- La certificación deberá ser renovada de forma anual.\nArtículo 60.- Los Prestadores de servicios para la atención, cuidado y desarrollo integral infantil promoverán la capacitación de su personal, por lo que deberán brindarles las facilidades necesarias para este efecto, de acuerdo a la modalidad correspondiente y sin perjuicio de lo establecido por la legislación laboral.\nEl personal de los Centros de Atención, no deberá contar con antecedente penal o administrativo por los delitos de lesiones, violación, estupro o cualquier otro delito que sea incompatible para el trato con un menor.\nArtículo 61.- El Ejecutivo y los Ayuntamientos implementarán acciones dirigidas a capacitar y certificar anualmente al personal que labora en los Centros de Atención.\nConcluida la vigencia de la certificación, el personal estará incapacitado para laborar con los menores.\nArticulo 62.- Los Ayuntamientos, en coordinación con el Consejo, determinarán las competencias, capacitación y aptitudes con las que deberá contar el personal que pretenda\nLey de Centros de Atención, Cuidado y Página 16 someterse dicho personal, a fin de garantizar la salud, la educación, la seguridad y la integridad física y psicológica de niñas y niños.\nArtículo 63.- El personal que labore en los Centros de Atención garantizará un ambiente de respeto en el marco de los derechos de niñas y niños.\nCapítulo III\nDe las visitas de verificación\nArtículo 64.- Conforme a lo previsto en la Ley General, la Secretaría de Educación y\nBienestar Social, la Secretaría de Salud, la Dirección de Protección Civil y los\nAyuntamientos, en el ámbito de sus respectivas competencias y conforme lo determine su reglamentación, deberán efectuar, cuando menos cada seis meses, visitas de verificación a los centros de atención, aplicando las sanciones correspondientes, sin perjuicio de la supervisión y seguimiento que realicen las autoridades federales en el ámbito de su competencia.\nArtículo 65.- Las visitas de verificación a las que se refiere el artículo anterior tendrán por objetivos los siguientes:\nI.- Vigilar mediante la práctica de la inspección al Centro de Atención, el cumplimiento de los requisitos y obligaciones impuestos por esta Ley, por parte de los prestadores de servicios para la atención, cuidado y desarrollo integral infantil; y\nII.- Notificar oportunamente a la autoridad responsable de la detección oportuna de cualquier riesgo para la integridad física o psicológica de niñas y niños y requerir de ésta su inmediata actuación.\nArtículo 66.- El personal comisionado a las visitas de verificación, deberá estar provisto del documento oficial que lo acredite como tal, así como de la orden escrita, fundada y motivada, expedida por la autoridad correspondiente, en la que se precisará el lugar y los servicios que han de inspeccionarse, el objeto que se persigue, el personal del\nCentro de Atención con el que se llevará a cabo la diligencia, la fecha y el lugar.\nArtículo 67.- El personal autorizado, al iniciar la inspección, se identificará plenamente con la persona con quien se entienda la diligencia, le exhibirá la orden respectiva, entregándole copia de ésta y la requerirá para que en el acto designe los dos testigos.\nArtículo 68.- En toda inspección se levantará acta en la que se harán constar en forma circunstanciada los actos, hechos u omisiones que se hubiesen presentado durante la diligencia.\nArtículo 69.- El inspector deberá sugerir las medidas correctivas, si encuentra\nLey de Centros de Atención, Cuidado y Página 17 irregularidades durante la visita de verificación, mismas que quedarán asentadas en el acta.\nArtículo 70.- La autoridad correspondiente deberá denunciar ante el Ministerio\nPúblico todas aquellas conductas que puedan constituir delitos.\nArtículo 71.- Al finalizar el acta se firmará por la persona con la que se entendió la diligencia, por dos testigos y por el personal autorizado, dejando copia al interesado, aunque se haya negado a firmar dicha acta.\nArtículo 72.- Las irregularidades detectadas, se harán del conocimiento al\nAyuntamiento o Autoridad correspondiente, de forma inmediata y por oficio, para su pronta atención, conocimiento y para los demás efectos legales a que haya lugar.\nArtículo 73.- Si se niega a firmar el representante del Centro de Atención, o de la persona que se encuentre en el Centro y con la que se lleve a cabo la diligencia, el acta circunstanciada motivo de la visita de verificación, se hará constar en la misma acta y la negativa no invalida de ninguna forma los efectos de la visita.\nArtículo 74.- El Consejo, en coordinación con los Municipios, implementará el\nPrograma Integral de Supervisión, Acompañamiento, Monitoreo y Evaluación del funcionamiento, el cual tendrá los siguientes objetivos:\nI.- Garantizar el mejoramiento progresivo y el fortalecimiento de los servicios de atención, cuidado y desarrollo integral infantil;\nII.- Establecer los mecanismos de colaboración técnico operativa para lograr una vigilancia efectiva del cumplimiento de la presente ley y de la normatividad que regula los servicios;\nIII.- Evitar la discrecionalidad y la corrupción en la asignación de autorizaciones para prestar servicios para la atención, cuidado y desarrollo integral infantil; y\nIV.- Garantizar la detección y corrección oportuna de cualquier riesgo para la integridad física o psicológica de niñas y niños.\nArtículo 75.- La madre, el padre, tutor o la persona que tenga la responsabilidad de cuidado y crianza, podrá solicitar la intervención de la autoridad correspondiente para constituir un riesgo en los Centros de Atención.\nTITULO V\nDEL RÉGIMEN DISCIPLINARIO\nArtículo 76.- Las autoridades verificadoras competentes podrán imponer medidas disciplinarias en los Centros de Atención, cuando adviertan situaciones que pudieran poner en riesgo la integridad de los sujetos de atención de cuidado y desarrollo integral infantil.\nLey de Centros de Atención, Cuidado y Página 18\nArtículo 77.- Cualquier ciudadano, podrá denunciar las conductas que constituyan una infracción a esta Ley.\nCapítulo I\nDe las medidas precautorias\nArtículo 78.- A efecto de prevenir situaciones de riesgo a la higiene, salud e integridad de los niños y niñas, se deberán imponer las medidas precautorias siguientes:\nI.- Apercibimiento escrito, el cual procederá en caso de que no se atienda la recomendación en el plazo establecido, señalándose un término de hasta diez días para corregir la causa que lo motivó;\nII.- Recomendación escrita, en la que se fije un plazo de hasta treinta días para corregir la causa que le dio origen; y\nIII.- Suspensión total o parcial de actividades en el Centro de Atención que se mantendrá hasta en tanto se corrija la situación que le dio origen.\nArtículo 79.- Los plazos a que se refiere el artículo anterior podrán ampliarse siempre y cuando ello se justifique a partir de la situación específica que originó la medida.\nArtículo 80.- La autoridad podrá suspender total o parcialmente actividades, con independencia de las demás medidas precautorias, cuando la causa lo amerite.\nCapítulo II\nDe las sanciones\nArtículo 81.- Conforme a lo previsto en la Ley General, los Ayuntamientos y las dependencias de la administración pública, en sus respectivos ámbitos de competencia, podrán aplicar las siguientes sanciones, como consecuencia al incumplimiento de esta Ley y su reglamento:\nI.- Amonestación con apercibimiento, cuando las infracciones sean menores y no reiteradas, entendiéndose por faltas leves las que se cometan por error o ignorancia, siempre y cuando no hayan afectado la seguridad o salud de los menores, en la forma inmediata;\nII.- Amonestación pública, cuando la infracción menor sea reiterada Multa de 500 a\n10,000 veces el valor diario de la Unidad de Medida y Actualización vigente, cuando:\nFracción Reformada\na) Exista reiteración en faltas menores;\nb) Se impida total o parcialmente el desarrollo de la visita por parte de los supervisores correspondientes;\nLey de Centros de Atención, Cuidado y Página 19\nc) Elaborar los alimentos ofrecidos a niñas y niños sin apego a los requisitos mínimos de alimentación balanceada e higiene establecidos en la normatividad aplicable;\nd) Modificar la estructura del inmueble o la distribución de los espacios sin contar con los permisos de la autoridad competente;\ne) Incumplir con las medidas de salud y atención médica en los términos que establezca la normatividad correspondiente; y\nf) Realizar por parte del personal de los Centros de Atención, algún acto de discriminación contra cualquiera de los trabajadores, padres, niños o niñas.\nLa multa no será condonable y se hará efectiva por las autoridades fiscales del\nEstado o de cada Ayuntamiento, a través del procedimiento administrativo de ejecución, en los términos previstos por la Ley.\nIII.- Suspensión temporal de la autorización, en los casos siguientes:\na) Cuando no se cuente con el personal competente o suficiente para brindar los servicios para la atención, cuidado y desarrollo integral infantil;\nb) Cuando no se regularice la situación que dio origen a la imposición de la multa o no haberla cubierto;\nc) Realizar actividades con niñas y niños fuera de las instalaciones del Centro de\nAtención sin el previo consentimiento de los padres, tutores o quienes tengan la responsabilidad de su atención, cuidado y crianza;\nd) El incumplimiento de los requisitos de autorización;\ne) El descuido por parte del personal que ponga en peligro la salud o la integridad física o psicológica de niñas y niños;\nf) Reincidir en alguna de las causas que originen las sanciones contenidas en el artículo que antecede; y\ng) En caso de pérdida de la vida o la existencia de lesiones graves en una niña o niño, en tanto se deslinde la responsabilidad al Centro de Atención o personal relacionado con el mismo. determine que se han solventado las irregularidades.\nIV.- Revocación de la autorización y cancelación del registro, cuando concurran las siguientes causas:\na) Pérdida de la vida o la existencia de lesiones graves en una niña o niño, disposiciones contenidas en la presente Ley;\nLey de Centros de Atención, Cuidado y Página 20\nb) Comisión de cualquier delito sexual acreditado al personal del Centro de Atención mediante resolución judicial;\nc) Falta de regularización oportuna de la situación que dio origen a la imposición de vigentes;\nd) Interrupción sin causa justificada de las actividades del Centro de Atención por un lapso mayor de 5 días naturales; y\ne) Realización reiterada de actividades diferentes a las autorizadas.\nA las personas a las que se les revoque la autorización no se les podrá expedir nueva licencia de funcionamiento.\nArtículo Reformado\nArtículo 82.- Son parámetros para calificar las infracciones y para individualizar las sanciones, los siguientes:\nI.- La gravedad de la infracción;\nII.- El riesgo o daño que se haya producido o pueda producirse en la salud de las personas, sobre todo de los menores;\nIII.- Las condiciones socioeconómicas del infractor;\nIV.- La calidad de reincidente del infractor; y\nV.- La naturaleza y demás circunstancias que sirvan para individualizar la sanción.\nArtículo 83.- Las sanciones administrativas, son independientes de las penales que resulten como consecuencia de la comisión de delitos en contra de niñas y niños en los\nCentros de Atención, Cuidado y Desarrollo Integral Infantil de acuerdo a lo establecido en la legislación penal correspondiente.\nArtículo 84.- Las violaciones a los preceptos de esta ley, sus reglamentos y disposiciones que de ella emanen, por parte de los servidores públicos constituyen infracción\nPúblicos del Estado de Baja California, sin perjuicio de las penas que correspondan cuando sean constitutivas de delitos.\nARTÍCULOS TRANSITORIOS\nPRIMERO.- La presente Ley entrará en vigor al día siguiente de su publicación en el\nPeriódico Oficial del Estado.\nSEGUNDO.- Las disposiciones reglamentarias de esta Ley deberán ser expedidas por el Ejecutivo del Estado y los Ayuntamientos de los Municipios dentro de los 90 días\nLey de Centros de Atención, Cuidado y Página 21 siguientes a la entrada en vigor de la presente Ley.\nTERCERO.- Los prestadores de servicios de atención, cuidado y desarrollo integral infantil que se encuentren operando con anterioridad a la entrada en vigor a esta Ley, adecuaciones necesarias a los Centros de Atención, a fin de obtener la autorización respectiva.\nCUARTO.- El Consejo al que se refiere esta Ley deberá instalarse dentro de los noventa días siguientes a la entrada en vigor de la Ley y tendrá 180 días contados a partir de su instalación para elaborar un diagnóstico sobre el estado que guardan los Centros de\nAtención en Baja California.\nDADO en el Salón de Sesiones “Lic. Benito Juárez García” del H. Poder Legislativo del Estado de Baja California, en la Ciudad de Mexicali, B.C., a los veintiséis días del mes de marzo del año dos mil quince.\nDIP. FCO. ALCIBÍADES GARCÍA LIZARDI\nPRESIDENTE\n(RÚBRICA)\nDIP. ROSALBA LÓPEZ REGALADO\nSECRETARIA\n(RÚBRICA)\nDE CONFORMIDAD CON LO DISPUESTO POR LA FRACCION I DEL ARTÍCULO 49\nMEXICALI, BAJA CALIFORNIA, A LOS ONCE DÍAS DEL MES DE MAYO DEL AÑO\nDOS MIL QUINCE.\nFRANCISCO ARTURO VEGA DE LAMADRID\nGOBERNADOR DEL ESTADO\n(RÚBRICA)\nFRANCISCO RUEDA GOMEZ\nSECRETARIO GENERAL DE GOBIERNO\n(RÚBRICA)\nLey de Centros de Atención, Cuidado y Página 22\nArtículo 3.- Fue reformado por Decreto No. 284, publicado en el Periódico Oficial No.\nLegislatura, siendo Gobernador Constitucional el C. Francisco Arturo Vega de Lamadrid\n2013-2019;\nArtículo 9.- Fue reformado por Decreto No. 284, publicado en el Periódico Oficial No.\n59, de fecha 28 de diciembre de 2018, Tomo CXXV, Sección III, expedido por la H. XXII\nLegislatura, siendo Gobernador Constitucional el C. Francisco Arturo Vega de Lamadrid\n2013-2019;\nArtículo 12.- Fue reformado por Decreto No. 284, publicado en el Periódico Oficial No.\n59, de fecha 28 de diciembre de 2018, Tomo CXXV, Sección III, expedido por la H. XXII\nLegislatura, siendo Gobernador Constitucional el C. Francisco Arturo Vega de Lamadrid\n2013-2019;\nArtículo 28.- Fue reformado por Decreto No. 284, publicado en el Periódico Oficial No.\n59, de fecha 28 de diciembre de 2018, Tomo CXXV, Sección III, expedido por la H. XXII\nLegislatura, siendo Gobernador Constitucional el C. Francisco Arturo Vega de Lamadrid\n2013-2019;\nArtículo 30.- Fue reformado por Decreto No. 284, publicado en el Periódico Oficial No.\n59, de fecha 28 de diciembre de 2018, Tomo CXXV, Sección III, expedido por la H. XXII\nLegislatura, siendo Gobernador Constitucional el C. Francisco Arturo Vega de Lamadrid\n2013-2019;\nArtículo 35.- Fue reformado por Decreto No. 284, publicado en el Periódico Oficial No.\n59, de fecha 28 de diciembre de 2018, Tomo CXXV, Sección III, expedido por la H. XXII\nLegislatura, siendo Gobernador Constitucional el C. Francisco Arturo Vega de Lamadrid\n2013-2019;\nArtículo 38.- Fue reformado por Decreto No. 284, publicado en el Periódico Oficial No.\n59, de fecha 28 de diciembre de 2018, Tomo CXXV, Sección III, expedido por la H. XXII\nLegislatura, siendo Gobernador Constitucional el C. Francisco Arturo Vega de Lamadrid\n2013-2019;\nArtículo 49.- Fue reformado por Decreto No. 170, publicado en el Periódico Oficial No.\nLegislatura, siendo Gobernadora Constitucional la C. Marina del Pilar Ávila Olmeda 20212027;\nArtículo 81.- Fue reformado por Decreto No. 281, publicado en el Periódico Oficial No.\nLey de Centros de Atención, Cuidado y Página 23\nLegislatura, siendo Gobernador Constitucional el C. Francisco Arturo Vega de Lamadrid\n2013-2019;\nLey de Centros de Atención, Cuidado y Página 24\nARTÍCULO DÉSIMO NOVENO TRANSITORIO DEL DECRETO No. 281, POR EL\nQUE SE REFORMA A LA FRACCIÓN II DEL ARTÍCULO 81, PUBLICADO EN EL\nPERIÓDICO OFICIAL No. 55, SECCION IV, TOMO CXXV, DE FECHA 30 DE NOVIEMBRE\nDE 2018, EXPEDIDO POR LA H. XXII LEGISLATURA, SIENDO GOBERNADOR\nCONSTITUCIONAL EL C. FRANCISCO ARTURO VEDA DE LAMADRID 2013-2019.\nARTÍCULOS TRANSITORIOS\nARTÍCULO PRIMERO.- El presente decreto entrará en vigor al día siguiente al de su publicación en el Periódico Oficial del Estado de Baja California.\nARTÍCULO SEGUNDO.- El valor diario de la Unidad de Medida y Actualización a la fecha de entrada en vigor, se tomará el valor publicado en el Diario Oficial de la Federación por el INEGI. El valor de la Unidad de Medida y Actualización a la fecha de entrada en vigor del presente Decreto, será producto de multiplicar el valor referido en el párrafo anterior por\n30.4. Por su parte, el valor anual será el producto de multiplicar el valor inicial mensual por\n12.\nARTÍCULO TERCERO.- Todas las menciones al salario mínimo como unidad de cuenta, índice, base, medida o referencia para determinar la cuantía de las obligaciones, sanciones, multas administrativas, conceptos de pago y montos de referencia, se entenderán referidas a la Unidad de Medida y Actualización.\nDADO en el Salón de Sesiones “Lic. Benito Juárez García” del H. Poder Legislativo del Estado de Baja California, en la Ciudad de Mexicali, B.C., a los veinticinco días del mes de octubre del año dos mil dieciocho.\nDIP. ROCÍO LÓPEZ GOROSAVE\nPRESIDENTA\n(RÚBRICA)\nDIP. MÓNICA HERNÁNDEZ ÁLVAREZ\nSECRETARIA\n(RÚBRICA)\nDE CONFORMIDAD CON LO DISPUESTO POR LA FRACCIÓN I DEL ARTÍCULO 49\nMEXICALI, BAJA CALIFORNIA, A LOS TREINTA DÍAS DEL MES DE NOVIEMBRE\nDEL AÑO DOS MIL DIECIOCHO.\nFRANCISCO ARTURO VEGA DE LAMADRID\nGOBERNADOR DEL ESTADO\nLey de Centros de Atención, Cuidado y Página 25\n(RÚBRICA)\nFRANCISCO RUEDA GÓMEZ\nSECRETARIO GENERAL DE GOBIERNO\n(RÚBRICA)\nARTÍCULO ÚNICO TRANSITORIO DEL DECRETO No. 284, POR EL QUE SE\nREFORMA A LOS ARTÍCULOS 3, 9, 12, 28, 30, 35 Y 38, PUBLICADO EN EL PERIÓDICO\nOFICIAL No. 59, SECCION III, TOMO CXXV, DE FECHA 28 DE DICIEMBRE DE 2018,\nEXPEDIDO POR LA H. XXII LEGISLATURA, SIENDO GOBERNADOR CONSTITUCIONAL\nEL C. FRANCISCO ARTURO VEDA DE LAMADRID 2013-2019.\nARTÍCULOS TRANSITORIOS\nÚNICO.- Las presentes reformas entrarán en vigor al día siguiente al de su publicación en el Periódico Oficial del Estado.\nDADO en el Salón de Sesiones “Lic. Benito Juárez García” del H. Poder Legislativo del Estado de Baja California, en la Ciudad de Mexicali, B.C., a los ocho días del mes de\nNoviembre del año dos mil dieciocho.\nDIP. ROCÍO LÓPEZ GOROSAVE\nPRESIDENTA\n(RÚBRICA)\nDIP. ALFA PEÑALOZA VALDEZ\nPRO SECRETARIA\n(RÚBRICA)\nDE CONFORMIDAD CON LO DISPUESTO POR LA FRACCIÓN I DEL ARTÍCULO 49\nMEXICALI, BAJA CALIFORNIA, A LOS VEINTIOCHO DÍAS DEL MES DE\nDICIEMBRE DEL AÑO DOS MIL DIECIOCHO.\nFRANCISCO ARTURO VEGA DE LAMADRID\nGOBERNADOR DEL ESTADO\n(RÚBRICA)\nFRANCISCO RUEDA GÓMEZ\nSECRETARIO GENERAL DE GOBIERNO\n(RÚBRICA)\nLey de Centros de Atención, Cuidado y Página 26\nARTÍCULO ÚNICO TRANSITORIO DEL DECRETO No. 170, POR EL QUE SE\nREFORMA EL ARTÍCULO 49, PUBLICADO EN EL PERIÓDICO OFICIAL No. 70, SECCIÓN\nLEGISLATURA, SIENDO GOBERNADORA CONSTITUCIONAL LA C. MARINA DEL PILAR\nÁVILA OLMEDA 2021-2027.\nTRANSITORIOS\nPRIMERO. La presente reforma entrará en vigor al día siguiente de su publicación en el Periódico Oficial del Estado.\nSEGUNDO. El Ejecutivo del Estado y los Municipios, en el ámbito de sus respectivas competencias, contarán con un plazo de 90 días naturales, contados al día siguiente de la publicación del presente Decreto, para realizar las modificaciones reglamentarias correspondientes.\nDADO en Sesión Ordinaria de la XXIV Legislatura en la Ciudad de Mexicali, B.C., a los diez días del mes de noviembre del año dos mil veintidós.\nDIP. ALEJANDRA MARÍA ANG HERNÁNDEZ\nPRESIDENTA\n(RÚBRICA)\nDIP. DUNNIA MONTSERRAT MURILLO LÓPEZ\nSECRETARIA\n(RÚBRICA)\nDE CONFORMIDAD CON LO DISPUESTO POR LA FRACCIÓN I DEL ARTÍCULO 49\nCALIFORNIA, IMPRÍMASE Y PUBLÍQUESE.\nMEXICALI, BAJA CALIFORNIA, A LOS DIECISÉIS DÍAS DEL MES DE NOVIEMBRE\nDEL AÑO DOS MIL VEINTIDÓS.\nMARINA DEL PILAR ÁVILA OLMEDA\nGOBERNADORA DEL ESTADO\nDE BAJA CALIFORNIA\n(RÚBRICA)\nCATALINO ZAVALA MÁRQUEZ\nSECRETARIO GENERAL DE GOBIERNO\nDEL ESTADO DE BAJA CALIFORNIA\n(RÚBRICA)\nLey de Centros de Atención, Cuidado y Página 27",
  "ordenamiento": "REGLAMENTO",
  "jurisdiccion": "BAJA CALIFORNIA",
  "fuente_oficial": "Periódico Oficial",
  "FECHA PER OFIC": "2022/12/02",
  "ESTATUS": "VIGENTE",
  "TOMO": "TOMO_VI",
  "URL": "https://www.congresobc.gob.mx/Documentos/ProcesoParlamentario/Leyes/TOMO_VI/20221202_LEYDESINTEGRALINFANTI.PDF",
  "es_escaneado": false,
  "tiene_tablas": true,
  "materia": [
    "social",
    "salud",
    "educación",
    "cultura"
  ]
}