{
  "titulo": "Ley DE DESARROLLO AGROPECUARIO DEL ESTADO DE BAJA CALIFORNIA",
  "Contenido": "LEY DE DESARROLLO AGROPECUARIO DEL ESTADO\nDE BAJA CALIFORNIA\nPublicada en el Periódico Oficial No. 43, Tomo CXVII, Sección I, de fecha\nTÍTULO PRIMERO\nDISPOSICIONES GENERALES\nCAPÍTULO I\nOBJETO Y APLICACIÓN DE LA LEY\nARTÍCULO 1.- La presente Ley es de orden público e interés social, tiene por objeto, la organización, control, sanidad, protección, explotación racional, fomento y conservación de la actividad agropecuaria en el Estado de Baja California, promoviendo prácticas sustentables que aseguren la conservación de los recursos naturales, la mitigación del impacto ambiental y la adaptación al cambio climático. Asimismo, garantizará la legítima propiedad de las especies animales, productos y subproductos agropecuarios, además de controlar su circulación dentro de la Entidad.\nArtículo Reformado\nARTÍCULO 2.- Se declara de utilidad pública en el Estado:\nI.- La planeación, organización, protección, conservación, fomento, explotación, reproducción, mejoramiento, instalación y comercialización de industrias agropecuarias, de sus productos y subproductos en el Estado;\nII.- La planeación para promover el pleno aprovechamiento, protección conservación, mejoramiento, fomento y explotación racional de los terrenos de uso agropecuario y del recurso de agua. determinen las Normas Oficiales Mexicanas, la normatividad ambiental del Estado y demás disposiciones aplicables.\nPárrafo Adicionado\nIII.- El fomento, mejoramiento, protección conservación y explotación de los terrenos agrícolas, pastizales naturales y artificiales;\nIV.- La organización con fines económicos y sociales de las personas físicas o morales que se dedican a la producción y explotación agropecuaria;\nLey de Desarrollo Agropecuario del Estado de Baja California. Página 1\nV.- La investigación científica aplicada a las actividades agropecuarias en todos sus aspectos y las acciones con el fin de lograr la protección, conservación, clasificación y selección de sus especies, así como de los productos y subproductos que genere su explotación y aprovechamiento sustentable;\nVI.- Las campañas para la erradicación de plagas y enfermedades que afecten a las especies agropecuarias;\nVII.- La Conservación y explotación del ganado productor de leche y el desarrollo de la industria lechera tendiente a mejorar la producción y distribución de la leche y sus subproductos. La comercialización de productos sustitutos sin valor nutricional, deberán de contener la información adecuada, para beneficio del consumidor.\nFracción Reformada\nVIII.- La supervisión, inspección, control, regulación y sanción de la movilización de las especies animales, productos y subproductos agropecuarios;\nIX.- El control del manejo y aplicación de químicos utilizados en la actividad agropecuaria;\nX.- La construcción, el fomento, conservación y mejoramiento de la infraestructura hidroagrícola y equipamiento agropecuario, destinado a la producción agropecuaria;\nFracción Reformada\nXI.- El servicio de asistencia técnica integral a los productores agropecuarios;\nXII.- El servicio de clasificación estatal de alimentos, y\nXIII.- El fomento de la reconversión productiva sustentable, mediante la incorporación de cambios tecnológicos, y de procesos que contribuyan a la productividad y competitividad del sector agropecuario, a la seguridad y soberanía alimentarias y al óptimo uso de las tierras mediante apoyos e inversiones complementarias;\nXIV.- Las demás que señalen las leyes y disposiciones federales y locales.\nFracción Reformada\nArtículo Reformado\nARTÍCULO 3.- Quedan sujetos a las disposiciones de esta Ley:\nI.- Los productores agropecuarios, los industriales, comerciantes y transportistas de productos y subproductos de la actividad agropecuaria;\nII.- Las personas físicas y morales que directa o indirectamente se dediquen o incidan en los sistemas y procesos productivos agropecuarios del Estado, y\nLey de Desarrollo Agropecuario del Estado de Baja California. Página 2\nIII.- Los terrenos dedicados directa o indirectamente a las explotaciones agrícolas y pecuarias, así como las instalaciones y medios de transporte para la producción y aprovechamiento de sus productos y subproductos.\nARTÍCULO 4.- Los Productores, Organizaciones, Sociedades, Asociaciones y\nUniones de Productores Agrícolas, Ganaderas, los comerciantes en mayoreo o en detalle, y los industriales de productos y subproductos de las especies a que se refiere esta Ley, están obligados a registrarse en la Secretaría de Agricultura y Desarrollo Rural del Estado, quien les expedirá la patente correspondiente, misma que deberá revalidarse dentro de los primeros noventa días de cada año.\nArtículo Reformado\nCAPÍTULO II\nDE LA TERMINOLOGÍA EMPLEADA EN ESTA LEY\nARTÍCULO 5.- Para los efectos de esta Ley se entiende por:\nI.- Actividad agropecuaria: Aquella relacionada con los procesos productivos basados en recursos naturales renovables: agricultura, ganadería y de otros animales domésticos a que se refiere la presente Ley;\nII.- Actividad ganadera o pecuaria: Conjunto de acciones para la explotación racional de especies animales orientadas a la producción de carne, leche, huevo, miel, lana y otras de interés zootécnico, con la finalidad de satisfacer necesidades vitales o del desarrollo humano;\nIII.- Agricultor: A toda persona física o moral que con fines de explotación y aprovechamiento cultive, posea o sea propietario de terrenos o aproveche instalaciones para la producción agrícola;\nIV.- Agricultor especializado: A toda persona física o moral que se dedique a la explotación de terrenos o instalaciones en el cultivo de determinada especie y específicamente a la producción de semillas patrones o especies para trasplante ya sean hortícolas o frutales;\nIV BIS.- Agricultura regenerativa: Es la rehabilitación del suelo con el objetivo de áreas, mediante métodos productivos que a través de prácticas que mejoren las productividades y contribuyan a la salud de los recursos naturales, el bienestar social y la seguridad económica de las personas productoras;\nFracción Adicionada\nTexto reubicado, antes era fracción XXXIV\nV.- Agroclústeres: Concentración geográfica de empresas de producción agropecuaria, proveedores especializados, oferentes de servicios e instituciones asociadas\nLey de Desarrollo Agropecuario del Estado de Baja California. Página 3 sostenido de economías de aglomeración;\nFracción Reformada\nVI.- Sistema dinámico que implica la combinación de dos procesos productivos, el agrícola y el industrial, con el que permite transformar de manera rentable los productos provenientes del campo;\nFracción Reformada\nVII.- Apicultura: La actividad relacionada a la cría, explotación y mejoramiento genético de las abejas, así como la industrialización de sus productos y subproductos;\nApiario: Al conjunto de colmenas instaladas en un lugar determinado;\nApicultor: Toda persona física o moral que se dedique a la cría y explotación, producción o mejoramiento de las abejas;\nColmena: La caja o cajón que se destina para habitación de las abejas a fin de que ahí finquen sus panales para el almacenamiento de miel;\nFracción Reformada\nVIII.- Arete: Identificación metálica o de plástico con inscripción registrada y autorizada por la Secretaría que se aplica en la oreja del ganado mayor y menor. En otra especie animal, puede aplicarse en otra parte del cuerpo;\nFracción Reformada\nIX.- Asistencia técnica: Al conjunto de acciones continuas, programadas y actualizadas por la experiencia y la investigación, y que tienden a mejorar los niveles de producción y productividad;\nFracción Reformada\nX.- Avicultura: La reproducción, cría y explotación de las especies y variedades de aves útiles para la alimentación humana o para la obtención de otros beneficios, directamente o por el aprovechamiento de sus subproductos;\nFracción Reformada\nXI.- Corridas o velas: La reunión que los productores hacen del ganado que se agosta en terrenos de su propiedad o de los cuales tengan posesión;\nFracción Reformada\nXII.- Desarrollo Rural Sustentable: El mejoramiento integral del bienestar social de núcleos considerados urbanos de acuerdo con las disposiciones aplicables, asegurando la conservación permanente de los recursos naturales, mediante el uso racional de los mismos, así como la biodiversidad y los servicios ambientales de dicho territorio;\nFracción Reformada\nXIII.- Especie animal; aquella cuya reproducción sea controlada por el hombre, con el objeto de propagarla, para obtener satisfactores de necesidades vitales o de desarrollo humano;\nLey de Desarrollo Agropecuario del Estado de Baja California. Página 4\nFracción Reformada\nFracción Reformada\nXV.- Fierro o marca de herrar: La señal que se graba en el cuarto trasero izquierdo generalmente con fierro candente;\nFracción Reformada\nXVI.- Ganadería Diversificada: Rama de la ganadería que, además de estar orientada a la producción de ganado doméstico, ha diversificado la producción mediante el aprovechamiento sustentable de los recursos naturales renovables que ofrecen sus predios, utiliza las distintas especies domésticas, silvestres, nativas e introducidas, y lacustres, las cuales transforman la producción integral en bienes de consumo, promoviendo el aprovechamiento sustentable, extractivo y no extractivo, de las especies silvestres, mediante actividades de caza, recreación, consumo, productos artesanales, exhibición, investigación, industrialización y comercialización;\nFracción Reformada\nXVII.- Ganadero: A toda persona física o moral que con fines de explotación pecuaria, sea propietaria de ganado de las especies a que se refieren las fracciones XVI y\nXVII de este apartado, y que tenga definido su asiento de producción;\nFracción Reformada\nXVIII.- Ganadero especializado: A todo aquel que se dedique a la cría y aprovechamiento de determinada especie animal y específicamente a la explotación de alguna función zootécnica de sus individuos;\nFracción Reformada\nXIX.- Ganado mayor: A los animales domésticos o domesticables de las especies bovina y equina;\nFracción Reformada\nXX.- Ganado menor: A los animales domésticos o domesticables de las especies ovina, porcina, caprina, cunícula, incluso las apícolas y avícolas;\nFracción Reformada\nXXI.- Granjas o Plantas Avícolas: Las empresas especializadas en la reproducción, cría y explotación avícola;\nFracción Reformada\nXXII.- Granja porcícola: La empresa pecuaria especializada en la cría, reproducción, mejoramiento y manejo de los cerdos para pie de cría o abasto;\nFracción Reformada\nXXII BIS.- Guía de tránsito Electrónica: Guía de tránsito emitida mediante un\nSistema de Registro Electrónico de la Movilización;\nFracción Adicionada\nLey de Desarrollo Agropecuario del Estado de Baja California. Página 5\nXXIII.- Ley: La Ley de Desarrollo Agropecuario del Estado de Baja California;\nFracción Reformada\nXXIV.- Marca de venta: Es potestativa y es la señal que se pone comúnmente en la paleta del animal del mismo lado en que se grabó el fierro que nulifica, esta deberá ser de fierro candente;\nFracción Reformada\nXXV.- Marca o reseña: La que se pone en la quijada de la marca o reseña del último propietario, con fierro candente, tinta indeleble o ácido corrosivo;\nFracción Reformada\nXXVI.- Orejano: Animal que no cuenta con ninguna marca de identificación en el cuerpo;\nFracción Reformada\nXXVII.- Porcicultura: La cría, reproducción, mejoramiento y explotación de los cerdos;\nFracción Reformada\nXXVIII.- Recuento: La verificación de la cantidad de semovientes que le pertenecen a un determinado ganadero y separar los ajenos;\nFracción Reformada\nXXIX.- Realeo: Desalojo de ganado que mediante el recuento realizado, resultó ser ajeno;\nFracción Reformada\nXXX.- Reconversión Productiva: Es el cambio o transformación voluntaria hacia una producción agropecuaria diferente a la actual; busca innovar y agregar valor a la producción mediante la utilización de sistemas tecnológicos eficientes en toda la cadena productiva;\nFracción Adicionada\nXXXI.- Secretaría: La Secretaría de Agricultura y Desarrollo Rural del Estado de Baja\nCalifornia;\nFracción Adicionada\nFracción Reformada\nXXXII.- Señal de sangre: Las cortadas, incisiones o perforaciones que se hagan en las orejas del ganado; y,\nFracción Adicionada\nFracción Reformada\nXXXIII.- Tatuajes: La impresión de dibujos, letras, números indelebles en las orejas o en el labio del animal.\nFracción Adicionada\nFracción Reformada\nArtículo Reformado\nLey de Desarrollo Agropecuario del Estado de Baja California. Página 6\nCAPÍTULO III\nDE LAS AUTORIDADES COMPETENTES.\nARTÍCULO 6.- Son autoridades competentes para la aplicación de esta Ley:\nFracción Reformada\nII.- La persona Titular de la Secretaría de Agricultura y Desarrollo Rural del Estado;\nFracción Reformada\nIII.- Las personas Titulares de las Subsecretarias de Agricultura y Desarrollo Rural del\nEstado;\nFracción Reformada\nIV.- Los Directores de área de la Secretaría;\nV.- Los representantes de la Secretaría en las diferentes Zonas o Municipios;\nVI.- Los jefes de departamentos de la Secretaría;\nVII.- Los inspectores agropecuarios que designe la Secretaría, y\nVIII.- Derogada.\nFracción Derogada\nArtículo Reformado\nARTÍCULO 7.- Son autoridades, y organismos auxiliares y de cooperación respectivamente:\nI.- La Fiscalía General del Estado de Baja California, los cuerpos de seguridad pública federales, estatales o municipales;\nFracción Reformada\nII.- Los Inspectores habilitados por la Secretaría, la Secretaría de Salud del Estado y las Organizaciones de productores agropecuarios, en los términos de la reglamentación respectiva; y\nIII.- Los presidentes y delegados municipales en los lugares que no cuenten con autoridad en la materia.\nArtículo Reformado\nARTÍCULO 8.- La Secretaría tendrá las siguientes facultades y atribuciones:\nA) En lo General:\nI.- Celebrar con la aprobación del Ejecutivo del Estado, convenios y acuerdos de coordinación, colaboración, participación y coadyuvancia en materia agropecuaria;\nLey de Desarrollo Agropecuario del Estado de Baja California. Página 7\nII.- Imponer las medidas de seguridad y las sanciones que correspondan a las infracciones establecidas en la presente Ley, comunicando las sanciones económicas que requerimiento de liquidación y ejecución;\nFracción Reformada\nIII.- Designar a los inspectores agropecuarios, y habilitar a los inspectores externos para esa función;\nIV.- Solicitar la cooperación en su caso, de los organismos auxiliares previstos en esta\nLey, para control y desarrollo de la agricultura, ganadería, avicultura, apicultura y del mercado de sus productos y subproductos;\nV.- Promover y fortalecer la participación de Universidades y Centros de Investigación\nCientífica, en el desarrollo agropecuario así como analizar, sancionar y coordinar todos aquellos estudios, proyectos e investigaciones científicas tendientes a fomentar el desarrollo del sector.\nVI.- Promover una mejor distribución y comercialización de la producción agropecuaria del Estado, privilegiando el abastecimiento del mercado interno, y\nVII.- Coadyuvar, promover y gestionar la transferencia al Gobierno del Estado, de programas, recursos y atribuciones en materia agropecuaria que en el marco legal sean factibles y de beneficio para la población del Estado de Baja California;\nVIII.- Impulsar acciones dirigidas a la reconversión productiva, competitividad e innovación tecnológica de las actividades agropecuarias;\nIX.- Fortalecer, priorizar y consolidar competitivamente a los agroclústeres del sector rural;\nX.- Impulsar la investigación y transferencia de tecnología para atender las cadenas productivas y mejorar su productividad y competitividad; y\nXI.- Las demás que le atribuyan las leyes, reglamentos, decretos y acuerdos sobre la materia.\nInciso Reformado\nB) En lo Agrícola:\nI.- Procurar y vigilar el debido abastecimiento de productos y subproductos agrícolas, tales como granos, legumbres y frutas en sus diferentes presentaciones, con objeto de cubrir las necesidades del Estado, vigilando que se cumplan las normas de calidad y sanidad establecidas;\nLey de Desarrollo Agropecuario del Estado de Baja California. Página 8\nII.- Autorizar o negar los permisos de entrada o salida del Estado de los productos y subproductos agrícolas, dando preferencia al productor local;\nIII.- Organizar a los productores agrícolas con base en la presente Ley, leyes y normas aplicables;\nIV.- Establecer el padrón de productores agrícolas del Estado;\nV.- Fomentar la producción y consumo de los productos de la región;\nVI.- Promover, vigilar, conservar y mejorar las instalaciones e infraestructura agrícola del Estado;\nVII.- Determinar la forma y documentación que deberá expedirse y requerirse para la movilización y estricta vigilancia sanitaria de los productos y subproductos agrícolas en el\nEstado, sobre todo aquellos que provienen de fuera de la Entidad;\nVIII.- Promover la protección y vigilancia en las explotaciones agrícolas, de la acción de plagas y enfermedades establecidas, e impedir la entrada de aquellas consideradas como exóticas;\nIX.- Promover la producción de semillas mejoradas en el Estado, con la finalidad de ser autosuficientes y lograr la exportación;\nX.- Divulgar toda aquella información relacionada con el sector que se considere de utilidad y fomento a la producción, y\nXI.- Promover la formación de agroindustrias de productos y subproductos agrícolas, así como fomentar el consumo de los mismos.\nC) En lo Ganadero:\nI.- Procurar el debido abastecimiento de carnes, productos y subproductos pecuarios en general para cubrir las necesidades de consumo en el Estado, vigilando que se cumplan las normas de calidad y sanidad establecidas;\nII.- Autorizar o negar con observación a las normas sanitarias los permisos para entrada o salida del Estado de animales y demás productos y subproductos pecuarios; en beneficio del productor y consumidor local.\nIII.- Reglamentar el sacrificio de animales en etapa productiva para preservar las explotaciones de cría;\nIV.- Apoyar a las organizaciones ganaderas en los términos de la Ley de\nOrganizaciones Ganaderas;\nLey de Desarrollo Agropecuario del Estado de Baja California. Página 9\nV.- Integrar el Padrón Ganadero Estatal, que incluirá, por lo menos, el registro de patentes, marcas de herrar, señales de sangre y tatuajes para ganado, y otros animales, en los términos de las disposiciones reglamentarias;\nVI.- Expedir títulos de marcas de herrar, señales de sangre y tatuajes;\nVII.- Fomentar la producción y consumo de todos los productos y subproductos de origen animal de la industria pecuaria local;\nVIII.- Vigilar la producción, conservación y comercialización de los productos y subproductos pecuarios, así como la instalación, operación, conservación y mejoramiento de toda unidad de producción pecuaria, así como plantas pasteurizadoras; rastros municipales, Tipo Inspección Federal (TIF) y particulares, salas de matanza, empacadoras y tenerías;\nIX.- Determinar la forma y documentación que deberá requerirse para expedir guías de tránsito de animales, productos y subproductos pecuarios para su movilización en el\nEstado;\nX.- Establecer y fortalecer el servicio de clasificación de alimentos;\nXI.- Otorgar los permisos para el establecimiento de expendios de carne clasificada, y\nXII.- Subastar los animales cuya procedencia legal no sea acreditada en los términos de la presente Ley, observando las disposiciones aplicables en la materia; y\nXIII.- Impulsar actividades de ganadería diversificada en el Estado de Baja California.\nArtículo Reformado\nARTÍCULO 9.- Los inspectores agropecuarios que sean designados por la Secretaría, deberán reunir los siguientes requisitos:\nI.- Ser ciudadano mexicano, en pleno ejercicio de sus derechos;\nII.- Ser profesionista, técnico titulado o poseer los conocimientos equivalentes a juicio de la Secretaría;\nIII.- No tener antecedentes penales por delitos intencionales;\nIV.- Ser de reconocida honorabilidad, y\nV.- Tener residencia en la zona o en municipio de que se trate con una antigüedad mínima de dos años.\nLas agrupaciones agrícolas, ganaderas y avícolas podrán proponer a la Secretaría, inspectoría.\nLey de Desarrollo Agropecuario del Estado de Baja California. Página 10\nARTÍCULO 10.- Son facultades y obligaciones de los inspectores agropecuarios de la\nSecretaría:\nA) En lo general:\nI.- Vigilar el estricto cumplimiento de la presente Ley, comunicando inmediatamente a las autoridades competentes, de las infracciones e irregularidades que se cometan;\nII.- Levantar censos o llevar acabo inventarios, de las especies que regula esta Ley, con los datos que la Secretaría juzgue convenientes;\nIII.- Documentar en los puntos de inspección fitozoonitarios la sanidad y legal procedencial de los animales, productos y subproductos;\nIV.- Hacer constar en acta circunstanciada los resultados de cada inspección que realice y comunicar a su superior jerárquico las omisiones o violaciones que, en su caso, sean observadas para la aplicación de las medidas preventivas o sanciones que sean procedentes, y\nV.- Las demás que les señalen las leyes, reglamentos y otras disposiciones.\nB) En lo Agrícola:\nI.- Inspeccionar los productos y subproductos agrícolas que vayan a ser movilizados en la Entidad;\nII.- Inspeccionar todos aquellos productos y subproductos agrícolas en tránsito, exigiendo la documentación que ampare su movilización y procedencia legal;\nIII.- Impedir que se hagan embarques de productos y subproductos agrícolas fuera del\nEstado cuando los interesados no presentan la documentación que compruebe su procedencia legal y condición sanitaria óptima.\nFracción Reformada\nIV.- Inspeccionar periódicamente los establecimientos y lugares que comercialicen condición sanitaria, así como la documentación que ampare la entrada a la entidad debidamente autorizada por la Secretaría;\nFracción Reformada\nV.- Inspeccionar periódicamente todos aquellos lugares que expendan productos y subproductos agrícolas con objeto de conocer las condiciones de sanidad, así como la detección de contaminación por productos o residuos químicos o radiación, en niveles superiores a los permitidos para consumo humano y animal, esto último se llevará a cabo con muestras tomadas al azar y enviadas al laboratorio, y\nLey de Desarrollo Agropecuario del Estado de Baja California. Página 11\nVI.- Inspeccionar que la movilización de productos químicos para uso agrícola, sea efectuado bajo las normas de manejo y seguridad establecidas, y sobre todo, impedir se movilicen junto con productos que impliquen riesgo de contaminación al medio ambiente, productos alimenticios o daño directo a humanos y animales.\nC) En lo Apícola:\nI.- Inspeccionar apiarios, empacadoras de miel, cera, establecimientos y lugares, así como los productos y subproductos derivados de la apicultura, que a juicio de la Secretaría sean necesarios para comprobar si en ellos se cumple con lo dispuesto por la presente Ley;\nII.- Inspeccionar las apiarios, colmenas, cajones, recolectores de miel, productos y subproductos que se vayan a movilizar, o que se encuentren en tránsito, exigiendo los documentos que comprueben la procedencia legal, condición sanitaria y tránsito dentro del\nEstado;\nIII.- Impedir que se hagan embarques de colmenas, cajas recolectoras, productos y subproductos apícolas, por cualquier vía de comunicación, mientras los interesados no presenten los documentos que comprueben su procedencia legal y condición sanitaria;\nIV.- Abstenerse de documentar productos y subproductos apícolas de otras zonas, sin guía de tránsito o constancia de las autoridades competentes, y\nV.- Documentar con guía de tránsito productos y subproductos apícolas, enjambres, cajas recolectoras y demás, cuando estos cumplan con los requisitos de procedencia legal y condición sanitaria.\nD) En lo Avícola:\nI.- Inspeccionar granjas avícolas, salas de matanza y demás establecimientos y lugares que a juicio de la Secretaría sean necesarios para comprobar si en ellos se cumple con lo dispuesto por la presente Ley;\nII.- Inspeccionar las carnes, huevos y demás productos y subproductos de origen aviar para comprobar el cumplimiento de las disposiciones de esta Ley;\nIII.- Inspeccionar las parvadas de gallinas, productos y subproductos que se vayan a movilizar, o que se encuentren en tránsito, exigiendo los documentos que comprueben la procedencia legal, condición sanitaria y tránsito dentro del Estado;\nIV.- Impedir que se hagan embarques de parvadas, productos y subproductos avícolas, por cualquier vía de comunicación, mientras los interesados no presenten los documentos que comprueben su procedencia legal y condición sanitaria de los mismos, y\nLey de Desarrollo Agropecuario del Estado de Baja California. Página 12\nVI (sic).- Documentar con guía de tránsito a parvadas de gallinas, productos y subproductos, cuando estos cumplan con los requisitos de procedencia legal y condición sanitaria.\nE) En lo Ganadero:\nI.- Inspeccionar los animales, productos y subproductos de origen animal que vayan a ser movilizados o se encuentren en tránsito, exigiendo los documentos que comprueben la legalidad de su procedencia; debiendo separar y detener los animales cuya procedencia legal no sea comprobada, informando en todo caso a su superior jerárquico;\nII.- Impedir que se hagan embarques de animales, productos y subproductos pecuarios, por cualquier vía de comunicación, mientras los interesados no presenten los documentos que comprueben su legal procedencia;\nIII.- Cerciorarse periódicamente que los sacrificios de animales en los rastros o lugares autorizados para sacrificio, se efectúen previa comprobación que se cumplieron los requisitos de procedencia legal y sanidad correspondientes de los animales;\nIV.- Inspeccionar establecimientos y lugares que a juicio de la Secretaría sean necesarios para comprobar si en ellos se cumple con lo dispuesto por la presente Ley;\nV.- Dirigir, ordenar, vigilar y sancionar las corridas o velas generales y parciales de los ganaderos de su zona o jurisdicción, debiendo previamente obtener las autorizaciones correspondientes de la Secretaría;\nVI.- Inspeccionar las carnes y demás productos y subproductos de origen animal para comprobar el cumplimiento de las disposiciones de esta Ley, tanto en las entidades productoras, como en los establecimientos dedicados a su comercialización.\nDe encontrarse alguna omisión o violación, se levantará el acta correspondiente y se procederá a decomisar los productos y subproductos que tuviesen la irregularidad o anomalía, poniéndolos de inmediato a disposición de la Secretaría y citando al propietario de ocurra ante la citada Secretaría a regularizar o corregir las anomalías detectadas, sin perjuicio de la aplicación de las sanciones que previene esta Ley o, que de los hechos, se desprendiere la posible comisión de algún delito, se hagan del conocimiento de la autoridad competente, y\nVII.- Abstenerse de documentar animales sin guía de tránsito o constancia de las autoridades competentes;\nF) En lo Porcícola:\nLey de Desarrollo Agropecuario del Estado de Baja California. Página 13\nI.- Inspeccionar granjas porcinas, salas de matanza y demás establecimientos y con lo dispuesto por la presente Ley;\nII.- Inspeccionar el ganado porcino, sus productos y subproductos que se vayan a movilizar, o que se encuentren en tránsito, exigiendo los documentos que comprueben la procedencia legal, condición sanitaria y tránsito dentro del Estado.\nIII.- Abstenerse de documentar ganado porcino, productos y subproductos de otras zonas, si este carece guía de tránsito de origen, y\nIV.- Documentar con guía de tránsito al ganado porcino, productos y subproductos, si estos cumplen con los requisitos de propiedad y condición sanitaria.\nArtículo Reformado\nARTICULO 11.- Las autoridades municipales auxiliarán en sus funciones a los inspectores agropecuarios cuando éstos lo soliciten. En los lugares en que no exista esta autoridad, corresponderá a las autoridades municipales las funciones del inspector.\nCAPÍTULO IV\nDE LOS CONVENIOS\nARTÍCULO 12.- El Ejecutivo del Estado por conducto de la Secretaría impulsara la celebración de instrumentos, convenios o acuerdos de coordinación, apoyos, participación, coadyuvancia de acciones o asunción de funciones con los siguientes organismos:\nI.- Gubernamentales.- Los poderes federales y estatales, los municipios, y cualquier otro ente público, y\nII.- No gubernamentales.- Instituciones de educación e investigación y organizaciones o instituciones internacionales, nacionales, estatales y municipales.\nEl Ejecutivo del Estado, a través de la Secretaría, promoverá la organización de las y los productores agropecuarios, fomentando la adopción de prácticas sustentables y la sostenibilidad de las actividades agropecuarias en el estado. Asimismo, impulsará el acceso a tecnologías limpias y la certificación de producción orgánica.\nPárrafo Reformado\nArtículo Reformado\nARTÍCULO 13.- Los convenios o acuerdos que se celebren versarán sobre los siguientes aspectos:\nI.- Fomento, investigación, difusión de conocimientos, aplicación, elaboración de programas de gobierno, científicos y tecnológicos del ramo agropecuario;\nLey de Desarrollo Agropecuario del Estado de Baja California. Página 14\nII.- La observancia y aplicación de las leyes federales y normas internacionales que tengan relación con el sector agropecuario, e impedir la introducción al Estado de maquinaria o equipo agrícola o pecuario, animales, productos y subproductos agropecuarios, que pudieran representar un riesgo para la sanidad vegetal o animal, así también aplicar las medidas de control fitosanitarias y zoosanitarias respectivas;\nFracción Reformada\nIII.- La promoción y desarrollo de la infraestructura productiva y el fomento y fortalecimiento de las actividades agropecuarias; y,\nFracción Reformada\nIV.- La implementación de campañas de carácter permanente con el objeto de informar a la población rural sobre derechos, apoyos y servicios de los que son beneficiarios, respecto a:\na) Los programas públicos que se implementan y a los requisitos necesarios para ser personas beneficiarias de los mismos.\nb) La presentación de quejas y denuncias, antes las instancias correspondientes en defensa de sus derechos.\nc) Información sobre las condiciones laborales que señala la materia.\nFracción con sus Incisos Adicionada\nArtículo Reformado\nARTÍCULO 13 BIS.- La Secretaría implementará programas de capacitación y asistencia técnica dirigidos a las y los productores agropecuarios, con el propósito de mejorar las prácticas de producción, manejo postcosecha, transformación y comercialización de los productos del sector, enfatizando la adopción de técnicas sustentables el uso eficiente de recursos naturales y transición hacia la agricultura regenerativa.\nArtículo Adicionado\nARTÍCULO 14.- El ejecutivo del Estado y los Ayuntamientos podrán celebrar los instrumentos legales necesarios para el ejercicio de la actividad agropecuaria a efecto de que estos últimos asuman de forma concurrente con la autoridad estatal las facultades y atribuciones que sean viablemente delegables dentro de su jurisdicción para mejorar la actividad en el sector, siempre y cuando garantice que cuenta con los recursos humanos capacitados, recursos materiales y financieros y la estructura institucional específica para atender y desarrollar las funciones que asumiría.\nAdministración Publica del Estado u otras disposiciones similares, se requiera la intervención de otras dependencias, la Secretaria ejercerá sus atribuciones en coordinación con las mismas.\nTÍTULO SEGUNDO\nDE LA PLANEACIÓN DEL DESARROLLO AGROPECUARIO\nLey de Desarrollo Agropecuario del Estado de Baja California. Página 15\nCAPÍTULO I\nDE LA PLANEACIÓN DEL DESARROLLO AGROPECUARIO\nARTÍCULO 15.- La planeación del desarrollo agropecuario en el Estado estará a órgano responsable del proceso de planeación en la entidad, y por los Ayuntamientos en sus respectivas jurisdicciones, en los términos establecidos en la Ley de Planeación para el\nEstado, esta Ley y demás disposiciones aplicables. En este proceso se incluirán lineamientos específicos para fomentar prácticas sustentables, garantizar la conservación de recursos naturales y promover la diversificación productiva.\nArtículo Reformado\nARTÍCULO 16.- La planeación del desarrollo agropecurario (sic), como instrumento para el diseño y ejecución de la política agropecuaria, comprenderá la elaboración, aplicación y seguimiento de los programas respectivos, que incluirán:\nI.- Los objetivos, estrategias y líneas de acción prioritarias, tomando en cuenta los criterios e instrumentos de la política nacional en el sector y buscando congruencia con los programas nacionales;\nII.- Las metas específicas de producción que habrán de alcanzarse a corto, mediano y largo plazo, de la actividad agropecuaria;\nIII.- La intervención en materia de capacitación, investigación, asistencia técnica, obras de infraestructura, crédito, insumos, equipos, instalaciones y demás elementos que propicien la producción y productividad, así como las propuestas sobre la participación del\nEstado;\nIV.- Las necesidades de producción, industrialización, almacenamiento, transporte, distribución, abasto y comercialización de los productos agropecuarios;\nV.- Las posibilidades consecuentes para el establecimiento y fortalecimiento de agroindustrias, y\nVI.- Así como las demás que sean necesarias para el beneficio del sector agropecuario.\nARTÍCULO 17.- En la elaboración de la planeación del desarrollo agropecuario, deberán tomarse en cuenta a los consejos y organizaciones agropecuarias respectivas, en los términos de la Ley de Planeación para el Estado.\nARTÍCULO 18.- Los programas que derive del cumplimiento de esta Ley, tendrán la vigencia que se determine en cada caso, debiendo ser acorde a los plazos previstos en la\nLey de Planeación para el Estado.\nLey de Desarrollo Agropecuario del Estado de Baja California. Página 16\nCAPÍTULO II\nDEL DESARROLLO RURAL\nARTÍCULO 19.- El desarrollo rural deberá ser promovido por las Instituciones gubernamentales del Estado y Municipios de Baja California, en forma coordinada con las que conduzca al bienestar de la población, a través del fomento y desarrollo de las actividades productivas y sociales del sector rural.\nARTÍCULO 20.- El Federalismo y la descentralización de la gestión publica serán criterios rectores para la puesta en práctica de los programas de apoyo al desarrollo rural.\nLos convenios que se celebren entre Estado y Federación, así como con los Gobiernos\nMunicipales, se ajustarán a dichos criterios.\nARTÍCULO 21.- El Ejecutivo del Estado implementará programas y acciones en el ámbito rural del Estado para el desarrollo de las actividades agropecuarias; así como las actividades económicas productivas no agropecuarias en las que se ocupen los pobladores del área rural. Para esto, orientará sus políticas mediante los siguientes objetivos:\nI.- Promover el bienestar social y económico de los productores, de sus comunidades, de los trabajadores del campo y en general, de la población rural;\nII.- Promover la equidad económica y social de las regiones rurales a través de programas de apoyo para inducir el desarrollo en las regiones de mayor rezago, con la participación integral de las instituciones públicas, impulsando la transformación y diversificación productiva y económica de dichas regiones; y\nIII.- Fomentar la conservación de la biodiversidad y el mejoramiento de la calidad de los recursos naturales a través de un aprovechamiento sustentable.\nIV.- Estimulará la reconversión productiva sustentable agropecuaria y demás actividades económicas del medio rural, para aprovechar eficientemente los recursos naturales, tecnológicos y humanos, y así, lograr mayor productividad, competitividad y rentabilidad.\nFracción Adicionada\nArtículo Reformado\nTÍTULO TERCERO\nDE LA AGRICULTURA\nCAPÍTULO I\nDE LAS ORGANIZACIONES DE PRODUCTORES AGRICOLAS.\nARTÍCULO 22.- La organización de los productores tiene por objeto alcanzar el aprovechamiento, industrialización y comercialización de los recursos agrícolas y frutícolas, Ley de Desarrollo Agropecuario del Estado de Baja California. Página 17 de esos recursos, legalmente constituidos.\nARTÍCULO 23.- Para lograr la efectiva organización de los productores y trabajadores del campo, la Secretaría coordinará acciones con las autoridades federales que tengan injerencia con la actividad agropecuaria.\nCAPÍTULO II\nDEL MANEJO Y APLICACIÓN DE QUÍMICOS EN LA ACTIVIDAD\nARTÍCULO 24.- La Secretaría en coordinación con las dependencias gubernamentales competentes supervisarán el cumplimiento de las normas técnicas para el control y uso de plaguicidas, fertilizantes, medicamentos, biológicos y sustancias tóxicas en las áreas agrícolas, pecuarias, y promoverán el desarrollo de programas encaminados a la realización de obras destinadas a la recolección, depósito, almacenamiento, tratamiento y destino final de desechos tóxicos de químicos, plásticos y otros productos utilizados en el sector agropecuario capaces de producir contaminación al medio ambiente y a la población en general.\nARTÍCULO 25.- La Secretaría vigilará que los envases de plaguicidas y todo producto químico que se usen en la actividad agropecuaria en el Estado, ostenten claramente en su etiqueta la leyenda sobre los peligros que implica el manejo del producto, su forma de uso, sus antídotos en caso de intoxicación, las fechas de elaboración y caducidad, número de lote de elaboración y el manejo de los envases que los contengan o los hayan contenido, de acuerdo a lo establecido en el Reglamento respectivo.\nEn caso de anomalías o violaciones a lo estipulado en el párrafo anterior, la\nSecretaría turnará a la autoridad competente el expediente respectivo para que se tomen las medidas pertinentes y se apliquen las sanciones que procedan.\nARTÍCULO 26.- Para la protección del medio ambiente, salud humana, animal y vegetal, se prohibe en el Estado el desecho en drenes, canales, lagos y en todo lugar que no sea el apropiado de conformidad con los reglamentos y normas respectivas, de productos químicos en sí, o de aquellos que resulten del lavado de mezcladoras, tanques, pipas, depósitos y transporte en general.\nARTÍCULO 27.- La Secretaría en coordinación con las autoridades competentes, aplicación de químicos, en la realización de muestreos en plantas y aeropistas, en la vigilancia del almacenaje de mezclas adecuadas, en la verificación de fechas de elaboración y caducidad, en la inutilización de los envases y en la vigilancia de los inspectores de aeródromos utilizados en la aplicación de químicos.\nLey de Desarrollo Agropecuario del Estado de Baja California. Página 18\nARTÍCULO 28.- La Secretaría instrumentará programas de seguridad en plantas, aeropistas de fumigación y en todos aquellos lugares en que se manejen químicos, así como programas de entrenamiento y capacitación para el personal que los maneje.\nARTÍCULO 29.- La Secretaría sancionará a toda persona que no use los equipos sustancias tóxicas, así como aquellas personas que provoquen una contaminación ambiental o daños a la salud humana, animal o vegetal, por un mal manejo de dichos productos, de conformidad con lo estipulado por esta Ley y su Reglamento.\nARTÍCULO 30.- La Secretaría, en coordinación con las organizaciones de productores, fomentará el uso del método de control biológico inducido para el combate de plagas y enfermedades de los diversos cultivos agrícolas y frutícolas, así como para el control, cuando sea técnicamente posible, de plagas y enfermedades de animales o vegetales.\nCAPÍTULO III\nDEL MEJORAMIENTO Y CONSERVACIÓN DE SUELOS AGRICOLAS.\nARTÍCULO 31.- La Secretaría promoverá la nivelación y conservación periódica de los predios agrícolas del Estado, como una medida para lograr un crecimiento uniforme de los cultivos y un cabal aprovechamiento del agua de riego.\nARTÍCULO 32.- Cuando los excedentes de agua lo permitan y/o la necesidad lo dicte, los predios agrícolas del Estado, serán sometidos al proceso del lavado de tierra a efecto de disminuir el contenido de sales en los mismos, procurando que el agua utilizada en este proceso no vuelva a aplicarse en el riego de cultivos.\nARTÍCULO 33.- Con la finalidad de optimizar la producción agrícola de la Entidad, la\nSecretaría sugerirá el cambio de aquellos cultivos que por factores de índole natural y económico, no sean los más convenientes, por otros que representen una mejor alternativa tanto para los productores como para las necesidades de la entidad y del país, de acuerdo\nARTÍCULO 34.- La Secretaría promoverá el pleno aprovechamiento, protección, mejoramiento, explotación racional de los acuíferos y aguajes naturales existentes, como propiciar el uso eficiente del recurso del agua.\nARTÍCULO 35- La Secretaría en coordinación con instituciones gubernamentales y académicas, fomentará el diseño, divulgación y prácticas de manejo del suelo y el agua. Así infraestructura hidráulica.\nLey de Desarrollo Agropecuario del Estado de Baja California. Página 19\nARTÍCULO 35 BIS.- La Secretaría impulsará las acciones necesarias y mantendrá la infraestructura hidroagrícola con la utilización de tecnología apropiada, como mecanismo que consolide el desarrollo sustentable, social y productivo de las actividades rurales.\nArtículo Adicionado\nARTÍCULO 35 TER.- La Secretaría impulsará la agricultura regenerativa, como alternativa para la conservación de los suelos agrícolas, coadyuvando al medio ambiente, cambio climático, y ahorro del agua, otorgará a la persona productora asesoría técnica, cursos de capacitación, para que vaya transitando de la agricultura común, a la regenerativa, la cual dará un valor agregado a su producto ya que este cambiará a ser orgánico, debido al uso de biofertilizantes.\nArtículo Adicionado\nARTÍCULO 35 QUARTER.- La utilización de biofertilizantes orgánicos, por medio de nutrientes vegetales y/o sustancias naturales, para la bioestimulación de cultivos, y en general todas las prácticas agronómicas que mejoren el suelo de manera orgánica y sustentable.\nArtículo Adicionado\nCAPÍTULO IV\nDE LA SANIDAD VEGETAL\nARTÍCULO 36.- La sanidad vegetal tiene como finalidad promover y vigilar la observancia de las disposiciones legales aplicables; diagnosticar y prevenir la diseminación e introducción de plagas de los vegetales, sus productos o subproductos que representen un riesgo fitosanitario; así como establecer medidas fitosanitarias y regular la efectividad de los insumos fitosanitarios y de los métodos de control integrado.\nLa regulación en materia de sistemas de reducción de riesgos de contaminación, tiene como finalidad, promover, verificar y certificar las actividades efectuadas en la producción primaria de vegetales encamindadas a evitar su contaminación por agentes fisicos, quimicos o microbiológicos, a través de la aplicación de Buenas Prácticas Agrícolas y el uso y manejo adecuados de insumos utilizados en el control de plagas, lo anterior en apego a la Ley\nFederal de Sanidad Vegetal y la legislación aplicable.\nARTÍCULO 37.- La Secretaría podrá contar con el apoyo del Consejo Estatal\nAgropecuario, Comité Estatal de Sanidad Vegetal y demás organismos, en materia de intensificación, planeación, programación, seguimiento y evaluación de los programas de sanidad vegetal que se establezcan en el Estado.\nARTÍCULO 38.- La Secretaría implementará las políticas y medidas necesarias para enfermedades, buscando también la protección a la salud humana. En las mismas, podrán participar las autoridades federales, estatales, municipales y los órganos fitosanitarios\nLey de Desarrollo Agropecuario del Estado de Baja California. Página 20 constituidos en el Estado, en los términos que marcan las disposiciones jurídicas de la materia.\nARTÍCULO 39.- La Secretaría impulsará las acciones necesarias para la difusión, plagas y enfermedades perjudiciales para la agricultura. Asimismo, podrán participar las autoridades federales, estatales y municipales y los órganos fitosanitarios constituidos en el\nEstado, en los términos que marcan las disposiciones jurídicas de la materia.\nARTÍCULO 40.- La Secretaría vigilará dentro de los límites del Estado, la movilización y venta al público de productos y subproductos agrícolas, a efecto de detectar la introducción de productos de desecho o contrabando, como una medida de protección a la producción local y para evitar la introducción de plagas o enfermedades que pudieran afectar a los cultivos o a la salud humana.\nARTÍCULO 41.- Es obligación de los productores agrícolas, acatar las medidas profilácticas y curativas que se establezcan para evitar una mayor incidencia y propagación de las plagas y enfermedades.\nTÍTULO CUARTO\nDE LA GANADERIA\nCAPÍTULO I\nDE LA ORGANIZACIÓN DE LOS GANADEROS\nARTÍCULO 42.- Los ganaderos del Estado, tendrán en todo momento el derecho de asociarse libre y voluntariamente, de conformidad al artículo noveno Constitucional, y la Ley de Organizaciones Ganaderas y su reglamento. Asimismo tendrán la obligación de obtener la patente a que se refiere el artículo 4 de esta Ley.\nARTÍCULO 43.- Las organizaciones ganaderas registradas conforme a la Ley de\nOrganizaciones Ganaderas, tendrán la obligación de comunicar a la Secretaría su constitución, para integrar el Padrón de Organizaciones Ganaderas en el Estado.\nARTÍCULO 44.- Los ganaderos, asociaciones, uniones ganaderas y toda organización de productores pecuarios, tendrán las siguientes obligaciones:\nI.- Cooperar con las autoridades competentes para que ellos y sus asociados cumplan de la Secretaría;\nII.- Coadyuvar con las autoridades competentes a combatir las plagas y epizóotias que atacan a los ganados;\nLey de Desarrollo Agropecuario del Estado de Baja California. Página 21\nIII.- Cooperar con las autoridades del Estado para la observancia de esta Ley, y promover entre sus agremiados, todas aquellas medidas encaminadas a que éstos presten igual colaboración;\nIV.- Participar cada año, en la elaboración de programas de desarrollo ganadero de cada región, en función de los intereses generales del Estado, formulándose de común acuerdo con la Secretaría proyectos específicos de desarrollo, para todas y cada una de ellas. Una vez aprobado el programa anual de desarrollo, su ejecución y realización será obligatorio;\nV.- Llevar un registro de las patentes, marcas de herrar y señales de sangre, que hayan sido autorizadas por la Secretaría, y\nVI.- Integrar, validar, canalizar y gestionar ante la Secretaría los expedientes de solicitudes para el registro y revalidación de títulos y patentes de marcas de herrar, señales de sangre y tatuajes.\nCAPÍTULO II\nDE LA PROPIEDAD DE LOS GANADOS Y ANIMALES.\nARTÍCULO 45.- La propiedad de los ganados y animales se acredita:\nI.- Con la marca de herrar para los bovinos y equinos, con la señal de sangre, aretes o tatuajes para los equinos, bovinos menores de un año, porcinos, ovinos y caprinos de cualquier edad, siempre que tales marcas y señales estén legalmente registradas en la\nSecretaría;\nII.- Con los documentos que conforme a la Ley tengan validez, cuando en ellos se describan los animales y se diseñen expresamente las marcas de herrar, las señales de sangre, los aretes o tatuajes correspondientes al o los animales que amparen dichos documentos, debiendo las marcas y señales estar registradas en la Secretaría, y\nIII.- Los demás métodos de identificación que reconozca la Secretaría.\nARTÍCULO 46.- Los animales de registro o pedigrí se exceptúan de la marca de fuego o señal de sangre y serán objeto únicamente de tatuaje.\nLa Secretaría llevará un libro de registro de este tipo de ganado, y expedirá los documentos que certifiquen la propiedad y pureza de los mismos, conforme a las disposiciones reglamentarias que se emitan.\nARTÍCULO 47.- Se consideran las crías de los animales propiedad del dueño de la madre y no del dueño del padre, salvo convenio en contrato.\nLey de Desarrollo Agropecuario del Estado de Baja California. Página 22\nARTÍCULO 48.- La propiedad del ganado se transferirá de conformidad con lo que establece el derecho común, debiendo el documento en que conste la transmisión, contener los datos que señala la fracción II del artículo 45 de esta Ley.\nCAPÍTULO III\nDE LOS CERCOS\nARTÍCULO 49.- Los propietarios o poseedores de terrenos destinados a la cría de ganado mayor o menor, están obligados a construir cercos de postes resistentes de tres o más hilos de alambre de púas o lisos, con distancia de metro y medio a dos metros de separación, amarrado o engrapado, en las zonas de explotación agrícola, a fin de impedir el acceso de animales a los cultivos; igualmente, tienen esta obligación los propietarios o poseedores de terrenos agrícolas ubicados dentro de las zonas ganaderas.\nEn caso de colindancia de un terreno ganadero con otro dedicado a la agricultura o que colinden dos terrenos dedicados a la ganadería, el costo del cerco que divida dichos terrenos deberá ser pagado por partes iguales.\nARTÍCULO 50.- Los ganaderos cuyos predios colinden con carreteras federales o estatales, están obligados a cercar dichas colindancias con postes resistentes, los cuales deberán tener una separación de metro y medio entre poste y poste. Dicho cerco deberá tener cuatro hilos de alambre de púas, los cuales deberán de sujetarse a cada poste con alambre.\nCAPÍTULO IV\nDE LAS MARCAS Y SEÑALES.\nARTÍCULO 51.- Queda prohibido el uso de marcas de herrar, señales de sangre y tatuajes, sin haber sido previamente registrados en la Secretaría y obtenido de dicha dependencia el certificado de título de registro que servirá para acreditar la propiedad de tales marcas.\nARTÍCULO 52.- El certificado de título de registro de marcas de herrar, señales de sangre y tatuajes, se revalidarán ante la Secretaría, dentro de los primeros noventa días de los años terminados en cero y en cinco.\nLa Secretaría cancelará los certificados de registro de título de marcas de herrar, señales de sangre y tatuajes, cuando el ganadero no ha revalidado el certificado en el plazo referido en el párrafo anterior, y en los demás supuestos que disponga el Reglamento. La conformidad a lo dispuesto a la fracción II del artículo 160 de esta Ley.\nARTÍCULO 53.- No podrá autorizarse por la Secretaría, más de una marca de herrar ni más de una señal de sangre para una misma persona.\nLey de Desarrollo Agropecuario del Estado de Baja California. Página 23\nARTÍCULO 54.- La Secretaría no registrará ninguna marca de herrar de diseño o dos o más letras o signos para aplicarse por separado en distintas partes del animal. alteración o de estrecha semejanza a otra y registrada dentro de un Municipio, siendo potestativo para el propietario el uso de otros medios de identificación como tatuajes o fichas metálicas, siempre que estén registradas en la Secretaría.\nARTÍCULO 55.- Cuando un ganadero tramite su título de registro o actualización de marca de herrar, tatuaje o señal de sangre, podrá elegir a un beneficiario o sucesor de este patrimonio, así como del ganado amparado por estos en caso de enfermedad o muerte, el cual deberá quedar por escrito en la certificación y cumplir los requisitos que exige el derecho civil para que tenga efectos contra terceros.\nPárrafo Reformado\nEl formato en el que se designe al beneficiario o sucesor, quedará bajo el resguardo de la secretaría, quien deberá integrarlo a un padrón de beneficiarios de estos derechos.\nPárrafo Adicionado\nCuando un ganadero desee dar de baja su marca de herrar, tatuaje o señal de sangre deberá manifestarlo por escrito a la secretaría y a la Unión Ganadera Regional o Asociación\nLocal, para el trámite correspondiente, quedando sin efecto la sucesión mencionada.\nPárrafo Adicionado\nArtículo Reformado\nARTÍCULO 56.- Queda estrictamente prohibido herrar con plancha llena, con alambre, ganchos, argollas o con fierro corrido, amputar una o más orejas, desfigurar o borrar las marcas o señales de los animales comprados, debiendo estos conservar el de los dueños o criadores. Queda igualmente prohibido herrar, señalar o reseñar ganado con marcas que no sean de su propiedad, así como conceder permiso para herrar, señalar o reseñar ganado ajeno. Para la movilización de animales, la marca de herrar deberá estar cicatrizada.\nARTÍCULO 57.- Las señales de sangre se aplicarán de la mitad hacia la punta de la oreja del ganado, sin que las cortadas o incisiones sean mayores que la superficie de la media oreja, quedando prohibido aplicar más de cuatro cortadas en cada una de ellas. Para la movilización de animales, la señal de sangre deberá estar cicatrizada.\nARTÍCULO 58.- Los animales que se encuentren con el fierro modificado o encimado, serán recogidos por las autoridades competentes para la investigación correspondiente.\nLos animales recogidos conforme a lo dispuesto en el párrafo anterior, serán puestos a disposición de la Secretaría, para que compruebe su legal procedencia, y en su caso, al remate (subasta) de los mismos.\nLey de Desarrollo Agropecuario del Estado de Baja California. Página 24\nCAPÍTULO V\nDE LOS ANIMALES MOSTRENCOS\nARTÍCULO 59.- Se consideran animales mostrencos para los efectos del presente instrumento:\nI.- El ganado mayor o menor abandonados, perdidos o aquellos cuyo dueño se ignore, incluyendo los apiarios;\nII.- Los orejanos que no pertenezcan al dueño del terreno en que pastan o se agostan;\nIII.- Los trasherrados y traseñalados en los cuales no sea posible identificar la marca de fuego, señal de sangre, reseña o tatuaje que posea el animal, y\nIV.- Los animales que ostenten marcas que no se encuentren registrados en el\nPadrón Ganadero Estatal de la Secretaría.\nARTÍCULO 60.- Toda persona que tenga conocimiento de un animal mostrenco, tendrá la obligación de dar aviso inmediato a la Secretaría, y en su caso a la Autoridad\nMunicipal más cercana donde se localice, para que se obtenga la identificación del mismo.\nARTÍCULO 61.- La Secretaría al recibir un animal mostrenco, dará aviso inmedianto a la autoridad municipal correspondiente, para que en un plazo de tres dias manifieste su conformidad para ponerlo a su disposición e inicie el procedimiento previsto en la legislación civil.\nTranscurrido el plazo previsto en el párrafo anterior, de no recibirse respuesta alguna de la autoridad municipal, la Secretaría procederá a la subasta pública de los animales mostrencos conforme a los disposiciones reglamentarias.\nARTÍCULO 62.- La Secretaría, para el deposito y cuidado de los animales mostrencos se apoyara con los organismos de cooperación y con las organizaciones ganaderas de la región.\nCAPÍTULO VI\nDE LA SANIDAD ANIMAL\nARTÍCULO 63.- La sanidad animal tiene como finalidad: diagnosticar y prevenir la introducción, permanencia y diseminación de enfermedades y plagas que afecten la salud o la vida de los animales; procurar el bienestar animal; así como establecer las buenas humano.\nLey de Desarrollo Agropecuario del Estado de Baja California. Página 25\nLa regulación, verificación, inspección y certificación del procesamiento de bienes de la atención de riesgos sanitarios por parte de la Secretaría, de conformidad a la legislación aplicable.\nARTÍCULO 64.- La Secretaría tendrá la obligación de prevenir, combatir y erradicar las plagas y efermedades que afecte al ganado mayor o menor, verificando el cumplimiento de las disposiciones emitidas en materia de sanidad pecuaria en los puntos de inspección fitozoonitarios establecidos\nARTÍCULO 65.- Las enfermedades infecciosas o parasitarias de los animales, enzoóticas o epizoóticas, serán prevenidas, combatidas, controladas y erradicadas de acuerdo con lo que esta Ley determina, lo previsto por las leyes federales de la materia, y lo establecido por la ciencia veterinaria.\nARTÍCULO 66.- Para los efectos de esta Ley, se considerarán por:\nI.- Por enfermedades infecciosas y parasitarias de los animales domésticos y de la fauna, todas aquellas alteraciones y reacciones que provocan en sus diferentes tejidos y órganos, la exposición a patógenos sean estos virus, bacterias, parásitos, hongos e incluso aquellos síndromes cuya etiología no esté definida; considerándose prioritarias aquellas enfermedades que por sus características comprometan la salud de los hatos en producción y máximo cuando sean transmisibles al hombre, y\nII.- Zoonosis, o enfermedades transmisibles al hombre, todas aquellas enfermedades de animales que sus agentes causales provoquen también alteraciones o reacciones en la salud humana; incluyendo las que parte de su ciclo biológico se desarrolle en el cuerpo humano, independientemente de la forma de transmisión. Las prioridades de salud con respecto a las zoonosis, serán determinadas por la Secretaría de Salud.\nARTÍCULO 67.- Toda persona está obligada a denunciar ante las autoridades competentes, cualquier indicio o síntoma de plaga o enfermedad que se presenten en el ganado mayor o menor propios o ajenos de las que tuviere conocimiento.\nARTÍCULO 68.- En casos urgentes, a juicio de las autoridades federales, estatales y municipales, los ganaderos y profesionistas ligados con la materia de los lugares donde existan plagas o enfermedades, tienen la obligación de cooperar en los trabajos de prevención, combate, control y erradicación de las mismas.\nARTÍCULO 69.- Las autoridades estatales y municipales de salud animal, están ciencia veterinaria en caso de desarrollo de una epizootia, debiendo comunicarlos simultáneamente a todos los integrantes del sector agropecuario.\nLey de Desarrollo Agropecuario del Estado de Baja California. Página 26\nARTÍCULO 70.- Los particulares que presten servicios relacionados con la prevención, combate, control y erradicación de plagas y enfermedades, actuarán bajo la normatividad que establecen las leyes sanitarias y zoosanitarias.\nARTÍCULO 71.- La Secretaría difundirá la información y conocimientos relacionados con la materia a fin de instruir a la población y obtener su cooperación en el combate, control, prevención y erradicación de plagas y enfermedades.\nARTÍCULO 72.- Se declara obligatoria en el Estado, en las zonas zootécnicas, la vacunación de los animales para prevenirlos de las enfermedades que a juicio del\nOrganismo Federal en cargado de la Salud Animal, el Comité Estatal de Fomento y\nProtección Pecuaria y el Ejecutivo Estatal, lo ameriten.\nARTÍCULO 73.- La Secretaría dictará con oportunidad las medidas técnicas de aplicación de las inoculaciones preventivas, reveladoras o curativas en los animales o ganados estabulados, en ferias o exposiciones, en el campo o en tránsito, así como las de los medios de diagnóstico que sean necesarios.\nARTÍCULO 74.- Los propietarios o encargados de ganado mayor o menor, y en cautiverio tienen la obligación de prodigar los cuidados higiénicos y zootécnicos necesarios, para conservarlos en las mejores condiciones de salud y defensa natural contra cualquier enfermedad, quedándoles prohibido efectuar cruzamientos con sementales afectados de enfermedades o problemas congénitos.\nARTÍCULO 75.- Los animales de ordeña, ya sea que estén estabulados o en vaquerías, serán sometidos a la prueba de la tuberculina y brucelosis, debiendo sacrificarse a los que reaccionen positivamente, declarándose no aptos para el consumo humano; los que reaccionen dudosamente deberán ser señalados y separados del ganado sano y serán sometidos a cuarentena, pasada la cual, se determinará lo conducente.\nARTÍCULO 76.- En el caso de aparición de una epizootía, la Secretaría en forma conjunta con el Comité Estatal de Fomento y Protección Pecuaria, harán una declaratoria oficial que deberá publicarse en los periódicos de mayor circulación en la zona afectada, señalando los alcances geográficos de tiempo y medidas de observancia obligatoria que se aplicarán hasta que se erradique el mal y se levante la declaratoria.\nARTÍCULO 77.- Mientras no se levante la declaratoria a que se refiere el artículo anterior, no se expedirán guías sanitarias, ni de tránsito de animales del predio o zona infectada a una libre o viceversa, y se dictará aislamiento completo o parcial de la zona, con prohibición de tránsito de personas o transportes de cosas, cuando sin desinfección previa, puedan ser vehículos de contagio.\nARTÍCULO 78.- Se declara obligatoria y de utilidad pública las campañas contra la garrapata boophilus (margaropus) annulatus, transmisora de la piroplasmosis bovina y la prevención y el combate de Cochlyoma o Callitroga homonivorax, conocido comúnmente\nLey de Desarrollo Agropecuario del Estado de Baja California. Página 27 como gusano barrenador o tornillo. Para la realización de dicha campaña, se establecerá el número de zonas libres y zonas infestadas que sean necesarias, las que se modificarán de acuerdo con los resultados de la campaña y previa consulta a las autoridades competentes.\nARTÍCULO 79.- Todos los propietarios o encargados de animales dentro de una zona declarada infestada, o bajo cuarentena están obligados a bañar o tratar a los animales, de acuerdo con el método que apruebe la autoridad competente.\nARTÍCULO 80.- El Ejecutivo del Estado, a través de la Secretaría y previo acuerdo con las autoridades federales competentes, fijará los corrales o potreros que sirvan de depósito para los animales con sospecha de alguna enfermedad.\nARTÍCULO 81.- Para la introducción y salida de animales, sus productos y subproductos al Estado, los interesados deberán comprobar ante la Secretaría, previamente a cualquier movilización, las buenas condiciones zoosanitarias y sanitarias respectivas, así como su legal procedencia, de conformidad a las disposiciones locales y federales correspondientes.\nSi la Secretaría oyendo a la Unión Ganadera Regional u organizaciones de productores, encontrare insatisfactoria la comprobación, no permitirá la entrada o salida de los animales, productos o subproductos; tampoco en caso de dañar la producción y comercialización estatal, la que tendrá preferencia en su consumo.\nARTÍCULO 82.- Con el fin de garantizar la protección a la actividad pecuaria localizada en las zonas limpias de enfermedades, la movilización de animales hacia estas zonas se hará en la forma siguiente:\nI.- Queda estrictamente prohibido el paso de animales procedente de zona sucia, a menos que se hayan llenado los requisitos sanitarios establecidos en esta Ley y en la Ley\nFederal de Sanidad Animal;\nII.- No podrá realizarse la movilización de animales de una zona sucia a una zona limpia, sin la guía de tránsito expedida por la Secretaría.\nDicha guía deberá ser entregada en el lugar de destino al Inspector Agropecuario o, en su caso, al Presidente o Delegado Municipal;\nARTICULO 83.- En los casos de exportación de producto pecuario deberán de seguirse las siguientes reglas:\nI.- Todo animal procedente de una zona sucia que se movilice con fines de exportación, deberá permanecer hasta sesenta días en la zona cuarentenaria antes de ser exportado con el fin de poder certificar que se encuentra libre de enfermedad;\nLey de Desarrollo Agropecuario del Estado de Baja California. Página 28\nII.- Toda movilización de animales de una zona sucia con rumbo a los centros de exportación, se hará pasando por los puntos de inspección forzosa para que se certifique que cada uno de los animales esté libre de parásitos;\nIII.- Los Presidentes o Delegados Municipales y los Inspectores Agropecuarios, están animal o partida de ganado que se movilice hacia los puntos de exportación.\nEn caso de que el encargado de los animales o su propietario no llevase consigo la guía, se procederá a la detención de la partida y se dará inmediato aviso a la Secretaría para los efectos a que haya lugar;\nARTÍCULO 84.- Con el fin de facilitar el control de los movimientos de animales procedentes de zonas sucias destinados a la exportación o al abastecimiento de los mercados locales, la Secretaría designará puntos o puestos de paso obligatorio para dicho ganado.\nPara que una partida de animales pueda continuar hacia una zona limpia, deberá redocumentarse por el Inspector Agropecuario o en su caso con la autoridad municipal donde haya estado en observación.\nCAPÍTULO VII\nCORRIDAS O VELAS\nARTÍCULO 85.- Las corridas o velas, recuentos o realeos serán generales cuando se haga la reunión de la totalidad de los ganados en todas las propiedades de una determinada zona ganadera, y serán parciales cuando se efectúen en uno o más predios ganaderos, ya sea propiedad privada, ejidal o comunal.\nARTÍCULO 86.- Los ganaderos están obligados a realizar corridas o velas generales cada año, si las condiciones lo permiten, en la época que la necesidad o costumbre de cada región lo requiera. Las corridas o velas parciales se realizarán en cualquier tiempo, previa la solicitud de uno a varios ganaderos y la justificación de su necesidad. La Secretaría otorgará en cada caso la orden y autorización correspondiente.\nARTÍCULO 87.- Los inspectores agropecuarios, de acuerdo con los ganaderos de la zona correspondiente, señalarán con un mes de anticipación, el lugar y la fecha en que deban dar principio las corridas o velas generales, y de inmediato solicitarán la autorización\nARTÍCULO 88.- Las corridas o velas sean parciales o generales, serán dirigidas por el Inspector Agropecuario, oyendo la opinión del dueño o mayordomo del rancho en que se verifiquen, estando obligados a concurrir a ella, desde su inicio, todos los ganaderos de la zona.\nLey de Desarrollo Agropecuario del Estado de Baja California. Página 29\nARTÍCULO 89.- El Inspector Agropecuario dirigirá, ordenará y vigilará la separación y deberán estar diseñadas las marcas y señales legalmente registradas.\nARTÍCULO 90.- Por ningún motivo se transferirán las fechas fijadas previamente para las corridas o velas en los lugares señalados, a no ser que dejaren de efectuarse por caso fortuito o fuerza mayor y en tal caso, el Inspector Agropecuario oyendo la opinión de los ganaderos, fijará nuevo día para su inicio.\nLos inspectores agropecuarios dirigirán las corridas o velas generales de manera que al terminar una de éstas en un rancho, principie la otra de inmediato.\nARTÍCULO 91.- Los inspectores agropecuarios procurarán que las corridas o velas no sufran dilaciones y para el efecto, las organizarán de común acuerdo con los dueños o encargados del terreno y el número de vaqueros necesarios, quienes desempeñarán los cargos o comisiones que el Inspector les encomiende.\nARTÍCULO 92.- Una vez recogido el ganado, el Inspector Agropecuario acompañado del dueño del rancho o de su representante legal y los concurrentes, pasará a reconocer los potreros, dehesas y demás terrenos cercados del propio rancho y si encontrare en ellos animales con marcas que no pertenezcan al dueño del rancho y éste no acreditare su procedencia legal, los agregará a la corrida o vela para los efectos del reparto que hará de inmediato.\nARTÍCULO 93.- El Inspector Agropecuario tomará a su cargo los animales con marcas desconocidas o no registradas, los que tengan marcas o señales desfiguradas y las crías recientemente herradas que no se encuentren al lado de la madre, salvo que se compruebe su procedencia legal.\nARTÍCULO 94.- Queda prohibido efectuar movilizaciones de ganado en cada rancho mientras se esté efectuando en él una corrida o vela, sin autorización del Inspector\nAgropecuario.\nCAPÍTULO VIII\nMOVILIZACIÓN DE GANADO, PRODUCTOS\nY SUBPRODUCTOS DE ORIGEN ANIMAL.\nARTÍCULO 95.- Toda conducción de animales en lo individual o en hato, productos y subproductos de origen animal, deberán ampararse con un documento que se denominará\n\"guía de tránsito\".\nARTÍCULO 96.- La guía de tránsito será expedida a solicitud de la persona propietaria de manera física, por las y los inspectores agropecuarios de la Secretaría o las personas\nLey de Desarrollo Agropecuario del Estado de Baja California. Página 30 habilitadas por esta, así como en su modalidad electrónica en la zona correspondiente, previo reconocimiento de los animales y exhibición del certificado zoosanitario.\nArtículo Reformado\nARTÍCULO 97.- La guía de tránsito contendrá los siguientes datos:\nI.- Nombre y domicilio del remitente (dueño de los animales y en su caso de su representante);\nII.- Rancho o lugar de procedencia;\nIII.- Nombre y domicilio del conductor, modelo, marca y placa del vehículo en que será transportado el ganado, sus productos o los subproductos;\nIV.- Nombre y domicilio del destinatario y lugar de destino;\nV.- Número de animales que se movilizan, cantidad y clase del producto o subproducto que se moviliza;\nVI.- Especie, clase y sexo de los animales;\nVII.- Marca y número del título de registro;\nVIII.- Fines de movilización, y\nIX.- Los demás que a juicio de la Secretaría, se requieran.\nLa guía deberá ir dirigida al Inspector Agropecuario de la zona de destino del ganado, producto o subproducto.\nARTÍCULO 98.- El Inspector Agropecuario que autorice una revisión sin haberla practicado, o de fé de algún hecho que no le constare, será sancionado conforme a la normatividad aplicable.\nARTÍCULO 99.- No podrá hacerse ningún movimiento o embarque de animales, de sus productos o subproductos, si no se comprueba previamente su procedencia con la guía de tránsito correspondiente debidamente autorizada por el Inspector Agropecuario.\nTampoco podrá hacerse ningún sacrificio de ganado o animales en los rastros, salas de matanza o plantas industrializadoras, si no se comprueba su procedencia con la copia de la guía de tránsito debidamente autorizada, y previa la cancelación que la autoridad correspondiente haga de la guía.\nARTÍCULO 100.- Los inspectores agropecuarios podrán inspeccionar en su zona las partidas de ganado o animales, o sus productos o subproductos, así como las demás\nLey de Desarrollo Agropecuario del Estado de Baja California. Página 31 especies a que se refiera esta Ley, exigiendo la comprobación de su legal procedencia, pero en ningún caso podrán cobrar emolumentos o derechos por este concepto.\nCAPÍTULO IX\nDE LA ENTRADA Y SALIDA DE GANADO,\nPRODUCTOS Y SUBPRODUCTOS EN EL ESTADO\nARTÍCULO 101.- Todo ganado, producto o subproducto que ingrese o salga del\nEstado, requerirá el amparo de permisos de introducción o en su caso de salida y con sus correspondientes guías de tránsito que emita la Secretaria, la cual tomará en cuenta para su expedición las condiciones de los productores y el consumo local.\nSi los bienes amparados por los documentos citados en el parrafo anterior permanecen por un período mayor de cuarenta días dentro de los límites territoriales del\nEstado, será objeto de todos los impuestos en vigor.\nQuienes movilicen animales de las especies domésticas productivas, productos y subproductos, tendrán la obligación de detenerse de manera obligatoria en los puntos de verificación fitozoosanitarios, para que se les revisen estos y les sellen la validación de guías de tránsito, facturas o documentos de transmisión de propiedad y certificados zoosanitarios.\nARTÍCULO 102.- Con la finalidad de proteger la producción estatal y la ganadería regional, la Secretaría establecerá en disposiciones reglamentarias las medidas zootécnicas, sanitarias o de calidad, de los animales para el abasto, así como para evitar la introducción y comercialización al Estado de animales de desecho y de salud dudosa.\nSe prohibe toda introducción de ganado mayor o menor al Estado en pie o en canal, y sus productos y subproductos sin la autorización de la Secretaría, a quien le competerá extender los permisos de introducción respectivos.\nARTÍCULO 103.- Para otorgar los permisos de introducción la Secretaría deberá considerar lo siguiente:\nI.- Demanda en el mercado interno;\nII.- Producción estatal;\nIII.- Programas ganaderos respectivos\nIV.- Condiciones zoosanitarias y sanitarias de los animales productos y subproductos,\nV.- En su caso, las opiniones de las organizaciones ganaderas establecidas en el\nEstado.\nLey de Desarrollo Agropecuario del Estado de Baja California. Página 32 cuenten con la patente a que se refiere el artículo 4 de esta Ley, y que cumplan con la normatividad aplicable.\nCAPÍTULO X\nMEJORAMIENTO DE LA GANADERIA.\nARTÍCULO 104.- La Secretaría promoverá la implementación de un Sistema Estatal de Cría, de acuerdo con las necesidades de la ganadería local, debiendo determinar las especies, razas y variedades más adecuadas zootécnica y económicamente, para cada zona del Estado y organizará dicho sistema como empresa de interés público, con la cooperación de los ganaderos locales, a fin de lograr el fomento efectivo de la ganadería.\nARTÍCULO 105.- El Sistema Estatal de Cría se integrará por una Estación Central de\nCría, por Postas Zootécnicas de Monta, y por Bancos de Semen.\nLa Secretaría determinará las especies y número de animales que integrarán cada una de las unidades a que se refiere el párrafo anterior, así como el lugar de ubicación y zona de influencia de las mismas.\nARTÍCULO 106.- La Estación Central de Cría, se encargará de:\nI.- Producir animales de razas superiores, para el mejoramiento de los ganados de la zona de influencia que corresponda a cada una de las unidades a que se refiere el artículo anterior;\nII.- Dotar de sementales a las Postas Zootécnicas de Monta;\nIII.- Canjear animales selectos por criollos que pertenezcan a ganaderos organizados;\nIV.- Vender al costo animales selectos, y\nV.- Prestar servicios de medicina veterinaria, investigaciones, demostración y enseñanza zootécnica.\nARTÍCULO 107.- Las Postas Zootécnicas, tendrán a su cargo, las siguientes funciones:\nI.- Proporcionar servicios de monta con sementales de razas mejoradas o mediante inseminación artificial y material fecundante a los bancos de semen;\nII.- Seleccionar las hembras destinadas a ser servidas por los sementales de las postas;\nIII.- Hacer demostraciones prácticas de bromatología y alimentación racional, y\nLey de Desarrollo Agropecuario del Estado de Baja California. Página 33\nIV.- Cooperar en la implementación de medidas de higiene veterinaria y alimentación racional.\nARTÍCULO 108.- Tanto la Estación Estatal de Cría como las Postas Zootécnicas, protegerán a las crías hembras, hijas de los sementales selectos que hayan prestado servicio de monta, dado que el objeto de tales servicios es el mejoramiento de la ganadería.\nCAPÍTULO XI\nDE LAS EMPRESAS LECHERAS\nARTÍCULO 109.- Constituyen empresas lecheras en el Estado, toda persona física o moral cuya actividad ganadera sea conformada por tierras propias, poseídas o arrendadas, ganado lechero, edificaciones y maquinaria, por medio de los cuales se produzca, industrialice y comercialice la leche y sus derivados.\nARTÍCULO 110.- La Secretaría en coordinación con la federación y municipios en el ámbito de sus competencias, promoverá y dictará las medidas que sean necesarias tendientes al fomento y desarrollo de la actividad lechera en el Estado.\nARTÍCULO 111.- Los propietarios o administradores de las empresas lecheras en el\nEstado, deberán registrarse ante la Secretaría e informar a dicha dependencia, los datos sobre producción y operación que les sean requeridos. Asimismo, deberán mostrar sus registros correspondientes a las autoridades competentes, cuando sean solicitados.\nARTÍCULO 112.- La Secretaría tendrá a su cargo el control y vigilancia de las empresas lecheras en la jurisdicción del Estado, a cuyo efecto llevará un Libro de Registro de las mismas, con especificación precisa de los elementos materiales que las constituyen, su forma de organización y su modo de operación.\nARTÍCULO 113.- Es facultad y obligación de la Secretaría, consolidar con medidas concretas y adecuadas para la unidad y fortalecimiento de la actividad lechera y evitar su desmantelamiento y extinción, para cuyo fin conciliará su acción de autoridad con los intereses del dueño, pero tan sólo hasta el límite en que no sufra el interés de la comunidad.\nCAPÍTULO XII\nDE LA APICULTURA\nARTÍCULO 114.- La Secretaría promoverá y fomentará la modernización de esta actividad para el incremento de la producción y mejoramiento genético.\nARTÍCULO 114 BIS.- La Secretaría atenderá las consultas técnicas que les formulen las personas que se inicien o se dediquen al negocio apícola.\nArtículo Adicionado\nLey de Desarrollo Agropecuario del Estado de Baja California. Página 34\nARTÍCULO 114 TER.- La Secretaría en coordinación con autoridades competentes y organismos auxiliares, deberán:\nI.- Atender las Normas Oficiales Mexicanas, lineamientos y procedimientos que se establezcan, para la prevención y control de las actividades del hombre que dañen a las abejas;\nII.- Establecer las medidas necesarias para la protección de las zonas y plantas que conforman el ecosistema del Estado; y,\nIII.- Fomentar la creación de organismos o asociaciones donde participen los apicultores en todas las actividades encaminadas a promover el desarrollo y tecnificación de la actividad apícola.\nArtículo Adicionado\nARTÍCULO 115.- Los apicultores están obligados a registrarse ante la Secretaría, proporcionar datos estadísticos de su producción, censos, ubicación de apiarios y marcar sus colmenas a fin de poder identificarlas.\nARTÍCULO 116.- La propiedad de los apiarios se acredita con:\nI.- Factura o documento legal que acredite la transferencia de dominio;\nII.- Guía de tránsito que ampara el traslado del lugar de origen al de ubicación del apiario, y\nIII.- La patente del registro correspondiente de la Secretaría.\nARTÍCULO 117.- La compra y venta de colmenas, material apícola marcado deberá efectuarse acompañado de la factura correspondiente. El comprador colocará su marca a un lado de la del vendedor sin borrarla.\nARTÍCULO 118.- Todo apicultor al instalar sus apiarios deberá observar las siguientes distancias:\nI.- En los caminos vecinales aproximadamente a quince metros de los mismos, y\nII.- En los predios, a una distancia no menor de 200 metros de la casa o casas habitación de la ranchería o centro de población; se deberá acreditar el derecho al uso del predio para instalar apiarios en terrenos de propiedad privada.\nFracción Reformada\nSecretaría. Las colmenas o núcleos quedarán a disposición de la Secretaría y el producto que se obtenga será entregado al infractor, previo pago de la sanción administrativa correspondiente.\nLey de Desarrollo Agropecuario del Estado de Baja California. Página 35\nArtículo Reformado\nCAPÍTULO XIII\nDE LA AVICULTURA\nARTÍCULO 119.- La Secretaría con el personal especializado necesario, organizará y encausará los trabajos de promoción avícola general y al efecto procederá a:\nI.- Planear, fomentar y asegurar técnicamente la producción avícola;\nII.- Definir, aplicar y difundir los métodos y procedimientos técnicos destinados a incrementar la productividad y rendimiento en las industrias conexas;\nIII.- Promover el mejoramiento y desarrollo de las granjas avícolas registradas ante la\nSecretaría;\nIV.- Promover la creación de plantas y granjas avícolas con el objeto de lograr una producción óptima que lleve a un mejor aprovechamiento de los recursos de la entidad,\nV.- Promover la participación de los productores organizados en los programas y acciones que se impulsen para el desarrollo de la avicultura en el Estado;\nVI.- Difundir e impartir conocimientos científicos y prácticos, acerca de la cría y explotación de aves;\nVII.- Fomentar y encausar la industrialización de los productos que se obtengan de estos animales, y\nVIII.- Fomentar las investigaciones de la especialidad, estableciendo y organizando estaciones experimentales, laboratorios y granjas piloto.\nARTÍCULO 120.- Las plantas o granjas avícolas deberán obtener su registro en la\nSecretaría y proporcionar los datos que le sean requeridos. e higiénicos, de acuerdo a las normas técnicas aplicables en la materia. urbana.\nARTÍCULO 121.- El Ejecutivo del Estado reglamentará el acceso de huevo y carnes de aves al Estado, cuando así lo requiera el sano desarrollo de la avicultura en la Entidad, observando las disposiciones de la presente Ley. La Secretaría regulará el programa de clasificación de huevo en el Estado, mismo que será de carácter obligatorio\nLey de Desarrollo Agropecuario del Estado de Baja California. Página 36\nCAPÍTULO XIV\nDE LA PORCICULTURA\nARTÍCULO 122.- La Secretaría en coordinación con las autoridades federales, municipales en materia pecuaria y productores especializados organizados, promoverán y el Estado.\nARTÍCULO 123.- Queda prohibida la instalación de granjas porcícolas en los centros y demarcaciones territoriales consideradas urbanas que señalen las autoridades agropecuarias.\nLas granjas porcícolas deberán contar con instalaciones y equipos higiénicos de acuerdo a las normas técnicas aplicables a la materia.\nARTÍCULO 124.- Toda persona física o moral que se dedique a la porcicultura deberá obtener el registro correspondiente ante la Secretaría y proporcionar los datos que le sean requeridos.\nARTÍCULO 125.- La Secretaría en coordinación con las autoridades competentes promoverá y coordinará el programa estatal de clasificación de carne de ganado porcino en canal.\nCAPÍTULO XV\nDE LOS RASTROS Y SACRIFICIOS DE GANADO\nARTÍCULO 126.- Sólo podrá sacrificarse animales para consumo humano o para procesos de transformación, en los rastros o salas de matanza legalmente autorizados.\nARTÍCULO 127.- El administrador del rastro o sala de matanza, vigilará bajo su más estricta responsabilidad, que se compruebe la propiedad de los animales, la documentación sanitarias y zoosanitarias correspondientes, previamente a su sacrificio.\nARTÍCULO 128.- Los administradores de rastros o responsables de salas de matanza, responderán personalmente del cumplimiento de esta Ley en relación con los sacrificios de animales que se efectúen en los establecimientos a su cargo; además están obligados a llevar un registro que contenga lo siguiente:\nI.- Estar elaborado en orden numérico y fechas;\nII.- Anotarán la entrada de los animales al rastro, el nombre y domicilio del introductor;\nIII.- El nombre del rancho o lugar de procedencia;\nLey de Desarrollo Agropecuario del Estado de Baja California. Página 37\nIV.- La especie, color, edad, clase y marca de los animales;\nV.- El número de guía de tránsito;\nVI.- El número y fecha del aviso de movilización;\nVII.- El nombre del Inspector Agropecuario que lo expidió;\nVIII.- Los nombres y domicilios del vendedor y del comprador;\nIX.- La fecha del sacrificio y\nX.- El costo generado, Debiendo reservar una columna para las anotaciones de circunstancias imprevistas y sellarán la carne con el sello especial de cada Rastro.\nLos registros de los rastros o salas de matanza, podrán ser revisados, en cualquier tiempo, por los inspectores agropecuarios.\nARTÍCULO 129.- Los administradores o encargados de rastros, deberán rendir periódicamente a la Secretaría, un informe del movimiento de animales y sacrificios efectuados y la entrega de las guías de tránsito canceladas.\nARTÍCULO 130.- El sacrificio de hembras se sujetará a las disposiciones que dicte el\nEjecutivo del Estado con el fin de proteger los hatos reproductores en la entidad y evitar su extinción.\nARTÍCULO 131.- Los ganados sacrificados fuera de la jurisdicción del Estado, que pretendan ser introducidos a la entidad, deberán ser presentados al rastro o sala de matanza que indique la Secretaría con el objeto de que se revisen los documentos relativos, se inspeccione la carne y se cubran los costos correspondientes.\nARTÍCULO 132.- Las carnes, productos y subproductos de origen animal, que se documentación que avale su legal procedencia, serán decomisados; procediendo la\nSecretaría a dar vista al Ministerio Público por si existiera la comisión de algún delito.\nCAPÍTULO XVI\nDE LOS SELLOS OFICIALES\nARTÍCULO 133.- La fabricación de sellos oficiales, registradores y fechadores para el de inspección, sólo serán autorizados por el Ejecutivo del Estado, a través de la Secretaría.\nLey de Desarrollo Agropecuario del Estado de Baja California. Página 38\nLas tintas y los sellos para el marcado de carnes, huevo, productos y subproductos de origen animal, así como la documentación oficial, serán diseñados y autorizados por la alimentos.\nPárrafo Reformado\nArtículo Reformado\nARTÍCULO 134.- Queda prohibido a toda persona fisica o moral, fabricar sellos oficiales, registradores o fechadores, sin orden expresa de la Secretaría.\nCAPÍTULO XVII\nDE LA INSPECCIÓN\nARTÍCULO 135.- La inspección de ganado, sus productos y subproductos y derivados, es obligatoria y tiene por objeto la comprobación de su procedencia, del cumplimiento de los requisitos sanitarios, de las obligaciones fiscales, de las guías de tránsito y demás documentos que exige esta Ley para su movilización, sacrificio, industrialización y comercialización.\nARTÍCULO 136.- La inspección ganadera, sus productos y subproductos y derivados, tendrán lugar:\nI.- En las propiedades ganaderas y avícolas;\nII.- En tránsito por la zona en su cargo;\nIII.- En los rastros y salas de matanzas, y\nIV.- En los corrales, establos, tenerías, talabarterías, granjas avícolas, porcícolas, cunícolas, apiarios y demás establecimientos en que se beneficien, distribuyan o vendan los productos y subproductos de origen animal, y\nV.- En las industrias pasteurizadoras, procesadoras y empacadoras del Estado.\nARTÍCULO 137.- Para la realización de toda inspección de ganado, la Secretaría oyendo la opinión de las organizaciones ganaderas, establecerá el número de zonas de inspección que sean necesarias.\nTÍTULO QUINTO\nDE LOS SERVICIOS A PRODUCTORES\nCAPÍTULO I\nASISTENCIA TÉCNICA INTEGRAL\nLey de Desarrollo Agropecuario del Estado de Baja California. Página 39\nARTÍCULO 138.- La Secretaría por sí o por conducto de la unidad administrativa que determine, prestará el servicio de asistencia técnica integral a que se refiere el presente capítulo y será la coordinadora general de ésta en el Estado.\nLos servicios de asistencia técnica, incluirán la asesoría y capacitación a productores agrícolas y pecuarios en el Estado, atendiendo de manera prioritaria a productores organizados, brindando los servicios de clasificación de alimentos y productos agropecuarios para procurar la sanidad, calidad e inocuidad en beneficio del consumidor final.\nLa Secretaría, tendrá como instrumento para el logro de los objetivos a que se refiere el presente capítulo, el Programa de Asistencia Técnica Integral. Las organizaciones de productores agropecuarios, participarán en la formulación del programa, conforme a los lineamientos que dicte la Secretaría.\nARTÍCULO 139.- La Secretaría, será la única Dependencia facultada para otorgar la asistencia técnica integral a los productores agropecuarios del Estado, de acuerdo con los lineamientos de los programas que se emitan; cualquier otra asistencia técnica dentro de este sector otorgada por particulares o niveles diferentes de Gobierno, deberá estar registrada ante la Secretaría, debiendo acatar los lineamientos que al respecto se emitan.\nARTÍCULO 140.- El Gobierno del Estado incluirá anualmente en su presupuesto de egresos, partidas presupuestales destinadas a cooperar para el sostenimiento de la unidad administrativa de la Secretaría, encargada de la asistencia técnica integral en la materia y al mismo fin deberán hacer sus aportaciones todos los sectores interesados de acuerdo a lo que la propia Secretaría proponga, a fin de llevar adelante sus programas.\nARTÍCULO 141.- Las aportaciones económicas de cualquier tipo que para el sostenimiento de las acciones en materia de asistencia técnica integral hagan los productores, dependencias oficiales o particulares, serán a través de convenios en los que se estipulen claramente los compromisos y condiciones de los contratantes y pueden ser promovidos por cualquier interesado, siendo en todo caso necesario contar con el punto de vista favorable de la Secretaría.\nARTÍCULO 142.- La Secretaría, podrá contratar los servicios de técnicos o de otro tipo de profesionales, para estudios o trabajos específicos que se requieran en el cumplimiento de sus programas de asistencia técnica integral.\nARTÍCULO 143.- La Secretaría, coordinará sus acciones con las de los demás sectores productivos, de servicio y de apoyo a fin de integrar correctamente las actividades en el Estado.\nARTÍCULO 144.- Prestarán su colaboración a la Secretaría, todos los organismos e agropecuaria del Estado.\nLey de Desarrollo Agropecuario del Estado de Baja California. Página 40\nARTÍCULO 145.- La Secretaría, promocionará nuevas tecnologías, con la finalidad de incrementar los rendimientos en, la productividad y disminuir los costos de inversión de los productores.\nCAPÍTULO II\nPRODUCCIÓN DE SEMILLAS CERTIFICADAS\nARTÍCULO 146.- Se establece como obligatorio en el Estado, el uso de semilla certificada y suficiente para la siembra de cultivos agrícolas de carácter comercial de acuerdo a las especificaciones y recomendaciones del Instituto Nacional de Investigaciones\nAgrícolas para la región.\nARTÍCULO 147.- La Secretaría promoverá la producción de semilla certificada a efecto de subsanar las necesidades del Estado en ese renglón y contribuir con los excedentes a los requerimientos nacionales y de exportación.\nARTÍCULO 148.- Se impulsará en el Estado, la investigación científica como medio para obtener semillas de mejor calidad y mayor productividad, adaptadas a las condiciones ecológicas de las distintas regiones en la Entidad.\nARTÍCULO 149.- La Secretaría en coordinación con la autoridad competente, apoyará en el establecimiento de medidas de vigilancia tendientes a evitar la comercialización de semillas que no se apeguen a las normas de calidad y fitosanitarias como lo establece la Ley Federal de Producción, Certificación y Comercio de Semillas.\nARTÍCULO 150.- La Secretaría en coordinación con la autoridad competente a solicitud expresa, vigilará y exigirá que los expendedores de semillas para siembra cumplan con las normas de calidad que garanticen la óptima germinación, vigor y características de las diversas variedades de semilla, señalando o acompañando esta información en las etiquetas adheridas al envase del producto.\nTÍTULO SEXTO\nDEL FOMENTO AL DESARROLLO AGROPECUARIO\nCAPÍTULO I\nDE LAS EXPOSICIONES AGROPECUARIAS\nARTÍCULO 151.- La Secretaría convocará periódicamente a todos los organismos gubernamentales y no gubernamentales, para la celebración de exposiciones, concursos, congresos y ferias agropecuarias, como medida de estímulo y fomento a las actividades agropecuarias. El Ejecutivo del Estado facultará a la Secretaría para que dicte las disposiciones necesarias al respecto.\nLey de Desarrollo Agropecuario del Estado de Baja California. Página 41\nARTÍCULO 152.- Los productos agrícolas y animales para la exposición, serán examinados previamente por los técnicos oficiales designados por la Secretaría, con el\nCAPÍTULO II\nARTÍCULO 153.- El Ejecutivo del Estado por conducto de la Secretaría y la Secretaría de Economía e Innovación promoverán el fomento y apoyo a la comercialización y organizarán la creación y permanencia de centros de promoción de agronegocios, con la finalidad de impulsar la comercialización de los productos y subproductos agropecuarios producidos en el Estado.\nArtículo Reformado\nARTÍCULO 154.- La Secretaría conjuntamente con la Secretaría de Economía e\nInnovación, impulsarán y organizarán cursos y asesorías sobre cultura empresarial, proyectos de inversión, producción de calidad, mercados, estrategias de comercialización, entre otros, a las asociaciones, sociedades y similares de productores agropecuarios y agroindustriales en el Estado.\nArtículo Reformado\nARTÍCULO 155.- La política de comercialización atenderá las siguientes propuestas:\nI.- Promover el equilibrio en la balanza comercial resultante del intercambio de productos ofertados por la sociedad rural, tanto en el mercado interior como exterior;\nII.- Lograr una mayor articulación de la producción primaria en los procesos de comercialización y transformación, para darles un mayor valor agregado, para así elevar la competitividad del sector rural y de las cadenas productivas del mismo;\nIII.- Dar certidumbre a los productores para favorecer la reactivación de la producción, y estimular la productividad y rentabilidad de los productos y subproductos agropecuarios;\nIV.- Estimular, fortalecer y normar la operación de empresas comercializadoras y de servicios para el acopio y almacenamiento de productos y subproductos agropecuarios;\nV.- Establecer e instrumentar reglas claras y equitativas para el intercambio de productos ofertados por la sociedad rural, tanto en el mercado interior como exterior;\nVI.- Fortalecer el mercado interno y la competitividad de la producción local; promoviendo mecanismos de concertación entre productores primarios, industriales y los características y cantidades de los productos, precios y formas de pago, y\nLey de Desarrollo Agropecuario del Estado de Baja California. Página 42\nVII.- Difundir la información de mercados regionales, nacionales e internacionales, relativos a la demanda y la oferta, inventarios existentes, expectativas de producción y estimaciones de precios por producto y calidad con el fin de facilitar la comercialización.\nEl Ejecutivo del Estado apoyará a los productores agropecuarios organizados, cuando éstos en legítima defensa de la planta productiva estatal, demuestren que son afectados por prácticas desleales de comercio nacional o internacional, implementando acciones provisionales de gobierno y promoverá ante el Ejecutivo Federal su intervención en la salvaguarda del desarrollo productivo y económico del Estado y del País.\nCAPÍTULO III\nFINANCIAMIENTO Y ESTÍMULOS A LA PRODUCTIVIDAD\nARTÍCULO 156.- La Secretaría con el objeto de elevar la productividad agropecuaria, y para fortalecer el empleo en el sector rural, le corresponderá fomentar, promover e impulsar la constitución de fideicomisos, fondos y organismos de participación pública y privada, con la intervención de aquellas instituciones crediticias que incidan para el otorgamiento de créditos y estímulos a los productores primarios del Estado.\nArtículo Reformado\nARTÍCULO 157.- La Secretaría para efecto de fortalecer y consolidar las actividades de los productores en el desarrollo agropecuario, impulsará los siguientes esquemas de financiamiento:\nI.- Apoyos financieros preferenciales;\nII.- Créditos puentes, de habilitación o avío;\nIII.- Créditos simples y refaccionarios, y\nIV.- Tratamientos de cartera.\nAsimismo, impulsará como fuentes alternas de pago, las garantías líquidas y complementarias.\nARTÍCULO 158.- Con los esquemas de crédito y financiamiento del artículo anterior productivo en sus actividades, y a los proyectos viables, rentables y estratégicos para el desarrollo del Estado.\nEl Ejecutivo del Estado podrá solicitar al Congreso del Estado, la aprobación de pertinentes; adicionalmente, podrá recibir participaciones y recursos de instituciones financieras públicas y privadas.\nLey de Desarrollo Agropecuario del Estado de Baja California. Página 43\nARTÍCULO 159.- Los fines de los fideicomisos, fondos y organismos de participación pública y privada serán los siguientes:\nI.- Promover la formalización de los apoyos gubernamentales directos para incrementar la productividad del sector en el Estado;\nII.- Establecer las bases para la instrumentación de esquemas novedosos y prácticos de financiamiento, bajo mecanismos de seguridad para la recuperación de los créditos y el control de la comercialización anticipada de la producción agropecuaria y agroindustrial;\nIII.- Otorgar garantías en forma complementada, a los productores que lo requieran, para el cumplimiento de las obligaciones crediticias que contraigan con intermediarios financieros facultados para otorgarles financiamientos, que les permitirán su incorporación a la producción tecnificada de productos cíclicos rentables;\nIV.- Otorgar apoyos financieros preferentes a los productores que se proporcionarán para consolidar el desarrollo de las actividades agropecuarias;\nV.- Otorgamiento de créditos puente para complementar el inicio de actividades agropecuarias dentro del Estado, de las empresas rurales que cuenten con autorización previa y/o el aval de los intermediarios financieros, que garanticen en primer lugar, el pago de créditos revolventes y en segundo lugar, que proporcione financiamiento suficiente para su incorporación a las actividades mencionadas;\nVI.- Fortalecer y consolidar los fondos de contingencia que se establezcan para abatir los riesgos climatológicos que afecten las actividades agropecuarias;\nVII.- Fomentar y promover los programas de saneamiento financiero de los sectores productivos agropecuarios y agroindustriales en el Estado, y\nVIII.- Promover y obtener de las instituciones financieras del país como del extranjero, líneas de crédito específicas para el desarrollo de los productores del campo.\nCAPÍTULO IV\nFONDO DE FOMENTO PARA EL DESARROLLO RURAL\nARTÍCULO 159 BIS.- El Ejecutivo del Estado, a través de la Secretaría creará un\nFondo de Fomento para el Desarrollo Rural Sustentable, cuyo fin primordial se orientará a incrementar la productividad y la competitividad en el ámbito rural, con el fin de fortalecer el empleo, el desarrollo de talentos profesionales regionales y elevar el ingreso de los productores; asimismo generar condiciones favorables para ampliar los mercados agropecuarios; a aumentar el capital natural para la producción, y creación de fuentes de trabajo en el sector rural, así como a la constitución y consolidación de empresas rurales.\nLa Secretaría deberá propiciar con este Fondo:\nLey de Desarrollo Agropecuario del Estado de Baja California. Página 44\nI. El impulso a la investigación y desarrollo tecnológico agropecuario;\nII. El desarrollo de los recursos humanos, promoviendo el desarrollo de padrones de técnicos y profesionistas egresados de las escuelas y universidades regionales rurales, a efecto de incentivar su contratación;\nIII. La inversión tanto pública como privada para la ampliación y mejoramiento de la infraestructura en el sector rural;\nIV. El fomento a los sistemas familiares de producción;\nV. El fomento al desarrollo de las capacidades productivas de los jóvenes, mujeres y pequeños productores del sector rural;\nVI. El impulso a la industria, agroindustria y la integración de cadenas productivas, así como el desarrollo de la infraestructura industrial en el medio rural;\nVII. El impulso a las actividades económicas no agropecuarias en el que se desempeñan los diversos agentes de la sociedad rural;\nVIII. La creación de condiciones adecuadas para enfrentar el proceso de globalización;\nIX. La conservación y mejoramiento de los recursos naturales; y\nX. Las demás que se deriven del cumplimiento de esta Ley.\nArtículo Adicionado\nTÍTULO SÉPTIMO\nDE LAS INFRACCIONES, SANCIONES Y\nMEDIO DE DEFENSA\nCAPÍTULO ÚNICO\nARTÍCULO 160.- Las infracciones a los preceptos de esta Ley y sus reglamentos, serán sancionadas administrativamente por la Secretaría, con alguna de las siguientes sanciones:\nI.- Por infracción al artículos 4, 45 o 46 de esta Ley, con multa de diez a veinte veces el valor diario de la Unidad de Medida y Actualización vigente;\nFracción Reformada\nII.- Por infracción al artículo 52 de esta Ley, con multa de veinte a cuarenta veces el valor diario de la Unidad de Medida y Actualización vigente;\nFracción Reformada\nIII.- Por infracción al artículo 51, 56, 58, 78, 94, 98 ó 133 de esta Ley, con multa de treinta a cincuenta veces el valor diario de la Unidad de Medida y Actualización vigente;\nFracción Reformada\nLey de Desarrollo Agropecuario del Estado de Baja California. Página 45\nIV.- Por infracción a cualquier otro artículo de esta Ley o su reglamento, diverso a los señalados en las fracciones anteriores, con:\na) Amonestación;\nb) Multa de diez a dos mil veces el valor diario de la Unidad de Medida y Actualización vigente, y\nInciso Reformado\nc) La suspensión o revocación de los permisos y autorizaciones correspondientes.\nArtículo Reformado\nARTÍCULO 161.- La Secretaría para imponer cualquiera de las sanciones previstas en este Capítulo, deberá proceder conforme a la normatividad aplicable.\nLas multas se harán efectivas por conducto de la Secretaría de Hacienda del Estado de Baja California conforme a las formalidades del Código Fiscal del Estado de Baja\nCalifornia.\nPárrafo Reformado\nArtículo Reformado\nARTÍCULO 162.- Para la fijación de las sanciones previstas en este Capítulo, se tomarán en consideración las circunstancias en que se realizó la infracción, la mayor o menor responsabilidad y condiciones económicas del infractor, así como el daño que causó o pudo causar a la industria agrícola o ganadera, a la salud agropecuaria o a la de los consumidores.\nARTÍCULO 163.- En caso de inconformidad por la aplicación de alguna de las disposiciones o resoluciones contenidas en esta Ley y su Reglamento, los interesados afectados podrán interponer el recurso de revocación en los términos del Título Quinto de la\nLey del Procedimiento para los actos de la Administración Pública del Estado.\nARTÍCULOS TRANSITORIOS:\nPRIMERO.- Las presentes reformas entrarán en vigor el día siguiente al de su publicación en el Periódico Oficial del Estado.\nSEGUNDO.- Se deroga la Ley de Fomento Agropecuario y Forestal del Estado de\nBaja California, así como las demás disposiciones que se opongan a la aplicación de la presente Ley.\nTERCERO.- Los asuntos que se encuentren en trámite a la entrada en vigor del presente decreto, serán resueltos conforme a las normas vigentes al momento de su inicio.\nLey de Desarrollo Agropecuario del Estado de Baja California. Página 46 del Estado de Baja California, en la Ciudad de Mexicali, B.C., a los veinticuatro días del mes de septiembre del año dos mil diez.\nDIP. JUAN MANUEL GASTÉLUM BUENROSTRO\nPRESIDENTE\n(RÚBRICA)\nDIP. CARLOS ALONSO ÂNGULO RENTERIA\nSECRETARIO\n(RÚBRICA)\nDE CONFORMIDAD CON LO DISPUESTO POR LA FRACCION I DEL ARTÍCULO 49\nMEXICALI, BAJA CALIFORNIA, A LOS TREINTA DIAS DEL MES DE SEPTIEMBRE\nDEL AÑO DOS MIL DIEZ.\nGOBERNADOR DEL ESTADO\nJOSE GUADALUPE OSUNA MILLÁN\n(RÚBRICA)\nSECRETARIO GENERAL DE GOBIERNO\nCUAUHTÉMOC CARDONA BENAVIDES\n(RÚBRICA)\nLey de Desarrollo Agropecuario del Estado de Baja California. Página 47\nArtículo 1.- Fue reformado mediante Decreto No. 147, publicado en el Periódico\nXXV Legislatura, siendo Gobernadora Constitucional la C. Marina del Pilar Ávila Olmeda\n2021-2027;\nArtículo 2.- Fue reformado por Decreto No. 513, publicado en el Periódico Oficial No.\n40, de fecha 13 septiembre de 2013, Sección I, Tomo CXX, expedido por la H. XX\nLegislatura, siendo Gobernador Constitucional el C. José Guadalupe Osuna Millán 20072013; fue reformado por Decreto No. 66, publicado en el Periódico Oficial No. 39, Sección II, de fecha 01 de agosto de 2014, Tomo CXXI, expedido por la H. XXI Legislatura, siendo\nGobernador Constitucional el C. Francisco Arturo Vega de Lamadrid 2013-2019;\nArtículo 4.- Fue reformado mediante Decreto No. 289, publicado en el Periódico\nOficial No. 55, Índice, de fecha 25 de septiembre de 2023, Tomo CXXX, expedido por la H.\nXXIV Legislatura, siendo Gobernadora Constitucional la C. Marina del Pilar Ávila Olmeda\n2021-2027;\nArtículo 5.- Fue reformado por Decreto No. 513, publicado en el Periódico Oficial No.\n40, de fecha 13 septiembre de 2013, Sección I, Tomo CXX, expedido por la H. XX\nLegislatura, siendo Gobernador Constitucional el C. José Guadalupe Osuna Millán 20072013; fue reformado por Decreto No. 146, publicado en el Periódico Oficial No. 50, Sección\nIII, de fecha 10 de noviembre de 2017, Tomo CXXIV, expedido por la H. XXII Legislatura, siendo Gobernador Constitucional el C. Francisco Arturo Vega de Lamadrid 2013-2019; fue reformado mediante Decreto No. 289, publicado en el Periódico Oficial No. 55, Índice, de fecha 25 de septiembre de 2023, Tomo CXXX, expedido por la H. XXIV Legislatura, siendo\nGobernadora Constitucional la C. Marina del Pilar Ávila Olmeda 2021-2027; fue reformado mediante Decreto No. 455, publicado en el Periódico Oficial No. 40, Índice, de fecha 16 de agosto de 2024, Tomo CXXXI, expedido por la H. XXIV Legislatura, siendo Gobernadora\nConstitucional la C. Marina del Pilar Ávila Olmeda 2021-2027; fue reformado mediante\nDecreto No. 97, publicado en el Periódico Oficial No. 37, Índice, de fecha 20 de junio de\n2025, Tomo CXXXII, expedido por la H. XXV Legislatura, siendo Gobernadora Constitucional la C. Marina del Pilar Ávila Olmeda 2021-2027;\nArtículo 6.- Fue reformado por Decreto No. 146, publicado en el Periódico Oficial No.\nLegislatura, siendo Gobernador Constitucional el C. Francisco Arturo Vega de Lamadrid\n2013-2019; fue reformado mediante Decreto No. 289, publicado en el Periódico Oficial No.\nLegislatura, siendo Gobernadora Constitucional la C. Marina del Pilar Ávila Olmeda 20212027;\nArtículo 7.- Fue reformado por Decreto No. 146, publicado en el Periódico Oficial No.\nLey de Desarrollo Agropecuario del Estado de Baja California. Página 48\nLegislatura, siendo Gobernador Constitucional el C. Francisco Arturo Vega de Lamadrid\n2013-2019; fue reformado mediante Decreto No. 289, publicado en el Periódico Oficial No.\nLegislatura, siendo Gobernadora Constitucional la C. Marina del Pilar Ávila Olmeda 20212027;\nArtículo 8.- Fue reformado por Decreto No. 513, publicado en el Periódico Oficial No.\n40, de fecha 13 septiembre de 2013, Sección I, Tomo CXX, expedido por la H. XX\nLegislatura, siendo Gobernador Constitucional el C. José Guadalupe Osuna Millán 20072013; fue reformado por Decreto No. 146, publicado en el Periódico Oficial No. 50, Sección\nIII, de fecha 10 de noviembre de 2017, Tomo CXXIV, expedido por la H. XXII Legislatura, siendo Gobernador Constitucional el C. Francisco Arturo Vega de Lamadrid 2013-2019; fue reformado mediante Decreto No. 289, publicado en el Periódico Oficial No. 55, Índice, de fecha 25 de septiembre de 2023, Tomo CXXX, expedido por la H. XXIV Legislatura, siendo\nGobernadora Constitucional la C. Marina del Pilar Ávila Olmeda 2021-2027;\nArtículo 10.- Fue reformado por Decreto No. 513, publicado en el Periódico Oficial No.\n40, de fecha 13 septiembre de 2013, Sección I, Tomo CXX, expedido por la H. XX\nLegislatura, siendo Gobernador Constitucional el C. José Guadalupe Osuna Millán 20072013;\nArtículo 12.- Fue reformado mediante Decreto No. 147, publicado en el Periódico\nOficial No. 61, Índice, de fecha 10 de octubre de 2025, Tomo CXXXII, expedido por la H.\nXXV Legislatura, siendo Gobernadora Constitucional la C. Marina del Pilar Ávila Olmeda\n2021-2027;\nArtículo 13.- Fue reformado mediante Decreto No. 455, publicado en el Periódico\nOficial No. 40, Índice, de fecha 16 de agosto de 2024, Tomo CXXXI, expedido por la H. XXIV\nLegislatura, siendo Gobernadora Constitucional la C. Marina del Pilar Ávila Olmeda 20212027;\nArtículo 13 BIS.- Fue adicionado mediante Decreto No. 147, publicado en el Periódico\nXXV Legislatura, siendo Gobernadora Constitucional la C. Marina del Pilar Ávila Olmeda\n2021-2027;\nArtículo 15.- Fue reformado mediante Decreto No. 147, publicado en el Periódico\nXXV Legislatura, siendo Gobernadora Constitucional la C. Marina del Pilar Ávila Olmeda\n2021-2027;\nArtículo 21.- Fue reformado por Decreto No. 66, publicado en el Periódico Oficial No.\nLey de Desarrollo Agropecuario del Estado de Baja California. Página 49\nLegislatura, siendo Gobernador Constitucional el C. Francisco Arturo Vega de Lamadrid\n2013-2019;\nArtículo 35 BIS.- Fue adicionado por Decreto No. 146, publicado en el Periódico\nH. XXII Legislatura, siendo Gobernador Constitucional el C. Francisco Arturo Vega de\nLamadrid 2013-2019;\nArtículo 35 TER.- Fue adicionado mediante Decreto No. 455, publicado en el\nPeriódico Oficial No. 40, Índice, de fecha 16 de agosto de 2024, Tomo CXXXI, expedido por la H. XXIV Legislatura, siendo Gobernadora Constitucional la C. Marina del Pilar Ávila\nOlmeda 2021-2027;\nArtículo 35 QUARTER.- Fue adicionado mediante Decreto No. 455, publicado en el\nPeriódico Oficial No. 40, Índice, de fecha 16 de agosto de 2024, Tomo CXXXI, expedido por la H. XXIV Legislatura, siendo Gobernadora Constitucional la C. Marina del Pilar Ávila\nOlmeda 2021-2027;\nArtículo 55.- Fue reformado por Decreto No. 343, publicado en el Periódico Oficial No.\n30, Sección III, de fecha 12 de julio de 2019, Tomo CXXVI, expedido por la H. XXII\nLegislatura, siendo Gobernador Constitucional el C. Francisco Arturo Vega de Lamadrid\n2013-2019;\nArtículo 96.- Fue reformado mediante Decreto No. 97, publicado en el Periódico\nOficial No. 37, Índice, de fecha 20 de junio de 2025, Tomo CXXXII, expedido por la H. XXV\nLegislatura, siendo Gobernadora Constitucional la C. Marina del Pilar Ávila Olmeda 20212027;\nArtículo 114 BIS.- Fue reformado mediante Decreto No. 289, publicado en el Periódico\nOficial No. 55, Índice, de fecha 25 de septiembre de 2023, Tomo CXXX, expedido por la H.\nXXIV Legislatura, siendo Gobernadora Constitucional la C. Marina del Pilar Ávila Olmeda\n2021-2027;\nArtículo 114 TER.- Fue reformado mediante Decreto No. 289, publicado en el por la H. XXIV Legislatura, siendo Gobernadora Constitucional la C. Marina del Pilar Ávila\nOlmeda 2021-2027;\nArtículo 118.- Fue reformado por Decreto No. 513, publicado en el Periódico Oficial\nLegislatura, siendo Gobernador Constitucional el C. José Guadalupe Osuna Millán 20072013;\nArtículo 133.- Fue reformado por Decreto No. 146, publicado en el Periódico Oficial\nLey de Desarrollo Agropecuario del Estado de Baja California. Página 50\nXXII Legislatura, siendo Gobernador Constitucional el C. Francisco Arturo Vega de Lamadrid\n2013-2019;\nArtículo 153.- Fue reformado mediante Decreto No. 289, publicado en el Periódico\nXXIV Legislatura, siendo Gobernadora Constitucional la C. Marina del Pilar Ávila Olmeda\n2021-2027;\nArtículo 154.- Fue reformado mediante Decreto No. 289, publicado en el Periódico\nOficial No. 55, Índice, de fecha 25 de septiembre de 2023, Tomo CXXX, expedido por la H.\nXXIV Legislatura, siendo Gobernadora Constitucional la C. Marina del Pilar Ávila Olmeda\n2021-2027;\nArtículo 156.- Fue reformado por Decreto No. 63, publicado en el Periódico Oficial No.\n35, de fecha 04 julio de 2014, Sección I, Tomo CXXI, expedido por la H. XXI Legislatura, siendo Gobernador Constitucional el C. Francisco Arturo Vega de Lamadrid 2013-2019;\nArtículo 159 BIS.- Fue adicionado por Decreto No. 63, publicado en el Periódico\nOficial No. 35, de fecha 04 julio de 2014, Sección I, Tomo CXXI, expedido por la H. XXI\nLegislatura, siendo Gobernador Constitucional el C. Francisco Arturo Vega de Lamadrid\n2013-2019;\nArtículo 160.- Fue reformado por Decreto No. 281, publicado en el Periódico Oficial\nLegislatura, siendo Gobernador Constitucional el C. Francisco Arturo Vega de Lamadrid\n2013-2019;\nArtículo 161.- Fue reformado mediante Decreto No. 289, publicado en el Periódico\nXXIV Legislatura, siendo Gobernadora Constitucional la C. Marina del Pilar Ávila Olmeda\n2021-2027;\nLey de Desarrollo Agropecuario del Estado de Baja California. Página 51\nARTÍCULO UNICO TRANSITORIO DEL DECRETO No. 513, POR EL QUE SE\nAPARTADO B) Y FRACCIÓN II DEL APARTADO C, TODAS DEL ARTÍCULO 8;\nFRACCIONES III Y IV DEL APARTADO B) DEL ARTÍCULO 10 Y SE REFORMA EL\nARTÍCULO 118, PUBLICADO EN EL PERIÓDICO OFICIAL No. 40, SECCION I, TOMO\nCXX, DE FECHA 13 DE SEPTIEMBRE DE 2013, EXPEDIDO POR LA H. XX\nLEGISLATURA, SIENDO GOBERNADOR CONSTITUCIONAL EL C. JOSÉ GUADALUPE\nOSUNA MILLÁN 2007-2013.\nARTÍCULO TRANSITORIO\nÚNICO.- Las presentes reformas entrarán en vigor al día siguiente de su publicación en el Periódico Oficial del Estado de Baja California.\nDADO en el Salón de Sesiones “Lic. Benito Juárez García” del H. Poder Legislativo del Estado de Baja California, en la Ciudad de Mexicali, B.C., a los dieciséis días del mes de agosto del año dos mil trece.\nDIP. GREGORIO CARRANZA HERNÁNDEZ\nPRESIDENTE\n(RÚBRICA)\nDIP. MARCO ANTONIO VIZCARRA CALDERÓN\nSECRETARIO\n(RÚBRICA)\nDE CONFORMIDAD CON LO DISPUESTO POR LA FRACCIÓN I DEL ARTÍCULO 49\nLey de Desarrollo Agropecuario del Estado de Baja California. Página 52\nMEXICALI, BAJA CALIFORNIA, A LOS VEINTISIETE DÍAS DEL MES DE AGOSTO\nDEL AÑO DOS MIL TRECE.\nJOSÉ GUADALUPE OSUNA MILLÁN\nGOBERNADOR DEL ESTADO\n(RÚBRICA)\nFRANCISCO ANTONIO GARCÍA BURGOS\nSECRETARIO GENERAL DE GOBIERNO\n(RÚBRICA)\nARTÍCULO UNICO TRANSITORIO DEL DECRETO No. 63, POR EL QUE SE\nREFORMAN LOS ARTÍCULOS 156 Y LA ADICIÓN DEL ARTÍCULO 159 BIS, PUBLICADO\nEN EL PERIÓDICO OFICIAL No. 35, SECCIÓN I, TOMO CXXI, DE FECHA 04 DE JULIOO\nDE 2014, EXPEDIDO POR LA H. XXI LEGISLATURA, SIENDO GOBERNADOR\nCONSTITUCIONAL EL C. FRANCISCO ARTURO VEDA DELAMADRID 2013-2019.\nARTÍCULOS TRANSITORIOS\nPRIMERO.- Las presentes reformas entrarán en vigor al día siguiente al de su publicación en el Periódico Oficial del Estado.\nSEGUNDO.- El artículo 159 bis por el que se crea el Fondo de Fomento para el\nDesarrollo Rural Sustentable, entrará en vigor el primero de enero de 2016, siempre que los\nPoderes Legislativo y Ejecutivo del Estado realicen las previsiones presupuestales que garanticen la viabilidad financiera de su instrumentación.\nTERCERO.- El Ejecutivo por conducto de la Secretaría, en un término no mayor a los\n30 días, posterior a la entrada en vigor del artículo 159 bis señalada en el transitorio anterior, deberá reglamentar la instrumentación y operación del Fondo de Fomento para el Desarrollo\nRural Sustentable. del Estado de Baja California, en la Ciudad de Mexicali, B.C., a los cinco días del mes de junio del año dos mil catorce.\nDIP. FELIPE DE JESÚS MAYORAL MAYORAL\nPRESIDENTE\n(RÚBRICA)\nDIP. GERARDO ÁLVAREZ HERNÁNDEZ\nSECRETARIO\nLey de Desarrollo Agropecuario del Estado de Baja California. Página 53\n(RÚBRICA)\nDE CONFORMIDAD CON LO DISPUESTO POR LA FRACCIÓN I DEL ARTÍCULO 49\nMEXICALI, BAJA CALIFORNIA, A LOS DIECISÉIS DÍAS DEL MES DE JUNIO DEL\nAÑO DOS MIL CATORCE.\nFRANCISCO ARTURO VEGA DE LAMADRID\nGOBERNADOR DEL ESTADO\n(RÚBRICA)\nFRANCISCO RUEDA GÓMEZ\nSECRETARIO GENERAL DE GOBIERNO\n(RÚBRICA)\nARTÍCULO TERCERO TRANSITORIO DEL DECRETO No. 66, POR EL QUE SE\nREFORMAN LOS ARTICULOS 2 y 21, PUBLICADO EN EL PERIÓDICO OFICIAL No. 39,\nSECCIÓN II, TOMO CXXI, DE FECHA 01 DE AGOSTO DE 2014, EXPEDIDO POR LA H.\nXXI LEGISLATURA, SIENDO GOBERNADOR CONSTITUCIONAL EL C. FRANCISCO\nARTURO VEGA DE LA MADRID 2013-2019.\nARTÍCULO TRANSITORIO\nÚNICO.- Las presentes reformas entrarán en vigor el día siguiente al de su publicación en el Periódico Oficial del Estado.\nDADO en el Salón de Sesiones “Lic. Benito Juárez García” del H. Poder Legislativo del Estado de Baja California, en la Ciudad de Mexicali, B.C., a los diecinueve días del mes de junio del año dos mil catorce.\nDIP. FELIPE DE JESÚS MAYORAL MAYORAL\nPRESIDENTE\n(RÚBRICA)\nDIP. GERARDO ÁLVAREZ HERNÁNDEZ\nSECRETARIO\n(RÚBRICA)\nDE CONFORMIDAD CON LO DISPUESTO POR LA FRACCIÓN I DEL ARTÍCULO 49\nMEXICALI, BAJA CALIFORNIA, A LOS VEINTITRES DÍAS DEL MES DE JULIO DEL\nAÑO DOS MIL CATORCE.\nLey de Desarrollo Agropecuario del Estado de Baja California. Página 54\nFRANCISCO ARTURO VEGA DE LAMADRID\nGOBERNADOR DEL ESTADO\n(RÚBRICA)\nGUILLERMO TREJO DOZAL\nSECRETARIO GENERAL DE GOBIERNO\n(RÚBRICA)\nARTÍCULO SEGUNDO TRANSITORIO DEL DECRETO No. 146, POR EL QUE SE\nAPRUEBAN LA REFORMA A LOS ARTICULOS 5, 6, 7, 8 Y 133, PUBLICADO EN EL\nPERIÓDICO OFICIAL No. 50, SECCIÓN III, TOMO CXXIV, DE FECHA 10 DE NOVIEMBRE\nDE 2017, EXPEDIDO POR LA H. XXII LEGISLATURA, SIENDO GOBERNADOR\nCONSTITUCIONAL EL C. FRANCISCO ARTURO VEGA DE LAMADRID 2013-2019.\nARTÍCULO TRANSITORIO\nÚNICO.- Las presentes reformas entrarán en vigor el día siguiente al de su publicación en el Periódico Oficial del Estado.\nDADO en el Salón de Sesiones “Lic. Benito Juárez García” del H. Poder Legislativo del Estado de Baja California, en la Ciudad de Mexicali, B.C., a los doce días del mes de octubre del año dos mil diecisiete.\nDIP. EDGAR BENJAMÍN GOMÉZ MACÍAS\nPRESIDENTE\n(RÚBRICA)\nDIP. EVA MARÍA VÁSQUEZ HERNÁNDEZ\nSECRETARIA\n(RÚBRICA)\nDE CONFORMIDAD CON LO DISPUESTO POR LA FRACCIÓN I DEL ARTÍCULO 49\nMEXICALI, BAJA CALIFORNIA, A LOS VEINTITRÉS DÍAS DE OCTUBRE DEL AÑO\nDOS MIL DIECISIETE.\nFRANCISCO ARTURO VEGA DE LAMADRID\nGOBERNADOR DEL ESTADO\n(RÚBRICA)\nFRANCISCO RUEDA GÓMEZ\nLey de Desarrollo Agropecuario del Estado de Baja California. Página 55\nSECRETARIO GENERAL DE GOBIERNO\n(RÚBRICA)\nARTÍCULO SEXTO TRANSITORIO DEL DECRETO No. 281, POR EL QUE SE\nREFORMA EL ARTÍCULO 160, PUBLICADO EN EL PERIÓDICO OFICIAL No. 55,\nH. XXII LEGISLATURA, SIENDO GOBERNADOR CONSTITUCIONAL EL C. FRANCISCO\nARTURO VEDA DE LAMADRID 2013-2019.\nARTÍCULOS TRANSITORIOS\nARTÍCULO PRIMERO.- El presente decreto entrará en vigor al día siguiente al de su publicación en el Periódico Oficial del Estado de Baja California.\nARTÍCULO SEGUNDO.- El valor diario de la Unidad de Medida y Actualización a la fecha de entrada en vigor, se tomará el valor publicado en el Diario Oficial de la Federación por el INEGI. El valor de la Unidad de Medida y Actualización a la fecha de entrada en vigor del presente Decreto, será producto de multiplicar el valor referido en el párrafo anterior por\n30.4. Por su parte, el valor anual será el producto de multiplicar el valor inicial mensual por\n12.\nARTÍCULO TERCERO.- Todas las menciones al salario mínimo como unidad de cuenta, índice, base, medida o referencia para determinar la cuantía de las obligaciones, sanciones, multas administrativas, conceptos de pago y montos de referencia, se entenderán referidas a la Unidad de Medida y Actualización. del Estado de Baja California, en la Ciudad de Mexicali, B.C., a los veinticinco días del mes de octubre del año dos mil dieciocho.\nDIP. ROCÍO LÓPEZ GOROSAVE\nPRESIDENTA\n(RÚBRICA)\nDIP. MÓNICA HERNÁNDEZ ÁLVAREZ\nSECRETARIA\n(RÚBRICA)\nLey de Desarrollo Agropecuario del Estado de Baja California. Página 56\nDE CONFORMIDAD CON LO DISPUESTO POR LA FRACCIÓN I DEL ARTÍCULO 49\nMEXICALI, BAJA CALIFORNIA, A LOS TREINTA DÍAS DEL MES DE NOVIEMBRE\nDEL AÑO DOS MIL DIECIOCHO.\nFRANCISCO ARTURO VEGA DE LAMADRID\nGOBERNADOR DEL ESTADO\n(RÚBRICA)\nFRANCISCO RUEDA GÓMEZ\nSECRETARIO GENERAL DE GOBIERNO\n(RÚBRICA)\nARTÍCULO ÚNICO TRANSITORIO DEL DECRETO No. 343, POR EL QUE SE\nREFORMA EL ARTÍCULO 55, PUBLICADO EN EL PERIÓDICO OFICIAL No. 30, SECCIÓN\nIII, TOMO CXXVI, DE FECHA 12 DE JULIO DE 2019, EXPEDIDO POR LA H. XXII\nLEGISLATURA, SIENDO GOBERNADOR CONSTITUCIONAL EL C. FRANCISCO ARTURO\nVEDA DE LAMADRID 2013-2019.\nARTÍCULOS TRANSITORIOS\nARTICULO PRIMERO. - La presente reforma entrará en vigor al día siguiente de su publicación en el Periódico Oficial del Estado.\nARTICULO SEGUNDO. - La Secretaría de Desarrollo Agropecuario, dentro de un plazo que no excederán de 60 días, contados a partir de la entrada en vigor de la presente reforma, realizará las adecuaciones administrativas pertinentes a efecto de implementar la presente reforma.\nARTICULO TERCERO. - La Secretaría de Desarrollo Agropecuario, entrada en vigor la presente reforma, realizará una campaña de difusión para la designación de beneficiario o sucesor en caso de fallecimiento de marca de herrar, tatuaje o señal de sangre, entre las organizaciones ganaderas, para efecto de contar con un padrón estatal de beneficiarios. del Estado de Baja California, en la Ciudad de Mexicali, B.C., a los diez días del mes de abril del año dos mil diecinueve.\nDIP. EDGAR BENJAMÍN GÓMEZ MACÍAS\nLey de Desarrollo Agropecuario del Estado de Baja California. Página 57\nPRESIDENTA\n(RÚBRICA)\nDIP. ROCÍO LÓPEZ GOROSAVE\nPROSECRETARIA\n(RÚBRICA)\nDE CONFORMIDAD CON LO DISPUESTO POR LA FRACCIÓN I DEL ARTÍCULO 49\nMEXICALI, BAJA CALIFORNIA, A LOS CINCO DÍAS DEL MES DE JULIO DEL AÑO\nDOS MIL DIECINUEVE.\nFRANCISCO ARTURO VEGA DE LAMADRID\nGOBERNADOR DEL ESTADO\n(RÚBRICA)\nFRANCISCO RUEDA GÓMEZ\nSECRETARIO GENERAL DE GOBIERNO\n(RÚBRICA)\nARTÍCULO ÚNICO TRANSITORIO DEL DECRETO No. 289, POR EL QUE SE\nAPRUEBA LA REFORMA A LOS ARTÍCULOS 4, 5, 6, 7, 8, 153, 154 Y 161, ASÍ COMO LA\nADICIÓN DE LOS ARTÍCULOS 114 BIS Y 114 TER; PUBLICADO EN EL PERIÓDICO\nOFICIAL No. 55, ÍNDICE, DE FECHA 25 DE SEPTIEMBRE DE 2023, TOMO CXXX,\nEXPEDIDO POR LA H. XXIV LEGISLATURA, SIENDO GOBERNADORA\nCONSTITUCIONAL LA C. MARINA DEL PILAR ÁVILA OLMEDA 2021–2027.\nARTÍCULO TRANSITORIO\nÚNICO.- La presente reforma entrará en vigor al día siguiente de su publicación en el\nPeriódico Oficial del Estado de Baja California.\nDADO en Sesión Ordinaria de la XXIV Legislatura en la Ciudad de Mexicali, B.C., a los siete días del mes de septiembre del año dos mil veintitrés.\nDIP. MANUEL GUERRERO LUNA\nPRESIDENTE\n(RÚBRICA)\nLey de Desarrollo Agropecuario del Estado de Baja California. Página 58\nDIP. DUNNIA MONTSERRAT MURILLO LÓPEZ\nSECRETARIA\n(RÚBRICA)\nDE CONFORMIDAD CON LO DISPUESTO POR LA FRACCION I DEL ARTÍCULO 49 DE\nCALIFORNIA, IMPRÍMASE Y PUBLÍQUESE.\nMEXICALI, BAJA CALIFORNIA, A LOS ONCE DÍAS DEL MES DE SEPTIEMBRE DEL AÑO\nDOS MIL VEINTITRÉS.\nMARINA DEL PILAR ÁVILA OLMEDA\nGOBERNADORA DEL ESTADO\nDE BAJA CALIFORNIA\n(RÚBRICA)\nCATALINO ZAVALA MÁRQUEZ\nSECRETARIO GENERAL DE GOBIERNO\nDEL ESTADO DE BAJA CALIFORNIA\n(RÚBRICA)\nARTÍCULO ÚNICO TRANSITORIO DEL DECRETO No. 455, POR EL QUE SE\nAPRUEBAN LAS REFORMAS A LOS ARTÍCULOS 5, 13 Y LA ADICIÓN DE LOS\nARTÍCULOS 35 TER Y 35 QUARTER; PUBLICADO EN EL PERIÓDICO OFICIAL No. 40,\nÍNDICE, DE FECHA 16 DE AGOSTO DE 2024, TOMO CXXXI, EXPEDIDO POR LA H. XXIV\nLEGISLATURA, SIENDO GOBERNADORA CONSTITUCIONAL LA C. MARINA DEL PILAR\nÁVILA OLMEDA 2021-2027.\nTRANSITORIOS\nÚNICO.- La presente reforma entrara en vigor al día siguiente de su publicación en el\nPeriódico Oficial del estado de Baja California.\nDADO en Sesión Ordinaria de la XXIV Legislatura en la Ciudad de Mexicali, B.C., a los veinticinco días del mes de julio del año dos mil veinticuatro.\nDIP. RAMÓN VÁZQUEZ VALADEZ\nPRESIDENTE\n(RÚBRICA)\nDIP. MANUEL GUERRERO LUNA\nSECRETARIO\n(RÚBRICA)\nLey de Desarrollo Agropecuario del Estado de Baja California. Página 59\nDE CONFORMIDAD CON LO DISPUESTO POR LA FRACCIÓN I DEL ARTÍCULO 49\nCALIFORNIA, IMPRÍMASE Y PUBLÍQUESE.\nMEXICALI, BAJA CALIFORNIA, A LOS TREINTA Y UN DÍAS DEL MES DE JULIO\nDEL AÑO DOS MIL VEINTICUATRO.\nMARINA DEL PILAR ÁVILA OLMEDA\nGOBERNADORA DEL ESTADO\nDE BAJA CALIFORNIA\n(RÚBRICA)\nALFREDO ÁLVAREZ CÁRDENAS\nSECRETARIO GENERAL DE GOBIERNO\nDEL ESTADO DE BAJA CALIFORNIA\n(RÚBRICA)\nARTÍCULO ÚNICO TRANSITORIO DEL DECRETO No. 97, POR EL QUE SE\nAPRUEBAN LAS REFORMAS A LOS ARTÍCULOS 5 Y 96; PUBLICADO EN EL\nPERIÓDICO OFICIAL No. 37, ÍNDICE, 20 DE JUNIO DE 2025; EXPEDIDO POR LA H. XXV\nLEGISLATURA, SIENDO GOBERNADORA CONSTITUCIONAL LA C. MARINA DEL PILAR\nÁVILA OLMEDA 2021-2027.\nTRANSITORIO\nÚNICO.- La presente reforma entrará en vigor al día siguiente de su publicación en el\nPeriódico Oficial del Estado de Baja California.\nDADO en Sesión Ordinaria de la XXV Legislatura en la Ciudad de Mexicali, B.C., a los cinco días del mes de junio del año dos mil veinticinco.\nDIP. MICHELLE ALEJANDRA TEJEDA MEDINA\nPRESIDENTA\n(RÚBRICA)\nDIP. NORMA ANGELICA PEÑALOZA ESCOBEDO\nSECRETARIA\n(RÚBRICA)\nDE CONFORMIDAD CON LO DISPUESTO POR LA FRACCIÓN I DEL ARTÍCULO 49\nCALIFORNIA, IMPRÍMASE Y PUBLÍQUESE.\nMEXICALI, BAJA CALIFORNIA, A LOS 6 DÍAS DEL MES DE JUNIO DEL AÑO DOS\nMIL VEINTICINCO.\nLey de Desarrollo Agropecuario del Estado de Baja California. Página 60\nMARINA DEL PILAR ÁVILA OLMEDA\nGOBERNADORA DEL ESTADO\nDE BAJA CALIFORNIA\n(RÚBRICA)\nALFREDO ÁLVAREZ CÁRDENAS\nSECRETARIO GENERAL DE GOBIERNO\nDEL ESTADO DE BAJA CALIFORNIA\n(RÚBRICA)\nARTÍCULO ÚNICO TRANSITORIO DEL DECRETO No. 147, POR EL QUE SE\nAPRUEBAN LAS REFORMAS A LOS ARTÍCULOS 1, 12 Y 15 Y LA ADICIÓN DEL\nARTÍCULO 13 BIS; PUBLICADO EN EL PERIÓDICO OFICIAL No. 61, ÍNDICE, 10 DE\nOCTUBRE DE 2025; EXPEDIDO POR LA H. XXV LEGISLATURA, SIENDO\nGOBERNADORA CONSTITUCIONAL LA C. MARINA DEL PILAR ÁVILA OLMEDA 2021-\n2027.\nTRANSITORIO\nÚNICO.- La presente reforma entrará en vigor al día siguiente al de su publicación en el\nPeriódico Oficial del Estado de Baja California.\nDADO en Sesión Ordinaria de la XXV Legislatura en la Ciudad de Mexicali, B.C., a los veinticinco días del mes de septiembre del año dos mil veinticinco.\nDIP. JAIME EDUCARDO CANTÓN ROCHA\nPRESIDENTA\n(RÚBRICA)\nDIP. MICHELLE ALEJANDRA TEJEDA MEDINA\nSECRETARIA\n(RÚBRICA)\nDE CONFORMIDAD CON LO DISPUESTO POR LA FRACCIÓN I DEL ARTÍCULO 49\nCALIFORNIA, IMPRÍMASE Y PUBLÍQUESE.\nMEXICALI, BAJA CALIFORNIA, A LOS 26 DÍAS DEL MES DE SEPTIEMBRE DEL\nAÑO DOS MIL VEINTICINCO.\nMARINA DEL PILAR ÁVILA OLMEDA\nGOBERNADORA DEL ESTADO\nDE BAJA CALIFORNIA\n(RÚBRICA)\nLey de Desarrollo Agropecuario del Estado de Baja California. Página 61\nALFREDO ÁLVAREZ CÁRDENAS\nSECRETARIO GENERAL DE GOBIERNO\nDEL ESTADO DE BAJA CALIFORNIA\n(RÚBRICA)\nLey de Desarrollo Agropecuario del Estado de Baja California. Página 62",
  "ordenamiento": "REGLAMENTO",
  "jurisdiccion": "BAJA CALIFORNIA",
  "fuente_oficial": "Periódico Oficial",
  "FECHA PER OFIC": "2025/10/10",
  "ESTATUS": "VIGENTE",
  "TOMO": "TOMO_VII",
  "URL": "https://www.congresobc.gob.mx/Documentos/ProcesoParlamentario/Leyes/TOMO_VII/20251010_LEYDESAGROPECUARIO.PDF",
  "es_escaneado": false,
  "tiene_tablas": false,
  "materia": [
    "ambiental",
    "urbanismo",
    "infraestructura"
  ]
}