{
  "titulo": "Ley DE INGRESOS DEL MUNICIPIO DE TIJUANA, BAJA CALIFORNIA PARA EL EJERCICIO FISCAL DEL 2025",
  "Contenido": "BAJA CALIFORNIA, EN USO DE LAS FACULTADES QUE LE CONFIERE EL ARTÍCULO\nSOBERANO DE BAJA CALIFORNIA, TIENE A BIEN APROBAR LA SIGUIENTE:\nLEY DE INGRESOS DEL\nMUNICIPIO DE TIJUANA, BAJA CALIFORNIA\nPARA EL EJERCICIO FISCAL DEL 2025\nÍNDICE GENERAL\nTÍTULO PRIMERO GENERALIDADES DE LOS INGRESOS\nTÍTULO SEGUNDO IMPUESTOS\nCAPÍTULO I IMPUESTO PREDIAL\nCAPÍTULO II IMPUESTO SOBRE ADQUISICIÓN DE INMUEBLES\nCAPÍTULO III IMPUESTO SOBRE ASISTENCIA A DIVERSIONES,\nJUEGOS PERMITIDOS Y ESPECTÁCULOS PÚBLICOS\nCAPÍTULO IV IMPUESTO PARA EL MANTENIMIENTO Y CONSERVACIÓN\nDE LAS VÍAS PÚBLICAS\nCAPÍTULO V IMPUESTO DE PLUSVALÍA\nA FORTALECER LA SEGURIDAD PÚBLICA Y SOCIAL\nCON APUESTAS O SORTEOS\nTÍTULO TERCERO DERECHOS\nVERIFICACIÓN MUNICIPAL\nPREVENCIÓN, CONTROL Y SANIDAD.\nMUNICIPAL\nMUNICIPALES\nCAPÍTULO VIII QUE PRESTA LA DIRECCIÓN MUNICIPAL DE\nADMINISTRACIÓN DE LA VÍA PÚBLICA\nCAPÍTULO IX QUE PRESTA LA DIRECCIÓN DE ADMINISTRACIÓN\nURBANA\nCAPÍTULO X QUE PRESTA LA DIRECCIÓN DE CATASTRO\nCAPÍTULO XI QUE PRESTA LA DIRECCIÓN DE PROTECCIÓN AL\nAMBIENTE\nCAPÍTULO XII QUE PRESTA LA DIRECCIÓN DE OBRAS E\nINFRAESTRUCTURA URBANA MUNICIPAL\nY VIGILANCIA AUXILIAR\nECONÓMICO\nCAPÍTULO XIX DERECHOS POR SERVICIOS DE RECEPCIÓN,\nSÓLIDOS E INDUSTRIALES\nCAPÍTULO XX DERECHOS POR EXPEDICIÓN DE CERTIFICADOS,\nTÍTULOS Y COPIAS DE DOCUMENTOS\nTÍTULO CUARTO INGRESOS POR VENTA DE BIENES, PRESTACIÓN DE\nSERVICIOS Y OTROS INGRESOS\nCAPÍTULO I SERVICIOS QUE PRESTAN ORGANISMOS\nPARAMUNICIPALES\nCAPÍTULO II QUE PRESTA EL SISTEMA PARA EL DESARROLLO\nINTEGRAL DE LA FAMILIA\nCAPÍTULO III QUE PRESTA EL INSTITUTO MUNICIPAL DEL DEPORTE\nDE TIJUANA\nCAPÍTULO IV QUE PRESTA EL INSTITUTO METROPOLITANO DE\nPLANEACIÓN\nCULTURA\nTEMÁTICOS DE TIJUANA\nADICCIONES\nDE TIJUANA\nDE TIJUANA\nOPERACIÓN DEL SISTEMA DE TRANSPORTE MASIVO\nURBANO DE PASAJEROS DE TIJUANA\nCAPÍTULO XII ORGANISMOS DESCENTRALIZADOS, PARAMUNICIPALES\nY/O FIDEICOMISOS\nTÍTULO QUINTO PRODUCTOS\nCAPÍTULO I CONTRAPRESTACIONES DE CONCESIONES, EXPLOTACIÓN\nO ARRENDAMIENTO DE BIENES MUEBLES E INMUEBLES\nPROPIEDAD DEL GOBIERNO MUNICIPAL\nCAPÍTULO II SUMINISTRO DE FORMAS DIVERSAS PARA TRÁMITES\nADMINISTRATIVOS\nCAPÍTULO III OTRAS ACTIVIDADES DEL GOBIERNO MUNICIPAL, QUE\nNO CORRESPONDAN A SUS FUNCIONES PROPIAS DE\nDERECHO PÚBLICO\nCAPÍTULO IV DEL PISO\nTÍTULO SEXTO APROVECHAMIENTOS\nCAPÍTULO I RECARGOS\nCAPÍTULO III GASTOS DE EJECUCIÓN\nCAPÍTULO IV MULTAS\nCAPÍTULO V REINTEGROS E INDEMNIZACIONES\nCAPÍTULO VI DONACIONES, CESIONES, HERENCIAS, LEGADOS Y\nOTROS A FAVOR DEL MUNICIPIO Y SUS ENTIDADES\nDESCENTRALIZADOS PARAMUNICIPALES, ORGANISMOS\nDE PARTICIPACIÓN MUNICIPAL, EMPRESAS\nMUNICIPALES, EMPRESAS PÚBLICO-PRIVADAS Y\nFIDEICOMISOS PÚBLICOS MUNICIPALES\nCAPÍTULO VII POR EL OTORGAMIENTO Y USUFRUCTO DE DERECHOS,\nPERMISOS, LICENCIAS, AUTORIZACIONES Y/O\nCONCESIONES EMITIDAS POR EL AYUNTAMIENTO A\nFAVOR DE PARTICULARES, CUYA EXPLOTACIÓN AL\nPÚBLICO SE REALICE POR TERCEROS\nVIDA\nCAPÍTULO IX CAUCIONES, FIANZAS Y DEPÓSITOS CUYA PÉRDIDA SE\nDECLARE POR RESOLUCIÓN FIRME\nCAPÍTULO X INGRESOS POR VENTA DE BIENES PATRIMONIALES\nTÍTULO SÉPTIMO PARTICIPACIONES, APORTACIONES, CONVENIOS,\nINCENTIVOS DERIVADOS DE LA COLABORACIÓN FISCAL\nY FONDOS DISTINTOS DE APORTACIÓN\nCAPÍTULO I PARTICIPACIONES FEDERALES\nCAPÍTULO II PARTICIPACIONES ESTATALES\nCOORDINACIÓN FISCAL\nCAPÍTULO IV APORTACIONES ESTATALES\nFEDERACIÓN PARA OBRAS Y SERVICIOS PÚBLICOS O\nPROGRAMAS ESPECIALES\nCAPÍTULO VI CONVENIOS\nTÍTULO OCTAVO TRANSFERENCIAS, ASIGNACIONES, SUBSIDIOS Y\nSUBVENCIONES, Y PENSIONES Y JUBILACIONES\nCAPÍTULO I CRÉDITOS OTORGADOS AL MUNICIPIO\nCAPÍTULO II OTROS\nTÍTULO DECIMO DISPOSICIONES GENERALES\nCAPÍTULO ÚNICO\nTRANSITORIOS\nTÍTULO PRIMERO\nGENERALIDADES DE LOS INGRESOS\nARTÍCULO 1.-Los ingresos del Municipio de Tijuana, Estado de Baja\nCalifornia, durante el ejercicio fiscal comprendido del primero de enero al treinta y uno de diciembre del año 2025, serán los que se obtengan por la recaudación de los conceptos siguientes:\nCONCEPTOS DE INGRESOS\nINGRESO\nRUBRO / TIPO / CONCEPTO\nESTIMADO 2025\n1 IMPUESTOS 2,936,572,809\n12 IMPUESTO SOBRE PATRIMONIO 2,554,002,682\n1201 IMPUESTO PREDIAL 1,340,821,824\nIMPUESTO SOBRE ADQUISICIÓN DE\n1202 1,213,180,857\nINMUEBLES\n1203 IMPUESTO DE PLUSVALÍA. IMPUESTO SOBRE PRODUCCIÓN, CONSUMO Y\n13 72,221,853\nLAS TRANSACCIONES\nASISTENCIA, DIVERSIONES, 1301 16,284,946\nJUEGOS Y ESPECTÁCULOS\nACTIVIDADES DE JUEGOS CON\n1302 55,936,907\nAPUESTAS O SORTEOS\n17 ACCESORIOS 88,184,643\n1701 ACCESORIOS DE IMPUESTOS 88,184,643\n18 OTROS IMPUESTOS 222,163,632\nIMP. FOMENTO DEPORTIVO Y\n1801 3,060,468\nEDUCACIONAL\n1802 IMP. FOMENTO TURÍSTICO Y DIF 578,184\nIMP. APOYO ORG. GUB. SIN FIN\n1803 5,998,414\nLUCRO\nIMP. MANT. Y CONSERVACIÓN\n1804 212,526,566\nVÍAS PÚBLICAS\nCUOTAS Y APORTACIONES DE SEGURIDAD\nSOCIAL\n3 CONTRIBUCIONES DE MEJORAS 4 DERECHOS 1,717,207,066\n43 DERECHOS POR PRESTACIÓN DE SERVICIOS 1,703,053,409\n4309 DIRECCIÓN DE REGISTRO CIVIL 59,825,975\nSECRETARÍA DE SEGURIDAD Y\n4312 PROTECCIÓN CIUDADANA 89,536,166\nMUNICIPAL\nDIRECCIÓN DE ADMINISTRACIÓN\n4319 413,031,202\nURBANA\n4320 DIRECCIÓN DE CATASTRO 38,953,743\nDIRECCIÓN DE PROTECCIÓN AL\n4321 23,086,599\nAMBIENTE\n4322 DIRECCIÓN DE BOMBEROS 104,908,332\nDIRECCIÓN DE BEBIDAS\n4323 126,689,771\nALCOHÓLICAS\nDIRECCIÓN MUNICIPAL DE\n4324 32,154,183\nPREVENCIÓN, CONTROL Y SANIDAD\nDIRECCIÓN MUNICIPAL DE\n4325 ADMINISTRACIÓN DE LA VÍA 11,745\nPÚBLICA\n4326 DIRECCIÓN GENERAL DE GOBIERNO 4,917,085\nDIRECCIÓN DE RECAUDACIÓN\n4327 61,752,538\nMUNICIPAL\nDIRECCIÓN DE INSPECCIÓN Y\n4328 41,441,720\nVERIFICACIÓN MUNICIPAL\nDIRECCIÓN DE SERVICIOS\n4332 477,268,934\nPÚBLICOS MUNICIPALES\n4333 DIRECCIÓN DE PROTECCIÓN CIVIL 4,727,029\n4334 224,277,801\nECONÓMICO\nDIRECCIÓN DE OBRAS E\n4335 470,585\nINFRAESTRUCTURA URBANA\n4336 OFICIALIA MAYOR 44 OTROS DERECHOS 11,689,043\n4401 OTROS DERECHOS 11,689,043\n45 ACCESORIOS 2,464,615\n4501 ACCESORIOS DE DERECHOS 2,464,615\n5 PRODUCTOS 72,106,776\n51 PRODUCTOS DE TIPO CORRIENTE 72,106,776\n5101 PRODUCTOS 72,106,776\n6 APROVECHAMIENTOS 169,302,361\n61 APROVECHAMIENTOS DE TIPO CORRIENTE 168,406,051\n6101 MULTAS 161,975,271\n6102 REINTEGRO E INDEMINIZACIONES 3,881,483\n6103 DONACIONES 2,151,251\n6104 OTROS APROVECHAMIENTOS 398,046\n62 APROVECHAMIENTOS PATRIMONIALES 896,310\nENAJENACIÓN DE BIENES MUEBLES\n6202 548,793\nE INMUEBLES\nARRENDAMIENTO O EXPLOTACIÓN\n6203 347,516\nDE BIENES INMUEBLES\n63 ACCESORIOS DE APROVECHAMIENTOS ACCESORIOS DE\n6301 APROVECHAMIENTOS\nINGRESOS POR VENTA DE BIENES Y\n7 104,762,807\nSERVICIOS\nINGRESOS PARAMUNICIPALES Y\n73 104,762,807\nFIDEICOMISOS\nSISTEMA PARA EL DESARROLLO\n7301 15,913,020\nINTEGRAL DE LA FAMILIA.\nINSTITUTO MUNICIPAL DEL\n7302 24,698,525\nDEPORTE DE TIJUANA.\nINSTITUTO METROPOLITANO DE\n7303 14,000,000\nPLANEACIÓN.\nINSTITUTO MUNICIPAL DE ARTE Y\n7304 9,000,000\nCULTURA.\nSISTEMA MUNICIPAL DE PARQUES\n7305 22,673,690\nTEMÁTICOS DE TIJUANA.\nINSTITUTO MUNICIPAL CONTRA\n7306 300,000\nLAS ADICCIONES.\nORGANISMO MUNICIPAL PARA LA\nOPERACIÓN DEL SISTEMA DE\n7307 1,600,000\nTRANSPORTE MASIVO URBANO DE\nPASAJEROS DE TIJUANA.\nFIDEICOMISO PROMOTORA\n7308 12,643,572\nMUNICIPAL DE TIJUANA\nCOMITÉ DE TURISMO Y\n7309 3,934,000\nCONVENCIONES DE TIJUANA.\nPARTICIPACIONES, APORTACIONES,\nCONVENIOS, INCENTIVOS DERIVADOS DE LA\n8 7,523,017,300\nCOLABORACIÓN FISCAL Y FONDOS DISTINTOS\nDE APORTACIONES\nPARTICIPACIONES FEDERALES Y\n81 5,326,512,974\nESTATALES\nPARTICIPACIÓN IMPUESTO\n8101 112,773,717\nADUANAL 0.136 DE RFP\nFONDO DE FISCALIZACIÓN Y\n8102 184,626,333\nRECAUDACIÓN\nIMP S/VENTA FINAL GASOLINA Y\n8103 123,807,436\nDIESEL\nFONDO GENERAL DE\n8104\nPARTICIPACIONES 2,815,132,943\n8105 PARTICIPACIONES ISR 411,806,732\nIMP ESPECIALES S/PRODUCCIÓN Y\n8106 108,145,662\nSERVICIOS IEPS\nFONDO ESTAB D LOS ING ENT FED\n8107 (FEIEF)\n8108 FONDO DE FOMENTO MUNICIPAL 476,253,444\nINTERÉS POR CARGAS\n8110 FINANCIERAS\n8151 FONDO COMPENSATORIO PARTICIPACIÓN IMP S/BEB.\n8152 16,438,090\nALCOH-TABAC\nPARTICIPACIÓN EN IMPUESTOS\n8153 328,512,812\nDEL EDO\n8154 FONDO COMPENSATORIO (ISSH) IMPUESTOS SOBRE TENENCIA\n8155 29,808,964\nESTATAL\n8156 IMPUESTO SOBRE HOSPEDAJE 75,124,980\nIMPUESTO SOBRE REMUNERACIONES\n8157 644,081,859\nAL PERSONAL\n82 APORTACIONES 2,101,117,808\nFONDO APORTACIONES\n8201 319,850,356\nINFRAESTRUCTURA SOCIAL\nFONDO APORTACIONES\n8202 1,781,267,452\nFORTALECIMIENTO MPIOS-D.F.\n83 CONVENIOS 351,763\n8301 FONDO APORTACIONES ZOFEMAT. 351,763\nINCENTIVOS DERIVADOS DE LA\n84 95,034,756\nCOLABORACIÓN FISCAL\n8401 RECARGOS ZOFEMAT 35,718\n8402 MULTAS ZOFEMAT 86,602\n8403 MULTAS FEDERALES 714,488\n8404 USO Y GOCE ZOFEMAT 1,401,251\nIMPUESTO SOBRE AUTOS NUEVOS\n8405 54,769,937\n(ISAN)\n8406 IMPUESTO SOBRE TENENCIA 13,560\n8407 COMPENSACIÓN DEL ISAN 7,715,445\n8408 INTERESES MULTAS FEDERALES ISR ENAJENACIÓN DE BIENES\n8409 30,297,757\nINMUEBLES\n85 FONDOS DISTINTOS DE APORTACIONES TRANSFERENCIAS, ASIGNACIONES, SUBSIDIOS\n9 Y SUBVENCIONES, Y PENSIONES Y JUBILACIONES\n0 INGRESOS DERIVADOS DE FINANCIAMIENTOS TOTAL DE INGRESOS 12,522,969,121\nARTÍCULO 2.-El Ejecutivo Municipal dentro de sus facultades que se refiere esta Ley, a personas discapacitadas, de extrema pobreza, que vivan en condiciones infrahumanas o personas mayores a 60 años.\nAsimismo, podrá eximir el pago de derechos, a personas físicas o morales que promuevan la generación de nuevos empleos, contraten a personas con discapacidad, así como a las que impulsen el desarrollo económico, deporte, social y cultural del Municipio, en términos de las disposiciones aplicables. otorgamiento de subsidios, que se establezcan en la reglamentación o normatividad.\nARTÍCULO 3.-El pago de los derechos que establece esta Ley deberá hacerse por el contribuyente, previamente a la prestación de los servicios, salvo los casos en que expresamente se señale otra época de pago.\nCuando no se compruebe que el pago de los derechos se ha efectuado previamente a la prestación del servicio y se trate de derechos que deban pagarse por anticipado, el servicio no se proporcionará.\nEn caso de que el pago de derechos deba efectuarse con posterioridad a la prestación del servicio por tratarse de servicios continuos o porque así se establezca en esta Ley, dejará de prestarse si no se efectúa dicho pago.\nComo parte del Procedimiento Administrativo de Ejecución y con el objeto de cubrir el importe del crédito fiscal adeudado, las giro, así como ordenar que se practique intervención a la caja o cajas de dichos establecimientos, y retener los ingresos diarios, con antelación a la intervención del establecimiento. Las sumas diariamente al crédito fiscal adeudado.\nTÍTULO SEGUNDO\nIMPUESTOS\nCAPÍTULO I\nIMPUESTO PREDIAL\nARTÍCULO 4.-El impuesto predial, se causará de acuerdo a lo que se\nInmobiliario, ambas del Estado de Baja California, así como en el\nCalifornia para el municipio de Tijuana, Baja California, de conformidad con la Tabla de Valores Catastrales Unitarios, elaborada por el Consejo Municipal del Catastro Inmobiliario de\nTijuana, y aprobadas por el H. Congreso del Estado de Baja\nCalifornia.\nEl monto del impuesto predial se determinará multiplicando los\nValores Catastrales Unitarios de Terreno y Construcción, según corresponda, por el número de metros cuadrados que corresponda a las superficies de terreno y de construcción de cada predio.\nPara efectos del cálculo del impuesto predial se obtendrá del valor catastral de los inmuebles sobre los cuales se cause dicho impuesto, aplicando el valor unitario de terreno que le corresponda adicionado con el producto que resulte de aplicar un 100% (cien por ciento) del valor unitario de construcción que le corresponda municipio de Tijuana. Al resultado obtenido se le aplicarán las siguientes:\nTASAS\nI.-La tasa general aplicable a todos los predios ubicados dentro del municipio de Tijuana será la siguiente: 4.29 AL MILLAR\nII.-El impuesto predial se causará a partir de la inscripción en el padrón catastral del año fiscal que corresponda. En los casos reportados en el registro catastral, se hará el cobro por cinco referidas, salvo que el interesado pruebe que la omisión de registro o de presentación de aviso de modificación, data de fecha posterior.\nTratándose de construcciones no manifestadas, si no se pudiera fijar con precisión la fecha desde la cual se omitió el aviso correspondiente, se hará el cobro del impuesto por los cinco años anteriores a la fecha en que se tenga conocimiento de la ocultación, salvo que el interesado pruebe que la omisión data de fecha posterior.\nCorresponde a los contribuyentes, determinar las diferencias de construcción a manifestar respecto a lo señalado en el párrafo anterior y en caso de no realizarlo, la autoridad fiscal lo determinará y aplicará directamente al predio de que se trate, dando aviso de este hecho al contribuyente.\nIII.- El derecho a cubrir el impuesto predial a la tasa que sea solicitada por el contribuyente, surtirá sus efectos a partir del ejercicio fiscal en el que se dé la aplicación de la tasa condiciones que sirvieron para su otorgamiento.\nLos sujetos beneficiados con la tasa referida, deberán manifestar tasa, independientemente de que en todo tiempo podrá la Tesorería\nMunicipal, realizar las investigaciones necesarias para tal efecto y modificar en su caso la tasa aplicable, evento en el cual se legales aplicables, a partir del momento en que la autoridad determine que se dejaron de llenar los requisitos de Ley. este artículo, por los predios que a continuación se enlistan se aplicable al valor catastral de los inmuebles correspondientes:\n• Predios urbanos destinados al uso industrial 4.10 al millar.\n• Predios baldíos 3.70 al millar, excepto los casos en que, previa inspección que realice la autoridad, se demuestre que el inmueble se encuentra destinado a estacionamiento de algún giro comercial.\n• Predios rústicos o rurales y suburbanos 3.70 al millar.\nLas definiciones de estado de conservación y elementos de calidad relacionadas con el impuesto predial serán las que se especifican en la Tabla de Valores Catastrales Unitarios, Base del Impuesto\nPredial, del Municipio de Tijuana, Baja California, para el\nEjercicio Fiscal 2025, la cual aprobadas por el Congreso del Estado forma parte de esta Ley.\nARTÍCULO 5.-La contribución por concepto del impuesto predial anual, se regirá en base a la Tabla de Valores Catastrales\nUnitarios, aprobados por el H. Congreso del Estado de Baja\nCalifornia, y no podrá ser menor a 3.99 veces la unidad de medida y actualización (UMA) vigente.\nEl impuesto predial deberá cubrirse anualmente del 01 de enero al\n31 de marzo del año en curso, ya que, si se paga fuera de este plazo, causará recargos y, en su caso, multas.\nARTÍCULO 6.-Los contribuyentes que estén obligados a cubrir al\n(INFONAVIT), créditos hipotecarios que éste les hubiere otorgado, podrán pagar el impuesto predial por conducto del INFONAVIT, en los términos dispuestos en este artículo y en su caso, por lo aplicables, siempre y cuando el municipio tenga celebrado convenio contribuyentes, en su carácter de derechohabientes del INFONAVIT, autoricen al citado instituto para ordenar a su respectivo patrón, predial por orden y cuenta suya.\nAsimismo, los contribuyentes que cumplan con lo señalado en los para el efecto, podrán pagar el citado impuesto de manera cuatrimestral mediante la retención o descuento que lleven a cabo las instituciones o empresas públicas o privadas autorizadas para tal efecto por la autoridad fiscal.\nEn los supuestos anteriores, los pagos del impuesto predial se efectuarán de manera cuatrimestral en tres pagos iguales durante el ejercicio fiscal de que se trate. El importe de cada pago cuatrimestral resultará de dividir entre tres el monto que resulte de la determinación del impuesto anual en términos de lo dispuesto por la Ley de Hacienda Municipal del Estado de Baja California.\nPara los efectos de este artículo, el primero de los cuatrimestres iniciará con el primer mes del ejercicio fiscal.\nEn estos supuestos, los pagos corresponderá realizarlos a las instituciones o empresas señaladas en los párrafos anteriores, a más tardar el día 17 del mes inmediato posterior al cuatrimestre correspondiente; debiendo enterarlo a su vez a la Hacienda\nMunicipal en términos de lo establecido en el convenio de colaboración que, para estos efectos, se tenga suscrito. anteriores deberán manifestar a la Tesorería Municipal, tal intención, igualmente deberán presentar los avisos que se indiquen en las reglas de carácter general que emita la autoridad fiscal.\nEn caso de que, por cualquier motivo, después de transcurridos los predial y/o sus accesorios, éstos deberán cubrirse en su totalidad que se causaron la contribución y sus accesorios.\nAdicional a lo anterior, los contribuyentes del impuesto predial titular, expedida por alguna institución integrante del sistema financiero mexicano. Los contribuyentes que pretendan cumplir con indicados en este párrafo deberán manifestar a la Tesorería\nMunicipal, tal intención, durante el mes de enero y febrero.\nIgualmente deberán presentar los avisos que se indiquen en las reglas de carácter general que emita la autoridad fiscal.\nEn cualquiera de las opciones de pago del impuesto predial, previstas en el presente artículo, no será procedente aplicar los beneficios de descuento por pronto pago, establecidos en el\nArtículo 7 de la presente Ley.\nLos pagos bimestrales o cuatrimestrales, según corresponda, que dejen de enterarse a la Recaudación de Rentas Municipal, serán exigibles y causarán recargos a partir de que debieron realizarse en los términos del presente artículo.\nEl presente artículo solo será aplicable, durante la vigencia del convenio de colaboración con INFONAVIT.\nARTÍCULO 7.-Los contribuyentes que paguen en una sola exhibición el impuesto predial durante los primeros tres meses del año, gozarán de la reducción de un 12% (doce por ciento) en el mes de enero, un 10% (diez por ciento) en el mes de febrero y un 5% (cinco por ciento) en el mes de marzo, del monto del impuesto total anual.\nLos propietarios de predios urbanos baldíos o no edificados, que expide la Dirección de Administración Urbana, gozarán de hasta un\n50% (cincuenta por ciento) de descuento en el pago del impuesto liquidación o pago, siempre y cuando no hayan recibido el beneficio a que se refiere el párrafo anterior. El descuento que otorga el forma bimestral. encuentran establecidas en el Artículo 32 de esta Ley.\nEl pago del impuesto predial, incluyendo las sobretasas correspondientes, tendrá una exención de un 3% (tres por ciento) adicional a cualquier otro estímulo fiscal aplicable, para través del portal de internet del Municipio.\nCAPÍTULO II\nIMPUESTO SOBRE ADQUISICIÓN DE INMUEBLES\nARTÍCULO 8.-Este Impuesto se calculará aplicando la tarifa que a continuación se establece, sobre la base gravable que se determine de acuerdo a la Ley de Hacienda Municipal del Estado de Baja\nCalifornia:\nTasa marginal sobre inferior\n1 0.01 800,000.00 - 1.500%\n2 800,000.01 1,600,000.00 12,000.00 2.000%\n3 1,600,000.01 2,600,000.00 28,000.00 2.500%\n4 2,600,000.01 3,800,000.00 53,000.00 3.000%\n5 3,800,000.01 5,200,000.00 89,000.00 3.500%\n6 5,200,000.01 6,800,000.00 138,000.00 4.000%\n7 6,800,000.01 En adelante 202,000.00 4.500%\nPara el cálculo de este Impuesto, la base del mismo deberá ubicarse en el renglón que le corresponda de entre los límites del recuadro; se le aplicará la tasa marginal que le corresponda; al resultado se le sumará la cuota fija del mismo rango; y, el importe de dicha operación más las sobretasas establecidas en el presente artículo, será el Impuesto Sobre Adquisición de Inmuebles a pagar; lo anterior, conforme a la siguiente fórmula:\n((BI-LI) *T) +CF+ST = Impuesto Sobre Adquisición de Inmuebles a pagar\nEn donde:\n• BI= Base del Impuesto\n• LI= Límite Inferior correspondiente\n• T= Tasa marginal sobre excedente del Límite Inferior correspondiente\n• CF= Cuota Fija correspondiente\n• ST= Sobretasa\nLa tarifa establecida en el presente artículo es aplicable para actos generados a partir del ejercicio fiscal 2021 para la determinación del Impuesto Sobre Adquisición de Inmuebles, respecto de los bienes inmuebles ubicados en el Municipio de\nTijuana, por lo que, en estos supuestos, no serán aplicables las deducciones ni la tasa que se encuentran establecidas en las fracciones III y IV del artículo 75-Bis B, de la Ley de Hacienda\nMunicipal del Estado de Baja California respectivamente.\nPor lo tanto, cualquier disposición emitida con anterioridad que se oponga a la presente disposición, no surtirá efecto alguno en el municipio de Tijuana, en tanto se encuentre vigente la misma.\nCalifornia (INDIVI), con el Instituto Nacional del Suelo\nSustentable (INSUS), pagarán el equivalente a dos unidades de medida y actualización (UMA) vigente siempre y cuando el predio sea destinado a casa habitación, y siempre que la suma de los predios adquiridos por una persona no supere los 250.00 M², en los fiscal actual.\nCentralizada y Descentralizada, quedará en valor nulo siempre y adquiridos por una persona no supere los 250.00 M².\nEs obligación de las personas físicas y morales que enajenen bienes inmuebles, efectuar el pago en la Recaudación de Rentas Municipal, dentro de los plazos que se establecen en el artículo 75 BIS B, de la Ley de Hacienda Municipal del Estado de Baja California.\nSerán responsables solidarios en el Impuesto Sobre Adquisición de\nInmuebles, los notarios y corredores públicos, de las operaciones y actos por las que se causen los mismos, cuando autoricen actos o contratos de adquisición de propiedad de inmuebles o de derechos reales o posesorios, inscriban o realicen anotaciones de escrituras, actos o contratos sin que el causante compruebe que se han cubierto estas contribuciones; consistiendo dicha responsabilidad solidaria, en el pago del importe total de las contribuciones mencionadas que indebidamente dejaron de pagar los contribuyentes.\nAsimismo, tendrán la misma responsabilidad solidaria sobre el\nImpuesto Sobre Adquisición de Inmuebles, los enajenantes de correspondiente, de las operaciones de Transmisión de Dominio que realicen, cuando dichas operaciones no se hayan formalizado ante\nFedatario Público o autoridad competente.\nAdicional a la tarifa prevista en el presente artículo, se\nAdquisición de Inmuebles:\nA).-Sobretasa en apoyo al fomento deportivo y educacional, del\n0.4% sobre la base del citado impuesto.\nLos contribuyentes al realizar el pago de este impuesto, además del Certificado de Libertad de Gravámenes Fiscales vigente, deberán exhibir copia del documento que acredite la adquisición, pago de impuesto predial del año en curso.\nCAPÍTULO III\nIMPUESTO SOBRE ASISTENCIA A DIVERSIONES, JUEGOS PERMITIDOS Y\nESPECTÁCULOS PÚBLICOS\nARTÍCULO 9.-Son sujetos de este impuesto, los asistentes a juegos permitidos, espectáculos públicos y centros de diversión, así como funciones de obra de teatro y circo.\nA) No se considerarán espectáculos públicos los presentados en restaurantes, bares, cabarets, salones de fiesta o baile y de centros nocturnos, cuando se acredite al menos 5 días hábiles previos a la celebración del evento, ante la Autoridad Fiscal\nMunicipal, que los ingresos por dichos espectáculos serán declarados conforme a la Ley del Impuesto Sobre la Renta.\nPara efectos de este supuesto, se deberá presentar ante la autoridad fiscal municipal, al menos 5 días hábiles previos a la celebración del evento, los documentos siguientes para su valoración:\nI. Declaración autorizada firmada por el contribuyente o representante legal debidamente acreditado, en el que impuesto, serán declarados conforme a la Ley del Impuesto sobre la Renta.\nII. Copia del contrato o contratos celebrados para su realización.\nIII. Copia de Constancia de Situación Fiscal.\nIV. Copia de Identificación Oficial (INE) de la persona o representante legal.\nV. Una vez revisada y valorada la documentación anterior, espectáculo público, expidiendo la constancia correspondiente.\nB) Tratándose de eventos organizados por partidos políticos y dependencias oficiales con registro ante institución oficial, que tengan por objeto allegarse de recursos para el cumplimiento de sus fines, causará este impuesto con una tasa \"0\" cero. Para efectos de este supuesto, al menos 5 días hábiles previos a su celebración, se deberá presentar ante la Autoridad Fiscal\nMunicipal los siguientes documentos para acreditar el carácter de organizador del evento:\nI. Declaración autorizada y firmada por el representante legal debidamente acreditado, así como por el titular del área financiera del instituto u organismo organizador, en la cual se haga constar que el objeto del evento o espectáculo es para allegarse de recursos para el cumplimiento de sus fines, cuyos recursos están obligados acumular y acreditar a sus ingresos. La autoridad municipal informará sobre el particular, a la autoridad electoral correspondiente.\nII. Acta Constitutiva o Instrumento de Creación de la institución que promueve el evento.\nIII. Copia del contrato o contratos celebrados para su realización. En caso de que el evento se efectúe en un que lo organiza, se deberá incluir copia del contrato de arrendamiento.\nIV. Copia de Constancia de Situación Fiscal.\nV. Copia de Identificación Oficial (INE) de la persona o representante legal.\nVI. Una vez revisada y valorada la documentación anterior, fracción expidiendo la constancia correspondiente.\nC) Las asociaciones civiles con fines no lucrativos debidamente la ley de la materia, pagarán el 2% (dos por ciento) sobre el precio de admisión, siempre y cuando demuestren fehacientemente ser los organizadores directos del espectáculo público y exhiban a la Recaudación de Rentas con cinco días hábiles previo al evento la siguiente documentación:\nI. Declaración autorizada y firmada por el representante legal debidamente acreditado, así como por el titular del área financiera de la asociación civil, en la cual se haga constar que el objeto del evento o espectáculo es para allegarse de recursos, para el cumplimiento de sus fines, cuyos recursos están obligados acumular y acreditar a sus ingresos.\nII. Copia del contrato o contratos celebrados para su realización.\nIII. Copia de Constancia de Situación Fiscal.\nIV. Copia de Identificación Oficial (INE) de la persona o representante legal.\nV. Una vez revisada y valorada la documentación anterior, arriba indicada, expidiendo la constancia correspondiente. impuesto establecido en el presente artículo, el Ayuntamiento, por conducto de la Tesorería, emitirá los lineamientos respectivos.\nARTÍCULO 10.-Tratándose de juegos permitidos, espectáculos públicos y centros de diversión, la tasa aplicable será del 6%\n(seis por ciento) sobre el precio de admisión o sobre el derecho de entrada. En el caso de funciones de obra de teatro y circo, la tasa será del 6% (seis por ciento). el 6% (seis por ciento), debiéndolo cobrar el empresario al momento espectáculo público.\nLos eventos organizados por personas que se dediquen a la venta, producción y distribución de cerveza artesanal, que tengan exclusivamente por objeto la promoción y el posicionamiento de la cerveza artesanal como producto emblemático de la región, pagarán el 2% (dos por ciento) sobre el precio de admisión, siempre y cuando demuestren fehacientemente ser los organizadores directos del espectáculo público.\nARTÍCULO 11.-Los organizadores o empresarios de los espectáculos públicos, juegos permitidos o centros de diversión, previamente a la iniciación de los actos generadores del mismo y garantizarán el crédito fiscal estimado por la Autoridad Fiscal Municipal, mediante cualquier medio de garantía de acuerdo a la Ley de\nHacienda Municipal del Estado de Baja California.\nEn garantías de interés fiscal efectuadas a través de cheque certificado, depósito bancario o en efectivo, se harán efectivas al determinarse en cantidad liquida a pagar, acreditándose el importe correspondiente al impuesto causado, y únicamente su remanente le será devuelto. La determinación para cualquiera de las garantías fiscales indicadas en este párrafo, se calcularán multiplicando el número de boletos, por el precio a la venta de cada boleto, a su resultado se le aplicará la tasa aplicable. En caso de haberse emitido boletos con distintos rangos de precio, se suma del importe determinado para cada rango.\nEn garantías mediante fianza mercantil, deberá ser otorgada por\nSeguros y Fianzas, por importe que no será inferior al impuesto a pagar estimado, considerando los días y horarios en que se realizará el evento. La garantía podrá hacerse efectiva cuando el tres días siguientes a la conclusión del evento.\nARTÍCULO 11 BIS.-El pago del impuesto establecido en este capítulo se efectuará diariamente al finalizar el evento. La Recaudación de impuesto causado, al siguiente día hábil de aquel en que se celebre la actividad.\nEn el caso de que se utilicen medios electrónicos para la expedición de boletos o control de asistencia a los eventos, espectáculos o diversiones públicas, las Personas Físicas o jurídicas responsables de la operación de estos medios, previamente pondrán a disposición de la Autoridad Fiscal Municipal los manuales de operación de los sistemas; y entregar al día siguiente los reportes de resultados que se les soliciten.\nCAPÍTULO IV\nIMPUESTO PARA EL MANTENIMIENTO Y CONSERVACIÓN DE LAS VÍAS\nPÚBLICAS\nARTÍCULO 12.-Son sujetos de este impuesto, las personas que soliciten la expedición o revalidación de las placas de circulación para el municipio de Tijuana, Baja California. esta obligación, a las personas adultos mayores que cuenten con\n(INAPAM), así como las personas que cuenten con la correspondiente credencial permanente de “Persona con Discapacidad”, expedidas por el DIF Municipal, respecto de un solo vehículo de su propiedad que otorga el DIF Municipal, este beneficio será aplicable únicamente circulación relativo al período del ejercicio fiscal vigente, no anteriores.\nARTÍCULO 13.-Este impuesto al igual que sus accesorios se enterará artículo anterior, a través de la Recaudación de Rentas del Estado, conforme a la siguiente:\nTARIFA\nUNIDAD DE MEDIDA Y\nACTUALIZACIÓN (UMA) VIGENTE\nI.-.. Vehículos de servicio particular........ 4.35 VECES\nII.-. Vehículos de servicio público de pasajeros............................... 8.40 VECES\nIII.- Vehículos particulares de carga pesada.. 15.68 VECES\nEl impuesto deberá pagarse a más tardar el día treinta del mes de junio del año en curso. Asimismo, al momento de revalidar el impuesto correspondiente al año fiscal en curso, se le cobrarán pendientes de liquidación o pago.\nCAPÍTULO V\nIMPUESTO DE PLUSVALÍA\nARTÍCULO 14.-Están obligados al pago del Impuesto de Plusvalía, 3 de la Ley del Impuesto de Plusvalía Relativa a la Obra de\nUrbanización del Boulevard Manuel de Jesús Clouthier del Rincón, del Municipio de Tijuana, Baja California y del Artículo 7 de la\nLey de Urbanización del Estado de Baja California; para la en la Ley de Plusvalía en comento.\nAsí también, serán sujetos de este impuesto todos aquéllos que con de la Ley de Urbanización del Estado de Baja California, sean beneficiados.\nCAPÍTULO VI\nDE LUCRO VINCULADOS A FORTALECER LA SEGURIDAD PÚBLICA Y SOCIAL\nARTÍCULO 15.-Serán sujetos de este impuesto las personas físicas y morales que operen los establecimientos señalados en los\nArtículos 20 fracción V, 22 fracciones III y VII y 25 de la presente\nLey, excepto los abarrotes, licorerías, fondas o loncherías.\nARTÍCULO 16.-El Impuesto para el Apoyo a Organismos No\nGubernamentales Sin Fines de Lucro Vinculados a Fortalecer la\nSeguridad Pública y Social, se causará a una tasa del 15% (quince por ciento) sobre el pago de derechos por revalidación anual del permiso de establecimientos para la venta, almacenaje y consumo público de bebidas alcohólicas, o por el pago de derechos por horario extraordinario, así como, sobre el pago de Derechos por revalidación anual del permiso de operación, de centros de apuesta, apuestas remotas, salas de sorteos de números y/o casinos. revalidación anual del permiso de establecimientos para la venta, almacenaje y consumo público de bebidas alcohólicas, o por el pago de derechos por horario extraordinario, así como, sobre el pago de derechos por revalidación anual del permiso de operación, de centros de apuestas, apuestas remotas, salas de sorteos de números y/o casinos. de Lucro Vinculados a Fortalecer la Seguridad Pública y Social, se revalidación de permisos.\nCAPÍTULO VII\nSORTEOS\nARTÍCULO 17.-Los permisionarios que, derivado de sus actividades de juegos con apuestas o sorteos, que otorguen premio en efectivo o en especie al amparo de un permiso federal otorgado por la\nSecretaría de Gobernación o de una resolución judicial que haya causado estado, registrados y reconocidos en la página oficial de la citada Secretaría de Gobernación, pagarán el impuesto correspondiente de acuerdo a lo siguiente:\nA).-Para los organizadores de juegos con apuestas permitidas y/o habilidades o destrezas................................ 3%\nPara los efectos de este artículo las personas que organicen juegos con apuestas permitidas se considerará como valor de las mismas la cantidad que se cobre o reciba por el billete o boleto que permita la participación o la apuesta, deduciéndose a dicha base gravable el valor del premio efectivamente pagado o entregado, así como la participantes. artículo, no causarán los impuestos y derechos contenidos en esta\nLey relativos a las máquinas de juego, calcomanía por máquina, holograma por máquina o cualquier otro análogo; así como para la obtención de permisos, revalidación o licencia de operación del establecimiento de los mismos.\nTÍTULO TERCERO\nDERECHOS\nCAPÍTULO I\nARTÍCULO 18.-Los derechos por servicios que prestan las Oficialías del Registro Civil, serán pagados por los usuarios, sujetándose a la siguiente:\nTARIFA\nUNIDAD DE MEDIDA Y\nACTUALIZACIÓN (UMA) VIGENTE\nI. - Nacimientos\nA).-Registro de nacimiento:\na).-En horas hábiles dentro de las oficinas EXENTO\nb).-En Instituciones de salud en módulo del\nRegistro Civil........................ EXENTO\nc).-En Instituciones Públicas o Privadas de\nSalud por enfermedad infantil o maternal\n...................................... EXENTO\nd).-Inscripción de registro de nacimiento ocurrido en territorio extranjero..... EXENTO\ne).-Nacimientos. Registro en “Campaña\nColectiva” de registros.............. EXENTO\nII.-Adopciones\nA).-Inscripción de sentencia de adopción proveniente de juzgado local........ EXENTO\nB).-Inscripción de adopción dictada fuera de la República proveniente de juzgado local................................. EXENTO\nIII.-Reconocimiento de hijos\nA).-Reconocimiento de hijo (en horas hábiles) EXENTO\nB).-Inscripción de acta de reconocimiento de hijo, celebrada en el extranjero, proveniente de juzgado local.......... EXENTO\nIV.-Matrimonios\nA).-Solicitud y formatos para los certificados médicos prenupciales... 2.00 VECES\nB).-Celebración:\na).-Dentro de las oficinas en horas hábiles 5.00 VECES\nb).-Dentro de las oficinas en horas inhábiles\n...................................... 8.75 VECES\nc).-A domicilio en horas hábiles........ 30.00 VECES\nd).-A domicilio en horas inhábiles:\n1).-De Lunes a Sábado..................... 50.00 VECES\n2).-En Domingo............................ 62.50 VECES\nC).-Inscripción de acta de matrimonio celebrado en territorio extranjero... 15.00 VECES\nD).-Celebración de matrimonio dentro de\n\"Campaña Matrimonios Colectivos\" EXENTO\nE).-Celebración urgente:\na).-Dentro de la oficina:\n1).-En horas hábiles...................... 30.00 VECES\n2).-En horas inhábiles.................... 40.00 VECES\nF).-Celebración en Instituciones de Salud\nPública o Privada EXENTO\nG).-Anotación de cambio de régimen matrimonial o registro o modificación a las capitulaciones matrimoniales 14.50 VECES\nV.-Divorcios y nulidades de matrimonio\nA).-Administrativo, tramitado en la oficina del Registro Civil.................. 25.00 VECES\nB).-Inscripción de sentencia de divorcio proveniente de juzgado local....... 12.50 VECES\nC).-Inscripción urgente (dentro de tres días hábiles) de sentencia de divorcio proveniente de juzgado local........ 18.00 VECES\nD).-Inscripción de divorcio tramitado fuera de la República, proveniente de juzgado local............................... 15.00 VECES\nE).-Inscripción de nulidad de matrimonio proveniente de juzgado local EXENTO\nF).-Inscripción de sentencias de divorcio provenientes de juzgado Local. Durante\n\"Campaña\" se podrá gozar del 50%\n(cincuenta por ciento) de descuento. 6.00 VECES\nVI.-Defunciones\nA).-Registro:\na).-En las oficinas en horas hábiles....... EXENTO\nb).-En las oficinas en horas inhábiles... 2.50 VECES\nB).-Inscripción de registro de presunción de muerte:\na).-En las oficinas en horas hábiles....... EXENTO\nb).-En las oficinas en horas inhábiles... 2.50 VECES\nC).-Permisos de Inhumación:\na).-Derechos por servicios a panteones en horas hábiles........................ 5.00 VECES\nb).-Derechos por servicios a panteones en horas inhábiles....................... 7.50 VECES\nc).-Inscripción de acta de defunción acaecida fuera del país...................... 15.00 VECES\nd).-Orden de traslado de cadáver........... 3.75 VECES\ne).-Orden de traslado de cadáver al extranjero........................... 18.75 VECES\nf).-Autorización de exhumación, cremación o reinhumación.......................... 6.25 VECES\ng).-Autorización de inhumación a perpetuidad en panteones particulares.......... 15.00 VECES\nVII.-Expedición de copias certificadas o búsqueda de datos para la certificación de actos o hechos registrados, o constancias de inexistencias.\nA).-Copias certificadas de Nacimiento:\na).-Primer copia certificada del registro de nacimiento........................... EXENTO\n(Debiéndose adicionar los derechos correspondientes a la de acuerdo su Ley de Ingresos vigente) será: 50% (cincuenta por ciento) del costo autorizado por la\nLey de Ingresos vigente. En las copias estatales o interestatales el 50% (cincuenta por ciento) de descuento se\nAyuntamiento de Tijuana (dos campañas por año).\nB).-Copias certificadas (Copia fiel del libro):.............................\na).-Servicio ordinario Copia fiel del libro\n(registro no automatizado o digitalizado), entrega en 2 días hábiles\n...................................... 1.50 VECES\nb).-Servicio urgente Copia fiel del libro\n(registro no automatizado o digitalizado) el mismo día............ 3.00 VECES\nc).-Servicio ordinario (registro automatizado o digitalizado), entrega inmediata........................... 2.00 VECES\nd).-Servicio urgente (registro automatizado o digitalizado, no localizado en sistema, dos campañas por año)................ 3.00 VECES\ne).-Copia certificada estatal o interestatal.\n(Debiéndose adicionar los derechos correspondientes a la Dirección del\nB.C. de acuerdo su Ley de Ingresos vigente, dos campañas por año) 2.00 VECES\nf).-Servicio ordinario en \"Campaña\" Copia fiel del libro (registro no automatizado o digitalizado, dos campañas por año.)\n...................................... 0.75 VECES\ng).-Servicio urgente en \"Campaña\" Copia fiel del libro (registro NO automatizado o digitalizado). El costo de copias certificadas en \"Campaña\" será: 50%\n(cincuenta por ciento) del costo autorizado por la Ley de Ingresos vigente. (Dos campañas por año)....... 1.50 VECES\nh).-Servicio ordinario en \"Campaña\" (registro automatizado o digitalizado). El costo de copias certificadas en \"Campaña\" será: 50% (cincuenta por ciento) del costo autorizado por la Ley de Ingresos vigente. (Dos campañas por año)....... 1.00 VECES\ni).-Copia certificada estatal o interestatal en \"Campaña\". (Debiéndose adicionar los derechos correspondientes a la\nDirección del Registro Civil de Gobierno del Estado de B.C. de acuerdo a su Ley de Ingresos vigente). El costo de copias certificadas en \"Campaña\" será:\n50% (cincuenta por ciento) del costo autorizado por la Ley de Ingresos vigente. En las copias estatales o interestatales el 50% (cincuenta por ciento) de descuento se aplicará únicamente en el importe que le corresponde al Ayuntamiento de Tijuana.\n(Dos campañas por año)................\n...................................... 1.00 VECES\nC).-Búsqueda de datos para expedición de copia certificada:\na).-Búsqueda de datos inmediata (localizados por sistema)......................... EXENTO\nb).-Búsqueda de datos (no localizados en sistema)........................... EXENTO\nD).-Expedición de constancias de inexistencia\na).-Inexistencia de registro de nacimiento municipal.......................... 2.00 VECES\nb).-Inexistencia de registro de nacimiento en\n“Campaña de Registro de Nacimiento\nExtemporáneo”........................ EXENTO\nc).-Inexistencia de registro de matrimonio municipal............................. 2.00 VECES\nd).-Inexistencia de registro de nacimiento estatal (Debiéndose adicionar los derechos correspondientes a la\nDirección del Registro Civil de Gobierno del Estado de B.C. de acuerdo a su Ley de Ingresos vigente)...............\n2.00 VECES\ne).-Inexistencia de registro de matrimonio estatal (Debiéndose adicionar los derechos correspondientes a la\nDirección del Registro Civil de Gobierno del Estado de B.C. de acuerdo a su Ley de Ingresos vigente)...............\n2.00 VECES\nVIII.- Otros\nA).-Rectificación de actas.................. EXENTO\nB).-Rectificación de actas por errores imputables a la Autoridad Municipal.\n(Derecho Estatal se pagará en Gobierno del Estado, de acuerdo al costo según\nLey de Ingresos del Estado de B.C. vigente)............................. EXENTO\nC).-Por búsqueda de datos para registro de campaña.............................. EXENTO\nD).-Trámite de cancelación de acta por duplicidad........................ 2.50 VECES\nE).-Certificación por hoja de apéndice...... 1.00 VECES\nF).-Certificación del total de hojas que integran el apéndice................. 3.50 VECES\nPara los casos de registros de nacimientos, matrimonios, defunciones, expedición de copias certificadas o búsqueda de datos para la certificación de actos o hechos registrados, o constancias de inexistencia, se debe considerar lo siguiente:\nPensionados, jubilados, esposos, viudos e hijos de éstos, menores de edad, pagarán el 50% (cincuenta por ciento) de la tarifa por los servicios previstos en este artículo, tratándose de documentos que estén a su nombre, debiendo comprobar su condición con identificación o documento expedida por Institución Pública.\nTratándose de grupos vulnerables: Indigentes, adultos mayores, personas con discapacidad, personas de escasos recursos, madres solteras, grupos indígenas y migrantes, estarán exentos de pago, previa solicitud y cumplimiento de requisitos.\nIndigentes: Previa solicitud y documento que lo acredite, expedido por la Comisión de Derechos Humanos, grupos vulnerables y Asuntos\nIndígenas de Regidores.\nAdultos mayores: Previa solicitud y acreditación con documento oficial con fotografía.\nPersonas con discapacidad: Previa presentación de tarjeta de discapacidad expedida por el Sistema Municipal para el Desarrollo condición, elaborado por una institución de salud pública o privada.\nPersonas de escasos recursos: Previa solicitud y estudio\nFamilia o Delegados Municipales.\nMadres solteras y personas pertenecientes a grupos indígenas: presentando documento que lo acredite, expedido por la Comisión de\nDerechos Humanos, Grupos Vulnerables y Asuntos Indígenas de\nRegidores.\nMigrantes: Presentando documento que lo acredite, expedido por la\nComisión de Asuntos Fronterizos de Regidores. respectivos.\nPara los casos de la fracción V Divorcios y nulidades de matrimonio, proveniente de una sentencia tipificada como violencia contra las mujeres, de conformidad a la Ley General de Acceso de las Mujeres a una Vida Libre de Violencia, estarán exentos de pago, previa solicitud y cumplimiento de requisitos Respectivos.\nPara los efectos de este artículo, son horas hábiles las transcurridas entre las ocho horas y hasta las quince horas de cualquier día hábil. Son días hábiles los días de lunes a viernes de todas las semanas, siempre que se encuentren abiertas al público las Oficinas del Registro Civil dentro de las horas hábiles.\nArtículo Reformado\nCAPÍTULO II\nQUE PRESTA LA DIRECCIÓN GENERAL DE GOBIERNO\nEVENTOS, ESPECTÁCULOS PÚBLICOS Y DE DIVERSIÓN\nARTÍCULO 19.-Para la realización de eventos, espectáculos públicos y de diversión sin venta y/o consumo de alcohol, deberá entregarse la documentación necesaria, previo el pago de derechos que se causen de acuerdo a la siguiente:\nI.- Por expedición de permisos, una vez que han sido autorizados, pagarán los siguientes derechos:\nTARIFA\nUNIDAD DE MEDIDA Y\nACTUALIZACIÓN (UMA) VIGENTE\nA).- Espectáculos o eventos públicos y masivos.\na).- Con fines de lucro y asistencia de 1000 o más personas....................... 65.00 VECES\nb).- Con fines de lucro y asistencia de 999 o menos personas..................... 39.00 VECES\nc).- Sin fines de lucro y asistencia de 1,000 o más personas....................... 26.00 VECES\nd).- Sin fines de lucro y asistencia de 999 o menos personas..................... 26.00 VECES\nB).- Eventos en vía pública\na).- Carreras, caminatas, rallys, maratones y eventos deportivos con fines de lucro para 500 o más personas 45.50 VECES\nb).- Carreras, caminatas, rallys, maratones y eventos deportivos con fines de lucro para 499 o menos personas............ 32.50 VECES\nc).- Carreras, caminatas, rallys, maratones y eventos deportivos sin fines de lucro para 500 o más personas............... 32.50 VECES\nd).- Carreras, caminatas, rallys, maratones y eventos deportivos sin fines de lucro para 499 o menos personas............ 19.50 VECES\ne).- Encuestas, inauguraciones, conferencias de prensa, filmaciones, exhibiciones y otros................. 16.25 VECES\nf).- Filmaciones documentales, comerciales, películas, series con una participación de más de 100 personas............... 50.00 VECES\ng).- Filmaciones documentales, comerciales, películas, series con una participación de 99 o menos personas............... 25.50 VECES\nCuando los eventos de la vía pública, establecidos en los incisos f) y g), de esta fracción, sean realizados por producciones estudiantiles con fines académicos, con el aval de la institución educativa correspondiente, se exentarán de dicho cobro.\nC).-Cierre total o parcial de la vía pública en otros eventos no especificados.............................. 5.53 VECES en la vía pública sin venta y/o consumo de alcohol, el causante del evento o espectáculo. Lo anterior podrá realizarse en el Artículo 29 de esta Ley. O en caso que el contribuyente decida efectuar la recolección por su cuenta o mediante un tercero, deberá garantizar el cumplimiento de dicha obligación con depósito en efectivo del monto fijado por la Dirección de\nServicios Públicos Municipales, ante la Dirección de\nRecaudación Municipal o Fianza de compañía autorizada.\nD).- Circos y juegos mecánicos................... 39.00 VECES\nII.-En general por la recepción y expedición de permisos para espectáculos y eventos urgentes (en menos de 72 horas) se cobrará el doble de la tarifa.\nTratándose de eventos organizados por partidos políticos, dependencias oficiales y organismos no gubernamentales con registro ante institución oficial, que tengan por objeto allegarse de recursos para el cumplimiento de sus fines, no se causará este derecho. Para efectos de este supuesto, al menos 5 días hábiles organizador del evento:\nI. Acta constitutiva o instrumento de creación de la que promueve el evento.\nII. Copia del contrato o contratos celebrados para su realización. En caso de que el evento se efectúe en un local organiza, se deberá incluir copia del contrato de arrendamiento.\nIII. Declaratoria firmada por el titular del área financiera del instituto u organismo organizador, en la cual se haga allegarse de recursos para el cumplimiento de sus fines, cuyos recursos están obligados acumular y acreditar a sus ingresos.\nLa autoridad municipal informará sobre el particular, a la autoridad electoral correspondiente.\nCENTROS DE APUESTAS, APUESTAS REMOTAS, SALAS DE SORTEOS DE\nNÚMEROS Y/O CASINOS.\nARTÍCULO 20.-Las máquinas de azar o con combinaciones de azar y destreza, con premios en efectivo o en especie que cuenten con autorización de la Secretaría de Gobernación, pagarán los derechos de instalación o explotación conforme a la siguiente tabla:\nTARIFA\nUNIDAD DE MEDIDA Y\nACTUALIZACIÓN (UMA) VIGENTE\nI).- Apertura del establecimiento.... 130,000.00 VECES\nII).- Cambio de domicilio............. 1,950.00 VECES\nIII).- Cambio de propietario........... 1,950.00 VECES\nIV).- Incremento por aparato.......... 78.00 VECES\nRevalidación anual de licencia de\nV).- 2,080.00 VECES operación por establecimiento...\nPermiso de operación por horario\nVI).- 1,950.00 VECES ampliado, anual.................\nAportación para programas\nVII).- 1,950.00 VECES preventivos para la ludopatía...\nINSTALACIÓN DE APARATOS MECÁNICOS, ELECTRÓNICOS,\nELECTROMECÁNICOS, APARATOS MUSICALES Y VIDEOJUEGOS\nARTÍCULO 21.-Para la autorización de apertura, cambio de domicilio o de propietario, cambio o incremento de aparatos y revalidación de máquinas electrónicas, electromecánicas, mecánicas, musicales, digitales, videojuego y cualquier tecnología similar que opera mediante la inserción de billete, moneda, ficha, tarjeta, banda magnética o cualquier otro medio de cobro integrado, a la máquina, incluyendo de manera enunciativa y no limitativa las máquinas expendedoras de bebidas, dulces, alimentos, botanas, golosinas, juguetes, computadoras, goma de mascar, tarjetas de teléfono, mercancías en general, entre otros. Dirigidas al público en general deberán cubrir los siguientes derechos:\nTARIFA\nUNIDAD DE MEDIDA Y\nACTUALIZACIÓN (UMA) VIGENTE\nI.- Por recepción y dictamen de las solicitudes............................ 65.00 VECES\nII.- Por expedición del permiso, pagarán la siguiente tarifa:\nA).-Apertura, cambio de domicilio y cambio de propietario................. 32.50 VECES\nB).-Por aparato adicional no incluido en el permiso original.................... 13.00 VECES\nIII.- Por verificación anual de aparatos:\nA).-Expendedores de refrescos, dulces, botanas, golosinas y alimentos que se consideren de poco valor nutritivo en términos de la regulación federal aplicable............................. 13.00 VECES\nB).-Otros.............................. 13.00 VECES antecede, deberá realizarse previo pago de derechos que deberán entregarse durante el mes de marzo de cada ejercicio fiscal. presente artículo, serán responsables solidarios del pago de los derechos que deban enterarse.\nCAPÍTULO III\nDERECHOS POR RECEPCIÓN, ANÁLISIS, EVALUACIÓN E INSPECCIÓN DE\nSOLICITUDES, EMISIÓN DE DOCUMENTOS, PERMISOS Y CERTIFICADOS\nREFERENTES A INSTALACIONES PARA LA VENTA, ALMACENAJE Y CONSUMO\nPÚBLICO DE BEBIDAS ALCOHÓLICAS, CAMBIO DE GIRO, CAMBIO DE\nTITULAR, CAMBIO DE DOMICILIO, CAMBIO DE NOMBRE COMERCIAL Y\nTRAMITACIÓN RELATIVA A LA OPERACIÓN DE GIROS DE CERVEZA, VINOS,\nLICORES, ALCOHOLES Y SIMILARES; Y LA EXPEDICIÓN DE PERMISOS\nEVENTUALES EN EVENTOS Y ESPECTÁCULOS PÚBLICOS PARA OPERAR LA\nVENTA DE BEBIDAS ALCOHÓLICAS.\nARTÍCULO 22.-Por la recepción, análisis, evaluación e inspección de solicitudes de permisos para la operación de establecimientos con venta, almacenaje y consumo de bebidas alcohólicas, cambio de giro, cambio de titular, cambio de nombre comercial, cambio de domicilio, así como la emisión de permisos que por dichos conceptos y similares se otorguen, estarán sujetos a la siguiente:\nTARIFA\nUNIDAD DE MEDIDA Y\nACTUALIZACIÓN (UMA) VIGENTE\nI.-Recepción, análisis, evaluación e inspección de solicitudes de permisos para operar la venta de bebidas alcohólicas, así como la emisión de los estudios y/o autorización que según la reglamentación aplicable sean necesarios......... 130.00 VECES\nII.-Recepción, análisis, evaluación de solicitudes y expedición de opinión técnica................................... 130 VECES\nIII.-Por expedición de permisos:\nA.-Por expedición de permisos nuevos, una vez que han sido aprobados, pagarán los siguientes derechos:\na).- Abarrotes..................... 2,101.06 VECES\nb).- Mercados...................... 3,151.66 VECES\nc).- Supermercado................... 6,999.46 VECES\nd).- Tienda de autoservicio y licorería 6,999.46 VECES\ne).- Agencias, sub-agencias y depósitos 4,811.69 VECES\nf).- Bodega......................... 4,374.18 VECES\ng).- Fonda o lonchería.............. 3,062.46 VECES\nh).- Restaurante.................... 3,936.93 VECES\ni).- Restaurante-Bar................ 9,266.66 VECES\nj).- Bar Turístico y Bar Terraza.... 9,844.43 VECES\nk).- Billares....................... 4,374.18 VECES\nl).- Expendio de cerveza y vino..... 6,562.27 VECES\nm).- Hotel y motel.................. 10,936.37 VECES\nn).- Café cantante, centro de espectáculos y discoteca....... 12,030.47 VECES ñ).- Sala de degustación de cerveza artesanal en envase abierto y/o cerrado........................ 472.42 VECES\no).- Boutique de cerveza artesanal en envase cerrado................. 472.42 VECES\np).- Micro cervecería............... 472.42 VECES\nq).- Restaurante con venta para consumo de vinos de mesa de producción nacional....................... 0 VECES\nPor expedición de autorizaciones de cambios a permisos, una\nB).vez que han sido autorizados, pagarán los siguientes derechos:\na).- En los permisos que se solicite el cambio de giro, se cobrará la diferencia del valor del costo del permiso, y en los casos de disminución de la actividad, se cobrará 6.50 veces la Unidad de Medida y Actualización\n(UMA) vigente.\nb).- Habiendo sido autorizado el cambio de titular o el cambio de domicilio, se pagará el 50% (cincuenta por ciento) y el 15% (quince por ciento) respectivamente, del giro solicitado.\nc).- Habiendo sido autorizado el cambio de titular, cuando el nuevo titular adquiera los derechos por adjudicación hereditaria se pagará el 10% (diez por ciento), sobre el valor de la expedición de un permiso nuevo del giro solicitado.\nd).- En caso de haber sido solicitados y autorizados el cambio de titular y el cambio de domicilio en el mismo trámite, se pagará el 55% (cincuenta y cinco por ciento) sobre el valor de la expedición de un permiso nuevo del giro solicitado por ambos conceptos.\ne).- Por el cambio de nombre comercial se pagará 1% (uno por ciento), sobre el valor de la expedición del permiso nuevo.\nIV.-Para efectos de los servicios adicionales, se otorgarán sólo en aquellos giros a que refiere la ley de la materia y su reglamento, pagando por la autorización los siguientes derechos:\nA).- Música grabada y aparatos musicales. 345.35 VECES\nB).- Conjuntos musicales................. 408.14 VECES\nC).- Mesas de billar, por cada mesa...... 78.49 VECES\nD).- Espectáculos artísticos............. 549.42 VECES\nE).- Pista de baile...................... 408.14 VECES\nEl pago por concepto de servicios adicionales, anteriormente especificado, es independiente al pago por concepto de expedición de permisos nuevos, o cambios.\nV.-Autorización respecto de cierre temporal y aviso de no inconveniente de intención de ceder derechos del permiso, de acuerdo a lo siguiente:\nA).- Autorización respecto a cierre temporal........ 6.50 VECES\nB).- Autorización respecto a aviso de no inconveniente de intención de ceder los derechos de permiso. 19.50 VECES\nVI-.-Expedición de nueva impresión de permisos otorgados....................... 13.00 VECES\nVII.-Derechos por revalidación anual de p ermisos:\nA).- Abarrotes..............................\n47.78 VECES\nB).- Mercados............................... 85.32 VECES\nC).- Supermercado........................... 170.63 VECES\nD).- Tienda de autoservicio y licorería..... 110.92 VECES\nE).- Agencias, sub-agencias y depósitos..... 127.97 VECES\nF).- Bodega................................. 110.92 VECES\nG).- Fonda o lonchería...................... 51.19 VECES\nH).- Restaurante............................ 102.38 VECES\nRestaurante con venta para consumo de\nI).vinos de mesa de producción nacional... 0 VECES\nJ).- Restaurante-Bar 221.82 VECES\nK).- Bar Turístico y Bar Terraza............ 213.29 VECES\nL).- Billares............................... 170.63 VECES\nM).- Expendio de cerveza y vino............. 127.97 VECES\nN).- Hotel y motel.......................... 221.82 VECES\nCafé cantante, centro de espectáculos y\nÑ).discoteca 255.94 VECES\nServicios adicionales, por cada servicio\nO).solicitado............................. 17.07 VECES\nSala de degustación de cerveza artesanal\nP).en envase abierto y/o cerrado..........\n47.78 VECES\nBoutique de cerveza artesanal en envase\nQ).cerrado................................ 47.78 VECES\nR).- Micro cervecería....................... 47.78 VECES la presente fracción, deberán cubrirlo anualmente en los siguientes plazos: a los siguientes giros:\na).- Restaurante-Bar\nb).- Bar Turístico y Bar Terraza\nc).- Billares\nd).- Expendio de cerveza y vino\ne).- Hotel y motel\nf).- Café cantante, centro de espectáculos y discoteca\nDurante el mes de mayo de cada año los permisos correspondientes a los siguientes giros:\na).- Licorerías y tiendas de autoservicio\nb).- Agencias, sub-agencias y depósitos\nc).- Bodega\nd).- Fonda o lonchería\ne).- Restaurante\nf).- Restaurante con venta para consumo de vinos de mesa de producción nacional\nDurante el mes de junio de cada año los permisos correspondientes a los siguientes giros:\na).- Abarrotes y mercados\nb).- Supermercado\nc).- Sala de degustación de cerveza artesanal\nd).- Boutique de cerveza artesanal\ne).- Micro cervecería\nf).- Cualquier otro no mencionado en los párrafos precedentes\nLos permisionarios, al momento de realizar la revalidación en los términos de esta fracción, deberán acreditar que el permiso de que se trate se encuentre en operación. la revocación del permiso de venta de bebidas alcohólicas, notificándolo para tal efecto, la autoridad competente en permiso de venta de bebidas alcohólicas, dentro de los 10 días naturales al mes de su vencimiento de revalidación anual.\nUna vez revocado el permiso de que se trate, si el contribuyente amparaba, se procederá a la inmediata clausura del establecimiento mediante mandamiento del Recaudador de Rentas Municipal.\nVIII.- Expedición de autorización de permiso temporal para la venta de bebidas alcohólicas, con vigencia de 60 días naturales, se cobrará:\nA).-Por recepción, análisis y evaluación de solicitud de permiso temporal......... 13.40 VECES\nB).-Por expedición de autorización de permiso temporal:\na).-Abarrotes........................... 47.78 VECES\nb).-Mercados............................ 85.32 VECES\nc).-Supermercado........................ 170.63 VECES\nd).-Tienda de autoservicio y licorería.. 110.92 VECES\ne).-Agencias, sub-agencias y depósitos.. 127.97 VECES\nf).-Bodega.............................. 110.92 VECES\ng).-Fonda o lonchería................... 51.19 VECES\nh).-Restaurante......................... 102.38 VECES\ni).-Restaurante con venta para consumo de vinos de mesa de producción nacional. 0 VECES\nj).-Restaurante-Bar..................... 221.82 VECES\nk).-Bar Turístico y Bar Terraza......... 213.29 VECES\nl).-Billares............................ 170.63 VECES\nm).-Expendio de cerveza y vino.......... 127.97 VECES\nn).-Hotel y motel....................... 221.82 VECES ñ).-Café cantante, centro de espectáculos y discoteca................ 255.94 VECES\no).-Sala de degustación de cerveza artesanal en envase abierto y/o cerrado. 47.78 VECES\np).-Boutique de cerveza artesanal en envase cerrado.......................... 47.78 VECES\nq).-Micro cervecería.................... 47.78 VECES\nr).-Servicios adicionales, por cada servicio solicitado................... 17.07 VECES permiso temporal. domicilio.\nLos permisos temporales deberán ser autorizados por el Secretario\nGeneral de Gobierno.\nIX.-Expedición de copia certificada de estudio de impacto social, para la solicitud de permiso, para la venta de bebidas alcohólicas, para cambio de nombre o domicilio en los permisos para la venta de bebidas alcohólicas y para permisos temporales.................................... 1 43.00 VECES\nX.-Expedición de copia certificada de permiso de operación, revalidación anual o permiso temporal...................................... 26.00 VECES\nDERECHOS POR RECEPCIÓN Y ANÁLISIS DE DOCUMENTOS Y EXPEDICIÓN DE\nPERMISOS EVENTUALES REFERENTES A LA REALIZACIÓN DE ESPECTÁCULOS\nPÚBLICOS Y EVENTOS DE DIVERSIÓN\nARTÍCULO 23.-Para la realización de eventos, espectáculos públicos y de diversión con venta de bebidas alcohólicas, deberá entregarse la documentación necesaria, previo el pago de derechos que se causen, de acuerdo a la siguiente:\nTARIFA\nUNIDAD DE MEDIDA Y\nACTUALIZACIÓN (UMA) VIGENTE\nI.-Recepción, análisis y evaluación de\n13.00 VECES solicitudes de permisos eventuales para operar la venta y/o consumo público de bebidas alcohólicas......................\nII.-Expedición de permisos eventuales para operar la venta y/o consumo público de bebidas alcohólicas:\nA).- Espectáculos públicos y masivos:\nPresentación de artistas, cantantes, funciones de box, lucha libre, obras de teatro, cine, eventos deportivos, eventos culturales, bailes, exposiciones, ferias, festivales, verbenas, congresos, exhibiciones de moda, con fines de lucro y asistencia de 1000 o más personas.............. 78.00 VECES\nB).- Espectáculos públicos y masivos:\nPresentación de artistas, cantantes, funciones de box, lucha libre, obras de teatro, cine, eventos deportivos, eventos culturales, bailes, exposiciones, ferias, festivales, verbenas, congresos, exhibiciones de moda, con fines de lucro y asistencia de 999 o menos personas............. 52.00 VECES\nC).- Espectáculos públicos y masivos:\nPresentación de artistas, cantantes, funciones de box, lucha libre, obras de teatro, cine, eventos deportivos, eventos culturales, bailes, exposiciones, ferias, festivales, verbenas, congresos, exhibiciones de moda, sin fines de lucro y asistencia de 1000 o más personas.............. 52.00 VECES\nD).- Espectáculos públicos y masivos:\nPresentación de artistas, cantantes, funciones de box, lucha libre, obras de teatro, cine, eventos deportivos, eventos culturales, bailes, exposiciones, ferias, festivales, verbenas, congresos, exhibiciones de moda, sin fines de lucro y asistencia de 999 o menos personas............. 35.10 VECES\nE).- Eventos particulares y sociales, sin cobro, admisión y/o cuota de 13.00 VECES recuperación con venta de bebidas alcohólicas.........................\nF).- Degustación por establecimiento comercial........................... 39.00 VECES\nG).- Espectáculos públicos y masivos, solicitados por asociaciones civiles, escuelas, asociaciones religiosas y dependencias de gobierno............ 26.00 VECES\nIII.-Expedición de permisos, para eventos con solicitud de cierre parcial o total de calle, uso de la vía pública con venta y/o consumo público de bebidas alcohólicas:\nA).- Espectáculos públicos y masivos:\nPresentación de artistas, cantantes, funciones de box, lucha libre, obras de teatro, cine, eventos deportivos, eventos culturales, bailes, exposiciones, feria, verbena, festivales, congresos, exhibiciones de moda, con fines de lucro y asistencia de 1000 o más personas... 130.00 VECES\nB).- Espectáculos públicos y masivos:\nPresentación de artistas, cantantes, funciones de box, lucha libre, obras de teatro, cine, eventos deportivos, eventos culturales, bailes, exposiciones, feria, verbena, festivales, congresos, exhibiciones de moda, con fines de lucro y asistencia de 999 o menos personas.. 78.00 VECES\nC).- Espectáculos públicos y masivos:\nPresentación de artistas, cantantes, funciones de box, lucha libre, obras de teatro, cine, eventos deportivos, eventos culturales, bailes, exposiciones, feria, verbena, festivales, congresos, exhibiciones de moda, sin fines de lucro y asistencia de 1000 o más personas... 78.00 VECES\nD).- Espectáculos públicos y masivos:\nPresentación de artistas, cantantes, funciones de box, lucha libre, obras 52.00 VECES de teatro, cine, eventos deportivos, eventos culturales, bailes, exposiciones, feria, verbena, festivales, congresos, exhibiciones de moda, sin fines de lucro y asistencia de 999 o menos personas..\nE).- Eventos particulares y sociales..... 3.25 VECES\nF).- Espectáculos públicos y masivos con cierre de calle, solicitados por asociaciones civiles y/o instituciones de gobierno........... 39.00 VECES\nPara realizar el pago por la expedición del permiso para la realización de espectáculos públicos y eventos de diversión en la vía pública con venta y/o consumo de alcohol, el causante deberá acreditar la forma en que cumplirá con su obligación de disponer de los residuos sólidos urbanos generados al final del evento o espectáculo. Lo anterior podrá realizarse exhibiendo el comprobante de pago de los derechos previstos en el artículo 29 de esta Ley. O en caso que el contribuyente decida efectuar la recolección por su cuenta o mediante un tercero, deberá garantizar el cumplimiento de dicha obligación con depósito en efectivo del monto fijado por la Dirección de Servicios Públicos Municipales, ante la Dirección de Recaudación Municipal o fianza de compañía autorizada.\nTratándose de eventos organizados por personas que se dediquen a la venta, producción y distribución de cerveza artesanal, que tengan exclusivamente por objeto la promoción y el posicionamiento de la cerveza artesanal como producto emblemático de la región, este derecho se causará solamente por el 50% del pago correspondiente. Para efectos de este supuesto, al menos 5 días carácter de organizador del evento:\nI.- Acta constitutiva o instrumento de creación del que promueve el evento.\nII.-Copia del contrato o contratos celebrados para su realización. En caso de que el evento se efectúe en un local organiza, se deberá incluir copia del contrato de arrendamiento.\nIII.-Declaratoria firmada por el o los solicitantes, en el la cerveza artesanal como producto emblemático de la región.\nIV.- En general por la recepción y expedición de documentos de espectáculos y eventos urgentes (en menos de\n72 horas) se cobrará el doble de la tarifa asignada.\nTratándose de eventos organizados por partidos políticos, dependencias oficiales y organismos no gubernamentales con registro ante institución oficial, que tengan por objeto allegarse de recursos para el cumplimiento de sus fines, no se causará este derecho. Para efectos de este supuesto, al menos 5 días hábiles previos a su celebración se deberá presentar ante la autoridad municipal los siguientes documentos para acreditar el carácter de organizador del evento:\nI.-Acta constitutiva o instrumento de creación del solicitante debidamente registrada respecto a la institución que promueve el evento.\nII.-Copia del contrato o contratos celebrados para su realización. En caso de que el evento se efectúe en un local organiza, se deberá incluir copia del contrato de arrendamiento.\nIII.-Declaratoria firmada por el titular del área financiera del instituto u organismo organizador, en la fines, cuyos recursos están obligados a acumular y acreditar a sus ingresos. La autoridad municipal informará sobre el particular, al Instituto Estatal Electoral de Baja\nCalifornia.\nCAPÍTULO IV\nARTÍCULO 24.-Las licencias o permisos por el uso u ocupación de las vías públicas para realizar actividad comercial, se pagará de acuerdo a la siguiente:\nTARIFA\nUNIDAD DE MEDIDA Y\nACTUALIZACIÓN (UMA) VIGENTE\nI.-Por análisis y emisión de factibilidad de opiniones técnicas de ocupación de la vía pública por el equipamiento del comercio en la vía pública con puestos fijos o semifijos en sus diferentes modalidades y que por su ubicación impactan la imagen urbana y el buen funcionamiento de la circulación peatonal:\nA). Por metro cuadrado o fracción de puesto fijo o semifijo para comercio en la vía pública................................. 3.90 VECES\nII.-Licencia o permiso anual\nA). Vendedores ambulantes:\na).- Aseador de calzado.................. EXENTO\nb).- Voceador............................ EXENTO\nc).- Vendedores ambulantes medida de 1 x\n1 M²...............................1 6.25 VECES\nd).- Vendedores ambulantes medida de 2 x\n1 M².............................. 16.25 VECES\nB). Puestos semifijos:\na).- Aseador de calzado................ EXENTO\nb).- Voceador.......................... EXENTO\nc).- Puestos semifijos medida de 2 x 1\nM²................................ 18.20 VECES\nd).- Puestos semifijos medida de 2 x 2 metros............................ 18.20 VECES\ne).- Puestos semifijos medida de 3 x 3 metros............................ 18.20 VECES\nf).- Puestos semifijos y camiones de comida semifijos hasta 3 x 7 M²... 45.50 VECES\nC). Mercado sobre ruedas................ 26.00 VECES\nIII.-Permiso accidental, tarifa diaria\nA). Vendedores ambulantes:\na).- Por expedición de permiso, medida de 2 x 1 M²....................... 3.38 VECES\nb).- Por expedición de permiso, medida de 2 x 2 M²....................... 3.38 VECES\nB). Puestos semifijos:\na).- Por expedición de permiso, medida de 2 x 1 M²....................... 5.20 VECES\nb).- Por expedición de permiso, medida de 2 x 2 M²....................... 5.20 VECES\nIV.-Expedición de gafetes de control administrativo y de identificación para ejercer el comercio en la vía pública:\nA). Expedición o Reposición de gafete o credencial...................................... 2.6 VECES\nAdultos mayores, jubilados, pensionados y personas con discapacidad, que cuenten con cualquier autorización de las que se refiere el presente Artículo de esta ley, que se encuentre vigente en estas fracciones, debiendo comprobar su condición con en su caso, estudio socioeconómico elaborado por la Secretaría de condición, elaborado por una Institución de Salud Pública.\nAsimismo, Madres Jefas de Familia sin cónyuge o pareja en aptitud de trabajar, que son el único sostén del hogar, con hijo o hijos menores de edad y/o personas con capacidades diferentes, tendrán el 50% (cincuenta por ciento) de descuento, en el pago de los derechos, estipulados en la Fracción II incisos A) y B) y el 100%\n(cien por ciento) de descuento en los casos del inciso C de la citada fracción II, para los cuales se realizará estudio matrimonio.\nDERECHOS POR EL PAGO DE HORARIO EXTENDIDO PARA LA VENTA,\nALMACENAJE Y CONSUMO PÚBLICO DE BEBIDAS ALCOHÓLICAS\nARTÍCULO 25.-Derechos por pago de horario extraordinario de operación de establecimientos que cuenten con permiso para la venta, almacenaje y consumo público de bebidas alcohólicas, por cada hora.\nA).-Bar Turístico............................ 58.50 VECES\nB).-Café Cantante............................ 55.90 VECES\nC).-Discoteca................................ 58.50 VECES\nD).-Centro de Espectáculos................... 58.50 VECES\nE).-Espectáculos públicos, bailes públicos, ferias, variedades y diversiones análogas................................ 36.40 VECES\nF).-Expendio................................. 19.50 VECES\nG).-Billar................................... 39.65 VECES\nH).-Bar Terraza.............................. 43.55 VECES\nI).-Restaurante.............................. 19.50 VECES\nJ).-Restaurante Bar.......................... 39.00 VECES\nK).-Licorería................................ 19.50 VECES\nL).-Bodega................................... 20.80 VECES\nM).-Agencias y Sub-agencias.................. 20.80 VECES\nN).-Depósito................................. 20.80 VECES\nARTÍCULO 25 BIS.-Por visitas de inspección o verificación a respecto de solicitudes de los giros comerciales, industriales y de prestación de servicios, se pagará por revisión a:\nI.-Giros industriales:\nA).-Hasta 500 M2 de superficie.......... 50.00 VECES\nB).-De más de 500 M2 de superficie...... 100.00 VECES\nC).-De más de 5,000 M2 de superficie.... 200.00 VECES\nD).-De más de 10,000 M2 de superficie... 500.00 VECES\nII.-Giros comerciales y de prestación de servicios:\nA).-Hasta 500 M2 de superficie.......... 25.00 VECES\nB).-De más de 500 M2 de superficie...... 50.00 VECES\nC).-De más de 5,000 M2 de superficie.... 100.00 VECES\nD).-De más de 10,000 M2 de superficie... 250.00 VECES\nCAPÍTULO V\nQUE PRESTA LA DIRECCIÓN MUNICIPAL DE PREVENCIÓN, CONTROL Y\nSANIDAD\nARTÍCULO 26.-Los servicios proporcionados por la Dirección\nMunicipal de Prevención, Control y Sanidad, se pagarán en base a la siguiente:\nTARIFA\nUNIDAD DE MEDIDA Y\nACTUALIZACIÓN (UMA) VIGENTE\nI.-Registro de afiliación de control sanitario 8.13 VECES\nII.-Expedición de tarjetas de salud........... 4.88 VECES\nIII.-Reposición de tarjeta de salud........... 4.88 VECES\nIV.-Servicios de laboratorio:\nA).-Pruebas de VIH y VDRL.................. 5.69 VECES\nB).-Cultivos de exudado vaginal, uretral, (gonorrea, monilia, tricomonas) a sexo servidoras................................. 5.69 VECES\nV.-Servicios elementales del departamento de control animal.\nA).-Alimentación de animales capturados, por día.................................... 0.65 VECES\nB).-Desparasitación general................ 0.65 VECES\nC).-Ovario histerectomía en cánidos........ 5.20 VECES\nD).-Orquiectomía en cánidos................ 2.60 VECES\nE).-Consulta............................... 0.65 VECES\nF).-Adopción de animales................... 1.30 VECES\nG).-Multa por captura en vía pública, por primera vez................................ 5.20 VECES\nH).-Observación clínica de animales agresores post mordedura................... 6.50 VECES\nI).-Sacrificio humanitario de animales de compañía, en caso de animales en reincidencia de captura, por término de plazo de observación clínica, o a petición de ciudadano............................... 2.60 VECES\nJ).-Recepción de cadáveres caninos o felinos.................................... 0.65 VECES\nVI.-Certificado de esencia a conductores bajo el influjo del alcohol, psicotrópicos o enervantes, sólo cuando el resultado sea positivo...................................... 32.50 VECES\nCAPÍTULO VI\nQUE PRESTA LA DIRECCIÓN DE RECAUDACIÓN MUNICIPAL\nARTÍCULO 27.-Los propietarios de giros comerciales, industriales personas con discapacidad neuromotora, auditivas, visuales e esta ciudad, podrán ocupar sitio exclusivo de estacionamiento una vez que obtengan autorización escrita, donde se indique el tipo de\nInfraestructura Urbana Municipal. Debiendo pagar mensualmente los derechos por este concepto, de acuerdo a la siguiente clasificación:\nTARIFA\nUNIDAD DE MEDIDA Y\nACTUALIZACIÓN (UMA) VIGENTE\nI.-Para estacionamiento de vehículos:\nA).-Por sitios exclusivos de estacionamiento de vehículos con señalamiento en los cordones de las banquetas, pagarán diariamente, por metro lineal en:\na).-Zona central....................... 0.052 VECES\nb).-Otras zonas........................ 0.033 VECES\nc).-Para transporte público sin itinerario fijo........................ 0.016 VECES\nB).-Por sitios exclusivos de estacionamiento de vehículos en batería, pagarán diariamente, por metro lineal en:\na).-Zona central....................... 0.09 VECES\nb).-Otras zonas........................ 0.0423 VECES\nQuedan exentas del pago por este derecho las personas con discapacidades neuromotoras, auditivas, visuales e intelectuales que soliciten y sea autorizado el estacionamiento exclusivo para vivienda únicamente.\nARTÍCULO 27 BIS.-Son sujetos obligados al pago del derecho por ocupación parcial de la vía pública, los comerciantes establecidos corredor turístico autorizado. anual este derecho, por cada metro cuadrado autorizado para ocupación, en unidades de medida y actualización (UMA) y conforme lo siguiente:\nUNIDAD DE MEDIDA Y\nACTUALIZACIÓN (UMA) VIGENTE\na).-De 0 a 1.80 m2 (por cada M2).............. 55.19 VECES\nb).-De 1.81 a 2.2 m2 (por cada M2)............ 58.19 VECES\nc).-De 2.21 m2 en adelante(por cada M2)........ 61.00 VECES\nAdemás de los requisitos que establezca la Presidencia Municipal, espacio de vía pública, los solicitantes deberán cumplir con los siguientes:\n1) El espacio de vía pública cuya ocupación se solicite, solicitante.\n2) El espacio de vía pública solicitado, deberá permitir el tránsito peatonal sin obstrucción alguna, por lo que en todo momento deberá respetar por lo menos 1.2 metros cuadrados para ello.\n3) Recibo del pago de derechos correspondiente.\nNo podrán expedirse certificados de ocupación de vía pública que se encuentren frente de comercio de terceros.\nARTÍCULO 28.-Los propietarios de vehículos que se estacionen en las zonas de la vía pública, cuyo uso del espacio para estacionamiento esté tarifado mediante aparatos contadores de tiempo o estacionómetros, pagarán:\nI.-Por uso del espacio para estacionamiento tarifado:\nA).-Por la primer hora o fracción del uso del espacio para estacionamiento tarifado: …………. 0.184 VECES\nB).- Por cada media hora adicional o fracción del uso del espacio para estacionamiento tarifado: ………….0.046 VECES\nC).-Personas con capacidades diferentes como neuromotoras, auditivas, visuales e intelectuales, que las zonas de la vía pública, cuyo uso del espacio para estacionarse esté tarifado por cualquier método, quedarán exentos de todo pago correspondiente............ EXENTO\nD).-Por infracción a este artículo, se causará una multa\nControl Vehicular del Municipio de Tijuana; si se liquida la infracción, gozará de un 50% (cincuenta por ciento) de descuento.\nE).-Por retiro de inmovilizador.......... 3.90 VECES\nCAPÍTULO VII\nQUE PRESTA LA DIRECCIÓN DE SERVICIOS PÚBLICOS MUNICIPALES\nARTÍCULO 29.-Los servicios que presta la Dirección de Servicios\nPúblicos Municipales se pagarán en base a la siguiente:\nTARIFA\nUNIDAD DE MEDIDA Y\nACTUALIZACIÓN (UMA) VIGENTE\nI.-Panteones municipales\nA).-Permiso de obra se pagarán por cada uno de los siguientes:\na) Instalación de lápida............ 6.50 VECES\nb) Instalación de cabezal........... 6.50 VECES\nc) Instalación de tres hiladas de bloque para realizar sobre caja......... 6.50 VECES\nd) Instalación de capilla cabezal... 6.50 VECES\ne) Instalación de nicho............. 6.50 VECES\nf) Instalación de mesa.............. 6.50 VECES\ng) Instalación de cordón............ 6.50 VECES\nh) Por alta o revalidación en el padrón de prestadores de servicios de excavación, albañilería y marmolería con vigencia de un año.................................. 3.00 VECES\nB).-Renta de espacio (por seis años) en panteones municipales.................... 10.00 VECES\nC).-Refrendo renta de espacio 5 años más 6.50 VECES\nD).-Reinhumación de restos áridos....... 11.70 VECES\nE).-Exhumación.......................... 7.80 VECES\nF).-Renta de espacios en gaveta individual por seis años en panteones municipales......\n........................................ 45.00 VECES\nG).-Refrendo de renta de espacios en gaveta individual por seis años en panteones municipales............................. 30.00 VECES\nSon solidariamente responsables del pago de los derechos a que se refiere este artículo, las personas físicas y morales que presten los servicios funerarios, de excavación, albañilería, marmolería y quienes mediante gestión o mandato realicen los trámites a nombre de los titulares. acuerdo del Titular de la Oficialía 01 del Registro Civil que corresponda, cuando el occiso y los deudos sean indigentes. respectivos. de las 16:00 horas o días festivos y domingos en que se cierran los panteones, se pagará el doble de las tarifas establecidas en este artículo.\nII.-Por ocupación temporal de la vía pública:\nA).-Con cobertizos o casetas en paradas de transporte público, se pagará anualmente..... 13.00 VECES\nB).-Con bancas publicitarias, se pagará anualmente por metro lineal.................. 5.20 VECES\nIII.-Por señalamientos y pinturas:\nA).-Se pagará por el poste soporte de la señal\n.......................................... 9.75 VECES\nB).-Se pagará por la señal................ 9.75 VECES\nC).-En caso de reposición por daño al poste, se pagará por el mismo, el valor de mercado al momento de reposición.\nD).-En caso de la reposición por daño a la señal se pagará por la misma, el valor de mercado al momento de reposición.\nE).-Se pagará anualmente por la pintura de acuerdo con lo siguiente:\na).-De 1 a 2.99 M...................... 4.29 VECES\nb).-De 3 a 5.99 M...................... 8.58 VECES\nc).-De 6 a 8.99 M...................... 12.87 VECES\nd).-De 9 a 11.99 M..................... 17.16 VECES\ne).-De 12 o más M...................... 21.45 VECES\nF).-Personas con discapacidades neuromotoras, auditivas, visuales e intelectuales, sólo en vivienda.\nIV.-Por recolección y disposición de residuos sólidos urbanos que sean contratados por personas físicas o morales.\nA) Cuando el servicio de recolección a giros comerciales, industriales o de servicio tenga carácter de extraordinario; públicos municipales, dependiendo de la ubicación, superficie del terreno, topografía, periodicidad de servicio y otros elementos que impacten en el costo del mismo. espectáculos eventuales como circos, ferias, exposiciones, etc., o cualquier espectáculo público, así como la recolección venta.\nB) La contratación del servicio de recolección de residuos sólidos urbanos, que tenga el carácter de ordinario sólo se proveerá, en su caso a pequeños generadores (según\nSólidos Urbanos). Éstos podrán optar a su conveniencia, por la contratación del servicio de recolección que ofrece el\nAyuntamiento a través de la Dirección de servicios públicos municipales, únicamente en rutas y horarios establecidos.\na).-Por servicio domiciliado en ruta cuya periodicidad sea de una vez por semana, se pagará anualmente y de forma anticipada 28.00 VECES\nb).-Por servicio domiciliado en ruta cuya periodicidad sea mayor a una vez por semana, se pagará anualmente y de forma anticipada 56.00 VECES\nC).-Por traslado de residuos sólidos urbanos al de la recepción de dichos residuos en sitios dispuestos y autorizados por la Autoridad\nMunicipal, se pagará por tonelada lo siguiente 10.00 VECES casa habitación o comercial; no se recepcionarán aquellos residuos que sean peligrosos, manejo especial o generados a partir de una actividad industrial.\nV.-Los derechos por servicios de limpia y mantenimiento en domicilios particulares, terrenos baldíos, unidades habitacionales, vía pública y otros, serán fijados en cada caso públicos municipales, dependiendo de la ubicación, superficie y incluir los servicios de demolición de construcciones.\nVI.-Reposición de bienes propiedad del ayuntamiento a cargo de la Dirección de servicios públicos municipales.\nLa reposición o reparación de bienes dañados a cargo de la\nDirección de servicios públicos municipales que se enlistan a continuación, y que sean propiedad del Ayuntamiento de Tijuana, serán fijados por la Dirección de servicios públicos municipales, de acuerdo con el catálogo de precios unitarios emitido por la\nDirección de obras e infraestructura urbana municipal.\nA).-Por daños al alumbrado público, serán fijados en cada caso, de acuerdo al valor de mercado al momento del daño.\nB).-Por daños a los semáforos serán fijados en cada caso, de acuerdo al valor de mercado al momento del daño.\nC).-Por daños a las áreas verdes serán fijados en cada caso, de acuerdo al valor de mercado al momento del daño.\nD).-Por daños a monumentos serán fijados en cada caso, de acuerdo al valor del mercado al momento del daño.\nE).-Por daños a fuentes serán fijados en cada caso, de acuerdo al valor de mercado al momento del daño.\nF).-Por daños a los panteones serán fijados en cada caso, de acuerdo al valor de mercado al momento del daño.\nG).-Por daños al señalamiento vial serán fijados en cada caso, de acuerdo al valor de mercado al momento del daño.\nH).-Por grafiti serán fijados en cada caso, de acuerdo al valor de mercado al momento del daño.\nI).-Por daños a los vehículos utilitarios serán fijados en cada caso, de acuerdo al valor de mercado al momento del daño.\nVII.-Servicios de supervisión a los siguientes rubros:\nA).-Para evaluar daños a bienes a cargo de la días y horas hábiles................... 6.50 VECES\nB).-Para evaluar daños a bienes a cargo de la\nDirección de servicios públicos municipales en días y horas inhábiles................. 6.50 VECES\nC).-Para evaluar solicitudes de permiso para tala o poda de árboles................. 6.50 VECES\nD).-Para inspeccionar fraccionamientos en proceso de entrega-recepción al Ayuntamiento de\nTijuana...................................... 6.50 VECES\nVIII.- Derechos por servicios de forestación\nA).-Por poda de árbol y arbusto en vía pública se pagará de acuerdo a lo siguiente:\na).-Poda con herramienta manual de pieza menor de 3.00 m. de altura (copa de 3.00 a\n4.00 m.), incluye: herramienta menor, realización del trabajo, limpieza, retiro y traslado del producto de la poda.... 15.60 VECES\nb).-Poda con maquinaria y equipo a pieza mayor a 3.00 m. y menor a 11.00 m. (copa de\n8.00 a 11.00 m.), incluye: grúa, equipo especial y herramienta menor, mano de obra, limpieza y retiro del producto de la poda\n..................................... 66.30 VECES\nB).-Por tala de árbol y arbusto en vía pública se pagará de acuerdo a lo siguiente:\na).-Tala con herramienta manual de pieza menor de 3.00 m de altura (copa de 3.00 a\n4.00 m.), incluye: herramienta menor, realización del trabajo, limpieza, retiro y traslado del producto de la tala..... 23.40 VECES\nb).-Tala con maquinaria y equipo a pieza mayor a 3.00 metros y menor a 6.00 metros\n(copa de 4.00 a 8.00 metros), incluye: grúa, equipo especial y herramienta menor, mano de obra, limpieza y retiro del producto de la tala................................. 66.30 VECES\nc).-Tala con maquinaria y equipo a pieza mayor a 6.00 metros y menor a 9.00 metros\n(copa de 8.00 a 11.00 metros), incluye: grúa, equipo especial y herramienta menor, mano de obra, limpieza y retiro del producto de la tala.... 163.77 VECES\nd).-Tala con maquinaria y equipo a pieza de 9.00 metros o mayor (copa de 11.00 metros o más), incluye: grúa, equipo especial y herramienta menor, mano de obra, limpieza y retiro del producto de la tala.............................. 369.11 VECES\nC).-Por tala de árbol y arbusto urgente en vía pública se pagará de acuerdo a lo siguiente:\na).-Tala con herramienta manual de pieza menor de 3.00 m de altura (copa de 3.00 a 4.00 m.), incluye: herramienta menor, realización del trabajo, limpieza, retiro y traslado del producto de la tala\n..................................... 123.50 VECES\nb).-Tala con maquinaria y equipo a pieza mayor a 3.00 metros y menor a 6.00 metros\n(copa de 4.00 a 8.00 metros), incluye: grúa, equipo especial y herramienta menor, mano de obra, limpieza y retiro del producto de la tala.............. 239.20 VECES\nc).-Tala con maquinaria y equipo a pieza mayor a 6.00 metros y menor a 9.00 metros\n(copa de 8.00 a 11.00 metros), incluye: grúa, equipo especial y herramienta menor, mano de obra, limpieza y retiro del producto de la tala............. 478.40 VECES\nd).-Tala con maquinaria y equipo a pieza de 9.00 metros o más (copa de 11.00 metros o más), incluye: grúa, equipo especial y herramienta menor, mano de obra, limpieza y retiro del producto de la tala............................. 956.00 VECES\nD).-Por transportar los productos de tala o poda de árboles y arbustos, se pagará de acuerdo con el volumen de producto y la distancia del lugar de la poda o tala a los sitios de disposición final autorizados por la Dirección de Servicios\nPúblicos Municipales.\nIX.-Derecho por servicios de alumbrado público\nEs objeto de este derecho, la prestación del servicio de alumbrado público, incluyendo su operación, ampliación, rehabilitación, reposición y mantenimiento, que se presta a través del Ayuntamiento de Tijuana, en la vía pública, en calles, avenidas, bulevares, caminos vecinales, plazas, parques, jardines y otros lugares de uso común, a través de la red de alumbrado público en el Municipio de Tijuana, Baja\nCalifornia.\nSon sujetos obligados al pago de este derecho, los refiere el párrafo anterior, propietarios o poseedores de inmuebles en el Municipio.\nA)- Este derecho se causará mensualmente conforme a la cuota fija que, en Unidad de Medida y Actualización (UMA), se representa para el Municipio prestar este servicio:\nCUOTA\na).-Cuota Única......................... 0.45 VECES/MES\nLa cuota del presente derecho se determinó y aprobó, tomando mismo, considerando el costo por el suministro de energía eléctrica para la prestación del servicio, los costos por la operación, mantenimiento y reposición del alumbrado público, incluyendo gastos administrativos y sueldos y salarios del personal, involucrados directamente con dicho servicio. Lo anterior en cumplimiento a los principios establecidos en el artículo 31 fracción IV de la Constitución\nPolítica de los Estados Unidos Mexicanos, tomando en cuenta los beneficiarios del servicio en el Municipio.\nB).- El pago deberá realizarse dentro de los primeros 10 días siguientes al mes en que se cause, en las oficinas recaudadoras municipales y demás instancias o establecimientos autorizados para tal efecto.\nEl citado plazo y lugar de pago, podrá modificarse o ampliarse en beneficio de los contribuyentes, cuando exista acuerdo entre el Municipio con otras instancias públicas, que permitan simplificar el entero de la contribución. Para tal efecto, las instancias competentes del Municipio podrán indicado con anterioridad.\nC).-Los ingresos que se perciban por el derecho establecido en esta sección, se destinarán prioritariamente al pago de conceptos que se requieran para el debido servicio, operación\nMunicipio, incluyendo su ampliación y renovación, así como, en su caso, rubros de sueldos y honorarios relacionados con este servicio.\nCAPÍTULO VIII\nPÚBLICA\nARTÍCULO 30.-Los derechos por los servicios de planeación para la municipal de administración de la vía pública, se pagarán, previo al inicio del trámite, de conformidad a lo siguiente:\nTARIFA\nUNIDAD DE MEDIDA Y\nACTUALIZACIÓN (UMA) VIGENTE\nI.-Por análisis y emisión de factibilidad de opinión técnica para autorización de cierres de circuito, lanzaderas y zonas de ascenso y descenso, a solicitud del interesado, así como por análisis y emisión de factibilidad de opinión técnica de congruencia para la ubicación o utilización de sitios exclusivos para el transporte público y otros, incluye la definición de las características geométricas, a solicitud\nII.-Por análisis y emisión de autorización para habilitado y rehabilitado con pintura y son cierres de circuito, sitios exclusivos, en lo específico............................... 36.00 VECES\nIII.-Copia certificada o cotejo de documentos oficiales y otros emitidos por la Dirección:\nA).-Cotejos de documentación:\n1.-Cotejo de boleta de infracción.... 3.00 VECES\n2.-Cotejo de archivo................ 3.00 VECES\nIV.-Servicios de vigilancia de transporte de carga, mediante escolta de dos inspectores y una patrulla, por traslado dentro de la ciudad..... 22.00 VECES\nV.-Expedición de anuencia mensual por instalación de rotulo de publicidad por unidades de transporte en general.......................... 9.00 VECES\nVI.-Derechos por concepto de uso de lanzadera\n“Rosas Magallón”, por las unidades del transporte público por cada unidad del transporte público por día........................................ 0.30 VECES\nCAPÍTULO IX\nQUE PRESTA LA DIRECCIÓN DE ADMINISTRACIÓN URBANA\nARTÍCULO 31.-Los derechos por revisión, análisis y verificación de anteproyectos y proyectos para construcción de obra nueva, ampliación, modificación, reparación, demolición, ampliación y traslado de: oficinas, comercios, casas móviles, y equipo pesado, así como ocupación de la vía pública, factibilidades, peritajes, registros, certificaciones, declaratorias, supervisión, opiniones y dictámenes técnicos, incluyendo fraccionamientos, movimientos de tierra, subdivisiones, relotificaciones, fusiones, usos del suelo, anuncios, rótulos o similares, instalación de antenas o mástiles, comerciales y permisos de operación, deberán ser cubiertos por los posteriormente, excepto cuando se trate de servicios solicitados\nCentralizada y Descentralizada, quienes quedarán exentos de pago.\nMunicipio de Tijuana, se otorgarán los siguientes beneficios para la construcción de vivienda del tipo económico de hasta 63,000\nUDIS apoyada por diferentes instituciones públicas o privadas; se exceptuarán de pago de derechos, por la revisión de anteproyecto, revisión de proyecto ejecutivo de los trámites de fraccionamiento, los permisos de las licencias de construcción, los permisos para la constitución de los regímenes de condominio, así como el 50%\n(cincuenta por ciento) de los derechos de urbanización en desarrollos que cuenten al menos con el 25% (veinticinco por ciento)de viviendas de tipo económico y el resto de hasta un máximo de 90,000 UDIS, y que presente, ya sea; copia del crédito con cualquiera de éstas, así como del contrato de venta total, o bien, plano de sembrado con prototipos de vivienda por construir acompañados de avalúo certificado de cada prototipo por autorizar no pudiendo ser modificado posteriormente el proyecto para incumplir esta proporción de viviendas, o de lo contrario, se deberán pagar los derechos correspondientes, así como los demás servicios que presta la Subdirección de Control Urbano.\nTARIFA\nUNIDAD DE MEDIDA Y\nACTUALIZACIÓN (UMA) VIGENTE\nEDIFICACIÓN\nI.- Por revisión, análisis y verificación de proyecto y otorgamiento, para licencia de construcción de obra nueva y ampliación de edificios habitacionales, comerciales, industriales y otros; se pagarán, previo al inicio de los trámites, hasta por 2 revisiones del mismo proyecto de acuerdo a la siguiente tabla:\nA).-Casa habitación y vivienda unifamiliar, tratándose de arrendamiento:\na).-Nueva, de hasta 60.00 M² de construcción, por M².................... 0.043 VECES\nb).-Nueva, mayor de 60.00 M² y de hasta\n90.00 M² de superficie de construcción, por M².................................. 0.215 VECES\nc).-Nueva, mayor de 90.00 M² y de hasta\n500.00 M² de superficie de construcción, por M².................................. 0.29 VECES\nd).-Nueva, mayor de 500.00 M² y de hasta\n6,000.00 M² de superficie de construcción, por M².................................. 0.44 VECES\ne).-Ampliación, en cualquier superficie de construcción, por M²................... 0.44 VECES\nf).-Nueva, mayor de 6,000.00 M² de superficie de construcción por M² de construcción............................ 0.49 VECES\nB).-Otras edificaciones e instalaciones, nuevas o ampliación:\na).-Habitacionales, unifamiliares y multifamiliares con fines de comercialización y/o arrendamiento, por unidad de vivienda:\n1).-Hasta 60.00 M² de superficie de construcción, por M².................. 0.07 VECES\n2).-Mayor de 60.00 M² y de hasta 90.00\nM², por M²............................ 0.235 VECES\n3).-Mayor de 90.00 M² y hasta de 300.00\nM², por M²............................ 0.358 VECES\n4).-Mayor de 300.00 M², por M²........ 0.43 VECES\nb).-Casas móviles en cualquier superficie, por casa tipo por M²................... 0.27 VECES\nc).-Hoteles, moteles, comercios, oficinas, salas de espectáculos, centros de reunión, hospitales, baños públicos, estacionamientos públicos, y otros, por M² 0.525 VECES\nd).-Por revisión, análisis, verificación y emisión de licencias de construcción y/o ampliación industrial hasta 2da revisión, por M².................................. 0.70 VECES\ne).-Para culto religioso e iglesias, por\n0.268 VECES\nf).-Cementerios y panteones sobre la superficie de construcción techada, por M²\ng).-Para educación, guarderías y jardines de niños, y primaria por M²............. 1.30 VECES\nh).-Para educación privada, guarderías, jardines de niños, primaria, secundaria, preparatoria y universidad por M²....... 2.60 VECES\ni).-Para la cultura, deporte y espectáculos deportivos, recreación y parques de diversiones sobre la superficie de construcción del uso y graderías, por\nM²...................................... 0.33 VECES\nj).-Para infraestructura especial, distribución de gas butano, estaciones de servicio y estaciones de carburación se cobrará sobre la superficie de construcción del uso especial, por M2... 6.50 VECES\nk).-Obra Pública: todo tipo de edificación promovida, realizada y en propiedad de cualquiera de los tres niveles de gobierno EXENTO\nC).-Edificaciones provisionales o temporales con duración máxima de hasta seis meses, destinadas a circo, espectáculos, convenciones, exposiciones, carpas, casas muestra; nuevas y ampliación, a solicitud del interesado o dependencia de gobierno, por cada 200.00 M² o fracción............ 7.15 VECES\nD).-Cercos, bardas y muros de contención; obra nueva y ampliación siempre que no forme parte integral de la edificación.\na).-Cerco de madera, lámina, malla ciclónica y reja metálica, por metro lineal.................................. 0.20 VECES\nb).-Bardas:\n1).-Hasta de 2.00 M de altura, por metro lineal................................ 0.65 VECES\n2).-Mayores de 2.00 a 5.00 M de altura, por metro lineal...................... 1.30 VECES\n3).-Mayores de 5.00 M de altura por metro lineal.......................... 3.90 VECES\nc).-Por la expedición de licencias para instalación, regularización, reubicación y/o ampliación de antenas o mástiles para telefonía y medios de comunicación; pagarán derechos anuales conforme a las siguientes tarifas:\n1)Por la Instalación o reubicación de la radiobase, estructura, mástil o similar:\na) Hasta 24 M de altura............. 600.00 VECES\nb) Mayores 24 M de altura........... 900.00 VECES\nc) Aviso de terminación de obra de instalación,....................... 40.00 VECES\n2)Por la regularización:\na) Hasta 24 M de altura............. 900.00 VECES\nb) Mayores 24 M de altura........... 1,350.00 VECES\nc) Aviso de terminación de obra de instalación......................... 50.00 VECES\n3)Por revalidación de licencia de instalación o reubicación de la radiobase, estructura, mástil o similar:\na) Hasta 24 M de altura............. 300.00 VECES\nb) Mayores 24 M de altura........... 450.00 VECES\n4)Por la colocación de cada antena de telefonía celular o cualquier elemento similar o accesorio que afecte el peso de una estructura, mástil, torre o inmueble\n...................................... 25.00 VECES\nd).-Muros de contención:\n1).-Hasta de 2.00 M de altura, por metro lineal................................ 2.00 VECES\n2).-Mayores de 2.00 a 5.00 M de altura, por metro lineal...................... 3.00 VECES\n3).-Mayores de 5.00 M de altura por metro lineal.......................... 5.00 VECES\ne).-Plantas de tratamiento, por M²\n........................................ 0.34 VECES\nf).-Por revisión y verificación de proyecto de taludes con concreto lanzado, geomalla y otro sistema por metro lineal 2.50 VECES\nII.-Por revisión, análisis y verificación de proyecto y emisión de licencia para modificación y reparación, incluyendo remodelación, restauración y reconstrucción de edificios habitacionales, comerciales, industriales y otros; se pagará previo al inicio de los trámites, por metro cuadrado de construcción, hasta por 2 revisiones del mismo proyecto de acuerdo a la siguiente tabla:\nA).-Para uso habitacional, por M².. 0.18 VECES\nB).-Para uso de hoteles, moteles, comercios, oficinas, salas de espectáculos, centros de reunión, hospitales, baños públicos, estacionamientos públicos, industriales y otros, por M²............. 0.30 VECES\nC).-Para edificios que se encuentran en el Catálogo de la Sociedad de Historia de Tijuana, A.C., así como los que menciona el Programa de Desarrollo\nUrbano del Centro de Población de\nTijuana, Baja California, 2002-2005, considerados como patrimonio histórico de la ciudad y los susceptibles de declaratoria que tengan más de 50 años de haberse producido y todos aquellos bienes culturales declarados\nPatrimonio Cultural de Baja\nCalifornia, con la finalidad de restauración y rescate del edificio, parcialmente o en su totalidad...... EXENTO\nIII.-Por revisión, análisis de proyecto y verificación de obra, construcción, para cualesquiera de los tipos de obra e instalaciones descritos en las fracciones I) y II) inmediatas anteriores de este artículo, que hayan sido ejecutadas total o parcialmente sin contar con las licencias correspondientes; se pagará previo al inicio del trámite, 50% (cincuenta por ciento) indicada en la tabla correspondiente a dichas fracciones.\nIV.-Por prórroga de licencias de construcción de edificios e instalaciones, incluyendo verificación en campo:\nA).-Habitacionales:\na).-Hasta de 90.00 M² de construcción................ 10.00 VECES\nb).-Mayor de 90.00 M² y hasta de\n250.00 M² de construcción...... 18.00 VECES\nc).-Mayor de 250.00 M² y hasta de\n500.00 M² de construcción...... 30.00 VECES\nd).-Mayor de 500.00 M² y hasta de\n1,000.00 M² de construcción... 50.00 VECES\ne).-Mayor de 1,000.00 M² y hasta de 5,000.00 M² de construcción. 100.00 VECES\nf).-Mayor de 5,000.00 M² de construcción................... 250.00 VECES\nB).-Para uso de hoteles, moteles, comercios, oficinas, salas de espectáculo, centros de reunión, hospitales, baños públicos, estacionamientos públicos, y otros.\na).-Hasta de 100.00 M²......... 20.00 VECES\nb).-Mayor de 100.00 M² y hasta de\n500.00 M²..................... 30.00 VECES\nc).-Mayor de 500.00 M² y hasta de\n1,000 M²...................... 200.00 VECES\nd).-Mayor de 1,000.00 M² de construcción................... 400.00 VECES\nC).-Para industrias:\na).-Hasta de 500.00 M² de construcción................... 200.00 VECES\nb).-Mayor de 500.00 M² y hasta de\n5,000.00 M² de construcción... 300.00 VECES\nc).-Mayor de 5,000.00 M² de construcción................... 500.00 VECES\nD).-Para edificios e instalaciones de otros tipos o usos............. 50.00 VECES\nE).-Para cercos y bardas............ 3.00 VECES\nF).-Para muros de contención....... 5.00 VECES\nG).-Por prorroga de licencia de demolición hasta por 6 meses.... 5.00 VECES\nV.-Por revisión y verificación de documentos y planos, y emisión instalaciones; se pagará, previo al inicio de los trámites, hasta por 2 revisiones del mismo proyecto de acuerdo a la siguiente tabla:\nA).-Edificaciones hasta de 50.00 M². 8.93 VECES\nB).-Edificaciones mayores de 50.00 M² hasta 100.00 M²................ 17.88 VECES\nC).-Mayores de 100.00 M²............ 26.00 VECES\nD).-Cercos, bardas y muros de contención, de 10.00 Ma 30.00 M.\n............................... 8.93 VECES\nE).-Cercos, bardas y muros de contención, mayores de 30.00 M 17.88 VECES\nF).-Cordón de banqueta o guarnición, de hasta 3.00 M................ 2.68 VECES\nG).-Cordón de banqueta o guarnición, mayor de 3.00 M y hasta de 10.00\nM.............................. 8.93 VECES\nH).-Cordón de banqueta o guarnición mayor de 10.00 M............... 14.30 VECES\nI).-Banquetas, con superficie de hasta\n3.00 M²........................ 5.36 VECES\nJ).-Banquetas, con superficie mayor de\n3.00 M² y hasta de 10.00 M².... 8.93 VECES\nK).-Banquetas, con superficies mayores de 10.00 M².................... 14.30 VECES\nL).-Arroyo de vialidades, con superficies de hasta 3.00 M².. 5.36 VECES\nM).-Arroyo de vialidades, con superficies mayores de 3.00 M² y 14.30 VECES hasta de 10.00 M².............\nN).-Arroyo de vialidades, con superficies mayores de 10.00 M² 4.88 VECES\nVI.-Servicios de elaboración de nota aclaratoria no incluida en el trámite original........................... 7.15 VECES\nVII.-Modificación de proyecto para obtención de licencia de construcción:\nA).-Menor de 200.00 M².............. 10.40 VECES\nB).-De 201.00 M² a 500.00 M²....... 17.88 VECES\nC).-De 501.00 M² a 1,000.00 M²..... 44.68 VECES\nD).-Mayores de 1,000.00 M².......... 53.63 VECES\nVIII.-Factibilidad de licencia de construcción, revisión y análisis de prototipo de vivienda:\nA).-Hasta de 60.00 M²............... 19.5 VECES\nB).-Mayores de 60.00 M²............. 35.75 VECES\nIX.-Por peritajes y dictámenes técnicos sobre inmuebles; se pagará, previo al inicio de los trámites, de acuerdo con la siguiente tabla:\nA).-Dictamen técnico ocular en condiciones ruinosas y peligrosas, se cobrará de la siguiente manera:\na).-Por vivienda............... 10.40 VECES\nb).-Por edificio hasta 6 niveles. 32.50 VECES\n1.-Por nivel excedente.... 2.60 VECES\nc).-Comercial y/o de servicio:\n1.-Con superficie de hasta\n200.00 M²................ 19.50 VECES\n2.-Con superficie de 200.01\nM2 hasta 500.00 M2....... 26.00 VECES\n3.-Mayores a 500.00 M2... 45.50 VECES\nd).-Industrial:\n1.-Con superficie de hasta\n1,000.00 M2.............. 45.50 VECES\n2.-Mayores a 1,000.00 M2. 78.00 VECES\ne).-Usos especiales:\nDistribución de Gas Butano, Estaciones de Servicio y\nEstaciones de Carburación se cobrará por unidad (no incluye estudios especializados, ni prueba de resistencia de materiales). 78.00 VECES\nB).-Dictamen técnico ocular sobre el estado físico aparente (daños y evaluación del riesgo), se cobra de la siguiente manera (no incluye estudios especializados):\na).-Habitacional:\n1.-Vivienda unifamiliar.. 10.40 VECES\n2.-Vivienda en edificio.. 15.60 VECES\n3.-Edificio hasta 4 niveles 32.50 VECES\n4.-En edificio mayor de 4\nNiveles por nivel excedente 5.20 VECES\nb).-Comercial y/o de servicio:\n1.-Con superficie de hasta\n200 M2............... 19.50 VECES\n2.-Con superficie de 200.01\nM2 hasta 500.00 M2.... 26.00 VECES\n3.-Mayores a 500.00 M2... 45.50 VECES\nc).-Industrial:\n1.-Con superficie de hasta\n1,000.00 M2.......... 45.50 VECES\n2.-Mayores a 1,000.00 M2.. 78.00 VECES\nd).-Usos especiales:\nDistribución de gas butano, estaciones de servicio y estaciones de carburación se cobrará por unidad (no incluye estudios especializados, ni prueba de resistencia de materiales).\n.......................... 78.00 VECES\nC).-Dictamen técnico ocular sobre el estado físico aparente de bardas y muros de contención, por cada 50.00 metros lineales o fracción.......... 6.50 VECES\nD).-Dictamen técnico ocular de ocupación de escuelas, incluye revisión de proyecto y verificación(no incluye estudios especializados, ni prueba de resistencia de materiales)........ 26.81 VECES\nE).-Dictamen técnico ocular sobre las condiciones físicas que restringen el aprovechamiento de un predio para edificación......................... 26.81 VECES\nF).-Dictamen técnico ocular sobre el estado físico aparente de edificios, inmuebles solicitados por los tres órdenes de gobierno (no incluye estudios especializados, ni prueba de resistencia de materiales)......... EXENTO\nG).-Dictamen técnico ocular sobre el estado físico aparente de edificios, ocupación del inmueble por cada 100 M2 de construcción o fracción (no incluye estudios especializados, ni pruebas de resistencia de materiales)......... 15.60 VECES\nH).-Evaluación de daños en edificaciones:\nPor revisión de documentación presentada, recabar información adicional de los archivos de esta\nDirección, y análisis, emitir un documento de resolución definitiva, en caso de afectación, daños y/o riesgo en edificaciones (no incluye estudios especializados, ni prueba de resistencia de materiales)................... 13.00 VECES\nX.-Por revisión de anteproyecto a solicitud del particular y/o promotor, para la construcción de edificios de todo tipo; se pagará previo al inicio del trámite, hasta por 2 revisiones del mismo proyecto de acuerdo con la siguiente tabla:\nA).-Hasta de 500.00 M² de construcción. 17.88 VECES\nB).-Mayor de 500.00 M² y hasta de\n1,000.00 M² de construcción. 44.68 VECES\nC).-Mayores de 1,000.00 M² de construcción................. 53.63 VECES\nXI.-Por registros como director de obra, director de proyecto y demás corresponsables; se pagará, previo al inicio del trámite, de acuerdo con la siguiente tabla:\nA).-Registro inicial (alta)......... 13.00 VECES\nB).-Revalidación anual (peritos sin trámites pendientes)........... 10.40 VECES\nC).-Revalidación anual (peritos con trámites inconclusos).......... 26.00 VECES\nD).-Por cambio de perito de obra.... 26.81 VECES\nXII.-Por ocupación temporal de la vía pública por día, se pagará previo al inicio del trámite, mínimo por tres días, de acuerdo con la siguiente tabla, excepto para el inciso d):\nA).-Para depósito de materiales de construcción:\na).-Hasta de 50.00 M² de ocupación, por día....... 3.90 VECES\nb).-Mayor de 50.00 M² y hasta de\n100.00 M², por día....... 6.50 VECES\nc).-Por metro cuadrado adicional de ocupación a los primeros 100.00\nM², por día.................... 0.65 VECES\nd).-En zonas con Estacionómetros, por día....................... 3.58 VECES\nB).-Por ocupación temporal de la vía pública por semana, se pagará previo al inicio del trámite, mínimo por una semana de acuerdo a la siguiente tabla:\na).-Para depósito de materiales de construcción.\n1).-Hasta de 50.00 M² de ocupación, por semana 10.4 VECES\n2).-Mayor de 50.00 M² y hasta de 100.00 M², por semana.............. 13.00 VECES\n3).-En zonas con\nEstacionómetros, por semana.............. 23.66 VECES\nC).-Para movimientos y maniobras con equipos de carga, izaje y/o montaje, incluyendo la zona o área acordonada para seguridad, por semana o fracción, excepto para el inciso d):\na).-Hasta 50.00 M² de ocupación, por semana..................... 13.00 VECES\nb).-Mayor de 50.00 M² y hasta\n100.00 M² de ocupación, por semana 19.50 VECES\nc).-Por M² adicional de ocupación a los primeros 100.00 M², por semana......................... 1.30 VECES\nd).-En zonas con estacionómetros, por cajón, por día............. 7.15 VECES\ne).-De requerirse los servicios de oficiales de seguridad pública para acordonamiento, se pagarán los derechos correspondientes de acuerdo a lo dispuesto en el\nArtículo 36 de esta Ley.\nXIII.-Por certificación de terminación de obra y/o instalaciones, y licencia o autorización; se pagará previo al inicio del trámite, hasta por 2 revisiones del mismo proyecto por edificio o condominio y de acuerdo con la siguiente tabla:\nA).-Para uso habitacional:\na).-Hasta de 60.00 M² de construcción................... 6.50 VECES\nb).-Mayor de 60.00 M² y hasta de\n90.00 M² de construcción....... 10.01 VECES\nc).-Mayor de 90.00 M² y hasta de\n500.00 M² de construcción..... 21.45 VECES\nd).-Mayores de 500.00 M² de construcción y hasta de 6,000.00\nM²............................. 35.75 VECES\ne).-Mayores de 6,000.00M² de construcción por M² de construcción adicional........ 0.029 VECES\nB).-Para uso de hoteles, moteles, comercios, oficinas, salas de espectáculos, centros de reunión, hospitales, baños públicos, estacionamientos públicos, y otros usos:\na).-Hasta de 60.00 M² de construcción................... 11.44 VECES\nb).-Mayor de 60.00 M² y hasta de\n100.00 M² de construcción..... 21.45 VECES\nc).-Mayor de 100.00 M² y hasta de\n1,000.00 M² de construcción.... 35.75 VECES\nd).-Mayor de 1,000.00 M² de construcción.................. 57.20 VECES\nC).-Para uso en educación, cultura, salud, deporte y espectáculos deportivos, recreación y parques de diversiones, y otros usos:\na).-Hasta de 500.00 M² de construcción................... 17.88 VECES\nb).-Mayor de 500.00 M² y hasta de\n1,000.00 M² de construcción.... 26.81 VECES\nc).-Mayor de 1,000.00 M² de construcción.................. 35.75 VECES\nD).-Para uso industrial:\na).-Hasta de 100.00 M² de construcción................... 26.81 VECES\nb).-Mayor de 100.00 M² y hasta de\n500.00 M² de construcción..... 44.68 VECES\nc).-Mayor de 500.00 M² y hasta de\n5,000.00 M² de construcción.... 62.56 VECES\nd).-Mayor de 5,000.00 M² de construcción.................. 64.35 VECES\nE).-Para edificios ubicados fuera de la mancha urbana se cobrará, sobre la tarifa anterior, un 10% (diez por ciento) adicional.\nF).-Obra pública: todo tipo de edificación promovida realizada y en propiedad de la Federación, Estado o Municipio............ EXENTO\nXIV.-Por análisis de solicitudes y emisiones de autorizaciones para constituir regímenes de propiedad en condominio de inmuebles; hasta por 2 revisiones del mismo proyecto se pagarán de acuerdo a la siguiente tabla y según las condiciones que a continuación se mencionan; en caso de no presentar el comprobante de haber enterado en la Recaudación de rentas municipal el monto total de los derechos en un plazo de 20 días hábiles a partir de la fecha de su notificación, quedará sin efecto la autorización y se suspenderá el trámite correspondiente.\nA).-Por análisis y dictamen de factibilidad de anteproyecto del régimen de propiedad en condominio sobre conjuntos sin construir, para uso habitacional, comercial, industrial o mixto:\na).-Por conjuntos de hasta diez unidades...................... 23.60 VECES\nb).-Por cada unidad que exceda de las diez primeras.............. 2.35 VECES\nB).-Por análisis y dictamen de factibilidad de conversión conjuntos habitacionales, comerciales, industriales o mixtos, ya construidos:\na).-En conjuntos de hasta diez unidades....................... 31.46 VECES\nb).-Por cada unidad que exceda de las diez primeras.............. 3.15 VECES\nC).-Por declaratoria para la constitución de régimen de propiedad en condominio de inmuebles o conjuntos, por cada vivienda, departamento, casa o local:\na).-Por cada unidad habitacional de tipo:\n1).-Interés social....... 3.15 VECES\n2).-Popular............... 4.72 VECES\n3).-Nivel medio........... 7.07 VECES\n4).-Nivel residencial.... 10.61 VECES\nb).-Por cada unidad de tipo comercial o industrial......... 28.60 VECES\nD).-Por verificación y certificación de memorias descriptivas de viviendas, departamento, casas o locales comerciales, pertenecientes a condominios:\na).-Por la primera revisión:\n1).-Por conjuntos de hasta diez unidades............. 25.74 VECES\n2).-Por cada unidad que exceda de las diez primeras\n.......................... 2.35 VECES\nb).-Por revisiones subsecuentes:\n1).-Por conjuntos de hasta diez unidades............. 12.87 VECES\n2).-Por cada unidad que exceda de las diez primeras 1.18 VECES\nc).-Por revisión de proyecto de condominio maestro............. 28.60 VECES\nE).-Por constancia de cumplimiento de requisitos para traslación de dominio en condominios:\na).-Por régimen, cada vez que se solicite....................... 23.60 VECES\nb).-Por régimen constituido sobre inmuebles construidos con un proyecto único, en un mismo conjunto inmobiliario y que sea susceptible de expedirse la constancia en un sólo documento que incluya varios regímenes:\n1).-Por el primer régimen. 17.62 VECES\n2).-Por cada régimen subsecuente al primero.... 1.89 VECES\nF).-Por constancia para cancelación de fianzas que en condominios:\na).-Por primera unidad......... 23.60 VECES\nb).-Por cada unidad que exceda de la primera................ 2.35 VECES\nG).-Por constancia para cancelación de fianza que garantice la terminación de las obras en áreas privativas y comunes en condominios.................... 15.73 VECES\nH).-Por certificación de libros de actas de asamblea de condominios\n............................... 3.15 VECES\nI).-Cobro para modificaciones de régimen de condominio:\na).-Por declaratoria modificada de régimen de propiedad en condominio de inmuebles o conjuntos, ya constituidos, sin afectar áreas comunes ni incrementar la superficie total del inmueble, por cada vivienda, departamento o local comercial modificados o resultantes de la modificación, lo que resulte mayor y cambio de nomenclatura:\n1).-Por cada unidad habitacional de tipo:\nI).-Interés social.. 1.053 VECES\nII).-Popular......... 1.40 VECES\nIII).-Nivel medio... 2.123 VECES\nIV).-Residencial.... 3.193 VECES\n2).-Comercial e industrial 9.01 VECES\nb).-Por declaratoria modificada de régimen de propiedad en condominio de inmuebles o conjuntos, ya constituidos cuando se afecten o modifican áreas comunes y/o incrementan la superficie total del inmueble y/o se cambia la nomenclatura; por cada vivienda de departamento, casa o local comercial del conjunto.\n1).-Por cada unidad habitacional de tipo:\nI).-Interés social.. 1.57 VECES\nII).-Popular......... 2.35 VECES\nIII).-Nivel medio... 3.539 VECES\nIV).-Residencial.... 5.34 VECES\n2).-Comercial e industrial 14.30 VECES\nXV.-Por otros servicios que presta el departamento de edificación, a solicitud del interesado, hasta por 2 revisiones correspondiente:\nA).-Por certificación de planos de proyectos autorizados por el departamento:\na).-Por un juego de planos..... 7.15 VECES\nb).-Por cada juego de planos adicional.................. 0.901 VECES\nB).-Por certificación de bitácora de proyectos autorizados por el departamento:\na).-Por primera bitácora....... 3.15 VECES\nb).-Por bitácora subsecuente... 1.50 VECES\nC).-Por dictamen técnico e inspección de obras bajo el régimen de propiedad en condominio....... 6.44 VECES\nD).-Emisión de identificación para placa de control............... 6.50 VECES\nE).-Por expedición de constancias y copias certificadas de documentos\na).-Copia certificada de documento por hoja........ 1.30 VECES\nb).-Copia simple por hoja...... 0.65 VECES\nF).-Por análisis y emisión de dictamen de no inconveniencia para la fusión de claves catastrales de predios registrados bajo régimen de propiedad en condominio..... 13.00 VECES\nG).-Por análisis de acciones de edificación; en expediente físico a partir de la tercera revisión y subsecuentes se pagará el 20%\n(veinte por ciento) adicional al valor inicial del trámite.\nH).-Los trámites ingresados al departamento de edificaciones sólo permanecerán 90 días, al vencimiento de éstos se cancelará y se tendrá que ingresar de nuevo con pago de derechos correspondientes.\nI).-Por la revisión y validación anual de la correcta instalación de antenas, emisores y receptores, por unidad, se pagará a más tardar al 31 de marzo:................. 300.00 VECES\nJ).-Por autorización a particulares de las construcciones de puentes o infraestructuras similares, sobre vialidades públicas, banquetas, y/o infraestructura urbana, competencia del municipio, que requieran autorización del cabildo, se pagará a más tardar al\n31 de marzo:.................... 2,000.00 VECES\nK).-Por la revisión anual del cumplimiento de los requisitos de los permisos o concesiones otorgadas para la construcción de los citados puentes o infraestructuras similares, se pagará a más tardar al 31 de marzo: 100.00 VECES\nLos derechos señalados en los incisos I) y J), se causarán con independencia de los demás derechos que les corresponda pagar al particular por las mencionadas construcciones.\nXV BIS-. Por la revisión de expediente y, en su caso autorización de transferencia de derechos de desarrollo por densificación y/o intensificación, con o sin cambio de uso de suelo, se cobrará previo a la expedición de la licencia de construcción, por metro cuadrado de construcción excedente de superficie habitable y/o rentable, conforme a lo siguiente:\nPara el uso habitacional, la superficie de construcción excedente, es el promedio de la superficie de las viviendas por\nCentro de Población Tijuana, y en apego a los Planes y Programas de Desarrollo Urbano del municipio de Tijuana; y para el uso comercial, de servicios e industrial, la superficie de construcción excedente, es la diferencia entre la superficie suelo, indicado en el Reglamento de Zonificación y Usos del Suelo del Centro de Población Tijuana, y en apego a los Planes y\nProgramas de Desarrollo Urbano del municipio de Tijuana; para todos los usos antes señalados el valor del metro cuadrado m2 de construcción excedente, será el que corresponda a la zona homogénea donde se encuentra el predio, de acuerdo a la Tabla de\nValores Catastrales Unitarios para el Municipio de Tijuana, Baja\nCalifornia. La superficie habitable es la indicada en el\nReglamento de la Ley de Edificaciones para el Municipio de\nTijuana B.C. y la superficie rentable es la superficie de construcción destinada a las actividades de comercio, servicios e industria, sin considerar circulaciones y estacionamiento cubiertos.\nA.-Por densidad e intensidad superior a la señalada en el\nReglamento de Zonificación y Usos del Suelo del Centro de Población Tijuana, y en apego a los Planes y Programas de Desarrollo Urbano del municipio de Tijuana, y sus reglamentos vigentes, cuando el predio se encuentre dentro de polígonos de densificación, se aplicarán los siguientes porcentajes:\na).-Por densificación e intensificación, 15% del valor de la superficie de construcción excedente por m2 sin cambio de uso de suelo.\nb).-Por densificación e intensificación, 25% del valor de la superficie de construcción excedente por m2 con cambio de uso de suelo.\nB.-Por densidad e intensidad superior a la señalada en el de Población Tijuana, y en apego a los Planes y Programas de Desarrollo Urbano del municipio de Tijuana; cuando el se aplicarán los siguientes porcentajes:\na).-Por densificación e intensificación 20% del valor de la superficie de construcción excedente por m2 sin cambio de uso de suelo.\nb).-Por densificación e intensificación 30% del valor de la superficie de construcción excedente por m2 con cambio de uso de suelo.\nC.-Por cambio de uso de suelo al asignado en los Planes y y sus reglamentos vigentes, se aplicarán los siguientes porcentajes, en base al valor catastral sobre la superficie sujeta a cambio de uso de suelo.\na).-Cambio de uso de suelo de un área asignada en\nPrograma de Desarrollo Urbano y su reglamento vigente como conservación, 50% del valor catastral por m2 sujeta a reasignación o cambio de uso de suelo. b.-Cambio de uso de suelo de un área asignada en el\nPrograma de Desarrollo Urbano del Centro de\nPoblación Tijuana o Programa Parcial y su reglamento vigente, 15 % del valor catastral por m2 sujeta a reasignación o cambio de uso de suelo, cuando el predio se encuentre dentro de un polígono de densificación............... c.-Cambio de uso de suelo de un área asignada en el\nPrograma de Desarrollo Urbano del Centro de\nPoblación Tijuana o Programa Parcial y su reglamento vigente, 20 % del valor catastral por m2 sujeta a reasignación o cambio de uso de suelo, cuando el predio se encuentre fuera de un polígono de densificación.\nURBANIZACIÓN\nXVI.-Por análisis de acciones de urbanización para fraccionamientos, dentro de los términos del capítulo octavo, California; se pagarán, previo al inicio de los trámites, hasta por 2 revisiones del mismo anteproyecto de acuerdo con la siguiente tabla:\nA).-Por análisis de anteproyecto de fraccionamientos sociales progresivos, según la superficie total de:\na).-Predios ubicados dentro del centro de población:\n1).-Con superficie de hasta\n5 Has............... 50.95 VECES\n2).-Por cada Ha. o fracción excedente.......... 4.47 VECES\nb).-Predios ubicados fuera del centro de población:\n1).-Con superficie de hasta\n5 Has............... 56.30 VECES\n2).-Por cada Ha. o fracción de Ha. excedente.... 4.91 VECES\nB).-Por regularización del análisis de anteproyecto de fraccionamientos sociales progresivos, para el cual se hayan iniciado actividades relacionadas a la urbanización y/o promoción de venta sin contar con la autorización correspondiente:\na).-En predios ubicados dentro del centro de población:\n1).-Con superficie de hasta\n5 Has............... 76.41 VECES\n2).-Por cada Ha. o fracción de Ha. excedente.... 6.70 VECES\nb).-En predios ubicados fuera del centro de población:\n1).-Con superficie de hasta\n5 Has............... 85.80 VECES\n2).-Por cada Ha. o fracción de Ha. excedente.... 7.44 VECES\nC).-Por análisis de proyectos de fraccionamientos sociales progresivos, nuevos, o modificaciones a proyectos aprobados que requieran de un nuevo dictamen, según la superficie fraccionada:\na).-Con superficie de hasta 5 Has 45.50 VECES\nb).-Por cada Ha. o fracción de Ha. excedente................. 6.50 VECES\nD).-Por recorrido de inspección y elaboración del acta correspondiente al fraccionamiento en proceso, con el fin de otorgar prórroga de urbanización:\na).-Dentro del centro de población................. 50.05 VECES\nb).-Fuera del centro de población 85.80 VECES\nE).-Se exentará el 50% (cincuenta por ciento) del pago sobre los servicios de: 1).-Revisión del anteproyecto, 2).Revisión de proyecto ejecutivo, 3).-Licencia de construcción, 4).-Aprobación de anteproyecto de condominio, 5).-Declaratoria de condominio, 6).Constancia de cumplimiento del fraccionamiento y 7).-\nConstancia de cumplimiento de condominio; así como del\n50% (cincuenta por ciento) de los derechos de urbanización, a los desarrolladores que promuevan vivienda económica con un costo de hasta 63,000 UDIS, siempre que dentro del desarrollo de que se trate se construya el 25% (veinticinco por ciento) de vivienda de tipo económico y el resto hasta con un valor máximo de 90,000 UDIS, ya sea que dicho porcentaje sea en número de viviendas, o en superficie de terreno, siempre la mayor de las dos.\nXVII.-Por análisis de acciones de urbanización; se pagarán, previo al inicio de los trámites, las primeras 2 revisiones, y de ahí pagará cada una de las revisiones subsecuentes, de acuerdo a la siguiente tabla:\nA).-Por análisis de anteproyecto de fraccionamientos u obras de pluviales, áreas verdes, alumbrado público, integración vial, señalamiento vial y/o semáforos, promovidos por particulares, según la superficie total del predio:\na).-Predios ubicados dentro del centro de población:\n1).-Con superficie de hasta\n5 Has................ 107.51 VECES\n2).-Por cada Ha. o fracción excedente........... 10.40 VECES\nb).-En predios ubicados fuera del centro de población:\n1).-Con superficie de hasta\n5 Has................ 128.38 VECES\n2).-Por cada Ha. o fracción excedente........... 10.40 VECES\nB).-Por análisis de anteproyecto de pluviales de fraccionamientos promovidos por particulares, según superficie total del predio:\na).-En predios ubicados dentro y fuera del centro de población:\n1).-Con superficie de hasta\n5 Has................. 21.45 VECES\n2).-Por cada Ha. o fracción excedente............ 4.29 VECES\nb).-Por reconsideración de anteproyecto de pluvial o modificación.\n1).-Con superficie de hasta\n5 Has................. 21.45 VECES\n2).-Por cada Hectárea o fracción excedente.... 4.29 VECES\nC).-Por análisis de anteproyecto de áreas verdes de fraccionamientos promovidos por particulares, según superficie total del predio:\na).-En predios ubicados dentro y fuera de población.\n1).-Con superficie de hasta\n5 Has................ 21.45 VECES\n2).-Por cada Ha. o fracción de excedente........ 4.29 VECES\nb).-Por reconsideración de anteproyecto de áreas verdes o modificación.\n1).-Con superficie de hasta\n5 Has................ 21.45 VECES\n2).-Por cada Ha. o fracción excedente........... 4.29 VECES\nD).-Por análisis de anteproyecto de alumbrado público de fraccionamientos promovidos por particulares, según superficie total del predio:\na).-En predios ubicados dentro y fuera de la población:\n1).-Con superficie de hasta\n5 Has................ 21.45 VECES\n2).-Por cada Ha. o fracción de excedente......... 4.29 VECES\nb).-Por reconsideración de anteproyecto de alumbrado público o modificación.\n1).-Con superficie de hasta\n5 Has................ 21.45 VECES\n2).-Por cada Ha. o fracción excedente........... 4.29 VECES\nE).-Por análisis de anteproyecto de señalamiento de integración vial, señalamientos y semáforos de fraccionamientos promovidos por particulares, según superficie total del predio:\na).-En predios ubicados dentro y fuera del centro de población:\n1).-Con superficie de hasta cinco Has........... 21.45 VECES\n2).-Por cada Ha. o fracción excedente........... 4.29 VECES\nb).-Por reconsideración de anteproyecto de alumbrado público o modificación\n1).-Con superficie de hasta cinco Has............ 21.45 VECES\n2).-Por cada Ha. o fracción excedente........... 4.29 VECES\nF).-Por análisis de proyectos de fraccionamientos tipo campestre, nuevos o modificaciones a proyectos aprobados que requieran de un nuevo dictamen, por superficie fraccionada o proyectada:\na).-Con superficie de hasta 5 Has 38.61 VECES\nb).-Por cada Ha. o fracción excedente................. 7.15 VECES\nG).-Por análisis previo de planos correspondientes a anteproyecto y/o proyecto ejecutivo de acciones de anteproyecto y/o proyecto ejecutivo sólo una revisión:\na).-En predios ubicados dentro del centro de población:\n1).-Con superficie de hasta\n5 Has................ 37.57 VECES\n2).-Por cada Ha. o fracción excedente........... 8.93 VECES\nb).-En predios ubicados fuera del centro de población:\n1).-Con superficie de hasta\n5 Has................ 44.68 VECES\n2).-Por cada Ha. o fracción excedente........... 8.93 VECES\nH).-Por recorrido de inspección y elaboración de acta correspondiente a fraccionamientos finalizados, con el fin de la entrega-recepción parcial o total al municipio para su mantenimiento:\na).-En fraccionamientos dentro del centro de población... 78.65 VECES\nb).-En fraccionamientos fuera del centro de población....... 125.13 VECES\nI).-Por recorrido de inspección de las dependencias involucradas y en su caso elaboración de dictamen de no inconveniente correspondiente a fraccionamientos finalizados, con el fin de la entrega-recepción parcial o total al municipio, se cobrará:\na).-Por dictamen de no inconveniente de entrega de alumbrado público......... 21.45 VECES\nb).-Por dictamen de no inconveniente de entrega de áreas verdes.............. 21.45 VECES\nc).-Por dictamen de no inconveniente de entrega de la ingeniería de tránsito. 21.45 VECES\nd).-Por dictamen de no inconveniente de entrega de rehabilitación y mantenimiento............. 21.45 VECES\ne).-Por dictamen de no inconveniente de entrega del señalamiento vial......... 21.45 VECES\nf).-Por dictamen de no inconveniente de entrega de pluviales................ 21.45 VECES\ng).-Por dictamen de no inconveniente de entrega de polígono envolvente y puntos de control................ 21.45 VECES\nJ).-Por recorrido de inspección de las dependencias involucradas y en su caso elaboración de reconsideración de dictamen de no inconveniente correspondiente a fraccionamientos finalizados, con el fin de la entrega-recepción parcial o total al municipio para su mantenimiento se cobrará:\na).-Por dictamen de no inconveniente de entrega de alumbrado público......... 35.75 VECES\nb).-Por dictamen de no inconveniente de entrega de las áreas verdes.......... 35.75 VECES\nc).-Por dictamen de no inconveniente de entrega de la ingeniería de tránsito. 35.75 VECES\nd).-Por dictamen de no inconveniente de entrega de rehabilitación y mantenimiento............. 35.75 VECES\ne).-Por dictamen de no inconveniente de entrega del señalamiento vial......... 35.75 VECES\nf).-Por dictamen de no inconveniente de entrega de pluviales................ 35.75 VECES\ng).-Por dictamen de no inconveniente de entrega de polígono envolvente y puntos de control 35.75 VECES\nK).-Por constancia de cumplimiento de requisitos para traslación de dominio en fraccionamientos, cada vez que se solicite............ 78.65 VECES\nL).-Por constancia de reducción y/o cancelación de fianza, en fraccionamientos y/o acciones de urbanización, cada vez que se solicite....................... 31.46 VECES\nM).-Por análisis de factibilidad para relotificación, subdivisión y/o fusión......................... 6.29 VECES\nN).-Por realización de inspección y elaboración de Dictamen Técnico, se deberá cubrir previo al inicio del trámite:\na).-Encaminado a la desincorporación de bienes públicos.................. 10.73 VECES\nb).-Encaminado al análisis técnico del estado que guardan construcciones tales como bardas, muros de contención, etc........... 10.73 VECES\nc).-Encaminado a dictaminar zonas aptas para desarrollo a solicitud de particulares 10.73 VECES\nd).-Encaminado a la obtención de dictamen técnico para la asignación en comodato de un bien del dominio público. 10.73 VECES\ne).-Encaminado a la certificación de datos sobre la ubicación, medidas y colindancias de un bien del dominio privado.. 10.73 VECES\nÑ).-Expedición y certificación de copias de documentos de archivo:\na).-Páginas hasta tamaño legal:\n1).-Copia simple por misma página............... 2.688 VECES\n2).-Copia simple por cada página adicional..... 0.358 VECES\n3).-Copia certificada por primera página...... 2.05 VECES\n4).-Copia certificada por cada página adicional 0.472 VECES\nb).-Planos en tamaños de pliego de papel:\n1).-Copia simple de plano por metro cuadrado de papel bond.......... 2.688 VECES\n2).-Copia certificada de plano................ 8.93 VECES\nc).-Nota Aclaratoria:\n1).-Cobro por elaboración de nota aclaratoria no incluida en trámite original............ 5.72 VECES\nO).-Por relotificación, subdivisión y/o fusión de lotes urbanos y certificación de memoria descriptiva de los mismos, por cada lote fusionado o lote resultante de la subdivisión, (lo que resulte mayor) se pagará:\na).-Sobre lotes baldíos........ 15.73 VECES\nb).-Sobre lotes con construcción 20.45 VECES\nc).-Sobre lotes que se encuentren en proceso de regularización por el Instituto Nacional de\nSuelo Sustentable (INSUS) o el Instituto para el\nDesarrollo Inmobiliario y de la Vivienda para el Estado de\nBaja California (INDIVI) 0.00 VECES\nP).-Por subdivisión de predios rústicos, que no requieran apertura de calles, por cada fracción resultante:\na).-Dentro de los límites del centro de población....... 52.00 VECES\nb).-Fuera de los límites del centro de población, para uso agropecuario y otros.. 42.90 VECES\nQ).-Por análisis de modificación de proyectos de requieran de un nuevo dictamen, por superficie modificada:\na).-Con superficie de hasta 5 Has 152.58 VECES\nb).-Por cada Ha. o fracción excedente................. 17.30 VECES\nR).-Se exentará 50% (cincuenta por ciento) del pago sobre los servicios de: I).-Revisión del anteproyecto, II).Revisión de proyecto ejecutivo, III).-Licencia de construcción, IV).-Aprobación de anteproyecto de condominio, V).-Declaratoria de condominio, VI).-\nVII).-Constancia de cumplimiento de condominio; así como del 50% (cincuenta por ciento) de los derechos de urbanización, a los desarrolladores que promuevan vivienda económica con un costo de hasta 63,000 UDIS, siempre que dentro del desarrollo de que se trate se construya el 25% (veinticinco por ciento) de vivienda de tipo económico y el resto hasta con un valor máximo de 90,000 UDIS, ya sea que dicho porcentaje sea en número de viviendas, o en superficie de terreno, siempre la mayor de las dos.\nS).-Por análisis y emisión de documento de situación legal de un fraccionamiento, se pagará por cada caso..................... 1.95 VECES\nT).-Por cambio de perito responsable por obras de urbanización..... 26.81 VECES\nXVIII.-Por supervisión de obras de urbanización realizadas en base al proyecto de obras autorizado; se pagará, sobre el importe total de los presupuestos presentados no incluyendo IVA 2.50%\n(dos punto cincuenta por ciento) definitiva. El cálculo del monto de estos derechos se hará con el carácter de provisional, debiendo revisarse al terminar el desarrollo total, a efecto de que, para fijar el monto definitivo de las obras declarado para efectos fiscales.\nXIX.-Por certificación de memorias descriptivas, planos y otros de fraccionamientos; se pagarán, previo al inicio de los trámites, de acuerdo con la siguiente tabla:\nA).-Hasta por tres revisiones y certificación de memorias autorizados, según la cantidad total de lotes, cada vez:\na).-Hasta 100 lotes............ 52.00 VECES\nb).-Por cada lote excedente.... 1.30 VECES\nc).-Predios que se encuentren en proceso de regularización por\nINSUS O INDIVI............ 0.00 VECES\nB).-Por certificación de planos correspondientes a relotificación, subdivisión y/o fusión, cada certificación. 6.29 VECES\nC).-Copia certificada de relotificación, subdivisión y/o fusión.......................... 3.15 VECES\nD).-Por rectificación de memorias descriptivas autorizadas previamente e inscritas ante el\nRegistro Público de la Propiedad y de Comercio, salvo el caso de predios a nombre de INSUS o INDIVI por cada lote................... 7.15 VECES\nXX.-Por nivelación, limpieza o despalme de tierra para el mejoramiento y desarrollo de predios; deberán ser cubiertos por el solicitante previo al inicio del trámite, según el volumen en metros cúbicos, de acuerdo con la siguiente tabla:\nA).-Por revisión, análisis de proyecto y licencia de hasta por 2 revisiones.\na).-Por superficie total documental y despalme, según mecánica de suelo.\n1).-Por volúmenes de hasta\n10,000.00 M³............... 38.61 VECES\n2).-Por cada M³ de volumen que exceda a 10,000.00 M³.. 0.0006756 VECES\nB).-Por revisión, análisis de proyecto y licencia de hasta por 2 revisiones.\na).-Por superficie total documental y despalme según mecánica de suelo.\n1).-Por volúmenes de hasta\n10,000.00 M³.......... 39.04 VECES\n2).-Por cada M³ de volumen que exceda a 10,000.00 M³\n...................... 0.0006756 VECES\nC).-Por revisión, análisis de proyecto y licencia para movimiento de tierra en predios dentro del centro de población hasta por 2 revisiones.\na).-Por movimientos de tierra con volumen de hasta 200.00 M³ en lotificación de fraccionamientos autorizados con uso habitacional unifamiliar................ 7.15 VECES\nb).-Movimientos con volúmenes de hasta 10,000.00 M³......... 52.00 VECES\nc).-Por cada M³ de volumen que exceda a 10,000.00 M³, por M³ 0.0006756 VECES\nD).-Por revisión, análisis de proyecto y licencia para movimiento de tierra en predios fuera del centro de población hasta por 2 revisiones.\na).-Para volúmenes de hasta\n10,000.00 M³............... 39.04 VECES\nb).-Por cada M³ de volumen que exceda a 10,000.00 M³ adicional a la cuota del inciso a), por M³.......... 0.0006756 VECES\nE).-Por revisión, análisis de proyecto y licencia de regularización de movimientos de tierra ejecutados total o parcialmente sin contar con las licencias correspondientes, se pagará el 50% (cincuenta por ciento) adicional de los derechos por trámite normal indicados en la tarifa de los puntos B) y C) inmediatos anteriores.\nF).-Por revisión de proyecto y regularización de licencia para movimientos de tierra en predios fuera del centro de población, hasta por 2 revisiones:\na).-Por movimientos de tierra con volumen de hasta 200.00 m3 en lotificación de fraccionamientos no autorizados con uso habitacional unifamiliar... 10.94 VECES\nb).-Movimientos con volúmenes hasta 10,000 m3............ 79.56 VECES\nG).-Por prorroga de licencia para movimiento de tierra:\na).-Para volúmenes de hasta\n10,000.00 M³............... 20.02 VECES\nb).-Por cada M³ de volumen que exceda de 10,000.00 M³ adicional a la cuota del inciso a), por M³.......... 0.0006756 VECES\nXXI.-Por análisis, emisión de licencia de urbanización y emisión de licencia de factibilidad de opinión técnica encaminada a la emisión de ocupación de la vía pública en el suelo, subsuelo y en sobresuelo o aérea, por elemento o mobiliario de servicios públicos concesionados a la iniciativa privada, o a cargo de dependencias, direcciones o cualquier organismo de gobierno ya sea municipal, estatal o federal; se pagará de acuerdo al tipo de elemento o mobiliario, previo el inicio del trámite.\nA).-Para los elementos o mobiliario urbano de los equipos de telefonía:\na).-Por Km o fracción de línea de telefonía subterránea o aérea..................... 20.02 VECES\nb).-Por poste o torre.......... 3.25 VECES\nc).-Por registro............... 1.78 VECES\nd).-Por Km o fracción de línea de fibra óptica de telefonía subterránea o aérea....... 28.60 VECES\ne).-Por colocación de base de concreto.................. 1.78 VECES\nf).-Por colocación de pedestal. 1.78 VECES\nB).-Para elementos o mobiliario urbanos de equipo de gas natural.\na).-Por Km o fracción de línea de gas natural subterránea o aérea.................... 20.02 VECES\nC).-Para los elementos o mobiliario urbano de los equipos de energía eléctrica:\na).-Por Km o fracción de línea de energía subterránea o aérea 15.73 VECES\nb).-Por poste o torre.......... 0.16 VECES\nc).-Por registro............... 1.57 VECES\nd).-Por Km o fracción de línea de fibra óptica de telefonía subterránea o aérea....... 28.60 VECES\nD).-Para los elementos o mobiliario urbano de los equipos de agua potable y drenaje sanitario.\na).-Por Km o fracción de línea de red de agua potable o drenaje sanitario................. 15.73 VECES\nb).-Por registro............... 1.573 VECES\nE).-Para los elementos o mobiliario urbano de los equipos de entretenimiento y comunicación multimedia por cable:\na).-Por Km o fracción de línea de energía subterránea o aérea 20.02 VECES\nb).-Por poste o torre.......... 0.20 VECES\nc).-Por registro............... 2.00 VECES\nd).-Por Km o fracción de línea de fibra óptica de telefonía subterránea o aérea....... 28.60 VECES\nF).-Por recorrido de inspección y elaboración de factibilidad de servicios dentro o fuera del centro de población:\na).-Infraestructura pluvial.... 21.45 VECES\nb).-Ruptura de pavimento....... 21.45 VECES\nc).-Infraestructura instalaciones (TELNOR,\nCOMPAÑIA DE GAS, CFE, CESPT, entre otros)....... 21.45 VECES\nG).-Por prórroga de licencia de ocupación de la vía pública en el suelo, subsuelo, sobresuelo y aérea......................... 17.88 VECES\nH).-Por concepto de renta anual y de supervisión anual en posterías resultantes del convenio de colaboración con empresas prestadoras de servicios de telecomunicaciones.\na).-Por renta anual por poste. 1.30 VECES\nb).-Por supervisión anual por poste. 0.59 VECES\nXXII.-Por revisión y verificación de documentos y planos; y emisión de licencia para demolición parcial o total de edificios e instalaciones, se pagará, previo al inicio de los trámites, de acuerdo a la siguiente tabla:\nA).-Cordón de banqueta o guarnición, de hasta 3.00 M................... 2.68 VECES\nB).-Cordón de banqueta o guarnición, mayor a 3.00 M y menor a 10.00 M\n............................... 8.93 VECES\nC).-Cordón de banqueta o guarnición, mayor a 10.00 M................ 14.30 VECES\nD).-Banquetas de hasta 3.00 M...... 2.72 VECES\nE).-Banqueta mayor a 3.00 M y hasta a\n10.00 M....................... 8.93 VECES\nF).-Banqueta mayor a 10.00 M....... 14.30 VECES\nG).-Arroyo de vialidades de hasta 3.00\nM.............................. 5.36 VECES\nH).-Arroyo de vialidades mayor a 3.00\nI).-Arroyo de vialidades mayor a 10.00\nM.............................. 17.88 VECES\nJ).-Obra Pública: Todo tipo de construcción, edificación y EXENTO urbanización promovida, realizada y en propiedad de los tres niveles de gobierno....................\nXXIII.-Nota aclaratoria:\nA).-Por elaboración de nota aclaratoria no incluida en trámite original............... 5.72 VECES\nXXIV.-Por análisis y emisión de factibilidad de opiniones vial a predios donde se pretenda impulsar el desarrollo urbano y que por su magnitud impactan el sector en que se ubiquen; incluye análisis de densidades, análisis normativo y análisis de congruencia con la estructura vial que plantea el Programa de\nDesarrollo Urbano del Centro de Población y los Planes y\nProgramas Parciales y Sectoriales de Desarrollo Urbano en vigor:\nA).-Por análisis y emisión de factibilidad de opinión técnica de integración vial, a predios de desarrollos habitacionales, desarrollos turísticos, centros comerciales, parques industriales, etc.; incluye definición de la ruta, definición del origen y destino de la vialidad; así como la definición de la normatividad de diseño y planeación para vialidades a las que se debe apegar; se pagará de acuerdo con la longitud del trazo, previo el inicio del trámite:\na).-Vialidades con longitud de hasta 2,500.00 metros lineales................ 35.75 VECES\nb).-Vialidades con longitudes mayores de 2,500.00 y hasta de 5,000.00 metros lineales de longitud.............. 53.63 VECES\nc).-Vialidades con longitudes mayores de 5,000.00 y hasta de 10,000.00 metros lineales de longitud..... 71.50 VECES\nd).-Vialidades con longitudes mayores de 10,000.00 metros lineales de longitud.... 125.13 VECES\nB).-Por análisis y emisión de factibilidad de dictamen técnico de integración vial, a predios de desarrollos habitacionales, desarrollos turísticos, centros comerciales, parques industriales, etc.; incluye definición de la ruta, definición del origen y destino de la vialidad; así como la definición de la sección que deberá absorber la vialidad, la definición de los otras vialidades existentes o propuestas, etc.; se pagará de acuerdo con la longitud del trazo, previo el inicio del trámite:\na).-Vialidades con longitud de hasta 2,500.00 metros lineales................. 71.50 VECES\nb).-Vialidades con longitudes mayores de 2,500.00 y hasta de 5,000.00 metros lineales de longitud............... 107.25 VECES\nc).-Vialidades con longitudes mayores de 5,000.00 y hasta de 10,000.00 metros lineales de longitud............... 143.00 VECES\nd).-Vialidades con longitudes mayores de 10,000.00 metros lineales de longitud..... 250.25 VECES\nC).-Por análisis y emisión de factibilidad de opinión técnica de estructura vial en predios de desarrollos habitacionales y parques industriales, incluye definición de sección de derecho de vía en base a los volúmenes de tráfico que deberá absorber la vialidad, la definición de los lineamientos viales en los cruces propuestas, etc.; se pagará de acuerdo con la superficie del predio, previo al inicio del trámite:\na).-Predios con superficie de hasta 10,000.00 M²........ 92.95 VECES\nb).-Predios con superficie mayor de 10,000.00 M² y de hasta\n100,000.00 M² de superficie\n.......................... 103.68 VECES\nc).-Predios con superficie mayor de 100,000.00 M² y de hasta\n500,000.00 M² de superficie\n.......................... 114.40 VECES\nd).-Predios con superficie mayor de 500,000.00 M².......... 125.125 VECES\nD).-Por análisis y reconsideración de opinión técnica o desarrollos habitacionales, desarrollos turísticos, centros comerciales, parques industriales, etc.; se pagará de acuerdo con la longitud del trazo, previo al inicio del trámite:\na).-Vialidades con longitud de hasta 2,500.00 metros lineales................. 17.88 VECES\nb).-Vialidades con longitudes mayores de 2,500.00 metros lineales y hasta de 5,000.00 metros lineales........... 28.60 VECES\nc).-Vialidades con longitudes mayores de 5,000.00 metros lineales y hasta de\n10,000.00 metros lineales. 35.75 VECES\nd).-Vialidades con longitudes mayores de 10,000.00 metros lineales.................. 64.35 VECES\nE).-Por análisis y reconsideración de opinión técnica de estructura vial a predios de desarrollos habitacionales y parques industriales; se pagará de acuerdo con la superficie del predio, previo al inicio del trámite:\na).-Predios con superficie de hasta 10,000.00 M²........ 25.03 VECES\nb).-Predios con superficie mayor de 10,000.00 M² y de hasta\n100,000.00 M² de superficie\n.......................... 28.60 VECES\nc).-Predios con superficie mayor de 100,000.00 M² y de hasta\n500,000.00 M² de superficie 32.18 VECES\nd).-Predios con superficie mayor de 500,000.00 M².......... 39.33 VECES\nF).-Por análisis y emisión de opinión técnica de afectación a predios; se pagará de acuerdo con la superficie del predio, previo al inicio del trámite:\na).-Predios con superficie de hasta 10,000.00 M²........ 23.23 VECES\nb).-Predios con superficie mayor de 10,000.00 M² y de hasta\n100,000.00 M² de superficie\n.......................... 26.81 VECES\nc).-Predios con superficie mayor de 100,000.00 M² y de hasta\n500,000.00 M² de superficie\n.......................... 28.60 VECES\nd).-Predios con superficie mayor de 500,000.00 M².......... 32.18 VECES\nG).-Por análisis y emisión de opinión técnica de proyecto de señalamiento de desvío de tránsito por obras de urbanización, se pagará previo al inicio del trámite.\na).-Por proyecto............... 27.17 VECES\nXXV.-Por análisis y emisión de factibilidad de opiniones técnicas y dictámenes técnicos de integración vial en predios para edificación y que por su ubicación impactan las vialidades con las que colindan; incluye el análisis normativo; se pagará de acuerdo a la superficie del predio, previo al inicio del trámite:\nA).-Por análisis y emisión de factibilidad de opinión técnica de integración vial a predios para edificaciones habitacionales, turísticos, comerciales, industriales, etc.\na).-Predios con superficie hasta de 200.00 M².............. 28.60 VECES\nb).-Predios con superficie mayor de 200.00 M² y de hasta\n600.00 M² de superficie... 35.75 VECES\nc).-Predios con superficie mayor de 600.00 M².............. 53.63 VECES\nB).-Por análisis y revisión de proyectos en apego a las edificaciones habitacionales, turísticos, comerciales, industriales, etc.\na).-Predios con superficie hasta de 200.00 M².............. 14.30 VECES\nb).-Predios con superficie mayor de 200.00 M² y de hasta\n600.00 M² de superficie... 17.88 VECES\nc).-Predios con superficie mayor de 600.00 M².............. 28.60 VECES\nC).-Por reconsideración de opiniones técnicas de habitacionales, turísticas, comerciales, industriales, etc.\na).-Predios con superficie hasta de 200.00 M².............. 14.30 VECES\nb).-Predios con superficie mayor de 200.00 M² y de hasta\n600.00 M² de superficie... 35.75 VECES\nc).-Predios con superficie mayor de 600.00 M².............. 28.60 VECES\nXXVI.-Por análisis y emisión de factibilidad de dictamen técnico para la desincorporación de superficie del régimen de vía pública, se pagará de acuerdo con la superficie, previo al inicio del trámite:\nA).-Por superficies en secciones de banqueta o circulación peatonal:\na).-Por cada metro o fracción en el primer cuadro de la ciudad\n.......................... 71.50 VECES\nb).-Por cada metro o fracción fuera del primer cuadro de la ciudad.................... 35.75 VECES\nB).-Por superficies en secciones de arroyos o en circulación vehicular:\na).-Por cada metro o fracción en el primer cuadro de la ciudad\n.......................... 35.75 VECES\nb).-Por cada metro o fracción fuera del primer cuadro de la ciudad.................... 17.88 VECES\nXXVI -BIS.-Por análisis, verificación y emisión de licencias de urbanización, prórroga y terminaciones de obra de infraestructura en predios privados, previo al inicio del trámite, hasta por 2 revisiones del mismo proyecto y de acuerdo a lo siguiente:\nA.-Por análisis, verificación y emisión de licencia de privados:\na).-En predios privados de uso habitacional hasta 15,000 m²\n.......................... 65.00 VECES\nb).-En predios privados de uso comercial hasta 20,000 m². 75.00 VECES\nc).-En predios privados de uso industrial hasta 50,000 m² 80.00 VECES\nB.-Por emisión de prórroga licencia de urbanización para obras de infraestructura en predios privados:\na).-En predios privados de uso habitacional hasta 15,000 m²\n.......................... 32.00 VECES\nb).-En predios privados de uso comercial hasta 20,000 m². 36.00 VECES\nc).-En predios privados de uso industrial hasta 50,000 m² 38.00 VECES\nC.-Por emisión de terminación de obras de licencia de urbanización para obras de infraestructura en predios privados:\na).-En predios privados de uso habitacional hasta 15,000 m²\n.......................... 50.00 VECES\nb).-En predios privados de uso comercial hasta 20,000 m². 55.00 VECES\nc).-En predios privados de uso industrial hasta 50,000 m² 60.00 VECES\nUSOS DEL SUELO\nXXVII.-Por análisis y emisión de constancia de zonificación, acreditación, dictamen de uso del suelo, cambios de uso del suelo y copias certificadas; las cuales se pagarán, previo al inicio del trámite:\nA).-Análisis y emisión de dictamen de uso de suelo:\na).-Para desarrollos habitacionales, industriales, comerciales y de servicios, de acuerdo con la superficie total del predio, por dictamen, se pagará:\n1).-Sobre predios de hasta\n10,000.00 M² de superficie.......... 53.17 VECES\n2).-Sobre predios mayores de\n10,000.00 M² y de hasta\n100,000.00 M² de superficie........... 59.30 VECES\n3).-Sobre predios mayores de\n100,000.00 M² de superficie........... 71.57 VECES\nb).-Por análisis y emisión de dictamen de uso de suelo; para factibilidad de uso y destino en predios habitacionales previo a la iniciación, se pagará por dictamen sobre predios:\n1).-Análisis y dictamen de uso de suelo; para factibilidad de uso y destino habitacional hasta 120.00 m2,..... 7.15 VECES\n2).-Análisis y dictamen de uso de suelo; para factibilidad de uso y destino habitacional mayor de 120.01 m2 y hasta 200.00 m2,..... 14.30 VECES\n3).-Análisis y dictamen de uso de suelo; para factibilidad de uso y destino habitacional mayor de 200.01 m2 y hasta 500.00 m2,..... 27.89 VECES\n4).-Análisis y dictamen de uso de suelo; para factibilidad de usos y 41.83 VECES destino habitacional mayor de 500.01 m2 y hasta 5,000.00 m2,...\n5.-Análisis y dictamen de uso de suelo; para factibilidad de usos y destino habitacional mayor de 5,000.01 m2. 50.00 VECES\nc).-Para factibilidad de predios, de uso industrial se pagará por predio, previo a la iniciación de trámites, por dictamen:\n1).-Análisis y dictamen de uso de suelo; y destino industrial\n(Microindustria) hasta\n500.00 m2............ 27.89 VECES\n2).-Análisis y dictamen de uso de suelo; y destino industrial hasta 500.01 m2 hasta 1,000.00 m2. 41.83 VECES\n3).-Análisis y dictamen de uso de suelo; y destino industrial sobre predios con superficie de 1,000.01 m2 hasta\n5,000.00 m2.......... 46.48 VECES\n4).-Análisis y dictamen de uso de suelo; y destino industrial sobre predios con superficie mayor de 5,000.01 m2. 60.00 VECES\nd).-Por análisis y dictamen de uso de suelo para factibilidad de usos y destinos de predios comercial o servicios se pagará previo a la iniciación de trámites por dictamen sobre predios:\n1).-Análisis y dictamen de usos de suelo y destino comercial o servicios con superficie hasta\n100.00 m2............ 17.88 VECES\n2).-Análisis y dictamen de usos de suelo y destino comercial o servicios con superficie mayor de\n100.01 m2 hasta 500.00\nM2................... 21.45 VECES\n3).-Análisis y dictamen de usos de suelo y destino comercial o servicios con superficie mayor de\n500.01 m2 hasta\n5,000.00 m2.......... 35.75 VECES\n4).-Análisis y dictamen de usos de suelo y destino comercial o servicios con superficie mayor de\n5,000.01 m2......... 44.68 VECES\ne).-Por análisis y emisión de dictamen de uso de suelo para factibilidad y destinos de predios de ocupación de uso especial, se pagará previo a la iniciación de trámites, por dictamen:\n1).-Análisis y emisión de dictamen de uso y destino con superficie menor a 200.00 m2,... 98.31 VECES\n2).-Análisis y emisión de dictamen de uso y destino con superficie mayor a 200.01 m2.... 178.75 VECES\n3).-Análisis y emisión de dictamen de uso y destino especial para infraestructura en instalaciones subterráneas (líneas de gas) por metro lineal.\n..................... 0.33 VECES\nf).-Copia certificada de dictamen de uso de suelo (todo tipo de dictamen de uso de suelo siempre y cuando exista el expediente). 21.45 VECES\ng).-Por análisis y emisión de dictamen de cambio de uso de suelo 52.00 VECES en predios de uso habitacional, industrial, comercial, especial o de servicios, debiendo presentar\nOpinión Técnica Favorable emitida por el Instituto Metropolitano de\nPlaneación, previo a la iniciación de trámites, se pagará por dictamen:..................\nh).-Por análisis y emisión de dictamen de uso de suelo para factibilidad de usos y destinos de predios para centros de apuestas, apuestas remotas, salas de sorteos de números y/o casinos, libro foráneo y similares:\n1).-Hasta 3,000.00 M² de superficie.......... 650.00 VECES\n2).-De 3,001.00 M² de terreno en adelante.. 975.00 VECES\nB).-Factibilidad para asentamiento y/o licencia de traslado para casas y oficinas móviles............... 16.08 VECES\nC).-Por análisis de gabinete de uso de suelo de tipo comercial sobre predios con superficie de ocupación comercial de 60.00 M² 11.70 VECES\nD).-Por reconsideración solicitada de uso de suelo, siendo el resultado de la misma favorable o desfavorable se pagarán, previo al inicio del trámite, las mismas cuotas señaladas en los conceptos A), B) y C).\nE).-Por análisis de gabinete y emisión de constancia de acreditación de uso de suelo en predios:\na).-Por análisis y emisión de constancia de acreditación de usos y destinos en predios de uso habitacional, comercial o de servicios se pagará previo al inicio del trámite...... 15.21 VECES\nb).-Constancia de acreditación de uso de suelo especial, en predios:\n1).-Constancia de acreditación de usos de 98.31 VECES suelo especial predio menor 200.00 m2........\n2).-Constancia de acreditación de usos de suelo especial predio mayor 200.01 m2........ 78.75 VECES\nF).-Por análisis y emisión de constancia de zonificación de uso y destino habitacional, industrial, comercial o de servicios se pagará previo al inicio del trámite y por constancia sobre cada predio.\n11.70 VECES\nG).-Por concepto de dictamen de uso de suelo mixto, se modificará el costo 1.50 veces más, que un Dictamen de Uso de Suelo.\nH).-Por expedición de copias simples de documentos (excepto uso especial):\na).-Copia certificada de documento por hoja........ 1.30 VECES\nb).-Copia simple por hoja...... 0.65 VECES\nI).-Por expedición de copias simples de dictamen de uso de suelo especial, por superficie de predio:\n1.-Predio con superficie menor a\n200.00 M²................. 52.00 VECES\n2.-Predio con superficie mayor a\n200.00 M²................. 130.00 VECES\nACTIVIDADES COMERCIALES, INDUSTRIALES Y/O PRESTACIÓN DE\nSERVICIOS\nXXVIII.-Por revisión, análisis, verificación y certificación para el otorgamiento, cambio de domicilio, cambio de propietario, aumento de superficie, aumento de actividad, cambio de actividad, operación para giros comerciales, industriales y de servicios, se causarán derechos conforme a lo siguiente:\nA).-Comercio básico pequeño, impulsado por programas de gobierno hasta de\n35.00 M² de superficie......... 5.36 VECES\nB).-Despachos de profesionistas y oficinas administrativas hasta\n100 M2......................... 14.30 VECES\nC).-Expendios, abarrotes, talleres de servicio, llanteras, loncherías, panaderías, tortillería, lavanderías, laboratorios, ópticas, ferreterías, refaccionarias, tiendas de ropa, misceláneas, farmacias, estéticas, papelería, librería, vidriera, florería, casas de cambio, venta de agua purificada\n(llenado de garrafón), casetas telefónicas, consultorios médicos, venta de alimentos preparados, cerrajerías, agencias de viajes, café internet, cafetería, curiosidades o artesanías, dulcerías, equipo de comunicación, frutería, fumigadoras, gimnasio, imprenta, joyería, granero, veterinaria, renta de autos, tiendas de segunda, videos, venta de celulares, zapaterías, auto lavado, mueblerías, despachos de profesionistas y oficinas administrativas mayores a 100.00\nM2............................. 17.88 VECES\nD).-Billares, bar, restaurante, mercado, supermercado, subagencia, bodegas de distribución, salón para eventos temporales, hospital, clínicas médicas, bancos, estacionamientos públicos, funerarias, teatros, limpiaduría, lotes de carros, madererías, máquinas de video juego, autoservicios, casa de 32.18 VECES empeño........................\nE).-Discotecas, tiendas departamentales y clubes deportivos café cantante, centro de espectáculos y salas cinematográficas............... 39.33 VECES\nF).-Moteles con ocupación de:\na).-Hasta 10 habitaciones...... 21.45 VECES\nb).-11 y hasta 20 habitaciones. 30.38 VECES\nc).-21 habitaciones o más...... 39.33 VECES\nG).-Hoteles con ocupación de:\na).-Hasta 30 habitaciones...... 39.33 VECES\nb).-31 habitaciones o más...... 57.20 VECES\nH).-Edificios educativos con:\na).-Hasta 5 aulas.............. 16.08 VECES\nb).-6 aulas o más.............. 26.81 VECES\nI).-Giros de alto riesgo tales como, distribuidoras de gases, combustible y lubricantes, oxígenos y acetilenos, estaciones de carburación de diésel, polvorines, gasolineras, lubricantes y demás de alto riesgo 214.50 VECES\nJ).-Yonkes, recicladoras y centros de acopio de material metálico... 48.62 VECES\nK).-Edificios industriales:\na).-Industrial hasta 1,000.00 M²\n(maquiladoras, fábricas, bodegas, almacenes, empacadoras, procesadoras)... 45.50 VECES\nb).-Industrial mayor a 1,000.00\nM² (maquiladoras, fábricas, bodegas, almacenes, empacadoras, procesadoras)... 105.30 VECES\nL).-Giros con apuestas (casinos, libros foráneos, palenques, etc.)\n............................... 78.65 VECES\nM).-Otros giros no especificados:\na).-Con superficie hasta 200.00\nM²........................... 17.88 VECES\nb).-Con superficie mayor a 200.00\nM²........................... 32.50 VECES\nN).-Corrección en documento oficial expedido(por error en expedición imputable al solicitante)...... 1.95 VECES\nÑ).-Copia certificada de licencia de operación por hoja............ 2.93 VECES de Licencia de Operación para giros comerciales, industriales y/o prestación de servicios, el causante deberá presentar el pago del establecimiento donde se ejerce la actividad señalada en el permiso en referencia. Excepto cuando tenga el carácter de arrendatario.\nXXIX.-Servicios para dar seguimiento a la obtención de la licencia de operación, por inspección de local comercial, industrial o de servicios se cobrará previo a la remisión del permiso a la Tesorería Municipal:\nA).-Por segunda inspección, revisión y/o análisis documental para seguimiento de la obtención de la licencia de operación.......... 3.25 VECES\nB).-Por tercera revisión, inspección y/o análisis documental para seguimiento de la obtención de la licencia de operación.......... 3.25 VECES\nC).-Por cuarta y/o subsecuente inspección, revisión, y/o análisis documental para seguimiento de la obtención de la licencia de operación......... 3.25 VECES\nXXX.-Por revalidación anual de licencia de operación para giros comerciales, industriales y de servicios, señalados en la\nFracción XXVIII del presente artículo, misma que deberá realizarse del 1º de enero al 30 de junio............................ 5.20 VECES\nOperación, el causante deberá presentar el pago del impuesto permiso en referencia. Excepto cuando tenga el carácter de arrendatario.\nXXXI.-Por otorgamiento de permiso provisional de operación para giros comerciales, industriales y de servicios, con vigencia de\n3 meses, por única vez y siempre que se encuentre en trámite el permiso definitivo:\nA).-Comercio básico pequeño, impulsado por programas de gobierno hasta de\n35.00 M² de superficie 1.34 VECES\nB).-Despachos de profesionistas y oficinas administrativas. Hasta\n100.00 M2...................... 3.58 VECES\nC).-Expendios, abarrotes, talleres de servicio, llanteras, loncherías, panaderías, tortillería, lavanderías, laboratorios, ópticas, ferreterías, refaccionarias, tiendas de ropa, misceláneas, farmacias, estéticas, papelería, librería, vidriera, florería, casas de cambio, venta de agua purificada (llenado de garrafón), casetas telefónicas, consultorios médicos, venta de alimentos preparados, cerrajerías, agencias de viajes, café internet, cafetería, curiosidades o artesanías, dulcerías, equipo de comunicación, frutería, fumigadoras, gimnasio, imprenta, joyería, granero, veterinaria, renta de autos, tiendas de segunda, videos, venta de celulares, zapaterías, auto lavado, mueblerías, despachos de profesionistas y oficinas administrativas, mayores a 100.00\nM2.............................. 4.47 VECES\nD).-Billares, restaurante, mercado, supermercado, bodegas de 8.03 VECES distribución, salón para eventos temporales, hospital, clínicas médicas, bancos, estacionamientos públicos, funerarias, teatros, limpiaduría, lotes de carros, madererías, autoservicios, casas de empeño.......................\nE).-Tiendas departamentales, clubes deportivos y salas cinematográficas............... 9.83 VECES\nF).-Moteles con ocupación de:\na).-Hasta 10 habitaciones...... 5.36 VECES\nb).-11 y hasta 20 habitaciones. 7.59 VECES\nc).-21 habitaciones o más...... 9.83 VECES\nG).-Hoteles con ocupación de:\na).-Hasta 30 habitaciones...... 9.83 VECES\nb).-31 habitaciones o más...... 14.30 VECES\nH).-Edificios educativos con:\na).-Hasta 5 aulas............. 4.02 VECES\nb).-6 aulas o más.............. 6.70 VECES\nI).-Giros de alto riesgo tales como, distribuidoras de gases, combustible y lubricantes, oxígenos y acetilenos, estaciones de carburación de diésel, polvorines, gasolineras, lubricantes y demás de alto riesgo 49.15 VECES\nJ).-Yonkes, recicladoras y centros de acopio de material metálico.... 12.16 VECES\nK).-Edificios industriales:\na).-Industrial hasta 1,000.00 M²\n(maquiladoras, fábricas, bodegas, almacenes, empacadoras, procesadoras).. 11.38 VECES\nb).-Industrial mayor a 1,000.00\nM² (maquiladoras, fábricas, bodegas, almacenes, empacadoras, procesadoras).. 24.05 VECES\nL).-Otros giros no especificados.\na).-Con superficie menor a 200.00\nM².......................... 4.47 VECES\nb).-Con superficie mayor a 200.00\nM².......................... 7.80 VECES\nM).-Corrección en documento oficial expedido (por error en expedición imputable al solicitante)...... 1.95 VECES\nN).-Venta de árboles, ornamentos navideños y/o ornamentos de temporada especial en propiedad privada (por temporada navideña o especial)...................... 20.80 VECES\nXXXII.-Inscripción y revalidación de constancia en el registro municipal de yonkes, recicladoras y centros de acopio de material metálico.\nA).-Inscripción y otorgamiento de constancia de inscripción....... 32.50 VECES\nB).-Revalidación de inscripción y otorgamiento de constancia de revalidación de inscripción..... 19.50 VECES\nC).-Expedición por reposición de constancia de inscripción o de constancia de revalidación de inscripción..................... 2.60 VECES\nD).-Expedición de copia certificada de constancia de inscripción o de constancia de revalidación de inscripción.................... 2.60 VECES\nE).-Expedición de copias simples de constancia de inscripción o de constancia de revalidación de inscripción.................... 0.65 VECES\nXXXIII.-Por revisión, análisis y verificación y certificación de factibilidad para la instalación, revalidación anual y regularización de rótulos, anuncios y similares, exceptuando la propaganda efectuada por partidos políticos; se pagará, previo al inicio del trámite, por superficie o cantidad, según se indique, de acuerdo a la siguiente tabla:\nA).-Licencia nueva con vigencia de hasta un año, cuando la licencia:\na).-Cartelera o anuncio autoportante para uso exclusivo de comercio establecido en el mismo predio a publicitar (excepto espectaculares):\n1).-De 0.01 M² a 1.00 M² en área de rótulo, por cartelera o anuncio autoportante.......... 13.00 VECES\n2).-De 1.01 M² a 5.99 M² en área de rótulo, por cartelera o anuncio autoportante.......... 52.00 VECES\n3).-De 6.00 M² a 30.00 M² en área de rótulo, por cartelera o anuncio autoportante.......... 91.00 VECES\nb).-Anuncio (autosoportado, autoportante o de cualquier otro tipo) de propaganda comercial tipo espectacular, por anuncio............... 260.00 VECES\nc).-Anuncio tipo espectacular de pantalla electrónica y/o electromecánico o digital, incluye torre directorio de pantalla electrónica, pantalla en vehículos, con o sin movimiento, por cara de pantalla, por cartelera y/o estructura................. 520.00 VECES\nd).-Rótulo pintado, denominativo mayor de 2.01 M² y/o rótulo con propaganda comercial de productos que se venden en el establecimiento, por fachada\n........................... 5.20 VECES\ne).-Rótulos pintados o adosados, para yonkes, recicladoras y centros de acopio, por fachada o barda............ 15.60 VECES\nf).-Rótulo adosado, toldo, marquesina, por anuncio:\n1).-Denominativos de 2.01 M² hasta 3.99 M² y/o rótulos con propaganda comercial de productos que se venden en el establecimiento de 0.01\nM² hasta 3.99 M²...... 5.85 VECES\n2).-Mayor de 3.99 M² hasta\n15.00 M2.............. 9.10 VECES\n3).-Los mayores de 15.00 M² costo por metro cuadrado o fracción excedente. 7.80 VECES\ng).-Rótulo electrónico y/o electromecánico, y de neón con o sin movimiento, exceptuando espectaculares y/o carteleras autoportantes y pantalla en vehículos:\n1).-De 0.01 M² y hasta 1.50\nM², por cara de anuncio.\n...................... 9.75 VECES\n2).-Mayor de 1.50 M², por cara de anuncio....... 26.00 VECES\n3).-Los mayores de 10.00 M2, costo por M2 o fracción excedente............. 7.80 VECES\nh).-Anuncio de evento (manta, cartel y pendones) con información laica, cultural, deportivo, económico, educativo, que beneficie a la comunidad en su desarrollo social, que no implique erogación económica alguna para los habitantes del municipio o con información gubernamental de la federación, estado o municipio.................. EXENTO\ni).-Torre directorio, por unidad\n(excepto electrónicas)..... 39.00 VECES\nj).-Mini porta cartel direccional exclusivamente para 14.30 VECES desarrollos habitacionales e industriales nuevos, por pieza por doce meses.......\nk).-Cobertizo publicitario y/o mobiliario urbano con publicidad, (banca publicitaria, bote de basura o buzón con publicidad, etc.), por unidad.......... 26.00 VECES\nl).-Carro de sonido por unidad, por 90 días................ 15.60 VECES\nm).-Torreta en techo de camión o taxi, por unidad........... 19.50 VECES\nn).-Rótulo en vehículo público o privado, por anuncio....... 12.19 VECES ñ).-Valla publicitaria de hasta\n12.50 M², por cada unidad.. 52.00 VECES\no).-Valla publicitaria por cada\nM² excedente.............. 10.40 VECES\np).-Publicidad móvil remolcada:\n1).-Con vehículo de tracción motriz de cuatro ruedas o más, en cualquier modalidad, sea en valla, cartelera giratoria, digital, etc., por 360 días, por unidad publicitaria (excepto pantalla electrónica).. 97.50 VECES\n2).-Con vehículo de tracción motriz o no motriz menor de cuatro ruedas, en cualquier modalidad, sea en valla, cartelera giratoria, digital, etc., por cara publicitada, por\n180 días, de unidad publicitaria (excepto pantalla electrónica).. 26.00 VECES\nq).-Anuncio adosado en plumas de acceso a estacionamientos, por cara de anuncio....... 8.53 VECES\nr).-Publicidad en nomenclatura vial, por placa con anuncio\n.......................... 32.50 VECES\ns).-Publicidad en banderas, banderolas o estandartes, pendón o gallardete en sitio público o privado, por pieza de anuncio por tres meses. 10.40 VECES\nt).-Anuncio ambulante conducido por personas, por anuncio por día....................... 3.25 VECES\nu).-Anuncio en tapial por cada\n12.50 M², por anuncio..... 39.00 VECES\nv).-Anuncio de proyección óptica, por anuncio.............. 65.00 VECES\nw).-Anuncio tipo caballete con superficie máxima de 1.20 m x 0.60 m., por 6 meses, por pieza..................... 11.70 VECES\nx).-Desmonte de estructura con grúa y acarreo........... 1,300.00 VECES\ny).-Almacenaje por día de la estructura................ 1.95 VECES\nz).-Nota aclaratoria........... 3.90 VECES aa).-Sonido de evento promocional en propiedad privada (al interior de locales comerciales) por día...... 5.20 VECES ab).-Anuncio instalado en puentes peatonales................ 13.00 VECES\nB).-Revalidación anual de licencia, al verificarse que aún se cumplen los requisitos de reglamento; con vigencia de hasta un año:\na).-Cartelera o anuncio autoportante, para uso exclusivo de comercio establecido en el mismo predio a publicitar. Por anuncio (a excepción de espectaculares) con superficies de:\n1).-De 0.01 M² a 1.00 M² en área de rótulo por cartelera o anuncio autoportante........... 6.50 VECES\n2).-De 1.01 M² a 5.99 M² en área de rótulo por cartelera o anuncio autoportante........... 26.00 VECES\n3).-De 6.00 M² a 30.00 M² en área de rótulo por cartelera o anuncio autoportante........... 45.50 VECES\nb).-Anuncio autosoportado o autoportante de propaganda comercial tipo espectacular, por anuncio................ 130.00 VECES\nc).-Anuncio tipo espectacular de pantalla electrónica y/o electromecánico o digital, incluye torre directorio de pantalla electrónica, pantallas en vehículos, con o sin movimiento, por cara de pantalla................... 260.00 VECES\nd).-Rótulos pintados o adosados para yonkes, recicladoras y centros de acopio. Por fachada o barda............ 10.40 VECES\ne).-Rótulo pintado, denominativo mayor de 2.01 M² y/o rótulo con propaganda comercial de productos que se venden en el establecimiento, por fachada\n........................... 3.90 VECES\nf).-Rótulo adosado, toldo, marquesina, por anuncio.\n1).-Denominativos de 2.01 M² hasta 3.99 M² y/o rótulo con propaganda comercial de productos que se venden en el establecimiento de\n0.01 M2 hasta 3.99 M².. 4.55 VECES\n2).-Mayor de 3.99 M² hasta\n15.00 M²............... 5.20 VECES\n3).-Mayor de 15.00 M² por M² o fracción excedente... 3.90 VECES\ng).-Rótulo electrónico y/o electromecánico de neón con o sin movimiento, por cara de anuncio, a excepción de espectaculares y/o carteleras autoportantes, pantallas de vehículos con superficies de:\n1).-De 0.01 M² a 1.50 M². 5.20 VECES\n2).-Mayor de 1.50 M² hasta\n10.00 M².............. 13.00 VECES\n3).-Mayor de 10.00 M2 por M² o fracción excedente... 13.00 VECES\nh).-Anuncio de evento cultural gratuito para la comunidad. 0.00 VECES\ni).-Torre directorio, por unidad\n(excepto electrónicas)..... 19.50 VECES\nj).-Mini porta cartel direccional, exclusivamente para desarrollos habitacionales e industriales nuevos, por pieza por tres meses...................... 7.80 VECES\nk).-Cobertizo publicitario y/o mobiliario urbano con publicidad (banca publicitaria, bote de basura o buzón con publicidad, etc.), por unidad.......... 13.00 VECES\nl).-Carro de sonido, por unidad por 90 días................ 7.80 VECES\nm).-Torreta en techo de camión o taxi, por unidad........... 9.75 VECES\nn).-Rótulo en vehículo público o privado, por anuncio....... 3.34 VECES ñ).-Valla publicitaria de hasta\n12.50 M²................... 26.00 VECES\no).-Valla publicitaria por cada\nM² excedente............... 5.72 VECES\np).-Publicidad móvil remolcada\n1).-Con vehículo de tracción motriz de cuatro ruedas o más, en cualquier modalidad, sea en valla, cartelera giratoria, digital, etc., por 360 días, por unidad publicitaria (excepto pantalla electrónica). 48.75 VECES\n2).-Con vehículo de tracción motriz o no motriz menor de cuatro ruedas, en cualquier modalidad, sea en valla, cartelera giratoria, digital, etc., por cara publicitada, por\n180 días, de unidad publicitaria (excepto pantalla electrónica).. 13.00 VECES\nq).-Anuncio adosado en plumas de acceso a estacionamiento, por cara de anuncio............ 6.50 VECES\nr).-Publicidad en banderas, banderolas o estandartes, pendón o gallardete en sitio público o privado, por pieza de anuncio por tres meses.. 5.85 VECES\ns).-Anuncio ambulante conducido por personas, por anuncio un día........................ 2.43 VECES\nt).-Publicidad en nomenclatura por placa con anuncio...... 16.25 VECES\nu).-Anuncio en tapial por cada\n12.50 M², por anuncio...... 19.50 VECES\nv).-Anuncio de proyección óptica, por anuncio............... 32.50 VECES\nw).-Anuncio tipo caballete con superficie máxima de 1.20 m x\n0.60 m, por 6 meses por pieza.\n........................... 5.85 VECES\nx).-Anuncio instalado en puentes peatonales por M².......... 6.50 VECES posterior a la fecha de vencimiento se agregará un 10% adicional, 20% dentro del segundo mes posterior al vencimiento y 30% dentro del tercer mes posterior al vencimiento. En estos casos la fecha de la licencia seguirá siendo la misma.\nC).-Licencia de regularización con vigencia de hasta un año, previamente con la licencia correspondiente y/o revalidación extemporánea de licencia, a partir del cuarto mes de vencimiento:\na).-Cartelera o anuncio autoportante para uso exclusivo de comercio establecido en el mismo predio a publicitar (a excepción de espectaculares), por cartelera:\n1).-De 0.01 M² a 1.00 M² en área de rótulo por cartelera............. 19.50 VECES\n2).-De 1.01 M² a 5.99 M² en área de rótulo por cartelera o anuncio autoportante........... 91.00 VECES\n3).-De 6.00 M² y hasta 30.00\nM² en área de rótulo, por cartelera o anuncio autoportante........... 130.00 VECES\nb).-Anuncio autosoportado o autoportante de propaganda comercial tipo espectacular por anuncio................. 390.00 VECES\nc).-Anuncio tipo espectacular de pantalla electrónica y/o electromecánica o digital, incluye torre directorio de pantalla electrónica, pantallas en vehículos, con o sin movimiento, por cara de pantalla.................... 780.00 VECES\nd).-Rótulo pintado, denominativo mayor de 2.01 M² y/o rótulo con propaganda comercial de productos que se venden en el 7.80 VECES establecimiento, por fachada.\n............................\ne).-Rótulos pintados, o adosados para yonkes, recicladoras y centros de acopio. Por fachada o barda..................... 23.40 VECES\nf).-Rótulo adosado, toldo, marquesina, por anuncio:\n1).-Denominativos de 2.01 M² hasta 3.99 M². y/o rótulo con propaganda comercial de productos que se venden en el establecimiento de\n0.01 M² hasta 3.99 M².. 9.10 VECES\n2).-Mayor de 3.99 M² hasta\n15.00 M²............... 14.30 VECES\n3).-Mayor de 15.00 M² por M² o fracción excedente... 11.70 VECES\ng).-Rótulo electrónico y/o electromecánico de neón, con o sin movimiento, a excepción de espectaculares, carteleras autoportantes y pantallas en vehículos con superficie:\n1).-De 0.01 M² a 1.50 M², por cara de anuncio........ 14.95 VECES\n2).-Mayor de 1.50 M² hasta\n10.00 M² por cara de anuncio............... 39.00 VECES\n3).-Mayor de 10.00 M² por M² o fracción excedente... 11.70 VECES\nh).-Anuncio de evento cultural gratuito para la comunidad.. 0.00 VECES\ni).-Torre directorio, por unidad\n(excepto electrónicas)...... 58.5 VECES\nj).-Mini porta cartel direccional exclusivamente para desarrollos habitacionales e industriales nuevos, por pieza por tres meses.............. 21.45 VECES\nk).-Cobertizo publicitario y/o mobiliario urbano con publicidad (banca 39.00 VECES publicitaria, bote de basura o buzón con publicidad), por unidad......................\nl).-Carro de sonido, por unidad, por 90 días................. 23.40 VECES\nm).-Torreta en techo de camión o taxi, por unidad............ 28.60 VECES\nn).-Rótulo en vehículo privado, por anuncio................. 18.20 VECES ñ).-Valla publicitaria de hasta\n12.50 M².................... 78.00 VECES\no).-Valla publicitaria por cada\nM² excedente por cara de unidad\n............................ 15.60 VECES\np).-Publicidad móvil remolcada con vehículo:\n1).-De tracción motriz de cuatro ruedas o más, en cualquier modalidad, en valla, cartelera giratoria, digital, etc.; por 360 días, por unidad publicitada (excepto pantalla electrónica).. 121.88 VECES\n2).-Con vehículo de tracción motriz o no motriz menor de cuatro ruedas en cualquier modalidad sea valla, cartelera giratoria, digital, etc.; por cara publicitada por\n180 días, de unidad publicitaria (excepto pantalla electrónica).. 32.50 VECES\nq).-Anuncio adosado en plumas de acceso a estacionamiento, por cara de anuncio....... 11.38 VECES\nr).-Publicidad en banderas, banderolas, estandartes, pendón o gallardete en sitio público o privado, por pieza de anuncio............... 15.60 VECES\ns).-Publicidad en nomenclatura por placa con anuncio..... 48.10 VECES\nt).-Anuncio ambulante conducido por personas, por anuncio, por día................... 4.88 VECES\nu).-Anuncio en tapial por cada\n12.50 M² o fracción, por anuncio................... 58.50 VECES\nv).-Anuncio de proyección óptica, por anuncio............... 97.50 VECES\nw).-Anuncio tipo caballete de\n1.20 m x 0.60 m por pieza, por 6 meses............... 15.60 VECES\nx).-Anuncio instalado en puentes peatonales por M²........ 19.50 VECES\nLas personas físicas, morales o unidades económicas que presten los servicios de publicidad así como los propietarios de los bienes inmuebles donde se instalen anuncios y las sucursales de giros comerciales e industriales y de instituciones de crédito, seguros y fianzas serán solidariamente responsables del pago de los créditos fiscales que se originen por incumplimiento de lo señalado en el presente inciso.\nD).-Licencia nueva con vigencia de hasta 15 días naturales, cuando la instalación se efectuará una vez que sea emitida esta licencia:\na).-Lona o barda en propiedad privada, por lona o barda.. 4.88 VECES\nb).-Volantes, por cada promoción\n........................... 4.88 VECES\nc).-Paquete de volantes con más de una información y/o promoción, que publiciten a más de un establecimiento comercial, industrial y/o de servicios. Por cada evento. 26.00 VECES\nd).-Figura inflable con publicidad, de duración temporal, por figura, por cada día................... 3.25 VECES\ne).-Cartel promocional en propiedad privada.......... 3.58 VECES\nf).-Cartel con información laica que beneficie a la comunidad en su desarrollo social, económico, educativo, cultural y deportivo y que no implique erogación económica alguna para los habitantes.\n........................... 0.00 VECES\ng).-Publicidad aérea\n(inscripciones en el aire) y/o zepelín por día........ 26.00 VECES\nE).-Revalidación temporal de licencia, al verificarse que se cumplan los requisitos de reglamento; con vigencia de hasta 15 días naturales:\na).-Lona o barda en propiedad privada, por cada lona o barda 3.58 VECES\nb).-Figura inflable con publicidad, de duración temporal, por día.......... 1.63 VECES\nc).-Volantes por cada promoción. EXENTO\nF).-Regularización de licencia con vigencia de hasta 15 días naturales, cuando se ha efectuado la instalación o el reparto sin contar con la licencia correspondiente:\na).-Lona o barda en propiedad privada, por cada lona o barda 10.73 VECES\nb).-Volantes, por cada promoción 10.73 VECES\nc).-Paquete de volantes con más de una información y/o promoción, que publiciten a más de un establecimiento comercial, industrial y/o de servicios. Por cada evento. 39.00 VECES\nd).-Figura inflable con publicidad, de duración temporal, por día.......... 4.88 VECES\ne).-Cartel promocional en propiedad privada.......... 6.50 VECES\nf).-Publicidad aérea\n(inscripciones en el aire) y/o zepelín por día........ 39.00 VECES\ng).-Volantes con información laica que beneficie a la comunidad en su desarrollo social, económico, educativo, cultural y deportivo, que no implique erogación económica alguna para los habitantes del municipio o con fines políticos, elaborados por partidos políticos directamente, o con información gubernamental de cualquiera de los tres niveles de gobierno.................. EXENTO\nG).-Por verificación y certificación de factibilidad para instalación, regularización y revalidación anual de aparatos de telefonía en la vía pública, existentes y de nueva instalación:\na).-Licencia para la instalación de teléfono público colocado en la vía pública existente y de nueva instalación, por aparato.................... 21.45 VECES\nb).-Regularización de teléfono público colocado en la vía pública, por aparato....... 28.60 VECES\nc).-Revalidación de teléfono público colocado en la vía pública en zona habitacional, por aparato............... 14.30 VECES\nd).-Revalidación de teléfono público colocado en la vía pública en zona comercial, por aparato................ 21.45 VECES\nH).-Copia certificada de documento por hoja........................... 1.30 VECES\nI).-Copia simple por hoja........... 0.65 VECES\nJ).-Corrección en documento oficial expedido(por error en expedición imputable al solicitante)..... 1.95 VECES\nK).-Por baja de anuncio............. 1.95 VECES\nXXXIV.-Las personas físicas o morales titulares de unidades económicas que realicen actividades con el público en general, que incluyan el comercio, servicios terceros, que por tal motivo y debido a que dichas actividades se consideran como de alto riesgo, deberán pagar en los meses de enero a marzo de cada ejercicio fiscal correspondiente, los derechos por la verificación y revisión anual del cumplimiento de disposiciones municipales, a través del despliegue técnico realizado por las dependencias del Municipio, incluyendo riesgos y aspectos de seguridad pública y protección civil, trabajo de campo y de gabinete derivado de las consecuencias de las actividades realizadas por las unidades económicas objeto del servicio. Lo anterior, conforme a la siguiente cuota: 200.00 VECES\nEn términos del artículo 73, fracción XXIX, punto 3º, de la instituciones de crédito no se encuentran incluidas en la obligación de pago de este derecho.\nLos contribuyentes que paguen este derecho no estarán obligados al pago de la cuota establecida en la fracción XXX de este artículo\nArtículo 32.-Es el documento expedido por la Dirección de\nAdministración Urbana, en el que se hace constar el estado físico de un predio urbano baldío; conforme lo define el Reglamento de la el Municipio de Tijuana y en base al artículo 7 de la presente Ley de Ingresos. del mismo, tendrán derecho a los siguientes descuentos en el pago anual del impuesto predial.\nA).-Predios Baldíos\nI.-Los predios baldíos deberán: estar libres de basura, maleza, escombro, cascajo o cualquier otro residuo, desecho o desperdicio................. 20%\nII.-Contar con guarniciones y banquetas en buen estado iluminación dentro del inmueble................ 10%\nIII.-Tener en sus colindancias barda, cerco de malla ciclónica, estructura metálica o similar debidamente rigidizados, con elementos estructurales uniformes. Libre de grafiti en muros propios o ajenos.............................. 10%\nIV.-Tener cerco similar a lo anterior en sus colindancias.................................... 5%\nTOTAL........................................... 45%\nB).-Cuando el predio baldío, se localice dentro de las zonas comerciales o industriales, además de lo anterior, deberá contener:\nI.-Si se ubica en esquina, contar con adecuaciones para personas con discapacidad 5%\nII.-Si se usa como bodega al aire libre para cualquier tipo de material, contar con barda de mampostería, concreto o similar al frente y en sus colindancias, pintada y en buen estado 5%\nIII.-Contar con árboles al frente del predio con espacio de seis metros entre cada uno 5%\nIV.-En caso de contar con anuncios espectaculares, Rótulos, Anuncios y Similares para el Municipio de\nTijuana Baja California 5%\nTOTAL............................................ 20%\nImagen Urbana:\nI.-Acreditar ser propietario o poseedor de un inmueble urbano que se encuentre baldío.\nII.-Al momento de inscribirse para adquirir el Certificado de\nMejoramiento de la Imagen Urbana, pagar la cuota correspondiente, en base a la siguiente tabla:\nCOSTO DEL CERTIFICADO\nUNIDAD DE MEDIDA Y\nACTUALIZACIÓN (UMA) VIGENTE\nVALOR CATASTRAL\n(UMA) VIGENTE\nDE A\n0 $37,200 0.33\n37,201 93,000 0.65\n93,001 186,000 1.95\n186,001 279,000 3.25\n279,001 372,000 5.20\n372,001 558,000 7.80\n558,001 744,000 10.40\n744,001 1’116,000 15.60\n1’116,001 1’488,000 19.50\n1’488,001 1’860,000 26.00\n1’860,001 2’232,000 32.50\n2’232,001 2’604,000 37.70\n2’604,001 2’976,000 42.25\n2’976,001 3’348,000 48.75\n3’348,001 3’720,000 55.25\n3’720,001 4’464,000 61.75\n4’464,001 5’208,000 71.50\n5’208,001 5’902,000 84.50\n5’902,001 6’696,000 94.25\n6’696,001 7’440,000 104.00\n7’440,001 8’164,000 113.75\n8’164,001 8’928,000 117.00\n8’928,001 9’672,000 120.25\n9’672,001 10’416,000 123.50\n10’416,001 11’160,000 126.75\n11’160,001 En adelante 130.00\nIII.-En caso de haber cumplido dentro del plazo de 6 meses con los requisitos señalados en los incisos “A” y “B” para obtener el estímulo fiscal correspondiente, la Dirección de Administración\nUrbana realizará una inspección otorgando en su caso, el\nCertificado de Mejoramiento de la Imagen Urbana.\nCAPÍTULO X\nQUE PRESTA LA DIRECCIÓN DE CATASTRO\nARTÍCULO 33.-Los servicios que presta la Dirección de Catastro, se pagarán conforme a la siguiente:\nTARIFA\nUNIDAD DE MEDIDA Y\nACTUALIZACIÓN (UMA) VIGENTE\nI.-Expedición y certificación de copias de documentos de archivo:\nA).-Páginas hasta tamaño legal:\na).-Copia simple o impresión simple, por primera página......................... 2.44 VECES\nb).-Copia simple o impresión simple, por cada página adicional a la primera 0.33 VECES\nc).-Copia certificada o impresión certificada, por primera página........ 3.25 VECES\nd).-Copia certificada o impresión certificada, por cada página adicional a la primera............................. 0.65 VECES\ne).-Copias certificadas de expediente solicitadas por una autoridad o dependencia............................ EXENTO\nB).-Planos en tamaños de pliego de papel:\na).-Copia simple de cartograma por metro cuadrado de papel bond................. 3.74 VECES\nb).-Copia certificada de cartograma.... 8.125 VECES\nc).-Copias certificadas de expedientes solicitadas por una autoridad o dependencia............................ EXENTO\nd).-Copia simple de cartograma......... 2.44 VECES\nII.-Constancias:\nA).-Constancia de no registro catastral 1.95 VECES\nB).-Certificación de datos descriptivos del inmueble.............................. 5.85 VECES\nC).-Certificación de datos cartográficos 4.88 VECES\nD).-Certificación de datos generales catastrales........................... 5.01 VECES\nE).-Certificación de datos descriptivos del inmueble urgente, pagarán adicionalmente sobre el costo del importe normal, un 200% (doscientos por ciento) más\nF).-Asignación de número oficial.......... 2.44 VECES\nIII.-Dictámenes:\nA).-Periciales de apeo y deslinde de bienes raíces solicitados a través de autoridad competente\na).-Dentro del área urbana............. 104 VECES\nb).-Fuera del área urbana.............. 156 VECES\nB).-Verificación en campo de aquellas superficies de taludes, cañadas, cauces de escurrimientos pluviales, predios agropecuarios en producción, con solicitud de reconsideración del importe a pagar............................... 17.55 VECES\nC).-Cálculo para aplicación de ajuste en zona de bulevar, rurales y suburbanos. 12.68 VECES\nD).-Cálculo para aplicar factores de demérito por profundidad interior o callejón y escarpado con pendiente mayor a 20% (veinte por ciento)............ 11.7 VECES\nE).-Por inspección en campo, de predios que requieran cambios de tasa, rectificación de superficie y valores de construcción 5.53 VECES\nIV.- Certificación de cartogramas:\nA).- Análisis, cálculo y verificación física de cartograma para certificación catastral, se pagará:\nPARA PREDIOS CON SUPERFICIES\nMAYORES DE HASTA\n001-00-00 Has. 005-00-00 Has. 79.30 VECES\n005-00-00 Has. 010-00-00 Has. 96.20 VECES\n010-00-00 Has. 025-00-00 Has. 114.40 VECES\n025-00-00 Has. 050-00-00 Has. 146.25 VECES\n050-00-00 Has. 075-00-00 Has. 175.50 VECES\n075-00-00 Has. 100-00-00 Has. 188.34 VECES\n100-00-00 Has. 250-00-00 Has. 205.40 VECES\n250-00-00 Has. 500-00-00 Has. 245.70 VECES\n500-00-00 Has. 1,000-00-00 Has. 286.00 VECES\nB).- Los predios que excedan de 1,000.00 Has., serán presupuestados por la Dirección de Catastro, previa solicitud del interesado.\nC).-Los deslindes y levantamientos urgentes, pagarán adicionalmente sobre el costo del importe normal, un 200%\n(doscientos por ciento) más.\nD).-Certificación de deslindes y levantamiento (menores de\nE).-Servicios del SIMUCO (Sistema Municipal de\nCoordenadas):\na).-Derechos de liga al sistema oficial........................... 6.50 VECES\nb).-Copia de cédula de información de vértices del sistema municipal de coordenadas....................... 1.63 VECES\nc).-Posicionamiento de vértices vía internet con GPS por pares de vértices:\n1).-En zona urbana................ 113.75 VECES\n2).-En área rural................. 227.50 VECES\nd).-Impresión de plano de la red de vértices del sistema municipal de coordenadas con cartografía básica por M² de impresión............... 5.85 VECES\nTodos los servicios de la Dirección de Catastro se pagarán previa su realización, en caso de cancelarse cualquier trabajo se solicitará su devolución, a la que se restará el 60% (sesenta por ciento) de su importe por gestiones administrativas realizadas.\nV).-Registro de peritos deslindadores:\nA).-Registro inicial, por alta............. 39.00 VECES\nB).-Revalidación anual..................... 20.80 VECES\nC).-Revalidación anual extemporánea........ 52.00 VECES\nVI).-Certificación de firmas:\nA).-Operaciones inmobiliarias y de garantía en operaciones inferiores a 10,000 veces la unidad de medida y actualización (UMA) vigente, establecido en el artículo 2191 del\nVII.-Acceso a la plataforma cartográfica y archivo digital vía internet\nA).-Por el acceso, a la plataforma cartográfica y archivo digital vía internet 75.40 VECES\nEl acceso a que se refiere esta fracción, será autorizada por términos de los formatos oficiales, a los peritos topógrafos adscritos y revalidados ante dicha autoridad.\nCatastro pagan derechos de registro y revalidación, el costo por el servicio a que se refiere el inciso A), de la presente fracción, será del 50% (cincuenta por ciento) de la cuota.\nVIII).-Otros:\nA).-Rectificación de la base de datos...... 2.60 VECES\nB).-La rectificación de base de datos urgente, pagará adicionalmente sobre el costo del importe normal, un 200%\n(doscientos por ciento) más.\nC).-Rectificación de la base de datos en caso de cambio de propietario................... 2.60 VECES\nEl derecho contenido en la fracción VIII inciso C) del presente artículo se pagará conjuntamente con el Impuesto sobre Adquisición de Inmuebles, siendo los fedatarios públicos responsables solidarios de su entero, cuando ante ellos se formalice o celebre la enajenación.\nEn caso de no recoger la documentación correspondiente al servicio solicitado a esta dirección dentro de los 40 días hábiles posteriores a la fecha señalada de entrega, el documento será destruido y deberá solicitarse nuevamente, en su caso.\nIX.-Información resultante de trabajos de aerofotogrametría:\nA).-Impresión de fotografías aéreas en formato 23cm x 23cm\na).-A cualquier escala (Fechas disponibles\n1993, 2003, 2005, 2008 y 2010)........... 5.72 VECES\nb).-Mosaico a color mancha urbana por cada\nM² de impresión........................... 26.00 VECES\nB).-Licencia de uso no comercial, de copia digital de aerofotogrametría por Km²:\na).-A cualquier escala (fechas disponibles\n1993, 2003, 2005, 2008 y 2010)........... 11.44 VECES\nC).-Licencia de uso no comercial, de impresión de cartografía resultante de restitución de foto aérea:\na).-Cartografía básica, contiene colonias, manzanas, nombres de calles y número de manzana por cada M² de impresión.......... 5.20 VECES\nb).-Impresión hoja tamaño carta, de ubicación cartográfica de predios en gabinete.................................. 8.91 VECES\nc).-Curvas de nivel con manzanero, por cada\nM² de impresión........................... 15.60 VECES\nd).-Cartografía básica, contiene manzanas, nombres de calles y número de manzana, tamaño carta, escala variable............. 1.30 VECES\ne).-Delimitación de zonas homogéneas...... 8.13 VECES\nD).-Licencia de uso no comercial, de información digital de cartografía resultante de restitución de foto aérea en formato PDF:\na).-Cartografía manzanera con información básica (manzanas, nombre de calle, delimitación de delegaciones y números de manzanas y colonias)..................... 149.50 VECES\nb).-Curvas de nivel a cada 5 M en mancha urbana, por Km²........................... 15.60 VECES\nc).-Cartografía manzanera con información básica (manzanero, nombre de calle y colonias), por Km² en formato PDF......... 5.33 VECES\nd).-Delimitación de zonas homogéneas...... 17.81 VECES\ne).-Lotificación por Km².................. 10.40 VECES\nPara efectos de la presente ley, específicamente en lo relativo a los servicios contemplados en su Artículo 33, fracción IX, incisos\nB) al D), se entiende por “Licencia de uso no comercial” al material impreso o digital, material que no podrá ser utilizado para uso diferente al personal, prohibiéndose su reproducción parcial o total por cualquier medio y/o su comercialización con para cada caso se lleve a cabo. ante la Dirección de Administración Urbana por parte del usuario, previo a la entrega del material en cuestión. Cualquier solicitud de uso diferente al personal, deberá ser turnado al H. Cabildo del\nAyuntamiento para su análisis y, en su caso, autorización.\nCAPÍTULO XI\nARTÍCULO 34.-Por los servicios que presta la Dirección Municipal de Protección al Ambiente, se cubrirán los derechos correspondientes conforme a la siguiente:\nTARIFA\nUNIDAD DE MEDIDA Y\nACTUALIZACIÓN (UMA) VIGENTE\nI).-Por los servicios que a continuación se señalan en materia de impacto ambiental:\nA).-Por la recepción, evaluación y resolución del Informe Preventivo Municipal sobre actividades de carácter público o privado destinadas al comercio y/o la prestación de servicios.................... 32.00 VECES\nEn el caso de los establecimientos que no utilicen combustible y tanques sujetos a presión; que no tengan un consumo superior a 100.00 M3 en agua; que no requieran dispositivos de control de emisiones a la atmósfera, ni de aguas residuales, que por su naturaleza se descarte la contaminación potencial del suelo; que no utilicen materiales peligrosos, no generen residuos peligrosos, y cuya superficie sea:\na).-Menor a 35.00 M²................... 17.55 VECES\nb).-De 35.00 M² a 70.00 M²............. 21.84 VECES\nc).-De 70.00 M² a 100.00 M²............ 26.20 VECES\nB).-Por la recepción, evaluación y resolución de la manifestación de impacto ambiental municipal, modalidad general, sobre actividades con impacto significativo de prestación de servicios:\na).-Hasta de 150.00 m2................. 56.00 VECES\nb).-Mayor de 150.01 y hasta 500 m2..... 72.00 VECES\nc).-Mayor de 500.01 y hasta 1000 m2.... 85.00 VECES\nd).-Mayor de 1000.01 m2................ 130.00 VECES\nC).-Por la recepción, evaluación y resolución de la\nManifestación de Impacto Ambiental Municipal, modalidad específica, sobre actividades de carácter público o privado destinadas al comercio y la prestación de servicios:\na).-Hasta de 500.00 m2................. 140.00 VECES\nb).-Mayor de 500.01 y hasta 1,000 m2... 160.00 VECES\nc).-Mayor a 1000.01 m2................. 180.00 VECES\nD).-Por el análisis de solicitud de prórroga para presentar la información adicional solicitada en materia de impacto ambiental 7.80 VECES\nE).-Por el análisis de solicitud de prórroga para dar cumplimiento a las condicionantes dictadas en la resolución de impacto ambiental................................. 7.80 VECES\nF).-Por la evaluación de modificaciones a proyectos autorizados en materia de impacto ambiental................................. 10.14 VECES\nG).-Por la solicitud de análisis para la\n8.19 VECES reconsideración condicionantes técnicas dictadas en la autorización en la resolución de impacto ambiental......................\nH).-Por el análisis de razón social, fusiones, transferencias de derechos y obligaciones relativas a la autorización en materia de impacto ambiental.............. 5.85 VECES\nI).-Por la recepción y evaluación de impacto ambiental municipal, para actividades clasificadas como bajo impacto............ 14.30 VECES\nJ).-Por la certificación del Plan General de\nPrevención y Respuesta a Emergencias y\nContingencias Ambientales................. 3.00 VECES\nII.-Por servicios relacionados con el registro de emisiones a la atmósfera:\nA).-Por el análisis de solicitud de registro fuentes emisoras a la atmósfera........... 57.20 VECES\nB).-Por el análisis de solicitud de revalidación de registro de fuentes emisoras a la atmósfera............................ 31.20 VECES\nC).-Por el análisis de solicitud de exención al trámite de registro de fuentes emisoras a la atmósfera.............................. 15.60 VECES\nD).-Por el análisis de prórroga para presentar información adicional requerida en el procesamiento de evaluación para el permiso de emisiones a la atmosfera....... 15.60 VECES\nE).-Análisis de solicitud de prórroga para dar cumplimiento a las condiciones técnicas, dictadas en el permiso de emisiones a la atmosfera................................. 15.60 VECES\nIII.-Certificación, cotejo y constancias de documentos emitidos y que se encuentran en el archivo de la Dirección:\nA).-Por cotejo de hoja por hoja........... 0.39 VECES\nB).-Por la expedición de información relativa al historial de la empresa....... 19.50 VECES\nIV.-Por expedición de opinión técnica para obtención, permiso, explotación y uso de propaganda publicitaria.................... 39.00 VECES\nV.-Prestadores de servicios ambientales:\nA).-Por la inscripción en el padrón de prestadores de servicios en materia de impacto ambiental......................... 55.64 VECES\nB).-Por la inscripción al padrón de auditores ambientales..................... 55.64 VECES\nVI.-Manejo integral de residuos sólidos urbanos:\nA).-En cuanto a las obligaciones en manejo integral de residuos sólidos urbanos...... EXENTA\nTijuana, B.C.:\na).-Pequeño Generador de residuos sólidos urbanos\nb).-Gran Generador de residuos sólidos urbanos\nGestión Integral de los Residuos se consideran como:\na).-Gran Generador: persona física o moral que genere una cantidad igual o superior a 10 toneladas en peso bruto total\nb).-Pequeño Generador: persona física o moral que genere una cantidad igual o mayor a 400 kg y menor a 10 toneladas otra unidad de medida.\nB).-Por el análisis de solicitud de modificación al registro municipal como generador de residuos sólidos urbanos..... 3.939 VECES\nC).-Por recepción y evaluación del plan de manejo de generadores de residuos sólidos urbanos................................... 24.245 VECES\nD).-Están obligadas las personas físicas o morales para la recepción y evaluación de la solicitud para el registro, para la realización de la actividad relativa a la prestación del servicio de manejo integral de residuos sólidos urbanos:.............\na).-El cobro por el análisis y evaluación por cada una de las etapas de manejo integral de residuos sólidos urbanos, solicitadas para su autorización....... 39.00 VECES integral: Las actividades de reducción en la fuente, separación, reutilización, reciclaje, co-procesamiento, tratamiento biológico, químico, físico o térmico, acopio, almacenamiento, transporte y disposición final de residuos, individualmente realizadas o combinadas de manera apropiada, para adaptarse a las condiciones y necesidades de cada lugar, cumpliendo objetivos de valoración, eficiencia sanitaria, ambiental, tecnológica, económica y social.\n1).-Por la actividad relativa a la recolección y transporte de residuos sólidos urbanos\n2).-Por la actividad relativa a la apertura de un centro de los mismos, en transferencia (por la segregación o separación de residuos), sin tratamiento de residuos; y disposición final\n3).-Por la actividad relativa a la Apertura de un centro de transferencia (por la segregación o separación de residuos) con tratamiento mecánico de residuos; y la disposición final en sitios autorizados\n4).-Por la operación de un centro de confinamiento de residuos sólidos urbanos.\nE).-Por el análisis para la reconsideración de condicionantes técnicas dictadas en la licencia del prestador de servicios para el manejo integral de residuos sólidos urbanos. 8.19 VECES\nF).-Por la evaluación en materia de manejo integral de residuos sólidos urbanos, por modificaciones o ampliaciones a las etapas de manejo integral de residuos sólidos urbanos................................... 39.00 VECES\nG).-Análisis de solicitud de prórroga para dar cumplimiento a condiciones técnicas dictadas en la licencia como prestador de servicio para manejo integral de residuos sólidos urbanos........................... 7.80 VECES\nH).-Análisis de solicitud de prórroga de la\n26.91 VECES vigencia de la licencia como prestador de servicio por el manejo integral de residuos sólidos urbanos...........................\nI).-Por la recepción y evaluación de la cédula de operación anual municipal....... 16.25 VECES\nJ).-Por la recepción, evaluación y resolución de la licencia ambiental integral 32.50 VECES\nVII.-Verificación e inspección por solicitud de remoción, tala o trasplante de árbol o jardín.\nA) Verificación e inspección por solicitud presentada................................ 5.00 VECES\nB) Por la remoción, tala o trasplante de árbol por motivo de construcción.......... 10.00 VECES\nC) Por la remoción, tala o trasplante por motivo de daños a particulares............ 7.50 VECES\nD) Por la remoción, tala o trasplante..... 7.50 VECES\nE) Por la solicitud o permiso para la remoción, tala de árboles que concluyeron su vida biológica o se encuentra seco........ 0.00 VECES de 60 años, cuando el trámite sea exclusivamente para ellos, y\nAdultas Mayores (INAPAM), Personas con Discapacidad (Previa\nSistema para el Desarrollo Integral de la Familia), se aplicará un beneficio del 50% (cincuenta por ciento) de descuento del costo total.\nCAPÍTULO XII\nMUNICIPAL\nARTÍCULO 35.-Por los servicios que presta la Dirección de Obras e\nInfraestructura Urbana Municipal, se cubrirán los derechos correspondientes conforme a la siguiente:\nTARIFA\nUNIDAD DE MEDIDA Y\nACTUALIZACIÓN (UMA) VIGENTE\nI.-Pago de derechos por inspección y opinión técnica de líneas exclusivas de uso comercial con vigencia de un año, cumpliendo con los siguientes requisitos:....................... 15.60 VECES\na).-Licencia de operación vigente al año en curso\nb).-Factibilidad autorizada del uso de suelo donde no se restringa el uso de la vía pública (calle), para estacionamiento de vehículos en espera de servicio y/o despacho\nc).-Predial vigente con cero adeudos\nd).-Documentos que demuestren la posesión o arrendamiento del predio utilizado\nII.-Pago de derechos por inspección y opinión técnica de reductores de velocidad en vía pública, cumpliendo con los requisitos siguientes:.............................. 2.60 VECES\na).-Recibo por pago de derechos de inspección y opinión técnica de reductores de velocidad en la vía pública.\nb).-Lista de anuencia vecinal del tramo impactado con al menos el 80% de los residentes, recabando nombre, dirección y número de contacto.\nc).-Anexar croquis de ubicación indicando el nombre de las vialidades aledañas.\nd).-Copia de identificación oficial.\ne).-Copia del recibo predial actual pagado.\nf).-Fotografías recientes (no de satelitales y/o de aplicación) indicando el sitio donde proponen sea colocado o colocados los dispositivos reductores de velocidad. y Gubernamentales.\nEn caso de emitir opinión técnica favorable, el interesado deberá de habilitar el reductor de velocidad de acuerdo a las especificaciones mencionadas en el oficio y plano de factibilidad. En caso de no cumplir con los requerimientos técnicos, el reductor de velocidad podrá ser retirado en cualquier momento por esta Dirección.\nTodo reductor de velocidad que no cuente con anuencia y/o no se encuentre debidamente regulado de acuerdo a lo estipulado en esta fracción podrá ser retirado por esta Dirección cuando así lo requieran las acciones de urbanización, desarrollo urbano, proyectos de mejora vial y cualquier otra intervención que ejecute el H. Ayuntamiento en beneficio de la movilidad, seguridad vial y bienestar de la ciudadanía.\nIII.-Pago de derechos por inspección y opinión técnica de rupturas de banquetas y pavimentos, que cumplan con los requisitos siguientes:... 13.00 VECES\na).-Solicitud de ruptura emitida por Comisión Estatal de\nServicios Públicos de Tijuana (vigencia de 3 meses).\nb).-Copia del recibo predial actual pagado.\nc).-Croquis de ubicación.\nd).-Fotografía impresa de la calle donde se requiere la ruptura.\ne).-Copia de la identificación del interesado y tramitador.\nf).-Permiso de uso de suelo (a partir de la segunda toma de agua o descarga sanitaria o en uso comercial).\nIV.-Pago de derechos por inspección y opinión técnica de valoración de daños en la vía pública 13.00 VECES\nV.-Deposito en garantía de rupturas de DE 18.20 A banquetas y pavimentos..................... 470.00 VECES\nVI.-Pago de derechos por inspección para de banquetas y pavimentos..................... 5.20 VECES\nVII.-Pago de derechos por bases de licitación para ejecución de obras y servicios........... 10.40 VECES\nVIII.-Pago de derechos por inspección y revalidación anual de opinión técnica de líneas exclusivas de uso comercial................... 5.20 VECES\nIX.-Pago de derechos por inspección y opinión técnica de postes y protección en vía pública.. 2.60 VECES\nX.-Pago de derechos por inspección y opinión técnica de línea roja frente acceso comercial, habitacional y/o industrial........ 2.60 VECES\nQuedan exentas de pago de los derechos establecidos en la fracción con discapacidad. anualmente su opinión técnica. línea exclusiva, notificándolo para tal efecto la autoridad emitido por esta Dirección. invalidada cuando así lo requieran las acciones de urbanización, desarrollo urbano, proyectos de mejora vial y cualquier otra intervención que ejecute el H. Ayuntamiento en beneficio de la movilidad y bienestar de la ciudadanía.\nCAPÍTULO XIII\nMUNICIPAL A TRAVÉS DE LA DIRECCIÓN DE SERVICIOS DE PROTECCIÓN\nCOMERCIAL Y DE VIGILANCIA AUXILIAR\nARTÍCULO 36.-Los derechos por los servicios de Protección\nComercial y Vigilancia Auxiliar que preste el Ayuntamiento a domicilios particulares, giros comerciales e instituciones de servicio u otros que lo soliciten, así como por servicios de guardia y servicio particular, se deberán cubrir de acuerdo a la siguiente:\nTARIFA\nUNIDAD DE MEDIDA Y\nACTUALIZACIÓN (UMA) VIGENTE\nI.-Servicios de vigilancia comercial en puntos fijos:\nA).-Por agente de protección comercial, por turno de 8 horas........................... 13.00 VECES\nB).-Por vigilancia armada en zonas habitacionales (contratadas por asociaciones civiles) por cada elemento armado, por turno de 8 horas................................. 13.00 VECES\nC).-Por vigilancia a instituciones gubernamentales, por cada elemento, por turno de 8 horas............................. 11.38 VECES\nII.-Servicios de agente de protección comercial:(elemento armado)\nA).-Agentes para servicios particulares\n\"Escolta\", por elemento armado, por turno de\n8 horas.................................... 13.65 VECES\nIII.-Por servicio de vigilancia auxiliar:\n(elemento desarmado)\nA).-En punto fijo por elemento desarmado, por turno de 8 horas........................... 6.50 VECES\nB).-Por vigilancia desarmada en zonas habitacionales (contratados por asociaciones civiles) por elemento desarmado por turno de\n8 horas.................................... 6.02 VECES\nIV.-Por la renta de una unidad patrulla:\nA).-Por la renta de unidad patrulla con un elemento armado, por turno de 6 horas...... 29.25 VECES\nV.-Por la renta de una unidad motocicleta:\nA).-Servicios de agentes funerales, desfiles, carreras atléticas y/o eventos deportivos, por turno de 6 horas........... 19.50 VECES\nVI.-Servicios extraordinarios:\nA).-Agente de protección comercial por turno de 6 horas................................. 13.00 VECES\nB).-Guardia de vigilancia auxiliar o por turno de 6 horas........................... 7.32 VECES\nC).-Por agente de protección comercial en eventos masivos, por turno de 6 horas...... 13.00 VECES\nD).-Por guardia de vigilancia auxiliar desarmado en eventos masivos, por turno de 6 horas...................................... 7.32 VECES\nVII.-Derechos por búsqueda judiciales o administrativas:\nA).-Búsqueda o localización de personas y/o domicilios a solicitud de autoridades judiciales y/o administrativas............. 0.00 VECES\nCuando la solicitud de búsqueda o localización de personas y/o domicilios, realizada por autoridades judiciales y/o administración pública municipal centralizada, desconcentrada o sus entidades auxiliares, dentro de procesos, procedimientos judiciales o administrativos en que estas sean parte, no se cobrarán los derechos correspondientes.\nVIII.- Por impartición de curso de manejo para automovilista:\nA).-Curso de manejo por persona............... 26.00 VECES\nIX.- Las personas físicas o morales que se dediquen a la instalación de alarmas comerciales e industriales, así como a los servicios de seguridad privada y vigilancia, deberán obtener autorización escrita de esta Dirección, debiendo cubrir las siguientes tarifas:\nA).-Por solicitud de opinión por escrito....... 39.00 VECES\nPor cada hora adicional de servicio contratado, de acuerdo al tipo servicio de protección comercial y vigilancia auxiliar, se pagará proporcional de acuerdo a la tarifa establecida.\nCAPÍTULO XIV\nQUE PRESTA LA DIRECCIÓN DE BOMBEROS\nARTÍCULO 37.-Los servicios que presta la Dirección de Bomberos a giros comerciales, industriales y de los sectores público y privado, se causarán conforme a la siguiente:\nTARIFA\nUNIDAD DE MEDIDA Y\nACTUALIZACIÓN (UMA) VIGENTE\nI.-Por factibilidad de proyectos o por revisión de proyectos de construcción (por m²):\nA).-Casa-habitación....... 0.052 VECES\nB).-Comercial............. 0.101 VECES\nC).-Industrial hasta 2,500\nM²........................ 0.13 VECES\nD).-Mayor de 2,500.00 M².. 0.091 VECES\nE).-Barda, fachada y remodelaciones............ 0.052 VECES\nLos servicios por factibilidad de proyectos o revisión de proyectos de modificación o cambios de construcción serán prestados con base en la tarifa establecida en la presente fracción.\nII.-Regularización de dispositivos de seguridad en edificios existentes a petición de parte y revalidación anual:\nA).-Comercio en pequeño, de hasta 50.00 M² de superficie............................. 6.50 VECES\na).-Personas de la tercera edad con credencial del INAPAM.................. 2.60 VECES\nb).-Madres Jefas de familia sin cónyuge o pareja en aptitud de trabajar, que son el único sostén del hogar, con hijo o hijos menores de edad y/o personas con capacidades diferentes................. 2.60 VECES\n15.60 VECES\nB).-Despachos de profesionistas y giros de servicio..................................\nC).-Giros comerciales:\na).-Billares, expendios, autoservicios, bares, ferreterías, refaccionarias, desmanteladoras, llanteras, taller mecánico, yonkes....................... 16.90 VECES\nb).-Loncherías, panaderías, tortillerías, lavanderías, tiendas de ropa, misceláneas, farmacias, papelerías, librerías y templos religiosos............................. 13.00 VECES\nc).-Loncherías, panaderías, tortillerías, lavanderías, tiendas de ropa, misceláneas, farmacias, papelerías, librerías y templos religiosos, menor a 50 M² de construcción 10.40 VECES\nD).-Bar turístico, café cantante, restaurante, mercado, supermercado, bodegas de distribución, salón de renta, hospital, salas cinematográficas, teatros........ 31.20 VECES\nE).-Discotecas, tiendas departamentales, plazas y/o centro comercial y clubes\nF).-Moteles:\na).-Hasta 10 habitaciones.............. 20.80 VECES\nb).-De 11 a 20 habitaciones............ 28.60 VECES\nc).-De 21 habitaciones en adelante..... 36.40 VECES\nG).-Hoteles:\na).-Hasta 30 habitaciones.............. 36.40 VECES\nb).-De 31 habitaciones en adelante..... 53.30 VECES\nH).-Edificios Educativos:\na).-Hasta 10 aulas..................... 15.60 VECES\nb).-De 11 aulas en adelante............ 24.70 VECES\nc).-Guarderías y estancias Infantiles.. 16.90 VECES\nI).-Giros de alto riesgo:\na).-Distribuidoras de gases, combustibles y lubricantes, oxígenos y acetilenos, polvorines y demás de alto riesgo................................. 182.00 VECES\nb).-Centros de apuestas, apuestas remotas, salas de sorteos de números y/o casinos, Dictamen de Operación......... 260.00 VECES\nc).-Gasolineras, Estaciones de gasolina, Depósitos y/o almacén de distribución de combustible y lubricantes y demás de alto riesgo................................. 182.00 VECES\nd).-Centro de acopio y/o recicladora hasta 400 M² de uso.................... 52.00 VECES\ne).-Centro de acopio y/o recicladora de\n400.01 M² a 1,000.00 M² de uso......... 130.00 VECES\nf).-Centro de acopio y/o recicladora mayor de 1,000.01 M² de uso............ 260.00 VECES\nJ).-Otros giros no especificados.......... 15.60 VECES\na).-Edificios Industriales:\n1).-Micro industria de 1 a 15 empleados.......................... 11.70 VECES\n2).-Pequeña industria de 16 a 50 empleados.......................... 18.20 VECES\n3).-Industria mediana de 51 a 100 empleados.......................... 36.40 VECES\n4).-Macro industria:\ni).-De 101 a 500 empleados...... 53.30 VECES ii).-De 501 a 1,000 empleados 89.70 VECES iii).-De 1,001 empleados en adelante........................ 107.90 VECES\nK).-Comercios de 51.00 M² a 100.00 M² no especificados............................. 10.40 VECES\nL).-Hospitales, clínicas y sanatorios.... 46.00 VECES\nM).-Consultorios......................... 26.00 VECES\nN).-Inspecciones subsecuentes por prorroga, 50% (cincuenta por ciento) del importe del pago de derechos realizados en la primer inspección(Sin perjuicio de la aplicación de las sanciones que prevé el reglamento específico, en el caso de correspondientes).\nIII.-Análisis de factibilidad para la prestación de servicios de bomberos en casos de emergencia:\nA).-Desarrollo habitacional.............. 57.20 VECES\nB).-Desarrollo industrial y comercial:\na).-Hasta 5,000.00 M² de superficie.... 36.40 VECES\nb).-Mayor de 5,000.00 M² de superficie. 54.60 VECES\nIV.-Certificación de daños en bienes siniestrados:\nA).-Todos los daños en general............ 10.40 VECES\nQuedan exceptuadas del pago de este derecho, aquellas casas habitación que no se encuentren aseguradas al ocurrir el siniestro.\nB).-Cambio y/o aumento de giro comercial de\nExpediente activo............ 10.40 VECES\nV.-Revisión de giros comerciales para obtención de autorización para la venta de bebidas alcohólicas:\nA).-Abarrotes, licorerías, sub agencias, expendios, billares y autoservicios....... 37.70 VECES\nB).-Restaurant-bar, bar turístico, café cantante, mercado, supermercado y bodegas de distribución.............................. 54.60 VECES\nC).-Discotecas, tiendas departamentales, hoteles y moteles......................... 88.40 VECES\nVI.-Expedición de documento por certificación y revalidación de equipo, dispositivos de seguridad y empresas:\n2.60 VECES\nA).-Vivienda..............................\nB).-Comercio.............................. 5.53 VECES\nC).-Industria............................. 13.00 VECES\nD).-Revisión y certificación de sistemas hidráulicos contra incendios.............. 49.00 VECES\nE).-Revalidación y certificación de medidas de seguridad de giros comerciales hasta\n200.00 M²................................. 3.90 VECES\nF).-Revalidación y certificación de medidas de seguridad de giros comerciales mayor de\n200.00 M² a 400.00 M²..................... 5.20 VECES\nG).-Certificación de empresas dedicadas a instalaciones de sistemas de alarma....... 52.00 VECES\nH).-Certificación de empresas de instalación de sistemas contra incendio... 52.00 VECES\nI).-Certificación de empresas de capacitación a personas morales o físicas en el área de formación de brigadas de primeros auxilios, uso y manejo de extintores, uso y manejo de mangueras, materiales peligrosos, sistemas administrativos de emergencia, previa acreditación de cursos............. 52.00 VECES\nJ).-Certificación de empresas dedicadas a la revisión de instalaciones eléctricas\n(termografía)............................. 52.00 VECES\nVII.-Revisión de las condiciones de seguridad en las instalaciones temporales:\nA).-Circos (por ubicación)............... 18.2 VECES\nB).-Juegos mecánicos por aparato mecánico revisado.................................. 3.60 VECES\nC).-Kermes................................ 12.10 VECES\nD).-Exposiciones, ferias, bailes populares, car show, eventos deportivos, eventos en vía pública, obras de teatro hasta 5,000 personas.................................. 36.00 VECES\nE).-Macro eventos, eventos deportivos mayor de 5,000 personas......................... 62.00 VECES\nF).-Conciertos............................ 68.50 VECES\nVIII.-Certificación de empresas dedicadas a mantenimiento, renta y/o venta de extintores portátiles:\nA).-Certificación de actividad comercial e instalaciones............................. 52.00 VECES\nIX.-Servicios especiales:\nA).- Cálculo de ocupación para cupo máximo. 32.50 VECES\nB).- Simulacros a petición de parte:\na).-Formación de brigadas.............. 19.50 VECES\nb).-Manejo de extintores............... 26.00 VECES\nC).- Curso:\na).-Formación de brigadas.............. 24.70 VECES\nb).-Manejo de extintores............... 33.80 VECES\nD).-Uso de equipo por hora:\na).-Máquina extinguidora............... 59.40 VECES\nb).-Máquina de iluminación............. 59.40 VECES\nc).-Máquina escala..................... 59.40 VECES\nd).-Máquina rescate.................... 59.40 VECES\ne).-Unidad de rescate.................. 59.40 VECES\nf).-Unidad tanque cisterna............. 59.40 VECES\ng).-Ambulancia......................... 59.40 VECES\nh).-Unidad de materiales peligrosos.... 59.40 VECES\nLos servicios especiales a que hace referencia este inciso, cuando se trate de escuelas públicas, quedarán exentos de pago, la misma institución.\nSe considera un servicio especial: cuando los inmuebles seguridad, y este servicio se exceda más de 4 horas de operaciones combatiendo el incendio, incidente o siniestro, después de la por hora.\nX.-Revisión de explosivos:\nA).-Revisión de polvorines o permisos de explosivos, previo acreditamiento de contar con permiso de la Secretaría de la Defensa\nNacional (SEDENA)........................ 81.9 VECES\nB).-Certificación de medidas de seguridad de fuegos pirotécnicos para temporada navideña 81.25 VECES\nC).-Certificación de medidas de seguridad de arbolitos de navidad para temporada navideña 48.75 VECES\nD).-Actividades pirotécnicas.............. 52.50 VECES\nE).-Revisión de establecimientos con venta de juegos pirotécnicos, que estén permitidos por la ley, en giros comerciales, abarrotes, autoservicios, mercados, farmacias, etc... 52.00 VECES\nXI.-Simulacro de evacuación por incendio..... 26.00 VECES\nXII.-Simulacro de incendio................... 30.00 VECES\nXIII.-Aprobación de medidas de seguridad en edificaciones,\nA).-Vehículos que transportan materiales peligrosos, combustibles líquidos y/o gases..................................... 29.50 VECES\nB).-Edificación e instalaciones que en su inventario de materiales peligrosos almacenen, cantidades menores a 200 litros\n(líquidos), o 200 kilos (sólidos), o 200 104.00 VECES pies cúbicos (gases).....................\nC).-Edificación e instalaciones que en su inventario de materiales peligrosos almacenen, cantidades iguales o mayores a\n200 litros (líquidos), o 200 kilos\n(sólidos), o 200 pies cúbicos (gases)..... 182.00 VECES\nARTÍCULO 38.-Los servicios extraordinarios que preste la Dirección de Bomberos a solicitud de la parte interesada, se pagarán conforme al presupuesto que al efecto formule la propia Dirección, mismo que deberá ser proporcional a la naturaleza del servicio que se preste y quedar comprendido entre los 5.00 y 200.00 VECES la unidad de medida y actualización (UMA) vigente.\nCAPÍTULO XV\nQUE PRESTA LA SECRETARÍA DE DESARROLLO ECONÓMICO\nDERECHOS POR LA EXPEDICIÓN DE PASES DEL PROGRAMA DE PASES DE CRUCE\nÁGIL A USUARIOS DE SERVICIOS MÉDICOS Y TURISMO DE NEGOCIOS Y\nESTUDIANTES TRANSFRONTERIZOS PROCEDENTES DE Y CON DESTINO A LOS\nESTADOS UNIDOS DE AMÉRICA, OBTENCIÓN DEL PERMISO PROVISIONAL DE 90\nDÍAS Y OPERACIÓN DEL PROGRAMA DE APERTURA RÁPIDA DE EMPRESAS\n“SARE”.\nARTÍCULO 39.-El cobro de derechos por los servicios que presta la sujetándose a lo siguiente:\nTARIFA\nUNIDAD DE MEDIDA Y\nACTUALIZACIÓN (UMA) VIGENTE\nI.-La emisión de pases del programa de pases de cruce ágil web del H. Ayuntamiento, dispuesta para el programa, y se pagará de la siguiente manera:\nA).-Costo por pase para los contribuyentes que estén adheridos al programa, que presten servicios médicos o presten servicios asociados o de apoyo a los clientes de servicios médicos.......................... 3.58 VECES\nB).-Costo por pase a cámaras, empresas y organismos empresariales no gubernamentales, así como instituciones públicas o asociaciones sin fines de lucro adheridos al programa, que presten servicios de turismo de negocios, o que impulsen y promuevan el desarrollo económico y empresarial en la región..................................... 5.98 VECES\nC).-Costo del pase mensual para estudiantes transfronterizos adheridos al programa..... 53.60 VECES\nD).-Costo por acompañante adicional (sin considerar al conductor) por cada pasajero, aplica solo a los vehículos catalogados como\nE).-Costo por inscripción o renovación anual al programa de cruce ágil de usuarios de servicios médicos, turismo de negocios y estudiantes trasnfronterizos............... 38.55 VECES\nII.-Por la obtención del permiso provisional de operación por 90 días naturales para giros de de apertura inmediata......................... 3.64 VECES\nIII.-Por la obtención de la licencia de operación mercantil, además del dictamen de uso de suelo, certificado de medidas de seguridad y registro como generador de residuos sólidos urbanos a través del Programa sistema de apertura rápida de empresas “SARE” en 3 días hábiles....................................... 38.48 VECES\nCAPITULO XVI\nQUE PRESTA LA DIRECCIÓN DE PROTECCIÓN CIVIL\nARTÍCULO 39 BIS.-Los servicios que presta la Dirección de\nProtección Civil a giros comerciales, industriales, de servicios, los sectores públicos, privados y sociales, se causarán conforme a la siguiente:\nTARIFA\nUNIDAD DE MEDIDA Y\nACTUALIZACIÓN (UMA)VIGENTE\nI).-Revisión de las condiciones de seguridad en instalaciones temporales, para la anuencia correspondiente:\nA).-Circos:\na).-Una pista......................... 9.75 VECES\nb).-dos o más pistas.................. 19.50 VECES\nB).-Juegos mecánicos...................... 13.00 VECES\nC).-Exposiciones, ferias y kermeses....... 6.50 VECES\nD).-Exhibición de autos, motocicletas..... 19.50 VECES\nE).-Carreras o competencias de vehículos 26.00 VECES\nF).-Paseo, caminata rural o turística..... 13.00 VECES\nG).-Eventos deportivos:\na).-De Hasta 500 asistentes........... 13.00 VECES\nb).-De 501 hasta 1,000 asistentes..... 26.00 VECES\nc).-De 1,001 hasta 2,000 asistentes... 39.00 VECES\nd).-De 2,001 hasta 5,000 asistentes... 91.00 VECES\ne).-De 5,001 hasta 10,000 asistentes.. 156.00 VECES\nf).-Más de 10,001 asistentes.......... 180.00 VECES\nH).-Eventos gastronómicos................. 13.00 VECES\nI).-Espectáculos en lugar cerrado:\na).-De hasta 500 asistentes........... 26.00 VECES\nb).-De hasta 1,500 asistentes. 52.00 VECES\nc).-De hasta 3,000 asistentes......... 78.00 VECES\nd).-De más de 3,000 asistentes........ 117.00 VECES\ne).-De más de 5,000 asistentes........ 156.00 VECES\nJ).-Espectáculos en lugar abierto:\na).-De hasta 500 asistentes........... 26.00 VECES\nb).-De hasta 1,500 asistentes......... 52.00 VECES\nc).-De hasta 3,000 asistentes......... 78.00 VECES\nd).-De más de 3,000 asistentes........ 117.00 VECES\ne).-De más de 9,000 asistentes........ 156.00 VECES\nK).-Otros eventos menores no especificados 26.00 VECES\nLos servicios a los que hace referencia esta fracción, cuando se trate de instituciones de asistencia social y no lucrativa, quedarán exentos de pago, siempre y cuando sea en las instalaciones de la misma institución.\nII).-Servicios especiales\nA).-Simulacros de gabinete................ 26.00 VECES\nB).-Simulacros de evacuación total conforme a lo siguiente:\na).-de hasta 100 participantes........ 5.00 VECES\nb).-de hasta 250 participantes........ 10.00 VECES\nc).-de hasta 500 participantes........ 15.00 VECES\nd).-de hasta 750 participantes........ 20.00 VECES\ne).-de hasta 1000 participantes....... 30.00 VECES\nf).-de hasta 2000 participantes....... 40.00 VECES\ng).-de 2,000 participantes en adelante 52.00 VECES\nC).-Asesorías PIPC........................ 26.00 VECES\nD).-Opiniones de riesgos de periodos para futura construcción....................... 10.00 VECES\n20.00 VECES\nE).-Revisión y autorización de planes de emergencia de inmuebles en construcción por vigencia de un año........................\nIII).-De los servicios que prestan las empresas\n(grupos) de respuesta a emergencia:\nA).-Empresa de servicios pre-hospitalarios, traslados, y/o transporte de pacientes.... 13.00 VECES\nLos servicios a que hace referencia esta fracción, cuando se fines no sean lucrativos, quedarán exentos de pago, siempre y cuando se acredite con documentación oficial.\nIV).-Por revisión, aprobación del programa interno de protección civil:\nA).-Instituciones Educativas Privadas y de\nAsistencia:\na).-Instituciones Educativas:\n1).-Jardín de Niños................ 13.01 VECES\n2).-Escuela Primaria............... 13.01 VECES\n3).-Escuela Secundaria............. 15.61 VECES\n4).-Escuela Preparatoria y/o Técnica 19.51 VECES\n5).-Colegio y/o Universidad........ 19.51 VECES\n6).-Centros de Investigación y\nDesarrollo........................ 26.03 VECES\n7).-Otros no especificados......... 26.03 VECES\nb).-Guarderías y estancias infantiles, de acuerdo a su capacidad:\n1).-De hasta 10 niños.............. 13.01 VECES\n2).-De hasta 25 niños.............. 15.61 VECES\n3).-De hasta 50 niños.............. 19.51 VECES\n4).-De hasta 99 niños.............. 26.03 VECES\n5).-Más de 100 niños............... 32.51 VECES\nc).-Casas de cuidados y centros de tareas............................ 13.01 VECES\nd).-Albergues......................... 15.61 VECES\ne).-Casa Hogar o de Asistencia........ 13.39 VECES\nf).-Centros de Rehabilitación:\n1).-Física......................... 19.51 VECES\n2).-De adicciones.................. 26.03 VECES\ng).-Otros no especificados............ 26.03 VECES\nB).-Comercios y de servicios:\na).-Librería, papelería, ferretería, oficina, miscelánea, panadería, tienda de ropa, restaurante, lavandería, farmacia y expendio de comida......... 13.01 VECES\nb).-Bar turístico, café-cantante, autoservicio, restaurante bar, discoteca, expendio de bebidas alcohólicas, billares, mercado, motel y hotel................................. 23.40 VECES\nc).-Sala cinematográfica, lugares para eventos sociales, centro de convenciones, teatro, sala de exposiciones, bodega de distribución, supermercado y tienda departamental... 31.21 VECES\nd).-Centros de atención telefónica.... 40.00 VECES\ne).-Otros Giros no especificados:\n1).-Menor de 150 M² de construcción 15.61 VECES\n2).-De 150 a 300 M² de construcción 19.51 VECES\n3).-De 301 a 500 M² de construcción 26.01 VECES\n4).-Mayor de 500 M² de construcción 32.51 VECES\nC).-Instituciones de Salud:\na).-Clínica y centro de salud......... 13.01 VECES\nb).-Centro médico..................... 15.61 VECES\nc).-Hospital.......................... 26.03 VECES\nd).-Laboratorio....................... 6.00 VECES\nD).-Instalaciones Industriales:\na).-Micro industria (hasta 25 empleados)........................... 19.51 VECES\nb).-Pequeña Industria (26 a 100 empleados)........................... 26.03 VECES\nc).-Mediana Industria (101 a 250 empleados)........................... 39.03 VECES\nd).-Macro Industria (más de 250 empleados)........................... 52.04 VECES\nE).-Giros considerados de alto riesgo:\na).-Estación de gasolina y gas para carburación........................... 32.51 VECES\nb).-Distribuidor de gas............... 39.03 VECES\nc).-Distribuidor de combustible y lubricante............................ 39.03 VECES\nd).-Almacén de materiales peligrosos.. 52.04 VECES\ne).-Establecimiento con venta de pirotecnia............................ 39.03 VECES\nf).-Centro de apuestas, apuestas remotas, sala de sorteos de números y/o casinos............................... 65.05 VECES\ng).-Recicladoras y-o centros de acopio 42.00 VECES\nh).-Fabricantes y ensambladoras de tarimas............................... 40.00 VECES\ni).-Otros giros de alto riesgo........ 39.03 VECES\nF).-Revisión y autorización de Planes de\nEmergencia de Inmuebles en construcción por vigencia de 1 año.........................\n20.00 VECES\nG).-Otros Giros no especificados.......... 26.03 VECES\nV).-Por revalidación del programa interno de protección civil:\nA).-Instituciones Educativas Privadas y de\nAsistencia:\na).-Instituciones Educativas:\n1).-Jardín de Niños................ 6.50 VECES\n2).-Escuela Primaria............... 6.50 VECES\n3).-Escuela Secundaria............. 7.80 VECES\n4).-Escuela Preparatoria y/o Técnica 9.75 VECES\n5).-Colegio y/o Universidad........ 9.75 VECES\n6).-Centros de Investigación y\nDesarrollo......................... 13.00 VECES\n7).-Otros no especificados......... 19.50 VECES\nb).-Guarderías y estancias infantiles, de acuerdo a su capacidad:\n1).-De hasta 10 niños.............. 6.50 VECES\n2).-De hasta 25 niños.............. 7.80 VECES\n3).-De hasta 50 niños.............. 9.75 VECES\n4).-De hasta 99 niños.............. 13.00 VECES\n5).-Más de 100 niños............... 16.25 VECES\nc).-Casas de cuidados y centros de tareas 6.50 VECES\nd).-Albergues...................... 7.80 VECES\ne).-Casa Hogar o de Asistencia..... 6.68 VECES\nf).-Centros de Rehabilitación:\n1).-Física......................... 9.75 VECES\n2).-De adicciones.................. 13.00 VECES\ng).-Otros no especificados......... 13.00 VECES\nB).-Comercios y de servicios:\na).-Librería, papelería, ferretería, oficina, miscelánea, panadería, tienda de ropa, restaurante, lavandería, farmacia y expendio de comida......... 6.50 VECES\nb).-Bar turístico, café-cantante, autoservicio, restaurante bar, discoteca, expendio de bebidas alcohólicas, billares, mercado, motel y hotel................................. 11.70 VECES\nc).-Sala cinematográfica, lugares para eventos sociales, centro de convenciones, teatro, sala de exposiciones, bodega de distribución, supermercado y tienda departamental... 15.60 VECES\nd).-Centros de atención telefónica.... 20.00 VECES\ne).-Otros Giros no especificados:\n1).-Menor de 150 M² de construcción 7.80 VECES\n2).-De 150 a 300 M² de construcción 9.75 VECES\n3).-De 301 a 500 M² de construcción 13.00 VECES\n4).-Mayor de 500 M² de construcción 16.25 VECES\nC).-Instituciones de Salud:\na).-Clínica y centro de Salud...... 6.50 VECES\nb).-Centro médico.................. 7.80 VECES\nc).-Hospital....................... 13.00 VECES\nd).-Laboratorios................... 3.00 VECES\nD).-Instalaciones Industriales:\na).-Micro industria (hasta 25 empleados)......................... 9.75 VECES\nb).-Pequeña Industria (26 a 100 empleados)......................... 13.00 VECES\nc).-Mediana Industria (101 a 250 empleados)......................... 19.50 VECES\nd).-Macro Industria (más de 250 empleados)......................... 26.00 VECES\nE).-Giros considerados de alto riesgo:\na).-Estación de gasolina y gas para carburación........................... 16.25 VECES\nb).-Distribuidor de gas............... 19.51 VECES\nc).-Distribuidor de combustible y lubricante............................ 19.51 VECES\nd).-Almacén de materiales peligrosos.. 26.01 VECES\ne).-Establecimiento con venta de pirotecnia............................ 19.51 VECES\nf).-Centro de apuestas, apuestas remotas, sala de sorteos de números y/o casinos............................... 32.53 VECES\ng).-Otros giros de alto riesgo........ 19.51 VECES\nh).-Recicladoras y/o Centros de Acopio 21.00 VECES\ni).-Fabricantes y ensambladoras de tarimas............................... 20.00 VECES\nF).-Otros Giros no especificados.......... 13.00 VECES\nVI).-Por revisión y aprobación del programa de atención de emergencias................. 19.50 VECES\nVII).-Por revisión y aprobación del programa interno de protección civil para obras en proceso de construcción remodelación y demolición.............................. 19.50 VECES\nCAPÍTULO XVII\nDERECHOS POR ARRASTRE DE VEHÍCULOS\nARTÍCULO 40.-Los derechos por arrastre de vehículos se cobrarán final, debiendo cubrirse siempre y cuando la maniobra se realice, de acuerdo con la siguiente:\nTARIFA\nUNIDAD DE MEDIDA Y\nACTUALIZACIÓN (UMA) VIGENTE\nI.-Por arrastre:\nA).-Automóvil, camioneta y pick-up........ 8.45 VECES\nB).-Camiones de pasajeros................. 13.00 VECES\nC).-Camiones de servicio público o particular de carga................... 13.00 VECES\nD).-Auto-tractores por cada maniobra de arrastre.............................. 26.00 VECES\n1).-Por caja......................... 13.00 VECES\n2).-Semiremolque y/o doble remolque\n(tipo dolly)........................ 13.00 VECES\nE).-En caso de que sean necesarias maniobras especiales se aplicará lo siguiente:\n1).-Cuando el vehículo que se va a remolcar no cuenta con llantas y/o se encuentra imposibilitado de rodar utilizándose el dolly, así como en camiones y tractocamiones, desatorado en los frenos de aire, volcaduras, salidas de carretera, utilización en dos o más ocasiones de equipo para arrastre.......... 2.60 VECES\n2).-Uso de grúa para vehículo con defensa adaptada a la original\n(spoiler)....................... 2.60 VECES\n3).-Uso de maniobra por parte del operador para retirar vehículo de cajón de estacionamiento con alto grado de dificultad.............. 2.60 VECES\n4).-Uso de maniobras con alto grado de dificultad cuando sea necesario retirar el cambio en la transmisión, siendo éste de tracción trasera y/o conlleve un alto riesgo para el operador de la grúa............................. 2.60 VECES\n5).-En caso de volcadura de vehículos ligeros en los siguientes casos.. 5.20 VECES\na).-Volcadura en áreas planas y aceras de carril de rodamiento.\nb).-Volcadura cuando el vehículo sale del camino y cae en un desbarrancamiento a menos de\n10 M de distancia del carril de arrollamiento.\nc).-Volcadura cuando el vehículo sale del camino y cae en un desbarrancamiento a más de 10\nM de distancia del carril de arrollamiento.\nd).-Volcadura cuando el vehículo cae en un desbarrancamiento poniéndose en riesgo el patrimonio y seguridad de terceras personas.\n6).-En caso de volcadura de vehículos de carga y/o autobuses, en los siguientes casos................. 29.25 VECES\na).-Volcadura en áreas planas y aceras de carril de rodamiento.\nb).-Volcadura cuando el vehículo sale del camino y cae en un desbarrancamiento a menos de\n10 M de distancia del carril de arrollamiento\nc).-Volcadura cuando el vehículo sale del camino y cae en un desbarrancamiento a más de 10\nM de distancia del carril de arrollamiento\nd).-Volcadura cuando el vehículo cae en un desbarrancamiento poniéndose en riesgo el patrimonio y seguridad de terceras personas\nF).-Motocicletas.......................... 10.40 VECES\nG).-Bicicletas............................ 1.30 VECES\nII.-Maniobras inconclusas de grúa, por el evento de presentarse el vehículo grúa al lugar donde exista violación a lo reglamentado, con infracción por escrito pero no se realice el servicio de remolque por causas no imputables al servicio de grúa, se pagarán por vehículo las cuotas siguientes:\nA).-Automóviles, camionetas y pick-ups.... 3.90 VECES\nB).-Camiones de pasajeros (microbús)..... 3.90 VECES\nC).-Remolques (tráileres) y autobuses de pasaje................................ 6.50 VECES\nD).-Remolque de tractocamiones de tres o más ejes, con una o más cajas............. 6.50 VECES\nE).-Motocicletas.......................... 1.95 VECES\nF).-Bicicletas............................ 1.30 VECES\nMunicipal, previa comprobación con documentos oficiales de autoridad competente, se exentará del pago de los derechos por arrastre de vehículos.\nCAPÍTULO XVIII\nDERECHOS POR ALMACENAJE DE VEHÍCULOS\nARTÍCULO 41.-Los derechos por almacenaje de vehículos en predios propiedad del Municipio o ajenos causarán una cuota diaria, de acuerdo con la siguiente:\nTARIFA\nUNIDAD DE MEDIDA Y\nACTUALIZACIÓN (UMA) VIGENTE\nI.-Por almacenaje:\nA).-Automóvil, camioneta y pick-up........ 0.98 VECES\nB).-Camiones de pasajeros................. 1.30 VECES\nC).-Camiones de servicio público o particular de carga:\na).-Sin carga.......................... 1.30 VECES\nb).-Con carga.......................... 1.63 VECES\nD).-Auto-tractores o tractocamiones:..... 1.30 VECES\na).-Remolques sin carga................ 0.98 VECES\nb).-Remolques con carga................ 1.30 VECES\nc).-Semiremolque y/o doble remolque\n(tipo dolly).......................... 0.98 VECES\nE).-Motocicletas y bicicletas............. 0.13 VECES\na).-Cuando la motocicleta exceda las setenta y dos horas almacenado en la estación de transferencia, será trasladado a la estación definitiva, en donde se le efectuara cobro adicional por derechos de almacenamiento por día almacenado............................. 0.98 VECES municipal, previa comprobación con documentos oficiales de autoridad competente, se exentará del pago de los derechos por almacenaje de vehículos.\nCAPÍTULO XIX\nDERECHOS POR SERVICIOS DE RECEPCIÓN, TRATAMIENTO Y CONFINAMIENTO\nFINAL DE RESIDUOS SÓLIDOS E INDUSTRIALES\nARTÍCULO 42.-Los derechos por el servicio, recepción, confinamiento, tratamiento y disposición final de residuos sólidos e industriales no peligrosos de particulares, en predios propiedad del municipio o ajenos, causarán una cuota de 1.96 veces la Unidad de Medida y Actualización por tonelada.\nLa tarifa que el Ayuntamiento pagará al concesionario por recepción y confinamiento de residuos sólidos no peligrosos de origen doméstico recolectados por el municipio, será de 1.38 veces la\nUnidad de Medida y Actualización vigente, por tonelada.\nCAPÍTULO XX\nDERECHOS POR EXPEDICIÓN DE CERTIFICADOS, TÍTULOS Y COPIAS DE\nDOCUMENTOS\nARTÍCULO 43.-Los certificados, copias simples, copias certificadas municipales, que no se encuentren previstos en algún otro artículo de la presente ley, se pagarán de acuerdo con el costo que representa prestar el servicio, incluyendo equipos, materiales y costos de personal, conforme a lo siguiente:\nTARIFA\nUNIDAD DE MEDIDA Y\nACTUALIZACIÓN (UMA) VIGENTE\nA).-Hojas tamaño carta\na).-Copia simple en servicio ordinario, entrega en 3 días hábiles............... 0.10 VECES\nb).-Copia simple en servicio urgente, entrega el mismo día solicitándola antes del medio día........................... 0.20 VECES\nc).-Copia certificada en servicio ordinario, entrega en 3 días hábiles primera hoja............................ 2.93 VECES\nd).-Copia certificada en servicio ordinario, entrega en 3 días hábiles hojas subsecuentes............................ 1.46 VECES\ne).-Copia certificada en servicio urgente, entrega el mismo día solicitándola antes del medio día, primera hoja............. 4.23 VECES\nf).-Copia certificada en servicio urgente, entrega el mismo día solicitándola antes del medio día, hojas subsecuentes....... 2.11 VECES\nB).-Hojas tamaño oficio\na).-Copia simple en servicio ordinario, entrega en 3 días hábiles............... 0.11 VECES\nb).-Copia simple en servicio urgente, entrega el mismo día solicitándola antes del medio día........................... 0.22 VECES\nc).-Copia certificada en servicio ordinario, entrega en 3 días hábiles primera hoja............................ 3.25 VECES\nd).-Copia certificada en servicio ordinario, entrega en 3 días hábiles hojas subsecuentes............................ 1.63 VECES\ne).-Copia certificada en servicio urgente, entrega el mismo día solicitándola antes del mediodía, primera hoja.............. 4.88 VECES\nf).-Copia certificada en servicio urgente, entrega el mismo día solicitándola antes del mediodía, hojas subsecuentes........ 2.43 VECES\n1.30 VECES\nC).-Copia certificada del pago de impuesto predial......................................\nD).-Búsqueda de datos para la expedición de copia simple o copia certificada:\na).-Búsqueda de datos inmediata\n(localizados por sistema)............ EXENTO\nb).-Búsqueda de datos inmediata(No localizados por sistema)............. EXENTO\nE).-Registro de Valuador Fiscal Municipal.... 24.38 VECES\nF).-Revalidación anual como Valuador Fiscal\nMunicipal................................. 24.38 VECES\nG).-Certificado o constancia de residencia, así como constancia de domicilio a extranjeros:\na).-Servicio ordinario.................. 1.95 VECES\nb).-Servicio urgente.................... 3.25 VECES\nH).-Atlas municipal de riesgos............... 9.75 VECES\nI).-Certificados que expide la Dirección de\nRecaudación Municipal:\na).-Certificado de libertad de gravámenes fiscales\n1)Servicio ordinario............... 4.88 VECES\n2)Servicio urgente................. 6.50 VECES\nb).-Certificado de no adeudo (comercio establecido)........................ 2.53 VECES\nc).-Certificado de no adeudo en rezagos municipales:\n1)Para personas físicas la primera expedición, pagará por unidad.. 0.00 VECES\n2)Para personas físicas por la reposición de certificado pagará por unidad.................... 1.00 VECES\n3)Para personas físicas con actividad empresarial y personas morales la primera expedición, por una y hasta\n5 unidades, pagará por unidad..\n............................... 1.50 VECES\n4)Para personas físicas con actividad empresarial y personas morales, de\n6 unidades en adelante, pagará por unidad......................... 1.00 VECES\n5)Para personas físicas con actividad empresarial y personas morales por la reposición de certificado pagará por unidad............... 1.00 VECES\nTratándose de dependencias de la\nAdministración Pública Estatal y Municipal\nCentralizada y Descentralizada, estarán exentos de pago de derechos en la expedición del certificado de no adeudo en rezagos municipales, previa solicitud que se realice por escrito a la Tesorería\nMunicipal.\nd).-Certificado de no adeudo en rezagos para póliza de seguro de cobertura extranjera...... 3.00 VECES\nJ).- Expedición de opiniones técnicas en materia de uso de explosivos, a cargo de la\nDirección General de Gobierno.........\n8.13 a 65 VECES\nK).-Certificación de avalúo para efectos fiscales:\na).-Servicio ordinario (siete dias\nb).-Servicio urgente (tres dias habiles)\nL).-La emisión de avalúos por parte de la Comisión Municipal de mismos, de acuerdo con los presupuestos que realicen, los que en todo caso serán proporcionales al costo del servicio.\nM).-Pago de derechos por cualquier solicitud de\nBases de Licitación Pública para la adquisición de bienes y servicios o arrendamientos, a cargo de la Oficialía\nMayor.................................... 23.14 VECES\nN).-Por la recepción y revisión de documentos en el trámite para la ratificación de firma, cada vez........................ 27.00 VECES\nÑ).-Por la ratificación de firma de documento, una vez revisado, cada vez.............. 65.00 VECES con documentación oficial, quedarán exentas de cubrir el monto para el trámite de certificado o constancia de residencia.\nAsimismo, quedarán exentas del cobro, las personas que comprueben con documentación oficial, tener su residencia ubicada al sur de la caseta de cobro de la carretera Federal de cuota TijuanaEnsenada hasta los límites con la ciudad de Playas de Rosarito.\nO).-Por la expedición de la constancia de antecedentes administrativos........ 2.93 VECES\nCAPÍTULO XXI\nOTROS SERVICIOS QUE PRESTA EL AYUNTAMIENTO\nARTÍCULO 44.-Cualquier solicitud de compra, permuta u otro medio de un bien inmueble propiedad del H. Ayuntamiento, deberá estar dicho procedimiento. El cual tendrá un costo de:\nA).-De 1 m2 a 500 m2........................ 32.50 VECES\nB).-De 501 m2 a 1,499 m2.................... 65.00 VECES\nC).-De 1,500 m2 a 2,999 m2.................. 97.50 VECES\nD).-De 3,000 m2 a 4,999 m2.................. 130.00 VECES\nE).-De 5,000 m2 a 9,999 m2.................. 195.00 VECES\nF).-De 10,000 m2 a 19,999 m2................ 260.00 VECES\nG).-De 20,000 m2 a 100,000 m2............... 325.00 VECES\nTÍTULO CUARTO\nINGRESOS POR VENTA DE BIENES, PRESTACIÓN DE SERVICIOS Y OTROS\nINGRESOS\nCAPÍTULO I\nARTÍCULO 45.-Ninguna contribución podrá recaudarse si no está prevista en la presente Ley de Ingresos Municipal.\nARTÍCULO 46.-El pago de los derechos por los servicios que presten las Entidades Paramunicipales y/o Fideicomisos, será pagado por los usuarios, conforme a lo siguiente:\nCAPÍTULO II\nARTÍCULO 47.-Los servicios que presta el Sistema para el Desarrollo\nIntegral de la Familia, se cobrarán conforme a lo siguiente:\nTARIFA\nUNIDAD DE MEDIDA Y\nACTUALIZACIÓN (UMA) VIGENTE\nA).-Credenciales y placas de discapacidad:\na).-Credencial............................. EXENTO\nb).-Segunda reposición de credencial de discapacidad y subsecuentes reposiciones... 2.15 VECES\nc).-Placa Azul para estacionamiento, primera vez........................................ EXENTO\nd).-Placa Azul para estacionamiento temporal, de acuerdo a Certificado Médico (desde 1 mes hasta 1 año).............................. EXENTO\ne).-Reposición placa azul de estacionamiento 2.15 VECES\nf).-Renovación anual placa azul de estacionamiento(Engomado)................. EXENTO\nB).-Servicio de traslado para personas con discapacidad o movilidad reducida.............. EXENTO\nC).-Atención en estancia de día para adultos mayores, se pagará semanalmente:\na).-Estancia adulto mayor.................. 4.01 VECES\nb).-Estancia adulto mayor bajos recursos... 2.01 VECES\nEl costo de los servicios a que se refiere el subinciso b) se determinará por el Departamento de Bienestar Social, mediante un grado de vulnerabilidad.\nD).-Atención a infantes en estancias, desde 3 meses hasta 5 años con 11 meses de edad:\na).-Servicio semanal, estancia 1er hijo.... 2.15 VECES\nb).-Servicio semanal, estancia 2do hijo.... 1.08 VECES\nc).-Servicio semanal, estancia 3er hijo.... 0.68 VECES\nd).-Servicio por hora, hijos de trabajadores en estancia................................ 0.08 VECES\ne).-Servicio semanal, estancia en condición vulnerable................................. BECA\nLa BECA a que se refiere el subinciso e) se determinará por el\nDepartamento de Bienestar Social del DIF, mediante un Estudio\nSocioeconómico, que determina el porcentaje a que es acreedor, desde un 25% (veinticinco por ciento) hasta un 100% (cien por ciento)\nE).-Consultas y terapias psicológicas:\na).-Consulta General o Terapia............. 0.81 VECES\nb).-Consulta o Terapia(caso especial) 0.07 a 0.55 VECES\nEl costo de la consulta o terapia a que se refiere el subinciso\nb) se determina por un estudio socioeconómico que realizará el\nDepartamento de Bienestar Social del DIF, el cual indicará su grado de vulnerabilidad del paciente y la cuota que ha de cubrir, o bien se indicará si se le exenta del pago.\nF).-Impartición de talleres en centros de desarrollo comunitario:\na).-Inscripción a Talleres................. 0.21 VECES\nb).-Taller de Repostería por hora.......... 0.15 VECES\nc).-Taller Deportivo por hora.............. 0.15 VECES\nd).-Taller Artístico por hora.............. 0.15 VECES\ne).-Taller de Manualidades por hora........ 0.15 VECES\nf).-Taller de Belleza por hora............. 0.15 VECES\ng).-Taller Educativo por hora.............. 0.15 VECES\nEl costo a que se refieren los subincisos b), c), d), e) y f), talleres 3 o más veces por semana, teniendo un costo de 0.05 UMA por hora.\nG).-Servicio de atención médica a personas de bajos recursos:\na).-Médico General......................... 0.68 VECES\nb).-Dentista............................... 0.81 VECES\n1.09 a 20.69\nc).-Servicios Dentales Básicos............\nVECES\n1).-Limpieza simple y profilaxis...... 1.35 VECES\n2).-Recementado por pieza............. 1.35 VECES\n3).-Extracciones simples.............. 2.01 VECES\n4).-Recubrimiento por pieza........... 2.68 VECES\n5).-Colocación de resinas............. 4.01 VECES\n6).-Extracciones muela del juicio..... 6.67 VECES\n7).-Sutura y corte de hueso........... 6.67 VECES\n8).-Corona de acero por pieza......... 8.01 VECES\n9).-Pulpotomía por pieza.............. 8.01 VECES\n10).-Colocación de poste por pieza 10.72 VECES\nd).-Servicios Dentales\nEspecializados............... 20.69 a 42.47 VECES\n1) Corona fija por pieza.............. 20.66 VECES\n2) Corona removible por pieza......... 40.02 VECES\ne).-Psicólogo.............................. 0.81 VECES\nH).- Distribución nutricional y alimentaria de despensas, desayunos fríos y calientes:\na).-Despensa Mensual Familia Marginada..... 0.61 VECES\nb).-Despensa Mensual Menor de 1 a 5 años de edad....................................... 0.61 VECES\nc).-Despensa Mensual Lactante.............. 0.61 VECES\nd).-Despensa Mensual Adulto Mayor.......... 0.61 VECES\ne).-Desayuno Diario modalidad frío........ 0.06 VECES\nF).-Desayuno Diario modalidad caliente..... 0.07 VECES\nLa distribución de las despensas y desayunos, se determinará el Departamento de Bienestar Social del DIF, los precios son establecidos de acuerdo al convenio de colaboración con DIF\nEstatal.\nI).-Pláticas prematrimoniales................... 2.72 VECES\nPara los casos de pláticas prematrimoniales se debe considerar lo siguiente: Adultos Mayores y Personas con Discapacidad pagarán el\n50% (cincuenta por ciento), de la tarifa, debiendo comprobar su condición de la siguiente manera:\nAdultos Mayores: Previa presentación de documento oficial con fotografía, expedido por el Instituto Nacional de las Personas\nAdultas Mayores (INAPAM).\nPersonas con discapacidad: Previa presentación de tarjeta vigente de la Familia.\nDentro de la celebración del Programa \"Matrimonios Colectivos\" se exentarán del costo total, las pláticas prematrimoniales a los participantes.\nJ).-Otros ingresos: institución, el ingreso se determinará dependiendo el tipo de evento a realizarse (artísticos, culturales, recreativos, sociales, etc.) los gastos de organización, audiencia y boletaje.\nCAPÍTULO III\nARTÍCULO 48.-Los servicios que presta el Instituto Municipal del\nDeporte de Tijuana, se cobrarán conforme a lo siguiente:\nTARIFA\nUNIDAD DE MEDIDA Y\nACTUALIZACIÓN (UMA) VIGENTE\nA).-Unidad deportiva CREA:\na).-Uso y aprovechamiento de espacios:\n1).-Vendedor ambulante por evento por día 2.15\nVECES\n2).-Vendedor ambulante por mes...... 7.15\nVECES\n3).-Puesto para venta semifijo por evento por\n4.29 día.................................\nVECES\n4).-Puesto para venta semifijo por mes 29.08\nVECES\n5).-Cafetería alberca mensual....... 58.20\nVECES\n6).-Cafetería interna mensual....... 36.00\nVECES\n7).-Uso de salón de usos múltiples por mes 85.87\nVECES\n8).-Uso de salón de usos múltiples por hora 2.15\nVECES\n9).-Evento en Pista de Atletismo a centros educativos.......................... EXENTO\n10).-Evento en Pista de Atletismo por día sin\n11.47 fines de lucro......................\nVECES\n11).-Evento en Pista de Atletismo por día con\n42.93 fines de lucro......................\nVECES\n12).-Renta de gimnasio de pesas por mes 85.87\nVECES\n13).-Campo fútbol soccer por hora diurno\n2.86 empastado..........................\nVECES\n14).-Campo fútbol soccer por hora nocturno\n3.58 empastado...........................\nVECES\n15).-Campo fútbol soccer por evento sin fines\n13.91 de lucro............................\nVECES\n16).-Campo fútbol soccer por evento con fines\n137.52 de lucro............................\nVECES\n17).-Uso de campo para eventos escolares\n6.90 deportivos.........................\nVECES\n18).-Campo béisbol por hora diurno empastado\n2.86\n....................................\nVECES\n19).-Campo béisbol por hora nocturno empastado\n3.58\n....................................\nVECES\n20).-Campo béisbol por evento sin fines de\n6.90 lucro...............................\nVECES\n21).-Campo béisbol por evento con fines de\n36.00 lucro...............................\nVECES\n22).-Campo softbol por hora diurno 2.90\nVECES\n23).-Campo softbol por hora nocturno 3.86\nVECES\n24).-Campo softbol por evento con fines de\n46.80 lucro..............................\nVECES\n25).-Campo softbol por evento sin fines de\n8.97 lucro..............................\nVECES\n26).-Cancha de básquetbol por hora diurna 2.15\nVECES\n27).-Cancha de básquetbol por hora nocturna 2.86\nVECES\n28).-Cancha de básquetbol por evento con fines\n36.00 de lucro............................\nVECES\n29).-Cancha de básquetbol por evento sin fines\n6.90 de lucro............................\nVECES\n30).-Cancha de tenis por hora diurno 0.36\nVECES\n31).-Cancha de tenis por hora nocturno 0.43\nVECES\n32).-Cancha de tenis por hora con fines de\n1.44 lucro..............................\nVECES\n33).-Cancha de tenis por hora sin fines de\n0.69 lucro..............................\nVECES\n34).-Cancha de voleibol por hora.... 0.69\nVECES\n35).-Cancha de voleibol playero por hora 0.69\nVECES\n36).-Alberca nado libre una hora niños 0.21\nVECES\n37).-Alberca nado libre una hora adultos 0.35\nVECES\n38).-Carril de alberca exclusivo sesión por\n5.52 hora entrenamiento.................\nVECES\n39).-Evento competitivo en alberca por sesión\n51.24\n....................................\nVECES\n40).-Explanada sin fines de lucro por evento\n6.90 de 1 a 100 personas.................\nVECES\n41).-Explanada sin fines de lucro por evento\n13.91 de 101 en adelante.................\nVECES\n42).-Explanada con fines de lucro por evento 72.02\nVECES\n1.39\n43).-Uso de salón de aerobics por hora\nVECES\n44).-Renta mensual local tipo 1.... 22.16\nVECES\n45).-Renta mensual local tipo 2..... 36.00\nVECES\n46).-Renta mensual local tipo 3.... 51.24\nVECES\n47).-Uso de salón de ballet por hora. 1.08\nVECES\n48).-Uso mensual de salón tipo \"A\". 14.40\nVECES\n49).-Uso mensual de salón tipo \"B\".. 22.16\nVECES\n50).-Evento competitivo en alberca por\n0.23 participante........................\nVECES\nb).-Clases:\n1).-Uso de espacio competitivo por niño por\n4.14 evento.............................\nVECES\n2).-Yoga por sesión................. 0.35\nVECES\n3).-Zumba por sesión............... 0.14\nVECES\n4).-Box niño por sesión............. 0.21\nVECES\n5).-Box adulto por sesión........... 0.35\nVECES\n6).-Inscripción de clase por alumno 0.69\nVECES\n7).-Artes marciales adulto por sesión 0.35\nVECES\n8).-Artes marciales niño por sesión. 0.27\nVECES\n9).-Esgrima por sesión............. 0.40\nVECES\n10).-Clase de disciplina por sesión 0.28\nVECES\n11).-Natación curso 4 sesiones infantil 1.73\nVECES\n12).-Natación curso 6 sesiones infantil 2.42\nVECES\n13).-Natación curso 8 sesiones infantil 4.14\nVECES\n14).-Natación cursos 12 sesiones infantil. 4.84\nVECES\n15).-Natación curso 4 sesiones adulto 2.07\nVECES\n16).-Natación curso 6 sesiones adulto 2.70\nVECES\n17).-Natación curso 8 sesiones adulto 4.14\nVECES\n18).-Natación curso 12 sesiones adulto 5.46\nVECES\n19).-Natación curso 20 sesiones masters 6.90\nVECES\n20).-Uso de aparatos de gimnasio diario 0.21\nVECES\n21).-Uso de aparatos de gimnasio mensual 2.07\nVECES\nc).-Bienes o servicios:\n1).-Estacionamiento por tres horas.. 0.14\nVECES\n2).-Pase estacionamiento por 30 días usuario\n2.77 frecuente...........................\nVECES\n3).-Espacio publicitario interno por M2\n2.86 mensual.............................\nVECES\n4).-Espacio publicitario externo por M2\n4.29 mensual.............................\nVECES\nB).-Unidad deportiva TIJUANA:\na).-Uso y aprovechamiento de espacios:\n1).-Vendedor ambulante por evento por día 4.29\nVECES\n2).-Vendedor ambulante por mes...... 8.59\nVECES\n3).-Puesto para venta semifijo por evento por\n3.58 día.................................\nVECES\n4).-Puesto para venta semifijo por mes 11.49\nVECES\n5).-Cafetería 1 mensual............. 72.02\nVECES\n6).-Cafetería 2 mensual............ 14.40\nVECES\n7).-Uso de salón de usos múltiples por mes 13.91\nVECES\n8).-Uso de salón de usos múltiples por hora 1.39\nVECES\n9).-Uso de pista de atletismo para evento por\n11.10 día sin fines de lucro..............\nVECES\n10).-Uso de pista de atletismo para evento por\n42.93 día con fines de lucro.............\nVECES\n11).-Renta de gimnasio de pesas por mes 85.87\nVECES\n12).-Campo fútbol soccer por hora diurno\n3.45 empastado..........................\nVECES\n13).-Campo fútbol soccer por hora nocturno\n4.14 empastado..........................\nVECES\n14).-Campo fútbol soccer por evento por día sin\n13.91 fines de lucro.....................\nVECES\n15).-Campo fútbol soccer por evento por día con\n72.02 fines de lucro.....................\nVECES\n16).-Cancha fútbol rápido por hora diurno 2.77\nVECES\n17).-Cancha fútbol rápido por hora nocturno 3.58\nVECES\n18).-Cancha fútbol rápido por evento por día\n13.91 sin fines de lucro.................\nVECES\n19).-Cancha fútbol rápido por evento por día\n41.48 con fines de lucro..................\nVECES\n20).-Campo béisbol por hora diurno empastado.\n2.07\n....................................\nVECES\n21).-Campo béisbol por hora nocturno\n2.77 empastado..........................\nVECES\n22).-Campo béisbol por evento por día con fines\n72.02 de lucro............................\nVECES\n23).-Campo béisbol por evento por día sin fines\n13.91 de lucro............................\nVECES\n24).-Cancha de básquetbol por hora. 2.07\nVECES\n25).-Cancha de básquetbol con duela por hora.\n4.14\n....................................\nVECES\n26).-Cancha de básquetbol por evento con fines\n36.00 de lucro............................\nVECES\n27).-Cancha de básquetbol por evento sin fines\n7.14 de lucro............................\nVECES\n28).-Cancha de tenis por hora diurno 0.35\nVECES\n29).-Cancha de tenis por hora nocturno 0.41\nVECES\n30).-Cancha de frontenis por hora diurno 0.14\nVECES\n31).-Cancha de frontenis por hora nocturno 0.21\nVECES\n32).-Cancha de voleibol por hora... 0.69\nVECES\n33).-Cancha de voleibol con duela por hora 4.14\nVECES\n34).-Cancha de voleibol playero por hora 0.69\nVECES\n35).-Alberca nado libre una hora niños 0.21\nVECES\n36).-Alberca nado libre una hora adultos 0.35\nVECES\n37).-Carril de alberca exclusivo sesión por\n5.52 hora por entrenamiento.............\nVECES\n38).-Evento en cancha, campo o pista para\n13.91 evento por día sin fines de lucro.\nVECES\n39).-Evento en cancha, campo o pista para\n42.93 evento por día con fines de lucro\nVECES\n40).-Evento competitivo en alberca por\n0.21 participante.......................\nVECES\n41).-Explanada por evento por día sin fin de\n13.91 lucro...............................\nVECES\n42).-Explanada por evento por día con fin de\n69.57 lucro..............................\nVECES\n43).-Explanada por hora............ 1.39\nVECES\n44).-Uso por hora de cancha central de gimnasio\n4.84 multifuncional.....................\nVECES\n45).-Uso por hora de salón de gimnasio\n2.07 multifuncional.....................\nVECES\n46).-Renta mensual local tipo 1..... 14.40\nVECES\n47).-Renta mensual local tipo 2.... 29.08\nVECES\n48).-Renta mensual local tipo 3.... 42.93\nVECES\n49).-Renta mensual de cafetería 3.. 114.95\nVECES\n50).-Evento por día sin fines de lucro de\n25.42 gimnasio multifuncional............\nVECES\n51).-Evento por día con fines de lucro de\n114.95 gimnasio multifuncional.............\nVECES\n52).-Renta de pista de atletismo por día 41.48\nVECES\nb).-Clases:\n1).-Uso de espacio competitivo por niño por\n4.14 evento............................\nVECES\n2).-Yoga por sesión................. 0.35\nVECES\n3).-Zumba por sesión.............. 0.14\nVECES\n4).-Inscripción a clases por alumno. 0.69\nVECES\n5).-Clase de disciplina diversa.... 0.28\nVECES\n6).-Natación mensual 4 sesiones infantil 1.73\nVECES\n7).-Natación mensual 6 sesiones infantil 2.42\nVECES\n8).-Natación mensual 8 sesiones infantil 3.45\nVECES\n9).-Natación mensual 12 sesiones infantil 4.84\nVECES\n10).-Natación mensual 4 sesiones adulto 2.07\nVECES\n11).-Natación mensual 6 sesiones adulto 2.70\nVECES\n12).-Natación mensual 8 sesiones adulto 4.14\nVECES\n13).-Natación mensual 12 sesiones adulto 5.46\nVECES\n14).-Natación mensual 20 sesiones masters 6.90\nVECES\nc).-Bienes o servicios:\n1).-Estacionamiento por 3 horas..... 0.14\nVECES\n2).-Pase estacionamiento por 30 días usuario\n2.77 frecuente...........................\nVECES\n3).-Espacio publicitario interno por M2\n2.86 mensual............................\nVECES\n4).-Espacio publicitario externo por M2\n4.29 mensual.............................\nVECES\nC).-Unidad deportiva REFORMA:\na).-Uso y aprovechamiento de espacios:\n1).-Uso de espacio a vendedores ambulantes por\n2.15 evento por día......................\nVECES\n2).-Uso de espacio a vendedores ambulantes por\n7.14 mes.\nVECES\n3).-Uso de espacio de cafetería interna por mes\n29.08\n....................................\nVECES\n4).-Uso de espacio de cafetería externa por mes\n36.00\n....................................\nVECES\n5).-Uso de salón de usos múltiples por hora 2.15\nVECES\n6).-Renta de gimnasio de pesas mensuales 14.40\nVECES\n7).-Uso campo de fútbol soccer por hora turno\n2.86 matutino empastado.................\nVECES\n8).-Uso campo de fútbol soccer por hora turno\n3.45 nocturno empastado..................\nVECES\n9).-Uso cancha de fútbol rápido por hora diurno\n2.07\n....................................\nVECES\n10).-Uso cancha de fútbol rápido por hora\n2.77 nocturno............................\nVECES\n11).-Uso cancha de básquetbol por hora 1.39\nVECES\n12).-Uso de cancha de voleibol por hora 1.39\nVECES\n13).-Uso de la pista de atletismo por evento\n42.93 con fines de lucro.................\nVECES\n14).-Uso de la pista de atletismo por evento\n13.91 sin fines de lucro.................\nVECES\n15).-Uso de cancha, campo o pista para evento\n29.08 con fines de lucro..................\nVECES\n16).-Uso de cancha, campo o pista para evento\n11.10 sin fines de lucro..................\nVECES\n17).-Alberca nado libre niños por hora 0.21\nVECES\n18).-Alberca nado libre adultos por hora 0.35\nVECES\n19).-Uso de un carril exclusivo de alberca por\n5.52 hora...............................\nVECES\n20).-Uso de espacios por evento sin fines de\n11.10 lucro...............................\nVECES\n21).-Uso de espacios para evento con fines de\n42.93 lucro.............................\nVECES\n22).-Uso de espacio competitivo por niño por\n4.14 evento..............................\nVECES\n23).-Evento competitivo por participante 0.21\nVECES\n24).-Puesto para venta semifijo mensual 4.14\nVECES\n25).-Puesto para venta semifijo por evento por\n2.07 día................................\nVECES\n26).-Renta de local por mes......... 13.91\nVECES\n27).-Uso de skatepark en evento por hora 3.45\nVECES\n28).-Uso de gimnasio básquetbol por evento sin\n41.48 fines de lucro......................\nVECES\n29).-Uso de gimnasio básquetbol por evento con\n72.02 fines de lucro......................\nVECES\n30).-Evento competitivo en alberca por sesión\n49.50 por día............................\nVECES\nb).-Clases:\n1).-Zumba por hora................. 0.41\nVECES\n2).-Inscripción a clases por alumno. 0.41\nVECES\n3).-Clase de disciplina diversa por sesión 0.28\nVECES\n4).-Natación mensual 4 sesiones infantil 1.39\nVECES\n5).-Natación mensual 6 sesiones infantil 1.73\nVECES\n6).-Natación mensual 8 sesiones infantil 2.77\nVECES\n7).-Natación mensual 12 sesiones infantil 3.45\nVECES\n8).-Natación mensual 4 sesiones adulto 2.07\nVECES\n9).-Natación mensual 6 sesiones adulto 2.70\nVECES\n10).-Natación mensual 8 sesiones adulto 4.14\nVECES\n11).-Natación mensual 12 sesiones adulto 4.84\nVECES\nc).-Bienes o servicios:\n1).-Espacio publicitario interno por M2\n1.39 mensual.............................\nVECES\n2).-Espacio publicitario externo por M2\n2.07 mensual............................\nVECES\n3).-Estacionamiento por 3 horas..... 0.14\nVECES\nD).-Unidad BENITO JUÁREZ:\na).-Uso y aprovechamiento de espacios:\n1).-Uso espacio cafetería mensual.. 21.41\nVECES\n2).-Uso de gimnasio por evento menores con\n41.48 fines de lucro......................\nVECES\n3).-Uso de gimnasio para evento menores sin\n21.41 fines de lucro......................\nVECES\n4).-Uso de gimnasio por evento mayores con\n69.57 fines de lucro.....................\nVECES\n5).-Uso de gimnasio por evento mayores sin\n21.41 fines de lucro.....................\nVECES\n6).-Uso cancha de fútbol rápido por hora diurno\n1.39\n....................................\nVECES\n7).-Uso cancha de fútbol rápido por hora\n2.07 nocturno............................\nVECES\n8).-Uso campo de béisbol por hora diurno 1.39\nVECES\n9).-Uso campo de béisbol por hora nocturno. 2.07\nVECES\n10).-Uso cancha de básquetbol por hora diurno\n2.07 y nocturno..........................\nVECES\n11).-Uso de cancha campo o pista para evento\n2.86 sin fines de lucro..................\nVECES\n12).-Uso de cancha, campo o pista para evento\n11.10 con fines de lucro..................\nVECES\n13).-Uso de explanada e instalaciones por hora.\n2.07\n....................................\nVECES\n14).-Uso de explanada por evento con fines de\n29.08 lucro..............................\nVECES\n15).-Uso de explanada por evento sin fines de\n6.90 lucro...............................\nVECES\n16).-Puesto de venta semifijo por evento por\n2.15 día.................................\nVECES\n17).-Puesto de venta semifijo por mes 4.29\nVECES\n18).-Vendedor ambulante por evento por día 2.15\nVECES\n19).-Vendedor ambulante por mes.... 2.86\nVECES\nb).-Clases:\n1).-Zumba por sesión................ 0.21\nVECES\n2).-Clase disciplina diversa........ 0.21\nVECES\n3).-Inscripción a clases por persona 0.41\nVECES\nc).-Bienes o servicios:\n1).-Espacio publicitario interno por M²\n1.15 mensual.............................\nVECES\n2).-Espacio publicitario externo por M²\n1.44 mensual.............................\nVECES\nE.-AUDITORIO MUNICIPAL\na).-Uso y aprovechamiento de espacios:\n1).-Vendedor ambulante por evento por día 4.29\nVECES\n2).-Puesto para venta semifijo por evento 7.14\nVECES\n3).-Renta mensual de espacio para venta de\n29.08 bebidas con graduación alcohólica...\nVECES\n4).-Uso de local chico tipo A, mensual 29.08\nVECES\n5).-Uso de local grande tipo B, mensual 72.02\nVECES\n6).-Uso de salón de usos múltiples por evento\n41.48 por día.............................\nVECES\n7).-Uso de salón de usos múltiples por mes 49.5\nVECES\n8).-Uso de salón de usos múltiples por hora.\n2.07\n....................................\nVECES\n9).-Cancha de básquetbol con duela por hora 5.52\nVECES\n10).-Cancha de voleibol techada por hora 2.07\nVECES\nb).-Uso de instalaciones para eventos masivos, espectáculos y otros:\n1).-Evento general por día de lunes a jueves 144.03\nVECES\n2).-Evento general por día de viernes a\n214.66 domingo............................\nVECES\n3).-Lucha libre:\na) Lunes a jueves................. 144.03\nVECES\nb) Viernes a domingo............. 214.66\nVECES\n4).-Evento de box y espectáculo masivo por día\n286.68 de 01 a 2,000 asistentes...........\nVECES\n5).-Evento de box y espectáculo masivo por día\n429.23 de 2,001 a 5,000 asistentes........\nVECES\n6).-Renta de ring para evento por un día 85.87\nVECES\n7).-Uso de cancha para actividades deportivas\n69.57 varias sin fines de lucro durante un día\nVECES\n8).-Uso de cancha para actividades deportivas\n144.59 varias con fines de lucro durante un día\nVECES\nc).-Clases:\n1).-Box niño por sesión............ 0.13\nVECES\n2).-Box adulto por sesión........... 0.18\nVECES\n3).-Lucha libre niño por sesión..... 0.13\nVECES\n4).-Lucha libre adulto por sesión.. 0.18\nVECES\n5).-Gimnasia por sesión............. 0.27\nVECES\n6).-Zumba por sesión................ 0.28\nVECES\n7).-Artes marciales niño por sesión. 0.2\nVECES\n8).-Artes marciales adulto por sesión 0.27\nVECES\n9).-Inscripción a clase por alumno.. 0.69\nVECES\n10).-Clase de disciplina diversa por sesión 0.28\nVECES\nd).-Bienes o servicios:\n1).-Venta de cerveza en eventos públicos 0.43\nVECES\n2).-Venta de bebidas sin alcohol en eventos\n0.22 públicos............................\nVECES\n3).-Espacio publicitario interno por M2. 2.86\nVECES\n4).-Espacio publicitario externo por M2 5.72\nVECES\nF.-Unidad deportiva JORGE FITCH:\na).-Uso y aprovechamiento de espacios:\n1).-Salón de usos múltiples por hora 2.07\nVECES\n2).-Uso de cancha de fútbol rápido por hora\n1.39 diurno............................\nVECES\n3).-Uso de cancha de fútbol rápido por hora\n2.07 nocturno...........................\nVECES\n4).-Uso de campo de béisbol por hora diurno 2.07\nVECES\n5).-Uso de campo de béisbol por hora nocturno\n2.07\n....................................\nVECES\n6).-Uso de cancha de básquetbol por hora diurno\n1.39 y nocturno.........................\nVECES\n7).-Uso de cancha, campo o pista por evento con\n11.49 fines de lucro\nVECES\n8).-Uso de cancha, campo o pista por evento sin\n11.10 fines de lucro.....................\nVECES\nb).-Clases:\n1).-Clases de box niños por sesión.. 0.14\nVECES\n2).-Clases de box adultos por sesión 0.28\nVECES\n3).-Clase de zumba por sesión....... 0.21\nVECES\n4).-Inscripción a clase por alumno.. 0.41\nVECES\n5).-Clase de disciplina diversa por sesión 0.28\nVECES\nc).-Bienes o servicios:\n1).-Estacionamiento por día........ 0.14\nVECES\n2).-Publicidad interior por M2 mensual. 1.15\nVECES\n3).-Publicidad exterior por M2 mensual. 1.39\nVECES\nG).-Unidad deportiva GRAN TENOCHTITLAN:\na).-Uso y aprovechamiento de espacios:\n1).-Uso espacio de cafetería por mes 11.10\nVECES\n2).-Uso de campo de fútbol soccer por hora\n1.04 turno diurno........................\nVECES\n3).-Uso de campo de fútbol soccer por hora\n1.39 turno nocturno.....................\nVECES\n4).-Uso de cancha de fútbol rápido por hora\n1.04 diurno..............................\nVECES\n5).-Uso de cancha de fútbol rápido por hora\n1.39 nocturno...........................\nVECES\n6).-Uso de diferentes instalaciones por hora\n2.07\n....................................\nVECES\n7).-Uso de cancha de básquetbol por hora. 0.69\nVECES\n8).-Uso de salón de usos múltiples por\n0.69 hora.................................\nVECES\n9).-Uso de salón de usos múltiples por evento\n16.06 por día.............................\nVECES\n10).-Uso de gimnasio con Ring por hora 2.07\nVECES\n11).-Uso de gimnasio con Ring por evento por\n22.16 día................................\nVECES\nb).-Bienes o servicios:\n1).-Estacionamiento por 3 horas.... 0.14\nVECES\n2).-Publicidad interior por M2 mensual. 1.11\nVECES\n3).-Publicidad exterior por M2 mensual. 1.39\nVECES\nH).-Unidad deportiva LAS HUERTAS:\na).-Uso y aprovechamiento de espacios:\n1).-Uso de salón de usos múltiples por hora.\n2.77\n....................................\nVECES\n2).-Uso de salón para eventos sin fines de\n28.10 lucro...............................\nVECES\n3).-Uso de salón para eventos sin fines de\n4.14 lucro por hora......................\nVECES\n4).-Uso campo de fútbol soccer por hora\n3.45 nocturno empastado.................\nVECES\n5).-Uso de salón para eventos con fines de\n69.57 lucro...............................\nVECES\n6).-Uso de salón para eventos con fines de\n13.91 lucro por hora......................\nVECES\n7).-Uso de jardín para evento...... 6.90\nVECES\n8).-Uso de jardín para eventos por hora 1.39\nVECES\n9).-Uso cancha de fútbol rápido por hora diurno\n1.39\n....................................\nVECES\n10).-Uso cancha de fútbol rápido por hora\n2.07 nocturno............................\nVECES\n11).-Uso cancha de voleibol por hora 1.39\nVECES\n12).-Uso de cancha de voleibol de playa por\n1.39 hora...............................\nVECES\n13).-Uso de cancha de básquetbol por hora 1.04\nVECES\n14).-Uso de cancha de ráquetbol por hora 0.83\nVECES\n15).-Uso de diferentes instalaciones por hora\n2.07\n....................................\nVECES\n16).-Puesto de venta semifijo por evento por\n2.07 día................................\nVECES\n17).-Puesto de venta semifijo por mes 4.29\nVECES\n18).-Vendedor ambulante por evento por día 1.44\nVECES\n19).-Vendedor ambulante por mes..... 2.86\nVECES\nb).-Clases:\n1).-Yoga por sesión................. 0.35\nVECES\n2).-Zumba por sesión................ 0.28\nVECES\n3).-Artes marciales por sesión...... 0.28\nVECES\n4).-Aerobics por sesión............. 0.28\nVECES\n5).-Inscripción a clases por alumno 0.41\nVECES\n6).-Clase de disciplina diversa por sesión 0.28\nVECES\nc).-Bienes o servicios:\n1).-Publicidad interior por M² mensual. 1.11\nVECES\n2).-Publicidad exterior por M² mensual 1.39\nVECES\n3).-Estacionamiento por 3 horas..... 0.14\nVECES\nI.-Unidad deportiva GIMNASIO INDEPENDENCIA:\na).-Uso y aprovechamiento de espacios:\n1).-Uso espacio cafetería mensual... 22.16\nVECES\n2).-Uso de gimnasio Independencia por evento 21.41\nVECES\n3).-Uso de gimnasio Independencia por evento\n41.48 sin fines de lucro..................\nVECES\n4).-Uso de gimnasio Independencia por evento\n69.57 con fines de lucro.................\nVECES\n5).-Uso de cancha de básquetbol por hora diurno\n2.07 y nocturno.........................\nVECES\n6).-Uso de cancha para básquetbol con duela por\n4.14 hora................................\nVECES\n7).-Uso de cancha de voleibol por hora diurno\n1.39 y nocturno..........................\nVECES\n8).-Uso de cancha de voleibol con duela por\n4.14 hora..............................\nVECES\n9).-Uso de cancha anexa por día.... 4.14\nVECES\n10).-Puesto de venta semifijo por evento por\n2.77 día................................\nVECES\n11).-Puesto de venta semifijo por mes 6.90\nVECES\n12).-Uso de diferentes instalaciones por hora\n2.07\n....................................\nVECES\n13).-Vendedor ambulante por evento por día. 1.44\nVECES\n14).-Vendedor ambulante por mes..... 2.15\nVECES\nb).-Clases:\n1).-Clases de artes marciales por sesión 0.28\nVECES\n2).-Clases de zumba por sesión..... 0.22\nVECES\n3).-Inscripción a clases por alumno. 0.41\nVECES\n4).-Clase de disciplina diversa por sesión 0.28\nVECES\nc).-Bienes o servicios:\n1).-Estacionamiento por 3 horas.... 0.14\nVECES\n2).-Publicidad interior por M2 mensual. 1.11\nVECES\n3).-Publicidad exterior por M2 mensual 1.39\nVECES\nJ.-Unidad deportiva MARIANO MATAMOROS:\na).-Uso y aprovechamiento de espacios:\n1).-Uso espacio cafetería mensual... 8.30\nVECES\n2).-Uso de gimnasio por evento sin fines de\n21.41 lucro...............................\nVECES\n3).-Uso de gimnasio por evento con fines de\n69.57 lucro...............................\nVECES\n4).-Uso de cancha de fútbol soccer por hora\n1.39 diurno.............................\nVECES\n5).-Uso de cancha de fútbol soccer por hora\n2.07 nocturno............................\nVECES\n6).-Uso de cancha básquetbol por hora diurno y\n1.39 nocturno............................\nVECES\n7).-Uso de cancha de voleibol por hora diurno\n1.39 y nocturno..........................\nVECES\n8).-Puesto de venta semifijo por evento por\n2.86 día................................\nVECES\n9).-Puesto de venta semifijo por mes 7.14\nVECES\n10).-Vendedor ambulante por evento.. 1.44\nVECES\n11).-Vendedor ambulante por mes.... 2.15\nVECES\n12).-Uso de cancha de fútbol rápido por hora\n2.07 diurno..............................\nVECES\n13).-Uso de cancha de fútbol rápido por hora\n2.77 nocturno...........................\nVECES\nb).-Clases:\n1).-Zumba por sesión................ 0.21\nVECES\n2).-Inscripción a clase por alumno.. 0.41\nVECES\n3).-Clase de disciplina diversa por sesión 0.28\nVECES\nc).-Bienes o servicios:\n1).-Estacionamiento por 3 horas..... 0.14\nVECES\n2).-Publicidad interior por M2 mensual 1.11\nVECES\n3).-Publicidad exterior por M2 mensual 1.39\nVECES\nK.-Unidad deportiva EL RUBI:\na).-Uso y aprovechamiento de espacios:\n1).-Uso de cafetería mensual....... 13.91\nVECES\n2).-Salón de usos múltiples por hora 1.39\nVECES\n3).-Uso de campo de fútbol soccer por hora\n1.39 turno diurno.......................\nVECES\n4).-Uso de campo de fútbol soccer por hora\n2.07 turno nocturno.....................\nVECES\n5).-Uso cancha de fútbol rápido por hora diurno\n1.39\n....................................\nVECES\n6).-Uso de cancha de fútbol rápido por hora\n2.07 nocturno...........................\nVECES\n7).-Uso campo de béisbol por hora diurno 1.39\nVECES\n8).-Uso de campo de béisbol por hora nocturno\n2.07\n....................................\nVECES\n9).-Cancha de básquetbol diurna.... 1.39\nVECES\n10).-Cancha de básquetbol nocturna. 2.07\nVECES\n11).-Uso de cancha de usos múltiples diurna 1.39\nVECES\n12).-Uso de cancha de usos múltiples nocturna\n2.07\n....................................\nVECES\n13).-Uso de puesto semifijo al mes.. 5.52\nVECES\n14).-Puesto semifijo al mes por evento 2.77\nVECES\n15).-Uso de campo de béisbol por evento con\n69.57 fines de lucro......................\nVECES\n16).-Uso de campo de béisbol por evento sin\n13.91 fines de lucro.....................\nVECES\n17).-Uso de Gimnasio de Box por hora 2.07\nVECES\n18).-Uso de Gimnasio de Box por evento por día\n14.40\n....................................\nVECES\n19).-Puesto de venta semifijo por evento 2.86\nVECES\n20).-Puesto de venta semifijo por mes 7.14\nVECES\n21).-Vendedor ambulante por evento. 1.44\nVECES\n22).-Vendedor ambulante por mes.... 2.15\nVECES\nb).-Clases:\n1).-Zumba por sesión................ 0.21\nVECES\n2).-Inscripción a clase por alumno.. 0.41\nVECES\n3).-Clase de disciplina diversa por sesión. 0.29\nVECES\nc).-Bienes o servicios:\n1).-Estacionamiento por 3 horas..... 0.14\nVECES\n2).-Publicidad interior por M2 mensual 1.15\nVECES\n3).-Publicidad exterior por M2 mensual. 1.44\nVECES\nL.-Unidad deportiva SALVATIERRA:\na).-Uso y aprovechamiento de espacios:\n1).-Cafetería interna en la cancha de fútbol\n13.91 mensual............................\nVECES\n2).-Uso espacio cafetería en la cancha béisbol\n4.14 mensual............................\nVECES\n3).-Uso de Gimnasio Salvatierra por evento sin\n6.90 fines de lucro......................\nVECES\n4).-Uso de Gimnasio Salvatierra por evento con\n69.57 fines de lucro.....................\nVECES\n5).-Uso de campo de fútbol soccer por hora\n2.77 turno diurno........................\nVECES\n6).-Uso de campo de fútbol soccer por hora\n3.45 turno nocturno.....................\nVECES\n7).-Uso cancha de fútbol rápido por hora diurno\n2.07\n....................................\nVECES\n8).-Uso cancha de fútbol rápido por hora\n2.77 nocturno............................\nVECES\n9).-Uso cancha de básquetbol por hora diurno y\n1.39 nocturno...........................\nVECES\n10).-Uso campo de béisbol por hora diurno 1.39\nVECES\n11).-Uso campo de béisbol por hora nocturno 2.07\nVECES\n12).-Uso de cancha de voleibol por hora diurno\n1.39 y nocturno..........................\nVECES\n13).-Puesto de venta semifijo por evento 2.86\nVECES\n14).-Puesto de venta semifijo por mes 7.14\nVECES\n15).-Vendedor ambulante por evento.. 1.44\nVECES\n16).-Vendedor ambulante por mes..... 2.15\nVECES\n17).-Uso de instalación para evento con fines\n72.02 de lucro............................\nVECES\nb).-Clases:\n1).-Inscripción a clase por alumno.. 0.41\nVECES\n2).-Clase de disciplina diversa por sesión. 0.14\nVECES\nc).-Bienes o servicios:\n1).-Estacionamiento por 3 horas.... 0.14\nVECES\n2).-Publicidad interior por M2 mensual. 1.15\nVECES\n3).-Publicidad exterior por M2 mensual. 1.39\nVECES\nM.-Unidad deportiva LAS CALIFORNIAS:\na).-Uso y aprovechamiento de espacios:\n1).-Uso de cancha de básquetbol por hora diurno\n1.39 y nocturno.........................\nVECES\n2).-Publicidad interior por M2 mensual 1.15\nVECES\n3).-Publicidad exterior por M2 mensual. 1.44\nVECES\nN.-Unidad deportiva NUEVA TIJUANA:\na).-Uso y aprovechamiento de espacios:\n1).-Uso de espacio para cafetería... 11.10\nVECES\n2).-Uso de campo de fútbol soccer por hora\n1.04 turno diurno.......................\nVECES\n3).-Uso de campo de fútbol soccer por hora\n1.39 turno nocturno.....................\nVECES\n4).-Uso de cancha de básquetbol por hora diurno\n1.39 y nocturno..........................\nVECES\n5).-Uso de cancha de voleibol por hora diurno\n1.39 y nocturno..........................\nVECES\n6).-Uso de diferentes instalaciones por hora 2.07\nVECES\n7).-Uso de cancha de básquetbol chica. 1.04\nVECES\n8).-Uso de cancha de básquetbol grande 1.39\nVECES\n9).-Puesto de venta semifijo por mes 4.14\nVECES\n10).-Vendedor ambulante por evento.. 1.39\nVECES\n11).-Vendedor ambulante por mes..... 2.07\nVECES\n12).-Uso de instalación para evento con fines\n69.57 de lucro............................\nVECES\nb).-Bienes o servicios:\n1).-Publicidad interior por M2 mensual 1.15\nVECES\n2).-Publicidad exterior por M2 mensual. 1.44\nVECES\n3).-Estacionamiento por 3 horas..... 0.14\nVECES\nc).-Clases:\n1).-Zumba por sesión............... 0.21\nVECES\n2).-Inscripción a clase por alumno. 0.41\nVECES\n3).-Clase de disciplina diversa por sesión. 0.21\nVECES\nÑ.-Unidad deportiva EL MIRADOR:\na).-Uso y aprovechamiento de espacios:\n1).-Uso espacio cafetería mensual 11.10\nVECES\n2).-Uso cancha de fútbol rápido por hora diurno\n1.04\n....................................\nVECES\n3).-Uso cancha de fútbol rápido por juego\n1.39 nocturno...........................\nVECES\n4).-Uso cancha de frontenis por hora por\n0.14 persona diurno......................\nVECES\n5).-Uso cancha de frontenis por hora por\n0.21 persona nocturno...................\nVECES\n6).-Puesto de venta semifijo por evento 1.44\nVECES\n7).-Puesto de venta semifijo por mes 3.58\nVECES\n8).-Vendedor ambulante por evento... 1.44\nVECES\n9).-Vendedor ambulante por mes...... 2.15\nVECES\n10).-Uso de salón de usos múltiples por hora\n0.69\n....................................\nVECES\n11).-Uso de salón de usos múltiples para\n16.06 evento.............................\nVECES\n12).-Uso de skatepark por evento por hora 3.45\nVECES\nb).-Clases:\n1).-Zumba por sesión................ 0.21\nVECES\n2).-Inscripción a clase por alumno. 0.41\nVECES\n3).-Clase de disciplina diversa por sesión 0.21\nVECES\nc).-Bienes o servicios:\n1).-Estacionamiento por 3 horas.... 0.14\nVECES\n2).-Publicidad interior por M2 mensual 1.11\nVECES\n3).-Publicidad exterior por M2 mensual. 1.39\nVECES\nO.-Unidad deportiva EL DORADO:\na).-Uso y aprovechamiento de espacios:\n1).-Uso espacio cafetería mensual... 6.90\nVECES\n2).-Uso de campo de fútbol soccer por hora\n2.77 diurno empastado...................\nVECES\n3).-Uso de campo de fútbol soccer por hora\n3.45 nocturno empastado.................\nVECES\n4).-Uso cancha de fútbol rápido por juego\n2.07 diurno empastado....................\nVECES\n5).-Uso cancha de fútbol rápido por juego\n2.77 nocturno empastado..................\nVECES\n6).-Uso cancha de fútbol infantil por hora\n1.39 diurno..............................\nVECES\n7).-Uso cancha de fútbol infantil por hora\n2.07 nocturno............................\nVECES\n8).-Campo de softbol por juego diurno 1.04\nVECES\n9).-Campo de softbol por juego nocturno 1.39\nVECES\n10).-Uso cancha de básquetbol por juego diurno\n1.39 y nocturno..........................\nVECES\n11).-Uso de cancha de voleibol por juego diurno\n0.69 y nocturno..........................\nVECES\n12).-Puesto de venta semifijo por evento. 2.86\nVECES\n13).-Puesto de venta semifijo por mes 7.14\nVECES\n14).-Vendedor ambulante por evento. 1.44\nVECES\n15).-Vendedor ambulante por mes.... 2.15\nVECES\nb).-Clases:\n1).-Zumba por sesión................ 0.21\nVECES\n2).-Inscripción a clase por alumno.. 0.41\nVECES\n3).-Clase de disciplina diversa por sesión 0.21\nVECES\nc).-Bienes o servicios:\n1).-Estacionamiento por 3 horas..... 0.14\nVECES\n2).-Publicidad interior por M2 mensual 1.15\nVECES\n3).-Publicidad exterior por M2 mensual. 1.44\nVECES\nP.-Gimnasio ERNESTO \"PAJARITO\" RUIZ\na).-Uso y aprovechamiento de espacios:\n1).-Uso de espacio para cafetería mensual 17.39\nVECES\n2).-Puesto semifijo mensual........ 6.90\nVECES\n3).-Uso de cancha de básquetbol por hora diurno\n2.07 y nocturno..........................\nVECES\n4).-Uso de cancha para básquetbol con duela por\n4.14 hora...............................\nVECES\n5).-Uso de diferentes instalaciones por hora 2.07\nVECES\n6).-Puesto de venta semifijo por evento 2.77\nVECES\n7).-Vendedor ambulante por evento... 1.39\nVECES\n8).-Vendedor ambulante por mes...... 2.07\nVECES\n9).-Uso de área exterior por hora.. 1.39\nVECES\nb).-Clases:\n1).-Zumba por sesión................ 0.21\nVECES\n2).-Inscripción a clases por alumno. 0.41\nVECES\n3).-Clase de disciplina diversa por sesión 0.21\nVECES\nc).-Bienes o servicios:\n1).-Estacionamiento por 3 horas..... 0.14\nVECES\n2).-Publicidad interior por M2 mensual 1.15\nVECES\n3).-Publicidad exterior por M2 mensual. 1.44\nVECES\nQ.-Unidad deportiva PARQUE AZTECA:\na).-Uso y aprovechamiento de espacios:\n1).-Uso de espacio a vendedores ambulantes por\n1.44 día................................\nVECES\n2).-Uso de espacio para venta mensual\n7.14 vendedores semifijo................\nVECES\n3).-Salón de usos múltiples por hora 2.07\nVECES\n4).-Uso de campo de fútbol soccer por juego\n2.77 diurno empastado...................\nVECES\n5).-Uso de campo de fútbol soccer por juego\n3.45 nocturno empastado.................\nVECES\n6).-Uso de campo de béisbol por juego diurno 2.77\nVECES\n7).-Uso de campo de béisbol por juego nocturno\n3.45\n....................................\nVECES\n8).-Uso de diferentes instalaciones por hora.\n2.07\n....................................\nVECES\n9).-Uso de cancha de usos múltiples diurno por\n1.39 hora................................\nVECES\n10).-Uso de cancha de usos múltiples nocturno\n2.07 por hora............................\nVECES\nb).-Clases:\n1).-Zumba por sesión................ 0.21\nVECES\n2).-Inscripción a clase por alumno.. 0.41\nVECES\n3).-Clase de disciplina diversa por sesión 0.21\nVECES\nc).-Bienes o servicios:\n1).-Estacionamiento por 3 horas..... 0.14\nVECES\n2).-Publicidad interior por M2 mensual 1.15\nVECES\n3).-Publicidad exterior por M2 mensual 1.44\nVECES\nR.-Unidad deportiva LAS CASCADAS:\na).-Uso y aprovechamiento de espacios:\n1).-Uso espacio cafetería........... 5.72\nVECES\n2).-Uso cancha de fútbol rápido por hora diurno\n1.39\n....................................\nVECES\n3).-Uso cancha de fútbol rápido por hora\n2.07 nocturno...........................\nVECES\n4).-Uso campo de béisbol por hora diurno. 2.77\nVECES\n5).-Uso campo de béisbol por hora nocturno 3.45\nVECES\n6).-Puesto de venta semifijo por evento. 2.86\nVECES\n7).-Vendedor ambulante por evento... 1.44\nVECES\n8).-Vendedor ambulante por mes...... 2.15\nVECES\n9).-Puesto de venta semifijo por mes 4.29\nVECES\n10).-Uso de cancha de fútbol siete por hora\n2.07 diurno..............................\nVECES\n11).-Uso de cancha de fútbol siete por hora\n2.77 nocturno............................\nVECES\n12).-Uso de evento en skatepark por hora. 3.45\nVECES\nb).-Clases:\n1).-Zumba por sesión................ 0.21\nVECES\n2).-Inscripción a clase por alumno.. 0.41\nVECES\n3).-Clase de disciplina diversa por sesión 0.21\nVECES\nc).-Bienes o servicios:\n1).-Estacionamiento por 3 horas..... 0.15\nVECES\n2).-Publicidad interior por M2 mensual 1.15\nVECES\n3).-Publicidad exterior por M2 mensual 1.44\nVECES\nS).-Unidad deportiva SÁNCHEZ TABOADA:\na).-Uso y aprovechamiento de espacios:\n1).-Uso de campo de fútbol soccer empastado por\n2.07 juego turno diurno..................\nVECES\n2).-Uso de campo de fútbol soccer empastado por\n2.77 juego turno nocturno................\nVECES\n3).-Uso cancha de fútbol rápido por juego\n0.69 diurno..............................\nVECES\n4).-Uso cancha de fútbol rápido por juego\n1.04 nocturno............................\nVECES\n5).-Uso cancha de básquetbol por juego diurno\n0.69 y nocturno..........................\nVECES\n6).-Puesto de venta semifijo por evento 2.77\nVECES\n7).-Vendedor ambulante por evento... 1.39\nVECES\n8).-Vendedor ambulante por mes...... 2.07\nVECES\n9).-Puesto de venta semifijo por mes. 4.14\nVECES\nb).-Clases:\n1).-Zumba por sesión................ 0.21\nVECES\n2).-Inscripción a clases por alumno. 0.41\nVECES\n3).-Clase de disciplina diversa por sesión 0.21\nVECES\nc).-Bienes o servicios:\n1).-Estacionamiento por 3 horas..... 0.14\nVECES\n2).-Publicidad interior por M2 mensual 1.15\nVECES\n3).-Publicidad exterior por M2 mensual 1.44\nVECES\nT.-Unidad deportiva PLANETARIO:\na).-Uso y aprovechamiento de espacios:\n1).-Uso cancha de fútbol rápido por hora diurno\n2.07\n....................................\nVECES\n2).-Uso cancha de fútbol rápido por hora\n2.77 nocturno............................\nVECES\n3).-Uso cancha de básquetbol por hora diurno y\n0.69 nocturno............................\nVECES\n4).-Puesto de venta semifijo por evento 2.86\nVECES\n5).-Vendedor ambulante por evento... 1.44\nVECES\n6).-Vendedor ambulante por mes...... 2.15\nVECES\n7).-Puesto de venta semifijo por mes 4.29\nVECES\n8).-Uso de evento en skatepark por evento por\n13.91 día.................................\nVECES\n9).-Uso de evento en skatepark por evento por\n3.45 hora................................\nVECES\nb).-Clases:\n1).-Zumba por sesión................ 0.21\nVECES\n2).-Inscripción a clase por alumno.. 0.41\nVECES\n3).-Clase de disciplina diversa por sesión 0.21\nVECES\nc).-Bienes o servicios:\n1).-Estacionamiento por 3 horas..... 0.14\nVECES\n2).-Publicidad interior por M2 mensual 1.15\nVECES\n3).-Publicidad exterior por M2 mensual. 1.44\nVECES\nU.-Unidad deportiva TORRES DEL MARIANO:\na).-Uso y aprovechamiento de espacios:\n1).-Uso espacio cafetería........... 4.14\nVECES\n2).-Uso de campo de fútbol soccer por hora\n1.04 turno diurno........................\nVECES\n3).-Uso de campo de fútbol soccer por hora\n1.39 turno nocturno.....................\nVECES\n4).-Uso cancha de fútbol rápido por hora\n1.04 diurno.............................\nVECES\n5).-Uso cancha de fútbol rápido por hora\n1.39 nocturno............................\nVECES\n6).-Uso cancha de básquetbol por hora diurno y\n1.39 nocturno............................\nVECES\n7).-Uso de diferentes instalaciones por hora 2.07\nVECES\n8).-Puesto de venta semifijo por evento 2.77\nVECES\n9).-Vendedor ambulante por evento... 1.39\nVECES\n10).-Vendedor ambulante por mes..... 2.07\nVECES\n11).-Puesto de venta semifijo por mes 4.14\nVECES\n12).-Uso de evento en skatepark por evento por\n3.45 hora................................\nVECES\nb).-Clases:\n1).-Zumba por sesión................ 0.21\nVECES\n2).-Inscripción a clase por alumno.. 0.41\nVECES\n3).-Clase de disciplina diversa por sesión 0.21\nVECES\nc).-Bienes o servicios:\n1).-Estacionamiento por 3 horas..... 0.14\nVECES\n2).-Publicidad interior por M2 mensual 1.15\nVECES\n3).-Publicidad exterior por M2 mensual. 1.44\nVECES\nV.-Unidad deportiva DEL BOSQUE:\na).-Uso y aprovechamiento de espacios:\n1).-Salón de usos múltiples sin fines de lucro\n1.39 por hora............................\nVECES\n2).-Salón para eventos con fines de lucro por\n2.15 hora................................\nVECES\n3).-Campo de fútbol siete por hora turno\n2.77 matutino empastado..................\nVECES\n4).-Campo de fútbol siete por hora turno\n3.45 nocturno empastado..................\nVECES\n5).-Campo de fútbol siete por evento con fines\n72.02 de lucro............................\nVECES\n6).-Cancha de fútbol rápido por hora diurno 2.07\nVECES\n7).-Cancha de fútbol rápido por hora nocturno\n2.77\n....................................\nVECES\n8).-Cancha de básquetbol por hora.. 2.07\nVECES\n9).-Cancha de voleibol por hora..... 1.39\nVECES\n10).-Alberca nado libre niños por hora 0.21\nVECES\n11).-Alberca nado libre adultos por hora 0.35\nVECES\n12).-Carril exclusivo alberca por hora sesión\n5.52 por entrenamiento..................\nVECES\n13).-Uso Explanadas por evento sin fines de\n13.91 lucro...............................\nVECES\n14).-Uso Explanadas por evento con fines de\n28.10 lucro...............................\nVECES\n15).-Uso de espacio competitivo por niño por\n4.14 evento.............................\nVECES\n16).-Puesto de venta semifijo por evento 2.86\nVECES\n17).-Vendedor ambulante por evento.. 1.44\nVECES\n18).-Vendedor ambulante por mes.... 2.15\nVECES\n19).-Puesto de venta semifijo por mes 7.14\nVECES\n20).-Evento competitivo en alberca por sesión\n49.5 por día.............................\nVECES\n21).-Evento competitivo en alberca por\n0.23 participante........................\nVECES\nb).-Clases:\n1).-Ballet por sesión............... 0.28\nVECES\n2).-Esgrima por sesión.............. 0.41\nVECES\n3).-Yoga niños sesión............... 0.21\nVECES\n4).-Yoga adultos sesión............. 0.28\nVECES\n5).-Pilates sesión................. 0.28\nVECES\n6).-Zumba sesión.................... 0.13\nVECES\n7).-Clase de disciplina diversa por sesión 0.21\nVECES\n8).-Inscripción por persona......... 0.28\nVECES\n9).-Natación mensual 4 sesiones infantil 1.73\nVECES\n10).-Natación mensual 6 sesiones infantil 2.07\nVECES\n11).-Natación mensual 8 sesiones infantil 3.45\nVECES\n12).-Natación mensual 12 sesiones infantil 4.29\nVECES\n13).-Natación mensual 4 sesiones\n2.07 adulto...............................\nVECES\n14).-Natación mensual 6 sesiones adulto 2.42\nVECES\n15).-Natación mensual 8 sesiones adulto 4.14\nVECES\n16).-Natación mensual 12 sesiones adulto 4.84\nVECES\n17).-Natación master 20 sesiones mes 6.9\nVECES\nc).-Bienes o servicios:\n1).-Estacionamiento por 3 horas..... 0.14\nVECES\n2).-Publicidad interior por M2 mensual 1.15\nVECES\n3).-Publicidad exterior por M2 mensual 1.44\nVECES\nW.-Unidad deportiva LA MORITA:\na).-Uso y aprovechamiento de espacios:\n1).-Uso espacio de cafetería por mes. 11.10\nVECES\n2).-Uso de campo de fútbol siete por hora\n1.04 diurno..............................\nVECES\n3).-Uso de campo de fútbol siete por hora\n1.73 nocturno............................\nVECES\n4).-Uso de cancha de fútbol rápido hora diurno\n1.04\n....................................\nVECES\n5).-Uso de cancha de fútbol rápido hora\n1.39 nocturno............................\nVECES\n6).-Uso de diferentes instalaciones por hora 1.39\nVECES\n7).-Puesto de venta semifijo por evento 2.77\nVECES\n8).-Vendedor ambulante por evento... 1.39\nVECES\n9).-Vendedor ambulante por mes..... 2.07\nVECES\n10).-Puesto de venta semifijo por mes 4.14\nVECES\n11).-Uso de cancha de básquetbol por hora 0.69\nVECES\nb).-Clases:\n1).-Zumba por sesión................ 0.21\nVECES\n2).-Inscripción a clase por alumno.. 0.41\nVECES\n3).-Clase de disciplina diversa por sesión 0.21\nVECES\nc).-Bienes o servicios:\n1).-Estacionamiento por 3 horas..... 0.14\nVECES\n2).-Publicidad interior por M2 mensual 1.15\nVECES\n3).-Publicidad exterior por M2 mensual. 1.44\nVECES\nX.-Unidad deportiva y centro recreativo CERRO DE LAS ABEJAS\n(Norma Enriqueta Basilio Sotelo \"Queta Basilio\")\na).-Uso y aprovechamiento de espacios:\n1).-Vendedor ambulante por evento por día...\nVECES\n2).-Vendedor ambulante por mes.... 8.59\nVECES\n3).-Puesto para venta semifijo por evento por\nVECES\n4).-Puesto para venta semifijo por mes....\n11.49\nVECES\n5).-Cafetería 1 mensual..... 72.01\nVECES\n6).-Cafetería 2 mensual....... 14.40\nVECES\n7).-Campo fútbol soccer por hora diurno 3.45 empastado. VECES\n8).-Campo fútbol soccer por hora nocturno\n4.15 empastado......................\nVECES\n9).-Campo fútbol soccer por evento por día sin fines de lucro..... 13.91\nVECES\n10).-Campo fútbol soccer por evento por día con\n72.01 fines de lucro................\nVECES\n11).-Cancha fútbol rápido por hora diurno..\n2.77\nVECES\n12).-Cancha fútbol rápido por hora nocturno 3.57\nVECES\n13).-Cancha fútbol rápido por evento por día sin fines de lucro 13.91\nVECES\n14).-Cancha fútbol rápido por evento por día con fines de lucro 41.48\nVECES\n15).-Campo béisbol por hora diurno empastado.\n2.07\nVECES\n16).-Campo béisbol por hora nocturno empastado... 2.77\nVECES\n17).-Campo béisbol por evento por día con fines\nVECES\n18).-Campo béisbol por evento por día sin fines\nVECES\n19).-Explanada sin fines de lucro por evento 6.90\n20).-Explanada sin fines de lucro por evento 13.91 de 101 personas en adelante...... VECES\n21).-Explanada con fines de lucro por evento. 72.01\n22).-Explanada por hora........... 1.39\nVECES\nb).-Bienes o servicios::\n1).-Estacionamiento por cada 3 horas..\n0.15\nVECES\n2).-Pase estacionamiento por 30 días usuario\n5.00 frecuente....\nVECES\nY.-Programa plan vacacional por niño de 4 a 13 años de edad:\na).-Unidad Deportiva CREA................ 13.91\nVECES\nb).-Unidad Deportiva Tijuana............. 13.91\nVECES\nc).-Unidad Deportiva Reforma............. 9.76\nVECES\nd).-Unidad Deportiva Benito Juárez....... 6.22\nVECES\ne).-Unidad Deportiva Parque Azteca....... 4.84\nVECES\nf).-Unidad Deportiva Rubí................ 5.52\nVECES\ng).-Unidad Deportiva Mariano Matamoros.. 5.52\nVECES\nh).-Unidad Deportiva Las Huertas......... 7.60\nVECES\ni).-Unidad Deportiva Salvatierra......... 5.52\nVECES\nj).-Unidad Deportiva Del Bosque......... 9.10\nVECES\nk).-Unidad Deportiva El Dorado........... 5.52\nVECES\nl).-Unidad Deportiva Las Cascadas........ 5.18\nVECES\nm).-Unidad deportiva y centro recreativo CERRO DE\nLAS ABEJAS (Norma Enriqueta Basilio Sotelo \"Queta 9.10\nBasilio\")................................ VECES\nZ.-Inscripción de carreras:\n1).-Inscripción a seriales delegacionales. 2.30\nVECES\n2).-Inscripción a medio maratón...... 2.30\nVECES\nNotas:\nPara los efectos de la aplicación de las tarifas diurna y nocturna, se establecen dos horarios de acuerdo con la temporada de verano e invierno, que regirán conforme al Decreto de Horario\nEstacionario, que para tal efecto emita el Honorable Congreso de la Unión. Por temporada de verano, el horario diurno se entenderá de 6:00 a.m. a 7:00 p.m. y el horario nocturno de 7:01 a 10:00 p.m. por temporada de invierno, el horario diurno se entenderá de\n6:00 a.m. a 5:00 p.m. y nocturno de 5:01 p.m. a 10:00 p.m.\nEl cobro adicional por fracciones de tiempo excedente, se fijará de forma proporcional a la tarifa establecida.\nTodos los conceptos de pago contemplados en el artículo 48, sus incisos y subincisos de la presente Ley, solicitados por: personas mayores de 60 años, que exhiban su credencial del Instituto\nNacional de las Personas Adultas Mayores (INAPAM), Personas con\nDiscapacidad (Previa presentación de tarjeta vigente de de la Familia), personas físicas o morales sin fines de lucro que armonicen con el objeto de la presente Entidad, ciudadanos con ingresos diarios inferiores a tres salarios mínimos, las personas físicas o morales, centros educativos, instituciones gubernamentales que requieran realizar eventos sin fines de lucro, siempre y cuando el servicio sea exclusivamente para ellos, previa solicitud y estudio socioeconómico a quien aplique, obtendrán un beneficio de hasta el 70% (setenta por ciento) de descuento del costo total, o en su caso se exentará de pago a quienes cumplan con la Normatividad que rige a las Entidades Paramunicipales de\nTijuana.\nEn el plan vacacional, aplica descuento de hasta el 25%\n(veinticinco por ciento), por concepto de pronto pago al realizarse antes de la fecha del 30 de junio del año en curso, Asimismo, aplicará beca de hasta el 100% (cien por ciento) a quienes reúnan los requisitos aplicables a la normatividad que rige a las\nEntidades Paramunicipales del Ayuntamiento de Tijuana, Baja\nCalifornia (Norma Técnica Número 15 fondo Único de Becas de las\nEntidades Paramunicipales).\nCAPÍTULO IV\nARTÍCULO 49.-Los servicios que presta el Instituto Metropolitano de Planeación, se cobrarán conforme a lo siguiente:\nTARIFA\nUNIDAD DE MEDIDA Y\nACTUALIZACIÓN (UMA) VIGENTE\nA).-Por evaluación de estudios de impacto urbano y emisión de dictamen para la implementación; se pagará previo al inicio de los trámites, de acuerdo a la siguiente tabla, con validez hasta 2 revisiones previo a la emisión del dictamen:\na).-Industrial.............................. 185.90 VECES\nb).-Habitacional económico (socialpopular)con superficie de hasta 10 Has 170.50 VECES\nc).-Habitacional unifamiliar y multifamiliar con superficie de hasta 10 Has......... 187.18 VECES\nd).-Habitacional turístico.................. 185.90 VECES\ne).-Mixto................................... 233.70 VECES\nf).-Comercio, servicios y equipamiento..... 185.90 VECES\ng).-Especial con superficie de hasta 10 Has.\n226.00 VECES\nh).-Por cada Ha. Adicional correspondiente a los subincisos b), c) y g)............. 3.10 VECES\nB).-Por evaluación de estudios de impacto urbano y emisión de dictamen para el cambio de uso o reasignación de uso de suelo al asignado en los Planes y Programas de Desarrollo Urbano del Municipio de Tijuana; se pagará previo al inicio de los trámites, de acuerdo a la siguiente tabla, con validez hasta\n2 revisiones previo a la emisión del dictamen:\na).-Industrial.............................. 806.90 VECES\nb).-Habitacional económico (social-popular) con superficie de hasta 10 Has......... 451.90 VECES\nc).-Habitacional unifamiliar y multifamiliar con superficie de hasta 10 Has..........\n484.10 VECES\nd).-Habitacional turístico................. 694.60 VECES\ne).-Mixto................................... 694.60 VECES\nf).-Comercio, servicios y equipamiento......\n557.68 VECES\ng).-Especial con superficie de hasta 10 Has. 806.90 VECES\nh).-Minería con superficie de hasta 10 has.. 806.90 VECES\ni).-Por cada Ha adicional correspondiente a los subincisos b), c), g) y h).......... 3.10 VECES\nEn los casos de mezcla de usos, tales como industria con otro uso de suelo, o de especial con otro uso de suelo, se cobrarán de conformidad con los subincisos a) y g) respectivamente.\nC).-Por evaluación de estudios de impacto urbano y emisión de dictamen para la densificación; se pagará previo al inicio de los trámites, de acuerdo a la siguiente tabla, con validez hasta 2 revisiones previo a la emisión del dictamen:\na).-Habitacional económico (socialpopular)con superficie de hasta 10 Has 404.10 VECES\nb).-Habitacional unifamiliar y multifamiliar, con superficie de hasta 10 Has 466.10 VECES\nc).-Habitacional turístico.................. 557.70 VECES\nd).-Mixto................................... 498.30 VECES\ne).-Por cada Ha adicional correspondiente a los subincisos a)y b)................. 3.10 VECES\nD).-Por evaluación de estudios de impacto urbano y emisión de dictamen para la intensificación; se pagará previo al inicio de los trámites, de acuerdo a la siguiente tabla, con validez hasta 2 revisiones previo a la emisión del dictamen:\na).-Industrial.............................. 694.60 VECES\nb).-Mixto................................... 498.30 VECES\nc).-Comercio, servicios y equipamiento...... 498.30 VECES\nE).-Por evaluación de estudios de impacto urbano para gasoductos, oleoductos, poliductos o similares, emisión de dictamen que aplique; se pagará previo al inicio de los trámites, con validez de hasta 2 revisiones previo a la emisión del dictamen:...................... 806.90 VECES\nF).-A partir de la segunda revisión de memoria descriptiva del proyecto a desarrollar; con validez de hasta una revisión, cada uno se pagará previo al inicio del trámite......\n29.00 VECES\nG).-Por elaboración y emisión de opinión técnica de factibilidad de desarrollo para implementación; se pagará previo al inicio de los trámites, de acuerdo a la siguiente tabla:\na).-Comercial, Mixto, Industria, Especial... 47.80 VECES\nb).-Habitacional con superficie hasta 10 Has 117.50 VECES\nc).-Fraccionamiento-conjunto comercial industrial............................ 117.50 VECES\nd).-Por cada Ha Adicional correspondiente al subinciso b)........................... 3.10 VECES\nH).-Por elaboración y emisión de opinión técnica de factibilidad de desarrollo para cambio de uso o reasignación de uso de suelo al asignado en los Planes y Programas de Desarrollo\nUrbano del Municipio de Tijuana, se pagará previo al inicio de los trámites, de acuerdo a la siguiente tabla:\na).-Comercial, mixto, industria, especial... 117.50 VECES\nb).-Habitacional con superficie hasta 10 Has\n175.60 VECES\nc).-Fraccionamiento-conjunto comercial, industrial............................. 175.60 VECES\nd).-Por cada Ha adicional correspondiente al inciso b)............................. 3.10 VECES\nI).-Por elaboración y emisión de opinión técnica de factibilidad de desarrollo para densificación; se pagará previo al inicio del trámite:\na).-Habitacional con superficie hasta\n10 Has)................................. 233.70 VECES\nb).-Por cada Ha adicional correspondiente al subinciso a)............................ 3.10 VECES\nJ).-Por elaboración y emisión de opinión técnica de factibilidad de desarrollo para intensificar, se pagará previo al inicio de los trámites, de acuerdo a la siguiente tabla:\na).-Comercial, mixto, industria, especial... 84.00 VECES\nb).-Fraccionamiento-conjunto comercial, industrial.............................. 117.50 VECES\nK).-Por evaluación de estudio de impacto vial (de movilidad)y emisión de dictamen, con validez hasta 2 revisiones previo a la emisión del dictamen: se pagará previo al inicio del trámite.................................... 200.60 VECES\nL).-Por emisión de opinión técnica de no ser zona de medio o alto riesgo, de conformidad al atlas de riesgo y/o a los Planes y Programas de Desarrollo Urbano del Municipio de Tijuana y la normatividad aplicable, con validez de hasta 2 revisiones previo a la emisión del dictamen, se pagará previo al inicio del trámite....................................\n117.50 VECES\na)Los predios que se ubiquen dentro de asentamientos irregulares, que se encuentren en proceso de regularización de su tenencia de la tierra, previa constancia emitida por la autoridad de regularización competente, pagarán previo inicio del trámite............. 29.00 VECES\nM).-Por emisión de opinión técnica de vialidad, se pagará previo al inicio de los trámites 51.60 VECES\nN).-Por elaboración de carta de no afectación, por declaratorias de riesgo, de conservación, de usos distintos y/o moratorias, se pagará previo al inicio de los trámites........... 45.40 VECES\nÑ).-Inscripción al registro de peritos urbanos en desarrollo urbano, peritos en movilidad y/o peritos en prevención de riesgos........... 50.20 VECES\nO).-Revalidación anual al registro de peritos en desarrollo urbano, peritos en movilidad y/o peritos en prevención de riesgos, dentro del primer mes del año......................... 39.60 VECES\nA partir del segundo mes del año, el pago será extemporáneo, pagando.................... 48.20 VECES\nLos peritos que no revaliden su registro durante dos años consecutivos, se les dará de baja el registro y deberán de iniciar de nueva cuenta su registro como peritos asignándoles nuevo número de registro.\nP).-Por impresión y/o elaboración de plano individual de temas específicos, se pagará previo al inicio del trámite, de acuerdo a la siguiente tabla:\na).-Tamaño carta............................ 2.50 VECES\nb).-Tamaño doble carta...................... 5.90 VECES\nc).-Tamaño 60x90............................ 10.10 VECES\nd).-Tamaño 1.50x0.90....................... 16.80 VECES\nQ).-Por impresión y/o elaboración de plano con topografía, se pagará previo al inicio del trámite, de acuerdo a la siguiente tabla:\na).-Tamaño carta............................\n2.50 VECES\nb).-Tamaño 60x90............................\n11.70 VECES\nc).-Tamaño 1.50x0.90.......................\n10.10 VECES\nR).-Por impresión y/o elaboración de plano de zonas con potencial de riesgo por factor físico, se pagará previo al inicio del trámite, de acuerdo a la siguiente tabla:\na).-Tamaño carta............................ 2.50 VECES\nb).-Tamaño doble carta..................... 3.40 VECES\nc).-Tamaño 60x90........................... 16.80 VECES\nd).-Tamaño 1.50x0.90........................ 20.70 VECES\nS).-Por impresión y/o elaboración de plano con modelo de aptitud para el desarrollo urbano, se pagará previo al inicio del trámite, de acuerdo a la siguiente tabla:\na).-Tamaño carta............................ 2.50 VECES\nb).-Tamaño doble carta..................... 3.40 VECES\nc).-Tamaño 60x90............................ 16.80 VECES\nd).-Tamaño 1.50x0.90....................... 20.70 VECES\nT).-Por impresión y/o elaboración de plano con distribución de la población por agebs, se pagará previo al inicio del trámite, de acuerdo a la siguiente tabla:\na).-Tamaño carta........................... 2.50 VECES\nb).-Tamaño doble carta..................... 3.40 VECES\nc).-Tamaño 60x90........................... 16.80 VECES\nd).-Tamaño 1.50x0.90........................ 20.70 VECES\nU).-Por impresión de mapa temático del censo por subsector, se pagará previo al inicio del trámite, de acuerdo a la siguiente tabla:\na).-Tamaño carta............................ 2.50 VECES\nb).-Tamaño doble carta...................... 3.40 VECES\nc).-Tamaño 60x90............................ 10.10 VECES\nd).-Tamaño 1.50x0.90........................ 13.30 VECES\nV).-Por impresión de plano con distribución de la vivienda por sector, se pagará previo al inicio del trámite, de acuerdo a la siguiente tabla:\na).-Tamaño carta............................ 2.50 VECES\nb).-Tamaño doble carta..................... 3.40 VECES\nc).-Tamaño 60x90........................... 5.99 VECES\nd).-Tamaño 1.50x0.90....................... 9.70 VECES\nW).-Por impresión de plano con esquema vial propuesto, se pagará previo al inicio del trámite, de acuerdo a la siguiente tabla:\na).-Tamaño carta........................... 2.50 VECES\nb).-Tamaño doble carta...................... 3.40 VECES\nc).-Tamaño 60x90........................... 10.10 VECES\nd).-Tamaño 1.50x0.90........................ 13.30 VECES\nX).-Por impresión de plano con carta urbana, se pagará previo al inicio del trámite, de acuerdo a la siguiente tabla:\na).-Tamaño doble carta..................... 3.40 VECES\nb).-Tamaño 60x90............................ 16.80 VECES\nc).-Tamaño 36x59........................... 20.70 VECES\nd).-Tamaño 36x59 (glossy)................... 27.20 VECES\ne).-Formato digital JPG.................... 19.40 VECES\nY).-Por impresión de plano con carta urbana por delegaciones, se pagará previo al inicio del trámite, de acuerdo a la siguiente tabla:\na).-Tamaño carta............................ 2.50 VECES\nb).-Tamaño doble carta..................... 3.40 VECES\nc).-Tamaño 60x90........................... 10.10 VECES\nZ).-Por impresión de plano con traza urbana de la ciudad de Tijuana, se pagará previo al inicio del trámite, de acuerdo a la siguiente tabla:\na).-Tamaño 36x92 (glossy)................... 40.10 VECES\nb).-Tamaño 36x92........................... 22.00 VECES\nc).-Formato digital DWG.................... 220.80 VECES\nd).-Formato digital PDF.................... 84.00 VECES\nAA).-Por impresión de plano con traza urbana de la ciudad de\nTijuana por zonas o sector, se pagará previo al inicio del trámite, de acuerdo a la siguiente tabla:\na).-Tamaño 60x90............................\n10.10 VECES\nAB).-Por impresión de plano con traza urbana de la ciudad de\nTijuana por delegaciones y/o transectos, se pagarán previo al inicio de trámite, de acuerdo a la siguiente tabla:\na).-Tamaño carta............................ 3.40 VECES\nb).-Tamaño doble carta...................... 6.70 VECES\nc).-Tamaño 60x90............................ 11.70 VECES\nd).-Formato digital DWG..................... 37.50 VECES\ne).-Formato digital PDF..................... 14.30 VECES\nAC).-Por impresión de plano con traza urbana con zoom específico, se pagará previo al inicio del trámite, de acuerdo a la siguiente tabla:\na).-Tamaño carta............................ 3.40 VECES\nb).-Tamaño doble carta...................... 5.00 VECES\nc).-Tamaño 60x90........................... 10.10 VECES\nAD).-Por adición de tema al plano, se pagará previo al inicio del trámite, de acuerdo a la siguiente tabla:\na).-Tamaño carta.................. 1.70 VECES x cada tema adicional\nb).-Tamaño doble carta............. 2.00 VECES x cada tema adicional\nc).-Tamaño 60x90................... 4.20 VECES x cada tema adicional\nd).-Tamaño 1.50x0.90............... 8.40 VECES x cada tema adicional\ne).-Tamaño 1.50x0.90 glossy 8.40 VECES x cada tema adicional\nAE).-Por impresión de la fotografía satelital, se pagará previo al inicio del trámite, de acuerdo a la siguiente tabla:\na).-Tamaño carta......................... 5.00 VECES\nb).-Tamaño doble carta.................... 6.70 VECES\nc).-Tamaño 60x90 (glossy)................. 27.20 VECES\nd).-Completa.............................. 165.30 VECES\nAF).-Por impresión de plano con posicionamiento, se pagará previo al inicio del trámite, de acuerdo a la siguiente tabla:\na).-Tamaño carta.......................... 11.70 VECES\nb).-Tamaño doble carta.................... 16.80 VECES\nc).-Tamaño 60x90(glossy).................. 20.70 VECES\nAG).-Por digitalización de predio, se pagará previo al inicio del trámite........... 5.00 VECES\nAH).-Por archivo digital en pdf, de los Planes y Programas de Desarrollo Urbano del\nMunicipio de Tijuana, se pagará previo al inicio del trámite.................. 34.90 VECES\nAI).-Por plano de los Planes y Programas de\nDesarrollo Urbano del Municipio de\nTijuana, en jpg, se pagará previo al inicio del trámite................... 3.40 VECES\nAJ).-Por impresión de los Planes y Programas de Desarrollo\nUrbano del Municipio de Tijuana, se pagará previo al inicio del trámite, de acuerdo a la siguiente tabla:\na).-Tamaño carta..........................\n3.40 VECES\nb).-Tamaño doble carta....................\n5.00 VECES\nc).-Tamaño 60x90.........................\n11.70 VECES\nAK).-Por integración de información de instrumentos de planeación correspondientes al medio físico natural, medio físico transformado, aspectos socioeconómicos, movilidad con 4 variables a elegir en polígonos prediseñados (municipio, delegaciones, unidades territoriales de planeación (utp), sectores, subsectores, colonias, fraccionamientos y/o asentamientos), así como polígonos proporcionados por el solicitante en formato digital kmz o dwg, se pagará previo al inicio del trámite\na).-Para información de más de un tipo.... 55.60 VECES\nb).-Para información del mismo tipo....... 41.40 VECES\nc).-Por variable adicional se cobrará el 10% (diez por ciento) adicional según su tipo(Incluye variables operadas)\nAL).-Por base de información de 3 variables, en polígonos diseñados por el usuario.\na).-Variables originales en polígono agrupado / sencillo................... 55.60 VECES\nb).-Variables operadas en polígono agrupado\n/ sencillo............................. 62.00 VECES\nc).-Variables originales en polígonos desagrupados / dispersos.............. 62.00 VECES\nd).-Variables operadas en polígonos desagrupados / dispersos.............. 69.80 VECES\ne).-Por variable adicional según su tipo se cobrara 10%\n(diez por ciento) adicional.\nAM).-Por el servicio de generación de información digital en: ortomosaico georreferenciado, malla de puntos texturizada y nube de puntos, según superficie:\na).-En una superficie de hasta 50 hectáreas, obtenida a una altura inferior a 60 metros o la altura mínima que permitan los obstáculos de la superficie a cubrir.......... 300.00 VECES\nb).-En una superficie de hasta 50 hectáreas, obtenida a una altura de 60 metros y de hasta 90 metros......\n250.00 VECES\nc).-En una superficie de hasta 50 hectáreas, obtenida a una altura superior a 90 metros y hasta 120 metros o la altura máxima que permita la autoridad aeronáutica y los obstáculos de la superficie a cubrir.\n................................. 150.00 VECES\nd).-Por procesamiento adicional para generar productos derivados en un conjunto de modelo digital de superficie, modelo de terreno y\ne).-Por procesamiento adicional para generar clasificación de nubes de puntos automatizada con software que opera este Instituto......... 25.00 VECES\nf).-Por cada Ha. adicional correspondiente al subinciso a) y b).\n6.00 VECES\ng).-Por cada Ha. adicional correspondiente al subinciso c).... 3.00 VECES\nh).-Por cada Ha. adicional correspondiente al subinciso e).... 2.00 VECES\nAN).-Por evaluación para determinar el cálculo del pago por transferencia de derechos de desarrollo, se pagará previo al inicio del trámite, de acuerdo a la siguiente tabla:\na).-Cambio y/o reasignación de uso de suelo al asignado en los Programas de\nDesarrollo Urbano del Municipio de\n100.70 VECES\nb).- Densidades mayores a las establecidas en el Reglamento de Zonificación y Usos del Suelo del Centro de Población de\nTijuana, en apego a los Programas de\nDesarrollo Urbano del municipio de\nTijuana......... 134.30 VECES\nAÑ).-Por evaluación para determinar el cálculo de pago por potencial de derechos de desarrollo, se pagará previo al inicio del trámite, de acuerdo a la siguiente tabla:\na).-Cambio o reasignación de uso de suelo al asignado en los Programas de\n144.60 VECES\nDesarrollo Urbano del municipio de\nb).-Densificación e intensificación mayores a las establecidas en el\nReglamento de Zonificación y Usos del\nSuelo del Centro de Población de\nTijuana, en apego a los Programas de\nDesarrollo Urbano del municipio de\nAO).-Los costos antes señalados en los incisos AN) y AÑ), aplicaran para los trámites que no cuenten con emisión de dictamen favorable de estudio de impacto urbano.\nAP).-El cálculo que determine el Instituto Metropolitano de\nPlaneación de Tijuana para el pago de transferencia de derechos de desarrollo y/o potencial de derechos de desarrollo, será el que utilizará la autoridad responsable para su cobro.\nAQ).-Por impartición de cursos, capacitaciones, diplomados y/o actualizaciones profesionales, relativos a planeación urbana, según convocatoria.\nAR).-Por la revisión y evaluación de declaratorias, moratorias, estudios de integración urbana y otras revisiones, se pagará previo al inicio del trámite:\na).-De hasta 50 hectáreas......... 1,381.60\nVECES\nb).-De 50.1 a 100 hectáreas........ 1,842.13\nVECES\nc).-Más de 100.01 A 500 hectáreas.... 2,763.19\nVECES\nAS).-Por la revisión y evaluación de planes y/o programas de desarrollo urbano y otras revisiones, se pagará previo al inicio del trámite:\na).-De hasta 100 hectáreas........ 2,763.19\nVECES\nb).-De 100.01 a 500 hectáreas...... 3,684.26\nVECES\nc).-Más de 500.001 hectáreas se pagará previo convenio autorizado por la Junta de Gobierno del Instituto.\nAT).-Por elaboración de estudios de integración urbana, moratorias, planes y/o programas de desarrollo urbano, se pagará previo contrato y/o convenio autorizado por la Junta de Gobierno del Instituto.\nAU).-Por copia simples y/o certificadas se pagarán previo al inicio del trámite, de conformidad a los derechos por expedición de certificados, título y copias señaladas en esta Ley.\nTratándose de dependencias gubernamentales del ámbito municipal, estatal o federal, estarán exentos de pago de derechos correspondientes a este artículo, previa solicitud que se realice por escrito, exceptuando elaboración de Planes y Programas de\nDesarrollo Urbano.\nARTÍCULO 50.- Las infracciones cometidas por peritos registrados ante el Instituto Metropolitano de Planeación de Tijuana, se sancionarán y/o multarán de conformidad a lo establecido en el\nReglamento de Zonificación y Uso del Suelo del Centro de Población de Tijuana, Baja California.\nCAPÍTULO V\nARTÍCULO 51.-Los servicios que presta el Instituto Municipal de la siguiente:\nA).- Asesoría jurídica en materia familiar\nB).- Asesoría jurídica en materia penal.\nC).- Terapia psicológica individual.\nD).- Terapia psicológica grupal.\nE).- Talleres y capacitaciones.\nCAPÍTULO VI\nARTÍCULO 52.-Los servicios que presta el Instituto Municipal de\nArte y Cultura, se cobrarán conforme a lo siguiente:\nTARIFA\nUNIDAD DE MEDIDA Y\nACTUALIZACIÓN (UMA) VIGENTE\nI.-Renta de espacios:\nA).-Feria del libro, renta de espacios por el periodo de duración del evento:\na).-Módulo de 3 x 3 Mt............... 73.58 VECES\nb).-Módulo de 3 x 3 Mt.. con giro comercial afín al evento.............. 100.69 VECES\nc).-Módulo de 3 x 3 Mt. a proyectos culturales............................ 73.58 VECES\nd).-Módulo de 3 x 3 Mt. a integrantes de la unión de libreros............... 20.66 VECES\ne).-Universidades y librerías independientes........................ 73.58 VECES\nf).-Renta de espacios para eventos culturales, 40% organizador, 40% IMAC y\n20% institución educativa\ng).-Renta de sala audiovisual Rubén\nVizcaino.............................. 14.46 VECES\nB).-Renta mensual del Pasaje 5 y 10:\na).-Renta mensual del Pasaje 5 y 10. 1,583.80 VECES\nC).-Casa de Cultura Tijuana:\na).-Renta de espacio para verbena popular............................... 4.68 VECES\nb).-Renta de teatro por evento....... 47.76 VECES\n1) Cuota por recuperación energía eléctrica............................. 3.86 VECES\n2) Deposito en garantía.......... 13.43 VECES\nc).-Servicio de limpieza por renta de teatro por evento de la Casa de Cultura\nTijuana............................... 4.00 VECES\nd).-Servicio técnico de audio y luces extra por renta de teatro por evento de la Casa de Cultura Tijuana............ 4.00 VECES\ne).-Servicio de tramoyista por renta de teatro por evento de la Casa de Cultura\nTijuana............................... 4.00 VECES\nf).-Renta de Café Foro Galería por evento................................ 33.56 VECES\n1).-Cuota recuperación energía eléctrica............................. 6.66 VECES\ng).-Renta de cajón de estacionamiento por evento............................ 0.27 VECES\nh).-Renta de salón 104 por hora..... 4.00 VECES\ni).-Renta de salón 104 por evento.... 10.72 VECES\nj).-Renta de salón en general por evento................................ 4.00 VECES\nk).-Renta de fachada, escalinata y jardines por hora..................... 4.68 VECES\nl).-Renta de fachada, escalinata y jardines por evento................... 47.76 VECES\n1) Cuota recuperación energía eléctrica........................ 3.86 VECES\nm).-Deposito en Garantía de renta de fachada, escalinata y jardines........ 13.43 VECES\nn).-Renta de espacio de 3 x 3 metros para venta de alimentos y bebidas..... 16.78 VECES\nD).-Casa de Cultura Playas:\na).-Café Literario:\n1).-Renta mensual................ 33.56 VECES\n2).-Cuota mensual de energía eléctrica.................. 6.66 VECES\nb).-Renta de espacio 3x3 Mt. para venta de productos en festivales en general. 16.78 VECES\nc).-Renta de cajón de estacionamiento por evento\n1).-Por evento................... 0.67 VECES\nd).-Renta de espacio publicitario.... 33.56 VECES\ne).-Renta de espacio para verbena popular por evento.................... 3.34 VECES\nf).-Lienzo Charro:\n1).-Renta por evento\ni).- A escuelas y asociaciones civiles de lunes a jueves... 27.11 VECES ii).- Al público en general, de lunes a jueves.............. 40.02 VECES iii).- Al público en general, de viernes a domingo........ 67.13 VECES\n2).-Renta por hora extra......... 6.66 VECES\n3).-Renta de ruedo por hora...... 1.07 VECES\n4).-Renta de manga por hora...... 1.07 VECES\n5).-Renta de corrales y toriles por hora.......................... 0.67 VECES\n6).-Renta de cojines por evento.. 0.27 VECES\n7).-Curso por convenio 70% MAESTRO\n- 30% IMAC, en clase de equitación y escaramuza\n8).-Depósito en garantía......... 6.66 VECES\n9).-Cuota de limpieza............ 6.66 VECES\ng).-Patio Kiosco:\n1).-Renta por evento:\ni).- A escuelas y asociaciones civiles, de lunes a jueves.... 13.43 VECES ii).- Al público en general.. 33.56 VECES\n2).-Servicio de limpieza......... 8.00 VECES\n3).-Renta de mobiliario (equipales) 6.66 VECES\n4).-Depósito en garantía......... 13.43 VECES\nh).-Patio Andaluz:\n1).-Renta por evento............. 20.66 VECES\n2).-Servicio de limpieza......... 4.00 VECES\n3).-Depósito en garantía......... 6.66 VECES\ni).-Teatro Griego:\n1).-Renta por evento:\ni).-A escuelas y asociaciones civiles, de lunes a jueves.... 4.00 VECES ii).-Al público en general, de lunes a jueves................ 13.43 VECES iii).-Al público en general, de viernes a domingo............. 20.66 VECES\n2).-Servicio de limpieza......... 4.00 VECES\n3).-Depósito en garantía......... 13.43 VECES\nj).-Salón los Arcos:\n1).-Renta por evento:\ni).-A escuelas y asociaciones civiles, de lunes a jueves\n......................... 38.73 VECES ii).-Al público en general, de lunes a jueves........... 49.06 VECES iii).-Al público en general, de viernes a domingo........ 80.04 VECES iv).-Renta de sonido......... 13.43 VECES\nv).-Renta de mobiliario..... 24.52 VECES vi).-Cuota energía eléctrica. 3.86 VECES\n2).-Servicio de limpieza......... 9.43 VECES\n3).-Depósito en garantía......... 20.66 VECES\nk).-Jardín del Arte:\n1).-Renta por evento:\ni).-A escuelas y asociaciones civiles, de lunes a jueves.... 34.86 VECES ii).-Al público en general, de lunes a jueves................ 40.02 VECES iii).-Al público en general, de viernes a domingo............. 60.67 VECES iv.-Cuota de energía eléctrica\n.............................. 3.86 VECES\n2).-Servicio de limpieza......... 6.66 VECES\n3).-Depósito en garantía......... 13.43 VECES\nl).-Renta de espacio para verbena sevillana............................. 20.66 VECES\nm).-Renta mensual de espacio individual de caballeriza........................ 7.34 VECES\nn).-Salón La Tasca:\n1).-Renta por evento:\ni).-A escuelas y asociaciones civiles, de lunes a jueves.... 20.66 VECES ii).-Al público en general, de lunes a jueves................ 27.11 VECES iii).-Al público en general, de viernes a domingo............. 40.02 VECES\n2).-Servicio de limpieza......... 4.00 VECES\n3).-Renta de mobiliario.......... 16.78 VECES\n4).-Depósito en garantía......... 13.43 VECES\n5)Cuota recuperación energía eléctrica............................. 3.86 VECES\no).-Renta de tarima.................. 8.00 VECES\np).-Renta de estacionamiento para evento de salón La Tasca:\n1).-Renta por evento............. 65.84 VECES\n2).-Servicio de limpieza......... 6.54 VECES\nq).-Renta de explanada exterior:\n1).-Renta por evento............. 32.27 VECES\n2).-Servicio de limpieza......... 6.54 VECES\n3)Deposito en garantía........... 9.64 VECES\nr).-Renta de espacios de 3x3 metros para guarda o almacenamiento de equipo de montura por mes.................... 16.78 VECES\ns).-Renta mensual de espacio individual para estacionar remolques para transportar caballos.................. 4.34 VECES\nE).-Casa de Cultura Pípila:\na).-Renta de espacio 3 x 3 M² para verbena popular....................... 2.67 VECES\nb).-Renta de sala de usos múltiples. 13.43 VECES\nc).-Renta de sala de usos múltiples incluye sonido y personal técnico.... 20.66 VECES\nd).-Contratación de la Orquesta\nSinfónica Infantil-Juvenil del IMAC por evento................................ 20.66 VECES\ne).-Renta de Anfiteatro por 4 horas. 13.43 VECES\nf).-Renta de Aula por 2 horas........ 2.67 VECES\ng).-Renta de explanada por 2 horas.. 2.67 VECES\nF).-Coordinación de Galerías:\na).-Renta de Galería de la Ciudad para presentaciones de danza, teatro, música o conferencias........................ 10.07 VECES\nb).-Renta de Galerías Benjamín Serrano y Álvarez Malo para presentaciones de danza, teatro, música o conferencias.. 6.01 VECES\nc).-Renta de espacios en festivales internos (jardín del arte, mercados artesanales y artísticos)............. 2.01 VECES\nG).-Venta de obras de arte:\na).-Obras en espacios galerísticos del IMAC........... 4.52 - 31.47 VECES\nb).-Obras en espacios externos\n(mercados de arte, jardín del\nArte)........................... 0.90 - 28.39 VECES\nH).-Casa de la Cultura Casa San\nAntonio de los Buenos:\na).-Renta de aula por hora........... 1.45 VECES\nb).-Renta de espacio 3x3 metros para verbena popular....................... 3.12 VECES\nc).-Renta de sala de usos múltiples por\n4 horas:\n1)Por evento..................... 17.83 VECES\n2)Deposito en Garantía........... 11.57 VECES\n3)Servicio de Limpieza........... 4.82 VECES\nd) Renta de Jardín trasero por 4 horas:\n1)Por evento..................... 8.68 VECES\n2)Deposito en Garantía........... 3.86 VECES\n3)Servicio de Limpieza........... 4.82 VECES\nII.-Recorridos:\nA).-Recorrido Binacional\na).-JPAUL GETTY MUSEUM............... 9.43 VECES\nb).-HEARTS CASTLE.................... 29.69 VECES\nc).-AQUARIUM OF THE PACIFIC.......... 15.49 VECES\nd).-GRIFFITH OBSERVATORY............. 9.43 VECES\ne).-CALIFORNIA SCIENCE CENTER........ 4.68 VECES\nB).-Taller en recorrido.................. 0.34 VECES\nC).-Recorrido por galerías del IMAC con degustación de vinos......... 4.52 - 20.65 VECES\nD).-Recorrido Histórico:\na).-Estudiante visita guiada a Museo de\nHistoria de Tijuana, Archivo Histórico y taller artístico.................. 0. 2 0 VECES\nb).-Estudiante visita guiada a Museo de\nHistoria de Tijuana, Archivo Histórico y cuenta cuentos...................... 0.34 VECES\nc).-Estudiante visita guiada a Museo de\nHistoria de Tijuana, Archivo Histórico y cuenta cuentos con transporte....... 0.48 VECES\nE).-Recorrido Cultural:\na).-Estudiante visita guiada a bibliotecas municipales y taller artístico............................. 0.20 VECES\nb).-Estudiante visita guiada a bibliotecas municipales y cuenta cuentos............................... 0.34 VECES\nc).-Estudiante visita guiada a Museo de\nHistoria de Tijuana, Archivo Histórico y taller artístico.................... 0.20 VECES\nd).-Estudiante visita guiada a bibliotecas municipales y cuenta cuentos con transporte................ 0.48 VECES\ne).-Estudiante visita guiada casas de cultura y taller artístico............ 0.20 VECES\nf).-Estudiante visita guiada casas de cultura y cuenta cuentos.............. 0.34 VECES\ng).-Estudiante visita guiada casas de cultura y taller artístico con transporte............................ 0.48 VECES\nh).-Estudiante visita guiada casas de cultura y cuenta cuentos con transporte 0.48 VECES\nF).-Función de teatro exclusiva para estudiantes organizado por el IMAC, en casas de cultura:\na).-Boleto de entrada................ 0.48 VECES\nG).-Actividades escénicas extra muros:\na).-Cobro por estudiante en escuelas de escasos recursos por cuenta cuentos... 0.08 VECES\nb).-Presentación de cuenta cuentos en escuelas de escasos recursos con matricula mayor a cien alumnos, precio por estudiante........................ 0.14 VECES\nc).-Presentación de obra de teatro en escuelas con matrículas mayor a 100 alumnos, precio por estudiante........ 0.34 VECES\nd).-Presentación de obra de teatro en escuelas con matrículas menor a 100 alumnos, precio por estudiante........ 0.48 VECES\nIII.-Cursos y talleres:\nA).-Casa de la Cultura Tijuana:\na).-Inscripción semestral a cursos y talleres......................... 1.60 VECES\nb).-Inscripción cursos EMNO Escuela de\nMúsica del Noroeste.............. 1.60 VECES\nc).-Mensualidad cursos EMNO Escuela de\nMúsica del Noroeste.............. 6.01 VECES\nd).-Campamento de verano, incluye camiseta......................... 19.37 VECES\ne).-Mensualidad curso o taller de música........................... 4.68 VECES\nf).-Mensualidad curso o taller de danza\n................................. 4.68 VECES\ng).-Mensualidad curso o taller de literatura....................... 4.68 VECES\nh).-Mensualidad curso o taller de idiomas.......................... 4.68 VECES\ni).-Mensualidad curso o taller de manualidades..................... 4.68 VECES\nj).-Mensualidad curso o taller de artes plásticas........................ 4.68 VECES\nk).-Mensualidad curso o taller de artes visuales......................... 4.68 VECES\nl).-Mensualidad curso o taller de artes escénicas........................ 4.68 VECES\nm).-Mensualidad curso o taller de disciplinas alternativas......... 4.68 VECES\nn).-Mensualidad de talleres, cursos, diplomados, seminarios y eventos en co-producción 70-30 (IMAC). 16.86 - 33.73 VECES ñ).-Mensualidad de talleres, cursos diplomados, seminarios y eventos en co-producción 8020 (IMAC)................... 0.00 - 25.81 VECES\nB).-Casa de la Cultura Playas:\na).-Curso de verano julio-agosto..... 6.01 VECES\nb).-Inscripción a curso de verano.... 1.35 VECES\nc).-Inscripción semestral a cursos y talleres......................... 1.6 VECES\nd).-Inscripción a cursos EMNO........ 1.34 VECES\ne).-Mensualidad curso EMNO........... 2.67 VECES\nf).-Mensualidad curso o taller de música........................... 4.68 VECES\ng).-Mensualidad curso o taller de danza\n................................. 4.68 VECES\nh).-Mensualidad curso o taller de literatura....................... 4.68 VECES\ni).-Mensualidad curso o taller de idiomas.......................... 4.68 VECES\nj).-Mensualidad curso o taller de manualidades.................... 4.68 VECES\nk).-Mensualidad curso o taller de artes plásticas........................ 4.68 VECES\nl).-Mensualidad curso o taller de artes visuales......................... 4.68 VECES\nm).-Mensualidad curso o taller de artes escénicas........................ 4.68 VECES\nn).-Mensualidad curso o taller de bienestar físico................. 4.68 VECES ñ).-Evento con la banda de Música para\nJóvenes de Preparatoria.......... 0.40 VECES\no).-Campamento de verano de música.. 6.66 VECES\np).-Mensualidad clases individuales de música, pintura y danza.......... 8.00 VECES\nq).-Recorrido Taller de Creatividad.. 0.20 VECES\nr).-Recorrido taller y cuenta cuentos 0.34 VECES\ns).-Recorrido taller y obra de teatro 0.40 VECES\nt).-Mensualidad curso o taller de disciplinas alternativas......... 3.37 VECES\nu).-Campamento de verano, incluye camiseta......................... 19.37 VECES\nv).-Playera campamento de verano..... 1.35 VECES\nC).-Casa de la Cultura Pípila:\na).-Inscripción semestral a cursos y talleres......................... 1.34 VECES\nb).-Mensualidad de Orquesta (Cuerdas y\nAlientos)........................ 3.34 VECES\nc).-Mensualidad de taller, canto, coro y teoría musical................. 3.34 VECES\nd).-Mensualidad de taller de piano.. 2.67 VECES\ne).-Mensualidad Taller de Iniciación a la Música........................ 2.67 VECES\nf).-Mensualidad Taller de Guitarra\nClásica.......................... 2.67 VECES\ng).-Mensualidad Taller de Guitarra\nPopular.......................... 2.67 VECES\nh).-Mensualidad Taller de Hip-Hop... 2.67 VECES\ni).-Mensualidad Taller de Jazz....... 2.67 VECES\nj).-Mensualidad Taller de Francés... 2.67 VECES\nk).-Mensualidad Taller de Danza Árabe\n................................. 2.67 VECES\nl).-Mensualidad Taller Fotografía\nInfantil....................... 2.67 VECES\nm).-Mensualidad Taller Cortometraje y\nVideo infantil................... 2.67 VECES\nn).-Mensualidad Taller Danza\nContemporánea.................... 2.67 VECES ñ).-Mensualidad Taller Batería y\nPercusiones...................... 2.67 VECES\no).-Mensualidad Taller Guitarra\nEléctrica........................ 2.67 VECES\np).-Mensualidad Taller Baile de Salón 3.34 VECES\nq).-Mensualidad Taller Ritmos Latinos 3.34 VECES\nr).-Mensualidad Taller de Iniciación a la Danza......................... 2.67 VECES\ns).-Mensualidad Taller Ballet Clásico 2.67 VECES\nt).-Mensualidad Curso de Inglés...... 2.67 VECES\nu).-Mensualidad Clase de Ajedrez..... 3.34 VECES\nv).-Mensualidad Taller Artes Plásticas\n................................. 2.67 VECES\nw).-Mensualidad Taller Creación de\nComics........................... 2.67 VECES\nx).-Mensualidad Taller de Manualidades\n................................. 2.67 VECES\ny).-Mensualidad Clase de Corte y\nConfección (vestuario)........... 2.67 VECES\nz).-Mensualidad Taller de Teatro..... 2.67 VECES aa).-Campamento de Verano............ 10.6 VECES ab).-Camiseta Campamento de Verano... 1.07 VECES ac).-Otras rentas de espacio......... 6.66 VECES ad).-Otros eventos................... 100.69 VECES ae).-Mensualidad curso taller de disciplinas alternativas......... 3.37 VECES af).-Mensualidad o curso taller de literatura....................... 2.89 VECES\nD).-Casa de la Cultura San Antonio de los\nBuenos:\na).-Taller de Artes Escénicas:\n1).-Inscripción Taller Artes\nEscénicas.................... 1.45 VECES\n2).-Mensualidad Ballet Clásico\nInfantil..................... 2.89 VECES\n3).-Mensualidad Ballet Clásico... 2.89 VECES\n4).-Mensualidad Jazz Infantil.... 2.89 VECES\n5).-Mensualidad Jazz............. 2.89 VECES\n6).-Mensualidad Danza Árabe infantil...................... 2.89 VECES\n7).-Mensualidad Danza Árabe...... 2.89 VECES\n8).-Mensualidad Taller Integral de\nDanza........................ 2.89 VECES\n9).-Mensualidad Baile Social..... 2.89 VECES\n10).-Mensualidad Danza\nContemporánea................ 2.89 VECES\n11).-Mensualidad Hip Hop......... 2.89 VECES\n12).-Mensualidad Danza Folclórica 2.89 VECES\n13).-Mensualidad Actuación....... 2.89 VECES\nb).-Taller de música:\n1).-Inscripción Taller de Música 1.45 VECES\n2).-Mensualidad Guitarra Clásica 2.89 VECES\n3).-Mensualidad Guitarra Popular 2.89 VECES\n4).-Mensualidad Guitarra Eléctrica 2.89 VECES\n5).-Mensualidad Clase de Piano... 2.89 VECES\n6).-Mensualidad Clase de Teclado 2.89 VECES\n7).-Mensualidad Canto y Coro..... 2.89 VECES\n8).-Mensualidad Clase de batería 2.89 VECES\n9).-Mensualidad Iniciación Musical 2.89 VECES\n10).-Mensualidad Clase\nInstrumento, Canto y Juego..... 2.89 VECES\n11).-Mensualidad Clase Bajo...... 2.89 VECES\n12).-Mensualidad Clase de Violín. 2.89 VECES\n13).-Mensualidad Orquesta........ 2.89 VECES\n14).-Mensualidad Saxofón......... 2.89 VECES\nc).-Taller de artes plásticas:\n1).-Inscripción Taller de Artes\nPlásticas.................... 1.45 VECES\n2).-Mensualidad Crayolarte, Iniciación a la Pintura...... 2.89 VECES\n3).-Mensualidad Taller de Pintura 2.89 VECES\n4).-Mensualidad Taller Dibujo\nArtístico..................... 2.89 VECES\n5).-Mensualidad Taller Serigrafía 2.89 VECES\n6).-Mensualidad Fotografía Digital\nI............................. 2.89 VECES\n7).-Mensualidad Fotografía Digital\nII............................ 2.89 VECES\n8).-Mensualidad Fotografía Digital\nIII........................... 2.89 VECES\nd).-Taller de idiomas:\n1).-Inscripción Taller de Idiomas 1.45 VECES\n2).-Mensualidad Inglés Infantil.. 2.89 VECES\n3).-Mensualidad Inglés Básico.... 2.89 VECES\n4).-Mensualidad Inglés\nPrincipiantes................ 2.89 VECES\n5).-Mensualidad Francés.......... 2.89 VECES\n6).-Mensualidad Alemán........... 2.89 VECES\n7).-Mensualidad Italiano......... 2.89 VECES\n8).-Mensualidad Portugués........ 2.89 VECES\ne).-Taller de Gastronomía:\n1).-Inscripción Taller de\nGastronomía.................. 1.45 VECES\n2).-Mensualidad Repostería y\nManualidades................. 2.89 VECES\n3).-Mensualidad Cocina Verde..... 2.89 VECES\n4).-Mensualidad Cocina Verde, Repostería y Manualidades.... 2.89 VECES\nf).-Taller de Yoga:\n1).-Inscripción Taller de Yoga.. 1.45 VECES\n2).-Mensualidad Yoga Infantil.... 2.89 VECES\n3).-Mensualidad Yoga adultos..... 2.89 VECES\ng).-Curso de Verano:\n1).-Campamento Infantil de Verano con camiseta................... 10.72 VECES\nh).-Mensualidad curso taller de\nDisciplinas alternativas....... 3.37 VECES\nE).-Casa de la Cultura Cerro Colorado:\na).-Inscripción semestral a cursos y talleres......................... 1.29 VECES\nb).-Mensualidad de Orquesta (Cuerdas y\nAlientos)........................ 3.23 VECES\nc).-Mensualidad de taller, canto, coro y teoría musical................. 3.23 VECES\nd).-Mensualidad de taller de piano... 2.28 VECES\ne).-Mensualidad taller de iniciación a la música........................ 2.58 VECES\nf).-Mensualidad taller de guitarra clásica.......................... 2.58 VECES\ng).-Mensualidad taller de guitarra popular.......................... 2.58 VECES\nh).-Mensualidad taller de hip-hop.... 2.58 VECES\ni).-Mensualidad taller de Jazz....... 2.58 VECES\nj).-Mensualidad taller de francés.... 2.58 VECES\nk).-Mensualidad taller de danza árabe 2.58 VECES\nl).-Mensualidad taller fotografía infantil......................... 2.58 VECES\nm).-Mensualidad taller cortometraje y video infantil................... 2.58 VECES\nn).-Mensualidad taller danza contemporánea.................... 2.58 VECES ñ).-Mensualidad taller batería y percusiones...................... 2.58 VECES\no).-Mensualidad taller guitarra eléctrica........................ 2.58 VECES\np).-Mensualidad taller baile de salón 3.23 VECES\nq).-Mensualidad taller ritmos latinos 3.23 VECES\nr).-Mensualidad taller de iniciación de danza............................ 2.58 VECES\ns).-Mensualidad taller ballet clásico 2.58 VECES\nt).-Mensualidad curso de inglés...... 2.58 VECES\nu).-Mensualidad clase de ajedrez.... 3.23 VECES\nv).-Mensualidad taller artes plásticas\n................................. 2.58 VECES\nw).-Mensualidad taller de creación de comics........................... 2.58 VECES\nx).-Mensualidad taller de manualidades\n................................. 2.58 VECES\ny).-Mensualidad clase de corte y confección (vestuario)........... 2.58 VECES\nz).-Mensualidad taller de teatro.... 2.58 VECES aa).-Campamento de verano............ 7.10 VECES ab).-Camiseta campamento de verano... 1.03 VECES ac).-Otras rentas de espacio......... 6.46 VECES ad).-Otros eventos................... 96.82 VECES ae).-Mensualidad curso o taller de\nDisciplinas alternativas......... 4.52 VECES\nIV.-Coproducciones donde el instituto colabora con un tercero para realizar eventos en que se genere un ingreso económico, se realizarán de acuerdo a las siguientes tasas de participación expresadas en porcentaje:\nA).-Curso o Taller Artístico por convenio 70% MAESTRO\n70-30............................... 3 0 % I M AC\n20% IMAC\n30% IMAC\nD).-Eventos culturales en colaboración con 40% ORGANIZADOR\n20% ESCUELA\n60% ORGANIZADOR,\n75% ORGANIZADOR,\nV.-Venta de artículos y alimentos\nA).-Venta de bebidas sin alcohol en distintas instalaciones de IMAC:\na).-Agua y refresco.................. 0.21 VECES\nb).-Clamato sin cerveza.............. 0.54 VECES\nB).-Venta de bebidas con alcohol en distintas instalaciones de IMAC:\na).-Cerveza.......................... 0.34 VECES\nb).-Clamato con cerveza.............. 0.88 VECES\nc).-Copa de tequila.................. 0.61 VECES\nd).-Palomita (tequila con refresco).. 0.54 VECES\ne).-Copa de vino..................... 0.61 VECES\nNotas adicionales:\n1.- Tratándose de Adultos Mayores que presenten su credencial del\nINAPAM y de personas con capacidades diferentes, podrán hacerse acreedores a un descuento del 50% (cincuenta por ciento), en los talleres que se imparten con maestros contratados por IMAC.\n2.- Tratándose de Adultos Mayores que presenten su credencial del\nINAPAM y de personas con capacidades diferentes, podrán hacerse acreedores a un descuento del 25% (veinticinco por ciento), en los talleres que se imparten con maestros vía convenio, previa autorización de los maestros.\n3.- Las personas referidas en el punto 1, se les aplicará un descuento del 50% (cincuenta por ciento), en el cobro de cajón de estacionamiento, durante el tiempo que se encuentren tomando el taller.\n4.- Las personas referidas en el punto 2, se les aplicará un descuento del 25% (veinticinco por ciento), en el cobro de cajón de estacionamiento, durante el tiempo que se encuentren tomando el taller.\n5.- Se otorgará un descuento del 50% (cincuenta por ciento) a todos los empleados de IMAC, que presenten su credencial vigente, en cursos y talleres que imparte la Institución así como en el arrendamiento de espacios de IMAC.\nNota.-Son beneficios para que los empleados hagan uso y disfrute de ellos, no se permite intercambiar o prestar dicho beneficio.\n6.-Tratándose del concepto de Campamento de Verano, se aplicará un descuento del 30% (treinta por ciento) para el segundo hijo, 50%\n(cincuenta por ciento) para tercer hijo y una beca del 100% (cien por ciento) para cuarto hijo.\n7.-Para actividades realizadas en los diferentes espacios del\nInstituto y que sean para recaudación de fondos del propio IMAC, no tendrá costo el uso de los mismos.\n8.-Se otorgará un descuento del 50% (cincuenta por ciento)a y talleres que imparte IMAC\nCAPÍTULO VII\nARTÍCULO 53.-Los servicios que presta el Sistema Municipal de\nParques Temáticos de Tijuana, a través del Parque José María usuarios, sujetándose a la siguiente:\nTARIFA\nUNIDAD DE MEDIDA Y\nACTUALIZACIÓN (UMA) VIGENTE\nI.-Parque JOSÉ MARÍA MORELOS Y PAVÓN\nA).-Estacionamiento público:\na).-Tarifa diaria en horario diurno de 8:00 am 5:00 pm............... 0.30 VECES\nb).-Tarifa diaria con horario nocturno de 5:01 pm a 7:59 am... 0.61 VECES\nc).-Tarifa deportistas sin credencial de 6:00 am a 10:00 am y\n5:00 pm a 8:00 pm............... 0.09 VECES\nd).-Credencial anual para deportistas...................... 4.49 VECES\ne).-Credencial Anual para comerciantes.................... 0.52 VECES\nf).-Tarifa proporcional por mes credencial deportistas.......... 0.37 VECES\ng).-Boleto perdido................ 0.67 VECES\nB).-Arrendamiento de espacios de recreación\na).-Kioscos por día............... 5.69 VECES\n1).-Cuota por limpieza............. 4.49 VECES\nb).-Palapas por día................ 5.69 VECES\n1).-Cuota por limpieza............. 4.49 VECES\nc).-Áreas verdes Olivos A, B Y C, Águilas A, B Y C................. 4.49 VECES\n1).-Cuota por limpieza............ 4.49 VECES\nC).-Arrendamiento de jardines temáticos y espacios para eventos.\na).-Jardín Oriental para eventos menores, con un máximo de 200 personas. En horarios de 8:00 am a\n4:00 pm.......................... 27.51 VECES\n1).-Cuota por limpieza......... 10.59 VECES\n2).-Hora excedente por renta de\nJardín Oriental.................. 4.49 VECES\n3).-Toma eléctrica............. 7.47 VECES\nb).-Jardín Oriental para eventos menores, con un máximo de 200 personas. En horarios de 4:00 am a\n10:00 pm......................... 34.74 VECES\n1).-Cuota por limpieza......... 10.59 VECES\n2).-Hora excedente por renta de\nJardín Oriental.................. 4.49 VECES\n3).-Toma eléctrica............. 7.47 VECES\nc).-Jardín Oriental para eventos 7 mayores, bodas, XV años, kermés, reuniones de alta afluencia, día completo......................... 75.27 VECES\n1).-Cuota por limpieza......... 10.59 VECES\n2).-Hora excedente por renta de\nJardín Oriental.................. 4.49 VECES\n3).-Toma eléctrica............. 7.47 VECES\nd).-Jardín Árabe para eventos menores, reuniones familiares y cumpleaños. En horarios de 8:00 am a 5:00 pm........................ 23.16 VECES\n1).-Cuota por limpieza......... 10.57 VECES\n2).-Hora excedente por renta de\nJardín Árabe..................... 4.49 VECES\ne).-Jardín Árabe para eventos mayores bodas, XV años, kermes, reuniones de alta afluencia de personas. Día completo...........\n37.64 VECES\n1).-Cuota por limpieza......... 10.57 VECES\n2).-Hora excedente por renta de\nJardín Árabe..................... 4.49 VECES\nf).-Jardín Presidentes para eventos menores, reuniones familiares y cumpleaños. En horarios de 8:00 am a 5:00 pm........................ 23.16 VECES\n1).-Cuota por limpieza......... 10.57 VECES\n2).-Hora excedente por renta de\nJardín Presidentes............... 4.49 VECES\ng).-Jardín Presidentes para eventos mayores bodas, XV años, kermés, reuniones de alta afluencia de personas. Día completo........... 75.27 VECES\n1).-Cuota por limpieza......... 10.57 VECES\n2).-Hora excedente por renta de\nJardín Presidentes............... 4.46 VECES\nh).-Área verde toboganes para eventos masivos reuniones, alta afluencia, día completo.......... 165.02 VECES\n1).-Cuota por limpieza......... 10.57 VECES\ni).-Área verde toboganes para evento mayor Kermés. En horarios de 8:00 am a 5:00 pm..................... 75.27 VECES\n1).-Cuota por limpieza......... 10.57 VECES\nj).-Área verde toboganes para evento menor, reuniones familiares y cumpleaños. Incluye chapoteadero de 9:00 a.m a 1:00 pm, evento en horarios de 8:00 am a 5:00 pm.... 37.64 VECES\n1).-Cuota por limpieza......... 10.57 VECES\nk).-Plaza Mexicana Cívica. En horarios de 8:00 am a 5:00 pm.\nCosto por hora(a partir de montaje)......................... 3.89 VECES\n1).-Cuota por limpieza......... 10.57 VECES\nl).-Plaza mexicana cívica. En horarios de 5:01 pm a 2:00 am.\nCosto por hora................... 7.47 VECES\n(en caso de instalación de módulos de venta se estará a la tarifa por modulo)\n1).-Cuota por limpieza......... 10.57 VECES\nm).-Jardín de los Abuelos para eventos menores, reuniones familiares y cumpleaños en horario de 8:00 am a 5:00 pm............. 8.19 VECES\n1).-Cuota por limpieza........ 4.49 VECES\nn).-Temazcal\n1).-Horario de 2:00 pm a 6:00 p.m 15.42 VECES\n2).-Horario de 6:01 pm a 10:00 p.m.......................... 15.42 VECES\n3).-Cuota por limpieza......... 4.49 VECES\nD).-Uso y aprovechamiento de espacios.\na).-Tarifas para acampar por día:\nHorario nocturno de 5:00 pm a 9:00\n1).-Adulto..................... 0.38 VECES\n2).-Infantil................... 0.23 VECES\nb).-Teatro al aire libre por hora.\nHorario diurno de 8:00 am a 5:00 pm (energía eléctrica incluida) 3. 89 VECES\n1).-Cuota por limpieza......... 4.49 VECES\nc).-Teatro al aire libre, por hora.\nHorario nocturno de 5:01 pm a 2:00 am.(energía eléctrica incluida) 7.47 VECES\n1).-Cuota por limpieza......... 4.49 VECES\nd).-Recorrido temático por persona. 0.16 VECES\ne).-Recorrido temático especial con transporte, por persona.......... 0.61 VECES\nf).-Recorrido en tren:\n1).-Adulto..................... 0.16 VECES\n2).-Infantil................... 0.06 VECES\ng).-Paseo en lanchas............... 0.54 VECES\nh).-Entrada a toboganes o zona acuática por persona............. 0.45 VECES\ni).-Uso de toma eléctrica:\n1).-Brincolín, equipo de sonido\n(El cobro es por bien)........... 2.23 VECES\n2).-Bocinas, mezcladora o tornamesa. (El cobro es por bien) 4.49 VECES\n3).-Tarifa concesionarios Parque\nJosé María Morelos y Pavón:\nA).-Aparatos menores de bajo consumo......................... 4.49 VECES\nB).-Aparatos mayores hasta dos equipos o electrodomésticos...... 7.47 VECES\nj).-Espacio para módulo 3 x 3\nM²(espacio máximo por módulo)\n1).-Empresas (reclutamiento de personal)........................ 30.40 VECES\n2).-Publicidad (eventos, conciertos, activaciones)........ 30.40 VECES\n3).-Ventas(cambaceo o al detalle)......................... 30.40 VECES\n4).-Social(asociaciones civiles, escuelas, o instituciones no gubernamentales).............. 5.24 VECES\nk).-Recorrido en Mariposario...... 0.16 VECES\nl).-Espacio para máquinas expendedoras\n1).-Botanas dulce y saladas.... 10.46 VECES\n2).-Bebidas sin graduación alcohólica (café, sodas, jugos, agua)............................ 11.86 VECES\n3).-Tarifa de consumos de energía eléctrica................ 7.14 VECES\n4).-Souvenir y mono de peluche 16.65 VECES\n5).-Mixta (Bebidas, dulces, galletas, etc.).................. 13.25 VECES\nm).-Espacio para antenas\n1).-Dimensiones de 0 - 70 metros cuadrados........................ 165.73 VECES\n2).-Dimensiones equivalentes 70 a 120 metros cuadrados.......... 229.17 VECES\nE).-Productos\na).-Venta de plantas (flor, arbusto, árbol):\n1).-Tarifa público general..... 0.23 VECES\n2).-Tarifa a negocios y empresarios...................... 0.30 VECES\nb).-Venta de Plantas de Ornato..... 0.54 VECES\nc).-Venta de Plantas Frutales..... 0.75 VECES\nd).-Venta de Cerveza Media......... 0.45 VECES\ne).-Venta de Bebida sin Alcohol... 0.23 VECES\nf).-Descorche de botellas de bebidas con graduación alcohólica........ 2.24 VECES\ng).-Comisión por venta de bebidas con graduación alcohólica. Por unidad vendida.................. 0.04 VECES\nh).-Comisión por venta de bebidas sin graduación alcohólica. Por unidad vendida.................. 0.03 VECES\ni).-Comisión por venta de bebidas preparadas con graduación alcohólica. Por unidad vendida... 0.06 VECES\nj).-Comisión por barril litros de cerveza......................... 4.53 VECES\nk).-Cubeta 5 galones de tierra y composta......................... 0.29 VECES\nF).-Clases y talleres.\na).-Taller de Hidroponía(5 sesiones)\n................................. 23.16 VECES\nb).-Campamento de verano. Tarifa por\nNiño(a).......................... 15.05 VECES\nG).-Arrendamiento de espacios para eventos.\na).-Estacionamiento No.1........... 209.90 VECES\n1).-Cuota de limpieza.......... 74.76 VECES\nb).-Estacionamiento No.2.......... 224.38 VECES\n1).-Cuota de limpieza.......... 75.27 VECES\nc).-Estacionamiento No.3........... 254.78 VECES\n1).-Cuota de limpieza.......... 75.27 VECES\nd).-Estacionamiento de palenque\n1).-Eventos deportivos......... 209.90 VECES\n2).-Eventos de espectáculos.... 299.65 VECES\n3).-Cuota de limpieza.......... 75.27 VECES\ne).-Estacionamiento Pinos......... 389.40 VECES\n1).-Cuota de limpieza.......... 75.27 VECES\nf).-Renta del Foro Cuauhtémoc\nMoctezuma (Palenque)Evento lucrativo, Profesional y\nConciertos....................... 664.65 VECES\n1).-Cuota de limpieza.......... 75.27 VECES\n2).-Cuota por día de Montaje.. 332.32 VECES\ng).- Renta del Foro Cuauhtémoc\nMoctezuma (Palenque). Eventos sociales, Culturales y educativos. 162.13 VECES\n1).-Cuota de limpieza.......... 75.27 VECES\nh).-Renta del Foro Cuauhtémoc\nMoctezuma (Palenque)Eventos de\nLucha Libre, Boxeo, Vale Todo o\nDeportes de Artes Marciales nivel amateur.......................... 125.94 VECES\n1).-Cuota de limpieza.......... 75.27 VECES\n2).-Cuota por día de Montaje... 62.97 VECES\ni).-Renta del Foro Cuauhtémoc\nMoctezuma (Palenque)Eventos no lucrativos de carácter público de alguna dependencia gubernamental. 0.00 VECES\n1).-Cuota de limpieza.......... 75.27 VECES\nj).-Renta de palenque para eventos de exhibición y casta de gallos. 145.28 VECES\n1).-Cuota de limpieza......... 75.27 VECES\n2).-Cuota de desinfección...... 30.85 VECES\n3).-Cuota por día de Montaje... 72.64 VECES\nk).-Estacionamiento plancha Nextel. 179.50 VECES\n1).-Cuota de limpieza.......... 75.27 VECES\nl)Estacionamiento CADETE.......... 361.00 VECES\nH).-Renta de espacios para venta de alimentos preparados.\na).-Sopes, flautas, tacos dorados y tostadas:\n1).-Abril- octubre............. 30.40 VECES\n2).-Noviembre – marzo......... 14.77 VECES\nb).-Burritos, tortas, arepas, quesadillas:\n1).-Abril- octubre............. 50.67 VECES\n2).-Noviembre – marzo......... 26.06 VECES\nc).-Tostadas de cuerito y carne, churritos, Sabritas y dulces:\n1).-Abril- octubre............. 43.43 VECES\n2).-Noviembre – marzo......... 24.61 VECES\nd).-Antojitos mexicanos (enchiladas, chilaquiles, pozole):\n1).-Abril- octubre............. 45.60 VECES\n2).-Noviembre – marzo......... 31.85 VECES\ne).-Pizzas:\n1).-Abril- octubre............. 34.74 VECES\n2).-Noviembre – marzo......... 27.50 VECES\nf).-Hot dog, hamburguesas en distintas versiones, salchipapas y papas fritas:\n1).-Abril- octubre............. 30.40 VECES\n2).-Noviembre – marzo.......... 20.27 VECES\ng).-Ensaladas de frutas, clamatos:(fijo y ambulante una carreta):\n1).-Abril- octubre............. 43.43 VECES\n2).-Noviembre – marzo......... 21.71 VECES\nh).-Churros, elotes asados y papas fritas:\n1).-Abril- octubre............. 33.29 VECES\n2).-Noviembre – marzo......... 23.16 VECES\ni).-Frituras, chicharrones, cacahuates,dulces y botanas\n(semifijo):\n1).-Abril- octubre............. 55.01 VECES\n2).-Noviembre – marzo......... 36.19 VECES\nj).-Tostilocos, clamatos, fijo:\n1).-Abril- octubre............. 55.01 VECES\n2).-Noviembre – marzo......... 36.19 VECES\nk).-Frituras, chicharrones, cacahuates, dulces, fijo:\n1).-Abril- octubre............. 78.17 VECES\n2).-Noviembre – marzo......... 66.68 VECES\nl).-Fruta picada, fijo:\n1).-Abril- octubre............. 36.19 VECES\n2).-Noviembre – marzo......... 30.40 VECES\nm).-Tostilocos, clamatos, semifijo\n(2 x 2 metros)::\n1).-Abril- octubre............. 20.27 VECES\n2).-Noviembre – marzo......... 8.98 VECES\nn).-Dulces ambulantes a granel:\n1).-Abril- octubre............. 20.27 VECES\n2).-Noviembre – marzo......... 8.98 VECES ñ).-Frituras y chicharrones de harina, fijo:\n1).-Abril- octubre............. 20.27 VECES\n2).-Noviembre – marzo......... 11.73 VECES\no).-Nieve Frosty, fijo:\n1).-Abril- octubre............. 17.37 VECES\n2).-Noviembre – marzo......... 13.32 VECES\np).-Paletas de hielo, ambulante:\n1).-Abril- octubre............. 4.70 VECES\n2).-Noviembre – marzo......... 3.91 VECES\nq).-Bolis Bon Ice, ambulante\n(incluye 2 ambulantes):\n1).-Abril- octubre............. 7.70 VECES\n2).-Noviembre – marzo......... 4.62 VECES\nr).-Helados Nestlé, fijo:\n1).-Abril- octubre............. 24.61 VECES\n2).-Noviembre – marzo......... 17.37 VECES\ns).-Helados Nestlé, ambulante:\n1).-Abril- octubre............. 4.69 VECES\n2).-Noviembre – marzo......... 4.69 VECES\nt).-Raspados, tipo ice y aguas frescas, fijo:\n1).-Abril- octubre............. 20.26 VECES\n2).-Noviembre – marzo......... 8.98 VECES\nu).-Tejuino, nieve y diablito fijo:\n1).-Abril- octubre............. 30.40 VECES\n2).-Noviembre – marzo......... 14.77 VECES\nv).-Pizzas, fijo:\n1).-Abril- octubre............. 138.97 VECES\n2).-Noviembre – marzo......... 108.57 VECES\nw).-Postres (pastel, flanes, panecillos dulces, churros, arroz con leche, plátanos flameados), fijo:\n1).-Abril- octubre............. 27.50 VECES\n2).-Noviembre – marzo......... 18.82 VECES\nx).-Mariscos y clamato, tosticamarones y tosticeviche fijo::\n1).-Abril- octubre............. 41.98 VECES\n2).-Noviembre – marzo......... 30.55 VECES\ny).-Nieve de Garrafa en diversas sabores y presentaciones:\n1).-Abril- octubre............. 30.40 VECES\n2).-Noviembre – marzo......... 14.77 VECES\nz).-Tacos Varios de maíz:\n1).-Abril- octubre............. 37.64 VECES\n2).-Noviembre – marzo......... 24.61 VECES aa).-Smothies, frappés, banderillas y crepas:\n1).-Abril- octubre............. 28.95 VECES\n2).-Noviembre – marzo......... 20.27 VECES ab).-Gorditas de Nata y Churros:\n1).-Abril- octubre............. 30.40 VECES\n2).-Noviembre – marzo......... 21.71 VECES ac).-Piñas Coladas Sin Alcohol y\nBobas:\n1).-Abril- octubre............. 27.50 VECES\n2).-Noviembre – marzo......... 15.92 VECES ad).-Alimentos preparados a base de carne de pollo, pollo asado, exceptuando nuggets y alitas:\n1).-Abril- octubre............. 33.29 VECES\n2).-Noviembre – marzo......... 23.16 VECES ae).-Nuggets, alitas y Papas\nSazonadas:\n1).-Abril- octubre............. 30.40 VECES\n2).-Noviembre – marzo......... 20.27 VECES af).-Elotes, Tostielotes, productos a base elotes cocidos:\n1).-Abril- octubre............. 30.40 VECES\n2).-Noviembre – marzo......... 18.83 VECES ag).-Plátanos Fritos y Papas Fritas:\n1).-Abril- octubre............. 30.40 VECES\n2).-Noviembre – marzo......... 14.77 VECES\nI).-Renta de espacio para juegos de diversión.\na).-Juegos mecánicos, semifijo\n(hasta 10 juegos):\n1).-Abril- octubre............. 277.94 VECES\n2).-Noviembre – marzo......... 124.49 VECES\nb).-Mini-autos eléctricos, fijo:\n1).-Abril- octubre............. 31.85 VECES\n2).-Noviembre – marzo......... 31.85 VECES\nc).-Frontón de canicas, fijo:\n1).-Abril- octubre............. 13.03 VECES\n2).-Noviembre – marzo......... 11.69 VECES\nd).-Tren recreativo, fijo:\n1).-Abril- octubre............. 46.32 VECES\n2).-Noviembre – marzo......... 23.16 VECES\ne).-Tren recreativo ambulante bajo ruta especificada:\n1).-Abril- octubre............. 46.32 VECES\n2).-Noviembre – marzo......... 23.16 VECES\nf).-Mini-autos Go-karts, bicicletas y patines eléctricos fijo:\n1).-Abril- octubre............. 42.46 VECES\n2).-Noviembre – marzo......... 43.43 VECES\ng).-Pintura de caritas, Tatuajes temporales henna y venta de accesorios, semifijo:\n1).-Abril- octubre............. 31.85 VECES\n2).-Noviembre – marzo......... 18.82 VECES\nh).-Bicicletas (25 bicicletas), fijo:\n1).-Abril- octubre............. 23.16 VECES\n2).-Noviembre – marzo......... 23.16 VECES\ni).-Burbujas de jabón, ambulante:\n1).-Abril- octubre............. 40.53 VECES\n2).-Noviembre – marzo......... 20.27 VECES\nj).-Figuras de yeso, fijo:\n1).-Abril- octubre............. 47.77 VECES\n2).-Noviembre – marzo......... 31.85 VECES\nk).-Figuras de yeso y accesorios, semifijo:\n1).-Abril- octubre............. 31.85 VECES\n2).-Noviembre – marzo......... 15.92 VECES\nl).-Pinturas en caballete, fijo:\n1).-Abril- octubre............. 20.27 VECES\n2).-Noviembre – marzo......... 11.87 VECES\nm).-Cama elástica brinca-brinca (Por cama elástica), semifijo:\n1).-Abril- octubre............. 36.19 VECES\n2).-Noviembre – marzo......... 26.06 VECES\nn).-Futbolito, fijo:\n1).-Abril- octubre............. 21.71 VECES\n2).-Noviembre – marzo......... 14.33 VECES ñ).-Tiro al blanco, fijo:\n1).-Abril- octubre............. 18.82 VECES\n2).-Noviembre – marzo......... 15.92 VECES\no).-Cancha de Gotcha:\n1).-Abril- octubre............. 101.33 VECES\n2).-Noviembre – marzo......... 101.33 VECES\np).-Pista de autos de radio control:\n1).-Abril- octubre............. 37.64 VECES\n2).-Noviembre – marzo......... 37.64 VECES\nq).-Realización de juegos de globos y básquetbol, semifijo:\n1).-Abril- octubre............. 21.71 VECES\n2).-Noviembre – marzo......... 15.92 VECES\nr).-Cama elástica pequeña:\n1).-Abril- octubre............. 21.71 VECES\n2).-Noviembre – marzo......... 15.92 VECES\ns).-Tirolesa (3 torres):\n1).-Abril- octubre............. 78.17 VECES\n2).-Noviembre – marzo......... 46.32 VECES\nt).-Brincolín inflable:\n1).-Abril- octubre............. 24.61 VECES\n2).-Noviembre – marzo......... 20.27 VECES\nu).-Bolas Choconas\n1).-Abril- octubre............. 21.71 VECES\n2).-Noviembre – marzo......... 15.92 VECES\nJ).-Renta de espacios para venta de diversos productos.\na).-Fotografía, Semifijo:\n1).-Abril- octubre............. 39.08 VECES\n2).-Noviembre – marzo......... 26.06 VECES\nb).-Fotografía, ambulante:\n1).-Abril- octubre............. 36.19 VECES\n2).-Noviembre – marzo......... 18.82 VECES\nc).-Juegos de mesa, monos inflables, papalotes, máscaras de luchadores, marionetas, juguetes, semifijo:\n1).-Abril- octubre............. 44.88 VECES\n2).-Noviembre – marzo......... 30.40 VECES\nd).-Figuras de vidrio y curiosidades, fijo:\n1).-Abril- octubre............. 20.27 VECES\n2).-Noviembre – marzo......... 15.92 VECES\ne).-Flores individuales\n(2 vendedores), ambulante:\n1).-Abril- octubre............. 15.92 VECES\n2).-Noviembre – marzo......... 7.82 VECES\nf).-Música y artículos artesanales, semifijo:\n1).-Abril- octubre............. 13.61 VECES\n2).-Noviembre – marzo......... 6.77 VECES\ng).-Manzanas enchiladas y dulces, semifijo:\n1).-Abril- octubre............. 8.83 VECES\n2).-Noviembre – marzo......... 5.08 VECES\nh).-Manzanas enmieladas, ambulante:\n1).-Abril- octubre............. 13.75 VECES\n2).-Noviembre – marzo......... 10.86 VECES\ni).-Algodones de azúcar, ambulante:\n1).-Abril- octubre............. 30.40 VECES\n2).-Noviembre – marzo......... 20.27 VECES\nj).-Figuras de madera y centros de mesa, fijos:\n1).-Abril- octubre............. 46.32 VECES\n2).-Noviembre – marzo......... 31.85 VECES\nk).-Carros de golf para transporte de personas y mobiliario hasta\n10 carritos:\n1).-Abril- octubre............. 46.32 VECES\n2).-Noviembre – marzo......... 15.92 VECES\nl).-Venta de peces y souvenir, semifijo:\n1).-Abril- octubre............. 15.92 VECES\n2).-Noviembre – marzo......... 12.30 VECES\nm).-Venta de lentes, sombrillas y accesorios, semifijo:\n1).-Abril- octubre............. 15.92 VECES\n2).-Noviembre – marzo......... 12.30 VECES\nn).-Carritos para limpieza de vehículos:\n1).-Abril- octubre............. 12.45 VECES\n2).-Noviembre – marzo......... 7.70 VECES ñ).-Venta de soda, refrescos y agua embotellada:\n1).-Enero a Diciembre.......... 9.64 VECES\nII.-Parque LA AMISTAD\nA).-Estacionamiento público:\na).-Tarifa por día en horario diurno de 8:00 am 5:00 pm............... 0.30 VECES\nb).-Tarifa por día en horario nocturno de 5:01 pm a 7:59 am... 0.75 VECES\nc).-Credencial anual para deportistas...................... 5.24 VECES\nd).-Tarifa deportistas sin credencial de 6:00 am a 10:00 am y\n5:00 pm a 8:00 pm............... 0.09 VECES\ne).-Credencial anual para\nComerciantes..................... 0.52 VECES\nf).-Tarifa proporcional mensual credencial deportistas........... 0.37 VECES\ng).-Boleto perdido de estacionamiento.................. 0.67 VECES\nB).-Arrendamiento de espacios de recreación\na).-Kioscos día.................... 5.69 VECES\n1).-Cuota por limpieza......... 4.49 VECES\nb).-Palapas día................... 4.49 VECES\n1).-Cuota por limpieza......... 4.49 VECES\nc).-Áreas verdes para eventos familiares...................... 4.49 VECES\n1).-Cuota por limpieza......... 4.49 VECES\nd).-Renta estacionamiento Parque de la Amistad por evento............ 144.59 VECES\n1).-Cuota por limpieza......... 38.56 VECES\nC).-Uso y aprovechamiento de espacios.\na).-Tarifas para acampar por día en horario nocturno de 5:00 pm a 9:00\n1).-Adulto..................... 0.38 VECES\n2).-Infantil................... 0.23 VECES\nb).-Teatro al aire libre por hora.\nHorario diurno de 8:00 am a 5:00 pm(energía eléctrica incluida)... 3.89 VECES\n1).-Cuota por limpieza......... 4.49 VECES\nc).-Teatro al aire libre por hora.\nHorario nocturno de 5:01 pm a 2:00 am(energía eléctrica incluida).. 7.47 VECES\n1).-Cuota por limpieza......... 4.49 VECES\nPara los arrendamientos de estos espacios recreativos, se dará al usuario la opción de manejar el concepto de “DEPÓSITO EN\nGARANTÍA” por un monto de 4.13 UMAS, para entregar limpio el espacio rentado y pasar después de 5 días hábiles por su cheque de depósito en garantía, previa autorización del Subdirector\nAdministrativo del SIMPATT.\nd).-Tarifa por uso de toma eléctrica\n1).-Brincolín, equipo de sonido\n(El cobro es por bien)........... 2.24 VECES\n2).-Bocinas, mezcladora o tornamesa. (El cobro es por bien) 4.49 VECES\n3).-Tarifa concesionarios Parque de la Amistad:\nA).-Aparatos menores bajo consumo..................... 4.49 VECES\nB).-Aparatos mayores hasta dos equipos o electrodomésticos 7.47 VECES\ne).-Espacio para módulo 3 x 3 M².\n(espacio máximo)\n1).-Empresas (reclutamiento de personal)........................ 30.40 VECES\n2).-Publicidad (eventos, conciertos, activaciones)........ 30.40 VECES\n3).-Ventas (cambaceo o al detalle)........................ 30.40 VECES\n4).-Social(asociaciones civiles, escuelas o instituciones no gubernamentales).............. 5.24 VECES\nf).-Muelle de lanchas. Diurno para eventos menores, reuniones familiares y cumpleaños en horario de 8:00 a.m. a 5:00 p.m.......... 30.40 VECES\n1).-Cuota por limpieza......... 15.05 VECES\ng).-Muelle de lanchas. Nocturno para eventos menores, reuniones familiares y cumpleaños en horario de 5:01 p.m. a 2:00 a.m.......... 3 7.64 VECES\n1).-Cuota por limpieza......... 15.05 VECES\nD)Productos.\na).-Venta de Plantas (flor, arbusto, árbol):\n1).-Tarifa público general..... 0.23 VECES\n2).-Tarifa a negocios y empresarios..................... 0.30 VECES\nb).-Venta de plantas de ornato.... 0.54 VECES\nc).-Venta de plantas frutales..... 0.75 VECES\nd).-Venta de cerveza media........ 0.45 VECES\ne).-Venta de bebida sin alcohol.... 0.23 VECES\nf).-Descorche de botellas de bebidas con graduación alcohólica. 2.24 VECES\ng).-Comisión por venta de bebidas con graduación alcohólica. Por unidad vendida.................. 0.04 VECES\nh).-Comisión por venta de bebidas sin graduación alcohólica. Por unidad vendida.................. 0.03 VECES\ni).-Comisión por venta de bebidas preparadas con graduación alcohólica. Por unidad vendida... 0.06 VECES\nj).-Comisión por barril litros de cerveza.......................... 4.49 VECES\nE).-Clases y talleres:\na).-Taller de Hidroponía (5 sesiones)........................ 23.16 VECES\nF).-Renta de espacios para venta de alimentos preparados.\na).-Comida mexicana:\n1).-Abril - octubre........... 17.37 VECES\n2).-Noviembre - marzo.......... 14.91 VECES\nb).-Tacos al vapor (ambulante):\n1).-Abril - octubre........... 8.18 VECES\n2).-Noviembre - marzo.......... 7.12 VECES\nc).-Hot dog, hamburguesas, sodas y agua embotellada:\n1).-Abril - octubre........... 20.27 VECES\n2).-Noviembre - marzo.......... 15.92 VECES\nd).-Elotes y tostitos:\n1).-Abril - octubre........... 13.03 VECES\n2).-Noviembre - marzo.......... 9.70 VECES\ne).-Frituras fijo:\n1).-Abril - octubre........... 15.05 VECES\n2).-Noviembre - marzo.......... 11.29 VECES\nf).-Frituras ambulante:\n1).-Abril - octubre........... 15.92 VECES\n2).-Noviembre - marzo.......... 11.73 VECES\ng).-Dulces, frituras, jugos, ensaladas:\n1).-Abril - octubre........... 18.82 VECES\n2).-Noviembre - marzo.......... 14.77 VECES\nh).-Fruta picada y aguas frescas fijo:\n1).-Abril - octubre........... 18.82 VECES\n2).-Noviembre - marzo.......... 13.03 VECES\ni).-Fruta picada y aguas frescas(ambulante):\n1).-Abril - octubre........... 18.82 VECES\n2).-Noviembre - marzo.......... 13.03 VECES\nj).-Nieve frosty:\n1).-Abril - octubre........... 20.27 VECES\n2).-Noviembre - marzo.......... 15.92 VECES\nk).-Paletas de hielo ambulante, por carrito:\n1).-Abril - octubre........... 4.67 VECES\n2).-Noviembre - marzo.......... 3.91 VECES\nl).-Bolis bon ice ambulante (incluye\n2 ambulantes):\n1).-Abril - octubre........... 18.82 VECES\n2).-Noviembre - marzo.......... 7.70 VECES\nm).-Raspados fijo:\n1).-Abril - octubre........... 18.82 VECES\n2).-Noviembre - marzo.......... 10.71 VECES\nn).-Raspados ambulante por carreta:\n1).-Abril - octubre........... 4.70 VECES\n2).-Noviembre - marzo.......... 3.91 VECES ñ).-Tejuino ambulante:\n1).-Abril - octubre........... 15.92 VECES\n2).-Noviembre - marzo.......... 8.01 VECES\no).-Comida vegetariana:\n1).-Abril - octubre........... 23.16 VECES\n2).-Noviembre - marzo.......... 7.70 VECES\np).-Pizzas fijo:\n1).-Abril - octubre........... 69.48 VECES\n2).-Noviembre - marzo.......... 69.48 VECES\nq).-Comida saludable:\n1).-Abril - octubre........... 50.67 VECES\n2).-Noviembre - marzo.......... 50.67 VECES\nr).-Carreta de Dulces Ambulantes:\n1).-Abril - octubre........... 9.26 VECES\n2).-Noviembre - marzo.......... 5.24 VECES\nG).-Renta de espacio para juegos de diversión.\na).-Juegos mecánicos y extremos semifijo:\n1).-Abril - octubre........... 78.17 VECES\n2).-Noviembre - marzo.......... 78.17 VECES\nb).-Tren recreativo ambulante:\n1).-Abril - octubre........... 20.27 VECES\n2).-Noviembre - marzo.......... 12.02 VECES\nc).-Renta de lanchas de pedal:\n1).-Abril - octubre........... 224.38 VECES\n2).-Noviembre - marzo.......... 154.89 VECES\nd).-Pinturas en caballete y alcancías de yeso:\n1).-Abril - octubre........... 39.08 VECES\n2).-Noviembre - marzo.......... 24.61 VECES\ne).-Cuatriciclos ambulante:\n1).-Abril - octubre........... 20.27 VECES\n2).-Noviembre - marzo.......... 18.82 VECES\nf).-Burbujas de jabón y espuma:\n1).-Abril - octubre........... 8.67 VECES\n2).-Noviembre - marzo.......... 8.67 VECES\ng).-Escaladora semifijo:\n1).-Abril - octubre........... 28.95 VECES\n2).-Noviembre - marzo.......... 15.92 VECES\nh).-Cama elástica brinca brinca, (1 cama) semifijo:\n1).-Abril - octubre........... 31.85 VECES\n2).-Noviembre - marzo.......... 23.16 VECES\ni).-Tiro al blanco fijo:\n1).-Abril - octubre........... 15.92 VECES\n2).-Noviembre - marzo.......... 7.70 VECES\nj).-Pista de autos de radio control:\n1).-Abril - octubre........... 37.64 VECES\n2).-Noviembre - marzo.......... 36.77 VECES\nk).-Brincolin Inflable:\n1).-Abril - octubre........... 23.16 VECES\n2).-Noviembre - marzo.......... 13.90 VECES\nl).-Fútbolito:\n1).-Abril - octubre........... 15.92 VECES\n2).-Noviembre - marzo.......... 7.70 VECES\nH).-Renta de espacios para venta de diversos productos.\na).-Fotografía ambulante:\n1).-Abril - octubre........... 20.27 VECES\n2).-Noviembre - marzo.......... 9.84 VECES\nb).-Golosinas fijo:\n1).-Abril - octubre........... 11.90 VECES\n2).-Noviembre - marzo.......... 10.71 VECES\nc).-Juegos de mesa, monos inflables, papalotes, máscaras de luchadores, marionetas, juguetes semifijo:\n1).-Abril - octubre........... 13.75 VECES\n2).-Noviembre - marzo.......... 10.86 VECES\nd).-Algodones de azúcar ambulante:\n1).-Abril - octubre........... 13.61 VECES\n2).-Noviembre - marzo.......... 12.16 VECES\ne).-Flores individuales ambulante:\n1).-Abril - octubre........... 8.83 VECES\n2).-Noviembre - marzo.......... 5.08 VECES\nf).-Música y artículos artesanales semifijo:\n1).-Abril - octubre........... 9.70 VECES\n2).-Noviembre - marzo.......... 6.17 VECES\ng).-Manzanas enmieladas ambulante:\n1).-Abril - octubre........... 11.73 VECES\n2).-Noviembre - marzo.......... 10.71 VECES\nh).-Globos ambulante:\n1).-Abril - octubre........... 20.27 VECES\n2).-Noviembre - marzo.......... 10.86 VECES\ni).-Figuras de madera y centros de mesa fijos:\n1).-Abril - octubre........... 23.16 VECES\n2).-Noviembre - marzo.......... 15.92 VECES\nj).-Vendedor ambulante, previa autorización de SIMPATT, tarifa por día.......................... 3.85 VECES\nIII.-Pista de hielo\n1).-Boleto para pista de hielo......... 1.13 VECES\nNotas adicionales:\n1).- Tendrá un descuento del 50% (cincuenta por ciento) para personas que cuenten con credencial de INAPAM solo en kioscos.\n2).-El horario de entrada en los parques JOSÉ MARÍA MORELOS Y PAVÓN y DE LA AMISTAD con credencial de corredores es libre.\n3).-Las personas que tomen clases de zumba, los pentatletas y scouts, podrán adquirir una credencial anual de estacionamiento con la misma tarifa que la de corredores que son 2.99 UMAS para\nPAVÓN y DE LA AMISTAD.\n4).-Corredores y ciclistas sin credencial pagarán una tarifa de\n0.06 UMAS.\n5).-Será aplicable un descuento del 50% (cincuenta por ciento) en la renta de todas las áreas para: empleados de gobierno municipal, ejército, policía, bomberos, grupos de rescate y casas hogar solicitándolo por escrito a la Dirección del SIMPATT.\n6).- La renta de todas las áreas para empleados de SIMPATT serán sin costo para eventos menores a un máximo de tres eventos por año, de acuerdo a disponibilidad y con un 50% (cincuenta por ciento) para eventos nocturnos solicitándolo por escrito a la\nDirección del SIMPATT.\n7).-Deberá de considerarse 50% (cincuenta por ciento) de descuento en el trámite de credenciales para los deportistas de la tercera edad o jubilados.\n8).-En los casos de arrendamientos de espacios para venta de alimentos preparados, renta de espacios para juegos de diversión y renta de espacios para venta de diversos productos, que se describen en el parque MORELOS Y PAVON en sus incisos H), I) y J) así como en el parque DE LA AMISTAD, en sus incisos F), G) y H), la cantidad que se establece en los periodos que marca la presente\nLey, se considerará como pago de renta mensual.\n9).-Será aplicable a los arrendatarios de los parques temáticos\n1.06 UMAS mensuales.\n10).-Tendrá descuento del 25% (veinticinco por ciento) para viernes, solo en lanchas y pistas de hielo\n11).-Los comerciantes que cuenten con un contrato vigente de arrendamiento en cualquiera de los dos parques, deberán contar con identificación para el titular y empleado, misma que será expedida por el SIMPATT con un costo 0.48 UMAS cada una.\n12).-La renta de los estacionamientos en los parques JOSÉ MARÍA\nMORELOS Y PAVÓN y DE LA AMISTAD para la realización de eventos, la solicitados, conforme a las tarifas establecidas en la fracción I, inciso A), a) y b), y fracción II, inciso A), a) y b), en el caso nocturno, el cobro se realizará en base a la suma de ambas tarifas.\nCAPÍTULO VIII\nQUE PRESTA EL INSTITUTO MUNICIPAL CONTRA LAS ADICCIONES\nARTÍCULO 54.-Los servicios que presta el Instituto Municipal contra las Adicciones, se cobrarán conforme a lo siguiente:\nTARIFA\nUNIDAD DE MEDIDA Y\nACTUALIZACIÓN.\nA).-Por evaluación para medir el nivel de consumo\na).-Entrevista de evaluación............. 0.96 VECES\nB).-Terapias psicológicas\na).-Terapia Psicológica individual (50 minutos por sesión)................... 0.96 VECES\nb).-Terapia Psicológica familiar (90 minutos por sesión)................... 1.45 VECES\nc).-Terapia Psicológica grupal (por sesión, por persona).................. 0.96 VECES\nC).-Por impartición de talleres psicoeducativos\na).-Talleres psicoeducativos para adultos mayores y adolescentes.................. 0.96 VECES\nD).-Capacitación por sesión por persona...... 2.89 VECES\nE).-Por impartición de pláticas preventivas en el sector privado (por persona)........ 0.48 VECES\nF).-Cuotas a internos con más de 6 meses en rehabilitación, por semana............. 2.89 VECES ser exentas de pago las tarifas anteriores, previo estudio\nContra las Adicciones, que así lo indique.\nCAPÍTULO IX\nQUE PRESTA EL FIDEICOMISO PROMOTORA MUNICIPAL DE TIJUANA\nARTICULO 54 BIS.-Los servicios que presta el Fideicomiso Promotora\nMunicipal de Tijuana, se cobrarán conforme a lo siguiente:\nTARIFA\nUNIDAD DE MEDIDA Y\nACTUALIZACIÓN.\nA).-Expedición de documentos:\na).-Carta finiquito.................... 5.79 VECES\nb).-Título de Propiedad................ 28.92 VECES\nc).-Cesiones de derechos............... 57.84 VECES\nd).-Integración de expedientes para contratación del contrato de compraventa de bien inmueble......... 14.46 VECES\nB).-Por trabajos técnicos:\na).-Inspecciones técnicas para habitantes de los fraccionamientos administrados por el mismo\nFideicomiso.......................... 14.46 VECES\nCAPÍTULO X\nARTÍCULO 55.-Los servicios que presta el Comité de Turismo y\nConvenciones de Tijuana, se cobrarán conforme a lo siguiente:\nTARIFA\nUNIDAD DE MEDIDA Y ACTUALIZACIÓN.\nA).-Precio por boleto para evento al \"Mérito\nTurístico\":\na)Desayuno.............................. 12.43 VECES\nb)Comida................................ 13.82 VECES\nc)Cena.................................. 16.58 VECES\nB).-Derecho por promoción dentro de Guías de\nTurismo para Reuniones:\n1)En Contraportada..................... 119.74 VECES\n2)En Portada interior.................. 69.08 VECES\n3)En Contraportada interior............ 69.08 VECES\n4)En Página interior................... 32.24 VECES\nC.-Derecho por promoción dentro de “Mapa\nTurístico de la Ciudad”:\n1)Medidas 8\" de alto 4.5\" de ancho...... 165.79 VECES\n2)Medidas 4\" de alto por 4\" de ancho.... 64.47 VECES\nD).-Derecho por promoción dentro de “Guía\nTurística de la Ciudad\":\n1)En Contraportada..................... 156.58 VECES\n2)En Portada interior.................. 110.53 VECES\n3)En Contraportada interior............ 156.58 VECES\n4)En Página interior................... 64.47 VECES\nE).-Tótem publicitario QR........ De 32.24 a 41.45 VECES\nF).-Espacio publicitario \"Caja de luz publicitaria en Modulo de\nInformación Turística MIT De 156.58 a 211.84 VECES\nRevolución\"..................\nG).-Ingresos por subsidios, aportaciones, subvenciones y donativos y Municipal y sus entidades paraestatales o paramunicipales, así como de organizaciones civiles, cámaras, personas físicas fiscales.\nH).-Espacio publicitarios en revista en formato impreso y digital:\nRevista Formato Impreso\nPortada................................. 414.48 VECES\nPortada interior........................ 322.37 VECES\nContraportada........................... 368.43 VECES\nContraportada interior.................. 276.32 VECES\nArtículo comercial informativo interior. 142.77 VECES\nPlana publicitaria completa............. 138.16 VECES\nMedia plana............................. 73.69 VECES\n1/4 de plana............................ 46.05 VECES\nPestaña interior........................ 32.24 VECES\nPestaña Superior........................ 30.40 VECES\nPestaña Inferior........................ 27.63 VECES\nDirectorio negocios según cluster al mes solo nombre y numero.................... 23.03 VECES\nSección las recomendaciones cotuco del mes\nRecomendación medica.................... 46.05 VECES\nRecomendación gastronómica.............. 46.05 VECES\nRecomendación Hotelera.................. 69.08 VECES\nRecomendación deportiva................. 73.69 VECES\nRecomendación turismo de aventura....... 73.69 VECES\nRecomendación tour operadores........... 55.26 VECES\nDirectorio plus con imagen logo nombre y numero.................................. 59.87 VECES\nSección los tops 5 cotuco del mes\nTop medico.............................. 92.11 VECES\nTop gastronómico........................ 92.11 VECES\nTop deportivo........................... 138.16 VECES\nTop aventura............................ 116.13 VECES\nTop atractivos turísticos............... 96.71 VECES\nRevista Formato Digital\nPortada................................. 276.32 VECES\nPortada interior........................ 138.16 VECES\nContraportada........................... 230.27 VECES\nContraportada interior.................. 124.34 VECES\nArtículo comercial informativo interior. 101.32 VECES\nPlana publicitaria completa............. 92.11 VECES\nMedia plana............................. 55.26 VECES\n1/4 de plana............................ 32.24 VECES\nPestaña interior........................ 23.03 VECES\nPestaña Superior........................ 20.26 VECES\nPestaña Inferior........................ 18.42 VECES\nDirectorio negocios según cluster al mes solo nombre y numero.................... 13.82 VECES\nSección las recomendaciones cotuco del mes\nRecomendación medica.................... 27.63 VECES\nRecomendación gastronómica.............. 27.63 VECES\nRecomendación Hotelera.................. 41.45 VECES\nRecomendación deportiva................. 41.45 VECES\nRecomendación turismo de aventura....... 41.45 VECES\nRecomendación tour operadores........... 32.24 VECES\nDirectorio plus con imagen logo nombre y numero.................................. 32.24 VECES\nSección los tops 5 cotuco del mes\nTop medico.............................. 55.26 VECES\nTop gastronómico........................ 55.26 VECES\nTop deportivo........................... 73.69 VECES\nTop aventura............................ 73.69 VECES\nTop atractivos turísticos............... 73.69 VECES\nLink para enlazar a página web externa\n(por link).............................. 23.03 VECES\nCAPÍTULO XI\nARTÍCULO 56.-Los servicios que presente el Organismo Municipal\nPasajeros de Tijuana se cobrará conforme a lo siguiente:\nA).-Por peaje..................................... 0.19 VECES\nB).-Por espacio publicitario en paradero al mes.... 2.67 VECES\nC).-Por espacio publicitario en estaciones al mes.. 6.00 VECES\nD).-Ingresos por beneficio del 6% sobre el total de los recursos provenientes del recaudo de la tarifa, del sistema de control de acceso a estaciones por medio de torniquetes y; el sistema tecnológico de gestión de flota en el servicio público de transporte en el subsistema 1 del servicio público masivo de pasajeros en el Municipio de Tijuana.\nE).-Ingresos por comisiones de las ventas generadas derivadas del de máquinas expendedoras.\nF).-Ingresos recaudados por contratos o convenios de asociación en morales legalmente constituidas.\nG).-Por otros ingresos derivados de la operación del transporte alimentadoras.\nCAPÍTULO XII\nORGANISMOS DESCENTRALIZADOS, PARAMUNICIPALES Y/O FIDEICOMISOS\nARTÍCULO 57.-Los rendimientos producidos por organismos descentralizados y/o paramunicipales, se percibirán cuando lo decreten y se exhiban, conforme a sus respectivos regímenes interiores.\nTÍTULO QUINTO\nPRODUCTOS\nCAPÍTULO I\nCONTRAPRESTACIONES DE CONCESIONES, EXPLOTACIÓN O ARRENDAMIENTO\nDE BIENES MUEBLES E INMUEBLES PROPIEDAD DEL GOBIERNO MUNICIPAL\nARTÍCULO 58.-La renta de los puestos interiores o exteriores de mercados, será fijada acorde a lo siguiente:\nUNIDAD DE MEDIDA Y\nACTUALIZACIÓN (UMA) VIGENTE\nA).-Los puestos interiores pagarán mensualmente por M²...................... 0.90 VECES\nB).-Los puestos exteriores pagarán mensualmente por M²...................... 1.10 VECES\nCAPÍTULO II\nARTÍCULO 59.-El suministro de formas impresas tales como oficinas municipales, se pagarán por forma impresa, en la caja recaudadora de la Tesorería Municipal............ 0.125 VECES\nCAPÍTULO III\nOTRAS ACTIVIDADES DEL GOBIERNO MUNICIPAL, QUE NO CORRESPONDAN A\nSUS FUNCIONES PROPIAS DE DERECHO PÚBLICO\nARTÍCULO 60.-Por concepto de producto por la explotación de bienes, derechos y/o actividades que realice el Ayuntamiento cuando no público.\nUNIDAD DE MEDIDA Y\nACTUALIZACIÓN (UMA) VIGENTE\nI.-Las rentas que produzcan los bienes propiedad del\nMunicipio que sean susceptibles de ser arrendados se pagarán en base a los contratos de arrendamientos que se celebren con cada uno de los inquilinos y el Ayuntamiento, cubriéndose el importe de la renta mensual los primeros cinco días hábiles del mes correspondiente.\nII.-Uso de Diseño Industrial \"Arco\nMonumental\", anual.................... 16,250.00 VECES\nIII.-Trámite para la expedición de pasaportes en vinculación con la\nDelegación de la Secretaría de\nRelaciones Exteriores................ 4.80 VECES\nIV.-Cuota de recuperación por el uso de las instalaciones del Centro Mutualista para Policías y Bomberos, destinadas para el mantenimiento del mismo centro, conforme a las siguientes:\nA) Salón con capacidad de 500 personas...................... 26.00 VECES\nB) Salón con capacidad de 150 personas....................... 16.00 VECES\nC) El uso de los salones para eventos institucionales del Ayuntamiento, no les serán aplicables el pago de cuotas de recuperación, para su uso, requerirán y Protección Ciudadana Municipal, quien verificará viabilidad y disponibilidad del espacio.\nARTÍCULO 61.-Los productos no pagados en el ejercicio fiscal en que se causaron, se cobrarán como rezago de ejercicios fiscales anteriores, aplicado en cuanto al fondo, las leyes vigentes a la fecha en que se generaron y en cuanto a la forma, mediante el procedimiento administrativo de ejecución que establece la Ley de\nHacienda Municipal del Estado de Baja California o en su caso, el procedimiento judicial que corresponda.\nCAPÍTULO IV\nDEL PISO\nARTÍCULO 62.-Las personas físicas o morales que previa autorización de la autoridad municipal correspondiente hagan uso del piso, de instalaciones subterráneas o áreas en las vías prestación de servicios en forma permanente o temporal, pagarán los productos correspondientes conforme a la siguiente:\nTARIFA\nUNIDAD DE MEDIDA Y\nACTUALIZACIÓN (UMA) VIGENTE\nI.-Casetas telefónicas, diariamente, por cada una; debiendo realizar el pago anualizado dentro de los primeros 60 días del ejercicio fiscal. 12.50 VECES\nII.-Instalaciones de infraestructura, por metro lineal, anualmente:\nA).-Redes subterráneas de:\na).-Telefonía........................... 0.019 VECES\nb).-Transmisión de datos................ 0.019 VECES\nc).-Transmisión de señales de televisión por cable............................... 0.019 VECES\nd).-distribución de gas................. 0.019 VECES\ne).-Energía eléctrica, siempre y cuando las instalaciones se usufructúen........ 0.019 VECES\nB).- Redes visibles de:\na).-Telefonía........................... 0.038 VECES\nb).-Transmisión de datos................ 0.038 VECES\nc).-Transmisión de señales de televisión por cable............................... 0.038 VECES\nd).-Energía eléctrica, siempre y cuando las instalaciones se usufructúen........ 0.038 VECES\nTÍTULO SEXTO\nAPROVECHAMIENTOS\nCAPÍTULO I\nRECARGOS\nARTÍCULO 63.-La tasa de recargos en caso de prórroga será del 1.50%\n(uno punto cincuenta por ciento) mensual, y será incrementada a un\n2% (dos por ciento) tratándose de mora. Los recargos se causarán hasta por 5 años.\nCAPÍTULO II\nREZAGOS DE EJERCICIOS FISCALES ANTERIORES\nARTÍCULO 64.-Los aprovechamientos no pagados en el ejercicio fiscal en que se causaron, se cobrarán como rezago de ejercicios fiscales anteriores, aplicado en cuanto al fondo, las leyes vigentes a la fecha en que se generaron y en cuanto a la forma, California o en su caso, el procedimiento judicial que corresponda.\nCAPÍTULO III\nGASTOS DE EJECUCIÓN\nARTICULO 65.-Los gastos de ejecución se cobrarán a quien se le requiera por haber incurrido en incumplimiento de obligaciones fiscales no satisfechas dentro de los plazos legales, una vez la Ley de Hacienda Municipal del Estado de Baja California. menores de 2.00 veces la UMA vigente, ni excederán de 500.00 veces intervengan. Los gastos por impresiones, publicaciones y cualquier otra erogación que, con el carácter de extraordinaria; sea necesaria para el éxito del procedimiento de ejecución, se liquidarán por separado.\nCAPÍTULO IV\nMULTAS\nARTÍCULO 66.-Las que se contemplan en los reglamentos municipales fiscales, asimismo la autoridad municipal, al hacer efectiva la sanción impuesta por las diversas dependencias municipales, por violaciones a los reglamentos emitidos por el Ayuntamiento, y al\nArtículo 88 de la Ley de Hacienda Municipal del Estado de Baja\nCalifornia.\nCAPÍTULO V\nREINTEGROS E INDEMNIZACIONES\nCAPÍTULO VI\nDONACIONES, CESIONES, HERENCIAS, LEGADOS Y OTROS A FAVOR DEL\nORGANISMOS DESCENTRALIZADOS PARAMUNICIPALES, ORGANISMOS DE\nPARTICIPACIÓN MUNICIPAL, EMPRESAS MUNICIPALES, EMPRESAS PUBLICOPRIVADAS Y FIDEICOMISOS PÚBLICOS MUNICIPALES.\nARTÍCULO 66 BIS.- Las cantidades que por concepto de donativo e indemnizaciones perciba el Municipio, se sujetarán a las convenios, contratos, normas o resoluciones relativas. Los ingresos por este concepto deberán destinarse al gasto público.\nCAPÍTULO VII\nPOR EL OTORGAMIENTO Y USUFRUCTO DE DERECHOS, PERMISOS,\nLICENCIAS, AUTORIZACIONES Y/O CONCESIONES EMITIDAS POR EL\nAYUNTAMIENTO A FAVOR DE PARTICULARES, CUYA EXPLOTACIÓN AL\nPÚBLICO SE REALICE POR TERCEROS. establecido por revalidación del derecho, permiso, licencia y/o concesión, que corresponda a la misma actividad dentro de la presente Ley de Ingresos y dentro del mismo plazo.\nCAPÍTULO VIII\nRECUPERACIÓN PARCIAL DE PRIMAS DE SEGUROS DE VIDA\nCAPÍTULO IX\nCAUCIONES, FIANZAS Y DEPÓSITOS CUYA PÉRDIDA SE DECLARE POR\nRESOLUCIÓN FIRME\nCAPÍTULO X\nINGRESOS POR VENTA DE BIENES PATRIMONIALES\nTITULO SÉPTIMO\nPARTICIPACIONES, APORTACIONES, CONVENIOS, INCENTIVOS DERIVADOS\nCAPÍTULO I\nPARTICIPACIONES FEDERALES\nI.- Por ingresos que reciben las Entidades Federativas y\nCoordinación Fiscal, determinados por las leyes.\nCAPÍTULO II\nPARTICIPACIONES ESTATALES\nI.- Por los ingresos que reciben los Municipios que se derivan del sistema estatal de coordinación fiscal, determinados por las leyes correspondientes.\nCAPÍTULO III\nAPORTACIONES FEDERALES DE LA LEY DE COORDINACIÓN FISCAL.\nI.-Fondo de Aportaciones para la Infraestructura Social Municipal.\nII.- Fondo de Aportaciones para el Fortalecimiento de los\nMunicipios.\nIII.-Otras.\nCAPÍTULO IV\nAPORTACIONES ESTATALES\nI.-Por Otros Impuestos o Ingresos del Estado, que señalen las\nLeyes, Acuerdos, Fideicomisos y Convenios que las regulen, que reciba el Municipio y sus Entidades Auxiliares Municipales, como lo son Organismos Descentralizados Paramunicipales, Organismos de\nParticipación Municipal, Empresas Municipales, Empresas PúblicoPrivadas y Fideicomisos Públicos Municipales.\nCAPÍTULO V\nCAPÍTULO VI\nCONVENIOS\nI.- Son los ingresos que reciben los Municipios derivados de convenios de coordinación, colaboración, reasignación o descentralización según corresponda, los cuales se acuerdan entre la Federación, las Entidades Federativas y/o los Municipios.\nCAPÍTULO VII\nINCENTIVOS DERIVADOS DE LA COLABORACIÓN FISCAL\nI.-Son los ingresos que reciben los Municipios derivados del ejercicio de facultades delegadas por la Federación mediante la celebración de convenios de colaboración administrativa en materia fiscal; que comprenden las funciones de recaudación, fiscalización y administración de ingresos federales.\nCAPÍTULO VIII\nFONDOS DISTINTOS DE APORTACIONES\nSon los ingresos que reciben los Municipios del Estado, derivados específicas, tales como el Fondo para Entidades Federativas y\nMunicipios Productores de Hidrocarburos, y Fondo para el\nDesarrollo Regional Sustentable de Estados y Municipios Mineros, entre otros. fomentar su política económica, fortalecer la hacienda pública programas públicos destinados al bienestar de la comunidad.\nTÍTULO OCTAVO\nTRANSFERENCIAS, ASIGNACIONES, SUBSIDIOS Y SUBVENCIONES, Y\nPENSIONES Y JUBILACIONES\nCAPÍTULO I\nOTORGUE EL GOBIERNO FEDERAL\nCAPÍTULO II\nEXTRAORDINARIOS U OTROS SUBSIDIOS\nTÍTULO NOVENO\nINGRESOS DERIVADOS DE FINANCIAMIENTOS\nCAPÍTULO I\nCRÉDITOS OTORGADOS AL MUNICIPIO\nCAPÍTULO II\nOTROS\nTÍTULO DECIMO\nDISPOSICIONES GENERALES\nCAPÍTULO ÚNICO\nARTÍCULO 67.-Los impuestos, derechos, productos y aprovechamientos no pagados en el ejercicio fiscal en que se causaron, se cobrarán pendientes de liquidación o pago, aplicando en cuanto al fondo, forma, mediante el Procedimiento Administrativo de Ejecución que\nCalifornia o en su caso, el Procedimiento Judicial que corresponda.\nARTÍCULO 68.-Las participaciones en impuestos federales y estatales que perciba el Municipio, serán las que fijen las leyes, convenios y acuerdos federales y estatales respectivos.\nARTÍCULO 69.-La validez de los permisos y autorizaciones otorgados por el Municipio, están condicionados al exacto cumplimiento de los ordenamientos legales.\nARTÍCULO 70.-Los gravámenes que prevé la presente Ley, no serán motivo de exención, condonación o modificación por parte de las autoridades municipales, salvo por lo dispuesto en el Reglamento para el Fomento a la Competitividad y Desarrollo Económico del\nMunicipio de Tijuana, Baja California, en lo relativo al Impuesto\nPredial y al Impuesto Sobre Adquisición de Inmuebles; o por autorización expresa del Congreso del Estado, con excepción de los recargos, que podrán condonarse total o parcialmente, conforme al artículo 110 de la Ley de Hacienda Municipal del Estado de Baja\nCalifornia.\nARTÍCULO 71.-Se entiende como fecha de iniciación de operaciones de las personas físicas y de las unidades económicas, aquéllas en que se efectúe la apertura del negocio o en la que se obtenga el primer ingreso. En el caso de personas morales el día de su constitución, aun cuando sea anterior a la fecha de apertura del negocio o a la fecha en que se obtenga el primer ingreso.\nARTÍCULO 72.-Las personas físicas, morales o unidades económicas ambulantes, agentes de ventas, comisionistas, repartidores, concesionarios o cualquier otro nombre que se le dé al expendedor, serán solidariamente responsables del pago de los impuestos, que ejerzan, para lo cual se constituirán en los retenedores de\nRentas Municipales, dentro de los plazos que fijan las Leyes\nFiscales.\nARTÍCULO 73.-Los gravámenes fiscales se pagarán con base a la\nUnidad de Medida y Actualización (UMA) vigente, al momento de la y al momento de realizarse el hecho o la situación jurídica, en el caso de impuestos.\nARTÍCULO 74.-Para efectos de esta ley se considerarán:\nVivienda de Interés Social: Aquella que consista en el suelo y las construcciones adheridas a él y cuyo valor, determinado mediante avalúo bancario o perito valuador, con antigüedad máxima de seis meses, no exceda de la suma que resulte de multiplicar por quince la Unidad de Medida y Actualización (UMA) elevado al año, vigente.\nVivienda Popular: Aquella que consista en el suelo y las construcciones adheridas a él y cuyo valor, determinado mediante avalúo bancario o perito valuador, con antigüedad máxima de seis meses, no exceda de la suma que resulte de multiplicar por veinticinco la Unidad de Medida y Actualización (UMA) elevado al año, vigente.\nVivienda de Nivel Medio: Aquella que consista en el suelo y las construcciones adheridas a él y cuyo valor, determinado mediante avalúo bancario o perito valuador, con antigüedad máxima de seis meses, no exceda de la suma que resulte de multiplicar por treinta la Unidad de Medida y Actualización (UMA) elevado al año, vigente.\nVivienda de Nivel Residencial: Aquella que consista en el suelo y las construcciones adheridas a él y cuyo valor, determinado mediante avalúo bancario o perito valuador, con antigüedad máxima de seis meses, no exceda de la suma que resulte de multiplicar por treinta la Unidad de Medida y Actualización (UMA) elevado al año, vigente.\nARTÍCULO 75.-El cheque recibido por las autoridades fiscales municipales que sea presentado en tiempo y no sea pagado, dará siempre del 20% del valor de éste, y se exigirá independientemente de los demás conceptos a que se refiere este artículo. Para tal efecto, la Recaudación de Rentas Municipal requerirá al librador del cheque para que, dentro de un plazo de tres días, efectúe el pago junto con la mencionada indemnización del 20% o bien, acredite fehacientemente, con las pruebas documentales procedentes, que se exclusivamente imputables a la institución de crédito. demuestre cualquiera de los extremos antes señalados, la autoridad fiscal municipal requerirá y cobrará el monto del cheque, la indemnización mencionada y los demás accesorios que correspondan, mediante el Procedimiento Administrativo de Ejecución, sin perjuicio de la responsabilidad que en su caso procediere.\nTRANSITORIOS\nARTÍCULO PRIMERO.-Las contribuciones cuyo cobro haya quedado suspendido con base a los acuerdos celebrados con el Gobierno\nFederal y las Leyes Fiscales de la Federación, en caso de reformas o modificaciones a estas disposiciones, que permitan el cobro de dichas contribuciones, se cobrará por este ejercicio la tasa que fija la Ley de Ingresos vigente en la fecha en que se haya incurrido la suspensión de cada contribución.\nARTÍCULO SEGUNDO.-Con relación al cobro de los derechos por los servicios que preste la Dirección de Catastro, contemplados en la presente Ley, se estará a lo dispuesto en el Convenio que en materia de Catastro y Control Urbano, celebraron el Gobierno\nConstitucional del Estado de Baja California y el Ayuntamiento de\nTijuana, Baja California.\nARTÍCULO TERCERO.-En caso de que durante el presente ejercicio fiscal las dependencias a que se refiere esta Ley, sufrieran alguna modificación en sus funciones o cambiaran su denominación, los servicios previstos para ser prestados por dichas dependencias, se entenderán referidos y prestados por las que las sustituyan, dando lugar al pago de los derechos que señala ésta.\nARTÍCULO CUARTO.-Tratándose de ciudadanos que emigren del interior\nRegistro Civil, previa solicitud y en su caso, estudio socioeconómico.\nARTÍCULO QUINTO.-El 5% (cinco por ciento) relativo al impuesto establecido en el Artículo 16 de la presente Ley, se destinará a contratación de personas con discapacidad por parte del H.\nAyuntamiento de Tijuana, Baja California, y que se controle en partida presupuestal exclusiva para ello.\nARTÍCULO SEXTO.-La autorización expresa del Congreso del Estado para la exención, condonación o modificación de gravámenes que prevé el Artículo 70 de la presente ley, se realizará mediante iniciativa de decreto que presente el Ayuntamiento de Tijuana, Baja California, ante el Órgano Legislativo Estatal, en los\nSoberano de Baja California.\nARTÍCULO SÉPTIMO.-Tratándose de personas con discapacidad, se deberá destinar a su favor un 20% (veinte por ciento) anual del total de los recursos recaudados por concepto de pago de derechos de horas extras que ingresan al Ayuntamiento, recurso que deberá ser entregado, administrado y ejercido por el Sistema Integral de la Familia.\nARTÍCULO OCTAVO.- La recaudación del “PROGRAMA DE CRUCE ÁGIL A\nUSUARIOS DE SERVICIOS MÉDICOS TURISMO DE NEGOCIOS Y ESTUDIANTES\nTRANSFRONTERIZOS PROCEDENTES DE Y CON DESTINO A LOS ESTADOS UNIDOS\nDE AMÉRICA” previsto en el Artículo 39 de la presente Ley de\nIngresos, correspondiente a los meses de enero a marzo se destinará el 100% (cien por ciento)a la Secretaría de Desarrollo Económico\nFIDEICOMISO FONDOS TIJUANA. Corresponde a la Secretaría DE para el ejercicio del gasto durante el presente ejercicio fiscal, el cual se destinará para la infraestructura física, tecnológica, mantenimiento, operación, equipamiento, rehabilitación, mejoras y estratégicos.\nARTÍCULO NOVENO.-Los impuestos adicionales al Fomento Deportivo y\nEducacional, y el de Fomento Turístico, Desarrollo Integral de la\nFamilia y Promoción de la Cultura, que se hayan causado en ejercicios anteriores al 2022, se deberán pagar conforme a la los mismos. De la misma forma se deberán pagar las Sobre Tasas en apoyo al Fomento Deportivo y Educacional, como las Sobre Tasas en apoyo al Fomento Turístico, Desarrollo Integral de la Familia y\nPromoción de la Cultura, que se hayan causado en ejercicios anteriores al 2022 y anteriores correspondiente al impuesto predial.\nARTÍCULO DÉCIMO.-En caso que alguna de las dependencias a que se refiere la presente Ley, sufriera alguna modificación o cambiara su denominación, los servicios previstos por dicha dependencia, se entenderán referidos y prestados por la que la sustituya.\nARTÍCULO DÉCIMO PRIMERO.-La presente ley entrará en vigor el día primero de enero del año dos mil veinticinco.\nARTÍCULO DÉCIMO SEGUNDO.-Cuando las actividades o eventos que se lleven a cabo en espacios del Ayuntamiento de su Administración\nCentral o Paramunicipal sean organizados por algún área del propio\nAyuntamiento, estarán exentas de pagar las contribuciones correspondientes al uso de instalaciones establecidas en esta ley.\nARTÍCULO DÉCIMO TERCERO.-Previa revisión, análisis y anuencia de la Recaudación de Rentas Municipal, podrá la Tesorería Municipal, contribuyentes, que obren en los estados de cuenta y registros de la dependencia, contra el pago de los adeudos fiscales Municipales, años antes o más, de la fecha en que se realice la compensación indicada, y se les haya dado aviso del saldo a favor por parte de la Autoridad Fiscal.\nARTÍCULO DÉCIMO CUARTO.-Se autoriza la recepción de pagos parciales respecto del impuesto predial, previa autorización de la\nTesorería Municipal, sin que por ello se consideren modificados sus accesorios, ni las consecuencias por pagos extemporáneo.\nARTÍCULO DÉCIMO QUINTO.-Los establecimientos con permiso de operación de abarrotes, mercados, fondas o loncherías, tributaran con tasa “0” cero en lo que respecta a la contribución establecida en el Capítulo VII del Título VI de esta Ley, debiendo cumplir con el trámite de declaración correspondiente.\nARTÍCULO DÉCIMO SEXTO.- Se exenta a las personas físicas y morales inscritas en el Programa Estatal de Vivienda 2022-2027, del pago de derechos que se causen por; factibilidades, dictámenes, certificados, autorizaciones, licencias y en general, por trámites relacionados con la construcción de vivienda social, exclusivamente para los proyectos habitacionales que cuenten con certificado expedido por el Titular de la Secretaría de\nInfraestructura, Desarrollo Urbano y Reordenación Territorial\n(SIDURT), y se lleven a cabo en términos de los Lineamientos\nGeneral para la Inscripción en el Programa Estatal de Vivienda publicado en el Periódico Oficial del Estado en fecha 21 de octubre de 2022 y actualizaciones posteriores, así como del Programa de\nVivienda para el Bienestar impulsado por la Federación a través de la Secretaría de Desarrollo Agrario, Territorial y Urbano\n(SEDATU), Instituto Nacional del Suelo Sustentable (INSUS), Comisión Nacional de Vivienda (CONAVI), Instituto del Fondo\nNacional de la Vivienda para los Trabajadores (INFONAVIT), del Estado (ISSSTE) y el Fondo de la Vivienda del Instituto de\n(FOVISSSTE), en conjunto con la Entidad Federativa y sus\nMunicipios.\nLos derechos a exentar se enuncian a continuación:\n1. Factibilidad de uso del suelo\n2. Certificado de libertad de gravamen\n3. Dictamen de uso del suelo\n4. Manifestación de impacto ambiental\n5. Movimiento de tierras\n6. Deslinde catastral\n7. Licencia de construcción\n8. Régimen de Propiedad en Condominio\n9. Licencia de Fraccionamiento\n10. Certificado de numero oficial\n11. Constancia de obra terminada\n12. Cambio de propietario\n13. Impuesto sobre adquisición de bienes inmuebles\nArtículo Transitorio Adicionado\nArtículo Transitorio Reformado\nARTÍCULO DÉCIMO SÉPTIMO.- Se exenta a las personas físicas y morales que se acrediten de manera fehaciente a juicio de la\nSecretaría de Gobierno Municipal estar inscritas en el Programa de identificación, empadronamiento y regularización de la situación jurídica y administrativa de las personas físicas o morales que se dediquen a la expedición y venta, en envase cerrado y abierto, de bebidas con contenido alcohólico, autorizado por el H. Cabildo de\nTijuana en sesión del 11 de diciembre de 2024, hasta un 80% del pago de los derechos a que se refieren los sub incisos b) y d) del inciso B) de la fracción III del artículo 22 de la Ley de Ingresos del Municipio de Tijuana, Baja California para el ejercicio fiscal\n2025.\nArtículo Transitorio Adicionado\nBaja California, a los veinte días del mes de diciembre del dos mil veinticuatro.\nDIP. EVELYN SÁNCHEZ SÁNCHEZ\nDIPUTADA PRESIDENTA\nDIP. MICHELLE ALEJANDRA TEJEDA MEDINA\nDIPUTADA SECRETARIA\nARTÍCULO DÉCIMO SEXTO TRANSITORIO. – Fue adicionado por Decreto No. 67, expedido por la H. XXV Legislatura, siendo Gobernadora Constitucional la C. Marina del\nPilar Ávila Olmeda 2021-2027; fue reformado por Decreto No. 104, publicado en el por la H. XXV Legislatura, siendo Gobernadora Constitucional la C. Marina del Pilar Ávila\nOlmeda 2021-2027;\nARTÍCULO DÉCIMO SÉPTIMO TRANSITORIO. – Fue adicionado por Decreto No. 67, CXXXII, expedido por la H. XXV Legislatura, siendo Gobernadora Constitucional la C.\nMarina del Pilar Ávila Olmeda 2021-2027;\nARTÍCULO 18.- Fue reformado por Decreto No. 105, publicado en el Periódico Oficial\nLegislatura, siendo Gobernadora Constitucional la C. Marina del Pilar Ávila Olmeda\n2021-2027;\nARTÍCULO ÚNICO TRANSITORIO DEL DECRETO No. 67, POR EL QUE SE\nTRANSITORIO Y DÉCIMO SÉPTIMO TRANSITORIO; PUBLICADO EN EL PERIÓDCO\nEXPEDIDO POR LA H. XXV LEGISLATURA; SIENDO GOBERNADORA\nCONSTITUCIONAL LA C. MARINA DEL PILAR ÁVILA OLMEDA 2021-2027.\nTRANSITORIOS\nÚNICO. La presente reforma entrará en vigor al día siguiente de su publicación en el\nPeriódico Oficial del Estado de Baja California.\nDADO en Sesión Ordinaria de la XXV Legislatura en la Ciudad de Mexicali, B.C., a los trece días del mes de marzo del año dos mil veinticinco.\nDIP. EVELYN SÁNCHEZ SÁNCHEZ\nPRESIDENTA\n(RÚBICA)\nDIP. MICHELLE ALEJANDRA TEJEDA MEDINA\nSECRETARIA\n(RÚBICA)\nDE CONFORMIDAD CON LO DISPUESTO POR LA FRACCIÓN I DEL\nDE BAJA CALIFORNIA, IMPRÍMASE Y PUBLÍQUESE.\nMEXICALI, BAJA CALIFORNIA, A LOS 21 DÍAS DEL MES DE MARZO DEL AÑO\nDOS MIL VEINTICINCO.\nMARINA DEL PILAR ÁVILA OLMEDA\nGOBERNADORA DEL ESTADO\nDE BAJA CALIFORNIA\n(RÚBRICA)\nALFREDO ÁLVAREZ CÁRDENAS\nSECRETARIO GENERAL DE GOBIERNO\nDEL ESTADO DE BAJA CALIFORNIA\n(RÚBRICA)\nARTÍCULO ÚNICO TRANSITORIO DEL DECRETO No. 104, POR EL QUE SE\nAPRUEBA LA REFORMA AL ARTÍCULO DÉCIMO SEXTO TRANSITORIO; PUBLICADO\nCXXXII; EXPEDIDO POR LA H. XXV LEGISLATURA; SIENDO GOBERNADORA\nCONSTITUCIONAL LA C. MARINA DEL PILAR ÁVILA OLMEDA 2021-2027.\nTRANSITORIOS\nÚNICO. La presente reforma entrará en vigor al día siguiente de su publicación en el\nPeriódico Oficial del Estado de Baja California.\nDADO en Sesión Ordinaria de la XXV Legislatura en la Ciudad de Mexicali, B.C., a los diecinueve días del mes de junio del año dos mil veinticinco.\nDIP. MICHELLE ALEJANDRA TEJEDA MEDINA\nPRESIDENTA\n(RÚBICA)\nDIP. NORMA ANGELICA PEÑALOZA ESCOBEDO\nSECRETARIA\n(RÚBICA)\nDE CONFORMIDAD CON LO DISPUESTO POR LA FRACCIÓN I DEL\nDE BAJA CALIFORNIA, IMPRÍMASE Y PUBLÍQUESE.\nMEXICALI, BAJA CALIFORNIA, A LOS 20 DÍAS DEL MES DE JUNIO DEL AÑO\nDOS MIL VEINTICINCO.\nMARINA DEL PILAR ÁVILA OLMEDA\nGOBERNADORA DEL ESTADO\nDE BAJA CALIFORNIA\n(RÚBRICA)\nALFREDO ÁLVAREZ CÁRDENAS\nSECRETARIO GENERAL DE GOBIERNO\nDEL ESTADO DE BAJA CALIFORNIA\n(RÚBRICA)\nARTÍCULO ÚNICO TRANSITORIO DEL DECRETO No. 105, POR EL QUE SE\nAPRUEBA LA REFORMA AL ARTÍCULO 18 FRACCIONES III Y VIII; PUBLICADO EN\nCXXXII; EXPEDIDO POR LA H. XXV LEGISLATURA; SIENDO GOBERNADORA\nCONSTITUCIONAL LA C. MARINA DEL PILAR ÁVILA OLMEDA 2021-2027.\nTRANSITORIOS\nÚNICO. La presente reforma entrará en vigor al día siguiente de su publicación en el\nPeriódico Oficial del Estado de Baja California.\nDADO en Sesión Ordinaria de la XXV Legislatura en la Ciudad de Mexicali, B.C., a los diecinueve días del mes de junio del año dos mil veinticinco.\nDIP. MICHELLE ALEJANDRA TEJEDA MEDINA\nPRESIDENTA\n(RÚBICA)\nDIP. NORMA ANGELICA PEÑALOZA ESCOBEDO\nSECRETARIA\n(RÚBICA)\nDE CONFORMIDAD CON LO DISPUESTO POR LA FRACCIÓN I DEL\nDE BAJA CALIFORNIA, IMPRÍMASE Y PUBLÍQUESE.\nMEXICALI, BAJA CALIFORNIA, A LOS 20 DÍAS DEL MES DE JUNIO DEL AÑO\nDOS MIL VEINTICINCO.\nMARINA DEL PILAR ÁVILA OLMEDA\nGOBERNADORA DEL ESTADO\nDE BAJA CALIFORNIA\n(RÚBRICA)\nALFREDO ÁLVAREZ CÁRDENAS\nSECRETARIO GENERAL DE GOBIERNO\nDEL ESTADO DE BAJA CALIFORNIA\n(RÚBRICA)",
  "ordenamiento": "REGLAMENTO",
  "jurisdiccion": "BAJA CALIFORNIA",
  "fuente_oficial": "Periódico Oficial",
  "FECHA PER OFIC": "2025/06/27",
  "ESTATUS": "VIGENTE",
  "TOMO": "TOMO_II",
  "URL": "https://www.congresobc.gob.mx/Documentos/ProcesoParlamentario/Leyes/TOMO_II/20250627_LEYINGRESOTIJUANA2025.PDF",
  "es_escaneado": false,
  "tiene_tablas": true,
  "materia": [
    "financiero",
    "fiscal",
    "económico"
  ]
}