{
  "titulo": "Ley PARA LAS PERSONAS CON DISCAPACIDAD EN EL ESTADO DE BAJA CALIFIORNIA",
  "Contenido": ".\nActualización Legislativa.\nÚltima reforma P.O. No. 13, Número Especial, 13-May-2025\nLEY PARA LAS PERSONAS CON DISCAPACIDAD EN\nEL ESTADO DE BAJA CALIFORNIA\nPublicada en el Periódico Oficial No. 44, Tomo CXVII, Sección III, de fecha\n15 de octubre de 2010\nTÍTULO PRIMERO\nDISPOSICIONES GENERALES\nCAPÍTULO I\nDEL OBJETO, PRINCIPIOS Y DEFINICIONES\nARTÍCULO 1.- La presente Ley es de orden Público, de interés social y de observancia general en todo el territorio de Baja California. Es reglamentaria del artículo 1 de la Constitución Política de los Estados Unidos Mexicanos y de la Convención sobre los\nDerechos de las Personas con Discapacidad, teniendo por objeto el respeto, protección y cumplimiento de las medidas y acciones que contribuyan al desarrollo integral de las personas con discapacidad, procurando su bienestar físico y mental, así como la igualdad de oportunidades en sus actividades, fortaleciendo el entorno donde se desenvuelven.\nPárrafo Reformado\nDe manera enunciativa y no limitativa, esta Ley reconoce a las personas con discapacidad sus derechos humanos y mandata el establecimiento de las políticas públicas necesarias para su ejercicio.\nPárrafo Adicionado\nArtículo Reformado\nARTÍCULO 2.- Los principios que rigen esta ley y que deberán observar las políticas públicas en la materia, son:\nI. El respeto a la dignidad inherente al ser humano;\nII. La autonomía, incluida la libertad de tomar las propias decisiones, y la independencia de las personas con discapacidad;\nIII. La no discriminación;\nIV. La igualdad de oportunidades;\nV. La equidad;\nVI. La accesibilidad;\nVII. La participación e inclusión, plenas y efectivas en la sociedad;\nLey para las Personas con Discapacidad en el Estado de Baja California. Página 1\n.\nActualización Legislativa.\nÚltima reforma P.O. No. 13, Número Especial, 13-May-2025\nVIII. La aceptación y respeto de las personas con discapacidad como parte de la diversidad y la condición humana;\nFracción Reformada\nIX. El reconocimiento de las diferencias de las personas con alguna discapacidad, con el objetivo de eliminar o minimizar las barreras que los mantienen en su discapacidad;\nX. El respeto a la evolución de las facultades de las niñas y los niños con discapacidad y de su derecho a preservar su identidad;\nFracción Reformada\nXI. El respeto al derecho de las personas con discapacidad a vivir en familia y comunidad, constituyendo el internamiento una medida especial de protección temporal de carácter subsidiario y como último recurso terapéutico.\nFracción Adicionada\nArtículo Reformado\nARTÍCULO 3.- Para los efectos de esta Ley se entenderá por:\nI.- Accesibilidad: Las medidas pertinentes para asegurar el acceso de las personas con discapacidad, en igualdad de condiciones con las demás, al entorno físico, el transporte, la información y las comunicaciones, incluidos los sistemas y las tecnologías de la información y las comunicaciones, y a otros servicios e instalaciones abiertos al público o de uso público, tanto en zonas urbanas como rurales;\nII.- Ajustes Razonables: Se entenderán las modificaciones y adaptaciones necesarias y adecuadas que no impongan una carga desproporcionada o indebida, cuando se requieran en un caso particular, para garantizar a las personas con discapacidad el goce o ejercicio, en igualdad de condiciones con las demás, de todos los derechos humanos y libertades fundamentales;\nII BIS.- Asistencia Social: Conjunto de acciones tendientes a modificar y mejorar las circunstancias de carácter social que impidan el desarrollo integral del individuo, así como la protección física, mental y social de personas en estado de necesidad, indefensión, desventaja física y mental, hasta lograr su incorporación a una vida plena y productiva;\nFracción Adicionada\nIII.- Ayudas técnicas: Aquellos dispositivos tecnológicos que contribuyen a la movilidad y comunicación de las personas con discapacidad;\nIV.- Barreras físicas: A los obstáculos que dificultan, entorpecen, impiden, o que comunicación, en espacios interiores o exteriores, sean públicos o privados, así como en el uso de herramientas, dispositivos y servicios comunitarios;\nLey para las Personas con Discapacidad en el Estado de Baja California. Página 2\n.\nActualización Legislativa.\nÚltima reforma P.O. No. 13, Número Especial, 13-May-2025\nV.- Comunidad de Sordos: Todo aquel grupo social cuyos miembros tienen alguna deficiencia del sentido auditivo que les limita sostener una comunicación y socialización regular y fluida en lengua oral; un sordo bilingüe es aquella persona que se comunica en dos lenguas, una de señas y otra escrita; un sordo señante es aquella persona en donde la forma prioritaria de comunicación e identidad social se define en torno de la cultura de una comunidad de sordos y su lenga de señas; un sordo hablante es toda aquella persona que creció hablando una lengua oral pero que en algún momento quedó sorda, pudiendo seguir hablando y, sin embargo, ya no puede comunicarse satisfactoriamente de esta manera; el sordo semilingüe es toda aquella persona que no ha desarrollado a plenitud ninguna lengua, debido a que quedó sordo antes de desarrollar una primera lengua oral y a que tampoco tuvo acceso a una lengua de señas.\nFracción Reformada\nVI.- Consejo Consultivo: Al Consejo Consultivo Para Personas Con Discapacidad\nDel Estado;\nVII.- Discapacidad.- es toda restricción o ausencia (debido a una deficiencia) de la capacidad para realizar una actividad en la forma o dentro del margen que se considera normal para un ser humano en función de su edad, sexo, o factores sociales y culturales;\nVIII.- Discapacidad Auditiva: A la Originada por una deficiencia sensorial congénita o adquirida, caracterizada por la pérdida severa de la capacidad de percepción de las formas acústicas, producida ya sea por una alteración del órgano de la audición o bien de la vía auditiva, y que por la carencia de la agudeza auditiva se limita o impide la comunicación oral;\nVIII BIS.- Discapacidad Intelectual: Se caracteriza por limitaciones significativas tanto en la estructura del pensamiento razonado, como en la conducta adaptativa de la persona, y que al interactuar con las barreras que le impone el entorno social, pueda impedir su inclusión plena y efectiva en la sociedad, en igualdad de condiciones con los demás;\nFracción Adicionada\nIX.- Discapacidad Mental: A la presencia de un desarrollo mental detenido o incompleto, derivado de lesiones o deficiencias en los procesos cerebrales, adquiridos de forma prenatal, perinatal, natal o posnatal, que afectan a nivel global la inteligencia, las funciones cognitivas, las del lenguaje, las motrices y la socialización, incluidos los trastornos del neurodesarrollo;\nX.- Discapacidad Motriz: Al Conjunto de alteraciones y deficiencias congénitas o adquiridas, que en distintos grados, afectan la ejecución y control de movimientos, la postura del cuerpo y la motricidad en general de la persona, independientemente de la causa o hecho desencadenante;\nXI.- Discapacidad Múltiple: A la presencia de dos o más discapacidades en una persona;\nLey para las Personas con Discapacidad en el Estado de Baja California. Página 3\n.\nActualización Legislativa.\nÚltima reforma P.O. No. 13, Número Especial, 13-May-2025\nXII.- Discapacidad Visual: A la derivada de una deficiencia sensorial del sentido de la vista, que se caracteriza por la carencia o disminución de la agudeza o campo visual, cuando esto represente una barrera insuperable, la cual impacte o restrinja la capacidad para realizar una actividad o función necesaria dentro del rol normal de la persona;\nXIII.- Discriminación por motivo de discapacidad: Se entenderá cualquier distinción, exclusión o restricción por motivos de discapacidad que tenga el propósito o el efecto de obstaculizar o dejar sin efecto el reconocimiento, goce o ejercicio, en igualdad de condiciones, de todos los derechos humanos y libertades fundamentales en los ámbitos político, económico, social, cultural, civil o de otro tipo. Incluye todas las formas de discriminación, entre ellas la denegación de ajustes razonables;\nXIV.- Diseño Universal: Al diseño de espacios, herramientas, programas, dispositivos y servicios comunitarios que puedan utilizar las personas con o sin discapacidad en la mayor medida posible, sin necesidad de adaptación ni diseño especializado y teniendo en cuenta el empleo de los elementos de asistencia particulares de cada discapacidad;\nXV.- Educación Escolar o Formal: Al sistema educativo institucionalizado, cronológicamente graduado y jerárquicamente estructurado que se inicia desde la escuela pre-escolar y continúa hasta la universidad;\nXVI.- Educación Especial: Al conjunto de servicios programas, orientación y recursos educativos especializados, puestos a disposición de las personas que padecen algún tipo de discapacidad, que favorezcan su desarrollo integral, y faciliten la adquisición de habilidades y destrezas que les capaciten para lograr los fines de la educación;\nXVII.- Educación No Escolar o Informal: Aquella que permite adquirir y acumular conocimientos y habilidades mediante las experiencias diarias y la relación con el medio ambiente;\nXVIII.- Educación Mixta: Toda actividad educativa, organizada y sistemática realizada fuera del marco del ámbito oficial, para facilitar determinadas clases de aprendizaje a subgrupos particulares de la población;\nXIX.- Empresa incluyente: Fuente de trabajo que adopta la cultura y el compromiso social de incluir en su planta laboral a personas con discapacidad;\nFracción Adicionada, recorriéndose las subsecuentes\nXX.- Equiparación de Oportunidades: Al proceso de adecuaciones, mejoras y ajustes necesarios en el entorno jurídico, social, cultural, de bienes y servicios, que faciliten a las personas con discapacidad una integración, convivencia y participación en igualdad de oportunidades y posibilidades con el resto de la población;\nLey para las Personas con Discapacidad en el Estado de Baja California. Página 4\n.\nActualización Legislativa.\nÚltima reforma P.O. No. 13, Número Especial, 13-May-2025\nXXI.- Estenografía Proyectada: Es el oficio y la técnica de transcribir un monólogo o dialogo oral de manera simultánea a su desenvolvimiento y, así como proyectar el texto resultante por medios electrónicos visuales;\nXXII.- Estimulación Temprana: Atención brindada a niños y niñas de entre 0 y 6 años para potenciar y desarrollar al máximo sus posibilidades físicas, intelectuales, sensoriales y afectivas, mediante programas sistemáticos y secuenciados que abarquen todas las áreas del desarrollo humano, sin forzar el curso natural de su maduración;\nXXIII.- Familia cuidadora: Al conjunto de personas, que dedican una importante actividad diaria al cuidado de sujetos con dependencias o discapacidades;\nXXIV.- Habilitación: Al proceso mediante el cual se dota por primera vez a la persona, de una capacidad o habilidad que le otorgue una mejor calidad de vida, y consiste en brindar asistencia multidisciplinaria y especializada, a la persona que sufre deficiencia congénita o desde temprana edad;\nXXV.- Lengua de Señas: A la Lengua que consiste en una serie de signos gestuales articulados con las manos y acompañados de expresiones faciales, mirada intencional y movimiento corporal, dotados de función lingüística;\nXXVI.- Lengua de Señas Mexicanas: Lengua de una comunidad de sordos, que consiste en una serie de signos gestuales articulados con las manos y acompañados de expresiones faciales, mirada intencional y movimiento corporal, dotados de función lingüística, forma parte del patrimonio lingüístico de dicha comunidad y es tan rica y compleja en gramática y vocabulario como cualquier lengua oral;\nXXVII.- Ley: A la Ley para las Personas con Discapacidad en el Estado de Baja\nCalifornia;\nXXVIII.- Ley General: La Ley General para la Inclusión de las Personas con\nDiscapacidad;\nXXIX.- Maestra sombra: Es una extensión del profesor, proporcionando atención a aquellos que lo necesitan más;\nXXX.- Organizaciones: A las organizaciones sociales constituidas legalmente para el cuidado, atención o salvaguarda de los derechos de las personas con discapacidad o que busquen apoyar y facilitar su participación en las decisiones relacionadas con el diseño, aplicación y evaluación de programas para su desarrollo e integración social;\nXXXI.- Persona con Discapacidad: Toda persona que por razón congénita o adquirida presenta una o más deficiencias de carácter físico, mental, intelectual o sensorial, Ley para las Personas con Discapacidad en el Estado de Baja California. Página 5\n.\nActualización Legislativa.\nÚltima reforma P.O. No. 13, Número Especial, 13-May-2025 social, pueda impedir su inclusión plena y efectiva, en igualdad de condiciones con los demás;\nXXXII.- Persona cuidadora: Son las personas o instituciones que se hacen cargo de las personas con algún nivel de dependencia. Son por tanto padres, madres, hijos/as, familiares, personal contratado o voluntario;\nXXXIII.- Persona dependiente: un estado en que se encuentran las personas que, por razones ligadas a la falta o a la pérdida de autonomía física, psíquica o intelectual tienen necesidad de asistencia o de ayudas importantes para realizar actos corrientes de la vida ordinaria;\nXXXIV.- Perro de asistencia: Los perros educados y adiestrados en centros especializados y oficialmente reconocidos, para prestar asistencia y auxilio a personas con alguna discapacidad;\nXXXV.- Política Pública: Todos aquellos planes, programas o acciones que la autoridad desarrolle para asegurar los derechos establecidos en la presente Ley;\nXXXVI.- Rehabilitación: Al proceso de duración limitada y con un objetivo definido, de orden médico, neuropsicológico, social y educativo entre otros, encaminado a facilitar que una persona con discapacidad alcance un nivel físico, mental o sensorial óptimo, permitiendo compensar la pérdida de una función, así como proporcionarle una mejor integración social;\nXXXVII.- Sistema de Escritura Braille: Sistema para la comunicación representado mediante signos en relieve, leídos en forma táctil por las personas ciegas;\nXXXVIII.- Subcomité Especial: Subcomité Especial de Asistencia Social a Personas con Discapacidad, órgano integrante del Comité de Planeación para el Desarrollo del Estado creado mediante acuerdo publicado en el Periódico Oficial del Estado de fecha 25 de agosto de 1995;\nXXXIX.- Terapia conductual: Consiste en enseñar al paciente a emitir respuestas adaptativas ante los estímulos que les provocan respuestas inadaptadas, bien sea con un desaprendizaje o extinción de la conducta inadecuada, bien sea aprendiendo un comportamiento más adecuado; y, XL.- Transversalidad: Es el proceso mediante el cual se instrumentan las políticas, programas y acciones, desarrollados por las dependencias y entidades de la administración pública, que proveen bienes y servicios a la población con discapacidad con un propósito común, y basados en un esquema de acción y coordinación de esfuerzos y recursos en tres dimensiones: vertical, horizontal y de fondo.\nArtículo Reformado\nLey para las Personas con Discapacidad en el Estado de Baja California. Página 6\n.\nActualización Legislativa.\nÚltima reforma P.O. No. 13, Número Especial, 13-May-2025\nCAPITULO II\nDERECHOS DE LAS PERSONAS CON DISCAPACIDAD\nARTÍCULO 4.- Las personas con discapacidad gozarán de todos los derechos inherentes al ser humano, así como los establecidos en el marco jurídico nacional e internacional, por lo que cualquier distinción, exclusión o restricción por motivos de discapacidad que tenga el propósito o el efecto de obstaculizar o dejar sin efecto el reconocimiento, goce o ejercicio, en igualdad de condiciones, de todos los derechos humanos y libertades fundamentales en los ámbitos político, económico, social, cultural, civil o de otro tipo, será considerada discriminación por motivo de discapacidad.\nArtículo Reformado\nARTÍCULO 4 BIS.- Se reconoce a las personas con discapacidad el derecho a vivir y crecer en el seno de su familia y a ser incluido en la comunidad, en igualdad de condiciones, opiniones y oportunidades de vida y desarrollo que la población en general.\nAquellas que además sean mayores de edad, tienen derecho a elegir su lugar de residencia y con quien habitar, garantizando su capacidad para desarrollarse en forma independiente.\nLas personas con discapacidad no podrán ser obligadas a vivir con arreglo a un sistema de vida específico, por lo que tendrán derecho de acceder a una variedad de servicios de asistencia y servicios de apoyo en la comunidad que les facilite la convivencia e inclusión evitando su aislamiento o separación de ésta.\nPara el cumplimiento de lo anterior, las autoridades estatales y municipales en el ámbito de sus respectivas competencias, adoptarán las medidas efectivas y pertinentes para facilitar el pleno goce de los derechos de las personas con discapacidad y su plena inclusión y participación en comunidad.\nArtículo Adicionado\nARTÍCULO 5.- Además de lo establecido en el artículo anterior, esta Ley reconoce y protege los siguientes derechos:\nI. Tener acceso a la debida y oportuna asistencia médica; atención neuropsicológica y conductual; habilitatoria y rehabilitatoria;\nII. Tener acceso a programas de asistencia específica a la discapacidad generada por la edad, especialmente a los adultos mayores;\nIII. Tener acceso a programas de capacitación para el trabajo;\nIV. La inclusión en bolsas de trabajo del sector público y privado;\nV. Recibir educación especial, escolar, no escolar o mixta que permita el máximo desarrollo de las capacidades de la persona.\nVI. Tener acceso a lugares de esparcimiento para desarrollar deportes;\nLey para las Personas con Discapacidad en el Estado de Baja California. Página 7\n.\nActualización Legislativa.\nÚltima reforma P.O. No. 13, Número Especial, 13-May-2025\nVII. Tener acceso a servicios de salud de buena calidad;\nVIII. Ser sujeto de un programa para contar con una vivienda digna y accesible a sus necesidades;\nIX. Contar con atención igual y trato equitativo;\nX. A la implementación del Diseño Universal de accesibilidad a fin de contar con las facilidades necesarias de acceso y desplazamiento en el interior de espacios laborales, comerciales y recreativos, así como en transportes públicos, incluido el uso de ayudas técnicas, perros de asistencia u otros apoyos;\nXI. Tener fácil acceso a la información y atención de las dependencias del estado; y\nXII. A recibir orientación jurídica en forma gratuita en los términos de la ley de la materia.\nXIII. Tener acceso a programas de asistencia y seguridad social para la persona o familia cuidadora, que les auxilie en el cuidado de la persona con discapacidad;\nXIV. Contar con apoyo de guarderías para niños con discapacidad; y\nXV. Contar con estancias para adultos con discapacidad.\nArtículo Reformado\nARTÍCULO 6.- Se reconoce a las discapacidades mental, intelectual, motriz, sensorial y múltiple, en sus distintos grados y manifestaciones, sin distinción de las causas que las originen, ni la edad en que se manifiesten; y las personas que las enfrentan son beneficiarios de los derechos que confiere esta Ley.\nArtículo Reformado\nARTÍCULO 6 BIS.- Las personas con discapacidad tendrán derecho a recibir un trato digno y apropiado en los procedimientos administrativos y judiciales en que sean parte, así como asesoría y representación jurídica en forma gratuita en dichos procedimientos, con peritos especializados en las diversas discapacidades y con la capacitación y sensibilización dirigido al personal de las instancias de impartición de justicia, sobre la atención a las personas con discapacidad.\nProcurando con la disponibilidad de los recursos para la comunicación, ayudas técnicas y humanas necesarias para la atención de las personas con discapacidad en sus respectivas jurisdicciones apoyo de intérpretes de Lengua de Señas Mexicana, así como la emisión de documentos en Sistema de Escritura Braille, bajo los términos que establezcan las leyes respectivas.\nArtículo Adicionado\nCAPÍTULO III\nDE LA PERSONALIDAD JURÍDICA\nCapítulo Adicionado\nARTÍCULO 6 TER.- Las personas con discapacidad tienen capacidad jurídica en igualdad de condiciones que las demás en todos los aspectos de la vida y, en su caso, Ley para las Personas con Discapacidad en el Estado de Baja California. Página 8\n.\nActualización Legislativa.\nÚltima reforma P.O. No. 13, Número Especial, 13-May-2025 aquéllas que no puedan ejercerla por sí mismas, se estarán a lo dispuesto en la legislación de la materia, en lo que respecta a la representación de las personas con discapacidad.\nArtículo Adicionado\nARTÍCULO 6 QUARTER.- Las autoridades estatales y municipales competentes, proporcionarán a las personas con discapacidad el apoyo que puedan necesitar en el ejercicio de su capacidad jurídica.\nArtículo Adicionado\nARTÍCULO 6 QUINQUIES.- La Fiscalía General del Estado y la Defensoría Pública del Estado en ejercicio de sus competencias, apoyarán jurídicamente a las niñas, niños y adolescentes y en general a las personas con discapacidad que así lo requieran, a efecto de que puedan ejercer su capacidad jurídica a través de sus representantes, en términos de la legislación de la materia.\nArtículo Adicionado\nArtículo Reformado\nARTÍCULO 6 SEXIES.- En todas las medidas y apoyos para el ejercicio de la capacidad jurídica de las personas con discapacidad, se establecerán salvaguardas para impedir abusos, conflictos de intereses o influencias, y conseguir que se respeten los derechos, la voluntad y las preferencias de las personas con discapacidad.\nEstas salvaguardas deberán ser proporcionales y adecuadas a las circunstancias de la persona y durarán el menor tiempo posible.\nArtículo Adicionado\nCAPÍTULO IV\nDE LA ATENCIÓN INTEGRAL\nCapítulo Adicionado\nARTÍCULO 6 SEPTIES.- Se entiende por atención integral los procesos o cualquier otra medida de intervención dirigidos a que las personas con discapacidad adquieran su máximo nivel de desarrollo y autonomía personal, y a lograr y mantener su máxima independencia, capacidad física, mental y social, y su inclusión y participación plena en todos los aspectos de la vida, así como la obtención de un empleo adecuado. la persona con discapacidad, así como de las oportunidades del entorno, considerando las promoción de la autonomía personal.\nLas dependencias y entidades del Gobierno Estatal y de los Municipios, en el ámbito de sus respectivas competencias, velarán por el mantenimiento de servicios de atención adecuados, mediante la coordinación de los recursos y servicios de habilitación y rehabilitación en los ámbitos de la salud, el empleo, la educación y los servicios necesarios, Ley para las Personas con Discapacidad en el Estado de Baja California. Página 9\n.\nActualización Legislativa.\nÚltima reforma P.O. No. 13, Número Especial, 13-May-2025 con el fin de garantizar a las personas con discapacidad una oferta de servicios y programas.\nArtículo Adicionado\nTÍTULO SEGUNDO\nCAPÍTULO I\nDE LAS AUTORIDADES Y SUS FUNCIONES\nARTÍCULO 7.- Las autoridades a las que corresponde el cumplimiento de la presente\nLey, son las siguientes:\nI. El Ejecutivo del Estado, a través de las dependencias y entidades siguientes:\na) Secretaría de Salud;\nb) Secretaría de Educación;\nInciso Reformado\nc) Secretaría del Trabajo y Previsión Social;\nd) Secretaría de Economía e Innovación;\nInciso Reformado\ne) Secretaría de Infraestructura, Desarrollo Urbano y Reordenación Territorial;\nInciso Reformado\nf) Secretaría de Bienestar;\nInciso Reformado\ng) Sistema Estatal para el Desarrollo Integral de la Familia;\nh) Instituto de Cultura de Baja California;\ni) Instituto del Deporte y la Cultura Física;\nj) El Instituto Estatal de Planeación;\nk) El Comité de Planeación del Estado;\nInciso Reformado\nFracción Adicionada\nFracción Adicionada\nLey para las Personas con Discapacidad en el Estado de Baja California. Página 10\n.\nActualización Legislativa.\nÚltima reforma P.O. No. 13, Número Especial, 13-May-2025\nIV.- Los Ayuntamientos.\nV.- La Comisión Estatal de los Derechos Humanos.\nAdemás de las autoridades señaladas en las fracciones del presente artículo, de igual forma corresponde la observancia y cumplimiento de esta Ley a las Entidades Paraestatales y Órganos Desconcentrados de la Administración Pública Estatal, Organismos\nConstitucionales Autónomos, en el ámbito de sus respectivas competencias, así como a las personas físicas o morales de los sectores social y privado que presten servicios a las personas con discapacidad.\nPárrafo Adicionado\nTodas las autoridades señaladas en el presente artículo, adoptarán medidas efectivas que en el ámbito de sus atribuciones correspondan, para que las personas con discapacidad puedan acceder en igualdad de condiciones respecto a las demás personas, a vivir en familia y comunidad con las mismas opciones y oportunidades de vida y desarrollo.\nPárrafo Adicionado\nArtículo Reformado\nARTÍCULO 7 BIS.- Las dependencias y entidades del Gobierno Estatal y de los\nMunicipios, en el ámbito de sus respectivas competencias, así como, las personas físicas o morales de los sectores social y privado que presten servicios a las personas con discapacidad, en coordinación con la Secretaría de Salud, constituyen el Sistema Estatal para el Desarrollo y la Inclusión de las Personas con Discapacidad.\nPárrafo Reformado\nEl Sistema tiene como objeto la coordinación y seguimiento continuo de los programas, acciones y mecanismos interinstitucionales públicos y privados, que permitan la ejecución de las políticas públicas para el desarrollo y la inclusión de las personas con discapacidad.\nArtículo Adicionado\nArtículo Reformado\nARTÍCULO 8.- Corresponde al Ejecutivo del Estado, realizar las siguientes acciones:\nI. Diseñar políticas públicas e implementar las acciones, estrategias y programas que en el ámbito Estatal, hagan efectivos los derechos de las personas con discapacidad y permitan los ajustes razonables; a fin de cumplir con las obligaciones derivadas de los tratados internacionales de derechos humanos de los que el estado Mexicano es parte, adoptando medidas legislativas, administrativas y de otra índole, para hacer efectivos los derechos de las personas con discapacidad;\nFracción Reformada\nII. Definir las estrategias y políticas necesarias para eliminar progresivamente la discriminación;\nIII. Aportar de acuerdo al presupuesto y de conformidad con las disposiciones legales, los recursos materiales, humanos, técnicos, y financieros, que sean necesarios para el\nLey para las Personas con Discapacidad en el Estado de Baja California. Página 11\n.\nActualización Legislativa.\nÚltima reforma P.O. No. 13, Número Especial, 13-May-2025 apoyo de personas con discapacidad a las instituciones y organismos públicos, cuyos fines sigan los objetivos de la presente ley;\nIV. Implementar políticas y programas que acordes al presupuesto, proporcionen a los espacios públicos, elementos de asistencia de uso general y común, como pantallas de información, sillas de ruedas y accesorios que empleen el Sistema de Escritura Braille, entre otros;\nV. Celebrar convenios de colaboración para el cumplimiento de la presente Ley, en beneficio de las personas con discapacidad;\nVI. Activar la prestación o suministro de bienes, servicios, instalaciones, programas y actividades, tales como el empleo, el transporte, las comunicaciones, la recreación, la educación, el deporte, la cultura y la adquisición o remodelación de vivienda, a las personas con discapacidad, en las modalidades que se requiera;\nVII. Otorgar reconocimiento público a las personas físicas, jurídicas, instituciones, grupos o asociaciones que se hayan distinguido por su apoyo a las personas con discapacidad y a los programas que los beneficien;\nVIII. Otorgar beneficios económicos y reconocimiento público a las personas con discapacidad que se distingan en actividades relacionadas con el arte, la ciencia, la cultura y los deportes, así como a las familias cuidadoras o la persona a cargo del dependiente;\nIX. Otorgar estímulos fiscales a las personas físicas o morales que brindan capacitación o trabajo a las personas con discapacidad, en los términos de las leyes correspondientes;\nX. Gestionar y facilitar de acuerdo a sus atribuciones la importación de:\na) Prótesis auditivas, visuales, físicas y órtesis;\nb) Equipos, medicamentos y elementos necesarios para la terapia y rehabilitación de personas con discapacidad;\nc) Equipos, maquinarias y útiles de trabajo especialmente diseñados o adaptados para ser usados por personas con discapacidad;\nd) Elementos de movilidad, cuidado e higiene personal necesarios para facilitar la autonomía y la seguridad de las personas con discapacidad;\ne) Elementos especiales para facilitar la comunicación, la información y la señalización para personas con discapacidad;\nf) Equipos y material pedagógico especiales para educación, capacitación y recreación de las personas con discapacidad, y\nXI. Impulsar programas específicos de apoyo suficiente a la familia cuidadora, para que pueda continuar haciéndose cargo de la persona dependiente;\nFracción Reformada\nLey para las Personas con Discapacidad en el Estado de Baja California. Página 12\n.\nActualización Legislativa.\nÚltima reforma P.O. No. 13, Número Especial, 13-May-2025\nXII. Establecer los convenios de coordinación con las Organizaciones de la Sociedad\nCivil que tengan por objeto la atención de las discapacidades, cuando no pueda proveer el servicio demandado por la ciudadanía y requiera canalizar a personas con discapacidad para su debida atención;\nXIII.- Brindar información sobre los centros especializados en el adiestramiento de perros de asistencia, nacionales o extranjeros, a las personas con discapacidad que así lo requieran;\nFracción Reformada\nXIV.- Considerar en todos los eventos oficiales, traducción simultánea a la Lengua de\nSeñas Mexicanas para lograr una comunicación eficiente y el ejercicio al derecho a la información de las personas sordas o con discapacidad auditiva;\nFracción Adicionada\nFracción Reformada\nXV. Garantizar el desarrollo integral de las personas con discapacidad, de manera plena y autónoma, en los términos de la presente Ley; y,\nFracción Adicionada, recorriéndose la subsecuente\nXVI.- Las demás que resulten de la aplicación de la presente Ley y demás ordenamientos legales aplicables a la materia.\nArtículo Reformado\nARTÍCULO 8 BIS.- El Sistema Estatal para el Desarrollo y la Inclusión de las\nPersonas con Discapacidad tendrá los siguientes objetivos:\nI. Difundir los derechos de las personas con discapacidad;\nII. Promover convenios de colaboración y coordinación entre las instancias y privadas nacionales e internacionales para el cumplimiento del presente ordenamiento legal;\nIII. Fortalecer los mecanismos de corresponsabilidad, solidaridad y subsidiariedad a favor de las personas con discapacidad;\nIV. Impulsar programas y acciones para generar condiciones de igualdad y de equiparación de oportunidades para las personas con discapacidad;\nV. Promover entre el sector público y la sociedad civil acciones dirigidas a mejorar la condición social de la población con discapacidad;\nVI. Promover que en las políticas, programas o acciones, se impulse la toma de consciencia respecto de las capacidades, habilidades, aptitudes, méritos y aportaciones de las personas con discapacidad en todos los ámbitos, y\nVII. Prestar servicios de atención a las personas con discapacidad con fundamento en los principios establecidos en la presente Ley.\nLey para las Personas con Discapacidad en el Estado de Baja California. Página 13\n.\nActualización Legislativa.\nÚltima reforma P.O. No. 13, Número Especial, 13-May-2025\nArtículo Adicionado\nCAPÍTULO II\nDE LA SECRETARÍA DE SALUD\nARTÍCULO 9.- La Secretaría de Salud será la autoridad responsable en el ámbito de su competencia, de las acciones previstas en la presente ley y en los programas que, en materia de salud se impulsen en favor de las personas con discapacidad en el Estado, debiendo incluir las siguientes:\nI. Crear y supervisar periódicamente mecanismos y manuales para la prevención, detección temprana, evaluación, atención oportuna, habilitación y rehabilitación de las diferentes discapacidades;\nII. Definir en coordinación con el Sistema Estatal para el Desarrollo Integral de la\nFamilia, los criterios generales y mecanismos que se emplearán en el Estado para el diagnóstico y tratamiento de la discapacidad de acuerdo a lo establecido en la Clasificación\nNacional de Discapacidades;\nIII. Garantizar que el diagnóstico que se establezca sobre una deficiencia que genere discapacidad, se formule acorde con diferentes procedimientos clínicos y bajo las normas científicas internacionales, observando ante todo la salvaguarda de los Derechos Humanos;\nIV. Aplicar mecanismos y programas para que las personas con discapacidad tengan atención médica a precios asequibles, de la misma calidad y variedad que las demás personas, mismos que se extenderán a las regiones rurales y comunidades indígenas del\nEstado;\nV. Proporcionar los servicios de salud que necesiten las personas como consecuencia de su discapacidad o trastorno del neurodesarrollo, incluidas la pronta detección e intervención cuando proceda, y servicios destinados a prevenir y reducir al máximo la aparición de nuevas discapacidades;\nVI. Realizar periódicamente, estudios e investigaciones, así como emprender campañas permanentes para la prevención y detección de la discapacidad;\nVII. Promover y coordinar ante las instituciones de salud del Estado, la creación de comités internos encargados del desarrollo, aplicación, seguimiento y evaluación de los programas y acciones de prevención, detección temprana, atención adecuada, habilitación y rehabilitación;\nVIII. Gestionar a través de los mecanismos institucionales correspondientes, la creación de bancos de prótesis, ortesis, elementos de asistencia, redes de apoyo a familias cuidadoras, estudios de alta especialización y medicinas de uso restringido, facilitando su obtención a la población con discapacidad de escasos recursos;\nLey para las Personas con Discapacidad en el Estado de Baja California. Página 14\n.\nActualización Legislativa.\nÚltima reforma P.O. No. 13, Número Especial, 13-May-2025\nIX. Establecer los mecanismos para brindar servicios de detección, atención y tratamiento psicológicos para personas con discapacidad, así como de la persona o familia cuidadora;\nX. Realizar la capacitación y actualización continua de los profesionales, técnicos y auxiliares de la salud, principalmente del personal especializado en rehabilitación a fin de que los profesionales de la salud proporcionen a las personas con discapacidad una atención digna y de calidad, sobre la base de un consentimiento libre e informado;\nFracción Reformada\nXI. Establecer acciones de coordinación con instituciones públicas y privadas, para impulsar la investigación y la producción de artículos especiales para la atención de las diferentes discapacidades, con el propósito de facilitar su oportuna adquisición;\nFracción Reformada\nXII. Remitir un informe-diagnóstico sobre los diversos aspectos de las limitaciones y funcionalidades de las personas con discapacidad, su personalidad y entorno familiar con apego a los lineamientos establecidos por la Clasificación Nacional de Discapacidad, al\nRegistro Estatal de Personas con Discapacidad;\nFracción Reformada\nXIII. Establecer centros asistenciales de carácter temporal para personas con discapacidad, donde sean atendidas en condiciones que respeten su dignidad y sus derechos, y les permita capacitarse para su inclusión en la sociedad, de conformidad con los principios establecidos en la presente Ley; y,\nFracción Adicionada, recorriéndose la subsecuente\nXIV. Las demás que sean necesarias para el cumplimiento de la presente ley.\nArtículo Reformado\nARTÍCULO 10.- Los procesos de prevención, habilitación y rehabilitación de las personas con discapacidad serán en los términos previstos por la Ley de Salud Pública para el Estado de Baja California del y los programas que sean creados para tal efecto.\nArtículo Reformado\nCAPÍTULO III\nDE LA SECRETARÍA DE EDUCACIÓN\nDenominación Modificada\nARTÍCULO 11.- La educación que imparta y regule el Estado deberá contribuir al desarrollo integral para potenciar y ejercer plenamente las capacidades, habilidades y aptitudes de las personas con discapacidad.\nARTÍCULO 12.- La educación especial escolar formal será impartida en las instituciones ordinarias, públicas o particulares del sistema educativo, mediante la\nLey para las Personas con Discapacidad en el Estado de Baja California. Página 15\n.\nActualización Legislativa.\nÚltima reforma P.O. No. 13, Número Especial, 13-May-2025 necesidades educativas especiales de cada alumno con discapacidad, y no a criterios estrictamente cronológicos.\nTratándose de menores de edad con discapacidad, esta educación propiciará su integración a los planteles de educación inicial-básica, mediante la aplicación de métodos técnicas y materiales específicos. Para quienes no logren esta integración, esta educación procurará la satisfacción de necesidades básicas de aprendizaje para la autónoma convivencia social y productiva, para lo cual se elaborarán programas y materiales de apoyo didácticos necesarios de acuerdo a la Ley General de Educación.\nLos alumnos que deseen ingresar a instituciones educativas que impartan educación especial, deberán cubrir el perfil de ingreso, el cual debe contar con una evaluación diagnóstica pertinente, estar apegado a los ordenamientos legales correspondientes y que no violente los derechos o discrimine a personas con discapacidad.\nPara el fin señalado, la Secretaría de Educación deberá otorgar criterios para establecer las condiciones básicas que deben de cumplir las instituciones educativas públicas, ordinarias y especiales para impartir la educación especial. De igual manera debe de otorgar los elementos necesarios para realizar los ajustes razonables en las instalaciones y espacios de dichas instituciones, de acuerdo al diseño universal de accesibilidad así como dotar a su personal de la capacitación y de las herramientas necesarias para atender a los alumnos con requerimientos especiales.\nPárrafo Reformado\nArtículo Reformado\nARTÍCULO 13.- La educación especial tendrá, de conformidad con la Ley General de\nEducación y la Ley de Educación del Estado, como propósito fortalecer la integración e inclusión de las personas con discapacidad en todos los niveles del Sistema Educativo\nEstatal.\nPara lo anterior, la coordinación de educación especial desarrollará y aplicará normas y reglamentos que eviten su discriminación y las condiciones de accesibilidad en instalaciones educativas, asegurándose que estas proporcionen los apoyos didácticos, materiales y técnicos y cuenten con personal docente capacitado; en conjunto la escuela, el maestro y los padres o tutores deben contribuir activamente a la inclusión de las niñas y los niños con discapacidad y/ o necesidades educativas especiales a la escuela regular.\nArtículo Reformado\nARTÍCULO 14.- Cuando la naturaleza o grado de discapacidad no haga posible la señalada integración a los cursos ordinarios, o cuando la Ley de Educación del Estado o sus programas lo declaren indispensable, la incorporación a la educación se hará en los Centros de Atención Múltiple en los cuales, bajo ninguna circunstancia podrá ser negada la atención. a raíz de alguna limitante, el Estado estará obligado a intervenir de manera oportuna y puntual para que se logre la provisión del servicio educativo para ello:\nLey para las Personas con Discapacidad en el Estado de Baja California. Página 16\n.\nActualización Legislativa.\nÚltima reforma P.O. No. 13, Número Especial, 13-May-2025\nI.- Otorgara estímulos y apoyos a las organizaciones de la sociedad civil debidamente constituidas, y a las cooperativas de maestros que se dediquen a la enseñanza de la educación especial bajo las modalidades de educación escolar, no escolar o mixta;\nII.- Promoverá de conformidad con los lineamientos que establezca la autoridad educativa estatal la participación de la sociedad civil en actividades que tengan por objeto fortalecer y elevar la calidad de la educación así como ampliar la cobertura de los servicios educativos.\nArtículo Reformado\nARTÍCULO 15.- La Secretaría de Educación promoverá el derecho a la educación de las personas con discapacidad, prohibiendo cualquier discriminación en planteles, centros educativos, bibliotecas, guarderías o por parte del personal docente o administrativo del\nSistema Educativo Estatal. Así mismo difundirá entre la comunidad académica el respeto a la diversidad.\nPárrafo Reformado\nPara tales efectos, llevara a cabo entre otras acciones:\nI.-Elaborar, establecer y fortalecer las evaluaciones psicopedagógicas para la elaboración de las adecuaciones curriculares a los planes y programas para la educación inclusiva de personas con discapacidad;\nII.- Realizar los ajustes razonables para la incorporación y oportuna canalización de las personas con discapacidad en todos los niveles del Sistema Educativo Estatal; así como verificar el cumplimiento de las normas para su integración educativa en apego a lo establecido a la Ley General de Inclusión para las Personas con Discapacidad;\nIII.- Garantizar en todo momento el acceso de las personas con discapacidad a una educación inclusiva y especial, diseñando para ello los métodos, técnicas o programas necesarios, en razón de los diversos tipos de discapacidad, brindando de esta forma la posibilidad de desarrollo integral de manera igualitaria, sin ningún tipo de distinción, ni discriminación.\nIV.- Fomentar, actualizar, capacitar y profesionalizar a los docentes y al personal que intervenga directamente en la integración educativa de personas con discapacidad; así la integración e inclusión educativa de personas con discapacidad, al Sistema Nacional de\nFormación, Actualización, Capacitación y Superación Profesional para Maestros de\nEducación Básica;\nV.- Proporcionar a los estudiantes con discapacidad materiales y ayudas técnicas que apoyen su rendimiento académico, procurando equipar los planteles y centros educativos con libros en braille, materiales didácticos, apoyo de intérpretes, traductores de lengua de señas mexicana, o especialistas en Sistema Braille, maestras sombra, equipos\nLey para las Personas con Discapacidad en el Estado de Baja California. Página 17\n.\nActualización Legislativa.\nÚltima reforma P.O. No. 13, Número Especial, 13-May-2025 computarizados con tecnología para personas ciegas y todos aquellos apoyos que se identifiquen como necesarios para brindar una educación con calidad;\nFracción Reformada\nVI.- Implementar el reconocimiento oficial de la Lengua de Señas Mexicana y el\nSistema de Escritura Braille, en la educación pública y privada, fomentando la producción y distribución de libros de texto gratuitos en Sistema de Escritura Braille, macrotipos y textos audibles que complementen los conocimientos de los alumnos con discapacidad; así como programas de capacitación e investigación, para su utilización en el Sistema Educativo\nEstatal.\nDe igual forma, diseñar, formular, promover, organizar e impartir capacitaciones y certificaciones en la Lengua de Señas Mexicanas;\nVII.- Asegurar el acceso de la población con discapacidad auditiva a la educación bilingüe, que comprenda además del idioma español, la Lengua de Señas Mexicana; promover que los programas educativos que se transmiten por televisión pública o privada local, incluyan tecnologías para texto, audio descripciones, estenografía proyectada o intérpretes de Lengua de Señas Mexicana;\nVIII.- Establecer un programa estatal de becas educativas y becas de capacitación para personas con discapacidad en todos los niveles del Sistema Educativo Estatal;\nIX.- Diseñar e implementar programas de formación y certificación de intérpretes estenógrafos del español y demás personal especializado en la difusión y uso conjunto del español y la Lengua de Señas; así como de las formas de comunicación de las personas con discapacidad visual entre ellas el sistema de escritura Braille y otras tecnologías;\nX.-Impulsar programas de investigación, preservación y desarrollo de la Lengua de\nSeñas Mexicana promoviendo la Educación Bilingüe para Sordos, que facilite al sordo hablante, al sordo señante o semilingüe, el desarrollo y uso de la lengua en forma escrita;\nXI. Establecer mecanismos a fin de que las niñas y los niños con discapacidad gocen del derecho a la admisión gratuita y obligatoria así como a la atención especializada, en los centros de desarrollo infantil, guarderías públicas y en guarderías privadas mediante convenios de servicios. Las niñas y niños con discapacidad no podrán ser condicionados en su integración a la educación inicial o preescolar;\nXII. Impulsar con los Centros de Enseñanza de Educación Superior, convenios y lineamientos que permitan la investigación y el desarrollo de bienes, servicios, equipo, tecnología e instalaciones de diseño universal;\nXIII. Promover que los estudiantes presten apoyo a personas con discapacidad que así lo requieran, a fin de que cumplan con el requisito del servicio social;\nXIV.-Establecer condiciones de inclusión de personas con discapacidad para lograr equidad en la promoción, el disfrute y la producción de servicios educativos y científicos;\nXV.- El Estado promoverá con los Ayuntamientos los Convenios de Colaboración a fin de que en las Bibliotecas y salas de lectura, entre otros, se incorporen equipos de cómputo\nLey para las Personas con Discapacidad en el Estado de Baja California. Página 18\n.\nActualización Legislativa.\nÚltima reforma P.O. No. 13, Número Especial, 13-May-2025 con tecnología adaptada, escritura e impresión en el Sistema de Escritura Braille, ampliadores y lectores de texto, espacios adecuados y demás innovaciones tecnológicas que permita su uso a las personas con discapacidad;\nXVI.- El Estado promoverá la participación de las Organizaciones de la Sociedad Civil en los procesos educativos tendientes a fortalecer o complementar los servicios educativos otorgados; y\nXVII.- Coordinar y promover el establecimiento y lineamientos de atención para el ingreso y continuidad de los estudiantes en condición de discapacidad en los niveles de educación media superior y superior.\nXVIII.- Las demás que sean necesarias para el cumplimiento de la presente Ley.\nArtículo Reformado\nARTÍCULO 16.- La educación especial tendrá por objeto, además de lo establecido en la Ley General de Educación y Ley de Educación Estatal, la formación de la vida independiente y la atención de necesidades educativas especiales que comprende entre otras, dificultades severas de aprendizaje, comportamiento, emocionales, discapacidad múltiple o severa y aptitudes sobresalientes, que le permita a las personas tener un desempeño académico equitativo, evitando así la desatención, deserción, rezago o discriminación. Así también a la consecución de los siguientes objetivos:\nI.- La superación de la discapacidad y los trastornos del neurodesarrollo, consecuencias o secuelas derivadas de aquéllas;\nII.-El desarrollo de habilidades, aptitudes y conocimientos que le permitan a la persona con discapacidad una mayor autonomía;\nIII.-El fomento y la promoción de todas las potencialidades de las personas con discapacidad para el desarrollo armónico de su personalidad;\nIV.-Desarrollar al máximo su capacidad de aprendizaje, enfatizando en el desarrollo de habilidades y competencias para la vida, y\nV.-Impulsar la incorporación a la vida social y al sistema de trabajo que permita a la persona con discapacidad servirse a sí mismo, a la sociedad y auto realizarse.\nVI.- La Coordinación de Educación Especial del Estado, deberá establecer procedimientos transparentes por medio de los cuales se expidan certificados, constancias, correspondan a cierto nivel educativo o grado escolar, adquiridos en forma autodidacta, de la educación escolar, no escolar o mixta.\nArtículo Reformado\nLey para las Personas con Discapacidad en el Estado de Baja California. Página 19\n.\nActualización Legislativa.\nÚltima reforma P.O. No. 13, Número Especial, 13-May-2025\nARTÍCULO 17.- La educación especial deberá contar con personal técnicamente capacitado y calificado que en actuación interdisciplinaria, proveerá las diversas atenciones que cada persona con discapacidad requiera.\nARTÍCULO 18.- Se garantizará que quienes participen en la elaboración de los programas de educación especial para la atención de las personas con discapacidad cuenten con título profesional, especialización, experiencia y aptitudes en la materia.\nArtículo Reformado\nCAPÍTULO IV\nDE LA SECRETARÍA DEL TRABAJO Y PREVISIÓN SOCIAL\nARTÍCULO 19.- La Secretaría del Trabajo y Previsión Social en el ámbito de su competencia, será la autoridad responsable de las acciones que en materia laboral se impulsen en la presente Ley y en los programas, en favor de las personas con discapacidad en el Estado, debiéndose incluir las siguientes:\nI. Impulsar su integración en el sistema ordinario de trabajo o en su caso, en un sistema de trabajo protegido garantizando que esta integración no sea menor al 2% de la plantilla laboral del sistema, de acuerdo a sus características individuales, en condiciones adecuadas, vigilando que estas no sean discriminatorias;\nII.- Impulso entre los sectores público, social y privado para la creación y desarrollo de bolsas de trabajo, programas de capacitación y becas de empleo dirigidos a las personas con discapacidad así como la persona o familia cuidadora;\nIII.- Promoción del otorgamiento de estímulos fiscales para aquellas personas físicas o morales que contraten personas con discapacidad, así como beneficios adicionales para quienes en virtud de dichas contrataciones realicen adaptaciones, eliminen barreras físicas o rediseñen sus áreas de trabajo; pudiendo otorgarles la denominación de “Empresa\nIncluyente”;\nFracción Reformada\nIV.- Coordinación con el Sistema para el Desarrollo Integral de la Familia, para la evaluación y acreditación de las habilidades para el trabajo de las personas con discapacidad, así como la persona y familia cuidadora;\nV.-Impulso a programas de capacitación y adiestramiento laboral, cursos especiales auxiliados con intérpretes y material didáctico especial;\nVI.-Promoción al desarrollo de programas de autoempleo;\nVII.- Impulso en coordinación con las autoridades educativas estatales y federales, el Estado, y\nVIII.-Las demás que sean necesarias para el cumplimiento de esta Ley.\nArtículo Reformado\nLey para las Personas con Discapacidad en el Estado de Baja California. Página 20\n.\nActualización Legislativa.\nÚltima reforma P.O. No. 13, Número Especial, 13-May-2025\nCAPÍTULO V\nDE LA SECRETARÍA DE INFRAESTRUCTURA, DESARROLLO URBANO Y\nREORDENACIÓN TERRITORIAL, Y DE LOS AYUNTAMIENTOS EN MATERIA DE\nDESARROLLO URBANO\nDenominación Modificada\nARTÍCULO 20.- La Secretaría de Infraestructura, Desarrollo Urbano y Reordenación\nTerritorial y los Ayuntamientos en el ámbito de sus competencias, serán las autoridades responsables que vigilarán el cumplimiento de las disposiciones que en materia de accesibilidad, desarrollo urbano y vivienda se establecen en la normatividad vigente, así como de las acciones que en materia urbana se impulsen en la presente Ley y en los programas, en favor de las personas con discapacidad en el Estado, debiéndose incluir las siguientes:\nPárrafo Reformado\nI.-Impulsar la construcción de infraestructura urbana de carácter público que suprima las barreras físicas y sean planeadas con Diseño Universal, observando lo establecido en el\nManual Estatal De Libre Acceso, que será creado por el Consejo Consultivo;\nII.- Impulsar la creación de normas, lineamientos y reglamentos que garanticen la ejecución de programas de construcción y adaptación de viviendas donde se asegure la accesibilidad universal, de conformidad con las normas y especificaciones técnicas de construcción que determinen las autoridades estatales y municipales responsables de los programas de vivienda, con estricto apego a las normas y convenciones internacionales;\nIII.- Realizar acciones tendientes a eliminar las barreras físicas existentes en los edificios de uso público y equipamiento urbano;\nIV.- Asegurar la determinación de espacios reservados para personas con discapacidad, en los auditorios, cines, teatros, salas de concierto, centros recreativos, deportivos y en general cualquier recinto en que se presenten espectáculos públicos;\nV.- Incluir programas y estrategias dentro del presupuesto, para lograr el Diseño\nUniversal obligatorio en espacios e instalaciones públicas o privadas, que les permita el libre desplazamiento en condiciones dignas y seguras, en base a las normas nacionales e internacionales; y\nVI.-Las demás que sean necesarias para el cumplimiento de la presente Ley.\nArtículo Reformado\nARTÍCULO 21.- Para facilitar la accesibilidad en la infraestructura básica, equipamiento urbano y espacios públicos, se contemplarán entre otros, los siguientes lineamientos:\nI.- Se ajusten al Diseño Universal;\nII.-Que cuenten con señalización e incluyan tecnologías para facilitar el acceso y acompañen, y\nLey para las Personas con Discapacidad en el Estado de Baja California. Página 21\n.\nActualización Legislativa.\nÚltima reforma P.O. No. 13, Número Especial, 13-May-2025\nIII.- Que la adecuación de las instalaciones públicas sea progresiva con metas anualizadas.\nArtículo Reformado\nARTÍCULO 22.- Las autoridades a que se refiere este capítulo impulsaran la inclusión de proyectos arquitectónicos que consideren las necesidades de Diseño Universal de las personas con discapacidad en los programas de vivienda.\nCAPÍTULO VI\nDE LOS SISTEMAS ESTATAL Y MUNICIPAL PARA EL DESARROLLO\nINTEGRAL DE LA FAMILIA\nARTÍCULO 23.- Corresponderá al Sistema Estatal para el Desarrollo Integral de la\nFamilia y autoridades municipales competentes en coordinación con la Secretaría de Salud, implementar el mecanismo para constatar, calificar, evaluar y declarar la certificación de condición de discapacidad, el cual debe de estar en estricto apego a lo establecido en la\nClasificación Nacional de Discapacidad.\nArtículo Reformado\nARTÍCULO 23 BIS.- El Sistema Estatal para el Desarrollo Integral de la Familia participará en el ámbito de su competencia, en el diseño y ejecución de programas de prevención y de atención a las personas con discapacidad para su rehabilitación, e inclusión social, en apego a las normas y disposiciones aplicables.\nArtículo Adicionado\nARTÍCULO 23 TER.- El Sistema Estatal para el Desarrollo Integral de la Familia otorgará a las personas con discapacidad atención especializada en materia de rehabilitación, atención psicológica, trabajo social así como la detección y su encauzamiento a los diversos programas, terapias y seguimientos que se requieran.\nArtículo Adicionado\nARTÍCULO 24.- La presente ley reconoce la credencial nacional de discapacidad del\nSistema Nacional para el Desarrollo Integral de la Familia, de validez oficial en el Estado y\nMunicipios que lo integran, la cual deberá ser emitida por los Sistemas Estatal y Municipal para el Desarrollo Integral de la Familia.\nArtículo Reformado\nARTÍCULO 25.- El Ejecutivo del Estado, debe de contar con un Registro Estatal de\nPersonas con Discapacidad, implementando un Sistema de Información Básica en materia de Asistencia Social, cuyo objetivo será reunir y mantener los antecedentes de las personas con discapacidad del Estado y de los organismos de la sociedad civil, que presten asistencia social a este sector, lo anterior en apego a lo que para tal fin se establece en el Sistema\nNacional para el Desarrollo Integral de la Familia.\nPárrafo Reformado\nLey para las Personas con Discapacidad en el Estado de Baja California. Página 22\n.\nActualización Legislativa.\nÚltima reforma P.O. No. 13, Número Especial, 13-May-2025\nEn el Registro Estatal anterior deberán ser integrados las y los menores de edad con discapacidad, las y los neonatos en los que se identifique una discapacidad congénita o genética, al momento del nacimiento o como resultado del Tamiz neonatal, incluyendo la correspondiente certificación de discapacidad para garantizar el interés superior de la niñez.\nPárrafo Adicionado\nArtículo Reformado\nARTÍCULO 26.- El Registro Estatal de Personas con Discapacidad tendrá las siguientes funciones:\nI.- Elaborar el Padrón Estatal de Personas con Discapacidad, que contabilice la población perteneciente a este sector, en base a los Informes y Diagnósticos que le sean remitidos, por el Sector Salud, el Sistema Estatal y Municipal para el Desarrollo Integral de la\nFamilia, Sistema Educativo y los demás que remitan los Ayuntamientos;\nII.-Contar con un registro de las organizaciones civiles de rehabilitación, productivas, educativas, de capacitación, de beneficencia, asistencia, gremiales, sindicales que desempeñen actividades de asistencia social en beneficio de las personas con discapacidad;\nIII.-Mantener actualizados los datos de registros de las personas con discapacidad en el Sistema de Información Básica en Materia de Asistencia Social;\nIV.- Canalización hacia organismos especializados públicos o privados, que contribuyan a la rehabilitación o desarrollo de alguna actividad laboral, educativa, cultural, deportiva, o de capacitación a las personas con discapacidad o trastornos del neurodesarrollo que acudan al Registro, para lo cual se deberán establecer Convenios de\nServicios y/o Colaboración con las instancias correspondientes;\nV.- El Sistema Estatal para el Desarrollo Integral de la Familia, deberá incorporar la información procedente de las Organizaciones de la Sociedad Civil, que tienen por objeto la atención de las personas con discapacidad;\nVI.- Y las demás que prevengan las disposiciones aplicables.\nArtículo Reformado\nCAPÍTULO VII\nDE LOS INSTITUTOS DEL DEPORTE Y LA CULTURA FÍSICA,\nY DE CULTURA DE BAJA CALIFORNIA\nARTÍCULO 27.- El Instituto del Deporte y la Cultura Física, y el Instituto de Cultura, ambos del Estado Baja California, en el ámbito de sus competencias, serán las autoridades programas en materia de deporte, como a la cultura, la recreación, el desarrollo de sus capacidades artísticas y la protección de sus derechos de propiedad intelectual, que se impulsen en la presente Ley y en los programas, en favor de las personas con discapacidad en el Estado. Para tales efectos, realizará las siguientes acciones:\nLey para las Personas con Discapacidad en el Estado de Baja California. Página 23\n.\nActualización Legislativa.\nÚltima reforma P.O. No. 13, Número Especial, 13-May-2025\nI.- Promoción y difusión del deporte popular y de alto rendimiento;\nII.- Establecer programas para apoyar el desarrollo artístico y cultural de las personas con discapacidad e impulsar el otorgamiento de becas para fomentar la participación en las competencias deportivas y culturales estatales, nacionales e internacionales, y de premios e incentivos a las personas que destaquen en las mismas;\nIII.- Establecer programas tendientes al desarrollo de las capacidades creadoras, artísticas e intelectuales, así como fomentar entre la sociedad el respeto a la diversidad y participación de las personas con discapacidad en actividades culturales y artísticas; considerando las necesidades especiales de este sector social;\nIV.- Asignar áreas y equipamiento apropiado para el desarrollo de la cultura en las bibliotecas públicas;\nV.- Asegurar que a la personas con discapacidad se les brinden facilidades de acceso a museos, teatros, cines, bibliotecas públicas, instalaciones deportivas y recreación, es decir a todo recinto donde se brinde actividad cultural y deportiva;\nVI.- Elaborar programas específicos que fomenten la participación de las personas con discapacidad, en donde se incluya la realización de encuentros, visitas guiadas, campamentos, talleres y cursos artísticos, así como el uso del sistema de escritura Braille, Lengua de Señas Mexicana, y Asistente Personal o apoyo de Sombra, para lograr equidad en la promoción, el disfrute y la producción de servicios artísticos y culturales;\nVII.- Impulsar el reconocimiento y el apoyo de su identidad cultural y lingüística específica, incluidas la Lengua de Señas Mexicana y la cultura de los sordos;\nVIII.- Establecer la capacitación de recursos humanos, el uso de materiales y tecnología con la finalidad de lograr su integración en las actividades culturales;\nIX.- Fomentar la elaboración de materiales de lectura, inclusive en sistema Braille u otros formatos accesibles;\nX.- Establecer actividades educativas, culturales, artísticas y deportivas que fomenten el aprendizaje de la lengua de Señas Mexicanas;\nFracción Adicionada\nXI.- Realizar campañas sociales para detectar la sordera en las niñas, niños y adolescentes, para garantizar el apoyo educativo y el acceso a la lengua de Señas\nMexicanas, así como establecer programas de capacitación de la Lengua de Señas\nMexicanas a los familiares en línea directa, con la finalidad de fortalecer la comunicación familiar.\nFracción Adicionada\nXII.- Implementar talleres y cursos dirigidos a personas sordas que les informen sobre los derechos que tienen en la sociedad; y\nFracción Adicionada\nXXIII.- Las demás necesarias para el cumplimiento de la presente Ley.\nLey para las Personas con Discapacidad en el Estado de Baja California. Página 24\n.\nActualización Legislativa.\nÚltima reforma P.O. No. 13, Número Especial, 13-May-2025\nDichas autoridades señaladas en el presente artículo, podrán llevar acabo acuerdos o convenios con las diferentes asociaciones civiles del Estado en materia de discapacidad para realizar dichas acciones.\nPárrafo Adicionado\nArtículo Reformado\nCAPÍTULO VIII\nDEL INSTITUTO ESTATAL DE PLANEACIÓN Y COMITÉ DE PLANEACIÓN PARA EL\nESTADO.\nARTÍCULO 28.- El Instituto Estatal de Planeación en coordinación con el Comité de\nPlaneación para el Desarrollo del Estado, auxiliaran al Ejecutivo Estatal, con el apoyo de la estructura del Sistema Estatal de Planeación del Desarrollo, para elaborar las estrategias, acciones y objetivos tendientes a la equiparación de oportunidades para el desarrollo integral de las personas con discapacidad en los términos de esta Ley y demás disposiciones aplicables.\nARTÍCULO 29.- El Subcomité Especial estará integrado por las dependencias, organismos y organizaciones previstas en su Acuerdo de Creación en vigor. Al subcomité especial, además de lo previsto en su Acuerdo de Creación le corresponde:\nI.- Establecer los mecanismos de concertación, coordinación y promoción de programas y acciones encaminados a mejorar y garantizar a las personas con discapacidad, las condiciones necesarias para su desarrollo e integración plena a la vida social y productiva en la entidad;\nII.- Velar por que las medidas que se adopten en acatamiento a las disposiciones de esta Ley, sean uniformes en toda la entidad y se armonicen con las disposiciones reglamentarias que expidan los ayuntamientos del Estado;\nIII.- Difundir los programas que contribuyan al desarrollo integral de las personas con discapacidad con la finalidad de concientizar e informar a la sociedad respecto de los mismos;\nIV.- Buscar activamente la colaboración e intercambio de información entre las dependencias, entidades, instituciones, organizaciones, agrupaciones docentes, de investigación o asistencia que se relacionen con el objeto de esta Ley, y\nV.- Las demás que se determinen en su seno, de conformidad con lo previsto en la presente Ley y disposiciones aplicables.\nArtículo Reformado\nARTÍCULO 30.- La Administración Pública Estatal y Municipal, a través del Subcomité\nEspecial determinarán las estrategias, las acciones y los objetivos a que deberán sujetarse las dependencias y entidades de éstas, con la participación que de conformidad con el\nSistema Estatal de Planeación corresponda a los sectores privado y social; para equiparar\nLey para las Personas con Discapacidad en el Estado de Baja California. Página 25\n.\nActualización Legislativa.\nÚltima reforma P.O. No. 13, Número Especial, 13-May-2025 oportunidades, generar condiciones de accesibilidad y propiciar el desarrollo integral y la inclusión social de todas las personas con discapacidad en el Estado.\nARTÍCULO 31.- Las estrategias y acciones relacionadas con la participación de los sectores privado y social referidas en el artículo anterior, garantizarán la concertación de acuerdos y convenios, que tengan por objeto, poner a disposición de las personas con discapacidad mental, sensorial y motora, elementos de asistencia y aditamentos de servicio adaptados al Sistema de Escritura Braille, a la Lengua de Señas Mexicana y Asistente\nPersonal o apoyo de Sombra, así como personal debidamente capacitado para su atención conforme a las necesidades propias de su discapacidad.\nArtículo Reformado\nARTÍCULO 32.- Los ayuntamientos deberán procurar la concordancia de las estrategias, las acciones y los objetivos que se aprueben en el Subcomité Especial.\nARTÍCULO 33.- La ejecución de los acuerdos tomados en el Subcomité Especial quedará a cargo de las dependencias y entidades de la Administración Pública Estatal y\nMunicipal en sus respectivos ámbitos de competencias.\nCAPÍTULO IX\nDEBERES Y FACULTADES DE LOS AYUNTAMIENTOS\nARTÍCULO 34.- Los Ayuntamientos, en sus ámbitos de competencia, deberán coordinarse con las Dependencias y Entidades referidas en la presente Ley, a efecto de otorgar una mejor prestación de los servicios a favor de las personas con discapacidad.\nDe igual forma y para la prestación de los servicios públicos que tienen a su cargo, los\nAyuntamientos en sus respectivos ámbitos de competencia establecerán ventanillas de atención preferente para las personas con discapacidad.\nArtículo Reformado\nARTÍCULO 35.- Además de lo establecido en el artículo anterior, los Ayuntamientos deberán de realizar lo siguiente:\nI.- Emitir políticas públicas municipales cuyo objetivo sea la equiparación de oportunidades para el desarrollo integral de las personas con discapacidad;\nII.- Formular y desarrollar programas municipales de atención a personas con\nSocial, conforme a los principios y objetivos de los Planes Nacional, Estatal y Municipal de\nDesarrollo;\nIII.- Celebrar convenios de colaboración para el cumplimiento de la presente Ley, en beneficio de las personas discapacidad;\nLey para las Personas con Discapacidad en el Estado de Baja California. Página 26\n.\nActualización Legislativa.\nÚltima reforma P.O. No. 13, Número Especial, 13-May-2025\nIV.- Vigilar y coadyuvar en la esfera de su competencia, el cumplimiento de la presente Ley, de la Ley de Transporte, Ley de Salud, y Ley de Asistencia, así como de las demás disposiciones legales y reglamentarias aplicables en esta materia;\nV.- Coadyuvar a la creación y actualización del Registro Estatal de Personas con\nDiscapacidad, a efecto de poder cumplir con lo previsto en esta Ley;\nVI.- Otorgar los reconocimientos, beneficios económicos, estímulos fiscales y apoyos a que se refieren las fracciones VII, VIII, IX y X del artículo 8 de la presente Ley;\nVII.- En materia de Transporte:\na) Establecer, especificaciones técnicas y diseños universales que permitan el libre acceso, uso y desplazamiento en los servicios de transporte público, para la adecuación de los vehículos destinados a la prestación de este servicio;\nb) Establecer que se reserven asientos y tarifas preferenciales para personas con discapacidad, en las unidades destinadas a la prestación del servicio público de transporte;\nc) Promover y concertar convenios a efecto de que se permita el acceso a las personas con discapacidad en los servicios públicos de transporte, cuando se desplacen acompañados de elementos de asistencia;\nd) Incorporar las disposiciones contenidas en los incisos anteriores, como obligaciones a cargo de los concesionarios dentro de los Títulos - Concesión que se otorguen para la prestación del servicio público de transporte;\ne) Realizar programas y campañas de educación vial y cortesía urbana, encaminados a generar hábitos de respeto hacia sus personas en su tránsito por la vía pública y en lugares de acceso al público;\nf) Establecer zonas preferenciales para el estacionamiento de vehículos en los que viajen personas con discapacidad, tanto en la vía pública, como en lugares de acceso al público;\ng) Promover y concertar convenios con las empresas de telefonía pública para que realicen las adecuaciones necesarias a sus aparatos en la vía pública, a efecto de facilitarles el acceso, y\nh) Las demás que le confieran esta Ley y otros ordenamientos legales y reglamentarios sobre la materia.\nVIII.- Considerar en todos los eventos oficiales, traducción simultánea a la Lengua de información de las personas sordas o con discapacidad auditiva.\nFracción Adicionada\nArtículo Reformado\nCAPÍTULO X\nHUMANOS.\nCapítulo Adicionado\nLey para las Personas con Discapacidad en el Estado de Baja California. Página 27\n.\nActualización Legislativa.\nÚltima reforma P.O. No. 13, Número Especial, 13-May-2025\nARTÍCULO 35 BIS.- La Comisión Estatal de los Derechos Humanos en el ámbito de su competencia, será la autoridad responsable de las acciones que en materia derechos humanos se impulsen en la presente Ley y en los programas, en favor de las personas con discapacidad en el Estado, debiéndose incluir las siguientes funciones y atribuciones:\nI.- Coordinar las actividades relacionadas con los derechos humanos y la discapacidad a nivel estatal y municipal;\nII.- Observar la acción gubernamental a fin de que respeten los derechos de las personas con discapacidad;\nIII.- Sensibilizar al público sobre las cuestiones relacionadas con la discapacidad y los derechos de las personas con discapacidad;\nIV.- Velar por que las personas con discapacidad que deseen participar en la formulación de las políticas y leyes que les afecten, no les sea vulnerado su derecho; y\nV.- Recomendar a las personas con discapacidad que participen en organizaciones y la sociedad civil, así como promover la creación de organizaciones de personas con discapacidad.\nArtículo Adicionado\nArtículo Reformado\nTÍTULO TERCERO\nDEL CONSEJO CONSULTIVO PARA PERSONAS CON DISCAPACIDAD DEL ESTADO\nCAPÍTULO I\nDE SU OBJETO Y ATRIBUCIONES\nARTÍCULO 36.- Se crea el Consejo Consultivo para las Personas con Discapacidad, como instrumento de coordinación entre el Gobierno del Estado y las organizaciones, de carácter técnico consultivo y que tiene por objeto contribuir al establecimiento de una Política de Estado en la materia, así como coadyuvar en la planeación, promoción, vigilancia y evaluación de las acciones, estrategias y programas encaminados a la atención, integración y desarrollo de las personas con discapacidad, que generen en éstas condiciones y lograr su plena inclusión y participación en la comunidad.\nArtículo Reformado\nARTÍCULO 37.- El Consejo tendrá las siguientes atribuciones:\nI. Proponer estrategias, políticas y programas en materia de discapacidad, emitiendo opiniones técnicas a las diversas instituciones del sector público, así como aquellas que correspondan a los sectores social y privado; como se estipula en la Ley general de Inclusión a las Personas con Discapacidad;\nLey para las Personas con Discapacidad en el Estado de Baja California. Página 28\n.\nActualización Legislativa.\nÚltima reforma P.O. No. 13, Número Especial, 13-May-2025\nII. Proponer en el marco del Plan Estatal de Desarrollo, el programa estatal de desarrollo de las personas con discapacidad, promoviendo acuerdos o convenios con las dependencias de la Administración Pública Estatal y los Municipios;\nIII. Evaluar el estricto cumplimiento de las disposiciones de esta Ley por las autoridades encargadas de su aplicación;\nIV. Conformar, implementar y supervisar acciones y programas a corto, mediano y largo plazo para la atención, habilitación, rehabilitación e integración social de las personas con discapacidad;\nV. Proponer las estrategias que promuevan la adecuada coordinación de las acciones que sean responsabilidad de cada uno los sectores público, social y privado en materia de discapacidad;\nVI. Impulsar acciones que fomenten la igualdad de las personas con discapacidad y el ejercicio pleno sus derechos, haciendo de su conocimiento los canales institucionales para hacerlos exigibles ante la autoridad competente;\nVII. Fomentar la cultura de igualdad, respeto y dignidad de las personas con discapacidad, a través de programas y campañas de prevención, educación y conciencia a la ciudadanía en general;\nVIII. Promover y garantizar la realización de programas de investigación y desarrollo tecnológico para beneficio de las personas con discapacidad, solicitando la participación de instituciones de educación superior, de investigación y tecnológicas;\nIX. Promover y vigilar la capacitación de funcionarios y servidores públicos en atención a las personas con discapacidad;\nX. Promover e incentivar, la suscripción de convenios para que las organizaciones y empresas otorguen descuentos a personas con discapacidad en centros comerciales, transporte de pasajeros, farmacias y otros establecimientos;\nXI. Crear el Manual Estatal de Libre Acceso, que tiene por objetivo establecer públicas a fin de mejorar la atención de la población con discapacidad; impulsando mecanismos de evaluación y asesoría, de captación de queja ciudadanas; coadyuvando con las autoridades competentes de acuerdo a la normatividad vigente;\nXII. Promover la ocupación laboral y la capacitación para el trabajo de las personas con discapacidad, estimulando la concertación y la participación activa de los sectores público, privado y social;\nLey para las Personas con Discapacidad en el Estado de Baja California. Página 29\n.\nActualización Legislativa.\nÚltima reforma P.O. No. 13, Número Especial, 13-May-2025\nXIII. Impulsar y fomentar el deporte, la cultura física, la recreación y el sano esparcimiento de las personas con discapacidad;\nXIV. Proponer al Ejecutivo del Estado la inclusión en el Proyecto de Presupuesto de\nEgresos partidas para la aplicación y ejecución de los programas dirigidos a las personas con discapacidad;\nXV. Rendir un informe público anual sobre el cumplimiento de sus objetivos, y\nXVI. Expedir en tiempo y forma su Reglamento Interno.\nArtículo Reformado\nCAPÍTULO II\nDE SU INTEGRACIÓN Y FUNCIONAMIENTO\nARTÍCULO 38.- El Consejo estará integrado por las personas titulares de:\nI. Secretaría de Bienestar;\nFracción Reformada\nII. Secretaría de Economía e Innovación;\nFracción Reformada\nIII. Sistema Estatal para el Desarrollo Integral de la Familia;\nIV. Secretaría de Salud;\nV. Secretaría de Educación;\nFracción Reformada\nVI. Secretaría del Trabajo y Previsión Social;\nVII. Secretaría de Infraestructura, Desarrollo Urbano y Reordenación Territorial;\nFracción Reformada\nVIII. Secretaría de Inclusión Social e Igualdad de Género; y,\nFracción Adicionada, recorriéndose la subsecuente\nIX. Fiscalía General del Estado.\nFracción Reformada\nArtículo Reformado\nARTÍCULO 39.- Además de los mencionados en el numeral anterior, el Consejo estará integrado por 9 representantes de la sociedad civil cuyo objeto sea la atención de las personas con discapacidad, las cuales deberán ser uno por cada Consejo Consultivo\nMunicipal, un experto por cada una de las cuatro de las discapacidades reconocidas en la\nClasificación Nacional de Discapacidades, con por lo menos cinco años de experiencia en el estudio o atención a personas con discapacidad, y un representante de la Comisión Estatal\nLey para las Personas con Discapacidad en el Estado de Baja California. Página 30\n.\nActualización Legislativa.\nÚltima reforma P.O. No. 13, Número Especial, 13-May-2025 de los Derechos Humanos, cuyo cargo tendrá una duración de tres años con la posibilidad ser ratificados hasta por otro periodo igual.\nArtículo Reformado\nARTÍCULO 40.- Los integrantes propietarios del sector público podrán designar suplentes, quienes deberán tener un nivel mínimo de Director.\nARTÍCULO 41.- El cargo de integrante del Consejo es honorífico, por lo que no recibirán retribución, emolumento, ni compensación alguna por su desempeño.\nARTÍCULO 42.- Los integrantes del Consejo cuentan con voz y voto para formar parte de las resoluciones o acuerdos que emita el mismo.\nARTÍCULO 43.- Los acuerdos del consejo se tomarán por mayoría de votos de los miembros presentes, teniendo el Presidente del Consejo voto de calidad en caso de empate.\nARTÍCULO 44.- El Consejo sesionará ordinariamente, por lo menos cada dos meses y extraordinariamente en cualquier tiempo a solicitud de su Presidente o de la mayoría de sus miembros, teniendo la obligación de informar a todos los miembros del Consejo sobre el contenido de las sesiones.\nArtículo Reformado\nARTÍCULO 45.- El Consejo determinará las ciudades sede para sesionar, tomando en cuenta el principio de equidad y empleando las instalaciones que para tal efecto proporcione la Secretaría de Bienestar.\nArtículo Reformado\nARTÍCULO 46.- Para la validez de las reuniones se requerirá de la asistencia de por lo menos la mitad más uno de total de los miembros del Consejo.\nArtículo Reformado\nARTÍCULO 47.- El Consejo podrá invitar a las sesiones ordinarias o extraordinarias que realice, a dos representantes de organizaciones sociales de reconocido prestigio y amplia representatividad en el ámbito de las personas con discapacidad, las cuales contarán con voz, pero sin voto, atendiendo al tema que se vaya a desarrollar.\nARTÍCULO 48.- El Presidente, Coordinador, Secretario Técnico y demás miembros, asignen en el Reglamento Interno del Consejo.\nARTÍCULO 49.- El Consejo será presidido por el Titular de la Secretaría de Salud.\nLos integrantes contarán con suplentes, quienes deberán tener un nivel mínimo de\nSubsecretario o Director General o su equivalente, teniendo como funciones y obligaciones siguientes:\nPresidir las sesiones del Consejo;\nLey para las Personas con Discapacidad en el Estado de Baja California. Página 31\n.\nActualización Legislativa.\nÚltima reforma P.O. No. 13, Número Especial, 13-May-2025\nConducir y organizar el funcionamiento del Consejo;\nI. Supervisar que se cumpla con el objetivo del Consejo y que los acuerdos adoptados por el mismo no contravengan esta Ley;\nII. Impulsar activamente la celebración de los convenios que el Consejo determine, que sean necesarios para el cumplimiento de sus objetivos;\nIII. Presentar anualmente al gobernador del estado un informe de labores;\nIV. Convocar, previo acuerdo con el Coordinador Estatal del Consejo, a la celebración de las sesiones ordinarias y extraordinarias, y\nV. Las demás que le encomiende el Gobernador del Estado.\nArtículo Reformado\nARTÍCULO 50.- El consejo contará con un coordinador que será uno de los integrantes expertos de la sociedad civil, cuyo cargo será rotativo para el resto de los expertos participantes y tendrá una vigencia que durará un año prorrogable al plazo que determinen los miembros en su conjunto, y tendrá las siguientes funciones:\nI. Presentar a consideración del Consejo propuestas de programas necesarios para el cumplimiento de los objetivos del Consejo;\nII. Presentar al Consejo el informe de las actividades realizadas y los resultados obtenidos;\nIII. Convocar a los integrantes del consejo, previo acuerdo con el Presidente, a la celebración de las sesiones extraordinarias, y\nIV. Las demás que le confiera el Presidente del Consejo.\nArtículo Reformado\nARTÍCULO 51.- El Presidente designara y removerá libremente a quien fungirá como\nSecretario Técnico del Consejo, quien tendrá las siguientes funciones:\nI.- Someter a consideración del coordinador del Consejo el programa anual de trabajo;\nII.- Coordinar los trabajos que corresponda desarrollar a las comisiones;\nIII.- Presentar al Coordinador del Consejo las propuestas que resulten de los trabajos y estudios realizados por las comisiones;\nIV.- Dar seguimiento a los acuerdos adoptados por el Consejo e informar periódicamente a éste el cumplimiento y ejecución de los mismos, y\nLey para las Personas con Discapacidad en el Estado de Baja California. Página 32\n.\nActualización Legislativa.\nÚltima reforma P.O. No. 13, Número Especial, 13-May-2025\nV.-Las demás que le asigne el Consejo.\nARTÍCULO 52.- El Consejo podrá determinar la creación de comisiones, tanto de carácter permanente como transitorio, según lo estime conveniente, para el estudio y solución de los asuntos específicos relacionados con su objeto. La integración de cada una de las comisiones, así como su organización y funcionamiento, se sujetarán a lo que disponga el Reglamento Interno Del Consejo.\nARTÍCULO 53.- El Consejo se regirá en lo que hace a su organización, estructura y funcionamiento, además de lo dispuesto por la Ley, por lo que establezca el reglamento que se expida para tal efecto.\nARTÍCULO 53 BIS.- El Consejo se apoyará del Subcomité Especial de Asistencia\nSocial para Personas con Discapacidad, para la acreditación de perros de asistencia utilizados en el Estado.\nArtículo Adicionado\nCAPÍTULO III\nDEL ACCESO A ESPACIOS PÚBLICOS A PERSONAS CON DISCAPACIDAD\nACOMPAÑADOS DE PERROS DE ASISTENCIA\nCapítulo Adicionado\nARTÍCULO 54.- Toda persona con discapacidad tiene derecho al acceso, recorridos y permanencia junto a su perro de asistencia, en los espacios públicos, incluido el transporte público. El acceso del perro de asistencia a los espacios públicos que implique un pago de entrada o peaje, no implicará pago adicional para la persona con discapacidad, salvo que su movilización constituya la prestación de un servicio agregado.\nArtículo Reformado\nARTÍCULO 55.- Los perros de asistencia pueden ser clasificados de la siguiente manera:\nI. Perro guía: Aquel que es adiestrado para guiar a una persona con discapacidad visual o visual y auditiva;\nII. Perro de servicio: Aquel que es adiestrado para prestar ayuda en las actividades de la vida diaria, tanto al entorno privado como al entorno externo, a las personas con una discapacidad física;\nIII.Perro de señalización de sonidos: Aquel que es adiestrado para avisar a las procedencia;\nIV. Perro de aviso: Aquel que es adiestrado para dar una alerta médica a las personas que padecen enfermedades que puedan necesitar su servicio; y\nLey para las Personas con Discapacidad en el Estado de Baja California. Página 33\n.\nActualización Legislativa.\nÚltima reforma P.O. No. 13, Número Especial, 13-May-2025\nV. Perro para personas con autismo: Aquel que es adiestrado para cuidar de la integridad física, controlar situaciones de emergencia y guiar a la persona con este tipo de discapacidad.\nARTÍCULO 56.- El Comité reconocerá la acreditación de la condición de perro de asistencia siempre que su usuario demuestre que aquél:\nI. Está entrenado en un centro oficialmente autorizado para la práctica de perros de asistencia;\nII. Cumple la normatividad sanitaria vigente;\nIII. Está vinculado a la asistencia o auxilio de la persona que lo usa para los fines previstos en la presente Ley; y\nIV. Contribuye a disminuir los efectos de la discapacidad de su usuario.\nArtículo Reformado\nARTÍCULO 57.- El reconocimiento de la condición de perro de asistencia se mantendrá durante toda su vida y sólo perderá dicha condición cuando se presenten las causas que establezca el Reglamento de esta Ley. La pérdida de la condición de perro de asistencia será declarada por el Comité, el cual procederá a la revocación de la acreditación.\nARTÍCULO 58.- Los perros de asistencia serán identificados mediante la colocación, en lugar visible, del distintivo que les otorgue el Comité.\nARTÍCULO 59.- El usuario del perro de asistencia, previo requerimiento, deberá exhibir la identificación expedida por el Comité que lo acredite como la persona autorizada para el uso del mismo, así como la documentación que acredite las condiciones sanitarias siguientes:\nI. Inspección veterinaria anual en la cual se demuestre que el perro de asistencia no padece ninguna enfermedad transmisible al hombre; y\nII. Cartilla de vacunación del perro de asistencia.\nARTÍCULO 60.- El usuario del perro de asistencia no podrá ejercitar los derechos reconocidos en esta Ley, cuando:\nI. Se trate de situaciones de grave peligro inminente para el usuario, para terceras personas o para el propio perro de asistencia;\nII. El animal presente síntomas visibles de enfermedad o heridas que por su tamaño o aspecto supongan un presumible riesgo para las personas; o\nIII. Se evidencie la falta de aseo o de atención respecto del animal.\nLey para las Personas con Discapacidad en el Estado de Baja California. Página 34\n.\nActualización Legislativa.\nÚltima reforma P.O. No. 13, Número Especial, 13-May-2025\nARTÍCULO 61.- El poseedor de un perro de asistencia deberá cumplir con las obligaciones que señala la normatividad vigente en la materia y, en particular, con las siguientes:\nI. Mantener al perro a su lado, con la correa y arnés que en su caso sea necesario, en los espacios y transportes a que se refiere esta Ley;\nII. Utilizar al perro de asistencia para aquellas funciones para las que fue entrenado, atendiendo siempre a las normas de higiene y seguridad en los lugares públicos, en la medida en que su discapacidad lo permita;\nIII. Garantizar el adecuado nivel de bienestar e higiene del perro de asistencia, a efecto de proporcionarle una buena calidad de vida; y\nIV. Tratándose de vehículos de alquiler, mantener al perro de asistencia, preferentemente, en la parte trasera del vehículo, a los pies de la persona con discapacidad.\nNo obstante, se podrán ocupar asientos delanteros, teniendo el perro de asistencia a sus pies, especialmente en los trayectos de largo recorrido.\nARTÍCULO 62.- El incumplimiento de lo dispuesto con relación al libre acceso de personas con discapacidad y sus perros de asistencia a los espacios públicos mencionados, será sancionado en los términos de esta Ley.\nCAPÍTULO IV\nGOBIERNO INCLUYENTE\nCapítulo Adicionado\nARTÍCULO 62 BIS.- Las autoridades señaladas en las fracciones I, II, III y IV del artículo 7 de esta Ley, contarán con al menos un módulo de atención y orientación para personas con discapacidad, en aquellas ciudades donde tengan presencia de servicios y que corresponda a su jurisdicción. Dicho módulo contará con el personal humano debidamente capacitado en Lengua de Señas Mexicanas y en el contenido de la presente\nLey.\nArtículo Adicionado\nTÍTULO CUARTO\nDE LA RESPONSABILIDAD Y SANCIONES DE LOS SERVIDORES PÚBLICOS\nDenominación del Título modificada\nCAPÍTULO PRIMERO\nDE LOS SERVIDORES PÚBLICOS\nDenominación del Capítulo modificada\nARTÍCULO 63.- Las y los servidores públicos de las Dependencias y Entidades mencionados en el artículo 7 de la presente Ley, deberán de tratar con respeto, dignidad, intervención en virtud de las funciones establecidas en la presente Ley. Así mismo, deberán de ejercitar los Planes, Programas y Presupuestos realizados conforme a la Ley de\nPresupuesto aplicable.\nLey para las Personas con Discapacidad en el Estado de Baja California. Página 35\n.\nActualización Legislativa.\nÚltima reforma P.O. No. 13, Número Especial, 13-May-2025\nPárrafo Reformado\nDe igual forma las dependencias y entidades a que se refiere la presente Ley y que proporcionen servicios al público en general, destinarán una ventanilla de atención preferente para las personas con discapacidad.\nPárrafo Adicionado\nArtículo Reformado\nARTÍCULO 64.- Ante el incumplimiento a lo establecido en la presente Ley, la persona con discapacidad podrá acudir a la Secretaría de la Honestidad y la Función\nPública, o bien ante el órgano interno de control que corresponda, a interponer el procedimiento disciplinario que corresponda, en los términos de la Ley de\nResponsabilidades Administrativas del Estado de Baja California.\nArtículo Reformado\nCAPÍTULO SEGUNDO\nSANCIONES DE LOS SERVIDORES PÚBLICOS\nCapítulo Adicionado\nARTÍCULO 65.- Las sanciones administrativas que imponga la Sindicatura, la\nSecretaría de la Honestidad y Función Pública, los Órganos Internos de Control, el Tribunal\nSuperior de Justicia, el Consejo de la Judicatura del Estado, el Tribunal Estatal de Justicia\nAdministrativa a los Servidores Públicos derivado de los procedimientos por la comisión de faltas administrativas graves, consistirán en:\nI. Suspensión del empleo, cargo o comisión.\nII. Destitución del empleo, cargo o comisión.\nIII. Sanción económica.\nIV. Inhabilitación temporal para desempeñar empleos, cargos o comisiones en el servicio público.\nArtículo Adicionado\nTRANSITORIOS\nARTÍCULO PRIMERO.- La presente Ley entrará en vigor al día siguiente de su publicación en el Periódico Oficial del Estado.\nARTÍCULO SEGUNDO.- Se abroga la Ley Para el Desarrollo Integral de Personas con Capacidades Diferentes para el Estado de Baja California, Publicada en el Periódico\nARTÍCULO TERCERO.- El Ejecutivo del Estado vigilara que la creación del Consejo\nConsultivo para Personas con Discapacidad del Estado, no exceda un plazo mayor de ciento ochenta días contados a partir de la entrada en vigor de la presente Ley.\nLey para las Personas con Discapacidad en el Estado de Baja California. Página 36\n.\nActualización Legislativa.\nÚltima reforma P.O. No. 13, Número Especial, 13-May-2025\nARTÍCULO CUARTO.- El Ejecutivo publicará y sancionará el Reglamento Interno del\nConsejo Consultivo para Personas con Discapacidad del Estado.\nARTÍCULO QUINTO.- El Ejecutivo del Estado y los Ayuntamientos tendrán un plazo de ciento ochenta días contados a partir de la entrada en vigor de la presente Ley, para adecuar su normatividad en el ámbito de su competencia.\nARTÍCULO SEXTO.- Las dependencias o entidades de Gobierno previstas en la presente Ley, deberán de establecer en el presupuesto de Egresos del ejercicio presupuestal inmediato siguiente a la publicación de la presente Ley, las necesidades presupuéstales en los programas respectivos para dar cumplimiento a las atribuciones y obligaciones previstas en la misma.\nDADO en el Salón de Sesiones “Lic. Benito Juárez García” del H. Poder Legislativo del Estado de Baja California, en la Ciudad de Mexicali, B.C., a los veintinueve días del mes de septiembre del año dos mil diez.\nDIP. JUAN MANUEL GASTÉLUM BUENROSTRO\nPRESIDENTE\n(RÚBRICA)\nDIP. CARLOS ALONSO ANGULO RENTERIA\nSECRETARIO\n(RÚBRICA)\nDE CONFORMIDAD CON LO DISPUESTO POR LA FRACCION I DEL ARTÍCULO 49\nMEXICALI, BAJA CALIFORNIA, A LOS OCHO DÍAS DEL MES DE OCTUBRE DEL\nAÑO DOS MIL DIEZ.\nGOBERNADOR DEL ESTADO\nJOSE GUADALUPE OSUNA MILLAN\n(RÚBRICA)\nSECRETARIO GENERAL DE GOBIERNO\nCUAUHTEMOC CARDONA BENAVIDES\n(RÚBRICA)\nLey para las Personas con Discapacidad en el Estado de Baja California. Página 37\n.\nActualización Legislativa.\nÚltima reforma P.O. No. 13, Número Especial, 13-May-2025\nARTÍCULO 1.- Fue adicionado mediante Decreto No. 190, publicado en el Periódico\nOficial No. 09, de fecha 23 de febrero de 2018, Tomo CXXV, Sección III, expedido por la H.\nXXII Legislatura, siendo Gobernador Constitucional el C. Francisco Arturo Vega de Lamadrid\n2013-2019;\nARTÍCULO 2.- Fue reformado mediante Decreto No. 155, publicado en el Periódico\nOficial No. 2, de fecha 06 de enero de 2012, Tomo CXIX, Sección II, expedido por la H. XX\nLegislatura, siendo Gobernador Constitucional el C. José Guadalupe Osuna Millán 20072013; fue reformado mediante Decreto No. 200, publicado en el Periódico Oficial No. 6, de fecha 27 de enero de 2023, Tomo CXXX, Índice, expedido por la H. XXIV Legislatura, siendo\nGobernadora Constitucional la C. Marina del Pilar Ávila Olmeda 2021-2027; fue reformado mediante Decreto No. 92, publicado en el Periódico Oficial No. 30, Número Especial, de fecha 13 de mayo de 2025, Tomo CXXXII, expedido por la H. XXV Legislatura, siendo\nGobernadora Constitucional la C. Marina del Pilar Ávila Olmeda 2021-2027;\nARTÍCULO 3.- Fue reformado mediante Decreto No. 155, publicado en el Periódico\nOficial No. 2, de fecha 06 de enero de 2012, Tomo CXIX, Sección II, expedido por la H. XX\nLegislatura, siendo Gobernador Constitucional el C. José Guadalupe Osuna Millán 20072013; fue reformado mediante Decreto No. 496, publicado en el Periódico Oficial No. 32, de fecha 15 de julio de 2016, Tomo CXXIII, Sección IV, expedido por la H. XXI Legislatura, siendo Gobernador Constitucional el C. Francisco Arturo Vega de Lamadrid 2013-2019; fue adicionado mediante Decreto No. 190, publicado en el Periódico Oficial No. 09, de fecha 23 de febrero de 2018, Tomo CXXV, Sección III, expedido por la H. XXII Legislatura, siendo\nGobernador Constitucional el C. Francisco Arturo Vega de Lamadrid 2013-2019; fue reformado mediante Decreto No. 215, publicado en el Periódico Oficial No. 7, de fecha 01 de febrero de 2019, Tomo CXXVI, Sección IV, expedido por la H. XXII Legislatura, siendo\nGobernador Constitucional el C. Francisco Arturo Vega de Lamadrid 2013-2019; fue reformado mediante Decreto No. 81, publicado en el Periódico Oficial No. 17, de fecha 04 de marzo de 2022, Tomo CXXIX, Sección I, expedido por la H. XXIV Legislatura, siendo\nGobernadora Constitucional la C. Marina del Pilar Ávila Olmeda 2021-2027; fue reformado mediante Decreto No. 92, publicado en el Periódico Oficial No. 30, Número Especial, de fecha 13 de mayo de 2025, Tomo CXXXII, expedido por la H. XXV Legislatura, siendo\nGobernadora Constitucional la C. Marina del Pilar Ávila Olmeda 2021-2027;\nARTÍCULO 4.- Fue reformado mediante Decreto No. 155, publicado en el Periódico\nLegislatura, siendo Gobernador Constitucional el C. José Guadalupe Osuna Millán 20072013;\nARTÍCULO 4 BIS.- Fue adicionado mediante Decreto No. 92, publicado en el expedido por la H. XXV Legislatura, siendo Gobernadora Constitucional la C. Marina del\nPilar Ávila Olmeda 2021-2027;\nARTÍCULO 5.- Fue reformado mediante Decreto No. 155, publicado en el Periódico\nLey para las Personas con Discapacidad en el Estado de Baja California. Página 38\n.\nActualización Legislativa.\nÚltima reforma P.O. No. 13, Número Especial, 13-May-2025\nLegislatura, siendo Gobernador Constitucional el C. José Guadalupe Osuna Millán 20072013; fue reformado mediante Decreto No. 496, publicado en el Periódico Oficial No. 32, de fecha 15 de julio de 2016, Tomo CXXIII, Sección IV, expedido por la H. XXI Legislatura, siendo Gobernador Constitucional el C. Francisco Arturo Vega de Lamadrid 2013-2019;\nARTÍCULO 6.- Fue reformado mediante Decreto No. 155, publicado en el Periódico\nOficial No. 2, de fecha 06 de enero de 2012, Tomo CXIX, Sección II, expedido por la H. XX\nLegislatura, siendo Gobernador Constitucional el C. José Guadalupe Osuna Millán 20072013; fue reformado mediante Decreto No. 92, publicado en el Periódico Oficial No. 30, Número Especial, de fecha 13 de mayo de 2025, Tomo CXXXII, expedido por la H. XXV\nLegislatura, siendo Gobernadora Constitucional la C. Marina del Pilar Ávila Olmeda 20212027;\nARTÍCULO 6 BIS.- Fue reformado mediante Decreto No. 155, publicado en el\nPeriódico Oficial No. 2, de fecha 06 de enero de 2012, Tomo CXIX, Sección II, expedido por la H. XX Legislatura, siendo Gobernador Constitucional el C. José Guadalupe Osuna Millán\n2007-2013;\nFue adicionado mediante Decreto No. 190, publicado en el Periódico Oficial No. 09, de fecha 23 de febrero de 2018, Tomo CXXV, Sección III, expedido por la H. XXII\nLegislatura, siendo Gobernador Constitucional el C. Francisco Arturo Vega de Lamadrid\n2013-2019;\nCAPÍTULO III\nDE LA PERSONALIDAD JURÍDICA\nARTÍCULO 6 TER.- Fue adicionado mediante Decreto No. 190, publicado en el\nPeriódico Oficial No. 09, de fecha 23 de febrero de 2018, Tomo CXXV, Sección III, expedido por la H. XXII Legislatura, siendo Gobernador Constitucional el C. Francisco Arturo Vega de\nLamadrid 2013-2019;\nARTÍCULO 6 QUARTER.- Fue adicionado mediante Decreto No. 190, publicado en el\nPeriódico Oficial No. 09, de fecha 23 de febrero de 2018, Tomo CXXV, Sección III, expedido por la H. XXII Legislatura, siendo Gobernador Constitucional el C. Francisco Arturo Vega de\nLamadrid 2013-2019;\nARTÍCULO 6 QUIQUIES.- Fue adicionado mediante Decreto No. 190, publicado en el\nPeriódico Oficial No. 09, de fecha 23 de febrero de 2018, Tomo CXXV, Sección III, expedido por la H. XXII Legislatura, siendo Gobernador Constitucional el C. Francisco Arturo Vega de\nLamadrid 2013-2019; fue reformado mediante Decreto No. 200, publicado en el Periódico\nLegislatura, siendo Gobernadora Constitucional la C. Marina del Pilar Ávila Olmeda 20212027;\nARTÍCULO 6 SEXIES.- Fue adicionado mediante Decreto No. 190, publicado en el por la H. XXII Legislatura, siendo Gobernador Constitucional el C. Francisco Arturo Vega de\nLamadrid 2013-2019;\nLey para las Personas con Discapacidad en el Estado de Baja California. Página 39\n.\nActualización Legislativa.\nÚltima reforma P.O. No. 13, Número Especial, 13-May-2025\nFue adicionado este Capítulo IV mediante Decreto No. 92, publicado en el Periódico Oficial\nNo. 30, Número Especial, de fecha 13 de mayo de 2025, Tomo CXXXII, expedido por la H.\nXXV Legislatura, siendo Gobernadora Constitucional la C. Marina del Pilar Ávila Olmeda\n2021-2027;\nCAPÍTULO IV\nDE LA ATENCIÓN INTEGRAL\nARTÍCULO 6 SEPTIES.- Fue adicionado mediante Decreto No. 92, publicado en el\nPeriódico Oficial No. 30, Número Especial, de fecha 13 de mayo de 2025, Tomo CXXXII, expedido por la H. XXV Legislatura, siendo Gobernadora Constitucional la C. Marina del\nPilar Ávila Olmeda 2021-2027;\nARTÍCULO 7.- Fue reformado mediante Decreto No. 155, publicado en el Periódico\nOficial No. 2, de fecha 06 de enero de 2012, Tomo CXIX, Sección II, expedido por la H. XX\nLegislatura, siendo Gobernador Constitucional el C. José Guadalupe Osuna Millán 20072013; fue reformado mediante Decreto No. 359, publicado en el Periódico Oficial No. 53, de fecha 20 de noviembre de 2015, Tomo CXXII, Sección I, expedido por la H. XXI Legislatura, siendo Gobernador Constitucional el C. Francisco Arturo Vega de Lamadrid 2013-2019; fue reformado mediante Decreto No. 190, publicado en el Periódico Oficial No. 09, de fecha 23 de febrero de 2018, Tomo CXXV, Sección III, expedido por la H. XXII Legislatura, siendo\nGobernador Constitucional el C. Francisco Arturo Vega de Lamadrid 2013-2019; fue reformado mediante Decreto No. 75, publicado en el Periódico Oficial No. 11, de fecha 11 de febrero de 2022, Tomo CXXIX, Sección IV, expedido por la H. XXIV Legislatura, siendo\nGobernadora Constitucional la C. Marina del Pilar Ávila Olmeda 2021-2027; fue reformado mediante Decreto No. 92, publicado en el Periódico Oficial No. 30, Número Especial, de fecha 13 de mayo de 2025, Tomo CXXXII, expedido por la H. XXV Legislatura, siendo\nGobernadora Constitucional la C. Marina del Pilar Ávila Olmeda 2021-2027;\nARTÍCULO 7 BIS.- Fue reformado mediante Decreto No. 155, publicado en el\nPeriódico Oficial No. 2, de fecha 06 de enero de 2012, Tomo CXIX, Sección II, expedido por la H. XX Legislatura, siendo Gobernador Constitucional el C. José Guadalupe Osuna Millán\n2007-2013; fue reformado mediante Decreto No. 92, publicado en el Periódico Oficial No. 30, Número Especial, de fecha 13 de mayo de 2025, Tomo CXXXII, expedido por la H. XXV\nLegislatura, siendo Gobernadora Constitucional la C. Marina del Pilar Ávila Olmeda 20212027;\nARTÍCULO 8.- Fue reformado mediante Decreto No. 155, publicado en el Periódico\nLegislatura, siendo Gobernador Constitucional el C. José Guadalupe Osuna Millán 20072013; fue reformado mediante Decreto No. 496, publicado en el Periódico Oficial No. 32, de siendo Gobernador Constitucional el C. Francisco Arturo Vega de Lamadrid 2013-2019; fue reformado mediante Decreto No. 215, publicado en el Periódico Oficial No. 7, de fecha 01 de\nGobernador Constitucional el C. Francisco Arturo Vega de Lamadrid 2013-2019; fue reformado mediante Decreto No. 92, publicado en el Periódico Oficial No. 30, Número\nLey para las Personas con Discapacidad en el Estado de Baja California. Página 40\n.\nActualización Legislativa.\nÚltima reforma P.O. No. 13, Número Especial, 13-May-2025\nEspecial, de fecha 13 de mayo de 2025, Tomo CXXXII, expedido por la H. XXV Legislatura, siendo Gobernadora Constitucional la C. Marina del Pilar Ávila Olmeda 2021-2027;\nARTÍCULO 8 BIS.- Fue reformado mediante Decreto No. 155, publicado en el\nPeriódico Oficial No. 2, de fecha 06 de enero de 2012, Tomo CXIX, Sección II, expedido por la H. XX Legislatura, siendo Gobernador Constitucional el C. José Guadalupe Osuna Millán\n2007-2013;\nARTÍCULO 9.- Fue reformado mediante Decreto No. 155, publicado en el Periódico\nOficial No. 2, de fecha 06 de enero de 2012, Tomo CXIX, Sección II, expedido por la H. XX\nLegislatura, siendo Gobernador Constitucional el C. José Guadalupe Osuna Millán 20072013; fue reformado mediante Decreto No. 92, publicado en el Periódico Oficial No. 30, Número Especial, de fecha 13 de mayo de 2025, Tomo CXXXII, expedido por la H. XXV\nLegislatura, siendo Gobernadora Constitucional la C. Marina del Pilar Ávila Olmeda 20212027;\nARTÍCULO 10.- Fue reformado mediante Decreto No. 155, publicado en el Periódico\nOficial No. 2, de fecha 06 de enero de 2012, Tomo CXIX, Sección II, expedido por la H. XX\nLegislatura, siendo Gobernador Constitucional el C. José Guadalupe Osuna Millán 20072013;\nFue modificada la denominación de este Capítulo mediante Decreto No. 75, publicado en el\nPeriódico Oficial No. 11, de fecha 11 de febrero de 2022, Tomo CXXIX, Sección IV, expedido por la H. XXIV Legislatura, siendo Gobernadora Constitucional la C. Marina del Pilar Ávila\nOlmeda 2021-2027;\nCAPÍTULO III\nDE LA SECRETARÍA DE EDUCACIÓN\nARTÍCULO 12.- Fue reformado mediante Decreto No. 155, publicado en el Periódico\nOficial No. 2, de fecha 06 de enero de 2012, Tomo CXIX, Sección II, expedido por la H. XX\nLegislatura, siendo Gobernador Constitucional el C. José Guadalupe Osuna Millán 20072013; fue reformado mediante Decreto No. 75, publicado en el Periódico Oficial No. 11, de fecha 11 de febrero de 2022, Tomo CXXIX, Sección IV, expedido por la H. XXIV Legislatura, siendo Gobernadora Constitucional la C. Marina del Pilar Ávila Olmeda 2021-2027;\nARTÍCULO 13.- Fue reformado mediante Decreto No. 155, publicado en el Periódico\nOficial No. 2, de fecha 06 de enero de 2012, Tomo CXIX, Sección II, expedido por la H. XX\nLegislatura, siendo Gobernador Constitucional el C. José Guadalupe Osuna Millán 20072013;\nARTÍCULO 14.- Fue reformado mediante Decreto No. 155, publicado en el Periódico\nLegislatura, siendo Gobernador Constitucional el C. José Guadalupe Osuna Millán 20072013;\nARTÍCULO 15.- Fue reformado mediante Decreto No. 155, publicado en el Periódico\nLegislatura, siendo Gobernador Constitucional el C. José Guadalupe Osuna Millán 2007Ley para las Personas con Discapacidad en el Estado de Baja California. Página 41\n.\nActualización Legislativa.\nÚltima reforma P.O. No. 13, Número Especial, 13-May-2025\n2013; fue reformado mediante Decreto No. 190, publicado en el Periódico Oficial No. 09, de fecha 23 de febrero de 2018, Tomo CXXV, Sección III, expedido por la H. XXII Legislatura, siendo Gobernador Constitucional el C. Francisco Arturo Vega de Lamadrid 2013-2019; fue reformado mediante Decreto No. 215, publicado en el Periódico Oficial No. 7, de fecha 01 de febrero de 2019, Tomo CXXVI, Sección IV, expedido por la H. XXII Legislatura, siendo\nGobernador Constitucional el C. Francisco Arturo Vega de Lamadrid 2013-2019; fue reformado mediante Decreto No. 75, publicado en el Periódico Oficial No. 11, de fecha 11 de febrero de 2022, Tomo CXXIX, Sección IV, expedido por la H. XXIV Legislatura, siendo\nGobernadora Constitucional la C. Marina del Pilar Ávila Olmeda 2021-2027;\nARTÍCULO 16.- Fue reformado mediante Decreto No. 155, publicado en el Periódico\nOficial No. 2, de fecha 06 de enero de 2012, Tomo CXIX, Sección II, expedido por la H. XX\nLegislatura, siendo Gobernador Constitucional el C. José Guadalupe Osuna Millán 20072013;\nARTÍCULO 18.- Fue reformado mediante Decreto No. 155, publicado en el Periódico\nOficial No. 2, de fecha 06 de enero de 2012, Tomo CXIX, Sección II, expedido por la H. XX\nLegislatura, siendo Gobernador Constitucional el C. José Guadalupe Osuna Millán 20072013;\nFue modificada la denominación de este Capítulo mediante Decreto No. 75, publicado en el\nPeriódico Oficial No. 11, de fecha 11 de febrero de 2022, Tomo CXXIX, Sección IV, expedido por la H. XXIV Legislatura, siendo Gobernadora Constitucional la C. Marina del Pilar Ávila\nOlmeda 2021-2027;\nCAPÍTULO V\nDE LA SECRETARÍA DE INFRAESTRUCTURA, DESARROLLO URBANO Y\nREORDENACIÓN TERRITORIAL, Y DE LOS AYUNTAMIENTOS EN MATERIA DE\nDESARROLLO URBANO\nARTÍCULO 19.- Fue reformado mediante Decreto No. 155, publicado en el Periódico\nOficial No. 2, de fecha 06 de enero de 2012, Tomo CXIX, Sección II, expedido por la H. XX\nLegislatura, siendo Gobernador Constitucional el C. José Guadalupe Osuna Millán 20072013; fue reformado mediante Decreto No. 81, publicado en el Periódico Oficial No. 17, de fecha 04 de marzo de 2022, Tomo CXXIX, Sección I, expedido por la H. XXIV Legislatura, siendo Gobernadora Constitucional la C. Marina del Pilar Ávila Olmeda 2021-2027; fue reformado mediante Decreto No. 255, publicado en el Periódico Oficial No. 45, de fecha 28\nGobernadora Constitucional la C. Marina del Pilar Ávila Olmeda 2021-2027;\nARTÍCULO 20.- Fue reformado mediante Decreto No. 155, publicado en el Periódico\nLegislatura, siendo Gobernador Constitucional el C. José Guadalupe Osuna Millán 20072013; fue reformado mediante Decreto No. 75, publicado en el Periódico Oficial No. 11, de siendo Gobernadora Constitucional la C. Marina del Pilar Ávila Olmeda 2021-2027;\nLey para las Personas con Discapacidad en el Estado de Baja California. Página 42\n.\nActualización Legislativa.\nÚltima reforma P.O. No. 13, Número Especial, 13-May-2025\nARTÍCULO 21.- Fue reformado mediante Decreto No. 155, publicado en el Periódico\nOficial No. 2, de fecha 06 de enero de 2012, Tomo CXIX, Sección II, expedido por la H. XX\nLegislatura, siendo Gobernador Constitucional el C. José Guadalupe Osuna Millán 20072013;\nARTÍCULO 23.- Fue reformado mediante Decreto No. 155, publicado en el Periódico\nOficial No. 2, de fecha 06 de enero de 2012, Tomo CXIX, Sección II, expedido por la H. XX\nLegislatura, siendo Gobernador Constitucional el C. José Guadalupe Osuna Millán 20072013;\nARTÍCULO 23 BIS.- Fue adicionado mediante Decreto No. 92, publicado en el\nPeriódico Oficial No. 30, Número Especial, de fecha 13 de mayo de 2025, Tomo CXXXII, expedido por la H. XXV Legislatura, siendo Gobernadora Constitucional la C. Marina del\nPilar Ávila Olmeda 2021-2027;\nARTÍCULO 23 TER.- Fue adicionado mediante Decreto No. 92, publicado en el\nPeriódico Oficial No. 30, Número Especial, de fecha 13 de mayo de 2025, Tomo CXXXII, expedido por la H. XXV Legislatura, siendo Gobernadora Constitucional la C. Marina del\nPilar Ávila Olmeda 2021-2027;\nARTÍCULO 24.- Fue reformado mediante Decreto No. 155, publicado en el Periódico\nOficial No. 2, de fecha 06 de enero de 2012, Tomo CXIX, Sección II, expedido por la H. XX\nLegislatura, siendo Gobernador Constitucional el C. José Guadalupe Osuna Millán 20072013;\nARTÍCULO 25.- Fue reformado mediante Decreto No. 155, publicado en el Periódico\nOficial No. 2, de fecha 06 de enero de 2012, Tomo CXIX, Sección II, expedido por la H. XX\nLegislatura, siendo Gobernador Constitucional el C. José Guadalupe Osuna Millán 20072013; fue reformado mediante Decreto No. 330, publicado en el Periódico Oficial No. 70, de fecha 08 de diciembre de 2023, Sección I, Tomo CXXX, expedido por la H. XXIV Legislatura, siendo Gobernadora Constitucional la C. Marina del Pilar Ávila Olmeda 2021-2027;\nARTÍCULO 26.- Fue reformado mediante Decreto No. 155, publicado en el Periódico\nOficial No. 2, de fecha 06 de enero de 2012, Tomo CXIX, Sección II, expedido por la H. XX\nLegislatura, siendo Gobernador Constitucional el C. José Guadalupe Osuna Millán 20072013;\nARTÍCULO 27.- Fue reformado mediante Decreto No. 155, publicado en el Periódico\nLegislatura, siendo Gobernador Constitucional el C. José Guadalupe Osuna Millán 20072013; fue reformado mediante Decreto No. 215, publicado en el Periódico Oficial No. 7, de siendo Gobernador Constitucional el C. Francisco Arturo Vega de Lamadrid 2013-2019;\nARTÍCULO 29.- Fue reformado mediante Decreto No. 155, publicado en el Periódico\nLegislatura, siendo Gobernador Constitucional el C. José Guadalupe Osuna Millán 20072013;\nLey para las Personas con Discapacidad en el Estado de Baja California. Página 43\n.\nActualización Legislativa.\nÚltima reforma P.O. No. 13, Número Especial, 13-May-2025\nARTÍCULO 31.- Fue reformado mediante Decreto No. 155, publicado en el Periódico\nOficial No. 2, de fecha 06 de enero de 2012, Tomo CXIX, Sección II, expedido por la H. XX\nLegislatura, siendo Gobernador Constitucional el C. José Guadalupe Osuna Millán 20072013;\nARTICULO 34.- Fue reformado mediante Decreto No. 457, publicado en el Periódico\nOficial No. 25, de fecha 31 de mayo de 2013, Sección I, Tomo CXX, expedido por la H. XX\nLegislatura, siendo Gobernador Constitucional el C. José Guadalupe Osuna Millán 20072013;\nARTÍCULO 35.- Fue reformado mediante Decreto No. 155, publicado en el Periódico\nOficial No. 2, de fecha 06 de enero de 2012, Tomo CXIX, Sección II, expedido por la H. XX\nLegislatura, siendo Gobernador Constitucional el C. José Guadalupe Osuna Millán 20072013; fue reformado mediante Decreto No. 215, publicado en el Periódico Oficial No. 7, de fecha 01 de febrero de 2019, Tomo CXXVI, Sección IV, expedido por la H. XXII Legislatura, siendo Gobernador Constitucional el C. Francisco Arturo Vega de Lamadrid 2013-2019;\nFue creado mediante Decreto No. 155, publicado en el Periódico Oficial No. 2, de fecha 06 de enero de 2012, Tomo CXIX, Sección II, expedido por la H. XX Legislatura, siendo\nGobernador Constitucional el C. José Guadalupe Osuna Millán 2007-2013;\nCAPÍTULO X\nFUNCIONES Y ATRIBUCIONES DE LA COMISIÓN ESTATAL DE LOS DERECHOS\nHUMANOS.\nARTÍCULO 35 BIS.- Fue adicionado mediante Decreto No. 155, publicado en el\nPeriódico Oficial No. 2, de fecha 06 de enero de 2012, Tomo CXIX, Sección II, expedido por la H. XX Legislatura, siendo Gobernador Constitucional el C. José Guadalupe Osuna Millán\n2007-2013; fue reformado mediante Decreto No. 359, publicado en el Periódico Oficial No.\n53, de fecha 20 de noviembre de 2015, Tomo CXXII, Sección I, expedido por la H. XXI\nLegislatura, siendo Gobernador Constitucional el C. Francisco Arturo Vega de Lamadrid\n2013-2019;\nARTÍCULO 36.- Fue reformado mediante Decreto No. 92, publicado en el Periódico\nOficial No. 30, Número Especial, de fecha 13 de mayo de 2025, Tomo CXXXII, expedido por la H. XXV Legislatura, siendo Gobernadora Constitucional la C. Marina del Pilar Ávila\nOlmeda 2021-2027;\nARTÍCULO 37.- Fue reformado mediante Decreto No. 155, publicado en el Periódico\nLegislatura, siendo Gobernador Constitucional el C. José Guadalupe Osuna Millán 20072013; fue reformado por Decreto No. 672, publicado en el Periódico Oficial No. 47, Sección\nGobernador Constitucional el C. Francisco Arturo Vega de Lamadrid 2013-2019;\nARTÍCULO 38.- Fue reformado mediante Decreto No. 75, publicado en el Periódico\nXXIV Legislatura, siendo Gobernadora Constitucional la C. Marina del Pilar Ávila Olmeda\nLey para las Personas con Discapacidad en el Estado de Baja California. Página 44\n.\nActualización Legislativa.\nÚltima reforma P.O. No. 13, Número Especial, 13-May-2025\n2021-2027; fue reformado mediante Decreto No. 172, publicado en el Periódico Oficial No.\n70, de fecha 02 de diciembre de 2022, Tomo CXXIX, Sección III, expedido por la H. XXIV\nLegislatura, siendo Gobernadora Constitucional la C. Marina del Pilar Ávila Olmeda 20212027;\nARTÍCULO 39.- Fue reformado mediante Decreto No. 155, publicado en el Periódico\nOficial No. 2, de fecha 06 de enero de 2012, Tomo CXIX, Sección II, expedido por la H. XX\nLegislatura, siendo Gobernador Constitucional el C. José Guadalupe Osuna Millán 20072013; fue reformado mediante Decreto No. 359, publicado en el Periódico Oficial No. 53, de fecha 20 de noviembre de 2015, Tomo CXXII, Sección I, expedido por la H. XXI Legislatura, siendo Gobernador Constitucional el C. Francisco Arturo Vega de Lamadrid 2013-2019;\nARTÍCULO 44.- Fue reformado mediante Decreto No. 155, publicado en el Periódico\nOficial No. 2, de fecha 06 de enero de 2012, Tomo CXIX, Sección II, expedido por la H. XX\nLegislatura, siendo Gobernador Constitucional el C. José Guadalupe Osuna Millán 20072013;\nARTÍCULO 45.- Fue reformado mediante Decreto No. 200, publicado en el Periódico\nOficial No. 6, de fecha 27 de enero de 2023, Tomo CXXX, Índice, expedido por la H. XXIV\nLegislatura, siendo Gobernadora Constitucional la C. Marina del Pilar Ávila Olmeda 20212027;\nARTÍCULO 46.- Fue reformado mediante Decreto No. 155, publicado en el Periódico\nOficial No. 2, de fecha 06 de enero de 2012, Tomo CXIX, Sección II, expedido por la H. XX\nLegislatura, siendo Gobernador Constitucional el C. José Guadalupe Osuna Millán 20072013;\nARTÍCULO 49.- Fue reformado mediante Decreto No. 155, publicado en el Periódico\nOficial No. 2, de fecha 06 de enero de 2012, Tomo CXIX, Sección II, expedido por la H. XX\nLegislatura, siendo Gobernador Constitucional el C. José Guadalupe Osuna Millán 20072013;\nARTÍCULO 50.- Fue reformado mediante Decreto No. 155, publicado en el Periódico\nOficial No. 2, de fecha 06 de enero de 2012, Tomo CXIX, Sección II, expedido por la H. XX\nLegislatura, siendo Gobernador Constitucional el C. José Guadalupe Osuna Millán 20072013;\nARTÍCULO 53 BIS.- Fue adicionado mediante Decreto No. 496, publicado en el por la H. XXI Legislatura, siendo Gobernador Constitucional el C. Francisco Arturo Vega de\nLamadrid 2013-2019;\nFue adicionado este Capítulo mediante Decreto No. 496, publicado en el Periódico Oficial\nLegislatura, siendo Gobernador Constitucional el C. Francisco Arturo Vega de Lamadrid\n2013-2019;\nCAPÍTULO III\nLey para las Personas con Discapacidad en el Estado de Baja California. Página 45\n.\nActualización Legislativa.\nÚltima reforma P.O. No. 13, Número Especial, 13-May-2025\nDEL ACCESO A ESPACIOS PÚBLICOS A PERSONAS CON DISCAPACIDAD\nACOMPAÑADOS DE PERROS DE ASISTENCIA\nARTICULO 54.- Fue reformado mediante Decreto No. 457, publicado en el Periódico\nOficial No. 25, de fecha 31 de mayo de 2013, Sección I, Tomo CXX, expedido por la H. XX\nLegislatura, siendo Gobernador Constitucional el C. José Guadalupe Osuna Millán 20072013; fue adicionado mediante Decreto No. 496, publicado en el Periódico Oficial No. 32, de fecha 15 de julio de 2016, Tomo CXXIII, Sección IV, expedido por la H. XXI Legislatura, siendo Gobernador Constitucional el C. Francisco Arturo Vega de Lamadrid 2013-2019;\nARTICULO 55.- Fue reformado mediante Decreto No. 496, publicado en el Periódico\nOficial No. 32, de fecha 15 de julio de 2016, Tomo CXXIII, Sección IV, expedido por la H. XXI\nLegislatura, siendo Gobernador Constitucional el C. Francisco Arturo Vega de Lamadrid\n2013-2019;\nTÍTULO TERCERO\nDEL CONSEJO CONSULTIVO PARA PERSONAS CON DISCAPACIDAD DEL ESTADO\nFue adicionado mediante Decreto No. 190, publicado en el Periódico Oficial No. 09, de fecha 23 de febrero de 2018, Tomo CXXV, Sección III, expedido por la H. XXII\nLegislatura, siendo Gobernador Constitucional el C. Francisco Arturo Vega de Lamadrid\n2013-2019;\nCAPÍTULO IV\nGOBIERNO INCLUYENTE\nARTICULO 62 BIS.- Fue adicionado mediante Decreto No. 190, publicado en el\nPeriódico Oficial No. 09, de fecha 23 de febrero de 2018, Tomo CXXV, Sección III, expedido por la H. XXII Legislatura, siendo Gobernador Constitucional el C. Francisco Arturo Vega de\nLamadrid 2013-2019;\nTÍTULO CUARTO\nCAPÍTULO ÚNICO\nDE LOS SERVIDORES PÚBLICOS\nFue modificada la denominación de este Título mediante Decreto No. 200, publicado en el\nH. XXIV Legislatura, siendo Gobernadora Constitucional la C. Marina del Pilar Ávila Olmeda\n2021-2027;\nTÍTULO CUARTO\nLey para las Personas con Discapacidad en el Estado de Baja California. Página 46\n.\nActualización Legislativa.\nÚltima reforma P.O. No. 13, Número Especial, 13-May-2025\nFue modificada la denominación de este Capítulo Primero mediante Decreto No. 200, publicado en el Periódico Oficial No. 6, de fecha 27 de enero de 2023, Tomo CXXX, Índice, expedido por la H. XXIV Legislatura, siendo Gobernadora Constitucional la C. Marina del\nPilar Ávila Olmeda 2021-2027;\nCAPÍTULO PRIMERO\nDE LOS SERVIDORES PÚBLICOS\nARTÍCULO 63.- Fue reformado mediante Decreto No. 200, publicado en el Periódico\nOficial No. 6, de fecha 27 de enero de 2023, Tomo CXXX, Índice, expedido por la H. XXIV\nLegislatura, siendo Gobernadora Constitucional la C. Marina del Pilar Ávila Olmeda 20212027;\nARTÍCULO 64.- Fue reformado mediante Decreto No. 75, publicado en el Periódico\nOficial No. 11, de fecha 11 de febrero de 2022, Tomo CXXIX, Sección IV, expedido por la H.\nXXIV Legislatura, siendo Gobernadora Constitucional la C. Marina del Pilar Ávila Olmeda\n2021-2027; fue reformado mediante Decreto No. 200, publicado en el Periódico Oficial No. 6, de fecha 27 de enero de 2023, Tomo CXXX, Índice, expedido por la H. XXIV Legislatura, siendo Gobernadora Constitucional la C. Marina del Pilar Ávila Olmeda 2021-2027;\nFue adicionado este Capítulo Segundo mediante Decreto No. 200, publicado en el Periódico\nLegislatura, siendo Gobernadora Constitucional la C. Marina del Pilar Ávila Olmeda 20212027;\nCAPÍTULO SEGUNDO\nSANCIONES DE LOS SERVIDORES PÚBLICOS\nARTÍCULO 65.- Fue adicionado mediante Decreto No. 200, publicado en el Periódico\nLegislatura, siendo Gobernadora Constitucional la C. Marina del Pilar Ávila Olmeda 20212027;\nLey para las Personas con Discapacidad en el Estado de Baja California. Página 47\n.\nActualización Legislativa.\nÚltima reforma P.O. No. 13, Número Especial, 13-May-2025\nARTICULO UNICO TRANSITORIO DEL DECRETO No. 155, POR EL QUE SE\nREFORMAN LOS ARTÍCULOS 2 FRACCIONES VIII, IX, LA ADICIÓN DE LA FRACCIÓN\nX; 3 FRACCIONES I, IV, VI, X, XI, XII, XIII, XIV, XV, XVI, XVII, XVIII, XIX, XX, XXI, LA\nADICIÓN DE LAS FRACCIONES XXII, XXIII, XXIV, XXV, XXVI, XXVII, XXVIII, XXIX, XXX,\nXXXI Y XXXII; 4; 5 FRACCIONES I, II, V, X, LA ADICIÓN DE LAS FRACCIONES XIII, XIV Y\nXV; 6; LA ADICIÓN DEL ARTÍCULO 6 BIS; 7 LA ADICIÓN DE LA FRACCIÓN III; LA\nADICIÓN DEL ARTÍCULO 7 BIS; 8 FRACCIONES I, IV, VI, VIII, XI, LA ADICIÓN DE LA\nFRACCIÓN XII Y XIII; LA ADICIÓN DEL ARTÍCULO 8 BIS; 9 FRACCIONES I, II, III, IV, V,\nVI, VII, VIII, IX, X, XII, LA ADICIÓN DE LA FRACCIÓN XIII; 10; 12; 13; 14 EN CUANTO A LA\nADICIÓN DEL SEGUNDO PÁRRAFO Y LAS FRACCIONES I Y II; 15 FRACCIONES I, II, III,\nIV, V, VI, VII, VIII, IX, X, LA ADICIÓN DE LAS FRACCIONES XI, XII, XIII, XIV, XV Y XVI; 16\nFRACCIÓN I, LA ADICIÓN DE LA FRACCIÓN VI; 18; 19 FRACCIONES I, II Y IV; 20\nFRACCIONES II, III, IV Y V; 21 FRACCIONES I Y III; 23; 24; 25; 26 FRACCIONES I, IV, V,\nLA ADICIÓN DE LA FRACCIÓN VI; 27 FRACCIONES II, III, IV, V, VI, VII, LA ADICIÓN DE\nLAS FRACCIONES VIII, IX Y X; 29 FRACCIONES II Y IV; 31; 35 FRACCIÓN I Y VII EN SUS\nINCISOS B, C, E, F, G; LA CREACIÓN DEL CAPÍTULO X DEL TÍTULO SEGUNDO\nDENOMINADO FUNCIONES Y ATRIBUCIONES DE LA PROCURADURÍA DE DERECHOS\nHUMANOS Y PROTECCIÓN CIUDADANA QUE INCLUYE LA ADICIÓN DEL ARTÍCULO 35\nBIS; 37 FRACCIONES I, IV, VIII, IX, X Y XVI; 39; 44; 46; 49 FRACCIÓN II; 50, PUBLICADO\nEN EL PERIODICO OFICIAL NO. 2, TOMO CXIX, SECCION II, DE FECHA 06 DE ENE DE\n2012, EXPEDIDO POR LA H. XX LEGISLATURA, SIENDO GOBERNADOR\nCONSTITUCIONAL EL C. JOSE GUADALUPE OSUNA MILLAN 2007-2013.\nTRANSITORIOS\nPRIMERO.- El presente decreto entrara en vigor al día siguiente de su publicación en el Periódico Oficial del Estado.\nSEGUNDO.- A partir de la entrada en vigencia de la presente ley la Secretaría de\nInfraestructura y Desarrollo Urbano del Estado en coordinación con las autoridades municipales competentes, tendrán un plazo de 60 días para la elaboración del reglamento y programa de obras de acondicionamiento y habilitación de equipamiento público que deberá normatividad en la materia, mismo que deberá ser presentado al Consejo Consultivo para\nPersonas con Discapacidad del Estado para su validación respectiva.\nTERCERO.- El ejecutivo del estado a través de las Secretarías a su cargo y responsables de los acondicionamientos y habilitaciones establecidas en la presente Ley, técnicas así como la infraestructura necesaria con base a planes y programas anuales, aprobación de la presente ley.\nLey para las Personas con Discapacidad en el Estado de Baja California. Página 48\n.\nActualización Legislativa.\nÚltima reforma P.O. No. 13, Número Especial, 13-May-2025\nCUARTO.- El Ejecutivo publicará y sancionará el Reglamento Interno del Consejo\nConsultivo para Personas con Discapacidad del Estado.\nQUINTO.- El Ejecutivo del Estado y los Ayuntamientos tendrán un plazo de ciento ochenta días contados a partir de la entrada en vigor de la presente Ley, para adecuar su normatividad en el ámbito de su competencia.\nSEXTO.- Las dependencias Estatales y municipales previstas en la presente Ley, deberán de establecer en el presupuesto de Egresos del ejercicio presupuestal inmediato siguiente a la publicación de la presente Ley, las necesidades presupuéstales en los programas respectivos para dar cumplimiento a las atribuciones y obligaciones previstas en la misma; con base a planes y programas anuales, mismas que deberán ser contempladas en el Presupuesto de Egresos próximo a la fecha de aprobación de la presente ley.\nSÉPTIMO.- Los representantes de los Consejos Consultivos Municipales, deberán ser designados a más tardar 60 días a la publicación de la presente Ley, y notificados a la\nProcuraduría de Derechos Humanos y Protección Ciudadana del Estado para la posterior integración y notificación al resto de los Consejeros.\nOCTAVO.- Los representantes expertos deberán ser los candidatos de la sociedad civil de mayor trayectoria y reconocimiento dentro del sector de la atención a personas con discapacidad, seleccionados de la Convocatoria que para tal fin emita la Procuraduría de\nDerechos Humanos y Protección Ciudadana del Estado, mismas que deberá ser publicada\n30 días posteriores a la publicación de la presente Ley.\nDADO en el Salón de Sesiones “Lic. Benito Juárez García” del H. Poder Legislativo del Estado de Baja California, en la Ciudad de Mexicali, B.C., a los veinte días del mes de diciembre del año dos mil once.\nLIC. MÁXIMO GARCÍA LÓPEZ\nDIPUTADO PRESIDENTE\n(RÚBRICA)\nPROFR. ALFONSO GARZÓN ZATARAIN\nDIPUTADO SECRETARIO\n(RÚBRICA)\nDE CONFORMIDAD CON LO DISPUESTO POR LA FRACCION I DEL ARTÍCULO 49\nMEXICALI, BAJA CALIFORNIA, A LOS VEINTISEIS DÍAS DEL MES DE DICIEMBRE\nDEL AÑO DOS MIL ONCE.\nGOBERNADOR DEL ESTADO\nJOSE GUADALUPE OSUNA MILLAN\n(RÚBRICA)\nLey para las Personas con Discapacidad en el Estado de Baja California. Página 49\n.\nActualización Legislativa.\nÚltima reforma P.O. No. 13, Número Especial, 13-May-2025\nSECRETARIO GENERAL DE GOBIERNO\nCUAUHTEMOC CARDONA BENAVIDES\n(RÚBRICA)\nARTÍCULO SEGUNDO TRANSITORIO DEL DECRETO No. 457, POR EL QUE SE\nADICIONA UN SEGUNDO PÁRRAFO AL ARTÍCULO 34, ASÍ COMO LA ADICIÓN DE UN\nSEGUNDO PÁRRAFO AL ARTÍCULO 54, PUBLICADO EN EL PERIÓDICO OFICIAL No.\n25, TOMO CXX, SECCION I, DE FECHA 31 DE MAYO DE 2013, EXPEDIDO POR LA H. XX\nLEGISLATURA, SIENDO GOBERNADOR CONSTITUCIONAL EL C. JOSÉ GUADALUPE\nOSUNA MILLÁN 2007-2013.\nARTÍCULOS TRANSITORIOS\nPRIMERO: El presente decreto entrará en vigor al día siguiente de su publicación en el Periódico Oficial del Estado.\nSEGUNDO: Túrnese el presente Decreto al Titular del Poder Ejecutivo del Estado para los efectos de publicación en el Periódico Oficial del Estado de Baja California.\nDADO en el Salón de Sesiones “Lic. Benito Juárez García” del H. Poder Legislativo del Estado de Baja California, en la Ciudad de Mexicali, B.C., a los dos días del mes de mayo del año dos mil trece.\nDIP. JULIO FELIPE GARCÍA MUÑOZ\nPRESIDENTE\n(RÚBRICA)\nDIP. MARCO ANTONIO VIZCARRA CALDERÓN\nSECRETARIO\n(RÚBRICA)\nDE CONFORMIDAD CON LO DISPUESTO POR LA FRACCIÓN I DEL ARTÍCULO 49\nMEXICALI, BAJA CALIFORNIA, A LOS VEINTE DÍAS DEL MES DE MAYO DEL AÑO\nDOS MIL TRECE.\nJOSÉ GUADALUPE OSUNA MILLÁN\nGOBERNADOR DEL ESTADO\n(RÚBRICA)\nFRANCISCO ANTONIO GARCÍA BURGOS\nSECRETARIO GENERAL DE GOBIERNO\nLey para las Personas con Discapacidad en el Estado de Baja California. Página 50\n.\nActualización Legislativa.\nÚltima reforma P.O. No. 13, Número Especial, 13-May-2025\n(RÚBRICA)\nARTÍCULO SEGUNDO TRANSITORIO DEL DECRETO No. 359, POR EL QUE SE\nREFORMA EL ARTÍCULO 7, LA DENOMINACIÓN DEL CAPÍTULO IX, ASÍ COMO LOS\nARTÍCULOS 35 BIS Y 39; PUBLICADO EN EL PERIÓDICO OFICIAL No. 53, SECCIÓN I,\nTOMO CXXII, DE FECHA 20 DE NOVIEMBRE DE 2015, EXPEDIDO POR LA H. XXI\nLEGISLATURA, SIENDO GOBERNADOR CONSTITUCIONAL EL C. FRANCISCO\nARTURO VEGA DE LAMADRID 2013-2019.\nÚNICO.- Las presentes reformas entrarán en vigor al día siguiente de su publicación en el Periódico Oficial del Estado de Baja California.\nDADO en el Salón de Sesiones “Lic. Benito Juárez García” del H. Poder Legislativo del Estado de Baja California, en la Ciudad de Mexicali, B.C., a los veintidós días del mes de octubre del año dos mil quince.\nDIP. IRMA MARTÍNEZ MANRÍQUEZ\nPRESIDENTA\n(RÚBRICA)\nDIP. MARIO OSUNA JIMÉNEZ\nSECRETARIO\n(RÚBRICA)\nDE CONFORMIDAD CON LO DISPUESTO POR LA FRACCIÓN I DEL ARTÍCULO 49\nMEXICALI, BAJA CALIFORNIA, A LOS TREINTA DÍAS DEL MES DE OCTUBRE\nDEL AÑO DOS MIL QUINCE.\nFRANCISCO ARTURO VEGA DE LAMADRID\nGOBERNADOR DEL ESTADO\n(RÚBRICA)\nFRANCISCO RUEDA GÓMEZ\nSECRETARIO GENERAL DE GOBIERNO\n(RÚBRICA)\nARTÍCULO UNICO TRANSITORIO DEL DECRETO No. 496, POR EL QUE SE\nREFORMAN LOS ARTÍCULOS 3, 5 FRACCIÓN X, 8 FRACCIÓN XIII, 54 Y 55, ASÍ COMO\nLA ADICIÓN DE UNA FRACCIÓN XIV AL ARTÍCULO 8, UN CAPÍTULO III “DEL ACCESO A\nLey para las Personas con Discapacidad en el Estado de Baja California. Página 51\n.\nActualización Legislativa.\nÚltima reforma P.O. No. 13, Número Especial, 13-May-2025\nPERROS DE ASISTENCIA” AL TÍTULO TERCERO, Y DE LOS ARTÍCULOS 53 BIS, 56, 57,\n58, 59, 60, 61 Y 62, SE RECORRE EL TÍTULO CUARTO “DE LA RESPONSABILIDAD DE\nLOS SERVIDORES PÚBLICOS”, Y DE LOS ARTÍCULOS 63 Y 64; PUBLICADO EN EL\nPERIÓDICO OFICIAL No. 32, SECCIÓN IV, TOMO CXXIII, DE FECHA 15 DE JULIO DE\n2016, EXPEDIDO POR LA H. XXI LEGISLATURA, SIENDO GOBERNADOR\nCONSTITUCIONAL EL C. FRANCISCO ARTURO VEGA DE LAMADRID 2013-2019.\nARTÍCULOS TRANSITORIOS\nPRIMERO.- El presente Decreto entrará en vigor el día siguiente al de su publicación en el Periódico Oficial del Estado.\nSEGUNDO.- El Ejecutivo del Estado contará con 90 días naturales posteriores a la publicación de este Decreto a efecto de realizar las adecuaciones reglamentarias y administrativas que resulten necesarias a efecto de instrumentar la acreditación de perros de asistencia.\nDADO en el Salón de Sesiones “Lic. Benito Juárez García” del H. Poder Legislativo del Estado de Baja California, en la Ciudad de Mexicali, B.C., a los dieciséis días del mes de junio del año dos mil dieciséis.\nDIP. MÓNICA BEDOYA SERNA\nPRESIDENTA\n(RÚBRICA)\nDIP. ROSA ISELA PERALTA CASILLAS\nSECRETARIO\n(RÚBRICA)\nDE CONFORMIDAD CON LO DISPUESTO POR LA FRACCIÓN I DEL ARTÍCULO 49\nMEXICALI, BAJA CALIFORNIA, A LOS SEIS DÍAS DEL MES DE JULIO DEL AÑO\nDOS MIL DIECISÉIS.\nFRANCISCO ARTURO VEGA DE LAMADRID\nGOBERNADOR DEL ESTADO\n(RÚBRICA)\nFRANCISCO RUEDA GÓMEZ\nSECRETARIO GENERAL DE GOBIERNO\n(RÚBRICA)\nLey para las Personas con Discapacidad en el Estado de Baja California. Página 52\n.\nActualización Legislativa.\nÚltima reforma P.O. No. 13, Número Especial, 13-May-2025\nARTÍCULO ÚNICO TRANSITORIO DEL DECRETO No. 672, POR EL QUE SE\nREFORMA LA FRACCIÓN XI DEL ARTÍCULO 37; PUBLICADO EN EL PERIÓDICO\nOFICIAL No. 47, SECCIÓN V, TOMO CXXIII, DE FECHA 21 DE OCTUBRE DE 2016,\nEXPEDIDO POR LA H. XXI LEGISLATURA, SIENDO GOBERNADOR CONSTITUCIONAL\nEL C. FRANCISCO ARTURO VEGA DE LAMADRID 2013-2019.\nARTÍCULO TRANSITORIO\nÚNICO.- El presente decreto entrará en vigor al día siguiente de su publicación en el\nPeriódico Oficial del Estado.\nDADO en el Salón de Sesiones “Lic. Benito Juárez García” del H. Poder Legislativo del Estado de Baja California, en la Ciudad de Mexicali, B.C., a los veintiocho días del mes de septiembre del año dos mil dieciséis.\nDIP. MÓNICA BEDOYA SERNA\nPRESIDENTA\n(RÚBRICA)\nDIP. MARGARITA MACRINA CORRO ARÁMBULA\nPRO-SECRETARIA\n(RÚBRICA)\nDE CONFORMIDAD CON LO DISPUESTO POR LA FRACCIÓN I DEL ARTÍCULO 49\nMEXICALI, BAJA CALIFORNIA, A LOS TRES DÍAS DEL MES DE OCTUBRE DEL\nAÑO DOS MIL DIECISÉIS.\nFRANCISCO ARTURO VEGA DE LAMADRID\nGOBERNADOR DEL ESTADO\n(RÚBRICA)\nFRANCISCO RUEDA GOMEZ\nSECRETARIO GENERAL DE GOBIERNO\n(RÚBRICA)\nARTÍCULO ÚNICO TRANSITORIO DEL DECRETO No. 161, POR EL QUE SE\nREFORMA A EL ARTÍCULO 15; PUBLICADO EN EL PERIÓDICO OFICIAL No. 09,\nXXII LEGISLATURA, SIENDO GOBERNADOR CONSTITUCIONAL EL C. FRANCISCO\nARTURO VEGA DE LAMADRID 2013-2019.\nARTÍCULO TRANSITORIO\nLey para las Personas con Discapacidad en el Estado de Baja California. Página 53\n.\nActualización Legislativa.\nÚltima reforma P.O. No. 13, Número Especial, 13-May-2025\nÚNICO.- La presente reforma entrará en vigor al día siguiente de su publicación en el\nPeriódico Oficial del Estado de Baja California.\nDADO en el Salón de Sesiones “Lic. Benito Juárez García” del H. Poder Legislativo del Estado de Baja California, en la Ciudad de Mexicali, B.C., a los veinte y tres días del mes de noviembre del año dos mil diecisiete.\nDIP. EDGAR BENJAMÍN GÓMEZ MACIAS\nPRESIDENTE\n(RÚBRICA)\nDIP. EVA MARÍA VÁSQUEZ HERNÁNDEZ\nSECRETARIA\n(RÚBRICA)\nDE CONFORMIDAD CON LO DISPUESTO POR LA FRACCIÓN I DEL ARTÍCULO 49\nMEXICALI, BAJA CALIFORNIA, A LOS QUINCE DÍAS DEL MES DE FEBRERO DEL\nAÑO DOS MIL DIECIOCHO.\nFRANCISCO ARTURO VEGA DE LAMADRID\nGOBERNADOR DEL ESTADO\n(RÚBRICA)\nFRANCISCO RUEDA GÓMEZ\nSECRETARIO GENERAL DE GOBIERNO\n(RÚBRICA)\nARTÍCULO ÚNICO TRANSITORIO DEL DECRETO No. 190, POR EL QUE SE\nREFORMA A LOS ARTÍCULOS 1, 3, 7 Y 15; ASÍ COMO LA ADICIÓN DEL CAPÍTULO III\nDENOMINADO “DE LA PERSONALIDAD JURÍDICA” AL TÍTULO PRIMERO,\nADICIONANDOSE LOS ARTÍCULOS 6 TER, 6 QUARTER, 6 QUINQUIES Y 6 SEXIES;\nADICIONÁNDOSE EL ARTÍCULO 62 BIS; PUBLICADO EN EL PERIÓDICO OFICIAL No.\nLA H. XXII LEGISLATURA, SIENDO GOBERNADOR CONSTITUCIONAL EL C.\nFRANCISCO ARTURO VEGA DE LAMADRID 2013-2019.\nARTÍCULO TRANSITORIO\nPRIMERO.- La presente reforma entrará en vigor al día siguiente de su publicación en el Periódico Oficial del Estado.\nLey para las Personas con Discapacidad en el Estado de Baja California. Página 54\n.\nActualización Legislativa.\nÚltima reforma P.O. No. 13, Número Especial, 13-May-2025\nSEGUNDO.- El Ejecutivo del Estado y los Ayuntamientos, deberá realizar las modificaciones necesarias a sus reglamentos a más tardar setenta días naturales contados a partir de la publicación de la presente reforma.\nTERCERO.- En un plazo no mayor a ciento ochenta días contados a partir de la publicación de la presente reforma, los sujetos obligados darán cumplimiento a lo establecido en el artículo 62 BIS.\nDADO en el Salón de Sesiones “Lic. Benito Juárez García” del H. Poder Legislativo del Estado de Baja California, en la Ciudad de Mexicali, B.C., a los veinticinco días del mes de enero del año dos mil dieciocho.\nDIP. MTRO. RAÚL CASTAÑEDA POMPOSO\nPRESIDENTE\n(RÚBRICA)\nDIP. ROCÍO LÓPEZ GOROSAVE\nSECRETARIA\n(RÚBRICA)\nDE CONFORMIDAD CON LO DISPUESTO POR LA FRACCIÓN I DEL ARTÍCULO 49\nMEXICALI, BAJA CALIFORNIA, A LOS VEINTIUN DÍAS DEL MES DE FEBRERO\nDEL AÑO DOS MIL DIECIOCHO.\nFRANCISCO ARTURO VEGA DE LAMADRID\nGOBERNADOR DEL ESTADO\n(RÚBRICA)\nFRANCISCO RUEDA GÓMEZ\nSECRETARIO GENERAL DE GOBIERNO\n(RÚBRICA)\nARTÍCULO ÚNICO TRANSITORIO DEL DECRETO No. 215, POR EL QUE SE\nREFORMAN LOS ARTÍCULOS 3, 8,15, 27 Y 35; PUBLICADO EN EL PERIÓDICO OFICIAL\nPOR LA H. XXII LEGISLATURA, SIENDO GOBERNADOR CONSTITUCIONAL EL C.\nFRANCISCO ARTURO VEGA DE LAMADRID 2013-2019.\nARTÍCULO TRANSITORIO\nLey para las Personas con Discapacidad en el Estado de Baja California. Página 55\n.\nActualización Legislativa.\nÚltima reforma P.O. No. 13, Número Especial, 13-May-2025\nPRIMERO.- La presente reforma entrará en vigor al día siguiente de su publicación en el Periódico Oficial del Estado.\nSEGUNDO.- Las disposiciones contenidas en los artículos 3 y 15 de la presente reforma, surtirán efectos a partir de la publicación en el Periódico Oficial del Estado, del\nDecreto 161 aprobado en fecha 23 de noviembre del 2017, así como del Decreto 190 aprobado en fecha 25 de enero de 2018.\nTERCERO.- El Ejecutivo del Estado dará cumplimiento al presente Decreto, de conformidad con la viabilidad financiera aprobada en cada ejercicio fiscal correspondiente.\nDADO en el Salón de Sesiones “Lic. Benito Juárez García” del H. Poder Legislativo del Estado de Baja California, en la Ciudad de Mexicali, B.C., al primer día del mes de marzo del año dos mil dieciocho.\nDIP. MTRO. RAÚL CASTAÑEDA POMPOSO\nPRESIDENTE\n(RÚBRICA)\nDIP. ROCÍO LÓPEZ GOROSAVE\nSECRETARIA\n(RÚBRICA)\nDE CONFORMIDAD CON LO DISPUESTO POR LA FRACCIÓN I DEL ARTÍCULO 49\nMEXICALI, BAJA CALIFORNIA, A LOS TREINTA Y UN DÍAS DEL MES DE ENERO\nDEL AÑO DOS MIL DIECINUEVE.\nFRANCISCO ARTURO VEGA DE LAMADRID\nGOBERNADOR DEL ESTADO\n(RÚBRICA)\nFRANCISCO RUEDA GÓMEZ\nSECRETARIO GENERAL DE GOBIERNO\n(RÚBRICA)\nARTÍCULO TERCERO TRANSITORIO DEL DECRETO No. 75, POR EL QUE SE\nREFORMAN LOS ARTÍCULOS 7, 12, 15, 20, 38, 64, ASÍ COMO EL CAMBIO DE\nDENOMINACIÓN DE LOS CAPÍTULOS III Y V; PUBLICADO EN EL PERIÓDICO OFICIAL\nPOR LA H. XXIV LEGISLATURA, SIENDO GOBERNADORA CONSTITUCIONAL LA C.\nMARINA DEL PILAR ÁVILA OLMEDA 2021-2027.\nLey para las Personas con Discapacidad en el Estado de Baja California. Página 56\n.\nActualización Legislativa.\nÚltima reforma P.O. No. 13, Número Especial, 13-May-2025\nTRANSITORIOS\nÚNICO. El presente Decreto entrará en vigor al día siguiente de su publicación en el\nPeriódico Oficial del Estado.\nDADO en Sesión Ordinaria Virtual de la XXIV Legislatura en la Ciudad de Mexicali, B.C., a los veintisiete días del mes de enero del año dos mil veintidós.\nDIP. JUAN MANUEL MOLINA GARCÍA\nPRESIDENTE\n(RÚBRICA)\nDIP. ARACELI GERALDO NÚÑEZ\nSECRETARIA\n(RÚBRICA)\nDE CONFORMIDAD CON LO DISPUESTO POR LA FRACCIÓN I DEL ARTÍCULO 49\nCALIFORNIA, IMPRÍMASE Y PUBLÍQUESE.\nMEXICALI, BAJA CALIFORNIA, A LOS DOS DÍAS DEL MES DE FEBRERO DEL\nAÑO DOS MIL VEINTIDÓS.\nMARINA DEL PILAR ÁVILA OLMEDA\nGOBERNADORA DEL ESTADO\nDE BAJA CALIFORNIA\n(RÚBRICA)\nCATALINO ZAVALA MÁRQUEZ\nSECRETARIO GENERAL DE GOBIERNO\nDEL ESTADO DE BAJA CALIFORNIA\n(RÚBRICA)\nARTÍCULO ÚNICO TRANSITORIO DEL DECRETO No. 81, POR EL QUE SE\nREFORMAN LOS ARTÍCULOS 3 Y 19; PUBLICADO EN EL PERIÓDICO OFICIAL No. 17,\nXXIV LEGISLATURA, SIENDO GOBERNADORA CONSTITUCIONAL LA C. MARINA DEL\nPILAR ÁVILA OLMEDA 2021-2027.\nTRANSITORIOS\nÚNICO. La presente reforma entrará en vigor al día siguiente a su publicación en el\nPeriódico Oficial del Estado.\nLey para las Personas con Discapacidad en el Estado de Baja California. Página 57\n.\nActualización Legislativa.\nÚltima reforma P.O. No. 13, Número Especial, 13-May-2025\nDADO en Sesión Ordinaria Virtual de la XXIV Legislatura en la Ciudad de Mexicali, B.C., a los veinticuatro días del mes de febrero del año dos mil veintidós.\nDIP. JUAN MANUEL MOLINA GARCÍA\nPRESIDENTE\n(RÚBRICA)\nDIP. AMINTHA GUADALUPE BRICEÑO CINCO\nPROSECRETARIA\n(RÚBRICA)\nDE CONFORMIDAD CON LO DISPUESTO POR LA FRACCIÓN I DEL ARTÍCULO 49\nCALIFORNIA, IMPRÍMASE Y PUBLÍQUESE.\nMEXICALI, BAJA CALIFORNIA, AL DÍA PRIMERO DEL MES DE MARZO DEL AÑO\nDOS MIL VEINTIDÓS.\nMARINA DEL PILAR ÁVILA OLMEDA\nGOBERNADORA DEL ESTADO\nDE BAJA CALIFORNIA\n(RÚBRICA)\nCATALINO ZAVALA MÁRQUEZ\nSECRETARIO GENERAL DE GOBIERNO\nDEL ESTADO DE BAJA CALIFORNIA\n(RÚBRICA)\nARTÍCULO ÚNICO TRANSITORIO DEL DECRETO No. 172, POR EL QUE SE\nREFORMAN EL ARTÍCULO 38; PUBLICADO EN EL PERIÓDICO OFICIAL No. 70,\nSECCIÓN III, TOMO CXXIX, DE FECHA 02 DE DICIEMBRE DE 2022, EXPEDIDO POR LA\nH. XXIV LEGISLATURA, SIENDO GOBERNADORA CONSTITUCIONAL LA C. MARINA\nDEL PILAR ÁVILA OLMEDA 2021-2027.\nTRANSITORIOS\nÚNICO. La presente reforma entrará en vigor al día siguiente a su publicación en el\nPeriódico Oficial del Estado de Baja California.\nDADO en Sesión Ordinaria de la XXIV Legislatura en la Ciudad de Mexicali, B.C., a los diez días del mes de noviembre del año dos mil veintidós.\nDIP. ALEJANDRA MARÍA ANG HERNÁNDEZ\nPRESIDENTA\nLey para las Personas con Discapacidad en el Estado de Baja California. Página 58\n.\nActualización Legislativa.\nÚltima reforma P.O. No. 13, Número Especial, 13-May-2025\n(RÚBRICA)\nDIP. DUNNIA MONTSERRAT MURILLO LÓPEZ\nSECRETARIA\n(RÚBRICA)\nDE CONFORMIDAD CON LO DISPUESTO POR LA FRACCIÓN I DEL ARTÍCULO 49\nCALIFORNIA, IMPRÍMASE Y PUBLÍQUESE.\nMEXICALI, BAJA CALIFORNIA, AL DÍA DIECISÉIS DEL MES DE NOVIEMBRE DEL\nAÑO DOS MIL VEINTIDÓS.\nMARINA DEL PILAR ÁVILA OLMEDA\nGOBERNADORA DEL ESTADO\nDE BAJA CALIFORNIA\n(RÚBRICA)\nCATALINO ZAVALA MÁRQUEZ\nSECRETARIO GENERAL DE GOBIERNO\nDEL ESTADO DE BAJA CALIFORNIA\n(RÚBRICA)\nARTÍCULO ÚNICO TRANSITORIO DEL DECRETO No. 200, POR EL QUE SE\nREFORMAN LOS ARTÍCULOS 2, 6 QUINQUIES, 45, 63 Y 64; LA DENOMINACIÓN DEL\nTÍTULO CUARTO; LA DENOMINACIÓN DEL CAPÍTULO PRIMERO DEL TÍTULO CUARTO;\nLA ADICIÓN DE UN CAPÍTULO SEGUNDO DENOMINADO SANCIONES DE LOS\nSERVIDORES PÚBLICOS AL TÍTULO CUARTO, COMO TAMBIÉN LA ADICIÓN DE UN\nARTÍCULO 65; PUBLICADO EN EL PERIÓDICO OFICIAL No. 6, ÍNDICE, TOMO CXXX, DE\nFECHA 27 DE ENERO DE 2023, EXPEDIDO POR LA H. XXIV LEGISLATURA, SIENDO\nGOBERNADORA CONSTITUCIONAL LA C. MARINA DEL PILAR ÁVILA OLMEDA 2021-\n2027.\nTRANSITORIOS\nÚNICO. El presente Decreto entrará en vigor al día siguiente de su publicación en el\nPeriódico Oficial del Estado.\nDADO en Sesión Ordinaria de la XXIV Legislatura en la Ciudad de Mexicali, B.C., a los doce días del mes de enero del año dos mil veintitrés.\nDIP. MARÍA DEL ROCÍO ADAME MUÑOZ\nPRESIDENTA\n(RÚBRICA)\nLey para las Personas con Discapacidad en el Estado de Baja California. Página 59\n.\nActualización Legislativa.\nÚltima reforma P.O. No. 13, Número Especial, 13-May-2025\nDIP. DUNNIA MONTSERRAT MURILLO LÓPEZ\nSECRETARIA\n(RÚBRICA)\nDE CONFORMIDAD CON LO DISPUESTO POR LA FRACCIÓN I DEL ARTÍCULO 49\nCALIFORNIA, IMPRÍMASE Y PUBLÍQUESE.\nMEXICALI, BAJA CALIFORNIA, A LOS TRECE DÍAS DEL MES DE ENERO DEL\nAÑO DOS MIL VEINTITRÉS.\nMARINA DEL PILAR ÁVILA OLMEDA\nGOBERNADORA DEL ESTADO\nDE BAJA CALIFORNIA\n(RÚBRICA)\nCATALINO ZAVALA MÁRQUEZ\nSECRETARIO GENERAL DE GOBIERNO\nDEL ESTADO DE BAJA CALIFORNIA\n(RÚBRICA)\nARTÍCULO ÚNICO TRANSITORIO DEL DECRETO No. 255, POR EL QUE SE\nREFORMA EL ARTÍCULO 19; PUBLICADO EN EL PERIÓDICO OFICIAL No. 45, SECCIÓN\nI, TOMO CXXX, DE FECHA 28 DE JULIO DE 2023, EXPEDIDO POR LA H. XXIV\nLEGISLATURA, SIENDO GOBERNADORA CONSTITUCIONAL LA C. MARINA DEL PILAR\nÁVILA OLMEDA 2021-2027.\nTRANSITORIOS\nÚNICO. La presente reforma entrará en vigor al día siguiente de su publicación en el\nPeriódico Oficial del Estado.\nDADO en Sesión Ordinaria de la XXIV Legislatura en la Ciudad de Mexicali, B.C., a los seis días del mes de julio del año dos mil veintitrés.\nDIP. MANUEL GUERRERO LUNA\nPRESIDENTE\n(RÚBRICA)\nDIP. ALEJANDRA MARÍA ANG HERNÁNDEZ\nSECRETARIA\n(RÚBRICA)\nLey para las Personas con Discapacidad en el Estado de Baja California. Página 60\n.\nActualización Legislativa.\nÚltima reforma P.O. No. 13, Número Especial, 13-May-2025\nDE CONFORMIDAD CON LO DISPUESTO POR LA FRACCIÓN I DEL ARTÍCULO 49\nCALIFORNIA, IMPRÍMASE Y PUBLÍQUESE.\nMEXICALI, BAJA CALIFORNIA, A LOS ONCE DÍAS DEL MES DE JULIO DEL AÑO\nDOS MIL VEINTITRÉS.\nMARINA DEL PILAR ÁVILA OLMEDA\nGOBERNADORA DEL ESTADO\nDE BAJA CALIFORNIA\n(RÚBRICA)\nCATALINO ZAVALA MÁRQUEZ\nSECRETARIO GENERAL DE GOBIERNO\nDEL ESTADO DE BAJA CALIFORNIA\n(RÚBRICA)\nARTÍCULO ÚNICO TRANSITORIO DEL DECRETO No. 330, POR EL QUE SE\nREFORMA EL ARTÍCULO 25; PUBLICADO EN EL PERIÓDICO OFICIAL No. 70, DE\nFECHA 28 DE JULIO DE 2023, SECCIÓN I, TOMO CXXX, EXPEDIDO POR LA H. XXIV\nLEGISLATURA, SIENDO GOBERNADORA CONSTITUCIONAL LA C. MARINA DEL PILAR\nÁVILA OLMEDA 2021-2027.\nTRANSITORIOS\nÚNICO. El presente Decreto entrará en vigor al día siguiente de su publicación en el\nPeriódico Oficial del Estado.\nDADO en Sesión Ordinaria de la XXIV Legislatura en la Ciudad de Mexicali, B.C., a los dieciséis días del mes de noviembre del año dos mil veintitrés.\nDIP. MANUEL GUERRERO LUNA\nPRESIDENTE\n(RÚBRICA)\nDIP. ALEJANDRA MARÍA ANG HERNÁNDEZ\nSECRETARIA\n(RÚBRICA)\nDE CONFORMIDAD CON LO DISPUESTO POR LA FRACCIÓN I DEL ARTÍCULO 49\nCALIFORNIA, IMPRÍMASE Y PUBLÍQUESE.\nLey para las Personas con Discapacidad en el Estado de Baja California. Página 61\n.\nActualización Legislativa.\nÚltima reforma P.O. No. 13, Número Especial, 13-May-2025\nMEXICALI, BAJA CALIFORNIA, A LOS VEINTITRÉS DÍAS DEL MES DE\nNOVIEMBRE DEL AÑO DOS MIL VEINTITRÉS.\nMARINA DEL PILAR ÁVILA OLMEDA\nGOBERNADORA DEL ESTADO\nDE BAJA CALIFORNIA\n(RÚBRICA)\nCATALINO ZAVALA MÁRQUEZ\nSECRETARIO GENERAL DE GOBIERNO\nDEL ESTADO DE BAJA CALIFORNIA\n(RÚBRICA)\nARTÍCULO PRIMERO TRANSITORIO DEL DECRETO No. 92, POR EL QUE SE\nREFORMAN LOS ARTÍCULOS 2, 3, 6, 7, 7 BIS, 8, 9, 36 Y ADICIONA EL ARTÍCULO 4 BIS,\nEL CAPÍTULO IV DENOMINADO “DE LA ATENCIÓN INTEGRAL”, CONTENIENDO EL\nARTÍCULO 6 SEPTIES AL TÍTULO PRIMERO “DISPOSICIONES GENERALES” Y LOS\nARTÍCULOS 23 BIS Y 23 TER; PUBLICADO EN EL PERIÓDICO OFICIAL No. 30,\nNÚMERO ESPECIAL, DE FECHA 13 DE MAYO DE 2025, TOMO CXXXII; EXPEDIDO POR\nLA H. XXV LEGISLATURA, SIENDO GOBERNADORA CONSTITUCIONAL LA C. MARINA\nDEL PILAR ÁVILA OLMEDA 2021-2027.\nARTÍCULOS TRANSITORIOS\nPRIMERO.- Las presentes reformas entrarán en vigor, al día siguiente de su publicación en el Periódico Oficial del Estado.\nSEGUNDO.- Las obligaciones que se generen con motivo de la entrada en vigor de las presentes reformas, se sujetarán a la disponibilidad presupuestal de quienes ejecutan el gasto en el ejercicio fiscal vigente y los subsecuentes.\nTERCERO.- Las obligaciones y facultades de las autoridades estatales que deriven de la vigencia de las presentes reformas y que resulten materia de convenios entre la\nFederación y el Estado, se sujetarán para su cumplimiento a las disposiciones jurídicas aplicables.\nDADO en Sesión Ordinaria de la XXV Legislatura en la Ciudad de Mexicali, B.C., a los ocho días del mes de mayo del año dos mil veinticinco.\nDIP. MICHELLE ALEJANDRA TEJEDA MEDINA\nPRESIDENTA\n(RÚBRICA)\nDIP. NORMA ANGELICA PEÑALOZA ESCOBEDO\nSECRETARIA\nLey para las Personas con Discapacidad en el Estado de Baja California. Página 62\n.\nActualización Legislativa.\nÚltima reforma P.O. No. 13, Número Especial, 13-May-2025\n(RÚBRICA)\nDE CONFORMIDAD CON LO DISPUESTO POR LA FRACCIÓN I DEL ARTÍCULO 49\nCALIFORNIA, IMPRÍMASE Y PUBLÍQUESE.\nMEXICALI, BAJA CALIFORNIA, A LOS 09 DÍAS DEL MES DE MAYO DEL AÑO DOS\nMIL VEINTICINCO.\nMARINA DEL PILAR ÁVILA OLMEDA\nGOBERNADORA DEL ESTADO\nDE BAJA CALIFORNIA\n(RÚBRICA)\nALFREDO ÁLVAREZ CÁRDENAS\nSECRETARIO GENERAL DE GOBIERNO\nDEL ESTADO DE BAJA CALIFORNIA\n(RÚBRICA)\nLey para las Personas con Discapacidad en el Estado de Baja California. Página 63",
  "ordenamiento": "REGLAMENTO",
  "jurisdiccion": "BAJA CALIFORNIA",
  "fuente_oficial": "Periódico Oficial",
  "FECHA PER OFIC": "2025/05/13",
  "ESTATUS": "VIGENTE",
  "TOMO": "TOMO_VI",
  "URL": "https://www.congresobc.gob.mx/Documentos/ProcesoParlamentario/Leyes/TOMO_VI/20250513_LEYDISCAPACIDAD.PDF",
  "es_escaneado": false,
  "tiene_tablas": true,
  "materia": [
    "social",
    "salud",
    "educación",
    "cultura"
  ]
}