{
  "titulo": "Ley DE INGRESOS DEL MUNICIPIO DE TECATE, BAJA CALIFORNIA PARA EL EJERCICIO FISCAL DE 2025",
  "Contenido": "BAJA CALIFORNIA, EN USO DE LAS FACULTADES QUE LE CONFIERE EL ARTÍCULO\nSOBERANO DE BAJA CALIFORNIA, TIENE A BIEN APROBAR LA SIGUIENTE:\nLEY DE INGRESOS DEL\nMUNICIPIO DE TECATE, BAJA CALIFORNIA,\nY TABLA DE VALORES CATASTRALES UNITARIOS,\nBASE DEL IMPUESTO PREDIAL PARA EL\nEJERCICIO FISCAL DE 2025\nTÍTULO I.- GENERALIDADES\nDE LOS INGRESOS\nARTÍCULO 1.- La presente Ley es de orden público y de interés social y tiene por objeto establecer los ingresos ordinarios que percibirá la hacienda pública del Municipio de Tecate, Baja California, los cuales se dividen en Impuestos, Contribuciones de Mejoras, Derechos, Productos y Aprovechamientos durante el ejercicio fiscal del 01 de enero al 31 de diciembre del 2025, y serán los que se obtengan por los siguientes conceptos, estimando las cantidades que a continuación se enumeran:\nTÍTULO II.- IMPUESTOS $110,099,218\nCAPÍTULO I\nIMPUESTO SOBRE LOS INGRESOS $4,373,799\n1.- Impuesto sobre asistencia a juegos permitidos y espectáculos públicos. $8,701\n2.- Impuesto a centros de apuestas, apuestas remotas, salas de sorteos, de números y/o casinos $4,365,098\nCAPÍTULO II\nIMPUESTO SOBRE EL PATRIMONIO $58,611,429\n3.- Impuesto Predial. $46,415,870\n4.- Impuesto sobre Adquisición de\nInmuebles. $11,877,998\n5.- Convenios Impuesto Predial. $317,560\nCAPÍTULO III\nACCESORIOS DE IMPUESTOS $10,278,037\n6.- Recargos. $10,061,988\n7.- Gastos de ejecución. $215,979\n8.- Sanciones. $69\nCAPÍTULO IV\nOTROS IMPUESTOS $8,031,246\n9.- Impuesto para el Mantenimiento y Conservación de las Vías\nPúblicas. $8,031,246\nCAPÍTULO V\nIMPUESTOS NO COMPRENDIDOS EN LA LEY DE INGRESOS VIGENTE, CAUSADOS EN\nEJERCICIOS FISCALES ANTERIORES PENDIENTES DE LIQUIDACIÓN O PAGO\n$28,804,708\n10.- Impuestos Causados en Ejercicios\nFiscales Anteriores Pendientes de\nLiquidación o Pago. $28,804,708\nTÍTULO III.- CUOTAS Y APORTACIONES DE SEGURIDAD SOCIAL\n1.- Otras Cuotas y Aportaciones de\nRecuperación de Servicios Médicos\n$0\nTÍTULO IV.- CONTRIBUCIONES DE MEJORAS $53,452\nCAPÍTULO I\nCONTRIBUCIÓN DE MEJORAS POR OBRAS PÚBLICAS $0\n1.- Aportaciones de Particulares para\nObras Públicas Municipales. $0\nCAPÍTULO II\nCONTRIBUCIÓN DE MEJORAS NO COMPRENDIDAS EN LA LEY DE INGRESOS VIGENTE,\nO PAGO $53,452\n2.- Aportaciones de Particulares para\nObras Públicas Municipales de\nAños Anteriores. $53,452\nTÍTULO V.- DERECHOS $171,374,864\nCAPÍTULO I\nDERECHOS POR PRESTACIÓN DE SERVICIOS $162,895,288\n1.- Derecho por Servicio de Alumbrado Público. $28,711,698\n2.- Derechos por Servicios que Presta el Registro Civil. $7,254,447\n3.- Derechos por Servicios que Presta el Departamento de Panteones. $856,830\n4.- Derechos por Servicios que Presta el Departamento de Rastro\nMunicipal. $187,173\n5.- Derechos por Expedición de\nPermisos por el Uso u Ocupación de las Vías Públicas por\nComerciantes Ambulantes o con\nPuestos Semifijos. $3,513,928\n6.- Derechos por Servicios que Presta la Dirección de Gestión Integral del Territorio. $67,209,960\n7.- Derechos por Servicios que Presta la Dirección de Gestión Integral del Territorio en materia de\nProtección al Ambiente. $3,089,429\n8.- Derechos por Servicio de Grúas. $0\n9.- Derechos por Almacenaje de\nVehículos. $0\n10.- Derechos por Estacionamiento de\nVehículos en la Vía Pública. $1,897,409\n11.- Derechos por Expedición de\nCertificados, Títulos o Copias de\nDocumentos. $1,728,943\n12.- Derechos por Otorgamiento y\nRevalidación de Licencias de\nOperación. $4,054,597\n13.- Derechos por Servicios que Presta la Dirección de Gestión Integral del Territorio en materia de\nLimpia. $0\n14.- Eliminado. $0\n15.- Derechos por Servicios que presta la Dirección de Seguridad\nCiudadana y Tránsito Municipal $24,353,224\n16.- Derechos por Recepción, Análisis y Revisión de Solicitudes, de\nEmisión de Documentos, Permisos y\nCertificados Referentes a\nInstalaciones para la Venta, Almacenaje o Consumo de Bebidas con Graduación Alcohólica, Cambio de Giro, Cambio de Permisionario, Cambio de Domicilio, Cambio de\nDenominación Comercial y\nTramitación Relativa a la\nOperación de Giros de Cerveza, Vinos, Licores, Alcoholes y\nSimilares. $7,561,008\n17.- Derechos por Servicios que Presta el Departamento de Servicios\nMédicos Municipales. $43,723\n18.- Derechos por Servicios que Presta la Coordinación Municipal de\nProtección Civil y Bomberos. $10,611,465\n19.- Derechos por Revisión y Análisis de Documentos Referentes a la\nInstalación de Aparatos\nElectromecánicos, Videojuegos, Máquinas Expendedoras y de\nDestreza. $4,945\n20.- Cuota de Recuperación por el Uso de Baños Públicos del Parque\nMiguel Hidalgo. $130,000.00\n21.- Derechos por Recepción, Análisis y Revisión de Solicitudes para\nAnuencia por Apertura de Agencias de Seguridad Privada. $0\n22.- Derechos Por Servicios Que Presta\nLa Dirección De Desarrollo\nEconómico $975,200\n23.- Convenios Otros. $711,310\nCAPÍTULO II\nOTROS DERECHOS $668,372\n24.- Derechos por Otros Servicios que\nPresta el Ayuntamiento a través de las Entidades Paramunicipales.\n$0\nCAPÍTULO III\nACCESORIOS DE DERECHOS $4,412,193\n25.- Recargos. $2,140,867\n26.- Gastos de ejecución. $145,125\n27.- Sanciones. $2,126,202\nCAPÍTULO IV\nDERECHOS NO COMPRENDIDOS EN LA LEY DE INGRESOS VIGENTE, CAUSADOS EN\nEJERCICIOS FISCALES ANTERIORES PENDIENTES DE LIQUIDACIÓN O PAGO\n$3,399,010\n28.- Derechos Causados en Ejercicios\nFiscales Anteriores Pendientes de\nLiquidación o Pago. $3,399,010\nTÍTULO VI. – PRODUCTOS DERIVADOS DE: $257,975\nCAPÍTULO I $257,975\nPRODUCTOS\n1.- Contraprestación de Concesiones, Explotación o Arrendamiento de\nBienes Muebles e Inmuebles, Propiedad del Gobierno Municipal $140,652\n2.- Suministro de Formas Diversas para Trámites Administrativos $2,950\n3.- Otras Actividades del Gobierno\nMunicipal, que no correspondan a sus Funciones Propias de Derecho\nPúblico. $0\n4.- Bienes Mostrencos. $350\n5.- Organismos Descentralizados y/o\nParamunicipales $0\n6.- Del Piso. $16,397\n7.- Productos financieros. $1,340\n8.- Intereses convenios. $96,285\nCAPÍTULO II\nPRODUCTOS NO COMPRENDIDOS EN LA LEY DE INGRESOS VIGENTE, CAUSADOS\n9.- Productos Causados en Ejercicios\nFiscales Anteriores Pendientes de\nLiquidación o Pago. $0\nTÍTULO VII.- APROVECHAMIENTOS $20,653,320\nCAPÍTULO I\nAPROVECHAMIENTOS $20,529,875\n1.- Multas. $4,705,302\n2.- Reintegros e Indemnizaciones. $5,842,370\n3.- Donaciones, Cesiones, Herencias y\nLegados a Favor del Municipio. $36,292\n4.- Otorgamiento y Usufructo de\nDerechos. $2,997\n5.- Otros Aprovechamientos. $9,942,914\nCAPÍTULO II\nAPROVECHAMIENTOS PATRIMONIALES $3,399\n6.- Cauciones, Fianzas y Depósitos\nCuya Pérdida se Declare por\nResolución Firme. $0\n7.- Ingresos por venta de Bienes\nPatrimoniales. $3,399\n8.- Otros Aprovechamientos de\nCapital. $0\nCAPÍTULO III\nACCESORIOS DE APROVECHAMIENTOS $120,038\n9.- Recargos. $0\n10.- Gastos de Ejecución. $7\n11.- Sanciones. $120,031\nCAPÍTULO IV\nAPROVECHAMIENTOS NO COMPRENDIDOS EN LA LEY DE INGRESOS VIGENTE,\nLIQUIDACIÓN O PAGO $9\n12.- Aprovechamientos Causados en Ejercicios\nFiscales Anteriores Pendientes de\nLiquidación o Pago. $9\nTÍTULO VIII.- INGRESOS POR VENTA DE BIENES PRESTACIÓN DE\nSERVICIOS Y OTROS INGRESOS $14\nCAPÍTULO I\nINGRESOS POR VENTA DE BIENES Y PRESTACIÓN DE SERVICIOS DE\nINSTITUCIONES PÚBLICAS DE SEGURIDAD SOCIAL\n1.- Ingresos por Venta de Bienes y\nServicios Producidos en\nEstablecimientos del Gobierno\nMunicipal. $0\nCAPÍTULO II\nOTROS INGRESOS\n2.- INGRESOS FINANCIEROS $0\n3.- DONATIVOS $0\n4.- OTROS INGRESOS $14\nTÍTULO IX.- PARTICIPACIONES, APORTACIONES, CONVENIOS,\nDISTINTOS DE APORTACIONES $637,565,181\nCAPÍTULO I\nPARTICIPACIONES $484,743,520\n1.- Participaciones de Impuestos\nFederales. $373,810,684\n2.- Participaciones de Impuestos\nEstatales: $56,859,087\na).- Por Convenios con el Gobierno del Estado, para la Realización de Obras.\nb).- Por Otros Impuestos o Ingresos del Estado que Señalen las\nLeyes, Acuerdos o Convenios que los Regulen.\n3.- Participaciones en Impuestos\nAduanales. $54,073,749\nCAPÍTULO II\nAPORTACIONES $138,832,548\n4.- Aportaciones del Gobierno del\nEstado o de la Federación para\nObras y Servicios Públicos o\nProgramas Especiales. $0\n5.- Aportaciones Federales del Ramo\n33: $138,832,548\na).- Fondo de Aportaciones para la\nInfraestructura Social\nMunicipal. $32,524,011\nb).- Fondo de Aportaciones para el\nFortalecimiento de los\nMunicipios. $93,353,444\nc).- Otras. $12,955,093\nCAPÍTULO III\nCONVENIOS $1,777,000\n6.- Otros Ingresos por Convenios\nFederales. $1,776,131\n7.- Otros Ingresos por Convenios\nEstatales. $869\n8.- Convenios celebrados por\nParamunicipales con Entidades\nFederales, Estatales, Municipales, Autónomos u otros. $0\nCAPÍTULO IV\nINCENTIVOS DERIVADOS DE COLABORACIÓN FISCAL $12,212,113\n9.- Ingresos por Convenios de\nColaboración Fiscal. $12,212,113\nCAPÍTULO V\nFONDOS DISTINTOS DE APORTACIONES $0\n10.- Ingresos por Fondos Distintos de Aportaciones. $0\nTÍTULO X.- TRANSFERENCIAS, ASIGNACIONES, SUBSIDIOS Y OTRAS\nAYUDAS\n1.- Subsidios que Otorgue el Gobierno\nFederal. $0\n2.- Subsidios que Otorgue el Gobierno del Estado. $0\n3.- Subsidios que Otorgue el Gobierno\nMunicipal a las Entidades\nParamunicipales. $0\nTÍTULO XI.- INGRESOS DERIVADOS DE FINANCIAMIENTOS $97,235,323\nCAPÍTULO I\nENDEUDAMIENTO INTERNO\n1.- Créditos Otorgados al Municipio. $97,235,323\n2.- Aportaciones Estatales y\nFederales. $0\n3.- Programas Especiales. $0\n4.- Los Provenientes de Bonos y\nObligaciones. $0\n5.- Otros.\nTOTAL DE INGRESOS $1,037,239,346\nTÍTULO II.- IMPUESTOS\nCAPÍTULO I\nIMPUESTO SOBRE LOS INGRESOS\n1.- IMPUESTO SOBRE ASISTENCIA A JUEGOS PERMITIDOS Y ESPECTÁCULOS\nPÚBLICOS\nARTÍCULO 2.- Son sujetos de este Impuesto, los asistentes a juegos permitidos, espectáculos públicos y centros de diversión, así como a funciones de obra de teatro y circo. No se considerarán espectáculos públicos los presentados en Restaurantes, Bares, Cabarets, Salones de Fiesta o de Baile y Centros Nocturnos, cuando se acredite previamente a la celebración del evento que los ingresos por dichos espectáculos, serán acumulados a los propios del establecimiento.\nARTÍCULO 3.- Tratándose de juegos permitidos, espectáculos públicos y centros de diversión la tasa aplicable será del doce por ciento.\nEn el caso de funciones de obra de teatro y circo, la tasa será del cuatro por ciento, en ambos casos, el Impuesto se calculará sobre el precio de admisión, debiéndose entregar al empresario al momento de comprar el boleto o a la entrada del espectáculo público.\nLos espectáculos taurinos y eventos deportivos se gravarán con el cinco por ciento, debiéndose entregar al empresario, en ambos casos, al momento de pagar o a la entrada del espectáculo.\nNo se pagará este Impuesto, tratándose de eventos realizados por\nPartidos Políticos o por el Sistema para el Desarrollo Integral de la Familia (DIF) Municipal.\nTratándose de espectáculos realizados por organismos no lucrativos que brinden servicios y asistencia médica de manera gratuita a enfermos que padezcan cáncer en etapa terminal, debidamente la ley de la materia, gravarán este impuesto a tasa cero.\nARTÍCULO 4.- Los propietarios del lugar donde se presenten, o realicen los espectáculos, juegos o centros de diversión, los organizadores o centros de diversión, serán solidariamente responsables del pago de este Impuesto, debiéndose enterar a la Recaudación de Rentas\nMunicipal, en el momento de celebrar éste por conducto del interventor(es) que al efecto designe la autoridad fiscal, previa\nMunicipal, en el caso que sea intervenido el evento.\nARTÍCULO 5.- Los espectáculos en los que participen deportistas, músicos y actores no profesionales, así como los realizados por instituciones educativas, entidades paramunicipales y por organizaciones que no persigan fines de lucro, independientemente de que participen deportistas, músicos o actores profesionales, sobre espectáculo, tres por ciento.\nARTÍCULO 6.- Los ingresos serán supervisados por los interventores que designe la autoridad fiscal, con las facultades que la Ley les otorga.\nNinguna de las actividades que señala el Artículo 2 de esta Ley aunque sea en forma eventual, podrá practicarse sin avisar por escrito a la\nRecaudación de Rentas Municipal, con mínimo de 24 horas de anticipación a su celebración, indicando la naturaleza y características de aquéllas.\n2.- IMPUESTO A CENTROS DE APUESTAS, APUESTAS REMOTAS, SALAS DE\nSORTEOS, DE NÚMEROS Y/O CASINOS\nARTÍCULO 7.- Los permisionarios que derivado de sus actividades de juegos con apuestas o sorteos, que otorguen premios en efectivo o en especie al amparo de un permiso federal otorgado por la Secretaría de Gobernación o de una resolución judicial que haya causado estado, registrados y reconocidos en la página oficial de la citada Secretaría de Gobernación, pagarán el Impuesto correspondiente conforme a lo siguiente:\nPara los organizadores de juegos con apuestas permitidas y/o habilidades y destrezas, tres por ciento.\nPara los efectos de este Artículo, las personas que organicen juegos la participación o la apuesta, deduciéndose a dicha base gravable el valor del premio efectivamente recibido de los participantes.\nArtículo, no causarán los Impuestos y Derechos contenidos en esta Ley relativos a las máquinas de juego, calcomanía por máquina, holograma por máquina o cualquier otro análogo; así como por la obtención de permisos, revalidación o licencia de operación del establecimiento de los mismos.\nCAPÍTULO II\nIMPUESTO SOBRE EL PATRIMONIO\n3.- IMPUESTO PREDIAL\nARTÍCULO 8.- El Impuesto Predial se causará de acuerdo a lo que se\nInmobiliario del Estado de Baja California, así como en el Reglamento del Catastro Inmobiliario del Municipio de Tecate, Baja California, de conformidad con la Tabla de Valores Catastrales Unitarios, elaborada por el Consejo Municipal del Catastro Inmobiliario de\nTecate, y aprobada por el Congreso del Estado para el Municipio de\nTecate, Baja California.\n-----------------------------------------------------------------------------------------------------------------------------------\nVALOR FISCAL\nPOR m²\n(PESOS)\n-----------------------------------------------------------------SECTOR \"A\"\n-----------------------------------------------------------------Colonia Pro-Hogar 2,000.00\nColonia Espinoza 2,000.00\nFraccionamiento Zorrilla 2,000.00\nColonia Federal 2,000.00\nFraccionamiento La Hacienda 2,000.00\nColonia Downey 2,000.00\nColonia Moderna 2,000.00\nPrimera Sección 2,200.00\nFraccionamiento Romero 2,000.00\n-----------------------------------------------------------------SUB-SECTOR “A”\n-----------------------------------------------------------------Colonia La Viñita\nViñita Norte 2,000.00\nViñita Sur 2,000.00\nFraccionamiento Ferrocarril 2,000.00\nInfonavit Fraccionamiento La Hacienda 2,000.00\nEntre Portes Gil y Presidente Rodríguez 2,500.00\nEntre Presidente Rodríguez y Ortiz Rubio 2,500.00\nEntre Ortiz Rubio y Cárdenas 2,750.00\nEntre Cárdenas y Presidente Calles 2,750.00\nEntre Presidente Calles y Presidente Carranza 2,500.00\nEntre Portes Gil y Ortiz Rubio 2,200.00\nEntre Ortiz Rubio y Presidente Calles 2,300.00\nEntre Presidente Calles y Carranza 2,000.00\nEntre Portes Gil y Presidente Abelardo L. Rodríguez 2,300.00\nEntre Presidente Abelardo L. Rodríguez y Calles 2,400.00\nEntre Presidente Calles y Carranza 2,400.00\nAvenida México Primera Sección 2,200.00\nCallejón Libertad Primera Sección 2,350.00\nCallejón Reforma Primera Sección 2,350.00\nCallejón Madero Primera Sección 2,000.00\nBulevar Defensores de Baja California\nEntre Bulevar Benito Juárez y\nCalle Dr. Arturo Guerra Flores 2,300.00\nEntre Calle Dr. Arturo Guerra y\nCalzada Universidad 2,400.00\nEntre Calzada Universidad y\nCalle Portes Gil 2,400.00\nRancho González 2,000.00\nPolígono Cervecería Tecate(PS-022-002)(53,219.00 m²) 2,750.00\nPolígono Casa Social (GR-001-011) (68,573.42 m²) 2,000.00\n-----------------------------------------------------------------SECTOR \"B\"\n-----------------------------------------------------------------Fraccionamiento San Fernando 2,000.00\nCentro Urbano 2,500.00\nCondominio Privada Rincón del Paraíso 2,500.00\n-----------------------------------------------------------------SUB-SECTOR “B”\n-----------------------------------------------------------------Calzada Universidad\nEntre Bulevar Defensores de Baja California y Bulevar Nuevo León 2,750.00\nSF-005-009 AL 014 1,800.00\nSF-010-003 1,800.00\nCorredor Avenida Nuevo León\nEntre Calzada Universidad a Calle Dr. Arturo Guerra F. 3,000.00\nPolígono Encinos\nClaves catastrales:\nLE-001-001 (39,486.30 m²) 2,000.00\nLE-001-002 (13,256.96 m²) 2,000.00\nLE-001-062 (38,350.45 m²) 2,000.00\nLE-001-122 (20,000.00 m²) 2,000.00\nLE-001-152 (20,000.00 m²) 1,750.00\nRancho San Francisco (CT-608-003)(67,419.22 m²) 800.00\nRancho San Francisco (CT-608-063)(40,000.00 m²) 900.00\n-----------------------------------------------------------------SECTOR “C”\n-----------------------------------------------------------------Fraccionamiento Valencia 1,600.00\nColonia Guajardo 1,300.00\nColonia IV Ayuntamiento 1,500.00\nColonia Militar 1,500.00\nColonia Cuauhtémoc 1,500.00\nFraccionamiento San Rafael 1,500.00\n-----------------------------------------------------------------SUB-SECTOR “C”\n-----------------------------------------------------------------Infonavit Colonia Cuauhtémoc Oeste (Las Huertas) 1,000.00\nInfonavit Colonia Guajardo (Industrial) 1,000.00\nCorredor Calzada Universidad\nEntre Bulevar Nuevo León a Calle Insurgentes 2,000.00\nPromotora de Mercados El Parián 2,000.00\nCN-000-003 (104,116.70 m²) 100.00\nCM-720-002 (3,195.64 m²) 100.00\nCM-720-003 (8,806.19 m²) 100.00\nCM-720-033 (2,272.74 m²) 100.00\nCN-000-002 (145,033.57 m²) 50.00\nCN-000-001 (341,566.01 m²) 40.00\nFraccionamiento Burócratas (irregular) 1,300.00\n-----------------------------------------------------------------SECTOR “D”\n-----------------------------------------------------------------Colonia Industrial 2,000.00\nFraccionamiento Pliego 2,400.00\n-----------------------------------------------------------------SUB-SECTOR “D”\n-----------------------------------------------------------------Colonia Esteban Cantú 1,800.00\nColonia Aldrete 1,800.00\nFraccionamiento El Descanso 2,000.00\nCorredor Avenida Juárez\nDe Calle Portes Gil a Monumento\nJosé María Morelos y Pavón 2,000.00\nCorredor Avenida Hidalgo\nDe Calle Portes Gil a Monumento\nJosé María Morelos y Pavón 2,000.00\nCorredor Paseo José María Morelos y Pavón\nTorreón 2,000.00\nInfonavit Fraccionamiento Pliego 2,400.00\nInfonavit Colonia Cuauhtémoc Este 1,600.00\nColonia Maestros (Magisterial) 1,300.00\nCA-525-001 (168,392.52 m²) 100.00\nCI-023-031 (50,000.00 m²) 1,500.00\nCI-023-001 (12,705.00 m²) 1,600.00\nCI-024-001 (7,317.00 m²) 1,200.00\nCI-023-091 (12,715.58 m²) 1,800.00\nCC-017-091 (25,830.00 m²) 286.65\nFOVISSSTE 2,000.00\nCI-023-032 (45,385.09 m²) 1,400.00\nCI-025-002 (18,046.90 m²) 1,200.00\nCI-026-001 (12,014.73 m²) 1,700.00\nFD-525-001 (3,514.71 m²) 1,400.00\nFD-525-031 (8,730.01 m²) 1,200.00\nFD-525-061 (19,313.77 m²) 900.00\nFD-525-151 (4,099.43 m²) 1,600.00\nFD-600-001 (39,980.90 m²) 800.00\nCorredor Tecate-Mexicali de la clave FD 525-151 a\nCecati 1,800.00\n-----------------------------------------------------------------SECTOR “E”\n-----------------------------------------------------------------Colonia Ampliación Colinas 2,000.00\nColonia Colinas del Cuchumá 2,000.00\nFraccionamiento El Refugio 2,000.00\nColonia Chávez 2,000.00\nColonia El Encanto Norte 2,000.00\nRancho Flores 1,800.00\nPrivada Mi Ranchito 2,000.00\nColonia El Encanto Sur 1,800.00\nPrivada Palmillas 2,000.00\n-----------------------------------------------------------------SUB-SECTOR “E”\n-----------------------------------------------------------------Colonia Bella Vista 1,500.00\nColonia Solidaridad 1,500.00\nColonia Cuchumá Norte 1,500.00\nAvenida Revolución de Calle 15 a Calle 2,100.00\nVenustiano Carranza\nAvenida Revolución de Calle 15 a Bulevar Benito Juárez 2,100.00\nBulevar Juárez\nDe Calle 15 a Calle Paralelo 28 2,200.00\nPlaza Cuchumá 1,800.00\nÁrea Industrial entre Encanto Sur y Colonia Chávez 1,500.00\nRR-026-010 (5,355.50 m²) 2,000.00\nEN-004-001 (19,622.75 m²) 1,750.00\nES-011-013 (9,870.34 m²) 1,750.00\nRF-018-031 (14,610.42 m²) 1,000.00\nRF-018-061 (3,570.00 m²) 1,000.00\nRF-018-151 (5,527.12 m²) 1,000.00\nCorredor Tecate-Tijuana Prolongación Bulevar Benito\n1,957.00\nJuárez de calle paralelo 28 a Bulevar Encinos\n-----------------------------------------------------------------SECTOR “F”\n-----------------------------------------------------------------Colonia Loma Alta 1,400.00\nResidencial San Jorge Media 1,600.00\nResidencial San Jorge Popular 1,500.00\nColonia El Paraíso 1,500.00\nColonia B. Maldonado 1,500.00\nColonia Benito Juárez 1,800.00\nCorredor Calle Quinta\nDe Calle Culiacán a Calle Mariano Escobedo 1,900.00\nCorredor Calle Dr. Arturo Guerra F.\nDe Calle Campeche a Quinta Avenida 2,200.00\nColonia Morelos 1,500.00\nAvenida Morelos de Calzada Universidad 1,800.00 a Calle Culiacán\nColonia Emiliano Zapata I 1,500.00\nColonia Emiliano Zapata II 1,500.00\n-----------------------------------------------------------------SUB-SECTOR “F”\n-----------------------------------------------------------------Infonavit Colonia El Paraíso 1,400.00\nInfonavit Colonia Loma Alta 1,400.00\n-----------------------------------------------------------------SECTOR “G”\n-----------------------------------------------------------------Colonia Primero de Mayo 1,100.00\nColonia Libertad (asentamiento irregular) 1,100.00\n-----------------------------------------------------------------SUB-SECTOR “G”\n-----------------------------------------------------------------Parque Industrial Tecate 1,500.00\nPI-010-005 (2,202.30 m²) 1,500.00\nFraccionamiento Arroyo 1,500.00\nFraccionamiento Andalucía 1,800.00\nEA-006-004 (10,118.49 m²) 1,000.00\nEA-007-000 (63,801.15 m²) 1,000.00\nEA-008-000 (60,850.60 m²) 1,000.00\nEA-008-003 (6,464.59 m²) 1,200.00\nMA-501-016 (36,672.44 m²) 500.00\nXL-030-016 (60,449.06 m²) 1,000.00\nXL-030-009 (144,859.96 m²) 1,000.00\nXL-030-008 (144,859.95 m²) 1,000.00\n-----------------------------------------------------------------SECTOR “H”\n-----------------------------------------------------------------Cucapáh 1,400.00\nFraccionamiento Emiliano Zapata 1,000.00\nJardines del Río 1,000.00\nFH-525-001 (129,884.67 m²) 800.00\nFH-525-002 (53,234.80 m²) 800.00\n-----------------------------------------------------------------SUB-SECTOR “H”\n-----------------------------------------------------------------Fraccionamiento Fundadores 1,200.00\nFraccionamiento Colosio 800.00\nColonia Santa Fe 1,000.00\nColonia Valle Verde 800.00\nLa Nopalera 1,000.00\nEl Jardín 1,000.00\nTerrazas del Río 1,500.00\nFraccionamiento El Mayab 1,500.00\nFraccionamiento Campestre Tecate 1,500.00\nCorredor Tecate-Mexicali de Cecati a Parque Industrial\nCorredor Tecate-Mexicali de Parque Industrial a puente 1,802.50\nSan José 1,622.25\nVistas del Sol 1,500.00\n-----------------------------------------------------------------SECTOR “I”\n-----------------------------------------------------------------Colonia Francisco Villa 1,100.00\nColonia Rincón Tecate\nAl Norte del Río 1,100.00\nAl Sur del Río 1,100.00\nFrancisco Villa Sur (asentamiento irregular) 1,100.00\nFraccionamiento Loma Dorada 1,500.00\nLos Olivos 1,500.00\n-----------------------------------------------------------------UB-SECTOR “I”\n-----------------------------------------------------------------Colonia La Bondad 1,100.00\nColonia XIII Ayuntamiento 1,100.00\nFraccionamiento Escudero 1,200.00\nFraccionamiento Universidad 1,100.00\nLa Rinconada 1,100.00\nCalzada Universidad\nDe Calle Insurgentes a Calle Jiquilpan 1,700.00\nCalzada Universidad\nDe Calle Jiquilpan a Calle Lázaro Cárdenas 1,100.00\nTR-577-001 (88,040.00 m²) 175.00\nTR-577-002 (67,500.00 m²) 175.00\nPrivada Santa María 1,200.00\nTerranova 800.00\nFraccionamiento La Brecha Norte y Sur 800.00\n-----------------------------------------------------------------SECTOR “J”\n-----------------------------------------------------------------Colonia Miguel Alemán 1.200.00\nColonia Lázaro Cárdenas I y II 1,200.00\nColonia Lázaro Cárdenas III 1,200.00\nAmpliación Descanso 1,200.00\nColonia Flores Magón 1,200.00\n-----------------------------------------------------------------SUB-SECTOR “J”\n-----------------------------------------------------------------Calzada Universidad\nDe Calle Lázaro Cárdenas hasta autopista de cuota 1,000.00\nXA-070-062 600.00\nCorredor Tecate-Ensenada de autopista Tecate-Tijuana a acceso Santa Anita 1,800.00\n-----------------------------------------------------------------SECTOR “K”\n-----------------------------------------------------------------Colonia Maclovio Herrera\nHasta 500.00 m² 1,000.00\nDe 501.00 m² hasta 1,001.00 m² 600.00\nMayores de 1,001.00 m² hasta 2,000.00 m² 500.00\nDe 2,001.00 m² hasta 5,000.00 m² 300.00\nDe 5,001.00 m² hasta 10,000.00 m² 150.00\nMayores de 10,000.00 m² 90.00\nAcceso Colonia Maclovio Herrera, zona comercial\nDe carretera a Tecate-Eda hasta bifurcación Santa\nAnita Aeropuerto 1,800.00\nColonia Alfonso Garzón\nHasta 2,000.00 m² 1,000.00\nDe 2,001.00 m² hasta 5,000.00 m² 400.00\nDe 5,001.00 m² hasta 10,000.00 m² 200.00\nMayores de 10,000.00 m² 150.00\nColonia Salamandra 800.00\nColonia Tanamá 1,200.00\nFraccionamiento Residencial Moctezuma 1,800.00\nColonia Cortez 500.00\n-----------------------------------------------------------------SUB-SECTOR “K”\n-----------------------------------------------------------------Zona Industrial Aeropuerto 1,000.00\nPolígonos Baldíos\nHasta 2,000.00 m² 300.00\nDe 2,001.00 m² a 5,000.00 m² 250.00\nDe 5,001.00 m² hasta 10,000.00 m² 150.00\nMH-505-006 (XA070010)(20,000.00 m²) 100.00\nFraccionamiento Santa Anita 1,600.00\nFraccionamiento Santa Anita Corredor Comercial 1,800.00\nFraccionamiento El Mirador 800.00\nColinas del Tepeyac 600.00\nFraccionamiento Las Torres 600.00\nColonia Lombardo Toledano 400.00\nRancho Heredia 600.00\nFraccionamiento Los Membrillos 1,000.00\nFraccionamiento Villa Las Flores 1,500.00\nFraccionamiento Los Arcos 300.00\nFraccionamiento Las Rocas 600.00\nPiedra Angular 600.00\nFraccionamiento Bicentenario 600.00\nFraccionamiento Ecochumá 600.00\nLos Presidentes 600.00\nCorredor Tecate-Ensenada de acceso Santa Anita a Km. 4 1,500.00\n-----------------------------------------------------------------SECTOR “L”\n-----------------------------------------------------------------Fraccionamiento Sierra de Tecate 600.00\nFraccionamiento Laderas 600.00\nFraccionamiento El Yaqui 600.00\nMontisán (asentamiento irregular) 500.00\nGranja El Porvenir 500.00\nColonia San José 500.00\n-----------------------------------------------------------------ZONIFICACIÓN SUBURBANA\n-----------------------------------------------------------------VALOR FISCAL\nPOR m²\n(PESOS)\n-----------------------------------------------------------------ZONA 2 (XA00)\n-----------------------------------------------------------------Parque Industrial El Bajío 1,500.00\nXA-150-006 900.00\nXA-150-008 900.00\nRancho La Puerta (XA02)\n(Casco construido) 1,200.00\nZona Rústica Rancho La Puerta 100.00\nColinas del Escorial 600.00\nColonia Vista Hermosa 500.00\nColonia La Joya 600.00\nColonia El Escorial 600.00\nLa Paloma (XA01) 600.00\nXA-040-013 (499,302.88 m²) 100.00\nXA-010-031 (371,215.00 m²) 100.00\nXA-020-020 (536,857.88 m²) 100.00\nÁrea Loma Linda (XA03)\nHasta 10,000.00 m² 500.00\nFraccionamiento San Ángel 1,400.00\nCondominio Santa Mónica 1,200.00\nCondominio San Francisco 1,200.00\nCondominio San Vicente 1,200.00\nCondominio Santa Lucía 1,200.00\nCondominio San José 1,200.00\nCondominio Santa Teresita 1,200.00\nCondominio San Lucas 1,200.00\nCondominio San Felipe 1,200.00\nÁrea Paso del Águila (XA04)\nHasta 2,000.00 m² 500.00\nPaso del Águila Área Industrial 500.00\nCañada Verde\nHasta 2,000.00 m² 300.00\nMayor de 2,000.00 m² 250.00\nXA-030-004 (31,542.72 m²) 1,500.00\nXA-180-035 (8.000.00 m²) 1,200.00\nXA-180-036 (512,298.00 m²) 70.00\nFraccionamiento Dos Caminos 400.00\nFraccionamiento La Ilusión 800.00\nCorredor Tecate-Tijuana\nDe Bulevar Encinos a Rancho La Puerta 1,100.00\nDe Rancho La Puerta a Km. 138 700.00\nDe Km. 138 a Acceso Autopista Tecate-Tijuana 1,100.00\nRancho Enriqueta 400.00\n-----------------------------------------------------------------ZONA 3 (XA00)\n-----------------------------------------------------------------Los Alisos (balneario) 250.00\nLos Sahuaros (balneario) 250.00\nRancho El Capiri\nÁrea Lotificada 250.00\nRancho Los Arcos\nÁrea Lotificada 250.00\nHawaiano 150.00\nFraccionamiento Santa Teresa 150.00\nTS-004-019 (39,055.46 m²) 100.00\nZona El Carricito\nÁrea Lotificada 150.00\nColonia La Fuente 150.00\nColonia Rincón Mediterráneo 150.00\n-----------------------------------------------------------------ZONA 4 (XB00)\n-----------------------------------------------------------------Rancho Tecate Fraccionamiento\nRancho Tecate Área lotificada 1,800.00\nRancho Tecate Área Turística 100.00\nRancho Tecate Área No Desarrollada 55.00\n-----------------------------------------------------------------ZONA 5 (XC00)\n-----------------------------------------------------------------Nueva Colonia Hindú (frente a carretera) 300.00\nNueva Colonia Hindú, hasta 2,500.00 m² 150.00\nMayor de 2,500.00 m² hasta 5,000.00 m² 100.00\nMayor de 5,000.00 m² hasta 10,000.00 m² 80.00\nTanamá, hasta 2,500.00 m² 150.00\nFraccionamiento Universitario (lotificado) 300.00\nFraccionamiento San Carlos (lotificado) 200.00\nColonia Viveros, hasta 2,500.00 m² 150.00\nColonia Buenos Aires, hasta 2,500.00 m² 150.00\nColonia Cerro Azul, hasta 2,500.00 m² 150.00\nColonia Cañón del Yaqui, hasta 2,500.00 m² 150.00\nColonia Cafetalera, hasta 2,500.00 m² 150.00\nColonia El 16, hasta 2,500.00 m² 150.00\nColonia Los Gordos, hasta 2,500.00 m² 150.00\nColonia Santa Mónica, hasta 2,500.00 m² 150.00\nFraccionamiento San Isidro (Fraccionamiento en proceso) 300.00\nLos Laureles 300.00\nFraccionamiento Cumbres 300.00\n-----------------------------------------------------------------ZONA 6 (XD00) (XE00)\n-----------------------------------------------------------------Valle de las Palmas (lotificado en poblado) 400.00\nRancho Viejo (lotificado)\nHasta 2,000.00 m² 200.00\nMayor de 2,000.00 m² 100.00\nFraccionamiento Arboledas (lotificado) 300.00\nColonia Pueblo y Gobierno (lotificado) 300.00\nColonia Parcela 94 (lotificado) 300.00\nXE-040-046 (50,000.00 m²) 150.00\nXE-040-090 (760,000.00 m²) 80.00\nXE-040-096 (1,960,000.00 m²) 10.00\nXE-040-167 (84,400.00 m²) 150.00\nXE-040-174 (99,450.00 m²) 150.00\nXE-040-220 (400,000.00 m²) 80.00\nDesarrollo Campestre Loma Bonita 300.00\n-----------------------------------------------------------------ZONA 7 (XG00)\n-----------------------------------------------------------------El Testerazo (lotificado) 150.00\nColonia El Chaco (lotificado) 150.00\nEjido Zaragoza (XI00) (lotificado) 150.00\n-----------------------------------------------------------------ZONA 8 (XG00)\n-----------------------------------------------------------------Ejido Carmen Serdán (lotificado) 100.00\n-----------------------------------------------------------------ZONA 9 (XF00)\n-----------------------------------------------------------------Ejido Héroes del Desierto (lotificado) 60.00\n-----------------------------------------------------------------ZONA 10\n-----------------------------------------------------------------Rancho Banchetti (lotificado) 500.00\n-----------------------------------------------------------------ZONA 11 (XX00)\n-----------------------------------------------------------------Fraccionamiento Los Manantiales (lotificado) 300.00\nColonia Ciénega Redonda (lotificado) 300.00\n-----------------------------------------------------------------ZONA 12\n-----------------------------------------------------------------El Encinal\nHasta 5,000.00 m² 200.00\nRancho La Escondida\nHasta 20,500.00 m² 160.00\nFraccionamiento Loma Bonita (lotificado) 300.00\nLOMA TOVA\nXN-050-053 (100,000.00 m²) 57.33\nLoma Tova (lotificado) 150.00\nFraccionamiento Las Fuentes 300.00\nFraccionamiento Campestre Manzanitos 200.00\nFraccionamiento Villa Esperanza 200.00\nFraccionamiento Héroes de México 200.00\nCampestre Paraíso Los Encinos 200.00\n-----------------------------------------------------------------ZONA 13 (XU00)\n-----------------------------------------------------------------Fraccionamiento Eréndira (lotificado) 500.00\n-----------------------------------------------------------------ZONA 14 (XU00)\n-----------------------------------------------------------------Cañada del Sol (lotificado) 40.00\nHuertas Cañada Verde Tecate 40.00\nHuertas Cañada Verde Tijuana 40.00\nHuertas Cañada Verde Ensenada 40.00\nHuertas Cañada Verde Mexicali 40.00\nCañada del Águila (lotificado) 15.00\nGranjas Mortera (lotificado) 15.00\nFraccionamiento San Andrés (lotificado) 75.00\nFraccionamiento Villa Soledad (lotificado) 40.00\nCañada Verde (El Edén) 120.00\nFraccionamiento Ruta de las Misiones 120.00\n-----------------------------------------------------------------ZONA 15 (XR00)\n-----------------------------------------------------------------Ejido Chula Vista (lotificado) 75.00\nJardines del Rincón (lotificado) 55.00\nRoca Magisterial (lotificado) 55.00\nEjido Mi Ranchito (XS00) 55.00\nEjido General Felipe Ángeles (XX00) (lotificado) 55.00\nFraccionamiento Alquimia Campestre 55.00\n-----------------------------------------------------------------ZONA 16 (XY00)\n-----------------------------------------------------------------Colonia Luis Echeverría (lotificado) 150.00\nAvenida Juárez entre carretera y Calle 21 250.00\nEjido Baja California (lotificado) 150.00\nFraccionamiento El Triunfo 150.00\nColonia Granjas El Hongo 110.00\n-----------------------------------------------------------------ZONA 17 (XU00)\n-----------------------------------------------------------------Las Juntas (lotificado) 50.00\nFraccionamiento California (lotificado) 50.00\nColonia El Piñón (lotificado) 50.00\n-----------------------------------------------------------------ZONA 18 (XO00)\n-----------------------------------------------------------------Santa Verónica (lotificado) 100.00\nEjido Nuevo Porvenir (XV00) (XW00) (lotificado) 40.00\nEjido Guadalajara (lotificado) 40.00\n-----------------------------------------------------------------ZONA 19\n-----------------------------------------------------------------Rancho Los Columpios (lotificado) 110.00\n-----------------------------------------------------------------ZONA 20 (XZ00)\n-----------------------------------------------------------------Ejido Jacumé (lotificado) 35.00\nEjido Jacumé Industrial 35.00\nRancho Denton (lotificado) 35.00\nRancho Sández (lotificado) 35.00\nColonia Sández (lotificado) 35.00\n-----------------------------------------------------------------ZONA 21 (KA00)\n-----------------------------------------------------------------El Cóndor (lotificado) 35.00\nColonia Mesa Colorada (lotificado) 35.00\nColonia La Raqueta (lotificado) 35.00\nFraccionamiento Bosques del Cóndor 80.00\nClub Campestre Las Rosas 40.00\n-----------------------------------------------------------------ZONA 22 (KE00)\n-----------------------------------------------------------------La Rumorosa Franja Comercial 500.00\nHasta 1,000.00 m²\nLa Rumorosa Habitacional 150.00\nEjido Aubanel Vallejo (lotificado) 100.00\nFraccionamiento Alaska (lotificado) 100.00\nFraccionamiento Sierra Linda (lotificado) 150.00\nFraccionamiento Campestre Club Hacienda(lotificado) 100.00\nFraccionamiento Lomas del Pinar (área lotificada) 100.00\nFraccionamiento Santa María del Oro (lotificado) 100.00\nColonia El Llano (lotificado) 100.00\nRancho Gámez (lotificado) 45.00\nColonia Municipio 86 (lotificado) 100.00\nColonia El Borrego (lotificado) 100.00\nColonia La Ponderosa (lotificado) 45.00\nColonia Las Caleras (lotificado) 80.00\nEjido José María Pino Suárez (KB00) (lotificado) 15.00\nEjido Cordilleras de Molina (KD00) (lotificado) 15.00\nCampo Turístico El Chaparral (Rumorosa) 50.00\nFraccionamiento Sierra Linda Campestre (lotificado) 100.00\nFraccionamiento Los Pinos 100.00\nFraccionamiento La Calera 100.00\nFraccionamiento Villa Campestre 100.00\nFraccionamiento Las Flores 100.00\nFraccionamiento Mexicali 100.00\nFraccionamiento Moderna 100.00\nFraccionamiento Loma Bonita 70.00\nFraccionamiento Las Choyas (irregular) 70.00\nFraccionamiento Pinos Altos (irregular) 70.00\nPrivada Punta del Cielo 150.00\nFraccionamiento Campestre Los Pinos 30.00\nFraccionamiento Valle de los Pinos 40.00\n-----------------------------------------------------------------ZONA 23 (XL00)\n-----------------------------------------------------------------Rancho Rivera, hasta 10,000.00 m² 100.00\nCañón Joe Bill, hasta 10,000.00 m² 100.00\nSan Pablo hasta 2,000.00 m² 200.00\nHacienda Tecate 1,300.00\nHacienda Tecate Sección Las Misiones 1,300.00\nSan José, Hasta 2,000.00 m² 250.00\nMayor de 2,001.00 a 5,000.00 m² 160.00\nVillas Artesanales, hasta 10,000.00 m² 130.00\nÁrea Industrial San Pablo 600.00\nXL-040-023 (10,000.00 m²) 700.00\nXL-040-024 (2,192.29 m²) 900.00\nXL-050-036 (10,156.17 m²) 700.00\nXL-050-089 (20,000.00 m²) 550.00\nFraccionamiento 2 Cumbres 500.00\n-----------------------------------------------------------------ZONA 24\n-----------------------------------------------------------------Agua Fría, hasta 10,000.00 m² 200.00\nXL-050-159 (60,428.43 m²) 500.00\nXL-070-001 (24,679.59 m²) 500.00\n-----------------------------------------------------------------de este Artículo, podrá pedir un peritaje especial sobre el predio o predios dubitados. Este nuevo avalúo se realizará por dos peritos debidamente autorizados, uno será designado por la autoridad municipal y el contribuyente designará al propio. En caso de discrepancia se designará un tercer perito en discordia seleccionado de entre los peritos valuadores debidamente registrados en plaza. El peritaje final vigente, para los efectos de este Artículo será el coincidente y en caso de discrepancia se tomará el promedio que resulte de los dos avalúos más bajos. El costo de los avalúos será con cargo al contribuyente.\nARTÍCULO 9.- Para efectos de la presente Ley se entenderá como:\nA.- PREDIOS URBANOS.- Son aquéllos comprendidos dentro de los límites del centro de población de la Ciudad de Tecate.\nB.- PREDIOS SUBURBANOS.- Son los comprendidos fuera de los límites del centro de población de la Ciudad de Tecate, pero dentro de los límites del centro de población de cualquier otro poblado, colonia, comunidad o ranchería.\nC.- PREDIOS RÚSTICOS.- Son los comprendidos fuera de los límites del centro de población de la Ciudad de Tecate, Delegaciones, Poblados, Colonias, Comunidades o Rancherías.\nD.- PREDIOS HABITACIONALES.- Son aquéllos en los cuales habite su propietario o poseedor.\nE.- PREDIOS COMERCIALES.- Son aquéllos sobre los cuales se transferidos en arrendamiento por su dueño o posesionario.\nF.- PREDIO CON USO MIXTO (HABITACIONAL-COMERCIAL).- Son aquéllos en los cuales habite su propietario o poseedor con justo título, mercantil del Régimen de Incorporación Fiscal, de conformidad con la Ley del Impuesto Sobre la Renta.\nG.- PREDIOS TURÍSTICOS.- Son aquéllos en que se establece una negociación del ramo turístico, siempre y cuando ésta sea del predio.\nH.- PREDIOS INDUSTRIALES.- Son aquéllos sobre los cuales se establezca una negociación industrial, siempre y cuando ésta propietaria del predio.\nI.- PREDIOS FRACCIONADOS.- Son aquéllos que son propiedad de fraccionamientos autorizados, destinados para su venta.\nJ.- PREDIOS DE USO SOCIAL.- Son aquéllos en propiedad o en posesión de Asociaciones Civiles, Sociedades u Organizaciones de\nProductores que realicen actividades agropecuarias y ganaderas, así como de Asociaciones Religiosas o de Beneficencia o Partidos\nPolíticos, todas debidamente constituidas y registradas.\nK.- PREDIOS CONSTRUIDOS.- Son aquéllos que cuenten con construcciones permanentes o móviles, siempre y cuando estén debidamente cimentadas o fijas.\nL.- PREDIOS BALDÍOS O NO EDIFICADOS.- Al que encuadre en cualquiera de los siguientes supuestos:\na).- Al Predio Urbano que no tenga construcciones y no presente condiciones de uso, aprovechamiento o habitabilidad.\nb).- Al Predio Urbano que teniendo construcciones en proceso, en receso o en estado ruinoso, presente condiciones de inseguridad y se encuentre improductivo.\nc).- Al Predio Urbano que teniendo construcciones no habitadas por el propietario, al hacerse el avalúo de éstas, resulten con terreno, en zonas que cuenten como mínimo con servicios de agua, electricidad y drenaje.\nd).- Al predio que teniendo construcciones, éstas sean de carácter provisional, los materiales usados sean de uso transitorio o improductivo.\nPara los efectos de lo dispuesto en los puntos anteriores, se entiende que un predio es improductivo, cuando siendo urbano, no sea utilizado con fines habitacionales, educativos, para la realización de actividades comerciales, industriales, de equipamiento o servicios y carezca de equipamiento y mantenimiento adecuado a su uso.\nNo se consideran Predios Baldíos o No Edificados, los que sean utilizados con fines habitacionales, educativos, comerciales, industriales, de prestación de servicios, cuyas áreas constituyan jardines ornamentales o se aprovechen en la realización de actividades deportivas, siempre y cuando cuenten con la infraestructura, equipamiento e instalaciones necesarias para dicho objeto.\nM.- PREDIOS SUBURBANOS ABANDONADOS.- Son aquéllos predios que cuenten con construcción o construcciones desocupadas que no presenten condiciones de uso, aprovechamiento o habitabilidad.\nN.- PREDIOS RÚSTICOS AGROPECUARIOS.- Son aquellos Predios Rústicos explotados por cualesquiera de las ramas de la actividad agropecuaria en producción por sus dueños.\nLos predios comprendidos dentro de los límites del centro de población de la Ciudad de Tecate baldíos sin unos o más de los servicios de agua, electricidad o drenaje se mantendrán en la tasa que indica el\nArtículo 10 inciso G) hasta que se establezca en ellos una construcción con fines habitacional, comercial, industrial, educativo, turísticos, religiosos o tenga los tres servicios anteriormente mencionados.\nARTÍCULO 10.- El monto del Impuesto Predial se determinará multiplicando el valor fiscal por metro cuadrado catastral, por el predio, considerando los incrementos o deméritos que determine la autoridad competente, de acuerdo a su uso o destino.\nAplicándole las siguientes:\nA).- Predios Habitacionales Urbanos destinados total o exclusivamente para habitación:\na).- De sus propietarios............... 0.20% sobre su valor\nb).- De sus propietarios cuando éstos sean pensionados, jubilados, discapacitados, por viudez e indigentes mayores de sesenta años, que acrediten su condición con identificación expedida por institución pública............... 0.15% sobre su valor\nNo aplicarán subvenciones en predios donde existan 2 o más construcciones habitacionales.\nc).- Predios con Uso Mixto............. 0.35% sobre su valor\nB).- Predios Habitacionales Suburbanos destinados total o exclusivamente para habitación:\na).- De sus propietarios............... 0.17% sobre su valor\nb).- De sus propietarios cuando éstos sean pensionados, jubilados, discapacitados e indigentes mayores de sesenta años, que acrediten su condición con identificación expedida por institución pública.. 0.11% sobre su valor\nc).- Predios con Uso Mixto............. 0.30% sobre su valor\nC).- Predios Comerciales y Turísticos\nUrbanos............................ 0.50% sobre su valor\na).- Predios Comerciales y Turísticos\nSuburbanos........................ 0.45% sobre su valor\nD).- Predios Industriales Urbanos....... 0.60% sobre su valor\na).- Predios Industriales Suburbanos... 0.55% sobre su valor\nb).- Predios Industriales o\nInstalaciones para la generación y transmisión de energía eléctrica......................... 0.60% sobre su valor\nE).- Predios Fraccionados............... 0.24% sobre su valor\nF).- Predios de Uso Social.............. 0.14% sobre su valor\nG).- Predios Baldíos o No Edificados.... 0.54% sobre su valor\nH).- Predios Rústicos................... 0.47% sobre su valor\nI).- Predios Rústicos Agropecuarios..... 0.16% sobre su valor\nJ).- Predios Suburbanos Baldíos......... 0.30% sobre su valor\nK).- Predios Suburbanos Abandonados..... 1.50% sobre su valor\nL).- Predios Urbanos Abandonados........ 1.50% sobre su valor\nM).- Predios Urbanos destinados total o parcialmente a fines distintos de los señalados en los incisos anteriores......................... 0.40% sobre su valor\na).- Predios Suburbanos destinados total o parcialmente a fines distintos de los señalados en los incisos anteriores................ 0.35% sobre su valor\nN).- Predios Baldíos, que se presenten en estado de contaminación......... 1.50% sobre su valor\nLos predios de Dominio Público, propiedad de la Federación, del Estado o de los Municipios, estarán exentos de pago de conformidad con lo estipulado en el Artículo 75 Bis A Fracción IX de la Ley de Hacienda\nMunicipal del Estado de Baja California.\nSe establece una sobretasa del 0.114% sobre la base del impuesto predial, para el fortalecimiento y modernización del servicio de manejo integral de residuos sólidos urbanos en el municipio de Tecate.\nARTÍCULO 11.- A los predios que no se les haya asignado un valor catastral determinado en la Tabla del Artículo 8, les será aplicado\nIntegral del Territorio, comparando las características del caso que\nFracción XII del Artículo 12 de la Ley del Catastro Inmobiliario del\nEstado de Baja California.\nPara el caso de predios accidentados, se aplicará el factor de demérito determinado de la siguiente manera:\nFACTORES DE DEMÉRITO\nPARA TERRENOS:\nA.- Por Profundidad\nLos terrenos urbanos cuya relación frente-profundidad es mayor a\n2.5 procederá el demérito aplicando la siguiente fórmula:\n-------/ --- X 2.5\n\\/ P\nDONDE:\nX =FACTOR DE DEMÉRITO\nF =FRENTE\nP =PROFUNDIDAD REAL EN METROS (LA DISTANCIA ENTRE EL FRENTE DEL\nPREDIO Y EL PUNTO MÁS ALEJADO DEL\nLINDERO, MEDIDO EN DIRECCIÓN\nPERPENDICULAR AL FRENTE DEL\nPREDIO).\nB.- Lote Escarpado ascendentes, con pendientes mayores del veinte por ciento, se demeritarán aplicando los siguientes porcentajes de demérito, solamente a las fracciones con dichas pendientes.\nPENDIENTE % DEMÉRITO\nHASTA 20 0\nMAYOR DE 20 HASTA 30 20\nMAYOR DE 30 HASTA 40 30\nMAYOR DE 40 HASTA 50 40\nMAYOR DE 50 50\n--- X 100 = PENDIENTE\nDONDE:\nH = ALTURA (DESNIVEL ENTRE EL PUNTO DE INICIO DE LA\nPENDIENTE Y EL PUNTO EN QUE ÉSTA TERMINA).\nF = FONDO (DISTANCIA HORIZONTAL ENTRE EL PUNTO DE INICIO\nDE LA PENDIENTE Y EL PUNTO EN QUE ÉSTA\nTERMINA).\nC.- Lotes con Rocas y/o Arroyo\nCuando en los predios se encuentren rocas con un diámetro mínimo de\n2.5 metros, se demeritarán en un porcentaje resultante de la superficie que ocupen, y en caso de afectación por arroyo o ríos, de igual manera se demeritarán en un porcentaje de la superficie que afecte al predio.\nVIGENCIA DE DEMÉRITOS\nPara predios que requieran demérito ya sea a través de avalúos por frente-profundidad, lotes escarpados, con rocas, arroyos y/o ríos, tendrán una vigencia de 3 años en el entendido de que el terreno no presente modificación en cuanto a superficie, topografía o traslación de dominio.\nDe todo demérito aplicado deberá quedar constancia por escrito tanto en la Dirección de Gestión Integral del Territorio como en la\nRecaudación de Rentas Municipales para su debida justificación.\nARTÍCULO 12.- La tasa inicial del Impuesto que corresponde pagar a no edificados o baldíos con servicios de agua, electricidad y drenaje, entre tanto conserven esa calidad, se enajenen o establezca en ellos alguna Industria o Comercio, será ascendente y aumentará automáticamente el veinticinco por ciento, cada año hasta completar diez años, al final de los cuales se interrumpe y mantendrá hasta que se establezca en ellos alguna edificación; únicamente cuando se realice traslación de dominio se volverá a la tasa inicial (artículo\n10 inciso G) con el incremento antes mencionado.\nLos efectos de este Artículo no serán aplicables:\nA.- A los predios destinados para su venta, propiedad de fraccionamientos debidamente autorizados.\nB.- Ni a los predios no edificados que formen parte de una unidad comercial o industrial.\nARTÍCULO 13.- Tratándose de Predios Rústicos o aquellos dedicados exclusivamente a la actividad agropecuaria, debidamente comprobado\nLocal de Tecate, A.C., de Asociación Municipal de Propietarios\nRurales de Tecate, A.C. o por las autoridades del ramo, se determinará la base del impuesto de acuerdo a la siguiente tabla:\nPOLÍGONOS RÚSTICOS\nVALOR\nMAYOR DE: HASTA: POR m²\n1.- 0 m² 2,000 m² 83.93\n2.- 2,000 m² 2,500 m² 50.80\n3.- 2,500 m² 5,000 m² 41.97\n4.- 5,000 m² 7,500 m² 35.34\n5.- 7,500 m² 10,000 m² 28.71\n6.- 10,000 m² 12,500 m² 26.51\n7.- 12,500 m² 20,000 m² 24.29\n8.- 20,000 m² 30,000 m² 17.67\n9.- 30,000 m² 40,000 m² 14.36\n10.- 40,000 m² 75,000 m² 7.73\n11.- 75,000 m² 100,000 m² 5.53\n12.- 100,000 m² 150,000 m² 4.42\n13.- 150,000 m² 200,000 m² 3.31\n14.- 200,000 m² 500,000 m² 1.77\n15.- 500,000 m² 750,000 m² 1.44\n16.- 750,000 m² 1,000,000 m² 1.11\n17.- 1,000,000 m² 1,500,000 m² 0.99\n18.- 1,500,000 m² 2,000,000 m² 0.78\n19.- 2,000,000 m² 3,500,000 m² 0.66\n20.- 3,500,000 m² 5,000,000 m² 0.55\n21.- 5,000,000 m² 10,000,000 m² 0.33\n22.-10,000,000 m² En adelante 0.27 a la explotación agropecuaria, pagarán el Impuesto Predial, de acuerdo a la tasa establecida para el uso y destino del suelo.\nARTÍCULO 14.- Tratándose de Predios Urbanos destinados para programas habitacionales con fines sociales, promovidos por institución oficial promotora de vivienda, pagarán el mínimo fijado por esta Ley.\nARTÍCULO 15.- Los predios urbanos ocupados por asentamientos irregulares, y se encuentren en proceso de regularización por\nOrganismo Oficial Federal, Estatal o Municipal, siempre que estén posesionarios, previa opinión favorable de los Organismos, pagará el mínimo establecido en esta Ley.\nARTÍCULO 16.- La contribución por concepto del Impuesto Predial\nAnual, no puede ser menor al importe de $427.72 M.N.\nARTÍCULO 17.- El Impuesto Predial deberá cubrirse de la siguiente forma:\na).- El Impuesto Predial por pagar deberá ser cubierto anualmente dentro de los meses de enero, febrero y marzo.\nb).- Se podrá optar por efectuar el pago bimestralmente, cuando el impuesto a pagar exceda del importe de $1,283.16 M.N.\nLos propietarios de predios urbanos baldíos que presenten condiciones de uso o aprovechamiento, que adquieran el Certificado de\nMejoramiento de la Imagen Urbana que expida el Departamento de Control\nTerritorial, gozarán de hasta un cincuenta por ciento de descuento en el pago de dicho Impuesto. Podrá aplicarse el certificado en forma bimestral.\nTransitorio de la presente Ley.\nEste descuento sólo es aplicable en el presente ejercicio fiscal, en el cual se haya solicitado y se realice el trámite correspondiente, para verificación y autorización del mismo.\nLas bases del Certificado de Mejoramiento a la Imagen Urbana, se encuentran establecidas en el numeral 11 del Artículo 38 de esta Ley.\n4.- IMPUESTO SOBRE ADQUISICIÓN DE INMUEBLES\nARTÍCULO 18.- El Impuesto Sobre Adquisición de Inmuebles, se causará a la tasa del dos por ciento, la que se aplicará sobre lo que en este\nCalifornia, y no se dará lugar a la causación de otro impuesto establecerse.\nCalifornia (INDIVI), con el Instituto Nacional del Suelo Sustentable\n(INSUS) o con el Instituto de Promoción del Desarrollo Urbano del\nMunicipio de Tecate, Baja California (INPRODEUR), y los que se realicen a través de cualquier dependencia oficial que promueva desarrollos habitacionales de interés social y popular, pagarán el equivalente al importe de $106.93 M.N.\nLos sujetos obligados al pago de este Impuesto, lo harán de acuerdo a lo establecido en el Artículo 75 BIS B, de la Ley de Hacienda\nMunicipal del Estado de Baja California.\nARTÍCULO 19.- Las personas físicas o morales que adquirieron bienes inmuebles o derechos derivados de la misma adquisición, con la finalidad de llevar a cabo sobre los mismos, edificaciones de vivienda, de esparcimiento o recreación turística, y cualquier otra adquisición de bienes inmuebles, dentro del Municipio de Tecate, Baja\nCalifornia, podrán obtener una condonación de un cincuenta por ciento del importe causado por concepto del Impuesto sobre Adquisición de\nInmuebles establecido en el Artículo 75 BIS B de la Ley de Hacienda\nMunicipal para el Estado de Baja California.\nDicha condonación se aplicará conforme a lo siguiente:\nA).- La condonación será acordada por la Tesorería del Municipio de\nTecate, Baja California, previa solicitud del causante del\nImpuesto, bajo los siguientes parámetros:\na).- Que el solicitante acredite estar inscrito en el Registro territorio nacional.\nb).- Que el bien inmueble esté al corriente del pago del Impuesto\nPredial.\nc).- Que el acto jurídico generador del Impuesto Sobre Adquisición de Inmuebles previsto en el Artículo 75 BIS B de la Ley de\nHacienda Municipal del Estado de Baja California, se hubiere en vigor de la presente Ley.\nd).- Que el Impuesto Sobre Adquisición de Inmuebles, derivado de los actos jurídicos a que se refiere el presente, sea por una cantidad mayor a un peso moneda nacional.\ne).- Que al momento de la causación del impuesto, en los casos que proceda, se cuente con factibilidad de Uso de Suelo, otorgado por la Dirección de Gestión Integral del Territorio Municipal, empleando para ello el inmueble cuya adquisición en propiedad o de derechos derivados del mismo, haya generado la obligación de pago del Impuesto Sobre Adquisición de Inmuebles.\nf).- Que las tareas de urbanización, en los casos que proceda, impliquen la realización de obras de cabecera de infraestructura hidráulica, eléctrica y sanitaria, y respecto a las cuales se extienda la licencia correspondiente por parte de la autoridad municipal, y se dé inicio a la edificación de dichas obras, a más tardar dentro de los 36 meses siguientes a la fecha en que se emita la autorización de condonación en los términos de este Artículo.\nB).- Para acceder al estímulo fiscal mencionado, se deberá presentar solicitud por escrito dirigida a la Tesorería del Municipio de\nTecate, Baja California, con copia para la Dirección de Gestión\nIntegral del Territorio Municipal, a la cual deberá anexarse lo siguiente:\na).- Original o copia certificada de la documentación con que se acredite, que se reúnen los requisitos establecidos del inciso\na) al f) de la letra A de este Artículo.\nb).- Constancia expedida por Recaudación de Rentas del Municipio de Tecate, Baja California, en la que se consigne que el contribuyente y el inmueble de que se trate, no han sido\nArtículo. requisitos establecidos, o si la autoridad estima necesaria información y/o documentación adicional, o bien, efectuar aclaración a la misma a efecto de integrar debidamente el expediente respectivo, se le requerirá dicha información, documentación y/o aclaraciones, notificación de dicho requerimiento, en el entendido que de no hacerlo, se le tendrá por no presentada su solicitud de condonación.\nUna vez presentada la solicitud en los términos antes establecidos, la misma deberá ser resuelta por la Tesorería del Municipio de Tecate, Baja California, dentro de los diez días hábiles siguientes a su presentación.\nC).- La resolución que dicte la Tesorería del Municipio de Tecate, Baja California, respecto de la solicitud a que se refiere el presente Artículo, no constituirá instancia y no podrá ser recurrida por algún medio de defensa.\nD).- El estímulo fiscal a que se refiere este precepto, no tiene efectos retroactivos en beneficio de persona alguna.\nE).- El presente estímulo fiscal aplicará también cuando proceda conforme a lo antes señalado, a los sujetos obligados al pago del Impuesto que hubieren transmitido el dominio de un bien inmueble, y hayan caído en la hipótesis jurídica prevista en la parte final del párrafo segundo del Artículo 75 BIS B, de la Ley de Hacienda Municipal para el Estado de Baja California, vigente.\nF).- El pago del importe resultante de la aplicación del presente estímulo fiscal, deberá realizarse en una sola exhibición, surta efectos la notificación de la autorización respectiva; no se aceptarán pagos en especie, dación en pago ni compensación. pago en el plazo citado en el párrafo anterior, la autoridad tendrá por no presentada la solicitud de condonación.\n5.- CONVENIOS IMPUESTO PREDIAL\nCAPÍTULO III\nACCESORIOS DE IMPUESTOS\n6.- RECARGOS.\nARTÍCULO 20.- La tasa de recargos por concepto de mora será del dos por ciento mensual, de igual manera en los conceptos de convenios en\nImpuestos.\nY los recargos se causarán hasta por 5 años.\n7.- GASTOS DE EJECUCIÓN.\nARTÍCULO 21.- Los gastos de ejecución derivados de Impuestos, se de obligaciones fiscales no satisfechas dentro de los plazos legales, en los términos que señala la Ley de Hacienda Municipal del Estado de Baja California.\n8.- SANCIONES.\nARTÍCULO 22.- Las que deriven del incumplimiento de las disposiciones fiscales en materia de Impuestos.\nCAPÍTULO IV\nOTROS IMPUESTOS\n9.- IMPUESTO PARA EL MANTENIMIENTO Y CONSERVACIÓN DE LAS VÍAS\nPÚBLICAS\nARTÍCULO 23.- Son sujetos de este Impuesto, los propietarios o poseedores de vehículos de motor, que residan dentro del territorio del municipio de Tecate, Baja California, para contribuir en el mantenimiento y conservación de las vías públicas municipales.\nARTÍCULO 24.- El pago de este impuesto se realizará anualmente y se autorizadas, previo convenio que se celebre con el Ayuntamiento de\nTecate, al momento en que aquellos realicen el trámite de expedición o revalidación de la tarjeta de circulación relativa, conforme a lo siguiente:\na).- $213.86 M.N. importe para automóviles, remolques, demostradoras y motocicletas, de placas de servicio particular y público.\nb).- $267.33 M.N. importe para vehículos tipo pick-up, de placas de servicio particular y público.\nc).- $588.12 M.N. importe para vehículos de uso de taxis.\nd).- $1,283.16 M.N. importe para vehículos de transporte público de pasajeros y de carga de servicio particular y público.\nLos ingresos que se recauden por este concepto, se destinarán al mantenimiento y conservación de las vías públicas municipales.\nCAPÍTULO V\nIMPUESTOS NO COMPRENDIDOS EN LA LEY DE INGRESOS VIGENTE, CAUSADOS EN\n10.- IMPUESTOS CAUSADOS EN EJERCICIOS FISCALES ANTERIORES PENDIENTES\nDE LIQUIDACIÓN O PAGO\nARTÍCULO 25.- Los Impuestos no pagados en el ejercicio fiscal en que se causaron, se cobrarán como ingreso de ejercicios fiscales anteriores, aplicando en cuanto al fondo, las leyes vigentes a la fecha en que se generaron, y en cuanto a la forma mediante el\nProcedimiento Administrativo de Ejecución que establece la Ley de\nHacienda Municipal del Estado de Baja California, o en su caso, el procedimiento judicial que corresponda.\nEn el caso del Impuesto Predial, cuando el Consejo del Catastro\nInmobiliario determine un valor catastral inferior al asignado con anterioridad, el nuevo valor se aplicará retroactivamente al Impuesto pendiente de pago.\nTÍTULO III.- CUOTAS Y APORTACIONES DE SEGURIDAD SOCIAL\n1.- OTRAS CUOTAS Y APORTACIONES DE RECUPERACIÓN DE SERVICIOS\nMÉDICOS\nARTÍCULO 26.- Los empleados municipales, los empleados de las social o médica por parte del Municipio, deberán aportar una cuota de recuperación de servicios médicos municipales.\nTÍTULO IV.- CONTRIBUCIONES DE MEJORAS\nCAPÍTULO I\nCONTRIBUCIÓN DE MEJORAS POR OBRAS PÚBLICAS\n1.- APORTACIONES DE PARTICULARES PARA OBRAS PÚBLICAS MUNICIPALES\nARTÍCULO 27.- Son Contribuciones de Mejoras las establecidas en la obras públicas.\nLos elementos de las Contribuciones de Mejoras, realizadas bajo el sistema de cooperación, son los siguientes:\nI.- Objeto: El incremento de valor y la mejoría específica de la propiedad, que se originan como consecuencia inmediata y directa de la ejecución de obras por el sistema de cooperación;\nII.- Sujeto Activo: Las autoridades previstas por el Artículo 16, fracciones I, V, VI y VII de la Ley de Urbanización del Estado de Baja California;\nIII.- Sujeto Pasivo: Las personas previstas por los Artículos 2 y 7 de la Ley de Urbanización del Estado de Baja California;\nIV.- Base: Los supuestos previstos en el Artículo 94 de la Ley de\nUrbanización del Estado de Baja California;\nV.- Cuota: La que se determine de conformidad al procedimiento previsto en los Artículos 88 y 93 de la Ley de Urbanización del\nEstado de Baja California;\nVI.- Época de pago: Las Contribuciones de Mejoras serán cubiertas en la fecha y el número de exhibiciones que se determine de conformidad al procedimiento previsto en los Artículos 88 y 93 de la Ley de Urbanización del Estado de Baja California.\nARTÍCULO 28.- Los propietarios o poseedores de los predios que resulten beneficiados con obras públicas, tales como pavimentación, banquetas y guarniciones, estarán obligados a cubrir el importe total\nMunicipal, y se determinará de la siguiente manera:\nA.- Cuando beneficien uniformemente alguna zona y no sea factible propietario, el monto total de las obras será dividido entre que tengan de frente sus predios.\nB.- El costo de la obra que sólo beneficie a determinado predio, se pagará por el propietario beneficiado. en exhibiciones parciales iguales, previo convenio que celebre con las autoridades, pero el plazo de liquidación total no podrá en ningún caso ser mayor de cinco años.\nLa obligación de cubrir los Derechos que establece este Artículo, nace desde el siguiente bimestre a aquél en que se inicien las obras, pudiendo interrumpirse la obligación del causante por la suspensión temporal o definitiva de las obras.\nCAPÍTULO II\nCONTRIBUCIÓN DE MEJORAS NO COMPRENDIDAS EN LA LEY DE INGRESOS VIGENTE,\nCAUSADAS EN EJERCICIOS FISCALES ANTERIORES PENDIENTES DE LIQUIDACIÓN\nO PAGO\n2.- APORTACIONES DE PARTICULARES PARA OBRAS PÚBLICAS MUNICIPALES\nDE AÑOS ANTERIORES\nARTÍCULO 29.-Las Contribuciones de Mejoras no pagadas en el ejercicio fiscal en que se causaron, se cobrarán como ingreso de ejercicios fiscales anteriores, aplicando en cuanto al fondo, las leyes vigentes a la fecha en que se generaron, y en cuanto a la forma mediante el\nProcedimiento Administrativo de Ejecución que establece la Ley de\nHacienda Municipal del Estado de Baja California, o en su caso, el procedimiento judicial que corresponda.\nTÍTULO V.- DERECHOS\nCAPÍTULO I\nDERECHOS POR PRESTACIÓN DE SERVICIOS\n1.- DERECHO POR SERVICIO DE ALUMBRADO PÚBLICO\nARTÍCULO 30.- En materia de Derechos por Servicio de Alumbrado\nPúblico, se aplicarán las siguientes disposiciones:\nI. Es objeto de este derecho, la prestación del servicio de alumbrado público. Se entiende por servicio de alumbrado público, el servicio de iluminación que las autoridades municipales otorgan a través de la red de alumbrado público, en espacios públicos y vialidades como calles, avenidas, bulevares, caminos vecinales, plazas, parques, jardines y otros lugares de uso común del Municipio de Tecate, Baja California.\nII. Son sujetos de este derecho, los beneficiarios del servicio de alumbrado público a que se refiere la fracción anterior, Tecate, Baja California.\nIII. El derecho por el servicio de alumbrado público se causará mensualmente conforme a una cuota fija de $50.00 pesos 00/100 m.n.\nIV. La base de este derecho es el costo anual actualizado del servicio de alumbrado público erogado por el municipio, el cual incluye el consumo de energía eléctrica de las redes de alumbrado público del Municipio de Tecate, Baja California así como la ampliación, instalación, reparación, limpieza y mantenimiento del alumbrado público, la calidad y cantidad de lámparas que conforman el alumbrado público en el municipio, así como gastos administrativos, sueldos y honorarios del personal directamente involucrado en la prestación del servicio.\nLa cuota fija mensual se obtuvo como resultado de dividir el costo anual actualizado del ejercicio fiscal 2020, que el\nMunicipio de Tecate erogó en la prestación de este servicio y dividido entre el número de sujetos de este derecho, el cociente fue dividido entre 12 para determinar el monto mensual del derecho a pagar.\nSe entiende por costo anual actualizado del ejercicio fiscal\n2020, la suma que resulte del total de las erogaciones efectuadas por el Municipio de Tecate en el ejercicio fiscal de 2020, por\nMunicipio de Tecate, Baja California, traídos a valor presente\nV. El pago del Derecho por el servicio de Alumbrado Público deberá realizarse dentro de los primeros 10 días siguientes al mes en que se cause, en las oficinas recaudadoras municipales y demás instancias o establecimientos autorizados para tal efecto.\nEl citado plazo y lugar de pago, podrá modificarse o ampliarse en beneficio de los contribuyentes, cuando existan acuerdos entre el Municipio con otras instancias públicas o privadas, que permitan simplificar el entero de la contribución. Para tal efecto, las instancias competentes del Municipio podrán celebrar anterioridad.\nVI. Los ingresos que perciban por el derecho establecido en este artículo, se destinaran prioritariamente al pago de conceptos que se requieran para el debido servicio, operación y mantenimiento del alumbrado público que proporciona el\nMunicipio, incluyendo su ampliación y renovación, así como sueldos y honorarios del personal directamente involucrado en la prestación del servicio.\n2.- DERECHOS POR SERVICIOS QUE PRESTA EL REGISTRO CIVIL\nARTÍCULO 31.- Los derechos por servicios que preste el Registro Civil, serán pagados por los usuarios, sujetándose a la siguiente:\nIMPORTE\nPESOS\nA.- NACIMIENTOS:\na).- Registro dentro de la oficina en horas hábiles.................... EXENTO\nb).- Campaña del Registro Civil y/o DIF\nMunicipal......................... EXENTO\nc).- Registro en institución de salud en módulo de Registro Civil....... EXENTO\nd).- Registro en institución de salud por enfermedad infantil o maternal.......................... EXENTO\ne).- Inscripción de registro de nacimiento ocurrido en territorio extranjero................. EXENTO\nIMPORTE\nPESOS\na).- Solicitud y formato para certificados médicos prenupciales para la celebración de matrimonios. $216.82\nb).- Trámite y celebración dentro de la oficina en horas hábiles.......... $1,069.30\nc).- Trámite y celebración dentro de la oficina en horas inhábiles........ $4,914.11\nd).- Trámite y celebración a domicilio en horas hábiles.................. $4,914.11\ne).- Trámite y celebración de matrimonio a domicilio en horas inhábiles de lunes a sábado.................... $4,811.84\nf).- Solicitud, formato para certificados médicos prenupciales y celebración de matrimonio dentro del Programa de Matrimonios\nColectivos........................ EXENTO\ng).- Inscripción de matrimonio celebrado en el extranjero........ $4,914.11\nh).- Trámite y celebración urgente en horas hábiles dentro de la oficina...... $3,799.95\ni).- Celebración en hospitales, excepto en instituciones de salud pública, los cuales serán exentos.......... $3,276.08\nj).- Cambio de régimen matrimonial o modificación a las capitulaciones matrimoniales..................... $4,368.10\nk).- Registro de capitulaciones........ $1,069.30\nl).- Trámite y celebración de matrimonio a domicilio en horas inhábiles en domingos........ $6,514.20\nm).- Trámite y celebración de matrimonio a domicilio\nUrgente........ $7,592.90\nIMPORTE\nPESOS\na).- Registro en las oficinas en horas hábiles........................... EXENTO\nb).- Registro en las oficinas en horas inhábiles......................... $748.51\nc).- Servicios a panteones particulares en horas hábiles.................. $1,069.30\nd).- Servicios a panteones particulares en horas inhábiles................ $1,283.16\ne).- Autorización de inhumación en hora hábil............................. EXENTO\nf).- Autorización de inhumación en hora inhábil........................... $748.51\ng).- Orden de traslado de cadáver dentro del Municipio.............. $213.86\nh).- Orden de traslado de cadáver fuera del Municipio..................... $1,069.30\ni).- Orden de traslado de cadáver al extranjero........................ $4,368.10\nj).- Inscripción de defunción acaecida fuera del país.................... $2,352.45\nk).- Autorización de exhumación, cremación y reinhumación.......... $534.65\nl).- Autorización de inhumación a perpetuidad en panteones particulares...................... $1,603.95\nIMPORTE\nPESOS\na).-Administrativo..................... $4,277.18\nb).- Divorcio proveniente del juzgado. $2,138.59\nc).- Divorcio proveniente del juzgado en trámite urgente (dentro de las siguientes 48 horas).............. $3,207.89\nd).- Inscripción de acta de divorcio celebrado en el extranjero y homologada en juzgado............. $4,368.10\ne).- Anulación de matrimonio proveniente del juzgado........... $534.65\nf).- Anotaciones marginales en acta de matrimonio, por virtud de inscripción de divorcio administrativo, divorcio proveniente de juzgado, inscripción de acta de matrimonio celebrado en el extranjero..................... $293.65\nLos incisos b) y d) dentro de los meses septiembre y octubre contarán con un descuento del cincuenta por ciento, en base al “Programa\nAhorro”.\nIMPORTE\nPESOS\na).- Inscripción de Sentencia de adopción proveniente del juzgado.. EXENTO\nb).- Inscripción de adopción celebrada en el extranjero.................. $1,497.01\nc).- Anotaciones marginales de reserva de acta de nacimiento por inscripción de adopción........... $293.65\nF.- RECONOCIMIENTO DE HIJOS:\nIMPORTE\nPESOS\na).- Reconocimiento de hijos menores de\n18 años........................... $427.72\nb).- Reconocimiento de hijos en campaña........................... EXENTO\nc).- Inscripción de acta de reconocimiento de hijo celebrado fuera de la República............. $1,497.01\nd).- Reconocimiento de hijos mayores de\n18 años........................... $855.43\ne).- Reconocimiento de paternidad por juicio............................ $855.43\nf).- Inscripción de reconocimiento de hijo celebrado fuera del estado de\nBaja California.................. $409.31\ng).- Anotaciones marginales en el acta de nacimiento por reconocimiento de hijo............................ $293.65\nG.- EXPEDICIÓN DE ACTAS:\nIMPORTE\nPESOS\na).- Al momento del registro de nacimiento........................ EXENTO\nb).- Copia certificada en servicio ordinario......................... $172.43\nc).- Segunda y más copias certificadas al momento del registro de nacimiento........................ $106.93\nd).- Copia certificada en servicio urgente........................... $209.00\ne).- Copia certificada foránea existente en el Estado o fuera de éste...... $320.78 se presten después del día de su registro, en menos de 24 horas contados a partir del momento de su solicitud. Y por urgentes las que se presten después del día de su registro, en un término menor de dos horas contadas a partir del momento de su solicitud.\nLos pensionados, jubilados, las esposas y las viudas e hijos de éstos, cuando estos últimos sean menores de 18 años, pagarán cincuenta por ciento de la tarifa, únicamente tratándose de documentos que estén a su nombre, debiendo comprobar su condición con identificación o documentación expedida por Institución Pública.\nTratándose de indigentes mayores de 60 años y las personas con discapacidad, estarán exentas de pago, previa solicitud y en su caso, estudio socioeconómico realizado por el DIF Municipal o certificado médico que acredite tal condición.\nIMPORTE\nPESOS\na).- Búsqueda de datos para registro de campaña del Registro Civil y/o DIF\nMunicipal......................... EXENTO\nb).- Constancia de inexistencia de registro y matrimonial............ $106.93\nc).- Constancia de inexistencia para registro de campaña del Registro\nCivil y/o DIF municipal........... EXENTO\nd).- Copias fotostáticas no certificadas por hoja............. $26.74\ne).- Recepción, trámite y anotación marginal de rectificación de acta. $213.86\nf).- Otras certificaciones............. $106.93\ng).- Trámite de cancelación de acta por duplicidad........................ $213.86\nh).- Constancia o copia certificada dentro del programa inscripciones escolares......................... $106.93\ni).- Constancia de inexistencia de registro y matrimonial urgente.... $160.39\nj).- Otras certificaciones en servicio urgente.......................... $160.39\nk).- Información Testimonial........... $641.57\nl).- Otras anotaciones marginales...... $293.65\nTratándose de indigentes mayores de 60 años y las personas con discapacidad, estarán exentas de pago, previa solicitud y en su caso, estudio socioeconómico realizado por el DIF Municipal o certificado médico que acredite tal condición.\nPor la expedición de Actas y Certificados Urgentes dentro de las 24 horas siguientes a la solicitud, se cobrará el DOBLE DE LA TARIFA.\n3.- DERECHOS POR SERVICIOS QUE PRESTA EL DEPARTAMENTO DE PANTEONES\nARTÍCULO 32.- Los Derechos por estos servicios se pagarán como sigue:\nA.- PANTEÓN NÚMERO UNO Y RURALES\nIMPORTE\nPESOS\na).- Depósito de cualquier tipo........ $641.58\nb).- Inhumaciones a perpetuidad........ $3,207.89\nc).- Apertura de fosa.................. $2,673.24\nd).- Apertura de fosa con sobrecaja de concreto.......................... $4,277.20\ne).- Apertura de fosa con sobrecaja de concreto doble.................... $5,988.07\nf).- Otros servicios................... $855.43\ng).- Inhumación a 5 años............... $1,603.94\nh).- Revalidación de inhumación a 5 años.............................. $1,603.94\ni).- Nicho para cenizas................ $5,000.00\nB).- PANTEÓN NÚMERO DOS\na).- Depósito de cualquier tipo........ $641.58\nb).- Inhumaciones a perpetuidad........ $3,207.89\nc).- Apertura de fosa.................. $2,673.24\nd).- Jardín familiar 6 gavetas y 6 osarios........................... $120,295.90\ne).- Osarios individuales.............. $2,994.03\nf).- Otros servicios................... $855.43\ng).- Inhumación a 5 años............... $1,603.94\nh).- Revalidación de inhumación a 5 años.............................. $1,603.94\ni).- Nicho para cenizas................ $5,000.00\nC).- PANTEÓN NÚMERO TRES\na).- Depósito de cualquier tipo........ $641.58\nb).- Inhumaciones a perpetuidad........ $3,207.89\nc).- Apertura de fosa.................. $2,673.24\nd).- Jardín familiar 6 gavetas y 6 osarios........................... $120,295.90\ne).- Osarios individuales.............. $2,994.03\nf).- Otros servicios................... $855.43\ng).- Inhumación a 5 años............... $1,603.94\nh).- Revalidación de inhumación a 5 años.............................. $1,603.94\ni).- Nicho para cenizas................ $5,000.00 refiere este Artículo, las personas físicas, morales o unidades económicas que presten los servicios.\nSolamente se concederán gratuitamente fosas con temporalidad por\nAcuerdo del C. Presidente Municipal, cuando el occiso y los deudos sean indigentes.\nPor inhumaciones y traslado de cadáveres en tiempo extraordinario después de las 15:00 horas o días festivos, sábados y domingos en que se cierren los panteones, se pagarán adicionalmente por los interesados un tanto igual a la tarifa que corresponda.\nEn cumplimiento a la fracción VIII del Artículo 63 de la Ley sobre\nDesaparición y Búsqueda de Personas para el Estado de Baja California, quedan exentas del pago de los derechos que se refieren en los\nApartados A, B y C, en sus incisos b).-, g).- y h).- respectivamente, de este artículo, los familiares que soliciten estos servicios respecto de una persona que fuere objeto de búsqueda y localización en términos de dicha Ley, previa comprobación del parentesco. La incisos e).-, f).-, k).- y l).- del apartado C del Artículo 31 de esta Ley.\n4.- DERECHOS POR SERVICIOS QUE PRESTA EL DEPARTAMENTO DE RASTRO\nMUNICIPAL\nARTÍCULO 33.- Los Derechos por estos servicios, serán cubiertos por el introductor o propietario, antes de retirar la carne del ganado sacrificado.\nARTÍCULO 34.- Los Derechos por cabeza de ganado sacrificado en el\nRastro Municipal, se pagarán de acuerdo con la siguiente:\nIMPORTE\nPESOS\nA.- Ganado bovino\na).- Ganado bovino hasta 200 kg. en pie. $333.65\nb).- Ganado bovino más de 200 kg. en pie $662.49\nB.- Ganado porcino..................... $376.92\nC.- Ganado caprino o lanar............. $229.93\nD.- Ganado caballar.................... $613.94\nE.- Degüello de ganado vacuno caído.... $409.30\nLas carnes de animales deberán ser retiradas del Rastro Municipal, dentro de las 12 horas siguientes a la matanza, y de no hacerlo así el introductor o propietario tendrán que pagar los derechos correspondientes por el servicio de refrigeración y almacenaje extraordinario, quedando el Ayuntamiento relevado de toda responsabilidad.\nARTÍCULO 35.- Los Derechos por otros servicios que preste el Rastro\nMunicipal, se pagarán conforme a la siguiente:\nA.- Refrigeración o almacenaje antes o después de las 24 horas de la matanza, por animal sacrificado por cada 24 horas o fracción:\nIMPORTE\nPESOS\na).- Ganado bovino..................... $360.00 a $839.99\nb).- Ganado porcino.................... $239.99 a $480.00\nc).- Ganado caprino o lanar............ $119.99 a $360.00\nd).- Ganado caballar................... $360.00 a $839.99\nB.- Por expedición de certificados de procedencia de pieles cada una..... $119.99\nC.- De utilización de básculas para pesar animales, por animal......... $60.00 a $180.00\nD.- De lavado de vísceras por animal... $60.00 a $239.99\nE.- Derechos por servicio de transporte de carne en canal, por animal...... $239.99 a $360.00\nF.- Por supervisión de matanza en\nRastros Particulares............... $239.99 a $360.00\nG.- Por guía de traslado de animales... $239.99\nH.- Por el uso de corrales por cabeza de ganado, por día................. $360.00\nI.- Por servicio de inspección de todas las carnes frescas o refrigeradas que se introduzcan al Municipio.... $1.50 por kg\nJ.- Por salado de pieles por pieza.... $119.99 a $719.97\nK.- Por la venta de sub-productos de ganado sacrificado................. $119.99 a $1,320.00\nPor peso en kilos\nL.- Desperdicios cárnicos.............. $119.99 a $1,320.00 por peso en kilos\n5.- DERECHOS POR EXPEDICIÓN DE PERMISOS POR EL USO U OCUPACIÓN DE\nSEMIFIJOS\nARTÍCULO 36.- Los Derechos por el uso u ocupación de los bienes o puestos semifijos, previo cumplimiento con el reglamento respectivo vigente.\nSerán pagados anualmente por los usuarios, sujetándose a la siguiente:\nIMPORTE\nPESOS\nA.- ANUALMENTE\na).- Aseadores de calzado y voceadores........................ $1,023.25\nb).- Fotógrafos ambulantes............. $855.43\nc).- Músicos ambulantes por persona.... $1,069.30\nd).- Vendedores ambulantes:\n1).- Zona centro..................... $2,673.24\n2).- Zona popular.................... $2,138.59\ne).- Puestos semifijos:\n1).- Zona centro venta de comida..... $3,207.89\n2).- Zona centro venta de artículos nuevos.......................... $2,887.10\n3).- Zona centro venta de artículos usados.......................... $2,673.24\n4).- Zona popular venta de comida.... $2,673.24\n5).- Zona popular venta de artículos nuevos.......................... $2,352.45\n6).- Zona popular venta de artículos usados.......................... $2,138.59\n7).- Zona popular venta con vehículo food truck y/o carretas con jalón, o similares que excedan dimensiones de 3x3 metros cuadrados....................... $4,092.99\n8).- Zona popular con venta en vehículo........................ $1,637.20\nf).- Mercados sobre ruedas:\nIMPORTE\nPESOS\nEspacios 3 X 3 metros cuadrados\n1................................. $ 1,330.23 $1,637.21\n2................................. $ 1,497.06 $ 1,924.72\n3................................. $ 1,603.95 $ 2,138.59\n4................................. $ 1,924.72 $ 2,352.45\n5................................. $ 2,138.59 $ 2,566.31\n6................................. $ 2,566.31 $ 2,780.17\nB.- OCUPACIÓN ACCIDENTAL O EVENTUAL DE LA VÍA PÚBLICA (DE 1 A 30\nDÍAS NATURALES)\na).- Vendedores ambulantes:\n1).- Zona centro..................... $427.72\n2).- Zona popular.................... $320.78\nb).- Vendedores en puestos semifijos:\n1).- Venta de comida y artículos nuevos.......................... $320.78\n2).- Venta de artículos usados....... $213.86\nC.- PAGO EXTRA POR AMPLIACIÓN DE PUESTO SEMIFIJO\na).- Por cada metro cuadrado adicional. $106.93\nD.- PERMISOS ESPECIALES:\na).- Parques........................... $3,207.89\nb).- Días festivos, eventos o espectáculos públicos por puesto:\n1).- Venta de arreglos florales y coronas......................... $1,069.30\n2).- Preparación y venta de alimentos con uso de fuego................ $1,023.25\n3).- Venta de alimentos preparados... $818.60\n4).- Venta de artículos misceláneos.. $534.65\n5).- Venta de artículos accesorios... $320.78\n6).- Venta de artículos artesanales.. $855.43\n7).-Diversión y entretenimiento... $1,201.23\nE.- Reposición por pérdida de permisos anuales............................ $276.93\nArtículo, deberá hacerse durante los meses de enero y febrero de cada año.\nAquellas personas que acrediten con documentación oficial ser mayores de 60 años y que cuenten con autorización vigente a su nombre cubrirán sólo el cincuenta por ciento por concepto de derechos a que hace referencia este Artículo.\n6.- DERECHOS POR SERVICIOS QUE PRESTA LA DIRECCIÓN DE GESTIÓN\nINTEGRAL DEL TERRITORIO.\nEXPEDICIÓN DE PERMISOS PARA CONSTRUCCIÓN, AMPLIACIÓN, RECONSTRUCCIÓN,\nTRASLADO O DEMOLICIÓN DE INMUEBLES\nARTÍCULO 37.- Los Derechos por estos permisos o licencias, deberán ser cubiertos por los solicitantes, de acuerdo con la siguiente:\n1.- POR REVISIÓN, ANÁLISIS Y VERIFICACIÓN DE PROYECTO DE\nOTORGAMIENTO, PARA LICENCIA DE CONSTRUCCIÓN DE OBRA NUEVA Y\nAMPLIACIÓN DE EDIFICIOS HABITACIONALES, COMERCIALES,\nINDUSTRIALES Y OTROS., SE PAGARÁN, PREVIO AL INICIO DE LOS\nTRÁMITES, HASTA POR 2 REVISIONES DEL MISMO PROYECTO DE ACUERDO\nA LA SIGUIENTE:\nIMPORTE\nPESOS\nA.- Casa habitación y vivienda de interés social unifamiliares tratándose de cualquier tipo de inmuebles:\na).- Hasta 60.00 m².................... $10.70 por m² de\nConstrucción\nb).- Vivienda con construcción mayor de\n60.00 m² hasta 150.00 m².......... $21.39 por m² de\nConstrucción\n1).- Por cada m² adicional........... $26.74\nc).- Ampliación de vivienda hasta\n60.00m²........................... $16.04 por m² de\nConstrucción\n1).- Por cada m² adicional........... $21.39\nd).- Habitacionales, unifamiliares y multifamiliares con fines de comercialización y/o arrendamiento, por unidad de vivienda............\n1).- Hasta 60.00 m² de superficie de construcción........... $15.51 por m²\n2).- Mayor de 60.00 m² hasta 150 m² de superficie de construcción.... $25.86 por m²\n3).- Mayor de 150 m² de superficie de construcción........... $36.19 por m²\n4).- Traslado de casa móvil..... $1,069.31\n5).- Instalación de casa móvil... $15.99 por m² construcción\nB.- Para comercios y servicios.........\n1).- Hasta 100.00 m² de superficie de construcción........... $31.03 por m²\n2).- Mayores de 100.00 m² de superficie de construcción.......... $41.36 por m²\nC.- Para industria.....................\n1).- Hasta 500.00 m² de superficie de construcción........... $25.86 por m²\n2).- Mayor de 500.00 m² hasta 3,000.00 m² de superficie de construcción. $36.19 por m²\n3).- Mayor de 3,000.00 m² de superficie de construcción.......... $46.53 por m²\nD.- Otras construcciones\na).- Educación, Salud, Servicios\nAsistenciales y Culto Religioso e\nIglesias..................... $20.68 por m² de\nConstrucción\nb).- Para bodegas exclusivamente para almacenar.........................\n1).-Bodega Habitacional.................. $24.73 por m²\nConstrucción\n2).-Bodega Industrial..................... $49.47 por m²\nConstrucción\n3).-Bodega Comercial..................... $38.55 por m²\nConstrucción\nc).- Techumbre........................\n1).- Para techumbres de lámina u otro material liviano en espacios abiertos hasta 60.00 m²......... $5.36 por m² de\nConstrucción\n2).- Para techumbres de lámina u otro material liviano en espacios abiertos mayor a 60.00 m²....... $10.70 por m² de\nConstrucción\nd).- Construcción de módulo aerogenerador de energía eólica... $400,986.36\ne).- Construcción de parque de energía solar\n1).- Hasta 500.00 m²................. $10.70 por m² de\nConstrucción\n2).- Mayor de 500.00 m².............. $5.36 por m² de\nConstrucción\nf).- Construcción y/o instalación de torre de medición de vientos.\n1).- Hasta 10.00 metros de altura.... $5,346.49\n2).- Mayor de 10.00 y hasta 20.00 metros de altura................ $21,385.93\n3).- Mayor de 20.00 y hasta 30.00 metros de altura................ $53,464.84\n4).- Mayor de 30.00 metros de altura. $80,197.28\ng).- Construcción de edificaciones para generación de energía...... $427.72 por m² de\nConstrucción\nh).-Hoteles, moteles, cabañas recreativas, comercios, oficinas, salas de espectáculos, centros de reunión, hospitales, baños públicos y otros por metro cuadrado...... $199.00 por m² de\nConstrucción\ni).-Para la cultura, deporte y espectáculos deportivos, recreación y parque de diversiones sobre la superficie de construcción de uso y gradería, por metro cuadrado.... $93.83 por m² de\nConstrucción\nj).-Para infraestructura especial, distribución de gas butano, estaciones de servicio y estaciones de carburación se cobrará sobre la superficie de construcción del uso especial, por metro cuadrado.... $995.04 por m² de\nConstrucción\nk).-Edificaciones provisionales o temporales con duración máxima de hasta seis meses..... $125.08 por m² de\nConstrucción\nl).- Construcción de alberca por metro cúbico...........................\n1).- En casa habitación............. $108.41\n2).- Otras.......................... $318.95\nm).- Torres Meteorológicas............ $1,847.80 por torre\nn).-Planta de tratamiento de aguas residuales y potabilizadoras..... $121.94 por m² de\nConstrucción\no).- Instalación de postes de luz...... $601.36 por poste\np).- Otras no consideradas en los anteriores....................... $32.00 por m² de\nConstrucción\nTratándose de obras provenientes de los propios propietarios que sean para uso doméstico según criterios de la CFE y de autoconsumo, no causarán el Derecho estipulado en los incisos d) y e) del Artículo anterior. o del Estado de Baja California, no causarán el Derecho estipulado en este inciso.\nE.- Estacionamiento y patios de maniobras para industria, comercio y servicios con necesidad:\na).- Hasta 20 cajones de estacionamiento................... $855.43\nb).- De 21 a 40 cajones de estacionamiento................... $1,283.16\nc).- De 41 a 100 cajones de estacionamiento................... $1,817.81\nd).- Por cada cajón subsecuente........ $7.49\nF.- Por revisión, análisis de proyecto y licencias de regularización de construcción ejecutada total o parcialmente sin contar con las licencias correspondientes, se pagará el 50% adicional de los derechos por trámite normal indicados en la tarifa de los incisos A.- al G.-.\nLos contribuyentes que lleven a cabo la regularización de su vivienda hasta 60.00 m² para la modificación de la tasa catastral que acrediten su condición de pensionado o jubilado a través de los documentos oficiales expedidos por las Instituciones Públicas de Seguridad\nSocial, tratándose de personas discapacitadas deberán acreditarlo mediante certificado médico, expedido por cualquier Institución\nPública de Salud con domicilio en el Estado, la viudez se acreditará con el acta de defunción del cónyuge, la indigencia con un estudio socioeconómico con vigencia anual que realice el Sistema para el\nDesarrollo Integral de la Familia del Municipio, y la población senecta que se identifique con credencial del INAPAM, tendrán un descuento del cincuenta por ciento del importe de los Derechos únicamente en el predio en el cual se demuestre que habita y que específicamente sea de uso habitacional.\nG.- Construcción de cercos, bardas y muros de contención; siempre que no forme parte integral de la edificación.\na).- Cercos de madera, lámina, malla ciclónica y reja metálica......... $21.39 por metro lineal.\nb).- Bardas:\n1).- Hasta 2.00 metros de altura... $51.71 por metro lineal.\n2).- Mayores de 2.00 a 5.00 metros de altura................ $103.41 por metro lineal.\n3).- Mayores de 5.00 metros de altura................ $206.82 metro lineal.\nc).- Muros de contención:\n1).- Hasta 2.00 metros de altura.... $155.12 por metro lineal\n2).- Mayores de 2.00 a 5.00 metros de lineal\n3).- Mayores de 5.00 metros de altura.. $413.65 por metro lineal\nH.- Emisión de licencia de ocupación de vía pública en el suelo, subsuelo y en el sobresuelo del área:\na).-Ocupación parcial por día, de acuerdo con la siguiente tabla:\n1).-Hasta de 50.00 m² de ocupación... $296.88 por día\n2).- Mayor de 50.00 m² hasta 100.00 m² de\n3).- Por m² adicional de ocupación a los primeros 100.00 m²......... $64.32 por m²\nb).-Por movimiento y maniobra con equipos de carga, izaje y/o montaje, incluyendo la zona o área acordonada para seguridad:\n1).-Hasta 50.00 m² de ocupación... $1,365.97 por día\n2).- Mayor de 50.00 m² de ocupación... $2,048.96 por día\n3).- Por metro adicional de ocupación a los primeros 100.00 m²......... $136.59\nI.- Por expedición de prórroga de licencia de construcción:\na).- Por vivienda unifamiliar.\n1).- Hasta 60.00 m² de construcción... $310.24\n2).- Mayor de 60.00 m² hasta 150.00 m²\n3).- Mayores de 150.00 m² de construcción. $1,344.37\nb).- Para conjuntos habitacionales multifamiliares se pagará por cada una de las primeras 10 viviendas......................... $534.65\n1).- Por cada vivienda subsecuente... $106.93\nc).- Edificios de comercio y turismo.\n1).- Hasta 100.00 m²........ $1,034.14\n2).- Mayor de 100.00 m²...... $1,551.20\nd).- Para industrias.\n1).- Hasta 500.00 m²......... $2,585.33\n2).- Mayor de 500.00 m² hasta 3,000.00 m²...... $3,619.47\n3).- Mayor de 3,000.00 m²...... $4,653.61\ne).- Otras construcciones,\n1).- Educación, salud, servicios asistenciales y culto religioso e\n2).- Para bodegas exclusivamente de almacén:\na).-Bodega Habitacional....... $24.73 por m²\n(costo por metro cuadrado)\nb).-Bodega industrial......... $49.47 por m²\n(costo por metro cuadrado)\nc).-Bodega Comercial......... $38.55 por m²\n(costo por metro cuadrado)\n3).- Hoteles, moteles, cabañas recreativas, comercios, oficinas, salas de espectáculos, centros de reunión, hospitales, baños públicos y otros por metro cuadrado.... $199.00\n4).- Para la cultura, deporte y espectáculos deportivos, recreación y parque de diversiones sobre la superficie de construcción del uso y gradería, por metro cuadrado.. $93.83\n5).-Para infraestructura especial, distribución de gas butano, estaciones de servicio y estaciones de carburación se cobrará sobre la superficie de construcción del uso especial, por metro cuadrado... $125.08\n6).- Edificaciones provisionales o temporales con duración máxima de hasta seis meses......... $125.08\nf).- Instalaciones para la generación y transmisión de energía eólica.\n1).- Por primer aerogenerador de energía eólica................... $16,039.46\n2).- Por aerogenerador subsecuente de energía eólica................... $7,485.08\ng).- Edificios o instalaciones para la generación y transmisión de energía eléctrica eólica.\n1).- Hasta 500.00 m².................. $5.36 por m²\n2).- Mayor a 500.00 m²................ $2.14 por m²\nJ.- Por certificación de terminación y/o ocupación de obra, se cobrará por edificio de la siguiente manera:\na)- Para uso habitacional.\n1).- Hasta 60.00 m² de construcción... $427.72\n2).- Mayor de 60.00 m² hasta 90.00 m² de construcción.................. $855.43\n3).- Mayor de 90.00 m² hasta 200.00 m² de construcción.................. $1,283.16\n4).- Mayor de 200.00 m² hasta 500.00 m² de construcción............... $1,710.88\n5).- Mayor de 500.00 m² de construcción..................... $2,138.59\nb).- Para uso turístico, comercial, espectáculos, hospital, estacionamientos y otros.\n1).- Hasta 100.00 m² de construcción.. $1,603.94\n2).- Mayor de 100.00 m² hasta 1,000.00 m² de construcción.............. $3,207.89\n3).- Mayor de 1,000.00 m² de construcción..................... $3,421.75\nc).- Para uso de educación, cultura, deporte, recreación y otros.\n1).- Hasta 500.00 m² de construcción.. $1,069.30\n2).- Mayor de 500.00 m² hasta 1,000.00 m² de construcción............... $1,603.94\n3).- Mayor de 1,000.00 m² de construcción..................... $2,138.59\nd).- Para uso industrial.\n1).- Hasta 500.00 m² de construcción.. $2,673.24\n2).- Mayor de 500.00 m² hasta 1,000.00 m² de construcción............... $3,207.89\n3).- Mayor de 1,000.00 m² de construcción..................... $3,742.53\n4).- Módulo aerogenerador de energía.. $16,039.46\n5).- Líneas de transmisión de energía por cada 10.00 metros lineales... $21.39\ne).- Edificaciones o instalaciones para la generación y transmisión de energía solar.\n1).- Hasta 500.00 m².................. $32.09 por m²\n2).- De 500.01 m² a 1 hectárea adicional a la cuota anterior.... $1.60 por m²\n3).- Por m² subsecuente a 1 hectárea.. $0.22 por m² o del Estado de Baja California, no causarán el Derecho estipulado en este inciso.\nK.- Por remodelación de:\na).- Construcción..................... $20.46 por m² de\nConstrucción\nb).- Remodelación de fachada estructural................ $20.46 por m² de\nConstrucción\nL.- Por registro como nuevo perito responsable proyectista y/o perito responsable de obra................ $2,138.59\nM.- Por revalidación anual como perito responsable proyectista y/o perito responsable de obra.\na).- Por revalidación anual en tiempo, hasta el mes de febrero... $1,034.14\nb).- Por revalidación anual a destiempo, posterior al mes de febrero.. $2,585.33\nc).- Por cambio de perito de obra... $2,068.27\nN.- Por registro provisional como perito responsable proyectista y/o perito de obra foráneo, por trámite....... $5,346.49\nÑ.- Demolición parcial o total de inmuebles, se pagará de acuerdo a las siguientes CUOTAS:\na).- Demolición parcial o total de inmuebles:\n1).- Hasta 25.00 m²................... $320.78\n2).- Mayor de 25.00 m² hasta 100.00 m² $534.65\n3).- Mayor de 100.00 m² la cuota anterior más por cada metro\nb).- Demolición de bardas por metro cuadrado.......................... $10.70\nc).- Demolición de cordón............. $213.86 por metro lineal\nd).- Demolición de banquetas.......... $320.78 por m²\ne).- Demolición de carpeta asfáltica... $213.83 por m²\nf).- Demolición de carpeta de concreto hidráulico........................ $292.73 por m²\nO.- Por movimientos de tierra para el mejoramiento y desarrollo de predios; deberán ser cubiertos por el solicitante previo al inicio del trámite, según el volumen de metros cúbicos, de acuerdo a la siguiente tabla:\na).- Por revisión, análisis de proyecto y licencia para movimiento de tierra en predios dentro del centro de población:\n1).- Por movimientos de tierra con volumen de hasta 200.00 metros cúbicos en lotificación de fraccionamientos autorizados con uso habitacional unifamiliar..... $855.43\n2).- Para volúmenes mayores de 200.00 m³ hasta 1,000.00 m³............. $2,566.32\n3).- Para volúmenes mayores de 1,000.00 m³ hasta 5,000.00 m³.... $5,132.63\n4).- Para volúmenes mayores de 5,000.00 m³ hasta 10,000 m³...... $7,698.93\n5).- Por cada metro cúbico de volumen que exceda a 10,000.00 m³........ $4.81/m³\nb).- Por revisión, análisis de proyecto y licencia para movimiento de tierra en predios fuera del centro de población:\n1).- Para volúmenes de hasta 10,000.00 m³............................... $4,277.18\n2).- Por cada metro cúbico de volumen que exceda a 10,000.00 m³ adicionar a la cuota del inciso anterior......................... $4.81/m³\nc).- Por revisión, análisis de proyecto y licencia de regularización de movimientos de tierra ejecutados total o parcialmente sin contar con las licencias correspondientes, se pagará el cincuenta por ciento adicional de los derechos por trámite normal indicados en la tarifa de los incisos a) y b), inmediatos anteriores.\nd).- Por prórroga de licencia para movimiento de tierra:\n1).- Para volumen de hasta 10,000.00 m³......... $1,069.30\n2).- Por cada metro cúbico de volumen que exceda de 10,000.00 m³ adicionar a la cuota del inciso anterior......................... $4.81/m³\nP.- Por la revisión de proyectos, autorización e inspección a la obra, licencia y revalidación anual de la instalación de líneas espacios de dominio público y privado.\na).- Para tuberías con diámetro menor a\n9 cm por cada 10.00 metros lineales......................... $106.93\nb).- De 9 cm a 20 cm de diámetro por cada 10.00 metros lineales....... $213.86\nc).- Mayor de 20 cm a 50 cm de diámetro por cada 10.00 metros lineales... $449.10\nd).- Mayor de 50 cm a 1.00 metro de diámetro por cada 10.00 metros lineales......................... $855.43\ne).- Mayor de 1.00 metro de diámetro por cada 10.00 metros lineales.... $1,283.16\nf).- Instalaciones aéreas por cada\n10.00 metros lineales............ $106.93\ng).- Estructuras subterráneas como registros, cajas de válvulas, etc., por metro cuadrado......... $320.78\nh).- Revalidación anual de licencia por la instalación de servicios subterráneos o aéreos, por cada\n10.00 metros de longitud por línea............................ $534.65\n1).- Por revalidación anual de licencia por la instalación de servicios subterráneos de alto riesgo, de conducción de gas por cada 10.00 metros de longitud por línea............................ $534.65\n2).- Por revalidación anual de licencia por la instalación de servicios subterráneos de alto riesgo de conducción de petróleo por cada\n10.00 metros de longitud por línea............................ $534.65\n3).- Por revalidación anual de la licencia por la instalación de servicios aéreos que sean de alto riesgo, por cada 10.00 metros de longitud de línea................ $534.65\nLa revalidación contemplada en el inciso h), así como subincisos 1),\n2) y 3) que anteceden, deberá hacerse durante los 10 días previos a su vencimiento.\ni).- Instalaciones de antenas de telefonía celular y radio comunicación.\n1).- Hasta 10.00 metros de altura..... $40,098.64\n2).- Mayor de 10.00 y hasta 20.00 metros de altura................. $80,197.28\n3).- Mayor de 20.00 y hasta 30.00 metros de altura................. $106,930.20\n4).- Mayor de 30.00 metros de altura.. $160,394.54\nj).- Por revisión, análisis de proyecto y licencia de regularización, de obras ejecutadas total o parcialmente sin contar con las licencias correspondientes, se pagará el cincuenta por ciento adicional de los derechos por trámite normal indicados en las tarifas del inciso a) al i) inmediatos anteriores.\nQ.- Por realización de inspección, peritaje y dictamen técnico sobre inmueble; se pagarán previo al inicio de los trámites, de acuerdo a lo siguiente:\na).- Dictamen técnico ocular en inmuebles de condición ruinosa y/o peligrosa, por cada 100.00 m² de construcción..................... $1,069.30\nb).- Peritaje de avance de trabajos por cada 100.00 m² de construcción... $1,069.30\nc).- Peritaje referente al apego a proyectos, especificaciones y reglamentos, por cada 100.00 m² de construcción..................... $1,603.94\nd).- Dictamen técnico ocular sobre el estado físico aparente (daños y evaluación de riesgo, no incluye estudios especializados) por cada\n100.00 m² de construcción........ $1,069.30\ne).- Emitir un documento de resolución definitiva en caso de afectación, daño, evaluación, rectificación, daño y/o riesgo en edificaciones; revisando documentación presentada, recabar información adicional de los archivos de esta Dirección y análisis. (No incluye estudios especializados, ni pruebas de resistencia de materiales)\n1).- Dictamen técnico ocular para evaluación de edificación (estado que guarda la edificación)....... $1,409.31\n2).- Constancia de uso de suelo....... $650.45\n3).- Dictamen técnico sobre análisis y aplicación de ajustes de tasa catastral, rectificación de superficie de valores de construcción y en base de datos.. $650.45\nf).- Dictamen técnico para la desincorporación de bienes públicos......................... $1,069.30\ng).- Dictamen técnico en zonas aptas para el desarrollo a solicitud de particulares..................... $1,069.30\nh).- Peritaje por inspección realizada fuera del centro de población... $1,069.30\ni).- Peritaje por afectación a vecinos por cierre de vialidades dentro del límite del centro de población... $2,138.59\nj).- Peritaje por afectación a vecinos por cierre de vialidades fuera del límite del centro de población... $5,346.49\nk).- Levantamiento de acta circunstanciada para emitir Peritaje\nTécnico:\n1).- Dentro del área urbana........... $1,603.95\n2).- Fuera del área urbana............ $3,207.90\nR.- POR LA EVALUACIÓN DE ANTEPROYECTO ARQUITECTÓNICO, PREVIA A LA\nEXPEDICIÓN DEL PERMISO O LICENCIA:\na).- Hasta 500.00 metros cuadrados de construcción..................... $1,069.30\nb).- Mayor de 500.00 hasta 1,000.00 metros cuadrados de construcción. $2,673.24\nc).- Mayor de 1,000.00 metros cuadrados de construcción.................. $3,207.89\nS.- Cuando el número de revisiones de dicho proyecto exceda de dos veces para un mismo trámite, siendo esto imputable al propietario se cobrará adicionalmente el 50% de la tarifa anterior.\nT.- Derechos por notificaciones........ $310.24\nU.- Por expedición de Factibilidad de Proyecto a solicitud del particular:\na).- Proyectos dentro de los límites del centro de población de la Ciudad de\nb).- Proyectos fuera de los límites del centro de población de la Ciudad de\nV.- Servicios de elaboración de nota aclaratoria no incluida en el trámite original, de los anteriores........ $723.89\nW.- Los trámites ingresados al Departamento de Control Territorial solo permanecerán 60 días, al vencimiento de estos se cancelarán correspondiente.\nARTÍCULO 38.- Por los servicios que presten los Departamentos de\nCatastro y Control Territorial se cubrirán las siguientes:\n1.- POR ANÁLISIS DE ACCIONES DE URBANIZACIÓN A REALIZARSE EN PREDIOS\nUBICADOS DENTRO Y FUERA DE LOS CENTROS DE POBLACIÓN, SE PAGARÁ\nPREVIO AL INICIO DEL TRÁMITE HASTA POR 2 REVISIONES DEL MISMO\nANTEPROYECTO DE ACUERDO CON:\nA.- Por análisis y emisión de dictamen sobre uso del suelo para el desarrollo urbano de predios, se pagará por dictamen:\nIMPORTE\nPESOS\na).- Por análisis de anteproyecto de fraccionamiento se pagará por la superficie total en la forma siguiente:\n1).- De terrenos ubicados dentro de los límites del centro de población de la Ciudad de Tecate:\nI).- Hasta cinco hectáreas: $6,415.78\nII).- Por cada metro cuadrado excedente. $0.10\n2).- En terrenos ubicados fuera de los límites del centro de población de la Ciudad de Tecate:\nI).- Hasta cinco hectáreas: $9,623.67\nII).- Por cada metro cuadrado excedente. $0.10\n3).- Por regularización de análisis de anteproyecto de fraccionamiento, para el cual se hayan iniciado actividades relacionados a la urbanización y/o promoción de venta sin contar con autorización correspondiente, se pagará adicionalmente el 50% de los derechos por trámite normal en los incisos a) y b).\nb).- Por análisis de proyecto de fraccionamientos habitacionales, comerciales, industriales o mixtos nuevos o modificaciones a proyectos aprobados que requieren de un nuevo dictamen, se pagará por superficie fraccionada en la forma siguiente.:\n1).- Hasta cinco hectáreas............. $7,485.07\n2).- Mayores de cinco hectáreas, por cada metro cuadrado excedente..... $0.11\nc).- Por análisis de anteproyecto de pluviales, área verde, alumbrado público, integración vial, señalamiento vial y/o semáforos de fraccionamientos promovidos por particulares, según la superficie total del predio:\n1).- Hasta cinco hectáreas............. $2,276.57\n2).- Mayores de cinco hectáreas, por cada metro cuadrado excedente..... $433.63\nd).- Por análisis de proyecto de fraccionamientos tipo granjas, y campestres nuevos o modificaciones a proyectos aprobados que requieran de un nuevo dictamen, se pagará por superficie fraccionada o proyectada en la forma siguiente:\n1).- Hasta cinco hectáreas............. $5,346.49\n2).- Mayores de cinco hectáreas, por cada metro cuadrado excedente..... $0.10\ne).- Por análisis previo de planos correspondiente al anteproyecto y/o proyecto ejecutivo de acciones de urbanización bajo la modalidad de fraccionamientos que no reúnan los requisitos para autorización completa de anteproyecto ejecutivo solo una revisión:\n1).- Predios ubicados dentro de los límites del centro de población de la Ciudad de Tecate:\nI).- Hasta cinco hectáreas: $4,011.11\nII).- Por cada hectárea o fracción excedente.................... $867.27\n2).- Predios ubicados fuera de los límites del centro de población de la Ciudad de Tecate:\nI).- Hasta cinco hectáreas: $4,769.97\nII).- Por cada hectárea o fracción excedente.................... $867.27\nf).- Por recorrido de inspección y elaboración del acta entrega-recepción parcial o total al Municipio para su mantenimiento se cobrará:\n1).- Para fraccionamientos dentro del centro de la población de la Ciudad de Tecate $5,346.49\n2).- Para fraccionamientos fuera del centro de la población de la Ciudad de Tecate $7,485.07\ng).-Por constancia de cumplimiento de requisitos para translación de dominio en\nh).- Relotificación, subdivisión o fusión de lotes urbanos:\n1).- Por relotificación de manzanas y certificación de la memoria descriptiva, por cada lote resultante. $1,069.30\n2).- Por la subdivisión o fusión de lotes urbanos y certificación de memoria descriptiva de los mismos, por cada lote fusionado o lote resultante de la subdivisión se pagará:\nI).- En baldíos y construidos..... $1,069.30\ni).- Por división o fusión de predios rústicos, que no requieran apertura de calle, por cada fracción y resto del predio:\n1).- Dentro de los límites de los centros de población de la Ciudad de Tecate, la Rumorosa y la Colonia\nLuis Echeverría Álvarez/Ejido Baja\nCalifornia.. $2,031.67\n2).- Fuera de los centros de población de la Ciudad de Tecate, la Rumorosa y la Colonia Luis Echeverría\nÁlvarez/Ejido Baja California.. $2,566.31\n2.- POR URBANIZACIÓN:\nPor urbanización de terrenos realizada por particulares, se pagará sobre el importe de los presupuestos presentados.\nEl pago de estos derechos se efectuará una vez aprobado el proyecto correspondiente por la Dirección de\nGestión Integral del Territorio y previamente al otorgamiento de la autorización definitiva. El cálculo de estos derechos se hará con el carácter provisional, debiendo revisarse al terminar el desarrollo total, a efecto de que, para fijar el monto definido sirva de base la aplicación del porcentaje citado al costo total de la obra declarada para efectos fiscales... 2.5%\n3.- POR CERTIFICACIÓN Y RECTIFICACIÓN DE MEMORIAS DESCRIPTIVAS:\nA.- Por verificación y certificación de memorias descriptivas de lotes pertenecientes a fraccionamientos y predios resultantes de subdivisiones, se pagará por cada revisión en la forma siguiente:\na).- De 1 a 20 lotes fraccionados...... $641.58 por lote\nb).- De 21 a 40 lotes fraccionados..... $534.65 por lote\nc).- De 41 a 60 lotes fraccionados..... $320.78 por lote\nd).- Más de 60 lotes fraccionados...... $106.92 por lote\nB.- Por verificación y rectificación de memorias descriptivas de lotes pertenecientes a fraccionamientos, se pagará por cada revisión en la forma siguiente:\na).- Por lote.......................... $641.58 el interesado previamente a la iniciación del trámite. numeral 1 y los incisos del numeral 2 y 4 de este Artículo, se hará resultantes.\nEl pago de los Derechos citados en el numeral 3 y 4 de este Artículo, se hará una vez aprobados los proyectos por la Autoridad Municipal, y previamente al otorgamiento de la autorización definitiva.\nEl cálculo del monto de los Derechos por Urbanización se hará con el carácter de provisional, debiendo revisarse anualmente y al terminarse el desarrollo total, a efecto de que, para fijar el monto definitivo, sirva de base la aplicación del porcentaje citado al costo total de las obras declarado para efectos fiscales.\n4.- POR ANÁLISIS DE CONDOMINIOS:\nA.- Por análisis y emisión de dictamen sobre el uso de inmuebles para el régimen condominal se pagará por dictamen:\na).- Para uso comercial................ $2,566.32\nb).- Para uso habitacional............. $2,138.59\nc).- Para uso mixto.................... $3,207.89\nB.- Por análisis y dictamen de factibilidad de anteproyecto de construir para uso habitacional, comercial, industrial o mixtos se pagará:\na).- Por unidad...................... $641.58\nC.- Por análisis y dictamen de factibilidad de conversión al régimen habitacionales, comerciales, y mixtos ya construidos se pagará:\na).- Por unidad........................ $641.58\nD.- Por declaratoria para la constitución del régimen de propiedad en condominio de inmuebles, se pagará por cada lote, departamento, vivienda, casa o local en la forma siguiente:\na).- Por cada unidad habitacional...... $855.44\nb).- Por cada unidad comercial o industrial........................ $1,710.88\nE).- Por constancia de cumplimiento de requisitos para traslación de dominio en régimen de propiedad en condominio, se pagará cada vez que se solicite........................ $2,493.39\nF.- Por verificación y certificación de memorias descriptivas de viviendas, departamentos, casas o locales comerciales, pertenecientes a condominios:\na).- Por la primera revisión:\n1).- Por conjunto hasta 10 unidades... $2,704.62\n2).- Por cada unidad que exceda de las 10 primeras......................... $246.91\nb).- Por revisiones subsecuentes:\n1).- Por conjuntos de hasta 10 unidades... $3,305.96\n2).- Por cada unidad que exceda de las 10 primeras......................... $1,352.31\nc).- Por revisión de proyecto de condominio maestro............................. $3,005.14\nG).- Por certificación de libro de actas de asamblea de condominio......... $325.22\n5.- POR ANÁLISIS DE PREDIOS PARA EDIFICACIÓN:\nA.- Por análisis y emisión de dictamen de uso del suelo para factibilidad de edificación en predios, se pagará por dictamen:\na).- Terrenos dentro de los límites del centro de población de la Ciudad de\nTecate......................... $1,603.94\nb).- Terrenos fuera de los límites del centro de población de la Ciudad de\nTecate......................... $2,138.59\n6.- POR ANÁLISIS Y EMISIÓN DE DICTAMEN DEL SUELO Y USO DE EDIFICIO:\nA.- Por análisis de dictamen de uso de suelo de edificaciones para desarrollos habitacionales, industriales, comerciales y de servicio, de acuerdo con la superficie de construcción, se pagará:\na).- En zonas habitacionales multifamiliar y especial:\n1).- Construcción hasta 100.00 m²..... $1,924.74\n2).- Construcción mayor de 100.00 m².. $2,138.59\nb).- En equipamiento y servicios\n1).- Comercio:\nAbastos y almacenaje: depósitos de productos básicos, de materiales de construcción, maquinaria, vehículos, gasolineras, tianguis y otros:\nI.- Hasta 500.00 m² de predio... $2,138.59\nII.- Mayor de 500.00 hasta\n1,000.00 m² de predio....... $2,352.45\nIII.- Mayor de 1,000.00 hasta\n5,000.00 m² de predio....... $2,780.17\nIV.- Mayor de 5,000.00 m² de predio...................... $4,063.33\nCentro comercial, tiendas de autoservicio y departamentos, comercio alimenticio, comercio especializado, centros cambiarios, artículos terminados, reparación o elaboración de artículos, abarrotes, mercado, supermercado, licorería, depósito, agencias y subagencias, bodega, fonda, lonchería, coctelerías, restaurante, restaurantes bar, bar turístico, bar terraza, billar, expendio, discoteca, café cantante y centro de espectáculos:\nV.- Hasta 25.00 m² de construcción................ $534.65\nVI.- Mayor de 25.00 m² hasta 50.00 m² de construcción.......... $2,138.59\nVII.- Mayor de 50.00 hasta 100.00 m² de construcción........... $2,352.45\nVIII.- Mayor de 100.00 hasta 500.00 m² de construcción.......... $2,566.32\nIX.- Mayor de 500.00 hasta\n1,000.00 m² de construcción. $3,207.89\nX.- Mayor de 1,000.00 hasta\n5,000.00 m² de construcción. $4,277.18\nXI.- Mayor de 5,000.00 m² de construcción................ $6,629.64\n2).- Educación y Cultura:\nGuarderías, preescolar; elemental, medio básico, medio superior; instalaciones de investigación y superior; museos, escuelas de idiomas, baile, arte, bibliotecas y hemerotecas e instalaciones religiosas.\nI.- Hasta 500.00 m² de predio... $1,069.30\nII.- Mayor de 500.00 hasta\n1,000.00 m² de predio....... $1,176.23\nIII.- Mayor de 1,000.00 hasta\n5,000.00 m² de predio....... $1,283.16\nIV.- Mayor de 5,000.00 m² de predio...................... $1,497.01\n3).- Salud y Servicios Asistenciales:\nHospitales, clínicas, centros de salud o consultorios, asistencia social, así como los orfanatorios, centro de integración, asociaciones civiles y asistencia para animales:\nI.- Hasta 50.00 m² de construcción................ $1,069.30\nII.- Mayor de 50.00 hasta 100.00 m² de construcción........... $1,164.43\nIII.- Mayor de 100.00 hasta 500.00 m² de construcción.......... $1,283.16\nIV.- Mayor de 500.00 hasta\n1,000.00 m² de construcción. $1,497.01\nV.- Mayor de 1,000.00 hasta\n5,000.00 m² de construcción. $2,031.66\nVI.- Mayor de 5,000.00 m² de construcción................ $3,207.89\n4).- Deporte y Recreación:\nParques y jardines; unidades deportivas, clubes y centros deportivos; plazas, zoológicos, balnearios públicos, pistas de patinaje, parque de diversiones, gimnasios, canchas, estadios, pistas.\nI.- Hasta 1,000.00 m² de predio. $1,283.16\nII.- Mayor de 1,000.00 hasta\n5,000.00 m² de predio....... $1,390.09\nIII.- Mayor de 5,000.00 hasta\n10,000.00 m² de predio...... $1,497.01\nIV.- Mayor de 10,000.00 m² de predio...................... $1,817.81\n5).- Servicios Administrativos:\nAdministración pública y administración privada, sucursales bancarias, aseguradoras, oficinas públicas de gobierno, sindicales, consulados, agencias comerciales:\nI.- Hasta 50.00 m² de construcción................ $962.36\nII.- Mayor de 50.00 hasta 100.00 m² de construcción........... $1,069.30\nIII.- Mayor de 100.00 hasta 500.00 m² de construcción.......... $1,176.23\nIV.- Mayor de 500.00 hasta\n1,000.00 m² de construcción. $1,497.01\nV.- Mayor de 1,000.00 m² de construcción................ $2,031.66\n6).- Turismo:\nAlojamiento (hoteles y moteles); agencias de viajes centros vacacionales.\nI.- Hasta 1,000.00 m² de construcción................ $1,069.30\nII.- Mayor de 1,000.00 hasta\n5,000.00 m² de construcción. $1,176.23\nIII.- Mayor de 5,000.00 hasta\n10,000.00 m² de construcción $1,390.09\nIV.- Mayor de 10,000.00 m² construcción................ $2,352.45\n7).- Servicios Mortuorios:\nCementerios, mausoleos y crematorios, agencias de inhumaciones funerarias.\nI.- Hasta 10 hectáreas de predio $1,390.09\nII.- Mayor de 10 hasta 20 hectáreas de predio.......... $1,600.40\nIII.- Mayor a 20 hectáreas de predio. $2,352.45\n8).- Comunicaciones y Transporte:\nT.V. y radio, telecomunicaciones; correos; telefonía; terminal de transporte urbano (autobús); terminal de transporte foráneo; terminal de ferrocarril, terminal aérea, sitios de taxis, estacionamiento y apeadero, encierro de transporte.\nI.- Hasta de 1,000.00 m² de predio. $1,176.23\nII.- Mayor de 1,000.00 hasta\n5,000.00 m² de predio....... $1,283.16\nIII.- Mayor de 5,000.00 hasta\n10,000.00 m² de predio...... $1,390.09\nIV.- Mayor de 10,000.00 m² de predio...................... $1,497.01\n9).- Diversión y Espectáculos:\nCines y teatros; auditorios y estadios; centros sociales, ferias; exposiciones y circos, centros de convenciones, clubes campestres, golf:\nI.- Hasta 1,000.00 m² de predio. $1,069.30\nII.- Mayor de 1,000.00 hasta\n5,000.00 m² de predio....... $1,283.16\nIII.- Mayor de 5,000.00 hasta\n10,000.00 m² de predio...... $2,780.17\nIV.- Mayor de 10,000.00 m² de predio...................... $4,704.91\n10).- Especial:\nI.- Hasta 1,000.00 m² de predio. $1,176.23\nII.- Mayor de 1,000.00 hasta\n5,000.00 m² de predio....... $1,283.16\nIII.- Mayor de 5,000.00 hasta\n10,000.00 m² de predio...... $1,390.09\nIV.- Mayor de 10,000.00 m² de predio...................... $1,817.81\nB.- En Industria:\na).- Extractiva:\nExplotación de minas y canteras; materiales de construcción contaminantes, explosiva que genere la utilización de vehículos hasta de una capacidad máxima de 14 toneladas para el transporte de materias primas y productos terminados, depósitos de productos inflamables y explosivos productos químicos en general:\n1.- Hasta 2 hectáreas de predio..... $4,277.18\n2.- Mayor de 2 hectáreas de predio.. $10,692.97\nb).- Transformación:\nFundición de minerales metálicos, fertilizantes, hules y plásticos, petróleo y derivados, papel y madera, bloque y ladrilleras; alimenticia; bebidas y tabaco, pigmentos, pintura colorantes y derivados; vidrios, cerámica y derivados.\n1.- Hasta 1,000.00 m² de predio..... $3,207.89\n2.- Mayor de 1,000.00 hasta 5,000.00 m² de predio.................... $3,635.61\n3.- Mayor de 5,000.00 m² de predio.. $4,491.05\nc).- Manufacturera:\nMáquinas y herramientas, textiles e industrias de cueros de la madera; productos de papel; ensamble de aparatos eléctricos o electrónicos, manufactura de productos alimenticios, bebidas y tabaco, maquiladoras de otros tipos:\n1.- Hasta 500.00 m² de construcción. $3,207.89\n2.- Mayor de 500.00 hasta 1,000.00 m² de construcción.............. $3,849.47\n3.- Mayor de 1,000.00 m² de construcción.................... $4,918.76\nd).- Agroindustria:\nEnvases y empaques; forrajes y otras.\n1.- Hasta 1,000.00 m² de predio..... $2,352.42\n2.- Mayor de 1,000.00 hasta 5,000.00 m² de predio.................... $2,994.03\n3.- Mayor de 5,000.00 m² de predio.. $3,849.47\nC.- Infraestructura.Instalaciones:\n1. Instalaciones de plantas, estaciones y subestaciones eléctricas; torres y antenas; depósitos, cárcamos y bombas, relleno sanitario, plantas de tratamiento de aguas, presas:\na).- Hasta 1,000.00 m² de predio....... $2,138.59\nb).- Mayor de 1,000.00 m² de predio.... $2,780.17\n2.- Instalaciones de torres y antenas:\na).- Hasta 10.00 metros lineales....... $10,692.97\nb).- Mayor de 10.00 hasta 20.00 metros lineales.......................... $16,039.46\nc).- Mayor de 20.00 metros lineales.... $21,385.93\nD.- En otros usos.Actividades agropecuarias; cauces y cuerpo de agua; deshuesadero\n(yonques), compra-venta, recolección y selección de fierro, metales no ferrosos, materiales de demolición, papel, cartón, vidrio y otros establecimientos de lavado, engrasado, lubricación y auto lavado de vehículos, establecimientos para la venta-compra y/o renta de vehículos automotores en general de construcción, industria y de servicio, centros de verificación, talleres eléctricos y/o electrónicos, mecánicos, hojalatería, pintura, llantera:\na).- De 100 a 500 metros de superficie. $1,626.12\nb).- Hasta 1 hectárea de predio........ $4,277.18\nc).- Mayor de 1 hectárea de predio..... $4,597.98\nE.- A estas cuotas se les acumulará $ 1.00 por cada kilómetro o urbana de la Ciudad de Tecate, medidos a partir de ésta.\nF.- Parque eólico.-\na).- Hasta 100 hectáreas de predio..... $133,673.92\nb).- Mayor de 100 hectáreas de predio.. $240,591.82\nG.- Parque Solar.-\na).- Hasta 3 hectáreas de predio....... $64,157.82\nb).- Mayor de 3 hectáreas de predio.... $106,929.70\nTratándose de obras provenientes de inversiones del Gobierno Federal o del Estado de Baja California, no causarán el derecho estipulado en la letra F del numeral 6 de este Artículo.\nH.- Central de generación de energía.... $160,394.54\nI.- Centros de apuestas, apuestas remotas, salas de sorteos de números y/o casinos, libro foráneo y similares.\na).- Hasta 3,000.00 m² de superficie.... $53,464.84\nb).- Mayor de 3,000.00 m² de terreno en adelante........................... $80,197.28\n7.- POR EXPEDICIÓN DE DOCUMENTOS:\nA.- Copias simples de planos, por cada metro de longitud de papel y el proporcional por cada fracción...... $320.78\nB.- Certificación de copias de planos... $427.72\nC.- Constancia en relación con los desarrollos urbanos................. $534.65\nD.- Registro de cesión de derechos posesorios.......................... $320.78\na).- Por concepto de cambio de tasa..... $106.93\nE.- Copia heliográfica de documentos por metro lineal........................ $320.78\nF.- Copias de documentos y constancias catastrales, por la primera hoja.... $106.93\nG.- Por hoja adicional.................. $53.46\na).- Constancia catastral para certificación de datos catastrales. $529.40\n1).- Constancia catastral para traslado de expediente.................... $741.16\nb).- Constancia catastral que requiera análisis técnico................... $1,620.82\nc).- Constancia de no propiedad......... $211.76\nH.- Copia de información catastral computarizada por hoja simple....... $213.86\nI.- Copia de información catastral computarizada certificada, por hoja. $320.78\nJ.- Copia certificada de documentos de propiedad por la primera hoja....... $213.86\nK.- Copia simple u hoja adicional....... $10.70\nL.- Copia certificada de deslinde o levantamiento catastral............. $320.78\nM.- Por inscripción de nuevos registros catastrales......................... $320.78\nN.- Por rectificación de antecedentes y cambio de propietario............... $320.78\nÑ.- Para la obtención de los documentos de las fracciones anteriores con carácter de urgente, en tiempos menores de lo los mismos.\nO.- Constancia de ocupación de obra..... $534.65\nP.- Por copia de planos digitalizados... $641.58\nQ.- Por dibujo de planos digitalizados.. $1,390.09\na).- Papel albanene por dm²............ $85.54\nb).- Papel bond por dm²................ $64.06\nc).- A color y en los tipos de papel, se pagará un aumento por dm² de... $10.70\nR.- Certificación de copias de planos para electrificación............... $534.65\nS.- Por dibujo y certificación de planos digitalizados para electrificación. $1,390.09\nT.- Certificación de copias de planos base para localización de redes de agua y drenaje..................... $1,023.25\nU.- Por dibujo y certificación de planos digitalizados para ubicación y/o localización de redes de agua y drenaje............................ $2,660.46\nV.- Historial registral de un predio urbano dentro de desarrollos autorizados, por registro catastral.......................... $938.84\n1).-Historial registral de un predio suburbano, rústico o rural, por registro catastral............. $1,470.28\n2).-Certificación de datos descriptivos del inmueble...... $481.18\n3).-Certificación de datos cartográficos.............. $400.98\n4).-Certificación de datos generales catastrales.............. $411.67\nW.- Análisis y aplicación de ajuste del valor unitario de predios suburbano y rurales, por predio............. $938.84\n1).-Por expedición de constancias de valor catastral de conformidad a la tabla de valores publicada... $938.84\n2).-Análisis y aplicación de ajuste del valor unitario de predios suburbanos y rurales, por predio.......................... $938.84\n3).-Por expedición de constancias de valor catastral de conformidad a la tabla de valores publicada... $748.51\n4).-Por modificación de expedientes derivados de relotificaciones en fraccionamientos, o condominios autorizados sobre predios propiedad del fraccionador, por predios o cuentas catastrales hasta 250 registros............. $336.82\n5).-Por modificación de expedientes derivados de relotificaciones en fraccionamientos, o condominios autorizados sobre predios propiedad del fraccionador, por predios o cuentas catastrales de\n251 registros en adelante...... $390.29\nX.- Para la obtención de los documentos de los incisos anteriores con carácter de urgente, en tiempos menores de lo que requiere el trabajo normal se les incrementará un 50% en el pago de los derechos normales de los mismos.\n8.- POR TRABAJOS TÉCNICOS:\nA.- Deslinde o levantamientos de predios:\na).- En predios urbanos y suburbanos en donde existen ejes físicos la siguiente TABLA:\nSUPERFICIE (m²) IMPORTE\nMAYOR DE HASTA PESOS\n1).- 0 130 $ 748.51\n2).- 130 160 $ 1,069.30\n3).- 160 250 $ 1,176.23\n4).- 250 350 $ 1,283.16\n5).- 350 500 $ 1,603.94\n6).- 500 600 $ 1,844.53\n7).- 600 700 $ 1,988.88\n8).- 700 800 $ 2,133.24\n9).- 800 900 $ 2,277.61\n10).- 900 1,000 $ 2,427.30\n11).- 1,000 1,200 $ 2,496.81\n12).- 1,200 1,400 $ 2,566.32\n13).- 1,400 1,600 $ 2,641.17\n14).- 1,600 1,800 $ 2,710.66\n15).- 1,800 2,000 $ 2,780.17\n16).- 2,000 2,400 $ 2,924.52\n17).- 2,400 2,600 $ 2,994.03\n18).- 2,600 2,800 $ 3,063.55\n19).- 2,800 3,000 $ 3,138.38\n20).- 3,000 3,200 $ 3,207.89\n21).- 3,200 3,400 $ 3,277.40\n22).- 3,400 3,600 $ 3,352.24\n23).- 3,600 3,800 $ 3,421.75\n24).- 3,800 4,000 $ 3,491.26\n25).- 4,000 4,200 $ 3,566.10\n26).- 4,200 4,400 $ 3,635.61\n27).- 4,400 4,600 $ 3,705.12\n28).- 4,600 4,800 $ 3,779.95\n29).- 4,800 5,000 $ 3,849.47\n30).- 5,000 5,500 $ 3,988.47\n31).- 5,500 6,000 $ 4,132.84\n32).- 6,000 6,500 $ 4,271.85\n33).- 6,500 7,000 $ 4,410.85\n34).- 7,000 7,500 $ 4,555.20\n35).- 7,500 8,000 $ 4,694.22\n36).- 8,000 8,500 $ 4,833.23\n37).- 8,500 9,000 $ 4,972.23\n38).- 9,000 9,500 $ 5,116.58\n39).- 9,500 10,000 $ 5,255.60\nSUPERFICIE (HECTÁREAS) IMPORTE\nMAYOR DE HASTA EN PESOS\n40).- 1 2 $ 6,469.24\n41).- 2 3 $ 7,174.98\n42).- 3 4 $ 7,886.06\n43).- 4 5 $ 8,591.79\n44).- 5 6 $ 9,297.54\n45).- 6 7 $10,008.61\n46).- 7 8 $10,714.36\n47).- 8 9 $11,425.44\n48).- 9 10 $12,024.25\n49).- 10 12 $12,997.31\n50).- 12 14 $13,858.09\n51).- 14 16 $14,713.52\n52).- 16 18 $15,585.00\n53).- 18 20 $16,451.13\n54).- 20 22 $17,311.92\n55).- 22 24 $18,178.05\n56).- 24 26 $18,803.58\n57).- 26 28 $19,429.12\n58).- 28 30 $20,054.66\n59).- 30 32 $20,680.21\n60).- 32 34 $21,305.75\n61) - 34 36 $21,925.93\n62).- 36 38 $23,177.02\n63).- 38 40 $23,802.54\n64).- 40 42 $24,428.09\n65).- 42 44 $25,160.55\n66).- 44 46 $25,679.17\n67).- 46 48 $26,304.71\n68).- 48 50 $31,651.19\n69)- 50 100 $36,997.67\n70).- 100 150 $42,344.16\n71).- 150 200 $47,690.65\n72).- 200 250 $53,037.13\n73).- 250 300 $58,383.62\n74).- 300 350 $63,730.11\n75).- 350 400 $69,076.58\n76).- 400 450 $74,423.07\n77).- 450 500 $79,769.55\n78).- 500 600 $85,116.04\n79).- 600 700 $90,462.53\n80).- 700 800 $95,809.01\n81).- 800 900 $101,155.49\n82).- 900 1,000 $104,677.34\nMayor de 1,000 (mil) hectáreas en adelante $106,501.98 M.N.\nB.- Por derechos de revisión, despacho y certificación de deslinde o levantamientos efectuados por peritos deslindadores externos se cobrará el treinta y cinco por ciento de lo previsto de la tabla de la letra A del numeral 8 de este Artículo.\nC.- Por obtención de deslindes o levantamiento, así como revisión, despacho y certificación de los mismos, con carácter de urgente en tiempos menores de lo que requiere el trabajo normal, se les incrementará el doscientos por ciento de los pagos de los\nDerechos normales de los mismos.\nD.- Por la actualización de deslindes o levantamientos vencidos conforme al Reglamento del Catastro Inmobiliario, se cobrará el cincuenta por ciento de los derechos previstos por la letra\nB que antecede, por cada mes que tengan de vencidos.\nE.- Por cada vez que sea revisado el plano, si contiene errores u omisiones en su contenido, el perito responsable deslindador, pagará el importe de $320.78 M.N. por cada prevención.\nF.- Por registro como perito deslindador $3,931.51\nG.- Por revalidación anual como perito deslindador........................ $2,647.00\nH.- Por revalidación anual a destiempo como perito deslindador............ $4,023.44\n9.- OTROS SERVICIOS:\nA.- Por servicios derivados del sistema de información geográfica.\na).- Utilización de vértices geodésicos.\n1).- Información por vértice, ubicación, coordenadas y descripción..................... $427.72\n2).- Por información grabada en disco de planos digitalizados por megabyte fracciones resultantes, pagará.......................... $1,069.30\n3).- Por impresión de planos digitalizados, se cobrará por cada 50 cm lineales............ $534.65\nOtros servicios derivados del sistema de información geodésico y demás servicios de Catastro y Control Territorial de la Subdirección de Administración Territorial que no se contemplan en forma específica en la presente Ley, se cobrarán de acuerdo al presupuesto que al efecto realice la Dirección de Gestión Integral del Territorio, el que en todo caso será proporcional al costo del servicio, y en su caso, a la contraprestación en especie a que esté obligado el usuario del servicio.\nB.- Los servicios por registro estatal de perito valuador en el municipio, que sea aprobado por el Consejo Estatal de Valuación deberán cubrirse de acuerdo a la tarifa siguiente:\na).- Por registro inicial como perito valuador.......................... $4,235.20\nb).- Por revalidación anual de registro como perito valuador.............. $3,176.40\nc).- Por certificación de avalúo....... $427.72\nd).- Por revisión de documentos para ratificación y legalidad de firmas............................ $213.86\ne).- Por revisión de documentos para cambio de propietario............. $213.86\nf).- Por revalidación anual a destiempo como perito valuador.............. $4,764.60\nC.- Por análisis y ubicación de predios\na).- Dentro de los centros urbanos y suburbanos........................ $534.65\nb).- Fuera de los centros de población urbanos y suburbanos.............. $1,069.30\nD.- Verificación en campo de aquellas superficies de taludes, cañadas, cauces de escurrimientos pluviales, predios agropecuarios en producción, con solicitud de reconsideración del importe a pagar.................... $1,443.55\nE.- Cálculo para aplicación de ajuste en zona de boulevard, rurales y suburbanos.................... $1,042.57\nF.- Cálculo para aplicar factores de demerito por profundidad interior o callejón y escarpado con pendiente mayor a 20%....................... $962.37\nG.- Por inspección en campo, de predios que requieran cambios de tasa, rectificación de superficie y valores de construcción........... $454.45\n10.- OPERATIVIDAD DE ACTIVIDADES MERCANTILES.\nA.- Por verificación y certificación de factibilidad para la instalación, revalidación anual y regularización de rótulos, anuncios y similares, exceptuando la propaganda efectuada por partidos políticos; se pagará, previo al inicio del trámite por superficie o cantidad, según se indique, de acuerdo a la siguiente tabla:\na).- Licencia nueva con o sin iluminación con vigencia de un año, esta licencia:\n1).-Anuncios de tipo adosado, rótulo pintado, toldo, microperforado, otros; que hagan referencia al denominativo y/o propaganda comercial de productos que se venden en el establecimiento se cobrará por metro cuadrado de imagen:\nI).- Sin iluminación............ $51.71 POR m²\nII).- Con iluminación........... $108.41 POR m²\n2).-Rótulo electrónico con o sin movimiento...................... $844.99 POR ANUNCIO\n3).-Figura cilíndrica............... $320.78 POR PIEZA\n4).-Torre directorio................ $517.07 POR PIEZA\n5).-Mini portacartel direccional, exclusivamente para desarrollos habitacionales e industriales nuevos.......................... $801.97 POR PIEZA\n6).-Banca publicitaria.............. $801.97 POR PIEZA\n7).-Cobertizo publicitario y/o mobiliario urbano con publicidad. $1,069.31 POR UNIDAD\n8).-Carro de sonido................. $1,069.30 POR UNIDAD\n9).-Torreta en techo de camión o taxi $855.43 POR UNIDAD\n10).-Rótulo en vehículo excepto aquellos de distintivo fiscal... $213.86 POR VEHÍCULO\n11).-Publicidad en pantalla electrónica:\nI.- Hasta 10.00 m²................. $5,346.49\nII.- De 10.01 a 15.00 m²............ $6,415.78\nIII.- Más de 15.00 m²................ $534.65 POR METRO\nADICIONAL\n12).-Valla Publicitaria. $160.40 POR m²\n13).-Anuncios de tipo espectaculares, por cara........................ $2,710.21 POR m²\nb).- Revalidación anual de licencia, al verificarse que aún se cumplen los requisitos del reglamento; con vigencia de un año y de establecimientos que se anuncian a sí mismos:\n1).-Anuncios de tipo adosado, rótulo pintado, toldo, microperforado, otros; que hagan referencia al denominativo y/o propaganda comercial de productos que se venden en el establecimiento se cobrará por metro cuadrado de imagen:\nI).-Sin iluminación............. $25.85 POR m²\nII).-Con iluminación............ $54.20 POR m²\n2).-Rótulo electrónico con o sin movimiento...................... $427.73 POR ANUNCIO\n3).-Figura cilíndrica............... $160.40 POR FIGURA\n4).-Torre directorio................ $258.52 POR PIEZA\n5).-Mini portacartel direccional, exclusivamente para desarrollos habitacionales e industriales nuevos.......................... $534.65 POR PIEZA\n6).-Banca publicitaria.............. $534.65 POR PIEZA\n7).-Cobertizo publicitario y/o mobiliario urbano con publicidad. $534.65 POR UNIDAD\n8).-Carro de sonido................. $534.65 POR UNIDAD\n9).-Torreta en techo de camión o taxi $427.73 POR UNIDAD\n10).-Rótulo en vehículo excepto aquellos de distintivo fiscal... $106.93 POR VEHÍCULO\n11).-Publicidad en pantalla electrónica:\nI.- Hasta 10.00 m²................. $3,207.90\nII.- De 10.01 a 15.00 m²............ $4,277.19\nIII.- Más de 15.00 m²................ $320.78 POR METRO\nADICIONAL\n12).-Valla Publicitaria. $85.53 POR m²\n13).-Anuncios de tipo espectaculares, por cara........................ $1,626.12 POR m²\nc).- Licencia de regularización con vigencia de un año, cuando se licencia correspondiente:\n1).-Anuncios de tipo adosado, rótulo pintado, toldo, microperforado, otros; que hagan referencia al denominativo y/o propaganda comercial de productos que se venden en el establecimiento se cobrará por metro cuadrado de imagen:\nI).- Sin iluminación............ $103.42 POR m²\nII).- Con iluminación........... $216.82 POR m²\n2).-Rótulo electrónico con o sin movimiento.................... $1,283.17 POR ANUNCIO\n3).-Figura cilíndrica............... $481.19 POR FIGURA\n4).-Torre directorio................ $827.30 POR PIEZA\n5).-Mini portacartel direccional, exclusivamente para desarrollos habitacionales e industriales nuevos.......................... $1,069.30 POR PIEZA\n6).-Banca publicitaria.............. $1,069.30 POR PIEZA\n7).-Cobertizo publicitario y/o mobiliario urbano con publicidad. $1,283.17 POR UNIDAD\n8).-Carro de sonido................. $1,283.17 POR UNIDAD\n9).-Torreta en techo de camión o taxi $1,069.30 POR UNIDAD\n10).-Rótulo en vehículo excepto aquellos de distintivo fiscal... $320.78 POR VEHÍCULO\n11).-Publicidad en pantalla electrónica:\nI.- Hasta 10.00 m²................. $7,485.07\nII.- De 10.01 a 15.00 m²............ $8,554.38\nIII.- Más de 15.00 m²................ $748.50 POR METRO\nADICIONAL\n12).-Valla Publicitaria. $481.19 POR m²\n13).-Anuncios de tipo espectaculares, por cara........................ $3,794.29 POR m²\nd).- Licencia nueva con vigencia de 15 días naturales, cuando la licencia:\n1).- Anuncio en propiedad privada.. $213.86 POR PROMOCIÓN\n2).- Volantes........................ $320.78\nNOTA: Volantes con beneficio a la comunidad, no lucrativos........ EXENTO\n3).- Figura inflable, con publicidad y de duración temporal.......... $213.86 POR DÍA\n4).- Cartel promocional en propiedad privada......................... $213.86\nNOTA: Carteles a beneficio de la comunidad, no lucrativos........ EXENTO\n5).- Lonas publicitarias............ $160.39 POR M²\n6).- Instalación de modulo informativo y/o publicitario................ $320.78 POR UNIDAD\n7).- Servicio de perifoneo........... $320.78 POR UNIDAD\n8).- Servicio de publicidad en caravanas...................... $534.64 POR UNIDAD\n9).- Servicio de publicidad de exhibición..................... $320.78 POR UNIDAD\n10).- Revalidación temporal de licencia, al verificarse que se cumplan los requisitos de reglamento; vigencia de 15 días naturales:\nI.- Anuncio en propiedad privada... $106.93\nII.- Figura inflable, con publicidad, y de duración temporal......... $106.93 POR DÍA\nIII.- Revalidación de publicidad en pantalla electrónica.\nIII.1.- Hasta 10.00 m²............ $5,346.49\nIII.2.- De 10.01 a 15.00 m²....... $6,415.78\nIII.3.- Más de 15.00 m²........... $534.65 POR METRO\nADICIONAL\n11).- Licencia de regularización con vigencia de 15 días naturales, cuando se ha efectuado la instalación o el reparto sin contar con la licencia correspondiente:\nI.- Anuncio en propiedad privada... $320.78\nII.- Volantes....................... $641.58\nNOTA: Volantes de beneficio a la comunidad, no lucrativos....... EXENTO\nIII.- Figura inflable, con publicidad, y de duración temporal......... $320.78 POR DÍA\n12).- Por verificación y certificación de factibilidad para instalación, regularización y revalidación anual de licencia de aparatos de telefonía en la vía pública, existentes y de nueva instalación:\nI.- Licencia nueva para la instalación de teléfono público en la vía pública.............. $1,069.30 POR\nAPARATO\nII.- Regularización de teléfono público colocado en la vía pública........................ $1,069.30 POR\nAPARATO\nIII.- Revalidación anual de licencia por la colocación de teléfono público instalado en la vía pública........................ $1,069.30 POR\nAPARATO\nIV.- Licencia nueva para la instalación de cualquier objeto en la vía pública.............. $534.65 POR m² O\nFRACCIÓN\nIV.1.- Revalidación de licencia para la instalación de cualquier objeto en la vía pública...... $534.65 POR m² O\nFRACCIÓN\nLa revalidación contemplada en las fracciones I a la IV.1 que anteceden deberá realizarse antes de los 10 días previos a su vencimiento.\ne).-Análisis y emisión de certificado de no existencia de anuncio $542.04 cada vez que sea solicitado\n11.- CERTIFICADO DE MEJORAMIENTO DE LA IMAGEN URBANA: urbano baldío o construido, conforme lo define esta Ley. del mismo, tendrán derecho a los siguientes descuentos en el pago anual del impuesto predial.\nA.- Predios baldíos o no edificados.\na).- Los predios baldíos o no edificados deberán: Estar libres de basura, maleza, escombro, cascajo o cualquier otro residuo, desecho o desperdicio............ 20%\nb).- Contar con guarniciones y banquetas que permitan el libre tránsito peatonal o con iluminación dentro del inmueble.. 10%\nc).- Tener bardas de malla ciclónica, metálica o similar, en sus colindancias..................... 10%\nB.- Cuando el predio baldío o no edificado, se localice dentro de las zonas comerciales o industriales, además de lo anterior, deberá contener:\n1).- Si se ubica en una esquina, contar con adecuaciones para personas con discapacidad....... 5%\n2).- Si se usa como bodega al aire libre para cualquier tipo de material, contar con barda de mampostería, concreto o similar al frente y en sus colindancias, pintada y en buen estado........ 2.5%\n3).- Contar con árboles al frente del predio con espacio de seis metros entre cada uno......... 2.5%\nC.- Predios edificados:\na).- Los predios edificados que busquen acreditar el certificado de imagen urbana deberán: Estar libres de basura, maleza, escombro, cascajo o cualquier otro residuo, desecho o desperdicio además de cumplir con el Reglamento de Imagen Urbana vigente para el Municipio de\nTecate, Baja California...... 40%\nD.- Bases para el otorgamiento del Certificado de Mejoramiento de la Imagen Urbana:\n1).- Acreditar ser propietario o poseedor con justo título de un inmueble urbano que se encuentre baldío, edificado o no edificado.\n2).- Al momento de inscribirse para adquirir el Certificado de\nMejoramiento de la Imagen Urbana, pagará la cuota correspondiente, en base a la siguiente tabla:\nA) Certificado nuevo\nVALOR CATASTRAL COSTO DEL CERTIFICADO\nMAYOR DE HASTA IMPORTE\nPESOS\n1).- 37,200 $ 26.74\n2).- 37,200 93,000 $ 53.46\n3).- 93,000 186,000 $ 160.39\n4).- 186,000 279,000 $ 213.86\n5).- 279,000 372,000 $ 267.32\n6).- 372,000 558,000 $ 320.78\n7).- 558,000 744,000 $ 427.72\n8).- 744,000 1,116,000 $ 641.58\n9).- 1,116,000 1,488,000 $ 855.43\n10).- 1,488,000 1,860,000 $1,069.30\n11).- 1,860,000 2,232,000 $1,390.09\n12).- 2,232,000 2,604,000 $1,603.94\n13).- 2,604,000 2,976,000 $1,710.88\n14).- 2,976,000 3,348,000 $2,031.66\n15).- 3,348,000 3,720,000 $2,245.52\n16).- 3,720,000 4,464,000 $2,566.32\n17).- 4,464,000 5,208,000 $2,994.03\n18).- 5,208,000 5,902,000 $3,528.68\n19).- 5,902,000 6,696,000 $3,849.47\n20).- 6,696,000 7,440,000 $4,277.18\n21).- 7,440,000 8,164,000 $4,704.91\n22).- 8,164,000 8,928,000 $4,811.84\n23).- 8,928,000 9,672,000 $4,918.76\n24).- 9,672,000 10,416,000 $5,132.63\n25).- 10,416,000 11,160,000 $5,239.56\n26).- MÁS DE 11,160,000 $5,346.49\nB) En caso de revalidación anual el solicitante pagará el treinta por ciento de lo indicado en la tabla anterior.\n3).- En caso de haber cumplido dentro del plazo de 6 meses con los requisitos señalados en las letras A y B que anteceden, para obtener el estímulo fiscal correspondiente, la Dirección de\nGestión Integral del Territorio realizará una inspección otorgando en su caso, el Certificado de Mejoramiento de la\nImagen Urbana, así mismo tendrá una vigencia de 2 años para predios construidos y/o habitacionales y de carácter comercial.\nArtículo 39.- Por la REVISIÓN DE EXPEDIENTE, Y EN SU CASO LA\nEXPEDICIÓN DE AUTORIZACIÓN DE DERECHOS DE DESARROLLO, que comprende acciones de urbanización o edificación que implican densificación, intensificación o cambio de uso de suelo, conforme a lo establecido en la normatividad vigente y del programa de desarrollo urbano del centro de población de Tecate 2020-2040, se cobrará conforme a la siguiente fórmula: factor determinado por acción de urbanización (f) multiplicado por el valor catastral del predio de acuerdo a la tabla de valores catastrales (vc) multiplicado por los metros cuadrados que se calculan de la siguiente manera según sea el caso (x):\nI. Respecto a densificación e intensificación: superficie privativa en metros cuadrados de la edificación o urbanización, de acuerdo al excedente que sobrepase la densidad o intensidad permitida;\nII. En el caso de cambio de uso de suelo, el factor se determina por los metros cuadrados totales de la superficie del predio.\nEl factor (f) es determinado en la siguiente forma:\n# Acción de urbanización Factor\n1 Densificación dentro del centro de población 0.4\n2 Densificación fuera del centro de población 0.6\n3 Intensificación del suelo dentro del centro de población 0.3\n4 Intensificación del suelo fuera del centro de población 0. 5\nCambio de uso de suelo dentro del centro de población, mediante el procedimiento que\n5 indica la legislación y normatividad aplicable y sin contravenir cualquier otra disposición normativa\n5.1 De habitacional a especial 2\n5.2 De habitacional a industrial 2.5\n5.3 De habitacional a comercial 1.8\n5.4 De habitacional a equipamiento 1.5\n5.5 De especial a habitacional 0.2\n5.6 De especial a industrial 1\n5.7 De especial a comercial 1\n5.8 De especial a equipamiento 0.8\n5.9 De especial a habitacional 0.3\n5.10 De industrial a comercial 0.5\n5.11 De industrial a especial 1\n5.12 De industrial a equipamiento 0.5\n5.13 De industrial a habitacional 0.3\n5.14 Desde uso de suelo de conservación 4\n5.15 Cualquier otro cambio de uso de suelo no contemplado 0.6\nCambio de uso de suelo fuera del centro de población, mediante el procedimiento que\n6 indica la legislación y normatividad aplicable y sin contravenir cualquier otra disposición normativa\n6.1 De habitacional a especial 3.5\n6.2 De habitacional a industrial 3\n6.3 De habitacional a comercial 2.5\n6.4 De habitacional a equipamiento 0.9\n6.5 De especial a habitacional 0.1\n6.6 De especial a industrial 1\n6.7 De especial a comercial 1\n6.8 De especial a equipamiento 0.8\n6.9 De especial a habitacional 0.3\n6.10 De industrial a comercial 0.5\n6.11 De industrial a especial 0.5\n6.12 De industrial equipamiento 0.3\n6.13 De industrial a habitacional 0.1\n6.14 Desde uso de suelo de conservación 5\n6.15 Cualquier otro cambio de uso de suelo no contemplado 0.5 para el desarrollo de infraestructura pública y/o equipamientos públicos, previo análisis técnico, así como los desarrollos habitacionales que promuevan la vivienda mínima, social y económica con un precio a la venta, previo avalúo certificado por el\nAyuntamiento, de hasta 600,000.00 pesos; un descuento del 50% en el caso de desarrollos habitacionales de más de 600,000.00 pesos y hasta\n1,200,000.00 pesos, previo avalúo certificado por el Ayuntamiento.\nQuedarán también exentos de pago de derechos de desarrollo, fraccionamientos de venta de lotes de interés social de hasta 120 metros cuadrados, siempre y cuando exista una opinión favorable de\nEstudio de Impacto Territorial Urbano.\n7.- DERECHOS POR LOS SERVICIOS QUE PRESTA LA DIRECCIÓN DE GESTIÓN\nINTEGRAL DEL TERRITORIO EN MATERIA DE PROTECCIÓN AL AMBIENTE\nARTÍCULO 40.- Por los servicios que presta el Departamento de Impacto\nAmbiental se cubrirán las siguientes:\nIMPORTE\nPESOS\n1.- Por permiso para transporte de aguas residuales domésticas (ejercicio fiscal)............................ $1,069.30\n2.- Por permiso para transporte de aguas residuales industriales (ejercicio fiscal)............................ $3,207.89\n3.- Anuencia de Impacto Ambiental\nA.- Por análisis, verificación y resolución de anuencia de impacto ambiental en su modalidad INFORME PREVENTIVO, para las obras o\na).- Informe preventivo para trámite de cualquier obra o actividad prestación de servicios, que representan el mínimo impacto al ambiente o desequilibrio ecológico, no rebasa los límites y condiciones señalados en los\nReglamentos y Normas Técnicas\nEcológicas aplicables............ $1,283.16 a $2,566.32\nb).- Informe preventivo para trámite de cualquier obra o actividad prestación de servicios, que representan mediano impacto ambiental, ocasionado por volumen de residuos generados superior a 5 kilos por día, cantidad de personal superior a 5 personas por turno, o área del inmueble superior a 250 metros cuadrados y que emplean medidas para mitigar y prevenir la contaminación del ambiente......................... $2,673.24 a $4,277.18\nc).- Por la inscripción en el padrón de prestadores de servicios en materia de impacto ambiental dentro del municipio............. $5,954.51\nd).- Por la inscripción de auditores ambientales dentro del municipio $5,954.51\nB.- Por análisis, verificación y resolución de anuencia de impacto ambiental en su modalidad de manifiesto de Impacto Ambiental para:\na).- Desarrollos habitacionales, inmobiliarios, fraccionamientos residenciales.................... $5,346.49 a $7,805.86\nb).- Desarrollos comerciales, plazas comerciales o de servicios, mixtos con habitacionales o residenciales.................... $8,028.02 A $54,243.42\nc).- Desarrollos industriales o de manufactura, parques industriales, mixtos con comerciales.................... $11,254.58 a $16,487.96\nd).- Desarrollos de energía renovable, parques eólicos, solares, mixtos con industriales, comerciales o habitacionales................... $16,487.96 a $24,154.86\ne).- Antenas de telecomunicaciones.... $24,154.86 a $35,386.87\nf).- Construcción y operación de centros de transferencia, almacenamiento, tratamiento de residuos y rellenos sanitarios... $35,386.87 a $51,841.76\nSe requiere, previamente la evaluación y otorgamiento de la Anuencia de Impacto Ambiental por la autoridad municipal, en los siguientes casos:\nC.- Por Anuencia de Impacto Ambiental para Obras o Actividades\nComerciales y de Servicios que pretendan realizarse dentro de la jurisdicción municipal\na).- Hasta 100.00 m² de superficie.... $534.65\nb).- Mayores de 100.00 hasta 250.00 m² $1,069.30\nc).- Mayores de 250.00 hasta 500.00 m² $1,283.16\nd).- Mayores de 500.00 hasta 750.00 m² $1,603.94\ne).- Mayores de 750.00 hasta\n1,000.00m²....................... $2,138.59\nf).- Mayores de 1,000.00 hasta 2,500.00 m²............................... $2,352.45\ng).- Mayores de 2,500.00 hasta 5,000.00 m²............................... $2,673.24\nh).- Mayores de 5,000.00 hasta 7,500.00 m²............................... $3,207.89\ni).- Mayores de 7,500.00 hasta\n10,000.00 m²..................... $3,421.75\nj).- Mayores de 1 hectárea hasta 5 hectáreas........................ $3,742.53\nk).- Mayores de 5 hectáreas........... $4,277.18\nD.- Por Anuencia de Impacto Ambiental para Fraccionamientos centro de población.\na).- Hasta 100.00 m² de superficie.... $534.65\nb).- Mayores de 100.00 hasta 250.00 m² $1,069.30\nc).- Mayores de 250.00 hasta 500.00 m² $1,283.16\nd).- Mayores de 500.00 hasta 750.00 m² $1,603.94\ne).- Mayores de 750.00 hasta 1,000.00 m²............................... $2,138.59\nf).- Mayores de 1,000.00 hasta 2,500.00 m²............................... $2,352.45\ng).- Mayores de 2,500.00 hasta 5,000.00 m²............................... $2,673.24\nh).- Mayores de 5,000.00 hasta 7,500.00 m²............................... $3,207.89\ni).- Mayores de 7,500.00 hasta\n10,000.00 m².................. $3,421.75\nj).- Mayores de 1 hectárea hasta 5 hectáreas........................ $3,742.53\nk).- Mayores de 5 hectáreas........... $4,277.18\nE.- Por Anuencia de Impacto Ambiental para Centrales de Abasto.\na).- Hasta 100.00 m² de superficie.... $1,069.30\nb).- De 101.00 hasta 250.00 m²........ $2,138.59\nc).- De 251.00 hasta 500.00 m²........ $3,207.89\nd).- Mayores de 500.00 m²............. $3,742.53\nF.- Por autorización de la Anuencia de\nImpacto Ambiental para la Actividad de Aprovechamiento de Minerales o\nSustancias no Reservados a la\nFederación, que constituyan depósitos de naturaleza semejante a los componentes de los terrenos, tales como rocas o productos de su desintegración para la fabricación de materiales para la construcción u ornato............................. $54,433.62\nG.- Por obras o actividades que, estando reservadas a la Federación o al\nEstado, se descentralicen a favor del Municipio a través del convenio respectivo......................... $4,277.20\nH.- Por otros conceptos de derechos en materia ambiental.................. $534.65\na).- Por la recepción de neumáticos de desecho para su disposición final en un sitio autorizado........... $6.68 a $26.71\nPOR NEUMÁTICO\nI.- Por concepto de pago en materia ambiental, solicitados por personas mayores de 60 años, cuando el trámite sea exclusivamente para ellos, y exhiban su credencial del INAPAM, CREDENCIAL DE ELECTOR Y/O CURP, se aplicará un beneficio del cincuenta por ciento de descuento del costo total (Persona\nFísica).\nJ.- Por Licencia de Transporte de Residuos Sólidos Urbanos\nMunicipales y de Manejo Especial:\n1. Domésticas:\na) Por viaje.................. $1,534.87\nb) Para el ejercicio fiscal... $13,104.30\n2. Comercio:\na) Por viaje.................. $2,046.50\nb) Para el ejercicio fiscal... $19,656.45\n3. Industria:\na) Por viaje.................. $3,069.76\nb) Para el ejercicio fiscal... $27,300.63\n4. Residuos Peligrosos:\na) Por viaje.................. $3,822.09\nb) Para el ejercicio fiscal... $32,760.75\nK.- Por el análisis de solicitud de prórroga para dar cumplimiento a las condiciones dictadas en la resolución....................... $1,069.30 EJERCICIO\nFISCAL\nL.- Por la revisión de solicitud de prórroga de cumplimiento de anuencia ambiental............... $1,711.75 EJERCICIO\nFISCAL\nM.- Cotejo y constancias de documentos emitidos y que se encuentren en el\nArchivo de la Dirección, cotejo de hoja por hoja.................... $37.42\nN.- Por expedición de copia simple... $11.00\n8.- DERECHOS POR SERVICIO DE GRÚAS\nARTÍCULO 41.- Los Derechos por Servicios de Grúas, que sean prestados acuerdo con la siguiente:\nPESOS\nA.- Costo de Arrastre dentro de la Zona Urbana.\na).- Automóviles o camionetas, pick-ups y vans......................... $695.04\nb).- Camiones........................ $1,069.30\nc).- Remolques y semirremolques...... $2,138.59\nd).- Tractocamiones.................. $2,673.24\ne).- Maniobras....................... $427.72 POR HORA\nDespués de transcurrido el tiempo inicial, se cobrará por el tiempo proporcional al tipo de maniobra realizada.\nf).- Motocicletas................... $320.78\ng).- Maniobras inconclusas de grúa, por el evento de presentarse reglamentado, con infracción por escrito, pero no se realice de grúa, se pagarán por vehículo las cuotas siguientes:\n1).- Automóviles, camionetas y pickups............................. $320.78\n2).- Camiones de pasajeros (microbús) $427.72\n3).- Remolques (tráiler) y autobuses de pasajeros.................... $534.65\n4).- Remolque de tractocamiones de tres o más ejes, con una o más cajas........................... $1,069.30\nB.- Costo de Arrastre fuera de Zona Urbana.\na).- Arrastre......................... $801.97\nb).- Maniobras inconclusas de grúa, por el evento de presentarse reglamentado, con infracción por escrito, pero no se realice de grúa, se pagarán por vehículo las cuotas siguientes:\n1).- Automóviles, camionetas y pickups............................. $320.78\n2).- Camiones de pasajeros (microbús) $427.72\n3).- Remolques (trailer) y autobuses de pasajeros................. $515.57\n4).- Remolque de tractocamiones de tres o más ejes, con una o más cajas........................... $1,069.30\nMás el importe de $19.24 M.N. por Km recorrido a partir de donde termina la Zona Urbana.\nTratándose de vehículos robados que ingresen al Depósito Municipal, previa comprobación con documentos oficiales de autoridad competente, se exentará del pago de los derechos de arrastre de vehículos, siempre y cuando el robo sea reportado dentro de las 72 horas subsecuentes al hecho.\nLa Zona Urbana comprenderá:\nHacia el Oriente carretera a Mexicali hasta Rancho la Paleta.\nHacia el Poniente carretera a Tijuana hasta Rancho la Puerta.\nHerrera por carretera a Ensenada.\nC.- Maniobras de Salvamento:\na).- Automóviles, camionetas y pickups.............................. $427.72\nb).- Camiones de pasajeros (microbús). $1,069.30\nc).- Remolques (tráiler) y autobuses de pasajeros........................ $1,603.95\nd).- Remolque de tractocamiones de tres o más ejes, con una o más cajas.. $2,138.59 para circular, hasta dejarlos en condiciones de arrastre o traslado, como es el caso de vehículos volcados, accidentados fuera de la carpeta asfáltica, dentro de un canal o barranco, entre otros.\n9.- DERECHOS POR ALMACENAJE DE VEHÍCULOS\nARTÍCULO 42.- Los Derechos por Almacenaje de Vehículos causarán una cuota diaria de:\nIMPORTE\nPESOS\na).- Automóviles, camionetas, pick-ups y vans........................... $42.78\nb).- Camiones de carga mediano........ $53.46\nc).- Camiones de carga grande......... $106.93\nd).- Tractor con remolque............. $213.86\ne).- Remolques (caja)................. $106.93\nf).- Tractores sin remolques.......... $106.93\ng).- Motocicletas y bicicletas........ $10.70\nh).- Camiones de pasajeros............ $106.93 cubrirán las tarifas anteriores, durante los tres primeros meses, y los días subsecuentes el veinticinco por ciento de la misma.\nPasados los tres meses, todas las unidades que constituyan garantías fiscales serán sujetas de remate.\nTratándose de vehículos robados que ingresen al Depósito Municipal, previa comprobación con documentos oficiales de autoridad competente, durante los primeros 15 días, siempre y cuando el robo sea reportado dentro de las 72 horas subsecuentes al hecho.\n10.- DERECHOS POR ESTACIONAMIENTO DE VEHÍCULOS EN LA VÍA PÚBLICA\nARTÍCULO 43.- Los propietarios de giros comerciales e industriales o aquellos que necesiten por razones propias del desarrollo de la actividad que ejerzan, ocupar sitios exclusivos de estacionamiento de vehículos, deberán obtener autorización escrita de la Tesorería\nMunicipal, debiendo pagar por mes dentro de los primeros diez días los Derechos por este concepto, de acuerdo a la siguiente clasificación:\nEN PESOS\nA.- Con señalamiento de cordones para sitios exclusivos de estacionamiento de vehículos diariamente, por metro lineal.\na).- En batería....................... $8.55\nb).- En cordón según su actividad:\n1).- En cordón para establecimiento comercial o industrial.......... $7.49\n2).- En cordón para unidades tipo taxi............................ $5.35\n3).- En cordón para carga y descarga........................ $7.49\nB.- En el estacionamiento de vehículos donde se encuentren instalados aparatos medidores de tiempo, de las 7:00 horas a las 19:00 horas diariamente, excepto domingos, días festivos y los que se determine para efecto de eventos cívicos, culturales, deportivos, gastronómicos, recreativos, esparcimiento y sociales..\na).- Cada 15 minutos................ $3.00\nC.- Cuota por retiro de inmovilizador.. $150.00\nD.- Multa por no pago o vencimiento de tiempo............................. $200.00\nE.- Exclusivos en zona de parquímetros para comercios mensual............. $1,600.00\nF.- Exclusivos en zona de parquímetros para taxis mensual............. $1,000.00\nG.- Grúa en zona de parquímetro arrastre $850.00\nH.- Grúa en zona de parquímetros por KM. después del arrastre................ $20.00\nI.- Almacenaje de vehículo por arrastre de grúa por infracción en zona de parquímetros, por día............... $55.00\nJ.- Calcomanías para residentes para el derecho de estacionarse en la zona de su domicilio de acuerdo al reglamento en zonas controladas por estacionometros y/o parquímetros semestral............... $800.00\nK.- Calcomanías para residentes para el derecho de estacionarse en la zona de su domicilio de acuerdo al reglamento en zonas controladas por estacionometros y/o parquímetros anual............... $1,500.00 el entendido de que, para esos efectos, se tomará el valor del mes en que se realice dicho pago.\n11.- DERECHOS POR EXPEDICIÓN DE CERTIFICADOS, TÍTULOS O COPIAS DE\nDOCUMENTOS\nARTÍCULO 44.- Los Certificados, copias certificadas, legalización de prestar el servicio, incluyendo equipos, materiales y costos de personal, conforme a lo siguiente:\nEN PESOS\nA.- Certificación en general........... $213.86\nB.- Copia adicional.................... $1.34\nC.- Certificado de alineamiento........ $213.86\nD.- Pago por número oficial del\nDepartamento de Nomenclatura....... $160.39\nE.- Certificados de Libertad de\nGravámenes......................... $427.72\nF.- Autorización para la realización de eventos:\n1).- Familiares en la vía pública.... $320.78\n2).- De juegos mecánicos............. $1,603.94\n3).- De kermeses..................... $1,603.94\n4).- De espectáculos de circo........ $2,138.59\n5).- Masivos y espectáculos especiales...................... $2,673.24\n6).- De uso de cruceros y vía pública......................... $320.78\n7).- Bailes populares................ $1,069.30\nG.- Certificados de Peritaje de Tránsito\nMunicipal, a solicitud del interesado......................... $1,069.30\nH.- Certificado de residencia.......... $267.32\nI.- Certificado de legalidad de firmas............................. $1,069.30\nJ.- Certificado de buena conducta...... $427.72\nK.- Certificación de documentos para titulación de terreno rústico o Certificado de Posesión:\na).- Hasta 1 hectárea................. $534.65\nb).- Por las siguientes 99 hectáreas........................ $160.39\nc).- Por las siguientes 200 hectáreas........................ $106.93\nd).- Mayor de 300 hectáreas........... $80.20\nL.- Copia fotostática de documentos oficiales o de las dependencias municipales....................... $26.74\nM.- Certificación testimonial solicitada por posesión de predios registrados.\na).- Zona urbana no mayor a 500.00 m². $2,138.59\nb).- Zona urbana mayor a 500.00 m².... $3,207.89\nc).- Zona rural hasta por 50 hectáreas $4,277.18\nd).- Zona rural mayor a 50 hectáreas.. $5,346.49\nN.- Certificación testimonial solicitada por posesión de predios no registrados:\na).- Zona urbana no mayor a 500.00 m². $2,673.24\nb).- Zona urbana mayor a 500.00 m².... $3,742.53\nc).- Zona rural hasta por 50 hectáreas $4,811.84\nd).- Zona rural mayor a 50 hectáreas.. $5,881.14\n1).- Después de 50 hectáreas, por cada\n50 hectáreas excedentes.... $1,069.30\nÑ.- Otras informaciones testimoniales.. $641.58\nO.- Por servicios de recepción de documentos para trámite de pasaporte mexicano ante la Secretaría de\nRelaciones Exteriores $219.63\nTratándose de personas mayores de 60 años y las personas con discapacidad, se otorgará descuento del cincuenta por ciento, bajo el criterio de equidad e igualdad.\na).- Por servicios de recepción de documentos para trámite de constitución de sociedad ante la\nSecretaría de Relaciones\nExteriores....................... $219.63\nb).- Por servicios de recepción de documentos para trámite de aviso de uso de nombre de la constitución de sociedad ante la\nSecretaría de Relaciones\nExteriores....................... $219.63\nP.- Certificado de Gravamen Fiscal..... $427.72\nQ.- Certificado de No adeudo Fiscal.... $641.58\nR.- Carta de dependencia económica..... $267.32\nS.- Constancia de identidad............ $213.86\nTratándose de trámite para el otorgamiento de Seguro Popular, este trámite se considerará exento.\nT.- Expedición, grabación y/o envío de documentos e información solicitada por la Unidad Municipal de Acceso a la Información, serán pagados por los peticionarios, sujetándose a la siguiente tarifa:\nIMPORTE\nPESOS\na).- Copia simple (después de la copia número 21)..................... $1.77\nb).- Copia certificada................ $17.11\nc).- Disco compacto (CD).............. $17.11\nU.- Legalización de Sociedad\nCooperativa........................ $641.58\nTratándose de espectáculos realizados por organismos no lucrativos que brinden servicios y asistencia médica de manera gratuita a enfermos que padezcan cáncer en etapa terminal, debidamente registrados ante institución oficial que para tales efectos señale la ley de la materia........................... $0.00\n12.- DERECHOS POR OTORGAMIENTO Y REVALIDACIÓN DE LICENCIAS DE\nOPERACIÓN.\nARTÍCULO 45.- Por otorgamiento y/o revalidación de licencias de operación para giros comerciales, industriales y de servicios, se causarán conforme a lo siguiente:\nA.- COSTO POR GIRO\nIMPORTE\nPESOS\nGIRO TARIFA\nDE: A:\n1.- ABARROTES Y MISCELÁNEAS $ 427.72 $1,069.30\n2.- ACADEMIAS PARTICULARES $ 213.86 $3,207.89\n3.- ACEITES Y LUBRICANTES $ 748.51 $1,497.01\n4.- ACUARIOS $ 838.53 $ 855.43\n5.- AGENCIAS ADUANALES $ 534.65 $1,069.30\n6.- AGENCIA AUTOMOTRIZ $2,673.24 $3,528.68\n7.- AGENCIAS DE BIENES RAÍCES $ 534.65 $1,069.30\n8.- AGENCIA DE MOTOCICLETAS $1,688.37 $3,376.73\n9.- AGENCIAS DE MUDANZAS $ 427.72 $ 855.43\n10.- AGENCIAS DE PUBLICIDAD $ 534.65 $1,069.30\n11.- AGENCIAS DE SEGUROS Y FIANZAS $ 534.65 $1,069.30\n12.- AGENCIAS DE VIAJES $ 534.65 $1,069.30\n13.- ALFARERÍAS $ 213.86 $ 534.65\n14.- ALIMENTOS BALANC. P/ANIMALES\n(ESTABLOS) $1,069.30 $2,138.59\n15.- ARRENDADORAS DE EQ. DE CONSTRUCCIÓN $1,069.30 $2,138.59\n16.- ARTESANÍAS DE VIDRIO $ 534.65 $1,069.30\n17.- ARTESANÍAS Y CURIOSIDADES $ 534.65 $1,069.30\n18.- ARTÍCULOS DE BELLEZA $ 534.65 $1,069.30\n19.- ARTÍCULOS PARA EL HOGAR $ 534.65 $1,069.30\n20.- ARTÍCULOS PARA FIESTAS $ 534.65 $1,069.30\n21.- AUTOLAVADO $ 641.58 $1,283.17\n22.- AUTOSERVICIOS $2,673.24 $3,528.68\n23.- AVÍCOLAS $ 641.58 $1,283.16\n24.- BARBERÍAS Y PELUQUERÍAS $1,155.97 $1,603.94\n25.- BARES Y CANTINAS $1,764.35 $3,528.68\n26.- BILLARES $1,336.62 $2,673.24\n27.- BODEGAS INDUSTRIALES $2,673.24 $3,207.88\n28.- BOLERÍAS $ 213.86 $ 534.65\n29.- BOTÁNICAS $ 641.58 $1,283.16\n30.- BOUTIQUES $ 534.65 $1,069.30\n31.- BUFETES JURÍDICOS $ 427.72 $ 855.43\n32.- CAFETERÍAS $ 534.65 $1,069.30\n33.- CAFÉ INTERNET $ 534.65 $1,069.30\n34.- CARNICERÍAS $ 534.65 $1,069.30\n35.- CARPINTERÍAS $ 748.51 $1,497.01\n36.- CASAS DE CAMBIO $ 534.65 $1,069.30\n37.- CASAS DE EMPEÑO $ 748.51 $1,497.01\n38.- CENTROS CAMBIARIOS $ 534.65 $1,069.30\n39.- CENTROS DE ABASTOS $ 801.97 $1,603.94\n40.- CENTROS DE APUESTAS $3,207.88 $4,277.16\n41.- CENTROS DE COPIADO $ 534.65 $1,069.30\n42.- CENTROS DE ESPECTÁCULOS $2,673.24 $3,528.68\n43.- CENTROS DE REDUCCIÓN DE PESO $ 534.65 $1,069.30\n44.- CENTROS DE REHABILITACIÓN $1,336.62 $2,673.24\n45.- CENTROS RECREATIVOS $1,764.35 $3,528.68\n46.- CENTROS VACACIONALES $1,764.35 $3,528.68\n47.- CERRAJERÍAS $ 534.65 $1,069.30\n48.- CREMATORIO $2,673.24 $3,528.68\n49.- CINEMAS $1,764.35 $3,528.68\n50.- CLÍNICAS VETERINARIAS $ 534.65 $1,069.30\n51.- CLÍNICAS Y SANATORIOS $1,764.35 $3,528.68\n52.- CLÍNICAS DE MASAJE Y TERAPIA FÍSICA $1,764.35 $3,528.68\n53.- COLCHONERA $1,069.31 $2,138.59\n54.- COLECTIVOS $1,023.26 $3,373.73\n55.- COLEGIOS PARTICULARES $1,764.35 $3,528.68\n56.- COLOCACIÓN DE PISOS $1,023.26 $2,046.50\n57.- COMERCIALIZADORAS $1,336.62 $2,673.24\n58.- COMERCIO AL POR MENOR DE CARNES $1,069.31 $2,138.59\n59.- COMISIONISTAS $ 801.97 $1,603.94\n60.- COMPLEMENTOS ALIMENTICIOS $ 850.10 $1,700.17\n61.- COMPRA VTA. DE COMPONENTES\nELECTRÓNICOS $1,336.62 $2,673.24\n62.- COMPRA VTA.DE MAQUINARIA\nINDUSTRIAL $2,673.24 $3,528.68\n63.- CONSTRUCTORAS $1,764.35 $3,528.68\n64.- CONSULTORIO DE ESPECIALIDADES $ 511.63 $1,023.26\n65.- CONSULTORIOS DENTALES $ 534.65 $1,069.30\n66.- CONSULTORIOS MÉDICOS $ 534.65 $1,069.30\n67.- CONSULTORIOS PSICOLÓGICOS $ 534.65 $1,069.30\n68.- CONTRATISTAS EN GENERAL $1,764.35 $3,528.68\n69.- DECORACIONES $ 801.97 $1,603.94\n70.- DEPÓSITO DENTAL $ 511.63 $1,023.26\n71.- DEPÓSITOS Y ALMACENES $1,069.30 $2,138.59\n72.- DESPACHOS CONTABLES $ 534.65 $1,069.30\n73.- DISCOTECAS Y SALONES DE BAILE $1,764.35 $3,528.68\n74.- DISEÑO GRÁFICO $ 534.65 $1,069.30\n75.- DISEÑO Y DECORACIÓN DE INTERIORES $1,023.26 $2,046.50\n76.- DISTRIBUCIÓN Y VTA. DE ALIMENTOS\nPREPARADOS $1,069.30 $2,138.59\n77.- DISTRIBUIDORAS $ 801.97 $1,603.94\n78.- DISTRIBUIDORAS DE GAS DOMÉSTICO $1,764.35 $3,528.68\n79.- DULCERÍA Y PUESTOS DE DULCES $ 213.86 $1,069.30\n80.- EDITORIALES/ PERIÓDICOS $ 801.97 $1,603.94\n81.- EMPACADORAS $1,764.35 $3,528.68\n82.- ENVASADORAS Y EMBOTELLADORAS $1,764.35 $3,528.68\n83.- ESCRITORIOS PÚBLICOS $ 427.72 $ 855.43\n84.- ESTABLO $2,138.59 $3,528.68\n85.- ESTACIONAMIENTO $ 534.65 $1,069.30\n86.- ESTACIONES DE SERV. AUTOMOTRIZ $1,710.88 $3,528.68\n87.- ESTÉTICA $ 801.97 $1,603.94\n88.- ESTÉTICA, PELUQUERÍA Y SPA PARA\nMASCOTAS $ 801.97 $1,603.95\n89.- ESTUDIOS DE FOTOGRAFÍA $ 534.65 $1,069.30\n90.- EXPENDIOS DE CERVEZA $ 801.97 $1,603.94\n91.- FÁBRICA DE CERVEZA $2,673.24 $3,528.68\n92.- FÁBRICA DE DULCES $2,673.24 $3,528.68\n93.- FÁBRICA DE PROD. ALIMENTICIOS $2,673.24 $3,528.68\n94.- FÁBRICA DE PROD. METÁLICOS $2,673.24 $3,528.68\n95.- FÁBRICAS DE CARTÓN $2,673.24 $3,528.68\n96.- FÁBRICAS DE CONCRETO $2,673.24 $3,528.68\n97.- FÁBRICAS DE CONSERVAS $2,673.24 $3,528.68\n98.- FÁBRICAS DE HELADOS $2,673.24 $3,528.68\n99.- FÁBRICAS DE MUEBLES $2,673.24 $3,528.68\n100.- FÁBRICAS DE PROD.DE BARRO Y CERÁMICA$2,673.24 $3,528.68\n101.- FÁBRICAS DE TEXTILES $2,673.24 $3,528.68\n102.- FÁBRICAS VARIOS PRODUCTOS $2,673.24 $3,528.68\n103.- FARMACIAS $1,069.31 $2,138.59\n104.- FARMACIAS Y AUTOSERVICIOS $2,138.59 $3,207.90\n105.- FERRETERÍAS $1,336.62 $2,673.24\n106.- FLORERÍAS $1,069.30 $2,138.59\n107.- FORRAJERÍAS $ 427.72 $ 855.43\n108.- FRACCIONAMIENTOS $ 748.51 $1,497.01\n109.- FRUTERÍAS Y VERDULERÍAS $ 801.97 $1,603.94\n110.- FUMIGADORAS $ 374.26 $ 749.55\n111.- FUNDICIONES $ 534.65 $1,069.30\n112.- FUNERARIAS $ 534.65 $1,069.30\n113.- GASES INDUSTRIALES $ 534.65 $1,069.30\n114.- GASOLINERAS $1,764.35 $3,528.68\n115.- GIMNASIOS $ 534.65 $1,069.30\n116.- GRANEROS $ 534.65 $1,069.30\n117.- (GRÚAS) SERVICIO DE ARRASTRE DE\nVEHÍCULOS $ 213.86 $ 534.65\n118.- GUARDERÍAS $2,138.59 $3,207.89\n119.- HERRERÍAS Y HOJALATERÍAS $ 748.51 $1,497.01\n120.- HOTELES Y MOTELES $1,764.35 $3,528.68\n121.- IMPRENTAS $ 534.65 $1,069.30\n122.- INDUSTRIA GENERADORA DE\nELECTRICIDAD $2,673.25 $3,528.68\n123.- INSTITUCIÓN FINANCIERA $1,069.31 $2,138.59\n124.- INSTITUCIONES BANCARIAS $2,138.59 $2,673.24\n125.- INSTITUCIONES NO LUCRATIVAS $ 213.86 $ 534.65\n126.- INSTITUTOS DE COMPUTACIÓN Y\nCOMERCIO $1,603.94 $2,138.59\n127.- JARDINES DE EVENTOS $2,138.59 $3,207.90\n128.- JARDINES DE EVENTOS CON ALBERCA $2,673.24 $3,207.90\n129.- JARDINES DE NIÑOS PARTICULARES $2,138.59 $3,207.89\n130.- JOYERÍAS $ 534.65 $1,069.30\n131.- JUGUETERÍAS $ 427.72 $ 855.43\n132.- LABORATORIO DE ANÁLISIS CLÍNICOS $1,069.30 $1,603.94\n133.- LABORATORIO DENTAL $ 511.63 $1,023.26\n134.- LABORATORIOS QUÍMICOS $1,069.30 $1,603.94\n135.- LADRILLERAS Y BLOQUERAS $ 855.43 $1,603.94\n136.- LAVAMÁTICAS $ 534.65 $1,069.30\n137.- LIBRERÍAS $ 425.20 $ 855.43\n138.- LICORERÍAS $1,069.30 $3,207.88\n139.- LIMPIADURÍAS $ 534.65 $1,069.30\n140.- LLANTERAS $ 427.72 $ 855.43\n141.- LONCHERÍAS $1,069.30 $2,138.59\n142.- LOTES DE AUTOS USADOS $ 748.51 $1,497.01\n143.- MADERERÍAS $1,764.35 $3,528.68\n144.- MAQUILA DE AP. ELÉCTRICOS O\nELECTRÓNICOS $2,673.24 $3,528.68\n145.- MAQUILA DE ARTÍCULOS DE PIEL $2,673.24 $3,528.68\n146.- MAQUILA DE COMPONENTES ELECTRÓNICOS $2,673.24 $3,528.68\n147.- MAQUILA DE PRODUCTO DE LIMPIEZA $2,673.24 $3,528.68\n148.- MAQUILA DE MUEBLES $2,673.24 $3,528.68\n149.- MAQUILA DE PLÁSTICOS $2,673.24 $3,528.68\n150.- MAQUILA DE PROD. ALIMENTICIOS $2,673.24 $3,528.68\n151.- MAQUILA DE PROD. DE VIDRIO $2,673.24 $3,528.68\n152.- MAQUILA DE PROD. METÁLICOS $2,673.24 $3,528.68\n153.- MAQUILA DE PRODUCTOS DE MADERA $2,673.24 $3,528.68\n154.- MAQUILA DE PRODUCTOS TEXTILES $2,673.24 $3,528.68\n155.- MAQUILAS DE PROD. DE BARRO Y\nCERÁMICA $2,673.24 $3,528.68\n156.- MAQUILAS EN GENERAL $2,673.24 $3,528.68\n157.- MAQUINADOS INDUSTRIALES $2,673.24 $3,528.68\n158.- MARMOLERÍAS $2,673.24 $3,528.68\n159.- MATERIALES PARA CONSTRUCCIÓN $2,673.24 $3,528.68\n160.- MATERIALES PÉTREOS $2,673.24 $3,528.68\n161.- MENSAJERÍA $2,673.24 $3,528.68\n162.- MENUDERÍA $1,069.30 $1,603.94\n163.- MERCADOS $1,764.35 $3,528.68\n164.- MOBILIARIO PARA ALQUILER $ 534.65 $1,069.31\n165.- MODISTAS $ 534.65 $1,069.31\n166.- MOSAICOS $ 534.65 $1,069.31\n167.- MUEBLERÍAS $1,763.68 $3,528.68\n168.- NOTARÍAS $ 534.65 $1,069.30\n169.- NUTRIÓLOGOS $ 534.65 $1,069.30\n170.- ÓPTICAS $ 534.65 $1,069.30\n171.- PALETERÍAS Y NEVERÍAS $ 641.58 $1,283.16\n172.- PANADERÍAS $ 534.65 $1,069.30\n173.- PANTEÓN $1,603.95 $2,558.13\n174.- PAPELERÍAS $ 534.65 $1,069.30\n175.- PASTELERÍAS $ 534.65 $1,069.30\n176.- PERFUMERÍAS $ 534.65 $1,069.30\n177.- PESCADERÍAS $ 641.58 $1,283.16\n178.- PINTURAS Y BARNICES $ 534.65 $1,069.30\n179.- PIZZERÍAS $ 374.26 $ 748.51\n180.- PLANTAS DE AGUA PURIFICADA $ 374.26 $ 748.51\n181.- PLOMERÍA Y ELECTRICIDAD $ 374.26 $ 748.51\n182.- PRODUCTOS LÁCTEOS $ 427.72 $ 855.43\n183.- PUERTAS Y VENTANAS $ 801.97 $1,603.95\n184.- PUESTOS DE DULCES $ 320.78 $ 644.46\n185.- PURIFICADORAS DE AGUA Y LLENADO DE\nGARRAFÓN $ 534.65 $1,069.30\n186.- RADIODIFUSORAS $ 427.72 $ 855.43\n187.- RAYOS X Y ULTRASONIDO $ 427.72 $ 855.43\n188.- RECICLADORAS $ 427.72 $ 855.43\n189- RECOLECTORAS DE BASURA $2,673.24 $3,528.68\n190.- RECONSTRUCTORA AUTOMOTRIZ $ 801.97 $1,603.94\n191.- REFACCIONARIAS $ 801.97 $1,603.94\n192.- REFACCIONES PARA APARATOS DÓMESTICOS$ 534.65 $1,069.30\n193.- REFACCIONES PARA MAQUINARIA PESADA $1,603.94 $2,673.24\n194.- REGALOS Y NOVEDADES $ 534.65 $1,069.30\n195.- RENTA DE AUTOS $1,069.31 $2,138.59\n196.- RENTA DE CASAS MÓVILES $ 374.26 $ 748.51\n197.- RENTA Y VENTA DE MAQUINARIA $ 801.97 $1,603.94\n198.- RENTA DE TUXEDOS $ 534.65 $1,069.30\n199.- RENTA, VENTA Y SERVICIO DE EQUIPO\nMÉDICO $1,023.26 $2,046.50\n200.- REPARACIÓN DE CALZADO $ 374.26 $ 748.51\n201.- REPARACIÓN Y VENTA DE LAVADORAS,\nSECADORAS Y ELECTRODOMÉSTICOS $ 374.26 $ 748.51\n202.- REPARACIÓN DE TODO TIPO EN GRAL. $ 374.26 $ 748.51\n203.- RESTAURANTES $1,069.30 $2,138.59\n204.- RESTAURANTES BAR $1,764.35 $3,528.68\n205.- RETACERÍAS $ 534.65 $1,069.30\n206.- ROSTICERÍAS $ 534.65 $1,069.30\n207.- ROTULISTAS $1,069.30 $1,603.94\n208.- SALAS DE BELLEZA $ 801.97 $1,603.94\n209.- SALONES P/FIESTAS Y ESPECTÁCULOS $1,069.30 $2,138.59\n210.- SALA DE DEGUSTACIÓN PARA LA VENTA\nDE CERVEZA ARTESANAL Y/O VINATERIA $1,764.35 $3,528.71\n211.- SASTRERÍAS $ 427.72 $ 855.43\n212.- SEGURIDAD Y PROTECCIÓN $ 427.72 $ 855.43\n213.- SERVICIO AUTOMOTRIZ $2,673.24 $3,528.68\n214.- SERV. DE INSTALACIONES ELÉCTRICAS $ 427.72 $ 855.43\n215.- SERV. DE LAVADO Y ENGRASADO $ 641.58 $1,283.16\n216.- SERV. PÚBLICO DE TRANSPORTE URBANO $1,603.94 $3,207.89\n217.- SERVICENTRO $ 641.58 $1,283.05\n218.- SERVICIO DE INSTALACIÓN Y\nMANTENIMIENTO DE ÁREAS VERDES $ 767.44 $2,046.50\n219.- SERVICIO DE LIMPIEZA $ 534.65 $1,069.30\n220.- SERVICIO DE TELÉFONO $ 534.65 $1,069.30\n221.- SERVICIOS ADMINISTRATIVOS $ 427.72 $ 855.43\n222.- SERVICIOS DE AIRE ACONDICIONADO $ 427.72 $ 855.43\n223.- SERVICIOS DE INFORMÁTICA $ 427.72 $ 855.43\n224.- SERVICIOS DE INGENIERÍA Y\nARQUITECTURA $ 748.51 $1,497.01\n225.- SERVICIOS DE PLOMERÍA $ 427.72 $ 855.43\n226.- SERVICIOS EN GENERAL $1,069.30 $1,603.94\n227.- SERVICIOS RELACIONADOS CON TRANSPORTE\nDE LOGÍSTICA $2,673.25 $3,528.68\n228.- SPA O CLÍNICA DE BELLEZA $1,603.95 $3,528.68\n229.- SUPERMERCADOS $1,764.35 $3,528.68\n230.- TALABARTERÍAS $ 374.26 $ 748.51\n231.- TALLER DE REPARACIÓN Y VENTA DE\nBICICLETAS $ 767.44 $2,046.50\n232.- TALLER DE REPARACIÓN, TV Y RADIO $ 534.65 $1,069.30\n233.- TALLER INDUSTRIAL $ 962.36 $1,924.74\n234.- TALLERES AUTOELÉCTRICOS $1,069.30 $2,138.59\n235.- TALLERES DE CARROCERÍA Y PINTURA $ 962.36 $1,756.41\n236.- TALLERES DE EQUIPO DE OFICINA $ 534.65 $1,069.30\n237.- TALLERES DE MOFLES Y RADIADORES $ 855.43 $1,603.94\n238.- TALLERES DE SOLDADURA $ 748.51 $1,497.01\n239.- TALLERES MECÁNICOS $ 748.51 $1,497.01\n240.- TALLERES PARA TORNEAR $ 641.58 $1,283.16\n241.- TAPICERÍAS $ 641.58 $1,283.16\n242.- TAQUERÍAS Y TORTERÍAS $1,764.35 $3,528.68\n243.- TATUAJES Y PERFORACIONES CORPORALES $ 534.65 $1,069.31\n244.- TELECOMUNICACIONES $ 427.72 $ 855.43\n245.- TELEFONÍA CELULAR $ 534.65 $1,069.30\n246.- TELEVISIÓN POR CABLE $ 534.65 $1,069.30\n247.- TERMINAL DE TRANSPORTE FORÁNEO $1,764.35 $3,528.68\n248.- TIENDAS DE ARTÍCULOS DE SEGUNDA $ 374.26 $ 748.51\n249.- TIENDAS DE ARTS. DEPORTIVOS $ 427.72 $ 855.65\n250.- TIENDAS DE ROPA Y MISCELÁNEAS $ 427.72 $ 855.43\n251.- TIENDAS DEPARTAMENTALES $2,558.13 $4,603.50\n252.- TORTILLERÍAS $ 534.65 $1,069.30\n253.- TRANSPORTISTAS $ 534.65 $1,069.30\n254.- VENTA DE ALFOMBRAS $ 534.65 $1,069.30\n255.- VENTA DE ARTÍCULOS RELIGIOSOS $ 534.65 $1,069.30\n256.- VENTA DE ARTÍCULOS Y ACCESORIOS\nPARA MASCOTAS $ 534.65 $1,069.30\n257.- VENTA DE BILLETES DE LOTERÍA,\nPRONÓSTICOS DEPORTIVOS Y OTROS\nBOLETOS DE SORTEOS $ 716.27 $1,432.55\n258.- VENTA DE DISCOS Y CASSETTES $ 534.65 $1,069.30\n259.- VENTA DE HIELO $ 534.65 $1,069.30\n260.- VENTA DE INSTRUMENTOS MUSICALES $ 511.63 $1,023.26\n261.- VENTA DE PAÑALES $ 534.65 $1,069.30\n262.- VENTA DE PRODUCTOS DE LIMPIEZA $ 534.65 $1,069.30\n263.- VENTA DE REVISTAS Y DULCERÍA $ 374.26 $ 748.51\n264.- VENTA DE TABACO Y ACCESORIOS $1,603.94 $2,138.59\n265.- VENTA DE UNIFORMES $1,069.31 $1,603.94\n266.- VETERINARIAS $ 534.65 $1,069.30\n267.- VENTA E INSTALACIÓN DE PANELES\nSOLARES $1,603.95 $2,325.26\n268.- VIDEO JUEGOS (COMERCIANTES) $ 534.65 $1,069.30\n269.- VIDEO JUEGOS (PROPIETARIOS) $ 534.65 $1,069.30\n270.- VIDEOS $ 534.65 $1,069.30\n271.- VIDRIERAS $ 534.65 $1,069.30\n272.- VINÍCOLAS $ 427.72 $ 855.43\n273.- VIVEROS $ 534.65 $1,069.30\n274.- VTA. DE ACUMULADORES $ 534.65 $1,069.30\n275.- VTA. DE EQUIPO DIVERSO $ 534.65 $1,069.30\n276.- VTA. DE MARISCOS PREPARADOS $ 801.97 $1,603.94\n277.- YONKES $ 801.97 $1,603.94\n278.- ZAPATERÍAS $ 534.65 $1,069.30\nPara aquellos comercios que poseen más de un giro, se les cobrará un\n100% para el giro principal más un 20% de cada uno de los giros adicionales.\nLos contribuyentes que se describen en el tabulador anterior, efectuarán sus pagos durante los tres primeros meses del año.\nEn lo relativo a los rangos en la tarifa respectiva del tabulador anterior, de empresas de nueva creación, la manera de aplicar los citados rangos será la siguiente:\nA partir del inicio de operaciones, según constancia de inscripción del año, se cobrará el rango máximo, si la inscripción ocurre dentro del segundo cuatrimestre del año, se cobrará la tarifa intermedia del rango mínimo y el máximo. Si dicha inscripción ocurre en el último cuatrimestre del año, la tarifa que se cobrará será la relativa al rango mínimo del giro respectivo.\nARTÍCULO 46.- ELIMINADO\n13.- DERECHOS POR SERVICIOS QUE PRESTA LA DIRECCIÓN DE GESTIÓN\nINTEGRAL DEL TERRITORIO EN MATERIA DE LIMPIA.\nARTÍCULO 47.- Los Derechos por el servicio de limpia, en domicilio particular de terrenos baldíos y otros, serán fijados en cada caso por las Autoridades Municipales, dependiendo de la ubicación y superficie del terreno, periodicidad del servicio y otros elementos que impacten en el costo del mismo.\nI. Por los servicios que presta el Departamento de Mantenimiento de Espacios Públicos, de la Sub Dirección de Obras Públicas de la Dirección de Gestión Integral del Territorio:\nA.- Poda en propiedades de particulares o de gobierno estatal o federal.\nIMPORTE\nPESOS\na).- Árbol hasta de 2m de altura..... $1,769.95\nb).- Árbol hasta de 4m de altura..... $3,539.90\nc).- Árbol mayor a 4m de altura..... $5,899.83\nB.- Desyerbe en propiedad de particulares o de gobierno estatal o federal.\nIMPORTE\nPESOS\na).- Por cada metro cuadrado de maleza......................... $11.80\nb).- Por cada tonelada retirada..... $294.99\n14.- ELIMINADO\nARTÍCULO 48.- ELIMINADO\n15.- DERECHOS POR SERVICIOS QUE PRESTA LA DIRECCIÓN DE SEGURIDAD\nCIUDADANA Y TRÁNSITO MUNICIPAL.\nARTÍCULO 49.- Los Derechos por el servicio de vigilancia policíaca, que preste el Ayuntamiento a domicilios particulares, giros comerciales o instituciones de servicio y otros que se soliciten, eventualmente se cobrará por elemento, por turno que comprenden de 8 horas el importe de $1,113.30 M.N. o el importe de $1,298.84 M.N. por servicio nocturno, o en su caso proporcional al número de horas que se brinde por el servicio.\nIMPORTE\nPESOS\nA.- Otros Servicios.\na).- Por contrato celebrado por más de\n90 días naturales, con 3 elementos o más por turno, con 3 turnos diarios, se pagará por cada elemento por turno.......... $988.98\nb).- Por guardia en el traslado de servicios funerarios que implique movimiento de tránsito vehicular para el libre acceso de este, solicitadas por empresas particulares dedicadas a prestar servicios funerarios............. entre $1,310.43 hasta $2,074.85\n1).-Por turno de 8 horas y por elemento en el traslado de servicios especiales que implique movimiento de tránsito vehicular para el libre acceso de este, solicitadas por particulares y/o empresas particulares ya sea para traslados, desfiles, recorridos, exposiciones, etc............... entre $1,310.43 hasta $2,074.85\n2).-Por turno de 8 horas y por unidad en el traslado o escolta que implique movimiento de tránsito vehicular para el libre acceso de este, solicitadas por particulares o empresas particulares......... entre $1,583.44 hasta $2,730.06\nc).- Los derechos por alimentación de detenidos a cargo de otras autoridades.................... $193.90 POR DÍA,\nPOR DETENIDO\nd).- Los derechos por traslado de detenidos a cargo de otras autoridades:\n1).- Dentro de la ciudad o poblado donde se ubiquen los separos municipales..................... $1,270.43\nPOR DETENIDO\n2).- Por traslado que implique cambio de jurisdicción, se adicionará.. $16.16 POR KM\nRECORRIDO\ne).- Por entrega de notificaciones y diligencias judiciales, administrativas o cualquier tipo de investigación girada por oficio, por Juzgado, Ministerio Publico y otras autoridades........$1,113.30 POR\nELEMENTO REQUERIDO\nPARA EJECUTAR LA\nNOTIFICACION O\nDILIGENCIA\nf).- Por localización de personas y domicilios, giradas por oficio de\nJuzgados, Ministerio Público y otras autoridades................ $646.33\ng).- Los propietarios de giros comerciales destinados a la instalación de alarmas comerciales e industriales deberán obtener autorización escrita de la\nDirección de Seguridad Ciudadana y\nTránsito Municipal debiendo pagar anualmente por cada sistema instalado............... $1,292.67\nh).- Los propietarios de giros comerciales destinados a la instalación de alarmas para casa habitación deberán obtener autorización escrita de la\nDirección de Seguridad Ciudadana y\nTránsito Municipal debiendo pagar anualmente por cada sistema instalado........................ $646.33\ni).- Servicio de protección de particulares se deberá pagar por cada elemento por mes, y por turno de 8 horas, 6 días de la semana.. $38,799.65\nj).- Los propietarios de giros comerciales destinados a la vigilancia y/o seguridad privada, comercial o industrial deberán obtener registro y anuencia escrita de la Dirección de\nSeguridad Ciudadana y Tránsito\nMunicipal debiendo pagar anualmente....................... $16,380.38\nk).- Por capacitación básica de competencias de la función de vigilancia, prevención y seguridad privada.......................... desde $546.01 hasta $6,552.15 por persona\nARTÍCULO 50.- Por instalación y mantenimiento de cámaras de videovigilancia, monitoreo de 24 horas 7 días de la semana y dispositivos botones de pánico, se pagará anual por cada unidad:\na).-Instalación de Cámara uso regular.... $3,918.19 - $7,634.35\nb).-Instalación de Cámara tipo PTZ...... $11,806.97 - $18,313.26\nc).-Instalación de Dispositivo botón de pánico $4,149.70 – $6,293.34\nd).-Mantenimiento Dispositivo Botón de pánico..... $570.58 mensual\ne).-Mantenimiento de cámaras....... de $570.58 - $1,141.17 mensual\nARTÍCULO 51.- Por unidad que circulen con exceso de peso, dentro de la zona centro se pagará:\nA.- Permiso para circular con exceso de peso dentro de la Zona\nCentro, por unidad.\na).-Por día............................... de $273.01 hasta $436.81\nb).-Por 1 mes............................. de $2,730.06 hasta $3,057.67\nc).-Por 3 meses........................... de $4,914.11 hasta $6,552.15\nB.- Permiso de exceso de dimensiones dentro de la\nCiudad (maquinaria pesada y casas rodantes)\nPor unidad.\na).-Por una maniobra...................... de $1,638.04 hasta $2,184.05\nb).-Por un mes........................... de $6,006.14 hasta $7,644.18\n16.- DERECHOS POR RECEPCIÓN, ANÁLISIS Y REVISIÓN DE SOLICITUDES, DE\nEMISIÓN DE DOCUMENTOS, PERMISOS Y CERTIFICADOS REFERENTES A\nINSTALACIONES PARA LA VENTA, ALMACENAJE O CONSUMO DE BEBIDAS\nCON GRADUACIÓN ALCOHÓLICA, CAMBIO DE GIRO, CAMBIO DE\nPERMISIONARIO, CAMBIO DE DOMICILIO, CAMBIO DE DENOMINACIÓN\nCOMERCIAL Y TRAMITACIÓN RELATIVA A LA OPERACIÓN DE GIROS DE\nCERVEZA, VINOS, LICORES, ALCOHOLES Y SIMILARES\nARTÍCULO 52.- Por la recepción, análisis y revisión de solicitudes de permisos nuevos para la operación de establecimientos con venta, almacenaje o consumo de bebidas alcohólicas o alcohol, cambio de giro, cambio de permisionario, cambio de nombre o denominación y cambio de domicilio, así como la emisión de permisos y certificados que por dichos conceptos y similares extienda el H. Ayuntamiento, estarán sujetos a la siguiente tarifa:\nA.- Pago de recepción, análisis y evaluación de solicitudes de permisos nuevos; traspasos, ampliación de servicios adicionales; cambio de domicilio; cambios de giro; cambio de permisionario; y cambios de denominación de establecimientos con permiso, para la venta de bebidas con graduación alcohólica o alcohol............... $3,207.89\nB.- Dictamen de No Inconveniencia para autorización de permisos nuevos, cambios de permisionario, cambio de giro y cambio de almacenaje de bebidas con graduación alcohólica y alcohol, el cual sólo se pagará en caso de que éste sea favorable al solicitante, de acuerdo a la siguiente:\nPESOS\na).- Abarrotes........................ $5,346.49\nb).- Mercados y Tiendas de\nAutoservicios.................... $10,692.97\nc).- Billares......................... $13,900.86\nd).- Loncherías, Fondas y Coctelerías. $9,623.67\ne).- Restaurante...................... $10,692.97\nf).- Agencias, Sub-agencias y\nDepósitos........................ $23,524.54\ng).- Expendio de Cerveza y Vinos...... $23,524.54\nh).- Restaurante-Bar.................. $21,385.93\ni).- Bar Turístico.................... $26,732.42\nj).- Bar Terraza...................... $32,078.91\nk).- Licorerías....................... $23,524.54\nl).- Café Cantante y Cabaret.......... $32,078.91\nm).- Almacén o Bodegas................ $19,247.34\nn).- Supermercado..................... $23,524.54 ñ).- Hotel............................ $24,593.83\no).- Discoteca........................ $24,593.83\np).- Centro de Espectáculos........... $9,623.67\nq).- Otros........................... $5,346.49 a $16,039.46\nC.- Expedición de permisos eventuales para operar la venta y/o consumo público de bebidas con graduación alcohólica.\na).- Espectáculos públicos y masivos: presentación de artistas, cantantes, funciones de box, lucha libre, obras de teatro, cine, eventos deportivos, eventos culturales, bailes, exposiciones, ferias, festivales, verbenas, congresos, exhibiciones de moda, carreras de carros y/o motos, casteo y/o peleas de gallos, otros, con fines de lucro y asistencia de 1000 o más personas $8,506.23\nb).- Espectáculos públicos y masivos: presentación de artistas, cantantes, funciones de box, lucha libre, obras de teatro, cine, eventos deportivos, eventos culturales, bailes, exposiciones, ferias, festivales, verbenas, congresos, exhibiciones de moda, carreras de carros y/o motos, casteo y/o peleas de gallos, otros, con fines de lucro y asistencia de 999 o menos personas......................... $5,670.82\nc).- Espectáculos públicos y masivos: presentación de artistas, cantantes, funciones de box, lucha libre, obras de teatro, cine, eventos deportivos, eventos culturales, bailes, exposiciones, ferias, festivales, verbenas, congresos, exhibiciones de moda, carreras de carros y/o motos, casteo y/o peleas de gallos, otros, sin fines de lucro y asistencia de 1000 o más personas $5,670.82\nd).- Espectáculos públicos y masivos: presentación de artistas, cantantes, funciones de box, lucha libre, obras de teatro, cine, eventos deportivos, eventos culturales, bailes, exposiciones, ferias, festivales, verbenas, congresos, exhibiciones de moda, carreras de carros y/o motos, casteo y/o peleas de gallos, otros, sin fines de lucro y asistencia de 999 o menos personas......................... $ 3,816.90\ne).- Eventos particulares y sociales: bodas, quinceañeras y similares; sin cobro, admisión y/o cuotas de recuperación con venta de bebidas alcohólicas...................... $3,000.00\nf).- Degustación por establecimiento comercial........................ $4,253.12\ng).- Espectáculos públicos y masivos, solicitados por asociaciones civiles, escuelas, asociaciones religiosas y dependencias de gobierno......................... $2,835.41\nD.- Expedición de permisos eventuales con solicitud de cierre parcial o total de calle, uso de la vía pública con venta y/o consumo público de bebidas alcohólicas.\na).- Espectáculos públicos y masivos: presentación de artistas, cantantes, funciones de box, lucha libre, obras de teatro, cine, eventos deportivos, eventos culturales, bailes, exposiciones, ferias, festivales, verbenas, congresos, exhibiciones de moda, carreras de carros y/o motos, casteo y/o peleas de gallos, otros, con fines de lucro y asistencia de 1000 o más personas $14,177.06\nb).- Espectáculos públicos y masivos: presentación de artistas, cantantes, funciones de box, lucha libre, obras de teatro, cine, eventos deportivos, eventos culturales, bailes, exposiciones, ferias, festivales, verbenas, congresos, exhibiciones de moda, carreras de carros y/o motos, casteo y/o peleas de gallos, otros, con fines de lucro y asistencia de 999 o menos personas......................... $8,506.23\nc).- Espectáculos públicos y masivos: presentación de artistas, cantantes, funciones de box, lucha libre, obras de teatro, cine, eventos deportivos, eventos culturales, bailes, exposiciones, ferias, festivales, verbenas, congresos, exhibiciones de moda, carreras de carros y/o motos, casteo y/o peleas de gallos, otros, sin fines de lucro y asistencia de 1000 o más personas $8,506.23\nd).- Espectáculos públicos y masivos: presentación de artistas, cantantes, funciones de box, lucha libre, obras de teatro, cine, eventos deportivos, eventos culturales, bailes, exposiciones, ferias, festivales, verbenas, congresos, exhibiciones de moda, carreras de carros y/o motos, casteo y/o peleas de gallos, otros, sin fines de lucro y asistencia de 999 o menos personas......................... $5,670.82\ne).- Espectáculos públicos y masivos, solicitados por asociaciones civiles y/o instituciones de gobierno......................... $ 4,253.12 vía pública con venta y/o consumo de alcohol el causante deberá acreditar la forma en que cumplirá con su obligación de disponer de los residuos sólidos urbanos generados al final del evento o espectáculo. Lo anterior podrá realizarse exhibiendo el comprobante de pago de derechos. O en caso de que el contribuyente decida efectuar la recolección por su cuenta o mediante un tercero, deberá garantizar el cumplimiento de dicha obligación con depósito en efectivo del monto fijado por la dirección de servicios públicos municipales, ante la Recaudación Municipal o fianza de compañía autorizada.\nE.- En general por la recepción y expedición de documentos de espectáculos y eventos urgentes (en menos de 72 horas) se cobrará el doble de la tarifa asignada.\nTratándose de eventos organizados por partidos políticos, dependencias oficiales y organismos no gubernamentales con registro ante institución oficial, que tengan por objeto allegarse de recursos para el cumplimiento de sus fines, no se causará este derecho. Para efectos de este supuesto, al menos 5 días hábiles previos a su celebración se deberá presentar ante la autoridad municipal los evento.\n1.- Acta constitutiva o instrumento de creación de la promueve el evento.\n2.- Copia del contrato o contratos celebrados para su sea propio de la institución u organismo que lo organiza, se deberá incluir copia del contrato de arrendamiento.\n3.- Declaratoria firmada por el titular del área financiera del el cumplimiento de sus fines, cuyos recursos están obligados a acumular y acreditar sus ingresos. La autoridad municipal informará sobre el particular al Instituto Estatal Electoral.\nF.- Derechos por concepto de autorización de horario extraordinario:\nTARIFA IMPORTE\nPESOS\na).- ABARROTES........................ NO AUTORIZADO\nb).- MERCADO Y TIENDA DE AUTOSERVICIO. NO AUTORIZADO\nc).- BILLARES......................... $2,181.09\nd).- LONCHERÍAS, FONDAS Y COCTELERÍAS. NO AUTORIZADO\ne).- RESTAURANT....................... $1,090.54\nf).- AGENCIAS, SUB-AGENCIA Y DEPÓSITO. $1,090.54\ng).- EXPENDIO DE CERVEZA Y VINOS...... $1,187.52\nh).- RESTAURANT BAR................... $2,181.09\ni).- BAR TURÍSTICO.................... $3,271.63\nj).- BAR TERRAZA...................... $3,271.63\nk).- LICORERÍAS....................... $1,385.44\nl).- CAFÉ CANTANTE Y CABARET.......... $3,053.52\nm).- ALMACÉN O BODEGAS................ $2,276.10\nn).- SUPERMERCADO..................... NO AUTORIZADO\nñ).- DISCOTECA........................ $3,271.63\no).- CENTRO DE ESPECTÁCULOS........... $3,271.63\nG.- Por expedición de permisos nuevos, pagarán los siguientes derechos, disminuyendo de éstos el pago realizado por el\nDictamen de No Inconveniencia:\nTARIFA IMPORTE\nPESOS\na).- ABARROTES........................ $191,646.14\nb).- MERCADOS......................... $269,927.26\nc).- TIENDA DE AUTOSERVICIO........... $325,203.75\nd).- BILLARES......................... $328,692.62\ne).- LONCHERÍAS, FONDAS Y COCTELERÍAS. $238,091.48\nf).- RESTAURANT....................... $328,692.62\ng).- AGENCIAS, SUB-AGENCIAS Y\nDEPÓSITOS........................ $369,141.51\nh).- EXPENDIO DE CERVEZA Y VINOS...... $493,431.88\ni).- RESTAURANT BAR................... $596,353.03\nj).- BAR TURÍSTICO.................... $693,386.73\nk).- BAR TERRAZA...................... $803,503.65\nl).- LICORERÍAS....................... $430,699.46\nm).- CAFÉ CANTANTE Y CABARET.......... $886,690.97\nn).- ALMACÉN O BODEGAS................ $407,343.23\nñ).- SUPERMERCADO..................... $615,323.67\no).- HOTEL Y MOTEL.................... $596,353.03\np).- DISCOTECA........................ $658,825.29\nq).- CENTRO DE ESPECTÁCULOS........... $394,582.75\nr).- BOUTIQUE DE CERVEZA ARTESANAL\nEN ENVASE CERRADO............... $43,549.39\ns).- SALA DE DEGUSTACIÓN PARA LA VENTA\nEXCLUSIVA DE CERVEZA ARTESANAL EN\nENVASE ABIERTO Y/O CERRADO....... $48,981.44\nt).- MICRO CERVECERÍA ARTESANAL....... $29,426.06\nu).- RESTAURANTE CON VENTA PARA CONSUMO\nDE VINOS DE MESA DE PRODUCCIÓN\nNACIONAL........................ $0\nv).- SALÓN DE EVENTOS................. $238,016.77\nw).- BANQUETES....................... $380,324.95\nH.- Por la expedición de autorización de cambios o modificación al permiso pagarán los siguientes derechos, disminuyéndose de éstos el pago realizado por el Dictamen de No Inconveniencia:\na).- Cambio de permisionario, se cobrará.......................... 20% sobre el valor del permiso nuevo\nb).- Cambio de domicilio, se cobrará.. 15% sobre el valor del permiso nuevo\nc).- Cambio de giro comercial de manera ascendente, se cobrará........... Diferencia entre las\nTarifas de los\nPermisos nuevos de los Giros que se modifican.\nd).- Cambio de giro comercial de manera descendente, se cobrará.......... 10% sobre el valor del permiso nuevo del giro que prevalece\ne).- Cambio de nombre comercial, se cobrará.......................... 3% sobre el valor del permiso nuevo, sin que proceda el\nDictamen de No\nInconveniencia.\nI.- SERVICIOS ADICIONALES\na).- Música grabada................... $23,524.54\nb).- Música en vivo................... $29,405.66\nc).- Baile............................ $29,405.66\nd).- Espectáculo Artístico........... $35,286.80\ne).- Mesas de billar (hasta 5 mesas).. $23,524.54\nJ.- Por revalidación de permisos para la venta o almacenaje de bebidas con graduación alcohólica.\nTARIFA\nIMPORTE\nPESOS\na).- ABARROTES........................ $4,602.79\nb).- LONCHERÍAS, FONDAS Y COCTELERÍAS. $6,098.69\nc).- SALÓN DE EVENTOS................ $6,098.69\nd).- MERCADO.......................... $8,515.15\ne).- RESTAURANTE...................... $10,126.13\nf).- BANQUETES........................ $10,126.13\ng).- ALMACÉN O BODEGAS................ $11,506.96\nh).- BILLARES......................... $12,082.32\ni).- AGENCIAS, SUB-AGENCIAS Y\nDEPÓSITOS........................ $12,082.32\nj).- EXPENDIO DE CERVEZA Y VINOS...... $12,082.32\nk).- LICORERÍAS....................... $12,082.32\nl).- HOTEL Y MOTEL.................... $13,402.20\nm).- TIENDA DE AUTOSERVICIO........... $14,843.98\nn).- RESTAURANT BAR................... $16,358.14\nñ).- DISCOTECA........................ $17,720.73\no).- BAR TURÍSTICO.................... $17,720.73\np).- BAR TERRAZA...................... $17,720.73\nq).- SUPERMERCADO..................... $17,720.73\nr).- CAFÉ CANTANTE Y CABARET.......... $21,810.86\ns).- CENTRO DE ESPECTÁCULOS........... $21,810.86\nt).- BOUTIQUE DE CERVEZA ARTESANAL\nENVASE CERRADO................... $5,218.56\nu).- SALA DE DEGUSTACIÓN PARA LA VENTA\nEXCLUSIVA DE CERVEZA ARTESANAL EN\nENVASE ABIERTO Y/O CERRADO....... $5,218.56\nv).- MICRO CERVECERÍA ARTESANAL....... $5,218.56\nw).- RESTAURANTE CON VENTA PARA CONSUMO\nDE VINOS DE MESA DE PRODUCCIÓN\nNACIONAL......................... $0.00\nX).- SERVICIOS ADICIONALES POR CADA\nSERVICIO SOLICITADO.............. $1,744.87\nK.- Por trámite extemporáneo de revalidación de permiso, estarán sujetos a la siguiente tarifa:\na).- BOUTIQUE DE CERVEZA ARTESANAL\nENVASE CERRADO................... $534.63\nb).- SALA DE DEGUSTACIÓN PARA LA VENTA\nEXCLUSIVA DE CERVEZA ARTESANAL EN\nENVASE ABIERTO Y/O CERRADO....... $534.63\nc).- MICRO CERVECERÍA ARTESANAL....... $534.63\nd).- SERVICIOS ADICIONALES POR CADA\nSERVICIO SOLICITADO.............. $534.63\ne).- ABARROTES........................ $1,069.27\nf).- LONCHERÍAS, FONDAS Y\nCOCTELERÍAS...................... $1,069.27\ng).- SALÓN DE EVENTOS................ $1,069.27\nh).- MERCADO.......................... $1,069.27\ni).- RESTAURANTE...................... $1,603.90\nj).- BANQUETES...................... $1,603.90\nk).- ALMACÉN O BODEGAS................ $1,603.90\nl).- BILLARES......................... $1,603.90\nm).- AGENCIAS, SUB-AGENCIAS Y\nDEPÓSITOS........................ $1,603.90\nn).- EXPENDIO DE CERVEZA Y VINO....... $1,603.90\nñ).- LICORERÍAS....................... $1,603.90\no).- HOTEL Y MOTEL.................... $2,138.53\np).- TIENDA DE AUTOSERVICIO........... $2,138.53\nq).- RESTAURANT BAR................... $2,138.53\nr).- DISCOTECA........................ $2,673.17\ns).- BAR TURÍSTICO.................... $2,673.17\nt).- BAR TERRAZA...................... $2,673.17\nu).- SUPERMERCADO..................... $2,673.17\nv).- CAFÉ CANTANTE Y CABARET.......... $2,673.17\nw).- CENTRO DE ESPECTÁCULOS........... $2,673.17\nL.- Por no contar a la vista con la revalidación correspondiente....... $1,069.30 A\n$5,346.49\nM.- Reposición por pérdida o extravío de permisos........................... $2,138.59\nN.- Por inspección, análisis y emisión de dictamen de distancia para factibilidad con venta, almacenaje o consumo de bebidas alcohólicas...\na).- Zona Urbana....................... $1,092.03\nb).- Zona rural...................... $1,638.04\nÑ.- Por expedición de autorización de permiso temporal para la venta de bebidas con graduación alcohólica, con vigencia de 60 días naturales se cobrará:\nA).- Por recepción de análisis y evaluación de solicitud de permiso temporal......................... $1,417.71\nB).- Por expedición de autorización de permiso temporal:\na).-Abarrotes. $5,013.91\nb).-Mercados. $8,902.26\nc).-Tienda de autoservicio...... $14,204.77\nd).-Billares..................... $11,562.03\ne).-Loncherías, fondas y coctelerías. $5,836.06\nf).-Restaurant.................. $10,711.55\ng).-Agencias, sub-agencias y depósitos........................ $13,388.92\nh).-Expendio de cerveza y vinos.. $13,388.92\ni).-Restaurant bar............... $23,023.07\nj).-Bar turístico................ $22,306.81\nk).-Bar terraza.................. $22,306.81\nl).-Licorerías................... $11,562.03\nm).-Café cantante y cabaret...... $26,706.77\nn).-Almacén o bodegas............ $11,605.05 ñ).-Supermercado................. $17,804.51\no).-Hotel y motel................ $23,023.07\np).-Discoteca.................... $16,957.63\nq).-Centro de espectáculos....... $26,706.77\nr).- Boutique de cerveza artesanal.... $5,320.89\ns).- Sala de degustación para la venta exclusiva de cerveza artesanal.... $5,320.89\nt).- Micro cervecería artesanal........ $5,320.89\nu).- Restaurante con venta para consumo de vinos de mesa de producción nacional.......................... $0.00\nv).- Salón de eventos.............. $5,836.06\nw).- Banquetes.................... $9,690.08\nx).- Servicios adicionales por cada servicio solicitado.............. $1,699.73 permiso temporal. por el mismo solicitante y exclusivamente para el mismo domicilio, hasta por cinco veces más, al término de la vigencia deberá ser autorizado por el Cabildo el permiso permanente. dichos permisos permanentes, será la Secretaría del Ayuntamiento, quien determine si siguen renovándose los permisos temporales. del Ayuntamiento.\n17.- DERECHOS POR SERVICIOS QUE PRESTA EL DEPARTAMENTO DE SERVICIOS\nMÉDICOS MUNICIPALES\nARTÍCULO 53.- Los servicios proporcionados por el Departamento de\nServicios Médicos Municipales, se pagarán de acuerdo a la siguiente:\nPESOS\nA.- Expedición de Certificados\nPrenupciales....................... $427.72\nB.- Consultas.......................... $106.93\nC.- Expedición de certificado de:\na).- Esencia y/o Aliento Alcohólico... $427.72\nb).- Estado de Ebriedad positivo o bajo influjo de enervantes............ $855.43\nD.- Revisión médica mensual............ $213.86\nE.- Expedición de tarjeta de control de salud.............................. $534.65\n18.- DERECHOS POR SERVICIOS QUE PRESTA LA COORDINACIÓN MUNICIPAL DE\nPROTECCIÓN CIVIL Y BOMBEROS\nARTÍCULO 54.- Los servicios que presta la Coordinación Municipal de\nProtección Civil y Bomberos a giros comerciales, industriales, de a la siguiente:\nPESOS\nA.- FACTIBILIDAD DE PROYECTO DE CONSTRUCCIÓN (POR METRO CUADRADO)\nCONSTRUCCIÓN REGULARIZACIÓN\na).- Casa/Departamento en renta y multi habitacional........... $2.14 $3.22\nb).- Comercial..................... $5.36 $6.43\nc).- Industrial hasta 2,500.00 m².. $5.36 $6.43\nd).- Mayor de 2,500.00 m².......... $7.50 $8.57\ne).- Barda, fachada y remodelaciones................ $2.14 $3.22\nf).- Las Microempresas que ingresen por trámite S.A.R.E. (Sistema de Apertura Rápida de Empresas) de hasta 100.00 m².. $534.65\nB.- CERTIFICADO DE MEDIDAS DE SEGURIDAD MEDIANTE INSPECCIÓN Y\nREGULARIZACIÓN DE DISPOSITIVOS DE SEGURIDAD EN EDIFICIOS,\nCOMERCIOS E INDUSTRIAS EXISTENTES, ASI COMO PUESTOS SEMIFIJOS\nDE OFICIO O A PETICIÓN DE PARTE:\na).- Comercio en pequeño, hasta 25.00 m² de superficie.\n1).- Puestos de dulces, puestos de segunda, Barberías, Abarrotes pequeños sin venta de cerveza, Ambulantes, Bolerías Cerrajerías, Purificadora de agua, food trucks.......................... $213.86 a $855.43\nb).- Despachos de profesionales y giros de servicio...................... $868.74\nc).- Loncherías, Panaderías, Lavanderías, Tiendas de Ropa, Miscelánea, Farmacias, Papelerías, Librerías, Templos Religiosos, Taquerías, Cafés, Carnicerías sin venta de cerveza, Centros de copiado, Botánicas, Terminales de autobuses........................ $1,069.30\nd).- Billares, Expendios, Autoservicios, Bares, Restaurant\nBar, Loncherías, Bar Café\nCantante, Centro de Espectáculos y\nDiscotecas, todos con venta de bebidas de graduación alcohólica. $2,138.59 a $3,207.89\ne).- Taller, Servicio de grúas, llantera........................ $1,283.16 a $1,744.89\nf).- Yonkes, Recicladoras, Desmanteladoras, Casa de Empeño, Recolectoras de Basura........... $5,346.49 a $10,692.97\ng).- Restaurante, Mercado, Supermercado, Bodegas de\nDistribución, Salón de Rentas, Salas Cinematógrafas y Teatros, depósitos y Sub agencias, eventos al aire libre, Telefónicas, Ferreterías y Refaccionarias..... $2,138.59 a $3,207.89\nh).- Tiendas departamentales, gimnasios e instalaciones deportivas....................... $3,207.89\ni).- Moteles:\n1).- Hasta 10 habitaciones........... $1,283.16 a $1,603.94\n2).- De 11 a 20 habitaciones......... $2,138.59 a $2,459.39\n3).- De 21 habitaciones en adelante.. $2,673.24 a $4,277.18\nj).- Hoteles:\n1).- Hasta 30 habitaciones........... $2,673.24 a $3,742.53\n2).- De 31 habitaciones en adelante.. $4,277.18 a $5,346.49\nk).- Edificios Educativos particulares:\n1).- Hasta 10 aulas................. $2,138.59 a $3,207.89\n2).- De 11 aulas en adelante......... $3,314.82 a $4,277.18\n3).- Guarderías...................... $1,603.94 a $2,138.59\nl).- Giros de alto riesgo:\n1).- Industrias generadoras de electricidad, distribuidoras de gases comprimidos y criogénicos, depósitos y bodegas de gases o líquidos combustibles y lubricantes, polvorines, gasolineras y demás de alto riesgo (aperturas).............. $16,119.61 a $19,247.34\n2).- Industrias generadoras de energía eléctrica, distribuidoras de gases criogénicos, comprimidos y gases o líquidos combustibles, lubricantes, depósitos bodegas de gases o líquidos combustibles, polvorines, gasolineras, y demás de alto riesgo (revalidación)... $4,277.19 a $7,485.08\n3).- Establecimiento con polvorines por temporada, previa acreditación y autorización de permiso por parte de la\n(SEDENA) $10,692.97 a $19,247.34\n4). Uso y manejo de juegos pirotécnicos en establecimientos temporales, así como la quema de castillos de fuegos artificiales en días festivos o fechas especiales... $2,673.24 a $7,485.08\n5). Establecimientos con venta de juegos pirotécnicos (temporal o no) que estén permitidos por la ley en giros comerciales, abarrotes, autoservicios, mercados, etc................... $2,138.59 a $4,277.18\n6). Otras actividades pirotécnicas. $2,138.59 a $4,277.18\n7). Vehículos de transporte de materiales peligrosos (válido por dos meses)...................... $1,820.22\n8). Venta y almacenamiento de arbolitos de navidad........... $1,603.94 a $3,207.89\n9).- Centros de Apuestas, Apuestas\nRemotas, Salas de Sorteos de\nNúmeros y/o Casinos, Dictamen de\nOperación....................... $21,385.93\nm).- Otros giros no especificados..... $1,069.30 a $2,138.59\nn).- Giros mixtos, para todos aquellos comercios que poseen más de un giro, se les cobrara un 100% para el giro principal, más un 20% de cada uno de los giros adicionales......................\no).- Los propietarios de giros comerciales destinados a la instalación de alarmas comerciales e industriales deberán obtener autorización escrita de la\nCoordinación Municipal de\nProtección Civil y Bomberos debiendo pagar por cada sistema instalado........................ $1,069.30 a $2,138.59\np).- Los propietarios de giros comerciales destinados a la instalación de alarmas para casa habitación deberán obtener autorización escrita de la\nCoordinación Municipal de\nProtección Civil y Bomberos debiendo pagar por cada sistema instalado........................ $534.65 a $1,069.30\nq).- Comercio al por menor de carne............................ $1,069.30 a $2,138.59\nr).- Farmacias y Autoservicios........ $2,138.59 a $3,207.81\ns).- Jardín de eventos................ $2,138.59 a $3,207.81\nt).- Jardín de eventos con alberca.... $2,138.59 a $3,207.81\nu).- Venta de tabaco y accesorios... $1,598.77 a $2,138.54\nv).- Venta de Uniformes............... $1,069.30 a $2,138.54\nw).- Panteón.......................... $1,603.95 a $2,673.25\nx).- Colchonera....................... $1,069.22 a $2,138.59\ny).- Suministros dentales............. $801.97 a $1,069.22\nz).- Establo.......................... $2,138.59 a $3,528.68 aa).- Institución financiera........... $1,069.22 a $2,138.59 bb).- Industria generadora de electricidad..................... $2,673.25 a $3,528.68 cc).- Venta e instalación de paneles solares......................... $1,603.95 a $2,673.25 dd).- Puertas y ventanas............... $801.97 a $1,603.95 ee).- Renta de vehículos.............. $1,603.95 a $3,528.68 ff).- Spa o clínicas de belleza........ $1,603.95 a $3,528.68 gg).- Servicios relacionados con transportes de logística......... $2,673.25 a $3,528.68 hh).- Agencia de motocicletas......... $1,764.35 a $3,528.68 ii).- Colectivos...................... $1,069.31 a $3,525.55 jj).- Colocación de pisos............. $1,069.31 a $2,138.59 kk).- Consultorio de especialidades.... $534.65 a $1,069.31 ll).- Depósito dental................. $534.65 a $1,069.31 mm).- Diseño y decoración de interiores $1,069.31 a $2,138.59 nn).- Laboratorio dental.............. $534.65 a $1,069.31 oo).- Renta, venta y servicio de equipo médico........................... $1,069.31 a $2,138.59 pp).- Servicio de instalación y mantenimiento de áreas verdes.. $801.97 a $2,138.59 qq).- Venta de alfombras.............. $534.65 a $1,069.31 rr).- Venta de artículos religiosos... $534.65 a $1,069.31 ss).- Venta de artículos y accesorios para mascota..................... $534.65 a $1,069.31 tt).- Venta de billetes de lotería, pronósticos deportivos y otros boletos de sorteos............... $748.50 a $1,497.01 uu).- Venta de instrumentos musicales $534.65 a $1,069.31\nvv).-CERTIFICADO DE MEDIDAS DE\nSEGURIDAD, MEDIANTE REVISIÓN DE\nEDIFICIOS INDUSTRIALES:\n1).- Micro industria: de 1 a 25 empleados....................... $1,283.16 a $2,138.59\n2).- Pequeña industria: de 26 a 100 empleados....................... $2,673.24 a $3,742.53\n3).- Industria mediana: de 101 a 250 empleados....................... $4,277.18 a $5,346.49\n4).- Macro industria: de 251 empleados en adelante........... $6,950.43 a $8,019.73\nww).- CERTIFICADO DE MEDIDAS DE\nSEGURIDAD, MEDIANTE REVISIÓN DE\nGIROS COMERCIALES PARA OBTENCIÓN\nDE AUTORIZACIÓN PARA LA VENTA DE\nBEBIDAS ALCOHÓLICAS:\n1).- Abarrotes, licorerías, sub agencia, expendio, billares, autoservicio.................... $5,346.49 a $7,485.08\n2).- Restaurant-bar, bar turístico.\nCafé cantante, mercado, supermercado, bodegas de distribución.................... $5,373.20 a $7,485.08\n3).- Discotecas, Bares Deportivos, tiendas departamentales, hoteles, moteles......................... $9,089.02 a $10,159.08\nC.- CERTIFICADO DE MEDIDAS DE SEGURIDAD, MEDIANTE REVISIÓN EQUIPO,\nDISPOSITIVOS Y MEDIDAS DE SEGURIDAD PARA:\n1).- Certificado de medidas de seguridad para vivienda.......... $213.86\n2).- Certificación de sistemas hidráulicos contra incendios..... $2,673.24 a $3,742.53\n3).- Certificación de medidas de seguridad para casa o departamento de renta......................... $213.86 seguridad.\nInspecciones subsecuentes, 50% (cincuenta por ciento) del importe del pago de derechos realizados en la primer inspección. (Sin perjuicio de la aplicación de las sanciones que prevé el reglamento específico, correspondientes).\nD.- CERTIFICACIÓN DE DAÑOS EN BIENES SINIESTRADOS:\nEMPRESAS E INDUSTRIAS:\nTodos los daños en general............. $10.70 POR m²\na) Casa habitacional asegurada.......... $427.72\nb) Casa o departamento en renta......... $427.72 a $1,069.30\nc) Vehículos comerciales................ $1,069.30 a $2,138.59\nd) Vehículos particulares asegurados.... $427.72 a $1,069.30\nQuedan exceptuados del pago de este derecho, aquellas casas habitación que no se encuentren aseguradas al ocurrir el siniestro.\nE.- FACTIBILIDAD DE SERVICIOS MEDIANTE ANÁLISIS DE FACTIBILIDAD EN\nLA PRESTACIÓN DE SERVICIOS DE BOMBEROS EN PROYECTOS DE\nDESARROLLOS URBANOS:\na).- Desarrollo habitacional.......... $3,742.53 a $4,811.84\nb).- Desarrollo industrial y comercial:\n1).-Hasta 5,000.00 m2 de superficie. $2,673.24 a $3,742.53\n2).-Mayor de 5,000.00 m2 de superficie....................... $4,277.18 a $6,414.44\nc).- Cambio de régimen de propiedad... $2,673.24 a 3,742.53\nF.- REVISIÓN DE LAS CONDICIONES DE SEGURIDAD EN LAS INSTALACIONES\nTEMPORALES:\na).- Circo.................. $2,138.59\nb).- Juegos mecánicos por aparato mecánico revisado................ $427.72 a $641.58\nc).- Exposiciones y kermeses.......... $641.58 a $1,069.30\nd).- Ferias.......................... $7,485.08\ne).- Bailes Populares................. $1,069.30 a $2,138.59\nf).- Eventos masivos.................. $2,138.59 a $10,692.97\ng).- Carreras de vehículos con o sin motor............................ $2,138.59 a $4,277.19\nG.- CERTIFICACIÓN DE EMPRESAS DEDICADAS A MANTENIMIENTO, RENTA Y/O\nVENTA DE EXTINTORES PORTÁTILES:\na).- Certificación de actividad comercial e instalaciones........ $1,283.17 a $2,138.59\nb).- Sello de autorización de etiquetas de extintores, por cada etiqueta $16.04\nc).- Por reposición de certificados... $121.54\nH.- SERVICIOS ESPECIALES:\na).- Revisión de proyectos de fraccionamiento..... $2,138.59 a $3,207.90\nb).- Revisión de estudios de NO asentamientos en zona de riesgos para nuevos fraccionamientos..... $2,138.59 a $3,207.90\nc).- Revisión y aprobación de programa interno de protección civil:\n1.- Comercial....................... $1,069.30 a $2,138.59\n2).-Industrial...................... $2,138.59 a $5,346.49\n3.- Giros de alto riesgo............ $2,138.59 a $5,346.49\n4).-Otros giros no especificados..... $2,138.59 a $5,346.49\nd).-Registro de asesor en\nProtección civil......... $2,717.00\ne).-Registro de instructor en Protección civil...................... $2,717.00\nf).-Registro de instructor de\nMateriales Peligrosos........ $2,717.00\ng).-Registro de empresa prestadora de servicios de sistemas y/o monitoreo contra incendios................. $2,717.00\nh).-Certificación de Unidad Interna de\nProtección civil................. $337.41\ni).-Revisión de Programa especial (Plan de Contingencias):\n1).-Comercial..................... $534.66 a $1,603.94\n2).-Industrial..................... $1,603.94 a $2,138.59\nj).-Supervisión por detonación (pago por detonación)....................... $641.58\nI).- CURSOS:\n1).- Evacuación y Resguardo grupo de 1 a 20 personas................... $6,684.51\na).- Por persona adicional....... $607.68\n2).- Primeros Auxilios grupo de 1 a 20 personas..................... $6,684.51\na).- Por persona Adicional.... $607.68\n3).-Prevención de incendios y manejo de extintores de 1 a 20 personas. $5,469.14\na).-Por persona adicional $607.68\n4).-Formación de Brigada contra incendio Industrial y/o Comercial de 1 a 20 personas... $ 7,899.87\na).-Por persona adicional.............. $607.68\n5).-Manejo de materiales peligrosos grupo de 1 a 10 personas......... $6,684.51\na).- Por persona adicional.......... $607.68\n6).- Búsqueda y Rescate grupo de 1 a\n20 personas................... $6,684.51\na).- Por persona adicional............ $607.68\n7).- Supervisión de cursos y simulacros:\na).-Se cobrará el equivalente a diez por ciento de lo establecido en el concepto de cursos impartidos, para efectos de validación de constancias.\nb).-Por supervisión de curso y/o simulacros con fuego.. $322.88\nc).-Por supervisión de simulacros de evacuación........ $322.88\nJ).- USO DE EQUIPO POR HORA:\n1).- Máquina extinguidora........... $3,742.53\n2).- Máquina de iluminación.......... $3,742.53\n3).- Máquina escala.................. $3,742.53\n4).- Pipa............................ $3,742.53\n5).- Ambulancia...................... $3,742.53\nK).- Servicios que prestan las empresas (grupos) de respuesta a emergencia:\na).-Empresa de servicios pre-hospitalarios, traslados y/o transporte de pacientes.............. $1,358.50\nLos servicios a que hace referencia esta fracción, cuando se trate lucrativos, quedaran exentos de pago, siempre y cuando se acredite y elevado a Registro Público de la Propiedad y Comercio. antecede, cuando se trate de escuelas públicas, quedarán exentas de pago, siempre y cuando sea en horas hábiles y en las instalaciones de la misma institución.\n19.- DERECHOS POR REVISIÓN Y ANÁLISIS DE DOCUMENTOS REFERENTES A LA\nINSTALACIÓN DE APARATOS ELECTROMECÁNICOS, VIDEOJUEGOS, MÁQUINAS\nEXPENDEDORAS Y DE DESTREZA\nARTÍCULO 55.- Para la apertura, cambio de domicilio, o de propietario o el incremento de aparatos electrónicos, electromecánicos, mecánicos, musicales, digitales, videojuegos deberá entregarse y analizarse la documentación necesaria, previo el pago de derechos que se causen, conforme a la tabla siguiente:\nA.- Apertura.\na).- Aparatos Electrónicos, Electromecánicos, Mecánicos, Musicales, Digitales, Videojuegos, o cualquier tecnología similar, que operen mediante la inserción de un billete, moneda, ficha, tarjeta, banda magnética o cualquier otro medio de cobro integrado a la máquina.\nIMPORTE\nPESOS\n1).- De 1 hasta 5 aparatos........... $4,277.18\n2).- De 6 aparatos en adelante....... $5,346.49\nb).- Máquinas tragamonedas por aparato.......................... $106.93 a $534.65\nc).- Centros de apuestas, apuestas remotas, salas de sorteos de números y/o casinos por establecimiento.................. $10,692,969.71\nB.- Cambio de domicilio................ $2,138.59\nC.- Revalidación, por aparato.......... $106.93 a $534.65\nD.- Incremento, por aparato.\na).- De 1 hasta 10 aparatos........... $534.65\nb).- Por los demás.................... $106.93\nLa revalidación de los documentos a que se refiere este Artículo, deberá realizarse a más tardar en el mes de marzo de cada año. revalidación anual en el plazo establecido, serán sujetas a un pago adicional del importe de $106.93 M.N. a $1,069.30 M.N. por aparato, por revalidación extemporánea.\nE.- Centros de Apuestas, Apuestas Remotas, Salas de Sorteos de\nNúmeros y/o Casinos. apuestas o sorteos, que otorguen premios en efectivo o en especie al amparo de un permiso federal otorgado por la Secretaría de\nGobernación, o una resolución judicial que haya causado estado y que se encuentre registrada y reconocida en la página oficial de la citada\nSecretaría de Gobernación, pagarán los derechos correspondientes al centro de apuestas remotas, salas de sorteos de números y/o casinos, conforme a la siguiente tabla:\n1).- Apertura de establecimiento..... $10,692,969.71\n2).- Aportación para Programas\nPreventivos para la Ludopatía, anual por establecimiento....... $53,464.84\n20.- CUOTA DE RECUPERACIÓN POR EL USO DE BAÑOS PÚBLICOS DEL PARQUE\nMIGUEL HIDALGO\nARTÍCULO 56.- La cuota de recuperación por el uso de baños públicos del Parque Miguel Hidalgo, se cobrará conforme a lo siguiente:\nCuota de recuperación por el uso de baños públicos del Parque Miguel\nHidalgo................................ $10.00 pesos\n21.- DERECHOS POR RECEPCIÓN, ANÁLISIS Y REVISIÓN DE SOLICITUDES PARA\nARTÍCULO 57.- Recepción, análisis y revisión de solicitudes para anuencia por apertura de agencias de seguridad privada.\nIMPORTE\nPESOS\nA.- Anuencia municipal................. $10,692.97\nB.- Certificado anual.................. $4,277.18\n22.- DERECHOS POR SERVICIOS QUE PRESTA LA DIRECCIÓN DE DESARROLLO\nECONÓMICO\nARTÍCULO 58.- El cobro de derechos por los servicios que presta la\nDirección de Desarrollo Económico será pagado por los usuarios, sujetándose a lo siguiente:\nI.-La emisión de pases del programa cruce ágil para usuarios de\nDirección de Desarrollo Económico, se pagará de la siguiente manera:\nA).- Costo por pase para los contribuyentes que estén adheridos al programa, que presten servicios médicos o presten servicios asociados o de apoyo a los clientes de servicios médicos............. $320.00\nB).- Costo por pase a cámaras, empresas y organismos empresariales no gubernamentales, así como instituciones públicas o asociaciones sin fines de lucro adheridos al programa, que presten servicios de turismo de negocios, o que impulsen y promuevan el desarrollo económico y empresarial en la región..................... $520.00\nC).- Costo por inscripción o renovación anual al programa de cruce ágil de usuarios de servicios médicos y turismo de negocios............... $3,500.00\n23.- CONVENIOS OTROS\nCAPÍTULO II\nOTROS DERECHOS\n24.- DERECHOS POR OTROS SERVICIOS QUE PRESTA EL AYUNTAMIENTO A TRAVÉS\nDE LAS ENTIDADES PARAMUNICIPALES\n1.- DERECHOS POR SERVICIOS QUE PRESTA LA PARAMUNICIPAL SISTEMA PARA\nEL DESARROLLO INTEGRAL DE LA FAMILIA.\nARTÍCULO 59.- Los servicios que presta la Paramunicipal Sistema para el Desarrollo Integral de la Familia, se cobrarán conforme a la siguiente:\nTARIFA IMPORTE\nPESOS\nA. Clínica\nb).- Certificado médico............. $88.00\nc).- Inyecciones intramusculares...... $28.00\nd).- Inyecciones intravenosas......... $39.00\ni).- Consulta de fisioterapia........ $105.00\nj).- Terapia de rehabilitación física.... $164.00\nk).- Consulta sanitaria............ $88.00\nl).- Tarjeta sanitaria............ $164.00\nm).- Tarjeta sanitaria por cambio de lugar de trabajo............................. $142.00\nn).- Reposición de tarjetones y/o credencial para personas con discapacidad por robo o extravío........................................ $105.00 ñ).- Cajón azul de estacionamiento para discapacidad en domicilio particular en cordón........................................ $209.00\no).- Credencial para personas con discapacidad.................................... $110.00\np).- Servicio de traslado foráneo para personas con discapacidad..........................$274.00\nq).- Servicio de traslado local para personas con discapacidad..........................$105.00\nr).- Terapia de personas con discapacidad................$88.00\nB. Psicología\na).- Consulta Psicológica público en general...........................................$132.00\nb).- Consulta Psicológica a imputados por el juzgado.....................................EXENTO\nc).- Pláticas prematrimoniales...... $262.00 POR PERSONA\nC. Atención a la niñez\na).- Inscripción a cursos y talleres culturales......... $105.00\nb).- Curso o talleres culturales..........................$105.00\nc).- Atención psicopedagógica...........................$105.00\nD. Alimenticio\na).- Consulta de Evaluación nutricional.............. $157.00\nb).- Consulta nutricional de seguimiento................$105.00\nc).- Despensa mensual atención prioritaria.............. $45.00\nd).- Despensa mensual 1000 días de vida..................$45.00\nE. Desarrollo Comunitario\na).- Inscripción a cursos y talleres de capacitación para el trabajo....................$164.00\nb).- Curso o taller de capacitación para el trabajo....................................$110.00\nF. Arrendamiento Clubes de la Alegría\na).- Público en general............ $3,604.00\nb).- Empleados DIF y Asociación Civil..... $3,058.00\nc).- Miembros Club de la Alegría........ $1,857.00\nG. Arrendamiento Estancia Infantil\na).- Arrendamiento mensual............ $12,000.00\nDIF podrá otorgar descuentos del 25% al 100% sobre el costo de los tramites o servicios que brinda, esto dependerá del grado de vulnerabilidad obtenido mediante la aplicación de un Estudio\nSocioeconómico por el área correspondiente de DIF, NO aplica para servicio Inciso E) Arrendamiento de Clubes de la Alegría e Inciso F)\nArrendamiento Estancia Infantil.\n2.- DERECHOS POR SERVICIOS QUE PRESTA EL INSTITUTO DE PROMOCIÓN DEL\nDESARROLLO URBANO.\nARTÍCULO 60.- Los servicios proporcionados por el Instituto de\nPromoción del Desarrollo Urbano, se pagarán de acuerdo a la siguiente:\nPESOS\nA.- Electrificación................ De $121.64 a $9,209.26 por metro lineal\nB.- Titulación.\na).- Por Emisión de Títulos de\nPropiedad..................... $56.27 por m²\nb).- Por trámite de titulación..... $14.06 por m2\nC.- Venta de Terreno.\na).- Fraccionamiento Piedra\nAngular. $53.46 a $1,603.94 por m²\nb).- Fraccionamiento Bicentenario.. $53.46 a $1,603.94 por m²\nc).- Fraccionamiento Las Choyas.... $53.46 a $1,603.94 por m²\nd).- Fraccionamiento El Escorial... $53.46 a $1,603.94 por m²\ne).- Fraccionamiento Cucapáh....... $53.46 a $1,603.94 por m²\nf).- Colonia Rincón Tecate......... $53.46 a $1,603.94 por m²\ng).- Fraccionamiento Lomas de Santa\nAnita......................... $53.46 a $1,603.94 por m²\nh).- Colonia Luis Echeverría Álvarez. $53.46 a $1,603.94 por m²\ni).- Fraccionamiento El Jardín..... $53.46 a $1,603.94 por m²\nj).- Fraccionamiento Las Torres.... $53.46 a $1,603.94 por m²\nk).- Fraccionamiento La Ilusión.... $53.46 a $1,603.94 por m²\nl).- Fraccionamiento Presidentes... $53.46 a $1,603.94 por m²\nm).- Fraccionamiento La Loma....... $53.46 a $1,603.94 por m²\nn).- Fraccionamiento Lomas del\nMirador....................... $53.46 a $1,603.94 por m²\no).- Fraccionamiento Los Compadres. $53.46 a $1,603.94 por m²\np).- Nuevos Fraccionamientos....... $53.46 a $1,603.94 por m²\nLos Ingresos que se produzcan por Ventas de Terrenos en Mandato, se pagarán en base al importe convenido por las partes, de acuerdo a los contratos de Mandato celebrados.\nD.- Deslindes y Trabajos Técnicos.\na).- Desde 0.01 m² hasta 160.00 m².... $1,126.27\nb).- Desde 160.01 m² hasta 250.00 m².. $1,238.14\nc).- Desde 250.01 m² hasta 350.00 m².. $1,350.69\nd).- Desde 350.01 m² hasta 500.00 m².. $1,463.24\ne).- Desde 500.01 m² hasta 600.00 m².. $1,575.81\nf).- Desde 600.01 m² hasta 700.00 m².. $1,688.36\ng).- Desde 700.01 m² hasta 800.00 m².. $1,800.93\nh).- Desde 800.01 m² hasta 900.00 m².. $1,913.48\ni).- Desde 900.01 m² hasta 1,000.00 m². $2,026.01\nj).- Desde 1,000.01 m² hasta 1,200.00 m² $2,138.60\nk).- Desde 1,200.01 m² hasta 1,400.00 m² $2,251.15\nl).- Desde 1,400.01 m² hasta 1,600.00 m² $2,363.71\nm).- Desde 1,600.01 m² hasta 1,800.00 m² $2,476.26\nn).- Desde 1,800.01 m² hasta 2,000.00 m² $2,588.83 ñ).- Desde 2,000.01 m² hasta 2,200.00 m² $2,701.39\no).- Desde 2,200.01 m² hasta 2,400.00 m² $2,813.94\np).- Desde 2,400.01 m² hasta 2,600.00 m² $2,926.50\nq).- Desde 2,600.01 m² hasta 2,800.00 m² $3,039.05\nr).- Desde 2,800.01 m² hasta 3,000.00 m² $3,151.61\ns).- Desde 3,000.01 m² hasta 3,200.00 m² $3,264.18\nt).- Desde 3,200.01 m² hasta 3,400.00 m² $3,376.74\nu).- Desde 3,400.01 m² hasta 3,600.00 m² $3,489.29\nv).- Desde 3,600.01 m² hasta 3,800.00 m² $3,601.84\nw).- Desde 3,800.01 m² hasta 4,000.00 m² $3,714.40\nx).- Desde 4,000.01 m² en adelante..... $1.13 por m²\nE.- Trabajos de subdivisión o fusión.\na).- Desde 160.01 m² hasta 250.00 m²... $1,013.01\nb).- Desde 250.01 m² hasta 350.00 m²... $1,125.58\nc).- Desde 350.01 m² hasta 500.00 m²... $1,238.14\nd).- Desde 500.01 m² hasta 600.00 m²... $1,350.69\ne).- Desde 600.01 m² hasta 700.00 m²... $1,463.24\nf).- Desde 700.01 m² hasta 800.00 m²... $1,575.81\ng).- Desde 800.01 m² hasta 900.00 m²... $1,688.36\nh).- Desde 900.01 m² hasta 1,000.00 m². $1,800.93\ni).- Desde 1,000.01 m² hasta 1,200.00 m² $1,913.48\nj).- Desde 1,200.01 m² hasta 1,400.00 m² $2,026.04\nk).- Desde 1,400.01 m² hasta 1,600.00 m² $2,138.60\nl).- Desde 1,600.01 m² hasta 1,800.00 m² $2,251.15\nm).- Desde 1,800.01 m² hasta 2,000.00 m² $2,363.71\nn).- Desde 2,000.01 m² hasta 2,200.00 m² $2,476.26 ñ).- Desde 2,200.01 m² hasta 2,400.00 m² $2,588.83\no).- Desde 2,400.01 m² hasta 2,600.00 m² $2,701.39\np).- Desde 2,600.01 m² hasta 2,800.00 m² $2,813.94\nq).- Desde 2,800.01 m² hasta 3,000.00 m² $2,926.50\nr).- Desde 3,000.01 m² hasta 3,200.00 m² $3,039.05\ns).- Desde 3,200.01 m² hasta 3,400.00 m² $3,151.61\nt).- Desde 3,400.01 m² hasta 3,600.00 m² $3,264.18\nu).- Desde 3,600.01 m² hasta 3,800.00 m² $3,370.99\nv).- Desde 3,800.01 m² hasta 4,000.00 m² $3,489.29\nw).- Desde 4,000.01 m² en adelante..... $1.13 por m²\nF.- Reintegros, recargos y gastos de ejecución.\na).- Reintegros por ingresos recibidos..................... 35% sobre el reintegro\nb).- Recargos....................... 3% mensual\nc).- Gastos de ejecución............ $225.10\nG.- Expedición de documentos.\na).- Planos impresos................ $450.24\nb).- Copias simples de planos....... $450.24\nc).- Copias de planos digitalizados. $450.24\nd).- Constancias.................... $450.24\ne).- Cesión de recibos.............. $3,603.68\nf).- Cesión de derechos............. $3,057.67\ng).- Copia simple de expediente..... $57.43 por hoja\nh).- Impresión de estados de cuenta. $56.25\ni).- Copia certificada de expediente primer hoja.................... $225.10\nj).- Copia certificada de expediente hoja adicional................. $11.24\nk).- Inspección y dictamen técnico de predios en fraccionamientos de creación del instituto....... $2,402.46\nl).- Actas circunstanciadas........ $703.35\nm).- Expedición de avalúos en fraccionamientos desarrollados por esta Paramunicipal.................. $3,344.00\nH.- Arrendamientos. que sean susceptibles de ser arrendados, se pagarán en base a cada uno de los arrendatarios.\nI.- Ejecución obra pública.\nLos contratos que celebre el INPRODEUR con terceros para la ejecución de obra pública, se cobrarán en base a lo pactado en contratos de obra celebrados.\nJ.- Mezcla asfáltica caliente\na).- Venta de mezcla asfáltica caliente....................... $3,000.00 a $3,500.00 por m3\n3.- DERECHOS POR SERVICIOS QUE PRESTA EL INSTITUTO MUNICIPAL DEL\nDEPORTE DE TECATE.\nARTÍCULO 61.- Los servicios proporcionados por el Instituto Municipal del Deporte de Tecate, se pagarán de acuerdo a la siguiente:\nPESOS\nA.- Estacionamiento por Entrada.\na).- Automóvil...................... $20.00\nB.- Cuotas de Inscripción (Centro de Iniciación Deportiva).\na).- Tae Kwon Do................... $250.00\nb).- Box............................ $250.00\nc).- Atletismo...................... $250.00\nd).- Natación....................... $250.00\ne).- Defensa personal............... $250.00\nf).- Softbol....................... $250.00\ng).- Fútbol............... $250.00\nh).- Fútbol Bandera............... $250.00\ni).- Voleibol............... $250.00\nj).- Gimnasio............... $250.00\nk).- Madres solteras................ 50% descuento\nl).- Adultos mayores................ 50% descuento\nm).- Personas con discapacidad...... exento\nn).- Pacientes referidos de otras instancias gubernamentales..... exento\nTratándose de personas con discapacidad, así como pacientes en tratamiento psicológico o por lesiones derivadas de la práctica de alguna disciplina deportiva, que lo acrediten mediante certificado médico expedido por cualquier Institución Pública de Salud, estarán enunciadas en los incisos anteriores.\nC.- Mensualidades (Centro de Iniciación Deportiva).\na).- Tae Kwon Do.................... $250.00\nb).- Box............................ $250.00\nc).- Atletismo...................... $250.00\nd).- Natación 2 días por semana..... $450.00\ne).- Natación 3 días por semana..... $550.00\nf).- Natación 5 días por semana..... $850.00\ng).- Defensa personal............... $250.00\nh).- Softbol....................... $250.00\ni).- Fútbol............... $250.00\nj).- Fútbol Bandera............... $250.00\nk).- Voleibol............... $250.00\nl).- Gimnasio............... $250.00\nm).- Madres solteras................ 50% descuento\nn).- Adultos mayores................ 50% descuento\nTratándose de personas con discapacidad, así como pacientes en de alguna disciplina deportiva, pagarán el 50% de las tarifas a que se refieren los incisos anteriores, debiendo comprobar previamente su condición, mediante certificado médico expedido por cualquier Institución Pública de Salud.\nD.- Cuotas de inscripción (curso de verano).\na).- Curso entero................... $900.00\nb).- Descuento 15% por segundo hijo. $765.00\nc).- Descuento 20% por el tercer hijo........................... $720.00\nd).- Descuento 100% por cuarto hijo. $0.00\ne).- Tarifa a grupos de 10-40....... $700.00\nf).- Madres solteras................ 50% descuento\nE.- Renta por mes (Tienda en Unidades Deportivas).\na).- Concesión tienda UDES.......... $2,800.00\nb).- Concesión tienda Gimnasio Lucio\nMercado Jáuregui............... $2,800.00\nc).- Concesión tienda Encinos....... $1,100.00\nd).- Concesión tienda Rubén Acosta.. $1,100.00\ne).- Concesión tienda Solidaridad.. $2,800.00\nf).- Concesión tienda Solidaridad\n(infantil)..................... $2,800.00\ng).- Concesión tienda Campo de Fútbol\nAmericano El Mayab............. $1,100.00\nF.- Renta Espacios Publicitarios por mes.\na).- 3 metros por lado.... $1,100.00\nG.- Renta de Muebles e Inmuebles.\na).- Renta por evento (un día) por el uso del Gimnasio Agustín Mondragón\n(capacidad máxima 600 personas)... $6,800.00\nb).- Renta por evento (un día) por el uso del Gimnasio Lucio Mercado\nJáuregui (capacidad máxima 1,000 personas)......................... $9,000.00\nc).- Renta mensual por el uso de instalaciones deportivas dentro del municipio de Tecate (incluyendo todas las disciplinas deportivas), llevando como condición un horario fijo preestablecido............... $8,000.00\nd).- Renta por evento (un día) por el uso del Campo de Fútbol Americano\nEl Mayab.......................... $9,000.00\ne).- Renta por evento (un día) por el uso del Gimnasio XX Ayuntamiento.. $9,000.00\nf).- Renta Mensual por el uso del Campo\nDeportivo Rubén Acosta, llevando las condiciones de horarios preestablecidas en el contrato.......................... $8,000.00\ng).- Descuento por trabajo en colaboración...................... 50% descuento\nh).- Condonación del pago por el uso de instalaciones deportivas dentro del municipio de Tecate para eventos de origen gubernamentales............ EXENTO\nH.- Eventos Especiales (por persona)\na).- Copa de porras:\n1) Costo de inscripción por equipo......................... $350.00\n2) Entrada general al evento...... $100.00\nb).- Medio maratón:\n1) Inscripción por persona........ $250.00\nc).- Carrera pedestre “Aniversario de\nTecate” $150.00\nd).- Carrera pedestre “Tecatrina”...... $230.00\ne).- Carreras pedestres (6) Delegacional $100.00\nf).- Otras competencias o eventos...... $100.00\nI.- Renta de Canchas para las ligas deportivas.\na) Por hora solicitada en las diferentes canchas deportivas y para cualquier disciplina, ya sea para uso de partidos, entrenamientos, u otras actividades $125.40\nJ.- Consulta:\na) Salud y Deporte..................... $220.00\nK.- Programas Deportivos:\na) Mensualidad por impartir programas o entrenamientos deportivos (20 horas de entrenamiento al mes por entrenador)......................... $2,200.00\nL.- Cobro de uso de baños:\na).-Baño de Eufrasio Santana........... $5.00\nb).-Gimnasio Lucio Mercado Jáuregui.... $5.00\nc).-Baño Campo de Fútbol Americano El\nMayab.................................. $5.00\n4.- DERECHOS POR SERVICIOS QUE PRESTA EL INSTITUTO MUNICIPAL DE LA\nJUVENTUD DE TECATE\nARTÍCULO 62.- Los Servicios que presta la Paramunicipal Instituto\nMunicipal de la Juventud de Tecate, se cobrarán conforme a la siguiente:\nPESOS\nA. Renta de espacio comercial en los eventos culturales, sociales, deportivos y conferencias que por su naturaleza se tenga que cobrar...................... $522.50\nB. Boleto por entrada de eventos culturales, sociales, deportivos y conferencias que por su naturaleza se tengan que cobrar.................. $31.35\nC. Cursos\nI.- Educación y formación (costo por sesión):\n1.- Curso de idiomas................................... $156.75\n2.- Curso de paquetería office......................... $156.75\n3.- Taller de reforzamiento escolar.................... $104.50\n4.- Lenguaje de señas...................................$156.75\n5.- Curso de Oratoria...................................$156.75\n6.- Clases Ukulele.......................................$52.25\n7.- Clases de Guitarra..................................$52.25\n8.- Asesoría Jurídica...................................$104.50\n9.- Test Vocacional.....................................$200.00\nII.- Empleo/emprendimiento (costo por sesión):\n1.- Curso de belleza................................... $163.80\n2.- Asesoramiento marca personal o de negocio, desarrollo de identidad de marca personal o de negocio............ $104.50\n3.- Asesoramiento de Marketing.......................... $109.20\nIII.- Prevención y salud (costo por sesión):\n1.- Defensa personal y acondicionamiento físico.........$163.80\n2.- Nutrición...........................................$109.20\n3.- Consulta Psicológica................................$200.00\n4.- Clases de Danza Urbana y kpop.......................$50.00\nIV.- Inclusión Social:\n1.-Curso de fotografía y edición........................$150.00\n2.-Curso de Verano........................................$150.00\n5.- DERECHOS POR SERVICIOS QUE PRESTA EL INSTITUTO MUNICIPAL DE LA\nMUJER DE TECATE.\nARTÍCULO 63.- Los servicios que presta la Paramunicipal de nombre\nInstituto Municipal de la Mujer, se pagarán conforme a la siguiente:\nPESOS\na).- Asesoría en elaboración de currículum vitae............ $109.20\nb).- Certificación de servicios con perspectiva de género... $209.00\nc).- Asesorías de emprendimiento. $109.20\nd).- Grupo de empoderamiento femenino.................... $65.52\ne).- Eventos culturales.......... $87.36\nf).- Sorteos...................... $109.20\ng).-Certificaciones, capacitaciones y talleres a empresas $2,184.05\n6.- DERECHOS POR SERVICIOS QUE PRESTA EL INSTITUTO DE PLANEACIÓN DEL\nDESARROLLO MUNICIPAL DE TECATE.\nARTÍCULO 64.- Los servicios que presta la Paramunicipal de nombre\nInstituto de Planeación del Desarrollo Municipal de Tecate, se pagarán conforme a la siguiente:\nPESOS\nA. Integración de Nuevos\nDesarrollos al Sistema de\nInformación Geográfica...... $3,742.53 POR HECTÁREA\nB. Integración de Proyectos\nUrbanos al Sistema de\nInformación Geográfica...... $0.22 POR m2\nC. Curso-Taller de Capacitación\nPresencial o Virtual......... $53.46 POR HORA\nD. Seminario Presencial o Virtual. $106.93 POR HORA\nE. Diplomado Presencial o Virtual. $133.67 POR HORA\nF. Organización de Consulta o\nAudiencia Ciudadana en Centro de Población de Tecate........ $102.52\n1).- Organización de Consulta o\nAudiencia Ciudadana en Zonas de\nNueva Colonia Hindú y Mi\nRanchito...................... $112.80 POR PERSONA\n2).- Organización de Consulta o\nAudiencia Ciudadana en Zonas de\nLuis Echeverría Álvarez y Valle de las Palmas................. $117.72 POR PERSONA\n3).- Organización de Consulta o\nAudiencia Ciudadana en Zonas de\nHéroes del Desierto y La\nRumorosa...................... $132.43 POR PERSONA\nG. Elaboración, Actualización de\nPrograma de Desarrollo Urbano\nMunicipal..................... HASTA $2,911,645.99\nH. Elaboración, Actualización de\nPrograma Sectorial de\nDesarrollo Urbano............. HASTA $2,510,039.64\nI. Elaboración o Actualización de\nProgramas Parciales de\nConservación, Mejoramiento y\nCrecimiento; Directrices\nGenerales de Desarrollo Urbano HASTA $2,008,031.72\nJ. Elaboración de Plan Maestro, Anteproyecto o Proyecto\nArquitectónico Ejecutivo...... $100.39 POR m2\nK.- Registro, revalidación y actualización en el padrón de especialistas en gestión territorial: peritos en desarrollo urbano, impacto social y peritos viales, del\nTecate:\na).- Registro o revalidación para\nPerito en desarrollo urbano o impacto social, con duración de\n1 año, cumpliendo los requisitos establecidos....... $1,845.28\nb).- Registro o revalidación para\nPerito Vial, con duración de 1 año, cumpliendo los requisitos establecidos................ $1,845.28\nc).- Registro o revalidación para\nPerito Social, con duración de\n1 año, cumpliendo los requisitos establecidos....... $1,845.28\nd).- Actualización del registro para\nPerito en Desarrollo Urbano, impacto social o para Perito\nVial, cumpliendo los requisitos establecidos.............. $820.12\nL.- Elaboración y/o evaluación de estudios de impacto territorial urbano e impacto social (Implementación):\na).- Elaboración de Estudio de Impacto\nTerritorial Urbano o Impacto Social para proyectos y/o acciones donde el interesado es alguna autoridad federal, estatal o municipal... DE $11,411.66 A $570,583.06\nb).- Por Evaluación de Estudios de\nImpacto Territorial Urbano o\nImpacto Social y Emisión de\nDictamen de Resolución; se pagará previo al inicio de los trámites, de acuerdo a lo siguiente, con validez hasta 2 revisiones:\n1).- Desarrollo de uso industrial, especial o infraestructura urbana, DENTRO del área de aplicación del Programa de\nDesarrollo Urbano de Centro de\nPoblación Vigente............. $36,905.55\n2).- Desarrollo de uso industrial, especial o infraestructura urbana, FUERA del área de aplicación del Programa de\nDesarrollo Urbano de Centro de\nPoblación Vigente............. $73,811.11\n3).- Desarrollo de comercial, servicios o equipamiento, DENTRO del área de aplicación del Programa de Desarrollo\nUrbano de Centro de Población\nVigente...................... $43,056.48\n4).- Desarrollo de comercial, servicios o equipamiento, FUERA del área de aplicación del\nPrograma de Desarrollo Urbano de Centro de Población\nVigente...................... $86,112.96\n5).- Desarrollo habitacional, residencial, mixto (mínimo un\n60% de la superficie de construcción con uso habitacional) o turístico\n(mínimo un 60% de la superficie de construcción con uso habitacional), DENTRO del área de aplicación del Programa de\nDesarrollo Urbano de Centro de\nPoblación Vigente, y HASTA\n10,000 m2 de construcción..... $18,452.78\n6).- Desarrollo habitacional, residencial, mixto (mínimo un\n60% de la superficie de construcción con uso habitacional) o turístico\n(mínimo un 60% de la superficie de construcción con uso habitacional) FUERA del área de aplicación del Programa de\nDesarrollo Urbano de Centro de\nPoblación Vigente, y HASTA\n10,000 m2 de construcción..... $37,436.54\n7).- Desarrollo habitacional, residencial, mixto (mínimo un\n60% de la superficie de construcción con uso habitacional) o turístico\n(mínimo un 60% de la superficie de construcción con uso habitacional),desarrollo de uso industrial, especial o infraestructura; desarrollo de uso comercial, servicios o equipamiento, DENTRO del área de aplicación del Programa de\nDesarrollo Urbano de Centro de\nPoblación Vigente, POR CADA\n10,000 m2 de construcción\nADICIONALES al cobro correspondiente por tipo de uso........................... $615.09\n8).- Desarrollo habitacional, residencial, mixto (mínimo un\n60% de la superficie de construcción con uso habitacional) o turístico\n(mínimo un 60% de la superficie de construcción con uso habitacional) desarrollo de uso industrial, especial o infraestructura; desarrollo de uso comercial, servicios o equipamiento, FUERA del área de aplicación del Programa de\nDesarrollo Urbano de Centro de\nPoblación Vigente, POR CADA\n10,000 m2 de construcción\nADICIONALES al cobro correspondiente por tipo de uso........................... $1,230.19\nM.- Elaboración y/o Evaluación de Estudios de Impacto\nTerritorial Urbano e Impacto Social (Densificación):\na).- Elaboración de Estudio de Impacto\nTerritorial Urbano o Impacto Social para proyectos y/o acciones donde el interesado es alguna autoridad federal, estatal o municipal... DE $11,411.66 A $570,583.06\nb).- Por Evaluación de Estudios de\nImpacto Territorial Urbano o\nImpacto Social y Emisión de\nDictamen de Resolución; se pagará previo al inicio de los trámites, de acuerdo a lo siguiente, con validez hasta 2 revisiones:\n1).- Desarrollo de uso industrial, especial o infraestructura urbana, DENTRO del área de aplicación del Programa de\nDesarrollo Urbano de Centro de\nPoblación Vigente............. $36,905.55\n2).- Desarrollo de uso industrial, especial o infraestructura urbana, FUERA del área de aplicación del Programa de\nDesarrollo Urbano de Centro de\nPoblación Vigente............. $73,811.11\n3).- Desarrollo de comercial, servicios o equipamiento, DENTRO del área de aplicación del Programa de Desarrollo\nUrbano de Centro de Población\nVigente...................... $43,056.48\n4).- Desarrollo de comercial, servicios o equipamiento, FUERA del área de aplicación del\nPrograma de Desarrollo Urbano de Centro de Población\nVigente...................... $86,112.96\n5).- Desarrollo habitacional, residencial, mixto (mínimo un\n60% de la superficie de construcción con uso habitacional) o turístico\n(mínimo un 60% de la superficie de construcción con uso habitacional), DENTRO del área de aplicación del Programa de\nDesarrollo Urbano de Centro de\nPoblación Vigente, y HASTA\n10,000 m2 de construcción..... $18,452.78\n6).- Desarrollo habitacional, residencial, mixto (mínimo un\n60% de la superficie de construcción con uso habitacional) o turístico\n(mínimo un 60% de la superficie de construcción con uso habitacional) FUERA del área de aplicación del Programa de\nDesarrollo Urbano de Centro de\nPoblación Vigente, y HASTA\n10,000 m2 de construcción..... $37,436.54\n7).- Desarrollo habitacional, residencial, mixto (mínimo un\n60% de la superficie de construcción con uso habitacional) o turístico\n(mínimo un 60% de la superficie de construcción con uso habitacional),desarrollo de uso industrial, especial o infraestructura; desarrollo de uso comercial, servicios o equipamiento, DENTRO del área de aplicación del Programa de\nDesarrollo Urbano de Centro de\nPoblación Vigente, POR CADA\n10,000 m2 de construcción\nADICIONALES al cobro correspondiente por tipo de uso........................... $615.09\n8).- Desarrollo habitacional, residencial, mixto (mínimo un\n60% de la superficie de construcción con uso habitacional) o turístico\n(mínimo un 60% de la superficie de construcción con uso habitacional) desarrollo de uso industrial, especial o infraestructura; desarrollo de uso comercial, servicios o equipamiento, FUERA del área de aplicación del Programa de\nDesarrollo Urbano de Centro de\nPoblación Vigente, POR CADA\n10,000 m2 de construcción\nADICIONALES al cobro correspondiente por tipo de uso........................... $1,230.19\nN.- Elaboración y/o Evaluación de Estudios de Impacto\nTerritorial Urbano e Impacto Social (Intensificación):\na).- Elaboración de Estudio de Impacto\nTerritorial Urbano o Impacto Social para proyectos y/o acciones donde el interesado es alguna autoridad federal, estatal o municipal... DE $11,411.66 A $570,583.06\nb).- Por Evaluación de Estudios de\nImpacto Territorial Urbano o\nImpacto Social y Emisión de\nDictamen de Resolución; se pagará previo al inicio de los trámites, de acuerdo a lo siguiente, con validez hasta 2 revisiones:\n1).- Desarrollo de uso industrial, especial o infraestructura urbana, DENTRO del área de aplicación del Programa de\nDesarrollo Urbano de Centro de\nPoblación Vigente............. $36,905.55\n2).- Desarrollo de uso industrial, especial o infraestructura urbana, FUERA del área de aplicación del Programa de\nDesarrollo Urbano de Centro de\nPoblación Vigente............. $73,811.11\n3).- Desarrollo de comercial, servicios o equipamiento, DENTRO del área de aplicación del Programa de Desarrollo\nUrbano de Centro de Población\nVigente...................... $43,056.48\n4).- Desarrollo de comercial, servicios o equipamiento, FUERA del área de aplicación del\nPrograma de Desarrollo Urbano de Centro de Población\nVigente...................... $86,112.96\n5).- Desarrollo habitacional, residencial, mixto (mínimo un\n60% de la superficie de construcción con uso habitacional) o turístico\n(mínimo un 60% de la superficie de construcción con uso habitacional), DENTRO del área de aplicación del Programa de\nDesarrollo Urbano de Centro de\nPoblación Vigente, y HASTA\n10,000 m2 de construcción..... $18,452.78\n6).- Desarrollo habitacional, residencial, mixto (mínimo un\n60% de la superficie de construcción con uso habitacional) o turístico\n(mínimo un 60% de la superficie de construcción con uso habitacional) FUERA del área de aplicación del Programa de\nDesarrollo Urbano de Centro de\nPoblación Vigente, y HASTA\n10,000 m2 de construcción..... $37,436.54\n7).- Desarrollo habitacional, residencial, mixto (mínimo un\n60% de la superficie de construcción con uso habitacional) o turístico\n(mínimo un 60% de la superficie de construcción con uso habitacional),desarrollo de uso industrial, especial o infraestructura; desarrollo de uso comercial, servicios o equipamiento, DENTRO del área de aplicación del Programa de\nDesarrollo Urbano de Centro de\nPoblación Vigente, POR CADA\n10,000 m2 de construcción\nADICIONALES al cobro correspondiente por tipo de uso........................... $615.09\n8).- Desarrollo habitacional, residencial, mixto (mínimo un\n60% de la superficie de construcción con uso habitacional) o turístico\n(mínimo un 60% de la superficie de construcción con uso habitacional) desarrollo de uso industrial, especial o infraestructura; desarrollo de uso comercial, servicios o equipamiento, FUERA del área de aplicación del Programa de\nDesarrollo Urbano de Centro de\nPoblación Vigente, POR CADA\n10,000 m2 de construcción\nADICIONALES al cobro correspondiente por tipo de uso........................... $1,230.19\nÑ.- Elaboración y/o Evaluación de Estudios de Impacto\nTerritorial Urbano e Impacto Social (Cambio de uso de suelo):\na).- Elaboración de Estudio de Impacto\nTerritorial Urbano o Impacto Social para proyectos y/o acciones donde el interesado es alguna autoridad federal, estatal o municipal... DE $11,411.66 A $570,583.06\nb).- Por Evaluación de Estudios de\nImpacto Territorial Urbano o\nImpacto Social y Emisión de\nDictamen de Resolución; se pagará previo al inicio de los trámites, de acuerdo a lo siguiente, con validez hasta 2 revisiones:\n1).- Desarrollo de uso industrial, especial o infraestructura urbana, DENTRO del área de aplicación del Programa de\nDesarrollo Urbano de Centro de\nPoblación Vigente............. $36,905.55\n2).- Desarrollo de uso industrial, especia lo infraestructura urbana, FUERA del área de aplicación del Programa de\nDesarrollo Urbano de Centro de\nPoblación Vigente............. $73,811.11\n3).- Desarrollo de comercial, servicios o equipamiento, DENTRO del área de aplicación del Programa de Desarrollo\nUrbano de Centro de Población\nVigente...................... $43,056.48\n4).- Desarrollo de comercial, servicios o equipamiento, FUERA del área de aplicación del\nPrograma de Desarrollo Urbano de Centro de Población\nVigente...................... $86,112.96\n5).- Desarrollo habitacional, residencial, mixto (mínimo un\n60% de la superficie de construcción con uso habitacional) o turístico\n(mínimo un 60% de la superficie de construcción con uso habitacional), DENTRO del área de aplicación del Programa de\nDesarrollo Urbano de Centro de\nPoblación Vigente, y HASTA\n10,000 m2 de construcción..... $18,452.78\n6).- Desarrollo habitacional, residencial, mixto (mínimo un\n60% de la superficie de construcción con uso habitacional) o turístico\n(mínimo un 60% de la superficie de construcción con uso habitacional) FUERA del área de aplicación del Programa de\nDesarrollo Urbano de Centro de\nPoblación Vigente, y HASTA\n10,000 m2 de construcción..... $37,436.54\n7).- Desarrollo habitacional, residencial, mixto (mínimo un\n60% de la superficie de construcción con uso habitacional) o turístico\n(mínimo un 60% de la superficie de construcción con uso habitacional),desarrollo de uso industrial, especial o infraestructura; desarrollo de uso comercial, servicios o equipamiento, DENTRO del área de aplicación del Programa de\nDesarrollo Urbano de Centro de\nPoblación Vigente, POR CADA\n10,000 m2 de construcción\nADICIONALES al cobro correspondiente por tipo de uso........................... $615.09\n8).- Desarrollo habitacional, residencial, mixto (mínimo un\n60% de la superficie de construcción con uso habitacional) o turístico\n(mínimo un 60% de la superficie de construcción con uso habitacional) desarrollo de uso industrial, especial o infraestructura; desarrollo de uso comercial, servicios o equipamiento, FUERA del área de aplicación del Programa de\nDesarrollo Urbano de Centro de\nPoblación Vigente, POR CADA\n10,000 m2 de construcción\nADICIONALES al cobro correspondiente por tipo de uso........................... $1,230.19\nO.- Elaboración y/o Evaluación de Estudios de Impacto\nTerritorial Vial y de Movilidad (Implementación):\na).- Elaboración de Estudio de\nImpacto Territorial Vial y de\nMovilidad para proyectos y/o acciones donde el interesado es alguna autoridad federal, estatal, o municipal...... DE $11,411.66\nA $570,583.06\nb).- Por Evaluación de Estudios de\nImpacto Territorial Vial y de\nMovilidad y Emisión de Dictamen de Resolución; se pagará previo al inicio de los trámites, de acuerdo a lo siguiente, con validez hasta 2 revisiones:\n1).- Desarrollo de uso industrial, especial o infraestructura urbana, DENTRO del área de aplicación del Programa de\nDesarrollo Urbano de Centro de\nPoblación Vigente............. $12,814.43\n2).- Desarrollo de uso industrial, especial o infraestructura urbana, FUERA del área de aplicación del Programa de\nDesarrollo Urbano de Centro de\nPoblación Vigente............. $15,377.31\n3).- Revisión de proyecto detallada de Integración Vial, DENTRO del área de aplicación del Programa de desarrollo Urbano del Centro de Población Vigente.......... $24,525.22\n4).- Revisión de proyecto detallada de integración Vial, FUERA del área de aplicación del Programa de Desarrollo Urbano del Centro de Población Vigente.......... $24,525.22\n5).- Desarrollo de comercial, servicios o equipamiento, DENTRO del área de aplicación del Programa de Desarrollo\nUrbano de Centro de Población\nVigente....................... $10,251.54\n6).- Desarrollo de comercial, servicios o equipamiento, FUERA del área de aplicación del\nPrograma de Desarrollo Urbano de Centro de Población\nVigente....................... $12,301.14\n7).- Desarrollo habitacional, residencial, mixto (mínimo un\n60% de la superficie de construcción con uso habitacional) o turístico\n(mínimo un 60% de la superficie de construcción con uso habitacional), DENTRO del área de aplicación del Programa de\nDesarrollo Urbano de Centro de\nPoblación Vigente, y HASTA\n10,000 m2 de construcción..... $9,226.39\n8).- Desarrollo habitacional, residencial, mixto (mínimo un\n60% de la superficie de construcción con uso habitacional) o turístico\n(mínimo un 60% de la superficie de construcción con uso habitacional) FUERA del área de aplicación del Programa de\nDesarrollo Urbano de Centro de\nPoblación Vigente, y HASTA\n10,000 m2 de construcción..... $11,276.70\n9).- Desarrollo habitacional, residencial, mixto (mínimo un\n60% de la superficie de construcción con uso habitacional) o turístico\n(mínimo un 60% de la superficie de construcción con uso habitacional), desarrollo de uso industrial, especial o infraestructura; desarrollo de uso comercial, servicios o equipamiento, DENTRO del área de aplicación del Programa de\nDesarrollo Urbano de Centro de\nPoblación Vigente, POR CADA\n10,000 m2 de construcción\nADICIONALES al cobro correspondiente por tipo de uso........................... $307.55\n10).- Desarrollo habitacional, residencial, mixto (mínimo un\n60% de la superficie de construcción con uso habitacional) o turístico\n(mínimo un 60% de la superficie de construcción con uso habitacional), desarrollo de uso industrial, especial o infraestructura; desarrollo de uso comercial, servicios o equipamiento, FUERA del área de aplicación del Programa de\nDesarrollo Urbano de Centro de\nPoblación Vigente, POR CADA\n10,000 m2 de construcción\nADICIONALES al cobro correspondiente por tipo de uso........................... $410.06\nP.- Elaboración y/o Evaluación de Estudios de Impacto\nTerritorial Vial y de Movilidad (Densificación):\na).- Elaboración de Estudio de\nImpacto Territorial Vial y de\nMovilidad para proyectos y/o acciones donde el interesado es alguna autoridad federal, estatal, o municipal.......... DE $11,411.66\nA $570,583.06\nb).- Por Evaluación de Estudios de\nImpacto Territorial Vial y de\nMovilidad y Emisión de Dictamen de Resolución; se pagará previo al inicio de los trámites, de acuerdo a lo siguiente, con validez hasta 2 revisiones:\n1).- Desarrollo de uso industrial, especial o infraestructura urbana, DENTRO del área de aplicación del Programa de\nDesarrollo Urbano de Centro de\nPoblación Vigente............. $12,814.43\n2).- Desarrollo de uso industrial, especial o infraestructura urbana, FUERA del área de aplicación del Programa de\nDesarrollo Urbano de Centro de\nPoblación Vigente............. $15,377.31\n3).- Revisión de proyecto detallada de Integración Vial, DENTRO del área de aplicación del Programa de desarrollo Urbano del Centro de Población Vigente.......... $24,525.22\n4).- Revisión de proyecto detallada de integración Vial, FUERA del área de aplicación del Programa de desarrollo Urbano del Centro de población Vigente.......... $24,525.22\n5).- Desarrollo de comercial, servicios o equipamiento, DENTRO del área de aplicación del Programa de Desarrollo\nUrbano de Centro de Población\nVigente....................... $10,251.54\n6).- Desarrollo de comercial, servicios o equipamiento, FUERA del área de aplicación del\nPrograma de Desarrollo Urbano de Centro de Población\nVigente....................... $12,301.14\n7).- Desarrollo habitacional, residencial, mixto (mínimo un\n60% de la superficie de construcción con uso habitacional) o turístico\n(mínimo un 60% de la superficie de construcción con uso habitacional), DENTRO del área de aplicación del Programa de\nDesarrollo Urbano de Centro de\nPoblación Vigente, y HASTA\n10,000 m2 de construcción..... $9,226.39\n8).- Desarrollo habitacional, residencial, mixto (mínimo un\n60% de la superficie de construcción con uso habitacional) o turístico\n(mínimo un 60% de la superficie de construcción con uso habitacional) FUERA del área de aplicación del Programa de\nDesarrollo Urbano de Centro de\nPoblación Vigente, y HASTA\n10,000 m2 de construcción..... $11,276.70\n9).- Desarrollo habitacional, residencial, mixto (mínimo un\n60% de la superficie de construcción con uso habitacional) o turístico\n(mínimo un 60% de la superficie de construcción con uso habitacional), desarrollo de uso industrial, especial o infraestructura; desarrollo de uso comercial, servicios o equipamiento, DENTRO del área de aplicación del Programa de\nDesarrollo Urbano de Centro de\nPoblación Vigente, POR CADA\n10,000 m2 de construcción\nADICIONALES al cobro correspondiente por tipo de uso........................... $307.55\n10).- Desarrollo habitacional, residencial, mixto (mínimo un\n60% de la superficie de construcción con uso habitacional) o turístico\n(mínimo un 60% de la superficie de construcción con uso habitacional), desarrollo de uso industrial, especial o infraestructura; desarrollo de uso comercial, servicios o equipamiento, FUERA del área de aplicación del Programa de\nDesarrollo Urbano de Centro de\nPoblación Vigente, POR CADA\n10,000 m2 de construcción\nADICIONALES al cobro correspondiente por tipo de uso........................... $410.06\nQ.- Elaboración y/o Evaluación de Estudios de Impacto\nTerritorial Vial y de Movilidad (Intensificación):\na).- Elaboración de Estudio de\nImpacto Territorial Vial y de\nMovilidad para proyectos y/o acciones donde el interesado es alguna autoridad federal, estatal, o municipal.......... DE $11,411.66\nA $570,583.06\nb).- Por Evaluación de Estudios de\nImpacto Territorial Vial y de\nMovilidad y Emisión de Dictamen de Resolución; se pagará previo al inicio de los trámites, de acuerdo a lo siguiente, con validez hasta 2 revisiones:\n1).- Desarrollo de uso industrial, especial o infraestructura urbana, DENTRO del área de aplicación del Programa de\nDesarrollo Urbano de Centro de\nPoblación Vigente............. $12,814.43\n2).- Desarrollo de uso industrial, especial o infraestructura urbana, FUERA del área de aplicación del Programa de\nDesarrollo Urbano de Centro de\nPoblación Vigente............. $15,377.31\n3).- Revisión de proyecto detallada de Integración Vial, DENTRO del área de aplicación del Programa de desarrollo Urbano del Centro de Población Vigente.......... $24,525.22\n4).- Revisión de proyecto detallada de integración Vial, FUERA del área de aplicación del Programa de Desarrollo Urbano del Centro de Población Vigente.......... $24,525.22\n5).- Desarrollo de comercial, servicios o equipamiento, DENTRO del área de aplicación del Programa de Desarrollo\nUrbano de Centro de Población\nVigente....................... $10,251.54\n6).- Desarrollo de comercial, servicios o equipamiento, FUERA del área de aplicación del\nPrograma de Desarrollo Urbano de Centro de Población\nVigente....................... $12,301.14\n7).- Desarrollo habitacional, residencial, mixto (mínimo un\n60% de la superficie de construcción con uso habitacional) o turístico\n(mínimo un 60% de la superficie de construcción con uso habitacional), DENTRO del área de aplicación del Programa de\nDesarrollo Urbano de Centro de\nPoblación Vigente, y HASTA\n10,000 m2 de construcción..... $9,226.39\n8).- Desarrollo habitacional, residencial, mixto (mínimo un\n60% de la superficie de construcción con uso habitacional) o turístico\n(mínimo un 60% de la superficie de construcción con uso habitacional) FUERA del área de aplicación del Programa de\nDesarrollo Urbano de Centro de\nPoblación Vigente, y HASTA\n10,000 m2 de construcción..... $11,276.70\n9).- Desarrollo habitacional, residencial, mixto (mínimo un\n60% de la superficie de construcción con uso habitacional) o turístico\n(mínimo un 60% de la superficie de construcción con uso habitacional), desarrollo de uso industrial, especial o infraestructura; desarrollo de uso comercial, servicios o equipamiento, DENTRO del área de aplicación del Programa de\nDesarrollo Urbano de Centro de\nPoblación Vigente, POR CADA\n10,000 m2 de construcción\nADICIONALES al cobro correspondiente por tipo de uso........................... $307.55\n10).- Desarrollo habitacional, residencial, mixto (mínimo un\n60% de la superficie de construcción con uso habitacional) o turístico\n(mínimo un 60% de la superficie de construcción con uso habitacional), desarrollo de uso industrial, especial o infraestructura; desarrollo de uso comercial, servicios o equipamiento, FUERA del área de aplicación del Programa de\nDesarrollo Urbano de Centro de\nPoblación Vigente, POR CADA\n10,000 m2 de construcción\nADICIONALES al cobro correspondiente por tipo de uso........................... $410.06\nR.- Elaboración y/o Evaluación de Estudios de Impacto\nTerritorial Vial y de Movilidad (Cambio de Uso de Suelo):\na).- Elaboración de Estudio de\nImpacto Territorial Vial y de\nMovilidad para proyectos y/o acciones donde el interesado es alguna autoridad federal, estatal, o municipal.......... DE $11,411.66\nA $570,583.06\nb).- Por Evaluación de Estudios de\nImpacto Territorial Vial y de\nMovilidad y Emisión de Dictamen de Resolución; se pagará previo al inicio de los trámites, de acuerdo a lo siguiente, con validez hasta 2 revisiones:\n1).- Desarrollo de uso industrial, especial o infraestructura urbana, DENTRO del área de aplicación del Programa de\nDesarrollo Urbano de Centro de\nPoblación Vigente............. $12,814.43\n2).- Desarrollo de uso industrial, especial o infraestructura urbana, FUERA del área de aplicación del Programa de\nDesarrollo Urbano de Centro de\nPoblación Vigente............. $15,377.31\n3).- Revisión de proyecto detallada de Integración Vial, DENTRO del área de aplicación del Programa de Desarrollo Urbano del Centro de Población Vigente.......... $24,525.22\n4).- Revisión de proyecto detallada de integración Vial, FUERA del área de aplicación del Programa de Desarrollo Urbano del Centro de Población Vigente.......... $24,525.22\n5).- Desarrollo de comercial, servicios o equipamiento, DENTRO del área de aplicación del Programa de Desarrollo\nUrbano de Centro de Población\nVigente....................... $10,251.54\n6).- Desarrollo de comercial, servicios o equipamiento, FUERA del área de aplicación del\nPrograma de Desarrollo Urbano de Centro de Población\nVigente....................... $12,301.14\n7).- Desarrollo habitacional, residencial, mixto (mínimo un\n60% de la superficie de construcción con uso habitacional) o turístico\n(mínimo un 60% de la superficie de construcción con uso habitacional), DENTRO del área de aplicación del Programa de\nDesarrollo Urbano de Centro de\nPoblación Vigente, y HASTA\n10,000 m2 de construcción..... $9,226.39\n8).- Desarrollo habitacional, residencial, mixto (mínimo un\n60% de la superficie de construcción con uso habitacional) o turístico\n(mínimo un 60% de la superficie de construcción con uso habitacional) FUERA del área de aplicación del Programa de\nDesarrollo Urbano de Centro de\nPoblación Vigente, y HASTA\n10,000 m2 de construcción..... $11,276.70\n9).- Desarrollo habitacional, residencial, mixto (mínimo un\n60% de la superficie de construcción con uso habitacional) o turístico\n(mínimo un 60% de la superficie de construcción con uso habitacional), desarrollo de uso industrial, especial o infraestructura; desarrollo de uso comercial, servicios o equipamiento, DENTRO del área de aplicación del Programa de\nDesarrollo Urbano de Centro de\nPoblación Vigente, POR CADA\n10,000 m2 de construcción\nADICIONALES al cobro correspondiente por tipo de uso........................... $307.55\n10).- Desarrollo habitacional, residencial, mixto (mínimo un\n60% de la superficie de construcción con uso habitacional) o turístico\n(mínimo un 60% de la superficie de construcción con uso habitacional), desarrollo de uso industrial, especial o infraestructura; desarrollo de uso comercial, servicios o equipamiento, FUERA del área de aplicación del Programa de\nDesarrollo Urbano de Centro de\nPoblación Vigente, POR CADA\n10,000 m2 de construcción\nADICIONALES al cobro correspondiente por tipo de uso........................... $410.06\nS.- Emisión de Pre-factibilidad de Potencial de Desarrollo:\na).- Cuando el promotor del proyecto tenga definida la actividad o uso de suelo, así como densidad e intensidad de desarrollo, por cada 10,000 m2 del polígono o predios a desarrollar o intervenir...... $5,114.36\nb).- Cuando el promotor no tenga definida ninguna actividad, uso, densidad e intensidad, y desee conocer opciones y potencial de desarrollo, por cada 10,000 m2 del polígono o predios a desarrollar o intervenir.................. $10,251.54\nc).- Por Emisión de dictamen o análisis de no ser zona de riesgos, se pagará previo al inicio de los trámites. $4,100.38\nd).- Por emisión de dictamen o análisis de no ser zona de riesgos, se pagará previo al inicio de los tramites, en zonas de Nueva Colonia Hindú y\nMi Ranchito. $4,316.20\ne).- Por Emisión de dictamen o análisis de no ser zona de riesgos, se pagará previo al inicio de los trámites, en zonas de Luis Echeverría\nÁlvarez y Valle de las Palmas. $4,512.40\nf).- Por Emisión de dictamen o análisis de no ser zona de riesgos, se pagará previo al inicio de los trámites, en zonas de Héroes del Desierto y\nLa Rumorosa. $5,100.95\ng).- Por cualquier análisis espacial en formato digital JPG, PDF y\nPaquete de datos vectoriales\nShapefile, por cada 1 variable de análisis (Capa, disponible en la base de datos de INPLADEM) sobre Mapa Base en un área de estudio indicada por el interesado. $512.58\nT.- Por la Emisión de Dictamen de Congruencia de Traza Vial, entre urbanización:\na).- Hasta por 10 hectáreas a\nb).- Por cada hectárea adicional dentro del centro de población $588.60\nc).- Por cada hectárea adicional fuera del centro de población $1,177.21\nU.- Por la Emisión de Certificado de Derechos Adquiridos Sobre el Uso del Suelo Previo a la Actualización del Programa de Desarrollo Urbano del Centro de Población de Tecate para complementar trámites ante la\nDirección de Gestión Integral del Territorio.\na).- Hasta por 10,000 metros cuadrados... $10,227.13\nb).- Por cada hectárea adicional dentro del centro de población $588.60\nc).- Por cada hectárea adicional fuera del centro de población $1,177.21\nV.- Por Emisión de Opinión Técnica de Congruencia Respecto de Acciones\nDesarrollo Urbano de Centro de Población de Tecate.\na).- Hasta por 10,000 metros cuadrados:\n1).- Por uso habitacional, residencial,\n2).- Industrial, especial o infraestructura\n3).- Comercio, servicios o equipamiento. $9,891.63\nb).- Por cada 10,000 adicionales... $297.66\nW.- Por el servicio de análisis de cálculo de adquisición de derechos de desarrollo........ $5,428.50\n7.- DERECHOS POR SERVICIOS QUE PRESTA EL INSTITUTO DE ARTE Y CULTURA\nDE TECATE BAJA CALIFORNIA.\nARTÍCULO 65.- Los servicios que presta la Paramunicipal de nombre\nInstituto de Arte y Cultura de Tecate, Baja California, se pagarán conforme a la siguiente:\nPESOS\nA.- Centro Cultural Tecate.\na).- Inscripción a cursos regulares de Arte y Cultura presencial y/o virtual.......................\n1. Para alumnos inscritos en oficina...................... $157.00\n2. Para alumnos inscritos en oficina con convenio escolar. Exento\n3. Por alumnos que son hermanos\n(de 2 a 5 estudiantes inscritos al mismo periodo de cursos y talleres)........... $100.00 c/u\n4. Adultos mayores de 60 años... Exento\nb).- Cursos regulares de arte y cultura por mes presenciales y/o virtuales......................\n1. Para alumnos inscritos en oficina...................... $400.00\n2. Para alumnos inscritos en oficina con convenio escolar. $250.00\n3. Por alumnos que son hermanos\n(de 2 a 5 estudiantes inscritos al mismo periodo de cursos y talleres)........... $250.00 c/u\n4. Adultos mayores de 60 años... $100.00\nc).- Inscripción a cursos de verano de Arte y Cultura.............. $200.00\nd).- Cursos de Verano de Arte y\nCultura......................... $523.00\ne).- Expedición de credencial individual para cursos regulares...................... $105.00\nf).- Expedición de credencial individual para cursos de verano......................... $126.00\ng).- Expedición de credencial grupal para cursos regulares de grupos de cinco personas o más........ $209.00\nh).- Expedición de credencial grupal para cursos de verano de grupos de cinco personas o más........ $262.00\ni).- Copia fotostática simple........ $4.00\nj).- Impresión en blanco y negro..... $6.00\nk).- Escaneo de imágenes y documentos $10.00\nl).- Impresión a color en tamaño carta........................... $27.00\nm).- Impresión a color en tamaño doble\nn).- Reposición de credencial........ $105.00 ñ).- Recorridos escolares para escuelas públicas (por persona).......... $11.00\no).- Recorridos escolares para escuelas particulares (por persona)...... $16.00\np).- Feria del libro, renta de espacios por el periodo de duración del evento:\n1.- Módulo de 2x2 mt............... $2,000.00\n2.- Módulo de 2x2 mt. con giro comercial afín al evento....... $4,000.00\nq).- Renta de Galería por evento..... $1,045.00\n1.- Renta Galería por 4 horas...... $836.00\n2.- Renta de Galería c/ servicio de cafetería.................. $1,359.00\nr).- Arrendamiento de espacios para preparación y/o venta de alimentos y cafetería.......... $5,225.00\ns).- Arrendamiento de instalaciones de la sala de usos múltiples del\nCentro Cultural Tecate, excepto cuando se trate de escuelas públicas....................... $4,000.00\nt).- Visita guiada a instalaciones, por persona o entrada a Museos. $16.00\nu).- Campamento de verano............ $1,045.00\nv).- Admisión a eventos especiales presenciales y/o virtuales..... $53.00\nw).- Venta de artículos promocionales De $25.00 a $200.00\nx).- Diplomados y cursos de especialización................ $3,000.00\ny).- Otros fondos, subsidios y/o convenios nacionales e internacionales................ hasta $1,045,000.00\nz).- Renta de jardines, patio y estacionamiento del Centro\nCultural Tecate para realización de eventos por particulares; bazares, mercados, ferias, exposiciones, colectivos, etc.. $2,000.00 aa).- Renta de jardines, patio y estacionamiento del Centro\nCultural Tecate para sesiones fotográficas de eventos sociales por particulares, de lunes a domingo........................ $200.00 bb).- Renta de cajón de estacionamiento en Centro\nCultural Tecate en día hábil de\n8:00 AM a 9:00 PM. (De 9:00 PM a\n8:00 AM permanece cerrado...... $15.00 cc).- Renta de cajón de estacionamiento por evento especial en Centro Cultural\nTecate......................... $30.00\nB.- Teatro de la ciudad.\na).- Arrendamiento de las instalaciones para llevar a cabo eventos musicales, obras de teatro y eventos masivos similares, presenciales y/o virtuales por evento........... $34,000.00\nb).- Arrendamiento de las instalaciones para llevar a cabo eventos recreativos, educativos, entre otros similares, presenciales y/o virtuales\n1- Con fines de lucro................ $22,000.00\n2- Sin fines de lucro................ $14,000.00\nc).- Arrendamiento de las instalaciones para llevar a cabo eventos para asociaciones civiles, servicios profesionales científicos, graduaciones escolares privadas, de beneficencia y otras similares, presenciales y/o virtuales.............................. $12,000.00\nd).- Arrendamiento de espacios para preparación y/o venta de alimentos y cafetería.............................. $5,225.00\ne).- otros fondos, subsidios y/o convenios nacionales e internacionales............ hasta $1,045,000.00\nf).- Servicio de preparación y/o venta de alimentos y cafetería............... $3,135.00\ng).- Taquilla del Teatro de la Ciudad en eventos producidos por IMACTE..\n1).- Estudiantes...................... $25.00 a $50.00\n2).- Público en general............... $100.00 a $300.00\nh).- Renta de equipo audiovisual, mecánico y de iluminación.............. $526.00\ni).- Renta de cajón de estacionamiento por evento en las instalaciones....... $10.00\n8.- DERECHOS POR SERVICIOS QUE PRESTA EL INSTITUTO MUNICIPAL DE\nBIENESTAR ANIMAL.\nARTÍCULO 65 BIS.- Captura, alimentación, consulta, adopciones y otros animales domésticos se cobrará conforme a la siguiente tarifa:\nIMPORTE\nPESOS\nA.- Vacuna triple canina, múltiple canina y vacuna felina............. $250.00\nB.- Alimentación (por día)............ $130.00 c.- Desparasitación externa\n(garrapaticida y pulguicida)....... $260.00 a $350.00\nD.- Desparasitación Interna (parásitos intestinales)..................... $50.00 a $200.00\nE.- Esterilización en hembras (ovario histerectomía) y machos\n(orquiectomía) felinas............ $450.00 a $1,000.00\nF.- Esterilización en hembras (ovario histerectomía) y machos\n(orquiectomía) caninas............ $600.00 a $1,500.00\nG.- Consulta................... $200.00\nH.- Adopción (se entrega vacunado, Cartilla de vacunación y esterilizado)...................... $600.00\nI.- Eutanasia............ $300.00 a $1,000.00\nJ.- Devolución de caninos capturados por el Instituto Municipal de\nBienestar Animal................... $130.00 a $1,300.00\nK.- Reclusión de caninos para observación en caso de agresión.\n(por día)......................... $130.00\nL.- Recepción de cadáveres caninos y felinos\na) Caninos raza pequeña de 3 a 10 kg.............................. $450.00\nb) Caninos raza mediana de 10.01 a\n25 kg........................... $650.00\nc) Caninos raza grande de 25.01 a 50 kg.............................. $800.00\nd) Canino raza gigante de 50.01 kg en adelante.................... $1,000.00\ne) Felinos......................... $300.00\nM.- Recepción de animales en el\nInstituto Municipal de Bienestar\nAnimal por parte del propietario............... $750.00\n9.- DERECHOS POR SERVICIOS QUE PRESTA EL SISTEMA MUNICIPAL DE\nPARQUES TEMÁTICOS DE TECATE\nARTÍCULO 65 TER.- Los Servicios que presta la paramunicipal denominada Sistema Municipal de Parques Temáticos de Tecate, se cobrarán conforme a la siguiente:\nPESOS\nI.- Parque Infantil Tecarroca.\na).- Arrendamiento de instalaciones, para eventos privados no lucrativos\n1).- Salón de usos múltiples........ $ 2,282.33\n2).- Espacio asador chico........... $ 342.35\n3).- Espacio asador grande.......... $ 570.58\nb).- Renta de dormitorio por persona por noche..................... $ 171.17\nc).- Uso de Alberca por persona por\n1).- Niños.......................... $ 34.23\n2).- Adultos....................... $ 57.06\nd).- Campamento en Parque Tecarroca por noche...................... $109.20 por persona\ne).- Admisión a eventos especiales, presenciales y/o virtuales\n1).- Habitantes de Tecate........... DE $0.00 A $ 228.23\n2).- Foráneos...................... DE $11.41 A $513.52\nf).- Punto de venta de artículos varios con fines de lucro\n1).- Para preparación y/o venta de alimentos........... $ 522.50 por evento\n2).- Para venta de artículos varios. $1,567.50 MENSUAL\n3).- Para renta de servicios de entretenimiento.............. $3,135.00 MENSUAL\n(Pintura de alcancías, cualquier actividad recreativa con algún costo y fines de lucro particular)\ng).-Eventos organizados por Colectivos\n1).- Con fines de lucro........... $ 313.50 por puesto\n2).- Sin fines de lucro........... $ 156.75 por puesto\nII.- Parque Los Encinos.\na).- Arrendamiento de instalaciones, tanto para eventos sin fines de lucro, como con fines de lucro, en base al espacio físico y asistencia de personas proyectada\nÁREA DE ASADORES:\n1.- Palapas......................... $ 570.58\n2.- Chapoteadero (invierno)......... $ 798.82\n3.- Chapoteadero con agua (verano).. $1,141.17\nEXPLANADAS:\n1.- Explanada principal con fines de lucro.\n1.1.-Hasta 100 personas.......... $5,705.83\n1.2.-De 101 hasta 500 personas... $11,411.66\n1.3.-De 501 o más personas....... $22,823.32\n2.- Explanada principal sin fines de lucro.\n2.1.-Hasta 100 personas.......... $ 546.01\n2.2.-De 101 a 250 personas....... $ 783.75\n2.3.-De 251 a 500 personas....... $ 1,254.00\n2.4.-De 501 a 1000 personas...... $ 1,724.25\n2.5.-Mas de 1000 personas....... $ 2,299.00\n3.- Explanada principal para eventos culturales, deportivos y cívicos.\n3.1.-Hasta 100 personas.......... $0.00\n3.2.-De 101 a más personas $5.23 por persona\n4.-Eventos organizados por\nColectivos\n4.1.-Con fines de lucro........ $ 313.50 por puesto\n4.2.-Sin fines de lucro........ $ 156.75 por puesto\nTEATRO AL AIRE LIBRE:\n1.- Con fines de lucro\n1.1.- Hasta 100 personas......... $2,852.91\n1.2.- De 101 a 250 personas...... $3,657.50\n1.3.- De 251 a 500 personas...... $5,705.84\n2.- Sin fines de lucro\n2.1.- Hasta 100 personas........ $ 285.29\n2.2.- De 101 a 250 personas...... $ 365.75\n2.3.- De 251 a 500 personas...... $ 570.58\n3.-Teatro al aire libre para eventos culturales, deportivos y cívicos.\n3.1.-Hasta 100 personas.......... $0.00\n3.2.-De 101 a más personas $ 5.23 por persona\n4.-Eventos organizados por\nColectivos\n4.1.-Con fines de lucro........ $ 313.50 por puesto\n4.2.-Sin fines de lucro........ $ 156.75 por puesto\nCUOTA DE RECUPERACIÓN POR USO DE\nESTACIONAMIENTO $10.45 por carro (diario)\nb)- Venta de artículos promocionales\nDE $11.41 A $1,027.05\nc).- Punto de venta de artículos varios con fines de lucro\n1.- Para preparación y/o venta de alimentos....................... $546.01 por evento\n2.- Para venta de artículos varios.. $1,638.04 mensual\n3.- Para renta de servicios de entretenimiento................. $3,276.08 mensual\n(Pintura de alcancías, cualquier actividad recreativa con algún costo y fines de lucro particular)\nd).- Admisión a eventos especiales, presenciales y/o virtuales de..\n1).- Habitantes de Tecate........... DE $0.00 A $228.23\n2).- Foráneos...................... DE $11.41 A $513.52\ne).- Cuota de recuperación por el uso de baños públicos.\n1).- Cuota por persona........... $5.46\n10.- DERECHOS POR SERVICIOS QUE PRESTA LA PARAMUNICIPAL DENOMINADA\nSERVICIOS INTEGRALES DE RESIDUOS DE TECATE\nARTÍCULO 65 Quater.- Los derechos por el servicio de recolección de basura que preste la Paramunicipal denominada Servicios Integrales de Residuos de Tecate a giros comerciales, industriales y servicios extraordinarios, serán fijados en cada caso por la Paramunicipal y se pagarán de la siguiente manera:\nA.- Los servicios que se presten por recolección de basura de desechos que excedan de 33 kilogramos por semana, se pagarán considerando tipo de recipiente, periodicidad del servicio, y la siguiente tarifa:\n1).- Servicio de tipo frontal:\nPOR MES ACUMULADOS PESOS\n1 $1,000,00\n2 $ 975.00\n3 $ 950.00\n4 $ 925.00\n5 $ 900.00\n6 $ 875.00\n7 $ 850.00\n8 $ 825.00\n9 $ 800.00\n10 $ 775.00\nDespués de los 10 servicios prestados, se cobrará $825.00 M.N. por cada servicio adicional.\n2).- Servicio tipo ROLL OFF por cada uno de los servicios prestados... $6,500.00\nB.- Los servicios extraordinarios que se presten por recolección de basura a giros comerciales e industriales, que no requieran contenedor de basura, se pagarán por mes conforme a las siguientes tarifas:\n1).- Cuando el servicio sea requerido una vez por semana en dicho periodo (solo aplica un tambo de\n200 litros)...................... $100.00\n2).- Cuando el servicio sea requerido de 2 a 3 veces por semana en dicho periodo (Solo aplica de 2 a 5 tambos de 200 litros)............ $726.00\n3).- Cuando el servicio sea requerido de 4 a 5 veces por semana en dicho periodo (solo aplica de 2 a 5 tambos de 200 litros) $1,452.00 comerciales, industriales y maquiladora, efectuarán el pago antes de que se preste el servicio.\nC.- Los servicios que se presten por el uso y depósito de residuos al relleno sanitario o al centro de transferencia, se cobrarán cada vez que se utilice el servicio, conforme a la siguiente tarifa:\nIMPORTE\nPESOS\na).- Vehículos particulares (basura doméstica)....................... $100.00\nb).- Pick-Up.......................... $350.00\nc).- Redilas.......................... $700.00\nd).- Camión de volteo................. $2,250.00\ne).- Recolector C.T. C.F.C.L.......... $7,700.00\nf).- Recolector roll off o trailer.... $7,000.00\nEl relleno sanitario recibirá los desechos domésticos, comerciales e industriales que se generan en el Municipio de Tecate, y los cuales no queden comprendidos dentro de aquellos, cuyo confinamiento en el relleno sanitario municipal, esté prohibido por las Autoridades\nEcológicas competentes.\nCAPÍTULO III\nACCESORIOS DE DERECHOS\n25.- RECARGOS.\nARTÍCULO 66.- La tasa de recargos por concepto de mora será del dos por ciento mensual, de igual manera en los conceptos de convenios en\nDerechos.\nY los recargos se causarán hasta por 5 años.\n26.- GASTOS DE EJECUCIÓN.\nARTÍCULO 67.- Los gastos de ejecución derivados de derechos se de obligaciones fiscales no satisfechas dentro de los plazos legales, de Baja California.\n27.- SANCIONES.\nARTÍCULO 68.- Las que deriven del incumplimiento de las disposiciones fiscales en materia de Derechos.\nCAPÍTULO IV\nDERECHOS NO COMPRENDIDOS EN LA LEY DE INGRESOS VIGENTE, CAUSADOS EN\nEJERCICIOS FISCALES ANTERIORES PENDIENTES DE LIQUIDACIÓN O PAGO.\n28.- DERECHOS CAUSADOS EN EJERCICIOS FISCALES ANTERIORES PENDIENTES\nDE LIQUIDACIÓN O PAGO.\nARTÍCULO 69.- Los Derechos no pagados en el ejercicio fiscal en que anteriores, aplicando en cuanto al fondo, las leyes vigentes en la fecha en que se generaron y en cuanto a la forma mediante el\nProcedimiento Administrativo de Ejecución que establece la Ley de\nHacienda Municipal del Estado de Baja California o en su caso, el procedimiento judicial que corresponda.\nTÍTULO VI. - PRODUCTOS DERIVADOS DE:\nCAPÍTULO I\nPRODUCTOS\n1.- CONTRAPRESTACIÓN DE CONCESIONES, EXPLOTACIÓN O ARRENDAMIENTO\nDE BIENES MUEBLES E INMUEBLES, PROPIEDAD DEL GOBIERNO MUNICIPAL\nARTÍCULO 70.- Las rentas que produzcan los bienes propiedad del\nMunicipio y que sean susceptibles de ser arrendados, se pagarán en base en los contratos de arrendamiento que se celebren con cada uno de los inquilinos y el Ayuntamiento, cubriéndose el importe de la renta mensual los primeros cinco días del mes correspondiente.\n2.- SUMINISTRO DE FORMAS DIVERSAS PARA TRÁMITES ADMINISTRATIVOS\nARTÍCULO 71.- Ingresos obtenidos por el suministro de formas impresas, tales como solicitudes que se utilizan en trámites administrativos en las oficinas municipales, se pagarán a razón del importe de $16.04 M.N. en la Caja Recaudadora de la Tesorería\nMunicipal.\n3.- OTRAS ACTIVIDADES DEL GOBIERNO MUNICIPAL, QUE NO CORRESPONDAN\nA SUS FUNCIONES PROPIAS DE DERECHO PÚBLICO\n4.- BIENES MOSTRENCOS\nARTÍCULO 72.- Ingresos obtenidos por los bienes mostrencos que se rematen o vendan de acuerdo a las disposiciones relativas.\n5.- ORGANISMOS DESCENTRALIZADOS Y/O PARAMUNICIPALES\nARTÍCULO 73.- Los rendimientos producidos por organismos descentralizados y/o paramunicipales, se percibirán cuando lo decreten y exhiban, conforme a sus respectivos regímenes interiores.\n6.- DEL PISO\nARTÍCULO 74.- Las personas físicas o morales que previa autorización de la autoridad municipal correspondiente, hagan uso del piso, de realización de actividades comerciales o de prestación de servicios en forma permanente o temporal, pagarán anualmente, dentro de los primeros sesenta días del ejercicio fiscal, los productos correspondientes a la siguiente tarifa.\nIMPORTE\nPESOS\nA.- Casetas telefónicas, diariamente, por cada una.................... $10.70\nB.- Instalaciones de infraestructura, por metro lineal, anualmente:\na).- Redes subterráneas de:\n1.- Telefonía..................... $1.60\n2.- Transmisión de datos.......... $1.60\n3.- Transmisión de señales de televisión por cable.......... $1.60\n4.- Distribución de gas........... $1.60\n5.- Energía eléctrica............. $1.60\nb).- Redes visibles o aéreas de:\n1.- Telefonía..................... $3.22\n2.- Transmisión de datos.......... $3.22\n3.- Transmisión de señales de televisión por cable.......... $3.22\n4.- Energía eléctrica.............. $3.22\nc).- Registro de instalaciones visibles o subterráneas, por cada uno..... $2.03\n7.- PRODUCTOS FINANCIEROS.\n8.- INTERESES CONVENIOS.\nCAPÍTULO II\nPRODUCTOS NO COMPRENDIDOS EN LA LEY DE INGRESOS VIGENTE, CAUSADOS EN\nEJERCICIOS FISCALES ANTERIORES PENDIENTES DE LIQUIDACIÓN O PAGO\n9.- PRODUCTOS CAUSADOS EN EJERCICIOS FISCALES ANTERIORES PENDIENTES\nDE LIQUIDACIÓN O PAGO\nARTÍCULO 75.- Los Productos no pagados en el ejercicio fiscal en que se causaron, se cobrarán como ingreso de ejercicios fiscales anteriores, aplicando en cuanto al fondo, las leyes vigentes en la fecha en que se generaron, y en cuanto a la forma, mediante el\nProcedimiento Administrativo de Ejecución que establece la Ley de\nHacienda Municipal del Estado de Baja California, o en su caso, el procedimiento judicial que corresponda.\nTÍTULO VII.- APROVECHAMIENTOS\nCAPÍTULO I\nAPROVECHAMIENTOS\nARTÍCULO 76.- Las que se contemplan en los reglamentos municipales, sanción impuesta por las diversas dependencias municipales, las que\nProcedimiento Administrativo de Ejecución, conforme a lo establecido por el Artículo 88 de la Ley de Hacienda Municipal del Estado de Baja\nCalifornia.\n2.- REINTEGROS E INDEMNIZACIONES.\n3.- DONACIONES, CESIONES, HERENCIAS Y LEGADOS A FAVOR DEL\nMUNICIPIO.\n4.- OTORGAMIENTO Y USUFRUCTO DE DERECHOS.\n5.- OTROS APROVECHAMIENTOS. acopio (puntos verdes) en los términos de la fracción VII del artículo\n48 del Reglamento Interno de Servicios Integrales de Residuos de\nTecate y demás aplicables.\nCAPÍTULO II\nAPROVECHAMIENTOS PATRIMONIALES\n6.- CAUCIONES, FIANZAS Y DEPÓSITOS CUYA PÉRDIDA SE DECLARE POR\nRESOLUCIÓN FIRME.\n7.- INGRESOS POR VENTA DE BIENES PATRIMONIALES.\nARTÍCULO 77.- El Ayuntamiento podrá disponer de bienes patrimoniales cuando éstos no tengan un uso y se requiera fortalecer las finanzas municipales, para ponerlos en venta con pago en una sola exhibición o en parcialidades fijas mediante suscripción de contrato, mismo que no podrá exceder los 5 años, con el financiamiento que para tales efectos proponga al Ayuntamiento la Tesorería Municipal.\nLos valores de los bienes patrimoniales serán aquellos que para tales valor fiscal, cuando el primero resulte inferior al segundo.\n8.- OTROS APROVECHAMIENTOS DE CAPITAL.\nCAPÍTULO III\nACCESORIOS DE APROVECHAMIENTOS\n9.- RECARGOS.\nARTÍCULO 78.- La tasa de recargos por concepto de mora será del dos por ciento mensual, de igual manera en los conceptos de convenios en\nAprovechamientos.\nY los recargos se causarán hasta por 5 años.\n10.- GASTOS DE EJECUCIÓN.\nARTÍCULO 79.- Los gastos de ejecución derivados de aprovechamientos plazos legales, en los términos que señala la Ley de Hacienda\nMunicipal del Estado de Baja California.\nARTÍCULO 80.- Las que deriven del incumplimiento de las disposiciones en materia de Aprovechamientos.\nCAPÍTULO IV\nAPROVECHAMIENTOS NO COMPRENDIDOS EN LA LEY DE INGRESOS VIGENTE,\nCAUSADOS EN EJERCICIOS FISCALES ANTERIORES PENDIENTES DE LIQUIDACIÓN\nO PAGO.\n12.- APROVECHAMIENTOS CAUSADOS EN EJERCICIOS FISCALES ANTERIORES\nPENDIENTES DE LIQUIDACIÓN O PAGO.\nARTÍCULO 81.- Los Aprovechamientos no pagados en el ejercicio fiscal en que se causaron, se cobrarán como ingreso de ejercicios fiscales anteriores, aplicando en cuanto al fondo, las leyes vigentes en la fecha en que se generaron, y en cuanto a la forma, mediante el\nProcedimiento Administrativo de Ejecución que establece la Ley de\nHacienda Municipal del Estado de Baja California, o en su caso, el procedimiento judicial que corresponda.\nTÍTULO VIII.- INGRESOS POR VENTA DE BIENES, PRESTACIÓN DE SERVICIOS\nY OTROS INGRESOS\nCAPÍTULO I\nINSTITUCIONES PÚBLICAS DE SEGURIDAD SOCIAL.\n1.- INGRESOS POR VENTA DE BIENES Y SERVICIOS PRODUCIDOS EN\nESTABLECIMIENTOS DEL GOBIERNO MUNICIPAL.\nCAPÍTULO II\nOTROS INGRESOS.\n2.- INGRESOS FINANCIEROS.\n3.- DONATIVOS.\n4.- OTROS INGRESOS.\nTÍTULO IX.- PARTICIPACIONES, APORTACIONES, CONVENIOS, INCENTIVOS\nAPORTACIONES\nCAPÍTULO I\nPARTICIPACIONES.\n1.- PARTICIPACIONES DE IMPUESTOS FEDERALES.\n2.- PARTICIPACIONES DE IMPUESTOS ESTATALES. de obras.\nb).- Por otros impuestos o ingresos del Estado que señalen las\nLeyes, Acuerdos o Convenios que los regulen.\n3.- PARTICIPACIONES EN IMPUESTOS ADUANALES.\nCAPÍTULO II\nAPORTACIONES.\n4.- APORTACIONES DEL GOBIERNO DEL ESTADO O DE LA FEDERACIÓN PARA\nOBRAS Y SERVICIOS PÚBLICOS O PROGRAMAS ESPECIALES.\n5.- APORTACIONES FEDERALES DEL RAMO 33:\na).- Fondo de Aportaciones para la Infraestructura Social\nMunicipal.\nb).- Fondo de Aportaciones para el Fortalecimiento de los\nMunicipios.\nc).- Otras.\nCAPÍTULO III\nCONVENIOS\n6.- OTROS INGRESOS POR CONVENIOS FEDERALES.\n7.- OTROS INGRESOS POR CONVENIOS ESTATALES.\n8.- CONVENIOS CELEBRADOS POR PARAMUNICIPALES CON ENTIDADES FEDERALES,\nESTATALES, MUNICIPALES, AUTÓNOMOS U OTRAS.\nCAPÍTULO IV\nINCENTIVOS DERIVADOS DE COLABORACIÓN FISCAL.\n9.- INGRESOS POR CONVENIOS DE COLABORACIÓN FISCAL.\nCAPITULO V\nFONDOS DISTINTOS DE APORTACIONES\n10.- INGRESOS POR FONDOS DISTINTOS DE APORTACIONES.......$0.00\nTÍTULO X.- TRANSFERENCIAS, ASIGNACIONES, SUBSIDIOS Y OTRAS AYUDAS.\n3.- SUBSIDIOS QUE OTORGUE EL GOBIERNO MUNICIPAL A LAS ENTIDADES\nPARAMUNICIPALES.\nTÍTULO XI.- INGRESOS DERIVADOS DE FINANCIAMIENTOS\nCAPÍTULO I\nENDEUDAMIENTO INTERNO.\n1.- CRÉDITOS OTORGADOS AL MUNICIPIO.\n2.- APORTACIONES ESTATALES Y FEDERALES.\n3.- PROGRAMAS ESPECIALES.\n4.- LOS PROVENIENTES DE BONOS Y OBLIGACIONES.\nDISPOSICIONES GENERALES:\nARTÍCULO 82.- Las Participaciones de Impuestos Federales y Estatales que perciba el Municipio, serán las que fijen las Leyes, Convenios y\nAcuerdos Federales y Estatales respectivos.\nARTÍCULO 83.- La validez de las Licencias y Permisos otorgados por ordenamientos legales.\nARTÍCULO 84.- Los gravámenes que prevé la presente Ley, no serán motivo de exención, condonación, o modificación por parte de las\nAutoridades Municipales, salvo por autorización expresa del Congreso del Estado; con excepción de los recargos, que podrán condonarse total o parcialmente, conforme al Artículo 110 de la Ley de Hacienda\nMunicipal del Estado de Baja California.\nARTÍCULO 85.- Se entiende como fecha de iniciación de operaciones de las personas físicas, aquella que estipule el Servicio de\nAdministración Tributaria, a través de sus formas y trámites oficiales, en el caso de personas morales, el día de su constitución, aún cuando ésta sea anterior a la fecha de apertura del negocio, o a la fecha en que se obtenga el primer ingreso, en ambos casos, se deberá anexar copia de los mismos a la Recaudación de Rentas\nMunicipal.\nARTÍCULO 86.- Las personas físicas, morales o unidades económicas, que para expender sus mercancías lo hagan a través de vendedores ambulantes, agentes de ventas, comisionistas, concesionarios ambulantes, o cualquier otro nombre que se le dé al expendedor, serán solidariamente responsables del pago de los Impuestos, Derechos o\nMultas que se originen con motivo de las actividades que ejerzan, para lo cual se constituirán en retenedores de los créditos fiscales, debiendo enterarlos a la Recaudación de Rentas Municipal, dentro de los plazos que fijan las Leyes Fiscales.\nARTÍCULO 87.- Las personas físicas, morales o unidades económicas que presten los servicios de publicidad, así como los propietarios de los comerciales e industriales y de instituciones de crédito, seguros y fianzas, serán solidariamente responsables del pago de las sanciones esta Municipalidad, por violaciones a los Reglamentos relativos.\nARTÍCULO 88.- Ninguna contribución podrá recaudarse si no está prevista en la presente Ley de Ingresos Municipal.\nARTÍCULO PRIMERO.- Las contribuciones cuyo cobro haya quedado y las Leyes Fiscales de la Federación, en caso de reformas o contribuciones, se cobrarán por este ejercicio a la tasa que fije la\nLey de Ingresos vigente, en la fecha en que haya ocurrido la suspensión de cada contribución.\nARTÍCULO SEGUNDO.- Con relación al cobro de los Derechos por los en la presente Ley, se estará a lo dispuesto en el Convenio que en\nMateria de Catastro y Control Urbano, celebraron el Gobierno\nConstitucional del Estado de Baja California y el Ayuntamiento de\nTecate, Baja California.\nARTÍCULO TERCERO.- Será el Cabildo quien reglamentará el uso de los rangos en los derechos por cobrar, de acuerdo al tabulador que para dicho efecto aprueben.\nARTÍCULO CUARTO.- Estarán exentos del pago total de los derechos correspondientes a los servicios que presta la Dirección de Gestión\nIntegral del Territorio, los fraccionamientos desarrollados por el\nInstituto de Promoción del Desarrollo Urbano de Tecate, así como los fraccionamientos promovidos por los sectores público o privado dirigidos a la construcción de viviendas de interés social con precio de venta inferior o igual a 55,000 UDIS.\nARTÍCULO QUINTO.- El Cabildo determinará los incentivos que recibirán\nCultural de Tecate, siempre que los conserven de acuerdo con los lineamientos que determine la misma Comisión.\nARTÍCULO SEXTO.- Los contribuyentes que cumplan con el pago del\nImpuesto Predial del ejercicio fiscal 2025 durante los meses de enero, febrero y marzo gozarán de la reducción de un diez por ciento, ocho por ciento y seis por ciento sobre el mismo, respectivamente. en el último párrafo del artículo 10 de la presente Ley.\nARTÍCULO SÉPTIMO.- Los contribuyentes que cumplan con el pago del\nImpuesto Predial del ejercicio fiscal 2025 y que acrediten su\nSocial, tratándose de personas discapacitadas, deberán acreditarlo mediante certificado médico, expedido por cualquier Institución\nPública de Salud con domicilio en el Estado. La viudez se acreditará con el acta de defunción del cónyuge, la indigencia con un estudio socioeconómico con vigencia anual que realice el Sistema para el\nDesarrollo Integral de la Familia del Municipio, y la población senecta que se identifique con credencial del INAPAM, tendrán derecho a un descuento del cien por ciento únicamente en el predio en el cual se demuestre que habita y que específicamente sea de uso habitacional, en caso de contar con más de un predio a su nombre, éstos deberán estar al corriente en el impuesto predial para hacer válido el descuento.\nAdemás de los descuentos previstos en el párrafo anterior, podrán obtener descuentos del 10% al 50% en el pago del impuesto predial personas indígenas y afrodescendientes, mujeres jefas de familias de escasos recursos y personas liberadas por amnistías, previo la aplicación de un estudio socioeconómico con vigencia anual que realice el sistema para el desarrollo integral de la familia del municipio.\nARTÍCULO OCTAVO.- Tratándose de personas jubiladas y pensionadas que lo acrediten con los documentos oficiales expedidos por las\nInstituciones Públicas de Seguridad Social, discapacitadas que lo acrediten mediante certificado médico expedido por cualquier\nInstitución Pública de Salud con domicilio en el Estado, viudez que se acredite con el acta de defunción del cónyuge, la indigencia acreditada con un estudio socioeconómico con vigencia anual que\nMunicipio, la población senecta que se identifique con credencial del\nINAPAM, personas que tengan a su cargo un familiar con alguna la Familia del Municipio, tendrán un descuento del cincuenta por\nRegistro Civil, sin contraponer a lo ya establecido en la letra G\nExpedición de Actas, último párrafo y letra H penúltimo párrafo del\nArtículo 31 Derechos por Servicios que Presta el Registro Civil, así\nPúblicas por Comerciantes Ambulantes o con Puestos Semifijos.\nARTÍCULO NOVENO.- La presente Ley entrará en vigor, el día primero de enero del año dos mil veinticinco.\nARTÍCULO DÉCIMO.- Las cuotas por los derechos a que se refiere esta\nLey, se actualizarán mensualmente a partir de que se conozca el índice cada mes, con el factor que se obtenga al momento de la actualización, de dividir el Índice Nacional de Precios al Consumidor que se publique en el Diario oficial de la Federación por el Instituto Nacional de\nEstadística y Geografía, o la dependencia federal que en sustitución de ésta lo aplique, del último mes inmediato anterior al mes por el cual se hace el ajuste, entre el citado índice del penúltimo mes inmediato anterior al del mismo mes que se actualiza, con excepción de los previstos en el Art. 30, 56, 59, 61, 62, 65, 65 Bis y 65 Ter de la presente Ley.\nARTÍCULO DÉCIMO PRIMERO. - Al monto del impuesto predial precisado en el Artículo 10 de esta Ley, se le aplicará un subsidio municipal, representado por la fórmula siguiente:\n[Impuesto Predial para el ejercicio 2025 - (valor fiscal por m² 2017\nX superficie 2025 X tasa 2025)] X.60 = Subsidio al Impuesto\nPredial para 2025.\nEn ningún caso, el subsidio será menor a cero.\nLos predios que en este año sean registrados por primera vez en la base catastral, será considerada la base del valor metro cuadrado para 2017 conforme al valor fiscal que corresponda según la zona y el sector donde debería aplicar.\nARTÍCULO DÉCIMO SEGUNDO.– En atención a lo dispuesto en el programa de desarrollo urbano de centro de población de Tecate 2020 – 2040, correspondiente al artículo 39 de esta ley, el 10% del monto dicho artículo 39 de esta ley.\nARTÍCULO DÉCIMO TERCERO.- Se exenta a las personas físicas y morales inscritas en el Programa Estatal de Vivienda 2022-2027, del pago de derechos que se causen por: factibilidades, dictámenes, certificados, autorizaciones, licencias y en general, por trámites relacionados con la construcción de vivienda social, exclusivamente para los proyectos de la Secretaría de Infraestructura, Desarrollo Urbano y Reordenación\nTerritorial, el Instituto para el Desarrollo Inmobiliario y de la\nPrograma Estatal de Vivienda publicado en el Periódico Oficial del\nEstado en fecha 21 de octubre de 2022 y actualizaciones posteriores, así como del Programa de Vivienda para el Bienestar impulsado por el\nGobierno Federal a través de la coordinación de SEDATU, CONAVI, INSUS, INFONAVIT, el Programa Municipal de Vivienda a través del INPRODEUR y cualquier otra institución que se relacione con el programa señalado durante el proceso de ejecución del mismo.\nLos derechos a exentar se enuncian a continuación:\nI. Factibilidad de uso del suelo;\nII. Certificado de libertad de gravamen;\nIII. Dictamen de uso del suelo;\nIV. Manifestación de impacto ambiental;\nV. Movimiento de tierras;\nVI. Deslinde catastral;\nVII. Licencia de Construcción;\nVIII. Régimen de Propiedad en Condominio;\nIX. Licencia de Fraccionamiento;\nX. Certificado de número oficial;\nXI. Constancia de obra terminada;\nXII. Cambio de propietario; y\nXIII. Impuesto sobre adquisición de bienes inmuebles.\nArtículo Transitorio Adicionado veinte días del mes de diciembre del año dos mil veinticuatro.\nC. EVELYN SÁNCHEZ SÁNCHEZ\nDIPUTADA PRESIDENTA\n(RÚBRICA)\nC. MICHELLE ALEJANDRA TEJEDA MEDINA\nDIPUTADA SECRETARIA\n(RÚBRICA)\nARTÍCULO ÚNICO TRANSITORIO DEL DECRETO No. 74, POR EL QUE SE\nTRANSITORIO A LA LEY DE INGRESOS DEL MUNICIPIO DE TECATE, BAJA\nCALIFORNIA Y TABLA DE VALORES CATASTRALES UNITARIOS, BASE DEL IMPUESTO\nPREDIAL PARA EL EJERCICIO FISCAL DE 2025; PUBLICADO EN EL PERIÓDICO\nPOR LA H. XXV LEGISLATURA; SIENDO GOBERNADORA CONSTITUCIONAL LA C.\nMARINA DEL PILAR ÁVILA OLMEDA 2021-2027.\nARTÍCULOS TRANSITORIOS\nPRIMERO.- La presente reforma entrará en vigor al día siguiente de su publicación en el periódico Oficial del Estado de Baja California.\nSEGUNDO.- Una vez publicada en el Periódico Oficial del Estado, se instruye al Tesorero\nMunicipal del XXV Ayuntamiento de Tecate Baja, California, a que realice las modificaciones presupuestarias correspondientes, con el fin de que surta efectos la presente reforma.\nDADO en Sesión Ordinaria de la XXV Legislatura en la Ciudad de Tijuana, B.C., a los veintisiete días del mes de marzo del año dos mil veinticinco.\nDIP. EVELYN SÁNCHEZ SÁNCHEZ\nPRESIDENTA\n(RÚBICA)\nDIP. MICHELLE ALEJANDRA TEJEDA MEDINA\nSECRETARIA\n(RÚBICA)\nDE CONFORMIDAD CON LO DISPUESTO POR LA FRACCIÓN I DEL ARTÍCULO\nCALIFORNIA, IMPRÍMASE Y PUBLÍQUESE.\nMEXICALI, BAJA CALIFORNIA, A LOS 31 DÍAS DEL MES DE MARZO DEL AÑO\nDOS MIL VEINTICINCO.\nMARINA DEL PILAR ÁVILA OLMEDA\nGOBERNADORA DEL ESTADO\nDE BAJA CALIFORNIA\n(RÚBRICA)\nALFREDO ÁLVAREZ CÁRDENAS\nSECRETARIO GENERAL DE GOBIERNO\nDEL ESTADO DE BAJA CALIFORNIA\n(RÚBRICA)",
  "ordenamiento": "REGLAMENTO",
  "jurisdiccion": "BAJA CALIFORNIA",
  "fuente_oficial": "Periódico Oficial",
  "FECHA PER OFIC": "2025/04/11",
  "ESTATUS": "VIGENTE",
  "TOMO": "TOMO_II",
  "URL": "https://www.congresobc.gob.mx/Documentos/ProcesoParlamentario/Leyes/TOMO_II/20250411_LEYINGRESOSTECATE2025.PDF",
  "es_escaneado": false,
  "tiene_tablas": true,
  "materia": [
    "financiero",
    "fiscal",
    "económico"
  ]
}