{
  "titulo": "Ley ORGÁNICA DEL PODER EJECUTIVO DEL ESTADO DE BAJA CALIFORNIA",
  "Contenido": "Publicado en el Periódico Oficial Número 99, Número Especial de fecha 06 de\nTÍTULO PRIMERO\nDISPOSICIONES PRELIMINARES\nCAPÍTULO I\nGENERALIDADES\nARTÍCULO 1. La presente Ley es de orden e interés público y de observancia general, y tiene por objeto regular las atribuciones del Poder Ejecutivo, así como establecer las bases de organización y funcionamiento de la Administración Pública del Estado de Baja\nCalifornia.\nARTÍCULO 2. Para los efectos de esta Ley se entiende por:\nI. Administración Pública: Al conjunto de dependencias y entidades que componen la\nAdministración Pública Centralizada y la Paraestatal del Estado de Baja California, jerárquicamente subordinadas a la Persona Titular del Poder Ejecutivo, para auxiliarla en el ejercicio de sus atribuciones y funciones;\nII. Administración Pública Centralizada: Las dependencias y los Órganos\nDesconcentrados;\nIII. Administración Pública Paraestatal: El conjunto de Entidades Paraestatales;\nBaja California;\nVI. Constitución Federal: La Constitución Política de los Estados Unidos Mexicanos;\nVII. Dependencias: Las Secretarías, la Coordinación de Gabinete, la Oficialía Mayor de Gobierno, la Consejería Jurídica, la Dirección del Registro Público de la Propiedad y del\nComercio, la Dirección de Comunicación Social y los órganos desconcentrados;\nVIII. Entidades Paraestatales: Los organismos descentralizados, las empresas de participación estatal mayoritaria y minoritaria y los fideicomisos públicos;\nX. Órgano Desconcentrado: Es la dependencia de la Administración Pública\nCentralizada, que tiene por objeto auxiliar a ésta, en el ejercicio de determinadas funciones, la cual se encuentra administrativamente subordinada, pero cuenta con autonomía técnica en el ejercicio de sus atribuciones;\nXI. Persona Titular del Poder Ejecutivo: La Gobernadora o el Gobernador del Estado de Baja California;\nXII. Poder Ejecutivo: El Poder Ejecutivo del Estado de Baja California cuya titularidad recae en la Gobernadora o el Gobernador del Estado; y,\nXIII. Servicio Público: La actividad técnica atribuida por ley a la Administración\nPública, destinada a satisfacer de manera general, uniforme, regular y continua una necesidad de carácter general, realizada directamente por ésta, o indirectamente a través de particulares, mediante concesión u otro instrumento jurídico.\nARTÍCULO 3. Cuando existan dudas sobre la interpretación y aplicación de esta Ley, así como de los Reglamentos que de ella emanen, o sobre la competencia para conocer de determinado asunto, la Persona Titular del Poder Ejecutivo del Estado por conducto de la titularidad de la Consejería Jurídica resolverá lo conducente.\nARTÍCULO 4. Las dependencias y entidades paraestatales de la Administración\nPública tienen la obligación de promover, respetar, proteger y garantizar los derechos humanos de conformidad con los principios de universalidad, interdependencia, indivisibilidad y progresividad.\nLas personas titulares de las dependencias y entidades paraestatales de la\nAdministración Pública y demás servidores públicos estarán obligadas a:\nI. Observar en su desempeño los principios de legalidad, imparcialidad, profesionalismo, disciplina, eficiencia, eficacia, lealtad, integridad, rendición de cuentas y respeto a la dignidad de las personas, que rigen el servicio público, y\nII. Presentar, bajo protesta de decir verdad, su declaración patrimonial y de intereses determine la ley.\nLos servidores públicos, adicionalmente a lo que dispone la ley de la materia, deberán intervenga, quien resolverá lo conducente en términos de la ley de la materia. de su competencia, determinarán dentro de su organización la unidad de transparencia encargada de recabar y difundir las obligaciones de trasparencia, recibir y tramitar las entre estas y los solicitantes en términos de la ley de la materia; dicha organización administrativa podrá considerar que la unidad de transparencia de la dependencia cabeza de sector realice las funciones anteriores en las entidades paraestatales sectorizadas.\nARTÍCULO 5. Para el cumplimiento y vigilancia de la implementación de la política pública en materia de justicia, combate a la desigualdad social y pobreza, se instalará al inicio de cada administración una Comisión Intersecretarial para su atención.\nAsimismo, se instalará un Comité de Honestidad de la Proveeduría Pública a fin de asegurar que los recursos económicos que se dispongan, se administren con eficiencia, eficacia, economía, transparencia y honradez para satisfacer los objetivos a los que estén destinados.\nDe igual forma se instalará el Consejo de Impacto y Seguimiento de Asuntos\nPrioritarios de la Administración Pública, que tendrá por objeto la elaboración de proyectos, programas, acciones y actividades que resulten prioritarios o relevantes para su ejercicio o el cumplimiento de metas o fines.\nLos entes señalados operarán y se integrarán en los términos de su decreto de creación.\nARTÍCULO 6. La Persona Titular del Poder Ejecutivo y demás titulares de la\nAdministración Pública, deberán:\nI. Observar lo establecido en la Ley General de Comunicación Social, con relación a la difusión de propaganda, así como las políticas públicas que se formulen, y\nII. Incluir en la documentación y en la difusión de sus programas en medios digitales, redes sociales, medios masivos de comunicación y en el portal institucional de internet la leyenda siguiente: “Este programa es público, ajeno a cualquier partido político. Queda prohibido el uso para fines distintos a los establecidos en el programa”.\nARTÍCULO 7. Para garantizar el destino social de bienes asegurados, donados y embargados que ingresen al patrimonio del Estado en los términos de Ley, se contará con el\nInstituto de Administración de Bienes Asegurados para el Bienestar Social, que operará en los términos de su decreto de creación y de la legislación aplicable.\nCAPÍTULO II de las atribuciones, facultades, funciones y obligaciones que le señalan la Constitución\nFederal, la Constitución del Estado y otras disposiciones legales aplicables, tendrá las siguientes:\nI. Expedir las disposiciones reglamentarias de las leyes secundarias locales que lo requieran, así como para proveer en la esfera administrativa al exacto y eficaz cumplimiento de sus atribuciones;\nII. Expedir, en los términos de ley, los decretos, acuerdos, lineamientos, instructivos, circulares y disposiciones de carácter general para el buen desempeño de sus atribuciones;\nIII. Expedir los reglamentos internos que regulen la organización y funcionamiento de las dependencias de la Administración Pública, y la forma en que los titulares podrán ser suplidos en sus ausencias, así como publicar los correspondientes a las entidades paraestatales;\nIV. Expedir los acuerdos de sectorización de las entidades, respecto a las dependencias correspondientes, de acuerdo a la materia de su competencia;\nV. Determinar, expedir y dirigir el diseño y la instrumentación de las políticas públicas que orienten la actividad general de la Administración Pública, procurando su racionalidad y vinculación con los requerimientos y el desarrollo socioeconómico del Estado;\nVI. Crear comisiones intersecretariales, consejos, patronatos, comités, y demás órganos que resulten necesarios para la buena marcha de la Administración Pública, así como organizar los gabinetes que resulten indispensables para el cumplimiento del Plan\nEstatal de Desarrollo y de los programas a su cargo; cuyo funcionamiento y operación se determinará mediante decreto; federativas o, en su caso, en el extranjero, a fin de llevar a cabo las relaciones institucionales que correspondan, incluso las de carácter internacional, en el ámbito de su competencia; cuyo funcionamiento y operación se determinará mediante decreto;\nVIII. Vigilar la aplicación de las políticas de la nueva gestión de gobierno digital, orientada a facilitar la gobernanza, y definir las de gobierno abierto de la Administración\nPública, a fin de transparentar la información de gobierno y los servicios públicos, en términos de las disposiciones aplicables;\nIX. Proponer la creación de organismos que requieran de autonomía para su funcionamiento y que sean necesarios para la prestación de servicios públicos y sociales, en los términos que dispongan las leyes de la materia;\nX. Expedir los decretos de creación, fusión o extinción de las dependencias o entidades paraestatales de la Administración Pública, con excepción de las creadas por ley o por decreto del Congreso del Estado, así como solicitar a este último la creación, fusión o extinción de aquellas creadas por ley o decreto;\nXI. Nombrar y remover libremente a las titularidades de la Administración Pública, y a las y los servidores públicos que forman parte del Poder Ejecutivo, salvo aquellos cuyo nombramiento o remoción sean regulados de manera específica por la Constitución del\nEstado o por otros ordenamientos legales aplicables, y\nXII. Llevar a cabo las relaciones internacionales que correspondan al Poder Ejecutivo.\nARTÍCULO 9. Las facultades que corresponden originalmente a la Persona Titular del\nPoder Ejecutivo podrán delegarse a las personas servidoras públicas subalternas, mediante acuerdos que se publicarán en el Periódico Oficial del Estado para su mayor difusión, excepto aquellas que por disposición jurídica no sean delegables.\nARTÍCULO 10. La Persona Titular del Poder Ejecutivo, podrá celebrar acuerdos, acuerdos interinstitucionales, convenios de coordinación o cooperación y contratos con los gobiernos Federal, Estatales y Municipales, órganos constitucionales autónomos, organismos públicos autónomos, instituciones académicas y científicas, organismos gubernamentales extranjeros u organizaciones internacionales, así ́ como con los ciudadanos, grupos y organizaciones sociales, para la realización de cualquier propósito de beneficio colectivo.\nARTÍCULO 11. Los decretos, reglamentos, acuerdos, circulares y disposiciones de carácter general deberán para su validez ser firmados por la persona titular de la Secretaría\nGeneral de Gobierno y publicados en el Periódico Oficial del Estado. correspondientes a reformas Constitucionales, a las leyes o, a decretos expedidos por el\nCongreso del Estado, para su validez y observancia Constitucional, deberán ser firmados por la persona titular de la Secretaría General de Gobierno o, en sus faltas, por la persona que haga sus veces, de conformidad con la Constitución del Estado.\nTÍTULO SEGUNDO\nDE LA ADMINISTRACIÓN PÚBLICA\nCAPÍTULO I\nDEL DERECHO A UNA BUENA ADMINISTRACIÓN\nPÚBLICA, DE SUS VALORES Y SUS PRINCIPIOS\nARTÍCULO 12. El derecho a una buena administración pública consiste en servir a la ciudadanía, realizar la función con racionalidad, justificar las actuaciones y orientarse continuamente al interés general.\nARTÍCULO 13. En Baja California las personas tienen el derecho a una buena administración pública, cuyo contenido implica:\nI. El trámite imparcial, equitativo y oportuno de sus asuntos, lo que se encamina a que los actos y resoluciones se emitan con objetividad y sin caer en dilación indebida para resolver, a fin que la resolución pueda ser eficaz;\nII. El debido proceso, que se refiere al derecho a ser oído antes que se dicte un acto o resolución;\nIII. El acceso al expediente administrativo, que consiste en poner a disposición del interesado el expediente para conocer de la situación jurídica, respetando la confidencialidad y el secreto profesional;\nIV. La motivación y fundamentación de los actos y resoluciones administrativas, lo que significa que todas las actuaciones deben estar sometidas a la ley y al derecho; y,\nV. La indemnización por los daños en sus derechos o bienes como consecuencia de la actividad administrativa irregular.\nARTÍCULO 14. Los actos y procedimientos de la Administración Pública, respetarán los valores de dignidad, ética, justicia, lealtad, libertad, honestidad y seguridad.\nARTÍCULO 15. La Administración Pública se regirá por los principios de atención ciudadana, simplificación, agilidad, economía, acceso a la información, innovación, precisión, legalidad, transparencia, gobierno abierto, proporcionalidad, buena fe, integridad, plena accesibilidad, debido procedimiento e imparcialidad, austeridad, eficiencia, profesionalización y eficacia.\nCAPÍTULO II\nDE LA ORGANIZACIÓN DE LA ADMINISTRACIÓN PÚBLICA\nARTÍCULO 16. La Administración Pública se organiza en:\nI. Centralizada: Las Secretarías, la Coordinación de Gabinete, la Oficialía Mayor de\nGobierno, la Consejería Jurídica, la Dirección del Registro Público de la Propiedad y del\nComercio, la Dirección de Comunicación Social y los Órganos Desconcentrados; y,\nII. Paraestatal: Los organismos descentralizados; las empresas de participación estatal mayoritaria y minoritaria, y los fideicomisos públicos.\nARTÍCULO 17. Las dependencias y entidades paraestatales de la Administración\nPública, que para su operación y funcionamiento cuenten con órganos colegiados, en casos fortuitos o de fuerza mayor que impidan o hagan inconveniente la presencia física de sus integrantes en un mismo lugar, podrán sesionar a distancia, empleando medios electrónicos, ópticos o cualquier otra tecnología que permita su funcionamiento.\nARTÍCULO 18. La Administración Pública contará con un servicio civil de carrera, que se sujetará a los principios de legalidad, disciplina, objetividad, profesionalismo, honradez, lealtad, imparcialidad, integridad, rendición de cuentas, eficacia y eficiencia, de conformidad con la ley que expida, para este efecto, el Congreso del Estado.\nCAPÍTULO III\nDE LA COORDINACIÓN DE GABINETE\nARTÍCULO 19. La Persona Titular del Poder Ejecutivo contará con la Coordinación de\nGabinete, como órgano responsable de la planeación seguimiento y evaluación permanente de las políticas públicas y los acuerdos, a fin de propiciar el desarrollo de la gestión gubernamental, así como de coordinar las actividades de agenda, representación, protocolo, giras, administración de la oficina de la Persona Titular del Poder Ejecutivo, y el despacho de los asuntos de su competencia, sin perjuicio de las atribuciones que ejercen las dependencias y entidades paraestatales de la Administración Pública en el ámbito de sus respectivas competencias.\nARTÍCULO 20. La Coordinación de Gabinete contará con las unidades de asesoría, de apoyo técnico, de planeación del desarrollo, de coordinación y atribuciones que determine su reglamento, sin perjuicio de las atribuciones que ejercen las dependencias y\nCoordinación de Gabinete.\nARTÍCULO 21. Para el ejercicio de sus funciones corresponderá a la Coordinación de\nGabinete, lo siguiente:\nI. Coordinar la planeación del desarrollo estatal, a través del Sistema Estatal de\nPlaneación del Desarrollo del Estado de Baja California;\nII. Coordinar, vigilar y dar seguimiento al cumplimiento del Plan Estatal de Desarrollo, dependencias y entidades paraestatales de la Administración Pública, y realizar su evaluación; con las titularidades de las dependencias y entidades paraestatales de la Administración\nPública que determine, a fin de definir o evaluar la política de la Administración Pública en asuntos prioritarios, cuando las circunstancias políticas, administrativas o estratégicas del gobierno lo ameriten, o para atender asuntos que sean de competencia concurrente de varias dependencias. Las reuniones serán presididas por la Persona Titular del Poder\nEjecutivo, o por quien designe;\nIV. Vigilar el correcto funcionamiento de la Administración Pública, coordinando a las personas titulares de las dependencias y demás servidores públicos, para garantizar el cumplimiento de las órdenes y acuerdos de la Persona Titular del Poder Ejecutivo;\nV. Formular y proponer a la Persona Titular del Poder Ejecutivo políticas públicas, planes, programas y acciones, generales o para cada ramo o sector;\nVI. Proponer a la Persona Titular del Poder Ejecutivo la organización de la\nAdministración Pública, la creación o eliminación de dependencias y entidades paraestatales de la Administración Pública para lograr la máxima eficacia, eficiencia y austeridad, así como previo acuerdo de la Persona Titular del Poder Ejecutivo, integrar y coordinar los gabinetes, comités y consejos en los que participen las distintas dependencias y entidades paraestatales de la Administración Pública;\nVII. Coordinar el Consejo de Impacto y Seguimiento de Asuntos Prioritarios de la\nAdministración Pública;\nVIII. Derogado.\nFracción Reformada\nFracción Derogada\nIX. Derogado.\nFracción Derogada\nX. Derogado.\nFracción Derogada\nXI. Coordinar y vigilar las actividades y el ejercicio de las atribuciones de las y los asesores especializados en temas jurídicos, técnicos y operativos, asignados a la Persona\nXII. Nombrar y remover libremente a las personas titulares de las unidades administrativas o áreas que le estén subordinadas, así como a las o los demás servidores públicos que correspondan, en los términos de la ley de la materia y el reglamento;\nXIII. Coordinar la programación de reuniones, giras, eventos, acuerdos y audiencias\nXIV. Planear, dirigir y controlar los mecanismos y estrategias de seguridad y ayudantía que sean necesarias para garantizar la seguridad de la Persona Titular del Poder\nEjecutivo en eventos, giras y en el desempeño cotidiano de sus funciones;\nXV. Coordinar la atención y el seguimiento hasta su conclusión a los escritos de petición que realicen las y los ciudadanos de manera pacífica y respetuosa a la Persona\nTitular del Poder Ejecutivo en las diferentes ramas de la Administración Pública, y turnar las mismas a las dependencias y entidades paraestatales de la Administración Pública; y,\nXVI. Las que determinen las leyes, reglamentos y demás disposiciones aplicables.\nEn casos fortuitos o de fuerza mayor que impidan o hagan inconveniente la presencia física de los miembros del gabinete en un mismo lugar, las reuniones podrán celebrarse a distancia, empleando medios electrónicos, ópticos o cualquier otra tecnología que permita su funcionamiento.\nArtículo Reformado\nTÍTULO TERCERO\nDE LA ADMINISTRACIÓN PÚBLICA CENTRALIZADA\nCAPÍTULO I\nDISPOSICIONES GENERALES\nARTÍCULO 22. Las dependencias de la Administración Pública, tienen por objeto competencia, de acuerdo con el ramo correspondiente, y conducirán sus actividades en forma programada, con base en las políticas que para el logro de objetivos y prioridades del\nPlan Estatal de Desarrollo. preeminencia entre ellas.\nARTÍCULO 23. Al frente de cada dependencia habrá una persona titular, quien para el despacho de los asuntos de su competencia se auxiliará de subsecretarías, subconsejerías, direcciones, subdirecciones, jefaturas de departamento, unidades administrativas, y las demás que se requieran, en los términos que establezca el reglamento interno respectivo, el presupuesto de egresos del Estado y otras disposiciones legales aplicables.\nARTÍCULO 24. Corresponde originalmente a las titularidades de las dependencias de la Administración Pública el trámite y resolución de los asuntos de su competencia, mismos que podrán delegar a los funcionarios a que se refiere el artículo anterior cualquiera de sus facultades, excepto aquéllas que por disposición de ley o del reglamento interno respectivo, correspondan ser ejercidas por dichas titularidades.\nARTÍCULO 25. Para ser titular de cualquier dependencia del Poder Ejecutivo, con excepción de la Persona Titular de la Secretaría General de Gobierno cuyos requisitos consigna expresamente la Constitución del Estado, se requiere:\nPárrafo Reformado\nI. Ser ciudadano mexicano;\nII. Ser mayor de veinticinco años;\nIII. Estar en pleno goce y ejercicio de sus derechos, y\nIV. Los que determinen las leyes, reglamentos y demás disposiciones aplicables.\nLas titularidades de las dependencias de la Administración Pública no podrán desempeñar otro puesto, cargo, comisión, empleo público, o de carácter privado que pueda constituir conflicto de interés, salvo aquellos que se desempeñen en instituciones académicas, asociaciones docentes, científicas, culturales, de investigación o de beneficencia, no remunerados.\nArtículo Reformado\nARTÍCULO 26. Al tomar posesión de su cargo, las titularidades de las dependencias de la Administración Pública, deberán levantar un inventario de los bienes recibidos y hacer una relación de los documentos respectivos, debiendo registrar este inventario en la Oficialía\nMayor de Gobierno, quien ordenará la verificación del mismo, de conformidad con la Ley de\nEntrega y Recepción de los Asuntos y Recursos Públicos para el Estado de Baja California.\nARTÍCULO 27. Las titularidades de las diferentes dependencias, sin detrimento de las atribuciones y obligaciones que les correspondan tendrán las siguientes: acuerdo a su competencia;\nII. Fijar, dirigir y controlar las políticas de la dependencia a su cargo, así como programar, coordinar y evaluar en los términos de la legislación aplicable las actividades de las entidades paraestatales del sector que le corresponda;\nIII. Aprobar los programas anuales de la dependencia a su cargo y los de las\nEstatal de Desarrollo;\nIV. Proponer el Anteproyecto de Presupuesto de Egresos de la dependencia a su cargo y de las entidades paraestatales del sector correspondiente, remitiéndolos a la\nSecretaría de Hacienda con la oportunidad que se le solicite;\nV. Someter al Acuerdo de la Persona Titular del Poder Ejecutivo los asuntos encomendados a la dependencia a su cargo y los del sector que le corresponda coordinar;\nVI. Desempeñar las comisiones y tareas que la Persona Titular del Poder Ejecutivo le confiera, manteniéndola informada sobre el desarrollo y ejecución de las mismas;\nVII. Proponer a la Persona Titular del Poder Ejecutivo por conducto de la Consejería\nJurídica, los anteproyectos de leyes, reglamentos, decretos, acuerdos y órdenes sobre los asuntos que competan a la dependencia a su cargo y al sector que le corresponda coordinar;\nVIII. Dar cuenta de manera formal al Congreso del Estado, de la situación que guarda su ramo o el sector correspondiente, en los términos de la Ley de Presupuesto y Ejercicio del Gasto Público del Estado;\nIX. Dar trámite y respuesta formal y puntual, a los puntos de acuerdo o exhortos remitidos por el Congreso del Estado, en un plazo que no exceda de 30 días naturales;\nX. Documentar, compilar y mantener actualizada la información de la dependencia a su cargo, con el objeto de integrar el Informe General que obliga a la Persona Titular del\nEstado; acuerdos interinstitucionales, convenios de coordinación o cooperación o contratos con las autoridades federales, estatales, municipales, órganos constitucionales autónomos, organismos públicos autónomos, entidades federativas, instituciones académicas y científicas, organismos gubernamentales extranjeros u organizaciones internacionales o con particulares, en las materias de su competencia;\nXII. Fomentar y apoyar la realización de programas de colaboración intermunicipales, para promover o ejecutar, según corresponda, proyectos de obras o servicios que incidan en la prevención o solución de problemas comunes a más de un municipio, o que faciliten la convivencia de sus habitantes, y\nXIII. Nombrar y remover libremente a las personas titulares de las unidades administrativas o áreas que le estén subordinadas, así como a las o los demás servidores públicos que correspondan en los términos de las leyes de la materia.\nARTÍCULO 28. Corresponde a la titularidad de cada dependencia de la\nAdministración Pública expedir los manuales de organización, de procedimientos y de servicios al público necesarios para su funcionamiento, los que deberán contener información sobre la estructura orgánica de la dependencia y las funciones de sus unidades administrativas, así como sobre los sistemas de comunicación y coordinación, y los principales procedimientos administrativos que se establezcan.\nLos manuales y demás instrumentos de apoyo administrativo interno, deberán mantenerse permanentemente actualizados.\nLos manuales de organización, procedimientos y de servicios al público deberán estar disponibles para consulta de los usuarios y de las y los servidores públicos, a través del registro electrónico que opere la Secretaría Anticorrupción y Buen Gobierno.\nPárrafo Reformado\nLos manuales de organización deberán publicarse en el Periódico Oficial del Estado.\nArtículo Reformado\nARTÍCULO 29. Para un eficiente, ágil y oportuno estudio, planeación y despacho de los asuntos competencia de la Administración Pública Centralizada la Persona Titular del\nPoder Ejecutivo podrá crear Órganos Desconcentrados, mediante acuerdos y decretos, que serán publicados en el Periódico Oficial del Estado. subordinados a la dependencia de la Administración Pública Centralizada que corresponda, y contarán con autonomía técnica en el ejercicio de sus atribuciones, mismas que se establecerán en los acuerdos, decretos, reglamentos y demás normatividad aplicable. principios de simplificación, transparencia, racionalidad, funcionalidad, eficacia y coordinación.\nCAPÍTULO II\nDE LAS DEPENDENCIAS\nARTÍCULO 30. Para el estudio, planeación, despacho y ejecución de los asuntos de dependencias siguientes:\nI. Secretaría General de Gobierno;\nII. Secretaría de Hacienda;\nIII. Oficialía Mayor de Gobierno;\nIV. Secretaría de Seguridad Ciudadana;\nV. Consejería Jurídica;\nVI. Secretaría de Bienestar;\nVII. Secretaría de Inclusión Social;\nFracción Reformada\nVIII. Secretaría de Educación;\nIX. Secretaría de Salud;\nX. Secretaría de Infraestructura, Desarrollo Urbano y Reordenación Territorial;\nXI. Secretaría de Economía e Innovación;\nXII. Secretaría del Trabajo y Previsión Social;\nXIII. Secretaría de Turismo;\nXIV. Secretaría de Agricultura y Desarrollo Rural;\nFracción Reformada\nXV. Secretaría de Pesca y Acuacultura;\nXVI. Secretaría de Medio Ambiente y Desarrollo Sustentable;\nXVII. Secretaría para el Manejo, Saneamiento y Protección del Agua;\nXVIII. Secretaría Anticorrupción y Buen Gobierno;\nFracción Reformada\nXIX. Secretaría de Cultura;\nXX. Secretaría de las Mujeres;\nFracción Adicionada, recorriéndose las subsecuentes\nXXI. Dirección del Registro Público de la Propiedad y del Comercio; y,\nXXII. Dirección de Comunicación Social.\nArtículo Reformado\nCAPITULO III\nDE LA COMPETENCIA DE LAS DEPENDENCIAS\nARTÍCULO 31. La Secretaría General de Gobierno, además de las atribuciones y obligaciones previstas por la Constitución del Estado, tendrá las siguientes:\nI. Atender la política interior del Estado, así como fortalecer y conducir las relaciones político institucionales con los Poderes Legislativo y Judicial, los Ayuntamientos, los Poderes\nFederales y con los órganos constitucionales autónomos, ejecutando acciones que garanticen la gobernabilidad, la gobernanza, la paz social y el respeto a los derechos humanos;\nII. Autorizar con su firma autógrafa, las reformas constitucionales, leyes y decretos que promulgue el Poder Ejecutivo, en los términos de la fracción I, del artículo 52, de la\nConstitución del Estado;\nIII. Autorizar y tramitar en el Periódico Oficial del Estado, la publicación de reformas constitucionales, leyes, decretos, reglamentos, y demás disposiciones de orden general que deban regir en el Estado;\nIV. Presentar ante el Congreso del Estado las iniciativas de ley y de decreto que envíe la Persona Titular del Poder Ejecutivo y dar seguimiento al desahogo del procedimiento legislativo ante los distintos órganos de aquel, o de aquellas que se presenten por los demás sujetos facultados por la Constitución del Estado, caso en el cual lo hará con base en la opinión que emita la Consejería Jurídica;\nAdministración Pública;\nVII. Fijar y dar a conocer el impacto político-social ante los distintos sectores públicos del Estado;\nVIII. Dirigir el Periódico Oficial del Estado, coordinar y supervisar la emisión de\nIX. Entregar al Congreso del Estado, el informe acerca de la situación que guarda la\nAdministración Pública, a que hace referencia la fracción V, del artículo 49 de la Constitución del Estado;\nX. Conducir las relaciones del Poder Ejecutivo con los partidos políticos, agrupaciones políticas y con organizaciones sociales;\nXI. Tramitar ante el Congreso del Estado, las ratificaciones de las personas titulares de las dependencias que correspondan;\nXII. Coordinar y administrar en el Estado el ejercicio de las atribuciones del Notariado, en términos de la normatividad aplicable;\nXIII. Proponer en el ramo de su competencia, a la persona titular del Poder Ejecutivo del Estado los Notarios Públicos que intervendrán en los actos en los que el Poder Ejecutivo sea parte;\nXIV. Establecer el Sistema Estatal de Protección Civil, y coordinar las acciones y programas del Poder Ejecutivo, relativos a la prevención de desastres, así como ordenar la participación civil en eventos de emergencia, a fin de prevenir, controlar y disminuir los daños materiales y humanos;\nXV. Solicitar, previa autorización de la Persona Titular del Poder Ejecutivo, la natural, así como proponer la aplicación de los fondos federales de desastres naturales en los términos de la normativa aplicable;\nXVI. Expedir permisos y concesiones, previo acuerdo de la Persona Titular del Poder\nEjecutivo, que no estén asignados a otras dependencias de la Administración Pública;\nXVII. Prestar asesoría, emitir opinión, resolver las consultas y coadyuvar en la\nAdministración Pública;\nXVIII. Coordinar, supervisar y evaluar las actividades y resultados de las entidades cuyo sector corresponda coordinar, promoviendo las acciones necesarias para preservar la integridad, estabilidad y permanencia de las instituciones del Estado;\nXIX. Dar seguimiento a las políticas, planes, programas y acciones de gobierno que se vinculen con sus atribuciones, evaluando su impacto político y social, informando a la\nPersona Titular del Poder Ejecutivo de sus resultados;\nXX. Realizar la apostilla o legalización de las firmas de las y los servidores públicos estatales, a quienes esté encomendada la Fe Pública y mantener un registro actualizado de estos;\nXXI. Realizar análisis y prospectiva política para contribuir a la gobernabilidad democrática que dé unidad y cohesión a la gobernanza estatal;\nXXII. Intervenir en el ámbito de su competencia, en auxilio y coordinación con las autoridades federales, en observancia a las disposiciones aplicables en las materias, electoral, agraria, culto religioso, juegos y sorteos, publicaciones y revistas ilustradas, trasmisiones de radio y televisión, películas y espectáculos públicos;\nXXIII. Promover, coadyuvar, coordinar y vigilar el efectivo cumplimiento de las atribuciones y responsabilidades que la Ley de Asociaciones Religiosas y Culto Público le confiere a las autoridades estatales, así ́ como auxiliar en la gestión e impulso de su eficaz cumplimiento ante todas las autoridades competentes en términos de los convenios que al efecto se celebren;\nXXIV. Promover y garantizar la generación de información pública, la rendición de cuentas y la transparencia en materia de derechos humanos;\nXXV. Coordinar, orientar y dar seguimiento, en el ámbito de su competencia, a los compromisos asumidos por el Estado Mexicano en materia de derechos humanos, vinculando acciones de protección, defensa, respeto y capacitación en las diferentes dependencias de la Administración Pública;\nXXVI. Formular y supervisar, en el ámbito de su competencia, la política de prevención, protección y atención para el cumplimiento de una vida libre de violencia por refuercen la igualdad, en coordinación con las dependencias de la Administración Pública, gobiernos municipales, instituciones públicas y privadas, y demás autoridades competentes;\nXXVII. Diseñar e instrumentar programas para la atención integral de víctimas y público y privado, que contribuyan a prevenir y eliminar la discriminación o vulnerabilidad de grupos sociales;\nXXVIII. Dar seguimiento y atención a las recomendaciones que, en materia de derechos humanos, emitan los organismos competentes y, en su caso, dictar las medidas administrativas necesarias para tal efecto;\nXXIX. Coordinar y promover acciones y convenios, en materia de asuntos fronterizos y migratorios, vigilando y coadyuvando en la ejecución y seguimiento de estos, por parte de las dependencias y entidades paraestatales de la Administración Pública competentes; además de intervenir en auxilio y coordinación con las autoridades federales en la asistencia y orientación para la defensa de los derechos humanos de los migrantes en los términos de las leyes aplicables;\nXXX. Gestionar la aportación de recursos económicos y financieros, con arreglo en las leyes de la materia, para la generación de empleo y combate a la pobreza en las comunidades de origen migrante, así como promover la educación cívica de la población del\nEstado, en coordinación con las distintas instituciones públicas y privadas, que promueva una cultura de respeto e integración de la población migrante en el Estado;\nXXXI. Elaborar y mantener actualizada una relación de los migrantes y organizaciones de atención a los mismos en el Estado por medio de un Registro Estatal, así como establecer un sistema de información y estudios, que permitan la identificación de las necesidades del fenómeno migratorio, en coordinación con las autoridades federales y municipales competentes, con la finalidad de facilitar a los migrantes el acceso a los servicios públicos que brinda el Estado;\nXXXII. Coordinar las acciones de la Administración Pública en materia de participación ciudadana, impulsando programas y mecanismos de atención y consulta que permitan captar propuestas y opiniones, que incentiven la participación ciudadana en órganos colegiados, con la finalidad de generar una sociedad participativa y organizada, que contribuyan a mejorar el funcionamiento de los servicios públicos;\nXXXIII. Participar y coordinar, en su caso, las actividades relacionadas con la beneficencia pública y privada;\nXXXIV. Tramitar los asuntos que en materia agraria sean competencia del Estado, en los términos que establezca la ley de la materia, así como atender los asuntos relacionados con las copropiedades rurales;\nXXXV. Promover, apoyar y ejecutar los programas de regularización de la tenencia de la tierra, impulsando la realización de jornadas notariales en apoyo a personas físicas, de conformidad con las bases que se emitan;\nXXXVI. Proporcionar asesoría y orientación a los municipios del Estado que lo soliciten, para la adecuada atención de los asuntos relacionados con la propiedad ejidal, comunal y privada;\nXXXVII. Coadyuvar en la esfera de su competencia con el Registro Agrario Nacional, en la actualización de información inherente a la situación jurídica de la tierra;\nXXXVIII. Coordinar y administrar en el Estado, el ejercicio de las atribuciones del\nRegistro Civil; y,\nXXXIX. Las que determinen las leyes, reglamentos y demás disposiciones aplicables.\nARTÍCULO 32. La Secretaría de Hacienda tendrá las atribuciones y obligaciones siguientes:\nI. Desarrollar la política fiscal y hacendaria estatal, así como coordinar y administrar lo relacionado al presupuesto, ingresos, egresos, gasto público, obligaciones, financiamientos, inversión de los recursos públicos;\nII. Formular y aplicar la política hacendaria, crediticia y del gasto público del Poder\nEjecutivo;\nIII. Proyectar y calcular, los ingresos y egresos del Poder Ejecutivo, tomando en cuenta las necesidades de recursos para la ejecución del Plan Estatal de Desarrollo y sus programas;\nIV. Elaborar los anteproyectos de Ley de Ingresos y Presupuesto de Egresos del\nEstado, conforme a las disposiciones legales de la materia; en materia hacendaria, fiscal, arancelaria o de obligaciones y financiamientos;\nVI. Orientar a las dependencias y entidades paraestatales de la Administración\nPública, para que sus programas y acciones concurran al cumplimiento de los objetivos y metas contenidos en el Plan Estatal de Desarrollo;\nVII. Elaborar con la colaboración de las dependencias y entidades paraestatales de la\nAdministración Pública, que correspondan, las normas y procedimientos de contabilidad gubernamental;\nVIII. Organizar y llevar la contabilidad de la Hacienda Pública Estatal, formular las\nCentralizada, así como coordinar las que corresponda a las entidades paraestatales;\nIX. Revisar y, en su caso, aprobar los programas financieros y crediticios de la\nAdministración Pública, así como administrar la deuda pública del Estado, informando a la\nPersona Titular del Poder Ejecutivo sobre la situación de la misma y, en general, sobre la situación que guardan las finanzas públicas;\nX. Administrar los fondos y valores del Poder Ejecutivo, incluyendo su aplicación, con base en el presupuesto anual de egresos;\nXI. Atender las observaciones que formule el Congreso del Estado de las Cuentas\nPúblicas del Poder Ejecutivo;\nXII. Establecer y mantener el sistema de presupuesto por programas en las dependencias y entidades paraestatales de la Administración Pública;\nXIII. Llevar el ejercicio, control, seguimiento y evaluación del gasto público del Poder\nEjecutivo, de conformidad a las disposiciones legales vigentes, así como efectuar los pagos que deba realizar;\nXIV. Planear, normar, autorizar, evaluar e integrar los programas de inversión de la\nAdministración Pública, y los derivados de convenios o de acciones que con tal fin celebre el\nPoder Ejecutivo con la Federación y los Municipios, así como vigilar la administración y ejercicio de los recursos de los mismos;\nXV. Dictaminar y validar las modificaciones a la estructura orgánica de las dependencias y entidades paraestatales de la Administración Pública;\nXVI. Proporcionar asesoría en materia de planeación, programación, presupuesto, financiamientos, obligaciones, organización administrativa e interpretación y aplicación de las leyes tributarias estatales y federales, que le sea solicitada por las demás dependencias organismos autónomos y por los Ayuntamientos;\nXVII. Emitir, con la colaboración de las dependencias y entidades paraestatales de la\nAdministración Pública, las normas, procedimientos y coordinación de la aplicación de normatividad, lineamientos y criterios referentes a reglamentos internos, manuales administrativos y la contratación de asimilados a salarios y honorarios;\nXVIII. Promover en las dependencias y entidades paraestatales de la Administración\nPública, los programas de modernización administrativa derivados del Plan Estatal de\nDesarrollo; paraestatales de la Administración Pública, e impulsar su disciplina financiera, así como la correcta recaudación y cobro de sus ingresos;\nXX. Cumplir y hacer cumplir las leyes, reglamentos, convenios y demás disposiciones de carácter fiscal;\nXXI. Normar la administración en lo relativo a política hacendaria, fiscal, arancelaria, de financiamientos y obligaciones, gasto público, control de riesgos proyectos e inversión de los recursos públicos, contabilidad gubernamental, así como las relativas al manejo de los fondos del Estado, procurando las mejores condiciones en beneficio del Poder Ejecutivo, controlando y evaluando el ejercicio presupuestal del gasto público de las dependencias y entidades paraestatales de la Administración Pública;\nXXII. Administrar la recaudación de los impuestos, derechos, contribuciones de mejoras, productos y aprovechamientos que le correspondan al Estado con base a las leyes locales o derivado de los convenios de colaboración administrativa en materia fiscal Federal que celebre el Estado con el Gobierno Federal, así como recibir y administrar las participaciones, aportaciones y demás ingresos federales que correspondan al Estado, a través del organismo desconcentrado denominado Servicio de Administración Tributaria del\nEstado de Baja California (SATBC);\nXXIII. Ejercer la representación del Estado, en materia hacendaria, incluyendo del presupuesto, financiamientos y obligaciones, inversión, deuda pública y contabilidad gubernamental, en los juicios que se ventilen ante los tribunales o instancias, cuando tenga interés el Fisco Estatal y el de la Federación, de conformidad con lo dispuesto en la Ley de\nCoordinación Fiscal y convenios suscritos en la materia que tengan vigencia en el Estado;\nXXIV. Emitir las bases para fijar precios, tarifas, tasas y cuotas y demás ingresos por concepto de servicios, enajenación o arrendamiento de bienes sujetos al dominio privado del\nEstado, y cuando correspondan a sus atribuciones que no estén previstas en la Ley de\nIngresos del Estado;\nXXV. Intervenir en el establecimiento de criterios y montos de los subsidios y estímulos fiscales, en coordinación con las dependencias de la Administración Pública a quien corresponda el fomento de las actividades productivas;\nXXVI. Ejercer directamente cuando así se considere las atribuciones que se confieran al Servicio de Administración Tributaria del Estado de Baja California (SAT BC), incluyendo\nXXVII. Establecer las bases para el monitoreo, control y administración de riesgos en las finanzas de la Administración Pública, así como para la instrumentación de acciones preventivas y correctivas que mitiguen y, en su caso, eviten impactos negativos en la hacienda pública estatal;\nXXVIII. Cobrar y verificar el debido cumplimiento, directamente o a través del Servicio de Administración Tributaria del Estado de Baja California (SAT BC), de las contribuciones y demás ingresos que tienen derecho a percibir las entidades paraestatales de la\nAdministración Pública por cualquier concepto, en los términos de los convenios que se celebren para tal efecto;\nXXIX. Organizar, operar y administrar los censos y registros de identificación vehicular, que en su caso se requieran;\nFracción Reformada\nXXX. Fijar y ejecutar en el ámbito de su competencia, las normas, políticas, lineamientos y criterios técnicos en materia de tecnología de la información y telecomunicaciones, a que deberá sujetarse para el mejor desempeño y cumplimiento de sus atribuciones, en los términos de la presente Ley y el reglamento interno correspondiente; y,\nXXXI. Las que determinen las leyes, reglamentos y demás disposiciones aplicables.\nLa Secretaría de Hacienda ejercerá por conducto de la unidad administrativa que determine su Reglamento Interno, facultades y atribuciones relacionadas con la modernización, innovación, fortalecimiento, regulación, dictaminación, soporte y transformación digital de las tecnologías de la información y de la red de telecomunicaciones inherentes a las funciones y servicios a su cargo.\nLa Secretaría de Hacienda contará con un organismo desconcentrado denominado\nServicio de Administración Tributaria del Estado de Baja California, quien tendrá a su cargo la recaudación, cobro y verificación del debido cumplimiento de las disposiciones fiscales, respecto de los impuestos, derechos, contribuciones de mejoras, productos y, favor en esta ley, la Ley del Servicio de Administración Tributaria del Estado de Baja\nCalifornia, el Reglamento Interior del Servicio de Administración Tributaria del Estado de\nBaja California, y demás disposiciones fiscales.\nArtículo Reformado\nARTÍCULO 33. La Oficialía Mayor de Gobierno tendrá las atribuciones y obligaciones siguientes:\nI. Administrar los recursos humanos y materiales de la Administración Pública, así como encargarse de la protección, resguardo y administración de los bienes del Estado;\nII. Formular y establecer las políticas, normas, procedimientos, programas y funciones vinculados con la administración de los recursos humanos de la Administración Pública, así como el manejo de su personal, los recursos materiales, y los bienes muebles e inmuebles del Poder Ejecutivo del Gobierno del Estado;\nIII. Apoyar a las dependencias y entidades paraestatales de la Administración Pública en la formulación de sus instrumentos normativos de carácter administrativo, y mantenerlos actualizados;\nIV. Elaborar con la colaboración de las dependencias y entidades paraestatales de la\nAdministración Pública, las normas, procedimientos y coordinación de la aplicación de normatividad, lineamientos y criterios referentes a las retenciones de impuestos por pagos de nóminas, asimilados a salarios, honorarios y arrendamientos;\nV. Normar y emitir los criterios y lineamientos sobre el reclutamiento, selección, contratación, inducción, baja y retiro del personal adscrito a la Administración Pública;\nVI. Seleccionar y contratar al personal de la Administración Pública, así como tramitar y registrar en coordinación con la dependencia correspondiente los nombramientos, promociones, licencias, jubilaciones y pensiones, y vigilar el cumplimiento de las disposiciones legales estatutarias que rijan las relaciones con los trabajadores;\nVII. Establecer y actualizar las políticas, normas y procedimientos para la proyección, integración organización, administración y funcionamiento del servicio civil de carrera, así como otorgar los estímulos, recompensas y escalafón para el personal de la Administración\nPública Centralizada, conforme a las disposiciones legales de la materia;\nVIII. Diseñar y establecer el sistema de movimientos e incidencias de personal, así como efectuar los trámites correspondientes;\nIX. Capacitar y establecer las normas de control y disciplina del personal de la\nAdministración Pública;\nX. Autorizar las compatibilidades de las y los servidores públicos para que puedan desempeñar más de un empleo, cargo o comisión, conforme a la ley de la materia;\nXI. Orientar a las entidades paraestatales acerca de las normas y políticas del Poder\nEjecutivo, en materia de administración y desarrollo del personal, adquisición y conservación de bienes;\nXII. Establecer y presidir el Comité de Adquisiciones, Arrendamiento y Servicios, con atribuciones para conocer de las adquisiciones, arrendamientos y servicios que deban adjudicarse o contratarse en los términos señalados en la Ley de Adquisiciones, Arrendamientos y Servicios para el Estado de Baja California y su reglamento;\nXIII. Fijar, regular y emitir a través del Comité de Adquisiciones, Arrendamiento y\nServicios, los criterios y lineamientos en materia de adquisiciones, arrendamientos, suministro, registro, almacenamiento y mantenimiento de bienes y servicios, materiales logísticos e informáticos necesarios para el cumplimiento de los objetivos de la\nAdministración Pública;\nXIV. Emitir los dictámenes que requieran las dependencias o entidades paraestatales de la Administración Pública relacionados con programas de capacitación, adquisición, arrendamientos y adquisición de servicios proporcionados por terceros, en los términos de la\nLey de Adquisiciones, Arrendamientos y Servicios para el Estado de Baja California y su reglamento;\nXV. Normar y controlar los procesos para la proveeduría de los bienes y servicios que requiera la Administración Pública, para el cumplimiento de sus objetivos bajo un esquema de transparencia y adecuada supervisión;\nXVI. Formar parte de los Órganos de Gobierno de las entidades paraestatales de la\nAdministración Pública;\nXVII. Formular y establecer las políticas, normas, procedimientos y programas para el manejo de los recursos materiales y bienes muebles e inmuebles del Poder Ejecutivo del\nGobierno del Estado;\nXVIII. Normar y mantener actualizado, el sistema de control de almacenes generales, así como establecer los lineamientos y procedimientos para su control y vigilancia;\nXIX. Registrar y resguardar los bienes muebles e inmuebles propiedad del Poder\nEjecutivo del Gobierno Estado y, en su caso, ejercer las acciones correspondientes, haciendo valer las excepciones y defensas legales que correspondan, así como las demás medidas previstas en la Ley General de Bienes del Estado para la obtención, conservación o recuperación de los mismos;\nXX. Normar, administrar y mantener actualizado el Padrón de Proveedores de Bienes y Servicios de la Administración Pública, en los términos de lo previsto en la Ley de\nAdquisiciones, Arrendamientos y Servicios para el Estado de Baja California;\nXXI. Administrar y verificar el mantenimiento a los bienes muebles e inmuebles del inventario de los mismos;\nXXII. Participar en el ámbito de su competencia y en coordinación con la dependencia competente en la integración, organización y funcionamiento de comités ciudadanos de vigilancia, obras públicas y licitaciones;\nXXIII. Administrar el Archivo del Poder Ejecutivo, así como coordinar las unidades de correspondencia y el Archivo General del Poder Ejecutivo del Gobierno del Estado;\nXXIV. Tramitar el pago de proyectos de inversión y de adquisiciones y servicios de la\nAdministración Pública Centralizada;\nXXV. Dar seguimiento a las políticas lineamientos y criterios técnicos en materia de tecnologías de informática y de las telecomunicaciones a que deberán sujetarse las dependencias y entidades paraestatales de la Administración Pública y asegurar su cumplimiento;\nFracción Reformada\nXXVI. Conducir y supervisar la ejecución de la política pública de Mejora Regulatoria del Estado, así como las acciones que corresponden en esta materia al Poder Ejecutivo a fin de promover la mejora de las regulaciones y la simplificación de trámites y servicios, así como la transparencia en la elaboración y aplicación de estos;\nFracción Adicionada\nXXVII. Dar seguimiento a los resultados en materia de gestión de datos, gobierno abierto, gobierno digital y gobernanza tecnológica;\nFracción Adicionada\nXXVIII. Definir la estrategia de crecimiento, administración y operación de la red estatal de telecomunicaciones y las redes particulares de las dependencias y entidades paraestatales de la Administración Pública integradas a éstas, asegurando el desarrollo ordenado de la infraestructura de cómputo y telecomunicaciones del Poder Ejecutivo; así como operar y administrar, la red estatal de datos y las redes particulares de las dependencias y entidades paraestatales de la Administración pública que así lo soliciten; y,\nFracción Adicionada\nXXIX. Las que determinen las leyes, reglamentos y demás disposiciones aplicables.\nFracción Recorrida\nLas atribuciones a que se refieren las fracciones XXV, XXVI, XXVII y XXVIII del presente artículo, se realizarán por conducto del órgano desconcentrado que se determine para esos efectos en la ley o decreto correspondiente.\nPárrafo Adicionado\nArtículo Reformado\nARTÍCULO 34. La Secretaría de Seguridad Ciudadana tendrá las atribuciones y obligaciones siguientes:\nPública, en los términos que corresponda;\nII. Coordinar al Consejo Estatal de Seguridad Ciudadana en los términos de ley;\nIII. Formular e instrumentar políticas públicas, planes, programas, estrategias y acciones que comprendan la prevención especial y general de los delitos y de las violencias en lo general, con un enfoque plural, diferenciado, con perspectiva de género, y en un marco de respeto a los derechos humanos;\nIV. Proponer al seno del Consejo Estatal de Seguridad Ciudadana, políticas, acciones y estrategias de coordinación en materia de prevención del delito y las violencias, y de política criminal en el Estado;\nV. Coadyuvar en la formulación de propuestas a la Persona Titular del Poder\nEjecutivo para la elaboración del Programa Estatal de Seguridad Ciudadana;\nVI. Establecer mecanismos para la coordinación entre las instituciones de seguridad y policiales, así como para el análisis y sistematización de investigaciones y el procesamiento de información de seguridad en el marco del Sistema Nacional de Seguridad;\nVII. Coordinar con la Federación y los Municipios, aspectos inherentes a la seguridad y aquellos que sean necesarios para mantener la paz y el orden público en el Estado;\nVIII. Realizar la inteligencia preventiva para la prevención especial y general de los delitos y de las violencias y, en general, aplicar la inteligencia para el desarrollo institucional;\nIX. Participar y coadyuvar en la investigación de los delitos en términos de la\nConstitución Federal, la Ley General del Sistema Nacional de Seguridad Pública, el Código\nNacional de Procedimientos Penales, la Ley de Seguridad estatal que corresponda, los acuerdos institucionales y demás normatividad aplicable;\nX. Integrar y administrar el Centro Estatal de Inteligencia Preventiva, en términos de la ley;\nXI. Establecer un sistema destinado a obtener, analizar, estudiar y procesar antisociales con el propósito de entenderlas, medirlas y de aplicar estrategias y programas para la prevención del delito y las violencias, mediante métodos que garanticen el respeto a los derechos humanos;\nXII. Coordinar, operar e impulsar la mejora continua del sistema de información, reportes y registro de datos en materia delictiva;\nXIII. Implementar y administrar los sistemas y políticas de inteligencia para dar servicio y soporte a las acciones de prevención, protección ciudadana, de inteligencia preventiva o de los delitos según corresponda, de conformidad con la normatividad aplicable;\nXIV. Efectuar en coordinación con la Fiscalía General del Estado estudios sobre hechos delictivos denunciados y no denunciados, para el diseño de las políticas en materia de prevención del delito y de las violencias;\nXV. Desarrollar las políticas, normas y sistemas para el suministro permanente o intercambio de información, en materia de seguridad entre las autoridades competentes;\nXVI. Solicitar y recibir de las autoridades federales, estatales y municipales, organismos no gubernamentales y particulares, la información de seguridad, así como del ámbito criminal y preventivo que requiera para el adecuado cumplimiento de las atribuciones que las leyes establezcan;\nXVII. Fomentar la capacitación y actualización de su personal adscrito, así como la especialización que la normatividad establezca;\nXVIII. Organizar, dirigir, administrar a la institución policial estatal a cargo de la prevención del delito y las violencias; así como la policía encargada de la vigilancia, seguridad y custodia en materia penitenciaria, ejecución de sanciones y medidas judiciales;\nXIX. Implementar el Servicio Profesional de Carrera Policial que defina los procedimientos de reclutamiento, selección, ingreso, formación, certificación, permanencia, evaluación, promoción, reconocimiento, adscripción, movilidad y conclusión;\nXX. Organizar, dirigir, supervisar y administrar el Instituto de Estudios de Prevención y\nFormación Interdisciplinaria y, en su caso, impartir estudios de nivel medio y superior a los interesados en incorporarse al Servicio Profesional de Carrera Policial, o aquellos que deseen continuar con su profesionalización, a través del órgano que se determine para esos efectos;\nXXI. Implementar, operar y administrar los procesos de evaluación, de control de confianza y de certificación, de los integrantes de las Instituciones de Seguridad Ciudadana del Estado, en los términos de las disposiciones aplicables;\nXXII. Suscribir acuerdos con las autoridades federales, estatales, municipales, órganos constitucionales autónomos, organismos públicos autónomos, entidades federativas, instituciones académicas y científicas, organismos gubernamentales extranjeros u organizaciones internacionales o con particulares, que contribuyan a mejorar las condiciones para la consecución de los propósitos de la seguridad ciudadana;\nXXIII. Supervisar las políticas y debida administración de los fondos destinados a la seguridad social para los integrantes de las instituciones de seguridad ciudadana en el\nEstado;\nXXIV. Cumplir en el ámbito de su competencia, con las leyes generales en materia de atención a víctimas y de acceso a las mujeres a una vida libre de violencia;\nXXV. Se deroga.\nFracción Derogada\nXXVI. Se deroga.\nFracción Derogada\nXXVII. Implementar y ejecutar procedimientos sencillos y expeditos para atender las denuncias y quejas que presenten los particulares con relación al ejercicio de sus atribuciones o por posibles actos ilícitos de las o los servidores públicos que la conforman y, en su caso, determinar lo correspondiente;\nXXVIII. Elaborar en coordinación con las distintas instancias públicas, los estudios, estadísticas e investigaciones sobre las funciones y materias de su competencia, sistematizar las cifras y datos y determinar las condiciones sobre su manejo y acceso;\nXXIX. Prestar apoyo a las autoridades jurisdiccionales que lo requieran, para el ejercicio de sus atribuciones;\nXXX. Diseñar, conducir, coordinar y evaluar la política de reinserción social en el\nEstado, de conformidad con la normatividad aplicable;\nXXXI. Organizar, administrar y operar el Sistema Estatal Penitenciario, así como los centros de internamiento para adolescentes en el Estado, sobre la base del respeto a los derechos humanos, del trabajo, la capacitación para el mismo, la educación, la salud y el deporte como medios para lograr la reinserción social; judiciales, de las personas sujetas a prisión preventiva o que se encuentren en proceso;\nXXXIII. Ejecutar las penas por delitos del orden común, y coadyuvar en las del fuero federal, en términos de la ley de la materia, así como coordinar y evaluar las funciones de los servicios postpenales, asistencia a preliberados, o a los que deban cumplir algún sustitutivo penal en el seno social, procurando su eficaz y pronta reinserción social;\nXXXIV. Organizar y dirigir las actividades relativas a la supervisión de medidas cautelares y suspensión condicional al proceso, de conformidad con la normativa aplicable y en coordinación con las autoridades competentes;\nXXXV. Conformar y administrar los registros y bases de datos de las personas privadas de la libertad que ingresen a los centros de reinserción social, y centros de internamiento para adolescentes, en los términos establecidos en la Ley Nacional de\nEjecución Penal, y la Ley Nacional del Sistema lntegral de Justicia Penal para Adolescentes, respectivamente, y demás normatividad aplicable;\nXXXVI. Expedir las constancias de antecedentes penales que soliciten las autoridades competentes y de no antecedentes penales a solicitud de la persona interesada, de conformidad con las disposiciones aplicables;\nXXXVII. Expedir las normas que regulen las actividades productivas no remuneradas para fines de reinserción social a cargo de terceros, a efecto de que se cumplan las prestaciones y servicios de seguridad social, con base en la legislación de la materia, así como para regular el acceso a servicios o productos básicos de las personas privadas de su libertad;\nXXXVIII. Establecer mecanismos y procedimientos eficaces que fomenten la participación ciudadana, para que coadyuven en la realización de programas y acciones tendientes a prevenir el delito y las violencias, analizando las causas que los originan, así como en la evaluación de las políticas de seguridad ciudadana, en los términos de las disposiciones aplicables;\nXXXIX. Fomentar en coordinación con la Secretaría de Salud del Estado, y demás dependencias y entidades del mismo, la participación ciudadana en la realización y adicción, a fin de prevenir conductas antisociales y delictivas;\nXL. Ejecutar las acciones dirigidas a salvaguardar la integridad y patrimonio de las personas, así como preservar las libertades, el orden y la paz públicos;\nXLI. Intervenir en el ámbito de su competencia, en auxilio y coordinación con las autoridades federales, en observancia a las disposiciones aplicables en las materias de combate a los delitos del orden federal;\nXLII. Establecer las características de la identificación oficial de sus servidoras o servidores públicos;\nXLIII. Autorizar, regular, evaluar, controlar, supervisar y registrar la prestación de los servicios de seguridad privada en el Estado, conforme a las disposiciones aplicables, y\nXLIV. Las que determinen las leyes, reglamentos y demás disposiciones aplicables y de forma específica los ordenamientos que le rijan.\nArtículo Reformado\nARTICULO 35. La Consejería Jurídica tendrá las atribuciones y obligaciones siguientes:\nI. Proporcionar asesoría jurídica a la Persona Titular del Poder Ejecutivo y, en su caso, atender las consultas que en materia jurídica le sean planteadas por las titularidades de las dependencias y entidades paraestatales de la Administración Pública;\nII. Brindar apoyo técnico jurídico en la elaboración de iniciativas de ley y de decreto que deban ser enviadas al Congreso del Estado, sus modificaciones o reservas, así ́como de los decretos, reglamentos, acuerdos, convenios y demás instrumentos que la Persona Titular del Poder Ejecutivo considere necesarios;\nIII. Revisar y opinar los proyectos de normas que se remitan a la Persona Titular del\nPoder Ejecutivo, elaborados por las titularidades de las dependencias y entidades paraestatales de la Administración Pública;\nIV. Asistir y elaborar por instrucción de la Persona Titular del Poder Ejecutivo, las observaciones que ésta juzgue conveniente hacer a un proyecto legislativo aprobado por el\nCongreso del Estado y, en su caso, dar el seguimiento correspondiente;\nV. Validar y rubricar los instrumentos jurídicos, relativos a la Administración Pública o de actos jurídicos que celebre el Estado con la intervención de la Persona Titular del Poder\nEjecutivo previo a su firma;\nVI. Opinar y validar sobre los proyectos de acuerdos, acuerdos interinstitucionales, dependencias y entidades paraestatales de la Administración Pública con la Federación, Estados, Municipios, órganos constitucionales autónomos, organismos públicos autónomos, instituciones académicas y científicas, organismos gubernamentales extranjeros u organizaciones internacionales, así como con las personas físicas o morales; la Subconsejería Jurídica; patrimonio o tenga interés jurídico; juicios o controversias de carácter administrativo, agrario, civil, electoral, laboral y penal, en que intervenga, sea parte, tenga interés jurídico o que afecte su patrimonio, pudiendo nombrar, designar, autorizar o revocar para que actúen dentro de los mismos a delegados, profesionistas y apoderados conforme las normas aplicables lo establezcan;\nX. Ejercer la representación legal del Gobierno del Estado, en el ámbito que corresponde al Poder Ejecutivo de conformidad con el artículo 73 de la Constitución del\nEstado, por sí o por conducto de la Subconsejería Jurídica, en todos los negocios, juicios o controversias de carácter administrativo, constitucional, agrario, civil, electoral, laboral y penal, en que intervenga, sea parte, tenga interés jurídico o que afecte su patrimonio, pudiendo nombrar, designar y/o autorizar para que actúen dentro de los mismos a delegados, profesionistas y apoderados conforme la normatividad aplicable lo prevea;\nXI. Asistir y ejercer la representación legal del Poder Ejecutivo del Gobierno del\nEstado y de la Persona Titular del Poder Ejecutivo, en las acciones y controversias constitucionales a que se refieren las fracciones I y II del artículo 105 de la Constitución\nFederal y su ley reglamentaria;\nXII. Participar por sí o por conducto de la Subconsejería Jurídica como coadyuvante en los juicios o negocios en que las dependencias y entidades paraestatales de la\nAdministración Pública intervengan con cualquier carácter, para ejercer las acciones y excepciones que correspondan a la defensa administrativa y judicial, cuando así se solicite y a su consideración se justifique la trascendencia para la Administración Pública;\nXIII. Atraer para su análisis y/o atención aquellos asuntos, negocios, juicios o controversias en los que intervengan o sean parte alguna de las dependencias o entidades paraestatales de la Administración Pública, cuando por su cuantía o trascendencia el resultado pudiese llegar a afectar el orden público o el patrimonio estatal;\nXIV. Coordinar la actuación de las áreas responsables del apoyo jurídico de las procedimientos jurídico administrativos, cuando se estime necesario para una adecuada\nXV. Requerir informes sobre cualquier asunto a las personas titulares de las áreas\nAdministración Pública, cuando se estime necesario para una adecuada defensa de los\nXVI. Emitir criterios que deberán observar las dependencias y entidades paraestatales de la Administración Pública en la elaboración de iniciativas de ley, decretos, reglamentos, acuerdos, convenios y demás instrumentos, así como para la atención de procedimientos legales;\nXVII. Vigilar, coordinar y observar la constitucionalidad y legalidad de los proyectos de iniciativas de leyes, decretos y reglamentos, que formulen las dependencias y entidades paraestatales de la Administración Pública;\nXVIII. Revisar nombramientos, resoluciones y demás instrumentos de carácter jurídico de la Persona Titular del Poder Ejecutivo, a efecto de someterlos a su consideración y, en su caso, a su firma;\nXIX. Vigilar la observancia de la Constitución Federal, la Constitución del Estado, las leyes, decretos, acuerdos, reglamentos, circulares y demás disposiciones, dictando las medidas necesarias de carácter administrativo para su debido cumplimiento;\nXX. Emitir opinión jurídica cuando se le solicite respecto a la atención a las recomendaciones públicas e informes que le formulen los organismos de protección de los derechos humanos, así como en su caso sobre las denuncias y quejas por probables violaciones a los derechos humanos que involucren a las dependencias y entidades paraestatales de la Administración Pública o a las o los servidores públicos que las integren;\nXXI. Emitir opinión previo al nombramiento y, en su caso, solicitar la remoción de las titularidades de las áreas responsables del apoyo jurídico y de la aplicación de procedimientos jurídico administrativos de las dependencias y entidades paraestatales de la\nAdministración Pública;\nXXII. Analizar y, en su caso, validar previamente la contratación de servicios de la Administración Pública;\nXXIII. Conocer y emitir opinión jurídica de contratos de adquisiciones de bienes y\nPública, cuando así se solicite;\nXXIV. Convenir la conclusión de asuntos por convenio judicial o extrajudicial, como las entidades paraestatales de la Administración Pública, en su caso, se encuentren debidamente satisfechos y protegidos;\nXXV. Elaborar los proyectos de decreto en materia de expropiación, ocupación temporal y limitación de dominio, en los casos de utilidad pública de acuerdo con la\nEjecutivo;\nXXVI. Vincularse con las áreas jurídicas de otros poderes u órdenes de gobierno, así como demás autoridades públicas u organismos privados o particulares;\nXXVII. Intervenir y dar seguimiento en el ámbito de su competencia y en coordinación con la dependencia correspondiente a las recomendaciones que formule el Comité\nCoordinador del Sistema Estatal Anticorrupción a las dependencias y entidades paraestatales de la Administración Pública; así como dar seguimiento a las quejas o denuncias por actos de corrupción que involucren a éstas o a las o los servidores públicos que las integren;\nXXVIII. Dar seguimiento y, en su caso, impulsar el mejoramiento y ampliación de la adopción de la justicia penal adversarial y oral en el Estado;\nXXIX. Impulsar y dar seguimiento, en coordinación con la Secretaría del Trabajo y\nPrevisión Social, a la implementación del nuevo sistema de justicia laboral, en el ámbito de su competencia;\nXXX. Coadyuvar con las autoridades jurisdiccionales que lo requieran, para el ejercicio de sus atribuciones;\nXXXI. Dirigir, organizar, administrar y evaluar la defensoría pública, así como prestar los servicios de orientación y asistencia jurídica en las materias que establezcan las leyes;\nXXXII. Presidir la Comisión de Estudios Jurídicos cuyo objeto es la coordinación en materia jurídica de las dependencias y entidades paraestatales de la Administración Pública para elaboración de propuestas de emisión de criterios a efecto de uniformar la interpretación de las disposiciones que rigen la Administración Pública, así como de funcionamiento y actividad de aquella; la cual estará integrada por las titularidades de las áreas jurídicas de las dependencias y entidades paraestatales de la Administración Pública; sentenciadas por delitos de competencia de los Tribunales del Fuero Común;\nXXXIV. Certificar, en la esfera de sus atribuciones, los documentos expedidos por la que le estén adscritos en el desempeño de sus funciones; y,\nXXXV. Las que determinen las leyes, reglamentos y demás disposiciones aplicables.\nARTÍCULO 36. La Secretaría de Bienestar, tendrá las atribuciones y obligaciones siguientes:\nI. Coordinar, ejecutar políticas públicas, estrategias y acciones que fortalezcan e impulsen el bienestar, el desarrollo y la cohesión social de la población del Estado;\nII. Impulsar la creación de programas, organismos y fondos necesarios para el combate efectivo a la pobreza en apego a la política nacional y estatal, así como dar seguimiento a los lineamientos y criterios que emita la instancia federal correspondiente respecto a la definición, identificación y medición de la pobreza y, en su caso, utilizar la información que se genere para la formulación de políticas públicas encaminadas a su disminución;\nIII. Formular, coordinar, evaluar y ejecutar la política estatal de bienestar y prosperidad social para el combate efectivo a la pobreza y atención a los sectores sociales más desprotegidos, mediante programas de integración, desarrollo y bienestar en materia de población, salud, vivienda, servicios públicos, educación, cultura, deporte y desarrollo humano con base en la legislación federal y estatal;\nIV. Elaborar diagnósticos en coordinación con las dependencias y entidades paraestatales de la Administración Pública, Ayuntamientos y comités vecinales impulsores de la transformación, sobre la situación que presentan las comunidades marginadas, en áreas urbanas y rurales, para formular, promover e implementar programas sociales de carácter transversal;\nV. Establecer las bases y criterios que deberán observar las dependencias y entidades paraestatales de la Administración Pública, para la creación e implementación de programas o acciones de integración y bienestar social que fomenten un mejor nivel de vida;\nVI. Solicitar a la Secretaría de Hacienda, la expedición de los lineamientos compromisos contenidos en el Programa Sectorial de Integración y Bienestar Social;\nVII. Evaluar y dar seguimiento a los resultados del Programa Sectorial de Integración y Bienestar Social, así como a los programas y proyectos de la Administración Pública\nEstatal y Federal, y organismos internacionales que incidan en la integración y bienestar de la población del Estado; ejecución de acciones y proyectos que coadyuven al bienestar social, comunitario y familiar, impacto en el Estado;\nIX. Gestionar la obtención de recursos económicos, materiales e intelectuales del sector público o privado, así como de organismos nacionales e internacionales, para el desarrollo e implementación de programas de integración y bienestar social, para el mejoramiento de la economía familiar y social, creando mecanismos de coordinación institucional con instancias del gobierno Federal, Estatal y Municipal;\nX. Coordinar, administrar y regular los fondos o fideicomisos destinados a la infraestructura social, para la integración y el bienestar social de la población, que promueva el desarrollo integral de la misma;\nXI. Fomentar la participación de instituciones académicas, de investigación, organizaciones no gubernamentales y de la sociedad en general en el desarrollo e instrumentación de estrategias para el combate efectivo a la pobreza e impulsar el bienestar social de la población;\nXII. Fomentar la creación y organización de comités vecinales como impulsores de la transformación de la población organizada, para la gestión de la participación ciudadana en la implementación de proyectos y programas que contribuyan a la solución de problemas comunitarios en barrios, colonias, fraccionamientos y comunidades rurales;\nXIII. Coordinar, implementar y ejecutar programas especiales y proyectos productivos para la atención de los sectores sociales más desprotegidos que permitan el mejoramiento y fortalecimiento de la calidad de vida de los ciudadanos, familias o grupos sociales en situación de vulnerabilidad o en zonas de mayor marginación;\nXIV. Promover la realización de acciones y construcción de obra de infraestructura y equipamiento para el desarrollo comunitario y el bienestar social, por sí o en coordinación con los gobiernos Federal y Municipal;\nXV. Implementar en coordinación con la dependencia de la Administración Pública que corresponda, acciones y programas para la recuperación de espacios públicos para el desarrollo comunitario y el bienestar social de las familias del Estado;\nXVI. Impulsar en coordinación con la dependencia de la Administración Pública que corresponda, políticas y programas para la rehabilitación, ampliación de vivienda, y apoyo de material de construcción, a fin de contribuir al bienestar social de las familias del Estado;\nXVII. Impulsar políticas y programas de protección de derechos y atención prioritaria a la niñez, juventudes, adultos mayores, mujeres en situación vulnerable, y personas en situación de marginalidad, así como impulsar políticas públicas y dar seguimiento a los programas de apoyo e inclusión de las juventudes a la vida social participativa y productiva, Pública, así como de los diferentes órdenes de gobierno;\nXVIII. Impulsar y fomentar políticas públicas, programas, proyectos productivos, capacitación y adiestramiento, para la atención de los adultos mayores, mujeres, personas con discapacidad, juventudes y grupos marginados o con rezago socioeconómico en el\nEstado;\nXIX. Articular, en coordinación con las dependencias y entidades paraestatales de la\nAdministración Pública, programas, proyectos y acciones tendientes a la prevención social del delito y de las violencias, instrumentando las medidas necesarias para su implementación;\nXX. Impulsar a través del Sistema Estatal de Asistencia Social Pública y Privada, políticas públicas en materia de asistencia social e integración familiar;\nXXI. Contribuir en el mejoramiento de la calidad de vida y nutrición de las familias y de la infancia, que habitan prioritariamente en zonas marginadas y desprotegidas;\nXXII. Coordinar sectorialmente a los organismos públicos constituidos como instituciones financieras de inversión o descentralizados, para la promoción y fomento de la vivienda de interés social y popular en el Estado;\nXXIII. Crear, coordinar y administrar los centros comunitarios y escuelas de artes y oficios, como herramientas elementales para consolidar la integración social, con especial énfasis en zonas indígenas, rurales y urbanas marginadas;\nXXIV. Coordinar e instrumentar la operación de las unidades móviles de servicios comunitarios, de conformidad con lo establecido por la política de integración y bienestar social del Estado;\nXXV. Coordinar e impulsar acciones tendientes a organizar y apoyar las actividades de bienestar social y asistencia que realicen los particulares, grupos intermedios y organismos no gubernamentales que actúan en el Estado;\nXXVI. Establecer, integrar y mantener actualizado el Registro Estatal de Organismos no gubernamentales;\nXXVII. Coordinar el Sistema Estatal de Asistencia Social Pública, y el Sistema Estatal de Bienestar Social del Estado, en los términos de las leyes aplicables;\nXXVIII. Promover, coordinar, fomentar y dirigir la enseñanza y práctica del deporte social y comunitario en los municipios del Estado, sin distinción de género, edad, discapacidad, condición social, religión, opiniones, preferencias o estado civil;\nXXIX. Impulsar programas para promover la corresponsabilidad de manera equitativa entre las familias, el Estado y las instituciones de asistencia social y privada, para el cuidado de la niñez y de los grupos vulnerables;\nXXX. Integrar, mantener y actualizar un sistema de información de padrones de beneficiarios de programas sociales de la Administración Pública;\nXXXI. Formular e instrumentar la política estatal de atención a las juventudes y al deporte social y comunitario, acorde con los objetivos, estrategias y líneas de acción contenidos en el Plan Estatal de Desarrollo;\nXXXII. Coordinar, supervisar y evaluar las actividades y resultados de las entidades paraestatales de la Administración Pública que le estén sectorizadas, promoviendo las acciones necesarias para preservar la integridad, estabilidad y permanencia de las instituciones del Estado;\nXXXIII. Impulsar programas en apoyo a los organismos de la sociedad civil, así como administrar y mantener actualizado el Catálogo Estatal de los mismos; y,\nXXXIV. Las que determinen las leyes, reglamentos y demás disposiciones aplicables.\nARTÍCULO 37. La Secretaría de Inclusión Social tendrá las atribuciones y obligaciones siguientes:\nPárrafo Reformado\nI. Proponer, dirigir, promover, ejecutar y evaluar la política estatal en materia de inclusión social y equidad de género, y fungir como dependencia rectora de dicha política;\nII. Coordinar la elaboración del Programa Estatal de Inclusión Social e Igualdad de\nGénero, con las dependencias y entidades paraestatales de la Administración Pública, Ayuntamientos, miembros de la sociedad civil, sector privado, instituciones académicas y grupos de interés;\nIII. Realizar estudios y diagnósticos, para identificar y ubicar geográficamente a grupos y personas en situación vulnerable, y violencia de género para realizar acciones de intervención y creación o adecuación de políticas públicas para su atención, para lo cual podrá solicitar de las autoridades federales, estatales y municipales, la información que se requiera, incluyendo los diagnósticos que se hayan realizado;\nIV. Elaborar, lineamientos y protocolos de atención, manejo e intervención dirigidos a las dependencias y entidades paraestatales de la Administración Pública, que contribuyan a la erradicación de cualquier manifestación de discriminación, y promuevan la inclusión social, la igualdad y equidad de género;\nV. Promover, fomentar, implementar y ejecutar políticas y programas generales para difundir y proteger los derechos relacionados con la equidad de género y la inclusión social de grupos vulnerables y de diversidad sexual;\nVI. Promover la incorporación estratégica y transversal de los derechos humanos, perspectiva de género e inclusión social en el Plan Estatal de Desarrollo y el Presupuesto de\nEgresos del Estado, desde un enfoque multidisciplinario;\nVII. Impulsar el empoderamiento de las mujeres, así como personas adultas mayores, personas con discapacidad, y personas miembros de los pueblos y comunidades indígenas, así como afromexicanas, en cuanto a su participación, promoción y capacitación en la toma de decisiones y en áreas de emprendimiento, en coordinación con las dependencias y entidades paraestatales de la Administración Pública;\nFracción Reformada\nVIII. Derogada.\nFracción Derogada\nIX. Crear mecanismos de coordinación institucional con instancias del Gobierno\nFederal, Estatal y Municipal, organismos no gubernamentales, instituciones de educación o investigación públicas o privadas para la promoción de la inclusión social e igualdad de género, en los programas y políticas públicas;\nX. Desarrollar acciones necesarias para impulsar la inclusión social e igualdad de género en todas las áreas de la vida económica, política, social y cultural del Estado, así desarrollo de la personalidad desde una perspectiva de derechos humanos y de género;\nXI. Contribuir en las acciones y programas que se establezcan en la Administración\nPública, en materia de derechos humanos, inclusión social e igualdad de género con el objetivo de erradicar los actos que atenten contra el libre desarrollo de la personalidad;\nXII. Establecer programas de capacitación, sensibilización, formación y profesionalización en materia de derechos humanos, inclusión social e Igualdad de género, otorgar la certificación correspondiente;\nXIII. Gestionar programas de difusión y acciones de sensibilización en medios de comunicación masiva y redes sociales, que promuevan la inclusión, una cultura libre de violencia de género y de discriminación, la utilización de lenguaje inclusivo, así como la identificación, erradicación y denuncia de la discriminación en todas sus formas, e incentivar la elaboración de programas educativos y campañas de concientización;\nXIV. Derogada.\nFracción Derogada\nXV. Coadyuvar con el sector público y privado en las demandas, necesidades y exigencias de inclusión social y equidad de género en el Estado, haciendo énfasis en las áreas de salud, empleo, educación, capacitación, seguridad, justicia, cultura y recreación;\nXVI. Realizar diagnósticos y estudios con enfoque de inclusión social e igualdad de género, que permitan tener datos actualizados de la problemática en el Estado para su debida atención;\nXVII. Establecer y vigilar el cumplimiento de normas, modelos, certificaciones y recomendaciones de protocolos de prevención, atención y manejo institucional para la protección de los derechos humanos vinculados a la inclusión social de los grupos en situación de vulnerabilidad, así como los relacionados con la equidad de género;\nXVIII. Impulsar iniciativas y proyectos con la sociedad, organizaciones civiles, comunitarias, instituciones académicas y de investigación, encaminadas al diseño, instrumentación y operación de políticas, programas y acciones relacionados con las materias a su cargo;\nXIX. Derogada.\nFracción Derogada\nXX. Proporcionar atención integral, asistencia jurídica y psicológica a personas en contexto de vulnerabilidad, que afronte un conflicto relacionado con violencia de género y/o con discriminación en el Estado, en el ámbito de su competencia;\nXXI. Generar y aplicar políticas públicas generales encaminadas a la inclusión social, y específicas para las personas que por razones económicas, emocionales o cualesquier condición viva en abandono o en situación de calle, así como a quienes egresen de las instituciones públicas o privadas de rehabilitación o de reinserción social, en coordinación con las dependencias y entidades paraestatales de la Administración Pública competentes;\nXXII. Llevar a cabo el registro, evaluación y estadística de las políticas, programas y acciones, que permitan su consulta por parte de las dependencias y entidades paraestatales de la Administración Pública, órganos autónomos y la ciudadanía, a fin de favorecer una participación y distribución equitativa de los recursos, oportunidades y beneficios relacionados con la inclusión social de los grupos en situación de vulnerabilidad, así como los relacionados con la igualdad de género;\nXXIII. Proponer en las políticas, programas y acciones de movilidad, obras públicas, servicios e instalaciones abiertos al público o de uso público, tanto en zonas urbanas como rurales, la inclusión de la accesibilidad de las personas con discapacidad y, en su caso, emitir lineamientos para hacerla efectiva; y,\nXXIV. Las que determinen las leyes, reglamentos y demás disposiciones aplicables.\nArtículo Reformado\nARTÍCULO 38. La Secretaría de Educación tendrá las atribuciones y obligaciones siguientes:\nI. Elaborar y proponer a la Persona Titular del Poder Ejecutivo la política de educación a ejecutarse en el Estado, observando las disposiciones establecidas en la Constitución\nFederal, la Constitución del Estado, la Ley General de Educación, y la Ley de Educación\nPública del Estado;\nII. Llevar el registro de las instituciones educativas, profesionistas, colegios y asociaciones de profesionistas, de los títulos, certificados y documentación escolar que expidan los planteles de sostenimiento público o privado incorporados al sistema educativo, así como regular el ejercicio profesional del Estado;\nIII. Expedir los certificados, otorgar las constancias y diplomas, y revalidar los estudios, diplomas, grados o títulos equivalentes a la enseñanza que se imparta en el\nEstado, en los términos de la ley de la materia;\nIV. Expedir a los profesionistas su Registro Profesional Estatal para el ejercicio profesional en el Estado y para su identidad en sus actividades profesionales, así como registrar el otorgado por autoridad competente en los términos de ley;\nV. Coordinarse con la autoridad educativa federal en la operación de los mecanismos de administración escolar;\nVI. Resolver sobre la autorización o el reconocimiento de validez oficial de estudios a instituciones particulares que ofrezcan y soliciten la incorporación de servicios educativos;\nVII. Otorgar, negar o revocar autorizaciones a los particulares para impartir la educación primaria, secundaria, normal y demás niveles educativos, de conformidad con las leyes de la materia;\nVIII. Imponer sanciones a las escuelas que infrinjan las disposiciones legales, locales y nacionales en materia educativa;\nIX. Proponer a la Secretaría de Educación Pública Federal, los contenidos regionales que hayan de incluirse en los planes y programas de estudio para la educación preescolar, primaria, secundaria, normal y demás para la formación de maestros de educación básica; bajo la perspectiva humanista, que permita desarrollar todas sus facultades, que dé prioridad a las actividades socioemocionales, deportivas, artísticas y culturales que fomenten el bienestar de niñas, niños, adolescentes y las juventudes para ser auténticos agentes de transformación;\nX. Ejercer la gobernanza educativa impulsando los Consejos de Participación Social, a través de los cuales se incluyan a los actores sociales, económicos, sindicatos, así como la comunidad educativa en general, para la generación de políticas, estrategias, acciones y orientaciones con la intención de generar procesos de excelencia educativa, equidad e inclusión social;\nXI. Aplicar los planes y programas de estudio oficiales en las escuelas de educación básica, normal y demás niveles educativos;\nXII. Prestar los servicios de educación inicial, básica, incluyendo la indígena, especial, normal y demás para la formación de maestros y maestras;\nXIII. Constituir el Sistema Estatal de Formación, Actualización, Capacitación y\nSuperación Profesional para Maestros y Maestras, incorporado al sistema nacional respectivo;\nXIV. Garantizar la alfabetización de la población y el acceso a la educación básica para adultos, en la cual se deberá proporcionar la capacitación necesaria para el uso de la tecnología, como herramienta fundamental de desarrollo e inclusión social;\nXV. Distribuir en tiempo y forma los libros de texto gratuitos y el material educativo complementario, que la Secretaría de Educación Pública Federal proporcione a los planteles, impulsando preferentemente su distribución digital;\nXVI. Vigilar el cumplimiento del calendario escolar oficial, en lo que se refiere a los actos cívicos escolares, a fin de impulsar la cultura cívica dentro de la población escolar;\nXVII. Promover los derechos humanos, la no discriminación, la perspectiva de género, el respeto a la diversidad, y la transparencia y el acceso a la información, en los contenidos de los programas educativos y en el proceso de enseñanza aprendizaje;\nXVIII. Promover la lectura, la instalación de bibliotecas y hemerotecas en los centros educativos y de enseñanza, así como impulsar la práctica literaria, la edición de libros, enseñanza-aprendizaje presencial, a distancia e híbrida para recuperar los aprendizajes perdidos, y promover oportunidades de aprendizaje que incluya las condiciones que marca la tendencia mundial de la tecnología, con énfasis en la atención a la población más vulnerable;\nXIX. Fomentar el intercambio académico, científico, tecnológico y humanístico con instituciones locales, nacionales e internacionales y promover su vinculación con las actividades públicas y privadas;\nXX. Fomentar una cultura de la paz en cada uno de los niveles educativos para el desarrollo de valores, conocimientos, actitudes y habilidades que formen a los educandos con esa visión, y para el ejercicio permanente del diálogo multicultural e intercultural, así como el respeto a los símbolos patrios y a la cultura cívica;\nXXI. Coordinar el Programa Estatal de Ciencia y Desarrollo Tecnológico que apoye el avance en la investigación y el equipamiento de la infraestructura científica y tecnológica;\nXXII. Otorgar becas, estímulos de desempeño y premios a estudiantes, de los programas que para el efecto se autoricen;\nXXIII. Otorgar reconocimientos, distinciones, estímulos y recompensas a los educadores que destaquen en el ejercicio de su profesión y, en general, realizar actividades que propicien mayor aprecio social a la labor desempeñada por el magisterio;\nXXIV. Prestar en forma permanente y con alto contenido de calidad los servicios de formación, actualización, capacitación y superación profesional para las y los maestros de educación básica, en coordinación con la Secretaría de Educación Pública Federal, así como renovar el compromiso con el Magisterio como agentes de transformación educativa, continua;\nEstatal de Evaluación y Mejora Continua, instancia que buscará que los diferentes actores y\nEstado; coordinación en materia educativa con la Federación y los Municipios del Estado;\nXXVII. Promover, fomentar y dirigir la enseñanza y práctica de la cultura física y el deporte en los centros escolares públicos, a fin de que estas actividades sean parte de la vida cotidiana de los alumnos;\nXXVIII. Diseñar en coordinación con la Secretaría General de Gobierno, a través de la unidad administrativa correspondiente, planes, programas y acciones que promuevan la cultura de la legalidad en el sector educativo, instituciones públicas, privadas y en los diversos sectores de la población; y,\nXXIX. Las que determinen las leyes, reglamentos y demás disposiciones aplicables.\nARTÍCULO 39. La Secretaría de Salud tendrá las atribuciones y obligaciones siguientes:\nI. Proponer, conducir y coordinar la política estatal en materia de salud, de conformidad con la política del Sistema Nacional de Salud y en los términos de la ley de la materia, y demás disposiciones aplicables;\nII. Planear, organizar, administrar y operar los servicios de salud a población abierta en materia de salubridad general, de regulación y control sanitario en el Estado;\nIII. Someter a la aprobación de la Persona Titular del Poder Ejecutivo los programas de salud necesarios para el cumplimiento de sus atribuciones, así como instrumentar su operación, supervisión y evaluación;\nIV. Planear, organizar y desarrollar el Sistema Estatal de Salud, así como definir los mecanismos de coordinación con las entidades públicas y los sectores público, privado y social, en los términos de la Ley General de Salud y la Ley de Salud Pública para el Estado de Baja California.\nV. Promover, determinar, coordinar, ejecutar y evaluar las políticas y programas que garanticen el derecho a la protección de la salud y el acceso a los servicios de salud de los habitantes del Estado, en los términos de la Ley General de Salud, Ley de Salud Pública para el Estado de Baja California y demás disposiciones aplicables;\nVI. Gestionar e impulsar la adecuada organización y operación de los servicios de atención médica, materno infantil, planificación familiar, salud mental y educación para la salud;\nVII. Formular y desarrollar programas de nutrición y de orientación alimentaria;\nVIII. Coordinar acciones preventivas, y mantener vigilancia y control permanente sobre los riesgos y daños para la salud derivados de las condiciones del ambiente, con la intervención de las autoridades competentes;\nIX. Promover la salud ocupacional y el saneamiento básico;\nX. Implementar acciones y programas para la prevención, vigilancia epidemiológica y el control de enfermedades transmisibles y no transmisibles;\nXI. Implementar acciones y programas para la prevención de accidentes, la atención de los padecimientos, y las secuelas a causa de ellos;\nXII. Implementar acciones de prevención y control de las causas y factores condicionantes de invalidez, así como para la identificación temprana y la atención oportuna de procesos físicos, mentales o sociales que puedan causar discapacidad, así como la rehabilitación de las personas con discapacidad;\nXIII. Coordinar con otras instancias públicas, sociales y privadas, el programa contra las adicciones con enfoque interdisciplinario, así como establecer criterios y procedimientos para la educación, promoción, prevención, atención, rehabilitación y control de las adicciones;\nXIV. Coordinar los programas de asistencia social en materia de salud, gestionando e impulsando su adecuada operación y tomar las medidas inmediatas que sean necesarias para la protección de las personas con discapacidad y ancianos, así como para la salud de los menores con la intervención que corresponda del Sistema Estatal para el Desarrollo\nIntegral de la Familia de Baja California;\nXV. Operar los programas, los servicios de salud y vigilancia sanitaria con sus respectivos procesos de planeación, programación, presupuestación, instrumentación, supervisión y evaluación;\nXVI. Coordinar la realización de campañas para prevenir y atacar las epidemias y enfermedades que por su naturaleza requieran de atención y cuidados especiales;\nXVII. Impulsar en coordinación con otras instancias públicas, sociales y privadas, campañas de concientización, educación, capacitación sanitaria y de salud, que contribuyan a mejorar las condiciones de vida de la población del Estado;\nXVIII. Coordinar, supervisar e inspeccionar, en coordinación con la Secretaría de\nEducación los servicios de salud en los centros educativos, para proteger la salud del educando y de la comunidad escolar;\nXIX. Coordinar, supervisar y ser corresponsable en la prestación de los servicios de salud y la atención médica a la población interna en los centros preventivos, centros de internamiento para adolescentes y centros de readaptación social;\nXX. Proponer y fortalecer la participación de la comunidad en los servicios de salud;\nXXI. Vigilar la aplicación de la normatividad general en materia de salud, tanto esquemas que logren su correcto cumplimiento.\nXXII. Ejercer atribuciones de regulación, vigilancia, control y fomento sanitarios conforme a la Ley General de Salud, la Ley de Salud para el Estado y los acuerdos celebrados con la Federación, y los demás ordenamientos aplicables que correspondan, a través del organismo público descentralizado denominado Instituto de Servicios de Salud\nPública del Estado de Baja California.\nFracción Reformada\nXXIII. Realizar acciones preferentemente de carácter preventivo relacionadas con problemas sanitarios y factores que condicionen o causen daños a la salud, tendientes a mejorar la calidad y seguridad en la prestación de los servicios de salud;\nXXIV. Promover la ampliación de la cobertura en la prestación de los servicios de salud, apoyando los programas que para tal efecto elabore la Secretaría de Salud del\nGobierno Federal;\nXXV. Promover y fomentar la formación académica, así como proveer la capacitación de los profesionales, especialistas y técnicos en materia de salud que presten sus servicios en el Estado;\nXXVI. Coadyuvar a que la formación y distribución de los recursos humanos sea congruente con las prioridades del Sistema Estatal de Salud;\nXXVII. Fomentar el desarrollo de la investigación y la enseñanza científica y tecnológica en materia de salud, integrando la bibliohemerografía necesaria que facilite a las autoridades e instituciones competentes, la investigación, estudio y análisis de ramas y aspectos específicos en materia de salud; través de publicaciones y actos académicos, los resultados de los trabajos de investigación, estudios, análisis y recopilación de información, documentación e intercambio que realiza;\nXXIX. Administrar los recursos que le sean asignados, provenientes del Gobierno instituciones, conforme a las leyes de la materia;\nXXX. Suscribir los convenios de coordinación en materia de salud con la federación, entidades federativas y los Municipios, previa validación de la Consejería Jurídica y\nXXXI. Representar institucionalmente al Estado ante todo tipo de Institutos y\nXXXII. Proponer a las dependencias de la Administración Pública competentes y entidades públicas integrantes del Sistema Estatal de Salud contemplar la asignación de los recursos que requieran los programas de salud;\nXXXIII. Proponer a la Persona Titular del Poder Ejecutivo para su aprobación, acuerdos de coordinación o colaboración con las entidades paraestatales de la\nAdministración Pública sectorizadas, tendientes a promover y apoyar los programas de salud;\nXXXIV. Proponer, impulsar e implementar con las dependencias y entidades paraestatales del Sistema Estatal de Salud la creación y mejora de infraestructura sanitaria que atienda las necesidades de servicios de salud a la población del Estado y mejorar la calidad de los mismos;\nXXXV. Proponer la planeación estratégica de esquemas que permitan privilegiar, regular y fortalecer el mantenimiento y desarrollo de la infraestructura y equipamiento de salud en coordinación con las dependencias de la Administración Pública y entidades públicas del Sistema Estatal de Salud;\nXXXVI. Promover el establecimiento de un Sistema Estatal de Información Básica en materia de salud, y determinar la periodicidad y características de la información que deberán proporcionar las dependencias y entidades paraestatales de la Administración\nPública que presten servicios de salud en el Estado, con sujeción a las disposiciones legales aplicables;\nXXXVII. Coadyuvar con las dependencias Federales competentes, en la regulación y control de la transferencia de tecnología en el área de salud;\nXXXVIII. Asumir las obligaciones que prevé la Ley que Establece las Bases de\nOperación de la Justicia Terapéutica para el Estado de Baja California;\nXXXIX. Ejercer las atribuciones que se le confieran en materia de sanidad internacional;\nXL. Impulsar la creación del Consejo Estatal de la Industria del Turismo Médico, cuyo objeto será diseñar las políticas públicas que fortalezcan las inversiones hospitalarias, la infraestructura y equipos de avanzada tecnología y la calidad de los servicios médicos, así como normar su funcionamiento, el cual estará integrado por instituciones públicas y organismos empresariales en términos de su decreto de creación; para estos efectos podrá coordinarse con la Secretaría de Turismo;\nXLI. Promover y diseñar la política de salud veterinaria que incluya el programa estatal de zoonosis y ejecutar y evaluar las acciones preventivas e integrales de control, en coordinación con la Secretaría del Medio Ambiente y Desarrollo Sustentable a través del órgano que se determine;\nXLII. Participar, en el ámbito de su competencia en la formulación de propuestas ante la Comisión Fronteriza Binacional México - Estados Unidos, a fin de impulsar el intercambio médico y sanitario binacional, y\nXLIII. Las que determinen las leyes, reglamentos y demás disposiciones aplicables.\nArtículo Reformado\nARTÍCULO 40. La Secretaría de Infraestructura, Desarrollo Urbano y Reordenación\nTerritorial tendrá las atribuciones y obligaciones siguientes:\nI. Formular, conducir, ejecutar y evaluar las políticas y programas sectoriales de infraestructura, desarrollo urbano sustentable, obras públicas y ordenamiento territorial, con base en las disposiciones legales aplicables y en congruencia con el Plan Estatal de\nDesarrollo;\nII. Coordinar e integrar el Programa Estatal de Infraestructura, Obra Pública y\nDesarrollo Urbano Sustentable, con la participación de las dependencias y entidades paraestatales de la Administración Pública, en congruencia con el Plan Estatal de Desarrollo y vigilar su ejecución;\nIII. Integrar el Sistema de Información Geográfica del Estado, en materia de uso, conservación, preservación y aprovechamiento del suelo, así como del ordenamiento territorial; el cual estará disponible para el público como una herramienta tecnológica que contribuya a una correcta planificación, gestión y divulgación de los usos del suelo;\nIV. Dictar las políticas generales sobre la construcción y conservación de las obras públicas, así como las relativas a los programas de desarrollo urbano sustentable; los términos de la Ley de Obras Públicas, Equipamientos, Suministros y Servicios\nRelacionados con la Misma del Estado de Baja California y demás disposiciones aplicables; arquitectónicos y de ingeniería necesaria para ejecutar las obras públicas e infraestructura, cumpliendo con lo previsto en las disposiciones legales y reglamentarias aplicables;\nVII. Participar, suscribir, ejecutar y, en su caso, representar a la Persona Titular del instrumentos que sean necesarios, que se celebren con autoridades federales y de otras entidades federativas, con los Ayuntamientos y la iniciativa privada, con el objeto de promover y regular la infraestructura pública y el desarrollo urbano sustentable en el Estado;\nVIII. Coordinar, supervisar y evaluar las actividades y resultados de las obras públicas, equipamientos, suministros y servicios que realicen las entidades paraestatales de la Administración Pública;\nIX. Realizar diagnósticos urbanos que contengan, la generación de indicadores de factibilidad para el desarrollo urbano sustentable, que garanticen la seguridad de la ciudadanía;\nX. Elaborar planes y programas de corto y mediano plazo, en concurrencia con los sectores social y privado para el desarrollo, inversión y operación de infraestructura, movilidad y telecomunicaciones;\nXI. Emitir, aplicar y vigilar el cumplimiento de los lineamientos sobre la construcción y conservación de las obras públicas, los relativos a los programas de desarrollo urbano sustentable y remodelación urbana, así como los relacionados con la constitución de reservas territoriales, previendo, en su caso, las necesidades para vivienda y la industria;\nXII. Aplicar las sanciones previstas en las disposiciones legales en las materias de su competencia, y dar seguimiento a la aplicación de las que correspondan a otras autoridades, así como resolver los recursos y quejas que le presenten, de conformidad con las disposiciones legales correspondientes;\nXIII. Procurar la generación de infraestructura social y productiva;\nXIV. Fomentar la cohesión social, articulando y ordenando el territorio para lograr la igualdad de oportunidades mediante la consolidación de una infraestructura integral, sustentable y compensatoria;\nXV. Promover y ejecutar, en su caso, las acciones de equipamiento urbano y vivienda que sean de su competencia, en coordinación con las dependencias que correspondan;\nXVI. Impulsar el acceso de la población a una vivienda digna, estableciendo en coordinación con la Secretaría de Hacienda, un programa de financiamiento para la construcción de vivienda en el Estado;\nXVII. Promover el desarrollo urbano de las comunidades rurales y fomentar la organización de sociedades cooperativas de vivienda y de materiales de construcción;\nXVIII. Promover de acuerdo a los objetivos del Plan Estatal de Desarrollo y al\nPrograma Estatal de Infraestructura, Obra Pública y Desarrollo Urbano Sustentable, la creación de fraccionamientos, unidades habitacionales y condominios;\nXIX. Expedir las bases a que deben sujetarse las licitaciones, para la ejecución de las obras a su cargo, así como adjudicarlas, cancelarlas y vigilar el cumplimiento de los contratos que celebre;\nXX. Crear un banco de proyectos ejecutivos de obras, que permitan una planeación y ejecución eficiente con los objetivos del Plan Estatal de Desarrollo y del Programa Estatal de\nInfraestructura, Obra Pública y Desarrollo Urbano Sustentable;\nXXI. Integrar los expedientes técnicos de obra pública y llevar durante la ejecución de estos, el seguimiento y control desde su gestión inicial hasta su conclusión, entrega y cierre de ejercicio;\nXXII. Integrar y mantener actualizado el censo de contratistas que lleven a cabo obras públicas o de infraestructura en el Estado;\nXXIII. Elaborar los lineamientos generales para la integración de los planes y programas de construcción, conservación o rehabilitación de carreteras, puentes y vías de comunicación a cargo del Estado;\nXXIV. Promover la construcción, instalación, conservación, mantenimiento o mejoramiento de las plazas, paseos, parques y edificios públicos que sean bienes inmuebles del patrimonio estatal, con excepción de los encomendados expresamente a otras dependencias u órganos creados para tal fin;\nXXV. Brindar asesoría a los Ayuntamientos para la formulación de los programas de desarrollo urbano municipal y su reglamentación respectiva, cuando lo soliciten;\nXXVI. Celebrar con los Ayuntamientos convenios de coordinación para la programación, proyección, ejecución, control, vigilancia y evaluación de la conservación, mantenimiento y modernización de las vías de comunicación e infraestructura pública; expropiación, ocupación temporal y limitación de dominio en los casos de utilidad pública, previa validación de la Consejería Jurídica; y,\nXXVIII. Las que determinen las leyes, reglamentos y demás disposiciones aplicables.\nARTÍCULO 41. La Secretaría de Economía e Innovación tendrá las atribuciones y obligaciones siguientes:\nI. Diseñar y coordinar la política pública de desarrollo económico, industrial y comercial del Estado;\nII. Coordinar e impulsar la implementación de la Política de Desarrollo Empresarial del\nEstado;\nIII. Diseñar, coordinar e impulsar la implementación de la política de innovación, desarrollo tecnológico y automatización en el Estado, encaminada a que las empresas crezcan y sean más competitivas;\nIV. Instrumentar acciones de gobierno con el objetivo de regular y establecer condiciones que favorezcan el abasto, comercialización y distribución del consumo básico, que se refleje en economías que beneficien a los sectores de la sociedad de atención prioritaria;\nV. Diseñar coordinadamente con las autoridades competentes, instrumentos de política pública, así como establecer programas de fomento para la creación, fortalecimiento y consolidación del sector económico deseable, de acuerdo a las vocaciones productivas del\nEstado, con enfoque de sustentabilidad ambiental y social, favoreciendo la inversión regional, local, nacional y extranjera;\nVI. Promover la organización formal de los distintos sectores económicos, estableciendo a su vez, programas, financiamiento e incentivos que les permita vincularse y ser más competitivos;\nVII. Integrar y proporcionar información socioeconómica local, nacional e internacional, que le permita conocer las tendencias, mercados, fondos e inversiones, dinámicas científicas y tecnológicas, y vocaciones productivas y, en general, toda aquella información que permita orientar, fomentar, incentivar e incluso desincentivar actividades económicas en el Estado;\nVIII. Promover y estimular el desarrollo de nuevas empresas y el crecimiento de las existentes;\nFracción Reformada\nIX. Identificar, impulsar y promover el desarrollo de proyectos estratégicos que detonen la capacidad productiva y competitividad del Estado, incluyendo la infraestructura, el ordenamiento industrial y la sustentabilidad en el uso de recursos.\nX. Apoyar en los procesos de protección y aprovechamiento adecuado de la\nXI. Otorgar estímulos y reconocimientos al mérito de la actividad productiva, tecnológica y empresarial en el Estado;\nXII. Fomentar, implementar, diseñar y promover acciones y programas para mejorar las capacidades técnicas y financieras de las empresas y de los distintos sectores económicos, que impulsen y mejoren la productividad, calidad y competitividad en el Estado;\nXIII. Fomentar, impulsar, apoyar y estimular el emprendimiento en los diferentes estratos de la sociedad mediante programas propios y en coordinación con instituciones académicas y del sector empresarial, nacionales o extranjeras, así como de la sociedad civil.\nXIV. Organizar, coordinar, participar, patrocinar o difundir congresos, foros, seminarios, exposiciones y ferias de carácter comercial, industrial y de desarrollo de negocios;\nXV. Promover, facilitar y apoyar la integración de cadenas productivas, el desarrollo de proveedores y la articulación de empresas e instituciones, especialmente para las vocaciones productivas del Estado;\nXVI. Impulsar y apoyar la participación en los mercados nacionales y extranjeros, de las industrias y empresas locales, facilitando el acceso de éstas a otros mercados;\nXVII. Elaborar, coordinar y ejecutar programas y acciones de promoción que incentiven la participación del comercio exterior e inversión extranjera y nacional, para el establecimiento de industrias y empresas que generen empleo eventual o permanente, en los distintos sectores de la economía y regiones del Estado;\nXVIII. Diseñar, fomentar, impulsar, promover y participar en programas de innovación, investigación científica, desarrollo, transferencia y asimilación tecnológica con enfoque de sustentabilidad, relacionados con las actividades de los sectores económicos y vocaciones productivas, orientados a los objetivos de desarrollo económico estatal y regional definidos;\nXIX. Impulsar, fomentar, articular, promover y estimular la formación, establecimiento\nEstado;\nXX. Fomentar y difundir la participación de las empresas del Estado en eventos nacionales e internacionales a fin de posicionar a la región;\nXXI. Diseñar y ejecutar programas de difusión de los sectores económicos y de las distintas localidades del Estado, a fin de promover la inversión pública y privada;\nXXII. Impulsar, promover y facilitar la creación de infraestructura de apoyo a las actividades productivas y de desarrollo tecnológico orientadas a las vocaciones del Estado, estimulando la colaboración de instituciones académicas, empresariales y de los diversos sectores económicos y social;\nXXIII. Impulsar en el Estado el uso y, en su caso, la generación y estándares de competencias tanto nacionales como internacionales, así como promover en los sectores económicos el ecosistema de certificaciones, que impulsen y mejoren la productividad, calidad y competitividad en el Estado, y\nXXIV. Promover y facilitar los mecanismos de apertura rápida de empresas a través del Programas respectivos; y,\nFracción Adicionada, recorriéndose la subsecuente\nXXV. Las que determinen las leyes, reglamentos y demás disposiciones aplicables, o bien que expresamente no estén conferidas a la federación o los Ayuntamientos y sean necesarias para la labor y gestión gubernamental.\nArtículo Reformado\nARTÍCULO 42. La Secretaría del Trabajo y Previsión Social tendrá las atribuciones y obligaciones siguientes:\nI. Ejercer las atribuciones que en materia de trabajo corresponden al Poder Ejecutivo;\nII. Fomentar el trabajo digno con perspectiva de género e inclusión de grupos vulnerables y sensibles, mediante acciones y programas que mejoren la calidad de los empleos existentes e impulsar la generación de empleos;\nIII. Generar y aplicar políticas públicas que establezcan la protección de los derechos de los menores que trabajan, así como combatir la explotación del trabajo infantil;\nIV. Difundir, promover y fomentar el empleo para personas con discapacidad y adultos mayores, y lograr en un plano de igualdad de oportunidades su incorporación al mercado laboral, coordinándose con las dependencias de la Administración Pública e instancias competentes;\nV. Vigilar la observancia y aplicación en el ámbito de su competencia de las disposiciones contenidas en el artículo 123 y demás relativas de la Constitución Federal, la\nConstitución del Estado, la Ley Federal del Trabajo y sus reglamentos;\nVI. Vigilar, mediante visitas e inspecciones, que los centros de trabajo cumplan con cuando así lo ameriten e imponer las sanciones administrativas procedentes;\nVII. Proponer la actualización de las medidas de seguridad e higiene en los centros de trabajo en el Estado, y promover su verificación a través de visitas de inspección;\nVIII. Propiciar la concertación en las discrepancias que se susciten entre grupos, organizaciones y sujetos de derechos, así como de los sindicatos y asociaciones obreros patronales, procurando ante la instancia correspondiente, la conciliación de sus intereses;\nIX. Participar en la firma de los contratos colectivos de las dependencias y entidades paraestatales de la Administración Pública;\nX. Promover ante la instancia correspondiente la integración del Registro Público de\nContratos Colectivos, Asociaciones Obreras, Gremiales y Patronales;\nXI. Coordinar la integración, establecimiento y funcionamiento del Tribunal de Arbitraje del Estado, así como de las comisiones que se formen para regular las relaciones obrero patronales de jurisdicción estatal y vigilar su funcionamiento conforme a la Ley del Servicio\nCivil, la Ley Federal del Trabajo y demás normatividad aplicable;\nXII. Organizar y operar el Servicio Estatal del Empleo, previo diagnóstico de la oferta y demanda de trabajo en el Estado;\nXIII. Ejecutar los convenios y acuerdos que en materia de trabajo, firme la Persona coadyuvando con la dependencia federal correspondiente en la formulación de contratos-ley, tratándose de empresas de jurisdicción local;\nXIV. Dirigir y coordinar la Procuraduría para la Defensa del Trabajo;\nXV. Impulsar y dar seguimiento, en coordinación con la Consejería Jurídica, a la implementación del nuevo sistema de justicia laboral, en el ámbito de su competencia;\nXVI. Coordinar al Centro de Conciliación Laboral del Estado de Baja California, que le estará sectorizado y proponer su reglamentación;\nXVII. Proponer y participar en el Comité de Planeación para el Desarrollo del Estado, para el diseño de la política laboral con visión regional y local, impulsando líneas estratégicas y de acción tendientes a la mejoría de la productividad, la ocupación y el empleo, la capacitación, adiestramiento y certificación, la salud e higiene, y todas aquellas del Estado y la mejoría de las personas que laboran en ella;\nXVIII. Vigilar el cumplimiento por parte del sector empresarial y patronal de los lineamientos en materia de trabajo establecidos en la Ley Federal de Trabajo y demás normas legales aplicables;\nXIX. Dar cumplimiento, en el ámbito de su competencia, a los convenios internacionales en materia de derecho laboral;\nXX. Promover la organización de las personas jornaleras agrícolas y pescadores, para garantizar la protección laboral y de seguridad social que establece la legislación aplicable;\nXXI. Promover la democracia sindical y tener acceso a la contratación colectiva;\nXXII. Diseñar, promover e impartir en su carácter de autoridad corresponsable en términos de la ley de la materia, cursos de capacitación y adiestramiento para el trabajo para personas liberadas de los centros de reinserción social o sujetas a los servicios postpenales para contribuir a la restitución plena del ejercicio de su libertad, así como para personas sin empleo o rehabilitadas del uso de sustancias psicotrópicas o estupefacientes con el fin de reintegrarlos a un trabajo fijo, en coordinación con las dependencias y entidades paraestatales de la Administración Pública, del gobierno federal, Ayuntamientos u organismos públicos o privados;\nXXIII. Promover la cultura y recreación entre las y los trabajadores y sus familias;\nXXIV. Vigilar el cumplimiento de la Ley del Servicio Civil del Estado, la reglamentación en la materia y demás normatividad aplicable, y\nXXV. Las que determinen las leyes, reglamentos y demás disposiciones aplicables.\nARTÍCULO 43. La Secretaría de Turismo tendrá las atribuciones y obligaciones siguientes:\nI. Diseñar y coordinar la política pública para planificar, fomentar, desarrollar y promover el turismo en el Estado;\nII. Proponer, ejecutar y evaluar la política pública, programas, instrumentos, declaratorias, acciones de fomento y promoción, información, investigación, formación de vocaciones, competencias y, en general, normar la actividad turística, induciendo e incentivando el turismo sustentable, inclusivo y de participación de las comunidades;\nIII. Normar, clasificar y verificar las actividades turísticas, así como promover la coadyuvancia con diversas autoridades en materias concurrentes al sector turístico; turísticas en el Estado, con su respectiva reglamentación, y promover ante las autoridades federales competentes la formulación de declaratorias para zonas de desarrollo turístico sustentable;\nV. Coadyuvar con las autoridades competentes para el cumplimiento de las leyes, reglamentos y normatividad en la materia por parte de las empresas de prestación de servicios turísticos;\nVI. Fomentar y mantener relaciones con organizaciones turísticas nacionales e internacionales, en apoyo a la difusión de los atractivos turísticos del Estado;\nVII. Integrar un sistema de información sobre el patrimonio turístico y prestar servicios de orientación e información al usuario;\nVIII. Realizar y coordinar los estudios e investigaciones para el desarrollo de la actividad turística, y formular la estadística en la materia;\nIX. Coordinarse con organizaciones públicas y privadas, incluyendo a empresas, asociaciones gremiales, instituciones educativas técnicas y de nivel superior, para ejecutar programas de capacitación y profesionalización turística en sus diversos aspectos;\nX. Promover la creación de organismos de carácter privado y social que tiendan a fomentar la inversión en materia turística y servicios conexos;\nXI. Proteger, auxiliar, orientar, proporcionar información, medir grado de satisfacción y, en su caso, representar a los turistas;\nXII. Establecer módulos de información y atención para los turistas;\nXIII. Regular, clasificar, capacitar, certificar y llevar un control de los servidores turísticos;\nXIV. Promover la formación, participación y fortalecimiento de asociaciones, comités y patronatos de carácter público, privado, social o mixto, de naturaleza turística o relacionados con las actividades y servicios conexos;\nXV. Promover y articular los esfuerzos para la mejora de infraestructura del sector turístico que haga más atractivos los destinos a visitantes;\nXVI. Establecer delegaciones para la atención de los asuntos de su competencia en funciones, conforme al presupuesto autorizado;\nXVII. Fomentar y promover la inversión nacional y extranjera necesaria para impulsar un mejor desarrollo del turismo en el Estado;\nXVIII. Generar e impulsar programas y estrategias para la promoción y publicidad turística en el territorio nacional y en el extranjero, para el incremento de la afluencia de visitantes, y\nXIX. Las que determinen las leyes, reglamentos y demás disposiciones aplicables, y en específico, las que se determinen expresamente en la Ley General de Turismo, o bien que expresamente no estén conferidas a la federación o Ayuntamientos y sean necesarias para la labor y gestión gubernamental.\nARTÍCULO 44. La Secretaría de Agricultura y Desarrollo Rural, tendrá las atribuciones y obligaciones siguientes:\nPárrafo Reformado\nI. Planear, implementar, coordinar, evaluar y ejecutar las políticas de desarrollo en los sectores agropecuario, silvícola y de seguridad alimentaria, así como de las acciones, programas y proyectos que permitan su desarrollo sustentable;\nII. Elaborar y presentar a la Persona Titular del Poder Ejecutivo, para su aprobación los programas y acciones en los sectores agrícola, pecuario, agropecuario, silvícola y de seguridad alimentaria, que requiera el Estado, en apego a las disposiciones legales aplicables;\nIII. Promover el aprovechamiento, reproducción, mejoramiento, fomento y protección de las especies agrícolas, ganaderas, avícolas y silvícolas;\nIV. Promover, coordinar y ejecutar actividades destinadas al fomento y mejora de los productos y subproductos agrícolas, ganaderos, avícolas y silvícolas;\nV. Promover y apoyar la industrialización y comercialización de los productos agrícolas, pecuarios y silvícolas, generados en el Estado, en coordinación con la dependencia de la Administración Pública competente;\nVI. Desarrollar e impulsar esquemas de comercialización eficientes que propicien la rentabilidad de las actividades primarias, mediante mecanismos de promoción colectiva y cobertura de precios;\nVII. Promover y asesorar técnica y jurídicamente a los productores agrícolas, ganaderos, pecuarios, avícolas y silvícolas mediante estudio y opinión que se emita para la obtención de créditos, su reestructuración y otros mecanismos de financiamiento destinados a la inversión de proyectos productivos para esos sectores que propicien su rentabilidad;\nVIII. Promover la organización con fines económicos y sociales de las personas físicas o morales que se dediquen a la producción y comercialización agrícola, ganadera, avícola y silvícola del Estado;\nIX. Gestionar la obtención de recursos económicos de organismos nacionales e internacionales para el desarrollo de proyectos productivos y dar seguimiento a la inversión pública en el sector agrícola, ganadero, avícola y silvícola;\nX. Establecer mecanismos de coordinación y promover la participación en la actividad agrícola, ganadero, avícola y silvícola de los sectores social y privado para el desarrollo del sector;\nXI. Impulsar políticas y programas que busquen que el campo sea productivo y rentable, implementando asesoría y asistencia técnica a los productores del sector agropecuario, mediante centros de capacitación y formación de técnicos especializados;\nXII. Coordinar la operación de los programas agropecuarios, que se implementen en apoyo a todas las regiones del Estado, como una alternativa de fomento a la productividad, destinados a lograr una mayor cobertura de la seguridad alimentaria;\nXIII. Asesorar y brindar asistencia técnica en el cultivo, almacenamiento y empaque para la comercialización, e impulsar la introducción o, en su caso, la reconversión de cultivos que sean rentables para los productores agropecuarios;\nXIV. Impulsar programas de siembra de hortalizas y huertos familiares para el autoconsumo e industrialización, en su caso, promoviendo la alimentación autosustentable en comunidades rurales;\nXV. Promover, la producción y comercialización para el consumo interno de los productos agrícolas y ganaderos, así como la industrialización y mejoramiento de la calidad en los productos finales, para competir en los mercados externos;\nXVI. Desarrollar la cultura empresarial de los productores del Estado, a través de la capacitación, investigación, innovación y transferencia de tecnología de los sistemas de producción que implementen la productividad del sector;\nXVII. Organizar, coordinar, participar o patrocinar congresos, concursos y eventos que promuevan el desarrollo y la competitividad de las actividades agrícolas, pecuarias, y silvícolas en el Estado, así como aquellos orientados a la consolidación y apertura de mercados, los cuales deberán promover el desarrollo de las actividades del sector;\nXVIII. Integrar el inventario de los recursos e infraestructura hidroagrícola y silvícola existentes en el Estado;\nXIX. Establecer las políticas, estrategias, objetivos y normas en el uso y abastecimiento del agua, para elevar la productividad agrícola y hacerla más eficiente, así como establecer programas para la introducción de nuevas y mejores tecnologías en los sistemas de riego e infraestructura hídrica en el sector;\nXX. Impulsar y promover la instalación de paneles solares para la producción de energía eléctrica en el sector agropecuario y pecuario;\nXXI. Promover, revisar y orientar los créditos agrícolas, pecuarios y silvícola, hacia los objetivos y metas prioritarios previstos en el Plan Estatal de Desarrollo, así como impulsar mecanismos novedosos de garantías, y proponer soluciones para los factores que originen las carteras vencidas;\nXXII. Impulsar la cría de ganado menor y la producción de los hatos ganaderos especialmente caprinos, porcinos y bovinos, para la industrialización y comercialización de los productos;\nXXIII. Impulsar la construcción de infraestructura para el procesamiento y transformación de productos, agrícolas y pecuarios en las zonas de producción del Estado;\nXXIV. Establecer los controles de inspección en sanidad e inocuidad, con el objeto de garantizar el cabal aprovechamiento de los recursos;\nMunicipal, los programas de sanidad animal y vegetal;\nXXVI. Diseñar, coordinar y promover programas y campañas de prevención, combate, control y erradicación de las plagas y enfermedades que afecten a las especies agrícolas, ganaderas, avícolas y silvícolas en el Estado;\nXXVII. Efectuar actividades de supervisión, control, regulación y sanción de la movilización de los productos y subproductos agropecuarios y silvícolas en el Estado;\nXXVIII. Proyectar y coordinar los programas de fomento, mejoramiento, protección y explotación de los terrenos agrícolas, pastizales naturales y cultivados, así como de los recursos silvícolas;\nXXIX. Impulsar y participar en los programas de investigación y experimentación agropecuaria y silvícola en todas sus modalidades;\nXXX. Fomentar la educación, investigación científica y programas de tecnología apropiada para el campo, ganadería, agricultura y silvicultura, así como coordinar la recopilación de información y estadísticas de cada sector para la toma de decisiones en su beneficio, en coordinación con la Secretaría de Educación y las instituciones de enseñanza e investigación;\nXXXI. Promover y coordinar la ejecución de programas de infraestructura física que contribuyan a incrementar la producción y productividad agropecuaria y silvícola;\nXXXII. Coordinar el Comité de Planeación para el Desarrollo del Estado, así como el funcionamiento del Subcomité Agropecuario y Forestal, en los términos de la ley de la materia;\nXXXIII. Ejercer las atribuciones que la legislación federal en materia agropecuaria establece para las entidades federativas, así como las atribuciones descentralizadas por la federación hacía el Estado, mediante convenios;\nFracción Reformada\nXXXIV. Participar en la planeación del desarrollo rural sustentable en términos de las leyes de la materia;\nFracción Adicionada\nXXXV. Coadyuvar con la federación mediante los mecanismos previstos para las entidades federativas en materia de desarrollo rural sustentable; y,\nFracción Adicionada\nXXXVI. Las que determinen las leyes, reglamentos y demás disposiciones aplicables.\nFracción Recorrida\nArtículo Reformado\nARTÍCULO 45. La Secretaría de Pesca y Acuacultura tendrá las atribuciones y obligaciones siguientes:\nI. Instrumentar y coordinar las políticas públicas en materia de pesca y acuacultura en el Estado;\nII. Coordinar la elaboración, ejecución y evaluación del Programa Estatal de Pesca y\nAcuacultura Sustentable y, en su caso, los planes de manejo y demás instrumentos que regulen la actividad responsable en el Estado, atendiendo a los requerimientos, necesidades e impedimentos que enfrenta el sector pesquero, acuícola y actividades de soporte o relacionadas con estas, procurando la alineación a los instrumentos nacionales, estatales, sectoriales y regionales que le correspondan;\nIII. Dirigir y supervisar la programación y presupuestación para el ejercicio de sus atribuciones y someterlo a consideración de la Persona Titular del Poder Ejecutivo, previa opinión de la Secretaría de Hacienda, así como autorizar el ejercicio del Presupuesto de\nEgresos de sus unidades administrativas;\nIV. Ejercer las acciones regulatorias necesarias relativas a la protección, restauración, conservación, preservación y aprovechamiento sustentable de los ecosistemas, recursos, bienes y servicios relacionados con la pesca y acuicultura, incluidas en materia sanitaria para prevenir, controlar, combatir y erradicar enfermedades y plagas;\nV. Coordinar las actividades relativas al control y administración de sistemas de información y registrales en materia de pesca y acuacultura para la toma de decisiones gubernamentales, los cuales serán de acceso al público, así como operar y mantener actualizada la información en el ámbito de su competencia;\nVI. Coadyuvar en la aplicación de las medidas de sanidad acuícola que se requieran para controlar, combatir y erradicar enfermedades y plagas que puedan afectar a las especies acuáticas y pesqueras, en coordinación con la autoridad sanitaria estatal, así como implementar dispositivos de emergencia en coordinación con la autoridad federal en materia sanitaria, en apoyo a las exportaciones de bienes acuícolas y pesqueros;\nVII. Atender los requerimientos y necesidades del sector pesquero y acuícola en concordancia con la Política Nacional de Pesca y Acuacultura Sustentables, vinculándolos con los programas nacionales, sectoriales y regionales, así como con el Plan Estatal de\nDesarrollo y el Programa Estatal de Pesca y Acuacultura;\nVIII. Participar con las dependencias competentes de la Administración Pública\nFederal, en la elaboración de planes de manejo y de normas oficiales, de conformidad con las disposiciones aplicables;\nIX. Presidir el Consejo Estatal de Pesca y Acuacultura;\nX. Participar en coordinación con la Federación, Municipios y, en su caso, con la ordenamiento territorial, así como de las unidades de manejo acuícola y pesqueros y zonas de desarrollo, en armonía con la conservación del medio ambiente y la biodiversidad;\nXI. Regular la conservación, preservación, aprovechamiento y control de los recursos acuícolas y pesqueros en el Estado;\nXII. Promover el fomento y la ordenación de las actividades acuícolas y pesqueras del\nEstado bajo un enfoque de desarrollo sustentable;\nXIII. Impulsar y apoyar a los productores acuícolas y pescadores del Estado para el cumplimiento y/o reforzamiento de las campañas que se implementen en materia de sanidad e inocuidad acuícola y pesquera;\nXIV. Instrumentar acciones, en coordinación con las autoridades federales para el cumplimiento de estándares internacionales y certificación de procesos productivos o extractivos, de sanidad e inocuidad necesarios para la exportación de los productos acuícolas y pesqueros del Estado;\nXV. Promover las condiciones para la integración, fomento y difusión de información pesquera y acuícola que apoye en la toma de decisiones para el beneficio del sector;\nXVI. Estimular la reconversión, en términos de estructura productiva sustentable mediante la incorporación de cambios tecnológicos y de procesos que contribuyan a la productividad y competitividad del sector acuícola y pesquero;\nXVII. Promover la aplicación de tecnologías para la producción, productividad y calidad en las cadenas productivas y en la comercialización de los productos acuícolas y pesqueros a fin de facilitar la integración de las mismas;\nXVIII. Impulsar la investigación acuícola y pesquera, la transferencia de tecnología a los productores, así como la inducción de prácticas sustentables, y\nXIX. Promover, convenir y coadyuvar en la implementación de acciones en materia de inspección y vigilancia en el litoral adyacente y aguas interiores del Estado donde existe aprovechamiento de recursos pesqueros, por acuacultura o pesca deportivo-recreativa, la comercialización y venta de éstos conforme a las leyes, normas y planes de manejo aplicables;\nXX. Promover y convenir con las autoridades federales y Municipios acciones para el cuidado de especies marinas bajo estatus de protección especial y/o en reservas ecológicas conforme a las leyes, normas y planes de manejo aplicables;\nXXI. Instrumentar las acciones que se deriven de la concertación y coordinación con organismos de productores y dependencias de los gobiernos Estatal, Federal y Municipal tendientes al fortalecimiento y modernización de las actividades pesqueras y acuícolas;\nXXII. Fomentar y apoyar el desarrollo y modernización de la infraestructura pesquera y acuícola en el Estado; y,\nXXIII. Las que determinen las leyes, reglamentos y demás disposiciones aplicables, y\nSustentables, o bien que expresamente no estén conferidas a la federación o Ayuntamientos y sean necesarias para la labor y gestión gubernamental.\nARTÍCULO 46. La Secretaría de Medio Ambiente y Desarrollo Sustentable tendrá las atribuciones y obligaciones siguientes:\nI. Coordinar la elaboración de los planes y programas en materia de política ambiental, en congruencia con lo establecido por la Federación y los criterios formulados por el Consejo Estatal de Protección al Ambiente, y en coordinación con los Ayuntamientos y la participación ciudadana;\nII. Ejecutar y vigilar los programas, acciones e instrumentos en materia estatal para prevenir, preservar, restaurar y, en general todas aquellas que tiendan a la protección al ambiente y al equilibrio ecológico, sea cual fuere su causa u origen, entre las cuales se encuentran la creación de áreas naturales protegidas;\nIII. Fomentar, ejecutar y, en su caso, administrar sitios, instalaciones, proyectos, actividades, sistemas de información electrónica, entre otras, que tengan por objeto generar y promover conocimiento, a fin de desarrollar en la población una mayor y mejor conciencia ambiental;\nIV. Ejercer acciones de rectoría y reglamentarias de actividades, bienes y servicios en materia de recursos naturales, tales como vida silvestre, flora, fauna, forestal y recursos pétreos, de competencia estatal o bien que sean en concurrencia con los Municipios o la\nFederación;\nV. Establecer y dar seguimiento, en el ámbito de su competencia y en coordinación con la Federación y los Ayuntamientos, a las políticas, planes, programas, estrategias y acciones encaminadas a asegurar que a todo animal se le garantice su bienestar, por conducto del órgano que se determine, así como a las recomendaciones que éste realice a respetuoso;\nVI. Evaluar, autorizar o, en su caso, negar la manifestación del impacto ambiental de los proyectos, planes, programas, obras y actividades de competencia estatal, así ́ como autorización respectiva, en los términos de la ley de la materia;\nVII. Otorgar y, en su caso, revocar los permisos, licencias, registros y autorizaciones, derivadas de la legislación ambiental del Estado, sus reglamentos, normas ambientales y demás disposiciones legales aplicables;\nVIII. Coordinar la participación de las dependencias y entidades paraestatales de la\nAdministración Pública, en las acciones de cultura ambiental, de prevención y control del deterioro ambiental, preservación, protección y restauración del ambiente en el territorio del\nEstado, así como celebrar con éstas los acuerdos que sean necesarios con el propósito de dar cumplimiento a los ordenamientos ambientales del Estado;\nIX. Participar conforme a las políticas y programas de protección civil, en las contingencias ambientales y emergencias ecológicas, o cuando se afecten zonas de dos o más Municipios del Estado, o bien cuando por su magnitud o repercusiones así se requiera;\nX. Formular, ejecutar y evaluar las políticas, planes, estrategias y acciones para el\nEstado, que atiendan a los programas creados por el Gobierno Federal e incluyan una perspectiva transversal entre las dependencias y entidades paraestatales de la\nAdministración Pública, y los Ayuntamientos, que contribuyan a la mitigación y adaptación al cambio climático, proponiendo, en su caso, las medidas y recomendaciones necesarias para fortalecer o reorientar los avances logrados;\nXI. Definir y coordinar la realización de las acciones para el diseño e instrumentación del Programa de Acción ante el cambio climático y la Estrategia Estatal de Acción Climática, las medidas de mitigación y adaptación, así como, su implementación, monitoreo, seguimiento y evaluación;\nXII. Aprobar las reglas de operación del Fondo Ambiental del Estado;\nXIII. Participar en la elaboración, formulación y aplicación de programas, planes, proyectos forestales o cuencas hidrológico-forestales que no estén expresamente atribuidas\nXIV. Promover y coordinar acciones de protección, conservación, reforestación, fomento y vigilancia de los recursos forestales en el Estado;\nXV. Promover los bienes y servicios ambientales de los ecosistemas forestales;\nXVI. Llevar a cabo acciones de prevención, capacitación y combate de incendios forestales, así como campañas contra plagas y enfermedades forestales en congruencia con el programa nacional respectivo;\nXVII. Promover y participar en la restauración de los ecosistemas forestales afectados mejoramiento del hábitat natural de los pueblos y comunidades indígenas;\nXVIII. Coordinar la formulación, ejecución, evaluación y actualización del Programa\nEstatal, los Subprogramas y demás instrumentos de política para la gestión integral y la economía circular de los residuos;\nXIX. Incorporar en los planes y programas de ordenamiento territorial, ordenamiento ecológico y desarrollo urbano, el establecimiento de la infraestructura indispensable para la gestión integral de los residuos;\nXX. Proponer en los términos de la ley de la materia, el establecimiento de normas ambientales estatales para el funcionamiento de los sistemas de recolección, transporte, almacenamiento, manejo, tratamiento, reciclaje y confinamiento de residuos de manejo especial, así como para evitar la contaminación del suelo y riesgos y daños a la salud pública y el ambiente;\nXXI. Ejercer todas aquellas acciones tendientes a la preservación y restauración del medio ambiente, de impulso al desarrollo sustentable, y de conservación de los recursos naturales;\nXXII. Formular, conducir y evaluar las políticas públicas, planes, programas, estrategias y acciones que garanticen el desarrollo de la movilidad sustentable así como la prestación del servicio de transporte público y privado a cargo del Poder Ejecutivo, que realizará a través del Instituto de Movilidad Sustentable del Estado de Baja California que le estará sectorizado;\nXXIII. Expedir permisos y concesiones relativos al Transporte Público competencia del\nEstado, previo acuerdo de la Persona Titular del Poder Ejecutivo, en los términos de la normatividad aplicable;\nXXIV. Proponer acciones programáticas para promover la movilidad urbana sustentable que permita impulsar un sistema de calidad, aceptable, suficiente y accesible que, en condiciones de igualdad y sostenibilidad, permitan el efectivo desplazamiento de las personas en el Estado, para la satisfacción de sus necesidades y pleno desarrollo;\nXXV. Coadyuvar en el ámbito de su competencia en la transición hacia modelos de desarrollo urbano para ciudades y comunidades sustentables, fomentando la movilidad no motorizada, preferentemente de carácter peatonal, el desarrollo de ciclovías, y la innovación hacia un transporte público y privado de alta eficiencia energética, bajo en emisiones de carbono y otros gases de efecto invernadero;\nXXVI. Establecer una estrategia estatal de movilidad urbana sustentable que vincule metas y recursos, de manera que se destinen para un fuerte cambio modal y una reducción significativa de las emisiones;\nXXVII. Contribuir al impulso e implementación de los objetivos del desarrollo sostenible o Agenda 2030 en la normatividad del Estado, así como en políticas públicas, planes y programas que de ella se deriven;\nXXVIII. Diseñar coordinadamente instrumentos de política pública, así como establecer programas de fomento con enfoque sostenible para la creación, fortalecimiento y consolidación del sector medio ambiente y desarrollo sustentable, de acuerdo a las vocaciones regionales del Estado, el impacto ambiental y social, favoreciendo la inversión local, nacional y extranjera; y,\nXXIX. Las que determinen las leyes, reglamentos y demás disposiciones aplicables.\nARTÍCULO 47. La Secretaría para el Manejo, Saneamiento y Protección del Agua tiene las atribuciones y obligaciones siguientes:\nI. Diseñar y coordinar la política pública en materia de gestión de recursos hídricos que correspondan al Estado, así como fomentar el uso racional del agua, en el ámbito de su competencia;\nII. Planear, gestionar, regular, validar, supervisar y coordinar los servicios de agua potable, alcantarillado, saneamiento y reúso que correspondan al Estado, y que no afecte facultades y atribuciones de los Ayuntamientos;\nIII. Gestionar, planear, programar, proyectar, contratar, ejecutar y supervisar, las obras de competencia estatal, por si o través de las entidades paraestatales del sector a su cargo, requeridas para aprovechar de forma sustentable el agua en las actividades urbanas y suburbanas, agrícolas, rurales, ganaderas y forestales de su competencia, así como su operación, conservación y mantenimiento, coordinando dichas acciones con las dependencias de la Administración Pública que corresponda;\nIV. Gestionar, promover y participar en la obtención de recursos, concertación de créditos, y otros mecanismos financieros incluso sobre la participación de terceros, en el financiamiento de obras y servicios, para la construcción, instalación, conservación, al Estado;\nV. Ejercer las atribuciones que la legislación federal en materia hídrica establece para los Estados, así como las atribuciones descentralizadas por la Federación hacia los Estados, mediante la celebración de convenios;\nVI. Elaborar los programas que derivados del Plan Estatal de Desarrollo se relacionen con los sistemas de agua potable, alcantarillado y saneamiento a cargo del Estado, y supervisar el cumplimiento de las prioridades y su ejecución;\nVII. Participar en la celebración de convenios y acuerdos que la Persona Titular del procedimientos, condiciones y términos conforme a los cuales se proceda, en su caso, a la transferencia del organismo operador, cuando un Municipio considere que su capacidad administrativa y financiera permitan la instalación y funcionamiento de la comisión municipal correspondiente;\nVIII. Gestionar ante las autoridades competentes la realización de acciones y emisión de actos administrativos necesarios para el ejercicio de sus funciones, en términos de las leyes locales y la Ley de Aguas Nacionales;\nIX. Proponer alternativas en la utilización de fuentes de energía para la operación de los sistemas de conducción de agua en el Estado;\nX. Formular y promover nuevas fuentes y sistemas de abastecimiento de agua, disminuyendo los daños ambientales y los costos en la producción de nuevas fuentes de agua que correspondan al Estado;\nXI. Coadyuvar en la promoción, apoyo, prevención, vigilancia, control y disminución de la contaminación del agua de competencia del Estado;\nXII. Coadyuvar con la dependencia de la Administración Pública competente, en la aplicación de la normatividad para el manejo y disposición final de residuos sólidos, de residuos industriales y para la construcción de sistemas de tratamiento de aguas residuales;\nXIII. Coadyuvar en la formulación conjunta con la Federación y los Municipios, de los de drenaje y alcantarillado competencia del Estado, así como la captación, tratamiento y uso eficiente de aguas pluviales;\nXIV. Participar con la Federación y con los Municipios para la planeación, realización y administración de las acciones de gestión de los recursos hídricos de competencia federal; infraestructura hidráulica a cargo del Estado;\nXVI. Fomentar y apoyar los servicios públicos urbanos y rurales de agua potable, alcantarillado, saneamiento, recirculación y reúso en el territorio del Estado y de los\nMunicipios, en tanto no impliquen restricción o menoscabo a las facultades de la Federación o de los Municipios;\nXVII. Impulsar y promover conjuntamente con las dependencias y entidades paraestatales de la Administración Pública que correspondan, y los Municipios, los programas de saneamiento, tratamiento y reúso de aguas, los de riego o drenaje y los de control de avenidas y protección contra inundaciones en el ámbito de su competencia;\nXVIII. Gestionar ante la Federación, el otorgamiento de concesiones y asignaciones para la explotación, uso o aprovechamiento de las aguas nacionales en cantidad y calidad, que estén bajo la administración y custodia del Estado y de la prestación de los servicios públicos de agua;\nXIX. Gestionar la celebración de convenios con la Federación y los Municipios, con la finalidad de mejorar y difundir permanentemente el conocimiento sobre la ocurrencia del agua en el ciclo hidrológico, la oferta y demanda de agua, los inventarios de la misma, suelo, usos y usuarios y de información pertinente vinculada con el agua y su gestión, así como la promoción de una gestión integrada de los recursos hídricos, con el apoyo que se considere necesario de usuarios del agua, organizaciones de la sociedad y particulares;\nXX. Promover la participación de la sociedad en la planeación, toma de decisiones, ejecución, evaluación y vigilancia de la política hídrica estatal;\nXXI. Coordinar la operación y actualización del sistema estatal de información de los servicios de agua potable, pluviales, alcantarillado sanitario y saneamiento, así como los de tratamiento y manejo de aguas residuales;\nXXII. Participar en el Sistema Estatal de Protección Civil y apoyar en la aplicación de los planes y programas para prevenir y atender situaciones de emergencia, causadas por fenómenos hidrometeorológicos extremos;\nXXIII. Apoyar a los organismos operadores del servicio en el desarrollo de programas aprovechamiento racional;\nXXIV. Elaborar y mantener actualizado, en coordinación con los Municipios, el inventario de los bienes y recursos del sistema de agua potable, alcantarillado y saneamiento, y de las reservas hidrológicas a cargo del Estado;\nXXV. Iniciar y aplicar los procedimientos administrativos e imponer las medidas correctivas y sancionadoras que procedan, por infracciones a la normatividad en materia hídrica Estatal, de acuerdo a sus atribuciones y conforme a los convenios y legislación aplicable;\nXXVI. Participar en reuniones tanto del ámbito binacional, federal, estatal y municipal en materia de servicio de agua potable, alcantarillado y saneamiento que correspondan al\nEstado;\nXXVII. Proponer a las instancias correspondientes políticas públicas, estrategias, programas, proyectos y acciones para hacer eficiente el uso de agua en riego, así como de los usos agropecuarios y acuícolas;\nXXVIII. Coadyuvar con las autoridades competentes en la creación de una educación y cultura ambiental en torno al cuidado y uso razonable del agua, en términos del Programa\nEstatal de Fomento a la Cultura del Cuidado y Uso Racional del Agua, y\nXXIX. Las que determinen las leyes, reglamentos y demás disposiciones aplicables.\nARTÍCULO 48. La Secretaría Anticorrupción y Buen Gobierno tendrá las atribuciones y obligaciones siguientes:\nPárrafo Reformado\nI. Organizar y coordinar la evaluación de la gestión gubernamental y de sus resultados, así como concertar y validar con las dependencias y entidades paraestatales de la Administración Pública, los indicadores de gestión para la evaluación de la gestión gubernamental, en los términos de las disposiciones aplicables;\nII. Inspeccionar el ejercicio del gasto público y su congruencia con los presupuestos de egresos;\nIII. Evaluar los resultados de la aplicación de los recursos públicos;\nIV. Promover el combate a la corrupción, impulsando los principios rectores de legalidad, respeto a la dignidad de las personas, disciplina, objetividad, profesionalismo, honradez, lealtad, imparcialidad, integridad, rendición de cuentas, eficacia y eficiencia que rigen el servicio público;\nV. Planear, programar, organizar, coordinar y supervisar el sistema de control interno;\nVI. Expedir, actualizar, difundir, sistematizar y supervisar la normatividad administrativa estatal y observar la de índole general y/o Federal que regulen el funcionamiento de los instrumentos, sistemas y procedimientos de control interno, fiscalización, transparencia, rendición de cuentas y datos abiertos de la Administración\nPública;\nVII. Elaborar un marco de referencia general de gestión gubernamental y vigilar su cumplimiento dentro de la Administración Pública, que impulse la transparencia, gobierno abierto, ética pública y rendición de cuentas, para prevenir, detectar, combatir y disuadir actos de corrupción;\nVIII. Opinar, en forma previa a su expedición, sobre los proyectos de normas de contabilidad gubernamental, control presupuestal, proyectos en materia de programación, presupuestación, administración de recursos humanos, materiales, financieros, contratación de deuda o manejo de fondos y valores, así como con respecto a la normatividad que expidan para regular las adquisiciones o arrendamiento de bienes y servicios y de obra pública, las dependencias y entidades paraestatales de la Administración Pública;\nIX. Opinar, en forma previa a su expedición, sobre los proyectos de iniciativas de leyes, reglamentos, acuerdos y lineamientos jurídicos que correspondan al ámbito de su competencia, cuando así se requiera;\nX. Designar y remover a los titulares de los órganos internos de control y de su personal adscrito, y de los comisarios públicos o su equivalente de las dependencias y entidades paraestatales de la Administración Pública, además de normar y controlar su desempeño;\nXI. Brindar asesoría y apoyo técnico a los órganos internos de control de los\nAyuntamientos, con base en los convenios y acuerdos celebrados con éstos, en materia de prevención de faltas administrativas, transparencia, rendición de cuentas y combate a la corrupción, para el fortalecimiento del Sistema de Control, del Sistema Estatal de\nFiscalización, de Evaluación Municipal y del combate a la corrupción;\nXII. Suscribir convenios de coordinación con las autoridades federales, estatales, municipales, órganos constitucionales autónomos, organismos públicos autónomos, entidades federativas, instituciones académicas y científicas, organismos gubernamentales extranjeros u organizaciones internacionales o con particulares en materia de Control\nInterno, Transparencia, Rendición de Cuentas, Fiscalización, Ética Pública y Combate a la\nXIII. Impulsar que en el desarrollo de los sistemas y programas a su cargo se promueva y asegure la participación ciudadana bajo los principios de gobierno abierto, transparencia y máxima publicidad;\nXIV. Organizar y coordinar los comités de protección de los recursos públicos, como recursos públicos, a fin de que sean aprovechados y aplicados en beneficio de la colectividad;\nXV. Evaluar los programas y acciones destinados a asegurar la buena calidad en las funciones y servicios a cargo de las dependencias y entidades de la Administración Pública, a fin que los recursos humanos, materiales y financieros, sean cabalmente aprovechados y aplicados, con criterios de eficacia, legalidad, eficiencia, simplificación administrativa, productividad, ahorro en el gasto público y transparencia, apoyando las acciones para la descentralización o desconcentración de los servicios, de conformidad con la normatividad aplicable;\nXVI. Establecer las bases generales para la realización de auditorías internas, transversales y externas, así como realizar las que requieran las dependencias y entidades paraestatales de la Administración Pública, en sustitución o apoyo de sus propios órganos internos de control;\nXVII. Expedir las normas que regulen los instrumentos y procedimientos de auditoría en las dependencias y entidades paraestatales de la Administración Pública;\nXVIII. Fiscalizar directamente o a través de los órganos internos de control, que las dependencias y entidades paraestales de la Administración Pública cumplan con las normas y disposiciones en materia de sistemas de registro y contabilidad, contratación y remuneraciones de personal, contratación de adquisiciones, arrendamientos, arrendamiento financiero, servicios y ejecución de obra pública, conservación, uso, destino, afectación, enajenación y baja de bienes muebles e inmuebles, almacenes y demás activos y recursos materiales;\nXIX. Auditar, revisar y evaluar técnica y financieramente los recursos federales ejercidos por las dependencias y entidades paraestatales de la Administración Pública, derivados de los acuerdos o convenios suscritos, así como establecer los esquemas de vigilancia y control preventivo, definiendo los mecanismos de interrelación entre los diferentes instrumentos de control interno;\nXX. Establecer y mantener coordinación e intercambiar información y documentación con la Auditoría Superior del Estado, sobre las normas, procedimientos y sistemas de justificativos y comprobatorios del ingreso y del gasto público;\nXXI. Recibir de la Auditoría Superior del Estado, los informes sobre las irregularidades en los procedimientos y sistemas de contabilidad que localice al revisar la Cuenta Pública, para dictar las medidas que correspondan, en coordinación con la Secretaría de Hacienda;\nXXII. Recibir y registrar la declaración de situación patrimonial, la declaración de intereses, la presentación de la constancia de declaración fiscal y determinar el conflicto de intereses de los servidores públicos del Estado, así como registrar la información sobre las sanciones administrativas que, en su caso, les hayan sido impuestas;\nXXIII. Atender y dar seguimiento a las denuncias y quejas que presenten los particulares con motivo de acuerdos, convenios o contratos que celebren con las dependencias, entidades paraestatales, organismos auxiliares y fideicomisos de la\nAdministración Pública, así como de las empresas de participación estatal, sociedades o asociaciones asimiladas a éstas;\nXXIV. Conocer e investigar los actos, omisiones o conductas de las o los servidores públicos que puedan constituir responsabilidades administrativas, substanciar los procedimientos correspondientes, por sí, o por conducto de los órganos internos de control que correspondan a cada área de la Administración Pública; así como coordinarse con la\nConsejería Jurídica para un eficaz seguimiento a las quejas o denuncias por actos de corrupción que involucren a las dependencias y entidades paraestatales de la Administración\nPública o a las o los servidores públicos que las integren;\nXXV. Requerir a las dependencias y entidades paraestatales de la Administración\nPública que coadyuven en la práctica de diligencias que se estimen pertinentes para la debida investigación, substanciación, trámite y resolución de los procedimientos de responsabilidades de las y los servidores públicos y, en su caso, en los recursos administrativos que interpongan;\nXXVI. Realizar investigaciones, inspecciones y supervisiones, a través de acciones encubiertas y usuario simulado, para verificar la legalidad, honradez, eficiencia y oportunidad de la prestación del servicio público;\nXXVII. Aplicar las sanciones en los casos que no sean de la competencia del Tribunal de Justicia Administrativa de Baja California y cuando se trate de faltas administrativas graves, ejercer la acción de responsabilidad ante ese Tribunal, así como presentar las denuncias correspondientes ante las autoridades competentes, en términos de las disposiciones legales aplicables;\nXXVIII. Establecer mecanismos internos para que la Administración Pública prevenga actos u omisiones que pudieran constituir responsabilidades administrativas;\nXXIX. Vigilar el cumplimiento de las normas internas por parte de sus servidores públicos e investigar las que pudieran constituir las responsabilidades administrativas, aplicándoles las correcciones que correspondan y, en su caso, formular y presentar las denuncias, querellas, acusaciones o quejas de naturaleza administrativa o penal ante las autoridades competentes;\nXXX. Intervenir en las actas de entrega-recepción de las unidades administrativas de las dependencias y entidades paraestatales de la Administración Pública, y emitir los lineamientos y manuales que se requieran para tales efectos, en los términos de la Ley de la materia;\nXXXI. Informar periódicamente al Comité́ Coordinador del Sistema Estatal\nAnticorrupción, así ́ como a la Persona Titular del Poder Ejecutivo del Estado, sobre los resultados de la evaluación de la gestión y de la revisión del ingreso, manejo, custodia y ejercicio de recursos públicos estatales, de las dependencias y entidades paraestatales de la\nAdministración Pública y, en su caso, promover ante las autoridades competentes las acciones que procedan para corregir las irregularidades detectadas;\nXXXII. Vigilar, en colaboración con las autoridades que integren el Comité́\nCoordinador del Sistema Estatal Anticorrupción, el cumplimiento de las normas de control interno y fiscalización, así ́ como asesorar y apoyar a los órganos internos de control de las dependencias y entidades paraestatales de la Administración Pública;\nXXXIII. Establecer los mecanismos de coordinación con los integrantes de los\nSistemas Nacional y Estatal de Fiscalización, así como los Sistemas Nacional y Estatal\nAnticorrupción, para la identificación de áreas comunes de auditoría y fiscalización, incluyendo la revisión de los ordenamientos legales en la materia y la formulación de propuestas que mejoren la eficacia del combate a la corrupción;\nXXXIV. Coordinarse con los Sistemas Nacional y Estatal de Fiscalización, así como con los Sistemas Nacional y Estatal Anticorrupción, en la ejecución de acciones en los rubros relacionados con el ejercicio de recursos federales, dirigidas a evaluar los avances y resultados generales de las dependencias y entidades paraestatales de la Administración\nPública en el desarrollo y cumplimiento de los respectivos planes, programas y presupuestos, conforme a las directrices que se deriven de dichos Sistemas;\nXXXV. Implementar las acciones que se acuerden en los Sistemas Nacional y Estatal de Fiscalización, así como en los Sistemas Nacional y Estatal Anticorrupción, en términos de las disposiciones aplicables;\nXXXVI. Llevar el control y funcionamiento de la Comisión Estatal de Avalúos y del manejo de los recursos que esta genere con motivo del pago de sus servicios;\nXXXVII. Llevar el registro electrónico que establece el artículo 28 de la presente Ley;\nXXXVIII. Proponer, coordinar la integración, organización y funcionamiento de comités ciudadanos de vigilancia, obras públicas y licitaciones de recurso Estatal y Federal;\nXXXIX. Vigilar la aplicación de las políticas de gobierno digital, de gobierno abierto, y datos abiertos de la Administración Pública, en los términos de las disposiciones aplicables;\nXL. Coadyuvar en la revisión del cumplimiento en materia de archivos que emitan las instancias correspondientes;\nFracción Reformada\nXLI. Ejercer las atribuciones que le correspondan en materia de transparencia, acceso a la información pública y protección de datos personales, de conformidad con las disposiciones jurídicas aplicables, así como conocer de los procedimientos relativos a su protección, verificación e imposición de sanciones;\nFracción Adicionada\nXLII. Establecer las políticas, bases y normativa para la determinación de la información de interés público que, en materia de anticorrupción y buen gobierno, se deba difundir proactivamente;\nFracción Adicionada\nXLIII. Promover y consolidar los principios de la transparencia y acceso a la información pública, y los mecanismos de participación ciudadana en la ejecución y evaluación de la gestión pública;\nFracción Adicionada\nXLIV. Impulsar la transparencia proactiva y la publicación de datos en formatos accesibles a la ciudadanía; vigilar la aplicación de las políticas de gobierno digital y las de gobierno y datos abiertos de la Administración Pública Estatal, en términos de las disposiciones jurídicas aplicables; y,\nFracción Adicionada\nXLV. Las que determinen las leyes, reglamentos y demás disposiciones aplicables.\nFracción Recorrida\nArtículo Reformado\nARTÍCULO 49. La Secretaría de Cultura tendrá las atribuciones y obligaciones siguientes:\nI. Preservar, promover y difundir la cultura y las artes de forma inclusiva en el Estado, así como generar las condiciones necesarias para que la sociedad tenga acceso a bienes, servicios, actividades artísticas y culturales, como elementos esenciales del desarrollo humano integral, dentro de un marco de respeto y tolerancia a la diversidad cultural;\nII. Ejercer las atribuciones que la legislación federal en materia de cultura establece para los Estados, así como las atribuciones descentralizadas por la Federación hacia los\nEstados mediante convenios;\nIII. Diseñar y aplicar la política cultural del Estado, en coordinación con la Federación y los Municipios y, en particular, coordinar, implementar y ejecutar el Programa Estatal de\nCultura;\nIV. Celebrar los convenios que resulten necesarios para lograr la adecuada coordinación interinstitucional, así como el cumplimiento en general de los objetivos de la política cultural del Estado;\nV. Promover, organizar y convocar en colaboración con otros órdenes de gobierno nacionales e internacionales, instituciones u organismos públicos o de interés estatal, la celebración de eventos en temas de interés cultural, artísticos o tendentes al mejoramiento cultural, y a la difusión de las bellas artes y los artes tradicionales o populares, así como organizar la feria estatal del libro;\nVI. Definir políticas y establecer estrategias que impulsen el desarrollo cultural de niños, niñas, adolescentes y las juventudes, personas adultas mayores y personas con discapacidad, que motiven la participación de este sector de la sociedad en la actividad cultural del Estado, así como vigilar su efectivo acceso a los servicios culturales;\nVII. Proponer procedimientos e integrar jurados y comisiones dictaminadoras para los concursos, becas y premios que promueva o los que sean promovidos por particulares que lo soliciten;\nFracción Reformada\nVIII. Administrar, coordinar y conservar los bienes muebles e inmuebles destinados a la preservación, promoción y difusión cultural y artística en el Estado;\nIX. Promover y administrar la apertura de nuevos centros y fuentes de cultura y arte que respondan a las iniciativas y a los procesos socioculturales del Estado;\nX. Coordinar con las dependencias y entidades paraestatales de la Administración\nPública, programas y acciones culturales de carácter comunitario en lugares donde se identifiquen problemáticas sociales específicas;\nXI. Instrumentar acciones y programas encaminados a que los espacios públicos recuperados se destinen a actividades culturales, en coordinación con la dependencia de la\nAdministración Pública que corresponda;\nXII. Promover y preservar los valores artísticos e históricos del Estado;\nXIII. Promover, apoyar y gestionar la preservación e incremento del patrimonio histórico originario, artístico, cultural y arquitectónico del Estado;\nXIV. Proteger, conservar y difundir el patrimonio cultural del Estado;\nXV. Fomentar programas y proyectos que promuevan la cultura, el patrimonio, la historia, el arte, las artesanías, la música de los pueblos originarios, así como promover su lengua indígena y el conocimiento tradicional de los usos medicinales de las plantas nativas;\nXVI. Fomentar la identidad colectiva estatal mediante el impulso de la memoria histórica y cultural regional, caracterizada por el reconocimiento de los pueblos originarios y la diversidad cultural generada por migraciones, individuales o colectivas, que se han establecido en el Estado;\nXVII. Fomentar, apoyar y gestionar las manifestaciones de la creación intelectual, artística y cultural de la población del Estado;\nXVIII. Promover, apoyar y gestionar las investigaciones estéticas, artísticas e intelectuales del Estado;\nXIX. Auspiciar la investigación, preservación, promoción y difusión de la cultura y las artes en general y, particularmente las que identifican a los bajacalifornianos;\nXX. Se deroga.\nFracción Derogada\nXXI. Fomentar la investigación de las manifestaciones culturales propias de cada\nMunicipio, sus ferias, tradiciones y costumbres;\nXXII. Proponer directrices en materia de educación y capacitación artística, así como diseñar esquemas curriculares y extracurriculares de sensibilización a la cultura y el arte;\nXXIII. Impulsar, conforme a su capacidad presupuestal, la producción literaria, pictórica, cinematográfica, de radio, televisión o digital, cuyo contenido tenga un enfoque preponderantemente regional, que exhiba o represente la topografía, paisajes, sitios naturales y diversidad biológica, presente o extinta del Estado;\nXXIV. Promover un programa para la edición o co-edición de obras de autores regionales, de obras agotadas, así como proponer la edición de libros premiados en los concursos literarios, cuyos autores sean residentes del Estado, con el objetivo de fomentar la identidad cultural regional;\nXXV. Promover un programa de fomento a la lectura con especial atención a niños, niñas, adolescentes y las juventudes, a través de presentación de lecturas dramatizadas y talleres, así como al público general por medio de concursos literarios, publicación de obras literarias y difusión de autores del Estado, con la finalidad de desarrollar el gusto por la lectura y la promoción de la cultura regional entre los residentes del Estado;\nXXVI. Promover y fomentar la adquisición de material didáctico y de lectura para personas con discapacidad en centros culturales y bibliotecas; así como promover ante acceder a libros y contenidos digitales;\nXXVII. Se deroga.\nFracción Derogada\nXXVIII. Impulsar, apoyar y promover a las personas y grupos interesados en la difusión de la cultura y las artes en el Estado;\nFracción Adicionada\nXXIX. Reconocer a las personas residentes en el Estado y a la población bajacaliforniana que se hayan distinguido en las distintas áreas de la cultura, artes, educación e investigación;\nFracción Adicionada\nXXX. Fomentar programas de intercambio cultural y artístico a nivel nacional y el extranjero para fortalecer el conocimiento y desarrollo de nuestros valores;\nFracción Adicionada\nXXXI. Formular estrategias que impulsen el reconocimiento de artistas, así como de las personas que promuevan y gestionen cultura o arte, dentro de los sectores público y privado;\nFracción Adicionada\nXXXII. Gestionar la instalación de sistemas electrónicos, de radio, televisión, internet o de cualquier otro tipo, para la promoción cultural y artística, ya sean propios o a través de convenios con diversas instancias, cumpliendo con lo dispuesto por las leyes federales y estatales vigentes en la materia;\nFracción Adicionada\nXXXIII. Fomentar las actividades culturales y artísticas entre el personal al servicio del\nFracción Adicionada\nXXXIV. Coordinar y promover acciones conjuntas con los ayuntamientos del Estado en cuanto a programas y actividades en beneficio de la comunidad, así como para la integración de las comisiones municipales para la preservación, promoción y difusión de la cultura y las artes;\nFracción Adicionada\nXXXV. Interactuar con instituciones públicas, como complemento en aquellos programas que tiendan al fortalecimiento del desarrollo cultural y artístico del Estado, principalmente en áreas rurales; y,\nFracción Adicionada\nXXXVI. Las que determinen las leyes, reglamentos y demás disposiciones aplicables.\nFracción Recorrida\nArtículo Reformado\nARTÍCULO 49 BIS.- La Secretaría de las Mujeres tendrá las atribuciones y obligaciones siguientes:\nI. Establecer y conducir la instrumentación, coordinación, supervisión, seguimiento, implementación y evaluación en el ámbito de su competencia, de la Política Estatal en materia de:\na) Mujeres, adolescentes y niñas, igualdad sustantiva y transversalización de la perspectiva de género.\nb) Prevención, atención y erradicación de las violencias contra las mujeres, adolescentes y niñas.\nc) Sistema de cuidados.\nII. Incorporar el principio de igualdad de derechos y oportunidades de desarrollo para la mujer en la formulación de políticas públicas;\nIII. Impulsar las propuestas de la sociedad para alcanzar la igualdad de derechos y oportunidades de desarrollo para la mujer en el ámbito político, social, cultural y económico;\nIV. Impulsar la incorporación de los lineamientos del Programa en el programa anual de cada dependencia y entidad de la Administración Pública del Estado, así como en el de los sectores en general vinculados con estos instrumentos, para la ejecución de sus programas sectoriales o, en su caso, institucionales específicos;\nV. Establecer y concertar acuerdos y convenios con las autoridades de los tres órdenes de gobierno para promover, con la participación, en su caso, de los sectores social y privado, las políticas, acciones y subprogramas que se establezcan en el Programa;\nVI. Elaborar lineamientos y protocolos de atención, manejo e intervención dirigidos a las dependencias y entidades paraestatales de la Administración Pública, que contribuyan a la erradicación de cualquier manifestación de discriminación contra las Mujeres;\nVII. Procurar, impulsar y apoyar ante los poderes públicos del Estado, acciones dirigidas al ejercicio pleno de los derechos de las mujeres, así como el fortalecimiento de mecanismos administrativos para el mismo fin;\nVIII. Establecer y operar en coordinación con el Comité de Planeación del Desarrollo del Estado y otras dependencias del Ejecutivo, un sistema de seguimiento de los programas federales, estatales y municipales relacionados con la mujer, de conformidad con lo previsto en las leyes y convenios respectivos;\nIX. Establecer vínculos de colaboración con el Poder Legislativo y con los\nAyuntamientos del Estado, para promover acciones legislativas y reglamentarias que garanticen a las mujeres la igualdad de derechos y oportunidades de desarrollo;\nX. Impulsar el empoderamiento de las mujeres en cuanto a su participación, promoción y capacitación en la toma de decisiones y en áreas de emprendimiento, en coordinación con las dependencias y entidades paraestatales de la Administración Pública;\nXI. Crear mecanismos de coordinación institucional con instancias del Gobierno\nFederal, Estatal y Municipal, organismos no gubernamentales, instituciones de educación o investigación públicas o privadas para la promoción de los derechos humanos de la Mujer en los programas y políticas públicas;\nXII. Desarrollar acciones necesarias para impulsar la igualdad sustantiva en todas las áreas de la vida económica, política, social y cultural del Estado, así como instrumentar mecanismos de ejecución y evaluación que permitan alcanzar el pleno desarrollo de la personalidad desde una perspectiva de derechos humanos;\nXIII. Gestionar programas de difusión y acciones de sensibilización en medios de comunicación masiva y redes sociales, que promuevan una cultura libre de violencia de género contra la mujer, e incentivar la elaboración de programas educativos y campañas de concientización;\nXIV. Proponer la creación de refugios seguros para víctimas de la violencia en términos de la Ley de Acceso a las Mujeres a una Vida Libre de Violencia para el Estado, así del Estado de Baja California;\nXV. Coadyuvar con el sector público y privado en las demandas, necesidades y exigencias en materia de derechos humanos de las Mujeres en el Estado, haciendo énfasis en las áreas de salud, empleo, educación, capacitación, seguridad, justicia, cultura y recreación;\nXVI. Establecer vínculos de colaboración con las instancias administrativas que se ocupen de los asuntos de las mujeres en los Ayuntamientos para promover y apoyar, en su caso, las políticas, programas, y acciones en materia de igualdad de oportunidades y desarrollo para las mujeres;\nXVII. Promover la prestación de servicios de seguridad social en apoyo a madres trabajadoras;\nXVIII. Promover ante las autoridades competentes que los contenidos y materiales educativos estén libres de prejuicios discriminatorios contra las mujeres y que fomenten la igualdad de derechos y oportunidades;\nXIX. Promover ante las autoridades competentes que se garantice el acceso de la mujer, y se aliente su permanencia o reingreso a las instituciones educativas en todos sus niveles, impulsando además a través del proceso de enseñanza-aprendizaje, la igualdad de oportunidades para hombres y mujeres;\nXX. Propiciar y fomentar el acceso de las mujeres de la tercera edad, con discapacidad y pertenecientes a pueblos originarios o afromexicanos, a todo tipo de programas destinados a la mujer;\nXXI. Promover ante las autoridades Federales, Estatales y Municipales en materia de salud, el acceso de las mujeres a servicios integrales de atención a la salud, considerando las características particulares de su ciclo de vida y condición social;\nXXII. Promover en coordinación con otras dependencias del Ejecutivo, acciones de combate a la pobreza, marginación y exclusión de las mujeres de las actividades económicas, culturales y sociales de la entidad, especialmente en el medio rural e indígena;\nXXIII. Participar, en el ámbito de su competencia, en la atención y seguimiento de la declaratoria de alerta de violencia de género contra las mujeres, emitida por la Secretaría de\nGobernación del Gobierno Federal, notificada al Poder Ejecutivo;\nXXIV. Estimular y fomentar la participación activa de las organizaciones que actúan en la promoción y defensa de los derechos de la mujer, en las tareas de formulación, ejecución, seguimiento y evaluación de las políticas y acciones públicas orientadas al desarrollo integral de la mujer;\nXXV. Promover ante las autoridades competentes la realización de acciones tendientes a prevenir, sancionar, atender y erradicar la violencia contra la mujer;\nXXVI. Promover acciones tendientes a reconocer las aportaciones de la mujer, derivadas de su participación en el desarrollo del Estado;\nXXVII. Impulsar en los medios de comunicación, una cultura de igualdad entre el hombre y la mujer, reconociendo y dignificando su imagen ante la sociedad;\nXXVIII. Proponer y ejecutar políticas, programas y acciones en materia de prevención, protección, atención y erradicación para el cumplimiento de una vida libre de violencia en contra de mujeres, niñas, niños y adolescentes en contexto de vulnerabilidad con un enfoque interseccional e intercultural, en coordinación con la Secretaría General de Gobierno y demás dependencias y entidades de la Administración Pública, así como con instituciones públicas y privadas; así como proponer las sanciones que correspondan;\nXXIX. Servir de enlace con organizaciones locales, nacionales e internacionales que apoyen proyectos dirigidos a la mujer, para lograr la captación de recursos y su adecuada distribución;\nXXX. Concertar y suscribir acuerdos de colaboración con organismos gubernamentales, no gubernamentales, públicos y privados, nacionales e internacionales, para el desarrollo de proyectos que beneficien a las mujeres;\nXXXI. Actuar como órgano de consulta, capacitación y asesoría de las dependencias y entidades de la Administración Pública del Estado, los poderes Legislativo y Judicial, los\nÓrganos Autónomos, así como de las Municipales, y de los sectores social y privado, en materia de equidad e igualdad de derechos y oportunidades para las mujeres;\nXXXII. Promover la ejecución de acciones para el reconocimiento público de las mujeres, así como para la difusión nacional e internacional de las actividades que las benefician;\nXXXIII. Promover estudios e investigaciones para instrumentar un sistema de información, registro, seguimiento y evaluación de las condiciones sociales, políticas, económicas y culturales de las mujeres en los distintos ámbitos de la sociedad;\nXXXIV. Participar y organizar reuniones y eventos para el intercambio de experiencias e información en los ámbitos de su competencia sobre los temas de las mujeres;\nXXXV. Promover, difundir y publicar obras relacionadas con las materias objeto de esta Ley;\nXXXVI. Promover las aportaciones de recursos provenientes de dependencias e instituciones públicas, organizaciones privadas y sociales, interesadas en apoyar el logro de la igualdad entre hombres y mujeres;\nXXXVII. Impulsar la cooperación nacional e internacional, para el apoyo financiero y técnico en la materia de igualdad sustantiva entre hombres y mujeres, de conformidad con las disposiciones aplicables;\nXXXVIII. Emitir informes de evaluación periódica para dar cuenta de resultados en el cumplimiento de los objetivos, estrategias y políticas del Programa, mismos que deberán contener las acciones, metas, indicadores y esquemas de medición necesarios para determinar el cumplimiento de sus objetivos;\nXXXIX. Actualizar anualmente el diagnóstico sobre la situación de las mujeres, en bases:\na) El diagnóstico deberá reflejar por lo menos, el porcentaje de participación de las mujeres en la dinámica social, política y económica de la entidad; el acceso de las mujeres a la educación superior y media superior; así como el índice de violencia familiar y de género contra la mujer a nivel estatal, y por municipio.\nb) Para la elaboración del diagnóstico, el instituto invitará a los organismos de la sociedad civil dedicados a temas de la mujer, para que, en los términos del reglamento respectivo, participen de manera activa en la fase de investigación e integración del mismo.\nc) La actualización del diagnóstico deberá prever la integración de avances bimestrales en cada uno de los rubros en que este se estructure.\nXL. Llevar a cabo todas las acciones que conforme a la normatividad en materia de prevención, atención, sanción y erradicación de violencia en contra de las mujeres le correspondan;\nXLI. Proponer e implementar acciones enfocadas a reflexionar, generar cambios de actitud y motivar a las mujeres a participar en talleres y cursos de emprendimiento de oficios, tradicionalmente dirigidos a hombres;\nXLII. Proponer, implementar y/o fomentar talleres y cursos de emprendimiento, para las mujeres de oficios tradicionalmente dirigidos a hombres; debiendo darse la máxima publicidad;\nXLIII. Diseñar, promover e implementar políticas públicas y acciones en materia de salud integral de las mujeres, con especial énfasis en la garantía de sus derechos sexuales y reproductivos, en coordinación con la Secretaría de Salud y las instituciones integrantes del\nSistema Estatal de Salud;\nXLIV. Participar y representar al Estado en foros, redes y mecanismos de cooperación nacionales e internacionales en el ámbito de competencia de la Secretaría de las Mujeres; y.\nXLV. Las demás que señale el reglamento de esta Ley.\nArtículo Adicionado\nDe conformidad con el Artículo Primero Transitorio, Fracción II, del Decreto 119, publicado en el Periódico Oficial de fecha 21 de\nARTICULO 50. La Dirección del Registro Público de la Propiedad y del Comercio tendrá las atribuciones y obligaciones siguientes:\nI. Realizar la actividad registral en el Estado y dar publicidad a la situación jurídica de bienes y derechos, así como a los actos jurídicos que lo requieran para surtir eficacia ante terceros en los términos de ley, a fin de otorgar certeza y seguridad jurídica a los mismos.\nII. Promover, organizar, vigilar y controlar el funcionamiento del Registro Público de la\nPropiedad y del Comercio;\nIII. Efectuar las inscripciones de los actos o contratos relativos, después de que se hayan satisfecho los requisitos legales;\nIV. Expedir copias certificadas de las inscripciones o constancias que figuren en los\nLibros de Registro, así como certificaciones de no existir asientos de ninguna especie o de especie determinada sobre bienes señalados o a cargo de ciertas personas;\nV. Formular la liquidación de los derechos de carácter fiscal que se causen por concepto de la inscripción registral, previo pago de los mismos;\nVI. Dar aviso a la Secretaría de Hacienda cuando tenga conocimiento de los casos en que los particulares no hayan dado cumplimiento a las disposiciones fiscales aplicables, debiéndose abstener de realizar trámite alguno mientras exista esa situación;\nVII. Dar los avisos correspondientes cuando en el ejercicio de las funciones de fe pública se implique la realización de actividades vulnerables en términos de la Ley Federal para la Prevención e Identificación de Operaciones con Recursos de Procedencia Ilícita;\nVIII. Desahogar las consultas que, de acuerdo con las disposiciones de la materia, hagan los interesados;\nIX. Permitir que las inscripciones sean examinadas dentro de las horas de labores por los interesados cuando acudan a las oficinas, pudiendo éstos tomar las notas y apuntes que juzguen necesarios;\nX. Diseñar, operar y evaluar el Sistema de Información Registral integral, y dar acceso a los interesados a la información ahí contenida de forma digital, de acuerdo a lo previsto en las disposiciones legales aplicables, y\nXI. Las que determinen las leyes, reglamentos y demás disposiciones aplicables.\nARTÍCULO 51. La Dirección de Comunicación Social tendrá las atribuciones y obligaciones siguientes: dependencias y entidades paraestatales de la Administración Pública, basándose en los\nII. Fungir como área normativa y de consulta en materia de comunicación social de la\nAdministración Pública;\nIII. Planear, diseñar y ejecutar las campañas de difusión publicitaria de la Persona\nTitular del Poder Ejecutivo y de las dependencias de la Administración Pública;\nIV. Promover mecanismos de difusión de información gubernamental a través del uso de las tecnologías y las plataformas digitales;\nV. Difundir las actividades públicas de la Persona Titular del Poder Ejecutivo y las que desarrollen las dependencias de la Administración Pública y, en su caso, las de las entidades paraestatales que así lo soliciten;\nVI. Difundir los programas sociales del Poder Ejecutivo y las acciones que realicen los servidores o servidoras públicos de las dependencias de la Administración Pública;\nVII. Supervisar y coordinar la información que se difunde sobre los programas o acciones de gobierno de las entidades paraestatales de la Administración Pública;\nVIII. Proporcionar información escrita, gráfica y/o grabada a los medios masivos de comunicación social que emita la Persona Titular del Poder Ejecutivo y las dependencias de la Administración Pública y, en su caso, de las entidades paraestatales que así lo soliciten;\nIX. Promover y coordinar entrevistas a la Persona Titular del Poder Ejecutivo y servidores o servidoras públicos de la Administración Pública;\nX. Asistir a giras y pre-giras para la designación de espacios para medios de servidores o servidoras públicos de la Administración Pública, y documentar con material fotográfico y/o en la forma en que las tecnologías de la información lo permitan;\nXI. Desarrollar investigaciones de opinión pública respecto de la imagen general del\nEjecutivo y de las dependencias y entidades paraestatales de la Administración Pública;\nXII. Ejercer el recurso presupuestal que le sea asignado, y distribuirlo entre las unidades administrativas a su cargo, así como coordinar el uso y destino del ejercicio del paraestatales de la Administración Pública;\nXIII. Emitir opinión previo al nombramiento y, en su caso, solicitar la remoción de las titularidades de las áreas responsables de comunicación social de las dependencias y entidades paraestatales de la Administración Pública;\nXIV. Atender, coordinar y monitorear a los medios de comunicación social respecto de información o seguimiento a la misma, de interés para la Persona Titular del Poder Ejecutivo, así como del manejo de información institucional que se difunda; y,\nXV. Las que determinen las leyes, reglamentos y demás disposiciones aplicables.\nTÍTULO CUARTO\nDE LA ADMINISTRACIÓN PÚBLICA PARAESTATAL\nCAPÍTULO I\nDISPOSICIONES GENERALES\nARTÍCULO 52. Los organismos descentralizados, las empresas de participación estatal mayoritaria y minoritaria, así como los fideicomisos públicos que se constituyan en el\nEstado, integran la Administración Pública Paraestatal, y serán coordinados en atención a su naturaleza jurídica por las dependencias, de conformidad a la ley de la materia y al acuerdo especial de sectorización que corresponda.\nLas leyes o decretos que establezcan la creación de las entidades paraestatales, determinarán sus atribuciones, el grado de autonomía, normas de funcionamiento, y las relaciones que deban darse entre éstas y el Poder Ejecutivo.\nARTÍCULO 53. Las personas titulares de las entidades paraestatales, podrán ser invitadas a las reuniones convocadas por la Coordinación de Gabinete, cuando así lo\nARTÍCULO 54. Los bienes que hayan formado parte de entidades paraestatales que se extingan serán incorporados al dominio público o privado del Estado, según su naturaleza.\nARTÍCULO 55. Para la interpretación de controversias que surjan entre dependencias y entidades paraestatales de la Administración Pública de un mismo sector; para prever organismos, se estará a lo que dispone el artículo 3 de esta Ley. de la Administración Pública, para fines de congruencia global de éstas con el Sistema\nEstatal de Planeación y con los lineamientos generales en materia de gasto, financiamiento, control y evaluación, se llevarán a cabo en la forma y términos que dispongan las leyes, por conducto de las dependencias a que se refiere el artículo 59 de esta Ley, en el ámbito de sus respectivas competencias, sin perjuicio de las atribuciones que competan a la coordinadora del sector.\nLas dependencias a que se refiere el párrafo anterior, emitirán los criterios para la clasificación de las entidades paraestatales de la Administración Pública conforme a sus objetivos y actividades, en aquellas que cumplan una función institucional y las que realicen fines comerciales con el propósito de, en su caso, establecer mecanismos diferenciados que hagan eficiente su organización, funcionamiento, control y evaluación. Los mecanismos contemplarán un análisis sobre los beneficios y costos de instrumentar prácticas de gobierno corporativo en las entidades paraestatales con fines comerciales, a efecto de considerar la conveniencia de su adopción.\nCAPÍTULO II\nDE LOS ORGANISMOS DESCENTRALIZADOS\nARTÍCULO 57. Los Organismos Descentralizados son entidades jurídicas públicas, con autonomía de gestión, personalidad y patrimonio propio, cualquiera que sea la forma o estructura legal que adopten.\nPodrán ser creados por ley o decreto del Congreso del Estado, o por decreto o acuerdo especial de la Persona Titular del Poder Ejecutivo, cuando la prestación de los servicios públicos o sociales, la explotación de bienes o recursos propiedad del Estado, la investigación científica y tecnológica o la obtención y aplicación de recursos para fines de asistencia o seguridad social, por su naturaleza y fines requieran ser atendidos de manera especial.\nEl instrumento de creación de los Organismos Descentralizados deberá:\nI. Precisar su objeto, fuente de recursos para conformar su patrimonio, integración del órgano de gobierno y la forma de nombrar a su titular y sus funciones; y,\nII. Observar y preservar la rectoría de los planes de Gobierno e incorporar las facultades de supraordenación y coordinación, que la presente Ley reserva a la Persona descentralizados, deberán observar lo dispuesto en la fracción VIII del artículo 27 de la presente Ley.\nARTICULO 58. Cuando algún Organismo Descentralizado no cumpla sus fines u objeto, o su funcionamiento no convenga para la economía o interés público, o de la comunidad, se procederá a su extinción, de conformidad con su naturaleza jurídica y en disposiciones aplicables.\nLa Secretaría de Hacienda atendiendo la opinión de la dependencia coordinadora del sector que corresponda, propondrá a la Persona Titular del Poder Ejecutivo la disolución, liquidación o extinción de aquél. Asimismo, podrá proponer su fusión, cuando su actividad combinada redunde en un crecimiento de eficiencia y productividad.\nARTÍCULO 59. Para lograr un control eficaz del régimen patrimonial y financiero de los Organismos Descentralizados, deberán observarse las normas siguientes:\nI. Corresponde a la Secretaría de Hacienda calcular anualmente sus ingresos, así como autorizar los financiamientos que constituyan la deuda pública y orientar sus planes y programas para que concurran al logro de los objetivos y se ajusten a las prioridades del desarrollo estatal, así como proyectar y calcular anualmente sus egresos, y\nII. Corresponde a la Secretaría Anticorrupción y Buen Gobierno, evaluar su operación y gestión pública y vigilar su funcionamiento, lo cual podrá realizar por sí o a través de los órganos internos de control adscritos a los Organismos Descentralizados.\nPárrafo de la Fracción Reformado\nLos órganos internos de control dependerán jerárquicamente, técnica y funcionalmente de la Secretaría Anticorrupción y Buen Gobierno ejercerán, las facultades que establezcan las leyes, y la normatividad y los lineamientos que aquella emita.\nPárrafo de la Fracción Reformado\nFracción Reformada\nARTÍCULO 60. El personal de base que presta sus servicios en los Organismos\nDescentralizados se rige por la Ley del Servicio Civil y por los Estatutos del Sindicato Único\nDescentralizadas de Baja California, y tendrá los mismos derechos y obligaciones que corresponden al personal que presta sus servicios en la Administración Pública Centralizada.\nCAPÍTULO III\nDE LAS EMPRESAS DE PARTICIPACIÓN ESTATAL cumplimiento estricto de sus fines, podrá asociarse a particulares en cualquiera de las formas que permiten las leyes mexicanas, previa autorización del Congreso del Estado, cuando se trate de apoyar actividades estratégicas del desarrollo económico.\nLey.\nARTÍCULO 62. Son empresas de participación estatal mayoritaria aquellas que satisfagan cualquiera de los requisitos siguientes: o separadamente, aporten o sean propietarias del 50 por ciento o más del capital social;\nII. Que en la constitución de su capital social figuren acciones de serie especial que sólo puedan ser suscritas por el Poder Ejecutivo; y,\nIII. Que a la Persona Titular del Poder Ejecutivo corresponda la atribución de nombrar a la mayoría de los miembros del Consejo de Administración y/o al Órgano Directivo equivalente, designar a la presidencia, la dirección o la gerencia, o cuando tenga atribuciones para vetar los acuerdos de la Asamblea General de Accionistas, Consejo de\nAdministración u Órgano de Gobierno equivalente.\nARTÍCULO 63. Para efectos de esta Ley, se asimilan a las empresas de participación estatal mayoritaria las sociedades y asociaciones civiles en que la mayoría de los asociados sean dependencias o entidades de la Administración Pública, o cuando alguno o varios de ellos se obliguen a realizar o realicen las aportaciones económicas preponderantes.\nARTÍCULO 64. En las empresas de participación estatal minoritaria donde el Poder\nEjecutivo, una o más entidades paraestatales consideradas conjunta o separadamente, representen menos del 50 por ciento de las acciones o parte del capital y hasta el 25 por ciento de aquél, la vigilancia de su participación estará a cargo de un Comisario designado por la Secretaría Anticorrupción y Buen Gobierno, quien además deberá reportar el desarrollo de las actividades que realiza la empresa a la persona titular de la dependencia coordinadora del sector correspondiente. autorización del Congreso del Estado podrán ser transferidos.\nPara el eficaz control del régimen patrimonial y financiero de esta participación, se estará a lo que establece el artículo 57 de esta Ley, excepto en las empresas de designar a la mayoría de los miembros del Consejo de Administración, o cuando carezca de atribuciones para vetar los acuerdos de la Asamblea General de Accionistas.\nCAPÍTULO IV\nDE LOS FIDEICOMISOS\nARTÍCULO 66. Para el cumplimiento de programas, proyectos específicos, ejecución de obras especiales, así como para la prestación de servicios públicos o sociales, la exploración de bienes o recursos públicos estatales, o bien para la obtención y aplicación de fideicomiso bienes y valores patrimoniales, señalando en su caso, la dependencia o entidad paraestatal que tendrá el carácter de fideicomisario.\nARTÍCULO 67. Para lograr el control eficaz del régimen patrimonial y financiero de los fideicomisos, en todo comité técnico que se constituya como órgano de dirección, deberán participar las dependencias a que se refiere el artículo 59 de esta Ley.\nCAPÍTULO V\nDE LA SECTORIZACIÓN\nARTÍCULO 68. La Persona Titular del Poder Ejecutivo, sin detrimento de las leyes, decretos o acuerdos especiales que establezcan la creación de las entidades paraestatales deberá emitir acuerdo especial que agrupe e identifique sectores en razón de la concurrencia de los fines u objetivos con las atribuciones de las dependencias de la\nAdministración Pública Centralizada, guardando la primacía que tienen éstas como auxiliares directas del Poder Ejecutivo para conducir la política del desarrollo estatal.\nARTÍCULO 69. El acuerdo de sectorización que obligue a las entidades paraestatales de la Administración Pública a coordinarse, deberá prever la participación de la persona titular de la dependencia que la encabeza en las juntas, consejo u órgano de gobierno equivalente.\nPRIMERO. La presente Ley deberá publicarse en el Periódico Oficial del Estado y entrará en vigor el primero de enero de dos mil veintidós.\nSEGUNDO. La Ley Orgánica de la Administración Pública del Estado de Baja\nCalifornia, publicada en el Periódico Oficial No. 49, de treinta y uno de octubre de dos mil diecinueve, Número Especial, Tomo CXXVI, quedará abrogada una vez que entre en vigor la presente Ley. adjetivos de la presente Ley, así como los nuevos reglamentos internos de las dependencias, seguirán aplicándose en lo conducente en todo lo que no se opongan a esta\nLey las disposiciones legales, reglamentarias y administrativas que regulaban los actos de que se trate con anterioridad.\nTERCERO. Dentro de un plazo no mayor de trescientos sesenta y cinco días siguientes a la entrada en vigor de la presente Ley, deberán expedirse las reformas de términos de esta Ley.\nCUARTO. Dentro del plazo de treinta días siguientes a la entrada en vigor de esta\nLey, se deberá conformar la comisión intersecretarial que tendrá como objeto realizar los trabajos para la elaboración de la iniciativa de ley que regule el servicio civil de carrera; la forma y términos para su funcionamiento será determinado por sus integrantes.\nLa comisión intersecretarial estará integrada por las titularidades, o las personas que estos designen, de las dependencias siguientes:\na) Secretaría General de Gobierno;\nb) Secretaría de Hacienda;\nc) Oficialía Mayor de Gobierno; y,\nd) Secretaría de la Honestidad y la Función Pública.\nLa Consejería Jurídica se integrará a la comisión intersecretarial una vez que inicie su funcionamiento.\nLa comisión intersecretarial tendrá un plazo no mayor de trescientos sesenta y cinco días a partir de su integración para presentar a la Persona Titular de Poder Ejecutivo el proyecto de iniciativa de ley que regule el servicio civil de carrera de las dependencias de la\nAdministración Pública.\nQUINTO. Se faculta a la Persona Titular del Poder Ejecutivo, para que en términos de la Ley correspondiente, realice las provisiones o ajustes necesarios al Presupuesto de\nEgresos para el ejercicio fiscal 2022, con el fin de que la nueva estructura orgánica del veintidós, debiendo comunicar de ello en los informes de evaluación del ejercicio del gasto público que rinda al Congreso del Estado.\nSEXTO. Los recursos humanos de las dependencias que se separan o transfieren funciones, transforman o modifican competencia que pasen o se adscriban a las dependencias a que se refiere la presente Ley, conservarán sus derechos laborales en términos de las leyes de la materia.\nSÉPTIMO. La Oficialía Mayor de Gobierno a partir de la publicación de esta ley y en un plazo no mayor al treinta y uno de diciembre de dos mil veintiuno, deberá:\na) Determinar el cambio o adscripción del personal de las dependencias que se separan, o transfieren funciones, transforman o modifican competencia, atendiendo a las funciones que previamente desarrollan, y\nb) Realizar las acciones administrativas necesarias para la transferencia del mobiliario, vehículos, equipos, tecnología, instrumentos, aparatos, maquinaria, archivos, información e instalaciones de las dependencias, subsecretarías y unidades administrativas que se separan o transfieren funciones, transforman o modifican competencia, a la dependencia que corresponda en términos de esta Ley, respetando las funciones que previamente se desarrollan en las mismas.\nOCTAVO. La integración y funcionamiento de la Secretaría de Seguridad Ciudadana del Estado de Baja California, prevista en los artículos 30, fracción IV y 34 de esta Ley, estará sujeta a la aprobación, publicación e inicio de vigencia de la reforma a los artículos cual se escinden las atribuciones de seguridad pública de la Fiscalía General del Estado.\nNOVENO. Hasta en tanto entre en vigor la presente Ley, las dependencias que se separan o transfieren funciones, transforman o modifican competencia, seguirán a cargo de las funciones, trámites, procedimientos y demás asuntos que les corresponda, en términos del artículo SEGUNDO transitorio de este Decreto, salvo la excepción prevista en el párrafo siguiente.\nEl Archivo General de Notarias denominado administrativamente como Dirección del\nArchivo General de Notarías actualmente adscrito a la Subsecretaría Jurídica del Estado seguirá dependiendo de la Secretaría General de Gobierno y ejerciendo las funciones que se le atribuyen en la Ley del Notariado para el Estado de Baja California; asimismo, la vigilancia del cumplimiento de dicha Ley se ejercerá por conducto de la Secretaría General de Gobierno y de la Dirección del Archivo General de Notarias en términos de la misma.\nDÉCIMO. Los asuntos administrativos que, con motivo de esta Ley deban pasar o ser transferidos de una dependencia a otra, y se encuentren pendientes de resolución o conclusión, continuarán atendiéndose por las dependencias que se separan o transfieren funciones, transforman o modifican competencia, en términos del artículo SEGUNDO transitorio de este Decreto; en caso de no concluirse pasarán a las unidades administrativas de las dependencias que señale la presente Ley.\nDÉCIMO PRIMERO. Cuando en otras disposiciones legales se dé una denominación la presente Ley, dichas atribuciones se entenderán conferidas para su ejercicio a la dependencia que se determine en la misma, en tanto no se realicen los ajustes legislativos, reglamentarios o normativos que correspondan.\nDÉCIMO SEGUNDO. El nombramiento que haga la Persona Titular del Poder artículo 49, fracción X de la Constitución del Estado y, en su caso, la ratificación que realice el Congreso del Estado de conformidad con el numeral 27, fracción XXXII de la misma\nConstitución, se entenderá efectuado al titular de la Secretaría de Bienestar una vez que entre en vigor la presente Ley.\nDÉCIMO TERCERO. La Persona Titular del Poder Ejecutivo para regular debidamente lo concerniente al funcionamiento de las dependencias de la Administración\nPública de conformidad a esta Ley, emitirá los nuevos reglamentos internos dentro del plazo de trescientos sesenta y cinco días posteriores a su entrada en vigor.\nDÉCIMO CUARTO. Las dependencias que se separan o transfieren funciones, transforman o modifican competencia, a través de sus unidades de apoyo para la administración de los recursos financieros, materiales y humanos, ejercerán provisionalmente las atribuciones y funciones que en ese ámbito se confieren a las dependencias que se prevén en la presente Ley, hasta en tanto se les aprueben los recursos necesarios en el presupuesto de egresos correspondiente.\nDÉCIMO QUINTO. Las atribuciones en materia de política de tecnologías de la información y telecomunicaciones para las dependencias y entidades paraestatales de la\nAdministración Pública, a que se refiere el artículo 21, fracción X de la presente Ley, que actualmente fija la Secretaría de Hacienda a través de la Subsecretaría de Tecnología de la\nInformación y Comunicaciones, las seguirá ejerciendo hasta en tanto no se emita la norma respectiva y se transfieran a la Coordinación de Gabinete por sí o a través del órgano que se determine; supuesto en el cual dichas atribuciones quedarán circunscritas al ámbito de competencia que le atribuye esta Ley a la Secretaría de Hacienda, con independencia de la vinculación que deberá tener con la Coordinación de Gabinete o el órgano que se determine para el ejercicio de las atribuciones que corresponden a estos últimos.\nDÉCIMO SEXTO. El inicio de funcionamiento del órgano desconcentrado a que se refiere el artículo 21, párrafo segundo de esta Ley, se determinará mediante el instrumento dispuesto en el artículo DÉCIMO QUINTO transitorio de este Decreto. jurídica y especialización, en su caso.\nDÉCIMO SÉPTIMO. La Consejería Jurídica y la Secretaría del Trabajo y Previsión\nSistema de Justicia Laboral, prevista en el artículo TERCERO Transitorio del Decreto número 21, expedido por el Congreso del Estado por el cual se aprueban reformas a publicado en el Periódico Oficial número 88, Tomo CXXVIII de veintisiete de octubre de dos mil veintiuno.\nDADO en Sesión Ordinaria de la XXIV Legislatura en la Ciudad de Mexicali, B.C., a los dieciocho días del mes de noviembre del año dos mil veintiuno.\nDIP. JUAN MANUEL MOLINA GARCÍA\nPRESIDENTE\n(RÚBRICA)\nDIP. ARACELI GERALDO NÚÑEZ\nSECRETARIA\n(RÚBRICA)\nDE CONFORMIDAD CON LO DISPUESTO POR LA FRACCIÓN I DEL ARTÍCULO 49 DE\nCALIFORNIA, IMPRÍMASE Y PUBLÍQUESE.\nMEXICALI, BAJA CALIFORNIA A LOS TRES DÍAS DEL MES DE DICIEMBRE DEL AÑO\nDOS MIL VEINTIUNO.\nMARINA DEL PILAR ÁVILA OLMEDA\nGOBERNADORA CONSTITUCIONAL\nDEL ESTADO DE BAJA CALIFORNIA\nCATALINO ZAVALA MÁRQUEZ\nSECRETARIO GENERAL DE GOBIERNO\nDEL ESTADO DE BAJA CALIFORNIA\nARTÍCULO 21.- Fue reformado por Decreto No. 195 publicado en el Periódico Oficial\nXXIV Legislatura, siendo Gobernadora Constitucional la C. Marina del Pilar Ávila Olmeda\n2021-2027; fue reformado por Decreto No. 95 publicado en el Periódico Oficial No. 34, de siendo Gobernadora Constitucional la C. Marina del Pilar Ávila Olmeda 2021-2027;\nARTÍCULO 25.- Fue reformado por Decreto No. 48 publicado en el Periódico Oficial\nNo. 9, de fecha 31 de enero de 2025, Sección III, Tomo CXXXII, expedido por la H. XXV\nLegislatura, siendo Gobernadora Constitucional la C. Marina del Pilar Ávila Olmeda 20212027;\nARTÍCULO 28.- Fue reformado por Decreto No. 146 publicado en el Periódico Oficial\nNo. 56, Índice, de fecha 16 de septiembre de 2025, Tomo CXXXII, expedido por la H. XXV\nLegislatura, siendo Gobernadora Constitucional la C. Marina del Pilar Ávila Olmeda 20212027;\nARTÍCULO 30.- Fue reformado por Decreto No. 169 publicado en el Periódico Oficial\nNo. 70, de fecha 02 de diciembre de 2022, Sección III, Tomo CXXIX, expedido por la H.\nXXIV Legislatura, siendo Gobernadora Constitucional la C. Marina del Pilar Ávila Olmeda\n2021-2027; fue reformado por Decreto No. 119 publicado en el Periódico Oficial No. 43, Número Especial, de fecha 21 de julio de 2025, Tomo CXXXII, expedido por la H. XXV\nLegislatura, siendo Gobernadora Constitucional la C. Marina del Pilar Ávila Olmeda 20212027; fue reformado por Decreto No. 146 publicado en el Periódico Oficial No. 56, Índice, de fecha 16 de septiembre de 2025, Tomo CXXXII, expedido por la H. XXV Legislatura, siendo\nGobernadora Constitucional la C. Marina del Pilar Ávila Olmeda 2021-2027;\nARTÍCULO 31.- Fue reformado por Decreto No. 119 publicado en el Periódico Oficial\nNo. 43, Número Especial, de fecha 21 de julio de 2025, Tomo CXXXII, expedido por la H.\nXXV Legislatura, siendo Gobernadora Constitucional la C. Marina del Pilar Ávila Olmeda\n2021-2027 (de conformidad con lo establecido en el Artículo Transitorio Primero de este\nARTÍCULO 32.- Fue reformado por Decreto No. 211 publicado en el Periódico Oficial\nLegislatura, siendo Gobernadora Constitucional la C. Marina del Pilar Ávila Olmeda 20212027;\nARTÍCULO 33.- Fue reformado por Decreto No. 95 publicado en el Periódico Oficial\nLegislatura, siendo Gobernadora Constitucional la C. Marina del Pilar Ávila Olmeda 20212027;\nARTÍCULO 34.- Fue reformado por Decreto No. 48 publicado en el Periódico Oficial\nLegislatura, siendo Gobernadora Constitucional la C. Marina del Pilar Ávila Olmeda 20212027;\nARTÍCULO 37.- Fue reformado por Decreto No. 48 publicado en el Periódico Oficial\nNo. 9, de fecha 31 de enero de 2025, Sección III, Tomo CXXXII, expedido por la H. XXV\nLegislatura, siendo Gobernadora Constitucional la C. Marina del Pilar Ávila Olmeda 20212027; fue reformado por Decreto No. 119 publicado en el Periódico Oficial No. 43, Número\nEspecial, de fecha 21 de julio de 2025, Tomo CXXXII, expedido por la H. XXV Legislatura, siendo Gobernadora Constitucional la C. Marina del Pilar Ávila Olmeda 2021-2027 (de conformidad con lo establecido en el Artículo Transitorio Primero de este Decreto, las reformas a este artículo entrarán en vigor el 01 de octubre de 2025 y el 01 de enero de\n2026);\nARTÍCULO 39.- Fue reformado por Decreto No. 194 publicado en el Periódico Oficial\nNo. 76, de fecha 30 de diciembre de 2022, Sección III, Tomo CXXIX, expedido por la H.\nXXIV Legislatura, siendo Gobernadora Constitucional la C. Marina del Pilar Ávila Olmeda\n2021-2027;\nARTÍCULO 41.- Fue reformado por Decreto No. 195 publicado en el Periódico Oficial\nNo. 76, de fecha 30 de diciembre de 2022, Sección III, Tomo CXXIX, expedido por la H.\nXXIV Legislatura, siendo Gobernadora Constitucional la C. Marina del Pilar Ávila Olmeda\n2021-2027;\nARTÍCULO 44.- Fue reformado por Decreto No. 169 publicado en el Periódico Oficial\nNo. 70, de fecha 02 de diciembre de 2022, Sección III, Tomo CXXIX, expedido por la H.\nXXIV Legislatura, siendo Gobernadora Constitucional la C. Marina del Pilar Ávila Olmeda\n2021-2027;\nARTÍCULO 48.- Fue reformado por Decreto No. 146 publicado en el Periódico Oficial\nNo. 56, Índice, de fecha 16 de septiembre de 2025, Tomo CXXXII, expedido por la H. XXV\nLegislatura, siendo Gobernadora Constitucional la C. Marina del Pilar Ávila Olmeda 20212027;\nARTÍCULO 49.- Fue reformado por Decreto No. 435 publicado en el Periódico Oficial\nLegislatura, siendo Gobernadora Constitucional la C. Marina del Pilar Ávila Olmeda 20212027;\nARTÍCULO 49 BIS.- Fue adicionado por Decreto No. 119 publicado en el Periódico la H. XXV Legislatura, siendo Gobernadora Constitucional la C. Marina del Pilar Ávila\nOlmeda 2021-2027 (de conformidad con lo establecido en el Artículo Transitorio Primero de\nARTÍCULO 59.- Fue reformado por Decreto No. 146 publicado en el Periódico Oficial\nLegislatura, siendo Gobernadora Constitucional la C. Marina del Pilar Ávila Olmeda 20212027;\nARTÍCULO 64.- Fue reformado por Decreto No. 146 publicado en el Periódico Oficial\nLegislatura, siendo Gobernadora Constitucional la C. Marina del Pilar Ávila Olmeda 20212027;\nARTÍCULO ÚNICO TRANSITORIO DEL DECRETO No. 169, POR EL QUE SE\nREFORMAN LOS ARTÍCULOS 30 Y 44; PUBLICADO EN PERIÓDICO OFICIAL No. 70, DE\nXXIV LEGISLATURA, SIENDO GOBERNADORA CONSTITUCIONAL LA C. MARINA DEL\nPILAR ÁVILA OLMEDA 2021-2027.\nTRANSITORIOS\nPRIMERO. Las presentes reformas entraran en vigor al día siguiente de su publicación en el\nPeriódico Oficial del Estado.\nSEGUNDO. Las referencias que se hacen o se hagan y las atribuciones que se otorguen en otras leyes, reglamentos, decretos y demás disposiciones legales a la Secretaría del Campo y la Seguridad Alimentaria, se entenderán hechas a la Secretaría de Agricultura y Desarrollo\nRural, a partir de la entrada en vigor del presente Decreto.\nTERCERO. Durante el ejercicio fiscal del año en curso, la Secretaría de Agricultura y\nDesarrollo Rural funcionará con la misma estructura con la que ha venido funcionando la\nSecretaría del Campo y la Seguridad Alimentaria, hasta que se realicen las adecuaciones presupuestales correspondientes.\nCUARTO. No se afectarán los derechos adquiridos y demás prestaciones reconocidas a los trabajadores con anterioridad al presente Decreto.\nQUINTO. Las funciones, facultades, derechos y obligaciones a cargo de la Secretaría del\nCampo y la Seguridad Alimentaria en cualquier ordenamiento legal, así como en contratos, convenios o acuerdos celebrados con dependencias o entidades del Poder Ejecutivo del\nEstado, con dependencias y entidades de la Federación y de los Municipios, y con cualquier persona física o moral, se entienden asumidas por la Secretaría de Agricultura y Desarrollo\nRural.\nSEXTO. En virtud del cambio de denominación de la Secretaría del Campo y la Seguridad\nAlimentaria, los tramites, procedimientos y demás asuntos que tenga pendiente de concluir o resolver, estarán a cargo de la Secretaría de Agricultura y Desarrollo Rural.\nDADO en Sesión Ordinaria de la XXIV Legislatura en la Ciudad de Mexicali, B.C., a los diez días del mes de noviembre del año dos mil veintidós.\nDIP. ALEJANDRA MARÍA ANG HERNÁNDEZ\nPRESIDENTA\n(RÚBRICA)\nDIP. DUNNIA MONTSERRAT MURILLO LÓPEZ\nSECRETARIA\n(RÚBRICA)\nDE CONFORMIDAD CON LO DISPUESTO POR LA FRACCIÓN I DEL ARTÍCULO 49\nCALIFORNIA, IMPRÍMASE Y PUBLÍQUESE.\nMEXICALI, BAJA CALIFORNIA A LOS DIECISÉIS DÍAS DEL MES DE NOVIEMBRE\nDEL AÑO DOS MIL VEINTIDÓS.\nMARINA DEL PILAR ÁVILA OLMEDA\nGOBERNADORA CONSTITUCIONAL\nDEL ESTADO DE BAJA CALIFORNIA\n(RÚBRICA)\nCATALINO ZAVALA MÁRQUEZ\nSECRETARIO GENERAL DE GOBIERNO\nDEL ESTADO DE BAJA CALIFORNIA\n(RÚBRICA)\nARTÍCULO SEGUNDO TRANSITORIO DEL DECRETO No. 194, POR EL QUE SE\nREFORMA EL ARTÍCULO 39; PUBLICADO EN PERIÓDICO OFICIAL No. 76, DE FECHA\n30 DE DICIEMBRE DE 2022, SECCIÓN III, TOMO CXXIX, EXPEDIDO POR LA H. XXIV\nLEGISLATURA, SIENDO GOBERNADORA CONSTITUCIONAL LA C. MARINA DEL PILAR\nÁVILA OLMEDA 2021-2027.\nTRANSITORIOS\nPrimero. El presente Decreto de reforma entrará en vigor al día siguiente de su publicación en el Periódico Oficial del Estado.\nDADO en Sesión Ordinaria de la XXIV Legislatura en la Ciudad de Mexicali, B.C., a los veinte días del mes de diciembre del año dos mil veintidós.\nDIP. MARÍA DEL ROCÍO ADAME MUÑOZ\nPRESIDENTA\n(RÚBRICA)\nDIP. DUNNIA MONTSERRAT MURILLO LÓPEZ\nSECRETARIA\n(RÚBRICA)\nDE CONFORMIDAD CON LO DISPUESTO POR LA FRACCIÓN I DEL ARTÍCULO 49\nCALIFORNIA, IMPRÍMASE Y PUBLÍQUESE.\nMEXICALI, BAJA CALIFORNIA A LOS VEINTIÚN DÍAS DEL MES DE DICIEMBRE\nDEL AÑO DOS MIL VEINTIDÓS.\nMARINA DEL PILAR ÁVILA OLMEDA\nGOBERNADORA CONSTITUCIONAL\nDEL ESTADO DE BAJA CALIFORNIA\n(RÚBRICA)\nCATALINO ZAVALA MÁRQUEZ\nSECRETARIO GENERAL DE GOBIERNO\nDEL ESTADO DE BAJA CALIFORNIA\n(RÚBRICA)\nARTÍCULO SEGUNDO TRANSITORIO DEL DECRETO No. 195, POR EL QUE SE\nREFORMAN LOS ARTÍCULOS 21 Y 41; PUBLICADO EN PERIÓDICO OFICIAL No. 76, DE\nFECHA 30 DE DICIEMBRE DE 2022, SECCIÓN III, TOMO CXXIX, EXPEDIDO POR LA H.\nXXIV LEGISLATURA, SIENDO GOBERNADORA CONSTITUCIONAL LA C. MARINA DEL\nPILAR ÁVILA OLMEDA 2021-2027.\nTRANSITORIOS\nPrimero. La presente reforma entrará en vigor al día siguiente de su publicación en el\nPeriódico Oficial del Estado.\nSegundo. El Ejecutivo Estatal dentro de los noventa días hábiles siguientes, contados a partir de la entrada en vigor del presento Decreto, realizará las modificaciones reglamentarias correspondientes.\nDADO en Sesión Ordinaria de la XXIV Legislatura en la Ciudad de Mexicali, B.C., a los veinte días del mes de diciembre del año dos mil veintidós.\nDIP. MARÍA DEL ROCÍO ADAME MUÑOZ\nPRESIDENTA\n(RÚBRICA)\nDIP. DUNNIA MONTSERRAT MURILLO LÓPEZ\nSECRETARIA\n(RÚBRICA)\nDE CONFORMIDAD CON LO DISPUESTO POR LA FRACCIÓN I DEL ARTÍCULO 49\nCALIFORNIA, IMPRÍMASE Y PUBLÍQUESE.\nMEXICALI, BAJA CALIFORNIA A LOS VEINTIÚN DÍAS DEL MES DE DICIEMBRE\nDEL AÑO DOS MIL VEINTIDÓS.\nMARINA DEL PILAR ÁVILA OLMEDA\nGOBERNADORA CONSTITUCIONAL\nDEL ESTADO DE BAJA CALIFORNIA\n(RÚBRICA)\nCATALINO ZAVALA MÁRQUEZ\nSECRETARIO GENERAL DE GOBIERNO\nDEL ESTADO DE BAJA CALIFORNIA\n(RÚBRICA)\nARTÍCULO SEGUNDO TRANSITORIO DEL DECRETO No. 211, POR EL QUE SE\nREFORMA EL ARTÍCULO 32; PUBLICADO EN PERIÓDICO OFICIAL No. 11, DE FECHA\n03 DE MARZO DE 2023, ÍNDICE, TOMO CXXX, EXPEDIDO POR LA H. XXIV\nLEGISLATURA, SIENDO GOBERNADORA CONSTITUCIONAL LA C. MARINA DEL PILAR\nÁVILA OLMEDA 2021-2027.\nARTÍCULOS TRANSITORIOS\nÚNICO.- La presente reforma entrará en vigor al día siguiente de su publicación en el\nPeriódico Oficial del Estado de Baja California.\nDADO en Sesión Ordinaria de la XXIV Legislatura en la Ciudad de Mexicali, B.C., a los dieciséis días del mes de febrero del año dos mil veintitrés.\nDIP. MARÍA DEL ROCÍO ADAME MUÑOZ\nPRESIDENTA\n(RÚBRICA)\nDIP. DUNNIA MONTSERRAT MURILLO LÓPEZ\nSECRETARIA\n(RÚBRICA)\nDE CONFORMIDAD CON LO DISPUESTO POR LA FRACCIÓN I DEL ARTÍCULO 49\nCALIFORNIA, IMPRÍMASE Y PUBLÍQUESE.\nMEXICALI, BAJA CALIFORNIA A LOS DIECISIETE DÍAS DEL MES DE FEBRERO\nDEL AÑO DOS MIL VEINTITRÉS.\nMARINA DEL PILAR ÁVILA OLMEDA\nGOBERNADORA CONSTITUCIONAL\nDEL ESTADO DE BAJA CALIFORNIA\n(RÚBRICA)\nCATALINO ZAVALA MÁRQUEZ\nSECRETARIO GENERAL DE GOBIERNO\nDEL ESTADO DE BAJA CALIFORNIA\n(RÚBRICA)\nARTÍCULO PRIMERO TRANSITORIO DEL DECRETO No. 435, POR EL QUE SE\nREFORMA EL ARTÍCULO 49; PUBLICADO EN PERIÓDICO OFICIAL No. 28, ÍNDICE, DE\nFECHA 31 DE MAYO DE 2024, TOMO CXXXI, EXPEDIDO POR LA H. XXIV\nLEGISLATURA, SIENDO GOBERNADORA CONSTITUCIONAL LA C. MARINA DEL PILAR\nÁVILA OLMEDA 2021-2027.\nARTÍCULO TRANSITORIO\nÚNICO.- La presente reforma entrará en vigor el día en que inicie su vigencia el Decreto de creación del organismo que determine el Ejecutivo del Estado de Baja California, encargado de las funciones concernientes a Cultura.\nDADO en Sesión Extraordinaria de la XXIV Legislatura en la Ciudad de Mexicali, B.C., a los veintinueve días del mes de mayo del año dos mil veinticuatro.\nDIP. RAMÓN VÁZQUEZ VALADEZ\nPRESIDENTE\n(RÚBRICA)\nDIP. MANUEL GUERRERO LUNA\nSECRETARIO\n(RÚBRICA)\nDE CONFORMIDAD CON LO DISPUESTO POR LA FRACCIÓN I DEL ARTÍCULO 49\nCALIFORNIA, IMPRÍMASE Y PUBLÍQUESE.\nMEXICALI, BAJA CALIFORNIA A LOS VEINTINUEVE DÍAS DEL MES DE MAYO\nDEL AÑO DOS MIL VEINTICUATRO.\nMARINA DEL PILAR ÁVILA OLMEDA\nGOBERNADORA CONSTITUCIONAL\nDEL ESTADO DE BAJA CALIFORNIA\n(RÚBRICA)\nALFREDO ÁLVAREZ CÁRDENAS\nSECRETARIO GENERAL DE GOBIERNO\nDEL ESTADO DE BAJA CALIFORNIA\n(RÚBRICA)\nARTÍCULO PRIMERO TRANSITORIO DEL DECRETO No. 48, POR EL QUE SE\nREFORMAN LOS ARTÍCULOS 25, 34 y 37; PUBLICADO EN PERIÓDICO OFICIAL No. 9,\nXXV LEGISLATURA, SIENDO GOBERNADORA CONSTITUCIONAL LA C. MARINA DEL\nPILAR ÁVILA OLMEDA 2021-2027.\nARTÍCULOS TRANSITORIOS\nPrimero.- La presente reforma entrará en vigor al día siguiente de su publicación en el\nPeriódico Oficial del Estado de Baja California.\nSegundo.- Los derechos laborales de las personas servidoras públicas y demás personal del Centro de Control, Comando, Comunicación, Cómputo, Calidad y Contacto Ciudadano del Estado de Baja California serán respetados en su totalidad.\nTercero.- Los recursos humanos, materiales, presupuestales y demás que estén asignados para la operación del Centro de Control, Comando, Comunicación, Cómputo, Calidad y\nContacto Ciudadano del Estado y el Servicio de Asistencia Telefónica, pasarán a cargo de la\nFiscalía General del Estado de Baja California y se continuarán realizando las funciones sustantivas correspondientes.\nCuarto.- Dentro de un plazo de 90 días naturales contados a partir de la entrada en vigor de la presente reforma, se deberá adecuar el Reglamento Interno de la Secretaría de Seguridad\nCiudadana..\nDADO en Sesión Ordinaria de la XXV Legislatura en la Ciudad de Mexicali, B.C., a los treinta días del mes de enero del año dos mil veinticinco.\nDIP. EVELYN SÁNCHEZ SÁNCHEZ\nPRESIDENTA\n(RÚBRICA)\nDIP. MICHELLE ALEJANDRA TEJEDA MEDINA\nSECRETARIA\n(RÚBRICA)\nDE CONFORMIDAD CON LO DISPUESTO POR LA FRACCIÓN I DEL ARTÍCULO 49\nCALIFORNIA, IMPRÍMASE Y PUBLÍQUESE.\nMEXICALI, BAJA CALIFORNIA A LOS 31 DÍAS DEL MES DE ENERO DEL AÑO\nDOS MIL VEINTICINCO.\nMARINA DEL PILAR ÁVILA OLMEDA\nGOBERNADORA DEL ESTADO DE\nBAJA CALIFORNIA\n(RÚBRICA)\nALFREDO ÁLVAREZ CÁRDENAS\nSECRETARIO GENERAL DE GOBIERNO\nDEL ESTADO DE BAJA CALIFORNIA\n(RÚBRICA)\nARTÍCULO PRIMERO TRANSITORIO DEL DECRETO No. 95, POR EL QUE SE\nAPRUEBA LA REFORMA AL ARTÍCULO 21 Y 33; PUBLICADO EN EL PERIÓDICO\nOFICIAL No. 34, SECCIÓN II, DE FECHA 30 DE MAYO DE 2025, TOMO CXXXII;\nEXPEDIDO POR LA H. XXV LEGISLATURA, SIENDO GOBERNADORA\nCONSTITUCIONAL LA C. MARINA DEL PILAR ÁVILA OLMEDA 2021-2027.\nTRANSITORIOS\nPrimero. Las presentes reformas entrarán en vigor al día siguiente de su publicación en el\nPeriódico Oficial del Estado.\nSegundo. La Persona Titular del Poder Ejecutivo deberá realizar las modificaciones reglamentarias que resulten necesarias.\nHasta en tanto se lleven a cabo las adecuaciones reglamentarias correspondientes a que se refiere este artículo, la Dirección General de la Agencia Digital del Estado funcionará conforme la estructura orgánica y ejercerá las atribuciones que le confieren las disposiciones reglamentarias vigentes en lo que no se contraponga a las presentes reformas.\nTercero. Los recursos presupuestales y financieros asignados en el Presupuesto de\nEgresos del Estado de Baja California para el ejercicio fiscal 2025, para la atención del programa de \"Gobierno Digital y Abierto al Servicio de la Población\" se ejercerán por la\nAgencia Digital del Estado.\nCuarto. La Oficialía Mayor de Gobierno en un plazo no mayor a sesenta días, deberá:\na) Determinar el cambio o adscripción del personal de las dependencias, órganos, áreas o unidades administrativas que se separan, o transfieren funciones, transforman o modifican competencia, atendiendo a las funciones que previamente desarrollaban; y,\nb) Realizar las acciones administrativas necesarias para la transferencia del mobiliario, vehículos, equipos, tecnología, instrumentos, aparatos, maquinaria, archivos, información e instalaciones de las dependencias, órganos, áreas o unidades administrativas, a la dependencia que corresponda en términos de esta Ley, respetando las funciones que previamente se desarrollaban en las mismas.\nQuinto. En la transferencia de personal que se realice con motivo de las presentes reformas, cualquiera que sea la naturaleza y forma en que presten sus servicios, se respetarán en todo momento sus derechos laborales. El personal de base cuya relación se encuentre tutelada por lo dispuesto en la Ley del Servicio Civil de los Trabajadores al\nServicio de los Poderes del Estado y Municipios de Baja California quedará a disposición de la Oficialía Mayor de Gobierno y sus derechos adquiridos y demás prestaciones no se afectarán por el presente Decreto.\nSexto. Los contratos cuya naturaleza no sea laboral o burocrática, convenios y demás instrumentos que a la fecha de publicación del Decreto se encuentren vigentes, continuarán surtiendo sus efectos hasta en tanto no se sustituyan los derechos sobre los bienes o la materia de los mismos, o se den por terminados por cualquier medio.\nSéptimo. Los asuntos, actos o tramites que se encuentren en curso o estén pendientes de resolución o conclusión a la fecha de entrada en vigor de las presentes reformas, y que con motivo de estas deban ser transferidos de una dependencia o entidad a otra dependencia, pasarán a las dependencias que señale la presente Ley de conformidad con el inicio de vigencia de las presentes reformas y de lo dispuesto en el artículo Octavo Transitorio de esta reforma.\nOctavo. Las atribuciones en materia de política de tecnologías de la información y telecomunicaciones para las dependencias y entidades paraestatales de la Administración\nPública, a que se refiere el artículo 33, fracción XXVIII de la presente Ley, que actualmente están a cargo de la Secretaría de Hacienda a través de la Subsecretaria de Tecnología de la\nInformación y Comunicaciones, las seguirá ejerciendo hasta en tanto no se emita la norma respectiva y se transfieran a la Oficialía Mayor de Gobierno por sí o a través del órgano que se determine; supuesto en el cual dichas atribuciones quedarán circunscritas al ámbito de competencia que le atribuye esta Ley a la Secretaría de Hacienda, con independencia de la vinculación que deberá tener con la Oficialía Mayor de Gobierno o la Dirección General de la\nAgencia Digital del Estado para el ejercicio de sus atribuciones.\nDADO en Sesión Ordinaria de la XXV Legislatura en la Ciudad de Mexicali, B.C., a los veintidós días del mes de mayo del año dos mil veinticinco.\nDIP. MICHELLE ALEJANDRA TEJEDA MEDINA\nPRESIDENTA\n(RÚBRICA)\nDIP. NORMA ANGELICA PEÑALOZA ESCOBEDO\nSECRETARIA\n(RÚBRICA)\nDE CONFORMIDAD CON LO DISPUESTO POR LA FRACCIÓN I DEL ARTÍCULO 49\nCALIFORNIA, IMPRÍMASE Y PUBLÍQUESE.\nMEXICALI, BAJA CALIFORNIA, A LOS 26 DÍAS DEL MES DE MAYO DEL AÑO DOS\nMIL VEINTICINCO.\nMARINA DEL PILAR ÁVILA OLMEDA\nGOBERNADORA DEL ESTADO\nDE BAJA CALIFORNIA\n(RÚBRICA)\nALFREDO ÁLVAREZ CÁRDENAS\nSECRETARIO GENERAL DE GOBIERNO\nDEL ESTADO DE BAJA CALIFORNIA\n(RÚBRICA)\nARTÍCULO PRIMERO TRANSITORIO DEL DECRETO No. 119, POR EL QUE SE\nAPRUEBA LA REFORMA A LOS ARTÍCULOS 30, 31 Y 37, Y SE ADICIONA EL ARTÍCULO\n49 BIS; PUBLICADO EN EL PERIÓDICO OFICIAL No. 43, NÚMERO ESPECIAL, DE\nFECHA 21 DE JULIO DE 2025, TOMO CXXXII; EXPEDIDO POR LA H. XXV\nLEGISLATURA, SIENDO GOBERNADORA CONSTITUCIONAL LA C. MARINA DEL PILAR\nÁVILA OLMEDA 2021-2027.\nARTÍCULOS TRANSITORIOS\nPRIMERO.- Las presentes reformas entrarán en vigor al día siguiente de su publicación en el Periódico Oficial del Estado de Baja California, con salvedad de lo dispuesto en las siguientes fracciones:\nI.- Las reformas a los artículos 37, fracciones VIII, XIV y XIX y 49 BIS fracciones XIV, XXIII y\nII.- Las reformas a los artículos 31 y 37, fracciones I, II, III, IV, V, VI, VII, IX, X, XI, XII, XIII,\nXV, XVI, XVII, XX y XXII y 49 BIS, I, II, III, IV, V, VI, VII, VIII, IX, X, XI, XII, XIII, XV, XVI, XVII,\nXVIII, XIX, XX, XXI, XXII, XXIV, XXV, XXVI, XXVII, XXIX, XXX, XXXI, XXXII, XXXIII, XXXIV, XXXV, XXXVI, XXXVII, XXXVIII, XXXIX, XL, XLI, XLII y XLIII entrarán en vigor el 01 de enero de 2026. paridad de género, realizará el nombramiento de la persona que será Titular de la Secretaría de las Mujeres, para que en coordinación con las dependencias relacionadas realice o gestione en el ámbito de las respectivas competencias, los procesos y acciones a que se refiere este apartado de artículos transitorios.\nEn ese tenor, la Persona Titular de la Secretaría de las Mujeres en coordinación con las diversas unidades administrativas de la Secretaría de Hacienda, realizará las previsiones necesarias para establecer los ramos, programas y partidas presupuestales que correspondan, dentro del Presupuesto de Egresos del Estado de Baja California para el ejercicio fiscal de 2025, con el fin de que la Secretaría de las Mujeres inicie funciones el 01 de octubre de 2025.\nTERCERO.- La persona Titular del Poder Ejecutivo, por conducto de la Secretaría de las\nMujeres señalará las bases para llevar a cabo la liquidación derivada de la extinción del\nInstituto de la Mujer para el Estado de Baja California, las cuales deberán considerar la eficacia, eficiencia y transparencia en todo momento del proceso de liquidación, así como la adecuada protección del interés público, por lo que podrá resolver cualquier situación inherente a dicho proceso.\nCUARTO.- La Persona Titular del Ejecutivo, por conducto de la Oficialía Mayor de Gobierno deberá:\na) Determinar el cambio o adscripción del personal de las dependencias que se separan, o transfieren funciones, transforman o modifican competencia, atendiendo a las funciones que previamente desarrollan; y,\nb) Realizar las acciones administrativas necesarias para la transferencia del mobiliario, vehículos, equipos, tecnología, instrumentos, aparatos, maquinaria, archivos, información e instalaciones de las dependencias, subsecretarías y unidades administrativas que se separan o transfieren funciones, transforman o modifican competencia, a la dependencia que corresponda en términos de esta Ley, respetando las funciones que previamente se desarrollan en las mismas.\nQUINTO.- En la transferencia de personal que se realice con motivo de las presentes reformas, cualquiera que sea la naturaleza y forma en que presten sus servicios, se respetarán en todo momento sus derechos laborales. Los derechos adquiridos y demás de Baja California no se afectarán por el presente decreto.\nSEXTO.- Los contratos cuya naturaleza no sea laboral o burocrática, convenios, encuentren vigentes, continuarán surtiendo sus efectos y obligarán en sus términos a la dependencia que señale la presente Ley, de conformidad con la entrada en vigor de las presentes reformas, hasta en tanto no se sustituyan los derechos sobre los bienes o la materia de los mismos, o se den por terminados por cualquier medio.\nSÉPTIMO.- Los asuntos, actos, trámites, proyectos, programas, registros, acciones e resolución o conclusión a la fecha de entrada en vigor de las presentes reformas, y deban ser transferidos con motivo de la modificación de la competencia de la Secretaría General de\nGobierno y de la Secretaría de Inclusión Social e Igualdad de Género, así como de la extinción del Instituto de la Mujer para el Estado de Baja California, pasarán a la Secretaría de las Mujeres de conformidad con el presente decreto.\nOCTAVO.- La Persona Titular del Poder Ejecutivo deberá realizar las modificaciones a la reglamentación que resulten necesarias.\nHasta en tanto se lleven a cabo las adecuaciones reglamentarias correspondientes a que se refiere este artículo, la Secretaría de las Mujeres funcionará conforme a la estructura orgánica y atribuciones que le confieren las disposiciones reglamentarias vigentes al Instituto de la Mujer para el Estado de Baja California, en lo que no se contraponga a las presentes reformas.\nNOVENO.- Toda referencia a la Secretaría de Inclusión Social e Igualdad de Género, se entenderá realizada a la Secretaría de Inclusión Social.\nDADO en Sesión Ordinaria de la XXV Legislatura en la Ciudad de Mexicali, B.C., a los diez días del mes de julio del año dos mil veinticinco.\nDIP. MICHELLE ALEJANDRA TEJEDA MEDINA\nPRESIDENTA\n(RÚBRICA)\nDIP. MARÍA TERESA MÉNDEZ VÉLEZ\nPROSECRETARIA\n(RÚBRICA)\nDE CONFORMIDAD CON LO DISPUESTO POR LA FRACCIÓN I DEL ARTÍCULO 49\nCALIFORNIA, IMPRÍMASE Y PUBLÍQUESE.\nMEXICALI, BAJA CALIFORNIA, A LOS 10 DÍAS DEL MES DE JULIO DEL AÑO DOS\nMIL VEINTICINCO.\nMARINA DEL PILAR ÁVILA OLMEDA\nGOBERNADORA DEL ESTADO\nDE BAJA CALIFORNIA\n(RÚBRICA)\nALFREDO ÁLVAREZ CÁRDENAS\nSECRETARIO GENERAL DE GOBIERNO\nDEL ESTADO DE BAJA CALIFORNIA\n(RÚBRICA)\nARTÍCULO PRIMERO TRANSITORIO DEL DECRETO No. 146, POR EL QUE SE\nAPRUEBA LA REFORMA A LOS ARTÍCULOS 28, 30, 48, 59 Y 64; PUBLICADO EN EL\nPERIÓDICO OFICIAL No. 56, NÚMERO ESPECIAL, DE FECHA 16 DE SEPTIEMBRE DE\n2025, TOMO CXXXII; EXPEDIDO POR LA H. XXV LEGISLATURA, SIENDO\nGOBERNADORA CONSTITUCIONAL LA C. MARINA DEL PILAR ÁVILA OLMEDA 2021-\n2027.\nTRANSITORIOS\nPRIMERO.- El presente Decreto entrará en vigor a los quince días de su publicación en el\nPeriódico Oficial del Estado de Baja California.\nSEGUNDO.- La persona titular del Poder Ejecutivo del Estado deberá realizar las adecuaciones al Reglamento Interno correspondiente dentro de los noventa días naturales siguientes a la entrada en vigor del presente Decreto.\nTERCERO.- Hasta en tanto no se lleven a cabo las adecuaciones normativas o reglamentarias que correspondan, toda referencia a la Secretaría de la Honestidad y la\nFunción Pública se entenderá realizada a la Secretaría Anticorrupción y Buen Gobierno.\nCUARTO.- Los contratos cuya naturaleza no sea laboral o burocrática, convenios y demás instrumentos celebrados por la Secretaría de la Honestidad y la Función Pública que a la fecha de publicación del Decreto se encuentren vigentes, continuarán surtiendo sus efectos y obligaran en sus términos a la Secretaría Anticorrupción y Buen Gobierno, hasta en tanto no se sustituyan los derechos sobre los bienes o la materia de los mismos, o se den por terminados por cualquier medio.\nDADO en Sesión Ordinaria de la XXV Legislatura en la Ciudad de Mexicali, B.C., a los once días del mes de septiembre del año dos mil veinticinco.\nDIP. JAIME EDUARDO CANTÓN ROCHA\nPRESIDENTE\n(RÚBRICA)\nDIP. MICHELLE ALEJANDRA TEJEDA MEDINA\nSECRETARIA\n(RÚBRICA)\nDE CONFORMIDAD CON LO DISPUESTO POR LA FRACCIÓN I DEL ARTÍCULO 49\nCALIFORNIA, IMPRÍMASE Y PUBLÍQUESE.\nMEXICALI, BAJA CALIFORNIA, A LOS 12 DÍAS DEL MES DE SEPTIEMBRE DEL\nAÑO DOS MIL VEINTICINCO.\nMARINA DEL PILAR ÁVILA OLMEDA\nGOBERNADORA DEL ESTADO\nDE BAJA CALIFORNIA\n(RÚBRICA)\nALFREDO ÁLVAREZ CÁRDENAS\nSECRETARIO GENERAL DE GOBIERNO\nDEL ESTADO DE BAJA CALIFORNIA\n(RÚBRICA)",
  "ordenamiento": "REGLAMENTO",
  "jurisdiccion": "BAJA CALIFORNIA",
  "fuente_oficial": "Periódico Oficial",
  "FECHA PER OFIC": "2025/09/16",
  "ESTATUS": "VIGENTE",
  "TOMO": "TOMO_I",
  "URL": "https://www.congresobc.gob.mx/Documentos/ProcesoParlamentario/Leyes/TOMO_I/20250916_LEYORGPE.PDF",
  "es_escaneado": false,
  "tiene_tablas": false,
  "materia": [
    "administrativo",
    "legislativo",
    "gobernanza"
  ]
}