{
  "titulo": "Ley DE TRANSPARENCIA, ACCESO A LA INFORMACIÓN PÚBLICA y APERTURA INSTITUCIONAL PARA EL ESTADO DE BAJ",
  "Contenido": ".\nActualización Legislativa.\nLEY DE TRANSPARENCIA, ACCESO A LA INFORMACIÓN PÚBLICA Y\nAPERTURA INSTITUCIONAL\nPARA EL ESTADO DE BAJA CALIFORNIA\nPublicada en el Periódico Oficial No. 56, de fecha 16 de septiembre de\n2025, Número Especial, Tomo CXXXII\nTÍTULO PRIMERO\nDISPOSICIONES GENERALES\nCapítulo I\nDisposiciones Preliminares\nARTÍCULO 1.- La presente Ley es de orden público y tiene por objeto desarrollar los principios y bases a los que deberán sujetarse las dependencias y entidades de la\nAdministración Pública Estatal y Municipal, el Poder Legislativo, el Poder Judicial, así como los organismos constitucionalmente autónomos del Estado, en el ámbito de sus respectivas competencias, conforme a la Ley General de Transparencia y Acceso a la Información de Baja California.\nARTÍCULO 2.- La presente Ley tiene por objeto:\nI. Desarrollar procedimientos sencillos y expeditos para el ejercicio del derecho de acceso a la información pública, que permitan garantizar condiciones homogéneas y accesibles para las personas solicitantes;\nII. Transparentar la gestión pública mediante la difusión de la información completa y actualizada que generan, administran o posean los sujetos obligados;\nIII. Establecer las bases y la información de interés público que se debe difundir proactivamente por los sujetos obligados;\nIV. Garantizar una adecuada y oportuna rendición de cuentas de los sujetos obligados a la ciudadanía, a través de la generación y publicación de información sobre sus indicadores de gestión y el ejercicio de los recursos públicos, de forma completa, veraz, oportuna y comprensible;\nV. Promover, fomentar y difundir la cultura de la transparencia en el ejercicio de la función pública, el acceso a la información pública, la participación ciudadana y la rendición de cuentas en la ciudadanía y las personas servidoras públicas;\nVI. Regular los medios de impugnación por parte de las Autoridades Garantes;\nVII. Regular la organización del Subsistema de Transparencia del Estado;\n.\nActualización Legislativa.\nVIII. Establecer los mecanismos necesarios para garantizar el cumplimiento de las disposiciones de esta ley, a través de la aplicación efectiva de medidas de apremio y sanciones que correspondan; y,\nIX. Regular las demás instituciones que se contienen en esta Ley.\nARTÍCULO 3.- Para los efectos de la presente Ley se entenderá por:\nI. Ajustes razonables: Modificaciones o adaptaciones necesarias y adecuadas que no impongan una carga desproporcionada o indebida, cuando se requieran en un caso particular, para garantizar a las personas con discapacidad el goce o ejercicio, en igualdad de condiciones, de los derechos humanos;\nII. Áreas: Instancias que disponen o pueden disponer de la información pública. En el sector público, serán aquellas que están previstas en el reglamento interior, estatuto orgánico respectivo o sus equivalentes;\nIII. Autoridad Garante Federal: Transparencia para el Pueblo, órgano administrativo desconcentrado de la Secretaría Anticorrupción y Buen Gobierno del Ejecutivo Federal;\nIV. Autoridades Garantes: Transparencia para el Pueblo, el órgano de control y disciplina del Poder Judicial del Estado, la Contraloría Interna del Poder Legislativo del\nEstado, los órganos internos de control o equivalentes de los órganos constitucionales autónomos del Estado;\nV. Comité de Transparencia: Instancia a la que hace referencia el artículo 32 de la presente Ley;\nVI. Consejo Nacional: Consejo del Sistema Nacional de Acceso a la Información\nPública y al que hace referencia el artículo 26 de la Ley General;\nVII. Datos Personales: Cualquier información concerniente a una persona física identificada o identificable;\nVIII. Datos Abiertos: Los datos digitales de carácter público que son accesibles en línea, que pueden ser usados, reutilizados y redistribuidos por cualquier persona interesada, los cuales tienen las siguientes características:\na) Accesibles: Disponibles para la mayor cantidad de personas usuarias posibles, para cualquier propósito;\nb) Integrales: Contienen el tema que describen a detalle y con los metadatos necesarios;\nc) Gratuitos: No requieren contraprestación alguna para su acceso;\n.\nActualización Legislativa.\nd) No discriminatorios: Están disponibles para cualquier persona, sin necesidad de registro;\ne) Oportunos: Son actualizados periódicamente, conforme se generen;\nf) Permanentes: Se conservan en el tiempo, para lo cual, las versiones históricas relevantes para uso público se mantendrán disponibles con identificadores adecuados al efecto;\ng) Primarios: Provienen de la fuente de origen con el máximo nivel de desagregación posible;\nh) Legibles por máquinas: Deberán estar estructurados, total o parcialmente, para ser procesados e interpretados por equipos electrónicos de manera automática;\ni) En formatos abiertos: Estarán disponibles con el conjunto de características técnicas y de presentación que corresponden a la estructura lógica usada para almacenar datos en un archivo digital, cuyas especificaciones técnicas están disponibles públicamente, que no suponen una dificultad de acceso y que su aplicación y reproducción no estén condicionadas a contraprestación alguna; y,\nj) De libre uso: Requieren la cita de la fuente de origen como único requisito para su uso.\nIX. Documento(s): Expedientes, reportes, estudios, actas, resoluciones, oficios, correspondencia, acuerdos, directivas, directrices, circulares, contratos, convenios, instructivos, notas, memorandos, estadísticas y, en general, cualquier registro que documente el ejercicio de las facultades, funciones y competencias de los sujetos obligados, sus personas servidoras públicas y demás integrantes, sin importar su fuente o fecha de elaboración, ni el medio en el que se encuentren, ya sea escrito, impreso, sonoro, visual, electrónico, informático u holográfico;\nX. Expediente: Unidad documental física o electrónica compuesta por documentos de archivo, ordenados y relacionados por un mismo asunto, actividad o trámite de los sujetos obligados;\nXI. Formatos Abiertos: Conjunto de características técnicas y de presentación de la integral y que facilitan su procesamiento digital, cuyas especificaciones están disponibles usuarias;\nXII. Formatos Accesibles: Cualquier manera o forma alternativa que dé acceso a las personas solicitantes de información, en forma tan viable y cómoda como la de las personas sin discapacidad ni otras dificultades para acceder a cualquier texto impreso y/o cualquier otro formato convencional en el que la información pueda encontrarse;\n.\nActualización Legislativa.\nXIII. Información de interés público: Es aquella que resulta relevante o útil para la sociedad y no simplemente de interés individual, cuya divulgación contribuye a que el público conozca las actividades que realizan los sujetos obligados en el ejercicio de sus funciones y como ejercen los recursos públicos, así como a exigir la rendición de cuentas y el combate a la corrupción;\nXIV. Ley: Ley de Transparencia, Acceso a la Información Pública y Apertura\nInstitucional para el Estado de Baja California;\nXV. Ley General: Ley General de Transparencia y Acceso a la Información Pública;\nXVI. Personas Servidoras Públicas: Las mencionadas en el primer párrafo del artículo 108 de la Constitución Política de los Estados Unidos Mexicanos y en el artículo 91\nXVII. Plataforma Nacional: Plataforma Nacional de Transparencia;\nXVIII. Secretaría: Secretaría Anticorrupción y Buen Gobierno del Estado de Baja\nCalifornia;\nXIX. Sistema Nacional: Sistema Nacional de Acceso a la Información Pública;\nXX. Subsistema Estatal: El Subsistema de Transparencia del Estado de Baja\nCalifornia dependiente del Sistema Nacional;\nXXI. Transparencia para el Pueblo: Órgano Administrativo Desconcentrado de la\nSecretaría Anticorrupción y Buen Gobierno del Estado de Baja California;\nXXII. Sujetos obligados: Cualquier autoridad, agencia, comisión, comité, corporación, ente, entidad, institución, órgano, organismo o equivalente de los poderes\nEjecutivo, Legislativo y Judicial en el ámbito estatal y municipal, órganos constitucionalmente autónomos, fideicomisos y fondos públicos, así como cualquier persona física o moral que reciba y ejerza recursos públicos o realice actos de autoridad en los referidos niveles de gobierno;\nXXIII. Unidad de Transparencia: Instancia a la que se hace referencia en el artículo\n34 de la presente Ley;\nXXIV. Versión Pública: Documento o expediente en el que se da acceso a información pública, previa eliminación u omisión de aquellas partes o secciones que se encuentran clasificadas conforme a la Ley.\nARTÍCULO 4.- El derecho humano de acceso a la información comprende solicitar, investigar, difundir, buscar y recibir información.\nToda información generada, obtenida, adquirida, transformada o en posesión de los sujetos obligados es pública y accesible a cualquier persona, en los términos y condiciones\n.\nActualización Legislativa.\nCalifornia, la Constitución Política de los Estados Unidos Mexicanos, los tratados internacionales de los que el Estado Mexicano sea parte, la Ley General, y la presente Ley.\nLa información podrá ser clasificada como reservada temporalmente por razones de interés público o seguridad nacional conforme a los términos establecidos por la Ley General y la presente Ley.\nARTÍCULO 5.- No podrá clasificarse como reservada aquella información relacionada con violaciones graves a los derechos humanos o con delitos de lesa humanidad, conforme al derecho internacional o a los tratados internacionales de los que el Estado Mexicano sea parte.\nNinguna persona podrá ser objeto de inquisición judicial o administrativa derivado del ejercicio del derecho de acceso a la información, ni se podrá restringir este derecho mediante vías o medios, directos o indirectos.\nARTÍCULO 6.- El Estado garantizará el efectivo acceso de toda persona a la información en posesión de cualquier autoridad, agencia, comisión, comité, corporación, ente, entidad, institución, órgano, organismo o equivalente de los poderes Ejecutivo, Legislativo y Judicial del Estado y municipios, órganos constitucionalmente autónomos, fideicomisos y fondos públicos, así como cualquier persona física o moral que reciba y ejerza recursos públicos o realice actos de autoridad del Estado o municipios.\nARTÍCULO 7.- El derecho de acceso a la información y la clasificación de la información se interpretarán conforme a los principios establecidos en la Constitución\nEstados Unidos Mexicanos, los tratados internacionales de los que el Estado mexicano sea parte, la Ley General y la presente Ley.\nEn la aplicación e interpretación de la presente Ley, deberá prevalecer el principio de máxima publicidad, conforme a lo dispuesto en la Constitución Política de los Estados\nUnidos Mexicanos, en los tratados internacionales de los que el Estado Mexicano sea parte, así como en las resoluciones y sentencias vinculantes que emitan los órganos nacionales e internacionales especializados. En todo momento, se deberá favorecer la protección más amplia de los derechos de las personas.\nPara el caso de la interpretación, se podrán tomar en cuenta los criterios, en dicha materia.\nCapítulo II\nDe los Principios Generales\nSección Primera\n.\nActualización Legislativa.\nARTÍCULO 8.- Las Autoridades Garantes deberán regir su funcionamiento de acuerdo a los siguientes principios:\nI. Certeza: Otorga seguridad y certidumbre a las personas particulares, ya que permite conocer si las acciones que realizan se ajustan a derecho y garantizan que los procedimientos sean verificables, fidedignos y confiables;\nII. Congruencia: implica que exista concordancia entre el requerimiento formulado por el particular y la respuesta proporcionada por el sujeto obligado;\nIII. Documentación: Consiste en que los sujetos obligados deberán otorgar acceso a los documentos que se encuentren en sus archivos o que estén obligados a documentar, de acuerdo con sus facultades, competencias o funciones, conforme a las características físicas de la información o del lugar donde se encuentre, sin que ello implique la elaboración de documentos para un fin determinado (ad hoc) para atender las solicitudes de información;\nIV. Eficacia: Tutela de manera efectiva el derecho de acceso a la información pública;\nV. Excepcionalidad: Implica que la información podrá ser clasificada como reservada o confidencial únicamente si se actualizan los supuestos que esta ley expresamente señala;\nVI. Exhaustividad: Significa que la respuesta se refiera expresamente a cada uno de los puntos solicitados, con las limitantes del principio de documentación;\nVII. Imparcialidad: Deben en sus actuaciones, ser ajenos o extraños a los intereses de las partes en controversia, sin inclinaciones hacia ninguna de las partes involucradas;\nVIII. Independencia: Deben actuar sin influencias que puedan afectar la imparcialidad o la eficacia del derecho de acceso a la información;\nIX. Legalidad: Ajustar su actuación a las disposiciones jurídicas aplicables, fundamentando y motivando sus resoluciones y actos;\nX. Máxima Publicidad: Promover que toda la información en posesión de los sujetos obligados documentada sea pública y accesible, salvo en los casos expresamente establecidos en esta Ley o en otras disposiciones jurídicas aplicables, en los que podrá ser nacional;\nXI. Objetividad: Ajustar su actuación a los supuestos de ley que deben ser aplicados al analizar el caso en concreto para resolver, sin considerar juicios personales;\nXII. Profesionalismo: Deben sujetar su actuación a conocimientos técnicos teóricos y metodológicos, que garanticen un desempeño eficiente y eficaz en el ejercicio de su actuar; y,.\nActualización Legislativa.\nXIII. Transparencia: Dar publicidad a los actos relacionados con sus atribuciones, así como dar acceso a la información que tengan obligación de documentar.\nSección Segunda\nDe los Principios en Materia de Transparencia y\nAcceso a la Información Pública.\nARTÍCULO 9.- Las Autoridades Garantes, así como los sujetos obligados, en el ejercicio, tramitación e interpretación de la presente Ley y demás disposiciones aplicables en la materia, deberán observar los principios establecidos en esta sección.\nARTÍCULO 10.- Las Autoridades Garantes otorgarán las medidas pertinentes para asegurar el acceso a la información a todas las personas, en igualdad de condiciones.\nEstá prohibida toda forma de discriminación que límite o impida el ejercicio del derecho de acceso a la información pública en posesión de los sujetos obligados.\nARTÍCULO 11.- Toda la información pública documentada, obtenida, adquirida, transformada o en posesión de los sujetos obligados es pública y debe ser accesible a cualquier persona. Para ello, se deberán habilitar los medios y acciones disponibles, conforme a los términos y condiciones establecidos en esta Ley y demás disposiciones jurídicas aplicables.\nARTÍCULO 12.- Los sujetos obligados en la generación, publicación y entrega de información, deberán:\nI. Garantizar que ésta sea accesible, confiable, verificable, veraz, oportuna, y atenderá las necesidades del derecho de acceso a la información de toda persona, sin embargo, estará sujeta a un régimen de excepciones claramente definido; y,\nII. Procurar que se utilice un lenguaje inclusivo, claro y comprensible para cualquier persona, y en la medida de lo posible, su accesibilidad y traducción a lenguas indígenas.\nARTÍCULO 13.- Las Autoridades Garantes, en el ámbito de sus atribuciones, deberán suplir cualquier deficiencia para garantizar el ejercicio del derecho de acceso a la información, sin que ello implique variar la solicitud, atendiendo al principio de congruencia.\nARTÍCULO 14.- El ejercicio del derecho de acceso a la información no podrá ser restringido ni estará condicionado a que la persona solicitante acredite interés alguno, ni a que justifique el uso que hará de la información solicitada.\nARTÍCULO 15.- El ejercicio del derecho de acceso a la información es gratuito y solo solicitada. En ningún caso los ajustes razonables que se realicen para garantizar el acceso a la información a personas solicitantes con discapacidad, serán con costo alguno.\n.\nActualización Legislativa.\nARTÍCULO 16.- Se presume que la información debe existir cuando se refiere a las facultades, competencias y funciones que los ordenamientos jurídicos aplicables otorgan a los sujetos obligados y se tenga la obligación jurídica de documentarla.\nEn los casos en que ciertas facultades, competencias o funciones no se hayan ejercido, el sujeto obligado deberá motivar la respuesta que lo justifique.\nARTÍCULO 17.- Ante la negativa de acceso a la información o la inexistencia de la misma, el sujeto obligado deberá indicar que la información solicitada se encuentra comprendida dentro de alguna de las excepciones previstas en esta Ley o, en su caso, que no corresponde a sus facultades, competencias o funciones, o bien, no existe la obligación jurídica de documentarla.\nARTÍCULO 18.- Todo procedimiento relacionado con el derecho de acceso, entrega y publicación a la información deberá:\nI. Sustanciarse de manera sencilla, clara y expedita, conforme a las disposiciones establecidas en esta Ley; y,\nII. Propiciar las condiciones necesarias para garantizar que esta sea accesible a\nCapítulo III\nDe los Sujetos Obligados\nARTÍCULO 19.- Son sujetos obligados a transparentar y permitir el acceso a su información y proteger los datos personales que obren en su poder:\nI. El Poder Ejecutivo del Estado;\nII. El Poder Judicial del Estado;\nIV. Los Ayuntamientos o Consejos Municipales y la Administración Pública Municipal;\nV. Los organismos descentralizados y desconcentrados de la Administración Pública\nEstatal y Municipal, así como las empresas de participación estatal o municipal;\nVI. Los organismos públicos autónomos del Estado;\nVII. Las universidades públicas, e instituciones de educación superior pública;\nVIII. Los fideicomisos y fondos públicos que cuenten con financiamiento público, parcial o total, o con participación de entidades de gobierno;\n.\nActualización Legislativa.\nIX. Las organizaciones de la sociedad civil que reciban y/o ejerzan recursos públicos en el ámbito estatal y municipal;\nX. Las instituciones de beneficencia que sean constituidas conforme a la ley en la materia; y,\nXI. Cualquier persona física o moral que reciba y ejerza recursos o bienes o servicios públicos, o realice actos de autoridad en los ámbitos estatal y municipal.\nARTÍCULO 20.- Los sujetos obligados deberán transparentar y garantizar el acceso a la información documentada en su poder, de conformidad con las disposiciones jurídicas aplicables.\nARTÍCULO 21.- Para el cumplimiento de los objetos de esta Ley, los sujetos obligados deberán cumplir con las siguientes obligaciones, según corresponda, de acuerdo con su naturaleza:\nI. Constituir el Comité de Transparencia y las Unidades de Transparencia, así como velar por su correcto funcionamiento conforme a su normativa interna;\nII. Designar a las personas titulares de las Unidades de Transparencia, quienes deberán depender directamente de la persona titular del sujeto obligado y, preferentemente, contar con experiencia en la materia;\nIII. Proporcionar capacitación continua y especializada al personal que forme parte de los Comités y la Unidades de Transparencia;\nIV. Constituir y mantener actualizados sus sistemas de archivo y gestión documental, conforme a la normatividad aplicable;\nV. Promover la generación, documentación y publicación de la información en formatos abiertos y accesibles;\nVI. Proteger y resguardar la información clasificada como reservada o confidencial, conforme a las disposiciones aplicables;\nVII. Reportar a las Autoridades Garantes competentes sobre las acciones de implementación de las disposiciones aplicables en la materia, en los términos que estos determinen;\nVIII. Atender los requerimientos, observaciones, recomendaciones y criterios en el Sistema Nacional;\nIX. Fomentar el uso de tecnologías de la información para garantizar la transparencia, el ejercicio del derecho de acceso a la información y la accesibilidad de éstos;\nX. Cumplir las resoluciones emitidas por las Autoridades Garantes;\n.\nActualización Legislativa.\nXI. Publicar y mantener actualizada la información relativa a las obligaciones de transparencia, integrando los archivos o ligas correspondientes en la Plataforma Nacional según los procedimientos que para ello se establezcan;\nXII. Difundir proactivamente la información de interés público;\nXIII. Dar atención a las recomendaciones de las Autoridades Garantes;\nXIV. Promover acuerdos con instituciones públicas especializadas que pudieran auxiliarles a entregar las respuestas a solicitudes de información en lengua indígena, braille, o cualquier otro ajuste razonable con el formato accesible correspondiente, en la forma más eficiente;\nXV. Promover la digitalización de la información en su posesión y la utilización de las tecnologías de información y comunicación, de conformidad con las políticas que al efecto establezca el Sistema Nacional;\nXVI. Responder las solicitudes en materia de acceso a la información a través de la\nPlataforma Nacional en los términos y plazos establecidos en la presente Ley, sin perjuicio del medio en que se hayan presentado o la modalidad de reproducción y entrada solicitada; y,\nXVII. Las demás que resulten de las disposiciones aplicables.\nARTÍCULO 22.- Los sujetos obligados serán responsables del cumplimiento de las obligaciones, procedimientos y responsabilidades establecidas en esta Ley y la Ley General, en los términos que estas dispongan.\nARTÍCULO 23.- Los fideicomisos y fondos públicos en el ámbito estatal y municipal que no cuenten con estructura orgánica y, por tanto, no sean considerados una entidad paraestatal, así como de los mandatos públicos y demás contratos análogos, deben cumplir con las obligaciones de esta Ley a través de la unidad administrativa responsable de coordinar su operación.\nTÍTULO SEGUNDO\nCapítulo I\nDel Subsistema de Transparencia del Estado\nARTÍCULO 24.- El Subsistema de Transparencia del Estado de Baja California es el conjunto orgánico y articulado de sus miembros, procedimientos e instrumentos y políticas\nEstatal.\nARTÍCULO 25.- El Subsistema Estatal tendrá las siguientes funciones:\n.\nActualización Legislativa.\nI. Dar a conocer al Consejo Nacional, a través de su Presidencia, las opiniones que tuvieren sobre el proyecto de política nacional en materia de transparencia y acceso a la información pública;\nII. Apoyar en la supervisión de la ejecución de la política nacional en materia de transparencia y acceso a la información pública;\nIII. Presentar al Consejo Nacional un informe anual sobre sus actividades;\nIV. Impulsar acciones de coordinación entre sus integrantes que promuevan el cumplimiento de obligaciones en materia de transparencia y acceso a la información pública;\nV. Opinar respecto de los demás asuntos que someta a su consideración el Consejo\nNacional; y,\nVI. Las demás que le confiera el Sistema Nacional.\nARTÍCULO 26.- El Comité del Subsistema Estatal se integrará con personas representantes de los órganos encargados de la contraloría u homólogos, como sigue:\nI. El Poder Ejecutivo, quien lo presidirá;\nII. El Poder Legislativo;\nIII. El Poder Judicial;\nIV. Un representante de cada municipio del Estado; y,\nV. Cada uno de los órganos constitucionales autónomos.\nLas personas integrantes del Comité del Subsistema Estatal, podrán ser suplidas en sus ausencias por la persona servidora pública que al efecto designen por escrito, quienes deberán tener el nivel jerárquico inmediato inferior al de ellas.\nQuienes integren el Comité del Subsistema Estatal contarán con voz y voto y ejercerán sus cargos a título honorifico, por lo que no recibirán retribución, emolumento, ni compensación por su participación. integrantes presentes. En caso de empate la persona que lo preside tendrá voto de calidad.\nARTÍCULO 27.- El Comité del Subsistema Estatal podrá invitar, por la naturaleza de los asuntos a tratar, a las personas, instituciones, representantes de los sujetos obligados y de la sociedad para el desahogo de las reuniones del mismo. En todo caso, los sujetos obligados tendrán la potestad de solicitar ser invitados a estas reuniones.\nCapítulo II\nDe las Autoridades Garantes\n.\nActualización Legislativa.\nARTÍCULO 28.- Las Autoridades Garantes serán responsables de garantizar, en el ámbito de su competencia, el ejercicio de los derechos de acceso a la información pública y la protección de datos personales, conforme a los principios y bases establecidos por la Ley\nGeneral de Transparencia y Acceso a la Información Pública, así como por lo previsto en esta Ley y demás disposiciones jurídicas aplicables.\nARTÍCULO 29.- Las Autoridades Garantes tendrán las atribuciones siguientes:\nI. Interpretar, en el ámbito de sus atribuciones, los ordenamientos que les resulten aplicables, derivados de esta Ley y de la Constitución Política de los Estados Unidos\nMexicanos;\nII. Conocer y resolver los recursos de revisión interpuestos por las personas particulares en contra de las resoluciones de los sujetos obligados en sus respectivos ámbitos de competencia, en términos de lo dispuesto en el Capítulo I del Título Séptimo de la presente Ley;\nIII. Imponer las medidas de apremio y sanciones, según corresponda, de conformidad con lo previsto en la presente Ley y demás disposiciones que deriven de la misma;\nIV. Promover y difundir el ejercicio de los derechos de acceso a la información, de conformidad con la política nacional en materia de transparencia y acceso a la información pública y las disposiciones jurídicas aplicables en la materia;\nV. Fomentar la cultura de la transparencia en el sistema educativo;\nVI. Brindar capacitación a las personas servidoras públicas y apoyo técnico a los sujetos obligados en materia de transparencia y acceso a la información;\nVII. Establecer políticas de transparencia con sentido social, atendiendo a las condiciones económicas, sociales y culturales;\nVIII. Suscribir convenios con los sujetos obligados que propicien la publicación de información en el marco de las políticas de transparencia con sentido social;\nIX. Suscribir convenios de colaboración con las personas particulares o con sectores social;\nX. Suscribir convenios de colaboración con otras Autoridades Garantes para el cumplimiento de sus atribuciones y promover mejores prácticas en la materia;\nXI. Promover la igualdad sustantiva;\nXII. Coordinarse con las autoridades competentes para que, en los procedimientos de acceso a la información y en los medios de impugnación, se contemple contar con la\n.\nActualización Legislativa. atendidos en la misma lengua y en su caso, se promuevan los ajustes razonables necesarios si se tratara de personas con discapacidad;\nXIII. Garantizar condiciones de accesibilidad para que los grupos de atención prioritaria puedan ejercer su derecho de acceso a la información pública en igualdad de circunstancias;\nXIV. Informar a la instancia competente sobre la probable responsabilidad de los sujetos obligados que incumplan las obligaciones previstas en la presente Ley y en las demás disposiciones aplicables;\nXV. Promover la participación y colaboración con organismos internacionales en el análisis y mejores prácticas en materia de acceso a la información pública;\nXVI. Fomentar los principios de transparencia, rendición de cuentas, participación ciudadana, accesibilidad e innovación tecnológica;\nXVII. Emitir recomendaciones a los sujetos obligados, con el propósito de diseñar, implementar y evaluar acciones de apertura gubernamental que permitan orientar las políticas internas en la materia;\nXVIII. Promover la digitalización de la Información pública en posesión de los sujetos obligados y la utilización de las tecnologías de información y comunicación, conforme a las políticas que establezca el Sistema Nacional; y,\nXIX. Las demás atribuciones que les confiera esta Ley y otras disposiciones aplicables.\nARTÍCULO 30.- Las Autoridades Garantes para el ejercicio y desempeño de las atribuciones que les otorga la presente Ley, tendrán la naturaleza Jurídica, adscripción y estructura administrativa que se establezca en sus respectivos Reglamentos Interiores o análogos o acuerdos de carácter general, en el ámbito de sus respectivas competencias.\nARTÍCULO 31.- La Autoridad Garante del Poder Ejecutivo del Estado se denominará\nTransparencia para el Pueblo, la cual será un órgano administrativo desconcentrado de la\nSecretaría Anticorrupción y Buen Gobierno del Estado de Baja California y tiene a su cargo el ejercicio de las atribuciones y el despacho de los asuntos que le otorgan la Ley General, esta Ley, otras leyes, reglamentos, decretos, acuerdos y demás disposiciones jurídicas aplicables. Asimismo, conocerá de los recursos de revisión y denuncias en materia de transparencia de los municipios del Estado.\nTransparencia para el Pueblo estará a cargo de una persona titular, quien será designada por la Gobernadora o Gobernador del Estado.\nCapítulo III\nDe los Comités de Transparencia\n.\nActualización Legislativa.\nARTÍCULO 32.- En cada sujeto obligado, la persona titular deberá integrar un Comité de Transparencia, de carácter colegiado y conformado por un número impar de integrantes.\nEl Comité de Transparencia adoptará sus resoluciones por mayoría de votos, en caso de empate, quien presida el Comité tendrá voto de calidad. A sus sesiones podrán asistir como personas invitadas, aquéllas que sus integrantes consideren necesarias, quienes tendrán voz, pero no voto.\nQuienes integren el Comité de Transparencia no podrán depender jerárquicamente entre sí, ni reunirse dos o más integrantes en una persona. Cuando se presente el caso, la persona titular del sujeto obligado tendrá que nombrar a la persona que supla al subordinado. Quienes integren los Comités de Transparencia contarán con suplentes cuya designación se realizará de conformidad con la normatividad interna de los respectivos sujetos obligados, y deberán corresponder a personas que ocupen cargos de la jerarquía inmediata inferior a la de las personas integrantes propietarias.\nLas personas integrantes del Comité de Transparencia tendrán acceso a la información para determinar su clasificación, conforme a las disposiciones jurídicas emitidas por los sujetos obligados para el resguardo o salvaguarda de la información.\nLas unidades administrativas de investigación y operaciones policiales de la Dirección de la Fuerza Estatal de Seguridad Ciudadana, las Direcciones de Investigación, de\nPrevención del Delito, de Prevención Social de las Violencias y de Inteligencia de la\nSecretaría de Seguridad Ciudadana, el Centro de Control, Comando, Comunicación, Cómputo, Calidad y de Contacto Ciudadano del Estado, así como la Agencia Estatal de\nInvestigación, no estarán sujetas a la autoridad de los Comités de Transparencia a que se refiere este artículo. Las funciones correspondientes serán responsabilidad exclusiva de la persona titular de la entidad o unidad administrativa.\nLa clasificación, desclasificación y acceso a la información que generan o custodian las instancias de inteligencia e investigación deberán apegarse a los términos previstos en la presente Ley y a los protocolos de seguridad y resguardos establecidos para ello.\nARTÍCULO 33.- Cada Comité de Transparencia tendrá las siguientes atribuciones:\nI. Instituir, coordinar y supervisar las acciones y procedimientos para asegurar la mayor eficacia en la gestión de las solicitudes en materia de acceso a la información, en términos de las disposiciones aplicables;\nII. Confirmar, modificar o revocar las determinaciones en materia de ampliación del plazo de respuesta, clasificación de la información y declaración de inexistencia o incompetencia, que sean adoptadas por las personas titulares de las áreas correspondientes de los sujetos obligados;\nIII. Ordenar, en su caso, a las áreas competentes que generen la información que derivado de sus facultades, competencias y funciones deban tener en posesión o que previa acreditación de la imposibilidad de su generación, exponga, de forma fundada y motivada,.\nActualización Legislativa. las razones por las cuales, en el caso particular, no ejercieron dichas facultades, competencias o funciones;\nIV. Establecer políticas para facilitar la obtención de información y el ejercicio del derecho de acceso a la información;\nV. Promover y establecer programas de capacitación en materia de transparencia, acceso a la información y accesibilidad para todas las personas servidoras públicas integrantes del sujeto obligado;\nVI. Recabar y enviar a las Autoridades Garantes los datos necesarios para la elaboración del informe anual, conforme a los lineamientos que dichas autoridades expidan;\nVII. Solicitar y autorizar la ampliación del plazo de reserva de la información, conforme a lo dispuesto en el artículo 88 de la presente Ley; y,\nVIII. Las demás que se desprendan de las disposiciones jurídicas aplicables.\nCapítulo IV\nDe las Unidades de Transparencia\nARTÍCULO 34.- Los sujetos obligados designarán a la persona responsable de la\nUnidad de Transparencia, quien tendrá las siguientes atribuciones:\nI. Recabar y difundir la información prevista en los Capítulos II, III y IV del Título\nCuarto de esta Ley, y propiciar que las áreas la actualicen periódicamente, conforme las disposiciones jurídicas aplicables;\nII. Recibir y dar trámite a las solicitudes de acceso a la información;\nIII. Auxiliar a las personas particulares en la elaboración de solicitudes de acceso a la información y, en su caso, orientarles sobre los sujetos obligados competentes conforme a las disposiciones jurídicas aplicables;\nIV. Realizar los trámites internos necesarios para la atención de las solicitudes de acceso a la información;\nV. Efectuar las notificaciones a las personas solicitantes, conforme las disposiciones jurídicas aplicables;\nVI. Proponer a Comité de Transparencia los procedimientos internos que aseguren la mayor eficiencia en la gestión de las solicitudes de acceso a la información, conforme a las disposiciones jurídicas aplicables;\nVII. Proponer personal habilitado que sea necesario para recibir y dar trámite a las solicitudes de acceso a la información;\n.\nActualización Legislativa.\nVIII. Llevar un registro de las solicitudes de acceso a la información, respuestas, resultados, costos de reproducción y envío;\nIX. Promover implementar políticas de transparencia con sentido social, procurando su accesibilidad;\nX. Fomentar la transparencia y accesibilidad al interior del sujeto obligado;\nXI. Hacer del conocimiento de la instancia competente la probable responsabilidad por el incumplimiento de las obligaciones previstas en la presente Ley y en las demás disposiciones jurídicas aplicables; y,\nXII. Las demás que se desprendan de las disposiciones jurídicas aplicables.\nCada sujeto obligado en el ámbito de sus facultades determinará dentro de su organización administrativa, la unidad que tendrá las funciones que esta Ley prevé para la\nUnidad de Transparencia.\nLos sujetos obligados promoverán acuerdos con instituciones públicas especializadas que pudieran auxiliarles a entregar las repuestas a solicitudes de información, en la lengua indígena, braille o cualquier formato accesible correspondiente, en forma más eficiente.\nARTÍCULO 35.- En caso de que alguna área de los sujetos obligados se negará a colaborar con la Unidad de Transparencia, esta informará a su superior jerárquico para que le ordene realizar sin demora las acciones conducentes.\nSi persiste la negativa de colaboración, la Unidad de Transparencia lo hará del conocimiento de la autoridad competente, quien podrá iniciar el procedimiento de responsabilidad respectivo.\nARTÍCULO 36.- Las oficinas que ocupen las Unidades de Transparencia se deben ubicar en lugares visibles al público en general y ser de fácil acceso.\nLas Unidades de Transparencia deben contar con las condiciones mínimas de operación que aseguren el cumplimiento de sus funciones.\nTransparencia, de conformidad con los lineamientos que para dicho efecto emita el Sistema\nNacional.\nTÍTULO TERCERO\nCapítulo I\n.\nActualización Legislativa.\nARTÍCULO 37.- Los sujetos obligados en coordinación con las Autoridades Garantes deberán capacitar y actualizar de forma permanente, a todas sus personas servidoras públicas en materia del derecho de acceso a la información, a través de los medios que se considere pertinentes.\nCon el objeto de crear una cultura de la transparencia y acceso a la información entre las personas habitantes del Estado de Baja California, las Autoridades Garantes podrán promover, en colaboración con instituciones educativas y culturales del sector público o privado, actividades, mesas de trabajo, exposiciones y concursos relativos a la transparencia y acceso a la información.\nARTÍCULO 38.- Las Autoridades Garantes, en el ámbito de sus respectivas competencias o a través de los mecanismos de coordinación que al efecto establezcan, podrán:\nI. Proponer, a las autoridades educativas competentes que incluyan contenidos sobre la importancia social del derecho de acceso a la información en los planes y programas de estudio de educación preescolar, primaria, secundaria, normal y para la formación de maestros de educación básica en sus respectivas jurisdicciones;\nII. Promover, entre las instituciones públicas y privadas de educación media superior, la inclusión, dentro de sus programas de estudio, actividades académicas curriculares y extracurriculares, de temas que ponderen la importancia social del derecho de acceso a la información y rendición de cuentas;\nIII. Promover, que en las bibliotecas y entidades especializadas en materia de archivos se prevea la instalación de módulos de información pública, que faciliten el ejercicio del derecho de acceso a la información y la consulta de la información derivada de las obligaciones de transparencia a que se refiere esta Ley;\nIV. Proponer, entre las instituciones públicas y privadas de educación superior, la creación de centros de investigación, difusión y docencia sobre transparencia, derecho de acceso a la información y rendición de cuentas;\nV. Establecer, entre las instituciones públicas de educación, acuerdos para la elaboración y publicación de materiales que fomenten la cultura del derecho de acceso a la información y rendición de cuentas;\nVI. Promover, en coordinación con autoridades federales, estatales y municipales, la participación ciudadana y de organizaciones sociales en talleres, seminarios y actividades información;\nVII. Desarrollar, programas de formación de personas usuarias de este derecho para incrementar su ejercicio y aprovechamiento, privilegiando a integrantes de grupos de atención prioritaria;\n.\nActualización Legislativa.\nVIII. Impulsar, estrategias que pongan al alcance de los diversos sectores de la sociedad los medios para el ejercicio del derecho de acceso a la información, acordes a su contexto sociocultural; y,\nIX. Desarrollar, con el concurso de centros comunitarios digitales y bibliotecas públicas, universitarias, gubernamentales y especializadas, programas para la asesoría y orientación de sus personas usuarias en el ejercicio y aprovechamiento del derecho de acceso a la información.\nARTÍCULO 39.- Para el cumplimiento de las obligaciones previstas en la presente\nLey, los sujetos obligados podrán desarrollar o adoptar, en lo individual o en acuerdo con otros sujetos obligados, esquemas de mejores prácticas que tengan por objeto:\nI. Elevar el nivel de cumplimiento de las disposiciones previstas en la presente Ley;\nII. Armonizar el acceso a la información por sectores;\nIII. Facilitar el ejercicio del derecho de acceso a la información a las personas; y,\nIV. Procurar la accesibilidad de la información.\nCapítulo II\nDe la Transparencia con Sentido Social\nARTÍCULO 40.- Las Autoridades Garantes emitirán políticas de transparencia con sentido social, en atención a los lineamientos generales definidos para ello por el Sistema\nNacional, diseñadas para incentivar a los sujetos obligados a publicar información de utilidad sobre temas prioritarios. Dichas políticas tendrán por objeto, entre otros, promover la reutilización y aprovechamiento de la información que generan los sujetos obligados, considerando la demanda de la sociedad, identificada con base en las metodologías previamente establecidas.\nARTÍCULO 41.- La información publicada por los sujetos obligados, en el marco de la política de transparencia con sentido social, se difundirá en los medios y formatos que más convengan al público al que va dirigida.\nARTÍCULO 42.- El Sistema Nacional emitirá los criterios para evaluar la efectividad de la política de la transparencia con sentido social, considerando como base, la reutilización y aprovechamiento que la sociedad haga a la información.\nLa información que se publique, como resultado de las políticas de transparencia, información, mejorar los accesos a trámites y servicios optimizar la toma de decisiones de autoridades cualquier persona, y deberá tener un objeto claro enfocado en las necesidades de sectores de la sociedad determinados determinables.\nCapítulo III\nDe la Apertura Institucional\n.\nActualización Legislativa.\nARTÍCULO 43.- Las Autoridades Garantes, en el ámbito de sus atribuciones, coadyuvarán con los sujetos obligados y representantes de la sociedad civil en la construcción e implementación de mecanismos de colaboración para la promoción e implementación de políticas y mecanismos de apertura institucional.\nARTÍCULO 44.- Los sujetos obligados, en el ámbito de su competencia, en materia de apertura institucional deben:\nI. Garantizar el ejercicio y cumplimiento de los principios de transparencia con sentido social, la participación ciudadana, la rendición de cuentas, la innovación y el aprovechamiento de la tecnología que privilegie su diseño centrado en el usuario;\nII. Implementar tecnología y datos abiertos incluyendo, en la digitalización de información relativa a servicios públicos, trámites y demás componentes del actuar gubernamental, la publicidad de datos de interés para la población, principalmente de manera automática y sin incremento de la carga administrativa, de conformidad con su disponibilidad presupuestaria; y,\nIII. Procurar mecanismos que fortalezcan la participación y la colaboración de las personas particulares en asuntos económicos, sociales, culturales y políticos de la Nación.\nARTÍCULO 45.- Las dependencias y entidades de la Administración Pública Estatal deberán realizar acciones en materia de datos abiertos y gobierno abierto conforme a los lineamientos que al efecto emita la Agencia Digital del Estado de Baja California.\nTÍTULO CUARTO\nOBLIGACIONES DE TRANSPARENCIA\nCapítulo I\nObligaciones Generales\nARTÍCULO 46.- Los sujetos obligados deberán cumplir con las obligaciones de transparencia y poner a disposición del público la información que se publique en sus portales de internet y a través de la Plataforma Nacional, la cual deberá mantenerse actualizada, de acuerdo con sus facultades, atribuciones, funciones u objeto social, según corresponda, la información, por lo menos, de los temas, documentos y políticas e información señalados en este Título. los supuestos de clasificación señalados en los artículos 96 y 99 de la presente Ley, no será objeto de la publicación a que se refiere este mismo artículo, salvo que pueda ser elaborada una versión pública. En todo caso se aplicará la prueba de daño a que se refiere el artículo\n91 de la presente Ley.\n.\nActualización Legislativa. transparencia de conformidad con este Título, atendiendo a la relevancia de la información, la incidencia de las solicitudes sobre la misma y el sentido reiterativo de las resoluciones.\nARTÍCULO 47.- Los lineamientos técnicos aprobados por el Sistema Nacional en los que se establezcan los formatos de publicación de la información a que se refiere este\nTítulo, deberán ser observados por los sujetos obligados para asegurar que la información sea veraz, confiable, oportuna, congruente, integral, actualizada, accesible, comprensible y verificable. Los lineamientos a que se refiere el párrafo anterior procurarán la homologación en la presentación de la información a la que hace referencia este Título por parte de los sujetos obligados.\nARTÍCULO 48.- La información correspondiente a las obligaciones de transparencia deberá actualizarse por lo menos cada tres meses, salvo que en la presente Ley se establezca un plazo diverso. El Sistema Nacional determinará los criterios que establezcan el plazo mínimo que deberá permanecer disponible y accesible la información, atendiendo a las cualidades de la misma.\nLa publicación de la información deberá indicar el sujeto obligado encargado de generarla, así como la fecha de su última actualización.\nARTÍCULO 49.- Las Autoridades Garantes, de oficio o a petición de las personas particulares, verificarán el cumplimiento que los sujetos obligados den a las disposiciones previstas en este Título.\nLas denuncias presentadas por las personas particulares podrán realizarse en cualquier momento, de conformidad con el procedimiento señalado en la presente Ley.\nARTÍCULO 50.- La página de inicio de los portales de internet de los sujetos obligados tendrá un vínculo de acceso directo al sitio donde se encuentra la información pública a la que se refiere este Título, el cual deberá contar con un buscador.\nLa información de obligaciones de transparencia deberá publicarse con perspectiva de género y discapacidad, cuando así corresponda, a su naturaleza.\nARTÍCULO 51.- Las Autoridades Garantes y los sujetos obligados establecerán las medidas que faciliten el acceso y búsqueda de la información para personas con discapacidad y se procurará que la información publicada sea accesible de manera focalizada a personas que hablen alguna lengua indígena. desarrollar de forma progresiva, políticas y programas tendientes a garantizar la accesibilidad de la información en la máxima medida posible.\nARTÍCULO 52.- Los sujetos obligados pondrán a disposición de las personas interesadas equipos de cómputo con acceso a internet, que permitan a las personas información en las oficinas de las Unidades de Transparencia. Lo anterior, sin perjuicio de\n.\nActualización Legislativa. que adicionalmente se utilicen medios alternativos de difusión de la información, cuando en determinadas poblaciones éstos resulten de más fácil acceso y comprensión.\nARTÍCULO 53.- La información publicada por los sujetos obligados, en términos del presente Título, no constituye propaganda gubernamental. Los sujetos obligados, incluso dentro de los procesos electorales, a partir del inicio de las precampañas y hasta la conclusión del proceso electoral, deberán mantener accesible la información en el portal de obligaciones de transparencia, salvo disposición expresa en contrario en las disposiciones jurídicas en materia electoral.\nARTÍCULO 54.- Los sujetos obligados y las personas particulares serán responsables de los datos personales en su posesión de conformidad con las disposiciones jurídicas aplicables en la materia.\nLos sujetos obligados no podrán difundir, distribuir o comercializar los datos personales contenidos en los sistemas de información, desarrollados en el ejercicio de sus funciones, salvo que haya mediado el consentimiento expreso, por escrito por un medio de autenticación similar, de las personas a que haga referencia la información de acuerdo a las disposiciones jurídicas aplicables. Lo anterior, sin perjuicio de lo establecido por el artículo\n103 de esta Ley.\nCapítulo II\nDe las Obligaciones de Transparencia Comunes\nARTÍCULO 55.- Los sujetos obligados pondrán a disposición del público y mantendrán actualizada, en los respectivos medios electrónicos, de acuerdo con sus facultades, atribuciones, funciones u objeto social, según corresponda, la información, por lo menos, de los temas, documentos y políticas que a continuación se señalan:\nI. El marco normativo aplicable al sujeto obligado, en el que deberá incluirse leyes, códigos, reglamentos, decretos de creación, manuales administrativos, reglas de operación, criterios, políticas, entre otros;\nII. Su estructura orgánica completa, en un formato que permita vincular cada parte de la estructura, las atribuciones responsabilidades que le corresponden a cada persona servidora pública y/o persona prestadora de servicios profesionales miembro de los sujetos obligados, de conformidad con las disposiciones aplicables;\nIII. Las facultades de cada área;\nIV. Las metas y objetivos de las áreas de conformidad con sus programas operativos;\nV. Los indicadores relacionados con temas de interés público o trascendencia social que, conforme a sus funciones, deban establecer, así como los que permitan rendir cuenta de sus objetivos y resultados;\n.\nActualización Legislativa.\nVI. El directorio de todas las personas servidoras públicas, a partir del nivel de jefatura de departamento su equivalente, de menor nivel, cuando se brinde atención al público; manejen o apliquen recursos públicos; realicen actos de autoridad o presten servicios profesionales bajo el régimen de confianza u honorarios y personal de base. El directorio deberá incluir, al menos el nombre, cargo o nombramiento asignado, nivel del puesto en la estructura orgánica, fecha de alta en el cargo, número telefónico, domicilio para recibir correspondencia dirección de correo electrónico oficiales;\nVII. La remuneración bruta y neta de todas las personas servidoras públicas de base o de confianza, de todas las percepciones, incluyendo sueldos, prestaciones, gratificaciones, primas, comisiones, dietas, bonos, estímulos, ingresos y sistemas de compensación, señalando la periodicidad de dicha remuneración;\nVIII. Los gastos de representación y viáticos, así como el objeto e informe de comisión correspondiente;\nIX. El número total de las plazas y del personal de base y confianza, especificando el total de las vacantes, por nivel de puesto, para cada unidad administrativa;\nX. Las contrataciones de servicios profesionales por honorarios, señalando los nombres de las personas prestadoras de servicios, los servicios contratados, el monto de los honorarios y el periodo de contratación;\nXI. La versión pública de las declaraciones patrimoniales de las personas servidoras públicas en términos de las disposiciones jurídicas aplicables, en los sistemas habilitados para ello;\nXII. El domicilio de la Unidad de Transparencia, además de la dirección electrónica donde podrán recibirse las solicitudes para obtener la información;\nXIII. Las convocatorias a concursos para ocupar cargos públicos y los resultados de los mismos, en los sistemas habilitados para ello, de conformidad con las disposiciones jurídicas aplicables;\nXIV. Los programas, subsidios, estímulos y apoyos, en el que se deberá informar respecto de los programas de transferencia, de servicios, de infraestructura social y de subsidio, en los que se deberá contener lo siguiente:\na) Área;\nb) Denominación del programa;\nc) Periodo de vigencia;\nd) Diseño, objetivos y alcances;\ne) Metas físicas;\n.\nActualización Legislativa.\nf) Población beneficiada estimada;\ng) Monto aprobado, modificado y ejercido, así como los calendarios de su programación presupuestal;\nh) Requisitos y procedimientos de acceso;\ni) Procedimiento de queja o inconformidad ciudadana;\nj) Mecanismos de exigibilidad;\nk) Mecanismos de evaluación, informes de evaluación y seguimiento de recomendaciones;\nl) Indicadores con nombre, definición, método de cálculo, unidad de medida, dimensión, frecuencia de medición, nombre de las bases de datos utilizadas para su cálculo;\nm) Formas de participación social;\nn) Articulación con otros programas sociales;\no) Vínculo a las reglas de operación o documento equivalente;\np) Informes periódicos sobre la ejecución y los resultados de las evaluaciones realizadas; y,\nq) Padrón de personas beneficiarias mismo que deberá contener los siguientes datos: nombre de la persona física o denominación social de las personas morales beneficiarias, el monto, recurso, beneficio o apoyo otorgado para cada una de ellas, unidad territorial, en su caso, edad y sexo.\nXV. Las condiciones generales de trabajo, contratos o convenios que regulen las relaciones laborales del personal de base o de confianza, así como los recursos públicos económicos, en especie o donativos, que sean entregados a los sindicatos y ejerzan como recursos públicos;\nXVI. La información curricular, desde el nivel de jefatura de departamento equivalente, hasta la titularidad del sujeto obligado;\nXVII. El listado de personas servidoras públicas con sanciones administrativas firmes, especificando la causa de sanción y la disposición, de conformidad a lo establecido en las disposiciones jurídicas aplicables;\nXVIII. Los servicios y trámites que ofrecen, incluyendo sus requisitos, en los sistemas habilitados para ello, de conformidad con las disposiciones jurídicas aplicables;\n.\nActualización Legislativa.\nXIX. La información financiera sobre el presupuesto asignado, así como los informes del ejercicio trimestral del gasto, en términos de la Ley General de Contabilidad\nGubernamental y demás disposiciones jurídicas aplicables;\nXX. La información relativa a la deuda pública, en términos de las disposiciones jurídicas aplicables;\nXXI. Los montos destinados a gastos relativos a comunicación social y publicidad oficial que permita identificar el tipo de medio, proveedores, número de contrato y concepto o compañía;\nXXII. Los informes de resultados de las auditorías al ejercicio presupuestal de cada sujeto obligado que se realicen y, en su caso, las aclaraciones que correspondan;\nXXIII. El resultado de la dictaminación de los estados financieros;\nXXIV. Los montos, criterios, convocatorias y listado de personas físicas o morales a quienes, por cualquier motivo, se les asigne o permita usar recursos públicos o, en los términos de las disposiciones aplicables, realicen actos de autoridad. Asimismo, los informes que dichas personas les entreguen sobre el uso y destino de dichos recursos;\nXXV. Las concesiones, contratos, convenios, permisos, licencias o autorizaciones otorgados, especificando las personas titulares de aquéllos, debiendo publicarse su objeto, nombre o razón social de la persona titular, vigencia, tipo, términos, condiciones, monto y modificaciones, así como si el procedimiento involucra el aprovechamiento de bienes, servicios y/o recursos públicos;\nXXVI. Los resultados de los procedimientos de adjudicación directa, invitación y licitación de cualquier naturaleza, incluyendo la versión pública del expediente respectivo de los contratos celebrados, que deberá contener, por lo menos, lo siguiente:\na) De licitaciones públicas o procedimientos de invitación:\n1. La convocatoria o invitación emitida, así como los fundamentos legales aplicados para llevarla a cabo;\n2. Los nombres de las personas participantes o invitadas;\n3. El nombre de la persona ganadora y las razones que lo justifican;\n4. El área solicitante y la responsable de su ejecución;\n5. Las convocatorias e invitaciones emitidas;\n6. Los dictámenes y fallo de adjudicación;\n7. El contrato y, en su caso, sus anexos;\n.\nActualización Legislativa.\n8. Los mecanismos de vigilancia y supervisión, incluyendo, en su caso, los estudios de impacto urbano ambiental, según corresponda;\n9. La partida presupuestal, de conformidad con el clasificador por objeto del gasto, en el caso de ser aplicable;\n10. Origen de los recursos especificando si son federales, estatales o municipales, así como el tipo de fondo de participación o aportación respectiva;\n11. Los convenios modificatorios que, en su caso, sean firmados, precisando el objeto y la fecha de celebración;\n12. Los informes de avance físico y financiero sobre las obras o servicios contratados;\n13. El convenio de terminación; y,\n14. El finiquito.\nb) De las adjudicaciones directas:\n1. La propuesta enviada por el participante;\n2. Los motivos y fundamentos legales aplicados para llevarla a cabo;\n3. La autorización del ejercicio de la opción;\n4. En su caso, las cotizaciones consideradas, especificando los nombres de proveedores y los montos;\n5. El nombre de la persona física o moral adjudicada;\n6. La unidad administrativa solicitante y la responsable de su ejecución;\n7. El número, fecha, el monto del contrato y el plazo de entrega o de ejecución de los servicios u obra;\n8. Los mecanismos de vigilancia y supervisión, incluyendo, en su caso, los estudios de impacto urbano y ambiental, según corresponda;\n9. Los informes de avance sobre las obras o servicios contratados;\n10. El convenio de terminación; y,\n11. El finiquito.\nXXVII. Los informes que generen de conformidad con las disposiciones jurídicas;\n.\nActualización Legislativa.\nXXVIII. Las estadísticas que generen en cumplimiento de sus facultades, competencias o funciones;\nXXIX. Los informes de avances programáticos o presupuestales, balances generales y su estado financiero;\nXXX. El Padrón de proveedores y contratistas en los sistemas habilitados para ello, de conformidad con las disposiciones jurídicas aplicables;\nXXXI. Los convenios de coordinación de concertación con los sectores social y privado;\nXXXII. El inventario de bienes muebles e inmuebles en posesión y propiedad;\nXXXIII. Las recomendaciones emitidas por los órganos públicos del Estado Mexicano u organismos internacionales garantes de los derechos humanos, así como las acciones que han llevado a cabo para su atención;\nXXXIV. Las resoluciones que se emitan en procesos o procedimientos seguidos en forma de juicio;\nXXXV. Los mecanismos de participación ciudadana;\nXXXVI. Los programas que ofrecen, incluyendo información sobre la población, objetivo y destino, así como los trámites, tiempos de respuesta, requisitos y formatos para acceder a los mismos;\nXXXVII. Las actas y resoluciones del Comité de Transparencia de los sujetos obligados;\nXXXVIII. Las evaluaciones y encuestas que hagan los sujetos obligados a programas financiados con recursos públicos;\nXXXIX. Los estudios financiados con recursos públicos;\nXL. El listado de personas jubiladas y pensionadas, así como el monto que reciben;\nXLI. Los ingresos recibidos por cualquier concepto señalando el nombre de las personas responsables de recibirlos, administrarlos y ejercerlos, así como su destino;\nXLII. Las donaciones hechas a terceros en dinero o en especie;\nXLIII. El catálogo de disposición y guía de archivo documental;\nXLIV. Las actas de sesiones ordinarias y extraordinarias, así como las opiniones y recomendaciones que, en su caso, emitan los consejos consultivos;\n.\nActualización Legislativa.\nXLV. El listado de solicitudes a las empresas concesionarias de telecomunicaciones y proveedores de servicios o aplicaciones de internet para la intervención de comunicaciones privadas, el acceso al registro de comunicaciones y la localización geográfica en tiempo real de equipos de comunicación, que contenga exclusivamente el objeto, el alcance temporal y los fundamentos legales del requerimiento, así como, en su caso, mención de que cuenta con la autorización judicial correspondiente; y, XLVI. Cualquier otra información que sea de utilidad o se considere relevante, además de la que, con base en la información estadística, responda a las preguntas hechas con más frecuencia por el público, y la que se encuentre prevista en otras disposiciones jurídicas aplicables.\nLos sujetos obligados deberán informar a las Autoridades Garantes de forma fundada y motivada cuáles son las fracciones de este artículo las que les resultan aplicables, para efecto de que las Autoridades las validen.\nUna vez que cuenten con la validación de referencia los sujetos obligados procederán a publicarlas en la Plataforma Nacional.\nCapítulo III\nDe las Obligaciones de Transparencia Específicas\nARTÍCULO 56.- Los sujetos obligados del Poder Ejecutivo del Estado, y de los municipios, además de lo señalado en el artículo anterior, deberán poner a disposición del público y actualizar, conforme al ámbito de su competencia, la información siguiente:\nI. Los planes y programas que se deriven de la aplicación de la Ley de Planeación para el Estado de Baja California;\nII. El presupuesto de egresos y las fórmulas de distribución de los recursos otorgados;\nIII. Los ingresos por concepto de participaciones federales y estatales; así como por la recaudación fiscal que se integre a la hacienda pública, incluyendo la de entidades paramunicipales;\nIV. Las expropiaciones decretadas y ejecutadas, que incluya, cuando menos la fecha de expropiación, el domicilio y la causa de utilidad pública y las ocupaciones superficiales;\nV. El nombre, denominación o razón social y clave del registro federal de contribuyentes a quienes se les hubiera cancelado o condonado algún crédito fiscal, así como los montos respectivos;\nVI. Los nombres de las personas a quienes se les habilitó para ejercer como notarios públicos, así como sus datos de contacto, la información relacionada con el proceso de otorgamiento de la patente y las sanciones que se les hubieran aplicado;\n.\nActualización Legislativa.\nVII. Los planes de desarrollo urbano, ordenamiento territorial y ecológico, los tipos y usos de suelo, licencias de uso y construcción otorgadas por los gobiernos municipales;\nVIII. Las aportaciones estatales a los municipios;\nIX. Los proyectos de disposiciones administrativas, salvo que su difusión pueda comprometer los efectos que se pretenden lograr con la disposición o se trate de situaciones de emergencia, en términos de lo previsto en la Ley Nacional para Eliminar Trámites\nBurocráticos;\nX. Las gacetas municipales, las cuales deberán comprender los resolutivos y acuerdos aprobados por los Ayuntamientos; y,\nXI. Las actas de sesiones de cabildo, los controles de asistencia de las personas integrantes del Ayuntamiento a las sesiones de cabildo y el sentido de votación de la y los miembros del cabildo sobre las iniciativas o acuerdos.\nARTÍCULO 57.- Los sujetos obligados del Poder Ejecutivo del Estado, además de lo señalado en el artículo anterior, de conformidad con la materia de sus atribuciones, deberán poner a disposición del público y actualizar la siguiente información:\nI. En materia hacendaria:\na) La cartera de programas y proyectos de inversión;\nb) Para efectos estadísticos, la lista de estímulos fiscales establecidos en las leyes fiscales, identificados por acreditamiento, devoluciones, diminuciones, y deducciones, tanto de personas físicas como morales, así como su porcentaje; y,\nc) El nombre, denominación o razón social y clave del registro federal de contribuyentes a quienes se les hubiera cancelado o condonado algún crédito fiscal, ya determinado y exigible, así como los montos respectivos; debiendo vincular tales actos con los datos de identificación de contribuyentes señalados en este párrafo. Asimismo, la información estadística sobre las exenciones previstas en las disposiciones fiscales.\nII. En materia de población:\na) El número de centros de reinserción social y centros de internamiento para adolescentes, indicando su capacidad instalada, así como su ubicación y la función de los espacios físicos de infraestructura con los que cuentan; y,\nb) La estadística de los grupos de protección a migrantes, por acciones de atención.\nIII. En materia de seguridad pública y procuración de justicia:\na) La estadística de los procesos de control de confianza desagregada por institución;\n.\nActualización Legislativa.\nb) La incidencia delictiva del fuero local, desagregada por tipo de delito, así como el número de víctimas desagregado por sexo y rango de edad; y,\nc) La estadística desagregada de procesos, denuncias e investigaciones relacionadas a las conductas consideradas como delitos en materia de justicia para adolescentes.\nIV. En materia del medio ambiente y recursos naturales:\na) El listado de áreas naturales protegidas, que contenga categoría, superficie, región y municipios que las comprenden.\nb) El listado de especies en riesgo, por grupo taxonómico.\nc) El listado de vegetación natural, por municipio, por ecosistema y por superficie.\nd) El listado estimado de residuos, por tipo, por volumen, por municipio y por año.\ne) El listado de zonas contaminadas, por tipo de contaminante y localización.\nf) Los tipos de vegetación forestal y de suelos, su localización, formaciones y clases, con tendencias y proyecciones que permitan clasificar y delimitar el estado actual de la deforestación y degradación, así como las zonas de conservación, protección, restauración y producción forestal, las regiones ecológicas, las áreas forestales permanentes y las áreas naturales protegidas.\ng) La dinámica de cambio de la vegetación forestal del estado, que permita conocer y evaluar las tasas de deforestación y las tasas de degradación y disturbio, registrando sus causas principales.\nh) Los criterios e indicadores de sustentabilidad, deforestación y degradación de los ecosistemas forestales.\ni) El listado de plantaciones comerciales forestales, que contenga su ubicación, superficie, tipo de especie forestal, nivel de producción y su estatus.\nj) Las manifestaciones y resoluciones en materia de impacto ambiental.\nk) Información estadística sobre los árboles históricos y notables del estado.\nl) Información estadística sobre sanciones, identificando la causa que haya motivado la sanción, el precepto legal infringido y la descripción de la sanción.\nm) El índice de participación ciudadana, que contenga la categoría, ponderación, unidad de medida y año.\nV. En materia de agricultura, ganadería, desarrollo rural, pesca y alimentación:\n.\nActualización Legislativa.\na) El listado de apoyos otorgados en materia de agricultura, ganadería, pesca o alimentación, que contenga municipio, población o localidad, descripción o monto del apoyo, y el número de beneficiarios distinguidos por género;\nb) El listado de activos y unidades económicas de pesca y acuacultura, que contenga municipio, embarcaciones, granjas laboratorios y tipo de actividad; y,\nc) El listado de agronegocios, empresas rurales y productos que reciben incentivos de riesgo compartido, que contenga objetivo y tipo de incentivo.\nVI. En materia de sector de educación y cultura:\na) El Catálogo de los Centros de Trabajo de carácter educativo en la educación básica, media superior, superior, especial, inicial y formación para el trabajo incluyendo la información relativa a su situación geográfica, tipo de servicio que proporciona y estatus de operación;\nb) El listado del personal que presta sus servicios en los sistemas de educación pública básica, tecnológica y de adultos, cuyas remuneraciones se cubren con cargo a recursos públicos estatales;\nc) El padrón de beneficiarios de las becas, así como los procedimientos y requisitos para obtenerlas, desagregado por nombre, tipo, fecha de inicio y término de la beca, área del conocimiento, así como el monto otorgado; y,\nd) El catálogo de museos, que contenga el nombre, ubicación, horarios, temática tratada, servicios disponibles y cuota de acceso.\nVII. En materia de salud:\na) El listado de los institutos o centros de salud, desagregados por nombre, especialidad, dirección y teléfono; y,\nb) El listado de las instituciones de beneficencia privada, que tengan por objeto la asistencia pública, desagregada por nombre, ubicación, datos de contacto y tipo.\nVIII. En materia de trabajo y previsión social:\na) El nombre y objeto de las asociaciones obreras y patronales de jurisdicción estatal y municipal registradas; y,\nb) El número de personas beneficiadas por las actividades de capacitación, promoción al empleo, colocación de trabajadores y vinculación laboral del Servicio Estatal de\nEmpleo, por año, municipio, oficio o profesión, género, rango de edad, ramo o industria y mecanismo de vinculación.\nIX. En materia de desarrollo agrario, territorial y urbano:\n.\nActualización Legislativa.\na) El listado de núcleos agrarios identificando los datos técnicos generales y la síntesis diagnóstica de los mismos.\nX. En materia de turismo:\na) Información estadística sobre las actividades económicas vinculadas al turismo, como número de visitantes internacionales, flujos aéreos, flujos de cruceros y flujos carreteros;\nb) Información correspondiente a destinos turísticos, con estadísticas sobre actividades turísticas;\nc) Información estadística sobre ocupación hotelera; y,\nd) El listado de prestadores de servicios turísticos.\nARTÍCULO 58.- Los sujetos obligados del Poder Legislativo del Estado, además de lo señalado en el artículo 55 de la presente Ley, deberán poner a disposición del público y actualizar la información siguiente:\nI. El Plan de Desarrollo Legislativo, así como las agendas legislativas correspondientes a los Grupos Parlamentarios y Diputaciones que cuenten con un escaño en el Poder Legislativo del Estado;\nII. Gaceta Parlamentaria;\nIII. Orden del día;\nIV. El Diario de Debates;\nV. Las versiones estenográficas;\nVI. La asistencia de cada una de las Diputaciones a sus sesiones del Pleno, Comisiones y Comités;\nVII. Las iniciativas de ley o decretos, puntos de acuerdo, la fecha en que se recibió, las Comisiones a las que se turnaron, y los dictámenes que, en su caso, recaigan sobre las mismas;\nVIII. Las leyes, decretos y acuerdos aprobados por el órgano legislativo;\nIX. Las convocatorias, actas, acuerdos, listas de asistencia y votación de las comisiones y comités y de las sesiones del Pleno, identificando el sentido del voto, en votación económica, y por cada diputación, en la votación nominal y el resultado de la votación por cédula, así como votos particulares y reservas de dictámenes y acuerdos sometidos a consideraciones;\nX. Las resoluciones definitivas sobre juicios políticos y declaratorias de procedencia;\n.\nActualización Legislativa.\nXI. Las versiones públicas de la información entregada en las audiencias públicas, comparecencias y en los procedimientos de designación, ratificación, elección, reelección o cualquier otro;\nXII. Las contrataciones de servicios personales señalando el nombre de la persona prestadora del servicio, objeto, monto y vigencia del contrato;\nXIII. El informe semestral del ejercicio presupuestal del uso y destino de los recursos financieros del área administrativa que lo ejerza; y,\nXIV. Los resultados de los estudios o investigaciones de naturaleza económica, política y social que realice el Poder Legislativo del Estado.\nARTÍCULO 59.- El Poder Judicial del Estado, además de lo señalado en el artículo 55 de la presente Ley, deberá poner a disposición del público y actualizar la información siguiente:\nI. Las versiones públicas de todas las sentencias y laudos emitidas;\nII. Las versiones estenográficas, los audios y las videograbaciones de las sesiones públicas, según corresponda;\nIII. La relacionada con los procesos por medio de los cuales fueron designadas las\nMagistraturas, Juezas y Jueces;\nIV. La lista de acuerdos que diariamente se publiquen;\nV. Sobre los procedimientos de designación de Magistraturas, Juezas y Jueces: la convocatoria, el registro de aspirantes, la lista de aspirantes aceptados, la lista de las personas aspirantes que avanzan cada una de las etapas, el resultado de las evaluaciones de cada etapa protegiendo, en su caso, los datos personales de las personas aspirantes y la lista de vencedores;\nVI. Sobre los procedimientos de ratificación: la resolución definitiva donde se plasmen las razones de esa determinación;\nVII. Las resoluciones que impongan sanciones disciplinarias a las personas disposiciones jurídicas aplicables;\nVIII. Los indicadores relacionados con el desempeño jurisdiccional que, conforme a sus funciones, deban establecer, publicitando por lo menos los números de ingresos de asuntos nuevos por mes y por año, números de resoluciones emitidas por mes y por año, sentido general del fallo de acuerdo con la materia, tiempo promedio de resolución de asuntos, número de impugnaciones recibidas por mes y por año, número de impugnaciones declaradas procedentes por mes y por año;\n.\nActualización Legislativa.\nIX. Las disposiciones de observancia general emitidas por los Plenos o sus\nPresidencias, para el adecuado ejercicio de sus atribuciones;\nX. Los votos concurrentes, minoritarios, aclaratorios, particulares, cualquier otro tipo, que emitan las personas integrantes de los Plenos; y,\nXI. Las resoluciones recaídas a los asuntos de contradicciones de criterios.\nARTÍCULO 60.- Los órganos autónomos, además de lo señalado en el artículo 55 de la presente Ley, deberán poner a disposición del público y actualizar la información siguiente:\nI. Instituto Estatal Electoral:\na) Los listados de partidos políticos, asociaciones y agrupaciones políticas o de las personas ciudadanas registradas ante la autoridad electoral;\nb) Los informes que presenten los partidos políticos, asociaciones y agrupaciones políticas o de personas ciudadanas;\nc) La geografía y cartografía electoral;\nd) El registro de personas candidatas a cargos de elección popular;\ne) El catálogo de estaciones de radio y canales de televisión, pautas de transmisión, versiones de spots de los institutos electorales y de los partidos políticos;\nf) Los montos de financiamiento público por actividades ordinarias, de campaña específicas otorgadas a los partidos políticos, asociaciones agrupaciones políticas o de personas ciudadanas y demás asociaciones políticas, así como los montos autorizados de financiamiento privado y los topes de los gastos de campañas;\ng) La metodología e informes sobre la publicación de encuestas por muestreo, encuestas de salida y conteos rápidos financiados por las autoridades electorales competentes;\nh) La metodología e informe del Programa de Resultados Preliminares Electorales;\ni) Los cómputos totales de las elecciones locales y procesos de participación ciudadana;\nj) Los resultados y declaraciones de validez de las elecciones;\nk) Las franquicias postales y telegráficas asignadas al partido político para el cumplimiento de sus funciones;\nl) La información sobre votos de mexicanas y mexicanos residentes en el extranjero para la elección de Gobernadora o Gobernador;\n.\nActualización Legislativa.\nm) Los dictámenes, informes y resoluciones sobre perdida de registro y liquidación del patrimonio de partidos políticos nacionales y locales; y,\nn) El monitoreo de medios.\nII. Tribunal de Justicia Electoral del Estado de Baja California:\na) Las tesis jurisprudenciales y aisladas del Tribunal;\nb) Las sentencias que dicte;\nc) La cantidad y clave de identificación de las resoluciones del Tribunal confirmadas, revocadas y modificadas por el Tribunal Electoral del Poder Judicial de la Federación;\nd) Las versiones estenográficas de sus sesiones; y,\ne) La lista de acuerdos que diariamente se publiquen.\nIII. Tribunal Estatal de Justicia Administrativa:\na) Las tesis jurisprudenciales y aisladas del Tribunal;\nb) Las sentencias que dicte;\nc) Las versiones estenográficas de sus sesiones; y,\nd) La lista de acuerdos que diariamente se publiquen.\nIV. Comisión Estatal de Derechos Humanos:\na) El listado y las versiones públicas de las recomendaciones emitidas, su destinatario o autoridad a la que se recomienda y el estado que guarda su atención, incluyendo, en su caso, las minutas de comparecencias de las personas titulares que se negaron a aceptar las recomendaciones;\nb) Las quejas y denuncias presentadas ante las autoridades administrativas y penales respectivas, señalando el estado procesal en que se encuentran y, en su caso, el sentido en el que se resolvieron;\nc) Las versiones públicas del acuerdo de conciliación, previo consentimiento del quejoso;\nd) Listado de medidas precautorias, cautelares o equivalentes, giradas una vez concluido el expediente;\ne) Toda la información con que cuente, relacionada con hechos constitutivos de violaciones graves de derechos humanos o delitos de lesa humanidad, una vez\n.\nActualización Legislativa. determinados así por la autoridad competente, incluyendo, en su caso, las acciones de reparación del daño, atención a víctimas y de no repetición;\nf) La información relacionada con las acciones y resultados de defensa, promoción y protección de los derechos humanos;\ng) Las actas y versiones estenográficas de las sesiones del consejo consultivo, así como las opiniones que emite;\nh) Los resultados de los estudios, publicaciones o investigaciones que realicen;\ni) Los programas de prevención y promoción en materia de derechos humanos;\nj) El estado que guardan los derechos humanos en el sistema penitenciario y de readaptación social del país;\nk) El seguimiento, evaluación y monitoreo, en materia de igualdad entre mujeres y hombres; y,\nl) Los programas y las acciones de coordinación con las dependencias competentes para impulsar el cumplimiento de tratados de los que el Estado mexicano sea parte, en materia de Derechos Humanos.\nV. Fiscalía General del Estado publicará la información estadística en las siguientes materias:\na) Incidencia delictiva;\nb) Indicadores de la procuración de justicia, en materia de carpetas de investigación y averiguaciones previas, deberá publicarse el número de aquéllas en las que se ejerció acción penal; en cuántas se decretó el no ejercicio de la acción penal; cuántas se archivaron; en cuántas se ejerció la facultad de atracción en materia de delitos cometidos contra la libertad de expresión; en cuántas se ejerció el criterio de oportunidad, y en cuántas ejerció la facultad de no investigar los hechos de su conocimiento. Dicha información deberá incluir el número de denuncias o querellas que le fueron interpuestas;\nc) La estadística relativa a la solución de controversias realizadas a través de los mecanismos alterativos de solución de controversias en materia penal, desagregada por medios de mediación, conciliación y proceso restaurativo; y,\nd) Número de órdenes de presentación, aprehensión y de cateo emitidas.\nARTÍCULO 61.- Además de lo señalado en el artículo 55, las Autoridades Garantes deberán poner a disposición del público y actualizar:\nI. La relación de observaciones y resoluciones emitidas y el seguimiento a cada una de ellas, incluyendo las respuestas entregadas por los sujetos obligados a las personas solicitantes en cumplimiento de las resoluciones;\n.\nActualización Legislativa.\nII. Los criterios orientadores que deriven de sus resoluciones;\nIII. Los resultados de la evaluación que, en su caso, se realice al cumplimiento de la presente Ley por parte de los sujetos obligados;\nIV. En su caso, las sentencias, ejecutorias o suspensiones judiciales que existan en contra de sus resoluciones; y,\nV. El número de quejas, denuncias y recursos de revisión dirigidos a cada uno de los sujetos obligados.\nARTÍCULO 62.- Las instituciones de educación superior públicas, además de lo señalado en el artículo 55 de la presente Ley, deberán poner a disposición del público y actualizar la información siguiente:\nI. Los planes y programas de estudio según el sistema que ofrecen, ya sea escolarizado o abierto; con las áreas de conocimiento, el perfil profesional de quien cursa el plan de estudios, la duración del programa con las asignaturas, su valor en créditos, formas y costos de titulación;\nII. La información relacionada con sus procedimientos administrativos;\nIII. La remuneración de los profesores, incluyendo los estímulos, prestaciones, gratificaciones, primas, comisiones, dietas, bonos, ingresos y sistemas de compensación, señalando la periodicidad de dicha remuneración, nivel y monto;\nIV. La lista con los profesores con licencia o en año sabático;\nV. El listado de las becas y apoyos que otorgan, así como los procedimientos y requisitos para obtenerlos;\nVI. Las convocatorias de los concursos de oposición;\nVII. La información relativa a los procesos de selección de los consejos;\nVIII. El resultado de las evaluaciones del cuerpo docente;\nIX. El listado de instituciones incorporadas y requisitos de incorporación;\nX. El número de personas estudiantes inscritas, desglosado por área de conocimiento, tipo de sistema de estudios, modalidad de estudio, grado académico y denominación o título del grado; y,\nXI. El número de personas egresadas y tituladas, desglosado por área de conocimiento, tipo de sistema de estudios, modalidad de estudio, grado académico y denominación o título del grado.\n.\nActualización Legislativa.\nARTÍCULO 63.- Los fideicomisos, fondos públicos estatales, mandatos o cualquier contrato análogo, además de lo señalado en el artículo 55 de la presente Ley, deberán poner a disposición del público y mantener actualizada y accesible, en lo que resulte aplicable a cada contrato, la información siguiente:\nI. El nombre de la persona servidora pública y de la persona física o moral que represente al fideicomitente, al fiduciario y al fideicomisario;\nII. La unidad administrativa responsable del fideicomiso;\nIII. El monto total, el uso y destino del patrimonio fideicomitido, distinguiendo las aportaciones públicas y fuente de los recursos, los subsidios, donaciones, transferencias, excedentes, inversiones realizadas aportaciones o subvenciones que reciban;\nIV. El saldo total al cierre del ejercicio fiscal, sin perjuicio de los demás informes que deban presentarse en los términos de las disposiciones aplicables;\nV. Las modificaciones que, en su caso, sufran los contratos o decretos de constitución del fideicomiso o el fondo público;\nVI. El padrón de beneficiarios, en su caso;\nVII. Causas por las que, en su caso, se inicie el proceso de constitución o extinción del fideicomiso o fondo público, especificando, de manera detallada, los recursos financieros destinados para tal efecto; y,\nVIII. Los contratos de obras, adquisiciones y servicios que involucren recursos públicos del fideicomiso, así como los honorarios derivados de los servicios y operaciones que realice la institución de crédito o la fiduciaria.\nARTÍCULO 64.- Para determinar la información adicional que publicarán todos los sujetos obligados de manera obligatoria, las Autoridades Garantes, en el ámbito de su competencia, deberán:\nI. Solicitar a los sujetos obligados que, atendiendo a los lineamientos emitidos por el\nSistema Nacional, remitan el listado de información que consideren de interés público;\nII. Revisar el listado que remitió el sujeto obligado con base en las funciones, atribuciones y competencias que las disposiciones jurídicas aplicables le otorguen; y,\nIII. Determinar el catálogo de información que el sujeto obligado deberá publicar como obligación de transparencia.\nCapítulo IV\n.\nActualización Legislativa.\nARTÍCULO 65.- Las Autoridades Garantes determinarán los casos en que las personas físicas o morales que reciban y ejerzan recursos públicos o realicen actos de autoridad, cumplirán con las obligaciones de transparencia y acceso a la información directamente o a través de los sujetos obligados que les asignen dichos recursos o, en los términos de las disposiciones aplicables, realicen actos de autoridad.\nLos sujetos obligados correspondientes deberán enviar a las Autoridades Garantes un listado de las personas físicas o morales a los que, por cualquier motivo, asignaron recursos públicos o, en los términos que establezcan las disposiciones aplicables, ejercen actos de autoridad.\nPara resolver sobre el cumplimiento de lo señalado en el párrafo anterior, las\nAutoridades Garantes tomarán en cuenta si realiza una función gubernamental, el nivel de financiamiento público, el nivel de regulación e involucramiento gubernamental y si el gobierno participó en su creación.\nARTÍCULO 66.- Para determinar la información que deberán hacer pública las personas físicas o morales que reciben y ejercen recursos públicos o realizan actos de autoridad, las Autoridades Garantes deberán:\nI. Solicitar a las personas físicas o morales que, atendiendo a los lineamientos emitidos por el Sistema Nacional, remitan el listado de información que consideren de interés público;\nII. Revisar el listado que remitió la persona física o moral en la medida en que reciba y ejerza recursos o realicen actos de autoridad que las disposiciones jurídicas aplicables le otorguen; y,\nIII. Determinar las obligaciones de transparencia que deben cumplir y los plazos para ello.\nCapítulo V\nDe la Verificación de las Obligaciones de Transparencia\nARTÍCULO 67.- Las Autoridades Garantes, en su ámbito de competencia, vigilarán que las obligaciones de transparencia que publiquen los sujetos obligados cumplan con lo dispuesto en esta Ley y demás disposiciones aplicables.\nARTÍCULO 68.- Las determinaciones que emitan las Autoridades Garantes deberán establecer los requerimientos, recomendaciones u observaciones que formulen y los términos y plazos en los que los sujetos obligados deberán atenderlas. El incumplimiento a los requerimientos formulados, será motivo para aplicar las medidas de apremio, sin perjuicio de las sanciones a que haya lugar.\nARTÍCULO 69.- Las Autoridades Garantes, en el ámbito de su competencia, vigilarán\n.\nActualización Legislativa. obligados y cumplan con lo dispuesto en los artículos 55 a 66 de esta Ley y demás disposiciones jurídicas aplicables.\nARTÍCULO 70.- Las acciones de vigilancia a que se refiere este Capítulo, se realizarán a través de la verificación virtual. Esta vigilancia surgirá de los resultados de la verificación que se lleve a cabo de manera oficiosa por las Autoridades Garantes al portal de internet de los sujetos obligados o de la Plataforma Nacional, ya sea de forma aleatoria o muestral y periódica.\nARTÍCULO 71.- La verificación que realice las Autoridades Garantes se sujetará a lo siguiente:\nI. Constatar que la información esté completa, publicada y actualizada en tiempo y forma;\nII. Emitir un dictamen en el que podrá determinar que el sujeto obligado cumple o no con lo establecido por esta Ley y demás disposiciones aplicables. En el supuesto de que determine que no da cumplimiento formulará los requerimientos que procedan a efecto de que el sujeto obligado subsane las inconsistencias detectadas e informe la atención a los requerimientos dentro de un plazo no mayor a veinte días; y,\nIII. Verificar el cumplimiento de la resolución una vez transcurrido el plazo y si considera que fueron atendidos los requerimientos del dictamen, emitirá un acuerdo de cumplimiento.\nLas Autoridades Garantes podrán solicitar los informes complementarios al sujeto obligado que requiera para allegarse de los elementos de juicio que consideren necesarios para llevar a cabo la verificación.\nCuando las Autoridades Garantes consideren que existe un incumplimiento total o parcial de la determinación, le notificará, por conducto de la Unidad de Transparencia, al superior jerárquico del servidor público responsable de dar cumplimiento, para el efecto de que, en un plazo no mayor a diez días, dé cumplimiento a los requerimientos del dictamen.\nEn caso de que las Autoridades Garantes consideren que subsiste el incumplimiento total o parcial de la resolución, en un plazo no mayor a cinco días impondrán las medidas de apremio o sanciones, conforme a lo establecido por esta Ley.\nAdicionalmente, las Autoridades Garantes podrán emitir recomendaciones a los sujetos obligados, a fin de procurar que los formatos en que se publique la información, sea de mayor utilidad.\nCapítulo VI\nARTÍCULO 72.- Cualquier persona podrá denunciar ante las Autoridades Garantes la falta de publicación de las obligaciones de transparencia previstas en los artículos 55 a 66\n.\nActualización Legislativa. de esta Ley y demás disposiciones jurídicas aplicables, en sus respectivos ámbitos de competencia.\nARTÍCULO 73.- El procedimiento de la denuncia se integra por las siguientes etapas:\nI. Presentación de la denuncia ante las Autoridades Garantes;\nII. Solicitud por parte de las Autoridades Garantes de un informe al sujeto obligado;\nIII. Resolución de la denuncia; y,\nIV. Ejecución de la resolución de la denuncia.\nARTÍCULO 74.- La denuncia por incumplimiento a las obligaciones de transparencia deberá cumplir, al menos, los siguientes requisitos:\nI. Nombre del sujeto obligado denunciado;\nII. Descripción clara y precisa del incumplimiento denunciado;\nIII. La persona denunciante podrá adjuntar los medios de prueba que estime necesarios para respaldar el incumplimiento denunciado;\nIV. En caso de que la denuncia se presente:\na) Por escrito, la persona denunciante deberá señalar el domicilio en la jurisdicción que corresponda o la dirección de correo electrónico para recibir notificaciones; y,\nb) Por medios electrónicos, se entenderá que se acepta que las notificaciones se efectúen por el mismo medio en el que la presente.\nEn caso de que no se señale domicilio o dirección de correo electrónico o se señale un domicilio fuera de la jurisdicción respectiva, las notificaciones, aún las de carácter personal, se practicarán a través de los estrados físicos de la Autoridad Garante competente.\nV. Opcionalmente el nombre de la persona denunciante.\nARTÍCULO 75.- La denuncia podrá presentarse de la forma siguiente:\nI. Por medio electrónico:\na) A través de la Plataforma Nacional; o,\nb) Por correo electrónico, dirigido a la dirección electrónica que al efecto se establezca por la Autoridad Garante competente.\n.\nActualización Legislativa.\nII. Por escrito libre, presentado físicamente ante la Unidad de Transparencia de las\nAutoridades Garantes, según corresponda.\nARTÍCULO 76.- Las Autoridades Garantes pondrán a disposición de las personas particulares el formato de denuncia correspondiente, a efecto de que estas, si así lo deciden, puedan utilizarlo. Asimismo, las personas particulares podrán optar por un escrito libre, conforme a lo previsto en esta Ley.\nARTÍCULO 77.- Las Autoridades Garantes, en el ámbito de sus competencias, deben resolver sobre la admisión de la denuncia, dentro de los tres días siguientes a su recepción.\nARTÍCULO 78.- Las Autoridades Garantes podrán prevenir a la persona denunciante dentro del plazo de tres días contados a partir del día hábil siguiente al de su recepción, para que en el plazo de tres días subsane lo siguiente:\nI. En su caso, exhiba ante la Autoridad Garante los documentos con los que acredite la personalidad del representante de una persona física o moral, en caso de aplicar; o,\nII. Aclare o precise alguno de los requisitos o motivos de la denuncia.\nEn el caso de que no se desahogue la prevención en el periodo establecido para tal efecto en este artículo, deberá desecharse la denuncia, dejando a salvo los derechos de la persona denunciante para volver a presentar la misma.\nARTÍCULO 79.- Las Autoridades Garantes podrán determinar la improcedencia de la denuncia cuando el incumplimiento hubiera sido objeto de una denuncia anterior en la que se resolvió instruir la publicación de las obligaciones de transparencia previstas en la presente Ley.\nARTÍCULO 80.- Si la denuncia no versa sobre presuntos incumplimientos a las obligaciones de transparencia establecidas en la presente Ley, o se refiere al ejercicio del derecho de acceso a la información o al trámite del recurso de revisión, la Autoridad Garante dictará un acuerdo de desechamiento y, en su caso, dejará a salvo los derechos de la persona promovente para que los haga valer por la vía y forma correspondientes.\nLas Autoridades Garantes, en el ámbito de sus competencias, deben notificar al sujeto obligado la denuncia dentro de los siete días siguientes a su admisión.\nARTÍCULO 81.- El sujeto obligado deberá enviar a las Autoridades Garantes correspondientes, un informe con justificación respecto de los hechos o motivos de la denuncia dentro de los cinco días siguientes a la notificación respectiva.\nLas Autoridades Garantes, pueden realizar las verificaciones virtuales que procedan, así como solicitar los informes complementarios al sujeto obligado que requiera, para allegarse de los elementos de juicio que considere necesarios para resolver la denuncia.\n.\nActualización Legislativa.\nEn el caso de informes complementarios, el sujeto obligado deberá responder a los mismos, en el término de tres días siguientes a la notificación correspondiente.\nARTÍCULO 82.- Las Autoridades Garantes, en el ámbito de sus competencias deben resolver la denuncia, dentro de los veinte días siguientes al término del plazo en que el sujeto obligado debe presentar su informe o, en su caso, los informes complementarios.\nLa resolución debe ser fundada y motivada e invariablemente debe pronunciarse sobre cumplimiento de la publicación de la información por parte del sujeto obligado.\nDe existir incumplimiento, se deberá señalar el artículo y fracción de la presente Ley, así como los preceptos contenidos en las disposiciones jurídicas aplicables que se incumplen, especificar los criterios y metodología del estudio y las razones por las cuales se considera que hay un incumplimiento, y establecer las medidas necesarias para garantizar la publicidad de la información respecto de la cual exista un incumplimiento, determinando así un plazo para que el sujeto obligado cumpla e informe sobre ello.\nARTÍCULO 83.- Las Autoridades Garantes, en el ámbito de sus competencias, deben notificar la resolución a la persona denunciante y al sujeto obligado, dentro de los tres días siguientes a su emisión.\nLas resoluciones que emitan las Autoridades Garantes, a que se refiere este capítulo, son definitivas e inatacables para los sujetos obligados. Las personas particulares podrán impugnar la resolución en los términos establecidos en la Ley General de Transparencia y\nAcceso a la Información Pública.\nEl sujeto obligado deberá cumplir con la resolución en un plazo de quince días, a partir del día siguiente en el que se le notifique la misma.\nARTÍCULO 84.- Transcurrido el plazo señalado en el artículo anterior, el sujeto obligado deberá informar a la Autoridad Garante correspondiente sobre el cumplimiento de la resolución.\nLas Autoridades Garantes verificarán el cumplimiento a la resolución; si fuera procedente se emitirá un acuerdo de cumplimiento y se ordenará el cierre del expediente.\nCuando las Autoridades Garantes consideren que existe un incumplimiento total o parcial de la resolución, le notificarán, por conducto de la Unidad de Transparencia del sujeto obligado, al superior jerárquico del servidor público responsable de dar cumplimiento, para el efecto de que, en un plazo no mayor a siete días, se dé cumplimiento a la resolución.\nARTÍCULO 85.- En caso de que las Autoridades Garantes consideren que subsiste el incumplimiento total o parcial de la resolución, en un plazo no mayor a cinco días posteriores al aviso de incumplimiento al superior jerárquico del servidor público responsable del mismo, se emitirá un acuerdo de incumplimiento y, en su caso, se impondrán las medidas de apremio o determinaciones que resulten procedentes.\n.\nActualización Legislativa.\nTÍTULO QUINTO\nINFORMACIÓN CLASIFICADA\nCapítulo I\nDe las Disposiciones Generales de la Clasificación y\nDesclasificación de la Información\nARTÍCULO 86.- La clasificación es el proceso mediante el cual el sujeto obligado determina que la información en su poder, actualiza alguno de los supuestos de reserva o de confidencialidad, de conformidad con lo dispuesto en el presente Título.\nLas personas titulares de las áreas de los sujetos obligados serán los responsables de clasificar la información, de conformidad con lo dispuesto en la presente Ley y la Ley\nGeneral.\nLos sujetos obligados deberán aplicar, de manera restrictiva y limitada, las excepciones al derecho de acceso a la información previstas en el presente Título y deberán acreditar su procedencia, sin ampliar las excepciones o supuestos de reserva o confidencialidad previstos en las leyes, de conformidad con lo establecido en esta Ley.\nLos sujetos obligados no podrán emitir acuerdos de carácter general ni particular que clasifiquen documentos o expedientes como reservados, ni clasificar documentos antes de dar respuesta a una solicitud de acceso a la información. La clasificación podrá establecerse de manera parcial o total de acuerdo al contenido de la información del documento y deberá estar acorde con la actualización de los supuestos definidos en el presente Título como información clasificada.\nLa clasificación de información reservada se realizará conforme a un análisis caso por caso, mediante la aplicación de la prueba de daño.\nARTÍCULO 87.- La clasificación de la información se llevará a cabo en el momento en que:\nI. Se reciba una solicitud de acceso a la Información;\nII. Se determine mediante resolución de autoridad competente; o,\nIII. Se generen versiones públicas para dar cumplimiento a las obligaciones de transparencia previstas en esta Ley.\nARTÍCULO 88.- Los documentos clasificados como reservados serán públicos cuando:\nI. Se extingan las causas que dieron origen a su clasificación;\nII. Expire el plazo de clasificación;\n.\nActualización Legislativa.\nIII. Exista resolución de una autoridad competente que determine que existe una causa de interés público que prevalece sobre la reserva de la información;\nIV. El Comité de Transparencia considere pertinente la desclasificación, de conformidad con lo señalado en el presente Título;\nV. Se trate de información que esté relacionada con violaciones graves a derechos humanos o delitos de lesa humanidad.\nLa información clasificada como reservada de conformidad con el artículo 96 de esta\nLey, podrá permanecer con tal carácter hasta por un periodo de cinco años. El periodo de reserva correrá a partir de la fecha en que se clasifica el documento.\nExcepcionalmente, los sujetos obligados, con la aprobación de su Comité de\nTransparencia, podrán ampliar el periodo de reserva hasta por un plazo de cinco años adicionales, siempre y cuando justifiquen que subsisten las causas que dieron origen a su clasificación, mediante la aplicación de una prueba de daño.\nPara los casos previstos por la fracción II de este artículo, cuando se trate de información cuya publicación pueda ocasionar Ia destrucción o inhabilitación de la infraestructura de carácter estratégico para la provisión de bienes o servicios públicos, o bien se refiera a las circunstancias expuestas en la fracción IV del artículo 96 de esta Ley y que a juicio de un sujeto obligado sea necesario ampliar nuevamente el periodo de reserva de la información, el Comité de Transparencia respectivo deberá hacer la solicitud correspondiente a la Autoridad Garante, debidamente fundada y motivada, aplicando la prueba de daño y señalando el plazo de reserva, por lo menos con tres meses de anticipación al vencimiento del periodo.\nARTÍCULO 89.- Cada área del sujeto obligado elaborará un índice de los expedientes clasificados como reservados, por área responsable de la información y tema.\nEl índice deberá elaborarse semestralmente y publicarse en Formatos Abiertos al día siguiente de su elaboración. Dicho índice deberá indicar el área que generó la información, el nombre del documento, si se trata de una reserva completa o parcial, la fecha en que inicia y finaliza la reserva, su justificación, el plazo de reserva y, en su caso, las partes del documento que se reservan y si se encuentra en prórroga.\nEn ningún caso el índice será considerado como información reservada.\nARTÍCULO 90.- En los casos en que se niegue el acceso a la información, por actualizarse alguno de los supuestos de clasificación, el Comité de Transparencia deberá confirmar, modificar o revocar la decisión.\nPara motivar la clasificación de la información y la ampliación del plazo de reserva, se deberán señalar las razones, motivos o circunstancias especiales que llevaron al sujeto\n.\nActualización Legislativa. invocada como fundamento. Además, el sujeto obligado deberá, en todo momento, aplicar una prueba de daño.\nTratándose de aquella información que actualice los supuestos de clasificación, deberá señalarse el plazo al que estará sujeta la reserva.\nARTÍCULO 91.- En la aplicación de la prueba de daño, el sujeto obligado deberá justificar que:\nI. La divulgación de la información representa un riesgo real, demostrable e identificable de perjuicio significativo al interés público o a la seguridad nacional;\nII. El riesgo de perjuicio que supondría la divulgación supera el interés público general de que se difunda; y,\nIII. La limitación se adecua al principio de proporcionalidad y representa el medio menos restrictivo disponible para evitar el perjuicio.\nARTÍCULO 92.- Los sujetos obligados deberán aplicar, de manera restrictiva y limitada, las excepciones al derecho de acceso a la información previstas en el presente\nTítulo y deberán acreditar su procedencia.\nLa carga de la prueba para justificar toda negativa de acceso a la información, por actualizarse cualquiera de los supuestos de reserva previstos, corresponderá a los sujetos obligados.\nARTÍCULO 93.- Los documentos clasificados parcial o totalmente deberán llevar una leyenda que indique tal carácter, la fecha de la clasificación, el fundamento legal y, en su caso, el periodo de reserva.\nARTÍCULO 94.- Los sujetos obligados deberán observar los lineamientos generales que emita el Sistema Nacional en materia de clasificación de la información reservada y confidencial y, para la elaboración de versiones públicas.\nARTÍCULO 95.- Los documentos clasificados serán debidamente custodiados y conservados, conforme a las disposiciones aplicables y, en su caso, a los lineamientos que expida el Sistema Nacional.\nCapítulo II\nDe la Información Reservada\nARTÍCULO 96.- Como información reservada podrá clasificarse aquella cuya publicación:\nI. Comprometa la seguridad pública o la paz social;\n.\nActualización Legislativa.\nII. Pueda menoscabar la conducción de las negociaciones y relaciones internacionales del Estado de Baja California o alguno de sus municipios;\nIII. Se entregue al Estado de Baja California o algunos de sus municipios expresamente con ese carácter o el de confidencial por otro u otros sujetos de derecho internacional, excepto cuando se trate de violaciones graves de derechos humanos o delitos de lesa humanidad de conformidad con el derecho internacional;\nIV. Pueda incrementar el costo de operaciones financieras que realicen los sujetos obligados del sector público estatal;\nV. Pueda poner en riesgo la vida, seguridad o salud de una persona física;\nVI. Obstruya las actividades de verificación, inspección y auditoría relativas al cumplimiento de las leyes o afecte la recaudación de contribuciones;\nVII. Pueda causar daño u obstruya la prevención o persecución de los delitos, altere el proceso de investigación de las carpetas de investigación, afecte o vulnere la conducción o los derechos del debido proceso en tanto no hayan quedado firmes o afecte la administración de justicia o la seguridad de una persona denunciante, querellante o testigo, así como sus familias, en los términos de las disposiciones jurídicas aplicables;\nVIII. La que contenga las opiniones, recomendaciones o puntos de vista que formen parte del proceso deliberativo de las personas servidoras públicas, hasta en tanto no sea adoptada la decisión definitiva, la cual deberá estar documentada;\nIX. Obstruya los procedimientos para fincar responsabilidad a las personas servidoras públicas, en tanto la resolución administrativa no haya causado estado;\nX. Afecte los derechos del debido proceso;\nXI. Afecte o vulnere la conducción de los expedientes judiciales o de los procedimientos administrativos seguidos en forma de juicio, incluidos los de denuncias, inconformidades, responsabilidades administrativas y resarcitorias o afecte la administración de justicia o la seguridad de una persona denunciante, querellante o testigo, así como sus familias, en los términos de las disposiciones jurídicas aplicables en tanto no hayan causado estado;\nXII. Se encuentre contenida dentro de las investigaciones de hechos que la ley señale como delitos y se tramiten ante el Ministerio Público;\nXIII. El daño que pueda producirse con la publicación de la información sea mayor que el interés público de conocer la información de referencia, siempre que esté hayan quedado firmes;\n.\nActualización Legislativa.\nXIV. Cuando se trate de información sobre estudios y proyectos cuya divulgación pueda causar daños al interés del Estado o suponga un riesgo para su realización, siempre que esté directamente relacionado con procesos o procedimientos administrativos o judiciales que no hayan quedado firmes;\nXV. Ponga en riesgo el funcionamiento o integridad de los sistemas tecnológicos, de telecomunicaciones o de defensa desarrollados, adquiridos u operados por el Gobierno del\nEstado de forma directa o indirecta, así como instalaciones, infraestructuras, proyectos, planes o servicios de protección estratégicos, prioritarios o de defensa; y,\nXVI. Las que por disposición expresa de una ley tengan tal carácter, siempre que sean acordes con las bases, principios y disposiciones establecidos en esta Ley y no la contravengan; así como las previstas en tratados internacionales.\nARTÍCULO 97.- Las causales de reserva previstas en el artículo anterior se deberán fundar y motivar, a través de la aplicación de la prueba de daño a la que se hace referencia en el presente Título.\nARTÍCULO 98.- No podrá invocarse el carácter de reservado cuando:\nI. Se trate de violaciones graves de derechos humanos o delitos de lesa humanidad; o,\nII. Se trate de información relacionada con actos de corrupción acreditados de acuerdo con las leyes aplicables.\nCapítulo III\nDe la Información Confidencial\nARTÍCULO 99.- Se considera información confidencial la que contiene datos personales concernientes a una persona física identificada o identificable. La información confidencial no estará sujeta a temporalidad alguna y sólo podrán tener acceso a ella los titulares de la misma, sus representantes y las personas servidoras públicas facultadas para ello.\nSe considera como información confidencial de personas físicas o morales los secretos bancario, fiduciario, industrial, comercial, fiscal, bursátil y postal, cuya titularidad obligados cuando no involucren el ejercicio de recursos públicos.\nAsimismo, será información confidencial aquella que presenten las personas particulares a los sujetos obligados, siempre que tengan el derecho a ello, de conformidad con lo dispuesto por las leyes o los tratados internacionales. quejas, denuncias y/o procedimientos administrativos seguidos en contra de personas\n.\nActualización Legislativa. servidoras públicas y particulares que se encuentren en trámite o no hayan concluido con una sanción firme.\nARTÍCULO 100.- Los sujetos obligados que se constituyan como fideicomitentes, fideicomisarios o fiduciarios en fideicomisos que involucren recursos públicos, no podrán clasificar, por ese solo supuesto, la información relativa al ejercicio de estos, como secreto bancario o fiduciario, sin perjuicio de las demás causales de clasificación que prevé la presente Ley.\nARTÍCULO 101.- Los sujetos obligados que se constituyan como personas usuarias o como institución bancaria en operaciones que involucren recursos públicos, no podrán clasificar, por ese solo supuesto, la información relativa al ejercicio de estos, como secreto bancario, sin perjuicio de las demás causales de clasificación que prevé la presente Ley.\nARTÍCULO 102.- Los sujetos obligados que se constituyan como contribuyentes o como autoridades estatales o municipales en materia tributaria, no podrán clasificar la información relativa al ejercicio de recursos públicos como secreto fiscal.\nARTÍCULO 103.- Para que los sujetos obligados puedan permitir el acceso a información confidencial requieren obtener el consentimiento de las personas particulares titulares de la información. No se requerirá el consentimiento del titular de la información confidencial cuando:\nI. La información se encuentre en registros públicos o fuentes de acceso público;\nII. Por ley tenga el carácter de pública;\nIII. Exista una orden judicial;\nIV. Por razones de seguridad pública y salubridad general, o para proteger los derechos de terceros, se requiera su publicación; o,\nV. Cuando se transmita entre sujetos obligados y entre estos y los sujetos de derecho internacional, en términos de los tratados y los acuerdos interinstitucionales, siempre y cuando la información se utilice para el ejercicio de facultades propias de los mismos.\nPara efectos de la fracción IV del presente artículo, la Autoridad Garante, debidamente fundada y motivada, deberá aplicar la prueba de interés público; además, se divulgación de la información confidencial y el interés público de la información.\nCapítulo IV\nDe las Versiones Públicas\nARTÍCULO 104.- Cuando un documento o expediente contenga partes o secciones reservadas o confidenciales, los sujetos obligados a través de sus áreas, para efectos de\n.\nActualización Legislativa. atender una solicitud de información, deberán elaborar una versión pública en la que se testen las partes o secciones clasificadas, indicando su contenido de manera genérica, fundando y motivando su clasificación, en términos de lo que determine el Sistema Nacional.\nARTÍCULO 105.- Los sujetos obligados deberán procurar que los sistemas o medios empleados para eliminar la información en las versiones públicas no permitan la recuperación o visualización de la misma.\nARTÍCULO 106.- En las versiones públicas no podrá omitirse la información que constituya obligaciones de transparencia previstas en la presente Ley.\nTÍTULO SEXTO\nPROCEDIMIENTOS DE ACCESO A LA INFORMACIÓN PÚBLICA\nCapítulo I\nDel Procedimiento de Acceso a la Información\nARTÍCULO 107.- Las Unidades de Transparencia de los sujetos obligados deberán garantizar las medidas y condiciones de accesibilidad para que toda persona pueda ejercer el derecho de acceso a la información mediante solicitudes de información y deberá apoyar a la persona solicitante en la elaboración de las mismas, de conformidad con las bases establecidas en el presente Título.\nARTÍCULO 108.- Cualquier persona por sí misma o a través de su representante, podrá presentar solicitud de acceso a información ante la Unidad de Transparencia, a través de la Plataforma Nacional, en la oficina u oficinas designadas para ello, vía correo electrónico, correo postal, mensajería, telégrafo, verbalmente o cualquier medio aprobado por el Sistema Nacional.\nARTÍCULO 109.- Tratándose de solicitudes de acceso a información formuladas mediante la Plataforma Nacional, esta asignará automáticamente un número de folio, con el que las personas solicitantes podrán dar seguimiento a sus requerimientos, en los términos de la Ley General. En los demás casos, la Unidad de Transparencia tendrá que registrar y capturar la solicitud de acceso en la Plataforma Nacional dentro de los cinco días posteriores a su recepción, y deberá enviar el acuse de recibo a la persona solicitante, en el que se indique la fecha de recepción, el folio que corresponda y los plazos de respuesta aplicables.\nARTÍCULO 110.- Para presentar una solicitud no se podrán exigir mayores requisitos que los siguientes:\nI. Medio para recibir notificaciones;\nII. La descripción de la información solicitada; y,\nIII. La modalidad en la que prefiera se otorgue el acceso a la información, la cual podrá ser verbal, siempre y cuando sea para fines de orientación, mediante consulta directa,.\nActualización Legislativa. mediante la expedición de copias simples o certificadas o la reproducción en cualquier otro medio, incluidos los electrónicos.\nEn su caso, la persona solicitante señalará el formato accesible o la lengua indígena en la que se requiera la información de acuerdo a lo señalado en la presente Ley.\nARTÍCULO 111.- Cuando el particular presente su solicitud por medios electrónicos a través de la Plataforma Nacional, se entenderá que acepta que las notificaciones le sean efectuadas por dicho sistema, salvo que señale un medio distinto para efectos de las notificaciones.\nLas respuestas que otorguen las Unidades de Transparencia a través de la\nPlataforma Nacional, se consideran válidas, aun cuando no cuenten con firma autógrafa.\nEn el caso de solicitudes recibidas en otros medios, en las que las personas solicitantes no proporcionen un domicilio o medio para recibir la información o, en su defecto, no haya sido posible practicar la notificación, se notificará por estrados en la oficina de la\nUnidad de Transparencia.\nARTÍCULO 112.- Los términos de todas las notificaciones previstas en esta Ley, empezarán a correr al día siguiente al que se practiquen.\nCuando los plazos fijados por esta Ley sean en días, estos se entenderán como hábiles.\nARTÍCULO 113.- De manera excepcional, cuando, de forma fundada y motivada, así lo determine el sujeto obligado, en aquellos casos en que la información solicitada que ya se encuentre en su posesión implique análisis, estudio o procesamiento de documentos cuya entrega o reproducción sobrepase las capacidades técnicas del sujeto obligado para cumplir con la solicitud, en los plazos establecidos para dichos efectos, se podrán poner a disposición de la persona solicitante los documentos en consulta directa, salvo la información clasificada.\nEn todo caso se facilitará su copia simple o certificada, así como su reproducción por cualquier medio disponible en las instalaciones del sujeto obligado previo pago de derechos o que, en su caso, aporte la persona solicitante.\nARTÍCULO 114.- Cuando los detalles proporcionados en la solicitud de acceso a información resulten insuficientes, incompletos o sean erróneos, para localizar la información solicitada, la Unidad de Transparencia podrá requerir a la persona solicitante, por una sola vez y dentro de un plazo que no podrá exceder de cinco días, contados a partir de la presentación de la solicitud, para que, en un término de hasta diez días, indique otros elementos o corrija los datos proporcionados.\nEste requerimiento interrumpirá el plazo de respuesta establecido en el artículo 118 de la presente Ley, por lo que comenzará a computarse nuevamente al día siguiente del\n.\nActualización Legislativa. desahogo por parte del particular. En este caso, el sujeto obligado atenderá la solicitud en los términos en que fue desahogado el requerimiento de información adicional.\nLa solicitud se tendrá por no presentada cuando las personas solicitantes no atiendan el requerimiento de información adicional. En el caso de requerimientos parciales no desahogados, se tendrá por presentada la solicitud por lo que respecta a los contenidos de información que no formaron parte del requerimiento.\nARTÍCULO 115.- Los sujetos obligados deberán otorgar los documentos que se encuentren en sus archivos o que estén obligados a documentar de acuerdo con sus facultades, competencias o funciones, conforme a las características físicas o electrónicas de la información con la que cuenten o del lugar donde se encuentre, sin necesidad de elaborar documentos adicionales para atender las solicitudes de acceso a información.\nTratándose de solicitudes de acceso a información cuyo contenido constituya una consulta, el sujeto obligado podrá dar una interpretación para verificar si dentro de los documentos con los que cuentan atendiendo a las características señaladas en el párrafo anterior puede darse atención, sin que se entienda que debe emitir pronunciamientos específicos, explicaciones y/o argumentaciones sobre supuestos hipotéticos.\nEn el caso de que la información solicitada consista en bases de datos se deberá privilegiar la entrega de la misma en formatos abiertos.\nARTÍCULO 116.- Cuando la información requerida por la persona solicitante ya esté disponible al público en medios impresos, tales como libros, compendios, trípticos, registros públicos, en formatos electrónicos disponibles en internet o en cualquier otro medio, se le hará saber por el medio requerido por la persona solicitante la fuente, el lugar y la forma en que puede consultar, reproducir o adquirir dicha información en un plazo no mayor a cinco días.\nARTÍCULO 117.- Las Unidades de Transparencia deberán garantizar que las solicitudes se turnen a todas las áreas competentes que cuenten con la información o deban tenerla de acuerdo a sus facultades, competencias y funciones, con el objeto de que realicen una búsqueda exhaustiva y razonable de la información solicitada.\nARTÍCULO 118.- La respuesta a la solicitud deberá ser notificada a la persona interesada en el menor tiempo posible, que no podrá exceder de veinte días, contados a partir del día siguiente a la presentación de aquella.\nExcepcionalmente, el plazo referido en el párrafo anterior podrá ampliarse hasta por diez días más, siempre y cuando se justifiquen de manera fundada y motivada las razones ante el Comité de Transparencia, y este emita la resolución respectiva, la cual deberá notificarse a la persona solicitante antes de su vencimiento.\nARTÍCULO 119.- El acceso se dará en la modalidad de entrega y, en su caso, de envío elegidos por la persona solicitante. Cuando la información no pueda entregarse o enviarse en la modalidad elegida, el sujeto obligado deberá justificar el impedimento, y\n.\nActualización Legislativa. notificar al particular la disposición de la información en todas las modalidades que permita el documento de que se trate, procurando reducir, en todo momento, los costos de entrega.\nARTÍCULO 120.- Los sujetos obligados establecerán la forma y términos en que darán trámite interno a las solicitudes en materia de acceso a la información.\nLa elaboración de versiones públicas, cuya modalidad de reproducción o envío tenga un costo, procederá una vez que se acredite el pago respectivo.\nAnte la falta de respuesta a una solicitud en el plazo previsto y en caso de que proceda el acceso, los costos de reproducción y envío correrán a cargo del sujeto obligado.\nARTÍCULO 121.- La Unidad de Transparencia tendrá disponible la información solicitada, durante un plazo mínimo de sesenta días, contado a partir de que la persona solicitante hubiere realizado, en su caso, el pago respectivo, el cual deberá efectuarse en un plazo no mayor a treinta días.\nTranscurridos dichos plazos, los sujetos obligados darán por concluida la solicitud y procederán, de ser el caso, a la destrucción del material en el que se reprodujo la información. Serán aplicables estas mismas disposiciones, en el cumplimiento a los recursos de revisión.\nARTÍCULO 122.- Cuando las Unidades de Transparencia determinen la notoria incompetencia por parte de los sujetos obligados, dentro del ámbito de su aplicación, para atender la solicitud de acceso a la información, deberán comunicarlo a la persona solicitante, dentro de los tres días posteriores a la recepción de la solicitud y, en caso de poderlo determinar, señalar a la persona solicitante el o los sujetos obligados competentes.\nSi los sujetos obligados son competentes para atender parcialmente la solicitud de acceso a la información, deberán dar respuesta respecto de dicha parte.\nARTÍCULO 123.- En caso de que los sujetos obligados consideren que la información deba ser clasificada, se sujetará a lo siguiente:\nEl área deberá remitir la solicitud, así como un escrito en el que funde y motive la clasificación al Comité de Transparencia, mismo que deberá resolver para:\nI. Confirmar la clasificación;\nII. Modificar la clasificación y otorgar total o parcialmente el acceso a la información; y,\nIII. Revocar la clasificación y conceder el acceso a la información. del área correspondiente, de la cual se haya solicitado su clasificación. el plazo de respuesta a la solicitud que establece el artículo 118 de la presente Ley.\n.\nActualización Legislativa.\nARTÍCULO 124.- Cuando la información no se encuentre en los archivos del sujeto obligado, el Comité de Transparencia:\nI. Analizará el caso y tomará las medidas necesarias para localizar la información;\nII. Expedirá una resolución que confirme la inexistencia del documento;\nIII. Ordenará, a través de la Unidad de Transparencia, que se exponga, de forma fundada y motivada, las razones por las cuales en el caso particular no cuenta con la información, lo cual notificará a la persona solicitante; y,\nIV. En su caso, notificará al órgano interno de control o equivalente del sujeto obligado.\nARTÍCULO 125.- La resolución del Comité de Transparencia que confirme la inexistencia de la información solicitada contendrá los elementos mínimos que permitan a la persona solicitante tener la certeza de que se utilizó un criterio de búsqueda exhaustivo, además de señalar las circunstancias de tiempo, modo y lugar que generaron la inexistencia.\nEn aquellos casos en que no se advierta obligación o competencia alguna de los sujetos obligados para contar con la información, derivado del análisis a las disposiciones jurídicas aplicables a la materia de la solicitud, además no se tengan elementos de convicción que permitan suponer que esta debe obrar en sus archivos, o bien, se cuente con atribuciones, pero no se ha generado la información no será necesario que el Comité de\nTransparencia emita una resolución que confirme la inexistencia de la misma.\nCuando se requiera un dato estadístico o numérico, y el resultado de la búsqueda de la información sea cero, este deberá entenderse como un dato que constituye un elemento numérico que atiende la solicitud, y no como la inexistencia de la información solicitada.\nARTÍCULO 126.- Las personas físicas y morales que reciban y ejerzan recursos públicos o realicen actos de autoridad serán responsables del cumplimiento de los plazos y términos para otorgar acceso a la información.\nCapítulo II\nDe las Cuotas de Acceso\nARTÍCULO 127.- En caso de existir costos para obtener la información, deberán cubrirse de manera previa a la entrega y no podrán ser superiores a la suma de:\nI. El costo de los materiales utilizados en la reproducción de la información;\nII. El costo de envío, en su caso; y,\nIII. El pago de la certificación de los documentos, cuando proceda.\n.\nActualización Legislativa.\nLas cuotas correspondientes deberán establecerse en la Ley de Ingresos del Estado de Baja California y en las Leyes de Ingresos de los municipios respectivos, según el ejercicio fiscal aplicable, y deberán publicarse en los sitios de internet de los sujetos obligados. En su determinación se deberá considerar que los montos permitan o faciliten el ejercicio del derecho de acceso a la información, asimismo, se establecerá la obligación de fijar una cuenta bancaria única y exclusivamente para que la persona solicitante realice el pago íntegro del costo de la información que solicitó.\nLa información deberá ser entregada sin costo, cuando implique la entrega de no más de veinte hojas simples. Las Unidades de Transparencia podrán exceptuar el pago de reproducción y envío atendiendo a las circunstancias socioeconómicas de la persona solicitante.\nTÍTULO SÉPTIMO\nDE LOS PROCEDIMIENTOS DE IMPUGNACIÓN\nCapítulo I\nDel Recurso de Revisión\nARTÍCULO 128.- La persona solicitante podrá interponer, por sí mismo o por conducto de su representante, de manera física o por medios electrónicos, recurso de revisión ante la Autoridad Garante que corresponda, o ante la Unidad de Transparencia que haya conocido de la solicitud dentro de los quince días siguientes a la fecha de la notificación de la respuesta, o del vencimiento del plazo para su notificación.\nEn el caso de que se interponga ante la Unidad de Transparencia, esta deberá remitir el recurso de revisión a la Autoridad Garante que corresponda a más tardar al día siguiente de haberlo recibido.\nPara el caso de personas que posean algún tipo de discapacidad que les dificulte una comunicación clara y precisa o de personas que sean hablantes de lengua indígena, se procurará proporcionarles gratuitamente un traductor o intérprete.\nAsimismo, cuando el recurso sea presentado por una persona con discapacidad ante la Unidad de Transparencia, dicha circunstancia deberá ser notificada a la Autoridad\nGarante, para que determine mediante acuerdo los ajustes razonables que garanticen la tutela efectiva del derecho de acceso a la información.\nARTÍCULO 129.- El recurso de revisión procede en contra de:\nI. La clasificación de la información;\nII. La declaración de inexistencia de información;\nIII. La declaración de incompetencia por el sujeto obligado;\n.\nActualización Legislativa.\nIV. La entrega de información incompleta;\nV. La entrega de información que no corresponda con lo solicitado;\nVI. La falta de respuesta a una solicitud de acceso a la información dentro de los plazos establecidos en la ley;\nVII. La notificación, entrega o puesta a disposición de información en una modalidad o formato distinto al solicitado;\nVIII. La entrega o puesta a disposición de información en un formato incomprensible y/o no accesible para la persona solicitante;\nIX. Los costos o tiempos de entrega de la información;\nX. La falta de trámite a una solicitud;\nXI. La negativa a permitir la consulta directa de la información;\nXII. La falta, deficiencia o insuficiencia de la fundamentación y/o motivación en la respuesta; o,\nXIII. La orientación a un trámite específico.\nLa respuesta que den los sujetos obligados derivada de la resolución al recurso de revisión que proceda por las causales señaladas en las fracciones III, VI, VIII, IX, X y XI de este artículo, es susceptible de ser impugnada de nueva cuenta, mediante recurso de revisión, ante la Autoridad Garante correspondiente.\nARTÍCULO 130.- El recurso de revisión debe contener:\nI. El sujeto obligado ante el cual se presentó la solicitud;\nII. El nombre de la persona solicitante que recurre o de su representante y, en su caso, de la persona tercera interesada, así como la dirección o medio que señale para recibir notificaciones;\nIII. El número de folio de respuesta de la solicitud de acceso;\nIV. La fecha en que fue notificada la respuesta a la persona solicitante o tuvo conocimiento del acto reclamado, o de presentación de la solicitud, en caso de falta de respuesta;\nV. El acto que se recurre;\nVI. Las razones o motivos de inconformidad; y,.\nActualización Legislativa.\nVII. La copia de la respuesta que se impugna y, en su caso, de la notificación correspondiente, salvo en el caso de respuesta de la solicitud.\nAdicionalmente, se podrán anexar las pruebas y demás elementos que considere procedentes someter a juicio de la Autoridad Garante.\nEn ningún caso será necesario que el particular ratifique el recurso de revisión interpuesto.\nARTÍCULO 131.- Si el escrito de interposición del recurso no cumple con alguno de los requisitos establecidos en el artículo anterior y la Autoridad Garante no cuenta con elementos para subsanarlos, se prevendrá al recurrente, por una sola ocasión y a través del medio que haya elegido para recibir notificaciones, con el objeto de que subsane las omisiones dentro de un plazo que no podrá exceder de cinco días, contados a partir del día siguiente de la notificación de la prevención, con el apercibimiento de que, de no cumplir, se desechará el recurso de revisión.\nLa prevención tendrá el efecto de interrumpir el plazo que tienen las Autoridades\nGarantes para resolver el recurso, por lo que comenzará a computarse a partir del día siguiente a su desahogo.\nEn los casos que no se proporcione un domicilio o medio para recibir notificaciones o, en su defecto, no haya sido posible practicar la notificación, se realizará por estrados en el domicilio de la Autoridad Garante.\nNo podrá prevenirse por el nombre o los datos que proporcione la persona solicitante.\nARTÍCULO 132.- La Autoridad Garante resolverá el recurso de revisión en un plazo que no podrá exceder de cuarenta días, contados a partir de la admisión del mismo, plazo que podrá ampliarse por una sola vez y hasta por un periodo de veinte días. Durante el procedimiento debe aplicarse la suplencia de la queja a favor del recurrente, sin cambiar los hechos expuestos, asegurándose de que las partes puedan presentar, de manera oral o escrita, los argumentos que funden y motiven sus pretensiones.\nARTÍCULO 133.- Cuando en el recurso de revisión se señale como agravio la omisión por parte del sujeto obligado de responder a una solicitud de acceso, y el recurso se resuelva de manera favorable para el recurrente, el sujeto obligado deberá darle acceso a la información en un periodo no mayor a los diez días hábiles; en cuyo caso se hará sin que se requiera del pago correspondiente de derechos por su reproducción, siempre que la resolución esté firme, la entrega sea en el formato requerido originalmente y no se trate de copias certificadas.\nARTÍCULO 134.- En todo momento las Autoridades Garantes deben tener acceso a la información clasificada para determinar su naturaleza según se requiera. El acceso se para el resguardo o salvaguarda de la información.\n.\nActualización Legislativa.\nTratándose de la información a que se refiere el último párrafo del artículo 88 de esta\nLey, los sujetos obligados deberán dar acceso a las Autoridades Garantes a dicha información mediante la exhibición de la documentación relacionada, en las oficinas de los propios sujetos obligados.\nARTÍCULO 135.- La información reservada o confidencial que, en su caso, sea consultada por las Autoridades Garantes por resultar indispensable para resolver el asunto, debe ser mantenida con ese carácter y no debe estar disponible en el expediente, salvo en los casos en los que sobreviniera la desclasificación de dicha información y continuara bajo el resguardo del sujeto obligado en el que originalmente se encontraba o cuando se requiera, por ser violaciones graves a derechos humanos o delitos de lesa humanidad, de conformidad con el derecho nacional y los tratados internacionales de los que el Estado\nMexicano sea parte.\nARTÍCULO 136.- Cuando, al resolver el recurso de revisión exista una colisión de derechos, la Autoridad Garante deberá aplicar una prueba de interés público basada en los principios de idoneidad, necesidad y proporcionalidad. Para estos efectos, se entiende por:\nI. Idoneidad: La legitimidad del derecho adoptado como preferente, que sea el adecuado para el logro de un fin constitucionalmente válido o apto para conseguir el fin pretendido;\nII. Necesidad: La falta de un medio alternativo menos lesivo a la apertura de la información, para satisfacer el interés público; y,\nIII. Proporcionalidad: El equilibrio entre perjuicio y beneficio a favor del interés público, a fin de que la decisión tomada represente un beneficio mayor al perjuicio que podría causar a la población.\nARTÍCULO 137.- Las Autoridades Garantes resolverán el recurso de revisión conforme a lo siguiente:\nI. Interpuesto el recurso de revisión deberán proceder a su análisis para que decrete su admisión o su desechamiento;\nII. Admitido el recurso de revisión deberán integrar un expediente y ponerlo a disposición de las partes, para que, en un plazo máximo de siete días, manifiesten lo que a su derecho convenga. De considerarse improcedente el recurso, deberá desecharse mediante acuerdo fundado y motivado, dentro de un plazo máximo de cinco días contados a intereses convenga, debiendo notificarle dentro de los tres días siguientes a la emisión del acuerdo;\nIII. En caso de existir persona tercera interesada, se le hará la notificación para que en el plazo mencionado en la fracción anterior acredite su carácter, alegue lo que a su derecho convenga y aporte las pruebas que estime pertinentes;\n.\nActualización Legislativa.\nIV. Dentro del plazo mencionado en la fracción II del presente artículo, las partes podrán ofrecer todo tipo de pruebas o alegatos excepto la confesional por parte de los sujetos obligados y aquéllas que sean contrarias a derecho. Se recibirán aquellas pruebas que resulten supervinientes por las partes, mismas que serán tomadas en cuenta, siempre y cuando no se haya dictado la resolución;\nV. Podrán determinar la celebración de audiencias con las partes durante la sustanciación del recurso de revisión;\nVI. Concluido el plazo señalado en la fracción II del presente artículo, procederán a decretar el cierre de instrucción. Asimismo, a solicitud de los sujetos obligados o los recurrentes, los recibirán en audiencia, a efecto de allegarse de mayores elementos de convicción que le permitan valorar los puntos controvertidos objeto del recurso de revisión;\nVII. No estarán obligadas a atender la información remitida por el sujeto obligado una vez decretado el cierre de instrucción; y,\nVIII. Decretado el cierre de instrucción, el expediente pasará a resolución, en un plazo que no podrá exceder de veinte días.\nARTÍCULO 138.- Las resoluciones de las Autoridades Garantes podrán:\nI. Desechar o sobreseer el recurso;\nII. Confirmar la respuesta del sujeto obligado; o,\nIII. Revocar o modificar la respuesta del sujeto obligado.\nLas resoluciones establecerán, en su caso, los plazos y términos para su cumplimiento y los procedimientos para asegurar su ejecución, los cuales no podrán exceder de diez días para la entrega de información. Excepcionalmente, las Autoridades Garantes previa fundamentación y motivación, podrán ampliar estos plazos cuando el asunto así lo requiera.\nARTÍCULO 139.- En las resoluciones las Autoridades Garantes podrán señalarles a los sujetos obligados que la información que deben proporcionar sea considerada como obligación de transparencia de conformidad con el Capítulo II del Título Cuarto, denominado\n“De las Obligaciones de Transparencia Comunes” de la presente Ley, atendiendo a la relevancia de la información, la incidencia de las solicitudes sobre la misma y el sentido reiterativo de las resoluciones.\nARTÍCULO 140.- En sus resoluciones, las Autoridades Garantes podrán observar los criterios de interpretación emitidos por la Autoridad Garante Federal. Asimismo, las obligados, que se establecerán por reiteración al resolver tres casos análogos de manera consecutiva en el mismo sentido, derivados de resoluciones que hayan causado estado.\n.\nActualización Legislativa.\nLos criterios se compondrán de un rubro, un texto y el precedente o precedentes que, en su caso, hayan originado su emisión.\nARTÍCULO 141.- Las Autoridades Garantes deben notificar a las partes y publicar las resoluciones, a más tardar, al tercer día siguiente de su aprobación.\nLos sujetos obligados deben informar a las Autoridades Garantes de que se trate el cumplimiento de sus resoluciones en un plazo no mayor a tres días.\nARTÍCULO 142.- Cuando las Autoridades Garantes determinen durante la sustanciación del recurso de revisión que pudo haberse incurrido en una probable responsabilidad por el incumplimiento a las obligaciones previstas en esta Ley y las demás disposiciones aplicables en la materia, debe hacerlo del conocimiento del órgano interno de control o de la instancia competente para que esta inicie, en su caso, el procedimiento de responsabilidad respectivo.\nARTÍCULO 143.- El recurso será desechado por improcedente cuando:\nI. Sea extemporáneo por haber transcurrido el plazo establecido en el artículo 128 de la presente Ley;\nII. Se esté tramitando ante el Poder Judicial algún recurso o medio de defensa interpuesto por el recurrente;\nIII. No actualice alguno de los supuestos previstos en el artículo 129 de la presente\nLey;\nIV. No se haya desahogado la prevención en los términos establecidos en el artículo\n131 de la presente Ley;\nV. Se impugne la veracidad de la información proporcionada;\nVI. Se trate de una consulta; o,\nVII. El recurrente amplíe su solicitud en el recurso de revisión, únicamente respecto de los nuevos contenidos.\nARTÍCULO 144.- El recurso será sobreseído, en todo o en parte, cuando, una vez admitido, se actualicen alguno de los siguientes supuestos:\nI. El recurrente se desista;\nII. El recurrente fallezca o tratándose de personas morales que se disuelvan;\nIII. El sujeto obligado responsable del acto lo modifique o revoque de tal manera que el recurso de revisión quede sin materia; o,.\nActualización Legislativa.\nIV. Admitido el recurso de revisión, aparezca alguna causal de improcedencia en los términos del presente Capítulo.\nARTÍCULO 145.- Las resoluciones de las Autoridades Garantes son vinculatorias, definitivas e inatacables para los sujetos obligados.\nARTÍCULO 146.- Las personas particulares podrán impugnar las determinaciones o resoluciones de las Autoridades Garantes por la vía del recurso de inconformidad que se señala en el artículo 162 de la Ley General, o ante los jueces y tribunales especializados en materia de transparencia establecidos por el Poder Judicial de la Federación mediante el juicio de amparo.\nEl recurso de inconformidad se presentará y substanciará ante la Autoridad Garante\nFederal respectiva, conforme a lo establecido por los artículos 163 al 183 de la Ley General.\nCapítulo II\nDel Cumplimiento de las Resoluciones\nARTÍCULO 147.- Los sujetos obligados deberán, por medio de sus Unidades de\nTransparencia, dar estricto cumplimiento a las resoluciones de las Autoridades Garantes e informar a estos sobre su cumplimiento.\nExcepcionalmente, considerando las circunstancias especiales del caso, los sujetos obligados podrán solicitar a las Autoridades Garantes, de manera fundada y motivada, una ampliación del plazo para el cumplimiento de la resolución.\nDicha solicitud debe presentarse, a más tardar, dentro de los primeros tres días del plazo otorgado para el cumplimiento, a efecto de que las Autoridades Garantes, resuelvan sobre la procedencia de la misma dentro de los cinco días siguientes. La presentación de esta solicitud suspenderá el plazo para cumplir con la resolución.\nARTÍCULO 148.- Transcurrido el plazo señalado en el artículo anterior, el sujeto obligado deberá informar a la Autoridad Garante sobre el cumplimiento de la resolución y publicar en la Plataforma Nacional la información con la que se atendió a la misma. a Autoridad Garante verificará de oficio la calidad de la información y, a más tardar al día siguiente de recibir el informe, dará vista al recurrente para que, dentro de los cinco días siguientes, manifieste lo que a su derecho convenga. Si dentro del plazo señalado el\nGarante, deberá expresar las causas específicas por las cuales así lo considera.\nARTÍCULO 149.- La Autoridad Garante deberá pronunciarse, en un plazo no mayor a cinco días, sobre todas las causas que el recurrente manifieste, así como del resultado de la verificación realizada. Si la autoridad antes señalada considera que se dio cumplimiento a la resolución, emitirá un acuerdo de cumplimiento y se ordenará el archivo del expediente. En caso contrario, dicha autoridad:\n.\nActualización Legislativa.\nI. Emitirá un acuerdo de incumplimiento;\nII. Notificará al superior jerárquico del responsable de dar cumplimiento, para el efecto de que, en un plazo no mayor a cinco días, se dé cumplimiento a la resolución; y,\nIII. Determinará las medidas de apremio o sanciones, según corresponda, que deberán imponerse o las acciones procedentes que deberán aplicarse, de conformidad con lo señalado en el siguiente Título.\nTÍTULO OCTAVO\nMEDIDAS DE APREMIO Y SANCIONES\nCapítulo I\nDe las Medidas de Apremio\nARTÍCULO 150.- Las Autoridades Garantes, en sus respectivos ámbitos de competencia, podrán imponer a la persona servidora pública encargada de cumplir con la resolución o a la persona física o moral responsable, las siguientes medidas de apremio para asegurar el cumplimiento de sus determinaciones:\nI. Amonestación pública; o,\nII. Multa, de ciento cincuenta hasta mil quinientas veces la Unidad de Medida y\nActualización vigente, al momento en que se cometa el incumplimiento.\nARTÍCULO 151.- Para calificar las medidas de apremio, las Autoridades Garantes deberán considerar:\nI. La gravedad de la falta del sujeto obligado, determinada por elementos tales como el daño causado, los indicios de intencionalidad, la duración del incumplimiento de las determinaciones de las Autoridades Garantes, y la afectación al ejercicio de sus atribuciones;\nII. La condición económica de la persona infractora; y,\nIII. La reincidencia. en las evaluaciones que realicen estas.\nARTÍCULO 152.- En caso de reincidencia, las Autoridades Garantes podrán imponer una multa equivalente hasta el doble de la que se hubiera determinado por las mismas. sancionada, cometa otra del mismo tipo o naturaleza.\n.\nActualización Legislativa.\nEn caso de que el incumplimiento de las determinaciones de las Autoridades\nGarantes implique la presunta comisión de un delito o una de las conductas señaladas en el artículo 156 de esta Ley, la Autoridad Garante respectiva deberá denunciar los hechos ante la autoridad competente.\nLas medidas de apremio de carácter económico no podrán ser cubiertas con recursos públicos.\nARTÍCULO 153.- Si a pesar de la ejecución de las medidas de apremio previstas en el artículo anterior no se cumple con la determinación, se requerirá el cumplimiento a la persona superior jerárquica para que en un plazo de cinco días lo instruya a cumplir sin demora. De persistir el incumplimiento, se aplicarán sobre la persona superior jerárquica las medidas de apremio establecidas en el artículo anterior.\nTranscurrido el plazo, sin que se haya dado cumplimiento, en su caso, determinará las sanciones que correspondan.\nARTÍCULO 154.- Las medidas de apremio a que se refiere el presente Capítulo, deberán ser impuestas por Autoridades Garantes y ejecutadas por sí mismo o con la intervención de la autoridad competente, de conformidad con los procedimientos que establezcan las disposiciones jurídicas aplicables, dentro de un plazo máximo de quince días, contados a partir de que sea notificada la medida de apremio a la persona infractora.\nLas multas que fijen las Autoridades Garantes se harán efectivas por conducto de la\nSecretaría de Hacienda u homólogos en sus respectivos poderes y ámbitos de competencia, a través del procedimiento que las leyes aplicables establezcan.\nARTÍCULO 155.- Será supletorio a los mecanismos de notificación y ejecución de medidas de apremio, lo dispuesto en la Ley del Procedimiento para los Actos de la\nAdministración Pública del Estado de Baja California.\nCapítulo II\nDe las causales de incumplimiento y las sanciones\nARTÍCULO 156.- Serán causas de sanción por incumplimiento de las obligaciones establecidas en la materia de la presente Ley, las siguientes:\nI. La falta de respuesta a las solicitudes de información en los plazos señalados en las disposiciones jurídicas aplicables;\nII. Actuar con negligencia, dolo o mala fe durante la sustanciación de las solicitudes en materia de acceso a la información o bien, al no difundir la información relativa a las obligaciones de transparencia previstas en la presente Ley;\nIII. Incumplir los plazos de atención previstos en la presente Ley;\n.\nActualización Legislativa.\nIV. Usar, sustraer, divulgar, ocultar, alterar, mutilar, destruir o inutilizar, total o parcialmente, sin causa legítima, conforme a las facultades correspondientes, la información que se encuentre bajo la custodia de los sujetos obligados y de sus personas servidoras públicas o a la cual tengan acceso o conocimiento con motivo de su empleo, cargo o comisión;\nV. Entregar información incomprensible, incompleta, en un formato no accesible, una modalidad de envío o de entrega diferente a la solicitada previamente por personas usuarias en su solicitud de acceso a la información, al responder sin la debida motivación y fundamentación establecidas en esta Ley;\nVI. No actualizar la información correspondiente a las obligaciones de transparencia en los plazos previstos en la presente Ley;\nVII. Declarar con dolo o negligencia la inexistencia de información cuando el sujeto obligado deba generarla, derivado del ejercicio de sus facultades, competencias o funciones;\nVIII. Declarar la inexistencia de la información cuando exista total o parcialmente en sus archivos;\nIX. No documentar con dolo o negligencia, el ejercicio de sus facultades, competencias, funciones o actos de autoridad, de conformidad con las disposiciones jurídicas aplicables;\nX. Realizar actos para intimidar a las personas solicitantes de información o inhibir el ejercicio del derecho;\nXI. Denegar intencionalmente información que no se encuentre clasificada como reservada o confidencial;\nXII. Clasificar como reservada, con dolo o negligencia, la información sin que se cumplan las características señaladas en la presente Ley. La sanción procederá cuando exista una resolución previa de las Autoridades Garantes, que haya quedado firme;\nXIII. No desclasificar la información como reservada cuando los motivos que le dieron origen ya no existan o haya fenecido el plazo, cuando Autoridades Garantes, determinen\nTransparencia;\nXIV. No atender los requerimientos establecidos en la presente Ley, emitidos por las\nAutoridades Garantes; o,\nXV. No acatar las resoluciones emitidas por las Autoridades Garantes, en ejercicio de sus funciones.\nARTÍCULO 157.- Para determinar el monto de las multas y calificar las sanciones establecidas en el presente Capítulo, la Autoridad Garante deberá considerar:\n.\nActualización Legislativa.\nI. La gravedad de la falta del sujeto obligado, determinada por elementos tales como el daño causado, los indicios de intencionalidad, la duración del incumplimiento de las determinaciones de las Autoridades Garantes, y la afectación al ejercicio de sus atribuciones;\nII. La condición económica de la persona infractora;\nIII. La reincidencia; y,\nIV. En su caso, el cumplimiento espontáneo de las obligaciones que dieron origen al procedimiento sancionatorio, el cual podrá considerarse como atenuante de la sanción a imponerse.\nARTÍCULO 158.- Con independencia del carácter de las personas presuntas infractoras, las Autoridades Garantes para conocer, investigar, remitir documentación y, en su caso, sancionar, prescribirán en un plazo de cinco años a partir del día siguiente en que se hubieran cometido las infracciones o a partir del momento en que hubieren cesado, si fueren de carácter continuo.\nLas sanciones de carácter económico no podrán ser cubiertas con recursos públicos.\nARTÍCULO 159.- Las conductas a que se refiere el artículo 156 serán sancionadas por las Autoridades Garantes, según corresponda y, en su caso, conforme a su competencia darán vista a la autoridad competente para que imponga o ejecute la sanción.\nARTÍCULO 160.- Las responsabilidades que resulten de los procedimientos administrativos correspondientes derivados de la violación a lo dispuesto por el artículo 156 de esta Ley, son independientes de las del orden civil, penal o de cualquier otro tipo que se puedan derivar de los mismos hechos.\nDichas responsabilidades se determinarán, en forma autónoma, a través de los procedimientos previstos en las leyes aplicables y las sanciones que, en su caso, se impongan por las autoridades competentes, también se ejecutarán de manera independiente.\nPara tales efectos, las Autoridades Garantes podrán denunciar ante las autoridades consideren pertinentes, en los términos de las leyes aplicables. reciban y ejerzan recursos públicos o realicen actos de autoridad, las Autoridades Garantes deberán dar vista al órgano interno de control del sujeto obligado relacionado con estos, cuando sean personas servidoras públicas, con el fin de que instrumenten los procedimientos administrativos a que haya lugar.\n.\nActualización Legislativa.\nARTÍCULO 162.- En aquellos casos en que la persona presunta infractora tenga la calidad de persona servidora pública, las Autoridades Garantes deberán remitir a la autoridad competente, junto con la denuncia correspondiente, un expediente en que se contengan todos los elementos que sustenten la presunta responsabilidad administrativa.\nLa autoridad que conozca del asunto deberá informar de la conclusión del procedimiento y, en su caso, de la ejecución de la sanción a la autoridad denunciante.\nARTÍCULO 163.- Cuando se trate de personas presuntas infractoras que no cuenten con la calidad de personas servidoras públicas, las Autoridades Garantes serán las autoridades facultadas para conocer y desahogar el procedimiento sancionatorio conforme a esta Ley, y llevar a cabo las acciones conducentes para la imposición y ejecución de las sanciones.\nARTÍCULO 164.- El procedimiento a que se refiere el artículo anterior dará comienzo con la notificación que efectúe la Autoridad Garante a la persona presunta infractora, sobre los hechos e imputaciones que motivaron el inicio del procedimiento y le otorgará un término de quince días para que rinda pruebas y manifieste por escrito lo que a su derecho convenga. En caso de no hacerlo, la autoridad competente que conozca del procedimiento resolverá de inmediato con los elementos de convicción que disponga.\nLa Autoridad Garante admitirá las pruebas que estime pertinentes y procederá a su desahogo. Una vez desahogadas las pruebas, la Autoridad Garante notificará a la persona presunta infractora el derecho que le asiste para que, de considerarlo necesario, presente sus alegatos dentro de los cinco días siguientes a su notificación.\nUna vez analizadas las pruebas y demás elementos de convicción, la Autoridad\nGarante resolverá, en definitiva, dentro de los treinta días siguientes a la fecha en que inició el procedimiento sancionador. Dicha resolución deberá ser notificada a la persona presunta infractora y, dentro de los diez días siguientes a la notificación, se hará pública la resolución correspondiente.\nCuando haya causa justificada debidamente fundada y motivada, la autoridad que conozca del asunto podrá ampliar el plazo de resolución por una sola vez y hasta por un periodo igual.\nARTÍCULO 165.- En las normas respectivas de las Autoridades Garantes se precisará toda circunstancia relativa a la forma, términos y cumplimiento de los plazos a que se refiere el procedimiento sancionatorio previsto en esta Ley, incluyendo la presentación de pruebas y alegatos, la celebración de audiencias, el cierre de instrucción y la ejecución de sanciones. En todo caso, será supletorio a este procedimiento sancionador lo dispuesto en\nCalifornia.\nARTÍCULO 166.- Las infracciones a lo previsto en la presente Ley por parte de sujetos obligados que no cuenten con la calidad de persona servidora pública, serán sancionadas con:\n.\nActualización Legislativa.\nI. Apercibimiento, por única ocasión, para que el sujeto obligado cumpla su obligación de manera inmediata, en los términos previstos en esta Ley, tratándose de los supuestos previstos en las fracciones I, III, V, VI y X del artículo 156 de esta Ley.\nSi una vez hecho el apercibimiento, no se cumple de manera inmediata con la obligación en los términos previstos en esta Ley, tratándose de los supuestos mencionados en esta fracción, se aplicará multa de ciento cincuenta a doscientos cincuenta veces el valor diario de la Unidad de Medida y Actualización;\nII. Multa de doscientos cincuenta a ochocientas veces el valor diario de la Unidad de\nMedida y Actualización, en los casos previstos en las fracciones II y IV del artículo 156 de esta Ley.\nIII. Multa de ochocientos a mil quinientas veces el valor diario de la Unidad de Medida y Actualización, en los casos previstos en las fracciones VII, VIII, IX, XI, XII, XIII, XIV y XV del artículo 156 de esta Ley.\nSe aplicará multa adicional de hasta cincuenta veces el valor diario de la Unidad de\nMedida y Actualización, por día, a quien persista en las infracciones citadas en las fracciones anteriores.\nARTÍCULO 167.- En caso de que el incumplimiento de las determinaciones de las\nAutoridades Garantes implique la presunta comisión de un delito, estos deberán denunciar los hechos ante la autoridad competente.\nARTÍCULO 168.- Las personas físicas o morales que reciban y ejerzan recursos públicos o ejerzan actos de autoridad deberán proporcionar la información que permita al sujeto obligado que corresponda, cumplir con sus obligaciones de transparencia y para atender las solicitudes de acceso correspondientes.\nTRANSITORIOS\nPRIMERO.- El presente Decreto entrará en vigor a los quince días de su publicación en el\nPeriódico Oficial del Estado.\nSEGUNDO.- Se abroga la Ley de Transparencia y Acceso a la Información Pública para el\nEstado de Baja California, publicada en el Periódico Oficial del Estado No. 21, de fecha 29\nInformación Pública para el Estado de Baja California, publicada en el Periódico Oficial No.\nTERCERO.- Las menciones, atribuciones o funciones contenidas en otras leyes, reglamentos y, en general, en cualquier disposición normativa, respecto al Instituto de\nTransparencia, Acceso a la Información Pública y Protección de Datos Personales del adquieren tales atribuciones o funciones, según corresponda.\n.\nActualización Legislativa.\nCUARTO.- A partir de la publicación del presente Decreto, el Instituto de Transparencia, Acceso a la Información Pública y Protección de Datos Personales del Estado de Baja\nCalifornia deberá iniciar el proceso de transferencia de los recursos financieros y materiales, tanto a la Secretaría de Hacienda, como a la Oficialía Mayor de Gobierno, respectivamente, con base en las disposiciones normativas vigentes. El proceso de transferencia deberá concluir a más tardar antes de la entrada en vigor del presente Decreto, a fin de que las dependencias del Poder Ejecutivo realicen las asignaciones correspondientes en favor de las Autoridades Garantes que, conforme al presente Decreto, asuman las funciones en la materia.\nLa Secretaría de Hacienda, y la Oficialía Mayor de Gobierno, en coordinación con la\nSecretaría Anticorrupción y Buen Gobierno, en el ámbito de sus respectivas competencias, resolverán de conformidad con la normatividad aplicable, sobre los aspectos administrativos no contemplados en el presente Decreto, para la asignación de los recursos financieros, de los programas y partidas presupuestales, así como de los recursos humanos y materiales, según correspondan, para la debida ejecución del presente Decreto.\nAsimismo, dicho Instituto deberá remitir a la Secretaría de Hacienda la información y formatos necesarios para la integración de la Cuenta Pública y de los demás informes correspondientes al trimestre fiscal en curso, en términos de las disposiciones jurídicas aplicables, a la entrada en vigor del presente Decreto.\nQUINTO.- Las personas que, a la entrada en vigor del presente Decreto, sean o hayan sido servidoras públicas del Instituto de Transparencia, Acceso a la Información Pública y\nProtección de Datos Personales del Estado de Baja California y que tengan pendiente la presentación de la declaración patrimonial y de intereses en cualquiera de sus modalidades, deberán cumplir con esta obligación en los sistemas habilitados por la Secretaría\nAnticorrupción y Buen Gobierno del Estado o en los medios que esta determine, conforme a la normativa aplicable a la Administración Pública Estatal.\nLas personas que dentro de los diez días previos a la entrada en vigor del presente Decreto se hayan desempeñado como personas servidoras públicas del Instituto de Transparencia, Acceso a la Información Pública y Protección de Datos Personales del Estado de Baja\nCalifornia, incluyendo a las personas Comisionadas, deben presentar acta administrativa de entrega-recepción institucional e individual, según corresponda, a la persona servidora pública que la Secretaría Anticorrupción y Buen Gobierno del Estado designe y conforme a la normativa aplicable a la Administración Pública Estatal, en los sistemas de la referida dependencia habilitados para tales efectos o en los medios que ésta determine, en el que pudieran llegarse a determinar por la autoridad competente con posterioridad.\nSEXTO.- Con motivo de las presentes reformas, se respetarán en todo momento los derechos laborales de las personas servidoras públicas del Instituto de Transparencia, California, conforme a las disposiciones jurídicas aplicables.\n.\nActualización Legislativa.\nSÉPTIMO.- Los contratos cuya naturaleza no sea laboral o burocrática, convenios y demás instrumentos celebrados por el Instituto de Transparencia, Acceso a la Información Pública y\nProtección de Datos Personales del Estado de Baja California que a la fecha de publicación del Decreto se encuentren vigentes, dejarán de surtir sus efectos de conformidad con la entrada en vigor de las presentes reformas.\nOCTAVO.- Los registros, padrones y sistemas informáticos, con los que cuenta el Instituto de Transparencia, Acceso a la Información Pública y Protección de Datos Personales del\nEstado de Baja California, incluso los que ya no se utilicen, pero contengan registros históricos, incluida su documentación y titularidad, serán transferidos a la Secretaría\nAnticorrupción y Buen Gobierno del Estado.\nNOVENO.- Los procedimientos iniciados con anterioridad a la entrada en vigor de este\nDecreto ante el Instituto de Transparencia, Acceso a la Información Pública y Protección de\nDatos Personales del Estado de Baja California, en materia de acceso a la información pública, se sustanciarán ante Transparencia para el Pueblo conforme a las disposiciones aplicables vigentes al momento de su inicio.\nLa defensa legal ante autoridades administrativas, jurisdiccionales y judiciales de los actos administrativos y jurídicos emitidos por el Instituto de Transparencia, Acceso a la Información\nPública y Protección de Datos Personales del Estado de Baja California, en materia de acceso a la información pública, se llevará a cabo por Transparencia para el Pueblo, la cual podrá remitir a la Autoridad Garante competente aquellos asuntos que se mencionan en los párrafos anteriores que le corresponda conforme al ámbito de sus atribuciones para su atención.\nDÉCIMO.- La persona titular del Poder Ejecutivo del Estado deberá expedir el Reglamento\nInterno de Transparencia para el Pueblo dentro de los noventa días naturales siguientes a la entrada en vigor del presente Decreto. Para tal efecto, deberá emplear los recursos humanos con los que cuente el área competente, así como aquellos que le sean asignados en razón de las funciones que asuma como Autoridad Garante, conforme a las necesidades de mejora y modernización de la gestión pública.\nDÉCIMO PRIMERO.- Los expedientes y archivos que a la publicación del presente Decreto estén a cargo del Instituto de Transparencia, Acceso a la Información Pública y Protección de Datos Personales del Estado de Baja California para el ejercicio de sus facultades sustantivas, competencias o funciones, de conformidad con la Ley General de Archivos y demás disposiciones jurídicas aplicables, serán transferidos a la Secretaría Anticorrupción y\nDecreto. mencionan en el párrafo anterior, podrá transferirlos a la Autoridad Garante correspondiente.\nDÉCIMO SEGUNDO.- El Órgano Interno de Control del Instituto de Transparencia, Acceso a\n.\nActualización Legislativa. queda extinto y sus asuntos y procedimientos que a la publicación del presente Decreto estén a su cargo, así como los expedientes y archivos, serán transferidos a la Secretaría\nAnticorrupción y Buen Gobierno del Estado dentro de los diez días hábiles siguientes a su publicación, y serán tramitados y resueltos por dicho órgano conforme a las disposiciones jurídicas vigentes al momento de su inicio.\nDÉCIMO TERCERO.- El Órgano de Control y Disciplina del Poder Judicial; los Órganos\nInternos de Control de los Órganos Constitucionales Autónomos y la Contraloría Interna del\nPoder Legislativo del Estado; en un plazo máximo de sesenta días naturales contados a partir de la entrada en vigor del presente Decreto deberán realizar las adecuaciones necesarias a su normativa interna para dar cumplimiento a lo dispuesto en este instrumento.\nDÉCIMO CUARTO.- Se suspenden por un plazo de noventa días naturales contados a partir de la publicación de este Decreto todos y cada uno de los trámites, procedimientos y demás medios de impugnación, establecidos en este instrumento y demás normativa aplicable, con excepción de la recepción y atención de las solicitudes de información que se tramitan a través de la Plataforma Nacional de Transparencia.\nDADO en Sesión Ordinaria de la XXV Legislatura en la Ciudad de Mexicali, B.C., a los once días del mes de septiembre del año dos mil veinticinco.\nDIP. JAIME EDUARDO CANTÓN ROCHA\nPRESIDENTE\n(RÚBICA)\nDIP. MICHELLE ALEJANDRA TEJEDA MEDINA\nSECRETARIA\n(RÚBICA)\nDE CONFORMIDAD CON LO DISPUESTO POR LA FRACCIÓN I DEL ARTÍCULO 49\nCALIFORNIA, IMPRÍMASE Y PUBLÍQUESE.\nMEXICALI, BAJA CALIFORNIA, A LOS 12 DÍAS DEL MES DE SEPTIEMBRE DEL\nAÑO DOS MIL VEINTICINCO.\nMARINA DEL PILAR ÁVILA OLMEDA\nGOBERNADORA DEL ESTADO\nDE BAJA CALIFORNIA\n(RÚBRICA)\nALFREDO ÁLVAREZ CÁRDENAS\nSECRETARIO GENERAL DE GOBIERNO\nDEL ESTADO DE BAJA CALIFORNIA\n(RÚBRICA)",
  "ordenamiento": "REGLAMENTO",
  "jurisdiccion": "BAJA CALIFORNIA",
  "fuente_oficial": "Periódico Oficial",
  "FECHA PER OFIC": "2025/09/16",
  "ESTATUS": "VIGENTE",
  "TOMO": "TOMO_I",
  "URL": "https://www.congresobc.gob.mx/Documentos/ProcesoParlamentario/Leyes/TOMO_I/20250916_LEYDETRANSPARENCIA.PDF",
  "es_escaneado": false,
  "tiene_tablas": false,
  "materia": [
    "administrativo",
    "legislativo",
    "gobernanza"
  ]
}