{
  "titulo": "Ley DE ACCESO DE LAS MUJERES A UNA VIDA LIBRE DE VIOLENCIA PARA EL ESTADO DE BAJA CALIFORNIA",
  "Contenido": "ESTADO DE BAJA CALIFORNIA\nPublicado en el Periódico Oficial No. 29,\nTITULO PRIMERO\nTítulo Adicionado\nCAPÍTULO UNICO\nDISPOSICIONES GENERALES\nCapítulo Modificado, manteniendo la misma denominación\nArtículo 1. Las disposiciones de la presente Ley son de orden público, interés social y observancia general en el Estado de Baja California, y tienen por objeto establecer las bases para prevenir, atender, sancionar y erradicar las violencias contra las mujeres, adolescentes y niñas, los principios y mecanismos para el pleno acceso a una vida libre de violencias, garantizando el goce y ejercicio de sus derechos humanos, así como la protección reforzada del Estado con estas, y fortalecer el régimen democrático establecido en la Constitución\nSoberano del Estado de Baja California, la Ley General, los Tratados Internacionales y las demás leyes vigentes en materia.\nArtículo Reformado\nArtículo 2. La presente Ley obliga a los órganos e instituciones públicas de orden estatal y municipal en el ámbito de sus respectivas competencias a expedir las normas legales y reglamentarias correspondientes, así como tomar las medidas presupuestales y administrativas, con perspectiva de género, para garantizar el derecho de las mujeres a una vida libre de violencia, de conformidad con los Tratados Internacionales en Materia de\nDerechos Humanos de las Mujeres, ratificados por el Estado mexicano, cumpliendo con los objetivos del Sistema y del Programa Estatal.\nPárrafo Reformado\nLos sujetos obligados deberán instrumentar las medidas presupuestales y administrativas necesarias y suficientes de carácter extraordinario para hacer frente a la\nAlerta de Violencia de Género contra las mujeres.\nPárrafo Adicionado\nArtículo Reformado\nArtículo 3. Los principios rectores para el acceso de todas las mujeres, adolescentes y de las políticas públicas estatales son:\nPárrafo Reformado\nI. La igualdad jurídica, sustantiva, de resultados y estructural;\nFracción Reformada\nLey de Acceso de las Mujeres a una Vida Libre de Violencia Página 1\nII. La dignidad de las mujeres;\nFracción Reformada\nIII. La no discriminación;\nFracción Reformada\nIV. La libertad de las mujeres;\nFracción Reformada\nV. La universalidad, interdependencia, indivisibilidad y la progresividad de los derechos humanos;\nFracción Adicionada\nVI. La perspectiva de género;\nFracción Adicionada\nVII. La debida diligencia;\nFracción Adicionada\nVIII. La interseccionalidad;\nFracción Adicionada\nIX. La interculturalidad; y,\nFracción Adicionada\nX. El enfoque diferencial.\nFracción Adicionada\nArtículo Reformado\nArtículo 3 BIS. Las víctimas directas o indirectas de cualquier tipo de violencia tendrán los derechos siguientes:\nPárrafo Reformado\nI. Contar con protección inmediata y efectiva por parte de las autoridades competentes;\nII. Ser tratada con respeto a su integridad y el ejercicio pleno de sus derechos;\nIII. Recibir información veraz y suficiente que les permita decidir sobre las opciones de atención;\nIV. Contar con asesoría jurídica gratuita y expedita; las mujeres indígenas serán conocimiento de su lengua y cultura.\nV. Recibir información, atención y acompañamiento médico y psicológico;\nVI. Ser valoradas y educadas libres de estereotipos de comportamiento y prácticas sociales y culturales basadas en conceptos de inferioridad o subordinación;\nVII. Contar con un refugio, mientras lo necesite; en los casos de violencia familiar, las mujeres que tengan hijas y/o hijos podrán acudir a los refugios con éstos. Cuando se trate de\nLey de Acceso de las Mujeres a una Vida Libre de Violencia Página 2 víctimas de trata de personas, recibirán atención integral con sus hijas e hijos en Refugios\nEspecializados, de conformidad a lo dispuesto por la Ley en la materia.\nVIII. La víctima no será obligada a participar en mecanismos de conciliación con su agresor;\nIX. Acceder a procedimientos expeditos y accesibles de procuración y administración de justicia; y,\nX. A la protección de su identidad y demás datos personales y de la víctima indirecta, de conformidad a lo dispuesto por la Ley de Protección de Datos personales en posesión de\nSujetos Obligados para el Estado de Baja California, el Código Nacional de Procedimientos\nPenales y demás Leyes aplicables.\nLas mujeres indígenas serán asistidas gratuitamente en todo tiempo por intérpretes y personas defensoras de oficio que tengan conocimiento de su lengua y cultura.\nPárrafo Adicionado\nLas mujeres con discapacidad tendrán derecho a que los procedimientos sean accesibles y a que se realicen los ajustes de procedimiento necesarios para ello. Las mujeres sordas tendrán derecho a contar con interpretación en lengua de señas mexicana, la cual será proporcionada gratuitamente.\nPárrafo Adicionado\nLos refugios y los Centros de Justicia para las Mujeres deberán contar con todas las condiciones necesarias para proporcionar atención, en igualdad de condiciones y sin discriminación.\nPárrafo Adicionado\nArtículo Adicionado\nArtículo Reformado\nArtículo 4. Para efectos de esta Ley se entenderá por:\nI. Ley: Ley de Acceso de las Mujeres a una Vida Libre de Violencia para el Estado de Baja California;\nII. Ley General: Ley General de Acceso de las Mujeres a una Vida Libre de\nViolencia;\nIII. Sistema Nacional: Sistema Nacional de Prevención, Atención, Sanción y\nErradicación de la Violencia en contra de las Mujeres;\nIV. Sistema: El Sistema Estatal de Prevención, Atención, Sanción y Erradicación de la Violencia en contra de las Mujeres;\nLey de Acceso de las Mujeres a una Vida Libre de Violencia Página 3\nV. Programa: Programa Integral para Prevenir, Atender, Sancionar y Erradicar la\nViolencia contra las Mujeres, en los términos de la Ley General;\nVI. Programa Estatal: Programa Estatal para Prevenir, Atender, Sancionar y\nErradicar la Violencia contra las Mujeres;\nVII. Violencia contra las Mujeres: Cualquier acción, conducta u omisión basada en su género, que les cause daño o sufrimiento psicológico, físico, patrimonial, económico, sexual o la muerte, tanto en el ámbito público como en el privado;\nVIII. Víctima: La mujer de cualquier edad a quien se le inflige cualquier tipo de violencia;\nFracción Reformada\nIX. Modalidades de Violencia: Las formas, manifestaciones o los ámbitos de ocurrencia en que se presenta la violencia contra las mujeres;\nFracción Reformada\nX. Misoginia: Son conductas de odio hacia las mujeres, las adolescentes y las niñas y se manifiestan en actos violentos y crueles contra ellas por el hecho de serlo;\nFracción Reformada\nXI. Persona agresora: Quien o quienes ejercen algún tipo de violencia contra la mujer de cualquier edad, en cualquiera de sus modalidades;\nFracción Reformada\nXII. Derechos Humanos de las Mujeres: Refiere a los derechos que son parte inalienable, integrante e indivisible de los derechos humanos universales contenidos en la\nConvención sobre la Eliminación de Todas las Formas de Discriminación contra la Mujer\n(CEDAW), la Convención sobre los Derechos de la Niñez, la Convención sobre los Derechos de las Personas con Discapacidad, la Convención Interamericana para Prevenir, Sancionar y\nErradicar la Violencia contra la Mujer (Belem do Pará) y demás instrumentos internacionales en la materia;\nFracción Reformada\nXIII. Empoderamiento de las Mujeres: Es un proceso por medio del cual las mujeres transitan de cualquier situación de opresión, desigualdad, discriminación, explotación o exclusión a un estadio de conciencia, inclusión, autodeterminación y autonomía, el cual se libertades;\nFracción Reformada\nXIV. Alerta de Violencia de Género contra las mujeres: Es el conjunto de acciones gubernamentales coordinadas, integrales, de emergencia y temporales realizadas entre las autoridades de los tres órdenes y niveles de gobierno, para enfrentar y erradicar la violencia feminicida en un territorio determinado; así como para eliminar el agravio comparado, Ley de Acceso de las Mujeres a una Vida Libre de Violencia Página 4 que impiden el reconocimiento o ejercicio de los derechos humanos de las mujeres, las adolescentes y las niñas, a fin de garantizar su pleno acceso al derecho a una vida libre de violencias. mujeres deberá ser pronto y expedito, atendiendo a la situación de urgencia de los hechos documentados que motiva su solicitud y al territorio especificado en la misma, así como al principio de debida diligencia.\nFracción Reformada\nXV. Organizaciones de la Sociedad Civil: Asociaciones Civiles debidamente constituidas y registradas en los términos de las leyes del Estado de Baja California y especializadas en apoyo a la mujer y la familia víctimas de violencia. Estas asociaciones deberán acreditar ante la Secretaría de Seguridad Ciudadana del Estado la documentación que acredite estar legalmente constituidas y que brinden apoyo a las mujeres víctimas violencia mediante sus centros de atención;\nFracción Adicionada\nFracción Reformada\nXVI. Tipos de violencia: Los distintos daños que puede ocasionar la violencia contra las mujeres;\nFracción Adicionada\nXVII. Víctima indirecta: Familiares de la víctima y/o personas que tengan o hayan tenido relación o convivencia con la misma y que sufran, hayan sufrido o se encuentren en situación de riesgo por motivo de la violencia ejercida contra las mujeres;\nFracción Adicionada\nXVIII. Medidas u órdenes de Protección: Son actos de urgente aplicación en función del interés superior de la víctima y víctima indirecta, son fundamentalmente precautorias y cautelares, deberán otorgarse de oficio o a petición de parte, por las autoridades administrativas, el Ministerio Público o por los órganos jurisdiccionales competentes, en el momento en que tengan conocimiento del hecho de violencia presuntamente constitutivo de un delito o infracción, que ponga en riesgo la integridad, la libertad o la vida de las mujeres, adolescentes, niñas y niños, evitando en todo momento que la persona agresora, víctima;\nFracción Adicionada\nFracción Reformada\nXIX. Centro: Centro de Justicia para las Mujeres de Baja California;\nFracción Adicionada\nXX. Registro: Registro Público de Agresores Sexuales;\nFracción Adicionada\nLey de Acceso de las Mujeres a una Vida Libre de Violencia Página 5\nXXI. Banco Nacional: Banco Nacional de Datos e Información sobre Casos de\nViolencia contra las Mujeres;\nFracción Adicionada\nXXII. Base Estatal: Base Estatal de Datos e Información sobre Casos de Violencia\nContra las Mujeres;\nFracción Adicionada\nXXIII. Muertes evitables: Conjunto de muertes que no deberían haber ocurrido en presencia de servicios de salud eficaces, con exámenes rutinarios para la detección temprana y tratamientos adecuados;\nFracción Adicionada\nXXIV. Interseccionalidad: Herramienta analítica para estudiar, entender y responder a las maneras en que el género se cruza con otras identidades creando múltiples ejes de diferencias que se intersectan en contextos históricos específicos, mismos que contribuyen a experiencias específicas de opresión y privilegio e influyen sobre el acceso de las mujeres y las niñas a derechos y oportunidades;\nFracción Adicionada\nXXV. Interculturalidad: El enfoque intercultural parte del reconocimiento y respeto de las diferencias culturales existentes, bajo la concepción de que las culturas pueden ser diferentes entre sí pero igualmente válidas, no existiendo culturas superiores ni inferiores.\nEstá orientado a abordar las particularidades de las mujeres de los pueblos indígenas, afrodescendientes y otros grupos étnicos diferenciados y su relación con la sociedad dominante, más allá de la coexistencia de culturas.\nFracción Adicionada\nXXVI. Enfoque diferencial: Tiene como objetivo visibilizar las diferentes situaciones de vulnerabilidad de las mujeres, las adolescentes y las niñas, ya sea por género, edad, etnia o discapacidad; así como las vulneraciones específicas a sus derechos humanos en tanto pertenecientes a grupos sociales o culturales específicos. Lo anterior con el objetivo de diseñar y ejecutar medidas afirmativas para la garantía del goce efectivo de los derechos de las mujeres, las adolescentes y las niñas;\nFracción Adicionada\nFracción Reformada\nXXVII. Debida diligencia: La obligación de las personas servidoras públicas de prevenir, atender, investigar y sancionar la violencia contra las mujeres de manera oficiosa, oportuna, competente, independiente, imparcial, exhaustiva y garantizando la participación individual y colectiva de las mujeres, para garantizar el derecho a una vida libre de violencia, a la verdad, la justicia y la reparación integral y transformadora;\nFracción Adicionada\nFracción Reformada\nLey de Acceso de las Mujeres a una Vida Libre de Violencia Página 6\nXXVIII. Espacio Público: Áreas, espacios abiertos o predios de los asentamientos humanos destinados al uso, disfrute o aprovechamiento colectivo, de acceso generalizado y libre tránsito;\nFracción Adicionada\nFracción Reformada\nXXIX. Programa Institucional: Programa Institucional en beneficio de las Mujeres; y,\nFracción Adicionada\nXXX. Registro Nacional: El Registro Nacional de Medidas u Órdenes de Protección de las Mujeres, Adolescentes, Niñas y Niños.\nFracción Adicionada\nArtículo Reformado\nTITULO SEGUNDO\nTIPOS Y MODALIDADES DE VIOLENCIA CONTRA LAS MUJERES, MEDIDAS U\nÓRDENES DE PROTECCIÓN Y REFUGIOS PARA MUJERES VÍCTIMAS DE VIOLENCIA\nTítulo Adicionado\nDenominación Modificada\nCAPÍTULO I\nDE LOS TIPOS DE VIOLENCIA CONTRA LAS MUJERES\nCapítulo y Denominación modificados\nArtículo 5.- Para efectos de la presente ley, la perspectiva de género es una visión científica, analítica y política sobre las mujeres y los hombres. Se propone eliminar las causas de la opresión de género como la desigualdad, la injusticia y la jerarquización de las personas basada en el género. Promueve la igualdad entre los géneros a través de la equidad, el adelanto y el bienestar de las mujeres; contribuye a construir una sociedad en donde las mujeres y los hombres tengan el mismo valor, la igualdad de derechos y oportunidades para acceder a los recursos económicos y a la representación política y social en los ámbitos de toma de decisiones.\nArtículo Reformado\nCAPÍTULO II\nTIPOS Y MODALIDADES DE VIOLENCIA\nCapítulo Adicionado\nArtículo 6. Los tipos y modalidades de violencia enumerados por ésta Ley, serán sancionados en los términos de la normatividad aplicable.\nReconociendo como tipos de violencia los siguientes:\nI. Violencia Psicológica.- Entendida como cualquier acto u omisión que dañe la estabilidad psicológica, que puede consistir en: negligencia, abandono, descuido reiterado, celotipia, insultos, humillaciones, devaluación, marginación, indiferencia, infidelidad, Ley de Acceso de las Mujeres a una Vida Libre de Violencia Página 7 comparaciones destructivas, rechazo, restricción a la autodeterminación y amenazas, que pueda conllevar a la víctima a la depresión, al aislamiento, a la devaluación de su autoestima e incluso al suicidio;\nII. Violencia Física.- Es cualquier acto que inflige daño no accidental, usando la fuerza física o algún tipo de arma u objeto que pueda provocar o no lesiones ya sean internas, externas, o ambas;\nIII. Violencia Patrimonial.- Es cualquier acto u omisión que afecta el desarrollo adecuado de la víctima, se manifiesta en: la transformación, sustracción, destrucción, retención o distracción de objetos, documentos personales, bienes y valores, derechos patrimoniales o recursos económicos destinados a satisfacer las necesidades de la víctima, así como los daños a los bienes comunes o propios de la víctima;\nIV. Violencia Económica.- Es toda acción u omisión del Agresor que afecta la supervivencia económica de la víctima, se manifiesta a través de limitaciones encaminadas a controlar el ingreso de sus percepciones económicas, así como la percepción de un salario menor por igual trabajo, dentro de un mismo centro laboral;\nV. Violencia Sexual.- Es cualquier acto que degrada o daña el cuerpo y/o la sexualidad de la víctima y que por tanto atenta contra su libertad, dignidad e integridad física, incluyéndose la exhibición del cuerpo de la mujer en imágenes privadas o comerciales que inciten a realizar actividades de índole sexual. Es una expresión de abuso de poder, que se puede dar en el espacio público o privado, que implica la supremacía masculina sobre la mujer, al denigrarla y concebirla como objeto;\nFracción Reformada\nVI. Violencia Obstétrica.- Toda conducta, acción u omisión que ejerza el personal de salud o personal administrativo de manera directa o indirecta, y que afecte a las mujeres durante los procesos de embarazo, parto o puerperio, mediante la apropiación del cuerpo y procesos reproductivos de las mujeres que se expresa en un trato deshumanizador, omisión de atención oportuna y eficaz, abuso de medicalización y patologización de los procesos naturales, prácticas sin consentimiento como esterilización o realizar cesárea sin motivo, o cualquier otra que tenga como resultado la pérdida de autonomía y capacidad de decidir libremente sobre su cuerpo y sexualidad, impactando la calidad de vida de las mujeres;\nFracción Reformada\nVII.- Violencia Digital.- Es toda acción dolosa realizada mediante el uso de tecnologías de la información y la comunicación, por la que se exponga, distribuya, difunda, exhiba, transmita, comercialice, oferte, intercambie o comparta mensajes de texto, imágenes, audios consentimiento, sin su aprobación o sin su autorización y que le cause daño psicológico o emocional, en cualquier ámbito de su vida privada o en su imagen propia.\nPárrafo Reformado\nAsí como aquellos actos dolosos que causen daño a la intimidad, privacidad y/o dignidad de las mujeres incluyendo los mensajes de odio, que se cometan por medio de las tecnologías de la información y la comunicación.\nLey de Acceso de las Mujeres a una Vida Libre de Violencia Página 8\nPárrafo Adicionado\nPara efectos de este tipo de violencia, se entenderá por Tecnologías de la Información y la Comunicación aquellos recursos, herramientas y programas que se utilizan para procesar, administrar y compartir la información mediante diversos soportes tecnológicos;\nPárrafo Adicionado\nFracción Adicionada\nFracción Reformada\nVIII.- Violencia Mediática.-.- Es todo acto a través de cualquier medio de comunicación, que de manera directa o indirecta promueva estereotipos sexistas, transmita y reproduzca dominación, cosificación, haga apología de la violencia contra las mujeres y las niñas, produzca o permita la producción y difusión de discurso de odio sexista, discriminación de género o desigualdad entre mujeres y hombres, naturalizando la subordinación de la mujer en la sociedad, promueva la explotación de mujeres o sus imágenes, que cause daño a las mujeres y niñas de tipo simbólico, psicológico, sexual, físico, económico, patrimonial o feminicida.\nPárrafo de Fracción Reformado\nLa violencia mediática se ejerce por cualquier persona física o moral que utilice un medio de comunicación para producir y difundir contenidos que atentan contra la autoestima, salud, integridad, libertad y seguridad de las mujeres y niñas, que impide su desarrollo y que atenta contra la igualdad y dignidad.\nPárrafo de Fracción Adicionado\nPárrafo de Fracción Reformado\nFracción Adicionada\nFracción Reformada\nIX.- Violencia Vicaria.- Es el acto u omisión intencional cometido contra la mujer, por parte de quien mantenga o mantuvo una relación, ya sea de hecho, de pareja o similares, aun sin convivencia y que por sí misma o por interpósita personas utilice como medio al descendiente, ascendiente, dependiente económico, o persona con relación afectiva, para causarle algún tipo de perjuicio o daño psicológico, patrimonial, económico, físico o de cualquier otra índole a la mujer.\nSe expresa a través de conductas, como:\na) Amenazar con causar daños a descendiente, ascendiente, dependientes económicos o personas allegadas;\nb) Ocultar, retener o sustraer a hijas e hijos, fuera de su domicilio custodio o lugar de residencia;\nc) Utilizar a hijos e hijas para obtener información respecto a la madre;\nd) Promover, incitar o fomentar actos de violencia de hijos e hijas en contra de la madre;\ne) Condicionar el pago o cumplimiento de obligaciones alimentarias a las mujeres, hijas e hijos;\nLey de Acceso de las Mujeres a una Vida Libre de Violencia Página 9\nf) Utilizar a otros familiares o personas allegadas de la mujer para cometer este tipo de violencia; y,\ng) Que las instituciones de procuración y administración de justicia no reconozcan la y del interés superior de la niñez.\nFracción Adicionada\nX. Violencia Ácida: Es aquella que pretenda causar daño físico irreversible que lastime, altere y/o cause alguna discapacidad, mediante la acción de arrojar ácido, álcalis, sustancias químicas, corrosivas, cáusticas, irritantes, tóxicas, inflamables, líquidos a altas temperaturas o cualquier otra sustancia que pueda provocar o no lesiones en órganos internos, externos o ambos.\nEste tipo de violencia implica una alta carga simbólica toda vez que la finalidad es causar de forma deliberada y permanente dolor, sufrimiento y humillación a la mujer, además de causar daño físico, psicológico y emocional irreparable e irreversible, es decir, dejar una marca permanente en ella.\nFracción Adicionada\nXI. Violencia Simbólica.- La que a través de patrones estereotipados, mensajes, valores, iconos o signos, transmita y reproduzca dominación, cosificación, desigualdad y discriminación en las relaciones sociales, naturalizando la subordinación de la mujer en la sociedad; y,\nFracción Adicionada\nXII. Cualesquiera otra forma análoga que lesione o sea susceptible de dañar la dignidad, integridad o libertad de las mujeres.\nFracción Recorrida\nArtículo Reformado\nArtículo 7. Violencia Familiar: Se considera violencia familiar el acto abusivo de poder u omisión intencional, dirigido a dominar, someter, controlar o agredir de manera física, verbal, psicológica, patrimonial, económica o sexual a las mujeres, dentro o fuera del domicilio familiar, cuya persona agresora tenga o haya tenido una relación de parentesco por consanguinidad o afinidad, de matrimonio, concubinato o mantengan o hayan mantenido una relación de hecho.\nPárrafo Reformado\nLos gobiernos estatal y municipales en forma coordinada, implementarán y operarán investigaciones de violencia familiar o violencia vicaria, lo que permitirá a las autoridades preventivas e investigadoras correspondientes, detectar en forma inmediata la reincidencia de toda persona agresora, a efecto de determinar en forma eficaz las medidas necesarias para salvaguardar la integridad de la víctima. También se considera violencia familiar cuando la persona agresora tenga responsabilidades de cuidado o de apoyo respecto de la víctima, aunque no tenga una relación de parentesco.\nLey de Acceso de las Mujeres a una Vida Libre de Violencia Página 10\nPárrafo Reformado\nArtículo Reformado de sus competencias, en materia de violencia familiar deberán desarrollar los modelos de atención, prevención, sanción y erradicación, que son el conjunto de medidas y acciones para proteger a las víctimas y víctimas indirectas de violencia familiar, como parte de la obligación del Estado, de garantizar a las mujeres su seguridad y ejercicio pleno de sus derechos humanos considerando la interseccionalidad, la interculturalidad y el enfoque diferenciado, y deberán:\nPárrafo Reformado\nI. Impulsar Unidades Especializadas para la atención psicológica y jurídica de las mujeres víctimas de violencia;\nII. Proporcionar de manera gratuita los servicios de atención, trabajo social, asesoría jurídica y tratamientos psicológicos especializados y gratuitos a las víctimas, que favorezcan su empoderamiento y reparen el daño causado por dicha violencia;\nIII. Brindar servicios reeducativos integrales, especializados y gratuitos a la víctima, víctima indirecta y persona agresora para erradicar las conductas violentas a través de una educación que elimine los estereotipos de supremacía masculina, y los patrones machistas que generaron su violencia;\nFracción Reformada\nIV. Evitar que la atención que reciban la víctima, víctima indirecta y la persona agresora sea proporcionada por la misma persona y en el mismo lugar. En ningún caso podrán brindar atención, aquellas personas que hayan sido sancionadas por ejercer algún tipo de violencia;\nFracción Reformada\nV. No utilizar procedimientos de mediación o conciliación ante instancias administrativas, por resultar inviables en una relación de sometimiento entre la persona agresora y la víctima;\nFracción Reformada\nVI. Emitir normas técnicas en los diferentes niveles de atención, para los centros de atención;\nFracción Reformada\nVII. Favorecer y promover la instalación y mantenimiento de refugios para las víctimas y víctimas indirectas; y,\nFracción Reformada\nVIII. Implementar de manera permanente campañas que tengan como objetivo la prevención, detección, atención y concientización de la población en general, de los tipos y modalidades de violencia que ponen en riesgo a la mujer en cualquier etapa de su vida.\nFracción Adicionada\nLey de Acceso de las Mujeres a una Vida Libre de Violencia Página 11\nLos modelos de atención, prevención, sanción y erradicación a los que se refiere el ajustarse a las condiciones específicas de las mujeres víctimas de violencia.\nPárrafo Adicionado\nArtículo Reformado\nArtículo 9. Violencia Laboral y Docente: Se ejerce por las personas que tienen un vínculo laboral, docente o análogo con la víctima, indepen0000dientemente de la relación jerárquica, consistente un acto o una omisión en abuso de poder que daña la autoestima, salud, integridad, libertad y seguridad de la víctima, e impide su desarrollo y atenta contra la igualdad.\nArtículo Reformado\nArticulo 9 BIS. Constituye violencia laboral: la negativa ilegal a contratar a la Víctima o a respetar su permanencia o condiciones generales de trabajo; la descalificación del trabajo realizado, las amenazas, la intimidación, las humillaciones, las conductas referidas en la Ley\nFederal del Trabajo, la explotación, el impedimento a las mujeres de llevar a cabo el período de lactancia previsto en la ley y todo tipo de discriminación por condición de género\nArtículo Adicionado\nArtículo 10. Constituyen violencia docente: aquellas conductas que dañen la autoestima de las alumnas con actos de discriminación por su sexo, edad, condición social, académica, limitaciones y/o características físicas, que les infligen maestras o maestros.\nArtículo Reformado\nArtículo 10 BIS.- El hostigamiento sexual es el ejercicio del poder, en una relación de subordinación real de la víctima frente al agresor en los ámbitos laboral y/o escolar. Se expresa en conductas verbales, físicas o ambas, relacionadas con la sexualidad de connotación lasciva.\nEl acoso sexual es una forma de violencia en la que, si bien no existe la subordinación, hay un ejercicio abusivo de poder que conlleva a un estado de indefensión y de riesgo para la víctima, independientemente de que se realice en uno o varios eventos.\nLas instituciones, organismos y dependencias públicas y privadas deberán contar con protocolos que prevean los mecanismos necesarios para la acreditación, investigación y sanción de estas conductas. públicos pertenecientes a instituciones, organismo o dependencias estatales o municipales, los Órganos Internos de Control y las Sindicaturas Municipales, en el respectivo ámbito de sus competencias, deberán investigar y sancionar dichas conductas de conformidad a lo que establece la Ley de Responsabilidades Administrativas del Estado de Baja California.\nArtículo Adicionado\nLey de Acceso de las Mujeres a una Vida Libre de Violencia Página 12 en materia de violencia laboral, docente y escolar, con independencia de que pudiesen constituir dichas conductas algún ilícito sancionado en la legislación de la materia, considerarán:\nI. Establecer normatividad interna que garantice espacios públicos gubernamentales libres de violencia contra las mujeres en su entorno laboral burocrático y reivindique la dignidad de la mujer al servicio del Estado;\nII. Encabezar la difusión y campañas permanentes para que el sector privado desarrolle políticas que garantice espacios laborales libres de violencia contra las mujeres y reivindique la dignidad de la mujer en la iniciativa privada;\nIII. Diseñar programas integrales que brinden servicios reeducativos para víctimas, victimas indirectas y personas agresoras;\nIV. Diseñar programas integrales que permitan evaluar y analizar el impacto psicoemocional que generan en quien las recibe y las diferentes formas de discriminación contra las mujeres, que se pueden presentar en razón de su género, alguna discapacidad, edad, religión, estado civil y pertenencia a alguna etnia;\nV. La celebración y/o adhesión a convenios para eliminar estas modalidades de violencia;\nVI. La elaboración de protocolos de atención a la víctima y víctima indirecta para estas modalidades de violencia;\nVII. Diseñar e implementar campañas permanentes para prevenir la violencia contra la mujer en los entornos públicos, privados o sociales en los que se pueden presentar estas modalidades de violencia; y,\nVIII. La evaluación continua y permanente de sus políticas públicas en forma volitiva, de los sectores públicos, privados o sociales.\nArtículo Reformado\nArtículo 11 BIS.- La violencia política contra las mujeres en razón de género, es toda acción u omisión, incluida la tolerancia, basada en elementos de género y ejercida dentro de la esfera pública o privada, que tenga por objeto o resultado limitar, anular o menoscabar el ejercicio efectivo de los derechos políticos y electorales de una o varias mujeres, el acceso al pleno ejercicio de las atribuciones inherentes a su cargo, labor o actividad, el libre desarrollo de la función pública, la toma de decisiones, la libertad de organización, así como el acceso y ejercicio a las prerrogativas, tratándose de precandidaturas, candidaturas, funciones o cargos públicos del mismo tipo.\nPárrafo Reformado\nLey de Acceso de las Mujeres a una Vida Libre de Violencia Página 13\nSe entenderá que las acciones u omisiones se basan en elementos de género, cuando se dirijan a una mujer por su condición de mujer; le afecten desproporcionadamente o tengan un impacto diferenciado en ella.\nPárrafo Adicionado puede ser perpetrada indistintamente por agentes estatales, por superiores jerárquicos, colegas de trabajo, personas dirigentes de partidos políticos, militantes, simpatizantes, precandidatas, precandidatos, candidatas o candidatos postulados por los partidos políticos o representantes de los mismos; medios de comunicación y sus integrantes, por un particular o por un grupo de personas particulares.\nPárrafo Adicionado\nArtículo Adicionado\nArtículo Reformado\nArticulo 11 TER. La violencia política contra las mujeres puede expresarse, entre otras, a través de las siguientes conductas:\nPárrafo Reformado\nI. Incumplir las disposiciones jurídicas nacionales e internacionales que reconocen el ejercicio pleno de los derechos políticos de las mujeres;\nFracción Reformada\nII. Restringir o anular el derecho al voto libre y secreto de las mujeres, u obstaculizar sus derechos de asociación y afiliación a todo tipo de organizaciones políticas y civiles, en razón de género;\nFracción Reformada\nIII. Ocultar información u omitir la convocatoria para el registro de candidaturas o para cualquier otra actividad que implique la toma de decisiones en el desarrollo de sus funciones y actividades;\nFracción Reformada\nIV. Proporcionar a las mujeres que aspiran u ocupan un cargo de elección popular información falsa o incompleta, que impida su registro como candidata o induzca al incorrecto ejercicio de sus atribuciones;\nFracción Reformada\nV. Proporcionar información incompleta o datos falsos a las autoridades administrativas, electorales o jurisdiccionales, con la finalidad de menoscabar los imagen pública o limitar sus derechos políticos y electorales;\nFracción Reformada\nVI. Difamar, calumniar, injuriar o realizar cualquier expresión que denigre o descalifique a las mujeres en ejercicio de sus funciones políticas, con base en estereotipos de género, con el objetivo o el resultado de menoscabar su imagen pública o limitar o anular sus derechos;\nFracción Reformada\nLey de Acceso de las Mujeres a una Vida Libre de Violencia Página 14\nVII. Divulgar imágenes, mensajes o información privada de una mujer candidata o en funciones, por cualquier medio físico o virtual, con el propósito de desacreditarla, difamarla, denigrarla y poner en entredicho su capacidad o habilidades para la política, con base en estereotipos de género;\nFracción Reformada\nVIII. Amenazar o intimidar a una o varias mujeres o a su familia o colaboradores con el objeto de inducir su renuncia a la candidatura o al cargo para el que fue electa o designada;\nFracción Reformada\nIX. Impedir, por cualquier medio, que las mujeres electas o designadas a cualquier puesto o encargo público tomen protesta de su encargo, asistan a las sesiones ordinarias o extraordinarias o a cualquier otra actividad que implique la toma de decisiones y el ejercicio del cargo, impidiendo o suprimiendo su derecho a voz y voto;\nFracción Reformada\nX. Restringir los derechos políticos de las mujeres con base a la aplicación de tradiciones, costumbres o sistemas normativos internos o propios, que sean violatorios de los derechos humanos;\nFracción Adicionada\nXI. Imponer, con base en estereotipos de género, la realización de actividades distintas a las atribuciones propias de la representación política, cargo o función;\nFracción Adicionada\nXII. Discriminar a la mujer en el ejercicio de sus derechos políticos por encontrarse en estado de embarazo, parto, puerperio, o impedir o restringir su reincorporación al cargo tras hacer uso de la licencia de maternidad o de cualquier otra licencia contemplada en la normatividad;\nFracción Adicionada\nXIII. Ejercer violencia física, sexual, simbólica, mediática, psicológica, económica o patrimonial contra una mujer en ejercicio de sus derechos políticos;\nFracción Adicionada\nFracción Reformada\nXIV. Limitar o negar arbitrariamente el uso de cualquier recurso o atribución inherente al cargo que ocupe la mujer, incluido el pago de salarios, dietas u otras prestaciones asociadas al ejercicio del cargo, en condiciones de igualdad;\nFracción Adicionada\nXV. Obligar a una mujer, mediante fuerza, presión o intimidación, a suscribir\nFracción Adicionada\nXVI. Obstaculizar o impedir el acceso a la justicia de las mujeres para proteger sus derechos políticos;\nFracción Adicionada\nLey de Acceso de las Mujeres a una Vida Libre de Violencia Página 15\nXVII. Limitar o negar arbitrariamente el uso de cualquier recurso o atribución inherente al cargo político que ocupa la mujer, impidiendo el ejercicio del cargo en condiciones de igualdad;\nFracción Adicionada\nXVIII. Imponer sanciones injustificadas o abusivas, impidiendo o restringiendo el ejercicio de sus derechos políticos en condiciones de igualdad, o\nFracción Adicionada\nXIX. Cualesquiera otras formas análogas que lesionen o sean susceptibles de dañar la dignidad, integridad o libertad de las mujeres en el ejercicio de un cargo político, público, de poder o de decisión, que afecte sus derechos políticos electorales. La violencia política contra las mujeres en razón de género se sancionará en los términos establecidos en la legislación electoral, penal y de responsabilidades administrativas.\nFracción Adicionada\nArtículo Adicionado\nArtículo Reformado\nArtículo 11 QUATER. Tratándose de violencia digital o mediática para garantizar la integridad de la víctima, el Ministerio Público o la persona juzgadora competente, ordenarán de manera inmediata, las medidas de protección necesarias, ordenando vía electrónica o mediante escrito a las empresas de plataformas digitales, de medios de comunicación, redes sociales o páginas electrónicas, personas físicas o morales, la interrupción, bloqueo, destrucción, o eliminación de imágenes, audios o videos relacionados con la investigación previa satisfacción de los requisitos de Ley.\nEn este caso se deberá identificar plenamente al proveedor de servicios en línea a cargo de la administración del sistema informático, sitio o plataforma de Internet en donde se encuentre alojado el contenido y la localización precisa del contenido en Internet, señalando el Localizador Uniforme de Recursos.\nLa autoridad que ordene las medidas de protección contempladas en este artículo deberá solicitar el resguardo y conservación lícita e idónea del contenido que se denunció de acuerdo a las características del mismo.\nLas plataformas digitales, medios de comunicación, redes sociales o páginas electrónicas darán aviso de forma inmediata al usuario que compartió el contenido, donde se una orden judicial.\nArtículo Adicionado\nArtículo 12. Violencia Institucional: Se entiende por violencia institucional, los actos u omisiones de los servidores públicos, de cualquier orden de gobierno, que discriminen, dilaten, obstaculicen o impidan el goce y ejercicio de los derechos humanos de las mujeres así como su acceso al disfrute de políticas públicas destinadas a prevenir, atender, investigar, sancionar y erradicar los diferentes tipos de violencia.\nLey de Acceso de las Mujeres a una Vida Libre de Violencia Página 16\nArtículo Reformado organizar el aparato gubernamental de tal forma que sean capaces de asegurar, en el ejercicio de sus funciones, el derecho de las mujeres a una vida libre de violencia, debiendo prevenir, atender, investigar, sancionar y reparar el daño que se les ocasiona.\nPárrafo Reformado\nAsí como diseñar, implementar y promover programas de capacitación integrales permanentes para las y los funcionarios públicos en materia de derechos humanos de las mujeres, cursos de sensibilización en materia de violencia de género, capacitar a su personal operativo para detectar, atender y canalizar a víctimas, victimas indirectas y personas agresoras.\nPárrafo Adicionado\nArtículo Reformado\nArtículo 14. Incurrirán en responsabilidad administrativa los servidores públicos del\nGobierno del Estado y de los Gobiernos Municipales, que en el ejercicio de su cargo o comisión, contravengan los principios y disposiciones que consagra la presente Ley o no den debido y cabal cumplimiento a las normas que de ella emanan, o bien, lleven a cabo cualquier práctica discriminatoria, dilatoria o de tolerancia de la violencia de género, y serán sancionados de conformidad con lo dispuesto por la Ley de Responsabilidades de los\nServidores Públicos del Estado de Baja California.\nArtículo Reformado\nArtículo 15. Violencia en la comunidad: Se entiende por violencia en la comunidad, los actos individuales o colectivos que transgreden derechos fundamentales de las mujeres y propician su denigración, discriminación, marginación o exclusión en el ámbito público.\nArtículo Reformado\nArtículo 15 BIS.- Acoso sexual en espacios públicos: Es una forma de violencia que conlleva un abuso de poder respecto de la víctima, sin que medie relación alguna con la persona agresora. Se manifiesta a través de una conducta física o verbal de connotación sexual no consentida ejercida sobre una o varias personas, en espacios y medios de transporte públicos, cuya acción representa una vulneración a los derechos humanos.\nFracción Reformada violencia en la comunidad, en perjuicio de las mujeres, establecerán las siguientes estrategias:\nI. Obtendrán la percepción individual y como grupo de las mujeres, del posible estado de riesgo en que se encuentran, en una sociedad que discrimina;\nII. Diseñarán e implementarán un sistema de monitoreo de patrones de comportamiento violento, en regiones, comunidades u áreas determinadas o situaciones que\nLey de Acceso de las Mujeres a una Vida Libre de Violencia Página 17 impliquen un estado de riesgo contra la mujer, favoreciendo la publicidad e información sobre dicho estado y los factores que lo acrediten;\nFracción Reformada\nIII. La delimitación georreferenciada de zonas que sufren de violencia comunitaria, que permitan elaborar diagnósticos, análisis estadísticos y el plan de acción para su acotamiento y adopción de medidas para la disminución y erradicación de la misma;\nFracción Adicionada, recorriéndose las subsecuentes\nIV. Impulsarán la cultura jurídica, de legalidad y de denuncia de actos violentos, públicos o privados, contra las mujeres;\nFracción Recorrida\nV. El establecimiento de un registro en la Base Estatal de las medidas u órdenes de protección que se emitan por las autoridades competentes para la protección de las mujeres y de personas sujetas a ellas, para brindar el adecuado seguimiento;\nFracción Recorrida y Reformada\nVI. La implementación de acciones en materia de prevención y seguridad pública a favor de las mujeres;\nFracción Recorrida y Reformada\nVII. La reeducación que eliminé estereotipos de supremacía masculina, y los patrones machistas que generaron su violencia, la información de alerta sobre el estado de riesgo que enfrentan las mujeres en una sociedad desigual y discriminatoria; y,\nFracción Recorrida y Reformada\nVIII. El diseño e implementación de políticas y programas dirigidos a promover y desarrollar espacios y transportes públicos seguros y libres de todo tipo de violencia contra las mujeres, las adolescentes y las niñas.\nFracción Adicionada\nArtículo Reformado\nArtículo 17. Violencia Feminicida: Es la forma extrema de violencia de género contra las mujeres, las adolescentes y las niñas, producto de la violación de sus derechos humanos y del ejercicio abusivo del poder, tanto en los ámbitos público y privado, que puede conllevar impunidad social y del Estado.\nPárrafo Reformado vidas o culminan en muertes violentas como el feminicidio, el suicidio y el homicidio, u otras formas de muertes evitables y en conductas que afectan gravemente la integridad, la seguridad, la libertad personal y el libre desarrollo de las mujeres, las adolescentes y las niñas.\nPárrafo Adicionado\nArtículo Reformado\nLey de Acceso de las Mujeres a una Vida Libre de Violencia Página 18\nMunicipios, o en su caso, cada uno de ellos, procurarán la protección del entorno común, disponiendo de las medidas preventivas para garantizar la seguridad de las mujeres; y en su caso, el cese de la violencia en su contra y la eliminación de las situaciones de desigualdad en que se encuentren.\nEn caso que se emita una declaración de alerta de violencia de género; a que se refiere la Ley General, se deberán implementar las siguientes estrategias:\nI. El Sistema Estatal sesionará inmediatamente para coordinar las acciones encaminadas a abatirla;\nII. Implementar las acciones preventivas, de seguridad y justicia, para enfrentar y abatir la violencia feminicida, dando parte al Ministerio Público para su intervención conducente;\nIII. Colaborar en la elaboración de reportes especiales sobre la zona y el comportamiento de los indicadores de la violencia contra las mujeres;\nIV. Asignar los recursos presupuestales necesarios para hacer frente a la contingencia de alerta de violencia de género contra las mujeres a que se refiere la Ley General, y\nV. Hacer del conocimiento público el motivo de la alerta de violencia de género contra las mujeres, y la zona territorial que abarcan las medidas a implementar.\nArtículo Reformado\nArtículo 19. Es compromiso del Estado velar por la erradicación de la violencia en contra de las mujeres, por lo que; ante la violencia feminicida, deberá resarcir el daño conforme a los parámetros establecidos en los Tratados Internacionales en materia de derechos humanos en los que sea parte, en la Ley General, la Ley General de Víctimas y en la local.\nPárrafo Reformado\nConforme a lo dispuesto por las leyes, las acciones encaminadas a reparar el daño consistirán en:\nPárrafo Reformado\nI. El derecho a la justicia pronta, expedita e imparcial: Se deben investigar todas las violaciones a derechos humanos vinculadas a la violencia feminicida, sancionar a las personas responsables y reparar el daño;\nFracción Reformada\nII. La rehabilitación: Se debe garantizar la prestación de servicios jurídicos, médicos y indirectas;\nFracción Reformada\nIII. La satisfacción y no repetición: Son las medidas que buscan una reparación contra las mujeres. Entre las medidas a adoptar se encuentran:\nLey de Acceso de las Mujeres a una Vida Libre de Violencia Página 19\na) La aceptación del Estado de su responsabilidad ante el daño causado y su compromiso de repararlo;\nb) La investigación de las personas servidoras públicas cuyas acciones u omisiones conllevaron a la violación de los derechos humanos de las víctimas y la impunidad, para sancionarlos conforme a la normatividad correspondiente;\nc) El diseño e instrumentación de políticas públicas enfocadas a la prevención, persecución, y seguimiento de la comisión de delitos cometidos contra las mujeres.\nAsimismo, las relativas a garantizar los derechos de los familiares a ser informados de manera oportuna de las acciones que las autoridades realicen tendientes a sancionar a los presuntos responsables; y,\nd) La verificación de los hechos y la publicidad de la verdad.\nFracción Reformada\nToda medida reparatoria deberá tener un enfoque transformador del contexto y cultura discriminatoria, siempre con el objetivo de erradicarla.\nPárrafo Adicionado\nArtículo Reformado\nArtículo 20. La Alerta de Violencia de Género, a la que se refiere la Ley General, podrá solicitarse por los organismos públicos autónomos de derechos humanos locales, nacional o internacionales, u organismos locales o internacionales de protección de los derechos humanos, así como por organizaciones de la sociedad civil legalmente constituidas o por colectivos o grupos de familiares de víctimas a través de una persona representante, ya sea en forma directa a la Secretaría Ejecutiva del Sistema Nacional, o a través de la Secretaría\nTécnica del Sistema Estatal, cuando:\nPárrafo Reformado\nI. Exista incremento persistente de hechos o temor fundado de la posible comisión de delitos de feminicidio, homicidio o delitos del orden común que involucren violaciones a los derechos a la vida, libertad, integridad y seguridad de las mujeres, las adolescentes y las niñas, que perturben la paz social en un territorio determinado y la sociedad así lo reclame; y,\nFracción Reformada\nII. Exista un agravio comparado que impida el ejercicio pleno de los derechos humanos de las mujeres, adolescentes y niñas.\nFracción Reformada\nArtículo Reformado\nArtículo 20 BIS. La solicitud de Alerta de Violencia de Género contra las mujeres deberá contener al menos lo siguiente:\nLey de Acceso de las Mujeres a una Vida Libre de Violencia Página 20\nI. Narración de los hechos de violencia cometidos contra las mujeres, adolescentes y niñas, sustentados con información documentada, datos estadísticos oficiales, testimonios u otra información que sustente las afirmaciones señaladas en la solicitud;\nII. Territorio específico sobre el cual se señalan los hechos de violencia;\nIII. Las autoridades responsables de atender la violencia señalada; y,\nIV. Los demás requisitos de forma que se establezcan en el Reglamento.\nArtículo Adicionado\nArtículo 20 TER. Una vez remitida y admitida la solicitud de Alerta de Violencia de\nGénero contra las mujeres, el o los solicitantes en conjunto con las autoridades actuarán y atenderán lo establecido en la Ley General y demás normatividad aplicable.\nArtículo Adicionado\nCAPÍTULO III\nMEDIDAS U ÓRDENES DE PROTECCIÓN\nDenominación Modificada\nArtículo 21. Las medidas u órdenes de protección son actos de urgente aplicación en función del interés superior de la víctima, son fundamentalmente precautorias y cautelares, deberán otorgarse de oficio o a petición de parte, por las autoridades administrativas, el\nMinisterio Público o por los órganos jurisdiccionales competentes, en el momento en que tengan conocimiento del hecho de violencia presuntamente constitutivo de un delito o infracción, que ponga en riesgo la integridad, la libertad o la vida de las mujeres, adolescentes, niñas o niños, evitando en todo momento que la persona agresora, directamente o a través de algún tercero, tenga contacto de cualquier tipo o medio con la víctima.\nPárrafo Reformado\nTienen como propósito prevenir o hacer cesar un acto de violencia, o impedir la comisión de un nuevo acto de violencia o delito.\nPárrafo Adicionado, recorriéndose el subsecuente\nEn materia de violencia política contra las mujeres en razón de género, el organismo público Local Electoral y el Tribunal de Justicia Electoral del Estado, podrán solicitar a las autoridades competentes el otorgamiento de las medidas a que se refiere el presente\nCapítulo.\nPárrafo Adicionado\nArtículo Reformado\nArtículo 22. Las medidas u órdenes de protección que consagra la presente ley son personalísimas e intransferibles y podrán ser:\nPárrafo Reformado\nI. De naturaleza administrativa: Aquéllas implementadas, otorgadas y ordenadas por el\nMinisterio Público y las autoridades municipales competentes, así como las proporcionadas y/o dictadas de forma directa por cualquier autoridad policial; y,\nFracción Reformada\nLey de Acceso de las Mujeres a una Vida Libre de Violencia Página 21\nII. De naturaleza jurisdiccional: que son las emitidas por los órganos encargados de la administración de justicia.\nFracción Reformada\nLas medidas u órdenes de protección tendrán una duración de hasta 60 días, prorrogables por 30 días más o por el tiempo que dure la investigación o prolongarse hasta que cese la situación de riesgo para la víctima.\nPárrafo Reformado\nDeberán expedirse de manera inmediata o a más tardar dentro de las 8 horas siguientes al conocimiento de los hechos que las generan.\nPárrafo Reformado\nArtículo Reformado\nArtículo 23. Quien en ejercicio de funciones públicas tenga conocimiento de la probable existencia de un hecho que la Ley señale como delito en contra de una mujer, adolescente o una niña, está obligado a denunciarlo inmediatamente al Ministerio Público, proporcionándole todos los datos que tuviere, poniendo a su disposición a la persona imputada, si hubieren sido detenida en flagrancia.\nPárrafo Reformado\nQuien tenga el deber jurídico de denunciar y no lo haga, será acreedor a las sanciones correspondientes.\nPárrafo Adicionado\nArtículo Reformado\nArtículo 24. Las medidas u órdenes de protección se deberán dictar e implementar con base en los siguientes principios:\nPárrafo Reformado\nI. Principio de protección: Considera primordial la vida, la integridad física, la libertad y la seguridad de las personas;\nFracción Reformada\nII. Principio de necesidad y proporcionalidad: Las medidas u órdenes de protección deben responder a la situación de violencia en que se encuentre la persona destinataria, y deben garantizar su seguridad o reducir los riesgos existentes;\nFracción Reformada\nIII. Principio de confidencialidad: Toda la información y actividad administrativa o jurisdiccional relacionada con el ámbito de protección de las personas, debe ser reservada para los fines de la investigación o del proceso respectivo;\nFracción Reformada\nIV. Principio de oportunidad y eficacia: Las medidas u órdenes deben ser oportunas, específicas, adecuadas y eficientes para la protección de la víctima, y deben ser otorgadas e implementadas de manera inmediata y durante el tiempo que garanticen su objetivo;\nFracción Reformada\nLey de Acceso de las Mujeres a una Vida Libre de Violencia Página 22\nV. Principio de accesibilidad: Se deberá articular un procedimiento sencillo para que facilite a las víctimas obtener la protección inmediata que requiere su situación;\nFracción Reformada\nVI. Principio de integralidad: El otorgamiento de la medida a favor de la víctima deberá generarse en un solo acto y de forma automática; y,\nFracción Reformada\nVII. Principio pro persona: Para interpretar lo referente al otorgamiento de las medidas u órdenes de protección, en caso de duda, con relación a la situación de violencia, se estará a lo más favorable para la víctima, tratándose de niñas, niños o adolescentes, siempre se garantizará que se cumpla en todas las decisiones que se tomen respecto de las medidas u órdenes de protección. De igual forma, cuando las determinaciones que se tomen respecto de una mujer víctima de violencia pudieran impactar en los derechos de las hijas o hijos menores de 18 años de edad.\nFracción Reformada\nArtículo Reformado\nArtículo 25. Cuando una mujer, adolescente o una niña, víctima de violencia soliciten una orden de protección a la autoridad administrativa, ministerial y/o judicial, se le deberá brindar toda la información disponible sobre el procedimiento relacionado con la propia orden.\nPárrafo Reformado\nLa autoridad deberá informar con un lenguaje claro, sencillo y empático a la mujer víctima de violencia sobre su derecho a solicitar las medidas u órdenes de protección, y evitará cualquier información tendiente a inhibir o desincentivar la solicitud.\nPárrafo Adicionado\nPárrafo Reformado\nLa autoridad deberá de realizar la medición y valoración del riesgo, la valoración médica en caso de requerirse, así como la valoración psicológica.\nPárrafo Adicionado\nLas autoridades competentes de los tres órdenes de gobierno, que reciban denuncias anónimas de mujeres y niñas víctimas de violencia, decretarán las medidas u órdenes de protección correspondientes.\nPárrafo Adicionado\nPárrafo Reformado\nArtículo Reformado\nArtículo 26. Para la emisión de las medidas u órdenes de protección las autoridades administrativas, el Ministerio Público o el órgano jurisdiccional competente tomará en consideración:\nPárrafo Reformado\nI. Los hechos relatados por la mujer, adolescente o la niña, en situación de violencia, autoridad;\nFracción Adicionada\nLey de Acceso de las Mujeres a una Vida Libre de Violencia Página 23\nII. Las peticiones explícitas de la mujer, adolescente o la niña, en situación de violencia, considerando su desarrollo evolutivo y cognoscitivo o de quien informe sobre el hecho;\nFracción Adicionada\nIII. Las medidas que ella considere oportunas, una vez informada de cuáles pueden ser esas medidas. Tratándose de niñas, las medidas siempre serán determinadas conforme al principio del interés superior de la niñez;\nFracción Adicionada\nIV. Las necesidades que se deriven de su situación particular analizando su identidad de género, orientación sexual, raza, origen étnico, edad, nacionalidad, discapacidad, religión, así como cualquier otra condición relevante;\nFracción Adicionada\nV. La persistencia del riesgo aún después de su salida de un refugio temporal; y,\nFracción Adicionada\nVI. La manifestación de actos o hechos previos de cualquier tipo de violencia que hubiese sufrido la víctima.\nFracción Adicionada\nArtículo Reformado\nArtículo 26 BIS. Las autoridades administrativas, el Ministerio Público o el órgano jurisdiccional competente, deberá ordenar la protección necesaria, considerando:\nI. Los principios establecidos en esta ley;\nII. Que sea adecuada, oportuna y proporcional;\nIII. Que los sistemas normativos propios basados en usos y costumbres no impidan la garantía de los derechos de las mujeres reconocidos en la Constitución Política de los\nEstados Unidos Mexicanos, así como en los tratados internacionales ratificados por el Estado\nMexicano;\nIV. La discriminación y vulnerabilidad que viven las mujeres y las niñas por razón de identidad de género, orientación sexual, raza, origen étnico, edad, nacionalidad, discapacidad, religión o cualquiera otra, que las coloque en una situación de mayor riesgo; y,\nV. Las necesidades expresadas por la mujer, adolescente o niña solicitante.\nLas autoridades administrativas, el Ministerio Público y los órganos jurisdiccionales determinarán las medidas u órdenes de protección para denunciantes anónimas de violencia, privilegiando la integridad y la seguridad de las víctimas.\nPárrafo Reformado\nArtículo Adicionado\nArtículo Reformado\nLey de Acceso de las Mujeres a una Vida Libre de Violencia Página 24\nArtículo 26 TER. Las autoridades administrativas, el Ministerio Público o el órgano jurisdiccional que emita las medidas u órdenes de protección, realizarán las gestiones necesarias para garantizar su cumplimiento, monitoreo y ejecución. Para lo anterior se allegará de los recursos materiales y humanos necesarios, asimismo podrá solicitar la colaboración de las autoridades competentes.\nPárrafo Reformado\nLas medidas u órdenes de protección podrán solicitarse en el Estado de Baja\nCalifornia, aun cuando los hechos hayan ocurrido en otra Entidad Federativa, sin que la competencia en razón del territorio pueda ser usada como excusa para no recibir la solicitud.\nPárrafo Adicionado\nPara efectos de lo anterior, y con el propósito de garantizar la efectiva protección de las mujeres, adolescentes, niñas y niños conforme a los principios rectores de las medidas u órdenes de protección, las autoridades administrativas, la Fiscalía General del Estado y el\nPoder Judicial del Estado podrán celebrar convenios de colaboración entre sí o con las autoridades administrativas, fiscalías y poderes judiciales de las demás entidades federativas o de la federación.\nPárrafo Adicionado\nArtículo Adicionado\nArtículo Reformado\nArtículo 26 QUÁTER. Las medidas u órdenes de protección administrativas, además de las previstas en otros ordenamientos, podrán consistir en una o varias de las siguientes:\nPárrafo Reformado\nI. El traslado de las víctimas a donde se requiera, cuantas veces sea necesario en las diferentes diligencias para garantizar su seguridad y protección;\nII. Custodia personal y o domiciliaria a las víctimas, que estará a cargo de los cuerpos policiacos adscritos a la Fiscalía General del Estado de Baja California. En caso de que no exista disponibilidad podrá apoyarse en las instituciones de seguridad pública municipal. Esta medida se aplicará bajo la más estricta responsabilidad del Ministerio Público.\nIII. Proporcionar a las mujeres, adolescentes o las niñas, en situación de violencia y a las victimas indirectas alojamiento temporal en espacios seguros tales como casas de emergencia, refugios y albergues que garanticen su seguridad y dignidad, en términos de las disposiciones aplicables de esta ley;\nIV. De requerirse brindar apoyo económico para garantizar su seguridad personal, transporte, alimentos, comunicación, mudanza y los trámites oficiales que requiera entre otros;\nV. Canalizar y trasladar sin demora alguna a las mujeres, o las niñas, en situación de manera inmediata los servicios de:\nLey de Acceso de las Mujeres a una Vida Libre de Violencia Página 25\na) aplicación de antirretrovirales de profilaxis post-exposición;\nb) anticoncepción de emergencia, y;\nc) interrupción legal y voluntaria del embarazo en el caso de violación.\nVI. Proveer los recursos y herramientas necesarias para garantizar la seguridad y acondicionamiento de vivienda;\nVII. Facilitar a la mujer, adolescente o la niña, y en su caso a las víctimas indirectas en situación de violencia, la reubicación de domicilio, residencia o del centro educativo.\nTratándose de niñas víctimas de violencia, la autoridad en todo momento ponderará su interés superior, siendo la remisión a instituciones públicas de acogida la última opción y por el menor tiempo posible;\nVIII. Prohibición inmediata a la persona agresora de acercarse al domicilio y al de familiares y amistades, al lugar de trabajo, de estudios, o cualquier otro que frecuente la víctima directa o víctimas indirectas;\nIX. Reingreso de la mujer y en su caso a las víctimas indirectas en situación de violencia al domicilio, una vez que se salvaguarde su seguridad, en caso de que así lo desee.\nPara el cumplimiento de esta orden se garantizará el acompañamiento, del Ministerio Público y del personal de la policía ministerial o policía municipal, a la mujer en situación de violencia para acceder al domicilio, lugar de trabajo u otro, con el propósito de recuperar sus pertenencias personales y en su caso las de las víctimas indirectas, en cualquier caso, podrá ser acompañada de una persona de su confianza. En caso de que no haya personal ministerial disponible, el acompañamiento será a cargo de personal de cualquier institución de seguridad pública municipal que garantice la seguridad de la mujer.\nX. Protección policíaca permanente a la mujer, o la niña, así como a su familia y/o víctimas indirectas;\nXI. Protección por seguridad privada, en los casos que sea necesario;\nXII. Utilización de herramientas tecnológicas que permitan brindar seguridad a las mujeres, o niñas en situación de violencia; así como a las víctimas indirectas y testigos. Entre auxilio policial, entre otros;\nXIII. Solicitud a la autoridad judicial competente, la suspensión temporal a la persona agresora del régimen de visitas y convivencia con sus descendientes;\nXIV. Ordenar la entrega inmediata de objetos de uso personal y documentos de identidad a la mujer en situación de violencia, o niña, y en su caso a las víctimas indirectas;\nLey de Acceso de las Mujeres a una Vida Libre de Violencia Página 26\nXV. La prohibición a la persona agresora de comunicarse por cualquier medio o por interpósita persona, con la mujer en situación de violencia y, en su caso, de sus hijas e hijos u otras víctimas indirectas;\nXVI. Prohibición a la persona agresora de intimidar o molestar por si, por cualquier medio o interpósita persona, a la mujer en situación de violencia y en su caso sus hijas e hijos u otras víctimas indirectas o testigos de los hechos o cualquier otra persona con quien la mujer tenga una relación familiar, afectiva, de confianza o de hecho;\nXVII. Resguardar las armas de fuego u objetos utilizados para amenazar o agredir a la mujer, o niña, en situación de violencia;\nXVIII. Solicitar a la autoridad jurisdiccional competente, para garantizar las obligaciones alimentarias, la elaboración de un inventario de los bienes de la persona agresora y su embargo precautorio, el cual deberá inscribirse con carácter temporal en el\nRegistro Público de la Propiedad;\nFracción Reformada\nXIX. En casos de peligro inminente o extrema urgencia, el Ministerio Público bajo su más estricta responsabilidad, podrá determinar la desocupación inmediata por la persona agresora, del domicilio conyugal o de pareja, independientemente de la acreditación de propiedad o posesión del inmueble, aún en los casos de arrendamiento del mismo; y,\nFracción Adicionada\nXX. Además de los anteriores, aquellas y cuantas sean necesarias para salvaguardar la integridad, la seguridad y la vida de la mujer, adolescente o la niña en situación de violencia.\nFracción Recorrida\nLas medidas u órdenes de protección señaladas en este artículo podrán ser ampliadas o modificadas por la autoridad administrativa, el Ministerio Público o el órgano jurisdiccional competente, siempre procurando la mayor protección de la víctima.\nPárrafo Reformado\nArtículo Adicionado\nArtículo Reformado\nArtículo 26 QUINQUIES. Las medidas u órdenes de naturaleza jurisdiccional, además de las previstas en otros ordenamientos, podrán consistir en una o varias de las siguientes acciones:\nPárrafo Reformado\nI. La reserva del domicilio, lugar de trabajo, profesión o cualquier otro dato que permita que a la persona agresora o su familia puedan ubicar a la víctima;\nII. El uso de medios o dispositivos electrónicos para impedir el contacto directo de la persona agresora con la víctima;\nLey de Acceso de las Mujeres a una Vida Libre de Violencia Página 27\nIII. La recuperación y entrega inmediata a la mujer víctima, de sus hijas y/o hijos menores de 18 años y/o personas incapaces que requieren cuidados especiales, que hayan sido sustraídos, retenidos u ocultados de la madre en términos de lo establecido en el artículo\n6 fracción IX de la presente Ley;\nIV. Entrega inmediata de objetos de uso personal y documentos de identidad de la víctima y en su caso, de sus hijas e hijos;\nV. Medidas para evitar que se capten y/o se transmitan por cualquier medio o tecnologías de la información y la comunicación, imágenes de la mujer en situación de violencia que permitan su identificación o la de sus familiares. Tratándose de niñas hay una prohibición absoluta de transmitir datos e imágenes que permitan su identificación;\nVI. Prohibir el acceso a la persona agresora al domicilio, permanente o temporal de la mujer, adolescente o la niña, en situación de violencia, así como acercarse al lugar de trabajo, estudio o cualquier lugar que frecuente;\nVII. Embargo preventivo de bienes de la persona agresora, a efecto de garantizar las obligaciones alimentarias;\nVIII. La desocupación por la persona agresora, del domicilio conyugal o de pareja, independientemente de la acreditación de propiedad o posesión del inmueble, aún en los casos de arrendamiento del mismo, y en su caso el reingreso de la mujer en situación de violencia una vez que se resguarde su seguridad;\nIX. Obligación alimentaria provisional e inmediata;\nX. La notificación al superior jerárquico inmediato, cuando la persona agresora sea servidora pública y en el ejercicio de su cargo, comisión o servicio, se le involucre en un hecho de violencia contra las mujeres;\nEsta orden será emitida en todos los casos donde la persona agresora pertenezca a los cuerpos policiacos, militares o de seguridad, ya sea corporaciones públicas o privadas.\nXI. La obligación de la persona agresora de presentarse periódicamente ante el órgano jurisdiccional que emitió la orden;\nXII. La colocación de localizadores electrónicos, previo consentimiento de la persona agresora;\nXIII. La prohibición a la persona agresora de salir sin autorización judicial del país o del ámbito territorial que fije el juez o la jueza; y,\nXIV. Las demás que se requieran para brindar una protección a la víctima.\nArtículo Adicionado\nArtículo Reformado\nLey de Acceso de las Mujeres a una Vida Libre de Violencia Página 28\nArtículo 26 SEXIES. La tramitación y otorgamiento de una orden de protección podrá contener una o varias medidas, atendiendo al principio de integralidad. No se necesita una orden para cada medida, una sola orden de protección podrá concentrar el número de violencia y en su caso de las víctimas indirectas.\nArtículo Adicionado\nArtículo 26 SEPTIES. Las medidas u órdenes de protección deberán ser evaluadas para modificarse o adecuarse, en caso de que al momento de evaluar la efectividad de la orden se detecten irregularidades o incumplimiento, se sustanciará la comunicación correspondiente a los órganos internos de control de las dependencias involucradas.\nPárrafo Reformado\nPrevio a la suspensión de las medidas u órdenes de protección decretadas, las autoridades administrativas, ministeriales y órganos jurisdiccionales deberán asegurarse bajo su más estricta responsabilidad que la situación de riesgo o peligro de la víctima ha cesado, realizando una nueva evaluación de riesgo y analizando los informes de implementación por parte de las autoridades responsables de su cumplimiento.\nPárrafo Reformado\nArtículo Adicionado\nArtículo Reformado\nArtículo 26 OCTIES. En los casos donde la persona agresora pertenezca a los cuerpos policiacos, militares o de seguridad, ya sea de corporaciones públicas o privadas, la autoridad deberá retirar el arma de cargo o de cualquier otra que tenga registrada.\nArtículo Adicionado\nArtículo 26 NONIES. Al momento de dictarse sentencia las autoridades judiciales competentes determinarán las medidas u órdenes de protección que deban dictarse de manera temporal o durante el tiempo que dure la sentencia.\nPárrafo Reformado\nLas medidas u órdenes de protección podrán ser dictadas de oficio o a solicitud de la mujer en situación de violencia, de su representante legal o del Ministerio Público, tratándose de niñas víctimas de un delito, la autoridad judicial se encuentra obligada a hacer la determinación del interés superior de la niñez, a fin de dictar las medidas u órdenes de protección, aun cuando no exista una solicitud.\nPárrafo Reformado\nArtículo Adicionado\nArtículo Reformado\nArtículo 26 DECIES. Por ninguna circunstancia las autoridades administrativas, el agresora a través de la víctima. Cualquier notificación es responsabilidad exclusiva de la autoridad.\nLey de Acceso de las Mujeres a una Vida Libre de Violencia Página 29\nLas autoridades que intervengan en el cumplimiento de una orden, también serán las periódica.\nArtículo Adicionado\nArtículo 26 UNDECIES. A ninguna mujer, adolescente o niña; y sus hijas e hijos en situación de violencia, que solicite orden de protección se le podrá requerir que acredite su situación migratoria, ni cualquier otro elemento que impida su derecho al acceso a la justicia y la protección.\nArtículo Adicionado\nArtículo 26 DUODECIES. Las medidas u órdenes de protección deberán ser registradas en la Base Estatal de Datos e Información sobre Casos de Violencia contra las\nMujeres.\nArtículo Adicionado\nArtículo Reformado\nArtículo 26 TERDECIES. La Procuraduría de Protección de Niñas, Niños y\nAdolescentes del Estado deberá solicitar las medidas u órdenes de protección a las autoridades correspondientes de manera oficiosa de conformidad con las disposiciones normativas aplicables.\nPárrafo Reformado\nEn el caso de que las víctimas o víctimas indirectas sean personas menores de dieciocho años, las autoridades administrativas, el Ministerio Público o los órganos jurisdiccionales tendrán en cuenta los principios del interés superior de las niñas, niños y adolescentes, la prevalencia de sus derechos, su protección integral y los derechos consagrados en la Constitución, en los Tratados, así como los previstos en la Ley para la\nProtección y Defensa de los Derechos de Niñas, Niños y Adolescentes del Estado de Baja\nCalifornia y en la presente Ley.\nArtículo Adicionado\nArtículo Reformado\nArtículo 26 QUATERDECIES. En caso de que la persona agresora incumpla la medida u orden de protección, se emitirán las medidas de apremio conforme a la legislación aplicable.\nPárrafo Reformado\nAsimismo, se reforzarán las acciones que se contemplaron en un primer momento con la finalidad de salvaguardar la vida y seguridad de las mujeres, adolescentes y niñas.\nArtículo Adicionado\nArtículo Reformado\nCAPÍTULO IV\nREFUGIOS PARA VÍCTIMAS DE VIOLENCIA\nDenominación Modificada\nLey de Acceso de las Mujeres a una Vida Libre de Violencia Página 30 respectivas competencias, la creación de refugios seguros para las víctimas y víctimas indirectas de violencia.\nArtículo Reformado\nArtículo 28. Los Refugios son lugares temporales de seguridad para las víctimas y víctimas indirectas que funcionarán de forma ininterrumpida y permanente.\nPárrafo Adicionado, recorriéndose el subsecuente\nCorresponde a las personas responsables de los refugios desde la perspectiva de género, interseccionalidad y enfoque diferenciado:\nPárrafo Reformado\nI. Velar por la seguridad de las mujeres que se hospeden en ellos, y sus familias en su caso, por lo que no se podrá proporcionar su ubicación a personas no autorizadas para acudir a ellos;\nII. Proporcionar a las mujeres la atención necesaria para su recuperación y la asesoría psicológica que les permita participar plenamente en la vida pública, social y privada;\nIII. Dar información en formato accesible a las víctimas sobre las instituciones encargadas de prestar asesoría jurídica gratuita;\nFracción Reformada\nIV. Otorgarles de manera gratuita: alimentación, calzado, vestido y servicios médicos elementales;\nV. Proveer a las víctimas de la información necesaria que les permita decidir sobre las opciones de atención;\nVI. Contar con el personal debidamente capacitado y especializado en perspectiva de género y derechos humanos con enfoque diferenciado, intercultural e interseccional;\nFracción Reformada\nVII. Todas aquellas inherentes a la prevención, protección y atención de las personas que se encuentren en ellos;\nVIII. Contar con programas reeducativos integrales y de capacitación para que puedan adquirir conocimientos para el desempeño de una actividad laboral, y\nIX. Bolsa de trabajo, con la finalidad de que puedan tener una actividad laboral remunerada en caso de que lo soliciten.\nX. Implementar programas de capacitación para las víctimas, en los que se incluyan:\na) Cursos y talleres en materia de derechos humanos;\nb) Talleres orientados a la identificación y detección de todos los tipos y modalidades de violencia;\nLey de Acceso de las Mujeres a una Vida Libre de Violencia Página 31\nc) Cursos sobre generalidades y aspectos básicos del marco jurídico en materia de igualdad de género y prevención, atención y erradicación de violencia de género; y\nd) Talleres de motivación y superación personal. condiciones de accesibilidad necesarias para proporcionar atención, en igualdad de condiciones y sin discriminación, a las mujeres con discapacidad, incluyendo la posibilidad de contar con asistencia de personal de apoyo.\nPárrafo Adicionado\nArtículo Reformado\nArtículo 28 BIS. Los Refugios para estar en condiciones óptimas y garantizar la protección y respeto a los derechos humanos de las víctimas y las víctimas indirectas, deberán cumplir con lo siguiente:\nI. Instalaciones higiénicas;\nII. Áreas suficientes, iluminadas y ventiladas;\nIII. Áreas especiales para la atención de adolescentes, las niñas y los niños que acompañen a las víctimas;\nIV. Áreas especiales para la atención de adultos mayores y/o personas con discapacidad, que acompañen a las víctimas;\nV. Agua potable, luz eléctrica, lavabos y regaderas suficientes, red de agua caliente para baños;\nVI. Personal femenino en las áreas de trabajo social, psiquiátrica, jurídica, psicológica y medica;\nVII. Dormitorios con camas individuales o espacios para una familia integrada por una mujer y sus dependientes;\nVIII. Seguridad en el acceso a las instalaciones; y,\nIX. Personal capacitado que apliquen las Normas Oficiales Mexicanas relativas y vigentes a este este tipo de Refugios para la atención a víctimas de violencia.\nArtículo Adicionado\nArtículo 29. Los refugios deberán ser lugares seguros para las víctimas, por lo que no se podrá proporcionar su ubicación a personas no autorizadas para acudir a ellos.\nArtículo Reformado\nArtículo 29 BIS. La permanencia de las víctimas en los refugios no podrá ser mayor a tres meses, a menos de que persista su inestabilidad física, psicológica o su situación de\nLey de Acceso de las Mujeres a una Vida Libre de Violencia Página 32 riesgo, siendo sujetas a evaluación por el personal médico, psicológico y jurídico del refugio.\nEn ningún caso se podrá mantener a las víctimas en los refugios en contra de su voluntad.\nArtículo Adicionado\nArtículo 29 TER. Es obligación de las autoridades que emitan las medidas de personas agresoras para vigilar el debido cumplimiento de las medidas de protección impuestas.\nArtículo Adicionado\nArtículo 30. En el caso de la o las personas agresoras, éstos deberán participar obligatoriamente en los programas de reeducación integral, así como acatar cualquiera de las medidas de protección impuestas por la autoridad competente.\nArtículo Reformado\nTITULO TERCERO\nDEL SISTEMA ESTATAL, DEL PROGRAMA ESTATAL PARA PREVENIR,\nATENDER, SANCIONAR Y ERRADICAR LA VIOLENCIA\nCONTRA LAS MUJERES, Y DEL PROGRAMA INSTITUCIONAL\nEN BENEFICIO DE LAS MUJERES\nTítulo Adicionado\nDenominación del Título Modificado\nCAPÍTULO I\nDEL SISTEMA ESTATAL\nCapítulo Modificado, manteniendo la misma denominación\nArtículo 31. El Sistema Estatal es un mecanismo permanente a través del cual el\nGobierno del Estado y los Gobiernos Municipales coordinarán su integración y funcionamiento para la conjunción de esfuerzos, instrumentos, políticas, servicios y acciones interinstitucionales para la prevención, atención, sanción y erradicación de la violencia contra las mujeres, atendiendo lo estipulado en esta Ley y en la Ley General.\nArtículo Reformado\nArtículo 32. El Sistema estará integrado por las personas titulares de:\nPárrafo Reformado\nI. La Secretaría General de Gobierno, quien lo presidirá;\nII. La Secretaría de las Mujeres, que ejercerá las funciones de una Secretaría\nTécnica;\nFracción Reformada\nIII. Vocales, que serán las personas titulares de:\nPárrafo de la Fracción Reformado\na) La Secretaría de Bienestar;\nInciso Reformado\nLey de Acceso de las Mujeres a una Vida Libre de Violencia Página 33\nb) La Secretaría de Inclusión Social e Igualdad de Género.\nInciso Reformado\nc) La Fiscalía General del Estado.\nInciso Reformado\nd) El Sistema Estatal para el Desarrollo Integral de la Familia.\ne) La Secretaría de Educación.\nInciso Reformado\nf) La Secretaría de Salud.\ng) La Secretaría del Trabajo y Previsión Social.\nInciso Reformado\nh) La Secretaría de Cultura.\nInciso Reformado\ni) La Secretaría de Seguridad Ciudadana.\nInciso Adicionado, recorriéndose el subsecuente\nj) La Comisión Estatal de Derechos Humanos.\nInciso Reformado\nk) Centro de Justicia para las Mujeres del Estado de Baja California.\nInciso Adicionado\nIV. Los Gobiernos Municipales a través de su respectiva instancia de la mujer, o a falta de ésta, quien tenga a su cargo la implementación de mecanismos para el adelanto de las mujeres en la administración pública municipal.\nV. Una Diputada o Diputado del Poder Legislativo del Estado de Baja California, quien presida la Comisión encargada de la materia de Igualdad entre mujeres y hombres.\nFracción Reformada\nVI. Un Magistrado o Magistrada del Poder Judicial del Estado de Baja California, quien presida el Tribunal Superior de Justicia y el Consejo de la Judicatura.\nFracción Reformada\nVII. Una persona representante de la sociedad civil por cada Municipio, quienes participaran con voz y voto, quienes serán electos de acuerdo a la Reglamentación que para tal efecto emita el Ejecutivo Estatal.\nFracción Reformada\nVIII. La persona representante en el Estado de la Comisión Nacional para el Desarrollo de los Pueblos Indígenas.\nFracción Adicionada\nLey de Acceso de las Mujeres a una Vida Libre de Violencia Página 34\nIX. El Instituto Estatal Electoral.\nFracción Adicionada\nArtículo Reformado\nArtículo 33. Serán atribuciones del Sistema:\nI. Validar el Programa Estatal;\nII. Fomentar la coordinación, concertación, colaboración e información entre las instituciones estatales y municipales, públicas y privadas que se ocupen de la atención a cualquier modalidad de violencia contra las mujeres;\nIII. Promover la capacitación y sensibilización de las y los funcionarios de sistema judicial, de procuración de justicia, del policial, del sistema de salud y en general, de cualquiera que preste servicios relacionados con cualquier tipo o modalidad de violencia contra las mujeres, así como diseñar, aprobar e implementar la Estrategia de Capacitación\nObligatoria en materia de Género, de Prevención y Erradicación de la Violencia contra las\nMujeres y su programa en términos de la Ley de Capacitación en materia de Género, de\nPrevención y Erradicación de la Violencia hacia las Mujeres para el Estado de Baja California;\nFracción Reformada\nIII-A. Aplicar un enfoque de interseccionalidad para atender de forma holística y sistemática las diversas variables que generan violencia en contra de las mujeres;\nFracción Adicionada\nIV. Difundir los contenidos de esta Ley;\nV. Gestionar ante los medios de comunicación, a fin de que participen en la difusión de programas, campañas públicas encaminadas a sensibilizar y concientizar a la población sobre el problema de la violencia contra las mujeres, y las medidas para su prevención, sanción y erradicación;\nVI. Sesionar de forma ordinaria cada tres meses al año y, de forma extraordinaria a solicitud de la Presidencia, o por conducto de la mayoría de sus integrantes.\nFracción Adicionada\nVII. Una vez formulado e implementado el programa estatal, los titulares de las dependencias, entidades y demás organismos, que lo integran se reunirán cada tres meses con la finalidad de evaluar el cumplimiento de los objetivos del programa, y determinar conforme al resultado de la evaluación, las propuestas necesarias para el diseño e instrumentación eficientes de las políticas en materia de prevención, atención y erradicación de la violencia;\nFracción Recorrida y Reformada\nVIII. Proponer al Ejecutivo estatal su reglamento interno;\nFracción Recorrida y Reformada\nIX. Impulsar la formulación e implementación de protocolos para la prevención, actuación y erradicación de la violencia contra las mujeres, en dependencias, entidades estatales y municipales, órganos autónomos, y demás entes públicos; y, Ley de Acceso de las Mujeres a una Vida Libre de Violencia Página 35\nFracción Adicionada\nX. Remitir la información que corresponda para mantener actualizado el Registro y la\nBase Estatal.\nFracción Adicionada\nArtículo Reformado\nArtículo 34. Las particularidades del funcionamiento, organización y atribuciones de los integrantes del Sistema Estatal quedarán establecidas en el Reglamento que para tal efecto se dicte.\nCAPÍTULO II\nDEL PROGRAMA ESTATAL\nCapítulo Modificado, manteniendo la misma denominación\nArtículo 35. La Secretaría Técnica del Sistema Estatal propondrá para su validación al mismo, un Programa Estatal con perspectiva de género, que sea congruente con el Programa\nNacional y con el Plan Estatal de Desarrollo y los Municipales, respectivamente, teniendo como objetivos los siguientes:\nI. Fomentar, promover, respetar, proteger y garantizar el respeto a los derechos humanos de las mujeres establecidos en esta Ley y los Tratados Internacionales adoptados por nuestro país como obligatorios;\nFracción Reformada\nII. Transformar los modelos socioculturales de conducta de las mujeres y los hombres con la finalidad de prevenir, atender y erradicar las conductas estereotipadas que permiten, fomentan o toleran la violencia contra las mujeres;\nIII. Educar y capacitar en materia de derechos humanos de las mujeres, y los conceptos contenidos en esta Ley, a los servidores públicos relacionados con la atención a cualquier modalidad de violencia contra las mujeres, particularmente al personal encargando de la impartición de justicia, a fin de dotarles de instrumentos que permitan juzgar con perspectiva de género;\nIV. Ofrecer servicios gratuitos y especializados, por medio de las dependencias públicas, así como apoyar a las instituciones privadas, encargadas de la atención y protección de mujeres víctimas de violencia;\nV. Impulsar y apoyar programas de educación pública y privada, que se destinen a mujeres; interseccionalidad;\nFracción Reformada\nVII. Publicar semestralmente la información general y estadística desagregada y con\nLey de Acceso de las Mujeres a una Vida Libre de Violencia Página 36\nEstatal de Datos e Información sobre Casos de Violencia contra las Mujeres, misma que deberá ser remitida al Sistema Nacional;\nFracción Reformada\nVIII. Promover la cultura de denuncia de la violencia contra las mujeres en formatos accesibles;\nFracción Reformada\nIX. Diseñar un modelo integral, diferencial y especializado de atención a las mujeres víctimas de violencia, que deberán instrumentar el Centro de Justicia para las Mujeres del\nEstado de Baja California y las demás instituciones y los refugios que atiendan a víctimas;\nFracción Reformada\nX. Establecer procesos de evaluación de la eficacia de las acciones desarrolladas para prevenir, atender, sancionar y erradicar la violencia contra las mujeres;\nFracción Adicionada\nFracción Reformada\nXI. Realizar estudios sobre los efectos de la violencia y la discriminación interseccional en las mujeres y proponer políticas públicas dirigidas a eliminarlos; y,\nFracción Adicionada\nXII. Difundir la oferta institucional de servicios especializados que brinden los Centros de Justicia para las Mujeres.\nFracción Adicionada\nArtículo Reformado\nCAPÍTULO III\nDEL PROGRAMA INSTITUCIONAL EN BENEFICIO DE LAS MUJERES\nCapítulo Adicionado\nARTÍCULO 35 BIS.- El Programa Institucional en beneficio de las Mujeres, es el instrumento elaborado por la Secretaría de las Mujeres que contiene las acciones que, en forma planeada y coordinada, deberán realizarse en beneficio de las mujeres en las dependencias y entidades de la Administración Pública del Poder Ejecutivo, en los Poderes\nLegislativo y Judicial, y en los Órganos Autónomos.\nEl Programa se elaborará con base en programas relativos a la mujer que emanen de los Gobiernos Federal y Estatal en esta materia.\nArtículo Adicionado\nARTÍCULO 35 TER.- En la elaboración del Programa Institucional a que hace referencia el artículo anterior, la Secretaría de las Mujeres consultará a los sectores público, privado y social, tales como organizaciones no gubernamentales, asociaciones civiles e instituciones académicas y de investigación, así como a los municipios del Estado; de manera sociedad.\nArtículo Adicionado\nLey de Acceso de las Mujeres a una Vida Libre de Violencia Página 37\nTITULO CUARTO\nDE LA DISTRIBUCIÓN DE COMPETENCIAS\nTítulo Adicionado\nCAPÍTULO I\nGENERALIDAD DE COMPETENCIAS\nCapítulo y Denominación Modificados\nArtículo 36. Para la efectiva aplicación de la Ley, las dependencias, entidades del\nGobierno del Estado, el Poder Legislativo y el Judicial, y demás órganos, establecerán una coordinación con perspectiva de género, promoviendo la eficiencia en la prestación de sus servicios. Participarán las Secretarías General de Gobierno, Bienestar, Salud, Educación, Trabajo y Previsión Social, Cultura, Inclusión Social, Mujeres, Centro de Justicia para las\nMujeres del Estado de Baja California, la Secretaría de Seguridad Ciudadana, la Fiscalía\nGeneral del Estado, así como los Gobiernos Municipales del Estado.\nPárrafo Reformado\nA su vez deberán instrumentar y articular sus políticas públicas y acciones en concordancia con la política nacional integral desde la perspectiva de género para prevenir, atender, sancionar y erradicar la violencia contra las mujeres; integrar y coadyuvar en la adopción y consolidación del Sistema, impulsar la participación de las organizaciones sociales dedicadas a la promoción y defensa de los derechos humanos de las mujeres, en la ejecución de los programas estatales, además de recibir sus propuestas.\nPárrafo Adicionado\nArtículo Reformado\nArtículo 37. Los entes antes referidos, dentro del marco de sus atribuciones deberán trabajar de manera coordinada en la creación de programas interinstitucionales que promuevan la prevención y detección temprana de violencia a la mujer en cualquiera de las etapas de vida en las que se encuentren, así como establecer directrices para realizar acciones que puedan evitar la comisión de delitos y otros actos de violencia contra las mujeres, atendiendo a los posibles factores de riesgo, tanto en los ámbitos público y privado.\nPárrafo Reformado\nAdemás de ejercer sus facultades reglamentarias para la aplicación de la presente\nLey, deberán promover la elaboración y aplicación de protocolos especializados con perspectiva de género en la búsqueda inmediata de mujeres, niñas y adolescentes desaparecidas, para la investigación de los delitos de discriminación, feminicidio, trata de contra las mujeres.\nPárrafo Adicionado\nArtículo Reformado\nArtículo 37 BIS. La prevención es el conjunto de acciones que deberán llevar a cabo las dependencias, entidades y organismos estatales y municipales en el respectivo ámbito de\nLey de Acceso de las Mujeres a una Vida Libre de Violencia Página 38 mujeres, atendiendo a los posibles factores de riesgo tanto en los ámbitos público y privado.\nArtículo Adicionado\nArtículo 37 TER. La prevención comprende medidas generales y especiales, entre las que deberán privilegiarse las de carácter no penal.\nArtículo Adicionado\nArtículo 37 QUÁTER. Las medidas de prevención general, son aquellas que se dirigen a la colectividad y que desde los distintos ámbitos de acción las dependencias, entidades y organismos estatales y municipales pretenden evitar la comisión de conductas delictivas y otros actos de violencia contra la mujer.\nArtículo Adicionado\nArtículo 37 QUINQUIES. Se considerarán como medidas especiales de prevención aquellas que implementen las dependencias, entidades y organismos estatales y municipal, en el respectivo ámbito de sus competencias, que permitan a las mujeres embarazadas, con alguna discapacidad, de la tercera edad o que se encuentren en cualquier otra condición de vulnerabilidad, el establecimiento de acciones obligatorias para que gocen de las siguientes facilidades:\nI. Contar con una atención preferente, ágil, pronta y expedita cunado se encuentren realizando algún trámite o solicitando algún servicio; y,\nII. Ser atendidas con prontitud y diligencia cuando estén solicitando ante cualquier autoridad auxilio por ser víctimas de violencia.\nArtículo Adicionado\nCAPÍTULO II\nDEL PODER EJECUTIVO DEL ESTADO\nCapítulo Adicionado\nArtículo 38. Compete al Poder Ejecutivo del Estado a través de sus diferentes\nDependencias y Entidades:\nI. Formular, instrumentar, articular y conducir la política integral estatal en materia de violencia contra las mujeres, desde la perspectiva de género;\nII. Aplicar el Programa Estatal a que se refiere la presente Ley, vinculando todos las tengan competencia en la materia;\nIII. Vigilar el cumplimiento de la presente Ley, así como de los Instrumentos\nInternacionales en la materia y demás normatividad aplicable en el Estado de Baja California;\nIV. Garantizar el ejercicio pleno del derecho de las mujeres a una vida libre de violencia;\nLey de Acceso de las Mujeres a una Vida Libre de Violencia Página 39\nV. Favorecer la creación de programas de reeducación con perspectiva de género, para quienes agreden a las mujeres en el ámbito familiar;\nVI. Garantizar el ejercicio pleno de los derechos de las mujeres indígenas a una vida libre de violencia, con base en el reconocimiento de la composición pluricultural de Baja\nCalifornia;\nVII. Impulsar acuerdos interinstitucionales de coordinación entre las diferentes\nDependencias y Entidades de la Administración Pública del Estado, para lograr la atención integral de las mujeres víctimas de violencia;\nVIII. Recibir de las organizaciones privadas, las propuestas y recomendaciones sobre la prevención, atención y sanción de la violencia contra las mujeres, a fin de mejorar los mecanismos para su erradicación;\nIX. Celebrar convenios de cooperación, coordinación y concertación así como adherirse a acuerdos en materia de discriminación y violencia de género;\nX. Impulsar la creación de refugios para las mujeres víctimas de violencia, conforme al modelo diseñado por el Sistema Estatal;\nXI. Difundir el contenido de esta Ley;\nXII. Coadyuvar con la Federación y los Gobiernos Municipales para el cumplimiento de los objetivos de la Ley General y la presente Ley;\nXIII. La capacitación del personal a su cargo en materia de derechos de las mujeres, políticas de prevención, atención, sanción y erradicación de la violencia contra las mujeres;\nXIV. Proveer de los recursos presupuestarios, humanos y materiales a las entidades de la Administración Pública Estatal que integran el Sistema, en concordancia con el\nPrograma Estatal;\nFracción Reformada\nXV. Crear, operar, organizar, implementar, gestionar, actualizar, monitorear y evaluar el Registro Público de Agresores Sexuales, conforme a su reglamento, en colaboración con el\nPoder Judicial del Estado;\nFracción Adicionada\nFracción Reformada\nXVI. Emitir la información general y estadística sobre los casos de violencia contra las mujeres en los términos dispuestos en la presente Ley, para integrar la Base Estatal;\nFracción Adicionada\nXVII. Impulsar la creación y equipamiento de los Centros de Justicia para las Mujeres de Baja California;\nFracción Adicionada\nXVIII. Certificar a los Centros de Justicia para las Mujeres de Baja California; y,\nFracción Adicionada\nLey de Acceso de las Mujeres a una Vida Libre de Violencia Página 40\nXIX. Todas aquellas que se requieran para tener un Estado libre de violencia de género, en cumplimiento de la presente Ley y las demás disposiciones vigentes.\nFracción Recorrida y Reformada\nArtículo Reformado\nArtículo 38 BIS. Las Organizaciones de la Sociedad Civil especializadas en atención a mujeres víctimas de violencia, deberán proporcionar datos obtenidos de la atención que presenten en Refugios y Centros, los cuales la Secretaría de las Mujeres en coordinación con la Secretaría de Seguridad Ciudadana valorarán y analizarán para remitir la información que deba integrarse a la Base Estatal.\nPárrafo Reformado\nLas Organizaciones de la Sociedad Civil especializadas en atención a mujeres víctimas de violencia, podrán proporcionar datos obtenidos de la atención que presenten en sus centros, los cuales la Secretaría de Seguridad Pública valorará y de ser necesario los ingresará e integrará a la base de datos que se refiere la fracción III del artículo 38 Bis de esta Ley.\nArtículo Adicionado\nArtículo Reformado\nArtículo 39. Corresponderá a la Secretaría de Educación, en su ámbito de acción, el implementar en la política educativa del Estado, los principios de igualdad, equidad y no discriminación entre mujeres y hombres y el respeto pleno de los derechos humanos. Así como el desarrollo de programas educativos que promuevan la cultura de una vida libre de violencia contra las mujeres, buscando la erradicación de la violencia docente.\nAsimismo, la Secretaría de Educación deberá eliminar de los programas educativos estatales los materiales que hagan apología de la violencia contra las mujeres o contribuyan a la promoción de estereotipos que discriminen y fomenten la desigualdad entre mujeres y hombres.\nPárrafo Adicionado\nArtículo Reformado\nArtículo 40. Corresponderá a la Secretaría del Trabajo y Previsión Social el formular y ejecutar políticas y programas de promoción de los derechos humanos de las mujeres y el desarrollo integral de sus capacidades y habilidades en su desempeño laboral. Incorporando en la supervisión de las condiciones laborales de los centros de trabajo, la vigilancia en el cumplimiento de las normas en materia de igualdad de oportunidades, de trato y no discriminación en el acceso al empleo, capacitación, ascenso y permanencia de las mujeres, brecha salarial de género, a efecto de promover su erradicación.\nArtículo Reformado\nArtículo 41. Corresponderá a la Secretaría de Salud:\nLey de Acceso de las Mujeres a una Vida Libre de Violencia Página 41\nI. En el marco de la política de salud integral de las mujeres, diseñar con perspectiva de género e inclusión, la política de prevención, atención y erradicación de la violencia en su contra, para lo cual tomará en cuenta la información contenida en el Registro Nacional;\nFracción Reformada\nII. Brindar por medio de las instituciones del sector salud de manera integral e interdisciplinaria atención médica y psicológica con perspectiva de género a las víctimas y víctimas indirectas;\nIII. Crear programas de capacitación para el personal del sector salud, respecto de la violencia contra las mujeres y se garanticen la atención a las víctimas y la aplicación de las\nNormas Oficiales Mexicanas vigentes en la materia;\nIV. Establecer programas y servicios profesionales y eficaces, en las dependencias públicas relacionadas con la atención de la violencia contra las mujeres;\nV. Brindar servicios reeducativos integrales a las víctimas y a los agresores, a fin de que logren estar en condiciones de participar plenamente en la vida pública, social y privada;\nVI. Difundir en las instituciones del sector salud, material referente a la prevención y atención de la violencia contra las mujeres;\nVII. Canalizar a las víctimas a las instituciones que prestan atención y protección a las mujeres;\nVIII. Mejorar la calidad de la atención, que se preste a las mujeres víctimas;\nIX. Participar activamente, en la ejecución del Programa, en el diseño de nuevos modelos de prevención, atención y erradicación de la violencia contra las mujeres, en colaboración con las demás autoridades encargadas de la aplicación de la presente ley;\nX. Asegurar que en la prestación de los servicios del sector salud sean respetados los derechos humanos de las mujeres;\nXI. Capacitar al personal del sector salud, con la finalidad de que detecten la violencia contra las mujeres;\nXII. Apoyar a las autoridades encargadas de efectuar investigaciones en materia de violencia contra las mujeres, proporcionando la siguiente información:\na) La relativa al número de víctimas que se atiendan en los centros y servicios hospitalarios;\nb) La referente a las situaciones de violencia que sufren las mujeres;\nc) El tipo de violencia por la cual se atendió a la víctima;\nLey de Acceso de las Mujeres a una Vida Libre de Violencia Página 42\nd) Los efectos causados por la violencia en las mujeres, y,\ne) Los recursos erogados en la atención de las víctimas.\nXIII. Celebrar convenios de cooperación, coordinación y concertación en la materia; y,\nXIV. Las demás previstas para el cumplimiento de la presente ley.\nArtículo Reformado\nArtículo 41 BIS. Corresponderá a la Secretaría de Salud del Estado garantizar el acceso gratuito a productos de gestión menstrual.\nArtículo Adicionado\nArtículo 42. Corresponderá a la Fiscalía General del Estado:\nPárrafo Reformado\nI. Diseñar la política en materia de procuración de justicia para la prevención, atención, sanción y erradicación de la violencia contra las mujeres;\nII. Especializar a las y los agentes del Ministerio Público, peritos, personal que atiende a víctimas a través de programas y cursos permanentes en:\na) Derechos humanos y género;\nb) Perspectiva de género para la debida diligencia en la conducción de averiguaciones previas y procesos judiciales relacionados con discriminación, violencia y feminicidio;\nc) Incorporación de la perspectiva de género en los servicios periciales;\nd) Eliminación de estereotipos sobre el rol social de las mujeres, entre otros.\nFracción Reformada\nIII. Dictar en el ámbito de su competencia, las órdenes de protección a favor de las víctimas y víctimas indirectas de violencia, a fin de que éstas no sigan expuestas a esa situación y reciban oportunamente la atención y tratamiento requerido;\nFracción Reformada\nIV. Proporcionar a las víctimas información objetiva que les permita ubicar su situación real y las opciones con que cuentan, así como las dependencias que pueden brindarles atención;\nV. Promover la cultura del respeto a los derechos procesales de las mujeres, y relacionado con la violencia de género;\nVI. Crear unidades especializadas de acuerdo al tipo de victimización de la mujer, evitando las prácticas de mediación o conciliación;\nLey de Acceso de las Mujeres a una Vida Libre de Violencia Página 43\nVII. Celebrar convenios de cooperación, coordinación y concertación en la materia,\nVIII. Crear un registro público sistemático de los delitos cometidos en contra de mujeres, que incluya la clasificación de los hechos de los que tenga conocimiento, lugar de ocurrencia y lugar de hallazgo de los cuerpos, características sociodemográficas de las víctimas y del sujeto activo, especificando su tipología, relación entre el sujeto activo y pasivo, móviles, diligencias básicas a realizar, así como las dificultades para la práctica de diligencias y determinaciones; los índices de incidencia y reincidencia, judicialización, estado procesal, sanción y reparación del daño. Este registro se integrará a la estadística criminal y victimal para definir políticas en materia de prevención del delito, procuración y administración de justicia, el cual deberá actualizarse y ser accesible en el portal electrónico de la Fiscalía. El registro deberá contener también los efectos que los hechos violentos produjeron en las víctimas, el fallecimiento o, en su caso, la discapacidad permanente;\nFracción Reformada\nIX. Integrar, administrar, operar y mantener actualizada la Base Estatal de Datos e\nInformación sobre Casos de Violencia contra las Mujeres;\nFracción Reformada\nX. Capacitar al personal del cuerpo de policía estatal y promover la capacitación de los cuerpos municipales en cuanto a la atención de casos de violencia en contra de las mujeres;\nFracción Reformada\nXI. Proporcionar la información que soliciten a través de los portales de acceso a la información pública, en términos de lo dispuesto por la Ley de Transparencia y Acceso a la\nInformación Pública para el Estado de Baja California;\nFracción Reformada\nXII. Diseñar, con una visión transversal e interseccional, la política integral con perspectiva de protección a la mujer orientada a la prevención, atención, sanción y erradicación de los delitos violentos contra las mujeres;\nFracción Reformada\nXIII. Elaborar e instrumentar en coordinación con la Secretaría de Seguridad\nCiudadana, acciones de política criminal que incidan en la prevención de la violencia contra las mujeres, dando prioridad a las zonas de mayor incidencia delictiva y en donde residen mayor número de personas inscritas en el Registro y en la Base Estatal;\nFracción Adicionada\nFracción Reformada\nXIV. Cumplir con las facultades y responsabilidades que le correspondan y que se derivan de la operación del Registro Nacional, en términos de lo dispuesto en la Ley General\nVida Libre de Violencia; y,\nFracción Adicionada\nXV. Las demás que determinen las leyes.\nFracción Recorrida\nLey de Acceso de las Mujeres a una Vida Libre de Violencia Página 44\nArtículo Reformado\nArtículo 43. A la Secretaría de las Mujeres del Estado de Baja California, le corresponderá:\nPárrafo Reformado\nI. La elaboración del Programa Estatal, que deberá ser sometido a consideración del\nSistema;\nII. Diseñar la política transversal en el estado, para que todas las Dependencias de\nGobierno adopten la perspectiva de género;\nII-A. Elaborar estudios bajo el enfoque de interseccionalidad que permitan el entendimiento sistemático de las múltiples causas que generan violencia hacia la mujer.\nFracción Adicionada\nIII. Asesorar al Sistema en el proceso de validación y seguimiento al cumplimiento del\nPrograma para Prevenir, Atender, Sancionar y Erradicar la Violencia contra las Mujeres;\nIV. Fungir como Secretaria Técnica del Sistema;\nV. Representar al Sistema ante el Sistema Nacional;\nVI. Promover la capacitación y especialización de las y los servidores públicos del\nGobierno del Estado en perspectiva de género y derechos humanos de las mujeres;\nVII. Realizar diagnósticos, investigaciones, estudios e informes sobre el cumplimiento de los objetivos de esta Ley;\nVIII. Integrar un registro de los programas y subprogramas estatales que contemplen acciones de prevención, atención, sanción y erradicación de la violencia, en coordinación con las dependencias y entidades de la Administración Pública Estatal, y recibir los de los Municipios;\nIX. Colaborar con las dependencias, entidades e instituciones del Estado, de igual forma, con las instancias de la mujer municipales, para diseñar, ejecutar y evaluar modelos de atención a las mujeres víctimas de violencia;\nX. Promover que las víctimas de violencia reciban servicios de educación y capacitación para el fortalecimiento de sus habilidades y desarrollo personal;\nXI. Impulsar la armonización normativa en materia de violencia de género, en concordancia con los instrumentos nacionales e internacionales;\nXII. Establecer los indicadores para la evaluación de la Administración Pública Estatal y sus servidores públicos en materia de discriminación y violencia de género;\nXIII. Promover una imagen de las mujeres, libre de prejuicios y estereotipos, así como la eliminación del lenguaje sexista y/o misógino;\nXIV. Impulsar la creación de refugios para víctimas directas e indirectas de cualquier modalidad de violencia, en especial la familiar, con los tipos que ésta implique;\nLey de Acceso de las Mujeres a una Vida Libre de Violencia Página 45\nXV. Fortalecer los refugios existentes de atención para víctimas directas e indirectas de cualquier modalidad de violencia, con los tipos que ésta implique;\nXVI. Celebrar convenios de cooperación, coordinación y concertación con empresas, organizaciones patronales y sindicatos, para promover los derechos de las mujeres en los ámbitos público y privado;\nXVII. Impulsar la creación de unidades o módulos especializados de atención y protección a las víctimas de violencia;\nFracción Reformada\nXVIII. Conforme a lo previsto por la Ley General, dar seguimiento a las solicitudes de alerta de violencia de género; y,\nFracción Reformada\nXIX. Difundir información sobre el funcionamiento y aprovechamiento del Registro\nNacional, así como cumplir con las facultades y responsabilidades que le correspondan y que se derivan de la operación del Registro Nacional, en términos de lo dispuesto en la Ley\nGeneral del Sistema Nacional de Seguridad Pública y la Ley General de Acceso de las\nMujeres a una Vida Libre de Violencia\nFracción Adiciona\nArtículo Reformado\nArtículo 44. Corresponderá a la Secretaría de Cultura de Baja California, el formular, coordinar y ejecutar políticas de promoción de los derechos humanos de las mujeres, a través de las diferentes manifestaciones culturales y artísticas. Así como diseñar y promover campañas de información sobre los tipos y modalidades de la violencia contra las mujeres, y las dependencias y entidades que la atienden.\nArtículo Reformado\nArtículo 44 BIS. Corresponderá a la Secretaría de Integración y Bienestar Social, en su ámbito de competencia, fomentar el desarrollo social utilizando las herramientas necesarias para proteger de manera integral los derechos fundamentales de las mujeres, garantizarles una vida libre de violencia promoviendo su plena participación en todos los ámbitos de la vida buscando que mejoren las condiciones de aquellas que se encuentra en situación de exclusión y pobreza.\nArtículo Adicionado\nArtículo Reformado\nArtículo 44 TER. Corresponde al Instituto Estatal Electoral del Estado, en el ámbito de sus competencias:\nI. Promover la cultura de la no violencia en el marco del ejercicio de los derechos políticos y electorales de las mujeres;\nII. Incorporar la perspectiva de género al monitoreo de las transmisiones sobre las noticias, durante los procesos electorales, y\nLey de Acceso de las Mujeres a una Vida Libre de Violencia Página 46\nIII. Sancionar, de acuerdo con la normatividad aplicable, las conductas que constituyan violencia política contra las mujeres en razón de género.\nArtículo Adicionado\nArtículo 44 QUATER. Corresponde a la Secretaría de Seguridad Ciudadana, en el ámbito de sus competencias:\nI. Intervenir en la atención y prevención de la violencia contra la mujer, debiendo atender los llamados de auxilio que tenga conocimiento de los actos de violencia, canalizando a las víctimas, víctimas indirectas y agresores de violencia contra la mujer;\nII. Establecer programas de capacitación continua para el personal de las corporaciones que atiendan los hechos derivados de la violencia contra la mujer, desde las perspectivas de género, derechos humanos, diferencial, interseccionalidad e interculturalidad;\nFracción Reformada\nIII. Monitorear en coordinación de las Instituciones, dependencias y entidades estatales y municipales de Seguridad el cumplimiento de las órdenes de protección que son emitidas por dichas instituciones;\nIV. Crear mecanismos de coordinación y colaboración con las dependencias encargadas de la seguridad pública en los municipios del Estado que coadyuven en la ejecución de las medidas que garanticen la seguridad de las víctimas;\nV. Elaborar e instrumentar en coordinación con la Fiscalía General del Estado, acciones de política criminal que incidan en la prevención de la violencia contra las mujeres, cometidos en los ámbitos público y privado, con perspectivas de género, derechos humanos, diferencial, interseccionalidad e interculturalidad dando prioridad a las zonas de mayor incidencia delictiva y en donde residen mayor número de personas inscritas en el Registro y en la Base Estatal;\nFracción Reformada\nVI. Recibir de las organizaciones no gubernamentales, civiles y sociales, propuestas y recomendaciones sobre la prevención, atención, sanción y erradicación de la violencia contra las mujeres, a fin de mejorar los mecanismos para su erradicación.\nLa Secretaría de Seguridad Ciudadana, analizará en conjunto con el Instituto de la\nMujer para el Estado, la información proporcionada, para su debida remisión a la Base\nEstatal.\nVII. Diseñar y establecer, un modelo de seguridad, basado en igualdad con perspectiva de género, para atender a víctimas, así como las estrategias de proximidad policial a que haya lugar;\nFracción Reformada\nLey de Acceso de las Mujeres a una Vida Libre de Violencia Página 47\nVIII. Realizar una página de Internet específica en la cual se encuentren los datos generales de las mujeres, adolescentes y niñas que sean reportadas como desaparecidas. La información sobre el paradero de las mujeres, adolescentes y niñas desaparecidas. Esta página deberá actualizarse de forma permanente;\nFracción Adicionada\nIX. Aplicar ajustes de procedimiento, en su caso, para recabar las denuncias y testimonios de las mujeres con discapacidad víctimas de violencia;\nFracción Adicionada\nFracción Reformada\nX. Implementar de manera directa e inmediata dentro de su ámbito competencial, las medidas u órdenes de protección necesarias para salvaguardar la vida, integridad, libertad y seguridad de las víctimas, sin condicionarlas a la presentación de una denuncia o querella.\nTratándose de delitos relacionados con violencia de género contra las mujeres, la información deberá incorporarse al Registro Nacional;\nFracción Adicionada\nXI. Coadyuvar con la Secretaría de las Mujeres para el cumplimiento de las funciones previstas con relación al Registro Nacional;\nFracción Adicionada\nXII. Integrar, procesar y actualizar la información para el Registro Nacional, en términos que establezcan los lineamientos correspondientes; y,\nFracción Adicionada\nXIII. Las demás que le atribuyan otros ordenamientos legales en materia.\nFracción Recorrida\nArtículo Adicionado\nArtículo Reformado\nArtículo 44 QUINQUIES. Los servicios a cargo del Centro de Justicia para las Mujeres de Baja California, se brindarán a través de la participación coordinada de las autoridades estatales, dependencias, entidades y unidades administrativas de la administración pública cuya competencia incida en la atención integral a mujeres víctimas de violencia, y previa firma de los convenios correspondientes, con autoridades federales y municipales.\nPárrafo Reformado\nLas dependencias, entidades y unidades administrativas estatales que en el ámbito de los Centros de Justicia para las Mujeres para tales fines, serán como mínimo las siguientes:\nPárrafo con sus Fracciones Adicionado\nI. Secretaría General de Gobierno;\nII. Secretaría de Seguridad Ciudadana;\nLey de Acceso de las Mujeres a una Vida Libre de Violencia Página 48\nIII. Secretaría de Salud;\nIV. Secretaría de Trabajo y Previsión Social;\nV. Secretaría de Educación;\nVI. Secretaría de Economía e Innovación;\nVII. Secretaría de Inclusión Social e Igualdad de Género;\nVIII. Sistema para el Desarrollo Integral de la Familia;\nIX. Instituto de la Mujer para el Estado de Baja California;\nX. Instituto de la Juventud;\nXI. Comisión Ejecutiva Estatal de Atención Integral a Víctimas;\nXII. Procuraduría de Protección de Niñas, Niños y Adolescentes del Estado; y,\nXIII. Defensoría Pública del Estado de Baja California.\nSe celebrarán convenios de colaboración con la Fiscalía General del Estado, Poder\nJudicial del Estado, otros órganos autónomos estatales y organizaciones de la sociedad civil, a fin de brindar servicios interinstitucionales, especializados y de calidad, desde los enfoques de género, intercultural, diferencial e interseccional.\nPárrafo Adicionado\nArtículo Adicionado\nArtículo Reformado\nCAPÍTULO III\nDEL PODER LEGISLATIVO\nCapítulo y Denominación Modificados\nArtículo 45. Compete al Poder Legislativo:\nI. Observar el debido cumplimiento de la presente Ley dentro de su ámbito de competencia;\nII. Celebrar convenios de cooperación, coordinación y concertación así como adherirse\nPoderes del Estado;\nIII. Realizar las acciones legislativas encaminadas a dar mayor diligencia a las iniciativas de ley que estén encaminadas a armonizar la legislación estatal, de acuerdo a lo previsto en esta Ley;\nLey de Acceso de las Mujeres a una Vida Libre de Violencia Página 49\nIV. Aprobar el presupuesto necesario para garantizar el cumplimiento de las acciones contenidas en el Programa Estatal para Prevenir, Atender, Sancionar y Erradicar la Violencia contra las Mujeres en el Estado, y\nV. Todas aquellas que se requieran en el ámbito de sus facultades o competencias para tener un Estado libre de violencia de género.\nCAPÍTULO IV\nDEL PODER JUDICIAL\nCapítulo Adicionado\nArtículo 46. El Poder Judicial observará el debido cumplimiento de la Ley, dentro de su ámbito de competencia, teniendo a su cargo las acciones necesarias para tramitar y emitir con celeridad institucional las medidas de protección en materia civil, familiar o penal que se requieran, además:\nPárrafo Reformado\nI. Capacitar y especializar a su personal en materia de derechos humanos de las mujeres, construyendo una cultura libre de conductas misóginas;\nII. Diseñar y promover campañas de información para el personal, sobre los tipos y modalidades de la violencia contra las mujeres;\nIII. Celebrar convenios de cooperación, coordinación y concertación así como adherirse a protocolos y acuerdos en la materia de discriminación y violencia de género con los demás Poderes del Estado;\nIV. Realizar acciones pertinentes para dar celeridad en la aplicación de las ordenes de protección en los casos en los que sea necesario;\nV. Fomentar el desarrollo social, desde la visión de protección integral de los derechos humanos de las mujeres;\nVI. Generar mecanismos, y promover su implementación, para la detección de violencia contra las mujeres;\nFracción Reformada\nVII. Coadyuvar en todo lo necesario con la autoridad administrativa del Poder Ejecutivo del Gobierno del Estado, para la debida implementación y operación del Registro Público de\nAgresores Sexuales;\nFracción Adicionada\nFracción Reformada\nVIII. Remitir a la Fiscalía General del Estado en los términos dispuesto por esta ley la información respecto al otorgamiento de órdenes de protección, para que sean registradas en la Base Estatal; y,\nFracción Adicionada\nIX. Las demás que le atribuyan otros ordenamientos legales.\nFracción Recorrida\nLey de Acceso de las Mujeres a una Vida Libre de Violencia Página 50\nArtículo Reformado\nCAPÍTULO V\nDE LOS MUNICIPIOS\nCapítulo Modificado, manteniendo la misma denominación\nArtículo 47. Corresponde a los municipios de Baja California de conformidad con esta\nLey y la demás normatividad en la materia, acorde con la perspectiva de género, las siguientes atribuciones:\nPárrafo Reformado\nI. Observar el debido cumplimiento de la presente Ley dentro de su ámbito de competencia;\nII. Instrumentar una política transversal e interseccional, para que todas sus dependencias y paramunicipales adopten la perspectiva de género;\nFracción Reformada\nIII. Implementar políticas acordes a erradicar, atender y prevenir la violencia en contra de las mujeres, en concordancia con el programa integral y el programa estatal;\nIV. Participar en el Sistema para Prevenir, Atender, Sancionar y Erradicar la Violencia contra las Mujeres, coadyuvando con las acciones que se lleven a cabo para la consolidación del programa estatal;\nV. Promover que el personal que labora en el Municipio, y que atiende a mujeres víctimas de violencia, tome cursos de capacitación respecto a la violencia de género y los derechos fundamentales de las mujeres;\nVI. Expedir a través de sus Jueces Municipales las órdenes de protección de conformidad a lo que establece el capítulo III, del Título Segundo de esta ley; mismas que podrán ser ejecutadas por las Instituciones de Seguridad Pública Municipal.\nFracción Reformada\nVII. Apoyar la creación de programas de reeducación integral para los agresores;\nVIII. Promover programas educativos sobre la igualdad y la equidad entre los géneros para eliminar la violencia contra las mujeres;\nIX. De acuerdo a su capacidad presupuestal, impulsar la creación de refugios seguros para las víctimas;\nX. Apoyar, con los estímulos posibles, a los refugios privados que para proteger a las víctimas directas e indirectas de violencia que existan en su municipio;\nLey de Acceso de las Mujeres a una Vida Libre de Violencia Página 51\nXI. Llevar a cabo, de acuerdo con el programa estatal, jornadas de información a la población respecto de la violencia contra las mujeres;\nXII. Contar con unidades especializadas para la atención a víctimas de cualquier tipo de violencia;\nXIII. Capacitar a sus fuerzas policíacas con perspectiva de género y sobre los derechos humanos de las mujeres;\nXIV. Realizar una evaluación de su reglamentación en materia de género y promover su adecuación y armonización con esta Ley y demás disposiciones aplicables;\nXV. Celebrar convenios de cooperación, coordinación y concertación en la materia;\nFracción Reformada\nXVI. Realizar las acciones necesarias para implementar las medidas establecidas en la\nAlerta de Violencia de Género contra las mujeres;\nFracción Adicionada\nFracción Reformada\nXVII. Cumplir con las facultades y responsabilidades que le correspondan y que se derivan de la operación del Registro Nacional, en términos de lo dispuesto en la Ley General del\nSistema Nacional de Seguridad Pública y la Ley General de Acceso de las Mujeres a una\nVida Libre de Violencia; y,\nFracción Adicionada\nXVIII. La atención de los demás asuntos que en materia de prevención, atención, sanción o erradicación de la violencia contra las mujeres que les conceda la Ley y su reglamentación interior.\nFracción Recorrida\nArtículo Reformado\nTITULO QUINTO\nDE LAS RESPONSABILIDADES Y SANCIONES,\nDEL REGISTRO PÚBLICO DE AGRESORES SEXUALES\nTítulo Adicionado\nCAPÍTULO I\nDE LAS RESPONSABILIDADES Y SANCIONES\nCapítulo Adicionado\nCapítulo Modificado, manteniendo la misma denominación\nArtículo 48.- Será causa de responsabilidad administrativa el incumplimiento de esta\nLey y se sancionará conforme a las leyes en la materia.\nArtículo Adicionado\nCAPÍTULO II\nLey de Acceso de las Mujeres a una Vida Libre de Violencia Página 52\nDEL REGISTRO PÚBLICO DE AGRESORES SEXUALES\nCapítulo Adicionado\nCapítulo Modificado, manteniendo la misma denominación\nArtículo 49.- El Registro Público de Agresores Sexuales es un mecanismo de personas condenadas con sentencia firme por delitos de violación, abuso sexual, corrupción de menores, estupro, acoso sexual, hostigamiento sexual, pederastia, pornografía, turismo sexual, lenocinio y contra la intimidad y la imagen, en cualquiera de sus modalidades, tipos o subtipos, previstos todos en el Código Penal para el Estado de Baja California.\nPárrafo Reformado\nEl Registro Público de Agresores Sexuales, estará a cargo y bajo la operación de la\nSecretaría General de Gobierno, en colaboración con el Poder Judicial del Estado.\nLa información que genere dicho registro se referirá a personas condenadas en el\nEstado de Baja California y en su caso, en el extranjero o en otras entidades federativas, de conformidad con los convenios que al efecto realice la Secretaría General de Gobierno.\nLa inscripción en el Registro Público de Agresores Sexuales será por un periodo igual al que dure su condena, en ningún caso podrá ser superior.\nArtículo Adicionado\nArtículo 50.- La autoridad jurisdiccional competente deberá notificar a la Secretaría\nGeneral del Gobierno sobre las personas agresoras sexuales que tengan sentencia firme por alguno de los delitos mencionados en el artículo anterior. También, notificarán los mecanismos de aceleración procesal que se hayan ejercido, beneficios preliberacionales y en general, cualquier resolución judicial que modifique su situación jurídica.\nLa Secretaría General de Gobierno procederá a integrar una ficha pública que deberá contener:\nI. Nombre completo;\nII. Apodos o alias;\nIII. Nacionalidad;\nIV. Fotografía actual de la persona agresora;\nV. Delito o delitos por el que fue condenado;\nVI. Pena privativa de libertad;\nVII. Fecha de nacimiento;\nVIII. Lugar de nacimiento; y,\nIX. CURP.\nArtículo Adicionado\nLey de Acceso de las Mujeres a una Vida Libre de Violencia Página 53\nArtículo 51.- El Registro Público de Agresores Sexuales, será actualizado de manera competente, quien tendrá a la responsabilidad de notificar a la Secretaría General de\nGobierno acerca de las personas que cuenten con sentencia firme.\nEl Registro Público de Agresores Sexuales, podrá ser consultado por cualquier persona con plena capacidad de ejercicio, siempre que se demuestre el interés legitimo para acceder a éste y trate de prevenir o atender actos relacionados con violencia sexual. Para tal efecto, la Secretaría General de Gobierno fijará en el reglamento correspondiente los criterios y requisitos de acceso, observando en todo momento las disposiciones normativas aplicables al derecho de acceso a la información pública y la protección de datos personales.\nArtículo Adicionado\nARTICULOS TRANSITORIOS\nPRIMERO. El presente Decreto entrará en vigor al día siguiente de su publicación en el Periódico Oficial del Estado de Baja California.\nSEGUNDO. A partir de la entrada en vigor de la presente Ley, para la debida instrumentación de las órdenes de protección, de emergencia y preventivas, se deberá adecuar el marco legal que rige al Poder Judicial y las demás Dependencias responsables de su aplicación.\nTERCERO. A partir de la entrada en vigor del presente Decreto, el Ejecutivo Estatal deberá emitir, en un plazo no mayor a ciento veinte días naturales, el Reglamento de la Ley que se crea.\nCUARTO. El Sistema Estatal para Prevenir, Atender, Sancionar y Erradicar la\nViolencia contra las Mujeres se instalará dentro de los noventa días naturales siguientes a la entrada en vigor de la presente Ley, mediante Decreto que emita el Ejecutivo Estatal.\nQUINTO. El Reglamento Interno del Sistema Estatal, se expedirá dentro de los sesenta días posteriores a su instalación.\nSEXTO. Los Municipios contarán con un plazo de ciento veinte días naturales a partir de la entrada en vigor de la presente Ley para adecuar su normatividad vigente.\nSÉPTIMO. Los recursos que se requieran para dar cumplimiento a la presente Ley se cubrirán del gasto autorizado para el presente ejercicio fiscal, asimismo, no se requerirán objetivos.\nEstado de Baja California, en la Ciudad de Mexicali, B.C., a los treinta días del mes de abril del año dos mil ocho.\nLey de Acceso de las Mujeres a una Vida Libre de Violencia Página 54\nDIP. JOSÉ ALFREDO FERREIRO VELAZCO\nPRESIDENTE\n(RÚBRICA)\nDIP. JUAN MANUEL GASTÉLUM BUENROSTRO\nSECRETARIO\n(RÚBRICA)\nDE CONFORMIDAD CON LO DISPUESTO POR LA FRACCION I DEL ARTICULO 49\nDE LA CONSTITUCION POLITICA DEL ESTADO, Y 9 DE LA LEY ORGANICA DE LA\nADMINISTRACION PUBLICA DEL ESTADO DE BAJA CALIFORNIA, IMPRIMASE Y\nPUBLÍQUESE.\nMEXICALI, BAJA CALIFORNIA, A LOS TREINTA DIAS DEL MES DE MAYO DEL\nAÑO DOS MIL OCHO.\nGOBERNADOR DEL ESTADO\nJOSE GUADALUPE OSUNA MILLAN\n(RÚBRICA)\nSECRETARIO GENERAL DE GOBIERNO\nJOSE FRANCISCO BLAKE MORA\n(RÚBRICA)\nLey de Acceso de las Mujeres a una Vida Libre de Violencia Página 55\nFue adicionado este Título mediante el Decreto No. 236, publicado en el Periódico Oficial No. siendo Gobernadora Constitucional la C. Marina del Pilar Ávila Olmeda 2021-2027;\nTITULO PRIMERO\nFue modificado este Capítulo manteniendo la misma denominación, mediante el Decreto No.\n236, publicado en el Periódico Oficial No. 33, de fecha 09 de junio de 2023, Índice, Tomo\nCXXX, expedido por la H. XXIV Legislatura, siendo Gobernadora Constitucional la C. Marina del Pilar Ávila Olmeda 2021-2027;\nCAPITULO UNICO\nDISPOSICIONES GENERALES\nARTÍCULO 1.- Fue reformado por Decreto No. 522, publicado en el Periódico Oficial\nNo. 34, de fecha 29 de julio de 2016, Sección VI, Tomo CXXIII, expedido por la H. XXI\nLegislatura, siendo Gobernador Constitucional el C. Francisco Arturo Vega de Lamadrid\n2013-2019; fue reformado por Decreto No. 236, publicado en el Periódico Oficial No. 33, de fecha 09 de junio de 2023, Índice, Tomo CXXX, expedido por la H. XXIV Legislatura, siendo\nGobernadora Constitucional la C. Marina del Pilar Ávila Olmeda 2021-2027; fue reformado por Decreto No. 119, publicado en el Periódico Oficial No. 43, Número Especial, de fecha 21 de julio de 2025, Tomo CXXXII, expedido por la H. XXV Legislatura, siendo Gobernadora\nConstitucional la C. Marina del Pilar Ávila Olmeda 2021-2027;\nARTÍCULO 2.- Fue reformado por Decreto No. 522, publicado en el Periódico Oficial\nNo. 34, de fecha 29 de julio de 2016, Sección VI, Tomo CXXIII, expedido por la H. XXI\nLegislatura, siendo Gobernador Constitucional el C. Francisco Arturo Vega de Lamadrid\n2013-2019; fue reformado por Decreto No. 236, publicado en el Periódico Oficial No. 33, de fecha 09 de junio de 2023, Índice, Tomo CXXX, expedido por la H. XXIV Legislatura, siendo\nGobernadora Constitucional la C. Marina del Pilar Ávila Olmeda 2021-2027;\nARTÍCULO 3.- Fue reformado por Decreto No. 522, publicado en el Periódico Oficial\nNo. 34, de fecha 29 de julio de 2016, Sección VI, Tomo CXXIII, expedido por la H. XXI\nLegislatura, siendo Gobernador Constitucional el C. Francisco Arturo Vega de Lamadrid\n2013-2019; fue reformado por Decreto No. 102, publicado en el Periódico Oficial No. 54, de fecha 02 de septiembre de 2020, NÚMERO ESPECIAL, Tomo CXXVII, expedido por la H.\nXXIII Legislatura, siendo Gobernador Constitucional el C. Jaime Bonilla Valdez, 2019-2021; fue reformado por Decreto No. 236, publicado en el Periódico Oficial No. 33, de fecha 09 de\nConstitucional la C. Marina del Pilar Ávila Olmeda 2021-2027;\nARTÍCULO 3 BIS.- Fue adicionado por Decreto No. 236, publicado en el Periódico\nLegislatura, siendo Gobernadora Constitucional la C. Marina del Pilar Ávila Olmeda 20212027; fue reformado mediante Decreto No. 294, publicado en el Periódico Oficial No. 57, Ley de Acceso de las Mujeres a una Vida Libre de Violencia Página 56 siendo Gobernadora Constitucional la C. Marina del Pilar Ávila Olmeda 2021-2027;\nARTÍCULO 4.- Fue reformado por Decreto No. 522, publicado en el Periódico Oficial\nLegislatura, siendo Gobernador Constitucional el C. Francisco Arturo Vega de Lamadrid\n2013-2019; fue reformado por Decreto No. 340, publicado en el Periódico Oficial No. 26, de fecha 14 de junio de 2019, Sección IV, Tomo CXXVI, expedido por la H. XXII Legislatura, siendo Gobernador Constitucional el C. Francisco Arturo Vega de Lamadrid 2013-2019; fue reformado por Decreto No. 236, publicado en el Periódico Oficial No. 33, de fecha 09 de junio de 2023, Índice, Tomo CXXX, expedido por la H. XXIV Legislatura, siendo Gobernadora\nConstitucional la C. Marina del Pilar Ávila Olmeda 2021-2027; fue reformado por Decreto No.\n86, publicado en el Periódico Oficial No. 25, Índice, de fecha 25 de abril de 2025, Tomo\nCXXXII, expedido por la H. XXV Legislatura, siendo Gobernadora Constitucional la C. Marina del Pilar Ávila Olmeda 2021-2027; fue reformado por Decreto No. 119, publicado en el\nPeriódico Oficial No. 43, Número Especial, de fecha 21 de julio de 2025, Tomo CXXXII, expedido por la H. XXV Legislatura, siendo Gobernadora Constitucional la C. Marina del Pilar\nÁvila Olmeda 2021-2027;\nFue adicionado este Título mediante el Decreto No. 236, publicado en el Periódico Oficial No.\n33, de fecha 09 de junio de 2023, Índice, Tomo CXXX, expedido por la H. XXIV Legislatura, siendo Gobernadora Constitucional la C. Marina del Pilar Ávila Olmeda 2021-2027;\nTITULO SEGUNDO\nTIPOS Y MODALIDADES DE VIOLENCIA CONTRA LAS MUJERES, ÓRDENES DE\nPROTECCIÓN Y REFUGIOS PARA MUJERES VÍCTIMAS DE VIOLENCIA\nFue modificada la denominación de este Título Segundo por Decreto No. 119, publicado en el Periódico Oficial No. 43, Número Especial, de fecha 21 de julio de 2025, Tomo CXXXII, expedido por la H. XXV Legislatura, siendo Gobernadora Constitucional la C.\nMarina del Pilar Ávila Olmeda 2021-2027;\nTITULO SEGUNDO\nTIPOS Y MODALIDADES DE VIOLENCIA CONTRA LAS MUJERES, MEDIDAS U\nARTÍCULO 5.- Fue reformado por Decreto No. 407, publicado en el Periódico Oficial\nLegislatura, siendo Gobernador Constitucional el C. Lic. José Guadalupe Osuna Millán, 20072013; fue reformado por Decreto No. 522, publicado en el Periódico Oficial No. 34, de fecha\nGobernador Constitucional el C. Francisco Arturo Vega de Lamadrid 2013-2019;\nLey de Acceso de las Mujeres a una Vida Libre de Violencia Página 57\nFue modificado este Capítulo y su denominación, mediante el Decreto No. 236, publicado en\nH. XXIV Legislatura, siendo Gobernadora Constitucional la C. Marina del Pilar Ávila Olmeda\n2021-2027;\nCAPÍTULO I\nDE LOS TIPOS DE VIOLENCIA CONTRA LAS MUJERES\nARTÍCULO 6.- Fue reformado por Decreto No. 407, publicado en el Periódico Oficial\nNo. 9, de fecha 15 de febrero de 2013, Sección I, Tomo CXX, expedido por la Honorable XX\nLegislatura, siendo Gobernador Constitucional el C. Lic. José Guadalupe Osuna Millán, 20072013; fue reformado por Decreto No. 454, publicado en el Periódico Oficial No. 14, Sección\nIV, Tomo CXXIII, de fecha 18 de marzo de 2016, expedido por la H. XXI Legislatura, siendo\nGobernador Constitucional el C. Francisco Arturo Vega de Lamadrid 2013-2019; fue reformado por Decreto No. 84, publicado en el Periódico Oficial No. 40, Índice, Tomo CXXVII, de fecha 10 de julio de 2020, expedido por la H. XXIII Legislatura, siendo Gobernador\nConstitucional el C. Jaime Bonilla Valdez 2019-2021; fue reformado por Decreto No. 218, publicado en el Periódico Oficial No. 13, de fecha 15 de marzo de 2023, Número Especial, Tomo CXXX, expedido por la H. XXIV Legislatura, siendo Gobernadora Constitucional la C.\nMarina del Pilar Ávila Olmeda 2021-2027; fue reformado por Decreto No. 237, publicado en el\nPeriódico Oficial No. 33, de fecha 09 de junio de 2023, Índice, Tomo CXXX, expedido por la\nH. XXIV Legislatura, siendo Gobernadora Constitucional la C. Marina del Pilar Ávila Olmeda\n2021-2027; fue reformado por Decreto No. 297, publicado en el Periódico Oficial No. 62, de fecha 06 de noviembre de 2023, Índice, Tomo CXXX, expedido por la H. XXIV Legislatura, siendo Gobernadora Constitucional la C. Marina del Pilar Ávila Olmeda 2021-2027; fue reformado por Decreto No. 336, publicado en el Periódico Oficial No. 70, de fecha 08 de diciembre de 2023, Sección I, Tomo CXXX, expedido por la H. XXIV Legislatura, siendo\nGobernadora Constitucional la C. Marina del Pilar Ávila Olmeda 2021-2027; fue reformado por Decreto No. 377, publicado en el Periódico Oficial No. 7, de fecha 09 de febrero de 2024, Índice, Tomo CXXXI, expedido por la H. XXIV Legislatura, siendo Gobernadora Constitucional la C. Marina del Pilar Ávila Olmeda, 2021-2027; fue reformado por Decreto No. 429, publicado en el Periódico Oficial No. 28, Índice, de fecha 31 de mayo de 2024, Tomo CXXXI, expedido por la H. XXIV Legislatura, siendo Gobernadora Constitucional la C. Marina del Pilar Ávila\nOlmeda, 2021-2027; fue reformado por Decreto No. 85, publicado en el Periódico Oficial No.\n25, Índice, de fecha 25 de abril de 2025, Tomo CXXXII, expedido por la H. XXV Legislatura, siendo Gobernadora Constitucional la C. Marina del Pilar Ávila Olmeda, 2021-2027; fue reformado por Decreto No. 86, publicado en el Periódico Oficial No. 25, Índice, de fecha 25 de\nConstitucional la C. Marina del Pilar Ávila Olmeda 2021-2027;\nFue adicionado este Capítulo mediante el Decreto No. 236, publicado en el Periódico Oficial\nLegislatura, siendo Gobernadora Constitucional la C. Marina del Pilar Ávila Olmeda 20212027;\nCAPÍTULO II\nLey de Acceso de las Mujeres a una Vida Libre de Violencia Página 58\nMODALIDADES DE VIOLENCIA CONTRA LAS MUJERES\nARTÍCULO 7.- Fue reformado por Decreto No. 550, publicado en el Periódico Oficial\nLegislatura, siendo Gobernador Constitucional el C. Lic. José Guadalupe Osuna Millán, 20072013; fue reformado por Decreto No. 522, publicado en el Periódico Oficial No. 34, de fecha\n29 de julio de 2016, Sección VI, Tomo CXXIII, expedido por la H. XXI Legislatura, siendo\nGobernador Constitucional el C. Francisco Arturo Vega de Lamadrid 2013-2019; fue reformado por Decreto No. 218, publicado en el Periódico Oficial No. 13, de fecha 15 de marzo de 2023, Número Especial, Tomo CXXX, expedido por la H. XXIV Legislatura, siendo\nGobernadora Constitucional la C. Marina del Pilar Ávila Olmeda 2021-2027; fue reformado mediante Decreto No. 294, publicado en el Periódico Oficial No. 57, Índice, de fecha 06 de octubre de 2023, Tomo CXXX, expedido por la H. XXIV Legislatura, siendo Gobernadora\nConstitucional la C. Marina del Pilar Ávila Olmeda 2021-2027;\nARTÍCULO 8.- Fue reformado por Decreto No. 522, publicado en el Periódico Oficial\nNo. 34, de fecha 29 de julio de 2016, Sección VI, Tomo CXXIII, expedido por la H. XXI\nLegislatura, siendo Gobernador Constitucional el C. Francisco Arturo Vega de Lamadrid\n2013-2019; fue reformado por Decreto No. 236, publicado en el Periódico Oficial No. 33, de fecha 09 de junio de 2023, Índice, Tomo CXXX, expedido por la H. XXIV Legislatura, siendo\nGobernadora Constitucional la C. Marina del Pilar Ávila Olmeda 2021-2027; fue reformado mediante Decreto No. 294, publicado en el Periódico Oficial No. 57, Índice, de fecha 06 de octubre de 2023, Tomo CXXX, expedido por la H. XXIV Legislatura, siendo Gobernadora\nConstitucional la C. Marina del Pilar Ávila Olmeda 2021-2027;\nARTÍCULO 9.- Fue reformado por Decreto No. 522, publicado en el Periódico Oficial\nNo. 34, de fecha 29 de julio de 2016, Sección VI, Tomo CXXIII, expedido por la H. XXI\nLegislatura, siendo Gobernador Constitucional el C. Francisco Arturo Vega de Lamadrid\n2013-2019; fue reformado por Decreto No. 236, publicado en el Periódico Oficial No. 33, de fecha 09 de junio de 2023, Índice, Tomo CXXX, expedido por la H. XXIV Legislatura, siendo\nGobernadora Constitucional la C. Marina del Pilar Ávila Olmeda 2021-2027;\nARTÍCULO 9 BIS.- Fue adicionado por Decreto No. 236, publicado en el Periódico\nOficial No. 33, de fecha 09 de junio de 2023, Índice, Tomo CXXX, expedido por la H. XXIV\nLegislatura, siendo Gobernadora Constitucional la C. Marina del Pilar Ávila Olmeda 20212027;\nARTÍCULO 10.- Fue reformado por Decreto No. 522, publicado en el Periódico Oficial\nLegislatura, siendo Gobernador Constitucional el C. Francisco Arturo Vega de Lamadrid\n2013-2019; fue reformado por Decreto No. 236, publicado en el Periódico Oficial No. 33, de\nGobernadora Constitucional la C. Marina del Pilar Ávila Olmeda 2021-2027;\nLey de Acceso de las Mujeres a una Vida Libre de Violencia Página 59\nARTÍCULO 10 BIS.- Fue adicionado por Decreto No. 87, publicado en el Periódico\nLegislatura, siendo Gobernadora Constitucional la C. Marina del Pilar Ávila Olmeda 20212027;\nARTÍCULO 11.- Fue reformado por Decreto No. 522, publicado en el Periódico Oficial\nNo. 34, de fecha 29 de julio de 2016, Sección VI, Tomo CXXIII, expedido por la H. XXI\nLegislatura, siendo Gobernador Constitucional el C. Francisco Arturo Vega de Lamadrid\n2013-2019; fue reformado por Decreto No. 236, publicado en el Periódico Oficial No. 33, de fecha 09 de junio de 2023, Índice, Tomo CXXX, expedido por la H. XXIV Legislatura, siendo\nGobernadora Constitucional la C. Marina del Pilar Ávila Olmeda 2021-2027;\nARTÍCULO 11 BIS.- Fue adicionado por Decreto No. 453, publicado en el Periódico\nOficial No. 14, Sección IV, Tomo CXXIII, de fecha 18 de marzo de 2016, expedido por la H.\nXXI Legislatura, siendo Gobernador Constitucional el C. Francisco Arturo Vega de Lamadrid\n2013-2019; fue reformado por Decreto No. 102, publicado en el Periódico Oficial No. 54, de fecha 02 de septiembre de 2020, NÚMERO ESPECIAL, Tomo CXXVII, expedido por la H.\nXXIII Legislatura, siendo Gobernador Constitucional el C. Jaime Bonilla Valdez, 2019-2021;\nARTÍCULO 11 TER.- Fue adicionado por Decreto No. 453, publicado en el Periódico Oficial\nNo. 14, Sección IV, Tomo CXXIII, de fecha 18 de marzo de 2016, expedido por la H. XXI\nLegislatura, siendo Gobernador Constitucional el C. Francisco Arturo Vega de Lamadrid\n2013-2019; fue reformado por Decreto No. 102, publicado en el Periódico Oficial No. 54, de fecha 02 de septiembre de 2020, NÚMERO ESPECIAL, Tomo CXXVII, expedido por la H.\nXXIII Legislatura, siendo Gobernador Constitucional el C. Jaime Bonilla Valdez, 2019-2021; fue reformado por Decreto No. 429, publicado en el Periódico Oficial No. 28, Índice, de fecha\n31 de mayo de 2024, Tomo CXXXI, expedido por la H. XXIV Legislatura, siendo Gobernadora\nConstitucional la C. Marina del Pilar Ávila Olmeda, 2021-2027;\nARTÍCULO 11 QUATER.- Fue adicionado por Decreto No. 336, publicado en el\nPeriódico Oficial No. 70, de fecha 08 de diciembre de 2023, Sección I, Tomo CXXX, expedido por la H. XXIV Legislatura, siendo Gobernadora Constitucional la C. Marina del Pilar Ávila\nOlmeda 2021-2027;\nARTÍCULO 12.- Fue reformado por Decreto No. 522, publicado en el Periódico Oficial\nLegislatura, siendo Gobernador Constitucional el C. Francisco Arturo Vega de Lamadrid\n2013-2019;\nARTÍCULO 13.- Fue reformado por Decreto No. 522, publicado en el Periódico Oficial\nLegislatura, siendo Gobernador Constitucional el C. Francisco Arturo Vega de Lamadrid\n2013-2019; fue reformado por Decreto No. 236, publicado en el Periódico Oficial No. 33, de\nLey de Acceso de las Mujeres a una Vida Libre de Violencia Página 60\nGobernadora Constitucional la C. Marina del Pilar Ávila Olmeda 2021-2027;\nARTÍCULO 14.- Fue reformado por Decreto No. 522, publicado en el Periódico Oficial\nLegislatura, siendo Gobernador Constitucional el C. Francisco Arturo Vega de Lamadrid\n2013-2019;\nARTÍCULO 15.- Fue reformado por Decreto No. 522, publicado en el Periódico Oficial\nNo. 34, de fecha 29 de julio de 2016, Sección VI, Tomo CXXIII, expedido por la H. XXI\nLegislatura, siendo Gobernador Constitucional el C. Francisco Arturo Vega de Lamadrid\n2013-2019;\nARTÍCULO 15 BIS.- Fue adicionado por Decreto No. 86, publicado en el Periódico\nOficial No. 25, Índice, de fecha 25 de abril de 2025, Tomo CXXXII, expedido por la H. XXV\nLegislatura, siendo Gobernadora Constitucional la C. Marina del Pilar Ávila Olmeda 20212027;\nARTÍCULO 16.- Fue reformado por Decreto No. 522, publicado en el Periódico Oficial\nNo. 34, de fecha 29 de julio de 2016, Sección VI, Tomo CXXIII, expedido por la H. XXI\nLegislatura, siendo Gobernador Constitucional el C. Francisco Arturo Vega de Lamadrid\n2013-2019; fue reformado por Decreto No. 236, publicado en el Periódico Oficial No. 33, de fecha 09 de junio de 2023, Índice, Tomo CXXX, expedido por la H. XXIV Legislatura, siendo\nGobernadora Constitucional la C. Marina del Pilar Ávila Olmeda 2021-2027; fue reformado por Decreto No. 86, publicado en el Periódico Oficial No. 25, Índice, de fecha 25 de abril de\n2025, Tomo CXXXII, expedido por la H. XXV Legislatura, siendo Gobernadora Constitucional la C. Marina del Pilar Ávila Olmeda 2021-2027; fue reformado por Decreto No. 119, publicado en el Periódico Oficial No. 43, Número Especial, de fecha 21 de julio de 2025, Tomo CXXXII, expedido por la H. XXV Legislatura, siendo Gobernadora Constitucional la C. Marina del Pilar\nÁvila Olmeda 2021-2027;\nARTÍCULO 17.- Fue reformado por Decreto No. 522, publicado en el Periódico Oficial\nNo. 34, de fecha 29 de julio de 2016, Sección VI, Tomo CXXIII, expedido por la H. XXI\nLegislatura, siendo Gobernador Constitucional el C. Francisco Arturo Vega de Lamadrid\n2013-2019; fue reformado por Decreto No. 236, publicado en el Periódico Oficial No. 33, de\nGobernadora Constitucional la C. Marina del Pilar Ávila Olmeda 2021-2027;\nARTÍCULO 18.- Fue reformado por Decreto No. 522, publicado en el Periódico Oficial\nLegislatura, siendo Gobernador Constitucional el C. Francisco Arturo Vega de Lamadrid\n2013-2019;\nLey de Acceso de las Mujeres a una Vida Libre de Violencia Página 61\nARTÍCULO 19.- Fue reformado por Decreto No. 252, publicado en el Periódico Oficial\nLegislatura, siendo Gobernador Constitucional el C. Lic. José Guadalupe Osuna Millán 20072013; fue reformado por Decreto No. 236, publicado en el Periódico Oficial No. 33, de fecha\nGobernadora Constitucional la C. Marina del Pilar Ávila Olmeda 2021-2027;\nARTÍCULO 20.- Fue reformado por Decreto No. 252, publicado en el Periódico Oficial\nNo. 38, de fecha 31 de agosto de 2012, Sección I, Tomo CXIX, expedido por la XX\nLegislatura, siendo Gobernador Constitucional el C. Lic. José Guadalupe Osuna Millán 20072013; fue reformado por Decreto No. 522, publicado en el Periódico Oficial No. 34, de fecha\n29 de julio de 2016, Sección VI, Tomo CXXIII, expedido por la H. XXI Legislatura, siendo\nGobernador Constitucional el C. Francisco Arturo Vega de Lamadrid 2013-2019; fue reformado por Decreto No. 236, publicado en el Periódico Oficial No. 33, de fecha 09 de junio de 2023, Índice, Tomo CXXX, expedido por la H. XXIV Legislatura, siendo Gobernadora\nConstitucional la C. Marina del Pilar Ávila Olmeda 2021-2027;\nARTÍCULO 20 BIS.- Fue adicionado por Decreto No. 236, publicado en el Periódico\nOficial No. 33, de fecha 09 de junio de 2023, Índice, Tomo CXXX, expedido por la H. XXIV\nLegislatura, siendo Gobernadora Constitucional la C. Marina del Pilar Ávila Olmeda 20212027;\nARTÍCULO 20 TER.- Fue adicionado por Decreto No. 236, publicado en el Periódico\nOficial No. 33, de fecha 09 de junio de 2023, Índice, Tomo CXXX, expedido por la H. XXIV\nLegislatura, siendo Gobernadora Constitucional la C. Marina del Pilar Ávila Olmeda 20212027;\nFue modificada la denominación de este Capítulo III por Decreto No. 119, publicado en el\nPeriódico Oficial No. 43, Número Especial, de fecha 21 de julio de 2025, Tomo CXXXII, expedido por la H. XXV Legislatura, siendo Gobernadora Constitucional la C. Marina del Pilar\nÁvila Olmeda 2021-2027;\nCAPÍTULO III\nMEDIDAS U ÓRDENES DE PROTECCIÓN\nARTÍCULO 21.- Fue reformado por Decreto No. 102, publicado en el Periódico Oficial por la H. XXIII Legislatura, siendo Gobernador Constitucional el C. Jaime Bonilla Valdez, 2019-2021; fue reformado por Decreto No. 236, publicado en el Periódico Oficial No. 33, de\nGobernadora Constitucional la C. Marina del Pilar Ávila Olmeda 2021-2027; fue reformado por Decreto No. 119, publicado en el Periódico Oficial No. 43, Número Especial, de fecha 21\nConstitucional la C. Marina del Pilar Ávila Olmeda 2021-2027;\nLey de Acceso de las Mujeres a una Vida Libre de Violencia Página 62\nARTÍCULO 22.- Fue reformado por Decreto No. 236, publicado en el Periódico Oficial\nLegislatura, siendo Gobernadora Constitucional la C. Marina del Pilar Ávila Olmeda 20212027; fue reformado por Decreto No. 119, publicado en el Periódico Oficial No. 43, Número siendo Gobernadora Constitucional la C. Marina del Pilar Ávila Olmeda 2021-2027;\nARTÍCULO 23.- Fue reformado por Decreto No. 550, publicado en el Periódico Oficial\nNo. 46, de fecha 18 de octubre de 2013, Tomo CXX, expedido por la Honorable XX\nLegislatura, siendo Gobernador Constitucional el C. Lic. José Guadalupe Osuna Millán, 20072013; fue reformado por Decreto No. 75, publicado en el Periódico Oficial No. 11, de fecha 11 de febrero de 2022, Sección IV, Tomo CXXIX, expedido por la H. XXIV Legislatura, siendo\nGobernadora Constitucional la C. Marina del Pilar Ávila Olmeda 2021-2027; fue reformado por Decreto No. 236, publicado en el Periódico Oficial No. 33, de fecha 09 de junio de 2023, Índice, Tomo CXXX, expedido por la H. XXIV Legislatura, siendo Gobernadora Constitucional la C. Marina del Pilar Ávila Olmeda 2021-2027;\nARTÍCULO 24.- Fue reformado por Decreto No. 550, publicado en el Periódico Oficial\nNo. 46, de fecha 18 de octubre de 2013, Tomo CXX, expedido por la Honorable XX\nLegislatura, siendo Gobernador Constitucional el C. Lic. José Guadalupe Osuna Millán, 20072013; fue reformado por Decreto No. 236, publicado en el Periódico Oficial No. 33, de fecha\n09 de junio de 2023, Índice, Tomo CXXX, expedido por la H. XXIV Legislatura, siendo\nGobernadora Constitucional la C. Marina del Pilar Ávila Olmeda 2021-2027; fue reformado por Decreto No. 119, publicado en el Periódico Oficial No. 43, Número Especial, de fecha 21 de julio de 2025, Tomo CXXXII, expedido por la H. XXV Legislatura, siendo Gobernadora\nConstitucional la C. Marina del Pilar Ávila Olmeda 2021-2027;\nARTÍCULO 25.- Fue reformado por Decreto No. 75, publicado en el Periódico Oficial\nNo. 11, de fecha 11 de febrero de 2022, Sección IV, Tomo CXXIX, expedido por la H. XXIV\nLegislatura, siendo Gobernadora Constitucional la C. Marina del Pilar Ávila Olmeda 20212027; fue reformado por Decreto No. 218, publicado en el Periódico Oficial No. 13, de fecha\n15 de marzo de 2023, Número Especial, Tomo CXXX, expedido por la H. XXIV Legislatura, siendo Gobernadora Constitucional la C. Marina del Pilar Ávila Olmeda 2021-2027; fue reformado por Decreto No. 236, publicado en el Periódico Oficial No. 33, de fecha 09 de junio de 2023, Índice, Tomo CXXX, expedido por la H. XXIV Legislatura, siendo Gobernadora\nConstitucional la C. Marina del Pilar Ávila Olmeda 2021-2027; fue reformado por Decreto No.\nTomo CXXXII, expedido por la H. XXV Legislatura, siendo Gobernadora Constitucional la C.\nMarina del Pilar Ávila Olmeda 2021-2027;\nARTÍCULO 26.- Fue reformado por Decreto No. 78, publicado en el Periódico Oficial\nLegislatura, siendo Gobernador Constitucional el C. Francisco Arturo Vega de Lamadrid, Ley de Acceso de las Mujeres a una Vida Libre de Violencia Página 63\n2013-2019; fue reformado por Decreto No. 236, publicado en el Periódico Oficial No. 33, de\nGobernadora Constitucional la C. Marina del Pilar Ávila Olmeda 2021-2027; fue reformado por Decreto No. 119, publicado en el Periódico Oficial No. 43, Número Especial, de fecha 21\nConstitucional la C. Marina del Pilar Ávila Olmeda 2021-2027; fue reformado por Decreto No.\n119, publicado en el Periódico Oficial No. 43, Número Especial, de fecha 21 de julio de 2025, Tomo CXXXII, expedido por la H. XXV Legislatura, siendo Gobernadora Constitucional la C.\nMarina del Pilar Ávila Olmeda 2021-2027;\nARTÍCULO 26 BIS.- Fue adicionado por Decreto No. 236, publicado en el Periódico\nOficial No. 33, de fecha 09 de junio de 2023, Índice, Tomo CXXX, expedido por la H. XXIV\nLegislatura, siendo Gobernadora Constitucional la C. Marina del Pilar Ávila Olmeda 20212027; fue reformado por Decreto No. 119, publicado en el Periódico Oficial No. 43, Número\nEspecial, de fecha 21 de julio de 2025, Tomo CXXXII, expedido por la H. XXV Legislatura, siendo Gobernadora Constitucional la C. Marina del Pilar Ávila Olmeda 2021-2027;\nARTÍCULO 26 TER.- Fue adicionado por Decreto No. 236, publicado en el Periódico\nOficial No. 33, de fecha 09 de junio de 2023, Índice, Tomo CXXX, expedido por la H. XXIV\nLegislatura, siendo Gobernadora Constitucional la C. Marina del Pilar Ávila Olmeda 20212027; fue reformado por Decreto No. 119, publicado en el Periódico Oficial No. 43, Número\nEspecial, de fecha 21 de julio de 2025, Tomo CXXXII, expedido por la H. XXV Legislatura, siendo Gobernadora Constitucional la C. Marina del Pilar Ávila Olmeda 2021-2027;\nARTÍCULO 26 QUÁTER.- Fue adicionado por Decreto No. 236, publicado en el\nPeriódico Oficial No. 33, de fecha 09 de junio de 2023, Índice, Tomo CXXX, expedido por la\nH. XXIV Legislatura, siendo Gobernadora Constitucional la C. Marina del Pilar Ávila Olmeda\n2021-2027; fue reformado por Decreto No. 119, publicado en el Periódico Oficial No. 43, Número Especial, de fecha 21 de julio de 2025, Tomo CXXXII, expedido por la H. XXV\nLegislatura, siendo Gobernadora Constitucional la C. Marina del Pilar Ávila Olmeda 20212027;\nARTÍCULO 26 QUINQUIES.- Fue adicionado por Decreto No. 236, publicado en el\nPeriódico Oficial No. 33, de fecha 09 de junio de 2023, Índice, Tomo CXXX, expedido por la\nH. XXIV Legislatura, siendo Gobernadora Constitucional la C. Marina del Pilar Ávila Olmeda\n2021-2027; fue reformado por Decreto No. 119, publicado en el Periódico Oficial No. 43, Legislatura, siendo Gobernadora Constitucional la C. Marina del Pilar Ávila Olmeda 20212027;\nARTÍCULO 26 SEXIES.- Fue adicionado por Decreto No. 236, publicado en el\nH. XXIV Legislatura, siendo Gobernadora Constitucional la C. Marina del Pilar Ávila Olmeda\n2021-2027;\nLey de Acceso de las Mujeres a una Vida Libre de Violencia Página 64\nARTÍCULO 26 SEPTIES.- Fue adicionado por Decreto No. 236, publicado en el\nH. XXIV Legislatura, siendo Gobernadora Constitucional la C. Marina del Pilar Ávila Olmeda\n2021-2027; fue reformado por Decreto No. 119, publicado en el Periódico Oficial No. 43, Legislatura, siendo Gobernadora Constitucional la C. Marina del Pilar Ávila Olmeda 20212027;\nARTÍCULO 26 OCTIES.- Fue adicionado por Decreto No. 236, publicado en el\nPeriódico Oficial No. 33, de fecha 09 de junio de 2023, Índice, Tomo CXXX, expedido por la\nH. XXIV Legislatura, siendo Gobernadora Constitucional la C. Marina del Pilar Ávila Olmeda\n2021-2027;\nARTÍCULO 26 NONIES.- Fue adicionado por Decreto No. 236, publicado en el\nPeriódico Oficial No. 33, de fecha 09 de junio de 2023, Índice, Tomo CXXX, expedido por la\nH. XXIV Legislatura, siendo Gobernadora Constitucional la C. Marina del Pilar Ávila Olmeda\n2021-2027; fue reformado por Decreto No. 119, publicado en el Periódico Oficial No. 43, Número Especial, de fecha 21 de julio de 2025, Tomo CXXXII, expedido por la H. XXV\nLegislatura, siendo Gobernadora Constitucional la C. Marina del Pilar Ávila Olmeda 20212027;\nARTÍCULO 26 DECIES.- Fue adicionado por Decreto No. 236, publicado en el\nPeriódico Oficial No. 33, de fecha 09 de junio de 2023, Índice, Tomo CXXX, expedido por la\nH. XXIV Legislatura, siendo Gobernadora Constitucional la C. Marina del Pilar Ávila Olmeda\n2021-2027;\nARTÍCULO 26 UNDECIES.- Fue adicionado por Decreto No. 236, publicado en el\nPeriódico Oficial No. 33, de fecha 09 de junio de 2023, Índice, Tomo CXXX, expedido por la\nH. XXIV Legislatura, siendo Gobernadora Constitucional la C. Marina del Pilar Ávila Olmeda\n2021-2027;\nARTÍCULO 26 DUODECIES.- Fue adicionado por Decreto No. 236, publicado en el\nPeriódico Oficial No. 33, de fecha 09 de junio de 2023, Índice, Tomo CXXX, expedido por la\nH. XXIV Legislatura, siendo Gobernadora Constitucional la C. Marina del Pilar Ávila Olmeda\n2021-2027; fue reformado por Decreto No. 119, publicado en el Periódico Oficial No. 43, Legislatura, siendo Gobernadora Constitucional la C. Marina del Pilar Ávila Olmeda 20212027;\nARTÍCULO 26 TERDECIES.- Fue adicionado por Decreto No. 236, publicado en el\nH. XXIV Legislatura, siendo Gobernadora Constitucional la C. Marina del Pilar Ávila Olmeda\n2021-2027; fue reformado por Decreto No. 119, publicado en el Periódico Oficial No. 43, Ley de Acceso de las Mujeres a una Vida Libre de Violencia Página 65\nLegislatura, siendo Gobernadora Constitucional la C. Marina del Pilar Ávila Olmeda 20212027;\nARTÍCULO 26 QUATERDECIES.- Fue adicionado por Decreto No. 236, publicado en\nH. XXIV Legislatura, siendo Gobernadora Constitucional la C. Marina del Pilar Ávila Olmeda\n2021-2027; fue reformado por Decreto No. 119, publicado en el Periódico Oficial No. 43, Número Especial, de fecha 21 de julio de 2025, Tomo CXXXII, expedido por la H. XXV\nLegislatura, siendo Gobernadora Constitucional la C. Marina del Pilar Ávila Olmeda 20212027;\nFue modificada la denominación de este Capítulo mediante el Decreto No. 236, publicado en el Periódico Oficial No. 33, de fecha 09 de junio de 2023, Índice, Tomo CXXX, expedido por la\nH. XXIV Legislatura, siendo Gobernadora Constitucional la C. Marina del Pilar Ávila Olmeda\n2021-2027;\nCAPÍTULO IV\nREFUGIOS PARA VÍCTIMAS DE VIOLENCIA\nARTICULO 27.- Fue reformado por Decreto No. 236, publicado en el Periódico Oficial\nNo. 33, de fecha 09 de junio de 2023, Índice, Tomo CXXX, expedido por la H. XXIV\nLegislatura, siendo Gobernadora Constitucional la C. Marina del Pilar Ávila Olmeda 20212027;\nARTICULO 28.- Fue reformado por Decreto No. 548, publicado en el Periódico Oficial\nNo. 43, Sección II, Tomo CXX, de fecha 04 de octubre de 2013, expedido por la H. XX\nLegislatura, siendo Gobernador Constitucional el C. José Guadalupe Osuna Millán 20072013; fue reformado por Decreto No. 236, publicado en el Periódico Oficial No. 33, de fecha\n09 de junio de 2023, Índice, Tomo CXXX, expedido por la H. XXIV Legislatura, siendo\nGobernadora Constitucional la C. Marina del Pilar Ávila Olmeda 2021-2027; fue reformado mediante Decreto No. 294, publicado en el Periódico Oficial No. 57, Índice, de fecha 06 de octubre de 2023, Tomo CXXX, expedido por la H. XXIV Legislatura, siendo Gobernadora\nConstitucional la C. Marina del Pilar Ávila Olmeda 2021-2027;\nARTÍCULO 28 BIS.- Fue adicionado por Decreto No. 236, publicado en el Periódico\nLegislatura, siendo Gobernadora Constitucional la C. Marina del Pilar Ávila Olmeda 20212027;\nARTICULO 29.- Fue reformado por Decreto No. 236, publicado en el Periódico Oficial\nLegislatura, siendo Gobernadora Constitucional la C. Marina del Pilar Ávila Olmeda 20212027;\nLey de Acceso de las Mujeres a una Vida Libre de Violencia Página 66\nARTÍCULO 29 BIS.- Fue adicionado por Decreto No. 236, publicado en el Periódico\nLegislatura, siendo Gobernadora Constitucional la C. Marina del Pilar Ávila Olmeda 20212027;\nARTÍCULO 29 TER.- Fue adicionado por Decreto No. 236, publicado en el Periódico\nOficial No. 33, de fecha 09 de junio de 2023, Índice, Tomo CXXX, expedido por la H. XXIV\nLegislatura, siendo Gobernadora Constitucional la C. Marina del Pilar Ávila Olmeda 20212027;\nARTÍCULO 30.- Fue reformado por Decreto No. 236, publicado en el Periódico Oficial\nNo. 33, de fecha 09 de junio de 2023, Índice, Tomo CXXX, expedido por la H. XXIV\nLegislatura, siendo Gobernadora Constitucional la C. Marina del Pilar Ávila Olmeda 20212027;\nFue adicionado este Título mediante el Decreto No. 236, publicado en el Periódico Oficial No.\n33, de fecha 09 de junio de 2023, Índice, Tomo CXXX, expedido por la H. XXIV Legislatura, siendo Gobernadora Constitucional la C. Marina del Pilar Ávila Olmeda 2021-2027;\nTITULO TERCERO\nSISTEMA ESTATAL Y PROGRAMA ESTATAL PARA\nPREVENIR, ATENDER, SANCIONAR Y ERRADICAR\nLA VIOLENCIA CONTRA LAS MUJERES\nFue modificada la denominación de este Título Tercero por Decreto No. 119, publicado en el\nPeriódico Oficial No. 43, Número Especial, de fecha 21 de julio de 2025, Tomo CXXXII, expedido por la H. XXV Legislatura, siendo Gobernadora Constitucional la C. Marina del Pilar\nÁvila Olmeda 2021-2027;\nTITULO TERCERO\nDEL SISTEMA ESTATAL, DEL PROGRAMA ESTATAL PARA PREVENIR,\nATENDER, SANCIONAR Y ERRADICAR LA VIOLENCIA\nCONTRA LAS MUJERES, Y DEL PROGRAMA INSTITUCIONAL\nEN BENEFICIO DE LAS MUJERES\nFue modificado este Capítulo manteniendo la misma denominación, mediante el Decreto No.\n236, publicado en el Periódico Oficial No. 33, de fecha 09 de junio de 2023, Índice, Tomo\nCXXX, expedido por la H. XXIV Legislatura, siendo Gobernadora Constitucional la C. Marina del Pilar Ávila Olmeda 2021-2027;\nCAPÍTULO I\nDEL SISTEMA ESTATAL\nARTICULO 31.- Fue reformado por Decreto No. 236, publicado en el Periódico Oficial\nLegislatura, siendo Gobernadora Constitucional la C. Marina del Pilar Ávila Olmeda 20212027;\nLey de Acceso de las Mujeres a una Vida Libre de Violencia Página 67\nARTICULO 32.- Fue reformado por Decreto No. 78, publicado en el Periódico Oficial\nLegislatura, siendo Gobernador Constitucional el C. Francisco Arturo Vega de Lamadrid, 2013-2019; fue reformado por Decreto No. 455, publicado en el Periódico Oficial No. 14, siendo Gobernador Constitucional el C. Francisco Arturo Vega de Lamadrid 2013-2019; fue reformado por Decreto No. 515, publicado en el Periódico Oficial No. 34, de fecha 29 de julio de 2016, Sección VI, Tomo CXXIII, expedido por la H. XXI Legislatura, siendo Gobernador\nConstitucional el C. Francisco Arturo Vega de Lamadrid 2013-2019; fue reformado por\nDecreto No. 229, publicado en el Periódico Oficial No. 20, de fecha 20 de abril de 2018,\nSección VIII, Tomo CXXV, expedido por la H. XXII Legislatura, siendo Gobernador\nConstitucional el C. Francisco Arturo Vega de Lamadrid 2013-2019; fue reformado por\nDecreto No. 102, publicado en el Periódico Oficial No. 54, de fecha 02 de septiembre de\n2020, NÚMERO ESPECIAL, Tomo CXXVII, expedido por la H. XXIII Legislatura, siendo\nGobernador Constitucional el C. Jaime Bonilla Valdez, 2019-2021; fue reformado por Decreto\nNo. 236, publicado en el Periódico Oficial No. 33, de fecha 09 de junio de 2023, Índice, Tomo\nCXXX, expedido por la H. XXIV Legislatura, siendo Gobernadora Constitucional la C. Marina del Pilar Ávila Olmeda 2021-2027; fue reformado mediante Decreto No. 294, publicado en el\nPeriódico Oficial No. 57, Índice, de fecha 06 de octubre de 2023, Tomo CXXX, expedido por la H. XXIV Legislatura, siendo Gobernadora Constitucional la C. Marina del Pilar Ávila\nOlmeda 2021-2027; fue reformado por Decreto No. 119, publicado en el Periódico Oficial No.\n43, Número Especial, de fecha 21 de julio de 2025, Tomo CXXXII, expedido por la H. XXV\nLegislatura, siendo Gobernadora Constitucional la C. Marina del Pilar Ávila Olmeda 20212027;\nARTICULO 33.- Fue reformado por Decreto No. 585, publicado en el Periódico Oficial\nNo. 47, de fecha 25 de octubre de 2013, Sección I, Tomo CXX, expedido por la H. XXI\nLegislatura, siendo Gobernador Constitucional el C. José Guadalupe Osuna Millán 20072013; fue reformado por Decreto No. 236, publicado en el Periódico Oficial No. 33, de fecha\n09 de junio de 2023, Índice, Tomo CXXX, expedido por la H. XXIV Legislatura, siendo\nGobernadora Constitucional la C. Marina del Pilar Ávila Olmeda 2021-2027; fue reformado por Decreto No. 426, publicado en el Periódico Oficial No. 23, de fecha 07 de mayo de 2024, Índice, Tomo CXXXI, expedido por la H. XXIV Legislatura, siendo Gobernadora Constitucional la C. Marina del Pilar Ávila Olmeda 2021-2027; fue reformado por Decreto No. 39, publicado en el Periódico Oficial No. 10, Índice, de fecha 07 de febrero de 2025, Tomo CXXXII, expedido por la H. XXV Legislatura, siendo Gobernadora Constitucional la C. Marina del Pilar\nÁvila Olmeda 2021-2027;\nFue modificado este Capítulo manteniendo la misma denominación, mediante el Decreto No.\nCXXX, expedido por la H. XXIV Legislatura, siendo Gobernadora Constitucional la C. Marina del Pilar Ávila Olmeda 2021-2027;\nCAPÍTULO II\nDEL PROGRAMA ESTATAL\nLey de Acceso de las Mujeres a una Vida Libre de Violencia Página 68\nARTICULO 35. Fue reformado mediante Decreto No. 406, publicado en el Periódico\nXXI Legislatura, siendo Gobernador Constitucional el C. Francisco Arturo Vega de Lamadrid\n2013-2019; fue reformado por Decreto No. 522, publicado en el Periódico Oficial No. 34, de siendo Gobernador Constitucional el C. Francisco Arturo Vega de Lamadrid 2013-2019; fue reformado por Decreto No. 236, publicado en el Periódico Oficial No. 33, de fecha 09 de junio de 2023, Índice, Tomo CXXX, expedido por la H. XXIV Legislatura, siendo Gobernadora\nConstitucional la C. Marina del Pilar Ávila Olmeda 2021-2027; fue reformado mediante\nDecreto No. 294, publicado en el Periódico Oficial No. 57, Índice, de fecha 06 de octubre de\n2023, Tomo CXXX, expedido por la H. XXIV Legislatura, siendo Gobernadora Constitucional la C. Marina del Pilar Ávila Olmeda 2021-2027; fue reformado por Decreto No. 426, publicado en el Periódico Oficial No. 23, de fecha 07 de mayo de 2024, Índice, Tomo CXXXI, expedido por la H. XXIV Legislatura, siendo Gobernadora Constitucional la C. Marina del Pilar Ávila\nOlmeda 2021-2027;\nFue adicionado este Capítulo III por Decreto No. 119, publicado en el Periódico Oficial No. 43, Número Especial, de fecha 21 de julio de 2025, Tomo CXXXII, expedido por la H. XXV\nLegislatura, siendo Gobernadora Constitucional la C. Marina del Pilar Ávila Olmeda 20212027;\nCAPÍTULO III\nDEL PROGRAMA INSTITUCIONAL EN BENEFICIO DE LAS MUJERES\nARTÍCULO 35 BIS.- Fue adicionado por Decreto No. 119, publicado en el Periódico\nOficial No. 43, Número Especial, de fecha 21 de julio de 2025, Tomo CXXXII, expedido por la\nH. XXV Legislatura, siendo Gobernadora Constitucional la C. Marina del Pilar Ávila Olmeda\n2021-2027;\nARTÍCULO 35 TER.- Fue adicionado por Decreto No. 119, publicado en el Periódico\nH. XXV Legislatura, siendo Gobernadora Constitucional la C. Marina del Pilar Ávila Olmeda\n2021-2027\nFue adicionado este Título mediante el Decreto No. 236, publicado en el Periódico Oficial No. siendo Gobernadora Constitucional la C. Marina del Pilar Ávila Olmeda 2021-2027;\nTITULO CUARTO\nDE LA DISTRIBUCIÓN DE COMPETENCIAS\nLey de Acceso de las Mujeres a una Vida Libre de Violencia Página 69\nFue modificado este Capítulo y su denominación, mediante el Decreto No. 236, publicado en\nH. XXIV Legislatura, siendo Gobernadora Constitucional la C. Marina del Pilar Ávila Olmeda\n2021-2027;\nCAPÍTULO I\nGENERALIDAD DE COMPETENCIAS\nARTÍCULO 36.- Fue reformado por Decreto No. 102, publicado en el Periódico Oficial\nNo. 54, de fecha 02 de septiembre de 2020, NÚMERO ESPECIAL, Tomo CXXVII, expedido por la H. XXIII Legislatura, siendo Gobernador Constitucional el C. Jaime Bonilla Valdez, 2019-2021; fue reformado por Decreto No. 236, publicado en el Periódico Oficial No. 33, de fecha 09 de junio de 2023, Índice, Tomo CXXX, expedido por la H. XXIV Legislatura, siendo\nGobernadora Constitucional la C. Marina del Pilar Ávila Olmeda 2021-2027; fue reformado mediante Decreto No. 294, publicado en el Periódico Oficial No. 57, Índice, de fecha 06 de octubre de 2023, Tomo CXXX, expedido por la H. XXIV Legislatura, siendo Gobernadora\nConstitucional la C. Marina del Pilar Ávila Olmeda 2021-2027; fue reformado por Decreto No.\n119, publicado en el Periódico Oficial No. 43, Número Especial, de fecha 21 de julio de 2025, Tomo CXXXII, expedido por la H. XXV Legislatura, siendo Gobernadora Constitucional la C.\nMarina del Pilar Ávila Olmeda 2021-2027;\nARTICULO 37.- Fue reformado por Decreto No. 236, publicado en el Periódico Oficial\nNo. 33, de fecha 09 de junio de 2023, Índice, Tomo CXXX, expedido por la H. XXIV\nLegislatura, siendo Gobernadora Constitucional la C. Marina del Pilar Ávila Olmeda 20212027;\nARTÍCULO 37 BIS.- Fue adicionado por Decreto No. 236, publicado en el Periódico\nOficial No. 33, de fecha 09 de junio de 2023, Índice, Tomo CXXX, expedido por la H. XXIV\nLegislatura, siendo Gobernadora Constitucional la C. Marina del Pilar Ávila Olmeda 20212027;\nARTÍCULO 37 TER.- Fue adicionado por Decreto No. 236, publicado en el Periódico\nOficial No. 33, de fecha 09 de junio de 2023, Índice, Tomo CXXX, expedido por la H. XXIV\nLegislatura, siendo Gobernadora Constitucional la C. Marina del Pilar Ávila Olmeda 20212027;\nARTÍCULO 37 QUATER.- Fue adicionado por Decreto No. 236, publicado en el\nH. XXIV Legislatura, siendo Gobernadora Constitucional la C. Marina del Pilar Ávila Olmeda\n2021-2027;\nARTÍCULO 37 QUINQUIES.- Fue adicionado por Decreto No. 236, publicado en el\nH. XXIV Legislatura, siendo Gobernadora Constitucional la C. Marina del Pilar Ávila Olmeda\n2021-2027;\nLey de Acceso de las Mujeres a una Vida Libre de Violencia Página 70\nFue adicionado este Capítulo mediante el Decreto No. 236, publicado en el Periódico Oficial\nLegislatura, siendo Gobernadora Constitucional la C. Marina del Pilar Ávila Olmeda 20212027;\nCAPÍTULO II\nDEL PODER EJECUTIVO DEL ESTADO\nARTICULO 38.- Fue reformado por Decreto No. 522, publicado en el Periódico Oficial\nNo. 34, de fecha 29 de julio de 2016, Sección VI, Tomo CXXIII, expedido por la H. XXI\nLegislatura, siendo Gobernador Constitucional el C. Francisco Arturo Vega de Lamadrid\n2013-2019; fue reformado por Decreto No. 235, publicado en el Periódico Oficial No. 60, de fecha 13 de agosto de 2021, Sección IV, Tomo CXXVIII, expedido por la H. XXIII Legislatura, siendo Gobernador Constitucional el C. Jaime Bonilla Valdez 2019-2021; fue reformado por\nDecreto No. 236, publicado en el Periódico Oficial No. 33, de fecha 09 de junio de 2023, Índice, Tomo CXXX, expedido por la H. XXIV Legislatura, siendo Gobernadora Constitucional la C. Marina del Pilar Ávila Olmeda 2021-2027;\nARTICULO 38 BIS. Fue adicionado mediante Decreto No. 406, publicado en el\nPeriódico Oficial No. 58, de fecha 18 de diciembre de 2015, Sección III, Tomo CXXII, expedido por la H. XXI Legislatura, siendo Gobernador Constitucional el C. Francisco Arturo\nVega de Lamadrid 2013-2019; fue reformado por Decreto No. 550, publicado en el Periódico\nOficial No. 46, de fecha 18 de octubre de 2013, Tomo CXX, expedido por la Honorable XX\nLegislatura, siendo Gobernador Constitucional el C. Lic. José Guadalupe Osuna Millán, 20072013; fue reformado por Decreto No. 102, publicado en el Periódico Oficial No. 54, de fecha\n02 de septiembre de 2020, NÚMERO ESPECIAL, Tomo CXXVII, expedido por la H. XXIII\nLegislatura, siendo Gobernador Constitucional el C. Jaime Bonilla Valdez, 2019-2021; fue reformado por Decreto No. 119, publicado en el Periódico Oficial No. 43, Número Especial, de fecha 21 de julio de 2025, Tomo CXXXII, expedido por la H. XXV Legislatura, siendo\nGobernadora Constitucional la C. Marina del Pilar Ávila Olmeda 2021-2027; fue reformado por Decreto No. 119, publicado en el Periódico Oficial No. 43, Número Especial, de fecha 21 de julio de 2025, Tomo CXXXII, expedido por la H. XXV Legislatura, siendo Gobernadora\nConstitucional la C. Marina del Pilar Ávila Olmeda 2021-2027);\nARTICULO 38 TER.- Fue reformado por Decreto No. 340, publicado en el Periódico\nOficial No. 26, de fecha 14 de junio de 2019, Sección IV, Tomo CXXVI, expedido por la H.\nXXII Legislatura, siendo Gobernador Constitucional el C. Francisco Arturo Vega de Lamadrid\n2013-2019;\nARTÍCULO 39.- Fue reformado por Decreto No. 102, publicado en el Periódico Oficial por la H. XXIII Legislatura, siendo Gobernador Constitucional el C. Jaime Bonilla Valdez, 2019-2021; fue reformado por Decreto No. 318, publicado en el Periódico Oficial No. 70, de siendo Gobernadora Constitucional la C. Marina del Pilar Ávila Olmeda 2021-2027;\nLey de Acceso de las Mujeres a una Vida Libre de Violencia Página 71\nARTÍCULO 40.- Fue reformado por Decreto No. 119, publicado en el Periódico Oficial\nXXV Legislatura, siendo Gobernadora Constitucional la C. Marina del Pilar Ávila Olmeda\n2021-2027; fue reformado por Decreto No. 119, publicado en el Periódico Oficial No. 43, Legislatura, siendo Gobernadora Constitucional la C. Marina del Pilar Ávila Olmeda 20212027;\nARTÍCULO 41.- Fue reformado por Decreto No. 236, publicado en el Periódico Oficial\nNo. 33, de fecha 09 de junio de 2023, Índice, Tomo CXXX, expedido por la H. XXIV\nLegislatura, siendo Gobernadora Constitucional la C. Marina del Pilar Ávila Olmeda 20212027; fue reformado por Decreto No. 119, publicado en el Periódico Oficial No. 43, Número\nEspecial, de fecha 21 de julio de 2025, Tomo CXXXII, expedido por la H. XXV Legislatura, siendo Gobernadora Constitucional la C. Marina del Pilar Ávila Olmeda 2021-2027; fue reformado por Decreto No. 119, publicado en el Periódico Oficial No. 43, Número Especial, de fecha 21 de julio de 2025, Tomo CXXXII, expedido por la H. XXV Legislatura, siendo\nGobernadora Constitucional la C. Marina del Pilar Ávila Olmeda 2021-2027;\nARTÍCULO 41 BIS.- Fue adicionado por Decreto No. 198, publicado en el Periódico\nOficial No. 6, de fecha 27 de enero de 2023, Índice, Tomo CXXX, expedido por la H. XXIV\nLegislatura, siendo Gobernadora Constitucional la C. Marina del Pilar Ávila Olmeda 20212027;\nARTICULO 42. Fue reformado mediante Decreto No. 406, publicado en el Periódico\nOficial No. 58, de fecha 18 de diciembre de 2015, Sección III, Tomo CXXII, expedido por la H.\nXXI Legislatura, siendo Gobernador Constitucional el C. Francisco Arturo Vega de Lamadrid\n2013-2019; fue reformado por Decreto No. 340, publicado en el Periódico Oficial No. 26, de fecha 14 de junio de 2019, Sección IV, Tomo CXXVI, expedido por la H. XXII Legislatura, siendo Gobernador Constitucional el C. Francisco Arturo Vega de Lamadrid 2013-2019; fue reformado por Decreto No. 102, publicado en el Periódico Oficial No. 54, de fecha 02 de septiembre de 2020, NÚMERO ESPECIAL, Tomo CXXVII, expedido por la H. XXIII\nLegislatura, siendo Gobernador Constitucional el C. Jaime Bonilla Valdez, 2019-2021; fue reformado por Decreto No. 75, publicado en el Periódico Oficial No. 11, de fecha 11 de febrero de 2022, Sección IV, Tomo CXXIX, expedido por la H. XXIV Legislatura, siendo\nGobernadora Constitucional la C. Marina del Pilar Ávila Olmeda 2021-2027; fue reformado por Decreto No. 236, publicado en el Periódico Oficial No. 33, de fecha 09 de junio de 2023, Índice, Tomo CXXX, expedido por la H. XXIV Legislatura, siendo Gobernadora Constitucional la C. Marina del Pilar Ávila Olmeda 2021-2027; fue reformado por Decreto No. 408, publicado por la H. XXIV Legislatura, siendo Gobernadora Constitucional la C. Marina del Pilar Ávila\nOlmeda 2021-2027; fue reformado por Decreto No. 426, publicado en el Periódico Oficial No. siendo Gobernadora Constitucional la C. Marina del Pilar Ávila Olmeda 2021-2027; fue reformado por Decreto No. 119, publicado en el Periódico Oficial No. 43, Número Especial, de\nLey de Acceso de las Mujeres a una Vida Libre de Violencia Página 72\nGobernadora Constitucional la C. Marina del Pilar Ávila Olmeda 2021-2027; fue reformado por Decreto No. 119, publicado en el Periódico Oficial No. 43, Número Especial, de fecha 21\nConstitucional la C. Marina del Pilar Ávila Olmeda 2021-2027;\nARTICULO 43.- Fue reformado por Decreto No. 252, publicado en el Periódico Oficial\nNo. 38, de fecha 31 de agosto de 2012, Sección I, Tomo CXIX, expedido por la XX\nLegislatura, siendo Gobernador Constitucional el C. Lic. José Guadalupe Osuna Millán 20072013; fue reformado por Decreto No. 522, publicado en el Periódico Oficial No. 34, de fecha\n29 de julio de 2016, Sección VI, Tomo CXXIII, expedido por la H. XXI Legislatura, siendo\nGobernador Constitucional el C. Francisco Arturo Vega de Lamadrid 2013-2019; fue reformado por Decreto No. 426, publicado en el Periódico Oficial No. 23, de fecha 07 de mayo de 2024, Índice, Tomo CXXXI, expedido por la H. XXIV Legislatura, siendo Gobernadora\nConstitucional la C. Marina del Pilar Ávila Olmeda 2021-2027; fue reformado por Decreto No.\n119, publicado en el Periódico Oficial No. 43, Número Especial, de fecha 21 de julio de 2025, Tomo CXXXII, expedido por la H. XXV Legislatura, siendo Gobernadora Constitucional la C.\nMarina del Pilar Ávila Olmeda 2021-2027; fue reformado por Decreto No. 119, publicado en el\nPeriódico Oficial No. 43, Número Especial, de fecha 21 de julio de 2025, Tomo CXXXII, expedido por la H. XXV Legislatura, siendo Gobernadora Constitucional la C. Marina del Pilar\nÁvila Olmeda 2021-2027;\nARTÍCULO 44.- Fue reformado por Decreto No. 102, publicado en el Periódico Oficial\nNo. 54, de fecha 02 de septiembre de 2020, NÚMERO ESPECIAL, Tomo CXXVII, expedido por la H. XXIII Legislatura, siendo Gobernador Constitucional el C. Jaime Bonilla Valdez, 2019-2021;\nARTICULO 44 BIS.- Fue reformado por Decreto No. 455, publicado en el Periódico\nOficial No. 14, Sección IV, Tomo CXXIII, de fecha 18 de marzo de 2016, expedido por la H.\nXXI Legislatura, siendo Gobernador Constitucional el C. Francisco Arturo Vega de Lamadrid\n2013-2019; fue reformado por Decreto No. 102, publicado en el Periódico Oficial No. 54, de fecha 02 de septiembre de 2020, NÚMERO ESPECIAL, Tomo CXXVII, expedido por la H.\nXXIII Legislatura, siendo Gobernador Constitucional el C. Jaime Bonilla Valdez, 2019-2021;\nARTÍCULO 44 TER.- Fue adicionado por Decreto No. 102, publicado en el Periódico expedido por la H. XXIII Legislatura, siendo Gobernador Constitucional el C. Jaime Bonilla\nValdez, 2019-2021;\nARTÍCULO 44 QUATER.- Fue adicionado por Decreto No. 236, publicado en el\nH. XXIV Legislatura, siendo Gobernadora Constitucional la C. Marina del Pilar Ávila Olmeda\n2021-2027; fue reformado por Decreto No. 408, publicado en el Periódico Oficial No. 18, de\nLey de Acceso de las Mujeres a una Vida Libre de Violencia Página 73\nGobernadora Constitucional la C. Marina del Pilar Ávila Olmeda 2021-2027; fue reformado por Decreto No. 119, publicado en el Periódico Oficial No. 43, Número Especial, de fecha 21\nConstitucional la C. Marina del Pilar Ávila Olmeda 2021-2027; fue reformado por Decreto No.\n119, publicado en el Periódico Oficial No. 43, Número Especial, de fecha 21 de julio de 2025, Tomo CXXXII, expedido por la H. XXV Legislatura, siendo Gobernadora Constitucional la C.\nMarina del Pilar Ávila Olmeda 2021-2027;\nARTÍCULO 44 QUINQUIES.- Fue adicionado por Decreto No. 236, publicado en el\nPeriódico Oficial No. 33, de fecha 09 de junio de 2023, Índice, Tomo CXXX, expedido por la\nH. XXIV Legislatura, siendo Gobernadora Constitucional la C. Marina del Pilar Ávila Olmeda\n2021-2027; fue reformado mediante Decreto No. 294, publicado en el Periódico Oficial No.\n57, Índice, de fecha 06 de octubre de 2023, Tomo CXXX, expedido por la H. XXIV\nLegislatura, siendo Gobernadora Constitucional la C. Marina del Pilar Ávila Olmeda 20212027;\nFue modificado este Capítulo y su denominación mediante el Decreto No. 236, publicado en el Periódico Oficial No. 33, de fecha 09 de junio de 2023, Índice, Tomo CXXX, expedido por la\nH. XXIV Legislatura, siendo Gobernadora Constitucional la C. Marina del Pilar Ávila Olmeda\n2021-2027;\nCAPÍTULO III\nDEL PODER LEGISLATIVO\nArtículo 45. (…)\nFue adicionado este Capítulo mediante el Decreto No. 236, publicado en el Periódico Oficial\nNo. 33, de fecha 09 de junio de 2023, Índice, Tomo CXXX, expedido por la H. XXIV\nLegislatura, siendo Gobernadora Constitucional la C. Marina del Pilar Ávila Olmeda 20212027;\nCAPÍTULO IV\nARTICULO 46.- Fue reformado por Decreto No. 235, publicado en el Periódico Oficial\nLegislatura, siendo Gobernador Constitucional el C. Jaime Bonilla Valdez 2019-2021; fue reformado por Decreto No. 236, publicado en el Periódico Oficial No. 33, de fecha 09 de junio de 2023, Índice, Tomo CXXX, expedido por la H. XXIV Legislatura, siendo Gobernadora\nConstitucional la C. Marina del Pilar Ávila Olmeda 2021-2027;\nLey de Acceso de las Mujeres a una Vida Libre de Violencia Página 74\nFue modificado este Capítulo manteniendo la misma denominación, mediante el Decreto No.\nCXXX, expedido por la H. XXIV Legislatura, siendo Gobernadora Constitucional la C. Marina del Pilar Ávila Olmeda 2021-2027;\nCAPÍTULO V\nDE LOS MUNICIPIOS\nARTICULO 47.- Fue reformado por Decreto No. 78, publicado en el Periódico Oficial\nNo. 38, de fecha 25 de julio de 2014, Sección I, Tomo CXXI, expedido por la Honorable XXI\nLegislatura, siendo Gobernador Constitucional el C. Francisco Arturo Vega de Lamadrid, 2013-2019; fue reformado por Decreto No. 236, publicado en el Periódico Oficial No. 33, de fecha 09 de junio de 2023, Índice, Tomo CXXX, expedido por la H. XXIV Legislatura, siendo\nGobernadora Constitucional la C. Marina del Pilar Ávila Olmeda 2021-2027; fue reformado por Decreto No. 426, publicado en el Periódico Oficial No. 23, de fecha 07 de mayo de 2024, Índice, Tomo CXXXI, expedido por la H. XXIV Legislatura, siendo Gobernadora Constitucional la C. Marina del Pilar Ávila Olmeda 2021-2027; fue reformado por Decreto No. 119, publicado en el Periódico Oficial No. 43, Número Especial, de fecha 21 de julio de 2025, Tomo CXXXII, expedido por la H. XXV Legislatura, siendo Gobernadora Constitucional la C. Marina del Pilar\nÁvila Olmeda 2021-2027; fue reformado por Decreto No. 119, publicado en el Periódico\nOficial No. 43, Número Especial, de fecha 21 de julio de 2025, Tomo CXXXII, expedido por la\nH. XXV Legislatura, siendo Gobernadora Constitucional la C. Marina del Pilar Ávila Olmeda\n2021-2027;\nFue adicionado mediante Decreto No. 406, publicado en el Periódico Oficial No. 58, de fecha 18 de diciembre de 2015, Sección III, Tomo CXXII, expedido por la H. XXI Legislatura, siendo Gobernador Constitucional el C. Francisco Arturo Vega de Lamadrid 2013-2019;\nCAPÍTULO X\nDE LAS RESPONSABILIDADES Y SANCIONES\nFue adicionado este Título mediante el Decreto No. 236, publicado en el Periódico Oficial No.\n33, de fecha 09 de junio de 2023, Índice, Tomo CXXX, expedido por la H. XXIV Legislatura, siendo Gobernadora Constitucional la C. Marina del Pilar Ávila Olmeda 2021-2027;\nTITULO QUINTO\nDE LAS RESPONSABILIDADES Y SANCIONES,\nDEL REGISTRO PÚBLICO DE AGRESORES SEXUALES\nFue modificado este Capítulo manteniendo la misma denominación, mediante el Decreto No.\nCXXX, expedido por la H. XXIV Legislatura, siendo Gobernadora Constitucional la C. Marina del Pilar Ávila Olmeda 2021-2027;\nCAPÍTULO I\nLey de Acceso de las Mujeres a una Vida Libre de Violencia Página 75\nDE LAS RESPONSABILIDADES Y SANCIONES\nARTICULO 48. Fue adicionado mediante Decreto No. 406, publicado en el Periódico\nXXI Legislatura, siendo Gobernador Constitucional el C. Francisco Arturo Vega de Lamadrid\n2013-2019;\nFue adicionado este Capítulo por Decreto No. 235, publicado en el Periódico Oficial\nNo. 60, de fecha 13 de agosto de 2021, Sección IV, Tomo CXXVIII, expedido por la H. XXIII\nLegislatura, siendo Gobernador Constitucional el C. Jaime Bonilla Valdez 2019-2021;\nCAPÍTULO XI\nDEL REGISTRO PÚBLICO DE AGRESORES SEXUALES\nFue modificado este Capítulo manteniendo la misma denominación, mediante el Decreto No.\n236, publicado en el Periódico Oficial No. 33, de fecha 09 de junio de 2023, Índice, Tomo\nCXXX, expedido por la H. XXIV Legislatura, siendo Gobernadora Constitucional la C. Marina del Pilar Ávila Olmeda 2021-2027;\nCAPÍTULO II\nDEL REGISTRO PÚBLICO DE AGRESORES SEXUALES\nARTICULO 49.- Fue adicionado por Decreto No. 235, publicado en el Periódico Oficial\nNo. 60, de fecha 13 de agosto de 2021, Sección IV, Tomo CXXVIII, expedido por la H. XXIII\nLegislatura, siendo Gobernador Constitucional el C. Jaime Bonilla Valdez 2019-2021; fue reformado por Decreto No. 87, publicado en el Periódico Oficial No. 22, de fecha 25 de marzo de 2022, Índice, Tomo CXXIX, expedido por la H. XXIV Legislatura, siendo Gobernadora\nConstitucional la C. Marina del Pilar Ávila Olmeda 2021-2027;\nARTICULO 50.- Fue adicionado por Decreto No. 235, publicado en el Periódico Oficial\nLegislatura, siendo Gobernador Constitucional el C. Jaime Bonilla Valdez 2019-2021;\nARTICULO 51.- Fue adicionado por Decreto No. 235, publicado en el Periódico Oficial\nLegislatura, siendo Gobernador Constitucional el C. Jaime Bonilla Valdez 2019-2021;\nLey de Acceso de las Mujeres a una Vida Libre de Violencia Página 76\nARTÍCULO ÚNICO TRANSITORIO DEL DECRETO No. 252, POR EL QUE SE\nREFORMAN LOS ARTÍCULOS 19, 20 Y 43, PUBLICADO EN EL PERIÓDICO OFICIAL No.\nXX LEGISLATURA, SIENDO GOBERNADOR CONSTITUCIONAL EL C. JOSÉ GUADALUPE\nOSUNA MILLÁN 2007-2013.\nARTÍCULO TRANSITORIO\nÚNICO.- Las presentes reformas entrarán en vigor al día siguiente de su publicación en el Periódico Oficial del Estado de Baja California.\nDADO en el Salón de Sesiones “Lic. Benito Juárez García” del H. Poder Legislativo del\nEstado de Baja California, en la Ciudad de Mexicali, B.C., a los treinta y un días del mes de julio del año dos mil doce.\nDIP. ALFONSO GARZÓN ZATARAIN\nDIPUTADO PRESIDENTE\n(RÚBRICA)\nDIP. FAUSTO ZÁRATE ZEPEDA\nDIPUTADO SECRETARIO\n(RÚBRICA)\nDE CONFORMIDAD CON LO DISPUESTO POR LA FRACCIÓN I DEL ARTÍCULO 49\nMEXICALI, BAJA CALIFORNIA, A LOS CATORCE DÍAS DEL MES DE AGOSTO DEL\nAÑO DOS MIL DOCE.\nGOBERNADOR DEL ESTADO\nJOSÉ GUADALUPE OSUNA MILLÁN\n(RÚBRICA)\nSECRETARIO GENERAL DE GOBIERNO\nFRANCISCO ANTONIO GARCÍA BURGOS\n(RÚBRICA)\nARTÍCULO UNICO TRANSITORIO DEL DECRETO No. 407, POR EL QUE SE\nREFORMAN LOS ARTÍCULOS 5 Y 6, PUBLICADO EN EL PERIÓDICO OFICIAL No. 9,\nLEGISLATURA, SIENDO GOBERNADOR CONSTITUCIONAL EL C. JOSÉ GUADALUPE\nOSUNA MILLÁN 2007-2013.\nLey de Acceso de las Mujeres a una Vida Libre de Violencia Página 77\nARTÍCULO TRANSITORIO\nÚNICO: Las presentes reformas entrarán en vigor al día siguiente de su publicación en el Periódico Oficial del Estado de Baja California.\nEstado de Baja California, en la Ciudad de Mexicali, B.C., a los quince días del mes de enero del año dos mil trece.\nDIP. ELISA ROSANA SOTO AGÜERO\nVICEPRESIDENTE\n(RÚBRICA)\nDIP. FAUSTO ZÁRATE ZEPEDA\nSECRETARIO\n(RÚBRICA)\nDE CONFORMIDAD CON LO DISPUESTO POR LA FRACCIÓN I DEL ARTÍCULO 49\nMEXICALI, BAJA CALIFORNIA, A LOS VEINTICINCO DÍAS DEL MES DE ENERO\nDEL AÑO DOS MIL TRECE.\nJOSÉ GUADALUPE OSUNA MILLÁN\nGOBERNADOR DEL ESTADO\n(RÚBRICA)\nFRANCISCO ANTONIO GARCÍA BURGOS\nSECRETARIO GENERAL DE GOBIERNO\n(RÚBRICA)\nARTÍCULO UNICO TRANSITORIO DEL DECRETO No. 548, POR EL QUE SE\nADICIONA UNA FRACCIÓN X AL ARTÍCULO 28, PUBLICADO EN EL PERIÓDICO OFICIAL\nLA H. XX LEGISLATURA, SIENDO GOBERNADOR CONSTITUCIONAL EL C. JOSÉ\nGUADALUPE OSUNA MILLÁN 2007-2013;\nARTÍCULO TRANSITORIO\nLey de Acceso de las Mujeres a una Vida Libre de Violencia Página 78\nÚNICO: Las presentes reformas entrarán en vigor al día siguiente de su publicación en el Periódico Oficial del Estado de Baja California.\nEstado de Baja California, en la Ciudad de Mexicali, B.C., a los trece días del mes de septiembre del año dos mil trece.\nDIP. GREGORIO CARRANZA HERNÁNDEZ\nPRESIDENTE\n(RÚBRICA)\nDIP. MARCO ANTONIO VIZCARRA CALDERÓN\nSECRETARIO\n(RÚBRICA)\nDE CONFORMIDAD CON LO DISPUESTO POR LA FRACCION I DEL ARTÍCULO 49\nMEXICALI, BAJA CALIFORNIA, A LOS TREINTA DÍAS DEL MES DE SEPTIEMBRE\nDEL AÑO DOS MIL TRECE.\nJOSÉ GUADALUPE OSUNA MILLÁN\nGOBERNADOR DEL ESTADO\n(RÚBRICA)\nFRANCISCO ANTONIO GARCÍA BURGOS\nSECRETARIO GENERAL DE GOBIERNO\n(RÚBRICA)\nARTÍCULO UNICO TRANSITORIO DEL DECRETO No. 550, POR EL QUE SE\nADICIONA UN SEGUNDO PÁRRAFO AL ARTÍCULO 7, ASÍ COMO LA REFORMA A LOS\nARTÍCULOS 23 Y 24, PUBLICADO EN EL PERIÓDICO OFICIAL No. 46, TOMO CXX, DE\nGOBERNADOR CONSTITUCIONAL EL C. JOSÉ GUADALUPE OSUNA MILLÁN 2007-2013.\nARTÍCULO TRANSITORIO\nÚNICO: Las presentes reformas entrarán en vigor al día siguiente de su publicación en el Periódico Oficial del Estado de Baja California.\nLey de Acceso de las Mujeres a una Vida Libre de Violencia Página 79\nEstado de Baja California, en la Ciudad de Mexicali, B.C., a los trece días del mes de septiembre del año dos mil trece.\nDIP. GREGORIO CARRANZA HERNÁNDEZ\nPRESIDENTE\n(RÚBRICA)\nDIP. MARCO ANTONIO VIZCARRA CALDERÓN\nSECRETARIO\n(RÚBRICA)\nDE CONFORMIDAD CON LO DISPUESTO POR LA FRACCIÓN I DEL ARTÍCULO 49\nMEXICALI, BAJA CALIFORNIA, A LOS TREINTA DÍAS DEL MES DE SEPTIEMBRE\nDEL AÑO DOS MIL TRECE.\nJOSÉ GUADALUPE OSUNA MILLÁN\nGOBERNADOR DEL ESTADO\n(RÚBRICA)\nFRANCISCO ANTONIO GARCÍA BURGOS\nSECRETARIO GENERAL DE GOBIERNO\n(RÚBRICA)\nARTÍCULO UNICO TRANSITORIO DEL DECRETO No. 585, POR EL QUE SE\nREFORMA EL ARTÍCULO 33, PUBLICADO EN EL PERIÓDICO OFICIAL No. 47, TOMO\nCXX, DE FECHA 25 DE OCTUBRE DE 2013, SEECION I, EXPEDIDO POR LA H. XX\nLEGISLATURA, SIENDO GOBERNADOR CONSTITUCIONAL EL C. JOSÉ GUADALUPE\nOSUNA MILLÁN 2007-2013.\nARTÍCULO TRANSITORIO\nÚNICO: La presente reforma entrará en vigor al día siguiente de su publicación en el\nPeriódico Oficial del Estado de Baja California.\nEstado de Baja California, en la Ciudad de Mexicali, B.C., a los veinticinco días del mes de septiembre del año dos mil trece.\nDIP. GREGORIO CARRANZA HERNÁNDEZ\nPRESIDENTE\nLey de Acceso de las Mujeres a una Vida Libre de Violencia Página 80\n(RÚBRICA)\nDIP. MARCO ANTONIO VIZCARRA CALDERÓN\nSECRETARIO\n(RÚBRICA)\nDE CONFORMIDAD CON LO DISPUESTO POR LA FRACCIÓN I DEL ARTÍCULO 49\nMEXICALI, BAJA CALIFORNIA, A LOS DOS DÍAS DEL MES DE OCTUBRE DEL\nAÑO DOS MIL TRECE.\nJOSÉ GUADALUPE OSUNA MILLÁN\nGOBERNADOR DEL ESTADO\n(RÚBRICA)\nFRANCISCO ANTONIO GARCÍA BURGOS\nSECRETARIO GENERAL DE GOBIERNO\n(RÚBRICA)\nARTÍCULO UNICO TRANSITORIO DEL DECRETO No. 78, POR EL QUE SE\nREFORMAN LOS ARTÍCULOS 26, 47 Y LA ADICIÓN DEL ARTÍCULO 32, PUBLICADO EN\nEL PERIÓDICO OFICIAL No. 38, TOMO CXXI, DE FECHA 25 DE JULIO DE 2014, SEECION\nI, EXPEDIDO POR LA H. XXI LEGISLATURA, SIENDO GOBERNADOR CONSTITUCIONAL\nEL C. FRANCISCO ARTURO VEGA DE LAMADRID 2013-2019.\nARTÍCULOS TRANSITORIOS\nPRIMERO.- Las presentes reformas entrarán en vigor al día siguiente de su publicación en el Periódico Oficial del Estado.\nSEGUNDO.- Los Municipios contarán con un plazo de ciento veinte días naturales a partir de la entrada en vigor de la presente reforma para adecuar su normatividad vigente.\nRosarito, declarado Recinto Oficial mediante Decreto No. 62, en Sesión Ordinaria de la\nHonorable XXI Legislatura, a los 26 días del mes de junio del año 2014.\nDIP. FELIPE DE JESÚS MAYORAL MAYORAL\nPRESIDENTE\n(RÚBRICA)\nDIP. GERARDO ÁLVAREZ HERNÁNDEZ\nSECRETARIO\nLey de Acceso de las Mujeres a una Vida Libre de Violencia Página 81\n(RÚBRICA)\nDE CONFORMIDAD CON LO DISPUESTO POR LA FRACCIÓN I DEL ARTÍCULO 49\nMEXICALI, BAJA CALIFORNIA, A LOS OCHO DÍAS DEL MES DE JULIO DEL AÑO\nDOS MIL CATORCE.\nFRANCISCO ARTURO VEGA DE LAMADRID\nGOBERNADOR DEL ESTADO\n(RÚBRICA)\nFRANCISCO RUEDA GOMEZ\nSECRETARIO GENERAL DE GOBIERNO\n(RÚBRICA)\nARTÍCULO PRIMERO TRANSITORIOS DEL DECRETO No. 406, POR EL QUE SE\nREFORMAN LOS ARTÍCULOS 35 Y 42; PUBLICADO EN EL PERIÓDICO OFICIAL No. 58,\nSECCIÓN III, TOMO CXXII, DE FECHA 18 DE DICIEMBRE DE 2015, EXPEDIDO POR LA H.\nXXI LEGISLATURA, SIENDO GOBERNADOR CONSTITUCIONAL EL C. FRANCISCO\nARTURO VEGA DE LA MADRID 2013-2019.\nARTÍCULOS TRANSITORIOS\nPRIMERO. El presente Decreto entrará en vigor al día siguiente de su publicación en el Periódico Oficial del Estado de Baja California.\nSEGUNDO. A partir de la entrada en vigor del presente Decreto, el Ejecutivo Estatal deberá emitir, en un plazo no mayor noventa días naturales, las modificaciones a los\nReglamentos correspondientes.\nTERCERO. A partir de la entrada en vigor del presente Decreto, el Ejecutivo Estatal por conducto de la Secretaría de Seguridad Pública del Estado emitirá en un plazo no mayor a ciento veinte días naturales, los lineamientos para la operación del Base Estatal de Datos e\nInformación sobre Casos de Violencia contra las Mujeres.\nEstado de Baja California, en la Ciudad de Mexicali, B.C., a los veintiséis días del mes de noviembre del año dos mil quince.\nDIP. IRMA MARTÍNEZ MANRÍQUEZ\nPRESIDENTA\n(RÚBRICA)\nLey de Acceso de las Mujeres a una Vida Libre de Violencia Página 82\nDIP. MARIO OSUNA JIMÉNEZ\nSECRETARIO\n(RÚBRICA)\nDE CONFORMIDAD CON LO DISPUESTO POR LA FRACCIÓN I DEL ARTÍCULO 49\nMEXICALI, BAJA CALIFORNIA, A LOS DOS DÍAS DEL MES DE DICIEMBRE DEL\nAÑO DOS MIL QUINCE.\nFRANCISCO ARTURO VEGA DE LAMADRID\nGOBERNADOR DEL ESTADO\n(RÚBRICA)\nFRANCISCO RUEDA GÓMEZ\nSECRETARIO GENERAL DE GOBIERNO\n(RÚBRICA)\nARTÍCULO SEGUNDO TRANSITORIO DEL DECRETO No. 406, POR EL QUE SE\nREFORMAN LOS ARTÍCULOS 48 Y SE ADICIONA EL ARTÍCULO 38 BIS; PUBLICADO EN\nEL PERIÓDICO OFICIAL No. 58, SECCIÓN III, TOMO CXXII, DE FECHA 18 DE DICIEMBRE\nDE 2015, EXPEDIDO POR LA H. XXI LEGISLATURA, SIENDO GOBERNADOR\nCONSTITUCIONAL EL C. FRANCISCO ARTURO VEGA DE LA MADRID 2013-2019.\nARTÍCULOS TRANSITORIOS\nPRIMERO.- El presente Decreto entrará en vigor al día siguiente de su publicación en el Periódico Oficial del Estado de Baja California.\nSEGUNDO.- A partir de la entrada en vigor del presente Decreto, el Ejecutivo Estatal deberá emitir, en un plazo no mayor noventa días naturales, las modificaciones a los\nReglamentos correspondientes.\nTERCERO.- A partir de la entrada en vigor del presente Decreto, el Ejecutivo Estatal a ciento veinte días naturales, los lineamientos para la operación del Base Estatal de Datos e\nInformación sobre Casos de Violencia contra las Mujeres.\nEstado de Baja California, en la Ciudad de Mexicali, B.C., a los veintiséis días del mes de noviembre del año dos mil quince.\nLey de Acceso de las Mujeres a una Vida Libre de Violencia Página 83\nDIP. IRMA MARTÍNEZ MANRÍQUEZ\nPRESIDENTA\n(RÚBRICA)\nDIP. MARIO OSUNA JIMÉNEZ\nSECRETARIO\n(RÚBRICA)\nDE CONFORMIDAD CON LO DISPUESTO POR LA FRACCIÓN I DEL ARTÍCULO 49\nMEXICALI, BAJA CALIFORNIA, A LOS DOS DÍAS DEL MES DE DICIEMBRE DEL\nAÑO DOS MIL QUINCE.\nFRANCISCO ARTURO VEGA DE LAMADRID\nGOBERNADOR DEL ESTADO\n(RÚBRICA)\nFRANCISCO RUEDA GÓMEZ\nSECRETARIO GENERAL DE GOBIERNO\n(RÚBRICA)\nARTÍCULO UNICO TRANSITORIO DEL DECRETO No. 453, POR EL QUE SE\nADICIONAN LOS ARTÍCULOS 11 BIS Y 11 TER; PUBLICADO EN EL PERIÓDICO OFICIAL\nNo. 14, SECCION IV, TOMO CXXIII, DE FECHA 18 DE MARZO DE 2016, EXPEDIDO POR\nLA H. XXI LEGISLATURA, SIENDO GOBERNADOR CONSTITUCIONAL EL C. FRANCISCO\nARTURO VEGA DE LAMADRID 2013-2019.\nTRANSITORIOS\nÚNICO.- El presente Decreto entrará en vigor al día siguiente al de su publicación en el\nPeriódico Oficial del Estado.\nEstado de Baja California, en la Ciudad de Mexicali, B.C., a los dieciocho días del mes de febrero del año dos mil dieciséis.\nDIP. RODOLFO OLIMPO HERNÁNDEZ BOJÓRQUEZ\nPRESIDENTE\n(RÚBRICA)\nDIP. ARMANDO REYES LEDESMA\nSECRETARIO\nLey de Acceso de las Mujeres a una Vida Libre de Violencia Página 84\n(RÚBRICA)\nDE CONFORMIDAD CON LO DISPUESTO POR LA FRACCION I DEL ARTÍCULO 49\nMEXICALI, BAJA CALIFORNIA, A LOS DOS DÍAS DEL MES DE MARZO DEL AÑO DOS\nMIL DIECISÉIS.\nFRANCISCO ARTURO VEGA DE LAMADRID\nGOBERNADOR DEL ESTADO\n(RÚBRICA)\nFRANCISCO RUEDA GOMEZ\nSECRETARIO GENERAL DE GOBIERNO\n(RÚBRICA)\nARTÍCULO UNICO TRANSITORIO DEL DECRETO No. 454, POR EL QUE SE\nREFORMA EL ARTÍCULO 6; PUBLICADO EN EL PERIÓDICO OFICIAL No. 14, SECCION\nIV, TOMO CXXIII, DE FECHA 18 DE MARZO DE 2016, EXPEDIDO POR LA H. XXI\nLEGISLATURA, SIENDO GOBERNADOR CONSTITUCIONAL EL C. FRANCISCO ARTURO\nVEGA DE LAMADRID 2013-2019.\nARTÍCULO TRANSITORIO\nÚNICO.- El presente decreto entrará en vigor al día siguiente de su publicación en el\nPeriódico Oficial del Estado, órgano de difusión del Poder Ejecutivo del Estado de Baja\nCalifornia.\nDADO en el Salón de Sesiones “Lic. Benito Juárez García” del H. Poder Legislativo del\nEstado de Baja California, en la Ciudad de Mexicali, B.C., a los dieciocho días del mes de febrero del año dos mil dieciséis.\nDIP. RODOLFO OLIMPO HERNÁNDEZ BOJÓRQUEZ\nPRESIDENTE\n(RÚBRICA)\nDIP. ARMANDO REYES LEDESMA\nSECRETARIO\n(RÚBRICA)\nDE CONFORMIDAD CON LO DISPUESTO POR LA FRACCION I DEL ARTÍCULO 49\nMEXICALI, BAJA CALIFORNIA, A LOS DOS DÍAS DEL MES DE MARZO DEL AÑO DOS\nMIL DIECISÉIS.\nLey de Acceso de las Mujeres a una Vida Libre de Violencia Página 85\nFRANCISCO ARTURO VEGA DE LAMADRID\nGOBERNADOR DEL ESTADO\n(RÚBRICA)\nFRANCISCO RUEDA GOMEZ\nSECRETARIO GENERAL DE GOBIERNO\n(RÚBRICA)\nARTÍCULO UNICO TRANSITORIO DEL DECRETO No. 455, POR EL QUE SE\nREFORMA EL ARTÍCULO 32 Y SE ADICIONA EL ARTÍCULO 44 BIS; PUBLICADO EN EL\nPERIÓDICO OFICIAL No. 14, SECCION IV, TOMO CXXIII, DE FECHA 18 DE MARZO DE\n2016, EXPEDIDO POR LA H. XXI LEGISLATURA, SIENDO GOBERNADOR\nCONSTITUCIONAL EL C. FRANCISCO ARTURO VEGA DE LAMADRID 2013-2019.\nARTÍCULO TRANSITORIO\nÚNICO.- El presente decreto entrará en vigor al día siguiente de su publicación en el\nPeriódico Oficial del Estado, órgano de difusión del Poder Ejecutivo del Estado de Baja\nCalifornia.\nDADO en el Salón de Sesiones “Lic. Benito Juárez García” del H. Poder Legislativo del\nEstado de Baja California, en la Ciudad de Mexicali, B.C., a los dieciocho días del mes de febrero del año dos mil dieciséis.\nDIP. RODOLFO OLIMPO HERNÁNDEZ BOJÓRQUEZ\nPRESIDENTE\n(RÚBRICA)\nDIP. ARMANDO REYES LEDESMA\nSECRETARIO\n(RÚBRICA)\nDE CONFORMIDAD CON LO DISPUESTO POR LA FRACCION I DEL ARTÍCULO 49\nMEXICALI, BAJA CALIFORNIA, A LOS DOS DÍAS DEL MES DE MARZO DEL AÑO DOS\nMIL DIECISÉIS.\nFRANCISCO ARTURO VEGA DE LAMADRID\nGOBERNADOR DEL ESTADO\n(RÚBRICA)\nFRANCISCO RUEDA GOMEZ\nSECRETARIO GENERAL DE GOBIERNO\nLey de Acceso de las Mujeres a una Vida Libre de Violencia Página 86\n(RÚBRICA)\nARTÍCULO ÚNICO TRANSITORIO DEL DECRETO No. 515, POR EL QUE SE\nREFORMA EL ARTÍCULO 32; PUBLICADO EN EL PERIÓDICO OFICIAL No. 34, SECCIÓN\nLEGISLATURA, SIENDO GOBERNADOR CONSTITUCIONAL EL C. FRANCISCO ARTURO\nVEGA DE LA MADRID 2013-2019.\nARTÍCULO TRANSITORIO\nÚNICO.- El presente decreto entrará en vigor al día siguiente de su publicación en el\nPeriódico Oficial del Estado.\nDADO en el Salón de Sesiones “Lic. Benito Juárez García” del H. Poder Legislativo del\nEstado de Baja California, en la Ciudad de Mexicali, B.C., a los veintitrés días del mes de junio del año dos mil dieciséis.\nDIP. MÓNICA BEDOYA SERNA\nPRESIDENTA\n(RÚBRICA)\nDIP. ROSA ISELA PERALTA CASILLAS\nSECRETARIO\n(RÚBRICA)\nDE CONFORMIDAD CON LO DISPUESTO POR LA FRACCIÓN I DEL ARTÍCULO 49\nMEXICALI, BAJA CALIFORNIA, A LOS SEIS DÍAS DEL MES DE JULIO DEL AÑO\nDOS MIL DIECISÉIS.\nFRANCISCO RUEDA GÓMEZ\nSECRETARIO GENERAL DE GOBIERNO\nEn suplencia por la ausencia del Gobernador del\nEstado, con fundamento en los artículos 45 y 52\n(RÚBRICA)\nLORETO QUINTERO QUINTERO\nOFICIAL MAYOR DE GOBIERNO de Gobierno, con fundamento en los artículos 54 de la\nLey de Acceso de las Mujeres a una Vida Libre de Violencia Página 87\n(RÚBRICA)\nARTÍCULO ÚNICO TRANSITORIO DEL DECRETO No. 522, POR EL QUE SE\nREFORMAN LOS ARTÍCULOS 1, 2, 3, 4 FRACCIONES XI, XII, XIII Y XIV, ARTÍCULOS 5, 7,\n8 FRACCIONES I, II, III, IV, V, VI Y VII, ARTÍCULOS 9, 10, 11 FRACCIONES I, II, III, IV, V,\nVI Y VII, ARTÍCULOS 12, 13, 14, 15, 16 PRIMER PÁRRAFO Y FRACCIONES IV, V, Y VI,\nARTÍCULOS 17, 18 PRIMER Y SEGUNDO PÁRRAFO, FRACCIONES I, II, III, IV Y V,\nARTÍCULO 20 PRIMER PÁRRAFO Y FRACCIONES I Y II, ARTÍCULO 35 FRACCIÓN III, V,\nVI Y IX ARTÍCULO 38 FRACCIONES XIII, XIV Y XV, Y 43 FRACCIONES III, IX, XIV XV,\nXVI, XVII Y XVIII; PUBLICADO EN EL PERIÓDICO OFICIAL No. 34, SECCIÓN VI, TOMO\nCXXIII, DE FECHA 29 DE JULIO DE 2016, EXPEDIDO POR LA H. XXI LEGISLATURA,\nSIENDO GOBERNADOR CONSTITUCIONAL EL C. FRANCISCO ARTURO VEGA DE LA\nMADRID 2013-2019.\nARTÍCULO TRANSITORIO\nÚNICO.- El presente decreto entrará en vigor al día siguiente de su publicación en el periódico oficial del Estado, órgano de difusión del Poder Ejecutivo del Estado Libre y\nSoberano de Baja California.\nDADO en el Salón de Sesiones “Lic. Benito Juárez García” del H. Poder Legislativo del\nEstado de Baja California, en la Ciudad de Mexicali, B.C., a los treinta días del mes de Junio del año dos mil dieciséis.\nDIP. MÓNICA BEDOYA SERNA\nPRESIDENTA\n(RÚBRICA)\nDIP. ROSA ISELA PERALTA CASILLAS\nSECRETARIO\n(RÚBRICA)\nDE CONFORMIDAD CON LO DISPUESTO POR LA FRACCIÓN I DEL ARTÍCULO 49\nMEXICALI, BAJA CALIFORNIA, A LOS SEIS DÍAS DEL MES DE JULIO DEL AÑO\nDOS MIL DIECISÉIS.\nFRANCISCO RUEDA GÓMEZ\nSECRETARIO GENERAL DE GOBIERNO\nEstado, con fundamento en los artículos 45 y 52\nLey de Acceso de las Mujeres a una Vida Libre de Violencia Página 88\n(RÚBRICA)\nLORETO QUINTERO QUINTERO\nOFICIAL MAYOR DE GOBIERNO\nEn suplencia por la ausencia del Secretario General de Gobierno, con fundamento en los artículos 54 de la\n(RÚBRICA)\nARTÍCULO ÚNICO TRANSITORIO DEL DECRETO No. 229, POR EL QUE SE\nADICIONA EL INCISO i) DE LA FRACCIÓN III Y REFORMA DE LA FRACCIÓN V Y VII DEL\nARTÍCULO 82, PUBLICADO EN EL PERIÓDICO OFICIAL No. 20, SECCION VIII, TOMO\nCXXV, DE FECHA 20 DE ABRIL DE 2018, EXPEDIDO POR LA H. XXII LEGISLATURA,\nSIENDO GOBERNADOR CONSTITUCIONAL EL C. FRANCISCO ARTURO VEGA DE\nLAMADRID 2013-2019.\nARTÍCULO TRANSITORIO\nÚNICO.- La presente reforma entrara en vigor al día siguiente de su publicación en el\nPeriódico Oficial del Estado.\nDADO en el Salón de Sesiones “Lic. Benito Juárez García” del H. Poder Legislativo del\nEstado de Baja California, en la Ciudad de Mexicali, B.C., a los ocho días del mes de marzo del año dos mil dieciocho.\nDIP. MTRO. RAÚL CASTAÑEDA POMPOSO\nPRESIDENTE\n(RÚBRICA)\nDIP. ROCIO LÓPEZ GOROSAVE\nSECRETARIA\n(RÚBRICA)\nDE CONFORMIDAD CON LO DISPUESTO POR LA FRACCIÓN I DEL ARTÍCULO 49\nLey de Acceso de las Mujeres a una Vida Libre de Violencia Página 89\nMEXICALI, BAJA CALIFORNIA, A LOS DIEZ Y NUEVE DÍAS DEL MES DE ABRIL DEL AÑO\nDOS MIL DIECIOCHO.\nFRANCISCO ARTURO VEGA DE LAMADRID\nGOBERNADOR DEL ESTADO\n(RÚBRICA)\nFRANCISCO RUEDA GÓMEZ\nSECRETARIO GENERAL DE GOBIERNO\n(RÚBRICA)\nARTÍCULO ÚNICO TRANSITORIO DEL DECRETO No. 340, POR EL QUE SE\nAPRUEBA LA REFORMA A LOS ARTÍCULOS 4 Y 42, ASÍ COMO LA ADICIÓN DEL\nARTÍCULO 38 TER A LA LEY DE ACCESO DE LAS MUJERES A UNA VIDA LIBRE DE\nVIOLENCIA PARA EL ESTADO DE BAJA CALIFORNIA, PUBLICADO EN EL PERIÓDICO\nOFICIAL No. 26, SECCION IV, TOMO CXXVI, DE FECHA 14 DE JUNIO DE 2019,\nEXPEDIDO POR LA H. XXII LEGISLATURA, SIENDO GOBERNADOR CONSTITUCIONAL\nEL C. FRANCISCO ARTURO VEGA DE LAMADRID 2013-2019.\n.\nARTÍCULO TRANSITORIO\nÚNICO.- Las presentes reformas entrarán en vigor al día siguiente al de su publicación en el Periódico Oficial del Estado.\nDADO en el Salón de Sesiones “Lic. Benito Juárez García” del H. Poder Legislativo del\nEstado de Baja California, en la Ciudad de Mexicali, B.C., a los diez días del mes de abril del año dos mil diecinueve.\nDIP. EDGAR BENJAMÍN GÓMEZ MACÍAS\nPRESIDENTE\n(RÚBRICA)\nDIP. ROCIO LÓPEZ GOROSAVE\nPROSECRETARIA\n(RÚBRICA)\nLey de Acceso de las Mujeres a una Vida Libre de Violencia Página 90\nDE CONFORMIDAD CON LO DISPUESTO POR LA FRACCIÓN I DEL ARTÍCULO 49\nMEXICALI, BAJA CALIFORNIA, A LOS SIETE DÍAS DEL MES DE JUNIO DEL AÑO DOS\nMIL DIECINUEVE.\nFRANCISCO ARTURO VEGA DE LAMADRID\nGOBERNADOR DEL ESTADO\n(RÚBRICA)\nFRANCISCO RUEDA GÓMEZ\nSECRETARIO GENERAL DE GOBIERNO\n(RÚBRICA)\nARTÍCULO SEGUNDO TRANSITORIO DEL DECRETO No. 84, POR EL QUE SE\nAPRUEBA LA REFORMA AL ARTÍCULO 6, PUBLICADO EN EL PERIÓDICO OFICIAL No.\n40, ÍNDICE, TOMO CXXVII, DE FECHA 10 DE JULIO DE 2020, EXPEDIDO POR LA H. XXIII\nLEGISLATURA, SIENDO GOBERNADOR CONSTITUCIONAL EL C. JAIME BONILLA\nVALDEZ 2019-2021.\nARTÍCULO TRANSITORIO\nÚNICO.- El presente Decreto entrará en vigor al día siguiente de su publicación en el\nPeriódico Oficial del Estado.\nDADO en el Salón de Sesiones “Lic. Benito Juárez García” del H. Poder Legislativo del\nEstado de Baja California, en la Ciudad de Mexicali, B.C., al primer día del mes de julio del año dos mil veinte.\nDIP. JULIO CÉSAR VÁZQUEZ CASTILLO\nVICEPRESIDENTE\n(RÚBRICA)\nDIP. EVA GRICELDA RODRÍGUEZ\nSECRETARIA\n(RÚBRICA)\nLey de Acceso de las Mujeres a una Vida Libre de Violencia Página 91\nDE CONFORMIDAD CON LO DISPUESTO POR LA FRACCIÓN I DEL ARTÍCULO 49\nMEXICALI, BAJA CALIFORNIA, A LOS DOS DÍAS DEL MES DE JULIO DEL AÑO DOS MIL\nVEINTE.\nJAIME BONILLA VALDEZ\nGOBERNADOR DEL ESTADO\n(RÚBRICA)\nAMADOR RODRÍGUEZ LOZANO\nSECRETARIO GENERAL DE GOBIERNO\n(RÚBRICA)\nARTÍCULO CUARTO TRANSITORIO DEL DECRETO No. 102, POR EL QUE SE\nREFORMAN LOS ARTÍCULOS 3, 11 BIS, 11TER, 21, 32, 36, 38 BIS, 39, 42, 44, 44 BIS, ASÍ\nCOMO LA ADICIÓN DE UN ARTÍCULO 44 TER; PUBLICADO EN EL PERIÓDICO OFICIAL\nNo. 54, NÚMERO ESPECIAL, TOMO CXXVII, DE FECHA 02 DE SEPTIEMBRE DE 2020,\nEXPEDIDO POR LA H. XXIII LEGISLATURA, SIENDO GOBERNADOR CONSTITUCIONAL\nEL C. JAIME BONILLA VALDEZ 2019-2021.\nARTÍCULOS TRANSITORIOS\nÚNICO.- La presente reforma entrará en vigor al día siguiente de su publicación en el\nPeriódico Oficial del Estado.\nDADO en Sesión Ordinaria Virtual, en la Ciudad de Mexicali, B.C., a los veintiséis días del mes de agosto del año dos mil veinte.\nDIP. JULIO CÉSAR VÁZQUEZ CASTILLO\nPRESIDENTE\n(RÚBRICA)\nDIP. EVA GRICELDA RODRÍGUEZ\nSECRETARIA\n(RÚBRICA)\nLey de Acceso de las Mujeres a una Vida Libre de Violencia Página 92\nDE CONFORMIDAD CON LO DISPUESTO POR LA FRACCIÓN I DEL ARTÍCULO 49\nCALIFORNIA, IMPRÍMASE Y PUBLÍQUESE.\nMEXICALI, BAJA CALIFORNIA, A LOS VEINTIOCHO DÍAS DEL MES DE AGOSTO DEL\nAÑO DOS MIL VEINTE.\nJAIME BONILLA VALDEZ\nGOBERNADOR DEL ESTADO\n(RÚBRICA)\nAMADOR RODRÍGUEZ LOZANO\nSECRETARIO GENERAL DE GOBIERNO\n(RÚBRICA)\nARTÍCULO PRIMERO TRANSITORIO DEL DECRETO No. 235, POR EL QUE SE\nAPRUEBA LA REFORMA A LOS ARTÍCULOS 38, 46; LA ADICIÓN DE UN CAPÍTULO XI\nDENOMINADO DEL REGISTRO PÚBLICO DE AGRESORES SEXUALES; LA ADICIÓN DE\nLOS ARTÍCULOS 49, 50 Y 51; PUBLICADO EN EL PERIÓDICO OFICIAL No. 60, SECCIÓN\nIV, TOMO CXXVIII, DE FECHA 13 DE AGOSTO DE 2021, EXPEDIDO POR LA H. XXIII\nLEGISLATURA, SIENDO GOBERNADOR CONSTITUCIONAL EL C. JAIME BONILLA\nVALDEZ 2019-2021.\nARTÍCULOS TRANSITORIOS\nPRIMERO. La presente reforma entrará en vigor al día siguiente de su publicación en el Periódico Oficial del Estado.\nSEGUNDO. El Ejecutivo del Estado dentro del os noventa días hábiles siguientes contados a partir de la entrada en vigor del presente Decreto, realizará las modificaciones reglamentarias correspondientes.\nTERCERO. Dentro de los ciento veinte días naturales contados a partir de la entrada en vigor de la presente reforma el Ejecutivo del Estado, realizará las acciones administración\nPersonas Agresoras Sexuales del Estado de Baja California.\nDADO en Sesión Ordinaria Virtual en la Ciudad de Mexicali, B.C., a los cinco días del mes de mayo del año dos mil veintiuno.\nDIP. EVA GRICELDA RODRÍGUEZ\nPRESIDENTE\n(RÚBRICA)\nLey de Acceso de las Mujeres a una Vida Libre de Violencia Página 93\nDIP. MARÍA LUISA VILLALOBOS ÁVILA\nSECRETARIA\n(RÚBRICA)\nDE CONFORMIDAD CON LO DISPUESTO POR LA FRACCIÓN I DEL ARTÍCULO 49\nCALIFORNIA, IMPRÍMASE Y PUBLÍQUESE.\nMEXICALI, BAJA CALIFORNIA, A LOS DIEZ DÍAS DEL MES DE JUNIO DEL AÑO DOS MIL\nVEINTIUNO.\nJAIME BONILLA VALDEZ\nGOBERNADOR DEL ESTADO\n(RÚBRICA)\nAMADOR RODRÍGUEZ LOZANO\nSECRETARIO GENERAL DE GOBIERNO\n(RÚBRICA)\nARTÍCULO PRIMERO TRANSITORIO DEL DECRETO No. 75, POR EL QUE SE\nREFORMAN LOS ARTÍCULOS 23, 25 Y 42; PUBLICADO EN EL PERIÓDICO OFICIAL No.\n11, SECCIÓN IV, TOMO CXXIX, DE FECHA 11 DE FEBRERO DE 2022, EXPEDIDO POR\nLA H. XXIV LEGISLATURA, SIENDO GOBERNADORA CONSTITUCIONAL LA C. MARINA\nDEL PILAR ÁVILA OLMEDA 2021-2027.\nTRANSITORIOS\nÚNICO. El presente Decreto entrará en vigor al día siguiente de su publicación en el\nPeriódico Oficial del Estado.\nDADO en Sesión Ordinaria Virtual de la XXIV Legislatura en la Ciudad de Mexicali, B.C., a los veintisiete días del mes de enero del año dos mil veintidós.\nDIP. JUAN MANUEL MOLINA GARCÍA\nPRESIDENTE\n(RÚBRICA)\nDIP. ARACELI GERALDO NÚÑEZ\nSECRETARIA\nLey de Acceso de las Mujeres a una Vida Libre de Violencia Página 94\n(RÚBRICA)\nDE CONFORMIDAD CON LO DISPUESTO POR LA FRACCIÓN I DEL ARTÍCULO 49\nCALIFORNIA, IMPRÍMASE Y PUBLÍQUESE.\nMEXICALI, BAJA CALIFORNIA, A LOS DOS DÍAS DEL MES DE FEBRERO DEL AÑO DOS\nMIL VEINTIDÓS.\nMARINA DEL PILAR ÁVILA OLMEDA\nGOBERNADORA DEL ESTADO\nDE BAJA CALIFORNIA\n(RÚBRICA)\nCATALINO ZAVALA MÁRQUEZ\nSECRETARIO GENERAL DE GOBIERNO\nDEL ESTADO DE BAJA CALIFORNIA\n(RÚBRICA)\nARTÍCULO SEGUNDO TRANSITORIO DEL DECRETO No. 87, POR EL QUE SE\nREFORMA EL ARTÍCULO 49, COMO TAMBIÉN, SE ADICIONA UN ARTÍCULO 10 BIS;\nPUBLICADO EN EL PERIÓDICO OFICIAL No. 22, ÍNDICE, TOMO CXXIX, DE FECHA 25 DE\nMARZO DE 2022, EXPEDIDO POR LA H. XXIV LEGISLATURA, SIENDO GOBERNADORA\nCONSTITUCIONAL LA C. MARINA DEL PILAR ÁVILA OLMEDA 2021-2027.\nTRANSITORIOS\nÚNICO. La presente reforma entrará en vigor al día siguiente de su publicación en el\nPeriódico Oficial del Estado.\nDADO en Sesión Ordinaria de la XXIV Legislatura en la Ciudad de Mexicali, B.C., a los diez días del mes de marzo del año dos mil veintidós.\nDIP. JUAN MANUEL MOLINA GARCÍA\nPRESIDENTE\n(RÚBRICA)\nLey de Acceso de las Mujeres a una Vida Libre de Violencia Página 95\nDIP. ARACELI GERALDO NÚÑEZ\nSECRETARIA\n(RÚBRICA)\nDE CONFORMIDAD CON LO DISPUESTO POR LA FRACCIÓN I DEL ARTÍCULO 49\nCALIFORNIA, IMPRÍMASE Y PUBLÍQUESE.\nMEXICALI, BAJA CALIFORNIA, A LOS ONCE DÍAS DEL MES DE MARZO DEL AÑO DOS\nMIL VEINTIDÓS.\nMARINA DEL PILAR ÁVILA OLMEDA\nGOBERNADORA DEL ESTADO\nDE BAJA CALIFORNIA\n(RÚBRICA)\nCATALINO ZAVALA MÁRQUEZ\nSECRETARIO GENERAL DE GOBIERNO\nDEL ESTADO DE BAJA CALIFORNIA\n(RÚBRICA)\nARTÍCULO CUARTO TRANSITORIO DEL DECRETO No. 198, POR EL QUE SE\nADICIONA EL ARTÍCULO 41 BIS; PUBLICADO EN EL PERIÓDICO OFICIAL No. 6, ÍNDICE,\nTOMO CXXX, DE FECHA 27 DE ENERO DE 2023, EXPEDIDO POR LA H. XXIV\nLEGISLATURA, SIENDO GOBERNADORA CONSTITUCIONAL LA C. MARINA DEL PILAR\nÁVILA OLMEDA 2021-2027.\nTRANSITORIOS\nPRIMERO. EI presente Decreto entrará en vigor al día siguiente de su publicación en el Periódico Oficial del Estado.\nSEGUNDO. El suministro gratuito de productos de gestión menstrual se sujetará a la disposiciones normativas aplicables en términos de la Ley General de Salud.\nDADO en Sesión Ordinaria de la XXIV Legislatura en la Ciudad de Mexicali, B.C., a los doce días del mes de enero del año dos mil veintitrés.\nLey de Acceso de las Mujeres a una Vida Libre de Violencia Página 96\nDIP. MARÍA DEL ROCÍO ADAME MUÑOZ\nPRESIDENTA\n(RÚBRICA)\nDIP. DUNNIA MONTSERRAT MURILLO LÓPEZ\nSECRETARIA\n(RÚBRICA)\nDE CONFORMIDAD CON LO DISPUESTO POR LA FRACCIÓN I DEL ARTÍCULO 49\nCALIFORNIA, IMPRÍMASE Y PUBLÍQUESE.\nMEXICALI, BAJA CALIFORNIA, A LOS TRECE DÍAS DEL MES DE ENERO DEL AÑO DOS\nMIL VEINTITRÉS.\nMARINA DEL PILAR ÁVILA OLMEDA\nGOBERNADORA DEL ESTADO\nDE BAJA CALIFORNIA\n(RÚBRICA)\nCATALINO ZAVALA MÁRQUEZ\nSECRETARIO GENERAL DE GOBIERNO\nDEL ESTADO DE BAJA CALIFORNIA\n(RÚBRICA)\nARTÍCULO PRIMERO TRANSITORIO DEL DECRETO No. 218, POR EL QUE SE\nREFORMAN LOS ARTÍCULOS 6, 7 Y 25; PUBLICADO EN EL PERIÓDICO OFICIAL No. 13,\nLA H. XXIV LEGISLATURA, SIENDO GOBERNADORA CONSTITUCIONAL LA C. MARINA\nDEL PILAR ÁVILA OLMEDA 2021-2027.\nTRANSITORIOS\nÚNICO. EI presente Decreto entrará en vigor el día siguiente a su publicación en el\nPeriódico Oficial del Estado.\nDADO en Sesión Ordinaria de la XXIV Legislatura en la Ciudad de Mexicali, B.C., a los dos días del mes de marzo del año dos mil veintitrés.\nLey de Acceso de las Mujeres a una Vida Libre de Violencia Página 97\nDIP. MARÍA DEL ROCÍO ADAME MUÑOZ\nPRESIDENTA\n(RÚBRICA)\nDIP. DUNNIA MONTSERRAT MURILLO LÓPEZ\nSECRETARIA\n(RÚBRICA)\nDE CONFORMIDAD CON LO DISPUESTO POR LA FRACCIÓN I DEL ARTÍCULO 49\nCALIFORNIA, IMPRÍMASE Y PUBLÍQUESE.\nMEXICALI, BAJA CALIFORNIA, A LOS DIEZ DÍAS DEL MES DE MARZO DEL AÑO DOS\nMIL VEINTITRÉS.\nMARINA DEL PILAR ÁVILA OLMEDA\nGOBERNADORA DEL ESTADO\nDE BAJA CALIFORNIA\n(RÚBRICA)\nCATALINO ZAVALA MÁRQUEZ\nSECRETARIO GENERAL DE GOBIERNO\nDEL ESTADO DE BAJA CALIFORNIA\n(RÚBRICA)\nARTÍCULO ÚNICO TRANSITORIO DEL DECRETO No. 236, POR EL QUE SE\nAPRUEBA LA REFORMA DE LOS ARTÍCULOS 1, 2, 3, 4, 8, 9, 10, 11,13, 16, 17, 19, 20, 21,\n22, 23, 24, 25, 26, 27, 28, 29, 30, 31, 32, 33, 35, 36, 37, 38, 41, 42, 46, 47 Y LA ADICIÓN\nDE LOS ARTÍCULOS 3 BIS, 9 BIS, 20 BIS, 20 TER, 26 BIS, 26 TER, 26 QUATER, 26\nQUINQUIES, 26 SEXIES, 26 SEPTIES, 26 OCTIES, 26 NONIES, 26 DIECIES, 26 UNDICIES,\n26 DUODECIES, 26 TERDECIES, 26 QUATERDECIES, 28 BIS, 29 BIS, 29 TER, 37 BIS, 37\nTER, 37 QUATER, 37 QUINQUIES, 44 QUATER Y 44 QUINQUIES, ASÍ COMO DIVERSAS\nMODIFICACIONES EN LOS TÍTULOS Y CAPÍTULOS; PUBLICADO EN EL PERIÓDICO\nPOR LA H. XXIV LEGISLATURA, SIENDO GOBERNADORA CONSTITUCIONAL LA C.\nMARINA DEL PILAR ÁVILA OLMEDA 2021-2027.\nARTICULOS TRANSITORIOS\nPRIMERO: La presente reforma entrará en vigor al día siguiente de su publicación en el\nPeriódico Oficial del Estado.\nLey de Acceso de las Mujeres a una Vida Libre de Violencia Página 98\nSEGUNDO: Las entidades, organismos y dependencias Estatales y Municipales que en el otorgamiento de órdenes de protección y la atención de las víctimas directas e indirectas, tendrán la obligación de actualizar sus reglamentos y protocolos internos de actuación, en un término no mayor a 90 días naturales contados a partir de la publicación de la presente reforma.\nTERCERO: El Sistema Estatal y el Poder Ejecutivo, en un plazo que no exceda de sesenta días naturales después de publicado el presente Decreto, deberán llevar a cabo las acciones necesarias para reformar el Reglamento, en aquellas partes que resulten necesarias para la implantación de este ordenamiento a través de un proceso participativo, tomando en cuenta la experiencia de quienes han participado en las alertas solicitadas.\nCUARTO: Para el cumplimiento de todas las acciones que deriven de la presente reforma, las entidades, organismos y dependencias Estatales y Municipales, estarán sujetas a la disponibilidad presupuestal para el ejercicio fiscal en el que entre en vigor la presente reforma; no excluyendo la responsabilidad de las entidades, organismos y dependencias\nEstatales y Municipales de programar y presupuestar para el inmediato ejercicio fiscal, el recurso que se requiera para el cumplimiento de lo dispuesto por la Ley.\nDADO en Sesión Ordinaria de la XXIV Legislatura en la Ciudad de Mexicali, B.C., a los veinticinco días del mes de mayo del año dos mil veintitrés.\nDIP. MANUEL GUERRERO LUNA\nPRESIDENTE\n(RÚBRICA)\nDIP. ALEJANDRA MARÍA ANG HERNÁNDEZ\nSECRETARIA\n(RÚBRICA)\nDE CONFORMIDAD CON LO DISPUESTO POR LA FRACCIÓN I DEL ARTÍCULO 49\nCALIFORNIA, IMPRÍMASE Y PUBLÍQUESE.\nMEXICALI, BAJA CALIFORNIA, A LOS TREINTA DÍAS DEL MES DE MAYO DEL AÑO DOS\nMIL VEINTITRÉS.\nMARINA DEL PILAR ÁVILA OLMEDA\nGOBERNADORA DEL ESTADO\nDE BAJA CALIFORNIA\n(RÚBRICA)\nLey de Acceso de las Mujeres a una Vida Libre de Violencia Página 99\nCATALINO ZAVALA MÁRQUEZ\nSECRETARIO GENERAL DE GOBIERNO\nDEL ESTADO DE BAJA CALIFORNIA\n(RÚBRICA)\nARTÍCULO ÚNICO TRANSITORIO DEL DECRETO No. 237, POR EL QUE SE\nREFORMA AL ARTÍCULO 6; PUBLICADO EN EL PERIÓDICO OFICIAL No. 33, ÍNDICE, DE\nFECHA 09 DE JUNIO DE 2023, TOMO CXXX, EXPEDIDO POR LA H. XXIV LEGISLATURA,\nSIENDO GOBERNADORA CONSTITUCIONAL LA C. MARINA DEL PILAR ÁVILA OLMEDA\n2021-2027.\nTRANSITORIOS\nÚNICO. La presente reforma entrará en vigor al día siguiente de su publicación en el\nPeriódico Oficial del Estado.\nDADO en Sesión Ordinaria de la XXIV Legislatura en la Ciudad de Mexicali, B.C., a los veinticinco días del mes de mayo del año dos mil veintitrés.\nDIP. MANUEL GUERRERO LUNA\nPRESIDENTE\n(RÚBRICA)\nDIP. ALEJANDRA MARÍA ANG HERNÁNDEZ\nSECRETARIA\n(RÚBRICA)\nDE CONFORMIDAD CON LO DISPUESTO POR LA FRACCIÓN I DEL ARTÍCULO 49\nCALIFORNIA, IMPRÍMASE Y PUBLÍQUESE.\nMEXICALI, BAJA CALIFORNIA, A LOS TREINTA DÍAS DEL MES DE MAYO DEL AÑO DOS\nMIL VEINTITRÉS.\nMARINA DEL PILAR ÁVILA OLMEDA\nGOBERNADORA DEL ESTADO\nDE BAJA CALIFORNIA\n(RÚBRICA)\nCATALINO ZAVALA MÁRQUEZ\nSECRETARIO GENERAL DE GOBIERNO\nDEL ESTADO DE BAJA CALIFORNIA\n(RÚBRICA)\nLey de Acceso de las Mujeres a una Vida Libre de Violencia Página 100\nARTÍCULO SEGUNDO TRANSITORIO DEL DECRETO No. 294, POR EL QUE SE\nAPRUEBA LA REFORMA A LOS ARTÍCULOS 3 BIS, 7, 8, 28, 32, 35, 36 Y 44 QUINQUIES;\nPUBLICADO EN EL PERIÓDICO OFICIAL No. 57, ÍNDICE, DE FECHA 06 DE OCTUBRE DE\n2023, TOMO CXXX, EXPEDIDO POR LA H. XXIV LEGISLATURA, SIENDO\nGOBERNADORA CONSTITUCIONAL LA C. MARINA DEL PILAR ÁVILA OLMEDA 2021 –\n2027.\nTRANSITORIO\nÚNICO.- La presente reforma entrará en vigor al día siguiente de su publicación en el\nPeriódico Oficial del Estado de Baja California.\nDADO en Sesión Ordinaria de la XXIV Legislatura en la Ciudad de Mexicali, B.C., a los veintiún días del mes de septiembre del año dos mil veintitrés.\nDIP. MANUEL GUERRERO LUNA\nPRESIDENTE\n(RÚBRICA)\nDIP. DUNNIA MONTSERRAT MURILLO LÓPEZ\nSECRETARIA\n(RÚBRICA)\nDE CONFORMIDAD CON LO DISPUESTO POR LA FRACCION I DEL ARTÍCULO 49\nCALIFORNIA, IMPRÍMASE Y PUBLÍQUESE.\nMEXICALI, BAJA CALIFORNIA, A LOS VEINTICINCO DÍAS DEL MES DE\nSEPTIEMBRE DEL AÑO DOS MIL VEINTITRÉS.\nMARINA DEL PILAR ÁVILA OLMEDA\nGOBERNADORA DEL ESTADO\nDE BAJA CALIFORNIA\n(RÚBRICA)\nCATALINO ZAVALA MÁRQUEZ\nSECRETARIO GENERAL DE GOBIERNO\nDEL ESTADO DE BAJA CALIFORNIA\n(RÚBRICA)\nARTÍCULO PRIMERO TRANSITORIO DEL DECRETO No. 297, POR EL QUE SE\nAPRUEBA LA REFORMA AL ARTÍCULO 6; PUBLICADO EN EL PERIÓDICO OFICIAL No.\nLey de Acceso de las Mujeres a una Vida Libre de Violencia Página 101\nXXIV LEGISLATURA, SIENDO GOBERNADORA CONSTITUCIONAL LA C. MARINA DEL\nPILAR ÁVILA OLMEDA 2021-2027.\nTRANSITORIO\nÚNICO.- El presente decreto entrará en vigor al día siguiente de su publicación en el\nPeriódico Oficial del Estado de Baja California.\nDADO en Sesión Ordinaria de la XXIV Legislatura en la Ciudad de Mexicali, B.C., a los diecinueve días del mes de octubre del año dos mil veintitrés.\nDIP. MANUEL GUERRERO LUNA\nPRESIDENTE\n(RÚBRICA)\nDIP. DUNNIA MONTSERRAT MURILLO LÓPEZ\nSECRETARIA\n(RÚBRICA)\nDE CONFORMIDAD CON LO DISPUESTO POR LA FRACCIÓN I DEL ARTÍCULO 49\nCALIFORNIA, IMPRÍMASE Y PUBLÍQUESE.\nMEXICALI, BAJA CALIFORNIA, A LOS VEINTITRÉS DÍAS DEL MES DE OCTUBRE\nDEL AÑO DOS MIL VEINTITRÉS.\nMARINA DEL PILAR ÁVILA OLMEDA\nGOBERNADORA DEL ESTADO\nDE BAJA CALIFORNIA\n(RÚBRICA)\nCATALINO ZAVALA MÁRQUEZ\nSECRETARIO GENERAL DE GOBIERNO\nDEL ESTADO DE BAJA CALIFORNIA\n(RÚBRICA)\nARTÍCULO CUARTO TRANSITORIO DEL DECRETO No. 318, POR EL QUE SE\nAPRUEBA LA REFORMA AL ARTÍCULO 39; PUBLICADO EN EL PERIÓDICO OFICIAL No.\nH. XXIV LEGISLATURA, SIENDO GOBERNADORA CONSTITUCIONAL LA C. MARINA DEL\nPILAR ÁVILA OLMEDA 2021-2027.\nTRANSITORIO\nLey de Acceso de las Mujeres a una Vida Libre de Violencia Página 102\nÚNICO.- La presente reforma entrará en vigor al día siguiente de su publicación en el\nPeriódico Oficial del Estado de Baja California.\nDADO en Sesión Ordinaria de la XXIV Legislatura en la Ciudad de Mexicali, B.C., a los nueve días del mes de noviembre del año dos mil veintitrés.\nDIP. MANUEL GUERRERO LUNA\nPRESIDENTE\n(RÚBRICA)\nDIP. DUNNIA MONTSERRAT MURILLO LÓPEZ\nSECRETARIA\n(RÚBRICA)\nDE CONFORMIDAD CON LO DISPUESTO POR LA FRACCIÓN I DEL ARTÍCULO 49\nCALIFORNIA, IMPRÍMASE Y PUBLÍQUESE.\nMEXICALI, BAJA CALIFORNIA, A LOS CATORCE DÍAS DEL MES DE NOVIEMBRE\nDEL AÑO DOS MIL VEINTITRÉS.\nMARINA DEL PILAR ÁVILA OLMEDA\nGOBERNADORA DEL ESTADO\nDE BAJA CALIFORNIA\n(RÚBRICA)\nCATALINO ZAVALA MÁRQUEZ\nSECRETARIO GENERAL DE GOBIERNO\nDEL ESTADO DE BAJA CALIFORNIA\n(RÚBRICA)\nARTÍCULO PRIMERO TRANSITORIO DEL DECRETO No. 336, POR EL QUE SE\nAPRUEBA LA REFORMA AL ARTÍCULO 6, COMO TAMBIEN LA ADICIÓN DEL NUMERAL\n11 QUATER; PUBLICADO EN EL PERIÓDICO OFICIAL No. 70, DE FECHA 08 DE\nLEGISLATURA, SIENDO GOBERNADORA CONSTITUCIONAL LA C. MARINA DEL PILAR\nÁVILA OLMEDA 2021-2027.\nTRANSITORIOS\nÚNICO.- La presente reforma entrará en vigor al día siguiente de su publicación en el\nPeriódico Oficial del Estado.\nDADO en Sesión Ordinaria de la XXIV Legislatura en la Ciudad de Mexicali, B.C., a los dieciséis días del mes de noviembre del año dos mil veintitrés.\nLey de Acceso de las Mujeres a una Vida Libre de Violencia Página 103\nDIP. MANUEL GUERRERO LUNA\nPRESIDENTE\n(RÚBRICA)\nDIP. DUNNIA MONTSERRAT MURILLO LÓPEZ\nSECRETARIA\n(RÚBRICA)\nDE CONFORMIDAD CON LO DISPUESTO POR LA FRACCIÓN I DEL ARTÍCULO 49\nCALIFORNIA, IMPRÍMASE Y PUBLÍQUESE.\nMEXICALI, BAJA CALIFORNIA, A LOS VEINTITRÉS DÍAS DEL MES DE\nNOVIEMBRE DEL AÑO DOS MIL VEINTITRÉS.\nMARINA DEL PILAR ÁVILA OLMEDA\nGOBERNADORA DEL ESTADO\nDE BAJA CALIFORNIA\n(RÚBRICA)\nCATALINO ZAVALA MÁRQUEZ\nSECRETARIO GENERAL DE GOBIERNO\nDEL ESTADO DE BAJA CALIFORNIA\n(RÚBRICA)\nARTÍCULO SEGUNDO TRANSITORIO DEL DECRETO No. 377, POR EL QUE SE\nAPRUEBA LA REFORMA AL ARTÍCULO 6; PUBLICADO EN EL PERIÓDICO OFICIAL No. 7,\nDE FECHA 09 DE FEBRERO DE 2024, ÍNDICE, TOMO CXXXI, EXPEDIDO POR LA H. XXIV\nLEGISLATURA, SIENDO GOBERNADORA CONSTITUCIONAL LA C. MARINA DEL PILAR\nÁVILA OLMEDA 2021-2027.\nTRANSITORIOS\nÚNICO.- La presente reforma entrará en vigor al día siguiente de su publicación en el\nPeriódico Oficial del Estado.\nDADO en Sesión Ordinaria de la XXIV Legislatura en la Ciudad de Mexicali, B.C., a los veinticinco días del mes de enero del año dos mil veinticuatro.\nDIP. ARACELI GERALDO NÚÑEZ\nPRESIDENTA\n(RÚBRICA)\nLey de Acceso de las Mujeres a una Vida Libre de Violencia Página 104\nDIP. MANUEL GUERRERO LUNA\nSECRETARIO\n(RÚBRICA)\nDE CONFORMIDAD CON LO DISPUESTO POR LA FRACCIÓN I DEL ARTÍCULO 49 DE LA\nIMPRÍMASE Y PUBLÍQUESE.\nMEXICALI, BAJA CALIFORNIA, A LOS VEINTINUEVE DÍAS DEL MES DE ENERO\nDEL AÑO DOS MIL VEINTICUATRO.\nMARINA DEL PILAR ÁVILA OLMEDA\nGOBERNADORA DEL ESTADO\nDE BAJA CALIFORNIA\n(RÚBRICA)\nALFREDO ÁLVAREZ CÁRDENAS\nSECRETARIO GENERAL DE GOBIERNO\nDEL ESTADO DE BAJA CALIFORNIA\n(RÚBRICA)\nARTÍCULO ÚNICO TRANSITORIO DEL DECRETO No. 408, POR EL QUE SE\nAPRUEBA LA REFORMA A LOS ARTÍCULOS 42 Y 44 QUATER; PUBLICADO EN EL\nPERIÓDICO OFICIAL No. 18, DE FECHA 05 DE ABRIL DE 2024, ÍNDICE, TOMO CXXXI,\nEXPEDIDO POR LA H. XXIV LEGISLATURA, SIENDO GOBERNADORA CONSTITUCIONAL\nLA C. MARINA DEL PILAR ÁVILA OLMEDA 2021-2027.\nTRANSITORIOS\nÚNICO.- El presente Decreto entrará en vigor el día siguiente al de su publicación en el\nPeriódico Oficial de Baja California.\nDADO en Sesión Extraordinaria de la XXIV Legislatura en la Ciudad de Mexicali, B.C., a los ocho días del mes de marzo del año dos mil veinticuatro.\nDIP. ARACELI GERALDO NÚÑEZ\nPRESIDENTA\n(RÚBRICA)\nDIP. MANUEL GUERRERO LUNA\nSECRETARIO\n(RÚBRICA)\nLey de Acceso de las Mujeres a una Vida Libre de Violencia Página 105\nDE CONFORMIDAD CON LO DISPUESTO POR LA FRACCIÓN I DEL ARTÍCULO 49 DE LA\nIMPRÍMASE Y PUBLÍQUESE.\nMEXICALI, BAJA CALIFORNIA, A LOS CATORCE DÍAS DEL MES DE MARZO DEL\nAÑO DOS MIL VEINTICUATRO.\nMARINA DEL PILAR ÁVILA OLMEDA\nGOBERNADORA DEL ESTADO\nDE BAJA CALIFORNIA\n(RÚBRICA)\nALFREDO ÁLVAREZ CÁRDENAS\nSECRETARIO GENERAL DE GOBIERNO\nDEL ESTADO DE BAJA CALIFORNIA\n(RÚBRICA)\nARTÍCULO SEGUNDO TRANSITORIO DEL DECRETO No. 426, POR EL QUE SE\nAPRUEBA LA REFORMA A LOS ARTÍCULOS 33, 35, 42, 43 Y 47; PUBLICADO EN EL\nPERIÓDICO OFICIAL No. 23, DE FECHA 07 DE MAYO DE 2024, ÍNDICE, TOMO CXXXI,\nEXPEDIDO POR LA H. XXIV LEGISLATURA, SIENDO GOBERNADORA CONSTITUCIONAL\nLA C. MARINA DEL PILAR ÁVILA OLMEDA 2021-2027.\nTRANSITORIOS\nPRIMERO. El presente decreto entrará en vigor al día siguiente de su publicación en el\nPeriódico Oficial del Estado de Baja California.\nSEGUNDO. Las autoridades sujetas a la observancia y aplicación de la presente Ley, en un plazo no mayor a 180 días naturales contados a partir del día siguiente de la publicación del presente Decreto, deberán realizar las adecuaciones necesarias a sus reglamentos para su debida implementación.\nDADO en Sesión de Ordinaria de la XXIV Legislatura en la Ciudad de Mexicali, B.C., a los dieciocho días del mes de abril del año dos mil veinticuatro.\nDIP. RAMÓN VÁZQUEZ VALADEZ\nPRESIDENTE\n(RÚBRICA)\nDIP. MANUEL GUERRERO LUNA\nSECRETARIO\n(RÚBRICA)\nLey de Acceso de las Mujeres a una Vida Libre de Violencia Página 106\nDE CONFORMIDAD CON LO DISPUESTO POR LA FRACCIÓN I DEL ARTÍCULO 49\nCALIFORNIA, IMPRÍMASE Y PUBLÍQUESE.\nMEXICALI, BAJA CALIFORNIA, A LOS VEINTICINCO DÍAS DEL MES DE ABRIL\nDEL AÑO DOS MIL VEINTICUATRO.\nMARINA DEL PILAR ÁVILA OLMEDA\nGOBERNADORA DEL ESTADO\nDE BAJA CALIFORNIA\n(RÚBRICA)\nALFREDO ÁLVAREZ CÁRDENAS\nSECRETARIO GENERAL DE GOBIERNO\nDEL ESTADO DE BAJA CALIFORNIA\n(RÚBRICA)\nARTÍCULO ÚNICO TRANSITORIO DEL DECRETO No. 429, POR EL QUE SE\nAPRUEBA LA REFORMA A LOS ARTÍCULOS 6 y 11 TER; PUBLICADO EN EL PERIÓDICO\nOFICIAL No. 28, DE FECHA 31 DE MAYO DE 2024, ÍNDICE, TOMO CXXXI, EXPEDIDO\nPOR LA H. XXIV LEGISLATURA, SIENDO GOBERNADORA CONSTITUCIONAL LA C.\nMARINA DEL PILAR ÁVILA OLMEDA 2021-2027.\nTRANSITORIO:\nÚNICO.– El presente decreto entrará en vigor al día siguiente de su publicación en el\nPeriódico Oficial del Estado de Baja California.\nDADO en Sesión Ordinaria de la XXIV Legislatura en la Ciudad de Mexicali, B.C., a los nueve días del mes de mayo del año dos mil veinticuatro.\nDIP. RAMÓN VÁZQUEZ VALADEZ\nPRESIDENTE\n(RÚBRICA)\nDIP. MANUEL GUERRERO LUNA\nSECRETARIO\n(RÚBRICA)\nDE CONFORMIDAD CON LO DISPUESTO POR LA FRACCIÓN I DEL ARTÍCULO 49\nCALIFORNIA, IMPRÍMASE Y PUBLÍQUESE.\nMEXICALI, BAJA CALIFORNIA, A LOS CATORCE DÍAS DEL MES DE MAYO DEL\nAÑO DOS MIL VEINTICUATRO.\nLey de Acceso de las Mujeres a una Vida Libre de Violencia Página 107\nMARINA DEL PILAR ÁVILA OLMEDA\nGOBERNADORA DEL ESTADO\nDE BAJA CALIFORNIA\n(RÚBRICA)\nALFREDO ÁLVAREZ CÁRDENAS\nSECRETARIO GENERAL DE GOBIERNO\nDEL ESTADO DE BAJA CALIFORNIA\n(RÚBRICA)\nARTÍCULO SEGUNDO TRANSITORIO DEL DECRETO No. 39, POR EL QUE SE\nAPRUEBA LA REFORMA AL ARTÍCULO 33; PUBLICADO EN EL PERIÓDICO OFICIAL No.\n10, ÍNDICE, DE FECHA 07 DE FEBRERO DE 2025, TOMO CXXXII; EXPEDIDO POR LA H.\nXXV LEGISLATURA, SIENDO GOBERNADORA CONSTITUCIONAL LA C. MARINA DEL\nPILAR ÁVILA OLMEDA 2021-2027.\nTRANSITORIO:\nÚNICO.– El presente decreto entrará en vigor al día siguiente de su publicación en el\nPeriódico Oficial del Estado de Baja California.\nDADO en Sesión Ordinaria de la XXV Legislatura en la Ciudad de Mexicali, B.C., a los dieciséis días del mes de enero del año dos mil veinticinco.\nDIP. EVELYN SÁNCHEZ SÁNCHEZ\nPRESIDENTA\n(RÚBRICA)\nDIP. MICHELLE ALEJANDRA TEJEDA MEDINA\nSECRETARIA\n(RÚBRICA)\nDE CONFORMIDAD CON LO DISPUESTO POR LA FRACCIÓN I DEL ARTÍCULO 49\nCALIFORNIA, IMPRÍMASE Y PUBLÍQUESE.\nMEXICALI, BAJA CALIFORNIA, A LOS VEINTE DÍAS DEL MES DE ENERO DEL\nAÑO DOS MIL VEINTICINCO.\nMARINA DEL PILAR ÁVILA OLMEDA\nGOBERNADORA DEL ESTADO\nDE BAJA CALIFORNIA\n(RÚBRICA)\nLey de Acceso de las Mujeres a una Vida Libre de Violencia Página 108\nALFREDO ÁLVAREZ CÁRDENAS\nSECRETARIO GENERAL DE GOBIERNO\nDEL ESTADO DE BAJA CALIFORNIA\n(RÚBRICA)\nARTÍCULO ÚNICO TRANSITORIO DEL DECRETO No. 85, POR EL QUE SE\nAPRUEBA LA REFORMA AL ARTÍCULO 6; PUBLICADO EN EL PERIÓDICO OFICIAL No.\n25, ÍNDICE, DE FECHA 25 DE ABRIL DE 2025, TOMO CXXXII; EXPEDIDO POR LA H. XXV\nLEGISLATURA, SIENDO GOBERNADORA CONSTITUCIONAL LA C. MARINA DEL PILAR\nÁVILA OLMEDA 2021-2027.\nTRANSITORIO\nÚNICO.– La presente reforma entrará en vigor al día siguiente de su publicación en el\nPeriódico Oficial del Estado de Baja California.\nDADO en Sesión Ordinaria de la XXV Legislatura en la Ciudad de Mexicali, B.C., a los diez días del mes de abril del año dos mil veinticinco.\nDIP. MICHELLE ALEJANDRA TEJEDA MEDINA\nPRESIDENTA\n(RÚBRICA)\nDIP. NORMA ANGELICA PEÑALOZA ESCOBEDO\nSECRETARIA\n(RÚBRICA)\nDE CONFORMIDAD CON LO DISPUESTO POR LA FRACCIÓN I DEL ARTÍCULO 49\nCALIFORNIA, IMPRÍMASE Y PUBLÍQUESE.\nMEXICALI, BAJA CALIFORNIA, A LOS 14 DÍAS DEL MES DE ABRIL DEL AÑO DOS\nMIL VEINTICINCO.\nMARINA DEL PILAR ÁVILA OLMEDA\nGOBERNADORA DEL ESTADO\nDE BAJA CALIFORNIA\n(RÚBRICA)\nALFREDO ÁLVAREZ CÁRDENAS\nSECRETARIO GENERAL DE GOBIERNO\nDEL ESTADO DE BAJA CALIFORNIA\n(RÚBRICA)\nLey de Acceso de las Mujeres a una Vida Libre de Violencia Página 109\nARTÍCULO ÚNICO TRANSITORIO DEL DECRETO No. 86, POR EL QUE SE\nAPRUEBA LA REFORMA A LOS ARTÍCULOS 4, 6, 16 Y SE ADICIONA EL ARTÍCULO 15\nBIS; PUBLICADO EN EL PERIÓDICO OFICIAL No. 25, ÍNDICE, DE FECHA 25 DE ABRIL\nDE 2025, TOMO CXXXII; EXPEDIDO POR LA H. XXV LEGISLATURA, SIENDO\nGOBERNADORA CONSTITUCIONAL LA C. MARINA DEL PILAR ÁVILA OLMEDA 2021-\n2027.\nTRANSITORIOS\nÚNICO.– La presente reforma entrará en vigor al día siguiente de su publicación en el\nPeriódico Oficial del Estado de Baja California.\nDADO en Sesión Ordinaria de la XXV Legislatura en la Ciudad de Mexicali, B.C., a los diez días del mes de abril del año dos mil veinticinco.\nDIP. MICHELLE ALEJANDRA TEJEDA MEDINA\nPRESIDENTA\n(RÚBRICA)\nDIP. NORMA ANGELICA PEÑALOZA ESCOBEDO\nSECRETARIA\n(RÚBRICA)\nDE CONFORMIDAD CON LO DISPUESTO POR LA FRACCIÓN I DEL ARTÍCULO 49\nCALIFORNIA, IMPRÍMASE Y PUBLÍQUESE.\nMEXICALI, BAJA CALIFORNIA, A LOS 14 DIAS DEL MES DE ABRIL DEL AÑO DOS\nMIL VEINTICINCO.\nMARINA DEL PILAR ÁVILA OLMEDA\nGOBERNADORA DEL ESTADO\nDE BAJA CALIFORNIA\n(RÚBRICA)\nALFREDO ÁLVAREZ CÁRDENAS\nSECRETARIO GENERAL DE GOBIERNO\nDEL ESTADO DE BAJA CALIFORNIA\n(RÚBRICA)\nARTÍCULO ÚNICO TRANSITORIO DEL DECRETO No. 119, POR EL QUE SE\nAPRUEBA LA REFORMA A LOS ARTÍCULOS 1, 4, 16, 21, 22, 24, 25, 26, 26 BIS, 26 TER,\n26 QUATER, 26 QUINQUIES, 26 SEPTIES, 26 NONIES, 26 DUODECIES, 26 TERDECIES,\n26 QUATERDECIES, 32, 36, 38 BIS, 40, 41, 42, 43, 44 QUATER, 47 Y LA DENOMINACIÓN\nDE DIVERSOS TÍTULOS Y CAPÍTULOS, Y SE ADICIONAN LOS ARTÍCULOS 35 BIS y 35\nTER; PUBLICADO EN EL PERIÓDICO OFICIAL No. 43, NÚMERO ESPECIAL, DE FECHA\nLey de Acceso de las Mujeres a una Vida Libre de Violencia Página 110\nSIENDO GOBERNADORA CONSTITUCIONAL LA C. MARINA DEL PILAR ÁVILA OLMEDA\n2021-2027.\nARTÍCULO TRANSITORIO\nÚNICO.– Las presentes reformas entrarán en vigor al día siguiente de su publicación en el\nPeriódico Oficial del Estado de Baja California, con salvedad de lo dispuesto en el siguiente párrafo.\nLas reformas a los artículos 32, 35 BIS, 35 TER, 36, 38 BIS, 43 y a la denominación del Título\nTercero, así como la adición de un Capítulo III del Título Tercero, para llamarse Capítulo III\n“del Programa Institucional”, entrarán en vigor el 01 de octubre de 2025.\nDADO en Sesión Ordinaria de la XXV Legislatura en la Ciudad de Mexicali, B.C., a los diez días del mes de julio del año dos mil veinticinco.\nDIP. MICHELLE ALEJANDRA TEJEDA MEDINA\nPRESIDENTA\n(RÚBRICA)\nDIP. MARÍA TERESA MÉNDEZ VÉLEZ\nPROSECRETARIA\n(RÚBRICA)\nDE CONFORMIDAD CON LO DISPUESTO POR LA FRACCIÓN I DEL ARTÍCULO 49\nCALIFORNIA, IMPRÍMASE Y PUBLÍQUESE.\nMEXICALI, BAJA CALIFORNIA, A LOS 10 DIAS DEL MES DE JULIO DEL AÑO DOS\nMIL VEINTICINCO.\nMARINA DEL PILAR ÁVILA OLMEDA\nGOBERNADORA DEL ESTADO\nDE BAJA CALIFORNIA\n(RÚBRICA)\nALFREDO ÁLVAREZ CÁRDENAS\nSECRETARIO GENERAL DE GOBIERNO\nDEL ESTADO DE BAJA CALIFORNIA\n(RÚBRICA)\nLey de Acceso de las Mujeres a una Vida Libre de Violencia Página 111",
  "ordenamiento": "REGLAMENTO",
  "jurisdiccion": "BAJA CALIFORNIA",
  "fuente_oficial": "Periódico Oficial",
  "FECHA PER OFIC": "2025/07/21",
  "ESTATUS": "VIGENTE",
  "TOMO": "TOMO_VI",
  "URL": "https://www.congresobc.gob.mx/Documentos/ProcesoParlamentario/Leyes/TOMO_VI/20250721_LEYLIBREVIOLENCIA-2.PDF",
  "es_escaneado": false,
  "tiene_tablas": false,
  "materia": [
    "social",
    "salud",
    "educación",
    "cultura"
  ]
}