{
  "titulo": "Ley DE INGRESOS DEL MUNICIPIO DE ENSENADA, BAJA CALIFORNIA PARA EL EJERCICIO FISCAL DEL 2025",
  "Contenido": "DE BAJA CALIFORNIA, EN USO DE LAS FACULTADES QUE LE CONFIERE EL\nLA SIGUIENTE:\nINICIATIVA DE LEY DE INGRESOS\nDEL MUNICIPIO DE ENSENADA, BAJA CALIFORNIA,\nPARA EL EJERCICIO FISCAL DEL 2025\nÍNDICE GENERAL\nTÍTULO PRIMERO GENERALIDADES\nTÍTULO SEGUNDO IMPUESTOS\nCAPÍTULO I IMPUESTO PREDIAL.\nCAPÍTULO II IMPUESTO SOBRE ADQUISICIÓN DE INMUEBLES.\nPERMITIDOS Y ESPECTÁCULOS PÚBLICOS.\nCAPÍTULO IV IMPUESTO PARA MANTENIMIENTO Y\nCONSERVACIÓN DE LAS VÍAS PÚBLICAS.\nCAPÍTULO V IMPUESTOS NO COMPRENDIDOS EN LAS\nFRACCIONES DE LA LEY DE INGRESOS CAUSADAS\nEN EJERCICIOS FISCALES ANTERIORES\nPENDIENTES DE LIQUIDACIÓN O PAGO.\nTÍTULO TERCERO DERECHOS\nCAPÍTULO I DERECHO POR SERVICIO DE ALUMBRADO PÚBLICO.\nGENERAL A TRAVÉS DE:\nI.- UNIDADES DEL REGISTRO CIVIL.\nII.- COORDINACIÓN MUNICIPAL DE\nPROTECCIÓN CIVIL.\nIII.- EVENTOS TURÍSTICOS.\nMUNICIPAL A TRAVÉS DE:\nI.- DIRECCIÓN DE RECAUDACIÓN.\nII.- DIRECCIÓN DE COMERCIO, ALCOHOLES Y\nESPECTÁCULOS PÚBLICOS.\nCAPÍTULO IV SERVICIOS QUE PRESTA LA UNIDAD\nMUNICIPAL DE TRANSPARENCIA Y ACCESO A\nLA INFORMACIÓN PÚBLICA.\nCAPÍTULO V SERVICIOS QUE PRESTA LA DIRECCIÓN DE\nBIENESTAR SOCIAL MUNICIPAL, A TRAVÉS DE:\nI.- DEPARTAMENTO DE SERVICIOS\nMÉDICOS.\nII.- DEPARTAMENTO DE EDUCACIÓN.\nADMINISTRACIÓN URBANA, ECOLOGÍA Y\nMEDIO AMBIENTE.\nINFRAESTRUCTURA.\nSERVICIOS PÚBLICOS MUNICIPALES A TRAVÉS\nDE:\n1.- SERVICIOS QUE PRESTA DEPARTAMENTO\nDE PARQUES Y JARDINES, Y PANTEONES.\n2.- SERVICIOS QUE PRESTA EL DEPARTAMENTO\nDE RASTRO.\n3.- SERVICIOS QUE PRESTA EL DEPARTAMENTO\nDE LIMPIA.\nDE SEGURIDAD PÚBLICA MUNICIPAL.\nCAPÍTULO X SERVICIOS QUE PRESTA LA DIRECCIÓN DE\nBOMBEROS.\nCAPÍTULO XI OTROS SERVICIOS QUE PRESTA EL AYUNTAMIENTO\nU ORGANISMOS PARAMUNICIPALES.\nCAPÍTULO XII SERVICIOS QUE PRESTA LA POLICÍA COMERCIAL.\nCAPÍTULO XIII EXPEDICIÓN DE CERTIFICADOS, TÍTULOS,\nCONSTANCIAS O COPIAS DE DOCUMENTOS.\nCAPÍTULO XIV DERECHOS NO COMPRENDIDOS EN LAS\nFRACCIONES DE LA LEY DE INGRESOS\nCAUSADAS EN EJERCICIOS FISCALES\nANTERIORES PENDIENTES DE LIQUIDACIÓN\nO PAGO.\nTÍTULO CUARTO PRODUCTOS\n1.- CONTRAPRESTACIÓN DE CONCESIONES,\nEXPLOTACIÓN O ARRENDAMIENTO DE\nBIENES MUEBLES E INMUEBLES\nPROPIEDAD DEL GOBIERNO MUNICIPAL.\n2.- OTRAS ACTIVIDADES DEL GOBIERNO\nMUNICIPAL, QUE NO CORRESPONDAN A\nSUS FUNCIONES PROPIAS DE DERECHO\nPÚBLICO.\n3.- SUMINISTRO DE FORMAS DIVERSAS PARA\nTRÁMITES ADMINISTRATIVOS.\n4.- DEL PISO.\n5.- BIENES MOSTRENCOS.\n6.- LOS PRODUCTOS DE LA GACETA MUNICIPAL.\n7.- ENAJENACIÓN DE BIENES MUEBLES E\nINMUEBLES PROPIEDAD DEL GOBIERNO\nMUNICIPAL.\n8.-ORGANISMOS DESCENTRALIZADOS Y EMPRESAS\nDE PARTICIPACIÓN MUNICIPAL.\n9.- OTROS.\n10.- PRODUCTOS NO COMPRENDIDOS EN LAS\nFRACCIONES DE LA LEY DE INGRESOS\nCAUSADAS EN EJERCICIOS FISCALES\nANTERIORES PENDIENTES DE LIQUIDACIÓN\nO PAGO.\nTÍTULO QUINTO APROVECHAMIENTOS\n1.- RECARGOS.\n2.- GASTOS DE EJECUCIÓN.\n3.- MULTAS.\n4.- VENTA DE SUBPRODUCTOS.\n5.- REINTEGROS E INDEMNIZACIONES.\n6.- DONACIONES, CESIONES, HERENCIAS Y\nLEGADOS A FAVOR DEL MUNICIPIO.\nO POR LA FEDERACIÓN PARA OBRAS Y\nSERVICIOS PÚBLICOS O PROGRAMAS\nESPECIALES.\n8.- OTORGAMIENTO Y USUFRUCTO DE DERECHOS.\n9.- RECUPERACIÓN PARCIAL DE PRIMAS DE\nSEGUROS DE VIDA.\n10.- PARTICIPACIONES EN IMPUESTOS\nFEDERALES.\n11.- PARTICIPACIONES EN IMPUESTOS\nESTATALES.\n12.- SUBSIDIOS QUE OTORGUE EL GOBIERNO DEL\nESTADO.\n13.- SUBSIDIOS QUE OTORGUE EL GOBIERNO\nFEDERAL.\n14.- CAUCIONES DE FIANZAS Y DEPÓSITOS\nCUYA PÉRDIDA SE DECLARE POR\nRESOLUCIÓN FIRME.\n15.- APORTACIONES FEDERALES DEL RAMO 33.\n16.- APROVECHAMIENTOS NO COMPRENDIDOS EN\nLAS FRACCIONES DE LA LEY DE\nINGRESOS CAUSADAS EN EJERCICIOS\nFISCALES ANTERIORES PENDIENTES DE\nLIQUIDACIÓN O PAGO.\nTÍTULO SEXTO EXTRAORDINARIOS\n1.- CRÉDITOS OTORGADOS AL MUNICIPIO.\n2.- APORTACIONES ESTATALES Y FEDERALES.\n3.- OTROS.\nCAPÍTULO ÚNICO GENERALIDADES\nTÍTULO PRIMERO\nGENERALIDADES\nARTÍCULO 1.- Los Ingresos del Municipio de Ensenada, del Estado de Baja California, durante el Ejercicio Fiscal del 1ro. de enero al 31 de diciembre del 2025, serán los que se obtengan por los siguientes conceptos:\n1.- IMPUESTOS $1,015,013,604.74\n11 IMPUESTOS SOBRE LOS INGRESOS\n12 IMPUESTOS SOBRE EL PATRIMONIO\n01.- Impuesto Predial. $472,523,265.40\n02.- Impuesto sobre Adquisición de Inmuebles. $180,984,051.95\n13 IMPUESTO SOBRE LA PRODUCCIÓN, EL CONSUMO Y LAS\nTRANSACCIONES.\n14 IMPUESTO AL COMERCIO EXTERIOR\n15 IMPUESTO SOBRE NÓMINAS Y ASIMILABLES\n16 IMPUESTOS ECOLÓGICOS\n17 ACCESORIOS DE IMPUESTOS\n01.- Recargos. $63,243,278.31\n02.- Gastos de ejecución.\n18 OTROS IMPUESTOS\n01.- Impuesto sobre Asistencia a Juegos\nPermitidos y Espectáculos Públicos. $16,283,323.55\n02.- Impuesto para Mantenimiento y\nConservación de las Vías Públicas. $46,963,738.66\n03.- Otros impuestos. $160,280,683.70\n19 IMPUESTOS NO COMPRENDIDOS EN LA LEY DE INGRESOS VIGENTE,\nCAUSADOS EN EJERCICIOS FISCALES ANTERIORES PENDIENTES DE\nLIQUIDACIÓN O PAGO.\n01.- Impuestos no comprendidos en las fracciones de la Ley de\nIngresos causadas en ejercicios fiscales anteriores pendientes de liquidación o pago. $74,735,263.17\n2.- CUOTAS Y APORTACIONES DE SEGURIDAD SOCIAL\n21 APORTACIONES PARA FONDOS DE VIVIENDA\n22 CUOTAS PARA LA SEGURIDAD SOCIAL\n23 CUOTAS DE AHORRO PARA EL RETIRO\n24 OTRAS CUOTAS Y APORTACIONES PARA LA SEGURIDAD SOCIAL\n25 ACCESORIOS DE CUOTAS Y APORTACIONES DE SEGURIDAD SOCIAL\n3.- CONTRIBUCIONES DE MEJORAS\n31 CONTRIBUCIONES DE MEJORAS POR OBRAS PÚBLICAS\n39 CONTRIBUCIONES DE MEJORAS NO COMPRENDIDAS EN LA LEY\nDE INGRESOS VIGENTE, CAUSADAS EN EJERCICIOS FISCALES\nANTERIORES PENDIENTES DE LIQUIDACIÓN O PAGO.\n4.- DERECHOS $486,126,534.15\n41 DERECHOS POR EL USO, GOCE, APROVECHAMIENTO O EXPLOTACIÓN\nDE BIENES DE DOMINIO PÚBLICO\n43 DERECHOS POR PRESTACIÓN DE SERVICIOS\n01.- Derecho por Servicio de Alumbrado Público.\n$124,329,347.40\n02.- Servicios que presta el Registro Civil.\n$37,418,960.87\n03.- Servicios que presta la Dirección de Recaudación.\n$690,825.41\n04.- Derechos que cobra la Dirección de Comercio, Alcoholes y Espectáculos Públicos. $59,824,977.62\n01.- Recepción, Análisis y Revisión de\nSolicitudes, de Emisión de Documentos, Permisos y Certificados Referentes a Instalaciones para la Venta, Almacenaje o Consumo de\nBebidas con Graduación Alcohólica, Ampliación\nCambio de Giro, Cambio de Permisionario, Cambio de Domicilio, Cambio de Nombre Comercial y Tramitación Relativa a la Operación de\nGiros de Cerveza, Vinos, Licores, Alcoholes y\nSimilares.\n02.- Recepción, Análisis y Revisión de\nDocumentos y por la Autorización para la\nInstalación y Explotación de Aparatos de\nSonido, Electrónicos, Mecánicos, Electromecánicos, Videojuegos y Similares.\n03.- Centros de apuestas, apuestas remotas, salas de sorteos de números y/o casinos.\n04.- Recepción y Análisis de Documentos y Expedición de Permisos Referentes a la Realización de Espectáculos Públicos y\nEventos de Diversión.\n05.- Los derechos para adquirir horas extras para la operación de salones sociales.\n06.- Recepción y Análisis de Documentos Referentes a la Instalación de Aparatos Musicales\n(sinfonolas).\n07.- Expedición de Permisos para el ejercicio del comercio en la Vía Pública por\nComerciantes Ambulantes, o con Puestos Fijos o\nSemifijos.\n08.- Arrendamiento de espacios en parques, playas, jardines y plazas destinadas al esparcimiento.\n05.- Servicios que presta la Coordinación Municipal de Protección Civil. $24,503,689.75\n06.- Eventos turísticos. $166,113.75\n07.- Servicios que presta la Unidad Municipal\n$0.00\n08.- Servicios que presta el Departamento de\nServicios Médicos. $1,824,140.36\n09.- Servicios que presta el Departamento de Educación.\n$153,827.93\n10.- Servicios que presta la Dirección de\nAdministración Urbana, Ecología y Medio Ambiente.\n$115,613,099.33\n11.- Servicios que presta la Subdirección de Ecología.\n$9,542,646.31\n12.- Servicio que presta la Dirección de Infraestructura.\n$492,598.41\n13.- Estacionamiento de Vehículos en la Vía Pública.\n$66,930,492.95\n14.- Estacionamientos Públicos Fijos y Transitorios.\n$667,954.93\n15.- Servicios que presta la Dirección de Servicios\nPúblicos Municipales. $0.00\n16.- Servicios que presta el Departamento de Parques y Jardines, y Panteones. $1,296,487.30\n17.- Servicios que presta el Departamento de Rastro.\n$4,600,322.78\n18.- Servicios que presta el Departamento de Limpia.\n$439.71\n19.- Servicios que presta la Dirección de Seguridad\nPública Municipal. $2,403,526.64\n20.- Almacenaje de Vehículos. $0.00\n21.- Servicios que presta la Dirección de Bomberos.\n$18,532,591.50\n22.- Los servicios que presta la Paramunicipal\nInstituto Metropolitano de Investigación y\nPlaneación de Ensenada, Baja California (IMIP).\n23.- Los servicios que presta el Sistema para el\nDesarrollo Integral de la Familia.\n24.- Servicios que presta el Centro Social, Cívico y Cultural Riviera Ensenada.\n25.- Los servicios que presta el Instituto Municipal de Cultura y Desarrollo Humano de Ensenada.\n26.- Los servicios que presta el Fideicomiso\nMunicipal para el Desarrollo Urbano de Ensenada.\n27.- Los servicios que presta el Fideicomiso la\nBufadora.\n28.- Servicios que presta el Consejo de Urbanización\nMunicipal de Ensenada.\n29.- Los servicios que presta el Instituto Municipal del Deporte y Recreación de Ensenada.\n30.- Los servicios que presta el Instituto Municipal de la Juventud de Ensenada.\n31.- Los servicios que presta el Comité de Planeación para el Desarrollo Municipal de Ensenada. (COPLADEM)\n32.- Los servicios que presta la paramunicipal\nProturismo de Ensenada.\n33.- Servicios que presta la Policía Comercial.\n34.- Expedición de Certificados, Títulos, Constancias o Copias de Documentos. $6,875,057.68\n44 OTROS DERECHOS\n01.- Otros derechos. $712,087.33\n02.- Trámite de Pasaporte Mexicano. $9,053,628.68\n45 ACCESORIOS DE DERECHOS\n01.- Recargos. $493,717.51\n49 DERECHOS NO COMPRENDIDOS EN LA LEY DE INGRESOS\nVIGENTE, CAUSADOS EN EJERCICIOS FISCALES ANTERIORES\nPENDIENTES DE LIQUIDACIÓN O PAGO\n01.- Derechos no comprendidos en las fracciones de la\nLey de Ingresos causadas en ejercicios fiscales anteriores pendientes de liquidación o pago.\n5.- PRODUCTOS $158,002.85\n51 PRODUCTOS\n01.- Contraprestación de Concesiones, Explotación o Arrendamiento de Bienes Muebles e\nInmuebles Propiedad del Gobierno Municipal.\n02.- Otras Actividades del Gobierno Municipal, que no correspondan a sus funciones propias de\nDerecho Público.\n03.- Suministro de formas diversas para Trámites\nAdministrativos.\n04.- Del Piso.\n05.- Bienes Mostrencos.\n06.- Los Productos de la Gaceta Municipal.\n07.- Enajenación de Bienes Muebles e Inmuebles Propiedad del Gobierno Municipal. $0.00\n08.- Organismos Descentralizados y Empresas de Participación Municipal.\n09.- Otros. $158,002.85\n59 PRODUCTOS NO COMPRENDIDOS EN LA LEY DE INGRESOS\nVIGENTE, CAUSADOS EN EJERCICIOS FISCALES ANTERIORES\nPENDIENTES DE LIQUIDACIÓN O PAGO.\n01.- Productos no comprendidos en las fracciones de la Ley de Ingresos causadas en ejercicios fiscales anteriores pendientes de liquidación o pago.\n6.- APROVECHAMIENTOS $117,703,432.38\n61 APROVECHAMIENTOS\n01.- Multas. $84,511,969.39\n02.- Indemnizaciones. $3,783.97\n03.- Reintegros. $1,096,181.39\n04.- Donaciones, Cesiones, Herencias y Legado.\n$94,746.80\n05.- Daños a Bienes Propiedad del Municipio. $983,897.25\n06.- Postura Legal para Remate. $1,531,217.90\n07.- Recuperación Parcial de Primas de Seguro de Vida.\n08.- Cauciones de Fianzas y Depósitos cuya Pérdida se declare por Resolución Firme.\n09.- Otros aprovechamientos. $11,155,930.08\n10.- 80% ZONA FEDERAL MARÍTIMA TERRESTRE Y TERRENOS\nGANADOS AL MAR. $6,379,853.99\n62 APROVECHAMIENTOS PATRIMONIALES\n01.- Venta de Subproductos. o Programas Especiales.\n03.- Ingresos por Licitaciones. $140,356.52\n63 ACCESORIOS DE APROVECHAMIENTOS\n01.- Recargos.\n02.- Gastos de Ejecución. $0.00\n03.- Gastos de Intervención. $380,647.35\n04.- Gastos de Administración. $1,402,751.08\n05.- Gastos de Notificación. $7,453,932.61\n69 APROVECHAMIENTOS NO COMPRENDIDOS EN LA LEY DE INGRESOS\nVIGENTE, CAUSADOS EN EJERCICIOS FISCALES ANTERIORES\nPENDIENTES DE LIQUIDACIÓN O PAGO.\n01.- Aprovechamientos no comprendidos en las fracciones de la Ley de Ingresos causadas en ejercicios fiscales anteriores pendientes de liquidación o pago. $2,568,164.05\n7.- INGRESOS POR VENTA DE BIENES, PRESTACIÓN DE SERVICIOS Y\nOTROS INGRESOS $13,969,641.62\n71 INGRESOS POR VENTA DE BIENES Y PRESTACIÓN DE SERVICIOS\n72 INGRESOS POR VENTA DE BIENES Y PRESTACIÓN DE SERVICIOS\nDE EMPRESAS PRODUCTIVAS DEL ESTADO\n73 INGRESOS POR VENTA DE BIENES Y PRESTACIÓN DE SERVICIOS\nY NO FINANCIEROS\n74 INGRESOS POR VENTA DE BIENES Y PRESTACIÓN DE\nSERVICIOS DE ENTIDADES PARAESTATALES EMPRESARIALES NO\nFINANCIERAS CON PARTICIPACIÓN ESTATAL MAYORITARIA\n75 INGRESOS POR VENTA DE BIENES Y PRESTACIÓN DE SERVICIOS\nDE ENTIDADES PARAESTATALES EMPRESARIALES FINANCIERAS\nMONETARIAS CON PARTICIPACIÓN ESTATAL MAYORITARIA\n76 INGRESOS POR VENTA DE BIENES Y PRESTACIÓN DE SERVICIOS\nDE ENTIDADES PARAESTATALES EMPRESARIALES FINANCIERAS\nNO MONETARIAS CON PARTICIPACIÓN ESTATAL MAYORITARIA\n77 INGRESOS POR VENTA DE BIENES Y PRESTACIÓN DE SERVICIOS\nESTATAL MAYORITARIA\n78 INGRESOS POR VENTA DE BIENES Y PRESTACIÓN DE SERVICIOS\nDE LOS PODERES LEGISLATIVO Y JUDICIAL, Y DE LOS\nÓRGANOS AUTÓNOMOS\n79 OTROS INGRESOS\n01 EXTRAORDINARIOS $13,969,641.62\n01.- Créditos Otorgados al Municipio.\n02.- Aportaciones Estatales y Federales.\n03.- Otros.\n8.- PARTICIPACIONES, APORTACIONES, CONVENIOS, INCENTIVOS DERIVADOS\n$1,616,951,785.80\n81 PARTICIPACIONES\n01 PARTICIPACIONES EN IMPUESTOS FEDERALES\n01 Fondo General de Participación Federal\n$633,807,058.00\n02 Fondo Fomento Municipal $104,692,064.00\n03 Fondo de Compensación I.S.A.N. $1,391,283.00\n04 Fondo Impuesto Sobre la Renta $95,710,657.00\n05 Fondo de Fiscalización $42,411,018.00\n06 Recaudación Federal 0.136% $5,291,307.00\n07 Impuesto Especial Sobre Productos y Servicios\n(I.E.P.S.) $22,492,304.00\n08 Impuesto Sobre Automóviles Nuevos (I.S.A.N.)\n$10,034,229.00\n09 Impuesto Sobre Tenencia o Uso de Vehículo. $0.00\n10 Impuesto Especial Sobre Producción y Servicios\nGasolina y diésel. $36,352,909.00\n11 Fondo de Estabilización $21,019,457.00\n02 PARTICIPACIONES EN IMPUESTOS ESTATALES la Realización de Obras.\n02 Por Otros Impuestos o Ingresos del Gobierno del\nEstado que señalen las Leyes, Acuerdos, o Convenios que las Regulen.\n03 Impuesto Sobre Servicios de Hospedaje.\n$4,458,831.00\n04 Impuesto Estatal a la Venta Final de Bebidas con\nContenido Alcohólico. $2,547,915.80\n05 Impuesto Sobre la Tenencia Estatal. $4,602,794.00\n06 Impuesto Estatal. $19,497,949.00\n07 Fondo Compensatorio. $0.00\n08 Fondo Compensatorio ISSH. $0.00\n09 Impuesto Sobre Remuneraciones al Trabajo Personal.\n$46,818,445.00\n82 APORTACIONES\n01 FONDO III INFRAESTRUCTURA SOCIAL MUNICIPAL\n$138,281,400.00\n02 FONDO DE FORTALECIMIENTO MUNICIPAL $398,040,000.00\n83 CONVENIOS\n84 INCENTIVOS DERIVADOS DE LA COLABORACIÓN FISCAL\n01 70% ZONA FEDERAL MARÍTIMA TERRESTRE Y\nTERRENOS GANADOS AL MAR $0.00\n85 FONDOS DISTINTOS DE APORTACIONES\n01 FONDOS DE INVERSIÓN\n01 FORTASEG $0.00\n02 CONAFOR $0.00\n03 DECRETO REGULARIZACIÓN DE VEHÍCULOS USADOS DE\nPROCEDENCIA EXTRANJERA $ 29,502,165.00\n9.- TRANSFERENCIAS, ASIGNACIONES, SUBSIDIOS Y SUBVENCIONES, Y\nPENSIONES Y JUBILACIONES\n91 TRANSFERENCIAS Y ASIGNACIONES\n93 SUBSIDIOS Y SUBVENCIONES\n01.- Subsidios que otorgue el Gobierno del Estado.\n02.- Subsidios que otorgue el Gobierno Federal.\n95 PENSIONES Y JUBILACIONES\n97 TRANSFERENCIAS DEL FONDO MEXICANO DEL PETRÓLEO PARA LA\nESTABILIZACIÓN Y EL DESARROLLO\n0.- INGRESOS DERIVADOS DE FINANCIAMIENTOS\n01 ENDEUDAMIENTO INTERNO\n02 ENDEUDAMIENTO EXTERNO\n03 FINANCIAMIENTO INTERNO\nARTÍCULO 1 BIS.- El Ejecutivo Municipal podrá otorgar estímulos fiscales sobre el pago de contribuciones, de acuerdo al\nCompetitividad y Desarrollo Económico del Municipio de Ensenada, Baja California, haciendo reducciones en el pago de Impuesto y/o\nDerechos, cuando los estímulos vayan destinados a personas físicas o morales que promuevan la generación de nuevos empleos, contratando personas con discapacidad, así como el que impulse aplicables.\nTÍTULO SEGUNDO\nIMPUESTOS\nCAPÍTULO I\nIMPUESTO PREDIAL\nARTÍCULO 2.- Es objeto del Impuesto Predial la propiedad y la posesión de predios urbanos, suburbanos, rústicos y cualquier otra clasificación así como las construcciones permanentes existentes en ellos.\nLos propietarios, poseedores o fideicomitentes de bienes inmuebles estarán obligados a manifestar a la Autoridad Catastral cualquier modificación que se haga a los elementos que caractericen al bien inmueble, tales como construcciones, ampliaciones, remodelaciones, fusión, subdivisión, relotificación y fraccionamiento o cualquier partir de la fecha de la modificación, lo anterior de conformidad con el artículo 37 de la Ley antes citada. primero. establecidos en el artículo 75 BIS A de la Ley de Hacienda Municipal del Estado de Baja California. Los fideicomitentes están obligados al pago del Impuesto Predial, mientras sean poseedores del predio fideicomiso.\nEl Impuesto Predial, se causará de acuerdo a lo que se establece en la Ley de Hacienda Municipal y la Ley del Catastro Inmobiliario, ambas del Estado de Baja California, así como en el Reglamento del Catastro Inmobiliario para el Municipio de Ensenada, B. C., de conformidad con la Tabla de Valores Catastrales Unitarios de\nTerreno y Construcción, Base del Impuesto Predial, del Municipio de Ensenada, B.C., elaborada por el Consejo Municipal del Catastro\nInmobiliario de Ensenada, y aprobada por el Congreso del Estado para el Municipio de Ensenada, Baja California.\nLa base del Impuesto Predial se determinará multiplicando el valor catastral unitario de terreno establecido en la Tabla de Valores\nCatastrales Unitarios de Terreno y Construcción, Base del Impuesto\nPredial, del Municipio de Ensenada, B.C. por la superficie del predio, sumándole a este el valor de construcción el cual se determinará multiplicando el número de metros cuadrados por el valor unitario de construcción, igualmente establecido en la\nTabla de Valores Catastrales Unitarios de Terreno y Construcción, Base del Impuesto Predial, del Municipio de Ensenada, B.C. que le corresponda de acuerdo a las características de la misma.\nEn la determinación del uso, calidad y estado de conservación utilizados en el cálculo del Valor Unitario de Construcción de este impuesto se utilizarán la Tabla de Usos, Calidades, Estados de Conservación; las Tablas de Características de la Tipología y Calidades de las Construcciones; la Tabla de\nEvaluación del Estado de Conservación de las Construcciones; la\nConstrucciones, la Tabla de Valores Unitarios por Tipo y Estado de Construcción en Pesos por m2, así como las definiciones para cada uno de estos, todas contenidas en la Tabla de Valores\nCatastrales Unitarios de Terreno y Construcción, Base del\nImpuesto Predial, del Municipio de Ensenada, B.C. aprobada para este ejercicio fiscal y anexa a la misma. se adicionará el 22.50 % (veintidós punto cincuenta por ciento) del valor total de la construcción de acuerdo con lo\nTerreno y Construcción, Base del Impuesto Predial, del Municipio de Ensenada, B.C., conforme a la siguiente fórmula:\n((S.T. * V.C.U.T.)+(S.C. * V.U.C.)*(F.C.))*T.M.\nDonde:\nS.T.: Superficie de Terreno\nV.C.U.T.: Valor Catastral Unitario de Terreno en Tabla de Valores\nS.C.: Superficie de Construcción\nV.U.C.: Valor Unitario de Construcción en Tabla de Valores\nF.C.: Factor de Construcción de 22.50%\nT.M.: Tasa al Millar\nAplicándole las siguientes:\n1.- PREDIOS URBANOS Y SUBURBANOS\na).- Destinados total y exclusivamente para habitación: a.1).- De sus propietarios o poseedores, clasificados como urbanos; sobre su valor catastral................ 3.74 al millar a.2).- De sus propietarios o poseedores, clasificados como suburbanos; sobre su valor catastral......... 3.74 al millar a.3).- De sus propietarios cuando éste sea habitado por el mismo siendo pensionado, persona con discapacidad, jubilados o personas mayores de sesenta años que acrediten su condición con identificación oficial expedida por Institución Pública, en predios clasificados como urbanos o suburbanos, cuya superficie no sea mayor a 1,750 m², en la zona urbana y 5,000 m² en las delegaciones, en propiedad única destinada a casa habitación; sobre su valor catastral......... 3.74 al millar a.4).- De sus propietarios, clasificados como urbanos y suburbanos cuando éstos se ubiquen en asentamientos irregulares y que se encuentren en proceso de regularización por organismo oficial, federal o estatal siempre que estén destinados total y exclusivamente para habitación de sus propietarios previa opinión favorable de los organismos, pagarán 1.84 al millar o 5.00 UMA (Unidad de\nMedida y Actualización) Vigente, o el que resulte mayor. a.5).- De sus propietarios o poseedores, ubicados en las zonas urbanas de los ejidos o poblados rurales, destinados exclusivamente a casa habitación; sobre su valor catastral......................... 3.74 al millar a.6).- De sus propietarios o poseedores, cuando es habitado en zona turística, bajo el tipo de régimen de propiedad en condominio y/o fideicomiso bancario; sobre su valor catastral................ 6.31 al millar\nb).- Predios urbanos con uso mixto habitacional–comercial, donde el uso predominante del predio sea de casa habitación y cuyo uso comercial sea dedicado exclusivamente a un sólo giro cuya superficie de construcción no sea mayor del 30% de la superficie del predio; sobre su valor catastral.......... 4.54 al millar\nc).- Predios destinados para su venta, propiedad de fraccionamientos debidamente autorizados, que cumplan con los reglamentos respectivos y que no hayan sido objeto de traslación de dominio por un periodo de tres años a partir de su autorización, prorrogable hasta por dos años siempre y cuando el fraccionador compruebe siga realizando ventas, además que no haya solicitado lo establecido en el apartado VI inciso H) e I) de la Tabla de\nValores Catastrales Unitarios de Terreno y Construcción; sobre su valor catastral.. 2.81 al millar\nd).- Predios urbanos y suburbanos destinados para programas habitacionales con fines sociales, promovidos por institución oficial, pagarán 1.87 al millar o\n5.00 UMA, (Unidad de Medida y Actualización) o el que resulte mayor.\ne).- Predios urbanos no edificados, que se encuentran improductivos, o que cuenten con construcciones en proceso, en receso o en estado ruinoso o que cuenten con construcciones que sean de carácter provisional con materiales que sean de uso transitorio o puedan removerse fácilmente y además se encuentre improductivo, o cuyo valor no llegue al 50% del valor del terreno en zonas que cuenten como mínimo con servicios de agua, electricidad y drenaje; sobre su valor catastral......................... 12.50 al millar\nf).- Predios urbanos y suburbanos ocupados por empresa industrial y que sean propiedad de la misma; sobre su valor catastral................................ 6.31 al millar\ng).- Predios urbanos y suburbanos destinados exclusivamente al uso de comercio y de servicios: g.1).- Con uso comercial y de servicios en general, comercial turístico y de oficinas; sobre su valor catastral......................... 6.31 al millar g.2).- Predios ocupados por giros de comercio y servicio que emitan contaminantes al suelo, subsuelo y atmósfera, como polvo, ruido, etc.; como talleres mecánicos y de carrocería, tornos, gasolineras, carpinterías, servicios de cambio y reciclaje de aceites y lubricantes, autolavados, depósitos de gas, marmolerías, etc.; sobre su valor catastral........... 8.40 al millar g.3).- Con usos deportivos, recreativos o turísticos recreativos, con o sin construcciones; sobre su valor catastral................... 6.31 al millar g.4).- Predios ocupados por hoteles y moteles que sean propiedad de la empresa hotelera; sobre su valor catastral......................... 6.31 al millar\nh).- Predios urbanos y suburbanos propiedad de asociaciones de profesionistas, sin fines de lucro, debidamente constituida conforme al Código Civil para el Estado de Baja California y registradas ante el\nDepartamento de profesiones en los términos establecidos por la Ley del\nEjercicio de los profesionistas para el\nEstado de Baja California................. 4.54 al millar\ni).- Predios urbanos y suburbanos propiedad de Organizaciones, Asociaciones o\nInstituciones de Asistencia Social\nPrivada, con fines de Interés Público, Humanitarios y no como Auxiliares de la\nAsistencia Social Privada, mismas que a su denominación deberá seguir el término\n“INSTITUCIÓN DE ASISTENCIA PRIVADA” o las siglas “I.A.P.”, debidamente constiLey de Asistencia Social ambas para el\nEstado de Baja California, y realizada la inscripción ante la autoridad municipal pagarán 5.00 UMA (Unidad de\nMedida y Actualización). De igual forma, predios urbanos de agrupaciones de productores que realicen actividades agropecuarias y pesqueras, debidamente constituidas, y registradas ante el\nRegistro Público de la Propiedad y de\nComercio, y realizada la inscripción ante la autoridad municipal, pagarán\n5.00 UMA (Unidad de Medida y Actualización).\nj).- Predios urbanos y suburbanos ocupados por o propiedad de instituciones de enseñanza que tengan autorización o reconocimiento de validez oficial de estudios en los términos de la Ley\nFederal de Educación..................... 4.54 al millar\nk).- Predios urbanos y suburbanos ocupados exclusivamente por instalaciones de infraestructura pública; sobre su valor catastral................................ 4.54 al millar\nl).- Predios urbanos y suburbanos ocupados exclusivamente por servidumbre de paso, formalmente constituidas de conformidad a lo establecido en el Código Civil del\nEstado de Baja California; sobre su valor catastral........................ 1.87 al millar\nm).- Predios urbanos y suburbanos del dominio público y del dominio privado de la\nFederación y el Estado, siempre que los primeros se utilicen con propósitos distintos de los de su objeto social; sobre su valor catastral.................. 4.54 al millar\nn).- Predios urbanos y suburbanos del dominio público de la Federación, del Estado y del Municipio que caigan en el caso de exención indicado en el artículo 115\nConstitucional así como en el Artículo\n75 BIS “A” de la Ley de Hacienda\nMunicipal para el Estado de Baja\nCalifornia.\no).- Predios suburbanos sin uso; sobre su valor catastral.......................... 8.40 al millar\np).- Predios urbanos destinados total o parcialmente a fines distintos a los señalados en los incisos anteriores; sobre su valor catastral.................. 6.31 al millar\nq).- Predios suburbanos destinados total o parcialmente a fines distintos a los señalados en los incisos anteriores; sobre su valor catastral.................. 6.04 al millar\nr).- Predios urbanos, suburbanos o rústicos destinados total o parcialmente al almacenaje de contenedores, tractocamiones y/o sus cajas; sobre su valor catastral... 15.00 al millar\n2.- PREDIOS RÚSTICOS\na).- Predios en zona rural destinados total y exclusivamente para casa habitación de sus propietarios, con superficie de hasta 5,000 m² (0.5 has); sobre su valor catastral................................ 3.74 al millar\nb).- Predios en zona rural, destinados total y exclusivamente para habitación de sus propietarios cuando éstos sean pensionados y jubilados o personas mayores de sesenta años que acrediten su condición con identificación oficial expedida por\nInstitución Pública, destinadas a casa habitación con superficie de hasta\n5,000 m² (0.5 has); sobre su valor catastral................................ 3.74 al millar\nc).- Predios en zona rural, ocupados por o propiedad de instituciones de enseñanza que tengan autorización o reconocimiento de validez oficial de estudios en los términos de la Ley Federal de Educación... 3.74 al millar\nd).- Predios rústicos de régimen privado y social (Ejidal), así como terrenos nacionales en uso y goce de particulares, dedicados a la actividad agropecuaria, pagarán el impuesto de acuerdo a lo dispuesto en el punto 3 de este Artículo.\ne).- Predios en zona rural, con usos deportivos, recreativos o turísticos recreativos con o sin construcciones y que no se contemplen en los casos descritos en el punto 4 de este\nArtículo; sobre su valor catastral...... 6.31 al millar\nf).- Predios en zona rural y del dominio público de la Federación, del Estado y del Municipio que caigan en el caso de la exención indicado en el Artículo 115\nConstitucional así como en el Artículo\n75 BIS “A” de la Ley de Hacienda\nMunicipal para el Estado de Baja\nCalifornia.\ng).- Predios rústicos de régimen privado y social, así como terrenos nacionales en uso y goce de particulares, destinados total o parcialmente a fines distintos a los señalados en los incisos anteriores, y que no se contemplen en los casos descritos en el punto 4 de este\nArtículo; sobre su valor catastral........ 6.04 al millar\n3.- TABLA DE COBRO DE PREDIAL PARA PREDIOS RURALES (AGROPECUARIOS\nCON USO COMERCIAL) rural, deberá ser considerado el tipo de clasificación del predio, pagando el impuesto predial que resulte del cálculo de estacionamiento, al cual se le asignará el valor unitario tasa correspondiente, al resultado se le sumará el impuesto de la superficie restante conforme a lo establecido a predios rurales destinados a la producción agropecuaria exclusivamente de la misma.\nTratándose de predios rurales destinados a la producción agropecuaria exclusivamente, únicamente causarán el impuesto que corresponda de acuerdo con la siguiente tabla:\nA.- DE RIEGO, TEMPORAL Y AGOSTADERO:\n1.- Mayor de 0.5 hasta 10 Ha............................ 16.38\n2.- Mayor de 10 hasta 20 Ha............................. 21.41\n3.- Mayor de 20 hasta 50 Ha............................. 26.46\n4.- Mayor de 50 hasta 100 Ha............................ 31.50\n5.- Mayor de 100 Ha.................................... 59.22\n4.- PREDIOS RÚSTICOS CON COLINDANCIAS AL MAR\n4.1.- PORCIÓN PACÍFICO NORTE, corresponde a la zona colindante con el Océano Pacífico, comprendida desde el área de Punta Banda conocida como Arbolitos.\nMECÁNICA DE DETERMINACIÓN DE VALOR\na).- La distancia frente al mar se multiplica por 100 metros cuando colinda con playa arenosa, 50 metros al mar y 25 metros cuando colinda con acantilado sin acceso al mar.\nb).- La superficie obtenida se multiplica por el valor unitario de zona turística rural, el cual será de\n$120.00 pesos por metro cuadrado.\nc).- El valor unitario mencionado en el punto anterior viene determinado por la letra \"T\", que constituye el tercer espacio de la clave catastral rural.\nd).- El valor obtenido se divide entre toda la superficie del predio y se obtiene el valor unitario promedio.\n4.2.- PORCIÓN PACÍFICO CENTRO, corresponde a la zona colindante con el Océano Pacífico, comprendida entre\nEl Puerto de Santo Tomás hasta el límite de la delegación de Punta Colonet.\nMECÁNICA DE DETERMINACIÓN DE VALOR\na).- La distancia frente al mar se multiplica por 50 metros cuando colinda con playa arenosa, 25 metros cuando se considerará como predio rústico sin valor fiscal, cuando colinda con acantilado sin acceso al mar.\nb).- La superficie obtenida se multiplica por el valor unitario de zona turística rural, el cual será de\n$ 30.00 pesos por metro cuadrado.\nc).- El valor unitario mencionado en el punto anterior viene determinado por la letra \"P\", que constituye el tercer espacio de la clave catastral rural.\nd).- El valor obtenido se divide entre toda la superficie del predio y se obtiene el valor unitario promedio. con colindancia al mar, estarán a lo dispuesto para los predios rurales a que se refiere el punto 3 anterior.\n5.- ÁREAS VERDES Y DECRETADAS COMO DE PRESERVACIÓN ECOLÓGICA\nLas áreas decretadas como de Preservación Ecológica en la carta urbana del Plan de Desarrollo Urbano de Ensenada, pagarán 5.00 UMA y las áreas verdes también indicadas dentro de la misma carta urbana quedarán exentas de éste pago, siempre y cuando éstas hayan sido donadas con todas las formalidades de ley a favor del Municipio y de conformidad a los términos a que se refiere el segundo párrafo del inciso c) de la fracción IV del Artículo 115 de la Constitución Política de los Estados Unidos Mexicanos.\n6.- LOTES \"CABECEROS\" O CON INCIDENCIA A LA VIALIDAD\nLos valores de calle, parte de la base de los valores de mercado de las manzanas, para los lotes \"cabeceros\" o con incidencia a la vialidad se les aplicará un premio al valor de un 30% y los lotes cabeceros que además de tener aplicará un premio del 50%.\nValores Catastrales Unitarios de Terreno y Construcción, Base del Impuesto Predial, del Municipio de Ensenada, B.C., se tipifican como \"Vialidades con Valores Comerciales\". Se entenderá como lotes \"cabeceros\" los lotes con frente a una vialidad comercial. antecede no será aplicable a los lotes cuyo uso, sea exclusivamente de casa-habitación.\n7.- DE LOS AJUSTES AL VALOR UNITARIO\nLos deméritos y/o castigos contemplados en la tabla de valores para efecto en el cálculo del impuesto predial, en ningún caso serán superiores del 30% en su totalidad. Así mismo no se\nUrbana en el mismo ejercicio fiscal.\nAdicional a las tasas referidas en las fracciones de este artículo, se establece la siguiente sobretasa del impuesto predial:\na).- Sobretasa para fortalecimiento de la Seguridad Pública municipal de 1.50 al millar sobre la base considerada para el cálculo del citado impuesto.\nARTÍCULO 3.- La contribución por concepto del Impuesto Predial\nAnual, se regirá con base en la Tabla de Valores Catastrales\nUnitarios de Terreno y Construcción, Base del Impuesto Predial, del Municipio de Ensenada, B.C., aprobada por el Congreso del\nEstado, y no podrá ser menor a 5.00 UMA (Unidad de Medida y\nActualización) Vigente.\nLos predios urbanos, suburbanos y rústicos destinados total y sean: jubilados, pensionados o mayores de 60 años y que acrediten que habitan esa propiedad mediante identificación oficial, además el predio tenga una superficie de hasta 1,750 metros en la zona urbana y suburbana y hasta 5,000 metros en la zona rústica, recibirán un descuento del 30 al 50% del impuesto siempre que el importe resultante no sea menor a 5.00 UMA, de acuerdo a la siguiente tabla:\n50%........valor fiscal hasta $ 1,500,000.00 (un millón quinientos mil pesos 00/100 m.n.).\n30%........valor fiscal de $ 1,500,000.01 (un millón quinientos mil pesos 01/100 m.n.) en adelante.\nAsí mismo los predios urbanos, suburbanos y rústicos destinados cuando estos sean: discapacitados, personas que tengan a su cargo credencial oficial con la que se acredite la discapacidad, viudas mayores de 50 años y mujeres jefas de familias de escasos recursos, los cuales acrediten su condición con identificación expedida por institución pública, recibirán un descuento del 30 al 50% del impuesto mediante estudio socioeconómico siempre que el importe resultante no sea menor a\n5.00 UMA. De acuerdo a lo estipulado en la tabla anterior.\nEl Impuesto Predial deberá cubrirse anualmente durante los tres primeros meses del año; cuando el último día de vencimiento sea día inhábil se recorrerá al día siguiente hábil.\nARTÍCULO 3 BIS.- Los contribuyentes que opten por pagar el\nImpuesto Predial durante los primeros tres meses del año, y que no presenten adeudos en ejercicios fiscales anteriores, gozarán de un descuento del 10% en el mes de enero, 7% en el mes de febrero y 5% en el mes de marzo, del monto del impuesto determinado de conformidad con lo dispuesto en el artículo anterior, siempre y cuando se cumpla con el pago total anual en una sola exhibición. gozará de un descuento del 6% en enero, 4% en febrero y 2% en marzo, siempre y cuando cumpla con el pago total anual en una sola exhibición. habitación, y siempre y cuando los contribuyentes realicen el pago durante los meses de enero, febrero o marzo, a través del descuento del 2% (dos por ciento) sobre el impuesto predial cuenta corriente sin accesorios, adicional a cualquier otro estímulo fiscal aplicado.\nLos propietarios de predios urbanos no edificados o baldíos, que expide la Dirección de Administración Urbana, Ecología y Medio\nAmbiente, gozarán de hasta un 50% de descuento, en el pago del impuesto predial del ejercicio fiscal en curso, siempre y mismo ejercicio fiscal.\nEl descuento por el Certificado de Mejoramiento de la Imagen\nUrbana no aplicará para predios baldíos localizados en vialidades comerciales.\nLas bases del Certificado de Mejoramiento a la Imagen Urbana, se encuentran establecidas en el Artículo 28 Bis inciso B), segundo párrafo, de esta Ley.\nARTÍCULO 3 TRI.- Los contribuyentes que estén obligados a cubrir al Instituto del Fondo Nacional de la Vivienda para los\nTrabajadores (INFONAVIT), créditos hipotecarios que éste les hubiere otorgado, podrán pagar el Impuesto Predial por conducto del INFONAVIT, en los términos dispuesto en este artículo y en su caso, por lo dispuesto en las disposiciones de carácter general que resulten aplicables, siempre y cuando el Municipio tenga celebrado convenio de colaboración con el INFONAVIT y a su vez los contribuyentes, en su carácter de derechohabientes del INFONAVIT, autoricen al citado Instituto para ordenar a su respectivo patrón, impuesto predial por orden y cuenta suya.\nAsí mismo, los contribuyentes que cumplan con lo señalado en los para el efecto, podrán pagar el citado impuesto de manera tal efecto por la autoridad fiscal.\nEn los supuestos anteriores, los pagos del impuesto predial se el ejercicio fiscal de que se trate. El importe de cada pago por la Ley de Hacienda Municipal del Estado de Baja California.\nPara los efectos de este artículo, el primero de los cuatrimestres iniciará con el primer mes del ejercicio fiscal.\nEn estos supuestos, los pagos corresponderá realizarlos a las instituciones o empresas señaladas en los párrafos anteriores, a más tardar el día 17 del mes inmediato posterior al cuatrimestre correspondiente; debiendo enterarlo a su vez a la Hacienda\nMunicipal en términos de lo establecido en el convenio de colaboración que para estos efectos se tenga suscrito.\nLos contribuyentes que pretendan cumplir con su obligación de pago, del impuesto predial en los términos indicados en los párrafos anteriores, deberán manifestar a la Tesorería Municipal, tal intención, igualmente deberán presentar los avisos que se indican en las reglas de carácter general que en su caso emita la autoridad fiscal.\nCAPÍTULO II\nIMPUESTO SOBRE ADQUISICIÓN DE INMUEBLES\nARTÍCULO 4.- Es objeto de este impuesto, toda adquisición de\nEnsenada, Baja California, por cualquiera de los medios\nCalifornia y la presente Ley. las construcciones adheridas a él, incluyendo los accesorios y las instalaciones especiales que pertenezcan al inmueble, ubicados en el municipio; la adquisición de derechos reales o posesionarios sobre los bienes inmuebles, al igual que los contemplados en el artículo 75 BIS B, apartado A de la Ley de Hacienda Municipal para el Estado de Baja California. sus formas. se establece, sobre la base gravable que se determine de acuerdo a la Ley de Hacienda Municipal del Estado de Baja California.\nRango Límite Límite Cuota Tasa marginal inferior superior fija sobre excedente límite inferior\n1 0.01 500,000.00 1.50%\n2 500,000.01 1,000,000.00 7,500.00 2.00%\n3 1,000,000.01 1,600,000.00 17,500.00 2.50%\n4 1,600,000.01 2,600,000.00 32,500.00 3.00%\n5 2,600,000.01 3,800,000.00 62,500.00 3.50%\n6 3,800,000.01 5,200,000.00 104,500.00 4.00%\n7 5,200,000.01 6,800,000.00 160,500.00 4.50%\n8 6,800,000.01 8,600,000.00 232,500.00 5.00%\n9 8,600,000.01 10,600,000.00 322,500.00 5.50%\n10 10,600,000.01 En adelante 432,500.00 6.00%\nPara el cálculo de este impuesto, la base del mismo deberá ubicarse en el renglón que le corresponda de entre los límites del recuadro, le aplicará la tasa marginal que le corresponda; al resultado se el impuesto sobre adquisición de inmuebles a pagar.\nLo anterior, conforme a la siguiente fórmula:\n((BI-LI)*T)+CF + ST = Impuesto sobre adquisición de inmuebles a pagar.\nEn donde:\nBI= Base del Impuesto\nLI= Límite inferior correspondiente\nT= Tasa marginal sobre excedente del límite inferior correspondiente\nCF= Cuota Fija correspondiente\nST= Sobretasa\nLas Autoridades Fiscales Municipales podrán tomar en cuenta el avalúo del inmueble referido a la fecha de adquisición, mismo que no deberá ser menor a los valores por metro cuadrado establecidos en la Tabla de Valores Catastrales Unitarios de Terreno y\nConstrucción, Base del Impuesto Predial, del Municipio de Ensenada,\nB.C.\nTratándose de este Impuesto el valor fiscal a considerar en la fórmula para el cálculo deberá ser el que resulte de aplicar los valores catastrales unitarios establecidos en la Tabla de Valores\nCatastrales Unitarios de Terreno y Construcción del ejercicio fiscal 2025, aprobada por el Congreso del Estado. De haberse aplicado demérito, éste solo será considerado hasta en un 30% de su totalidad de conformidad con lo establecido en la Tabla de\nValores Catastrales Unitarios de Terreno y Construcción.\nSe aplicará a la base gravable la tasa 0%, cuando la adquisición sea por alguno de los siguientes supuestos:\na) Por donación, herencia o legado entre cónyuges.\nb) Por donación, herencia o legado que se realicen de padres a hijos o de hijos a padres.\nc) En las operaciones en que los adquirientes sean asociaciones civiles, o asociaciones religiosas que no persigan fines de lucro, debidamente registradas en el\nEstado.\nd) Por la adquisición de terrenos a través de títulos de propiedad, expedidos por el Registro Agrario Nacional que obtengan los ejidatarios.\nLa tasa del 0% no será aplicable cuando los donatarios, herederos o legatarios cedan sus derechos sobre los bienes gravables, y cuando los adquirientes a que se refiere el inciso d) cedan sus inciso. partir del ejercicio fiscal 2025 para la determinación del impuesto sobre adquisición de inmuebles, respecto de los bienes inmuebles ubicados en el Municipio de Ensenada, por lo que en estos supuestos no será aplicable la tasa establecida por la Legislatura Estatal.\nPor lo tanto, cualquier disposición emitida con anterioridad que se oponga a la presente disposición no surtirá efecto alguno en el\nMunicipio de Ensenada, en tanto se encuentre vigente la misma.\nPara la revisión y aceptación de este impuesto, el contribuyente deberá presentar la siguiente documentación legible:\n1.- Formato previamente llenado de la declaración de Impuesto\nSobre Adquisición de Inmuebles.\n2.- Contrato o sentencia donde se adquieren derechos reales o posesorios.\n3.- Identificación de las partes.\n4.- Avalúo vigente.\n5.- Libertad de Gravamen con vigencia al ejercicio fiscal en curso.\n6.- Acta de Nacimiento en caso del párrafo séptimo inciso\nb) de este artículo y en los casos del inciso a), deberá de separación de bienes.\nCalifornia (INDIVI), o con el Instituto Nacional del Suelo\nSustentable(INSUS), Fideicomiso Municipal para el Desarrollo\nUrbano de Ensenada (FIDUE) y los que se realicen a través de habitacionales de interés social y popular, pagarán el equivalente de ocho UMA vigente, además indistintamente deberán cumplir con los siguientes requisitos:\n1.- No supere los 250 m² de superficie; y\n2.- Solo se podrá regularizar un predio por persona física. inmuebles, el dar aviso dentro de los primeros 15 días hábiles después del hecho imponible a la autoridad fiscal municipal, siendo exigible una vez transcurrido el término otorgado en el presente párrafo.\nSerán responsables solidarios del Impuesto sobre Adquisición de\nInmuebles los notarios y corredores públicos de las operaciones y actos por la que se causen los mismos cuando: autoricen actos o contratos de adquisición de propiedad de inmuebles o de derechos reales o posesorios, así como cuando inscriban o realicen anotaciones de escrituras, actos o contratos sin que el causante compruebe que se han cubierto estas contribuciones.\nLa responsabilidad solidaria, consiste en el pago del importe total de las contribuciones mencionadas que indebidamente dejaron de pagar los contribuyentes.\nAsí mismo, tendrán la misma responsabilidad solidaria sobre el fedatario público o autoridad competente. obligaciones fiscales. Por lo tanto, se procederá a la aplicación\nAdquisición de Inmuebles de conformidad con el artículo 89 fracción\nI, inciso l) de la Ley de Hacienda Municipal del Estado de Baja morales que se encuentran en el supuesto jurídico, misma que se cobrará con base en la siguiente tabla:\nAÑOS UMAS\n1992 y anteriores 85\n1993-1996 80\n1997-1999 75\n2000-2002 65\n2003-2006 60\n2007-2009 55\n2010-2012 50\n2013-2016 45\n2017-2019 40\n2020-2021 35\n2022-2023 30\n2024 25\nPARA EL EJERCICIO FISCAL 2025\nMESES UMAS\n5 10\n6 12\n7 14\n8 16\n9 18\n10 20\n11 22\n12 24\nAdicional a la tarifa prevista en el presente artículo, se\nAdquisición de Inmuebles:\nA).- Sobretasa para el fortalecimiento de la Seguridad Pública municipal del 0.4% sobre la base del citado impuesto.\nCAPÍTULO III\nY ESPECTÁCULOS PÚBLICOS\nARTÍCULO 5.- Son sujetos de este impuesto, las personas que adquieran boletos, pulseras, sellos o cualquier otro medio de acceso que condicione su entrada individual al espectáculo público y que pueden ser: funciones de teatro, circo, lucha libre, boxeo, espectáculos deportivos, audiciones, eventos culturales, espectáculos musicales, centros de diversión, centros nocturnos de diversión o de cualquier otro tipo con cuota de admisión así como la explotación de aparatos electromecánicos, mecánicos, electrónicos y otros similares accionados o no por monedas, que se realicen en el territorio del Municipio de Ensenada. para espectáculos públicos y los señalados en el párrafo anterior. de entrada vendidos, entregados y de cortesía. de personal designado por la Dirección de Recaudación, quienes que correrán a cargo del promotor u organizador del espectáculo.\nARTÍCULO 6.- Tratándose de juegos permitidos, espectáculos públicos, centros de diversión, centros nocturnos de diversión y juegos mecánicos, se causará conforme a las siguientes:\nTASAS:\nI.- Espectáculos en que participen deportistas, músicos y actores no profesionales, así como los realizados por Instituciones lucro; obras de teatro, funciones de circo, espectáculos cómicos, taurinos, audiencias musicales, bailes, eventos de box y lucha, espectáculos públicos en los que participen deportistas profesionales, cursos, conferencias y talleres; el impuesto se causará sobre la cuota de admisión o por cada boleto vendido para el espectáculo o diversión............ 5%\nII.- Tratándose de conciertos, centros nocturnos de diversión, otras diversiones y espectáculos públicos; sobre la cuota de admisión o por cada boleto vendido para el ingreso al espectáculo o diversión................................. 10%\nIII.- Tratándose de espectáculos cuyas actividades comprendan la promoción y difusión de la cultura en el Municipio a través de la música, artes plásticas, artes dramáticas, danza y literatura tales como: danza folclórica y regional, fotografía, pintura, eventos relacionados con la conservación, difusión y recuperación del arte de las comunidades indígenas en todas las manifestaciones de sus propias lenguas, usos y costumbres, artesanías, tradiciones una propuesta con fin solamente cultural, que se presenten\nMunicipio o en espacios culturales independientes, sobre espectáculo público o diversión......................... 0%\nLas personas físicas o morales, organizadores de espectáculos objeto de solicitud, así mismo, no se deberá realizar ni permitir la venta y/o consumo de bebidas con graduación alcohólica de ningún tipo ni superar los 250 asistentes.\nAdemás, se deberá cumplir con los siguientes requisitos:\n1.- Exhibir opinión favorable del Instituto Municipal de\nCultura y Desarrollo Humano de Ensenada (IMCUDHE) en el corresponde a lo descrito en esta fracción, debiendo anexar además la documentación mediante la cual acredita tales supuestos, para el análisis que se realice en la resolución final que emita la Tesorería Municipal;\n2.- Presentar por escrito a la Tesorería Municipal a través de la Dirección de Recaudación, cuando menos cinco días hábiles antes de la realización del evento, solicitud de exención, acompañada de la constancia expedida por el Instituto Municipal de la Cultura y Desarrollo\nHumano (IMCUDHE), mediante la cual dicho organismo confirme que las personas físicas y/o morales realizan primordialmente las actividades a que se refiere esta fracción;\n3.- Acreditar ante la Dirección de Recaudación que las personas físicas o morales organizadores de espectáculos sujetos de esta fracción, tengan domicilio fiscal en el Municipio de Ensenada.\n4.- Acreditar ante la Dirección de Recaudación el carácter de representante legal de quien comparece, tratándose de personas morales;\n5.- Presentar ante la Dirección de Comercio, Alcoholes y\nEspectáculos Públicos, para su sellado, el boletaje y el programa que corresponda a cada función, cuando menos con evento correspondiente;\n6.- Destinar para el acceso gratuito de las personas con discapacidad, conforme a su acepción según la Ley para\nCalifornia el equivalente al 10% (diez por ciento) del boletaje que emitan, en un área en la que permita su disfrute del espectáculo;\n7.- Contar con autorización de exención por escrito\nEmitida por la autoridad fiscal;\n8.- No vender boletos en tanto no estén sellados por la\nDirección de Comercio, Alcoholes y Espectáculos Públicos.\nAsí mismo, deberá de presentar todos los requisitos anteriormente señalados ante la Dirección de Recaudación cuando menos un día antes del evento, para efectos de la aplicación de la tasa prevista en esta fracción.\nIV.- Tratándose de espectáculos realizados por Organismos no lucrativos que brinden servicios y asistencia médica de manera gratuita a enfermos que padezcan cáncer en etapa terminal, debidamente registrados ante la Secretaría de Salud del Estado gravarán este impuesto a tasa cero, sobre la cuota de admisión o por cada boleto vendido para el espectáculo público o diversión............................................... 0% referencia esta fracción, se deberá acreditar que el organismo no lucrativo. en las fracciones I, II, III, Y IV, se llevará a cabo con base en lo siguiente:\n1.- Con respecto al otorgamiento de los permisos de espectáculos públicos la Dirección de Comercio, Alcoholes y Espectáculos\nPúblicos, será la encargada de emitirlos;\n2.- En lo que refiere a la aprobación de la tasa del impuesto documentación emitida y aprobada por la Dirección de Comercio, Alcoholes y Espectáculos Públicos;\n3.- Para poder acceder a la tasa establecida en la fracción IV de este artículo, el organizador del evento, diversión o espectáculo objeto de solicitud no deberá realizar ni permitir la venta de bebidas con graduación alcohólica de ningún tipo;\n4.- De no contar con domicilio fiscal establecido en el Municipio de Ensenada, el organizador o promotor deberá designar un responsable solidario que cuente con domicilio en el municipio el cual deberá ser hecho del conocimiento a la\nAutoridad Fiscal;\n5.- Para el otorgamiento del permiso respectivo será obligatorio que el organizador presente constancia de no adeudo municipal vigente.\nEl monto del Impuesto Sobre Asistencia a Juegos Permitidos y\nEspectáculos Públicos se determinará aplicándole la tasa autorizada a cada boleto, pulsera, sello, importe de consumo obligatorio\n(COVER) o cualquier otro medio de acceso adquirido por el asistente, multiplicado por la cantidad de localidades con ese mismo importe.\nPara los efectos del cobro de este impuesto, el organizador en su como boletos vendidos, a los cuales se les aplicará la tasa en cortesía. ofertado al público. Para efectos de lo anterior, será definiendo claramente el precio de la localidad, asiento y fila si es el caso, lugar, fecha y horario del espectáculo o evento.\nARTÍCULO 7.- Los permisionarios que, derivado de sus actividades de juegos con apuestas o sorteos, que otorguen premio en efectivo causado estado, registrados y reconocidos en la página oficial de la citada Secretaría de Gobernación, pagarán de manera mensual lo siguiente:\nA).- Para los organizadores de juegos con apuestas permitidas y/o habilidades o destrezas........ 3.00% sobre la base gravable.\nPara los efectos de este artículo las personas que organicen juegos con apuestas permitidas se considerarán como valor de las mismas la cantidad que se cobre o reciba por el billete o boleto que permita la participación o la apuesta, deduciéndose a dicha base gravable el valor del premio efectivamente pagado o entregado, así como la devolución de las cantidades efectivamente recibidas de los participantes.\nAdicional a la tarifa prevista en el presente artículo, se establece la siguiente sobretasa para los organizadores de juegos con apuestas permitidas y/o habilidades o destrezas:\nI).- Sobretasa para fortalecimiento de la Seguridad Pública\nMunicipal del 0.5% sobre la base gravable del citado impuesto. el Municipio de Ensenada, B.C.\nDirección de Recaudación y se pagará a más tardar el día 17 del el pago, utilizando para la declaración del mismo el formato que expida la Dirección de Recaudación. anterior, el contribuyente pagará una cuota mensual de 14,000.00\nUMA. impuesto. artículo, no causarán los derechos contenidos en esta Ley relativos a las máquinas de juego, calcomanía por máquina, holograma por máquina o cualquier otro análogo; así como para la obtención de permisos, revalidación o licencia de operación del establecimiento de los mismos.\nARTÍCULO 8.- Los organizadores, empresarios o promotores de los espectáculos públicos, juegos permitidos, centros de diversión o centros de diversión nocturnos serán solidariamente responsables del pago de este impuesto, debiendo retener al momento de pagar el asistente el boleto de admisión o su similar y enterarlo al momento de celebrarse este, previa liquidación o comprobación del ingreso al interventor municipal, en el caso en que sea intervenido el evento o en su defecto, en la Dirección de Recaudación el día hábil siguiente al de la celebración del espectáculo público.\nLos gastos de intervención se cobrarán por cada interventor con espectáculo público o evento de conformidad con la siguiente tabla:\n1).- De 100.00 A 300.99.................. 2.00 UMA\n2).- De 301.00 A 500.99.................. 3.00 UMA\n3).- De 501.00 A 700.99.................. 4.00 UMA\n4).- De 701.00 A 900.99.................. 5.00 UMA\n5).- De 901.00 A 1,500.99.................. 6.00 UMA\n6).- De 1,501.00 A 3,000.99.................. 7.00 UMA\n7).- De 3,001.00 A 6,000.99.................. 8.00 UMA\n8).- De 6,001.00 A 10,000.99.................. 9.00 UMA\n9).- De 10,001.00 En Adelante................. 10.00 UMA\nCAPÍTULO IV\nPÚBLICAS\nARTÍCULO 9.- Son sujetos de este impuesto, los propietarios o poseedores de vehículos de motor, que residan dentro del territorio del Municipio de Ensenada, Baja California, para contribuir en el mantenimiento y conservación de las vías públicas municipales.\nEste impuesto se enterará al pagar el importe correspondiente a la expedición o revalidación de las placas de circulación, a través de la Recaudación de Rentas del Estado y/o ante el Instituto de\nMovilidad Sustentable (IMOS) o los equivalentes de estos, los cuales serán retenedores del mismo; sujetándose a la siguiente:\nUNIDAD DE MEDIDA Y ACTUALIZACIÓN\n(UMA)VIGENTE\na).- Vehículos de uso particular........................ 4.50 UMA\nb).- Vehículos de transporte público de pasajeros....................................... 9.20 UMA\nc).- Camiones de uso particular........................ 10.00 UMA\nd).- Camiones de transporte público de pasajeros...................................... 13.00 UMA\ne).- Camiones de carga pesada.......................... 20.00 UMA\nLos ingresos que se recauden por este concepto, se destinarán públicas municipales.\nCAPÍTULO V\nPENDIENTES DE LIQUIDACIÓN O PAGO.\nARTÍCULO 10.- Los impuestos no pagados en el ejercicio fiscal en que se causaron, se cobrarán como ingresos causados en ejercicios fiscales anteriores, pendientes de liquidación o pago, aplicando en cuanto al fondo, las Leyes vigentes a la fecha en que se generaron y en cuanto a la forma, mediante el procedimiento administrativo de ejecución que establece la Ley de Hacienda\nMunicipal del Estado de Baja California o en su caso, el procedimiento judicial que corresponda.\nTÍTULO TERCERO\nDERECHOS\nCAPÍTULO I\n1.- DERECHO POR SERVICIO DE ALUMBRADO PÚBLICO.\nARTÍCULO 11.- Es objeto de este derecho, la prestación del servicio de alumbrado público en la vía pública, en calles, avenidas, bulevares, caminos vecinales, plazas, parques, jardines y otros lugares de uso común, por medio de la red de alumbrado público en el Municipio de Ensenada, Baja California, que se presta bajo la modalidad determinada por el mismo conforme a sus atribuciones.\nSon sujetos obligados al pago de este derecho, los beneficiarios anterior, propietarios o poseedores de los inmuebles y/o predios\nMunicipio de Ensenada, Baja California, con las excepciones dispuestas en este capítulo. mensualmente conforme a una cuota fija de $67.72 pesos (sesenta y siete pesos 72/100 M.N.)\nARTÍCULO 12.- Este derecho se causará mensualmente conforme a lo siguiente:\nLa base de este Derecho es el costo anual del servicio de alumbrado público erogado por el Municipio de Ensenada, el cual incluye el gasto por pago del servicio de energía eléctrica consumida por el\nMunicipio para la prestación del servicio de alumbrado público, así como la ampliación, instalación, reparación, limpieza y mantenimiento del alumbrado público y luminarias, semaforización, alumbrado ornamental de temporada además de gastos administrativos, servicios contratados a terceros, sueldos y honorarios del personal directamente involucrado en la prestación de este servicio;\nLa cuota fija mensual para el pago del Derecho por Servicio de\nAlumbrado Público, se obtuvo como resultado de dividir el costo anual actualizado del ejercicio fiscal 2023, erogado por el\nMunicipio en la prestación de este servicio, actualizado por inflación y dividido entre el número de sujetos de este derecho.\nEl cociente fue dividido entre 12 para determinar el monto mensual del derecho a pagar.\nSe entiende por costo anual actualizado del ejercicio fiscal 2023, Municipio en 2023, por el gasto directamente involucrado con la prestación de este servicio, traídos a valor presente tras la aplicación de un factor de actualización que se obtiene,\nARTÍCULO 13.- No estarán obligados al pago de este derecho los inmuebles de uso público de las Entidades Públicas Federales, Estatales y Municipales.\nARTÍCULO 14.- El pago deberá realizarse dentro de los primeros 10 días siguientes al mes en que se cause, en las oficinas recaudadoras tal efecto.\nEl citado plazo y lugar de pago, podrá modificarse o ampliarse en beneficio de los contribuyentes, cuando existan acuerdos entre el\nMunicipio con otras instancias públicas o privadas, que permitan simplificar el entero de la contribución. Para tal efecto, las instancias competentes del Municipio podrán celebrar convenios a través de los cuales se logre lo indicado con anterioridad.\nARTÍCULO 15.- Los ingresos que se perciban por el derecho establecido en esta sección, se destinarán al pago de conceptos que se requieran para asegurar la debida prestación del Servicio de Alumbrado Público en el Municipio de Ensenada, Baja California.\nCAPÍTULO II\nSERVICIOS QUE PRESTA LA SECRETARÍA GENERAL A TRAVÉS DE:\nI.- EL REGISTRO CIVIL.\nARTÍCULO 16.- Los derechos por servicios que preste el Registro\nCivil, serán pagados por el usuario sujetándose a la siguiente:\nUNIDAD DE MEDIDA Y ACTUALIZACIÓN\n(UMA)VIGENTE\nA.- NACIMIENTOS:\na).- Registro en horas hábiles dentro de la oficina, con anticipación de 8 días, previa cita..................................... EXENTOS\nb).- Registro urgente en horas hábiles dentro de la oficina, menos de 7 días a\n48 horas, previa cita y serán canalizados a el área de trabajo social para su valoración..................................... EXENTOS\nc).- Registro en hospitales, excepto en instituciones de salud pública los cuales estarán exentos.......................... EXENTOS c.1.- Registro de nacimiento en centro de rehabilitación, ceresos, casa hogar, casas de retiro, tutelar de menores, registros de niños que realiza la Procuraduría para la Defensa del Menor y la Familia y otros.................................. EXENTOS\nd).- Registro de nacimientos hasta los\n5 años.......................................... EXENTOS\ne).- Registro a domicilio, fuera de la mancha urbana con anticipación de 8 días, previa cita:\na).- En horas hábiles........................... EXENTOS\nb).- En horas inhábiles........................ EXENTOS\nf).- Registro de nacimiento fuera del término de los 6 meses.......................... EXENTOS\ng).- Inscripción de registro de nacimientos ocurridos en territorio extranjero, en\n“campaña colectiva”............................. EXENTOS\nh).- Inscripción de nacimientos de personas nacidas en el extranjero........................ EXENTOS\ni).- Inscripción de nacimientos de personas nacidas fuera del Municipio, hasta los\n5 años.......................................... EXENTOS\nj).- Registro de nacimiento dentro del programa \"Jornadas del Registro Civil\", en horas Inhábiles, dentro de la oficina........................................ EXENTOS\nk).- Registro en instituciones de salud, en módulo de Registro Civil, dentro de los quince días de nacido........................... EXENTOS\nl).- Declaratoria de hechos, para registro de nacimientos extemporáneos en campaña......... EXENTOS\nm).- Inscripción de nacimientos urgente, de personas nacidas en el extranjero será canalizado a el área de trabajo social para su valoración.............................. EXENTOS\nn).- Exentos de pago a registros extemporáneos, de niños que realiza la\nProcuraduría para la Defensa del Menor y la Familia.................................... EXENTOS\nB.- MATRIMONIOS:\na).- Celebración en horas hábiles dentro de la oficina, con anticipación de 8 días, previa cita................................... 13.50 UMA\nb).- Celebración urgente, en horas hábiles dentro de la oficina, menos de 7 días a\n48 horas, previa cita........................ 24.98 UMA b.1).- Celebración de matrimonio extraordinario, en horas hábiles, con anticipación de 24 horas, previa cita............................ 40.50 UMA\nc).- Celebraciones en hospitales, excepto en instituciones de salud pública, los cuales estarán exentos........................ 15.50 UMA\nPara obtener exención contemplada en el inciso c), deberán que se trate. c.1.- Celebración de matrimonio de personas mayores de 18 años en establecimientos de tratamiento de adicciones, ceresos, casa hogar, casa de retiro, tutelar de menores y otros................................ 6.00 UMA\nd).- Celebración de matrimonio ordinario\n(en viernes o sábado), dentro de la oficina, con anticipación de 8 días previa cita................................... 20.25 UMA\ne).- Celebración de matrimonio urgente\n(en viernes o sábado), dentro de la oficina, con anticipación de 7 días a\n48 horas, previa cita.......................... 41.85 UMA e.1).- Celebración de matrimonio extra urgente,(en viernes o sábado), dentro de la oficina, con 24 horas de anticipación y previa cita................................... 57.38 UMA\nf).- Celebración de matrimonio a domicilio dentro de la ciudad con anticipación de\n8 días, previa cita:\na).- En horas hábiles......................... 54.00 UMA\nb).- En horas inhábiles....................... 81.00 UMA\nc).- En día inhábil (domingo)................. 90.00 UMA\ng).- Celebración de matrimonio urgente a domicilio, dentro de la ciudad, con anticipación de 7 días a 48 horas, previa cita:\na).- En horas hábiles........................ 74.25 UMA\nb).- En horas inhábiles...................... 94.50 UMA\nc).- En día inhábil (domingo)................ 100.00 UMA g.1).- Celebración de matrimonio extra urgente a domicilio, dentro de la ciudad, con anticipación de\n24 horas, previa cita:\na).- En horas hábiles................. 94.50 UMA\nb).- En horas inhábiles............... 114.75 UMA\nc).- En día inhábil\n(domingo)........................ 120.00 UMA\nh).- Celebración de matrimonio a domicilio, fuera de la mancha urbana, con anticipación de 8 días, previa cita:\na).- En horas hábiles....................... 74.25 UMA\nb).- En horas inhábiles..................... 101.25 UMA\nc).- En día inhábil\n(domingo).............................. 110.00 UMA h.1).- Celebración de matrimonio a domicilio, urgente fuera de la mancha urbana, con anticipación de 7 días a 48 horas previa cita:\na).- En horas hábiles................ 87.75 UMA\nb).- En horas inhábiles.............. 108.00 UMA\nc).- En día inhábil\n(domingo)........................ 115.00 UMA h.2).- Celebración de matrimonio a domicilio, extra urgente fuera de la mancha urbana, con anticipación de 24 horas, previa cita:\na).- En horas hábiles................ 108.00 UMA\nb).- En horas inhábiles.............. 128.25 UMA\nc).- En día inhábil\n(domingo)....................... 130.00 UMA h.3).- Celebración de matrimonio celebrado por la Oficialía, en\nDelegaciones:\na).- Ordinario con anticipación de documentos recibidos, 7 días antes en la Oficialía...... 141.75 UMA\nb).- Urgente con anticipación de documentos recibidos, 4 días antes en la Oficialía...... 157.95 UMA\nc).- Extra urgente con anticipación de documentos, recibidos un día antes en la Oficialía.................... 172.80 UMA\ni).- Inscripción de matrimonio, celebrado fuera de la República........................ 27.00 UMA i.1).- Inscripción de matrimonio extra urgente, celebrado fuera de la\nRepública.............................. 54.00 UMA\nj).- Solicitud y formato para certificados médicos prenupciales para celebración de matrimonio................................. 2.03 UMA\nk).- Solicitud, formato para certificados médicos, pláticas prenupciales y celebración de matrimonios dentro del programa de matrimonios colectivos........... $1.00 PESO\nl).- Cambio de régimen matrimonial o modificación a las capitulaciones matrimoniales................................. 21.60 UMA\nm).- Inscripción de matrimonio urgente, celebrado fuera de la República\nMexicana...................................... 40.50 UMA\nn).- Pláticas prematrimoniales..................... 2.70 UMA n.1).- Pláticas prematrimoniales urgentes............................... 4.00 UMA n.2).- Pláticas prematrimoniales en línea (no presencial)............... 5.00 UMA ñ).- Inexistencia de matrimonio local para trámite de matrimonio expedida por sistema SID.................................... 2.70 UMA\nC.- DEFUNCIONES:\na).- Registro en las oficinas en horas hábiles......................................... EXENTO\nb).- Registro en las oficinas en horas inhábiles...................................... 4.05 UMA\na).- Fuera de la oficina en horas inhábiles................................. 6.08 UMA\nc).- Permiso de inhumaciones a panteones particulares en:\na).- Horas hábiles............................ 10.13 UMA\nb).- Horas inhábiles.......................... 11.48 UMA\nd).- Inscripción de defunciones ocurridas fuera de la República......................... 18.90 UMA\ne).- Permiso de cremación a panteones particulares en:\na).- Horas hábiles........................... 8.78 UMA\nb).- Horas inhábiles.......................... 10.13 UMA\nf).- Permiso de inhumación de cenizas a panteones particulares en:\na).- Horas hábiles............................. 3.38 UMA\nb).- Horas inhábiles........................... 3.38 UMA\ng).- Expedición de orden de inhumación:\na).- Horas hábiles e inhábiles................. 6.08 UMA\nh).- Registro de defunciones extemporáneas, ordenadas por el Ministerio Público o autoridad competente........................... 6.08 UMA\ni).- Presunción de muerte........................... 27.00 UMA\nj).- Expedición de orden de exhumación.............. 8.10 UMA\nPara obtener exención de los incisos anteriores, deberán\nMunicipal, el cual emitirá el estudio socioeconómico correspondiente y éste a su vez girará oficio al C. Oficial del\nRegistro Civil, para exentar el pago de derechos.\nEn el caso de las defunciones SARS-COV2 (COVID19), se exentará el registro, orden de inhumación y/o incineración según sea el caso, tramitados por un familiar directo.\nD.- DIVORCIOS:\na).- Divorcio administrativo por mutuo consentimiento, tramitado en oficina del Registro Civil............................ 54.00 UMA a.1).- Divorcio administrativo por mutuo consentimiento, tramitado\nen CERESO.............................. 76.95 UMA a.2).- Divorcio administrativo urgente\n(dentro de las 48 horas la primera cita), por mutuo consentimiento, tramitado en oficina de Registro Civil...................... 60.75 UMA a.3).- Cambio de régimen y anotación en el acta de matrimonio para inscripción de Divorcio Administrativo................................ 5.00 UMA\nb).- Por registro de divorcio proveniente del juzgado................................... 27.00 UMA b.1).- Campaña de inscripciones de divorcio proveniente del Juzgado dentro de la República................. 20.25 UMA\nc).- Registro de divorcio urgente, proveniente del juzgado, (dentro del plazo de 48 horas).................................. 54.00 UMA c.1).- Registro de divorcio extraordinario, proveniente del juzgado\n(dentro del plazo de 24 horas)......... 67.50 UMA\nd).- Inscripción de divorcio efectuado fuera de la República, ordenado por el Juez competente.................................... 40.50 UMA\ne).- Proveniente de la defensoría de oficio, previa solicitud y constancia de estudio socioeconómico de la misma............. EXENTO\nf).- Inscripción de divorcio urgente, efectuado fuera de la República, por un\nJuez competente.............................. 54.00 UMA\nE.- ADOPCIONES\na).- Registro...................................... 27.00 UMA a.1).- Registro extraordinario, dentro de las 48 horas........................ 40.50 UMA\nb).- Inscripción de adopción, efectuado fuera de la República......................... 33.75 UMA\nF.- EXPEDICIÓN DE ACTAS Y CERTIFICADOS:\na).- Servicio ordinario............................ 2.03 UMA\nLa solicitud es de 8:00 a 12:00 horas, para ser entregada de 12:00 a 16:30 horas.\nb).- Servicio extraordinario....................... 6.75 UMA\nSolicitado antes de las 12:00 horas, para entrega en 45 minutos.\nC).- En el caso de las actas de nacimiento, exento el 100% del cobro, de expedición de la primera copia certificada del acta de registro de nacimiento.\nF.1.- EXPEDICIÓN DE ACTAS INTERESTATALES PAGO A\nMUNICIPIO.......................................... 1.5 UMA\nF.2.- EXPEDICIÓN DE ACTAS INTERESTATALES PAGO\nF.3.- EXPEDICIÓN DE ACTAS INTERESTATALES PAGO DE\nIMPUESTO A LA EDUCACIÓN PARA GOBIERNO DEL\nESTADO................................................ 35%\nF.4.- Las personas pensionadas o jubiladas y sus cónyuges; las personas viudas; las madres solteras; de escasos recursos, e hijos de éstas, siempre que sean menores de edad; las personas pertenecientes a pueblos originarios o afromexicanas; pagarán\n50% de la tarifa únicamente tratándose de documentos que estén a su nombre, debiendo comprobar su condición con identificación o documentación expedida por Institución\nPública.\nF.5.- Tratándose de personas en situación de calle mayores de 60 años y las personas con discapacidad, estarán exentos de pago previa solicitud y en su caso, estudio socioeconómico y certificado médico que acredite tal condición.\nF.6.- Las personas físicas de escasos recursos que utilicen los servicios de la Defensoría de Oficio en la tramitación de procedimientos Judiciales, Civiles y\nPenales, previo estudio socioeconómico que elabore la Dirección de Educación, Cultura y Asistencia Social, se les exentará del pago de los derechos por los servicios que presta el Registro Civil, a solicitud expresa del Titular de la Defensoría de\nOficio siempre y cuando no exceda de 13.50\nUMA por servicio, exención que será otorgada al interesado por única ocasión.\nG.- POR TRÁMITE DE TRASLADO DE CADÁVERES:\na).- Fuera del País................................ 33.75 UMA\nb).- Fuera del Municipio........................... 4.05 UMA\nc).- Dentro del Municipio.......................... 1.35 UMA\nd).- Fuera del Estado.............................. 6.75 UMA\nH.- POR TRÁMITE DE TRASLADO DE CENIZAS:\na).- Fuera del País................................ 6.75 UMA\nb).- Fuera del Municipio........................... 2.03 UMA\nc).- Dentro del Municipio.......................... 1.35 UMA\nd).- Fuera del Estado.............................. 3.38 UMA\nI.- OTROS:\na).- Reconocimiento de hijos:\na).- Registro o celebración ordinarios........ 8.10 UMA\nb).- Registro o celebración urgente........... 10.80 UMA\nc).- Registro o celebración extra urgente.................................. 13.50 UMA\nd).- Registro de reconocimiento de hijos dentro del programa “Jornadas del Registro Civil”.................. 4.05 UMA d.1) Trámite de anotación marginal y reserva en Acta de Nacimiento y reconocimiento de hijos:.............................. 2.70 UMA\nb).- Trámite de rectificación de actas.............. 4.05 UMA\nc).- Registro de capitulaciones..................... 13.50 UMA\nd).- Renovación de comprobantes de nacimiento, matrimonio y otros......................... 4.05 UMA\ne).- Trascripción de juicios de divorcios, adopción, tutela, ausencia, pérdida o limitación de la capacidad para administrar bienes, nacimientos, matrimo- nios o cambios de régimen...................... 4.05 UMA\nf).- Recepción, trámite y anotación marginal....................................... 1.35 UMA\ng).- Trámite de cancelación de actas por duplicidad..................................... 6.75 UMA\nh).- Constancia o copia certificada, dentro del programa inscripciones escolares........... 1.00 UMA\ni).- Otros certificados............................. 1.35 UMA\n1).- Otros certificados urgentes............... 2.70 UMA\n2).- Expedición de copia certificada, por cada hoja del apéndice................ 1.35 UMA\n3).- Expedición de todo el apéndice............ 4.05 UMA\n4).- Constancia por trámites que se les realiza en esta oficialía a usuarios... 1.35 UMA\n5).- Devolución de documentos extranjeros y/o traducciones oficiales integrados en apéndices de actos registrales........ 2.03 UMA\n6).- Reimpresión de actas de los diferentes actos registrales (por error, omisión y/o cancelación por parte de usuarios).... 2.03 UMA\n7).- Copias certificadas del apéndice urgente................................... 8.10 UMA\n8).- Copias certificadas del apéndice extraordinaria........................... 16.20 UMA\nj).- Reimpresión de CURP............................ 0.34 UMA\nk).- Sello de Oficialía para trámite de apostilla...................................... 1.00 UMA\nl).- Gestión, llenado y revisión de formatos........ 0.05 UMA\nm).- Por expedición de actas y certificados urgentes, se cobrará el doble de la tarifa.\nn).- Las personas pensionadas o jubiladas y sus cónyuges; las personas viudas; las madres solteras; e hijos de éstas, siempre que sean menores de edad; las personas pertenecientes a pueblos originarios o afromexicanas; pagarán 50% de la tarifa únicamente tratándose de documentos que estén a su nombre, debiendo comprobar su condición con identificación o documentación expedida por Institución Pública.\no).- Tratándose de personas en situación de calle mayores de 60 años y las personas con discapacidad, estarán exentos de pago, previa solicitud y en su caso, estudio socioeconómico y certificado médico que acredite tal condición.\np).- Las personas físicas de escasos recursos que utilicen los servicios de la defensoría de oficio en la tramitación de procedimientos\nJudiciales, Civiles y Penales, previo estudio socioeconómico que elabore dicha dependencia se les exentará del pago de los derechos por los servicios que presta el Registro civil, a solici- tud expresa del titular de la Defensoría de\nOficio siempre y cuando no exceda de 13.50\nUMA por servicio, exención que será otorgada al interesado por única ocasión.\nq).- Rectificación de acta de nacimiento por cambio de identidad sexogenérica................. EXENTO\nII.- LA COORDINACIÓN MUNICIPAL DE PROTECCIÓN CIVIL\nARTÍCULO 17.- Los servicios que presta la Coordinación Municipal de Protección Civil a giros comerciales, industriales, de servicios, los sectores públicos y sociales, se causarán conforme a la siguiente:\nUNIDAD DE MEDIDA Y ACTUALIZACIÓN\n(UMA)VIGENTE\nI.- POR EVALUACIÓN Y ANÁLISIS A PROYECTOS DE EDIFICACIÓN\n1.- POR FACTIBILIDAD DE PROYECTOS O POR REVISIÓN DE PROYECTOS\nDE CONSTRUCCIÓN:\nCONSTRUCCIÓN REGULARIZACIÓN\n1).- Casa habitación............... 13.50 UMA 27.00 UMA\n2).- Fraccionamientos.............. 18.90 UMA 37.80 UMA\n(por edificación)\n3).- Condominios:\na).- De 1 a 5 viviendas....... 27.00 UMA 54.00 UMA\nb).- De 6 hasta 10 viviendas.. 54.00 UMA 104.00 UMA\nc).- De 11 hasta 20 viviendas. 81.00 UMA 162.00 UMA\nd).- De 21 viviendas en adelante 121.50 UMA 243.00 UMA\n4).- Departamentos habitacionales:\na) De 1 a 10 viviendas........ 20.25 UMA 40.50 UMA\nb) Más de 10 viviendas........ 40.50 UMA 81.00 UMA\n5).- Comercial(por metro cuadrado):\na).- Hasta 200 m².............. 0.16 UMA 0.34 UMA\nb).- De 201 hasta 400 m²....... 0.18 UMA 0.35 UMA\nc).- De 401 hasta 700 m²....... 0.19 UMA 0.38 UMA\nd).- De 701 hasta 1,000 m²..... 0.22 UMA 0.43 UMA\ne).- De 1,001 hasta 2,000 m²... 0.24 UMA 0.49 UMA\nf).- De más de 2,000 m²........ 0.27 UMA 0.54 UMA\n6).- Mixto:\na).- Habitacional-comercial\n(por metro cuadrado)...... 0.14 UMA 0.27 UMA\nb).- Industrial-comercial\n(por metro cuadrado)...... 0.18 UMA 0.35 UMA\n7).- Comercial o industrial de alto riesgo.................. 270.00 UMA 540.00 UMA\n8).- Industrial:\na) De hasta 2,500 m²......... 67.50 UMA 135.00 UMA\nb) Mayor de 2,500 m²......... 135.00 UMA 270.00 UMA\n9).- Casas de asistencia, estancias infantiles.......... 13.50 UMA 27.00 UMA\n10).- Escuelas primarias, secundarias:\nPor metro cuadrado............. 0.27 UMA 0.47 UMA\n11).- Preparatorias, universidades:\nPor metro cuadrado............. 0.54 UMA 0.68 UMA\n12).- Anuncios:\na).- Espectaculares........... 20.25 UMA 27.00 UMA\nb).- Tipo pantalla............ 33.75 UMA 47.25 UMA\n13).- Antena de radiocomunicación y telecomunicaciones........... 270.00 UMA 337.50 UMA\n14).- Patios de maniobras y de almacenamiento de contenedores marítimos.\n(por cada 250 m² o fracción de terreno)........................ 45.00 UMA 87.50 UMA\n15).- Otros no especificados (Por metro cuadrado)................. 0.16 UMA 0.31 UMA\n16).- Por revaluación de proyectos por cambios generados a proyectos ya aprobados\n(por cada plano)............. 0.75 UMA A 1.00 UMA\n2).- OPINIÓN TÉCNICA SOBRE ANÁLISIS DE RIESGO\na).- De acuerdo al uso y superficie del predio:\n1) Casa habitación unifamiliar..... 1.35 UMA por cada\n25 m² o fracción\n2) Multifamiliar:\nI) De hasta 4 viviendas................ 13.50 UMA\nII) De hasta 12 viviendas............... 40.50 UMA\nIII) De hasta 20 viviendas............... 67.80 UMA\nIV) De más de 20 viviendas... 3.40 UMA por vivienda\n3) Fraccionamientos (por hectárea o fracción):\nI) De hasta 10,000 m²................. 130.00 UMA\nII) De hasta 50,000 m²................. 120.00 UMA\nIII) De hasta 100,000 m²................ 110.00 UMA\nIV) De más de 100,000 m²............... 100.00 UMA\n4) Servicios:\nI) De baja vulnerabilidad.............. 10.80 UMA\nII) De media vulnerabilidad............. 27.00 UMA\nIII) De alta vulnerabilidad.............. 43.20 UMA\n5) Comercial:\nI) Hasta 70 m² de área de operación...... 13.50 UMA\nII) Hasta 140 m² de área de operación.... 33.75 UMA\nIII) Hasta 210 m² de área de operación.... 54.00 UMA\nIV) Hasta 350 m² de área de operación.... 92.50 UMA\nV) Hasta 700 m² de área de operación.... 190.00 UMA\nVI) Hasta 1,050 m² de área de operación.. 292.50 UMA\nVII) Hasta 1,400 m² de área de operación.. 400.00 UMA\nVIII) Más de 1,400 m² de área de operación.\n(Por cada 140 m² de área de operación o fracción)............................ 41.00 UMA\n6) Industrial:\nI) De hasta 500 m²...................... 20.25 UMA\nII) De hasta 1,000 m².................... 40.50 UMA\nIII) De hasta 2,500 m².................... 81.00 UMA\nIV) De hasta 10,000 m²................... 135.00 UMA\nV) De más de 10,000 m².......... 2.025 UMA por cada\n100 m² o fracción\n7) Mixto: Comercial-habitacional:\nI) De hasta 3,000 m²............ 0.675 UMA por cada\n20 m² o fracción\nII) De más de 3,000 m².......... 1.35 UMA por cada\n20 m² o fracción\n8) Mixto: Industrial-Comercial:\nI) De hasta 5,000 m²............ 0.675 UMA por cada\n16 m² o fracción\nII) De más de 5,000 m²........... 1.35 UMA por cada\n16 m² o fracción\n9) Educativo:\nI) Guarderías y/o preescolares.......... 13.50 UMA\nII) Primaria y/o secundaria.............. 16.20 UMA\nIII) Preparatoria y/o universidad......... 27.00 UMA\nIV) Mixto................................ 20.25 UMA\n10) Agrícola, pecuario o forestal.... 1.35 UMA por cada\n50 m² o fracción\n11) Alto riesgo.................... 1.35 UMA por cada\n12 m² o fracción\n12).- Por revaluación de proyectos por cambios generados a proyectos ya aprobados\n(por cada plano)........... 0.75 UMA A 1.00 UMA\n13).- Patios de maniobras y de almacenamiento de contenedores marítimos:\nI) De hasta 500 m²................... 56.25 UMA\nII) De hasta 1,000 m²................. 112.50 UMA\nIII) De hasta 2,500 m²................. 281.25 UMA\nIV) De hasta 10,000 m²................ 1,125.00 UMA\nV) De más de 10,000 m²...........11.25 UMA por cada\n100 m² o fracción\nb).- En caso de procedimientos para regularización, el monto a cubrir será el doble de lo indicado en el inciso anterior.\nc).- Para instalaciones con dos o más actividades, el monto se determinará de acuerdo a la suma de las áreas de superficie ocupada por cada actividad.\nII.- REGISTRO DE EMPRESAS QUE MANEJAN MATERIALES PELIGROSOS, CON\nUNA VIGENCIA DE UN AÑO:\nREGISTRO REVALIDACIÓN\n1).- Microindustria, de 1 a 25 empleados................. 13.50 UMA 10.80 UMA\n2).- Pequeña industria, de 26 a 100 empleados................ 27.00 UMA 20.25 UMA\n3).- Pequeña industria, de 101 a 250 empleados................ 40.50 UMA 33.75 UMA\n4).- Macroindustria, de 251 empleados en adelante.......... 67.50 UMA 47.25 UMA\nIII.- INSPECCIONES DE MEDIDAS DE SEGURIDAD EN EDIFICACIONES, A\nPETICIÓN DE PARTE:\nEn zona En zona urbana rural (más de 80 Km.)\n1).- Solicitudes a través del Sistema de Apertura Rápida De Empresas\n(SARE) por superficie de operación, que incluye: construcción, estacionamiento, patio de servicio y áreas verdes:\na).- De 1 a 50 Metros de operación. 6.75 UMA 13.50 UMA\nb).- De 51 a 100 Metros de operación..................... 10.13 UMA 20.25 UMA\nc).- De 101 a 150 Metros de operación..................... 13.50 UMA 27.00 UMA\nd).- De 151 a 200 Metros de operación..................... 16.88 UMA 33.75 UMA\ne).- Regularización de comercio, servicios y otros a través del\nSistema de Apertura Rápida de\nEmpresas (SARE), hasta 200 m² de superficie de operación, 50% adicional al costo del trámite normal, por año que se haya encontrado operando.\n2).- Comercio en pequeño, hasta 50 m² de superficie:\na) Sin venta de bebidas alcohólicas.................. 10.13 UMA 20.25 UMA\nb) Con venta de bebidas alcohólicas.................. 16.88 UMA 33.75 UMA\n3).- Despachos de profesionistas, zapaterías, neverías, casas de cambio y giros de servicios..... 9.45 UMA 18.90 UMA\n4).- Desmanteladoras, recicladoras, panaderías, lavanderías, clínicas, ferreterías, pizzerías, tiendas de ropa, misceláneas, farmacias, papelerías, librerías, telefonía y templos religiosos....................... 13.50 UMA 27.50 UMA\n5).- Café internet, centros de copiado y/o impresión, videojuegos.... 10.80 UMA 21.60 UMA\n6).- Fonda, loncherías, coctelería, cocina económica:\na) Sin venta de bebidas alcohólicas................... 13.50 UMA 20.25 UMA\nb) Con venta de bebidas alcohólicas................... 27.00 UMA 40.25 UMA\n7).- Restaurante:\na) Sin venta de bebidas alcohólicas................... 27.00 UMA 30.25 UMA\nb) Con venta de bebidas alcohólicas................... 40.50 UMA 67.50 UMA\n8).- Abarrotes, tienda de autoservicio, billares:\na) Sin venta de bebidas alcohólicas................... 13.50 UMA 20.25 UMA\nb) Con venta de bebidas alcohólicas................... 40.50 UMA 54.00 UMA\n9).- Mercado, supermercado, bodega de distribución:\na) Sin venta de bebidas alcohólicas................... 27.00 UMA 40.50 UMA\nb) Con venta de bebidas alcohólicas................... 60.75 UMA 81.00 UMA\n10).- Establecimientos Vitivinícolas o de cervecería artesanal:\na).- Microcervecería............. 16.20 UMA 21.60 UMA\nb).- Cervecería Artesanal:\nI).- De hasta 50 personas de ocupación........... 20.25 UMA 27.00 UMA\nII).- De más de 50 personas de ocupación........... 40.50 UMA 54.00 UMA\nc).- Establecimientos Vitivinícolas:\nI).- Cavas.................. 20.25 UMA 40.50 UMA\nII).- Sala de degustación, boutique............... 27.00 UMA 40.50 UMA\nIII).- Colectivos............. 40.50 UMA 54.00 UMA\nd).- Industria y conceptos no especificados............ 54.00 UMA 67.50 UMA\n11).- Licorerías, expendio, centro botanero, agencia, subagencia, depósito... 40.50 UMA 54.00 UMA\n12).- Bar turístico, restaurant-bar, bar terraza...................... 60.75 UMA 81.00 UMA\n13).- Café cantante.................... 60.75 UMA 81.00 UMA\n14).- Discotecas....................... 94.50 UMA 108.00 UMA\n15).- Tiendas departamentales.......... 33.75 UMA 43.20 UMA\n16).- Hospital, cines, teatros......... 27.00 UMA 40.50 UMA\n17).- Centros deportivos, gimnasios:\na).- De hasta 200 personas....... 20.25 UMA 37.80 UMA\nb).- De hasta 500 personas....... 40.50 UMA 54.00 UMA\nc).- De hasta 1000 personas..... 45.00 UMA 56.00 UMA\nd).- De hasta 2500 personas...... 55.00 UMA 66.00 UMA\ne).- De hasta 5000 personas...... 65.00 UMA 75.00 UMA\nf).- De 5,001 personas en adelante.................. 75.00 UMA 85.00 UMA\n18).- Centros Recreativos:\na).- Albercas:\nI).- Sin consumo de bebidas alcohólicas............ 27.00 UMA 40.50 UMA\nII).- Con consumo de bebidas alcohólicas........... 40.50 UMA 47.25 UMA\nb).- Balnearios:\nI).- Sin consumo de bebidas alcohólicas........... 27.00 UMA 51.30 UMA\nII).- Con consumo de bebidas alcohólicas........... 54.00 UMA 60.75 UMA\nc).- Centros de entretenimiento, de juegos infantiles y similares................... 22.50 UMA 30.00 UMA\n19).- Salón para eventos, con capacidad:\na).- De hasta 100 personas:\nI).- Sin consumo de alcohol:\na).- En área abierta........ 13.50 UMA 20.25 UMA\nb).- En área cerrada o mixta................... 12.50 UMA 17.50 UMA\nII).- Con consumo de alcohol:\na).- En área abierta....... 16.00 UMA 21.00 UMA\nb).- En área cerrada o mixta................. 18.50 UMA 23.50 UMA\nb).- De 101 hasta 250 personas:\nI).- Sin consumo de alcohol:\na).- En área abierta....... 20.25 UMA 30.38 UMA\nb).- En área cerrada o mixta................. 23.97 UMA 34.09 UMA\nII).- Con consumo de alcohol:\na).- En área abierta........ 28.35 UMA 38.48 UMA\nb).- En área cerrada o mixta.................. 32.07 UMA 31.75 UMA\nc).- De 251 hasta 500 personas:\nI).- Sin consumo de alcohol:\na).- En área abierta........ 27.00 UMA 40.50 UMA\nb).- En área cerrada o mixta.................. 31.05 UMA 44.55 UMA\nII).- Con consumo de alcohol:\na).- En área abierta....... 35.10 UMA 48.60 UMA\nb).- En área cerrada o mixta................. 39.15 UMA 52.65 UMA\nd).- De 501 hasta 750 personas:\nI).- Sin consumo de alcohol:\na).- En área abierta....... 33.75 UMA 50.63 UMA\nb).- En área cerrada o mixta.................. 39.15 UMA 56.03 UMA\nII).- Con consumo de alcohol:\na).- En área abierta....... 41.85 UMA 58.73 UMA\nb).- En área cerrada o mixta................. 47.25 UMA 64.13 UMA\ne).- De más de 751 personas:\nI).- Sin consumo de alcohol:\na).- En área abierta....... 40.50 UMA 57.38 UMA\nb).- En área cerrada o mixta.................. 47.25 UMA 64.13 UMA\nII).- Con consumo de alcohol:\na).- En área abierta....... 48.60 UMA 65.48 UMA\nb).- En área cerrada o mixta.................. 41.00 UMA 53.50 UMA\n20).- Hoteles y moteles:\nA) Sin venta de bebidas alcohólicas:\na).- Hasta 10 habitaciones.... 20.25 UMA 29.70 UMA\nb).- De 11 a 20 habitaciones.. 27.00 UMA 40.50 UMA\nc).- De 21 a 30 habitaciones.. 40.50 UMA 56.70 UMA\nd).- De 31 a 40 habitaciones.. 56.70 UMA 76.95 UMA\ne).- De 41 a 50 habitaciones.. 72.90 UMA 93.15 UMA\nf).- De 51 a 60 habitaciones.. 89.10 UMA 109.35 UMA\ng).- De 61 habitaciones en adelante................. 105.30 UMA 125.55 UMA\nB) Con venta de bebidas alcohólicas:\na).- Hasta 10 habitaciones.... 27.00 UMA 36.45 UMA\nb).- De 11 a 20 habitaciones.. 33.75 UMA 47.25 UMA\nc).- De 21 a 30 habitaciones.. 47.25 UMA 63.45 UMA\nd).- De 31 a 40 habitaciones.. 63.45 UMA 83.70 UMA\ne).- De 41 a 50 habitaciones.. 79.65 UMA 99.90 UMA\nf).- De 51 a 60 habitaciones.. 129.40 UMA 116.10 UMA\ng).- De 61 habitaciones en adelante................. 112.05 UMA 132.30 UMA\n21).- Instituciones educativas y/o de asistencia privadas:\nA).- Instituciones educativas privadas:\na).- Jardín de niños........ 10.13 UMA 13.50 UMA\nb).- Escuela primaria....... 10.13 UMA 13.50 UMA\nc).- Escuela secundaria..... 6.75 UMA 13.50 UMA\nd).- Escuela preparatoria y/o técnica........... 10.13 UMA 13.50 UMA\ne).- Colegios............... 20.25 UMA 33.75 UMA\nf).- Universidad............ 20.25 UMA 33.75 UMA\ng).- Otros no especificados.. 13.50 UMA 27.00 UMA\nB).- Guarderías y estancias infantiles, de acuerdo a su capacidad:\na).- De 1 hasta 10 niños.... 5.07 UMA 10.80 UMA\nb).- De 11 hasta 50 niños... 10.13 UMA 13.50 UMA\nc).- De 51 hasta 100 niños.. 20.25 UMA 33.75 UMA\nd).- Más de 101 niños....... 30.38 UMA 40.50 UMA\nC).- Casa de cuidado y centros de tareas................... 5.07 UMA 13.50 UMA\nD).- Albergues................... 10.13 UMA 13.50 UMA\nE).- Casa hogar de asistencia.... 10.13 UMA 13.50 UMA\nF).- Centros de rehabilitación física y de adicciones...... 31.90 UMA 51.03 UMA\n22).- Instalaciones industriales:\na).- Microindustria, hasta 50 empleados................... 27.00 UMA 40.50 UMA\nb).- Pequeña industria, de 51 a\n200 empleados............... 40.50 UMA 57.38 UMA\nc).- Mediana industria, de 201 a 500 empleados............. 60.75 UMA 75.60 UMA\nd).- Mega industria, de 501 a\n1,000 empleados............. 81.00 UMA 103.28 UMA\ne).- Macroindustria, de 1,001 empleados en adelante (por cada 100 empleados o fracción)................. 8.10 UMA 8.78 UMA\n23).- Giros de alto riesgo:\na).- Estaciones de gasolina y gas para carburación....... 81.00 UMA 101.25 UMA\nb).- Distribuidores de gases y químicos.................... 148.50 UMA 168.75 UMA\nc).- Distribuidores de combustible y lubricantes... 148.50 UMA 168.75 UMA\nd).- Almacenes de materiales peligrosos................. 148.50 UMA 168.75 UMA\ne).- Lugares con venta de\nPirotecnia.................. 81.00 UMA 101.25 UMA\nf).- Polvorines................. 148.50 UMA 168.75 UMA\ng).- Centros de apuestas, apuestas remotas, salas de sorteos de número y/o casinos, dictamen de operación............... 297.00 UMA 324.00 UMA\nh).- Plantas distribuidoras y/o de almacenamiento de gas L.P. o natural a gran escala.... 800.00 UMA 960.25 UMA\ni).- Plantas generadoras de energía eléctrica.................. 350.00 UMA 420.00 UMA\nj).- Industria de alto riesgo.... 81.00 UMA 101.25 UMA\nk).- Patios de maniobras y de almacenamiento, de contenedores marítimos...................250.00 UMA 340.90 UMA\nl).- Otros de alto riesgo....... 148.50 UMA 168.75 UMA\n24).- Casas de empeño.................. 27.00 UMA 47.25 UMA\n25).- Instituciones bancarias y similares........................ 40.50 UMA 60.75 UMA\n26).- Refaccionarias, autopartes, venta de pinturas, venta de productos de limpieza,talleres y actividades similares.......... 23.63 UMA 37.80 UMA\n27).- Mercados comunes o públicos:\na).- En vía o área pública:\nI) De hasta 50 puestos.... 13.50 UMA 20.25 UMA\nII) De hasta 100 puestos.... 20.25 UMA 27.00 UMA\nIII) De hasta 150 puestos.... 27.00 UMA 33.75 UMA\nIV) De hasta 200 puestos.... 33.75 UMA 40.50 UMA\nV) De hasta 250 puestos.... 40.50 UMA 47.25 UMA\nVI) De hasta 300 puestos.... 47.25 UMA 54.00 UMA\nVII) De más de 300 puestos.... 54.00 UMA 60.75 UMA\nb).- En propiedad privada:\nI) De hasta 50 puestos.... 27.00 UMA 33.75 UMA\nII) De hasta 100 puestos.... 33.75 UMA 40.50 UMA\nIII) De hasta 150 puestos.... 40.50 UMA 47.25 UMA\nIV) De hasta 200 puestos.... 47.25 UMA 54.00 UMA\nV) De hasta 250 puestos.... 54.00 UMA 60.75 UMA\nVI) De hasta 300 puestos.... 60.75 UMA 67.50 UMA\nVII) De más de 300 puestos.... 67.50 UMA 91.13 UMA\n28).- Otros giros menores no especificados.................... 20.25 UMA 27.00 UMA\n29).- Otros giros mayores no especificados.................... 47.25 UMA 54.00 UMA\nIV.- INSPECCIONES DE MEDIDAS DE SEGURIDAD EN EDIFICACIONES,\nDE OFICIO:\nSe cobrarán las UMA (Unidad de Medida y Actualización) vigente, indicado en el apartado anterior, más el 40% del mismo.\nV.- POR SEGUNDA O POSTERIOR VERIFICACIÓN DE CUMPLIMIENTO DE\nMEDIDAS DICTAMINADAS:\nSe cobrarán a razón del 30% del monto establecido en la fracción\nIII anterior.\nVI.- POR REVISIÓN DE PROGRAMA INTERNO DE PROTECCIÓN CIVIL Y/O\nPLAN DE CONTINGENCIAS SUJETO A APROBACIÓN:\nAPROBACIÓN REVALIDACIÓN\n1).- Instituciones educativas y de asistencia:\nA).- Instituciones educativas:\na).- Jardín de niños, escuela primaria........ 13.50 UMA 9.45 UMA\nb).- Escuela secundaria...... 16.20 UMA 10.80 UMA\nc).- Escuela preparatoria y/o técnica, colegios... 20.25 UMA 13.50 UMA\nd).- Universidad............. 24.30 UMA 16.20 UMA\ne).- Centros de investigación y desarrollo, y otros no especificados........... 27.00 UMA 20.25 UMA\nB).- Guarderías y estancias infantiles, de acuerdo a su capacidad:\na).- De 1 hasta 10 niños..... 10.13 UMA 7.09 UMA\nb).- De 11 hasta 50 niños.... 12.15 UMA 8.10 UMA\nc).- De 51 hasta 100 niños... 15.19 UMA 10.13 UMA\nd).- Más de 101 niños........ 20.25 UMA 15.19 UMA\nC).- Casas de cuidado y centros de tareas....................... 13.50 UMA 9.45 UMA\nD).- Albergues................... 16.20 UMA 10.80 UMA\nE).- Casa hogar o de asistencia... 13.50 UMA 9.45 UMA\nF).- Centros de rehabilitación:\na).- Física.................. 20.25 UMA 13.50 UMA\nb).- De adicciones........... 27.00 UMA 20.25 UMA\nG).- Otros no especificados....... 27.00 UMA 20.25 UMA\n2).- Comercios y de servicios:\nA).- Librerías, papelerías, ferreterías, oficinas, misceláneas, tiendas de ropa, restaurantes, billares, panaderías, lavanderías, farmacias, expendios de comida.......... 13.50 UMA 9.45 UMA\nB).- Bar turístico, café-cantante, autoservicios, restaurant-bar, casas de empeño, discotecas, expendios de bebidas alcohólicas, moteles, mercados, hoteles............ 24.30 UMA 16.20 UMA\nC).- Salas cinematográficas, lugares para eventos sociales, templos religiosos, centros de convenciones, teatros, salas de exposiciones, bodega de distribución, supermercados, tienda departamental, vinícolas.................... 34.40 UMA 24.30 UMA\nD).- Otros giros no especificados:\na).- De menos de 150 m² de construcción......... 16.20 UMA 10.80 UMA\nb).- De 150 a 300 m² de construcción............ 20.25 UMA 13.50 UMA\nc).- De más de 301 a 500 m² de construcción...... 27.00 UMA 20.25 UMA\nd).- De más de 500 m² de construcción............ 33.75 UMA 27.00 UMA\n3).- Instituciones de salud:\nA).- Clínicas y centros de\nSalud........................ 13.50 UMA 9.45 UMA\nB).- Centros médicos.............. 16.20 UMA 10.80 UMA\nC).- Hospitales................... 27.00 UMA 20.25 UMA\n4).- Instalaciones industriales:\nA).- Microindustria, hasta 50 empleados.................... 20.25 UMA 13.50 UMA\nB).- Pequeña industria, de 51 a 200 empleados.............. 37.80 UMA 24.98 UMA\nC).- Mediana industria, de 201 a 500 empleados.............. 67.50 UMA 47.25 UMA\nD).- Mega industria, de 501 a\n1,000 empleados.............. 81.00 UMA 54.00 UMA\nE).- Macroindustria, de más de\n1,000 empleados.............. 94.50 UMA 62.10 UMA\n5).- Giros considerados de alto riesgo:\nA).- Estaciones de gasolina y gas para carburación........ 33.75 UMA 27.00 UMA\nB).- Distribuidores de gases...... 40.50 UMA 33.75 UMA\nC).- Distribuidores de combustibles y lubricantes... 40.50 UMA 33.75 UMA\nD).- Almacenes de materiales peligrosos................... 54.00 UMA 43.20 UMA\nE).- Lugares con venta de pirotecnia................... 40.50 UMA 33.75 UMA\nF).- Centros de apuestas, apuestas remotas, salas de sorteos de números y/o casinos..................... 270.00 UMA 270.00 UMA\nG).- Plantas distribuidoras y/o almacenamiento de gas L.P. o natural a gran escala..... 500.00 UMA 400.00 UMA\nH).- Plantas generadoras de energía eléctrica.................... 250.00 UMA 200.00 UMA\nI).- Otros de alto riesgo......... 40.50 UMA 33.75 UMA\nJ).- Patios de maniobras y de almacenamiento de contenedores marítimos................... 45.00 UMA 37.50 UMA\n6).- Otros giros no especificados...... 27.00 UMA 20.25 UMA\nVII.- POR SEGUNDA O POSTERIOR REVISIÓN DE PROGRAMAS INTERNOS DE\nPROTECCIÓN CIVIL Y/O PLAN DE CONTINGENCIAS PARA SU\nAPROBACIÓN:\nSe cobrarán a razón del 50% del monto establecido en el apartado anterior, la segunda y posteriores revisiones al programa interno de Protección Civil.\nVIII.- CERTIFICACIÓN DE DAÑOS POR BIENES SINIESTRADOS:\n1).- Todos los daños en general....... De 6.75 a 67.50 UMA\nQuedan exceptuados del pago de este derecho, aquellas siniestro.\nIX.- POR DETERMINACIÓN DE LAS MEDIDAS DE SEGURIDAD Y DE\nTEMPORALES:\n1).- Circos:\na).- Chicos (una pista)...................... 10.13 UMA\nb).- Grandes(de dos o más pistas)............ 20.25 UMA\n2).- Juegos mecánicos:\nEn zona En zona rural urbana (más de 80 km.)\na).- Chicos: hasta 10 atracciones. 13.50 UMA 20.25 UMA\nb).- Grandes: más de 10 atracciones 27.00 UMA 33.75 UMA\n3).- Exposiciones, ferias y kermeses:\na).- Por único día........................ 3.38 UMA\nb).- De hasta 5 días...................... 6.75 UMA\nc).- De hasta 15 días..................... 18.00 UMA\nd).- De hasta 30 días..................... 30.60 UMA\ne).- De más de 30 días (por día).......... 1.05 UMA\n4).- Exhibición de autos, motos................... 20.25 UMA\n5).- Carreras o competencias de vehículos (área urbana)...................... 27.00 UMA\n6).- Carreras de caballos, peleas de gallos....................................... 27.00 UMA\n7).- Rodeos, jaripeo, charreadas.................. 40.50 UMA\n8).- Paseo, caminata rural o turística.................................... 13.50 UMA\n9).- Eventos deportivos:\nA.- De bajo riesgo:\na).- De hasta 250 asistentes............. 7.50 UMA\nb).- De hasta 500 asistentes............. 10.80 UMA\nc).- De hasta 1,000 asistentes........... 13.50 UMA\nd).- De más de 1,000 asistentes.\n(Por cada 100 participantes o fracción).. 1.35 UMA\nB.- De alto riesgo:\na).- De hasta 500 asistentes.......... 40.50 UMA\nb).- De hasta 1,000 asistentes.......... 81.00 UMA\nc).- De hasta 2,500 asistentes.......... 87.75 UMA\nd).- De hasta 5,000 asistentes.......... 94.50 UMA\ne).- De hasta 7,500 asistentes......... 101.25 UMA\nf).- De hasta 10,000 asistentes......... 108.00 UMA\ng).- De hasta 15,000 asistentes......... 121.50 UMA\nh).- De más de 15,000 asistentes........ 135.00 UMA\n10).- Eventos gastronómicos:\na).- De hasta 500 asistentes................. 13.50 UMA\nb).- De hasta 1,000 asistentes............... 27.00 UMA\nc).- De hasta 2,000 asistentes............... 40.50 UMA\nd).- De más de 2,000 asistentes.............. 60.75 UMA\n11).- Espectáculos:\nEN LUGAR EN LUGAR\nCERRADO ABIERTO\na).- De hasta 500 asistentes.. 13.50 UMA 13.50 UMA\nb).- De 501 hasta 1,000 asistentes 27.00 UMA 24.30 UMA\nc).- De 1,001 hasta 2,500 asistentes 40.50 UMA 35.10 UMA\nd).- De 2,501 hasta 5,000 asistentes. 60.75 UMA 51.30 UMA\ne).- De 5,001 hasta 7,500 asistentes 81.00 UMA 67.50 UMA\nf).- De 7,501 hasta 10,000 asistentes 108.00 UMA 87.75 UMA\ng).- De 10,001 hasta 15,000 asistentes 135.00 UMA 108.00 UMA\nh).- De más de 15,000 asistentes. 162.00 UMA 141.75 UMA\n12).- Giros de alto riesgo:\na).- Distribuidores de Combustible y\nLubricantes.............................. 40.50 UMA\nb).- Otros giros de riesgo no especificados............................ 33.75 UMA\n13).- Otros eventos menores, no especificados................................ 13.50 UMA\n14).- Otros eventos mayores no especificados................................ 40.50 UMA\n15).- Cuando un evento se desarrolle en distintas áreas y con distintas actividades y en días distintos, se cubrirán los montos referidos considerando los mismos como eventos individuales y separados.\nLos servicios a los que hace referencia este inciso, quedarán exentos de pago únicamente, cuando sean organizados por instituciones de asistencia social o humanitarias y no lucrativas, así como las paramunicipales con la finalidad de apoyar su actividad.\nTodo trámite presentado con menos de 15 días naturales a la fecha de realización del evento, pagará un 200% del monto especificado y quedará fuera de la exención referida, de ser el caso.\nX.- SERVICIOS ESPECIALES:\n1).- Cálculo de ocupación para aforo máximo permitido:\nEn zona En zona urbana rural(más de 80 km.)\na).- Hasta 150 m² de Construcción...... 20.25 UMA 27.00 UMA\nb).- De 151 a 500 m² de Construcción... 33.75 UMA 40.50 UMA\nc).- De 501 a 750 m² de Construcción... 40.50 UMA 47.25 UMA\nd).- De 751 m² a 1,000 m² de\nConstrucción...................... 47.25 UMA 54.00 UMA\ne).- De 1,001 m² a 1,500 m² de\nConstrucción...................... 60.75 UMA 67.50 UMA\nf).- De 1,501 hasta 2,000 m² de\nConstrucción...................... 74.25 UMA 81.00 UMA\ng).- De 2,001 hasta 2,500 m² de\nConstrucción...................... 87.75 UMA 94.50 UMA\nh).- Más de 2,500 m² de Construcción.. 101.25 UMA 108.00 UMA\n2).- Cursos y talleres (por hora):\nEn zona En zona urbana rural (más de 80 km.)\nA).- Programa Interno de\nProtección Civil.............. 20.25 UMA 27.00 UMA\nB).- Análisis de riesgo y recursos...................... 27.00 UMA 40.50 UMA\nC).- Evacuación de Inmuebles....... 20.25 UMA 27.00 UMA\nD).- Señales y avisos de\nProtección Civil.............. 20.25 UMA 27.00 UMA\nE).- Otros no especificados........ 20.25 UMA 27.00 UMA\n3).- Pláticas informativas (por hora):\nA).- Sismos, incendios, ¿Qué hacer en caso de emergencia? 16.20 UMA 27.00 UMA\nB).- Brigadas Comunitarias y/o escolares..................... 16.20 UMA 27.00 UMA\nC).- Planeación y evaluación de\nSimulacros.................... 16.20 UMA 27.00 UMA\nD).- Otros no especificados........ 16.20 UMA 27.00 UMA\n4).- Evaluación técnica de simulacros de emergencia:\nEn zona En zona urbana Rural (más de 80 km.)\nA).- Comercial.................... 9.45 UMA 16.20 UMA\nB).- Industrial (Por cada 100 personas de ocupación o fracción)..... 7.10 UMA 6.75 UMA adicionales al monto a cubrir para zona urbana\nC).- Casas de asistencia, guarderías.................... 6.75 UMA 13.50 UMA\nD).- Giros de alto riesgo.......... 29.70 UMA 36.45 UMA\nE).- Otros no especificados........ 10.80 UMA 17.55 UMA\nLas evaluaciones técnicas de simulacros realizados fuera de horario laboral de la dependencia, deberán cubrir un monto de 6.75\nUMA, además del referido en el presente inciso.\n5).- Prórroga para dar cumplimiento a observaciones referidas en acta de inspección:\nA).- Por evaluación de solicitud.............. 0.68 UMA\nB).- Por otorgamiento de prórroga de hasta 20 días naturales:\n1).- Para establecimientos de baja ocupación y riesgo (comercio en pequeño, giros de servicio, café internet, despachos, loncherías, guarderías, refaccionarias, abarrotes, farmacias, microcervecería) y demás giros similares de acuerdo al apartado 3 de este artículo..... 10.00 UMA\n2).- Para establecimientos de media ocupación y/o riesgo medio (mercados, restaurantes, licorerías, gimnasios, albercas, vinícolas, cervecerías, salón de eventos hasta 200 asistentes, abarrotes, casas de empeño, bancos) y demás giros similares de acuerdo al apartado 3 de este artículo........................... 20.00 UMA\n3).- Para establecimientos de alta ocupación y/o riesgo alto de hasta\n1,000 ocupantes (discotecas, bares, tiendas departamentales, escuelas, hospitales, salones para eventos, hoteles y moteles, cines, industrias) y demás giros similares de acuerdo al apartado 3 de este artículo........................... 40.00 UMA\n4).- Para establecimientos de alta ocupación y/o riesgo alto mayor a\n1,000 ocupantes (giros de alto riesgo, salones para eventos, macroin- dustria), y demás giros similares de acuerdo al apartado 3 de este artículo........................... 60.00 UMA\nC).- Por otorgamiento de prórroga de hasta 40 días naturales.. 200% del monto referido en inciso B) de esta sección\nD).- Por otorgamiento de prórroga de hasta 60 días naturales. 300% del monto referido en inciso B) de esta sección\n6).- Por copia simple de documentos(por hoja)...... 0.09 UMA\n7).- Por evaluación de requisitos para obtención de registro municipal para desarrollar actividades:\nA).- Como asesor / consultor en materia de protección civil y gestión de riesgos... 25.00 UMA\nB).- Como capacitador en materia de protección civil y gestión de riesgos... 17.00 UMA\nLos servicios a que hacen referencia los incisos 3 y 4, cuando se trate de instituciones públicas, quedarán exentos de pago, siempre y cuando sea en horas hábiles y en las instalaciones de la misma institución. Así como las pláticas informativas que se realicen como medida preventiva a población vulnerable en general.\nXI.- REVISIÓN DE EXPLOSIVOS:\n1).- Revisión de polvorines, instalaciones de compra-venta de explosivos, como requisito para contar con permiso de la Secretaría dela Defensa Nacional(SEDENA).. 94.50 UMA\n2).- Utilización de explosivos en espectáculos de pirotecnia................ 81.00 UMA\nXII.- SANCIONES ECONÓMICAS QUE PODRÁ IMPONER LA COORDINACIÓN\nMUNICIPAL DE PROTECCIÓN CIVIL:\n1).- Por no contar las empresas con el\nPrograma Interno de Protección\nCivil vigente y/o por no aplicarlo....................... De 40.50 a 405.00 UMA\n2).- Por utilizar, vender, almacenar y/o distribuir materiales peligrosos, sin contar con los permisos respectivos..................... De 135.00 a 405.00 UMA\n3).- Por no registrarse las empresas que manejan materiales peligrosos, ante la Coordinación Municipal de\nProtección Civil................ De 40.50 a 135.00 UMA\n4).- Por seguir realizando actividades las empresas que manejan materiales peligrosos, sin renovar el permiso correspondiente.................. De 40.50 a 135.00 UMA\n5).- Por no informar las empresas de cualquier incidente ocurrido, en actividades que involucran materiales peligrosos....................... De 40.50 a 135.00 UMA\n6).- Por almacenar materiales peligrosos en áreas, lugares o ambientes, que no reúnen las condiciones de seguridad necesarias...................... De 135.00 a 405.00 UMA\n7).- Cuando se realice el traslado de materiales peligrosos, dentro de la ciudad, sin observar las medidas de seguridad necesarias........ De 81.00 a 270.00 UMA\n8).- Por almacenar o utilizar materiales peligrosos, sin autorización de la\nCoordinación Municipal de Protección\nCivil.......................... De 81.00 a 270.00 UMA\n9).- Por no registrarse los cuerpos de emergencias, ante la Coordinación\nMunicipal de Protección Civil... De 40.50 a 135.00 UMA\n10).- Por no informar las empresas, a la\nCoordinación Municipal de Protección\nCivil, de las actividades que pudieran constituir algún riesgo.......................... De 40.50 a 135.00 UMA\n11).- Por negar el acceso al inspector de la Coordinación Municipal de\nProtección Civil, donde se realizará una inspección o donde haya ocurrido un siniestro o desastre......... De 135.00 a 405.00 UMA\n12).- Cuando no se hayan ejecutado las medidas de seguridad ordenadas por la Coordinación Municipal de\nProtección Civil, derivadas de una inspección...................... De 40.50 a 405.00 UMA\n13).- Por sobrepasar capacidad permitida y/o poner en riesgo a los ocupantes de un inmueble.................. De 81.00 a 270.00 UMA\n14).- Por realizar eventos masivos sin medidas de seguridad y/o supervisión, de la Coordinación Municipal de\nProtección Civil................. De 81.00 a 135.00 UMA\n15).- Por no activar las empresas, procedimientos de respuesta ante una emergencia que ponga en peligro a trabajadores, usuarios y/o vecinos......................... De 135.00 a 405.00 UMA\n16).- Por infracciones al Reglamento\nMunicipal de Protección Civil, no contempladas en los anteriores incisos.......................... De 40.50 a 675.00 UMA\n17).- Por mantener obstaculizadas rutas de evacuación y/o salidas de emergencia\n(por cada una).................. De 135.00 a 405.00 UMA\n18).- Por retirar sin autorización y/o violar, sellos de clausura o suspensión instalados (por sello)........... 135.00 UMA\n19).- Por no observar medidas de seguridad al realizar transporte de materiales y/o equipos................................ 135.00 UMA\n20).- Por realizar actividades consideradas como riesgo, sin observar medidas de seguridad personal y/o a terceros......................................... 135.00 UMA\n21).- Por realizar obras de edificación o instalación, sin contar con la factibilidad de la Coordinación\nMunicipal de Protección Civil............... 135.00 UMA\n22).- Por no presentar informes solicitados sobre las actividades emprendidas, los asesores registrados..................... 27.00 UMA\n23).- Por seguir ejerciendo funciones de asesor sin contar con el registro respectivo................................... 67.50 UMA\n24).- Por no contar las albercas no particulares, con salvavidas y equipo de emergencia....................... De 67.50 a 135.00 UMA\n25).- Por obstruir caudales, cauces y/o afectar propiedades normales del suelo generando riesgo a la poblacición............................ De 135.00 a 405.00 UMA\n26).- Por negligencia o irresponsabilidad del propietario, poseedor, encargado u ocupante, en el manejo de per- sonas, uso de material o por no haber atendido las recomendaciones de la autoridad correspondiente.. De 135.00 a 405.00 UMA\n27).- Por realizar falsa alarma y/o bromas que conlleve a la alerta y/o acción de las autoridades de protección civil............................ De 13.50 a 135.00 UMA\n28).- Por ayudar o facilitar a los propietarios, poseedores, administradores, representantes, organizadores y demás personas involucradas en violaciones al reglamento Municipal de Protección\nCivil........................... De 135.00 a 675.00 UMA\n29).- Por brindar información falsa, incompleta o errónea que permita incumplir medidas de seguridad y/o protección civil en inmuebles, instalaciones o actividades..................... De 135.00 a 675.00 UMA\n30).- Por infracciones menores en medidas de seguridad y/u observaciones marcadas durante visitas de inspección..... De 10.00 a 40.00 UMA\n31).- Por iniciar operaciones un inmueble o actividad sin cumplir con medidas de seguridad requeridas........ De 100.00 a 1,000.00 UMA\n32).- En caso de reincidencia 200% del monto aplicado en la primera sanción.\nIII.- EVENTOS TURÍSTICOS\nARTÍCULO 18.- Por la recuperación del costo que impacta en el desarrollo de este tipo de eventos, por concepto de recolección de basura, seguridad pública y servicios adicionales, se pagará por el participante en los eventos, siendo responsables solidarios y retenedores los organizadores de los mismos, el servicio, de acuerdo a la siguiente tarifa:\nI.- Eventos con unidades motorizadas, por unidad............................................. 3.38 UMA\nII.- Eventos con unidades no motorizadas, por participante....................................... 0.40 UMA\nCAPÍTULO III\nSERVICIOS QUE PRESTA LA TESORERÍA MUNICIPAL A TRAVÉS DE:\nI.- DIRECCIÓN DE RECAUDACIÓN\nARTÍCULO 19.- Los servicios que preste la Dirección de Recaudación de Rentas Municipales, se regirán bajo la siguiente:\nUNIDAD DE MEDIDA Y ACTUALIZACIÓN\n(UMA)VIGENTE\n1.- CONSTANCIA DE NO ADEUDO:\n1.1) Constancia de No Adeudo de contratistas........ 1.35 UMA\n1.2) Constancia de No Adeudo de alcoholes........... 1.35 UMA\n1.3) Constancia de No Adeudo de multas de tránsito.. 1.35 UMA\n1.4) Constancia de No Adeudo de impuesto predial.... 1.35 UMA\n1.5) Constancia de No Adeudo Municipal.............. 1.35 UMA\n2.- PARA EFECTO DE CUBRIR LOS DERECHOS DE REGISTRO COMO PERITO\nSU REGISTRO COMO PERITOS VALUADORES, ADEMÁS DE CUMPLIR CON\nDE AVALÚOS FISCALES, SE ESTARÁ A LO SIGUIENTE:\n2.1) Registro inicial (alta)...................... 49.95 UMA\n2.2) Revalidación anual dentro de los tres primeros meses del ejercicio fiscal en curso.... 20.80 UMA\n2.3) Multa por revalidación extemporánea adicionalmente al pago del inciso anterior......... 16.20 UMA revalidación anual como perito valuador, el beneficiario al ejercicio fiscal 2025.\n3.- Certificación de Libertad de gravámenes........ 0.50 UMA\nII.- DIRECCIÓN DE COMERCIO, ALCOHOLES Y ESPECTÁCULOS PÚBLICOS\n1.- RECEPCIÓN, ANÁLISIS Y REVISIÓN DE SOLICITUDES, DE EMISIÓN\nDE DOCUMENTOS, PERMISOS Y CERTIFICADOS REFERENTES A\nINSTALACIONES PARA LA VENTA, ALMACENAJE O CONSUMO DE BEBIDAS\nCON GRADUACIÓN ALCOHÓLICA, AMPLIACIÓN, CAMBIO DE GIRO, CAMBIO\nDE PERMISIONARIO, CAMBIO DE DOMICILIO, CAMBIO DE NOMBRE\nCOMERCIAL Y TRAMITACIÓN RELATIVA A LA OPERACIÓN DE GIROS\nDE CERVEZA, VINOS, LICORES, ALCOHOLES Y SIMILARES.\nARTÍCULO 19 BIS.- La recepción, análisis y revisión de solicitudes de permisos nuevos para la operación de establecimientos con venta, almacenaje o consumo de bebidas alcohólicas o alcohol, ampliación de servicios adicionales o de instalaciones, cambio de giro, cambio de permisionario, cambio de nombre o denominación comercial y cambio de domicilio, así como la emisión de permisos\nMunicipio, estarán sujetos a la siguiente:\nUNIDAD DE MEDIDA Y ACTUALIZACIÓN\n(UMA)VIGENTE\n1.- Por la recepción, análisis y evaluación de solicitudes de permisos nuevos, servicios adicionales, ampliación de instalaciones para atención al público, cambio de domicilio, cambio de giro, cambio de permisionario, y cambio de nombre o denominación comercial de establecimientos con permiso, para la venta de bebidas con graduación alcohólica o alcohol................... 54.00 UMA\nA).- Por el costo de inspecciones para permisos nuevos o cambios a los permisos ya autorizados:\na).- 1ra. Inspección......................... 33.75 UMA\nb).- 2da. Inspección......................... 40.00 UMA\nc).- 3ra. Inspección......................... 45.00 UMA\nd).- 4ta. Inspección......................... 50.00 UMA\nB).- Emisión de copias simples..................... 0.09 UMA\n2.- Recepción, análisis y evaluación de solicitudes de modificaciones o ajuste de horario a establecimientos donde se vendan, consuman o almacenen bebidas con graduación alcohólica o alcohol.............................. 25.65 UMA\n3.- Recepción, análisis y evaluación de bebidas con graduación alcohólica en ferias, verbenas o diversiones análogas o cualquiera otra de carácter transitorio o eventual............ 9.45 UMA\n4.- Recepción, análisis y evaluación de bebidas con graduación alcohólica en eventos masivos o en parques deportivos.................... 9.45 UMA\n5.- Autorización de carácter transitorio, de modificación o ajuste de horario:\nI.- De lunes a miércoles, solo se autorizará una hora........................... 67.50 UMA\nII.- De jueves a domingo y días festivos solo se autorizarán hasta dos horas: a.- Primera hora.............................. 81.00 UMA b.- Segunda hora............................. 135.00 UMA para el desarrollo de sus eventos durante el mes en curso, podrán obtener un 50% de descuento en la tarifa establecida a partir de la adquisición de cuatro horas adicionales, siempre y cuando sean solicitados los primeros 3 días hábiles de cada mes y cumplan con el pago en una sola exhibición. Solo se autorizarán un máximo de dos horas por evento para los días que haya sido adquirido el derecho. Los días festivos serán aquellos que la Ley en la materia señale.\nEntendiéndose los días señalados en los paquetes como aquellos en los que se dará inicio el evento.\nEl presente derecho se autorizará previo análisis efectuado por la\nDirección de Comercio, Alcoholes y Espectáculos Públicos.\n6.- Autorización respecto al aviso de no\nInconveniente de intención de ceder los derechos de un permiso........................... 20.25 UMA\n7.- Derechos por la expedición del permiso y autorización de venta de bebidas con graduación alcohólica, de carácter eventual o transitorio:\na).- Ferias, verbenas, festejos, diversiones análogas y otros, por espacio o local autorizado, por día: a.1).- De 1 a 500 personas por barra\n3x3 m................................. 40.50 UMA a.1.1) metro cuadrado adicional de carpa 3x3 metros............ 13.50 UMA a.2).- De 501 a 1,000 personas por barra\n3x3 m................................. 67.50 UMA a.2.1) metro cuadrado adicional de carpa 3x3 metros.......... 13.50 UMA a.3).- De 1,001 a 2,500 personas por barra 3x3 m.......................... 94.50 UMA a.3.1) metro cuadrado adicional de carpa 3x3 metros............ 13.50 UMA a.4).- De 2,501 a 5,000 personas por barra 3x3 m......................... 121.50 UMA a.4.1) metro cuadrado adicional de carpa 3x3 metros........... 13.50 UMA a.5).- De 5,001 a 7,500 personas por barra 3x3 m.......................... 202.50 UMA a.5.1) metro cuadrado adicional de carpa 3x3 metros............ 13.50 UMA a.6).- De 7,501 a 10,000 personas por barra 3x3 m........................ 270.00 UMA a.6.1) metro cuadrado adicional de carpa 3x3 metros............ 13.50 UMA a.7).- De 10,001 a 15,000 personas por barra 3x3 m......................... 337.50 UMA a.7.1) metro cuadrado adicional de carpa 3x3 metros............ 13.50 UMA a.8).- De 15,001 personas en adelante por barra 3x3 m...................... 472.50 UMA a.8.1) metro cuadrado adicional de carpa 3x3 metros............ 13.50 UMA\nb).- Tratándose de eventos organizados en que participen deportistas, músicos, actores y grupos de danza no profesionales, así como, los realizados por instituciones educativas, dependencias oficiales, organizaciones no gubernamentales con registro ante institución oficial, asociaciones civiles y organizaciones que no perciben fines de lucro pagarán por barra 3x3 m²................................. 40.50 UMA\nc).- En parques deportivos, por espacio o local autorizado, un 20% sobre el monto en UMA que corresponda según clasificación establecida en el punto 11 de este artículo, para la expedición de permisos.\nd).- Otros por local, un 20% sobre el monto en UMA que corresponda según clasificación establecida en el punto 11 de este artículo, para la expedición de permisos.\ne).- Permiso Transitorio, para llevar a cabo la venta, degustación y consumo de vinos de mesa nacional por día..................... 27.00 UMA e.1).- Permiso Transitorio para la venta y/o consumo de vino de mesa nacional en espectáculos públicos por barra, por día............................... 20.25 UMA e.2).- Metro cuadrado adicional de barra de 3x3 metros para venta, degustación y consumo de vinos de mesa nacionales, por día............................... 13.50 UMA\nf).- Permiso Transitorio, para llevar a cabo la venta, degustación y consumo de vinos importados(locales comerciales), por día..... 33.75 UMA f.1).- Metro cuadrado adicional de barra de 3x3 metros para venta, degustación y consumo de vinos importados\n(locales comerciales), por día........ 13.50 UMA\ng).- Permiso transitorio, para la venta, degustación y consumo de licores importados(locales comerciales), por día..... 47.25 UMA g.1).- Permiso transitorio para la venta, degustación y consumo de bebidas con graduación alcohólica en eventos y/o espectáculos públicos por barra 3x1 m por día.............. 121.50 UMA g.2).- Permiso transitorio, para llevar a cabo la venta, degustación y consumo de licores regionales, por día............................... 23.62 UMA\nh).- Permiso por espacio o local, autorizado por día, dentro de la zona de festejos públicos municipales, cuando éstos sean organizados por la Administración\nPública Centralizada, de conformidad a la clasificación de zonas y con base en\nla UMA ACTUALIZADA\n1.- Cerveza y Vino\n1.1.- Zona A............................. 44.55 UMA\n1.2.- Zona B............................ 29.70 UMA\n1.3.- Zona C............................. 20.25 UMA\n1.4.- Zona D............................. 13.50 UMA\n2.- Cerveza y Licor\n2.1.- Zona A.............................. 98.55 UMA\n2.2.- Zona B.............................. 91.80 UMA\n2.3.- Zona C.............................. 68.85 UMA\n2.4.- Zona D.............................. 40.50 UMA\ni).- Cuando la organización del festejo recaiga en Entidades de la\nAdministración Pública Descentralizada, el permiso general otorgado a estas, para su uso de conformidad a las disposiciones legales que le sean aplicables.................................... 0.00 UMA\nLa clasificación de zonas y puestos, así como el plano de su ubicación, dentro de la zona destinada a la realización del festejo de que se trate, deberá ser emitido por el Presidente Municipal, cuando su organización esté a cargo del\nGobierno Central, o del Director de que se trate cuando su organización esté a cargo del Órgano Descentralizado de la Organización Municipal, y deberá ser publicado en la página electrónica del Gobierno Municipal previo al inicio de la autorización de los permisos.\nj).- Permiso transitorio para venta, degustación y consumo de cerveza artesanal, en eventos masivos por día: j.1).- De 1 a 500 personas por barra\n3x3 m................................. 6.75 UMA j.1.1) metro cuadrado adicional de carpa 3x3 metros............... 2.70 UMA j.2).- De 501 a 1,000 personas por barra\n3x3 m................................ 13.50 UMA j.2.1) metro cuadrado adicional de carpa 3x3 metros............... 2.70 UMA j.3).- De 1,001 a 2,500 personas por barra\n3x3 m................................ 20.25 UMA j.3.1) metro cuadrado adicional de carpa 3x3 metros.............. 2.70 UMA j.4).- De 2,501 a 5,000 personas por barra\n3x3 m................................ 27.00 UMA j.4.1) metro cuadrado adicional de carpa 3x3 metros.............. 2.70 UMA j.5).- De 5,001 a 7,500 personas por barra\n3x3 m................................ 33.75 UMA j.5.1) metro cuadrado adicional de carpa 3x3 metros.............. 2.70 UMA j.6).- De 7,501 a 10,000 personas por barra 3x3 m.......................... 40.50 UMA j.6.1) metro cuadrado adicional de carpa 3x3 metros.............. 2.70 UMA j.7).- De 10,001 a 15,000 personas por barra 3x3 m......................... 47.25 UMA j.7.1) metro cuadrado adicional de carpa 3x3 metros.............. 2.70 UMA j.8).- De 15,001 personas en adelante por barra 3x3 m.......................... 54.00 UMA j.8.1) metro cuadrado adicional de carpa 3x3 metros............. 2.70 UMA\n8.- Derechos por revalidación anual de permisos y servicios adicionales.\na).- Tienda de abarrotes........................... 50.00 UMA\nb).- Billares...................................... 170.00 UMA\nc).- Loncherías, fondas y coctelerías: c.1.- De 1 a 199 personas..................... 85.00 UMA c.2.- De 200 personas en adelante............ 143.00 UMA\nd).- Restaurantes: d.1.- De 1 a 199 personas.................... 140.00 UMA d.2.- De 200 personas en adelante............ 175.00 UMA\ne).- Restaurant-bar: e.1.- De 1 a 199 personas.................... 180.00 UMA e.2.- De 200 personas en adelante............ 235.00 UMA\nf).- Agencias, subagencias o depósitos............ 200.00 UMA\ng).- Licorerías................................... 200.00 UMA\nh).- Bar turístico: h.1.- De 1 a 199 personas.................... 345.00 UMA h.2.- De 200 personas en adelante............ 400.00 UMA\ni).- Cafés cantantes, cabarets y discotecas: i.1.- De 1 a 199 personas.................... 345.00 UMA i.2.- De 200 a 799 personas.................. 400.00 UMA i.3.- De 800 personas en adelante............ 600.00 UMA\nj).- Supermercados y tiendas departamentales...... 350.00 UMA\nk).- Bodegas o almacenes.......................... 300.00 UMA\nl).- Salón social con consumo de alcohol.......... 135.00 UMA\nm).- Mercados y autoservicios con horario hasta las 22:00 horas........................ 250.00 UMA\nn).- Mercados y autoservicios con horario hasta las 24:00 horas.............................. 300.00 UMA ñ).- Terrazas..................................... 200.00 UMA\no).- Expendio de cerveza o vinos.................. 150.00 UMA\np).- Hoteles: p.1.- De 1 a 50 habitaciones................. 250.00 UMA p.2.- De 51 habitaciones en adelante......... 400.00 UMA\nq).- Centros sociales y deportivos................ 100.00 UMA\nr).- Balnearios................................... 200.00 UMA\ns).- Vinaterías................................... 200.00 UMA s.1) Vinaterías y establecimientos que almacenan y venden exclusivamente vinos de producción nacional con consumo de alimentos..................... 81.00 UMA\nt).- Vitivinícolas y establecimientos que producen y / o almacenan y venden exclusivamente vinos de mesa propios, de producción regional, en envase cerrado, abierto o al copeo como actividad principal. Pudiendo ser vinícola, bodega o mostrador comercial:\na).- De 1.00 a 9,000.00 litros producidos anuales................................. 140.00 UMA\nb).- De 9,000.01 a 45,000.00 litros producidos anuales................................. 270.00 UMA\nc).- De 45,000.01 a 450,000.00 litros producidos anuales................................. 540.00 UMA\nd).- Los establecimientos que cuenten con giro adicional, también pagarán revalidación de estos.\nu).- Otros......................................... 87.75 UMA\nv).- Cerveza Artesanal............................. 60.00 UMA\nw).- Microcervecería.............................. 60.00 UMA\nx).- Local comercial para la venta de comida rápida, que su área de operación no exceda de\n5x5 metros (solo cerveza y vino), como cafeterías, taquerías, mariscos y similares......... 60.00 UMA\ny).- Destilados.................................... 60.00 UMA\nz).- Unidad deportiva no administrada por INMUDERE con venta exclusiva de cerveza con una capacidad hasta de 200 personas (solo para juegos de adultos)........................... 162.00 UMA z.1).- Unidad deportiva no administrada por INMUDERE con venta exclusiva de cerveza con una capacidad de 201 a 500 personas (solo para juegos de adultos)............... 216.00 UMA z.2).- Unidad deportiva no administrada por INMUDERE con venta exclusiva de cerveza con una capacidad de 501 personas en adelante (solo para juegos de adultos).............. 270.00 UMA aa).- La falta de revalidación oportuna de los permisos o fuera de los plazos establecidos conforme a la ley de la materia causará una sanción económica hasta del\n50% del importe de la propia revalidación, independientemente de las sanciones administrativas a que hubiese lugar. No procederá sanción alguna cuando previamente se haya otorgado prórroga para la revalidación de permisos por parte de la depen- dencia competente. Las prórrogas o plazos otorgados serán por única vez y no podrán exceder de 90 días naturales.\n9.- Recepción, análisis y evaluación de solicitud de plazo, para revalidación de permisos de alcohol........................................ 16.20 UMA\n10.- Evaluación y dictamen sobre la procedencia de ampliación al plazo para inicio de operaciones....................................... 10.80 UMA\n11.- Por la expedición de permisos nuevos, y de cambios a permisos otorgados, una vez que han sido autorizados por el Ayuntamiento, se causarán los siguientes derechos:\na).- Tienda de abarrotes....................... 1,899.45 UMA\nb).- Billares.................................. 3,936.60 UMA\nc).- Loncherías, fondas y coctelerías.......... 2,760.75 UMA\nd).- Restaurantes.............................. 3,545.10 UMA\ne).- Restaurant-bar............................ 6,758.10 UMA\nf).- Agencias, subagencias o depósitos......... 4,490.10 UMA\ng).- Licorerías................................ 4,926.15 UMA\nh).- Bar turístico y cantinas.................. 8,035.20 UMA\ni).- Café cantante y cabarets.................. 9,817.20 UMA\nj).- Supermercados y tiendas departamentales... 6,288.30 UMA\nk).- Bodegas o almacenes....................... 4,722.30 UMA\nl).- Mercados y autoservicios con horario hasta las 22:00 horas..................... 3,580.20 UMA\nm).- Mercados y autoservicios con horario hasta las 24:00 horas..................... 4,228.20 UMA\nn).- Expendio de cerveza y vinos............... 5,769.90 UMA ñ).- Hoteles................................... 8,464.50 UMA\no).- Centros sociales y deportivos............. 2,643.30 UMA\np).- Balnearios................................ 2,970.00 UMA\nq).- Salón social con consumo de alcohol....... 2,970.00 UMA\nr).- Vinaterías................................ 3,685.50 UMA r.1) Vinaterías y establecimientos que almacenan y venden exclusivamente vinos de producción nacional con consumo de alimentos..................... 0.00 UMA\ns).- Vitivinícolas y establecimientos que producen (siembra de uva y produzca vino) y / o almacenan y venden exclusivamente vinos de mesa propios, de producción regional, en envase cerrado, abierto o al copeo como actividad principal.\nPudiendo ser vinícola, bodega o mostrador comercial................................... 500.00 UMA s.1.).- Giros adicionales: s.1.1).- Restaurante.............. 1,181.70 UMA s.1.2).- Salón social............... 337.50 UMA\nt).- Establecimientos de Cerveza Artesanal....... 500.00 UMA\nu).- Microcervecería............................. 500.00 UMA\nv).- Local comercial para la venta de comida rápida, que su área de operación no exceda de\n5x5 metros (solo cerveza y vino), como cafeterías, taquerías, mariscos y similares....... 500.00 UMA\nw).- Destilados.................................. 500.00 UMA\nx).- Unidad deportiva no administrada por INMUDERE con venta exclusiva de cerveza con una capacidad hasta de 200 personas (solo para juegos de adultos).......................... 810.00 UMA x.1).- Unidad deportiva no administrada por INMUDERE con venta exclusiva de cerveza con una capacidad de 201 a 500 personas\n(solo para juegos de adultos)........ 945.00 UMA x.2).- Unidad deportiva no administrada por INMUDERE con venta exclusiva de cerveza con una capacidad de 501 personas en adelante (solo para juegos de adultos)............ 1,215.00 UMA\ny).- Servicios adicionales:\n1).- Música grabada, por semana autorizada o fracción................... 20.25 UMA\n2).- Música en vivo, por semana autorizada o fracción................... 45.90 UMA\n3).- Baile, por semana autorizada o fracción.............................. 67.50 UMA\n4).- Espectáculo artístico, por semana autorizada o fracción............ 94.50 UMA\n5).- Mesa de billar por semana............... 20.25 UMA\nz).- Otros Servicios adicionales:\n1).- Música grabada, por incorporarlos al permiso............................. 297.00 UMA\n2).- Música en vivo, por incorporarlos al permiso de los giros:\n2.1).- Lonchería....................... 371.25 UMA\n2.2).- Restaurante..................... 371.25 UMA\n3).- Baile, por incorporarlos al permiso de los giros:\n3.1).- Lonchería....................... 472.50 UMA\n3.2).- Restaurante..................... 472.50 UMA\n4).- Espectáculo artístico, por incorporarlos al permiso de los giros.\n4.1).- Restaurant-bar.................. 506.25 UMA\n4.2).- Bar Turístico................... 506.25 UMA\n5).- Mesa de billar por incorporarlos al permiso de los giros en envase abierto................................. 27.00 UMA aa).- Cervecería artesanal, establecimiento que produce, almacena, distribuye y vende en envase abierto y/o cerrado cerveza elaborada de forma manual hasta su embotellamiento.................... 405.00 UMA ab).- Microcervecería, establecimiento independiente que produce y almacena para su dis- tribución y venta, cerveza artesanal, de producción propia, así como un diverso productor de cerveza artesanal, siempre que el capital, para realizar tal actividad no intervenga con una inversión mayor al 25% de una persona física o moral dedicada a la industria de la producción cervecera, de degustación con música en vivo o grabada, área en el interior o exterior para dar servicios y cuyo volumen de producción de cerveza artesanal no exceda los cinco millones de hectolitros anuales............. 405.00 UMA ac).- Barras móviles............................. 270.00 UMA ad).- Barras para evento en salón social........... 81.00 UMA ae).- Autorización de consumo de bebidas con graduación alcohólica en salón social........ 17.55 UMA af).- Terraza. Para adicionar este servicio adicional el interesado deberá pagar el 20% del valor del permiso ya autorizado. ag).- Los giros con venta de bebidas alcohólicas en envase cerrado, podrán solicitar giro adicional de degustación, únicamente en bebidas como tequila, mezcal, cerveza artesanal y vino mexicano................... 250.00 UMA\n12.- Por la expedición de autorización de cambios o modificación al permiso, pagarán los siguientes Derechos:\na).- Por cambio de domicilio dentro del\nMunicipio, se cobrará 30% sobre el valor del permiso nuevo.\nb).- Por cambio de permisionario se cobrará 50% sobre el valor del permiso nuevo. b.1).- Cuando se trate de un cambio a favor de viuda o viudo, se cobrará el 25% sobre el valor del permiso nuevo. b.2).- Cuando se trate de un cambio a favor de viuda o viudo, y además este cuente con más de 60 años, se cobrará el 12.5% sobre el valor del permiso nuevo.\nEstos subincisos b.1 y b.2, aplicarán solamente a los giros de abarrotes, autoservicio, fonda, lonchería, cócteles y restaurantes, de acuerdo a los artículos\n19 BIS y 20 del Reglamento de Alcoholes\nMunicipal.\nc).- Por cambio de nombre comercial, se cobrará\n5% sobre el valor del permiso nuevo.\nd).- Por cambio de giro comercial de manera descendente, se cobrará 10% sobre el valor del permiso nuevo del giro que prevalece.\ne).- Por cambio de giro comercial de manera ascendente, se cobrará la diferencia entre las tarifas de los permisos nuevos de los giros que se modifican.\nf).- Por autorización de ampliación de instalaciones, para atención al público en el mismo local (no incluye terrazas), se cobrará 10% sobre el valor del permiso nuevo.\ng).- Por autorización de contrato de comodato y reactivación de permiso................... 150.00 UMA\n2.- RECEPCIÓN, ANÁLISIS Y REVISIÓN DE DOCUMENTOS, Y POR LA\nAUTORIZACIÓN PARA LA INSTALACIÓN Y EXPLOTACIÓN DE APARATOS\nDE SONIDO, ELECTRÓNICOS, MECÁNICOS, ELECTROMECÁNICOS,\nVIDEOJUEGOS Y SIMILARES.\nARTÍCULO 20.- La recepción, análisis y revisión de solicitudes de permisos para la instalación y explotación de aparatos mecánicos, electrónicos, electromecánicos, videojuegos, de sonido, cafés internet y similares; cambio de domicilio, así como la emisión de permisos, de revalidaciones, registro y ampliación similares extienda el Municipio, estarán sujetos a la siguiente:\nUNIDAD DE MEDIDA Y ACTUALIZACIÓN\n(UMA)VIGENTE\n1.- Recepción, análisis y revisión de solicitudes de permisos para la instalación y control de la explotación de aparatos mecánicos, electrónicos, electromecánicos, musicales, videojuegos, café internet y similares:\na).- Mecánicos, electrónicos, electromecánicos, musicales, videojuegos y similares.................................... 13.50 UMA\nb).- Cafés Internet................................ 1.35 UMA\n2.- Recepción, análisis y revisión de solicitudes de cambio de domicilio........................... 13.50 UMA\n3.- Recepción, análisis y revisión de solicitudes correspondientes, para la instalación u operación de aparatos mecánicos, electrónicos, electromecánicos, musicales, videojuegos y otros, en ferias, verbenas o diversiones análogas de carácter transitorio...... 13.50 UMA\n4.- Por el permiso ya sea en ruta o fijo como propietario, comisionista, arrendador, asociado o cualquier otra figura o denominación para la explotación de aparatos mecánicos, electrónicos, electromecánicos, musicales, videojuegos, café internet y otros:\n4.1.- Permisionario fijo.......................... 94.50 UMA\n4.2.- Permisionario ruta.......................... 94.50 UMA\n4.3.- Permiso para café internet.................. 20.25 UMA\n4.4.- Permisionario de máquinas mecánicas expendedoras de dulces y juguetes........... 27.00 UMA\n4.5.- Permisionarios de máquinas electromecánicas expendedoras de refrescos y golosinas....................... 94.50 UMA\n5.- Por las autorizaciones que expida el\nMunicipio, respecto de aparatos a que se refiere este artículo:\n5.1.- Por aparato registrado...................... 13.50 UMA\n5.2.- Por cambio de domicilio..................... 13.50 UMA\n5.3.- Incremento, por aparato..................... 13.50 UMA\n5.4.- Para café internet por el registro de las computadoras: a.- Hasta 10 aparatos....................... 13.50 UMA b.- De 11 a 20 aparatos..................... 27.00 UMA c.- Más de 20 aparatos...................... 40.50 UMA\n5.5.- Por revalidación anual, por aparato de video juego.................................. 4.05 UMA\n5.6.- Por aparato registrado de máquinas mecánicas expendedoras de dulces y juguetes..................................... 6.75 UMA\n5.7.- Por aparato registrado de máquinas electromecánicas expendedoras de refrescos y golosinas....................... 20.25 UMA\n5.8.- Por revalidación anual por aparato registrado de máquinas mecánicas expendedoras de dulces y juguetes............ 4.05 UMA\n5.9.- Por revalidación anual de máquinas electromecánicas expendedoras de refrescos y golosinas....................... 33.75 UMA\n5.10.-Por revalidación anual del permiso para la explotación de cafés internet........... 27.00 UMA\n6.- Emisión de copias simples.......................... 0.09 UMA\n3.- CENTROS DE APUESTAS, APUESTAS REMOTAS, SALAS DE SORTEOS DE\nNÚMEROS Y/O CASINOS.\nARTÍCULO 21.- Las máquinas de azar o con combinaciones de azar y destreza, con premios en efectivo o en especie que cuenten con autorización de la Secretaría de Gobernación, pagarán los derechos de instalación o explotación conforme a la siguiente tabla:\na).- Dictamen de opinión favorable o anuencia, por establecimiento en apertura................................... 67,500.00 UMA\nb).- Permiso por horario ampliado anual por establecimiento............................ 2,025.00 UMA\nc).- Cambio de domicilio............................ 2,025.00 UMA\nd).- Cambio de propietario.......................... 2,025.00 UMA\ne).- Revalidación anual por establecimiento se realizará durante los meses de enero a marzo de cada año................................... 13,500.00 UMA en la presente Ley causará un cobro del 3% mensual, adicional al cobro de la revalidación.\nf).- Aportación para programas preventivos para la ludopatía.............................. 2,025.00 UMA\n4.- RECEPCIÓN Y ANÁLISIS DE DOCUMENTOS Y EXPEDICIÓN DE PERMISOS\nDE DIVERSIÓN.\nARTÍCULO 22.- Para la realización de eventos, espectáculos públicos y de diversión, deberá entregarse la documentación correspondientes, previo el pago de los derechos que se causen de acuerdo a la siguiente:\nUNIDAD DE MEDIDA Y ACTUALIZACIÓN\n(UMA)VIGENTE\n1.- Circos:\na).- Por Delegación Municipal...................... 20.25 UMA\nPOR DÍA\nb).- Zona Urbana Ensenada.......................... 27.00 UMA\nPOR DÍA\n2.- Juegos Mecánicos:\na).- Zona Urbana Ensenada.......................... 20.25 UMA\nPOR DÍA\nb).- Por Delegación Municipal...................... 13.50 UMA\nPOR DÍA\nc).- Cuando la organización del festejo, recaiga en la Administración Pública\nCentralizada, en zona de festejos, públicos municipales......................... 135.00 UMA\nPOR DÍA\nd).- Cuando la organización del festejo recaiga en Entidades de la Administración Pública\nDescentralizada, el permiso general otorgado a estas, para su uso de conformidad a las disposiciones legales que le sean aplicables.................................... 27.00 UMA\n3.- Cierre de Calle:\na).- Eventos públicos.............................. 40.50 UMA\nPOR DÍA\nPOR CADA CALLE\nb).- Eventos privados.............................. 54.00 UMA\nPOR DÍA\nPOR CADA CALLE\n4.- Desfiles promocionales............................. 33.75 UMA\nPOR EVENTO\n5.- Desfiles relativos a centros educativos por exposición de presentaciones temáticas y alusivas a sus actividades académicas............... EXENTO\n6.- Exhibición de modas y otros........................ 71.00 UMA\nPOR EVENTO\n6.1.- Caravanas.................................... 27.00 UMA\nPOR EVENTO\n7.- Funciones:\na).- Box a.1) Profesional.............................. 81.00 UMA\nPOR EVENTO a.2) Amateur.................................. 40.50 UMA\nPOR EVENTO\nb).- Lucha libre b.1).-Profesional............................. 81.00 UMA\nPOR EVENTO b.2).-Amateur................................. 40.50 UMA\nPOR EVENTO\nc).- Obras de teatro c.1) Locales no profesionales................. 27.00 UMA\nPOR DÍA c.2) Locales que pertenezcan al padrón de promotores culturales locales de\nEnsenada, del Instituto Municipal de Cultura y Desarrollo Humano........ 13.50 UMA c.3) Artistas profesionales................... 67.50 UMA\nPOR DÍA\nd).- Cine.......................................... 13.50 UMA\nPOR DÍA\ne).- Otros......................................... 13.50 UMA\nPOR DÍA\nf).- Autocinemas: f.1).- De 1 a 50 vehículos..................... 6.75 UMA\nPOR DÍA f.2).- De 51 a 100 vehículos.................. 13.50 UMA\nPOR DÍA f.3).- De 101 vehículos en adelante........... 20.25 UMA\nPOR DÍA\n8.- Espectáculos Masivos:\na).- Corrida de toros............................. 202.50 UMA\nPOR EVENTO\nb).- Presentación de entretenedores y comediantes: b.1).- De 1 a 250 personas.................... 33.75 UMA\nPOR DÍA b.2).- De 251 en adelante..................... 67.50 UMA\nPOR DÍA\nc).- Bailes en salones: c.1).- Artistas profesionales................. 67.50 UMA\nPOR DÍA c.2).- Artistas locales o no profesionales.... 33.75 UMA\nPOR DÍA\nd).- Conciertos con presentación de artistas profesionales: d.1).- De 1 a 500 personas................... 250.00 UMA\nPOR DÍA d.2).- De 501 a 1,500 personas............... 500.00 UMA\nPOR DÍA d.3).- De 1,501 a 4,000 personas............. 750.00 UMA\nPOR DÍA d.4).- De 4,001 a 6,000 personas........... 1,000.00 UMA\nPOR DÍA d.5).- De 6,001 personas en adelante....... 1,500.00 UMA\nPOR DÍA\ne).- Conciertos con músicos locales no profesionales: e.1).- De 1 a 500 personas.................... 27.00 UMA\nPOR DÍA e.2).- De 501 personas en adelante........... 54.00 UMA\nPOR DÍA\nf).- Carreras de automóviles, motocicletas y vehículos con motor: f.1).- Arrancones............................ 202.50 UMA\nPOR EVENTO f.2).- Carreras fuera de camino tipo off-road locales..................... 101.25 UMA\nPOR EVENTO f.3).- Paseos o recorridos de exhibición...... 67.50 UMA\nPOR EVENTO f.4).- Carrera de exhibición y otros.......... 40.50 UMA\nPOR EVENTO\nNota: Los eventos de arrancones del inciso f), no podrán zona turística y frente al mar, así como en zonas habitacionales.\ng).- Carreras atléticas, ciclistas y paseo sin fines de lucro............................ 27.00 UMA\nPOR DÍA g.1).- Carreras atléticas, ciclistas y paseo con fines de lucro..................... 54.00 UMA\nPOR DÍA\nh).- Charreada, Rodeo, Jaripeo: h.1).- Zona urbana Ensenada................... 67.50 UMA\nPOR DÍA h.2).- En Delegaciones Municipales............ 40.50 UMA\nPOR DÍA\ni).- Peleas de gallos (con cruce de apuestas)..... 250.00 UMA\nPOR DÍA\nj).- Exhibición de gallos, peleas de casteo\n(sin apuesta)................................ 150.00 UMA\nPOR DÍA\nk).- Tlacuachadas, carreras parejeras con apuestas..................................... 200.00 UMA\nPOR DÍA\nl).- Tlacuachadas, carreras parejeras sin apuestas..................................... 100.00 UMA\nPOR DÍA\nm).- Festejos, ferias populares.................... 67.50 UMA\nPOR DÍA\nn).- Festejos, ferias populares en\nDelegaciones Municipales...................... 40.50 UMA\nPOR DÍA ñ).- Otros......................................... 30.00 UMA\nPOR EVENTO\no).- Tratándose de expo, bazar, feria o festival, inauguraciones y aniversarios:\n1).- Realizado por Organismos no Lucrativos... 54.00 UMA\nPOR DÍA\n2).- Realizado por Organismos Lucrativos..... 121.50 UMA\nPOR DÍA\n3).- Realizado en la vía pública.\n3.1.- Por evento......................... 54.00 UMA\n3.2.- Por carpa de 3x3 metros............. 7.36 UMA\n3.3.- Por metro adicional de carpa 3x3 metros.............................. 1.35 UMA\n4).- Realizado en predios privados.\n4.1.- Por evento de 1 a 200 personas..... 13.50 UMA\n4.2.- Por evento de 201 a 400 personas... 27.00 UMA\n4.3.- Por evento de 401 a 800 personas... 40.50 UMA\n4.4.- Por evento de 801 a 1,500 personas.. 67.50 UMA\n4.5.- Por evento de 1,500 en adelante.... 135.00 UMA\n4.6.- Por carpa de 3x3 metros en predios privados............................ 7.36 UMA\n4.7.- Por metro adicional de carpa en predios privados.................... 1.35 UMA\n5) Inauguraciones y aniversarios en establecimientos comerciales................................ 27.00 UMA\np).- Tratándose de espectáculos realizados por\nOrganismos no lucrativos que brinden servicios y asistencia médica de manera gratuita a enfermos que padezcan cáncer en etapa terminal, debidamente registrados ante institución oficial que para tales efectos señale la Ley de la materia. No aplica para conciertos con artistas profesionales........................ 30.00 UMA\nq).- Los eventos relacionados y/o enfocados a profesionistas y estudiantes.................. 13.50 UMA\nPOR EVENTO q.1) Taller de capacitación con fines de lucro.......................... 13.50 UMA\nPOR EVENTO q.2) Taller de capacitación sin fines de lucro............................ 6.75 UMA\nPOR EVENTO\nr).- Congresos con fines de lucro.................. 13.50 UMA\nPOR EVENTO\ns).- Congresos sin fines de lucro................... 6.75 UMA\nPOR EVENTO\nt).- Simposium con fines de lucro.................. 13.50 UMA\nPOR EVENTO\nu).- Simposium sin fines de lucro................... 6.75 UMA\nPOR EVENTO\nv).- Cursos de capacitación con fines de lucro..... 13.50 UMA\nPOR EVENTO\nw).- Cursos de capacitación sin fines de lucro.... 6.75 UMA\nPOR EVENTO\nx).- Conferencias con fines de lucro............... 13.50 UMA\nPOR EVENTO\ny).- Conferencias sin fines de lucro................ 6.75 UMA\nPOR EVENTO\nz).- Eventos realizados por ligas deportivas locales....................................... 13.50 UMA\nPOR DÍA aa).- Recepción análisis y evaluación de solicitudes de eventos y espectáculos públicos............. 6.00 UMA aa.1).- Inspección de factibilidad para eventos y espectáculos públicos................. 27.00 UMA aa.2).- En general por la recepción y análisis de documentos de espectáculos y eventos de carácter urgente (en menos de 72 horas), se cobrará el doble de la tarifa ordinaria. aa.3).- Filmaciones y/o grabaciones de películas y/o cortometrajes.................... 13.50 UMA aa.4).- Cena maridaje......................... 30.00 UMA aa.5).- Emisión de oficios para eventos y / o espectáculos públicos por 2da ocasión... 2.00 UMA aa.6).- Derechos por la prestación de servicios en eventos sociales como organizadores de eventos............................ 75.00 UMA ab).- Empresas de venta de boletaje electrónico para eventos sociales, espectáculos públicos y eventos masivos: ab.1) Registro de empresas con venta de boletaje electrónico para eventos sociales, espectáculos públicos y eventos masivos.............................. 1,000.00 UMA ab.2) Revalidación anual de empresas con venta de boletaje electrónico para eventos sociales, espectáculos públicos y eventos masivos................................ 500.00 UMA funcionamiento de establecimientos para eventos sociales o fiestas, deberán iniciar los trámites correspondientes conforme al reglamento de la materia, en la Dirección de Comercio, Alcoholes y Espectáculos Públicos, y una vez dictaminado el cumplimiento a cabalidad de los requisitos y condiciones exigidos para tal efecto, se deberá efectuar el pago de derechos que se causen conforme a lo siguiente:\nI.- Inspección de factibilidad........................ 27.00 UMA\nII.- Emisión de copia simple.......................... 0.09 UMA\nIII.- Por la recepción, análisis y evaluación de solicitudes de permisos nuevos, servicios adicionales, cambio de domicilio, cambio de permisionario y campermiso vigente.................................. 54.00 UMA\nIV.- Permiso transitorio.......................... 20% del valor del permiso\nV.- Apertura:\nA).- En zona habitacional:\n1.- Establecimiento en área abierta, con horario de 11:00 a 22:00 horas:\na).- Con cupo de 1 a 100 personas....... 540.00 UMA\nb).- Con cupo de 101 a 200 personas..... 675.00 UMA\nc).- Con cupo de 201 a 300 personas..... 810.00 UMA\nd).- Con cupo de 301 a 400 personas..... 945.00 UMA\ne).- Con cupo de 401 a 600 personas... 1,080.00 UMA\nf).- Con cupo de 601 a 800 personas... 1,215.00 UMA\ng).- Con cupo de más de 800 personas... 1,350.00 UMA\n2.- Establecimiento mixto, de 11:00 a 22:00 horas en área abierta y hasta las\n24:00 horas en área cerrada:\na).- Con cupo de 1 a 100 personas....... 810.00 UMA\nb).- Con cupo de 101 a 200 personas..... 945.00 UMA\nc).- Con cupo de 201 a 300 personas... 1,080.00 UMA\nd).- Con cupo de 301 a 400 personas... 1,215.00 UMA\ne).- Con cupo de 401 a 600 personas... 1,350.00 UMA\nf).- Con cupo de 601 a 800 personas... 1,485.00 UMA\ng).- Con cupo de más de 800 personas.. 1,620.00 UMA\n3.- Establecimiento en área cerrada, de\n11:00 a 24:00 horas:\na).- Con cupo de 1 a 100 personas....... 405.00 UMA\nb).- Con cupo de 101 a 200 personas..... 540.00 UMA\nc).- Con cupo de 201 a 300 personas..... 675.00 UMA\nd).- Con cupo de 301 a 400 personas..... 810.00 UMA\ne).- Con cupo de 401 a 600 personas..... 945.00 UMA\nf).- Con cupo de 601 a 800 personas... 1,080.00 UMA\ng).- Con cupo de más de 800 personas... 1,350.00 UMA\n4.- Piñatero en zona habitacional de 11:00 a 20:00 horas:\na).- Con cupo de 1 a 100 personas....... 270.00 UMA\nb).- Con cupo de 101 a 200 personas..... 405.00 UMA\nc).- Con cupo de 201 a 300 personas..... 540.00 UMA\nd).- Con cupo de 301 a 400 personas..... 675.00 UMA\ne).- Con cupo de 401 a 600 personas..... 810.00 UMA\nf).- Con cupo de 601 a 800 personas..... 945.00 UMA\ng).- Con cupo de más de 800 personas... 1,215.00 UMA\nB).- En zona comercial:\n1.- Establecimiento en área abierta, con horario de 11:00 a 23:59 horas:\na).- Con cupo de 1 a 100 personas....... 540.00 UMA\nb).- Con cupo de 101 a 200 personas..... 675.00 UMA\nc).- Con cupo de 201 a 300 personas..... 810.00 UMA\nd).- Con cupo de 301 a 400 personas..... 945.00 UMA\ne).- Con cupo de 401 a 600 personas... 1,080.00 UMA\nf).- Con cupo de 601 a 800 personas... 1,215.00 UMA\ng).- Con cupo de más de 800 personas... 1,350.00 UMA\n2.- Establecimiento mixto, de 11:00 a 23:59 horas en área abierta y hasta las\n02:00 horas en área cerrada:\na).- Con cupo de 1 a 100 personas....... 675.00 UMA\nb).- Con cupo de 101 a 200 personas..... 810.00 UMA\nc).- Con cupo de 201 a 300 personas..... 945.00 UMA\nd).- Con cupo de 301 a 400 personas... 1,080.00 UMA\ne).- Con cupo de 401 a 600 personas.... 1,215.00 UMA\nf).- Con cupo de 601 a 800 personas... 1,350.00 UMA\ng).- Con cupo de más de 800 personas.. 1,485.00 UMA\n3.- Establecimiento en área cerrada, de\n11:00 a 02:00 horas:\na).- Con cupo de 1 a 100 personas....... 810.00 UMA\nb).- Con cupo de 101 a 200 personas..... 945.00 UMA\nc).- Con cupo de 201 a 300 personas... 1,080.00 UMA\nd).- Con cupo de 301 a 400 personas... 1,215.00 UMA\ne).- Con cupo de 401 a 600 personas... 1,350.00 UMA\nf).- Con cupo de 601 a 800 personas... 1,485.00 UMA\ng).- Con cupo de más de 800 personas.. 1,620.00 UMA\n4.- Piñatero en zona comercial de 11:00 a 20:00 horas:\na).- Con cupo de 1 a 100 personas....... 270.00 UMA\nb).- Con cupo de 101 a 200 personas..... 405.00 UMA\nc).- Con cupo de 201 a 300 personas..... 540.00 UMA\nd).- Con cupo de 301 a 400 personas..... 675.00 UMA\ne).- Con cupo de 401 a 600 personas..... 810.00 UMA\nf).- Con cupo de 601 a 800 personas..... 945.00 UMA\ng).- Con cupo de más de 800 personas... 1,215.00 UMA el funcionamiento de establecimientos para eventos sociales o fiestas, deberán cubrirse conforme a los siguientes porcentajes sobre el costo del permiso y la zona:\nVI.- Cambio de domicilio\na).- Zona habitacional................................ 30%\nb).- Zona comercial................................... 30%\nVII.- Cambio de propietario\na).- Zona habitacional................................ 40%\nb).- Zona comercial................................... 40%\nVIII.- Cambio de nombre comercial\na).- Zona habitacional................................ 15%\nb).- Zona comercial................................... 15%\nIX.- La revalidación anual del permiso deberá efectuarse en el lapso comprendido de Enero a Marzo de cada año. Por este derecho deberá cubrirse el 5% del valor del permiso.\nPara llevar a cabo la revalidación del permiso, el el reglamento de la materia, así como la constancia de no adeudo municipal.\nX.- Se impondrá una multa de 40.50 a 135.00 Unidad de Medida y Actualización (UMA) a quienes no revaliden el permiso en forma oportuna, o a quienes lo hagan fuera de los plazos establecidos en la presente Ley.\nXI.- Derechos por la prestación de servicios en eventos sociales como organizadores de eventos sociales........... 75.00 UMA\n5.- LOS DERECHOS PARA ADQUIRIR HORAS EXTRAS PARA LA OPERACIÓN DE\nSALONES SOCIALES.\nI.- De lunes a miércoles, solo se autorizará una hora........................... 150.00 UMA\nII.- De jueves a domingo y días festivos solo se autorizarán hasta dos horas: a.- Primera hora.............................. 100.00 UMA b.- Segunda hora.............................. 200.00 UMA\nAquellos salones que opten por adquirir las horas extra necesarias para el desarrollo de sus eventos durante el mes en curso, se podrá obtener un 50% de descuento en la tarifa establecida a partir de la adquisición de cuatro horas adicionales, siempre y cuando sean solicitados los primeros 3 días hábiles de cada mes y cumplan con el pago en una sola exhibición. Solo se autorizarán un máximo de derecho. Los días festivos serán aquellos que la Ley en la materia señale. los que se dará inicio el evento.\nDirección de Comercio, Alcoholes y Espectáculos Públicos.\n6.- RECEPCIÓN Y ANÁLISIS DE DOCUMENTOS REFERENTES A LA INSTALACIÓN\nDE APARATOS MUSICALES (SINFONOLAS)\nARTÍCULO 23.- Para la apertura (inicio de actividades), cambio de permisionario, cambio de domicilio o el incremento de aparatos musicales (sinfonolas), deberán entregarse y conforme a la tabla siguiente:\nPROPIETARIO DEL APARATO\na).- Por aparato (sinfonola), cuando es inicio de actividades................................... 135.00 UMA\nb).- Cambio de domicilio............................... 13.50 UMA\nc).- Verificación anual por aparato.................... 40.50 UMA\n7.- EXPEDICIÓN DE PERMISOS PARA EL EJERCICIO DEL COMERCIO EN LA\nVÍA PÚBLICA POR COMERCIANTES AMBULANTES O CON PUESTOS FIJOS O\nSEMI FIJOS.\nARTÍCULO 24.- Los derechos por la expedición y/o revalidación de permisos para el uso u ocupación de las vías públicas, por comerciantes ambulantes o con puestos fijos o semifijos serán pagados por los usuarios en los meses de enero a marzo del ejercicio en curso, según corresponda conforme a la siguiente:\nUNIDAD DE MEDIDA Y ACTUALIZACIÓN\n(UMA)VIGENTE\nA.- ANUALMENTE:\na).- Ambulante\n1).- AMBULANTE CON CAJA:\n1.1.- Segundo cuadro..................... 10.80 UMA\n1.2.- Zona rural.......................... 6.75 UMA\n2).- AMBULANTE CON CARRETA:\n2.1.- Segundo cuadro..................... 13.50 UMA\n2.2.- Zona rural.......................... 9.45 UMA\n3).- AMBULANTE MOTORIZADO:\n3.1.- Segundo cuadro..................... 16.20 UMA\n3.2.- Zona rural......................... 12.15 UMA\n4).- PUESTOS FIJOS:\n4.1.- Segundo cuadro..................... 33.75 UMA\n4.2.- Zona rural......................... 28.35 UMA\n5).- PUESTOS SEMIFIJOS:\n5.1.- Segundo cuadro..................... 29.70 UMA\n5.2.- Zona rural......................... 24.30 UMA\n6).- MERCADOS COMUNES EN LA VÍA PÚBLICA:\n6.1.- Primer cuadro...................... 16.20 UMA\n6.2.- Segundo cuadro..................... 16.20 UMA\n6.3.- Zona rural......................... 10.80 UMA\n7).- MERCADOS COMUNES EN PREDIO PRIVADO:\n7.1.- Segundo cuadro..................... 16.20 UMA\n7.2.- Zona rural......................... 10.80 UMA\n8).- PUESTOS DE REVISTAS:\n8.1.- Segundo cuadro...................... 8.10 UMA\n8.2.- Zona rural.......................... 4.05 UMA\n9).- ASEADORES DE CALZADO:\n9.1.- Segundo cuadro..................... 1.35 UMA\n9.2.- Zona rural......................... 1.35 UMA\n10).- FOTÓGRAFOS AMBULANTES:\n10.1.- Segundo cuadro..................... 8.10 UMA\n10.2.- Zona rural......................... 4.05 UMA\n11).- Camión ambulante (medida 3 metros)....... 87.75 UMA\n12).- Metro excedente de camión ambulante...... 27.00 UMA\n13).- Cerrajeros ambulantes.................... 33.75 UMA\n14).- Los ambulantes que se dediquen a la venta exclusiva de artesanías mexicanas, pagarán el 50% de los derechos causados.\n15).- Otras actividades realizadas en vía pública.................................. 60.00 UMA\nB.- POR EVENTO:\n1).- Permiso por día\na).- Mercado común............................. 1.02 UMA\nb).- Días festivos............................. 6.75 UMA\nc).- Eventos deportivos.......... DE 6.75 HASTA 33.75 UMA c1).- Carpa 3x3 m²....................... 10.80 UMA c2).- Metro cuadrado adicional de carpa\n3x3 m².............................. 1.35 UMA\nd).- Por mesa de 2 a 4 personas en vía pública, o fracción................ 0.80 UMA\ne).- Eventos privados (graduaciones, obras de teatro o lugares donde se realicen eventos y/o espectáculos públicos), sin que esta autorización exceda de dos horas en la misma ubicación........................... 4.05 UMA\nf).- Envolturas de regalos...................... 5.40 UMA\ng).- Autorización por metro excedente en puesto fijo o semifijo considerando mobiliario y equipo de trabajo, no pudiendo exceder de dos metros:\n1).- Anual................................ 50.00 UMA\n2).- Mensual.............................. 17.55 UMA\n2).- Permiso tarifa semanal........................ 4.05 UMA\n3).- Permiso tarifa quincenal...................... 6.75 UMA\n4).- Permiso tarifa mensual........................ 10.80 UMA\n5).- Permiso tarifa diaria......................... 0.68 UMA\nLas personas mayores de 60 años, así como las personas con discapacidad, los jubilados y pensionados y que cuenten con autorización a su nombre, estarán exentos del pago de los derechos contemplados en los apartados A.- y B.- numeral 1 Inciso\na) de este artículo debiendo comprobar su condición con identificación oficial o en su caso certificado médico que acredite tal condición, elaborado por una institución de salud pública.\nAsí mismo las personas que se dediquen a la venta de mercancía deteriorada o usada a través del mercado común, pagarán el 50%\n(cincuenta por ciento) de los derechos previstos en el apartado\nB.-) numeral 1 inciso a) de este artículo, previo estudio socioeconómico elaborado por la Dirección de Bienestar Social\nMunicipal o por el Sistema para el Desarrollo Integral de la\nFamilia.\n6).- Permiso dentro de la zona de festejos, organizados y / o coordinados por la\nAdministración Pública Municipal Centralizada, por día según la siguiente tabla:\nEn UMA Vigente, Unidad de Medida y Actualización.\n1).- Carpa de 3x3 metros...................... 90.45 UMA\n1.1).- Metro cuadrado adicional de carpa 3x3...................... 1.35 UMA\n7).- Cuando la organización del festejo recaiga en Entidades de la Administración Pública\nDescentralizada, el permiso general otorgado a estas, para su uso de conformidad a las disposiciones legales que le sean aplicables..................... 0.00 UMA\nLa clasificación de zonas y puestos, así como el plano de su ubicación, dentro de la zona destinada a la realización del festejo de que se trate, deberá ser emitido por el Presidente Municipal, cuando su organización esté a cargo del Gobierno Central, o del\nDirector de que se trate cuando su organización esté a cargo del\nÓrgano Descentralizado de la Organización Municipal, y deberá ser publicado en la página electrónica del Gobierno Municipal previo al inicio de la comercialización de los espacios.\nDe igual forma para madres jefas de familia sin cónyuge o pareja en aptitud de trabajar, que son el único sostén del hogar, con hijo o hijos menores de edad y/o personas con capacidades diferentes, tendrán el 50% (cincuenta por ciento) de descuento en el pago de los derechos estipulados en los apartados A.- y B.- numeral 1) inciso a) de este artículo para lo cual se realizará estudio socioeconómico por medio de la Dirección de Bienestar Social\nMunicipal o por el Sistema para el Desarrollo Integral de la de matrimonio.\nC.- REVALIDACIÓN: en la vía pública en su modalidad de ambulante, fijo, marzo del ejercicio fiscal correspondiente, el no revalidar durante ese periodo generará un cobro de 3% mensual hasta en tanto sea cubierto dicha revalidación.\n1).- AMBULANTE CON CAJA:\n1.1.- Segundo cuadro.......................... 10.80 UMA\n1.2.- Zona rural.............................. 6.75 UMA\n1.3.- Primer cuadro y Zona turística......... 13.50 UMA\n2).- AMBULANTE CON CARRETA:\n2.1.- Segundo cuadro.......................... 13.50 UMA\n2.2.- Zona rural.............................. 9.45 UMA\n2.3.- Primer cuadro y Zona turística.......... 16.20 UMA\n3).- AMBULANTE MOTORIZADO:\n3.1.- Segundo cuadro.......................... 16.20 UMA\n3.2.- Zona rural.............................. 12.15 UMA\n3.3.- Primer cuadro y Zona turística.......... 18.90 UMA\n4).- PUESTOS FIJOS:\n4.1.- Segundo cuadro.......................... 33.75 UMA\n4.2.- Zona rural.............................. 28.35 UMA\n4.3.- Primer cuadro y Zona turística.......... 46.00 UMA\n5).- PUESTOS SEMIFIJOS:\n5.1.- Segundo cuadro.......................... 29.70 UMA\n5.2.- Zona rural.............................. 24.30 UMA\n5.3.- Primer cuadro y Zona turística.......... 46.00 UMA\n6).- MERCADOS COMUNES EN LA VÍA PÚBLICA:\n6.1.- Primer cuadro........................... 16.20 UMA\n6.2.- Segundo cuadro.......................... 16.20 UMA\n6.3.- Zona rural.............................. 10.80 UMA\n6.4.- Zona turística.......................... 18.90 UMA\n7).- MERCADOS COMUNES EN PREDIO PRIVADO:\n7.1.- Segundo cuadro.......................... 16.20 UMA\n7.2.- Zona rural.............................. 10.80 UMA\n7.3.- Primer cuadro y Zona turística.......... 18.90 UMA\n8).- PUESTOS DE REVISTAS:\n8.1.- Segundo cuadro.......................... 8.10 UMA\n8.2.- Zona rural.............................. 4.05 UMA\n8.3.- Primer cuadro y Zona turística.......... 10.80 UMA\n9).- ASEADORES DE CALZADO:\n9.1.- Segundo cuadro........................... 1.35 UMA\n9.2.- Zona rural.............................. 1.35 UMA\n9.3.- Primer cuadro y Zona turística........... 4.05 UMA\n10).- FOTÓGRAFOS AMBULANTES:\n10.1.- Segundo cuadro.......................... 8.10 UMA\n10.2.- Zona rural.............................. 4.05 UMA\n10.3.- Primer cuadro y Zona turística.......... 10.80 UMA\n11).- Camión ambulante (medida 3 metros)............. 40.50 UMA\n12).- Cerrajeros ambulantes.......................... 6.75 UMA\n13).- Otras actividades realizadas en vía pública.... 30.00 UMA\nLas personas mayores de 60 años, así como las personas con discapacidad, los jubilados y pensionados y que cuenten con autorización a su nombre, estarán exentos del pago de los derechos contemplados en el apartado C.- de este artículo debiendo comprobar médico que acredite tal condición, elaborado por una Institución de Salud Pública. en aptitud de trabajar, que son el único sostén del hogar, con hijo o hijos menores de edad y/o personas con capacidades diferentes, tendrán el 50% (cincuenta por ciento) de descuento en el pago de los derechos estipulados en este apartado C.- del presente artículo certificado de inexistencia de matrimonio, no aplicando este beneficio sobre el cobro del 3% mensual que se aplica en caso de no revalidar durante los meses de enero a marzo.\nD.- VENTA DE PRODUCTOS (EN MOVIMIENTO) EN ESPACIOS PÚBLICOS.\n1).- En parques, playas, jardines y plazas destinadas al esparcimiento......................... 12.29 UMA MENSUAL\nE.- MÚSICOS AMBULANTES CON FINES DE LUCRO.\n1).- En parques, playas, jardines y plazas destinadas al esparcimiento......................... 12.29 UMA MENSUAL\n8.- ARRENDAMIENTO DE ESPACIOS PÚBLICOS EN PARQUES, PLAYAS, JARDINES\nY PLAZAS DESTINADAS AL ESPARCIMIENTO.\na).- Elaboración y venta de alimentos, productos y bebidas sin graduación alcohólica (puestos fijos)........... 148.50 UMA MENSUAL\nApoyo del 50% a discapacitados y a mayores de 60 años y puestos semifijos.\nb).- Eventos especiales sin fines recaudatorios o de lucro\n(exposiciones, muestras musicales).............................. 4.86 UMA DIARIO b1).- Eventos especiales sin fines recaudatorios o de lucro\n(exposiciones, muestras musicales) con autorización del Instituto de Cultura y\nDesarrollo Humano................ 0.00 UMA DIARIO b2).- Eventos especiales recaudatorios o de lucro, con el fin de promover la cultura local (artesanías locales)........ 1.96 UMA DIARIO\nNota: Se entiende por artesanía, aquel producto creado por artesanos, siempre que la contribución manual directa sea el componente más importante del producto acabado. Sus características distintivas pueden ser utilitarias, estéticas, artísticas, creativas, tradicionales, simbólicas y significativas culturalmente.\nc).- Eventos especiales con fines recaudatorios o de lucro para beneficio social (kermeses, boteos, venta de productos).......... 7.36 UMA DIARIO\nd).- Actividades recreativas sin fines recaudatorios o de lucro\n(torneos, rallys, juegos, reuniones)............................ 4.86 UMA DIARIO\ne).- Actividades recreativas de uso reiterado con fines recaudatorios o de lucro\n(pinturas, manualidades, pirograbados y payasos)............... 12.29 UMA MENSUAL\nf).- Actividades recreativas de uso reiterado con fines de lucro\n(renta de carritos de tracción eléctrica, vehículos eléctricos o de gasolina, bicicletas, inflables\n(brincolines), sombrillas y mesas)................................ 33.75 UMA SEMANAL\ng).- Uso de espacios habilitados para estacionamiento temporal por evento a actividad especial (Playa\nMunicipal, Parque Ecológico Cañón de Doña Petra)............................. 0.49 UMA POR\nVEHÍCULO\nh).- Acampado en áreas destinadas para tal fin.................................... 1.35 UMA POR\nPERSONA\ni).- Renta por día del parque costero\nPlaya Hermosa.\na) 1 a 50 personas........................... 40.50 UMA\nb) 51 a 100 personas......................... 81.00 UMA\nc) 101 a 150 personas........................ 162.00 UMA\nd) 151 a 300 personas........................ 270.00 UMA\ne) 300 personas en adelante.................. 405.00 UMA\nj).- Renta por día del parque\nNiños Héroes…................................ 27.00 UMA\nCAPÍTULO IV\nACCESO A LA INFORMACIÓN PÚBLICA:\nARTÍCULO 25.- Servicios que presta la Unidad Municipal de reproducción de información solicitada, será pagada por los solicitantes, de acuerdo a lo siguiente:\na) Copia simple (después de la copia número 21)......... 0.02 UMA\nb) Copia certificada.................................... 0.20 UMA\nCAPÍTULO V\nSERVICIOS QUE PRESTA LA DIRECCIÓN DE BIENESTAR SOCIAL MUNICIPAL,\nA TRAVÉS DE:\nI.- DEPARTAMENTO DE SERVICIOS MÉDICOS\nARTÍCULO 26.- Los servicios que preste el Departamento de\nServicios Médicos, se regirán bajo la siguiente:\nUNIDAD DE MEDIDA Y ACTUALIZACIÓN\n(UMA)VIGENTE\nA).- Consulta médica y psicológica en servicios médicos:\n1.-Consulta médica general....................... 1.00 UMA\n2.-Consulta psicológica............................ 1.00 UMA\nB).- Registro en servicio médico:\n1.- Registro en servicio médico, nuevo ingreso y reingreso (3 o más meses de ser usuario irregular)..................................... 4.50 UMA\n2.- Registro en servicio médico, usuario regular................................ 2.00 UMA\n3.- Registro en servicio médico, usuario irregular............................. 4.00 UMA\nC).- Expedición y reposición de tarjeta de salud:\n1.-Expedición de tarjeta, de salud nuevo ingreso y reingreso................. 3.00 UMA\n2.- Reposición de tarjeta, de salud regular.................................. 2.00 UMA\n3.- Reposición de tarjeta, de salud irregular................................ 4.00 UMA\nD).- Certificados médicos de salud:\n1.- Certificados médicos de salud: para estudiantes, licencias de conducir, comercio ambulante, empleo, de integridad física, para portación de arma, antidoping, pasaporte, visa, prenupciales y otros.......................... 3.00 UMA\n2.- Certificado Médico de Esencia a conductores bajo el influjo del Alcohol, Psicotrópicos o\nEnervantes; sólo cuando el resultado sea positivo....................... 10.00 UMA\nSe exentará del cobro de todos los incisos anteriores, tratándose de personas que no cuenten con servicios médicos de Instituciones de Salud Pública y exista notoria falta de recursos económicos, le practique.\nE).- Multas por infracciones menores a disposiciones del Departamento de Servicios Médicos................. 1.00 a 100.00 UMA\nF).- Multas por infracciones mayores a disposiciones del Departamento de Servicios Médicos.................. 100.00 a 300.00 UMA\nII.- EL DEPARTAMENTO DE EDUCACIÓN\nARTÍCULO 27.- Los servicios que preste el Departamento de\nEducación, se regirán bajo la siguiente:\nUNIDAD DE MEDIDA Y ACTUALIZACIÓN\n(UMA)VIGENTE\n1.- Renta de Parque Club Rotario, Calle Novena.............................. 13.50 UMA POR DÍA.\n2.- Renta de Parque Club Rotario, Calle Once................................ 13.50 UMA POR DÍA.\n3.- Renta de Parque Mundo Infantil:\na).- Área de Kiosko...................... 20.25 UMA POR DÍA.\nb).- Área de Piñatero..................... 20.25 UMA POR DÍA.\nc).- Área Explanada....................... 20.25 UMA POR DÍA.\n4-. Cobro de entrada Parque Mundo\nInfantil por persona............................ $6.75 PESOS. edad, discapacitados y escuelas públicas, cuando realicen actividades sin fines de lucro.\nCAPÍTULO VI\nSERVICIOS QUE PRESTA LA DIRECCIÓN DE ADMINISTRACIÓN URBANA,\nECOLOGÍA Y MEDIO AMBIENTE\nARTÍCULO 28.- Los servicios que preste la Dirección de\nAdministración Urbana, Ecología y Medio Ambiente a través de sus subdirecciones, se pagarán conforme a la siguiente:\nUNIDAD DE MEDIDA Y ACTUALIZACIÓN\n(UMA)VIGENTE\nI.- POR REVISIÓN Y ANÁLISIS PARA LA EXPEDICIÓN DE PERMISOS\nPARA CONSTRUCCIÓN, AMPLIACIÓN, RECONSTRUCCIÓN, TRASLADO O\nDEMOLICIÓN DE INMUEBLES\nA.- Para construcción, reconstrucción, ampliación y remodelación de edificios habitacionales, comerciales e industriales sobre metro cuadrado de construcción, de acuerdo a la siguiente tabla:\n1.- Casa habitación y vivienda de interés social unifamiliares, tratándose de inmuebles construidos sin fines de comercialización ni de arrendamiento.\n1.1.- Casa habitación nueva con superficie de:\na).- Hasta 60 m²...................... 0.20 UMA\nb).- Más de 60 hasta 180 m²........... 0.30 UMA\nc).- Más de 180 m² hasta 500 m²....... 0.40 UMA\nd).- Más de 500 m² hasta 1,000 m²..... 0.45 UMA\ne).- Más de 1,000 m².................. 0.50 UMA\n2.- Ampliación de casa habitación por metro cuadrado hasta 180 m²...................... 0.30 UMA\n2.a).- Ampliación de casa habitación por metro cuadrado mayor de 180 m²... 0.40 UMA\n3.- Otras edificaciones e instalaciones:\na).- Otras construcciones diferentes a casa habitación, construcción o ampliación.\n1) Hasta 100 m²........................ 0.40 UMA\n2) Más de 100 m² a 200 m².............. 0.45 UMA\n3) Más de 200 m² a 500 m².............. 0.50 UMA\n4) Más de 500 m²....................... 0.55 UMA\nb).- Otras construcciones industriales, construcción o ampliación.\n1) Hasta 200 m²........................ 0.50 UMA\n2) Más de 200 m² a 500 m².............. 0.60 UMA\n3) Más de 500 m² a 1,000 m²............ 0.70 UMA\n4) Más de 1,000 m²..................... 0.80 UMA\nc).- Instalación de casa móvil.............. 0.25 UMA\nd).- Licencia de construcción provisional:\na).- Hasta 100 m²...................... 0.15 UMA\nb).- Más de 100 m²..................... 0.20 UMA\ne).- Permiso de instalación de línea o red de agua potable, drenaje sanitario o drenaje pluvial por km o fracción.\nIncluye demolición.................... 20.25 UMA\nf).- Construcción o conexión a pozo de visita, construcción de caja de válvulas y/o, registros para línea de agua potable o drenaje sanitario, instalación de descarga sanitaria o toma de agua potable. Por unidad.\nIncluye demolición..................... 2.03 UMA\ng).- Permiso para construcción de carpeta de pavimento asfáltico y concreto hidráulico, a particulares por m². Incluye demolición............. 0.20 UMA\n4.- Bardas y cercos, muros de contención:\na).- Bardas por metro lineal de construcción........................ 0.30 UMA\nb).- Cercos por metro lineal de construcción........................ 0.25 UMA\nc).- Muro de contención menor a 1.5 m de altura, por metro lineal........................... 0.35 UMA c.1).- Muro de contención mayor a 1.5 m de altura por metro lineal.................... 0.50 UMA\n5.- Ocupación parcial de la vía pública con material, equipo o herramienta de construcción el m² por día.\na).- Zona urbanizada........................ 0.34 UMA\nb).- Zona no urbanizada..................... 0.20 UMA\n6.- Regularizaciones de construcción, ampliación, remodelación, demolición o reconstrucción, 50% adicional al costo del trámite normal de la licencia.\nReferentes a los incisos del 1 al 4 del punto I.A\n7.- Prórrogas, 25% del costo actualizado del trámite normal de la licencia, con antigüedad máxima de un año.\na).- Prórrogas, 35% del costo actualizado o del trámite normal de la licencia, con antigüedad mayor a 1 año y menor a 5 años.\nb).- Prórrogas, 50% del costo actualizado o del trámite normal de la licencia, con antigüedad mayor a 5 años.\nc).- Casa de interés social de un nivel de hasta 38 m² de construcción cobro del 25% sobre el costo inicial.\n8.- Constancia de terminación de obra, autorización de ocupación, 10% del costo actualizado del trámite normal de la licencia.\na).- Casa de interés social de un nivel de hasta 38 m² de construcción, cobro del 10% sobre el costo inicial.\n9.- Cambio de techo o cambio de fachada.\na).- Cambio de techo, 25% del costo normal del trámite de la licencia.\nb).- Cambio de fachada por metro cuadrado............................... 0.45 UMA\n10.- Reconstrucciones, 50% del costo normal del trámite de la licencia.\n11.- La obra pública estará exenta del pago de los derechos por los permisos que se establecen en el artículo 22, Urbana, Ecología y Medio Ambiente, las\nEspecificaciones técnicas y proyecto a realizar.\n12.- Remodelación, 25% del costo normal de la licencia.\n13.- Construcción de fosa séptica, cisterna, tanque de almacenamiento, superficial o subterráneo, por m³....................................... 0.30 UMA\n14.- Construcción de alberca por m³: a.- Casa habitación......................... 2.70 UMA b.- Otros................................... 4.73 UMA\n15.- Construcción y/o instalación de antena (torre) para sistemas de comunicación por metro lineal de altura................................... 8.10 UMA\n16.- Licencia de construcción y/o instalación de torre para anuncio espectacular por metro lineal de altura................................... 8.10 UMA\nB.- Para demolición parcial o total de inmuebles se pagará de acuerdo a las siguientes cuotas:\n1.- Demolición de inmuebles más de 16m², por metro cuadrado........................ 0.20 UMA\n1.1- Demolición de inmuebles más de 100 m², por metro cuadrado..................... 0.40 UMA\n2.- Bardas por metro cuadrado................... 0.18 UMA\n3.- Demolición de cordón banqueta............... 1.50 UMA\nPOR ml\n4.- Demolición de banquetas..................... 2.00 UMA\nPOR m²\n5.- Demolición de torre para anuncio espectacular por metro lineal de altura.................. 2.70 UMA\nC.- Revisión previa de anteproyectos.\na).- Anteproyecto de casa habitación. a.1) 1-100 m².............................. 6.75 UMA a.2) 101-500 m²............................ 9.45 UMA a.3) 501-1000 m².......................... 12.15 UMA a.4) Más de 1000 m²....................... 14.85 UMA\nb).- Anteproyecto de otras construcciones. b.1) 1-100 m²............................. 10.80 UMA b.2) 101-500 m²........................... 13.50 UMA b.3) Más de 500 m²........................ 22.95 UMA\nD.- Gastos de notificación.......................... 2.03 UMA\n1).- Gastos de ejecución 10% del monto del adeudo.\n2).- Denuncia ciudadana......................... 1.35 UMA\nE.- Derechos de registro como responsable y/o corresponsable de obras, el pago se realiza al iniciar el trámite.\n1.- Registro inicial........................... 18.00 UMA\n2.- Revalidación anual (peritos sin trámites pendientes)....................... 14.00 UMA\n3.- Revalidación anual (peritos con trámites inconclusos, con más de 40 días de antigüedad).................. 16.00 UMA\n4.- Por cambio de responsable director de obra..................................... 8.00 UMA revalidación anual de responsable y/o corresponsable de obras, el beneficiario deberá presentar constancia de no adeudo municipal vigente al ejercicio fiscal 2025.\nF.- Movimientos de tierra:\n1.- Hasta 200 m³ dentro del centro de población................................... 6.75 UMA\n2.- Dentro del centro de población:\n2.1.- De 201 a 500 m³...................... 33.75 UMA\n2.2.- De 501 a 2000 m³..................... 67.50 UMA\n2.3.- De 2001 a 5000 m³................... 101.25 UMA\n2.4.- De 5001 a 10000 m³.................. 135.00 UMA\n3.- Por m³ de volumen excedente a 10,000 m³ dentro del centro de población.................................. 0.015 UMA\n4.- Hasta 200 m³ fuera del centro de de población................................ 4.05 UMA\n5.- Fuera del centro de población:\n5.1.- De 201 a 500 m³...................... 31.05 UMA\n5.2.- De 501 a 2000 m³..................... 64.80 UMA\n5.3.- De 2001 a 5000 m³.................... 98.55 UMA\n5.4.- De 5001 a 10000 m³.................. 132.30 UMA\n6.- Por m³ de volumen excedente a\n10,000 m³ fuera del centro de población................................... 0.01 UMA\n7.- Regularización de movimientos de tierra, 50% adicional al costo de trámite normal de la licencia.\nReferente a los puntos del 1 al 6 fracción I.-, letra F.\n8.- Prórroga de movimientos de tierra\n50% del costo actualizado de trámite normal de la licencia.\nReferente a los puntos del 1 al 6 fracción I.-, letra F.\nG.- Certificación de planos autorizados, adicionales a los otorgados al obtenerse los permisos a que se refiere el apartado A, por cada juego adicional. Debiendo realizar el pago al iniciar el trámite.\n1.- Por juego de hasta 25 planos................ 2.03 UMA\n2.- Por juego de más de 25 planos............... 5.40 UMA\nH.- Modificación de proyecto autorizado 10% el costo actualizado del trámite normal de la licencia. Para licencias vigentes.\n1.- Modificación de proyecto autorizado, 45% del costo actualizado del trámite normal con antigüedad menor a 5 años.\nI.- Factibilidad de licencia de construcción, revisión y análisis de prototipo de vivienda.\n1. Hasta por 180 m²............................. 4.05 UMA\n2. Mayor de 180 m².............................. 6.75 UMA\nJ.- Por suspensión temporal, por la reactivación de licencia de obra, o constancia de requerimiento o no licencia de construcción.................................... 1.35 UMA\nK.- Por aprobación de prototipo de vivienda.\n1. Hasta 180 m²................................ 10.80 UMA\n2. Mayor de 180 m²............................. 16.20 UMA\nL.- Por revisiones subsecuentes a la segunda revisión:\n1. Por la tercera revisión..................... 1.35 UMA\nSe paga al ingresar documentos por revisión.\n2. Por revisiones subsecuentes a partir de la cuarta revisión.............................. 2.70 UMA\nSe paga al ingresar documentos por revisión.\nII.- POR ANÁLISIS DE DESARROLLOS URBANOS:\na).- Por análisis y emisión de dictamen sobre uso del suelo para el desarrollo urbano de predios, se pagará por dictamen:\n1.- De terrenos ubicados dentro de los límites del centro de la población de la cabecera municipal................................ 81.00 UMA\n1.1 Los fraccionamientos tipo interés social progresivo tendrán un 50% de descuento de estas cuotas. Siempre y cuando los urbanizadores sean instituciones gubernamentales, paraestatales y paramunicipales.\n1.2 Los fraccionamientos o asentamientos humanos que sean previamente clasificados como TIPO POPULAR y que sean notificados por el Instituto Nacional del Suelo Sustentable (INSUS) en proceso de regularización del suelo con base en el convenio de colaboración con el Ayuntamiento de Ensenada, B.C. que se encuentre vigente, estarán exentos del pago de los conceptos de este apartado.................... 0.00 UMA\n2.- De terrenos ubicados dentro de los límites de los centros de población de los poblados.\n........................................ 121.50 UMA\n2.1 Los fraccionamientos tipo interés social progresivo tendrán un 50% de descuento de estas cuotas. Siempre y cuando los urbanizadores sean instituciones gubernamentales, paraestatales y paramunicipales.\n2.2 Los fraccionamientos o asentamientos humanos que sean previamente clasificados como TIPO POPULAR y que sean notificados por el Instituto Nacional del Suelo Sustentable (INSUS) en proceso de regularización del suelo con base en el convenio de colaboración con el Ayuntamiento de\nEnsenada, B.C. que se encuentre vigente, estarán exentos del pago de los conceptos de este apartado..... 0.00 UMA\n3.- De terrenos ubicados dentro del área de aplicación del Programa Regional de\nDesarrollo Urbano, Turístico y Ecológico del corredor costero Tijuana-Ensenada....... 121.50 UMA\n3.1 Los fraccionamientos tipo interés social progresivo tendrán un 50% de descuento de estas cuotas. Siempre y cuando los urbanizadores sean instituciones gubernamentales, paraestatales y paramunicipales.\n3.2 Los fraccionamientos o asentamientos humanos que sean previamente clasificados como TIPO POPULAR y que sean notificados por el Instituto Nacional del Suelo Sustentable (INSUS) en proceso de regularización del suelo con base en el convenio de colaboración con el Ayuntamiento de Ensenada, B.C. que se encuentre vigente, estarán exentos del pago de los conceptos de este apartado....................... 0.00 UMA\n4.- De terrenos ubicados fuera de los límites de los centros de población.............. 121.50 UMA\n4.1 Los fraccionamientos tipo interés social progresivo tendrán un 50% de descuento de estas cuotas. Siempre y cuando los urbanizadores sean instituciones gubernamentales, paraestatales y paramunicipales.\n4.2 Los fraccionamientos o asentamientos humanos que sean previamente clasificados como TIPO POPULAR y que sean notificados por el Instituto Nacional del Suelo Sustentable (INSUS) en proceso de regularización del suelo con base en el convenio de colaboración con el Ayuntamiento de Ensenada, B.C. que se encuentre vigente, estarán exentos del pago de los conceptos de este apartado............................ 0.00 UMA\nb).- Por análisis de anteproyecto de fraccionamiento se pagará por la superficie total en la forma siguiente:\n1.- En terrenos ubicados dentro de los centros de población:\n1.1).- Por las primeras cinco hectáreas.. 202.50 UMA\n1.2).- Los fraccionamientos tipo interés social progresivo tendrán un 50% de descuento de estas cuotas, siempre y cuando los urbanizadores sean instituciones gubernamentales, paraestatales y paramunicipales.\n1.3).- Por cada hectárea, excedente de cinco hectáreas hasta diez hectáreas.... 50.00 UMA\n1.4).- Los fraccionamientos tipo interés social progresivo tendrán un 50% de descuento de estas cuotas, siempre y cuando los urbanizadores sean instituciones gubernamentales, paraestatales y paramunicipales.\n1.5).- Por cada hectárea, excedente de diez hectáreas........................... 8.10 UMA\n1.6).- Los fraccionamientos tipo interés social progresivo tendrán un 50% de descuento de estas cuotas, siempre y cuando los urbanizadores sean instituciones gubernamentales, paraestatales y paramunicipales.\n1.7).- Los fraccionamientos o asentamientos humanos que sean previamente clasificados como TIPO POPULAR y que sean notificados por el Instituto Nacional del Suelo Sustentable (INSUS) en proceso de regularización del suelo con base en el convenio de colaboración con el Ayuntamiento de Ensenada, B.C. que se encuentre vigente, estarán exentos del pago de los conceptos de este apartado......... 0.00 UMA\n2.- En terrenos ubicados dentro del área de aplicación del Programa Regional de\nDesarrollo Urbano, Turístico y Ecológico del\nCorredor Costero Tijuana-Rosarito-Ensenada.\n2.1).- Por las primeras cinco hectáreas.. 243.00 UMA\n2.2).- Los fraccionamientos tipo interés social progresivo tendrán un 50% de descuento de estas cuotas, siempre y cuando los urbanizadores sean instituciones gubernamentales, paraestatales y paramunicipales.\n2.3).- Por cada hectárea, excedente de cinco hectáreas en fraccionamientos menores a 10 hectáreas.................... 50.00 UMA\n2.4).- Los fraccionamientos tipo interés social progresivo tendrán un 50% de descuento de estas cuotas, siempre y cuando los urbanizadores sean instituciones gubernamentales, paraestatales y paramunicipales.\n2.5).- Por cada hectárea excedente de diez hectáreas o fracción adicional..... 9.45 UMA\n2.6).- Los fraccionamientos tipo interés social progresivo tendrán un 50% de descuento de estas cuotas, siempre y cuando los urbanizadores sean instituciones gubernamentales, paraestatales y paramunicipales.\n2.7).- Los fraccionamientos o asentamientos humanos que sean previamente clasificados como TIPO POPULAR y que sean notificados por el Instituto Nacional del Suelo Sustentable (INSUS) en proceso de regularización del suelo con base en el convenio de colaboración con el Ayuntamiento de Ensenada, B.C. que se encuentre vigente, estarán exentos del pago de los conceptos de este apartado......... 0.00 UMA\n3.- En terrenos ubicados fuera de los límites de los centros de población:\n3.1).- Por las primeras cinco hectáreas.. 283.50 UMA\n3.2).- Los fraccionamientos tipo interés social progresivo tendrán un 50% de descuento de estas cuotas, siempre y cuando los urbanizadores sean instituciones gubernamentales, paraestatales y paramunicipales.\n3.3).- Por cada hectárea, excedente de cinco hectáreas en fraccionamientos menores a 10 hectáreas.................... 50.00 UMA\n3.4).- Los fraccionamientos tipo interés social progresivo tendrán un 50% de descuento de estas cuotas, siempre y cuando los urbanizadores sean instituciones gubernamentales, paraestatales y paramunicipales.\n3.5).- Por cada hectárea, excedente de diez hectáreas o fracción adicional..... 8.10 UMA\n3.6).- Los fraccionamientos tipo interés social progresivo tendrán un 50% de descuento de estas cuotas, siempre y cuando los urbanizadores sean instituciones gubernamentales, paraestatales y paramunicipales.\n3.7).- Los fraccionamientos o asentamientos humanos que sean previamente clasificados como TIPO POPULAR y que sean notificados por el Instituto Nacional del Suelo Sustentable (INSUS) en proceso de regularización del suelo con base en el convenio de colaboración con el Ayuntamiento de Ensenada, B.C. que se encuentre vigente, estarán exentos del pago de los conceptos de este apartado.......... 0.00 UMA\n4.- Para acciones de urbanización por incorporación o reincorporación municipal:\na).- En terrenos ubicados dentro de los centros de población: a.1).- Por las primeras cinco hectáreas................... 121.50 UMA a.2).- Los fraccionamientos tipo interés social progresivo tendrán un 50% de descuento de estas cuotas, siempre y cuando los urbanizadores sean instituciones gubernamentales, paraestatales y paramunicipales. a.3).- Por cada hectárea, excedente de cinco hectáreas en fraccionamientos menores a 10 hectáreas.. 50.00 UMA a.4).- Los fraccionamientos tipo interés social progresivo tendrán un 50% de descuento de estas cuotas, siempre y cuando los urbanizadores sean instituciones gubernamentales, paraestatales y paramunicipales. a.5).- Por cada hectárea, excedente de diez hectáreas o fracción adicional..................... 6.08 UMA a.6).- Los fraccionamientos tipo interés social progresivo tendrán un 50% de descuento de estas cuotas, siempre y cuando los urbanizadores sean instituciones gubernamentales, paraestatales y paramunicipales.\nb).- En terrenos ubicados fuera de los límites de los centros de población: b.1).- Por las primeras cinco hectáreas................... 202.50 UMA b.2).- Los fraccionamientos tipo interés social progresivo tendrán un 50% de descuento de estas cuotas, siempre y cuando los urbanizadores sean instituciones gubernamentales, paraestatales y paramunicipales. b.3).- Por cada hectárea, excedente de cinco hectáreas en fraccionamientos menores a 10 hectáreas... 50.00 UMA b.4).- Los fraccionamientos tipo interés social progresivo tendrán un 50% de descuento de estas cuotas, siempre y cuando los urbanizadores sean instituciones gubernamentales, paraestatales y paramunicipales. b.5).- Por cada hectárea, excedente de diez hectáreas o fracción adicional...................... 8.10 UMA b.6).- Los fraccionamientos tipo interés social progresivo tendrán un 50% de descuento de estas cuotas, siempre y cuando los urbanizadores sean instituciones gubernamentales, paraestatales y paramunicipales.\nc).- Por análisis de proyecto de fraccionamientos, habitacionales, comerciales, industriales o mixtos, nuevos o modificaciones a proyectos aprobados que requieran de un nuevo dictamen, se pagará por superficie fraccionada en la forma siguiente: c.1).- Por las primeras cinco hectáreas................... 121.50 UMA c.2).- Los fraccionamientos tipo interés social progresivo tendrán un 50% de descuento de estas cuotas, siempre y cuando los urbanizadores sean instituciones gubernamentales, paraestatales y paramunicipales. c.3).- Por cada hectárea, excedente de cinco hectáreas hasta diez hectáreas.................... 50.00 UMA c.4).- Los fraccionamientos tipo interés social progresivo tendrán un 50% de descuento de estas cuotas, siempre y cuando los urbanizadores sean instituciones gubernamentales, paraestatales y paramunicipales. c.5).- Por cada hectárea, excedente de diez hectáreas o fracción adicional.................... 16.20 UMA c.6).- Los fraccionamientos tipo interés social progresivo tendrán un 50% de descuento de estas cuotas, siempre y cuando los urbanizadores sean instituciones gubernamentales, paraestatales y paramunicipales. c.7).- Los fraccionamientos o asentamientos humanos que sean previamente clasificados como\nTIPO POPULAR y que sean notificados por el Instituto\nNacional del Suelo Sustentable\n(INSUS) en proceso de regularización del suelo con base en el convenio de colaboración con el\nAyuntamiento de Ensenada, B.C. que se encuentre vigente, estarán exentos del pago de los conceptos de este apartado............. 0.00 UMA\nd).- Para acciones de urbanización por incorporación o reincorporación municipal. d.1).- Hasta cinco hectáreas............. 108.00 UMA d.2).- Los fraccionamientos tipo interés social progresivo tendrán un 50% de descuento de estas cuotas, siempre y cuando los urbanizadores sean instituciones gubernamentales, paraestatales y paramunicipales. d.3).- Por cada hectárea, excedente de cinco hectáreas o fracción adicional......................... 13.50 UMA d.1.- Los fraccionamientos tipo interés social progresivo tendrán un 50% de descuento de estas cuotas, siempre y cuando los urbanizadores sean instituciones gubernamentales, paraestatales y paramunicipales.\ne).- Por análisis de proyectos de fraccionamientos tipo granjas, nuevos o modifi- caciones a proyectos que requieran de un nuevo dictamen se pagará por superficie fraccionada o proyectada en la forma siguiente: e.1).- Hasta cinco hectáreas....... 101.25 UMA e.2).- Los fraccionamientos tipo interés social progresivo tendrán un 50% de descuento de estas cuotas, siempre y cuando los urbanizadores sean instituciones gubernamentales, paraestatales y paramunicipales. e.3).- Por cada hectárea, excedente de cinco hectáreas o fracción adicional..................... 9.45 UMA e.4).- Los fraccionamientos tipo interés social progresivo tendrán un 50% de descuento de estas cuotas, siempre y cuando los urbanizadores sean instituciones gubernamentales, paraestatales y paramunicipales.\nf).- Para acciones de urbanización por incorporación o reincorporación municipal. f.1).- Hasta cinco hectáreas........ 60.75 UMA f.2).- Los fraccionamientos tipo interés social progresivo tendrán un 50% de descuento de estas cuotas, siempre y cuando los urbanizadores sean instituciones gubernamentales, paraestatales y paramunicipales. f.3).- Por cada hectárea, excedente de cinco hectáreas o fracción adicional..................... 6.08 UMA f.4).- Los fraccionamientos tipo interés social progresivo tendrán un 50% de descuento de estas cuotas, siempre y cuando los urbanizadores sean instituciones gubernamentales, paraestatales y paramunicipales.\ng).- Relotificación, subdivisión o fusión de lotes urbanos:\n1.- Por la recepción de trámite de relotificación, subdivisión o fusión de predios, dentro o fuera del límite del centro de población... 4.05 UMA\n2.- Por relotificación de manzanas y certificación de la memoria descriptiva, por cada lote resultante...................... 16.20 UMA\n3.- Por subdivisión o fusión de lotes urbanos y certificación de memoria descriptiva de los mismos, por cada lote fusionado o lote resultante de la subdivisión, se pagará:\na).- En baldíos o construidos... 18.00 UMA\n4.- Estará exenta la subdivisión, previo estudio socioeconómico tratándose de deslinde familiares.\n5.- Para los predios en fraccionamientos o asentamientos humanos que sean previamente clasificados como\nTIPO POPULAR y que sean notificados por el Instituto Nacional del Suelo\nSustentable (INSUS) en proceso de regularización del suelo con base en el convenio de colaboración con el\nAyuntamiento de Ensenada, B.C. que se encuentre vigente, estarán exentos del pago de los conceptos de este apartado......................... 0.00 UMA\nh).- Por división de predios rústicos dentro o fuera de los límites de los centros de población que no requieran apertura de calles, por cada fracción resultante.......................... 33.75 UMA\ni).- Por división de predios rústicos para uso agropecuario que no requieran apertura de calle, por cada fracción resultante.......................... 33.75 UMA\nj).- Por división de predios rústicos, ubicados dentro del área de aplicación del Programa Regional de Desarrollo\nUrbano, Turístico y Ecológico del\nCorredor Costero Tijuana-Ensenada... 33.75 UMA\nk).- Por división de predios rústicos, ubicados dentro del área de aplicación del Programa Sectorial de Desarrollo\nUrbano-Turístico de los Valles Vitivinícolas de la Zona Norte del Municipio de Ensenada (región del Vino), B.C... 50.22 UMA\nl).- Por división de predio derivado de un juicio de prescripción positiva o cualquier otra modalidad de juicio donde se dicta sentencia para declarar propietario a otra persona de un polígono inmerso dentro de otro mayor\n(por fracción)..................... 135.00 UMA\nm).- Por cancelación de división de predios, fusión, relotificación y régimen en condominio.......................... 10.80 UMA\nn).- Por oficio rectificatorio de memorias de régimen de condominios, de división de predios, fusión y relotificación por lote o unidad en caso de condominio... 4.00 UMA\no).- Por tercera revisión de proyectos de división de predios, fusión, y relotificación..................... 2.50 UMA\nEl pago de los derechos a que se refieren los incisos a), b), c) y d), de la sección II, los hará el interesado previamente a la iniciación del trámite, según notificación de la Dirección de\nAdministración Urbana, Ecología y Medio Ambiente.\nEl pago de los derechos a que se refieren los incisos e), f), g),\nh), i), j), k), l), m) y n), de la sección II, se hará previa notificación de la Dirección de Administración Urbana, Ecología y\nMedio Ambiente.\nIII.- POR URBANIZACIÓN:\na).- Por supervisión de obras de urbanización realizadas con base en el proyecto de obras, se pagará sobre el importe total de los presupuestos presentados........................ 3.00% a.1) Los fraccionamientos tipo interés social progresivo tendrán un 50% de descuento de estas cuotas, siempre y cuando los urbanizadores sean instituciones gubernamentales, paraestatales y paramunicipales.\nb).- Por supervisión de obras de urbanización en el proyecto de obras actual, se pagará sobre el importe total de los presupuestos presentados.... 3.00% b.1) Los fraccionamientos tipo interés social progresivo tendrán un 50% de descuento de estas cuotas, siempre y cuando los urbanizadores sean instituciones gubernamentales, paraestatales y paramunicipales.\nc).- Por modificación al Acuerdo de fraccionamientos autorizado y publicado en el Periódico Oficial del Gobierno del Estado, por cambio urbanizador y/o nombre del fraccionamiento............. 675.00 UMA c.1) Los fraccionamientos tipo interés social progresivo tendrán un 50% de descuento de estas cuotas, siempre y cuando los urbanizadores sean instituciones gubernamentales, paraestatales y paramunicipales.\nd).- Por el dictamen de recepción de fraccionamientos, realizado con base en el proyecto de obra de urbanización se pagará sobre el costo total de obra, el...................................... 4.05\nAL MILLAR\ne).- Por la revisión de proyecto y recepción de redes de alumbrado público de fraccionamientos, pagará por luminaria................................ 1.35 UMA\nf).- Prórroga de permiso de fraccionamiento por 2 años........................................ 94.50 UMA\ng).- Multa por no haber solicitado prórroga del fraccionamiento en tiempo, por cada 2 años a de autorización del fraccionamiento en el\nBaja California............................ 135.00 UMA\nh).- Multa por iniciar cualquier acción de urbanización tipo fraccionamiento, colonia, calles o lotificaciones sin contar con los permisos y/o licencias correspondientes. h.1) Con superficie de hasta 5 hectáreas... 270.00 UMA h.2) Por cada hectárea excedente de las primeras 5 hectáreas................... 81.00 UMA\nEl pago de la sección III, a que se refieren los incisos a) y b) se harán una vez aprobados los proyectos previa notificación de la Dirección de Administración Urbana, Ecología y Medio\nAmbiente. Los incisos c) y d) se harán una vez aprobados los proyectos, previa notificación de la Dirección de Infraestructura, en ambos casos los proyectos deberán ser aprobados por el\nH. Ayuntamiento de Ensenada, quien otorgará la autorización definitiva.\nEn el caso de no enterar los derechos correspondientes en la Dirección de Recaudación, en un plazo de veinte días a partir de la fecha de su notificación, se suspenderá el trámite correspondiente.\nIV.- POR CERTIFICACIÓN DE MEMORIAS DESCRIPTIVAS\na).- Por verificación y certificación de memorias descriptivas de lotes pertenecientes a fraccionamientos, se pagará por cada revisión, en la forma siguiente:\n1.- Hasta 100 lotes.......................... 67.50 UMA\n2.- Por cada lote que exceda de 100 lotes.... 1.35 UMA\n3.- Para los predios ubicados en fraccionamientos o asentamientos humanos que sean previamente clasificados como TIPO POPULAR y que sean notificados por el Instituto Nacional del\nSuelo Sustentable (INSUS) en proceso de regularización del suelo con base en el convenio de colaboración con el Ayuntamiento de\nEnsenada, B.C. que se encuentre vigente, estarán exentos del pago de los conceptos de este apartado............................. 0.00 UMA\nV.- POR ANÁLISIS DE PREDIO PARA FACTIBILIDAD; LAS AUTORIDADES DE\nLOS TRES ÓRDENES DE GOBIERNO ESTARÁN EXENTAS DE PAGO DE LOS\nCONCEPTOS DE ESTE APARTADO, ASÍ COMO LAS INSTITUCIONES\nEDUCATIVAS Y ASOCIACIONES DE LA SOCIEDAD CIVIL SIN FINES DE\nLUCRO.\n1.- Por análisis y emisión de factibilidad de uso de suelo por verificación de:\na).- Compatibilidad:\n1. Dentro del centro de población de la ciudad de Ensenada, conforme a lo establecido en el\nPrograma de Desarrollo Urbano del Centro de\nPoblación de Ensenada........................ 7.00 UMA\n2. Fuera del centro de población de la ciudad de Ensenada, conforme a lo establecido en el\nPrograma de Desarrollo Urbano del Centro de\nPoblación de Ensenada........................ 9.00 UMA\nb).- Congruencia: de construcción será la superficie del predio, y cuando se superficie arrendada.\n1. Para uso habitacional, comercio y servicios, talleres, bodegas y almacenes, no considerados como uso industrial:\n1.1) Hasta 1,000 m² de superficie del predio.............................. 9.00 UMA\n1.2) Mayor de 1,000 a 5,000 m² de sup. del predio............................. 11.00 UMA\n1.3) Mayor de 5,000 a 10,000 m² de sup. del predio............................. 13.00 UMA\n1.4) Mayor de 10,000 m² de sup. del predio............................. 15.00 UMA\n2. Para educación y cultura, salud, servicios asistenciales, deporte y recreación.......... 9.00 UMA\n3. Para industria extractiva, manufacturera, de transformación, agroindustria; yonques y deshuesaderos, centros de acopio, recicladoras y predios destinados al almacenaje de contenedores, tractocamiones y las cajas de estos:\n3.1) Hasta 1,000 m² de superficie del predio............................ 12.00 UMA\n3.2) Mayor de 1,000 a 5,000 m² de sup. del predio............................ 15.00 UMA\n3.3) Mayor de 5,000 a 10,000 m² de sup. del predio............................ 18.00 UMA\n3.4) Mayor de 10,000 m² de sup. del predio............................ 30.00 UMA\n4. Especial, distribución de gas butano, gasolineras, centros de carburación y/o almacén de hidrocarburos, plantas, estaciones y subestaciones, plantas de tratamiento, cárcamos, bombas, rellenos sanitarios, presas, plantas desaladoras, etc:\n4.1) Hasta 1,000 m² de superficie del predio............................ 20.00 UMA\n4.2) Mayor de 1,000 a 5,000 m² de sup. del predio............................ 25.00 UMA\n4.3) Mayor de 5,000 a 10,000 m² de sup. del predio............................ 30.00 UMA\n4.4) Mayor de 10,000 m² de sup. del predio............................ 35.00 UMA\n5. Centros de apuestas, apuestas remotas, salas de sorteos de números y/o casinos, libro foráneo y similares:\n5.1) Hasta 3,000 m² de superficie.......... 20.00 UMA\n5.2) De 3,001 m² de terreno en adelante........................... 30.00 UMA\nc).- Congruencia en zona federal............... 14.00 UMA\nd).- Congruencia temporal...................... 12.00 UMA\ne).- Congruencia para giros ingresados por el Sistema de Apertura Rápida de Empresas (SARE), hasta por\n200m² de construcción (aplica solo para permisos de operación).............................. 0.00 UMA\nf).- Por la tercera revisión................... 1.35 UMA\nSe paga al ingresar documentos por revisión.\ng).- Por revisiones subsecuentes a partir de la cuarta revisión............................ 2.70 UMA\nSe paga al ingresar documentos por revisión.\nh).- Constancia de uso de suelo conforme al Plan y/o\nPrograma de Desarrollo Urbano aplicable:\n1. Dentro del centro de población de la ciudad de Ensenada, conforme a lo establecido en el\nPrograma de Desarrollo Urbano del Centro de\nPoblación de Ensenada................... 5.00 UMA\n2. Fuera del centro de población de la ciudad de\nEnsenada, conforme a lo establecido en el\nPrograma de Desarrollo Urbano del Centro de\nPoblación de Ensenada................... 7.00 UMA\ni).- Contestación en relación al derecho de preferencia a que hacen referencia la Ley Agraria y la\nLey General de Asentamientos Humanos....... 5.00 UMA\nVI.- POR ANÁLISIS DEL SUELO Y USO DE EDIFICIO: LAS AUTORIDADES DE\nLOS TRES ÓRDENES DE GOBIERNO ESTARÁN EXENTAS DE PAGO\nDE LOS CONCEPTOS DE ESTE APARTADO, ASÍ COMO LAS\nINSTITUCIONES EDUCATIVAS Y ASOCIACIONES DE LA SOCIEDAD\nCIVIL SIN FINES DE LUCRO.\na).- Por análisis de dictamen de uso de edificaciones:\n1.- En zonas habitacionales: Construcción de viviendas multifamiliares, condominios, departamentos:\n1) Hasta 500 m² de operación........... 27.00 UMA\n2) Mayor de 500 m² hasta 1,000 m² de operación............................. 40.50 UMA\n3) Mayor de 1,000 m² hasta 5,000 m² de operación............................. 60.75 UMA\n4) Mayor de 5,000 m² de operación........ 81.00 UMA\n2.- En equipamiento y servicios:\nA.- Comercio: Abastos y almacenaje al por menor: depósitos de productos básicos, de materiales de construcción, maquinaria, vehículos, tianguis, saldos, segundas y otros, así como talleres de recepción y servicio, no considerados como de uso industrial:\n1) Hasta 500 m² de operación.......... 27.00 UMA\n2) Mayor de 500 m² hasta 1,000 m² de operación....................... 33.75 UMA\n3) Mayor de 1,000 m² hasta 5,000 m² de operación....................... 47.25 UMA\n4) Mayor de 5,000 m² de operación..... 60.75 UMA\nA.1).- Centro comercial, tiendas de autoservicio y departamentos, tiendas CONASUPO, comercio alimenticio; comercio especializado, tiendas institucionales, supermercados:\n1) Hasta 500 m² de operación......... 29.70 UMA\n2) Mayor de 500 m² hasta 1,000 m² de operación....................... 37.80 UMA\n3) Mayor de 1,000 m² hasta 5,000 m² de operación....................... 51.30 UMA\n4) Mayor de 5,000 m² de operación..... 81.00 UMA\nA.2).- Por uso de suelo: Almacenaje, depósito y/o acopio mayor, superficie para zonas de carga y descarga, depósitos mayores para almacenaje o acopio de sal, minerales, arena, grava y otros materiales en general:\n1) Hasta 5,000 m² de superficie..... 2.70 UMA por tonelada anualmente\n2) De 5,001 a 10,000 m² de superficie... 1.35 UMA por tonelada anualmente\n3) De 10,001 m² en adelante.......... 0.34 UMA por tonelada anualmente\nB.- Educación y Cultura.\nPreescolar, elemental, medio básico, medio superior, instalaciones de investigación y superior, museos, bibliotecas y hemerotecas e instalaciones religiosas:\n1) Hasta 500 m² de operación.......... 13.50 UMA\n2) Mayor de 500 m² hasta 1,000 m² de operación.......................... 14.85 UMA\n3) Mayor de 1,000 m² hasta 5,000 m² de operación....................... 16.88 UMA\n4) Mayor de 5,000 m² de operación.... 21.60 UMA\nC.- Salud y Servicios Asistenciales, hospitales, clínicas, centros de salud o consultorios, asistencia social y asistencia para animales:\n1) Hasta 500 m² de operación.......... 29.03 UMA\n2) Mayor de 500 m² hasta 1,000 m² de operación.......................... 36.45 UMA\n3) Mayor de 1,000 m² hasta 5,000 m² de operación....................... 49.95 UMA\n4) Mayor de 5,000 m² de operación..... 72.90 UMA\n5) En los casos que sean para edificaciones que no persigan fines de lucro se cobrará el 50%.\nD.- Deporte y Recreación.\nParques y jardines: unidades deportivas, clubes y centros deportivos; plazas, zoológicos y balnearios públicos:\n1) Hasta 1,000 m² de operación........ 24.98 UMA\n2) Mayor de 1,000 m² hasta 5,000 m² de operación....................... 29.70 UMA\n3) Mayor de 5,000 m² hasta 10,000 m² de operación....................... 34.43 UMA\n4) Mayor de 10,000 m² de operación.... 43.88 UMA\n5) En los casos que sean para edificaciones que no persigan fines de lucro se cobrará el 50%.\nE.- Servicios administrativos, Administración Pública y Privada:\n1) Hasta 500 m² de operación......... 29.03 UMA\n2) Mayor de 500 m² hasta 1,000 m² de operación....................... 36.45 UMA\n3) Mayor de 1,000 m² de operación..... 49.95 UMA\nF.- Turismo, alojamiento (hoteles y moteles), agencias de viajes, centros vacacionales:\n1) Hasta 1,000 m² de operación....... 29.70 UMA\n2) Mayor de 1,000 m² hasta 5,000 m² de operación....................... 32.67 UMA\n3) Mayor de 5,000 m ²hasta 10,000 m² de operación....................... 40.10 UMA\n4) Mayor de 10,000 m² de operación.... 66.83 UMA\nG.- Servicios Mortuorios, Cementerios; mausoleos y crematorios, agencias de inhumaciones funerarias:\n1) Hasta de 10,000 m² de operación.... 28.35 UMA\n2) Mayor de 1 hasta 10 hectáreas de de operación....................... 33.75 UMA\n3) Mayor de 10 hasta 20 hectáreas de operación....................... 41.18 UMA\n4) Mayor de 20 hectáreas de operación.......................... 57.38 UMA\nH.- Comunicaciones y Transportes, T.V. y radio, telecomunicaciones, correos, telefonía, terminal de transporte urbano (autobús), terminal de transporte foráneo, terminal de ferrocarril, terminal aérea, estacionamientos y apeadero, encierro de transporte:\n1) Hasta de 1,000 m² de operación..... 24.30 UMA\n2) Mayor de 1,000 m² hasta 5,000 m² de operación....................... 27.00 UMA\n3) Mayor de 5,000 m² hasta 10,000 m² de operación...................... 31.05 UMA\n4) Mayor de 10,000 m² de operación.... 39.15 UMA\nI.- Diversión y espectáculos, cines y teatros, auditorios y estadios, centros sociales, centros nocturnos, salón de fiestas, ferias, exposiciones y circos, centros de convenciones, centros de esparcimiento:\n1) Hasta 500 m² de operación.......... 27.00 UMA\n2) Mayor de 500 m² hasta 1,000 m² de operación....................... 33.75 UMA\n3) Mayor de 1,000 m² hasta 5,000 m² de operación....................... 40.50 UMA\n4) Mayor de 5,000 m² hasta 10,000 m² de operación....................... 81.00 UMA\n5) Mayor a 10,000 m² de operación... 108.00 UMA\nJ.- Especial, distribución de gas butano, gasolineras, centros de carburación y/o almacén de hidrocarburos, plantas, estaciones y subestaciones, plantas de tratamiento, cárcamos, bombas, rellenos sanitarios, plantas desaladoras, etc..................... 202.50 UMA\nK.- Sistema de Apertura Rápida de Empresas:\nK.1).- Dictamen de Uso de Suelo, para giros de Empresas (SARE) por superficie de operación que incluye: construcción, estacionamiento, patio de servicio y áreas verdes:\n1) Hasta 50 m² de operación.............. 16.20 UMA\n2) Desde 51 m² hasta 100 m² de operación............................. 20.25 UMA\n3) Desde 101 m² hasta 150 m² de operación............................. 24.30 UMA\n4) Desde 151 m² hasta 200 m² de operación............................. 27.00 UMA\n5) Regularización de comercio, servicios y otros a través del Sistema de Apertura\nRápida de Empresas (SARE), hasta 200 m² de superficie de operación, 50% adicional al costo del trámite normal, por año que se haya encontrado operando.\nb).- En Industria:\n1.- Extractiva: Explotación de minas y canteras; materiales de construcción contaminante, explosiva que genera vehículos hasta de una capacidad máxima de 14 toneladas para el transporte de materias primas y productos terminados:\n1) Hasta 1 hectárea de operación........ 175.50 UMA\n2) Mayor de 1 hectárea hasta 5 hectáreas de operación............... 260.55 UMA\n3) Mayor de 5 hectáreas hasta 10 hectáreas de operación............... 351.00 UMA\n4) Por cada hectárea excedente adicional a lo antes considerado, se cobrarán........................... 54.00 UMA\n2.- Transformación: Fundición de minerales metálicos, fertilizantes, hules y plásticos, petróleos y derivados, papel madera, bloqueras y ladrilleras, alimenticia, bebidas, tabaco, pigmentos, pintura, colorantes y derivados, vidrios, cerámica y derivados:\n1) Hasta 500 m² de operación.......... 35.10 UMA\n2) Mayor de 500 m² hasta 1,000 m² de operación.......................... 45.90 UMA\n3) Mayor de 1,000 m² hasta 5,000 m² de operación...................... 56.70 UMA\n4) Mayor de 5,000 m² de operación........ 81.00 UMA\n3.- Manufacturera, máquinas y herramientas, textiles e industrias de cueros de la madera, productos de papel, ensamble de aparatos eléctricos o electrónicos; maquiladoras de otros tipos y predios destinados al almacenamiento de contenedores, tractocamiones y sus cajas:\n1) Hasta 500 m² de operación............ 35.10 UMA\n2) Mayor de 500 m² hasta 1,000 m² de operación............................. 45.90 UMA\n3) Mayor de 1,000 m² hasta 5,000 m² de operación.......................... 56.70 UMA\n4) Mayor de 5,000 m² de operación........ 81.00 UMA\n4.- Agroindustria, envases y empaques; forrajes y otras:\n1) Hasta 1,000 m² de operación........... 29.03 UMA\n2) Mayor de 1,000 m² hasta 5,000 m² de operación............................ 37.80 UMA\n3) Mayor de 5,000 m² de operación........ 45.90 UMA\nc).- Infraestructura e instalaciones como:\nPlantas, estaciones y subestaciones; torres y antenas; depósitos, cárcamos y bombas:\n1) Hasta 1,000 m² de operación.............. 33.75 UMA\n2) Mayor de 1,000 m² de operación........... 40.50 UMA\nd).- En otros usos como:\nActividades agropecuarias, cauces y cuerpo de agua, deshuesadero (yonques):\n1) Hasta 1 hectárea de operación............. 52.65 UMA\n2) Mayor de 1 hectárea de operación.......... 58.05 UMA\ne).- Centros de apuestas, apuestas remotas, salas de sorteos de números y/o casinos, libro foráneo y similares: e.1) Hasta 3,000 m² de superficie........... 675.00 UMA e.2) De 3,001 m² de terreno en adelante.......................... 1,012.50 UMA e.3) A las cuotas indicadas se les acumulará por cada kilómetro de distancia al centro de población de la cabecera municipal................................ 2.16 UMA\nf).- En zonas localizadas fuera de las manchas urbanas, donde existan oficinas, residencia o sub-residencia de la dependencia:\n1).- Por dictamen se cobrará lo que marcan los números anteriores más $ 1.20 para cada kilómetro fuera de la ciudad, en donde existan oficinas, residencia o sub-residencia de la dependencia.\ng).- Por expedición de documentos, constancias y dictámenes de la Dirección de Administración Urbana, Ecología y Medio Ambiente:\n1).- Constancia de condición de inmueble apta o no apta para su uso............... 4.05 UMA\n2).- Verificación de cumplimiento de requisitos para traslación de dominio en fraccionamientos, cada vez que se solicite................ 47.25 UMA\n3).- Verificación de cumplimiento de requisitos para traslación de dominio en condominios, cada vez:\na).- Por conjuntos hasta de 10 unidades.. 17.55 UMA\nb).- Por cada unidad excedente de las diez primeras....................... 1.35 UMA\n4).- Verificación para cancelación de fianza de fraccionamientos, cada vez... 60.75 UMA\n5).- Verificación de fianza de condominios, cada vez................... 20.25 UMA\n6).- Asignación y expedición de número oficial:\na).- En lote habitacional interés social o popular.................... 6.75 UMA\nb).- En lote habitacional residencial.. 10.00 UMA\nc).- En lote habitacional residencial en régimen de condominio ubicados dentro de la zona del COCOTREN..... 15.00 UMA\nd).- En lote habitacional campestre o granjas.......................... 12.00 UMA\ne).- En lote habitacional industrial, comercial o mixto.................. 17.00 UMA\nf).- Por número oficial urgente se pagará el doble dependiendo el tipo de lote.\n7).- Certificado de Alineamiento.............. 3.38 UMA\nh).- Cuando el dictamen de uso de suelo se solicite para regularización de construcción, ampliación, o instalación, el dictamen tendrá un costo adicional del\n50%.\ni).- Cuando la asignación y expedición de número oficial corresponda a predio ubicado en fraccionamientos o asentamientos humanos que sean previamente clasificados como TIPO POPULAR y que sean notificados por el Instituto Nacional del Suelo Sustentable (INSUS) en proceso de regularización del suelo con base en el convenio de colaboración con el Ayuntamiento de Ensenada, B.C. que se encuentre vigente, estarán exentos del pago de los conceptos de este apartado............. 0.00 UMA\nVII.- POR EXPEDICIÓN DE DOCUMENTOS CONSTANCIAS Y DICTÁMENES DE\nLA DIRECCIÓN DE ADMINISTRACIÓN URBANA, ECOLOGÍA Y MEDIO\nAMBIENTE:\na).- Copias simples de planos oficiales o autorizados de desarrollos urbanos, ejidos, colonias agrícolas o mosaicos rústicos, de centros urbanos, programas cartográfico oficial en formato 90x60 cm, por plano........................................ 6.50 UMA a.1).- Copias simples de planos oficiales o autorizados de desarrollos urbanos, ejidos, colonias agrícolas o mosaicos rústicos, de centros urbanos, programas de centro de población que conformen el archivo cartográfico oficial en formato doble carta, por plano................................. 2.70 UMA\nb).- Certificación de copias de planos oficiales o autorizados de desarrollos urbanos, ejidos, colonias agrícolas o mosaicos rústicos, de centros urbanos, programas de centro de población que conformen el archivo cartográfico oficial en formato 90x60 cm, por plano.................. 9.60 UMA b.1).- Certificación de copias de planos oficiales o autorizados de desarrollos urbanos, ejidos, colonias agrícolas o mosaicos rústicos, de centros urbanos, programas de centro de población que conformen el archivo cartográfico oficial en formato doble carta, por plano................ 7.50 UMA\nc).- Copia certificada de deslinde o levantamiento catastral.................................... 7.50 UMA\nd).- Copias certificadas de documentos por página...0.85 UMA\ne).- Copias simples de documentos catastrales por página....................................... 0.30 UMA\nf).- Constancia de registro catastral, con datos básicos actuales administrativos y de ubicación, por predio y/o memoria descriptiva.................................. 4.15 UMA\ng).- Historial registral de un predio urbano dentro de desarrollos autorizados, por registro catastral........................... 8.78 UMA g.1).- Historial registral de un predio suburbano, rústico o rural, por registro catastral................... 13.75 UMA\nh).- Constancia de las condiciones de uso, físicas, de ubicación y accesibilidad previa verificación física, por predio....... 7.25 UMA\ni).- Constancia de no propiedad................... 2.03 UMA\nj).- Constancia de antigüedad de construcción..... 3.00 UMA\nk).- Constancia de uso de suelo registrado y/o uso oficial o autorizado por autoridad competente, por predio....................... 7.00 UMA\nl).- Análisis y aplicación de ajuste del valor unitario de predios suburbanos y rurales, por predio.................................. 12.00 UMA\nm).- Por expedición de constancias de valor catastral de conformidad a la tabla de valores publicada............................ 7.00 UMA\nn).- Cálculo para aplicar los factores de demérito en predios urbanos, por predio..... 16.50 UMA ñ).- Verificación en campo del uso de suelo en predios, por predio:\n1.- Uso habitacional........................ 12.00 UMA\n2.- Uso comercial........................... 18.00 UMA\n3.- Uso industrial.......................... 20.00 UMA\nPor el registro de construcciones mayores a 100 metros cuadrados de construcción se cobrará el metro excedente, de la siguiente manera:\n1.- Uso habitacional por metro cuadrado de construcción................. 0.12 UMA\n2.- Uso comercial por metro cuadrado de construcción................. 0.17 UMA\n3.- Uso industrial por metro cuadrado de construcción................. 0.20 UMA\no).- Certificado de libertad de gravámenes fiscales..................................... 6.00 UMA o.1- Para predios ubicados en fraccionamientos o asentamientos humanos que sean previamente clasificados como\nTIPO POPULAR y que sean notificados por el Instituto Nacional del Suelo\nSustentable (INSUS) en proceso de regularización del suelo con base en el convenio de colaboración con el\nAyuntamiento de Ensenada, B.C. que se encuentre vigente, estarán exentos del pago del concepto de este apartado, por única vez para efectos de alta del registro catastral...................... 0.00 UMA\np).- Asignación de clave catastral urbana en nuevos fraccionamientos..................... 10.80 UMA p.1).- La asignación de clave catastral urbana para fraccionamientos o asentamientos humanos que sean previamente clasificados como TIPO\nPOPULAR y que sean notificados por el Instituto Nacional del Suelo\nSustentable (INSUS) en proceso de regularización del suelo con base en el convenio de colaboración con el Ayuntamiento de Ensenada, B.C. que se encuentre vigente, estarán exentos del pago del concepto de este apartado, por única vez para efectos de alta del registro catastral................. 0.00 UMA p.2).- La asignación de clave catastral urbana para fraccionamientos o asentamientos humanos que sean previamente clasificados como TIPO\nPOPULAR, y que sean desarrollados o regularizados por organismos gubernamentales, paraestatales o paramunicipales tendrán un 50% de descuento.\nq).- Por apertura de expedientes en fraccionamientos o condominios nuevos autorizados, por predios o cuentas catastrales nuevas hasta 250 registros.......................... 2.45 UMA q1).- Por apertura de expedientes en fraccionamientos o condominios nuevos autorizados, por predios o cuentas catastrales nuevas de 251 registros en adelante............................ 4.00 UMA q2).- Por apertura de expediente (cuenta catastral nueva) derivada de título o sentencia emitida por la autoridad competente por predio o cuenta catastral.............................. 3.45 UMA q3).- Para predios ubicados en fraccionamientos o asentamientos humanos que sean previamente clasificados como\nTIPO POPULAR y que sean notificados por el Instituto Nacional del Suelo\nSustentable (INSUS) en proceso de regularización del suelo con base en el convenio de colaboración con el\nAyuntamiento de Ensenada, B.C. que se encuentre vigente, estarán exentos del pago del concepto de este apartado, por única vez para efectos de alta del registro catastral......... 0.00 UMA q4).- Para predios ubicados en fraccionamientos o asentamientos humanos que sean previamente clasificados como\nTIPO POPULAR, y que sean desarrollados o regularizados por organismos gubernamentales, paraestatales o paramunicipales tendrán un 50% de descuento.\nr).- Por modificación de expedientes derivados de relotificaciones en fraccionamientos o condominios autorizados sobre predios propiedad del fraccionador, por predios o cuentas catastrales hasta 250 registros...... 3.15 UMA r1).- Por modificación de expedientes derivados de relotificaciones en fraccionamientos o condominios autorizados sobre predios propiedad del fraccionador, por predios o cuentas catastrales de 251 registros en adelante............................ 3.65 UMA\ns).- Constancia en relación con los desarrollos urbanos...................................... 8.20 UMA\nt).- Copia de información catastral computarizada certificada............................. 5.40 UMA\nu).- Por análisis, dictámenes y registro catastral provisional de POSESIONES en asentamientos humanos consolidados no autorizados (no se crea derecho de propiedad) por predio........................ 6.75 UMA u.1).- Por análisis, dictámenes y registro catastral provisional de POSESIONES de predios urbanos, suburbanos, rústicos o rurales sin antecedentes registrales (no se crea derecho de propiedad), por predio............... 13.50 UMA\nv).- Rectificación, modificación o actualización de la base de datos, referente a los atributos estadísticos, jurídicos de propiedad, técnicos, fiscales de valor, ubicación de un predio....................... 3.65 UMA v.1).- Para predios ubicados en fraccionamientos o asentamientos humanos que sean previamente clasificados como\nTIPO POPULAR y que sean notificados por el Instituto Nacional del Suelo\nSustentable (INSUS) en proceso de regularización del suelo con base en el convenio de colaboración con el Ayuntamiento de Ensenada, B.C. que se encuentre vigente, estarán exentos del pago del concepto de este apartado, por única vez para efectos de alta del registro catastral............................. 0.00 UMA v.2).- Para predios ubicados en fraccionamientos o asentamientos humanos que sean previamente clasificados como\nTIPO POPULAR, y que sean desarrollados o regularizados por organismos gubernamentales, paraestatales o paramunicipales tendrán un 50% de descuento por única vez para efectos de regularización o alta del registro catastral.\nw).- Las personas físicas de escasos recursos, que utilicen los servicios de la\nDefensoría de Oficio, en la tramitación de procedimientos judiciales, civiles y penales, previo estudio socioeconómico, que elabore la Dirección de Educación, Cultura y Asistencia Social, se les exentará del pago de los derechos por el servicio de\nCertificado de Libertad de Gravámenes\nFiscales, a solicitud expresa del titular de la Defensoría de Oficio, esta exención será otorgada al interesado por única ocasión.\nx).- Para la obtención de los documentos de los incisos anteriores con carácter de urgente, en tiempos menores de lo que requiere el trabajo normal se les incrementará un 50% en el pago de los derechos normales de los mismos.\nVIII.- POR TRABAJOS TÉCNICOS:\nA).- Análisis, cálculo y certificación de cartograma para certificación catastral, se pagará:\nPARA PREDIOS CON SUPERFICIES:\nMAYORES DE HASTA UMA\n100-00-00 HAS 250-00-00 HAS 205.40 UMA\n250-00-00 HAS 500-00-00 HAS 245.70 UMA\n500-00-00 HAS 1,000-00-00 HAS 286.00 UMA\nB).- Certificación de deslindes y levantamiento hasta\n180 m²..................................... 12.00 UMA\nC).- Los deslindes y levantamientos urgentes, pagarán adicionalmente sobre el costo del importe normal, un 100% más.\nD).- Los predios que excedan a 1,000 HAS, serán presentados por la Dirección de Administración Urbana, Ecología y Medio Ambiente, previa Solicitud del interesado.\nE).- Derechos de liga al Sistema Oficial......... 6.50 UMA\nF).- Copia de cédula de información de vértices del\nSistema Municipal de Coordenadas............ 1.63 UMA\nG).- Registro de peritos deslindadores:\nG.1).- Registro inicial (alta)............. 39.00 UMA\nG.2).- Revalidación anual dentro de los 3 primeros meses del año en curso................20.80 UMA\nG.3).- Multa por revalidación extemporánea adicionalmente al pago del inciso anterior............................ 16.20 UMA revalidación anual de perito deslindador, el beneficiario deberá fiscal 2025.\nH).- Para efecto de cubrir los derechos de admisión a examen teórico y práctico como perito deslindador................................ 11.15 UMA\nI).- Los trabajos de levantamiento, deslinde y estudio, cálculo y verificación física de planos, para efectos de certificaciones catastrales en zonas donde no exista oficina de Administración\nUrbana, Ecología y Medio Ambiente, causará una cuota adicional, equivalente a los gastos de transporte, alojamiento y alimentación del personal que se utilice.\nJ).- Análisis de deslinde por segunda revisión.... 2.00 UMA\nIX.- SERVICIOS DERIVADOS DEL SISTEMA DE INFORMACIÓN GEOGRÁFICA\n(PRODUCTOS CATASTRALES Y SERVICIOS CARTOGRÁFICOS)\n1.- CARTOGRAFÍA URBANA DIGITAL\n1.1.- Archivo de cartografía digital por zona catastral urbana en formatos DWG o DXF o SHAPE con información básica(traza de manzanas y lotes, nomenclatura de manzana, lote y vialidades),por archivo.. 10.80 UMA\n1.2.- Archivo de cartografía digital por zona catastral urbana en formato PDF (no editable) con información básica(traza de manzanas y lotes, nomenclatura de manzana, lote y vialidades), por archivo.. 5.40 UMA\n1.3.- Archivo de cartografía digital por zona catastral urbana en formatos DWG o DXF o SHAPE con información básica(traza de manzanas y lotes, nomenclatura de predios, superficie y clave catastral), por archivo............................. 13.50 UMA\n1.4.- Archivo de cartografía digital por zona catastral urbana en formato PDF (no editable) con información básica (traza de manzanas y lotes, nomenclatura de predios, superficie y clave catastral), por archivo.............................. 6.75 UMA\nX.- POR VERIFICACIÓN Y CERTIFICACIÓN DE FACTIBILIDAD PARA LA\nINSTALACIÓN, REVALIDACIÓN ANUAL Y REGULARIZACIÓN DE RÓTULOS,\nANUNCIOS Y SIMILARES; ASÍ COMO MESAS Y SILLAS, EXCEPTUANDO\nLA PROPAGANDA EFECTUADA POR PARTIDOS POLÍTICOS, SIEMPRE QUE\nNO SE DERIVE A TERCEROS; SE PAGARÁ POR PERIODO ANUAL,\nEXCEPTUANDO LOS PERMISOS QUE SERÁN POR DÍA, PREVIO AL INICIO\nDEL TRÁMITE POR SUPERFICIE O CANTIDAD, SEGÚN SE INDIQUE\nDE ACUERDO A LA SIGUIENTE TABLA:\nA.- Licencia nueva con vigencia al ejercicio fiscal en curso\n(a diciembre), independientemente de la fecha de ingreso\nY permisos por día, cuando la instalación se efectúe después que sea emitida la licencia o permiso. Se entiende por permiso la autorización temporal que se paga por día y que no excede de un período de tres meses. Mientras que la licencia se paga por anualidad.\nEstarán EXENTOS de los conceptos 1, 2, 3, 4 y 6b, del presente inciso, la propaganda efectuada en propiedad privada con publicidad de establecimiento y/o negocio, y/o giro comercial ubicado en la propiedad que se publicite, con superficie de hasta 3 m², siempre que no se derive a terceros. Así como la publicidad promovida por Instituciones Educativas, de gobierno, asociaciones de la sociedad civil sin fines de lucro, para eventos de apoyo a la comunidad y la publicidad con información gubernamental de la Federación, Estado o\nMunicipio.\n1.- Permiso posters de pared o adosados......................... 0.20 UMA por m² por día\n2.- Licencia anuncio adosado en propiedad privada:\na).- Sin iluminación....................... 4.05 UMA por m²\nb).- Con iluminación....................... 5.40 UMA por m²\nc).- Sin iluminación para el Sistema de\nApertura Rápida de Empresas durante el primer año................. 2.03 UMA por m²\nd).- Con iluminación para el Sistema de\nApertura Rápida de Empresas durante el primer año................. 2.70 UMA por m²\n3.- Licencia rótulos:\n3.1 Sin iluminación........................ 2.70 UMA por m²\n3.2 Con iluminación........................ 5.40 UMA por m²\n4.- Licencia rótulos electrónicos............................... 6.75 UMA por m²\n5.- Licencia anuncio tipo bandera o paleta:\na).- Pintado............................... 4.05 UMA por m² por lado.\nb).- Luminosos............................. 5.40 UMA por m² por lado.\n6.- Permisos de lonas o Mantas:\na).- En vía pública por un período máximo de 15 días (no incluye instalación, ni retiro).............. 0.41 UMA por m² por día\nb).- Adosados en propiedad privada (no incluye instalación, ni retiro).... 0.20 UMA por m² por día\nc).- En vía pública por un periodo máximo de 15 días para eventos sin fines de lucro por asociaciones civiles, que no se derive a terceros, (no incluye instalación ni retiro)... 0.14 UMA por m² por día\nd).- Instalación y retiro de mantas por personal del\nAyuntamiento en vía pública........ 20.25 UMA por pieza\n7.- Por mampara en camellón central de no más de 2 m de altura por 1.20 metros de ancho, a una distancia no menor de 3 metros de la esquina del mismo....................... 6.75 UMA por unidad\n8.- Para instalación de torre fija, tipo directorio para instalación de anuncios diversos por ambos lados........... 8.00 UMA por m²\n9.- Mini porta cartel direccional exclusivamente para desarrollos habitacionales e industriales nuevos................... 10.13 UMA por pieza por 90 días\n10.- Cobertizo publicitario y/o mobiliario urbano con publicidad con fines comerciales (banca publicitaria, bote de basura o buzón con publicidad, etc.)...... 8.10 UMA por unidad\n11.- Carro de sonido.......................... 10.80 UMA por unidad por 90 días\n12.- Torreta en techo de camión o taxi........ 10.80 UMA por unidad\n13.- Rótulo en vehículo....................... 10.13 UMA por unidad\n14.- Instalación de áreas con mesas, sillas y bancas, incluyendo estructuras y elementos que delimiten la ocupación de la vía pública. Estas instalaciones en ningún caso podrán ser fijas y deberán ser desmontadas, cuando la autoridad previo aviso lo solicite:\na).- En zona comercial y turística, comprendida entre el perímetro formado por el Bulevar Teniente\nAzueta, Avenida Ryerson, Calle\nNovena, Avenida Floresta y Avenida\nClub Rotario................ 21.60 UMA por m²\nb).- Fuera de la zona comercial y turística, definida en el inciso anterior.................... 10.80 UMA por m²\n15.- Licencia anuncio tipo tripié........... 13.50 UMA por pieza\n16.- Permiso de pendón o cartel en poste de hasta 1.00 metro cuadrado de superficie (no incluye instalación o retiro).... 0.14 UMA por pieza por día\n17.- Permiso volantes:\na).- Vigencia por un período de 15 días naturales............................ 5.40 UMA\nb).- Vigencia por un período mayor de 15 días naturales hasta 30 días en ubicación fija...................... 10.80 UMA\nc).- Vigencia por un período mayor de 15 días naturales en zona habitacional, colonia o fraccionamiento….......... 20.25 UMA\nd).- Volantes a beneficio de la comunidad... EXENTOS\n18.- Permiso figura inflable con publicidad.\n.................................. 4.73 UMA por día\na) Vigencia por un período de 1 a 5 días naturales.............................. 4.05 UMA\nb) Vigencia por un período de 6 a 15 días naturales............................. 13.50 UMA\nc) Vigencia por un período de 16 a 30 días naturales........................ 32.40 UMA\nd) Después de 30 días naturales por día adicional.............................. 0.68 UMA\n19.- Licencia anuncio tipo cartelera y/o espectacular (con o sin iluminación) por unidad............................. 2.70 UMA por m²\nLa superficie base para el cálculo del cobro se realizará considerando la totalidad de la superficie a exponer publicidad.\n20.- Anuncio tipo espectacular de pantalla electrónica y/o electromecánico o digital, con o sin movimiento (por cartelera y/o estructura)\na) Para uso exclusivo del comercio establecido en el mismo predio a publici- tar.................................... 8.10 UMA por m² por lado\nb) Para publicitar a terceros\n13.50 UMA por m² por lado\n21.- Valla publicitaria por metro cuadrado\n(con o sin iluminación)............ 2.03 UMA por m²\nLa superficie base para el cálculo del cobro se realizará considerando la totalidad de la superficie a exponer publicidad.\n22.- Publicidad móvil remolcada en cualquier modalidad, ya sea valla, cartelera giratoria, digital, etc.\na).- Con vehículo de tracción motriz de cuatro ruedas o más................ 49.95 UMA\nb).- Con vehículo de tracción motriz o no motriz menor a cuatro ruedas........ 20.25 UMA\n23.- Publicidad aérea, en esferas, dirigibles, globos aerostáticos o banderas en el cielo, por pieza.\na).- Vigencia por un período de 1 día..... 4.05 UMA\nb).- Vigencia por un período de 1 a 5 días naturales...................... 13.50 UMA\nc).- Vigencia por un período de 6 a 15 días naturales...................... 32.40 UMA\nd).- Vigencia por un período de 16 a 30 días naturales...................... 48.60 UMA\ne).- Después de 30 días, por día adicional............................... 0.68 UMA\n24.- Publicidad en vía pública mediante botargas, flechas y otros elementos, operado por una persona, por pieza.\na).- Vigencia por un período de 1 día.... 4.05 UMA\nb).- Vigencia por un período de 1 a 5 días naturales...................... 13.50 UMA\nc).- Vigencia por un período de 6 a 15 días naturales...................... 32.40 UMA\nd).- Vigencia por un período de 16 a 30 días naturales...................... 48.60 UMA\ne).- Después de 30 días, por día adicional............................ 0.68 UMA\n25.- Licencia de anuncio tipo banderola o gallardete............................... 10.80 UMA por pieza\n26.- Instalación y/o ocupación en vía pública temporal con almacén móvil, mesas, exhibición de mercancía, aplica únicamente para vía pública colindante a predio o local establecido del solicitante:\na).- En zona comercial y turística comprendida en el inciso a) del punto 14 anterior............. 2.03 UMA por m² por cada 7 días\nb).- Fuera de la zona comercial y turística comprendida en el inciso\na) del punto 14 anterior...... 1.01 UMA por m² por cada 7 días\nc).- En zona comercial y turística comprendida en el inciso a) del punto 14 anterior............. 2.70 UMA por m² por cada 90 días\nd).- Fuera de la zona comercial y turística comprendida en el inciso\na) del punto 14 anterior...... 1.35 UMA por m² por cada 90 días\nEstarán EXENTOS, los primeros 5m² de superficie de los rótulos y anuncios de pared o adosados pintados no luminosos, en propiedad privada con superficie de hasta 1m², y hasta de 5m² en trámites realizados vía Sistema de Apertura Rápida de Empresas, la renovación será considerada por concepto normal.\nB.- Revalidación anual de licencia, a pagarse en los tres primeros meses del año, al verificarse que aún se cumplen los requisitos de reglamento, con vigencia al ejercicio fiscal en curso (a diciembre).\n1.- Anuncios de pared o adosados:\na).- Pintados....................... 2.03 UMA por m²\nb).- Luminosos...................... 2.70 UMA por m²\nc).- Pintados para el Sistema de Apertura Rápida de Empresas (SARE)... 1.35 UMA por m² por lado\nd).- Luminoso para el Sistema de Apertura Rápida de Empresas (SARE).... 2.03 UMA por m² por lado\n2.- Rótulos sin iluminación............. 1.35 UMA por m²\n3.- Rótulos con iluminación............. 2.70 UMA por m²\n4.- Licencia rótulos electrónicos....... 3.38 UMA por m²\n5.- Licencia anuncio tipo bandera o paleta.\na) Pintado.......................... 2.03 UMA por m² por lado\nb) Luminosos........................ 2.70 UMA por m² por lado\n6.- Para instalación de torre fija, tipo directorio para instalación de anuncios diversos, por ambos lados........... 4.00 UMA por m²\n7.- Cobertizo publicitario y/o mobiliario urbano con publicidad, con fines comerciales (banca publicitaria, bote de basura o buzón con publicidad, etc.)...... 5.40 UMA por pieza\n8.- Torreta en techo de camión o taxi.......... 5.40 UMA por unidad\n9.- Rótulo publicitario en vehículo.......... 5.06 UMA por unidad\n10.- Instalación de áreas con mesas, sillas y bancas, incluyendo estructuras y elementos que delimiten la ocupación de la vía pública. Esta licencia en particular podrá pagarse proporcional a los meses que se consideren turísticos del año. En ningún momento podrán ser fijas y deberán ser desmontadas, cuando la autoridad previo aviso lo solicite:\na).- En zona comercial y turística comprendida entre el perímetro formado por el Bulevar Lázaro Cárdenas, Bulevar Teniente Azueta, Avenida\nRyerson, Calle Novena, Avenida\nFloresta y Avenida Club\nRotario....................... 10.80 UMA por m²\nb).- Fuera de la zona comercial y turística definida en el inciso a), anterior....................... 5.40 UMA por m²\n11.- Anuncio tipo tripié....................... 6.75 UMA\n12.- Licencia anuncio tipo cartelera y/o espectacular (con o sin iluminación) por unidad.............................. 1.35 UMA por m²\nLa superficie base para el cálculo del cobro se realizará considerando la totalidad de la superficie a exponer publicidad.\n13.- Anuncio tipo espectacular de pantalla electrónica y/o electromecánico o digital, con o sin movimiento (por cartelera y/o estructura):\na) Para uso exclusivo del comercio establecido en el mismo predio a publi- citar............................. 4.05 UMA por m² por lado\nb) Para publicitar a terceros....... 6.75 UMA por m² por lado\n14.- Valla publicitaria por metro cuadrado\n(con o sin iluminación)............ 1.02 UMA por m²\n15.- Publicidad móvil remolcada en cualquier modalidad, ya sea valla, cartelera giratoria, digital, etc:\na) Con vehículo de tracción motriz de cuatro ruedas o más.................... 24.30 UMA\nb) Con vehículo de tracción motriz o no motriz menor a cuatro ruedas........... 10.13 UMA\nC.- La regularización de cualquier licencia, es decir cuando se encuentren anuncios fijos instalados o publicitándose, se incrementará en 50% de las tarifas\n28 de esta Ley, independientemente de las multas a las que se hagan acreedores los responsables propietarios. apartado A de la fracción X del artículo 28 de esta ley, se ingrese a partir del mes de junio, se podrá restantes del ejercicio fiscal.\nLos anuncios sin permiso en la vía pública, incluso los adosados a muros, cercos o bardas con paramento hacia la en su caso por personal del Ayuntamiento, sin derecho responsables propietarios.\nLa revalidación anual, se hará en los meses de enero a marzo de cada año, en caso de excederse en este plazo, se podrá hacer acreedor a una multa.\nLas personas físicas, morales o unidades económicas que presten los servicios de publicidad, así como los propietarios de los bienes inmuebles, donde se instalen anuncios y las sucursales de giros comerciales e industriales y de instituciones de crédito, seguros y fianzas, serán solidariamente responsables del pago de las sanciones que se originen con motivo de los anuncios que tengan instalados en esta municipalidad, por violaciones a los Reglamentos relativos.\nXI.- POR ANÁLISIS DE SOLICITUD Y EMISIÓN DE DECLARATORIA PARA LA\nINMUEBLES:\na).- Por análisis y dictamen de factibilidad de constitución del régimen sobre conjuntos sin construir, habitacionales, comerciales o mixtos, únicos que estarán bajo el régimen de propiedad en condominio:\n1.- Por conjuntos hasta de 10 unidades....... 20.25 UMA\n2.- Por cada unidad excedente de las diez primeras............................. 1.35 UMA\nb).- Por análisis y dictamen de factibilidad de constitución del régimen sobre conjuntos sin construir, habitacionales, comerciales o mixtos, que se utilizarán un solo conjunto inmobiliario, se pagará por el el diez por ciento de estas para las subsecuentes.\nc).- Por análisis y dictamen de factibilidad de conversión al conjuntos habitacionales, comerciales o mixtos, ya construidos, se pagará:\n1.- Por conjuntos hasta de diez unidades................................. 27.00 UMA\n2.- Por cada unidad excedente de las diez primeras...................... 1.35 UMA c.1).- En caso de que el conjunto condominal se localice fuera de los límites de los centros de población, las tarifas indicadas en los incisos a), b) y c), se incrementarán en un veinticinco por ciento.\nd).- Por la declaratoria de factibilidad para la constitución del régimen de propiedad en condominio de inmuebles, se pagará por cada unidad, departamento, vivienda, casa o local en la forma siguiente:\n1.- Por cada unidad habitacional de tipo interés social...................... 2.70 UMA\n2.- Por cada unidad habitacional de tipo popular............................. 4.05 UMA\n3.- Por cada unidad habitacional de tipo nivel medio......................... 4.73 UMA\n4.- Por cada unidad habitacional de tipo nivel residencial................... 8.10 UMA\n5.- Por cada unidad comercial o industrial.............................. 21.60 UMA\ne).- Por verificación y certificación de memorias descriptivas de departamentos, viviendas, casas o locales, pertenecientes a condominios, se pagará por la primera revisión en la forma siguiente:\n1.- Hasta diez unidades...................... 27.00 UMA\n2.- Por cada unidad que exceda de diez........ 1.35 UMA\n3.- En el caso de revisiones subsecuentes, se pagará el cincuenta por ciento de la tarifa por la primera revisión.\nf).- Por expedición de oficio para cancelación de fianza de régimen de propiedad en condominio, por condominio\n............................................... 5.40 UMA\ng).- Por expedición de oficio de solicitud de monto de fianza de régimen de propiedad en condominio, por condominio.................................... 5.00 UMA\nXII.- POR ANÁLISIS Y EMISIÓN DE FACTIBILIDAD DE OPINIONES TÉCNICAS\nCIRCULACIÓN PEATONAL, TALES COMO:\na).- Para los elementos o mobiliario urbano de los equipos de telefonía:\n1.- Por kilómetro o fracción de línea de telefonía subterránea o aérea........... 16.20 UMA\n2.- Por poste o torre........................ 1.35 UMA\n3.- Por registro............................. 2.70 UMA\n4.- Por caseta de telefonía pública.......... 6.75 UMA\n5.- Antenas................................. 13.50 UMA\nb).- Para los elementos o mobiliario urbano de los equipos de energía eléctrica:\n1.- Por kilómetro o fracción de línea de energía eléctrica subterránea o aérea................................... 16.20 UMA\n2.- Por poste o torre........................ 1.35 UMA\n3.- Por registro............................. 2.70 UMA\nc).- Por kilómetro o fracción de ciclovía, incluye demolición.......................... 13.50 UMA\nXIII.- DÉFICIT DE CAJONES DE ESTACIONAMIENTO.\nA.- Los propietarios o arrendatarios de locales de comercios y servicios que al regularizar uso de suelo resulten con déficit en cantidad de cajones de estacionamiento respecto al reglamento correspondiente, deberán obtener la autorización escrita de la Dirección de Administración Urbana, Ecología y vías públicas, hasta en tanto habiliten los cajones de arrendamiento público, de acuerdo a la tabla siguiente:\na) En la zona comprendida entre el perímetro formado por el Bulevar\nLázaro Cárdenas, Bulevar Teniente\nAzueta, Avenida Ryerson, Calle\nNovena, Avenida Floresta y Avenida\nClub Rotario................................. 47.25 UMA por cajón\nb) En la zona comprendida fuera del perímetro descrito en el inciso a), anterior...................................... 32.40 UMA por cajón\nc) En cualquier zona tratándose de giros determinados en el Sistema de\nApertura Rápida de Empresas durante el primer año................................. 13.50 UMA por cajón\nB.- Las renovaciones deberán hacerse en los meses de enero a febrero aplicando la tarifa de acuerdo a la tabla siguiente:\na) En la zona comprendida entre el perímetro formado por el Bulevar\nLázaro Cárdenas, Bulevar Teniente\nAzueta, Avenida Ryerson, Calle\nNovena, Avenida Floresta y Avenida\nClub Rotario................................. 23.63 UMA por cajón\nb) En la zona comprendida fuera del perímetro descrito en el inciso a), anterior..................................... 16.20 UMA por cajón\nc) En cualquier zona tratándose de giros determinados en el Sistema de Apertura Rápida de Empresas durante el primer año.................................... 13.50 UMA por cajón artículo 28 de esta Ley, se podrá tratar el trámite como licencia nueva para efectos de cobro.\nA, de la fracción XIII del artículo 28 de esta Ley, se ingrese a partir del mes de junio, se podrá aceptar la consideración de la tarifa por los meses restantes al ejercicio fiscal.\nXIV.- DÉFICIT DE ESPACIO PARA CONTENEDOR.\nA.- Los propietarios o arrendatarios de locales de comercios y espacio, para alojar contenedor para basura, deberán obtener\nUrbana, Ecología y Medio Ambiente y pagar anualmente una tarifa por uso de vías públicas, hasta en tanto habiliten espacio para alojar el contenedor en un terreno de su propiedad o en arrendamiento, de acuerdo a la siguiente tabla:\na).- En la zona comprendida entre el perímetro formado por el\nBulevar Lázaro Cárdenas, Bulevar Teniente Azueta, Avenida Ryerson, Calle\nNovena, Avenida Floresta y\nAvenida Club Rotario................ 33.75 UMA por pieza\nb).- En zona comprendida fuera del perímetro descrito en el inciso a) anterior................. 27.00 UMA por pieza\nB).- Las renovaciones deberán hacerse en los meses de enero a febrero aplicando la tarifa de acuerdo a la tabla siguiente:\na).- En la zona comprendida entre el perímetro formado por el Bulevar\nLázaro Cárdenas, Bulevar Teniente\nAzueta, Avenida Ryerson, Calle\nNovena, Avenida Floresta y Avenida\nClub Rotario....................... 20.25 UMA por pieza\nb).- En zona comprendida fuera del perímetro descrito en el inciso a) anterior.......................... 13.50 UMA por pieza\nEn caso de excederse en este plazo, se tratará el trámite como licencia nueva. del año, se podrá aceptar la consideración de la tarifa por los meses restantes al ejercicio fiscal.\nARTÍCULO 28 BIS.- Es el documento expedido por la Dirección de\nAdministración Urbana, Ecología y Medio Ambiente, en el que se hace constar el estado físico de un predio urbano no edificado o baldío; conforme lo define el Reglamento del Catastro\nInmobiliario para el Municipio de Ensenada, Baja California.\nLos contribuyentes que adquieran el Certificado de Mejoramiento de la Imagen Urbana de conformidad con las bases para el otorgamiento del mismo, tendrán derecho a los siguientes descuentos en el pago anual del Impuesto Predial.\nA).- Predios no Edificados o Baldíos\nI.- Los predios no edificados o baldíos deberán: estar libres de basura, maleza, escombro, cascajo o cualquier otro residuo, desecho o desperdicio.......................... 20%\nII.- Contar con guarniciones y banquetas en buen estado que permitan el libre tránsito peatonal o con iluminación dentro del inmueble..... 10%\nIII.- Tener en sus colindancias barda, cerco de malla ciclónica, estructura metálica o similar debidamente rigidizados, con elementos estructurales uniformes. Libre de grafiti en muros propios o ajenos... 10%\nIV.- Tener cerco similar a lo anterior en sus colindancias.................. 5%\nTOTAL 45%\nB).- Cuando el predio no edificado o baldío, se localice dentro de las zonas comerciales o industriales, además de lo anterior, deberá contener:\nI.- Si se ubica en esquina, contar con adecuaciones para personas con discapacidad..................... 5%\nII.- Si se usa como bodega al aire libre para cualquier tipo de material, contar con barda de mampostería, concreto o similar al frente y en sus colindancias, pintada y en buen estado............................... 5%\nIII.- Contar con árboles al frente del predio con espacio de seis metros entre cada uno....................... 5%\nIV.- En caso de contar con anuncios espectaculares, cumplir con lo dispuesto por el Reglamento de la Ley de Edificaciones para el\nMunicipio de Ensenada, B.C., Reglamento de Protección y\nMejoramiento de la Imagen Urbana de la Zona Turística del Centro de la ciudad de Ensenada, Reglamento para la Prevención de la Contaminación\nLumínica en el Municipio de\nEnsenada, B.C., que resulte aplicable y en su caso por las normas de la Coordinación de Imagen\nUrbana............................... 5%\nTOTAL 20% la Imagen Urbana:\nI.- Acreditar ser propietario o poseedor de un inmueble urbano que se encuentre no edificado o baldío.\nII. - Al momento de inscribirse para adquirir el Certificado de Mejoramiento de la Imagen Urbana, pagar la cuota correspondiente, con base en la siguiente tabla:\nVALOR CATASTRAL COSTO DEL CERTIFICADO\nUNIDAD DE MEDIDA Y ACTUALIZACIÓN\n(UMA)VIGENTE\nDE A\n$ 0 $ 37,200 1.00\n37,201 93,000 2.00\n93,001 186,000 3.00\n186,001 279,000 4.00\n279,001 372,000 5.00\n372,001 558,000 8.00\n558,001 744,000 10.00\n744,001 1’116,000 17.00\n1’116,001 1’488,000 20.00\n1’488,001 1’860,000 28.00\n1’860,001 2’232,000 34.00\n2’232,001 2’604,000 40.00\n2’604,001 2’976,000 44.00\n2’976,001 3’348,000 51.00\n3’348,001 3’720,000 58.00\n3’720,001 4’464,000 65.00\n4’464,001 5’208,000 75.00\n5’208,001 5’902,000 88.00\n5’902,001 6’696,000 98.00\n6’696,001 7’440,000 108.00\n7’440,001 8’164,000 119.00\n8’164,001 8’928,000 122.00\n8’928,001 9’672,000 125.00\n9’672,001 10’416,000 129.00\n10’416,001 11’160,000 132.00\n11’160,001 En adelante 136.00\nIII.- En caso de haber cumplido dentro del plazo de 6 meses con los requisitos señalados en los incisos A) y B), para obtener el estímulo fiscal correspondiente, la\nDirección de Administración Urbana, Ecología y\nMedio Ambiente realizará una inspección otorgando en su caso, el Certificado de Mejoramiento de la Imagen Urbana.\nSUBDIRECCIÓN DE ECOLOGÍA Y MEDIO AMBIENTE\nARTÍCULO 29.- Los servicios que presta la Subdirección de Ecología y Medio Ambiente se cobrarán conforme a la siguiente tarifa:\n1.- Por verificación e inspección de solicitud de licencia ambiental.................................. 4.05 UMA\n1.1 Verificación e inspección de solicitud de licencia ambiental para construcción/operación de restaurantes o comercios con venta de alimentos y bebidas.................... 5.05 UMA\n1.2 Verificación e inspección de solicitud de licencia ambiental para construcción/operación de jardines sociales o salones de eventos......................................... 5.00 UMA\n1.3 Verificación e inspección de solicitud de licencia ambiental para guarderías, escuelas y centros educativos................... 3.05 UMA\n1.4 Verificación e inspección de solicitud de licencia ambiental para hoteles y moteles....... 6.00 UMA\n1.5 Verificación e inspección de solicitud de licencia ambiental para tiendas de abarrotes....................................... 3.00 UMA\n1.6 Verificación e inspección de solicitud de licencia ambiental para casas de asistencia, casas hogar, orfanatos, albergues, entre otros.......................... 2.00 UMA\n1.7 Verificación e inspección de solicitud de licencia ambiental para mercados, tiendas de autoservicio, entre otros.................... 8.00 UMA\n1.8 Verificación e inspección de solicitud de licencia ambiental para patios de maniobras y de almacenamiento de contenedores\n2.- Por recepción y evaluación de informe preventivo\n(construcción y operación):\na) 1-500 m²................................ 54.00 UMA\nb) 501-1000 m²............................... 114.75 UMA\nc) 1001-2000 m²............................... 128.25 UMA\nd) 2001-3000 m²............................... 141.75 UMA\ne) 3001-4000 m²............................... 155.25 UMA\nf) Mayor de 4001 m²............................... 162.00 UMA\n2.1 Por recepción y evaluación de informe preventivo para restaurantes con venta de alimentos y bebidas (construcción/operación):\na) 1-500 m²............................ 56.00 UMA\nb) 501-1000 m²........................... 115.75 UMA\nc) 1001-2000 m²........................... 129.25 UMA\nd) 2001-3000 m²........................... 142.75 UMA\ne) 3001-4000 m²........................... 156.25 UMA\nf) Mayor de 4001 m²........................... 163.00 UMA\n2.2 Por recepción y evaluación de informe preventivo para jardines sociales o salones de eventos (construcción/operación):\na) 1-500 m²............................. 70.05 UMA\nb) 501-1000 m²............................ 117.00 UMA\nc) 1001-2000 m²............................ 128.50 UMA\nd) 2001-3000 m²............................ 142.75 UMA\ne) 3001-4000 m²............................ 156.25 UMA\nf) Mayor de 4001 m²............................ 163.00 UMA\n2.3 Por recepción y evaluación de informe preventivo para guarderías, escuelas y centros educativos (construcción/operación):\na) 1-500 m².............................. 52.00 UMA\nb) 501-1000 m²............................. 112.75 UMA\nc) 1001-2000 m²............................. 125.25 UMA\nd) 2001-3000 m²............................. 138.75 UMA\ne) 3001-4000 m²............................. 154.25 UMA\nf) Mayor de 4001 m²............................. 160.00 UMA\n2.4 Por recepción y evaluación de informe preventivo para hoteles y moteles\n(construcción/operación):\na) 1-500 m².............................. 80.00 UMA\nb) 501-1000 m²............................. 116.75 UMA\nc) 1001-2000 m²............................. 130.25 UMA\nd) 2001-3000 m²............................. 143.75 UMA\ne) 3001-4000 m²............................. 157.25 UMA\nf) Mayor de 4001 m²............................. 164.00 UMA\n2.5 Por recepción y evaluación de informe preventivo para tiendas abarrotes\n(construcción/operación):\na) 1-500 m².............................. 54.00 UMA\nb) 501-1000 m²............................. 75.75 UMA\nc) 1001-2000 m²............................ 100.25 UMA\nd) 2001-3000 m²............................ 125.75 UMA\ne) 3001-4000 m²............................ 135.25 UMA\nf) Mayor de 4001 m²............................. 142.00 UMA\n2.6 Por recepción y evaluación de informe preventivo para establecimientos con servicio de venta y consumo de bebidas alcohólicas en envase abierto(construcción/ operación):\na) 1-500 m².............................. 84.00 UMA\nb) 501-1000 m²............................. 117.75 UMA\nc) 1001-2000 m²............................. 131.25 UMA\nd) 2001-3000 m²............................. 144.75 UMA\ne) 3001-4000 m²............................. 158.25 UMA\nf) Mayor de 4001 m²............................. 165.00 UMA\n2.7 Por recepción y evaluación de informe preventivo para mercados, tiendas de autoservicio, entre otros (construcción/ operación):\na) 1-500 m².............................. 85.00 UMA\nb) 501-1000 m²............................. 117.75 UMA\nc) 1001-2000 m²............................. 131.25 UMA\nd) 2001-3000 m²............................. 144.75 UMA\ne) 3001-4000 m²............................. 158.25 UMA\nf) Mayor de 4001 m²............................. 165.00 UMA\n3.- Por recepción y evaluación de Manifiesto de Impacto Ambiental (MIA) Modalidad específico........................................ 170.00 UMA\n4.- Por recepción y evaluación de Manifiesto de Impacto Ambiental (MIA) Modalidad particular para fraccionamientos de cualquier tipo.................................... 200.00 UMA\n5.- Cambio de Propietario y/o razón social\nFusión, Transferencia de derechos.................. 47.25 UMA\n6.- Regularización de actividades de obra civil, comercio y servicios y otros....................... 40.50 UMA\n7.- Análisis de prórroga para presentar información adicional en Materia de\nImpacto Ambiental (por única vez).................. 13.50 UMA\n8.- Registro de emisiones a la atmósfera por fuente fija.................................... 27.00 UMA\n8.1.- Revalidación de registro de emisiones a la atmósfera por fuente fija.............. 13.50 UMA\n9.- Registro de fuentes fijas de descarga de aguas residuales comerciales y servicios........................................ 27.00 UMA\n9.1- Revalidación de registro de fuentes fijas de descarga de aguas residuales comerciales y servicios...................... 13.50 UMA\n10.- Por permiso para la remoción, trasplante o poda de árboles:\na).- Por cada árbol por motivo de presentar riesgo a infraestructura............ 4.05 UMA\nb).- Por cada árbol por motivo de construcción................................. 67.50 UMA\nc).- La verificación e inspección por cada solicitud de remoción, poda o trasplante de árbol...................................... 2.00 UMA\nd).- Por cada árbol que se encuentra en la vía pública por motivos de remoción.............. 33.75 UMA\ne).- Por cada árbol por motivos de poda............ 0.68 UMA\nf).- Por cada árbol por motivo de trasplante...... 13.50 UMA\n11.- Licencia de prestador de Servicios de recolección y transporte de residuos sólidos urbano y de manejo especial por unidad y anual................................... 101.25 UMA\n12.- Licencia de prestadores de servicios para el transporte de agua residual doméstica y comercial.\na)Doméstica....................................... 67.50 UMA\nb)Comercial...................................... 101.25 UMA\n13.- Licencia de prestador de servicios de transporte de materiales pétreos (anual)......... 101.25 UMA\n14.- Licencia de prestador de servicios de transporte de materiales pétreos productos de la construcción (anual)............ 33.75 UMA\n15.- Licencia Ambiental ingresada a través del Sistema de Apertura Rápida de\nEmpresas SARE, hasta 200 m² de superficie de operación, que incluye: construcción, estacionamiento, patio de servicio y áreas verdes:\n1) Hasta 50 m² en superficie de operación......... 16.20 UMA\n2) Desde 51 m² hasta 100 m² en superficie de operación...................................... 20.25 UMA\n3) Desde 101 m² hasta 150 m² en superficie de operación...................................... 24.30 UMA\n4) Desde 151 m² hasta 200 m² en superficie de operación...................................... 27.00 UMA\n5) Regularización de comercio, servicios y otros a través del Sistema de\nApertura Rápida de Empresas (SARE), hasta 200 m² de superficie de operación, 50% adicional al costo del trámite normal de la licencia, por año que se haya encontrado operando.\n16.- Licencia Ambiental para el manejo, transporte y disposición final de residuos producto de la demolición\n(residuos especiales) parcial o total de inmuebles................................ 30.00 UMA\n17.- Por licencia ambiental temporal (90 días):\na) Circos\nb) Exposiciones y ferias\nc) Ventas de artículos navideños, deportivos y/o prendas en cualquier modalidad\nd) Mercados sobre ruedas\nPor cada uno de los incisos anteriores................. 33.75 UMA\n17.1 Licencia Ambiental para venta de árboles navideños........................... 60.00 UMA\n18.- Licencia Ambiental para autorización de eventos temporales:\na) De 1 a 500 personas............................ 33.75 UMA\nb) De 501 a 1000 personas......................... 54.00 UMA\nc) Mayor a 1000 personas.......................... 81.00 UMA\nd) Evento temporal sin fines de lucro.............. 0.00 UMA\n19.- Licencia Ambiental para la evaluación de obra civil para casa habitación............... 27.00 UMA\n20.- Licencia Ambiental para la construcción y operación de antenas de telecomunicaciones............................ 101.25 UMA\n21.- Licencia Ambiental para la evaluación de proyectos de áreas verdes de fraccionamientos.................................. 75.00 UMA\n22.- Licencia Ambiental para comercio ambulante fijo y semifijo......................... 20.00 UMA\n23.- Licencia Ambiental para la operación de pantallas electrónicas o digitales(anual)....................................... 120.00 UMA\n24.- Licencia Ambiental para la operación de patios de maniobras y de almacenamiento de contenedores marítimos (anual)................ 200.00 UMA\n25.- Licencia Ambiental para autorización de movimiento de tierra por motivo de construcción o aprovechamiento del terreno en predios sin vegetación nativa:\n1).- De 1 m³ hasta 500 m³ en superficie................................... 47.25 UMA\n2).- Desde 501 m³ hasta 1000 m³ en superficie................................... 60.00 UMA\n3).- Desde 1001 m³ hasta 1500 m³ en superficie................................... 75.00 UMA\n4).- Desde 1501 m³ en adelante de superficie................................... 90.00 UMA\n26.- Modificación de proyectos autorizados............. 40.50 UMA\n27.- Prórroga para dar cumplimiento a condiciones de impacto ambiental................... 6.75 UMA\n28.- Licencia Ambiental para funcionamiento de albergues para el cuidado y protección de animales domésticos.................. 6.75 UMA\n29.- Cuando se realice el pago correspondiente de los derechos indicados en el numeral 9 y 12, durante el primer trimestre del año, se hará un descuento del 15% del costo del servicio.\n30.- Licencia Ambiental por construcción y operación de anuncios espectaculares............. 162.00 UMA\n31.- Revalidación anual de la licencia ambiental de operación:\na) 1-250 m²................................... 10.00 UMA\nb) 251-500 m²................................... 20.25 UMA\nc) 501-1000 m².................................... 26.75 UMA\nd) 1001-2000 m²................................... 30.25 UMA\ne) 2001-3000 m²................................... 43.75 UMA\nf) 3001-4000 m²................................... 57.25 UMA\ng) Mayor de 4001 m²............................... 64.00 UMA\n31.1.- Revalidación extemporánea de licencia ambiental, adicional al monto por la revalidación (por mes)....... 2.50 UMA\n32.- Módulos informativos y/o de venta\n(hasta 90 días naturales)......................... 20.25 UMA\n33.- Licencia Ambiental para centro de acopio de residuos sólidos urbanos reciclables de origen doméstico, con finalidad de servicio comunitario, no comercial....................................... 0.00 UMA\n34.- Licencia Ambiental para recolección de residuos sólidos urbanos reciclables de origen doméstico, con finalidad de servicio comunitario, no comercial................. 0.00 UMA\n35.- Licencia Ambiental para la construcción y operación de vallas publicitarias por metro cuadrado..................................... 2.35 UMA\n36.- Licencia Ambiental para operación de\nNegocio Eco-Responsable........................... 30.25 UMA\n37.- Licencia de prestador de servicios de recolección y transporte de residuos sólidos urbano de origen doméstico(anual).\na) Primera Unidad................................. 40.50 UMA\nb) Por unidad adicional........................... 20.25 UMA\n38.- Licencia ambiental de operación para asociaciones civiles registradas, que prestan servicio comunitario en actividades sin fines de lucro..................... 0.00 UMA\n39.- Licencia ambiental de comercios y servicios para la compra venta de autopartes nuevas y usadas:\na) 1-500 m²................................. 54.00 UMA\nb) 501-1000 m²................................ 114.75 UMA\nc) 1001-2000 m²................................ 128.25 UMA\nd) 2001-3000 m²................................ 141.75 UMA\ne) 3001-4000 m²................................ 155.25 UMA\nf) Mayor de 4001 m²............................... 162.00 UMA\n40.- Licencia ambiental de comercios y servicios para talleres(mecánicos, carrocería, pintura, alineación y balanceo, afinación, frenos y mantenimiento, etc.):\na) 1-500 m²................................. 54.00 UMA\nb) 501-1000 m²................................ 114.75 UMA\nc) 1001-2000 m²................................ 128.25 UMA\nd) 2001-3000 m²................................ 141.75 UMA\ne) 3001-4000 m²................................ 155.25 UMA\nf) Mayor de 4001 m²............................... 162.00 UMA\n41.- Licencia ambiental para eventos temporales exclusivos del Gobierno\nMunicipal.......................................... 0.00 UMA\n42.- Permiso de remoción, trasplante o poda de árboles solicitadas por instituciones públicas del\nGobierno Municipal, Estatal o\nFederal............................................ 0.00 UMA\n43.- Permiso de remoción, trasplante o poda de árboles a propietarios de escasos recursos previamente calificado por medio de un Estudio\nSocioeconómico realizado por la\nDirección de Bienestar social\nMunicipal.......................................... 0.00 UMA\n44.- Resguardo de animales, en el Centro de Atención Canino y Felino:\n1.- Vacunación antirrábica........ EXENTO\n2.- Alimentación y resguardo de caninos.................... 1.00 UMA por período de 24 horas\n3.-Consulta médica veterinaria.... 1.50 UMA\n4.-Tratamiento o desparasitación.. 1.00 UMA\n5.-Eutanasia humanitaria y traslado:\n5.a) Con un peso de 0.01 kg a 10.00 kg.......... 3.00 UMA\n5.b) Con un peso de 10.01 kg a 20.00 kg.......... 4.00 UMA\n5.c) Con un peso de 20.01 kg a 35.00 kg.......... 5.00 UMA\n5.d) Con un peso de 35.01 kg en adelante, por kilo.................................... 0.25 UMA\n6.-Recepción de cadáveres canino y felino....................... 2.00 UMA\n7.- Esterilización y vacunación de caninos y felinos, dados en adopción....................... 4.00 UMA\n8.-Observación clínica de caninos agresores...................... 10.00 UMA\n9.-Certificado médico (caninos y felinos) 2.00 UMA\n10.- Esterilizaciones caninas y felinas:\n10.a) Con un peso de 0.01 kg a 10.00 kg......... 4.00 UMA\n10.b) Con un peso de 10.01 kg a 20.00 kg......... 5.00 UMA\n10.c) Con un peso de 20.01 kg a 35.00 kg......... 6.00 UMA\n10.d) Con un peso de 35.01 kg en adelante, por kilo.................................. 0.25 UMA\n11.- Servicio de cremaciones caninas y felinas:\n11.a) Con un peso de 0.01 kg a 10.00 kg......... 9.63 UMA\n11.b) Con un peso de 10.01 kg a 20.00 kg........ 11.56 UMA\n11.c) Con un peso de más de 20.01 kg............ 15.42 UMA\nCAPÍTULO VII\nSERVICIOS QUE PRESTA LA DIRECCIÓN DE INFRAESTRUCTURA:\nARTÍCULO 30.- Los derechos por servicios que presta la\nDirección de Infraestructura.\nI.- POR PARTICIPAR EN UN PADRÓN DE CONTRATISTAS DE LA DIRECCIÓN\nDE INFRAESTRUCTURA.\n1).- Inscripción.................................. 47.25 UMA\n2).- Revalidación................................ 22.95 UMA\nII.- POR PARTICIPAR EN CONCURSO DE OBRAS.\n1).- Invitación a cuando menos\n3 contratistas................................ 5.40 UMA\n2).- Licitación pública........................... 37.13 UMA\nEn el caso de contar con registro y no revalidar uno o más años; al actualizar su registro, se deberá considerar como alta.\nARTÍCULO 31.- Los propietarios de giros comerciales e industriales de la actividad que ejerza, ocupar sitios exclusivos de estacionamiento o para el ingreso y salida de vehículos, deberán obtener autorización escrita de la autoridad municipal, debiendo siguiente clasificación:\nA).- Con señalamiento de cordones para sitios exclusivos de estacionamiento de vehículos en zonas de tiempo limitado por espacio de automóvil, se entenderá zonas de tiempo limitado:\nLa comprendida sobre el Bulevar Lázaro Cárdenas a Bulevar\nTeniente Azueta, a Avenida Ryerson, a Calle Novena, a Calle\nFloresta y a Avenida Club Rotario.\nUNIDAD DE MEDIDA Y ACTUALIZACIÓN\n(UMA)VIGENTE\na).- En batería............................... 0.23 POR DÍA\nb).- En cordón................................ 0.31 POR DÍA\nc).- Por metro lineal adicional/excedente, en zonas de tiempo limitado, zona centro comprendidas de acuerdo a inciso A) anterior, por espacio de existentes:\na).- En batería........................... 0.03 POR DÍA\nb).- En cordón............................ 0.03 POR DÍA\nB).- Con señalamiento de cordones para sitios exclusivos de estacionamiento de vehículos en zonas de tiempo ilimitado, deberán pagar el 75.00% de la cuota del inciso A) anterior, por espacio de un automóvil.\nC).- Con señalamiento de cordones para sitios exclusivos de tiempo ilimitado, deberán pagar el 50.00% de la cuota del inciso A) anterior, por espacio de un automóvil.\nD).- Por el estacionamiento de vehículos en zona de tiempo limitado:\n1.- Comprobantes de pago por el derecho de estacionarse en zonas de tiempo limitado, hasta de un máximo de dos horas consecutivas, para vehículos con placas nacionales, una cuota de 4.00 UMA por año.\nEl pago del derecho antes referido es obligatorio, para todo propietario por cada vehículo con placas en el\nMunicipio de Ensenada, exceptuando las Delegaciones de\nSanto Tomás, Erendira, La Misión, El Porvenir, San\nAntonio de las Minas, Francisco Zarco, Real del\nCastillo, Valle de la Trinidad, San Vicente, Punta\nColonet e Isla de Cedros.\nLos estacionamientos exclusivos para vehículos no serán utilizados para talleres de reparación o renta de cualquier clase de vehículos; así mismo queda prohibido el ejercicio comercial en estos espacios. expedición de placas y tarjeta de circulación, conforme a las leyes y disposiciones relativas que correspondan, en los módulos que al efecto instale el Ayuntamiento.\nE).- Por infracciones al excederse de dos horas consecutivas, si se liquida dentro de los 15 días siguientes........ 0.25 UMA\nF).- Por infracciones al excederse de dos horas consecutivas, si se liquida después de los 15 días siguientes....... 0.50 UMA\nG).- Ocupación de rampas por cada metro lineal que exceda de seis metros pagarán................................ 0.05 UMA\nH).- Zona exclusiva de carga y descarga por cada metro lineal pagarán........................................... 0.05 UMA\nI).- Ruptura o demolición de pavimentos, cordones y banquetas, sondeos de tuberías e instalaciones; gas, agua, cable, comunicaciones, en general de instalaciones subterráneas, instalación de señalamientos, topes y otras alteraciones y obstrucciones a las vialidades deberá solicitar permiso escrito a la Dirección de Servicios Públicos Municipales, pagando por anticipado por metro lineal............ 0.50 UMA\nJ).- Por pintar o colocar señales que indiquen estacionamiento exclusivo sin poseer el permiso vigente........... 1.00 UMA por día por metro lineal\nK).- Los propietarios de giros comerciales e industriales o aquellos que gocen de sitios exclusivos de estacionamiento en vía pública tendrán como fecha límite el día 31 o el último día hábil del mes de enero para realizar su renovación, de lo contrario se harán acreedores a una sanción.................................... 4.00 UMA por metro lineal\nK.1).- De acuerdo con el inciso K) la sanción incrementará\n0.30 UMA de acuerdo al mes transcurrido quedando de la siguiente manera:\nK.1.1 Marzo................. 4.30 UMA por metro lineal\nK.1.2 Abril................. 4.60 UMA por metro lineal\nK.1.3 Mayo.................. 4.90 UMA por metro lineal\nK.1.4 Junio................. 5.20 UMA por metro lineal\nK.1.5 Julio................. 5.50 UMA por metro lineal\nK.1.6 Agosto................ 5.80 UMA por metro lineal\nK.1.7 Septiembre............ 6.10 UMA por metro lineal\nK.1.8 Octubre............... 6.40 UMA por metro lineal\nK.1.9 Noviembre............. 6.70 UMA por metro lineal\nK.1.10 Diciembre............ 7.00 UMA por metro lineal\nL).- Los propietarios de giros comerciales e industriales o o para el ingreso o salida de vehículos en vía pública, municipal, debiendo pagar anualmente los derechos por los sitios autorizados durante el mes de enero... 12.00 UMA por metro lineal\nL.1) Si el propietario pinta por su propia cuenta metros lineales de más, se hará acreedor a una sanción por no contar con el permiso del excedente........ 1.00 UMA por día, por metro lineal\nM).- Las multas que podrá interponer el Departamento de Ingeniería de Tránsito por incumplimiento a las disposiciones de la ley, son las siguientes:\nM.1) Por falsificar el pintado de cordón de estacionamiento exclusivo.................................... 25.00 UMA\nM.2) Por no informar al Departamento de Ingeniería de\nTránsito, un mes antes de que venza el permiso vigente el interés de no renovar el mismo.... 10.00 UMA\nM.3) Por utilizar señalamientos en fachada, barda o vía pública que prohíban el estacionamiento de vehículos, sin contar con el permiso.................... 25.00 UMA\nM.4) Por no exhibir en lugar visible el permiso de estacionamiento exclusivo vigente............ 10.00 UMA\nM.5) En caso de reincidencia en cualquiera de las multas descritas en los incisos anteriores, se cobrará un\n100% adicional a la tarifa correspondiente.\nN).- Por recepción, análisis y emisión de opiniones técnicas de ocupación de la vía pública........................ 4.00 UMA\nÑ).- Por recepción, análisis y emisión de opiniones técnicas de ocupación de la vía pública, por altos de disco, topes, vados y otros elementos reductores de velocidad...... 2.00 UMA\nO).- Por la canalización de instalaciones subterráneas, tales como: cable conductor, fibra óptica, tuberías, instalación de casetas telefónicas y postes de luz o similar.\nLos derechos a que hace referencia la presente fracción se determinarán de acuerdo a las siguientes cuotas o tarifas:\nSe calcularán, determinarán y cubrirán por los sujetos obligados en UMA el vigente para el Estado de Baja California, por construcción de tuberías, tendido de cables, fibras ópticas o similares y conducciones, aéreas de uso público y privado, sean eléctricas, telefónicas, telecomunicaciones, de transportación de gas domiciliario o industrial u otros, se pagará por metro lineal:\na).- Líneas aéreas...................... 0.9 UMA\nb).- Líneas subterráneas................ 0.10 UMA\nc).- Casetas telefónicas................ 1.21 UMA\nd).- Postes de luz y teléfono........... 1.21 UMA correspondiente, el número de permiso y los metros lineales los revalide el derecho respectivo.\nESTACIONAMIENTOS PÚBLICOS FIJOS\nARTÍCULO 31 BIS.- El pago de derechos por permiso y/o licencia de\nEstacionamientos Públicos Fijos, se cobrará de la siguiente manera:\nTARIFA\nUNIDAD DE MEDIDA Y ACTUALIZACIÓN\n(UMA)VIGENTE\nI.- Las licencias para estacionamiento público fijo, se cobrará de acuerdo a la capacidad del estacionamiento, conforme a la siguiente tarifa:\na).- De 1 a 25 vehículos........................ 182.25 UMA\nb).- De 26 a 50 vehículos....................... 229.50 UMA\nc).- De 51 a 75 vehículos....................... 270.00 UMA\nd).- De 76 a 100 vehículos...................... 324.00 UMA\ne).- De 101 vehículos en adelante............... 371.25 UMA\nII.- El cobro de la revalidación de la licencia anual, se cobrará de acuerdo a la capacidad del estacionamiento, conforme a la siguiente tarifa:\na).- De 1 a 25 vehículos......................... 40.50 UMA\nb).- De 26 a 50 vehículos........................ 54.00 UMA\nc).- De 51 a 75 vehículos........................ 67.50 UMA\nd).- De 76 a 100 vehículos....................... 81.00 UMA\ne).- De 101 vehículos en adelante................ 94.50 UMA\nIII.- Las multas a los estacionamientos no regulados, se cobrarán conforme a lo siguiente:\na).- De 1 a 25 vehículos............................ 62.68 UMA\nb).- De 26 a 50 vehículos........................... 75.21 UMA\nc).- De 51 a 75 vehículos........................... 100.28 UMA\nd).- De 76 a 100 vehículos.......................... 112.82 UMA\ne).- De 101 vehículos en adelante................... 125.37 UMA\nIV.- Las multas a los estacionamientos públicos permanentes y transitorios, por incumplimiento de cada uno de los requisitos operativos y lineamientos técnicos, se cobrarán de acuerdo a la siguiente tarifa:\na).- De 1 a 25 vehículos............................ 62.68 UMA\nb).- De 26 a 50 vehículos........................... 75.21 UMA\nc).- De 51 a 75 vehículos........................... 100.28 UMA\nd).- De 76 a 100 vehículos.......................... 112.82 UMA\ne).- De 101 vehículos en adelante................... 125.37 UMA\nESTACIONAMIENTOS PÚBLICOS TRANSITORIOS\nARTÍCULO 31 TER.- El pago de derechos por permiso de estacionamientos públicos transitorios, se cobrará de la siguiente manera:\nTARIFA\nUNIDAD DE MEDIDA Y ACTUALIZACIÓN\n(UMA)VIGENTE\nI.- Las licencias para estacionamiento público transitorio, se cobrarán de acuerdo a la capacidad del estacionamiento, conforme en la siguiente tarifa:\na) De 1 a 25 vehículos........................... 13.50 UMA\nb) De 26 a 50 vehículos.......................... 27.00 UMA\nc) De 51 a 75 vehículos.......................... 54.00 UMA\nd) De 76 a 100 vehículos......................... 67.50 UMA\ne) De 101 vehículos en adelante................... 81.00 UMA\nII.- Las multas a los estacionamientos no regulados, se cobrarán conforme a lo siguiente:\na).- De 1 a 25 vehículos............................ 62.68 UMA\nb).- De 26 a 50 vehículos........................... 75.21 UMA\nc).- De 51 a 75 vehículos........................... 100.28 UMA\nd).- De 76 a 100 vehículos.......................... 112.82 UMA\ne).- De 101 vehículos en adelante................... 125.37 UMA\nIII.- Las multas a los estacionamientos públicos permanentes y la siguiente tarifa:\na).- De 1 a 25 vehículos............................ 62.68 UMA\nb).- De 26 a 50 vehículos........................... 75.21 UMA\nc).- De 51 a 75 vehículos........................... 100.28 UMA\nd).- De 76 a 100 vehículos.......................... 112.82 UMA\ne).- De 101 vehículos en adelante................... 125.37 UMA\nARTÍCULO 32.-Los propietarios de vehículos de transporte público de pasajeros que necesitan la ocupación de la vía pública, para sitios exclusivos, deberán obtener autorización escrita de la\nDirección, debiendo pagar anualmente los derechos por el espacio de vehículo:\na).- En batería y en cordón............................ 50.00 UMA\nARTÍCULO 32 BIS.- POR LINEAMIENTOS VIALES PARA DESARROLLOS URBANOS:\n1.- Por recepción, análisis y revisión de opiniones técnicas de revisión en proyectos de nuevos desarrollos comerciales, habitacionales, industriales, etc................... 4.00 UMA\n1.1.- Pasados 30 días hábiles para presentar las correcciones señaladas en la última versión entregada se establecerá un cobro de...................... 4.00 UMA\n2.- Por expedición de lineamientos viales para el desarrollo urbano y obra de infraestructura, incluyendo copia del plano relativo, siguiente forma:\na).- En predios ubicados dentro o colindando con los límites de los centros de población:\n1.- Menores de una hectárea................... 13.50 UMA\n2.- De 1 a 5 hectáreas........................ 60.75 UMA\n3.- Por cada hectárea o fracción adicional a 5 hectáreas.................... 4.05 UMA\n4.- Para predios donde se ubiquen fraccionamientos o asentamientos humanos que sean previamente clasificados como TIPO POPULAR y que sean notificados por el Instituto Nacional del Suelo\nSustentable (INSUS) en proceso de regularización del suelo con base en el convenio de colaboración con el Ayuntamiento de Ensenada, B.C. que se encuentre vigente, estará exenta del pago de este concepto.................... 0.00 UMA\nb).- En predios ubicados fuera de los centros de población:\n1.- Menores de una hectárea................... 20.25 UMA\n2.- De 1 a 5 hectáreas........................ 91.13 UMA\n3.- Por cada hectárea o fracción adicional a 5 hectáreas.................... 6.08 UMA\n4.- Para predios donde se ubiquen fraccionamientos o asentamientos humanos que sean previamente clasificados como TIPO POPULAR y que sean\nSustentable (INSUS) en proceso de regularización del suelo con base en el convenio de colaboración con el Ayuntamiento de Ensenada, B.C. que se encuentre vigente, estará exenta del pago de este concepto...................... 0.00 UMA\nc).- Por análisis de accesos vehiculares se pagará de la forma siguiente:\n1.- En predios ubicados dentro del límite del centro de población:\n1.1.- Por accesos a lotes comerciales, habitacionales y de servicios...... 13.50 UMA\n1.2.- Por acceso a centros comerciales y lotes industriales............... 27.00 UMA\n1.3.- Por acceso a fraccionamientos...... 54.00 UMA\n2.- En predios ubicados fuera del límite del centro de población:\n2.1.- Por acceso a lotes comerciales habitacionales y de servicios...... 20.25 UMA\n2.2.- Por acceso a centros comerciales y lotes industriales............... 40.50 UMA\n2.3.- Por acceso a fraccionamientos...... 81.00 UMA\n3.- Por revisión de proyectos para señalamiento vial en nuevos desarrollos comerciales, habitacionales, industriales, etc.:\n3.1.- Hasta 5 hectáreas.................. 27.00 UMA\n3.2.- Por cada hectárea o fracción adicional a 5 hectáreas............. 2.70 UMA\n4.- Por revisión en proyectos de semaforización........................... 27.00 UMA\n5.- Por revisión en proyectos que contemplen estacionamiento para vehículos:\n5.1.- De 20 a 30 cajones de estacionamiento..................... 6.75 UMA\n5.2.- Por cada 10 cajones adicionales..... 2.70 UMA\nd).- Por eliminación de cajones de estacionamiento para nuevos desarrollos, el cobro será anual:\n1.- Por la eliminación de cajones de estacionamiento en la vía pública, para dar acceso a inmuebles de uso comercial y el buen funcionamiento de la circulación peatonal:\n1.1.- Por cada cajón de estacionamiento eliminado, dentro y fuera del límite de población................. 13.50 UMA\n2.- Los propietarios de giros comerciales e industriales que cuenten con la autorización escrita de la autoridad municipal, para la eliminación de cajones en la vía pública, para el ingreso o salida de vehículos en vía pública, deberán de pagar los derechos anualmente, así mismo tendrá como fecha límite el último día hábil del mes de enero:\n2.1 Por cada cajón de estacionamiento eliminado, dentro y fuera del límite de población................... 6.75 UMA\n3.- Por la modificación geométrica de integraciones viales a estacionamientos ya autorizados y/o no cumplan con la normatividad establecida en la Ley de Edificaciones del Estado de Baja\nCalifornia............................. 1,080.00 UMA\ne).- Los fraccionamientos populares o de interés social tendrán un 50% de descuento de estas cuotas, sólo construidos por el Gobierno (Municipal, Estatal o\nFederal). e.1).- Los fraccionamientos populares o de interés social compañía privada deberán pagar el 100%\nCAPÍTULO VIII\nSERVICIOS QUE PRESTA LA DIRECCIÓN DE SERVICIOS PÚBLICOS\nMUNICIPALES, A TRAVÉS DE:\n1.- SERVICIOS QUE PRESTAN DEPARTAMENTO DE PARQUES Y JARDINES, Y\nPANTEONES\nARTÍCULO 33.- Los derechos por estos servicios se pagarán de acuerdo a lo siguiente:\nUNIDAD DE MEDIDA Y ACTUALIZACIÓN\n(UMA)VIGENTE\na).- Inhumaciones a perpetuidad........................ 20.25 UMA\nb).- Inhumaciones y apertura, de fosa refrendo\n(cada 7 años)..................................... 27.00 UMA\nc).- Pago por derecho de exhumaciones.................. 8.10 UMA\nd).- Apertura de fosa.................................. 4.05 UMA\ne).- Reinhumación...................................... 2.70 UMA\nf).- Inhumación a perpetuidad de cenizas............... 6.75 UMA\ng).- Inhumaciones y refrendo de cenizas (cada\n5 años)........................................... 1.35 UMA\nh).- Reinhumación de cenizas........................... 1.35 UMA\nMunicipales, por trámite:\ni).- Lápida............................................ 4.05 UMA\nj).- Permiso por cabezal............................... 4.05 UMA\n(40x60x8 cm.)\nk).- Sobre caja........................................ 4.05 UMA\nl).- Plancha........................................... 4.05 UMA\nm).- Cordón............................................ 4.05 UMA\nn).- Boleta de perpetuidad............................. 4.05 UMA ñ).- Cerco metálico.................................... 4.05 UMA\no).- Otros Servicios................................... 4.05 UMA\np).- Construcción sobre caja cabezal en el panteón No.4...................................... 33.75 UMA\nq).- Caja e inscripción de cabezal en caso de reinhumación en el panteón No.4................ 27.00 UMA\nr).- Refrendo por única vez (7 años).................... 6.75 UMA\ns).- Permiso de construcción............................ 6.75 UMA\n(En área de 2 m de profundidad 2.20 m de largo y 1 m de ancho.)\nt).- Servicios de velación: t.1).- Velación por horas: t.1.1).- Renta de espacio toda la noche.... 16.75 UMA t.1.2).- Renta mensual de espacio adyacente por m² para instalación de negocio o local..... 5.60 UMA la situación económica de los deudos de acuerdo a estudio socioeconómico que para este efecto realice la Dirección de\nBienestar Social Municipal, DIF Municipal o DIF Estatal.\na).- Son solidariamente responsables del pago de los derechos referidos, las personas físicas, morales o unidades económicas que presten este servicio fúnebre.\nb).- Por inhumaciones de cadáveres en tiempo extraordinario después de los horarios fijados por el Ayuntamiento para el servicio de panteones, se pagará el doble de las cuotas establecidas en este artículo.\n2.- SERVICIOS QUE PRESTA EL DEPARTAMENTO DE RASTRO\nARTÍCULO 34.- Los derechos por este servicio serán cubiertos por el introductor o propietario, al solicitar el sacrificio de ganado(incluyendo el servicio de refrigeración por las primeras\n24 horas, servicio de báscula y el lavado de menudo).\nARTÍCULO 35.- Los derechos por cabeza de ganado sacrificado en el Departamento de Rastro o en las Delegaciones, se pagarán de acuerdo con la siguiente tarifa:\nUNIDAD DE MEDIDA Y ACTUALIZACIÓN\n(UMA)VIGENTE\nI.- Ganado Vacuno..................................... 6.50 UMA\nII.- Ganado Porcino.................................... 4.00 UMA\nIII.- Ganado Caprino o Lanar............................ 2.50 UMA\nIV.- Ganado Caballar................................... 5.50 UMA\nV.- Otro tipo de animales............................. 3.00 UMA de Rastro dentro de las 24 horas siguientes a la matanza. El\nAyuntamiento quedará relevado de toda responsabilidad, en caso de que los introductores no las retiren en el plazo establecido.\nARTÍCULO 36.- En las Delegaciones Municipales en que no exista\nRastro, se pagará por expedición de permiso de matanza por cabeza de ganado sacrificado, de acuerdo a la siguiente:\nUNIDAD DE MEDIDA Y ACTUALIZACIÓN\n(UMA)VIGENTE\nI.- Ganado Vacuno..................................... 1.00 UMA\nII.- Ganado Porcino.................................... 1.00 UMA\nIII.- Ganado Caprino o Lanar............................ 1.00 UMA\nIV.- Ganado Caballar................................... 1.00 UMA\nARTÍCULO 37.- Derechos por otros servicios que presta el\nDepartamento de Rastro o las Delegaciones Municipales.\nA).- Después de 24 horas siguientes de la matanza por cada día de refrigeración, se cobrará por cada animal sacrificado, de acuerdo a la siguiente:\nUNIDAD DE MEDIDA Y ACTUALIZACIÓN\n(UMA)VIGENTE\nI.- Ganado Vacuno....................... 5.50 UMA por cada\n24 horas adicionales\nII.- Ganado Porcino...................... 4.50 UMA por cada\n24 horas adicionales\nIII.- Ganado Caprino o Lanar.............. 3.10 UMA por cada\n24 horas adicionales\nIV.- Ganado Caballar..................... 6.60 UMA por cada\n24 horas adicionales\nV.- Otro tipo de animales.............. 2.00 UMA por cada\n24 horas adicionales\nB).- Por la estancia de un animal en los corrales del Rastro Municipal después de las primeras 24 horas se pagará por cada día, por cabeza\n(no incluye alimento)............................. 1.00 UMA\nC).- Por el sacrificio ocasional de ganado fuera del horario establecido, por animal............................ 1.00 UMA\nD).- Por guía de traslado de animales.................. 1.00 UMA\n3.- SERVICIOS QUE PRESTA EL DEPARTAMENTO DE LIMPIA\nARTÍCULO 38.- Los derechos que por el servicio de recolección de el Ayuntamiento a giros comerciales, industriales, instituciones de crédito y demás similares, deberá pagarse conforme a la siguiente:\nUNIDAD DE MEDIDA Y ACTUALIZACIÓN\n(UMA)VIGENTE\na).- Por levante de recipiente para depósito de basura que no exceda los 200 litros de volumen.................. 1.28 UMA.\nb).- Por levante de recipiente para depósito de basura que exceda los 200 litros de volumen 1.28 UMA por cada 200 litros y por fracción que exceda dicha medida.\nPor otros servicios que presta el Departamento de Limpia, se dicho departamento, el que en todo caso será proporcional al servicio prestado.\nARTÍCULO 39.- Los derechos por recepción de basura comercial, industrial, de prestadores de servicios y demás similares en el relleno sanitario municipal, deberá pagarse conforme a lo siguiente:\nPor cada tonelada....................................... 6.00 UMA de su propiedad en el relleno sanitario municipal.\nCAPÍTULO IX\nSERVICIOS QUE PRESTA LA DIRECCIÓN DE SEGURIDAD PÚBLICA:\nUNIDAD DE MEDIDA Y ACTUALIZACIÓN\n(UMA)VIGENTE\nARTÍCULO 40.- Las empresas dedicadas a la prestación de servicios y monitoreo de alarmas, deberán cubrir un importe anual, por los servicios de asistencia que brinde la Subdirección de Policía y Tránsito Municipal, con motivo de respuesta a los llamados de los sistemas de alarmas instalados en comercios, industrias y casa habitación......................... 137.70 UMA\nARTÍCULO 40 BIS.- Análisis de factibilidad para la prestación de Servicios de la Dirección de Seguridad Pública, en proyectos de estudios de factibilidad solicitados por la Dirección de\nComercio, Alcoholes y Espectáculos Públicos.......... 44.55 UMA\nARTÍCULO 40 TER.- Los particulares que soliciten curso de manejo\nSubdirección de Policía y Tránsito Municipal............ 3.00 UMA\nARTÍCULO 40 QUÁTER.- Verificación de serie vehicular en sitio.................................................. 5.00 UMA\nARTÍCULO 40 QUINQUIES.- Expedición de constancia de no robo de vehículo................................................ 2.00 UMA\nARTÍCULO 40 SEXIES.- Traducción de título vehicular americano............................................... 6.00 UMA\nARTÍCULO 40 SEPTIES.- Copias fotostáticas no certificadas por hoja.................................................... 0.02 UMA\nARTÍCULO 40 OCTIES.- Impartición de curso de manejo por persona................................................ 10.50 UMA\nARTÍCULO 40 NONIES.- Guía de traslado de contenedor... 1.00 UMA\nALMACENAJE DE VEHÍCULOS\nARTÍCULO 41.- Los derechos por almacenaje de vehículos en predios propiedad del Municipio o del concesionario, causarán después de las primeras 24 horas una cuota diaria de...................................................... 0.74 UMA\nTratándose de vehículos robados que ingresen al depósito\nMunicipal, previa comprobación con documentos oficiales de autoridad competente, se exentará del pago de los derechos de almacenaje de vehículos, siempre y cuando el robo sea reportado dentro de las primeras 72 horas subsecuentes al hecho.\nARRASTRE DE VEHÍCULOS\nARTÍCULO 42.- Los derechos por servicios de grúa que sean prestados por el Municipio, para el arrastre de vehículos incluido el uso de patines, deberán cubrirse de acuerdo a la siguiente:\nUNIDAD DE MEDIDA Y ACTUALIZACIÓN\n(UMA)VIGENTE\nI.- POR ARRASTRE\na).- Automóviles, camionetas y pick-Ups............ 10.13 UMA\nb).- Camiones de pasajeros......................... 13.50 UMA\nc).- Remolques (tráilers).......................... 16.20 UMA\nd).- Remolque de tracto camiones de tres o más ejes, con una o dos cajas..................... 29.70 UMA\ne).- Auto-tractores o tracto camión solos o con remolques..................................... 29.70 UMA\nf).- Motocicletas.................................. 10.80 UMA\ng).- Bicicletas..................................... 1.35 UMA\nII.- POR MANIOBRAS\nEn caso de que sean necesarias maniobras especiales se aplicará lo siguiente:\nA).- Maniobras extras (volcaduras, choques y desperfectos en el sistema de rodamiento):\nA.1).- En caso de volcadura de vehículos ligeros o de\nCarga y/o autobuses.\n1) Volcaduras en áreas planas y aceras de carril de rodamiento.\n2) Volcadura cuando el vehículo sale del camino y cae en un desbarrancamiento a menos de\n10 M. de distancia del carril de arrodillamiento.\n3) Volcadura cuando el vehículo sale del camino y cae en un desbarrancamiento a más de\n10 M. de distancia del carril de arrodillamiento.\n1).- Automóviles, camionetas y pick-ups...... 16.20 UMA\n1.1) Cuando el vehículo que se va a remolcar no cuenta con llantas y/o se encuentra imposibilitado de rodar utilizándose el jalón (dolly), así como en camiones y tractocamiones, desatirado en los frenos de aire, volcaduras, salidas de carretera, utilización de dos o más ocasiones de equipo para arrastre.\n1.2) Uso de grúa para vehículo con defensa adaptada a la original (spoiler).\n1.3) Uso de maniobra por parte del operador para retirar vehículo de cajón de estacionamiento con alto grado de dificultad.\n1.4) Uso de maniobras con alto grado de dificultad cuando sea necesario retirar el cambio de la transmisión, siendo este de tracción trasera y/o conlleve un alto riesgo para el operador de grúa.\n2).- Camiones de Pasajeros de Servicio\nPúblico, particular o de carga.......... 22.95 UMA\n3).- Remolques (tráilers) y autobuses de pasaje.................................. 29.70 UMA\n4).- Remolque de tracto camiones de tres o más ejes, solo o con remolque........... 44.55 UMA\nB).- Maniobras inconclusas de grúa, por el evento de presentarse el vehículo grúa al lugar donde exista violación a lo reglamentado, con la infracción por escrito pero no se realice el servicio de remolque por causas no imputables al servicio de grúa se pagarán por vehículo las cuotas siguientes:\n1).- Automóviles, camionetas y pick-ups....... 5.40 UMA\n2).- Camiones de pasajeros (microbús)......... 8.10 UMA\n3).- Remolques (tráilers) y autobuses de pasaje................................ 9.45 UMA\n4).- Remolque de tracto camiones de tres o más ejes, con una o más cajas........... 16.20 UMA\n5).- Motocicletas............................. 5.40 UMA\n6).- Bicicletas............................... 1.35 UMA\nPara efectos del cobro de los derechos de arrastre y almacenaje, así como de las maniobras adicionales, el operador deberá señalar en el inventario del vehículo el tipo de servicio y maniobras extraordinarias.\nMunicipal, previa comprobación con documentos oficiales de autoridad competente, se exentará del pago de los derechos de arrastre de vehículo, siempre y cuando el robo sea reportado dentro de las primeras 72 horas subsecuentes al hecho.\nCAPÍTULO X\nARTÍCULO 43.- Los servicios que presta la Dirección de Bomberos, a giros comerciales, industriales, de servicios, los sectores públicos y sociales, se causarán conforme a la siguiente:\nUNIDAD DE MEDIDA Y ACTUALIZACIÓN\n(UMA)VIGENTE\nI.- PRESTACIÓN DE SERVICIOS DE LA DIRECCIÓN DE BOMBEROS, EN\nPROYECTOS DE CONSTRUCCIÓN, REGULARIZACIÓN Y ANÁLISIS DE\nFACTIBILIDAD DE DESARROLLOS URBANOS.\nA).- FACTIBILIDAD DE PROYECTOS (POR M²)\nCONSTRUCCIÓN REGULARIZACIÓN\n1.- Desarrollo Habitacional.... 0.08 UMA 0.10 UMA\n2.- Desarrollo Comercial...... 0.13 UMA 0.14 UMA\n3.- Desarrollo Industrial...... 0.16 UMA 0.17 UMA\n4.- Otro tipo de instalaciones.. 0.12 UMA 0.13 UMA\n5.- Giros de alto riesgo....... 0.30 UMA 0.32 UMA\nB).- FACTIBILIDAD DE SERVICIOS:\n1.- Desarrollo Habitacional... 50.00 UMA\n2.- Desarrollo Comercial...... 20.00 UMA\n3.- Desarrollo Industrial..... 40.00 UMA\n4.- Otro tipo de instalaciones. 50.00 UMA\n5.- Giros de alto riesgo..... 100.00 UMA\nII.- INSPECCIONES DE DISPOSITIVOS DE SEGURIDAD, PREVENCIÓN, CONTROL\nPETICIÓN DE PARTE.\n1).- Comercio ambulante y puestos semi fijos........................................ 5.40 UMA\n2).- Despachos de profesionistas y giros de servicios.................................... 15.00 UMA\n3).- Billares, expendios, autoservicios, loncherías, panaderías, lavanderías, clínicas, ferreterías, desmanteladoras, talleres mecánicos, tiendas de ropa, misceláneas, farmacias, papelería, templos religiosos, casas de empeño, tortillerías y teatros:\n3.1).- Hasta 50 m²............................ 9.00 UMA\n3.2).- De 51 m² hasta 150 m²................. 13.50 UMA\n3.3).- De 151 m² hasta 500 m²................ 29.70 UMA\n3.4).- De 501 m² hasta 1000 m²............... 54.00 UMA\n3.5).- De 1001 m² hasta 3000 m².............. 67.50 UMA\n4).- Bar turístico, café cantante, restaurante, mercado, supermercado, bodegas de distribución, salón de renta, hospital, salas cinematográficas e instituciones bancarias:\n4.1).- Hasta 50 m²........................... 20.25 UMA\n4.2).- De 51 m² hasta 150 m²................. 24.30 UMA\n4.3).- De 151 m² hasta 500 m²................ 32.40 UMA\n4.4).- De 501 m² hasta 1000 m²............... 64.80 UMA\n4.5).- De 1001 m² hasta 3000 m².............. 75.60 UMA\n5).- Discotecas, tiendas departamentales, centros de entretenimiento, balnearios y/o albercas:\n5.1).- Hasta 150 m².......................... 32.40 UMA\n5.2).- De 151 m² hasta 500 m²................ 40.50 UMA\n5.3).- De 501 m² hasta 1000 m²............... 70.20 UMA\n5.4).- De 1001 m² hasta 3000 m².............. 86.40 UMA\n5.5).- De 3001 m² en adelante............... 105.30 UMA\n6).- Edificios para depósito y almacenamiento en exterior de vehículos, materias primas, contenedores, animales, hangares y/o similares por m² de operación............. 0.14 UMA\n7).- Moteles:\n7.1).- Hasta 10 habitaciones................. 18.90 UMA\n7.2).- De 11 a 20 habitaciones............... 26.50 UMA\n7.3).- De 21 habitaciones en adelante........ 35.00 UMA\n8).- Hoteles:\n8.1).- Hasta 30 habitaciones................. 56.70 UMA\n8.2).- De 31 habitaciones hasta\n50 habitaciones....................... 81.00 UMA\n8.3).- De 50 habitaciones en adelante....... 108.00 UMA\n9).- Edificios educativos, asilos, guarderías y estancias infantiles:\n9.1).- Edificios educativos públicos......... 13.50 UMA\n9.2).- Edificios educativos privados\n9.2.1).- De 1 a 10 aulas.............. 16.20 UMA\n9.2.2).- De 11 a 20 aulas............. 24.30 UMA\n9.2.3).- De 21 aulas en adelante...... 32.40 UMA\n9.3).- Asilos, guarderías y estancias infantiles............................ 16.20 UMA\n10).- Giros de alto riesgo:\n10.1).- Distribuidores de gases, químicos, lubricantes, oxígenos, acetilenos, polvorines, gasolineras (estaciones de servicio) y estaciones de gas L.P. para carburación..................... 220.00 UMA\n10.2).- Industrias generadoras de electricidad, plantas de almacenamiento de gas natural y licuado de petróleo, depósitos de combustibles y demás giros de alto riesgo............ 0.34 UMA por m²\n11).- Clubes deportivos, gimnasios, escuelas de danza y ballet:\n11.1).- De 1 m² hasta 100 m²................. 13.00 UMA\n11.2).- De 101 m² hasta 200 m²............... 16.00 UMA\n11.3).- De 201 m² hasta 400 m²............... 20.00 UMA\n11.4).- De 401 m² en adelante................ 30.00 UMA\n12).- Edificios Industriales:\n12.1).- Micro industria, de 1 a 50 empleados............................ 27.00 UMA\n12.2).- Pequeña industria, de 51 a 200 empleados............................ 44.00 UMA\n12.3).- Mediana industria, de 201 a 500 empleados............................ 81.00 UMA\n12.4).- Megaindustria, de 501 empleados a 1000 empleados........................... 112.00 UMA\n12.5).- Macro industria, de 1001 empleados en adelante......................... 140.00 UMA\n13).- Centros de apuestas, apuestas remotas, salas de sorteos de número y/o casinos............ 270.00 UMA\n14).- Solicitudes a través del Sistema de Apertura\nRápida De Empresas (SARE) por superficie de operación que incluye: construcción, estacionamiento, patio de servicio y áreas verdes:\n14.1).- De 1 a 50 metros de operación......... 6.75 UMA\n14.2).- De 51 a 100 metros de operación...... 10.13 UMA\n14.3).- De 101 a 150 metros de operación..... 13.50 UMA\n14.4).- De 151 a 200 metros de operación..... 16.88 UMA\n14.5).- Regularización de comercio, servicios y otros a través del\nSistema de Apertura Rápida de\nEmpresas (SARE), hasta 200 m² de superficie de operación, 50% adicional al costo del trámite normal, por año que se haya encontrado operando.\n15).- Otros giros no especificados................. 40.50 UMA\nLas reinspecciones que deban realizarse en cualquiera de los casos contenidos en esta fracción, se realizarán por el 50% del costo estipulado para la inspección que corresponda.\nLas inspecciones o reinspecciones que se realicen a una distancia mayor de 80 km. fuera de la mancha urbana se cobrará un 100% más sobre el costo estipulado para la inspección o reinspección que corresponda.\nIII.- ANÁLISIS DE RIESGO\n1).- Abarrotes, licorerías, sub-agencia, expendio, billares y autoservicio........... 37.80 UMA\n2).- Restaurante-bar, bar turístico, café cantante, mercado, supermercado, y bodega de distribución...................... 54.00 UMA\n3).- Discotecas, tiendas departamentales, hoteles y moteles........................... 97.20 UMA\nIV.- REVISIÓN DE LAS CONDICIONES DE SEGURIDAD Y PREVENCIÓN EN\nINSTALACIONES TEMPORALES, PARA LA ANUENCIA CORRESPONDIENTE:\n1.- Circos:\n1.5).- Periodo de 61 días en adelante..... 45.00 UMA\n2.- Juegos mecánicos:\n2.1).- Por juego mecánico...................... 2.54 UMA\n2.2).- Por puesto de comida.................... 2.54 UMA\n3.- Exposiciones, ferias y kermeses:\n3.1).- Periodo de 1 a 15 días.................. 9.00 UMA\n3.2).- Periodo de 16 a 30 días................ 18.00 UMA\n3.3).- Periodo de 31 a 45 días................. 27.00 UMA\n3.4).- Periodo de 46 a 60 días................. 36.00 UMA\n3.5).- Periodo de 61 días en adelante.......... 45.00 UMA\n4.- Eventos deportivos (por día):\n4.1).- Hasta 300 personas..................... 13.50 UMA\n4.2).- De 301 personas a 1000 personas........ 20.25 UMA\n4.3).- De 1001 personas a 3000 personas....... 40.50 UMA\n4.4).- De 3001 personas en adelante........... 54.00 UMA\n5.- Eventos masivos (por día):\n5.1).- De 1 hasta 1000 asistentes............. 30.00 UMA\n5.2).- De 1001 a 3000 asistentes.............. 57.00 UMA\n5.3).- De 3001 a 5000 asistentes.............. 84.00 UMA\n5.4).- De 5001 asistentes en adelante........ 115.00 UMA\n6.- Venta de combustible de alto octanaje para carreras................................. 67.50 UMA\n7.- Otros eventos no especificados................ 33.75 UMA\nV.- CONSTANCIA DE DAÑOS EN BIENES SINIESTRADOS POR INCENDIO O\nEXPLOSIÓN:\n1.- Casa habitación................................ 13.50 UMA\nQuedan exceptuados del pago de este derecho, aquellas casas habitación que no se encuentren aseguradas al ocurrir el siniestro.\n2.- Desarrollo comercial........................... 40.50 UMA\n3.- Desarrollo industrial.......................... 60.75 UMA\n4.- Otros tipos de instalaciones.................. 202.50 UMA\n5.- Vehículos automotores:\n5.1).- Automóviles............................. 13.50 UMA\n5.2).- Camiones de transporte/ pasajeros....... 24.30 UMA\n5.3).- Tracto camiones......................... 32.40 UMA\n5.4).- Embarcaciones pequeñas (botes, yates, lanchas)................................ 13.50 UMA\n5.5).- Embarcaciones medianas (barcos pesqueros).............................. 24.30 UMA\n5.6).- Embarcaciones grandes (cruceros, carga, etc.)................................... 32.40 UMA\n6.- Vehículos de tracción humana o animal.......... 13.50 UMA mayor de 80 km. fuera de la mancha urbana se cobrará un 100% más sobre el costo estipulado para el concepto que corresponda.\nLos sujetos a quienes les sea aplicable el segundo párrafo del numeral 1 de esta fracción, quedarán exentos también del cobro que estipula el párrafo anterior.\nVI.- CERTIFICACIÓN DE EQUIPO DE DISPOSITIVOS DE SEGURIDAD:\n1.- Vivienda unifamiliar........................... 1.35 UMA\n2.- Comercio (portátiles).......................... 3.50 UMA\n3.- Industria (portátiles)........................ 10.00 UMA\n4.- Certificación de sistemas hidráulicos contra incendios (fijos)...................... 50.00 UMA\n5.- Transportes de todo tipo que se encuentren dentro del municipio........................... 9.45 UMA\nVII.- AUTORIZACIÓN O CERTIFICACIÓN PARA REGISTRO Y/O\nEMPADRONAMIENTO DE EMPRESAS:\n1.- Personas físicas o morales dedicadas a la venta, renta, mantenimiento y recarga de extintores portátiles............. 27.00 UMA\n1.1).- Suministro de etiquetas para verificación de la calidad del agente extintor, por etiqueta......... 0.14 UMA\n2.- Personas físicas o morales dedicadas a sistemas contra incendio, sistemas especiales para extinción, sistemas de rociadores automáticos, sistemas de mangueras y sistemas de detección y alarmas contra incendios..................... 81.00 UMA\n3.- Organizaciones civiles, empresas e instructores independientes que presten servicios de capacitación vinculados a temas de prevención y control de siniestros........................ 40.50 UMA\nVIII.- SERVICIOS ESPECIALES:\nA.- CURSOS POR HORA:\n1.- Combate de incendios.................... 27.00 UMA\n2.- Uso y manejo de equipo contra incendio................................ 27.00 UMA\n3.- Identificación de materiales peligrosos.............................. 27.00 UMA\n4.- Conocimientos básicos de rescate........ 27.00 UMA\n5.- Otros no especificados relativos a incendios............................... 27.00 UMA\n6.- Copias fotostáticas no certificadas...... 0.34 UMA\n7.- Reposición de certificado original....... 1.25 UMA\nLos cursos a que hace referencia este apartado, cuando se trate de instituciones públicas, quedarán exentos de pago, siempre misma institución.\nB.- USO DE EQUIPO Y PERSONAL POR HORA:\n1.- Máquina extinguidora.................... 44.00 UMA\n2.- Máquina de iluminación.................. 44.00 UMA\n3.- Máquina escala.......................... 44.00 UMA\n4.- Auto cisterna (con agua)................ 54.00 UMA\n5.- Unidad de rescate o ambulancia.......... 44.00 UMA\n6.- Traslado de ambulancia en delegaciones, a petición de particular................ 0.20 UMA\n(POR KM)\nC.- PRÓRROGAS PARA DAR CUMPLIMIENTO A OBSERVACIONES DE\nLAS ACTAS DE INSPECCIÓN, POR LOS CONCEPTOS DE:\n1.- Extintores y detector de humo hasta por 5 días............................... 5.00 UMA\n2.- Instalación eléctrica y de gas hasta por 10 días.............................. 8.00 UMA\n3.- Capacitación hasta por 15 días.......... 12.00 UMA\n4.- Dictámenes eléctricos y de gas hasta por 20 días............................. 15.00 UMA\n5.- PAECI, Sistemas de alarma contra incendios hasta 30 días................. 22.00 UMA\n6.- Sistemas fijos contra incendios hasta por\n60 días................................. 44.00 UMA\n7.- Aprobación de plan de atención a emergencias contra incendios PAECI...... 27.00 UMA\nIX.- REVISIÓN DE EXPLOSIVOS:\n1.- Revisión de equipos contra incendio en instalaciones para venta de artificios pirotécnicos....................... 40.50 UMA\n2.- Revisión de equipos contra incendio para anuencias de explosivos y polvorines................................... 100.00 UMA\nX.- SANCIONES ECONÓMICAS QUE PODRÁ IMPONER LA DIRECCIÓN\nDE BOMBEROS:\n1).- Por negar el acceso al inspector de la Dirección de Bomberos, donde se realizará una inspección o donde haya ocurrido un incendio, fuga o explosión.......................... 20.00 a 2,000.00 UMA\n2).- Por iniciar las empresas actividades sin la autorización de la Dirección de Bomberos........................ 20.00 a 2,000.00 UMA\n3).- Por infracciones al reglamento no contempladas en los incisos anteriores......................... 20.00 a 2,000.00 UMA\n4).- Por no cumplir con las medidas ordenadas derivadas de un acta de inspección......................... 20.00 a 2,000.00 UMA\n5).- En caso de reincidencia............ 20.00 a 2,000.00 UMA\n6).- Por utilizar, vender, almacenar y/o distribuir materiales peligrosos, sin contar con los permisos respectivos. 20.00 a 2,000.00 UMA\n7).- Por no informar las empresas de cualquier incidente ocurrido, en activi- dades que involucran materiales peligrosos......................... 20.00 a 2,000.00 UMA\n8).- Por almacenar materiales peligrosos en áreas, lugares o ambientes, que no reúnen las condiciones de seguridad necesarias............... 20.00 a 2,000.00 UMA\n9).- Por no informar las empresas, a la\nDirección de Bomberos, de las actividades que pudieran constituir algún riesgo....................... 20.00 a 2,000.00 UMA\n10).- Por no activar las empresas, procedimientos de respuesta ante una emergencia que ponga en peligro a trabajadores, usuarios y/o vecinos.. 20.00 a 2,000.00 UMA\n11).- Por retirar sin autorización y/o violar, sellos de clausura o suspensión instalados (por sello).................. 135.00 UMA\n12).- Por seguir ejerciendo funciones de asesor sin contar con el registro respectivo......................... 20.00 a 2,000.00 UMA\n13).- Por realizar falsa alarma y/o bromas que conlleve a la alerta y/o acción de las unidades de la Dirección de\nBomberos........................... 20.00 a 2,000.00 UMA\nXI.- DICTAMEN DE DAÑOS EN BIENES SINIESTRADOS POR INCENDIO Y\nEXPLOSIÓN:\n1.- Desarrollo habitacional............. 67.50 a 270.00 UMA\n2.- Desarrollo comercial................ 135.00 a 270.00 UMA\n3.- Desarrollo industrial............... 135.00 a 270.00 UMA\n4.- Otro tipo de instalaciones.......... 135.00 a 405.00 UMA\n5.- Vehículos automotores............... 13.50 a 135.00 UMA\n6.- Vehículos de tracción humana o animal. 13.50 a 135.00 UMA\nCAPÍTULO XI\nOTROS SERVICIOS QUE PRESTA EL AYUNTAMIENTO\nU ORGANISMOS PARAMUNICIPALES\nARTÍCULO 44.- Ninguna contribución podrá recaudarse si no está prevista en la presente Ley de Ingresos Municipal.\nI.- LOS SERVICIOS QUE PRESTA LA PARAMUNICIPAL INSTITUTO\nMETROPOLITANO DE INVESTIGACIÓN Y PLANEACIÓN DE ENSENADA, BAJA\nCALIFORNIA(IMIP), SE PAGARÁN CONFORME A LO SIGUIENTE:\nUNIDAD DE MEDIDA Y ACTUALIZACIÓN\n(UMA)VIGENTE\n1.- Por tipo de información, impresión de mapas, polígonos, líneas, imágenes y textos:\na).- En calidad bond de acuerdo al tamaño: a.1) 22\" x 34\" (55.88 cm. x 86.36 cm)...... 9.00 UMA a.2) 42\" x 60\" (1.06 m. x 1.52 m.)........ 15.00 UMA\nb).- En calidad fotográfica (glossy) de acuerdo al tamaño: b.1) 22\" x 34\" (55.88 cm. x 86.36 cm.).... 11.00 UMA b.2) 42\" x 60\" (1.06 m. x 1.52 m.)........ 19.00 UMA\n2.- En servicio, técnico por hora:\na).- Digitalización o capa de información\n(Técnico/PC), en formatos específicos......... 10.00 UMA\nb).- Generación en campo de datos GPS\n(Técnico/GPS), en formatos específicos........ 10.00 UMA\nc).- Elaboración de mapas (Técnico/PC), en formatos específicos.......................... 12.00 UMA\nd).- Generación de bases de datos, en formatos específicos................................... 10.00 UMA\ne).- Georeferenciación de imágenes en formatos específicos.......................... 10.00 UMA\nf).- Otros servicios, en formato varios............ 8.00 UMA\ng).- Generación de datos GPS, en formato RINEX/Dat, con intervalos de medición personalizados..... 10.00 UMA\nh).- Venta de datos de corrección de señal\nGPS en tiempo real (Emisión RTK).............. 10.00 UMA\n3.- Curso de elaboración de estudio de impacto urbano, por persona................................... 75.00 UMA\n4.- Por Servicios de asesoría, capacitación e impartición de talleres, por persona:\na).- De 1 hasta 2 horas............. 6.30 UMA\nb).- De 2 horas en adelante......... 3.15 UMA (por hora)\n5.- Elaboración de opinión técnica a solicitud de particulares.............115.00 UMA\n6.- Dictaminación de estudio de impacto urbano y/o vial iniciar los trámites, conforme a la tabla que se detalla a continuación:\na).- De 0 a 200 metros........................... 150.00 UMA\nb).- De 201 metros a 500 metros.................. 200.00 UMA\nc).- De 501 metros a 2,000 metros................ 400.00 UMA\nd).- De 2,001 metros a 5,000 metros.............. 500.00 UMA\ne).- De 5,001 metros a 10,000 metros............. 550.00 UMA\nf).- Por cada Ha adicional correspondiente al subinciso e).............................. 3.10 UMA\ng).- Por revisiones subsecuentes a partir de la tercera revisión...................... 3.10 UMA\n7.- Elaboración de estudio de impacto ponderación de densidad se deberá realizar el pago correspondiente antes de iniciar los trámites, conforme a la tabla que se detalla a continuación:\na).- De 0 a 200 metros........................... 400.00 UMA\nb).- De 201 metros a 500 metros.................. 450.00 UMA\nc).- De 501 metros a 2,000 metros................ 500.00 UMA\nd).- De 2,001 metros a 5,000 metros.............. 550.00 UMA\ne).- De 5,001 metros a 10,000 metros............. 600.00 UMA\nf).- Por cada Ha adicional correspondiente al subinciso e)............. 3.10 UMA\n8.- Elaboración de estudio de impacto modalidad incorporación de iniciar los trámites, conforme a la tabla que se detalla a continuación:\na).- De 0 a 200 metros.......................... 500.00 UMA\nb).- De 201 metros a 500 metros................. 550.00 UMA\nc).- De 501 metros a 2,000 metros............... 600.00 UMA\nd).- De 2,001 metros a 5,000 metros............. 650.00 UMA\ne).- De 5,001 metros a 10,000 metros............. 700.00 UMA\nf).- Por cada Ha adicional correspondiente al subinciso e)............. 3.10 UMA\n9.- Elaboración de estudio de impacto urbano modalidad cambio de uso de suelo:\na).- En predio hasta diez hectáreas.............. 750.00 UMA\nb).- En predio mayor a diez hectáreas 750.00 UMA más por hectárea excedente de la misma........... 75.00 UMA\n10. -Elaboración de estudio de impacto vial en el municipio de Ensenada:\na).- En predio hasta diez hectáreas............. 750.00 UMA\nb).- En predio mayor a diez hectáreas 750.00 UMA más por hectárea excedente de la misma.......... 75.00 UMA\n11.- Elaboración de análisis o estudio por hora......... 7.00 UMA\n12.- Elaboración de documento o estudio relacionado territoriales y/o desarrollo urbano sujeto a vigente, según previa calendarización del\nInstituto, por semana............................ 600.00 UMA\n13.- Copia simple solicitada a través de la Unidad de\nTransparencia (después de la copia número 21)...... 0.03 UMA\n14.- Alta en registro de especialistas en estudios de impacto urbano y/o vial........................ 46.04 UMA\n15.- Revalidación anual del registro de especialistas en estudios de impacto urbano y/o vial............ 20.80 UMA\n15.1.- A partir del tercer mes del año: anualmente al pago del inciso anterior...... 16.20 UMA\n16.- SERVICIOS DIGITALES\na).- Derechos de acceso y consulta del Sistema de Información Geográfica Municipal......... 60.00 UMA\nLos servicios solicitados por dependencias municipales u otras entidades gubernamentales estarán exentos de cobro por parte del\nIMIP. Sin embargo, cuando los servicios sean requeridos para trámites de particulares o entidades externas al gobierno, se aplicarán los cargos correspondientes.\nII.- LOS SERVICIOS QUE PRESTA EL SISTEMA PARA EL DESARROLLO\nINTEGRAL DE LA FAMILIA, SE PAGARÁN CONFORME A LO SIGUIENTE:\n1.- Cuotas coordinación psicológica:\nMínima Máxima\na).- Asesoría psicológica...... 0.30 UMA 2.20 UMA\nSesión\nb).- Pláticas pre-matrimoniales................ 3.00 UMA\nSesión\nc).- Maestros Sombras.......... 2.96 UMA 9.47 UMA\nSemanal\nd).- Conferencias:\n1).- Hasta 10 personas.................... 5.75 UMA\n2).- Hasta 25 personas................... 14.39 UMA\n3).- Hasta 50 personas................... 28.78 UMA\n4).- Más de 50 personas.................. 57.56 UMA\ne).- Evaluaciones psicológicas.... 5.92 UMA 23.68 UMA\nEvaluación\nf).- Pláticas prematrimoniales urgentes.................................. 8.30 UMA\nSesión\ng).- Inscripción capacitación Maestro\nSombra.................................... 2.37 UMA\nh).- Visita Supervisada........... 2.32 UMA 3.50 UMA\ni).- Certificación Maestro Sombra.............. 5.75 UMA\n2.- Cuotas casas de cuidado y estancias infantiles DIF:\nCASA O ESTANCIA POR SEMANA/ CURSO DE\nINSCRIPCIÓN VERANO\nPOR SEMANA\na).- México-Japón............... 3.70 UMA 2.37 UMA\nb).- Maneadero.................. 2.20 UMA 2.37 UMA\nc).- Real San Fernando.......... 1.50 UMA 2.37 UMA\n3.- Cuotas Taxi DIF:\nMínima Máxima\na).- Traslado local.............. 0.71 UMA 1.54 UMA\nb).- Traslado foráneo (Tijuana).. 4.15 UMA 5.92 UMA\nc).- Traslado especial.......... 29.59 UMA\nd).- Traslado Foráneo(Mexicali).. 11.50 UMA 16.11 UMA\n4.- Registro y revalidación a estancias infantiles:\nUNIDAD DE MEDIDA Y ACTUALIZACIÓN\n(UMA)VIGENTE\nREGISTRO REVALIDACIÓN\na).- Hasta 10 niños.......... 20.00 UMA 10.00 UMA\nb).- Hasta 25 niños.......... 30.00 UMA 15.00 UMA\nc).- Hasta 50 niños.......... 40.00 UMA 20.00 UMA\nd).- Más de 50 niños......... 50.00 UMA 25.00 UMA\nPara los registros y revalidación a estancias infantiles, por pago oportuno en los primeros tres meses, se hará un descuento del\n10%.\nEn caso de exceder los 180 días sin haber revalidado, se aplicará una sanción del 50% adicional de la cuota de revalidación correspondiente.\n5.- Cuotas Centro de Desarrollo Comunitario\nMínima Máxima\na).- Inscripción......... 1.54 UMA\nPor curso\nb).- Cursos................. 3.55 UMA 23.68 UMA\nPor persona\n6.- Cuota Nutri DIF\nMínima Máxima\na).- Consulta nutricional....... 0.30 UMA 0.83 UMA\nb).- Conferencias nutricionales\n1).- Hasta 10 personas................... 6.69 UMA\n2).- Hasta 25 personas................... 16.74 UMA\n3).- Hasta 50 personas................... 33.47 UMA\n4).- Más de 50 personas.................. 72.53 UMA\nc).- Plan de Orientación y Educación Alimentaria\n1).- Hasta 10 personas........ 5.02 UMA Por persona\n2).- Hasta 15 personas......... 4.57 UMA Por persona\n3).- Hasta 25 personas........ 4.13 UMA Por persona\n4).- Hasta 50 personas......... 3.68 UMA Por persona\n5).- Más de 100 personas...... 3.35 UMA Por persona\n7.- Credencial y Tarjetón de Discapacidad\na).- Credencial de discapacidad primera vez................................. Exento\nb).- Expedición de tarjetón para uso de estacionamiento en personas con discapacidad primera vez............................... 1.19 UMA\nc).- Por reposición, por extravío, mutilación o daño al tarjetón de discapacidad....................... 1.78 UMA\nd).- Por reposición, por extravío, mutilación o daño a la credencial de discapacidad................... 1.19 UMA\ne).- Renovación de la credencial de discapacidad............................. Exento\nf).- Renovación del tarjetón de discapacidad.............................. 0.95 UMA\n8.- CIMAD:\na).- Inscripción................. EXENTO\nCiclo Escolar\nb).- Mensualidad................ EXENTO\n9.- Curso de Lengua de Señas Mexicanas\na).- Inscripción..................... 1.63 UMA Por curso\nb).- Cursos: Por persona\n1).- Nivel Bajo........................... 8.93 UMA\n2).- Nivel Medio.......................... 8.93 UMA\n3).- Nivel Avanzado....................... 8.93 UMA correspondientes a los servicios que presta DIF, mediará un estudio socioeconómico realizado por la paramunicipal.\nIII.- LOS SERVICIOS QUE PRESTA EL CENTRO SOCIAL, CÍVICO Y CULTURAL\nRIVIERA DE ENSENADA, SE PAGARÁN CONFORME A LO SIGUIENTE:\n1) COSTO NORMAL ACTUAL POR DÍA: a.1) Salón Catedral de lunes a jueves\n(450 personas).......................... 238.91 UMA a.2) Salón Catedral de viernes a domingo\n(450 personas).......................... 293.50 UMA b.1) Salón Casino de lunes a jueves\n(200 personas).......................... 224.49 UMA b.2) Salón Casino de viernes a domingo\n(200 personas)......................... 238.04 UMA c.1) Salón Rojo de lunes a jueves\n(220 personas).......................... 199.54 UMA c.2) Salón Rojo de viernes a domingo\n(220 personas).......................... 221.61 UMA d.1) Salón Ventanal o Comedor de lunes a jueves (50 personas).......... 32.21 UMA d.2) Salón Ventanal o Comedor de viernes a domingo (50 personas).......... 37.14 UMA e.1) Salón Dorado de lunes a jueves\n(50 personas)............................ 21.86 UMA e.2) Salón Dorado de viernes a domingo\n(50 personas)............................ 26.81 UMA\n2.- Los Jardines, Patios y Terrazas a.1) Jardín Rotonda de lunes a jueves\n(250 personas).......................... 149.44 UMA a.2) Jardín Rotonda de viernes a domingo\n(250 personas).......................... 182.80 UMA a.3) Jardín Desértico de lunes a jueves\n(250 personas).......................... 149.44 UMA a.4) Jardín Desértico de viernes a domingo\n(250 personas).......................... 182.80 UMA b.1) Jardín Misional y Capilla de lunes a jueves (100 personas)............ 89.77 UMA b.2) Jardín Misional y Capilla de viernes a domingo (100 personas)........ 109.83 UMA c.1) Terraza Catedral de lunes a jueves\n(capacidad 50 personas).................. 63.27 UMA c.2) Terraza Catedral de viernes a domingo (capacidad 50 personas).......... 78.33 UMA\n2) EVENTOS MASIVOS:\nEventos masivos a partir de 1,000 personas:\na) Salón Catedral............................. 381.53 UMA\nb) Salón Casino............................... 309.45 UMA\nc) Salón Rojo................................. 288.10 UMA\nd) Salón Ventanal o Salón Comedor.............. 48.29 UMA\ne) Salón Dorado................................ 34.85 UMA\nf) Jardín Rotonda.............................. 237.64 UMA\ng) Jardín Misional y Capilla................... 142.77 UMA\nh) Terraza Catedral............................ 142.77 UMA\ni) Paseo “Las Américas”........................ 95.70 UMA\nj) Paseo “Estado de Baja California”........... 95.70 UMA\nk) Estacionamiento lengüeta, central y misional.................................. 366.69 UMA\nl) Bar........................................ 781.08 UMA\nm) Instalación de carpas 3x3................... 557.91 UMA\n3) ESTACIONAMIENTO: d.1) Cooperación para Seguridad, Mantenimiento y Limpieza del espacio de estacionamiento........ $20.00 PESOS d.2) Cobro por vehículo en eventos especiales......................... 0.62 a 1.84 UMA\n4) SERVICIO DE BARRA LIBRE POR PERSONA (un máximo de 450 personas)\nDurante un período de tiempo de 5 horas, se tendrá a disposición la composición de los mismos. Todos los invitados podrán tomar la cantidad y variedad de tragos y bebidas que deseen de forma libre. e.1) Barra Libre “Todo incluido” de\nLunes a jueves............................ 3.01 UMA e.1.1) Barra Libre “Todo incluido” de\nViernes a domingo.................. 3.34 UMA e.2) Barra Libre “plus” de\nLunes a jueves............................ 3.51 UMA e.2.1) Barra Libre “Plus” de\nViernes a domingo.................. 3.91 UMA\n5) POR EL COBRO DE EVENTOS DE 1 A 7 HORAS EN ESPACIOS DEL\nRIVIERA: a.1) Teatro José Luis Fernández Bandini de lunes a jueves (4 horas)(438 personas)... 73.85 UMA a.2) Teatro José Luis Fernández Bandini de viernes a domingo (4 horas)\n(438 personas)........................... 84.30 UMA b.1) Paseo de las Américas de lunes a jueves\n(máximo 20 carpas)....................... 63.05 UMA b.2) Paseo de las Américas de viernes a domingo\n(máximo 20 carpas)....................... 88.73 UMA c.1) Patio Bugambilias de lunes a jueves\n(150 personas)........................... 59.83 UMA c.2) Patio Bugambilias de viernes a domingo\n(150 personas)........................... 66.29 UMA d.1) Patio Margaritas de lunes a jueves\n(50 personas)............................ 31.17 UMA d.2) Patio Margaritas de viernes a domingo\n(50 personas)............................ 37.14 UMA e.1) Áreas Familiares de lunes a jueves\n(capacidad 90 personas).................. 39.82 UMA e.2) Áreas Familiares de viernes a domingo\n(capacidad 90 personas).................. 48.91 UMA f.1) Salón del Bar de lunes a jueves (por hora)\n(capacidad 25 Personas)................... 1.38 UMA f.2) Salón del Bar de viernes a domingo (por hora)\n(capacidad 25 Personas)................... 1.67 UMA\n6) COSTO DE LOS SALONES SI SE LIQUIDAN DENTRO DEL PRIMER MES\nDE SU CONTRATACIÓN: a.1) Salón Catedral de lunes a jueves (por día)\n(capacidad 450 personas)................ 215.01 UMA a.2) Salón Catedral de viernes a domingo (por día)\n(capacidad 450 personas)................ 264.14 UMA b.1) Salón Casino de lunes a jueves (por día)\n(capacidad 200 personas)................. 202.04 UMA b.2) Salón Casino de viernes a domingo (por día)\n(capacidad 200 personas)................ 214.23 UMA c.1) Salón Rojo de lunes a jueves (por día)\n(capacidad 220 personas)................ 179.58 UMA c.2) Salón Rojo de viernes a domingo (por día)\n(capacidad 220 personas)................ 199.44 UMA d.1) Salón Ventanal o Salón Comedor de lunes a jueves\n(por día)(capacidad 50 personas c/u)..... 28.99 UMA d.2) Salón Ventanal o Salón Comedor de viernes a domingo\n(por día)(capacidad 50 personas c/u)..... 33.42 UMA e.1) Salón Dorado de lunes a jueves (por día)\n(capacidad 50 personas).................. 19.65 UMA e.2) Salón Dorado de viernes a domingo (por día)\n(capacidad 50 personas).................. 24.07 UMA\nLos Jardines, Patios y Terrazas f.1) Jardín Rotonda de lunes a jueves\n(capacidad de 250 personas)............. 133.90 UMA f.2) Jardín Rotonda de viernes a domingo\n(capacidad de 250 personas)............. 164.77 UMA f.3) Jardín Desértico de lunes a jueves\n(capacidad 250 personas)................. 133.90 UMA f.4) Jardín Desértico de viernes a domingo\n(capacidad 250 personas)................. 164.77 UMA g.1) Jardín Misional y Capilla de lunes a jueves\n(100 personas)........................... 80.79 UMA g.2) Jardín Misional y Capilla de viernes a domingo\n(100 personas)........................... 98.85 UMA h.1) Terraza Catedral de lunes a jueves\n(capacidad máxima 50 personas)........... 56.94 UMA h.2) Terraza Catedral de viernes a domingo\n(capacidad máxima 50 personas)........... 70.49 UMA\n7) COSTO PARA BANQUETEROS QUE EN EL AÑO INMEDIATO ANTERIOR\nHAYAN CONTRATADO 3 O MÁS VECES AL AÑO:\n1.- Salones Sociales: a.1) Salón Catedral de lunes a jueves\n(capacidad 450 personas)................ 203.06 UMA a.2) Salón Catedral de viernes a domingo\n(capacidad 450 personas)................ 249.55 UMA b.1) Salón Casino de lunes a jueves\n(capacidad de 200 personas)............. 190.82 UMA b.2) Salón Casino de viernes a domingo\n(capacidad de 200 personas)............. 202.33 UMA c.1) Salón Rojo de lunes a jueves\n(capacidad 220 personas)................ 169.60 UMA c.2) Salón Rojo de viernes a domingo\n(capacidad 220 personas)................ 188.37 UMA d.1) Salón Ventanal o Salón Comedor de lunes a jueves\n(por día) (capacidad 50 personas)........ 27.38 UMA d.2) Salón Ventanal o Salón Comedor de viernes a domingo\n(por día) (capacidad 50 personas)........ 31.57 UMA e.1) Salón Dorado de lunes a jueves (por día)\n(capacidad 50 personas).................. 18.55 UMA e.2) Salón Dorado de viernes a domingo (por día)\n(capacidad 50 personas).................. 22.80 UMA\nLos Jardines, Patios y Terrazas a.1) Jardín Rotonda de lunes a jueves\n(capacidad 250 personas)................ 126.98 UMA a.2) Jardín Rotonda de viernes a domingo\n(capacidad 250 personas)................ 155.76 UMA b.1) Jardín Misional y Capilla de lunes a jueves\n(capacidad 100 personas)................. 76.30 UMA b.2) Jardín Misional y Capilla de viernes a domingo\n(capacidad 100 personas)................. 93.36 UMA c.1) Terraza Catedral de lunes a jueves\n(capacidad 50 personas)................. 53.77 UMA c.2) Terraza Catedral de viernes a domingo\n(capacidad 50 personas).................. 66.58 UMA\n8) DE LAS RENTAS EN LOS ESPACIOS Y OFICINAS DEL RIVIERA\n(MENSUAL):\na) Oficina 1a(planta baja)...................... 111.58 UMA\nb) Oficina 2a(planta baja)...................... 89.27 UMA\nc) Oficina 4 (planta alta)...................... 111.58 UMA\nd) Oficina 5 (planta baja)...................... 27.90 UMA\ne) Oficina 6 (planta baja)...................... 55.79 UMA\nf) Oficina 7 (teatro)........................... 32.08 UMA\ng) Oficina 8 (teatro)........................... 32.08 UMA\nh) Oficina 9................................... 55.79 UMA\ni) Plaza Artesanal para artesanos internos...... 13.51 UMA\nj) Plaza Artesanal para artesanos externos...... 13.51 UMA\nk) Museo de Historia de Ensenada................ 55.80 UMA\nl) Casa de la Cultura........................... 0.00 UMA\n9) OTROS COBROS:\na) Aportación voluntaria...................... $10.00 pesos\nb) Plaza Artesanal cobro por día.............. 102.45 UMA\nc) Plaza Gastronómica.................... 20.79 A 44.64 UMA\nd) Otros espacios........................ 3.35 A 155.89 UMA\n10) COBROS PARA EL PERSONAL DEL RIVIERA, ASÍ COMO PARA EVENTOS\nPROMOVIDOS POR LA ENTIDAD:\n1.- Salones sociales: a.1) Salón Catedral de lunes a jueves (por día)\n(capacidad máxima 450 personas)......... 149.32 UMA a.2) Salón Catedral de viernes a domingo (por día)\n(capacidad máxima 450 personas)......... 183.43 UMA b.1) Salón Casino de lunes a jueves (por día)\n(capacidad máxima 200 personas)......... 140.30 UMA b.2) Salón Casino de viernes a domingo (por día)\n(capacidad máxima 200 personas)......... 148.77 UMA c.1) Salón Rojo de lunes a jueves (por día)\n(capacidad máxima 220 personas)......... 124.71 UMA c.2) Salón Rojo de viernes a domingo (por día)\n(capacidad máxima 220 personas)......... 138.50 UMA d.1) Salón Ventanal o Salón Comedor de lunes a jueves\n(por día) (capacidad 50 personas c/u)..... 15.91 UMA d.2) Salón Ventanal o Salón Comedor de viernes a domingo\n(por día) (capacidad 50 personas c/u).... 27.85 UMA e.1) Salón Dorado de lunes a jueves (por día)\n(capacidad 50 personas).................. 16.34 UMA e.2) Salón Dorado de viernes a domingo (por día)\n(capacidad 50 personas).................. 20.11 UMA\nLos Jardines, Patios y Terrazas a.1) Jardín Rotonda de lunes a jueves (por día)\n(capacidad 250 personas)................ 112.29 UMA a.2) Jardín Rotonda de viernes a domingo (por día)\n(capacidad 250 personas)................ 136.88 UMA b.1) Jardín Misional y Capilla de lunes a jueves (por día)\n(capacidad 100 personas)................. 67.33 UMA b.2) Jardín Misional y Capilla de viernes a domingo\n(por día) (capacidad 100 personas)....... 82.37 UMA c.1) Terraza Catedral de lunes a jueves (por día)\n(capacidad 50 personas).................. 47.45 UMA c.2) Terraza Catedral de viernes a domingo (por día)\n(capacidad 50 personas)................. 58.75 UMA d.1) Áreas Familiares de lunes a jueves (por día)\n(capacidad 90 personas).................. 19.91 UMA d.2) Áreas Familiares de viernes a domingo (por día)\n(capacidad 90 personas).................. 24.45 UMA\n11) DE LOS PAQUETES PARA EVENTOS (POR PERSONA) ENTRE LOS QUE SE\nINCLUYEN:\na) Cafetería\nPor persona...................... de 0.74 A 15 UMA\n12) PARA EVENTOS DE 1 A 4 HORAS EN LOS SALONES:\n1.- Salones a.1) Salón Catedral de lunes a jueves (por hora)\n(capacidad 450 personas)................. 34.13 UMA a.2) Salón Catedral de viernes a domingo (por hora)\n(capacidad 450 personas)................. 41.93 UMA b.1) Salón Casino de lunes a jueves (por hora)\n(capacidad 200 personas)................. 32.07 UMA b.2) Salón Casino de viernes a domingo (por hora)\n(capacidad 200 personas)................. 34.01 UMA c.1) Salón Rojo de lunes a jueves (por hora)\n(capacidad 220 personas)................. 28.50 UMA c.2) Salón Rojo de viernes a domingo (por hora)\n(capacidad 220 personas)................. 32.18 UMA d.1) Salón Ventanal o Salón Comedor de lunes a jueves\n(por hora)(capacidad 50 personas)......... 4.36 UMA d.2) Salón Ventanal o Salón Comedor de viernes a domingo\n(por hora)(capacidad 50 personas)......... 6.02 UMA e.1) Salón Dorado de lunes a jueves (por hora)\n(capacidad 50 personas)................... 4.36 UMA e.2) Salón Dorado de viernes a domingo (por hora)\n(capacidad 50 personas)................... 6.02 UMA\nLos Jardines, Patios y Terrazas a.1) Jardín Rotonda de lunes a jueves (por hora)\n(capacidad 250 personas)................. 29.80 UMA a.2) Jardín Rotonda de viernes a domingo (por hora)\n(capacidad 250 personas)................. 41.19 UMA b.1) Jardín Misional y Capilla de lunes a jueves (por hora)(capacidad 150 personas)........... 12.65 UMA b.2) Jardín Misional y Capilla de viernes a domingo\n(por hora)(capacidad 150 personas)....... 17.63 UMA c.1) Terraza Catedral de lunes a jueves (por hora)\n(capacidad 50 personas).................. 12.65 UMA c.2) Terraza Catedral de viernes a domingo (por hora)\n(capacidad 50 personas).................. 17.63 UMA\n13) IMPORTE POR DEPÓSITOS EN GARANTÍA POR DAÑOS Y PERJUICIOS\nREEMBOLSABLE POR EL USO DE ESPACIOS POR MÁS DE DOS HORAS:\na) Salón Catedral........................ 2.23 a 111.58 UMA\nb) Salón Casino........................... 2.23 a 111.58 UMA\nc) Salón Rojo............................ 2.23 a 111.58 UMA\nd) Jardín Rotonda........................ 2.23 a 111.58 UMA\ne) Jardín Misional....................... 2.23 a 111.58 UMA\nf) Paseo de las Américas................. 2.23 a 111.58 UMA\ng) Terraza Catedral...................... 2.23 a 111.58 UMA\nh) Mezzanine............................. 2.23 a 111.58 UMA\ni) Salón Ventanales...................... 2.23 a 111.58 UMA\nj) Teatro José Luis Fernández Bandini.... 2.23 a 111.58 UMA\nk) Salón Comedor......................... 2.23 a 111.58 UMA\nl) Salón Dorado.......................... 2.23 a 111.58 UMA\nm) Patio Bugambilias..................... 2.23 a 111.58 UMA\nn) Patio Margaritas...................... 2.23 a 111.58 UMA\no) Área Familiar #1...................... 2.23 a 111.58 UMA\np) Área Familiar #2...................... 2.23 a 111.58 UMA\nq) Plaza Artesanal....................... 2.23 a 111.58 UMA\nr) Jardín Desértico...................... 2.23 a 111.58 UMA\n14) OTROS SERVICIOS PRESTADOS EN DIFERENTES ÁREAS Y ÉPOCAS DEL\nAÑO POR PERSONA:\na) Tours................................ De 0.31 a 5.00 UMA\nb) Recorridos nocturnos................. De 1.11 a 5.00 UMA\nc) Pláticas............................. De 1.11 a 5.00 UMA\n15) SERVICIO DE VIGILANCIA CONSIDERANDO EL TIPO DE EVENTO\n(1 GUARDIA POR C/50 PERSONAS):\na) Turno de 8 horas.............................. 9.37 UMA\nb) Turno de 12 horas............................. 12.01 UMA\nc) Turno de 24 horas............................. 24.01 UMA\nd) Servicios de vigilancia de policía sin portar arma d.1) Turno de 6 horas......................... 9.35 UMA\ne) Servicios de vigilancia de policía portando arma e.1) Turno de 6 horas......................... 11.00 UMA\n16) MATRIMONIOS CELEBRADOS EN CAPILLA DEL JARDÍN MISIONAL: a.1) Renta de Capilla para celebración de matrimonios de lunes a jueves a.1.1) De 8 am a 3 pm (hora hábiles)...... 4.46 UMA a.1.2) De 3 pm a 5 pm (horas inhábiles)... 5.58 UMA a.2) Renta de Capilla para celebración de matrimonios de viernes a domingo a.2.1) De 8:00 am a 1:00 pm............... 6.70 UMA a.2.2) De 1:00 pm a 5:00 pm............... 7.81 UMA\n17) COBRO POR TOMAR FOTOGRAFÍAS DENTRO DE LAS INSTALACIONES Y\nJARDINES DEL RIVIERA:\na) Bodas, XV años, graduaciones y otros.............. 4.28 UMA\n18) DESCUENTOS Y PROMOCIONES:\na)Los Eventos Masivos quedan excluidos de los descuentos y/o promociones de la presente Ley.\nb)Los descuentos y/o promociones de la presente Ley no son acumulables entre sí.\nc)Los descuentos para personal del Riviera serán válidos únicamente 1 vez por año.\n19) BENEFICIOS FISCALES:\nLa renta de los salones, oficinas y/o espacios solicitados por las siempre y cuando:\n1.- Sean en beneficio de la propia dependencia y no de un tercero.\n2.- Si la dependencia municipal percibe ingresos derivados tercero.\n3.- El evento objeto de beneficio no se contraponga al objeto público de la dependencia.\n4.- Sean solicitados a través del Presidente Municipal.\n20) VENTAS DEL BAR \"ANDALUZ\":\na) Cerveza............................... $ 45.00 a $ 100.00\nb) Vinos y licores....................... $ 70.00 a $1,000.00\nc) Margaritas............................ $ 50.00 a $ 200.00\nd) Bebidas Preparadas.................... $ 60.00 a $ 250.00\ne) Agua, Café y Refrescos................ $ 25.00 a $ 70.00\nf) Botanas............................... $ 30.00 a $ 150.00\ng) Otros................................. $ 20.00 a $ 250.00\n* Los precios del Bar pueden variar debido al costo de los insumos, Promociones y Eventos Especiales.\nIV.- SERVICIOS QUE PRESTA EL INSTITUTO MUNICIPAL DE CULTURA Y\nDESARROLLO HUMANO DE ENSENADA:\n1.- Los derechos por los talleres impartidos en la casa de la cultura Ensenada:\nI. Por concepto de inscripción a grupo, será cubierto por persona, de acuerdo a la siguiente tabla:\na) Inscripción................................. 4.16 UMA a.1) Cuando se inscriban dos o más miembros de una misma familia......... 2.08 UMA a.2) Tratándose de personas con discapacidad, empleados del\nInstituto Municipal de\nCultura y Desarrollo Humano de Ensenada y/o comisionados a este instituto...................... 0.00 UMA a.3) Tratándose de personas adultas mayores, jubilados o pensionados y empleados del\nGobierno Municipal.................... 2.08 UMA a.4) Tratándose de personas de escasos recursos y sean seleccionados por medio de un estudio socioeconómico a consideración del Titular del\nIMCUDHE............................... 2.08 UMA\nII.- Por concepto de mensualidad, será cubierto por persona de acuerdo a lo siguiente:\na) Mensualidad.................................... 6.24 UMA a.1) Cuando se trate de dos o más miembros de una misma familia, a partir del segundo alumno............... 3.12 UMA a.2) Tratándose de personas con discapacidad, empleados del\nInstituto Municipal de Cultura y Desarrollo Humano de Ensenada y/o comisionados a este instituto........ 0.00 UMA a.3) Tratándose de personas adultas mayores, jubilados o pensionados y empleados del Gobierno Municipal.......... 3.12 UMA a.4) Tratándose de personas de escasos recursos y sean seleccionados por medio de un estudio socioeconómico a consideración del Titular del IMCUDHE.............................. 3.12 UMA a.5) Tratándose de estudiantes de los talleres de piano y violín cuando se suspendan clases por instrucciones de Oficialía Mayor................ 3.12 UMA\n2.- Los talleres impartidos en las extensiones de la casa de la cultura ubicadas en las delegaciones, serán cubiertos por personas de acuerdo a la siguiente tabla:\nI. Por concepto de inscripción a grupo, será cubierto por persona, de acuerdo a lo siguiente:\na) Inscripción................................. 2.50 UMA a.1) Cuando se inscriben dos o más miembros de una misma familia, los subsecuentes....................... 1.25 UMA a.2) Tratándose de personas con discapacidad, empleados del\nInstituto Municipal de Cultura y Desarrollo Humano de Ensenada y/o comisionados a este instituto...... 0.00 UMA a.3) Tratándose de personas adultos mayores, jubilados o pensionados y empleados del\nGobierno Municipal..................... 1.01 UMA\nII. Por concepto de mensualidad en las extensiones, será cubierto por persona de acuerdo a la siguiente:\na) Mensualidad.................................... 5.00 UMA a.1) Cuando se trate de dos o más miembros de una misma familia, a partir del segundo alumno.................................... 2.50 UMA a.2) Tratándose de personas con discapacidad, empleados del\nInstituto Municipal de Cultura y Desarrollo Humano de Ensenada y/o comisionados a este instituto......... 0.00 UMA a.3) Tratándose de personas adultos mayores, jubilados o pensionados y empleados del\nGobierno Municipal........................ 2.50 UMA\n3.- Cobro de entradas para eventos de promoción y difusión cultural:\na) Clausuras o cierres casa de la cultura................................... 0.45 a 1.68 UMA\nb) Clausuras o cierres casa de la cultura extensiones....................... 0.00 a 1.32 UMA\nc) Presentaciones artísticas................. 0.00 a 6.24 UMA\nd) Presentaciones musicales y/o conciertos................................ 0.00 a 8.40 UMA\ne) Presentaciones artísticas dirigidas a una población de hasta 500 personas....................... 0.00 a 10.40 UMA\nf) Por concepto de eventos\nRecaudatorios........................ 0.00 UMA EN ADELANTE\n4.- Los talleres impartidos en el Centro de Desarrollo Comunitario de la Col. 89\nI. Por concepto de inscripción a grupo, será cubierto por persona, de acuerdo a lo siguiente:\na) Inscripción........................ 2.50 UMA a.1) Cuando se inscriben dos o más miembros de una misma familia, los subsecuentes................. 1.25 UMA a.2) Tratándose de personas con discapacidad, empleados del\nInstituto Municipal de\nCultura y Desarrollo Humano de Ensenada y/o comisionados a este instituto................. 0.00 UMA a.3) Tratándose de personas adultas mayores, jubilados o pensionados y empleados del\nGobierno Municipal........... 2.50 UMA\nII. Por concepto de mensualidad en el Centro de Desarrollo\nComunitario en Col. 89 será cubierto por persona de acuerdo a la siguiente:\na) Mensualidad...................... 3.50 UMA a.1) Cuando se trate de dos o más miembros de una misma familia, a partir del segundo alumno....................... 2.50 UMA a.2) Tratándose de personas con discapacidad, empleados del\nInstituto Municipal de\nCultura y Desarrollo Humano de Ensenada y/o comisionados a este instituto............. 0.00 UMA a.3) Tratándose de personas adultas mayores, jubilados o pensionados y empleados del\nGobierno Municipal............ 2.50 UMA\n5.- Participación en espacios para venta en eventos de promoción y difusión cultural:\na) Venta de alimentos.................. 0.00 UMA a 20.80 UMA\nb) Artesanías.......................... 0.00 UMA a 20.80 UMA\nc) Venta de bebidas con graduación alcohólica\n(excepto cerveza)............................. 53.26 UMA\nd) Venta de cerveza............................... 56.81 UMA\ne) Venta de vino.................................. 30.77 UMA\nf) Venta de cerveza artesanal..................... 30.77 UMA\ng) Todas las anteriores, para venta y uso exclusivo del Instituto Municipal de\nCultura y desarrollo humano de Ensenada.......... 0.00 UMA\nh) Venta de Suvenires............... 9.21 UMA A 30.77 UMA\n6.- Los derechos por los cursos de verano impartidos en la Casa de de la Col. 89.\na) Cursos de verano por paquete......... 7.82 UMA A 10.40 UMA\nb) Cursos de verano por taller.......... 4.47 UMA A 6.30 UMA\nc) Cursos de verano en extensiones por paquete.......................... 4.47 UMA A 6.30 UMA\nd) Curso de verano en extensiones por taller........................... 2.24 UMA A 4.15 UMA\ne) Curso de verano en el C.D.C col. 89 por paquete............... 2.24 UMA A 4.15 UMA\nf) Curso de verano en el C.D.C col. 89 por taller................ 2.24 UMA A 4.15 UMA\n7.- Los derechos por reinscripción o renovación al padrón de\nCultura y Desarrollo Humano de Ensenada............ 2.00 UMA\n8.- Capacitaciones en General................ 1.12 UMA A 6.30 UMA\n9.- Venta de playeras y/o sudaderas de Casa de la Cultura............................. 1.12 UMA A 6.70 UMA\n10.- Cursos extracurriculares............... 3.00 UMA A 31.20 UMA\n11.- Constancia con valor curricular........ 2.00 UMA A 5.20 UMA\n12.- Otros ingresos:\na) Venta de alimentos...................... 0.10 UMA A 4.20 UMA\nb) Venta de bebidas........................ 0.15 UMA A 1.05 UMA\nc) Venta de suvenires...................... 0.22 UMA A 6.70 UMA\nd) Venta de libros......................... 0.56 UMA A 5.58 UMA\ne) Sala audiovisual de la Biblioteca\nPública Modelo “José Alfredo Cañas\nMendoza” (costo por día)............... 4.20 UMA A 52.00 UMA\nf) Estacionamiento por cajón de la\nBiblioteca Pública Modelo “José\nAlfredo Cañas Mendoza”\n(costo por día)........................ 0.26 UMA A 1.10 UMA\ng) Estacionamiento de la Biblioteca\nPública Modelo “José Alfredo\nCañas Mendoza” (costo mensual)........ 50.00 UMA A 63.00 UMA\nh) Por concepto de donativos.............. 16.74 UMA EN ADELANTE\ni) Por concesión de espacios............ 40.00 UMA A 223.17 UMA\nj) Por concepto de renta del salón\nMorisco de Casa de la Cultura\n(costo por día)....................... 20.00 UMA A 42.00 UMA\nk) Cobro de copias e impresiones en la Biblioteca Digital........ 0.0085 UMA A 0.085 UMA\n(Costo por hoja)\nV.- LOS SERVICIOS QUE PRESTA EL FIDEICOMISO MUNICIPAL PARA EL\nDESARROLLO URBANO DE ENSENADA, SE COBRARÁN CONFORME A LO\nSIGUIENTE:\n1.- Expedición de títulos, constancias o copias de documentos, legalización de firmas y demás servicios administrativos prestados:\na) Copia(s) cotejada(s) de 1 a 5 hojas.............. 2.32 UMA a.1) Copia cotejada a partir de la hoja número 6 en adelante........................ 0.31 UMA\n(Copias de: Números Oficiales, Medidas y Colindancias, Títulos de Propiedad, Contratos, Adendums, Convenios).\nb)Cesión de derechos................................ 10.39 UMA\nc)Carta de instrucción sin cesión de derechos.................................. 40.66 a 44.73 UMA\n(Inmuebles con superficie de 1 a 500 m²).\nd)Carta de instrucción con cesión de derechos.................................. 48.48 a 53.33 UMA\n(Inmuebles con superficie de 1 a 500 m²).\ne)Carta de instrucción para escrituración por medio de notaría pública: e1)Inmuebles con superficie de 501 a 1000m²\n71.40 a 78.54 UMA e2)Inmuebles con superficie de 1001 a 1500m²\n102.13 a 112.34 UMA e3)Inmuebles con superficie de 1501 a 2000m²\n148.23 a 163.05 UMA e4)Inmuebles con superficie de 2001 a 3000m²\n194.33 a 213.76 UMA e5)Inmuebles con superficie de 3001 a 4000m²\n278.84 a 306.72 UMA e6)Inmuebles con superficie de 4001 a 5000m²\n371.04 a 408.14 UMA e7)Inmuebles con superficie de 5001 a 6000m² el cobro será negociable.................\nNota: El cobro del inciso e7), se determinará con base en la variante de las Leyes de Ingresos Estatal y Municipal vigentes. e8)Firma del fiduciario por escrituración.. 9.60 a 10.56 UMA e9)Renovación de carta instrucción........ 16.88 a 18.57 UMA\nf)Renovación de carta instrucción........... 16.88 a 18.57 UMA\ng) Elaboración de adendum o convenios a beneficiarios..................................... 3.50 a 6.00 UMA h.1)Elaboración de adendum a las Asociaciones\nPúblico Privadas....................... 20.00 a 40.00 UMA h.2)Elaboración de convenios a las Asociaciones\nPúblico Privadas........................ 40.00 a 80.00 UMA\ni)Servicio de entrega de deslinde físico posterior a la venta...................... 35.00 UMA\nj)Carta de liquidación..................... 2.00 UMA\nk)Titulación sin Cesión de Derechos, con libertad de gravámenes............................ 140.00 a 150.00 UMA\nl)Titulación con Cesión de Derechos, con libertad de gravámenes............................ 160.00 a 170.00 UMA\nm)Otros servicios............................\nSe cobrarán derechos de conformidad al presupuesto que al efecto se realicen para los servicios que presta el Fideicomiso\nMunicipal para el Desarrollo Urbano de Ensenada, los que en todo caso serán proporcionales al costo del servicio.\nn)Gastos operativos por contratación de inmuebles....... 2.5 %\no)Tasa de Interés Anual por contratación de inmuebles.... 6.51%\np)Recargos por concepto de mora a beneficiarios del fideicomiso....................................... 1.0%\nSe cobrará un recargo moratorio del 1% mensual por cada pago.\nq)Recargos por concepto de mora a Asociaciones Público\nPrivadas privadas.\n2)Servicios relacionados con Obra Pública\n2.1)Por participar en un padrón de contratistas del Fideicomiso:\n2.1.1)Registro Anual al Padrón de Contratistas... 10.00 UMA\n2.2)Por participar en concursos de obras\n2.2.1)Por participar en cursos de obra o invitación a cuando menos 3.............................. 5.40 UMA\nVI.- LOS SERVICIOS QUE PRESTA EL FIDEICOMISO LA BUFADORA, SE\nCOBRARÁN DE LA SIGUIENTE MANERA:\nCon fundamento en los artículos 18 y 32 del REGLAMENTO DEL\nFIDEICOMISO DEL CENTRO COMERCIAL LA BUFADORA se establece que:\nTodos los usuarios cubrirán el pago que se origine del impuesto predial, concesión de la zona federal, de electricidad, limpieza, vigilancia y todo lo necesario para el óptimo mantenimiento del\nCentro Comercial, en forma proporcional a su derecho de uso.\nPor cargas comunes se entiende el costo de la atención de las áreas comunes, prestación de servicios comunes, como limpieza, vigilancia, administración, mantenimiento y todos aquellos servicios que sean para beneficio de los usuarios en general.\nPor lo tanto, se establecen las siguientes cuotas:\na) CUOTAS LOCATARIOS.- Según lo establecido en el artículo\n34 del REGLAMENTO DEL FIDEICOMISO DEL CENTRO COMERCIAL\nLA BUFADORA: su uso y aprovechamiento..................... 1.38 UMA\nLOCALES Cuota\nLocal 1........................................ 4.13 UMA\nLocal 2........................................ 17.21 UMA\nLocal 97....................................... 15.14 UMA\nLocal 98....................................... 14.18 UMA\nb) RENTA DE BAÑOS.- Según lo establecido en el artículo 34\nBUFADORA:\nLos usuarios pagarán una renta mensual por el uso de los baños:\nBaños.......................................... 66.94 UMA\nc) RENTA DE KIOSKO.- Según lo establecido en el artículo 34\ndel REGLAMENTO DEL FIDEICOMISO DEL CENTRO COMERCIAL LA\nBUFADORA:\nLos usuarios pagarán una renta mensual por día:\nKiosco por día................................ 39.05 UMA\nKiosco por mes................................ 250.00 UMA\nd) RECOLECCIÓN DE LA BASURA PARA LOCALES COMERCIALES Y\nRESTAURANTES.- Según lo establecido en el artículo 34 del\nBUFADORA: basura:\nRestaurantes grandes........................... 23.43 UMA\nRestaurantes chicos............................ 13.38 UMA\nPiñeros........................................ 8.93 UMA\nCarretas de comida............................. 5.57 UMA\nArtesanos...................................... 2.24 UMA\nNeveros y paleteros............................ 4.46 UMA\ne) ESTACIONAMIENTO.- Según lo establecido en el artículo 34\nBUFADORA:\nLos usuarios pagarán una renta mensual por estacionamiento:\nEstacionamiento................................ 27.89 UMA\nf) Entrada al Fenómeno Natural (KIAMA) COOPERACIÓN f.1) Adultos................................ $15.00 pesos f.2) Niños.................................. $10.00 pesos f.3) Cooperación preferente Turista en tu\nEstado, residentes de Baja California... $10.00 pesos f.4) Residentes del municipio de Ensenada, discapacitados y adultos mayores de 65 años................................... Entrada gratuita\ng) CUOTAS SEMIFIJOS.- Según lo establecido en los artículos\n34 y 40 inciso s, del REGLAMENTO DEL FIDEICOMISO DEL\nCENTRO COMERCIAL LA BUFADORA:\nEl Administrador del Fideicomiso La Bufadora, cuando lo estime pertinente, podrá otorgar permisos para actividades de comercio semifijo, temporales, previo el pago de las cuotas mensuales, semestrales, o anuales que en cada caso determine el comité técnico, atendiendo a la naturaleza de la actividad que se realice.\nEl Administrador del Fideicomiso La Bufadora, tendrá la facultad\nLa Bufadora. Estos permisos y sus cuotas se regirán también por lo predispuesto en el Reglamento del Fideicomiso.\nActividad SEMIFIJOS Cuota\na) Elaboración, exposición y venta de artesanías pintadas a mano en platos y/o conchas............................. 20.65 UMA\nb) Venta de fotollaveros.......................... 13.77 UMA\nc) Exposición y venta de cuarzos.................. 33.09 UMA\nd) Elaboración, exposición y venta de artesanías pintadas a mano en madera......................................... 13.77 UMA\ne) Elaboración y venta de Souvenirs............... 22.37 UMA\nf) Exposición y venta de productos artesanales Ecu................................ 42.36 UMA\ng) Elaboración y venta de productos comestibles.................................... 68.83 UMA\nh) Elaboración y venta de productos comestibles.................................... 22.37 UMA\ni) Elaboración y venta de productos comestibles.................................... 45.00 UMA\nj) Elaboración y venta de productos comestibles.................................... 18.07 UMA\nk) Músico solista, norteños, mariachis y conjuntos musicales:\nSolista....................................... 7.82 UMA\nNorteño, mariachis y conjuntos................ 14.00 UMA\nl) Danzantes...................................... 17.51 UMA\nm) Fotografía y videos............................ 33.47 UMA\nn) Paletas y nieves............................... 5.57 UMA\no) Publicidad:\nLos usuarios pagarán una renta mensual por publicidad de:\nCarteleras 2.5 x 3............................. 44.63 UMA\nCarteleras 3.5 x 6............................. 89.26 UMA\nAdemás de las cuotas establecidas, el artículo 38 del\nREGLAMENTO DEL FIDEICOMISO DEL CENTRO COMERCIAL LA BUFADORA, establece que:\n1) El usuario que no cubra puntualmente sus cuotas, pagará 2% mora.\n2) Después de treinta días de mora, cubrirá además, como pena convencional una cantidad igual al 50% del importe mensual de su cuota por cada mes en que se mantuviere en mora.\n3) Siempre que sea necesario efectuar procedimiento de cobro y ejecución, el Fideicomiso cobrará por este concepto el equivalente al 20% del total del crédito insoluto.\nVII.- SERVICIOS QUE PRESTA EL CONSEJO DE URBANIZACIÓN\nMUNICIPAL DE ENSENADA:\nUNIDAD DE MEDIDA Y ACTUALIZACIÓN\n(UMA)VIGENTE\nI.- Certificación de libertad de gravamen fiscal. Por predio.................... 4.29 UMA\nII.- Constancias certificadas.\nPor predio..................................... 4.29 UMA\nIII.- Ubicación de toma o descarga.\nPor predio..................................... 7.24 UMA\nIV.- Elaboración del presupuesto para obra de pavimentación. Por m²............. 0.04 UMA\nV.- Elaboración del proyecto para obra de pavimentación. Por m²............. 0.40 UMA\nVI.- Otros servicios que presta la paramunicipal:\n1.- Copias simples en tamaño carta u oficio escala de grises; por página...................... 0.02 UMA\n2.- Copias simples en tamaño doble carta escala de grises 27.94 x 43.18 cm; por página........ 0.03 UMA\n3.- Copias digitalizadas tamaño carta y doble carta en PDF a todo color o escala de grises; por página................................. 0.02 UMA\n4.- Copias certificadas de documentos emitidos por el CUME en tamaño carta u oficio escala de grises:\n4.1) Primeras 1 a 3 hojas.................. 4.01 UMA\n4.2) Hojas de la 4 y posteriores extras cada una....................... 0.23 UMA\n5.- Constancia de registro de contratista CUME.\nRevalidación cada primer trimestre del año.. 7.15 UMA\n6.- Por participar en las siguientes modalidades de contratación: a.- Adjudicación directa; por obra......... 3.30 UMA b.- Invitación a cuando menos 3 personas; por obra............................... 4.40 UMA c.- Licitación pública; por obra........... 7.42 UMA\n7.- Presentación en cursos de urbanización con duración de 8 horas, presencial y/o en línea, mínimo 10 inscripciones. Por persona....... 2.66 UMA\n8.- Presentación en conferencias de urbanización con duración de 1 hora, presencial y/o en línea, mínimo 10 inscripciones. Por persona................................... 0.89 UMA\n9.- Presentación de proyectos en promoción de obras, con duración de 1 hora, presencial y/o en línea, mínimo 20 asistentes. Por persona.................................. 0.45 UMA\n10.- Por la supervisión técnica de obra para vigilar cumplimiento de las normas de calidad y especificaciones aprobadas del proyecto definitivo de pavimentación. Por m²........ 0.43 UMA\nVIII.- LOS SERVICIOS QUE PRESTA EL INSTITUTO MUNICIPAL DEL\nDEPORTE Y RECREACIÓN DE ENSENADA, BAJA CALIFORNIA, SE\nCOBRARÁN DE LA MANERA SIGUIENTE:\n1.- ENTRADAS EN GENERAL: COOPERACIÓN\nA) UNIDAD DEPORTIVA RAÚL RAMÍREZ LOZANO EN VALLE DORADO:\na) Público en general.............................. 0.052 UMA\nb) Futbolistas..................................... 0.052 UMA\nc) Campo empastado fútbol soccer................... 0.104 UMA\nd) Campo fútbol americano.......................... 0.156 UMA\ne) Cancha de tenis por persona..................... 0.310 UMA\n(POR HORA)\nf) Fútbol americano o Flag con convenio............ 0.208 UMA\ng) Box en evento amateur........................... 0.104 UMA\nh) Rugby........................................... 0.156 UMA\ni) Frisbee......................................... 0.104 UMA\nB) UNIDAD DEPORTIVA JUAN A. RODRÍGUEZ SULLIVAN:\na) Público en general.............................. 0.052 UMA\nb) Deportistas de fútbol rápido.................... 0.052 UMA\nc) Campo empastado soccer.......................... 0.104 UMA\nd) Béisbol......................................... 0.052 UMA\ne) Béisbol eventos especiales...................... 0.104 UMA\nC) GIMNASIO MUNICIPAL ÓSCAR ¨TIGRE¨ GARCÍA:\na) Entradas básquetbol y voleibol.................. 0.052 UMA\nD) UNIDAD DEPORTIVA TRES COLONIAS:\na) Público en general.............................. 0.052 UMA\nE) UNIDAD DEPORTIVA SIGLO XXI:\na) Público en general.............................. 0.052 UMA\nb) Deportistas..................................... 0.052 UMA\nc) Sóftbol (con convenio).......................... 0.104 UMA\nF) UNIDAD DEPORTIVA PÓRTICOS DEL MAR:\na) Público en general.............................. 0.052 UMA\nG) GIMNASIO JOSÉ JEREMÍAS REYES RONFINNI EN MANEADERO:\na) Público en general.............................. 0.052 UMA\nb) Tae Kwon Do (por hora).......................... 0.208 UMA\nH) UNIDAD DEPORTIVA VICENTE GUERRERO EN COLONIA HIDALGO:\na) Público en general.............................. 0.052 UMA\nb) Deportistas..................................... 0.052 UMA\nc) Cancha de tenis por persona..................... 0.310 UMA\n(POR HORA)\nI) UNIDAD DEPORTIVA MISIONES DE LA PRESA:\na) Público en general.............................. 0.052 UMA\nJ) UNIDAD DEPORTIVA EN DELEGACIÓN EL SAUZAL:\na) Público en general.............................. 0.052 UMA\nb) Deportistas..................................... 0.052 UMA\nc) Tae kwon Do (por hora).......................... 0.208 UMA\nK) GIMNASIO JOSÉ MARÍA MORELOS EN EL EX-EJIDO CHAPULTEPEC:\na) Público en general.............................. 0.052 UMA\nb) Deportistas..................................... 0.052 UMA\nc) Tae kwon Do (por hora).......................... 0.208 UMA\nL) UNIDAD DEPORTIVA FRANCISCO VILLA-VIDA DIGNA:\na) Público en general.............................. 0.052 UMA\nM) CAMPO EMPASTADO FÚTBOL 7 EN VILLAS VI:\na) Deportistas..................................... 0.052 UMA\nN) CAMPO EMPASTADO EN LA COL. AMPLIACIÓN 89:\na) Público en general.............................. 0.052 UMA\nO) GIMNASIO DE ACONDICIONAMIENTO FÍSICO EN U.D SULLIVAN:\na) Público en general................... 0.450 UMA (POR HORA)\nb) Personas de escasos recursos......... 0.156 UMA (POR HORA)\nc) Estudiantes.......................... 0.104 UMA (POR HORA)\nd) Mensualidad por 6 días a la semana..... de 2.64 a 5.96 UMA\ne) Entrenamientos deportistas seleccionados.. GRATUITO\nP) UNIDAD DEPORTIVA TODOS SANTOS:\na) Público en general.............................. 0.052 UMA\nQ) UNIDAD DEPORTIVA SANTO TOMÁS:\na) Público en general.............................. 0.052 UMA\nR) UNIDAD DEPORTIVA VALLE DE LAS PALMAS:\na) Público en general.............................. 0.052 UMA\nS) UNIDAD DEPORTIVA EN EL POBLADO DE OJOS NEGROS:\na) Público en general.............................. 0.052 UMA\nT) UNIDAD DEPORTIVA GRANJAS EL GALLO:\na) Público en general.............................. 0.052 UMA\nU) UNIDAD DEPORTIVA SALVADOR ROSAS MAGALLÓN:\na) Público en general.............................. 0.052 UMA\nV) UNIDAD DEPORTIVA NOROESTE (REAL MADRID)\na) Público en general.............................. 0.052 UMA\nb) Deportistas campo empastado..................... 0.104 UMA\nW) SALÓN DE LA FAMA DEL DEPORTE:\na) Público en general............................. 0.210 UMA\nb) Alumnos de escuelas públicas................... GRATUITO\nc) Recorrido guiado (Mínimo 5 personas, máximo 10 personas, público en general)..... 0.420 UMA POR\nPERSONA\nd) Recorrido guiado (Mínimo 5 alumnos, máximo 10 alumnos, escuelas privadas)....... 0.170 UMA POR\nPERSONA\nX) OTRAS UNIDADES\na) Público en general.............................. 0.052 UMA\nY) TODAS LAS UNIDADES:\na) En eventos especiales en colaboración............ 0.220 UMA\nb) En eventos especiales........................... 0.310 UMA\n2.- PROGRAMA VACACIONAL DE VERANO:\na) Unidad Deportiva Juan A.\nRodríguez Sullivan............................... 18.42 UMA\nb) Unidad Deportiva Raúl Ramírez Lozano............. 18.42 UMA\nc) Unidad Deportiva Tres Colonias................... 11.81 UMA\nd) Unidad Deportiva Pórticos del Mar................ 11.81 UMA\ne) Unidad Deportiva Francisco Villa................. 11.81 UMA\nf) Unidad Deportiva Vicente Guerrero en Colonia Hidalgo............................... 13.63 UMA\ng) Unidad Deportiva Misiones de la Presa............. 6.49 UMA\nh) Unidad Deportiva Adolfo Ruiz Cortines............. 6.49 UMA\ni) Unidad Deportiva Bella Vista...................... 6.49 UMA\nj) Todas las Delegaciones Municipales................ 6.49 UMA\nk) Unidad Deportiva Todos Santos..................... 6.49 UMA\n3.- DESCUENTOS PROGRAMA VACACIONAL\nTIPO COSTO COSTO COSTO COSTO\nHermanos 1 18.42 UMA 11.81 UMA 13.63 UMA 6.49 UMA\nHermanos 2 14.73 UMA 9.44 UMA 10.90 UMA 5.19 UMA\nHermanos 3 12.90 UMA 8.27 UMA 9.55 UMA 4.55 UMA\nHermanos 4 11.05 UMA 7.08 UMA 8.17 UMA 3.89 UMA\nSindicato en Unidad Deportiva Raúl Ramírez Lozano...... 13.63 UMA\nNOTA.- SE APRUEBA AL DIRECTOR, EN 3RA SESIÓN ORDINARIA DE JUNTA\nFORMA DISCRECIONAL OTORGUE LOS DESCUENTOS HASTA EL 100% EN\nCASOS ESPECÍFICOS.\n4.- ESPACIOS DE CAFETERÍA Y OTROS:\nMENSUAL\na) Unidad Deportiva Raúl Ramírez Lozano cafetería........................................ 62.44 UMA\nb) Unidad Deportiva Juan A. Rodríguez\nSullivan cafetería............................... 62.44 UMA\nc) Gimnasio Municipal Oscar ¨Tigre¨ García cafetería........................................ 62.44 UMA\nd) Unidad Vicente Guerrero en Col. Hidalgo.......... 29.89 UMA\ne) Unidad Deportiva Pórticos del Mar (puesto)....... 22.89 UMA\nf) Puesto de tacos.................................. 93.69 UMA\ng) Expendio de agua................................. 93.69 UMA\nh) Espacio para carrito de hotdogs.................. 31.22 UMA\ni) Unidad Deportiva Tres Colonias (puesto).......... 31.22 UMA\nj) Unidad Deportiva Francisco Villa cafetería....... 31.22 UMA\nk) Gimnasio José Ma Morelos cafetería............... 27.09 UMA\nl) Unidad Deportiva Todos Santos.................... 22.89 UMA\nm) Unidad Deportiva Santo Tomás..................... 22.89 UMA\nn) Unidad Deportiva Valle De Las Palmas............. 22.89 UMA\no) Unidad Deportiva en el Poblado de Ojos Negros.... 22.89 UMA\np) Unidad Deportiva Granjas El Gallo................ 22.89 UMA\nq) Unidad Deportiva Salvador Rosas Magallón......... 22.89 UMA\nr) Kiosko en Unidad Deportiva Raúl Ramírez\nLozano........................................... 57.99 UMA\ns) Gimnasio José J. Reyes Ronfinni (puesto)......... 31.22 UMA\nt) Espacios de Food Court en Unidad Deportiva\nRaúl Ramírez Lozano.............................. 42.00 UMA\nu) Otras cafeterías................................. 30.00 UMA\nv) Otros espacios................................... 30.00 UMA\nw) Espacio para almacenaje bajo gradas de\nEstadio en Unidad Deportiva Raúl Ramírez\nLozano........................................... 21.00 UMA\nx) Gimnasio de box y deportes de combate en\nUnidad Deportiva Juan A. Rodríguez Sullivan...... 63.00 UMA\ny) Local en Canchas Gemelas col. 89................. 28.00 UMA\nz) Área de baños en Canchas Gemelas col. 89......... 21.00 UMA aa) Local para snack en Unidad Deportiva\nRaúl Ramírez Lozano, parte baja................. 62.43 UMA bb) Local para snack en Unidad Deportiva\nRaúl Ramírez Lozano, parte alta................. 62.43 UMA cc) Área para Gimnasio de box y deportes de combate, arriba de la parte anexa de\nGimnasio de Acondicionamiento Físico en Unidad Deportiva Juan A. Rodríguez\nSullivan, con acceso al gimnasio................. 52.38 UMA dd) Oficina bajo gradas en la parte sur del campo No. 1 en Unidad Deportiva\nRaúl Ramírez Lozano.............................. 22.89 UMA ee) Oficina bajo gradas en la parte oeste del campo No. 1 en Unidad Deportiva\nRaúl Ramírez Lozano.............................. 48.00 UMA ff) Espacio bajo gradas del Estadio en Unidad\nDeportiva Raúl Ramírez Lozano, Zona oeste........ 57.57 UMA gg) Local en oficinas de la Unidad Deportiva\n3 Colonias....................................... 30.00 UMA hh) Gimnasio de box y deportes de combate en la Unidad Deportiva Raúl Ramírez Lozano.......... 33.15 UMA\n5.- COBRO DE USO DE INSTALACIONES DEPORTIVAS, POR EVENTO:\na) Gimnasio para box sin ring en Gimnasio Municipal.. 148.72 UMA\nb) Gimnasio para box con ring en Gimnasio Municipal.. 190.72 UMA\nc) Ring para función de box......................... 90.00 UMA\nINCLUYE TRASLADO, ARMADO Y DESARMADO, CONSIDERANDO HORARIO EXTRA.\nNOTA: ESTE NÚMERO CON SUS INCISOS TAMBIÉN APLICA PARA LUCHA LIBRE\nY DEPORTES DE COMBATE.\nd) Gimnasio para box sin ring en Gimnasio Chapultepec. 120.00 UMA\ne) Gimnasio para box con ring en Gimnasio Chapultepec. 150.00 UMA\nf) Gimnasio para box sin ring en Gimnasio Col. Hidalgo.110.00 UMA\ng) Gimnasio para box con ring en Gimnasio Col. Hidalgo.140.00 UMA\nh) Gimnasio para box sin ring en Gimnasio del Sauzal...120.00 UMA\ni) Gimnasio para box con ring en Gimnasio del Sauzal...150.00 UMA\nj) Gimnasio para box sin ring en Gimnasio Maneadero....125.00 UMA\nk) Gimnasio para box con ring en Gimnasio Maneadero....155.00 UMA\n6.- COBRO POR HORA:\na) Fútbol 7 infantil, empastado. Con fines de lucro.. 0.59 UMA a.1) Sin fines de lucro........................... 0.00 UMA\nb) Fútbol 7 juvenil, empastado. Con fines de lucro.. 0.75 UMA b.1) Sin fines de lucro........................... 0.00 UMA\nc) Fútbol 7 adultos, empastado. Con fines de lucro... 0.89 UMA c.1) Sin fines de lucro........................... 0.00 UMA\nd) Futsal en Unidad Deportiva Juan A. Rodríguez\nSullivan (lunes a viernes)........................ 0.44 UMA d.1) Sin fines de lucro........................... 0.00 UMA\ne) Futsal en Unidad Deportiva Juan A. Rodríguez\nSullivan (sábado y domingo)....................... 0.22 UMA e.1) Sin fines de lucro........................... 0.00 UMA\nf) Fútbol Soccer infantil, empastado. Con fines de lucro.......................................... 0.70 UMA f.1) Sin fines de lucro........................... 0.00 UMA\ng) Fútbol Soccer juvenil, empastado. Con fines de lucro.......................................... 0.82 UMA g.1) Sin fines de lucro........................... 0.00 UMA\nh) Fútbol Soccer adulto, empastado. Con fines de lucro.......................................... 0.95 UMA h.1) Sin fines de lucro........................... 0.00 UMA\ni) Fútbol Americano infantil empastado para juegos... 1.00 UMA i.1) Para entrenamiento 40 yardas................. 0.50 UMA i.2) Sin fines de lucro........................... 0.00 UMA\nj) Fútbol Americano juvenil empastado para juegos.... 1.50 UMA j.1) Para entrenamiento 40 yardas................. 0.75 UMA j.2) Sin fines de lucro........................... 0.00 UMA\nk) Fútbol Americano adulto empastado para juegos..... 1.50 UMA k.1) Para entrenamiento 40 yardas................. 0.95 UMA k.2) Sin fines de lucro........................... 0.00 UMA\nl) Cancha de tenis para entrenamiento................ 0.93 UMA\n(POR HORA) l.1) Sin fines de lucro........................... 0.00 UMA\nm) Cancha de baloncesto para juegos al aire libre..... 0.60 UMA\n(POR HORA) m.1) Sin fines de lucro........................... 0.00 UMA m.2) Cancha de baloncesto para juegos en gimnasio cerrado....................................... 0.80 UMA\nn) Cancha de baloncesto para entrenamiento al aire libre...................................... 0.30 UMA\n(POR HORA) n.1) Sin fines de lucro........................... 0.00 UMA n.2) Cancha de baloncesto para entrenamiento en gimnasio cerrado............................. 0.45 UMA\no) Pista de atletismo para entrenamiento de particulares o escuelas privadas (1 CARRIL)....... 1.00 UMA\n(POR HORA) o.1) Sin fines de lucro........................... 0.00 UMA\np) Rugby campo empastado para juegos................. 1.50 UMA\n(POR HORA) p.1) Para entrenamiento 30 yardas................. 0.95 UMA p.2) Sin fines de lucro........................... 0.00 UMA\nq) Frisbee campo empastado para juegos............... 0.95 UMA\n(POR HORA) q.1) Para entrenamiento........................... 0.50 UMA q.2) Sin fines de lucro........................... 0.00 UMA\nr) Cancha de voleibol para juegos al aire libre...... 0.60 UMA r.1) Para juegos en gimnasio cerrado.............. 0.80 UMA r.2) Sin fines de lucro........................... 0.00 UMA\ns) Cancha de voleibol para entrenamientos al aire libre.............................................. 0.30 UMA s.1) Para entrenamientos en gimnasio cerrado....... 0.45 UMA s.2) Sin fines de lucro............................ 0.00 UMA\nt) Campo de beisbol empastado para entrenamiento...... 0.60 UMA t.1) Sin fines de lucro............................ 0.00 UMA t.2) Para juegos................................... 1.00 UMA\nu) Fútbol flag infantil empastado para juegos......... 1.00 UMA u.1) Para entrenamiento....................... 0.50 UMA u.2) Sin fines de lucro............................ 0.00 UMA\nv) Fútbol flag juvenil empastado para juegos.......... 1.50 UMA v.1) Para entrenamiento............................ 0.75 UMA v.2) Sin fines de lucro............................ 0.00 UMA\nw) Fútbol flag adulto empastado para juegos........... 1.50 UMA w.1) Para entrenamiento............................ 0.95 UMA w.2) Sin fines de lucro............................ 0.00 UMA\n7.- COBRO DE ESPACIOS DEPORTIVOS (EVENTOS ESPECIALES):\na) Gimnasio José J. Reyes................. De 0.01 a 89.23 UMA\nb) Gimnasio Oscar Tigre García............ De 0.01 a 297.44 UMA\nc) Campo No. 1 Unidad Deportiva\nRaúl Ramírez Lozano.................... De 0.01 a 892.32 UMA\nd) Unidad Deportiva Juan A. Rodríguez\nSullivan Canchas de Básquetbol......... De 0.01 a 74.36 UMA\ne) Campo fútbol empastado colonia Morelos 1. De 0.01 a 29.74 UMA\nf) Campo empastado No. 3 Unidad\nDeportiva Raúl Ramírez Lozano.......... De 0.01 a 74.36 UMA\ng) Campo empastado de usos múltiples No. 5 en Deportiva Raúl Ramírez Lozano....... De 0.01 a 44.61 UMA\nh) Campo empastado fútbol americano\nUnidad Deportiva Raúl Ramírez Lozano... De 0.01 a 74.36 UMA\ni) Pista de atletismo para particulares o escuelas privadas.................... De 0.01 a 74.36 UMA\nj) Campo empastado en Granjas El Gallo...... De 0.01 a 29.74 UMA\nk) Gimnasio en Chapultepec.................. De 0.01 a 89.23 UMA\nl) Unidad Deportiva Francisco Villa-Vida\nDigna Canchas de Basquetbol.............. De 0.01 a 29.74 UMA\nm) Unidad Deportiva Francisco Villa-Vida\nDigna estacionamiento.................... De 0.01 a 29.74 UMA\nn) Campo empastado No. 6 Unidad\nDeportiva Raúl Ramírez Lozano............ De 0.01 a 74.36 UMA\no) Skate Park Playa Hermosa.................. De 0.01 a 74.36 UMA\np) Explanada Skate Park Playa Hermosa........ De 0.01 a 74.36 UMA\nq) Cancha de voleibol en Skate Park\nPlaya Hermosa............................. De 0.01 a 74.36 UMA\nr) Gimnasio Col. Hidalgo..................... De 0.01 a 89.23 UMA\ns) Gimnasio en Sauzal........................ De 0.01 a 89.23 UMA\nt) Campo empastado en Unidad Deportiva\nFrancisco Villa-Vida Digna................ De 0.01 a 74.36 UMA\n8.- COBROS POR EL USO DE ALBERCA EN UNIDAD DEPORTIVA FRANCISCO\nVILLA-(VIDA DIGNA):\na) Alberca, público general (por hora)............... 0.345 UMA\nb) Alberca, personas de escasos recursos (por hora).. 0.173 UMA\nc) Curso de natación 2 días a la semana (mensual).... 5.06 UMA\nd) Curso de natación 3 días a la semana (mensual).... 6.26 UMA\ne) Curso de natación 5 días a la semana (mensual).... 9.16 UMA\nf) Curso de aquaerobics 2 días a la semana (mensual).. 5.06 UMA\ng) Descuento paquete familiar (3 en adelante)...... 25% en curso\nh) Descuento a trabajadores e hijos de trabajadores del Ayuntamiento de Ensenada............... 50%\ni) Descuento a personas de la tercera edad................. 50%\nj) Descuento a personas por rehabilitación................. 50%\nk) Descuento a personas de escasos recursos................. 50%\nl) Alberca, alumnos Universidad Autónoma de Baja California y Cet Del Mar(por hora)........ 0.173 UMA\nm) Equipo de natación 6 días de lunes a sábado\n(mensual)......................................... 9.00 UMA\nn) Personas con discapacidad......................... GRATUITO\nNOTA: INCIO l) APLICA EN ASIGNATURA CURRICULAR.\n9.- COBRO POR EL USO DE ALBERCA EN UNIDAD DEPORTIVA RAÚL RAMÍREZ\nLOZANO:\na) Alberca, público general (por hora)............... 0.402 UMA\nb) Alberca, personas de escasos recursos (por hora).. 0.201 UMA\nc) Curso de natación 2 días a la semana (mensual).... 5.53 UMA\nd) Curso de natación 3 días a la semana (mensual).... 6.72 UMA\ne) Curso de natación 5 días a la semana (mensual).... 9.63 UMA\nf) Curso de aquaerobics 2 días a la semana (mensual).. 5.53 UMA\ng) Descuento paquete familiar (3 en adelante)....... 25% en curso\nh) Descuento a trabajadores e hijos de trabajadores del Ayuntamiento de Ensenada....................... 50%\ni) Descuento a personas de la tercera edad............. 50%\nj) Descuento a personas por rehabilitación............ 50%\nk) Descuento a personas de escasos recursos........... 50%\nl) Equipo de natación 6 días de lunes a sábado (mensual)......................... 9.00 UMA\nm) Alberca, alumnos Universidad Autónoma de\nBaja California y Cet Del Mar(por hora)........... 0.201 UMA\nn) Personas con discapacidad......................... GRATUITO\nNOTA: INCISO m) APLICA EN ASIGNATURA CURRICULAR.\n10.- COBROS POR DÍA POR USO DE ESPACIO DEPORTIVO EN EVENTOS\nFACTIBLES:\na) Campo 2 en Unidad Deportiva Raúl\nRamírez Lozano...................... De 0.01 a 33.74 UMA\nb) Campo 4 en Unidad Deportiva Raúl\nRamírez Lozano...................... De 0.01 a 33.74 UMA\nc) Campo de softbol en Unidad Deportiva\nRaúl Ramírez Lozano................. De 0.01 a 44.61 UMA\nd) Cancha de básquetbol en Unidad\nDeportiva Raúl Ramírez Lozano....... De 0.01 a 29.74 UMA\ne) Cancha de futsal en Unidad Deportiva\nRaúl Ramírez Lozano................. De 0.01 a 14.87 UMA\nf) Alberca en Unidad Deportiva Raúl\nRamírez Lozano...................... De 0.01 a 148.72 UMA\ng) Explanada en Unidad Deportiva\nRaúl Ramírez Lozano................. De 0.01 a 14.87 UMA\nh) Cancha de tenis en Unidad Deportiva\nRaúl Ramírez Lozano................. De 0.01 a 74.36 UMA\ni) Pista de atletismo en Unidad\nDeportiva Raúl Ramírez Lozano....... De 0.01 a 29.74 UMA\nj) Pista de ciclismo en Unidad\nDeportiva Raúl Ramírez Lozano....... De 0.01 a 29.74 UMA\nk) Campo de fútbol empastado en Unidad\nDeportiva Juan A. Rodríguez\nSullivan............................ De 0.01 a 74.36 UMA\nl) Pista de atletismo en Unidad\nDeportiva Juan A. Rodríguez\nSullivan............................ De 0.01 a 29.74 UMA\nm) Cancha de futsal en Unidad Deportiva\nJuan A. Rodríguez Sullivan....... De 0.01 a 14.87 UMA\nn) Campo de béisbol en Unidad Deportiva\nJuan A. Rodríguez Sullivan....... De 0.01 a 29.74 UMA\no) Campo de béisbol infantil en Unidad\nDeportiva Juan A. Rodríguez\nSullivan............................ De 0.01 a 14.87 UMA\np) Cancha de voleibol c/malla sombra en\nUnidad Deportiva Juan A. Rodríguez\nSullivan............................ De 0.01 a 29.74 UMA\nq) Cancha de voleibol en Unidad Deportiva\nJuan A. Rodríguez Sullivan......... De 0.01 a 14.87 UMA\nr) Cancha de futsal en Tres Colonias... De 0.01 a 14.87 UMA\ns) Cancha de frontón en Tres Colonias.. De 0.01 a 7.43 UMA\nt) Cancha de básquetbol en Tres\nColonias............................ De 0.01 a 14.87 UMA\nu) Cancha de voleibol en Tres Colonias.. De 0.01 a 14.87 UMA\nv) Área de palapa en Tres Colonias..... De 0.01 a 10.00 UMA\nw) Área de explanada Tres Colonias.... De 0.01 a 7.40 UMA\nx) Campo de fútbol en Siglo XXI........ De 0.01 a 29.74 UMA\ny) Campo de béisbol en Siglo XXI....... De 0.01 a 14.87 UMA\nz) Cancha de fútbol rápido en Siglo XXI.. De 0.01 a 7.43 UMA aa) Cancha de frontón en Siglo XXI...... De 0.01 a 7.43 UMA bb) Cancha de voleibol en Siglo XXI..... De 0.01 a 14.87 UMA cc) Cancha de básquetbol en Siglo XXI... De 0.01 a 14.87 UMA dd) Gimnasio en Deleg. El Sauzal........ De 0.01 a 74.36 UMA ee) Cancha de futsal en Pórticos del Mar.. De 0.01 a 7.43 UMA ff) Campo empastado fútbol en Pórticos del Mar............................. De 0.01 a 29.74 UMA gg) Cancha de usos múltiples en Pórticos del Mar............................ De 0.01 a 14.87 UMA hh) Gimnasio en Unidad Vicente Gro.\nCol. Hidalgo........................ De 0.01 a 74.36 UMA ii) Cancha de básquetbol en Unidad Vicente\nGro. Col. Hidalgo................... De 0.01 a 14.87 UMA jj) Cancha de tenis en Unidad Vicente\nGro. Col. Hidalgo.................. De 0.01 a 29.74 UMA kk) Alberca en U.D. Fco. Villa.......... De 0.01 a 128.72 UMA ll) Campo empastado fútbol en U.D.\nFco. Villa.......................... De 0.01 a 44.61 UMA mm) Campo fútbol en U.D. Fco. Villa.... De 0.01 a 14.87 UMA nn) Cancha de básquetbol en U.D. Fco.\nVilla............................... De 0.01 a 14.87 UMA oo) Gimnasio José María Morelos en\nEx-Ejido Chapultepec................ De 0.01 a 74.36 UMA pp) Unidad Deportiva en la Colonia\nJesús Munguía....................... De 0.01 a 14.87 UMA qq) Campo empastado fútbol en\nVillas VI........................... De 0.01 a 29.74 UMA rr) Unidad Deportiva Noroeste\n(Real Madrid)....................... De 0.01 a 29.74 UMA ss) Unidad Deportiva en Colonia Salvador\nRosas Magallón...................... De 0.01 a 14.87 UMA tt) Unidad Deportiva Granjas el Gallo... De 0.01 a 14.87 UMA uu) Campo empastado en Col.\nAmpliación 89....................... De 0.01 a 44.61 UMA vv) Área grande de Gimnasio de\nAcondicionamiento Físico en Unidad\nDeportiva Juan A. Rodríguez\nSullivan............................ De 0.01 a 74.36 UMA ww) Área chica de Gimnasio de\nAcondicionamiento Físico en Unidad\nDeportiva Juan A. Rodríguez\nSullivan............................ De 0.01 a 44.61 UMA xx) Área de segundo piso del área grande Gimnasio de Acondicionamiento Físico en Unidad Deportiva\nJuan A. Rodríguez Sullivan........... De 0.01 a 14.87 UMA yy) Unidad Deportiva Todos Santos........ De 0.01 a 29.74 UMA zz) Unidad Deportiva Santo Tomás......... De 0.01 a 14.87 UMA aaa) Unidad Deportiva Valle de las Palmas.. De 0.01 a 17.11 UMA bbb) Unidad Deportiva en el poblado de\nOjos Negros.......................... De 0.01 a 17.11 UMA ccc) Unidad Deportiva en Granjas el Gallo.. De 0.01 a 74.36 UMA ddd) Unidad Deportiva en Col. Salvador\nRosas Magallón....................... De 0.01 a 29.74 UMA eee) Campo 5 empastado flag en\nUnidad Deportiva Raúl Ramírez\nLozano............................... De 0.01 a 74.36 UMA fff) Campo No. 6 empastado de usos múltiples en Unidad Deportiva Raúl Ramírez\nLozano............................... De 0.01 a 50.56 UMA ggg) Campo de béisbol empastado en\nUnidad Deportiva Raúl Ramírez\nLozano............................... De 0.01 a 74.36 UMA\n11.- ESPACIOS PUBLICITARIOS EN LOS DIFERENTES ESPACIOS DEPORTIVOS:\na) Barda o lona por metro cuadrado............. 15.23 UMA ANUAL\nb) Valla por metro cuadrado.................... 15.23 UMA ANUAL\nc) Espectacular por metro cuadrado.............. 15.23 UMA ANUAL\n12.- OTROS\na) Estacionamiento en Unidad Deportiva Juan A.\nRodríguez Sullivan................................ 0.180 UMA\nb) Estacionamiento en Unidad Deportiva Francisco\nVilla............................................. 0.180 UMA\nc) Estacionamiento en eventos especiales en\nUnidad Deportiva Juan A. Rodríguez Sullivan........ 0.52 UMA\nd) Estacionamiento en eventos especiales en\nUnidad Deportiva Raúl Ramírez Lozano................ 0.52 UMA\ne) Estacionamiento en Unidad Deportiva Raúl\nRamírez Lozano................................... 0.180 UMA\nf) Estacionamiento en Unidad Deportiva\nPórticos del Mar............................... 0.180 UMA\n13.- PROYECTOS ESPECIALES:\na) MEDIO MARATÓN a.1) Inscripción................................ 4.15 UMA\nPara cubrir necesidades del instituto, las cuales se establecerán en la convocatoria del medio maratón.\nb) PROYECTOS CON APORTACIÓN VOLUNTARIA\na) Aportación voluntaria para la Rehabilitación de cerco, baños e iluminación de acceso y andadores en la Unidad\nDeportiva Siglo XXI...................... De 0.52 UMA en adelante\nb) Aportación voluntaria para la\nRehabilitación de palapas e iluminación de acceso y andadores en la Unidad\nDeportiva Tres Colonias.................. De 0.52 UMA en adelante\nc) Aportación voluntaria para la Rehabilitación de cerco, baños e iluminación de acceso y pasillos en la Unidad\nDeportiva Raúl Ramírez Lozano........... De 0.52 UMA en adelante\nd) Aportación voluntaria para luminarias de pista de atletismo en la Unidad Deportiva\nJuan A. Rodríguez Sullivan................ De 0.52 UMA en adelante\ne) Aportación voluntaria para iluminación campo en la Unidad Deportiva Villas II... De 0.52 UMA en adelante\nf) Aportación voluntaria para pintura e iluminación de Skate Park en Punta\nBanda.............................. De 0.52 UMA en adelante\ng) Aportación voluntaria para iluminación en la Unidad Deportiva\nPórticos del Mar................... De 0.52 UMA en adelante\nIX.- LOS SERVICIOS QUE PRESTA EL INSTITUTO MUNICIPAL DE LA\nJUVENTUD DE ENSENADA, BAJA CALIFORNIA, SE COBRARÁN DE LA\nMANERA SIGUIENTE:\nUNIDAD DE MEDIDA Y ACTUALIZACIÓN\n(UMA)VIGENTE\n1.- CURSOS DE CAPACITACIÓN.\nCUOTA TRIMESTRAL\na) Jóvenes de entre 12 y 29 años de edad.......... 5.60 UMA\n2.- Cursos intensivos, cursos, talleres, clases y capacitaciones:\na) Idiomas..................................... 1.89 UMA\nb) Computación básico.......................... 1.67 UMA\nc) Maquillaje social........................... 1.67 UMA\nd) Redacción y ortografía...................... 1.67 UMA\ne) Dibujo para principiantes................... 1.89 UMA\nf) Belleza..................................... 1.89 UMA\ng) Fotografía.................................. 1.67 UMA\nh) Diseño de aplicaciones...................... 3.00 UMA\ni) Diseño gráfico social...................... 1.89 UMA\nj) Mercadotecnia (Introducción al community management)....................... 1.89 UMA\nk) Creación y edición para historias de Instagram................................ 1.89 UMA\nl) Técnicas modernas en acuarela............... 1.67 UMA\nm) Introducción al Adobe Ilustrator............ 2.22 UMA\nn) Estrategias para vender..................... 1.67 UMA\no) Fotografía y video con celular.............. 2.22 UMA\np) Refuerzo escolar primaria (asesorías)....... 1.67 UMA\nq) Refuerzo escolar secundaria(asesorías)...... 1.67 UMA\nr) Refuerzo escolar preparatoria(asesorías).... 1.67 UMA\ns) Diseño de presentaciones.................... 1.67 UMA\nt) Envoltura de regalos........................ 1.67 UMA\nu) Música (introducción)....................... 1.89 UMA\nv) Negocios.................................... 2.22 UMA\nw) Moda........................................ 2.22 UMA\nx) Programación................................ 2.22 UMA\ny) Mi Primer Empleo............................ 1.67 UMA\nz) Radio y comunicación........................ 1.67 UMA aa) Yoga y meditación........................... 1.67 UMA bb) Liderazgo................................... 1.67 UMA cc) Decisiones estratégicas(Administración)..... 1.89 UMA dd) Primeros Auxilios.......................... 1.67 UMA\n3.- Conferencias y congresos....................... 2.23 UMA\nX.- LOS SERVICIOS QUE PRESTA EL COMITÉ DE PLANEACIÓN PARA\nEL DESARROLLO MUNICIPAL DE ENSENADA, BAJA CALIFORNIA (COPLADEM)\nSE COBRARÁN DE LA MANERA SIGUIENTE:\nUNIDAD DE MEDIDA Y ACTUALIZACIÓN\n(UMA)VIGENTE\n1.- POR TIPO DE CONSULTA PÚBLICA:\nA) CAMBIO DE USO DE SUELO\n1.- Publicación de la consulta pública en el diario de mayor circulación del\nMunicipio.............................. 150.00 UMA\n2.- Diagnóstico de la consulta pública entregada por escrito o virtual....... 100.000 UMA\n3.- Celebración de la sesión de la consulta pública...................... 100.00 UMA\n4.- Dictamen por escrito de la consulta pública....................... 250.00 UMA\nB) CONSULTA VECINAL\n1.- A realizarse en las instalaciones del Ayuntamiento de Ensenada.......... 120.00 UMA\n2.- A realizarse en el sitio donde se desarrolla la actividad............... 150.00 UMA\n3.- Las consultas que se realicen en el sitio, y se encuentren fuera de los límites del centro de población, por kilómetro excedente...................... 0.50 UMA\nC) PROGRAMAS SECTORIALES\n1.- Publicación de la consulta pública en el diario de mayor circulación del\nMunicipio.............................. 150.00 UMA\n2.- Diagnóstico de la consulta pública entregada por escrito o virtual........ 100.00 UMA\n3.- Celebración de la sesión de la consulta pública....................... 100.00 UMA\n4.- Dictamen por escrito de la consulta pública....................... 250.00 UMA\n5.- Las consultas que se realicen en el sitio, y se encuentren fuera de los límites del centro de población por cada kilómetro excedente................ 1.00 UMA\n2.- CURSOS, TALLERES Y CONGRESOS RELACIONADOS CON ACTIVIDAD\nDEL AYUNTAMIENTO Y COMITÉ DEL COPLADEM PARA AL MENOS 5\nPERSONAS POR HORA/PERSONA...................... 3.20 UMA exentos del cobro por los servicios brindados por COPLADEM, siempre solicitados por el Presidente Municipal.\nAsí mismo, las solicitudes de servicio que sean solicitadas por el Presidente Municipal, en su carácter de Presidente de la junta de gobierno de COPLADEM, tendrán un costo de hasta un 50% del valor de los conceptos aplicables, exceptuando la publicación en el diario oficial de mayor circulación.\nXI.- LOS SERVICIOS QUE PRESTA LA PARAMUNICIPAL PROTURISMO DE\nENSENADA, SE COBRARÁN CONFORME A LO SIGUIENTE:\nUNIDAD DE MEDIDA Y ACTUALIZACIÓN\n(UMA) VIGENTE\n1.- MÓDULO DE BAÑOS:\na) Entrada general............................ 0.058 UMA\nCAPÍTULO XII\nSERVICIOS QUE PRESTA LA POLICÍA COMERCIAL\nARTÍCULO 45.- Los servicios que preste el Ayuntamiento a través se prestan a domicilios particulares, giros comerciales e instituciones de servicio u otros que lo soliciten, así como los servicios de escolta, se deberán cubrir de acuerdo a lo siguiente:\nUNIDAD DE MEDIDA Y ACTUALIZACIÓN\n(UMA)VIGENTE\nI.- Servicios de vigilancia en puntos fijos:\n1.- Por agente armado, por turno de ocho horas........................................ 13.50 UMA\n2.- Por agente armado en vigilancia comunitaria en zonas habitacionales\n(contratadas por asociaciones civiles) por cada elemento, por turno de ocho horas................................... 12.15 UMA\n3.- Por agente armado en vigilancia a instituciones gubernamentales por cada elemento, por turno de ocho horas............ 12.15 UMA\n4.- Por agente armado en contrato celebrado por más de 90 días naturales, contratando\n5 o más elementos, por turno de ocho horas........................................ 12.15 UMA\n5.- Agente armado en eventos masivos por turno de seis horas.......................... 13.50 UMA\n6.- Agente para servicios protección personal a particulares por elemento armado de ocho horas................................... 14.85 UMA\nII.- Servicio de vigilancia a cargo de inspectores de Seguridad\nCiudadana:\n1.- En punto fijo por elemento desarmado, por turno de ocho horas.......................... 11.48 UMA\n2.- Por vigilancia comunitaria en zonas habitacionales (contratados por asociaciones ci- viles) por elemento desarmado por turno de ocho horas................................... 10.13 UMA\n3.- Por vigilancia a instituciones gubernamentales por cada elemento desarmado, por turnos de ocho horas......................... 10.13 UMA\n4.- Por contrato celebrado por más de 90 días naturales contratando 5 o más elementos desarmados por turno de ocho horas........... 10.80 UMA\n5.- Por elemento desarmado en eventos masivos por turno de seis horas...................... 11.48 UMA\nIII.- Por la renta de una unidad patrulla\n1.- Renta de unidad patrulla con elemento armado por turno de seis horas............... 30.38 UMA\nIV.- Por la renta de una unidad motocicleta\n1.- Servicios de agentes funerales, desfiles, carreras atléticas y/o eventos deportivos, por turno de seis horas...................... 20.25 UMA\nV.- Derechos por búsqueda o localización judicial o administrativa:\nBúsqueda o localización de personas y/o domicilios a solicitud de autoridades judiciales y/o administrativas........................................ 6.75 UMA\nCuando la solicitud de búsqueda o localización de personas y/o domicilios, realizada por autoridades judiciales y/o administración pública municipal centralizada, desconcentrada o sus entidades auxiliares, dentro de procesos, procedimientos judiciales o administrativos en que estas sean parte, no se cobrarán los derechos correspondientes.\nPor cada hora adicional de servicio contratado, de acuerdo al tipo de servicio, se pagará.................................. 1.35 UMA\nCAPÍTULO XIII\nEXPEDICIÓN DE CERTIFICADOS, TÍTULOS,\nCONSTANCIAS O COPIAS DE DOCUMENTOS\nARTÍCULO 46.- Los certificados, títulos, constancias, copias fotostáticas certificadas, legalización de firmas y demás servicios administrativos prestados por las oficinas municipales, deberán pagarse conforme a la siguiente:\nUNIDAD DE MEDIDA Y ACTUALIZACIÓN\n(UMA)VIGENTE\na).- Certificados de residencia y legalización de firmas............................. 1.62 UMA\nb).- Copia adicional certificada........................ 0.34 UMA\nc).- Certificados de productos de origen................ 1.02 UMA\nd).- Derechos por titulación de terrenos............... 5.40 UMA\ne).- Certificados de peritaje........................... 1.35 UMA\nf).- Certificados de obras públicas........... De 2.70 a 8.10 UMA\ng).- Certificación o constancia de archivos municipales........................................ 1.35 UMA\nh).- Certificación de avalúo............................ 8.10 UMA h.1 Certificación de avalúo urgente, (se tiene que presentar antes de las 10:00 hrs) se entrega a las 14:00 hrs del mismo día...... 16.20 UMA h.2 Certificación de avalúo extra urgente, (se tiene que presentar antes de las 13:00 hrs) se entrega de 1 a 2 horas después de la recepción............................... 21.60 UMA h.3 Copia certificada de avalúo.................... 5.40 UMA h.4 Por modificación de hoja en avalúo ya certificado................................. 4.05 UMA\nEl pago por la certificación de un avalúo solo tendrá vigencia de uso por 30 días naturales y hasta 2 reingresos.\nREINGRESOS: a partir del pago de certificación de avalúo tendrá la oportunidad de 2 reingresos dentro de un período de 30 días naturales. un costo del 50% del valor del primer ingreso.\ni).- Certificado de opinión para establecimiento de maquiladoras de acuerdo a clasificación federal de la SECOFI: i.1) Industria micro............................... 6.75 UMA i.2) Industria mediana............................ 20.25 UMA i.3) Industria grande............................. 33.75 UMA\nj).- Constancias de autoconstrucción\nHasta 120m²........................................ 5.40 UMA\nk).- Certificaciones a particulares, por hoja............................................... 2.03 UMA\nl).- Dispensa de edad................................... 1.76 UMA\nm).- Carta de residencia................................ 2.03 UMA\nn).- Constancia de supervivencia........................ 1.35 UMA ñ).- Constancia de explosivos........................... 6.75 UMA\no).- Dictámenes a particulares......................... 6.75 UMA\np).- Emisión de documentos simples...................... 0.33 UMA\nq).- Fotocopia de Leyes, reglamentos que se tienen en la dependencia, por hoja............................................... 0.34 UMA\nr).- Derechos por cartas y certificaciones expedidos por la Sindicatura Municipal: r.1) Carta de antecedentes administrativos......... 2.70 UMA r.2) Copias certificadas de 1 a 20................. 2.03 UMA r.3) Copia adicional certificada................... 0.07 UMA r.4) Expedición de copias fotostáticas simples..... 0.00 UMA\ns).- Constancia de ratificación de firmas.............. 27.00 UMA\nt).- Modificación de la constancia de ratificación, costo por hoja..................................... 1.35 UMA\nu).- Expedición de constancia y registro de las\nAsociaciones Religiosas............................ 4.05 UMA\nv).- Renovación de constancia y registro de las\nAsociaciones Religiosas............................ 1.35 UMA\nw).- Expedición de constancia y registro de las\nAsociaciones Civiles............................... 4.05 UMA\nx).- Renovación de constancia y registro de las\nAsociaciones Civiles............................... 1.35 UMA\ny).- Licencia de operación.............................. 0.00 UMA\nLas personas físicas de escasos recursos que utilicen los servicios de la Defensoría de Oficio en la tramitación de procedimientos judiciales, civiles y penales, previo estudio socioeconómico que elabore la Dirección de Educación, Cultura y Asistencia Social se les exentará del pago de los Derechos por el servicio de Certificado de Residencia y Certificado de Libertad de Gravámenes, a solicitud expresa del titular de la Defensoría de Oficio, esta exención será otorgada al interesado por única ocasión.\nCAPÍTULO XIV\nLIQUIDACIÓN O PAGO.\nARTÍCULO 47.- Los derechos no pagados en el ejercicio fiscal en que se causaron, se cobrarán como ingresos causados en ejercicios fiscales anteriores, pendientes de liquidación o pago, aplicando en cuanto al fondo, las Leyes vigentes en la fecha en que se generaron y en cuanto a la forma, mediante el caso, el procedimiento judicial que corresponda.\nTÍTULO CUARTO\nPRODUCTOS\n1.- CONTRAPRESTACIÓN DE CONCESIONES, EXPLOTACIÓN O ARRENDAMIENTO\nARTÍCULO 48.- La renta o contraprestación de las concesiones de los locales internos o externos de los mercados, será fijada en cada caso por las autoridades fiscales, dependiendo de su ubicación y superficie ocupada o en su caso, de acuerdo al contrato de arrendamiento respectivo.\nLa renta o contraprestación será señalada por períodos mensuales y su importe deberá ser liquidado en la Caja Recaudadora de la\nTesorería Municipal, dentro de los primeros cinco días de cada mes en forma anticipada.\n2.- OTRAS ACTIVIDADES DEL GOBIERNO MUNICIPAL, QUE NO CORRESPONDAN\nA SUS FUNCIONES PROPIAS DE DERECHO PÚBLICO\nARTÍCULO 48-A.- Las rentas que produzcan los bienes propiedad del Municipio y que sean susceptibles de ser arrendados, se con cada uno de los inquilinos y el Ayuntamiento, cubriéndose el importe de la renta de la siguiente manera:\n1.- Renta mensual:\nLos primeros cinco días hábiles del mes correspondiente.\n2.- Renta diaria:\nHasta 24 horas antes del día de la ocupación.\n3.- SUMINISTRO DE FORMAS DIVERSAS PARA TRÁMITES ADMINISTRATIVOS\nARTÍCULO 48-B.- Ingresos obtenidos por el suministro de formas impresas tales como formatos para pago de Impuestos, Municipales, se pagarán a razón de 0.10 UMA por forma impresa, en la caja recaudadora de la Tesorería Municipal.\n4.- DEL PISO\nARTÍCULO 48-C.- Las personas físicas o morales que uso del piso, de instalaciones subterráneas o áreas en las vías públicas para la realización de actividades comerciales o de prestación de servicios en forma permanente o temporal, pagarán los productos correspondientes conforme a la siguiente:\nI.- Casetas telefónicas, diariamente, por cada una; debiendo realizar el pago anualizado dentro de los primeros 60 días del ejercicio fiscal......... 0.10 UMA\nII.- Instalaciones de infraestructura, por metro lineal, anualmente:\na).- Redes subterráneas de:\n1.- Telefonía................................ 0.015 UMA\n2.- Transmisión de datos..................... 0.015 UMA\n3.- Transmisión de señales de televisión por cable............................... 0.015 UMA\n4.- Distribución de gas...................... 0.015 UMA\n5.- Energía eléctrica........................ 0.015 UMA\nb).- Redes visibles de:\n1.- Telefonía................................ 0.030 UMA\n2.- Transmisión de datos..................... 0.030 UMA\n3.- Transmisión de señales de televisión por cable................................ 0.030 UMA\n4.- Energía eléctrica........................ 0.030 UMA\n5.- BIENES MOSTRENCOS\nARTÍCULO 48-D.- Ingresos obtenidos por los bienes mostrencos que se rematen o vendan de acuerdo a las disposiciones relativas.\n6.- LOS PRODUCTOS DE LA GACETA MUNICIPAL\nARTÍCULO 48-E.- Se regirán por las siguientes tarifas:\nI.- SUSCRIPCIONES Y EJEMPLARES\na).- Suscripción anual............................. 15.00 UMA\nb).- Ejemplar mensual.............................. 2.00 UMA\nc).- Ejemplar atrasado del año en curso............. 1.50 UMA\nd).- Ejemplar de ediciones especiales, reglamentos, bandos, etc....................... 2.50 UMA\nII.- INSERCIONES:\na).- Publicación a particulares, por plana........ 90.00 UMA\nb).- Publicación a particulares, por media de plana..................................... 45.00 UMA\nc).- Publicación a particulares, por cuarto de plana..................................... 25.00 UMA\n7.- ENAJENACIÓN DE BIENES MUEBLES E INMUEBLES PROPIEDAD DEL\nGOBIERNO MUNICIPAL\n8.- ORGANISMOS DESCENTRALIZADOS Y EMPRESAS DE PARTICIPACIÓN\nMUNICIPAL\nARTÍCULO 49.- Los rendimientos producidos por organismos descentralizados y empresas de participación municipal, se percibirán cuando lo decreten y exhiban, conforme a sus respectivos regímenes interiores.\nARTÍCULO 49-A.- Trámite de pasaporte mexicano:\nTrámite de citas para pasaporte:\na).- Cita ordinaria................................ 5.50 UMA\nARTÍCULO 49-B.- Pago de derechos por recepción y revisión de documentos, por trámite y solicitudes de donación al municipio o adquisición de predios............................. 2.00 UMA\n10.- PRODUCTOS NO COMPRENDIDOS EN LAS FRACCIONES EN LA LEY DE\nINGRESOS CAUSADOS EN EJERCICIOS FISCALES ANTERIORES\nPENDIENTES DE LIQUIDACIÓN O PAGO.\nARTÍCULO 49-C.- Los productos no pagados en el ejercicio fiscal en que se causaron, se cobrarán como ingresos causados en ejercicios fiscales anteriores, pendientes de liquidación o pago, aplicando en cuanto al fondo, las\nLeyes vigentes a la fecha en que se generaron y en cuanto a la forma, mediante el procedimiento administrativo de\nEstado de Baja California o en su caso, el procedimiento judicial que corresponda.\nTÍTULO QUINTO\nAPROVECHAMIENTOS\n1.- RECARGOS\nARTÍCULO 50.- La tasa de recargos en caso de prórroga, será del\n2.00% mensual y será incrementada en un 50% tratándose de mora.\nLos recargos se causarán hasta por 5 años.\n2.- GASTOS DE EJECUCIÓN\nARTÍCULO 51.- Los gastos de ejecución se cobrarán a quien se le requiera, por haber incurrido en incumplimiento de obligaciones fiscales no satisfechas dentro de los plazos legales, señala la Ley de Hacienda Municipal del Estado de Baja California.\nSe cobrarán por:\nI. El requerimiento;\nII. El embargo;\nIII. El remate, enajenación fuera de remate o adjudicación del Municipio.\nLos gastos por impresiones, publicaciones, avalúos de inmuebles o cualquier otra erogación que, con el carácter de extraordinario, sea necesaria para el éxito del procedimiento administrativo de ejecución se liquidarán por separado.\nLos honorarios de los interventores con cargo a la caja y de los administradores se determinarán discrecionalmente por las autoridades fiscales, tomando en consideración el monto del crédito fiscal adecuado y la situación económica del deudor.\n3.- MULTAS\nARTÍCULO 52.- Las multas por infracciones a las disposiciones\nMunicipal para el Estado de Baja California, esta Ley de\nIngresos, los ordenamientos legales correspondientes y, en su defecto, con multa de hasta 100.00 UMA (Unidad de Medida y\nActualización), el importe.\nTratándose de Impuesto Predial, cuando se omita el pago del mismo, del impuesto, que para ello se realice de conformidad con el artículo 2 de la presente Ley de Ingresos y la Ley de Ingresos del ejercicio fiscal en que se haya omitido el pago del impuesto, según sea el caso, misma que se aplicará conforme a lo siguiente:\nDESDE HASTA MULTA\n$ 100.00 $ 2,000.00........................... 2.00 UMA\n$ 2,001.00 $12,000.00.......................... 5.00 UMA\n$12,001.00 $21,000.00.......................... 15.00 UMA\n$21,001.00 $49,999.00........................... 40.00 UMA\n$50,000.00 en adelante.......................... 75.00 UMA\nARTÍCULO 52 BIS.- Por infracciones cometidas a disposiciones reglamentarias en situaciones de flagrancia, exceptuando aquellas contenidas en el Reglamento de Tránsito Municipal y en el Bando de\nPolicía y Gobierno............................. 21.00 a 78.00 UMA\n4.- VENTA DE SUBPRODUCTOS\nARTÍCULO 53.- Venta de subproductos del Departamento de Rastro que se regirá bajo la siguiente:\na).- Sangre................................ $0.375 por litro\nb).- Cebos-Grasas........................... $0.100 por kilo\n5.- REINTEGROS E INDEMNIZACIONES\na) En caso de pago de contribuciones por medio de cheque recibido en las cajas de la Dirección de Recaudación, en tiempo y no sea acreditado por la Institución Bancaria, dará lugar al cobro del monto e indemnización del 20% del valor del mismo.\nLa indemnización mencionada, el monto del cheque y en su caso de los recargos, se cobrarán mediante el procedimiento administrativo de ejecución, salvo que el librador del cheque demuestre que la falta de pago no le es imputable.\nb) Indemnización derivada de daños o deterioros en las instalaciones, infraestructura vial, hidráulica, de servicios públicos y demás bienes de propiedad municipal, que se cobrarán de acuerdo a su costo, que aprobará la\nSindicatura Municipal.\n6.- DONACIONES, CESIONES, HERENCIAS Y LEGADOS A FAVOR DEL\nMUNICIPIO\n6.1.- Aquellas cantidades que por concepto de donativos o indemnizaciones se establezcan a favor del Municipio de\nEnsenada, B.C. se sujetaran a las disposiciones de los donantes o a las estipulaciones de los convenios, contratos, normas o resoluciones relativas. Los ingresos por este concepto deberán destinarse al gasto público.\n7.- APORTACIONES DEL GOBIERNO DEL ESTADO O POR LA FEDERACIÓN PARA\nOBRAS Y SERVICIOS PÚBLICOS O PROGRAMAS ESPECIALES\n8.- OTORGAMIENTO Y USUFRUCTO DE DERECHOS\n9.- RECUPERACIÓN PARCIAL DE PRIMAS DE SEGUROS DE VIDA\n10.- PARTICIPACIONES EN IMPUESTOS FEDERALES\n11.- PARTICIPACIONES EN IMPUESTOS ESTATALES: realización de obras. que señalen las Leyes, Acuerdos o Convenios que las regulen.\n14.- CAUCIONES DE FIANZAS Y DEPÓSITOS CUYA PÉRDIDA SE DECLARE POR\nRESOLUCIÓN FIRME\n15.- APORTACIONES FEDERALES DEL RAMO 33\na).- Fondo de Aportaciones para la Infraestructura Social\nMunicipal.\nb).- Fondo de Aportaciones para el Fortalecimiento de los\nMunicipios.\nc).- Otras.\n16.- APROVECHAMIENTOS NO COMPRENDIDOS EN LAS FRACCIONES DE LA LEY\nDE INGRESOS CAUSADAS EN EJERCICIOS FISCALES ANTERIORES\nPENDIENTES DE LIQUIDACIÓN O PAGO.\nARTÍCULO 54.- Los aprovechamientos no pagados en el ejercicio fiscal en que se causaron, se cobrarán como ingresos causados en ejercicios fiscales anteriores, pendientes de liquidación o pago, aplicando en cuanto al fondo, las Leyes vigentes a la fecha en que se generaron y en cuanto a la forma, mediante el procedimiento administrativo de ejecución que establece la Ley de Hacienda Municipal del Estado de\nBaja California o en su caso, el procedimiento judicial que corresponda.\nLos pagos que se hagan, se aplicarán a los créditos más del adeudo principal, a los accesorios en el siguiente orden:\n1.- Gastos de ejecución.\n2.- Recargos.\n3.- Multas.\n4.- Crédito fiscal, suerte principal.\nTÍTULO SEXTO\n1.- CRÉDITOS OTORGADOS AL MUNICIPIO\n2.- APORTACIONES ESTATALES Y FEDERALES\n3.- OTROS\nCAPÍTULO ÚNICO\nARTÍCULO 55.- Las Participaciones en Impuestos Federales y\nEstatales que perciba el Municipio, serán las que fijen las Leyes, Convenios y Acuerdos Federales y Estatales respectivos.\nARTÍCULO 56.- La validez de las licencias y permisos otorgados por el Municipio, está condicionada al exacto cumplimiento de los ordenamientos legales.\nARTÍCULO 57.- Las cuotas de Impuestos y Derechos, serán proporcionales en los casos de apertura, siempre que el período sea menor de seis meses, a excepción de los correspondientes a los contribuyentes eventuales.\nARTÍCULO 58.- Los gravámenes que prevé la presente Ley, no serán municipales, salvo por autorización expresa del Congreso del\nEstado; con excepción de los recargos, que podrán condonarse total o parcialmente, conforme al artículo 110 de la Ley de Hacienda Municipal del Estado.\nARTÍCULO 59.- Se entiende como fecha de iniciación de operaciones de las personas físicas y de las unidades económicas, aquella en el primer ingreso. En caso de personas morales, el día de su constitución, aún cuando esta sea anterior a la fecha de apertura\nARTÍCULO 60.- Las personas físicas, morales o unidades económicas vendedores ambulantes, agentes de ventas, comisionistas, repartidores, concesionarios, ambulantes o cualquier otro nombre que se le da al expendedor, serán solidariamente responsables del pago del impuesto, derecho o multa que origine el motivo de las actividades que ejerzan, para lo cual se constituirán en retenedores de los créditos fiscales, debiendo enterarlos a la Recaudación de Rentas Municipal, dentro de los plazos que fijan las Leyes Fiscales Municipales.\nARTÍCULO 61.- Cuando no se establezca un plazo específico para el pago de un derecho o impuesto, y este se refiera a un pago anual, se tomará como plazo para poder realizarlo los meses de enero, febrero y marzo del ejercicio fiscal en curso, vencido este término se causará un recargo económico del 3% mensual sobre el monto que corresponda, independientemente de las sanciones administrativas a que se tuviese lugar.\nARTÍCULO 62.- Todos aquellos trámites de permisos, revalidaciones, inspecciones, derechos, constancias, certificados, licencias o similares que se encuentren establecidas en el apartado de Derechos de la presente Ley de Ingresos, a excepción de aquellos trámites que incidan en la modificación de factores de cálculo en el Impuesto\nPredial, estarán sujetas para su aprobación, a la liquidación al la actividad del trámite solicitado.\nARTÍCULO 63.- Para efectos del Impuesto Para Mantenimiento y\nConservación de las Vías Públicas; se entenderá por:\nVehículo de uso particular: aquellos impulsados por motor trasladarse de un punto a otro pudiendo ser de tipo sedán, coupé, pick-up o motocicleta.\nVehículo de transporte público de pasajeros: aquellos vehículos establecida.\nCamiones de uso particular: aquellos vehículos impulsados por motor destinados al transporte de mercancía, material, insumos o poseedor, de dos o más ejes y que puede estar adecuado con redilas, caja, caja lisa, plataforma, equipo de control de temperatura y demás aditamentos para carga y transporte.\nCamiones de transporte público de pasajeros: aquellos impulsados por motor de gasolina, diésel o gas, de dos o más ejes usados para el transporte de pasajeros o trabajadores, en el que sus asientos están ubicados en dirección al conductor y su capacidad es mayor a los 10 pasajeros, pudiendo o no tener una ruta establecida.\nCamiones de carga pesada: aquellos impulsados por motor de gasolina o diésel de 3 o más ejes y de más de 5 toneladas destinados al transporte de mercancía, material o insumos ya sea en tractocamión solo o con remolque o semirremolque.\nARTÍCULO 64.- Adultos mayores de 60 años, jubilados, pensionados, personas con discapacidad, así como madres jefas de familia sin cónyuge o pareja en aptitud de trabajar, que son el único sostén del hogar, con hijo o hijos menores de edad y/o personas con capacidades diferentes, de escasos recursos propietarios de predios urbanos, suburbanos y rústicos destinados total y exclusivamente\nFamilia, que no estén de acuerdo con el valor de construcción y Construcción, Base del Impuesto Predial del Municipio de\nEnsenada, B.C., podrán solicitar una inspección sin costo ante la\nDirección de Administración Urbana, Ecología y Medio Ambiente, la en su caso efectuar la modificación correspondiente.\nARTÍCULO 65.- La Autoridad Fiscal tendrá la facultad de hacer multas y/o infracciones impuestas por una misma dependencia que estén registradas a nombre de la misma persona física, moral, del predio o vehículo.\nARTÍCULO 66.- Por cada multa que impongan las dependencias municipales que dentro de sus facultades tengan las de inspección, calificación, determinación, imposición y notificación de multas, se cobrará una cantidad adicional del 3% sobre el valor de la multa siempre y cuando este porcentaje no rebase de 10.00 UMA ni sea menor de 1.00 UMA. El recurso que se obtenga se destinará a fortalecer la operatividad de las áreas encargadas en llevar a cabo estas actividades.\nARTÍCULO 67.- Tratándose de Impuesto Predial, a ningún propietario o poseedor se le aplicará la condonación de multas y recargos si su predio fue objeto de prescripción y/o Certificado de\nMejoramiento de la Imagen Urbana.\nARTÍCULO 68.- Tratándose del descuento a jubilados, pensionados y adultos mayores de 60 años mencionado en el artículo 3 segundo párrafo de la presente Ley de Ingresos, independientemente de que se haya cumplido a cabalidad con los requisitos establecidos, la año inmediato anterior hayan obtenido el beneficio, habiten el inmueble y que el mismo sea la propiedad objeto de descuento.\nCuando falsifiquen, alteren, supriman u oculten documentos públicos o privados, o teniendo la obligación legal de conducirse con verdad en un acto ante la autoridad fiscal, se compruebe que se condujo con falsedad, serán sancionados eliminando el beneficio otorgado y durante el ejercicio fiscal en curso y/o ejercicios anteriores más accesorios que pudiera generar, extendiendo esta sanción hasta por un periodo de cinco años anteriores.\nARTÍCULO 69.- Para la liberación de los vehículos que estén en garantía por infracciones al Reglamento de Tránsito Municipal, sin excepción, será necesario presentar recibo de pago expedido por la Dirección de Recaudación.\nSolamente en los casos en los que, previa sentencia emitida liberación de vehículo y además ésta exima del pago correspondiente se autorizará la liberación del vehículo sin que exista pago correspondiente.\nARTÍCULO 70.- No se causará la cuota fija y sobretasa establecida en la fórmula para el cálculo del Impuesto\nSobre Adquisición de Inmuebles en los supuestos a), b), c) y\nd)señalados en el párrafo octavo referente a la base gravable tasa\n0%. Lo anterior no exime las multas y recargos que pudieran generarse al no presentar la declaración en el tiempo establecido.\nARTÍCULO 71.- Con el fin de fortalecer la operatividad así como impulsar la promoción y asistencia a estas, aquellas\nEntidades Paramunicipales que cuenten con permiso para venta de alcohol estarán exentas del pago de revalidación anual de permisos y servicios adicionales que expide la Dirección de\nComercio, Alcoholes y Espectáculos Públicos, siempre y cuando señale.\nARTÍCULO 72.- Conforme a lo estipulado en el Artículo 63 fracción\nEstado de Baja California, se establece la exención de los Derechos\nMunicipio de Ensenada, B.C. cuando estos tengan relación con la búsqueda y localización de personas desaparecidas.\nARTÍCULO 73.- Entidades paramunicipales cuyas oficinas principales creadas, estarán exentas del pago de Impuesto Predial siempre y debidamente registrado ante las autoridades correspondientes.\nARTÍCULO 74.- Asociaciones Civiles constituidas en el Municipio de\nEnsenada, B.C., con una antigüedad mayor a 3 años en la ciudad que cumplimiento de sus fines, podrán acceder al pago del Impuesto\nSobre Asistencia a Juegos Permitidos y Espectáculos Públicos a tasa\n0%; previa autorización de la Autoridad Fiscal a través de la\nPresidencia.\nLo anterior aplicará siempre y cuando demuestren ser los organizadores únicos y directos de dicho evento, el cual no deberá superar el aforo de 500 (quinientas) personas ni exceder el boletaje el monto de totalizado $ 500,000.00 (quinientos mil pesos\n00/100 m.n.).\nEl contenido del presente artículo no exenta a la asociación organizadora de acudir a realizar el trámite o trámites de todos los permisos y anuencias correspondientes ante las autoridades municipales respectivas. De igual manera no se autorizará la exención del citado impuesto si se detecta que existe asociación con promotora y/o terceros involucrados o con fines lucrativos particulares, lo cual no limitará que se desarrolle el evento sino hasta haber cubierto el monto del impuesto correspondiente.\nARTÍCULO 75.- La autoridad fiscal, en ejercicio de sus facultades establecido en el artículo 37 de la citada Ley, podrá actualizar o modificar los valores fiscales y/o factores que intervienen propietario o poseedor, así como las que realmente caractericen al inmueble en cuestión.\nTRANSITORIOS\nARTÍCULO PRIMERO.- Las contribuciones, cuyo cobro haya caso de reformas o modificaciones a estas disposiciones, que permitan el cobro de dichas contribuciones, se cobrarán por el ejercicio a la tasa que fijaba la Ley de Ingresos vigente, en contribución.\nARTÍCULO SEGUNDO.- Con relación al cobro de los Derechos por servicios que prestan las Oficinas de la Dirección de Catastro y la Dirección de Administración Urbana, Ecología y Medio Ambiente contemplados en la presente Ley se estará a lo dispuesto en el\nConvenio que en Materia de Catastro y Control Urbano, celebraron el Gobierno Constitucional del Estado de Baja California y el\nAyuntamiento de Ensenada, Baja California.\nARTÍCULO TERCERO.- La inspección de dispositivos de seguridad por parte de la Dirección de Bomberos y la Coordinación de\nProtección Civil a que se refiere al artículo 43 fracción II, sólo dará lugar al cobro de derechos, tratándose de la primera inspección, sin perjuicio de la aplicación de las sanciones que prevé el reglamento específico, en el caso de incumplimiento de los dispositivos de seguridad correspondientes.\nARTÍCULO CUARTO.- Será el Cabildo quien reglamentará el uso de los rangos en los derechos por cobrar, de acuerdo al tabulador que para dicho efecto aprueben.\nARTÍCULO QUINTO.- En caso de que durante el presente ejercicio fiscal las dependencias a que se refiere esta Ley, sufrieran denominación, los servicios previstos para ser prestados por dichas dependencias, se entenderán referidos y prestados por las que las sustituyan, dando lugar al pago de los derechos que señala esta.\nARTÍCULO SEXTO.- Con relación a la vigencia del artículo 28 fracción XI, inciso C); se establece un período del 1ro. de enero deberán acudir a regularizar su licencia, pagando la tarifa establecida en el inciso a) del mismo inciso y artículo.\nARTÍCULO SÉPTIMO.- A los beneficiarios del derecho por el servicio de alumbrado público del ejercicio fiscal 2025 que, conforme a la aplicación de la cuota contemplada en la presente Ley en su artículo\n11, resultare un importe diferente hasta en un 10% o más al importe pagado en el ejercicio fiscal 2024, la tarifa a cubrir se actualizará solo $5.00 (cinco pesos 00/100 m.n.) mensuales más de lo que se pagó en el ejercicio fiscal 2024.\nARTÍCULO OCTAVO.- Adultos mayores de 65 años de escasos recursos y personas con alguna discapacidad, que acrediten su condición con estudio socioeconómico realizado por el Sistema para el Desarrollo\nIntegral de la Familia (DIF) y/o documento vigente expedido por la autoridad competente, podrán obtener hasta un 100% de descuento en el pago del derecho por servicio de alumbrado público presentando solicitud ante la autoridad fiscal durante los primeros veinte días del año.\nARTÍCULO NOVENO.- Tratándose del Impuesto Sobre Asistencia a Juegos\nPermitidos y Espectáculos Públicos, aquellas Entidades\nParamunicipales del Municipio de Ensenada, Baja California, que organicen espectáculos públicos, eventos o diversiones causarán el impuesto a tasa 0% siempre y cuando estos sean organizados exclusivamente por la paramunicipal y que el 100% de lo recaudado sea ingresado a la misma.\nARTÍCULO DÉCIMO.- En la aplicación de la sobretasa para\nEnsenada, establecida en el artículo 2 de esta Ley, se otorgarán los descuentos siguientes:\nI.- Descuento del 1.3 al millar de la sobretasa, respecto a las tasas establecidas en los incisos 1.a.1, 1.a.2, 1.a.3,\nII.- Descuento del 1.2 al millar de la sobretasa, respecto a las tasas establecidas en los incisos 1.a.6, 1 b, 1 g, 3, 4, 4.1, 4.2, 5.\nIII.- Descuento del 0.51 al millar de la sobretasa respecto a\nLas tasas establecidas en los incisos 1 e, 1 f, 1.g.2, 1 o, 1 r.\nARTÍCULO UNDÉCIMO.- El cálculo de Impuesto Predial del ejercicio fiscal 2025 en ningún caso será superior del 10% para los siguientes incisos: 1.- a.1), 1.- a.2), 1.- a.3), 1.- a.4), 1.- a.5), 2.-a),\n2.-b) y 2.-c); del 20% para los siguientes incisos: 1.-b), 1.g.1), 1.-g.4),1.-h), 1.-i), 1.-j); y del 30% para los siguientes incisos: 1.-a.6), 1.-c), 1.-d), 1.-e), 1.-f), 1.-g.2), 1.-g.3),\n1.-k), 1.-l), 1.-m), 1.-o), 1.-p), 1.-q), 1.-r), 2.-e), 2.-g) y demás usos contemplados en el artículo 2 de la presente Ley, con respecto a lo aprobado en el ejercicio fiscal 2024. Lo anterior no aplicará para aquellos predios que, por medio de trámites hechos en el área encargada del Catastro, se modifiquen sus valores, características catastrales y/o destino que afecte el cálculo del impuesto.\nARTÍCULO DUODÉCIMO.- El Impuesto Predial se pagará por los últimos cinco años, de conformidad con lo establecido en el artículo 188 de la Ley de Hacienda Municipal, independientemente que se encuentre requerida o embargada, siempre y cuando el pago se realice en una sola exhibición, pudiendo tener este beneficio las claves catastrales que se encuentren en proceso judicial (siempre y cuando se desistan para obtener este beneficio).\nARTÍCULO DECIMOTERCERO.- Los trámites contenidos en la fracción\nI, numerales 6 y 7 de los servicios que presta la Paramunicipal\nEnsenada, Baja California (IMIP) así como los establecidos en la fracción X, numeral 1 fracciones A 1, 2, 3 y 4 de los servicios de Ensenada, B.C. (COPLADEM) tendrán un 50% (cincuenta por ciento) pequeñas tiendas de conveniencia, restaurantes y cafeterías así como los demás establecidas en el Programa de Desarrollo Urbano del Centro de Población de Ensenada (PDUCPE) 2024-2036 y la\nLey de Desarrollo Urbano del Estado de Baja California en su artículo Segundo Transitorio, y además no sean mayores a 200 m² en la totalidad del proyecto.\nARTÍCULO DECIMOCUARTO.- De conformidad con el Reglamento de\nFomento a la Competitividad y Desarrollo Económico para el\nMunicipio de Ensenada, Baja California y una vez cumplidos los requisitos y condiciones que el mismo señala, el Ejecutivo\nMunicipal a través de la Autoridad Fiscal podrá otorgar estímulo fiscal consistentes en hasta el 50% de descuento en el Impuesto\nPredial cuenta corriente, hasta el 50% de descuento en Impuesto sobre Adquisición de Inmuebles y hasta el 50% de descuento sobre el costo de derechos municipales respecto de los predios que sean destinados a este programa, para empresas que los soliciten. Estos estímulos serán aplicados solamente para el lugar o lugares donde se desarrolle o pretenda desarrollar la actividad.\nARTÍCULO DECIMOQUINTO.- Beneficiarios del Programa Estatal de\nVivienda residentes del Municipio de Ensenada B.C. que comprueben través de este programa, podrán exentar por única ocasión los su vivienda establecidos por la Dirección de Administración Urbana, Ecología y Medio Ambiente, así como los impuestos que se generen, de la vivienda beneficiario del programa.\nARTÍCULO DECIMOSEXTO.- La presente Ley entrará en vigor el día\n1ro. de enero del año dos mil veinticinco.\nARTÍCULO DECIMOSÉPTIMO.- En beneficio e impulso del programa inicio del programa, los organismos públicos e instituciones del pago de los impuestos y derechos que se causen. Dicha exención por la edificación y desarrollo de las viviendas a cargo de las empresas, constructoras y/o desarrolladoras adheridas, contratadas o registradas en el programa, durante el tiempo que duren las obras, sujetándose a la normatividad municipal en la materia y siempre que se encuentren dentro del marco establecido en el programa citado.\nLa exención fiscal tendrá vigencia desde el inicio de las obras y concluirá con la obtención de la constancia de obra terminada o la entrega oficial del desarrollo, lo que ocurra primero.\nLa presente exención no incluye el Impuesto Predial ni otras contribuciones periódicas vinculadas a la propiedad del predio.\nAsimismo, esta exención no exime a los responsables de realizar los trámites y notificaciones correspondientes ante las autoridades municipales competentes.\nLas contribuciones municipales exentas son las siguientes:\nI. Impuestos exentos:\n1. Impuesto sobre Adquisición de Inmuebles (ISAI).\nII. Trámites administrativos de derechos exentos:\n1. Factibilidad de uso del suelo;\n2. Certificado de libertad de gravamen;\n3. Dictamen de uso del suelo;\n4. Manifestación de impacto ambiental;\n5. Movimiento de tierra;\n6. Deslinde catastral;\n7. Licencia de construcción;\n8. Régimen de propiedad en condominio;\n9. Licencia de fraccionamiento;\n10. Certificado de número oficial;\n11. Constancia de obra terminada;\n12. Cambio de propietario.\nQuedarán excluidos del presente los impuestos, derechos, exenciones, condonaciones, beneficios fiscales y demás contribuciones causadas con anterioridad inmediata al inicio del programa sobre los predios a desarrollar, así como aquellas que se generen una vez concluidos los trabajos de desarrollo.\nPor única ocasión, los ciudadanos beneficiarios del programa estarán exentos del impuesto generado por concepto de traslado de dominio (ISAI) con motivo de la formalización de adquisición de vivienda, siempre que presenten la documentación correspondiente ante las autoridades municipales competentes.\nArtículo Transitorio Adicionado\nCalifornia, a los veinte días del mes de diciembre del año dos mil veinticuatro.\nC. EVELYN SÁNCHEZ SÁNCHEZ\nDIPUTADA PRESIDENTA\nC. MICHELLE ALEJANDRA TEJEDA MEDINA\nDIPUTADA SECRETARIA\nARTÍCULO DECIMOSÉPTIMO TRANSITORIO. – Fue reformado por Decreto No. 106, expedido por la H. XXV Legislatura, siendo Gobernadora Constitucional la C. Marina del\nPilar Ávila Olmeda 2021-2027;\nARTÍCULO ÚNICO TRANSITORIO DEL DECRETO No. 106, POR EL QUE SE\nDECIMOSÉPTIMO TRANSITORIO; PUBLICADO EN EL PERIÓDICO OFICIAL No. 39,\nLEGISLATURA, SIENDO GOBERNADORA CONSTITUCIONAL LA C. MARINA DEL\nPILAR ÁVILA OLMEDA 2021-2027.\nTRANSITORIOS\nÚNICO. La presente reforma entrará en vigor al día siguiente de su publicación en el\nPeriódico Oficial del Estado de Baja California.\nDADO en Sesión Ordinaria de la XXV Legislatura en la Ciudad de Mexicali, B.C., a los diecinueve días del mes de junio del año dos mil veinticinco.\nDIP. MICHELLE ALEJANDRA TEJEDA MEDINA\nPRESIDENTA\n(RÚBRICA)\nDIP. NORMA ANGELICA PEÑALOZA ESCOBEDO\nSECRETARIA\n(RÚBRICA)\nDE CONFORMIDAD CON LO DISPUESTO POR LA FRACCIÓN I DEL ARTÍCULO 49\nCALIFORNIA, IMPRÍMASE Y PUBLÍQUESE.\nMEXICALI, BAJA CALIFORNIA, A LOS 20 DÍAS DEL MES DE JUNIO DEL AÑO DOS\nMIL VEINTICINCO.\nMARINA DEL PILAR ÁVILA OLMEDA\nGOBERNADORA DEL ESTADO\nDE BAJA CALIFORNIA\n(RÚBRICA)\nALFREDO ÁLVAREZ CÁRDENAS\nSECRETARIO GENERAL DE GOBIERNO\nDEL ESTADO DE BAJA CALIFORNIA\n(RÚBRICA)",
  "ordenamiento": "REGLAMENTO",
  "jurisdiccion": "BAJA CALIFORNIA",
  "fuente_oficial": "Periódico Oficial",
  "FECHA PER OFIC": "2025/06/27",
  "ESTATUS": "VIGENTE",
  "TOMO": "TOMO_II",
  "URL": "https://www.congresobc.gob.mx/Documentos/ProcesoParlamentario/Leyes/TOMO_II/20250627_LEYINGRESOENSENADA2025.PDF",
  "es_escaneado": false,
  "tiene_tablas": true,
  "materia": [
    "financiero",
    "fiscal",
    "económico"
  ]
}