{
  "titulo": "Ley DE FISCALIZACIÓN y RENDICIÓN DE CUENTAS DEL ESTADO DE BAJA CALIFORNIA y SUS MUNICIPIOS",
  "Contenido": "BAJA CALIFORNIA Y SUS MUNICIPIOS\nPublicado en el Periódico Oficial No. 37,\nTÍTULO PRIMERO\nDisposiciones Generales\nCAPÍTULO ÚNICO\nArtículo 1.- La presente Ley es de orden público, reglamentaria de los artículos 22, 27\nI. La revisión y fiscalización de:\na) La Cuenta Pública;\nb) Las situaciones irregulares que se denuncien en términos de esta Ley, respecto al ejercicio fiscal en curso o a ejercicios anteriores distintos al de la Cuenta Pública en revisión;\nc) La aplicación de las fórmulas de distribución, ministración y ejercicio de las participaciones, conforme a las disposiciones aplicables; y,\nd) El destino y ejercicio de los recursos provenientes de financiamientos y obligaciones contratados por todas las Entidades Fiscalizadas.\nPara efectos de esta fracción, la Auditoría Superior del Estado, podrá fiscalizar las operaciones que involucren recursos de la hacienda pública estatal o municipal, o el patrimonio de las Entidades Fiscalizadas, a través de contrataciones, subsidios, transferencias, donativos, fideicomisos, fondos, mandatos, asociaciones público privadas o cualquier otra figura jurídica, financiamientos y obligaciones y el otorgamiento de garantías respectivas, entre otras.\nII. La organización de la Auditoría Superior del Estado, sus atribuciones, incluyendo aquellas para conocer, investigar y substanciar la comisión de faltas administrativas graves que detecte en sus funciones de fiscalización, en términos de esta Ley y de la legislación aplicable en materia de responsabilidades administrativa; así como su evaluación, control y vigilancia por parte del Congreso.\nArtículo 2.- La fiscalización de la Cuenta Pública comprende:\nLey de Fiscalización y Rendición de Cuentas del Estado de Baja California y sus Municipios. Página 1\nI. La fiscalización de la gestión financiera de las Entidades Fiscalizadas para\nEgresos, y demás disposiciones legales aplicables, en cuanto a los ingresos y gastos públicos, así como de los financiamientos y obligaciones, incluyendo la revisión del manejo, custodia, aplicación de recursos públicos, y demás información financiera, contable, patrimonial, presupuestaria y programática que las Entidades Fiscalizadas deban incluir en dicho documento, conforme a las disposiciones aplicables; y,\nII. La práctica de auditorías sobre el desempeño para verificar el grado de cumplimiento de los objetivos de los Programas de las Entidades Fiscalizadas.\nArtículo 3.- La fiscalización de la Cuenta Pública tiene el objeto establecido en esta\nLey y se llevará a cabo conforme a los principios de legalidad, definitividad, imparcialidad y confiabilidad.\nArtículo 4.- Las autoridades responsables de la aplicación de esta Ley, serán el\nCongreso y la Auditoría Superior del Estado, en el ámbito de sus respectivas competencias, correspondiéndole a esta última la interpretación de la misma.\nArtículo 5.- Para efectos de esta Ley, indistintamente en singular y plural se entenderá por:\nI. Auditoría Superior del Estado: La Auditoría Superior del Estado de Baja California, órgano técnico de fiscalización del Congreso a que se refieren los artículos 27, fracciones\nCalifornia;\nII. Auditorías: Proceso sistemático en el que de manera objetiva se obtiene y se evalúa evidencia para determinar si las acciones llevadas a cabo por los entes sujetos a revisión se realizaron de conformidad con la normatividad establecida o con base en principios que aseguren una gestión pública adecuada;\nIII. Autonomía de gestión: La facultad de la Auditoría Superior del Estado para decidir sobre su organización interna, estructura, funcionamiento y resoluciones, así como la administración de sus recursos humanos, materiales y financieros que utilice para la ejecución de sus atribuciones, en los términos contenidos en la Constitución Política del\nFracción Reformada\nIV. Autonomía técnica: La facultad de la Auditoría Superior del Estado para decidir sobre la planeación, programación, ejecución, informe y seguimiento en el proceso de la fiscalización superior;\nV. Congreso: El Congreso del Estado de Baja California;\nLey de Fiscalización y Rendición de Cuentas del Estado de Baja California y sus Municipios. Página 2\nVI. Comisión: La Comisión de trabajo del Congreso que dispone la fracción XIII del vigilancia, coordinación y evaluación del funcionamiento de la Auditoría Superior del Estado;\nCalifornia;\nVIII. Cuenta Pública: La información anual que los Entes Públicos presenten al\nCongreso sobre su gestión financiera, comprendida del 1 de enero al 31 de diciembre de cada año de calendario, excepto cuando se trate de ejercicios de iniciación de operación, liquidación, fusión, escisión o terminación, la cual se formula e integra en términos de lo dispuesto en la Ley General de Contabilidad Gubernamental, Ley de Presupuesto y Ejercicio del Gasto Público del Estado de Baja California, y demás disposiciones aplicables en la materia;\nIX. Entes Públicos: Los Poderes del Estado, los Municipios del Estado, Entidades\nParaestatales, Entidades Paramunicipales y los Órganos Constitucionales Autónomos;\nX. Entidades Fiscalizadas: Los Entes Públicos; las entidades de interés público distintas a los partidos políticos; los mandantes, mandatarios, fideicomitentes, fiduciarios, fideicomisarios o cualquier otra figura jurídica análoga, así como los mandatos, fondos o fideicomisos, públicos o privados, cuando hayan recibido por cualquier título, recursos públicos federales, estatales o municipales, no obstante que sean o no considerados entidades paraestatales o paramunicipales en términos de las disposiciones que las regulan y aun cuando pertenezcan al sector privado o social y, en general, cualquier entidad, persona física o moral, pública o privada, que haya captado, recaudado, administrado, manejado, ejercido, cobrado o recibido en pago directo o indirectamente recursos públicos, incluidas aquellas personas morales de derecho privado que tengan autorización para expedir recibos deducibles de impuestos por donaciones destinadas para el cumplimiento de sus fines;\nXI. Faltas administrativas graves: Las así señaladas en la legislación aplicable en materia de responsabilidades administrativas;\nXII. Financiamiento y Obligaciones: Toda operación constitutiva de un pasivo, directo o contingente, de corto, mediano o largo plazo, derivada de un crédito, empréstito o préstamo, incluyendo arrendamientos y factorajes financieros o cadenas productivas, independientemente de la forma mediante la que se instrumente, u obligación de pago, en los términos del artículo 117 Fracción VIII de la Constitución Política de los Estados Unidos\nMexicanos, de la Ley de Disciplina Financiera de las Entidades Federativas y los Municipios, disposiciones, reglamentos y criterios que de éstas deriven;\nLey de Fiscalización y Rendición de Cuentas del Estado de Baja California y sus Municipios. Página 3\nXIII. Fiscalía Especializada: La fiscalía especializada en materia de combate a la corrupción en el Estado;\nXIV. Fiscalización Superior: La facultad del Congreso, ejercida por conducto de la\nAuditoría Superior del Estado, para la revisión, análisis y auditoría de la Cuenta Pública de los Entes Públicos del ejercicio fiscal correspondiente, la cual comprende la Cuenta Pública, los Informes de Avance de Gestión Financiera y la documentación comprobatoria y justificatoria mensual del ingreso y gasto público, incluyendo a cualquier persona física o moral pública o privada que haya tenido o tenga a su cargo la administración, el manejo, custodia, o el ejercicio y aplicación de recursos públicos estatales o municipales, en los términos constitucionales, de esta Ley y demás disposiciones aplicables;\nXV. Gestión financiera: Las acciones, tareas y procesos que, en la ejecución de los\nProgramas, realizan las Entidades Fiscalizadas para captar, recaudar u obtener recursos públicos conforme a la Ley de Ingresos y Presupuesto de Egresos respectivos, y las demás disposiciones aplicables, así como para administrar, manejar, custodiar, ejercer y aplicar dichos recursos y demás fondos, patrimonio y recursos, en términos del Presupuesto de\nEgresos y las demás disposiciones aplicables;\nXVI. Informe de Avance de Gestión Financiera: El informe trimestral, que, como parte integrante de la Cuenta Pública, rinden los Entes Públicos al Congreso, sobre los avances físicos y financieros de los Programas aprobados, de conformidad con lo establecido en la presente Ley, y en las demás disposiciones aplicables;\nXVII. Informe General: El Informe General Ejecutivo del Resultado de la Fiscalización\nSuperior de la Cuenta Pública;\nXVIII. Informe Específico: El informe derivado de las denuncias fundadas de cualquier persona, cuando se presuma el manejo, aplicación o custodia irregular de recursos públicos o de su desvío, las cuales se practicarán en relación al ejercicio fiscal en curso, así como respecto a ejercicios fiscales anteriores;\nXIX. Informes Individuales: Los informes de cada una de las auditorías practicadas a las Entidades Fiscalizadas;\nXX. Ley de Ingresos: La Ley de Ingresos del Estado y las Leyes de Ingresos de los\nMunicipios del Estado de Baja California, del ejercicio fiscal correspondiente;\nXXI. Órgano Constitucional Autónomo: Son los órganos creados inmediata y fundamentalmente en la Constitución, que no se adscriben a los poderes del Estado, y que cuentan con autonomía e independencia funcional y financiera;\nXXII. Órgano Interno de Control: Las unidades administrativas a cargo de promover, evaluar y fortalecer el buen funcionamiento del control interno en los Entes Públicos, así como de la investigación, substanciación y, en su caso, de sancionar las faltas\nLey de Fiscalización y Rendición de Cuentas del Estado de Baja California y sus Municipios. Página 4 materia de responsabilidades administrativa;\nXXII BIS. Perspectiva de Género: Concepto que se refiere a la metodología y los mecanismos que permiten identificar, cuestionar y valorar la discriminación, desigualdad y exclusión de las mujeres, que se pretende justificar con base en las diferencias biológicas entre mujeres y hombres, así como las acciones que deben emprenderse para actuar sobre los factores de género y crear las condiciones de cambio que permitan avanzar en la construcción de la igualdad de género;\nFracción Adicionada\nXXIII. Presupuesto de Egresos: El Presupuesto de Egresos de cada uno de los Entes\nPúblicos, del ejercicio fiscal correspondiente;\nXXIV. Proceso concluido: Aquél que las Entidades reporten como tal, en el Informe de\nAvance de Gestión Financiera, con base en el gasto devengado, y/o pagado, conforme a la\nLey General de Contabilidad Gubernamental y las demás disposiciones aplicables;\nXXV. Programas: Los señalados en la Ley de Planeación para el Estado de Baja\nCalifornia, en la Ley de Presupuesto y Ejercicio del Gasto Público del Estado de Baja\nCalifornia y los contenidos en el Presupuesto de Egresos, con base en los cuales las\nEntidades Fiscalizadas realizan sus actividades en cumplimiento de sus atribuciones y se presupuesta el gasto público;\nFracción Reformada\nXXVI. Programa Operativo Anual: El documento que sustenta el Presupuesto de\nEgresos de los Entes Públicos y que convierte los lineamientos de la Planeación Estatal y\nMunicipal económica y social, en objetivos, resultados y metas concretas, señalando responsables de cada Programa, estableciendo indicadores para medir su costo, beneficios y tiempo para su ejecución;\nXXVII. Recursos Públicos: Los ingresos, independientemente de su origen; egresos y patrimonio que recaudan, administran y ejercen las Entidades Fiscalizadas, así como los derechos y obligaciones propiedad de las mismas;\nXXVIII. Reunión: La o las reuniones realizadas con las Entidades Fiscalizadas, sus servidores públicos o quienes dejaron de serlo, terceros, y la Auditoría Superior del Estado en el proceso de fiscalización, así como para conocer directamente el ejercicio de sus funciones;\nFracción Reformada\nXXIX. Servidores públicos: Los señalados en la Constitución y en la legislación aplicable en materia de responsabilidades administrativas;\nXXX. Tribunal: El Tribunal Estatal de Justicia Administrativa del Estado de Baja\nCalifornia;\nLey de Fiscalización y Rendición de Cuentas del Estado de Baja California y sus Municipios. Página 5\nXXXI. Titulares de las Entidades: Los servidores públicos que se señalan en los siguientes incisos: administración pública centralizada, y en relación a las entidades paraestatales que forman\nGobernador como sus responsables;\nb) En los Poderes Legislativo y Judicial, los servidores públicos que funjan como sus respectivos Presidentes;\nc) En los Municipios, el Presidente Municipal tratándose de la administración pública centralizada y en relación a las entidades paramunicipales las personas físicas señaladas como responsables de acuerdo a su instrumento de creación; y,\nd) En el Instituto Estatal Electoral, el Presidente del Consejo General Electoral, en la\nComisión Estatal de los Derechos Humanos, en el Tribunal y en el Tribunal de Justicia\nElectoral, así como en los demás Órganos Constitucionales Autónomos, las personas físicas que los presiden de conformidad a las leyes de su creación.\nXXXII. Unidad Administrativa: Las distintas áreas que integran la estructura organizacional de la Auditoría Superior del Estado, de conformidad con lo dispuesto en su\nReglamento Interior; y,\nXXXIII. Unidad de Medida y Actualización: El valor establecido por el Instituto\nNacional de Estadística y Geografía, en términos del artículo 26, apartado B Sexto párrafo, de la Constitución Política de los Estados Unidos Mexicanos y la ley federal en la materia, para determinar la cuantía del pago de las obligaciones y supuestos previstos en las leyes.\nLas definiciones previstas en la Ley General de Contabilidad Gubernamental, Ley de\nDisciplina Financiera de las Entidades Federativas y los Municipios, legislación local en materia de financiamientos y obligaciones y Ley de Presupuesto y Ejercicio del Gasto\nPúblico del Estado de Baja California, le serán aplicables a la presente Ley.\nArtículo Reformado\nArtículo 6.- Tratándose de los informes a que se refieren las fracciones XVII, XVIII y\nXIX del artículo anterior, la información contenida en los mismos será publicada en el portal institucional de internet de la Auditoría Superior del Estado, conforme lo establece la\nBaja California, siempre y cuando no se revele información que se considere temporalmente reservada o que forme parte de un proceso de investigación, en los términos previstos en la legislación aplicable. La información reservada se incluirá una vez que deje de serlo. observaciones hasta que rinda los informes a que se refiere el presente artículo. Los\nLey de Fiscalización y Rendición de Cuentas del Estado de Baja California y sus Municipios. Página 6 en esta Ley y la legislación aplicable en materia de responsabilidades administrativas.\nArtículo 7.- La fiscalización de la Cuenta Pública que realiza la Auditoría Superior del\nEstado se lleva a cabo de manera posterior al término de cada ejercicio fiscal; una vez que el programa anual de auditoría esté aprobado y publicado en su página de internet; tiene carácter externo y por lo tanto se efectúa de manera independiente y autónoma de cualquier otra forma de control o fiscalización que realicen los Órganos Internos de Control.\nArtículo 8.- A falta de disposición expresa en esta Ley, se aplicarán en forma supletoria y en lo conducente, la Ley General de Contabilidad Gubernamental; la Ley de\nDisciplina Financiera de las Entidades Federativas y los Municipios; la legislación local en materia de financiamientos y obligaciones; la Ley de Coordinación Fiscal del Estado de Baja\nCalifornia; la Ley de Presupuesto y Ejercicio del Gasto Público del Estado de Baja California; el Código Fiscal del Estado de Baja California; la legislación aplicable en materia del sistema nacional y estatal anticorrupción y de responsabilidades administrativas en el Estado, la Ley de Ingresos y Presupuesto de Egresos; así como las disposiciones del derecho común sustantivo y procesal del Estado.\nArtículo 9.- La Auditoría Superior del Estado deberá emitir los criterios relativos a la ejecución de auditorías, mismos que deberán sujetarse a las disposiciones establecidas en la presente Ley y publicarse en el Periódico Oficial del Estado de Baja California.\nArtículo 10.- Los Entes Públicos facilitarán los auxilios que requiera la Auditoría\nSuperior del Estado para el ejercicio de sus funciones.\nLos servidores públicos, así como cualquier entidad, persona física o moral, pública o privada, fideicomiso, mandato o fondo, o cualquier otra figura jurídica, que reciban o ejerzan recursos públicos, deberán proporcionar la información y documentación que solicite la\nAuditoría Superior del Estado, para efectos de sus auditorías e investigaciones, de conformidad con los procedimientos establecidos en las leyes y sin perjuicio de la competencia de otras autoridades.\nDe no proporcionar la información, los responsables serán sancionados en los términos de la presente Ley, con independencia de lo que prevea la legislación aplicable en materia de responsabilidades administrativas y, en su caso, en términos de la legislación penal aplicable.\nCuando esta Ley no prevea plazo, la Auditoría Superior del Estado podrá fijarlo y no será inferior a cinco días hábiles ni mayor a quince días hábiles, contados a partir del día siguiente de su notificación.\nPárrafo Reformado\nAuditoría Superior del Estado, las Entidades Fiscalizadas podrán solicitar por escrito\nLey de Fiscalización y Rendición de Cuentas del Estado de Baja California y sus Municipios. Página 7 fundado, un plazo mayor para atenderlo; la Auditoría Superior del Estado determinará si lo concede por un término que no deberá exceder de cinco días hábiles, sin que pueda prorrogarse de modo alguno. solicitada, los anexos, estudios, memorias de cálculo y demás documentación soporte relacionada con la solicitud.\nArtículo Reformado\nArtículo 11.- La Auditoría Superior del Estado podrá imponer multas, conforme a lo siguiente:\nI. Cuando no se atiendan, o se atiendan de forma incompleta o fuera del plazo otorgado, los requerimientos a que refiere el artículo precedente, o bien obstaculicen la actividad fiscalizadora, salvo que exista disposición legal o mandato judicial que lo impida, o por causas ajenas a su responsabilidad, la Auditoría Superior del Estado podrá imponer:\nPárrafo de la Fracción Reformado\na) A los servidores públicos y las personas físicas una multa mínima de ciento cincuenta a una máxima de dos mil veces el valor diario de la Unidad de Medida y\nActualización;\nb) Tratándose de personas morales, públicas o privadas, la multa consistirá en un mínimo de seiscientos cincuenta a diez mil veces el valor diario de la Unidad de Medida y\nActualización;\nFracción Reformada\nII. Se aplicarán las multas previstas en este artículo a los terceros que hubieran firmado contratos para explotación de bienes públicos o recibido en concesión o subcontratado obra pública, administración de bienes o prestación de servicios mediante cualquier título legal con las entidades fiscalizadas, cuando no entreguen la documentación e información que les requiera la Auditoría Superior del Estado;\nII BIS. Cuando no se presente la Cuenta Pública y/o los Informes de Avance de\nGestión al Congreso, en los plazos y términos que establece esta Ley, se aplicará a la persona titular de la Entidad Fiscalizada, una multa por cada omisión, que consistirá en un\nActualización;\nFracción Adicionada\nII TER. Cuando no se atienda el requerimiento de información a que hace mención el artículo 77 de esta Ley, se aplicará a la persona titular del Órgano Interno de Control, una multa por cada omisión, que consistirá en un mínimo de cincuenta a cien veces el valor diario de la Unidad de Medida y Actualización;\nFracción Adicionada\nLey de Fiscalización y Rendición de Cuentas del Estado de Baja California y sus Municipios. Página 8\nIII. La reincidencia se sancionará con una multa hasta del doble de la impuesta anteriormente, sin perjuicio de que persista la obligación de atender el requerimiento respectivo;\nIV. Las multas establecidas en esta Ley tendrán el carácter de créditos fiscales y se fijarán en cantidad líquida. La Secretaría de Hacienda del Estado se encargará de hacer efectivo su cobro en términos del Código Fiscal del Estado de Baja California, y de las demás disposiciones aplicables;\nFracción Reformada\nV. Para imponer la multa que corresponda, la Auditoría Superior del Estado, debe oír previamente al presunto infractor y tener en cuenta sus condiciones económicas, así como la gravedad de la infracción cometida y en su caso, elementos atenuantes, su nivel jerárquico y la necesidad de evitar prácticas tendientes a contravenir las disposiciones contenidas en esta Ley; y,\nVI. Las multas que se impongan en términos de este artículo son independientes de las sanciones administrativas y penales que, en términos de las leyes en dichas materias, resulten aplicables por la negativa a entregar información o cumplir con los requerimientos de la Auditoría Superior del Estado, así como por los actos de simulación que se presenten para entorpecer y obstaculizar la actividad fiscalizadora o la entrega de información falsa.\nLa Auditoría Superior del Estado celebrará los convenios y/o mecanismos de colaboración con la Secretaría de Hacienda del Estado, para que los ingresos derivados de estas multas se reintegren a la Auditoría Superior del Estado, los cuales serán destinados a propiciar el desarrollo institucional y mejora continua del mismo, conforme a su Plan de\nDesarrollo Institucional, y en ningún caso podrá destinarse al pago de sueldos, salarios o incentivos económicos.\nPárrafo Reformado\nLa Auditoría Superior del Estado, a través de la persona Titular, podrá emitir el reglamento para normar el procedimiento relativo a la imposición de las multas descritas en este artículo.\nPárrafo Adicionado\nArtículo Reformado\nArtículo 12.- La negativa a entregar o proporcionar de forma incompleta información a la Auditoría Superior del Estado, así como los actos de simulación que se presenten para aplicable en materia de responsabilidades administrativa y la ley penal aplicable.\nPárrafo Reformado\nCuando los servidores públicos y las personas físicas y morales, públicas o privadas aporten información falsa, serán sancionados penalmente conforme a las disposiciones legales que regulan la materia.\nArtículo Reformado\nLey de Fiscalización y Rendición de Cuentas del Estado de Baja California y sus Municipios. Página 9\nTÍTULO SEGUNDO la Fiscalización de la Cuenta Pública\nCAPÍTULO I\nArtículo 13.- El Informe de Avance de Gestión Financiera deberá ser integrado en los mismos términos de la Cuenta Pública a que se refiere el artículo 19 de la presente Ley.\nArtículo 14.- La información a que se refiere el artículo anterior deberá ser presentada de forma impresa y en dispositivos electrónicos de almacenamiento de datos de uso común conformidad con los lineamientos de carácter general que en su caso se establezcan por la\nAuditoría Superior del Estado.\nArtículo Reformado\nArtículo 15.- La documentación original comprobatoria y justificatoria del ingreso y gasto público parte integrante de los Informes de Avance de Gestión Financiera, deberá mantenerse a disposición de la Auditoría Superior del Estado, para cuando ésta lo solicite y en los términos previstos para las Cuentas Públicas en la presente Ley.\nArtículo 16.- En los casos en que las Entidades Fiscalizadas incumplan con lo dispuesto en el artículo anterior se aplicará lo dispuesto en los artículos 11 y 12 de esta Ley.\nArtículo 17.- Las Entidades Fiscalizadas deberán remitir al Congreso los Informes de\nAvance de Gestión Financiera por los trimestres primero, segundo y tercero de cada año, a más tardar el último día hábil de los meses de abril, julio y octubre del ejercicio en curso, respectivamente, con cifras y datos mensuales y acumulados al último día del último mes del trimestre que se informa y que corresponderán a la Cuenta Pública del año en curso.\nPárrafo Reformado\nLa información correspondiente al cuarto trimestre deberá enviarse por separado, en la misma fecha de la entrega de la Cuenta Pública del ejercicio de que se trate.\nPárrafo Adicionado\nTranscurridos los plazos señalados en el párrafo primero de este artículo, sin que se hubieren remitido los Informes de Avance de Gestión Financiera, el Congreso del Estado, través de la Presidencia de la Comisión, instruirá a la Auditoría Superior del Estado, requerir de requerimiento, de no presentarse el informe correspondiente en este plazo, se aplicará la multa prevista en el Artículo 11 de esta Ley; con independencia de las sanciones administrativas y penales que, en los términos de las leyes en dichas materias, resulten aplicables.\nPárrafo Reformado\nLey de Fiscalización y Rendición de Cuentas del Estado de Baja California y sus Municipios. Página 10 administrativas.\nPárrafo Adicionado\nArtículo Reformado\nArtículo 18.- La Auditoría Superior del Estado podrá auditar los conceptos reportados trimestralmente en el correspondiente Informe de Avance de Gestión Financiera como procesos concluidos, así como la parte ejecutada de los procesos no concluidos. Para el efecto, la Auditoría Superior del Estado, realizará reuniones con las Entidades Fiscalizadas para la revisión de los resultados de la cuenta pública en los términos de esta Ley.\nPárrafo Reformado\nEn lo procedente, los resultados de la fiscalización a que se refiere el presente artículo deberán incorporarse a los Informes Individuales derivado de la fiscalización de la\nCuenta Pública del ejercicio de que se trate.\nLa Auditoría Superior del Estado deberá informar a la Comisión de los hallazgos y resoluciones del caso, cuando así lo juzgue pertinente.\nPara los efectos de lo señalado anteriormente, la Auditoría Superior del Estado podrá realizar visitas, inspecciones y auditorías a las Entidades Fiscalizadas, durante el ejercicio fiscal en curso, mediante orden debidamente fundada y motivada, emitida por el Auditor\nSuperior del Estado y conforme a lo establecido en el artículo 38 de la presente Ley.\nArtículo Reformado\nCAPÍTULO II\nDe la Fiscalización de la Cuenta Pública\nArtículo 19.- La Cuenta Pública se integrará en términos de lo dispuesto en la Ley\nGeneral de Contabilidad Gubernamental, Ley de Presupuesto y Ejercicio del Gasto Público del Estado de Baja California, y demás disposiciones aplicables en la materia, y deberá presentarse de forma impresa y en dispositivos electrónicos de almacenamiento de datos de uso común o a través de medios electrónicos, al Congreso a más tardar el 30 de abril del año siguiente del ejercicio fiscal correspondiente.\nPárrafo Reformado\nContabilidad Gubernamental, Ley de Presupuesto y Ejercicio del Gasto Público del Estado de Baja California, y demás disposiciones aplicables en la materia, se aplicará la multa prevista en el Artículo 11 de esta Ley.\nPárrafo Adicionado, recorriéndose los subsecuentes\nAdicionalmente, la persona Titular de la Secretaría de Hacienda del Estado y las\nTesorerías Municipales, respectivamente, deberán integrar y enviar al Congreso la Cuenta\nLey de Fiscalización y Rendición de Cuentas del Estado de Baja California y sus Municipios. Página 11\nPública consolidada, correspondiente al ejercicio fiscal anterior, de conformidad con las reglas que emita el Consejo Nacional de Armonización Contable.\nPárrafo Reformado\nPara efectos de lo dispuesto en el párrafo anterior de este artículo, las Entidades\nParaestatales, los Órganos Constitucionales Autónomos y los Poderes del Estado, deberán entregar a la Secretaría de Hacienda del Estado, y las Entidades Paramunicipales a las\nTesorerías Municipales, a más tardar en el mes de marzo, la información y documentación que deban presentar en su respectiva Cuenta Pública.\nPárrafo Reformado\nLa Secretaría de Hacienda del Estado y las Tesorerías Municipales, respectivamente, podrán emitir reglas o criterios a las que se sujetarán los Entes Públicos, para cumplir con la consolidación de la Cuenta Pública.\nPárrafo Reformado\nArtículo Reformado\nArtículo 19 BIS.- Cuando no se presente la Cuenta Pública de la Entidad Fiscalizada en los plazos descritos en el artículo anterior, el Congreso del Estado, través de la\nPresidencia de la Comisión, instruirá a la Auditoría Superior del Estado, requerir su entrega en un término de tres días hábiles siguientes a la fecha de notificación del oficio de requerimiento, de no presentarse en este plazo, se aplicará la multa prevista en el Artículo\n11 de esta Ley; con independencia de las sanciones administrativas y penales que, en los términos de las leyes en dichas materias, resulten aplicables.\nSólo se podrá ampliar el plazo de presentación de la Cuenta Pública, en un término que no deberá exceder de quince días naturales, cuando medie solicitud previa al vencimiento del plazo de presentación, por parte de la persona titula del Poder Ejecutivo del\nEstado, las Presidencias Municipales y personas Titulares de los Órganos\nConstitucionalmente Autónomos, misma que deberá estar suficientemente justificada a juicio del Congreso, quien a través de la Presidencia de la Comisión emitirá la respuesta y el plazo que, en su caso, considere pertinente otorgar.\nEn este supuesto, la Auditoría Superior del Estado contará, con el mismo tiempo adicional para presentar el Informe Individual correspondiente.\nUna vez concluido el plazo otorgado por la Comisión, si la persona titular de la\nEntidad Fiscalizada no remitió la Cuenta Pública correspondiente, se aplicará la multa prevista en el Artículo 11 de esta Ley; con independencia de las sanciones administrativas y penales que, en los términos de las leyes en dichas materias, resulten aplicables. administrativas.\nLey de Fiscalización y Rendición de Cuentas del Estado de Baja California y sus Municipios. Página 12 fiscalización superior, si la Cuenta Pública no está integrada y disponible en los plazos y requisitos señalados.\nArtículo Adicionado\nArtículo 20.- La Fiscalización Superior tiene por objeto:\nI. Evaluar los resultados de la gestión financiera, conforme al artículo 21 de la presente Ley;\nII. Verificar el cumplimiento de los objetivos contenidos en los Programas, debiendo considerar:\na) Realizar auditorías del desempeño de los Programas, verificando la eficiencia, la eficacia y la economía en el cumplimiento de los objetivos de los mismos;\nb) Si se cumplieron las metas de los indicadores aprobados en el Presupuesto de\nEgresos, y si dicho cumplimiento tiene relación con el Plan Estatal de Desarrollo, los Planes\nMunicipales de Desarrollo respectivos y los programas sectoriales correspondientes; y,\nc) Si se cumplieron los objetivos de los Programas y las metas de gasto que promuevan la Perspectiva de Género.\nFracción Reformada\nInciso Reformado\nIII. Promover las acciones o denuncias correspondientes para la imposición de las sanciones administrativas y penales por las faltas graves que se adviertan derivado de sus auditorías e investigaciones, así como dar vista a las autoridades competentes, cuando detecte la probable comisión de faltas administrativas no graves, para que inicien, o en su caso, continúen la investigación respectiva y promuevan la imposición de las sanciones que procedan; y,\nFracción Reformada\nIV. Las demás que formen parte de la fiscalización de la Cuenta Pública o de la revisión del cumplimiento de los objetivos de los Programas establecidos.\nArtículo Reformado\nArtículo 21.- La evaluación de los resultados de la gestión financiera comprenderá:\nI. La ejecución de la Ley de Ingresos y el ejercicio del Presupuesto de Egresos, para verificar la forma y términos en que los ingresos fueron recaudados, obtenidos, captados y administrados; así como constatar que los recursos provenientes de financiamientos y obligaciones se contrataron, recibieron y aplicaron de conformidad con lo aprobado; y revisar que los egresos se ejercieron en los conceptos y partidas autorizadas, incluidos entre otros aspectos, la contratación de servicios y obra pública, las adquisiciones, arrendamientos, subsidios, aportaciones, donativos, transferencias, aportaciones a fondos, fideicomisos y\nLey de Fiscalización y Rendición de Cuentas del Estado de Baja California y sus Municipios. Página 13 demás instrumentos financieros, así como cualquier esquema o instrumento de pago a largo plazo;\nII. Si se cumplió con las disposiciones jurídicas aplicables en materia de sistemas de registro y contabilidad gubernamental; contratación de servicios, obra pública, adquisiciones, arrendamientos, conservación, uso, destino, afectación, enajenación y baja de bienes muebles e inmuebles; almacenes y demás activos; recursos materiales y demás normatividad aplicable al ejercicio del gasto público;\nIII. Si la captación, recaudación, administración, custodia, manejo, ejercicio y aplicación de recursos estatales y/o municipales, incluyendo subsidios, transferencias y donativos, y si los actos, contratos, convenios, mandatos, fondos, fideicomisos, prestación de servicios públicos, operaciones o cualquier acto que las entidades fiscalizadas, celebren o realicen, relacionados con el ejercicio del gasto público, se ajustaron a la legalidad, y si no han causado daños o perjuicios, o ambos, en contra de la hacienda pública o, en su caso, del patrimonio de los Entes Públicos;\nIV. Comprobar si el ejercicio de la Ley de Ingresos y el Presupuesto de Egresos, se han ajustado a los criterios señalados en los mismos y a su vez verificar:\na) Si las cantidades correspondientes a los ingresos y a los egresos, se ajustaron o corresponden a los conceptos y a las partidas respectivas;\nb) Si los Programas y su ejecución se ajustaron a los términos y montos aprobados en el Presupuesto de Egresos; y,\nc) Si los recursos provenientes de financiamientos y obligaciones se obtuvieron en los términos autorizados y se aplicaron con la periodicidad y forma establecida por las leyes y demás disposiciones aplicables, y si se cumplieron los compromisos adquiridos en los actos respectivos.\nArtículo 22.- Las observaciones que, en su caso, emita la Auditoría Superior del\nEstado, derivado de la Fiscalización Superior, podrán derivar en:\nI. Acciones: Solicitudes de aclaración, pliegos de observaciones, informes de presunta responsabilidad administrativa, promociones del ejercicio de la facultad de comprobación fiscal, promociones de responsabilidad administrativa sancionatoria, denuncias de hechos ante la Fiscalía Especializada y denuncias de juicio político; y,\nFracción Reformada\nII. Recomendaciones.\nArtículo Reformado\nArtículo 23.- La Mesa Directiva del Congreso turnará, a más tardar en dos días hábiles contados a partir de su recepción, los Informes de Avance de Gestión y la Cuenta\nLey de Fiscalización y Rendición de Cuentas del Estado de Baja California y sus Municipios. Página 14\nPública a la Comisión. Esta Comisión tendrá el mismo plazo para turnarlos a la Auditoría\nSuperior del Estado.\nArtículo 24.- Para la fiscalización de la Cuenta Pública, la Auditoría Superior del\nEstado tendrá las atribuciones siguientes:\nI. Realizar conforme al programa anual de auditorías aprobado, las auditorías e investigaciones. Para la práctica de auditorías, la Auditoría Superior del Estado podrá solicitar información y documentación durante el desarrollo de las mismas.\nCon independencia de la entrega de los Informes de Avance de Gestión Financiera y su fiscalización, que establece el Capítulo I del presente Título, la Auditoría Superior del\nEstado podrá iniciar el proceso de Fiscalización a partir del primer día hábil del ejercicio fiscal siguiente, sin perjuicio de que las observaciones o recomendaciones que, en su caso realice, deberán referirse a la información definitiva presentada en la Cuenta Pública. Una vez que le sea entregada la Cuenta Pública, podrá realizar las modificaciones al programa anual de las auditorías que se requieran y lo hará del conocimiento de la Comisión;\nII. Establecer los lineamientos técnicos y criterios para las auditorías y su seguimiento, procedimientos, investigaciones, encuestas, métodos y sistemas necesarios para la fiscalización superior;\nIII. Fiscalizar los subsidios y subvenciones que otorgue el Gobierno del Estado y los\nMunicipios, cualesquiera que sean sus fines y destino, así como verificar su aplicación al objeto autorizado;\nIV. Proponer a las instancias correspondientes, en los términos de la Ley General de\nContabilidad Gubernamental y demás legislación aplicable, las modificaciones a los principios, normas, procedimientos, métodos y sistemas de registro y contabilidad; las disposiciones para el archivo, guarda y custodia de los libros y documentos justificativos y comprobatorios del ingreso, gasto, financiamientos y obligaciones; así como todos aquellos elementos que posibiliten la adecuada rendición de cuentas y la práctica idónea de las auditorías;\nV. Practicar auditorías sobre el desempeño en el cumplimiento de los objetivos contenidos en los Programas, conforme a los indicadores establecidos en el Presupuesto de\nEgresos y tomando en cuenta el Plan Estatal de Desarrollo, los planes Municipales de\nDesarrollo, los programas sectoriales, los Programas Operativos Anuales, y demás\nProgramas de las entidades fiscalizadas, entre otros, a efecto de verificar el desempeño de los mismos y, en su caso, el uso de recursos públicos;\nV BIS. Practicar auditorías forenses que tengan por objeto la revisión de los procesos, irregularidad o conducta ilícita, documentando con pruebas válidas y suficientes las conclusiones derivadas de los hallazgos e irregularidades detectadas, apoyándose con la\nLey de Fiscalización y Rendición de Cuentas del Estado de Baja California y sus Municipios. Página 15 presente fracción.\nFracción Adicionada\nVI. Verificar que las Entidades Fiscalizadas que hubieren captado, recaudado, custodiado, manejado, administrado, aplicado o ejercido recursos públicos, lo hayan realizado conforme a los Programas aprobados y montos autorizados, así como en el caso de los egresos, con cargo a las partidas correspondientes; además, con apego a las disposiciones legales, reglamentarias y administrativas aplicables;\nVII. Verificar que las operaciones que realicen las Entidades Fiscalizadas sean acordes con la Ley de Ingresos y el Presupuesto de Egresos que les corresponda, y se efectúen con apego a las disposiciones correspondientes de la legislación fiscal, la legislación en materia de financiamientos y obligaciones; la Ley de Hacienda del Estado, la\nLey de Presupuesto y Ejercicio del Gasto Público; la Ley Orgánica de la Administración\nPública, todas del Estado de Baja California; así como, en su caso, la Ley del Régimen\nMunicipal, la Ley de Hacienda Municipal y demás leyes correspondientes a los Municipios del Estado, así como las demás disposiciones legales, reglamentarias y administrativas aplicables a estas materias;\nVIII. Verificar obras, bienes adquiridos, arrendamientos y servicios contratados por las\nEntidades Fiscalizadas para comprobar si los recursos de las inversiones y los gastos autorizados a éstas se ejercieron en los términos de las disposiciones legales aplicables;\nIX. Requerir a los auditores externos de las Entidades Fiscalizadas copia de todos los informes y dictámenes de las auditorías y revisiones por ellos practicadas a las Entidades\nFiscalizadas y de ser necesario, el soporte documental;\nX. Requerir a terceros que hubieran contratado con las Entidades Fiscalizadas obra pública, bienes, arrendamientos o servicios mediante cualquier título legal y a cualquier entidad o persona física o moral, pública o privada, o aquellas que hayan sido subcontratados por terceros, la información relacionada con la documentación justificativa y comprobatoria del ejercicio de recursos públicos a efecto de realizar las compulsas correspondientes;\nXI. Requerir, en su caso, a terceros, sean personas físicas o morales, públicas o privadas, que hubieran contratado bienes o servicios mediante cualquier título legal con las\nEntidades Fiscalizadas, la información relacionada con la documentación justificativa y comprobatoria de la Cuenta Pública respectiva, a efecto de realizar las compulsas correspondientes;\nXII. Requerir la presencia de particulares, sean personas físicas o morales, a quienes se les hubiere concedido recursos públicos por concepto de subsidios, asignaciones, concesiones, participaciones, donativos, convenios o contratos;\nLey de Fiscalización y Rendición de Cuentas del Estado de Baja California y sus Municipios. Página 16\nXIII. Solicitar a las Entidades Fiscalizadas, la remisión de la documentación e sus funciones, atendiendo a las disposiciones legales aplicables;\nXIV. Solicitar, obtener y tener acceso a toda la información y documentación, a través de medios físicos o electrónicos mediante herramientas tecnológicas, que, a juicio de la\nAuditoría Superior del Estado, sea necesaria para llevar a cabo la auditoría correspondiente, sin importar el carácter de confidencial o reservado de la misma, que obren en poder de:\nPárrafo Reformado\na) Las Entidades Fiscalizadas;\nb) Los Órganos Internos de Control;\nc) Los auditores externos de las Entidades Fiscalizadas;\nd) Instituciones de crédito, fideicomisos u otras figuras del sector financiero; y,\ne) Autoridades hacendarias federales, estatales y municipales.\nLa Auditoría Superior del Estado tendrá acceso a la información que las disposiciones legales consideren como de carácter reservado o confidencial cuando esté relacionada directamente con la captación, recaudación, administración, manejo, custodia, ejercicio, aplicación de los ingresos y egresos de recursos públicos y de los financiamientos y obligaciones, estando obligada a mantener la misma reserva, en términos de las disposiciones aplicables. Dicha información solamente podrá ser solicitada en los términos de las disposiciones aplicables, de manera indelegable por el Titular de la Auditoría Superior del Estado, subauditor general y auditor especial de fiscalización, a que se refiere esta Ley.\nCuando derivado de la práctica de auditorías se entregue a la Auditoría Superior del\nEstado información de carácter reservado o confidencial, ésta deberá garantizar que no se incorpore en los resultados, observaciones, recomendaciones y acciones de los informes de auditoría respectivos, información o datos que tengan esta característica en términos de la legislación aplicable. Dicha información será conservada por la Auditoría Superior del Estado en sus documentos de trabajo, y sólo podrá ser revelada a la autoridad competente, en términos de las disposiciones aplicables. responsabilidades administrativas y penales establecidas en las leyes correspondientes;\nFracción Reformada\nXV. Fiscalizar los recursos públicos locales que se hayan otorgado al Estado, municipios, fideicomisos, fondos, mandatos o, cualquier otra figura análoga, personas físicas o morales, públicas o privadas, cualesquiera que sean sus fines y destino, así como verificar su aplicación al objeto autorizado;\nLey de Fiscalización y Rendición de Cuentas del Estado de Baja California y sus Municipios. Página 17\nXVI. Investigar, en el ámbito de su competencia, los actos u omisiones que impliquen alguna irregularidad o presunta conducta ilícita, o comisión de faltas administrativas, en los términos establecidos en la Constitución, esta Ley, y en la legislación aplicable en materia de responsabilidades administrativa;\nXVII. Efectuar visitas domiciliarias, para exigir la exhibición de los libros, papeles, contratos, convenios, nombramientos, dispositivos magnéticos o electrónicos de almacenamiento de información, documentos y archivos indispensables para la realización de sus investigaciones, sujetándose a lo establecido en la presente Ley, así como realizar entrevistas y reuniones con particulares o con los servidores públicos de las Entidades\nFiscalizadas, necesarias para conocer directamente el ejercicio de sus funciones;\nXVIII. Formular recomendaciones, solicitudes de aclaración, pliegos de observaciones, promociones del ejercicio de la facultad de comprobación fiscal, promociones de responsabilidad administrativa sancionatoria, informes de presunta responsabilidad administrativa, denuncias de hechos y denuncias de juicio político;\nXIX. Promover las responsabilidades administrativas, por conducto de la Unidad\nAdministrativa a cargo de las investigaciones de la Auditoría Superior del Estado, la cual presentará el informe de presunta responsabilidad administrativa correspondiente, ante la\nUnidad Administrativa substanciadora de la misma Auditoría Superior del Estado, para que de considerarlo procedente, se turne y presente el expediente, ante el Tribunal o, en el caso de las no graves, ante el Órgano Interno de Control respectivo.\nCuando detecte posibles responsabilidades no graves dará vista a los Órganos\nInternos de Control competentes, para que continúen la investigación respectiva y, en su caso, promuevan la imposición de las sanciones que procedan, en los términos de las disposiciones aplicables en materia de responsabilidades administrativa;\nXX. Promover y dar seguimiento ante las autoridades competentes para la imposición de las sanciones que correspondan a los servidores públicos, tanto del Estado, como de los municipios y los particulares, en los términos previstos en el Título Cuarto de la Constitución\nPolítica de los Estados Unidos Mexicanos, el Título Octavo de la Constitución y demás disposiciones aplicables en la materia; asimismo presentar en su caso las denuncias y querellas penales correspondientes;\nXXI. Recurrir, a través de la Unidad competente, las determinaciones del Tribunal y de la Fiscalía Especializada, en términos de las disposiciones legales aplicables;\nXXII. Conocer y resolver sobre el recurso de reconsideración que se interponga en contra de las multas que imponga;\nXXIII. Participar en el sistema nacional y estatal anticorrupción, en los términos previstos en la Constitución Política de los Estados Unidos Mexicanos, la Constitución, Ley\nGeneral del Sistema Nacional Anticorrupción y las demás disposiciones en la materia, así\nLey de Fiscalización y Rendición de Cuentas del Estado de Baja California y sus Municipios. Página 18 con sus atribuciones y participar en foros estatales, nacionales e internacionales;\nXXIV. Desarrollar los trabajos de planeación de las auditorías, pudiendo solicitar a las entidades fiscalizadas información del ejercicio en curso, respecto de procesos concluidos y no concluidos; sin perjuicio de la revisión y fiscalización que la Auditoría Superior del Estado lleve a cabo conforme a lo contenido en la Fracción I, inciso b) del artículo 1 de esta Ley;\nXXV. Obtener durante el desarrollo de las auditorías e investigaciones copia de los documentos originales que se tengan a la vista, y certificarlas mediante cotejo con sus originales así como también poder solicitar la documentación en copias certificadas;\nXXVI. Expedir certificaciones de los documentos en los términos de la presente Ley, previo el pago de los derechos que establezca la Ley de Ingresos del Estado vigente en el ejercicio fiscal que corresponda;\nXXVII. Solicitar la comparecencia de las personas que se considere, en los casos concretos que así se determine;\nXXVIII. Comprobar la existencia, procedencia y registro de los activos y pasivos de las\nEntidades Fiscalizadas, de los fideicomisos, fondos y mandatos o cualquier otra figura análoga, para verificar la razonabilidad de las cifras mostradas en los estados financieros consolidados y particulares de la Cuenta Pública;\nXXIX. Fiscalizar el financiamiento público en los términos establecidos en esta Ley, así como en las demás disposiciones aplicables;\nXXX. Solicitar la información financiera, incluyendo los registros contables, presupuestarios, programáticos y económicos, así como los reportes institucionales y de los sistemas de contabilidad gubernamental que los Entes Públicos están obligados a operar con el propósito de consultar la información contenida en los mismos;\nXXXI. Establecer lineamientos o bases generales para la entrega-recepción de la\nFiscalizadas, con motivo de las auditorías que les sean practicadas;\nXXXII. Fiscalizar las cancelaciones, condonaciones o compensaciones de adeudos o de cualquier otro concepto análogo que concedan u otorguen las Entidades Fiscalizadas, verificando que se haya cumplido con la normatividad aplicable;\nXXXIII. Coadyuvar en la parte informativa y de capacitación a los contralores sociales de los Programas y acciones de desarrollo social, para el mejor cumplimiento de sus funciones; para el efecto realizará al menos dos encuentros anuales de carácter estatal en los que se les informe, capacite y proporcione documentación, instructivos, manuales y\nLey de Fiscalización y Rendición de Cuentas del Estado de Baja California y sus Municipios. Página 19 formatos, en los términos establecidos por la Ley de Desarrollo Social para el Estado de\nBaja California; y,\nXXXIV. Las demás que le sean conferidas por esta Ley o cualquier otro ordenamiento legal para la fiscalización de la Cuenta Pública.\nArtículo Reformado\nARTÍCULO 24 Bis.- Los procesos de fiscalización a que hace referencia esta Ley, podrán ser realizados por la Auditoría Superior del Estado de manera presencial o por medios electrónicos a través de las herramientas tecnológicas y de conformidad con sus\nReglas de carácter general.\nLa Auditoria Superior del Estado contará con un Buzón Digital, a través del cual, de manera enunciativa mas no limitativa realizará la notificación de solicitudes de información preliminar, órdenes de auditoría, e informes individuales que contengan acciones, previsiones o recomendaciones, así como, en su caso, cualquier acto que se emita, los cuales constarán en documentos digitales.\nPor su parte, las entidades fiscalizadas presentarán solicitudes o darán atención a requerimientos de información de la Auditoría Superior del Estado a través de documentos o archivos digitales certificados enviados a través del Buzón Digital o celebrarán los actos que se requieran dentro del proceso de fiscalización superior.\nLos procesos de fiscalización que se realicen a través de medios electrónicos mediante las herramientas tecnológicas constarán en expedientes electrónicos o digitales.\nArtículo Adicionado\nARTICULO 24 Ter.- Las disposiciones relativas a la auditoría presencial le serán aplicables en lo conducente a la auditoría realizada a través de medios digitales o electrónicos, sin perjuicio de que de manera particular se esté a lo siguiente:\nI. Previo al inicio de la auditoria por medios digitales la Auditoria Superior del Estado requerirá por escrito a la entidad fiscalizada, el nombre, cargo, registro federal de contribuyentes y correo o dirección electrónica del servidor público que fungirá como enlace o coordinador para la atención de la auditoria;\nII. Una vez recibida la información a que hace referencia la fracción anterior, la\nAuditoría Superior del Estado enviará por única ocasión, al correo o dirección electrónica designada, un aviso de confirmación que servirá para corroborar la autenticidad y correcto funcionamiento de este; lll. Los servidores públicos de la entidad fiscalizada que se encuentren autorizados electrónicos o digitales, y deberán consultarlo a más tardar dentro de los dos días hábiles\nEstado;\nLey de Fiscalización y Rendición de Cuentas del Estado de Baja California y sus Municipios. Página 20\nIV. Las notificaciones digitales, se tendrán por realizadas cuando se genere el acuse de recibo digital de notificación del acto de autoridad de que se trate, en el que se hará aplicables, que refleja la fecha y hora en que el servidor público de la entidad fiscalizada se autentico para abrir el documento a notificar o bien, se tuvo por notificado;\nV. Ante la falta de consulta de la notificación digital, esta se tendrá por realizada al tercer día hábil siguiente, contado a partir del día en que fue enviado el referido aviso.\nSerá responsabilidad de las entidades fiscalizadas mantener vigente la cuenta de correo electrónico señalada para efectos de notificación de los actos derivados de la auditoría por medios electrónicos o digitales;\nVI. En los documentos electrónicos o digitales, la firma electrónica avanzada amparada por un certificado vigente sustituirá a la firma autógrafa del firmante, garantizará la integridad del documento y producirá los mismos efectos que las leyes otorgan a los documentos con firma autógrafa, teniendo el mismo valor probatorio; y,\nVII. Cuando la Auditoría Superior del Estado por caso fortuito o fuerza mayor, se vea impedida para continuar con la auditoría por medios digitales o electrónicos, esta se suspenderá hasta que la causa desaparezca, lo cual se deberá publicar en la página de\nInternet de la Auditoria Superior· del Estado acompañada de la fundamentación y motivación correspondiente.\nEn caso de que la auditoría pueda ser continuada por la vía presencial, esta se cambiará de modalidad para cumplir con el mandato constitucional en tiempo y forma.\nEn el mismo sentido, el cambio de una auditoría presencial a una digital podrá realizarse en cualquier tiempo fundando y motivando debidamente la determinación.\nArtículo Adicionado\nArtículo 25.- La Auditoría Superior del Estado notificará por escrito a las Entidades\nFiscalizadas, los resultados con observaciones que derivan de la revisión de la Cuenta\nPública respectiva, a través de la Cédula de Resultados Finales y Observaciones\nPreliminares.\nPárrafo Reformado\nPreliminares, deberán entregar por escrito y en dispositivos electrónicos de almacenamiento de datos de uso común o en medios electrónicos, a la Auditoría Superior del Estado, las que derivan de la revisión de la Cuenta Pública.\nPárrafo Reformado\nLey de Fiscalización y Rendición de Cuentas del Estado de Baja California y sus Municipios. Página 21 párrafo anterior, traerá como consecuencia que la Auditoría Superior del Estado proceda a la emisión del Informe Individual respectivo.\nPárrafo Adicionado\nFinales a las Entidades Fiscalizadas el resultado de la revisión de la Cuenta Pública, de manera previa a la fecha de presentación de los Informes Individuales.\nPárrafo Adicionado\nSi la Auditoría Superior del Estado no encuentra observaciones, no se sujetará a lo previsto en los párrafos siguientes de este artículo.\nPárrafo Adicionado\nLa Auditoría Superior del Estado deberá analizar y valorar las justificaciones, aclaraciones y demás información y documentación presentada por las Entidades\nFiscalizadas, dentro de un término que no podrá exceder de quince días hábiles, salvo los casos debidamente justificados, hasta por un periodo igual, para determinar la procedencia de rectificar o ratificar los resultados con observaciones.\nPárrafo Adicionado\nLa Auditoría Superior del Estado citará por escrito, con por lo menos cinco días hábiles de anticipación, a las Entidades Fiscalizadas a la Reunión de Pre-cierre para dar a conocer el análisis en relación con la continuidad de los resultados con observaciones descritos en el párrafo que antecede, y cuando proceda, sobre posibles sugerencias de aclaración, todo ello contenido en la Cédula de Análisis de la Información presentada por la\nEntidad.\nPárrafo Adicionado\nA esta reunión deberá asistir la persona titular de la Entidad Fiscalizada, o bien la o las personas servidoras públicas que designe por escrito, quienes podrán acompañarse de quienes dejaren de serlo, siempre que guarden relación con la cuenta pública; la inasistencia no justificada de la Entidad Fiscalizada por quien legalmente la represente, constituirá la aceptación de la Cédula de Análisis de Información presentada por la Entidad; lo que traerá como consecuencia que se pierda el derecho de presentar cualquier información adicional\nInforme Individual; de esta reunión se levantará el acta correspondiente.\nPárrafo Adicionado hábiles contados a partir del día de la celebración de la misma, para presentar por escrito y electrónicos, a la Auditoría Superior del Estado, la información adicional que estime pertinente para la aclaración y justificación de las observaciones que persistan.\nPárrafo Adicionado\nLey de Fiscalización y Rendición de Cuentas del Estado de Baja California y sus Municipios. Página 22 para aclarar y justificar las observaciones que derivan de la revisión de la Cuenta Pública, el cual no será prorrogable bajo ninguna circunstancia.\nPárrafo Adicionado\nArtículo Reformado\nArtículo 26.- Una vez concluido el procedimiento previsto en el artículo 25 de esta\nLey, la Auditoría Superior del Estado, deberá analizar y valorar la información adicional presentada por la Entidad Fiscalizada para determinar, en un plazo que no deberá exceder de treinta días hábiles, las observaciones no aclaradas que deriven de la revisión de la\nCuenta Pública y la clasificación de las observaciones en acciones y recomendaciones, las cuales se darán a conocer mediante el pronunciamiento respectivo, previamente al Informe\nIndividual correspondiente.\nPárrafo Reformado\nLa Auditoría Superior del Estado citará por escrito, por lo menos con cinco días hábiles de anticipación, a la persona Titular de la Entidad Fiscalizada para que, por sí o por la o las personas servidoras públicas que designe por escrito, acuda a una reunión final donde le dará a conocer el pronunciamiento respectivo y se levantará el acta correspondiente. Ante la inasistencia no justificada de la Entidad Fiscalizada por quien legalmente la represente, se tendrá por notificada a la misma del pronunciamiento respectivo.\nPárrafo Reformado\nArtículo Reformado\nArtículo 26 BIS.- La Auditoría Superior del Estado podrá grabar en audio o video, cualquiera de las reuniones y audiencias previstas en esta Ley, previo consentimiento por escrito de la o las personas que participen o a solicitud de la Entidad Fiscalizada, para integrar el expediente electrónico correspondiente.\nArtículo Reformado\nArtículo 27.- La Auditoría Superior del Estado podrá solicitar y revisar, de manera casuística y concreta, información y documentación de ejercicios anteriores al de la Cuenta\nPública en revisión, sin que por este motivo se entienda, para todos los efectos legales, abierta nuevamente la Cuenta Pública del ejercicio al que pertenece la información solicitada, exclusivamente cuando el Programa, proyecto o la erogación, contenidos en el fiscales o se trate de auditorías sobre el desempeño.\nLas observaciones, incluyendo las acciones y recomendaciones que la Auditoría\nSuperior del Estado emita, sólo podrán referirse al ejercicio de los recursos públicos de la\nCuenta Pública en revisión. Lo anterior, sin perjuicio de que, de encontrar en la revisión que se practique presuntas responsabilidades a cargo de servidores públicos o particulares, correspondientes a otros ejercicios fiscales, se dará vista a la unidad administrativa a cargo de las investigaciones de la Auditoría Superior del Estado, para que proceda a formular las promociones de responsabilidades administrativas o las denuncias correspondientes.\nLey de Fiscalización y Rendición de Cuentas del Estado de Baja California y sus Municipios. Página 23\nArtículo 28.- La Auditoría Superior del Estado tendrá acceso a contratos, convenios, documentos, datos, libros, archivos y documentación justificativa y comprobatoria relativa al ingreso, gasto público y cumplimiento de los objetivos de los Programas de los Entes\nPúblicos, así como a la demás información que resulte necesaria para la revisión y fiscalización de la Cuenta Pública.\nArtículo 29.- Cuando conforme a esta Ley o las demás Leyes correspondientes, los\nÓrganos Internos de Control deban colaborar con la Auditoría Superior del Estado en lo que concierne a la revisión de la Cuenta Pública, deberá establecerse una coordinación entre ambos a fin de garantizar el debido intercambio de información que al efecto se requiera, y otorgar las facilidades que permitan a los auditores llevar a cabo el ejercicio de sus funciones. Asimismo, deberán proporcionar la documentación que les solicite la Auditoría\nSuperior del Estado sobre los resultados de la fiscalización que realicen o cualquier otra que se les requiera, para realizar la auditoría correspondiente.\nPara efecto de lo dispuesto en este artículo, los Órganos Internos de Control de las\nEntidades Fiscalizadas deberán proporcionar a la Auditoría Superior del Estado, a más tardar dentro de los quince días naturales del mes de diciembre del ejercicio fiscal anterior al que corresponda, los programas mínimos de auditoría interna que fijen para las entidades o dependencias públicas de su ámbito de competencia. En caso de incumplimiento, la\nAuditoría Superior del Estado lo hará del conocimiento de la Comisión para que determine lo procedente.\nArtículo 30.- La información y datos que para el cumplimiento de lo previsto en los artículos 28 y 29 se proporcionen, estarán afectos exclusivamente al objeto de esta Ley.\nArtículo 31.- Durante sus actuaciones los comisionados o habilitados que hubieren intervenido en las revisiones, deberán levantar actas circunstanciadas en presencia de dos testigos, en las que harán constar hechos y omisiones que hubieren encontrado. Las actas, declaraciones, manifestaciones o hechos en ellas contenidos, harán prueba en términos de ley.\nArtículo 32.- Los servidores públicos de la Auditoría Superior del Estado deberán guardar estricta reserva sobre la información y documentos que con motivo del objeto de esta Ley conozcan, así como de sus actuaciones y observaciones.\nArtículo 33.- Las actuaciones dentro del procedimiento de fiscalización superior se practicarán en días y horas hábiles.\nSon días hábiles todos los del año, excepto los sábados, domingos y aquellos en que no hubiere labores en las oficinas de la Auditoría Superior del Estado, o los que se indiquen en los acuerdos expedidos por la persona Titular de la Auditoría Superior del Estado; los cuales los plazos que establece esta Ley.\nPárrafo Reformado\nLey de Fiscalización y Rendición de Cuentas del Estado de Baja California y sus Municipios. Página 24 horas.\nEn los casos, cuando hubiere causa justificada que lo exija, el Auditor Superior del\nEstado, con expresión de la misma, podrá habilitar los días y horas inhábiles para que se validez, señalando los que hayan de practicarse.\nDe presentarse situaciones por caso fortuito o fuerza mayor que imposibiliten el debido desarrollo y cumplimiento de las labores de la Auditoría Superior del Estado, quedarán en suspenso los plazos previstos en la presente Ley, hasta en tanto se reanuden las labores respectivas, mismo que no deberá exceder de treinta días naturales.\nPara efectos de lo anterior, el Auditor Superior del Estado dictará las medidas administrativas conducentes para hacerlo del conocimiento de la Comisión y de las\nEntidades Fiscalizadas, así como del aviso de reanudación de labores y cómputo de plazos.\nArtículo Reformado\nArtículo 34.- La Auditoría Superior del Estado será responsable subsidiario de los daños y perjuicios que en términos de este capítulo, causen los servidores públicos de la misma, sin perjuicio de que la Auditoría Superior del Estado promueva las acciones legales que correspondan en contra de los responsables.\nCAPÍTULO III\nDe las visitas, inspecciones y auditorías\nArtículo 35.- La Auditoría Superior del Estado podrá efectuar visitas, inspecciones y auditorías, revisar toda clase de libros, documentos, bodegas, almacenes, plantas industriales, laboratorios, oficinas, escritorios, cajas fuertes, vehículos y otros bienes muebles e inmuebles, inspeccionar obras y, en general, recabar todos los elementos de información y documentación que se consideren necesarios para la Fiscalización Superior.\nArtículo 36.- Las Entidades Fiscalizadas, sus titulares y sus servidores públicos están obligados a permitir la práctica de visitas, inspecciones y auditorías necesarias para la revisión de sus Cuentas Públicas y de los Informes de Avance de Gestión Financiera, así del Estado.\nIgual obligación tienen las instituciones públicas o privadas y los particulares, a concepto de subsidios, asignaciones, concesiones, participaciones, donativos, convenios o contratos.\nArtículo 37.- Las Entidades Fiscalizadas mantendrán en sus oficinas principales u otras correspondientes a disposición del personal designado para llevar a cabo las visitas, Ley de Fiscalización y Rendición de Cuentas del Estado de Baja California y sus Municipios. Página 25 inspecciones o auditorías, desde el momento de la iniciación de la visita, inspección o auditoría y hasta su terminación, los libros, registros y documentos comprobatorios y justificatorios de las operaciones realizadas, así como los Programas y subprogramas respectivos.\nArtículo 38.- Las visitas, inspecciones y auditorías ordenadas por la Auditoría Superior del Estado, para practicarse en el domicilio legal y demás instalaciones físicas de las\nEntidades Fiscalizadas, se sujetarán a lo siguiente:\nI. Se practicarán mediante orden de inicio escrita expedida por el Auditor Superior del\nEstado, en la que se expresará:\na) Nombre, denominación o razón social y el domicilio de la Entidad Fiscalizada;\nb) El nombre de las personas comisionadas que practicarán la visita, inspección o auditoría, los cuales podrán ser sustituidos, aumentados o reducidos en su número, en cualquier tiempo, en cuyo caso, se comunicará a la Entidad Fiscalizada la sustitución o aumento del personal designado para llevar a cabo las visitas, inspecciones o auditorías, los cuales para efectuar la revisión la podrán hacer conjunta o separadamente;\nc) La solicitud de poner a disposición del personal designado para llevar a cabo las visitas, inspecciones o auditorías, toda la información relativa a la Cuenta Pública del ejercicio fiscal de que se trate, tanto en las oficinas principales como en otras de la propia\nEntidad;\nd) El ejercicio fiscal al que se limitará la visita, inspección y auditoría; y,\ne) La solicitud de designar a los representantes de la Entidad Fiscalizada responsables de atender las diligencias de los visitadores, lo que deberá formalizar mediante escrito dirigido al Auditor Superior del Estado.\nII. Al iniciarse la visita, inspección o auditoría se entregará el oficio que contenga la orden, a la Entidad Fiscalizada por sí o a través de quien ostente la representación legal; en los casos en que tales personas no estuvieren presentes, se les dejará citatorio para que siguiente.\nEn caso de que no se atendiere el citatorio, los visitadores entregarán el oficio que contenga la orden, a la persona que se encuentre presente en el domicilio de la Entidad\nFiscalizada y con ella se iniciará y entenderá la visita, inspección o auditoría;\nIII. Al dar inicio a la visita, inspección o auditoría, el personal designado para llevar a cabo las visitas, inspecciones o auditorías que en ellas intervenga se deberá identificar ante la persona con quien se entienda la diligencia, levantándose el Acta de inicio correspondiente, requiriéndole para que designe dos testigos; si éstos no son designados o\nLey de Fiscalización y Rendición de Cuentas del Estado de Baja California y sus Municipios. Página 26 los designados no aceptan servir como tales, el personal comisionado para llevar a cabo las visitas, inspecciones o auditorías los designarán haciendo constar esta situación en el Acta que levanten, sin que esta circunstancia invalide el inicio de la orden y de los resultados de la visita, inspección o auditoría. donde se esté llevando a cabo la visita, inspección o auditoría, por ausentarse de él antes de que concluya la diligencia o por manifestar su voluntad de dejar de ser testigo, y en tales circunstancias la persona con la que se entienda la visita, inspección o auditoría deberá designar de inmediato otros y ante su negativa o impedimento de los designados, el personal comisionado podrán designar a quienes deban sustituirlos. La sustitución de los testigos no invalida los resultados de la visita, inspección o auditoría;\nIV. En caso de ser necesario el traslado del personal designado para llevar a cabo las visitas, inspecciones o auditorías a otro lugar en donde la Entidad Fiscalizada tenga oficinas, documentos o bienes, se hará constar este hecho en un acta, sin necesidad de una nueva orden del Auditor Superior del Estado, y,\nV.- Las Entidades Fiscalizadas estarán obligadas a proporcionar al personal designado para llevar a cabo las visitas, inspecciones o auditorías de la Auditoría Superior del Estado, un lugar adecuado para el desempeño de sus funciones y que garantice la confidencialidad y guarda de la información que les haya sido proporcionada.\nArtículo 39.- Las auditorías, visitas e inspecciones que se efectúen en los términos de esta Ley, se practicarán por el personal expresamente comisionado para el efecto por el titular de la Auditoría Superior del Estado.\nLos servidores públicos de la Auditoría Superior del Estado tendrán la obligación de abstenerse de conocer asuntos referidos a las Entidades Fiscalizadas en las que hubiesen prestado servicios, de cualquier índole o naturaleza, o con los que hubieran mantenido cualquier clase de relación contractual durante el periodo que abarque la revisión de que se trate, o en los casos en que tengan conflicto de interés en los términos previstos en la legislación aplicable en materia de responsabilidades administrativa.\nArtículo 40.- Las personas a que se refiere el artículo anterior tendrán el carácter de conferida. Para tal efecto, deberán presentar previamente el oficio de comisión respectivo e identificarse plenamente como personal actuante de dicha Auditoría.\nArtículo 41.- Las Entidades Fiscalizadas deberán proporcionar a la Auditoría Superior del Estado los medios y facilidades necesarios para el cumplimiento de sus atribuciones, posibilite la realización de sus actividades.\nLey de Fiscalización y Rendición de Cuentas del Estado de Baja California y sus Municipios. Página 27\nArtículo 42.- Durante el desarrollo de una visita, inspección o auditoría el personal expresamente comisionado o habilitado, a fin de asegurar los libros, registros o sistemas de contabilidad, documentos comprobatorios y justificatorios de las operaciones, correspondencia o bienes, podrán indistintamente, sellar o colocar marcas en dichos documentos, bienes o en muebles, archiveros u oficinas donde se encuentren, así como dejarlos en calidad de depósito al titular de la Entidad Fiscalizada o con quién se entienda la diligencia, previo inventario que al efecto formulen. En el caso de que algún documento que se encuentre en los muebles, archiveros u oficinas que se sellen, sea necesario para que el personal de la Entidad Fiscalizada realice sus actividades, se le permitirá extraerlo ante la presencia del personal comisionado, quiénes podrán sacar copia del mismo.\nArtículo 43.- Los dictámenes que emitan los profesionales externos contratados por las Entidades Fiscalizadas, con apego a los lineamientos indicados por el Órgano Interno de\nControl correspondiente, podrán emplearse para motivar la emisión de los Informes\nIndividuales y en su caso del Informe General respectivo, cuando así se considere conveniente a juicio de la Auditoría Superior del Estado.\nCAPÍTULO IV\nDel contenido del Informe General y su análisis\nArtículo 44.- La Auditoría Superior del Estado tendrá un plazo de hasta 30 días hábiles posteriores al plazo a que se refiere el primer párrafo del artículo 46 de la presente\nLey, para rendir el Informe General correspondiente al Congreso, por conducto de la\nComisión, mismo que tendrá carácter público.\nPárrafo Reformado\nEn aquellos casos en que a la Auditoría Superior del Estado no le fuere suficiente el plazo señalado en el párrafo que antecede, podrá solicitar a la Comisión una prórroga no mayor a treinta días naturales, para concluir la entrega del Informe General en cita, expresando los razonamientos que funden y motiven su petición.\nEl Congreso del Estado remitirá copia del Informe General al Comité Coordinador y al\nComité de Participación Ciudadana, del sistema estatal anticorrupción.\nA solicitud de la Comisión, el Auditor Superior del Estado y los servidores públicos que éste designe presentarán, ampliarán o aclararán el contenido del Informe General, en del mismo, siempre y cuando no se revele información reservada o que forme parte de un proceso de investigación. Lo anterior, sin que se entienda para todos los efectos legales como una modificación al Informe General.\nArtículo Reformado\nArtículo 45.- El Informe General contendrá como mínimo:\nI. Un resumen de las auditorías realizadas y las observaciones realizadas;\nLey de Fiscalización y Rendición de Cuentas del Estado de Baja California y sus Municipios. Página 28\nII. Las áreas claves con riesgo identificadas en la fiscalización;\nIII. Un resumen de los resultados de la fiscalización del gasto público, y la evaluación de los financiamientos y obligaciones fiscalizados;\nIV. La descripción de la muestra del gasto público auditado, señalando:\na) En el caso de la Cuenta Pública del Estado la proporción respecto del ejercicio de los Poderes del Estado, la Administración Pública Estatal y Paraestatal, así como el gasto público ejercido por Órganos Constitucionales Autónomos; y,\nb) Tratándose de las Cuentas Públicas Municipales, la proporción respecto del ejercicio de los Ayuntamientos, sus dependencias y entidades paramunicipales.\nV. Derivado de las Auditorías, en su caso y dependiendo de la relevancia de las observaciones, un apartado donde se incluyan sugerencias al Congreso, para modificar disposiciones legales a fin de mejorar la gestión financiera y el desempeño de las entidades fiscalizadas; y,\nVI. La demás información que se considere necesaria.\nCAPÍTULO V\nDe los Informes Individuales\nArtículo 46.- La Auditoría Superior del Estado entregará los Informes Individuales de auditoría al Congreso, por conducto de la Comisión, a más tardar en el mes de mayo del año siguiente a la presentación de la Cuenta Pública correspondiente.\nPárrafo Reformado\nLos Informes Individuales podrán presentarse en los meses de septiembre y noviembre siguientes a la presentación de la cuenta pública, y en mayo del año siguiente, sin que exceda del plazo previsto en el párrafo anterior.\nPárrafo Reformado\nLo anterior sin perjuicio de que se puedan presentar conforme se generen.\nEntidades Fiscalizadas al Comité Coordinador y al Comité de Participación Ciudadana, del\nSistema Estatal Anticorrupción.\nPárrafo Reformado\nArtículo Reformado\nArtículo 47.- Los Informes Individuales de auditoría contendrán como mínimo lo siguiente:\nI. Los criterios de selección, el objetivo, el alcance, los procedimientos de auditoría aplicados y el dictamen de la revisión;\nLey de Fiscalización y Rendición de Cuentas del Estado de Baja California y sus Municipios. Página 29\nII. Los nombres de los servidores públicos de la Auditoría Superior del Estado a cargo de realizar la auditoría;\nIII. El cumplimiento, en su caso, de la Ley General de Contabilidad Gubernamental y las disposiciones que de ella emanen, Ley de Disciplina Financiera de las Entidades\nFederativas y los Municipios, legislación local en materia de financiamientos y obligaciones, Ley de Ingresos, Presupuesto de Egresos, la Ley de Coordinación Fiscal del Estado de Baja\nCalifornia, y demás disposiciones legales aplicables;\nFracción Reformada\nIV. Los resultados de la fiscalización efectuada;\nV. Las observaciones, recomendaciones, acciones, con excepción de los informes de presunta responsabilidad administrativa, y en su caso denuncias de hechos; y,\nVI. Un apartado específico en cada una de las auditorías realizadas donde se incluyan una síntesis de las justificaciones y aclaraciones que, en su caso, las Entidades\nFiscalizadas hayan presentado en relación con los resultados y las observaciones que se les hayan hecho durante las revisiones.\nAsimismo, considerará en su caso, el cumplimiento de los objetivos de aquellos\nProgramas que promuevan la Perspectiva de Género, así como la erradicación de la violencia y cualquier forma de discriminación de género.\nPárrafo Reformado\nLos Informes Individuales a que hace referencia el presente capítulo tendrán el carácter de públicos, y se mantendrán en el portal institucional de internet de la Auditoría\nSuperior del Estado, en formatos abiertos conforme a lo establecido en la Ley de\nTransparencia y Acceso a la Información Pública para el Estado de Baja California.\nArtículo Reformado\nArtículo 48.- La Auditoría Superior del Estado dará cuenta a la Comisión en los\nInformes Individuales de las observaciones, recomendaciones y acciones y, en su caso, de la imposición de las multas respectivas, y demás acciones que deriven de los resultados de las auditorías practicadas.\nArtículo 49.- La Auditoría Superior del Estado informará al Congreso, por conducto de la Comisión, del estado que guarda la solventación de observaciones a las Entidades\nFiscalizadas, respecto a cada uno de los Informes Individuales que se deriven de las funciones de fiscalización.\nPara tal efecto, el reporte a que se refiere este artículo será semestral y deberá ser presentado a más tardar los días primero de los meses de mayo y noviembre de cada año, con los datos disponibles al cierre del primer y tercer trimestres del año, respectivamente.\nLey de Fiscalización y Rendición de Cuentas del Estado de Baja California y sus Municipios. Página 30\nPública o al patrimonio de los Entes Públicos, derivados de la fiscalización de la Cuenta\nPública y en un apartado especial, la atención a las recomendaciones, así como el estado administrativa promovidos en términos de la legislación aplicable en materia de responsabilidad administrativa y esta Ley. Asimismo deberá publicarse en el portal institucional de internet de la Auditoría Superior del Estado en la misma fecha en que sea presentado en formato de datos abiertos conforme a lo establecido en la Ley de\nTransparencia y Acceso a la Información Pública del Estado y se mantendrá de manera permanente en el portal institucional de internet.\nEn el informe, la Auditoría Superior del Estado dará a conocer el seguimiento específico de las promociones de los informes de presunta responsabilidad administrativa, a fin de identificar a la fecha del informe las estadísticas sobre dichas promociones identificando también las sanciones que al efecto hayan procedido.\nEn dicho informe se dará a conocer el número de pliegos de observaciones emitidos, su estatus procesal y las causas que los motivaron, así como el número de denuncias penales formuladas ante la Fiscalía Especializada o las autoridades competentes, la información actualizada sobre la situación que guardan las denuncias penales, las causas que las motivaron, las razones sobre su procedencia o improcedencia así como, en su caso, la pena impuesta.\nCapítulo VI\nDe las Acciones y Recomendaciones derivadas de la Fiscalización\nArtículo 50.- La persona Titular de la Auditoría Superior del Estado enviará a las\nEntidades Fiscalizadas, dentro de un plazo de diez días hábiles siguientes a que haya sido entregado al Congreso, a través de la Comisión, el Informe Individual que contenga las acciones y las recomendaciones que les correspondan.\nPárrafo Reformado\nCon la notificación del Informe Individual a las Entidades Fiscalizadas quedarán informe, salvo en los casos del informe de presunta responsabilidad administrativa y de las denuncias penales y de juicio político, los cuales se notificarán a los presuntos responsables en los términos de las leyes que rigen los procedimientos respectivos.\nArtículo Reformado\nArtículo 51.- La Auditoría Superior del Estado al promover o emitir las acciones a que se refiere esta Ley, observará lo siguiente:\nI. A través de las solicitudes de aclaración, requerirá a las Entidades Fiscalizadas que presenten información adicional para atender las observaciones que se hayan realizado;\nLey de Fiscalización y Rendición de Cuentas del Estado de Baja California y sus Municipios. Página 31\nII. Tratándose de los pliegos de observaciones, determinará en cantidad líquida los daños o perjuicios, o ambos a la Hacienda Pública o, en su caso, al patrimonio de los Entes\nPúblicos;\nIII. Mediante las promociones del ejercicio de la facultad de comprobación fiscal, detectado en el ejercicio de sus facultades de fiscalización;\nIV. A través del informe de presunta responsabilidad administrativa, la Auditoría\nSuperior del Estado promoverá en los términos de la legislación aplicable en materia de responsabilidades administrativa, la imposición de sanciones a los servidores públicos por las faltas administrativas graves que conozca derivado de sus auditorías, así como sanciones a los particulares vinculados con dichas faltas.\nEn caso de que la Auditoría Superior del Estado determine la existencia de daños o perjuicios, o ambos a la Hacienda Pública o al patrimonio de los Entes Públicos, que deriven de faltas administrativas no graves, procederá en los términos de la legislación aplicable en materia de responsabilidades administrativas;\nV. Por medio de las promociones de responsabilidad administrativa, dará vista a los\nÓrganos Internos de Control cuando detecte posibles responsabilidades administrativas no graves, para que inicien o continúen la investigación respectiva y, en su caso, inicien el procedimiento sancionador correspondiente en los términos de la legislación aplicable en materia de responsabilidades administrativas;\nFracción Reformada\nVI. Mediante las denuncias de hechos, hará del conocimiento de la Fiscalía\nEspecializada, la posible comisión de hechos delictivos, y\nVII. Por medio de la denuncia de juicio político, hará del conocimiento del Congreso la presunción de actos u omisiones de los servidores públicos a que se refieren los artículos 92 y 93 de la Constitución, legislación aplicable en materia de responsabilidades administrativas, que redunden en perjuicio de los intereses públicos fundamentales o de su buen despacho, a efecto de que se substancie el procedimiento y resuelva sobre la responsabilidad política correspondiente.\nArtículo Reformado\nArtículo 52.- En la reunión a que se refiere el artículo 26 de esta Ley, la Auditoría motivo a las recomendaciones que contendrá el Informe Individual. Las Entidades personal de las áreas auditoras correspondientes de la Auditoría Superior del Estado, las actas en las que consten los términos de las recomendaciones que, en su caso, sean acordadas, los mecanismos y plazos para su atención. La Auditoría Superior del Estado, Fiscalizadas, las cuales deberán ser atendidas por éstas.\nLey de Fiscalización y Rendición de Cuentas del Estado de Baja California y sus Municipios. Página 32\nArtículo Reformado\nArtículo 53.- La información, documentación o consideraciones aportadas por las reunión a que se refiere el artículo 26 de esta Ley, deberán precisar las mejoras realizadas y las acciones emprendidas. En caso contrario, deberán justificar la improcedencia de lo recomendado o las razones por los cuales no resulta factible su implementación.\nPárrafo Reformado\nLa falta de atención a las recomendaciones acordadas o emitidas, sin causa justificada, dará lugar a las responsabilidades administrativas correspondientes. La Auditoría\nSuperior del Estado podrá emitir las disposiciones que estime necesarias al respecto.\nPárrafo Reformado\nArtículo Reformado\nArtículo 54.- La Auditoría Superior del Estado, podrá promover, en cualquier momento en que cuente con los elementos necesarios, las acciones previstas en el artículo 51 de esta\nLey, a través de sus Unidades Administrativas competentes.\nArtículo Reformado\nCAPÍTULO VII\nDE LA CONCLUSIÓN DE LA REVISIÓN DE LA CUENTA PÚBLICA POR EL CONGRESO\nDEL ESTADO\nDenominación Modificada\nArtículo 55.- La Comisión realizará la revisión, análisis, evaluaciones y dictaminación de la Cuenta Pública de las Entidades Fiscalizadas con base en los Informes Individuales y en su caso en los Informes Específicos y el Informe General correspondiente.\nPárrafo Reformado\nEl análisis de la Comisión podrá incorporar aquellas sugerencias que juzgue conveniente y que haya hecho la Auditoría Superior del Estado, para modificar disposiciones legales que pretendan mejorar la gestión financiera y el desempeño de las entidades fiscalizadas.\nArtículo Reformado\nArtículo 56.- En aquellos casos en que la Comisión detecte errores en el Informe\nGeneral o bien, considere necesario aclarar o profundizar el contenido del mismo, podrá pertinentes, así como la comparecencia del Titular de la Auditoría Superior del Estado o de otros servidores públicos de la misma, las ocasiones que considere necesarias, a fin de realizar las aclaraciones correspondientes, sin que ello implique la reapertura del Informe\nGeneral.\nLa Comisión podrá formular recomendaciones a la Auditoría Superior del Estado, las cuales serán incluidas en las conclusiones sobre el Informe General.\nLey de Fiscalización y Rendición de Cuentas del Estado de Baja California y sus Municipios. Página 33\nArtículo 57.- La Comisión después de analizar y hacer las aclaraciones o las recomendaciones respectivas, someterá a votación del pleno el dictamen de Cuenta Pública correspondiente de conformidad con lo establecido en el artículo 22 de la Constitución.\nPárrafo Reformado sustentado en conclusiones técnicas del Informe Individual y en su caso, recuperando las discusiones técnicas realizadas en la Comisión, para ello acompañará a su dictamen, en un apartado de antecedentes, el análisis realizado por la Comisión.\nPárrafo Reformado\nLa dictaminación de la Cuenta Pública de la Entidad Fiscalizada, no modifica los\nInformes Individuales de Auditoria correspondientes, ni suspende las acciones promovidas por la Auditoría Superior del Estado, mismas que seguirán el procedimiento previsto en esta\nLey y demás aplicables.\nPárrafo Reformado\nArtículo Reformado\nArtículo 58.- El Congreso publicará en su portal institucional de Internet, los dictámenes a que se refiere este Capítulo, asimismo, remitirá al Poder Ejecutivo Estatal para su publicación en el Periódico Oficial del Estado, los resolutivos de dichos dictámenes dentro del plazo de quince días naturales contados a partir de la fecha de emisión de su dictamen.\nPárrafo Reformado\nLa Auditoría Superior del Estado deberá publicar los informes individuales referidos en el presente capítulo, en su portal institucional de Internet, dentro del plazo de tres días hábiles siguientes a que haya sido notificado a la Entidad Fiscalizada.\nPárrafo Reformado\nArtículo Reformado\nCAPÍTULO VIII\nDe la Fiscalización del Cumplimiento de la Ley de Disciplina Financiera de las\nEntidades Federativas y los Municipios\nArtículo 59.- La Auditoría Superior del Estado, respecto de las reglas presupuestarias y de ejercicio, y de la contratación de financiamientos y obligaciones previstas en el artículo\n117, Fracción VIII, de la Constitución Política de los Estados Unidos Mexicanos, en la Ley de disposiciones, reglamentos y criterios que de éstas deriven, así como en la legislación local en materia de financiamientos y obligaciones, fiscalizará:\nI. La observancia de las reglas de disciplina financiera;\nII. La contratación de los financiamientos y obligaciones de acuerdo con la autorización emitida por el Congreso o por las autoridades competentes, de conformidad con local en materia de financiamientos y obligaciones;\nLey de Fiscalización y Rendición de Cuentas del Estado de Baja California y sus Municipios. Página 34\nIII. La contratación de los financiamientos y obligaciones de acuerdo a las disposiciones aplicables;\nIV. El cumplimiento de inscribir y publicar la totalidad de sus financiamientos y obligaciones que procedan, en el registro público único establecido en la Ley de Disciplina\nFinanciera de las Entidades Federativas y los Municipios y el registro estatal que establezca la legislación local en materia de financiamientos y obligaciones;\nV. El destino y ejercicio de los recursos correspondientes a los financiamientos y obligaciones contratados que hayan realizado el Estado y los Municipios, y en su caso, las garantías otorgadas; y,\nVI. Los demás conceptos que establezcan las disposiciones aplicables.\nArtículo 60.- La Auditoría Superior del Estado, con motivo de la fiscalización de las cuentas públicas, podrá solicitar a las Entidades Fiscalizadas que hayan obtenido algún financiamiento u obligación, la información correspondiente a la autorización para su contratación, el proceso competitivo instrumentado para su contratación en las mejores condiciones de mercado, las condiciones jurídicas y financieras en que se hubiera contraído, el destino de los recursos obtenidos, el cumplimiento de las proyecciones económicas presentadas durante el trámite de autorización, el cumplimiento de las obligaciones adquiridas y demás que estime indispensable al respecto; formulando las observaciones que de ello se deriven, sin perjuicio de las demás responsabilidades a que hubiere lugar.\nTÍTULO TERCERO\nDe la Fiscalización del Gasto Federalizado\nCAPÍTULO ÚNICO\nDe la Fiscalización del Gasto Federalizado\nArtículo 61.- La Auditoría Superior del Estado, podrá llevar a cabo las auditorías sobre las participaciones federales a través de los mecanismos de coordinación que implemente la\nAuditoría Superior de la Federación, en términos de las disposiciones legales aplicables.\nArtículo 62.- Sin perjuicio de lo dispuesto en el artículo anterior, la Auditoría Superior disposiciones aplicables.\nTÍTULO CUARTO\nCAPÍTULO ÚNICO\nLey de Fiscalización y Rendición de Cuentas del Estado de Baja California y sus Municipios. Página 35\nArtículo 63.- En los términos previstos en el artículo 37 de la Constitución, cualquier persona podrá presentar denuncias fundadas cuando se presuma el manejo, aplicación o custodia irregular de recursos públicos, o de su desvío, en los supuestos previstos en esta\nLey, la Auditoría Superior del Estado, previa autorización de su Titular, podrá revisar la gestión financiera de las Entidades Fiscalizadas, durante el ejercicio fiscal en curso, así como respecto a ejercicios fiscales distintos al de la Cuenta Pública en revisión, sin que por este motivo se entienda, para todos los efectos legales, abierta nuevamente la Cuenta\nPública.\nLas denuncias podrán presentarse al Congreso, a la Comisión o directamente a la\nAuditoría Superior del Estado.\nArtículo 64.- Las denuncias que se presenten deberán estar fundadas con documentos y evidencias mediante los cuales se presuma el manejo, aplicación o custodia irregular de recursos públicos o de su desvío, en los supuestos establecidos en esta Ley.\nEl escrito de denuncia podrá presentarse de forma presencial o a través de medios electrónicos y deberá contar, como mínimo, con los siguientes elementos:\nPárrafo Reformado\nI. El ejercicio en que se presentaron los presuntos hechos irregulares; y,\nFracción Reformada\nII. Descripción de los presuntos hechos irregulares.\nAl escrito de denuncia deberán acompañarse los elementos de prueba, cuando sea posible, que se relacionen directamente con los hechos denunciados. La Auditoría Superior del Estado deberá proteger en todo momento la identidad del denunciante.\nArtículo Reformado\nArtículo 65.- Las denuncias deberán referirse a presuntos daños o perjuicios a la\nHacienda Pública o al patrimonio de los Entes Públicos, en algunos de los siguientes supuestos para su procedencia:\nI. Desvío de recursos hacia fines distintos a los autorizados;\nII. Irregularidades en la captación o en el manejo y utilización de los recursos públicos;\nIII. Actos presuntamente irregulares en la contratación y ejecución de obras, contratación y prestación de servicios públicos, adquisición de bienes, y otorgamiento de permisos, licencias y concesiones entre otros;\nIV. La comisión recurrente de irregularidades en el ejercicio de los recursos públicos; y, Ley de Fiscalización y Rendición de Cuentas del Estado de Baja California y sus Municipios. Página 36\nV. Inconsistencia en la información financiera o programática de cualquier entidad fiscalizada que oculte o pueda originar daños o perjuicios a su patrimonio. sobre la procedencia de iniciar la revisión correspondiente.\nEn el caso de las denuncias a través de medios electrónicos, la respuesta se realizará por el mismo medio de conformidad con las disposiciones aplicables.\nPárrafo Adicionado\nArtículo Reformado\nArtículo 66.- El Titular de la Auditoría Superior del Estado, con base en el dictamen técnico que al efecto emita la Unidad Administrativa competente autorizará, en su caso, la revisión de la gestión financiera correspondiente, ya sea del ejercicio fiscal en curso o de ejercicios anteriores a la Cuenta Pública en revisión.\nArtículo 67.- Las Entidades Fiscalizadas estarán obligadas a proporcionar la información que les solicite la Auditoría Superior del Estado.\nArtículo 68.- La Auditoría Superior del Estado tendrá las atribuciones señaladas en esta Ley para la realización de las auditorías a que se refiere este Capítulo.\nLa Auditoría Superior del Estado, deberá reportar en los informes correspondientes en los términos del artículo 49 de esta Ley, el estado que guarden las observaciones, detallando las acciones relativas a dichas auditorías, así como la relación que contenga la totalidad de denuncias recibidas.\nArtículo 69.- De la revisión efectuada al ejercicio fiscal en curso o a los ejercicios anteriores, la Auditoría Superior del Estado, rendirá un informe al Congreso, a más tardar a los treinta días hábiles posteriores a la conclusión de la auditoría. Asimismo, promoverá las acciones que, en su caso, correspondan para el fincamiento de las responsabilidades administrativas, penales y políticas a que haya lugar, ante el Tribunal, la Fiscalía\nEspecializada o las autoridades competentes conforme lo establecido en esta Ley y demás legislación aplicable.\nArtículo 70.- Lo dispuesto en el presente Capítulo, no excluye la imposición de las administrativa, ni de otras que se deriven de la revisión de la Cuenta Pública.\nTÍTULO QUINTO\nResponsabilidades\nCAPÍTULO I o al Patrimonio de los Entes Públicos\nLey de Fiscalización y Rendición de Cuentas del Estado de Baja California y sus Municipios. Página 37\nArtículo 71.- Si de la fiscalización, revisiones o investigaciones que realice la Auditoría responsabilidades a cargo de servidores públicos o particulares, ésta procederá a:\nI. Proponer las bases para la determinación de daños y perjuicios que afecten a la\nHacienda Pública Estatal o Municipal, o al Patrimonio de las Entes Públicos Estatales y\nMunicipales; así como para las indemnizaciones y sanciones pecuniarias correspondientes a los responsables, haciéndolo del conocimiento del Congreso quien procederá conforme a la\nLey;\nII. Promover ante el Tribunal, en los términos de la legislación en materia de responsabilidades administrativas, la imposición de sanciones a los servidores públicos por las faltas administrativas graves que detecte durante sus auditorías e investigaciones, en que incurran los servidores públicos, así como sanciones a los particulares vinculados con dichas faltas;\nIII. Dar vista a los Órganos Internos de Control competentes, cuando detecte posibles responsabilidades administrativas distintas a las mencionadas en la fracción anterior.\nEn caso de que la Auditoría Superior del Estado determine la existencia de daños o perjuicios, o ambos a la Hacienda Pública Estatal o Municipal, o al patrimonio de las\nEntidades Fiscalizadas, que deriven de faltas administrativas no graves, procederá en los términos de la legislación aplicable en materia de responsabilidades administrativas;\nIV. Presentar las denuncias y querellas penales, que correspondan ante la Fiscalía\nEspecializada, por los probables delitos que se detecten derivado de sus auditorías, revisiones o investigaciones;\nV. Coadyuvar con la Fiscalía Especializada en los procesos penales correspondientes, tanto en la etapa de investigación, como en la judicial. En estos casos, la\nFiscalía Especializada recabará previamente la opinión de la Auditoría Superior del Estado, respecto de las resoluciones que dicte sobre el no ejercicio o el desistimiento de la acción penal.\nPreviamente a que la Fiscalía Especializada determine declinar su competencia, abstenerse de investigar los hechos denunciados, archivar temporalmente las investigaciones o decretar el no ejercicio de la acción penal, deberá hacerlo del conocimiento de la Auditoría Superior del Estado, para que exponga las consideraciones que estime convenientes.\nLa Auditoría Superior del Estado, podrá impugnar ante la autoridad competente, las omisiones de la Fiscalía Especializada en la investigación de los delitos, así como las resoluciones que emita en materia de declinación de competencia, reserva, no ejercicio o desistimiento de la acción penal, o suspensión del procedimiento; y, Ley de Fiscalización y Rendición de Cuentas del Estado de Baja California y sus Municipios. Página 38\nVI. Presentar las denuncias de juicio político ante el Congreso que, en su caso, correspondan en términos de las disposiciones aplicables. político, deberán presentarse por parte de la Auditoría Superior del Estado cuando se cuente con los elementos que establezcan las leyes en dichas materias.\nLas resoluciones del Tribunal podrán ser recurridas por la Auditoría Superior del\nEstado, cuando lo considere pertinente, en términos de las disposiciones aplicables.\nArtículo 72.- La promoción del procedimiento a que se refiere la fracción II del artículo anterior, tiene por objeto resarcir el monto de los daños y perjuicios estimables en dinero que se hayan causado a la Hacienda Pública Estatal y Municipal o, en su caso, al patrimonio de las Entidades Fiscalizadas.\nLo anterior, sin perjuicio de las demás sanciones administrativas que, en su caso, el\nTribunal imponga a los responsables.\nLas sanciones que imponga el Tribunal se fincarán independientemente de las demás sanciones a que se refiere el artículo anterior que, en su caso, impongan las autoridades competentes.\nArtículo 73.- La Auditoría Superior del Estado, a través de la unidad administrativa competente a cargo de las investigaciones, promoverá el informe de presunta responsabilidad administrativa y, en su caso, penal a los servidores públicos de la Auditoría\nSuperior del Estado, cuando derivado de las auditorías, revisiones o investigaciones a cargo de ésta, no formulen las observaciones sobre las situaciones irregulares que detecten o violen la reserva de información en los casos previstos en esta Ley.\nArtículo 74.- Las responsabilidades que se finquen a los servidores públicos de las\nEntidades Fiscalizadas y de la Auditoría Superior del Estado, no eximen a éstos ni a los particulares, personas físicas o morales, de sus obligaciones, cuyo cumplimiento se les exigirá, aun cuando la responsabilidad se hubiere hecho efectiva total o parcialmente.\nArtículo 75.- La unidad administrativa de la Auditoría Superior del Estado, a cargo de las investigaciones, promoverá el informe de presunta responsabilidad administrativa ante la unidad de la propia Auditoría encargada de fungir como autoridad substanciadora, cuando los pliegos de observaciones no sean solventados por las entidades fiscalizadas.\nLo anterior, sin perjuicio de que la unidad administrativa a cargo de las investigaciones, podrá promover el informe de presunta responsabilidad administrativa, en cualquier momento en que cuente con los elementos necesarios.\nLey de Fiscalización y Rendición de Cuentas del Estado de Baja California y sus Municipios. Página 39 y la imposición de sanciones por parte del Tribunal, se regirá por lo dispuesto en la legislación aplicable en materia de responsabilidades administrativas.\nArtículo 76.- La unidad administrativa a cargo de la substanciación, deberá ser distinta de la unidad administrativa que se encargue de las labores de investigación.\nPara efectos de lo previsto en el párrafo anterior, el Reglamento Interior de la\nAuditoría Superior del Estado, deberá considerar, la existencia de la unidad administrativa de investigaciones, así como la unidad administrativa substanciadora.\nArtículo 77.- Los Órganos Internos de Control deberán informar a la Auditoría Superior del Estado, dentro de los treinta días hábiles siguientes de recibida la vista a que se refiere la fracción V del artículo 51 de esta Ley, el número de expediente con el que se inició la investigación o procedimiento respectivo.\nPárrafo Reformado\nAsimismo, los Órganos Internos de Control deberán informar a la Auditoría Superior del Estado de la resolución definitiva que se determine o recaiga a sus promociones, dentro de los diez días hábiles posteriores a que se notifique dicha resolución.\nLa falta de presentación, sin causa justificada, de la información señalada en este artículo, dará lugar a un requerimiento por parte de la Auditoría Superior del Estado para que, dentro de los cinco días hábiles siguientes al día de la notificación del requerimiento, el\nÓrgano Interno de Control presente la información solicitada, de lo contrario se aplicará la multa prevista en el artículo 11 de esta Ley.\nPárrafo Reformado\nArtículo Reformado\nArtículo 78.- La Auditoría Superior del Estado, en los términos de la Ley General del\nSistema Nacional Anticorrupción, y la legislación estatal en la materia, incluirá en la plataforma digital correspondiente, la información relativa a los servidores públicos y particulares sancionados por resolución definitiva firme, por la comisión de faltas administrativas graves o actos vinculados a éstas.\nCAPÍTULO II\nDel Recurso de Reconsideración\nArtículo 79.- La tramitación del recurso de reconsideración, en contra de las multas impuestas por la Auditoría Superior del Estado, se sujetará a las disposiciones siguientes:\nI. Se iniciará mediante escrito que deberá presentarse ante la Auditoría Superior del notificación de la multa, el cual contendrá lo siguiente:\nPárrafo de la Fracción Reformado\nLey de Fiscalización y Rendición de Cuentas del Estado de Baja California y sus Municipios. Página 40\na) La mención de la unidad administrativa que impuso la multa, el nombre y firma autógrafa o huella dactilar del recurrente, o en su caso de quien deba hacerlo en su nombre y representación, requisito sin el cual no se dará trámite al recurso;\nb) El domicilio que señala para oír y recibir notificaciones en el lugar de residencia de la Auditoría Superior del Estado;\nc) El monto de la multa que se recurre y la fecha en que se le notificó;\nd) La descripción de los hechos que son antecedentes de la multa que se impugna; y,\ne) Los agravios que le causan y los argumentos de derecho que se hagan valer en contra de la multa impugnada.\nAsimismo se acompañará el documento en que conste la multa que se impugna y de la constancia de notificación respectiva, así como los documentos que acrediten la personalidad del recurrente o en su caso, cuando actúe a nombre o en representación de otro o de persona jurídica, así como las pruebas documentales o de cualquier otro de carácter superveniente que ofrezca y que tengan relación inmediata y directa con la sanción recurrida y con los agravios expresados;\nFracción Reformada\nII. Cuando no se cumpla con alguno de los requisitos establecidos en este artículo para la presentación del recurso de reconsideración, o no se acompañe alguno de los documentos señalados en la fracción I del presente artículo, la Auditoría Superior del Estado prevendrá por una sola vez al recurrente para que, en un plazo de cinco días hábiles, subsane la irregularidad en que hubiere incurrido en su presentación;\nIII. La Auditoría Superior del Estado al emitir el acuerdo sobre la admisión de las pruebas documentales y supervenientes ofrecidas, desechará de plano las que no fueren ofrecidas conforme a derecho y las que sean contrarias a la moral o al derecho; y,\nIV. Desahogadas las pruebas, si las hubiere, la Auditoría Superior del Estado a través de la unidad administrativa competente, examinará todos y cada uno de los agravios hechos valer y las pruebas ofrecidas por el recurrente teniendo la facultad de invocar hechos notorios, pero cuando uno de los agravios sea suficiente para desvirtuar la validez de la multa recurrida, bastará con el examen de dicho agravio; posterior a ello, se declarará cerrada la instrucción, debiendo emitir resolución dentro de los sesenta días hábiles siguientes, a partir del cierre de la misma, notificando dicha resolución al recurrente dentro de los veinte días hábiles siguientes a su emisión. resolución respectiva, en este caso, la Auditoría Superior del Estado lo sobreseerá sin mayor trámite, ordenando el archivo total y definitivo del asunto respectivo.\nUna vez desahogada la prevención señalada por la Fracción II del presente artículo, la Auditoría Superior del Estado, en un plazo que no excederá de quince días hábiles, Ley de Fiscalización y Rendición de Cuentas del Estado de Baja California y sus Municipios. Página 41 acordará sobre la admisión o el desechamiento del recurso. En este último caso, cuando se ubique en alguno de los siguientes supuestos:\na) Se presente fuera del plazo señalado;\nb) El escrito de impugnación no contenga la firma autógrafa o huella dactilar del recurrente o de quien deba hacerlo en su nombre y representación;\nc) No acompañe cualquiera de los documentos a que se refiere la fracción I del presente artículo;\nd) La multa impugnada no afecte los intereses jurídicos del promovente;\ne) No se exprese agravio alguno; o,\nf) Se encuentra en trámite ante el Tribunal algún recurso o defensa legal o cualquier otro medio de defensa interpuesto por el promovente, en contra de la sanción recurrida.\nArtículo Reformado\nArtículo 80.- En tratándose de notificaciones y de pruebas, se seguirán y aplicarán las reglas establecidas en el Código de Procedimientos Civiles para el Estado de Baja\nCalifornia, y en lo no previsto por éste, lo que disponga el Código Fiscal del Estado de Baja\nCalifornia.\nArtículo 81.- La interposición del recurso suspenderá la ejecución de la multa recurrida, siempre y cuando el recurrente garantice en cualquiera de las formas establecidas por el Código Fiscal del Estado de Baja California el pago de la multa.\nArtículo 82.- La resolución que ponga fin al recurso tendrá por efecto confirmar, modificar o revocar la multa impugnada.\nContra la resolución que pronuncie la Auditoría Superior del Estado, no procederá recurso alguno.\nCAPÍTULO III\nDe la Prescripción de Responsabilidades\nArtículo 83.- La acción para fincar responsabilidades e imponer las sanciones por faltas administrativas graves prescribirá en siete años. de carácter continuo.\nEn todos los casos, la prescripción a que alude este precepto se interrumpirá en los administrativas.\nLey de Fiscalización y Rendición de Cuentas del Estado de Baja California y sus Municipios. Página 42\nArtículo 84.- Las responsabilidades distintas a las mencionadas en el artículo anterior, que resulten por actos u omisiones, prescribirán en la forma y tiempo que fijen las leyes aplicables.\nTÍTULO SEXTO\nCAPÍTULO ÚNICO\nDe la Comisión\nArtículo 85.- Para los efectos de lo dispuesto en la fracción XIII del artículo 27 de la\nConstitución, el Congreso contará con la Comisión que tendrá las atribuciones de coordinar las relaciones entre éste y la Auditoría Superior del Estado; evaluar el desempeño de esta última, conforme a los programas y disposiciones previstas para ello; constituir el enlace que permita garantizar la debida coordinación entre ambos órganos, y solicitarle que le informe sobre la evolución de sus trabajos de fiscalización, salvo las excepciones que las leyes prevean.\nArtículo 86.- Son atribuciones de la Comisión:\nI. Ser el conducto de comunicación entre el Congreso, y la Auditoría Superior del\nEstado;\nII. Recibir de la Mesa Directiva del Congreso, los Informes de Avance de Gestión\nFinanciera y las Cuentas Públicas de los Entes Públicos y turnarla a la Auditoría Superior del\nEstado para su revisión y fiscalización;\nIII. Presentar al Pleno del Congreso, los Dictámenes de las Cuentas Públicas de las\nEntidades Fiscalizadas, con base a los criterios vigentes para dictaminar las cuentas públicas de las Entidades Fiscalizadas y en su caso, los correspondientes a los Informes\nEspecíficos y General;\nFracción Reformada\nIV. Analizar el programa anual de auditorías de la Cuenta Pública y conocer el cumplimiento de sus funciones y atribuciones, elabore la Auditoría Superior del Estado, así como sus modificaciones, y evaluar su cumplimiento.\nCon respecto a los procedimientos, alcances, métodos, lineamientos y resoluciones omitan áreas relevantes de la Cuenta Pública;\nV. Citar por conducto de su presidente, al Titular de la Auditoría Superior del Estado, para conocer en lo específico de los Informes Individuales, y del Informe General;\nFracción Reformada\nLey de Fiscalización y Rendición de Cuentas del Estado de Baja California y sus Municipios. Página 43\nVI. Conocer y opinar sobre el proyecto de presupuesto anual de la Auditoría Superior fiscal, así como sus modificaciones presupuestales y analizar el informe anual de su ejercicio;\nVII. Evaluar el desempeño de la Auditoría Superior del Estado respecto al cumplimiento de su mandato, atribuciones y ejecución de las auditorías; proveer lo necesario para garantizar su autonomía técnica y de gestión, y requerir informes sobre la evolución de los trabajos de fiscalización.\nLa evaluación del desempeño tendrá por objeto conocer y valorar de forma objetiva si la Auditoría Superior del Estado cumple con las atribuciones que conforme a la Constitución y esta Ley le corresponden; el efecto o la consecuencia de la acción fiscalizadora en la gestión financiera y el desempeño de los Entes Públicos, en los resultados de los Programas y proyectos autorizados en el Presupuesto de Egresos, y en la administración de los recursos públicos que ejerzan;\nPárrafo Reformado\nDe dicha evaluación, la Comisión podrá proponer las políticas de organización y funcionamiento que deban regular a dicho Órgano en los términos establecidos en la normatividad estatal vigente;\nPárrafo Adicionado\nVIII. Proponer las bases y requisitos que deberá contener la convocatoria pública para la designación del titular de la Auditoría Superior del Estado;\nIX. Coadyuvar en su caso en la presentación al Congreso de las propuestas de los candidatos a ocupar el cargo de Titular de la Auditoría Superior del Estado, para lo cual consultará a las organizaciones civiles y asociaciones que estime pertinente, en términos de la Constitución y conforme lo establezcan las disposiciones legales;\nX. Presentar al Congreso la solicitud de remoción del titular de la Auditoría Superior del Estado, en términos del artículo 37 de la Constitución;\nXI. Conocer el Reglamento Interior de la Auditoría Superior del Estado y validar los proyectos de reforma, propuestos por su Titular, en los términos del artículo 66 de la Ley\nFracción Reformada\nXII. Analizar la información, en materia de fiscalización superior del Estado, de contabilidad y auditoría gubernamentales y de rendición de cuentas, y podrá solicitar la comparecencia de servidores públicos vinculados con los resultados de la fiscalización;\nXIII. Invitar a la sociedad civil organizada a que participe como observadores o testigos sociales en las sesiones de la Comisión, dejando constancia de ello;\nLey de Fiscalización y Rendición de Cuentas del Estado de Baja California y sus Municipios. Página 44\nXIV. Promover la realización de ejercicios de contraloría social en los que se articule a la población con las Entidades Fiscalizadas;\nXV. Citar a las personas titulares de las Entidades Fiscalizadas y de los Órganos observaciones de los dictámenes de cuenta pública;\nFracción Reformada\nXVI. Generar, modificar y ratificar los criterios para dictaminar las cuentas públicas de las entidades fiscalizadas, dentro de los primeros treinta días naturales siguientes a la instalación de la Comisión, con base a los principios de legalidad, definitividad, imparcialidad y confiabilidad; una vez aprobados se deberá gestionar su difusión y publicación en la\nGaceta Parlamentaria;\nFracción Adicionada\nXVII. Solicitar a la Unidad de Contraloría Interna del Congreso, el inicio de revisiones especiales a las áreas de la Auditoría Superior del Estado, para efectos de vigilancia y evaluación del desempeño; y,\nFracción Adicionada\nXVIII. Las demás que establezcan esta Ley y demás disposiciones legales aplicables.\nFracción Recorrida\nArtículo Reformado\nArtículo 87.- La Comisión presentará directamente a la Auditoría Superior del Estado un informe que contenga las observaciones y las recomendaciones que se deriven del ejercicio de las atribuciones que esta Ley le confiere en materia de evaluación de su desempeño a más tardar el último día hábil de agosto del año en que presente el Informe\nGeneral. La Auditoría Superior del Estado dará cuenta de su atención al presentar el Informe\nGeneral del ejercicio siguiente.\nTÍTULO SÉPTIMO\nDe la Auditoría Superior del Estado\nCAPÍTULO I\nIntegración y Organización\nArtículo 88.- Al frente de la Auditoría Superior del Estado, habrá un Titular que se denominará Auditor Superior del Estado de Baja California, que será designado conforme a lo previsto por el artículo 37 de la Constitución, por el voto de las dos terceras partes de los miembros del Congreso.\nArtículo 89.- La designación del Titular de la Auditoría Superior del Estado se sujetará al procedimiento siguiente:\nI. El Presidente de la Mesa Directiva del Congreso emitirá convocatoria pública a más\nLey de Fiscalización y Rendición de Cuentas del Estado de Baja California y sus Municipios. Página 45 designado el Auditor Superior del Estado, a efecto de recibir solicitudes de los interesados en ocupar el referido cargo;\nII. Las solicitudes de los interesados a los que se refiere la fracción anterior serán recibidas por la Comisión, durante un período de diez días naturales, contados a partir de la fecha de la publicación de la convocatoria correspondiente;\nIII. Concluido el plazo señalado en la fracción anterior y dentro de los tres días naturales siguientes, la Comisión procederá en sesión permanente a la revisión y análisis de las solicitudes recibidas para determinar el cumplimiento de los requisitos previstos en la\nConstitución y en esta Ley, desechando las solicitudes que no hayan satisfecho los mismos y seleccionando las que continuarán en el proceso de designación, hechos que se harán constar en el acta de la sesión respectiva;\nIV. La comisión competente procederá a entrevistar de manera individual a los candidatos seleccionados en un plazo de cinco días naturales contados a partir de la fecha en que haya concluido la sesión de selección a que se refiere la fracción anterior;\nV. Del resultado del análisis integral de cada solicitud y de las entrevistas realizadas, la Comisión seleccionará a un número no mayor de tres candidatos a ocupar el cargo de\nAuditor Superior del Estado y formulará la opinión correspondiente en la que señalará en orden de prelación de los integrantes de la terna. En caso de que la cantidad de seleccionados haya sido menor de tres por no cumplir con los requisitos de Ley, se hará constar tal hecho en la opinión respectiva;\nVI. La opinión a que se refiere la fracción anterior deberá ser remitida a la Junta de\nCoordinación Política, a efecto de que realice su revisión y propuesta ante el Pleno del\nCongreso;\nVII. Previa convocatoria en los términos de Ley y en un plazo que no deberá exceder de tres días naturales contados a partir de la recepción de la opinión a que se refiere la fracción anterior, la Junta de Coordinación Política presentará al Pleno del Congreso el acuerdo que contenga la propuesta correspondiente, para que éste proceda a la designación del Auditor Superior del Estado;\nVIII. En caso de que ninguno de los candidatos de la terna obtenga la votación requerida, el Presidente de la Mesa Directiva del Congreso convocará a nueva sesión la cual deberá realizarse dentro de los tres días naturales siguientes a la sesión anterior, en la cual someterá nuevamente a votación la designación del Auditor Superior del Estado. En caso de no obtener en esa segunda sesión los votos necesarios, se iniciará nuevamente el procedimiento establecido en el presente artículo, en este supuesto ningún candidato cuenta en el proceso de selección; y, Ley de Fiscalización y Rendición de Cuentas del Estado de Baja California y sus Municipios. Página 46\nIX. La persona designada para ocupar el cargo de Auditor Superior del Estado, protestará su cargo ante el Pleno del Congreso, en sesión pública.\nArtículo 90.- La designación del Auditor Superior del Estado no podrá ser otorgada de manera temporal, debiendo cumplirse, en todo caso, con los períodos de Ley.\nPor lo anterior, el Congreso deberá llevar a cabo tantos procedimientos consecutivos sean necesarios hasta en tanto haya sido designado un nuevo Auditor Superior del Estado.\nSin embargo, si al término del período para el cual fue elegido un titular de la\nAuditoría Superior del Estado, el Congreso no hubiere nombrado a su sucesor, el Auditor\nSuperior del Estado en turno podrá continuar en sus funciones hasta en tanto resuelva el\nCongreso, lo que deberá ser formalmente acordado por ambas partes a más tardar en la fecha misma en que debiera concluir su gestión, independientemente de la causa o circunstancia que ocurriere la falta de resolución no podrá ser considerada como ratificación o reelección. De ser el caso, deberá extenderse el plazo del nombramiento respectivo para los efectos administrativos y legales correspondientes.\nEn caso de no presentarse el acuerdo de las partes a que se refiere el párrafo anterior, la Auditoría Superior del Estado quedará a cargo del servidor público que así lo determine su Reglamento Interior.\nArtículo 91.- El Titular de la Auditoría Superior del Estado durará en el encargo siete años sin que proceda su ratificación. Podrá ser removido por el Congreso, por las causas graves a que se refiere esta Ley, con la misma votación requerida para su nombramiento, así como por las causas y conforme a los procedimientos previstos en el Título Octavo de la\nConstitución.\nArtículo 92.- El Titular de la Auditoría Superior del Estado será suplido en sus ausencias temporales de conformidad con lo dispuesto en el Reglamento Interior de la\nAuditoría Superior del Estado. En caso de falta definitiva, la Comisión dará cuenta al\nCongreso, para que realice nueva designación de acuerdo con el procedimiento de Ley, al\nAuditor que concluirá el encargo.\nArtículo 93.- Para ser Titular de la Auditoría Superior del Estado, se requiere satisfacer los siguientes requisitos:\nI. Ser ciudadano mexicano por nacimiento en pleno ejercicio de sus derechos civiles y políticos;\nII. Tener cuando menos treinta y cinco años cumplidos el día de la designación;\nIII. Gozar de buena reputación y no haber sido condenado por delito intencional que amerite pena corporal de más de un año de prisión; pero si se tratare de robo, fraude, Ley de Fiscalización y Rendición de Cuentas del Estado de Baja California y sus Municipios. Página 47 falsificación, abuso de confianza u otro que afecte seriamente la buena fama en el concepto público, inhabilitará para el cargo cualquiera que haya sido la pena;\nIV. Haber residido en el Estado durante los diez años anteriores al día de su designación;\nV. No haber ocupado cargo de elección popular, ni haber sido titular de los Poderes\nEjecutivo, Legislativo y Judicial, Municipios y Órganos Constitucionales Autónomos, así como titular de sus respectivas Entidades, Dependencias y Unidades Administrativas equivalentes, durante los tres años previos al día de la designación;\nVI. Poseer Título profesional de Contador Público o Titulo afín;\nVII. Tener reconocido prestigio profesional y experiencia técnica de por lo menos diez años en materia de administración pública, así como de control, auditoría financiera y de responsabilidades;\nVIII. No haber sido inhabilitado para desempeñar un empleo, cargo o comisión en el servicio público, ni removido por causa grave de algún cargo del sector público o privado;\nIX. No desempeñar, ni haber desempeñado cargo de dirección nacional, estatal o municipal, en algún partido político, durante los tres años anteriores al día de la designación;\nX. No haber sido candidato a algún cargo de elección popular, durante los tres años anteriores al día de la designación;\nXI. Presentar sus declaraciones de intereses, patrimonial y fiscal, previo a su designación; y,\nXII. Haber destacado por su contribución en materia de fiscalización, de rendición de cuentas, prevención, investigación, detección y combate a la corrupción.\nArtículo 94.- La persona Titular de la Auditoría Superior del Estado, tendrá las siguientes atribuciones:\nPárrafo Reformado\nI. Representar a la Auditoría Superior del Estado, ante las Entidades Fiscalizadas, autoridades federales, estatales y municipales, ya sean administrativas o jurisdiccionales, y demás personas físicas y morales, públicas o privadas;\nII. Elaborar el proyecto de presupuesto anual de la Auditoría Superior del Estado, así como sus modificaciones presupuestales, atendiendo a las previsiones del ingreso y del gasto público y las disposiciones aplicables;\nIII. Administrar los bienes y recursos a cargo de la Auditoría Superior del Estado y\nLey de Fiscalización y Rendición de Cuentas del Estado de Baja California y sus Municipios. Página 48 de la misma, sujetándose a lo dispuesto en el artículo 100 de la Constitución, sus leyes como gestionar la incorporación, destino y desincorporación de bienes inmuebles del dominio público del Estado, afectos a su servicio;\nIV. Aprobar el Programa Operativo Anual de actividades y el programa anual de auditorías. Una vez aprobados serán enviados a la Comisión para su conocimiento;\nV. Expedir de conformidad con lo establecido en esta Ley y hacerlo del conocimiento de la Comisión, el Reglamento Interior de la Auditoría Superior del Estado, en el que se distribuirán las atribuciones de sus Unidades Administrativas que lo integran y de sus titulares, además de establecer la forma en que deberán ser suplidos estos últimos en sus ausencias, su organización interna y funcionamiento, debiendo publicarlo en el Periódico\nOficial del Estado de Baja California;\nVI. Expedir los manuales, de organización y procedimientos que se requieran para la debida organización y funcionamiento de la Auditoría Superior del Estado, los que deberán ser presentados para su conocimiento a la Comisión y los cuales deberán publicarse en el\nPeriódico Oficial del Estado y el Portal Institucional de Internet de la Auditoría Superior del\nEstado.\nAsimismo, expedir las normas para el ejercicio, manejo y aplicación del presupuesto de la Auditoría Superior del Estado, ajustándose a las disposiciones aplicables del\nPresupuesto de Egresos y de la Ley de Presupuesto y Ejercicio del Gasto Público del\nEstado de Baja California, e informar a la Comisión sobre el ejercicio de su presupuesto, y cuando la Comisión le requiera información adicional;\nVII. Nombrar al personal de la Auditoría Superior del Estado, quienes no deberán haber sido sancionados con la inhabilitación para el ejercicio de un puesto o cargo público, así como remover a los mismos;\nVIII. Expedir aquellas normas y disposiciones que esta Ley le confiere a la Auditoría\nSuperior del Estado; así como establecer los elementos que posibiliten la adecuada rendición de cuentas y la práctica idónea de las auditorías, tomando en consideración las propuestas que formulen las entidades fiscalizadas y las características propias de su operación;\nAsimismo, expedir las Reglas de carácter general aplicables a los procesos de fiscalización superior por medios electrónicos, así como la normatividad relativa a los protocolos de seguridad que para tal efecto se implementen. La información y documentación así obtenida, tendrá para todos los efectos legales, pleno valor probatorio.\nPárrafo Adicionado\nFracción Reformada\nIX. Participar, cuando sea electo, en el Comité Rector del Sistema Nacional de\nLey de Fiscalización y Rendición de Cuentas del Estado de Baja California y sus Municipios. Página 49\nFiscalización, ejerciendo las atribuciones que correspondan al respecto;\nFracción Reformada\nX. Ser el enlace entre la Auditoría Superior del Estado, el Congreso y sus comisiones;\nXI. Solicitar a las entidades fiscalizadas, servidores públicos, y a los particulares, sean éstos personas físicas o morales, la información que con motivo de la fiscalización del\nInforme de Avance de Gestión Financiera y de la Cuenta Pública se requiera;\nXII. Solicitar a los Entes Públicos el auxilio que necesite para el ejercicio expedito de las funciones de revisión y fiscalización superior;\nXIII. Ejercer las atribuciones que corresponden a la Auditoría Superior del Estado en los términos de la Constitución, la presente Ley y del Reglamento Interior de la propia\nAuditoría Superior del Estado;\nXIV. Tramitar, instruir y resolver el recurso de reconsideración interpuesto en contra de las multas que se impongan conforme a esta Ley;\nXV. Formular y entregar al Congreso, por conducto de la Comisión, el Informe\nGeneral en el plazo previsto en la presente Ley;\nXVI. Formular y entregar al Congreso, por conducto de la Comisión, los Informes\nIndividuales en los plazos previstos en esta Ley;\nXVII. Autorizar, previa denuncia, la revisión durante el ejercicio fiscal en curso a las entidades fiscalizadas, así como respecto de ejercicios anteriores conforme lo establecido en la presente Ley;\nXVIII. Concertar y celebrar, en los casos que estime necesario, convenios con las entidades fiscalizadas y sus Órganos Internos de Control, con el propósito de apoyar y hacer más eficiente la fiscalización, sin detrimento de su facultad fiscalizadora, la que podrá ejercer de manera directa; así como convenios de colaboración con los organismos nacionales que agrupen a entidades de fiscalización superior homólogas o con éstas directamente, con entes públicos federales y de las Entidades Federativas, el sector privado y con colegios de profesionales, instituciones académicas e instituciones de reconocido prestigio;\nFracción Reformada\nXIX. Dar cuenta comprobada al Congreso, a través de la Comisión, de la aplicación de su presupuesto aprobado, dentro de los treinta primeros días del mes siguiente al que corresponda su ejercicio;\nXX. Solicitar a la Secretaría de Hacienda, el cobro de las multas que se impongan en los términos de esta Ley y celebrar los convenios que se requieran para tal efecto;\nFracción Reformada\nLey de Fiscalización y Rendición de Cuentas del Estado de Baja California y sus Municipios. Página 50\nXXI. Instruir la presentación de las denuncias penales o de juicio político que procedan, como resultado de las irregularidades detectadas con motivo de la fiscalización, con apoyo en los dictámenes técnicos respectivos, de conformidad con las disposiciones legales aplicables;\nXXI BIS. Ordenar la práctica de Auditorías Forenses, mediante la revisión de hechos o evidencias que permitan decretar o investigar actos u omisiones que impliquen probables irregularidades o conductas ilícitas, así como sus causas, efectos y consecuencias, de conformidad con el procedimiento, los alcances y en los términos que determine la\nConstitución, la presente Ley, su Reglamento Interior y demás disposiciones que resulten aplicables.\nFracción Adicionada\nXXII. Expedir la política de remuneraciones, prestaciones y estímulos del personal de confianza de la Auditoría Superior del Estado, observando lo aprobado en el Presupuesto de\nEgresos correspondiente y a las disposiciones de la Ley de Presupuesto y Ejercicio del\nGasto Público del Estado de Baja California;\nXXIII. Elaborar y aprobar para su envío a la Comisión, el plan estratégico de la\nAuditoría Superior del Estado;\nXXIV. Presentar el recurso de revisión administrativa respecto de las resoluciones que emita el Tribunal;\nXXV. Recurrir las determinaciones de la Fiscalía Especializada y del Tribunal;\nXXVI. Transparentar y dar seguimiento a todas las denuncias, quejas, solicitudes, y opiniones realizadas por los particulares o la sociedad civil organizada, salvaguardando en todo momento los datos personales;\nXXVII. Establecer los mecanismos necesarios para fortalecer la participación ciudadana en la rendición de cuentas de las Entidades Fiscalizadas;\nXXVIII. En el marco del sistema nacional y estatal anticorrupción, presentar desde su de recursos públicos, de prevención, control y disuasión de faltas administrativas y hechos de corrupción, por lo que hace a las causas que los generan;\nXXIX. Elaborar en cualquier momento estudios y análisis, así como publicarlos;\nXXX. Recibir de la Comisión, los Informes de Avance de Gestión Financiera y la\nCuenta Pública de los Entes Públicos para su revisión y fiscalización;\nXXXI. Evaluar el Informe de Avance de Gestión Financiera de los Entes Públicos concluidos y la parte ejecutada de los procesos no concluidos;\nLey de Fiscalización y Rendición de Cuentas del Estado de Baja California y sus Municipios. Página 51\nXXXII. Certificar la documentación que forme parte de la Cuenta Pública de los Entes\nPúblicos que se genere por la Auditoría Superior del Estado, solicitada por escrito por las autoridad judicial que conozca o tramite el asunto, siempre y cuando justifiquen de manera fundada y motivada dicha solicitud; así como la demás documentación propia de la Auditoría\nSuperior del Estado que se estime necesaria para efecto de dar cumplimiento a lo dispuesto por la presente Ley y demás disposiciones aplicables; asimismo certificar la documentación que genere la Auditoría Superior del Estado que sea solicitada en los términos de las disposiciones aplicables en materia de transparencia, previo cobro de los derechos correspondientes que se establecen para tales efectos en la Ley de Ingresos del Estado de\nBaja California;\nXXXIII. Proponer, en los términos de la Ley General de Contabilidad Gubernamental, las modificaciones a los principios, normas, procedimientos, métodos y sistemas de registro y contabilidad; las disposiciones para el archivo, guarda y custodia de los libros y documentos justificativos y comprobatorios del ingreso, gasto y de los financiamientos y obligaciones; así como todos aquellos elementos que posibiliten la adecuada rendición de cuentas y la práctica idónea de las auditorías;\nXXXIV. Emitir las opiniones respectivas sobre lo que establece el artículo 105 de esta\nLey; y,\nXXXV. Las demás que señale esta Ley y otras disposiciones legales aplicables.\nDe las atribuciones previstas a favor del Titular de la Auditoría Superior del Estado en esta Ley, sólo las mencionadas en las fracciones II, IV, V, VI, VII, VIII, XIII, XIV, XVII, XVIII, XIX, XXII, XXV, XXX, XXXIII y XXXIV de este artículo, son de ejercicio exclusivo del Titular de la Auditoría Superior del Estado y, por tanto, no podrán ser delegadas.\nArtículo Reformado\nArtículo 95.- El Titular de la Auditoría Superior del Estado, será auxiliado en sus funciones por el subauditor general, el auditor especial de fiscalización, titulares, directores, subdirectores, jefes de departamentos y demás servidores públicos que al efecto señale el\nReglamento Interior de la Auditoría Superior del Estado, de conformidad con el presupuesto autorizado. En dicho Reglamento se asignarán las facultades y atribuciones previstas en esta Ley.\nArtículo 96.- El Titular de la Auditoría Superior del Estado durante el ejercicio de su cargo, tendrá prohibido:\nI. Formar parte de partido político alguno, participar en actos políticos partidistas y hacer cualquier tipo de propaganda o promoción partidista;\nII. Desempeñar otro empleo, cargo o comisión en los sectores público, privado o social, salvo los no remunerados en asociaciones científicas, docentes, artísticas, de\nLey de Fiscalización y Rendición de Cuentas del Estado de Baja California y sus Municipios. Página 52 beneficencia, o Colegios de Profesionales en representación de la Auditoría Superior del\nEstado; y,\nIII. Hacer del conocimiento de terceros o difundir de cualquier forma, la información ejercicio de sus atribuciones, la cual deberá utilizarse sólo para los fines a que se encuentra afecta.\nArtículo 97.- El Auditor Superior del Estado, podrá ser removido de su cargo por las siguientes causas graves de responsabilidad administrativa:\nI. Ubicarse en los supuestos de prohibición establecidos en el artículo anterior;\nII. Utilizar en beneficio propio o de terceros la documentación e información confidencial en los términos de la presente Ley, y sus disposiciones reglamentarias;\nIII. Dejar de determinar sin causa justificada, las bases de las responsabilidades en el ámbito de su competencia y en los casos previstos en la Ley, y disposiciones reglamentarias, cuando deban establecerse como consecuencia de las revisiones e investigaciones que en el ejercicio de sus atribuciones realice;\nIV. Ausentarse de sus labores por más de diez días naturales, sin mediar autorización de la Comisión o causa justificada;\nFracción Reformada\nV. Abstenerse de presentar dentro de los términos de la presente Ley, sin causa justificada, los Informes Individuales y el Informe General;\nVI. Sustraer, destruir, ocultar o utilizar indebidamente la documentación e información que por razón de su cargo tenga a su cuidado o custodia o que exista en la Auditoría\nSuperior del Estado, con motivo del ejercicio de sus atribuciones;\nVII. Aceptar la injerencia de los partidos políticos en el ejercicio de sus funciones y de esta circunstancia, conducirse con parcialidad en el proceso de revisión de las Cuentas se refiere esta Ley; y,\nFracción Reformada\nVIII. Incurrir en cualquiera de las conductas consideradas faltas administrativas graves, en los términos de la legislación aplicable en materia de responsabilidades administrativa, así como la inobservancia de lo previsto en el artículo 3 de la presente Ley.\nArtículo Reformado\nArtículo 98.- El Congreso dictaminará sobre la existencia de los motivos de la\nLey de Fiscalización y Rendición de Cuentas del Estado de Baja California y sus Municipios. Página 53 responsabilidad, y deberá dar derecho de audiencia al afectado. La remoción requerirá del voto de las dos terceras partes de los miembros del Congreso.\nArtículo Reformado\nArtículo 99.- El Titular de la Auditoría Superior del Estado sólo estará obligado a absolver posiciones o rendir declaración en juicio, en representación de la Auditoría Superior del Estado o en virtud de sus funciones, cuando las posiciones y preguntas se formulen por medio de oficio expedido por autoridad competente, misma que se contestará por escrito dentro del término establecido por dicha autoridad.\nArtículo 100.- La Auditoría Superior del Estado contará con un servicio fiscalizador de carrera, debiendo emitir para ese efecto un estatuto que deberá publicarse en el Periódico\nOficial del Estado de Baja California.\nEl personal de la Auditoría Superior del Estado, contará con los conocimientos y la experiencia profesional que se requiera para desempeñar el cargo público encomendado, de conformidad con la estructura que establezca esta Ley y el Reglamento Interior, así como los catálogos de puestos, funciones, y demás disposiciones que para el efecto se emitan.\nAsimismo, conforme a las bases que se emitan, deberán sujetarse y aprobar los procesos de evaluación y control de confianza que se determinen, para lo cual el Auditor Superior del\nEstado podrá celebrar los convenios que sean necesarios con las instituciones públicas o privadas encargadas de su aplicación.\nPárrafo Reformado\nArtículo Reformado\nArtículo 101.- La Auditoría Superior del Estado elaborará su proyecto de presupuesto anual que contenga, de conformidad con las previsiones de gasto, los recursos necesarios para cumplir con su encargo, el cual será remitido por el Titular de la Auditoría Superior del\nEstado a la Comisión a más tardar el 01 de Noviembre, para su inclusión en el proyecto de\nPresupuesto de Egresos para el siguiente ejercicio fiscal. Asimismo se elaborarán las modificaciones presupuestales que se estimen necesarias para su adecuado funcionamiento.\nArtículo 102.- La Auditoría Superior del Estado ejercerá autónomamente su aplicables.\nArtículo 103.- Los servidores públicos de la Auditoría Superior del Estado se clasifican en trabajadores de confianza y trabajadores de base, y se regirán por el Apartado B del artículo 123 de la Constitución Política de los Estados Unidos Mexicanos y la Ley del\nCalifornia.\nLey de Fiscalización y Rendición de Cuentas del Estado de Baja California y sus Municipios. Página 54\nSon trabajadores de confianza, los que tengan tal carácter conforme a lo previsto en\nMunicipios de Baja California, y el Reglamento Interior de la Auditoría Superior del Estado.\nCalifornia.\nArtículo 104.- Para todos los efectos, la relación jurídica de trabajo se entiende establecida entre la Auditoría Superior del Estado, a través de su Titular y los trabajadores a su servicio.\nCAPÍTULO II\nDe las opiniones de la Auditoría Superior del Estado\nArtículo 105.- La Auditoría Superior del Estado, emitirá opinión de lo solicitado por el\nCongreso o sus comisiones, sobre:\nI. Las iniciativas de Leyes de Ingresos y pronósticos de ingresos, así como respecto de los Programas y subprogramas de las Entidades Fiscalizadas, y los Proyectos de\nPresupuestos de Egresos que corresponda aprobar al Congreso;\nII. Las iniciativas de reformas a las Leyes de Ingresos, Leyes y Decretos fiscales estatales o municipales y otras disposiciones que contengan disposiciones de carácter fiscal que rijan a las Entidades Fiscalizadas;\nIII. Las iniciativas de Ley y de reformas a las Leyes, así como los Decretos o\nAcuerdos del Ejecutivo del Estado, o de los Municipios, para la creación, liquidación, escisión o fusión de Entes Públicos, cualquiera que sea la forma o estructura legal que se les asigne;\nIV. Los Acuerdos del Poder Ejecutivo del Estado o de los Municipios para asociarse en empresas de participación estatal o municipal, o para asociarse a los intereses de los particulares en los términos de las Leyes que rijan en la materia de que trate;\nV. La transferencia, ampliación, creación o supresión de partidas en los Presupuestos de Egresos de los Entes Públicos que deban ser aprobados por el Congreso;\nVI. Las solicitudes de financiamientos y obligaciones previstas en el artículo 117,\nFracción VIII, de la Constitución Política de los Estados Unidos Mexicanos, en la Ley de\nDisciplina Financiera de las Entidades Federativas y los Municipios, las demás disposiciones, reglamentos y criterios que de éstas deriven y la legislación local en materia de financiamientos y obligaciones;\nVII. La celebración de contratos, convenios o actos, cuando requieran aprobación del\nCongreso, relacionados con las materias que regula esta Ley;\nLey de Fiscalización y Rendición de Cuentas del Estado de Baja California y sus Municipios. Página 55\nVIII. Las solicitudes de desincorporación de bienes muebles e inmuebles de dominio público para su enajenación, cambio de destino o desafectación de dichos bienes cuando estén destinados a un servicio público o sean de uso común; y,\nIX. Cualquier otra opinión o informe solicitado por el Congreso o sus Comisiones que tengan relación con las funciones, atribuciones y obligaciones de la Auditoría Superior del\nEstado.\nArtículo 106.- Para efectos de emitir las opiniones a que se refiere el artículo anterior, la Auditoría Superior del Estado recibirá del Congreso, por conducto de la comisión que corresponda, los elementos documentales y demás información que se considere pertinente.\nPara el debido cumplimento de lo previsto en el presente y anterior artículos, la\nAuditoría Superior del Estado podrá requerir información adicional de manera directa a las\nEntidades Fiscalizadas que tengan interés en el asunto de que se trate, quienes estarán obligados a atender los requerimientos de que sean objeto en los plazos y términos solicitados.\nCAPÍTULO III\nDe la vigilancia de la Auditoría Superior del Estado\nArtículo 107.- La Comisión, a través de la Unidad de Contraloría Interna del Congreso, vigilará que el Titular de la Auditoría Superior del Estado, subauditor general, el auditor especial de fiscalización, titulares, directores, subdirectores, jefes de departamento y los demás servidores públicos de la Auditoría Superior del Estado en el desempeño de sus funciones, se sujeten a lo establecido en la legislación aplicable en materia de responsabilidades administrativa.\nLa Unidad de Contraloría Interna del Congreso, en el caso de los servidores públicos de la Auditoría Superior del Estado, podrá imponer las sanciones administrativas no graves previstas en la legislación aplicable en materia de responsabilidades administrativa.\nAsimismo, podrá proporcionar el apoyo técnico que la Comisión le requiera en la evaluación del desempeño de la Auditoría Superior del Estado.\nTÍTULO OCTAVO\nDe la Contraloría Social\nCAPÍTULO ÚNICO\nArtículo 108.- La Comisión recibirá peticiones, propuestas, solicitudes y denuncias fundadas y motivadas por la sociedad civil, las cuales podrán ser consideradas en los informes individuales y, en su caso, en el Informe General. Dichas propuestas, solicitudes y correlativa en el Estado, debiendo el Auditor Superior del Estado informar a la Comisión, así\nLey de Fiscalización y Rendición de Cuentas del Estado de Baja California y sus Municipios. Página 56 propuestas relacionadas con el programa anual de auditorías.\nArtículo Reformado\nArtículo 109.- La Unidad de Contraloría Interna del Congreso recibirá de parte de la sociedad opiniones, solicitudes y denuncias sobre el funcionamiento de la fiscalización que ejerce la Auditoría Superior del Estado a efecto de participar, aportar y contribuir a mejorar la función de fiscalización.\nPárrafo Reformado\nLas Unidad de Contraloría Interna del Congreso, informará en tiempo y forma a la\nComisión, con respecto a la recepción de dichas opiniones, solicitudes y denuncias, en apego a la normatividad vigente.\nPárrafo Adicionado\nDichas opiniones, solicitudes o denuncias podrán presentarse por medios electrónicos o por escrito libre dirigido ante la Unidad de Contraloría Interna del Congreso, misma que pondrá a disposición de los particulares los formatos correspondientes.\nPárrafo Recorrido y Reformado\nArtículo Reformado\nTÍTULO NOVENO\nDel Archivo de la documentación interna de la Auditoría\nSuperior del Estado\nCAPÍTULO ÚNICO\nArtículo 110.- La Auditoría Superior del Estado, conservará en su poder los Informes\nIndividuales, el Informe General y los Informes Específicos y la documentación soporte de los mismos, derivados de la revisión de las Cuentas Públicas, durante un plazo de siete años, contado a partir de la fecha en que haya sido publicado en el Periódico Oficial del\nEstado el dictamen correspondiente.\nLa documentación a que se refiere el párrafo anterior, se conservará de conformidad con las leyes aplicables, privilegiándose el uso de expedientes electrónicos o digitales.\nPárrafo Reformado\nArtículo Reformado\nArtículo 111.- Cuando se trate de documentación que corresponda a conceptos respecto de los cuales se hubiera promovido algún recurso o juicio, el plazo de conservación resolución que les ponga fin, o haya prescrito la procedencia de la acción correspondiente en los términos de Ley. señalados para la conservación de la documentación a que se refiere el presente artículo, se estará a lo establecido en las mismas.\nLey de Fiscalización y Rendición de Cuentas del Estado de Baja California y sus Municipios. Página 57\nArtículo 112.- Transcurridos los plazos de guarda de la documentación a que se refiere el presente capítulo, la Auditoría Superior del Estado, podrá proceder a su destrucción, con base en los lineamientos que para el efecto emita el Auditor Superior del\nEstado. Los hechos deberán ser asentados en acta circunstanciada que deberán firmar el\nTitular de la Auditoría Superior del Estado, el titular de la Unidad Administrativa competente y el Contralor Interno del Poder Legislativo.\nTRANSITORIOS\nPRIMERO.- La presente Ley entrará en vigor al día siguiente de su publicación en el\nPeriódico Oficial del Estado de Baja California, sin perjuicio de lo previsto en los transitorios siguientes.\nSEGUNDO.- Se abroga la Ley de Fiscalización Superior de los Recursos Públicos para el Estado de Baja California y sus Municipios, publicada en el Periódico Oficial del\nEstado de Baja California el día 22 de Octubre de 2010 con sus reformas y adiciones, a partir de la entrada en vigor de la presente Ley, y se derogan todas las disposiciones legales y administrativas que contravengan o se opongan a la presente Ley.\nLas referencias que se hagan en otras leyes y disposiciones a la Ley de Fiscalización\nSuperior de los Recursos Públicos para el Estado de Baja California y sus Municipios, se tendrán por realizadas a la presente Ley.\nTERCERO.- La fiscalización de la cuenta pública correspondiente al ejercicio fiscal\n2016 y los demás asuntos que se encuentren en trámite o en proceso, a la entrada en vigor de la presente Ley, continuarán tramitándose hasta su terminación en los términos de la Ley que se abroga.\nLos asuntos que se encuentren en trámite ante el Órgano de Fiscalización Superior del Estado de Baja California, o en los que éste sea parte, continuarán substanciándose por la Auditoría Superior del Estado, hasta su total conclusión.\nHasta en tanto entre en funciones la Auditoría Superior del Estado seguirá operando el Órgano de Fiscalización Superior del Estado de Baja California, conforme a la estructura orgánica y personal que lo integra a la fecha de la entrada en vigor de la presente Ley, y sus actuaciones tendrán plena validez.\nCUARTO.- Los artículos de la presente Ley que se vinculen con la aplicación de la legislación que regula el sistema nacional y estatal anticorrupción, serán aplicables a partir de la cuenta pública correspondiente al ejercicio fiscal 2017, con excepción de lo previsto en el Título Cuarto.\nQUINTO.- El seguimiento que se prevé en los artículos 63 al 66 de la Ley de\nLey de Fiscalización y Rendición de Cuentas del Estado de Baja California y sus Municipios. Página 58 vigor de la presente Ley hayan sido dictaminadas por el Congreso del Estado, concluirá con la remisión del informe que en términos del artículo 64 rindan los Síndicos Procuradores y el último día hábil del mes de octubre del año 2017.\nEn el mes de marzo del año 2018, la Auditoría Superior del Estado rendirá a la Comisión un informe final sobre la evaluación del seguimiento a las observaciones de cuenta pública con base en los informes referidos en el párrafo que antecede.\nPara el seguimiento de las observaciones de las cuentas públicas correspondientes a los ejercicios fiscales 2016 y anteriores, que deriven de los dictámenes que sean aprobados por el Congreso del Estado en fecha posterior a la entrada en vigor de la presente Ley, les será aplicable lo dispuesto en el artículo 63 de la Ley que se abroga.\nCon independencia de los informes a que se refiere el presente artículo, los Síndicos\nProcuradores y los titulares de los Órganos Internos de Control de las Entidades\nFiscalizadas deberán dar continuidad hasta su total resolución a los procedimientos y acciones que deriven del seguimiento a las observaciones de las cuentas públicas conforme a las atribuciones que en el ámbito de sus competencias establecen las legislaciones aplicables. Asimismo deberán informar a la Auditoría Superior del Estado de la resolución definitiva que se determine o recaiga a sus promociones, dentro de los diez días hábiles posteriores a que se notifique dicha resolución.\nSEXTO.- Lo dispuesto en los artículos 14 y 19 de la Ley, relativos a la utilización de medio remotos de comunicación electrónica, se implementará una vez que se realicen las adecuaciones normativas y se cuente con la disponibilidad presupuestal para ello.\nEl título Octavo de la presente Ley, entrará en vigor una vez que sea aprobado el presupuesto para su implementación.\nSÉPTIMO.- El reglamento interior a que hace referencia la presente Ley, deberá emitirse en un plazo no mayor a 180 días naturales contados a partir de que entre en funciones la Auditoría Superior del Estado. artículo 105 de la presente Ley, en un plazo no mayor a un año contado a partir de la vigencia de la misma.\nSe ratifica el contenido de los acuerdos, circulares, guías, lineamientos, políticas, criterios, manuales, procedimientos, así como la demás normatividad del Órgano de\nFiscalización Superior del Estado de Baja California, que se encuentre vigente a la fecha de entrada en vigor de la presente Ley, en tanto se sustituyan o dejen sin efecto.\nLey de Fiscalización y Rendición de Cuentas del Estado de Baja California y sus Municipios. Página 59\nOCTAVO.- Serán válidos hasta su terminación o conclusión de vigencia, los\nÓrgano de Fiscalización Superior del Estado de Baja California.\nNOVENO.- Los recursos humanos, materiales, financieros y presupuestales con que cuenta el Órgano de Fiscalización Superior del Estado de Baja California, incluyendo todos sus bienes y los derechos, pasarán a formar parte de la Auditoría Superior del Estado en términos de lo previsto por esta Ley y las leyes aplicables.\nDÉCIMO.- Las disposiciones previstas en la presente Ley, no afectarán los derechos adquiridos y demás prestaciones reconocidas a los trabajadores del Órgano de Fiscalización\nSuperior del Estado de Baja California por lo que éstos, formarán parte de la nueva estructura orgánica de la Auditoría Superior del Estado.\nDÉCIMO PRIMERO.- El Auditor Superior de Fiscalización en funciones o el servidor público que se encuentre desempeñando el cargo de titular en el Órgano de Fiscalización\nSuperior del Estado de Baja California a la fecha de entrada en vigor de la presente Ley, continuará en el cargo hasta en tanto sea nombrado el Auditor Superior del Estado de Baja\nCalifornia, lo que deberá acontecer dentro del término que establece el artículo transitorio séptimo de la reforma constitucional aprobada por esta H. Legislatura de fecha 6 de julio de\n2017.\nDÉCIMO SEGUNDO.- Para el cumplimiento de las facultades conferidas en la presente Ley a la Auditoría Superior del Estado de Baja California, deberán preverse los recursos presupuestales necesarios.\nDÉCIMO TERCERO.- Los lineamientos que se emitan para el manejo del archivo a que se refiere el Título Noveno de la presente Ley, deberán ser concordantes con las disposiciones establecidas en la Ley General de Administración Documental para el Estado de Baja California, así como con las disposiciones que en materia de archivo documental se publiquen con posterioridad.\nEstado de Baja California, en la Ciudad de Mexicali, B.C., a los veintiséis días del mes de julio del año dos mil diecisiete.\nDIP. JOB MONTOYA GAXIOLA\nPRESIDENTE\n(RÚBRICA)\nDIP. IRAÍS MARÍA VÁZQUEZ AGUIAR\nSECRETARIA\n(RÚBRICA)\nLey de Fiscalización y Rendición de Cuentas del Estado de Baja California y sus Municipios. Página 60\nDE CONFORMIDAD CON LO DISPUESTO POR LA FRACCIÓN I DEL ARTÍCULO 49 DE\nMEXICALI, BAJA CALIFORNIA, A LOS DOS DÍAS DEL MES DE AGOSTO DEL AÑO DOS\nMIL DIECISIETE.\nFRANCISCO ARTURO VEGA DE LAMADRID\nGOBERNADOR DEL ESTADO\n(RÚBRICA)\nFRANCISCO RUEDA GÓMEZ\nSECRETARIO GENERAL DE GOBIERNO\n(RÚBRICA)\nLey de Fiscalización y Rendición de Cuentas del Estado de Baja California y sus Municipios. Página 61\nARTÍCULO 5.- Fue reformado por Decreto No. 213, publicado en el Periódico Oficial No. 11, siendo Gobernadora Constitucional la C. Marina del Pilar Ávila Olmeda 2021-2027; fue reformado por Decreto No. 310, publicado en el Periódico Oficial No. 62, de fecha 06 de\nGobernadora Constitucional la C. Marina del Pilar Ávila Olmeda 2021-2027;\nARTÍCULO 10.- Fue reformado por Decreto No. 310, publicado en el Periódico Oficial No.\n62, de fecha 06 de noviembre de 2023, Sección I, Tomo CXXX, expedido por la H. XXIV\nLegislatura, siendo Gobernadora Constitucional la C. Marina del Pilar Ávila Olmeda 20212027;\nARTÍCULO 11.- Fue reformado por Decreto No. 224, publicado en el Periódico Oficial No.\n31, índice, de fecha 07 de mayo de 2021, Tomo CXXVIII, expedido por la H. XXIII\nLegislatura, siendo Gobernador Constitucional el C. Jaime Bonilla Valdez 2019-2021; fue reformado por Decreto No. 310, publicado en el Periódico Oficial No. 62, de fecha 06 de noviembre de 2023, Sección I, Tomo CXXX, expedido por la H. XXIV Legislatura, siendo\nGobernadora Constitucional la C. Marina del Pilar Ávila Olmeda 2021-2027;\nARTÍCULO 12.- Fue reformado por Decreto No. 310, publicado en el Periódico Oficial No.\n62, de fecha 06 de noviembre de 2023, Sección I, Tomo CXXX, expedido por la H. XXIV\nLegislatura, siendo Gobernadora Constitucional la C. Marina del Pilar Ávila Olmeda 20212027;\nARTÍCULO 14.- Fue reformado por Decreto No. 310, publicado en el Periódico Oficial No.\n62, de fecha 06 de noviembre de 2023, Sección I, Tomo CXXX, expedido por la H. XXIV\nLegislatura, siendo Gobernadora Constitucional la C. Marina del Pilar Ávila Olmeda 20212027;\nARTÍCULO 17.- Fue reformado por Decreto No. 310, publicado en el Periódico Oficial No.\n62, de fecha 06 de noviembre de 2023, Sección I, Tomo CXXX, expedido por la H. XXIV\nLegislatura, siendo Gobernadora Constitucional la C. Marina del Pilar Ávila Olmeda 20212027;\nARTÍCULO 18.- Fue reformado por Decreto No. 310, publicado en el Periódico Oficial No.\nLegislatura, siendo Gobernadora Constitucional la C. Marina del Pilar Ávila Olmeda 20212027;\nARTÍCULO 19.- Fue reformado por Decreto No. 224, publicado en el Periódico Oficial No.\nLegislatura, siendo Gobernador Constitucional el C. Jaime Bonilla Valdez 2019-2021; fue reformado por Decreto No. 310, publicado en el Periódico Oficial No. 62, de fecha 06 de\nLey de Fiscalización y Rendición de Cuentas del Estado de Baja California y sus Municipios. Página 62\nGobernadora Constitucional la C. Marina del Pilar Ávila Olmeda 2021-2027;\nARTÍCULO 19 BIS.- Fue adicionado por Decreto No. 310, publicado en el Periódico Oficial\nLegislatura, siendo Gobernadora Constitucional la C. Marina del Pilar Ávila Olmeda 20212027;\nARTÍCULO 20.- Fue reformado por Decreto No. 310, publicado en el Periódico Oficial No.\n62, de fecha 06 de noviembre de 2023, Sección I, Tomo CXXX, expedido por la H. XXIV\nLegislatura, siendo Gobernadora Constitucional la C. Marina del Pilar Ávila Olmeda 20212027;\nARTÍCULO 22.- Fue reformado por Decreto No. 310, publicado en el Periódico Oficial No.\n62, de fecha 06 de noviembre de 2023, Sección I, Tomo CXXX, expedido por la H. XXIV\nLegislatura, siendo Gobernadora Constitucional la C. Marina del Pilar Ávila Olmeda 20212027;\nARTÍCULO 24.- Fue reformado por Decreto No. 213, publicado en el Periódico Oficial No.\n11, Índice, de fecha 03 de marzo de 2023, Tomo CXXX, expedido por la H. XXIV Legislatura, siendo Gobernadora Constitucional la C. Marina del Pilar Ávila Olmeda 2021-2027; fue reformado por Decreto No. 107, publicado en el Periódico Oficial No. 39. Índice, de fecha 27 de junio de 2025, Tomo CXXXII, expedido por la H. XXV Legislatura, siendo Gobernadora\nConstitucional la C. Marina del Pilar Ávila Olmeda 2021-2027;\nARTÍCULO 24 BIS.- Fue adicionado por Decreto No. 213, publicado en el Periódico Oficial\nNo. 11, Índice, de fecha 03 de marzo de 2023, Tomo CXXX, expedido por la H. XXIV\nLegislatura, siendo Gobernadora Constitucional la C. Marina del Pilar Ávila Olmeda 20212027;\nARTÍCULO 24 TER.- Fue adicionado por Decreto No. 213, publicado en el Periódico Oficial\nNo. 11, Índice, de fecha 03 de marzo de 2023, Tomo CXXX, expedido por la H. XXIV\nLegislatura, siendo Gobernadora Constitucional la C. Marina del Pilar Ávila Olmeda 20212027;\nARTÍCULO 25.- Fue reformado por Decreto No. 310, publicado en el Periódico Oficial No.\nLegislatura, siendo Gobernadora Constitucional la C. Marina del Pilar Ávila Olmeda 20212027;\nARTÍCULO 26.- Fue reformado por Decreto No. 310, publicado en el Periódico Oficial No.\nLegislatura, siendo Gobernadora Constitucional la C. Marina del Pilar Ávila Olmeda 20212027;\nLey de Fiscalización y Rendición de Cuentas del Estado de Baja California y sus Municipios. Página 63\nARTÍCULO 26 BIS.- Fue adicionado por Decreto No. 310, publicado en el Periódico Oficial\nLegislatura, siendo Gobernadora Constitucional la C. Marina del Pilar Ávila Olmeda 20212027;\nARTÍCULO 33.- Fue reformado por Decreto No. 310, publicado en el Periódico Oficial No.\n62, de fecha 06 de noviembre de 2023, Sección I, Tomo CXXX, expedido por la H. XXIV\nLegislatura, siendo Gobernadora Constitucional la C. Marina del Pilar Ávila Olmeda 20212027;\nARTÍCULO 44.- Fue reformado por Decreto No. 310, publicado en el Periódico Oficial No.\n62, de fecha 06 de noviembre de 2023, Sección I, Tomo CXXX, expedido por la H. XXIV\nLegislatura, siendo Gobernadora Constitucional la C. Marina del Pilar Ávila Olmeda 20212027;\nARTÍCULO 46.- Fue reformado por Decreto No. 310, publicado en el Periódico Oficial No.\n62, de fecha 06 de noviembre de 2023, Sección I, Tomo CXXX, expedido por la H. XXIV\nLegislatura, siendo Gobernadora Constitucional la C. Marina del Pilar Ávila Olmeda 20212027;\nARTÍCULO 47.- Fue reformado por Decreto No. 310, publicado en el Periódico Oficial No.\n62, de fecha 06 de noviembre de 2023, Sección I, Tomo CXXX, expedido por la H. XXIV\nLegislatura, siendo Gobernadora Constitucional la C. Marina del Pilar Ávila Olmeda 20212027;\nARTÍCULO 50.- Fue reformado por Decreto No. 310, publicado en el Periódico Oficial No.\n62, de fecha 06 de noviembre de 2023, Sección I, Tomo CXXX, expedido por la H. XXIV\nLegislatura, siendo Gobernadora Constitucional la C. Marina del Pilar Ávila Olmeda 20212027;\nARTÍCULO 51.- Fue reformado por Decreto No. 310, publicado en el Periódico Oficial No.\n62, de fecha 06 de noviembre de 2023, Sección I, Tomo CXXX, expedido por la H. XXIV\nLegislatura, siendo Gobernadora Constitucional la C. Marina del Pilar Ávila Olmeda 20212027;\nARTÍCULO 52.- Fue reformado por Decreto No. 310, publicado en el Periódico Oficial No.\nLegislatura, siendo Gobernadora Constitucional la C. Marina del Pilar Ávila Olmeda 20212027;\nARTÍCULO 53.- Fue reformado por Decreto No. 310, publicado en el Periódico Oficial No.\nLegislatura, siendo Gobernadora Constitucional la C. Marina del Pilar Ávila Olmeda 20212027;\nLey de Fiscalización y Rendición de Cuentas del Estado de Baja California y sus Municipios. Página 64\nARTÍCULO 54.- Fue reformado por Decreto No. 310, publicado en el Periódico Oficial No.\nLegislatura, siendo Gobernadora Constitucional la C. Marina del Pilar Ávila Olmeda 20212027;\nFue modificada la denominación de este Capítulo por Decreto No. 310, publicado en el\nPeriódico Oficial No. 62, de fecha 06 de noviembre de 2023, Sección I, Tomo CXXX, expedido por la H. XXIV Legislatura, siendo Gobernadora Constitucional la C. Marina del\nPilar Ávila Olmeda 2021-2027;\nCAPÍTULO VII\nDE LA CONCLUSIÓN DE LA REVISIÓN DE LA CUENTA PÚBLICA POR EL CONGRESO\nDEL ESTADO\nARTÍCULO 55.- Fue reformado por Decreto No. 310, publicado en el Periódico Oficial No.\n62, de fecha 06 de noviembre de 2023, Sección I, Tomo CXXX, expedido por la H. XXIV\nLegislatura, siendo Gobernadora Constitucional la C. Marina del Pilar Ávila Olmeda 20212027;\nARTÍCULO 57.- Fue reformado por Decreto No. 310, publicado en el Periódico Oficial No.\n62, de fecha 06 de noviembre de 2023, Sección I, Tomo CXXX, expedido por la H. XXIV\nLegislatura, siendo Gobernadora Constitucional la C. Marina del Pilar Ávila Olmeda 20212027;\nARTÍCULO 58.- Fue reformado por Decreto No. 310, publicado en el Periódico Oficial No.\n62, de fecha 06 de noviembre de 2023, Sección I, Tomo CXXX, expedido por la H. XXIV\nLegislatura, siendo Gobernadora Constitucional la C. Marina del Pilar Ávila Olmeda 20212027;\nARTÍCULO 64.- Fue reformado por Decreto No. 213, publicado en el Periódico Oficial No.\n11, Índice, de fecha 03 de marzo de 2023, Tomo CXXX, expedido por la H. XXIV Legislatura, siendo Gobernadora Constitucional la C. Marina del Pilar Ávila Olmeda 2021-2027; fue reformado por Decreto No. 310, publicado en el Periódico Oficial No. 62, de fecha 06 de\nGobernadora Constitucional la C. Marina del Pilar Ávila Olmeda 2021-2027;\nARTÍCULO 65.- Fue reformado por Decreto No. 213, publicado en el Periódico Oficial No. siendo Gobernadora Constitucional la C. Marina del Pilar Ávila Olmeda 2021-2027;\nARTÍCULO 77.- Fue reformado por Decreto No. 310, publicado en el Periódico Oficial No.\nLegislatura, siendo Gobernadora Constitucional la C. Marina del Pilar Ávila Olmeda 20212027;\nLey de Fiscalización y Rendición de Cuentas del Estado de Baja California y sus Municipios. Página 65\nARTÍCULO 79.- Fue reformado por Decreto No. 310, publicado en el Periódico Oficial No.\nLegislatura, siendo Gobernadora Constitucional la C. Marina del Pilar Ávila Olmeda 20212027;\nARTÍCULO 86.- Fue reformado por Decreto No. 73, publicado en el Periódico Oficial No. 11,\nSección IV, de fecha 11 de febrero de 2022, Tomo CXXIX, expedido por la H. XXIV\nLegislatura, siendo Gobernadora Constitucional la C. Marina del Pilar Ávila Olmeda 20212027; fue reformado por Decreto No. 310, publicado en el Periódico Oficial No. 62, de fecha\n06 de noviembre de 2023, Sección I, Tomo CXXX, expedido por la H. XXIV Legislatura, siendo Gobernadora Constitucional la C. Marina del Pilar Ávila Olmeda 2021-2027;\nARTÍCULO 94.- Fue reformado por Decreto No. 224, publicado en el Periódico Oficial No.\n31, Índice, de fecha 07 de mayo de 2021, Tomo CXXVIII, expedido por la H. XXIII\nLegislatura, siendo Gobernador Constitucional el C. Jaime Bonilla Valdez 2019-2021; fue reformado por Decreto No. 213, publicado en el Periódico Oficial No. 11, Índice, de fecha 03 de marzo de 2023, Tomo CXXX, expedido por la H. XXIV Legislatura, siendo Gobernadora\nConstitucional la C. Marina del Pilar Ávila Olmeda 2021-2027; fue reformado por Decreto No.\n310, publicado en el Periódico Oficial No. 62, de fecha 06 de noviembre de 2023, Sección I, Tomo CXXX, expedido por la H. XXIV Legislatura, siendo Gobernadora Constitucional la C.\nMarina del Pilar Ávila Olmeda 2021-2027; fue reformado por Decreto No. 107, publicado en el Periódico Oficial No. 39. Índice, de fecha 27 de junio de 2025, Tomo CXXXII, expedido por la H. XXV Legislatura, siendo Gobernadora Constitucional la C. Marina del Pilar Ávila\nOlmeda 2021-2027;\nARTÍCULO 97.- Fue reformado por Decreto No. 310, publicado en el Periódico Oficial No.\n62, de fecha 06 de noviembre de 2023, Sección I, Tomo CXXX, expedido por la H. XXIV\nLegislatura, siendo Gobernadora Constitucional la C. Marina del Pilar Ávila Olmeda 20212027;\nARTÍCULO 98.- Fue reformado por Decreto No. 310, publicado en el Periódico Oficial No.\n62, de fecha 06 de noviembre de 2023, Sección I, Tomo CXXX, expedido por la H. XXIV\nLegislatura, siendo Gobernadora Constitucional la C. Marina del Pilar Ávila Olmeda 20212027;\nARTÍCULO 100.- Fue reformado por Decreto No. 310, publicado en el Periódico Oficial No.\nLegislatura, siendo Gobernadora Constitucional la C. Marina del Pilar Ávila Olmeda 20212027;\nARTÍCULO 108.- Fue reformado por Decreto No. 73, publicado en el Periódico Oficial No.\nLegislatura, siendo Gobernadora Constitucional la C. Marina del Pilar Ávila Olmeda 20212027;\nLey de Fiscalización y Rendición de Cuentas del Estado de Baja California y sus Municipios. Página 66\nARTÍCULO 109.- Fue reformado por Decreto No. 73, publicado en el Periódico Oficial No.\nLegislatura, siendo Gobernadora Constitucional la C. Marina del Pilar Ávila Olmeda 20212027;\nARTÍCULO 110.- Fue reformado por Decreto No. 310, publicado en el Periódico Oficial No.\nLegislatura, siendo Gobernadora Constitucional la C. Marina del Pilar Ávila Olmeda 20212027;\nARTÍCULO TRANSITORIO CUARTO, DEL DECRETO No. 310, EXPEDIDO POR LA H.\nXXIV LEGISLATURA.- Fue modificado por Decreto No. 387, publicado en el Periódico Oficial\nLegislatura, siendo Gobernadora Constitucional la C. Marina del Pilar Ávila Olmeda 20212027;\nLey de Fiscalización y Rendición de Cuentas del Estado de Baja California y sus Municipios. Página 67\nARTÍCULO ÚNICO TRANSITORIO DEL DECRETO No. 224, POR EL QUE SE APRUEBA\nLA REFORMA A LOS ARTÍCULOS 11, 19 Y 94; PUBLICADO EN EL PERIÓDICO OFICIAL\nXXIII LEGISLATURA, SIENDO GOBERNADOR CONSTITUCIONAL EL C. JAIME BONILLA\nVALDEZ 2019-2021.\nTRANSITORIOS\nÚNICO.- El presente decreto entrará en vigor el día siguiente de su publicación en el\nPeriódico Oficial del Estado de Baja California.\nDADO en Sesión Ordinaria Virtual en la Ciudad de Mexicali, B.C., a los nueve días del mes de abril del año dos mil veintiuno.\nDIP. EVA GRICELDA RODRÍGUEZ\nPRESIDENTA\n(RÚBRICA)\nDIP. MARÍA LUISA VILLALOBOS ÁVILA\nSECRETARIA\n(RÚBRICA)\nDE CONFORMIDAD CON LO DISPUESTO POR LA FRACCIÓN I DEL ARTÍCULO 49 DE\nCALIFORNIA, IMPRÍMASE Y PUBLÍQUESE.\nMEXICALI, BAJA CALIFORNIA, A LOS CATORCE DÍAS DEL MES DE ABRIL DEL\nAÑO DOS MIL VEINTIUNO.\nJAIME BONILLA VALDEZ\nGOBERNADOR DEL ESTADO\n(RÚBRICA)\nAMADOR RODRÍGUEZ LOZANO\nSECRETARIO GENERAL DE GOBIERNO\n(RÚBRICA)\nLey de Fiscalización y Rendición de Cuentas del Estado de Baja California y sus Municipios. Página 68\nARTÍCULO ÚNICO TRANSITORIO DEL DECRETO No. 73, POR EL QUE SE APRUEBA LA\nREFORMA A LOS ARTÍCULOS 86, 108 Y 109; PUBLICADO EN EL PERIÓDICO OFICIAL\nPOR LA H. XXIV LEGISLATURA, SIENDO GOBERNADORA CONSTITUCIONAL LA C.\nMARINA DEL PILAR ÁVILA OLMEDA 2021-2027.\nTRANSITORIOS\nÚNICO. El presente Decreto entrará en vigor el día siguiente de su publicación en el\nPeriódico Oficial del Estado.\nDADO en Sesión Ordinaria Virtual de la XXIV Legislatura en la Ciudad de Mexicali, B.C., a los veintisiete días del mes de enero del año dos mil veintidós.\nDIP. JUAN MANUEL MOLINA GARCÍA\nPRESIDENTE\n(RÚBRICA)\nDIP. ARACELI GERALDO NÚÑEZ\nSECRETARIA\n(RÚBRICA)\nDE CONFORMIDAD CON LO DISPUESTO POR LA FRACCIÓN I DEL ARTÍCULO 49 DE\nCALIFORNIA, IMPRÍMASE Y PUBLÍQUESE.\nMEXICALI, BAJA CALIFORNIA, AL PRIMER DÍA DEL MES DE FEBRERO DEL AÑO\nDOS MIL VEINTIDÓS.\nMARINA DEL PILAR ÁVILA OLMEDA\nGOBERNADORA DEL ESTADO\nDE BAJA CALIFORNIA\n(RÚBRICA)\nCATALINO ZAVALA MÁRQUEZ\nSECRETARIO GENERAL DE GOBIERNO\nDEL ESTADO DE BAJA CALIFORNIA\n(RÚBRICA)\nLey de Fiscalización y Rendición de Cuentas del Estado de Baja California y sus Municipios. Página 69\nARTÍCULO ÚNICO TRANSITORIO DEL DECRETO No. 213, POR EL QUE SE APRUEBA\nLA REFORMA A LOS ARTÍCULOS 5, 24, 64, 65, Y 94, COMO TAMBIÉN LA ADICIÓN DE\nLOS ARTÍCULOS 24 BIS Y 24 TER; PUBLICADO EN EL PERIÓDICO OFICIAL No. 11,\nLEGISLATURA, SIENDO GOBERNADORA CONSTITUCIONAL LA C. MARINA DEL PILAR\nÁVILA OLMEDA 2021-2027.\nTRANSITORIOS\nPRIMERO. Las presentes reformas entrarán en vigor el día siguiente al de su publicación en el Periódico Oficial del Estado de Baja California.\nSEGUNDO. La Auditoría Superior del Estado realizará y adecuará las disposiciones reglamentarias correspondientes, a fin de poner en funcionamiento la herramienta electrónica a que hace referencia el artículo 24 Bis de la presente Ley, dentro del plazo de ciento ochenta días naturales, contados a partir de la entrada en vigor de las presentes reformas.\nTERCERO. Las disposiciones previstas en el Articulo 24 TER de la presente Ley, relativas al\n\"sello digital de tiempo\" previsto en la fracción IV y la \"firma electrónica avanzada amparada por un certificado vigente\" prevista en la fracción VI, entrarán en vigor dentro del plazo de trescientos sesenta y cinco días naturales, contados a partir de la entrada en vigor de las presentes reformas.\nCUARTO. Las auditorías presenciales iniciadas antes de la entrada en vigor de la presente reforma se concluirán bajo la misma modalidad.\nQUINTO. El Congreso del Estado homologará y armonizará la Ley Orgánica del Poder\nLegislativo del Estado de Baja California, a fin de permitir la recepción, por medios electrónicos de las denuncias a que se refiere la presente Ley, dentro del plazo de ciento ochenta días naturales, contados a partir de la entrada en vigor de las presentes reformas.\nDADO en Sesión Ordinaria de la XXIV Legislatura en la Ciudad de Mexicali, B.C., a los dieciséis días del mes de febrero del año dos mil veintitrés.\nDIP. MARÍA DEL ROCÍO ADAME MUÑOZ\nPRESIDENTA\n(RÚBRICA)\nDIP. DUNNIA MONTSERRAT MURILLO LÓPEZ\nSECRETARIA\n(RÚBRICA)\nLey de Fiscalización y Rendición de Cuentas del Estado de Baja California y sus Municipios. Página 70\nDE CONFORMIDAD CON LO DISPUESTO POR LA FRACCIÓN I DEL ARTÍCULO 49 DE\nCALIFORNIA, IMPRÍMASE Y PUBLÍQUESE.\nMEXICALI, BAJA CALIFORNIA, A LOS DIECISIETE DÍAS DEL MES DE FEBRERO\nDEL AÑO DOS MIL VEINTITRÉS.\nMARINA DEL PILAR ÁVILA OLMEDA\nGOBERNADORA DEL ESTADO\nDE BAJA CALIFORNIA\n(RÚBRICA)\nCATALINO ZAVALA MÁRQUEZ\nSECRETARIO GENERAL DE GOBIERNO\nDEL ESTADO DE BAJA CALIFORNIA\n(RÚBRICA)\nARTÍCULO SEGUNDO TRANSITORIO DEL DECRETO No. 310, POR EL QUE SE\nAPRUEBA LA REFORMA A LOS ARTÍCULOS 5, 10, 11, 12, 14, 17, 18, 19, 20, 22, 25, 26,\n33, 44, 46, 47, 50, 51, 52, 53, 54, 55, 57, 58, 64, 77, 79, 86, 94, 97, 98, 100, 110 Y\nADICIONA LOS ARTÍCULOS 19 BIS Y 26 BIS; PUBLICADO EN EL PERIÓDICO OFICIAL\nNo. 62, DE FECHA 06 DE NOVIEMBRE DE 2023, SECCIÓN I, TOMO CXXX, EXPEDIDO\nPOR LA H. XXIV LEGISLATURA, SIENDO GOBERNADORA CONSTITUCIONAL LA C.\nMARINA DEL PILAR ÁVILA OLMEDA 2021-2027.\nTRANSITORIOS\nPRIMERO.- Las presentes reformas entrarán en vigor al día siguiente de su publicación en el Periódico Oficial del Estado de Baja California, sin perjuicio de lo previsto en los transitorios siguientes.\nSEGUNDO.- Las presentes reformas aplicarán para el proceso de fiscalización de la cuenta pública correspondiente al ejercicio fiscal dos mil veintitrés y subsecuentes.\nTERCERO.- El proceso de fiscalización de la cuenta pública correspondiente al ejercicio ejercicios fiscales anteriores, continuarán tramitándose hasta su conclusión en los términos de la normatividad vigente hasta antes de la entrada en vigor de las presentes reformas.\nCUARTO.- La Auditoría Superior del Estado contará con 180 días para emitir el reglamento para normar el procedimiento relativo a la imposición de las multas descritas en el artículo 11 de la presente Ley, previa validación del proyecto, por parte de la Comisión de Fiscalización del Gasto Público.\nArtículo Transitorio Modificado\nLey de Fiscalización y Rendición de Cuentas del Estado de Baja California y sus Municipios. Página 71\nQUINTO.- La reforma al artículo 17 será aplicable para la entrega del Informe de Avance de subsecuentes.\nDADO en Sesión Ordinaria de la XXIV Legislatura en la Ciudad de Mexicali, B.C., a los diecinueve días del mes de octubre del año dos mil veintitrés.\nDIP. MANUEL GUERRERO LUNA\nPRESIDENTE\n(RÚBRICA)\nDIP. DUNNIA MONTSERRAT MURILLO LÓPEZ\nSECRETARIA\n(RÚBRICA)\nDE CONFORMIDAD CON LO DISPUESTO POR LA FRACCIÓN I DEL ARTÍCULO 49 DE\nCALIFORNIA, IMPRÍMASE Y PUBLÍQUESE.\nMEXICALI, BAJA CALIFORNIA, A LOS VEINTE DÍAS DEL MES DE OCTUBRE DEL\nAÑO DOS MIL VEINTITRÉS.\nMARINA DEL PILAR ÁVILA OLMEDA\nGOBERNADORA DEL ESTADO\nDE BAJA CALIFORNIA\n(RÚBRICA)\nCATALINO ZAVALA MÁRQUEZ\nSECRETARIO GENERAL DE GOBIERNO\nDEL ESTADO DE BAJA CALIFORNIA\n(RÚBRICA)\nARTÍCULO ÚNICO TRANSITORIO DEL DECRETO No. 387, POR EL QUE SE APRUEBA\nLA REFORMA QUE MODIFICA EL ARTÍCULO CUARTO TRANSITORIO DEL\nRESOLUTIVO SEGUNDO DEL DECRETO NO. 310, PUBLICADO EN FECHA 06 DE\nPERIÓDICO OFICIAL DEL ESTADO DE BAJA CALIFORNIA; PUBLICADO EN EL\nCXXXI, EXPEDIDO POR LA H. XXIV LEGISLATURA, SIENDO GOBERNADORA\nCONSTITUCIONAL LA C. MARINA DEL PILAR ÁVILA OLMEDA 2021-2027.\nTRANSITORIO\nÚNICO. La presente reforma entrará en vigor al día siguiente de su publicación en el\nPeriódico Oficial del Estado de Baja California.\nLey de Fiscalización y Rendición de Cuentas del Estado de Baja California y sus Municipios. Página 72\nDADO en Sesión Extraordinaria de la XXIV Legislatura en la Ciudad de Mexicali, B.C., a los nueve días del mes de febrero del año dos mil veinticuatro.\nDIP. ARACELI GERALDO NÚÑEZ\nPRESIDENTA\n(RÚBRICA)\nDIP. MANUEL GUERRERO LUNA\nSECRETARIO\n(RÚBRICA)\nDE CONFORMIDAD CON LO DISPUESTO POR LA FRACCIÓN I DEL ARTÍCULO 49 DE\nCALIFORNIA, IMPRÍMASE Y PUBLÍQUESE.\nMEXICALI, BAJA CALIFORNIA, A LOS NUEVE DÍAS DEL MES DE FEBRERO DEL\nAÑO DOS MIL VEINTICUATRO.\nMARINA DEL PILAR ÁVILA OLMEDA\nGOBERNADORA DEL ESTADO\nDE BAJA CALIFORNIA\n(RÚBRICA)\nALFREDO ÁLVAREZ CÁRDENAS\nSECRETARIO GENERAL DE GOBIERNO\nDEL ESTADO DE BAJA CALIFORNIA\n(RÚBRICA)\nARTÍCULO ÚNICO TRANSITORIO DEL DECRETO No. 107, POR EL QUE SE APRUEBA\nLA REFORMA A LOS ARTÍCULOS 24 Y 94; PUBLICADO EN EL PERIÓDICO OFICIAL No.\n39, ÍNDICE, DE FECHA 27 DE JUNIO DE 2025, TOMO CXXXII; EXPEDIDO POR LA H.\nXXV LEGISLATURA, SIENDO GOBERNADORA CONSTITUCIONAL LA C. MARINA DEL\nPILAR ÁVILA OLMEDA 2021-2027.\nARTÍCULO TRANSITORIO\nÚNICO. La presente reforma entrará en vigor al día siguiente de su publicación en el\nPeriódico Oficial del Estado de Baja California.\nDADO en Sesión Ordinaria de la XXV Legislatura en la Ciudad de Mexicali, B.C., a los diecinueve días del mes de junio del año dos mil veinticinco.\nDIP. MICHELLE ALEJANDRA TEJEDA MEDINA\nPRESIDENTA\nLey de Fiscalización y Rendición de Cuentas del Estado de Baja California y sus Municipios. Página 73\n(RÚBRICA)\nDIP. NORMA ANGELICA PEÑALOZA ESCOBEDO\nSECRETARIA\n(RÚBRICA)\nDE CONFORMIDAD CON LO DISPUESTO POR LA FRACCIÓN I DEL ARTÍCULO 49\nCALIFORNIA, IMPRÍMASE Y PUBLÍQUESE.\nMEXICALI, BAJA CALIFORNIA, A LOS 20 DÍAS DEL MES DE JUNIO DEL AÑO DOS\nMIL VEINTICINCO.\nMARINA DEL PILAR ÁVILA OLMEDA\nGOBERNADORA DEL ESTADO\nDE BAJA CALIFORNIA\n(RÚBRICA)\nALFREDO ÁLVAREZ CÁRDENAS\nSECRETARIO GENERAL DE GOBIERNO\nDEL ESTADO DE BAJA CALIFORNIA\n(RÚBRICA)\nLey de Fiscalización y Rendición de Cuentas del Estado de Baja California y sus Municipios. Página 74",
  "ordenamiento": "REGLAMENTO",
  "jurisdiccion": "BAJA CALIFORNIA",
  "fuente_oficial": "Periódico Oficial",
  "FECHA PER OFIC": "2025/06/27",
  "ESTATUS": "VIGENTE",
  "TOMO": "TOMO_II",
  "URL": "https://www.congresobc.gob.mx/Documentos/ProcesoParlamentario/Leyes/TOMO_II/20250627_LEYFISRENCUE.PDF",
  "es_escaneado": false,
  "tiene_tablas": true,
  "materia": [
    "financiero",
    "fiscal",
    "económico"
  ]
}