{
  "titulo": "Ley QUE ESTABLECE LAS BASES DE OPERACIÓN DE LAS CASAS DE EMPEÑO DEL ESTADO DE BAJA CALIFORNIA",
  "Contenido": ". rio y\nActualización Legislativa.\nÚltima Reforma P.O. No. 55, Sección IV, 30-Nov-2018\nLEY QUE ESTABLECE LAS BASES DE OPERACIÓN DE LAS CASAS DE\nEMPEÑO DEL ESTADO DE BAJA CALIFORNIA\nPublicado en el Periódico Oficial No. 37, de fecha 27 de agosto de 2010, Tomo CXVII, Sección II\nCAPÍTULO PRIMERO\nDISPOSICIONES GENERALES\nARTÍCULO 1.- La presente Ley es de orden público e interés social, y tiene por objeto regular la instalación y operación de establecimientos cuyo objeto sea ofertar al público la celebración de contratos de mutuo con interés y garantía prendaria.\nARTÍCULO 2.- Son sujetos de esta Ley, las personas físicas y morales que tengan como actividad ofertar al público la celebración de contratos de mutuo con interés y garantía prendaria o similares a éstos.\nARTÍCULO 3.- Las personas físicas y morales que desempeñen las actividades descritas en el artículo anterior, independientemente de las obligaciones que otras leyes o reglamentos les impongan, deberán obtener permiso del Ejecutivo del Estado, por conducto de la Secretaría General de Gobierno, para su instalación y operación, de conformidad a esta Ley y sus disposiciones reglamentarias.\nARTÍCULO 4.- Corresponde la aplicación y supervisión del cumplimiento de las normas contenidas en esta Ley y su Reglamento, al Ejecutivo del Estado, a través de la\nSecretaría General de Gobierno.\nARTÍCULO 5.- Para efectos de la presente Ley, se entenderá por:\nI. Casa de Empeño.- Todo aquel establecimiento cuyo actividad sea ofertar al público la celebración de contratos de mutuo con interés y garantía prendaria o similares a éstos;\nII. Contrato.- Al contrato de mutuo con interés y garantía prendaria o similar a éste;\nIII. Empeño.- A la celebración del contrato de mutuo con interés y garantía prendaria o similares a éste, por medio del cual el pignorante recibe el préstamo y garantiza su restitución a través de una prenda;\nV. Ley.- A la Ley que Establece las Bases de Operación de las Casas de Empeño del\nEstado de Baja California;\nLey que Establece las Bases de Operación de las Casas de Empeño Página 1\n. rio y\nActualización Legislativa.\nÚltima Reforma P.O. No. 55, Sección IV, 30-Nov-2018\nVI. Secretaría.- A la Secretaría General de Gobierno;\nVII. Permiso.- Documento por medio del cual se autoriza la instalación y operación de una casa de empeño;\nVIII. Permisionario.- La persona física o moral que obtenga el permiso a que se refiere esta Ley;\nIX. Peticionario.- La persona física o moral que conforme a la Ley solicite la expedición, revalidación o modificación del permiso; y\nX. Pignorante.- Persona que solicita un préstamo en dinero con garantía prendaria.\nARTÍCULO 6.- En lo no establecido en esta Ley se aplicarán supletoriamente las disposiciones de la Ley del Procedimiento para los Actos de la Administración Pública del\nEstado, y en su caso, el Código de Procedimientos Civiles para el Estado.\nCAPÍTULO SEGUNDO\nDE LAS AUTORIDADES Y SUS ATRIBUCIONES\nARTÍCULO 7.- Son autoridades competentes para la aplicación de esta Ley:\nI. El Gobernador del Estado;\nII. El Secretario General de Gobierno;\nIII. Los Subsecretarios de Gobierno de la Secretaría;\nIV. El Director de Gobierno de la Secretaría;\nV. Los Delegados de la Secretaría en las diferentes Zonas o Municipios;\nVI. El Jefe de Departamento de la Dirección de Gobierno de la Secretaría; y\nVII. Los inspectores, ejecutores y notificadores, que designe la Secretaría.\nARTÍCULO 8.- A la Secretaría corresponderán las siguientes atribuciones:\nI. La recepción y estudio de las solicitudes de expedición, revalidación, modificación y reposición del permiso;\nII. Elaborar la resolución respecto a las solicitudes que se mencionan en la fracción anterior;\nFracción Reformada\nIII. Notificar las resoluciones correspondientes;\nIV. Llevar a cabo las visitas de inspección a las casas de empeño, de conformidad con la normatividad aplicable;\nLey que Establece las Bases de Operación de las Casas de Empeño Página 2\n. rio y\nActualización Legislativa.\nÚltima Reforma P.O. No. 55, Sección IV, 30-Nov-2018\nV. Aplicar las medidas cautelares previstas en esta Ley;\nVI. Aplicar las sanciones por infracciones a esta Ley y su Reglamento;\nVII. Dar vista al Ministerio Público, cuando se presuma la comisión de un delito en la operación de la casa de empeño, y\nFracción Reformada\nVIII. Las demás que sean necesarias para el debido cumplimiento de la Ley y su\nReglamento.\nFracción Reformada\nArtículo Reformado\nCAPÍTULO TERCERO\nDE LOS PERMISOS\nARTÍCULO 9.- La expedición, revalidación, modificación, reposición y cancelación de los permisos a que se refiere esta Ley, serán otorgados por el Ejecutivo del Estado, por conducto de la Secretaría.\nARTÍCULO 10.- El permiso expedido autoriza la instalación y operación de una casa de empeño, dentro del horario comprendido entre las siete horas hasta las veintidós horas del día; en caso de que el interesado desee establecer sucursales u otros similares, deberá solicitar el permiso respectivo en los términos de esta ley.\nARTÍCULO 11.- Es obligación de los permisionarios colocar dentro de la casa de empeño de manera permanente y visible, el permiso original vigente expedido en los términos de esta Ley y su Reglamento.\nARTÍCULO 12.- La Secretaría realizará en base a la información que se le presente, estudio de cumplimiento de los requisitos contenidos en esta Ley y su Reglamento, por el cual se generarán los costos que se establezcan en la Ley de Ingresos del Estado.\nARTÍCULO 13.- El Permiso deberá especificar:\nI.- Fundamento legal para la expedición, especificando que se han cumplido con los requisitos exigidos por la Ley y el Reglamento;\nII.- Número y clave de identificación del permiso;\nIII.- Nombre o razón social del permisionario;\nIV.- Nombre comercial de la casa de empeño;\nV.- Registro Federal del Contribuyente;\nVI.- Domicilio de la casa de empeño;\nVII.- La obligación del permisionario de revalidar el permiso en los términos que establece la Ley;\nLey que Establece las Bases de Operación de las Casas de Empeño Página 3\n. rio y\nActualización Legislativa.\nÚltima Reforma P.O. No. 55, Sección IV, 30-Nov-2018\nVIII.- Fecha y lugar de expedición;\nIX.- Vigencia del permiso; y\nX.- Nombre y firma del Servidor Público autorizado para expedir el permiso.\nARTÍCULO 14.- La expedición, revalidación, modificación y reposición de los permisos se hará conforme a las condiciones y plazos establecidos en esta Ley, y su\nReglamento.\nSECCIÓN PRIMERA\nDE LA SOLICITUD DEL PERMISO\nARTÍCULO 15.- Para obtener el permiso respectivo, el peticionario deberá satisfacer los siguientes requisitos:\nI.- Formular solicitud por escrito dirigida a la Secretaría, la que deberá contener:\na) Nombre o razón social del peticionario, y del representante legal, en su caso;\nb) Nombre comercial de la casa de empeño;\nc) Domicilio donde operará la casa de empeño;\nd) Domicilio para oír y recibir notificaciones y persona o personas autorizadas para recibirlas en su nombre y representación, y\ne) Fecha y lugar de la solicitud.\nII.- Si el peticionario es persona física, deberá acompañar copia de identificación oficial con fotografía;\nIII.- Si el peticionario es persona moral, deberá acompañar copia certificada del acta constitutiva, cuyo objeto social comprenda la actividad del empeño, así como del Poder\nNotarial otorgado al representante legal;\nIV.- Póliza de seguro otorgada por compañía aseguradora autorizada, cuyo monto asegurado sea equivalente a doce mil veces el salario mínimo general vigente de la región, o el suficiente para garantizar los daños y perjuicios que pudiera ocasionarse a los pignorantes, misma que en ningún caso podrá ser menor a la cantidad antes estipulada.\nDicha póliza se presentará dentro de los diez días hábiles, contados a partir del día siguiente a la notificación de la aprobación de la solicitud; tendrá vigencia de un año y deberá ser refrendada anualmente para efectos de la revalidación del permiso correspondiente;\nV.- Cubrir el costo que se establezca en la Ley de Ingresos del Estado, para la realización del estudio de cumplimiento de los requisitos, referido en el artículo 12 de esta\nLey;\nVI.- Exhibir copia certificada del Registro Federal de Contribuyente;\nLey que Establece las Bases de Operación de las Casas de Empeño Página 4\n. rio y\nActualización Legislativa.\nÚltima Reforma P.O. No. 55, Sección IV, 30-Nov-2018\nVII.- Exhibir copia certificada de los avisos de apertura ante el Registro Federal de\nContribuyente y Registro Estatal de Causantes;\nVIII.- Exhibir el contrato que utilizarán para la celebración de los prestamos ofertados al público, mismo que deberá contener el registro expedido por la Procuraduría Federal del\nConsumidor, y en su caso Condusef.\nFracción Reformada\nIX.- Exhibir constancia de uso de suelo, expedida por la autoridad municipal correspondiente;\nX.- Exhibir constancia de vigencia de la autorización de ocupación, expedida por la autoridad municipal correspondiente; y\nXI. Las demás que determine el Reglamento.\nArtículo Reformado\nARTÍCULO 16.- Recibida la solicitud, la Secretaría procederá a realizar el estudio de cumplimiento de requisitos y practicará las visitas de verificación que considere necesarias.\nCuando el peticionario no cumpla con los requisitos establecidos en el artículo anterior, la Secretaría lo requerirá para que exhiba los documentos o información omitida, otorgándole un plazo de cinco días hábiles para su cumplimiento; apercibiéndolo que de no hacerlo la Secretaría resolverá que se tendrá por no presentada la solicitud, quedando a salvo su derecho para hacerlo de nuevo.\nARTÍCULO 17.- La Secretaría contará con un plazo de veinte días hábiles para resolver lo conducente, a partir de la presentación de la solicitud de permiso, y en caso de que se hubiese requerido al peticionario, a partir del vencimiento del plazo concedido. La resolución deberá notificarse al peticionario personalmente o por correo certificado con acuse de recibo.\nARTÍCULO 18.- La existencia de un dato falso en la solicitud y documentos anexos o alteración de éstos, será motivo suficiente para resolver negativamente la solicitud.\nDe igual forma será motivo suficiente para negar el permiso, cuando el anteriores a la presentación de la misma, por haber operado sin el permiso correspondiente, y no sea una persona moral o física de acreditada solvencia, y una continuidad en sus operaciones de mínimo tres años.\nPárrafo Reformado\nArtículo Reformado\nSECCIÓN SEGUNDA\nDE LA EXPEDICIÓN DEL PERMISO\nLey que Establece las Bases de Operación de las Casas de Empeño Página 5\n. rio y\nActualización Legislativa.\nÚltima Reforma P.O. No. 55, Sección IV, 30-Nov-2018\nARTÍCULO 19.- La Secretaría al resolver favorablemente la solicitud de un permiso, requerirá al peticionario para que dentro del término de diez días hábiles, contados a partir del día siguiente a la notificación de la resolución, exhiba la póliza de seguro en los términos previstos por la fracción IV del artículo 15, apercibiéndolo que de no hacerlo se negará la expedición del permiso, quedando a salvo su derecho a presentar nueva solicitud.\nArtículo Reformado\nARTÍCULO 20.- Exhibido en tiempo y forma los documentos señalados en el artículo anterior, la Secretaría deberá expedir y hacer entrega del original del permiso al peticionario mismo, debiéndola anexar al expediente respectivo.\nARTÍCULO 21.- El Permiso que se expida será personal e intransferible y con vigencia de un año.\nSECCIÓN TERCERA\nDE LA REVALIDACIÓN DEL PERMISO\nARTÍCULO 22.- El permisionario tiene la obligación de revalidar su permiso dentro de los treinta días anteriores a la fecha de su vencimiento, debiendo presentar ante la\nSecretaría lo siguiente:\nI.- Solicitud por escrito;\nII.- El permiso original sujeto a revalidación;\nIII.- Cubrir el costo que se establezca en la Ley de Ingresos del Estado para la realización del estudio de cumplimiento de los requisitos, referido en el artículo 12 de esta\nLey;\nIV.- El recibo original del refrendo de la póliza de seguro prevista en la fracción IV del artículo 15 de la Ley; y\nV.- Las demás que se establezcan en el Reglamento de la Ley.\nARTÍCULO 23.- La Secretaría, recibida la solicitud de revalidación, procederá a realizar el estudio de cumplimiento de requisitos y practicará las visitas de verificación que considere necesarias. anterior, la Secretaría lo requerirá para que exhiba los documentos o información omitida, otorgándole un plazo de cinco días hábiles para su cumplimiento; apercibiéndolo que de no hacerlo la Secretaría resolverá que se tiene por no presentada la solicitud, quedando a salvo su derecho a formular nueva solicitud.\nPárrafo Reformado\nArtículo Reformado\nLey que Establece las Bases de Operación de las Casas de Empeño Página 6\n. rio y\nActualización Legislativa.\nÚltima Reforma P.O. No. 55, Sección IV, 30-Nov-2018\nARTÍCULO 24.- La Secretaría contará con un plazo de diez días hábiles para resolver lo conducente, a partir de la presentación de la solicitud de revalidación, y en caso de que se hubiese requerido al peticionario, a partir del vencimiento del plazo concedido.\nLa Secretaría al resolver favorablemente la solicitud de revalidación, requerirá al peticionario para que dentro del término de cinco días hábiles contados a partir del día siguiente a la notificación de la resolución, exhiba comprobante de pago de obligaciones fiscales; apercibiéndolo que de no hacerlo se negará la expedición del nuevo permiso.\nPárrafo Reformado\nArtículo Reformado\nARTÍCULO 25.- Transcurrido el plazo a que se refiere el artículo 22 de esta Ley, se considerará extemporánea la solicitud de revalidación presentada, aplicándose por la\nSecretaría una multa administrativa de cincuenta a cien días de salario mínimo general vigente en la región; debiendo la Secretaría girar oficio a la Secretaría de Planeación y\nFinanzas de Gobierno del Estado, acompañándole copia certificada de la solicitud y del permiso vencido, para que proceda conforme a la facultad económica coactiva.\nARTÍCULO 26.- La presentación extemporánea de la solicitud de revalidación del permiso, será motivo suficiente para resolver negativamente, cuando se presente a partir del tercer mes del vencimiento del permiso.\nSECCIÓN CUARTA\nDE LA MODIFICACIÓN DEL PERMISO\nARTÍCULO 27.- La Secretaría podrá autorizar la modificación de un permiso, por las causas siguientes:\nI.- Por cambio de la razón social del permisionario;\nII.- Por cambio del nombre comercial de la casa de empeño;\nIII.- Por cambio de domicilio del establecimiento autorizado; y\nIV.- Las demás que se establezcan en el Reglamento de la Ley.\nARTÍCULO 28.- El permisionario deberá solicitar la modificación del permiso en un plazo que no exceda de cinco días hábiles, contados a partir de que se dé alguno de los supuestos previstos en el artículo que antecede; debiendo presentar:\nI.- Solicitud por escrito expresando la causa que motiva la petición;\nII.- El permiso original;\nIII.- Cubrir el costo que se establezca en la Ley de Ingresos del Estado, para la realización del estudio de cumplimiento de los requisitos, referido en el artículo 12 de esta\nLey;\nLey que Establece las Bases de Operación de las Casas de Empeño Página 7\n. rio y\nActualización Legislativa.\nÚltima Reforma P.O. No. 55, Sección IV, 30-Nov-2018\nIV.- En su caso, los documentos idóneos que acrediten la causa invocada;\nV.- Tratándose de cambio de domicilio, la constancia de uso de suelo y la de vigencia de autorización de ocupación, expedidas por la autoridad municipal correspondiente; y\nVI.- Las demás que determine el Reglamento.\nARTÍCULO 29.- La Secretaría recibida la solicitud de modificación procederá a realizar el estudio de cumplimiento de requisitos y practicará las visitas de verificación que considere necesarias.\nCuando el peticionario no cumpla con los requisitos establecidos en el artículo anterior, la Secretaría lo requerirá para que exhiba los documentos o información omitida, otorgándole un plazo de cinco días hábiles para su cumplimiento; apercibiéndolo que de no hacerlo la Secretaría resolverá que se tiene por no presentada la solicitud, quedando a salvo su derecho a formular nueva solicitud.\nPárrafo Reformado\nArtículo Reformado\nARTÍCULO 30.- La Secretaría contará con un plazo de diez días hábiles para resolver lo conducente, a partir de la presentación de la solicitud, y en caso de que se hubiese requerido al peticionario, a partir del vencimiento del plazo concedido.\nDe aprobarse la modificación se expedirá un nuevo permiso y se cancelará el anterior, dejando constancia de ello en el expediente respectivo.\nARTÍCULO 31.- Es obligación del permisionario, en los casos de modificación del permiso por cambio de domicilio, informar a los pignorantes mediante aviso en lugar visible del establecimiento que ocupaba; además de publicarlo en un diario de mayor circulación del municipio respectivo.\nSECCIÓN QUINTA\nDE LA REPOSICIÓN DEL PERMISO\nARTÍCULO 32.- El permisionario deberá solicitar la reposición del permiso ante la\nSecretaría, cuando éste hubiere sido extraviado, robado o sufrido deterioro grave.\nARTÍCULO 33.- Para obtener la reposición del permiso, el peticionario deberá satisfacer los siguientes requisitos:\nI.- Solicitud por escrito;\nII.- Exhibir el permiso original en los casos de deterioro grave;\nIII.- Exhibir constancia de robo o extravío expedida por el Ministerio Público; y\nLey que Establece las Bases de Operación de las Casas de Empeño Página 8\n. rio y\nActualización Legislativa.\nÚltima Reforma P.O. No. 55, Sección IV, 30-Nov-2018\nIV.- Cubrir el costo que se establezca en la Ley de Ingresos del Estado, para la realización del estudio de cumplimiento de los requisitos, referido en el artículo 12 de esta\nLey.\nARTÍCULO 34.- La Secretaría contará con un plazo de diez días hábiles para resolver lo conducente, a partir de la presentación de la solicitud de reposición.\nCAPÍTULO CUARTO\nDE LOS CONTRATOS\nARTÍCULO 35.- Los permisionarios deberán sujetar los contratos que celebren, a las formalidades que se establecen en esta Ley, debiendo contener los requisitos estipulados en la legislación federal aplicable a la celebración de contratos de mutuo con interés y garantía prendaria, así como también a las normas oficiales mexicanas sobre este tipo de servicio.\nArtículo Reformado\nARTÍCULO 36.- Las casas de empeño deberán adoptar las medidas indispensables para cerciorarse de la identidad de los pignorantes y su propiedad sobre los bienes pignorados, para lo cual requerirá factura o los documentos que los acrediten, así como el documento oficial con fotografía y comprobante de domicilio que amparen la identidad del pignorante.\nPárrafo Reformado\nEn caso de no contar el pignorante con la documentación que acredite la propiedad del bien pignorado, deberá emitir manifiesto, bajo protesta de decir verdad, en el que reconozca expresamente que es su legítimo e indiscutible propietario y señale cómo obtuvo la propiedad del bien.\nPárrafo Adicionado\nEl pignorante, que realice varias operaciones y estas lleguen a la etapa de comercialización, y las demásías, no sean reclamadas, se denominaran operación inusuales.\nPárrafo Adicionado\nArtículo Reformado\nARTÍCULO 37.- La casa de empeño deberá otorgar fianza ante la Secretaría, en caso que lesione intereses de los pignorantes y/o en caso de cierre operaciones, se hará válida la misma, cada año será requisito indispensable para que se otorgue el permiso.\nArtículo Reformado\nCAPÍTULO QUINTO\nDE LAS MEDIDAS CAUTELARES Y DE LAS SANCIONES\nLey que Establece las Bases de Operación de las Casas de Empeño Página 9\n. rio y\nActualización Legislativa.\nÚltima Reforma P.O. No. 55, Sección IV, 30-Nov-2018\nARTÍCULO 38.- Corresponde a la Secretaría, mediante la práctica de diligencias de inspección, supervisar y vigilar el cumplimiento de las disposiciones de esta Ley y su\nReglamento.\nCualquier infracción, será sancionada por la Secretaría en los términos previstos en esta Ley y su Reglamento.\nARTÍCULO 39.- Los permisionarios, quienes operen casas de empeño, sus representantes, o la persona con quien se entienda la diligencia de inspección que ordene la\nSecretaría, están obligados a permitir a los inspectores designados, el acceso al lugar o lugares objeto de la misma, la verificación de bienes y mercancías pignoradas, de los contratos, así como de los documentos de identificación personal de los pignorantes y de cualquier otro relacionado con su actividad.\nLas visitas de inspección y verificación deberán desarrollarse conforme a las normas previstas en el Título Cuarto de la Ley del Procedimiento para los Actos de la Administración\nPública del Estado.\nARTÍCULO 40.- Las infracciones a las disposiciones de esta Ley y su Reglamento, se sancionarán con:\nI. Multa de cincuenta a quinientos días de salario mínimo general vigente en la región;\nII. Suspensión temporal del permiso, hasta por treinta días naturales; o\nIII. Cancelación del permiso.\nARTÍCULO 41.- Se impondrá multa al permisionario, cuando:\nI. Opere la casa de empeño fuera del horario establecido en esta Ley;\nII. No coloque el permiso, dentro del establecimiento de manera permanente y visible;\nIII. Celebre en la casa de empeño, contratos diversos al exhibido al momento de la solicitud del permiso;\nIV. No cumpla con el pago de obligaciones fiscales y comerciales;\nV. Omita dar cumplimiento a lo dispuesto en el artículo 31 de esta Ley;\nVI. Omita anexar al contrato, copia del documento oficial con fotografía y comprobante de domicilio que acredite la identidad del pignorante, factura o documento con que se acredite la propiedad del bien pignorado, o bien el manifiesto a que se refiere esta Ley;\nFracción Reformada\nVII. Se oponga sin causa justificada, a la práctica de una diligencia de inspección;\nLey que Establece las Bases de Operación de las Casas de Empeño Página 10\n. rio y\nActualización Legislativa.\nÚltima Reforma P.O. No. 55, Sección IV, 30-Nov-2018\nVIII. Se oponga sin causa justificada, a exhibir al inspector designado, el permiso, la constancia de revalidación o de modificación del permiso, así como el recibo de pago de obligaciones fiscales y de cualquier otro documento relacionado con sus operaciones;\nIX. Solicite extemporáneamente la revalidación del permiso, dentro de los dos meses siguientes a su vencimiento, o\nX. Por las demás infracciones a las disposiciones de esta Ley, que no ameriten la suspensión o cancelación del permiso.\nArtículo Reformado\nARTÍCULO 42.- Se impondrá suspensión temporal al permisionario, cuando:\nI.- No solicite la modificación del permiso en los términos previstos en esta Ley y el\nReglamento; o\nII.- Acumule una multa dentro de un período de veinticuatro meses, y no cuente con una operación de tres años continuos, celebrando contratos de mutuo con interés y garantía prendaria, y no sea de acreditada solvencia.\nArtículo Reformado\nARTÍCULO 43.- Se impondrá cancelación del permiso, cuando:\nI.- El permisionario acumule dos sanciones de suspensión temporal dentro de un período de veinticuatro meses; o\nII.- El permisionario, su representante legal, los miembros del consejo de administración o el administrador único, cometan acciones delictivas con motivo de las actividades reguladas por esta Ley y su Reglamento, previa resolución judicial ejecutoriada.\nEn estos casos, el propietario de la casa de empeño, será el depositario de los bienes en prenda, quedando bajo su más estricta responsabilidad la guarda y custodia de los mismos.\nAsimismo, previa autorización de la Secretaría, el propietario de la casa de empeño sólo podrá continuar con las operaciones relativas a la devolución de prendas.\nARTÍCULO 44.- Para la imposición de las sanciones a que se refiere el artículo 40 de esta Ley, la Secretaría notificará al permisionario el acuerdo de inicio del procedimiento, que contendrá:\nI.- Los motivos que dan origen al procedimiento;\nII.- La infracción que de manera presuntiva se le atribuye;\nIII.- Los elementos de prueba existentes;\nLey que Establece las Bases de Operación de las Casas de Empeño Página 11\n. rio y\nActualización Legislativa.\nÚltima Reforma P.O. No. 55, Sección IV, 30-Nov-2018\nIV.- Su derecho a contestar por escrito, formulando alegatos y ofreciendo las pruebas que respalden su defensa, en un término de cinco días hábiles contados a partir del día siguiente en que surta efectos la notificación del acuerdo de inicio; y\nV.- Su derecho a defenderse por sí o hacerse representar o patrocinar por uno o más abogados procuradores.\nRecibido el escrito a que se refiere la fracción IV y desahogadas las pruebas, si las hubiere, o transcurrido el término previsto en este artículo, la Secretaría procederá a resolver lo conducente dentro de un término de diez días hábiles, debiendo notificar a los interesados, la resolución respectiva.\nLas notificaciones que deban efectuarse en el procedimiento, se realizarán de conformidad a lo dispuesto en la Ley del Procedimiento para los Actos de la Administración\nPública del Estado.\nARTÍCULO 45.- Iniciado el procedimiento, la autoridad, a fin de asegurar la eficacia de la resolución que pudiera recaer, o para salvaguardar la seguridad pública, podrá adoptar las medidas cautelares siguientes:\nI.- Clausura temporal; y\nII.- Derogada.\nFracción Derogada\nLas medidas cautelares no prejuzgan sobre la materia de las imputaciones atribuidas en el procedimiento a que se refiere el artículo anterior, y cesarán cuando así lo determine la\nSecretaría o cuando concluya el procedimiento.\nTratándose de la suspensión temporal, el propietario de la casa de empeño será el depositario de los bienes en prenda, quedando bajo su más estricta responsabilidad la guarda y custodia de los mismos.\nArtículo Reformado\nARTÍCULO 46.- La Secretaría, para la imposición de las sanciones, deberá tomar en consideración:\nI. Las circunstancias socioeconómicas del infractor.\nII. El carácter intencional o negligente de la acción u omisión constitutiva de la infracción.\nIII. La conveniencia de evitar prácticas tendientes a contravenir las disposiciones de esta Ley y su Reglamento; y\nIV. La reincidencia.\nLey que Establece las Bases de Operación de las Casas de Empeño Página 12\n. rio y\nActualización Legislativa.\nÚltima Reforma P.O. No. 55, Sección IV, 30-Nov-2018\nPara los efectos previstos en este Capítulo, habrá reincidencia cuando el permisionario acumule dos sanciones dentro del período de veinticuatro meses contado a partir del día siguiente de la primera.\nARTÍCULO 47.- Las multas a que alude esta Ley, se harán efectivas por conducto de la Secretaría de Planeación y Finanzas, conforme a las formalidades del Código Fiscal del\nEstado.\nARTÍCULO 48.- La Secretaría, para la ejecución de sus determinaciones, podrá hacer uso de las medidas necesarias, incluyendo el auxilio de la fuerza pública.\nARTÍCULO 49.- La Secretaría podrá clausurar en forma inmediata y sin que medie procedimiento, la casa de empeño que opere sin el permiso regulado en esta Ley.\nEl propietario de la casa de empeño, será el depositario de los bienes en prenda, quedando bajo su más estricta responsabilidad la guarda y custodia de los mismos.\nEn este caso, previa autorización de la Secretaría, el propietario de la casa de empeño sólo podrá continuar con las operaciones relativas a la devolución de prendas.\nCAPÍTULO SEXTO\nDE LOS RECURSOS\nARTÍCULO 50.- En caso de inconformidad por la aplicación de alguna de las disposiciones o resoluciones contenidas en esta Ley y su Reglamento, los interesados afectados podrán interponer los recursos en los términos de la Ley del Procedimiento para los actos de la Administración Pública del Estado.\nArtículo Reformado\nARTÍCULOS TRANSITORIOS\nPRIMERO. La presente Ley entrará en vigor al día siguiente de su publicación en el\nPeriódico Oficial del Estado.\nSEGUNDO.- Se abroga la Ley que establece las bases de operación de las casas de empeño del Estado de Baja California, publicada en el Periódico Oficial del Estado No. 45, TERCERO.- El Ejecutivo del Estado dentro de los sesenta días siguientes a la entrada en vigor de esta Ley, deberá expedir las disposiciones reglamentarias correspondientes.\nCUARTO.- Dentro de los cuarenta y cinco días siguientes a la entrada en vigor del\nReglamento de esta Ley, los peticionarios de expedición, revalidación y modificación de permisos, cuya solicitud se encuentre pendiente de resolución, deberán adecuarla conforme a las disposiciones de esta Ley y de su Reglamento. De no atenderse lo anterior, la solicitud se tendrá por no presentada.\nLey que Establece las Bases de Operación de las Casas de Empeño Página 13\n. rio y\nActualización Legislativa.\nÚltima Reforma P.O. No. 55, Sección IV, 30-Nov-2018\nQUINTO.- Los permisos expedidos conforme a la normatividad que se abroga seguirán vigentes, debiendo los permisionarios solicitar la revalidación dentro de los treinta días anteriores a la fecha de su vencimiento, conforme a las disposiciones de la presente\nLey.\nSEXTO.- Dentro de los treinta días siguientes a la entrada en vigor del presente\nDecreto, los permisionarios deberán presentar ante la Secretaría, el libro de registro de contratos a que se refiere el artículo 37 de esta Ley para su autorización, y exhibir el contrato utilizado para la celebración de los prestamos ofertados al público, debidamente registrado ante la Procuraduría Federal del Consumidor.\nSÉPTIMO.- Se derogan todas las disposiciones que se opongan al presente Decreto.\nDADO en el Salón de Sesiones “Lic. Benito Juárez García” del H. Poder Legislativo del Estado de Baja California, en la Ciudad de Mexicali, B.C., a los dieciséis días del mes de agosto del año dos mil diez.\nDIP. JUAN MANUEL GASTÉLUM BUENROSTRO\nPRESIDENTE\n(RÚBRICA)\nDIP. CARLOS ALONSO ANGULO RENTERIA\nSECRETARIO\n(RÚBRICA)\nDE CONFORMIDAD CON LO DISPUESTO POR LAFRACCION I DEL ARTICULO 49\nDE LA CONSTITUCION POLITICA DEL ESTADO, IMPRÍMASE Y PUBLIQUESE.\nMEXICALI, BAJA CALIFORNIA, A LOS VEINTICUATRO DIAS DEL MÊS DE AGOSTO DEL\nAÑO DOS MIL DIEZ.\nJOSE GUADALUPE OSUNA MILLAN\nGOBERNADOR DEL ESTADO\n(RÚBRICA)\nCUAUHTEMOC CARDONA BENAVIDEZ\nSECRETARIO GENERAL DE GOBIERNO\n(RÚBRICA)\nLey que Establece las Bases de Operación de las Casas de Empeño Página 14\n. rio y\nActualización Legislativa.\nÚltima Reforma P.O. No. 55, Sección IV, 30-Nov-2018\nArtículo 8.- Fue reformado mediante Decreto No. 84, publicado en el Periódico Oficial\nNo. 36, de fecha 29 de julio de 2011, Sección I, Tomo CXVIII, expedido por la H. XX\nLegislatura, siendo Gobernador Constitucional el C. José Guadalupe Osuna Millán 20072013;\nArtículo 15.- Fue reformado mediante Decreto No. 84, publicado en el Periódico\nOficial No. 36, de fecha 29 de julio de 2011, Sección I, Tomo CXVIII, expedido por la H. XX\nLegislatura, siendo Gobernador Constitucional el C. José Guadalupe Osuna Millán 20072013;\nArtículo 18.- Fue reformado mediante Decreto No. 84, publicado en el Periódico\nOficial No. 36, de fecha 29 de julio de 2011, Sección I, Tomo CXVIII, expedido por la H. XX\nLegislatura, siendo Gobernador Constitucional el C. José Guadalupe Osuna Millán 20072013;\nArtículo 19.- Fue reformado mediante Decreto No. 84, publicado en el Periódico\nOficial No. 36, de fecha 29 de julio de 2011, Sección I, Tomo CXVIII, expedido por la H. XX\nLegislatura, siendo Gobernador Constitucional el C. José Guadalupe Osuna Millán 20072013;\nArtículo 23.- Fue reformado mediante Decreto No. 84, publicado en el Periódico\nOficial No. 36, de fecha 29 de julio de 2011, Sección I, Tomo CXVIII, expedido por la H. XX\nLegislatura, siendo Gobernador Constitucional el C. José Guadalupe Osuna Millán 20072013;\nArtículo 24.- Fue reformado mediante Decreto No. 84, publicado en el Periódico\nOficial No. 36, de fecha 29 de julio de 2011, Sección I, Tomo CXVIII, expedido por la H. XX\nLegislatura, siendo Gobernador Constitucional el C. José Guadalupe Osuna Millán 20072013;\nArtículo 29.- Fue reformado mediante Decreto No. 84, publicado en el Periódico\nOficial No. 36, de fecha 29 de julio de 2011, Sección I, Tomo CXVIII, expedido por la H. XX\nLegislatura, siendo Gobernador Constitucional el C. José Guadalupe Osuna Millán 20072013;\nArtículo 35.- Fue reformado mediante Decreto No. 84, publicado en el Periódico\nOficial No. 36, de fecha 29 de julio de 2011, Sección I, Tomo CXVIII, expedido por la H. XX\nLegislatura, siendo Gobernador Constitucional el C. José Guadalupe Osuna Millán 20072013;\nArtículo 36.- Fue reformado mediante Decreto No. 84, publicado en el Periódico\nLegislatura, siendo Gobernador Constitucional el C. José Guadalupe Osuna Millán 20072013; fue reformado por Decreto No. 282, publicado en el Periódico Oficial No. 55, de fecha\nXXII, siendo Gobernador Constitucional el C. Francisco Arturo Vega de Lamadrid 2013-2019;\nLey que Establece las Bases de Operación de las Casas de Empeño Página 15\n. rio y\nActualización Legislativa.\nÚltima Reforma P.O. No. 55, Sección IV, 30-Nov-2018\nArtículo 37.- Fue reformado mediante Decreto No. 84, publicado en el Periódico\nOficial No. 36, de fecha 29 de julio de 2011, Sección I, Tomo CXVIII, expedido por la H. XX\nLegislatura, siendo Gobernador Constitucional el C. José Guadalupe Osuna Millán 20072013;\nArtículo 41.- Fue reformado mediante Decreto No. 84, publicado en el Periódico\nOficial No. 36, de fecha 29 de julio de 2011, Sección I, Tomo CXVIII, expedido por la H. XX\nLegislatura, siendo Gobernador Constitucional el C. José Guadalupe Osuna Millán 20072013; fue reformado por Decreto No. 282, publicado en el Periódico Oficial No. 55, de fecha\n30 de noviembre de 2018, Tomo CXXV, Sección IV, expedido por la Honorable Legislatura\nXXII, siendo Gobernador Constitucional el C. Francisco Arturo Vega de Lamadrid 2013-2019;\nArtículo 42.- Fue reformado mediante Decreto No. 84, publicado en el Periódico\nOficial No. 36, de fecha 29 de julio de 2011, Sección I, Tomo CXVIII, expedido por la H. XX\nLegislatura, siendo Gobernador Constitucional el C. José Guadalupe Osuna Millán 20072013;\nArtículo 45.- Fue reformado mediante Decreto No. 84, publicado en el Periódico\nLegislatura, siendo Gobernador Constitucional el C. José Guadalupe Osuna Millán 20072013;\nArtículo 50.- Fue reformado mediante Decreto No. 84, publicado en el Periódico\nLegislatura, siendo Gobernador Constitucional el C. José Guadalupe Osuna Millán 20072013;\nLey que Establece las Bases de Operación de las Casas de Empeño Página 16\n. rio y\nActualización Legislativa.\nÚltima Reforma P.O. No. 55, Sección IV, 30-Nov-2018\nARTICULO UNICO TRANSITORIO DEL DECRETO No. 84, POR EL QUE SE\nAPRUEBA LA REFORMA A LOS ARTÍCULOS 8, 15 FRACCION VIII, 18, 19, 23, 24, 29, 35,\n36, 37, 41, 42, 45 Y 50, PUBLICADO EN EL PERIODICO OFICIAL No. 36, TOMO CXVIII,\nDE FECHA 15 DE JULIO DE 2011, SECCION I, EXPEDIDO POR LA H. XX LEGISLATURA,\nSIENDO GOBERNADOR CONSTITUCIONAL EL C. JOSE GUADALUPE OSUNA MILLAN\n2007-2013.\nTRANSITORIOS\nPRIMERO. El presente Decreto iniciara su vigencia el día siguiente al de su publicación en el Periódico Oficial del Estado de Baja California.\nSEGUNDO. El Ejecutivo del Estado, tendrá un plazo de 45 días naturales, a partir de la publicación del Presente Decreto, para realizar los cambios a los reglamentos aplicables.\nDADO en el Salón de Sesiones “Lic. Benito Juárez García” del H. Poder Legislativo del Estado de Baja California, en la Ciudad de Mexicali, B.C., a los trece días del mes de julio del año dos mil once.\nDIP. CARLOS MURGUÍA MEJÍA\nDIPUTADO PRESIDENTE\n(RÚBRICA)\nDIP. VIRGINIA NORIEGA RÍOS\nDIPUTADA SECRETARIA\n(RÚBRICA)\nDE CONFORMIDAD CON LO DISPUESTO POR LA FRACCION I DEL ARTÍCULO 49\nMEXICALI, BAJA CALIFORNIA, A LOS 20 DÍAS DEL MES DE JULIO DEL AÑO DOS\nMIL ONCE.\nGOBERNADOR DEL ESTADO\nJOSE GUADALUPE OSUNA MILLÁN\n(RÚBRICA)\nCUAUHTEMOC CARDONA BENAVIDEZ\nSECRETARIO GENERAL DE GOBIERNO\n(RÚBRICA)\nLey que Establece las Bases de Operación de las Casas de Empeño Página 17\n. rio y\nActualización Legislativa.\nÚltima Reforma P.O. No. 55, Sección IV, 30-Nov-2018\nARTÍCULO PRIMERO TRANSITORIO DEL DECRETO No. 282, POR EL QUE SE\nREFORMA EL ARTÍCULO 36, FRACCIÓN VIII DEL ARTÍCULO 41, PUBLICADO EN EL\nPERIÓDICO OFICIAL No. 55, SECCION IV, TOMO CXXV, DE FECHA 30 DE NOVIEMBRE\nDE 2018, EXPEDIDO POR LA H. XXII LEGISLATURA, SIENDO GOBERNADOR\nCONSTITUCIONAL EL C. FRANCISCO ARTURO VEDA DE LAMADRID 2013-2019.\nARTÍCULOS TRANSITORIOS\nÚNICO.- La presente Reforma entrará en vigor el día siguiente de su publicación en el\nPeriódico Oficial del Estado de Baja California.\nDADO en el Salón de Sesiones “Lic. Benito Juárez García” del H. Poder Legislativo del Estado de Baja California, en la Ciudad de Mexicali, B.C., a los veinticinco días del mes de octubre del año dos mil dieciocho.\nDIP. ROCÍO LÓPEZ GOROSAVE\nPRESIDENTA\n(RÚBRICA)\nDIP. MÓNICA HERNÁNDEZ ÁLVAREZ\nSECRETARIA\n(RÚBRICA)\nDE CONFORMIDAD CON LO DISPUESTO POR LA FRACCIÓN I DEL ARTÍCULO 49\nMEXICALI, BAJA CALIFORNIA, A LOS TREINTA DÍAS DEL MES DE NOVIEMBRE\nDEL AÑO DOS MIL DIECIOCHO.\nFRANCISCO ARTURO VEGA DE LAMADRID\nGOBERNADOR DEL ESTADO\n(RÚBRICA)\nFRANCISCO RUEDA GÓMEZ\nSECRETARIO GENERAL DE GOBIERNO\n(RÚBRICA)\nLey que Establece las Bases de Operación de las Casas de Empeño Página 18",
  "ordenamiento": "REGLAMENTO",
  "jurisdiccion": "BAJA CALIFORNIA",
  "fuente_oficial": "Periódico Oficial",
  "FECHA PER OFIC": "2018/11/30",
  "ESTATUS": "VIGENTE",
  "TOMO": "TOMO_IV",
  "URL": "https://www.congresobc.gob.mx/Documentos/ProcesoParlamentario/Leyes/TOMO_IV/30112018_LEYCASAEMPE%C3%91O.PDF",
  "es_escaneado": false,
  "tiene_tablas": false,
  "materia": [
    "propiedad",
    "notarial",
    "registro civil"
  ]
}