{
  "titulo": "Ley DE ADQUISICIONES, ARRENDAMIENTOS y SERVICIOS PARA EL ESTADO DE BAJA CALIFORNIA",
  "Contenido": "LEY DE ADQUISICIONES, ARRENDAMIENTOS Y SERVICIOS\nPARA EL ESTADO DE BAJA CALIFORNIA\nPublicado en el Periódico Oficial No. 45,\nCAPÍTULO PRIMERO\nDISPOSICIONES GENERALES\nARTÍCULO 1.- La presente Ley es de orden público y tiene por objeto regular las\nBaja California, correspondientes a la planeación, programación, presupuestación, contratación, gasto y control de las adquisiciones, arrendamientos y servicios que realice:\nPárrafo Reformado\nI.- El Poder Ejecutivo;\nII.- El Poder Legislativo;\nIII.- El Poder Judicial;\nIV.- Las personas de derecho público de carácter estatal con autonomía derivada de\nLos municipios, en el ámbito de su competencia, observarán las bases previstas en esta Ley.\nArtículo Reformado\nARTÍCULO 2.- Los contratos que se celebren entre dos o más entes públicos a que se refiere el artículo anterior, no estarán sujetos a la aplicación de esta Ley; sin embargo, dichos actos quedarán sujetos a este ordenamiento, cuando la parte que deba entregar el bien o prestar el servicio, no tenga capacidad para hacerlo por sí misma y contrate un tercero para su realización.\nLas adquisiciones, arrendamientos y servicios con cargo total o parcial a fondos federales conforme a los convenios o acuerdos celebrados entre el Ejecutivo Federal y esta\nEntidad Federativa, con la participación que en su caso corresponda a los Municipios interesados, estarán sujetos a las disposiciones federales correspondientes; siempre y cuando dichos fondos conserven su naturaleza en los términos del Presupuesto de Egresos de la Federación.\nSe sujetarán a lo dispuesto en esta Ley, las aportaciones registradas en las Leyes como ingresos propios, en los que la administración y ejercicio de los mismos, sean indistintamente en el Presupuesto de Egresos de la Federación, en el Capítulo V de la Ley de Coordinación Fiscal o en el ordenamiento jurídico respectivo.\nLa Unidad Administrativa, podrá promover contratos marco, previa determinación de las características técnicas y de calidad acordadas, mediante los cuales éstas adquieran bienes, arrendamientos o servicios, a través de la suscripción de convenios específicos.\nLey de Adquisiciones, Arrendamientos y Servicios para el Estado de Baja California. Página 1\nPárrafo Adicionado\nPárrafo Reformado\nArtículo Reformado\nARTÍCULO 3.- Para los efectos de esta Ley se entenderá por:\nI.- Ley.- La Ley de Adquisiciones, Arrendamientos y Servicios para el Estado de Baja\nCalifornia.\nII.- Reglamento.- El reglamento de esta Ley;\nIII.- Unidad Administrativa.- En el Poder Ejecutivo y Poder Legislativo, a la Oficialía\nMayor; en los demás sujetos obligados, la que posea atribuciones para adquirir y contratar bienes y servicios.\nIV.- Contraloría.- La autoridad que ejerza atribuciones de control y evaluación administrativa interna en cada uno de los sujetos obligados;\nV.- Órgano.- En el Poder Ejecutivo del Gobierno del Estado de Baja California, conjunto de Dependencias y Entidades que componen la Administración Pública\nCentralizada y la paraestatal; en los demás sujetos obligados, los que señale su normatividad interna;\nFracción Reformada\nVI.- Tesorería.- En el Poder Ejecutivo, la Secretaría de Hacienda; y en los demás sujetos obligados, la que ejerza atribuciones para efectuar pagos;\nFracción Reformada\nVII.- Sujetos obligados:\na) Los Poderes del Estado: Ejecutivo, Legislativo y Judicial;\nb) Los órganos constitucionales autónomos;\nc) Los municipios de la entidad, según lo dispuesto en el Capítulo Octavo de la Ley.\nVIII.- El Comité.- El órgano de cada uno de los sujetos obligados, con atribuciones para conocer de las adquisiciones, arrendamientos y servicios que deban adjudicarse o contratarse en los términos de la Ley;\nIX.- Proveedor.- Persona que celebre contrato de adquisiciones, arrendamientos o servicios;\nX.- Licitante.- Persona que participe en el procedimiento de licitación pública o de invitación;\nXI.- Fabricante o productor regional.- Son las personas físicas o morales que lleven a cabo procesos de elaboración, producción, transformación, reparación, industrialización u otros similares, de los cuales se obtengan productos terminados o semiterminados; siempre y cuando tengan el asiento principal de sus negocios y su domicilio fiscal, al menos con un año de antigüedad en el Estado;\nLey de Adquisiciones, Arrendamientos y Servicios para el Estado de Baja California. Página 2\nXII.- Productos o mercancías regionales.- Son los bienes y servicios desarrollados o transformados por fabricantes o productores regionales;\nXIII.- Distribuidor regional.- Es la persona física o moral que distribuye productos regionales o foráneos, del tipo específico a que se refiere el procedimiento de adquisición, arrendamiento o servicio respectivo, siempre y cuando tengan el asiento principal de sus negocios y su domicilio fiscal al menos con un año de antigüedad en el Estado;\nFracción Reformada\nXIV.- Medios electrónicos.- Los medios de comunicación electrónica que determine y autorice la unidad administrativa o la contraloría, en su ámbito de competencia, en los casos previstos por esta Ley;\nFracción Reformada\nXV.- Comisión.- La Comisión Interinstitucional prevista en la Ley de Asociaciones\nPúblico-Privadas para el Estado de Baja California;\nFracción Reformada\nXVI.- Sustentabilidad Ambiental.- La administración eficiente y racional de los recursos naturales, de manera tal que sea posible mejorar el bienestar de la población actual sin comprometer la calidad de vida de las generaciones futuras;\nFracción Reformada\nXVII.- Adquisición Sustentable.- Es la compra o adquisición de cualquier bien o servicio que por su característica, composición y propiedades, resulten favorable a la preservación y cuidado del medio ambiente;\nFracción Adicionada\nFracción Reformada\nXVIII.- Administrador del contrato.- La Unidad Administrativa o la persona servidora pública designada por la misma, encargada de administrar, así como de dar seguimiento y verificación al cumplimiento de la contratación;\nFracción Adicionada\nXIX.- Caso fortuito o fuerza mayor.- El acontecimiento proveniente del hombre o de la naturaleza, caracterizado por ser imprevisible, inevitable, irresistible, insuperable, así como inimputable y ajeno a la voluntad de las partes contratantes, de los órganos o de los sujetos obligados;\nFracción Adicionada\nXX.- Compra consolidada.- Aquellas que efectúen en un solo contrato, dos o más sujetos de esta ley o bien, entre dos o más órganos solicitantes;\nFracción Adicionada\nXXI.- Contrato marco.- Instrumento que celebra la Unidad Administrativa, conjuntamente con la Contraloría, y uno o más posibles proveedores, mediante los cuales se establecen de manera general las especificaciones técnicas y de calidad, alcances, precios y condiciones derivadas de la investigación de mercado;\nFracción Adicionada\nXXII.- Contratos integrales.- Aquel que permita adquirir, arrendar bienes y contratar servicios en un mismo acto jurídico;\nLey de Adquisiciones, Arrendamientos y Servicios para el Estado de Baja California. Página 3\nFracción Adicionada\nXXIII.- Convocante.- Al Comité o Subcomité de Adquisiciones, arrendamientos y\nServicios, así como aquellos sujetos obligados identificados por la Unidad Administrativa, responsables de agotar el procedimiento de contratación en los términos de la Ley;\nFracción Adicionada\nXXIV.- Entidades paraestatales: Los organismos descentralizados, las empresas de participación estatal mayoritaria y minoritaria y los fideicomisos públicos que aluden los artículos 2, fracción VIII, y 52 de la Ley Orgánica del Poder Ejecutivo del Estado de Baja\nCalifornia;\nFracción Adicionada\nXXV.- Investigación de mercado.- La verificación de la existencia de bienes, arrendamientos o servicios, de proveedores, y del precio estimado sobre los mismos, basado en la información que se obtenga de conformidad con las disposiciones contenidas en la presente Ley; y,\nFracción Adicionada\nXXVI.- Precio no aceptable.- Es aquel que derivado de la investigación de mercado realizada, resulte superior en un diez por ciento al ofertado respecto del que se observa en dicha investigación o en su defecto, el de las ofertas presentadas en un procedimiento de contratación de adquisiciones, arrendamientos y/o servicios\nFracción Adicionada\nArtículo Reformado\nARTÍCULO 4.- Para los efectos de la Ley, entre las adquisiciones, arrendamientos y servicios, quedan comprendidos:\nI.- Las adquisiciones y arrendamientos de bienes muebles;\nII.- Las adquisiciones de bienes muebles que deban incorporarse, adherirse o destinarse a un inmueble, necesarios para la realización de las obras públicas por administración directa, o los que suministren las unidades administrativas, de acuerdo a lo pactado en los contratos de obras;\nIII.- Las adquisiciones de bienes muebles que incluyan la instalación, por parte del proveedor, en inmuebles de los órganos, cuando su precio sea superior al de su instalación;\nIV.- La contratación de servicios relativos a bienes muebles que se encuentren incorporados o adheridos a inmuebles, cuyo mantenimiento no implique modificación alguna al propio inmueble, y sea prestado por persona cuya actividad comercial corresponda al servicio requerido;\nV.- La reconstrucción y mantenimiento de bienes muebles;\nVI.- La contratación de seguros, así como los servicios de transportación, limpieza y vigilancia;\nVII.- La contratación de arrendamiento financiero de bienes muebles;\nLey de Adquisiciones, Arrendamientos y Servicios para el Estado de Baja California. Página 4\nVIII.- La contratación de servicios profesionales, consultorías, asesorías, estudios e investigaciones, excepto la contratación de servicios personales bajo el régimen de honorarios;\nIX.- La contratación de proyectos derivados de la Ley de Asociaciones PúblicoPrivadas para el Estado de Baja California;\nFracción Reformada\nX.- La adquisición y arrendamiento de bienes intangibles;\nFracción Adicionada\nXI.- La contratación de proyectos integrales; y,\nFracción Adicionada\nXII.- En general las adquisiciones, arrendamientos y servicios de cualquier naturaleza cuya prestación genere una obligación de pago, cuando no se encuentren regulados en forma específica por otras disposiciones legales.\nFracción Recorrida\nArtículo Reformado\nARTÍCULO 5.- Será responsabilidad de los sujetos obligados mantener adecuada y satisfactoriamente asegurados los bienes con que cuenten, en los términos que disponga la unidad administrativa; excepto cuando la naturaleza de los bienes o el tipo de riesgo a los que están expuestos, el costo del aseguramiento represente una erogación que no guarde relación directa con el beneficio que pudiera obtenerse. La unidad administrativa autorizará previamente esta excepción.\nARTÍCULO 6.- El gasto de las adquisiciones, arrendamientos y servicios se sujetará, en su caso, a las disposiciones específicas de los presupuestos anuales de egresos, así como a lo previsto en la Ley de Presupuesto y Ejercicio del Gasto Público del Estado de\nBaja California y demás disposiciones aplicables.\nArtículo Reformado\nARTÍCULO 7.- La unidad administrativa, la tesorería y la contraloría, en las materias de su competencia, estarán facultadas para interpretar la Ley y su Reglamento, así como para dictar las normas y políticas que sean necesarias para su adecuado cumplimiento, dichas normas y políticas deberán publicarse en el Periódico Oficial del Estado de Baja\nCalifornia.\nARTÍCULO 8.- En igualdad de condiciones, siempre se preferirá a los fabricantes y distribuidores regionales de productos o mercancías regionales sobre los foráneos, favorables a la preservación y cuidado del medio ambiente. Se considera que existe igualdad de condiciones, cuando la diferencia entre los precios propuestos no sea mayor del cinco por ciento y hasta 10 por ciento.\nPárrafo Reformado\nEconomía e Innovación en su respectivo ámbito de competencia, dictará las disposiciones\nLey de Adquisiciones, Arrendamientos y Servicios para el Estado de Baja California. Página 5 regionales, especialmente de las micro, pequeñas y medianas empresas, las que deberán observar las unidades administrativas.\nPárrafo Reformado\nArtículo Reformado\nARTÍCULO 9.- En materia de adquisiciones, arrendamientos y servicios, los titulares de las dependencias y entidades observarán los criterios de modernización, desarrollo administrativo y sobre todo de austeridad y ahorro en el gasto público, que establezca la unidad administrativa.\nEn la selección, adquisición y arrendamiento de los equipos de computación, relacionados con el Sistema Estatal de Informática, los titulares de las dependencias y entidades, tendrán la obligación de incluir las especificaciones técnicas relacionadas a las soluciones tecnológicas que impidan el acceso de cualquier persona a sitios de Internet con contenido sexual o erótico, no educativo.\nArtículo Reformado\nARTÍCULO 10.- En lo no previsto por la Ley y las disposiciones que de ella deriven, serán aplicables supletoriamente el Código Civil y de Procedimientos Civiles, ambos para el\nEstado de Baja California.\nARTÍCULO 11.- No se podrá financiar a proveedores la adquisición o arrendamiento de bienes o la prestación de servicios, cuando éstos vayan a ser objeto de contratación. No se considerará como operación de financiamiento, el otorgamiento de anticipos, los cuales en todo caso, deberán garantizarse en los términos del artículo 47 de esta Ley.\nLa tesorería podrá autorizar el pago de suscripciones, seguros o de otros servicios, en los que no sea posible pactar que su costo sea cubierto después de que la prestación del servicio se realice.\nNo procederá el pago de anticipos y, por ello, no deberá realizarse pago alguno antes de recibir los servicios derivados de los proyectos de Asociación Público-Privada a que se refiere la ley de la materia.\nArtículo Reformado\nARTÍCULO 12.- Las controversias que se susciten con motivo de la interpretación o aplicación de la Ley, o de los contratos celebrados con base en ella, serán resueltas por las autoridades competentes.\nLos actos, contratos y convenios que se celebren en contravención a lo dispuesto por la Ley, serán nulos previa declaración de autoridad competente.\nARTÍCULO 13.- La unidad administrativa mediante disposiciones de carácter general determinará los bienes y servicios de uso generalizado que, en forma consolidada podrá adquirir, arrendar o contratar, con objeto de obtener las mejores condiciones en cuanto a calidad, precio, oportunidad y protección al medio ambiente.\nPárrafo Reformado expedientes respectivos para efectos de simplificación administrativa, registrándolos y\nLey de Adquisiciones, Arrendamientos y Servicios para el Estado de Baja California. Página 6 clasificándolos por el giro a que se dediquen, conforme a los criterios y procedimientos que se fijen en el Reglamento.\nArtículo Reformado\nCAPÍTULO SEGUNDO\nDE LA PLANEACIÓN, PROGRAMACIÓN Y PRESUPUESTACIÓN\nARTÍCULO 14.- En la elaboración de los programas de adquisiciones, arrendamientos y servicios, los sujetos obligados, en lo que les resulte aplicable, deberán ajustarse a:\nI.- Los objetivos y prioridades del Plan Estatal de Desarrollo, a los Planes Municipales de Desarrollo, así como a las previsiones contenidas en sus programas anuales, sectoriales e institucionales;\nII.- Los objetivos, metas y previsiones de recursos establecidos en los presupuestos de egresos que corresponda;\nIII.- A las disposiciones establecidas sobre la materia, en la Ley de Presupuesto y\nEjercicio del Gasto Público del Estado de Baja California.\nFracción Reformado\nArtículo Reformado\nARTÍCULO 15.- Los órganos que requieran servicios profesionales, de consultorías, asesorías, estudios e investigaciones, o servicios de difusión, previamente verificarán si en sus archivos o, en su caso, en los de la coordinadora del sector correspondiente, existen trabajos sobre la materia o cuenta con personal adscrito que realice funciones o trabajos semejantes. De advertirse su existencia y de comprobar que los mismos satisfacen sus requerimientos, no procederá su contratación, con excepción de aquellos trabajos que sean necesarios para su adecuación, actualización o complemento.\nA fin de cumplimentar lo anterior, los interesados deberán remitir a la unidad administrativa una descripción suscinta del objeto de los contratos que en estas materias se pretendan celebrar, así como el programa de trabajo, fechas de entrega, productos y la demás información que se requiera.\nPara la contratación de servicios profesionales, de consultorías, asesorías, estudios e investigaciones, o servicios de difusión, la unidad administrativa requerirá de la autorización escrita del titular del órgano solicitante, así como manifestación del responsable del área respectiva, de que no se cuenta con personal capacitado o disponible para su realización.\nEn caso de proceder la contratación de los servicios previstos en el presente artículo, con la periodicidad que se establezca en el contrato.\nArtículo Reformado\nARTÍCULO 16.- Los órganos formularán sus programas anuales de adquisiciones, arrendamientos y servicios, y los que comprendan más de un ejercicio presupuestal, así como sus respectivos presupuestos, considerando:\nI.- Las acciones previas, las de ejecución y las posteriores a la realización de dichas operaciones;\nLey de Adquisiciones, Arrendamientos y Servicios para el Estado de Baja California. Página 7\nII.- Los objetivos y metas a corto, mediano y largo plazo;\nIII.- La calendarización física y financiera de los recursos necesarios;\nIV.- Las unidades responsables de su instrumentación;\nV.- La existencia en cantidad suficiente de los bienes, los plazos estimados de suministro, los avances tecnológicos incorporados en los bienes, y en su caso, los planos, proyectos y especificaciones;\nVI.- Los requerimientos de mantenimiento de los bienes muebles a su cargo;\nVII.- Las demás previsiones que deban tomarse en cuenta según la naturaleza y características de la adquisición, arrendamiento o servicio.\nARTÍCULO 17.- La unidad administrativa, a más tardar el treinta y uno de marzo de cada año, pondrá a disposición de los interesados los programas anuales de adquisiciones, arrendamientos y servicios de las dependencias o entidades, con excepción de aquella información que se considere de naturaleza confidencial.\nLos programas serán de carácter informativo, no implicarán compromiso de contratación y podrán ser adicionados, modificados, suspendidos o cancelados por las dependencias o entidades, sin responsabilidad alguna para la unidad administrativa.\nArtículo Reformado\nARTÍCULO 18.- La unidad administrativa establecerá y presidirá el Comité, el cual se integrará además por la tesorería, la contraloría y los órganos solicitantes en los términos que señale el Reglamento y tendrá las siguientes funciones:\nI.- Convocar y adjudicar las adquisiciones, arrendamientos y servicios;\nII.- Revisar los programas y presupuestos de adquisiciones, arrendamientos y servicios, así como formular las observaciones y recomendaciones convenientes;\nIII.- Dictaminar la procedencia de contrataciones mediante adjudicación directa por excepción al procedimiento de licitación pública por encontrarse en alguno de los supuestos de excepción previstos en el artículo 38 de esta Ley, salvo en los casos de las fracciones II y\nIV del mismo precepto, en cuyo caso se deberá informar al Comité una vez concluida la contratación respectiva;\nFracción Reformada\nIV.- Proponer y aplicar las políticas, bases y lineamientos en materia de adquisiciones, arrendamientos y servicios;\nEl Comité establecerá en dichas políticas, bases y lineamientos, los aspectos de sustentabilidad ambiental, incluyendo la evaluación de las tecnologías que permitan la reducción de la emisión de gases de efecto invernadero y la eficiencia energética, que deberán observarse en las adquisiciones, arrendamientos y servicios, con el objeto de ambientales. En la definición de los aspectos de sustentabilidad ambiental el Comité\nLey de Adquisiciones, Arrendamientos y Servicios para el Estado de Baja California. Página 8 u órgano equivalente en el ámbito municipal.\nPárrafo de la Fracción Reformado\nFracción Reformada\nV.- Analizar exclusivamente para su opinión, cuando se le solicite, los dictámenes y fallos emitidos por los servidores públicos responsables de ello;\nVI.- Autorizar, cuando se justifique, la creación de Subcomités de adquisiciones, arrendamientos y servicios; los cuales, podrán llevar a cabo procedimientos de contratación únicamente con autorización previa y por escrito de la Presidencia del Comité;\nFracción Reformada\nVII.- Proceder a la corrección de un error aritmético, mecanográfico o de cualquier otra naturaleza que no afecte el resultado de las evaluaciones realizadas por la persona convocante, siempre que no se haya firmado contrato respectivo.\nCuando se advierta en cualquier etapa del procedimiento alguna de las inconsistencias a que se refiere el párrafo que antecede, se procederá a la corrección del acto, aclarando o rectificando el mismo, mediante el acta administrativa correspondiente, en la que se harán constar los motivos que lo originaron y las razones que sustentan su enmienda, hecho que se notificará a las y los participantes en el procedimiento de contratación, remitiendo copia de la misma a la Contraloría dentro de los cinco días hábiles posteriores a la fecha de su firma.\nSi el error cometido no fuera susceptible de corrección conforme a lo dispuesto en esta fracción, el Comité dará vista a la Contraloría, a efecto de que, previa intervención de oficio, se emitan en su caso, las directrices para su reposición.\nFracción Adicionada, recorriéndose los subsecuentes\nVIII.- Coadyuvar al cumplimiento de la Ley y demás disposiciones aplicables; y,\nFracción Reformada\nIX.- Las que se señalen en el Reglamento y demás disposiciones que se emitan al respecto.\nPara la contratación de los proyectos de Asociaciones Público-Privadas prevista en la ley de la materia, el Comité se auxiliará de la Comisión en la elaboración de convocatorias y bases, así como en las juntas de aclaraciones y en la evaluación de las proposiciones a que se refiere esta Ley.\nPárrafo reformado\nArtículo Reformado\nARTÍCULO 19.- En los contratos de adquisiciones, arrendamientos y servicios, cuya vigencia rebase un ejercicio presupuestal, los órganos deberán proyectar tanto el presupuesto total como el relativo a los ejercicios de que se trate; en la formulación de los presupuestos de los ejercicios subsecuentes, se considerarán los costos que, en su momento, se encuentren vigentes, y se dará prioridad a las previsiones para el cumplimiento de las obligaciones contraídas en ejercicios anteriores.\nLey de Adquisiciones, Arrendamientos y Servicios para el Estado de Baja California. Página 9\nCAPÍTULO SEGUNDO BIS\nDEL PADRÓN DE PROVEEDORES\nCapítulo Adicionado\nARTÍCULO 19 BIS 1.- Los sujetos obligados a que se refiere esta Ley, integrarán un padrón de proveedores registrados y clasificados, por giro, conforme a los criterios y procedimientos que al respecto fije el Reglamento de la materia.\nLas personas interesadas en inscribirse en el padrón de proveedores del Estado o\nMunicipios, deberán solicitarlo por escrito, acompañando la información y documentación que al efecto se señale en el reglamento de esta Ley, agregando el comprobante que ampare el pago de los derechos que fije la Ley de Ingresos correspondientes.\nLa unidad administrativa del sujeto obligado correspondiente, dentro de un plazo que no exceda de diez días hábiles, contados a partir de la fecha en que reciba la solicitud, emitirá resolución de la petición planteada fundando y motivando su proceder. Transcurrido ese plazo, sin que haya respuesta o aclaración, se tendrá por aprobada la solicitud y registrado al solicitante.\nArtículo Adicionado\nARTÍCULO 19 BIS 2.- Las dependencias o entidades solo podrán celebrar contratos de adquisiciones, arrendamiento o servicios, salvo los supuestos contemplados en el artículo\n49 de esta Ley, con las personas inscritas en el padrón y en el portal de internet que se trate.\nLa clasificación a que se refiere el párrafo primero del artículo 19 bis 1, deberá ser considerada por las dependencias y entidades en la convocatoria y contratación de adquisiciones, arrendamientos y servicios.\nArtículo Adicionado\nARTÍCULO 19 BIS 3.- El registro en el padrón de proveedores tendrá vigencia indefinida, siempre y cuando no se incurra en alguna de las causales a que se contrae el artículo 49 de esta Ley.\nArtículo Adicionado\nARTÍCULO 19 BIS 4.- En el mes de enero de cada año, los sujetos obligados por conducto del órgano o unidad que indique el reglamento respectivo, mandara publicar en el\nPeriódico Oficial del Estado y en la página oficial de internet, los nombres de las personas físicas o morales registradas en el padrón de proveedores; así mismo informará a las dependencias y entidades de las inscripciones, suspensiones y cancelaciones que se lleven a cabo con posterioridad a dicha publicación.\nArtículo Adicionado\nCAPÍTULO TERCERO\nDE LOS PROCEDIMIENTOS DE CONTRATACIÓN\nY SUS EXCEPCIONES\nSECCIÓN PRIMERA\nGENERALIDADES\nLey de Adquisiciones, Arrendamientos y Servicios para el Estado de Baja California. Página 10\nARTÍCULO 20.- La unidad administrativa podrá contratar adquisiciones, arrendamientos y servicios para los órganos, sólo cuando éstos cuenten con saldo disponible en la partida del presupuesto autorizado a las mismas, y que el Comité haya previamente convocado y adjudicado en los términos de la presente Ley.\nEn casos excepcionales y previa autorización de la tesorería, el Comité podrá convocar sin contar con dicha autorización.\nPrevio al inicio de los procedimientos de contratación previstos en el artículo 21 de esta Ley, el órgano solicitante, deberá realizar una investigación de mercado de la cual se desprendan las condiciones que imperan en el mismo, respecto del bien, arrendamiento o servicio objeto de la contratación, a efecto de buscar las mejores condiciones para el Estado.\nPárrafo Adicionado\nDel resultado de la investigación de mercado se determinará:\nPárrafo Adicionado\na) Si existe oferta de bienes y servicios en la cantidad, calidad y oportunidad requerida;\nInciso Adicionado\nb) Si hay proveedores con la capacidad para cumplir con las necesidades de contratación; y,\nInciso Adicionado\nc) Los precios a partir de los cuales los proveedores no podrán ofertar precios superiores a los de dicha investigación.\nInciso Adicionado\nLa investigación de mercado que realicen los órganos solicitantes deberá integrarse, de acuerdo con las características del bien o servicio a contratar, con información obtenida de cuando menos tres fuentes.\nPárrafo Adicionado\nArtículo Reformado\nARTÍCULO 21.- La unidad administrativa llevará a cabo la contratación de adquisiciones, arrendamientos y servicios, mediante los procedimientos que a continuación se señalan:\nI.- Licitación pública;\nII.- Invitación;\nIII.- Adjudicación directa. condiciones para todos los participantes, especialmente por lo que se refiere a tiempo y lugar de entrega, forma y plazo para pago, penas convencionales, anticipos y garantías; con dichos procedimientos, a fin de evitar favorecer a algún participante.\nLey de Adquisiciones, Arrendamientos y Servicios para el Estado de Baja California. Página 11\nEl Comité pondrá a disposición pública a través de medios electrónicos, la información las licitaciones, y en su caso, sus modificaciones; las actas de las juntas de aclaraciones y de visita a instalaciones, los fallos de dichas licitaciones o las cancelaciones de éstas, y los datos relevantes de los contratos. Las sesiones del Comité o Subcomité, previstos en esta\nLey o su Reglamento, podrán ser transmitidas en vivo por los medios oficiales electrónicos de comunicación social para la población en general.\nPárrafo Reformado\nEn todos los casos tratándose de licitaciones públicas, invitaciones o adjudicaciones directas se priorizará a empresas radicadas en del Estado que cumplan con los requisitos técnicos y que sus ofertas sean competentes respecto a las demás ofertas.\nArtículo Reformado\nARTÍCULO 22.- Las adquisiciones, arrendamientos y servicios, se contratarán por regla general, a través de licitaciones públicas, mediante convocatoria pública, para que libremente se presenten proposiciones en sobre cerrado o a través de medios electrónicos, que será abierto públicamente, a fin de asegurar al sujeto obligado, las mejores condiciones disponibles en cuanto a precio, calidad, financiamiento, garantías, formas de pago, oportunidad y demás circunstancias que se estimen pertinentes.\nPárrafo Reformado\nLa proposición a que hace referencia este artículo podrá entregarse, a elección del licitante, en sobre cerrado en el lugar de celebración del acto de presentación y apertura de proposiciones; o bien, si así lo establece el Comité, enviarlo a través del servicio postal o de mensajería, o por medios electrónicos, conforme a las disposiciones técnicas y administrativas que establezca la unidad administrativa.\nLa proposición presentada por medios electrónicos, deberá generarse mediante el uso de tecnologías que resguarden la confidencialidad de la información, de tal forma que sea inviolable, conforme a las disposiciones técnicas que al efecto establezca la unidad administrativa.\nLas proposiciones presentadas deberán ser firmadas autógrafamente por los interesados o sus apoderados; en caso de que sean enviadas a través de medios electrónicos, se emplearán medios de identificación electrónica, los cuales producirán los mismos efectos que las leyes otorgan a dichos documentos, y en consecuencia, tendrán el mismo valor probatorio. medios de identificación electrónica que utilicen los participantes, y será responsable de ejercer el control de estos medios, salvaguardando la confidencialidad de la información que se remita por esta vía.\nArtículo Reformado\nARTÍCULO 23.- Los bienes y servicios que se pretendan adquirir por medio de procedimientos de contratación internacional se sujetarán a las siguientes bases:\nI.- Ser destinados a inversiones públicas productivas;\nLey de Adquisiciones, Arrendamientos y Servicios para el Estado de Baja California. Página 12\nII.- Que las propuestas aseguren al sujeto obligado las mejores condiciones financieras, comerciales y de servicios;\nIII.- Que las propuestas nacionales contengan un margen de preferencia hasta del diez por ciento en el precio respecto de los bienes de importación, salvo los casos previstos en el artículo 25, en cuyo caso no será necesario cubrir el porcentaje antes señalado.\nEn los procedimientos de contratación internacional, la unidad administrativa optará en igualdad de condiciones, por el empleo de recursos humanos del país y por la adquisición y arrendamiento de bienes producidos en el mismo, debiendo contar en la comparación económica de las propuestas, con el margen de preferencia indicado en la fracción anterior.\nSECCIÓN SEGUNDA\nDE LA LICITACIÓN PÚBLICA\nARTÍCULO 24.- Las licitaciones públicas podrán ser:\nI.- Regionales.- Cuando atendiendo a programas para incentivar los sectores de la economía regional, independientemente del origen de los bienes o servicios, únicamente puedan participar personas con residencia en el Estado de Baja California; solamente se realizarán licitaciones regionales en apego a las disposiciones establecidas en el\nReglamento.\nII.- Nacionales.- Cuando únicamente puedan participar personas de nacionalidad mexicana y los bienes y/o servicios a adquirir sean producidos en el país, y cuenten por lo menos con un cincuenta por ciento de contenido nacional.\nEn el Reglamento se señalarán los casos en que no será exigible el porcentaje mencionado, así como un procedimiento expedito para determinar el grado del contenido nacional de los bienes que se oferten, para lo cual tomará en cuenta la opinión de la\nSecretaría de Economía e Innovación.\nPárrafo de la Fracción Reformado\nFracción Reformadao\nIII.- Internacionales.- Cuando puedan participar personas de nacionalidad mexicana como extranjera y los bienes a adquirir sean de origen nacional o extranjero.\nArtículo Reformado\nARTÍCULO 25.- Solamente se realizarán licitaciones internacionales, en los siguientes casos:\nI.- Cuando la unidad administrativa determine que no existe oferta de proveedores nacionales, respecto de bienes o servicios en cantidad o calidad requeridas, o sea conveniente en términos de precio.\nII.- Cuando habiéndose realizado una licitación de carácter nacional, no se presente alguna propuesta o ninguna cumpla con los requisitos establecidos por la convocante. internacionales, cuando con el país del cual sean nacionales no se tenga celebrado un\nLey de Adquisiciones, Arrendamientos y Servicios para el Estado de Baja California. Página 13 tratado, y ese país no conceda un trato recíproco a los licitantes, proveedores, bienes o servicios mexicanos.\nARTÍCULO 26.- Las convocatorias podrán referirse a uno o más bienes y servicios, y contendrán:\nI.- El nombre, denominación o razón social de la convocante;\nII.- La indicación de los lugares, fechas y horarios en que los interesados podrán obtener las bases de la licitación, en su caso, el costo y forma de pago de las mismas.\nCuando las bases impliquen un costo, éste será fijado sólo en razón de la recuperación de las erogaciones por publicación de la convocatoria y de la reproducción de los documentos que se entreguen; los interesados podrán revisarlas previamente a su pago, el cual será requisito para participar en la licitación. Igualmente los interesados podrán consultar y adquirir las bases de las licitaciones por los medios de difusión electrónica que autorice la unidad administrativa;\nIII.- La indicación de sí la proposición podrá ser presentada a través de medios electrónicos;\nIV.- La fecha, hora y lugar de celebración de las dos etapas, relativas al acto de presentación y apertura de proposiciones; debiendo indicarse si la etapa de apertura económica se realizará con propuesta a precio fijo o a través de subasta inversa, de conformidad con el Reglamento;\nV.- Indicación de sí la licitación es regional, nacional o internacional; en caso de ser internacional, se deberá señalar el idioma o idiomas, además del español, en que podrán presentarse las proposiciones;\nVI.- La indicación de que ninguna de las condiciones contenidas en las bases de la licitación, así como en las proposiciones presentadas por los licitantes, podrán ser negociadas;\nVII.- La descripción general, cantidad y unidad de medida de por lo menos tres de las partidas más relevantes de los bienes o servicios que sean objeto de la licitación;\nVIII.- Lugar y plazo de entrega;\nIX.- Condiciones de pago, señalando el momento en que se haga exigible el mismo;\nX.- Descripción completa de los bienes o servicios, o indicación de los sistemas empleados para identificación de los mismos; información específica que requieran respecto a mantenimiento, asistencia técnica y capacitación; relación de refacciones que deberán cotizarse cuando sean parte integrante del contrato; dibujos, cantidades, muestras y pruebas que se realizarán, así como método para ejecutarlas; en ningún caso se podrán especificar marcas que limiten la participación de productos, mercancías o distribuidores regionales.\nXI.- La indicación de que no podrán participar las personas que se encuentren en los supuestos del artículo 49 de esta Ley;\nLey de Adquisiciones, Arrendamientos y Servicios para el Estado de Baja California. Página 14\nXII.- En el caso de arrendamiento y en los proyectos de Asociación Público-Privada, la indicación en su caso, de que éste es con o sin opción a compra.\nXIII.- La indicación de que las adquisiciones sustentables tendrán preferencia.\nFracción Adicionada\nArtículo Reformado\nARTÍCULO 27.- En el caso de licitaciones regionales, las convocatorias deberán ser publicadas en el Periódico Oficial del Estado y en un diario de amplia circulación estatal. En el caso de licitaciones nacionales e internacionales las convocatorias deberán ser publicadas en un diario de circulación nacional. En todos los casos, conjuntamente podrán utilizarse los medios de difusión electrónica que autorice la unidad administrativa.\nTratándose de licitaciones regionales y en cumplimiento con el principio de máxima publicidd se dará conocimiento a los colegios, barras, agrupaciones y demás grupos técnicos organizados y reconocidos según sea la materia de que se trate.\nArtículo Reformado\nARTÍCULO 28.- Las bases que emita el Comité para las licitaciones públicas, se pondrán a disposición de los interesados, tanto en el domicilio señalado en la convocatoria, como en los medios electrónicos, a partir del día en que se publique la convocatoria y hasta el sexto día natural previo al acto de presentación y apertura de proposiciones, siendo responsabilidad exclusiva de los interesados adquirirlas oportunamente durante este período.\nLas bases contendrán en lo aplicable como mínimo lo siguiente:\nI.- Nombre, denominación o razón social de la convocante;\nII.- Forma en que deberá acreditar la existencia y personalidad jurídica el licitante;\nIII.- Fecha, hora y lugar de la junta de aclaraciones sobre las bases de la licitación, siendo optativa la asistencia a las reuniones que en su caso se realicen; fecha, hora y lugar de celebración de las dos etapas relativas al acto de presentación y apertura de proposiciones; plazos para la comunicación del fallo y firma del contrato;\nIV.- La indicación de sí la proposición podrá ser presentada a través de medios electrónicos. Para la etapa de apertura económica, la indicación de que esta se realizará con propuesta a precio fijo o a través de subasta inversa, de conformidad con lo que establece el\nReglamento;\nV.- Señalamiento de que será causa de descalificación el incumplimiento de alguno de los requisitos establecidos en las bases de la licitación, así como la comprobación de que algún licitante ha acordado con otro u otros elevar los precios de los bienes o servicios, o cualquier otro acuerdo que tenga como fin obtener una ventaja sobre los demás licitantes;\nVI.- En el caso de las licitaciones internacionales, las proposiciones deberán ser presentadas siempre en idioma español. Los anexos técnicos, folletos o equivalentes podrán ser presentados en el idioma del país de origen de los bienes o servicios, acompañados de una traducción simple al español de la parte de la descripción del bien o servicio propuesto;\nLey de Adquisiciones, Arrendamientos y Servicios para el Estado de Baja California. Página 15\nVII.- Moneda en que se cotizará y efectuará el pago respectivo. En los casos de licitación internacional, en que la convocante determine efectuar los pagos a proveedores extranjeros en moneda extranjera, los licitantes nacionales podrán presentar sus proposiciones en la misma moneda extranjera que determine la convocante. No obstante, el cambio establecido por el Banco de México y publicado en el Diario Oficial de la Federación, vigente en la fecha en que esté a disposición del proveedor el pago correspondiente;\nVIII.- La indicación de que ninguna de las condiciones contenidas en las bases de la licitación, así como en las proposiciones presentadas por los licitantes podrán ser negociadas;\nIX.- Criterios claros y detallados para la adjudicación de los contratos de conformidad a lo establecido en el artículo 33 de esta Ley;\nX.- Descripción completa de los bienes o servicios, o indicación de los sistemas empleados para identificación de los mismos; información específica que requieran respecto a mantenimiento, asistencia técnica y capacitación; relación de refacciones que deberán cotizarse cuando sean parte integrante del contrato; dibujos, cantidades, muestras y pruebas que se realizarán, así como método para ejecutarlas; en ningún caso se podrán especificar marcas que limiten la participación de productos o mercancías regionales.\nXI.- Plazo y condiciones de entrega, así como la indicación del lugar, dentro del territorio nacional, donde deberán efectuarse las entregas;\nXII.- Requisitos que deberán cumplir quienes deseen participar, los cuales no deberán limitar la libre participación de los interesados;\nXIII.- Condiciones de precio y pago, señalando el momento en que se haga exigible el mismo;\nXIV.- Datos sobre las garantías, así como la indicación de si se otorgará anticipo, caso en el cual deberá señalarse el porcentaje respectivo y el momento en que se entregará, el que no podrá exceder del cincuenta por ciento del monto total del contrato;\nXV.- La indicación de si la totalidad de los bienes o servicios objeto de la licitación, o bien, de cada partida o concepto de los mismos, serán adjudicados a uno o varios proveedores, o si la adjudicación se hará mediante el procedimiento de abastecimiento simultáneo a que se refiere el artículo 36 de la Ley, caso en el cual deberá precisarse el número de fuentes de abastecimiento requeridas, los porcentajes que se asignarán a cada una, y el porcentaje diferencial en precio que se considerará;\nXVI.- La indicación de que el licitante que no firme el contrato por causas imputables al mismo será sancionado en los términos del artículo 59 de la Ley;\nXVII.- En el caso de contratos abiertos, la información a que alude el artículo 46 de la\nLey;\nXVIII.- Las penas convencionales por atraso en la entrega de los bienes o en la prestación de los servicios;\nLey de Adquisiciones, Arrendamientos y Servicios para el Estado de Baja California. Página 16\nXIX.- En su caso, términos y condiciones a que deberá ajustarse la participación de mensajería, o por medios electrónicos. El que los licitantes opten por utilizar alguno de estos medios para enviar sus proposiciones no limita, en ningún caso, que asistan a los diferentes actos derivados de una licitación.\nXX.- En el caso de arrendamiento y en los proyectos de Asociación Público-Privada, la indicación en su caso de que es con o sin opción a compra, así como las reglas y condiciones a que deberá sujetarse el proyecto respectivo.\nXXI.- La indicación de que las adquisiciones sustentables tendrán preferencia.\nFracción Adicionada\nArtículo Reformado\nARTÍCULO 29.- El plazo para la presentación y apertura de proposiciones de las licitaciones internacionales, no podrá ser inferior a quince días naturales, contados a partir de la fecha de publicación de la convocatoria.\nEn licitaciones nacionales y regionales, el plazo para la presentación y apertura de proposiciones será cuando menos, de doce días naturales contados a partir de la fecha de publicación de la convocatoria.\nCuando no puedan observarse los plazos indicados en este artículo por que existan razones justificadas del área solicitante de los bienes o servicios, siempre que ello no tenga por objeto limitar el número de participantes, el Comité podrá reducir los plazos a no menos de diez días naturales, contados a partir de la fecha de publicación de la convocatoria.\nARTÍCULO 30.- El Comité, siempre que ello no tenga por objeto limitar el número de licitantes, podrá modificar los plazos u otros aspectos establecidos en la convocatoria o en las bases de la licitación, a partir de la fecha en que sea publicada la convocatoria y hasta inclusive el sexto día natural previo al acto de presentación y apertura de proposiciones, siempre que:\nI.- Tratándose de la convocatoria, las modificaciones se hagan del conocimiento de los interesados a través de los mismos medios utilizados para su publicación;\nII.- En el caso de las bases de licitación, se publique un aviso en el Periódico Oficial del Estado, en un diario de circulación estatal y en medios electrónicos, a fin de que los interesados concurran ante la propia convocante para conocer, de manera específica, las modificaciones respectivas.\nNo será necesario hacer la publicación del aviso a que se refiere la fracción anterior, cuando las modificaciones deriven de las juntas de aclaraciones, siempre que, a más tardar dentro del plazo señalado en este artículo, se entregue copia del acta respectiva a cada uno de los licitantes que hayan adquirido las bases de la correspondiente licitación. sustitución de los bienes o servicios convocados originalmente, adición de otros de distintos rubros o en variación significativa de sus características, que limiten la libre participación de productos, mercancías o distribuidores regionales.\nLey de Adquisiciones, Arrendamientos y Servicios para el Estado de Baja California. Página 17\nCualquier modificación a las bases de la licitación, derivada del resultado de juntas de aclaraciones, será considerada como parte integrante de las propias bases de licitación.\nArtículo Reformadoa\nARTÍCULO 31.- La entrega de proposiciones se hará en dos sobres cerrados, o bien a través de los medios electrónicos, que contendrán por separado, la propuesta técnica y la propuesta económica. La documentación distinta a las propuestas podrá entregarse a elección del licitante, dentro o fuera del sobre o bien a través de medios electrónicos.\nEn el caso de que en las bases se haya establecido que la apertura económica se lleve a cabo mediante el mecanismo de subasta inversa, solo deberá entregarse el sobre que contenga la propuesta técnica, o en su caso, enviar ésta a través de medios electrónicos.\nPrevio al acto de presentación y apertura de proposiciones, las convocantes podrán efectuar el registro de participantes, así como realizar revisiones preliminares a la documentación distinta a la propuesta técnica y económica.\nARTÍCULO 32.- El acto de presentación y apertura de proposiciones se sujetará a lo siguiente:\nI.- Primera etapa.- Relativa a la apertura de la propuesta técnica de los licitantes;\nII.- Segunda etapa.- Relativa a la apertura de la propuesta económica de los licitantes.\nPara efectos del procedimiento que rija a ambas etapas, se estará a lo dispuesto por el Reglamento.\nARTÍCULO 33.- El Comité, para hacer la evaluación de las proposiciones deberá verificar que las mismas cumplan con los requisitos solicitados en las bases de licitación.\nNo será objeto de evaluación, las condiciones establecidas por la convocante que tengan como propósito facilitar la presentación de las proposiciones y agilizar la conducción de los actos de la licitación; así como cualquier otro requisito, cuyo incumplimiento por sí mismo, no afecte la solvencia de las propuestas. La inobservancia por parte de los licitantes respecto a dichos requisitos no será motivo para desechar sus propuestas.\nEn la evaluación de proposiciones, en ningún caso podrán utilizarse mecanismos de puntos o porcentajes, excepto cuando se trate de servicios, en los que se demuestre la propuestas, de acuerdo con los lineamientos que previamente se hayan emitido por el\nComité.\nDentro de los criterios de adjudicación, podrá establecerse el relativo a costo beneficio, siempre y cuando sea definido, medible y aplicable a todas las propuestas.\nUna vez realizada la evaluación de las proposiciones, el contrato se adjudicará de entre los licitantes, a aquel cuya propuesta resulte solvente; porque reúne, conforme a los\nLey de Adquisiciones, Arrendamientos y Servicios para el Estado de Baja California. Página 18 criterios de adjudicación establecidos en las bases de licitación, las condiciones legales, técnicas, económicas y ambientales requeridas por la convocante, y garantiza satisfactoriamente el cumplimiento de las obligaciones respectivas.\nPárrafo Reformado\nSi resultare que dos o más proposiciones son solventes, porque satisfacen la totalidad de los requerimientos solicitados por la convocante, el contrato se adjudicará a quien presente la proposición cuyo precio sea más bajo, incluyendo en su caso, los porcentajes previstos en los artículos 8 y la fracción III del artículo 23 de este Ordenamiento. En caso de que el precio también sea el mismo, se adjudicará mediante insaculación.\nEl Comité emitirá un dictamen que servirá como base para el fallo, en el que hará constar una reseña cronológica de los actos del procedimiento, el análisis de las proposiciones y las razones para admitirlas o desecharlas.\nArtículo Reformado\nARTÍCULO 34.- En junta pública se dará a conocer el fallo de la licitación, a la que libremente podrán asistir los licitantes que hubieren participado en el acto de presentación y apertura de proposiciones, levantándose el acta respectiva que firmarán los asistentes, a quienes se entregará copia de la misma. La falta de firma de algún licitante no invalidará su contenido y efectos, poniéndose a partir de esa fecha a disposición de los que no hayan asistido, para efectos de su notificación. En sustitución de esa junta, el Comité podrá optar por notificar el fallo de la licitación por escrito a cada uno de los licitantes, dentro de los cinco días naturales siguientes a su emisión.\nEn el mismo acto del fallo o adjunta a la comunicación referida, el Comité proporcionará por escrito a los licitantes la información acerca de las razones por las cuales su propuesta no resultó ganadora.\nCon la notificación del fallo por el que se adjudica el contrato, las obligaciones derivadas de este serán exigibles, sin perjuicio de la obligación de las partes de formalizarlo en los términos de lo establecido en el artículo 45 de esta Ley.\nPárrafo Adicionado\nArtículo Reformado\nARTÍCULO 35.- El Comité procederá a declarar desierta la licitación, cuando las propuestas presentadas no reúnan los requisitos establecidos en las bases de licitación o sus precios no fueren aceptables, debiéndose expedir una nueva convocatoria. propuestas satisfactorias, el Comité podrá proceder a convocar una nueva licitación, o bien a aplicar el procedimiento de invitación o de adjudicación directa, según corresponda.\nPárrafo Reformado\nAsimismo, tratándose de licitaciones en las que una o varias partidas se declaren desiertas por no haberse recibido propuestas satisfactorias, el Comité podrá proceder, sólo respecto a esas partidas, a convocar una nueva licitación, o bien a aplicar el procedimiento de invitación o de adjudicación directa, según corresponda.\nPárrafo Adicionado\nLey de Adquisiciones, Arrendamientos y Servicios para el Estado de Baja California. Página 19 fuerza mayor. De igual manera, podrá cancelar cuando existan circunstancias, debidamente justificadas, que provoquen la extinción de la necesidad para adquirir o arrendar los bienes o contratar la prestación de los servicios, y que de continuarse con el procedimiento de contratación se pudiera ocasionar un daño o perjuicio al órgano correspondiente.\nPárrafo Reformado\nArtículo Reformado\nARTÍCULO 36.- El Comité podrá distribuir, entre dos o más proveedores la partida de un bien o servicio, previa justificación de su conveniencia, siempre y cuando así se haya establecido en las bases de la licitación.\nEn este caso, los precios de los bienes o servicios contenidos en una misma partida y distribuidos entre dos o más proveedores no podrán exceder del cinco por ciento respecto de la propuesta solvente más baja.\nSECCIÓN TERCERA\nDE LAS EXCEPCIONES A LA LICITACIÓN PÚBLICA\nARTÍCULO 37.- En los supuestos que prevé el artículo 38 de esta Ley, el Comité podrá optar por no llevar a cabo el procedimiento de licitación pública, y la unidad administrativa podrá celebrar contratos a través de los procedimientos de invitación o de adjudicación directa.\nPárrafo Reformado\nLa selección del procedimiento deberá fundarse y motivarse, según las circunstancias que concurran en cada caso, en criterios de economía, eficacia, eficiencia, imparcialidad y honradez que aseguren las mejores condiciones para el sujeto obligado. El acreditamiento de los criterios mencionados y la justificación de las razones para el ejercicio de la opción, deberá constar por escrito y ser firmado por el titular del órgano usuario o requirente de los bienes o servicios.\nEn cualquier supuesto se invitará a personas que cuenten con capacidad de respuesta inmediata, con los recursos técnicos, financieros y demás que sean necesarios, debiendo sus actividades comerciales o profesionales estar relacionadas con los bienes o servicios objeto del contrato a celebrarse.\nArtículo Reformado\nARTÍCULO 38.- La unidad administrativa podrá contratar adquisiciones, arrendamientos y servicios, sin sujetarse al procedimiento de licitación pública, a través de los procedimientos de invitación o de adjudicación directa, cuando:\nI.- El contrato sólo pueda celebrarse con una determinada persona por tratarse de obras de arte, titularidad de patentes, derechos de autor u otros derechos exclusivos, así como aquellos sujetos a precios oficiales; o bien, por no existir bienes o servicios alternativos o sustitutos técnicamente razonables, supuesto que se acreditará con la investigación de mercado;\nFracción Reformada\nII.- Peligre o se altere el orden social, la economía, los servicios públicos, la salubridad, la seguridad o el ambiente de alguna zona o región del Estado de Baja\nLey de Adquisiciones, Arrendamientos y Servicios para el Estado de Baja California. Página 20\nCalifornia, como consecuencia de desastres afectaciones y daños producidos por fenómenos naturales o emergencias sanitarias;\nFracción Reformada\nIII.- Existan circunstancias que puedan provocar pérdidas o costos adicionales importantes debidamente justificadas;\nIV.- Derivado de caso fortuito o de fuerza mayor, no sea posible obtener bienes o servicios mediante el procedimiento de licitación pública en el tiempo requerido para atender la eventualidad de que se trate, en este supuesto las cantidades o conceptos deberán limitarse a lo estrictamente necesario para afrontarla;\nV.- Se hubiere rescindido el contrato respectivo por causas imputables al proveedor que hubiere resultado ganador en el procedimiento de contratación. En este caso, se estará conforme al Reglamento.\nFracción Reformada\nVI.- Se realicen dos licitaciones públicas que hayan sido declaradas desiertas;\nVII.- Exista razón justificada para la adquisición o arrendamiento de bienes de marca determinada;\nVIII.- Se trate de adquisiciones, arrendamientos o servicios que, de realizarse bajo un procedimiento de licitación pública, pudieran comprometer información de naturaleza confidencial para el Estado;\nIX.- Se trate de adquisiciones de bienes provenientes de personas que, sin ser proveedores habituales, ofrezcan bienes en condiciones favorables, en razón de encontrarse en estado de liquidación o disolución, o bien, bajo intervención judicial;\nX.- Se trate de servicios profesionales prestados por una persona física, siempre que éstos sean realizados por ella misma sin requerir de más de un especialista o técnico;\nXI.- Se trate de servicios de mantenimiento de bienes en los que no sea posible precisar su alcance, establecer las cantidades de trabajo o determinar las especificaciones correspondientes;\nXII.- Se acepte la adquisición de bienes o la prestación de servicios a título de dación en pago, cuando las disposiciones legales lo permitan;\nXIII.- Se trate de adquisiciones de bienes perecederos, granos y productos alimenticios básicos o semiprocesados, semovientes y bienes usados;\nXIV.- Se trate de adquisiciones de armamento necesario para el desempeño de las funciones propias de las áreas de seguridad pública.\nXV.- Se trate de la contratación de servicios de comunicación o difusión en medios de comunicación social, incluidos radio, televisión, prensa escrita, medios electrónicos y plataformas digitales, según corresponda;\nFracción Reformada\nLey de Adquisiciones, Arrendamientos y Servicios para el Estado de Baja California. Página 21\nXVI.- Se trate de la contratación de un bien, arrendamiento, o servicio, con algún licitación pública en el ejercicio fiscal en curso o en el inmediato anterior, que acepte y técnicas, de calidad, precio, alcances y demás especificaciones previamente ofertadas;\nFracción Adicionada\nXVII.- Se trate de servicios de consultorías, asesorías, estudios o investigaciones, debiendo aplicar el procedimiento de invitación a cuando menos tres personas, entre las que preferentemente se incluirán instituciones públicas y privadas de educación superior y centros públicos de investigación; y,\nFracción Adicionada\nXVIII.- Se trate de la suscripción de convenios específicos que deriven de un contrato marco.\nFracción Adicionada\nArtículo Reformado\nARTÍCULO 39.- Sin perjuicio de lo dispuesto en el artículo anterior, la unidad administrativa podrá contratar adquisiciones, arrendamientos y servicios, a través del procedimiento de invitación o de adjudicación directa, cuando el importe de cada operación no exceda de los montos máximos que al efecto establezca la tesorería para cada uno de los órganos; siempre que las operaciones no se fraccionen para quedar comprendidas en los supuestos a que se refiere este artículo.\nLa suma de las operaciones que se realicen al amparo de este artículo, no podrán exceder del quince por ciento del presupuesto de adquisiciones, arrendamientos y servicios, autorizado al órgano en cada ejercicio presupuestal.\nLa unidad administrativa deberá someter a consideración del Comité, los procedimientos de contratación cuya adjudicación se fundamente en este artículo.\nArtículo Reformado\nARTÍCULO 40.- En el supuesto de que el procedimiento de invitación haya sido declarado desierto, el Comité podrá adjudicar directamente el contrato.\nArtículo Reformado\nARTÍCULO 41.- Los órganos podrán adquirir sin sujetarse a los procedimientos previstos por esta Ley, siempre y cuando se trate de artículos de consumo preferentemente biodegradables o gastos de servicios, y el monto de las operaciones no sea superior a los que fije la unidad administrativa y la tesorería.\nArtículo Reformado\nARTÍCULO 42.- El procedimiento de invitación se sujetará a lo siguiente:\nI.- Deberá invitarse a cuando menos tres personas, de las cuales dos de ellas, si las hubiere, deberán ser fabricantes o distribuidores regionales;\nFracción Reformada\nII.- El acto de presentación y apertura de proposiciones se llevará a cabo en dos etapas, para lo cual la apertura de los sobres podrá hacerse sin la presencia de los\nLey de Adquisiciones, Arrendamientos y Servicios para el Estado de Baja California. Página 22 correspondientes licitantes, pero invariablemente se invitará a un representante de la contraloría;\nIII.- En la primera etapa de presentación y apertura de proposiciones será requisito indispensable contar con un mínimo de dos propuestas, susceptibles de analizarse técnicamente; caso contrario deberá declarase desierta;\nFracción Reformada\nIV.- En las invitaciones se indicarán, como mínimo, la cantidad y descripción de los bienes o servicios requeridos, plazo y lugar de entrega, así como condiciones de pago;\nV.- Los plazos para la presentación de las proposiciones se fijarán para cada operación atendiendo al tipo de bienes o servicios requeridos, así como a la complejidad para elaborar la propuesta;\nVI.- Una vez realizada la evaluación de las proposiciones, y emitido el fallo en los términos del artículo 34 de la Ley, el contrato se adjudicará de entre los invitados, a aquel cuya propuesta resulte solvente porque reúne, conforme a los criterios de la invitación, las condiciones legales, técnicas y económicas requeridas por la solicitante y garantiza satisfactoriamente el cumplimiento de las obligaciones respectivas.\nArtículo Reformado\nCAPÍTULO CUARTO\nDE LOS CONTRATOS\nARTÍCULO 43.- En las adquisiciones, arrendamientos y servicios deberá pactarse preferentemente la condición de precio fijo. No obstante, en casos justificados se podrán pactar en el contrato decrementos o incrementos a los precios, de acuerdo con la fórmula o mecanismo de ajuste que determine la unidad administrativa, previamente a la presentación de las propuestas.\nCuando con posterioridad a la adjudicación de un contrato se presenten circunstancias económicas de tipo general, como resultado de situaciones supervenientes ajenas a la responsabilidad de las partes, que provoquen directamente un aumento o reducción en los precios de los bienes o servicios aún no entregados, prestados o pagados, y que por tal razón no pudieron haber sido objeto de consideración en la propuesta que sirvió de base para la adjudicación del contrato correspondiente, la unidad administrativa podrá reconocer incrementos o requerir reducciones.\nTratándose de bienes o servicios sujetos a precios oficiales, se reconocerán los incrementos autorizados.\nARTÍCULO 44.- Los contratos contendrán como mínimo, lo siguiente:\nI.- La autorización del presupuesto para cubrir el compromiso derivado del contrato;\nII.- La indicación del procedimiento, conforme al cual se llevó a cabo la adjudicación del contrato;\nIII.- El precio unitario y el importe total a pagar por los bienes o servicios;\nLey de Adquisiciones, Arrendamientos y Servicios para el Estado de Baja California. Página 23\nIV.- La fecha, lugar y condiciones de entrega;\nV.- Porcentaje, número y plazos para el pago de los anticipos que se otorguen;\nVI.- Forma y términos para garantizar el total de los anticipos y el cumplimiento del contrato;\nVII.- Plazo y condiciones de pago del precio de los bienes o servicios;\nVIII.- Precisión de sí el precio es fijo o sujeto a ajustes y, en este último caso, la fórmula o condición en que se hará y calculará el ajuste;\nIX.- Penas convencionales por el atraso en la entrega de los bienes o prestación de los servicios, por causas imputables a los proveedores;\nX.- La descripción pormenorizada de los bienes o servicios objeto del contrato, incluyendo en su caso la marca y modelo de los bienes;\nXI.- Las condiciones que garanticen la correcta operación y funcionamiento de los bienes; en su caso la obtención de una póliza de seguro por parte del proveedor, que garantice la integridad de los bienes hasta el momento de su entrega y de ser necesario, la capacitación del personal que operará los equipos;\nXII.- Salvo que exista impedimento, la estipulación de que los derechos de autor u otros derechos exclusivos que se deriven de los servicios de consultorías, asesorías, estudios e investigaciones contratados, invariablemente se constituirán en favor del sujeto obligado correspondiente.\nXIII.- El importe del finiquito por la prestación de los servicios o la entrega de los bienes de parte del proveedor, tendrá que ser liquidado a más tardar en cinco días hábiles una vez finalizado el contrato;\nXIV.- Penas por el atraso de pagos conforme a la fracción V de este artículo, por la entrega de bienes o prestaciones de servicios, por causas imputables a los sujetos obligados;\nXV.- En los contratos derivados de los proyectos a que se refiere la Ley de\nAsociaciones Público-Privadas para el Estado de Baja California, se deberá contener, además de los anteriores requisitos y de lo previsto en éste último ordenamiento:\nPárrafo de la Fracción Reformado\na) La especificación si el proyecto se llevará a cabo con activos del Proveedor, del\nÓrgano, de un tercero o de un grupo de proveedores con base en lo requerido por la\nAdministración Pública;\nb) La situación jurídica de todos aquellos bienes inmuebles involucrados en el proyecto, para los efectos contractuales, derechos, obligaciones y condiciones de las partes respecto a los mismos, que garanticen satisfactoriamente el cumplimiento del objeto del proyecto;\nLey de Adquisiciones, Arrendamientos y Servicios para el Estado de Baja California. Página 24\nc) Los riesgos que asumirán tanto el Sujeto Obligado como el Proveedor;\nd) La duración del contrato, y el plazo para dar inicio a la prestación de los servicios o para la entrega de los bienes, en su caso;\ne) Las fórmulas y metodología para evaluar el cumplimiento del Proveedor, incluyendo indicadores de disponibilidad y de desempeño, y detallando la forma y cálculo de penalizaciones y deducciones a los pagos que deba realizar la Administración;\nf) Los medios para solucionar las controversias entre las partes, para cuyos efectos podrán establecerse, en primer orden, el arbitraje, y en su defecto los medios previstos en esta Ley, así como los mecanismos para las controversias que se susciten entre el\nProveedor y los usuarios.\nFracción Reformada\nArtículo Reformado\nARTÍCULO 45.- La adjudicación del contrato obligará a las partes, a formalizar el documento relativo dentro de los veinte días naturales siguientes al de la notificación del fallo.\nSi la persona favorecida con el fallo, no firmare el contrato por causas imputables al mismo, dentro del plazo a que se refiere el párrafo anterior, el Comité podrá, sin necesidad de un nuevo procedimiento, adjudicar el contrato al participante que haya presentado la siguiente proposición solvente más baja, de conformidad con lo asentado en el dictamen a que se refiere el artículo 33 de la Ley, y así sucesivamente en caso de que este último no acepte la adjudicación, siempre que la diferencia en precio con respecto a la propuesta que inicialmente hubiere resultado ganadora, no sea superior al diez por ciento.\nEl proveedor no estará obligado a suministrar los bienes o prestar el servicio, si la unidad administrativa, por causas imputables a la misma, no firmare el contrato. En este supuesto, se cubrirán a solicitud escrita del proveedor, los gastos no recuperables en que hubiere incurrido para preparar y elaborar su propuesta, siempre que éstos sean razonables, estén debidamente comprobados y se relacionen directamente con el procedimiento de que se trate.\nEl plazo para la entrega de los bienes o servicios contratados, empezará a contar a partir de la entrega del anticipo, en caso de que se haya ofrecido como forma de pago en las bases, y el proveedor lo haya solicitado en su propuesta.\nEn el caso de licitaciones para la adquisición de bienes, los plazos de entrega adquirirse. forma parcial ni total en favor de cualquier otra persona, con excepción de los derechos de cobro, en cuyo caso se deberá contar con el consentimiento previo de la unidad administrativa.\nArtículo Reformado\nARTÍCULO 46.- Cuando se requiera del suministro de un mismo bien o servicio de manera reiterada, podrán celebrarse contratos abiertos conforme a lo siguiente:\nLey de Adquisiciones, Arrendamientos y Servicios para el Estado de Baja California. Página 25\nI.- Se establecerá la cantidad mínima y máxima de bienes por adquirir o arrendar; o bien, el presupuesto mínimo y máximo que podrá ejercerse en la adquisición, el arrendamiento o la prestación del servicio;\nII.- Se hará una descripción completa de los bienes o servicios con sus correspondientes precios unitarios;\nIII.- En la solicitud y entrega de los bienes y servicios, se hará referencia al contrato celebrado;\nIV.- Su vigencia no excederá del ejercicio fiscal correspondiente a aquél en que se suscriba, y en casos excepcionales y debidamente justificados podrá comprender más de un ejercicio fiscal de conformidad a lo preceptuado por el artículo 19 de la Ley, en cuyo caso su vigencia no excederá de tres ejercicios fiscales;\nV.- Los plazos para el pago de los bienes o servicios, no podrán exceder de treinta días naturales una vez entregado el bien o prestado el servicio a entera satisfacción.\nARTÍCULO 47.- Los proveedores que celebren los contratos a que se refiere esta Ley, deberán garantizar la totalidad del monto de los anticipos que reciban, así como el cumplimiento del contrato.\nLa unidad administrativa fijará las bases, forma y porcentajes a que deberán sujetarse las garantías que deban constituirse.\nLa garantía de cumplimiento del contrato deberá presentarse a más tardar dentro de los quince días naturales siguientes a la firma del contrato, salvo que la entrega de los bienes o la prestación de los servicios se realice dentro del citado plazo y, la correspondiente al anticipo se presentará previamente a la entrega de éste, a más tardar en la fecha establecida en el contrato.\nArtículo Reformado\nARTÍCULO 48.- Las garantías que deban otorgarse conforme a esta Ley se constituirán a favor del sujeto obligado que corresponda, por conducto de la tesorería.\nARTÍCULO 49.- La unidad administrativa se abstendrá de recibir propuestas o celebrar contrato alguno en las materias a que se refiere la Ley, con las personas físicas o morales siguientes:\nI.- Aquellas con las que el servidor público que intervenga en cualquier etapa del procedimiento de contratación, tenga interés personal, familiar o de negocios, pueda resultar algún beneficio para él su cónyuge, concubina o concubinario, o sus parientes consanguíneos hasta el cuarto grado, por afinidad o civil, o para terceros con los que tenga relaciones profesionales, laborales o de negocios, o para socios o sociedades parte;\nII.- Las que desempeñen un empleo, cargo o comisión en el servicio público, o bien, las sociedades de las que dichas personas formen parte o que hayan formado parte, durante un año previo a la fecha de celebración del procedimiento de contratación de que se trate;\nLey de Adquisiciones, Arrendamientos y Servicios para el Estado de Baja California. Página 26\nIII.- Aquellos proveedores que por causas imputables a ellos mismos, la unidad administrativa les hubiere rescindido algún contrato, dentro de un lapso de dos años calendario, contados a partir de la notificación. El impedimento prevalecerá durante dos años calendario, contados a partir de la notificación de la rescisión;\nIV.- Las que se encuentren inhabilitadas por resolución de la Contraloría conforme al\nCapítulo Sexto de esta Ley;\nV.- Las que se encuentren inhabilitadas para desempeñar un empleo, cargo o comisión en el servicio público, en los términos de la Ley de Responsabilidades\nAdministrativas del Estado de Baja California;\nFracción Reformada\nVI.- Los proveedores que se encuentren en situación de atraso en las entregas de los bienes o en la prestación de los servicios por causas imputables a ellos mismos, respecto de otro u otros contratos celebrados con la unidad administrativa;\nNo se aplicará lo dispuesto en el párrafo anterior, a quienes, en su momento, hubieren acreditado que las causas del atraso se debieron a caso fortuito o fuerza mayor.\nVII.- Aquellas que hayan sido declaradas en suspensión de pagos, estado de quiebra o sujetas a concurso de acreedores;\nVIII.- Las que pretendan participar en un procedimiento de contratación y previamente hayan realizado o se encuentren realizando, por sí o a través de empresas que formen parte del mismo grupo empresarial, en virtud de otro contrato, trabajos de análisis y control de calidad o preparación de especificaciones;\nIX.- Aquellas que por sí o a través de empresas que formen parte del mismo grupo empresarial, pretendan ser contratadas para elaboración de dictámenes, peritajes y avalúos, cuando éstos hayan de ser utilizados para resolver discrepancias derivadas de los contratos en los que dichas personas o empresas sean parte; y\nX.- Aquellos que presenten garantías, que no resulte posible hacerlas efectivas por causas no imputables a la unidad administrativa solicitante.\nXI.- Las demás que por cualquier causa se encuentren impedidas para ello por disposición legal.\nArtículo Reformado\nARTÍCULO 50.- El plazo de pago al proveedor que la unidad administrativa estipule en los contratos quedará sujeto a las condiciones que establezca la misma; sin embargo, no respectiva, previa entrega de los bienes o prestación de los servicios a entera satisfacción en los términos del contrato.\nEn caso de incumplimiento del pago en los términos del párrafo anterior, la tesorería, a solicitud del proveedor, deberá pagar gastos financieros conforme al procedimiento establecido en el ordenamiento fiscal respectivo, como si se tratara del supuesto de prórroga para el pago de créditos fiscales. Dichos gastos se calcularán sobre las cantidades no\nLey de Adquisiciones, Arrendamientos y Servicios para el Estado de Baja California. Página 27 pagadas y se computarán por días naturales desde que se venció el plazo pactado, hasta la fecha en que se pongan efectivamente las cantidades a disposición del proveedor. Una vez efectuado el pago del principal, y si el proveedor no solicita el pago de los gastos financieros en un término de cinco días hábiles, no procederá la solicitud.\nTratándose de pagos en exceso que haya recibido el proveedor, éste deberá reintegrar las cantidades pagadas en exceso, más los intereses correspondientes, conforme al procedimiento señalado en el párrafo anterior. Los cargos se calcularán sobre las cantidades pagadas en exceso en cada caso y se computarán por días naturales desde la fecha de pago, hasta la fecha en que se pongan efectivamente las cantidades a disposición de la tesorería.\nEn caso de incumplimiento en la entrega de los bienes o la prestación de servicios, el proveedor deberá reintegrar los anticipos que haya recibido más los intereses correspondientes, conforme a lo indicado en este artículo. Los cargos se calcularán sobre el monto del anticipo no amortizado, y se computarán por días naturales desde la fecha de su entrega hasta la fecha en que se pongan las cantidades a disposición de la tesorería, en los términos del párrafo anterior.\nARTÍCULO 51.- La unidad administrativa dentro de los límites del presupuesto aprobado y disponible, bajo su responsabilidad y por razones fundadas, podrá acordar el incremento en la cantidad de bienes o servicios, mediante modificaciones a sus contratos vigentes, dentro de los doce meses posteriores a su firma; siempre que el monto total de las modificaciones no rebase en conjunto, el veinte por ciento del monto o cantidad de los conceptos y volúmenes establecidos originalmente en los mismos, y el precio de los bienes o servicios sea igual al pactado originalmente.\nIgual porcentaje se aplicará a las modificaciones que por ampliación de la vigencia se hagan de los contratos de arrendamiento o servicios, cuya prestación se realice de manera continua y reiterada.\nTratándose de contratos en los que se incluyan bienes o servicios de diferentes características, el porcentaje se aplicará para cada partida o concepto de los bienes o servicios de que se trate.\nCualquier modificación a los contratos deberá formalizarse por escrito por la unidad administrativa; los instrumentos legales respectivos serán suscritos por el servidor público que lo haya hecho en el contrato, quien lo sustituya o quien esté facultado para ello.\nLa unidad administrativa se abstendrá de hacer modificaciones que se refieran a precios, anticipos, pagos progresivos, especificaciones sustanciales y en general, cualquier cambio que implique otorgar condiciones más ventajosas a un proveedor comparadas con las establecidas originalmente.\nARTÍCULO 51 BIS.- Sin perjuicio de lo establecido por el artículo 51 de esta Ley, de prestación de servicios, que requieran continuidad una vez concluido el ejercicio fiscal en el que terminaría su vigencia original, siempre y cuando resulten indispensables para no exceda del primer trimestre del ejercicio fiscal siguiente; debiendo necesariamente contar para su ampliación.\nLey de Adquisiciones, Arrendamientos y Servicios para el Estado de Baja California. Página 28 presupuestaria con la que cuente el órgano para el ejercicio fiscal siguiente, por lo que la presupuestarios respectivos. El precio de la contratación sujeto a la ampliación, será igual al pactado originalmente.\nArtículo Adicionado\nARTÍCULO 52.- La unidad administrativa deberá pactar penas convencionales a cargo del proveedor por atraso en el cumplimiento de entrega de los bienes o de la prestación del servicio en las fechas pactadas, las que no excederán del monto de la garantía de cumplimiento del contrato, y serán determinadas en función de los bienes o servicios no entregados o prestados oportunamente. En las operaciones en que se pactare ajuste de precios, la penalización se calculará sobre el precio ajustado.\nLos proveedores quedarán obligados ante la unidad administrativa a responder de los defectos y vicios ocultos de los bienes y de la calidad de los servicios, así como de cualquier otra responsabilidad en que hubieren incurrido, en los términos señalados en el contrato respectivo y en la legislación aplicable.\nLos proveedores cubrirán las cuotas compensatorias, conforme a la ley de la materia, a que pudiere estar sujeta la importación de bienes objeto de un contrato, y en estos casos no procederán incrementos a los precios pactados, ni cualquier otra modificación al contrato.\nArtículo Reformado\nARTÍCULO 53.- La unidad administrativa podrá rescindir administrativamente los contratos en caso de incumplimiento de las obligaciones a cargo del proveedor, en cuyo caso el procedimiento deberá iniciarse dentro de los quince días naturales siguientes a aquel en que se hubiere agotado el monto límite de aplicación de las penas convencionales. Si previamente a la determinación de dar por rescindido el contrato, se hiciere entrega de los bienes o se prestaren los servicios, el procedimiento iniciado quedará sin efecto.\nEn caso de rescisión administrativa, la unidad administrativa comunicará por escrito al proveedor el incumplimiento en que haya incurrido, y se procederá conforme a lo establecido en el Reglamento.\nAsimismo, la unidad administrativa podrá dar por terminados anticipadamente los contratos cuando concurran razones de interés general, o bien, cuando por causas justificadas se extinga la necesidad de requerir los bienes o servicios originalmente contratados, y se demuestre que de continuar con el cumplimiento de las obligaciones pactadas, se ocasionaría algún daño o perjuicio al sujeto obligado correspondiente. En estos supuestos la tesorería reembolsará al proveedor los gastos no recuperables, los que correspondiente.\nARTÍCULO 54.- Los órganos estarán obligados a mantener los bienes adquiridos o arrendados en condiciones apropiadas de operación y mantenimiento, así como vigilar que determinados.\nPara los efectos del párrafo anterior, la unidad administrativa en los actos o contratos de adquisiciones, arrendamientos o servicios que promueva a instancias de los órganos, Ley de Adquisiciones, Arrendamientos y Servicios para el Estado de Baja California. Página 29 deberán estipular las condiciones que garanticen su correcta operación y funcionamiento; en su caso, la obtención de una póliza de seguro por parte del proveedor, que garantice la integridad de los bienes hasta el momento de su entrega, y de ser necesario, la capacitación del personal que operará los equipos. propiedad del proveedor, podrá realizarse cuando en las bases de la contratación se le establezca la obligación de proporcionar dicho equipo sin costo alguno, durante el tiempo requerido para el consumo de los materiales.\nCAPÍTULO QUINTO\nDE LA INFORMACIÓN Y VERIFICACIÓN\nARTÍCULO 55.- La unidad administrativa conservará en forma ordenada y sistemática, la documentación comprobatoria de los actos y contratos, por el término que corresponda, atendiendo a la Ley de Presupuesto y Ejercicio del Gasto Público del Estado de Baja California.\nArtículo Reformado\nARTICUL0 56.- La contraloría, en ejercicio de sus atribuciones, podrá verificar en cualquier tiempo, que las adquisiciones, arrendamientos y servicios se realicen conforme a lo establecido en la Ley y demás disposiciones aplicables. Si la contraloría determina la nulidad total del procedimiento de contratación por causas imputables a la convocante, el órgano reembolsará a los licitantes los gastos no recuperables en que hayan incurrido, siempre que éstos sean razonables, estén debidamente comprobados y se relacionen directamente con la operación correspondiente.\nLa contraloría podrá realizar visitas e inspecciones con base en la Ley y podrá solicitar a las partes datos e informes relacionados con los actos de que se trate.\nARTICUL0 57.- La contraloría y la unidad administrativa podrán verificar la calidad de las especificaciones de los bienes muebles, a través de los laboratorios, instituciones educativas y de investigación, o con las que cuente el órgano, o cualquier tercero con la capacidad necesaria para practicar la comprobación a que se refiere este artículo.\nEl resultado de las comprobaciones se hará constar en un dictamen que será firmado por quien lo haya realizado, así como por el proveedor y el representante de la unidad administrativa, si hubiere intervenido. La falta de firma del proveedor no invalidará el dictamen.\nCAPÍTULO SEXTO\nDE LAS INFRACCIONES Y SANCIONES\nARTICUL0 58.- Los licitantes o proveedores que infrinjan las disposiciones contenidas en la Ley, serán sancionados por la contraloría, mediante escrito en el cual se funde y motive dicha sanción, con multa equivalente a la cantidad de diez hasta quinientas veces el infracción.\nArtículo Reformado\nLey de Adquisiciones, Arrendamientos y Servicios para el Estado de Baja California. Página 30\nARTÍCULO 59.- La contraloría, además de la sanción a que se refiere el artículo anterior, inhabilitará para participar temporalmente en procedimientos de contratación o celebrar contratos regulados por la Ley, al licitante o proveedor que se ubique en alguno de los supuestos siguientes:\nI.- Los licitantes que injustificadamente y por causas imputables a los mismos no formalicen el contrato adjudicado por la convocante;\nII.- Los proveedores que se encuentren en el supuesto de la fracción III del artículo 49 de este ordenamiento;\nIII.- Los proveedores que no cumplan con sus obligaciones contractuales por causas imputables a ellos y que, como consecuencia, causen daños o perjuicios graves al órgano a favor de quien se haya contratado por parte de la unidad administrativa, así como aquellos que entreguen bienes con especificaciones sustanciales distintas de las convenidas;\nIV.- Los licitantes o proveedores que proporcionen información falsa o que actúen con dolo o mala fe en algún procedimiento de contratación, en la celebración del contrato o durante su vigencia, o bien, en la presentación o desahogo del recurso de inconformidad.\nLa inhabilitación que se imponga no será menor de seis meses ni mayor de tres años, plazo que comenzará a contarse a partir del día siguiente a la fecha en que la contraloría lo haga del conocimiento del órgano mediante publicación en el Periódico Oficial del Estado.\nArtículo Reformado\nARTÍCULO 60.- La contraloría observará el siguiente procedimiento previo a la determinación de la infracción y sanción:\nI.- Se comunicará por escrito al presunto infractor los hechos constitutivos de la infracción, para que dentro del término de diez días hábiles, exponga lo que a su derecho convenga y aporte las pruebas que estime pertinentes;\nII.- Transcurrido el término a que se refiere la fracción anterior y dentro de un plazo no mayor de diez días hábiles, se dictará la resolución que corresponda, considerando los argumentos y pruebas que se hubieren hecho valer;\nIII.- La resolución será debidamente fundada y motivada y se comunicará por escrito al infractor.\nARTÍCULO 61.- La Contraloría impondrá las sanciones, considerando:\nI.- Los daños o perjuicios que se hubieren producido o puedan producirse;\nII.- El carácter intencional de la acción u omisión constitutiva de la infracción;\nIII.- La gravedad de la infracción.\nARTÍCULO 62.- Los servidores públicos del órgano, que en ejercicio de sus funciones correspondiente.\nLey de Adquisiciones, Arrendamientos y Servicios para el Estado de Baja California. Página 31\nARTÍCULO 63.- Las y los servidores públicos que infrinjan las disposiciones contenidas en la Ley, serán sancionados en los términos de la Ley de Responsabilidades\nAdministrativas del Estado de Baja California.\nArtículo Reformado\nARTÍCULO 64.- Las responsabilidades a que se refiere la Ley, son independientes de las de orden civil o penal, que puedan derivar de la comisión de los mismos hechos.\nARTÍCULO 65.- No se impondrán sanciones o multas, cuando se haya incurrido en la infracción por causa de fuerza mayor o de caso fortuito, o cuando se observe en forma espontánea el precepto que se hubiese dejado de cumplir. No se considerará que el cumplimiento es espontáneo cuando la omisión sea descubierta por las autoridades o medie requerimiento, visita, excitativa o cualquier otra gestión efectuada por las mismas.\nCAPÍTULO SÉPTIMO\nDEL RECURSO DE INCONFORMIDAD Y DEL PROCEDIMIENTO DE CONCILIACIÓN\nSECCIÓN PRIMERA\nDEL RECURSO DE INCONFORMIDAD\nARTÍCULO 66.- Los interesados podrán interponer el recurso de inconformidad en contra de los actos y resoluciones definitivas que les afecten, emitidas por las autoridades encargadas de aplicar la Ley, o bien intentar las vías jurisdiccionales correspondientes.\nARTÍCULO 67.- El recurso de inconformidad tiene por objeto que la contraloría confirme, modifique, revoque o anule el acto administrativo impugnado.\nARTÍCULO 68.- El plazo para interponer el recurso de inconformidad será de diez días hábiles, contados a partir del día siguiente a aquél en que se hubiere notificado el acto o resolución que se recurra.\nTranscurrido el plazo antes mencionado, precluye el derecho del interesado para interponerlo, sin perjuicio de que la contraloría pueda actuar en cualquier tiempo en los términos de la Ley.\nARTÍCULO 69.- El recurso de inconformidad deberá presentarse ante la contraloría por escrito o por los medios electrónicos, y deberá contener los siguientes requisitos:\nI.- El órgano administrativo a quien se dirige y la autoridad emisora del acto impugnado;\nII.- El nombre del recurrente, del tercero perjudicado si lo hubiere y el domicilio que señale para efectos de oír y recibir notificaciones;\nIII.- El acto que se recurre y la fecha en que se le notificó o tuvo conocimiento del mismo, manifestando los hechos que se estiman irregulares, relacionados con el acto o actos impugnados;\nIV.- Manifestar bajo protesta de decir verdad, los agravios que se le causan, bajo pena de desechar el recurso en caso de no hacerlo;\nLey de Adquisiciones, Arrendamientos y Servicios para el Estado de Baja California. Página 32\nV.- En su caso, copia de la resolución o acto que se impugna y de la notificación correspondiente. Tratándose de actos que por no haberse resuelto en tiempo, se entiendan negados, deberá acompañarse el escrito de iniciación del procedimiento, o el documento sobre el cual no hubiere recaído solución alguna;\nVI.- Las pruebas que ofrezca, que tengan relación inmediata y directa con la resolución o acto impugnado, debiendo acompañar las documentales con que cuente, incluyendo las que acrediten su personalidad cuando actúen en nombre de otro o de personas morales;\nVII.- La firma del recurrente o representante legal, o el equivalente de la firma en los medios electrónicos que determine la contraloría.\nEn caso de incurrir en falsedad, respecto a la manifestación a que se refiere la fracción IV, en alguno de los hechos expresados por el recurrente, se le sancionará conforme a las disposiciones legales aplicables.\nARTÍCULO 70.- La interposición del recurso suspenderá la ejecución del acto impugnado, siempre y cuando:\nI.- Lo solicite expresamente el recurrente;\nII.- Se admita el recurso;\nIII.- No se siga perjuicio al interés social o se contravengan disposiciones de orden público;\nIV.- No se ocasionen daños o perjuicios a terceros, a menos que se garanticen éstos para el caso de no obtener resolución favorable.\nLa contraloría deberá acordar, en su caso, la suspensión o la denegación de la suspensión, dentro de los cinco días hábiles siguientes a la interposición del recurso. En caso de que la contraloría acuerde procedente la suspensión, el recurrente deberá garantizarla mediante una fianza expedida por una institución autorizada.\nARTÍCULO 71.- La fianza mencionada en el artículo anterior, tiene por objeto garantizar los daños y perjuicios que pudieran ocasionarse con motivo de la suspensión del acto impugnado, por lo que al momento de proceder dicha suspensión, el recurrente deberá presentar la fianza por el monto que fije la contraloría, de conformidad con los lineamientos que al efecto expida; sin embargo, el tercero perjudicado podrá otorgar contrafianza por el mismo monto afianzado, dejando sin efectos la suspensión concedida.\nArtículo Reformado\nARTÍCULO 72.- La suspensión tendrá como efecto que las cosas se mantengan en el estado que se encuentran en tanto se pronuncia la resolución al recurso.\nARTÍCULO 73.- Recibido el recurso por la contraloría, le solicitará a la autoridad emisora del acto impugnado, un informe sobre el asunto, así como la remisión del expediente respectivo o documentación necesaria en un plazo de diez días hábiles, a fin de que ésta pueda realizar las investigaciones procedentes.\nLey de Adquisiciones, Arrendamientos y Servicios para el Estado de Baja California. Página 33\nARTÍCULO 74.- En un término de tres días hábiles, contados a partir de la recepción del informe, la contraloría deberá resolver sobre la admisión o desechamiento del recurso, lo cual deberá de notificársele personalmente al recurrente y, en su caso, a los terceros perjudicados, para que antes de la celebración de la audiencia de Ley, manifiesten lo que a su interés convenga.\nARTÍCULO 75.- En la resolución que admita el recurso, se señalará fecha para la audiencia de Ley, la cual será única y se verificará dentro de los diez días hábiles subsecuentes a la notificación de la misma. Si dentro del plazo antes mencionado, el tercero no hace manifestación alguna, precluirá su derecho.\nARTÍCULO 76.- El recurso se tendrá por no interpuesto y se desechará cuando:\nI.- Se presente fuera de plazo;\nII.- No se haya acompañado la documentación que acredite la personalidad del recurrente;\nIII.- No se suscriba por quien deba hacerlo, a menos que se firme antes del vencimiento del plazo para interponerlo.\nARTÍCULO 77.- Se desechará por improcedente el recurso:\nI.- Contra actos que sean materia de otro recurso y que se encuentre pendiente de resolución, promovido por el mismo recurrente y respecto al mismo acto impugnado;\nII.- Contra actos que no afecten los intereses jurídicos del promovente;\nIII.- Contra actos consumados de imposible reparación;\nIV.- Contra actos consentidos expresamente;\nV.- Cuando se esté tramitando ante los tribunales algún recurso o defensa legal interpuesto por el promovente, que pueda tener por efecto modificar, revocar o nulificar el mismo acto.\nARTÍCULO 78.- Será sobreseído el recurso cuando:\nI.- El promovente se desista expresamente del recurso;\nII.- El agraviado fallezca durante el procedimiento, si el acto impugnado sólo afecta su persona; asimismo, cuando el recurrente sea una persona moral y se encuentre imposibilitada para dar seguimiento al recurso;\nIII.- Durante el procedimiento sobrevenga alguna de las causas de improcedencia a que se refiere el artículo anterior;\nIV.- Hubieren cesado los efectos del acto impugnado;\nV.- Por falta de objeto o materia del acto impugnado;\nLey de Adquisiciones, Arrendamientos y Servicios para el Estado de Baja California. Página 34\nVI.- No se probare la existencia del acto impugnado.\nARTÍCULO 79.- La audiencia de Ley tendrá por objeto admitir y desahogar las pruebas ofrecidas, así como recibir los alegatos. Se admitirán toda clase de pruebas, incluyendo las supervinientes, las que se podrán presentar hasta antes de la celebración de la audiencia, con excepción de la confesional a cargo de la autoridad, y las contrarias a la moral, el derecho y las buenas costumbres.\nPara la resolución del recurso, sólo se tomarán en cuenta los hechos, documentos o alegatos vertidos oportunamente por el recurrente, durante el procedimiento administrativo.\nARTÍCULO 80.- La contraloría deberá emitir la resolución del recurso, al término de la audiencia de Ley o dentro de los quince días hábiles siguientes a la celebración de ésta.\nARTÍCULO 81.- La resolución del recurso deberá fundarse en derecho y examinar todos y cada uno de los agravios hechos valer por el recurrente, teniendo la contraloría la facultad de invocar hechos notorios.\nSi en la resolución se ordena realizar un determinado acto o reponer el procedimiento, deberá cumplirse en un plazo de quince días hábiles.\nARTÍCULO 82.- La contraloría al resolver el recurso, podrá:\nI.- Desecharlo por improcedente o sobreseerlo;\nII.- Confirmar el acto impugnado;\nIII.- Declarar la nulidad del acto impugnado;\nIV.- Revocar total o parcialmente el acto impugnado;\nV.- Modificar u ordenar la modificación del acto impugnado, u ordenar la emisión de uno nuevo que lo sustituya.\nARTÍCULO 83.- Contra la resolución que recaiga, procede interponer recurso ante el\nTribunal Estatal de Justicia Administrativa de Baja California.\nArtículo Reformado\nSECCIÓN SEGUNDA\nDEL PROCEDIMIENTO DE CONCILIACIÓN\nARTÍCULO 84.- Los proveedores podrán presentar quejas ante la contraloría, con tengan celebrados con la unidad administrativa.\nUna vez recibida la queja respectiva, la contraloría señalará día y hora para que tenga verificativo la audiencia de conciliación y citará a las partes. La asistencia a la audiencia de conciliación será obligatoria para ambas partes, por lo que la inasistencia por parte del proveedor traerá como consecuencia tenerlo por desistido de su queja.\nLey de Adquisiciones, Arrendamientos y Servicios para el Estado de Baja California. Página 35\nARTÍCULO 85.- En el supuesto de que las partes lleguen a una conciliación, el convenio respectivo obligará a las mismas, y su cumplimiento podrá ser demandado por la vía jurisdiccional correspondiente.\nEn caso contrario, quedarán a salvo sus derechos, para que los hagan valer ante los tribunales estatales competentes.\nARTÍCULO 86.- El procedimiento de conciliación deberá ajustarse a lo previsto en el\nReglamento.\nCAPÍTULO OCTAVO\nDE LAS BASES GENERALES PARA LAS ADQUISICIONES, ARRENDAMIENTOS Y\nSERVICIOS EN EL ÁMBITO MUNICIPAL\nARTÍCULO 87.- Los Ayuntamientos deberán emitir disposiciones reglamentarias que normen la planeación, programación, presupuestación, contratación, gasto y control de las adquisiciones, arrendamientos y servicios, en sus respectivas competencias.\nARTÍCULO 88.- Los Ayuntamientos deberán establecer y desarrollar en sus reglamentos las siguientes bases:\nI.- Las autoridades responsables de aplicar las disposiciones en la materia;\nII.- Las actividades comprendidas como adquisiciones, arrendamientos y servicios, según lo dispuesto en el artículo 4 de la Ley;\nIII.- Que sus programas de adquisiciones, arrendamientos y servicios, se ajustarán a lo dispuesto en el artículo 14 de la Ley, en lo que resulte aplicable;\nIV.- La creación y funcionamiento de un Comité u órgano equivalente;\nV.- Los procedimientos a que se refieren los artículos 21, 23, 24, 38 y 42 de la Ley;\nVI.- Los elementos que deberán contener los contratos a que se refiere el artículo 44 de la Ley;\nVII.- Las prohibiciones a que se refiere el artículo 49 de la Ley;\nVIII.- La autoridad responsable del cumplimiento de las disposiciones de verificación;\nIX.- Las infracciones y sanciones a que se refiere el Capítulo Sexto de esta Ley;\nX.- El recurso que podrán interponer los licitantes o proveedores, así como la instancia responsable de conocerlo.\nARTICULOS TRANSITORIOS:\nPRIMERO.- La presente Ley entrará en vigor al día siguiente de su publicación en el\nPeriódico Oficial del Estado de Baja California.\nLey de Adquisiciones, Arrendamientos y Servicios para el Estado de Baja California. Página 36 dentro de los ciento ochenta días siguientes a la entrada en vigor de la misma.\nTERCERO.- Los Ayuntamientos deberán reglamentar la materia, de conformidad con lo establecido en la presente Ley, dentro de los ciento ochenta días siguientes a la entrada en vigor de la misma.\nDADO en el Salón de Sesiones “Lic. Benito Juárez García” del Honorable Poder\nLegislativo, en la ciudad de Mexicali, Baja California, a los veinticinco días del mes de septiembre del año dos mil dos.\nDIP. JESUS ALEJANDRO RUIZ URIBE\nPRESIDENTE\n(RÚBRICA)\nDIP. LAURA SANCHEZ MEDRANO\nSECRETARIA\n(RÚBRICA)\nDE CONFORMIDAD CON LO DISPUESTO POR LA FRACCION I DEL ARTICULO 49\nDE LA CONSTITUCION POLITICA DEL ESTADO, MANDO SE IMPRIMA Y PUBLIQUE.\nMEXICALI, BAJA CALIFORNIA, A LOS DOS DIAS DEL MES DE OCTUBRE DEL\nAÑO DOS MIL DOS.\nGOBERNADOR DEL ESTADO\nEUGENIO ELORDUY WALTHER\n(RÚBRICA)\nSECRETARIO GENERAL DE GOBIERNO\nBERNARDO BORBON VILCHES\n(RÚBRICA)\nLey de Adquisiciones, Arrendamientos y Servicios para el Estado de Baja California. Página 37\nARTÍCULO 1.- Fue reformado por Decreto No. 386, publicado en el Periódico Oficial\nLegislatura, siendo Gobernadora Constitucional la C. Marina del Pilar Ávila Olmeda 20212027;\nARTÍCULO 2.- Fue reformado mediante Decreto No. 248, publicado en el Periódico\nOficial No. 39, de fecha 07 de julio de 2023, Tomo CXXX, Índice, expedido por la H. XXIV\nLegislatura, siendo Gobernadora Constitucional la C. Marina del Pilar Ávila Olmeda 20212027; fue reformado por Decreto No. 386, publicado en el Periódico Oficial No. 13, de fecha\n08 de marzo de 2024, Sección I, Tomo CXXXI, expedido por la H. XXIV Legislatura, siendo\nGobernadora Constitucional la C. Marina del Pilar Ávila Olmeda 2021-2027;\nARTÍCULO 3.- Fue reformado por Decreto No. 283, publicado en el Periódico Oficial\nNo. 48, de fecha 30 de octubre de 2009, Tomo CXVI, Sección II, expedido por la Honorable\nXIX Legislatura, siendo Gobernador Constitucional el C. Lic. José Guadalupe Osuna Millán, 2007-2013; fue reformado por Decreto No. 345, publicado en el Periódico Oficial No. 7, de fecha 05 de febrero de 2010, Tomo CXVII, Sección I, expedido por la Honorable XIX\nLegislatura, siendo Gobernador Constitucional el C. Lic. José Guadalupe Osuna Millán, 2007-2013; fue reformado por Decreto No. 193, publicado en el Periódico Oficial No. 24, de fecha 25 de mayo de 2012, Tomo CXIX, expedido por la Honorable XX Legislatura, siendo\nGobernador Constitucional el C. Lic. José Guadalupe Osuna Millán, 2007-2013; fue reformado por Decreto No. 93, publicado en el Periódico Oficial No. 43, Sección I, de fecha\n29 de agosto de 2014, Tomo CXXI, expedido por la H. XXI Legislatura, siendo Gobernador\nConstitucional el C. Francisco Arturo Vega de Lamadrid 2013-2019; fue reformado por\nDecreto No. 205, publicado en el Periódico Oficial No. 20, Sección VII, de fecha 20 de abril de 2018, Tomo CXXV, expedido por la H. XXII Legislatura, siendo Gobernador\nConstitucional el C. Francisco Arturo Vega de Lamadrid 2013-2019; fue reformado por\nDecreto No. 245, publicado en el Periódico Oficial No. 47, Sección II, Tomo CXXVIII de fecha\n02 de julio de 2021, expedido por la H. XXIII Legislatura, siendo Gobernador Constitucional el C. Jaime Bonilla Valdez 2019-2021; fue reformado por Decreto No. 386, publicado en el\nPeriódico Oficial No. 13, de fecha 08 de marzo de 2024, Sección I, Tomo CXXXI, expedido por la H. XXIV Legislatura, siendo Gobernadora Constitucional la C. Marina del Pilar Ávila\nOlmeda 2021-2027;\nARTÍCULO 4.- Fue reformado por Decreto No. 283, publicado en el Periódico Oficial\nNo. 48, de fecha 30 de octubre de 2009, Tomo CXVI, Sección II, expedido por la Honorable\nXIX Legislatura, siendo Gobernador Constitucional el C. Lic. José Guadalupe Osuna Millán, 2007-2013; fue reformado por Decreto No. 386, publicado en el Periódico Oficial No. 13, de siendo Gobernadora Constitucional la C. Marina del Pilar Ávila Olmeda 2021-2027;\nARTÍCULO 6.- Fue reformado por Decreto No. 315, publicado en el Periódico Oficial\nLegislatura, siendo Gobernador Constitucional el C. Lic. José Guadalupe Osuna Millán, 2007-2013;\nARTÍCULO 8.- Fue reformado por Decreto No. 345, publicado en el Periódico Oficial\nLey de Adquisiciones, Arrendamientos y Servicios para el Estado de Baja California. Página 38\nXIX Legislatura, siendo Gobernador Constitucional el C. Lic. José Guadalupe Osuna Millán, 2007-2013; fue reformado por Decreto No. 193, publicado en el Periódico Oficial No. 24, de\nGobernador Constitucional el C. Lic. José Guadalupe Osuna Millán, 2007-2013; fue reformado por Decreto No. 93, publicado en el Periódico Oficial No. 43, Sección I, de fecha\n29 de agosto de 2014, Tomo CXXI, expedido por la H. XXI Legislatura, siendo Gobernador\nConstitucional el C. Francisco Arturo Vega de Lamadrid 2013-2019, fue reformado por\nDecreto No. 142, publicado en el Periódico Oficial No. 50, Sección VI, Tomo CXXIV de fecha\n10 de noviembre de 2017, expedido por la H. XXII Legislatura, siendo Gobernador\nConstitucional el C. Francisco Arturo Vega de Lamadrid 2013-2019; fue reformado por\nDecreto No. 245, publicado en el Periódico Oficial No. 47, Sección II, Tomo CXXVIII de fecha\n02 de julio de 2021, expedido por la H. XXIII Legislatura, siendo Gobernador Constitucional el C. Jaime Bonilla Valdez 2019-2021; fue reformado por Decreto No. 386, publicado en el\nPeriódico Oficial No. 13, de fecha 08 de marzo de 2024, Sección I, Tomo CXXXI, expedido por la H. XXIV Legislatura, siendo Gobernadora Constitucional la C. Marina del Pilar Ávila\nOlmeda 2021-2027;\nARTÍCULO 9.- Fue reformado por Decreto No. 314, publciado en el Periódico Oficial\nNo. 52, de fecha 23 de noviembre de 2012, Sección I, Tomo CXIX, Expedido por la\nHonorable XX Legislatura, siendo Gobernador Constitucional el C. LIc. José Guadalupe\nOsuna Millán 2007-2013; fue reformado por Decreto No. 519, publicado en el Periódico\nOficial No. 41, de fecha 20 septiembre de 2013, Tomo CXX, expedido por la H. XX\nLegislatura, siendo Gobernador Constitucional el C. José Guadalupe Osuna Millán 20072013;\nARTÍCULO 11.- Fue reformado por Decreto No. 283, publicado en el Periódico Oficial\nNo. 48, de fecha 30 de octubre de 2009, Tomo CXVI, Sección II, expedido por la Honorable\nXIX Legislatura, siendo Gobernador Constitucional el C. Lic. José Guadalupe Osuna Millán, 2007-2013; fue reformado por Decreto No. 193, publicado en el Periódico Oficial No. 24, de fecha 25 de mayo de 2012, Tomo CXIX, expedido por la Honorable XX Legislatura, siendo\nGobernador Constitucional el C. Lic. José Guadalupe Osuna Millán, 2007-2013; fue reformado por Decreto No. 93, publicado en el Periódico Oficial No. 43, Sección I, de fecha\n29 de agosto de 2014, Tomo CXXI, expedido por la H. XXI Legislatura, siendo Gobernador\nConstitucional el C. Francisco Arturo Vega de Lamadrid 2013-2019;\nARTÍCULO 13.- Fue reformado por Decreto No. 546, publicado en el Periódico Oficial\nNo. 41, Sección I, Tomo CXXIII, de fecha 09 de septiembre de 2016, expedido por la H. XXI\nLegislatura, siendo gobernador constitucional el C. Francisco Arturo Vega de Lamadrid\n2013-2019; fue reformado por Decreto No. 245, publicado en el Periódico Oficial No. 47, siendo Gobernador Constitucional el C. Jaime Bonilla Valdez 2019-2021;\nARTÍCULO 14.- Fue reformado por Decreto No. 315, publicado en el Periódico Oficial\nLegislatura, siendo Gobernador Constitucional el C. Lic. José Guadalupe Osuna Millán, 2007-2013; fue reformado por Decreto No. 386, publicado en el Periódico Oficial No. 13, de\nLey de Adquisiciones, Arrendamientos y Servicios para el Estado de Baja California. Página 39\nLegislatura, siendo Gobernadora Constitucional la C. Marina del Pilar Ávila Olmeda 20212027;\nARTÍCULO 15.- Fue reformado por Decreto No. 345, publicado en el Periódico Oficial\nXIX Legislatura, siendo Gobernador Constitucional el C. Lic. José Guadalupe Osuna Millán, 2007-2013;\nARTÍCULO 17.- Fue reformado por Decreto No. 193, publicado en el Periódico Oficial\nNo. 24, de fecha 25 de mayo de 2012, Tomo CXIX, expedido por la Honorable XX\nLegislatura, siendo Gobernador Constitucional el C. Lic. José Guadalupe Osuna Millán, 2007-2013; fue reformado por Decreto No. 93, publicado en el Periódico Oficial No. 43,\nSección I, de fecha 29 de agosto de 2014, Tomo CXXI, expedido por la H. XXI Legislatura, siendo Gobernador Constitucional el C. Francisco Arturo Vega de Lamadrid 2013-2019;\nARTÍCULO 18.- Fue reformado por Decreto No. 193, publicado en el Periódico Oficial\nNo. 24, de fecha 25 de mayo de 2012, Tomo CXIX, expedido por la Honorable XX\nLegislatura, siendo Gobernador Constitucional el C. Lic. José Guadalupe Osuna Millán, 2007-2013; fue reformado por Decreto No. 93, publicado en el Periódico Oficial No. 43,\nSección I, de fecha 29 de agosto de 2014, Tomo CXXI, expedido por la H. XXI Legislatura, siendo Gobernador Constitucional el C. Francisco Arturo Vega de Lamadrid 2013-2019; fue reformado por Decreto No. 205, publicado en el Periódico Oficial No. 20, Sección VII, de fecha 20 de abril de 2018, Tomo CXXV, expedido por la H. XXII Legislatura, siendo\nGobernador Constitucional el C. Francisco Arturo Vega de Lamadrid 2013-2019; fue reformado por Decreto No. 386, publicado en el Periódico Oficial No. 13, de fecha 08 de marzo de 2024, Sección I, Tomo CXXXI, expedido por la H. XXIV Legislatura, siendo\nGobernadora Constitucional la C. Marina del Pilar Ávila Olmeda 2021-2027;\nFue adicionado este Capítulo mediante Decreto No. 546, publicado en el Periódico\nOficial No. 41, Sección I, Tomo CXXIII, de fecha 09 de septiembre de 2016, expedido por la\nH. XXI Legislatura, siendo gobernador constitucional el C. Francisco Arturo Vega de\nLamadrid 2013-2019;\nCAPÍTULO SEGUNDO BIS\nDEL PADRÓN DE PROVEEDORES\nARTÍCULO 19 BIS 1.- Fue por Decreto No. 546, publicado en el Periódico Oficial No.\n41, Sección I, Tomo CXXIII, de fecha 09 de septiembre de 2016, expedido por la H. XXI\nLegislatura, siendo gobernador constitucional el C. Francisco Arturo Vega de Lamadrid\n2013-2019;\nARTÍCULO 19 BIS 2.- Fue por Decreto No. 546, publicado en el Periódico Oficial No.\nLegislatura, siendo gobernador constitucional el C. Francisco Arturo Vega de Lamadrid\n2013-2019;.\nARTÍCULO 19 BIS 3.- Fue por Decreto No. 546, publicado en el Periódico Oficial No.\nLegislatura, siendo gobernador constitucional el C. Francisco Arturo Vega de Lamadrid\nLey de Adquisiciones, Arrendamientos y Servicios para el Estado de Baja California. Página 40\n2013-2019;.\nARTÍCULO 19 BIS 4.- Fue por Decreto No. 546, publicado en el Periódico Oficial No.\nLegislatura, siendo gobernador constitucional el C. Francisco Arturo Vega de Lamadrid\n2013-2019;.\nARTÍCULO 20.- Fue reformado por Decreto No. 386, publicado en el Periódico Oficial\nNo. 13, de fecha 08 de marzo de 2024, Sección I, Tomo CXXXI, expedido por la H. XXIV\nLegislatura, siendo Gobernadora Constitucional la C. Marina del Pilar Ávila Olmeda 20212027;\nARTÍCULO 21.- Fue reformado por Decreto No. 142, publicado en el Periódico Oficial\nNo. 50, Sección VI, Tomo CXXIV de fecha 10 de noviembre de 2017, expedido por la H. XXII\nLegislatura, siendo Gobernador Constitucional el C. Francisco Arturo Vega de Lamadrid\n2013-2019; fue reformado mediante Decreto No. 248, publicado en el Periódico Oficial No.\n39, de fecha 07 de julio de 2023, Tomo CXXX, Índice, expedido por la H. XXIV Legislatura, siendo Gobernadora Constitucional la C. Marina del Pilar Ávila Olmeda 2021-2027;\nARTÍCULO 22.- Fue reformado por Decreto No. 386, publicado en el Periódico Oficial\nNo. 13, de fecha 08 de marzo de 2024, Sección I, Tomo CXXXI, expedido por la H. XXIV\nLegislatura, siendo Gobernadora Constitucional la C. Marina del Pilar Ávila Olmeda 20212027;\nARTÍCULO 24.- Fue reformado por Decreto No. 386, publicado en el Periódico Oficial\nNo. 13, de fecha 08 de marzo de 2024, Sección I, Tomo CXXXI, expedido por la H. XXIV\nLegislatura, siendo Gobernadora Constitucional la C. Marina del Pilar Ávila Olmeda 20212027;\nARTÍCULO 26.- Fue reformado por Decreto No. 283, publicado en el Periódico Oficial\nNo. 48, de fecha 30 de octubre de 2009, Tomo CXVI, Sección II, expedido por la Honorable\nXIX Legislatura, siendo Gobernador Constitucional el C. Lic. José Guadalupe Osuna Millán, 2007-2013; fue reformado por Decreto No. 193, publicado en el Periódico Oficial No. 24, de fecha 25 de mayo de 2012, Tomo CXIX, expedido por la Honorable XX Legislatura, siendo\nGobernador Constitucional el C. Lic. José Guadalupe Osuna Millán, 2007-2013; fue reformado por Decreto No. 93, publicado en el Periódico Oficial No. 43, Sección I, de fecha\nConstitucional el C. Francisco Arturo Vega de Lamadrid 2013-2019; fue reformado por\nDecreto No. 245, publicado en el Periódico Oficial No. 47, Sección II, Tomo CXXVIII de fecha el C. Jaime Bonilla Valdez 2019-2021;\nARTÍCULO 27.- Fue reformado por Decreto No. 142, publicado en el Periódico Oficial\nLegislatura, siendo Gobernador Constitucional el C. Francisco Arturo Vega de Lamadrid\n2013-2019;\nLey de Adquisiciones, Arrendamientos y Servicios para el Estado de Baja California. Página 41\nARTÍCULO 28.- Fue reformado por Decreto No. 283, publicado en el Periódico Oficial\nXIX Legislatura, siendo Gobernador Constitucional el C. Lic. José Guadalupe Osuna Millán, 2007-2013; fue reformado por Decreto No. 345, publicado en el Periódico Oficial No. 7, de\nLegislatura, siendo Gobernador Constitucional el C. Lic. José Guadalupe Osuna Millán, 2007-2013; fue reformado por Decreto No. 245, publicado en el Periódico Oficial No. 47,\nSección II, Tomo CXXVIII de fecha 02 de julio de 2021, expedido por la H. XXIII Legislatura, siendo Gobernador Constitucional el C. Jaime Bonilla Valdez 2019-2021;\nARTÍCULO 30.- Fue reformado por Decreto No. 345, publicado en el Periódico Oficial\nNo. 7, de fecha 05 de febrero de 2010, Tomo CXVII, Sección I, expedido por la Honorable\nXIX Legislatura, siendo Gobernador Constitucional el C. Lic. José Guadalupe Osuna Millán, 2007-2013;\nARTÍCULO 33.- Fue reformado por Decreto No. 345, publicado en el Periódico Oficial\nNo. 7, de fecha 05 de febrero de 2010, Tomo CXVII, Sección I, expedido por la Honorable\nXIX Legislatura, siendo Gobernador Constitucional el C. Lic. José Guadalupe Osuna Millán, 2007-2013; fue reformado por Decreto No. 245, publicado en el Periódico Oficial No. 47,\nSección II, Tomo CXXVIII de fecha 02 de julio de 2021, expedido por la H. XXIII Legislatura, siendo Gobernador Constitucional el C. Jaime Bonilla Valdez 2019-2021;\nARTÍCULO 34.- Fue reformado por Decreto No. 386, publicado en el Periódico Oficial\nNo. 13, de fecha 08 de marzo de 2024, Sección I, Tomo CXXXI, expedido por la H. XXIV\nLegislatura, siendo Gobernadora Constitucional la C. Marina del Pilar Ávila Olmeda 20212027;\nARTÍCULO 35.- Fue reformado por Decreto No. 386, publicado en el Periódico Oficial\nNo. 13, de fecha 08 de marzo de 2024, Sección I, Tomo CXXXI, expedido por la H. XXIV\nLegislatura, siendo Gobernadora Constitucional la C. Marina del Pilar Ávila Olmeda 20212027;\nARTÍCULO 37.- Fue reformado por Decreto No. 386, publicado en el Periódico Oficial\nNo. 13, de fecha 08 de marzo de 2024, Sección I, Tomo CXXXI, expedido por la H. XXIV\nLegislatura, siendo Gobernadora Constitucional la C. Marina del Pilar Ávila Olmeda 20212027;\nARTÍCULO 38.- Fue reformado por Decreto No. 345, publicado en el Periódico Oficial\nXIX Legislatura, siendo Gobernador Constitucional el C. Lic. José Guadalupe Osuna Millán, 2007-2013; fue reformado por Decreto No. 386, publicado en el Periódico Oficial No. 13, de siendo Gobernadora Constitucional la C. Marina del Pilar Ávila Olmeda 2021-2027;\nARTÍCULO 39.- Fue reformado por Decreto No. 193, publicado en el Periódico Oficial\nLey de Adquisiciones, Arrendamientos y Servicios para el Estado de Baja California. Página 42\nLegislatura, siendo Gobernador Constitucional el C. Lic. José Guadalupe Osuna Millán, 2007-2013;\nARTÍCULO 40.- Fue reformado por Decreto No. 386, publicado en el Periódico Oficial\nLegislatura, siendo Gobernadora Constitucional la C. Marina del Pilar Ávila Olmeda 20212027;\nARTÍCULO 41.- Fue reformado por Decreto No. 245, publicado en el Periódico Oficial\nNo. 47, Sección II, Tomo CXXVIII de fecha 02 de julio de 2021, expedido por la H. XXIII\nLegislatura, siendo Gobernador Constitucional el C. Jaime Bonilla Valdez 2019-2021;\nARTÍCULO 42.- Fue reformado por Decreto No. 142, publicado en el Periódico Oficial\nNo. 50, Sección VI, Tomo CXXIV de fecha 10 de noviembre de 2017, expedido por la H. XXII\nLegislatura, siendo Gobernador Constitucional el C. Francisco Arturo Vega de Lamadrid\n2013-2019; fue reformado por Decreto No. 386, expedido por la H. XXIV Legislatura, siendo\nGobernadora Constitucional la C. Marina del Pilar Ávila Olmeda 2021-2027;\nARTÍCULO 44.- Fue reformado por Decreto No. 283, publicado en el Periódico Oficial\nNo. 48, de fecha 30 de octubre de 2009, Tomo CXVI, Sección II, expedido por la Honorable\nXIX Legislatura, siendo Gobernador Constitucional el C. Lic. José Guadalupe Osuna Millán, 2007-2013; fue reformado por Decreto No. 193, publicado en el Periódico Oficial No. 24, de fecha 25 de mayo de 2012, Tomo CXIX, expedido por la Honorable XX Legislatura, siendo\nGobernador Constitucional el C. Lic. José Guadalupe Osuna Millán, 2007-2013; fue reformado por Decreto No. 386, publicado en el Periódico Oficial No. 13, de fecha 08 de marzo de 2024, Sección I, Tomo CXXXI, expedido por la H. XXIV Legislatura, siendo\nGobernadora Constitucional la C. Marina del Pilar Ávila Olmeda 2021-2027;\nARTÍCULO 45.- Fue reformado por Decreto No. 345, publicado en el Periódico Oficial\nNo. 7, de fecha 05 de febrero de 2010, Tomo CXVII, Sección I, expedido por la Honorable\nXIX Legislatura, siendo Gobernador Constitucional el C. Lic. José Guadalupe Osuna Millán, 2007-2013;\nARTÍCULO 47.- Fue reformado por Decreto No. 345, publicado en el Periódico Oficial\nNo. 7, de fecha 05 de febrero de 2010, Tomo CXVII, Sección I, expedido por la Honorable\nXIX Legislatura, siendo Gobernador Constitucional el C. Lic. José Guadalupe Osuna Millán, 2007-2013;\nARTÍCULO 49.- Fue reformado por Decreto No. 289, publicado en el Periódico Oficial\nHonorable XIX Legislatura, siendo Gobernador Constitucional el C. Lic. José Guadalupe\nOsuna Millán, 2007-2013; fue reformado por Decreto No. 345, publicado en el Periódico\nHonorable XIX Legislatura, siendo Gobernador Constitucional el C. Lic. José Guadalupe\nOsuna Millán, 2007-2013; Fue reformado por Decreto No. 546, publicado en el Periódico\nH. XXI Legislatura, siendo Gobernador Constitucional el C. Francisco Arturo Vega de\nLamadrid 2013-2019; fue reformado por Decreto No. 386, publicado en el Periódico Oficial\nLey de Adquisiciones, Arrendamientos y Servicios para el Estado de Baja California. Página 43\nLegislatura, siendo Gobernadora Constitucional la C. Marina del Pilar Ávila Olmeda 20212027;\nARTÍCULO 51 BIS.- Fue adicionado por Decreto No. 386, publicado en el Periódico\nXXIV Legislatura, siendo Gobernadora Constitucional la C. Marina del Pilar Ávila Olmeda\n2021-2027;\nARTÍCULO 52.- Fue reformado por Decreto No. 345, publicado en el Periódico Oficial\nNo. 7, de fecha 05 de febrero de 2010, Tomo CXVII, Sección I, expedido por la Honorable\nXIX Legislatura, siendo Gobernador Constitucional el C. Lic. José Guadalupe Osuna Millán, 2007-2013;\nARTÍCULO 55.- Fue reformado por Decreto No. 315, publicado en el Periódico Oficial\nNo. 9, de fecha 15 de febrero de 2013, Sección I, Tomo CXX, expedido por la Honorable XX\nLegislatura, siendo Gobernador Constitucional el C. Lic. José Guadalupe Osuna Millán, 2007-2013;\nARTÍCULO 58.- Fue reformado por Decreto No. 281, publicado en el Periódico Oficial\nNo. 55, Sección IV, Tomo CXXV de fecha 30 de noviembre de 2018, expedido por la H. XXII\nLegislatura, siendo Gobernador Constitucional el C. Francisco Arturo Vega de Lamadrid\n2013-2019;\nARTÍCULO 59.- Fue reformado por Decreto No. 193, publicado en el Periódico Oficial\nNo. 24, de fecha 25 de mayo de 2012, Tomo CXIX, expedido por la Honorable XX\nLegislatura, siendo Gobernador Constitucional el C. Lic. José Guadalupe Osuna Millán, 2007-2013; fue reformado por Decreto No. 93, publicado en el Periódico Oficial No. 43,\nSección I, de fecha 29 de agosto de 2014, Tomo CXXI, expedido por la H. XXI Legislatura, siendo Gobernador Constitucional el C. Francisco Arturo Vega de Lamadrid 2013-2019;\nARTÍCULO 63.- Fue reformado por Decreto No. 386, publicado en el Periódico Oficial\nNo. 13, de fecha 08 de marzo de 2024, Sección I, Tomo CXXXI, expedido por la H. XXIV\nLegislatura, siendo Gobernadora Constitucional la C. Marina del Pilar Ávila Olmeda 20212027;\nARTÍCULO 71.- Fue reformado por Decreto No. 193, publicado en el Periódico Oficial\nLegislatura, siendo Gobernador Constitucional el C. Lic. José Guadalupe Osuna Millán, 2007-2013; fue reformado por Decreto No. 93, publicado en el Periódico Oficial No. 43, siendo Gobernador Constitucional el C. Francisco Arturo Vega de Lamadrid 2013-2019;\nARTÍCULO 83.- Fue reformado por Decreto No. 386, publicado en el Periódico Oficial\nLegislatura, siendo Gobernadora Constitucional la C. Marina del Pilar Ávila Olmeda 20212027;\nLey de Adquisiciones, Arrendamientos y Servicios para el Estado de Baja California. Página 44\nARTICULO CUARTO TRANSITORIO DEL DECRETO No. 283, POR EL QUE SE\nREFORMAN LA FRACCIÓN IX DEL ARTÍCULO 4, LA FRACCIÓN XII DEL ARTÍCULO 26,\nLA ADICIÓN DE LA FRACCIÓN XV DEL ARTÍCULO 3, UN PÁRRAFO FINAL AL\nARTÍCULO 11, LA FRACCIÓN XX AL ARTÍCULO 28 Y LA FRACCIÓN XIII DEL ARTÍCULO\n44, PUBLICADO EN EL PERIODICO OFICIAL No. 48, DE FECHA 30 DE OCTUBRE DE\n2009, TOMO CXVI, SECCION II, EXPEDIDO POR LA H. XIX LEGISLATURA DEL ESTADO,\nSIENDO GOBERNADOR CONSTITUCIONAL EL C. LIC. JOSE GUADALUPE OSUNA\nMILLAN 2007-2013\nARTÍCULO TRANSITORIO\nÚNICO: Las presentes reformas entrarán en vigor al día siguiente de su publicación en el Periódico Oficial del Estado.\nDADO en el Salón de Sesiones “Lic. Benito Juárez García” del H. Poder Legislativo del Estado de Baja California, en la Ciudad de Mexicali, B.C., a los treinta días del mes de septiembre de dos mil nueve, rúbrica la Mesa Directiva del Primer Periodo Ordinario de\nSesiones del Tercer Año de Ejercicio Constitucional, el día quince de octubre de dos mil nueve.\nDIP. ANTONIO RICARDO CANO JIMÉNEZ\nPRESIDENTE\n(RÚBRICA)\nDIP. RUBÉN ERNESTO ARMENTA ZANABIA\nSECRETARIO\n(RÚBRICA)\nDE CONFORMIDAD CON LO DISPUESTO POR LA FRACCIÓN I DEL ARTÍCULO 49\nMEXICALI, BAJA CALIFORNIA, A LOS VEINTISÉIS DIAS DEL MES DE OCTUBRE\nDEL AÑO DOS MIL NUEVE.\nJOSÉ GUADALUPE OSUNA MILLÁN\nGOBERNADOR DEL ESTADO.\n(RÚBRICA)\nJOSÉ FRANCISCO BLACKE MORA\nSECRETARIO GENERAL DE GOBIERNO\n(RÚBRICA)\nARTICULO TRANSITORIO DEL DECRETO No. 289, POR EL QUE SE APRUEBA\nEL PERIODICO OFICIAL No. 51, SECCION II, TOMO CXVI, DE FECHA 13 DE\nLey de Adquisiciones, Arrendamientos y Servicios para el Estado de Baja California. Página 45\nGOBERNADOR CONSTITUCIONAL EL C. JOSE GUADALUPE OSUNA MILLAN 2007-\n2013.\nARTÍCULOS TRANSITORIOS:\nPRIMERO.- Las presentes reformas a la Ley de Adquisiciones, Arrendamientos y\nServicios para el Estado de Baja California, entrarán en vigor al día siguiente al de su publicación en el Periódico Oficial, órgano de Gobierno del Estado.\nSEGUNDO.- Se derogan todas las disposiciones que se opongan a las presentes reformas.\nDADO en el Salón de Sesiones “Lic. Benito Juárez García” del H. Poder Legislativo del Estado de Baja California, en la Ciudad de Mexicali, B.C., a los quince días del mes de octubre de dos mil nueve.\nDIP. ANTONIO RICARDO CANO JIMÉNEZ\n(RÚBRICA)\nDIP. RUBÉN ERNESTO ARMENTA ZANABIA\n(RÚBRICA)\nDE CONFORMIDAD CON LO DISPUESTO POR LA FRACCION I DEL ARTÍCULO 49\nMEXICALI, BAJA CALIFORNIA, A LOS VEINTISEIS DIAS DEL MES DE OCTUBRE\nDEL AÑO DOS MIL NUEVE.\nGOBERNADOR DEL ESTADO\nJOSE GUADALUPE OSUNA MILLAN\n(RÚBRICA)\nSECRETARIO GENERAL DE GOBIERNO\nJOSE FRANCISCO BLAKE MORA\n(RÚBRICA)\nARTICULO TRANSITORIO DEL DECRETO No. 345, POR EL QUE SE APRUEBA\nLA REFORMA A LOS ARTÍCULOS 3, 8, 15, 28, 30, 33, 38, 45, 47, 49 Y 52 49,\nPUBLICADO EN EL PERIODICO OFICIAL No. 07, SECCION I, TOMO CXVII, EXPEDIDO\nPOR LA H. XIX LEGISLATURA, SIENDO GOBERNADOR CONSTITUCIONAL EL C. JOSE\nGUADALUPE OSUNA MILLAN 2007-2013.\nARTÍCULOS TRANSITORIOS\nPRIMERO.- Las presentes reformas entrarán en vigor al día siguiente de su publicación en el Periódico Oficial del Estado de Baja California.\nLey de Adquisiciones, Arrendamientos y Servicios para el Estado de Baja California. Página 46\nSEGUNDO.- La unidad administrativa respectiva, dentro del plazo de noventa días posteriores a la entrada en vigor del presente Decreto, deberá dictaminar si los criterios\nEstado o sus municipios, se encuentran actualizados a las condiciones generales del mercado, considerando la naturaleza de los bienes o servicios. De no ser así, procederá a actualizarlos en los términos del presente Dictamen.\nDADO en el Salón de Sesiones “Lic. Benito Juárez García” del H. Poder Legislativo del Estado de Baja California, en la ciudad de Mexicali, B.C., a los veintiocho días del mes de diciembre de dos mil nueve.\nDIP. ANTONIO RICARDO CANO JIMÉNEZ\n(RÚBRICA)\nDIP. RUBÉN ERNESTO ARMENTA ZANABIA\n(RÚBRICA)\nDE CONFORMIDAD CON LO DISPUESTO POR LA FRACCION I DEL ARTÍCULO 49\nMEXICALI, BAJA CALIFORNIA, A LOS DIECIOCHO DIAS DEL MES DE ENERO\nDEL AÑO DOS MIL DIEZ.\nGOBERNADOR DEL ESTADO\nJOSE GUADALUPE OSUNA MILLAN\n(RÚBRICA)\nSECRETARIO GENERAL DE GOBIERNO\nJOSE FRANCISCO BLAKE MORA\n(RÚBRICA)\nARTÍCULO ÚNICO TRANSITORIO DEL DECRETO No. 193, POR EL QUE SE\nREFORMA LA FRACCIÓN VIII DEL ARTÍCULO 3; LOS ARTÍCULOS 8, 11 Y SU PÁRRAFO\nTERCERO, 17, 18, FRACCIÓN II DEL ARTÍCULO 26, SEGUNDO PÁRRAFO DEL\nARTÍCULO 39, SEGUNDO PÁRRAFO DEL ARTÍCULO 59 Y ARTÍCULO 71, SE ADICIONA\nUN PÁRRAFO TERCERO AL ARTÍCULO 39, Y SE ADICIONAN LAS FRACCIONES XIII Y\nXIV AL ARTÍCULO 44 RECORRIÉNDOSE LA SUBSECUENTE, PUBLICADO EN EL\nPOR LA H. XX LEGISLATURA DEL ESTADO, SIENDO GOBERNADOR\nCONSTITUCIONAL EL C. LIC. JOSÉ GUADALUPE OSUNA MILLÁN 2007-2013.\nTRANSITORIOS\nPRIMERO.- El presente Decreto entrará en vigor al día siguiente de su publicación en el Periódico Oficial del Estado.\nLey de Adquisiciones, Arrendamientos y Servicios para el Estado de Baja California. Página 47\nSEGUNDO.- El Ejecutivo del Estado en un término no mayor de 60 días contados a de Adquisiciones, Arrendamientos y Servicios para el Estado de Baja California.\nTERCERO.- Hasta en tanto se modifique el Reglamento, las Secretarías de\nPlaneación y Finanzas; y de Desarrollo Económico, podrán emitir las disposiciones de carácter general que consideren necesarias para la aplicación del presente Decreto.\nDADO en el Salón de Sesiones “Lic. Benito Juárez García” del H. Poder Legislativo del Estado de Baja California, en la Ciudad de Mexicali, B.C., a los diecisiete días del mes de abril del año dos mil doce.\nDIP. DAVID JORGE LOZANO PÉREZ\nPRESIDENTE\n(RÚBRICA)\nDIP. ALFONSO GARZÓN ZATARAIN\nSECRETARIO\n(RÚBRICA)\nDE CONFORMIDAD CON LO DISPUESTO POR LA FRACCIÓN I DEL ARTÍCULO 49\nMEXICALI, BAJA CALIFORNIA, A LOS TREINTA DÍAS DEL MES DE ABRIL DEL\nAÑO DOS MIL DOCE.\nJOSÉ GUADALUPE OSUNA MILLÁN\nGOBERNADOR DEL ESTADO\n(RÚBRICA)\nCUAUHTÉMOC CARDONA BENAVIDES\nSECRETARIO GENERAL DE GOBIERNO\n(RÚBRICA)\nARTÍCULO TERCERO TRANSITORIO DEL DECRETO NO. 314, POR EL QUE SE\nAPRUEBA LA ADICIÓN DE UN PÁRRAFO SEGUNDO AL ARTÍCULO 9; PUBLICADO EN\nTOMO CXIX, EXPEDIDO POR LA H. XX LEGISLATURA; SIENDO GOBERNADOR\nCONSTITUCIONAL EL C. JOSE GUADALUPE OSUNA MILLAN 2007-2013.\nARTÍCULOS TRANSITORIOS\nPRIMERO.- La presente reforma entrará en vigor a partir del día siguiente al de su publicación en el Periódico Oficial del Estado.\nLey de Adquisiciones, Arrendamientos y Servicios para el Estado de Baja California. Página 48\nSEGUNDO.- El Ejecutivo del Estado en un término no mayor de 90 días contados a de Adquisiciones, Arrendamientos y Servicios para el Estado de Baja California. del Estado de Baja California, en la Ciudad de Mexicali, B.C., a los veinticinco días del mes de septiembre del año dos mil doce.\nDIP. ALFONSO GARZÓN ZATARAIN\nPRESIDENTE\n(RÚBRICA)\nDIP. FAUSTO ZÁRATE ZEPEDA\nSECRETARIO\n(RÚBRICA)\nDE CONFORMIDAD CON LO DISPUESTO POR EL ARTÍCULO 49 DE LA\nMEXICALI, BAJA CALIFORNIA, A DÍA PRIMERO DEL MES DE NOVIEMBRE DEL\nAÑO DOS MIL DOCE.\nJOSÉ GUADALUPE OSUNA MILLÁN\nGOBERNADOR DEL ESTADO.\n(RÚBRICA)\nFRANCISCO ANTONIO GARCÍA BURGOS\nSECRETARIO GENERAL DE GOBIERNO\n(RÚBRICA)\nARTÍCULO PRIMERO TRANSITORIO DEL DECRETO No. 315, POR EL QUE SE\nREFORMAN LOS ARTÍCULOS 6, 14 FRACCIÓN III Y 55, PUBLICADO EN EL PERIÓDICO\nOFICIAL No. 9, TOMO CXX, DE FECHA 15 DE FEBRERO DE 2013, SECCION I,\nEXPEDIDO POR LA H. XX LEGISLATURA, SIENDO GOBERNADOR CONSTITUCIONAL\nEL C. JOSÉ GUADALUPE OSUNA MILLÁN 2007-2013.\nARTÍCULO TRANSITORIO\nÚNICO.- Las presentes reformas entrarán en vigor al día siguiente de su publicación en el Periódico Oficial del Estado. del Estado de Baja California, en la Ciudad de Mexicali, B.C., a los quince días del mes de enero del año dos mil trece.\nDIP. ELISA ROSANA SOTO AGÜERO\nVICEPRESIDENTE\n(RÚBRICA)\nLey de Adquisiciones, Arrendamientos y Servicios para el Estado de Baja California. Página 49\nDIP. FAUSTO ZÁRATE ZEPEDA\nSECRETARIO\n(RÚBRICA)\nDE CONFORMIDAD CON LO DISPUESTO POR LA FRACCIÓN I DEL ARTÍCULO 49\nMEXICALI, BAJA CALIFORNIA, A LOS VEINTICINCO DÍAS DEL MES DE ENERO\nDEL AÑO DOS MIL TRECE.\nJOSÉ GUADALUPE OSUNA MILLÁN\nGOBERNADOR DEL ESTADO\n(RÚBRICA)\nFRANCISCO ANTONIO GARCÍA BURGOS\nSECRETARIO GENERAL DE GOBIERNO\n(RÚBRICA)\nARTÍCULO UNICO TRANSITORIO DEL DECRETO No. 519, POR EL QUE SE\nREFORMA EL PRIMER PARRAFO DEL ARTÍCULO 9, PUBLICADO EN EL PERIÓDICO\nOFICIAL No. 41, TOMO CXX, DE FECHA 20 DE SEPTIEMBRE DE 2013, EXPEDIDO POR\nLA H. XX LEGISLATURA, SIENDO GOBERNADOR CONSTITUCIONAL EL C. JOSÉ\nGUADALUPE OSUNA MILLÁN 2007-2013.\nARTÍCULOS TRANSITORIOS\nPRIMERO.- El presente Decreto entrará en vigor al día siguiente de su publicación en el Periódico Oficial del Estado.\nSEGUNDO.- Túrnese el presente Decreto al Titular del Poder Ejecutivo del Estado para los efectos de publicación en el Periódico Oficial del Estado de Baja California.\nDADO en el Salón de Sesiones “Lic. Benito Juárez García” del H. Poder Legislativo del Estado de Baja California, en la Ciudad de Mexicali, B.C., a los dieciséis días del mes de agosto del año dos mil trece.\nDIP. GREGORIO CARRANZA HERNÁNDEZ\nPRESIDENTE\n(RÚBRICA)\nDIP. MARCO ANTONIO VIZCARRA CALDERÓN\nSECRETARIO\n(RÚBRICA)\nDE CONFORMIDAD CON LO DISPUESTO POR LA FRACCIÓN I DEL ARTÍCULO 49\nLey de Adquisiciones, Arrendamientos y Servicios para el Estado de Baja California. Página 50\nMEXICALI, BAJA CALIFORNIA, A LOS VEINTISIETE DÍAS DEL MES DE AGOSTO\nDEL AÑO DOS MIL TRECE.\nJOSÉ GUADALUPE OSUNA MILLÁN\nGOBERNADOR DEL ESTADO\n(RÚBRICA)\nFRANCISCO ANTONIO GARCÍA BURGOS\nSECRETARIO GENERAL DE GOBIERNO\n(RÚBRICA)\nARTÍCULO UNICO TRANSITORIO DEL DECRETO No. 93, POR EL QUE SE\nREFORMAN LOS ARTÍCULOS 3 FRACCIÓN VIII, 8, 11 TERCER PÁRRAFO, 17 PRIMER\nPÁRRAFO, 18 PRIMER PÁRRAFO, 26 FRACCIÓN II, 59 ÚLTIMO PÁRRAFO Y 71,\nPUBLICADO EN EL PERIÓDICO OFICIAL No. 43, SECCIÓN I, TOMO CXXI, DE FECHA 29\nDE AGOSTO DE 2014, EXPEDIDO POR LA H. XXI LEGISLATURA, SIENDO\nGOBERNADOR CONSTITUCIONAL EL C. FRANCISCO ARTURO VEGA DE LA MADRID\n2013-2019.\nARTÍCULO TRANSITORIO\nÚNICO: El presente Decreto entrara en vigor al día siguiente de su publicación en el\nPeriódico Oficial del Estado de Baja California.\nDADO en el Salón de Sesiones “Lic. Benito Juárez García” del H. Poder Legislativo del Estado de Baja California, en la Ciudad de Mexicali, B.C., a los diez días del mes de julio del año dos mil catorce.\nDIP. FELIPE DE JESÚS MAYORAL MAYORAL\nPRESIDENTE\n(RÚBRICA)\nDIP. GERARDO ÁLVAREZ HERNÁNDEZ\nSECRETARIO\n(RÚBRICA)\nDE CONFORMIDAD CON LO DISPUESTO POR LA FRACCIÓN I DEL ARTÍCULO 49 DE\nMEXICALI, BAJA CALIFORNIA, A LOS OCHO DÍAS DEL MES DE AGOSTO DEL\nAÑO DOS MIL CATORCE.\nFRANCISCO ARTURO VEGA DE LA MADRID\nGOBERNADOR DEL ESTADO\n(RÚBRICA)\nFRANCISCO RUEDA GOMEZ\nSECRETARIO GENERAL DE GOBIERNO\n(RÚBRICA)\nLey de Adquisiciones, Arrendamientos y Servicios para el Estado de Baja California. Página 51\nARTÍCULO UNICO TRANSITORIO DEL DECRETO No. 546, POR EL QUE SE\nREFORMAN LOS ARTÍCULOS 13, 49 FRACCIONES III, X Y XI; 19 BIS 1, 19 BIS 2, 19\nBIS 3 Y 19 BIS 4, DEL CAPÍTULO SEGUNDO BIS, DENOMINADO DEL PADRÓN DE\nPROVEEDORES; PUBLICADO EN EL PERIÓDICO OFICIAL No. 41, SECCION I, TOMO\nLEGISLATURA, SIENDO GOBERNADOR CONSTITUCIONAL EL C. FRANCISCO ARTURO\nVEGA DE LAMADRID 2013-2019.\nARTÍCULOS TRANSITORIOS\nPRIMERO.- Las presentes reformas a la Ley de Adquisiciones, Arrendamientos y\nServicios para el Estado de Baja California entrarán en vigor al día siguiente de su publicación.\nSEGUNDO.- Los poderes del Estado, los órganos constitucionales autónomos y los\nAyuntamientos, en un plazo no mayor a 90 días contados a partir de la entrada en vigor del presente decreto deberán modificar los Reglamentos correspondientes de la Ley de\nAdquisiciones, Arrendamientos y Servicios para el Estado de Baja California.\nDADO en el Salón de Sesiones “Lic. Benito Juárez García” del H. Poder Legislativo del Estado de Baja California, en la Ciudad de Mexicali, B.C., a los cuatro días del mes de agosto del año dos mil dieciséis.\nDIP. MÓNICA BEDOYA SERNA\nPRESIDENTA\n(RÚBRICA)\nDIP. ROSA ISELA PERALTA CASILLAS\nSECRETARIA\n(RÚBRICA)\nDE CONFORMIDAD CON LO DISPUESTO POR LA FRACCION I DEL ARTÍCULO 49\nMEXICALI, BAJA CALIFORNIA, A LOS VEINTIDÓS DÍAS DEL MES DE AGOSTO\nDEL AÑO DOS MIL DIECISÉIS.\nFRANCISCO ARTURO VEGA DE LAMADRID\nGOBERNADOR DEL ESTADO\n(RÚBRICA)\nFRANCISCO RUEDA GOMEZ\nSECRETARIO GENERAL DE GOBIERNO\n(RÚBRICA)\nARTÍCULO PRIMERO TRANSITORIO DEL DECRETO No. 142, POR EL QUE SE\nAPRUEBA LAS REFORMAS A LOS ARTÍCULOS 8, 21, 27 Y 42; PUBLICADO EN EL\nPERIÓDICO OFICIAL No. 50, SECCION VI, TOMO CXXIV, DE FECHA 10 DE NOVIEMBRE\nLey de Adquisiciones, Arrendamientos y Servicios para el Estado de Baja California. Página 52\nDE 2017, EXPEDIDO POR LA H. XXII LEGISLATURA, SIENDO GOBERNADOR\nCONSTITUCIONAL EL C. FRANCISCO ARTURO VEGA DE LAMADRID 2013-2019.\nARTÍCULOS TRANSITORIOS\nÚNICO.- La presente reforma entrara en vigor al día siguiente de su publicación en el\nPeriódoco Oficial del Estado de Baja California.\nDADO en el Salón de Sesiones “Lic. Benito Juárez García” del H. Poder Legislativo del Estado de Baja California, en la Ciudad de Mexicali, B.C., a los doce días del mes de octubre del año dos mil diecisiete.\nDIP. EDGAR BENJAMÍN GÓMEZ MACÍAS\nPRESIDENTE\n(RÚBRICA)\nDIP. EVA MARÍA VÁSQUEZ HERNÁNDEZ\nSECRETARIA\n(RÚBRICA)\nDE CONFORMIDAD CON LO DISPUESTO POR LA FRACCION I DEL ARTÍCULO 49\nMEXICALI, BAJA CALIFORNIA, A LOS TREINTA DÍAS DE OCTUBRE DEL AÑO DOS MIL\nDIECISIETE.\nFRANCISCO ARTURO VEGA DE LAMADRID\nGOBERNADOR DEL ESTADO\n(RÚBRICA)\nFRANCISCO RUEDA GÓMEZ\nSECRETARIO GENERAL DE GOBIERNO\n(RÚBRICA)\nARTÍCULO ÚNICO TRANSITORIO DEL DECRETO No. 205, POR EL QUE SE\nAPRUEBA LAS REFORMAS A LOS ARTÍCULOS 3 Y 18; PUBLICADO EN EL PERIÓDICO\nEXPEDIDO POR LA H. XXII LEGISLATURA, SIENDO GOBERNADOR CONSTITUCIONAL\nEL C. FRANCISCO ARTURO VEGA DE LAMADRID 2013-2019.\nARTÍCULOS TRANSITORIOS\nARTÍCULO ÚNICO.- Las presentes reformas entrarán en vigor al día siguiente de su publicación en el Periódoco Oficial del Estado. del Estado de Baja California, en la Ciudad de Mexicali, B.C., al primer día del mes de marzo del año dos mil dieciocho.\nLey de Adquisiciones, Arrendamientos y Servicios para el Estado de Baja California. Página 53\nDIP. MTRO. RAÚL CASTAÑEDA POMPOSO\nPRESIDENTE\n(RÚBRICA)\nDIP. ROCÍO LÓPEZ GOROSAVE\nSECRETARIA\n(RÚBRICA)\nDE CONFORMIDAD CON LO DISPUESTO POR LA FRACCION I DEL ARTÍCULO 49\nMEXICALI, BAJA CALIFORNIA, A LOS DIEZ Y NUEVE DÍAS DEL MES DE ABRIL DEL\nAÑO DOS MIL DIECIOCHO.\nFRANCISCO ARTURO VEGA DE LAMADRID\nGOBERNADOR DEL ESTADO\n(RÚBRICA)\nFRANCISCO RUEDA GÓMEZ\nSECRETARIO GENERAL DE GOBIERNO\n(RÚBRICA)\nARTÍCULO DÉSIMO SEXTO TRANSITORIO DEL DECRETO No. 281, POR EL QUE\nSE REFORMA EL ARTÍCULO 58, PUBLICADO EN EL PERIÓDICO OFICIAL No. 55,\nSECCION IV, TOMO CXXV, DE FECHA 30 DE NOVIEMBRE DE 2018, EXPEDIDO POR LA\nH. XXII LEGISLATURA, SIENDO GOBERNADOR CONSTITUCIONAL EL C. FRANCISCO\nARTURO VEDA DE LAMADRID 2013-2019.\nARTÍCULOS TRANSITORIOS\nARTÍCULO PRIMERO.- El presente decreto entrará en vigor al día siguiente al de su publicación en el Periódico Oficial del Estado de Baja California.\nARTÍCULO SEGUNDO.- El valor diario de la Unidad de Medida y Actualización a la fecha de entrada en vigor, se tomará el valor publicado en el Diario Oficial de la Federación por el INEGI. El valor de la Unidad de Medida y Actualización a la fecha de entrada en vigor del presente Decreto, será producto de multiplicar el valor referido en el párrafo anterior por\n30.4. Por su parte, el valor anual será el producto de multiplicar el valor inicial mensual por\n12.\nARTÍCULO TERCERO. - Todas las menciones al salario mínimo como unidad de cuenta, índice, base, medida o referencia para determinar la cuantía de las obligaciones, sanciones, multas administrativas, conceptos de pago y montos de referencia, se entenderán referidas a la Unidad de Medida y Actualización. del Estado de Baja California, en la Ciudad de Mexicali, B.C., a los veinticinco días del mes de octubre del año dos mil dieciocho.\nLey de Adquisiciones, Arrendamientos y Servicios para el Estado de Baja California. Página 54\nDIP. ROCÍO LÓPEZ GOROSAVE\nPRESIDENTA\n(RÚBRICA)\nDIP. MÓNICA HERNÁNDEZ ÁLVAREZ\nSECRETARIA\n(RÚBRICA)\nDE CONFORMIDAD CON LO DISPUESTO POR LA FRACCIÓN I DEL ARTÍCULO 49\nMEXICALI, BAJA CALIFORNIA, A LOS TREINTA DÍAS DEL MES DE NOVIEMBRE\nDEL AÑO DOS MIL DIECIOCHO.\nFRANCISCO ARTURO VEGA DE LAMADRID\nGOBERNADOR DEL ESTADO\n(RÚBRICA)\nFRANCISCO RUEDA GÓMEZ\nSECRETARIO GENERAL DE GOBIERNO\n(RÚBRICA)\nARTÍCULO ÚNICO TRANSITORIO DEL DECRETO No. 245, POR EL QUE SE\nAPRUEBA LA REFORMA A LOS ARTÍCULOS 3, 8, 13, 26, 28, 33 Y 41, PUBLICADO EN EL\nPERIÓDICO OFICIAL No. 47, SECCION II, TOMO CXXVIII, DE FECHA 02 DE JULIO DE\n2021, EXPEDIDO POR LA H. XXIII LEGISLATURA, SIENDO GOBERNADOR\nCONSTITUCIONAL EL C. JAIME BONILLA VALDEZ 2019-2021.\nTRANSITORIOS\nÚNICO.- La presente reforma entrará en vigor al día siguiente de su publicación en el\nPeriódico Oficial del Estado.\nDADO en Sesión Ordinaria Virtual en la Ciudad de Mexicali, B.C., a los diecinueve días del mes de mayo del año dos mil veintiuno.\nDIP. EVA GRICELDA RODRÍGUEZ\nPRESIDENTA\n(RÚBRICA)\nDIP. MARÍA LUISA VILLALOBOS ÁVILA\nSECRETARIA\n(RÚBRICA)\nDE CONFORMIDAD CON LO DISPUESTO POR LA FRACCIÓN I DEL ARTÍCULO 49\nCALIFORNIA, IMPRÍMASE Y PUBLÍQUESE.\nLey de Adquisiciones, Arrendamientos y Servicios para el Estado de Baja California. Página 55\nMEXICALI, BAJA CALIFORNIA, A LOS TREINTA Y UN DÍAS DEL MES DE MAYO\nDEL AÑO DOS MIL VEINTIUNO.\nJAIME BONILLA VALDEZ\nGOBERNADOR DEL ESTADO\n(RÚBRICA)\nAMADOR RODRÍGUEZ LOZANO\nSECRETARIO GENERAL DE GOBIERNO\n(RÚBRICA)\nARTÍCULO ÚNICO TRANSITORIO DEL DECRETO No. 248, POR EL QUE SE\nREFORMAN LOS ARTÍCULOS 2 Y 21; PUBLICADO EN EL PERIÓDICO OFICIAL No. 39,\nÍNDICE, TOMO CXXX, DE FECHA 07 DE JULIO DE 2023, EXPEDIDO POR LA H. XXIV\nLEGISLATURA, SIENDO GOBERNADORA CONSTITUCIONAL LA C. MARINA DEL PILAR\nÁVILA OLMEDA 2021-2027.\nTRANSITORIOS\nÚNICO. Toda La presente reforma entrará en vigor al siguiente día de su publicación en el\nPeriódico Oficial del Estado.\nDADO en Sesión Ordinaria de la XXIV Legislatura en la Ciudad de Mexicali, B.C., a los veintidós días del mes de junio del año dos mil veintitrés.\nDIP. MANUEL GUERRERO LUNA\nPRESIDENTE\n(RÚBRICA)\nDIP. ALEJANDRA MARÍA ANG HERNÁNDEZ\nSECRETARIA\n(RÚBRICA)\nDE CONFORMIDAD CON LO DISPUESTO POR LA FRACCIÓN I DEL ARTÍCULO 49 DE\nBAJA CALIFORNIA, IMPRÍMASE Y PUBLÍQUESE.\nMEXICALI, BAJA CALIFORNIA, A LOS VEINTISIETE DÍAS DEL MES DE JUNIO DEL AÑO\nDOS MIL VEINTITRÉS.\nMARINA DEL PILAR ÁVILA OLMEDA\nGOBERNADOR DEL ESTADO\nDE BAJA CALIFORNIA\n(RÚBRICA)\nCATALINO ZAVALA MÁRQUEZ\nSECRETARIO GENERAL DE GOBIERNO\nDEL ESTADO DE BAJA CALIFORNIA\n(RÚBRICA)\nLey de Adquisiciones, Arrendamientos y Servicios para el Estado de Baja California. Página 56\nARTÍCULO ÚNICO TRANSITORIO DEL DECRETO No. 386, POR EL QUE SE\nAPRUEBA LA REFORMA A LOS ARTÍCULOS 1, 2, 3, 4, 8, 14, 18, 20, 22, 24, 34, 35, 37,\n38, 40, 42, 44, 49, 63 Y 83, ASÍ COMO LA ADICIÓN DEL ARTÍCULO 51 BIS; PUBLICADO\nEN EL PERIÓDICO OFICIAL No. 13, SECCIÓN I, TOMO CXXXI, DE FECHA 08 DE MARZO\nDE 2024, EXPEDIDO POR LA H. XXIV LEGISLATURA, SIENDO GOBERNADORA\nCONSTITUCIONAL LA C. MARINA DEL PILAR ÁVILA OLMEDA 2021-2027.\nARTÍCULOS TRANSITORIOS\nPRIMERO.- El presente Decreto entrará en vigor al día siguiente de su publicación en el\nPeriódico Oficial del Estado de Baja California.\nSEGUNDO.- Los procedimientos de contratación iniciados con anterioridad a la entrada en vigor de las presentes reformas, se seguirán sustanciando hasta su conclusión conforme a las disposiciones vigentes al momento de su inicio.\nDADO en Sesión Extraordinaria de la XXIV Legislatura en la Ciudad de Mexicali, B.C., a los nueve días del mes de febrero del año dos mil veinticuatro.\nDIP. ARACELI GERALDO NÚÑEZ\nPRESIDENTA\n(RÚBRICA)\nDIP. MANUEL GUERRERO LUNA\nSECRETARIO\n(RÚBRICA)\nDE CONFORMIDAD CON LO DISPUESTO POR LA FRACCIÓN I DEL ARTÍCULO 49\nCALIFORNIA, IMPRÍMASE Y PUBLÍQUESE.\nMEXICALI, BAJA CALIFORNIA, A LOS DIECISÉS DÍAS DEL MES DE FEBRERO\nDEL AÑO DOS MIL VEINTICUATRO.\nMARINA DEL PILAR ÁVILA OLMEDA\nGOBERNADORA DEL ESTADO\nDE BAJA CALIFORNIA\n(RÚBRICA)\nALFREDO ÁLVAREZ CÁRDENAS\nSECRETARIO GENERAL DE GOBIERNO\nDEL ESTADO DE BAJA CALIFORNIA\n(RÚBRICA)\nLey de Adquisiciones, Arrendamientos y Servicios para el Estado de Baja California. Página 57",
  "ordenamiento": "REGLAMENTO",
  "jurisdiccion": "BAJA CALIFORNIA",
  "fuente_oficial": "Periódico Oficial",
  "FECHA PER OFIC": "2024/03/08",
  "ESTATUS": "VIGENTE",
  "TOMO": "TOMO_II",
  "URL": "https://www.congresobc.gob.mx/Documentos/ProcesoParlamentario/Leyes/TOMO_II/20240308_LEYADQUI.PDF",
  "es_escaneado": false,
  "tiene_tablas": true,
  "materia": [
    "financiero",
    "fiscal",
    "económico"
  ]
}