{
  "titulo": "Ley ORGÁNICA DEL PODER LEGISLATIVO DEL ESTADO DE BAJA CALIFORNIA",
  "Contenido": ".\nActualización Legislativa.\nÚltima reforma Gaceta No. 63, Especial, 14-Ago-2025\nLEY ORGÁNICA DEL PODER LEGISLATIVO DEL ESTADO\nDE BAJA CALIFORNIA\nPublicada en el Periódico Oficial No. 27, de fecha 25 de Junio de 2002, Tomo CIX.\nTITULO PRIMERO\nDISPOSICIONES GENERALES\nCAPITULO UNICO\nARTICULO 1. La presente Ley es de orden público, y rige la estructura, organización y funcionamiento del Poder Legislativo, cuyo ejercicio se deposita en una Asamblea de\nRepresentantes del Pueblo, denominada Congreso del Estado, que se integra de conformidad con lo dispuesto por la Constitución Local.\nArtículo Reformado\nARTICULO 2. El Poder Legislativo es el órgano de gobierno del Estado de Baja\nCalifornia, al que le corresponde el ejercicio de las funciones legislativas, de fiscalización, así como el ámbito de la gestoría comunitaria, que la Constitución Política de los Estados\nUnidos Mexicanos y la Constitución Local le confieren, así como las demás que le otorgan la presente Ley, y otras disposiciones legales.\nARTICULO 3. Los Diputados gozan del fuero que reconoce la Constitución Local y nunca podrán ser enjuiciados por las opiniones que manifiesten en el desempeño de su cargo o con motivo de él.\nARTICULO 4. Los Diputados son responsables de los delitos que cometan durante el tiempo de su encargo, pero no podrán ser privados de su investidura, de su libertad, ni ejercer en su contra acción penal, hasta que seguido el procedimiento constitucional, se ante los tribunales competentes.\nARTICULO 5. El desempeño de la función pública de los Diputados es incompatible con cualquier otro cargo de elección popular o por designación, independientemente del\nToda fuerza pública estará impedida de tener acceso al mismo, salvo que el Presidente del\nCongreso le otorgue permiso, quedando ésta bajo su mando.\n.\nActualización Legislativa.\nÚltima reforma Gaceta No. 63, Especial, 14-Ago-2025\nArtículo Reformado\nARTICULO 7. El Presidente del Congreso, podrá solicitar el auxilio de la fuerza pública para salvaguardar la inmunidad constitucional de los Diputados y la inviolabilidad del edificio del Poder Legislativo o del recinto parlamentario que se habilite en términos de esta\nLey.\nCuando sin mediar autorización se hiciere presente la fuerza pública, el Presidente podrá decretar la Suspensión de la sesión hasta que dicha fuerza abandone el recinto.\nArtículo Reformado\nARTICULO 8. Ninguna autoridad podrá ejecutar mandamientos judiciales o administrativos sobre los bienes del Poder Legislativo, ni sobre las personas o bienes de los\nDiputados al interior del edificio del Poder Legislativo o del recinto parlamentario que se habilite en términos de esta Ley.\nArtículo Reformado\nARTICULO 9. El Congreso del Estado tiene su residencia oficial, en el edificio del\nPoder Legislativo con sede en la ciudad capital del Estado; podrá habilitar otro lugar como residencia oficial, mediante acuerdo aprobado por mayoría calificada.\nEl ejercicio de las funciones del Congreso se llevará a cabo en Legislaturas, Períodos y Sesiones.\nEl desempeño de las funciones de los Diputados durante tres años, constituye una\nLegislatura.\nLos Períodos, se constituyen por la realización de una serie continuada de sesiones durante un determinado lapso de tiempo.\nLa sesión, es la reunión oficial de los integrantes del Pleno del Congreso del Estado, en el recinto parlamentario denominado “Benito Juárez García”; podrá habilitar otro lugar como recinto parlamentario mediante acuerdo aprobado por mayoría calificada.\nCuando por caso fortuito o causas de fuerza mayor, sea imposible llevar a cabo la sesión en el recinto parlamentario, el presidente de la Mesa Directiva, por acuerdo de la\nJunta de Coordinación Política, podrá convocar a los Diputados en el lugar distinto a este, debiendo hacerlo por escrito especificando únicamente los temas a tratar, por tratarse de una ocasión extraordinaria.\nTratándose de sucesos señalados en el párrafo anterior, que imposibiliten que las y los diputados puedan reunirse a sesionar de manera presencial, por haberse decretado una medida de seguridad por la autoridad competente, el presidente de la Mesa Directiva o los presidentes de las comisiones de trabajo, por acuerdo de la Junta de Coordinación Política, podrán convocar a los Diputados a sesión virtual de pleno o de comisiones respectivamente, con el propósito de evitar poner en riesgo la salud del público en general, así como de los\n.\nActualización Legislativa.\nÚltima reforma Gaceta No. 63, Especial, 14-Ago-2025 legisladores y del personal que labora en el Congreso del Estado, debiendo hacerlo por escrito o vía electrónica, especificando únicamente los temas a tratar, por tratarse de una ocasión extraordinaria.\nPárrafo Adicionado\nAsimismo, se denominan sesiones las reuniones de los integrantes de las\nComisiones, en la sala de juntas de las mismas o en la que se acuerde, para tratar todo lo inherente al desarrollo de sus funciones.\nArtículo Reformado\nARTICULO 10.– La presente Ley sólo podrá ser modificada, reformada, abrogada o derogada por mayoría calificada de los miembros del Pleno.\nPara los efectos de esta Ley y sus Reglamentos se entenderá por:\nCalifornia;\nII. Ley: La Ley Orgánica del Poder Legislativo del Estado de Baja California;\nIII. Plan: El Plan de Desarrollo Legislativo;\nIV. Reglamento Interior: El Reglamento Interior del Poder Legislativo del Estado de Baja\nCalifornia, y\nV. Reglamento: El Reglamento de la Ley.\nArtículo Reformado\nTITULO SEGUNDO\nDE LA TRANSICION E INSTALACION DEL CONGRESO\nCAPITULO I\nDE LA TRANSICION\nARTICULO 11. La Mesa Directiva de la Legislatura saliente, se erigirá en una\nAsamblea de Transición, y tendrá las siguientes atribuciones:\nI. Entregar a más tardar el día quince de Julio del año de la elección, credenciales de identificación y acceso a los Diputados Electos que integrarán la nueva Legislatura, cuya constancia de mayoría y validez, de asignación proporcional o por resolución firme del\nÓrgano jurisdiccional electoral competente, haya recibido el Congreso;\nII. Citar a los Diputados electos a Junta previa a celebrarse el día anterior al inicio de la Legislatura entrante; y,.\nActualización Legislativa.\nÚltima reforma Gaceta No. 63, Especial, 14-Ago-2025\nIII. Entregar a la Mesa Directiva de la Legislatura entrante, el inventario justipreciado de los bienes muebles e inmuebles del Poder Legislativo y el estado que guardan en forma documental, reservando la entrega física en acto formal posterior a la junta previa, mediante el levantamiento de una Acta de Entrega Recepción circunstanciada y signada por la Mesa\nDirectiva saliente y la entrante, así como las memorias, oficios, comunicaciones, asuntos o dictámenes pendientes y demás documentos recibidos que correspondan al Congreso.\nArtículo Reformado\nARTICULO 12. La Asamblea de Transición convocará a los Diputados electos, a hora determinada, para que presentes en el Recinto Parlamentario, procedan al desarrollo de la junta previa a celebrarse el día anterior al inicio del ejercicio de la Legislatura, con el fin de que se aboquen a la designación de la Mesa Directiva de la Legislatura a instalarse, de conformidad con el procedimiento siguiente:\nI. La Asamblea de Transición, por conducto de su Secretario:\na) Pasará lista de asistencia a los Diputados electos, para en su caso declarar el quórum legal. Si no se integrara el quórum legal, se procederá en los términos establecidos en la Constitución Local para tal efecto; y,\nb) Dará cuenta del ejercicio de las atribuciones establecidas en el artículo anterior;\nII. La Asamblea de Transición, a través de su Presidente, exhortará a los Diputados electos a que por mayoría calificada en votación por cédula, elijan la primera Mesa Directiva de la nueva Legislatura, misma que se integrará de conformidad con lo establecido en la presente Ley;\nIII. La Asamblea de Transición, por conducto de su Secretario, proclamará los resultados de la elección de la primera Mesa Directiva de la Legislatura entrante y, por conducto de su Presidente, solicitará a sus integrantes tomar su lugar en el Presidium, para rendir la protesta de Ley, en los términos de la fracción siguiente;\nIV. El Presidente de la Mesa Directiva de la Legislatura entrante protestará su cargo, pidiendo a los Diputados asistentes que se pongan de pie y dirá: “Protesto guardar y hacer guardar la Constitución Política de los Estados Unidos Mexicanos, la particular del Estado de\nBaja California y las Leyes que de ambas emanen, desempeñando leal y patrióticamente el\nBaja California, que el pueblo me ha conferido, mirando en todo por el bien y prosperidad de la Unión y del Estado, y si así no lo hiciere, que el pueblo me lo demande”;\nV. El Presidente de la Mesa Directiva de la Legislatura entrante tomará la protesta a los demás miembros integrantes de la Legislatura en los siguientes términos:\n“Protestan guardar y hacer guardar la Constitución Política de los Estados Unidos\nMexicanos, la particular del Estado de Baja California y las Leyes que de ambas emanen, desempeñando leal y patrióticamente el cargo de Diputado a la (número) Legislatura\n.\nActualización Legislativa.\nÚltima reforma Gaceta No. 63, Especial, 14-Ago-2025 conferido, mirando en todo por el bien y prosperidad de la Unión y del Estado, los Diputados electos responderán: “Si, protesto”; el Presidente dirá: “Si así no lo hicieren, que el pueblo se los demande”; y,\nVI. Rendida la protesta que antecede, la Asamblea de Transición, hará entrega a la nueva Mesa Directiva de los expedientes e inventarios señalados en la fracción III del\nArtículo anterior; acto seguido, la Mesa Directiva electa convocará a los Diputados de la\nLegislatura entrante a la primera sesión del primer año de su ejercicio constitucional, señalando la hora en que deberá celebrarse y solicitará a los Diputados miembros de la\nAsamblea de Transición que pasen a ocupar sus lugares en el Presidium, decretando esta un receso, para efectos de proceder a la entrega material de los expedientes e inventarios referidos y, una vez realizada la entrega y recepción, declarará concluidas las funciones de la Asamblea de Transición y clausurada la sesión.\nArtículo Reformado\nCAPITULO II\nDE LA INSTALACION\nARTICULO 13. El día primero de agosto del año de la renovación del Congreso, se llevará a cabo la sesión de Instalación, procediéndose de la siguiente forma:\nI. El Presidente de la Mesa Directiva observará lo establecido en el primer párrafo del\nArtículo 101 de esta ley en lo que corresponda;\nII. Una vez cumplidas las prescripciones ceremoniales establecidas en la fracción anterior, el Presidente pronunciará las siguientes palabras: instalada la (número) Legislatura así como la apertura del primer año del Ejercicio\nConstitucional”; y,\nIII. Conforme lo establece la Ley, una vez instalada la Legislatura, se procederá a dar integrantes de la Junta de Coordinación Política, confirmando que se hayan satisfecho los requisitos de la presente Ley para el caso.\nArtículo Reformado\nTITULO TERCERO\nDE LA EXPEDICIÓN DE LOS BANDOS SOLEMNES\nCAPITULO I\nDEL BANDO SOLEMNE PARA LA\nDECLARACIÓN DE GOBERNADOR ELECTO\n.\nActualización Legislativa.\nÚltima reforma Gaceta No. 63, Especial, 14-Ago-2025\nARTICULO 14.- El Congreso del Estado expedirá el Bando Solemne para dar a conocer en todo el Estado la declaración de Gobernador electo que hubiere hecho el\nInstituto Estatal Electoral, y ésta haya quedado firme conforme a las leyes electorales.\nArtículo Reformada\nCAPITULO II\nDEL BANDO SOLEMNE PARA LA\nDECLARACIÓN DE MUNICIPES ELECTOS\nARTICULO 15. El Congreso del Estado expedirá el Bando Solemne para dar a conocer en el Municipio respectivo, la declaración de Munícipes electos que hubiere hecho el Instituto Estatal Electoral, y ésta haya quedado firme conforme a las leyes electorales.\nArtículo Reformada\nTITULO CUARTO\nDE LAS FACULTADES LEGISLATIVAS DEL CONGRESO\nCAPITULO PRIMERO\nATRIBUCIONES\nARTICULO 16. Son atribuciones del Congreso del Estado, las que derivan de la\nLeyes que de ella emanen, de la presente Ley y de los Reglamentos respectivos.\nCAPITULO SEGUNDO\nDEL PLAN DE DESARROLLO LEGISLATIVO\nARTÍCULO 16 BIS. El Plan de Desarrollo Legislativo es el documento rector y guía en materia de planeación y gestión legislativa de una legislatura. Dicho Plan establece las directrices a que deberá sujetarse el Congreso del Estado para definir objetivos, estrategias y líneas de acción en materia de legislación, fiscalización del gasto público, gestoría comunitaria y modernización institucional del Poder Legislativo; de conformidad con sus atribuciones.\nArtículo Reformada\nARTÍCULO 16 TER. El Plan se integra por una Agenda Legislativa Básica que deberá elaborarse bajo los siguientes principios:\nI. De Economía Funcional, para garantizar una mayor racionalidad en la toma de decisiones, ahorrando tiempo y esfuerzo en la realización de la Agenda Legislativa;\nII. De Eficiencia, para garantizar la mayor producción legislativa con el menor esfuerzo posible, aprovechando al máximo los recursos materiales, humanos y económicos disponibles, en el contenido Agenda, y\n.\nActualización Legislativa.\nÚltima reforma Gaceta No. 63, Especial, 14-Ago-2025\nIII. Democrático, para garantizar la participación equitativa de todos los Grupos\nParlamentarios con representación en el Congreso del Estado en la toma de decisiones, y asegurar la inclusión de las demandas de la sociedad en la elaboración de la Agenda.\nARTÍCULO 16 QUARTER. El Plan se elaborará, aprobará, controlará, evaluará y coordinará conforme a los siguientes procedimientos y plazos:\nI. La Junta de Coordinación Política, es el órgano de gobierno del\nCongreso del Estado, encargado de organizar los trabajos para la elaboración del\nPlan;\nII. Durante el primer período de sesiones del inicio de una Legislatura, cada Diputado a través de su Coordinador del Grupo Parlamentario correspondiente enviará sus propuestas para elaborar la Agenda Legislativa Básica;\nIII. La Agenda Legislativa Básica será consensuada y acordada por los integrantes de la Junta de Coordinación Política antes de concluir el primer período de sesiones de inicio de la Legislatura, para ser incorporada al Plan;\nIV. La Junta de Coordinación Política deberá incorporar al Plan, las propuestas de las\nDirecciones y Unidades Auxiliares del Congreso, así como de la Auditoría Superior del\nEstado, para la mejora continua de sus funciones y servicios mediante la optimización de sus estructuras y organización técnica de los recursos materiales y humanos disponibles, antes de concluir el primer período de sesiones del inicio de la legislatura;\nFracción Reformada\nV. Los integrantes de la Junta de Coordinación Política deberán procurar que el anteproyecto de Plan se encuentre completo al iniciar el segundo período de sesiones del inicio de la Legislatura, habiendo incluido los objetivos, estrategias y líneas de acción en materia de legislación, fiscalización del gasto público, gestoría comunitaria y modernización institucional;\nVI. El Plan deberá aprobarse por el Pleno del Congreso del Estado, hasta antes de concluir el segundo período de sesiones del inicio de la legislatura, y remitirse\nVII. En la aplicación y ejecución del Plan deberán respetarse las disposiciones previstas en el Artículo 88 de esta Ley;\nVIII. Para el control, seguimiento y evaluación del Plan, el Congreso del Estado podrá utilizar los indicadores que considere necesarios para el proceso de toma de decisiones, de conformidad con el Reglamento;\nIX. El Congreso del Estado, deberá publicar periódicamente los resultados de la aplicación del Plan, mediante los medios impresos y electrónicos disponibles;\n.\nActualización Legislativa.\nÚltima reforma Gaceta No. 63, Especial, 14-Ago-2025\nX. Para mejorar los procedimientos de elaboración, control y evaluación del Plan, el\nCongreso del Estado podrá celebrar convenios de coordinación con las instituciones y organismos que considere necesario, y\nXI. Para garantizar la continuidad en materia de planeación legislativa, la Legislatura entrante tomará en consideración los avances, evaluaciones, resultados y acciones por concluir, que se contemplaron en el Plan aprobado por la legislatura saliente.\nArtículo Reformado\nTITULO QUINTO\nDE LOS DIPUTADOS\nCAPITULO I\nDE LAS OBLIGACIONES DE LOS DIPUTADOS\nARTICULO 17. Son obligaciones de los Diputados:\nI. Rendir protesta y tomar posesión de su cargo;\nII. Acatar los acuerdos del Pleno del Congreso y de la Presidencia de conformidad con la presente Ley;\nIII. Asistir puntualmente a las sesiones tanto del Pleno del Congreso como de las\nComisiones de las que formaren parte, en los casos de inasistencia sin causa justificada se estará a lo dispuesto por esta Ley y el Reglamento;\nIV. Asistir y participar en las sesiones de la Glosa del Informe de Gobierno del\nEjecutivo del Estado;\nV. Permanecer en el salón de sesiones del Pleno del Congreso o de las Comisiones, durante el desarrollo de las mismas;\nVI. Dirigirse con respeto y cortesía a los demás Diputados durante las sesiones;\nVII. Votar a favor o en contra tanto en las votaciones del Pleno del Congreso, como de las Comisiones que formare parte, en caso de abstención deberá fundar la misma;\nVIII. Formular al término de cada ejercicio anual, un informe por escrito sobre sus intervenciones en el Pleno del Congreso y su resultado; el último párrafo del Artículo 14 de la Constitución Local;\nX. Guardar prudente reserva de todo lo que se trate o resuelva en las sesiones privadas;\n.\nActualización Legislativa.\nÚltima reforma Gaceta No. 63, Especial, 14-Ago-2025\nXI. Tratar con consideración y respeto a los servidores públicos que presten sus servicios al Poder Legislativo, absteniéndose de participar en forma directa en asuntos laborales y administrativos de las Direcciones y Unidades Auxiliares del Congreso del\nEstado;\nXII. Aprobar el Plan de conformidad con los procedimientos y plazos previstos en esta\nLey y el Reglamento, y\nXIII. Las demás que le confiere la Constitución Local, esta Ley, sus Reglamentos y las que deriven de acuerdos del Pleno del Congreso del Estado.\nArtículo Reformado\nCAPITULO II\nDE LOS DERECHOS DE LOS DIPUTADOS\nARTICULO 18. Son derechos de las y los Diputados:\nPárrafo Reformada\nI. Elegir y ser electos para integrar los órganos de dirección y de trabajo del Congreso del Estado;\nII. Formar parte de un Grupo Parlamentario y/o Coalición Legislativa;\nIII. Participar en las discusiones y votaciones de iniciativas de leyes y decretos de conformidad con lo establecido por la Constitución Local;\nIV. Participar en los trabajos, deliberaciones, debates y comparecencias del Pleno del\nCongreso y de las Comisiones de conformidad con los procedimientos previstos en esta Ley y el Reglamento;\nV. Contar con la credencial e insignia que los acredite como Diputados de la\nLegislatura correspondiente;\nVI. Percibir la dieta que les corresponde de conformidad con el Presupuesto de conclusión de su mandato Constitucional;\nVII. Recibir por lo menos tres días antes de la discusión en Comisiones y en el Pleno, los Proyectos de Dictámenes, los Dictámenes de las Comisiones y opiniones de las\nDirecciones, Unidades Auxiliares o de la Auditoría Superior del Estado según le corresponda su análisis de conformidad con el objeto de debate;\nFracción Reformada\n.\nActualización Legislativa.\nÚltima reforma Gaceta No. 63, Especial, 14-Ago-2025\nVIII. Recibir copias de la versión estenográfica, de la grabación audiovisual de la sesión, o de la correspondencia recibida y despachada por la Mesa Directiva, si así lo solicita;\nIX. Recibir el acta de la sesión anterior con por lo menos una anticipación de veinticuatro horas a la celebración de la siguiente sesión;\nX. Contar con el personal de apoyo necesario conforme lo establezca el Presupuesto de Egresos del Poder Legislativo. Cada diputado tendrá asignado a su oficina un Secretario\nTécnico, que fungirá como enlace con el secretariado técnico de las Comisiones, y demás direcciones y unidades auxiliares del Congreso. El Secretario Técnico, designado libremente por cada representante popular, no formará parte del servicio civil de carrera del Congreso del estado;\nXI. Participar en los trabajos, deliberaciones y discusiones para la elaboración, seguimiento y evaluación del Plan de conformidad con los procedimientos y plazos previstos en esta Ley y el Reglamento, y,\nXII. Los demás que le confiera la Constitución Local, la presente Ley, sus\nReglamentos y los que se deriven de acuerdos que emita el Pleno del Congreso.\nArtículo Reformado\nCAPITULO III\nDE LAS FALTAS, AUSENCIAS Y LICENCIAS\nARTICULO 19. Los Diputados que falten injustificadamente a tres sesiones de las\nComisiones a las cuales pertenezcan, dentro de un período o tres faltas consecutivas entre dos períodos serán sustituidos por conducto del Coordinador del Grupo Parlamentario al que pertenezcan.\nArtículo Reformado\nARTICULO 20. Si los Diputados faltan a tres sesiones consecutivas del Pleno del\nCongreso ya sea dentro de un mismo período ordinario de sesiones, o entre dos períodos ordinarios de sesiones, según el calendario establecido por el Congreso, sin causa justificada o sin previo aviso, se entenderá que renuncian a concurrir hasta el período inmediato, llamándose desde luego a los suplentes.\nArtículo Reformado\nARTICULO 21. Queda prohibido a los Diputados ausentarse durante el desarrollo de las sesiones del Pleno del Congreso o de las Comisiones, sin el permiso previo de su\nPresidente. Tal conducta será equiparable, con todas sus consecuencias, a una falta injustificada.\nArtículo Reformado\nARTICULO 22. Será falta injustificada, además de las conductas previstas en el artículo anterior, cuando los Diputados, en el Pleno y en las Comisiones:\n.\nActualización Legislativa.\nÚltima reforma Gaceta No. 63, Especial, 14-Ago-2025\nI. Al pasar el Secretario lista de asistencia, no digan presente o no se encuentren presentes; o,\nII. Al realizarse alguna votación, no emitan el sentido de su voto.\nArtículo Reformado\nARTICULO 23. Los Diputados que falten injustificadamente a cualquier sesión del\nPleno del Congreso o de Comisiones a las que pertenezca, no tendrán derecho a recibir la dieta del día que corresponda.\nArtículo Reformado\nARTICULO 24. Los Diputados sólo podrán dejar de asistir a las sesiones del Pleno o de las Comisiones, por las siguientes causas:\nI. Cuando previamente a la sesión, haya avisado y expuesto el motivo de su inasistencia al Presidente del Congreso o al de la Comisión respectiva, los que calificarán la inasistencia de justificada o injustificada;\nII. Cuando se reporte enfermo o delicado de salud. En este caso, el Presidente del\nCongreso o de la Comisión respectiva, designará a dos o más Diputados para que lo visiten periódicamente hasta el término de su enfermedad, debiendo rendir informe de su estado de salud.\nEn el caso de que algún Diputado no pudiere concurrir a las sesiones del Pleno o de la Comisión a la que pertenezca por motivos de salud fehacientemente comprobada ante el\nPresidente del Congreso, el Pleno del Congreso llamará a su suplente para que lo sustituya durante el tiempo que dure la enfermedad, si ésta excede de quince días; y,\nIII. Cuando la falta corresponda al Presidente del Congreso del Estado, el aviso corresponderá darlo al Vicepresidente o Secretario, en ausencia de aquel, en los casos de los Presidentes de las Comisiones, el aviso corresponderá darlo al Secretario, y se deberá reunir el requisito establecido en la fracción I y, en su caso, cumplir con lo dispuesto en la fracción II, ambas de este artículo. Las faltas sin previo aviso solamente se justificarán en casos de fuerza mayor que hayan imposibilitado dar dicho aviso.\nNo son causas de justificación de faltas, las relativas a labores partidistas o actividades para la obtención de nominación o cargos de elección popular. no se hubiere reunido el quórum correspondiente, para lo cual el Presidente del Congreso o asistencias e inasistencias y demás hechos que se consideren necesarios.\nArtículo Reformado\n.\nActualización Legislativa.\nÚltima reforma Gaceta No. 63, Especial, 14-Ago-2025\nARTICULO 25. Las licencias temporales y definitivas, serán otorgadas por el Pleno del Congreso del Estado, en votación por mayoría simple.\nSe entenderá por licencias temporales aquellas que otorgue el Pleno a un Diputado para ausentarse de sus funciones por más de quince días, debiéndose cubrir dicha ausencia por el diputado suplente.\nSe entenderá por licencias definitivas aquellas que otorgue el Pleno a un Diputado para ausentarse definitivamente de sus funciones, debiendo llamar a su suplente para que lo sustituya durante el resto de la legislatura.\nEn el Reglamento se establecerá el Procedimiento relativo al otorgamiento de licencias temporales o definitivas que por los Diputados hayan sido solicitadas.\nARTICULO 26. No se concederán licencias con goce de dietas, salvo el caso de incapacidad por enfermedad comprobada.\nCAPITULO IV\nDE LOS GRUPOS PARLAMENTARIOS\nARTICULO 27. Los Diputados con igual afiliación de partido, podrán organizarse en\nGrupos Parlamentarios para sostener los principios y lineamientos de sus respectivos partidos y para coadyuvar al mejor desarrollo del proceso legislativo por medio de la orientación de criterios comunes en las discusiones y deliberaciones.\nLas Diputadas y los Diputados que no deseen o dejen de pertenecer a un Grupo\nParlamentario, se les guardarán las consideraciones que a las Diputadas y los Diputados coordinados, y apoyándolos en lo individual, conforme a las posibilidades y presupuesto del\nCongreso del Estado, para que puedan desempeñar sus funciones de representación popular.\nPárrafo Reformado\nEl órgano de gobierno denominado Junta de Coordinación Política se integra, exclusivamente, con cada uno de las y los Diputados Coordinadores de los Grupos\nParlamentarios de los Partidos Políticos con representación en el Congreso, así como por las y los Diputados pertenecientes a Partidos Políticos que cuenten con un solo escaño. La resoluciones por el voto ponderado de sus integrantes, quienes se constituyen en representantes de su Grupo Parlamentario, procurando el máximo consenso posible.\nPárrafo Reformado\nDirectiva serán rotativas.\nPárrafo Reformado\nArtículo Reformado\n.\nActualización Legislativa.\nÚltima reforma Gaceta No. 63, Especial, 14-Ago-2025\nARTICULO 28. Los Diputados de la misma afiliación de partido deberán constituir un solo Grupo Parlamentario, siendo requisito esencial que lo integre cuando menos dos\nDiputados. Un Diputado sólo podrá pertenecer a un Grupo Parlamentario.\nLas Diputadas y los Diputados que se hayan separado de su Grupo Parlamentario original, podrán integrarse y formar parte de otro, siempre que se cumplan con las formalidades y exigencias establecidas en la presente Ley.\nPárrafo Reformado\nLos Grupos Parlamentarios se tendrán por constituidos cuando presenten a la Mesa\nDirectiva del Congreso, los siguientes documentos:\nI. Acta en la que conste la decisión de sus integrantes de constituirse en Grupo, con especificación del nombre del mismo y la lista de sus integrantes; y,\nII. Nombre del Diputado que haya sido designado como Coordinador del Grupo, así como el de quien desempeñe otras actividades directivas.\nEn caso de cualquier controversia relativa a la aplicación de este artículo, será determinada por las normas estatutarias y los lineamientos de los respectivos partidos políticos.\nLas y los Diputados que no se inscriban o dejen de pertenecer a un Grupo\nParlamentario, o en su caso renuncien a la militancia del partido de que se trate, serán considerados como Diputadas o Diputados sin partido. La Junta de Coordinación Política, deberá informarle oportunamente de los acuerdos que se emitan.\nPárrafo Adicionado\nArtículo Reformado\nARTICULO 29. Los Grupos Parlamentarios deberán entregar la documentación requerida en el artículo anterior, en la sesión inicial del Primer Período de sesiones de cada\nLegislatura, o cuando se integre un nuevo grupo o se efectúen modificaciones a lo ya constituido.\nExaminada por el Presidente del Congreso la documentación referida, dará cuenta de\nParlamentarios para los efectos de esta Ley.\nEl funcionamiento, las actividades y los procedimientos para la designación de los\nCoordinadores de los Grupos Parlamentarios, serán regulados por las normas estatutarias y los lineamientos de los respectivos partidos políticos, en el marco de las disposiciones de esta Ley.\nArtículo Reformado\nARTICULO 30. La Coalición Legislativa es el órgano que se conforma del acuerdo de los diputados con representación en el Congreso del Estado, con la finalidad de dar\n.\nActualización Legislativa.\nÚltima reforma Gaceta No. 63, Especial, 14-Ago-2025 seguimiento y representación a sus plataformas, principios y acuerdos en beneficio de los intereses de la ciudadanía.\nSe conformará en la segunda sesión ordinaria de la Legislatura entrante, presentando ante la Presidencia del Congreso para la declaratoria correspondiente, la siguiente documentación:\nA) Acta de constitución de la Coalición Legislativa debidamente firmada por todos los integrantes;\nB) Declaración de principios;\nC) Agenda común;\nD) Programa de trabajo;\nE) Representación;\nF) Forma de gobierno;\nG) Responsabilidades y derechos.\nLa Coalición Legislativa se tendrá como un solo órgano legislativo; su representación recae en un titular que se denominará Coordinador General, que asumirá el espacio que corresponda ante la Junta de Coordinación Política, teniendo voz y voto, tendrá además un vicecoordinador y tres secretarios que auxiliarán en las diversas tareas que se encomienden.\nLa Coalición Legislativa dispondrá, como si se tratase de un solo Grupo\nParlamentario, de los espacios adecuados, asesores, personal y materiales necesarios para el cumplimiento de sus funciones, atendiendo al número de sus integrantes.\nArtículo Reformado\nARTICULO 31. Corresponde a los Coordinadores de los Grupos Parlamentarios, en el Congreso, realizar las tareas de coordinación con la Mesa Directiva del Congreso del\nEstado, así como las siguientes atribuciones:\nI. Proponer a los Diputados de su Grupo Parlamentario o Coalición Legislativa en los cargos y Comisiones que se derivan de esta Ley;\nII. Informar a la Junta de Coordinación Política de la sustitución de Diputados pertenecientes a su Grupo Parlamentario y/o Coalición Legislativa en las diversas\nComisiones;\n.\nActualización Legislativa.\nÚltima reforma Gaceta No. 63, Especial, 14-Ago-2025\nIII. Asistir a las reuniones de las sesiones de la Junta de Coordinación Política para considerar, conjuntamente, las acciones específicas que propicien el mejor desarrollo de las labores legislativas; y\nIV. Presentar ante la Junta de Coordinación Política las propuestas de los integrantes de sus Grupos Parlamentarios y/o Coaliciones Legislativas, para elaborar la Agenda\nLegislativa Básica del Plan, de conformidad con los procedimientos y plazos previstos en esta Ley y el Reglamento.\nArtículo Reformado\nARTICULO 32. Cuando un partido político cambie de denominación, el Grupo\nParlamentario o Coalición Legislativa respectivos también cambiará su denominación, comunicándolo a la Mesa Directiva, para que ésta informe al Pleno del Congreso.\nArtículo Reformado\nARTICULO 33. En el caso de que un Grupo Parlamentario o Coalición Legislativa se disuelva por decisión de sus integrantes, se informará a la Mesa Directiva para que ésta informe al Pleno del Congreso. En el caso de que la disolución se presente por no reunir los requisitos establecidos en el Artículo 28 y 30 de la presente Ley, la Mesa Directiva lo informará al Pleno del Congreso.\nArtículo Reformado\nARTICULO 34. Derogado.\nArtículo Derogado\nARTICULO 35. Los Grupos Parlamentarios dispondrán de locales adecuados en las instalaciones del Congreso del Estado, así como de los asesores, personal y elementos materiales necesarios para el cumplimiento de sus funciones, atendiendo a la importancia cuantitativa de cada uno de ellos, de acuerdo con las posibilidades y el presupuesto de egresos del propio Congreso.\nTITULO SEXTO\nDEL CONGRESO DEL ESTADO\nCAPITULO I\nDE LA ORGANIZACIÓN DEL CONGRESO\nARTICULO 36. Para el cumplimiento de sus atribuciones y su debido funcionamiento, el Congreso del Estado integra su estructura con Órganos de Gobierno; Trabajo; así como\nTécnicos y Administrativos.\nArtículo Reformado\nARTICULO 37. El Congreso del Estado se organiza y funciona con los siguientes órganos de Gobierno y de Trabajo:\nI. La Mesa Directiva del Congreso del Estado y la Junta de Coordinación Política;\n.\nActualización Legislativa.\nÚltima reforma Gaceta No. 63, Especial, 14-Ago-2025\nII. Las Comisiones;\nIII. Los demás que se consideran necesarios para el cumplimiento de sus atribuciones.\nArtículo Reformado\nARTICULO 38. Al órgano de gobierno, denominado Mesa Directiva, le corresponde la conducción del Congreso, que es ejercida por su Presidente y Secretario quienes tendrán la representación legal del Congreso ante todo género de autoridades.\nArtículo Reformado\nARTICULO 39. Las Comisiones del Congreso, son órganos de trabajo que se integran de conformidad con esta Ley, y cuyo objeto lo constituye el estudio, consulta, supervisión, vigilancia, investigación, opinión o dictamen de los asuntos que esta Ley o la\nMesa Directiva les atribuya o encomiende, para el cumplimiento de las facultades de la\nConstitución Local que le confiere al Congreso del Estado.\nArtículo Reformado\nARTÍCULO 40. Son órganos Técnicos y Administrativos, las áreas profesionales del\nCongreso del Estado a las que les corresponden tareas de apoyo al órgano de Gobierno, así como a los órganos de Trabajo, para el cumplimiento de sus atribuciones constitucionales y legales, siendo estos:\nI. Dirección de Administración;\nII. Dirección de Contabilidad y Finanzas;\nIII. Dirección de Procesos Parlamentarios;\nIV. Dirección de Consultoría Legislativa;\nV. Las Unidades Auxiliares siguientes:\na). Unidad de Asuntos Jurídicos;\nb). Unidad de Contraloría Interna;\nc). Unidad de Transparencia;\nInciso Reformado\nd). Unidad de Comunicación Social; y,\nInciso Reformado\ne). Unidad de Igualdad de Género.\n.\nActualización Legislativa.\nÚltima reforma Gaceta No. 63, Especial, 14-Ago-2025\nInciso Adicionado\nFracción Reformada\nEl Poder Legislativo del Estado por mayoría calificada del Pleno y a solicitud de la\nJunta de Coordinación Política, podrá modificar su estructura orgánica cuando ello sea necesario para apoyar el cumplimiento de las atribuciones del Congreso del Estado, y bajo los términos y condiciones previstas en la Constitución Local.\nEl Poder Legislativo observará el principio de paridad de género, en la integración de estas áreas.\nPárrafo Adicionado\nArtículo Reformado\nARTICULO 40 BIS. Las Unidades Auxiliares del Congreso del Estado, como órganos\nTécnicos y Administrativos, son áreas a las que les corresponden tareas de apoyo al órgano de gobierno y a las Comisiones, para el cumplimiento de sus atribuciones constitucionales y legales.\nArtículo Reformado\nARTÍCULO 40 TER. La Auditoría Superior del Estado de Baja California, es el órgano del Congreso del Estado con autonomía técnica y de gestión en el ejercicio de sus atribuciones para decidir sobre su organización interna, recursos, funcionamiento y resoluciones. Contará con las atribuciones y obligaciones que establecen la Constitución\nLocal y la Ley de la materia.\nArtículo Reformado\nCAPITULO II\nDE LA ORGANIZACION DEL\nCONGRESO Y SUS FUNCIONES\nSECCION I\nDE LA MESA DIRECTIVA\nARTICULO 41. La Mesa Directiva del Congreso del Estado, se integrará con un\nPresidente, un Vicepresidente, un Secretario, un Prosecretario y un Secretario Escrutador.\nLa integración de la Mesa Directiva se comunicará al Ejecutivo del Estado, al\nPresidente del Tribunal Superior de Justicia del Estado, a los Ayuntamientos de los como a las demás autoridades que se determine.\nArtículo Reformado\nARTICULO 42. Para la integración de la Mesa Directiva, la Junta de Coordinación misma, así como el cargo que ocuparán. En sesión previa, celebrada con anticipación al\n.\nActualización Legislativa.\nÚltima reforma Gaceta No. 63, Especial, 14-Ago-2025 inicio del período correspondiente, el Pleno elegirá a la Mesa Directiva mediante mayoría calificada.\nEn el caso de que la Junta de Coordinación Política, y para efecto de lo dispuesto en la primera parte del párrafo anterior, no presente al Pleno del Congreso la propuesta de\nDiputadas y Diputados que habrán de integrar la nueva Mesa Directiva, así como el cargo que ocuparán; la Mesa Directiva saliente seguirá ejerciendo las atribuciones y facultades que la ley otorga, en tanto se designe la nueva.\nPárrafo Adicionado\nArtículo Reformado\nARTICULO 43. Los Diputados electos como miembros de la Mesa Directiva, desempeñarán sus respectivos cargos durante la duración del período por el cual hayan sido designados.\nARTICULO 44. El Vicepresidente y el Prosecretario auxiliarán al Presidente y\nSecretario en el desempeño de sus funciones, los suplirán en sus ausencias y tomarán su lugar cuando los titulares participen en las discusiones y debates.\nARTICULO 45. En caso de ausencia del Secretario y Prosecretario a una sesión del\nCongreso, el Presidente designará de entre los Diputados presentes a los que deban desempeñar dichos cargos, solamente para el desarrollo de dicha sesión.\nARTICULO 46. Cuando a una sesión del Congreso no concurriera el Presidente ni el\nVicepresidente, dentro de los treinta minutos posteriores de la hora fijada, desempeñará las veces del primero el Secretario para el solo efecto de que los Diputados presentes designen de entre ellos, por mayoría simple en votación por cédula, al Presidente y al Vicepresidente quienes fungirán con tal carácter exclusivamente para el desarrollo de esa sesión.\nARTICULO 47. Si durante una sesión del Congreso el Presidente debiere abandonar justificadamente el recinto parlamentario, sin encontrarse presente el Vicepresidente, la\nAsamblea elegirá por mayoría simple en votación por cédula a quien deberá suplirlo durante la sesión.\nARTICULO 48. Corresponde a la Mesa Directiva, bajo la autoridad del Presidente, preservar la libertad de las deliberaciones, cuidar la efectividad del trabajo legislativo, y\nCongreso, así como informar públicamente al término de cada Período el destino de los\nLegislativo, y la productividad legislativa.\nArtículo Reformado\nARTICULO 49. Los integrantes de la Mesa Directiva sólo podrán ser removidos de conformidad con el procedimiento establecido por el Artículo 52 de esta Ley.\n.\nActualización Legislativa.\nÚltima reforma Gaceta No. 63, Especial, 14-Ago-2025\nSECCION II\nDE LA PRESIDENCIA DE LA MESA DIRECTIVA\nARTICULO 50. Son atribuciones del Presidente del Congreso:\nI. Velar por el respeto del fuero constitucional de los Diputados y preservar la inviolabilidad del edificio del Poder Legislativo y del recinto parlamentario;\nII. En las sesiones del Congreso:\na) Presidir, abrir y clausurar las sesiones así como prorrogarlas y suspenderlas por causa justificada;\nb) Declarar que no hay quórum legal para sesionar, cuando es visible su falta; ordenando a la Secretaría pase lista para constatarlo;\nc) Exhortar a los Diputados ausentes para que concurran a las sesiones, apercibiéndolos de los plazos que establece la Constitución Local en su Artículo 24, para el llamado a los Diputados suplentes;\nd) Informar a la Asamblea sobre la justificación de las ausencias de los Diputados a las sesiones y someter a su consideración los casos de faltas injustificadas de los Diputados para los efectos correspondientes;\ne) Cumplir el orden del día aprobado por el Pleno del Congreso, y en el caso del punto del orden del día relativo a asuntos generales el Presidente preguntará hasta en dos ocasiones a la Asamblea si hay algún Diputado que desee presentar algún asunto general;\nf) Dar curso a los asuntos y determinar los trámites que deban recaer en éstos, así como turnar a las comisiones respectivas el estudio de los asuntos que les corresponda y en el caso de que, en razón de su naturaleza, sea turnado a Comisiones Unidas, designar cual será la Comisión responsable que deberá dirigir los trabajos;\ng) Conducir los debates, las deliberaciones y declarar las votaciones;\nh) Conceder o negar el uso de la palabra de conformidad al orden que señala el\nArtículo 129 de esta Ley, y, en el punto de asuntos generales del orden del día en el estricto orden en que la pidieren, o negar el uso de la palabra cuando se incumpla lo previsto en la fracción IV del citado precepto;\ni) Hacer uso del voto de calidad que le asiste en los casos de empate en las votaciones y proclamar los resultados de la misma;\nj) Exigir orden al público asistente a las sesiones e imponerlo cuando hubiere motivo para ello o altere su desarrollo; en su caso mandar desalojar el recinto parlamentario, en los términos establecidos en el Artículo 7 de esta Ley;\n.\nActualización Legislativa.\nÚltima reforma Gaceta No. 63, Especial, 14-Ago-2025\nk) Requerir a los Diputados que se presenten en estado de ebriedad o bajo influencia de algún narcótico o enervante a abandonar el recinto parlamentario, no permitiéndoles el uso de la palabra ni participar en las votaciones, en tanto permanezcan en el mismo; y,\nl) Requerir a los Diputados que se presenten armados al recinto parlamentario a que se desarmen y en caso de negativa, compelerlos para que lo abandonen, no permitiéndoles el uso de la palabra ni participar en las votaciones, en tanto permanezcan en el mismo.\nIII. Acordar con el Secretario los asuntos en cartera;\nIV. Citar a sesiones cuando menos con veinticuatro horas de anticipación, salvo el caso de sesiones extraordinarias.\nEn el caso de que el Presidente de la Mesa Directiva no convoque a sesión ordinaria, podrán convocar la mayoría de los Diputados integrantes de la Legislatura. La responsabilidad en que incurra el Presidente de la Mesa Directiva será calificada por la\nAsamblea atendiendo a lo previsto en esta Ley;\nV. Citar a la totalidad de los Diputados para las sesiones de la Glosa del Informe de\nGobierno del Ejecutivo del Estado, así como a los servidores públicos que habrán de atenderlas;\nVI. Firmar con el Secretario, decretos, acuerdos, oficios, fe de erratas, informes y todo comunicado que expida el Congreso del Estado, así como el acta de la sesión anterior inmediatamente después de aprobada y toda iniciativa o convenio de coordinación, colaboración y cooperación técnica que se promuevan con el Congreso de la Unión, con los\nCongresos de las demás Entidades Federativas, con los otros Poderes del Estado y sus\nAyuntamientos; Instituciones de Educación Superior, Científicas o Tecnológicas, y otros organismos o instituciones;\nVII. Requerir a las Comisiones para que presenten dictamen o informe de estudio sobre los asuntos que se les hubieren encomendado, exhortándolas para que lo hagan en el plazo establecido en el Artículo 124 de la presente Ley y para el caso de que no lo hicieren, señalarles un término para presentarlo; si la omisión persiste, turnar el asunto a la Comisión que para ese efecto designe la Asamblea, la cual deberá proceder a dictaminar o presentar informe de estudio según corresponda en el plazo que la misma Asamblea establezca;\nVIII. Nombrar a las Comisiones Especiales, cuyo objeto fuere de ceremonia o cortesía;\nIX. Representar al Congreso del Estado en actos o ceremonias oficiales, así como delegar su representación en otro Diputado;\nX. Nombrar la Comisión o comisionado para representar al Congreso del Estado en ceremonias culturales, científicas, literarias, deportivas y de cualquier otra naturaleza, a la\n.\nActualización Legislativa.\nÚltima reforma Gaceta No. 63, Especial, 14-Ago-2025 que hubiere sido invitado el Congreso y se considere oportuno asistir;\nXI. Firmar con el Secretario, los nombramientos de los Servidores Públicos del\nCongreso del Estado, de conformidad con lo dispuesto por la Ley de la materia; y con fundamento en el Artículo 107 de la Constitución Local, tomar la protesta de Ley a los\nServidores Públicos que la deban rendir ante el Pleno del Congreso;\nXII. Declarar al Congreso en Jurado de Sentencia en los términos previstos por el\nArtículo 93 de la Constitución Local;\nXIII. Remitir al Ejecutivo del Estado el Proyecto de Presupuesto Anual del Poder\nLegislativo en el plazo que para el efecto establece la Ley de Presupuesto y Ejercicio del\nGasto Público del Estado de Baja California;\nXIV. Hacer la Declaratoria de Incorporación Constitucional, mediante el recuento de los votos que emitan los Ayuntamientos de conformidad con el Artículo 112 de la\nConstitución Local;\nXV. Otorgar siempre que así se requiera, Poderes Generales o Especiales, amplios y suficientes en los procedimientos judiciales, laborales o de cualquier otra índole en los que el\nCongreso del Estado sea o pudiera ser parte actora, demandada, tercerista o coadyuvante, así como para nombrar delegados en los Juicios de Garantías; y,\nXVI. Las demás que se deriven de la Constitución Local, de esta Ley, sus\nReglamentos y de las disposiciones o acuerdos que emita el Congreso del Estado.\nArtículo Reformado\nARTICULO 51. En los casos en que el Presidente deje de asistir injustificadamente a tres de las sesiones del Pleno del Congreso dentro del período ordinario correspondiente, se procederá a una nueva elección de Presidente de la Mesa Directiva conforme al procedimiento establecido en el Artículo 52 de la presente Ley.\nARTICULO 52. Cuando el Presidente no observare las prescripciones de esta Ley, podrá ser removido, requiriéndose para ello, que alguno de los Diputados lo solicite, apruebe, en su caso, la remoción por mayoría calificada en votación por cédula, debiendo la establecido en el Reglamento respectivo.\nSECCION III\nDE LA SECRETARIA DE LA MESA DIRECTIVA\nARTICULO 53. Son atribuciones del Secretario del Congreso del Estado:\nI. Auxiliar al Presidente en el desempeño de sus funciones;\n.\nActualización Legislativa.\nÚltima reforma Gaceta No. 63, Especial, 14-Ago-2025\nII. Concurrir, por los menos una hora antes de que se celebre la sesión, con el objeto de revisar el acta de la sesión anterior y tomar conocimiento de los asuntos en cartera con los que se deberá dar cuenta a la Asamblea, elaborando el orden del día para las sesiones, previo acuerdo con el Presidente;\nIII. Cuidar que los dictámenes que vayan a ser objeto de discusión, se reproduzcan y distribuyan entre los Diputados, en el plazo establecido en la fracción VII del Artículo 18 de la presente Ley;\nIV. En las sesiones del Pleno del Congreso y a solicitud del Presidente:\na) Pasar lista de asistencia de los Diputados para informar al Presidente si hay o no quórum legal;\nb) Dar lectura:\n1) Al orden del día de la sesión, y levantar el resultado de la votación económica para su aprobación o en su caso enmendarla;\n2) Al acta de la sesión anterior, en los casos que la Asamblea no dispense su lectura, y hacer las modificaciones que determine la Asamblea; y,\n3) Al listado de la correspondencia recibida y despachada.\nc) Recoger y computar las votaciones y proclamar sus resultados, cuando así lo disponga el Presidente;\nd) Dar lectura de los artículos de esta Ley o de cualquier ordenamiento legal aplicable para moción de orden al Diputado orador o al público asistente, para moción suspensiva a un dictamen o a petición de algún Diputado para sustentar su debate;\ne) Dar lectura de algún documento enlistado en el punto de correspondencia recibida o despachada, previa solicitud de cualquier Diputado.\nV. Extender el acta de las sesiones y firmarlas después de aprobadas por la\nAsamblea y asentarlas bajo su firma en el libro respectivo. Las actas contendrán como mínimo el nombre del Diputado que presida la sesión, la hora de apertura y de clausura, las observaciones, correcciones y aprobaciones del acta anterior, mención nominal de los\nDiputados presentes y una relación sucinta, ordenada y clara de cuanto se trate y resolviere, asentando el nombre de los Diputados que hayan hablado a favor y en contra, si se suscitó discusión, absteniéndose de expresar opinión respecto de los discursos, exposiciones y proyectos de Ley;\nVI. Abrir, integrar y actualizar los expedientes de los asuntos recibidos por el\nCongreso del Estado;\n.\nActualización Legislativa.\nÚltima reforma Gaceta No. 63, Especial, 14-Ago-2025\nVII. Verificar que las actas de sesiones públicas del Congreso, queden debidamente asentadas para su integración y publicación en el Diario de los Debates;\nVIII. Expedir previo acuerdo con el Presidente, las certificaciones de la documentación que forme parte del archivo del Congreso del Estado, solicitada por escrito a través del\nServidor Público competente, de autoridades federales, estatales y municipales o bien a los particulares, así como por autoridad judicial que conozca o tramite el asunto, siempre y cuando justifique motivada y fundadamente dicha solicitud;\nIX. Presentar en la primera sesión de cada período, una relación de los asuntos recibidos y despachados;\nX. Verificar y constatar, que la Dirección de Procesos Parlamentarios envíe para su publicación en el Periódico Oficial del Estado de Baja California, los decretos, acuerdos, fe de erratas, y en los casos que proceda, oficios, informes y todo comunicado que expida el\nCongreso;\nXI. Hacer que se entreguen a las Comisiones los asuntos que le correspondan a más tardar el tercer día hábil siguiente de su presentación a la Asamblea; y,\nXII. Las demás que se deriven de la Constitución Local, de esta Ley, sus\nReglamentos y de las disposiciones o acuerdos que emita el Congreso del Estado.\nArtículo Reformado\nARTÍCULO 53 BIS. Son atribuciones del Secretario Escrutador:\nI. Auxiliar al Presidente en el desempeño de sus funciones;\nII. A solicitud del Presidente, en las sesiones del Congreso recoger y computar las votaciones y proclamar sus resultados, cuando así lo disponga el Presidente; y,\nIII. Las demás que se deriven de la Constitución Local, de esta Ley, sus Reglamentos y de las disposiciones o acuerdos que emita el Congreso del Estado.\nArtìculo Adicionado\nARTICULO 54. En los casos de que el Secretario deje de asistir injustificadamente a tres sesiones del Pleno del Congreso, dentro del período ordinario correspondiente, se procedimiento establecido en el Artículo 52 de la presente Ley.\nSECCION IV\nDE LOS ORGANOS DE TRABAJO LAS COMISIONES\nARTICULO 55. Las Comisiones, como órganos de trabajo del Congreso del estado, conforme a los dispuesto en el Artículo 39 de esta Ley, les corresponde el ejercicio y cumplimiento de las facultades atribuidas al Congreso por la Constitución Local, así como de\n.\nActualización Legislativa.\nÚltima reforma Gaceta No. 63, Especial, 14-Ago-2025 acuerdo a su denominación, les corresponde sus funciones en relación a las respectivas áreas de la administración pública estatal o municipal.\nLas comisiones que el Pleno determine para el ejercicio y cumplimiento de las facultades atribuidas al Congreso por la Constitución local, se crean por acuerdo de la mayoría calificada del Pleno a propuesta de la Junta de Coordinación Política.\nLas Comisiones serán de dictamen legislativo, Ordinarias, de Investigación y\nEspeciales; funcionarán para el despacho de los asuntos a su cargo y atender los que les sean turnados por el Pleno del Congreso.\nEn cumplimiento de sus atribuciones las comisiones se sujetarán a los procedimientos establecidos en la Constitución del Estado, de esta Ley, del Reglamento y demás disposiciones aplicables.\nLas Comisiones que requieran información de otra, la solicita directamente a través de su Presidente. Igualmente atiende las peticiones de otras comisiones o de diputados relacionados con asuntos de su competencia. En ambos casos considerará el estado que guardan los asuntos de que se trata.\nLas comisiones de dictamen legislativo y las Ordinarias, se constituyen con carácter definitivo y funcionan para toda la legislatura.\nLas comisiones de dictamen legislativo conocerán de las iniciativas que correspondan a su materia y serán las responsables de su dictaminación. Elaborarán informes y opiniones, respecto de los asuntos que se les turnan; y ejercen las facultades de información, evaluación y control que les correspondan.\nPor acuerdo del Pleno las comisiones se pueden dividir en secciones; éstas conservan el nombre de aquélla y se les adiciona otra denominación que las distinga. Una comisión sólo se divide hasta en 3 secciones. La Comisión propone a la Mesa Directiva la forma de integración de las secciones, su materia y duración.\nArtículo Reformado\nARTÍCULO 56. Las Comisiones de dictamen legislativo son:\nI.- De Gobernación, Legislación y Puntos Constitucionales;\nII.- De Hacienda y Presupuesto;\nIII.- De Fiscalización del Gasto Público;\nIV.- De Reforma de Estado y Jurisdiccional;\nV.- De Educación, Humanidades, Ciencia y Tecnología;\nFracción Reformada\n.\nActualización Legislativa.\nÚltima reforma Gaceta No. 63, Especial, 14-Ago-2025\nVI.- De Desarrollo Económico y Comercio Binacional;\nVII.- De Justicia;\nVIII.- De Desarrollo Metropolitano, Conurbación, Infraestructura, Movilidad, Comunicaciones y Transportes;\nFracción Reformada\nIX.- De Medio Ambiente y Desarrollo Sustentable;\nX.- De Salud;\nXI.- De Seguridad Ciudadana y Protección Civil;\nFracción Reformada\nXII.- De Energía y Recursos Hidráulicos;\nXIII.- De Asuntos Fronterizos y Migratorios;\nXIV.- De Igualdad de Género;\nFracción Reformada\nXV.- De Fortalecimiento Municipal;\nFracción Reformada\nXVI.- De Pueblos y Comunidades Indígenas y Afromexicanas;\nFracción Adicionada\nFracción Reformada\nXVII.- De Agricultura, Ganadería, Asuntos Portuarios y Pesca;\nFracción Adicionada\nXVIII.- De Cultura y Deporte;\nFracción Adicionada\nXIX.- De Bienestar, Derechos de la Niñez, Juventudes, Personas con\nDiscapacidad y Adultos Mayores;\nFracción Adicionada\nXX.- Turismo e Inversión;\nFracción Adicionada\nXXI.- De Vivienda y Ordenamiento Territorial;\nFracción Adicionada\nXXII.- De Derechos Humanos;\nFracción Adicionada\nFracción Reformada\n.\nActualización Legislativa.\nÚltima reforma Gaceta No. 63, Especial, 14-Ago-2025\nXXIII.- De Trabajo y Previsión Social; y,\nFracción Adicionada\nFracción Reformada\nXXIV.- De la Diversidad.\nFracción Adicionada\nLas comisiones de dictamen legislativo tienen las atribuciones siguientes:\n1. Dictaminar las iniciativas, minutas, proyectos y proposiciones que les son turnados;\n2. Revisar, evaluar y emitir opinión, en lo que corresponde, el informe sobre el estado que guarda la Administración Pública Estatal que presenta la persona titular del Poder Ejecutivo del Estado, así como los que remiten los titulares de las dependencias y entidades estatales, los órganos autónomos y cualquier otro ente público obligado. En el cumplimiento de sus atribuciones, las comisiones se sujetan a los procedimientos establecidos en la Constitución del estado, de esta Ley, del\nReglamento y demás disposiciones aplicables.\nPárrafo Reformado\nLa comisión que requiere información de otra, la solicita directamente a través de su\nPresidencia. Igualmente atiende las peticiones de otras comisiones o de las diputaciones relacionadas con asuntos de su competencia. En ambos casos se considera el estado que guardan los asuntos de que se trata. Las comisiones pueden resolver por sí mismas los asuntos cuya naturaleza y trascendencia así lo requieran, sin que contravengan los ordenamientos relativos.\nPárrafo Reformado\nArtículo Reformado\nARTICULO 57. Los diputados que integren las comisiones de dictamen legislativo durarán en sus cargos por el término de toda la Legislatura, pudiendo ser separados de las mismas por las causas previstas en esta Ley.\nSe integrarán durante los primeros 30 días del primer año de ejercicio constitucional de la Legislatura, a propuesta de la Junta de Coordinación Política, la cual deberá quedar integrada en la primera sesión ordinaria de la Legislatura entrante.\nEn tanto órganos colegiados, las comisiones tienen las atribuciones siguientes:\n1. Aprobar su Programa de Trabajo;\n2. Aprobar el nombramiento del Secretario Técnico propuesto por el Presidente de la\nComisión;\n3. Autorizar el calendario anual de reuniones ordinarias;\n.\nActualización Legislativa.\nÚltima reforma Gaceta No. 63, Especial, 14-Ago-2025\n4. Acordar la integración de subcomisiones o grupos de trabajo;\n5. Realizar consultas y audiencias, en sede legislativa o fuera de ella, relacionadas con las materias de su competencia;\n6. Aprobar el Orden del Día de las reuniones y ratificar, en su caso, el trámite a los asuntos programados;\n7. Autorizar, en lo procedente, los informes que presentan la Mesa Directiva de la\nComisión, las subcomisiones o los grupos de trabajo;\n8. Solicitar información y documentos en términos del artículo 166 de esta Ley;\n9. Realizar reuniones de trabajo con servidores públicos, en los términos de la\nConstitución del estado y la Ley, para ilustrar su juicio en el despacho de los asuntos que les competen;\n10. Emitir opiniones que se les solicitan en las materias de su competencia;\n11. Presentar al Pleno informe anual o final de actividades, por conducto de su\nPresidente y, en su caso, los reportes específicos que se les solicitan. Los informes de actividades incluyen, por lo menos: la relación ordenada de asuntos turnados, los trabajos realizados, la documentación generada y el estado en que se encuentran; el cumplimiento del programa de trabajo; actas de las reuniones de trabajo celebradas; viajes realizados y objetivos alcanzados; y la información administrativa y presupuestal que corresponda. El informe se publicará en la Gaceta o en la página de Internet del Congreso; y,\n12. Las demás que se derivan de esta Ley y su Reglamento y otras disposiciones aplicables.\nArtículo Reformado\nARTICULO 58. Son Comisiones Ordinarias las que se constituyen de acuerdo a las necesidades del Congreso del Estado, funcionan para toda la legislatura y sus miembros se integran, sustituirán o removerán de conformidad a lo previsto en esta Ley. las facultades atribuidas al Congreso por la Constitución local, se crearán por acuerdo de la mayoría calificada del Pleno a propuesta de la Junta de Coordinación Política; en ningún caso están facultadas para dictaminar.\nEl Congreso podrá aumentar el número de las Comisiones ordinarias, según lo exija la importancia de la materia o asunto, estas se regirán por el Reglamento que determinará su organización y funcionamiento.\nArtículo Reformado\n.\nActualización Legislativa.\nÚltima reforma Gaceta No. 63, Especial, 14-Ago-2025\nARTICULO 59. Las Comisiones de Investigación y las Especiales se constituyen con carácter de transitorio, funcionarán en los términos de esta Ley, cuando así lo acuerde el\nPleno del Congreso y conocerán específicamente de los hechos o asuntos que hayan motivado su integración.\nEl acuerdo que las crea precisará su naturaleza, objeto y plazo de cumplimiento, número y nombre de sus integrantes. La Junta de Coordinación Política, propondrá al Pleno su creación e integración, la cual deberá ser aprobada por acuerdo de la mayoría calificada del Pleno del Congreso del Estado.\nLos resultados de las investigaciones se podrán hacer del conocimiento del Ejecutivo del estado por conducto del Presidente de la Mesa Directiva.\nEstas comisiones se extinguen al cumplir su objeto, al considerar el Pleno concluidas sus actividades de forma anticipada o, en su caso, al término de la Legislatura en la cual se constituyeron. El Presidente formaliza ante el Pleno la declaratoria correspondiente.\nTendrán el carácter de Especiales las comisiones que se integren para tratar asuntos que no sean competencia de las ordinarias o de investigación.\nSi al concluir el plazo previsto una comisión especial no ha cumplido su objeto, el\nPleno puede prorrogarlo a propuesta de la Mesa Directiva de la Comisión.\nPor acuerdo del Pleno, a propuesta de la Junta de Coordinación Política, se pueden crear comités, en el que se señala su forma de integración, objeto y duración.\nLos comités tienen a su cargo la gestión de tareas específicas, distintas de las asignadas a las comisiones, relativas al funcionamiento del Congreso.\nArtículo Reformado\nARTÍCULO 60. Las Comisiones se integrarán por no menos de tres Diputaciones y no más de nueve. La Junta de Coordinación Política cuidará que en ellas se encuentren representados los diferentes Grupos Parlamentarios, así como las Diputadas y los Diputados no coordinados, tanto en las Presidencias como en las Secretarías.\nPárrafo Reformado\nLa competencia de las comisiones es la que deriva de acuerdo a su denominación; así como las que se derivan de las facultades que al Congreso asigna la Constitución Local, la presente Ley, su Reglamento y las necesidades del trabajo legislativo.\nPárrafo Reformado\nArtículo Reformado\nARTICULO 61. Derogado.\nArtículo Derogado\nARTICULO 62. Corresponde a la Comisión de Gobernación, Legislación y Puntos\nConstitucionales el conocimiento, estudio y dictamen de los siguientes asuntos:\n.\nActualización Legislativa.\nÚltima reforma Gaceta No. 63, Especial, 14-Ago-2025\nI. Los que se refieran a modificaciones a la Constitución Política de los Estados\nUnidos Mexicanos o la Constitución Local;\nII. Los concernientes a Leyes Reglamentarias u Orgánicas que se deriven de preceptos de la Constitución Local y de los que la Constitución Federal autorice reglamentar;\nIII. Derogado.\nFracción Derogada\nIV. La división del territorio del Estado, así como de los convenios que el Ejecutivo del\nEstado celebre con los Estados vecinos sobre cuestión de límites;\nV. El establecimiento y modificación de la extensión del territorio que corresponda a los Municipios, así como los convenios que celebren cualquiera de los Ayuntamientos sobre cuestión de límites de extensión territorial;\nVI. Sobre la creación de Municipios y distritos locales electorales, en las circunstancias y condiciones que señala la Constitución Local y los demás ordenamientos aplicables;\nVII. Sobre la supresión de aquellos Municipios que dejen de tener la población suficiente o los recursos económicos indispensables para la satisfacción de los servicios municipales, así como de los conflictos sobre límites que se susciten entre los Municipios;\nVIII. Remitir a la Junta de Coordinación Política, el dictamen respecto a la propuesta relativa a la licencia del Gobernador y Diputados conforme a la Constitución Local y las\nLeyes respectivas;\nIX. Los cambios de residencia de los Poderes del Estado y del Recinto Parlamentario del Congreso del Estado;\nX. La concesión de amnistía, a que se refiere la Constitución Local;\nXI. Derogado;\nFracción Derogada\nXII. Derogado;\nFracción Derogada\nXIII. Derogado.\nFracción Derogada\nXIV. Turnar a la Junta de Coordinación Política el dictamen correspondiente al\nPresidente de la Comisión Estatal de los Derechos Humanos, previa revisión del cumplimiento de los requisitos señalados en las leyes;\n.\nActualización Legislativa.\nÚltima reforma Gaceta No. 63, Especial, 14-Ago-2025\nXV. Presentar a la Junta de Coordinación Política, las propuestas de nombramiento o remoción del Titular de la Dirección de Consultoría Legislativa así como del titular de la\nUnidad de Asuntos Jurídicos;\nXVI. Elaborar los proyectos de Reglamentos que se deriven de esta Ley y sus reformas, con base en las propuestas que las Comisiones, la Unidad de Contraloría o cualquiera de los Diputados le hagan llegar; debiendo remitirlos a la Junta de Coordinación\nPolítica;\nXVII. Derogado;\nFracción Derogada\nXVIII. Los demás que le confiera la Constitución Local, esta Ley, sus Reglamentos y los acuerdos emanados del Congreso.\nArtículo Reformado\nARTICULO 63. Para el cumplimiento de las atribuciones señaladas en el artículo que antecede la Comisión de Gobernación, Legislación y Puntos Constitucionales solicitará a la\nDirección de Consultoría Legislativa y a la Unidad de Asuntos Jurídicos el estudio y análisis respectivo.\nArtículo Reformado\nARTÍCULO 64. Derogado.\nArtículo Derogado\nARTICULO 65. Corresponde a la Comisión de Hacienda y Presupuesto el conocimiento, estudio y dictamen de los siguientes asuntos:\nI. De Estudio Legislativo, los relacionados con la Hacienda y Administración Pública\nFederal, Estatal o Municipal que en materia fiscal señale la Constitución Local del Estado, otras disposiciones legales o por acuerdo del Pleno del Congreso;\nII. De Orden Presupuestal v Crédito Público, el conocimiento, estudio y Dictamen de los siguientes asuntos:\n1. Presupuesto de egresos y sus programas y subprogramas de las Entidades que corresponda aprobar al Congreso del Estado;\n2. Transferencia, ampliación, creación o supresión de partidas en los Presupuestos de\nEgresos de las Entidades que deban ser aprobados por el Congreso del Estado;\n3. Financiamientos y obligaciones concertados o celebrados entre las Entidades o entre éstas con terceros, comprendidos en el artículo 117, Fracción VIII, de la Constitución Política de los Estados Unidos Mexicanos, en la Ley de Disciplina Financiera de las Entidades\nFederativas y los Municipios y en la legislación local que rige la materia;\n.\nActualización Legislativa.\nÚltima reforma Gaceta No. 63, Especial, 14-Ago-2025\nNumeral Reformado\n4. Celebración de contratos, convenios, o actos que afecten cualquier aspecto de la situación presupuestal de las Entidades, cuando sus efectos excedan del período de Gobierno del Ejecutivo del Estado;\n5. Todos los actos, convenios o contratos celebrados entre las Entidades de la\nAdministración Publica Estatal y Municipal o entre éstas con terceros cuando requieran aprobación o autorización del Congreso del Estado.\n6. Los acuerdos del Ejecutivo del Estado para asociarse en empresas de participación estatal mayoritaria o minoritaria o para asociarse a los intereses de los particulares en los términos de las Leyes que rijan en la materia;\n7. El conocimiento, estudio y elaboración de dictámenes para la desincorporación de bienes muebles e inmuebles de dominio público, para su enajenación, cambio de destino o desafectación de dichos bienes cuando estén destinados a un servicio público o sean de uso común, solicitada por las Entidades, exceptuando a los Ayuntamientos; y,\n8. Los demás asuntos relacionados que le encomiende el Congreso en esta materia y que requieran la elaboración de dictamen o de estudio.\nFracción Reformada\nIII. De Orden Hacendario, el conocimiento, estudio y dictamen de los siguientes asuntos:\n1. Iniciativas de Leyes de Ingresos del Gobierno del Estado o de los Municipios;\n2. Iniciativas de reformas a las Leyes de Ingresos, Leyes y decretos fiscales estatales o municipales y otras disposiciones de carácter fiscal que rijan a las Entidades;\n3. Iniciativas, reformas o adiciones de Leyes estatales o municipales en materia fiscal;\n4. Iniciativas de Ley y de reformas a las Leyes, así como los Decretos o Acuerdos para la creación, liquidación, escisión o fusión de Entidades del Ejecutivo del Estado y de los\nAyuntamientos;\nPara el cumplimiento de sus atribuciones, la Comisión de Hacienda y Presupuesto, solicitará a la Auditoría Superior del Estado, el estudio, análisis y opinión de los asuntos que le encomiende, así como la elaboración de los proyectos de dictamen que le correspondan, en los términos de este artículo.\nPárrafo Reformado\nArtículo Reformado\n.\nActualización Legislativa.\nÚltima reforma Gaceta No. 63, Especial, 14-Ago-2025\nARTICULO 66. Corresponde a la Comisión de Fiscalización del Gasto Público el conocimiento, estudio y dictamen de los siguientes asuntos:\nI. De Cuenta Pública: Revisar, analizar y dictaminar la Cuenta Pública Anual de las\nEntidades Fiscalizadas, con base en los informes correspondientes a que se refiere la Ley de la materia;\nFracción Reformada\nII. De Orden Patrimonial: Supervisar el inventario y control de los bienes muebles e inmuebles del Gobierno del Estado, organismos descentralizados, paraestatales y todos aquellos sujetos a fiscalización por el Congreso del Estado.\nFracción Reformada\nIII. En los términos de la fracción XIII del artículo 27 de la Constitución Política del\nEstado de Baja California: Vigilar, coordinar, evaluar el funcionamiento y desempeño de la\nAuditoría Superior del Estado, así como proponer las políticas de organización y funcionamiento que deban regularla;\nFracción Reformada\nIV. Proponer a la Comisión de Legislación y Puntos Constitucionales, las políticas, manuales de organización y funciones de la propia Comisión de Fiscalización del Gasto\nPúblico para incorporarse a los Reglamentos de la presente Ley;\nFracción Reformada\nV. Conocer y enviar a la Comisión de Administración y Finanzas el proyecto de presupuesto anual de la Auditoría Superior del Estado, cuidando que el monto que se formule sea suficiente para que dicha Auditoría cumpla con las atribuciones que establece la\nLey de la materia;\nFracción Reformada\nVI. Vigilar y evaluar el avance presupuestal y programático de la Auditoría Superior del Estado; y,\nFracción Reformada\nVII. Presentar a la Junta de Coordinación Política, las propuestas de nombramiento o remoción de la persona Titular de la Auditoría Superior del Estado.\nFracción Reformada\nPara el cumplimiento de sus atribuciones, la Comisión de Fiscalización del Gasto\nPúblico, ordenará a la Auditoría Superior del Estado el estudio, análisis y opinión de los asuntos que le encomiende, así como el conocimiento, estudio y elaboración de los\nAnual de las Entidades Fiscalizadas, previstas en la Ley de la materia.\nPárrafo Reformado\nCuenta Pública sin el Informe correspondiente a que se refiere la Ley de la materia.\n.\nActualización Legislativa.\nÚltima reforma Gaceta No. 63, Especial, 14-Ago-2025\nPárrafo Reformado\nArtículo Reformado\nARTICULO 67. Corresponde a la Comisión de Administración y Finanzas, el conocimiento, estudio y resolución de los siguientes asuntos:\nI. Poner a la consideración de la Comisión de Gobernación, Legislación y Puntos\nConstitucionales, las políticas, manuales de organización y funciones de los Órganos\nTécnicos y Administrativos señalados en el artículo 40 de esta Ley, así como las relativas a dicha Comisión, para incorporarse a los Reglamentos de la presente Ley;\nII.- Elaborar el anteproyecto de Presupuesto Anual de Egresos del Poder Legislativo, con base en los montos, metas y programas que hubieren formulado los Órganos Técnicos y\nAdministrativos señalados en el artículo 40 de esta Ley y la Auditoría Superior del Estado de\nBaja California y, ponerlo a la consideración de la Junta de Coordinación Política para los fines previstos en esta Ley;\nFracción Reformada\nIII.- Solicitar opinión a las Comisiones cuya actividad y funciones se encuentren relacionadas con los servicios que prestan los Órganos Técnicos y Administrativos o la\nAuditoría Superior del Estado de Baja California, con relación a las necesidades presupuestales planteadas por dichos Órganos;\nFracción Reformada\nIV.- Someter a la consideración de la Junta de Coordinación Política, el anteproyecto de Presupuesto Anual de Egresos del Poder Legislativo, cuidando que el monto del presupuesto que se proponga sea suficiente para que cada uno de los Órganos Técnicos y\nAdministrativos del Congreso y la Auditoría Superior del Estado de Baja California, cumplan eficientemente con sus atribuciones y funciones legales, reglamentarias y programáticas;\nFracción Reformada\nV.- Evaluar el avance presupuestal y programático de cada uno de los Órganos\nTécnicos y Administrativos del Congreso;\nVI.- Supervisar el desempeño de los Órganos Técnicos y Administrativos, proponiendo en su caso, medidas para eficientar su funcionamiento; y,\nVII.- Presentar a la Junta de Coordinación Política, las propuestas de nombramiento o remoción de los Titulares de la Dirección de Administración, así como de la Dirección de\nContabilidad y Finanzas.\nArtículo Reformado\nARTICULO 67 BIS. Derogado;\nArtículo Derogado\nARTICULO 67 TER. Derogado;\nArtículo Derogado\n.\nActualización Legislativa.\nÚltima reforma Gaceta No. 63, Especial, 14-Ago-2025\nARTICULO 68. Cuando la naturaleza de un asunto tenga conexión o relación con otra u otras comisiones podrán éstas unirse a solicitud de la Comisión responsable de los\nTrabajos para su desarrollo en forma conjunta.\nLas Comisiones Unidas serán de carácter transitorio y se extinguirán cumplido el objetivo u objetivos que la formaron.\nARTICULO 69. Derogado.\nArtículo Derogado\nARTICULO 70. El Quórum legal en cada sesión de las comisiones se integra, por la asistencia de más de la mitad de los integrantes de las comisiones y tomarán sus decisiones por mayoría simple de sus miembros. Sus Presidentes tendrán voto de calidad en caso de empate.\nCuando alguno de sus miembros disienta de la resolución adoptada podrá firmar el dictamen y expresar su voto particular por escrito dirigido al presidente de la comisión respectiva y al coordinador de su grupo parlamentario.\nLos votos particulares serán declarativos y su fin es el de dejar asentada una determinada posición con algún punto particular del Dictamen o bien, en general con el\nDictamen en su integridad.\nARTICULO 71. Cuando algún Diputado integrante de una comisión tuviere interés particular en un asunto que sea objeto de Dictamen, se abstendrá de intervenir y lo comunicará de inmediato y por escrito al Presidente a fin de que se le sustituya en el caso de que se trate.\nARTICULO 72. La Convocatoria para la reunión de las comisiones deberá expedirse cuando menos con veinticuatro horas de anticipación, salvo los casos considerados urgentes por la Presidencia. Se tendrán por notificados los Diputados cuando sea recibida dicha convocatoria por su personal de apoyo cuando no fuere posible entregársela personalmente.\nEn el caso de que el Presidente de la Comisión respectiva no convocara a sesiones en un término de treinta días naturales, la mayoría de los integrantes de la Comisión podrán convocar a fin de desahogar los asuntos que les correspondan. La responsabilidad en que incurra el Presidente de la Comisión será calificada por la Asamblea.\nArtículo Reformado\nARTICULO 73. Las reuniones de las Comisiones serán por regla general públicas; sin embargo, cuando así lo acuerden los integrantes de la Comisión, podrán celebrar reuniones privadas en las que se podrá invitar de manera expresa, a servidores Públicos\nFederales, Estatales o Municipales para que informen y opinen respecto de algún asunto concerniente a sus respectivos ámbitos de competencia, así como también a representantes de grupos sociales interesados, peritos y otras personas que puedan ampliar la información sobre el particular.\n.\nActualización Legislativa.\nÚltima reforma Gaceta No. 63, Especial, 14-Ago-2025\nEn las deliberaciones de las comisiones participarán con derecho a voz los titulares de los órganos técnicos administrativos según sea el asunto de su competencia, así como aquellos a que se hace referencia en el párrafo que antecede.\nEn las resoluciones de las Comisiones solo podrán participar los Diputados y únicamente votarán los que sean miembros de las mismas.\nArtículo Reformado\nARTICULO 74. Quien presente una iniciativa podrá participar por sí o por conducto de su representante designado por escrito, en la sesión de trabajo, de la comisión que conozca de la iniciativa.\nEl Presidente de la Comisión respectiva, además de la convocatoria que expida a los integrantes de la comisión, deberá invitar al inicialista.\nSu participación será para efecto de informar, respecto de los motivos y razonamientos que fundan y sustentan su iniciativa, y defender los argumentos en contrario, adquiriendo por este hecho, el derecho de voz en la sesión de trabajo sobre el tema correspondiente, más no el de voto.\nArtículo Reformado\nARTICULO 75. Los miembros de las Comisiones no tendrán derecho a ninguna retribución adicional a su dieta como diputados.\nCAPITULO III\nDE LOS ORGANOS TÉCNICOS Y ADMINISTRATIVOS\nDenominación Modificada\nSECCION I\nDISPOSICIONES GENERALES\nARTÍCULO 76. Al frente de cada una de las Direcciones y Unidades Auxiliares habrá una persona titular, que será nombrada y removida por mayoría calificada de las y los\nDiputados integrantes del Pleno del Congreso.\nPárrafo Reformado\nLas y los titulares deberán permanecer en el ejercicio de sus funciones, hasta que sean designados sus sucesores.\nPárrafo Reformado\nEn la designación de las personas titulares, deberá aplicarse el principio de paridad de género.\nPárrafo Adicionado\nArtículo Reformado\nARTÍCULO 76 BIS. - Para ocupar el cargo de Titular de las Direcciones y Unidades\nAuxiliares a que se refiere el Artículo 40 de esta Ley se requiere:\n.\nActualización Legislativa.\nÚltima reforma Gaceta No. 63, Especial, 14-Ago-2025\nI. Ser ciudadano mexicano en pleno goce de sus derechos civiles y políticos;\nII. Tener por lo menos 25 años de edad cumplidos;\nIII. Tener residencia en el Estado de por lo menos tres años anteriores al día de la designación;\nIV. No haber sido condenado en sentencia firme por delito intencional que amerite pena privativa de libertad;\nV. No estar inhabilitado para ejercer algún cargo público;\nVI. Acreditar los conocimientos, experiencia y capacidad de acuerdo al cargo;\nVII. Contar con título de licenciatura legalmente expedido por lo menos con tres años anteriores al día de la designación y cédula profesional; y\nVIII. Las demás que señale el Reglamento respectivo.\nArtículo Reformado\nSECCIÓN II\nDE LA DIRECCIÓN DE ADMINISTRACIÓN\nSección Adicionada\nARTICULO 77. La Dirección de Administración tendrá como función, la planeación, dirección y administración de los recursos humanos y materiales, así como la ejecución y realización de los asuntos de esta naturaleza, según la estructura presupuestal aprobada anualmente.\nArtículo Reformado\nARTÍCULO 77 BIS. Corresponderá a la Dirección de Administración las atribuciones siguientes:\nI. Coordinar las adquisiciones, servicios y suministros de los órganos de gobiernos, las Comisiones, y en general, de las áreas que integran la estructura orgánica del Congreso del Estado;\nII. Informar trimestralmente a la Comisión de Administración y Finanzas, sobre el estado que guarde el patrimonio y los recursos humanos, materiales del Congreso del\nEstado;\nIII. Emitir e implementar programa de capacitación y profesionalización que deberá desempeñen.\n.\nActualización Legislativa.\nÚltima reforma Gaceta No. 63, Especial, 14-Ago-2025\nConstituida cada nueva legislatura la Dirección debe presentar proyecto de programa de capacitación y profesionalización en un plazo de 60 días a la Comisión de Administración y Finanzas del Congreso del Estado.\nLa Comisión de Administración y Finanzas del Congreso del Estado contará con un plazo de 30 días para elaborar el dictamen correspondiente y someterlo a consideración del\nPleno del Congreso.\nEl programa deberá atender durante los primeros seis meses, contados a partir de la aprobación del programa ante el Pleno, la capacitación y formación del personal de nuevo ingreso, con el propósito de lograr su apropiada incorporación a las funciones que les fueron asignadas, concluida dicha etapa el programa deberá garantizar la profesionalización y capacitación permanente de todos los servidores públicos que laboran en el Congreso, con el objetivo de hacer eficientes y eficaces las labores del personal y generar un ambiente laboral apropiado para la buena práctica parlamentaria.\nIV. Conducir las relaciones con los empleados del Congreso del Estado y vigilar el cumplimiento de sus derechos y obligaciones laborales establecidos en la Ley del Servicio\nCivil de los Trabajadores al servicio de los Poderes del Estado y Municipios de Baja\nCalifornia, así como en las Condiciones Generales de Trabajo del Poder Legislativo,\nV. Mantener actualizados los sistemas administrativos que sirvan de base para la evaluación y control de los recursos humanos y materiales;\nVI. Proporcionar los servicios de recursos materiales, que comprenden inventario, provisión y control de bienes muebles, materiales de oficina, papelería y adquisiciones de recursos materiales;\nVII. Mantener actualizados los inventarios y resguardos de los bienes muebles e inmuebles propiedad del Congreso del Estado;\nVIII. Prestar los servicios generales que comprenden entre otras cosas, el mantenimiento de bienes inmuebles, muebles y construcción, remodelación o reparación de bienes muebles e inmuebles;\nIX. Proporcionar el auxilio operativo a los Diputados para el buen desarrollo de sus trabajos;\nX. Supervisar los servicios de seguridad y protección que comprenden la vigilancia y cuidado de bienes muebles e inmuebles, seguridad y control de accesos, así como el personal que al efecto se requiera;\nXI. Resguardar y manejar la agenda de eventos en las instalaciones del Congreso del\nEstado, así como la administración de los recursos humanos y materiales que sean necesarios para el funcionamiento de las mismas;\n.\nActualización Legislativa.\nÚltima reforma Gaceta No. 63, Especial, 14-Ago-2025\nXII. Implementar las políticas, manuales de organización de los órganos técnicos y administrativos del Congreso del Estado;\nXIII. DEROGADA\nFracción Derogada\nXIV. Coordinar el servicio de Biblioteca;\nXV. Implementar el programa de desarrollo ambiental dentro del Congreso del Estado;\nXVI. Las demás que la Ley y el Reglamento le confieran.\nEl desempeño de las atribuciones de la Dirección de Administración, estará bajo la vigilancia y control de la Comisión de Administración y Finanzas del Congreso del Estado, quien realizará a la Junta de Coordinación Política la propuesta de nombramiento correspondiente.\nArtículo Adicionado y Reformado\nSECCION III\nDE LA DIRECCIÓN DE PROCESOS PARLAMENTARIOS\nSección Adicionada\nARTÍCULO 77 TER. La Dirección de Procesos Parlamentarios tiene como función el apoyo en el proceso legislativo, incluido el registro parlamentario, la dirección del Diario de los Debates, de la Gaceta Parlamentaria y del Archivo; así como los servicios de asistencia a la Presidencia de la Mesa Directiva, el apoyo en las sesiones y reuniones de carácter parlamentario, de comisiones y en general; todo aquello que se relacione con las funciones legislativas y parlamentarias.\nArtículo Adicionado y Reformado\nARTÍCULO 77 QUARTER. Corresponde a la Dirección de Procesos Parlamentarios las atribuciones siguientes:\nI. Informar trimestralmente a la Mesa Directiva en turno, sobre el estado que guarden los asuntos que por Ley se encuentran bajo su encargo;\nII. Preparar los elementos necesarios para celebrar las sesiones del Congreso del\nEstado, en los términos previstos por la Ley, proporcionar los servicios de elaboración de actas, diarios de debates y versiones estenográficas de las mismas; así como vigilar la entrega oportuna a los Diputados de los citatorios, las convocatorias, los acuerdos, las iniciativas, los dictámenes, las proposiciones y los posicionamientos que correspondan para las mismas;\nFracción Reformada\n.\nActualización Legislativa.\nÚltima reforma Gaceta No. 63, Especial, 14-Ago-2025\nIII. Prestar servicios de asistencia operativa a la Junta de Coordinación Política y a la\nPresidencia de la Mesa Directiva, así como de asistencia técnica los cuales corresponden a turnos y control de documentos; certificación y autenticación documental de aquellos documentos originales que se encuentren en poder de la Dirección;\nFracción Reformada\nIV. Integrar y publicar la Gaceta Parlamentaria, así como los documentos que requieran su difusión y publicación por el Congreso del Estado;\nV. Registrar las iniciativas de leyes o decretos, dando seguimiento al estado legislativo que guarden, distribuyendo al pleno los documentos sujetos a conocimiento;\nVI. Proporcionar los servicios de archivo y oficialía de partes del Congreso del Estado, que comprenden la recepción, registro, control y custodia de los asuntos y documentos que se remitan al Congreso del Estado; así como los de formación, clasificación y custodia de los documentos del Pleno y las Comisiones; debiendo mantener permanentemente informados y dentro de los plazos legales correspondiente al asunto que se trate, a los Legisladores, Órganos Técnicos y Administrativos del Congreso del Estado;\nFracción Reformada\nVII. Cumplir a solicitud de las Comisiones, el requerimiento técnico que éstas le soliciten para la preparación y desarrollo de sus trabajos, así como proporcionar los servicios estenográficos, grabación de audio y video, elaboración de minutas y actas de las sesiones de las mismas;\nFracción Reformada\nVIII. Cumplir con las atribuciones y el correcto funcionamiento de los servicios legislativos;\nIX. Informar a la Junta de Coordinación Política y al Presidente de la Mesa Directiva, sobre cualquier procedimiento parlamentario o legislativo que amerite el cumplimiento de alguna atribución del Congreso.\nX. Coadyuvar con los trámites legislativos para la remisión de las reformas a la y publicación; y\nXI. Realizar servicios de análisis, revisión y actualización permanente de la legislación estatal;\nFracción Reformada bajo la vigilancia y control de la Mesa Directiva. Corresponde a la Junta de Coordinación\nPolítica realizar la propuesta de nombramiento del titular ante el pleno del Congreso.\nArtículo Adicionado y Reformado\n.\nActualización Legislativa.\nÚltima reforma Gaceta No. 63, Especial, 14-Ago-2025\nARTICULO 77 QUINQUIES. Para el buen desempeño de las funciones y el correcto desarrollo de sus asuntos, la Dirección de Procesos Parlamentarios contará con las coordinaciones siguientes:\nI. Coordinación General de la Dirección de Procesos Parlamentarios;\nII. Coordinación de Proceso Parlamentario;\nIII. Coordinación de Editorial y seguimiento a Comisiones;\nIV. Coordinación de apoyo a Órganos de Gobierno;\nV. Coordinación de Oficialía de Partes, Archivo y Gaceta Parlamentaria;\nVI. Coordinación de Registro Parlamentario y Actualización Legislativa; y\nVII. Coordinación de Transparencia.\nArtículo Adicionado con sus fracciones\nSECCION IV\nDE LA DIRECCIÓN DE CONTABILIDAD Y FINANZAS\nSección Adicionada\nARTICULO 78. La Dirección de Contabilidad y Finanzas tendrá a su cargo la programación, ejecución financiera y contable del presupuesto del Poder Legislativo, así como la realización de tareas de apoyo que permitan el estudio y planeación de asuntos de naturaleza presupuestal relativas del Poder Legislativo, de conformidad con esta Ley y el\nReglamento;\nArtículo Reformado\nARTICULO 79. Corresponderá a la Dirección de Contabilidad y Finanzas las atribuciones siguientes;\nI. Llevar el registro contable de los egresos de acuerdo a los principios de contabilidad gubernamental, así como a las políticas, lineamientos y demás normatividad aplicable en la materia;\nII. Auxiliar en la elaboración del anteproyecto de presupuesto de egresos del Poder\nLegislativo del Estado;\nIII. Presentar trimestralmente a la Comisión de Administración y Finanzas, un informe sobre la administración de los recursos económicos del Congreso del Estado;\nIV. Proponer a la Comisión de Administración y Finanzas, las políticas de sueldos, honorarios, contratación de servicios profesionales, así como de utilización de recursos y\n.\nActualización Legislativa.\nÚltima reforma Gaceta No. 63, Especial, 14-Ago-2025 patrimonio del Congreso del Estado, y las bases para el otorgamiento de compensación e incentivos al personal;\nV. Elaborar el Programa Operativo Anual, en el cual se deberá considerar las actividades de los órganos de gobiernos, las Comisiones, y en general, de las áreas que integran la estructura orgánica del Congreso del Estado;\nVI. Recibir la comprobación del ejercicio de los recursos presupuestales que se asignen a los órganos de gobierno, Comisiones, y en general, de quienes integran la estructura orgánica del Congreso;\nVII. Vigilar el correcto ejercicio del presupuesto aprobado, de conformidad con los programas y montos establecidos;\nVIII. Proporcionar los servicios de tesorería que comprende programación y presupuesto, control presupuestal, contabilidad y cuenta pública y finanzas;\nIX. Proponer transferencias, ajustes y ampliaciones presupuestales a la Comisión de\nAdministración y Finanzas en los términos de la Ley en la materia;\nX. Establecer los lineamientos generales en materia de contabilidad y finanzas los cuales deberán ser observados por los Órganos Técnicos y Administrativos del Congreso del\nEstado;\nXI. Brindar el apoyo necesario a los Diputados y Titulares de los Órganos Previstos en esta Ley, relativos a los documentos para la presentación de las declaraciones fiscales; y\nXII. Las demás que la Ley y el Reglamento le confieran.\nEl desempeño de las atribuciones de la Dirección de Contabilidad y Finanzas estará bajo la vigilancia y control de la Comisión de Administración y Finanzas, quien realizará a la\nJunta de Coordinación Política la propuesta de nombramiento correspondiente.\nArtículo Reformado\nSECCION V\nDE LA DIRECCIÓN DE CONSULTORÍA LEGISLATIVA\nSección Adicionada\nARTICULO 80. La Dirección de Consultoría Legislativa tiene como función asesorar, analizar y emitir opinión de viabilidad y técnica legislativa sobre las iniciativas, propuestas, asuntos de naturaleza legislativa que se le planteen.\nArtículo Reformado\nARTÍCULO 80 BIS.- Corresponderá a la Dirección de Consultoría Legislativa las atribuciones siguientes:\n.\nActualización Legislativa.\nÚltima reforma Gaceta No. 63, Especial, 14-Ago-2025\nI. Informar trimestralmente a la Mesa Directiva en turno, sobre el estado que guarden los asuntos que por Ley se encuentran bajo su encargo;\nII. Emitir opinión sobre la viabilidad y técnica legislativa de las iniciativas de Ley y de reforma, adición y derogación presentadas ante el Congreso del Estado;\nIII. Realizar análisis y estudios a solicitud de Pleno del Congreso y las Comisiones, en los asuntos que le sean planteados;\nIV. Elaborar los proyectos de dictámenes relativos a las iniciativas de Ley y de reformas, adición y derogación, que le hayan sido turnadas para ese fin;\nV. Apoyar y asesorar al Pleno del Congreso del Estado y a sus Comisiones en el proceso de análisis y aprobación de acuerdos y decretos;\nVI.- Validar los dictámenes aprobados por el Pleno, y en su caso los decretos que de ellos se deriven, previo a su remisión al Poder Ejecutivo para su promulgación y publicación;\nVII.- Las demás que establezca la Ley y Reglamento.\nEl desempeño de las atribuciones y obligaciones de la Dirección de Consultoría\nLegislativa, estará bajo la vigilancia y control de la Comisión de Gobernación, Legislación y\nPuntos Constitucionales.\nArtículo Reformado\nSECCIÓN VI\nDE LA UNIDAD DE CONTRALORÍA INTERNA\nSección Adicionada\nARTICULO 81. La Unidad de Contraloría Interna es un órgano dependiente del Pleno del Congreso del Estado, que tiene a su cargo las funciones de control y evaluación del desempeño de las Direcciones, Unidades Auxiliares y de la Auditoría Superior del Estado, así como la atención de quejas y denuncias, investigación, substanciación, calificación de las faltas administrativas de las y los servidores públicos adscritos a los mismos, y en su caso, los términos previstos en las leyes de la materia. Asimismo, la Unidad de Contraloría Interna indemnización por responsabilidad patrimonial señalados en la Ley de la materia.\nArtículo Reformado\nARTICULO 81 BIS. En el desempeño de sus funciones, la Unidad de Contraloría\nUnidades Auxiliares del Congreso y de la Auditoría Superior del Estado.\nPárrafo Reformado\n.\nActualización Legislativa.\nÚltima reforma Gaceta No. 63, Especial, 14-Ago-2025\nLa persona Titular de la Unidad podrá designar dentro de su estructura orgánica a las y los servidores públicos que fungirán como autoridades investigadora, substanciadora y en su caso resolutora respectivamente, en donde la función de la Autoridad Substanciadora, en ningún caso podrá ser ejercida por una Autoridad investigadora, conforme a lo dispuesto en la ley de la materia.\nPárrafo Adicionado\nLa persona Titular de la Unidad de Contraloría Interna deberá rendir informe de actividades a la Mesa Directiva por lo menos dos veces al año.\nPárrafo Reformado\nArtículo Adicionado\nArtículo Reformado\nARTICULO 81 TER. Corresponde a la Unidad de Contraloría Interna, el despacho de los siguientes asuntos:\nI. A través de los medios electrónicos correspondientes, recibir y registrar las declaraciones patrimoniales y de intereses que deban presentar las y los Diputados y demás personas servidoras públicas del Congreso del Estado y de la Auditoría Superior, en términos de la Ley respectiva; así como verificar la evolución patrimonial de las y los servidores públicos de acuerdo con las Leyes y demás ordenamientos legales aplicables;\nFracción Reformada\nII. Conocer e investigar los actos, omisiones o conductas de las y los servidores públicos de las Direcciones y Unidades Auxiliares del Congreso del Estado y de las áreas homologas de la Auditoría Superior del Estado, así como de los particulares señalados en la\nLey respectiva, para constituir responsabilidades administrativas, así como aplicar las sanciones que correspondan en los términos que señale las leyes de la materia, y en su caso, hacer las denuncias correspondientes ante la fiscalía Especializada en Combate a la\nCorrupción o ante otras autoridades competentes, prestándole para tal efecto la colaboración que le fuere requerida;\nFracción Reformada\nIII. Atender las quejas o denuncias que se presenten con motivo del incumplimiento de las obligaciones de los servidores públicos del Congreso del Estado;\nIV. Establecer y operar los sistemas de información y bases de datos, mediante quejas o denuncias que procedan en el ámbito de su competencia;\nFracción Adicionada, recorriéndose las subsecuentes\nV. Desarrollar las tareas de revisión, inspección y auditoría interna del ejercicio del presupuesto de egresos del Congreso del Estado;\nVI. Proponer a la Comisión de Administración y Finanzas, las políticas, manuales de organización y funciones de las Direcciones y Unidades Auxiliares, que permitan optimizar y\n.\nActualización Legislativa.\nÚltima reforma Gaceta No. 63, Especial, 14-Ago-2025 eficientar los recursos humanos y materiales, así como la calidad de los servicios que se prestan;\nVII. Intervenir en los procedimientos de entrega y recepción del Congreso del Estado y Auditoría Superior del Estado, conforme al Reglamento y a la Ley de la materia;\nFracción Adicionada\nVIII. Las demás, que le señale el Reglamento y la Ley en la materia.\nEl desempeño de las atribuciones de la Unidad de Contraloría Interna estará bajo la vigilancia y control de la Mesa Directiva. Corresponde a la Junta de Coordinación Política realizar ante el pleno del Congreso la propuesta de nombramiento correspondiente.\nArtículo Adicionado\nArtículo Reformado\nARTICULO 81 QUARTER. Derogado;\nArtículo Derogado\nSECCIÓN VII\nUNIDAD DE ASUNTOS JURÍDICOS\nSección Adicionada\nARTICULO 82. La Unidad de Asuntos Jurídicos, tiene como función asesorar y atender los asuntos legales del Congreso del Estado, en sus aspectos consultivos y contenciosos, de conformidad con esta Ley y el Reglamento.\nArtículo Reformado\nARTÍCULO 82 BIS. Corresponderá a la Unidad de Asuntos Jurídicos, las atribuciones siguientes:\nI.- Representar y proteger los intereses del Congreso del Estado en todos aquellos asuntos de carácter jurídico en los que intervenga, en todas y cada una de las instancias correspondientes;\nII.- Dar respuesta y puntual seguimiento a los asuntos de carácter contencioso en los que el Congreso del Estado actúe como parte ante los tribunales;\nIII. Representar a la Mesa Directiva en los juicios, diligencias y trámites administrativos jurisdiccionales;\nIV. Realizar los trámites judiciales de los juicios de amparo, controversias constitucionales y de otro tipo de acciones, cuando así lo requiera el Presidente de la Mesa\nDirectiva;\nV. Vigilar y revisar que todos los actos jurídicos suscritos por cualquier servidor público en representación de la Mesa Directiva, cumplan con los requisitos y formalidades jurídicas;\n.\nActualización Legislativa.\nÚltima reforma Gaceta No. 63, Especial, 14-Ago-2025\nVI. Integrar y mantener actualizado el registro de los compromisos jurídicos del\nCongreso del Estado, y\nVII.- Las demás que establezca esta Ley y el Reglamento.\nEl desempeño de las atribuciones y obligaciones de la Unidad de Asuntos Jurídicos estará bajo la vigilancia y control de la Comisión de Gobernación, Legislación y Puntos\nConstitucionales, correspondiéndole a esta la formulación de la propuesta de nombramiento de su titular ante la Junta de Coordinación Política.\nArtículo Adicionado\nSECCIÓN IV (sic)\nDEROGADA\nSección Derogada\nARTICULO 83. Derogado.\nArtículo Derogado\nSECCION VIII\nDE LA UNIDAD DE COMUNICACIÓN SOCIAL\nSección Adicionada\nARTICULO 83 BIS. - La Unidad de Comunicación Social tiene como función atender, estudiar, diseñar y ejecutar las estrategias de comunicación social para el Poder Legislativo del Estado; así como difundir las actividades legislativas, fortalecer la imagen del Congreso y de los Diputados en sus relaciones con los medios de comunicación, de conformidad con la\nLey y Reglamento.\nArtículo Adicionado\nArtículo Reformado\nARTICULO 83 TER. Corresponde a la Unidad de Comunicación Social las atribuciones siguientes:\nI. Informar trimestralmente a la Comisión de Comunicación Social y Relaciones\nPúblicas, sobre el estado que guarden los asuntos que por Ley se encuentran bajo su encargo;\nII. Conducir las relaciones informativas con los medios de comunicación, para difundir información veraz, oportuna y completa; lineamientos que en la materia sean emitidos, conduciéndose bajo los principios de legalidad, pluralidad, objetividad e imparcialidad;\n.\nActualización Legislativa.\nÚltima reforma Gaceta No. 63, Especial, 14-Ago-2025\nIV. Diseñar los programas relativos a la difusión de las diversas actividades legislativas y parlamentarias en los medios de comunicación conforme las políticas, lineamientos y estrategias que establezca la Junta de Coordinación Política;\nV. Generar estrategias que permitan al Congreso del Estado, a las Comisiones y a los\nGrupos Parlamentarios acceder a los medios de comunicación;\nVI. Elaborar y proponer el programa anual de comunicación social del Congreso del\nEstado;\nVII. Organizar conferencias de prensa, entrevistas y demás actividades de difusión informativa que requieran los integrantes de la Legislatura o cualquiera de sus órganos;\nVIII. Elaborar y circular, entre los Diputados, los trabajos de síntesis, análisis y clasificación de las noticias relevantes para el desarrollo de sus actividades;\nIX. Emitir, bajo su más estricta responsabilidad los boletines de información relativos a los trabajos y resoluciones relevantes de la actividad legislativa;\nX. Ejecutar las demás instrucciones que en materia de comunicación social reciba de la Junta de Coordinación Política, o en su caso del Pleno del Congreso del Estado.\nXI. Las demás que establezca la Ley y Reglamento.\nEl desempeño de las atribuciones de la Unidad de Comunicación Social estará bajo la vigilancia y control de la Junta de Coordinación Política, correspondiéndole a ésta realizar la propuesta de nombramiento de su titular ante el pleno del Congreso.\nArtículo Adicionado\nArtículo Reformado\nARTICULO 83. QUATER. Derogado.\nArtículo Derogado\nARTICULO 83. QUINQUIES. Derogado.\nArtículo Derogado\nARTÍCULO 83. SEXIES. Derogado.\nArtículo Derogado\nSECCIÓN IX\nSección Adicionada\nARTICULO 84. El Comité de Transparencia es el responsable de instituir, coordinar y supervisar, en términos de las disposiciones aplicables, las acciones y los procedimientos información, y tendrá las demás atribuciones que establezcan las leyes de la materia.\n.\nActualización Legislativa.\nÚltima reforma Gaceta No. 63, Especial, 14-Ago-2025\nEl Comité de Transparencia se conformará por un número impar, y se integrará por un\nPresidente que será el Diputado que presida la Comisión de Administración y Finanzas; un\nVicepresidente que será el Diputado que designe la Junta de Coordinación Política; así también integran dicho Comité los titulares de cada una de las Direcciones y de las\nUnidades Auxiliares a que se refiere el artículo 40 de esta Ley. Este órgano deberá adoptar sus resoluciones por mayoría de voto, y en caso de empate, el Presidente tendrá voto de calidad. A sus sesiones podrán asistir como invitados aquellos que sus integrantes consideren necesarios, quienes tendrán voz, pero no voto.\nDada la naturaleza jurídica de las funciones que realiza este Comité, las ausencias de sus integrantes con excepción del Secretario, podrán ser sustituidas por un suplente que ellos mismos designen, los cuales contarán con los mismos derechos y obligaciones de sus titulares. Las ausencias del Secretario Ejecutivo deberán ser sustituidas por el Coordinador de la Unidad de Transparencia, lo anterior en los términos de la presente Ley y el\nReglamento que al efecto expida el Congreso.\nEl Comité de Transparencia contará con un Secretario Ejecutivo, función que recaerá en el Titular de la Unidad de Transparencia, el cual tendrá voz pero no voto dentro de las sesiones.\nLos integrantes del Comité de Transparencia tendrán acceso a la información para determinar su clasificación, conforme a la normatividad previamente establecida por los sujetos obligados para el resguardo o salvaguarda de la información.\nEl desempeño de las atribuciones del Comité de Transparencia estará bajo la vigilancia y control de la Mesa Directiva.\nArtículo Reformado\nARTICULO 85. La Unidad de Transparencia es el área operativa encargada de verificar que los órganos del Congreso den cumplimiento de las obligaciones a cargo del\nPoder Legislativo en materia de transparencia y acceso a la información, y tendrá las atribuciones que les establezcan las leyes de la materia.\nEl desempeño de las atribuciones de la Unidad de Transparencia estará bajo la vigilancia y control del Comité de Transparencia.\nArtículo Reformado\nSECCIÓN X\nDE LA UNIDAD DE IGUALDAD DE GÉNERO\nSección Adicionada\nARTÍCULO 85 BIS. La Unidad de Igualdad de Género es el área técnica de del Estado, así como en su ejercicio legislativo.\n.\nActualización Legislativa.\nÚltima reforma Gaceta No. 63, Especial, 14-Ago-2025\nEl desempeño de las atribuciones de la Unidad de Igualdad de Género estará bajo la vigilancia y control de la Junta de Coordinación Política, misma que deberá aprobar su nombramiento.\nArtículo Adicionado\nARTÍCULO 85 BIS 1. Corresponderá a la Unidad de Igualdad de Género, las atribuciones siguientes:\nI. Promover acciones para institucionalizar y transversalizar la perspectiva de género en todos los órganos y espacios del Congreso del Estado;\nII. Coordinar esfuerzos con la Comisión de Igualdad de Género y Juventudes, para auxiliar a ésta en sus funciones y atribuciones;\nIII. Informar trimestralmente a la Comisión de Igualdad de Género y Juventudes las acciones, políticas y programas efectuados para alcanzar los objetivos trazados;\nIV. Impulsar acciones y estrategias encaminadas a institucionalizar un lenguaje inclusivo no sexista, como parte del trabajo cotidiano en las áreas del Congreso del Estado;\nV. Cuando así lo soliciten las Comisiones, emitir opinión fundada, imparcial y objetiva, respecto a iniciativas o decretos en materia de igualdad de género;\nVI. Gestionar la incorporación y transversalidad de la perspectiva de género en el\nCongreso;\nVII. Generar estudios técnicos y estadísticos que permitan tomar decisiones en materia de igualdad de género, mediante un sistema informativo, de registro, seguimiento y evaluación de la situación de igualdad entre mujeres y hombres;\nVIII. Divulgar al interior del Congreso la información relacionada con la perspectiva de género; y,\nIX. Promover acciones para contar con espacios laborales libres de cualquier tipo de violencia.\nArtículo Adicionado\nCAPITULO IV\nDE LA COMISION PERMANENTE\nDEROGADO\nCapitulo Derogado\nARTICULO 86. Derogado.\nArtículo Derogado\nARTICULO 87. Derogado.\nArtículo Derogado\n.\nActualización Legislativa.\nÚltima reforma Gaceta No. 63, Especial, 14-Ago-2025\nARTICULO 87 BIS. Derogado.\nArtículo Derogado\nARTICULO 87 TER. Derogado.\nArtículo Derogado\nARTICULO 87 QUARTER. Derogado.\nArtículo Derogado\nARTICULO 87 QUINQUIES. Derogado.\nArtículo Derogado\nTITULO SEPTIMO\nDEL PROCEDIMIENTO Y PRACTICAS PARLAMENTARIAS\nCAPITULO I\nDE LAS SESIONES\nARTICULO 88. El Congreso del Estado tendrá cada año tres períodos de Sesiones ordinarias, el Primer Período inicia a partir del primero de agosto al último día de noviembre de cada año, el Segundo Período comprende del primero de diciembre al último día de marzo de cada año, y el Tercer Período será a partir del primero de abril al último día de julio de cada año.\nEn los tres períodos ordinarios, la Legislatura del Estado estudiará y votará los dictámenes de las cuentas públicas y modificaciones presupuestales, que sean presentados a su consideración, así como las iniciativas de Leyes, decretos o acuerdos económicos; y resolverá los demás asuntos que le correspondan, conforme a la Constitución.\nEn cada Período de Sesiones Ordinarias el Congreso se ocupará de manera preferente de los asuntos que señale su Ley Orgánica, así como de las iniciativas que el\nGobernador del Estado haya señalado con ese carácter conforme a esta Constitución.\nDurante el Primer Período Ordinario de Sesiones, concluida la Glosa del Informe, el\nCongreso del Estado podrá solicitar durante los siguientes 15 días al Gobernador ampliar la información mediante el procedimiento de Pregunta Parlamentaria, misma que se hará por escrito y tendrá un plazo de 30 días para su respuesta. Los titulares de las dependencias del sus informes bajo protesta de decir verdad. La Ley del Congreso y sus reglamentos regularán el ejercicio de esta facultad.\nEn el Segundo Período Ordinario, antes de concluir el año, examinará, discutirá, y en su caso, modificará y aprobará las Leyes de Ingresos del Estado y de los Municipios, así como los presupuestos de Egresos de los Poderes Ejecutivo, Legislativo y Judicial y de los organismos públicos autónomos, correspondiente al siguiente Ejercicio Fiscal, en los términos de la ley de la materia. Si al iniciarse el año fiscal correspondiente, el Congreso del\n.\nActualización Legislativa.\nÚltima reforma Gaceta No. 63, Especial, 14-Ago-2025\nEstado no hubiese aprobado las leyes de ingresos del Estado y de los Municipios, así como los presupuestos de Egresos correspondientes, en tanto sean expedidas, continuará rigiendo el Presupuesto que hubiere estado vigente el año anterior.\nEn el Tercer Período Ordinario de cada año, el Congreso deberá concluir la revisión, análisis, dictaminación y, en su caso, aprobación o no aprobación, de las Cuentas Públicas recibidas en el ejercicio anterior, que hayan sido fiscalizadas en los términos de la Ley de la materia.\nArtículo Reformado\nARTICULO 89. El Congreso del Estado deberá celebrar sus sesiones en el salón denominado “Benito Juárez García” ubicado en el edificio del Poder Legislativo o en aquél que por decreto del propio Congreso se declare como tal en los términos del artículo 9 de esta Ley. Para efectos de esta Ley el lugar donde sesione el Pleno del Congreso, se denomina recinto parlamentario.\nArtículo Reformado\nARTICULO 90. Las Comisiones sesionarán en las salas de juntas ubicadas en el edificio del Poder Legislativo o en los lugares que para tal efecto se acuerde en cada una de ellas con anterioridad y previa autorización de sus integrantes, debiendo de notificar de su cambio a la Presidencia del Congreso para los efectos de hacerla pública.\nARTICULO 91. De toda sesión se levantará versión taquigráfica, estenográfica o con ayuda de medios electrónicos adecuados para ello, por personal especializado de la\nDirección de Procesos Parlamentarios, debiendo transcribir exactamente lo dicho en la\nSesión. Esta transcripción será publicada en la página de internet o en la Gaceta\nParlamentaria cuando así lo disponga obligatoriamente esta Ley o lo acuerde la Comisión, pero en todo caso se guardará registro electrónico de la misma.\nArtículo Reformado\nARTICULO 92. De toda sesión se elaborará por el Secretario acta circunstanciada en los términos establecidos en la presente Ley, para su publicación en la Gaceta\nParlamentaria.\nArtículo Reformado\nARTICULO 93. En cualquier tipo de Sesiones del Pleno del Congreso del Estado, se dará cuenta de los asuntos en el orden siguiente:\nI. Lista de asistencia;\nII. Lectura, modificación y aprobación del orden del día;\nIII. Acta de la sesión anterior;\nIV. Comunicaciones oficiales;\n.\nActualización Legislativa.\nÚltima reforma Gaceta No. 63, Especial, 14-Ago-2025\nV. Informes;\nVI. Acuerdos de los órganos de gobierno;\nVII. Iniciativas;\nVIII. Dictámenes;\nIX. Proposiciones;\nX. Posicionamientos; y,\nXI. Cita.\nEn caso de no existir Quórum Legal, después del primer pase de lista, se volverá a pasar lista por segunda vez, quince minutos después para que el Presidente pueda declarar que no hay asistencia requerida para estar en posibilidad con el Quórum Legal o para abrir la Sesión. También se pasará lista de asistencia durante las Sesiones o al final de ellas cuando así lo acuerde la Asamblea o por moción de cuando menos tres Diputados.\nUna vez consensuado por la Junta de Coordinación Política, el proyecto de Orden del día de la Sesión Ordinaria deberá publicarse en la página principal de internet y en las cuentas oficiales de redes sociales de este Poder Legislativo del Estado con anticipación suficiente, y cruzado con la palabra PROYECTO; precisando que está sujeta su aprobación final por el Pleno.\nPárrafo Adicionado\nArtículo Reformado\nARTICULO 94. En las sesiones, los Diputados ocuparan las curules sin preferencia alguna en el recinto parlamentario, excepto en el presídium, el presidente ocupara la situada al centro del mismo, y el vicepresidente y el Secretario se sentara a su lado izquierdo y derecho respectivamente, el prosecretario al lado derecho del Secretario y el Secretario\nEscrutador al lado izquierdo del Vicepresidente; todo lo anterior, salvo los casos de excepción previstos por esta Ley.\nPor disposición del Pleno del Congreso, a petición de la Junta de Coordinación\nPolítica, cada grupo parlamentario tendrá derecho a que sus miembros se ubiquen en el salón de sesiones en asientos contiguos, en la ubicación acordada por la Comisión, tanto durante las sesiones ordinarias, extraordinarias, como en las solemnes.\nArtículo Reformado\nARTICULO 95. Todas las personas sin excepción alguna tienen el derecho de asistir a presenciar el desarrollo de las sesiones públicas del Congreso del Estado, ocupando la butaquería destinada al público en el recinto parlamentario.\n.\nActualización Legislativa.\nÚltima reforma Gaceta No. 63, Especial, 14-Ago-2025\nEl libre acceso del público al recinto parlamentario será garantizado por el Presidente de la Mesa Directiva por conducto del personal de vigilancia del Congreso, con excepción de los casos que así lo acuerde el Pleno del Congreso de limitar el acceso del público al recinto parlamentario, mediante tarjetas o invitaciones.\nArtículo Reformado\nARTICULO 96. No se permitirá la entrada al edificio del Poder Legislativo o al recinto parlamentario, a personas que se presenten armadas, con el rostro cubierto, en estado de embriaguez o bajo la influencia de alguna sustancia tóxica, narcótica o enervante o pretendan introducir objetos extraños sin someterlos a la inspección del personal de vigilancia del Congreso del Estado.\nNo son objetos extraños, para los efectos de esta Ley, las mantas o pancartas que manifiesten expresiones que no representen injurias contra alguna persona o institución.\nLa infracción a lo dispuesto anteriormente será sancionada por el Presidente del\nCongreso, ordenando abandonar el salón de sesiones al o los responsables, y siendo las faltas a los Bandos de Policía y Buen Gobierno o delitos mandará detener al que la cometiere y bajo la correspondiente custodia lo pondrá a disposición de las autoridades competentes.\nArtículo Reformado\nARTICULO 97. Los asistentes a las sesiones del Pleno conservarán el mayor respeto y compostura y por ningún motivo podrán tomar parte en las discusiones, ni realizar manifestaciones verbales de ningún género salvo el caso de audiencia o foro público con autorización del Pleno del Congreso.\nARTICULO 98. Cuando el Presidente del Congreso, lo considere conveniente y necesario, con fundamento en el inciso j) de la fracción II del Artículo 50 de esta ley, solicitará se sitúen policías o fuerza armada en el edificio del Poder Legislativo o en el recinto parlamentario.\nSi las disposiciones ordenadas por el Presidente del Congreso no bastaren para contener el desorden en el salón de sesiones, de inmediato levantará la sesión pública, desalojará al público asistente y podrá continuarla en privado, lo mismo hará cuando no pueda restablecerse el orden alterado por los miembros de la legislatura. podrá entrar a la sesión privada, el personal auxiliar de los diputados y los servidores públicos de los órganos técnicoadministrativos del Congreso del Estado.\nArtículo Reformado\nARTICULO 99. En caso necesario, se destinarán las primeras filas de la butaquería a los Ministros de la Suprema Corte de Justicia de la Nación, a los Gobernadores de otras legislaturas de otras Entidades Federativas, de la Asamblea de Representantes del Distrito\n.\nActualización Legislativa.\nÚltima reforma Gaceta No. 63, Especial, 14-Ago-2025\nFederal, de otras Naciones, a los Magistrados del Tribunal Superior de Justicia, a los\nMunícipes de los Ayuntamientos del Estado; y, demás servidores públicos de los tres niveles de gobierno.\nSECCION I\nDEL CEREMONIAL DE LAS SESIONES\nARTICULO 100. Se entiende por ceremonial a las formalidades que deberán observarse durante la celebración de las sesiones.\nEl Presidente, para abrir o cerrar las sesiones, usará respectivamente, las expresiones siguientes: “Se abre la sesión” y “ Se levanta la sesión”, seguido de un toque de timbre.\nArtículo Reformado\nARTICULO 101. El día primero de agosto de cada año, el Congreso del Estado abrirá su Primer Periodo Ordinario de Sesiones y después de cumplirse con las prescripciones de la fracción II del Artículo 50 y IV del Artículo 53, en lo que corresponda, la Sesión se sujetará al orden siguiente:\nI. Derogado;\nFracción Derogada\nII. Honores a la Bandera cuando corresponda al inicio del primer año de ejercicio de la\nLegislatura;\nIII. Derogado;\nFracción Derogada\nIV. El Presidente del Congreso hará uso de la palabra para anunciar la recepción del\nInforme General a que hace referencia el artículo 49, fracción V, de la Constitución Política del Estado;\nEn esta Sesión el Presidente del Congreso del Estado, está impedido para hacer apreciaciones, calificar o emitir juicio con relación al contenido de dicho Informe. Asimismo no procederán intervenciones o interrupciones por parte de los Diputados asistentes.\nV. Derogado;\nFracción Derogada\nVI. Cumplido con lo dispuesto en las fracciones que anteceden, el Presidente del\nCongreso del Estado, levantará la Sesión, citando para la próxima.\nArtículo Reformado\nARTICULO 102. Una vez recibido el Informe General al que se hace alusión en el artículo que antecede, el Pleno del Congreso del Estado en la siguiente sesión ordinaria\n.\nActualización Legislativa.\nÚltima reforma Gaceta No. 63, Especial, 14-Ago-2025 comparezcan ante esta Soberanía para el desahogo de la Glosa correspondiente, mediante el procedimiento establecido en el reglamento.\nSECCION II\nDE LA FORMA Y PERIODICIDAD DE LAS SESIONES\nARTICULO 103. Durante los períodos ordinarios, previstos por la Constitución Local, el Congreso del Estado deberá celebrar sesiones cuantas veces sea necesario, para el oportuno despacho de los asuntos de su competencia, debiendo al efecto hacerlo cuando menos dos veces por mes según el calendario que fije la Mesa Directiva.\nARTICULO 104. Las sesiones podrán ser:\nI. Previas;\nII. Ordinarias;\nIII. Extraordinarias;\nIV. Solemnes;\nV. Públicas;\nVI. Privadas; y\nVII. Abiertas.\nArtículo Reformado\nARTICULO 105. Son sesiones previas aquellas que se desahogan antes de iniciarse un período ordinario de sesiones y tienen como único objetivo la elección de los miembros de la Mesa Directiva del Congreso del Estado en los términos de los artículos 41 y 42 de la presente Ley.\nARTICULO 106. Son sesiones ordinarias aquellas que se celebran en la fecha fijada en el calendario de Sesiones del Congreso del Estado. fechas fijadas en el Calendario de Sesiones al que se refiere el párrafo que antecede.\nARTICULO 107. Son sesiones solemnes aquellas en las que:\nI. Se conmemoren aniversarios históricos;\nII. Concurra el Presidente de la República;\n.\nActualización Legislativa.\nÚltima reforma Gaceta No. 63, Especial, 14-Ago-2025\nIII. Se declare la apertura del Primer Periodo Ordinario de Sesiones del Congreso del\nEstado en los términos establecidos en el Artículo 101 de esta Ley;\nIV. Se imponga alguna presea o reconocimiento instituídos por el Congreso del\nEstado, o rindan su protesta los Magistrados del Poder Judicial; y,\nV. Así lo acuerde el Pleno del Congreso.\nEn lo referente a las formalidades de las sesiones solemnes se estará a lo que establece el Reglamento.\nSin perjuicio de lo anterior, en las sesiones solemnes, se entonará el Himno Nacional.\nArtículo Reformado\nARTICULO 108. Derogado.\nArtículo Derogado\nARTICULO 109. Todas las sesiones del Congreso del Estado serán públicas, y deberán ser interpretadas con apoyo en Lengua de Señas Mexicanas.\nArtículo Reformado\nARTICULO 109 BIS. Son sesiones abiertas aquéllas en las que exclusivamente el\nCongreso del Estado reciba directamente de los ciudadanos opiniones, propuestas, peticiones o proyectos relacionados con temas de interés general, a efecto de que sean atendidos y en su caso turnados a los Órganos de Gobierno correspondientes para su análisis y trámite respectivo conforme a este artículo.\nA propuesta de la Junta de Coordinación Política el Congreso del Estado podrá llevar a cabo una sesión abierta por mes, conforme al orden del día aprobado previamente para tal efecto por el Pleno en sesión ordinaria.\nLa propuesta del orden del día estará conformada por las solicitudes de los ciudadanos que hayan sido recibidas por la Presidencia de la Mesa Directiva y acordadas por la Junta de Coordinación Política.\nAprobado por el Pleno del Congreso el orden del día de la sesión abierta, la de que asistan a la sesión abierta, con derecho a voz exclusivamente y se colocarán en la mesa de comparecientes.\nArtículo Adicionado\nArtículo Reformado\nCAPITULO II\nDE LAS INICIATIVAS\nARTICULO 110. Las Iniciativas que se presenten al Congreso del Estado, podrán ser:\n.\nActualización Legislativa.\nÚltima reforma Gaceta No. 63, Especial, 14-Ago-2025\nI. Iniciativa de Ley o de reformas a una Ley vigente;\nII Iniciativa con proyecto de decreto; y,\nIII. Proposición de acuerdo económico.\nArtículo Reformado\nARTICULO 111. Son Iniciativas de ley, las que tiendan a una resolución que contemple la formación de un ordenamiento jurídico que no existía o que abrogue uno anterior.\nARTICULO 112. Son Iniciativas de reformas de ley, las que tiendan a introducir reformas consistentes en modificación, derogación o adición a un ordenamiento jurídico vigente.\nARTICULO 113. Es Iniciativa con proyecto de decreto aquella que tienda a una resolución que otorgue derechos o imponga obligaciones a determinadas personas físicas o morales en mandamientos particulares y concretos.\nArtículo Reformado\nARTICULO 114. Es proposición de acuerdo económico, la determinación que tienda a una resolución que por su naturaleza no requiera de sanción, promulgación y publicación o que fije la posición del Congreso del Estado respecto de algún hecho, acontecimiento o fenómeno social.\nArtículo Reformado\nARTICULO 115. Las Iniciativas de Leyes y Decretos corresponde:\nI. A los Diputados;\nII. Al Gobernador del Estado;\nIII. Al Tribunal Superior de Justicia, en asuntos relacionados con la organización y funcionamiento de la administración de justicia; así como al Tribunal de Justicia Electoral en asuntos inherentes a la materia electoral;\nIV. A los Ayuntamientos;\nV. Al Instituto Estatal Electoral, exclusivamente en materia electoral; y,\nVI. A los ciudadanos residentes en el Estado, a las Organizaciones de la Sociedad materia.\nToda petición de particulares o autoridades que no tengan derecho de Iniciativa, se turnará por el Presidente del Congreso a la Comisión que corresponda, según la naturaleza\n.\nActualización Legislativa.\nÚltima reforma Gaceta No. 63, Especial, 14-Ago-2025 del asunto de que se trate, la que determinará si son de tomarse o no en consideración. En los casos que procedan, la Comisión la hará suya para presentarla como Iniciativa.\nArtículo Reformado\nARTICULO 116. Las Iniciativas de Ley o Decreto deberán sujetarse a los trámites siguientes:\nI. Dictamen de Comisiones;\nII. Discusión; y,\nIII. Votación.\nARTICULO 117. Toda Iniciativa deberá presentarse al Presidente del Congreso por escrito y firmada, con su exposición de motivos en la cual exponga su autor o autores las consideraciones jurídicas, políticas, sociales o económicas que justifican, explican, motivan y dan procedencia a la proposición de creación, reforma, derogación o abrogación de una Ley, artículo de la misma o decreto.\nLas iniciativas de Ley o de Decreto que sean recepcionadas por Oficialía de Partes del Congreso, en las que tenga interés el Diputado inicialista darle lectura a dicho documento ante la Sesión del Pleno, deberá así expresarlo en su escrito que por duplicado deberá presentar cuando menos con 48 horas previo a la Sesión. Lo anterior para los efectos de que sea remitida en tiempo y forma, al Director de Procesos Parlamentarios para su Registro y agenda Correspondiente.\nEn cuanto a las iniciativas señaladas en el artículo 110 de esta Ley que sean presentadas ante el Pleno, y una vez agotada su lectura, los diputados podrán adherirse o sumarse a las mismas.\nPara efectos del párrafo anterior, el adherirse o sumarse a las iniciativas, sólo tendrá el efecto de coincidir con la pretensión del autor o autores de la iniciativa, la cual quedará transcrita en el Diario de los Debates.\nEn el caso de las iniciativas ciudadanas que no reúnan los requisitos relativos a la motivación de la iniciativa, la Comisión de Dictamen Legislativo que corresponda subsanará dicho requisito. sean dictaminadas por la Comisión respectiva, mediante escrito firmado por el inicialista o quien legalmente lo represente, dirigido al Presidente del Congreso motivando la causa de su retiro.\nArtículo Reformado\nARTICULO 118. Todo proyecto se turnará por el Presidente del Congreso a la\nComisión que corresponda según la naturaleza del asunto de que se trate.\n.\nActualización Legislativa.\nÚltima reforma Gaceta No. 63, Especial, 14-Ago-2025\nSi del estudio y análisis de las iniciativas dentro de las Comisiones de dictamen legislativo es necesario complementarlas o clarificarlas, bastará con que así lo manifieste su inicialista o algunos de los integrantes de la Comisión, a través de una adenda en forma escrita, hasta antes de que sean dictaminados por la Comisión respectiva.\nEl dictamen se presentará al Pleno del Congreso en los plazos señalados en el\nArtículo 124 de esta Ley, para el cumplimiento de las fracciones II y III del Artículo 29\nConstitucional.\nArtículo Reformado\nARTICULO 119. Solo podrá dispensarse del trámite de ser turnada una iniciativa o proposición de acuerdo económico a la Comisión competente, en los asuntos que por acuerdo del Pleno del Congreso del Estado, por mayoría simple y en votación económica, se califiquen de urgente y de obvia resolución, de conformidad con lo dispuesto en la\nConstitución Local, la presente ley y su reglamento.\nAdemás de lo señalado en el párrafo anterior, para la procedencia de la dispensa de trámite resultará necesario cuando menos la existencia de determinados hechos que generen una condición de urgencia en la discusión y aprobación de una iniciativa de ley o decreto, que de no realizarse traería consecuencias negativas para la sociedad. Así mismo, la condición de urgencia deberá evidenciar la necesidad de omitirse los trámites parlamentarios correspondientes, sin que esto implique la afectación a principios o valores democráticos.\nNo podrá dispensarse el trámite a comisiones de ninguna cuenta pública.\nArtículo Reformado\nARTICULO 120. Las Comisiones de Dictamen Legislativo respectivas, anunciarán al\nEjecutivo del Estado, a los Ayuntamientos y al Poder Judicial, cuando menos con cinco días de anticipación la fecha de la Sesión, a efecto de que concurran al desahogo de las sesiones si lo estiman conveniente; a presentar o hacer valer sus opiniones o alegatos, tal y como lo establece el Artículo 30 de la Constitución Local; además de que el mismo procedimiento se seguirá con el Tribunal de Justicia Electoral y el Instituto Estatal Electoral, cuando la\nIniciativa se refiera a los asuntos de carácter Electoral.\nArtículo Reformado\nARTICULO 121. Desechada una iniciativa en lo general, no podrá volver a presentarse en el mismo período de sesiones de conformidad con el Artículo 32 de la\nConstitución Local.\nCAPITULO III\nDE LOS DICTAMENES\nARTICULO 122. Los dictámenes deberán contener:\nI. Nombre de la Comisión o Comisiones de dictamen;\n.\nActualización Legislativa.\nÚltima reforma Gaceta No. 63, Especial, 14-Ago-2025\nII. Número de dictamen;\nIII. Antecedentes del asunto;\nIV. Análisis y estudio de la iniciativa;\nV. Considerandos tomados en cuenta para el apoyo, modificación o rechazo de la iniciativa o asunto;\nVI. Conclusiones o puntos resolutivos; y,\nVII. Fecha y espacio para la firma de las Diputadas y los Diputados.\nFracción Reformada\nEl contenido de los dictámenes deberá realizarse con perspectiva de género y estar redactados en lenguaje incluyente y no sexista.\nPárrafo Reformado\nArtículo Reformado\nARTICULO 123. Una vez firmados los dictámenes, a favor o en contra, por la mayoría de los miembros de la Comisión o Comisiones encargadas de una iniciativa o asunto, se remitirán a los Diputados en los términos de la presente Ley y, se imprimirán y adjuntarán los votos particulares si los hubiera para su conocimiento.\nARTICULO 124. Las Comisiones de dictamen legislativo a las que se turnen las iniciativas, rendirán ante el Pleno del Congreso el dictamen correspondiente por escrito, en un plazo no mayor de treinta días naturales a partir de su recepción en la Comisión, salvo prórroga que apruebe el Pleno a petición de la Comisión respectiva. En ningún caso la prórroga excederá de quince días; en caso de incumplimiento se estará a lo dispuesto en la presente Ley.\nCAPITULO IV\nDE LOS DEBATES\nARTICULO 125. Se entiende por debate las discusiones que se originan entre los\nDiputados en las sesiones del Pleno del Congreso o de sus Comisiones, para deliberar acerca de los asuntos que son de su competencia.\nARTICULO 126. Las discusiones sólo pueden producirse por:\nI. El acta de la sesión anterior;\nII. Los trámites o sus dispensas;\nIII. Los dictámenes;\n.\nActualización Legislativa.\nÚltima reforma Gaceta No. 63, Especial, 14-Ago-2025\nIV. Las iniciativas de leyes y decretos;\nV. Las proposiciones de acuerdo económico;\nVI. Las mociones suspensivas; y,\nVII. Las mociones de orden.\nLas discusiones sobre modificaciones y/o adiciones a los asuntos antes mencionados, se regirán por las reglas previstas en este capítulo.\nArtículo Reformado\nARTICULO 127. El Presidente del Congreso declarará abierto el debate una vez que se haya dado lectura al oficio, documento, iniciativa, dictamen o asunto en cuestión señalados en las fracciones I, III, IV y V del Artículo anterior.\nArtículo Reformado\nARTICULO 128. El Presidente formulará una lista de los Diputados que pidiesen la palabra en pro y otra de los que la pidiesen en contra, las cuales leerá integras antes de preguntar si algún otro Diputado desea hablar en pro o en contra e iniciar las discusiones.\nARTICULO 129. Los Diputados hablarán alternativamente en pro y en contra, sujetándose el debate al siguiente orden:\nI. Siempre se iniciará el debate con los oradores inscritos en contra; de no haberse registrado ninguno, no harán uso de la palabra los oradores en pro;\nII. Cuando en el debate los Diputados que se inscribieren para hacer el uso de la palabra, lo hicieren solo en contra, podrán hablar todos los inscritos, pero después de que hubiesen hablado tres, el Presidente preguntará si el asunto está suficientemente discutido;\nIII. De no haber inscritos oradores en contra o en pro, podrá hacer uso de la palabra un miembro de los Grupos Parlamentarios para razonar su voto;\nIV. Los Diputados solo podrán hablar dos veces sobre cualquier asunto; y,\nV. Cuando algún Diputado que hubiese pedido la palabra, no estuviera presente en el salón de sesiones cuando le corresponda intervenir, se desechará su participación por el\nPresidente del Congreso.\nARTICULO 130. Cuando se presenten a discusión los dictámenes de las Comisiones dictaminadoras en sesión del Pleno del Congreso, el orden de intervención se conformará de la siguiente manera:\n.\nActualización Legislativa.\nÚltima reforma Gaceta No. 63, Especial, 14-Ago-2025\nI. Intervención de un miembro de la Comisión dictaminadora, fundando y motivando el dictamen; y,\nII. Discusión en lo general y en lo particular.\nARTICULO 131. Todo dictamen se discutirá primero en lo general y después en lo particular, de conformidad con las siguientes prevenciones:\nI. La discusión en lo general versará sobre lo establecido por las fracciones III a la V del Artículo 122 de la presente Ley, en lo relativo a los dictámenes; y,\nII. La discusión en lo particular versará restrictivamente sobre los libros, títulos, capítulos, secciones, artículos, fracciones o incisos de una iniciativa de Ley o decreto o de los puntos resolutivos del dictamen que al inicio de la discusión en lo general, se hayan reservado, para su debate y votación por separado, a petición de uno o más Diputados.\nPodrá ser objeto de modificación o adición la parte del asunto que se haya reservado o cualquier otra que se considere relacionada con la misma.\nPara efectos de la discusión en lo general o en lo particular, podrán hacer uso de la voz hasta tres Diputados a favor y hasta tres en contra del asunto de que se trate, además del Presidente o un miembro de la Comisión de dictamen legislativo correspondiente. Hecho lo anterior, se declarará cerrado el debate.\nArtículo Reformado\nARTICULO 132. Cuando se declare un asunto suficientemente discutido en lo general y no hubiera solicitado su discusión en lo particular, se someterá a votación y en caso de ser aprobado, se entenderá que lo es, en lo general y en lo particular, sin necesidad de someterlo nuevamente a votación, previa declaración del Presidente del Congreso.\nArtículo Reformado\nARTICULO 133. Si declarado un asunto suficientemente discutido en lo general y pasado a votación, no fuera aprobado, el Pleno resolverá en votación económica, si se regresa o no el asunto a la Comisión de dictamen legislativo correspondiente. Si la resolución fuese afirmativa, el dictamen se turnará a la Comisión de referencia, si fuese negativa se tendrá por desechado el asunto.\nARTICULO 134. Cerrada la discusión en lo particular, se procederá a la votación de manera individual y por separado de los libros, títulos, capítulos, secciones, artículos, fracciones o incisos de una iniciativa de ley o decreto o de un dictamen, sobre los cuales se hubiere solicitado reserva de conformidad con la fracción II del Artículo 131 de esta Ley; en caso de ser aprobados, se procederá a su incorporación a la parte del asunto que no se hubiera reservado, cuando ésta haya sido aprobada en lo general. propuestas se tendrá por desechada, y el pleno procederá a someter a votación el texto de la iniciativa o dictamen en los términos presentados para su aprobación en lo general.\n.\nActualización Legislativa.\nÚltima reforma Gaceta No. 63, Especial, 14-Ago-2025\nArtículo Reformado\nARTICULO 135. La Comisión o Comisiones de dictamen legislativo a quien se le regrese un asunto de conformidad con lo dispuesto en los dos artículos anteriores, contarán con quince días para presentar ante el Pleno del Congreso nuevamente el asunto para su discusión y votación.\nARTICULO 136. Ningún Diputado podrá ser interrumpido cuando se encuentre en uso de la palabra, salvo por el Presidente para exhortarlo a que se atenga al tema de discusión; llamarlo al orden cuando ofenda al Congreso; a alguno de sus miembros o al público, o para que concluya su participación cuando se le haya otorgado tiempo medido; o para preguntarle si acepta contestar alguna interpelación que desee formularle otro Diputado.\nARTICULO 137. Las interpelaciones que se formulen a los Diputados que estén en el uso de la palabra, con el propósito de esclarecer la intervención o para pedir que ilustre la discusión con la lectura de algún documento, deberán ser solicitadas al Presidente.\nQuien solicite la interpelación lo hará desde su lugar y en forma que todos los\nDiputados asistentes puedan escucharle. Quedan absolutamente prohibidas las discusiones en forma de diálogo.\nARTICULO 138. Iniciado un debate, solo podrá suspenderse por los siguientes motivos:\nI. Desintegración del quórum;\nII. Desórdenes en el salón de sesiones, a juicio del Presidente;\nIII. Por moción suspensiva que presente alguno o algunos de los miembros del\nCongreso y que esta se apruebe;\nIV. Por acuerdo del Pleno de dar preferencia a otro asunto de mayor urgencia o gravedad; y,\nV. Por acuerdo del Pleno, en cuyo caso se deberá fijar de inmediato fecha y hora para su continuación.\nARTICULO 139. En el caso de presentarse una moción suspensiva, el Presidente atenderá a su autor para los efectos de que la fundamente; enseguida la someterá a discusión, pudiendo hacer uso de la palabra hasta dos oradores en contra y dos en pro.\nAgotada la discusión, la moción se someterá a votación del Pleno y, en caso de que ésta fuese negativa, se tendrá por desechada.\nNo podrá presentarse más de una moción suspensiva en la discusión de un asunto.\nArtículo Reformado\n.\nActualización Legislativa.\nÚltima reforma Gaceta No. 63, Especial, 14-Ago-2025\nARTICULO 140. En cualquier estado del debate un Diputado podrá pedir la observancia de la presente Ley formulando una moción de orden. Al efecto deberá citar el precepto o preceptos cuya aplicación reclama. Escuchada la moción, el Presidente resolverá lo conducente.\nNo podrá llamarse al orden al Diputado que critique o censure a servidores públicos por faltas o errores cometidos en el desempeño de sus atribuciones.\nARTICULO 141. Si en el curso del debate alguno de los oradores hiciese alusiones sobre la persona o conducta de un Diputado, éste podrá solicitar al Presidente hacer uso de la palabra, para dar contestación a las alusiones formuladas. Cuando la alusión afecte a un grupo parlamentario, el Presidente podrá conceder el uso de la palabra solicitada por un miembro del grupo aludido, para dar contestación a las alusiones.\nEn éstos casos el Presidente concederá el uso de la palabra inmediatamente después de que haya concluido el orador que profirió las alusiones.\nARTICULO 142. En el curso de un debate los miembros del Congreso podrán rectificar hechos al concluir el orador.\nARTICULO 143. Agotada la lista de oradores dada a conocer al inicio del debate y concluidas las alusiones personales o las rectificaciones a que se refieren los artículos anteriores, el Presidente preguntará al Pleno si el asunto se encuentra suficientemente discutido, en cuyo caso cerrará el debate y llamará de inmediato a votación.\nSi se declara que el asunto no se considera suficientemente discutido se continuará con la discusión, pero bastará que hable un Diputado en pro y otro en contra, para que repita la pregunta.\nARTICULO 144. Al momento de cerrarse un debate y antes de proceder a recoger la votación, el Presidente ordenará a la Dirección de Procesos Parlamentarios, que hagan el anuncio correspondiente a fin de que todos los Diputados presentes en el recinto parlamentario pasen de inmediato a ocupar sus asientos en el salón de sesiones y puedan emitir su voto.\nArtículo Reformado\nARTICULO 145. Cuando se dispense el trámite a que se refiere el Artículo 119 de esta Ley, se pondrá a discusión inmediatamente después de que su autor la haya presentado, pudiendo hacer uso de la palabra hasta dos Diputados en contra y dos en pro, e inmediatamente se someterá a votación del Pleno la propuesta. De ser aprobada se le dará el trámite correspondiente y, en caso contrario se turnará a la Comisión correspondiente.\nArtículo Reformado\nARTICULO 145 BIS. Las proposiciones de acuerdo económico se presentarán por escrito y firmadas, con su exposición de motivos en la cual exponga su autor o autores las\n.\nActualización Legislativa.\nÚltima reforma Gaceta No. 63, Especial, 14-Ago-2025 consideraciones jurídicas, políticas, sociales o económicas que justifican, explican, motivan y dan procedencia a la proposición, y se sujetarán al procedimiento siguiente:\nI. El Presidente del Congreso someterá a solicitud del Diputado Inicialista la dispensa de trámite en los términos referidos en el artículo 119 de esta ley, en caso de no aprobarse por el Pleno o no solicitarse dispensa, se turnará invariablemente a la Comisión competente.\nII. Aprobada la dispensa de trámite y abierto el debate por el Presidente del\nCongreso, los Diputados podrán adherirse o sumarse a la proposición de acuerdo económico presentada.\nIII. Sí algún Diputado considera necesario complementarla o clarificarla, podrá hacerlo mediante escrito que deberá leer, precisando la modificación o adición que sugiere, al punto de acuerdo económico presentado por el Diputado inicialista.\nIV. Presentada la modificación o adición, el Presidente del Congreso preguntará al\nDiputado Inicialista si acepta la modificación o adición en cuyo caso se incorporarán los planteamientos propuestos al punto de acuerdo; en caso de no aceptarse se someterá la proposición inicial al trámite respectivo.\nV. Las modificaciones o adiciones a las proposiciones de acuerdo económico, que no sean presentadas por escrito al momento de que el Diputado haga uso de la palabra, sólo quedará registrada en el Diario de los Debates, sin que se someta al procedimiento señalado en el presente Artículo.\nArtículo Adicionado\nCAPITULO V\nDE LAS VOTACIONES\nARTICULO 146. Las resoluciones del Congreso del Estado se tomarán por mayoría de votos de los Diputados.\nPara la aprobación de las minutas de reformas a la Constitución Federal, se requerirá de mayoría calificada.\nPárrafo Adicionando\nArtículo Reformando\nARTICULO 147. La mayoría de votos puede ser simple, absoluta o calificada, entendiéndose por:\nI. Mayoría simple, la correspondiente a más de la mitad de los Diputados que asistan a la sesión;\nII. Mayoría absoluta, la correspondiente a más de la mitad de los Diputados que integran el Congreso del Estado; y,.\nActualización Legislativa.\nÚltima reforma Gaceta No. 63, Especial, 14-Ago-2025\nIII. Mayoría calificada, la correspondiente a las dos terceras partes de los Diputados que integran el Congreso del Estado.\nEn los casos en que la Constitución Local, esta Ley, sus Reglamentos u otros ordenamientos, no definan la clase de votación para resolver un asunto de competencia del\nCongreso, se entenderá que deberá efectuarse por mayoría simple.\nARTICULO 148. Habrá tres tipos de votaciones: nominal, económica o por cédula.\nARTICULO 149. Se aprobará por votación nominal los dictámenes de iniciativa de\nLey o decretos, en lo general, y cada libro, título, capítulo, sección o artículo, en lo particular.\nIgualmente podrá sujetarse a votación nominal un acuerdo o propuesta cuando lo solicite un Diputado y sea apoyado por otros dos Diputados por lo menos; siempre y cuando sea aprobado por el Pleno del Congreso del Estado.\nARTICULO 150. La votación nominal se emitirá de la siguiente forma:\nI. Cada miembro del Congreso, comenzando por el lado derecho del Presidente dirá: en voz alta su nombre completo, apellido paterno o apellido paterno y materno, añadiendo la expresión \"a favor\", \"en contra\" o \"me abstengo\";\nII. El Secretario anotará a los Diputados que aprueben y a los que desaprueben;\nIII. Concluído este acto, el Secretario preguntará dos veces en voz alta si falta algún\nDiputado por votar y no faltando, se procederá a tomar la votación de los integrantes de la\nMesa Directiva, empezando por el Prosecretario, Secretario, Vicepresidente y por último votará el Presidente, sin que se admita después voto alguno; y,\nIV. El Secretario hará enseguida el cómputo definitivo de los votos y dará a conocer al\nPresidente el resultado de la votación para que éste haga la declaratoria correspondiente.\nARTICULO 151. Las votaciones serán económicas, cuando se trate de aprobar:\nI. El acta de la sesión anterior;\nII. El orden del día;\nIII. Las proposiciones de acuerdo económico, excepto en el caso previsto en el\nArtículo 149 de esta Ley;\nIV. La prolongación de las sesiones; y,\nV. Las resoluciones que no tenga señalada un tipo específico de votación.\nArtículo Reformado\n.\nActualización Legislativa.\nÚltima reforma Gaceta No. 63, Especial, 14-Ago-2025\nARTICULO 152. Para llevar a cabo una votación económica, el Secretario de la Mesa\nDirectiva, preguntará: \"Por instrucciones de la Presidencia se pregunta a los señores\nDiputados si están a favor o en contra de la propuesta sometida a su consideración\", debiendo los Diputados expresar su voto levantando la mano, primeramente los que están a favor y enseguida los que están en contra.\nARTICULO 153. El Secretario hará el recuento de los votos y dirá en voz alta el número total de votos a favor, de votos en contra y abstenciones, y el Presidente declarará el resultado final.\nARTICULO 154. Cuando hubiera duda sobre el resultado de la votación, cualquier\nDiputado podrá solicitar que se repita, dando a conocer de inmediato el resultado de la misma.\nCuando se objetare por más de dos ocasiones el resultado de la votación económica, el Presidente ordenará al Secretario que la efectúe de forma nominal.\nARTICULO 155. Los Diputados en las votaciones nominales y económicas tienen la obligación de votar a favor o en contra, en caso de abstención deberán razonar ésta.\nARTICULO 156. Las votaciones para elegir Diputados que ocuparán algún cargo en la Mesa Directiva, se realizarán conforme a la propuesta que presente la Junta de\nCoordinación Política de acuerdo a lo previsto por el artículo 148 de la Presente Ley.\nConcluida la votación, el Secretario hará el cómputo de los votos y lo dará a conocer al Presidente, quien hará la declaratoria correspondiente.\nArtículo Reformado\nARTICULO 157. Para llevar a cabo una votación por cédula, se estará a lo siguiente:\nI. El Titular de la Dirección de Procesos Parlamentarios, distribuirá a los Diputados las cédulas correspondientes y colocará un ánfora transparente en la tribuna frente al\nPresidente;\nII. El Secretario de la Mesa Directiva por instrucciones del Presidente, llamará a los\nDiputados a depositar su voto en orden alfabético. Los Diputados podrán o no firmar la cédula que contenga su voto;\nIII. Concluida la votación el Secretario extraerá las cédulas de la ánfora, hará el computo de los votos y lo dará a conocer al Presidente; y,\nIV. El Presidente hará la declaratoria correspondiente.\nEn las votaciones por cédula se entenderá que el voto es nulo, cuando la misma este\nArtículo Reformado\n.\nActualización Legislativa.\nÚltima reforma Gaceta No. 63, Especial, 14-Ago-2025\nARTICULO 158. Cuando hubiera empate en cualquier tipo de votación se repetirá ésta hasta por dos veces; si no obstante el empate continuara, el Presidente hará uso del voto de calidad que le asiste.\nARTICULO 159. En las votaciones, cualquier Diputado podrá pedir que conste en el acta el sentido en que emita su voto.\nCAPITULO VI\nDE LOS DECRETOS\nARTICULO 160. Toda resolución del Congreso del Estado tendrá el carácter de Ley o\nDecreto. El primer nombre corresponde a las que versen sobre materias de interés común, dentro del ámbito de atribuciones del Poder Legislativo. El segundo corresponde a las que dentro del ámbito sean solo relativas a determinados tiempos, lugares, Entidades públicas o personas.\nARTICULO 161. Los proyectos de Leyes y los Decretos aprobados por el Congreso, se remitirán al Ejecutivo firmados por el Presidente y el Secretario de la Mesa Directiva del\nCongreso del Estado.\nARTICULO 162. Las iniciativas, adquirirán el carácter de Ley, cuando sean aprobadas por el Congreso del Estado y publicadas por el Ejecutivo.\nSi la Ley no fija el día en que deba comenzar a observarse, será obligatoria en todo el\nEstado tres días después de la fecha de su publicación en el Periódico Oficial del Estado.\nARTICULO 163. En el caso de que el Ejecutivo juzgue conveniente hacer observaciones a un proyecto aprobado por el Congreso del Estado, éste podrá ejercitar su derecho de Veto, atendiendo a lo previsto por el Artículo 34 de la Constitución Local.\nARTICULO 164. El Gobernador del Estado no podrá hacer observaciones sobre los actúe en funciones de Jurado de Sentencia.\nCAPITULO VII\nDE LA GESTORIA COMUNITARIA comunitaria, a efecto de atender los asuntos siguientes:\nI. La atención a las peticiones de los particulares, que se formulen por escrito o en forma oral, de manera pacífica y respetuosa;\n.\nActualización Legislativa.\nÚltima reforma Gaceta No. 63, Especial, 14-Ago-2025\nII. Turnar a las dependencias y entidades correspondientes del Gobierno del Estado, las demandas y peticiones de los ciudadanos;\nIII. Turnar a las Comisiones respectivas del Congreso del Estado y participar en unión con ellas en la resolución, atención y gestión, de las peticiones y asuntos que presente la\nCiudadanía; y\nIV. Las demás que se consideren necesarias.\nA fin de apoyar los trabajos de Gestoría Comunitaria, los diputados contarán con\nMódulos de Atención Ciudadana, los cuales funcionarán conforme a lo previsto por el\nReglamento respectivo.\nCAPITULO VIII\nDE LAS COMPARECENCIAS\nARTICULO 166. El Pleno del Congreso o las Comisiones directamente involucradas en el tema o asunto, por mayoría simple de sus integrantes, podrán citar a comparecer a los\nSecretarios del ramo, Procurador de Justicia del Estado, Titulares o Administradores de los\nOrganismos Descentralizados Estatales o de las empresas de participación estatal mayoritaria, así como al Presidente del Tribunal Superior de Justicia y del Consejo de la\nJudicatura y a los Titulares de los Órganos Constitucionales Autónomos, para que informen cuando se discute una Ley, se realice la Glosa del Informe que rindan el Titular del Ejecutivo del Estado o del Poder Judicial o cuando se estudie un asunto concerniente a sus respectivos ramos o actividades, estando obligados a acudir a las sesiones respectivas.\nLos servidores públicos que no concurran a las sesiones correspondientes, se harán acreedores a las sanciones previstas en la Ley de Responsabilidades de los Servidores\nPúblicos del Estado.\nArtículo Reformado\nCAPITULO IX\nDE LAS DESIGNACIONES\nARTICULO 167. Para la designación de los Servidores Públicos que por disposición\nConstitucional o Legal le corresponda realizar al Poder Legislativo, se atenderá al procedimiento previsto en el Reglamento, excepto en los casos en que dicho procedimiento se encuentre regulado por otro ordenamiento legal.\nTÍTULO OCTAVO\nDenominación Adicionada\nCAPÍTULO PRIMERO\nDECLARACIÓN PATRIMONIAL Y DE INTERÉSES\nDenominación Modificada\n.\nActualización Legislativa.\nÚltima reforma Gaceta No. 63, Especial, 14-Ago-2025\nARTICULO 168. Tienen la obligación de presentar su declaración de situación patrimonial y de intereses, bajo protesta de decir verdad, las y los Diputados, las y los\nTitulares de las Direcciones y Unidades Auxiliares, la persona Titular de la Auditoría Superior del Estado, y demás personas servidoras públicas del Poder Legislativo conforme a las modalidades y plazos que señala la Ley de Responsabilidades Administrativas del Estado de\nBaja California.\nArtículo Reformado\nARTICULO 169. La declaración patrimonial será presentada ante la Unidad de\nContraloría Interna del Congreso del Estado.\nArtículo Reformado\nCAPÍTULO SEGUNDO\nDEL SEMÁFORO DE VOTACIONES\nCapítulo Adicionado\nCapítulo Derogado\nCapítulo Adicionado\nARTÍCULO 169 BIS. El registro individual de votaciones se publicará en el portal de internet con la denominación “Semáforo de Votaciones”, y contendrá el registro de votaciones nominales y económicas dadas en pleno y comisiones.\nArtículo Adicionado\nArtículo Derogado\nArtículo Adicionado\nCAPÍTULO TERCERO\nDEL PARLAMENTO ABIERTO\nCapítulo Adicionado\nARTICULO 170. El Congreso del Estado fomentará la implementación de un\nParlamento Abierto basado en los principios de transparencia en la información, rendición de cuentas, evaluación del desempeño legislativo, participación ciudadana y uso de tecnologías de la información. En el ejercicio de sus funciones, las y los Diputados deberán establecer un marco de apertura institucional que permita a la ciudadanía involucrarse de manera pacífica y organizada en los procesos legislativos.\nPárrafo Adicionado\nAdemás, el Congreso del Estado promoverá la adopción de mejores prácticas de transparencia para alcanzar los principios establecidos en este artículo, así como la municipal.\nPárrafo Adicionado\nComo parte de los mecanismos de participación ciudadana, se creará un espacio recibirán las opiniones de la ciudadanía sobre las iniciativas de ley presentadas.\nPárrafo Adicionado\nArtículo Derogado\nArtículo Reformado\n.\nActualización Legislativa.\nÚltima reforma Gaceta No. 63, Especial, 14-Ago-2025\nCAPÍTULO CUARTO\nDE LAS INICIATIVAS CIUDADANAS\nCapítulo Adicionado\nARTÍCULO 170 BIS. El Congreso del Estado deberá habilitar y mantener actualizado, dentro del portal oficial de internet, un apartado específico en el que la ciudadanía pueda consultar de manera accesible y ordenada, las iniciativas ciudadanas que hayan sido presentadas conforme a lo establecido por esta Ley y la Ley de Participación Ciudadana del\nEstado de Baja California.\nEste apartado deberá contener, al menos, la siguiente información de cada iniciativa ciudadana:\nI. La fecha de presentación de la iniciativa;\nII. La pretensión legislativa;\nIII. Indicar si la iniciativa fue presentada por:\na) 500 o más personas ciudadanas;\nb) Una Organización de la Sociedad Civil; o,\nc) Una Institución de Educación Superior.\nIV.- El documento presentado sin datos personales;\nV.- Etapa del proceso en el que se encuentre la iniciativa; y,\nVI.- El documento parlamentario con el que concluya su trámite independientemente de su resultado.\nArtículo Adicionado\nTÍTULO NOVENO\nArtículo 171. La Gaceta es el órgano informativo oficial del Congreso del Estado, depende de la Mesa Directiva y cuenta con un Consejo Directivo, formado por los propios el Director de Administración; el Presidente de la Mesa Directiva lo es del Consejo.\nLa Gaceta estará a cargo de la Dirección de Procesos Parlamentarios. Los\nReglamento.\n.\nActualización Legislativa.\nÚltima reforma Gaceta No. 63, Especial, 14-Ago-2025\nLa Gaceta publica en medios impresos o en la página de Internet del Congreso del estado, lo siguiente:\nI. Los citatorios a las diversas actividades del Congreso;\nII. El Proyecto de Orden del Día de las sesiones del Pleno;\nIII. Las comunicaciones oficiales dirigidas al Congreso;\nIV. Las solicitudes de licencia de los diputados;\nV. Las comunicaciones de particulares dirigidas al Congreso;\nVI. Los proyectos de ley iniciados por los ciudadanos o los ayuntamientos, y los proyectos de ley o decreto remitidos por el gobernador del estado;\nVII. Las proposiciones de acuerdo económico o los acuerdos sobre el régimen interior del Congreso que presentan sus órganos de gobierno;\nVIII. Los cambios aprobados en la integración de las comisiones y los comités;\nIX. Las proposiciones de acuerdo económico que presentan los legisladores;\nX. Las observaciones sobre proyectos de ley o decreto enviadas por el Titular del\nPoder Ejecutivo Estatal;\nXI. Las actas, informes, resoluciones, acuerdos, declaraciones y pronunciamientos del\nPleno, la Mesa, la Junta, las comisiones y los comités;\nXII. Los dictámenes de las comisiones y los votos particulares;\nXIII. Los informes de las representaciones y delegaciones del Congreso que asistan a reuniones interparlamentarias o internacionales;\nXIV. La información sobre administración y los servicios del Congreso;\nXV. Las convocatorias y los proyectos de Orden del Día de las reuniones de comisiones y de comités;\nXVI. El registro de asistencia e inasistencia de los diputados a las sesiones del\nPleno;\nXVII. El registro de asistencia e inasistencia de los diputados a las reuniones de comisiones y de comités;\n.\nActualización Legislativa.\nÚltima reforma Gaceta No. 63, Especial, 14-Ago-2025\nXVIII.Las reformas a los ordenamientos que rigen la vida interna del Poder Legislativo una vez aprobadas por el Pleno; y,\nXIX. Los demás documentos oficiales que dispongan la Mesa y la Junta.\nLa Gaceta se publica los días cuando sesiona el Pleno y podrá publicarse los demás días hábiles.\nArtículo Reformado\nArtículo 172. El Congreso del estado cuenta con un órgano oficial de información denominado \"Diario de los Debates\", donde consta la siguiente información de las sesiones del Pleno:\n1. Lugar, fecha y hora del inicio y término de cada sesión;\n2. Carácter de la sesión;\n3. Declaratoria del quorum;\n4. Orden del día;\n5. Nombre del Presidente y de quienes presidan la sesión durante su desarrollo;\n6. Copia fiel del acta de la sesión anterior;\n7. Transcripción de los debates en el orden en que se realizan;\n8. Intervenciones de los diputados en tribuna y desde las cumies;\n9. Textos leídos;\n10. Textos no leídos cuya inserción ordenan el Presidente o el Pleno;\n11. Documentos a los que se de turno;\n12. Propuestas y resoluciones aprobadas;\n13. Dictámenes y votos particulares y;\n14. Resultado de las votaciones. término de la sesión, indistintamente en medio impreso o en la página electrónica del\nCongreso en Internet.\nTÍTULO DÉCIMO\nPRÁCTICAS SUSTENTABLES\n.\nActualización Legislativa.\nÚltima reforma Gaceta No. 63, Especial, 14-Ago-2025\nTítulo Adicionado\nArtículo 173. El Poder Legislativo contará con un programa de desarrollo ambiental, para regular prácticas ambientales sustentables en todas sus oficinas e instalaciones.\nEl programa contemplará el sistema de manejo ambiental, que incluya capacitación, formación y mejoramiento ambiental en la prestación de servicios.\nAsimismo regulará la eficiencia administrativa, con políticas para lograr el consumo racional y sustentable de los recursos materiales y financieros, así como las adquisiciones de bienes para la prestación de sus servicios y cumplimiento de sus funciones, optando por la utilización y el consumo de productos compuestos total o parcialmente de materiales valorizables.\nLa Dirección de Administración se encargará de implementar y dar seguimiento al programa de desarrollo ambiental, incluyendo todas las acciones derivadas del mismo que comprenderán los aspectos de manejo de residuos sólidos, fomento de uso de energías alternativas y ahorro de agua, disminución del impacto negativo al medio y entorno generado por las actividades cotidianas del Poder Legislativo.\nLas oficinas e instalaciones de este Poder Legislativo contarán con contenedores especiales para el reciclaje de las distintas clases de desperdicios, atendiendo al programa de desarrollo ambiental.\nArtículo Adicionado\nArtículo Reformado\nTÍTULO DÉCIMO PRIMERO\n“DE LA OBLIGACIÓN DE IMPARCIALIDAD EN PROCESO ELECTORAL”\nTítulo Adicionado\nArtículo 174.- Los diputados que sean postulados para su elección consecutiva se ajustaran a la forma, términos y condiciones que señale la Ley Electoral del Estado.\nArtículo Adicionado\nArtículo 175.- Queda prohibido a los diputados que participen en el proceso de\nArtículo Adicionado\nArtículo 176.- Está prohibido realizar actos de expresión que se realicen bajo político, o expresiones solicitando cualquier tipo de apoyo para contender en el proceso electoral por alguna candidatura o para un partido político.\nArtículo Adicionado\n.\nActualización Legislativa.\nÚltima reforma Gaceta No. 63, Especial, 14-Ago-2025\nArtículo 177.- Está prohibido la utilización del personal asignado al Poder Legislativo labores. Se considera horario oficial de labores el previsto en los artículos 24 y 25 de la Ley del Servicio Civil de los Trabajadores al Servicio de los Poderes del Estado y Municipios de\nBaja California.\nArtículo Adicionado\nTratándose de Diputados, además de lo anterior, será considerado oficial y hábil cualquier horario en el que se desarrollen las sesiones de pleno o de comisiones de las que formen parte.\nArtículo 178.- Es injustificable la ausencia de un diputado a una sesión ordinaria o de comisión de la cual sea integrante, para asistir o participar como candidato o militante de algún partido político en un acto o evento de campaña política.\nArtículo Adicionado\nARTICULOS TRANSITORIOS\nPRIMERO. La presente Ley entrará en vigor al día siguiente al de su publicación en el\nPeriódico Oficial, órgano de Gobierno del Estado.\nSEGUNDO. A partir de la iniciación de su vigencia, queda abrogada la Ley Orgánica del Poder Legislativo del Estado de Baja California, publicada en el Periódico Oficial número\n43 de fecha trece de septiembre de 1995, así como las reformas y adiciones surgidas desde el momento de su promulgación.\nTERCERO. En un término de ciento ochenta días posteriores a la entrada en vigor de esta Ley, se crearán los Reglamentos respectivos, y se modificarán los ordenamientos jurídicos correlativos a la misma en todo lo que se opongan o contradigan con ésta.\nCUARTO. Cualquier controversia que se origine con anterioridad a la creación del\nReglamento Interior, así como del Reglamento de Procedimientos y Prácticas\nParlamentarias, ambos del Poder Legislativo del Estado de Baja California; se resolverá mediante acuerdo por el Pleno del Congreso del Estado.\nQUINTO. Con relación al órgano auxiliar denominado de la Dirección de\nProgramación y Gasto Interno, éste se creará una vez que se cuenten con los recursos presupuestales correspondientes, para tal efecto.\nDADO en el Salón de Sesiones “Lic. Benito Juárez García” del Honorable Poder\nLegislativo, en la ciudad de Mexicali, Baja California, a los veinte días del mes de junio del año dos mil dos.\nDIP. JESUS ALEJANDRO RUIZ URIBE\nPRESIDENTE\n.\nActualización Legislativa.\nÚltima reforma Gaceta No. 63, Especial, 14-Ago-2025\n(RÚBRICA).\nDIP. MARIA ROSALBA MARTIN NAVARRO\nPROSECRETARIA\n(RÚBRICA).\nDE CONFORMIDAD CON LO DISPUESTO POR LA FRACCION I DEL ARTICULO 49\nDE LA CONSTITUCION POLITICA DEL ESTADO, MANDO SE IMPRIMA Y PUBLIQUE.\nMEXICALI, BAJA CALIFORNIA, A LOS VEINTICUATRO DIAS DEL MES DE JUNIO\nDEL AÑO DOS MIL DOS.\nGOBERNADOR DEL ESTADO.\nEUGENIO ELORDUY WALTHER.\nSECRETARIO GENERAL DE GOBIERNO.\nBERNARDO BORBON VILCHES.\n.\nActualización Legislativa.\nÚltima reforma Gaceta No. 63, Especial, 14-Ago-2025\nARTICULO 1. Fue reformado por Decreto No. 145, publicado en el Periódico Oficial\nNo. 03, de fecha 14 de enero de 2003, Número Especial, Tomo CX, expedido por la H. XVII\nLegislatura, siendo Gobernador Constitucional el C. Eugenio Elorduy Walther 2001-2007;\nARTICULO 6. Fue reformado por Decreto No. 2, Publicado en el Periódico Oficial No.\n50, de fecha 19 de noviembre de 2004, Sección II, Tomo CXI, expedido por la H. XVIII\nLegislatura, siendo Gobernador Constitucional el C. Eugenio Elorduy Walther 2001-2007;\nARTICULO 7. Fue reformado por Decreto No. 2, Publicado en el Periódico Oficial No.\n50, de fecha 19 de noviembre de 2004, Sección II, Tomo CXI, expedido por la H. XVIII\nLegislatura, siendo Gobernador Constitucional el C. Eugenio Elorduy Walther 2001-2007;\nARTICULO 8. Fue reformado por Decreto No. 2, Publicado en el Periódico Oficial No.\n50, de fecha 19 de noviembre de 2004, Sección II, Tomo CXI, expedido por la H. XVIII\nLegislatura, siendo Gobernador Constitucional el C. Eugenio Elorduy Walther 2001-2007;\nARTICULO 9. Fue reformado por Decreto No. 2, Publicado en el Periódico Oficial No.\n50, de fecha 19 de noviembre de 2004, Sección II, Tomo CXI, expedido por la H. XVIII\nLegislatura, siendo Gobernador Constitucional el C. Eugenio Elorduy Walther 2001-2007; fue reformado mediante Decreto No. 145, publicado en el Periódico Oficial No. 50, de fecha 10 de noviembre de 2017, Tomo CXXIV, Sección V, expedido por la H. XXII Legislatura, siendo\nGobernador Constitucional el C. Francisco Arturo Vega de Lamadrid 2013-2019; fue reformado mediante Iniciativa, publicada en la Gaceta Parlamentaria No. 47, de fecha 08 de abril de 2020, expedido por la H. XXIII Legislatura, siendo Gobernador Constitucional el C.\nJaime Bonilla Valdez 2019-2021;\nARTICULO 10. Fue reformado por Decreto No. 150, publicado en el Periódico Oficial\nNo. 06, de fecha 31 de enero de 2003, Sección II, Tomo CX, expedido por la H. XVII\nLegislatura, siendo Gobernador Constitucional el C. Eugenio Elorduy Walther 2001-2007; fue reformado por Decreto No. 387, Publicado en el Periódico Oficial No. 29, de fecha 02 de julio de 2010, Tomo CXVII, expedido por la H. XIX Legislatura, siendo Gobernador Constitucional el C. José Guadalupe Osuna Millán 2007-2013; Fue reformado mediante sesión de Pleno efectuada el día 02 de octubre de 2010; fue reformado por Decreto No. 11, publicado en el\nPeriódico Oficial No. 56, de fecha 17 de diciembre de 2010, Tomo CXVII, Sección III, expedido por la H. XX Legislatura, siendo Gobernador Constitucional el C. José Guadalupe\nOsuna Millán 2007-2013; fue reformado mediante Decreto No. 19, publicado en el Periódico\nH. XXII Legislatura, siendo Gobernador Constitucional el C. Francisco Arturo Vega de\nLamadrid 2013-2019;\nARTICULO 11. Fue reformado por Decreto No. 2, Publicado en el Periódico Oficial\nLegislatura, siendo Gobernador Constitucional el C. Eugenio Elorduy Walther 2001-2007; fue reformado por Decreto No. 52, publicado en el Periódico Oficial No. 27, de fecha 03 de junio\n.\nActualización Legislativa.\nÚltima reforma Gaceta No. 63, Especial, 14-Ago-2025 de 2011, Tomo CXVIII, Sección I, expedido por la H. XX Legislatura, siendo Gobernador\nConstitucional el C. José Guadalupe Osuna Millán 2007-2013;\nARTICULO 12. Fue reformado por Decreto No. 2, Publicado en el Periódico Oficial\nNo. 50, de fecha 19 de noviembre de 2004, Sección II, Tomo CXI, expedido por la H. XVIII\nLegislatura, siendo Gobernador Constitucional el C. Eugenio Elorduy Walther 2001-2007; fue reformado mediante el Dictamen No. 266 de la Comisión de Gobernación, Legislación y\nPuntos Constitucionales, publicdo en la Gaceta Parlamentaria del Congreso del Estado en fecha 27 de agosto de 2013, expedido por la H. XX Legislatura, siendo Gobernador\nConstitucional el C. José Guadalupe Osuna Millán 2007-2013;\nARTICULO 13. Fue reformado mediante sesión de Pleno efectuada el día 02 de octubre de 2010; fue reformado mediante el Dictamen No. 266 de la Comisión de\nGobernación, Legislación y Puntos Constitucionales, publicdo en la Gaceta Parlamentaria del Congreso del Estado en fecha 27 de agosto de 2013, expedido por la H. XX Legislatura, siendo Gobernador Constitucional el C. José Guadalupe Osuna Millán 2007-2013; fue reformado mediante Decreto No. 19, publicado en el Periódico Oficial No. 52, de fecha 25 de noviembre de 2016, Tomo CXXIII, Sección IV, expedido por la H. XXII Legislatura, siendo\nGobernador Constitucional el C. Francisco Arturo Vega de Lamadrid 2013-2019;\nARTICULO 14. Fue reformado mediante el Dictamen No. 266 de la Comisión de\nGobernación, Legislación y Puntos Constitucionales, publicdo en la Gaceta Parlamentaria del Congreso del Estado en fecha 27 de agosto de 2013, expedido por la H. XX Legislatura, siendo Gobernador Constitucional el C. José Guadalupe Osuna Millán 2007-2013; fue reformado mediante Decreto No. 19, publicado en el Periódico Oficial No. 52, de fecha 25 de noviembre de 2016, Tomo CXXIII, Sección IV, expedido por la H. XXII Legislatura, siendo\nGobernador Constitucional el C. Francisco Arturo Vega de Lamadrid 2013-2019;\nARTICULO 15. Fue reformado mediante el Dictamen No. 266 de la Comisión de\nGobernación, Legislación y Puntos Constitucionales, publicdo en la Gaceta Parlamentaria del Congreso del Estado en fecha 27 de agosto de 2013, expedido por la H. XX Legislatura, siendo Gobernador Constitucional el C. José Guadalupe Osuna Millán 2007-2013; fue reformado mediante Decreto No. 19, publicado en el Periódico Oficial No. 52, de fecha 25 de\nGobernador Constitucional el C. Francisco Arturo Vega de Lamadrid 2013-2019;\nFue adicionado este capítulo por Decreto No. 387, Publicado en el Periódico Oficial No. 29, Gobernador Constitucional el C. José Guadalupe Osuna Millán 2007-2013;\nCAPÍTULO SEGUNDO\nDEL PLAN DE DESARROLLO LEGISLATIVO\n.\nActualización Legislativa.\nÚltima reforma Gaceta No. 63, Especial, 14-Ago-2025\nARTICULO 16 BIS. Fue adicionado por Decreto No. 387, Publicado en el Periódico\nOficial No. 29, de fecha 02 de julio de 2010, Tomo CXVII, expedido por la H. XIX Legislatura, siendo Gobernador Constitucional el C. José Guadalupe Osuna Millán 2007-2013; fue reformado mediante sesión de Pleno efectuada el día 02 de octubre de 2010; fue reformado por Decreto No. 11, publicado en el Periódico Oficial No. 56, de fecha 17 de diciembre de\n2010, Tomo CXVII, Sección III, expedido por la H. XX Legislatura, siendo Gobernador\nConstitucional el C. José Guadalupe Osuna Millán 2007-2013;\nARTICULO 16 TER. Fue adicionado por Decreto No. 387, Publicado en el Periódico\nOficial No. 29, de fecha 02 de julio de 2010, Tomo CXVII, expedido por la H. XIX Legislatura, siendo Gobernador Constitucional el C. José Guadalupe Osuna Millán 2007-2013;\nARTICULO 16 QUARTER. Fue adicionado por Decreto No. 387, Publicado en el\nPeriódico Oficial No. 29, de fecha 02 de julio de 2010, Tomo CXVII, expedido por la H. XIX\nLegislatura, siendo Gobernador Constitucional el C. José Guadalupe Osuna Millán 20072013; fue reformado mediante sesión de Pleno efectuada el día 02 de octubre de 2010; fue reformado mediante Decreto No. 19, publicado en el Periódico Oficial No. 52, de fecha 25 de noviembre de 2016, Tomo CXXIII, Sección IV, expedido por la H. XXII Legislatura, siendo\nGobernador Constitucional el C. Francisco Arturo Vega de Lamadrid 2013-2019; fue reformado por Decreto No. 310, publicado en el Periódico Oficial No. 62, de fecha 06 de noviembre de 2023, Sección I, Tomo CXXX, expedido por la H. XXIV Legislatura, siendo\nGobernadora Constitucional la C. Marina del Pilar Ávila Olmeda 2021-2027;\nARTICULO 17. Fue reformado por Decreto No. 145, publicado en el Periódico Oficial\nNo. 03, de fecha 14 de enero de 2003, Número Especial, Tomo CX, expedido por la H. XVII\nLegislatura, siendo Gobernador Constitucional el C. Eugenio Elorduy Walther 2001-2007; fue adicionado por Decreto No. 387, Publicado en el Periódico Oficial No. 29, de fecha 02 de julio de 2010, Tomo CXVII, expedido por la H. XIX Legislatura, siendo Gobernador\nConstitucional el C. José Guadalupe Osuna Millán 2007-2013; fue reformado mediante\nDecreto No. 19, publicado en el Periódico Oficial No. 52, de fecha 25 de noviembre de 2016, Tomo CXXIII, Sección IV, expedido por la H. XXII Legislatura, siendo Gobernador\nConstitucional el C. Francisco Arturo Vega de Lamadrid 2013-2019;\nARTICULO 18. Fue reformado por Decreto No. 2, Publicado en el Periódico Oficial\nNo. 50, de fecha 19 de noviembre de 2004, Sección II, Tomo CXI, expedido por la H. XVIII\nLegislatura, siendo Gobernador Constitucional el C. Eugenio Elorduy Walther 2001-2007; fue adicionado por Decreto No. 387, Publicado en el Periódico Oficial No. 29, de fecha 02 de\nConstitucional el C. José Guadalupe Osuna Millán 2007-2013; fue reformado por Decreto\nCXVII, Sección III, expedido por la H. XX Legislatura, siendo Gobernador Constitucional el C.\nJosé Guadalupe Osuna Millán 2007-2013; fue reformado mediante el Dictamen No. 266 de la Comisión de Gobernación, Legislación y Puntos Constitucionales, publicdo en la Gaceta\n.\nActualización Legislativa.\nÚltima reforma Gaceta No. 63, Especial, 14-Ago-2025\nXX Legislatura, siendo Gobernador Constitucional el C. José Guadalupe Osuna Millán 20072013; fue reformado mediante Decreto No. 19, publicado en el Periódico Oficial No. 52, de fecha 25 de noviembre de 2016, Tomo CXXIII, Sección IV, expedido por la H. XXII\nLegislatura, siendo Gobernador Constitucional el C. Francisco Arturo Vega de Lamadrid\n2013-2019; fue reformado por Decreto No. 310, publicado en el Periódico Oficial No. 62, de fecha 06 de noviembre de 2023, Sección I, Tomo CXXX, expedido por la H. XXIV\nLegislatura, siendo Gobernadora Constitucional la C. Marina del Pilar Ávila Olmeda 20212027;\nARTICULO 19. Fue reformado por Decreto No. 2, Publicado en el Periódico Oficial\nNo. 50, de fecha 19 de noviembre de 2004, Sección II, Tomo CXI, expedido por la H. XVIII\nLegislatura, siendo Gobernador Constitucional el C. Eugenio Elorduy Walther 2001-2007;\nARTICULO 20. Fue reformado por Decreto No. 2, Publicado en el Periódico Oficial\nNo. 50, de fecha 19 de noviembre de 2004, Sección II, Tomo CXI, expedido por la H. XVIII\nLegislatura, siendo Gobernador Constitucional el C. Eugenio Elorduy Walther 2001-2007;\nARTICULO 21. Fue reformado por Decreto No. 2, Publicado en el Periódico Oficial\nNo. 50, de fecha 19 de noviembre de 2004, Sección II, Tomo CXI, expedido por la H. XVIII\nLegislatura, siendo Gobernador Constitucional el C. Eugenio Elorduy Walther 2001-2007;\nARTICULO 22. Fue reformado por Decreto No. 2, Publicado en el Periódico Oficial\nNo. 50, de fecha 19 de noviembre de 2004, Sección II, Tomo CXI, expedido por la H. XVIII\nLegislatura, siendo Gobernador Constitucional el C. Eugenio Elorduy Walther 2001-2007;\nARTICULO 23. Fue reformado por Decreto No. 2, Publicado en el Periódico Oficial\nNo. 50, de fecha 19 de noviembre de 2004, Sección II, Tomo CXI, expedido por la H. XVIII\nLegislatura, siendo Gobernador Constitucional el C. Eugenio Elorduy Walther 2001-2007; fue reformado mediante sesión de Pleno efectuada el día 02 de octubre de 2010;\nARTICULO 24. Fue reformado por Decreto No. 2, Publicado en el Periódico Oficial\nNo. 50, de fecha 19 de noviembre de 2004, Sección II, Tomo CXI, expedido por la H. XVIII\nLegislatura, siendo Gobernador Constitucional el C. Eugenio Elorduy Walther 2001-2007;\nARTICULO 27. Fue reformado por Decreto No. 42, Publicado en el Periódico Oficial\nNo. 5, de fecha 28 de enero de 2005, Tomo CXII, expedido por la H. XVIII Legislatura, siendo Gobernador Constitucional el C. Eugenio Elorduy Walther 2001-2007; reformado mediante el Dictamen No. 266 de la Comisión de Gobernación, Legislación y Puntos\nC. José Guadalupe Osuna Millán 2007-2013; fue reformado mediante Decreto No. 19,\nSección IV, expedido por la H. XXII Legislatura, siendo Gobernador Constitucional el C.\nFrancisco Arturo Vega de Lamadrid 2013-2019; fue reformado mediante Iniciativa, publicado\n.\nActualización Legislativa.\nÚltima reforma Gaceta No. 63, Especial, 14-Ago-2025 la H. XXIII Legislatura, siendo Gobernador Constitucional el C. Francisco Arturo Vega de\nLamadrid 2013-2019; fue reformado mediante Decreto No. 311, publicado en la Gaceta\nParlamentaria, No. 122, Especial, de fecha 09 de noviembre de 2023, y en el Periódico\nOficial No. 67, de fecha 01 de diciembre de 2023, Sección I, Tomo CXXX, expedido por la H.\nXXIV Legislatura, siendo Gobernadora Constitucional la C. Marina del Pilar Ávila Olmeda\n2021-2027;\nARTICULO 28. Fue reformado por Decreto No. 2, Publicado en el Periódico Oficial\nNo. 50, de fecha 19 de noviembre de 2004, Sección II, Tomo CXI, expedido por la H. XVIII\nLegislatura, siendo Gobernador Constitucional el C. Eugenio Elorduy Walther 2001-2007; fue reformado por Decreto No. 680, publicado en el Periódico Oficial No. 47, Sección V, Tomo\nCXXIII, de fecha 21 de octubre de 2016, expedido por la H. XXI Legislatura, siendo gobernador constitucional el C. Francisco Arturo Vega de Lamadrid 2013-2019; fue reformado mediante Decreto No. 311, publicado en la Gaceta Parlamentaria, No. 122, Especial, de fecha 09 de noviembre de 2023, y en el Periódico Oficial No. 67, de fecha 01 de diciembre de 2023, Sección I, Tomo CXXX, expedido por la H. XXIV Legislatura, siendo\nGobernadora Constitucional la C. Marina del Pilar Ávila Olmeda 2021-2027;\nARTICULO 29. Fue reformado mediante el Dictamen No. 266 de la Comisión de\nGobernación, Legislación y Puntos Constitucionales, publicdo en la Gaceta Parlamentaria del Congreso del Estado en fecha 27 de agosto de 2013, expedido por la H. XX Legislatura, siendo Gobernador Constitucional el C. José Guadalupe Osuna Millán 2007-2013;\nARTICULO 30. Fue reformado mediante el Dictamen No. 266 de la Comisión de\nGobernación, Legislación y Puntos Constitucionales, publicdo en la Gaceta Parlamentaria del Congreso del Estado en fecha 27 de agosto de 2013, expedido por la H. XX Legislatura, siendo Gobernador Constitucional el C. José Guadalupe Osuna Millán 2007-2013;\nARTICULO 31. Fue reformado por Decreto No. 145, publicado en el Periódico Oficial\nNo. 03, de fecha 14 de enero de 2003, Número Especial, Tomo CX, expedido por la H. XVII\nLegislatura, siendo Gobernador Constitucional el C. Eugenio Elorduy Walther 2001-2007; fue reformado por Decreto No. 2, Publicado en el Periódico Oficial No. 50, de fecha 19 de noviembre de 2004, Sección II, Tomo CXI, expedido por la H. XVIII Legislatura, siendo\nGobernador Constitucional el C. Eugenio Elorduy Walther 2001-2007; fue adicionado por\nDecreto No. 387, Publicado en el Periódico Oficial No. 29, de fecha 02 de julio de 2010, Tomo CXVII, expedido por la H. XIX Legislatura, siendo Gobernador Constitucional el C.\nJosé Guadalupe Osuna Millán 2007-2013; fue reformado mediante sesión de Pleno\nComisión de Gobernación, Legislación y Puntos Constitucionales, publicdo en la Gaceta\nXX Legislatura, siendo Gobernador Constitucional el C. José Guadalupe Osuna Millán 20072013;\nARTICULO 32. Fue reformado mediante el Dictamen No. 266 de la Comisión de\n.\nActualización Legislativa.\nÚltima reforma Gaceta No. 63, Especial, 14-Ago-2025 del Congreso del Estado en fecha 27 de agosto de 2013, expedido por la H. XX Legislatura, siendo Gobernador Constitucional el C. José Guadalupe Osuna Millán 2007-2013;\nARTICULO 33. Fue reformado mediante el Dictamen No. 266 de la Comisión de\nGobernación, Legislación y Puntos Constitucionales, publicdo en la Gaceta Parlamentaria del Congreso del Estado en fecha 27 de agosto de 2013, expedido por la H. XX Legislatura, siendo Gobernador Constitucional el C. José Guadalupe Osuna Millán 2007-2013;\nARTICULO 34. Fue reformado mediante sesión de Pleno efectuada el día 02 de octubre de 2010; fue derogado mediante el Dictamen No. 266 de la Comisión de\nGobernación, Legislación y Puntos Constitucionales, publicdo en la Gaceta Parlamentaria del Congreso del Estado en fecha 27 de agosto de 2013, expedido por la H. XX Legislatura, siendo Gobernador Constitucional el C. José Guadalupe Osuna Millán 2007-2013;\nARTICULO 36. Fue reformado por Decreto No. 145, publicado en el Periódico Oficial\nNo. 03, de fecha 14 de enero de 2003, Número Especial, Tomo CX, expedido por la H. XVII\nLegislatura, siendo Gobernador Constitucional el C. Eugenio Elorduy Walther 2001-2007; fue reformado mediante sesión de Pleno efectuada el día 02 de octubre de 2010; fue reformado mediante Decreto No. 19, publicado en el Periódico Oficial No. 52, de fecha 25 de noviembre de 2016, Tomo CXXIII, Sección IV, expedido por la H. XXII Legislatura, siendo Gobernador\nConstitucional el C. Francisco Arturo Vega de Lamadrid 2013-2019;\nARTICULO 37. Fue reformado por Decreto No. 145, publicado en el Periódico Oficial\nNo. 03, de fecha 14 de enero de 2003, Número Especial, Tomo CX, expedido por la H. XVII\nLegislatura, siendo Gobernador Constitucional el C. Eugenio Elorduy Walther 2001-2007;\nFue reformado por Decreto No. 2, Publicado en el Periódico Oficial No. 50, de fecha 19 de noviembre de 2004, Sección II, Tomo CXI, expedido por la H. XVIII Legislatura, siendo\nGobernador Constitucional el C. Eugenio Elorduy Walther 2001-2007; fue reformado mediante sesión de Pleno efectuada el día 02 de octubre de 2010; fue reformado por\nDecreto No. 11, publicado en el Periódico Oficial No. 56, de fecha 17 de diciembre de 2010, Tomo CXVII, Sección III, expedido por la H. XX Legislatura, siendo Gobernador\nConstitucional el C. José Guadalupe Osuna Millán 2007-2013; fue reformado por Decreto\nNo. 52, publicado en el Periódico Oficial No. 27, de fecha 03 de junio de 2011, Tomo CXVIII,\nSección I, expedido por la H. XX Legislatura, siendo Gobernador Constitucional el C. José\nGuadalupe Osuna Millán 2007-2013; fue reformado mediante Decreto No. 19, publicado en expedido por la H. XXII Legislatura, siendo Gobernador Constitucional el C. Francisco Arturo\nVega de Lamadrid 2013-2019;\nARTICULO 38. fue reformado mediante sesión de Pleno efectuada el día 02 de\nLegislatura, siendo Gobernador Constitucional el C. José Guadalupe Osuna Millán 20072013; fue reformado mediante el Dictamen No. 266 de la Comisión de Gobernación,.\nActualización Legislativa.\nÚltima reforma Gaceta No. 63, Especial, 14-Ago-2025 del Estado en fecha 27 de agosto de 2013, expedido por la H. XX Legislatura, siendo\nGobernador Constitucional el C. José Guadalupe Osuna Millán 2007-2013;\nARTICULO 39. Fue reformado por Decreto No. 145, publicado en el Periódico Oficial\nNo. 03, de fecha 14 de enero de 2003, Número Especial, Tomo CX, expedido por la H. XVII\nLegislatura, siendo Gobernador Constitucional el C. Eugenio Elorduy Walther 2001-2007; fue modificado por Fe de Erratas, publicado en el Periódico Oficial No. 09, de fecha 21 de febrero de 2003, Tomo CX, expedido por la H. XVII Legislatura, siendo Gobernador\nConstitucional el C. Eugenio Elorduy Walther 2001-2007;\nARTICULO 40. Fue reformado por Decreto No. 145, publicado en el Periódico Oficial\nNo. 03, de fecha 14 de enero de 2003, Número Especial, Tomo CX, expedido por la H. XVII\nLegislatura, siendo Gobernador Constitucional el C. Eugenio Elorduy Walther 2001-2007; fue modificado por Fe de Erratas, publicado en el Periódico Oficial No. 09, de fecha 21 de febrero de 2003, Tomo CX, expedido por la H. XVII Legislatura, siendo Gobernador\nConstitucional el C. Eugenio Elorduy Walther 2001-2007; Fue reformado por Decreto No. 2, Publicado en el Periódico Oficial No. 50, de fecha 19 de noviembre de 2004, Sección II, Tomo CXI, expedido por la H. XVIII Legislatura, siendo Gobernador Constitucional el C.\nEugenio Elorduy Walther 2001-2007; fue reformado mediante sesión de Pleno efectuada el día 02 de octubre de 2010; fue reformado por Decreto No. 11, publicado en el Periódico\nOficial No. 56, de fecha 17 de diciembre de 2010, Tomo CXVII, Sección III, expedido por la\nH. XX Legislatura, siendo Gobernador Constitucional el C. José Guadalupe Osuna Millán\n2007-2013; fue reformado por Decreto No. 172, publicado en el Periódico Oficial No. 8, de fecha 10 de febrero de 2012, Tomo CXIX, Sección I, expedido por la H. XX Legislatura, siendo Gobernador Constitucional el C. José Guadalupe Osuna Millán 2007-2013; fue reformado mediante el Dictamen No. 266 de la Comisión de Gobernación, Legislación y\nPuntos Constitucionales, publicado en la Gaceta Parlamentaria del Congreso del Estado en fecha 27 de agosto de 2013, expedido por la H. XX Legislatura, siendo Gobernador\nConstitucional el C. José Guadalupe Osuna Millán 2007-2013; fue reformado mediante\nDecreto No. 19, publicado en el Periódico Oficial No. 52, de fecha 25 de noviembre de 2016, Tomo CXXIII, Sección IV, expedido por la H. XXII Legislatura, siendo Gobernador\nConstitucional el C. Francisco Arturo Vega de Lamadrid 2013-2019; fue reformado por\nDecreto No. 226, publicado en el Periódico Oficial No. 30, de fecha 26 de mayo de 2023, Índice, Tomo CXXX, expedido por la H. XXIV Legislatura, siendo Gobernadora\nConstitucional la C. Marina del Pilar Ávila Olmeda, 2021-2027; fue reformado por Decreto\n2013, expedido por la H. XXIV Legislatura, siendo Gobernadora Constitucional la C. Marina del Pilar Ávila Olmeda, 2021-2027;\nARTICULO 40 BIS. Fue reformado por Decreto No. 145, publicado en el Periódico\nH. XVII Legislatura, siendo Gobernador Constitucional el C. Eugenio Elorduy Walther 20012007; fue modificado por Fe de Erratas, publicado en el Periódico Oficial No. 09, de fecha 21\n.\nActualización Legislativa.\nÚltima reforma Gaceta No. 63, Especial, 14-Ago-2025 de febrero de 2003, Tomo CX, expedido por la H. XVII Legislatura, siendo Gobernador\nConstitucional el C. Eugenio Elorduy Walther 2001-2007; Fue reformado por Decreto No. 2, Publicado en el Periódico Oficial No. 50, de fecha 19 de noviembre de 2004, Sección II, Tomo CXI, expedido por la H. XVIII Legislatura, siendo Gobernador Constitucional el C.\nEugenio Elorduy Walther 2001-2007; Fue reformado por Decreto No. 316, Publicado en el\nPeriódico Oficial No. 57, de fecha 18 de diciembre de 2009, Tomo CXVI, expedido por la H.\nXIX Legislatura, siendo Gobernador Constitucional el C. José Guadalupe Osuna Millán 20072013; fue reformado mediante Decreto No. 19, publicado en el Periódico Oficial No. 52, de fecha 25 de noviembre de 2016, Tomo CXXIII, Sección IV, expedido por la H. XXII\nLegislatura, siendo Gobernador Constitucional el C. Francisco Arturo Vega de Lamadrid\n2013-2019;\nARTÍCULO 40 TER.- Fue adicionado mediante Decreto No. 19, publicado en el\nPeriódico Oficial No. 52, de fecha 25 de noviembre de 2016, Tomo CXXIII, Sección IV, expedido por la H. XXII Legislatura, siendo Gobernador Constitucional el C. Francisco Arturo\nVega de Lamadrid 2013-2019; fue reformado por Decreto No. 331, publicado en el Periódico\nOficial No. 70, de fecha 08 de diciembre de 2023, Sección I, Tomo CXXX, expedido por la H.\nXXIV Legislatura, siendo Gobernadora Constitucional la C. Marina del Pilar Ávila Olmeda\n2021-2027;\nARTICULO 41. Fue reformado mediante sesión de Pleno efectuada el día 02 de octubre de 2010; fue reformado mediante el Dictamen No. 266 de la Comisión de\nGobernación, Legislación y Puntos Constitucionales, publicado en la Gaceta Parlamentaria del Congreso del Estado en fecha 27 de agosto de 2013, expedido por la H. XX Legislatura, siendo Gobernador Constitucional el C. José Guadalupe Osuna Millán 2007-2013;\nARTICULO 42. Fue reformado por Decreto No. 145, publicado en el Periódico Oficial\nNo. 03, de fecha 14 de enero de 2003, Número Especial, Tomo CX, expedido por la H. XVII\nLegislatura, siendo Gobernador Constitucional el C. Eugenio Elorduy Walther 2001-2007;\nFue reformado por Decreto No. 150, publicado en el Periódico Oficial No. 06, de fecha 31 de enero de 2003, Sección II, Tomo CX, expedido por la H. XVII Legislatura, siendo Gobernador\nConstitucional el C. Eugenio Elorduy Walther 2001-2007; fue reformado por Decreto No. 2, Publicado en el Periódico Oficial No. 50, de fecha 19 de noviembre de 2004, Sección II, Tomo CXI, expedido por la H. XVIII Legislatura, siendo Gobernador Constitucional el C.\nEugenio Elorduy Walther 2001-2007; fue reformado mediante sesión de Pleno efectuada el siendo Gobernador Constitucional el C. José Guadalupe Osuna Millán 2007-2013; fue adicionado mediante Decreto No. 294, publicado en el Periódico Oficial No. 54, de fecha 29 siendo Gobernador Constitucional el C. Francisco Arturo Vega de Lamadrid 2013-2019;\n.\nActualización Legislativa.\nÚltima reforma Gaceta No. 63, Especial, 14-Ago-2025\nARTICULO 48. Fue reformado mediante el Dictamen No. 266 de la Comisión de\nGobernación, Legislación y Puntos Constitucionales, publicado en la Gaceta Parlamentaria del Congreso del Estado en fecha 27 de agosto de 2013, expedido por la H. XX Legislatura, siendo Gobernador Constitucional el C. José Guadalupe Osuna Millán 2007-2013;\nARTICULO 50. Fue reformado por Decreto No. 2, Publicado en el Periódico Oficial\nNo. 50, de fecha 19 de noviembre de 2004, Sección II, Tomo CXI, expedido por la H. XVIII\nLegislatura, siendo Gobernador Constitucional el C. Eugenio Elorduy Walther 2001-2007; fue reformado por Decreto No. 315, publicado en el Periódico Oficial No. 9, de fecha 15 de febrero de 2013, Sección I, Tomo CXX, expedido por la Honorable XX Legislatura, siendo\nGobernador Constitucional el C. Lic. José Guadalupe Osuna Millán, 2007-2013; fue reformado por Decreto No. 516, publicado en el Periódico Oficial No. 40, de fecha 13 septiembre de 2013, Tomo CXX, expedido por la H. XX Legislatura, siendo Gobernador\nConstitucional el C. José Guadalupe Osuna Millán 2007-2013;\nARTICULO 53. Fue reformado mediante el Dictamen No. 266 de la Comisión de\nGobernación, Legislación y Puntos Constitucionales, publicado en la Gaceta Parlamentaria del Congreso del Estado en fecha 27 de agosto de 2013, expedido por la H. XX Legislatura, siendo Gobernador Constitucional el C. José Guadalupe Osuna Millán 2007-2013; Fue adicionado mediante Decreto No. 19, publicado en el Periódico Oficial No. 52, de fecha 25 de noviembre de 2016, Tomo CXXIII, Sección IV, expedido por la H. XXII Legislatura, siendo\nGobernador Constitucional el C. Francisco Arturo Vega de Lamadrid 2013-2019;\nARTICULO 53 BIS. Fue reformado mediante sesión de Pleno efectuada el día 02 de octubre de 2010;\nARTICULO 55. Fue reformado por Decreto No. 145, publicado en el Periódico Oficial\nNo. 03, de fecha 14 de enero de 2003, Número Especial, Tomo CX, expedido por la H. XVII\nLegislatura, siendo Gobernador Constitucional el C. Eugenio Elorduy Walther 2001-2007; fue reformado por Decreto No. 2, Publicado en el Periódico Oficial No. 50, de fecha 19 de noviembre de 2004, Sección II, Tomo CXI, expedido por la H. XVIII Legislatura, siendo\nGobernador Constitucional el C. Eugenio Elorduy Walther 2001-2007; fue reformado mediante sesión de Pleno efectuada el día 02 de octubre de 2010; fue reformado por\nDecreto No. 52, publicado en el Periódico Oficial No. 27, de fecha 03 de junio de 2011, Tomo\nCXVIII, Sección I, expedido por la H. XX Legislatura, siendo Gobernador Constitucional el C.\nJosé Guadalupe Osuna Millán 2007-2013; reformado mediante el Dictamen No. 266 de la\nComisión de Gobernación, Legislación y Puntos Constitucionales, publicado en la Gaceta\nXX Legislatura, siendo Gobernador Constitucional el C. José Guadalupe Osuna Millán 20072013;\nARTICULO 56. Fue reformado por Decreto No. 145, publicado en el Periódico Oficial\nLegislatura, siendo Gobernador Constitucional el C. Eugenio Elorduy Walther 2001-2007;\nFue reformado por Decreto No. 150, publicado en el Periódico Oficial No. 06, de fecha 31 de\n.\nActualización Legislativa.\nÚltima reforma Gaceta No. 63, Especial, 14-Ago-2025 enero de 2003, Sección II, Tomo CX, expedido por la H. XVII Legislatura, siendo Gobernador\nConstitucional el C. Eugenio Elorduy Walther 2001-2007; fue reformado por Decreto No. 2, Publicado en el Periódico Oficial No. 50, de fecha 19 de noviembre de 2004, Sección II, Tomo CXI, expedido por la H. XVIII Legislatura, siendo Gobernador Constitucional el C.\nEugenio Elorduy Walther 2001-2007; fue reformado mediante sesión de Pleno efectuada el día 02 de octubre de 2010; fue reformado por Decreto No. 11, publicado en el Periódico\nOficial No. 56, de fecha 17 de diciembre de 2010, Tomo CXVII, Sección III, expedido por la\nH. XX Legislatura, siendo Gobernador Constitucional el C. José Guadalupe Osuna Millán\n2007-2013; fue reformado por Decreto No. 35, publicado en el Periódico Oficial No. 12, de fecha 25 de febrero de 2011, Tomo CXVIII, Sección I, expedido por la H. XX Legislatura, siendo Gobernador Constitucional el C. José Guadalupe Osuna Millán 2007-2013; fue reformado por Decreto No. 259, publicado en el Periódico Oficial No. 38, de fecha 31 de agosto de 2012, Tomo CXIX, Sección I, expedido por la XX Legislatura, siendo Gobernador\nConstitucional el C. Lic. José Guadalupe Osuna Millán 2007-2013; fue reformado mediante el Dictamen No. 266 de la Comisión de Gobernación, Legislación y Puntos Constitucionales, publicado en la Gaceta Parlamentaria del Congreso del Estado en fecha 27 de agosto de\n2013, expedido por la H. XX Legislatura, siendo Gobernador Constitucional el C. José\nGuadalupe Osuna Millán 2007-2013; fue reformado mediante sesión de Pleno efectuada el día 10 de octubre de 2013; fue reformado por Decreto No. 1, publicado en el Periódico\nOficial No. 49, de fecha 04 de noviembre de 2013, Tomo CXX, Sección I, expedido por la H.\nXXI Legislatura, siendo Gobernador Constitucional el C. José Guadalupe Osuna Millán 20072013; fue reformado mediante sesión de Pleno efectuada el día 16 de octubre de 2014; fue reformado mediante Decreto No. 362, publicado en el Periódico Oficial No. 56, de fecha 04 de diciembre de 2015, Tomo CXXII, Sección IV, expedido por la H. XXI Legislatura, siendo\nGobernador Constitucional el C. Francisco Arturo Vega de Lamadrid 2013-2019; fue reformado mediante Decreto No. 373, publicado en el Periódico Oficial No. 58, de fecha 18 de diciembre de 2015, Tomo CXXII, Sección III, expedido por la H. XXI Legislatura, siendo\nGobernador Constitucional el C. Francisco Arturo Vega de Lamadrid 2013-2019; fue reformado mediante Decreto No. 19, publicado en el Periódico Oficial No. 52, de fecha 25 de noviembre de 2016, Tomo CXXIII, Sección IV, expedido por la H. XXII Legislatura, siendo\nGobernador Constitucional el C. Francisco Arturo Vega de Lamadrid 2013-2019; fue reformado mediante Dictamen No. 09 de la Comisión de Gobernación, Legislación y Puntos\nConstitucionales, publicado en la Gaceta Parlamentaria No. 29, de fecha 14 de enero de\n2022, y Decreto No. 68 publicado en el Periódico Oficial No. 7, Número Especial Sección I, Tomo CXXIX, de fecha 25 de enero de 2022, expedido por la H. XXIV Legislatura, siendo\nGobernadora Constitucional la C. Marina del Pilar Ávila Olmeda 2021-2027; fue reformado mediante Dictamen No. 12 de la Comisión de Gobernación, Legislación y Puntos\n2022 y Decreto No. 69 publicado en el Periódico Oficial No. 9, Sección III, Tomo CXXIX, de\nConstitucional la C. Marina del Pilar Ávila Olmeda 2021-2027; fue reformado por Decreto No.\n.\nActualización Legislativa.\nÚltima reforma Gaceta No. 63, Especial, 14-Ago-2025\nC. Marina del Pilar Ávila Olmeda, 2021-2027; fue reformado por Decreto No. 459, publicado en la Gaceta Parlamentaria No. 159 del Congreso del Estado, en fecha 31 de julio de 2014, y en el Periódico Oficial No. 40, Índice, de fecha 16 de agosto de 2024, Tomo CXXXI, expedido por la H. XXIV Legislatura, siendo Gobernadora Constitucional la C. Marina del\nPilar Ávila Olmeda, 2021-2027; fue reformado por Decreto No. 18, mediante la aprobación de los dictámenes 10 y 11 de la Comisión de Gobernación, Legislación y Puntos\nConstitucionales, publicados en la Gaceta Parlamentaria No. 18, de fecha 07 de noviembre de 2024, expedido por la H. XXV Legislatura, siendo Gobernadora Constitucional la C.\nMarina del Pilar Ávila Olmeda, 2021-2027;\nARTICULO 57. Fue reformado por Decreto No. 145, publicado en el Periódico Oficial\nNo. 03, de fecha 14 de enero de 2003, Número Especial, Tomo CX, expedido por la H. XVII\nLegislatura, siendo Gobernador Constitucional el C. Eugenio Elorduy Walther 2001-2007;\nFue reformado por Decreto No. 150, publicado en el Periódico Oficial No. 06, de fecha 31 de enero de 2003, Sección II, Tomo CX, expedido por la H. XVII Legislatura, siendo Gobernador\nConstitucional el C. Eugenio Elorduy Walther 2001-2007; fue reformado por Decreto No. 2, Publicado en el Periódico Oficial No. 50, de fecha 19 de noviembre de 2004, Sección II, Tomo CXI, expedido por la H. XVIII Legislatura, siendo Gobernador Constitucional el C.\nEugenio Elorduy Walther 2001-2007; fue reformado mediante sesión de Pleno efectuada el día 02 de octubre de 2010;\nARTICULO 58. Fue reformado por Decreto No. 145, publicado en el Periódico Oficial\nNo. 03, de fecha 14 de enero de 2003, Número Especial, Tomo CX, expedido por la H. XVII\nLegislatura, siendo Gobernador Constitucional el C. Eugenio Elorduy Walther 2001-2007; fue reformado por Decreto No. 2, Publicado en el Periódico Oficial No. 50, de fecha 19 de noviembre de 2004, Sección II, Tomo CXI, expedido por la H. XVIII Legislatura, siendo\nGobernador Constitucional el C. Eugenio Elorduy Walther 2001-2007; fue derogado mediante sesión de Pleno efectuada el día 02 de octubre de 2010; reformado mediante el\nDictamen No. 266 de la Comisión de Gobernación, Legislación y Puntos Constitucionales, publicado en la Gaceta Parlamentaria del Congreso del Estado en fecha 27 de agosto de\n2013, expedido por la H. XX Legislatura, siendo Gobernador Constitucional el C. José\nGuadalupe Osuna Millán 2007-2013;\nARTICULO 59. Fue reformado por Decreto No. 145, publicado en el Periódico Oficial\nNo. 03, de fecha 14 de enero de 2003, Número Especial, Tomo CX, expedido por la H. XVII\nLegislatura, siendo Gobernador Constitucional el C. Eugenio Elorduy Walther 2001-2007;\nFue reformado por Decreto No. 150, publicado en el Periódico Oficial No. 06, de fecha 31 de\nConstitucional el C. Eugenio Elorduy Walther 2001-2007; fue reformado por Decreto No. 2, Tomo CXI, expedido por la H. XVIII Legislatura, siendo Gobernador Constitucional el C.\nEugenio Elorduy Walther 2001-2007; fue reformado por Decreto No. 42, Publicado en el\nLegislatura, siendo Gobernador Constitucional el C. Eugenio Elorduy Walther 2001-2007; fue\n.\nActualización Legislativa.\nÚltima reforma Gaceta No. 63, Especial, 14-Ago-2025 reformado por Decreto No. 176, publicado en el Periódico Oficial No. 63, de fecha 26 de diciembre de 2008, Tomo CXV, expedido por la H. XIX Legislatura, siendo Gobernador\nConstitucional el C. José Guadalupe Osuna Millan 2007-2013; Fue adicionado por Decreto\nNo. 387, Publicado en el Periódico Oficial No. 29, de fecha 02 de julio de 2010, Tomo CXVII, expedido por la H. XIX Legislatura, siendo Gobernador Constitucional el C. José Guadalupe\nOsuna Millán 2007-2013; fue derogado mediante sesión de Pleno efectuada el día 02 de octubre de 2010; fue reformado mediante el Dictamen No. 266 de la Comisión de\nGobernación, Legislación y Puntos Constitucionales, publicado en la Gaceta Parlamentaria del Congreso del Estado en fecha 27 de agosto de 2013, expedido por la H. XX Legislatura, siendo Gobernador Constitucional el C. José Guadalupe Osuna Millán 2007-2013;\nARTICULO 60. Fue reformado por Decreto No. 150, publicado en el Periódico Oficial\nNo. 06, de fecha 31 de enero de 2003, Sección II, Tomo CX, expedido por la H. XVII\nLegislatura, siendo Gobernador Constitucional el C. Eugenio Elorduy Walther 2001-2007; fue reformado mediante sesión de Pleno efectuada el día 02 de octubre de 2010; fue reformado por Decreto No. 11, publicado en el Periódico Oficial No. 56, de fecha 17 de diciembre de\n2010, Tomo CXVII, Sección III, expedido por la H. XX Legislatura, siendo Gobernador\nConstitucional el C. José Guadalupe Osuna Millán 2007-2013; fue reformado por Decreto\nNo. 35, publicado en el Periódico Oficial No. 12, de fecha 25 de febrero de 2011, Tomo\nCXVIII, Sección I, expedido por la H. XX Legislatura, siendo Gobernador Constitucional el C.\nJosé Guadalupe Osuna Millán 2007-2013; fue reformado por Decreto No. 259, publicado en el Periódico Oficial No. 38, de fecha 31 de agosto de 2012, Tomo CXIX, Sección I, expedido por la XX Legislatura, siendo Gobernador Constitucional el C. Lic. José Guadalupe Osuna\nMillán 2007-2013; fue reformado mediante el Dictamen No. 266 de la Comisión de\nGobernación, Legislación y Puntos Constitucionales, publicado en la Gaceta Parlamentaria del Congreso del Estado en fecha 27 de agosto de 2013, expedido por la H. XX Legislatura, siendo Gobernador Constitucional el C. José Guadalupe Osuna Millán 2007-2013; fue reformado mediante Decreto No. 362, publicado en el Periódico Oficial No. 56, de fecha 04 de diciembre de 2015, Tomo CXXII, Sección IV, expedido por la H. XXI Legislatura, siendo\nGobernador Constitucional el C. Francisco Arturo Vega de Lamadrid 2013-2019; fue reformado mediante Decreto No. 373, publicado en el Periódico Oficial No. 58, de fecha 18 de diciembre de 2015, Tomo CXXII, Sección III, expedido por la H. XXI Legislatura, siendo\nGobernador Constitucional el C. Francisco Arturo Vega de Lamadrid 2013-2019; fue reformado mediante Decreto No. 19, publicado en el Periódico Oficial No. 52, de fecha 25 de noviembre de 2016, Tomo CXXIII, Sección IV, expedido por la H. XXII Legislatura, siendo\nGobernador Constitucional el C. Francisco Arturo Vega de Lamadrid 2013-2019; fue reformado mediante Decreto No. 16, publicado en el Periódico Oficial No. 06, de fecha 06 de\nGobernador Constitucional el C. Francisco Arturo Vega de Lamadrid 2013-2019; fue reformado mediante Dictamen No. 09 de la Comisión de Gobernación, Legislación y Puntos\n2022, y Decreto No. 68 publicado en el Periódico Oficial No. 7, Número Especial Sección I, Gobernadora Constitucional la C. Marina del Pilar Ávila Olmeda 2021-2027; fue reformado\n.\nActualización Legislativa.\nÚltima reforma Gaceta No. 63, Especial, 14-Ago-2025 mediante Dictamen No. 12 de la Comisión de Gobernación, Legislación y Puntos\nConstitucionales, publicado en la Gaceta Parlamentaria No. 30, de fecha 17 de enero de\n2022 y Decreto No. 69 publicado en el Periódico Oficial No. 9, Sección III, Tomo CXXIX, de fecha 04 de febrero de 2022, expedido por la H. XXIV Legislatura, siendo Gobernadora\nConstitucional la C. Marina del Pilar Ávila Olmeda 2021-2027; fue reformado por Decreto No.\n417, en el Periódico Oficial No. 21, Índice, de fecha 26 de abril de 2024, Tomo CXXXI y en la\nGaceta Parlamentaria No. 145 del Congreso del Estado, en fecha 31 de marzo de 2013, expedido por la H. XXIV Legislatura, siendo Gobernadora Constitucional la C. Marina del\nPilar Ávila Olmeda, 2021-2027; fue reformado por Decreto No. 459, publicado en la Gaceta\nParlamentaria No. 159 del Congreso del Estado, en fecha 31 de julio de 2014, y en el\nPeriódico Oficial No. 40, Índice, de fecha 16 de agosto de 2024, Tomo CXXXI, expedido por la H. XXIV Legislatura, siendo Gobernadora Constitucional la C. Marina del Pilar Ávila\nOlmeda, 2021-2027;\nARTICULO 61. Fue reformado por Decreto No. 145, publicado en el Periódico Oficial\nNo. 03, de fecha 14 de enero de 2003, Número Especial, Tomo CX, expedido por la H. XVII\nLegislatura, siendo Gobernador Constitucional el C. Eugenio Elorduy Walther 2001-2007;\nFue reformado por Decreto No. 2, Publicado en el Periódico Oficial No. 50, de fecha 19 de noviembre de 2004, Sección II, Tomo CXI, expedido por la H. XVIII Legislatura, siendo\nGobernador Constitucional el C. Eugenio Elorduy Walther 2001-2007; fue derogado mediante sesión de Pleno efectuada el día 02 de octubre de 2010;\nARTICULO 62. Fue reformado por Decreto No. 150, publicado en el Periódico Oficial\nNo. 06, de fecha 31 de enero de 2003, Sección II, Tomo CX, expedido por la H. XVII\nLegislatura, siendo Gobernador Constitucional el C. Eugenio Elorduy Walther 2001-2007; fue reformado por Decreto No. 2, Publicado en el Periódico Oficial No. 50, de fecha 19 de noviembre de 2004, Sección II, Tomo CXI, expedido por la H. XVIII Legislatura, siendo\nGobernador Constitucional el C. Eugenio Elorduy Walther 2001-2007; fue reformado por\nDecreto No. 176, publicado en el Periódico Oficial No. 63, de fecha 26 de diciembre de 2008, Tomo CXV, expedido por la H. XIX Legislatura, siendo Gobernador Constitucional el C. José\nGuadalupe Osuna Millan 2007-2013; fue reformado mediante sesión de Pleno efectuada el día 02 de octubre de 2010; fue reformado mediante el Dictamen No. 266 de la Comisión de\nGobernación, Legislación y Puntos Constitucionales, publicado en la Gaceta Parlamentaria del Congreso del Estado en fecha 27 de agosto de 2013, expedido por la H. XX Legislatura, siendo Gobernador Constitucional el C. José Guadalupe Osuna Millán 2007-2013; fue reformado mediante Decreto No. 359, publicado en el Periódico Oficial No. 53, de fecha 20\nGobernador Constitucional el C. Francisco Arturo Vega de Lamadrid 2013-2019; fue reformado mediante Decreto No. 19, publicado en el Periódico Oficial No. 52, de fecha 25 de\nGobernador Constitucional el C. Francisco Arturo Vega de Lamadrid 2013-2019;\nARTICULO 63. Fue reformado mediante sesión de Pleno efectuada el día 02 de\n.\nActualización Legislativa.\nÚltima reforma Gaceta No. 63, Especial, 14-Ago-2025\nGobernación, Legislación y Puntos Constitucionales, publicado en la Gaceta Parlamentaria del Congreso del Estado en fecha 27 de agosto de 2013, expedido por la H. XX Legislatura, siendo Gobernador Constitucional el C. José Guadalupe Osuna Millán 2007-2013; fue reformado mediante Decreto No. 19, publicado en el Periódico Oficial No. 52, de fecha 25 de noviembre de 2016, Tomo CXXIII, Sección IV, expedido por la H. XXII Legislatura, siendo\nGobernador Constitucional el C. Francisco Arturo Vega de Lamadrid 2013-2019;\nARTICULO 64. Fue derogado por Decreto No. 145, publicado en el Periódico Oficial\nNo. 03, de fecha 14 de enero de 2003, Número Especial, Tomo CX, expedido por la H. XVII\nLegislatura, siendo Gobernador Constitucional el C. Eugenio Elorduy Walther 2001-2007; fue reformado por Decreto No. 2, Publicado en el Periódico Oficial No. 50, de fecha 19 de noviembre de 2004, Sección II, Tomo CXI, expedido por la H. XVIII Legislatura, siendo\nGobernador Constitucional el C. Eugenio Elorduy Walther 2001-2007; fue reformado mediante sesión de Pleno efectuada el día 02 de octubre de 2010; fue reformado mediante el Dictamen No. 266 de la Comisión de Gobernación, Legislación y Puntos Constitucionales, publicado en la Gaceta Parlamentaria del Congreso del Estado en fecha 27 de agosto de\n2013, expedido por la H. XX Legislatura, siendo Gobernador Constitucional el C. José\nGuadalupe Osuna Millán 2007-2013; fue reformado mediante sesión de Pleno efectuada el día 10 de octubre de 2013; fue reformado por Decreto No. 1, publicado en el Periódico\nOficial No. 49, de fecha 04 de noviembre de 2013, Tomo CXX, Sección I, expedido por la H.\nXXI Legislatura, siendo Gobernador Constitucional el C. José Guadalupe Osuna Millán 20072013; fue reformado mediante Decreto No. 19, publicado en el Periódico Oficial No. 52, de fecha 25 de noviembre de 2016, Tomo CXXIII, Sección IV, expedido por la H. XXII\nLegislatura, siendo Gobernador Constitucional el C. Francisco Arturo Vega de Lamadrid\n2013-2019;\nARTICULO 65. Fue reformado por Decreto No. 145, publicado en el Periódico Oficial\nNo. 03, de fecha 14 de enero de 2003, Número Especial, Tomo CX, expedido por la H. XVII\nLegislatura, siendo Gobernador Constitucional el C. Eugenio Elorduy Walther 2001-2007;\nFue reformado por Decreto No. 150, publicado en el Periódico Oficial No. 06, de fecha 31 de enero de 2003, Sección II, Tomo CX, expedido por la H. XVII Legislatura, siendo Gobernador\nConstitucional el C. Eugenio Elorduy Walther 2001-2007; fue reformado por Decreto No. 2, Publicado en el Periódico Oficial No. 50, de fecha 19 de noviembre de 2004, Sección II, Tomo CXI, expedido por la H. XVIII Legislatura, siendo Gobernador Constitucional el C.\nEugenio Elorduy Walther 2001-2007; fue reformado mediante sesión de Pleno efectuada el\nH. XX Legislatura, siendo Gobernador Constitucional el C. José Guadalupe Osuna Millán\n2007-2013; fue reformado por Decreto No. 172, publicado en el Periódico Oficial No. 8, de siendo Gobernador Constitucional el C. José Guadalupe Osuna Millán 2007-2013; fue mediante Decreto No. 19, publicado en el Periódico Oficial No. 52, de fecha 25 de noviembre de 2016, Tomo CXXIII, Sección IV, expedido por la H. XXII Legislatura, siendo Gobernador\n.\nActualización Legislativa.\nÚltima reforma Gaceta No. 63, Especial, 14-Ago-2025\nConstitucional el C. Francisco Arturo Vega de Lamadrid 2013-2019; fue reformado por\nDecreto No. 310, publicado en el Periódico Oficial No. 62, de fecha 06 de noviembre de\n2023, Sección I, Tomo CXXX, expedido por la H. XXIV Legislatura, siendo Gobernadora\nConstitucional la C. Marina del Pilar Ávila Olmeda 2021-2027;\nARTICULO 66. Fue reformado por Decreto No. 145, publicado en el Periódico Oficial\nNo. 03, de fecha 14 de enero de 2003, Número Especial, Tomo CX, expedido por la H. XVII\nLegislatura, siendo Gobernador Constitucional el C. Eugenio Elorduy Walther 2001-2007;\nFue derogado por Decreto No. 150, publicado en el Periódico Oficial No. 06, de fecha 31 de enero de 2003, Sección II, Tomo CX, expedido por la H. XVII Legislatura, siendo Gobernador\nConstitucional el C. Eugenio Elorduy Walther 2001-2007; fue reformado por Decreto No. 2, Publicado en el Periódico Oficial No. 50, de fecha 19 de noviembre de 2004, Sección II, Tomo CXI, expedido por la H. XVIII Legislatura, siendo Gobernador Constitucional el C.\nEugenio Elorduy Walther 2001-2007; fue reformado mediante sesión de Pleno efectuada el día 02 de octubre de 2010; fue reformado por Decreto No. 172, publicado en el Periódico\nOficial No. 8, de fecha 10 de febrero de 2012, Tomo CXIX, Sección I, expedido por la H. XX\nLegislatura, siendo Gobernador Constitucional el C. José Guadalupe Osuna Millán 20072013; fue reformado mediante el Dictamen No. 266 de la Comisión de Gobernación, Legislación y Puntos Constitucionales, publicado en la Gaceta Parlamentaria del Congreso del Estado en fecha 27 de agosto de 2013, expedido por la H. XX Legislatura, siendo\nGobernador Constitucional el C. José Guadalupe Osuna Millán 2007-2013; fue reformado mediante Decreto No. 539, publicado en el Periódico Oficial No. 40, de fecha 02 de septiembre de 2016, Tomo CXXIII, Sección I, expedido por la H. XXI Legislatura, siendo\nGobernador Constitucional el C. Francisco Arturo Vega de Lamadrid 2013-2019; fue reformado mediante Decreto No. 19, publicado en el Periódico Oficial No. 52, de fecha 25 de noviembre de 2016, Tomo CXXIII, Sección IV, expedido por la H. XXII Legislatura, siendo\nGobernador Constitucional el C. Francisco Arturo Vega de Lamadrid 2013-2019; fue reformado por Decreto No. 310, publicado en el Periódico Oficial No. 62, de fecha 06 de noviembre de 2023, Sección I, Tomo CXXX, expedido por la H. XXIV Legislatura, siendo\nGobernadora Constitucional la C. Marina del Pilar Ávila Olmeda 2021-2027;\nARTICULO 67. Fue derogado por Decreto No. 145, publicado en el Periódico Oficial\nNo. 03, de fecha 14 de enero de 2003, Número Especial, Tomo CX, expedido por la H. XVII\nLegislatura, siendo Gobernador Constitucional el C. Eugenio Elorduy Walther 2001-2007; fue reformado por Decreto No. 2, Publicado en el Periódico Oficial No. 50, de fecha 19 de\nGobernador Constitucional el C. Eugenio Elorduy Walther 2001-2007; fue reformado el Dictamen No. 266 de la Comisión de Gobernación, Legislación y Puntos Constitucionales, 2013, expedido por la H. XX Legislatura, siendo Gobernador Constitucional el C. José\nGuadalupe Osuna Millán 2007-2013; fue reformado mediante Decreto No. 19, publicado en expedido por la H. XXII Legislatura, siendo Gobernador Constitucional el C. Francisco Arturo\n.\nActualización Legislativa.\nÚltima reforma Gaceta No. 63, Especial, 14-Ago-2025\nVega de Lamadrid 2013-2019; fue reformado por Decreto No. 331, publicado en el Periódico\nOficial No. 70, de fecha 08 de diciembre de 2023, Sección I, Tomo CXXX, expedido por la H.\nXXIV Legislatura, siendo Gobernadora Constitucional la C. Marina del Pilar Ávila Olmeda\n2021-2027;\nARTICULO 67 BIS. Fue adicionado por Decreto No. 145, publicado en el Periódico\nOficial No. 03, de fecha 14 de enero de 2003, Número Especial, Tomo CX, expedido por la\nH. XVII Legislatura, siendo Gobernador Constitucional el C. Eugenio Elorduy Walther 20012007; Fue reformado por Decreto No. 150, publicado en el Periódico Oficial No. 06, de fecha\n31 de enero de 2003, Sección II, Tomo CX, expedido por la H. XVII Legislatura, siendo\nGobernador Constitucional el C. Eugenio Elorduy Walther 2001-2007; fue derogado por\nDecreto No. 2, Publicado en el Periódico Oficial No. 50, de fecha 19 de noviembre de 2004,\nSección II, Tomo CXI, expedido por la H. XVIII Legislatura, siendo Gobernador\nConstitucional el C. Eugenio Elorduy Walther 2001-2007; fue reformado mediante sesión de\nPleno efectuada el día 27 de agosto de 2013;\nARTICULO 67 TER. Fue adicionado por Decreto No. 145, publicado en el Periódico\nOficial No. 03, de fecha 14 de enero de 2003, Número Especial, Tomo CX, expedido por la\nH. XVII Legislatura, siendo Gobernador Constitucional el C. Eugenio Elorduy Walther 20012007; Fue reformado por Decreto No. 150, publicado en el Periódico Oficial No. 06, de fecha\n31 de enero de 2003, Sección II, Tomo CX, expedido por la H. XVII Legislatura, siendo\nGobernador Constitucional el C. Eugenio Elorduy Walther 2001-2007; fue modificado por Fe de Erratas, publicado en el Periódico Oficial No. 09, de fecha 21 de febrero de 2003, Tomo\nCX, expedido por la H. XVII Legislatura, siendo Gobernador Constitucional el C. Eugenio\nElorduy Walther 2001-2007; fue derogado por Decreto No. 2, Publicado en el Periódico\nOficial No. 50, de fecha 19 de noviembre de 2004, Sección II, Tomo CXI, expedido por la H.\nXVIII Legislatura, siendo Gobernador Constitucional el C. Eugenio Elorduy Walther 20012007;\nARTICULO 69. Fue reformado mediante sesión de Pleno efectuada el día 02 de octubre de 2010; fue reformado mediante el Dictamen No. 266 de la Comisión de\nGobernación, Legislación y Puntos Constitucionales, publicado en la Gaceta Parlamentaria del Congreso del Estado en fecha 27 de agosto de 2013, expedido por la H. XX Legislatura, siendo Gobernador Constitucional el C. José Guadalupe Osuna Millán 2007-2013;\nARTICULO 72. Fue reformado mediante sesión de Pleno efectuada el día 02 de siendo Gobernador Constitucional el C. José Guadalupe Osuna Millán 2007-2013;\nARTICULO 73. Fue reformado por Decreto No. 37, publicado en el Periódico Oficial siendo Gobernador Constitucional el C. Francisco Arturo Vega de Lamadrid 2013-2019;\n.\nActualización Legislativa.\nÚltima reforma Gaceta No. 63, Especial, 14-Ago-2025\nARTICULO 74. Fue reformado por Decreto No. 79, publicado en el Periódico Oficial\nNo. 34, de fecha 15 de julio de 2011, Tomo CXVIII, Sección I, expedido por la H. XX\nLegislatura, siendo Gobernador Constitucional el C. José Guadalupe Osuna Millán 20072013;\nCAPITULO III\nDE LOS ORGANOS DE APOYO PARLAMENTARIO Y\nADMINISTRATIVO\nSECCION I\nDE LA SECRETARÍA DE SERVICIOS ADMINISTRATIVOS\nFue modificado este Capítulo mediante Decreto No. 19, publicado en el Periódico Oficial No.\n52, de fecha 25 de noviembre de 2016, Tomo CXXIII, Sección IV, expedido por la H. XXI\nLegislatura, siendo Gobernador Constitucional el C. Francisco Arturo Vega de Lamadrid\n2013-2019;\nCAPÍTULO III\nDE LOS ORGANOS TÉCNICOS Y ADMINISTRATIVOS\nSECCIÓN I\nDISPOSICIONES GENERALES\nARTICULO 76. Fue reformado por Decreto No. 145, publicado en el Periódico Oficial\nNo. 03, de fecha 14 de enero de 2003, Número Especial, Tomo CX, expedido por la H. XVII\nLegislatura, siendo Gobernador Constitucional el C. Eugenio Elorduy Walther 2001-2007; fue reformado mediante sesión de Pleno efectuada el día 02 de octubre de 2010; fue reformado mediante Decreto No. 19, publicado en el Periódico Oficial No. 52, de fecha 25 de noviembre de 2016, Tomo CXXIII, Sección IV, expedido por la H. XXII Legislatura, siendo Gobernador\nConstitucional el C. Francisco Arturo Vega de Lamadrid 2013-2019; fue reformado por\nDecreto No. 417, en el Periódico Oficial No. 21, Índice, de fecha 26 de abril de 2024, Tomo\nCXXXI y en la Gaceta Parlamentaria No. 145 del Congreso del Estado, en fecha 31 de marzo de 2013, expedido por la H. XXIV Legislatura, siendo Gobernadora Constitucional la\nC. Marina del Pilar Ávila Olmeda, 2021-2027;\nARTÍCULO 76 BIS.- Fue adicionado mediante Decreto No. 19, publicado en el expedido por la H. XXII Legislatura, siendo Gobernador Constitucional el C. Francisco Arturo\nVega de Lamadrid 2013-2019;\nFue adicionada esta Sección mediante Decreto No. 19, publicado en el Periódico Oficial No.\nLegislatura, siendo Gobernador Constitucional el C. Francisco Arturo Vega de Lamadrid\n2013-2019;\nSECCIÓN II\n.\nActualización Legislativa.\nÚltima reforma Gaceta No. 63, Especial, 14-Ago-2025\nDE LA DIRECCIÓN DE ADMINISTRACIÓN\nARTICULO 77. Fue reformado por Decreto No. 145, publicado en el Periódico Oficial\nNo. 03, de fecha 14 de enero de 2003, Número Especial, Tomo CX, expedido por la H. XVII\nLegislatura, siendo Gobernador Constitucional el C. Eugenio Elorduy Walther 2001-2007; fue modificado por Fe de Erratas, publicado en el Periódico Oficial No. 09, de fecha 21 de febrero de 2003, Tomo CX, expedido por la H. XVII Legislatura, siendo Gobernador\nConstitucional el C. Eugenio Elorduy Walther 2001-2007; fue reformado por Decreto No. 2, Publicado en el Periódico Oficial No. 50, de fecha 19 de noviembre de 2004, Sección II, Tomo CXI, expedido por la H. XVIII Legislatura, siendo Gobernador Constitucional el C.\nEugenio Elorduy Walther 2001-2007; fue reformado mediante sesión de Pleno efectuada el día 02 de octubre de 2010; fue reformado por Decreto No. 177, publicado en el Periódico\nOficial No. 10, de fecha 24 de Febrero de 2012, Tomo CXIX, Sección I, expedido por la XX\nLegislatura, siendo Gobernador Constitucional del Estado el C. Lic. José Guadalupe Osuna\nMillán 2007-2013; fue reformado por Decreto No. 251, publicado en el Periódico Oficial No.\n38, de fecha 31 de agosto de 2012, Tomo CXIX, Sección I, expedido por la XIX Legislatura, siendo Gobernador Constitucional el C. Lic. José Guadalupe Osuna Millán 2007-2013; fue reformado mediante el Dictamen No. 266 de la Comisión de Gobernación, Legislación y\nPuntos Constitucionales, publicado en la Gaceta Parlamentaria del Congreso del Estado en fecha 27 de agosto de 2013, expedido por la H. XX Legislatura, siendo Gobernador\nConstitucional el C. José Guadalupe Osuna Millán 2007-2013; fue reformado mediante\nDecreto No. 358, publicado en el Periódico Oficial No. 53, de fecha 20 de noviembre de\n2015, Tomo CXXII, Sección I, expedido por la H. XXI Legislatura, siendo Gobernador\nConstitucional el C. Francisco Arturo Vega de Lamadrid 2013-2019; fue reformado mediante\nDecreto No. 19, publicado en el Periódico Oficial No. 52, de fecha 25 de noviembre de 2016, Tomo CXXIII, Sección IV, expedido por la H. XXII Legislatura, siendo Gobernador\nConstitucional el C. Francisco Arturo Vega de Lamadrid 2013-2019;\nARTICULO 77 BIS. Fue reformado mediante sesión de Pleno efectuada el día 02 de octubre de 2010; fue reformado mediante el Dictamen No. 266 de la Comisión de\nGobernación, Legislación y Puntos Constitucionales, publicado en la Gaceta Parlamentaria del Congreso del Estado en fecha 27 de agosto de 2013, expedido por la H. XX Legislatura, siendo Gobernador Constitucional el C. José Guadalupe Osuna Millán 2007-2013; fue reformado mediante Decreto No. 19, publicado en el Periódico Oficial No. 52, de fecha 25 de\nGobernador Constitucional el C. Francisco Arturo Vega de Lamadrid 2013-2019; fue reformado mediante Decreto No. 144, publicado en el Periódico Oficial No. 50, de fecha 10\nGobernador Constitucional el C. Francisco Arturo Vega de Lamadrid 2013-2019; fue siendo Gobernador Constitucional el C. Jaime Bonilla Valdez 2019-2021;\n.\nActualización Legislativa.\nÚltima reforma Gaceta No. 63, Especial, 14-Ago-2025\nFue adicionada esta Sección mediante Decreto No. 19, publicado en el Periódico Oficial No.\n52, de fecha 25 de noviembre de 2016, Tomo CXXIII, Sección IV, expedido por la H. XXI\nLegislatura, siendo Gobernador Constitucional el C. Francisco Arturo Vega de Lamadrid\n2013-2019;\nSECCIÓN III\nDIRECCIÓN DE PROCESOS PARLAMENTARIOS\nARTICULO 77 TER. Fue reformado mediante sesión de Pleno efectuada el día 02 de octubre de 2010; fue reformado mediante el Dictamen No. 266 de la Comisión de\nGobernación, Legislación y Puntos Constitucionales, publicado en la Gaceta Parlamentaria del Congreso del Estado en fecha 27 de agosto de 2013, expedido por la H. XX Legislatura, siendo Gobernador Constitucional el C. José Guadalupe Osuna Millán 2007-2013; fue reformado mediante Decreto No. 19, publicado en el Periódico Oficial No. 52, de fecha 25 de noviembre de 2016, Tomo CXXIII, Sección IV, expedido por la H. XXII Legislatura, siendo\nGobernador Constitucional el C. Francisco Arturo Vega de Lamadrid 2013-2019;\nARTICULO 77 QUARTER.- Fue adicionado mediante Decreto No. 19, publicado en el\nPeriódico Oficial No. 52, de fecha 25 de noviembre de 2016, Tomo CXXIII, Sección IV, expedido por la H. XXII Legislatura, siendo Gobernador Constitucional el C. Francisco Arturo\nVega de Lamadrid 2013-2019; fue reformado mediante Iniciativa, publicado en la Gaceta\nParlamentaria No. 111, de fecha 19 de mayo de 2021, Especial, expedido por la H. XXII\nLegislatura, siendo Gobernador Constitucional el C. Jaime Bonilla Valdez 2019-2021; fue reformado mediante Iniciativa, publicado en la Gaceta Parlamentaria No. 111, de fecha 19 de mayo de 2021, Especial; y Decreto No. 239 publicado en el Periódico Oficial No. 49, de fecha 09 de julio de 2021, Tomo CXXVIII, Sección IV expedido por la H. XXIII Legislatura, siendo Gobernador Constitucional el C. Jaime Bonilla Valdez 2019-2021;\nARTÍCULO 77 QUINQUIES.- Fue adicionado mediante Iniciativa, publicado en la\nGaceta Parlamentaria No. 111, de fecha 19 de mayo de 2021, Especial; y Decreto No. 239\nSección IV expedido por la H. XXIII Legislatura, siendo Gobernador Constitucional el C.\nJaime Bonilla Valdez 2019-2021;\nFue adicionada esta Sección mediante Decreto No. 19, publicado en el Periódico Oficial No.\nLegislatura, siendo Gobernador Constitucional el C. Francisco Arturo Vega de Lamadrid\n2013-2019;\nSECCIÓN IV\nDE LA DIRECCIÓN DE CONTABILIDAD Y FINANZAS\n.\nActualización Legislativa.\nÚltima reforma Gaceta No. 63, Especial, 14-Ago-2025\nARTICULO 78. Fue derogado por Decreto No. 2, Publicado en el Periódico Oficial No.\n50, de fecha 19 de noviembre de 2004, Sección II, Tomo CXI, expedido por la H. XVIII\nLegislatura, siendo Gobernador Constitucional el C. Eugenio Elorduy Walther 2001-2007; fue reformado mediante Decreto No. 19, publicado en el Periódico Oficial No. 52, de fecha 25 de noviembre de 2016, Tomo CXXIII, Sección IV, expedido por la H. XXII Legislatura, siendo\nGobernador Constitucional el C. Francisco Arturo Vega de Lamadrid 2013-2019;\nARTICULO 79. Fue reformado por Decreto No. 145, publicado en el Periódico Oficial\nNo. 03, de fecha 14 de enero de 2003, Número Especial, Tomo CX, expedido por la H. XVII\nLegislatura, siendo Gobernador Constitucional el C. Eugenio Elorduy Walther 2001-2007; fue derogado por Decreto No. 2, Publicado en el Periódico Oficial No. 50, de fecha 19 de noviembre de 2004, Sección II, Tomo CXI, expedido por la H. XVIII Legislatura, siendo\nGobernador Constitucional el C. Eugenio Elorduy Walther 2001-2007; fue reformado mediante Decreto No. 19, publicado en el Periódico Oficial No. 52, de fecha 25 de noviembre de 2016, Tomo CXXIII, Sección IV, expedido por la H. XXII Legislatura, siendo Gobernador\nConstitucional el C. Francisco Arturo Vega de Lamadrid 2013-2019;\nFue adicionada esta Sección mediante Decreto No. 19, publicado en el Periódico\nOficial No. 52, de fecha 25 de noviembre de 2016, Tomo CXXIII, Sección IV, expedido por la\nH. XXI Legislatura, siendo Gobernador Constitucional el C. Francisco Arturo Vega de\nLamadrid 2013-2019;\nSECCION V\nDE LA DIRECCIÓN DE CONSULTORÍA LEGISLATIVA\nARTICULO 80. Fue reformado por Decreto No. 2, Publicado en el Periódico Oficial\nNo. 50, de fecha 19 de noviembre de 2004, Sección II, Tomo CXI, expedido por la H. XVIII\nLegislatura, siendo Gobernador Constitucional el C. Eugenio Elorduy Walther 2001-2007; fue reformado mediante sesión de Pleno efectuada el día 02 de octubre de 2010; fue reformado mediante el Dictamen No. 266 de la Comisión de Gobernación, Legislación y Puntos\nConstitucionales, publicado en la Gaceta Parlamentaria del Congreso del Estado en fecha el C. José Guadalupe Osuna Millán 2007-2013; fue reformado mediante Decreto No. 19,\nSección IV, expedido por la H. XXII Legislatura, siendo Gobernador Constitucional el C.\nFrancisco Arturo Vega de Lamadrid 2013-2019;\nARTICULO 80 BIS.- Fue adicionado mediante Decreto No. 19, publicado en el expedido por la H. XXII Legislatura, siendo Gobernador Constitucional el C. Francisco Arturo\nVega de Lamadrid 2013-2019;\n.\nActualización Legislativa.\nÚltima reforma Gaceta No. 63, Especial, 14-Ago-2025\nFue adicionada esta Sección mediante Decreto No. 19, publicado en el Periódico\nOficial No. 52, de fecha 25 de noviembre de 2016, Tomo CXXIII, Sección IV, expedido por la\nH. XXI Legislatura, siendo Gobernador Constitucional el C. Francisco Arturo Vega de\nLamadrid 2013-2019;\nSECCIÓN VI\nDE LA UNIDAD DE CONTRALORÍA INTERNA\nARTICULO 81. Fue reformado por Decreto No. 145, publicado en el Periódico Oficial\nNo. 03, de fecha 14 de enero de 2003, Número Especial, Tomo CX, expedido por la H. XVII\nLegislatura, siendo Gobernador Constitucional el C. Eugenio Elorduy Walther 2001-2007;\nFue reformado por Decreto No. 150, publicado en el Periódico Oficial No. 06, de fecha 31 de enero de 2003, Sección II, Tomo CX, expedido por la H. XVII Legislatura, siendo Gobernador\nConstitucional el C. Eugenio Elorduy Walther 2001-2007; fue reformado por Decreto No. 2, Publicado en el Periódico Oficial No. 50, de fecha 19 de noviembre de 2004, Sección II, Tomo CXI, expedido por la H. XVIII Legislatura, siendo Gobernador Constitucional el C.\nEugenio Elorduy Walther 2001-2007; fue reformado mediante sesión de Pleno efectuada el día 02 de octubre de 2010; fue reformado por Decreto No. 310, publicado en el Periódico\nOficial No. 62, de fecha 06 de noviembre de 2023, Sección I, Tomo CXXX, expedido por la\nH. XXIV Legislatura, siendo Gobernadora Constitucional la C. Marina del Pilar Ávila Olmeda\n2021-2027;\nARTICULO 81 BIS. Fue derogado por Decreto No. 2, Publicado en el Periódico Oficial\nNo. 50, de fecha 19 de noviembre de 2004, Sección II, Tomo CXI, expedido por la H. XVIII\nLegislatura, siendo Gobernador Constitucional el C. Eugenio Elorduy Walther 2001-2007; fue reformado por Decreto No. 310, publicado en el Periódico Oficial No. 62, de fecha 06 de noviembre de 2023, Sección I, Tomo CXXX, expedido por la H. XXIV Legislatura, siendo\nGobernadora Constitucional la C. Marina del Pilar Ávila Olmeda 2021-2027;\nARTICULO 81 TER. Fue derogado por Decreto No. 2, Publicado en el Periódico\nOficial No. 50, de fecha 19 de noviembre de 2004, Sección II, Tomo CXI, expedido por la H.\nXVIII Legislatura, siendo Gobernador Constitucional el C. Eugenio Elorduy Walther 20012007; fue reformado mediante Decreto No. 19, publicado en el Periódico Oficial No. 52, de fecha 25 de noviembre de 2016, Tomo CXXIII, Sección IV, expedido por la H. XXII\nLegislatura, siendo Gobernador Constitucional el C. Francisco Arturo Vega de Lamadrid\n2013-2019; fue reformado por Decreto No. 310, publicado en el Periódico Oficial No. 62, de\nLegislatura, siendo Gobernadora Constitucional la C. Marina del Pilar Ávila Olmeda 20212027;\nARTICULO 81 QUARTER. Fue derogado por Decreto No. 2, Publicado en el por la H. XVIII Legislatura, siendo Gobernador Constitucional el C. Eugenio Elorduy Walther\n2001-2007;\n.\nActualización Legislativa.\nÚltima reforma Gaceta No. 63, Especial, 14-Ago-2025\nFue adicionada esta Sección mediante Decreto No. 19, publicado en el Periódico Oficial No.\n52, de fecha 25 de noviembre de 2016, Tomo CXXIII, Sección IV, expedido por la H. XXI\nLegislatura, siendo Gobernador Constitucional el C. Francisco Arturo Vega de Lamadrid\n2013-2019;\nSECCIÓN VII\nUNIDAD DE ASUNTOS JURÍDICOS\nARTICULO 82. Fue reformado por Decreto No. 2, Publicado en el Periódico Oficial\nNo. 50, de fecha 19 de noviembre de 2004, Sección II, Tomo CXI, expedido por la H. XVIII\nLegislatura, siendo Gobernador Constitucional el C. Eugenio Elorduy Walther 2001-2007; fue reformado mediante sesión de Pleno efectuada el día 02 de octubre de 2010; fue reformado mediante el Dictamen No. 266 de la Comisión de Gobernación, Legislación y Puntos\nConstitucionales, publicado en la Gaceta Parlamentaria del Congreso del Estado en fecha\n27 de agosto de 2013, expedido por la H. XX Legislatura, siendo Gobernador Constitucional el C. José Guadalupe Osuna Millán 2007-2013; fue reformado mediante Decreto No. 19, publicado en el Periódico Oficial No. 52, de fecha 25 de noviembre de 2016, Tomo CXXIII,\nSección IV, expedido por la H. XXII Legislatura, siendo Gobernador Constitucional el C.\nFrancisco Arturo Vega de Lamadrid 2013-2019;\nARTÍCULO 82 BIS.- fue reformado mediante Decreto No. 19, publicado en el\nPeriódico Oficial No. 52, de fecha 25 de noviembre de 2016, Tomo CXXIII, Sección IV, expedido por la H. XXII Legislatura, siendo Gobernador Constitucional el C. Francisco Arturo\nVega de Lamadrid 2013-2019;\nFue derogada esta Sección mediante Decreto No. 44, publicado en el Periódico Oficial No.\n06, de fecha 06 de enero de 2017, Tomo CXXIV, Sección IV, expedido por la H. XXII\nLegislatura, siendo Gobernador Constitucional el C. Francisco Arturo Vega de Lamadrid\n2013-2019;\nSECCION IV\nDE LA DIRECCIÓN GENERAL DE ASUNTOS JURÍDICOS\nARTICULO 83. Fue reformado por Decreto No. 145, publicado en el Periódico Oficial\nLegislatura, siendo Gobernador Constitucional el C. Eugenio Elorduy Walther 2001-2007; fue reformado por Decreto No. 2, Publicado en el Periódico Oficial No. 50, de fecha 19 de\nGobernador Constitucional el C. Eugenio Elorduy Walther 2001-2007; fue reformado el Dictamen No. 266 de la Comisión de Gobernación, Legislación y Puntos Constitucionales,.\nActualización Legislativa.\nÚltima reforma Gaceta No. 63, Especial, 14-Ago-2025\n2013, expedido por la H. XX Legislatura, siendo Gobernador Constitucional el C. José\nGuadalupe Osuna Millán 2007-2013; fue derogado mediante Decreto No. 44, publicado en el\nPeriódico Oficial No. 06, de fecha 06 de enero de 2017, Tomo CXXIV, Sección I, expedido por la H. XXII Legislatura, siendo Gobernador Constitucional el C. Francisco Arturo Vega de\nLamadrid 2013-2019;\nFue adicionada esta Sección mediante Decreto No. 19, publicado en el Periódico Oficial No.\n52, de fecha 25 de noviembre de 2016, Tomo CXXIII, Sección I, expedido por la H. XXI\nLegislatura, siendo Gobernador Constitucional el C. Francisco Arturo Vega de Lamadrid\n2013-2019;\nSECCIÓN VIII\nUNIDAD DE COMUNICACIÓN SOCIAL\nARTICULO 83 BIS. Fue adicionado por Decreto No. 145, publicado en el Periódico\nOficial No. 03, de fecha 14 de enero de 2003, Número Especial, Tomo CX, expedido por la\nH. XVII Legislatura, siendo Gobernador Constitucional el C. Eugenio Elorduy Walther 20012007; fue reformado mediante el Dictamen No. 266 de la Comisión de Gobernación, Legislación y Puntos Constitucionales, publicado en la Gaceta Parlamentaria del Congreso del Estado en fecha 27 de agosto de 2013, expedido por la H. XX Legislatura, siendo\nGobernador Constitucional el C. José Guadalupe Osuna Millán 2007-2013; fue reformado mediante Decreto No. 19, publicado en el Periódico Oficial No. 52, de fecha 25 de noviembre de 2016, Tomo CXXIII, Sección IV, expedido por la H. XXII Legislatura, siendo Gobernador\nConstitucional el C. Francisco Arturo Vega de Lamadrid 2013-2019;\nARTICULO 83 TER. Fue adicionado por Decreto No. 145, publicado en el Periódico\nOficial No. 03, de fecha 14 de enero de 2003, Número Especial, Tomo CX, expedido por la\nH. XVII Legislatura, siendo Gobernador Constitucional el C. Eugenio Elorduy Walther 20012007; fue reformado por Decreto No. 2, Publicado en el Periódico Oficial No. 50, de fecha 19 de noviembre de 2004, Sección II, Tomo CXI, expedido por la H. XVIII Legislatura, siendo\nGobernador Constitucional el C. Eugenio Elorduy Walther 2001-2007; fue reformado mediante sesión de Pleno efectuada el día 02 de octubre de 2010; fue reformado mediante el Dictamen No. 266 de la Comisión de Gobernación, Legislación y Puntos Constitucionales, 2013, expedido por la H. XX Legislatura, siendo Gobernador Constitucional el C. José\nGuadalupe Osuna Millán 2007-2013; fue reformado mediante Decreto No. 19, publicado en expedido por la H. XXII Legislatura, siendo Gobernador Constitucional el C. Francisco Arturo\nVega de Lamadrid 2013-2019;\nFue adicionada esta Sección mediante Decreto No. 19, publicado en el Periódico Oficial No.\n.\nActualización Legislativa.\nÚltima reforma Gaceta No. 63, Especial, 14-Ago-2025\nLegislatura, siendo Gobernador Constitucional el C. Francisco Arturo Vega de Lamadrid\n2013-2019;\nSECCION VI\nDE LA DIRECCION DE COMUNICACIÓN SOCIAL\nARTICULO 83 QUARTER. Fue adicionado por Decreto No. 145, publicado en el\nPeriódico Oficial No. 03, de fecha 14 de enero de 2003, Tomo CX, Número Especial, expedido por la H. XVII Legislatura, siendo Gobernador Constitucional el C. Eugenio Elorduy\nWalther 2001-2007; fue reformado mediante sesión de Pleno efectuada el día 02 de octubre de 2010; fue reformado por Decreto No. 11, publicado en el Periódico Oficial No. 56, de fecha 17 de diciembre de 2010, Tomo CXVII, Sección III, expedido por la H. XX Legislatura, siendo Gobernador Constitucional el C. José Guadalupe Osuna Millán 2007-2013; fue derogado mediante Decreto No. 19, publicado en el Periódico Oficial No. 52, de fecha 25 de noviembre de 2016, Tomo CXXIII, Sección IV, expedido por la H. XXII Legislatura, siendo\nGobernador Constitucional el C. Francisco Arturo Vega de Lamadrid 2013-2019;\nARTICULO 83 QUINQUIES. Fue Adicionado por Decreto No. 145, publicado en el\nPeriódico Oficial No. 03 de fecha 14 de enero de 2003, Tomo CX, Número Especial, expedido por la H. XVII Legislatura, siendo Gobernador Constitucional el C. Eugenio Elorduy\nWalther 2001-2007; fue reformado por Decreto No. 2, Publicado en el Periódico Oficial No.\n50, de fecha 19 de noviembre de 2004, Sección II, Tomo CXI, expedido por la H. XVIII\nLegislatura, siendo Gobernador Constitucional el C. Eugenio Elorduy Walther 2001-2007; fue reformado mediante sesión de Pleno efectuada el día 02 de octubre de 2010; fue reformado por Decreto No. 11, publicado en el Periódico Oficial No. 56, de fecha 17 de diciembre de\n2010, Tomo CXVII, Sección III, expedido por la H. XX Legislatura, siendo Gobernador\nConstitucional el C. José Guadalupe Osuna Millán 2007-2013; fue reformado mediante el\nDictamen No. 266 de la Comisión de Gobernación, Legislación y Puntos Constitucionales, publicado en la Gaceta Parlamentaria del Congreso del Estado en fecha 27 de agosto de\n2013, expedido por la H. XX Legislatura, siendo Gobernador Constitucional el C. José\nGuadalupe Osuna Millán 2007-2013; fue derogado mediante Decreto No. 19, publicado en el\nPeriódico Oficial No. 52, de fecha 25 de noviembre de 2016, Tomo CXXIII, Sección IV, expedido por la H. XXII Legislatura, siendo Gobernador Constitucional el C. Francisco Arturo\nVega de Lamadrid 2013-2019;\nARTICULO 83 SEXIES. Fue reformado mediante sesión de Pleno efectuada el día 02\nLegislatura, siendo Gobernador Constitucional el C. José Guadalupe Osuna Millán 20072013; fue reformado por Decreto No. 88, publicado en el Periódico Oficial No. 42, de fecha 2\nGobernador Constitucional el C. José Guadalupe Osuna Millán 2007-2013; fue reformado\n.\nActualización Legislativa.\nÚltima reforma Gaceta No. 63, Especial, 14-Ago-2025\nTomo CXIX, Sección I, expedido por la H. XX Legislatura, siendo Gobernador Constitucional el C. José Guadalupe Osuna Millán 2007- 2013; fue derogado mediante Decreto No. 19, publicado en el Periódico Oficial No. 52, de fecha 25 de noviembre de 2016, Tomo CXXIII,\nSección IV, expedido por la H. XXII Legislatura, siendo Gobernador Constitucional el C.\nFrancisco Arturo Vega de Lamadrid 2013-2019;\nFue modificada la denominación de este Capítulo, por Decreto No. 2, Publicado en el\nPeriódico Oficial No. 50, de fecha 19 de noviembre de 2004, Sección II, Tomo CXI, expedido por la H. XVIII Legislatura, siendo Gobernador Constitucional el C. Eugenio Elorduy Walther\n2001-2007; fue derogado este Capítulo por Decreto No. 52, publicado en el Periódico Oficial\nNo. 27, de fecha 03 de junio de 2011, Tomo CXVIII, Sección I, expedido por la H. XX\nLegislatura, siendo Gobernador Constitucional el C. José Guadalupe Osuna Millán 20072013;\nCAPITULO IV\nDE LA COMISION PERMANENTE\nFue adicionada esta Sección mediante Decreto No. 19, publicado en el Periódico Oficial No.\n52, de fecha 25 de noviembre de 2016, Tomo CXXIII, Sección IV, expedido por la H. XXI\nLegislatura, siendo Gobernador Constitucional el C. Francisco Arturo Vega de Lamadrid\n2013-2019;\nSECCIÓN IX\nDEL COMITÉ DE TRANSPARENCIA Y LA UNIDAD DE TRANSPARENCIA\nARTICULO 84. Fue derogado por Decreto No. 145, publicado en el Periódico Oficial\nNo. 03 de fecha 14 de enero de 2003, Tomo CX, Número Especial, expedido por la H. XVII\nLegislatura, siendo Gobernador Constitucional el C. Eugenio Elorduy Walther 2001-2007; fue reformado por Decreto No. 2, Publicado en el Periódico Oficial No. 50, de fecha 19 de noviembre de 2004, Sección II, Tomo CXI, expedido por la H. XVIII Legislatura, siendo\nGobernador Constitucional el C. Eugenio Elorduy Walther 2001-2007; fue derogado por\nCXVIII, Sección I, expedido por la H. XX Legislatura, siendo Gobernador Constitucional el C.\nJosé Guadalupe Osuna Millán 2007-2013; fue reformado mediante Decreto No. 19,\nSección IV, expedido por la H. XXII Legislatura, siendo Gobernador Constitucional el C.\nFrancisco Arturo Vega de Lamadrid 2013-2019; fue reformado mediante Decreto No. 126,\nSección III, expedido por la H. XXII Legislatura, siendo Gobernador Constitucional el C.\nFrancisco Arturo Vega de Lamadrid 2013-2019;\n.\nActualización Legislativa.\nÚltima reforma Gaceta No. 63, Especial, 14-Ago-2025\nARTICULO 85. Fue derogado por Decreto No. 145, publicado en el Periódico Oficial\nNo. 03 de fecha 14 de enero de 2003, Tomo CX, Número Especial, expedido por la H. XVII\nLegislatura, siendo Gobernador Constitucional el C. Eugenio Elorduy Walther 2001-2007; fue reformado por Decreto No. 2, Publicado en el Periódico Oficial No. 50, de fecha 19 de noviembre de 2004, Sección II, Tomo CXI, expedido por la H. XVIII Legislatura, siendo\nGobernador Constitucional el C. Eugenio Elorduy Walther 2001-2007; fue derogado por\nDecreto No. 52, publicado en el Periódico Oficial No. 27, de fecha 03 de junio de 2011, Tomo\nCXVIII, Sección I, expedido por la H. XX Legislatura, siendo Gobernador Constitucional el C.\nJosé Guadalupe Osuna Millán 2007-2013; fue reformado mediante Decreto No. 19, publicado en el Periódico Oficial No. 52, de fecha 25 de noviembre de 2016, Tomo CXXIII,\nSección IV, expedido por la H. XXII Legislatura, siendo Gobernador Constitucional el C.\nFrancisco Arturo Vega de Lamadrid 2013-2019;\nFue adicionada esta Sección por Decreto No. 226, publicado en el Periódico Oficial\nNo. 30, de fecha 26 de mayo de 2023, Índice, Tomo CXXX, expedido por la H. XXIV\nLegislatura, siendo Gobernadora Constitucional la C. Marina del Pilar Ávila Olmeda, 20212027;\nSECCIÓN X\nDE LA UNIDAD DE IGUALDAD DE GÉNERO\nARTICULO 85 BIS. Fue adicionado por Decreto No. 226, publicado en el Periódico\nOficial No. 30, de fecha 26 de mayo de 2023, Índice, Tomo CXXX, expedido por la H. XXIV\nLegislatura, siendo Gobernadora Constitucional la C. Marina del Pilar Ávila Olmeda, 20212027;\nARTICULO 85 BIS 1. Fue adicionado por Decreto No. 226, publicado en el Periódico\nOficial No. 30, de fecha 26 de mayo de 2023, Índice, Tomo CXXX, expedido por la H. XXIV\nLegislatura, siendo Gobernadora Constitucional la C. Marina del Pilar Ávila Olmeda, 20212027;\nARTICULO 86. Fue Derogado, por Decreto No. 145, publicado en el Periódico Oficial\nNo. 03 de fecha 14 de enero de 2003, Tomo CX, Número Especial, expedido por la H. XVII\nLegislatura, siendo Gobernador Constitucional el C. Eugenio Elorduy Walther 2001-2007; fue reformado por Decreto No. 2, Publicado en el Periódico Oficial No. 50, de fecha 19 de\nGobernador Constitucional el C. Eugenio Elorduy Walther 2001-2007; fue derogado por\nCXVIII, Sección I, expedido por la H. XX Legislatura, siendo Gobernador Constitucional el C.\nJosé Guadalupe Osuna Millán 2007-2013;\nARTICULO 87. Fue Derogado por Decreto No. 145, publicado en el Periódico Oficial\nLegislatura, siendo Gobernador Constitucional el C. Eugenio Elorduy Walther 2001-2007; fue reformado por Decreto No. 2, Publicado en el Periódico Oficial No. 50, de fecha 19 de\n.\nActualización Legislativa.\nÚltima reforma Gaceta No. 63, Especial, 14-Ago-2025 noviembre de 2004, Sección II, Tomo CXI, expedido por la H. XVIII Legislatura, siendo\nGobernador Constitucional el C. Eugenio Elorduy Walther 2001-2007; fue derogado por\nDecreto No. 52, publicado en el Periódico Oficial No. 27, de fecha 03 de junio de 2011, Tomo\nCXVIII, Sección I, expedido por la H. XX Legislatura, siendo Gobernador Constitucional el C.\nJosé Guadalupe Osuna Millán 2007-2013;\nARTICULO 87 BIS. Fue reformado por Decreto No. 2, Publicado en el Periódico\nOficial No. 50, de fecha 19 de noviembre de 2004, Sección II, Tomo CXI, expedido por la H.\nXVIII Legislatura, siendo Gobernador Constitucional el C. Eugenio Elorduy Walther 20012007; fue derogado por Decreto No. 52, publicado en el Periódico Oficial No. 27, de fecha 03 de junio de 2011, Tomo CXVIII, Sección I, expedido por la H. XX Legislatura, siendo\nGobernador Constitucional el C. José Guadalupe Osuna Millán 2007-2013;\nARTICULO 87 TER. Fue reformado por Decreto No. 2, Publicado en el Periódico\nOficial No. 50, de fecha 19 de noviembre de 2004, Sección II, Tomo CXI, expedido por la H.\nXVIII Legislatura, siendo Gobernador Constitucional el C. Eugenio Elorduy Walther 20012007; fue derogado por Decreto No. 52, publicado en el Periódico Oficial No. 27, de fecha 03 de junio de 2011, Tomo CXVIII, Sección I, expedido por la H. XX Legislatura, siendo\nGobernador Constitucional el C. José Guadalupe Osuna Millán 2007-2013;\nARTICULO 87 QUARTER. Fue reformado por Decreto No. 2, Publicado en el\nPeriódico Oficial No. 50, de fecha 19 de noviembre de 2004, Sección II, Tomo CXI, expedido por la H. XVIII Legislatura, siendo Gobernador Constitucional el C. Eugenio Elorduy Walther\n2001-2007; fue derogado por Decreto No. 52, publicado en el Periódico Oficial No. 27, de fecha 03 de junio de 2011, Tomo CXVIII, Sección I, expedido por la H. XX Legislatura, siendo Gobernador Constitucional el C. José Guadalupe Osuna Millán 2007-2013;\nARTICULO 87 QUINQUIES. Fue reformado por Decreto No. 2, Publicado en el\nPeriódico Oficial No. 50, de fecha 19 de noviembre de 2004, Sección II, Tomo CXI, expedido por la H. XVIII Legislatura, siendo Gobernador Constitucional el C. Eugenio Elorduy Walther\n2001-2007; fue derogado por Decreto No. 52, publicado en el Periódico Oficial No. 27, de fecha 03 de junio de 2011, Tomo CXVIII, Sección I, expedido por la H. XX Legislatura, siendo Gobernador Constitucional el C. José Guadalupe Osuna Millán 2007-2013;\nARTICULO 88. Fue reformado por Decreto No. 2, Publicado en el Periódico Oficial\nLegislatura, siendo Gobernador Constitucional el C. Eugenio Elorduy Walther 2001-2007;\nFue reformado por Decreto No. 316, Publicado en el Periódico Oficial No. 57, de fecha 18 de\nConstitucional el C. José Guadalupe Osuna Millán 2007-2013; fue reformado por Decreto\nCXVII, Sección III, expedido por la H. XX Legislatura, siendo Gobernador Constitucional el C.\nJosé Guadalupe Osuna Millán 2007-2013; fue reformado por Decreto No. 52, publicado en el\n.\nActualización Legislativa.\nÚltima reforma Gaceta No. 63, Especial, 14-Ago-2025 la H. XX Legislatura, siendo Gobernador Constitucional el C. José Guadalupe Osuna Millán\n2007-2013; fue reformado mediante Decreto No. 19, publicado en el Periódico Oficial No. 52, de fecha 25 de noviembre de 2016, Tomo CXXIII, Sección IV, expedido por la H. XXII\nLegislatura, siendo Gobernador Constitucional el C. Francisco Arturo Vega de Lamadrid\n2013-2019;\nARTICULO 89. Fue reformado por Decreto No. 2, Publicado en el Periódico Oficial\nNo. 50, de fecha 19 de noviembre de 2004, Sección II, Tomo CXI, expedido por la H. XVIII\nLegislatura, siendo Gobernador Constitucional el C. Eugenio Elorduy Walther 2001-2007;\nARTICULO 91. Fue reformado mediante sesión de Pleno efectuada el día 02 de octubre de 2010; fue reformado mediante Decreto No. 19, publicado en el Periódico Oficial\nNo. 52, de fecha 25 de noviembre de 2016, Tomo CXXIII, Sección IV, expedido por la H.\nXXII Legislatura, siendo Gobernador Constitucional el C. Francisco Arturo Vega de Lamadrid\n2013-2019;\nARTICULO 92. Fue reformado mediante sesión de Pleno efectuada el día 02 de octubre de 2010;\nARTICULO 93. Fue reformado por Decreto No. 11, publicado en el Periódico Oficial\nNo. 56, de fecha 17 de diciembre de 2010, Tomo CXVII, Sección III, expedido por la H. XX\nLegislatura, siendo Gobernador Constitucional el C. José Guadalupe Osuna Millán 20072013; fue reformado por Decreto No. 417, en el Periódico Oficial No. 21, Índice, de fecha 26 de abril de 2024, Tomo CXXXI y en la Gaceta Parlamentaria No. 145 del Congreso del\nEstado, en fecha 31 de marzo de 2013, expedido por la H. XXIV Legislatura, siendo\nGobernadora Constitucional la C. Marina del Pilar Ávila Olmeda, 2021-2027;\nARTICULO 94. Fue reformado por Decreto No. 2, Publicado en el Periódico Oficial\nNo. 50, de fecha 19 de noviembre de 2004, Sección II, Tomo CXI, expedido por la H. XVIII\nLegislatura, siendo Gobernador Constitucional el C. Eugenio Elorduy Walther 2001-2007; fue reformado por Decreto No. 11, publicado en el Periódico Oficial No. 56, de fecha 17 de diciembre de 2010, Tomo CXVII, Sección III, expedido por la H. XX Legislatura, siendo\nGobernador Constitucional el C. José Guadalupe Osuna Millán 2007-2013; fue reformado mediante Decreto No. 145, publicado en el Periódico Oficial No. 50, de fecha 10 de\nGobernador Constitucional el C. Francisco Arturo Vega de Lamadrid 2013-2019;\nARTICULO 95. Fue reformado por Decreto No. 2, Publicado en el Periódico Oficial\nLegislatura, siendo Gobernador Constitucional el C. Eugenio Elorduy Walther 2001-2007; fue reformado por Decreto No. 11, publicado en el Periódico Oficial No. 56, de fecha 17 de\nGobernador Constitucional el C. José Guadalupe Osuna Millán 2007-2013; fue reformado mediante Decreto No. 19, publicado en el Periódico Oficial No. 52, de fecha 25 de noviembre\n.\nActualización Legislativa.\nÚltima reforma Gaceta No. 63, Especial, 14-Ago-2025 de 2016, Tomo CXXIII, Sección IV, expedido por la H. XXII Legislatura, siendo Gobernador\nConstitucional el C. Francisco Arturo Vega de Lamadrid 2013-2019;\nARTICULO 96. Fue reformado por Decreto No. 2, Publicado en el Periódico Oficial\nNo. 50, de fecha 19 de noviembre de 2004, Sección II, Tomo CXI, expedido por la H. XVIII\nLegislatura, siendo Gobernador Constitucional el C. Eugenio Elorduy Walther 2001-2007; fue reformado mediante sesión de Pleno efectuada el día 02 de octubre de 2010; fue reformado mediante el Dictamen No. 266 de la Comisión de Gobernación, Legislación y Puntos\nConstitucionales, publicado en la Gaceta Parlamentaria del Congreso del Estado en fecha\n27 de agosto de 2013, expedido por la H. XX Legislatura, siendo Gobernador Constitucional el C. José Guadalupe Osuna Millán 2007-2013;\nARTICULO 98. Fue reformado por Decreto No. 2, Publicado en el Periódico Oficial\nNo. 50, de fecha 19 de noviembre de 2004, Sección II, Tomo CXI, expedido por la H. XVIII\nLegislatura, siendo Gobernador Constitucional el C. Eugenio Elorduy Walther 2001-2007;\nARTICULO 100. Fue reformado por Decreto No. 2, Publicado en el Periódico Oficial\nNo. 50, de fecha 19 de noviembre de 2004, Sección II, Tomo CXI, expedido por la H. XVIII\nLegislatura, siendo Gobernador Constitucional el C. Eugenio Elorduy Walther 2001-2007;\nARTICULO 101. Fue reformado por Decreto No. 2, Publicado en el Periódico Oficial\nNo. 50, de fecha 19 de noviembre de 2004, Sección II, Tomo CXI, expedido por la H. XVIII\nLegislatura, siendo Gobernador Constitucional el C. Eugenio Elorduy Walther 2001-2007; fue reformado por Decreto No. 126, publicado en el Periódico Oficial No. 48, de fecha 30 de septiembre de 2008, Tomo CXV, expedido por la H. XIX Legislatura, siendo Gobernador\nConstitucional el C. José Guadalupe Osuna Millán 2007-2013; fue reformado mediante el\nDictamen No. 266 de la Comisión de Gobernación, Legislación y Puntos Constitucionales, publicado en la Gaceta Parlamentaria del Congreso del Estado en fecha 27 de agosto de\n2013, expedido por la H. XX Legislatura, siendo Gobernador Constitucional el C. José\nGuadalupe Osuna Millán 2007-2013; fue reformado mediante Decreto No. 19, publicado en el Periódico Oficial No. 52, de fecha 25 de noviembre de 2016, Tomo CXXIII, Sección IV, expedido por la H. XXII Legislatura, siendo Gobernador Constitucional el C. Francisco Arturo\nVega de Lamadrid 2013-2019;\nARTICULO 104. Fue reformado mediante Decreto No. 524, publicado en el Periódico\nXXI Legislatura, siendo Gobernador Constitucional el C. Francisco Arturo Vega de Lamadrid\n2013-2019;\nARTICULO 107. Fue reformado por Decreto No. 126, publicado en el Periódico Oficial siendo Gobernador Constitucional el C. José Guadalupe Osuna Millán 2007-2013; fue reformado por Decreto No. 508, publicado en el Periódico Oficial No. 37, de fecha 23 de\nConstitucional el C. Lic. José Guadalupe Osuna Millán, 2007-2013;\n.\nActualización Legislativa.\nÚltima reforma Gaceta No. 63, Especial, 14-Ago-2025\nARTICULO 108. Fue derogado mediante sesión de Pleno efectuada el día 02 de octubre de 2010;\nARTICULO 109.- Fue reformado mediante Decreto No. 19, publicado en el Periódico\nOficial No. 52, de fecha 25 de noviembre de 2016, Tomo CXXIII, Sección IV, expedido por la\nH. XXII Legislatura, siendo Gobernador Constitucional el C. Francisco Arturo Vega de\nLamadrid 2013-2019; fue reformado mediante Decreto No. 261, publicado en el Periódico\nOficial No. 7, de fecha 01 de febrero de 2019, Tomo CXXVI, Sección III, expedido por la H.\nXXII Legislatura, siendo Gobernador Constitucional el C. Francisco Arturo Vega de Lamadrid\n2013-2019;\nARTICULO 109 BIS. Fue adicionado mediante Decreto No. 524, publicado en el\nPeriódico Oficial No. 35, de fecha 05 de agosto de 2016, Tomo CXXIII, Sección IV, expedido por la H. XXI Legislatura, siendo Gobernador Constitucional el C. Francisco Arturo Vega de\nLamadrid 2013-2019; fue reformado mediante Decreto No. 19, publicado en el Periódico\nOficial No. 52, de fecha 25 de noviembre de 2016, Tomo CXXIII, Sección IV, expedido por la\nH. XXII Legislatura, siendo Gobernador Constitucional el C. Francisco Arturo Vega de\nLamadrid 2013-2019;\nARTICULO 110. Fue reformado mediante sesión de Pleno efectuada el día 02 de octubre de 2010; fue reformado por Decreto No. 48, publicado en el Periódico Oficial No. 29,\nSección II, Tomo CXXI, de fecha 30 de mayo de 2014, expedido por la H. XXI Legislatura, siendo Gobernador Constitucional el C. Francisco Arturo Vega de Lamadrid 2013-2019.\nARTICULO 113. Fue reformado mediante sesión de Pleno efectuada el día 02 de octubre de 2010;\nARTICULO 114. Fue reformado por Decreto No. 145, publicado en el Periódico Oficial\nNo. 03 de fecha 14 de enero de 2003, Tomo CX, Número Especial, expedido por la H. XVII\nLegislatura, siendo Gobernador Constitucional el C. Eugenio Elorduy Walther 2001-2007; fue reformado mediante sesión de Pleno efectuada el día 02 de octubre de 2010; fue reformado por Decreto No. 48, publicado en el Periódico Oficial No. 29, Sección II, Tomo CXXI, de fecha 30 de mayo de 2014, expedido por la H. XXI Legislatura, siendo Gobernador\nConstitucional el C. Francisco Arturo Vega de La Madrid 2013-2019.\nARTICULO 115. Fue reformado mediante sesión de Pleno efectuada el día 02 de siendo Gobernador Constitucional el C. José Guadalupe Osuna Millán 2007-2013; fue reformado mediante Decreto No. 19, publicado en el Periódico Oficial No. 52, de fecha 25 de\nGobernador Constitucional el C. Francisco Arturo Vega de Lamadrid 2013-2019;\n.\nActualización Legislativa.\nÚltima reforma Gaceta No. 63, Especial, 14-Ago-2025\nARTICULO 117. Fue reformado por Decreto No. 249, publicado en el Periódico Oficial\nNo. 46, de fecha 03 de noviembre de 2006, Tomo CXIII, expedido por la H. XVIII Legislatura, siendo Gobernador Constitucional el C. Eugenio Elorduy Walther 2001-2007; fue reformado por Decreto No. 52, publicado en el Periódico Oficial No. 27, de fecha 03 de junio de 2011, Tomo CXVIII, Sección I, expedido por la H. XX Legislatura, siendo Gobernador\nConstitucional el C. José Guadalupe Osuna Millán 2007-2013; fue reformado mediante sesión de Pleno efectuada el día 13 de noviembre de 2014; fue reformado mediante Decreto\nNo. 126, publicado en el Periódico Oficial No. 50, de fecha 10 de noviembre de 2017, Tomo\nCXXIV, Sección III, expedido por la H. XXII Legislatura, siendo Gobernador Constitucional el\nC. Francisco Arturo Vega de Lamadrid 2013-2019;\nARTICULO 118. Fue reformado por Decreto No. 249, publicado en el Periódico Oficial\nNo. 46, de fecha 03 de noviembre de 2006, Tomo CXIII, expedido por la H. XVIII Legislatura, siendo Gobernador Constitucional el C. Eugenio Elorduy Walther 2001-2007; fue reformado mediante sesión de Pleno efectuada el día 02 de octubre de 2010; fue reformado por\nDecreto No. 11, publicado en el Periódico Oficial No. 56, de fecha 17 de diciembre de 2010, Tomo CXVII, Sección III, expedido por la H. XX Legislatura, siendo Gobernador\nConstitucional el C. José Guadalupe Osuna Millán 2007-2013; fue reformado por Decreto\nNo. 172, publicado en el Periódico Oficial No. 8, de fecha 10 de febrero de 2012, Tomo\nCXIX, Sección I, expedido por la H. XX Legislatura, siendo Gobernador Constitucional el C.\nJosé Guadalupe Osuna Millán 2007-2013; fue reformado mediante Decreto No. 19, publicado en el Periódico Oficial No. 52, de fecha 25 de noviembre de 2016, Tomo CXXIII,\nSección IV, expedido por la H. XXII Legislatura, siendo Gobernador Constitucional el C.\nFrancisco Arturo Vega de Lamadrid 2013-2019;\nARTICULO 119. Fue reformado por Decreto No. 11, publicado en el Periódico Oficial\nNo. 56, de fecha 17 de diciembre de 2010, Tomo CXVII, Sección III, expedido por la H. XX\nLegislatura, siendo Gobernador Constitucional el C. José Guadalupe Osuna Millán 20072013; fue reformado por Decreto No. 514, publicado en el Periódico Oficial No. 38, de fecha\n30 de agosto de 2013, Sección I, Tomo CXX, expedido por la Honorable XX Legislatura, siendo Gobernador Constitucional el C. Lic. José Guadalupe Osuna Millán, 2007-2013; fue reformado por Decreto No. 48, publicado en el Periódico Oficial No. 29, Sección II, Tomo\nCXXI, de fecha 30 de mayo de 2014, expedido por la H. XXI Legislatura, siendo Gobernador\nConstitucional el C. Francisco Arturo Vega de Lamadrid 2013-2019; fue reformado mediante\nDecreto No. 539, publicado en el Periódico Oficial No. 40, de fecha 02 de septiembre de\n2016, Tomo CXXIII, Sección I, expedido por la H. XXI Legislatura, siendo Gobernador\nConstitucional el C. Francisco Arturo Vega de Lamadrid 2013-2019;\nARTICULO 120. Fue reformado mediante sesión de Pleno efectuada el día 02 de\nXXII Legislatura, siendo Gobernador Constitucional el C. Francisco Arturo Vega de Lamadrid\n2013-2019;\n.\nActualización Legislativa.\nÚltima reforma Gaceta No. 63, Especial, 14-Ago-2025\nARTICULO 122.- Fue reformado mediante Decreto No. 81, publicado en el Periódico\nOficial No. 22, Índice, de fecha 11 de abril de 2025, Tomo CXXXII, expedido por la H. XXV\nLegislatura, siendo Gobernadora Constitucional la C. Marina del Pilar Ávila Olmeda 20212027;\nARTICULO 126. Fue reformado por Decreto No. 11, publicado en el Periódico Oficial\nNo. 56, de fecha 17 de diciembre de 2010, Tomo CXVII, Sección III, expedido por la H. XX\nLegislatura, siendo Gobernador Constitucional el C. José Guadalupe Osuna Millán 20072013; fue reformado por Decreto No. 48, publicado en el Periódico Oficial No. 29, Sección II, Tomo CXXI, de fecha 30 de mayo de 2014, expedido por la H. XXI Legislatura, siendo\nGobernador Constitucional el C. Francisco Arturo Vega de Lamadrid 2013-2019.\nARTICULO 127. Fue reformado por Decreto No. 11, publicado en el Periódico Oficial\nNo. 56, de fecha 17 de diciembre de 2010, Tomo CXVII, Sección III, expedido por la H. XX\nLegislatura, siendo Gobernador Constitucional el C. José Guadalupe Osuna Millán 20072013;\nARTICULO 139. Fue reformado por Decreto No. 48, publicado en el Periódico Oficial\nNo. 29, Sección II, Tomo CXXI, de fecha 30 de mayo de 2014, expedido por la H. XXI\nLegislatura, siendo Gobernador Constitucional el C. Francisco Arturo Vega de Lamadrid\n2013-2019.\nARTICULO 144. Fue reformado por Decreto No. 2, Publicado en el Periódico Oficial\nNo. 50, de fecha 19 de noviembre de 2004, Sección II, Tomo CXI, expedido por la H. XVIII\nLegislatura, siendo Gobernador Constitucional el C. Eugenio Elorduy Walther 2001-2007; fue reformado por Decreto No. 11, publicado en el Periódico Oficial No. 56, de fecha 17 de diciembre de 2010, Tomo CXVII, Sección III, expedido por la H. XX Legislatura, siendo\nGobernador Constitucional el C. José Guadalupe Osuna Millán 2007-2013; fue reformado mediante Decreto No. 19, publicado en el Periódico Oficial No. 52, de fecha 25 de noviembre de 2016, Tomo CXXIII, Sección IV, expedido por la H. XXII Legislatura, siendo Gobernador\nConstitucional el C. Francisco Arturo Vega de Lamadrid 2013-2019;\nARTICULO 145. Fue reformado por Decreto No. 48, publicado en el Periódico Oficial\nLegislatura, siendo Gobernador Constitucional el C. Francisco Arturo Vega de Lamadrid\n2013-2019.\nARTICULO 145 BIS. Fue adicionado por Decreto No. 48, publicado en el Periódico\nLegislatura, siendo Gobernador Constitucional el C. Francisco Arturo Vega de Lamadrid\n2013-2019.\nARTICULO 146. Fue adicionado por Decreto No. 199, publicado en el Periódico\n.\nActualización Legislativa.\nÚltima reforma Gaceta No. 63, Especial, 14-Ago-2025\nXXII Legislatura, siendo Gobernador Constitucional el C. Francisco Arturo Vega de Lamadrid\n2013-2019.\nARTICULO 151. Fue reformado por Decreto No. 11, publicado en el Periódico Oficial\nNo. 56, de fecha 17 de diciembre de 2010, Tomo CXVII, Sección III, expedido por la H. XX\nLegislatura, siendo Gobernador Constitucional el C. José Guadalupe Osuna Millán 20072013; fue reformado por Decreto No. 48, publicado en el Periódico Oficial No. 29, Sección II, Tomo CXXI, de fecha 30 de mayo de 2014, expedido por la H. XXI Legislatura, siendo\nGobernador Constitucional el C. Francisco Arturo Vega de Lamadrid 2013-2019..\nARTICULO 156. Fue reformado por Decreto No. 150, publicado en el Periódico Oficial\nNo. 06, de fecha 31 de enero de 2003, Sección II, Tomo CX, expedido por la H. XVII\nLegislatura, siendo Gobernador Constitucional el C. Eugenio Elorduy Walther 2001-2007; fue reformado por Decreto No. 11, publicado en el Periódico Oficial No. 56, de fecha 17 de diciembre de 2010, Tomo CXVII, Sección III, expedido por la H. XX Legislatura, siendo\nGobernador Constitucional el C. José Guadalupe Osuna Millán 2007-2013;\nARTICULO 157. Fue reformado por Decreto No. 150, publicado en el Periódico Oficial\nNo. 06, de fecha 31 de enero de 2003, Sección II, Tomo CX, expedido por la H. XVII\nLegislatura, siendo Gobernador Constitucional el C. Eugenio Elorduy Walther 2001-2007; fue reformado por Decreto No. 11, publicado en el Periódico Oficial No. 56, de fecha 17 de diciembre de 2010, Tomo CXVII, Sección III, expedido por la H. XX Legislatura, siendo\nGobernador Constitucional el C. José Guadalupe Osuna Millán 2007-2013; fue reformado mediante Decreto No. 19, publicado en el Periódico Oficial No. 52, de fecha 25 de noviembre de 2016, Tomo CXXIII, Sección IV, expedido por la H. XXII Legislatura, siendo Gobernador\nConstitucional el C. Francisco Arturo Vega de Lamadrid 2013-2019;\nARTICULO 166. Fue reformado por Decreto No. 2, Publicado en el Periódico Oficial\nNo. 50, de fecha 19 de noviembre de 2004, Sección II, Tomo CXI, expedido por la H. XVIII\nLegislatura, siendo Gobernador Constitucional el C. Eugenio Elorduy Walther 2001-2007;\nFue adicionada la denominación a este Título por Decreto No. 310, publicado en el\nPeriódico Oficial No. 62, de fecha 06 de noviembre de 2023, Sección I, Tomo CXXX, expedido por la H. XXIV Legislatura, siendo Gobernadora Constitucional la C. Marina del\nPilar Ávila Olmeda 2021-2027;\nTÍTULO OCTAVO\nFue reformada la denominación de este Capítulo por Decreto No. 310, publicado en el expedido por la H. XXIV Legislatura, siendo Gobernadora Constitucional la C. Marina del\nPilar Ávila Olmeda 2021-2027;\nCAPÍTULO PRIMERO\nDECLARACIÓN PATRIMONIAL Y DE INTERÉSES\n.\nActualización Legislativa.\nÚltima reforma Gaceta No. 63, Especial, 14-Ago-2025\nARTICULO 168. Fue reformado por Decreto No. 2, Publicado en el Periódico Oficial\nNo. 50, de fecha 19 de noviembre de 2004, Sección II, Tomo CXI, expedido por la H. XVIII\nLegislatura, siendo Gobernador Constitucional el C. Eugenio Elorduy Walther 2001-2007; fue reformado mediante sesión de Pleno efectuada el día 02 de octubre de 2010; fue reformado mediante Decreto No. 19, publicado en el Periódico Oficial No. 52, de fecha 25 de noviembre de 2016, Tomo CXXIII, Sección IV, expedido por la H. XXII Legislatura, siendo Gobernador\nConstitucional el C. Francisco Arturo Vega de Lamadrid 2013-2019; fue reformado por\nDecreto No. 310, publicado en el Periódico Oficial No. 62, de fecha 06 de noviembre de\n2023, Sección I, Tomo CXXX, expedido por la H. XXIV Legislatura, siendo Gobernadora\nConstitucional la C. Marina del Pilar Ávila Olmeda 2021-2027;\nARTICULO 169.- Fue reformado mediante Decreto No. 19, publicado en el Periódico\nOficial No. 52, de fecha 25 de noviembre de 2016, Tomo CXXIII, Sección IV, expedido por la\nH. XXII Legislatura, siendo Gobernador Constitucional el C. Francisco Arturo Vega de\nLamadrid 2013-2019;\nFue adicionado mediante sesión de Pleno efectuada el día 02 de octubre de 2010; fue derogado este Capítulo mediante Decreto No. 19, publicado en el Periódico Oficial No. 52, de fecha 25 de noviembre de 2016, Tomo CXXIII, Sección IV, expedido por la H. XXI\nLegislatura, siendo Gobernador Constitucional el C. Francisco Arturo Vega de Lamadrid\n2013-2019;\nCAPÍTULO SEGUNDO\nDE LA TRANSPARENCIA Y EL ACCESO A LA INFORMACIÓN\nFue adicionado mediante Decreto No. 249, publicado en el Periódico Oficial No. 39, de fecha 07 de julio de 2023, Tomo CXXX, Índice, expedido por la H. XXIV Legislatura, siendo Gobernadora Constitucional la C. Marina del Pilar Ávila Olmeda 2021-2027\nCAPÍTULO SEGUNDO\nDEL SEMÁFARO DE VOTACIONES\nARTICULO 169 BIS. Fue adicionado mediante sesión de Pleno efectuada el día 02 de octubre de 2010; fue reformado mediante el Dictamen No. 266 de la Comisión de siendo Gobernador Constitucional el C. José Guadalupe Osuna Millán 2007-2013; fue derogado mediante Decreto No. 19, publicado en el Periódico Oficial No. 52, de fecha 25 de\nGobernador Constitucional el C. Francisco Arturo Vega de Lamadrid 2013-2019; fue adicionado mediante Decreto No. 249, publicado en el Periódico Oficial No. 39, de fecha 07\nGobernadora Constitucional la C. Marina del Pilar Ávila Olmeda 2021-2027;\n.\nActualización Legislativa.\nÚltima reforma Gaceta No. 63, Especial, 14-Ago-2025\nFue adicionado este Capítulo Tercero mediante Decreto No. 78, publicado en el Periódico\nOficial No. 22, Índice, de fecha 11 de abril de 2025, Tomo CXXXII, expedido por la H. XXV\nLegislatura, siendo Gobernadora Constitucional la C. Marina del Pilar Ávila Olmeda 20212027;\nCAPÍTULO TERCERO\nDEL PARLAMENTO ABIERTO\nARTICULO 170. Fue derogado mediante Decreto No. 19, publicado en el Periódico\nOficial No. 52, de fecha 25 de noviembre de 2016, Tomo CXXIII, Sección IV, expedido por la\nH. XXII Legislatura, siendo Gobernador Constitucional el C. Francisco Arturo Vega de\nLamadrid 2013-2019; fue reformado mediante Decreto No. 78, publicado en el Periódico\nOficial No. 22, Índice, de fecha 11 de abril de 2025, Tomo CXXXII, expedido por la H. XXV\nLegislatura, siendo Gobernadora Constitucional la C. Marina del Pilar Ávila Olmeda 20212027;\nFue adicionado este Capítulo Cuarto mediante Decreto No. 129, publicado en la Gaceta No.\n63, Especial de fecha 14 de agosto de 2025; expedido por la H. XXV Legislatura, siendo\nGobernadora Constitucional la C. Marina del Pilar Ávila Olmeda 2021-2027;\nCAPÍTULO CUARTO\nDE LAS INICIATIVAS CIUDADANAS\nARTÍCULO 170 BIS. Fue adicionado mediante Decreto No. 129, publicado en la\nGaceta No. 63, Especial de fecha 14 de agosto de 2025, y en el Periódico Oficial No. 54, Índice, de fecha 05 de septiembre de 2025, Tomo CXXXII; expedido por la H. XXV\nLegislatura, siendo Gobernadora Constitucional la C. Marina del Pilar Ávila Olmeda 20212027;\nARTICULO 171. Fue reformado mediante sesión de Pleno efectuada el día 02 de octubre de 2010; fue reformado mediante el Dictamen No. 266 de la Comisión de\nGobernación, Legislación y Puntos Constitucionales, publicado en la Gaceta Parlamentaria del Congreso del Estado en fecha 27 de agosto de 2013, expedido por la H. XX Legislatura, siendo Gobernador Constitucional el C. José Guadalupe Osuna Millán 2007-2013; fue reformado por Decreto No. 48, publicado en el Periódico Oficial No. 29, Sección II, Tomo\nConstitucional el C. Francisco Arturo Vega de Lamadrid 2013-2019; fue reformado mediante\nTomo CXXIII, Sección IV, expedido por la H. XXII Legislatura, siendo Gobernador\nConstitucional el C. Francisco Arturo Vega de Lamadrid 2013-2019;\nARTICULO 172. Fue reformado mediante sesión de Pleno efectuada el día 02 de\n.\nActualización Legislativa.\nÚltima reforma Gaceta No. 63, Especial, 14-Ago-2025\nFue adicionado este Título mediante Decreto No. 358, publicado en el Periódico Oficial No.\n53, de fecha 20 de noviembre de 2015, Tomo CXXII, Sección I, expedido por la H. XXI\nLegislatura, siendo Gobernador Constitucional el C. Francisco Arturo Vega de Lamadrid\n2013-2019;\nTÍTULO DÉCIMO\nPRÁCTICAS SUSTENTABLES\nArtículo 173.- Fue adicionado mediante Decreto No. 358, publicado en el Periódico\nOficial No. 53, de fecha 20 de noviembre de 2015, Tomo CXXII, Sección I, expedido por la\nH. XXI Legislatura, siendo Gobernador Constitucional el C. Francisco Arturo Vega de\nLamadrid 2013-2019; fue reformado mediante Decreto No. 19, publicado en el Periódico\nOficial No. 52, de fecha 25 de noviembre de 2016, Tomo CXXIII, Sección IV, expedido por la\nH. XXII Legislatura, siendo Gobernador Constitucional el C. Francisco Arturo Vega de\nLamadrid 2013-2019;\nTÍTULO DÉCIMO PRIMERO\n“DE LA OBLIGACIÓN DE IMPARCIALIDAD EN PROCESO ELECTORAL”\nArtículo 174.- Fue reformado mediante Decreto No. 244, publicado en el Periódico\nOficial No. 28, de fecha 09 de junio de 2018, Tomo CXXV, NÚMERO ESPECIAL, expedido por la H. XXII Legislatura, siendo Gobernador Constitucional el C. Francisco Arturo Vega de\nLamadrid 2013-2019;\nArtículo 175.- Fue reformado mediante Decreto No. 244, publicado en el Periódico\nOficial No. 28, de fecha 09 de junio de 2018, Tomo CXXV, NÚMERO ESPECIAL, expedido por la H. XXII Legislatura, siendo Gobernador Constitucional el C. Francisco Arturo Vega de\nLamadrid 2013-2019;\nArtículo 176.- Fue reformado mediante Decreto No. 244, publicado en el Periódico\nOficial No. 28, de fecha 09 de junio de 2018, Tomo CXXV, NÚMERO ESPECIAL, expedido por la H. XXII Legislatura, siendo Gobernador Constitucional el C. Francisco Arturo Vega de\nLamadrid 2013-2019;\nArtículo 177.- Fue reformado mediante Decreto No. 244, publicado en el Periódico por la H. XXII Legislatura, siendo Gobernador Constitucional el C. Francisco Arturo Vega de\nLamadrid 2013-2019;\nArtículo 178.- Fue reformado mediante Decreto No. 244, publicado en el Periódico por la H. XXII Legislatura, siendo Gobernador Constitucional el C. Francisco Arturo Vega de\nLamadrid 2013-2019;\n.\nActualización Legislativa.\nÚltima reforma Gaceta No. 63, Especial, 14-Ago-2025\nARTICULO UNICO TRANSITORIO DEL DECRETO NO. 145, POR EL QUE SE\nREFORMAN LOS ARTICULOS 1, 17, 31, 36, 37, 39, 40, 40 BIS, 42, 55, 56, 57, 58, 59, 61,\n62, 65, 66, 76, 77, 79, 81, 83, 114 Y SE DEROGAN LOS ARTICULOS 64, 67; LA SECCION\n67BIS, 67TER; LA SECCION V DE LA DIRECCION DE PROGRAMACION Y GASTO\nINTERNO, 83 BIS, 83 TER, LA SECCION VI, DE LA DIRECCION DE COMUNICACIÓN\nSOCIAL, ARTICULOS 83 QUARTER, 83 QUINQUIES DEL CAPITULO III DEL TITULO\nSEXTO, PUBLICADA EN EL PERIODICO OFICIAL NO. 03, DE FECHA 14 DE ENERO DE\n2003, TOMO CX, NUMERO ESPECIAL, EXPEDIDO POR LA H. XVII LEGISLATURA,\nSIENDO GOBERNADOR CONSTITUCIONAL EL C. EUGENIO ELORDUY WALTHER 2001-\n2007.\nPRIMERO. Remítanse las presentes reformas, derogaciones y adiciones a la Ley\nOrgánica del Poder Legislativo de Baja California al Poder Ejecutivo del Gobierno del\nEstado, solicitando las inserte en el Periódico Oficial, órgano del Gobierno del Estado; entrando en vigor el día de su publicación.\nSEGUNDO. En los términos del artículo 34 párrafo segundo de la Constitución\nEstado que, por lo urgente del caso, el término que aprueba el Congreso para su derecho a observar se resuelve sea de tres días.\nTERCERO. Cualquier controversia que se origine en la interpretación de esta Ley y sus reformas, con anterioridad a la creación de los Reglamentos Interior y de Procedimientos y Prácticas Parlamentarias, se resolverán mediante la opinión que emita la Comisión de\nLegislación y Puntos Constitucionales misma que será sometida por la Comisión de\nRégimen Interno y Prácticas Parlamentarias al Pleno del Congreso del Estado, en los términos de la fracción V del artículo 59 de la Ley Orgánica del Poder Legislativo.\nDADO en el Salón de Sesiones “Lic. Benito Juárez García” del Honorable Poder\nLegislativo, en la Ciudad de Mexicali, Baja California, a los nueve días del mes de enero del año dos mil tres.\nDIP. MARIA ROSALBA MARTIN NAVARRO\nPRESIDENTA\nDIP. JUAN MANUAL SALAZAR CASTRO\nSECRETARIO\nDE CONFORMIDAD CON LO DISPUESTO POR LA FRACCION I DEL ARTCIULO 49\nDE LA CONSTITUCION POLITICA DEL ESTADO, MANDO SE IMPRIMA Y PUBLIQUE.\nMEXICALI, BAJA CALIFORNIA, A LOS DIEZ DIAS DEL MES DE ENERO DEL AÑO\n.\nActualización Legislativa.\nÚltima reforma Gaceta No. 63, Especial, 14-Ago-2025\nDOS MIL TRES.\nGOBERNADOR DEL ESTADO.\nEUGENIO ELORDUY WALTHER.\n(RÚBRICA)\nSECRETARIO GENERAL DE GOBIERNO\nBERNARDO H. MARTINEZ AGUIRRE.\n(RÚBRICA)\nARTICULO UNICO TRANSITORIO DEL DECRETO NO. 150, POR EL QUE SE\nREFORMAN LOS ARTICULOS 10, 42, 56, 57, 59, 60, 62, 65, 67BIS, 67 TER, 81, 156 Y\n157, Y SE DEROGA EL ARTICULO 66, PUBLICADO EN EL PERIODICO OFICIAL NO. 06,\nDE FECHA 31 DE ENERO DE 2003, SECCION II, TOMO CX, EXPEDIDO POR LA H. XVII\nLEGISLATURA, SIENDO GOBERNADOR CONSTITUCIONAL EL C. EUGENIO ELORDUY\nWALTHER 2001-2007.\nPRIMERO. Las presentes reformas entrarán en vigor al día siguiente de su publicación en el Periódico Oficial del Estado de Baja California.\nSEGUNDO. En los términos del artículo 34, párrafo segundo de la Constitución que por la urgencia del caso, el término que aprueba el Congreso para su derecho a observar las presentes reformas, se resuelve sea de tres días.\nTERCERO. Dentro de los ciento ochenta días siguientes a la entrada en vigor de las presentes reformas, el Congreso del Estado aprobará los Reglamentos a que se refiere la\nLey Orgánica del Poder Legislativo del Estado de Baja California.\nDADO en el Salón de Sesiones “Lic. Benito Juárez García” del Honorable Poder\nLegislativo, en la Ciudad de Mexicali, Baja California, a los veinte días del mes de enero del año dos mil tres.\nDIP. MARIA ROSALBA MARTIN NAVARRO\nPRESIDENTA\nDIP. JUAN MANUEL SALAZAR CASTRO\nSECRETARIO\nDE CONFORMIDAD CON LO DISPUESTO POR LA FRACCION I DEL ARTICULO 49\nDE LA CONSTITUCION POLITICA DEL ESTADO, MANDO SE IMPRIMA Y PUBLIQUE.\n.\nActualización Legislativa.\nÚltima reforma Gaceta No. 63, Especial, 14-Ago-2025\nMEXICALI, BAJA CALIFORNIA, A LOS VEINTICUATRO DIAS DEL MES DE ENERO\nDEL AÑO DOS MIL TRES.\nGOBERNADOR DEL ESTADO\nEUGENIO ELORDUY WALTHER\n(RÚBRICA)\nSECRETARIO GENERAL DE GOBIERNO\nBERNARDO H. MARTINEZ AGUIRRE\n(RÚBRICA)\nFE DE ERRATAS AL DECRETO NO. 145, POR EL QUE SE MODIFICAN LOS\nARTICULOS 39, 40, 40BIS, 67 TER Y 77, PUBLICADO EN EL PERIODICO OFICIAL NO.\n09, DE FECHA 21 DE FEBRERO DE 2003, TOMO CX, EXPEDIDA POR LA H. XVII\nLEGISLATURA, SIENDO GOBERNADOR CONSTITUCIONAL EL C. EUGENIO ELORDUY\nWALTHER 2001-2007.\nATENTAMENTE\nSUFRAGIO EFECTIVO. NO REELECCION.\nMexicali, B.C., a 04 de febrero de 2003.\nDIP. LAURA SANCHEZ MEDRANO\nPRESIDENTA\n(RÚBRICA)\nDIP. JESUS ALEJANDRO RUIZ URIBE\nSECRETARIO\n(RÚBRICA)\nARTICULO UNICO TRANSITORIO DEL DECRETO NO. 2, POR EL QUE SE\nREFORMAN LOS ARTICULOS 6; 7; 8; 9; 11; 12; 18 FRACCIONES VIII, IX Y X; 19; 20; 21;\nFRACCIÓN III A LA VI; 57 PRIMER PÁRRAFO; 58 PRIMER PÁRRAFO; 59; 61 FRACCIÓN\nII; 62 FRACCIONES VIII, XIII, XIV, XV, XVI, XVII; 64; 65 PARRAFOS PRIMERO,\nANTEPENÚLTIMO Y ULTIMO; 66; 67; 77 PÁRRAFOS PRIMERO Y TERCERO; 80; 81; 82;\n83 PARRAFOS PRIMERO Y TERCERO; 83 TER PARRAFOS PRIMERO Y TERCERO; 83\nQUINQUIES PÁRRAFOS PRIMERO Y TERCERO; 84; 85; 86; 87; 88 PÁRRAFOS\nPRIMERO Y TERCERO; 89; 94 PRIMER PARRAFO; 95; 96 PRIMER PARRAFO; 98\nPRIMER PARRAFO; 100 SEGUNDO PARRAFO; 101 FRACCION I; 144 PRIMER\nPARRAFO, 166 Y 168, ASÍ COMO LA DENOMINACION DEL CAPITULO CUARTO DEL\n.\nActualización Legislativa.\nÚltima reforma Gaceta No. 63, Especial, 14-Ago-2025\nTITULO SEXTO; QUE ADICIONA EL PARRAFO SEXTO AL ARTÍCULO 9; LA FRACCIÓN\nXI AL ARTÍCULO 18; LOS PÁRRAFOS TERCERO Y CUARTO AL ARTICULO 55; LA\nFRACCION IV AL ARTICULO 61; LA FRACCION XVIII AL ARTICULO 62; LOS ARTICULOS\n87 BIS, 87 TER, 87 QUARTER, 87 QUINQUIES Y, EL PARRAFO CUARTO AL ARTICULO\n88; QUE DEROGA LA FRACCION II DEL ARTICULO 40; LOS ARTICULOS 67 BIS; 67 TER;\n78; 79; 81 BIS; 81 TER Y 81 QUARTER; PUBLICADO EN EL PERIODICO OFICIAL NO. 50,\nDE FECHA 19 DE NOVIEMBRE, SECCION II, TOMO CXI, EXPEDIDO POR LA H. XVIII\nLEGISLATURA, SIENDO GOBERNADOR CONSTITUCIONAL EL C. EUGENIO ELORDUY\nWALTHER 2001-2007.\nPRIMERO. Las presentes reformas entrarán en vigor al día siguiente de su publicación en el Periódico Oficial del Estado de Baja California.\nSEGUNDO. Cuando en otras Leyes se aluda a Comisiones del Congreso del Estado y que con motivo de las presentes reformas cambien de denominación o se otorgue intervención a otra diversa, aquéllas se tendrán sustituidas por estas últimas.\nCuando en otras Leyes se señalen requisitos y procedimientos de designaciones o nombramientos de servidores públicos por parte del Congreso del Estado, se estará a lo señalado en ellas, en lo que no contravengan las disposiciones contenidas en la presente reforma.\nTERCERO. Dentro de los ciento ochenta días siguientes a la entrada en vigor de las presentes reformas, el Congreso del Estado, realizará las adecuaciones a otras Leyes sobre las que tengan incidencia.\nCUARTO. A la entrada en vigor de estas reformas, y por única ocasión, el Congreso del Estado, mediante la mayoría absoluta de sus integrantes, podrá remover y nombrar a los titulares de los órganos TécnicoAdministrativos, señalados en el artículo 40 de esta Ley.\nEfectuado lo anterior, en los casos subsecuentes y hasta el 30 de Septiembre del año 2007, el Congreso del Estado mediante mayoría calificada, podrá remover o nombrar a los titulares de los órganos TécnicoAdministrativo.\nQUINTO. Por única ocasión, a partir de la entrada en vigor de las presentes reformas y hasta el día 30 de Septiembre del año 2007, la Comisión de Legislación y Puntos\nConstitucionales se integrará por siete miembros.\nDADO en el Salón de Sesiones “Lic. Benito Juárez García” del Honorable Poder\nLegislativo, en la Ciudad de Mexicali, Baja California, a los dos días del mes de noviembre del año dos mil cuatro.\nDIP. GUILLERMO ALDRETE HAAS\nPRESIDENTE\n.\nActualización Legislativa.\nÚltima reforma Gaceta No. 63, Especial, 14-Ago-2025\nDIP. ELVIRA LUNA PINEDA\nSECRETARIA\n(RÚBRICA)\nDE CONFORMIDAD CON LO DISPUESTO POR LA FRACCION I DEL ARTICULO 49\nDE LA CONSTITUCION POLITICA DEL ESTADO, IMPRIMASE Y PUBLIQUESE.\nMEXICALI, BAJA CALIFORNIA, A LOS QUINCE DIAS DEL MES DE NOVIEMBRE\nDEL AÑO DOS MIL CUATRO.\nGOBERNADOR DEL ESTADO\nEUGENIO ELORDUY WALTHER\n(RÚBRICA)\nSECRETARIO GENERAL DE GOBIERNO\nBERNARDO H. MARTINEZ AGUIRRE\n(RÚBRICA)\nARTICULO UNICO TRANSITORIO DEL DECRETO NO. 42, POR EL QUE SE\nREFORMAN LOS ARTICULOS 27 PARRAFO SEGUNDO Y 59 PARRAFO SEGUNDO,\nFRACCIONES II Y X, PUBLICADO EN EL PERIODICO OFICIAL NO. 5, DE FECHA 28 DE\nENERO DE 2005, TOMO CXII, EXPEDIDO POR LA H. XVIII LEGISLATURA, SIENDO\nGOBERNADOR CONSTITUCIONAL EL C. EUGENIO ELORDUY WALTHER 2001-2007.\nUNICO. La presente reforma entrará en vigor al día siguiente de su publicación en el\nPeriódico Oficial del Estado de Baja California.\nDADO. En el Salón de Sesiones “Lic. Benito Juárez García” del Honorable Poder\nLegislativo, en la Ciudad de Mexicali, Baja California, a los siete días del mes de enero del año dos mil cinco.\nDIP. GUILLERMO ALDRETE HAAS\nPRESIDENTE\nDIP. ELVIRA LUNA PINEDA\nSECRETARIA\nDE CONFORMIDAD CON LO DISPUESTO POR LA FRACCION I DEL ARTICULO 49\nDE LA CONSTITUCION POLITICA DEL ESTADO, IMPRIMASE Y PUBLIQUESE.\n.\nActualización Legislativa.\nÚltima reforma Gaceta No. 63, Especial, 14-Ago-2025\nMEXICALI, BAJA CALIFORNIA, A LOS VEINTIUN DIAS DEL MES DE ENERO DEL\nAÑO DOS MIL CINCO.\nGOBERNADOR DEL ESTADO\nEUGENIO ELORDUY WALTHER\n(RÚBRICA)\nSECRETARIO GENERAL DE GOBIERNO\nBERNARDO H. MARTINEZ AGUIRRE\n(RÚBRICA)\nARTICULO UNICO TRANSITORIO DEL DECRETO NO. 249, POR EL QUE SE\nREFORMAN LOS ARTICULOS 117 Y 118, PUBLICADO EN EL PERIODICO OFICIAL NO.\n46, DE FECHA 03 DE NOVIEMBRE DE 2006, TOMO CXIII, EXPEDIDO POR LA H. XVIII\nLEGISLATURA, SIENDO GOBERNADOR CONSTITUCIONAL EL C. EUGENIO ELORDUY\nWALTHER 2001-2007.\nLas presentes reformas entrarán en vigor al día siguiente de su publicación en el\nPeriódico Oficial del Estado de Baja California.\nDADO en el Salón de Sesiones “Lic. Benito Juárez García” del Honorable Poder\nLegislativo, en la Ciudad de Mexicali, Baja California, a los cinco días del mes de octubre del año dos mil seis.\nDIP. RICARDO MAGAÑA MOSQUEDA\nPRESIDENTE\n(RÚBRICA)\nDIP. CARLOS ALBERTO MONTAÑO QUINTANA\nSECRETARIO\nDE CONFORMIDAD CON LO DISPUESTO POR LA FRACCION I DEL ARTICULO 49\nDE LA CONSTITUCION POLITICA DEL ESTADO, IMPRIMASE Y PUBLIQUESE.\nMEXICALI, BAJA CALIFORNIA, A LOS DIECISIETE DIAS DEL MES DE OCTUBRE\nDEL AÑO DOS MIL SEIS.\nGOBERNADOR DEL ESTADO\nEUGENIO ELORDUY WALTHER\n.\nActualización Legislativa.\nÚltima reforma Gaceta No. 63, Especial, 14-Ago-2025\nSECRETARIO GENERAL DE GOBIERNO\nBERNARDO H. MARTINEZ AGUIRRE\n(RÚBRICA)\nARTICULOS TRANSITORIO DEL DECRETO No. 126, POR EL QUE SE APRUEBA\nREFORMA A LOS ARTÍCULOS 101 Y 107, PUBLICADO EN EL PERIODICO OFICIAL NO.\n48, DE FECHA 30 DE SEPTIEMBRE DE 2008, TOMO CXV, EXPEDIDO POR LA H. XIX\nLEGISLATURA, SIENDO GOBERNADOR CONSTITUCIONAL EL C. JOSE GUADALUPE\nOSUNA MILLAN 2007-2013.\nARTÍCULO TRANSITORIO\nÚNICO. Las presentes reformas entrarán en vigor al día siguiente de su publicación en el Periódico Oficial del Estado de Baja California.\nDADO en el Salón de Sesiones “Lic. Benito Juárez García” del H. Poder Legislativo del Estado de Baja California, en la Ciudad de Mexicali, B.C., a los veintinueve días del mes de septiembre del año dos mil ocho.\nDIP. HÉCTOR HUMBERTO LÓPEZ BARRAZA\nPRESIDENTE\n(RÚBRICA)\nDIP. JORGE CASILLAS ARIAS\nSECRETARIO\n(RÚBRICA)\nDE CONFORMIDAD CON LO DISPUESTO POR LA FRACCION I DEL ARTICULO 49\nDE LA CONSTITUCION POLITICA DEL ESTADO, IMPRIMASE Y PUBLIQUESE.\nMEXICALI, BAJA CALIFORNIA, A LOS TREINTA DIAS DEL MES DE SEPTIEMBRE\nDEL AÑO DOS MIL OCHO.\nGOBERNADOR DEL ESTADO\nJOSE GUADALUPE OSUNA MILLAN\nSECRETARIO GENERAL DE GOBIERNO\nJOSE FRANCISCO BLAKE MORA\nARTICULO TERCERO TRANSITORIO DEL DECRETO No. 176, POR EL QUE SE\n.\nActualización Legislativa.\nÚltima reforma Gaceta No. 63, Especial, 14-Ago-2025\nAPRUEBA REFORMA A LOS ARTÍCULOS 59 Y 62, DE FECHA 26 DE DICIEMBRE DE\n2008, TOMO CXV, EXPEDIDO POR LA H. XIX LEGISLATURA, SIENDO GOBERNADOR\nCONSTITUCIONAL EL C. JOSE GUADALUPE OSUNA MILLAN 2007-2013.\nTRANSITORIOS\nPRIMERO. Córrase el trámite que señala el artículo 112 de la Constitución Política del\nEstado, enviándose las presentes reformas a los artículos 27 y 49 de la Constitución Política del Estado a los Ayuntamientos del Estado, para que emitan su opinión en los términos de\nLey.\nSEGUNDO. Agotado el trámite y pronunciada la declaratoria señalada en el artículo\nCalifornia, artículo 8° de la Ley Orgánica de la Procuraduría General de Justicia del Estado y fracción VI del párrafo Cuarto del artículo 59 y fracción XIII del artículo 62 de la Ley\nOrgánica del Poder Legislativo del Estado de Baja California, por parte de la Presidencia de este Congreso al Poder Ejecutivo para su publicación.\nTERCERO. Las presentes reformas entrarán en vigor al día siguiente de su publicación en el Periódico Oficial del Estado de Baja California.\nDADO en el Salón de Sesiones “Lic. Benito Juárez García” del H. Poder Legislativo del Estado de Baja California, en la Ciudad de Mexicali, B.C., a los cuatro días del mes de diciembre del año dos mil ocho.\nDIP. GINA ANDREA CRUZ BLACKLEDGE\nPRESIDENTA\n(RÚBRICA)\nDIP. JUAN MANUEL MOLINA GARCÍA\nSECRETARIO\nDE CONFORMIDAD CON LO DISPUESTO POR LA FRACCION I DEL ARTICULO 49\nDE LA CONSTITUCION POLITICA DEL ESTADO, IMPRIMASE Y PUBLIQUESE.\nMEXICALI, BAJA CALIFORNIA, A LOS DIECIOCHO DIAS DEL MES DE\nDICIEMBRE DEL AÑO DOS MIL OCHO.\nGOBERNADOR DEL ESTADO\nJOSE GUADALUPE OSUNA MILLAN\nSECRETARIO GENERAL DE GOBIERNO\n.\nActualización Legislativa.\nÚltima reforma Gaceta No. 63, Especial, 14-Ago-2025\nJOSE FRANCISCO BLAKE MORA\n(RÚBRICA)\nARTICULO PRIMERO TRANSITORIO DEL DECRETO No. 316, POR EL QUE SE\nAPRUEBA REFORMA A LOS ARTÍCULOS 40 BIS Y 88, DE FECHA 18 DE DICIEMBRE DE\n2009, TOMO CXVI, EXPEDIDO POR LA H. XIX LEGISLATURA, SIENDO GOBERNADOR\nCONSTITUCIONAL EL C. JOSE GUADALUPE OSUNA MILLAN 2007-2013.\nTRANSITORIOS\nÚNICO. Las presentes Reformas entrarán en vigor al día siguiente de su publicación en el Periódico Oficial del Estado de Baja California.\nDADO en el Salón de Sesiones “Lic. Benito Juárez García” del H. Poder Legislativo del Estado de Baja California, en la ciudad de Mexicali, B.C., a los treinta días del mes de noviembre de dos mil nueve.\nDIP. ANTONIO RICARDO CANO JIMÉNEZ\nPRESIDENTE\n(RÚBRICA)\nDIP. RUBÉN ERNESTO ARMENTA ZANABIA\nSECRETARIO\n(RÚBRICA)\nDE CONFORMIDAD CON LO DISPUESTO POR LA FRACCION I DEL ARTICULO 49\nDE LA CONSTITUCION POLITICA DEL ESTADO, IMPRIMASE Y PUBLIQUESE.\nMEXICALI, BAJA CALIFORNIA, A LOS TRES DIAS DEL MES DE DICIEMBRE DEL\nAÑO DOS MIL NUEVE.\nGOBERNADOR DEL ESTADO\nJOSE GUADALUPE OSUNA MILLAN\nSECRETARIO GENERAL DE GOBIERNO\nJOSE FRANCISCO BLAKE MORA\n.\nActualización Legislativa.\nÚltima reforma Gaceta No. 63, Especial, 14-Ago-2025\nARTÍCULO ÚNICO TRANSITORIO DEL DECRETO NO. 387, POR EL QUE SE\nAPRUEBAN LAS REFORMAS A LOS ARTICULOS 10, 17, 18, 31 Y 59 Y SE ADICIONA UN\nCAPÍTULO SEGUNDO AL TITULO CUARTO BAJO LA DENOMINACIÓN “DEL PLAN DE\nDESARROLLO LEGISLATIVO”, DICHO CAPITULO SE INTEGRARÁ POR LOS\nARTICULOS 16 BIS, 16 TER Y 16 QUARTER, PUBLICADO EN EL PERIODICO OFICIAL\nNo. 29, TOMO CXVII, SECCION I, DE FECHA 7 DE FEBRERO DE 2010, EXPEDIDO POR\nLA XIX LEGISLATURA DEL ESTADO, SIENDO GOBERNADOR CONSTITUCIONAL EL C.\nJOSE GUADALUPE OSUNA MILLAN 2007-2013.\nPRIMERO. Las presentes reformas entrarán en vigor el día siguiente al de su publicación en el Periódico Oficial del Estado de Baja California.\nSEGUNDO. Se derogan todas aquellas disposiciones que se opongan a las presentes reformas y continúan vigentes los actos, resoluciones, acuerdos y demás disposiciones de carácter general emitidas con fundamento en la Ley que se reforma.\nDADO en el Salón de Sesiones “Lic. Benito Juárez García” del H. Poder Legislativo del\nEstado de Baja California, en la Ciudad de Mexicali, B.C., a los quince días del mes de junio de dos mil diez.\nDIP. ÓSCAR R. MARTÍNEZ GARZA\nPRESIDENTE\n(RÚBRICA)\nDIP. JUAN MANUEL MOLINA GARCÍA\nSECRETARIO\n(RÚBRICA)\nDE CONFORMIDAD CON LO DISPUESTO POR LA FRACCIÓN I DEL ARTÍCULO 49\nMEXICALI, BAJA CALIFORNIA, A LOS VEINTIOCHO DÍAS DEL MES DE JUNIO DEL\nAÑO DOS MIL DIEZ.\nGOBERNADOR DEL ESTADO.\nJOSÉ GUADALUPE OSUNA MILLÁN.\nSECRETARIO GRENERAL DE GOBIERNO\nJOSÉ FRANCISCO BLAKE MORA\n.\nActualización Legislativa.\nÚltima reforma Gaceta No. 63, Especial, 14-Ago-2025\nARTÍCULO UNICO TRANSITORIO, POR EL QUE SE REFORMA LOS ARTÍCULOS\n10, 13 FRACCIÓN III, 16 BIS, 16 QUARTER FRACCIÓN I, III, IV Y V, 23, 31 FRACCIÓN II,\nIII Y IV, 34, 36, 37, 38, 40, 41, 42, 55, 56, 57, 60, 62, 63, 64, 65 FRACCIÓN II Y III, 66, 67,\n69, 72, 76, 77, 80, 81, 82 FRACCIÓN I Y II, 83, 83 TER, 83 QUATER, 83 QUINQUIES, 91,\n92, 96, 110, 113, 114, 115, 118, 120, 168, LA DENOMINACIÓN DEL CAPÍTULO III Y LAS\nSECCIONES I, IV, VI, Y LA DENOMINACIÓN DEL TÍTULO OCTAVO; SE ADICIONAN LOS\nNUEVOS ARTÍCULOS 53 BIS, 77 BIS, 77 TER, 83 SEXIES, 169 BIS, 171 Y 172, LA\nSECCIÓN VII DEL CAPÍTULO III Y EL TÍTULO IX; Y, SE DEROGAN LOS ARTÍCULOS 58,\n59, 61 Y 108, APROBADO EL DÍA 02 DE OCTUBRE DEL AÑO 2010.\nARTÍCULOS TRANSITORIOS\nPRIMERO. Se derogan las disposiciones que contravengan el presente Decreto.\nSEGUNDO. Toda vez que las presentes reformas solo implican modificaciones al régimen interno del Poder Legislativo, entrarán en vigor al momento de su aprobación por el\nPleno del Congreso del Estado y se publicarán en La Gaceta del Poder Legislativo.\nTERCERO. Los Órganos de Apoyo Parlamentario y Administrativo que se agregan a la Estructura Orgánica del Poder Legislativo, iniciarán sus funciones conforme lo permita la disponibilidad presupuestal del Congreso del Estado de Baja California. Corresponderá a la\nComisión de Administración y Finanzas la asignación de los recursos que se requieran para su adecuado funcionamiento.\nHOJA DE FIRMAS\nINICIATIVA POR LA QUE SE REFORMAN, ADICIONAN Y DEROGAN DIVERSAS\nDISPOSICIONES A LA LEY ORGÁNICA DEL PODER LEGISLATIVO DEL ESTADO DE\nBAJA CALIFORNIA, QUE PRESENTAN LEGISLADORES INTEGRANTES DE LA XX\nLEGISLATURA DEL CONGRESO DEL ESTADO DE BAJA CALIFORNIA.\nDIP. JULIO FELIPE GARCÍA MUÑOZ\nDIP. VICTOR HUGO NAVARRO GUTIÉRREZ\nDIP. NANCY GUADALUPE SÁNCHEZ ARREDONDO\nDIP. JUAN BAUTISTA MONTEJANO DE LA TORRE\nDIP. ELÍ TOPETE ROBLES\n.\nActualización Legislativa.\nÚltima reforma Gaceta No. 63, Especial, 14-Ago-2025\nDIP.VIRGINIA NORIEGA RÍOS\n(RÚBRICA)\nDIP. JUAN VARGAS RODRÍGUEZ\n(RÚBRICA)\nDIP. DAVID LOZANO PÉREZ\n(RÚBRICA)\nDIP. FAUSTO ZARATE ZEPEDA\n(RÚBRICA)\nDIP. CARLOS MURGUIA MEJÍA\n(RÚBRICA)\nDIP. LAURENCIO DADO ALATORRE\n(RÚBRICA)\nDIP. GREGORIO BARRETO LUNA\n(RÚBRICA)\nDIP. MARCOVIZCARRA CALDERÓN\n(RÚBRICA)\nDIP. ALFONSO GARZÓN ZATARAIN\n(RÚBRICA)\nDIP. ELISA ROSANA SOTO AGÜERO\n(RÚBRICA)\nDIP. CLAUDIA JOSEFINA AGATÓN MUÑIZ\nDIP. FRANCISCO JAVIER SÁNCHEZ CORONA\nDIP. GREGORIO CARRANZA HERNÁNDEZ\nDIP. ARCELIA GALARZA VILLARINO\nDIP. MARÍA DEL ROSARIO RODRÍGUEZ RUBIO\n.\nActualización Legislativa.\nÚltima reforma Gaceta No. 63, Especial, 14-Ago-2025\n(RÚBRICA)\nDIP. RICARDO MAGAÑA MOSQUEDA\n(RÚBRICA)\nDIP. JOSÉ MÁXIMO GARCÍALÓPEZ\n(RÚBRICA)\nDIP. LIZBETH MATA LOZANO\n(RÚBRICA)\nDIP. RUBÉN ALANÍS QUINTERO\n(RÚBRICA)\nDIP. GUSTAVO MAGLLANES CORTÉS\n(RÚBRICA)\nARTICULO UNICO TRANSITORIO DEL DECRETO NO. 11, POR EL QUE SE\nAPRUEBA REFORMA LA DENOMINACIÓN DE LA SECCIÓN VI Y VII DEL CAPÍTULO III,\nTÍTULO SEXTO, LOS ARTÍCULOS 10, 16 BIS, 18, 37, 38, 40, 56, 60, 65, 83 SEXIES, 88,\n93, 94 SEGUNDO PÁRRAFO, 95 SEGUNDO PÁRRAFO, 118, 119,126, 127, 144, 151, 156,\n157; SE DEROGA EL SEGUNDO PÁRRAFO DEL ARTÍCULO 83 QUATER, Y LOS\nPÁRRAFOS 6º, 7º, 8º Y 9º DEL ARTÍCULO 83 QUINQUIES, PUBLICADO EN EL\nPERIODICO OFICIAL NO. 56, TOMO CXVII, SECCION III, DE FECHA 17 DE DICIEMBRE\nDE 2010, EXPEDIDO POR LA H. XX LEGISLATURA, SIENDO GOBERNADOR\nCONSTITUCIONAL EL C. JOSE GUADALUPE OSUNA MILLAN 2007-2013.\nARTÍCULOS TRANSITORIOS\nPRIMERO. Se derogan todas las disposiciones que contravengan al presente\nDecreto.\nSEGUNDO. Publíquense las presentes Reformas en el Periódico Oficial del Estado de\nBaja California.\nTERCERO. Las reformas al artículo 88 contenidas en el presente Decreto entrarán en vigor hasta en tanto sean aprobadas las reformas al artículo 22 de la Constitución Política en el artículo 112 constitucional.\n.\nActualización Legislativa.\nÚltima reforma Gaceta No. 63, Especial, 14-Ago-2025\nDADO en el Salón de Sesiones “Lic. Benito Juárez García” del H. Poder Legislativo del Estado de Baja California, en la Ciudad de Mexicali, B.C., a los dos días del mes de diciembre del año dos mil diez.\nDIP. NANCY G. SÁNCHEZ ARREDONDO\nPRESIDENTA\n(RÚBRICA)\nDIP. CLAUDIA JOSEFINA AGATÓN MUÑIZ\nSECRETARIA\n(RÚBRICA)\nDE CONFORMIDAD CON LO DISPUESTO POR LA FRACCION I DEL ARTÍCULO 49\nMEXICALI, BAJA CALIFORNIA, A LOS QUINCE DÍAS DEL MES DE DICIEMBRE\nDEL AÑO DOS MIL DIEZ.\nGOBERNADOR DEL ESTADO\nJOSE GUADALUPE OSUNA MILLAN\n(RÚBRICA)\nSECRETARIO GENERAL DE GOBIERNO\nCUAUHTEMOC CARDONA BENAVIDES\n(RÚBRICA)\nARTICULO UNICO TRANSITORIO DEL DECRETO NO. 35, POR EL QUE SE\nREFORMA EL NUMERAL 9 DEL ARTÍCULO 56 Y EL INCISO F) PÁRRAFO TERCERO DEL\nARTÍCULO 60, PUBLICADO EN EL PERIODICO OFICIAL NO. 12, TOMO CXVIII, SECCION\nSIENDO GOBERNADOR CONSTITUCIONAL EL C. JOSE GUADALUPE OSUNA MILLAN\n2007-2013.\nARTÍCULO TRANSITORIO\nPRIMERO. La presente Reforma entrará en vigor al día siguiente de su aprobación por el Pleno del Congreso.\nSEGUNDO. Túrnese la presente reforma al Periódico Oficial del Estado de Baja\nCalifornia, para su publicación.\n.\nActualización Legislativa.\nÚltima reforma Gaceta No. 63, Especial, 14-Ago-2025\nDADO en el Salón de Sesiones “Lic. Benito Juárez García” del H. Poder Legislativo del Estado de Baja California, en la Ciudad de Mexicali, B.C., a los nueve días del mes de febrero del año dos mil once.\nDIP. MARCO ANTONIO VIZCARRA CALDERÓN\nPRESIDENTE\n(RÚBRICA)\nDIP. LAURENCIO DADO ALATORRE\nSECRETARIO\n(RÚBRICA)\nDE CONFORMIDAD CON LO DISPUESTO POR LA FRACCION I DEL ARTÍCULO 49\nMEXICALI, BAJA CALIFORNIA, A LOS CATORCE DÍAS DEL MES DE FEBRERO\nDEL AÑO DOS MIL ONCE.\nGOBERNADOR DEL ESTADO\nJOSE GUADALUPE OSUNA MILLAN\n(RÚBRICA)\nSECRETARIO GENERAL DE GOBIERNO\nCUAUHTEMOC CARDONA BENAVIDES\n(RÚBRICA)\nARTICULO PRIMERO TRANSITORIO DEL DECRETO NO. 52, POR EL QUE SE\nREFORMAN LOS ARTICULOS 11, 37, 55, 88 Y 117, PUBLICADO EN EL PERIODICO\nEXPEDIDO POR LA H. XX LEGISLATURA, SIENDO GOBERNADOR CONSTITUCIONAL\nEL C. JOSE GUADALUPE OSUNA MILLAN 2007-2013.\nARTÍCULO TRANSITORIO\nPRIMERO. Se derogan las disposiciones que contravengan el presente Decreto.\nSEGUNDO. Las presentes reformas entrarán en vigor al momento de su aprobación\nCalifornia, \"Órgano del Gobierno Constitucional del Estado de Baja California\".\n.\nActualización Legislativa.\nÚltima reforma Gaceta No. 63, Especial, 14-Ago-2025\nDADO en el Salón de Sesiones “Lic. Benito Juárez García” del H. Poder Legislativo del Estado de Baja California, en la Ciudad de Mexicali, B.C., a los cuatro días del mes de mayo del año dos mil once.\nDIP. MARCO ANTONIO VIZCARRA CALDERÓN\nPRESIDENTE\n(RÚBRICA)\nDIP. LAURENCIO DADO ALATORRE\nSECRETARIO\n(RÚBRICA)\nDE CONFORMIDAD CON LO DISPUESTO POR LA FRACCION I DEL ARTÍCULO 49\nMEXICALI, BAJA CALIFORNIA, A LOS VEINTE DÍAS DEL MES DE MAYO DEL AÑO\nDOS MIL ONCE.\nGOBERNADOR DEL ESTADO\nJOSE GUADALUPE OSUNA MILLAN\n(RÚBRICA)\nSECRETARIO GENERAL DE GOBIERNO\nCUAUHTEMOC CARDONA BENAVIDES\n(RÚBRICA)\nARTICULO SEGUNDO TRANSITORIO DEL DECRETO NO. 52, POR EL QUE SE\nDEROGA EL CAPÍTULO IV, DENOMINADO “DE LA COMISIÓN PERMANENTE”, DEL\nTÍTULO SEXTO, Y LOS ARTÍCULOS 84, 85, 86, 87, 87 BIS, 87 TER, 87 QUARTER, 87\nQUINQUIES, PUBLICADO EN EL PERIODICO OFICIAL NO. 27, TOMO CXVIII, SECCION I,\nGOBERNADOR CONSTITUCIONAL EL C. JOSE GUADALUPE OSUNA MILLAN 2007-\n2013.\nARTÍCULO TRANSITORIO\nPRIMERO. Se derogan las disposiciones que contravengan el presente Decreto.\nSEGUNDO. Las presentes reformas entrarán en vigor al momento de su aprobación\nCalifornia, \"Órgano del Gobierno Constitucional del Estado de Baja California\".\n.\nActualización Legislativa.\nÚltima reforma Gaceta No. 63, Especial, 14-Ago-2025\nDADO en el Salón de Sesiones “Lic. Benito Juárez García” del H. Poder Legislativo del Estado de Baja California, en la Ciudad de Mexicali, B.C., a los cuatro días del mes de mayo del año dos mil once.\nDIP. MARCO ANTONIO VIZCARRA CALDERÓN\nPRESIDENTE\n(RÚBRICA)\nDIP. LAURENCIO DADO ALATORRE\nSECRETARIO\n(RÚBRICA)\nDE CONFORMIDAD CON LO DISPUESTO POR LA FRACCION I DEL ARTÍCULO 49\nMEXICALI, BAJA CALIFORNIA, A LOS VEINTE DÍAS DEL MES DE MAYO DEL AÑO\nDOS MIL ONCE.\nGOBERNADOR DEL ESTADO\nJOSE GUADALUPE OSUNA MILLAN\n(RÚBRICA)\nSECRETARIO GENERAL DE GOBIERNO\nCUAUHTEMOC CARDONA BENAVIDES\n(RÚBRICA)\nARTICULO UNICO TRANSITORIO DEL DECRETO No. 79, POR EL QUE SE\nAPRUEBA LA REFORMA AL ARTÍCULO 74, PUBLICADO EN EL PERIODICO OFICIAL\nNo. 34, TOMO CXVIII, DE FECHA 15 DE JULIO DE 2011, SECCION I, EXPEDIDO POR\nLA H. XX LEGISLATURA, SIENDO GOBERNADOR CONSTITUCIONAL EL C. JOSE\nGUADALUPE OSUNA MILLAN 2007-2013.\nARTÍCULO TRANSITORIO\nÚNICO. Las presentes reformas entrarán en vigor al momento de su aprobación por\nCalifornia, \"Órgano del Gobierno Constitucional del Estado de Baja California\". del Estado de Baja California, en la Ciudad de Mexicali, B.C., a los 22 días del mes de junio del año dos mil once.\n.\nActualización Legislativa.\nÚltima reforma Gaceta No. 63, Especial, 14-Ago-2025\nDIP. CARLOS MURGUÍA MEJÍA\nDIPUTADO PRESIDENTE\n(RÚBRICA)\nDIP. VIRGINIA NORIEGA RÍOS\nDIPUTADA SECRETARIA\n(RÚBRICA)\nDE CONFORMIDAD CON LO DISPUESTO POR LA FRACCION I DEL ARTÍCULO 49\nMEXICALI, BAJA CALIFORNIA, A LOS SIETE DÍAS DEL MES DE JULIO DEL AÑO\nDOS MIL ONCE.\nGOBERNADOR DEL ESTADO\nJOSE GUADALUPE OSUNA MILLAN\n(RÚBRICA)\nSECRETARIO GENERAL DE GOBIERNO\nCUAUHTEMOC CARDONA BENAVIDES\n(RÚBRICA)\nARTICULO UNICO TRANSITORIO DEL DECRETO No. 88, POR EL QUE SE\nAPRUEBA LA REFORMA AL ARTÍCULO 83 SEXIES, PUBLICADO EN EL PERIODICO\nOFICIAL No. 42, TOMO CXVIII, DE FECHA 02 DE SEPTIEMBRE DE 2011, SECCION II,\nEXPEDIDO POR LA H. XX LEGISLATURA, SIENDO GOBERNADOR CONSTITUCIONAL\nEL C. JOSE GUADALUPE OSUNA MILLAN 2007-2013.\nARTÍCULOS TRANSITORIOS\nPRIMERO. Dado que la presente reforma implica modificaciones a la Ley Orgánica momento de su aprobación por el pleno del Congreso del Estado.\nSEGUNDO. Se derogan todas las disposiciones normativas que contravengan el presente ordenamiento.\nTERCERO. Publíquese la presente reforma en el Periódico Oficial del Estado.\n.\nActualización Legislativa.\nÚltima reforma Gaceta No. 63, Especial, 14-Ago-2025\nDADO en el Salón de Sesiones “Lic. Benito Juárez García” del H. Poder Legislativo del Estado de Baja California, en la Ciudad de Mexicali, B.C., a los treinta y un días del mes de agosto del año dos mil once.\nDIP. CARLOS MURGUÍA MEJÍA\nDIPUTADO PRESIDENTE\n(RÚBRICA)\nDIP. VIRGINIA NORIEGA RÍOS\nDIPUTADA SECRETARIA\n(RÚBRICA)\nDE CONFORMIDAD CON LO DISPUESTO POR LA FRACCION I DEL ARTÍCULO 49\nMEXICALI, BAJA CALIFORNIA, AL PRIMER DÍA DEL MES DE SEPTIEMBRE DEL\nAÑO DOS MIL ONCE.\nGOBERNADOR DEL ESTADO\nJOSE GUADALUPE OSUNA MILLAN\n(RÚBRICA)\nSECRETARIO GENERAL DE GOBIERNO\nCUAUHTEMOC CARDONA BENAVIDES\n(RÚBRICA)\nARTICULO UNICO TRANSITORIO DEL DECRETO No. 172, POR EL QUE SE\nAPRUEBA LA REFORMA A LOS ARTÍCULOS 40; 65 SEGUNDO PÁRRAFO; 66\nSEGUNDO PÁRRAFO; 83 SEXIES Y 118 TERCER PÁRRAFO, SE DEROGA EL PÁRRAFO\nTERCERO DEL ARTÍCULO 65; LOS PÁRRAFOS DÉCIMO PRIMERO Y DÉCIMO QUINTO\nDEL ARTÍCULO 83 SEXIES, PUBLICADO EN EL PERIODICO OFICIAL No. 8, TOMO\nLEGISLATURA, SIENDO GOBERNADOR CONSTITUCIONAL EL C. JOSE GUADALUPE\nOSUNA MILLAN 2007-2013.\nARTÍCULOS TRANSITORIOS\nPRIMERO. Conforme a las facultades del Congreso del Estado que se establecen en de su publicación en el Periódico Oficial del Estado.\n.\nActualización Legislativa.\nÚltima reforma Gaceta No. 63, Especial, 14-Ago-2025\nSEGUNDO. Aprobadas las reformas que aquí se consignan, la Junta de Coordinación\nPolítica, deberá proponer al pleno del H. Congreso, a efecto de su correspondiente designación, a quien habrá de fungir como Director General del Instituto de Opinión\nCiudadana, Estudios Económicos y Sociales, en sustitución de los actuales titulares de los extintos Institutos, de Estudios de Economía y Finanzas Publicas y de Estudios sobre la\nOpinión Publica.\nTERCERO. A la entrada en vigor de las presentes reformas, cualquier inmueble, asignaciones presupuestales autorizadas, mobiliario, vehículos, instrumentos, aparatos, equipo de cómputo y comunicación, archivos y demás bienes que hayan estado asignados, respectivamente, al Instituto de Estudios de Economía y Finanzas Publicas y al Instituto de\nEstudios sobre la Opinión Publica, pasarán a ser parte integrante del patrimonio y presupuesto del Instituto de Opinión Ciudadana, Estudios Económicos y Sociales.\nCUARTO. Se derogan todas las disposiciones normativas que contravengan las presentes reformas.\nQUINTO. Publíquese en la Gaceta Parlamentaria y túrnese al Ejecutivo del Estado para su publicación en el Periódico Oficial del Estado.\nDADO en el Salón de Sesiones “Lic. Benito Juárez García” del H. Poder Legislativo del Estado de Baja California, en la Ciudad de Mexicali, B.C., a los diecisiete días del mes de enero del año dos mil doce.\nLIC. MÁXIMO GARCÍA LÓPEZ\nDIPUTADO PRESIDENTE\n(RÚBRICA)\nPROFR. ALFONSO GARZÓN ZATARAIN\nDIPUTADO SECRETARIO\n(RÚBRICA)\nDE CONFORMIDAD CON LO DISPUESTO POR LA FRACCION I DEL ARTÍCULO 49\nMEXICALI, BAJA CALIFORNIA, A LOS VEINTICUATRO DÍAS DEL MES DE ENERO\nDEL AÑO DOS MIL ONCE.\nGOBERNADOR DEL ESTADO\nJOSE GUADALUPE OSUNA MILLAN\nSECRETARIO GENERAL DE GOBIERNO\nCUAUHTEMOC CARDONA BENAVIDES\n.\nActualización Legislativa.\nÚltima reforma Gaceta No. 63, Especial, 14-Ago-2025\nARTICULO UNICO TRANSITORIO DEL DECRETO NO. 177, POR EL QUE SE\nADICIONA EL PÁRRAFO SÉPTIMO AL ARTÍCULO 77, PUBLICADO EN EL PERIODICO\nOFICIAL NO. 10, TOMO CXIX, SECCION I, DE FECHA 24 DE FEBRERO DE 2012,\nEXPEDIDO POR LA H. XX LEGISLATURA, SIENDO GOBERNADOR CONSTITUCIONAL\nEL C. JOSE GUADALUPE OSUNA MILLAN 2007-2013.\nARTÍCULOS TRANSITORIOS\nPrimero. La presente reforma entrará en vigor al momento de su aprobación por el\nPleno del Congreso del Estado.\nSegundo. Publíquese en la Gaceta del Poder Legislativo, Órgano Oficial de difusión del Congreso del Estado de Baja California.\nTercero. Remítase al Poder Ejecutivo del Estado para su publicación en el Periódico\nOficial del Estado.\nDADO en el Salón de Sesiones “Lic. Benito Juárez García” del H. Poder Legislativo del Estado de Baja California, en la Ciudad de Mexicali, B.C., a los ocho días del mes de febrero del año dos mil doce.\nLIC. DAVID JORGE LOZANO PÉREZ\nDIPUTADO PRESIDENTE\n(RÚBRICA)\nPROFR. ALFONSO GARZÓN ZATARAIN\nDIPUTADO SECRETARIO\n(RÚBRICA)\nDE CONFORMIDAD CON LO DISPUESTO POR LA FRACCION I DEL ARTÍCULO 49\nMEXICALI, BAJA CALIFORNIA, A LOS CATORCE DÍAS DEL MES DE FEBRERO\nDEL AÑO DOS MIL DOCE.\nGOBERNADOR DEL ESTADO\nJOSE GUADALUPE OSUNA MILLAN\nSECRETARIO GENERAL DE GOBIERNO\nCUAUHTEMOC CARDONA BENAVIDES\n.\nActualización Legislativa.\nÚltima reforma Gaceta No. 63, Especial, 14-Ago-2025\nARTÍCULO ÚNICO TRANSITORIO DEL DECRETO NO. 199, POR EL QUE SE\nREFORMA A LOS ARTÍCULO 131, 132 Y 134 PUBLICADO EN EL PERIÓDICO OFICIAL\nNo. 25, TOMO CXIX, DE FECHA 01 DE JUNIO DE 2012, EXPEDIDO POR LA H. XX\nLEGISLATURA, SIENDO GOBERNADOR CONSTITUCIONAL EL C. JOSÉ GUADALUPE\nOSUNA MILLÁN 2007-2013.\nARTÍCULOS TRANSITORIOS\nPRIMERO. La presente reforma entrará en vigor al momento de su aprobación por el\nPleno del Congreso del Estado de Baja California.\nSEGUNDO. Publíquese en el Periódico Oficial del Estado y en la Gaceta\nParlamentaria del Congreso del Estado de Baja California.\nDADO en el Salón de Sesiones “Lic. Benito Juárez García” del H. Poder Legislativo del Estado de Baja California, en la Ciudad de Mexicali, B.C., a los tres días del mes de mayo del año dos mil doce.\nLIC. DAVID JORGE LOZANO PÉREZ\nDIPUTADO PRESIDENTE\n(RÚBRICA)\nPROFR. ALFONSO GARZÓN ZATARAIN\nDIPUTADO SECRETARIO\n(RÚBRICA)\nDE CONFORMIDAD CON LO DISPUESTO POR LA FRACCIÓN I DEL ARTÍCULO 49\nMEXICALI, BAJA CALIFORNIA, A LOS QUINCE DÍAS DEL MES DE MAYO DEL\nAÑO DOS MIL DOCE.\nGOBERNADOR DEL ESTADO\nJOSÉ GUADALUPE OSUNA MILLÁN\nSECRETARIO GENERAL DE GOBIERNO\nCUAUHTEMOC CARDONA BENAVIDES\nARTÍCULO ÚNICO TRANSITORIO DEL DECRETO No. 251, POR EL QUE SE\nREFORMA EL ARTÍCULO 77, PUBLICADO EN EL PERIÓDICO OFICIAL No. 38, TOMO\n.\nActualización Legislativa.\nÚltima reforma Gaceta No. 63, Especial, 14-Ago-2025\nLEGISLATURA, SIENDO GOBERNADOR CONSTITUCIONAL EL C. JOSÉ GUADALUPE\nOSUNA MILLÁN 2007-2013.\nARTÍCULOS TRANSITORIOS\nPRIMERO. La presente reforma entrará en vigor al momento de su aprobación por el\nPleno del Congreso del Estado.\nSEGUNDO. Publíquese en la Gaceta del Poder Legislativo, Órgano Oficial de difusión del Congreso del Estado de Baja California.\nTERCERO. Remítase al Poder Ejecutivo del Estado para su publicación en el\nPeriódico Oficial del Estado.\nDADO en el Salón de Sesiones “Lic. Benito Juárez García” del H. Poder Legislativo del Estado de Baja California, en la Ciudad de Mexicali, B.C., a los treinta y un días del mes de julio del año dos mil doce.\nDIP. ALFONSO GARZÓN ZATARAIN\nDIPUTADO PRESIDENTE\n(RÚBRICA)\nDIP. FAUSTO ZÁRATE ZEPEDA\nDIPUTADO SECRETARIO\n(RÚBRICA)\nDE CONFORMIDAD CON LO DISPUESTO POR LA FRACCIÓN I DEL ARTÍCULO 49\nMEXICALI, BAJA CALIFORNIA, A LOS CATORCE DÍAS DEL MES DE AGOSTO\nDEL AÑO DOS MIL DOCE.\nGOBERNADOR DEL ESTADO\nJOSÉ GUADALUPE OSUNA MILLÁN\nSECRETARIO GENERAL DE GOBIERNO\nFRANCISCO ANTONIO GARCÍA BURGOS\nARTÍCULO ÚNICO TRANSITORIO DEL DECRETO No. 259, POR EL QUE SE\nAPRUEBA REFORMA QUE ADICIONA UN NUMERAL 15 AL ARTÍCULO 56 Y UN INCISO\n.\nActualización Legislativa.\nÚltima reforma Gaceta No. 63, Especial, 14-Ago-2025\nJ) AL ARTÍCULO 60, PUBLICADO EN EL PERIÓDICO OFICIAL No. 38, TOMO CXIX,\nSECCIÓN I, DE FECHA 31 DE AGOSTO DE 2012, EXPEDIDO POR LA H. XX\nLEGISLATURA, SIENDO GOBERNADOR CONSTITUCIONAL EL C. JOSÉ GUADALUPE\nOSUNA MILLÁN 2007-2013.\nARTÍCULO TRANSITORIO\nÚNICO. La presente reforma entrará en vigor al momento de su aprobación por el\nPleno del Congreso del Estado, se publicarán en la Gaceta del Poder Legislativo, enviándose al Poder Ejecutivo para su publicación en el Periódico Oficial del Estado de Baja\nCalifornia.\nDADO en el Salón de Sesiones “Lic. Benito Juárez García” del H. Poder Legislativo del Estado de Baja California, en la Ciudad de Mexicali, B.C., a los veintiún días del mes de agosto del año dos mil doce.\nDIP. ALFONSO GARZÓN ZATARAIN\nPRESIDENTE\n(RÚBRICA)\nDIP. FAUSTO ZÁRATE ZEPEDA\nSECRETARIO\n(RÚBRICA)\nDE CONFORMIDAD CON LO DISPUESTO POR LA FRACCIÓN I DEL ARTÍCULO 49\nMEXICALI, BAJA CALIFORNIA, A LOS VEINTITRÉS DÍAS DEL MES DE AGOSTO\nDEL AÑO DOS MIL DOCE.\nGOBERNADOR DEL ESTADO\nJOSÉ GUADALUPE OSUNA MILLÁN\nSECRETARIO GENERAL DE GOBIERNO\nFRANCISCO ANTONIO GARCÍA BURGOS\nARTÍCULO SEPTIMO TRANSITORIO DEL DECRETO No. 315, POR EL QUE SE\nREFORMA EL ARTICULO 50 FRACCIÓN XIII, PUBLICADO EN EL PERIÓDICO OFICIAL\nLA H. XX LEGISLATURA, SIENDO GOBERNADOR CONSTITUCIONAL EL C. JOSÉ\nGUADALUPE OSUNA MILLÁN 2007-2013.\n.\nActualización Legislativa.\nÚltima reforma Gaceta No. 63, Especial, 14-Ago-2025\nARTÍCULO TRANSITORIO\nÚNICO. Las presentes reformas entrarán en vigor al día siguiente de su publicación en el Periódico Oficial del Estado.\nDADO en el Salón de Sesiones “Lic. Benito Juárez García” del H. Poder Legislativo del Estado de Baja California, en la Ciudad de Mexicali, B.C., a los quince días del mes de enero del año dos mil trece.\nDIP. ELISA ROSANA SOTO AGÜERO\nVICEPRESIDENTE\n(RÚBRICA)\nDIP. FAUSTO ZÁRATE ZEPEDA\nSECRETARIO\n(RÚBRICA)\nDE CONFORMIDAD CON LO DISPUESTO POR LA FRACCIÓN I DEL ARTÍCULO 49\nMEXICALI, BAJA CALIFORNIA, A LOS VEINTICINCO DÍAS DEL MES DE ENERO\nDEL AÑO DOS MIL TRECE.\nJOSÉ GUADALUPE OSUNA MILLÁN\nGOBERNADOR DEL ESTADO\n(RÚBRICA)\nFRANCISCO ANTONIO GARCÍA BURGOS\nSECRETARIO GENERAL DE GOBIERNO\nARTÍCULO UNICO TRANSITORIO DEL DECRETO No. 508, POR EL QUE SE\nADICIONA UN TERCER PÁRRAFO AL ARTÍCULO 107, PUBLICADO EN EL PERIÓDICO\nXX LEGISLATURA, SIENDO GOBERNADOR CONSTITUCIONAL EL C. JOSÉ\nGUADALUPE OSUNA MILLÁN 2007-2013.\nARTÍCULO TRANSITORIO\nÚNICO. La presente reforma entrará en vigor al momento de su aprobación por el\n.\nActualización Legislativa.\nÚltima reforma Gaceta No. 63, Especial, 14-Ago-2025 al Poder Ejecutivo para su publicación en el Periódico Oficial del Estado de Baja California.\nDADO en el Salón de Sesiones “Lic. Benito Juárez García” del H. Poder Legislativo del Estado de Baja California, en la Ciudad de Mexicali, B.C., a los treinta días del mes de julio del año dos mil trece.\nDIP. GREGORIO CARRANZA HERNÁNDEZ\nPRESIDENTE\n(RÚBRICA)\nDIP. MARCO ANTONIO VIZCARRA CALDERÓN\nSECRETARIO\n(RÚBRICA)\nDE CONFORMIDAD CON LO DISPUESTO POR LA FRACCIÓN I DEL ARTÍCULO 49\nMEXICALI, BAJA CALIFORNIA, A LOS OCHO DÍAS DEL MES DE AGOSTO DEL\nAÑO DOS MIL TRECE.\nJOSÉ GUADALUPE OSUNA MILLÁN\nGOBERNADOR DEL ESTADO\n(RÚBRICA)\nFRANCISCO ANTONIO GARCÍA BURGOS\nSECRETARIO GENERAL DE GOBIERNO\n(RÚBRICA)\nARTÍCULO ÚNICO TRANSITORIO DEL DICTAMEN No. 266 DE LA COMISIÓN DE\nGOBERNACIÓN, LEGISLACIÓN Y PUNTOS CONSTITUCIONALES, POR EL QUE SE\nAPRUEBA LA REFORMA A LOS ARTÍCULOS 12 FRACCIÓN II, 13 FRACCIÓN III, 14, 15,\n18 FRACCIÓN II, A LA DENOMINACIÓN DEL CAPÍTULO IV, 27, 29, 30, 31, 32, 33, 38, 40,\n41, 42, 48, 53 FRACCIÓN X, 55, 56, 58, 59, 60, 62 FRACCIÓN III, XIII, XIV Y XV, 63, 64,\n66 FRACCIÓN VII, 67, 72, 77, 77 BIS, 77 TER, 80, 82, 83, 83 BIS, 83 TER, 83 QUINQUIES,\n96, 101, 115 FRACCIÓN V, 169 BIS Y 171; SE DEROGA EL CONTENIDO DE LOS\nPOR LA H. XX LEGISLATURA.\nARTÍCULOS TRANSITORIOS\nPRIMERO. Las presentes reformas entrarán en vigor el día 30 de septiembre del año 2013.\n.\nActualización Legislativa.\nÚltima reforma Gaceta No. 63, Especial, 14-Ago-2025\nSEGUNDO. Publíquese en la Gaceta del Poder Legislativo del Estado de Baja\nCalifornia.\nDADO en el Salón de Comisiones “Dr. Francisco Dueñas Montes” del H. Poder\nLegislativo en la ciudad de Mexicali, Baja California, a los 27 días del mes de agosto del año\n2013”.\nDIP. GREGORIO CARRANZA HERNÁNDEZ\nPRESIDENTE\n(RÚBRICA)\nDIP. MARCO ANTONIO VIZCARRA CALDERÓN\nSECRETARIO\n(RÚBRICA)\nARTÍCULO UNICO TRANSITORIO DEL DECRETO No. 514, POR EL QUE SE\nADICIONA UN SEGUNDO PÁRRAFO AL ARTÍCULO 119, PUBLICADO EN EL PERIÓDICO\nOFICIAL No. 38, SECCION I, TOMO CXX, DE FECHA 30 DE AGOSTO DE 2013,\nEXPEDIDO POR LA H. XX LEGISLATURA, SIENDO GOBERNADOR CONSTITUCIONAL\nEL C. JOSÉ GUADALUPE OSUNA MILLÁN 2007-2013.\nARTÍCULO TRANSITORIO\nÚNICO. La presente reforma entrará en vigor al momento de su aprobación por el\nPleno del Congreso del Estado, se publicará en la Gaceta del Poder Legislativo, enviándose al Poder Ejecutivo para su publicación en el Periódico Oficial del Estado de Baja California.\nDADO en el Salón de Sesiones “Lic. Benito Juárez García” del H. Poder Legislativo del Estado de Baja California, en la Ciudad de Mexicali, B.C., a los dieciséis días del mes de agosto del año dos mil trece.\nDIP. GREGORIO CARRANZA HERNÁNDEZ\nPRESIDENTE\nDIP. MARCO ANTONIO VIZCARRA CALDERÓN\nSECRETARIO\nDE CONFORMIDAD CON LO DISPUESTO POR LA FRACCIÓN I DEL ARTÍCULO 49\n.\nActualización Legislativa.\nÚltima reforma Gaceta No. 63, Especial, 14-Ago-2025\nMEXICALI, BAJA CALIFORNIA, A LOS OCHO DÍAS DEL MES DE AGOSTO DEL\nAÑO DOS MIL TRECE.\nJOSÉ GUADALUPE OSUNA MILLÁN\nGOBERNADOR DEL ESTADO\n(RÚBRICA)\nFRANCISCO ANTONIO GARCÍA BURGOS\nSECRETARIO GENERAL DE GOBIERNO\n(RÚBRICA)\nARTÍCULO UNICO TRANSITORIO DEL DECRETO No. 516, POR EL QUE SE\nREFORMA EL INCISO F DE LA FRACCIÓN II, DEL ARTÍCULO 50, PUBLICADO EN EL\nPERIÓDICO OFICIAL No. 40, TOMO CXX, DE FECHA 13 DE SEPTIEMBRE DE 2013,\nEXPEDIDO POR LA H. XX LEGISLATURA, SIENDO GOBERNADOR CONSTITUCIONAL\nEL C. JOSÉ GUADALUPE OSUNA MILLÁN 2007-2013.\nARTÍCULOS TRANSITORIOS\nPRIMERO. El presente Decreto entrará en vigor al día siguiente de su publicación en la Gaceta Parlamentaria del Congreso del Estado.\nSEGUNDO. Envíese el presente Decreto al Poder Ejecutivo para su publicación en el\nPeriódico Oficial del Estado de Baja California.\nDADO en el Salón de Sesiones “Lic. Benito Juárez García” del H. Poder Legislativo del Estado de Baja California, en la Ciudad de Mexicali, B.C., a los dieciséis días del mes de agosto del año dos mil trece.\nDIP. GREGORIO CARRANZA HERNÁNDEZ\nPRESIDENTE\nDIP. MARCO ANTONIO VIZCARRA CALDERÓN\nSECRETARIO\nDE CONFORMIDAD CON LO DISPUESTO POR LA FRACCIÓN I DEL ARTÍCULO 49\n.\nActualización Legislativa.\nÚltima reforma Gaceta No. 63, Especial, 14-Ago-2025\nMEXICALI, BAJA CALIFORNIA, A LOS VEINTISIETE DÍAS DEL MES DE AGOSTO\nDEL AÑO DOS MIL TRECE.\nJOSÉ GUADALUPE OSUNA MILLÁN\nGOBERNADOR DEL ESTADO\n(RÚBRICA)\nFRANCISCO ANTONIO GARCÍA BURGOS\nSECRETARIO GENERAL DE GOBIERNO\n(RÚBRICA)\nÚNICO. SE APRUEBA LA REFORMA A LOS ARTÍCULOS 64; Y SE ADICIONA\nNUMERAL 12, RECORRIÉNDOSE LOS ACTUALES 12, 13 Y 14, PARA SER 13, 14 Y 15\nDEL ARTÍCULO 56, PUBLICADO EN LA GACETA PARLAMENTARIA DEL CONGRESO\nDEL ESTADO DE BAJA CALIFORNIA, DE FECHA 10 DE OCTUBRE DE 2013\nARTÍCULOS TRANSITORIOS\nPRIMERO. La presente reforma entrará en vigor al momento de su aprobación por el\nPleno del Congreso del Estado.\nSEGUNDO. Por única ocasión, a partir de la entrada en vigor de la presente reforma y hasta el 30 de septiembre del año 2016, las Comisiones de dictamen legislativo de\nREFORMA DEL ESTADO y HACIENDA Y PRESUPUESTO, así como las Comisiones\nOrdinarias de ADMINISTRACIÓN Y FINANZAS y COMUNICACIÓN SOCIAL Y\nRELACIONES PÚBLICAS, se integrarán respectivamente hasta por siete miembros.\nTERCERO. Publíquese en la Gaceta del Poder Legislativo, órgano Oficial de difusión del Congreso del Estado de Baja California.\nCUARTO. Remítase al Poder Ejecutivo del Estado para su Publicación en el Periódico\nOficial del Estado.\nDADO en el Salón de Sesiones “Lic. Benito Juárez García” del Honorable Poder\nLegislativo, en la Ciudad de Mexicali, Baja California, a los 10 días del mes de octubre de\n2013.\nHOJA DE FIRMAS\nMODERNIZAR Y FORTALECER LAS COMISIONES, COMO ÓRGANOS DE TRABAJO DEL\nCONGRESO DEL ESTADO, A CARGO DE LOS INTEGRANTES DE LA JUNTA DE\n.\nActualización Legislativa.\nÚltima reforma Gaceta No. 63, Especial, 14-Ago-2025\nCOORDINACIÓN POLÍTICA DE LA VIGÉSIMA PRIMER LEGISLATURA DEL HONORABLE\nCONGRESO DEL ESTADO DE BAJA CALIFORNIA.\nDIP. RENÉ ADRIÁN MENDIVIL ACOSTA\nPRESIDENTE\n(RÚBRICA)\nDIP. GUSTAVO SÁNCHEZ VÁSQUEZ\nINTEGRANTE\n(RÚBRICA)\nDIP. JOSÉ FRANCISCO BARRAZA CHIQUETE\nINTEGRANTE\n(RÚBRICA)\nDIP. JOSÉ ALBERTO MARTÍNEZ CARRILLO\nINTEGRANTE\n(RÚBRICA)\nDIP. FRANCISCO ALCIBÍADES GARCÍA LIZARDI\nINTEGRANTE\n(RÚBRICA)\nDIP. JULIO CESAR VÁZQUEZ CASTILLO\nINTEGRANTE\n(RÚBRICA)\nDIP. RODOLFO OLIMPO HERNÁNDEZ BOJÓRQUEZ\nINTEGRANTE\n(RÚBRICA)\nDIP. JOSÉ ROBERTO DÁVALOS FLORES\nINTEGRANTE\nDIP. FAUSTO GALLARDO GARCÍA\nINTEGRANTE\nARTÍCULO UNICO TRANSITORIO DEL DECRETO No. 1, POR EL QUE SE\nREFORMA ARTÍCULO 64; Y SE ADICIONA EL NUMERAL 12, RECORRIÉNDOSE LOS\nACTUALES 12, 13 Y 14, PARA SER 13, 14 Y 15 DEL ARTÍCULO 56, PUBLICADO EN EL\n.\nActualización Legislativa.\nÚltima reforma Gaceta No. 63, Especial, 14-Ago-2025\nEXPEDIDO POR LA H. XX LEGISLATURA, SIENDO GOBERNADOR CONSTITUCIONAL\nEL C. JOSÉ GUADALUPE OSUNA MILLÁN 2007-2013.\nARTÍCULOS TRANSITORIOS\nPRIMERO. La presente reforma entrará en vigor al momento de su aprobación por el\nPleno del Congreso del Estado.\nSEGUNDO. Por única ocasión, a partir de la entrada en vigor de la presente reforma y hasta el 30 de septiembre del año 2016, las Comisiones de Dictamen Legislativo de Reforma del Estado; y Hacienda y Presupuesto, así como las Comisiones Ordinarias de\nAdministración y Finanzas; y Comunicación Social y Relaciones Públicas, podrán integrarse respectivamente hasta por siete miembros.\nTERCERO. Publíquese en la Gaceta del Poder Legislativo, Órgano Oficial de difusión del Congreso del Estado de Baja California.\nCUARTO. Remítase al Poder Ejecutivo del Estado para su Publicación en el Periódico\nOficial del Estado.\nDADO en el Salón de Sesiones “Lic. Benito Juárez García” del H. Poder Legislativo del Estado de Baja California, en la Ciudad de Mexicali, B.C., a los diez días del mes de octubre del año dos mil trece.\nDIP. CUAUHTÉMOC CARDONA BENAVIDES\nPRESIDENTE\n(RÚBRICA)\nDIP. JOSÉ ALBERTO MARTINEZ CARRILLO\nSECRETARIO\nDE CONFORMIDAD CON LO DISPUESTO POR LA FRACCIÓN I DEL ARTÍCULO 49\nMEXICALI, BAJA CALIFORNIA, A LOS CATORCE DÍAS DEL MES DE OCTUBRE\nDEL AÑO DOS MIL TRECE.\nJOSÉ GUADALUPE OSUNA MILLÁN\nGOBERNADOR DEL ESTADO\nFRANCISCO ANTONIO GARCÍA BURGOS\n.\nActualización Legislativa.\nÚltima reforma Gaceta No. 63, Especial, 14-Ago-2025\nSECRETARIO GENERAL DE GOBIERNO\n(RÚBRICA)\nARTÍCULO UNICO TRANSITORIO DEL DECRETO No. 37, POR EL QUE SE\nREFORMA ARTÍCULO 73; PUBLICADO EN EL PERIÓDICO OFICIAL No. 7, TOMO CXXI,\nDE FECHA 07 DE FEBRERO DE 2014, EXPEDIDO POR LA H. XXI LEGISLATURA,\nSIENDO GOBERNADOR CONSTITUCIONAL EL C. FRANCISCO ARTURO VEGA DE LA\nMADRID 2013-2019.\nARTÍCULO TRANSITORIO\nPRIMERO. La presente reforma entrará en vigor al día siguiente de su aprobación por el Pleno del Congreso, publíquese en la Gaceta Parlamentaria.\nSEGUNDO. Remítase al Poder Ejecutivo para su publicación en el Periódico Oficial.\nDADO en el Salón de Sesiones “Lic. Benito Juárez García” del H. Poder Legislativo del Estado de Baja California, en la Ciudad de Mexicali, B.C., a los dieciséis días del mes de enero del año dos mil catorce.\nDIP. CUAUHTÉMOC CARDONA BENAVIDES\nPRESIDENTE\n(RÚBRICA)\nDIP. JOSÉ ALBERTO MARTINEZ CARRILLO\nSECRETARIO\n(RÚBRICA)\nDE CONFORMIDAD CON LO DISPUESTO POR LA FRACCIÓN I DEL ARTÍCULO 49\nMEXICALI, BAJA CALIFORNIA, A LOS VEINTIÚN DÍAS DEL MES DE ENERO DEL\nAÑO DOS MIL CATORCE.\nFRANCISCO ARTURO VEGA DE LA MADRID\nGOBERNADOR DEL ESTADO\nGUILLERMO TREJO DOZAL\nSECRETARIO GENERAL DE GOBIERNO\n.\nActualización Legislativa.\nÚltima reforma Gaceta No. 63, Especial, 14-Ago-2025\nARTÍCULO UNICO TRANSITORIO DEL DECRETO No. 48, POR EL QUE SE\nREFORMAN LOS ARTÍCULOS 110, 114, 119, 126, 139, 145, LA ADICIÓN DE UN\nARTÍCULO 145 BIS, 151 Y 171; PUBLICADO EN EL PERIÓDICO OFICIAL No. 29,\nSECCIÓN II, TOMO CXXI, DE FECHA 30 DE MAYO DE 2014, EXPEDIDO POR LA H. XXI\nLEGISLATURA, SIENDO GOBERNADOR CONSTITUCIONAL EL C. FRANCISCO ARTURO\nVEGA DE LA MADRID 2013-2019.\nARTÍCULO TRANSITORIO\nÚNICO: Las presentes reformas se publicarán en la Gaceta Parlamentaria del Poder\nLegislativo del Estado y entrarán en vigor al día siguiente de su publicación en el Periódico\nOficial del Estado de Baja California.\nDADO en el Salón de Sesiones “Lic. Benito Juárez García” del H. Poder Legislativo del Estado de Baja California, en la Ciudad de Mexicali, B.C., a los diez días del mes de abril del año dos mil catorce.\nDIP. RENÉ ADRIÁN MENDÍVIL ACOSTA\nPRESIDENTE\n(RÚBRICA)\nDIP. MARÍA DEL CARMEN FRÍAS\nSECRETARIA\n(RÚBRICA)\nDE CONFORMIDAD CON LO DISPUESTO POR LA FRACCIÓN I DEL ARTÍCULO 49\nMEXICALI, BAJA CALIFORNIA, A LOS QUINCE DÍAS DEL MES DE MAYO DEL\nAÑO DOS MIL CATORCE.\nFRANCISCO ARTURO VEGA DE LAMADRID\nGOBERNADOR DEL ESTADO\nFRANCISCO RUEDA GÓMEZ\nSECRETARIO GENERAL DE GOBIERNO\nARTÍCULO PRIMERO TRANSITORIO DEL DECRETO No. 138, POR EL QUE SE\nREFORMAN LOS ARTÍCULOS 56 Y 64; PUBLICADO EN EL PERIÓDICO OFICIAL No. 29,.\nActualización Legislativa.\nÚltima reforma Gaceta No. 63, Especial, 14-Ago-2025\nLEGISLATURA, SIENDO GOBERNADOR CONSTITUCIONAL EL C. FRANCISCO ARTURO\nVEGA DE LA MADRID 2013-2019.\nARTICULOS TRANSITORIOS\nPRIMERO.- La presente reforma entrará en vigor quince días después de su aprobación por el Pleno del Congreso del Estado y consecuentemente publíquese en la\nGaceta Parlamentaria del Poder Legislativo del Estado de Baja California.\nSEGUNDO.- Una vez aprobada la presente reforma por el Congreso del Estado, remítase al Titular del Poder Ejecutivo para su publicación en el Periódico Oficial del Estado de Baja California.\nDado en el salón de sesiones “Licenciado Benito Juárez García” del Poder Legislativo del Estado de Baja California, a los dieciséis días del mes de octubre del año dos mil catorce.\nDIP. DAVID RUVALCABA FLORES\nPRESIDENTE\n(RÚBRICA)\nDIP. ARMANDO REYES LEDESMA\nSECRETARIO\n(RÚBRICA)\nDE CONFORMIDAD CON LO DISPUESTO POR LA FRACCIÓN I DEL ARTÍCULO 49\nMEXICALI, BAJA CALIFORNIA, A LOS NUEVE DÍAS DEL MES DE DICIEMBRE DEL\nAÑO DOS MIL CATORCE.\nFRANCISCO ARTURO VEGA DE LAMADRID\nGOBERNADOR DEL ESTADO\nFRANCISCO RUEDA GÓMEZ\nSECRETARIO GENERAL DE GOBIERNO\nSE APRUEBA REFORMA AL ARTÍCULO 117, PUBLICADO EN LA GACETA\nPARLAMENTARIA DEL CONGRESO DEL ESTADO DE BAJA CALIFORNIA, DE FECHA 13\n.\nActualización Legislativa.\nÚltima reforma Gaceta No. 63, Especial, 14-Ago-2025\nARTÍCULOS TRANSITORIOS\nPRIMERO.- La presente reforma entrará en vigor al día siguiente de su aprobación por el Pleno del Congreso del Estado y consecuentemente publíquese en la Gaceta\nParlamentaria del Poder Legislativo del Estado de Baja California.\nSEGUNDO.- Una vez aprobada la presente reforma por el Congreso del Estado, remítase al Titular del Poder Ejecutivo para su publicación en el Periódico Oficial del Estado de Baja California.\nDADO en el Salón de Sesiones “Lic. Benito Juárez García” del H. Poder Legislativo del Estado de Baja California, en la Ciudad de Mexicali, B.C., a los trece días del mes de noviembre del año dos mil catorce.\nDIP. DAVID RUVALCABA FLORES\nPRESIDENTE\n(RÚBRICA)\nDIP. ARMANDO REYES LEDESMA\nSECRETARIO\n(RÚBRICA)\nARTÍCULO UNICO TRANSITORIO DEL DECRETO No. 358, POR EL QUE SE\nREFORMA EL ARTÍCULO 77 Y SE ADICIONA EL ARTICULO 173 DEL TÍTULO DÉCIMO\nDE LAS PRÁCTICAS SUSTENTABLES; PUBLICADO EN EL PERIÓDICO OFICIAL No. 53,\nSECCIÓN I, TOMO CXXII, DE FECHA 20 DE NOVIEMBRE DE 2015, EXPEDIDO POR LA\nH. XXI LEGISLATURA, SIENDO GOBERNADOR CONSTITUCIONAL EL C. FRANCISCO\nARTURO VEGA DE LAMADRID 2013-2019.\nÚNICO.- La presente reforma entrará en vigor al día siguiente de su publicación en el\nPeriódico Oficial del Estado de Baja California. del Estado de Baja California, en la Ciudad de Mexicali, B.C., a los veintidós días del mes de octubre del año dos mil quince.\nDIP. IRMA MARTÍNEZ MANRÍQUEZ\nPRESIDENTA\n.\nActualización Legislativa.\nÚltima reforma Gaceta No. 63, Especial, 14-Ago-2025\nDIP. MARIO OSUNA JIMÉNEZ\nSECRETARIO\n(RÚBRICA)\nDE CONFORMIDAD CON LO DISPUESTO POR LA FRACCIÓN I DEL ARTÍCULO 49\nMEXICALI, BAJA CALIFORNIA, A LOS TREINTA DÍAS DEL MES DE OCTUBRE\nDEL AÑO DOS MIL QUINCE.\nFRANCISCO ARTURO VEGA DE LAMADRID\nGOBERNADOR DEL ESTADO\n(RÚBRICA)\nFRANCISCO RUEDA GÓMEZ\nSECRETARIO GENERAL DE GOBIERNO\n(RÚBRICA)\nARTÍCULO DÉCIMO SEGUNDO TRANSITORIO DEL DECRETO No. 359, POR EL\nQUE SE REFORMA EL ARTÍCULO 62; PUBLICADO EN EL PERIÓDICO OFICIAL No. 53,\nSECCIÓN I, TOMO CXXII, DE FECHA 20 DE NOVIEMBRE DE 2015, EXPEDIDO POR LA\nH. XXI LEGISLATURA, SIENDO GOBERNADOR CONSTITUCIONAL EL C. FRANCISCO\nARTURO VEGA DE LA MADRID 2013-2019.\nÚNICO.- La presente reforma entrará en vigor al día siguiente de su publicación en el\nPeriódico Oficial del Estado de Baja California.\nDADO en el Salón de Sesiones “Lic. Benito Juárez García” del H. Poder Legislativo del Estado de Baja California, en la Ciudad de Mexicali, B.C., a los veintidós días del mes de octubre del año dos mil quince.\nDIP. IRMA MARTÍNEZ MANRÍQUEZ\nPRESIDENTA\nDIP. MARIO OSUNA JIMÉNEZ\nSECRETARIO\nDE CONFORMIDAD CON LO DISPUESTO POR LA FRACCIÓN I DEL ARTÍCULO 49\n.\nActualización Legislativa.\nÚltima reforma Gaceta No. 63, Especial, 14-Ago-2025\nMEXICALI, BAJA CALIFORNIA, A LOS TREINTA DÍAS DEL MES DE OCTUBRE\nDEL AÑO DOS MIL QUINCE.\nFRANCISCO ARTURO VEGA DE LAMADRID\nGOBERNADOR DEL ESTADO\n(RÚBRICA)\nFRANCISCO RUEDA GÓMEZ\nSECRETARIO GENERAL DE GOBIERNO\n(RÚBRICA)\nARTÍCULO UNICO TRANSITORIO DEL DECRETO No. 362, POR EL QUE SE\nREFORMAN LOS ARTÍCULOS 56 Y 60; PUBLICADO EN EL PERIÓDICO OFICIAL No. 56,\nSECCIÓN IV, TOMO CXXII, DE FECHA 04 DE DICIEMBRE DE 2015, EXPEDIDO POR LA\nH. XXI LEGISLATURA, SIENDO GOBERNADOR CONSTITUCIONAL EL C. FRANCISCO\nARTURO VEGA DE LAMADRID 2013-2019.\nARTÍCULOS TRANSITORIOS\nPRIMERO.- La presente reforma entrará en vigor al día siguiente de su aprobación por el Pleno del Congreso del Estado y consecuentemente publíquese en la Gaceta\nParlamentaria del Poder Legislativo del Estado de Baja California.\nSEGUNDO.- Una vez aprobada la presente reforma por el Congreso del Estado, remítase al Titular del Poder Ejecutivo para su publicación en el Periódico Oficial del Estado de Baja California.\nTERCERO.- Todos los asuntos turnados a la actual Comisión de Dictamen legislativo de Equidad y Género del Congreso del Estado de Baja California, se entenderán remitidos a la Comisión para la Igualdad entre Mujeres y Hombres. del Estado de Baja California, en la Ciudad de Mexicali, B.C., a los cinco días del mes de noviembre del año dos mil quince.\nDIP. IRMA MARTÍNEZ MANRÍQUEZ\nPRESIDENTA\nDIP. MARIO OSUNA JIMÉNEZ\nSECRETARIO\n.\nActualización Legislativa.\nÚltima reforma Gaceta No. 63, Especial, 14-Ago-2025\nDE CONFORMIDAD CON LO DISPUESTO POR LA FRACCIÓN I DEL ARTÍCULO 49\nMEXICALI, BAJA CALIFORNIA, A LOS DIEZ DÍAS DEL MES DE NOVIEMBRE DEL\nAÑO DOS MIL QUINCE.\nFRANCISCO ARTURO VEGA DE LAMADRID\nGOBERNADOR DEL ESTADO\n(RÚBRICA)\nFRANCISCO RUEDA GÓMEZ\nSECRETARIO GENERAL DE GOBIERNO\n(RÚBRICA)\nARTÍCULO UNICO TRANSITORIO DEL DECRETO No. 373, POR EL QUE SE\nREFORMAN LOS ARTÍCULOS 56 Y 60; PUBLICADO EN EL PERIÓDICO OFICIAL No. 58,\nSECCIÓN III, TOMO CXXII, DE FECHA 18 DE DICIEMBRE DE 2015, EXPEDIDO POR LA\nH. XXI LEGISLATURA, SIENDO GOBERNADOR CONSTITUCIONAL EL C. FRANCISCO\nARTURO VEGA DE LAMADRID 2013-2019.\nARTÍCULOS TRANSITORIOS\nPRIMERO.- La presente reforma entrará en vigor al día siguiente de su aprobación por el Pleno del Congreso del Estado y consecuentemente publíquese en la Gaceta\nParlamentaria del Poder Legislativo del Estado de Baja California.\nSEGUNDO.- Una vez aprobada la presente reforma por el Congreso del Estado, remítase al Titular del Poder Ejecutivo para su publicación en el Periódico Oficial del Estado de Baja California.\nTERCERO.- Todos los asuntos turnados a la Comisión de Asuntos Fronterizos, Comercio, Desarrollo y Fomento Económico e Industrial y Competitividad, se entenderán\nLegislativo del Estado de Baja California.\nCUARTO.- La Comisión de Asuntos Fronterizos y Desarrollo Económico del Poder\nComisión de Asuntos Fronterizos, Comercio, Desarrollo y Fomento Económico e Industrial y\nCompetitividad, en sus respectivos puestos.\nQUINTO.- La Comisión de Asuntos Fronterizos y Desarrollo Económico del Poder\n.\nActualización Legislativa.\nÚltima reforma Gaceta No. 63, Especial, 14-Ago-2025 disposiciones administrativas vigentes establecen para la actual Comisión de Asuntos\nFronterizos, Comercio, Desarrollo y Fomento Económico e Industrial y Competitividad.\nDADO en el Salón de Sesiones “Lic. Benito Juárez García” del H. Poder Legislativo del Estado de Baja California, en la Ciudad de Mexicali, B.C., a los veintiséis días del mes de noviembre del año dos mil quince.\nDIP. IRMA MARTÍNEZ MANRÍQUEZ\nPRESIDENTA\n(RÚBRICA)\nDIP. MARIO OSUNA JIMÉNEZ\nSECRETARIO\n(RÚBRICA)\nDE CONFORMIDAD CON LO DISPUESTO POR LA FRACCIÓN I DEL ARTÍCULO 49\nMEXICALI, BAJA CALIFORNIA, A LOS DOS DÍAS DEL MES DE DICIEMBRE DEL\nAÑO DOS MIL QUINCE.\nFRANCISCO ARTURO VEGA DE LAMADRID\nGOBERNADOR DEL ESTADO\n(RÚBRICA)\nFRANCISCO RUEDA GÓMEZ\nSECRETARIO GENERAL DE GOBIERNO\n(RÚBRICA)\nARTÍCULO PRIMERO TRANSITORIO DEL DECRETO No. 524, POR EL QUE SE\nREFORMAN LAS FRACCIONES IV, VI Y SE ADICIONA UNA FRACCIÓN VII AL ARTÍCULO\n104, ASÍ COMO SE ADICIONA UN ARTÍCULO 109 BIS; PUBLICADO EN EL PERIÓDICO\nEXPEDIDO POR LA H. XXI LEGISLATURA, SIENDO GOBERNADOR CONSTITUCIONAL\nEL C. FRANCISCO ARTURO VEGA DE LAMADRID 2013-2019.\nTRANSITORIOS\nARTÍCULO PRIMERO.- La presente reforma entrará en vigor al día siguiente de su publicación en el Periódico Oficial del Estado.\n.\nActualización Legislativa.\nÚltima reforma Gaceta No. 63, Especial, 14-Ago-2025\nARTÍCULO SEGUNDO.- Dentro de un término no mayor al de 180 días, contados a partir de la fecha en que entre en vigor la presente reforma, el Congreso del Estado emitirá las disposiciones reglamentarias correspondientes.\nARTÍCULO TERCERO.- La Junta de Coordinación Política del Congreso del Estado, podrá tomar los acuerdos que sean necesarios para dar cumplimiento a las presentes reformas hasta en tanto se aprueben las disposiciones a que se refiere el artículo transitorio anterior.\nDADO en el Salón de Sesiones “Lic. Benito Juárez García” del H. Poder Legislativo del Estado de Baja California, en la Ciudad de Mexicali, B.C., a los siete días del mes de\nJulio del año dos mil dieciséis.\nDIP. MÓNICA BEDOYA SERNA\nPRESIDENTA\n(RÚBRICA)\nDIP. ROSA ISELA PERALTA CASILLAS\nSECRETARIO\n(RÚBRICA)\nDE CONFORMIDAD CON LO DISPUESTO POR LA FRACCIÓN I DEL ARTÍCULO 49\nMEXICALI, BAJA CALIFORNIA, A LOS VEINTIOCHO DÍAS DEL MES DE JULIO DEL\nAÑO DOS MIL DIECISÉIS.\nFRANCISCO ARTURO VEGA DE LAMADRID\nGOBERNADOR DEL ESTADO\n(RÚBRICA)\nFRANCISCO RUEDA GÓMEZ\nSECRETARIO GENERAL DE GOBIERNO\nARTÍCULO ÚNICO TRANSITORIO DEL DECRETO No. 540, POR EL QUE SE\nREFORMAN LOS ARTICULOS 66 Y 119; PUBLICADO EN EL PERIÓDICO OFICIAL No. 40,\nH. XXI LEGISLATURA, SIENDO GOBERNADOR CONSTITUCIONAL EL C. FRANCISCO\nARTURO VEGA DE LAMADRID 2013-2019.\nTRANSITORIO\n.\nActualización Legislativa.\nÚltima reforma Gaceta No. 63, Especial, 14-Ago-2025\nPRIMERO.- El presente Decreto entrará en vigor al día siguiente de su publicación en la Gaceta Parlamentaria del Congreso del Estado.\nSEGUNDO.- Envíese el presente Decreto al Poder Ejecutivo para su publicación en el\nPeriódico Oficial del Estado de Baja California.\nDADO en el Salón de Sesiones “Lic. Benito Juárez García” del H. Poder Legislativo del Estado de Baja California, en la Ciudad de Mexicali, B.C., a los catorce días del mes de julio del año dos mil dieciséis.\nDIP. MÓNICA BEDOYA SERNA\nPRESIDENTA\n(RÚBRICA)\nDIP. ROSA ISELA PERALTA CASILLAS\nSECRETARIO\n(RÚBRICA)\nDE CONFORMIDAD CON LO DISPUESTO POR LA FRACCIÓN I DEL ARTÍCULO 49\nMEXICALI, BAJA CALIFORNIA, A LOS 11 DÍAS DEL MES DE AGOSTO DEL AÑO\nDOS MIL DIECISÉIS.\nFRANCISCO ARTURO VEGA DE LAMADRID\nGOBERNADOR DEL ESTADO\n(RÚBRICA)\nFRANCISCO RUEDA\nSECRETARIO GENERAL DE GOBIERNO\nARTÍCULO ÚNICO TRANSITORIO DEL DECRETO No. 680, POR EL QUE SE\nREFORMA EL ARTÍCULO 28; PUBLICADO EN EL PERIÓDICO OFICIAL No. 47, SECCIÓN\nLEGISLATURA, SIENDO GOBERNADOR CONSTITUCIONAL EL C. FRANCISCO ARTURO\nVEGA DE LAMADRID 2013-2019.\nÚNICO: El presente Decreto entrará en vigor al día siguiente de su publicación en el\nPeriódico Oficial del Estado de Baja California.\n.\nActualización Legislativa.\nÚltima reforma Gaceta No. 63, Especial, 14-Ago-2025\nDADO en el Salón de Sesiones “Lic. Benito Juárez García” del H. Poder Legislativo del Estado de Baja California, en la Ciudad de Mexicali, B.C., a los veintiocho días del mes de septiembre del año dos mil dieciséis.\nDIP. MÓNICA BEDOYA SERNA\nPRESIDENTA\n(RÚBRICA)\nDIP. MARGARITA MACRINA CORRO ARÁMBULA\nPRO-SECRETARIA\n(RÚBRICA)\nDE CONFORMIDAD CON LO DISPUESTO POR LA FRACCIÓN I DEL ARTÍCULO 49\nMEXICALI, BAJA CALIFORNIA, A LOS TRES DÍAS DEL MES DE OCTUBRE DEL\nAÑO DOS MIL DIECISÉIS.\nFRANCISCO ARTURO VEGA DE LAMADRID\nGOBERNADOR DEL ESTADO\n(RÚBRICA)\nFRANCISCO RUEDA GOMEZ\nSECRETARIO GENERAL DE GOBIERNO\n(RÚBRICA)\nARTÍCULO ÚNICO TRANSITORIO DEL DECRETO No. 19, POR EL QUE SE\nREFORMAN LOS ARTICULOS 10; 11, 13; 14; 15; 16 QUATER; 17 FRACCIÓN XI; 18\nFRACCIONES VII Y X; 27; 36; 37; 40; LA CREACIÓN DE LOS ARTÍCULOS 40 BIS Y 40\nTER; LA REFORMA A LOS ARTÍCULOS 53 FRACCIÓN X; 56; 60; 62; 63; LA\nDEROGACIÓN DEL ARTÍCULO 64, LA REFORMA A LOS ARTÍCULOS 65; 66; 67; 76; 76\nBIS; 77; 77 BIS; 77 TER; 77 QUARTER; 78; 79; 80; 80 BIS, 81; 81 BIS; 81 TER; 82; 82 BIS;\n83 BIS; 83 TER; LA DEROGACIÓN DE LOS ARTÍCULOS 83 QUARTER, 83 QUINQUIES,\n83 SEXIES; LA REFORMA DE LOS ARTÍCULOS 84; 85; 86; 86 BIS; 88; 91; 95, 101, 109;\n115; 118; 120; 144; 157; 168; 169; ASÍ COMO LA DEROGACIÓN DE LOS ARTÍCULOS 169\nBIS Y 170 Y LA REFORMA A LOS ARTÍCULOS 171 Y 173; PUBLICADO EN EL\nPERIÓDICO OFICIAL No. 52, SECCIÓN IV, TOMO CXXIII, DE FECHA 25 DE NOVIEMBRE\nDE 2016, EXPEDIDO POR LA H. XXI LEGISLATURA, SIENDO GOBERNADOR\nCONSTITUCIONAL EL C. FRANCISCO ARTURO VEGA DE LAMADRID 2013-2019.\n.\nActualización Legislativa.\nÚltima reforma Gaceta No. 63, Especial, 14-Ago-2025\nARTÍCULOS TRANSITORIOS\nPRIMERO. Se derogan las disposiciones que contravengan el presente Decreto.\nSEGUNDO. La reforma prevista en el Artículo 13 será aplicable en los términos establecidos en el Artículo Sexto Transitorio del Decreto 112 de fecha 11 de septiembre de\n2014 publicado en el Periódico Oficial No. 50 de fecha 17 de octubre de 2014.\nTERCERO. Las presentes reformas deberán publicarse en la Gaceta del Poder\nLegislativo, y entrarán en vigor al día siguiente de su publicación en el Periódico Oficial del\nEstado de Baja California.\nCUARTO.- La Junta de Coordinación Política, propondrá al pleno el nombramiento de los titulares de:\nI. La Dirección de Administración;\nII. La Dirección de Contabilidad y Finanzas;\nIII. La Dirección de Procesos Parlamentarios;\nIV. La Dirección de Consultoría Legislativa;\nV. Las Unidades Auxiliares siguientes:\na). Unidad de Contraloría Interna;\nb) Unidad de Asuntos Jurídicos;\nc). Unidad de Transparencia; y\nd). Unidad de Comunicación Social.\nQUINTO.- El Congreso del Estado deberá realizar los ajustes presupuestales presente reforma así como cubrir las erogaciones que deban hacerse al personal que, con motivo de la supresión de plazas de empleados de confianza, sean separados de sus anterior, en virtud de la entrada en vigor de las presentes reformas. De igual forma, deberá orgánica en este Congreso Local.\nSEXTO.- La Mesa Directiva encabezará y gestionará el proceso de entrega recepción de los Órganos de Apoyo Parlamentario y Administrativo que se derogan.\n.\nActualización Legislativa.\nÚltima reforma Gaceta No. 63, Especial, 14-Ago-2025\nSÉPTIMO.- Los recursos humanos y financieros adscritos a los órganos de apoyo\nParlamentario y Administrativo, así como a los órganos de gobierno, tratándose de personal de base serán reasignados en relación a sus funciones y experiencia, de conformidad a lo dispuesto por el artículo ocho de la Ley del Servicio Civil de los Poderes del Estado y\nMunicipio, por la Dirección de administración con el visto bueno y con la presencia de la\nAutoridad Sindical; tratándose de recursos financieros se sujetará a las determinaciones de la Comisión de Administración y Finanzas.\nOCTAVO.- Las presentes reformas no afectarán los derechos adquiridos y demás prestaciones reconocidas a los trabajadores de base con anterioridad al presente Decreto.\nNOVENO.- Los actos jurídicos realizados por los Diputados, Órganos de Gobierno, de\nTrabajo, de Apoyo Parlamentario y Administrativo, así como por la demás estructura del\nPoder Legislativo durante el lapso de tiempo que transcurra entre la entrada en vigor de las presentes reformas y la designación de los titulares a que se refiere el artículo CUARTO\nTransitorio del presente Decreto, se considerarán como legalmente válidos, por lo que en tanto, no se realicen las designaciones de los nuevos servidores públicos, las funciones parlamentarias y administrativas, seguirán siendo realizadas por los actuales titulares y conforme a los procedimientos que se venían realizando hasta antes de la entrada en vigor de las presentes reformas.\nDÉCIMO.- Las referencias que en lo particular se hagan en leyes y demás disposiciones normativas a la comisión de reformas de Estado o a la Comisión jurisdiccional en lo sucesivo se entenderá hechas a la Comisión de Reforma de Estado y Jurisdiccional a la que hace referencia las presentes reformas.\nDADO en el Salón de Sesiones “Lic. Benito Juárez García” del H. Poder Legislativo del Estado de Baja California, en la Ciudad de Mexicali, B.C., a los veinticuatro días del mes de noviembre del año dos mil dieciséis.\nDIP. MTRO. RAÚL CASTAÑEDA POMPOSO\nPRESIDENTE\nDIP. MARCO A. CORONA BOLAÑOS CACHO\nSECRETARIO\nDE CONFORMIDAD CON LO DISPUESTO POR LA FRACCIÓN I DEL ARTÍCULO 49\n.\nActualización Legislativa.\nÚltima reforma Gaceta No. 63, Especial, 14-Ago-2025\nMEXICALI, BAJA CALIFORNIA, A LOS VEINTICINCO DÍAS DEL MES DE\nNOVIEMBRE DEL AÑO DOS MIL DIECISÉIS.\nFRANCISCO ARTURO VEGA DE LAMADRID\nGOBERNADOR DEL ESTADO\n(RÚBRICA)\nFRANCISCO RUEDA\nSECRETARIO GENERAL DE GOBIERNO\n(RUBRICA)\nARTÍCULO ÚNICO TRANSITORIO DEL DECRETO No. 44, POR EL QUE SE\nREFORMA EL ARTÍCULO 60 Y SE DEROGA LA SECCIÓN CUARTA DENOMINADA\nDIRECCIÓN GENERAL DE ASUNTOS JURÍDICOS DEL CAPÍTULO TERCERO; ASÍ COMO\nEL ARTÍCULO 83; PUBLICADO EN EL PERIÓDICO OFICIAL No. 06, SECCIÓN I, TOMO\nCXXIV, DE FECHA 06 DE ENERO DE 2017, EXPEDIDO POR LA H. XXII LEGISLATURA,\nSIENDO GOBERNADOR CONSTITUCIONAL EL C. FRANCISCO ARTURO VEGA DE\nLAMADRID 2013-2019.\nARTÍCULO TRANSITORIO\nÚNICO.- Las presentes reformas deberán publicarse en la Gaceta del Poder\nLegislativo, y entrarán en vigor al día siguiente de su publicación en el Periódico Oficial del\nEstado de Baja California.\nDADO en el Salón de Sesiones “Lic. Benito Juárez García” del H. Poder Legislativo del Estado de Baja California, en la Ciudad de Mexicali, B.C., a los ocho días del mes de diciembre del año dos mil dieciséis.\nDIP. MTRO. RAÚL CASTAÑEDA POMPOSO\nPRESIDENTE\nDIP. MARCO A. CORONA BOLAÑOS CACHO\nSECRETARIO\nDE CONFORMIDAD CON LO DISPUESTO POR LA FRACCIÓN I DEL ARTÍCULO 49\nMEXICALI, BAJA CALIFORNIA, A LOS VEINTIÚN DÍAS DEL MES DE DICIEMBRE\nDEL AÑO DOS MIL DIECISÉIS.\n.\nActualización Legislativa.\nÚltima reforma Gaceta No. 63, Especial, 14-Ago-2025\nFRANCISCO ARTURO VEGA DE LAMADRID\nGOBERNADOR DEL ESTADO\n(RÚBRICA)\nFRANCISCO RUEDA GOMEZ\nSECRETARIO GENERAL DE GOBIERNO\n(RÚBRICA)\nARTÍCULO ÚNICO TRANSITORIO DEL DECRETO No. 126, POR EL QUE SE\nAPRUEBA LA ADICIÓN DE UN PÁRRAFO TERCERO AL ARTÍCULO 84, ASÍ COMO UN\nPÁRRAFO SEGUNDO AL ARTÍCULO 117; PUBLICADO EN EL PERIÓDICO OFICIAL No.\n50, SECCIÓN III, TOMO CXXIV, DE FECHA 10 DE NOVIEMBRE DE 2017, EXPEDIDO\nPOR LA H. XXII LEGISLATURA, SIENDO GOBERNADOR CONSTITUCIONAL EL C.\nFRANCISCO ARTURO VEGA DE LAMADRID 2013-2019.\nARTÍCULO TRANSITORIO\nÚNICO.- De conformidad con el artículo 34, párrafo H, de la Constitución Política del\nEstado de Baja California, las presentes reformas entrarán en vigor al día siguiente de su publicación en la Gaceta del Poder Legislativo.\nDADO en el Salón de Sesiones “Lic. Benito Juárez García” del H. Poder Legislativo del Estado de Baja California, en la Ciudad de Mexicali, B.C., a los veintinueve días del mes de septiembre del año dos mil diecisiete.\nDIP. EDGAR BENJAMÍN GÓMEZ MACÍAS\nPRESIDENTE\n(RÚBRICA)\nDIP. EVA MARÍA VÁSQUEZ HERNÁNDEZ\nSECRETARIA\nDE CONFORMIDAD CON LO DISPUESTO POR LA FRACCIÓN I DEL ARTÍCULO 49\nMEXICALI, BAJA CALIFORNIA, A LOS DIECIOCHO DÍAS DE OCTUBRE DEL AÑO\nDOS MIL DIECISIETE.\nFRANCISCO ARTURO VEGA DE LAMADRID\nGOBERNADOR DEL ESTADO\n.\nActualización Legislativa.\nÚltima reforma Gaceta No. 63, Especial, 14-Ago-2025\nFRANCISCO RUEDA GÓMEZ\nSECRETARIO GENERAL DE GOBIERNO\n(RÚBRICA)\nARTÍCULO ÚNICO TRANSITORIO DEL DECRETO No. 144, POR EL QUE SE\nAPRUEBA LA REFORMA AL ARTÍCULO 77 BIS; PUBLICADO EN EL PERIÓDICO\nOFICIAL No. 50, SECCIÓN V, TOMO CXXIV, DE FECHA 10 DE NOVIEMBRE DE 2017,\nEXPEDIDO POR LA H. XXII LEGISLATURA, SIENDO GOBERNADOR CONSTITUCIONAL\nEL C. FRANCISCO ARTURO VEGA DE LAMADRID 2013-2019.\nARTÍCULO TRANSITORIO\nPRIMERO.- El presente Decreto entrará en vigor al día siguiente de su publicación en la Gaceta Parlamentaria del H. Congreso del Estado de Baja California, de acuerdo al\nCalifornia.\nSEGUNDO.- Remítase al Titular del Poder Ejecutivo en el Estado para que se ordene su publicación en el Periódico Oficial del Estado.\nTERCERO.- La Dirección de Administración del Congreso del Estado deberá presentar a la Comisión de Administración y Finanzas proyecto del programa de capacitación y profesionalización adjuntando al mismo el proyecto de presupuesto que contenga la creación de una partida presupuestal exclusiva para la implementación y funcionamiento de dicho programa.\nDADO en el Salón de Sesiones “Lic. Benito Juárez García” del H. Poder Legislativo del Estado de Baja California, en la Ciudad de Mexicali, B.C., a los doce días del mes de octubre del año dos mil diecisiete.\nDIP. EDGAR BENJAMÍN GÓMEZ MACÍAS\nPRESIDENTE\nDIP. EVA MARÍA VÁSQUEZ HERNÁNDEZ\nSECRETARIA\nDE CONFORMIDAD CON LO DISPUESTO POR LA FRACCIÓN I DEL ARTÍCULO 49\n.\nActualización Legislativa.\nÚltima reforma Gaceta No. 63, Especial, 14-Ago-2025\nMEXICALI, BAJA CALIFORNIA, A LOS VEINTITRÉS DÍAS DE OCTUBRE DEL AÑO\nDOS MIL DIECISIETE.\nFRANCISCO ARTURO VEGA DE LAMADRID\nGOBERNADOR DEL ESTADO\n(RÚBRICA)\nFRANCISCO RUEDA GÓMEZ\nSECRETARIO GENERAL DE GOBIERNO\n(RÚBRICA)\nARTÍCULO ÚNICO TRANSITORIO DEL DECRETO No. 145, POR EL QUE SE\nAPRUEBA LA REFORMA AL ARTÍCULO 9 Y 94; PUBLICADO EN EL PERIÓDICO\nOFICIAL No. 50, SECCIÓN V, TOMO CXXIV, DE FECHA 10 DE NOVIEMBRE DE 2017,\nEXPEDIDO POR LA H. XXII LEGISLATURA, SIENDO GOBERNADOR CONSTITUCIONAL\nEL C. FRANCISCO ARTURO VEGA DE LAMADRID 2013-2019.\nARTÍCULO TRANSITORIO\nÚNICO.- Las presentes reformas deberán publicarse en la Gaceta del Poder\nLegislativo, y entrará en vigor al día siguiente de su publicación en el Periódico Oficial del\nEstado de Baja California.\nDADO en el Salón de Sesiones “Lic. Benito Juárez García” del H. Poder Legislativo del Estado de Baja California, en la Ciudad de Mexicali, B.C., a los doce días del mes de octubre del año dos mil diecisiete.\nDIP. EDGAR BENJAMÍN GÓMEZ MACÍAS\nPRESIDENTE\nDIP. EVA MARÍA VÁSQUEZ HERNÁNDEZ\nSECRETARIA\nDE CONFORMIDAD CON LO DISPUESTO POR LA FRACCIÓN I DEL ARTÍCULO 49\nMEXICALI, BAJA CALIFORNIA, A LOS VEINTITRÉS DÍAS DE OCTUBRE DEL AÑO\nDOS MIL DIECISIETE.\n.\nActualización Legislativa.\nÚltima reforma Gaceta No. 63, Especial, 14-Ago-2025\nFRANCISCO ARTURO VEGA DE LAMADRID\nGOBERNADOR DEL ESTADO\n(RÚBRICA)\nFRANCISCO RUEDA GÓMEZ\nSECRETARIO GENERAL DE GOBIERNO\n(RÚBRICA)\nARTÍCULO ÚNICO TRANSITORIO DEL DECRETO No. 199, POR EL QUE SE\nAPRUEBA LA ADICIÓN DE UN SEGUNDO PÁRRAFO AL ARTÍCULO 146; PUBLICADO EN\nEL PERIÓDICO OFICIAL No. 10, SECCIÓN II, TOMO CXXV, DE FECHA 02 DE MARZO DE\n2018, EXPEDIDO POR LA H. XXII LEGISLATURA, SIENDO GOBERNADOR\nCONSTITUCIONAL EL C. FRANCISCO ARTURO VEGA DE LAMADRID 2013-2019.\nARTÍCULO TRANSITORIO\nÚNICO.- La presente iniciativa entrará en vigor al día siguiente de su publicación en el\nPeriódico Oficial del Estado de Baja California.\nDADO en el Salón de Sesiones “Lic. Benito Juárez García” del H. Poder Legislativo del Estado de Baja California, en la Ciudad de Mexicali, B.C., a los veinticinco días del mes de enero del año dos mil dieciocho.\nDIP. MTRO. RAÚL CASTAÑEDA POMPOSO\nPRESIDENTE\n(RÚBRICA)\nDIP. ROCÍO LÓPEZ GOROSAVE\nSECRETARIA\nDE CONFORMIDAD CON LO DISPUESTO POR LA FRACCIÓN I DEL ARTÍCULO 49\nMEXICALI, BAJA CALIFORNIA, A LOS DOS DÍAS DE MARZO DEL AÑO DOS MIL\nDIECIOCHO.\nFRANCISCO ARTURO VEGA DE LAMADRID\nGOBERNADOR DEL ESTADO\n.\nActualización Legislativa.\nÚltima reforma Gaceta No. 63, Especial, 14-Ago-2025\nFRANCISCO RUEDA GÓMEZ\nSECRETARIO GENERAL DE GOBIERNO\n(RÚBRICA)\nARTÍCULO SEXTO TRANSITORIO DEL DECRETO No. 244, POR EL QUE SE\nAPRUEBA LA ADICIÓN DEL TÍTULO DÉCIMO PRIMERO DENOMINADO “DE LA\nOBLIGACIÓN DE IMPARCIALIDAD EN EL PROCESO ELECTORAL, ASÍ COMO LOS\nARTÍCULOS 174, 175, 176, 177 Y 178; PUBLICADO EN EL PERIÓDICO OFICIAL No. 28,\nNÚMERO ESPECIAL, TOMO CXXV, DE FECHA 09 DE JUNIO DE 2018, EXPEDIDO POR\nLA H. XXII LEGISLATURA, SIENDO GOBERNADOR CONSTITUCIONAL EL C.\nFRANCISCO ARTURO VEGA DE LAMADRID 2013-2019.\nARTÍCULO TRANSITORIO\nÚNICO.- La presente reforma entrará en vigor al día siguiente de su publicación en el\nPeriódico Oficial del Estado.\nDADO en el Salón de Sesiones “Lic. Benito Juárez García” del H. Poder Legislativo del Estado de Baja California, en la Ciudad de Mexicali, B.C., a los siete días del mes de junio del año dos mil dieciocho.\nDIP. MARCO ANTONIO CORONA BOLAÑOS CACHO\nPRESIDENTE\n(RÚBRICA)\nDIP. VICTORIA BENTLEY DUARTE\nSECRETARIA\n(RÚBRICA)\nDE CONFORMIDAD CON LO DISPUESTO POR LA FRACCIÓN I DEL ARTÍCULO 49\nMEXICALI, BAJA CALIFORNIA, A LOS NUEVE DÍAS DEL MES DE JUNIO DEL AÑO\nDOS MIL DIECIOCHO.\nFRANCISCO ARTURO VEGA DE LAMADRID\nGOBERNADOR DEL ESTADO\nFRANCISCO RUEDA GÓMEZ\nSECRETARIO GENERAL DE GOBIERNO\n.\nActualización Legislativa.\nÚltima reforma Gaceta No. 63, Especial, 14-Ago-2025\n(RÚBRICA)\nARTÍCULO SEXTO TRANSITORIO DEL DECRETO No. 294, POR EL QUE SE\nAPRUEBA LA REFORMA QUE ADICIONA UN SEGUNDO PÁRRAFO AL ARTÍCULO 42;\nPUBLICADO EN EL PERIÓDICO OFICIAL No. 54, NÚMERO ESPECIAL, TOMO CXXV, DE\nFECHA 29 DE NOVIEMBRE DE 2018, EXPEDIDO POR LA H. XXII LEGISLATURA,\nSIENDO GOBERNADOR CONSTITUCIONAL EL C. FRANCISCO ARTURO VEGA DE\nLAMADRID 2013-2019.\nARTÍCULO TRANSITORIO\nÚNICO.- La presente reforma entrará en vigor al día siguiente de su publicación en el\nPeriódico Oficial del Estado.\nDADO en el Salón de Sesiones “Lic. Benito Juárez García” del H. Poder Legislativo del Estado de Baja California, en la Ciudad de Mexicali, B.C., a los ocho días del mes de noviembre del año dos mil dieciocho.\nDIP. ROCÍO LÓPEZ GOROSAVE\nPRESIDENTA\n(RÚBRICA)\nDIP. ALFA PEÑALOZA VALDEZ\nPROSECRETARIA\n(RÚBRICA)\nDE CONFORMIDAD CON LO DISPUESTO POR LA FRACCIÓN I DEL ARTÍCULO 49\nMEXICALI, BAJA CALIFORNIA, A LOS VEINTINUEVE DÍAS DEL MES DE\nNOVIEMBRE DEL AÑO DOS MIL DIECIOCHO.\nFRANCISCO ARTURO VEGA DE LAMADRID\nGOBERNADOR DEL ESTADO\nFRANCISCO RUEDA GÓMEZ\nSECRETARIO GENERAL DE GOBIERNO\n.\nActualización Legislativa.\nÚltima reforma Gaceta No. 63, Especial, 14-Ago-2025\nARTÍCULO ÚNICO TRANSITORIO DEL DECRETO No. 261, POR EL QUE SE\nREFORMA EL ARTÍCULO 109; PUBLICADO EN EL PERIÓDICO OFICIAL No. 7, SECCIÓN\nIII, TOMO CXXVI, DE FECHA 01 DE FEBRERO DE 2019, EXPEDIDO POR LA H. XXII\nLEGISLATURA, SIENDO GOBERNADOR CONSTITUCIONAL EL C. FRANCISCO ARTURO\nVEGA DE LAMADRID 2013-2019.\nARTÍCULO TRANSITORIO\nARTÍCULO PRIMERO.- La presente reforma entrará en vigor al día siguiente de su aprobación por el Pleno de este Congreso, lo anterior de conformidad con lo establecido en\nARTÍCULO SEGUNDO.- Esta Soberanía en ejercicio de las facultades que le confiere la Constitución Política del Estad Libre y Soberano de Baja California así como la Ley\nOrgánica del Poder Legislativo del Estado de Baja California, hará las previsiones presupuestales para asignar los recursos necesarios para el cumplimiento de este Decreto.\nARTÍCULO SEGUNDO.- Publiquese el presente Decreto en la Gaceta Parlamentaria y en el Periódico Oficial del Estado.\nDADO en el Salón de Sesiones “Lic. Benito Juárez García” del H. Poder Legislativo del Estado de Baja California, en la Ciudad de Mexicali, B.C., a los seis días del mes de septiembre del año dos mil dieciocho.\nDIP. ROCÍO LÓPEZ GOROSAVE\nPRESIDENTA\n(RÚBRICA)\nDIP. MÓNICA HERNÁNDEZ ÁLVAREZ\nSECRETARIA\n(RÚBRICA)\nDE CONFORMIDAD CON LO DISPUESTO POR LA FRACCIÓN I DEL ARTÍCULO 49\nMEXICALI, BAJA CALIFORNIA, A LOS TREINTA Y UN DÍAS DEL MES DE ENERO\nDEL AÑO DOS MIL DIECINUEVE.\nFRANCISCO ARTURO VEGA DE LAMADRID\nGOBERNADOR DEL ESTADO\nFRANCISCO RUEDA GÓMEZ\nSECRETARIO GENERAL DE GOBIERNO\n.\nActualización Legislativa.\nÚltima reforma Gaceta No. 63, Especial, 14-Ago-2025\n(RÚBRICA)\nARTÍCULO ÚNICO TRANSITORIO DE LA INICIATIVA, POR EL QUE SE SUPRIME\nLA ÚLTIMA PARTE DEL CUARTO PÁRRAFO DEL ARTÍCULO 27; PUBLICADO EN LA\nGACETA PARLAMENTARIA No. 02, ESPECIAL, DE FECHA 02 DE AGOSTO DE 2019,\nEXPEDIDO POR LA H. XXIII LEGISLATURA, SIENDO GOBERNADOR CONSTITUCIONAL\nEL C. FRANCISCO ARTURO VEGA DE LAMADRID 2013-2019.\nARTÍCULO TRANSITORIO\nÚNICO.- Toda vez que las presentes reformas solo implican modificaciones al régimen interno del Poder Legislativo, entrarán en vigor al momento de su aprobación por la mayoría calificada del Pleno de este Honorable Congreso del Estado y se publicarán en la\nGaceta del Poder Legislativo.\nDado en el Salón de Sesiones “Lic. Benito Juárez García” del Honorable Congreso del Estado de Baja California, el primer día del mes de agosto del año 2019.\nDIP. CATALINO ZAVALA MÁRQUEZ\nPRESIDENTE\n(RÚBRICA)\nDIP. ARACELI GERALDO NÚÑEZ\nSECRETARIA\n(RÚBRICA)\nARTÍCULO ÚNICO TRANSITORIO DE LA INICIATIVA, POR EL QUE SE REFORMA\nEL ARTÍCULO 9; PUBLICADA EN LA GACETA PARLAMENTARIA No. 47, DE FECHA 08\nDE ABRIL DE 2020, EXPEDIDO POR LA H. XXIII LEGISLATURA, SIENDO GOBERNADOR\nCONSTITUCIONAL EL C. JAIME BONILLA VALDEZ 2019-2021.\nARTÍCULO TRANSITORIO\nÚNICO.- Toda vez que la presente reforma solo implica modificaciones al régimen del Estado de Baja California, en la Ciudad de Mexicali, B.C., a los ocho días del mes de abril del año dos mil veinte.\n.\nActualización Legislativa.\nÚltima reforma Gaceta No. 63, Especial, 14-Ago-2025\nDIP. LUIS MORENO HERNÁNDEZ\nPRESIDENTE\n(RÚBRICA)\nDIP. EVA GRICELDA RODRÍGUEZ\nSECRETARIA\n(RÚBRICA)\nARTÍCULO ÚNICO TRANSITORIO DE LA INICIATIVA, POR EL QUE SE DEROGA\nLA FRACCIÓN XIII DEL ARTÍCULO 77 BIS; SE REFORMAN LAS FRACCIONES II, III, VI,\nVII Y XI DEL ARTÍCULO 77QUARTER; Y SE ADICIONA EL ARTÍCULO 77 QUINQUIES;\nPUBLICADA EN LA GACETA PARLAMENTARIA No. 111, DE FECHA 19 DE MAYO DE\n2021; Y DECRETO No. 239, PUBLICADO EN EL PERIÓDICO OFICIAL No. 49, SECCIÓN\nIV, TOMO CXXVIII, DE FECHA 09 DE JULIO DE 2021 EXPEDIDO POR LA H. XXIII\nLEGISLATURA, SIENDO GOBERNADOR CONSTITUCIONAL EL C. JAIME BONILLA\nVALDEZ 2019-2021.\nARTÍCULO TRANSITORIO\nPRIMERO.- Toda vez que las presentes reformas solo implican modificaciones al régimen interno del Poder Legislativo, entrarán en vigor al momento de su aprobación por la mayoría calificada del Pleno de este Honorable Congreso del Estado, las cuales se publicarán en la Gaceta Parlamentaria del Poder Legislativo y se remitirán al Poder Ejecutivo solo para su publicación.\nSEGUNDO.- Con la finalidad de no generar afectaciones presupuestales y en salvaguarda de derechos laborales, las coordinaciones instruidas en el artículo 77\nQUNQUIES serán asignadas por la Presidencia de la Mesa Directiva a los trabajadores que actualmente ejercen dichas funciones.\nDado en Sesión Virtual transmitida en la modalidad de videoconferencia a los 18 días\nDIP. EVA GRICELDA RODRÍGUEZ\nPRESIDENTA\nDIP. MARÍA LUISA VILLALOBOS ÁVILA\nSECRETARIA\n.\nActualización Legislativa.\nÚltima reforma Gaceta No. 63, Especial, 14-Ago-2025\nDE CONFORMIDAD CON LO DISPUESTO POR LA FRACCIÓN I DEL ARTÍCULO 49\nCALIFORNIA, IMPRÍMASE Y PUBLÍQUESE.\nMEXICALI, BAJA CALIFORNIA, A LOS VEINTIOCHO DÍAS DEL MES DE MAYO\nDEL AÑO DOS MIL VEINTIUNO.\nJAIME BONILLA VALDEZ\nGOBERNADOR DEL ESTADO\n(RÚBRICA)\nAMADOR RODRÍGUEZ LOZANO\nSECRETARIO GENERAL DE GOBIERNO\n(RÚBRICA)\nARTÍCULO PRIMERO TRANSITORIO DEL RESOLUTIVO DEL DICTAMEN No. 09\nDE LA COMISIÓN DE GOBERNACIÓN, LEGISLACIÓN Y PÚNTOS CONSTITUCIONALES,\nPOR EL QUE SE REFORMA A LOS ARTÍCULOS 56 Y 60; PUBLICADO EN LA GACETA\nPARLAMENTARIA No. 29, DE FECHA 14 DE ENERO DE 2022; ASÍ COMO DEL DECRETO\nNo. 68 PUBLICADO EN EL PERIÓDICO OFICIAL No. 7, NÚMERO ESPECIAL SECCIÓN I,\nTOMO CXXIX, DE FECHA 25 DE ENERO DE 2022, EXPEDIDO POR LA H. XXIV\nLEGISLATURA, SIENDO GOBERNADORA CONSTITUCIONAL LA C. MARINA DEL PILAR\nÁVILA OLMEDA 2021-2027.\nTRANSITORIOS\nPRIMERO. La presente reforma entrará en vigor al momento de su aprobación por el\nPleno de esta Soberanía.\nSEGUNDO. Todas las referencias que se hagan a la Comisión de Igualdad entre\nMujeres, Hombres y Juventud del Congreso del Estado, en la normatividad interna del Poder\nLegislativo y en la legislación estatal, se entenderán hecha a la Comisión de Igualdad de\nGénero y Juventud.\nTERCERO. Publíquese la presente reforma en el Periódico Oficial del Estado, para los efectos conducentes.\nCUARTO. Todos los asuntos turnados a la actual Comisión de Dictamen legislativo de\nIgualdad entre Mujeres, Hombres y Juventud del Congreso del Estado de Baja California, se con su trámite legislativo correspondiente ante la Consultoría legislativa, Oficialía de Partes, Presidencia y demás áreas competentes.\n.\nActualización Legislativa.\nÚltima reforma Gaceta No. 63, Especial, 14-Ago-2025\nAsimismo, las contrataciones de servicios, prestadores de servicios, personal, así como las compras y pagos de productos y servicios en trámites ejercidos con autorización de la Dirección de Administración del Congreso, así como cualquier otro trámite administrativo y compromiso de pago solicitado por la Comisión de Igualdad entre Mujeres, Hombres y Juventud a dicha dirección, serán asumidos y con cargo a la Comisión de\nIgualdad de Género y Juventudes.\nDADO en Sesión Ordinaria Virtual de la XXIV Legislatura en la Ciudad de Mexicali, B.C., a los trece días del mes de enero del año dos mil veintidós.\nDIP. JUAN MANUEL MOLINA GARCÍA\nPRESIDENTE\n(RÚBRICA)\nDIP. ARACELI GERALDO NÚÑEZ\nSECRETARIA\n(RÚBRICA)\nDE CONFORMIDAD CON LO DISPUESTO POR LA FRACCIÓN I DEL ARTÍCULO 49\nCALIFORNIA, IMPRÍMASE Y PUBLÍQUESE.\nMEXICALI, BAJA CALIFORNIA, A LOS DIECINUEVE DÍAS DEL MES DE ENERO\nDEL AÑO DOS MIL VEINTIDOS.\nMARINA DEL PILAR ÁVILA OLMEDA\nGOBERNADORA DEL ESTADO\nDE BAJA CALIFORNIA\n(RÚBRICA)\nCATALINO ZAVALA MÁRQUEZ\nSECRETARIO GENERAL DE GOBIERNO\n(RÚBRICA)\nARTÍCULO ÚNICO TRANSITORIO DEL RESOLUTIVO DEL DICTAMEN No. 12 DE\nLA COMISIÓN DE GOBERNACIÓN, LEGISLACIÓN Y PÚNTOS CONSTITUCIONALES,\nPOR EL QUE SE APRUEBA LA ADICIÓN DE UNA FRACCIÓN XVI AL ARTÍCULO 56,\nCOMO TAMBIEN LA ADICIÓN DEL INCISO M, AL ARTÍCULO 60; PUBLICADO EN LA\nDECRETO No. 69 PUBLICADO EN EL PERIÓDICO OFICIAL No. 9, SECCIÓN III, TOMO\nLEGISLATURA, SIENDO GOBERNADORA CONSTITUCIONAL LA C. MARINA DEL PILAR\nÁVILA OLMEDA 2021-2027.\n.\nActualización Legislativa.\nÚltima reforma Gaceta No. 63, Especial, 14-Ago-2025\nTRANSITORIOS\nPRIMERO. La presente reforma entrará en vigor al momento de su aprobación por el\nPleno de esta Soberanía.\nSEGUNDO. Todas las referencias que se hagan a la Comisión de Desarrollo Social y\nAsuntos Indígenas, en su normatividad interna del Poder Legislativo y en la legislación estatal, se entenderán hecha a la Comisión de Asuntos Indígenas y Bienestar Social.\nTERCERO. Publíquese la presente reforma en el Periódico Oficial del Estado, para los efectos legales conducentes.\nDADO en Sesión Ordinaria Virtual de la XXIV Legislatura en la Ciudad de Mexicali, B.C., a los trece días del mes de enero del año dos mil veintidós.\nDIP. JUAN MANUEL MOLINA GARCÍA\nPRESIDENTE\n(RÚBRICA)\nDIP. ARACELI GERALDO NÚÑEZ\nSECRETARIA\n(RÚBRICA)\nDE CONFORMIDAD CON LO DISPUESTO POR LA FRACCIÓN I DEL ARTÍCULO 49\nCALIFORNIA, IMPRÍMASE Y PUBLÍQUESE.\nMEXICALI, BAJA CALIFORNIA, A LOS VEINTISIETE DÍAS DEL MES DE ENERO\nDEL AÑO DOS MIL VEINTIDOS.\nMARINA DEL PILAR ÁVILA OLMEDA\nGOBERNADORA DEL ESTADO\nDE BAJA CALIFORNIA\nCATALINO ZAVALA MÁRQUEZ\nSECRETARIO GENERAL DE GOBIERNO\n.\nActualización Legislativa.\nÚltima reforma Gaceta No. 63, Especial, 14-Ago-2025\nARTÍCULO PRIMERO TRANSITORIO DEL DECRETO No. 226, POR EL QUE SE\nREFORMA EL ARTÍCULO 40; ASÍ COMO LA ADICIÓN DE UNA SECCIÓN X\nDENOMINADA DE LA UNIDAD DE IGUALDAD DE GÉNERO, EN EL TÍTULO SEXTO,\nCAPÍTULO III, ASÍ COMO LA ADICIÓN DE LOS ARTÍCULOS DE NUEVA CREACIÓN 85\nBIS Y 85 BIS 1; PUBLICADO EN EL PERIÓDICO OFICIAL No. 30, ÍNDICE, TOMO CXXX,\nDE FECHA 26 DE MAYO DE 2023, EXPEDIDO POR LA H. XXIV LEGISLATURA, SIENDO\nGOBERNADORA CONSTITUCIONAL LA C. MARINA DEL PILAR ÁVILA OLMEDA 2021-\n2027.\nTRANSITORIOS\nPRIMERO. Las presentes reformas entrarán en vigor al momento de su aprobación por el\nPleno del Congreso.\nSEGUNDO. Publíquese el presente Decreto en el Periódico Oficial del Estado de Baja\nCalifornia.\nSEGUNDO.- Túrnese el presente Dictamen a la Junta de Coordinación Política de este H.\nCongreso del Estado de Baja California, para que este órgano realice lo conducente en cuanto al trámite legislativo correspondiente.\nDADO en Sesión Extraordinaria de la XXIV Legislatura en la Ciudad de Mexicali, B.C., a los veintiocho días del mes de abril del año dos mil veintitrés.\nDIP. MANUEL GUERRERO LUNA\nPRESIDENTE\n(RÚBRICA)\nDIP. ALEJANDRA MARÍA ANG HERNÁNDEZ\nSECRETARIA\n(RÚBRICA)\nDE CONFORMIDAD CON LO DISPUESTO POR LA FRACCIÓN I DEL ARTÍCULO 49 DE\nBAJA CALIFORNIA, IMPRÍMASE Y PUBLÍQUESE.\nMEXICALI, BAJA CALIFORNIA, A LOS CINCO DÍAS DEL MES DE MAYO DEL AÑO DOS\nMIL VEINTITRÉS.\nMARINA DEL PILAR ÁVILA OLMEDA\nGOBERNADOR DEL ESTADO\nDE BAJA CALIFORNIA\n.\nActualización Legislativa.\nÚltima reforma Gaceta No. 63, Especial, 14-Ago-2025\nCATALINO ZAVALA MÁRQUEZ\nSECRETARIO GENERAL DE GOBIERNO\nDEL ESTADO DE BAJA CALIFORNIA\n(RÚBRICA)\nARTÍCULO ÚNICO TRANSITORIO DEL DECRETO No. 249, POR EL QUE SE\nADICIONA UN CAPÍTULO SEGUNDO AL TÍTULO OCTAVO Y ADICIONA UN ARTÍCULO\n169 BIS; PUBLICADO EN EL PERIÓDICO OFICIAL No. 39, ÍNDICE, TOMO CXXX, DE\nFECHA 07 DE JULIO DE 2023, EXPEDIDO POR LA H. XXIV LEGISLATURA, SIENDO\nGOBERNADORA CONSTITUCIONAL LA C. MARINA DEL PILAR ÁVILA OLMEDA 2021-\n2027.\nTRANSITORIOS\nPRIMERO. La presente reforma entrará en vigor al momento de su aprobación por el Pleno de esta Soberanía.\nSEGUNDO. En un plazo que no deberá exceder de 30 días naturales a partir de la entrada en vigor del presente Decreto, el Departamento de Informática en coordinación con la\nDirección de Procesos Parlamentarios, deberán realizar las modificaciones señaladas en el presente decreto en el Portal de Internet del Congreso del Estado y mantener su actualización.\nTERCERO. Publíquese la presente reforma en el Periódico Oficial del Estado, para los efectos legales conducentes.\nDADO en Sesión Ordinaria de la XXIV Legislatura en la Ciudad de Mexicali, B.C., a los veintidós días del mes de junio del año dos mil veintitrés.\nDIP. MANUEL GUERRERO LUNA\nPRESIDENTE\n(RÚBRICA)\nDIP. ALEJANDRA MARÍA ANG HERNÁNDEZ\nSECRETARIA\nDE CONFORMIDAD CON LO DISPUESTO POR LA FRACCIÓN I DEL ARTÍCULO 49 DE\nBAJA CALIFORNIA, IMPRÍMASE Y PUBLÍQUESE.\nMEXICALI, BAJA CALIFORNIA, A LOS VEINTISIETE DÍAS DEL MES DE JUNIO DEL AÑO\nDOS MIL VEINTITRÉS.\nMARINA DEL PILAR ÁVILA OLMEDA\n.\nActualización Legislativa.\nÚltima reforma Gaceta No. 63, Especial, 14-Ago-2025\nGOBERNADOR DEL ESTADO\nDE BAJA CALIFORNIA\n(RÚBRICA)\nCATALINO ZAVALA MÁRQUEZ\nSECRETARIO GENERAL DE GOBIERNO\nDEL ESTADO DE BAJA CALIFORNIA\n(RÚBRICA)\nARTÍCULO CUARTO TRANSITORIO DEL DECRETO No. 310, POR EL QUE SE\nAPRUEBA LA REFORMA A LOS ARTÍCULOS 16 QUATER, 18, 65, 66, 81, 81 BIS, 81 TER\nY 168, Y LA ADICIÓN DE LA DENOMINACIÓN “DE HERRAMIENTAS DE LA\nTRANSPARENCIA Y RENDICIÓN DE CUENTAS DEL PODER LEGISLATIVO” AL TÍTULO\nOCTAVO, LA REFORMA A LA DENOMINACIÓN DEL CAPÍTULO PRIMERO PARA\nQUEDAR “DECLARACIÓN PATRIMONIAL Y DE INTERÉSES”; PUBLICADO EN EL\nPERIÓDICO OFICIAL No. 62, DE FECHA 06 DE NOVIEMBRE DE 2023, SECCIÓN I, TOMO\nCXXX, EXPEDIDO POR LA H. XXIV LEGISLATURA, SIENDO GOBERNADORA\nCONSTITUCIONAL LA C. MARINA DEL PILAR ÁVILA OLMEDA 2021-2027.\nTRANSITORIOS:\nPRIMERO.- La presente Reforma entrará en vigor al día siguiente de su publicación en el\nPeriódico Oficial del Estado de Baja California.\nSEGUNDO.- La Unidad de Contraloría Interna del Congreso del Estado tendrá un plazo de\n60 días hábiles para la implementación del sistema de información a que se refiere la fracción IV del artículo 81 TER.\nTERCERO.- El Congreso del Estado realizará mesas de trabajo, a fin de analizar y en su momento expedir el Reglamento de Entrega y Recepción de los asuntos y recursos públicos\nDADO en Sesión Ordinaria de la XXIV Legislatura en la Ciudad de Mexicali, B.C., a los diecinueve días del mes de octubre del año dos mil veintitrés.\nDIP. MANUEL GUERRERO LUNA\nPRESIDENTE\nDIP. DUNNIA MONTSERRAT MURILLO LÓPEZ\nSECRETARIA\n.\nActualización Legislativa.\nÚltima reforma Gaceta No. 63, Especial, 14-Ago-2025\nDE CONFORMIDAD CON LO DISPUESTO POR LA FRACCIÓN I DEL ARTÍCULO 49\nCALIFORNIA, IMPRÍMASE Y PUBLÍQUESE.\nMEXICALI, BAJA CALIFORNIA, A LOS VEINTE DÍAS DEL MES DE OCTUBRE DEL\nAÑO DOS MIL VEINTITRÉS.\nMARINA DEL PILAR ÁVILA OLMEDA\nGOBERNADORA DEL ESTADO\nDE BAJA CALIFORNIA\n(RÚBRICA)\nCATALINO ZAVALA MÁRQUEZ\nSECRETARIO GENERAL DE GOBIERNO\nDEL ESTADO DE BAJA CALIFORNIA\n(RÚBRICA)\nARTÍCULO ÚNICO TRANSITORIO DEL DECRETO No. 311, POR EL QUE SE\nAPRUEBA LA REFORMA A LOS ARTÍCULOS 27 Y 28; PUBLICADO EN EL PERIÓDICO\nOFICIAL No. 67, DE FECHA 01 DE DICIEMBRE DE 2023, SECCIÓN I, TOMO CXXX,\nEXPEDIDO POR LA H. XXIV LEGISLATURA, SIENDO GOBERNADORA\nCONSTITUCIONAL LA C. MARINA DEL PILAR ÁVILA OLMEDA 2021-2027.\nTRANSITORIOS\nPRIMERO. La presente reforma entrará en vigor al momento de su aprobación en el Pleno de esta Soberanía.\nSEGUNDO. Publíquese el presente Decreto en la Gaceta Parlamentaria y en el Periódico\nOficial del Estado, para los efectos legales conducentes.\nDADO en Sesión Ordinaria de la XXIV Legislatura en la Ciudad de Mexicali, B.C., a los nueve días del mes de noviembre del año dos mil veintitrés.\nDIP. MANUEL GUERRERO LUNA\nPRESIDENTE\nDIP. DUNNIA MONTSERRAT MURILLO LÓPEZ\nSECRETARIA\n.\nActualización Legislativa.\nÚltima reforma Gaceta No. 63, Especial, 14-Ago-2025\nDE CONFORMIDAD CON LO DISPUESTO POR LA FRACCIÓN I DEL ARTÍCULO 49\nCALIFORNIA, IMPRÍMASE Y PUBLÍQUESE.\nMEXICALI, BAJA CALIFORNIA, A LOS CATORCE DÍAS DEL MES DE NOVIEMBRE\nDEL AÑO DOS MIL VEINTITRÉS.\nMARINA DEL PILAR ÁVILA OLMEDA\nGOBERNADORA DEL ESTADO\nDE BAJA CALIFORNIA\n(RÚBRICA)\nCATALINO ZAVALA MÁRQUEZ\nSECRETARIO GENERAL DE GOBIERNO\nDEL ESTADO DE BAJA CALIFORNIA\n(RÚBRICA)\nARTÍCULO ÚNICO TRANSITORIO DEL DECRETO No. 331, POR EL QUE SE\nAPRUEBA LA REFORMA A LOS ARTÍCULOS 40 TER Y 67; PUBLICADO EN EL\nPERIÓDICO OFICIAL No. 70, DE FECHA 08 DE DICIEMBRE DE 2023, SECCIÓN I, TOMO\nCXXX, EXPEDIDO POR LA H. XXIV LEGISLATURA, SIENDO GOBERNADORA\nCONSTITUCIONAL LA C. MARINA DEL PILAR ÁVILA OLMEDA 2021-2027.\nTRANSITORIOS\nPRIMERO. La presente reforma entrará en vigor al momento de su aprobación en el Pleno de esta Soberanía.\nSEGUNDO. Publíquese la presente reforma en el Periódico Oficial del Estado, para los efectos legales conducentes.\nDADO en Sesión Ordinaria de la XXIV Legislatura en la Ciudad de Mexicali, B.C., a los dieciséis días del mes de noviembre del año dos mil veintitrés.\nDIP. MANUEL GUERRERO LUNA\nPRESIDENTE\nDIP. DUNNIA MONTSERRAT MURILLO LÓPEZ\nSECRETARIA\n.\nActualización Legislativa.\nÚltima reforma Gaceta No. 63, Especial, 14-Ago-2025\nDE CONFORMIDAD CON LO DISPUESTO POR LA FRACCIÓN I DEL ARTÍCULO 49\nCALIFORNIA, IMPRÍMASE Y PUBLÍQUESE.\nMEXICALI, BAJA CALIFORNIA, A LOS VEINTITRÉS DÍAS DEL MES DE\nNOVIEMBRE DEL AÑO DOS MIL VEINTITRÉS.\nMARINA DEL PILAR ÁVILA OLMEDA\nGOBERNADORA DEL ESTADO\nDE BAJA CALIFORNIA\n(RÚBRICA)\nCATALINO ZAVALA MÁRQUEZ\nSECRETARIO GENERAL DE GOBIERNO\nDEL ESTADO DE BAJA CALIFORNIA\n(RÚBRICA)\nARTÍCULO ÚNICO TRANSITORIO DEL DECRETO No. 417, POR EL QUE SE\nAPRUEBA LA REFORMA A LOS ARTÍCULOS 40, 56, 60, 76 y 93; PUBLICADO EN LA\nGACETA PARLAMENTARIA No. 145, DE FECHA 31 DE MARZO DE 2024, Y EN EL\nPERIÓDICO OFICIAL No. 21, ÍNDICE, DE FECHA 26 DE ABRIL DE 2024, TOMO CXXXI,\nEXPEDIDO POR LA H. XXIV LEGISLATURA, SIENDO GOBERNADORA\nCONSTITUCIONAL LA C. MARINA DEL PILAR ÁVILA OLMEDA 2021-2027.\nTRANSITORIOS\nPRIMERO. La presente reforma entrará en vigor al momento de su aprobación por el Pleno de esta Soberanía.\nSEGUNDO. Publíquese la presente reforma en el Periódico Oficial del Estado, para los efectos conducentes.\nDADO en Sesión de Clausura de la XXIV Legislatura en la Ciudad de Mexicali, B.C., a los treinta y un días del mes de marzo del año dos mil veinticuatro.\nDIP. ARACELI GERALDO NÚÑEZ\nPRESIDENTA\nDIP. MANUEL GUERRERO LUNA\nSECRETARIO\n.\nActualización Legislativa.\nÚltima reforma Gaceta No. 63, Especial, 14-Ago-2025\nDE CONFORMIDAD CON LO DISPUESTO POR LA FRACCIÓN I DEL ARTÍCULO 49\nCALIFORNIA, IMPRÍMASE Y PUBLÍQUESE.\nMEXICALI, BAJA CALIFORNIA, A LOS ONCE DÍAS DEL MES DE ABRIL DEL AÑO\nDOS MIL VEINTICUATRO.\nMARINA DEL PILAR ÁVILA OLMEDA\nGOBERNADORA DEL ESTADO\nDE BAJA CALIFORNIA\n(RÚBRICA)\nALFREDO ÁLVAREZ CÁRDENAS\nSECRETARIO GENERAL DE GOBIERNO\nDEL ESTADO DE BAJA CALIFORNIA\n(RÚBRICA)\nARTÍCULO ÚNICO TRANSITORIO DEL DECRETO No. 459, POR LA QUE SE\nAPRUEBAN LAS REFORMAS A LOS ARTÍCULOS 56 y 60; PUBLICADO EN LA GACETA\nPARLAMENTARIA No. 159, DE FECHA 31 DE JULIO DE 2024, Y EN EL PERIÓDICO\nOFICIAL No. 40, ÍNDICE, DE FECHA 16 DE AGOSTO DE 2024, TOMO CXXXI, EXPEDIDO\nPOR LA H. XXIV LEGISLATURA, SIENDO GOBERNADORA CONSTITUCIONAL LA C.\nMARINA DEL PILAR ÁVILA OLMEDA 2021-2027.\nTRANSITORIOS\nPRIMERO. La presente reforma entrará en vigor al momento de su aprobación por el Pleno de esta Soberanía.\nSEGUNDO. Publíquese en la Gaceta del Congreso del Estado de Baja California.\nTERCERO. Publíquese en el Periódico Oficial del Estado, para los efectos conducentes.\nDADO en Sesión Ordinaria de Clausura de la XXIV Legislatura en la Ciudad de Mexicali, B.C., a los treinta y un días del mes de julio del año dos mil veinticuatro.\nDIP. RAMÓN VÁZQUEZ VALADEZ\nPRESIDENTE\nDIP. MANUEL GUERRERO LUNA\nSECRETARIO\n.\nActualización Legislativa.\nÚltima reforma Gaceta No. 63, Especial, 14-Ago-2025\nDE CONFORMIDAD CON LO DISPUESTO POR LA FRACCIÓN I DEL ARTÍCULO 49\nCALIFORNIA, IMPRÍMASE Y PUBLÍQUESE.\nMEXICALI, BAJA CALIFORNIA, AL DÍA PRIMERO DEL MES DE AGOSTO DEL AÑO\nDOS MIL VEINTICUATRO.\nMARINA DEL PILAR ÁVILA OLMEDA\nGOBERNADORA DEL ESTADO\nDE BAJA CALIFORNIA\n(RÚBRICA)\nALFREDO ÁLVAREZ CÁRDENAS\nSECRETARIO GENERAL DE GOBIERNO\nDEL ESTADO DE BAJA CALIFORNIA\n(RÚBRICA)\nARTÍCULO ÚNICO TRANSITORIO DEL DECRETO No. 18, POR EL QUE SE\nAPRUEBA LA REFORMA AL ARTÍCULO 56; MEDIANTE LOS DICTÁMENES NÚMEROS\n10 Y 11 DE LA COMISIÓN DE GOBERNACIÓN, LEGISLACIÓN Y PUNTOS\nCONSTITUCIONALES, PUBLICADOS EN LA GACETA PARLAMENTARIA No. 18, DE\nFECHA 07 DE NOVIEMBRE DE 2024; ASÍ COMO EN EL PERIÓDICO OFICIAL No. 59,\nÍNDICE, DE FECHA 29 DE NOVIEMBRE DE 2024; EXPEDIDO POR LA H. XXV\nLEGISLATURA, SIENDO GOBERNADORA CONSTITUCIONAL LA C. MARINA DEL PILAR\nÁVILA OLMEDA 2021-2027.\nTRANSITORIOS\nPRIMERO. La presente reforma entrará en vigor al momento de su aprobación por el\nPleno de esta Soberanía.\nSEGUNDO. Publíquese en la Gaceta del Congreso del Estado de Baja California.\nDADO en Sesión Ordinaria de la XXV Legislatura en la Ciudad de Mexicali, B.C., a los siete días del mes de noviembre del año dos mil veinticuatro.\nDIP. DUNNIA MONTSERRAT MURILLO LÓPEZ\nPRESIDENTA\nDIP. ALEJANDRA MARÍA ANG HERNÁNDEZ\nSECRETARIA\n.\nActualización Legislativa.\nÚltima reforma Gaceta No. 63, Especial, 14-Ago-2025\nDE CONFORMIDAD CON LO DISPUESTO POR LA FRACCIÓN I DEL ARTÍCULO 49\nCALIFORNIA, IMPRÍMASE Y PUBLÍQUESE.\nMEXICALI, BAJA CALIFORNIA, A LOS DOCE DÍAS DEL MES DE NOVIEMBRE DEL\nAÑO DOS MIL VEINTICUATRO.\nMARINA DEL PILAR ÁVILA OLMEDA\nGOBERNADORA DEL ESTADO\nDE BAJA CALIFORNIA\n(RÚBRICA)\nALFREDO ÁLVAREZ CÁRDENAS\nSECRETARIO GENERAL DE GOBIERNO\nDEL ESTADO DE BAJA CALIFORNIA\n(RÚBRICA)\nARTÍCULO SEGUNDO TRANSITORIO DEL DECRETO No. 78, POR EL QUE SE\nAPRUEBA MEDIANTE EL DICTAMEN No. 23 DE LA COMISIÓN DE GOBERNACIÓN,\nLEGISLACIÓN Y PUNTOS CONSTITUCIONALES LA REFORMA AL ARTÍCULO 170,\nCOMO TAMBIÉN LA ADICIÓN DEL CAPÍTULO TERCERO DENOMINADO DEL\nPARLAMENTO ABIERTO AL TÍTULO OCTAVO; PUBLICADO EN EL PERIÓDICO OFICIAL\nNo. 22, ÍNDICE, DE FECHA 11 DE ABRIL DE 2025, TOMO CXXXII; EXPEDIDO POR LA H.\nXXV LEGISLATURA, SIENDO GOBERNADORA CONSTITUCIONAL LA C. MARINA DEL\nPILAR ÁVILA OLMEDA 2021-2027.\nTRANSITORIOS\nPRIMERO.- La presente reforma entrará en vigor al momento de su aprobación por el Pleno de esta Soberanía.\nSEGUNDO.- Publíquese en la Gaceta del Congreso del Estado de Baja California.\nTERCERO.- Publíquese en el Periódico Oficial del Estado, para los efectos conducentes.\nCUARTO.- El Congreso del Estado tendrá un plazo de 180 días, contados a partir de la entrada en vigor de la presente reforma, para realizar las adecuaciones necesarias en los procesos legislativos internos, a fin de cumplir con los principios establecidos en materia de parlamento abierto. Corresponderá a la Junta de Coordinación Política velar por el cumplimiento de lo anterior.\nDADO en Sesión Ordinaria de la XXV Legislatura en la Ciudad de Tijuana, B.C., a los veintisiete días del mes de marzo del año dos mil veinticinco.\nDIP. EVELYN SÁNCHEZ SÁNCHEZ\nPRESIDENTA\nDIP. MICHELLE ALEJANDRA TEJEDA MEDINA\nSECRETARIA\n.\nActualización Legislativa.\nÚltima reforma Gaceta No. 63, Especial, 14-Ago-2025\nDE CONFORMIDAD CON LO DISPUESTO POR LA FRACCIÓN I DEL ARTÍCULO 49\nCALIFORNIA, IMPRÍMASE Y PUBLÍQUESE.\nMEXICALI, BAJA CALIFORNIA, A LOS 31 DÍAS DEL MES DE MARZO DEL AÑO\nDOS MIL VEINTICUATRO.\nMARINA DEL PILAR ÁVILA OLMEDA\nGOBERNADORA DEL ESTADO\nDE BAJA CALIFORNIA\n(RÚBRICA)\nALFREDO ÁLVAREZ CÁRDENAS\nSECRETARIO GENERAL DE GOBIERNO\nDEL ESTADO DE BAJA CALIFORNIA\n(RÚBRICA)\nARTÍCULO ÚNICO TRANSITORIO DEL DECRETO No. 81, POR EL QUE SE\nAPRUEBA LA REFORMA AL ARTÍCULO 122, MEDIANTE EL DICTAMEN No. 27 DE LA\nCOMISIÓN DE GOBERNACIÓN, LEGISLACIÓN Y PUNTOS CONSTITUCIONALES,\nPUBLICADO EN EL PERIÓDICO OFICIAL No. 22, ÍNDICE, DE FECHA 11 DE ABRIL DE\n2025, TOMO CXXXII; EXPEDIDO POR LA H. XXV LEGISLATURA, SIENDO\nGOBERNADORA CONSTITUCIONAL LA C. MARINA DEL PILAR ÁVILA OLMEDA 2021-\n2027.\nTRANSITORIO\nÚNICO.- La presente reforma entrará en vigor al día siguiente al de su publicación en el\nPeriódico Oficial del Estado.\nDADO en Sesión Ordinaria de la XXV Legislatura en la Ciudad de Tijuana, B.C., a los veintisiete días del mes de marzo del año dos mil veinticinco.\nDIP. EVELYN SÁNCHEZ SÁNCHEZ\nPRESIDENTA\nDIP. MICHELLE ALEJANDRA TEJEDA MEDINA\nSECRETARIA\nDE CONFORMIDAD CON LO DISPUESTO POR LA FRACCIÓN I DEL ARTÍCULO 49\nCALIFORNIA, IMPRÍMASE Y PUBLÍQUESE.\n.\nActualización Legislativa.\nÚltima reforma Gaceta No. 63, Especial, 14-Ago-2025\nMEXICALI, BAJA CALIFORNIA, A LOS 31 DÍAS DEL MES DE MARZO DEL AÑO\nDOS MIL VEINTICUATRO.\nMARINA DEL PILAR ÁVILA OLMEDA\nGOBERNADORA DEL ESTADO\nDE BAJA CALIFORNIA\n(RÚBRICA)\nALFREDO ÁLVAREZ CÁRDENAS\nSECRETARIO GENERAL DE GOBIERNO\nDEL ESTADO DE BAJA CALIFORNIA\n(RÚBRICA)\nARTÍCULO ÚNICO TRANSITORIO DEL DECRETO No. 129, POR EL QUE SE\nAPRUEBA LA REFORMA QUE CREA UN CAPÍTULO CUARTO, Y SE ADICIONA EL\nARTÍCULO 170 BIS, EN EL TÍTULO OCTAVO; PUBLICADO EN LA GACETA No. 63,\nESPECIAL, DE FECHA 14 DE AGOSTO DE 2025, Y EN EL PERIÓDICO OFICIAL No. 54,\nÍNDICE, DE FECHA 05 DE SEPTIEMBRE DE 2025, TOMO CXXXII; EXPEDIDO POR LA H.\nXXV LEGISLATURA, SIENDO GOBERNADORA CONSTITUCIONAL LA C. MARINA DEL\nPILAR ÁVILA OLMEDA 2021-2027.\nTRANSITORIOS\nPRIMERO. La presente reforma entrará en vigor al momento de su aprobación por el Pleno de esta Soberanía.\nSEGUNDO. Publíquese en la Gaceta del Congreso del Estado de Baja California.\nTERCERO. Publíquese en el Periódico Oficial del Estado, para los efectos conducentes.\nDADO en Sesión Ordinaria de la XXV Legislatura en la Ciudad de Mexicali, B.C., a los catorce días del mes de agosto del año dos mil veinticinco.\nDIP. JAIME EDUARDO CANTÓN ROCHA\nPRESIDENTE\nDIP. MICHELLE ALEJANDRA TEJEDA MEDINA\nSECRETARIA\nDE CONFORMIDAD CON LO DISPUESTO POR LA FRACCIÓN I DEL ARTÍCULO 49\nCALIFORNIA, IMPRÍMASE Y PUBLÍQUESE.\nMEXICALI, BAJA CALIFORNIA, A LOS 18 DÍAS DEL MES DE AGOSTO DEL AÑO\nDOS MIL VEINTICINCO.\n.\nActualización Legislativa.\nMARINA DEL PILAR ÁVILA OLMEDA\nGOBERNADORA DEL ESTADO\nDE BAJA CALIFORNIA\nALFREDO ÁLVAREZ CÁRDENAS\nSECRETARIO GENERAL DE GOBIERNO\nDEL ESTADO DE BAJA CALIFORNIA",
  "ordenamiento": "REGLAMENTO",
  "jurisdiccion": "BAJA CALIFORNIA",
  "fuente_oficial": "Periódico Oficial",
  "FECHA PER OFIC": "2025/08/14",
  "ESTATUS": "VIGENTE",
  "TOMO": "TOMO_I",
  "URL": "https://www.congresobc.gob.mx/Documentos/ProcesoParlamentario/Leyes/TOMO_I/20250814_LEYOCONG.PDF",
  "es_escaneado": false,
  "tiene_tablas": true,
  "materia": [
    "administrativo",
    "legislativo",
    "gobernanza"
  ]
}