{
  "titulo": "Ley DEL TRIBUNAL ESTATAL DE JUSTICIA ADMINISTRATIVA DE BAJA CALIFORNIA",
  "Contenido": "BAJA CALIFORNIA\nPublicada en el Periódico Oficial No. 43,\nTÍTULO PRIMERO\nCAPÍTULO PRIMERO\nDISPOSICIONES GENERALES\nARTÍCULO 1. El Tribunal Estatal de Justicia Administrativa de Baja California es un órgano constitucional autónomo, independiente de cualquier autoridad, dotado de plena autonomía jurisdiccional, administrativa y de gestión presupuestal, e imperio suficiente para hacer cumplir sus resoluciones.\nEl Tribunal tendrá a su cargo, dirimir las controversias de carácter administrativo y fiscal que se susciten entre la Administración Pública del Estado, los Municipios, Entidades\nParaestatales, Paramunicipales y los particulares; así como entre el fisco estatal y los fiscos municipales, sobre preferencias en el cobro de créditos fiscales.\nAsimismo, conocerá de las responsabilidades administrativas de los servidores públicos y particulares vinculados con faltas graves promovidas por la Auditoría Superior del\nEstado, Secretaría de la Honestidad y la Función Pública, Sindicaturas Municipales y los\nÓrganos Internos de Control de los entes públicos estatales y municipales, para la imposición de sanciones en términos de lo dispuesto por la Ley de Responsabilidades\nAdministrativas. Así como fincar a los responsables el pago de las indemnizaciones y\nPública Estatal o Municipal, o el patrimonio de los entes públicos estatales o municipales. sanciones a particulares en los términos de la legislación aplicable.\nARTÍCULO 2. El Tribunal formará parte del Sistema Estatal Anticorrupción y estará\nSoberano de Baja California y en el presente ordenamiento.\nLey del Tribunal Estatal de Justicia Administrativa de Baja California. Página 1\nLas resoluciones que emita el Tribunal deberán apegarse a los principios de legalidad, máxima publicidad, respeto a los derechos humanos, verdad material, razonabilidad, proporcionalidad, presunción de inocencia, tipicidad abierta y debido proceso.\nEjercicio del Gasto Público del Estado y las disposiciones aplicables, bajo los principios de legalidad, certeza, independencia, honestidad, responsabilidad y transparencia. Su administración será eficiente bajo el principio de rendición de cuentas.\nDicho ejercicio deberá realizarse con base en los principios de honestidad, responsabilidad, eficiencia, eficacia, transparencia, rendición de cuentas, austeridad, racionalidad y bajo estos principios estará sujeto a la evaluación y control de los órganos correspondientes.\nConforme a los principios a que se refiere el párrafo anterior, y de acuerdo a lo establecido en la Ley de Presupuesto y Ejercicio del Gasto Público, el Tribunal se sujetará a las reglas siguientes:\nI. Ejercerá directamente su presupuesto aprobado por el Congreso del Estado, en términos de lo establecido en la Ley de Presupuesto y Ejercicio del Gasto Publico del\nEstado;\nII. Realizará las adecuaciones presupuestarias en términos de lo establecido en la\nEstado, siempre y cuando no rebase su techo global aprobado por el Congreso del Estado;\nIII. Determinará los ajustes que correspondan a su presupuesto en caso de disminución de ingresos durante el ejercicio fiscal;\nIV. Realizará los pagos, llevará la contabilidad y elaborará sus informes, a través de su propia unidad administrativa;\nV. En los casos que requiera ampliar el presupuesto autorizado del ejercicio, por motivos distintos a los de ampliación automática, mediante la utilización de remanentes obtenidos de ejercicios anteriores, el Tribunal deberá solicitar la autorización al Congreso del\nEstado; y,\nVI. El Tribunal contará con un presupuesto en términos del artículo 55 de la\nLey del Tribunal Estatal de Justicia Administrativa de Baja California. Página 2\nARTÍCULO 3. El principio de carrera jurisdiccional en sus dimensiones de formación, promoción y ascenso, bajo los parámetros de excelencia, objetividad, imparcialidad, profesionalismo e independencia, es uno de los principios rectores de esta ley.\nLos Magistrados y Jueces, durante su periodo constitucional de ejercicio, gozarán de autonomía e independencia, que les permitan desempeñar efectivamente su función con absoluta libertad y seguridad.\nCAPÍTULO SEGUNDO\nINTEGRACIÓN Y COMPETENCIA DEL TRIBUNAL\nARTÍCULO 4. El Tribunal se integra por los órganos siguientes:\nI. El Pleno;\nII. Las Salas Unitarias;\nIII. Una Sala Especializada en Responsabilidades Administrativas y Combate a la\nCorrupción; y,\nIV. Los Juzgados de Primera Instancia.\nARTÍCULO 5. El Pleno estará integrado por tres Magistrados.\nLas Salas tendrán como Titular a un Magistrado.\nLos Juzgados de Primera Instancia tendrán como Titular a un Juez.\nEl Tribunal contará con un Secretario General de Acuerdos, Secretarios de Estudio y\nCuenta, Secretarios de Acuerdos, Actuarios y demás personal que requiera el servicio, quienes estarán adscritos a los órganos y ejercerán las facultades que determine esta Ley.\nARTÍCULO 6. El Tribunal contará con una Sala Especializada en materia de\nResponsabilidades Administrativas y Combate a la Corrupción, que resolverá sobre las sanciones a que se refiere el párrafo tercero del artículo 1 de esta ley.\nARTÍCULO 7. Los Magistrados del Tribunal desempeñarán su cargo por el período que prevea la Constitución del Estado, durante el cual sólo podrán ser removidos por faltas graves, y podrán ser ratificados en los términos que prevea la constitución.\nARTÍCULO 8. Para ser nombrado Magistrado del Tribunal, se requiere:\nLey del Tribunal Estatal de Justicia Administrativa de Baja California. Página 3\nI. Cumplir con los mismos requisitos que para ser Magistrado del Tribunal Superior de\nSoberano de Baja California;\nSentencia a Acción de Inconstitucionalidad 111/2021\nII. Tener por lo menos cinco años de experiencia profesional en Derecho\nAdministrativo o Tributario, responsabilidades administrativas, hechos de corrupción, transparencia o rendición de cuentas;\nIII. No desempeñar ni haber desempeñado cargo de dirección nacional, estatal o municipal en algún partido político en los últimos tres años anteriores a su designación;\nIV. No haber sido candidato, de algún partido político, durante los tres años anteriores a la fecha de la emisión de la convocatoria para el nombramiento;\nV. Presentar su declaración de intereses, patrimonial y fiscal; y,\nVI. Aprobar el examen de conocimientos aplicado en el procedimiento de selección del Fiscal Anticorrupción.\nARTÍCULO 9. Para ser nombrado Juez, se requiere:\nI.- Cumplir con los mismos requisitos que para ser Juez del Poder Judicial del Estado, California;\nSentencia a Acción de Inconstitucionalidad 111/2021\nII. Tener por lo menos cinco años de experiencia profesional en Derecho\nAdministrativo o Tributario, responsabilidades administrativas, hechos de corrupción, transparencia o rendición de cuentas;\nIII. No desempeñar ni haber desempeñado cargo de dirección nacional, estatal o municipal en algún partido político en los últimos tres años anteriores a su designación;\nIV. No haber sido candidato, de algún partido político, durante los tres años anteriores a la fecha de la emisión de la convocatoria para el nombramiento;\nV. Presentar su declaración de intereses, patrimonial y fiscal; y,\nVI. Haber satisfecho los requisitos de la convocatoria que expida el Pleno del Tribunal.\nARTÍCULO 10. Los Jueces serán designados en los términos de esta Ley; durarán cuatro años en el cargo, y podrán ser ratificados hasta por dos periodos más, cuando se\nLey del Tribunal Estatal de Justicia Administrativa de Baja California. Página 4 criterios objetivos que disponga esta Ley. En ningún caso podrán permanecer por más de doce años en el cargo.\nDurante su encargo, los Jueces sólo podrán ser removidos por faltas graves.\nPara la ratificación de los Jueces se tomará en cuenta lo siguiente:\nI. Los cursos de actualización y especialización acreditados de manera fehaciente, durante los últimos cuatro años;\nII. Las sanciones que en su caso se le hubieren impuesto; y,\nIII. Los demás aspectos que el Pleno estime pertinentes.\nARTÍCULO 11. No podrán reducirse los emolumentos de los Magistrados y Jueces durante su encargo. Los Magistrados y Jueces no se considerarán como trabajadores.\nLos Magistrados de Sala, incluyendo al de la Sala Especializada en\nResponsabilidades Administrativas y Combate a la Corrupción, así como los Jueces de\nPrimera Instancia, tendrán los emolumentos previstos en el Presupuesto de Egresos del\nTribunal que apruebe el Congreso del Estado.\nLos emolumentos de los servidores públicos del Tribunal en ningún caso podrán ser menores a los que correspondan a los cargos homólogos del Poder Judicial del Estado de\nBaja California, de acuerdo a la disponibilidad presupuestaria del Tribunal.\nARTÍCULO 12. Las faltas temporales de los Magistrados de Pleno serán cubiertas por el Secretario de Estudio y Cuenta adscrito a la ponencia del Magistrado ausente que cuente con mayor antigüedad en el cargo, la definitivas serán cubiertas en los términos previstos por la Constitución del Estado. Los Titulares de las Salas y de los Juzgados de Primera\nInstancia serán suplidos por su primer Secretario de Acuerdos, en tanto éste se reincorpore o se provea al nombramiento de quien lo sustituirá en los términos de la Ley, según corresponda. Por el periodo de suplencia, el funcionario que cubra la ausencia recibirá los mismos emolumentos del Magistrado o Juez, según corresponda.\nARTÍCULO 13. Las licencias a los Magistrados y Jueces serán resueltas en los términos previstos por la Constitución del Estado, las primeras y las segundas por el Pleno sin goce de sueldo, hasta por dos meses, con excepción de licencias que se soliciten con el objeto de realizar actividades de investigación académica, las cuales podrán otorgarse hasta por seis meses, y por única ocasión durante el período en que estén fungiendo en el cargo.\nLey del Tribunal Estatal de Justicia Administrativa de Baja California. Página 5\nARTÍCULO 14. El Tribunal tendrá un Presidente. Durará en su cargo dos años con la posibilidad de ser reelecto por un periodo adicional.\nARTÍCULO 15. Para ser Secretario de Estudio y Cuenta o Secretario de Acuerdos del\nTribunal, se requiere:\nI. Ser ciudadano mexicano, en pleno ejercicio de sus derechos políticos y civiles;\nII. Poseer título profesional de Licenciado en Derecho, legalmente registrado;\nIII. Notoria buena conducta y con experiencia profesional en materia administrativa y fiscal, de un mínimo de tres años;\nIV. No haber sido condenado por delito intencional; y\nFracción IV invalidada por Sentencia a Acción de Inconstitucionalidad 111/2021\nV. Tener una residencia en el Estado de cinco años anteriores al día de su nombramiento.\nEn el caso de los Secretarios de la Sala Especializada en materia de\nResponsabilidades Administrativas y Combate a la Corrupción, deberán acreditar además de los requisitos anteriores, experiencia profesional de cinco años en materias administrativa, penal y constitucional.\nPara ser Actuario del Tribunal, se requiere cumplir con los mismos requisitos que se establecen para Secretario de Estudio y Cuenta o Secretario de Acuerdos, excepto la experiencia profesional a que se refiere la tercera fracción.\nARTÍCULO 16. Los Magistrados, Jueces, Secretario General de Acuerdos, Secretarios de Estudio y Cuenta, Secretarios de Acuerdos y Actuarios en funciones, estarán impedidos para desempeñar cualquier otro cargo o empleo de la Federación, Estado, Municipio, entidades públicas paraestatales o de índole privada, excepto los de carácter docente u honorifico.\nARTÍCULO 17. Los órganos jurisdiccionales y administrativos del Tribunal contarán con dirección de correo electrónico institucional, mismo que servirá como el medio de comunicación que deberá prevalecer en las correspondencias internas.\nCAPÍTULO TERCERO\nDEL PLENO\nLey del Tribunal Estatal de Justicia Administrativa de Baja California. Página 6\nARTÍCULO 18. El Pleno será el máximo órgano jurisdiccional y administrativo del\nTribunal. Se integrará por tres Magistrados. Para que pueda sesionar, será indispensable la presencia de todos sus miembros.\nARTÍCULO 19. Las resoluciones del Pleno se tomarán por unanimidad o por mayoría de votos de los Magistrados, que no podrán abstenerse de votar, sino cuando tengan impedimento legal.\nARTÍCULO 20. Es competencia del Tribunal en Pleno:\nI. Calificar las excusas, recusaciones e impedimentos de los Magistrados y Jueces y, en su caso, designar a quien deba sustituirlos para la resolución del caso concreto, de conformidad con lo previsto en esta ley;\nII. Resolver los recursos que esta y otras leyes establecen como competencia del\nTribunal, contra los acuerdos y las resoluciones que dicten los Órganos de Primera\nInstancia, y decretar la caducidad en la revisión;\nIII. Resolver los conflictos que surjan entre el Fisco Estatal y los Fiscos Municipales, sobre preferencias en el cobro de créditos fiscales;\nIV. Fijar y modificar la jurisprudencia del Tribunal;\nV. Resolver los conflictos de competencia que se susciten entre los Órganos de\nPrimera Instancia del Tribunal;\nVI. Fijar la circunscripción territorial de los Juzgados de Primera Instancia;\nVII. Dictar sentencia definitiva en los recursos de revisión que se promuevan contra las determinaciones de los Órganos de Primera Instancia, con motivo de la tramitación del recurso previsto en la Ley del Notariado para el Estado de Baja California;\nVIII. Determinar el establecimiento de Salas Unitarias y de Juzgados, ordinarios, auxiliares y especializados, así como el lugar de su residencia;\nIX. Otorgar competencia a los Juzgados de Primera Instancia para que conozcan de los asuntos previstos en el artículo 27, fracción II, de esta Ley, o a la Sala Especializada para conocer de los establecidos en el artículo 26 de esta ley, atendiendo a las necesidades del servicio; y,\nX. Distribuir los asuntos entre los Órganos de Primera Instancia.\nARTÍCULO 21. El Tribunal en Pleno tiene, además, las siguientes atribuciones:\nLey del Tribunal Estatal de Justicia Administrativa de Baja California. Página 7\nI. Designar a su Presidente, y acordar el sistema para suplirlo en caso de faltas temporales;\nII. Nombrar y ratificar a los Jueces de Primera Instancia;\nIII. Determinar la adscripción de los Jueces de Primera Instancia, así como la de los\nSecretarios de Acuerdos y Actuarios;\nIV. Asignar por razón de turno los asuntos que correspondan a las Salas Unitarias;\nV. Llamar al Secretario de Estudio y Cuenta del Magistrado de Pleno ausente, o al\nPrimer Secretario de las Salas o Juzgados, ya sea por falta temporal o definitiva que corresponda de conformidad con lo previsto en el artículo 12 de esta Ley;\nVI. Elaborar, discutir, y aprobar el Presupuesto de Egresos del Tribunal;\nVII. Aprobar y reformar el Reglamento Interno del Tribunal;\nVIII. Nombrar y remover al Secretario General de Acuerdos, Secretarios de Estudio y\nCuenta, Actuarios y demás personal adscrito al Pleno;\nIX. Nombrar y remover a los Secretarios de Acuerdos, Actuarios y demás personal de las Salas y de los Juzgados de Primera Instancia, previa opinión de sus titulares;\nX. Resolver acerca de los permisos, licencias y renuncias del personal, previa opinión del Magistrado o Juez al cual se encuentren subordinados;\nXI. Designar al servidor público adscrito al Pleno que suplirá las faltas temporales del\nSecretario General de Acuerdos;\nXII. Dictar las medidas que exijan el buen servicio y la disciplina del Tribunal e imponer las sanciones administrativas que procedan a los Magistrados, Jueces y demás personal del mismo, en los términos que señalen las disposiciones legales aplicables;\nXIII. Resolver el recurso de apelación que interpongan las partes contra las\nAdministrativas, en los términos de la ley aplicable;\nXIV. Emitir los acuerdos que contengan los lineamientos técnicos y formales que del Boletín Jurisdiccional y del sistema de control de expedientes; y, Ley del Tribunal Estatal de Justicia Administrativa de Baja California. Página 8\nXV. Resolver los demás asuntos que señalen las disposiciones aplicables.\nCAPÍTULO CUARTO\nDEL PRESIDENTE\nARTÍCULO 22. El Presidente del Tribunal será designado de entre sus miembros, en la primera sesión anual del Pleno.\nARTÍCULO 23. Son atribuciones del presidente del Tribunal:\nI. Representar al Tribunal, ante todo tipo de autoridades pudiendo delegar dicha representación por acuerdo del pleno;\nII. Rendir los informes previos y justificados cuando los actos reclamados en los juicios de amparo sean imputados al Pleno, así como informar del cumplimiento dado a las ejecutorias en dichos juicios;\nIII. Conocer y despachar la correspondencia del Pleno;\nIV. Dirigir la Oficialía de Partes y los archivos del Pleno;\nV. Convocar a sesiones plenarias, dirigir sus debates y conservar el orden;\nVI. Autorizar con el Secretario General de Acuerdos las actas del Pleno, en las que se harán constar las deliberaciones y resoluciones que se tomen;\nVII. Publicar los precedentes y la jurisprudencia del Tribunal;\nVIII. Sustanciar los recursos que sean de la competencia del Tribunal en Pleno hasta ponerlos en estado de resolución y designar por turno al Magistrado Ponente;\nIX. Proyectar y someter a la consideración del Pleno, el Presupuesto Anual de\nEgresos del Tribunal y dictar las órdenes relacionadas con el ejercicio del mismo;\nX. Enviar oportunamente el Anteproyecto del Presupuesto de Egresos del Tribunal al\nXI. Proyectar y someter a consideración del Pleno, el Reglamento Interior del Tribunal;\nXII. Suministrar al Congreso Local o al Ejecutivo, los informes que soliciten respecto a la impartición de justicia administrativa;\nLey del Tribunal Estatal de Justicia Administrativa de Baja California. Página 9\nXIII. Formar parte de Comité Coordinador del Sistema Estatal Anticorrupción en términos de lo dispuesto por el artículo 95 de la Constitución Política de Baja California;\nXIV. Las demás que le confiera el Pleno del Tribunal.\nCAPÍTULO QUINTO\nDE LAS SALAS UNITARIAS\nARTÍCULO 24. Las Salas Unitarias estarán integradas por un Magistrado cada una y el personal jurídico y administrativo que sea necesario para el cumplimiento de sus funciones.\nLas Salas Unitarias tendrán a su cargo el dictado de las resoluciones de la competencia del Pleno y de los Órganos de Primera Instancia, conforme la asignación de la carga de expedientes que determine el Pleno del Tribunal, atendiendo a las cargas de trabajo, los requerimientos de administración de justicia y la disponibilidad presupuestaria del\nTribunal.\nCAPÍTULO SEXTO\nDE LOS ÓRGANOS DE PRIMERA INSTANCIA\nARTÍCULO 25. El Tribunal funcionará en primera instancia, a través de los Juzgados y de una Sala Especializada en Responsabilidades Administrativas y Combate a la\nCorrupción, que contarán con el personal jurídico y administrativo que sea necesario para el cumplimiento de sus funciones.\nARTÍCULO 26. Los Juzgados de Primera Instancia del Tribunal son competentes para conocer de los juicios que se promuevan contra los actos o resoluciones definitivas siguientes:\nI. Los de carácter administrativo emanados de las Autoridades Estatales, Municipales o de sus Organismos Descentralizados, cuando éstos actúen como autoridades, que causen agravio a los particulares;\nII. Los de naturaleza fiscal emanados de Autoridades Fiscales Estatales, Municipales o de sus Organismos Fiscales Autónomos, que causen agravio a los particulares;\nIII. Los que versen sobre pensiones y jubilaciones a cargo del Instituto de Seguridad y\nServicios Sociales para los Trabajadores del Estado y Municipios de Baja California;\nIV. Los dictados conforme a otras leyes que le otorguen competencia al Tribunal;\nLey del Tribunal Estatal de Justicia Administrativa de Baja California. Página 10\nV. Los que se emitan con motivo de la aplicación de la Ley del Notariado para el\nEstado de Baja California.\nEn estos casos, el Órgano de Primera Instancia instruirá el procedimiento especial previsto en la Ley del Notariado para el Estado de Baja California, dictando la resolución de primera instancia.\nVI. Las que se susciten entre los Miembros de las Instituciones Policiales del Estado de Baja California y las Dependencias de la Administración Pública Centralizada Estatal o\nMunicipal, con motivo de la prestación de sus servicios, distintas a las previstas en el artículo\n27, fracción II, incisos a) y b);\nVII. Las que resuelvan los recursos administrativos en contra de las resoluciones que se indican en las demás fracciones de este artículo; y,\nVIII. Las demás que determine el Pleno.\nLos Juzgados de Primera Instancia del Tribunal conocerán por razón de territorio, respecto de los juicios que promuevan los particulares o las autoridades, con domicilio en su circunscripción territorial.\nARTÍCULO 27. La Sala Especializada en materia de Responsabilidades\nAdministrativas y Combate a la Corrupción es competente para conocer de:\nI. Los procedimientos y resoluciones a que se refiere el párrafo tercero del artículo 1 de esta Ley, con las siguientes facultades:\na) Resolverá respecto de las faltas administrativas graves, investigadas y sustanciadas por la Auditoría Superior del Estado, Secretaría de la Contraloría y\nTransparencia, Sindicaturas Municipales y órganos internos de control de los entes públicos\nEstatales y Municipales, según sea el caso, ya sea que el procedimiento se haya seguido por denuncia, de oficio o derivado de las auditorías practicadas por las autoridades competentes;\nb) Impondrá sanciones que correspondan a los servidores públicos y particulares, personas físicas o morales, órganos constitucionalmente autónomos y órganos internos de control que intervengan en actos vinculados con faltas administrativas graves, con independencia de otro tipo de responsabilidades. Así como fincar a los responsables el pago de las cantidades por concepto de responsabilidades resarcitorias, las indemnizaciones y\nPública Estatal o Municipal o al patrimonio de los entes públicos Estatales o Municipales; y, Ley del Tribunal Estatal de Justicia Administrativa de Baja California. Página 11\nc) Dictar las medidas preventivas y cautelares para evitar que el procedimiento sancionador quede sin materia, y el desvío de recursos obtenidos de manera ilegal.\nII. Los juicios que se promuevan contra los actos o resoluciones definitivas siguientes:\na) Las que emitan los Órganos de la Administración Pública del Estado, los Municipios\nJudicial del Estado, con motivo de la aplicación de sanciones por responsabilidad administrativa a los servidores públicos, en términos de la legislación aplicable;\nb) Las resoluciones por las que se impongan sanciones administrativas, así como las que determinen la separación, remoción, baja, cese o cualquier otra forma de terminación del servicio de los miembros de las instituciones policiales, en términos de la legislación aplicable;\nc) Las que resuelvan los recursos administrativos en contra de las resoluciones que se indican en los demás incisos de esta fracción; y,\nd) Las demás que determine el Pleno.\nPara la sustanciación del procedimiento de responsabilidad administrativa, la Sala\nEspecializada deberá observar y cumplir con las disposiciones contempladas en la Ley de\nResponsabilidades Administrativas y demás disposiciones aplicables.\nLa Sala Especializada en Responsabilidades Administrativas y Combate a la\nCorrupción tendrá competencia territorial en todo el Estado de Baja California.\nARTÍCULO 28. Los Juzgados y la Sala Especializada contarán con competencia concurrente para conocer de los juicios que se promuevan contra los actos o resoluciones definitivas siguientes:\nI. Las que se originen por fallos en licitaciones públicas y las que versen sobre contratos de obras públicas, adquisiciones, arrendamientos y servicios, y en general de contratos administrativos en los que el Estado, Municipios o sus Organismos\nDescentralizados sean parte;\nII. Las que versen sobre responsabilidad patrimonial del Estado, en los términos de la contengan un régimen especial sobre la materia; y,\nIII. Las que resuelvan los recursos administrativos en contra de las resoluciones que se indican en las demás fracciones de este artículo.\nLey del Tribunal Estatal de Justicia Administrativa de Baja California. Página 12\nPara efectos del presente artículo, cuando en una ciudad tenga su sede uno o más\nAdministrativas y Combate a la Corrupción, operará una oficina de correspondencia común, que recibirá las demandas, las registrará por orden numérico riguroso y las turnará disposiciones que dicte el Pleno.\nARTÍCULO 29. Los Juzgados y la Sala Especializada conocerán también de los juicios que promuevan las autoridades para que sean anuladas las resoluciones administrativas favorables a un particular, en las materias de su competencia.\nARTÍCULO 30. Para efectos de los artículos 26, 27, fracción II, 28 y 29 de esta Ley, son definitivos los actos o resoluciones que no puedan ser revocados o modificados, sino mediante recurso administrativo o medio de defensa previsto por la ley que rija el acto, o en el proceso contencioso administrativo.\nARTÍCULO 31. Son facultades de los Magistrados de las Salas y de los Jueces:\nI. Despachar la correspondencia de la Sala o Juzgado del que sean Titulares;\nII. Aplicar las medidas y criterios que exijan el orden, buen servicio y la disciplina de la\nSala o Juzgado del que sean Titulares;\nIII. Imponer las correcciones disciplinarias en materia laboral al personal;\nIV. Emitir opinión respecto de las solicitudes de licencia que presente el personal de la\nSala o del Juzgado del que sean Titulares;\nV. Rendir oportunamente un informe al presidente del Tribunal, respecto de las labores de la Sala o Juzgado del que sean Titulares, y principales resoluciones dictadas por ellas; y,\nVI. Las demás que les señalen las disposiciones legales.\nARTÍCULO 32. El Magistrado de la Sala Especializada en materia de\nResponsabilidades Administrativas y Combate a la Corrupción, tendrá las atribuciones siguientes:\nI. Admitir, prevenir, reconducir o mejor proveer, la acción de responsabilidades contenida en el informe de presunta responsabilidad administrativa;\nII. Admitir o tener por contestada la demanda, en sentido negativo;\nLey del Tribunal Estatal de Justicia Administrativa de Baja California. Página 13\nIII. Admitir o rechazar la intervención del tercero;\nIV. Admitir, desechar o tener por no ofrecidas las pruebas;\nV. Admitir, desechar y tramitar los incidentes y recursos que le competan;\nVI. Dictar los acuerdos o providencias de trámite necesarios para instruir el procedimiento sancionatorio, incluyendo la imposición de las medidas de apremio necesarias para hacer cumplir sus determinaciones, acordar las promociones de las partes y los informes de las autoridades y atender la correspondencia necesaria, autorizándola con su firma;\nVII. Formular el proyecto de resolución definitiva que corresponda;\nVIII. Dictar los acuerdos y providencias relativas a las medidas cautelares provisionales definitivas en los términos de la Ley de Responsabilidades Administrativas;\nIX. Hacer la designación del perito tercero;\nX. Solicitar la debida integración del expediente para un mejor conocimiento de los hechos en la búsqueda de la verdad material, asimismo el Magistrado instructor podrá acordar la exhibición de cualquier documento que tenga relación con los mismos, ordenar la práctica de cualquier diligencia o proveer la preparación y desahogo de la prueba pericial cuando se planteen cuestiones de carácter técnico y no hubiere sido ofrecida por las partes, en el procedimiento de investigación;\nXI. Dirigir la audiencia de vista con el personal de apoyo administrativo y jurisdiccional que requiera;\nXII. Dar seguimiento y proveer la ejecución de las resoluciones que emita; y,\nXIII. Las demás que les correspondan conforme a las disposiciones legales aplicables.\nCAPÍTULO SÉPTIMO\nDE LOS SECRETARIOS Y ACTUARIOS\nARTÍCULO 33. El Secretario General de Acuerdos estará adscrito al Pleno, y tendrá las siguientes facultades:\nI. Acordar con el Magistrado Presidente, lo relativo a las sesiones del Tribunal en\nPleno;\nLey del Tribunal Estatal de Justicia Administrativa de Baja California. Página 14\nII. Dar cuenta en las sesiones del Pleno, tomar la votación de los Magistrados, formular el acta relativa y comunicar las decisiones que se acuerden;\nIII. Engrosar los fallos del Pleno autorizándolos con su firma en unión del Presidente;\nIV. Llevar el turno de los Magistrados que deban formular ponencias para la resolución del Pleno;\nV. Tramitar y firmar la correspondencia administrativa del Pleno, que no competa al\nPresidente;\nVI. Llevar el registro de las personas que puedan ser designadas peritos terceros o en rebeldía de las partes;\nVII. Expedir y certificar constancias que obran en los expedientes;\nVIII. Proyectar los autos y resoluciones que le indique el Presidente del Tribunal; y,\nIX. Las demás que le encomiende el Presidente del Tribunal, esta Ley y demás\nOrdenamientos legales.\nARTÍCULO 34. Son facultades de los Secretarios de Estudio y Cuenta, las siguientes:\nI. Auxiliar a los Magistrados del Pleno en la formulación de proyectos de resoluciones que se les encomienden;\nII. Suplir las faltas temporales del Secretario General de Acuerdos; y,\nIII. Las demás que les encomienden los Magistrados del Pleno, el Secretario General de Acuerdos, esta Ley y demás disposiciones legales y reglamentarias aplicables.\nLos Secretarios de Estudio y Cuenta estarán adscritos al Pleno.\nARTÍCULO 35. Son facultades de los Secretarios de Acuerdos, las siguientes:\nI. Auxiliar al Titular del Órgano de su adscripción en la formulación de proyectos de autos de trámite y de resoluciones que se les encomienden;\nII. Efectuar las diligencias que les encomiende el Titular del órgano de su adscripción, cuando éstas deban practicarse fuera del local del Tribunal;\nIII. Redactar y autorizar las actas de las audiencias en las que les corresponda dar cuenta y autorizar las resoluciones que recaigan en los expedientes;\nLey del Tribunal Estatal de Justicia Administrativa de Baja California. Página 15\nIV. Expedir y certificar constancias que obren en los expedientes; y,\nV. Las demás que les encomienden los Magistrados, los Jueces, el Secretario\nGeneral de Acuerdos, esta Ley y demás ordenamientos.\nARTÍCULO 36. Son atribuciones de los Actuarios:\nI. Notificar en tiempo y forma prescritos por la Ley, las resoluciones recaídas en los expedientes que para tal efecto les sean turnadas;\nII. Formular los oficios de notificación de los acuerdos que se dicten y enviarlos a su destino, asentado en el expediente, la razón de haber hecho la notificación y de haber entregado los oficios de notificación, respectivos;\nIII. Practicar las diligencias que les encomienden los Magistrados y Jueces de su adscripción; y,\nIV. Las demás que les señalen los Magistrados, los Jueces, el Secretario General de\nAcuerdos, los Secretarios de Estudio y Cuenta y Secretarios de Acuerdos, esta Ley y demás ordenamientos legales aplicables.\nLos Actuarios estarán adscritos al Pleno, a las Salas o a los Juzgados.\nCAPÍTULO OCTAVO\nDEL ÓRGANO DE CONTROL INTERNO\nARTÍCULO 37. El Tribunal contará con un Órgano Interno de Control con autonomía técnica y de gestión que tendrá a su cargo la vigilancia, disciplina y fiscalización del Tribunal, y ejercerá las facultades a que se refiere la fracción III del artículo 92 de la Constitución\nAdministrativas.\nARTÍCULO 38. Corresponde al Titular del Órgano Interno de Control:\nI. Resolver sobre las responsabilidades de los servidores públicos establecidos en el artículo 5, párrafo último, de esta Ley, e imponer, en su caso, las sanciones administrativas correspondientes en términos de la Ley de Responsabilidades Administrativas;\nII. Vigilar el cumplimiento de los acuerdos y demás normas que expida el Pleno, excepto en funciones jurisdiccionales;\nLey del Tribunal Estatal de Justicia Administrativa de Baja California. Página 16\nIII. Comprobar el cumplimiento por parte de los órganos administrativos del Tribunal de las obligaciones derivadas de las disposiciones en materia de planeación, presupuestación, ingresos, egresos, financiamiento, patrimonio y fondos;\nIV. Llevar el registro y seguimiento de la evolución de la situación patrimonial de los servidores públicos del Tribunal;\nV. Inspeccionar y vigilar el cumplimiento de las normas y disposiciones relativas a los sistemas de registro y contabilidad, contratación y pago de personal, contratación de servicios y recursos materiales del Tribunal; y,\nVI. Las demás que determinen las leyes, reglamentos y acuerdos generales correspondientes.\nARTÍCULO 39. El Titular del Órgano Interno de Control deberá reunir los mismos requisitos que la ley de la materia requiera para el Auditor Superior del Estado. [Para el nombramiento del Titular del Órgano Interno de Control se estará al procedimiento contenido\nPorción Normativa de este Artículo 39 invalidada por Sentencia a Controversia Constitucional 356/2023\nCAPÍTULO NOVENO\nDE LAS VACACIONES Y GUARDIAS\nARTÍCULO 40. El personal del Tribunal disfrutará de su período vacacional, en los mismos términos que se señale para el Poder Judicial del Estado.\nAntes de iniciar el período de vacaciones, el presidente designará al personal correspondiente, para que provean y despachen durante el receso, las resoluciones de notoria urgencia relativas a la suspensión de los actos impugnados.\nTÍTULO SEGUNDO\nDEL JUICIO CONTENCIOSO ADMINISTRATIVO\nCAPÍTULO PRIMERO\nDISPOSICIONES GENERALES\nARTÍCULO 41. Los juicios que se promuevan ante el Tribunal, se sustanciarán y resolverán con arreglo al procedimiento que determina este Título, salvo cuando en ley sustanciación del asunto; observándose en todos los casos, los principios de legalidad y buena fe.\nLey del Tribunal Estatal de Justicia Administrativa de Baja California. Página 17 casos siguientes:\nI.- Cuando el promovente sea persona menor o incapaz.\nII.- Cuando se impugne un crédito fiscal que no rebase doscientas veces el valor diario de la unidad de medida y actualización o multas indeterminadas; en el supuesto de que se impugnaren diversos créditos en un sólo juicio, la deficiencia de la queja operará sólo cuando la suma de éstos no exceda el monto señalado.\nIII.- En favor de quienes por sus condiciones de pobreza, marginación o vulnerabilidad se encuentren en clara desventaja social para su defensa en el juicio.\nIV.- En favor de los agentes del Ministerio Público, los peritos y los miembros de las instituciones policiales del Estado y Municipios, salvo que la resolución impugnada verse sobre responsabilidad administrativa.\nA falta de disposición expresa, se aplicarán supletoriamente, el Código Civil y el\nCódigo de Procedimientos Civiles del Estado, siempre que se refiera a Instituciones previstas en esta Ley o la que rija el acto impugnado; y que la disposición supletoria se avenga al juicio administrativo.\nSiempre que esta ley establezca un término para cualquier acto ante el Tribunal, se otorgará un día más por razón de la distancia, en los términos previstos en el Código de\nProcedimientos Civiles para el Estado de Baja California.\nARTÍCULO 42. Son partes en el juicio contencioso administrativo:\nI. El demandante;\nII. El demandado. Tendrá ese carácter:\na) La autoridad que realizó el acto o emitió la resolución impugnada;\nb) El particular a quien favorezca la resolución, cuya nulidad o modificación pida la autoridad administrativa.\nIII. El Titular de la Dependencia o Entidad Administrativa Pública Estatal o Municipal, de la que dependa la autoridad mencionada en la fracción anterior; y,\nIV. El tercero que tenga un derecho incompatible con la pretensión del demandante.\nLey del Tribunal Estatal de Justicia Administrativa de Baja California. Página 18\nARTÍCULO 43. Toda promoción deberá estar firmada por quien la formule y sin este requisito se tendrá por no presentada, a menos que el promovente no sepa o no pueda firmar, caso en el que estampará su huella digital y firmará otra persona a su ruego.\nARTÍCULO 44. Ante el Tribunal no procederá la gestión de negocios. Quien promueva a nombre de otro, deberá acreditar que la representación le fue otorgada a más tardar en la fecha de presentación de la demanda o de la contestación en su caso.\nLa representación de los particulares, se otorgará en Escritura Pública o Carta Poder, firmada ante dos testigos y ratificadas las firmas del otorgante y testigos ante Notario Público o ante el Secretario General de Acuerdos o Secretarios de Acuerdos.\nLos particulares o sus representantes, podrán autorizar por escrito a Licenciado en\nDerecho o Contador Público que a su nombre reciba notificaciones. La persona así autorizada podrá hacer promociones de trámite, rendir pruebas, presentar alegatos e interponer recursos, y realizar cualquier acto que resulte ser necesario para la defensa de los derechos del autorizante, y demás previstas por esta Ley y ordenamientos reglamentarios.\nLos profesionistas autorizados en los juicios contencioso administrativos, podrán ser coadyuvantes de la justicia administrativa para efectos de la entrega de oficios de notificación a las autoridades, en los términos del Reglamento Interior.\nLa representación de las autoridades corresponderá a la Subsecretaría, Dirección, Coordinación o unidad administrativa encargada de su defensa jurídica, en términos de la normatividad aplicable.\nLos Ayuntamientos serán representados en juicio por el Síndico, en los términos de la legislación municipal aplicable.\nTratándose de autoridades colegiadas, la representación legal recaerá en la persona que ostente el carácter de Presidente y en su ausencia, en el titular de la unidad administrativa encargada de su defensa jurídica. delegados, quienes estarán facultados para recibir notificaciones, excepción hecha de los requerimientos, rendir pruebas, alegar, hacer promociones en las mismas audiencias e interponer recursos.\nARTÍCULO 45. En los juicios que se tramiten ante el Tribunal no habrá lugar a condenación en costas. Cada parte será responsable de sus propios gastos y los que originen las diligencias que promuevan.\nLey del Tribunal Estatal de Justicia Administrativa de Baja California. Página 19\nARTÍCULO 46. Cuando las Leyes o Reglamentos de las distintas Dependencias\nEstatales, Municipales o de sus Organismos Descentralizados establezcan medios de defensa o algún recurso administrativo, será optativo para el particular agotarlo o intentar directamente el juicio contencioso administrativo. De igual forma, podrán promover dicho juicio, dentro del plazo legal, cuando una vez interpuesto un recurso administrativo o medio de defensa, se hubieren desistido del mismo.\nARTÍCULO 47. El Tribunal, para hacer cumplir sus determinaciones, podrá aplicar cualquiera de los siguientes medios de apremio y medidas disciplinarias:\nI. Amonestación;\nII. Multa equivalente al valor mensual de la unidad de medida y actualización. Si no se atiende el primer requerimiento, se impondrá multa de tres veces el valor mensual de la unidad de medida y actualización; en caso de persistir la desobediencia, se impondrá multa equivalente al valor anual de la unidad de medida y actualización; y,\nIII. Uso de la fuerza pública.\nLos Magistrados y Jueces del Tribunal en el ejercicio de sus funciones tienen el deber de mantener el buen orden y de exigir que se guarde el respeto y la consideración debidos, corrigiendo en el acto las faltas que se cometieren, haciendo uso de los medios de apremio y medidas disciplinarias que este artículo prevé.\nCAPÍTULO SEGUNDO\nDE LAS NOTIFICACIONES Y TÉRMINOS\nARTÍCULO 48. En el juicio contencioso administrativo las notificaciones se harán:\nI. Mediante Boletín Jurisdiccional;\nII. Personalmente o por correo certificado con acuse recibido; y,\nIII. Por oficio o telegrama.\nARTÍCULO 49. Las notificaciones se harán:\nI. Mediante Boletín Jurisdiccional:\na) A las autoridades, salvo que se trate del emplazamiento.\nb) A los particulares, salvo los supuestos previstos en la fracción III de este artículo.\nLey del Tribunal Estatal de Justicia Administrativa de Baja California. Página 20\nII. Por oficio o telegrama a las autoridades en los casos siguientes:\na) Tratándose del emplazamiento.\nb) Cuando así lo determine el órgano jurisdiccional en virtud de las particularidades del caso, debiendo fundar y motivar su determinación.\nIII. Personalmente o por correo certificado con acuse de recibido a los particulares tratándose de las resoluciones siguientes:\na) La que mande citar a un tercero ajeno a la relación sustancial.\nb) La primera notificación al tercero llamado a juicio y al particular señalado como demandado.\nc) Cuando así lo determine el órgano jurisdiccional en virtud de las particularidades del caso, debiendo fundar y motivar su determinación.\nARTÍCULO 50. Los particulares y las autoridades en su primer escrito en el juicio deberán señalar una dirección de correo electrónico o dirección de correo electrónico institucional, según corresponda, en caso de no hacerlo y hasta en tanto no lo señalen, se les notificará por Boletín Jurisdiccional sin que medie el aviso a que se refiere el artículo 51, fracción II, de esta Ley.\nEs obligación de las dependencias, organismos o autoridades cuyos actos o resoluciones sean susceptibles de impugnarse ante el Tribunal, así como aquéllas encargadas de su defensa en el juicio y quienes puedan promover juicio de lesividad, registrar su dirección de correo electrónico institucional.\nPara los casos contemplados en el artículo 49, fracción III, de esta Ley, los particulares en el primer escrito que presenten, deberán señalar domicilio en la población donde resida el Órgano de Primera Instancia ante el que se promueva, y comunicar en su caso, el cambio del mismo, para que en éste se practiquen las notificaciones que deban ser personales. En caso de no hacerlo así, éstas se realizarán por Boletín Jurisdiccional, hasta en tanto no se señale el domicilio conforme a este párrafo. notificaciones personales. propia administración pública, podrán señalar en su primer escrito como domicilio para recibir notificaciones, las oficinas públicas de dicho departamento o área jurídica en la circunscripción que corresponda a la instancia en que se promueve.\nLey del Tribunal Estatal de Justicia Administrativa de Baja California. Página 21 encontrarse presentes en las oficinas del Tribunal.\nARTÍCULO 51. Las notificaciones mediante Boletín Jurisdiccional se harán conforme a las reglas siguientes:\nI. Se entenderán realizadas con la sola publicación en el Boletín Jurisdiccional.\nII. Previamente a la notificación mediante Boletín Jurisdiccional, deberá enviarse un aviso electrónico a la dirección de correo electrónico o dirección de correo electrónico institucional de la parte a notificar, según sea el caso, de que se realizará la notificación, a más tardar el tercer día siguiente a aquél en que el expediente haya sido turnado al actuario para ese efecto.\nIII. El aviso de notificación deberá ser enviado cuando menos con tres días de anticipación a la publicación del acuerdo, resolución o sentencia de que se trate en el Boletín\nJurisdiccional.\nIV. Dicho aviso deberá incluir el archivo electrónico que contenga el acuerdo o resolución a notificar.\nV. Los particulares y las autoridades, mientras no se haya realizado la notificación por\nBoletín Jurisdiccional, podrán apersonarse en el Tribunal para ser notificados personalmente o por oficio, según corresponda. Una vez realizada la notificación por Boletín Jurisdiccional, las partes, cuando esto proceda, deberán acudir al Tribunal a recoger sus traslados de ley, en el entendido de que con o sin la entrega de los traslados, los plazos comenzarán a computarse a partir del día siguiente al en que surta efectos la notificación correspondiente.\nEl Actuario o el Secretario de Acuerdos, en todos los casos, previo levantamiento de razón, entregará los traslados de ley.\nVI. La notificación surtirá sus efectos al tercer día hábil siguiente a aquél en que se haya realizado la publicación en el Boletín Jurisdiccional.\nVII. El Boletín Jurisdiccional deberá contener el nombre de la persona a quien se notifica, número de expediente, la fecha y síntesis del contenido de los acuerdos o resoluciones de que se trata. El Actuario autorizará con su firma el Boletín, asentando en autos la constancia correspondiente.\nVIII. El Boletín Jurisdiccional podrá consultarse en la página electrónica del Tribunal o juicios.\nLey del Tribunal Estatal de Justicia Administrativa de Baja California. Página 22\nIX. El Tribunal llevará en archivo especial las publicaciones atrasadas del Boletín\nJurisdiccional y hará la certificación que corresponda, a través de los servidores públicos competentes.\nARTÍCULO 52. Las notificaciones surtirán sus efectos al día hábil siguiente a aquel en que se fueron hechas, con excepción de las contempladas en el artículo 49, fracción I, de esta Ley, las cuales surtirán sus efectos al tercer día hábil siguiente a aquél en que se haya realizado la publicación en el Boletín Jurisdiccional.\nEn las actuaciones respectivas, el Actuario deberá asentar la razón del envío por correo o entrega de los Oficios de notificación, así como de las notificaciones personales y por Boletín. Los acuses postales de recibido y las piezas certificadas devueltas, se agregarán como constancia a dichas actuaciones.\nLa notificación omitida o irregular, se entenderá legalmente hecha a partir de la fecha en que el interesado se haga sabedor de la misma, salvo cuando se promueva su nulidad.\nLas notificaciones personales y por oficio, podrán efectuarse a las partes de encontrarse presentes en las oficinas del Tribunal.\nARTÍCULO 53. El cómputo de plazos, se sujetará a las reglas siguientes:\nI. Empezará a correr a partir del día siguiente a aquel en que surta efectos la notificación y serán improrrogables;\nII. Se contarán por días hábiles, entendiéndose por éstos, aquéllos en que se encuentren abiertas al público las oficinas del Tribunal. La existencia de personal de guardia no habilitará los días; y,\nIII. Los plazos serán comunes, con excepción de los que se concedan para la interposición de recursos y para contestar la demanda.\nCAPÍTULO TERCERO\nDE LA IMPROCEDENCIA Y SOBRESEIMIENTO\nARTÍCULO 54. El juicio ante el Tribunal Estatal de Justicia Administrativa es improcedente contra actos o resoluciones:\nI. Cuya impugnación no corresponda conocer al Tribunal;\nII. Que se hayan consumado de modo irreparable o que no afecten el interés jurídico del demandante, entendiéndose por éste, la afectación de un derecho subjetivo o la lesión autoridades fiscales contrarios a la ley.\nLey del Tribunal Estatal de Justicia Administrativa de Baja California. Página 23\nSe considera que no afectan el interés jurídico del demandante, cuando tratándose de expropiaciones, sea dudoso el derecho de propiedad o posesión de la actora por existir terceros que invocan la misma calidad. El juicio podrá iniciarse una vez que sea notificada la sobre el bien afectado.\nIII. Que hayan sido materia de sentencia de fondo pronunciada por el Tribunal, siempre que hubiere identidad de partes y se trate del mismo acto impugnado, aunque las violaciones alegadas sean diversas;\nIV. Respecto de las cuales hubiere consentimiento expreso o tácito, entendiéndose por este último cuando no se promovió medio de defensa en los términos de las Leyes respectivas o juicio ante el Tribunal, en los plazos de la Ley.\nSe considera que existe consentimiento tácito respecto del contenido de un acuerdo de expropiación, cuando el particular opte por el juicio pericial previsto por el artículo 18 de la\nLey de Expropiación para el Estado de Baja California.\nV. Que sean materia de un recurso o juicio que se encuentre pendiente de resolución ante la Autoridad Administrativa Estatal, Municipal, sus Organismos Descentralizados o ante el propio Tribunal;\nVI. Cuando de las constancias de autos apareciere claramente, que no existe la resolución o acto impugnado;\nVII. Que hayan sido materia de resolución en diverso proceso jurisdiccional;\nVIII. Respecto de los cuales hayan cesado los efectos o no puedan surtir sus efectos legales o materiales, por haber dejado de existir el objeto o materia del mismo; o que deriven de actos consentidos;\nIX.- Cuando no se hagan valer motivos de inconformidad, salvo el caso de suplencia de la queja deficiente previsto en el artículo 41 de esta ley;\nX. Cuando la demanda se hubiere interpuesto por la misma parte y en contra del mismo acto impugnado por dos o más ocasiones; y,\nXI. En los demás casos en que la improcedencia resulte de alguna disposición de la\nLey.\nLa procedencia del juicio será examinada aun de oficio.\nLey del Tribunal Estatal de Justicia Administrativa de Baja California. Página 24\nARTÍCULO 55. Procede el sobreseimiento del juicio:\nI. Cuando el demandante se desista del juicio;\nII. Cuando durante el juicio apareciere o sobreviniere alguna de las causales de improcedencia a que se refiere el artículo anterior;\nIII. Cuando el demandante muera durante el juicio, si su pretensión es intrasmisible o si su muerte deja sin materia dicho juicio;\nIV. Cuando la autoridad demandada haya satisfecho la pretensión del actor;\nV. Si el juicio queda sin materia; y,\nVI. En los demás casos, en que por disposición legal exista impedimento para emitir resolución en cuanto al fondo.\nEl sobreseimiento del juicio en los términos previstos por la fracción IV, impide a la autoridad responsable repetir el acto impugnado, motivado en los mismos hechos; en caso contrario el demandante podrá denunciar ante el Órgano de Primera Instancia del conocimiento la repetición del acto, la cual dará vista con la denuncia por un término de cinco días a las autoridades demandadas en el juicio, para que expongan lo que a su derecho convenga. En caso de que el órgano de primera instancia, no obstante, las manifestaciones hechas valer por las autoridades demandadas, encontrará fundada la denuncia correspondiente, requerirá a la autoridad ordenadora la revocación del acto, apercibida de que en caso de insistir se hará acreedora a cualquiera de los medios de apremio previstos en esta Ley.\nARTÍCULO 56. La caducidad de la instancia operará de pleno derecho, cualquiera que sea el estado del procedimiento, desde la presentación de la demanda hasta antes de que se cite a las partes para oír resolución, si transcurridos seis meses naturales contados a partir de la notificación de la última determinación jurisdiccional, no hubiere promoción, de cualquiera de las partes, que tienda a llevar adelante el procedimiento, siempre que la promoción sea necesaria para la continuación de procedimiento en el juicio o en la revisión. parte interesada. Es de orden público, irrenunciable, no puede ser materia de convenio entre partes, ya sea en el expediente principal o en cualquier incidente.\nCaducado el expediente principal caducan los incidentes. La caducidad del incidente sólo produce la del principal cuando haya suspendido el procedimiento de éste.\nLey del Tribunal Estatal de Justicia Administrativa de Baja California. Página 25\nEn los juicios que se encuentren en revisión, la inactividad producirá la caducidad de esa instancia y el Pleno declarará firme la resolución recurrida. tribunales no puedan actuar, y en los casos en que es necesario esperar la resolución de una cuestión principal, previa o conexa, por el mismo juzgador o por otra autoridad jurisdiccional.\nLos actos o promociones de mero trámite, que no impliquen ordenación o impulso al procedimiento, no se considerarán como actividad procesal de las partes ni impedirán que la caducidad se consume.\nCAPÍTULO CUARTO\nDE LOS IMPEDIMENTOS\nARTÍCULO 57. Los Magistrados y Jueces del Tribunal estarán impedidos para conocer de los juicios en que intervengan, en los casos siguientes:\nI. Si son cónyuges o parientes consanguíneos o civiles de las partes o de sus representantes; en línea recta, sin limitación de grado. Dentro del cuarto grado en la colateral por consanguinidad, o dentro del segundo en la colateral por afinidad;\nII. Si tienen interés personal en el asunto que haya motivado el juicio;\nIII. Si han sido Abogados o Apoderados de las partes en el mismo asunto;\nIV. Si tuviesen amistad estrecha o enemistad manifiesta con alguna de las partes o con sus representantes;\nV. Si hubiesen aconsejado como asesores respecto del acto impugnado, o si hubiesen emitido, en otra instancia, la resolución o procedimiento combatido;\nVI. Si son partes en un juicio similar pendiente de resolución por el Tribunal; y,\nVII. Si hubiesen dictado en la primera instancia del juicio la resolución recurrida.\nARTÍCULO 58. Los Magistrados y los Jueces del Tribunal que se consideren impedidos para conocer de algún asunto, harán la manifestación ante el Pleno del Tribunal, el que calificará la excusa y en su caso, procederá en los términos previstos en esta Ley.\nARTÍCULO 59. En caso de excusa, recusación o impedimento de los Magistrados y\nJueces, conocerá del asunto:\nLey del Tribunal Estatal de Justicia Administrativa de Baja California. Página 26\nI. Tratándose de un Magistrado del Pleno, éste se integrará, para efectos del conocimiento del asunto en cuestión, por el Secretario de Estudio y Cuenta adscrito a la ponencia del Magistrado impedido, que cuente con mayor antigüedad en el cargo.\nII. En el caso del Magistrado Especializado en materia de Responsabilidades\nAdministrativas y Combate a la Corrupción, el Tribunal en Pleno resolverá de conformidad con lo establecido en artículo 20, fracción IX de esta Ley.\nIII. Cuando se trate de los Jueces de Primera Instancia, conocerá del asunto el siguiente en orden numérico de la misma ciudad y, de no haberlo, el del Estado.\nIV. Cuando se trate de los Magistrados de las Salas Unitarias, conocerá del asunto la siguiente en orden numérico y, de no haberlo, el Tribunal en Pleno resolverá de conformidad con lo establecido en artículo 20, fracción IX de esta Ley.\nARTÍCULO 60. El Magistrado y el Juez que teniendo impedimento para conocer de un negocio no haga la manifestación correspondiente, o que, no teniéndolo, presente excusa apoyándose en causas diversas de las señaladas en el artículo 57 de esta ley, pretendiendo que se le aparte del conocimiento del juicio, incurre en responsabilidad.\nARTÍCULO 61. Cuando uno de los integrantes del Pleno se excuse o sea recusado, los restantes resolverán lo conducente. En caso de empate, el Presidente tendrá voto de calidad. Si el Presidente es quien se excusa o es recusado, el voto de calidad lo tendrá el\nPresidente suplente.\nCAPÍTULO QUINTO\nDE LA DEMANDA\nARTÍCULO 62. La demanda deberá formularse por escrito, salvo el caso previsto en el artículo 150 de esta Ley, y presentarse directamente ante el Órgano de Primera Instancia correspondiente al domicilio del demandante o enviarse por correo certificado, dentro de los quince días siguientes, a aquel en que haya surtido efectos la notificación del acto o resolución impugnados conforme a la ley del acto, o al día en que se haya tenido conocimiento del mismo.\nLa entrega de una resolución, por escrito al particular, se considera como notificación, aunque no se utilice este término por la autoridad.\nLos efectos de la presentación de la demanda ante el Tribunal, son interrumpir la prescripción de los derechos del demandante, así como de las facultades de la autoridad responsable, si no lo están por otros medios y señalar el principio de la instancia. La prescripción referida, comenzará a correr una vez que la sentencia respectiva haya causado ejecutoria.\nLey del Tribunal Estatal de Justicia Administrativa de Baja California. Página 27\nEn los casos de negativa ficta, el interesado podrá interponer la demanda en cualquier tiempo mientras no se dicte resolución expresa. Si en la ley de la materia se contempla la negativa ficta, habrá de estarse al término previsto en esa ley para su configuración. En caso de que no se prevea esa figura, entonces el silencio de la autoridad a la petición, instancia o sesenta días naturales, contados a partir de la presentación de la solicitud o la instancia.\nLas autoridades podrán deducir la acción de lesividad de sus actos o resoluciones que hayan resultado a favor de los particulares, dentro de los cinco años siguientes a la fecha en que se hayan notificado los mismos, salvo que dichos actos o resoluciones hayan producido efectos de tracto sucesivo, caso en el cual la autoridad podrá demandar la nulidad en cualquier época, sin exceder de los cinco años del último efecto producido.\nLa autoridad que deduce la acción de lesividad podrá invocar para tal efecto, la incompetencia de quién emitió los actos o resoluciones, la indebida fundamentación y motivación de los mismos, derivada del error de quién emitió el acto o resolución, el dolo del particular beneficiado, el pago de lo indebido, el reconocimiento u otorgamiento de los derechos que no correspondan, así como el indebido ejercicio de facultades discrecionales.\nARTÍCULO 63. En cada demanda sólo podrá aparecer un demandante, salvo en los casos que se trate de la impugnación de resoluciones conexas, o que se afecte los intereses jurídicos de dos o más personas, mismas que podrán promover el juicio contra dichas resoluciones en una sola demanda.\nEn los casos en que sean dos o más demandantes éstos ejercerán su acción a través de un representante común.\nEn la demanda en que promuevan dos o más personas en contravención de lo dispuesto en los párrafos anteriores, el Órgano de Primera Instancia requerirá a los promoventes para que en el plazo de cinco días presenten cada uno de ellos su demanda correspondiente, apercibidos que de no hacerlo se desechará la demanda inicial.\nARTÍCULO 64. En los actos impugnables ante el Tribunal deberá indicarse la procedencia del juicio contencioso administrativo en su contra, el plazo para su interposición y el órgano ante el que debe promoverse. Cuando se omita el señalamiento de referencia, para interponer el juicio contencioso administrativo.\nARTÍCULO 65. El demandante tendrá derecho de ampliar la demanda dentro de los demanda, en los casos siguientes:\nLey del Tribunal Estatal de Justicia Administrativa de Baja California. Página 28\nI. Cuando se demanda una negativa ficta; y\nII. Cuando el demandante no conozca los fundamentos o motivos del acto impugnado, sino hasta que la demanda esté contestada.\nEn los casos anteriores, la omisión de la ampliación de la demanda no traerá como y motivos expresados al contestarse la demanda.\nARTÍCULO 66. La demanda deberá indicar:\nI. Nombre del demandante, así como domicilio y dirección de correo electrónico para oír y recibir notificaciones.\nCuando el demandante sea un particular, además, deberá declarar bajo protesta de decir verdad su domicilio particular.\nII. Resolución o acto administrativo que se impugne;\nIII. Autoridad o autoridades demandadas o el nombre y domicilio del particular demandado, cuando el juicio sea promovido por la autoridad administrativa;\nIV. Nombre y domicilio del tercero perjudicado, en su caso;\nV. Los hechos que den motivo a la demanda, bajo protesta de decir verdad;\nVI. La fecha en que se tuvo conocimiento del acto o resolución impugnada;\nVII. Las pruebas que ofrezca; y,\nVIII. La expresión de los motivos de inconformidad, los cuales deberán consistir en el señalamiento de una o varias de las causales de nulidad previstas en esta Ley, así como los hechos y razones por las cuales se consideran aplicables al acto o resolución impugnada.\nTratándose de resoluciones dictadas en recursos administrativos, el demandante deberá expresar motivos de inconformidad contra éstas, y simultáneamente podrá repetir, como motivos de inconformidad, los agravios expresados dentro del recurso intentando, o dentro del recurso. En todos los casos el demandante se deberá sujetar a lo dispuesto en la fracción VIII.\nARTÍCULO 67. El demandante deberá adjuntar a su demanda:\nLey del Tribunal Estatal de Justicia Administrativa de Baja California. Página 29\nI. Una copia de la demanda y de los documentos anexos para cada una de las partes y dos para el cuaderno de suspensión, siempre que se pidiere;\nII. El documento que acredite su personalidad o en el que conste que le fue reconocida por la autoridad demandada, cuando no se gestione en nombre propio;\nIII. El documento en que conste la resolución o acto impugnado, o en caso de negativa ficta, copia de la instancia no resuelta por la autoridad;\nIV. Constancia de la notificación del acto impugnado, excepto cuando el demandante declare bajo protesta de decir verdad, que no recibió constancia o cuando hubiese sido por correo. Si la notificación fue por Edictos, deberá señalar la fecha de la última publicación y el nombre del órgano en que ésta se hizo;\nV. Las pruebas documentales que ofrezca.\nSi al examinarse la demanda, se advierte que ésta es obscura o irregular, o cuando no se adjunten las copias o documentos a que se refiere este precepto, el Órgano de\nPrimera Instancia requerirá al demandante, para que la corrija, aclare, complete o exhiba los documentos en el plazo de cinco días, apercibiéndolo de que, en caso de no hacerlo, se desechará de plano la demanda o se tendrán por no ofrecidas las pruebas, en su caso.\nLa falta de exhibición de las copias para el cuaderno de suspensión, sólo dará lugar a la postergación de su apertura.\nARTÍCULO 68. De contar el órgano jurisdiccional con elementos que hagan presumir que el demandante hubiera declarado falsamente en los casos previstos en los artículos 66, fracción I párrafo segundo, y fracción V, y 67, fracción IV, de esta Ley, se dará vista al\nMinisterio Público del Estado por la posible comisión del delito de falsedad ante las autoridades establecido en el artículo 320 del Código Penal para el Estado, acompañando las constancias que se estimen necesarias.\nARTÍCULO 69. La demanda se admitirá dentro de las veinticuatro horas siguientes a la de su presentación. En el mismo auto se aceptará o rechazará la intervención del tercero y se tendrán por ofrecidas las pruebas del actor, mismas que se admitirán o desecharán hasta que se fije la litis.\nARTÍCULO 70. En cualquier etapa del juicio, hasta antes de la citación para sentencia, las partes podrán celebrar convenios para conciliar sus intereses. En tal caso, los instancia del conocimiento para que, en su caso, sea elevado a la categoría de cosa juzgada.\nLey del Tribunal Estatal de Justicia Administrativa de Baja California. Página 30\nARTÍCULO 71. La demanda se desechará, en los casos siguientes:\nI. Si se encontrase motivo manifiesto o indudable de improcedencia.\nLa causal de improcedencia prevista en el artículo 54, fracción IX, de esta Ley, no originará en ningún caso el desechamiento de la demanda, sino únicamente el sobreseimiento en resolución definitiva, en su caso.\nII. Cuando prevenido el demandante para subsanar los defectos de la misma, no lo hiciere en el plazo de Ley.\nCAPÍTULO SEXTO\nDE LA CONTESTACIÓN\nARTÍCULO 72. Admitida la demanda, se correrá traslado de ella a las partes para que contesten dentro del plazo de quince días siguientes a aquél en que surta efectos la notificación del emplazamiento. El plazo para contestar la ampliación de la demanda, también será de quince días, a partir de aquél en que surta efectos la notificación del acuerdo que la admita.\nCuando alguna autoridad que deba ser parte en el juicio no fuese señalada por el demandante como demandada, de oficio se le correrá traslado de la demanda para que la conteste en el plazo a que se refiere el párrafo anterior.\nSi no se produce la contestación en tiempo, o ésta no se refiere a todos los hechos, se tendrán como ciertos los que el demandante impute de manera precisa al demandado, salvo que, por las pruebas rendidas, o por hechos notorios, resulten desvirtuados.\nARTÍCULO 73. La parte demandada, en su contestación, se referirá a cada uno de los hechos señalados en el escrito de demanda, citará los fundamentos legales que considere aplicables al caso y ofrecerá las pruebas que estime pertinentes. Asimismo, deberá anexarse el documento en que se acredite la personalidad, cuando el demandado sea un particular y no gestione en nombre propio. de los documentos anexos a ella para cada una de las partes, y en su defecto, se requerirá al demandado para que exhiba los documentos o copias en el plazo de cinco días, apercibiéndole de que, en caso de no hacerlo, se desechará la contestación de la demanda o se tendrán por no ofrecidas las pruebas, en su caso. pruebas de las partes, y se ordenen las diligencias correspondientes para el desahogo.\nLey del Tribunal Estatal de Justicia Administrativa de Baja California. Página 31\nARTÍCULO 74. El tercero perjudicado que no haya sido llamado a juicio, podrá apersonarse a juicio hasta antes del cierre de instrucción, formulando alegatos y aportando las pruebas que considere pertinentes.\nARTÍCULO 75. En la contestación de la demanda no podrán cambiarse los fundamentos de derecho de la resolución impugnada. En el caso de resolución de negativa ficta, la autoridad expresará los hechos y el derecho en que se apoye la misma.\nEn la contestación de la demanda o hasta antes del cierre de instrucción, la autoridad demandada podrá revocar la resolución impugnada o allanarse a las pretensiones del demandante. De ocurrir alguno de estos supuestos, se dará vista al demandante para que manifieste lo que a su derecho convenga en el plazo de tres días; de no haber oposición se considerará que ha quedado sin materia el juicio y, en consecuencia, procederá el sobreseimiento total o, en su caso, parcial.\nARTÍCULO 76. La contestación de la demanda y de la ampliación de demanda, en su caso, se acordará dentro de los tres días siguientes al de su presentación.\nEn el acuerdo en que se provea el escrito con el que se fije la litis, se tendrán por admitidas o desechadas las pruebas ofrecidas por las partes, y de ser necesario, se proveerá sobre la preparación que fuere necesaria para su desahogo, debiendo señalarse fecha dentro de los treinta días siguientes, para la celebración de la audiencia referida en el artículo 104 de esta ley.\nSi no se hubiere ofrecido prueba que requiera audiencia o diligencia para su desahogo y no existiere cuestión alguna pendiente que impida la resolución del juicio, en el mismo acuerdo se ordenará dar vista a las partes con los autos para que dentro del término de cinco días formulen alegatos por escrito. De existir alguna diligencia pendiente, una vez resuelta, se otorgará a las partes el plazo para formular alegatos.\nAl vencer el plazo de cinco días para formular alegatos, con alegatos o sin ellos, quedará cerrada la instrucción del juicio y se entenderá citado para sentencia, sin necesidad de una declaratoria expresa, y a partir del día siguiente empezará a computarse el plazo previsto en el artículo 105 de esta Ley.\nCAPÍTULO SÉPTIMO\nDE LA SUSPENSIÓN\nARTÍCULO 77. La suspensión se tramitará en cuaderno por separado y por duplicado. veinticuatro horas siguientes a su solicitud, haciéndolo saber a la autoridad demandada, para su cumplimiento, si se concede.\nLey del Tribunal Estatal de Justicia Administrativa de Baja California. Página 32 informe relativo a la suspensión definitiva, que deberá rendirse en el término de cuarenta y ocho horas siguientes a aquél en que surta efectos la notificación del acuerdo respectivo.\nVencido el término, con el informe o sin él, se resolverá la suspensión definitiva, dentro de los cinco días siguientes. considere necesarias, a efecto de resolver sobre la suspensión definitiva. En el cuaderno de suspensión, únicamente se admitirán las pruebas documentales y de inspección judicial.\nARTÍCULO 78. La suspensión podrá solicitarla el demandante en la demanda o en cualquier momento del juicio y tendrá por efecto mantener las cosas en el estado en que se encuentren, hasta en tanto se pronuncie sentencia ejecutoria.\nLa suspensión podrá concederse con efectos restitutorios, cuando se trate de actos privativos de libertad decretados al particular por la autoridad administrativa, cuando a juicio del órgano jurisdiccional sea necesario otorgarle estos efectos con el objeto de preservar la materia del litigio o impedir perjuicios irreparables al particular, o cuando atendiendo a la naturaleza del acto reclamado sea jurídica y materialmente posible.\nARTÍCULO 79. La suspensión definitiva podrá ser revocada en cualquier momento del juicio si varían las condiciones bajo las cuales se otorgó.\nARTÍCULO 80. No se otorgará la suspensión, si se sigue perjuicio a evidente interés social, si se contravienen disposiciones de orden público o se deja sin materia el juicio.\nARTÍCULO 81. Cuando los actos materia de impugnación, hubieren sido ejecutados y afecten a los particulares de escasos recursos económicos, impidiendo el ejercicio de su única actividad personal de subsistencia, y entre tanto se pronuncie la resolución que corresponda, los Órganos de Primera Instancia podrán dictar las medidas cautelares que estimen pertinentes, para preservar el medio de subsistencia del quejoso.\nLas medidas cautelares que dicten, no serán impugnables en procedimiento.\nARTÍCULO 82. Cuando el acto impugnado verse sobre determinación, liquidación, ejecución o cobro de contribuciones o créditos de naturaleza fiscal, podrá concederse la suspensión, la que surtirá efectos si se ha constituido o se constituye la garantía del interés fiscales aplicables, o en su caso, si se acredita que la garantía le fue dispensada por dichas autoridades.\nLey del Tribunal Estatal de Justicia Administrativa de Baja California. Página 33\nTribunal, siempre que el demandante acredite ser persona de escasos recursos económicos de la unidad de medida y actualización. En el supuesto de que se impugnaren diversos créditos en un sólo juicio, si la suma de éstos excede el equivalente señalado, el demandante deberá garantizar el interés fiscal, para que subsista la suspensión obtenida previamente.\nEl órgano jurisdiccional está facultado para reducir el monto de la garantía o dispensar su otorgamiento, en los casos siguientes:\nI. Si realizado el embargo por las autoridades fiscales, éste haya quedado firme y los bienes del contribuyente embargados fueran suficientes para asegurar la garantía del interés fiscal;\nII. Si el monto de los créditos excediere la capacidad económica del demandante; y,\nIII. Si se tratase de tercero distinto al sujeto obligado de manera directa o solidaria al pago del crédito.\nARTÍCULO 83. En los casos en que proceda la suspensión, pero pueda ocasionar daños o perjuicios a terceros, se concederá si el demandante otorga garantía bastante para reparar el daño e indemnizar los perjuicios que con aquella se causaren, si no obtiene sentencia favorable en el juicio.\nCuando con la suspensión puedan afectarse los derechos de terceros no estimables en dinero, el Órgano de Primera Instancia fijará discrecionalmente el importe de la garantía.\nARTÍCULO 84. La suspensión otorgada conforme al artículo anterior, quedará sin efecto si el tercero otorga a su vez, caución bastante para restituirlas cosas al estado que guardaban antes de la violación y pagar los daños y perjuicios que sobrevengan al demandante, en el caso de que éste obtenga sentencia favorable.\nPara que surta efectos la caución que ofrezca el tercero, en el caso del párrafo anterior, deberá cubrir el costo de la que hubiere otorgado el demandante.\nARTÍCULO 85. La suspensión, cualquiera que sea su naturaleza, surtirá sus efectos desde el momento en que se pronuncie el acuerdo relativo, aun cuando sea recurrido.\nLos efectos de la suspensión dejarán de surtirse, en su caso, si dentro del plazo de cinco días siguientes al en que surta efectos la notificación del acuerdo de suspensión, el demandante no otorga la garantía y así lo determina el órgano jurisdiccional. Al vencimiento\nLey del Tribunal Estatal de Justicia Administrativa de Baja California. Página 34 demandadas, las que podrán ejecutar el acto impugnado. No obstante lo anterior, mientras no se ejecute, el demandante podrá exhibir la garantía, con lo cual, de inmediato, vuelve a surtir efectos la medida suspensional.\nARTÍCULO 86. Para hacer efectivas las garantías otorgadas con motivo de la suspensión, el interesado deberá solicitarlo dentro de los treinta días siguientes a la notificación de la sentencia; se dará vista con la solicitud a las demás partes por un término de cinco días y citará a una audiencia de pruebas y alegatos dentro de los cinco días siguientes, en la que dictará la sentencia que corresponda.\nCAPÍTULO OCTAVO\nDE LOS INCIDENTES\nARTÍCULO 87. En el juicio contencioso administrativo, serán de previo y especial pronunciamiento, los siguientes incidentes:\nI. Acumulación de autos;\nII. Nulidad de notificaciones; y,\nIII. Recusación por impedimento.\nARTÍCULO 88. Procede la acumulación de dos o más juicios pendientes de resolución, en los casos en que:\nI. Las partes sean las mismas y se invoquen idénticos agravios;\nII. Siendo diferentes las partes e invocándose distintos agravios, el acto impugnado sea uno mismo o se impugne varias partes del mismo acto; y,\nIII. Independientemente de que las partes y los agravios sean o no diversos, se impugnen actos o resoluciones que sean unos antecedentes o consecuencias de los otros.\nARTÍCULO 89. Las partes podrán hacer valer el incidente de acumulación de autos, hasta antes del cierre de instrucción. ante el Órgano de Primera Instancia que esté conociendo del juicio más reciente, el cual, en el plazo de cinco días, resolverá lo que proceda.\nARTÍCULO 91. Una vez decretada la acumulación, el Órgano de Primera Instancia que conozca del juicio más reciente, deberá turnar los autos al que conoció del primer juicio, en un plazo que no exceda de tres días. Cuando no pueda concretarse la acumulación\nLey del Tribunal Estatal de Justicia Administrativa de Baja California. Página 35 porque en alguno de los juicios se hubiere cerrado la instrucción, a petición de parte, o de oficio, se decretará la suspensión del procedimiento en el juicio en trámite; la suspensión subsistirá hasta que pronuncie la resolución definitiva en el otro negocio.\nARTÍCULO 92. Las notificaciones que no fueren hechas conforme a lo dispuesto en la\nLey, o en su caso, de acuerdo con las disposiciones aplicables, serán nulas. El perjudicado, podrá pedir que se declare la nulidad, dentro de los cinco días siguientes a aquél en que conoció el hecho, ofreciendo las pruebas pertinentes en el mismo escrito en el que se promueva la nulidad. Las promociones de nulidad notoriamente infundadas, se desecharán de plano. Si se admite el incidente, se dará vista a las demás partes por el término de cinco días, para que expongan lo que a su derecho convenga; transcurrido dicho plazo, en un término también de cinco días, se dictará la interlocutoria respectiva.\nSi se declara la nulidad de la notificación impugnada, se ordenará la reposición de la misma y la de todas las actuaciones subsecuentes, hasta la fecha en que se haya declarado la nulidad.\nARTÍCULO 93. Las partes podrán recusar a los Magistrados y Jueces, cuando estén en alguno de los casos de impedimento a que se refiere esta Ley.\nARTÍCULO 94. La recusación de Magistrados y Jueces se promoverá ante el Tribunal en Pleno, en cualquier estado del juicio hasta antes del cierre de instrucción, mediante escrito al que acompañarán las pruebas pertinentes.\nEl Presidente del Tribunal ordenará al Magistrado o Juez objeto de la recusación que en el plazo de cinco días rinda un informe sobre la materia. A falta de informe, se presumirá cierto el impedimento. Si el Pleno declara fundada la recusación, el Magistrado o Juez será sustituido en los términos de esta Ley.\nLos Magistrados que conozcan de una recusación, son irrecusables para ese sólo efecto.\nARTÍCULO 95. Los afectados por el exceso o defecto de la ejecución del auto en que declarado procedente la pretensión del demandante, podrán inconformarse ante el órgano hecho, ofreciendo las pruebas pertinentes en su caso. Si se admite el incidente, se dará vista a las demás partes por el término de cinco días, para que expongan lo que a su derecho convenga; transcurrido dicho plazo, en un término también de cinco días, el órgano de primera instancia dictará la interlocutoria respectiva.\nÓrgano de Primera Instancia al exigir el cumplimiento, no se ajusta al tenor exacto del auto\nLey del Tribunal Estatal de Justicia Administrativa de Baja California. Página 36 alcance; en tanto, hay defecto, cuando la autoridad deja de cumplir en su integridad lo ordenado, esto es, deja de hacer algo que se le ordenó en el auto o sentencia de cuya ejecución se trata. incidente deberá plantearse hasta que el Órgano de Primera Instancia correspondiente tenga por cumplida la sentencia o la suspensión del acto reclamado en su caso.\nCAPÍTULO NOVENO\nDE LAS PRUEBAS\nARTÍCULO 96. En los juicios que se tramiten ante el Tribunal serán admisibles toda clase de pruebas, excepto las de posiciones y la declaración de parte cuando sean a cargo de las autoridades, sin perjuicio de que el Tribunal pueda solicitarles informe específico que considere necesario para mejor proveer. Para efectos de su admisión, las pruebas ofrecidas deberán reunir los siguientes elementos, o de lo contrario, se desecharán de plano:\nI. No ser contrarias a la moral y al derecho; y,\nII. Tener relación inmediata y directa con los puntos controvertidos.\nAquellas que se hubieren rendido ante las autoridades demandadas, deberán ponerse a disposición del Tribunal con el expediente relativo, cuando la parte demandante así lo solicite.\nLas pruebas supervenientes podrán presentarse siempre que no se haya dictado sentencia. En este caso, el Órgano de Primera Instancia ordenará dar vista a la contraparte, para que en el plazo de tres días exprese lo que a su derecho convenga, reservándose su admisión y valoración, hasta la sentencia en primera instancia.\nARTÍCULO 97. Los Órganos de Primera Instancia del Tribunal podrán ordenar de oficio, la práctica de cualquier diligencia que tenga relación con los hechos controvertidos, o conducentes, notificando oportunamente a las partes, a fin de que puedan intervenir, si así conviene a sus intereses.\nARTÍCULO 98. A fin de que las partes puedan rendir sus pruebas, los funcionarios o autoridades tienen obligación de expedir con toda oportunidad, las copias de los documentos que soliciten dichas partes; si las autoridades o funcionarios no cumplen con esa obligación, la parte interesada pedirá al Tribunal que requiera a los omisos.\nLey del Tribunal Estatal de Justicia Administrativa de Baja California. Página 37\nEl propio Tribunal hará el requerimiento, pero si no obstante el mismo, no se expidieran las copias solicitadas, el Tribunal hará uso de los medios de apremio.\nARTÍCULO 99. La prueba pericial tendrá lugar en las cuestiones de carácter técnico, científico o artístico. El Perito deberá tener título en la especialidad a la que pertenezca la cuestión sobre la que deba rendirse el peritaje, si estuviere legalmente reglamentada. Si no lo estuviese, o estándolo no fuere posible obtenerlo, podrá nombrarse a una persona entendida en la materia.\nARTÍCULO 100. Al ofrecer la prueba pericial, la parte oferente presentará el cuestionario del perito, precisando los hechos sobre las que versará y señalando el nombre y domicilio del perito. Sin estos señalamientos la pericial se tendrá por no ofrecida.\nEn el acuerdo en que se admita la prueba pericial, se requerirá a las partes para que dentro del plazo de diez días presenten a sus peritos, a fin de que acrediten que reúnen los requisitos correspondientes, acepten el cargo y protesten su legal desempeño, apercibiéndolas de que, si no lo hacen sin justa causa, o la persona propuesta no acepta el cargo o no reúne los requisitos de ley, sólo se considerará el peritaje de quien haya cumplimentado el requerimiento.\nLos peritos deberán rendir su propio dictamen autónomo e independiente y exponer sus razones o sustentos en los que se apoyan, por lo que no deberán sustentar su dictamen en las respuestas expuestas por otro perito, ni remitirse a ellas para justificar su opinión técnica.\nA partir de la fecha en que el perito acepte el cargo y se tome la protesta correspondiente, el Órgano de Primera Instancia le concederá un plazo de por lo menos diez días para rendir su dictamen, con el apercibimiento a la parte que lo propuso de que únicamente se considerarán los dictámenes rendidos dentro del plazo concedido.\nPor una sola vez y por causa que lo justifique, comunicada al Órgano de Primera\nInstancia antes de vencer los plazos mencionados en este artículo, las partes podrán solicitar la ampliación del plazo para rendir el dictamen.\nEl perito tercero será designado por el Órgano de Primera Instancia correspondiente, idóneo, la designación de una persona con la preparación o conocimientos técnicos o científicos necesarios para que funja como perito del Tribunal dentro del juicio. El Titular será apercibido de que, en caso de no proporcionar el perito solicitado, o no proporcionare las facilidades necesarias para desempeñar esta función, se le aplicarán los medios de apremio previstos para que el Juzgador haga cumplir sus determinaciones.\nLey del Tribunal Estatal de Justicia Administrativa de Baja California. Página 38\nDependencias y Entidades de la Administración Pública Estatal o Municipal, deberán desempeñar el cargo de perito como parte de sus funciones, quienes deberán rendir su dictamen por escrito en el mismo plazo que el aplicable para los peritos de las partes. dictamen, el perito del Tribunal contará con los apoyos que se determinen en el Reglamento\nInterior.\nEn el caso de que, tratándose del perito del Tribunal, no hubiere alguno en la ciencia o arte sobre el cual verse el peritaje, el Órgano de Primera Instancia designará bajo su responsabilidad a la persona que deba rendir dicho dictamen.\nUna vez presentados los dictámenes, serán puestos a disposición de las partes, para que estén en posibilidad de presentar objeciones a los mismos por escrito, antes de la celebración de la audiencia. En ningún caso el plazo que se le otorgue a las partes podrá ser menor de cinco días hábiles para conocer del dictamen y formular sus objeciones si las consideran necesarias, las cuales deberán contener los elementos técnicos en que se basan. En caso de ser necesario, la celebración de la audiencia se diferirá para respetar los plazos precisados en este párrafo.\nEn la audiencia, el perito o los peritos estarán obligados a dar respuesta a los cuestionamientos que verbalmente le formulen las partes y el Titular del Órgano de Primera\nInstancia, las que se harán constar en forma resumida en el acta que se levante de la audiencia, para ser valoradas al momento de la sentencia, junto con el dictamen y objeciones formuladas por escrito por las partes.\nLos peritos no serán recusables, pero deberán excusarse por alguna de las causas siguientes:\nI. Consanguinidad dentro del cuarto grado con alguna de las partes, o parentesco por afinidad;\nII. Interés directo o indirecto en el litigio; y,\nIII. Tener dependencia o relaciones de índole económica con cualquiera de las partes.\nARTÍCULO 101. Cuando el particular oferente de la prueba pericial esté imposibilitado órgano jurisdiccional, se designará al perito del Tribunal desde la admisión de la prueba.\nARTÍCULO 102. Al ofrecerse la prueba testimonial, se precisarán los hechos sobre las que deba versar y se señalarán los nombres y domicilios de los testigos. Sin estos señalamientos se tendrán por no ofrecidas.\nLey del Tribunal Estatal de Justicia Administrativa de Baja California. Página 39\nLos testigos, que no podrán exceder de tres en relación con cada hecho, deberán ser presentados por la oferente, y sólo en caso de que ésta manifieste imposibilidad para hacerlo, el Tribunal los mandará citar. Una vez admitida la prueba testimonial, no se aceptará la sustitución de testigos.\nCuando alguno de los testigos tenga el carácter de autoridad, el desahogo de esta prueba se hará por escrito, en un plazo no mayor de cinco días.\nARTÍCULO 103. La valoración de las pruebas, se hará de acuerdo con las disposiciones relativas del Código de Procedimientos Civiles del Estado de Baja California.\nCAPÍTULO DÉCIMO\nDE LA AUDIENCIA\nARTÍCULO 104. En el caso previsto en el artículo 76, párrafo segundo, de esta ley, se celebrará audiencia que tendrá como objeto el desahogo de las pruebas que requieran diligencia especial, misma que se celebrará ante la presencia del Titular del órgano jurisdiccional del conocimiento, quien podrá formular a las partes, a sus representantes, a los testigos y peritos, toda clase de preguntas respecto a las cuestiones debatidas.\nLas promociones que las partes presenten o formulen en la audiencia, así como sus oposiciones contra los acuerdos que en ella se dicten, se resolverán en la misma audiencia o en el plazo de tres días, a juicio del juzgador.\nDe existir alguna razón que amerite el diferimiento o suspensión de la audiencia, se señalará nueva fecha.\nLas partes podrán presentar sus alegatos por escrito o verbalmente. En este último caso, se oirán los alegatos del actor, de la parte demandada y del tercero perjudicado, los que se producirán en ese orden, sin que sea necesaria su transcripción en los autos, ni podrán exceder de media hora por cada parte.\nAl concluir la audiencia, quedará cerrada la instrucción y se citará para sentencia.\nARTÍCULO 105. La resolución definitiva se pronunciará dentro de los diez días siguientes al cierre de la instrucción y citación para sentencia.\nCAPÍTULO DECIMOPRIMERO\nDE LA SENTENCIA\nLey del Tribunal Estatal de Justicia Administrativa de Baja California. Página 40\nARTÍCULO 106. La resolución que decrete el sobreseimiento del juicio por alguna de las causales previstas en esta Ley, podrá dictarse antes del cierre de instrucción o incluso durante la audiencia.\nARTÍCULO 107. Las sentencias que dicte el Tribunal no necesitarán formulismo alguno, pero deberán contener:\nI. La fijación clara y precisa de los puntos controvertidos, así como el examen y valoración de las pruebas que se hayan rendido.\nII. Los fundamentos legales en que se apoyen para dictar la resolución definitiva; y\nLos puntos resolutivos en los que se expresarán los actos o resoluciones cuya validez se reconozca o cuya nulidad se declare; la reposición del procedimiento que se ordene, los términos de la modificación del acto impugnado, y en su caso, la condena que se decrete.\nARTÍCULO 108. Serán causas de nulidad de los actos y resoluciones impugnadas, las siguientes:\nI. Incompetencia de la autoridad que la haya dictado, ordenado o tramitado el procedimiento del que deriva dicha resolución;\nII. Incumplimiento u omisión de los requisitos formales que legalmente deba revestir, siempre que afecte las defensas del particular y trascienda al sentido de la resolución impugnada;\nIII. Vicios del procedimiento, siempre que afecten las defensas del particular y trasciendan al sentido de la resolución impugnada;\nIV. Si los hechos que la motivaron no se realizaron, fueron distintos o se apreciaron en forma equivocada, o bien si se dictó en contravención de las disposiciones aplicadas o dejó de aplicar las debidas, en cuanto al fondo del asunto;\nV. Cuando la resolución administrativa dictada en ejercicio de facultades discrecionales no corresponda a los fines para los cuales la ley confiera dichas facultades; y,\nVI. Arbitrariedad, desproporción, desigualdad, injusticia manifiesta o cualquier otra causa similar.\nEl Tribunal podrá hacer valer de oficio al momento de resolver, incluso en segunda instancia, cualquiera de las causales señaladas, si estima que ha sido acreditada en autos su existencia, aunque esta no se haya invocado expresamente por el demandante.\nARTÍCULO 109. La sentencia definitiva podrá:\nLey del Tribunal Estatal de Justicia Administrativa de Baja California. Página 41\nI. Reconocer la validez de la resolución impugnada.\nII. Declarar la nulidad de la resolución impugnada.\nIII. En los supuestos previstos en las fracciones II y III del artículo 108 de esta ley, resolución; en los demás casos, cuando corresponda a la pretensión deducida, también administrativa.\nIV. Declarar la nulidad de la resolución impugnada y, además:\na) Reconocer al actor la existencia de un derecho subjetivo y condenar al cumplimiento de la obligación correlativa.\nb) Otorgar o restituir al demandante en el goce de los derechos afectados.\nLa resolución que decrete injustificada la separación, remoción, baja, cese o cualquier otra forma de terminación del servicio de un Agente del Ministerio Público, Perito o Miembro de las Instituciones Policiales, la autoridad responsable sólo estará obligada a pagar la indemnización y demás prestaciones a que tenga derecho el afectado.\nEn ningún caso procede la reincorporación al servicio, cualquiera que sea el resultado del juicio o medio de defensa que se hubiere promovido.\nCAPÍTULO DECIMOSEGUNDO\nDEL CUMPLIMIENTO DE LA SENTENCIA\nARTÍCULO 110. Causan ejecutoria las sentencias pronunciadas por el Tribunal no impugnadas en términos de Ley o que habiéndolo sido se haya declarado desierto o improcedente el medio de impugnación, o haya desistido de él el promovente, y las consentidas expresamente por las partes, sus representantes legítimos o sus mandatarios.\nARTÍCULO 111. Todas las autoridades que tengan o deban tener intervención en el cumplimiento de la sentencia, están obligadas a realizar, dentro del ámbito de su competencia, los actos necesarios para su eficaz cumplimiento y estarán sujetos a las mismas responsabilidades a que alude este Capítulo.\nARTÍCULO 112. Cuando haya causado ejecutoria una sentencia favorable al demandante, el Tribunal la comunicará por oficio y sin demora alguna a las autoridades demandadas, para su cumplimiento.\nLey del Tribunal Estatal de Justicia Administrativa de Baja California. Página 42 cumpla con la ejecutoria dentro del plazo de tres días, apercibida que de no hacerlo así sin causa justificada, se impondrá a su titular el medio de apremio previsto en el artículo 47, fracción II, de esta ley.\nARTÍCULO 113. Si en el plazo concedido la autoridad demandada no acredita el cabal cumplimiento de la ejecutoria, se le requerirá nuevamente por el plazo de tres días, previniéndola de que, en caso de renuencia, se le impondrá nueva multa, en términos del artículo anterior.\nARTÍCULO 114. En el supuesto de que la autoridad demandada persista en su actitud omisa, el Tribunal solicitará al Titular de la Dependencia Estatal, Municipal u\nOrganismo Descentralizado a quien se encuentre subordinado, para que conmine al funcionario responsable a cumplir con las determinaciones del Tribunal.\nSi no obstante los requerimientos anteriores no se da cumplimiento a la resolución, el\nÓrgano de Primera Instancia remitirá el expediente al Pleno, quien podrá decretar la destitución del servidor público responsable, excepto de que se trate de autoridad electa por voto popular, en cuyo caso se procederá en los términos de la Ley de Responsabilidades.\nLas sanciones mencionadas en este artículo, también serán procedentes cuando no se cumplimente en sus términos, la suspensión que se hubiere decretado respecto al acto reclamado en el juicio.\nARTÍCULO 115. Prescribirá en cinco años la facultad del demandante para ejecutar la sentencia que implique actos, resoluciones o prestaciones relacionadas con bienes inmuebles, así como la que conceda pensiones; y en dos años, la que se refiera al pago de honorarios, sueldos, salarios u otras retribuciones por la prestación de cualquier servicio.\nLa demandada podrá liberarse de su obligación de pago derivada de la sentencia ejecutoriada, mediante consignación ante el propio Tribunal; en tal caso, será aplicable el procedimiento previsto en el Código de Procedimientos Civiles para el Estado.\nARTÍCULO 116. Independientemente de lo establecido en el presente capítulo, el cumplida la ejecutoria. Del convenio se dará aviso al órgano de primera instancia correspondiente, para su aprobación, en su caso. convenio fueron cumplidos, dictará acuerdo en el que verifique tal cumplimiento.\nCAPÍTULO DÉCIMOTERCERO\nDE LOS RECURSOS\nLey del Tribunal Estatal de Justicia Administrativa de Baja California. Página 43\nARTÍCULO 117. Las partes podrán interponer el recurso de reclamación en contra de las resoluciones de los Órganos de Primera Instancia que:\nI. Desechen o tengan por no interpuesta la demanda, la contestación o la ampliación de ambas;\nII. Admitan o desechen las pruebas;\nIII. Nieguen o admitan la intervención de terceros;\nIV. Nieguen o concedan la suspensión provisional del acto reclamado; y,\nV. Determinen la improcedencia de la vía de mínima cuantía.\nEl recurso deberá interponerse dentro de los tres días siguientes contados a partir del día que surta efectos su notificación, expresando los agravios que le cause, ante el Órgano de Primera instancia que hubiere dictado el acto recurrido.\nARTÍCULO 118. Interpuesto el recurso a que se refiere el artículo anterior, el Órgano de Primera Instancia dará vista a las partes por el término de tres días para que expresen lo que a su derecho convenga y, sin más trámite, resolverá en el término de tres días posteriores.\nARTÍCULO 119. El recurso de queja es procedente contra la resolución interlocutoria a que se refiere el artículo 95 de esta Ley.\nDicho recurso deberá interponerse ante el Órgano de Primera Instancia correspondiente dentro del plazo de cinco días siguientes al surtimiento de efectos la notificación de la resolución que se pretenda recurrir, acompañando una copia del recurso para cada una de las partes.\nARTÍCULO 120. Interpuesto el recurso a que se refiere el artículo anterior, el Órgano para que provea sobre su admisión; si lo considera inadmisible, lo someterá al Pleno para que se decida en forma colegiada su admisión o rechazo. El Magistrado Presidente, al admitir el recurso, designará por turno al Magistrado Ponente, mandando correr traslado del mismo a las partes, para que expresen lo que a su derecho convenga dentro de un plazo de tres días. Transcurrido dicho lapso, el Pleno resolverá lo conducente dentro del plazo de diez días.\nLey del Tribunal Estatal de Justicia Administrativa de Baja California. Página 44\nARTÍCULO 121. Las partes podrán interponer el recurso de revisión, con el objeto de\nÓrganos de Primera Instancia:\nI. Los acuerdos o interlocutorias que concedan o nieguen la suspensión definitiva;\nII. Las interlocutorias que confirmen el desechamiento de la demanda o la contestación;\nIII. Las resoluciones que decreten o nieguen el sobreseimiento o la caducidad; y,\nIV. Las sentencias que resuelvan el asunto en definitiva.\nEl recurso deberá interponerse por escrito ante el órgano que dictó la resolución o acuerdo recurrido dentro del plazo de diez días siguientes a aquel en que surta efectos la notificación del acuerdo o de la resolución que se pretenda recurrir, debiéndose expresar los agravios que causa al inconforme, precisando la parte de la resolución impugnada que le causa perjuicio, los preceptos legales que estima se violaron y los razonamientos tendientes a demostrar dichas violaciones.\nEl Órgano de Primera Instancia lo remitirá dentro de los tres días siguientes al\nMagistrado Presidente para que provea sobre su admisión; si lo considera inadmisible, lo someterá al Pleno para que se decida en forma colegiada su admisión o rechazo.\nCuando se promueva recurso de revisión en los casos previstos en las fracciones I y\nII, de este artículo, el expediente original del cuaderno de suspensión deberá remitirse al\nPleno, quedando su duplicado ante el órgano jurisdiccional en contra de cuya resolución se interpuso el recurso.\nEn casos de urgencia, el expediente deberá remitirse al Pleno del Tribunal mediante los correos electrónicos institucionales, en términos del artículo 17 de esta Ley.\nEl Magistrado Presidente, al admitir el recurso, designará por turno al Magistrado\nPonente, mandando correr traslado del mismo a las partes, para que expresen lo que a su derecho convenga dentro de un plazo de cinco días.\nTranscurrido el plazo previsto en el párrafo anterior, el Magistrado Ponente, dentro de un plazo de diez días, formulará proyecto de resolución y lo someterá a la consideración de los Magistrados, quienes deberán emitir su voto dentro de una audiencia que tendrá verificativo dentro de los quince días siguientes; tratándose de los supuestos previstos en las respectivamente.\nLey del Tribunal Estatal de Justicia Administrativa de Baja California. Página 45 del Tribunal en Pleno.\nEl Pleno podrá aplicar el medio de apremio o medida disciplinaria, de los previstos por esta Ley, cuando se denosté o falte al respeto a los Magistrados a través de la interposición de los recursos o cualquier otro ocurso. Si las faltas llegaran a constituir delitos, se procederá con arreglo a lo dispuesto en el Código Penal, consignando al culpable a la autoridad competente.\nCuando la falta se cometa en primera instancia, corresponderá a los Titulares de los\nÓrganos de Primera Instancia, dictar la aplicación del medio de apremio o medida disciplinaria.\nARTÍCULO 122. La parte que obtuvo resolución favorable en el juicio puede adherirse a la revisión interpuesta por otra de las partes dentro del plazo de cinco días, contados a partir del día siguiente a aquél en que surta efectos la notificación de la admisión del recurso, expresando los agravios correspondientes; la adhesión al recurso sigue la suerte procesal de éste.\nCAPÍTULO DECIMOCUARTO\nDE LA JURISPRUDENCIA\nARTÍCULO 123. Las sentencias firmes del Pleno del Tribunal constituirán\nJurisprudencia, siempre que lo resuelto se sustente en tres ejecutorias no interrumpidas por otra en contrario y hayan sido aprobadas por unanimidad de votos de los Magistrados que lo integran.\nLa jurisprudencia del Tribunal será obligatoria para el Pleno, las Salas Unitarias y los\nÓrganos de Primera Instancia. También estarán obligadas a su observancia las autoridades administrativas sometidas a su jurisdicción; excepción hecha en materia tributaria. Cuando se invoquen tesis jurisprudenciales de este órgano, deberán proporcionarse los datos suficientes para su identificación y verificación.\nCuando algún órgano jurisdiccional del Tribunal o autoridad administrativa, dicte o ejecute un acto contraviniendo una tesis jurisprudencial, el Tribunal le solicitará un informe.\nUna vez confirmado el incumplimiento, el Pleno del Tribunal le aplicará los medios de apremio que establece esta Ley.\nEn caso de que el acto dé lugar a un juicio en los términos de la presente ley, el Pleno del Tribunal deberá suspender el procedimiento mencionado en el párrafo anterior, hasta en tanto dicho juicio se resuelva en definitiva.\nLey del Tribunal Estatal de Justicia Administrativa de Baja California. Página 46\nARTÍCULO 124. Cuando existan razones fundadas por las que se considere que deba interrumpirse la observancia del criterio sustentado en una tesis jurisprudencial, la autoridad administrativa y los particulares que demuestren interés jurídico, podrán solicitar su revisión al Pleno del Tribunal.\nSi se consideran procedentes las razones expuestas, el Pleno del Tribunal, por unanimidad de votos de los Magistrados que lo integran, resolverá la interrupción del criterio sustentado en la tesis jurisprudencial. Dicha resolución no afectará las situaciones jurídicas concretas derivadas de los juicios en los cuales se hubiesen dictado las sentencias que constituyeron los precedentes de la tesis jurisprudencial.\nEl Pleno del Tribunal deberá dictar la resolución dentro de un plazo de treinta días y ordenar su publicación en los términos previstos por el artículo 125 de esta Ley. Si no se resuelve en dicho plazo, se suspenderá la aplicación de la tesis jurisprudencial.\nARTÍCULO 125. La jurisprudencia perderá tal carácter cuando el Pleno del Tribunal, por unanimidad de votos de los Magistrados que lo integran, pronuncie una resolución en contrario, debiendo expresarse en ellas las razones que motiven el cambio de criterio; las cuales deberán referirse a las que se tuvieron en consideración para establecerla.\nPara la modificación de la jurisprudencia, se observarán las mismas reglas establecidas por esta Ley para su formación.\nARTÍCULO 126. Los Titulares de los Órganos de Primera Instancia, al emitir las sentencias, deberán apegarse a los criterios jurídicos que hayan aplicado al resolver otros casos sobre la misma materia. Para modificarlos, deberán razonar detalladamente los motivos por los que se abandonan dichos criterios.\nEn caso de que existan criterios contradictorios sostenidos por diferentes Órganos de\nPrimera Instancia, cualquiera de los Magistrados, Jueces o de las partes, podrán solicitar al\nPleno del Tribunal resuelva dicha contradicción, definiendo el criterio que deba imperar, mismo que tendrá el carácter de jurisprudencia, y que podrá ser interrumpida por nuevo criterio razonado en sentencia dictada por el Tribunal en Pleno. Las resoluciones dictadas por el Pleno para dirimir las contradicciones de criterio, no modificarán las sentencias que hayan motivado la contradicción.\nCAPÍTULO DECIMOQUINTO\nDEL JUICIO EN LÍNEA\nARTÍCULO 127. Para los efectos de este capítulo se entenderá por:\nI. Acuse de Recibo Electrónico: Constancia que acredita que un documento digital fue\nLey del Tribunal Estatal de Justicia Administrativa de Baja California. Página 47 electrónica avanzada. En este caso, el acuse de recibo electrónico identificará al órgano jurisdiccional que recibió el documento y se presumirá, salvo prueba en contrario, que el documento digital fue recibido en la fecha y hora que se consignen en dicha constancia. El notificaciones puedan verificar la autenticidad de los acuses de recibo electrónico.\nII. Archivo Electrónico: Información contenida en texto, imagen, audio o video generada, enviada, recibida o archivada por medios electrónicos, ópticos o de cualquier otra tecnología que forma parte del Expediente Electrónico.\nIII. Aviso electrónico: Mensaje enviado a la dirección de correo electrónico de las partes de que se realizará una notificación por Boletín Jurisdiccional.\nIV. Clave de acceso: Conjunto único de caracteres alfanuméricos asignados por el\nSistema de Justicia en Línea del Tribunal a las partes, como medio de identificación de las personas facultadas en el juicio en que promuevan para utilizar el Sistema, y asignarles los privilegios de consulta del expediente respectivo o envío vía electrónica de promociones relativas a las actuaciones procesales con el uso de la firma electrónica avanzada en un procedimiento contencioso administrativo.\nV. Contraseña: Conjunto único de caracteres alfanuméricos, asignados de manera confidencial por el Sistema de Justicia en Línea del Tribunal a los usuarios, la cual permite validar la identificación de la persona a la que se le asignó una Clave de Acceso.\nVI. Dirección de Correo Electrónico: Sistema de comunicación a través de redes informáticas, señalado por las partes en el juicio contencioso administrativo.\nVII. Dirección de Correo Electrónico Institucional: Sistema de comunicación a través de redes informáticas, dentro del dominio definido y proporcionado por los órganos gubernamentales a los servidores públicos.\nVIII. Documento Electrónico o Digital: Todo mensaje de datos que contiene texto o escritura generada, enviada, recibida o archivada por medios electrónicos, ópticos o de cualquier otra tecnología que forma parte del Expediente Electrónico.\nIX. Expediente Electrónico: Conjunto de información contenida en archivos electrónicos o documentos digitales que conforman un juicio contencioso administrativo, independientemente de que sea texto, imagen, audio o video, identificado por un número específico.\nLey del Tribunal Estatal de Justicia Administrativa de Baja California. Página 48 mediante el Sistema de Justicia en línea, y que produce los mismos efectos jurídicos que la\nXI. Juicio en línea: Sustanciación y resolución del juicio contencioso administrativo en todas sus etapas, a través del Sistema de Justicia en Línea.\nXII. Sistema de Justicia en Línea: Sistema informático establecido por el Tribunal a efecto de registrar, controlar, procesar, almacenar, difundir, transmitir, gestionar, administrar y notificar el procedimiento contencioso administrativo que se sustancie ante el Tribunal.\nARTÍCULO 128. El juicio contencioso administrativo se promoverá, sustanciará y resolverá en línea, a través del Sistema de Justicia en Línea, que deberá establecer y desarrollar el Tribunal, en términos de lo dispuesto en el presente Capítulo y las demás disposiciones específicas que resulten aplicables de esta Ley. En todo lo no previsto, se aplicarán las demás disposiciones que resulten aplicables de este ordenamiento.\nARTÍCULO 129. Es optativo para el demandante promover el juicio contencioso administrativo en línea. Cuando ejerza este derecho, las autoridades demandadas deberán comparecer y tramitar el juicio en la misma vía.\nSi el demandante no señala expresamente su dirección de correo electrónico, se tramitará el juicio en la vía tradicional y el acuerdo correspondiente se notificará en el Boletín\nJurisdiccional.\nARTÍCULO 130. Cuando la demandante sea una autoridad, el particular demandado, al contestar la demanda, tendrá derecho a ejercer su opción para que el juicio se tramite y resuelva en línea conforme a las disposiciones de este Capítulo, señalando para ello su domicilio y dirección de correo electrónico.\nA fin de emplazar al particular demandado, el Secretario de Acuerdos que corresponda, imprimirá y certificará la demanda y sus anexos que se notificarán de manera personal. juicio en la vía tradicional.\nARTÍCULO 131. En el Sistema de Justicia en Línea del Tribunal se integrará el\nExpediente Electrónico, mismo que incluirá todas las promociones, pruebas y otros anexos que presenten las partes, oficios, acuerdos, y resoluciones tanto interlocutorias como definitivas, así como las demás actuaciones que deriven de la sustanciación del juicio en línea, garantizando su seguridad, inalterabilidad, autenticidad, integridad y durabilidad, conforme a los lineamientos que expida el Tribunal.\nLey del Tribunal Estatal de Justicia Administrativa de Baja California. Página 49\nEn los juicios en línea, la autoridad requerida, desahogará las pruebas testimoniales utilizando el método de videoconferencia, cuando ello sea posible. proporcionarán, a través del Sistema de Justicia en Línea del Tribunal, previa obtención del de Acceso y Contraseña, implica el consentimiento expreso de que dicho Sistema registrará la fecha y hora en la que se abran los Archivos Electrónicos, que contengan las constancias que integran el Expediente Electrónico, para los efectos legales establecidos en este ordenamiento.\nPara hacer uso del Sistema de Justicia en Línea deberán observarse los lineamientos que, para tal efecto, expida el Tribunal.\nARTÍCULO 133. La Firma Electrónica Avanzada producirá los mismos efectos legales que la firma autógrafa y garantizará la integridad del documento, teniendo el mismo valor probatorio.\nARTÍCULO 134. Solamente, las partes, las personas autorizadas y delegados tendrán acceso al Expediente Electrónico, exclusivamente para su consulta, una vez que tengan registrada su Clave de Acceso y Contraseña.\nARTÍCULO 135. Los titulares de una Firma Electrónica Avanzada, Clave de Acceso y\nContraseña serán responsables de su uso, por lo que el acceso o recepción de las notificaciones, la consulta al Expediente Electrónico y el envío de información mediante la utilización de cualquiera de dichos instrumentos, les serán atribuibles y no admitirán prueba en contrario, salvo que se demuestren fallas del Sistema de Justicia en Línea.\nARTÍCULO 136. Una vez recibida por vía electrónica cualquier promoción de las partes, el Sistema de Justicia en Línea del Tribunal emitirá el Acuse de Recibo Electrónico correspondiente, señalando la fecha y la hora de recibido.\nARTÍCULO 137. Cualquier actuación en el Juicio en Línea se efectuará a través del\nSistema de Justicia en Línea del Tribunal en términos del presente capítulo. Dichas actuaciones serán validadas con las firmas electrónicas avanzadas de los Magistrados, Jueces, Secretario General de Acuerdos y Secretarios de Acuerdos que den fe según corresponda.\nARTÍCULO 138. Los documentos que las partes ofrezcan como prueba, incluido el expediente administrativo que, en su caso se ofrezca, deberán exhibirlos de forma legible a través del Sistema de Justicia en Línea del Tribunal.\nLey del Tribunal Estatal de Justicia Administrativa de Baja California. Página 50\nTratándose de documentos digitales, se deberá manifestar la naturaleza de los mismos, especificando si la reproducción digital corresponde a una copia simple, una copia certificada o al original y tratándose de esta última, si tiene o no firma autógrafa. Los particulares deberán hacer esta manifestación bajo protesta de decir verdad, la omisión de la manifestación presume en perjuicio sólo del promovente, que el documento digitalizado corresponde a una copia fotostática.\nLas pruebas documentales que ofrezcan y exhiban las partes tendrán el mismo valor probatorio que su constancia física, siempre y cuando se observen las disposiciones de la presente Ley y de los acuerdos normativos que emitan los órganos del Tribunal para asegurar la autenticidad de la información, así como de su transmisión, recepción, validación y notificación.\nARTÍCULO 139. Para el caso de pruebas diversas a las documentales, los instrumentos en los que se haga constar la existencia de dichas pruebas se integrarán al\nExpediente Electrónico. El Secretario de Acuerdos al que corresponda el asunto, deberá digitalizar las constancias relativas y procederá a la certificación de su cotejo con los originales físicos, así como a garantizar el resguardo de los originales y de los bienes materiales que en su caso hubieren sido objeto de prueba.\nPara el caso de pruebas diversas a las documentales, éstas deberán ofrecerse en la demanda y ser presentadas al órgano jurisdiccional que esté conociendo del asunto, en la misma fecha en la que se registre en el Sistema de Justicia en Línea del Tribunal la promoción correspondiente a su ofrecimiento, haciendo constar su recepción por vía electrónica.\nARTÍCULO 140. Para los juicios que se sustancien en términos de este capítulo no será necesario que las partes exhiban copias para correr los traslados que la Ley establece, salvo que hubiese tercero, en cuyo caso, a fin de correrle traslado, el demandante deberá presentar la copia de traslado con sus respectivos anexos.\nEn el escrito a través del cual el tercero se apersone en juicio, deberá precisar si desea que el juicio se continúe sustanciando en línea y señalar en tal caso, su dirección de correo electrónico. En caso de que manifieste su oposición, el órgano jurisdiccional dispondrá lo conducente para que se digitalicen los documentos que dicho tercero presente, a fin de que se prosiga con la instrucción del juicio en línea con relación a las demás partes, electrónica, a fin de que se integre el expediente del tercero en un Juicio en la vía tradicional.\nARTÍCULO 141. Las notificaciones que se practiquen dentro del juicio en línea, se efectuarán conforme a lo siguiente:\nLey del Tribunal Estatal de Justicia Administrativa de Baja California. Página 51\nI. Todas las actuaciones y resoluciones que conforme a las disposiciones de esta Ley deban notificarse en forma personal, mediante correo certificado con acuse de recibo, o por oficio, se deberán realizar a través del Sistema de Justicia en Línea del Tribunal.\nII. El actuario deberá elaborar la minuta electrónica en la que precise la actuación o resolución a notificar, así como los documentos que se adjunten a la misma. Dicha minuta, Justicia en Línea del Tribunal junto con la actuación o resolución respectiva y los documentos adjuntos.\nIII. El actuario enviará a la dirección de correo electrónico de la o las partes a notificar, un aviso informándole que se ha dictado una actuación o resolución en el Expediente\nElectrónico, la cual está disponible en el Sistema de Justicia en Línea del Tribunal.\nIV. El Sistema de Justicia en Línea del Tribunal registrará la fecha y hora en que se efectúe el envío señalado en la fracción anterior.\nV. Se tendrá como legalmente practicada la notificación, conforme a lo señalado en las fracciones anteriores, cuando el Sistema de Justicia en Línea del Tribunal genere el\nAcuse de Recibo Electrónico donde conste la fecha y hora en que la o las partes notificadas ingresaron al Expediente Electrónico, lo que deberá suceder dentro del plazo de tres días hábiles siguientes a la fecha de envío del aviso a la dirección de correo electrónico de la o las partes a notificar.\nVI. En caso de que, en el plazo señalado en la fracción anterior, el Sistema de Justicia en Línea del Tribunal no genere el acuse de recibo donde conste que la notificación fue realizada, la misma se efectuará mediante Boletín Jurisdiccional al cuarto día hábil contado a partir de la fecha de envío del correo electrónico, fecha en que se tendrá por legalmente notificado.\nARTÍCULO 142. Para los efectos del Juicio en Línea son hábiles las veinticuatro horas de los días en que se encuentren abiertas al público las Oficinas del Tribunal.\nLas promociones se considerarán, salvo prueba en contrario, presentadas el día y\nLínea del Tribunal, en el lugar en donde el promovente tenga su domicilio y, por recibidas, en el lugar de la sede del órgano al que corresponda conocer del juicio por razón de territorio.\nTratándose de un día inhábil se tendrán por presentadas el día hábil siguiente.\nARTÍCULO 143. Las autoridades cuyos actos sean susceptibles de impugnarse ante el Tribunal, deberán registrar en la Secretaría General de Acuerdos o ante los Órganos de\nPrimera Instancia, según corresponda, la Dirección de correo electrónico institucional, así\nLey del Tribunal Estatal de Justicia Administrativa de Baja California. Página 52 representación en los juicios contenciosos administrativos, para el efecto de emplazarlas demandada.\nEn el caso de que las autoridades demandadas no cumplan con esta obligación, las notificaciones que de conformidad con el artículo 49 de esta Ley se le deban hacer mediante\nBoletín Jurisdiccional, se harán sin aviso electrónico, hasta que se cumpla con dicha formalidad.\nARTÍCULO 144. Para la presentación y trámite de los juicios de amparo que se promuevan contra las actuaciones y resoluciones derivadas del Juicio en Línea, no será aplicable lo dispuesto en el presente Capítulo.\nEl Secretario General de Acuerdos del Tribunal y los Secretarios de Acuerdos de los\nÓrganos de Primera Instancia, según corresponda, deberán imprimir el archivo del\nExpediente Electrónico y certificar las constancias del juicio que deban ser remitidos a los\nJuzgados de Distrito y Tribunales Colegiados de Circuito, cuando se impugnen resoluciones de los juicios del órgano correspondiente.\nSin perjuicio de lo anterior, en aquellos casos en que así lo solicite el Juzgado de\nDistrito o el Tribunal Colegiado se podrá remitir la información a través de medios electrónicos.\nARTÍCULO 145. En caso que el Tribunal advierta que alguna persona modificó, alteró, destruyó o provocó la pérdida de información contenida en el Sistema de Justicia en\nLínea, se tomarán las medidas de protección necesarias, para evitar dicha conducta hasta que concluya el juicio, el cual se continuará tramitando a través de un Juicio en la vía tradicional.\nSi el responsable es usuario del Sistema, se cancelará su Firma Electrónica\nAvanzada, Clave y Contraseña para ingresar al Sistema de Justicia en Línea y no tendrá posibilidad de volver a promover juicios en línea.\nSin perjuicio de lo anterior, y de las responsabilidades penales respectivas, se impondrá al responsable una multa de trescientas unidades de medida y actualización.\nARTÍCULO 146. Cuando por caso fortuito, fuerza mayor o por fallas técnicas se interrumpa el funcionamiento del Sistema de Justicia en Línea, haciendo imposible el cumplimiento de los plazos establecidos en la ley, las partes deberán dar aviso al Órgano\nJurisdiccional correspondiente en la misma promoción sujeta a término, quien pedirá un\nSistema sobre la existencia de la interrupción del servicio.\nLey del Tribunal Estatal de Justicia Administrativa de Baja California. Página 53 causa y el tiempo de dicha interrupción, indicando la fecha y hora de inicio y término de la misma. Los plazos se suspenderán, únicamente, el tiempo que dure la interrupción del\nSistema. Para tal efecto, el órgano jurisdiccional correspondiente hará constar esta situación mediante acuerdo en el expediente electrónico y, considerando el tiempo de la interrupción, realizara el cómputo correspondiente, para determinar si hubo o no incumplimiento de los plazos legales.\nCAPÍTULO DECIMOSEXTO\nDEL JUICIO DE MÍNIMA CUANTÍA\nARTÍCULO 147. El juicio contencioso administrativo se tramitará y resolverá en la vía de mínima cuantía, de conformidad con las disposiciones específicas que para su simplificación y abreviación se establecen en este Capítulo y, en lo no previsto, se aplicarán las demás disposiciones de esta Ley.\nARTÍCULO 148. Procederá el juicio de mínima cuantía cuando se impugnen actos en los que se impongan multas, se determinen o se requiera el pago de créditos fiscales, cuyo importe no exceda de doscientas veces el valor diario de la unidad de medida y actualización al momento de su emisión.\nPara determinar la cuantía en los casos precisados en el párrafo anterior, sólo se considerará el crédito principal sin accesorios ni actualizaciones. Cuando en un mismo acto se contenga más de una resolución de las mencionadas anteriormente no se acumulará el monto de cada una de ellas para efectos de determinar la procedencia de esta vía.\nLa interposición del juicio en la vía incorrecta no genera el desechamiento, improcedencia o sobreseimiento. En todos los casos, y en cualquier fase del procedimiento, mientras no haya quedado cerrada la instrucción, el juzgador debe reconducir el juicio en la vía correcta, debiendo realizar las regularizaciones que correspondan, siempre y cuando no impliquen repetir alguna promoción de las partes.\nARTÍCULO 149. La tramitación del Juicio de mínima cuantía será improcedente cuando:\nI. No se encuentra en alguno de los supuestos previstos en el artículo 148.\nII. Se trate de resoluciones que además de imponer una sanción pecuniaria, determinar o requerir un crédito fiscal, incluyan alguna otra carga u obligación que no sea accesoria de tales supuestos.\nLey del Tribunal Estatal de Justicia Administrativa de Baja California. Página 54\nEn estos casos el juzgador, antes de resolver sobre la admisión de la demanda, conforme a las demás disposiciones de esta Ley.\nContra la determinación de improcedencia de la vía de mínima cuantía, procederá el recurso de reclamación.\nARTÍCULO 150. En horas de atención al público, los particulares podrán hacer promociones por comparecencia ante la fe del Secretario de Acuerdos del órgano de primera instancia correspondiente, incluyendo la demanda.\nARTÍCULO 151. La demanda podrá presentarse a través de formatos apropiados y gratuitos para que el interesado sólo llene los espacios en blanco, así mismo se tendrá como excepción hecha a la representación a que hace referencia el artículo 44 de esta ley, que en este caso el interesado podrá optar ser representado por el profesionista señalado o por persona de su confianza la cual tendrá las mismas facultades.\nARTÍCULO 152. El incidente de acumulación sólo podrá plantearse respecto de expedientes que se encuentren tramitando en esta misma vía.\nARTÍCULO 153. Las medidas cautelares se tramitarán conforme a las reglas generales establecidas en el Capítulo Séptimo del Título segundo de esta Ley. El Órgano de\nPrimera Instancia estará facultado para decretar de oficio la resolución provisional o definitiva que corresponda a las medidas cautelares.\nARTÍCULO 154. No procederá recurso alguno contra las sentencias que resuelvan el asunto en definitiva ni contra las resoluciones que decreten o nieguen el sobreseimiento o la caducidad.\nARTÍCULO 155. En los escritos de demanda y de contestación las partes expresarán si tienen interés en resolver la controversia a través de un convenio y, de ser así, deberán exponer la propuesta correspondiente.\nDe no manifestarse las partes en los términos antes señalados, se entenderá que no tienen interés en convenir la solución de la controversia.\nCon la propuesta respectiva se dará vista a la contraparte por el plazo de tres días, quien podrá aceptarla en sus términos o realizar una contraoferta. Si la rechaza sin contraoferta, se dará seguimiento normal al procedimiento.\nDe formularse una contraoferta, se dará vista por el mismo plazo a la contraparte correspondiente para que decida si la acepta o la rechaza.\nLey del Tribunal Estatal de Justicia Administrativa de Baja California. Página 55\nARTÍCULO 156. En caso de que en términos del artículo anterior se hubiera convenido la solución de la controversia, el juzgador verificará que los términos convenidos:\na) No contravengan disposiciones de orden público.\nb) No afecten derechos de terceros.\nc) No resulten notoriamente desproporcionados.\nVerificado lo anterior, el juzgador resolverá sobre la procedencia de lo convenido, para en su caso, dar por terminado el juicio, precisando los términos del convenio de las partes; de considerar improcedente el convenio, se dará seguimiento normal al procedimiento.\nLa resolución que de por terminado el juicio en virtud de un convenio de las partes se notificará personalmente a los particulares y por oficio a las autoridades.\nARTÍCULO 157. En caso de incumplimiento de un convenio, se aplicarán en lo conducente, las reglas que para la ejecución de sentencia se establecen en la presente Ley, previo derecho de audiencia de las partes. Si el demandante es quien incumple, la autoridad demandada tendrá expedita su facultad para realizar los actos que considere pertinentes, sin menoscabo de proceder a su ejecución forzosa.\nLas ofertas, contraofertas y la aceptación de los convenios, en su caso, podrán realizarse, en el caso de los particulares optativamente en forma personal, por medio de representante o de abogado autorizado y, en el caso de las autoridades, por sí o a través de cualquiera de sus delegados. Para efectos de lo anterior, los abogados autorizados y los delegados invariablemente deberán contar con facultades expresas para tal efecto.\nARTÍCULO 158. Las gestiones para convenir la solución de la controversia no suspenden el procedimiento.\nARTÍCULO 159. Aun cuando las partes no hubieren convenido la solución de la controversia en la etapa postulatoria, podrán hacerlo hasta antes de la citación para sentencia, supuesto en el que se procederá de conformidad con lo dispuesto en los artículos\n155 y 156.\nTRANSITORIOS\nPRIMERO. La presente Ley entrará en vigor al día siguiente de su publicación en el\nPeriódico Oficial del Estado.\nLey del Tribunal Estatal de Justicia Administrativa de Baja California. Página 56\nSEGUNDO. Se abroga la Ley del Tribunal Estatal de Justicia Administrativa del\nEstado de Baja California, publicada en el Periódico Oficial No. 36, de fecha 07 de agosto de\n2017, Número Especial, Tomo CXXIV.\nTERCERO. Los juicios iniciados con anterioridad a la entrada en vigor de la presente\nLey, continuarán tramitándose hasta su resolución final conforme a las disposiciones aplicables vigentes a su inicio, salvo lo que se refiere a los preceptos legales siguientes:\n- Artículos 48, 49, 50, 51, 52 y 53 de la presente Ley, en materia de notificaciones.\n- Artículos 70 y 116 de la presente Ley, que regulan la conciliación hasta antes de la citación de sentencia y la posibilidad de las partes de convenir el cumplimiento de la ejecutoria.\n- Artículos 99, 100 y 101 de la presente Ley, que regulan la prueba pericial, salvo los casos en que ya se hubiera designado al perito del Tribunal, supuestos en los que se continuará su tramitación conforme la Ley que se abroga.\nCUARTO. Los Magistrados de Sala que a la entrada en vigor de la presente Ley se encuentren en ejercicio de su cargo, continuarán en ellos hasta concluir el periodo para el cual fueron designados, ejerciendo durante dicho tiempo las atribuciones que determine el\nPleno, que podrán consistir en las correspondientes a los Jueces de Primera Instancia hasta en tanto éstos sean nombrados.\nQUINTO. El Pleno del Tribunal designará a los jueces de primera instancia cuyos juzgados se encuentren vacantes, dentro de los noventa días siguientes al de la publicación del presente Decreto en el Periódico Oficial del Estado.\nSEXTO. Las autoridades a que se refieren los artículos 50, párrafo segundo, y 143 de esta Ley, contarán con un plazo de un mes a partir de la entrada en vigor del presente\nDecreto, para realizar el registro de su correo electrónico institucional ante el Tribunal.\nSÉPTIMO. El Sistema de Juicio en Línea operará una vez que el Tribunal cuente con la disponibilidad financiera necesaria. Cuando esto suceda, el Pleno del Tribunal lo de internet oficial del Tribunal.\nOCTAVO. El Pleno del Tribunal expedirá los Acuerdos a que hace referencia el artículo 21, fracción XIV, del presente ordenamiento, para la regulación del Sistema de Juicio\nDADO en Sesión Ordinaria Virtual en la Ciudad de Mexicali, B.C., a los dieciséis días del mes de junio del año dos mil veintiuno.\nLey del Tribunal Estatal de Justicia Administrativa de Baja California. Página 57\nDIP. EVA GRICELDA RODRÍGUEZ\nPRESIDENTA\n(RÚBRICA)\nDIP. MARÍA LUISA VILLALOBOS ÁVILA\nSECRETARIA\n(RÚBRICA)\nDE CONFORMIDAD CON LO DISPUESTO POR LA FRACCIÓN I DEL ARTÍCULO 49\nCALIFORNIA, IMPRÍMASE Y PUBLÍQUESE.\nMEXICALI, BAJA CALIFORNIA, A LOS DIECISÉIS DÍAS DEL MES DE JUNIO DEL\nAÑO DOS MIL VEINTIUNO.\nJAIME BONILLA VALDEZ\nGOBERNADOR DEL ESTADO\n(RÚBRICA)\nAMADOR RODRÍGUEZ LOZANO\nSECRETARIO GENERAL DE GOBIERNO\nLey del Tribunal Estatal de Justicia Administrativa de Baja California. Página 58\nARTÍCULO 8.- Sentencia a Acción de Inconstitucionalidad 111/2021, notificada al\nARTÍCULO 9.- Sentencia a Acción de Inconstitucionalidad 111/2021, notificada al\nARTÍCULO 15.- Sentencia a Acción de Inconstitucionalidad 111/2021, notificada al\nARTÍCULO 39.- Sentencia a Controversia Constitucional 356/2023, notificada al\nLey del Tribunal Estatal de Justicia Administrativa de Baja California. Página 59\nSENTENCIA DE LA ACCIÓN DE INCONSTITUCIONALIDAD 111/2021, NOTIFICADA\nAL CONGRESO DEL ESTADO DE BAJA CALIFORNIA EL DÍA 28 DE SEPTIEMBRE DE\n2022, DE CONFORMIDAD CON SU PUNTO RESOLUTIVO TERCERO, MEDIANTE EL\nCUAL SE DECLARA LA INVALIDEZ DEL ARTÍCULO 8, FRACCIÓN I, EN RELACIÓN CON\nEL CONTENIDO NORMATIVO QUE POR VÍA DE REMISIÓN TOMA DEL ARTÍCULO 60,\nFRACCIÓN I, DE LA CONSTITUCIÓN POLÍTICA LOCAL, EN LA PORCIÓN “POR\nNACIMIENTO”, ASÍ COMO LA FRACCIÓN VI, EN LA PORCIÓN “U OTRO QUE LASTIME\nSERIAMENTE LA BUENA FAMA EN EL CONCEPTO PÚBLICO”; DEL ARTÍCULO 9,\nFRACCIÓN I, EN RELACIÓN CON EL CONTENIDO NORMATIVO QUE RETOMA POR VÍA\nDE REMISIÓN AL ARTÍCULO 62, FRACCIÓN V, DE LA CONSTITUCIÓN POLÍTICO\nLOCAL, EN LA PARTE QUE DICE: “U OTRO QUE LESIONE LA BUENA FAMA EN EL\nCONCEPTO PÚBLICO”; Y DEL ARTÍCULO 15, FRACCIÓN IV, TODOS DE LA LEY DEL\nTRIBUNAL ESTATAL DE JUSTICIA ADMINISTRATIVA DE BAJA CALIFORNIA, EXPEDIDA\nMEDIANTE DECRETO NÚMERO 255 PUBLICADO EN EL PERIÓDICO OFICIAL DE ESA\nENTIDAD FEDERATIVA EL DIECIOCHO DE JUNIO DE DOS MIL VEINTIUNO.\nNOTA: CON RELACIÓN A LAS PORCIONES NORMATIVAS QUE ALCANZARON\nINVALIDEZ, SE PRECISA QUE ÉSTA SOLO CONCIERNE A LA REMISIÓN QUE HACE A\nLA CONSTITUCIÓN LOCAL LAS NORMAS PRECISADAS, PARA QUE NO SEAN\nAPLICADAS LAS PORCIONES NORMATIVAS INVALIDADAS.\nSENTENCIA A CONTROVERSIA CONSTITUCIONAL 356/2023, NOTIFICADA AL\nCONGRESO DEL ESTADO DE BAJA CALIFORNIA EL DÍA 09 DE ABRIL DE 2025,\nMEDIANTE LA CUAL SE RESOLVIÓ EN LOS TÉRMINOS SIGUIENTES:\n“PRIMERO. Es procedente y parcialmente fundada la presente controversia constitucional.\nSEGUNDO. Se desestima en la presente controversia constitucional respecto de Baja California, adicionado mediante el DECRETO No. 97, publicado en el Periódico\nOficial de dicha entidad federativa el veintiocho de julio de dos mil diecisiete, así como de los transitorios décimo quinto y décimo sexto del referido decreto.\nTERCERO. Se declara la invalidez del artículo 39 en su porción normativa ‘Para la Ley del Tribunal Estatal de Justicia Administrativa de Baja California, expedida mediante el DECRETO No. 255, publicado en el referido Periódico Oficial el dieciocho de junio de dos mil veintiuno; y de la convocatoria para la selección de aspirantes a\nJusticia Administrativa de Baja California, publicada en el citado medio difusión oficial\nLey del Tribunal Estatal de Justicia Administrativa de Baja California. Página 60 el doce de mayo de dos mil veintitrés, la cual surtirá sus efectos a partir de la notificación de estos puntos resolutivos al Congreso de dicho Estado.\nPeriódico Oficial del Estado de Baja California, así como en el Semanario Judicial de la Federación y su Gaceta.”\n…\n…\nATENTAMENTE\nLICENCIADO RAFAEL COELLO CETINA\n(RÚBRICA)\nLey del Tribunal Estatal de Justicia Administrativa de Baja California. Página 61",
  "ordenamiento": "REGLAMENTO",
  "jurisdiccion": "BAJA CALIFORNIA",
  "fuente_oficial": "Periódico Oficial",
  "FECHA PER OFIC": "2021/06/18",
  "ESTATUS": "VIGENTE",
  "TOMO": "TOMO_V",
  "URL": "https://www.congresobc.gob.mx/Documentos/ProcesoParlamentario/Leyes/TOMO_V/20210618_LEYTRIBJUSTADMTVA-2.PDF",
  "es_escaneado": false,
  "tiene_tablas": false,
  "materia": [
    "penal",
    "seguridad",
    "justicia"
  ]
}