{
  "titulo": "Ley QUE CREA LA COMISIÓN ESTATAL DEL SISTEMA PENITENCIARIO DE BAJA CALIFORNIA",
  "Contenido": ".\nActualización Legislativa.\nÚltima reforma P. O. No.7, Índice, 09-Feb-2024\nLEY QUE CREA LA COMISIÓN ESTATAL DEL SISTEMA PENITENCIARIO DE\nBAJA CALIFORNIA\nPublicado en el Periódico Oficial No. 22, de fecha 30 de abril de 2020, Número Especial, Tomo CXXVII.\nTÍTULO PRIMERO\nDISPOSICIONES GENERALES\nArtículo 1. Esta Ley es de orden público e interés social y tiene por objeto regular la organización y funcionamiento de la Comisión Estatal del Sistema Penitenciario de Baja\nCalifornia.\nArtículo 2. Se crea la Comisión Estatal del Sistema Penitenciario de Baja California, como organismo público descentralizado de la Administración Pública del Estado, con personalidad jurídica, patrimonio propio y autonomía de gestión para el cumplimiento de sus fines.\nLa Comisión Estatal del Sistema Penitenciario de Baja California estará sectorizada a la Secretaría de Seguridad Ciudadana.\nPárrafo Adicionado\nArtículo Reformado\nArtículo 3. para los efectos de esta ley, se entenderá por:\nI. El Consejo: Consejo de Desarrollo Policial.\nII. La Comisionada o Comisionado: la persona Titular de la Comisión Estatal del\nSistema Penitenciario del Estado.\nFracción Reformada\nIII. La Comisión: La Comisión Estatal del Sistema Penitenciario de Baja California.\nIV. Ley de Ley de Ejecución: Ley Nacional de Ejecución Penal.\nV. Ley de Justicia para Adolescentes: Ley Nacional del Sistema Integral de Justicia\nPenal para Adolescentes.\nVI. Miembro: las y los servidores públicos integrantes de la Fuerza Estatal de\nSeguridad y Custodia Penitenciaria.\nFracción Reformada\nLey que Crea la Comisión Estatal del Sistema Penitenciario de Baja California. Página 1\n.\nActualización Legislativa.\nÚltima reforma P. O. No.7, Índice, 09-Feb-2024\nVII. Unidades de Abastecimiento: Las Unidades de Abastecimiento de productos, servicios alimentarios y de higiene que se establezcan en los Centros de Reinserción Social.\nArtículo Reformado\nArtículo 4. La Comisión será la autoridad encargada de integrar, operar y administrar el Sistema Penitenciario, la cual tiene por objeto la ejecución material de la prisión preventiva, así como de las sanciones y medidas de seguridad previstas en las leyes penales, sobre la base del respeto a los derechos humanos, el trabajo, la capacitación para el mismo, la educación, la salud y el deporte, como medios para procurar la reinserción de las mujeres y hombres sentenciados, a la sociedad y procurar que no vuelva a delinquir.\nTÍTULO SEGUNDO\nDE LA COMISIÓN ESTATAL DEL SISTEMA PENITENCIARIO\nCAPÍTULO I\nDE LAS ATRIBUCIONES\nArtículo 5. Para el cumplimiento de su objeto, la Comisión tendrá las siguientes atribuciones:\nI. Operar y administrar el Sistema Estatal Penitenciario, así como a la Autoridad\nPenitenciaria y al Supervisor de libertad condicionada a que se refiere la Ley Nacional de\nEjecución Penal, así como a la Autoridad Administrativa especializada en la ejecución de medidas para adolescentes, en los términos de la Ley Nacional del Sistema Integral de\nJusticia Penal para Adolescentes y demás normatividad aplicable;\nII. Organizar la operación y administración de los Centros de Reinserción Social y de los Centros de Internamiento para Adolescentes en el Estado;\nIII. Elaborar un Programa Estatal de Reinserción Social;\nIV. Elaborar y expedir las normas técnicas, protocolos y manuales de operación\nAdolescentes en el Estado;\nV. Garantizar el respeto a los derechos humanos de las mujeres y hombres privados\nAdolescentes en el Estado, durante la ejecución de la prisión preventiva o las sanciones penales impuestas, de conformidad con las disposiciones legales aplicables;\nVI. Organizar las instalaciones de los Centros de Reinserción Social y de los Centros de Internamiento para Adolescentes en el Estado para mantener la seguridad, tranquilidad e integridad, de las mujeres y hombres privados de su libertad, del personal y de los visitantes, Ley que Crea la Comisión Estatal del Sistema Penitenciario de Baja California. Página 2\n.\nActualización Legislativa.\nÚltima reforma P. O. No.7, Índice, 09-Feb-2024 ejerciendo las medidas y acciones pertinentes para el buen funcionamiento, en términos de las disposiciones normativas aplicables;\nVII. Procurar la reinserción social efectiva mediante los distintos programas institucionales;\nVIII. Garantizar condiciones de internamiento dignas y seguras acordes al género de las personas privadas de su libertad, asegurando en todo momento a las mujeres y personas menstruantes el acceso a los productos de gestión menstrual en los Centros de Reinserción\nSocial y Centros de Internamiento para Adolescentes, conforme a la legislación aplicable;\nFracción Reformada\nIX. Gestionar la custodia penitenciaria;\nX. Instrumentar una clasificación de las distintas áreas y espacios en los Centros de\nReinserción Social y de los Centros de Internamiento para Adolescentes en el Estado, en términos de las disposiciones aplicables;\nXI. Promover la modernización de la infraestructura y determinar las necesidades para la operación del Sistema Penitenciario con perspectiva de género;\nXII. Promover que los Centros de Reinserción Social sean sustentables;\nXIII. Ejecutar las medidas disciplinarias a las personas privadas de la libertad por violación al régimen de disciplina en los Centros de Reinserción Social y de los Centros de\nInternamiento para Adolescentes en el Estado;\nXIV. Ejecutar el traslado de las personas privadas de la libertad de un Centro de\nReinserción Social y de los Centros de Internamiento para Adolescentes en el Estado a otro, de conformidad con las disposiciones aplicables;\nXV. Ejecutar, controlar, vigilar y dar seguimiento a las penas que imponga o modifique el órgano jurisdiccional competente;\nXVI. Aplicar las sanciones penales impuestas por los órganos jurisdiccionales, de conformidad con las disposiciones aplicables;\nXVII. Aplicar y supervisar normatividad sobre las medidas de seguridad en los Centros de Reinserción Social y de los Centros de Internamiento para Adolescentes en el Estado, así como aquellos que determinen las disposiciones aplicables;\nXVIII. Prestar la seguridad y custodia de la persona privada de su libertad en los\nLey que Crea la Comisión Estatal del Sistema Penitenciario de Baja California. Página 3\n.\nActualización Legislativa.\nÚltima reforma P. O. No.7, Índice, 09-Feb-2024\nCentros de Internamiento para Adolescentes en el Estado a donde se haya autorizado su traslado, de conformidad con las disposiciones aplicables;\nXIX. Ordenar y ejecutar los traslados y excarcelaciones de personas privadas de la libertad, en los términos de la Ley de Ejecución, la Ley de Justicia para Adolescentes y demás normatividad aplicable;\nXX. Establecer y administrar los registros fidedignos de información respecto a los\nCentros de Reinserción Social y de los Centros de Internamiento para Adolescentes en el\nEstado;\nXXI. Establecer y administrar una base de datos de personas privadas de la libertad con la información de cada persona que ingrese al Sistema Penitenciario, en los términos de las disposiciones aplicables;\nXXII. Promover y gestionar la incorporación de proyectos productivos de la iniciativa privada, así como la promoción de mano de obra de las personas privadas de su libertad para su propia activación laboral;\nXXIII. Fortalecer la coordinación e intercambio de información con instituciones del\nSistema Estatal de Seguridad;\nXXIV. Coordinar los mecanismos de enlace e intercambio de información con instituciones policiales, de procuración de justicia y demás instituciones de seguridad;\nXXV. Promover la consolidación del Servicio Profesional de Carrera Penitenciaria;\nXXVI. Organizar, operar y supervisar la prestación de los servicios postpenales para el apoyo a liberados o externados en su reinserción social y procurar su vida digna y prevenir la reincidencia, en términos de la Ley de Ejecución y demás disposiciones aplicables;\nXXVII. Organizar, operar y supervisar la prestación de los procesos de justicia restaurativa y los servicios de mediación en internamiento, de conformidad a la Ley de\nEjecución, la Ley de Justicia para Adolescentes y demás disposiciones aplicables, según corresponda;\nXXVIII. Participar en la elaboración y verificar el cumplimiento de los convenios de coordinación que se celebren con la Federación y los gobiernos de las entidades federativas, Ley que Crea la Comisión Estatal del Sistema Penitenciario de Baja California. Página 4\n.\nActualización Legislativa.\nÚltima reforma P. O. No.7, Índice, 09-Feb-2024\nXXIX. Garantizar el abastecimiento manejo, administración, control vigilancia y seguimiento de las unidades de abastecimientos de productos, servicios alimentarios y de higiene que se establezcan en los Centros de Reinserción Social, y\nXXX. Las demás que establezcan otras disposiciones aplicables.\nArtículo Reformado\nCAPÍTULO II\nDEL PATRIMONIO\nArtículo 6. El patrimonio de la Comisión se integra de la siguiente manera:\nI. Los bienes muebles e inmuebles y recursos de su propiedad;\nII. Las aportaciones de la Federación, Estado y municipios en su caso;\nIII. Los ingresos que perciba por la realización de actividades, servicios y operaciones que desarrolle en cumplimiento de su objeto;\nIV. Las aportaciones otorgadas por los particulares, y\nV. Los demás que se obtengan por cualquier título legal.\nArtículo 7. El domicilio del organismo será la ciudad de Mexicali, Baja California y podrán establecerse oficinas representativas en otros puntos de la entidad para el cumplimiento de sus objetivos.\nCAPÍTULO III\nDE LOS ÓRGANOS DE LA COMISIÓN\nArtículo 8. La Comisión contará con los órganos siguientes:\nI. Un Órgano de Gobierno que será la Junta de Gobierno;\nII. Un Órgano denominado Consejo de Desarrollo Policial;\nIII. La Unidad de Asuntos Internos, y\nIV. Las demás unidades administrativas que establezca su reglamento interior.\nCAPÍTULO IV\nDE LA JUNTA DE GOBIERNO\nLey que Crea la Comisión Estatal del Sistema Penitenciario de Baja California. Página 5\n.\nActualización Legislativa.\nÚltima reforma P. O. No.7, Índice, 09-Feb-2024\nArtículo 9. La Junta de Gobierno es el órgano máximo de gobierno al interior de la\nComisión, el cual estará integrado por los titulares de las siguientes dependencias:\nI. La persona Titular de la Secretaría de Seguridad Ciudadana, quien la presidirá;\nFracción Reformada\nII. La persona Titular de la Secretaría de Educación;\nFracción Reformada\nIII. La persona titular de la Secretaría de Salud;\nFracción Reformada\nIV. La persona Titular de la Secretaría del Trabajo y Previsión Social;\nFracción Reformada\nV. La persona titular de la Secretaría de Inclusión Social e Igualdad de Género; y,\nFracción Adicionada\nVI. Una Secretaría Técnica, a cargo de la persona Titular de la Comisión Estatal, quien participará sólo con voz en las sesiones de la Junta de Gobierno.\nLa presidencia de la Junta Gobierno y las demás personas que la integren, serán suplidas en sus ausencias temporales por quien éstos designen, con las mismas facultades.\nPárrafo Reformado\nArtículo Reformado\nArtículo 10. Las y los servidores públicos que integran la Junta de Gobierno previstos en el artículo anterior, durarán en su cargo en tanto sean titulares de las Dependencias en cuestión. Los cargos serán honoríficos.\nArticulo Reformado\nArtículo 11. Las sesiones que celebre la Junta de Gobierno, serán ordinarias y extraordinarias. Las primeras se llevarán a cabo cuando menos cuatro veces al año, en forma trimestral, teniendo el o la presidente de la Junta de Gobierno, la facultad de convocar a los demás miembros para la celebración de sesiones. este, con la de su suplente y con la asistencia de la mayoría de sus integrantes. Las resoluciones serán tomadas por mayoría de votos de los miembros presentes, teniendo voto de calidad en caso de empate, quien presida la sesión.\nArtículo 12. Las reglas de organización de las sesiones de la Junta se regularán por su Reglamento Interno.\nArtículo 13. Corresponde a la Junta de Gobierno:\nLey que Crea la Comisión Estatal del Sistema Penitenciario de Baja California. Página 6\n.\nActualización Legislativa.\nÚltima reforma P. O. No.7, Índice, 09-Feb-2024\nI. Establecer las políticas generales y aprobar los planes de trabajo y programas a desarrollar de la Comisión en congruencia con el Plan Estatal de Desarrollo;\nII. Aplicar y supervisar el cumplimiento de esta ley, así como las disposiciones que de ella emanen;\nIII. Aprobar el proyecto de presupuesto anual de ingresos y egresos del organismo;\nIV. Expedir el Reglamento Interno y aprobar la organización administrativa de la\nComisión;\nV. Aprobar los Estados Financieros de la Comisión;\nVI. Aprobar el calendario de sesiones ordinarias de la Junta de Gobierno;\nVII. Nombrar y remover a las y los servidores públicos de la Comisión, en los supuestos que establezcan las disposiciones aplicables;\nFracción Reformada\nVIII. Otorgar en favor de la persona que ocupa el cargo de Comisionada o\nComisionado, Poder General para pleitos y cobranzas, actos de administración y dominio, con todas las facultades generales y las especiales que requieran clausula especial conforme a la Ley;\nFracción Reformada\nIX. Aprobar la estructura orgánica, salarial y ocupacional conforme a las disposiciones aplicables;\nX. Acordar la celebración de convenios de coordinación y colaboración por parte de la\nComisión, con Dependencias y Entidades federales, estatales o municipales, organizaciones de la sociedad civil o instituciones con objetos afines;\nXI. Conocer de los asuntos que someta a su consideración;\nXII. Analizar y aprobar, en su caso, los informes periódicos que rinda el Comisionado,\nXIII. Los demás que se requieren y sean propios para el cumplimiento de sus funciones y fines de la Comisión.\nArtículo Reformado\nArtículo 14. La persona que preside la Junta de Gobierno tiene las atribuciones siguientes:\nPárrafo Reformado\nLey que Crea la Comisión Estatal del Sistema Penitenciario de Baja California. Página 7\n.\nActualización Legislativa.\nÚltima reforma P. O. No.7, Índice, 09-Feb-2024\nI. Presidir las sesiones de la Junta de Gobierno, teniendo voto de calidad;\nII. Convocar, por conducto de la Secretaría o Secretario Técnico, a las sesiones ordinarias y extraordinarias;\nFracción Reformada\nIII. Proponer el calendario de sesiones de la Junta de Gobierno;\nIV. Instalar, dirigir y levantar las sesiones;\nV. Firmar las actas de las sesiones, y\nVI. Las demás que establezcan otras disposiciones aplicables.\nArtículo Reformado\nArtículo 15. La persona a cargo de la Secretaría Técnica tendrá las atribuciones siguientes:\nPárrafo Reformado\nI. Notificar y entregar la convocatoria de las sesiones a las personas integrantes de la\nJunta de Gobierno;\nFracción Reformada\nII. Pasar lista de asistencia y verificar la existencia de quórum legal para sesionar;\nIII. Levantar, certificar y archivar las actas de las sesiones de la Junta de Gobierno;\nIV. Firmar las actas de las sesiones y recabar la de las y los integrantes de la Junta de\nGobierno que asistan a las sesiones;\nFracción Reformada\nV. Dar seguimiento a los acuerdos de la Junta de Gobierno, y\nVI. Las demás que establezcan otras disposiciones aplicables.\nArtículo Reformado\nCAPÍTULO V\nDEL COMISIONADO\nArtículo 16. Al frente de la Comisión estará la persona Comisionada o Comisionado, Artículo Reformada\nArtículo 17. Para acceder al cargo de Comisionado se requiere:\nI. Ser mexicana o mexicano;\nSentencia de Acción de Inconstitucionalidad 182/2020\nLey que Crea la Comisión Estatal del Sistema Penitenciario de Baja California. Página 8\n.\nActualización Legislativa.\nÚltima reforma P. O. No.7, Índice, 09-Feb-2024\nFracción Reformada\nII. Ser mayor de treinta años;\nIII. Contar con título profesional a nivel licenciatura o grado superior y cédula profesional con antigüedad de por lo menos con cinco años de ejercicio profesional;\nIV. No haber sido condenada o condenado por delito doloso;\nFracción Reformada\nV. No desempeñar ningún otro empleo, cargo, puesto o comisión, a excepción de los relacionados con la docencia, y\nVI. Ser de notoria buena conducta, honradez y probidad.\nArtículo Reformado\nArtículo 18. La persona que se desempeñe como Comisionada o Comisionado tendrá las siguientes facultades y obligaciones:\nPárrafo Reformado\nI. Administrar el sistema penitenciario;\nII. Operar y administrar el funcionamiento de los Centros de Reinserción Social, los\nCentros de Internamiento para Adolescentes en el Estado;\nIII. Ejercer la representación legal de la Comisión;\nIV. Supervisar las instalaciones de los de Reinserción Social, los Centros de\nInternamiento para Adolescentes en el Estado;\nV. Celebrar y otorgar toda clase de actos y documentos inherentes al objeto y funciones de la Comisión;\nVI. Proponer a la Junta de Gobierno el nombramiento y la remoción de las personas servidoras públicas, en los términos de las disposiciones aplicables;\nFracción Reformada\nVII. Presentar periódicamente, a la Junta de Gobierno, el informe del desempeño de las actividades de la Comisión, en los términos de las disposiciones aplicables;\nVIII. Ejecutar los acuerdos que dicte la Junta de Gobierno;\nIX. Coordinar las actividades de las direcciones, coordinaciones y demás unidades administrativas a su cargo;\nLey que Crea la Comisión Estatal del Sistema Penitenciario de Baja California. Página 9\n.\nActualización Legislativa.\nÚltima reforma P. O. No.7, Índice, 09-Feb-2024\nX. Emitir los lineamientos para autorizar el acceso a particulares y autoridades a los de Reinserción Social, los Centros de Internamiento para Adolescentes en el Estado, quienes deberán acatar en todo momento las disposiciones aplicables;\nXI. Supervisar la ejecución de las medidas disciplinarias impuestas a las personas privadas de la libertad por violación al régimen de disciplina al interior de los de Reinserción\nSocial, los Centros de Internamiento para Adolescentes en el Estado;\nXII. Supervisar el traslado de las personas privadas de la libertad de un Centro de\nReinserción Social y de los Centros de Internamiento para Adolescentes en el Estado a otro, en los términos de las disposiciones aplicables;\nXIII. Realizar propuestas o hacer llegar solicitudes de otorgamiento de beneficios que supongan una modificación a las condiciones de cumplimiento de la pena o una reducción de la misma a favor de las personas sentenciadas, en los términos de las disposiciones aplicables;\nXIV. Organizar la ejecución, control, vigilancia y seguimiento a las penas que imponga o modifique el órgano jurisdiccional competente;\nXV. Supervisar la aplicación de sanciones penales impuestas por los órganos jurisdiccionales y que se cumplan en los Centro de Reinserción Social y los Centros de\nInternamiento para Adolescentes en el Estado, de conformidad con las leyes aplicables;\nXVI. Promover ante las autoridades judiciales las acciones legales que correspondan y cumplir los mandatos de las autoridades judiciales dentro del ámbito de su competencia;\nXVII. Coordinar la aplicación las medidas de seguridad o vigilancia a las personas privadas de la libertad que lo requieran;\nXVIII. Administrar el archivo correspondiente a los expedientes médicos y expedientes únicos de ejecución penal de las personas que ingresen al sistema penitenciario, conforme a las disposiciones legales aplicables;\nXIX. Celebrar convenios con instituciones privadas relativos a la prestación de pena de trabajos a favor de la comunidad;\nXX. Celebrar convenios con instituciones públicas y privadas del sector salud en los ámbitos federal y estatal, a efecto de atender las urgencias médico-quirúrgicas cuya de Internamiento para Adolescentes en el Estado, así como para la designación del personal\nSistema Penitenciario, en términos de las disposiciones aplicables;\nLey que Crea la Comisión Estatal del Sistema Penitenciario de Baja California. Página 10\n.\nActualización Legislativa.\nÚltima reforma P. O. No.7, Índice, 09-Feb-2024\nXXI. Celebrar convenios de colaboración con Instituciones públicas y privadas de carácter nacional e internacional en materias educativas, culturales y deportivas para ampliar la oferta y calidad de los servicios ofrecidos en los Centros de Reinserción Social y Centros de Internamiento para Adolescentes en el Estado;\nXXII. Celebrar convenios de colaboración con Instituciones públicas y privadas de carácter nacional e internacional, con el objetivo de consolidar el Servicio Profesional de\nCarrera Penitenciaria, así como la actualización y capacitación del personal de la Comisión;\nXXIII. Emitir, avalar y negociar títulos de crédito, en los términos de las disposiciones aplicables;\nXXIV. Formular querellas y otorgar perdón;\nXXV. Ejercitar y desistirse de acciones judiciales, inclusive del juicio de amparo;\nXXVI. Comprometer asuntos en arbitraje y celebrar transacciones, conforme a las disposiciones aplicables;\nXXVII. Ejercer el presupuesto de egresos autorizado y vigilar su correcta aplicación, de conformidad con las disposiciones legales aplicables;\nXXVIII. Implementar mecanismos de participación y firmar convenios de colaboración con organizaciones de la sociedad civil a fin de diseñar o brindar servicios en internamiento y de naturaleza post-penal;\nXXIX. Solicitar el traslado involuntario de las personas privadas de la libertad procesadas o sentenciadas, en los términos de las disposiciones aplicables;\nXXX. Todas aquellas que expresamente le señale la Ley Nacional de Ejecución\nPenal;\nXXXI. Supervisar la aplicación de la normativa, protocolos y procedimientos aplicables a la operación del Sistema Penitenciario;\nXXXII. Expedir órdenes, circulares y demás documentos en el ámbito administrativo necesarios para el eficaz despacho de las funciones de la Comisión;\nXXXIII. Ejecutar las órdenes de traslado de las autoridades jurisdiccionales de las mujeres y los hombres privados de la libertad o solicitar las mismas, en los términos de las disposiciones aplicables, y\nXXXIV. Las demás que establezcan otras disposiciones aplicables.\nLey que Crea la Comisión Estatal del Sistema Penitenciario de Baja California. Página 11\n.\nActualización Legislativa.\nÚltima reforma P. O. No.7, Índice, 09-Feb-2024\nPara el despacho de los asuntos que competen a la persona Comisionada o\nComisionado, dispondrá de personal de seguridad y custodia, técnico, jurídico, administrativo, y de policía procesal necesario para garantizar el debido cumplimiento de sus funciones.\nPárrafo Reformado\nLas ausencias temporales de la persona Comisionada o Comisionado hasta por quince días naturales serán suplidas por el funcionario que el designe; en las mayores de este periodo, serán por quién designe la persona titular del Poder Ejecutivo del Estado.\nPárrafo Reformado\nArtículo Reformado\nCAPÍTULO VI\nDEL CONSEJO DE DESARROLLO POLICIAL\nArtículo 19. Si la naturaleza del asunto a tratar corresponde a una controversia que se suscite con relación al Régimen Disciplinario procedimientos del Servicio Profesional de\nCarrera, el Consejo se integrará de la forma siguiente:\nI.- La persona que ocupa el cargo de presidente.\nFracción Reformada\nII.- La persona que ocupa la Secretaría Técnica.\nFracción Reformada\nIII.- Tres Vocales, que serán:\nA) La persona titular de la Unidad de Asuntos Internos.\nInciso Reformado\nB) La persona titular de la Dirección del Centro de Reinserción Social o del Centro de Internamiento para Adolescentes en el Estado, al que pertenezca el Miembro sujeto al procedimiento.\nInciso Reformado\nC) Una persona representante, que será una o un Miembro de la unidad operativa, ya sea de investigación, prevención o de reacción del Centro al que pertenezca el Miembro sujeto al procedimiento.\nInciso Reformado\nLey.\nArtículo Reformado\nArtículo 20. Son funciones del Consejo, las siguientes:\nA) En materia del Régimen Disciplinario:\nLey que Crea la Comisión Estatal del Sistema Penitenciario de Baja California. Página 12\n.\nActualización Legislativa.\nÚltima reforma P. O. No.7, Índice, 09-Feb-2024\nI. Conocer y resolver toda controversia que se suscite con relación a los procedimientos del Régimen Disciplinario de los Miembros;\nII. Resolver sobre la suspensión preventiva del Miembro al inicio del procedimiento o en su caso, confirmar o revocar la decretada por la Dirección de Asuntos Internos;\nIII. Aplicar los medios de apremio para la correcta y eficaz substanciación de los procedimientos aplicables al Régimen Disciplinario;\nIV. Substanciar los procedimientos disciplinarios por incumplimiento a los deberes u obligaciones de los Miembros, preservando el derecho de garantía de audiencia;\nV. Sancionar a los Miembros por incumplimiento a los deberes previstos en esta Ley, su reglamento y demás disposiciones aplicables;\nVI. Ordenar el levantamiento de la suspensión preventiva en los casos de no responsabilidad de los Miembros;\nVII. Emitir y firmar las resoluciones y acuerdos de los procedimientos del Régimen\nDisciplinario, y\nVIII. Las demás que señalen en esta Ley, su Reglamento y demás disposiciones aplicables.\nB) En materia del Servicio Profesional de Carrera:\nI. Recibir las quejas o denuncias presentadas con relación al Servicio Profesional de\nCarrera;\nII. Conocer y resolver toda controversia que se suscite con relación a los procedimientos del Servicio Profesional de Carrera de las personas Aspirantes, Cadetes o\nMiembros;\nFracción Reformada\nIII. Validar y otorgar a las personas Miembros, condecoraciones, estímulos y promociones, instruyendo en éstas últimas, el otorgamiento de la constancia de grado policial correspondiente, y de conformidad a los procedimientos establecidos en esta Ley, su\nReglamento y demás disposiciones aplicables, y\nFracción Reformada\nIV. Las demás que señalen en esta Ley, su Reglamento y demás disposiciones aplicables.\nInciso Reformado\nLey que Crea la Comisión Estatal del Sistema Penitenciario de Baja California. Página 13\n.\nActualización Legislativa.\nÚltima reforma P. O. No.7, Índice, 09-Feb-2024\nC) Comunes tanto en materia del Régimen Disciplinario, así como en materia del\nServicio Profesional de Carrera:\nI. Analizar la excusa realizada por alguno de sus integrantes para conocer determinado procedimiento disciplinario y resolver su procedencia;\nII. Solicitar a las autoridades Federales, Estatales y Municipales, en el ámbito de su competencia, la información o documentación que obre en su poder y que sea necesaria para el ejercicio de sus funciones;\nIII. Proponer las reformas necesarias a los procedimientos jurídicos que regulan el\nRégimen Disciplinario;\nIV. Dictar las medidas necesarias para el despacho pronto y expedito de los asuntos de su competencia;\nV. Llevar y mantener actualizado el registro de datos de las personas Aspirantes, Cadetes y Miembros, así como supervisar su operatividad y confidencialidad, proporcionando la información a del Registro Nacional de Personal de Seguridad Pública y al\nSistema Estatal de Información sobre Seguridad Ciudadana; y,\nFracción Reformada\nVI. Las demás que señalen en la Ley, su Reglamento y demás disposiciones aplicables.\nInciso Reformado\nArtículo Reformado\nCAPÍTULO VII\nDEL ACCESO A SERVICIOS O PRODUCTOS BÁSICOS\nArtículo 21. La Comisión para lograr el acceso a servicios y acceso a productos básicos de las mujeres y los hombres privados de la libertad, así como personas adolescentes en internamiento, contará con unidades de abastecimiento que en todo momento procurará cumplir con las necesidades acordes a cada género, mismas que para su debida administración, control y vigilancia, podrá operar mediante fideicomiso o el instrumento jurídico que determine la Junta de Gobierno.\nPárrafo Reformado\nAdolescentes, deberán garantizar el acceso gratuito a productos de gestión menstrual para las mujeres, adolescentes y personas menstruantes privadas de la libertad.\nPárrafo Adicionado\nPárrafo Reformado\nArtículo Reformado\nLey que Crea la Comisión Estatal del Sistema Penitenciario de Baja California. Página 14\n.\nActualización Legislativa.\nÚltima reforma P. O. No.7, Índice, 09-Feb-2024\nArtículo 22. Cuando la Comisión deje de cumplir con su objetivo o su funcionamiento no resulte conveniente para la economía estatal o el interés público la Secretaría de\nHacienda, atendiendo la opinión de la dependencia coordinadora de sector, propondrá al\nEjecutivo del Estado su extinción, de conformidad con la Ley de Entidades Paraestatales del\nEstado de Baja California y demás disposiciones aplicables.\nTRANSITORIOS\nPRIMERO. La presente Ley entrará en vigor el día de su publicación en el Periódico\nOficial del Estado.\nSEGUNDO. Los recursos humanos, materiales y financieros con que cuenta la\nSubsecretaría del Sistema Estatal Penitenciario adscrita a la Secretaría General de\nGobierno, formarán parte del organismo público descentralizado denominado Comisión\nEstatal del Sistema Penitenciario.\nTERCERO. La Junta de Gobierno expedirá el Reglamento Interno de la Comisión dentro de los sesenta días siguientes a la entrada en vigor de esta Ley, mientras tanto, para el despacho de los asuntos de su competencia, seguirán rigiendo las disposiciones reglamentarias aplicables.\nCUARTO. Los trabajadores de la Subsecretaría del Sistema Estatal Penitenciario adscrita a la Secretaría de General de Gobierno, por virtud de la presente Ley, se transferirán al organismo público descentralizado denominado Comisión Estatal del Sistema\nPenitenciario. Los trabajadores de base, conservarán todos sus derechos laborales, de conformidad con las disposiciones aplicables.\nQUINTO. Los procedimientos disciplinarios y de promoción policial que hayan sido iniciados antes de la entrada en vigor de la presente Ley, continuarán su desarrollo hasta concluirse definitivamente, conforme a las disposiciones legales que se encontraban vigentes al momento de su inicio.\nSEXTO. Dentro de los 60 días contados a partir de la entrada en vigor de la presente materia penitenciaria. del Estado de Baja California, en la Ciudad de Mexicali, B.C., a los veinticuatro días del mes de abril del año dos mil veinte.\nDIP. LUIS MORENO HERNÁNDEZ\nPRESIDENTE\nLey que Crea la Comisión Estatal del Sistema Penitenciario de Baja California. Página 15\n.\nActualización Legislativa.\nÚltima reforma P. O. No.7, Índice, 09-Feb-2024\nDIP. EVA GRICELDA RODRÍGUEZ\nSECRETARIA\n(RÚBRICA)\nDE CONFORMIDAD CON LO DISPUESTO POR LA FRACCIÓN I DEL ARTÍCULO 49\nMEXICALI, BAJA CALIFORNIA, A LOS VEINTIOCHO DÍAS DEL MES DE ABRIL DEL\nAÑO DOS MIL VEINTE.\nJAIME BONILLA VALDEZ\nGOBERNADOR DEL ESTADO\nAMADOR RODRÍGUEZ LOZANO\nSECRETARIO GENERAL DE GOBIERNO\nLey que Crea la Comisión Estatal del Sistema Penitenciario de Baja California. Página 16\n.\nActualización Legislativa.\nÚltima reforma P. O. No.7, Índice, 09-Feb-2024\nARTÍCULO 2.- Fue reformado mediante Decreto No. 66, publicado en el Periódico Oficial\nNo. 109, de fecha 31 de diciembre de 2021, Índice, Tomo CXXVIII, expedido por la H. XXIV\nLegislatura, siendo Gobernadora Constitucional la C. Marina del Pilar Ávila Olmeda 20212027;\nARTÍCULO 3.- Fue reformado mediante Decreto No. 66, publicado en el Periódico Oficial\nNo. 109, de fecha 31 de diciembre de 2021, Índice, Tomo CXXVIII, expedido por la H. XXIV\nLegislatura, siendo Gobernadora Constitucional la C. Marina del Pilar Ávila Olmeda 20212027; fue reformado por Decreto No. 375, publicado en el Periódico Oficial No. 7, de fecha\n09 de febrero de 2024, Índice, Tomo CXXXI, expedido por la H. XXIV Legislatura, siendo\nGobernadora Constitucional la C. Marina del Pilar Ávila Olmeda, 2021-2027;\nARTÍCULO 5.- Fue reformado mediante Decreto No. 198, publicado en el Periódico Oficial\nNo. 6, de fecha 27 de enero de 2023, Índice, Tomo CXXX, expedido por la H. XXIV\nLegislatura, siendo Gobernadora Constitucional la C. Marina del Pilar Ávila Olmeda 20212027; fue reformado por Decreto No. 375, publicado en el Periódico Oficial No. 7, de fecha\n09 de febrero de 2024, Índice, Tomo CXXXI, expedido por la H. XXIV Legislatura, siendo\nGobernadora Constitucional la C. Marina del Pilar Ávila Olmeda, 2021-2027;\nARTÍCULO 9.- Fue reformado mediante Decreto No. 66, publicado en el Periódico Oficial\nNo. 109, de fecha 31 de diciembre de 2021, Índice, Tomo CXXVIII, expedido por la H. XXIV\nLegislatura, siendo Gobernadora Constitucional la C. Marina del Pilar Ávila Olmeda 20212027; fue reformado por Decreto No. 375, publicado en el Periódico Oficial No. 7, de fecha\n09 de febrero de 2024, Índice, Tomo CXXXI, expedido por la H. XXIV Legislatura, siendo\nGobernadora Constitucional la C. Marina del Pilar Ávila Olmeda, 2021-2027;\nARTÍCULO 10.- Fue reformado por Decreto No. 375, publicado en el Periódico Oficial No. 7, de fecha 09 de febrero de 2024, Índice, Tomo CXXXI, expedido por la H. XXIV Legislatura, siendo Gobernadora Constitucional la C. Marina del Pilar Ávila Olmeda, 2021-2027;\nARTÍCULO 13.- Fue reformado por Decreto No. 375, publicado en el Periódico Oficial No. 7, siendo Gobernadora Constitucional la C. Marina del Pilar Ávila Olmeda, 2021-2027;\nARTÍCULO 14.- Fue reformado por Decreto No. 375, publicado en el Periódico Oficial No. 7, siendo Gobernadora Constitucional la C. Marina del Pilar Ávila Olmeda, 2021-2027;\nARTÍCULO 15.- Fue reformado por Decreto No. 375, publicado en el Periódico Oficial No. 7, siendo Gobernadora Constitucional la C. Marina del Pilar Ávila Olmeda, 2021-2027;\nLey que Crea la Comisión Estatal del Sistema Penitenciario de Baja California. Página 17\n.\nActualización Legislativa.\nÚltima reforma P. O. No.7, Índice, 09-Feb-2024\nARTÍCULO 16.- Fue reformado por Decreto No. 375, publicado en el Periódico Oficial No. 7, de fecha 09 de febrero de 2024, Índice, Tomo CXXXI, expedido por la H. XXIV Legislatura, siendo Gobernadora Constitucional la C. Marina del Pilar Ávila Olmeda, 2021-2027;\nARTÍCULO 17.- Mediante Sentencia de Acción de Inconstitucionalidad 182/2020, publicada en el Periódico Oficial no. 8, de fecha 28 de enero de 2022, Sección V, Tomo CXXIX, siendo\nGobernadora Constitucional la C. Marina del Pilar Ávila Olmeda 2021-2027; mediante la cual, en los términos de su Resolutivo Tercero, se declara la invalidez del Artículo 17,\nFracción I, en su porción normativa “por nacimiento”, expedida mediante el Decreto No. 58, publicado en el Periódico Oficial No. 22, de fecha 30 de abril de 2020, Número Especial, Tomo CXXVII.\nARTÍCULO 18.- Fue reformado por Decreto No. 375, publicado en el Periódico Oficial No. 7, de fecha 09 de febrero de 2024, Índice, Tomo CXXXI, expedido por la H. XXIV Legislatura, siendo Gobernadora Constitucional la C. Marina del Pilar Ávila Olmeda, 2021-2027;\nARTÍCULO 19.- Fue reformado por Decreto No. 375, publicado en el Periódico Oficial No. 7, de fecha 09 de febrero de 2024, Índice, Tomo CXXXI, expedido por la H. XXIV Legislatura, siendo Gobernadora Constitucional la C. Marina del Pilar Ávila Olmeda, 2021-2027;\nARTÍCULO 20.- Fue reformado mediante Decreto No. 66, publicado en el Periódico Oficial\nNo. 109, de fecha 31 de diciembre de 2021, Índice, Tomo CXXVIII, expedido por la H. XXIV\nLegislatura, siendo Gobernadora Constitucional la C. Marina del Pilar Ávila Olmeda 20212027; fue reformado por Decreto No. 375, publicado en el Periódico Oficial No. 7, de fecha\nGobernadora Constitucional la C. Marina del Pilar Ávila Olmeda, 2021-2027;\nARTÍCULO 21.- Fue reformado mediante Decreto No. 198, publicado en el Periódico Oficial\nLegislatura, siendo Gobernadora Constitucional la C. Marina del Pilar Ávila Olmeda 20212027; fue reformado por Decreto No. 375, publicado en el Periódico Oficial No. 7, de fecha\nGobernadora Constitucional la C. Marina del Pilar Ávila Olmeda, 2021-2027;\nLey que Crea la Comisión Estatal del Sistema Penitenciario de Baja California. Página 18\n.\nActualización Legislativa.\nÚltima reforma P. O. No.7, Índice, 09-Feb-2024\nARTÍCULO TERCERO TRANSITORIO DEL DECRETO No. 66, POR EL QUE SE\nREFORMAN LOS ARTÍCULOS 2, 3, 9 Y 20; PUBLICADO EN EL PERIÓDICO OFICIAL No.\n109, DE FECHA 31 DE DICIEMBRE DE 2021, ÍNDICE, TOMO CXXVIII, EXPEDIDO POR LA\nH. XXIV LEGISLATURA, SIENDO GOBERNADORA CONSTITUCIONAL LA C. MARINA\nDEL PILAR ÁVILA OLMEDA 2021-2027.\nARTÍCULO TRANSITORIO\nPRIMERO. Las presentes reformas entrarán en vigor el primero de enero de 2022.\nSEGUNDO. Dentro de un plazo de treinta días contados a partir de la entrada en vigor de las presentes reformas, deberá emitirse en la Acuerdo de Sectorización que determine como cabeza de sector de la Comisión Estatal del Sistema Penitenciario de Baja California, a la Secretaría de Seguridad Ciudadana.\nDADO en Sesión Extraordinaria de la XXIV Legislatura en la Ciudad de Mexicali, B.C., a los veintisiete días del mes de diciembre del año dos mil veintiuno.\nDIP. JUAN MANUEL MOLINA GARCÍA\nPRESIDENTE\n(RÚBRICA)\nDIP. AMINTHA GUADALUPE BRICEÑO CINCO\nPROSECRETARIA\n(RÚBRICA)\nDE CONFORMIDAD CON LO DISPUESTO POR LA FRACCIÓN I DEL ARTÍCULO 49\nCALIFORNIA, IMPRÍMASE Y PUBLÍQUESE.\nMEXICALI, BAJA CALIFORNIA, A LOS VEINTINUEVE DÍAS DEL MES DE\nDICIEMBRE DEL AÑO DOS MIL VEINTIUNO.\nMARINA DEL PILAR ÁVILA OLMEDA\nGOBERNADORA DEL ESTADO\nDE BAJA CALIFORNIA\nCATALINO ZAVALA MÁRQUEZ\nSECRETARIO GENERAL DE GOBIERNO\nLey que Crea la Comisión Estatal del Sistema Penitenciario de Baja California. Página 19\n.\nActualización Legislativa.\nÚltima reforma P. O. No.7, Índice, 09-Feb-2024\nSENTENCIA DE ACCIÓN DE INCONSTITUCIONALIDAD 182/2020, PUBLICADA EN\nEL PERIÓDICO OFICIAL No. 8, DE FECHA 28 DE ENERO DE 2022, SECCIÓN V, TOMO\nCXXIX, SIENDO GOBERNADORA CONSTITUCIONAL LA C. MARINA DEL PILAR ÁVILA\nOLMEDA 2021-2027; MEDIANTE LA CUAL EN LOS TÉRMINOS DE SU RESOLUTIVO\nTERCERO, SE DECLARA LA INVALIDEZ DEL ARTÍCULO 17, FRACCIÓN I, EN SU\nPORCIÓN NORMATIVA “POR NACIMIENTO”, EXPEDIDA MEDIANTE EL DECRETO No.\n58, PUBLICADO EN EL PERIÓDICO OFICIAL No. 22, DE FECHA 30 DE ABRIL DE 2020,\nNÚMERO ESPECIAL, TOMO CXXVII.\nARTÍCULO TERCERO TRANSITORIO DEL DECRETO No. 198, POR EL QUE SE\nREFORMAN LOS ARTÍCULOS 5 Y 21; PUBLICADO EN EL PERIÓDICO OFICIAL No. 6, DE\nFECHA 27 DE ENERO DE 2023, ÍNDICE, TOMO CXXX, EXPEDIDO POR LA H. XXIV\nLEGISLATURA, SIENDO GOBERNADORA CONSTITUCIONAL LA C. MARINA DEL PILAR\nÁVILA OLMEDA 2021-2027.\nTRANSITORIOS\nPRIMERO. El presente Decreto entrará en vigor al día siguiente de su publicación en el Periódico Oficial del Estado.\nSEGUNDO. El suministro gratuito de productos de gestión menstrual se sujetará a la disponibilidad presupuestaria de la Comisión Estatal del Sistema Penitenciario de Baja\nCalifornia y con base a las disposiciones normativas aplicables en términos de la Ley\nGeneral de Salud.\nDADO en Sesión Ordinaria de la XXIV Legislatura en la Ciudad de Mexicali, B.C., a los doce días del mes de enero del año dos mil veintitrés.\nDIP. MARÍA DEL ROCÍO ADAME MUÑOZ\nPRESIDENTA\nDIP. DUNNIA MONTSERRAT MURILLO LÓPEZ\nSECRETARIA\nDE CONFORMIDAD CON LO DISPUESTO POR LA FRACCIÓN I DEL ARTÍCULO 49\nCALIFORNIA, IMPRÍMASE Y PUBLÍQUESE.\nLey que Crea la Comisión Estatal del Sistema Penitenciario de Baja California. Página 20\n.\nActualización Legislativa.\nÚltima reforma P. O. No.7, Índice, 09-Feb-2024\nMEXICALI, BAJA CALIFORNIA, A LOS TRECE DÍAS DEL MES DE ENERO DEL\nAÑO DOS MIL VEINTITRÉS.\nMARINA DEL PILAR ÁVILA OLMEDA\nGOBERNADORA DEL ESTADO\nDE BAJA CALIFORNIA\n(RÚBRICA)\nCATALINO ZAVALA MÁRQUEZ\nSECRETARIO GENERAL DE GOBIERNO\nDEL ESTADO DE BAJA CALIFORNIA\n(RÚBRICA)\nARTÍCULO ÚNICO TRANSITORIO DEL DECRETO No. 375, POR EL QUE SE\nAPRUEBAN LAS REFORMAS A LOS ARTÍCULOS 3, 5, 9, 10, 13, 14, 15, 16, 18, 19, 20 Y\n21; PUBLICADO EN EL PERIÓDICO OFICIAL No. 7, DE FECHA 09 DE FEBRERO DE\n2024, ÍNDICE, TOMO CXXXI, EXPEDIDO POR LA H. XXIV LEGISLATURA, SIENDO\nGOBERNADORA CONSTITUCIONAL LA C. MARINA DEL PILAR ÁVILA OLMEDA 2021-\n2027.\nTRANSITORIOS\nÚNICO.- El presente Decreto entrará en vigor el día siguiente al de su publicación en el\nPeriódico Oficial del Estado de Baja California.\nDADO en Sesión Ordinaria de la XXIV Legislatura en la Ciudad de Mexicali, B.C., a los veinticinco días del mes de enero del año dos mil veinticuatro.\nDIP. ARACELI GERALDO NÚÑEZ\nPRESIDENTA\n(RÚBRICA)\nDIP. MANUEL GUERRERO LUNA\nSECRETARIO\nDE CONFORMIDAD CON LO DISPUESTO POR LA FRACCIÓN I DEL ARTÍCULO 49 DE\nCALIFORNIA, IMPRÍMASE Y PUBLÍQUESE.\nMEXICALI, BAJA CALIFORNIA, A LOS VEINTINUEVE DÍAS DEL MES DE ENERO\nDEL AÑO DOS MIL VEINTICUATRO.\nMARINA DEL PILAR ÁVILA OLMEDA\nLey que Crea la Comisión Estatal del Sistema Penitenciario de Baja California. Página 21\n.\nActualización Legislativa.\nGOBERNADORA DEL ESTADO\nDE BAJA CALIFORNIA\nALFREDO ÁLVAREZ CÁRDENAS\nSECRETARIO GENERAL DE GOBIERNO\nDEL ESTADO DE BAJA CALIFORNIA\nLey que Crea la Comisión Estatal del Sistema Penitenciario de Baja California. Página 22",
  "ordenamiento": "REGLAMENTO",
  "jurisdiccion": "BAJA CALIFORNIA",
  "fuente_oficial": "Periódico Oficial",
  "FECHA PER OFIC": "2024/02/09",
  "ESTATUS": "VIGENTE",
  "TOMO": "TOMO_V",
  "URL": "https://www.congresobc.gob.mx/Documentos/ProcesoParlamentario/Leyes/TOMO_V/20240209_LEYCOMSISPENIT.PDF",
  "es_escaneado": false,
  "tiene_tablas": false,
  "materia": [
    "penal",
    "seguridad",
    "justicia"
  ]
}