{
  "titulo": "Ley DE PREVENCIÓN, TRATAMIENTO y CONTROL DE LAS ADICCIONES PARA EL ESTADO DE BAJA CALIFORNIA",
  "Contenido": ".\nActualización Legislativa.\nÚltima reforma P.O. No. 30, Número Especial, 13-May-2025\nLEY DE PREVENCIÓN, TRATAMIENTO Y CONTROL DE LAS ADICCIONES\nPARA EL ESTADO DE BAJA CALIFORNIA\nPublicada en el Periódico Oficial No. 48, Sección IX, de fecha 28 de octubre de 2016, Tomo CXXIII\nCAPÍTULO PRIMERO\nPREVENCIONES GENERALES\nARTÍCULO 1.- La presente Ley es de orden público e interés social, su objeto es regular la prestación de asistencia integral a personas con problemas de adicción para lograr su rehabilitación y reintegración a la sociedad.\nARTÍCULO 2.- El Estado y la sociedad asumen la tarea de prevenir, tratar, rehabilitar y reintegrar a la vida productiva a personas con factores de riesgo para desarrollar uso, abuso y dependencia a cualquier sustancia psicoactiva, mediante la creación de establecimientos especializados en adicciones.\nARTÍCULO 3.- Para efectos de la presente ley se aplicarán los conceptos establecidos en la Ley General de Salud, la Norma Oficial Mexicana NOM-028-SSA2-2009 y los siguientes:\nI. Comisión: Comisión Interdisciplinaria de Establecimientos Especializados en\nAdicciones;\nII. Comité Municipal: Comité Municipal para la Prevención y Control de las Adicciones;\nIII. Consejo: Consejo Estatal de Prevención y Control de las Adicciones;\nIV. Establecimiento: Establecimiento Especializado en Adicciones;\nV. Instituto: Instituto de Psiquiatría del Estado de Baja California;\nVI. Ley de Salud: Ley de Salud Pública para el Estado de Baja California, y\nVII. Secretaría: Secretaría de Salud del Estado.\nARTÍCULO 4.- Para los efectos de la presente ley se entiente por establecimiento del cargo. constituida y reconocida en términos de la Ley de Asistencia Social para el Estado, que tenga por objeto la atención de las adicciones. Este tipo de establecimiento deberá cumplir\nLey de Prevención, Tratamiento y Control de las Adicciones Página 1\n.\nActualización Legislativa.\nÚltima reforma P.O. No. 30, Número Especial, 13-May-2025 con sus obligaciones derivadas del ordenamiento en comento, sin perjuicio de la observancia a la presente ley.\nLas personas morales con fines lucrativos cuyo objeto sea la atención de las adicciones se considerarán establecimientos del sector privado.\nCAPÍTULO SEGUNDO\nAUTORIDADES E INSTANCIAS DE COORDINACIÓN\nSECCIÓN I\nDISPOSICIONES GENERALES\nARTÍCULO 5.- Son autoridades locales en materia de adicciones las señaladas en la\nLey de Salud.\nSECCIÓN II\nSECRETARÍA\nARTÍCULO 6.- Corresponde al Ejecutivo del Estado por conducto de la Secretaría, las siguientes atribuciones:\nI. Efectuar el control sanitario de los establecimientos, de conformidad con las disposiciones aplicables de la Ley de Salud;\nII. Llevar el registro de los establecimientos, así como de sus programas de trabajo;\nIII. La atención a las adicciones, de conformidad con la Ley General de Salud, la Ley de Salud y la presente ley;\nIV. Emitir opinión sobre el otorgamiento y cancelación de subsidios a establecimientos del sector social, de conformidad con lo previsto en la Ley de Fomento a las Actividades de\nBienestar y Desarrollo Social para el Estado, y\nV. Las demás que determine la Ley de Salud.\nSECCIÓN III\nINSTITUTO\nARTÍCULO 7.- El Instituto tendrá a su cargo las siguientes funciones:\nI. Coordinarse con la Secretaría para la ejecución en el Estado del Programa Nacional para la Prevención y Tratamiento de la Farmacodependencia;\nII. Proponer a la Secretaría la revocación de autorizaciones para el funcionamiento de establecimientos;\nLey de Prevención, Tratamiento y Control de las Adicciones Página 2\n.\nActualización Legislativa.\nÚltima reforma P.O. No. 30, Número Especial, 13-May-2025\nIII. Proponer a la Secretaría de Salud la celebración de convenios o acuerdos de coordinación y concertación de acciones con instituciones públicas y privadas en materia de adicciones, y\nIV. Las demás que determine la Ley de Salud y su decreto de Creación.\nSECCIÓN IV\nCONSEJO\nARTÍCULO 8.- Se crea el Consejo Estatal de Prevención y Control de las Adicciones, con el objeto de concertar, coordinar, promover, implementar y evaluar las acciones en materia de prevención, tratamiento y control de las adicciones, de acuerdo a la Ley General de Salud, la Ley de Salud y la presente ley.\nARTÍCULO 9.- El Consejo estará integrado de la siguiente forma:\nI. Gobernador del Estado, quien fungirá como Presidente;\nII. Secretario de Salud, quien fungirá como Coordinador General;\nIII. Un Secretario Técnico, quien será designado por el Gobernador a propuesta del\nCoordinador General;\nIV. El titular de la Secretaría General de Gobierno;\nV. El titular de la Secretaría de Desarrollo Social;\nVI. El titular de la Secretaría de Educación y Bienestar Social;\nVII. El titular de la Secretaría de Seguridad Pública;\nVIII. El titular de la Procuraduría General de Justicia del Estado;\nIX. El titular de la Secretaría del Trabajo y Previsión Social;\nX. El titular del Instituto de Psiquiatría del Estado;\nXI. El titular del Instituto de la Juventud del Estado;\nXII. Un representante de la Comisión, y\nXIII. Un representante de cada Comité Municipal para la Prevención y Control de las adicciones a que refiere la presente ley.\nLos integrantes señalados en las fracciones IV a XIII fungirán como Consejeros.\nARTÍCULO 10.- Los integrantes podrán nombrar a un suplente, quien deberá ser registrado ante el Coordinador General.\nEn caso de ausencia del Presidente, el Coordinador General lo suplirá.\nLey de Prevención, Tratamiento y Control de las Adicciones Página 3\n.\nActualización Legislativa.\nÚltima reforma P.O. No. 30, Número Especial, 13-May-2025\nARTÍCULO 11.- El Presidente podrá invitar, previo acuerdo del Pleno del Consejo, a representantes de dependencias u organizaciones de la sociedad civil con derecho a voz, sin voto.\nARTÍCULO 12.- El Consejo sesionará periódicamente conforme al calendario anual propuesto por el Presidente.\nPodrán convocar a sesiones extraordinarias cuando se justifique la urgencia del asunto a tratar, previa convocatoria del Presidente, del Coordinador General o en su caso más del cincuenta por ciento de los integrantes del Consejo.\nLas sesiones se llevarán a cabo en la fecha, hora y sede que se establezca en la convocatoria expedida por el Coordinador General, para lo cual los integrantes del Consejo deberán ser notificados con por lo menos setenta y dos horas de anticipación para el caso de sesiones ordinarias y con veinticuatro horas de anticipación para sesiones extraordinarias.\nEl quórum será con la presencia de más de la mitad de los Consejeros y los acuerdos serán válidos con la aprobación de más de la mitad de los Consejeros presentes. En caso de empate, el Presidente tendrá el voto de calidad para la aprobación del acuerdo respectivo.\nARTÍCULO 13.- El Consejo establecerá mesas de trabajo enfocadas a la prevención, tratamiento, control y vigilancia epidemiológica de las adicciones.\nSECCIÓN V\nCOMISIÓN\nARTÍCULO 14.- Se crea la Comisión Interdisciplinaria de Establecimientos\nEspecializados en Tratamiento de las Adicciones, misma que será instalada por el Poder\nEjecutivo del Estado a través de la Secretaría de Salud, la cual estará integrada de la siguiente forma:\nI. Secretario de Salud, Presidente;\nII. Subdirector de Normatividad del área de Adicciones del Instituto, Secretario;\nIII. Un Secretario Ejecutivo, designado por el Presidente;\nIV. Secretario de Desarrollo Social del Estado;\nV. Jefe de la Jurisdicción Sanitaria de Mexicali;\nVI. El Jefe de la Jurisdicción Sanitaria de Tijuana;\nVII. El Jefe de la Jurisdicción Sanitaria de Ensenada;\nVIII. Un representante de alguna asociación profesional de medicina;\nIX. Dos representantes de los establecimientos de Mexicali;\nLey de Prevención, Tratamiento y Control de las Adicciones Página 4\n.\nActualización Legislativa.\nÚltima reforma P.O. No. 30, Número Especial, 13-May-2025\nX. Dos representantes de los establecimientos de Tijuana;\nXI. Un representante de los establecimientos de Tecate;\nXII. Un representante de los establecimientos de Playas de Rosarito, y\nXIII. Un representante de los establecimientos de Ensenada.\nARTÍCULO 15.- Para la selección de los integrantes señalados en las fracciones VIII a XIII del artículo anterior, el Gobernador deberá emitir una convocatoria con base a la cual participen las asociación de profesionales en el campo de medicina, así como los establecimientos que deseen formar parte de la Comisión.\nUno de los criterios orientadores para la decisión de los representantes por parte de los establecimientos será que cumpla la normatividad aplicable para la prevencion, tratamiento y control de las adicciones y que no haya sido sancionado por lo menos en los últimos tres años inmediatos anteriores al día de emitirse la convocatoria.\nARTÍCULO 16.- El Presidente designará y removerá libremente al Secretario de la\nComisión.\nARÍCULO 17.- La Comisión Interdisciplinaria tendrá las siguientes funciones:\nI. Llevar un registro de los establecimientos que operan en el Estado, así como los programas que aplican en materia de adicciones;\nII. Opinar, previa solicitud de la Secretaría de Desarrollo Social, respecto a la asignación de recursos públicos a los establecimientos del sector social, con base a las disposiciones contenidas en la Ley de Asistencia Social para el Estado y la Ley de Fomento a las Actividades de Bienestar y Desarrollo Social para el Estado;\nIII. Prestar asistencia técnica a establecimientos del sector social o privado;\nIV. Ejecutar en forma coordinada con las autoridades Federales y Municipales programas aplicables en materia de adicciones;\nV. Proponer al Ejecutivo del Estado la celebración de convenios o acuerdos de coordinación y concertación de acciones con las Instituciones Públicas y Privadas de técnicos especializados en el área a que se refiere esta Ley, y\nVI. Solicitar a la autoridad y organismos correspondientes y con base a los acuerdos celebrados, la habilitación de los hospitales, clínicas y centros de salud que tuvieren a su cargo, de acuerdo con sus respectivas competencias, para la prestación de servicios destinados a la rehabilitación de las personas con problema de adicción.\nSECCIÓN VI\nCOMITÉS MUNICIPALES\nLey de Prevención, Tratamiento y Control de las Adicciones Página 5\n.\nActualización Legislativa.\nÚltima reforma P.O. No. 30, Número Especial, 13-May-2025\nARTÍCULO 18.- Cada municipio del Estado deberá instalar un Comité Municipal para la Prevención y Control de Adicciones.\nARTÍCULO 19.- Los Comités Municipales son instancias de coordinación y concertación para la prevención, atención e investigación de las adicciones, en los cuales participan instituciones públicas, organismos privados y sociales.\nARTÍCULO 20.- La integración de cada Comité Municipal será prevista en las disposiciones jurídicas aplicables, con base a las necesidades y determinaciones particulares de cada Municipio.\nARTÍCULO 21.- Los comités municipales tendrán al menos las siguientes atribuciones:\nI. Aplicar las políticas y estrategias adecuadas en materia de adicciones;\nII. Fomentar la concurrencia de otros programas de educación, seguridad e higiene en el trabajo, desarrollo juvenil y comunitario, de atención a las adicciones en los reclusorios municipales, incorporando conceptos que promuevan estilos de vida saludable;\nIII. Impulsar actividades de investigación epidemiológica, demográfica y psicosocial en la materia;\nIV. Promover actividades de sensibilización e información entre la población sobre el daño que produce a la salud el consumo de alcohol, tabaco y otras drogas, y convocar a la comunidad para que participe y apoye la reinserción social de los individuos afectados por el problema de las adicciones;\nV. Coadyuvar al cumplimiento de la normatividad vigente en materia de comercialización y consumo de bebidas alcohólicas, tabaco y otras drogas, así como proponer nuevos instrumentos que desalienten su consumo, y\nVI. Coadyuvar en la vigilancia para la aplicación de la normatividad vigente en materia de publicidad relativa a alcohol y tabaco.\nCAPÍTULO TERCERO\nESTABLECIMIENTOS\nARTÍCULO 22.- Los establecimientos del sector público ofrecerán los servicios en forma gratuita. cuando, derivado de un estudio socioeconómico, se determine la incapacidad de pago por parte del usuario o de sus familiares.\nEn el caso de los establecimientos de carácter privado, las tarifas serán las que cada uno determine.\nLey de Prevención, Tratamiento y Control de las Adicciones Página 6\n.\nActualización Legislativa.\nÚltima reforma P.O. No. 30, Número Especial, 13-May-2025\nARTÍCULO 23.- Los establecimientos deberán operar de acuerdo a lo que establece la Ley General de Salud y la Norma Oficial Mexicana aplicable en materia de adicciones.\nARTÍCULO 24.- Los establecimientos deberán funcionar bajo principios básicos de respeto y fomento a la dignidad de las personas, sus derechos, valores familiares y creencias personales.\nEl personal que labore en los centros tiene la obligación de vigilar, proteger y dar seguridad a los usuarios mientras permanezcan en el mismo, basando el trato hacia los mismos en el respeto a su persona.\nARTÍCULO 25.- La Secretaría autorizará la operación de los establecimientos, siempre que se cumplan con los siguientes requerimientos:\nI. Contar con instalaciones y equipo apropiados para la atención de usuarios, organizados y distribuidos conforme a grupos de edad y sexo de los usuarios apegado a las disposiciones legales aplicables en materia de salud y control de adicciones;\nII. Contar con un programa de trabajo apegado a las disposiciones legales aplicables en materia de salud y control de adicciones;\nIII. Contar con personal capacitado y recursos humanos suficientes para desarrollar los servicios del establecimiento;\nIV. Los servicios de los establecimientos deberán garantizar a los usuarios una alimentación adecuada, bajo condiciones estrictas de calidad alimenticia e higiene;\nV. Los programas de los establecimientos deberán contar con actividades que incluyan la participación de la familia del usuario, así como el fomento de valores familiares, el respeto a su persona, a sus derechos y a sus pertenencias, y\nVI. Los establecimientos deberán contar con procedimientos para recibir quejas, sugerencias y comentarios de evaluación de los servicios y trato del personal, tanto por parte de los usuarios, como de sus familiares y personas autorizadas para visitar al usuario.\nARTÍCULO 26.- La autorización para la operación de los establecimientos será revalidada anualmente por la Secretaría, en los términos de la Ley de Salud y la presente\nLey.\nARTÍCULO 27.- La Secretaría podrá revocar la autorización de un establecimiento en la forma y términos previstos en el capítulo décimo primero de la Ley de Salud.\nARTÍCULO 28.- En todo lo no previsto por esta ley en materia de autorizaciones a los establecimientos, se aplicará de forma supletoria las disposiciones previstas en la Ley de\nSalud.\nCAPÍTULO CUARTO\nINSPECCIÓN Y VIGILANCIA\nLey de Prevención, Tratamiento y Control de las Adicciones Página 7\n.\nActualización Legislativa.\nÚltima reforma P.O. No. 30, Número Especial, 13-May-2025\nARTÍCULO 29.- La Secretaría de Salud vigilará la operación de los establecimientos para verificar el cumplimiento de la presente ley.\nARTÍCULO 30.- La vigilancia se realizará a través de visitas a cargo del personal expresamente autorizado por la Secretaría, quienes deberán realizar las diligencias de conformidad con esta Ley y demás disposiciones aplicables.\nARTÍCULO 31.- La vigilancia de los establecimientos comprenderá:\nI. Que cuenten con autorización vigente de operación como establecimiento y las certificaciones correspondientes del personal que labore en el establecimiento;\nII. Las condiciones del establecimiento, verificando que sus instalaciones cumplan con los requerimientos de equipamiento, seguridad, higiene, espacios adecuados y suficientes, así como la organización adecuada de las diferentes áreas de servicio, en términos de la normatividad aplicable;\nIII. Las condiciones en que se encuentren las personas usuarias, verificando que estas sean adecuadas para garantizar un servicio eficiente, basado en un trato respetuoso, en beneficio de su bienestar físico y psicológico;\nFracción Reformada\nIV. La revisión de las áreas encargadas de servicios médicos, terapéuticos y de alimentación de las personas usuarias, para verificar que éstas cumplan con los requerimientos de la presente ley y su reglamento;\nFracción Reformada\nV. La vigilancia de los establecimientos también comprenderá el cumplimiento de lo establecido en los artículos 38 y 40 de esta ley; y,\nFracción Adicionada\nFracción Reformada\nVI. La revisión de que en la población interna se encuentren sólo personas con padecimientos de consumo de sustancias psicoactivas y de adicciones y no personas con algún tipo de discapacidad u otro padecimiento, cuyo fin del internamiento sea resolver problemas familiares, sociales, laborales, de vivienda o cuidados.\nFracción Adicionada\nArtículo Reformado\nARTÍCULO 32.- El resultado de la supervisión deberá hacerse constar en acta circunstanciada que deberá ser firmada tanto por el supervisor a cargo, como por el responsable del establecimiento y el personal que haya participado en la supervisión.\nARTÍCULO 33.- La Secretaría deberá realizar un mínimo de una visita por mes, asimismo, llevará a cabo visitas sin previo aviso a los establecimientos.\nLey de Prevención, Tratamiento y Control de las Adicciones Página 8\n.\nActualización Legislativa.\nÚltima reforma P.O. No. 30, Número Especial, 13-May-2025\nARTÍCULO 34.- En todo lo no previsto por esta ley en materia de inspeccion y vigilancia a los establecimientos, se aplicará de forma supletoria las disposiciones previstas en la Ley de Salud.\nCAPÍTULO QUINTO\nDEL TRATAMIENTO DE LAS ADICCIONES\nDenominación Reformada\nARTÍCULO 35.- La prestación de los servicios de tratamiento a las adicciones se consideran de interés público y social, por lo que se deberán implementar y prestar dichos servicios, contra la farmacodependencia, el alcoholismo y el tabaquismo en los términos de la Ley General de Salud, la Ley General para el Control del Tabaco y la demás normatividad aplicable.\nArtículo Reformado\nARTÍCULO 36.- Los servicios de tratamiento a las adicciones se proporcionarán a las personas que por voluntad propia o por mandato judicial requieran de dichos servicios. Para el caso de menores de edad o incapaces legales, se requerirá el consentimiento de los padres, tutor o representante legal.\nArtículo Reformado\nARTÍCULO 37.- La duración de los tratamientos proporcionados será́ supervisada por la Secretaría, la que deberá́ constatar que se alcance los objetivos del tratamiento y de acuerdo con el grado de adicción que tenga cada persona.\nArtículo Reformado\nARTÍCULO 38.- Las personas que estén bajo un tratamiento de adicciones tendrán los siguientes derechos:\nI. A recibir información sobre los servicios a los que pueden acceder;\nII. A recibir un tratamiento adecuado según la adicción o adicciones que padezca;\nIII. A ser respetado y no ser discriminado en su tratamiento por ningún motivo;\nIV. A la confidencialidad de la información relacionada con su proceso de tratamiento;\nV. A recibir por escrito el medicamento que se le prescriba para su tratamiento;\nVI. A que se le extienda constancia gratuita sobre el tratamiento que haya seguido o esté siguiendo;\nVII. A que se integre un expediente sobre todo su tratamiento, y\nVIII. Los demás que establezca la presente Ley y demás disposiciones aplicables.\nLey de Prevención, Tratamiento y Control de las Adicciones Página 9\n.\nActualización Legislativa.\nÚltima reforma P.O. No. 30, Número Especial, 13-May-2025\nArtículo Reformado\nARTÍCULO 39.- Además de lo dispuesto en los programas contra las adicciones previstos en la Ley General de Salud y demás normatividad aplicable, la Secretaría podrá promover los siguientes servicios para el tratamiento de las adicciones:\nI. Atención Médica;\nII. Terapias grupales e individuales;\nIII. Terapias conductuales específicas para evitar la recaída;\nIV. Farmacoterapia para reducir la necesidad imperiosa de consumir sustancias psicoactivas con potencial adictivo, y\nV. Orientación a la familia de la persona que sufre problemas de adicción.\nArtículo Reformado\nARTÍCULO 40.- Los Establecimientos que reciban subsidios o recursos públicos deberán incorporar en sus programas de trabajo la capacitación en oficios.\nArtículo Reformado\nARTÍCULO 41.- No se proporcionarán subsidios o recursos públicos a los\nEstablecimientos que no cumplan con lo previsto en los artículos 31, 38 y 40 de esta Ley.\nArtículo Reformado\nARTÍCULO 42.- Cualquier persona podrá denunciar ante la Secretaría las irregularidades que se den en los Establecimientos.\nArtículo Reformado\nCAPÍTULO SEXTO\nSANCIONES\nCapítulo Adicionado\nARTÍCULO 43.- Las violaciones a los preceptos de esta Ley, Normas Oficiales\nMexicanas, reglamentos y demás disposiciones aplicables, serán sancionadas administrativamente por la Secretaría.\nArtículo Reformado\nARTÍCULO 44.- Las sanciones administrativas podrán ser:\nI. Amonestación con apercibimiento;\nII. Multa;\nIII. Clausura temporal o definitiva, que podrá́ ser parcial o total, y\nLey de Prevención, Tratamiento y Control de las Adicciones Página 10\n.\nActualización Legislativa.\nÚltima reforma P.O. No. 30, Número Especial, 13-May-2025\nIV. Arresto hasta por treinta y seis horas.\nArtículo Adicionado\nARTÍCULO 45.- Al imponer una sanción la Secretaría fundará y motivará la resolución, tomando en cuenta:\nI. Los daños que se hayan producido o puedan producirse en la salud de las personas;\nII. La gravedad de la infracción;\nIII. Las condiciones socioeconómicas del infractor, y\nIV. La calidad de reincidente del infractor.\nArtículo Adicionado\nARTÍCULO 46.- Se sancionará con multa de veinte y hasta mil veces el salario mínimo general diario vigente en el Estado, por violación a las disposiciones contenidas en esta Ley.\nEn caso de reincidencia se duplicará el monto de la multa. Para los efectos de este\nCapítulo se entiende por reincidencia, que el infractor cometa la misma violación a las disposiciones de esta Ley o sus Reglamentos dos o más veces dentro del período de un año natural.\nArtículo Adicionado\nARTÍCULO 47.- La aplicación de las sanciones será́ sin perjuicio de que se dicten las medidas de seguridad sanitaria que procedan, en términos de la Ley de Salud, hasta en tanto se subsanen las irregularidades.\nImpuesta una multa, se comunicará a la Autoridad Fiscal correspondiente, para que la haga efectiva a través de su procedimiento económico coactivo.\nCuando la Autoridad Fiscal haga efectiva la multa, deberá́ dar aviso a la Secretaría.\nArtículo Adicionado\nARTÍCULO 48.- Procederá́ la clausura temporal o definitiva, parcial o total según la gravedad de la infracción, en los casos previstos en el artículo 185 de la Ley de Salud.\nArtículo Adicionado\nARTÍCULO 49.- En los casos de clausura definitiva, quedarán sin efecto las establecimiento.\nArtículo Adicionado\nLey de Prevención, Tratamiento y Control de las Adicciones Página 11\n.\nActualización Legislativa.\nÚltima reforma P.O. No. 30, Número Especial, 13-May-2025\nARTÍCULO 50.- Se sancionará con arresto hasta por treinta y seis horas:\nI. A la persona que interfiera o se oponga al ejercicio de las funciones de la\nSecretaría, y\nII. A la persona que en rebeldía se niegue a cumplir los requerimientos y disposiciones de la Secretaría, provocando con ello un peligro a la salud de las personas.\nSólo procederá́ esta sanción, si previamente se dictó́ cualquiera otra de las sanciones a que se refiere este Capítulo.\nArtículo Adicionado\nARTÍCULO 51.- El procedimiento para aplicar las sanciones establecidas en esta ley será́ el previsto en la Ley de Salud.\nArtículo Adicionado\nARTÍCULOS TRANSITORIOS\nPRIMERO.- Esta Ley entrará en vigor al día siguiente de su publicación en el\nPeriódico Oficial del Estado.\nSEGUNDO.- Se abroga la Ley de Rehabilitación y Reintegración Social de Personas con Problemas de Drogadicción y Alcoholismo para el Estado de Baja California, publicada en el Periódico Oficial del Estado No. 51, de fecha 13 de octubre de 1995, Tomo CI.\nTERCERO.- Se abroga el Acuerdo por el que se crea el Consejo Estatal Contra las\nAdicciones, publicado en el Periódico Oficial del Estado en fecha 3 de diciembre de 1999.\nCUARTO.- La convocatoria señalada en el artículo 15 de esta ley, será emitida a más tardar a los sesenta días posteriores de iniciada la vigencia de este ordenamiento.\nQUINTO.- El Consejo, la Comisión y los Comités Municipales para la Prevención y posteriores a la entrada en vigor del presente ordenamiento. del Estado de Baja California, en la Ciudad de Mexicali, B.C., a los veintidós días del mes de septiembre del año dos mil dieciséis.\nDIP. MÓNICA BEDOYA SERNA\nPRESIDENTA\n(RÚBRICA)\nLey de Prevención, Tratamiento y Control de las Adicciones Página 12\n.\nActualización Legislativa.\nÚltima reforma P.O. No. 30, Número Especial, 13-May-2025\nDIP. ROSA ISELA PERALTA CASILLAS\nSECRETARIA\n(RÚBRICA)\nDE CONFORMIDAD CON LO DISPUESTO POR LA FRACCION I DEL ARTÍCULO 49\nMEXICALI, BAJA CALIFORNIA, A LOS TRES DÍAS DEL MES DE OCTUBRE DEL\nAÑO DOS MIL DIECISÉIS.\nFRANCISCO ARTURO VEGA DE LAMADRID\nGOBERNADOR DEL ESTADO\n(RÚBRICA)\nFRANCISCO RUEDA GOMEZ\nSECRETARIO GENERAL DE GOBIERNO\n(RÚBRICA)\nLey de Prevención, Tratamiento y Control de las Adicciones Página 13\n.\nActualización Legislativa.\nÚltima reforma P.O. No. 30, Número Especial, 13-May-2025\nArtículo 31.- Fue reformado por Decreto No. 192, publicado en el Periódico Oficial No.\n10, de fecha 02 de marzo de 2018, Sección II, Tomo CXXV, expedido por la H. XXII\nLegislatura, siendo Gobernador Constitucional el C. Francisco Arturo Vega de Lamadrid\n2013 – 2019; fue reformado mediante Decreto No. 92, publicado en el Periódico Oficial No.\n30, Número Especial, de fecha 13 de mayo de 2025, Tomo CXXXII, expedido por la H. XXV\nLegislatura, siendo Gobernadora Constitucional la C. Marina del Pilar Ávila Olmeda 20212027;\nFue reformada la denominación de este Capítulo por Decreto No. 192, publicado en el\nPeriódico Oficial No. 10, de fecha 02 de marzo de 2018, Sección II, Tomo CXXV, expedido por la H. XXII Legislatura, siendo Gobernador Constitucional el C. Francisco Arturo Vega de\nLamadrid 2013 - 2019.\nCAPÍTULO QUINTO\nDEL TRATAMIENTO DE LAS ADICCIONES\nArtículo 35.- Fue reformado por Decreto No. 192, publicado en el Periódico Oficial No.\n10, de fecha 02 de marzo de 2018, Sección II, Tomo CXXV, expedido por la H. XXII\nLegislatura, siendo Gobernador Constitucional el C. Francisco Arturo Vega de Lamadrid\n2013 - 2019.\nArtículo 36.- Fue reformado por Decreto No. 192, publicado en el Periódico Oficial No.\n10, de fecha 02 de marzo de 2018, Sección II, Tomo CXXV, expedido por la H. XXII\nLegislatura, siendo Gobernador Constitucional el C. Francisco Arturo Vega de Lamadrid\n2013 - 2019.\nArtículo 37.- Fue reformado por Decreto No. 192, publicado en el Periódico Oficial No.\n10, de fecha 02 de marzo de 2018, Sección II, Tomo CXXV, expedido por la H. XXII\nLegislatura, siendo Gobernador Constitucional el C. Francisco Arturo Vega de Lamadrid\n2013 - 2019.\nArtículo 38.- Fue reformado por Decreto No. 192, publicado en el Periódico Oficial No.\n10, de fecha 02 de marzo de 2018, Sección II, Tomo CXXV, expedido por la H. XXII\nLegislatura, siendo Gobernador Constitucional el C. Francisco Arturo Vega de Lamadrid\n2013 - 2019.\nArtículo 39.- Fue reformado por Decreto No. 192, publicado en el Periódico Oficial No.\nLegislatura, siendo Gobernador Constitucional el C. Francisco Arturo Vega de Lamadrid\n2013 - 2019.\nArtículo 40.- Fue reformado por Decreto No. 192, publicado en el Periódico Oficial No.\nLey de Prevención, Tratamiento y Control de las Adicciones Página 14\n.\nActualización Legislativa.\nÚltima reforma P.O. No. 30, Número Especial, 13-May-2025\nLegislatura, siendo Gobernador Constitucional el C. Francisco Arturo Vega de Lamadrid\n2013 - 2019.\nArtículo 41.- Fue reformado por Decreto No. 192, publicado en el Periódico Oficial No.\n10, de fecha 02 de marzo de 2018, Sección II, Tomo CXXV, expedido por la H. XXII\nLegislatura, siendo Gobernador Constitucional el C. Francisco Arturo Vega de Lamadrid\n2013 - 2019.\nArtículo 42.- Fue reformado por Decreto No. 192, publicado en el Periódico Oficial No.\n10, de fecha 02 de marzo de 2018, Sección II, Tomo CXXV, expedido por la H. XXII\nLegislatura, siendo Gobernador Constitucional el C. Francisco Arturo Vega de Lamadrid\n2013 - 2019.\nFue adicionado este Capítulo por Decreto No. 192, publicado en el Periódico Oficial No. 10, de fecha 02 de marzo de 2018, Sección II, Tomo CXXV, expedido por la H. XXII Legislatura, siendo Gobernador Constitucional el C. Francisco Arturo Vega de Lamadrid 2013 - 2019.\nCAPÍTULO SEXTO\nSANCIONES\nArtículo 43.- Fue reformado por Decreto No. 192, publicado en el Periódico Oficial No.\n10, de fecha 02 de marzo de 2018, Sección II, Tomo CXXV, expedido por la H. XXII\nLegislatura, siendo Gobernador Constitucional el C. Francisco Arturo Vega de Lamadrid\n2013 - 2019.\nArtículo 44.- Fue adicionado por Decreto No. 192, publicado en el Periódico Oficial\nNo. 10, de fecha 02 de marzo de 2018, Sección II, Tomo CXXV, expedido por la H. XXII\nLegislatura, siendo Gobernador Constitucional el C. Francisco Arturo Vega de Lamadrid\n2013 - 2019.\nArtículo 45.- Fue adicionado por Decreto No. 192, publicado en el Periódico Oficial\nNo. 10, de fecha 02 de marzo de 2018, Sección II, Tomo CXXV, expedido por la H. XXII\nLegislatura, siendo Gobernador Constitucional el C. Francisco Arturo Vega de Lamadrid\n2013 - 2019.\nArtículo 46.- Fue adicionado por Decreto No. 192, publicado en el Periódico Oficial\nLegislatura, siendo Gobernador Constitucional el C. Francisco Arturo Vega de Lamadrid\n2013 - 2019.\nArtículo 47.- Fue adicionado por Decreto No. 192, publicado en el Periódico Oficial\nLey de Prevención, Tratamiento y Control de las Adicciones Página 15\n.\nActualización Legislativa.\nÚltima reforma P.O. No. 30, Número Especial, 13-May-2025\nLegislatura, siendo Gobernador Constitucional el C. Francisco Arturo Vega de Lamadrid\n2013 - 2019.\nArtículo 48.- Fue adicionado por Decreto No. 192, publicado en el Periódico Oficial\nNo. 10, de fecha 02 de marzo de 2018, Sección II, Tomo CXXV, expedido por la H. XXII\nLegislatura, siendo Gobernador Constitucional el C. Francisco Arturo Vega de Lamadrid\n2013 - 2019.\nArtículo 49.- Fue adicionado por Decreto No. 192, publicado en el Periódico Oficial\nNo. 10, de fecha 02 de marzo de 2018, Sección II, Tomo CXXV, expedido por la H. XXII\nLegislatura, siendo Gobernador Constitucional el C. Francisco Arturo Vega de Lamadrid\n2013 - 2019.\nArtículo 50.- Fue adicionado por Decreto No. 192, publicado en el Periódico Oficial\nLegislatura, siendo Gobernador Constitucional el C. Francisco Arturo Vega de Lamadrid\n2013 - 2019.\nArtículo 51.- Fue adicionado por Decreto No. 192, publicado en el Periódico Oficial\nLegislatura, siendo Gobernador Constitucional el C. Francisco Arturo Vega de Lamadrid\n2013 - 2019.\nLey de Prevención, Tratamiento y Control de las Adicciones Página 16\n.\nActualización Legislativa.\nÚltima reforma P.O. No. 30, Número Especial, 13-May-2025\nARTÍCULO ÚNICO TRANSITORIO DEL DECRETO No. 192, POR EL QUE SE\nAPRUEBA LA REFORMA AL ARTÍCULO 31 FRACCIÓN IV Y V, LA DENOMINACIÓN DEL\nCAPÍTULO QUINTO, ASÍ COMO LOS ARTÍCULOS 35, 36, 37, 38, 39, 40, 41, Y 42, Y SE\nADICIONA UN CAPÍTULO SEXTO DENOMINADO “SANCIONES” Y LOS ARTÍCULOS 43,\n44, 45, 46, 47, 48, 49, 50 Y 51; PUBLICADO EN EL PERIÓDICO OFICIAL No. 10, TOMO\nCXXV, SECCIÓN II, DE FECHA 02 DE MARZO DE 2018, EXPEDIDO POR LA H. XXII\nLEGISLATURA, SIENDO GOBERNADOR CONSTITUCIONAL EL C. FRANCISCO ARTURO\nVEGA DE LAMADRID 2013 – 2019.\nPRIMERO.- Las presentes reformas entrarán en vigor dentro de los noventas días siguientes al de su publicación en el Periódico Oficial del Estado.\nSEGUNDO.- Los Establecimientos que reciban subsidios o recursos públicos, en un plazo no mayor al de noventa días contados a partir de la publicación de las presentes reformas, deberán adecuar sus programas conforme a lo establecido en el presente Decreto.\nDADO en el Salón de Sesiones “Lic. Benito Juárez García” del H. Poder Legislativo del\nEstado de Baja California, en la Ciudad de Mexicali, B.C., a los veinticinco días del mes de enero del año dos mil dieciocho.\nDIP. MTRO. RAÚL CASTAÑEDA POMPOSO\nPRESIDENTE\n(RÚBRICA)\nDIP. ROCÍO LÓPEZ GOROSAVE\nSECRETARIA\n(RÚBRICA)\nDE CONFORMIDAD CON LO DISPUESTO POR LA FRACCIÓN I DEL ARTÍCULO 49 DE\nMEXICALI, BAJA CALIFORNIA, A LOS DOS DÍAS DEL MES DE MARZO DEL AÑO DOS\nMIL DIECIOCHO.\nFRANCISCO ARTURO VEGA DE LAMADRID\nGOBERNADOR DEL ESTADO\n(RÚBRICA)\nFRACNCISCO RUEDA GÓMEZ\nSECRETARIO GENERAL DE GOBIERNO\n(RÚBRICA)\nLey de Prevención, Tratamiento y Control de las Adicciones Página 17\n.\nActualización Legislativa.\nÚltima reforma P.O. No. 30, Número Especial, 13-May-2025\nARTÍCULO CUARTO TRANSITORIO DEL DECRETO No. 92, POR EL QUE SE\nAPRUEBA LA REFORMA AL ARTÍCULO 31; PUBLICADO EN EL PERIÓDICO OFICIAL No.\n30, NÚMERO ESPECIAL, DE FECHA 13 DE MAYO DE 2025, TOMO CXXXII; EXPEDIDO\nPOR LA H. XXV LEGISLATURA, SIENDO GOBERNADORA CONSTITUCIONAL LA C.\nMARINA DEL PILAR ÁVILA OLMEDA 2021-2027.\nARTÍCULO TRANSITORIO\nÚNICO.- Las presentes reformas entrarán en vigor, al día siguiente de su publicación en el\nPeriódico Oficial del Estado.\nDADO en Sesión Ordinaria de la XXV Legislatura en la Ciudad de Mexicali, B.C., a los ocho días del mes de mayo del año dos mil veinticinco.\nDIP. MICHELLE ALEJANDRA TEJEDA MEDINA\nPRESIDENTA\n(RÚBRICA)\nDIP. NORMA ANGELICA PEÑALOZA ESCOBEDO\nSECRETARIA\n(RÚBRICA)\nDE CONFORMIDAD CON LO DISPUESTO POR LA FRACCIÓN I DEL ARTÍCULO 49 DE\nCALIFORNIA, IMPRÍMASE Y PUBLÍQUESE.\nMEXICALI, BAJA CALIFORNIA, A LOS 09 DÍAS DEL MES DE MAYO DEL AÑO DOS MIL\nVEINTICINCO.\nMARINA DEL PILAR ÁVILA OLMEDA\nGOBERNADORA DEL ESTADO\nDE BAJA CALIFORNIA\n(RÚBRICA)\nALFREDO ÁLVAREZ CÁRDENAS\nSECRETARIO GENERAL DE GOBIERNO\nDEL ESTADO DE BAJA CALIFORNIA\n(RÚBRICA)\nLey de Prevención, Tratamiento y Control de las Adicciones Página 18",
  "ordenamiento": "REGLAMENTO",
  "jurisdiccion": "BAJA CALIFORNIA",
  "fuente_oficial": "Periódico Oficial",
  "FECHA PER OFIC": "2025/05/13",
  "ESTATUS": "VIGENTE",
  "TOMO": "TOMO_VI",
  "URL": "https://www.congresobc.gob.mx/Documentos/ProcesoParlamentario/Leyes/TOMO_VI/20250513_LEYPREVADICCIONES.PDF",
  "es_escaneado": false,
  "tiene_tablas": false,
  "materia": [
    "social",
    "salud",
    "educación",
    "cultura"
  ]
}