{
  "titulo": "Ley DE INGRESOS DEL MUNICIPIO DE SAN QUINTÍN, BAJA CALIFORNIA, PARA EL EJERCICIO FISCAL DEL 2025",
  "Contenido": "BAJA CALIFORNIA, EN USO DE LAS FACULTADES QUE LE CONFIERE EL ARTÍCULO\nLEY DE INGRESOS DEL MUNICIPIO DE SAN QUINTÍN, BAJA CALIFORNIA,\nPARA EL EJERCICIO FISCAL DEL 2025\nÍNDICE GENERAL\nTÍTULO PRIMERO GENERALIDADES.\nTÍTULO SEGUNDO IMPUESTOS.\nIMPUESTOS SOBRE EL PATRIMONIO.\nCAPÍTULO I IMPUESTO PREDIAL.\nCAPÍTULO II IMPUESTO SOBRE ADQUISICIÓN DE INMUEBLES.\nIMPUESTOS SOBRE LA PRODUCCIÓN, EL CONSUMO Y LAS\nTRANSACCIONES.\nY ESPECTÁCULOS PÚBLICOS.\nANTERIORES PENDIENTES DE LIQUIDACIÓN O PAGO.\nOTROS IMPUESTOS.\nLAS VÍAS PÚBLICAS.\nACCESORIOS DE IMPUESTOS.\nTÍTULO TERCERO DERECHOS.\nCAPÍTULO I DERECHOS POR SERVICIO DE ALUMBRADO PÚBLICO.\nAYUNTAMIENTO DE SAN QUINTÍN, BAJA CALIFORNIA.\n1.- DERECHOS POR SERVICIOS QUE PRESTA EL\nREGISTRO CIVIL.\n2.- DERECHOS QUE PRESTA LA DIRECCIÓN DE\nCOMERCIO, ALCOHOLES Y ESPECTÁCULOS PÚBLICOS.\nSOCIAL, A TRAVÉS DE:\n1.- COORDINACIÓN SERVICIOS MÉDICOS MUNICIPALES.\nCAPÍTULO V SERVICIOS QUE PRESTA LA DIRECCIÓN DE\nADMINISTRACIÓN URBANA Y SUS COORDINACIONES.\nCERTIFICADO DE MEJORAMIENTO DE LA IMAGEN URBANA.\nESTACIONAMIENTO DE VEHÍCULOS EN VÍA PÚBLICA.\nCAPÍTULO VI SERVICIOS QUE PRESTA LA COORDINACIÓN DE\nINFRAESTRUCTURA.\nPÚBLICOS, A TRAVÉS DE:\n1.- SERVICIOS QUE PRESTA EL DEPARTAMENTO DE\nMANTENIMIENTO DE BIENES MUNICIPALES, PARQUES,\nJARDINES, ÁREAS VERDES Y PANTEONES.\n2.- SERVICIOS QUE PRESTA LA COORDINACIÓN DE\nSERVICIOS PÚBLICOS (RASTRO).\n3.- SERVICIOS QUE PRESTA EL DEPARTAMENTO DE\nRECOLECCIÓN DE BASURA Y LIMPIA.\nSEGURIDAD PÚBLICA, PROTECCIÓN CIVIL, Y BOMBEROS\nA TRAVÉS DE:\n1.- SERVICIOS QUE PRESTA LA COORDINACIÓN DE\nPOLICÍA Y TRÁNSITO:\nALMACENAJE DE VEHÍCULOS.\n2.- SERVICIOS DE VIGILANCIA POLICÍACA.\n3.- SERVICIOS QUE PRESTAN LAS DIRECCIONES DE\nPROTECCIÓN CIVIL Y DE BOMBEROS.\nDE SAN QUINTÍN, BAJA CALIFORNIA.\n1.- SERVICIOS PRESTADOS EN LA DIRECCIÓN DE\nADMINISTRACIÓN URBANA.\n2.- SERVICIOS PRESTADOS POR LA DIRECCIÓN DE\nBIENESTAR SOCIAL.\n3.- SERVICIOS PRESTADOS EN LA COORDINACIÓN DE\nEDUCACIÓN Y CULTURA.\n4.- OTROS SERVICIOS PRESTADOS EN LA DIRECCIÓN DE\nADMINISTRACIÓN URBANA.\n5.-SERVICIOS PRESTADOS EN LA DIRECCIÓN DE\nDEPORTE.\n6.-OTROS SERVICIOS.\nCAPÍTULO X EXPEDICIÓN DE CERTIFICADOS, TÍTULOS,\nCONSTANCIAS O COPIAS DE DOCUMENTOS.\nACCESORIOS DE DERECHOS.\nANTERIORES PENDIENTES DE LIQUIDACIÓN O PAGO.\nTÍTULO CUARTO PRODUCTOS.\n1.- CONTRAPRESTACIÓN DE CONCESIONES, EXPLOTACIÓN O ARRENDAMIENTO DE BIENES MUEBLES E\nINMUEBLES PROPIEDAD DEL GOBIERNO MUNICIPAL.\n2.- OTRAS ACTIVIDADES DEL AYUNTAMIENTO DE SAN\nQUINTÍN BAJA CALIFORNIA, QUE NO CORRESPONDAN A\nSUS FUNCIONES PROPIAS DE DERECHO PÚBLICO.\n3.- SUMINISTRO DE FORMAS DIVERSAS PARA\nTRÁMITES ADMINISTRATIVOS.\n4.- DEL PISO.\n5.- BIENES MOSTRENCOS.\n6.- LOS PRODUCTOS DE LA GACETA MUNICIPAL.\n7.- ENAJENACIÓN DE BIENES MUEBLES E INMUEBLES\nPROPIEDAD DEL GOBIERNO MUNICIPAL.\n8.- ORGANISMOS DESCENTRALIZADOS, PARAMUNICIPALES Y/O FIDEICOMISOS.\n9.- OTROS.\n10.- PRODUCTOS NO COMPRENDIDOS EN LAS FRACCIONES\nEN LA LEY DE INGRESOS CAUSADOS EN EJERCICIOS\nPAGO.\n11.- PRODUCTOS FINANCIEROS DE LAS CUENTAS\nSAN QUINTÍN, BAJA CALIFORNIA.\nTÍTULO QUINTO APROVECHAMIENTOS.\n1.- RECARGOS.\n2.- GASTOS DE EJECUCIÓN.\n3.- MULTAS.\n4.- VENTA DE SUBPRODUCTOS.\n5.- REINTEGROS E INDEMNIZACIONES.\n6.- DONACIONES, CESIONES, HERENCIAS Y LEGADOS\nA FAVOR DEL MUNICIPIO.\n7.- OTORGAMIENTO Y USUFRUCTO DE DERECHOS.\n8.- RECUPERACIÓN PARCIAL DE PRIMAS DE SEGUROS DE\nVIDA.\n9.- CAUCIONES DE FIANZAS Y DEPÓSITOS CUYA\nPÉRDIDA SE DECLARE POR RESOLUCIÓN FIRME.\n10.- SUBSIDIOS QUE OTORGUE EL GOBIERNO DEL\nESTADO.\n11.- SUBSIDIOS QUE OTORGUE EL GOBIERNO FEDERAL.\n12.- APROVECHAMIENTOS NO COMPRENDIDOS EN LAS\nFRACCIONES DE LA LEY DE INGRESOS CAUSADAS EN\nEJERCICIOS FISCALES ANTERIORES PENDIENTES DE\nLIQUIDACIÓN O PAGO.\nTÍTULO SEXTO PARTICIPACIONES, APORTACIONES, CONVENIOS,\nY FONDOS DISTINTOS DE APORTACIONES.\nPARTICIPACIONES.\n1.- PARTICIPACIONES EN IMPUESTOS FEDERALES.\n2.- PARTICIPACIONES EN IMPUESTOS ESTATALES.\n3.- APORTACIONES.\nPROGRAMAS ESPECIALES, INCLUYENDO LAS QUE TENGAN\nPARTICIPACIÓN LAS PARAMUNICIPALES.\nb).- APORTACIONES RAMO 33.\nFONDO PARA LA INFRAESTRUCTURA SOCIAL MUNICIPAL.\nFONDO PARA EL FORTALECIMIENTO DE LOS MUNICIPIOS.\n1).- CONVENIOS.\n2).- INCENTIVOS DERIVADOS DE LA COLABORACIÓN\nFISCAL.\nTÍTULO SÉPTIMO EXTRAORDINARIOS.\n1).- CRÉDITOS OTORGADOS AL MUNICIPIO.\n2).- APORTACIONES EXTRAORDINARIAS ESTATALES Y\nFEDERALES.\n3).- OTROS.\nCAPÍTULO ÚNICO DISPOSICIONES GENERALES.\nTRANSITORIOS\nTÍTULO PRIMERO\nGENERALIDADES\nARTÍCULO 1.- Las contribuciones que se prevén en esta Ley tendrán\nMunicipio de San Quintín, Baja California, creado mediante Decreto\nNúmero 46 publicado en el Periódico Oficial del Estado de Baja que habrá de percibir dicho Municipio, durante el ejercicio fiscal\n2025.\nARTÍCULO 2.- Para los efectos de esta Ley, el ejercicio fiscal será\nARTICULO 3.- Las contribuciones que se establecen en esta Ley para el ejercicio fiscal 2025, se actualizarán al cumplirse los supuestos, condiciones y demás requisitos que se establezcan para ello, cumpliéndose con las formas, procedimientos y demás formalidades que respecto; y conforme a los costos y tarifas que se determinen para ello.\nARTICULO 4.- Para los efectos de esta Ley, y para otorgar certeza, seguridad, objetividad y continuidad a las obligaciones y servicios que se comprenden en la misma, se deberán tomar como válidos todos los actos que hubieren sido emitidos con anterioridad y en ejercicio de sus atribuciones, por las autoridades del Municipio de San Quintín, Baja California. En el entendido de que dichos actos se hubieren ajustado al marco legal que los rige.\nARTÍCULO 5.- Los ingresos que habrán de percibirse por el Municipio de San Quintín, Baja California, durante el ejercicio fiscal 2025, serán los que se obtengan por los siguientes conceptos:\n1.- IMPUESTOS. $40,337,710.23\nIMPUESTOS SOBRE EL PATRIMONIO.\n1.1 IMPUESTO PREDIAL. $14,554,410.96\n1.2 IMPUESTO SOBRE ADQUISICIÓN DE $8,398,250.95\nINMUEBLES.\nIMPUESTOS SOBRE LA PRODUCCIÓN, EL\nCONSUMO Y LAS TRANSACCIONES.\n1.3 IMPUESTO SOBRE ASISTENCIA A JUEGOS $750,000.00\nPERMITIDOS Y ESPECTÁCULOS PÚBLICOS.\nIMPUESTOS NO COMPRENDIDOS EN LAS $7,477,544.37\nFRACCIONES DE LA LEY DE INGRESOS\nCAUSADAS EN EJERCICIOS FISCALES\nANTERIORES PENDIENTES DE LIQUIDACIÓN\nO PAGO.\nOTROS IMPUESTOS.\nIMPUESTO PARA EL MANTENIMIENTO Y $6,884,404.22\nCONSERVACIÓN DE LAS VÍAS PÚBLICAS.\n1.4 ACCESORIOS DE IMPUESTOS. $2,273,099.73\n2.- DERECHOS. $59,473,913.77\n2.1 DERECHOS POR SERVICIO DE ALUMBRADO $14,261,061.03\nPÚBLICO.\n2.2 DERECHOS POR SERVICIOS QUE PRESTA EL\nAYUNTAMIENTO DE SAN QUINTÍN, BAJA\nCALIFORNIA.\n2.2.1 DERECHOS POR SERVICIOS QUE PRESTA EL $4,774,090.65\nREGISTRO CIVIL.\n2.3 DERECHOS QUE PRESTA LA DIRECCIÓN DE $14,243,094.37\nCOMERCIO, ALCOHOLES Y ESPECTÁCULOS\nPÚBLICOS.\n1.- RECEPCIÓN, ANÁLISIS Y REVISIÓN DE\nSOLICITUDES, DE EMISIÓN DE\nDOCUMENTOS, PERMISOS Y CERTIFICADOS\nREFERENTES A INSTALACIONES PARA LA\nVENTA, ALMACENAJE O CONSUMO DE BEBIDAS\nCON GRADUACIÓN ALCOHÓLICA,\nAMPLIACIÓN, CAMBIO DE GIRO, CAMBIO DE\nPERMISIONARIO, CAMBIO DE DOMICILIO,\nCAMBIO DE NOMBRE COMERCIAL Y\nTRAMITACIÓN RELATIVA A LA OPERACIÓN DE\nGIROS DE CERVEZA, VINOS, LICORES,\nALCOHOLES Y SIMILARES.\n2.- RECEPCIÓN, ANÁLISIS Y REVISIÓN DE\nDOCUMENTOS Y POR LA AUTORIZACIÓN PARA\nLA INSTALACIÓN Y EXPLOTACIÓN DE\nAPARATOS DE SONIDO, ELECTRÓNICOS,\nMECÁNICOS, ELECTROMECÁNICOS,\nVIDEOJUEGOS Y SIMILARES.\n3.- CENTROS DE APUESTAS, APUESTAS\nREMOTAS, SALAS DE SORTEOS DE NÚMEROS\nY/O CASINOS.\n4.- RECEPCIÓN Y ANÁLISIS DE DOCUMENTOS\nY EXPEDICIÓN DE PERMISOS REFERENTES A\nLA REALIZACIÓN DE ESPECTÁCULOS\nPÚBLICOS Y EVENTOS DE DIVERSIÓN.\n5.- RECEPCIÓN Y ANÁLISIS DE DOCUMENTOS\nREFERENTES A LA INSTALACIÓN DE\nAPARATOS MUSICALES (SINFONOLAS).\n6.- EXPEDICIÓN DE PERMISOS PARA EL\nEJERCICIO DEL COMERCIO EN LA VÍA\nPÚBLICA POR COMERCIANTES AMBULANTES,\nO CON PUESTOS FIJOS O SEMIFIJOS.\n7.- ARRENDAMIENTO DE ESPACIOS EN\nPARQUES, PLAYAS, JARDINES Y PLAZAS\nDESTINADAS AL ESPARCIMIENTO.\n2.4 SERVICIO QUE PRESTA LA UNIDAD $0.00\nMUNICIPAL DE TRANSPARENCIA Y ACCESO A\nLA INFORMACIÓN.\n2.5 SERVICIOS QUE PRESTA LA DIRECCIÓN DE $279,598.68\nBIENESTAR SOCIAL, A TRAVÉS DE LA\nCOORDINACIÓN DE SERVICIOS MÉDICOS\nMUNICIPALES.\n2.6 SERVICIOS QUE SE PRESTAN DE LA $1,865,598.80\nCOORDINACIÓN DE CATASTRO.\nCERTIFICADO DE MEJORAMIENTO DE LA\nIMAGEN URBANA.\n2.6.1 ESTACIONAMIENTO DE VEHÍCULOS EN LA VÍA $29,433.00\nPÚBLICA.\n2.7 SERVICIOS QUE PRESTA LA COORDINACIÓN $470,165.94\nDE INFRAESTRUCTURA.\n2.8 SERVICIOS QUE PRESTA LA COORDINACIÓN\nDE SERVICIOS PÚBLICOS, A TRAVÉS DE:\n2.8.1 SERVICIOS QUE PRESTA EL $202,438.67\nDEPARTAMENTO DE MANTENIMIENTO DE\nBIENES MUNICIPALES, PARQUES,\nJARDINES, ÁREAS VERDES Y PANTEONES.\n2.8.2 SERVICIOS QUE PRESTA LA COORDINACIÓN DE $11,953.13\nSERVICIOS PÚBLICOS (RASTRO).\n2.8.3 SERVICIOS QUE PRESTA EL DEPARTAMENTO DE $0.00\nRECOLECCIÓN DE BASURA Y LIMPIA.\n2.9 SERVICIOS QUE PRESTAN LAS DIRECCIONES\nDE SEGURIDAD PÚBLICA, PROTECCIÓN\nCIVIL Y BOMBEROS A TRAVÉS DE:\n2.9.1 SERVICIOS QUE PRESTA LA COORDINACIÓN\nDE POLICÍA Y TRÁNSITO. $425,850.82\n2.9.2 SERVICIOS DE VIGILANCIA POLICÍACA $29,591.53\n2.9.3 ALMACENAJE DE VEHÍCULOS.\n2.9.4 SERVICIOS QUE PRESTA PROTECCIÓN\nCIVIL. $2,559,318.98\n2.9.5 SERVICIOS QUE PRESTA BOMBEROS. $2,700,692.45\n2.10 OTROS SERVICIOS QUE PRESTA EL\nAYUNTAMIENTO DE SAN QUITÍN, BAJA\nCALIFORNIA.\n2.10.1 SERVICIOS DE DESARROLLO URBANO. $13,823,597.55\n2.10.2 SERVICIOS PRESTADOS POR LA DIRECCIÓN $302,228.87\nDE BIENESTAR SOCIAL.\n2.10.3 SERVICIOS PRESTADOS EN LA $720.91\nCOORDINACIÓN DE EDUCACIÓN Y CULTURA.\n2.10.4 SERVICIOS TURÍSTICOS. $8,934.99\n2.10.5 OTROS SERVICIOS PRESTADOS EN LA\nDIRECCIÓN DE ADMINISTRACIÓN URBANA.\n2.10.6 SERVICIOS PRESTADOS EN LA DIRECCIÓN DE $398.18\nDEPORTE.\n2.10.7 OTROS SERVICIOS. $0.00\n2.10.8 EXPEDICIÓN DE CERTIFICADOS, TÍTULOS,\nCONSTANCIAS O COPIAS DE DOCUMENTOS. $436,005.67\n2.10.9 GASTOS DE INTERVENCIÓN EN $49,442.95\nESPECTÁCULOS PÚBLICOS.\n3.- ACCESORIOS DE DERECHOS. $2,999,696.60\nDERECHOS NO COMPRENDIDOS EN LAS $0.00\nFRACCIONES DE LA LEY DE INGRESOS\nCAUSADAS EN EJERCICIOS FISCALES\nANTERIORES PENDIENTES DE LIQUIDACIÓN\nO PAGO.\n4.- PRODUCTOS $49,875.59\n1.- CONTRAPRESTACIÓN DE CONCESIONES, $0.00\nEXPLOTACIÓN O ARRENDAMIENTO DE BIENES\nMUEBLES E INMUEBLES PROPIEDAD DEL\nGOBIERNO MUNICIPAL.\n2.- OTRAS ACTIVIDADES DEL AYUNTAMIENTO DE\nSAN QUINTÍN, QUE NO CORRESPONDAN A\nSUS FUNCIONES PROPIAS DEL DERECHO\nPÚBLICO.\n3.- SUMINISTRO DE FORMAS DIVERSAS PARA $0.00\nTRÁMITES ADMINISTRATIVOS.\n4.- DEL PISO. $0.00\n5.- BIENES MOSTRENCOS. $0.00\n6.- LOS PRODUCTOS DE LA GACETA MUNICIPAL. $0.00\n7.- ENAJENACIÓN DE BIENES MUEBLES E $0.00\nINMUEBLES PROPIEDAD DEL GOBIERNO\nMUNICIPAL.\n8.- ORGANISMOS DESCENTRALIZADOS, $0.00\nPARAMUNICIPALES Y/O FIDEICOMISOS.\n9.- OTROS. $0.00\n10.- PRODUCTOS NO COMPRENDIDOS EN LAS $0.00\nFRACCIONES EN LA LEY DE INGRESOS\nCAUSADOS EN EJERCICIOS FISCALES\nANTERIORES PENDIENTES DE LIQUIDACIÓN\nO PAGO.\n11.- PRODUCTOS FINANCIEROS DE LAS CUENTAS $49,875.59\nBANCARIAS ADMINISTRADAS POR EL\nAYUNTAMIENTO DE SAN QUINTÍN, BAJA\nCALIFORNIA.\n5.- APROVECHAMIENTOS. $8,672,455.13\n1.- RECARGOS. $13,820.65\n2.- GASTOS DE EJECUCIÓN. $0.00\n3.- MULTAS. $8,585,540.34\n4.- VENTA DE SUBPRODUCTOS. $0.00\n5.- REINTEGROS E INDEMNIZACIONES. $55,440.62\n6.- DONACIONES, CESIONES, HERENCIAS Y $17,653.52\nLEGADOS A FAVOR DEL MUNICIPIO.\n7.- OTORGAMIENTO Y USUFRUCTO DE DERECHOS. $0.00\n8.- RECUPERACIÓN PARCIAL DE PRIMAS DE $0.00\nSEGUROS DE VIDA.\n9.- CAUCIONES DE FIANZAS Y DEPÓSITOS CUYA $0.00\nPÉRDIDA SE DECLARE POR RESOLUCIÓN\nFIRME.\n10.- SUBSIDIOS QUE OTORGUE EL GOBIERNO DEL $0.00\nESTADO.\n11.- SUBSIDIOS QUE OTORGUE EL GOBIERNO $0.00\nFEDERAL.\n12.- APROVECHAMIENTOS NO COMPRENDIDOS EN $0.00\nLAS FRACCIONES DE LA LEY DE INGRESOS\nCAUSADOS EN EJERCICIOS FISCALES\nANTERIORES PENDIENTES DE LIQUIDACIÓN\nO PAGO.\n6.- PARTICIPACIONES, APORTACIONES, $332,230,779.53\nCONVENIOS, INCENTIVOS DERIVADOS DE LA\nCOLABORACIÓN FISCAL Y FONDOS\nDISTINTOS DE APORTACIONES.\n6.1 PARTICIPACIONES.\n6.1.1 PARTICIPACIONES EN IMPUESTOS $118,500,747.93\nFEDERALES.\n6.1.2 PARTICIPACIONES EN IMPUESTOS $21,151,802.40\nESTATALES.\nAPORTACIONES.\na).- APORTACIONES DEL GOBIERNO DEL\nESTADO O DE LA FEDERACIÓN PARA OBRAS\nY SERVICIOS PÚBLICOS O PROGRAMAS\nESPECIALES, INCLUYENDO LAS QUE TENGAN\nPARTICIPACIÓN LAS PARAMUNICIPALES.\n6.2 APORTACIONES RAMO 33.\n6.2.1 FONDO PARA LA INFRAESTRUCTURA SOCIAL $76,670,497.32\nMUNICIPAL.\n6.2.2 FONDO PARA EL FORTALECIMIENTO DE LOS $109,646,847.62\nMUNICIPIOS.\n6.3 CONVENIOS. $161,169.00\n6.4 INCENTIVOS DERIVADOS DE LA $6,099,715.26\nCOLABORACIÓN FISCAL.\n7.- EXTRAORDINARIOS. $0.00\n7.1 CRÉDITOS OTORGADOS AL MUNICIPIO. $0.00\n7.2 APORTACIONES EXTRAORDINARIAS $0.00\nESTATALES Y FEDERALES.\n7.3 OTROS. $0.00\nARTÍCULO 6.- El Ayuntamiento de San Quintín, Baja California a través contribuciones, de acuerdo al procedimiento que establece el para el municipio de Ensenada, Baja California haciendo reducciones en el pago de Impuestos y/o Derechos, cuando los estímulos vayan de nuevos empleos, contratando personas con discapacidad, así como disposiciones aplicables.\nTÍTULO SEGUNDO\nIMPUESTOS\nCAPÍTULO I\nIMPUESTO PREDIAL\nARTÍCULO 7.- El Impuesto Predial, se causará de acuerdo a lo que se establece en la Ley de Hacienda Municipal y Ley del Catastro\nInmobiliario, ambas del Estado de Baja California, así como en el\nReglamento del Catastro Inmobiliario para el Municipio de Ensenada, Baja California, de conformidad con la Tabla de Valores Catastrales\nUnitarios, elaborada por el Consejo Municipal del Catastro\nInmobiliario de San Quintín, Baja California, y aprobada por el\nCongreso del Estado para el Municipio de San Quintín, Baja\nCalifornia.\nEl monto del Impuesto Predial se determinará multiplicando el valor catastral unitario por el número de metros cuadrados que corresponda a la superficie de cada predio, aplicándole al resultado las siguientes:\n1).- PREDIOS URBANOS Y SUB URBANOS\na).- Destinados total y exclusivamente para habitación: a.1).- De sus propietarios, clasificados como urbanos, sobre su valor catastral........................... 3.74 al millar a.2).- De sus propietarios, clasificados como sub urbanos, sobre su valor catastral........................... 3.74 al millar a.3).- De sus propietarios cuando éste sea habitado por el mismo siendo pensionado, persona con discapacidad, jubilados o personas mayores de sesenta años que acrediten su condición con identificación oficial expedida por Institución Pública, en predios clasificados como urbanos o sub urbanos, cuya superficie no sea mayor a 2,500 m², en la zona urbana y\n5,000 m² en las delegaciones, en propiedad única destinada a casa habitación, sobre su valor catastral........................... 3.74 al millar a.4).- De sus propietarios, clasificados como urbanos y sub urbanos cuando éstos se ubiquen en asentamientos irregulares y que se encuentren en proceso de regularización por organismo oficial, federal o estatal siempre que estén destinados total y exclusivamente para habitación de sus propietarios previa opinión favorable de los organismos, pagarán 1.84 al millar o 5.00 Unidad de Medida y\nActualización (UMA) vigente, o el que resulte mayor. a.5).- De sus propietarios ubicados en las zonas urbanas de los ejidos o poblados rurales, destinados exclusivamente a casa habitación, sobre su valor catastral........................... 3.74 al millar a.6).- De sus propietarios, cuando es habitado en zona turística, bajo los tipos de régimen en propiedad en condominio y/o fideicomiso bancario, sobre su valor catastral............ 6.31 al millar\nb).- Predios urbanos con uso mixto habitacional– comercial, donde el uso predominante del predio sea de casa habitación y cuyo uso comercial sea dedicado exclusivamente a un solo giro cuya superficie de construcción no sea mayor del 30% de la superficie del predio; sobre su valor catastral.................... 4.54 al millar\nc).- Predios destinados para su venta, propiedad que no hayan sido objeto de traslación de dominio, por un periodo de dos años a partir de su autorización, para su venta sobre su valor catastral............................. 1.87 al millar\nd).- Predios urbanos y sub urbanos destinados para programas habitacionales con fines sociales, promovidos por institución oficial, pagarán\n1.87 al millar o 5.00 UMA, o el que resulte mayor.\ne).- Predios urbanos no edificados, que se encuentran improductivos, o que se cuenten con construcciones en proceso, en receso o en estado ruinoso o que se cuenten con construcciones que sean de carácter provisional con materiales que sean de uso transitorio o puedan removerse fácilmente y además se encuentre improductivo, o cuyo valor no llegue al 50% del valor del terreno de agua, electricidad y drenaje; sobre su valor catastral............................. 8.40 al millar\nf).- Predios urbanos y sub urbanos ocupados por industria que sean propiedad de la empresa industrial, sobre su valor catastral........ 6.31 al millar\ng).- Predios urbanos y sub urbanos destinados exclusivamente al uso de comercio y de servicios: g.1).- Con uso comercial y de servicios en general comercial turístico y de oficinas; sobre su valor catastral.. 6.31 al millar g.2).- Predios ocupados por giros de comercio y servicio que emitan contaminantes al suelo, subsuelo y atmósfera, como polvo, ruido, etc.; como talleres mecánicos y de carrocería, tornos, gasolineras, carpinterías, de cambio y reciclaje de aceites y lubricantes, auto lavados, depósitos de gas, marmolerías, etc., sobre su valor catastral........................... 8.40 al millar g.3).- Con usos deportivos, recreativos o turísticos recreativos con o sin construcciones; sobre su valor catastral........................... 6.31 al millar g.4).- Predios ocupados por hoteles y moteles que sean propiedad de la empresa hotelera; sobre su valor catastral........................... 6.31 al millar\nh).- Predios urbanos y sub urbanos propiedad de asociaciones de profesionistas, sin fines de lucro, debidamente constituida conforme\nCódigo Civil para el Estado de Baja California y registradas ante el Departamento de profesiones en los términos establecidos por la Ley de Ejercicio de las Profesiones para el Estado de Baja California............... 4.54 al millar\ni).- Predios urbanos y sub urbanos propiedad de\nOrganizaciones, Asociaciones o Instituciones de Asistencia Social Privada, con fines de\nInterés Público, Humanitarios y no como\nAuxiliares de la Asistencia Social Privada, término “INSTITUCIÓN DE ASISTENCIA PRIVADA” o las siglas “I.A.P.”, debidamente constituidas\nCalifornia, y realizar la inscripción ante la autoridad municipal pagarán 5.00 UMA. De igual forma predios urbanos de agrupaciones pesqueras, debidamente constituidas, y registradas ante el Registro Público de la\nPropiedad y de Comercio, y realizar la inscripción ante la autoridad municipal, pagarán 5.00 UMA.\nj).- Predios urbanos y sub urbanos ocupados por o propiedad de instituciones de enseñanza que tengan autorización o reconocimiento de validez oficial de estudios en los términos de la Ley General de Educación............. 4.54 al millar\nk).- Predios urbanos y sub urbanos ocupados exclusivamente por instalaciones de infraestructura pública, sobre su valor catastral................................... 4.54 al millar\nl).- Predios urbanos y sub urbanos ocupados exclusivamente por servidumbre de paso formalmente constituidas de conformidad a lo establecido en el Código Civil del Estado de\nBaja California; sobre su valor catastral... 1.87 al millar\nm).- Predios urbanos y sub urbanos del dominio público y del dominio privado de la Federación y el Estado, siempre que los primeros se utilicen con propósitos distintos de los de su objeto social; sobre su valor catastral.. 4.54 al millar\nn).- Predios urbanos y sub urbanos de dominio público de la Federación, del Estado y del\nMunicipio que caigan en el caso de exención indicado en el artículo 115 Constitucional, así como en el Artículo 75 BIS “A” de la Ley de Hacienda Municipal para el Estado de Baja\nCalifornia.\no).- Predios sub urbanos sin uso; sobre su valor catastral................................... 8.40 al millar\np).- Predios urbanos destinados total o parcialmente a fines distintos señalados en los incisos anteriores, sobre su valor catastral................................... 6.31 al millar\nq).- Predios urbanos destinados total o parcialmente a fines distintos señalados en los incisos anteriores, sobre su valor catastral................................... 6.04 al millar\n2.- PREDIOS RÚSTICOS\na).- Predios en zona rural destinados total y exclusivamente habitación de sus propietarios y con superficie de hasta 5,000 m² (0.5 has); sobre su valor catastral.................... 3.74 al millar\nb).- Predios en zona rural, destinados total y exclusivamente para habitación de sus propietarios cuando éstos sean pensionados y jubilados o personas mayores de sesenta años que acrediten su condición con identificación oficial expedida por Institución Pública, destinadas a casa habitación con superficie de hasta 5,000 m² (0.5 has); sobre su valor catastral................................... 3.74 al millar\nc).- Predios en zona rural, ocupados por propiedad de instituciones de enseñanza que tengan autorización o reconocimiento de validez\nGeneral de Educación........................ 3.74 al millar\nd).- Predios rústicos de régimen privado y social\n(Ejidal), así como terrenos nacionales en uso y goce de particulares, dedicados a la actividad agropecuaria, pagarán el impuesto de acuerdo a lo dispuesto en el punto 3 de este Artículo.\ne).- Predios en zona rural, con usos deportivos, recreativos o turísticos recreativos con o sin construcciones y que no se contemplen en los casos descritos en el punto 4 de este\nArtículo; sobre su valor catastral.......... 6.31 al millar\nf).- Predios en zona rural y del dominio público de la Federación, del Estado y del Municipio en el Artículo 115 Constitucional, así como en el Artículo 75 BIS “A” de la Ley de\nHacienda Municipal para el Estado de Baja\nCalifornia.\ng).- Predios rústicos de régimen privado y social, así como terrenos nacionales en uso y goce de particulares, destinados total o parcialmente a fines distintos a los señalados en los incisos anteriores, y que no se contemplen en los casos descritos en el punto 4 de este\nArtículo; sobre su valor catastral.......... 6.04 al millar\n3.- TABLA DE COBRO DE PREDIAL PARA PREDIOS RURALES (AGROPECUARIOS\nCON USO COMERCIAL)\nPara la aplicación de la tasa o valor de un terreno rural, deberá ser considerado el tipo de clasificación del predio, pagándose el\nImpuesto Predial que resulte del cálculo de la superficie con actividad comercial incluyendo el área utilizada para estacionamiento; la superficie restante causará el impuesto.\nTratándose de predios rurales destinados a la producción agropecuaria, únicamente causarán el impuesto que corresponda de acuerdo con la siguiente tabla:\nA.- DE RIEGO, TEMPORAL Y AGOSTADERO:\n1.- Mayor de 0.50 hasta 10.00 Has........... 16.38\n2.- Mayor de 10.01 hasta 20.00 Has.......... 24.05\n3.- Mayor de 20.01 hasta 30.00 Has.......... 26.46\n4.- Mayor de 30.01 hasta 40.00 Has......... 29.11\n5.- Mayor de 40.01 hasta 50.00 Has.......... 32.01\n6.- Mayor de 50.01 hasta 75.00 Has......... 38.50\n7.- Mayor de 75.01 hasta 100.00 Has......... 48.12\n8.- Mayor de 100.01 hasta 150.00 Has........ 60.15\n9.- Mayor de 150.01 hasta 200.00 Has........ 75.19\n10.- Mayor de 200.01 Has..................... 93.99\n4.- PREDIOS RÚSTICOS CON COLINDANCIAS AL MAR\n4.1.- PORCIÓN PACÍFICO NORTE, corresponde desde paralelo 31 latitud norte Ejido Rubén Jaramillo, hasta el paralelo 28 latitud norte Villa Jesús María, zona costera de las delegaciones que corresponden: Camalú, Vicente Guerrero, San\nQuintín, Rosario, El Mármol, Punta Prieta y Villa de Jesús\nMaría es la zona costa del Pacífico del Municipio de San\nQuintín, Baja California.\nMECÁNICA DE DETERMINACIÓN DE VALOR\na).- La distancia frente al mar se multiplica por 100 metros cuando colinda con playa arenosa, 50 metros cuando colinda con acantilado que permita el acceso al mar y 25 metros cuando colinda con acantilado sin acceso al mar.\nb).- La superficie obtenida se multiplica por el valor unitario de zona turística rural, el cual será de $100.00 pesos por metro cuadrado.\nc).- El valor unitario mencionado en el punto anterior viene determinado por la letra \"T\", que constituye el tercer espacio de la clave catastral rural.\nd).- El valor obtenido se divide entre toda la superficie del predio y se obtiene el valor unitario promedio.\n4.2.- PORCIÓN PACÍFICO CENTRO, corresponde a la zona colindante con el Océano Pacífico, vértice de división entre Ejido San José de las Palomas y Ejido Revolución (Delegación del Mármol).\nMECÁNICA DE DETERMINACIÓN DE VALOR\na).- La distancia frente al mar se multiplica por 50 metros cuando colinda con playa arenosa, 25 metros cuando considerará como predio rústico sin valor fiscal, cuando colinda con acantilado sin acceso al mar.\nb).- La superficie obtenida se multiplica por el valor unitario de zona turística rural, el cual será de $25.00 pesos por metro cuadrado.\nc).- El valor unitario mencionado en el punto anterior viene determinado por la letra \"P\", que constituye el tercer espacio de la clave catastral rural.\nd).- El valor obtenido se divide entre toda la superficie del predio y se obtiene el valor unitario promedio.\n4.3.- PORCIÓN DEL GOLFO DE CALIFORNIA O MAR DE CORTEZ, corresponde\nCortez, comprende al Norte con el Paralelo 29.40 Norte, Delegación Bahía de los Ángeles, Islote Norte colindante con\nIsla Ángel de la Guarda, al Paralelo 28 Norte.\nMECÁNICA DE DETERMINACIÓN DE VALOR\na).- La distancia frente al mar se multiplica por 50 metros cuando colinda con playa arenosa, 25 metros cuando colinda con acantilado que permita el acceso al mar y se considerará como predio rústico sin valor fiscal, cuando colinda con acantilados sin acceso al mar.\nb).- La superficie obtenida se multiplica por el valor unitario de zona turística rural, el cual será de $25.00 pesos por metro cuadrado.\nc).- El valor unitario mencionado en el punto anterior viene determinado por las letras \"PA\", que constituye el tercer y cuarto espacio de la clave catastral rural.\nd).- El valor obtenido se divide entre toda la superficie del predio y se obtiene el valor unitario promedio. colindancia al mar, estarán a lo dispuesto para los predios rurales a que se refiere el punto 3 anterior.\n5.- ÁREAS VERDES Y DECRETADAS COMO DE PRESERVACIÓN ECOLÓGICA\nLas áreas verdes decretadas, así como los predios ubicados en áreas gubernamental pagarán 5.00 UMA, siempre y cuando en dichos predios los ecosistemas naturales. Las áreas decretadas, también quedarán exentas de este pago, siempre y cuando éstas hayan sido donadas con a los términos a que se refiere el segundo párrafo del inciso c) de la fracción IV del Artículo 115 de la Constitución Política de los\nEstado Unidos Mexicanos.\n6.- LOTES \"CABECEROS\" O CON INCIDENCIA A LA VIALIDAD\nLos valores de calle, parte de la base de los valores de mercado de las manzanas, para los lotes \"cabeceros\" o con incidencia a la vialidad se les aplicará un premio al valor de un 30% y los lotes encuentren dentro de zonas cuyo uso de suelo esté declarado como comercial se aplicará un premio del 35%. Esto se aplica solamente a las vialidades que en la Tabla de Valores Catastrales se tipifican como \"Vialidades con Valores Comerciales\". Se entenderá como lotes\n\"cabeceros\" los lotes con frente a una vialidad comercial.\nEl premio al valor a que se hace referencia en el párrafo que antecede no será aplicable a los lotes cuyo uso, sea exclusivamente de casahabitación.\nLos deméritos y/o castigos contemplados en la tabla de valores para efecto en el cálculo del impuesto predial, en ningún caso serán superiores del 35% en su totalidad con excepción aquellos que se vean afectados por utilidad pública.\n7.- PREDIOS DESTINADOS EXCLUSIVAMENTE A CASA HABITACIÓN fiscal 2025 correspondiente a predios destinados exclusivamente a casa habitación, que conforme a la aplicación de la fórmula para calcular el Impuesto y/o la adición de beneficio fiscal, resulte en el monto de cuota mínima, cubrirán el referido Impuesto aplicando la tarifa de 3.99 UMA.\nARTÍCULO 8.- La contribución por concepto del Impuesto Predial Anual, se regirá con base en la Tabla de Valores Catastrales Unitarios, aprobados por el Congreso del Estado, y no podrá ser menor a 5.00\nUnidad de Medida y Actualización (UMA) Vigente.\nLos predios urbanos, sub urbanos y rústicos destinados total sean: jubilados, pensionados o mayores de 60 años y que acrediten que habitan esa propiedad mediante identificación oficial, y cuyos predios tengan una superficie de hasta 2,500 metros en la zona urbana y sub urbana y hasta 5,000 metros en la zona rústica, recibirán un descuento del 50% siempre que el importe resultante no sea menor a\n5.00 UMA.\nAsimismo, los predios urbanos, sub urbanos y rústicos destinados estos sean:\nPersonas con discapacidad, personas que tengan a su cargo un familiar con alguna discapacidad y residan en el mismo domicilio y además se encuentren registradas como responsables en la credencial oficial con la que se acredite la discapacidad, viudas mayores de 50 años, y mujeres jefas de familias de escasos recursos, los cuales acrediten su condición con identificación expedida por institución pública y previo estudio socioeconómico pagarán el 50% del impuesto siempre que el importe resultante no sea menor a 5.00 UMA.\nEl Impuesto Predial deberá cubrirse dentro de los primeros tres meses del año; cuando el último día de vencimiento sea día inhábil se recorrerá al día siguiente hábil.\nARTÍCULO 9.- Los contribuyentes que opten por pagar el Impuesto\nPredial durante este periodo fiscal, y que no presenten adeudos en ejercicios fiscales anteriores, gozarán de un descuento del 12% en el mes de enero, 8% en el mes de febrero y 5% en el mes de marzo, del artículo anterior, siempre y cuando se cumpla con el pago total anual en una sola exhibición. obtendrá un descuento del 2% sobre el Impuesto Predial cuenta corriente sin accesorios, adicional a cualquier otro estímulo aplicado.\nLos propietarios de predios urbanos no edificados o baldíos, que expide la Dirección de Administración Urbana, gozarán de hasta un\n50% de descuento, en el pago del impuesto predial y su rezago, siempre anterior. El descuento que otorga el certificado podrá aplicarse en forma bimestral.\nLas bases del Certificado de Mejoramiento a la Imagen Urbana, se encuentran establecidas en el Artículo 34 de esta Ley.\nARTÍCULO 10.- Los contribuyentes que estén obligados a cubrir al\n(INFONAVIT), créditos hipotecarios que éste les hubiere otorgado, podrán pagar el Impuesto Predial por conducto del INFONAVIT, en los términos dispuestos en este Artículo y en su caso, por lo dispuesto en las disposiciones de carácter general que resulten aplicables, siempre y cuando el Municipio tenga celebrado convenio de colaboración con el INFONAVIT y a su vez los contribuyentes, en su carácter de derechohabientes del INFONAVIT, autoricen al citado\nInstituto para ordenar a su respectivo patrón, que realice los correspondientes descuentos a su salario y así mismo instruyan al propio INFONAVIT para realizar el pago del impuesto predial por orden y cuenta suya.\nAsimismo, los contribuyentes que cumplan con lo señalado en los siguientes párrafos del presente artículo y en las disposiciones de carácter general que en su caso emita el Ayuntamiento de San Quintín, Baja California para el efecto, podrán pagar el citado impuesto de manera cuatrimestral mediante la retención o descuento que lleven a para tal efecto por la autoridad fiscal.\nEn los supuestos anteriores, los pagos del impuesto predial se ejercicio fiscal de que se trate. El importe de cada pago la Ley de Hacienda Municipal del Estado de Baja California. Para los efectos de este artículo, el primero de los cuatrimestres iniciará con el primer mes del ejercicio fiscal.\nEn estos supuestos, los pagos corresponderá realizarlos a las instituciones o empresas señaladas en los párrafos anteriores, a más tardar el día 17 del mes inmediato posterior al cuatrimestre correspondiente; debiendo enterarlo a su vez a la Hacienda Municipal para estos efectos se tenga suscrito.\nLos contribuyentes que pretendan cumplir con su obligación de pago, anteriores, deberán manifestar a la Tesorería Municipal, tal intención, igualmente deberán presentar los avisos que se indican en las reglas de carácter general que en su caso emita la autoridad fiscal.\nCAPÍTULO II\nIMPUESTO SOBRE ADQUISICIÓN DE INMUEBLES\nARTÍCULO 11.- Es objeto de este impuesto, toda adquisición de inmuebles que se realice dentro del territorio del Municipio de San\nQuintín, Baja California, por cualquiera de los medios establecidos en la Ley de Hacienda Municipal del Estado de Baja California y la presente Ley.\nSon sujetos de este impuesto las personas físicas o morales que adquieran inmuebles consistentes en el suelo y las construcciones adheridas a él, incluyendo los accesorios y las instalaciones especiales que pertenezcan al inmueble, ubicados en el municipio; la adquisición de derechos reales o posesionarios sobre los bienes inmuebles, al igual que los contemplados en el artículo 75 BIS B, California. formas. se establece, sobre la base gravable que se determine de acuerdo a la Ley de Hacienda Municipal del Estado de Baja California.\nRango Monto Monto Cuota Tasa marginal inferior superior fija sobre\n(pesos) (pesos) (pesos) excedente\n1 0.01 300,000.00 2.00%\n2 300,000.01 700,000.00 6,000.00 2.25%\n3 700,000.01 1,400,000.00 15,000.00 2.50%\n4 1,400,000.01 2,600,000.00 32,500.00 3.00%\n5 2,600,000.01 3,800,000.00 68,500.00 3.50%\n6 3,800,000.01 5,200,000.00 110,500.00 4.00%\n7 5,200,000.01 6,800,000.00 166,500.00 4.50%\n8 6,800,000.01 8,600,000.00 238,500.00 5.00%\n9 8,600,000.01 10,600,000.00 328,500.00 5.50%\n10 10,600,000.01 En adelante 438,500.00 6.00%\nLas operaciones en moneda extranjera se cobrarán a su equivalente en moneda nacional.\nPara el cálculo de este impuesto, la base del mismo deberá ubicarse en el renglón que le corresponda de entre los montos del recuadro anterior, a la base se le disminuirá el monto inferior del rango que le corresponda y a la diferencia del excedente del monto inferior se le aplicará la tasa marginal que le corresponda; al resultado se le sumará la cuota fija del mismo rango y el importe de dicha operación será el impuesto sobre adquisición de inmuebles a pagar.\nLo anterior, conforme a la siguiente fórmula:\n((BI-MI)*T)+CF = Impuesto sobre adquisición de inmuebles a pagar.\nEn donde:\nBI= Base del Impuesto\nMI= Monto inferior correspondiente\nT= Tasa marginal sobre excedente del monto inferior correspondiente\nCF= Cuota Fija correspondiente\nLas Autoridades Fiscales Municipales podrán practicar, ordenar o tomar en cuenta el avalúo del inmueble, referido a la fecha de adquisición y cuando el valor que resulte de dicho avalúo, exceda en más de un 10% del precio pactado, éste no se tomará en cuenta, y el impuesto se calculará sobre el valor del avalúo, que al efecto diferencias del impuesto que resulte, mismo que no deberá ser menor\nSan Quintín, Baja California. de Medida y Actualización (UMA) Vigente, elevado al año, con las\nBaja California.\nSe aplicará a la base gravable la tasa 0%, cuando la adquisición sea por alguno de los siguientes supuestos:\na).- Por donación, herencia o legado entre cónyuges.\nb).- Por donación, herencia o legado que se realicen de padres a hijos o de hijos a padres;\nc).- En las operaciones en que los adquirentes sean asociaciones civiles, o asociaciones religiosas que no persigan fines de lucro, debidamente registradas en el Estado.\nd).- Por la adquisición de terrenos a través de títulos de propiedad, expedidos por el Registro Agrario Nacional que obtengan los ejidatarios.\nLa tasa del 0% no será aplicable cuando los donatarios, herederos o legatarios cedan sus derechos sobre los bienes gravables, y cuando los adquirentes a que se refiere el inciso d) cedan sus derechos a personas distintas a las que hacen alusión en dicho inciso\nLa tarifa establecida en el presente artículo será aplicable a partir del ejercicio fiscal 2025 para la determinación del impuesto sobre adquisición de inmuebles, respecto de los bienes inmuebles ubicados en el Municipio de San Quintín.\nPor lo tanto, cualquier disposición emitida con anterioridad que se\nMunicipio de San Quintín, en tanto se encuentre vigente la misma.\nPara la revisión y aceptación de este impuesto, el contribuyente deberá presentar la siguiente documentación legible:\n1.- Formato previamente llenado de la declaración de Impuesto\nSobre Adquisición de Inmuebles.\n2.- Contrato o sentencia donde se adquieren derechos reales o posesorios.\n3.- Identificación de las partes.\n4.- Avalúo vigente.\n5.- Libertad de gravamen con vigencia del ejercicio fiscal en curso.\n6.- Acta de nacimiento en caso del párrafo séptimo inciso b) de este artículo y en los casos del inciso a), deberá presentar bienes.\n(INDIVI) o con el Instituto Nacional del Suelo Sustentable (INSUS), y los que se realicen a través de cualquier dependencia oficial que promueva desarrollos habitacionales de interés social y popular, pagarán el equivalente de 4.00 UMA vigente siempre y cuando el predio sea destinado a casa habitación, y siempre que la suma de los predios adquiridos por una persona no superen los 250.00 M².\nEs obligación de las personas físicas o morales que enajenan inmuebles, el dar aviso dentro de los primeros 15 días hábiles después de la operación a la autoridad fiscal municipal.\nSerán responsables solidarios del Impuesto sobre Adquisición de\nInmuebles los notarios públicos y demás autoridades públicas a que se hacen referencia en la fracción IX del artículo 75 BIS B de la\nLey de Hacienda Municipal del Estado de Baja California, de las operaciones y actos por la que se causen los mismos cuando: autoricen actos o contratos de adquisición de propiedad de inmuebles o de derechos reales o posesorios, así como cuando inscriban o realicen anotaciones de escrituras, actos o contratos sin que el causante compruebe que se han cubierto estas contribuciones.\nLa responsabilidad solidaria, consiste en el pago del importe total los contribuyentes. jurídico al no ponerse al corriente en sus obligaciones fiscales, Inmuebles de conformidad con el artículo 89 fracción I, inciso l) de en el supuesto jurídico, misma que se cobrará con base en la siguiente tabla:\nAÑOS UMA\n1994 y anteriores 75.00\n1995-1998 70.00\n1999-2001 65.00\n2002-2004 60.00\n2005-2008 55.00\n2009-2011 50.00\n2012-2014 45.00\n2015-2018 40.00\n2019-2021 35.00\n2022-2023 30.00\n2024 25.00\nPARA EL EJERCICIO FISCAL 2025\nMESES UMA\n1 2.00\n2 4.00\n3 6.00\n4 8.00\n5 10.00\n6 12.00\n7 14.00\n8 16.00\n9 18.00\n10 20.00\n11 22.00\n12 24.00\nCAPÍTULO III\nPÚBLICOS\nARTÍCULO 12.- Es objeto de este impuesto, el ingreso bruto que se obtenga por la venta de boletos, pulseras, sellos o cualquier otro los que se obtenga dicho ingreso, y que pueden ser la realización de funciones de teatro, circo, lucha libre, boxeo, espectáculos deportivos, audiciones, eventos culturales, y espectáculos musicales de aparatos electromecánicos, mecánicos, electrónicos y otros similares accionados o no por monedas, que se realicen en el territorio del Municipio de San Quintín.\nARTÍCULO 13.- Tratándose de juegos permitidos, espectáculos públicos, centros de diversión y juegos mecánicos, se causará conforme a las siguientes:\nTASAS:\nI.- Espectáculos en que participen deportistas, músicos y actores no profesionales, así como los realizados por instituciones educativas y organizaciones que no persigan fines de lucro, sobre la cuota de admisión o por cada boleto vendido. El impuesto se causará sobre la cuota de admisión o por cada boleto vendido para el ingreso al espectáculo o diversión......................................... 2.5%\nII.- Tratándose de eventos realizados por partidos políticos; siempre y cuando se acredite fehacientemente a través de contrato o evento, que es organizado por el Partido Político, y no por una persona física o moral independiente, gravarán la tasa del impuesto del 5% sobre la cuota de admisión o por cada boleto vendido para el ingreso al espectáculo o diversión, se deberá presentar ante evento:\na) Acta constitutiva o instrumento de creación de a la institución que promueve el evento.\nb) Copia del contrato o contratos celebrados para su realización, en caso de que el evento se efectúe en un local que sea propio o de la institución u organismo que lo organiza, se deberá incluir copia del contrato de arrendamiento.\nc) Declaratoria firmada por el titular del área financiera del instituto u organismo organizador, en el cual se haga constar que el evento o espectáculo es para allegarse de recursos para el cumplimiento de sus fines, cuyos recursos están obligados acumular y acreditar a sus ingresos la autoridad municipal informará sobre el particular a la autoridad electoral correspondiente.\nIII.- Tratándose de obras de teatro, funciones de circo, espectáculos cómicos, taurinos, audiencias musicales, bailes, eventos de box y lucha, espectáculos públicos en los que participen deportistas profesionales, así como congresos, cursos, conferencias, talleres; por el ingreso bruto percibido, sobre la cuota de admisión o por cada boleto vendido para el ingreso al espectáculo o diversión......................................... 5%\nIV.- Tratándose de conciertos, otras diversiones y espectáculos públicos, sobre el ingreso bruto diversión......................................... 10% con base en lo siguiente:\n1.- Con respecto al otorgamiento de los permisos de espectáculos públicos, la Dirección de Comercio, Alcoholes y Espectáculos\nPúblicos, es la encargada de emitirlos.\n2.- En lo que refiere a la aprobación de la tasa del impuesto a documentación emitida y aprobada por la Dirección de Comercio, Alcoholes y Espectáculos Públicos. admisión o importe del consumo obligatorio (COVER).\nPara los efectos del cobro de este impuesto, sobre asistencia a juegos permitidos y espectáculos públicos, el organizador en su escrito de petición para la autorización del evento mencionará cuantos boletos de cortesía se otorgarán y éstos serán considerados como boletos vendidos, por ningún motivo se autorizarán boletos con un costo menor al ofertado al público.\nTratándose de espectáculos realizados por Organismos no lucrativos que brinden servicios y asistencia médica de manera gratuita a enfermos que padezcan cáncer en etapa terminal, debidamente registrados ante la Secretaría de Salud del Estado, gravarán este\nImpuesto a tasa cero.\nPara efecto de la aplicación de la tasa a que hace referencia el párrafo anterior, se deberá acreditar que el espectáculo público es realizado por el respectivo organismo no lucrativo en términos de las reglas de carácter general que emita la Dirección de Asuntos\nJurídicos a través de una Norma Técnica.\nArtículo 14.- Los permisionarios que, derivado de sus actividades de juegos con apuestas o sorteos, que otorguen premio en efectivo o de Gobernación o de una resolución judicial que haya causado estado, acuerdo a lo siguiente:\nA).- Para los organizadores de juegos con apuestas permitidas y/o habilidades o destrezas.............. 3.00% la participación o la apuesta, deduciéndose a dicha base gravable el valor del premio efectivamente pagado o entregado, así como la participantes. Las personas que realizan las actividades a que se refiere este Artículo, no causarán los Impuestos y Derechos contenidos en esta Ley relativos a las máquinas de juego, calcomanía por máquina, holograma por máquina o cualquier otro análogo; así como para la obtención de permisos, revalidación o licencia de operación del establecimiento de los mismos.\nARTÍCULO 15.- Los organizadores o empresarios de los espectáculos públicos, juegos permitidos, o centros de diversión, serán retenedores y solidarios responsables del pago del impuesto, debiéndolo enterar al Departamento de Recaudación, el día hábil siguiente al de la celebración del evento o bien en el momento de celebrarse éste, previa liquidación o comprobación del ingreso al interventor municipal en el caso que sea intervenido el evento.\nLos gastos de intervención se cobrarán con base en el monto del impuesto determinado para la realización del evento de conformidad a la siguiente tabla:\n1).- De 100.00 A 300.99............ 2.00 UMA\n2).- De 301.00 A 500.99............ 3.00 UMA\n3).- De 501.00 A 700.99............ 4.00 UMA\n4).- De 701.00 A 900.99............ 5.00 UMA\n5).- De 901.00 A 1,500.99............ 6.00 UMA\n6).- De 1,501.00 A 3,000.99............ 7.00 UMA\n7).- De 3,001.00 A 6,000.99............ 8.00 UMA\n8).- De 6,001.00 A 10,000.99............ 9.00 UMA\n9).- De 10,001.00 En Adelante............. 10.00 UMA\nCAPÍTULO IV\nLIQUIDACIÓN O PAGO.\nARTÍCULO 16.- Los impuestos no pagados en el ejercicio fiscal en que se causaron, se cobrarán como ingresos causados en ejercicios fiscales anteriores, pendientes de liquidación o pago, aplicando en cuanto al fondo, las Leyes vigentes a la fecha en que se generaron y en cuanto a la forma, mediante el procedimiento administrativo\nBaja California o en su caso, el procedimiento judicial que corresponda.\nCAPÍTULO V\nPÚBLICAS.\nARTÍCULO 17.- Son sujetos de este impuesto, los propietarios o poseedores de vehículos de motor, que residan dentro del territorio del Municipio de San Quintín, Baja California, para contribuir en el mantenimiento y conservación de las vías públicas municipales.\nEste impuesto se enterará al pagar el importe correspondiente a la expedición o revalidación de las placas de circulación, a través de la Recaudación de Rentas del Estado y/o ante el Instituto de\nMovilidad Sustentable (IMOS) o los equivalentes de estos, los cuales serán retenedores del mismo; sujetándose a la siguiente:\nACTUALIZACIÓN (UMA) VIGENTE\na).- Vehículos de uso particular........................ 4.50 UMA\nb).- Vehículos de transporte público de pasajeros....... 9.20 UMA\nc).- Camiones de uso particular......................... 10.00 UMA\nd).- Camiones de transporte público de pasajeros........ 13.00 UMA\ne).- Camiones de carga pesada........................... 20.00 UMA municipales.\nTÍTULO TERCERO\nDERECHOS\nCAPÍTULO I\nDERECHOS POR SERVICIO DE ALUMBRADO PÚBLICO\nARTÍCULO 18.- Es objeto de este derecho, la prestación del servicio de alumbrado público. Se entiende por servicio de alumbrado público, el servicio de iluminación, incluyendo su operación, ampliación, rehabilitación, reposición y mantenimiento, que las autoridades municipales otorgan en espacios públicos y vialidades como calles, avenidas, bulevares, caminos vecinales, plazas, parques, jardines y otros lugares de uso común del Municipio de San Quintín.\nSon sujetos de este derecho, los beneficiarios del servicio de alumbrado público a que se refiere el párrafo anterior, dentro de la circunscripción territorial del Municipio de San Quintín, Baja\nCalifornia con las excepciones dispuestas en este capítulo.\nEl derecho por Servicio de Alumbrado Público se causará mensualmente conforme a una cuota fija de $51.12 pesos (cincuenta y un pesos\n12/100 M.N.).\nARTÍCULO 19.- Este derecho se causará conforme a lo siguiente:\nLa base de este Derecho es el costo anual globalizado del servicio de alumbrado público erogado por el municipio, el cual incluye el consumo de energía eléctrica de las redes de alumbrado público del\nMunicipio, así como la ampliación, instalación, reparación, limpieza y mantenimiento del alumbrado público y luminarias, además de gastos administrativos, servicios contratados a terceros, sueldos y honorarios del personal directamente involucrado en la prestación del servicio; la cuota fija para el pago del Derecho por Servicio anual del ejercicio fiscal 2023 erogado por el Municipio en prestación de este servicio, actualizado por inflación y dividido entre el número de sujetos de este derecho. El cociente fue dividido entre 12 para determinar el monto mensual del derecho a pagar.\nSe entiende por costo anual actualizado del ejercicio fiscal 2023, Municipio en 2023, por el gasto directamente involucrado con la prestación de este servicio, traídos a valor presente tras la\n2024 entre el Índice Nacional de Precios al Consumidor\nARTÍCULO 20.- No estarán obligados al pago de este derecho los\nInmuebles de uso Público de las Entidades Federales, Estatales y\nMunicipales.\nARTÍCULO 21.- El pago deberá realizarse dentro de los primeros 10 días siguientes al mes en que se cause, en las oficinas recaudadoras tal efecto.\nEl citado plazo y lugar de pago, podrá modificarse o ampliarse en beneficio de los contribuyentes, cuando existan acuerdos entre el\nMunicipio con otras instancias públicas o privadas, que permitan simplificar el entero de la contribución. Para tal efecto, las instancias competentes del Municipio podrán celebrar convenios a través de los cuales se logre lo indicado con anterioridad.\nARTÍCULO 22.- Los ingresos que se perciban por el derecho establecido en esta sección, se destinarán prioritariamente al pago de conceptos que se requieran para el debido servicio, operación y mantenimiento del alumbrado público y luminarias que proporciona el Municipio, incluyendo su ampliación, instalación, reparación, servicios contratados a terceros, limpieza y renovación, así como en caso de los rubros de sueldos, gastos administrativos y honorarios relacionados con este servicio.\nCAPÍTULO II\nDERECHOS POR SERVICIOS QUE PRESTA EL AYUNTAMIENTO DE SAN QUINTÍN,\nBAJA CALIFORNIA\n1.- DERECHOS POR SERVICIOS QUE PRESTA EL REGISTRO CIVIL.\nARTÍCULO 23.- Los Derechos por servicios que preste el Registro\nCivil, serán pagados por el usuario sujetándose a la siguiente:\nUNIDAD DE MEDIDA Y ACTUALIZACIÓN (UMA) VIGENTE\nA.- NACIMIENTOS:\na).- Registro en horas hábiles dentro de la oficina, con anticipación de 8 días, previa cita.......... EXENTOS\nb).- Registro urgente en horas hábiles dentro de la oficina, menos de 7 días a 48 horas, previa cita y su valoración.................................... EXENTOS\nc).- Registro en hospitales, excepto en instituciones de Salud Pública los cuales estarán exentos.................. EXENTOS c.1).- Registro de nacimiento en centro de rehabilitación, ceresos, casas hogar, casas de retiro, tutelar de menores, registros de niños que realiza la Procuraduría para la\nDefensa del Menor y la Familia y otros.... EXENTOS\nd).- Registro de nacimientos hasta los 5 años.......... EXENTOS\ne).- Registro a domicilio, fuera de la mancha urbana con anticipación de 8 días, previa cita:\na).- En horas hábiles............................ EXENTOS\nb).- En horas inhábiles.......................... EXENTOS\nf).- Registro de nacimiento fuera del término de los 6 meses............................................ EXENTOS\ng).- Inscripción de registro de nacimientos ocurridos en territorio extranjero, en “campaña colectiva”........................................ EXENTOS\nh).- Inscripción de nacimientos de personas nacidas en el extranjero..................................... EXENTOS\ni).- Inscripción de nacimientos de personas nacidas fuera del Municipio, hasta los 5 años................... EXENTOS\nj).- Registro de nacimiento dentro del programa\n\"Jornadas del Registro Civil\", en horas inhábiles, dentro de la oficina............................. EXENTOS\nk).- Registro en Instituciones de Salud, en módulo de\nRegistro Civil, dentro de los quince días de nacido............................................ EXENTOS\nl).- Declaratoria de hechos, para registro de nacimientos extemporáneos en campaña.............. EXENTOS\nm).- Inscripción de nacimientos urgente, de personas nacidas en el extranjero será canalizado a la\nDirección de Bienestar Social para su valoración........................................ EXENTOS\nn).- Exentos de pago a registros extemporáneos de niños, que realiza la Procuraduría de Protección de Niñas, Niños y Adolescentes............................. EXENTOS\nB.- MATRIMONIOS:\na).- Celebración en horas hábiles dentro de la oficina, con anticipación de 8 días, previa cita........... 13.50 UMA\nb).- Celebración urgente, en horas hábiles dentro de la oficina, menos de 7 días a 48 horas, previa cita.. 24.98 UMA b.1).- Celebración de matrimonio extraordinario, en horas hábiles, con anticipación de 24 horas, previa cita............................... 40.50 UMA\nc).- Celebraciones en hospitales, excepto en instituciones de salud pública, los cuales estarán exentos.......................................... 12.15 UMA\nPara obtener exención del inciso c), deberán\nBienestar Social, la cual emitirá el estudio girará oficio al C. Oficial del Registro Civil, para exentar el pago de Derechos. c.1).- Celebración de matrimonio, de personas mayores de edad, a centro de rehabilitación, ceresos, casas hogar, casas de retiro, tutelar de menores y otros..... 4.05 UMA\nd).- Celebración en horas extraordinarias (sábado), dentro de la oficina, con anticipación de 8 días previa cita....................................... 20.25 UMA\ne).- Celebración ordinaria en horas inhábiles (sábado), dentro de la oficina, con anticipación de 7 días a\n48 horas, previa cita............................. 41.85 UMA e.1).- Celebración de matrimonio extraordinario, en horario inhábil (sábado) dentro de la oficina, con 24 horas de anticipación y previa cita............................... 57.38 UMA\nf).- Celebración a domicilio dentro de la Ciudad con anticipación de 8 días, previa cita:\na).- En horas hábiles............................ 54.00 UMA\nb).- En horas inhábiles.......................... 81.00 UMA\ng).- Celebración urgente a domicilio, dentro de la ciudad, con anticipación de 7 días a 48 horas, previa cita:\na).- En horas hábiles............................ 74.25 UMA\nb).- En horas inhábiles.......................... 94.50 UMA g.1).- Celebración de matrimonio extraordinario a domicilio, dentro de la ciudad, con anticipación de 24 horas, previa cita:\na).- En horas hábiles...................... 94.50 UMA\nb).- En horas inhábiles.................... 114.75 UMA\nh).- Celebración a domicilio, fuera de la mancha urbana, con anticipación de 8 días, previa cita:\na).- En horas hábiles............................ 74.25 UMA\nb).- En horas inhábiles.......................... 101.25 UMA h.1).- Celebración de matrimonio a domicilio, urgente fuera de la mancha urbana, con anticipación de 7 días a 48 horas previa cita:\na).- En horas hábiles...................... 87.75 UMA\nb).- En horas inhábiles.................... 108.00 UMA h.2).- Celebración de matrimonio a domicilio, extraordinario fuera de la mancha urbana, con anticipación de 24 horas, previa cita:\na).- En horas hábiles...................... 108.00 UMA\nb).- En horas inhábiles.................... 128.25 UMA h.3).- Celebración de matrimonio celebrado por la\nOficialía, en Delegaciones:\na).- Ordinario con anticipación de documentos recibidos, 7 días antes en la Oficialía......................... 141.75 UMA\nb).- Urgente con anticipación de documentos recibidos, 4 días antes en la Oficialía......................... 157.95 UMA\nc).- Extra urgente con anticipación de documentos, recibidos un día antes en la Oficialía......................... 172.80 UMA\ni).- Inscripción de matrimonio, celebrado fuera de la\nRepública........................................ 27.00 UMA i.1).- Inscripción de matrimonio extra urgente, celebrado fuera de la República............ 54.00 UMA\nj).- Registro o celebración de matrimonios, verificados dentro del programa de \"Matrimonios Colectivos\", en horas hábiles o inhábiles, dentro o fuera del domicilio de las oficinas....................... EXENTO\nk).- Solicitud y formato para certificados médicos prenupciales y celebración de matrimonio......... 2.03 UMA\nl).- Celebración de matrimonio dentro del programa de matrimonios colectivos........................... $1.00\nm).- Cambio de régimen matrimonial o modificación a las capitulaciones matrimoniales..................... 21.60 UMA\nn).- Inscripción de matrimonio urgente, celebrado fuera de la República Mexicana......................... 40.50 UMA ñ).- Pláticas prematrimoniales........................ 2.70 UMA\nC.- DEFUNCIONES:\na).- Registro en las oficinas en horas hábiles........ EXENTO\nb).- Registro en las oficinas en horas inhábiles...... 4.05 UMA\na).- Fuera de la oficina en horas inhábiles..... 6.08 UMA\nc).- Permiso de inhumaciones a panteones particulares en:\na).- En horas hábiles........................... 10.13 UMA\nb).- En horas inhábiles......................... 11.48 UMA\nd).- Inscripción de defunciones ocurridas fuera de la\nRepública........................................ 18.90 UMA\ne).- Permiso de cremación a panteones particulares en:\na).- En horas hábiles........................... 8.78 UMA\nb).- En horas inhábiles......................... 10.13 UMA\nf).- Permiso de inhumación de cenizas a panteones particulares en:\na).- En horas hábiles........................... 3.38 UMA\nb).- En horas inhábiles......................... 3.38 UMA\ng).- Expedición de orden de inhumación:\na).- Horas hábiles e inhábiles.................. 6.08 UMA\nh).- Registro de defunciones extemporáneas, ordenadas por el Ministerio Público o Autoridad Competente.. 6.08 UMA\ni).- Presunción de muerte............................. 27.00 UMA\nPara obtener exención de los incisos anteriores, deberán solicitarlo al área de Bienestar Social, el cual emitirá el estudio socioeconómico correspondiente y éste a su vez girará oficio al C.\nOficial del Registro Civil, para exentar el pago de Derechos.\nEn cumplimiento a la fracción VIII del artículo 63 de la Ley sobre\nDesaparición y Búsqueda de Personas para el Estado de Baja\nCalifornia, quedan exentas del pago de los derechos a que se refieren los incisos c).-, f).- y g).- de este Apartado, los familiares que soliciten estos servicios respecto de una persona que fuere objeto de búsqueda y localización en términos de dicha Ley, previa comprobación del parentesco.\nD.- DIVORCIOS:\na).- Divorcio administrativo por mutuo consentimiento, tramitado en oficina del Registro Civil.......... 54.00 UMA a.1).- Divorcio administrativo por mutuo consentimiento, tramitado en CERESO....... 76.95 UMA a.2).- Divorcio administrativo urgente (dentro de las 48 horas la primera cita), por mutuo consentimiento, tramitado en oficina de\nRegistro Civil............................ 60.75 UMA\nb).- Por registro de divorcio proveniente del juzgado.. 27.00 UMA b.1).- Campaña de inscripciones de divorcio proveniente del Juzgado dentro de la\nRepública................................. 20.25 UMA\nc).- Registro de divorcio urgente, proveniente del juzgado, (dentro del plazo de 48 horas).......... 54.00 UMA c.1).- Registro de divorcio extraordinario, proveniente del juzgado (dentro del plazo de 24 horas).............................. 67.50 UMA\nd).- Inscripción de divorcio efectuado fuera de la\nRepública, ordenado por el Juez competente....... 40.50 UMA\ne).- Proveniente de la defensoría de oficio, previa solicitud y constancia de estudio socioeconómico de la misma......................................... EXENTO\nf).- Inscripción de divorcio urgente, efectuado fuera de la República, por un Juez competente.......... 54.00 UMA\nE.- ADOPCIONES\na).- Registro........................................ 27.00 UMA a.1).- Registro extraordinario, dentro de las 48 horas..................................... 40.50 UMA\nb).- Inscripción de adopción, efectuado fuera de la\nRepública........................................ 33.75 UMA\nF.- EXPEDICIÓN DE ACTAS Y CERTIFICADOS:\na).- Servicio ordinario............................... 2.03 UMA\nLa solicitud es de 8:00 a 12:00 horas, para ser entregada de 12:00 a 16:30 horas. a.1).- Servicio ordinario, en Registro Civil 02, en\nVicente Guerrero.......................... 2.03 UMA\nLa solicitud es de 8:00 a 13:00 horas, para ser entregada en el término de 3 días hábiles, después de haber solicitado.\nb).- Servicio extraordinario.......................... 6.75 UMA\nSolicitado antes de las 12:00 horas, para entrega en 45 minutos.\nc).- En el caso de las actas de nacimiento, exento el\n100% del cobro, de expedición de la primera copia certificada del acta de registro de nacimiento.\nF.1.- Expedición de actas interestatales pago a\nMunicipio...................................... 1.50 UMA\nF.2.- Expedición de actas interestatales pago para\nGobierno del Estado............................ 1.50 UMA\nF.3.- Expedición de actas interestatales pago de impuesto a la educación para Gobierno del\nEstado......................................... 35%\nF.4.- Los pensionados y jubilados, así como sus esposas, madres solteras y viudas jefas de familia de escasos recursos, e hijos de éstas, cuando estos últimos sean menores de 18 años, pagarán 50% de la tarifa únicamente tratándose de documentos que estén a su nombre, debiendo comprobar su condición con identificación o documentación expedida por institución pública.\nF.5.- Tratándose de indigentes mayores de 60 años y las personas con discapacidad, estarán exentos de pago previa solicitud y en su caso, estudio tal condición.\nF.6.- Las personas físicas de escasos recursos que en la tramitación de procedimientos Judiciales, Civiles y Penales, previo estudio socioeconómico que elabore el área de Bienestar Social, se les exentará del pago de los derechos por los servicios que presta el Registro Civil, a de Oficio siempre y cuando no exceda de 13.50\nUMA por servicio, exención que será otorgada al interesado por única ocasión.\nG.- POR TRÁMITE DE TRASLADO DE CADÁVERES:\na).- Fuera del País............................. 33.75 UMA\nb).- Fuera del Municipio........................ 4.05 UMA\nc).- Dentro del Municipio....................... 1.35 UMA\nd).- Fuera del Estado........................... 6.75 UMA\nH.- POR TRÁMITE DE TRASLADO DE CENIZAS:\na).- Fuera del País............................. 6.75 UMA\nb).- Fuera del Municipio........................ 2.03 UMA\nc).- Dentro del Municipio....................... 1.35 UMA\nd).- Fuera del Estado........................... 3.38 UMA\nI.- OTROS:\na).- Para dar trámite a la solicitud de expedición de actas del Registro Civil, a través de llamada\nMunicipios y Estados de la República............. 1.35 UMA\nb).- Reconocimiento de hijos:\na).- Registro o celebración ordinarios.......... 8.10 UMA\nb).- Registro o celebración urgente............. 10.80 UMA\nc).- Registro o celebración extra urgente........ 13.50 UMA\nd).- Registro de reconocimiento de hijos dentro del programa “Jornadas del Registro Civil”, en horas hábiles o extraordinarias, dentro o fuera del domicilio de las oficinas......... $1.00 d.1).- Trámite de anotación marginal y reserva en acta de nacimiento y reconocimiento de hijos.............. 2.70 UMA\nc).- Copias fotostáticas no certificadas.............. 0.34 UMA\nd).- Trámite de rectificación de actas................ 4.05 UMA\ne).- Registro de capitulaciones....................... 13.50 UMA\nf).- Renovación de comprobantes de nacimiento, matrimonio y otros............................... 4.05 UMA\ng).- Transcripción de juicios de divorcios, adopción, nacimientos, matrimonios o cambios de régimen... 4.05 UMA\nh).- Recepción, trámite y anotación marginal de rectificación de acta............................ 1.35 UMA\ni).- Trámite de cancelación de actas por duplicidad... 6.75 UMA\nj).- Constancia o copia certificada, dentro del programa inscripciones escolares......................... 0.68 UMA\nk).- Otros certificados.............................. 1.35 UMA\na).- Otros certificados urgente................ 2.70 UMA\nb).- Expedición de copia certificada, por cada hoja del apéndice.......................... 1.35 UMA\nc).- Expedición de todo el apéndice............. 4.05 UMA\nd).- Constancia por trámites que se les realiza en esta Oficialía a usuarios............... 1.35 UMA\ne).- Devolución de documentos extranjeros y/o traducciones oficiales integrados en apéndices de actos registrales.............. 2.03 UMA\nf).- Reimpresión de actas de los diferentes actos registrales (por error, omisión y/o cancelación por parte de usuarios)......... 2.03 UMA\ng).- Copias certificadas del apéndice urgente... 8.10 UMA\nh).- Copias certificadas del apéndice extraordinaria............................. 16.20 UMA\nl).- Reimpresión de CURP.............................. 0.34 UMA\nm).- Por la expedición de actas y certificados urgentes, se cobrará el doble de la tarifa.\nn).- Los pensionados, jubilados, las esposas y las viudas e hijos de éstas, cuando estos últimos sean menores de 18 años, pagarán 50% de la tarifa, únicamente tratándose de documentos que estén a su nombre debiendo comprobar su condición con identificación o documentación expedida por\nInstitución Pública.\no).- Tratándose de indigentes mayores de 60 años y las personas con discapacidad, estarán exentos de pago, previa solicitud y en su caso, estudio socioeconómico y certificado médico que acredite tal condición por medio de la Dirección de\nBienestar Social.\np).- Las personas físicas de escasos recursos que utilicen los servicios de la Defensoría de Oficio en la tramitación de procedimientos judiciales, civiles y penales, previo estudio socioeconómico servicios que presta el Registro Civil, a solicitud siempre y cuando no exceda de 13.50 UMA por servicio, exención que será otorgada al interesado por única ocasión.\nLey.\n2.- DERECHOS QUE PRESTA LA DIRECCIÓN DE COMERCIO, ALCOHOLES Y\nESPECTÁCULOS PÚBLICOS\nARTÍCULO 24.- Por la recuperación del costo que impacta en el desarrollo de este tipo de eventos, por concepto de recolección de basura, seguridad pública y servicios adicionales, se pagará por el participante en los eventos, siendo responsables solidarios y retenedores los organizadores de los mismos, debiendo cubrirse los\nDerechos correspondientes al solicitarse el servicio, de acuerdo a la siguiente tarifa:\nI.- Eventos con unidades motorizadas, por unidad.. 2.00 UMA\nII.- Eventos con unidades no motorizadas, por participante..................................... 0.20 UMA\nI.- RECEPCIÓN, ANÁLISIS Y REVISIÓN DE SOLICITUDES, DE EMISIÓN DE\nDOCUMENTOS, PERMISOS Y CERTIFICADOS REFERENTES A INSTALACIONES\nPARA LA VENTA, ALMACENAJE O CONSUMO DE BEBIDAS CON GRADUACIÓN\nALCOHÓLICA, AMPLIACIÓN, CAMBIO DE GIRO, CAMBIO DE PERMISIONARIO,\nCAMBIO DE DOMICILIO, CAMBIO DE NOMBRE COMERCIAL Y TRAMITACIÓN\nRELATIVA A LA OPERACIÓN DE GIROS DE CERVEZA, VINOS, LICORES,\nALCOHOLES Y SIMILARES.\nARTÍCULO 25.- La recepción, análisis y revisión de solicitudes de permisos nuevos para la operación de establecimientos con venta, almacenaje o consumo de bebidas alcohólicas o alcohol, ampliación de servicios adicionales o de instalaciones, cambio de giro, cambio de permisionario, cambio de nombre o denominación comercial y cambio de domicilio, así como la emisión de permisos y certificados que por dichos conceptos y similares extienda el Municipio, estarán ssujetos a la siguiente:\nUNIDAD DE MEDIDA Y ACTUALIZACIÓN (UMA) VIGENTE\n1.- Por la recepción, análisis y evaluación de solicitudes de permisos nuevos, servicios adicionales, ampliación de instalaciones para atención al público, cambio de domicilio, cambio de giro, cambio de permisionario, y cambio de nombre permiso, para la venta de bebidas con graduación alcohólica o alcohol.............................. 54.00 UMA\nA).- Por el costo de inspecciones para permisos nuevos o cambios a los permisos ya autorizados:\na).- 1ra. Inspección............................ 33.75 UMA\nb).- 2da. Inspección............................ 27.00 UMA\nc).- 3ra. Inspección............................ 20.25 UMA\nd).- 4ta. Inspección............................ 13.50 UMA\ne).- 5ta. Inspección............................ 13.50 UMA\nB).- Emisión de copias simples........................ 0.09 UMA\n2.- Recepción, análisis y evaluación de solicitudes de modificaciones o ajuste de horario a establecimientos donde se vendan, consuman o almacenen bebidas con graduación alcohólica o alcohol.......................................... 9.45 UMA\n3.- Recepción, análisis y evaluación de solicitudes correspondientes para la venta de bebidas con graduación alcohólica en ferias, verbenas o diversiones análogas o cualquiera otra de carácter transitorio o eventual............................ 9.45 UMA\n4.- Recepción, análisis y evaluación de solicitudes parques deportivos................................ 9.45 UMA\n5.- Autorización de carácter transitorio, de modificación o ajuste de horario, por cada hora adicional:\nI.- De domingo a miércoles, sólo se autorizará una hora........................................ 20.00 UMA\nII.- De jueves a sábado y días festivos sólo se autorizarán hasta dos horas: a.- Primera hora........................... 30.00 UMA b.- Segunda hora........................... 40.00 UMA\n6.- Autorización respecto al aviso de no inconveniente de intención de ceder los derechos de un permiso.......................................... 20.25 UMA\n7.- Derechos por la expedición del permiso y alcohólica, de carácter eventual o transitorio:\na).- Ferias, verbenas, festejos, diversiones análogas y otros, por espacio o local autorizado, por día: a.1).- De 1 a 500 personas por barra 3X3m.... 40.50 UMA a.1.1) Metro cuadrado adicional de carpa 3x3 metros............ 13.50 UMA a.2).- De 501 a 1,000 personas por barra\n3x3m.................................. 67.50 UMA a.2.1) Metro cuadrado adicional de carpa 3x3 metros............ 13.50 UMA a.3).- De 1,001 a 2,500 personas por barra\n3x3m.................................. 94.50 UMA a.3.1) Metro cuadrado adicional de carpa 3x3 metros............ 13.50 UMA a.4).- De 2,501 a 5,000 personas por barra\n3x3m.................................. 121.50 UMA a.4.1) Metro cuadrado adicional de carpa 3x3 metros............. 13.50 UMA a.5).- De 5,001 a 7,500 personas por barra\n3x3m.................................. 202.50 UMA a.5.1) Metro cuadrado adicional de carpa 3x3 metros............ 13.50 UMA a.6).- De 7,501 a 10,000 personas por barra\n3x3m.................................. 270.00 UMA a.6.1) Metro cuadrado adicional de carpa 3x3 metros............ 13.50 UMA a.7).- De 10,001 a 15,000 personas por barra\n3x3m.................................. 337.50 UMA a.7.1) Metro cuadrado adicional de carpa 3x3 metros............ 13.50 UMA a.8).- De 15,001 personas en adelante por barra 3x3m............................ 472.50 UMA a.8.1) Metro cuadrado adicional de carpa 3x3 metros............ 13.50 UMA\nb).- Tratándose de eventos organizados en que participen deportistas, músicos, actores y grupos de danza no profesionales, así como, los realizados por instituciones educativas, dependencias oficiales, organizaciones no gubernamentales con registro ante institución oficial, asociaciones civiles y pagarán por barra 3x3 m²..................... 40.50 UMA\nc).- En parques deportivos, por espacio o local autorizado, un 20% sobre el monto en UMA que corresponda según clasificación establecida en el punto 11 de este Artículo, para la expedición de permisos.\nd).- Otros por local, un 20% sobre el monto en\nUMA que corresponda según clasificación establecida en el punto 11 de este Artículo, para la expedición de permisos.\ne).- Permiso transitorio, para llevar a cabo la venta, degustación y consumo de vinos de mesa nacional por día............................. 27.00 UMA e.1).- Permiso transitorio para la venta y/o consumo de vino de mesa nacional en espectáculos públicos por barra, por día.................................. 20.25 UMA\nf).- Permiso transitorio, para llevar a cabo la venta, degustación y consumo de vinos importados (locales comerciales), por día.... 33.75 UMA\ng).- Permiso transitorio, para la venta, degustación y consumo de licores importados\n(locales comerciales), por día............... 47.25 UMA g.1).- Permiso transitorio para la venta, degustación y consumo de bebidas con graduación alcohólica en eventos y/o espectáculos públicos por barra 3x1 m por día.............................. 121.50 UMA\nh).- Permiso por espacio o local, autorizado por día, dentro de la zona de festejos públicos municipales cuando éstos sean organizados por la Administración Pública, de conformidad a la clasificación de zonas y con base en la UMA\nActualizada.\n1.- Cerveza y Vino:\n1.1.- Zona A.......................... 44.55 UMA\n1.2.- Zona B.......................... 29.70 UMA\n1.3.- Zona C.......................... 20.25 UMA\n1.4.- Zona D.......................... 13.50 UMA\n2.- Cerveza y licor:\n2.1.- Zona A.......................... 98.55 UMA\n2.2.- Zona B.......................... 91.80 UMA\n2.3.- Zona C.......................... 68.85 UMA\n2.4.- Zona D.......................... 40.50 UMA\ni).- Cuando la organización del festejo recaiga en Entidades de la Administración Pública, el permiso general otorgado a estas para su uso de conformidad a las disposiciones legales que le sean aplicables............. 0.00 UMA\nLa clasificación de zonas y puestos, así como el plano de su ubicación, dentro de la zona se trate, deberá ser emitido por el Presidente del Ayuntamiento de San Quintín, Baja\nCalifornia y deberá ser publicado en la página electrónica del Gobierno Municipal\n(www.sanquintin.gob.mx) previo al inicio de la autorización de los permisos.\nj).- Permiso transitorio para venta, degustación, y consumo de cerveza artesanal, en eventos masivos por día: j.1).- De 1 a 500 personas por barra\n3x3m................................. 6.75 UMA j.1.1) Metro cuadrado adicional de carpa 3x3 metros............ 2.70 UMA j.2).- De 501 a 1,000 personas por barra\n3x3m................................. 13.50 UMA j.2.1) Metro cuadrado adicional de carpa 3x3 metros............ 2.70 UMA j.3).- De 1,001 a 2,500 personas por barra\n3x3m................................. 20.25 UMA j.3.1) Metro cuadrado adicional de carpa 3x3 metros............ 2.70 UMA j.4).- De 2,501 a 5,000 personas por barra\n3x3m................................. 27.00 UMA j.4.1) Metro cuadrado adicional de carpa 3x3 metros............ 2.70 UMA j.5).- De 5,001 a 7,500 personas por barra\n3x3m................................. 33.75 UMA j.5.1) Metro cuadrado adicional de carpa 3x3 metros............ 2.70 UMA j.6).- De 7,501 a 10,000 personas por barra\n3x3m................................. 40.50 UMA j.6.1) Metro cuadrado adicional de carpa 3x3 metros............ 2.70 UMA j.7).- De 10,001 a 15,000 personas por barra\n3x3m................................. 47.25 UMA j.7.1) Metro cuadrado adicional de carpa 3x3 metros............ 2.70 UMA j.8).- De 15,001 personas en adelante por barra 3x3m........................... 54.00 UMA j.8.1) Metro cuadrado adicional de carpa 3x3 metros............ 2.70 UMA\n8.- Derechos por revalidación anual de permisos y servicios adicionales.\na).- Tienda de abarrotes.......................... 49.95 UMA\nb).- Billares.................................... 98.55 UMA\nc).- Loncherías, fondas y coctelerías............. 58.05 UMA\nd).- Restaurantes................................. 94.50 UMA\ne).- Restaurant-bar.............................. 124.20 UMA\nf).- Agencias, sub agencias o depósitos.......... 108.00 UMA\ng).- Licorerías.................................. 153.90 UMA\nh).- Bar turístico............................... 240.30 UMA\ni).- Cafés cantantes, cabarets y discotecas...... 280.80 UMA\nj).- Supermercados y tiendas departamentales..... 216.00 UMA\nk).- Bodegas o almacenes......................... 236.25 UMA\nl).- Salón social con consumo de alcohol......... 135.00 UMA\nm).- Mercados y autoservicios con horario hasta las\n22:00 horas.................................. 129.60 UMA\nn).- Mercados y autoservicios con horario hasta las\n24:00 horas.................................. 179.55 UMA ñ).- Terrazas.................................... 109.35 UMA\no).- Expendio de cerveza o vinos................. 139.05 UMA\np).- Hoteles..................................... 198.45 UMA\nq).- Centros sociales y deportivos................ 58.05 UMA\nr).- Balnearios.................................. 135.00 UMA\ns).- Vinaterías.................................. 162.00 UMA s.1) Vinaterías y establecimientos que almacenan y venden exclusivamente vinos de producción nacional con consumo de alimentos................. 81.00 UMA\nt).- Vitivinícolas y establecimientos que producen y/o almacenan y venden exclusivamente vinos de mesa propios, de producción regional, en envase cerrado, abierto o al copeo como actividad principal. Pudiendo ser vinícola, bodega o mostrador comercial................ 81.00 UMA\nu).- Otros....................................... 87.75 UMA\nv).- Cerveza artesanal........................... 54.00 UMA\nw).- Micro cervecería............................ 54.00 UMA\nx).- Establecimiento en espacio abierto, para la venta de alimentos preparados artesanalmente con suministros de producción local y/o regional (solo cerveza y vino), no aplica para locales sobre la vía pública................. 54.00 UMA\ny).- Unidad deportiva no administrada por la\nDirección de Deporte competente con venta exclusiva de cerveza con una capacidad hasta de 200 personas (solo para juegos de adultos).................................... 162.00 UMA y.1).- Unidad deportiva no administrada por la Dirección de Deporte competente con venta exclusiva de cerveza con una capacidad hasta de 201 a 500 personas (solo para juegos de adultos)............................. 216.00 UMA y.2).- Unidad deportiva no administrada por la Dirección de Deporte competente con venta exclusiva de cerveza con una capacidad de 501 personas en adelante (solo para juegos de adultos)............................. 270.00 UMA\nz).- La falta de revalidación oportuna de los permisos o fuera de los plazos establecidos conforme a la Ley de la materia causará una sanción económica hasta del 50% del importe de la propia revalidación, independientemente lugar. No procederá sanción alguna cuando revalidación de permisos por parte de la dependencia competente. Las prórrogas o plazos otorgados serán por única vez y no podrán exceder de 90 días naturales.\n9.- Recepción, análisis y evaluación de solicitud de plazo, para revalidación de permisos de alcohol.......................................... 16.20 UMA\n10.- Evaluación y dictamen sobre la procedencia de ampliación al plazo para inicio de operaciones..................................... 10.80 UMA\n11.- Por la expedición de permisos nuevos, y de cambios a permisos otorgados, una vez que han sido autorizados por la autoridad municipal, se causarán los siguientes Derechos:\na).- Tienda de abarrotes....................... 1,899.45 UMA\nb).- Billares................................. 3,936.60 UMA\nc).- Loncherías, fondas y coctelerías.......... 2,760.75 UMA\nd).- Restaurantes............................. 3,545.10 UMA\ne).- Restaurant-bar........................... 6,758.10 UMA\nf).- Agencias, sub-agencias o depósitos........ 4,490.10 UMA\ng).- Licorerías............................... 4,926.15 UMA\nh).- Bar turístico y cantinas.................. 8,035.20 UMA\ni).- Café cantante y cabarets.................. 9,817.20 UMA\nj).- Supermercados y tiendas departamentales.. 6,288.30 UMA\nk).- Bodegas o almacenes....................... 4,722.30 UMA\nl).- Mercados y autoservicios con horario hasta las 22:00 horas..................... 3,580.20 UMA\nm).- Mercados y autoservicios con horario hasta las 24:00 horas.......................... 4,228.20 UMA\nn).- Expendio de cerveza y vinos............... 5,769.90 UMA ñ).- Hoteles.................................. 8,464.50 UMA\no).- Centros sociales y deportivos............. 2,643.30 UMA\np).- Balnearios............................... 2,970.00 UMA\nq).- Salón social con consumo de alcohol....... 2,970.00 UMA\nr).- Vinaterías............................... 3,685.50 UMA r.1).- Vinaterías y establecimientos que almacenan y venden exclusivamente vinos de producción nacional con consumo de alimentos.............. 0.00 UMA\ns).- Vitivinícolas y establecimientos que producen (siembra de uva y produzca vino) y/o almacenan y venden exclusivamente vinos de mesa propios, de producción regional, en envase cerrado, abierto o al copeo como actividad principal. pudiendo ser vinícola, bodega o mostrador comercial................................ 0.00 UMA s.1.).- Servicios adicionales: s.1.1).- Restaurante............. 1,181.70 UMA s.1.2).- Salón social............ 337.50 UMA\nt).- Establecimientos de Cerveza Artesanal.... 405.00 UMA\nu).- Micro cervecería......................... 405.00 UMA\nv).- Establecimiento en espacio abierto, para la venta de alimentos preparados artesanalmente con suministros de producción local y/o regional (solo cerveza y vino), no aplica para locales sobre la vía pública.............................. 337.50 UMA\nw).- Unidad deportiva no administrada por la\nDirección de Deporte competente con venta exclusiva de cerveza con una capacidad hasta de 200 personas (solo para juegos de adultos).............................. 810.00 UMA w.1).- Unidad deportiva no administrada por la Dirección de Deporte competente con venta de cerveza con una capacidad hasta de 201 a\n500 personas (solo para juegos de adultos).......................... 945.00 UMA w.2).- Unidad deportiva no administrada por la Dirección de Deporte competente con venta exclusiva de cerveza con una capacidad de 501 personas en adelante (solo para juegos de adultos)................ 1,215.00 UMA\nx).- Servicios adicionales:\n1).- Música grabada, por semana autorizada o fracción.......................... 20.25 UMA\n2).- Música en vivo, por semana autorizada o fracción.......................... 45.90 UMA\n3).- Baile, por semana autorizada o fracción............................ 67.50 UMA\n4).- Espectáculo artístico, por semana autorizada o fracción................ 94.50 UMA\n5).- Mesa de billar por semana............ 20.25 UMA\ny).- Otros servicios adicionales:\n1).- Música grabada, por incorporarlos al permiso............................. 297.00 UMA\n2).- Música en vivo, por incorporarlos al permiso de los giros:\n2.1).- Lonchería.................... 371.25 UMA\n2.2).- Restaurante.................. 371.25 UMA\n3).- Baile, por incorporarlos al permiso de los giros:\n3.1).- Lonchería.................... 472.50 UMA\n3.2).- Restaurante.................. 472.50 UMA\n4).- Espectáculo artístico, por incorporarlos al permiso de los giros.\n4.1).- Restaurant-bar............... 506.25 UMA\n4.2).- Bar Turístico................ 506.25 UMA\n5).- Mesa de billar por incorporarlos al permiso de los giros en envase abierto............................. 27.00 UMA\nz).- Cervecería artesanal, establecimiento que produce, almacena, distribuye vende en envase abierto y/o cerrado cerveza elaborada de forma manual hasta su embotellamiento.......................... 405.00 UMA aa).- Micro cervecería, establecimiento independiente que produce y almacena para su distribución y venta, cerveza artesanal, de producción propia, así como un diverso productor de cerveza artesanal, siempre que el capital, para realizar tal actividad no intervenga con una inversión mayor al 25% de una persona física o moral dedicada a la industria de la producción cervecera, de degustación con música en vivo o grabada, área en el interior o exterior para dar servicios y cuyo volumen de producción de cerveza artesanal no exceda los cinco millones de hectolitros anuales......... 405.00 UMA ab).- Barras móviles.......................... 270.00 UMA ac).- Barras para evento en salón social...... 81.00 UMA ad).- Autorización de consumo de bebidas con graduación alcohólica en salón social... 17.55 UMA ae).- Terraza. Para agregar este servicio adicional el interesado deberá pagar el\n20% del valor del permiso ya autorizado.\n12.- Por la expedición de autorización de cambios o modificación al permiso, pagarán los siguientes\nDerechos:\na).- Por cambio de domicilio dentro del\nMunicipio, se cobrará 30% sobre el valor del permiso nuevo.\nb).- Por cambio de permisionario se cobrará 50% sobre el valor del permiso nuevo. b.1).- Cuando se trate de un cambio a favor de viuda o viudo, se cobrará el 25% sobre el valor del permiso nuevo. b.2).- Cuando se trate de un cambio a favor de viuda o viudo, y además este cuente con más de 60 años, se cobrará el 12.5% sobre el valor del permiso nuevo.\nEstos sub incisos b.1) y b.2), aplicarán solamente a los giros de abarrotes, autoservicio, fonda, lonchería, cocteles y restaurantes, de acuerdo al Reglamento en Materia de Alcoholes.\nc).- Por cambio de nombre comercial, se cobrará\n5% sobre el valor del permiso nuevo.\nd).- Por cambio de giro comercial de manera descendente, se cobrará 10% sobre el valor del permiso nuevo del giro que prevalece.\ne).- Por cambio de giro comercial de manera ascendente, se cobrará la diferencia entre las tarifas de los permisos nuevos de los giros que se modifican.\nf).- Por autorización de ampliación de instalaciones, para atención al público en el mismo local (no incluye terrazas), se cobrará 10% sobre el valor del permiso nuevo.\ng).- Por autorización de contrato de comodato y reactivación de permiso.................. 70.00 UMA\nII.- RECEPCIÓN, ANÁLISIS Y REVISIÓN DE DOCUMENTOS, Y POR LA\nAUTORIZACIÓN PARA LA INSTALACIÓN Y EXPLOTACIÓN DE APARATOS DE\nSONIDO, ELECTRÓNICOS, MECÁNICOS, ELECTROMECÁNICOS, VIDEOJUEGOS Y\nSIMILARES.\nARTÍCULO 26.- La recepción, análisis y revisión de solicitudes de permisos para la instalación y explotación de aparatos mecánicos, electrónicos, electromecánicos, videojuegos, de sonido, cafés internet y similares; cambio de domicilio, así como la emisión de permisos, de revalidaciones, registro y ampliación de aparatos y\nMunicipio, estarán sujetos a la siguiente:\nUNIDAD DE MEDIDA Y ACTUALIZACIÓN (UMA) VIGENTE\n1.- Recepción, análisis y revisión de solicitudes de permisos para la instalación y control de la explotación de aparatos mecánicos, electrónicos, electromecánicos, musicales, videojuegos, café internet y similares:\na).- Mecánicos, electrónicos, electromecánicos, musicales, videojuegos y similares........... 13.50 UMA\nb).- Cafés Internet............................... 1.35 UMA\n2.- Recepción, análisis y revisión de solicitudes de cambio de domicilio............................... 13.50 UMA\n3.- Recepción, análisis y revisión de solicitudes correspondientes, para la instalación u operación de aparatos mecánicos, electrónicos, electromecánicos, musicales, videojuegos y otros, en ferias, verbenas o diversiones análogas de carácter transitorio...................................... 13.50 UMA\n4.- Por el permiso ya sea en ruta o fijo como propietario, comisionista, arrendador, asociado o cualquier otra figura o denominación para la explotación de aparatos mecánicos, electrónicos, electromecánicos, musicales, videojuegos, café\nInternet y otros:\n4.1.- Permisionario fijo......................... 94.50 UMA\n4.2.- Permisionario ruta......................... 94.50 UMA\n4.3.- Permiso para café internet................. 20.25 UMA\n4.4.- Permisionario de máquinas mecánicas expendedoras de dulces y juguetes.......... 27.00 UMA\n4.5.- Permisionarios de máquinas electromecánicas expendedoras de refrescos y golosinas...... 94.50 UMA\n5.- Por las autorizaciones que expida el Municipio, respecto de aparatos a que se refiere este\nArtículo:\n5.1.- Por aparato registrado..................... 13.50 UMA\n5.2.- Por cambio de domicilio.................... 13.50 UMA\n5.3.- Incremento, por aparato.................... 13.50 UMA\n5.4.- Para café internet por el registro de las computadoras: a.- Hasta 10 aparatos..................... 13.50 UMA b.- De 11 a 20 aparatos................... 27.00 UMA c.- Más de 20 aparatos.................... 40.50 UMA\n5.5.- Por revalidación anual, por aparato de video juego...................................... 4.05 UMA\n5.6.- Por aparato registrado de máquinas mecánicas expendedoras de dulces y juguetes................................... 6.75 UMA\n5.7.- Por aparato registrado de máquinas electromecánicas expendedoras de refrescos y golosinas.................................. 20.25 UMA\n5.8.- Por revalidación anual por aparato registrado de máquinas mecánicas expendedoras de dulces y juguetes.......... 4.05 UMA\n5.9.- Por revalidación anual de máquinas electromecánicas expendedoras de refrescos y golosinas.................................. 33.75 UMA\n5.10.- Por revalidación anual del permiso para la explotación de cafés internet.............. 27.00 UMA\n6.- Emisión de copias simples......................... 0.09 UMA\nIII.- CENTROS DE APUESTAS, APUESTAS REMOTAS, SALAS DE SORTEOS\nDE NÚMEROS Y/O CASINOS.\nARTÍCULO 27.- Las máquinas de azar o con combinaciones de azar y destreza, con premios en efectivo o en especie que cuenten con autorización de la Secretaría de Gobernación, pagarán los derechos de instalación o explotación conforme a la siguiente tabla:\na).- Dictamen de opinión favorable o anuencia, por establecimiento en apertura.................. 67,500.00 UMA\nb).- Permiso por horario ampliado anual por establecimiento.............................. 2,025.00 UMA\nc).- Cambio de domicilio.......................... 2,025.00 UMA\nd).- Cambio de propietario........................ 2,025.00 UMA\ne).- Revalidación que deba realizarse dentro del ejercicio fiscal............................ 27,000.00 UMA\nLa falta de revalidación oportuna causará un cobro del 3% mensual, adicional al cobro de la revalidación.\nf).- Aportación para programas preventivos para la ludopatía.................................... 2,025.00 UMA\nIV.- RECEPCIÓN Y ANÁLISIS DE DOCUMENTOS Y EXPEDICIÓN DE PERMISOS\nDIVERSIÓN.\nARTÍCULO 28.- Para la realización de eventos, espectáculos públicos y de diversión, deberá entregarse la documentación correspondientes, previo el pago de los Derechos que se causen de acuerdo a la siguiente:\nUNIDAD DE MEDIDA Y ACTUALIZACIÓN (UMA) VIGENTE\n1.- Circos:\na).- Una pista................................... 20.25 UMA\nPOR DÍA\nb).- Dos pistas.................................. 27.00 UMA\nPOR DÍA\nc).- Zona Sur San Quintín (Delegaciones de El\nMármol, Punta Prieta, Bahía de Los Ángeles y\nVilla Jesús María).......................... 10.13 UMA\nPOR DÍA\n2.- Juegos Mecánicos:\na).- Zona urbana San Quintín...................... 20.25 UMA\nPOR DÍA\nb).- Por Delegación Municipal................... 4.00 UMA\nPOR DÍA\nc).- Cuando la organización del festejo, recaiga en la Administración Pública en zona de festejos, públicos municipales............. 135.00 UMA\nPOR DÍA\nd).- Cuando la organización del festejo recaiga en\nEntidades de la Administración Pública, el permiso general otorgado a éstas, para su uso de conformidad con las disposiciones legales que le sean aplicables............ 27.00 UMA\nPOR DÍA\n3.- Cierre de Calle:\na).- Eventos públicos............................. 40.50 UMA\nPOR DÍA\nb).- Eventos privados............................. 27.00 UMA\nPOR DÍA\n4.- Desfiles promocionales............................ 67.50 UMA\nPOR EVENTO\n5.- Desfiles relativos a centros educativos por a sus actividades académicas.................... EXENTO\n6.- Exhibición de modas y otros....................... 81.00 UMA\nPOR EVENTO\n7.- Funciones:\na).- Box a.1).- Profesional........................... 81.00 UMA\nPOR EVENTO a.2).- Amateur............................... 40.50 UMA\nPOR EVENTO a.3).- Cuando la Organización de los eventos estipulados en los incisos a.1) y a.2) sean organizados por la Asociación\nMunicipal de Box Amateur, Selección o\nRepresentativo Municipal, se cobrará el\n50%.\nb).- Lucha libre: b.1).- Profesional........................... 81.00 UMA\nPOR EVENTO b.2).- Amateur............................... 40.50 UMA\nPOR EVENTO\nc).- Obras de teatro c.1).- Locales............................... 27.00 UMA\nPOR DÍA c.2).- Foráneas.............................. 67.50 UMA\nPOR DÍA\nd).- Cine......................................... 13.50 UMA\nPOR DÍA\ne).- Otros........................................ 13.50 UMA\nPOR DÍA\nf).- Auto cinemas: f.1).- De 1 a 50 vehículos................... 6.75 UMA\nPOR DÍA f.2).- De 51 a 100 vehículos................. 13.05 UMA\nPOR DÍA f.3).- De 101 vehículos en adelante......... 20.25 UMA\nPOR DÍA\n8.- Espectáculos masivos:\na).- Corrida de toros............................. 202.50 UMA\nPOR EVENTO\nb).- Presentación de entretenedores y comediantes. 67.50 UMA\nPOR DÍA\nc).- Bailes en salones............................ 67.50 UMA\nPOR DÍA c.1).- Zona Norte de San Quintín (Delegaciones de Camalú, Vicente Guerrero, San\nQuintín y El Rosario)................. 67.50 UMA\nPOR DÍA c.2).- Zona Sur de San Quintín Delegaciones de\nEl Mármol, Punta Prieta, Bahía de los\nÁngeles y Villa Jesús María).......... 33.75 UMA\nPOR DÍA\nd).- Conciertos con presentación de artistas foráneos..................................... 202.50 UMA\nPOR DÍA\ne).- Conciertos con músicos locales............... 27.00 UMA\nPOR DÍA e.1).- De 1 a 500 personas................... 27.00 UMA\nPOR DÍA e.2).- De 501 a 1,000 personas............... 54.00 UMA\nPOR DÍA e.3).- De 1,001 a 2,000 personas............. 108.00 UMA\nPOR DÍA e.4).- De 2,001 personas en adelante......... 216.00 UMA\nPOR DÍA\nf).- Carreras de automóviles, motocicletas y vehículos con motor: f.1).- Arrancones local...................... 48.00 UMA f.1.1).- Arrancones foráneo.......... 95.00 UMA f.2).- Carrera fuera de camino tipo off-road local................................. 48.00 UMA f.2.1).- Carrera fuera de camino tipo off-road foráneo............ 95.00 UMA f.3).- Paseos o recorridos de exhibición local................................. 24.00 UMA f.3.1).- Paseos o recorridos de exhibición foráneo.......... 48.00 UMA f.4).- Carrera de exhibición local............ 24.00 UMA f.4.1).- Carrera de exhibición foráneo..................... 48.00 UMA\nNota: Los eventos de arrancones del inciso f), no podrán autorizarse dentro de los límites del al mar, así como en zonas habitacionales.\ng).- Charreada, Rodeo, Jaripeo: g.1).- Zona Urbana San Quintín............... 67.50 UMA\nPOR DÍA g.2).- En Delegaciones Municipales........... 40.50 UMA\nPOR DÍA\nh).- Peleas de gallos............................. 202.50 UMA\nPOR DÍA\ni).- Exhibición de gallos, peleas de casteo (sin apuesta).................................... 135.00 UMA\nPOR DÍA\nj).- Tlacuachadas, carreras parejeras con apuestas.................................... 135.00 UMA\nPOR DÍA\nk).- Tlacuachadas, carreras parejeras sin apuestas.................................... 67.50 UMA\nPOR DÍA\nl).- Festejos, ferias populares................... 67.50 UMA\nPOR DÍA\nm).- Festejos, ferias populares en Delegaciones\nMunicipales................................. 40.50 UMA\nPOR DÍA\nn).- Otros....................................... 27.00 UMA\nPOR DÍA ñ).- Tratándose de expo, bazar, feria o festival, masivo:\n1).- Realizado por Organismos no Lucrativos.. 54.00 UMA\nPOR DÍA\n2).- Realizado por Organismos Lucrativos..... 121.50 UMA\nPOR DÍA\n3).- Realizado en la vía pública:\n3.1.- Por evento...................... 54.00 UMA\n3.2.- Por carpa de 3x3 metros......... 7.36 UMA\n3.3.- Por metro adicional de carpa 3x3 metros.......................... 1.35 UMA\n4).- Realizado en predios privados:\n4.1.- Por evento de 1 a 200 personas.. 13.50 UMA\n4.2.- Por evento de 201 a 400 personas 27.00 UMA\n4.3.- Por evento de 401 a 800 personas.. 40.50 UMA\n4.4.- Por evento 801 a 1,500 personas... 67.50 UMA\n4.5.- Por evento 1,500 en adelante.... 135.00 UMA\no).- Tratándose de espectáculos realizados por organismos no lucrativos que brinden servicios y asistencia médica de manera gratuita a enfermos que padezcan cáncer en etapa terminal, debidamente registrados ante institución oficial que para tales efectos señale la Ley de la materia................. 27.00 UMA\np).- Los eventos relacionados y/o enfocados a profesionistas y estudiantes................. 13.50 UMA\nPOR EVENTO\nq).- Congresos con fines de lucro................. 13.50 UMA\nPOR EVENTO\nr).- Congresos sin fines de lucro................. 6.75 UMA\nPOR EVENTO\ns).- Simposium con fines de lucro................. 13.50 UMA\nPOR EVENTO\nt).- Simposium sin fines de lucro................. 6.75 UMA\nPOR EVENTO\nu).- Cursos de capacitación con fines de lucro.... 13.50 UMA\nPOR EVENTO\nv).- Cursos de capacitación sin fines de lucro......................................... 6.75 UMA\nPOR EVENTO\nw).- Conferencias con fines de lucro.............. 13.50 UMA\nPOR EVENTO\nx).- Conferencias sin fines de lucro.............. 6.75 UMA\nPOR EVENTO\ny).- Eventos realizados por ligas deportivas locales..................................... 13.50 UMA\nPOR DÍA\nz).- En general por la recepción y análisis de documentos de espectáculos y eventos urgentes\n(en menos de 72 horas), se cobrará el doble de la tarifa.\n9).- Filmaciones, documentales, comerciales, videoclips musicales, películas y series:\na) Participación de más de 100 personas........ 50.00 UMA\nb) Participación de 99 a menos personas........ 25.50 UMA en los incisos a) y b) de este numeral, sean académicos, con el aval de la Institución Educativa correspondiente se exentará de dicho cobro.\nLas personas físicas o morales que soliciten para eventos sociales o fiestas, deberán iniciar los trámites correspondientes conforme a los reglamentos aplicables, en las Direcciones eventos de diversión, y una vez dictaminado el cumplimiento a cabalidad de los requisitos y condiciones exigidos para tal efecto, se deberá a lo siguiente:\nI.- Inspección de factibilidad...................... 27.00 UMA\nII.- Emisión de copia simple......................... 0.09 UMA\nIII.- Por la recepción, análisis y evaluación de solicitudes de permisos nuevos, servicios adicionales, cambio de domicilio, cambio de permisionario y cambio de nombre comercial de los establecimientos con permiso vigente........ 54.00 UMA\nIV.- Apertura:\nA).- En zona habitacional:\n1.- Establecimiento en área abierta, con horario de 11:00 a 22:00 horas:\na).- Con cupo de 1 a 100 personas.... 540.00 UMA\nb).- Con cupo de 101 a 200 personas.. 675.00 UMA\nc).- Con cupo de 201 a 300 personas.. 810.00 UMA\nd).- Con cupo de 301 a 400 personas.. 945.00 UMA\ne).- Con cupo de 401 a 600 personas.. 1,080.00 UMA\nf).- Con cupo de 601 a 800 personas.. 1,215.00 UMA\ng).- Con cupo de más de 800 personas. 1,350.00 UMA\n2.- Establecimiento mixto, de 11:00 a 22:00 horas en área abierta y hasta las 24:00 horas en área cerrada:\na).- Con cupo de 1 a 100 personas.... 810.00 UMA\nb).- Con cupo de 101 a 200 personas.. 945.00 UMA\nc).- Con cupo de 201 a 300 personas.. 1,080.00 UMA\nd).- Con cupo de 301 a 400 personas.. 1,215.00 UMA\ne).- Con cupo de 401 a 600 personas.. 1,350.00 UMA\nf).- Con cupo de 601 a 800 personas.. 1,485.00 UMA\ng).- Con cupo de más de 800 personas. 1,620.00 UMA\n3.- Establecimiento en área cerrada, de\n11:00 a 24 horas:\na).- Con cupo de 1 a 100 personas.... 405.00 UMA\nb).- Con cupo de 101 a 200 personas.. 540.00 UMA\nc).- Con cupo de 201 a 300 personas.. 675.00 UMA\nd).- Con cupo de 301 a 400 personas.. 810.00 UMA\ne).- Con cupo de 401 a 600 personas.. 945.00 UMA\nf).- Con cupo de 601 a 800 personas.. 1,080.00 UMA\ng).- Con cupo de más de 800 personas. 1,350.00 UMA\n4.- Piñatero en zona habitacional de 11:00 a 20:00 horas:\na).- Con cupo de 1 a 100 personas.... 270.00 UMA\nb).- Con cupo de 101 a 200 personas.. 405.00 UMA\nc).- Con cupo de 201 a 300 personas.. 540.00 UMA\nd).- Con cupo de 301 a 400 personas.. 675.00 UMA\ne).- Con cupo de 401 a 600 personas.. 810.00 UMA\nf).- Con cupo de 601 a 800 personas.. 945.00 UMA\ng).- Con cupo de más de 800 personas. 1,215.00 UMA\nB).- En zona comercial:\n1.- Establecimiento en área abierta, con horario de 11:00 a 23:59 horas:\na).- Con cupo de 1 a 100 personas.... 540.00 UMA\nb).- Con cupo de 101 a 200 personas.. 675.00 UMA\nc).- Con cupo de 201 a 300 personas.. 810.00 UMA\nd).- Con cupo de 301 a 400 personas.. 945.00 UMA\ne).- Con cupo de 401 a 600 personas.. 1,080.00 UMA\nf).- Con cupo de 601 a 800 personas.. 1,215.00 UMA\ng).- Con cupo de más de 800 personas. 1,350.00 UMA\n2.- Establecimiento mixto de 11:00 a 23:59 horas en área abierta y hasta las\n02:00 horas en área cerrada:\na).- Con cupo de 1 a 100 personas.... 675.00 UMA\nb).- Con cupo de 101 a 200 personas.. 810.00 UMA\nc).- Con cupo de 201 a 300 personas.. 945.00 UMA\nd).- Con cupo de 301 a 400 personas.. 1,080.00 UMA\ne).- Con cupo de 401 a 600 personas.. 1,215.00 UMA\nf).- Con cupo de 601 a 800 personas.. 1,350.00 UMA\ng).- Con cupo de más de 800 personas. 1,485.00 UMA\n3.- Establecimiento en área cerrada, de\n11:00 a 02:00 horas:\na).- Con cupo de 1 a 100 personas.... 810.00 UMA\nb).- Con cupo de 101 a 200 personas.. 945.00 UMA\nc).- Con cupo de 201 a 300 personas.. 1,080.00 UMA\nd).- Con cupo de 301 a 400 personas.. 1,215.00 UMA\ne).- Con cupo de 401 a 600 personas.. 1,350.00 UMA\nf).- Con cupo de 601 a 800 personas.. 1,485.00 UMA\ng).- Con cupo de más de 800 personas. 1,620.00 UMA\n4.- Piñatero en zona comercial de 11:00 a\n20:00 horas:\na).- Con cupo de 1 a 100 personas.... 270.00 UMA\nb).- Con cupo de 101 a 200 personas.. 405.00 UMA\nc).- Con cupo de 201 a 300 personas.. 540.00 UMA\nd).- Con cupo de 301 a 400 personas.. 675.00 UMA\ne).- Con cupo de 401 a 600 personas.. 810.00 UMA\nf).- Con cupo de 601 a 800 personas.. 945.00 UMA\ng).- Con cupo de más de 800 personas. 1,215.00 UMA funcionamiento de establecimientos para eventos sociales o fiestas, del permiso y la zona:\nV.- Cambio de domicilio:\na).- Zona habitacional........................... 30%\nb).- Zona comercial.............................. 30%\nVI.- Cambio de propietario:\na).- Zona habitacional........................... 40%\nb).- Zona comercial.............................. 40%\nVII.- Cambio de nombre comercial:\na).- Zona habitacional........................... 15%\nb).- Zona comercial.............................. 15%\nVIII.- Por la revalidación del permiso que deba realizarse dentro del ejercicio fiscal, deberá cubrirse el 5% del valor del permiso.\nPara llevar a cabo la revalidación del permiso, el propietario deberá presentar la documentación requerida en el reglamento de la materia, así como la constancia de no adeudo municipal.\nIX.- Se impondrá una multa de 40.50 a 135.00 Unidad de Medida y Actualización (UMA) a quienes no revaliden el permiso en forma oportuna.\nV.- RECEPCIÓN Y ANÁLISIS DE DOCUMENTOS REFERENTES A LA INSTALACIÓN\nDE APARATOS MUSICALES (SINFONOLAS).\nARTÍCULO 29.- Para la apertura (inicio de actividades), cambio de permisionario, cambio de domicilio o el incremento de aparatos musicales (sinfonolas), deberán entregarse y analizarse la siguiente:\nPROPIETARIO DEL APARATO:\na) Por aparato (sinfonola), cuando es inicio de actividades....................................... 135.00 UMA\nb) Cambio de domicilio............................... 13.50 UMA\nc) Verificación durante lo que corresponda del ejercicio fiscal 2025 por aparato................. 40.50 UMA\nVI.- EXPEDICIÓN DE PERMISOS PARA EL EJERCICIO DEL COMERCIO EN LA\nVÍA PÚBLICA POR COMERCIANTES AMBULANTES, O CON PUESTOS FIJOS O\nSEMIFIJOS\nARTÍCULO 30.- Los Derechos por la expedición y/o revalidación de permisos para el uso u ocupación de las vías públicas, por por los usuarios desde la entrada en vigor de la presente Ley hasta el 31 de diciembre del ejercicio fiscal en curso, según corresponda conforme a la siguiente:\nUNIDAD DE MEDIDA Y ACTUALIZACIÓN VIGENTE\nA.- ANUALMENTE:\n1) AMBULANTE CON CAJA:\n1.1 Zona Urbana.......................... 10.80 UMA\n1.2 Zona Suburbana y/o Rural............. 6.75 UMA\n2) AMBULANTE CON CARRETA:\n2.1 Zona Urbana.......................... 13.50 UMA\n2.2 Zona Suburbana y/o Rural............. 9.45 UMA\n3) AMBULANTE MOTORIZADO:\n3.1 Zona Urbana.......................... 16.20 UMA\n3.2 Zona Suburbana y/o Rural............. 12.15 UMA\n4) PUESTOS FIJOS:\n4.1 Zona Urbana.......................... 33.75 UMA\n4.2 Zona Suburbana y/o Rural............. 28.35 UMA\n5) PUESTOS SEMIFIJOS:\n5.1 Zona Urbana.......................... 29.70 UMA\n5.2 Zona Suburbana y/o Rural............. 24.30 UMA\n6) MERCADOS COMUNES EN LA VÍA PÚBLICA:\n6.1 Zona Urbana.......................... 16.20 UMA\n6.2 Zona Suburbana y/o Rural............. 10.80 UMA\n7) MERCADOS COMUNES EN PREDIO PRIVADO:\n7.1 Zona Urbana........................... 16.20 UMA\n7.2 Zona Suburbana y/o Rural.............. 4.05 UMA\n8) PUESTOS DE REVISTAS:\n8.1 Zona Urbana.......................... 8.10 UMA\n8.2 Zona Suburbana y/o Rural............. 4.05 UMA\n9) ASEADORES DE CALZADO:\n9.1 Zona Urbana.......................... 1.35 UMA\n9.2 Zona Suburbana y/o Rural............. 1.35 UMA\n10) FOTÓGRAFOS AMBULANTES:\n10.1 Zona Urbana......................... 8.10 UMA\n10.2 Zona Suburbana y/o Rural............ 4.05 UMA\n11) CAMIÓN AMBULANTE (MEDIDA 3 METROS)........... 87.75 UMA\n12) METRO EXCEDENTE DE CAMIÓN AMBULANTE.......... 27.00 UMA\n13) CERRAJEROS AMBULANTES........................ 33.75 UMA\n14) LOS AMBULANTES QUE SE DEDIQUEN A LA VENTA\nEXCLUSIVA DE ARTESANÍAS MEXICANAS, PAGARÁN EL\n50% DE LOS DERECHOS CAUSADOS.\n15) LAS MUJERES INDÍGENAS ARTESANAS, REGISTRADAS\nEN EL PADRÓN MUNICIPAL, QUEDARÁN EXENTAS DEL\nPAGO DE DERECHOS CAUSADOS POR PERMISO ANUAL.\nDE ARTESANÍAS MEXICANAS.\nB.- POR EVENTO:\n1 PERMISO POR DÍA:\na) MERCADO COMÚN.......................... 1.02 UMA\nb) DÍAS DE FESTIVIDAD..................... 6.75 UMA\nb1) MUJERES INDÍGENAS ARTESANAS\nEMPADRONADAS.................... 0.51 UMA\nc) EVENTOS DEPORTIVOS..................... DE 6.75\nHASTA\n33.75 UMA\nc1 CARPA 3X3 M².................... 10.80 UMA\nc2 METRO CUADRADO ADICIONAL DE\nCARPA 3X3 M².................... 1.35 UMA\nd) EVENTOS PRIVADOS (GRADUACIONES, OBRAS DE\nTEATRO O LUGARES DONDE SE REALICEN\nEVENTOS Y/O ESPECTÁCULOS PÚBLICOS), SIN\nQUE ESTA AUTORIZACIÓN EXCEDA DE DOS\nHORAS EN LA MISMA UBICACIÓN............ 4.05 UMA\ne) ENVOLTURAS DE REGALOS.................. 5.40 UMA\nf) AUTORIZACIÓN POR METRO EXCEDENTE EN\nPUESTO FIJO O SEMIFIJO CONSIDERANDO\nMOBILIARIO Y EQUIPO DE TRABAJO, NO\nPUDIENDO EXCEDER DE DOS METROS......... 17.55 UMA\nPOR MES\n2) PERMISO TARIFA DIARIA....................... 0.68 UMA\n3) PERMISO TARIFA SEMANAL...................... 4.05 UMA\n4) PERMISO TARIFA QUINCENAL.................... 6.75 UMA\n5) PERMISO TARIFA MENSUAL...................... 10.80 UMA\nLas personas mayores de 60 años, así como las personas con discapacidad, los jubilados y a su nombre, estarán exentos del pago de los derechos de este artículo.\nAsí mismo, las personas que se dediquen a la venta mercado común, pagarán el 50% de los derechos, previstos en el apartado b) numeral 1 inciso a) de este artículo, previo estudio socioeconómico.\n6).- PERMISO DENTRO DE LA ZONA DE FESTEJOS,\nORGANIZADOS Y/O COORDINADOS POR LA\nADMINISTRACIÓN PÚBLICA MUNICIPAL, POR DÍA\nSEGÚN LA SIGUIENTE TABLA:\n1).- Carpa de 3x3 metros.................... 90.45 UMA\n1.1).- Metro cuadrado adicional de carpa 3x3 metros................ 1.35 UMA\n7) Cuando la organización del festejo recaiga en\nEntidades de la Administración Pública, el permiso general otorgado a éstas, para su uso de conformidad a las disposiciones legales que le sean aplicables........................... 0.00 UMA\nLa clasificación de zonas y puestos, así como el plano de su ubicación, dentro de la zona destinada a la realización del festejo de que se trate, deberá ser emitido por el Presidente del\nAyuntamiento de San Quintín, Baja California, cuando su organización esté a cargo del Gobierno Municipal, o del Director de que se trate y deberá ser publicado en la página electrónica del Ayuntamiento de\nSan Quintín, Baja California - www.sanquintin.gob.mx - previo al inicio de la comercialización de los espacios.\nLas madres jefas de familia que son el único sostén del hogar, con hijo o hijos menores de edad y/o personas con discapacidad, tendrán el 50% (cincuenta por ciento) de descuento en el pago de los derechos estipulados en los apartados A.- y B.- numeral 1) inciso a) de este certificado de inexistencia de matrimonio.\nC).- REVALIDACIÓN: pública en su modalidad de ambulante, fijo, semifijo y mercado común enero a marzo del ejercicio fiscal correspondiente, el no revalidar durante ese periodo generará un cobro de 3% mensual hasta en tanto sea cubierta dicha revalidación.\n1).- AMBULANTE CON CAJA:\n1.1 Zona Urbana.......................... 10.80 UMA\n1.2 Zona Suburbana y/o rural............. 6.75 UMA\n1.3 Zona turística....................... 13.50 UMA\n2).- AMBULANTE CON CARRETA:\n2.1 Zona Urbana.......................... 13.50 UMA\n2.2 Zona Suburbana y/o rural............. 9.45 UMA\n2.3 Zona turística....................... 16.20 UMA\n3).- AMBULANTE MOTORIZADO:\n3.1 Zona Urbana.......................... 16.20 UMA\n3.2 Zona Suburbana y/o rural............. 12.15 UMA\n3.3 Zona turística....................... 18.90 UMA\n4).- PUESTOS FIJOS:\n4.1 Zona Urbana.......................... 33.75 UMA\n4.2 Zona Suburbana y/o rural............. 28.35 UMA\n4.3 Zona turística....................... 46.00 UMA\n5).- PUESTOS SEMIFIJOS:\n5.1 Zona Urbana.......................... 29.70 UMA\n5.2 Zona Suburbana y/o rural............. 24.30 UMA\n5.3 Zona turística....................... 46.00 UMA\n6).- MERCADOS COMUNES EN LA VÍA PÚBLICA:\n6.1 Zona Urbana.......................... 16.20 UMA\n6.2 Zona Suburbana y/o rural............. 10.80 UMA\n6.3 Zona turística....................... 18.90 UMA\n7).- MERCADOS COMUNES EN PREDIO PRIVADO:\n7.1 Zona Urbana.......................... 16.20 UMA\n7.2 Zona Suburbana y/o rural............. 10.80 UMA\n7.3 Zona turística....................... 18.90 UMA\n8).- PUESTOS DE REVISTAS:\n8.1 Zona Urbana.......................... 8.10 UMA\n8.2 Zona Suburbana y/o rural............. 4.05 UMA\n8.3 Zona turística....................... 10.80 UMA\n9).- ASEADORES DE CALZADO:\n9.1 Zona Urbana.......................... 1.35 UMA\n9.2 Zona Suburbana y/o rural............. 1.35 UMA\n9.3 Zona turística....................... 4.05 UMA\n10).- FOTÓGRAFOS AMBULANTES:\n10.1 Zona Urbana......................... 8.10 UMA\n10.2 Zona Suburbana y/o rural............ 4.05 UMA\n10.3 Zona turística...................... 10.80 UMA\n11).- CAMIÓN AMBULANTE (MEDIDA 3 METROS)........... 40.50 UMA\n12).- CERRAJEROS AMBULANTES........................ 6.75 UMA\nLas personas mayores de 60 años, así como las personas con discapacidad, los jubilados y pensionados y que cuenten con autorización a su nombre, estarán exentos del pago de los derechos contemplados en el apartado C).- de este artículo debiendo comprobar su condición con identificación oficial o en su caso certificado médico que acredite tal condición, elaborado por una\nInstitución de Salud Pública. De igual forma para madres jefas de familia, que son el único sostén del hogar, con hijo o hijos menores de edad y/o personas con discapacidad, tendrán el 50%\n(cincuenta por ciento) de descuento en el pago de los derechos estipulados en este apartado C.- del presente artículo para lo cual se realizará estudio socioeconómico por medio de la Dirección de matrimonio, no aplicando este beneficio sobre el cobro del 3% mensual que se aplica en caso de no revalidar durante los meses de enero a marzo.\nD.- VENTA DE PRODUCTOS (EN MOVIMIENTO) EN ESPACIOS PÚBLICOS.\n1).- En parques, playas, jardines y plazas destinadas al esparcimiento.................. 12.29 UMA\nPOR MES\nE.- MÚSICOS AMBULANTES CON FINES DE LUCRO.\n1).- En parques, playas, jardines y plazas destinadas al esparcimiento.................. 12.29 UMA\nPOR MES\nF.- ARRENDAMIENTO DE ESPACIOS PÚBLICOS EN PARQUES, PLAYAS,\nJARDINES Y PLAZAS DESTINADAS AL ESPARCIMIENTO.\na).- Elaboración y venta de alimentos, productos y bebidas sin graduación alcohólica (puestos fijos)...................................... 24.00 UMA\nPOR MES\nApoyo del 50% a personas con discapacidad y a adultos mayores.\nb).- Eventos especiales sin fines recaudatorios o de lucro (exposiciones, muestras musicales).................................. 4.86 UMA\nPOR DÍA b.1).- Eventos especiales sin fines recaudatorios o de lucro (exposiciones, muestras musicales) con autorización de la Dirección de Bienestar Social...... 0.00 UMA\nPOR DÍA b.2).- Eventos especiales recaudatorios o de lucro, con el fin de promover la cultura local (artesanías locales).... 1.96 UMA\nPOR DÍA\nNota: Se entiende por artesanía, aquel producto creado por artesanos, siempre que la contribución producto acabado. Sus características distintivas pueden ser utilitarias, estéticas, artísticas, creativas, tradicionales, simbólicas y significativas culturalmente.\nc).- Eventos especiales con fines recaudatorios o de lucro para beneficio social (Kermeses, boteos, venta de productos).................. 7.36 UMA\nPOR DÍA\nd).- Actividades recreativas sin fines recaudatorios o de lucro (Torneos, rallys, juegos, reuniones)........................... 4.86 UMA\nPOR DÍA\ne).- Actividades recreativas de uso reiterado con fines recaudatorios o de lucro (Pinturas, manualidades, pirograbados y payasos)........ 12.29 UMA\nPOR MES\nf).- Actividades recreativas de uso reiterado con fines de lucro (Renta de carritos de tracción eléctrica, vehículos eléctricos o de gasolina, bicicletas, inflables (brincolines), sombrillas y mesas).......................... 33.75 UMA\nPOR SEMANA\ng).- Uso de espacios habilitados para estacionamiento temporal por evento a actividad especial (Playa Municipal)......... 0.49 UMA\nPOR VEHÍCULO\nh).- Acampado en áreas destinadas para tal fin.... 1.35 UMA\nPOR PERSONA\ni).- Renta por día del parque..................... 27.00 UMA\nCAPÍTULO III\nINFORMACIÓN:\nARTÍCULO 31.- Los servicios que presta la Unidad de Transparencia y\nAcceso a la Información, por la expedición y reproducción de la información solicitada, será pagada por los solicitantes, de acuerdo a lo siguiente:\nUNIDAD DE MEDIDA Y\nACTUALIZACIÓN VIGENTE\na) Copia simple por hoja (después de la copia número\n21).............................................. 0.03 UMA\nb) Copia certificada por hoja........................ 0.20 UMA\nCAPÍTULO IV\nSERVICIOS QUE PRESTA LA DIRECCIÓN DE BIENESTAR SOCIAL, A TRAVÉS DE:\n1.- COORDINACIÓN SERVICIOS MÉDICOS MUNICIPALES\nARTÍCULO 32.- Los servicios que presta la Dirección de Bienestar\nSocial a través de la Coordinación Servicios Médicos Municipales se regirán bajo la siguiente:\nUNIDAD DE MEDIDA Y\nACTUALIZACIÓN VIGENTE\nA).- Consulta médica y psicológica en servicios médicos:\nA.1).- Consulta médica general................ $50.00 pesos\nA.2).- Consulta psicológica (en caso de contar con el servicio)....................... $100.00 pesos\nA.3).- Control de embarazo, peso, talla, chequeo del foco fetal................. $50.00 pesos\nA.4).- Control del niño sano (peso y talla)... $50.00 pesos\nA.5).- Oximetría.............................. $10.00 pesos\nA.6).- Toma de presión arterial............... $10.00 pesos\nA.7).- Aplicación de inyección (no incluye material).............................. $10.00 pesos\nA.8).- Prueba para detectar niveles de azúcar. $20.00 pesos\nA.9).- Lavado ótico (cada oído)............... $50.00 pesos\nA.10).- Retiro de puntos (incluye material).... $50.00 pesos por cada punto\nA.11).- Retiro de sonda........................ $50.00 pesos\nA.12).- Extracción de uña enterrada............ $150.00 pesos por uña\nA.13).- Nebulizaciones (adultos y niños) no incluye material....................... $100.00 pesos\nA.14).- Curaciones............................. $50.00 pesos\nA.15).- Sutura (incluye material).............. $50.00 pesos cada punto\nA.16).- Aplicación de suero multivitamínico.... $500.00 pesos\nA.17).- Consulta de nutrición.................. $150.00 pesos\nB).- Registro en Servicio Médico:\nB.1).- Registro en servicio médico, nuevo ingreso y reingreso.................... $150.00 pesos\nB.2).- Registro en servicio médico, usuario regular................................ $100.00 pesos\nB.3).- Registro en servicio médico, usuario irregular.............................. $250.00 pesos\nC).- Expedición y reposición de tarjeta de salud:\nC.1).- Expedición de tarjeta de salud, nuevo ingreso y reingreso.................... $200.00 pesos\nC.2).- Reposición de tarjeta de salud, regular................................ $200.00 pesos\nC.3).- Reposición de tarjeta de salud, irregular.............................. $350.00 pesos\nD).- Certificados Médicos de Salud:\nD.1).- Certificados médicos de salud: para estudiantes, adultos mayores y población vulnerable............................. $50.00 pesos\nD.2).- Certificado Médico de Esencia a conductores bajo el influjo del Alcohol, Psicotrópicos o Enervantes; sólo cuando el resultado sea positivo.............. $1,050.00 pesos\nD.3).- Certificado médico para licencia, empleo, integridad física, antidoping y pasaporte.............................. $80.00 pesos\nSe exentará del cobro de todos los incisos anteriores, tratándose de personas que no cuenten\nPública y exista notoria falta de recursos económicos, lo cual deberá sustentarse con el estudio socioeconómico que se le practique.\nE).- Resguardo de animales, en el Centro de Atención\nCanino y Felino:\nE.1).- Vacunación antirrábica................... EXENTO\nE.2).- Alimentación y resguardo de caninos capturados por día....................... 2.50 UMA\nE.3).- Consulta médica veterinaria............... 1.50 UMA\nE.4).- Tratamiento o desparasitación............. 2.00 UMA\nE.5).- Eutanasia humanitaria y traslado.......... 2.50 UMA\nE.6).- Recepción de cadáveres canino y felino... 1.50 UMA\nE.7).- Esterilización y vacunación de caninos y felinos, dados en adopción............... 4.00 UMA\nE.8).- Observación clínica de caninos agresores................................ 10.00 UMA\nE.9).- Certificado Médico (caninos y felinos)... 2.00 UMA\nE.10).- Esterilizaciones caninas y felinas........ 4.00 UMA\nSe exentará del cobro de todos los incisos anteriores, cuando el usuario compruebe su vulnerabilidad, lo cual deberá sustentarse con el estudio socioeconómico que se le practique.\nF).- Multas por infracciones menores a disposiciones de la Coordinación Servicios Médicos Municipales..... 1.00 HASTA\n100.00 UMA\nG).- Multas por infracciones mayores a disposiciones de la Coordinación Servicios Médicos Municipales.... 100.00 HASTA\n300.00 UMA\nCAPÍTULO V\nCOORDINACIONES.\nARTÍCULO 33.- Los servicios que presta la Dirección de Administración\nUrbana, se pagarán conforme a la siguiente:\nUNIDAD DE MEDIDA Y ACTUALIZACIÓN (UMA) VIGENTE\nI.- POR REVISIÓN Y ANÁLISIS PARA LA EXPEDICIÓN DE PERMISOS Y/O\nLICENCIAS PARA CONSTRUCCIÓN, AMPLIACIÓN, RECONSTRUCCIÓN, TRASLADO O\nDEMOLICIÓN DE INMUEBLES.\nA.- Para construcción, reconstrucción, ampliación y remodelación de edificios habitacionales, construcción, de acuerdo a la siguiente tabla:\n1.- Casa habitación y vivienda de interés social unifamiliares, tratándose de inmuebles construidos sin fines de comercialización ni de arrendamiento.\n1.1.- Casa Habitación nueva con superficie de:\na).- Hasta 60 m²..................... 0.15 UMA\nb).- Más de 60 hasta 180 m².......... 0.29 UMA\nc).- Más de 180 m²................... 0.37 UMA\nd).- Vivienda multifamiliar hasta 180 m².............................. 0.27 UMA\n2.- Ampliación de casa habitación por metro cuadrado:\n2.1.- Hasta 180 m²......................... 0.27 UMA\n2.2.- Mayor de 180 m²...................... 0.34 UMA\n3.- Otras Edificaciones e Instalaciones:\n3.1.- Otras construcciones diferentes a casa habitación construcción o ampliación:\na).- Hasta 60 m²..................... 0.20 UMA\nb).- Más de 60 hasta de 200 m²....... 0.27 UMA\nc).- Más de 200 hasta 500 m²......... 0.29 UMA\nd).- Más de 500 m²................... 0.37 UMA\n3.2.- Habitacionales, unifamiliares y multifamiliares con fines de comercialización y/o arrendamiento, por unidad de vivienda:\na).- Vivienda de interés social de hasta 38m²...................... 0.14 UMA\nb).- Mayor de 38 m² hasta 180 m²..... 0.27 UMA\nc).- Mayor de 180 m²................. 0.34 UMA\n3.3.- Instalación de casa móvil............ 0.20 UMA\nLicencia de construcción provisional:\na).- Hasta 100 m².................... 0.14 UMA\nb).- Más de 100 m²................... 0.17 UMA\n3.4.- Permiso de instalación de línea o red de agua potable, para uso agrícola, drenaje sanitario o drenaje pluvial por km o fracción, incluye demolición........................... 20.25 UMA\n3.5.- Construcción o conexión a pozo de visita, construcción de caja de válvulas y/o, registros para línea de agua potable o drenaje sanitario, instalación de descarga sanitaria o toma de agua potable. Por unidad\n(incluye demolición)................. 2.03 UMA\n3.6.- Permiso para construcción de carpeta de pavimento asfáltico y concreto hidráulico, a particulares por m².\nIncluye demolición................... 0.07 UMA\n4.- Bardas y cercos, muros de contención:\n4.1.- Bardas por metro lineal de construcción......................... 0.27 UMA\n4.2.- Cercos por metro lineal de construcción......................... 0.20 UMA\n4.3.- Muro de contención menor a 1.5 m de altura, por metro lineal............. 0.30 UMA\n4.4.- Muro de contención mayor a 1.5 m de altura por metro lineal.............. 0.34 UMA\n5.- Ocupación parcial de la vía pública con material, equipo o herramienta de construcción el m² por día:\n5.1.- Zona urbanizada...................... 0.34 UMA\n5.2.- Zona no urbanizada................... 0.20 UMA\n6.- Regularizaciones de construcción, ampliación, remodelación, o reconstrucción, 50% adicional al costo del trámite normal de la licencia. referentes a los numerales del 1 al 4 del\nApartado A, Fracción I.\n7.- Prórrogas:\n7.1.- Prórrogas, 25% del costo actualizado del trámite normal del permiso y/o licencia, con antigüedad máxima de un año.\n7.2.- Prórrogas, 35% del costo actualizado o del trámite normal del permiso y/o licencia, con antigüedad mayor a 1 año menor a 5 años.\n7.3.- Prórrogas, 50% del costo actualizado o del trámite normal del permiso y/o licencia, con antigüedad mayor a 5 años.\n7.4.- Casa de interés social de un nivel de hasta 38 m² de construcción, cobro del\n25% sobre el costo inicial.\n8.- Constancia de terminación de obra autorización de ocupación, 10% del costo actualizado del trámite normal de la licencia.\n8.1.- Casa de interés social de un nivel de hasta 38 m² de construcción, cobro del\n10% sobre el costo inicial.\n9.- Cambio de techo o cambio de fachada.\n9.1.- Cambio de techo, 25% del costo normal del trámite de la licencia.\n9.2.- Cambio de fachada por metro cuadrado. 0.41 UMA\n10.- Reconstrucciones, 50% del costo normal del trámite de la licencia.\n11.- La obra pública estará exenta del pago de los derechos por los permisos que se establecen en este Artículo, en todos los casos la entidad ejecutora deberá notificar previamente a la\nDirección de Administración Urbana, las especificaciones técnicas y proyecto a realizar.\n12.- Remodelación, 25% del costo normal del permiso y/o licencia.\n13.- Construcción de fosa séptica, cisterna, tanque de almacenamiento, superficial o subterráneo, por m³....................................... 0.27 UMA\n14.- Construcción de alberca por m³:\n14.1.- Casa habitación..................... 2.70 UMA\n14.2.- Otros............................... 4.73 UMA\n15.- Construcción y/o instalación de antena (torre) de altura.................................... 8.70 UMA\n16.- Licencia de construcción y/o instalación de torre para anuncio espectacular por metro lineal de altura............................. 8.10 UMA\n17.- Regularizaciones de construcción, ampliación, remodelación, demolición o reconstrucción, 200% adicional al costo del trámite normal de la licencia. Referentes a los numerales 15 y\n16 del Apartado A, Fracción I.\nB.- Para demolición parcial o total de inmuebles se pagará de acuerdo a las siguientes cuotas:\n1.- Demolición de inmuebles más de 16m², por metro cuadrado.................................... 0.14 UMA\n2.- Bardas por metro cuadrado................... 0.14 UMA\n3.- Demolición cordón banqueta, por metro lineal. 1.35 UMA\n4.- Demolición de banquetas, por metro cuadrado.. 1.35 UMA\n5.- Demolición de torre para anuncio espectacular, por metro lineal de altura................... 2.70 UMA\nC.- Revisión previa de anteproyectos.\n1.- Anteproyecto de casa habitación:\n1.1.- De 1 hasta 100 m².................... 6.75 UMA\n1.2.- De 101 hasta 500 m².................. 9.45 UMA\n1.3.- De 501 hasta 1,000 m²................ 12.15 UMA\n1.4.- Más de 1,000 m²...................... 14.85 UMA\n2.- Anteproyecto de otras construcciones:\n2.1.- De 1 hasta 100 m².................... 10.80 UMA\n2.2.- De 101 hasta 500 m².................. 13.50 UMA\n2.3.- Más de 500 m²........................ 22.95 UMA\nD.- Gastos de notificación............................ 2.18 UMA\n1.- Gastos de ejecución 10% del monto del adeudo.\n2.- Denuncia ciudadana........................... 1.35 UMA\nE.- Derechos de registro como responsable y/o corresponsable de obras, el pago se realiza al iniciar el trámite.\n1.- Registro inicial............................. 10.13 UMA\n2.- Revalidación anual (peritos sin trámites pendientes)................................. 8.70 UMA\n3.- Revalidación anual (peritos con trámites inconclusos, con más de 40 días de antigüedad.................................. 10.88 UMA\n4.- Por cambio de responsable director de obra... 2.70 UMA\nF.- Movimientos de tierra:\n1.- Hasta 200 m³ dentro del centro de población.. 6.75 UMA\n2.- Dentro del centro de población:\n2.1.- De 201 a 500 m³...................... 33.75 UMA\n2.2.- De 501 a 2,000 m³.................... 67.50 UMA\n2.3.- De 2,001 a 5,000 m³.................. 101.25 UMA\n2.4.- De 5,001 a 10,000 m³................. 135.00 UMA\n2.5.- Por m³ de volumen excedente a 10,000 m³ dentro del centro de población....... 0.013 UMA\n3.- Hasta 200 m³ fuera del centro de población... 4.05 UMA\n4.- Fuera del centro de población:\n4.1.- De 201 a 500 m³...................... 31.05 UMA\n4.2.- De 501 a 2,000 m³.................... 64.80 UMA\n4.3.- De 2,001 a 5,000 m³.................. 98.55 UMA\n4.4.- De 5,001 a 10,000 m³................. 132.30 UMA\n4.5.- Por m³ de volumen excedente a 10,000 m³ fuera del centro de población........ 0.007 UMA\n5.- Regularización de movimientos de tierra, 50% adicional al costo de trámite normal de la licencia referente a los numerales del 1 al 4, del Apartado F, Fracción I.\n6.- Prórroga de movimientos de tierra 50% del costo actualizado de trámite normal de la licencia referente a los numerales del 1 al 4, del Apartado F, Fracción I.\nG.- Certificación de planos autorizados, adicionales a refiere el Apartado A, por cada juego adicional.\nDebiendo realizar el pago al iniciar el trámite.\n1.- Por juego de hasta 25 planos................. 2.03 UMA\n2.- Por juego de más de 25 planos................ 5.40 UMA\nH.- Modificación de proyecto autorizado 10% el costo actualizado del trámite normal de la licencia. Para licencias vigentes.\n1.- Modificación de proyecto autorizado, 45% del costo actualizado del trámite normal con antigüedad menor a 5 años.\n2.- Modificación de proyecto autorizado, 60% del costo actualizado del trámite normal con antigüedad mayor a 5 años.\nI.- Factibilidad de licencia de construcción, revisión y análisis de prototipo de vivienda:\n1.- Hasta por 180 m²............................. 4.05 UMA\n2.- Mayor de 180 m².............................. 6.75 UMA\nJ.- Por suspensión temporal, por la reactivación de licencia de obra, o constancia de requerimiento o no licencia de construcción....................... 1.35 UMA\nK.- Por aprobación de prototipo de vivienda:\n1.- Hasta 180 m²................................. 10.80 UMA\n2.- Mayor de 180 m².............................. 16.20 UMA\nL.- Por revisiones subsecuentes a la segunda revisión. Se paga al ingresar documentos por revisión:\n1).- Por la tercera revisión...................... 1.35 UMA\n2).- Por revisiones subsecuentes a partir de la cuarta revisión.............................. 2.70 UMA\nII.- POR ANÁLISIS DE DESARROLLOS URBANOS:\nA.- Por análisis y emisión de dictamen sobre uso del suelo para el desarrollo urbano de predios, se pagará por dictamen:\n1.- De terrenos ubicados dentro de los límites del centro de la población de la cabecera municipal................................... 54.00 UMA\n1.1.- Los fraccionamientos tipo interés social progresivo tendrán un 50% de descuento de estas cuotas. Siempre y cuando los urbanizadores sean instituciones gubernamentales.\n1.2.- Los fraccionamientos o asentamientos humanos que sean previamente clasificados como TIPO POPULAR y que sean notificados por el Instituto\nNacional del Suelo Sustentable (INSUS) en proceso de regularización del suelo con base en el convenio de colaboración con el Municipio de San\nQuintín, B.C., durante el periodo de su vigencia estarán exentos del pago de los conceptos de este apartado... 0.00 UMA\n2.- De terrenos ubicados dentro de los límites de los centros de población de los poblados..... 81.00 UMA\n2.1.- Los fraccionamientos tipo interés social progresivo tendrán un 50% de descuento de estas cuotas. Siempre y cuando los urbanizadores sean instituciones gubernamentales.\n2.2.- Los fraccionamientos o asentamientos humanos que sean previamente clasificados como TIPO POPULAR y que sean notificados por el Instituto\nNacional del Suelo Sustentable (INSUS) en proceso de regularización del suelo con base en el convenio de colaboración con el Municipio de San\nQuintín, B.C., durante el periodo de su vigencia estarán exentos del pago de los conceptos de este apartado.... 0.00 UMA\n3.- De terrenos ubicados dentro del área de aplicación de la zona natural protegida..... 81.00 UMA\n3.1.- Los fraccionamientos tipo interés social progresivo tendrán un 50% de descuento de estas cuotas. Siempre y cuando los urbanizadores sean instituciones gubernamentales.\n3.2.- Los fraccionamientos o asentamientos humanos que sean previamente clasificados como TIPO POPULAR y que sean notificados por el Instituto\nNacional del Suelo Sustentable (INSUS) en proceso de regularización del suelo con base en el convenio de colaboración con el Municipio de San\nQuintín, B.C., durante el periodo de su vigencia estarán exentos del pago de los conceptos de este apartado.... 0.00 UMA\n4.- De terrenos ubicados fuera de los límites de los centros de población.................... 81.00 UMA\n4.1.- Los fraccionamientos tipo interés social progresivo tendrán un 50% de descuento de estas cuotas. Siempre y cuando los urbanizadores sean instituciones gubernamentales.\n4.2.- Los fraccionamientos o asentamientos humanos que sean previamente clasificados como TIPO POPULAR y que sean notificados por el Instituto\nNacional del Suelo Sustentable (INSUS) en proceso de regularización del suelo con base en el convenio de colaboración con el Municipio de San\nQuintín, B.C., durante el periodo de su vigencia estarán exentos del pago de los conceptos de este apartado.... 0.00 UMA\n5.- Centros de apuestas, apuestas remotas, salas de sorteos de números y/o casinos, libro foráneo y similares:\n5.1.- Hasta 3,000 m² de superficie............ 675.00 UMA\n5.2.- De 3,001 m² de terreno en adelante..... 1,012.50 UMA\n5.3.- A las cuotas indicadas se les acumulará por cada kilómetro de distancia al centro de población de la cabecera municipal.............................. 2.16 UMA\nB.- Por análisis de anteproyecto de fraccionamiento se pagará por la superficie total en la forma siguiente:\n1.- En terrenos ubicados dentro de los centros de población:\n1.1.- Hasta de cinco hectáreas............. 101.25 UMA\n1.2.- Los fraccionamientos tipo interés social progresivo tendrán un 50% de descuento de estas cuotas, siempre y cuando los urbanizadores sean instituciones gubernamentales.\n1.3.- Por cada hectárea, excedente de cinco hectáreas............................ 8.10 UMA\n1.4.- Los fraccionamientos tipo interés social progresivo tendrán un 50% de descuento de estas cuotas, siempre y cuando los urbanizadores sean instituciones gubernamentales.\n1.5.- Los fraccionamientos o asentamientos humanos que sean previamente clasificados como TIPO POPULAR y que sean notificados por el Instituto\nNacional del Suelo Sustentable (INSUS) en proceso de regularización del suelo con base en el convenio de colaboración con el Municipio de San\nQuintín, B.C. durante el periodo de su vigencia estarán exentos del pago de los conceptos de este apartado.... 0.00 UMA\n2.- En terrenos ubicados dentro del área de la zona natural protegida:\n2.1.- Hasta de cinco hectáreas............. 121.50 UMA\n2.2.- Los fraccionamientos tipo interés social progresivo tendrán un 50% de descuento de estas cuotas, siempre y cuando los urbanizadores sean instituciones gubernamentales.\n2.3.- Por cada hectárea, excedente de cinco hectáreas o fracción adicional....... 9.45 UMA\n2.4.- Los fraccionamientos tipo interés social progresivo tendrán un 50% de descuento de estas cuotas, siempre y cuando los urbanizadores sean instituciones gubernamentales.\n2.5.- Los fraccionamientos o asentamientos humanos que sean previamente clasificados como TIPO POPULAR y que sean notificados por el Instituto\nNacional del Suelo Sustentable (INSUS) en proceso de regularización del suelo con base en el convenio de colaboración con el Municipio de San\nQuintín, B.C. durante el periodo de su vigencia estarán exentos del pago de los conceptos de este apartado.... 0.00 UMA\n3.- En terrenos ubicados fuera de los límites de los centros de población:\n3.1.- Hasta de cinco hectáreas............. 141.75 UMA\n3.2.- Los fraccionamientos tipo interés social progresivo tendrán un 50% de descuento de estas cuotas, siempre y cuando los urbanizadores sean instituciones gubernamentales.\n3.3.- Por cada hectárea, excedente de cinco hectáreas o fracción adicional....... 8.10 UMA\n3.4.- Los fraccionamientos tipo interés social progresivo tendrán un 50% de descuento de estas cuotas, siempre y cuando los urbanizadores sean instituciones gubernamentales.\n3.5.- Los fraccionamientos o asentamientos humanos que sean previamente clasificados como TIPO POPULAR y que sean notificados por el Instituto\nNacional del Suelo Sustentable (INSUS) en proceso de regularización del suelo con base en el convenio de colaboración con el Municipio de San\nQuintín, B.C. durante el periodo de su vigencia estarán exentos del pago de los conceptos de este apartado.... 0.00 UMA\n4.- Para acciones de urbanización por incorporación o reincorporación municipal:\n4.1.- En terrenos ubicados dentro de los centros de población:\na).- Hasta de cinco hectáreas....... 60.75 UMA\nb).- Los fraccionamientos tipo interés social progresivo tendrán un 50% de descuento de estas cuotas, siempre y cuando los urbanizadores sean instituciones gubernamentales.\nc).- Por cada hectárea excedente de cinco hectáreas o fracción adicional...................... 6.08 UMA\nd).- Los fraccionamientos tipo interés social progresivo tendrán un 50% de descuento de estas cuotas, siempre y cuando los urbanizadores sean instituciones gubernamentales.\n4.2.- En terrenos ubicados fuera de los límites de los centros de población:\na).- Hasta de cinco hectáreas........ 101.25 UMA\nb).- Los fraccionamientos tipo interés social progresivo tendrán un 50% de descuento de estas cuotas, siempre y cuando los urbanizadores sean instituciones gubernamentales.\nc).- Por cada hectárea excedente de cinco hectáreas o fracción adicional...................... 8.10 UMA\nd).- Los fraccionamientos tipo interés progresivo tendrán un\n50% de descuento de estas cuotas, siempre y cuando los urbanizadores sean instituciones gubernamentales.\nC.- Por análisis de proyecto de fraccionamientos, habitacionales, comerciales, industriales o mixtos, nuevos o modificaciones a proyectos aprobados que requieran de un nuevo dictamen, se pagará por superficie fraccionada en la forma siguiente:\n1.- Hasta cinco hectáreas........................ 121.50 UMA\n2.- Los fraccionamientos tipo interés social progresivo tendrán un 50% descuento de estas cuotas, siempre y cuando los urbanizadores sean instituciones gubernamentales.\n3.- Por cada hectárea excedente de cinco hectáreas o fracción adicional............. 16.20 UMA\n4.- Los fraccionamientos tipo interés social progresivo tendrán un 50% de descuento de estas cuotas, siempre y cuando los urbanizadores sean instituciones gubernamentales.\n5.- Los fraccionamientos o asentamientos humanos que sean previamente clasificados como TIPO\nPOPULAR y que sean notificados por el\nInstituto Nacional del Suelo Sustentable\n(INSUS) en proceso de regularización del suelo\nMunicipio de San Quintín, B.C., durante el periodo de su vigencia estarán exentos del pago de los conceptos de este apartado...... 0.00 UMA\nD.- Para acciones de urbanización por incorporación o reincorporación municipal:\n1.- Hasta cinco hectáreas........................ 108.00 UMA\n2.- Los fraccionamientos tipo interés social progresivo tendrán un 50% de descuento de estas cuotas, siempre y cuando los urbanizadores sean instituciones gubernamentales.\n3.- Por cada hectárea excedente de cinco hectáreas o fracción adicional............. 13.50 UMA\n3.1.- Los fraccionamientos tipo interés social progresivo tendrán un 50% de descuento de estas cuotas, siempre y cuando los urbanizadores sean instituciones gubernamentales.\nE.- Por análisis de proyectos de fraccionamientos tipo granjas, nuevos o modificaciones a proyectos que requieran de un nuevo dictamen se pagará por superficie fraccionada o proyectada en la forma siguiente:\n1.- Hasta cinco hectáreas........................ 101.25 UMA\n2.- Los fraccionamientos tipo interés social progresivo tendrán un 50% de descuento de estas cuotas, siempre y cuando los urbanizadores sean instituciones gubernamentales.\n3.- Por cada hectárea excedente de cinco hectáreas o fracción adicional............. 9.45 UMA\n4.- Los fraccionamientos tipo interés social progresivo tendrán un 50% de descuento de estas cuotas, siempre y cuando los urbanizadores sean instituciones gubernamentales.\nF.- Para acciones de urbanización por incorporación o reincorporación municipal:\n1.- Hasta cinco hectáreas........................ 60.75 UMA\n2.- Los fraccionamientos tipo interés social progresivo tendrán un 50% de descuento de estas cuotas, siempre y cuando los urbanizadores sean instituciones gubernamentales.\n3.- Por cada hectárea excedente de cinco hectáreas o fracción adicional.............. 6.08 UMA\n4.- Los fraccionamientos tipo interés social progresivo tendrán un 50% de descuento de estas cuotas, siempre y cuando los urbanizadores sean instituciones gubernamentales.\nG.- Relotificación, subdivisión o fusión de lotes urbanos:\n1.- Por la recepción de trámite de relotificación, subdivisión o fusión de predios, dentro o fuera del límite del centro de población.... 4.05 UMA\n2.- Por relotificación de manzanas y certificación de la memoria descriptiva, por cada lote resultante.................................. 16.20 UMA\n3.- Por subdivisión o fusión de lotes urbanos y certificación de memoria descriptiva de los mismos, por cada lote fusionado o lote resultante de la subdivisión, se pagará:\n3.1.- En baldíos........................... 14.49 UMA\n3.2.- En construidos....................... 17.39 UMA\n4.- Estará exenta la subdivisión, previo estudio\nSocial, tratándose de deslinde familiares.\n5.- Para los predios en fraccionamientos o asentamientos humanos que sean previamente clasificados como TIPO POPULAR y que sean notificados por el Instituto Nacional del\nSuelo Sustentable (INSUS) en proceso de regularización del suelo con base en el convenio de colaboración con el Municipio de\nSan Quintín, B.C., durante el periodo de su vigencia estarán exentos del pago de los conceptos de este apartado................... 0.00 UMA\nH.- Por división de predios rústicos dentro o fuera de los límites de los centros de población que no requieran apertura de calles, por cada fracción resultante....................................... 33.75 UMA\nI.- Por división de predios rústicos para uso agropecuario que no requieran apertura de calle, por cada fracción resultante...................... 33.75 UMA\nJ.- Por división de predios rústicos, ubicados dentro del área natural protegida y zonas costeras...... 33.75 UMA\nK.- Por división de predios rústicos, ubicados dentro del área o zona natural protegida y Vitivinícolas de la Zona Norte del Municipio de San Quintín (región del Vino), B.C.................................... 40.50 UMA\nL.- Por división de predio derivado de un juicio de dentro de otro mayor (por fracción)............... 135.00 UMA\nM.- Por cancelación de división de predios, fusión, relotificación y régimen en condominio............ 10.80 UMA\nN.- Por oficio rectificatorio de memorias de régimen de condominios, de división de predios, fusión y relotificación................................... 13.50 UMA\nApartados A, B, C y D, de la Fracción II, los hará trámite, según notificación en la Dirección de\nAdministración Urbana.\nFracción II, se hará previa notificación en la\nDirección de Administración Urbana.\nIII.- POR URBANIZACIÓN:\nA.- Por supervisión de obras de urbanización realizadas con base en el proyecto de obras, se pagará sobre el importe total de los presupuestos presentados.. 3.00%\nLos fraccionamientos tipo interés social progresivo tendrán un 50% de descuento de estas cuotas, siempre y cuando los urbanizadores sean instituciones gubernamentales.\nB.- Por supervisión de obras de urbanización en modificaciones a proyectos aprobados con base en el proyecto de obras actual, se pagará sobre el importe total de los presupuestos presentados..... 3.00%\nLos fraccionamientos tipo interés social progresivo tendrán un 50% de descuento de estas cuotas, siempre y cuando los urbanizadores sean instituciones gubernamentales.\nC.- Por modificación al Acuerdo de fraccionamientos urbanizador y/o nombre del fraccionamiento........ 675.00 UMA tendrán un 50% de descuento de estas cuotas, siempre y cuando los urbanizadores sean instituciones gubernamentales.\nD.- Por el dictamen de recepción de fraccionamientos, realizado con base en el proyecto de obra de obra............................................. 4.05 AL\nMILLAR\nE.- Por la revisión de proyecto y recepción de redes de alumbrado público de fraccionamientos, pagará por luminaria........................................ 1.35 UMA\nF.- Prórroga de permiso de fraccionamiento por 2 años............................................. 94.50 UMA\nG.- Multa por no haber solicitado prórroga del fraccionamiento en tiempo, por cada 2 años a partir de la fecha de publicación del acuerdo de autorización del fraccionamiento en el Periódico\nOficial del Estado de Baja\nCalifornia....................................... 135.00 UMA\nH.- Multa por iniciar cualquier acción de urbanización tipo fraccionamiento, colonia, calles o lotificaciones sin contar con los permisos y/o licencias correspondientes:\n1.- Con superficie de hasta 5 hectáreas.......... 270.00 UMA\n2.- Por cada hectárea excedente de las primeras 5 hectáreas................................... 81.00 UMA\nEl pago de la Fracción III, a que se refieren los una vez aprobados los proyectos, previa e Infraestructura, en ambos casos los proyectos\nQuintín, Baja California quien otorgará la autorización definitiva.\nEn el caso de no enterar los derechos correspondientes en el área de Recaudación, en un notificación, se suspenderá el trámite correspondiente.\nIV.- POR CERTIFICACIÓN DE MEMORIAS DESCRIPTIVAS\nA.- Por verificación y certificación de memorias descriptivas de lotes pertenecientes a fraccionamientos, se pagará por cada revisión, en la forma siguiente:\n1.- Hasta 100 lotes.............................. 72.47 UMA\n2.- Por cada lote que exceda de 100 lotes........ 1.45 UMA\n3.- Para los predios ubicados en fraccionamientos o asentamientos humanos que sean previamente clasificados como TIPO POPULAR y que sean notificados por el Instituto Nacional del\nSuelo Sustentable (INSUS) en proceso de regularización del suelo con base en el convenio de colaboración con el Municipio de\nSan Quintín, B.C., durante el periodo de su vigencia estarán exentos del pago de los conceptos de esta fracción................... 0.00 UMA\nV.- POR ANÁLISIS DE PREDIO PARA FACTIBILIDAD LAS AUTORIDADES DE LOS\nDE ESTA FRACCIÓN, ASÍ COMO LAS INSTITUCIONES EDUCATIVAS Y\nASOCIACIONES DE LA SOCIEDAD CIVIL SIN FINES DE LUCRO.\nA.- Por análisis y emisión de factibilidad de uso de suelo por verificación de:\n1.- Compatibilidad.............................. 5.08 UMA\n2.- Congruencia por superficie de operación y construcción:\n2.1 Hasta 200.00 m2...................... 9.43 UMA\n2.2 De 200.01 m2 hasta 1,000.00 m2........ 11.31 UMA\n2.3 Más de 1,000.00 m²................... 13.57 UMA\n3.- Congruencia en zona federal.................. 11.59 UMA\n4.- Congruencia temporal......................... 9.43 UMA\n5.- Congruencia para giros ingresados por el\nSistema de Apertura Rápida de Empresas (SARE), hasta por 200 m² de construcción (aplica solo para permisos de operación).................. 0.00 UMA\n6. Por la tercera revisión..................... 1.35 UMA\nSe paga al ingresar documentos por revisión.\n7. Por revisiones subsecuentes a partir de la cuarta revisión............................. 2.70 UMA\nSe paga al ingresar documentos por revisión.\nVI.- POR ANÁLISIS DEL SUELO Y USO DE EDIFICIO: LAS AUTORIDADES DE\nLOS TRES ÓRDENES DE GOBIERNO ESTARÁN EXENTAS DE PAGO DE LOS CONCEPTOS\nDE ESTA FRACCIÓN, ASÍ COMO LAS INSTITUCIONES EDUCATIVAS Y\nASOCIACIONES DE LA SOCIEDAD CIVIL SIN FINES DE LUCRO.\na).- Por análisis de dictamen de uso de edificaciones.\n1.- En zonas habitacionales: Construcción de viviendas multifamiliares, condominios, departamentos:\n1) Hasta 100 m² de operación............... 24.30 UMA\n2) Mayor de 100 m² hasta 500 m² de operación............................... 27.00 UMA\n3) Mayor de 500 m² hasta 1,000 m² de operación.............................. 40.50 UMA\n4) Mayor de 1,000 m² hasta 5,000 m² de operación.............................. 60.75 UMA\n5) Mayor de 5,000 m² de operación.......... 81.00 UMA\n2.- En equipamiento y servicios.\nA.- Comercio: Abastos y almacenaje al por menor: depósitos de productos básicos, de materiales de construcción, maquinaria, vehículos, tianguis, saldos, segundas y otros, así como talleres de recepción y servicio, no considerados como de uso industrial.\n1) Hasta 500 m² de operación.......... 27.00 UMA\n2) Mayor de 500 m² hasta 1,000 m² de operación......................... 33.75 UMA\n3) Mayor de 1,000 m² hasta 5,000 m² de operación......................... 47.25 UMA\n4) Mayor de 5,000 m² de operación..... 60.75 UMA\nA.1.- Centro comercial, tiendas de autoservicio y departamentos, tiendas DICONSA, comercio alimenticio; comercio especializado, tiendas institucionales, supermercados.\n1) Hasta 50 m² de operación... 24.30 UMA\n2) Mayor de 50 m² hasta 100 m² de operación.............. 25.65 UMA\n3) Mayor de 100 m² hasta 500 m² de operación........... 29.70 UMA\n4) Mayor de 500 m² hasta 1,000 m² de operación........... 37.80 UMA\n5) Mayor de 1,000 m² hasta\n5,000 m² de operación...... 51.30 UMA\n6) Mayor de 5,000 m² de operación................. 81.00 UMA\nA.2).- Por uso de suelo: Almacenaje, depósito y/o acopio mayor, superficie para zonas de carga y descarga, depósitos mayores para almacenaje o acopio de sal, minerales, arena, grava y otros materiales en general:\n1) De 0 a 500 m² de superficie 2.70 UMA por tonelada anualmente\n2) De 501 a 1,000 m² de superficie................ 2.03 UMA por tonelada anualmente\n3) De 1,001 a 5,000 m² de superficie................ 1.35 UMA por tonelada anualmente\n4) De 5,001 a 10,000 m² de superficie................ 0.68 UMA por tonelada anualmente\n5).- De 10,001 en adelante...... 0.34 UMA por tonelada anualmente\nB.- Educación y Cultura.\nPreescolar, elemental, medio básico, medio superior, instalaciones de investigación y superior, museos, bibliotecas y hemerotecas e instalaciones religiosas:\n1) Hasta 500 m² de operación.......... 13.50 UMA\n2) Mayor de 500 m² hasta 1,000 m² de operación......................... 14.85 UMA\n3) Mayor de 1,000 m² hasta 5,000 m² de operación....................... 16.88 UMA\n4) Mayor de 5,000 m² de operación... 21.60 UMA\nC.- Salud y servicios asistenciales, hospitales, clínicas, centros de salud o consultorios, asistencia consultorios, asistencia social y asistencia para animales:\n1) Hasta 50 m² de operación........... 22.95 UMA\n2) Mayor de 50 m² hasta 100 m² de operación......................... 25.65 UMA\n3) Mayor de 100 m² hasta 500 m² de operación......................... 29.03 UMA\n4) Mayor de 500 m² hasta 1,000 m² de operación......................... 36.45 UMA\n5) Mayor de 1,000 m² hasta 5,000 m² de operación....................... 49.95 UMA\n6) Mayor de 5,000 m² de operación..... 72.90 UMA\n7) En los casos que sean para edificaciones que no persigan fines de lucro se cobrará el 50%.\nD.- Deporte y recreación, parques y jardines: unidades deportivas, clubes y centros deportivos; plazas, zoológicos y balnearios públicos:\n1) Hasta 1,000 m² de operación........ 24.98 UMA\n2) Mayor de 1,000 m² hasta 5,000 m² de operación....................... 29.70 UMA\n3) Mayor de 5,000 m² hasta 10,000 m² de operación....................... 34.43 UMA\n4) Mayor de 10,000 m² de operación.... 43.88 UMA\n5) En los casos que sean para edificaciones que no persigan fines de lucro se cobrará el 50%.\nE.- Servicios administrativos, administración pública y privada:\n1) Hasta 50 m² de operación........... 22.95 UMA\n2) Mayor de 50 m² hasta 100 m² de operación......................... 25.65 UMA\n3) Mayor de 100 m² hasta 500 m² de operación......................... 29.03 UMA\n4) Mayor de 500 m² hasta 1,000 m² de operación....................... 36.45 UMA\n5) Mayor de 1,000 m² de operación..... 49.95 UMA\nF.- Turismo, alojamiento (hoteles y moteles), agencias de viajes, centros vacacionales.\n1) Hasta 1,000 m² de operación....... 27.00 UMA\n2) Mayor de 1,000 m² hasta 5,000 m² de operación....................... 29.70 UMA\n3) Mayor de 5,000 m² hasta 10,000 m² de operación....................... 36.45 UMA\n4) Mayor de 10,000 m² de operación.... 60.75 UMA\nG.- Servicios mortuorios, cementerios; mausoleos y crematorios, agencias de inhumaciones funerarias:\n1) Hasta de 10,000 m² de operación.... 28.35 UMA\n2) Mayor de 1 hasta 10 hectáreas de operación......................... 33.75 UMA\n3) Mayor de 10 hasta 20 hectáreas de operación....................... 41.18 UMA\n4) Mayor de 20 hectáreas de operación. 57.38 UMA\nH.- Comunicaciones y transportes, T.V. y radio, telecomunicaciones, correos, telefonía, terminal de transporte urbano\n(autobús), terminal de transporte foráneo, terminal de ferrocarril, terminal aérea, estacionamientos y apeadero, encierro de transporte.\n1) Hasta de 1,000 m² de operación..... 24.30 UMA\n2) Mayor de 1,000 m² hasta 5,000 m² de operación....................... 27.00 UMA\n3) Mayor de 5,000 m² hasta 10,000 m² de operación...................... 31.05 UMA\n4) Mayor de 10,000 m² de operación.... 39.15 UMA\nI.- Diversión y espectáculos, cines y teatros, auditorios y estadios, centros sociales, centros nocturnos, salón de fiestas, ferias, exposiciones y circos, centros de convenciones, centros de esparcimiento:\n1) Hasta 500 m² de operación.......... 27.00 UMA\n2) Mayor de 500 m² hasta 1,000 m² de operación......................... 33.75 UMA\n3) Mayor de 1,000 m² hasta 5,000 m² de operación......................... 40.50 UMA\n4) Mayor de 5,000 m² hasta 10,000 m² de operación......................... 81.00 UMA\n5) Mayor a 10,000 m² de operación.... 108.00 UMA\nJ.- Especial, distribución de gas butano, gasolineras, centros de carburación y/o almacén de hidrocarburos, plantas, estaciones y subestaciones, plantas de tratamiento, cárcamos, bombas, rellenos sanitarios, presas, plantas desaladoras, etc.................................... 202.50 UMA\nK.- Sistema de Apertura Rápida de Empresas:\nK.1).- Dictamen de uso de suelo, para giros determinados en el\nSistema de Apertura Rápida de\nEmpresas (SARE).\n1) Hasta 50 m² de construcción 16.20 UMA\n2) Desde 51 m² hasta 100 m² de construcción............... 20.25 UMA\n3) Desde 101 m² hasta 150 m² de construcción............... 24.30 UMA\n4) Desde 151 m² hasta 200 m² de construcción............... 27.00 UMA\nb).- En Industria:\n1.- Extractiva: Explotación de minas y canteras; materiales de construcción contaminante, explosiva que genera vehículos hasta de una capacidad máxima de 14 toneladas para el transporte de materias primas y productos terminados:\n1) Hasta 1 hectárea de operación............ 175.50 UMA\n2) Mayor de 1 hectárea hasta 5 hectáreas de operación............................ 260.55 UMA\n3) Mayor de 5 hectáreas hasta 10 hectáreas de operación............................ 351.00 UMA\n4) Por cada hectárea excedente adicional a lo antes considerado, se cobrarán....... 54.00 UMA\n2.- Transformación: fundición de minerales metálicos fertilizantes, hules y plásticos, petróleos y derivados, papel, madera, bloqueras y ladrilleras, alimenticia, bebidas, tabaco, pigmentos, pintura, colorantes y derivados, vidrios, cerámica y derivados.\n1) Hasta 500 m² de operación............ 35.10 UMA\n2) Mayor de 500 m² hasta 1,000 m² de operación............................... 45.90 UMA\n3) Mayor de 1,000 m² hasta 5,000 m² de operación............................... 56.70 UMA\n4) Mayor de 5,000 m² de operación.......... 81.00 UMA\n3.- Manufacturera, máquinas y herramientas, textiles e industrias de cueros de la madera; productos de papel; ensamble de aparatos eléctricos o electrónicos; maquiladoras de otros tipos:\n1) Hasta 500 m² de operación.............. 35.10 UMA\n2) Mayor de 500 m² hasta 1,000 m² de operación............................... 45.90 UMA\n3) Mayor de 1,000 m² hasta 5,000 m² de operación............................... 56.70 UMA\n4.- Agroindustria, envases y empaques; forrajes y otras.\n1) Hasta 1,000 m² de operación............ 29.03 UMA\n2) Mayor de 1,000 m² hasta 5,000 m² de operación............................... 37.80 UMA\n3) Mayor de 5,000 m² de operación......... 45.90 UMA\nc).- Infraestructura e instalaciones como: Plantas, estaciones y subestaciones; torres y antenas; depósitos, cárcamos y bombas.\n1) Hasta 1,000 m² de operación................. 33.75 UMA\n2) Mayor de 1,000 m² de operación.............. 40.50 UMA\nd).- En otros usos como: Actividades agropecuarias, cauces y cuerpo de agua, deshuesadero (yonques):\n1) Hasta 1 hectárea de operación................ 52.65 UMA\n2) Mayor de 1 hectárea de operación............. 58.05 UMA\ne).- En zonas localizadas fuera de las manchas urbanas, donde existan oficinas, residencia o subresidencia de la dependencia:\n1).- Por dictamen se cobrará lo que marcan los números anteriores más $1.20 para cada kilómetro fuera de la ciudad, en donde existan oficinas, residencia o subresidencia de la dependencia.\nf).- Por expedición de documentos, constancias y dictámenes de la Dirección de Administración\nUrbana.\n1).- Constancia de condición de inmueble apta o no apta para su uso............................. 4.05 UMA\n2).- Verificación de cumplimiento de requisitos para traslación de dominio en fraccionamientos, cada vez que se solicite... 47.25 UMA\n3).- Verificación de cumplimiento de requisitos para traslación de dominio en condominios, cada vez.................................... 17.55 UMA\n4).- Verificación para cancelación de fianza de fraccionamientos, cada vez................... 60.75 UMA\n5).- Verificación de fianza de condominios, cada vez......................................... 20.25 UMA\n6).- Asignación y expedición de número oficial... 6.75 UMA\n7).- Certificado de Alineamiento................. 3.38 UMA\ng).- Cuando el dictamen de uso de suelo se solicite para regularización de construcción, ampliación, o instalación, el dictamen tendrá un costo adicional del 50%.\nh).- Cuando la asignación y expedición de número oficial asentamientos humanos que sean previamente clasificados como TIPO POPULAR y que sean\nSustentable (INSUS) en proceso de regularización del suelo con base en el convenio de colaboración con el Municipio de San Quintín, B.C. durante el período de su vigencia estarán exentos del pago de los conceptos de este apartado.................... 0.00 UMA\nVII.- POR EXPEDICIÓN DE DOCUMENTOS, CONSTANCIAS Y DICTÁMENES DE LA\nDIRECCIÓN DE ADMINISTRACIÓN URBANA:\nA.- Copias simples de planos oficiales o autorizados de desarrollos urbanos, ejidos, colonias agrícolas o mosaicos rústicos, de centros urbanos, programas de centro de población que conformen el archivo cartográfico oficial en formato 90x60 cm, por plano............................................ 6.41 UMA\n1.- Copias simples de planos oficiales o autorizados de desarrollos urbanos, ejidos, colonias agrícolas o mosaicos rústicos, de centros urbanos, programas de centro de población que conformen el archivo cartográfico oficial en formato doble carta, por plano.................................... 2.70 UMA\nB.- Certificación de copias de planos oficiales o autorizados de desarrollos urbanos, ejidos, colonias agrícolas o mosaicos rústicos, de centros urbanos, programas de centro de población que conformen el archivo cartográfico oficial en formato 90x60 cm, por plano....................... 9.45 UMA\n1.- Certificación de copias de planos oficiales o autorizados de desarrollos urbanos, ejidos, colonias agrícolas o mosaicos rústicos, de centros urbanos, programas de centro de población que conformen el archivo cartográfico oficial en formato doble carta, por plano................................... 7.43 UMA\nC.- Copia certificada de deslinde o levantamiento catastral........................................ 7.43 UMA\nD.- Copias certificadas de documentos por página...... 0.81 UMA\nE.- Copias simples de documentos catastrales por página........................................... 0.41 UMA\nF.- Constancia de registro catastral, con datos básicos actuales administrativos y de ubicación, por predio y/o memoria descriptiva.......................... 4.05 UMA\nG.- Historial registral de un predio urbano dentro de desarrollos autorizados, por registro catastral... 8.78 UMA\n1.- Historial registral de un predio suburbano, rústico o rural, por registro catastral...... 13.50 UMA\nH.- Constancia de las condiciones de uso físicas, de física, por predio................................ 6.75 UMA\nI.- Constancia de no propiedad........................ 2.03 UMA\nJ.- Constancia de antigüedad de construcción........... 2.70 UMA\nK.- Constancia de uso de suelo registrado y/o uso oficial o autorizado por autoridad competente, por predio........................................... 5.40 UMA\nL.- Análisis y aplicación de ajuste del valor unitario de predios suburbanos y rurales, por predio....... 10.80 UMA\nM.- Por expedición de constancias de valor catastral de conformidad a la tabla de valores publicada....... 4.05 UMA\nN.- Cálculo para aplicar los factores de demérito en predios urbanos, por predio....................... 4.05 UMA\nÑ.- Verificación en campo del uso de suelo en predios, por predio........................................\n5.40 UMA\nO.- Certificado de libertad de gravámenes fiscales.... 6.50 UMA\n1.- Para predios ubicados en fraccionamientos o asentamientos humanos que sean previamente clasificados como TIPO POPULAR y que sean notificados por el Instituto Nacional del\nSuelo Sustentable (INSUS) en proceso de regularización del suelo con base en el convenio de colaboración con el Municipio de\nSan Quintín, B.C., durante el periodo de su vigencia estarán exentos del pago de los conceptos de este apartado................... 0.00 UMA\n2.- Las personas físicas de escasos recursos, que utilicen los servicios del área de Defensoría de Oficio, en la tramitación de procedimientos judiciales, civiles y penales, previo estudio socioeconómico, que elabore la Dirección de\nBienestar Social, se les exentará del pago de los derechos por el servicio de Certificado de\nLibertad de Gravámenes Fiscales, a solicitud\nOficio, esta exención será otorgada al interesado por única ocasión.\nP.- Asignación de clave catastral urbana en nuevos fraccionamientos................................. 11.59 UMA\n1.- La asignación de clave catastral urbana para fraccionamientos o asentamientos humanos que sean previamente clasificados como TIPO\nPOPULAR y que sean notificados por el\nInstituto Nacional del Suelo Sustentable\n(INSUS) en proceso de regularización del suelo\nMunicipio de San Quintín, B.C. durante el periodo de su vigencia estarán exentos del pago de los conceptos de este apartado....... 0.00 UMA\nQ.- Por apertura de expedientes en fraccionamientos o condominios nuevos autorizados, por predios o cuentas catastrales nuevas........................ 2.36 UMA\n1.- Por apertura de expediente (cuenta catastral nueva) derivada de título o sentencia, emitida por la autoridad competente por predio o cuenta catastral............................. 3.63 UMA\n2.- Para predios ubicados en fraccionamientos o asentamientos humanos que sean previamente clasificados como TIPO POPULAR y que sean notificados por el Instituto Nacional del\nSuelo Sustentable (INSUS) en proceso de regularización del suelo con base en el convenio de colaboración con el Municipio de\nSan Quintín, B.C. durante el periodo de su vigencia estarán exentos del pago de los conceptos de este apartado................... 0.00 UMA\nR.- Por modificación de expedientes derivados de autorizados sobre predios propiedad del fraccionador, por predios o cuentas catastrales... 3.04 UMA\nS.- Derechos de registro como perito deslindador:\n1.- Registro inicial (alta)...................... 14.49 UMA\n2.- Revalidación anual........................... 7.25 UMA\nT.- Constancia en relación con los desarrollos urbanos.......................................... 8.10 UMA\nU.- Copia de información catastral computarizada certificada...................................... 5.40 UMA\nV.- Por análisis, dictámenes y registro catastral consolidados no autorizados (No se crea derecho de propiedad), por predio............................ 6.75 UMA\n1).- Por análisis, dictámenes y registro catastral provisional de POSESIONES de predios urbanos, suburbanos rústicos o rurales sin antecedentes registrales (No se crea derecho de propiedad), por predio........... 13.50 UMA\nW.- Rectificación, modificación o actualización de la base de datos, referente a los atributos estadísticos, jurídicos de propiedad, técnicos, fiscales de valor, ubicación de un predio......... 2.53 UMA\n1.- Para predios ubicados en fraccionamientos o asentamientos humanos que sean previamente clasificados como TIPO POPULAR y que sean notificados por el Instituto Nacional del\nSuelo Sustentable (INSUS) en proceso de regularización del suelo con base en el convenio de colaboración con el Municipio de\nSan Quintín, B.C. estarán exentos del pago de los conceptos de este apartado............... 0.00 UMA\nX.- Las personas físicas de escasos recursos, que utilicen los servicios del área de Defensoría de\nOficio, en la tramitación de procedimientos judiciales, civiles y penales, previo estudio socioeconómico, que elabore la Dirección de\nBienestar Social, se les exentará del pago de los de Gravámenes Fiscales, a solicitud expresa del titular del área Defensoría de Oficio, esta ocasión.\nY.- Para la obtención de los documentos de los incisos anteriores con carácter de urgente, en tiempos incrementará un 50% en el pago de los derechos normales de los mismos.\nVIII.- POR TRABAJOS TÉCNICOS:\nA.- Deslinde de predios, realizados por Dirección de\nAdministración Urbana:\n1.- En zonas urbanas en donde existan ejes físicos correctos y comprobados, así como puntos de control:\n1.1.- Predios con superficie hasta de\n180m²................................ 29.70 UMA\n1.2.- Para predios con superficie mayor de\n180 m² hasta 300 m², pagará la cuota máxima del inciso anterior, más 0.034\nUMA por cada metro cuadrado excedente de 180 m².\n1.3.- Para predios con superficie mayor de\n300 m² hasta 500 m², pagará la cuota máxima del inciso anterior, más 0.03\nUMA por cada metro cuadrado excedente de 300 m².\n1.4.- Para predios con superficie mayor de\n500 m² hasta 1,000 m², pagará la cuota máxima del inciso anterior, más 0.025\nUMA por cada metro cuadrado excedente de 500 m².\n1.5.- Para predios con superficie mayor de\n1,000 m² hasta 2,500 m², pagará la cuota máxima del inciso anterior, más\n0.017 UMA por cada metro cuadrado excedente de 1,000 m².\n1.6.- Para predios con superficie mayor de\n2,500 m² hasta 5,000 m², pagará la cuota máxima del inciso anterior, más\n0.011 UMA por cada metro cuadrado excedente de 2,500 m².\n1.7.- Para predios con superficie mayor de\n5,000 m² hasta 10,000 m², pagará la cuota máxima del inciso anterior, más\n0.007 UMA por cada metro cuadrado excedente de 5,000 m².\n1.8.- Para predios con superficie mayor de\n10,000 m² hasta 50 hectáreas, pagará la cuota máxima del inciso anterior, más 1.62 UMA por hectárea o fracción excedente de 10,000 m².\n1.9.- Para predio con superficie mayor a 50 hectáreas hasta 200 hectáreas, pagará la cuota máxima anterior, más 0.27 UMA por hectárea o fracción excedente.\n1.10.- Para predios con superficie mayor a\n200 hectáreas hasta 500 hectáreas, pagará la cuota mayor del inciso anterior, más 0.16 UMA por hectárea excedente.\n1.11.- Para predios con superficie mayor a\n500 hectáreas, pagará la cuota mayor del inciso anterior, más 0.14 UMA por hectárea excedente.\n2.- En zonas urbanas en donde no exista la definidos, a las cuotas anteriores se les incrementará un 25%.\n3.- En las zonas urbanas irregulares o carentes de puntos de control y ejes físicos definitivos, se les incrementará un 50% a las cuotas indicadas en el inciso 1.\n4.- Para predios ubicados fuera de la zona urbana pero dentro del centro de población de la valores del número anterior.\n5.- Para predios cuya superficie exceda de las\n1,000 hectáreas pagará los derechos de deslinde de acuerdo al presupuesto que al costo del servicio y previa solicitud del interesado.\n6.- A los predios ubicados fuera de la zona urbana, además de las cuotas anteriores se les acumulará 0.34 UMA para cada kilómetro fuera de la ciudad.\n7.- Para terrenos semicerriles o lomeríos, los cuales para efectos fiscales se considerarán aquéllos de pendientes uniformes menores de\n30 grados, tendrán las cuotas anteriores un incremento de 40%; los terrenos cerriles, considerándose para el efecto aquellos con cambios bruscos de pendientes mayores de 30 grados tendrán un aumento del 75% a las cuotas establecidas.\n8.- Para la obtención del deslinde con carácter de urgente, en tiempos menores a los que requiere el trabajo normal, se les incrementará un 100% en el pago del servicio normal del mismo.\n8.1.- Las personas físicas de escasos recursos que utilicen servicios del área de la Defensoría de Oficio en la tramitación de procedimientos judiciales, civiles y penales, previo estudio socioeconómico que elabore la\nDirección de Bienestar Social se les exentará del pago de los derechos por los servicios de deslinde de predios, a solicitud expresa del titular del área de la Defensoría de Oficio, siempre y cuando no exceda de 40.50\nUMA por servicio, exención que será otorgada al interesado por única ocasión.\nB.- Levantamiento de predios realizados por la\nDirección de Administración Urbana:\n1.- Para predios con superficie hasta de 180.00 m² pagará 24.30 UMA.\n2.- Para predios superficie mayor de 180 m² hasta\n300 m², pagará la cuota máxima del inciso anterior más 0.036 UMA por cada m² excedente de 180 m².\n3.- Para predios con superficie mayor de 300 m² hasta 500 m², pagará la cuota máxima del inciso anterior más 0.031 UMA por cada m² excedente de 300 m².\n4.- Para predios con superficie mayor de 500 m² hasta 1,000 m², pagará la cuota máxima del inciso anterior más 0.027 UMA por cada m² excedente de 500 m².\n5.- Para predios con superficie mayor de 1,000 m² hasta 2,500 m², pagará la cuota máxima del inciso anterior más 0.014 UMA por cada m² excedente de 1,000 m².\n6.- Para predios con superficie mayor de 2,500 m² hasta 5,000 m², pagará la cuota máxima del inciso anterior más 0.008 UMA por cada m² excedente de 2,500 m².\n7.- Para predios con superficie mayor de 5,000 m² hasta 10,000 m², pagará la cuota máxima del inciso anterior más 0.004 UMA por cada m² excedente de 5,000 m².\n8.- Para predios con superficie mayor de 10,000 m², se pagará la cuota máxima del inciso anterior, más 10.80 UMA por hectárea o fracción excedente de 10,000 m².\n9.- Los predios cuya superficie exceda de 250-0000 hectáreas, pagarán los Derechos de\nUrbana, el que, en todo caso, será equivalente al costo del servicio y previa solicitud del interesado.\n10.- Los predios ubicados fuera de la zona urbana, además de las cuotas anteriores, se le acumulará 0.34 UMA para cada kilómetro fuera de la ciudad.\n11.- Para terrenos semicerriles o lomeríos los cuales para efectos fiscales se consideran aquellos de pendientes uniformes menores de 30 grados, tendrán las cuotas anteriores un aumento del 40%.\n11.1.- Para terrenos cerriles, considerándose para el efecto aquellos con cambios bruscos de pendientes mayores de 30 grados, tendrán aumento del 75% a las cuotas establecidas.\n12.- Para la obtención de levantamiento con carácter de urgente, en tiempos menores a los que requiere el trabajo normal, se les incrementará un 120% en el pago del servicio normal del mismo.\n13.- Los predios ubicados en áreas populares o de interés social, clasificados como tales en los programas de centro de población, tendrán el\n50% de descuento sobre la cuota normal que le correspondiese cubrir.\nC.- Para el estudio, cálculo y verificación física de planos para efectos de certificaciones catastrales:\n1.- Para deslindes, se pagará de conformidad con la siguiente tabla:\n1.1.- Para predios con superficie de hasta\n10,000 metros cuadrados el 33% de los derechos que se causen por el servicio de deslinde.\n1.2.- Para predios con superficie mayor de 1 hectárea hasta 50 hectáreas, el 31% de los derechos que se causen por el servicio de deslinde.\n1.3.- Para los predios con superficie mayor de 50 hectáreas hasta 250 hectáreas, el 28% de los derechos que se causen por el servicio de deslinde.\n1.4.- Para los predios con superficie mayor de 250 hectáreas hasta 1,000 hectáreas, el 26% de los derechos que se causen por el servicio de deslinde.\n1.5.- Para los predios con superficie mayor de 1,000 hectáreas, los predios que excedan esa superficie pagarán 0.04\nUMA por hectárea adicional.\n2.- Para levantamientos, se pagará de conformidad con la siguiente tabla:\n2.1.- Para predios con superficie de hasta\n10,000 metros cuadrados, el 35% de los derechos que se causen por el servicio de levantamiento.\n2.2.- Para predios con superficie mayor de\n1 hectárea hasta 50 hectáreas, el 30% de los derechos que se causen por el servicio de levantamiento.\n2.3.- Para los predios con superficie mayor de 50 hectáreas hasta 100 hectáreas, el 27.5% de los derechos que se causen por el servicio de levantamiento.\n2.4.- Para los predios con superficie mayor de 100 hectáreas, los predios que excedan esa superficie pagarán 0.014\nUMA por hectárea adicional.\n3.- Para la verificación física de planos con carácter de urgente, en tiempos menores a los que requiere el trabajo normal, se les incrementará un 100% en el pago de los derechos normales de los mismos.\n4.- Para predios cuya superficie exceda de las\n1,000 hectáreas, pagará los derechos de estudio, cálculo y verificación física de planos para efectos de certificaciones catastrales de acuerdo al presupuesto que al efecto realice la Dirección de Administración\nUrbana.\n5.- En caso de no realizarse el o los servicios previstos por causas imputables al solicitante y se compruebe por parte de la Dirección de\nAdministración Urbana, se llevará a cabo la devolución del 50% del importe pagado.\n6.- Para predios ubicados en fraccionamientos o asentamientos humanos que sean previamente clasificados como TIPO POPULAR y que sean notificados por el Instituto Nacional del\nSuelo Sustentable (INSUS) en proceso de regularización del suelo con base en el convenio de colaboración con el Municipio de\nSan Quintín, B.C. estarán exentos del pago de los conceptos de este apartado............... 0.00 UMA\nD.- Los trabajos de levantamiento, deslinde y estudio, cálculo y verificación física de planos, para donde no existen oficinas de la Dirección de\nAdministración Urbana, causará una cuota adicional, equivalente a los gastos de transporte, alojamiento y alimentación del personal que se utilice.\nIX.- POR LINEAMIENTOS VIALES PARA DESARROLLOS URBANOS: obra de infraestructura, incluyendo copia del plano relativo se pagará por la superficie del predio estudiado de la siguiente forma:\nA.- En predios ubicados dentro o colindando con los límites de los centros de población:\n1.- Menores de 1 hectárea...................... 13.50 UMA\n2.- De 1 a 5 hectáreas........................... 60.75 UMA\n3.- Por cada hectárea o fracción adicional a 5 hectáreas.................................. 4.05 UMA\n4.- Para predios donde se ubiquen fraccionamientos o asentamientos humanos que sean previamente clasificados como TIPO POPULAR y que sean notificados por el Instituto Nacional del\nSuelo Sustentable (INSUS) en proceso de regularización del suelo con base en el convenio de colaboración con el Municipio de\nSan Quintín, B.C., estará exenta del pago de este concepto................................ 0.00 UMA\nB.- En predios ubicados fuera de los centros de población, a una distancia menor a 101 km de la\nCiudad de San Quintín:\n1.- Menores de una hectárea...................... 20.25 UMA\n2.- De 1 a 5 hectáreas........................... 91.13 UMA\n3.- Por cada hectárea o fracción adicional a 5 hectáreas.................................. 6.08 UMA\n4.- Para predios donde se ubiquen fraccionamientos o asentamientos humanos que sean previamente clasificados como tipo popular y que sean notificados por el Instituto Nacional del\nSuelo Sustentable (INSUS) en proceso de regularización del suelo con base en el convenio de colaboración con el Municipio de\nSan Quintín, B.C., estará exenta del pago de este concepto................................ 0.00 UMA\nC.- En predios ubicados fuera de los centros de población a una distancia entre 101 km y 250 km de la Ciudad de San Quintín:\n1.- Menores de una hectárea...................... 40.50 UMA\n2.- De 1 a 5 hectáreas........................... 111.38 UMA\n3.- Por cada hectárea o fracción adicional a 5 hectáreas.................................. 6.08 UMA\nD.- En predios ubicados fuera de los centros de población, a una distancia mayor a 250 km y hasta\n400 km de la Ciudad de San Quintín:\n1.- Menores de una hectárea...................... 60.75 UMA\n2.- De 1 a 5 hectáreas........................... 131.63 UMA\n3.- Por cada hectárea o fracción adicional a 5 hectáreas.................................. 6.08 UMA\nE.- En predios ubicados fuera de los centros de población, a una distancia mayor a 400 km y hasta\n550 km de la Ciudad de San Quintín:\n1.- Menores de una hectárea...................... 81.00 UMA\n2.- De 1 a 5 hectáreas........................... 151.88 UMA\n3.- Por cada hectárea o fracción adicional a 5 hectáreas.................................. 6.08 UMA\nF.- Por análisis de accesos vehiculares se pagará de la forma siguiente:\n1.- En predios ubicados dentro del límite del centro de población:\n1.1.- Por accesos a lotes comerciales, habitacionales y de servicios........ 13.50 UMA\n1.2.- Por acceso a centros comerciales y lotes industriales................... 27.00 UMA\n1.3.- Por acceso a fraccionamientos........ 54.00 UMA\n2.- En predios ubicados fuera del límite del centro de población, a una distancia menor a 100 km de la ciudad de San Quintín:\n2.1.- Por accesos a lotes comerciales, habitacionales y de servicios........ 20.25 UMA\n2.2.- Por acceso a centros comerciales y lotes industriales................... 40.50 UMA\n2.3.- Por acceso a fraccionamientos........ 81.00 UMA\n3.- En predios ubicados fuera del límite del centro de población, a una distancia entre 100 km y hasta 250 km de la ciudad de San Quintín:\n3.1.- Por accesos a lotes comerciales, habitacionales y de servicios........ 40.50 UMA\n3.2.- Por acceso a centros comerciales y lotes industriales................... 60.75 UMA\n3.3.- Por acceso a fraccionamientos........ 101.25 UMA\n4.- En predios ubicados fuera del límite del centro de población a una distancia mayor de\n250 km y hasta 400 km de la ciudad de San\nQuintín:\n4.1.- Por accesos a lotes comerciales, habitacionales y de servicios........ 60.75 UMA\n4.2.- Por acceso a centros comerciales y lotes industriales................... 81.00 UMA\n4.3.- Por acceso a fraccionamientos........ 121.50 UMA\n5.- En predios ubicados fuera del límite del centro de población, a una distancia mayor de 400 km y hasta 550 km de la ciudad de San Quintín:\n5.1.- Por acceso a lotes comerciales, habitacionales y de servicios........ 81.00 UMA\n5.2.- Por acceso a centros comerciales y lotes industriales................... 101.25 UMA\n5.3.- Por acceso a fraccionamientos........ 141.75 UMA\n6.- Por revisión en proyectos para señalamiento vial en nuevos desarrollos comerciales, habitacionales, industriales, etc.:\n6.1.- Hasta 5 hectáreas.................... 27.00 UMA\n6.2.- Por cada hectárea o fracción adicional a 5 hectáreas........................ 2.70 UMA\n7.- Por revisión en proyectos de semaforización.. 27.00 UMA\n8.- Por revisión en proyectos que contemplen estacionamiento para vehículos:\n8.1.- De 20 a 30 cajones de estacionamiento...................... 6.75 UMA\n8.2.- Por cada 10 cajones adicionales...... 2.70 UMA\nG.- Por eliminación de cajones de estacionamiento para nuevos desarrollos, el cobro será anual:\n1.- Por la eliminación de cajones de estacionamiento en la vía pública, para dar acceso a inmuebles de uso comercial y el buen funcionamiento de la circulación peatonal:\n1.1.- Por cada cajón de estacionamiento eliminado, dentro y fuera del límite de población......................... 13.50 UMA\n2.- Los propietarios de giros comerciales e industriales que cuenten con la autorización escrita de la autoridad municipal, para la eliminación de cajones en la vía pública, para el ingreso o salida de vehículos en vía pública, deberán de pagar los derechos dentro del ejercicio fiscal.\n2.1.- Por cada cajón de estacionamiento eliminado, dentro y fuera del límite de población......................... 6.75 UMA\n3.- Por la modificación geométrica de integraciones viales a estacionamientos ya autorizados y/o no cumplan con la normatividad establecida en la Ley de Edificaciones del\nEstado de Baja California................... 540.00 UMA\nH.- Los fraccionamientos populares o de interés social tendrán un 50% de descuento de estas cuotas, sólo construidos por el gobierno (Municipal, Estatal o Federal).\n1.- Los fraccionamientos populares o de interés social cuando sean tramitados o construidos por cualquier compañía privada deberán pagar el 100%.\nX.- SERVICIOS DERIVADOS DEL SISTEMA DE INFORMACIÓN GEOGRÁFICA\n(PRODUCTOS CATASTRALES Y SERVICIOS CARTOGRÁFICOS).\nA.- CARTOGRAFÍA URBANA DIGITAL:\n1.- Archivo de cartografía digital por zona catastral urbana en formatos con información básica (traza de manzanas y lotes, nomenclatura de manzana, lote y vialidades), por archivo.................................. 10.80 UMA\n2.- Archivo de cartografía digital por zona catastral urbana en formato PDF (no editable) con información básica (traza de manzanas y lotes, nomenclatura de manzana, lote y vialidades), por archivo..................... 5.40 UMA\n3.- Archivo de cartografía digital por zona con información básica (traza de manzanas y lotes, nomenclatura de predios, superficie y clave catastral), por archivo.............. 13.50 UMA\n4.- Archivo de cartografía digital por zona catastral urbana en formato PDF (no editable) con información básica (traza de manzanas y lotes, nomenclatura de predios, superficie y clave catastral), por archivo............... 6.75 UMA\nB.- SERVICIOS DIGITALES:\n1.- Derechos de ACCESO Y CONSULTA remota del\nARCHIVO DIGITAL de los expedientes catastrales................................. 94.50 UMA\n2.- Derechos de ACCESO Y CONSULTA del Sistema de Información Geográfica Municipal.......... 94.50 UMA\nXI.- POR VERIFICACIÓN Y CERTIFICACIÓN DE FACTIBILIDAD PARA LA\nINSTALACIÓN, REVALIDACIÓN Y REGULARIZACIÓN DE RÓTULOS, ANUNCIOS Y\nSIMILARES; ASÍ COMO MESAS Y SILLAS, EXCEPTUANDO LA PROPAGANDA\nEFECTUADA POR PARTIDOS POLÍTICOS, SIEMPRE QUE NO SE DERIVE A\nTERCEROS; EL PAGO SERÁ POR ESTE PERIODO FISCAL, EXCEPTUANDO LOS\nPERMISOS QUE DEBAN SER COBRADOS POR DÍA, PREVIO AL INICIO DEL\nTRÁMITE, POR SUPERFICIE O CANTIDAD, SEGÚN SE INDIQUE DE ACUERDO A\nLA SIGUIENTE TABLA:\nA.- Licencia nueva con validez para este ejercicio fiscal, independientemente de la fecha de ingreso, y permisos por día. Se entiende por permiso la autorización temporal que se paga por día y que no exceda de un período de tres meses.\nEstarán EXENTOS de los conceptos 1, 2, 3, 4, 6b del presente inciso, la propaganda efectuada en propiedad privada con publicidad del establecimiento, negocio o giro comercial, ubicado en la propiedad en que se publicite, con superficie de hasta 3 m², siempre que no se derive a terceros.\nAsí como la publicidad promovida por instituciones educativas, de gobierno, asociaciones de la sociedad civil sin fines de lucro, para eventos de apoyo a la comunidad y la publicidad con información gubernamental de la Federación, Estado y\nMunicipio.\n1.- Permiso posters de pared o adosados.......... 0.20 UMA por m² por día\n2.- Licencia anuncio adosado en propiedad privada:\na).- Sin iluminación......................... 4.05 UMA por m²\nb).- Con iluminación.......................... 5.40 UMA por m²\nc).- Sin iluminación para el Sistema de\nApertura Rápida de Empresas durante el primer año.............................. 2.03 UMA por 1.5 m²\nd).- Con iluminación para el Sistema de\nApertura Rápida de Empresas durante el primer año.............................. 2.70 UMA por 1.5 m²\n3.- Licencia rótulos\n3.1 Sin iluminación...................... 2.70 UMA por m²\n3.2 Con iluminación...................... 5.40 UMA por m²\n4.- Licencia rótulos electrónicos................ 6.75 UMA por m²\n5.- Licencia anuncio tipo bandera o paleta:\na).- Pintado............................... 4.05 UMA por lado\nb).- Luminosos.............................. 5.40 UMA por lado\n6.- Permisos de lonas o mantas:\na).- En vía pública por un período máximo de\n15 días (no incluye instalación, ni retiro)................................ 0.41 UMA por m² por día\nb).- Adosados en propiedad privada (no incluye instalación, ni retiro)....... 0.20 UMA por m² por día\nc).- En vía pública por un periodo máximo de\n15 días para eventos sin fines de lucro por asociaciones civiles, que no se derive a terceros, (no incluye instalación ni retiro)................. 0.14 UMA por m² por día\nd).- Instalación y retiro de mantas por personal del Municipio en vía pública... 20.25 UMA por pieza\n7.- Por mampara en camellón central de no más de 2 m de altura por 1.20 metros de ancho, a una distancia no menor de 3 metros de la esquina del mismo........................... 6.75 UMA por unidad\n8.- Para instalación de torre fija, tipo directorio para instalación de anuncios diversos por ambos lados..................... 20.25 UMA por m²\n9.- Mini porta cartel direccional exclusivamente para desarrollos habitacionales e industriales nuevos...................................... 10.13 UMA por pieza por\n90 días\n10.- Cobertizo publicitario y/o mobiliario urbano con publicidad con fines comerciales (banca publicitaria, bote de basura o buzón con publicidad, etc.)........................... 8.10 UMA por unidad\n11.- Carro de sonido............................. 10.80 UMA por unidad por 90 días\n12.- Torreta en techo de camión o taxi........... 10.80 UMA por unidad\n13.- Rótulo en vehículo........................... 10.13 UMA por unidad\n14.- Instalación de áreas con mesas, sillas y bancas, incluyendo estructuras y elementos que delimiten la ocupación de la vía pública. fijas y deberán ser desmontadas, cuando la autoridad previo aviso lo solicite:\na).- En zona comercial sobre la carretera\nTranspeninsular y turística sobre la franja de la playa del Pacífico y Bahía de los Ángeles del Municipio de San\nQuintín................................ 21.60 UMA por m²\nb).- Fuera de la zona comercial y turística, definida en el inciso anterior......... 10.80 UMA por m²\n15.- Licencia anuncio tipo tripié................. 13.50 UMA por pieza\n16.- Permiso de pendón o cartel en poste de hasta\n1.00 metro cuadrado de superficie (no incluye instalación o retiro)........................ 0.14 UMA por pieza por día\n17.- Permiso volantes:\na).- Vigencia por un período de 15 días naturales.............................. 5.40 UMA\nb).- Vigencia por un período mayor de 15 días naturales hasta 30 días en ubicación fija................................... 10.80 UMA\nc).- Vigencia por un período mayor de 15 días naturales en zona habitacional, colonia o fraccionamiento....................... 20.25 UMA\nd).- Volantes a beneficio de la comunidad.... EXENTOS\n18.- Permiso figura inflable con publicidad....... 4.73 UMA por día\na) Vigencia por un periodo de 1 a 5 días naturales.............................. 4.05 UMA\nb) Vigencia por un periodo de 6 a 15 días naturales.............................. 13.50 UMA\nc) Vigencia por un periodo de 16 a 30 días naturales.............................. 32.40 UMA\nd) Después de 30 días naturales por día adicional.............................. 0.68 UMA\n19.- Licencia anuncio tipo cartelera y/o espectacular (con o sin iluminación) por unidad...................................... 2.70 UMA por m²\nLa superficie base para el cálculo del cobro se realizará considerando la totalidad de la superficie a exponer publicidad.\n20.- Anuncio tipo espectacular de pantalla electrónica y/o electromecánico o digital, con o sin movimiento (por cartelera y/o estructura):\na) Para uso exclusivo del comercio establecido en el mismo predio a publicitar............................. 8.10 UMA por m² por lado\nb) Para publicitar a terceros.............. 13.50 UMA por m² por lado\n21.- Valla publicitaria por metro cuadrado (con o sin iluminación)............................. 2.03 UMA por m²\nLa superficie base para el cálculo del cobro se realizará considerando la totalidad de la superficie a exponer publicidad.\n22.- Publicidad móvil remolcada en cualquier modalidad, ya sea valla, cartelera giratoria, digital, etc.:\na).- Con vehículo de tracción motriz de cuatro ruedas o más.................... 49.95 UMA\nb).- Con vehículo de tracción motriz o no motriz menor a cuatro ruedas......... 20.25 UMA\n23.- Publicidad aérea, en esferas, dirigibles, globos aerostáticos o banderas en el cielo, por pieza:\na).- Vigencia por un periodo de 1 día........ 4.05 UMA\nb).- Vigencia por un periodo de 1 a 5 días naturales.............................. 13.50 UMA\nc).- Vigencia por un periodo de 6 a 15 días naturales.............................. 32.40 UMA\nd).- Vigencia por un periodo de 16 a 30 días naturales.............................. 48.60 UMA\ne).- Después de 30 días, por día adicional... 0.68 UMA\n24.- Publicidad en vía pública mediante botargas, flechas y otros elementos, operado por una persona, por pieza:\na).- Vigencia por un período de 1 día........ 4.05 UMA\nb).- Vigencia por un período de 1 a 5 días naturales.............................. 13.50 UMA\nc).- Vigencia por un período de 6 a 15 días naturales.............................. 32.40 UMA\nd).- Vigencia por un período de 16 a 30 días naturales.............................. 48.60 UMA\ne).- Después de 30 días, por día adicional.............................. 0.68 UMA\n25.- Licencia de anuncio tipo banderola o gallardete.................................. 10.80 UMA por pieza\n26.- Instalación y/o ocupación en vía pública temporal con almacén móvil, mesas, exhibición de mercancía, aplica únicamente para vía pública colindante a predio o local establecido del solicitante:\na).- En zona comercial y turística comprendida en el inciso a) del punto 14 anterior... 2.03 UMA por m² por cada 7 días\nb).- Fuera de la zona comercial y turística comprendida en el inciso a) del punto 14 anterior............................... 1.01 UMA por m² por cada 7 días\nc).- En zona comercial y turística comprendida en el inciso a) del punto 14 anterior... 2.70 UMA por m² por cada 90 días\nd).- Fuera de la zona comercial y turística comprendida en el inciso a) del punto 14 anterior............................... 1.35 UMA por cada 90 días\nEstarán EXENTOS, los primeros 5m² de superficie de los rótulos y anuncios de pared o adosados pintados no luminosos, en propiedad privada con superficie de hasta 1m², y hasta de 5m² en trámites realizados vía Sistema de Apertura Rápida de\nEmpresas, la renovación será considerada por concepto normal.\nB.- Revalidación procederá al verificarse que aún se cumpla con los requisitos para el otorgamiento, con vigencia por el ejercicio fiscal.\n1. Anuncios de pared o adosados:\na).- Pintados............................... 2.03 UMA por m²\nb).- Luminosos.............................. 2.70 UMA por m²\nc).- Pintados para el Sistema de Apertura\nRápida de Empresas (SARE).............. 1.35 UMA por m² por lado\nd).- Luminoso para el Sistema de Apertura\nRápida de Empresas (SARE).............. 2.03 UMA por m² por lado\n2. Rótulos sin iluminación...................... 1.35 UMA por m²\n3. Rótulos con iluminación...................... 2.70 UMA por m²\n4. Licencia rótulos electrónicos............... 3.38 UMA por m²\n5. Licencia anuncio tipo bandera o paleta:\na) Pintado................................ 2.03 UMA por m² por lado\nb) Luminosos.............................. 2.70 UMA por m² por lado\n6. Para instalación de torre fija, tipo directorio para instalación de anuncios diversos, por ambos lados.................... 10.13 UMA por m²\n7. Cobertizo publicitario y/o mobiliario urbano con publicidad, con fines comerciales (banca publicitaria, bote de basura o buzón con publicidad, etc.)............................ 5.40 UMA por pieza\n8. Torreta en techo de camión o taxi............ 5.40 UMA por unidad\n9. Rótulo publicitario en vehículo............. 5.06 UMA por unidad\n10. Instalación de áreas con mesas, sillas y bancas, incluyendo estructuras y elementos que delimiten la ocupación de la vía pública. Esta licencia en particular podrá pagarse proporcional a los meses que se consideren turísticos del año. En ningún momento podrán ser fijas y deberán ser desmontadas, cuando la autoridad previo aviso lo solicite:\na).- En zona comercial sobre la carretera\nTranspeninsular y turística sobre la franja de la playa del Pacífico y Bahía de los Ángeles del Municipio de San\nQuintín, B.C............................ 10.80 UMA por m²\nb).- Fuera de la zona comercial y turística definida en el inciso a, anterior...... 5.40 UMA por m²\n11.- Anuncio tipo tripié.......................... 6.75 UMA\n12.- Licencia anuncio tipo cartelera y/o espectacular (con o sin iluminación) por unidad...................................... 35.00 UMA por m²\nLa superficie base para el cálculo del cobro se realizará considerando la totalidad de la superficie a exponer publicidad.\n13.- Anuncio tipo espectacular de pantalla electrónica y/o electromecánico o digital, con o sin movimiento (por cartelera y estructura):\na) Para uso exclusivo del comercio establecido en el mismo predio a publicitar............................. 4.05 UMA por m² por lado\nb) Para publicitar a terceros.............. 6.75 UMA por m² por lado\n14.- Valla publicitaria por metro cuadrado (con o sin iluminación)............................. 0.68 UMA por m²\n15.- Publicidad móvil remolcada en cualquier modalidad, ya sea valla, cartelera giratoria, digital, etc.:\na) Con vehículo de tracción motriz de cuatro ruedas o más............................ 24.30 UMA\nb) Con vehículo de tracción motriz o no motriz menor o cuatro ruedas............ 10.13 UMA\nC).- La regularización de cualquier licencia, cuando se encuentren anuncios fijos instalados o publicitándose, se incrementará en 50% de las tarifas fijadas en el apartado A de la fracción\nXI del Artículo 33 de esta Ley. Lo anterior, independientemente propietarios.\nSolamente cuando la regularización de los conceptos del apartado A de la fracción XI del presente artículo, se ingrese a partir del mes de julio, se podrá aceptar la consideración de la tarifa por los meses restantes del ejercicio fiscal.\nLos anuncios sin permiso en la vía pública, incluso los adosados a muros, cercos o bardas con paramento hacia la vía pública deberán ser removidos por el propietario o en su caso por personal del\nMunicipio, sin derecho a ser regresados o reparados al propietario, independientemente de las multas a las que se hagan acreedores los responsables propietarios.\nLa falta de revalidación fuera de los plazos establecidos, será motivo de multa.\nLas personas físicas, morales o unidades económicas que presten los servicios de publicidad, así como los propietarios de los bienes inmuebles, donde se instalen anuncios, y las y de instituciones de crédito, seguros y fianzas, sanciones que se originen con motivo de los anuncios que tengan instalados en esta municipalidad, por violaciones a la normatividad aplicable.\nXII.- POR ANÁLISIS DE SOLICITUD Y EMISIÓN DE DECLARATORIA PARA LA\nCONSTITUCIÓN DEL RÉGIMEN DE PROPIEDAD EN CONDOMINIO INMUEBLES:\na).- Por análisis y dictamen de factibilidad de constitución del régimen sobre conjuntos sin construir, habitacionales, comerciales o mixtos, condominio:\n1.- Por conjuntos hasta de 10 unidades........... 20.25 UMA\n2.- Por cada unidad excedente de las diez primeras.................................... 1.35 UMA\nb).- Por análisis y dictamen de factibilidad de constitución del régimen sobre conjuntos sin construir, habitacionales, comerciales o mixtos, que se utilizarán en forma múltiple en predios uniformes y que conforman un solo conjunto inmobiliario, se pagará por el primero las mismas cuotas del inciso anterior y el diez por ciento de éstas para las subsecuentes.\nc).- Por análisis y dictamen de factibilidad de conversión al régimen de propiedad en condominio de inmuebles o de conjuntos habitacionales, comerciales o mixtos, ya construidos, se pagará:\n1.- Por conjuntos hasta de diez unidades......... 27.00 UMA\n2.- Por cada unidad excedente de las diez primeras.................................... 35.00 UMA fuera de los límites de los centros de población, las tarifas indicadas en los incisos a), b) y\nc), se incrementarán en un veinticinco por ciento.\nd).- Por la declaratoria de factibilidad para la de inmuebles, se pagará por cada unidad, departamento, vivienda, casa o local, en la forma siguiente:\n1.- Por cada unidad habitacional de tipo interés\nSocial...................................... 2.70 UMA\n2.- Por cada unidad habitacional de tipo popular. 4.05 UMA\n3.- Por cada unidad habitacional de tipo nivel\nMedio....................................... 4.73 UMA\n4.- Por cada unidad habitacional de tipo nivel\nResidencial.................................. 8.10 UMA\n5.- Por cada unidad comercial o industrial... 21.60 UMA\ne).- Por verificación y certificación de memorias descriptivas de departamentos, viviendas, casas o locales pertenecientes a condominios, se pagará por la primera revisión en la forma siguiente:\n1.- Hasta diez unidades.......................... 27.00 UMA\n2.- Por cada unidad que exceda de diez........... 1.35 UMA\n3.- En el caso de revisiones subsecuentes, se pagará el cincuenta por ciento de la tarifa por la primera revisión.\nf).- Por expedición de oficio para cancelación de fianza de régimen de propiedad en condominio, por condominio....................................... 5.40 UMA\nXIII.- POR ANÁLISIS Y EMISIÓN DE FACTIBILIDAD DE OPINIONES TÉCNICAS\nDE OCUPACIÓN DE LA VÍA PÚBLICA POR ELEMENTOS O MOBILIARIO DE LOS\nSERVICIOS PÚBLICOS QUE POR SU UBICACIÓN IMPACTAN LA IMAGEN\nURBANA Y EL BUEN FUNCIONAMIENTO DE LA CIRCULACIÓN PEATONAL,\nTALES COMO:\na).- Para los elementos o mobiliario urbano de los equipos de telefonía:\n1.- Por kilómetro o fracción de línea de telefonía subterránea o aérea.......................... 16.20 UMA\n2.- Por poste o torre............................ 1.35 UMA\n3.- Por registro................................. 2.70 UMA\n4.- Por caseta de telefonía pública.............. 6.75 UMA\n5.- Antenas..................................... 13.50 UMA\nb).- Para los elementos o mobiliario urbano de los equipos de energía eléctrica:\n1.- Por kilómetro o fracción de línea de energía eléctrica subterránea o aérea............... 16.20 UMA\n2.- Por poste o torre............................ 1.35 UMA\n3.- Por registro................................. 2.70 UMA\nc).- Por kilómetro o fracción de ciclovía, incluye demolición....................................... 13.50 UMA\nXIV.- DERECHOS DE REGISTRO COMO PERITO VALUADOR, ANTE LA TESORERÍA\nMUNICIPAL. QUIENES SOLICITEN SU REGISTRO COMO PERITOS VALUADORES,\nAPLICABLE, ESTARÁ VIGENTE EN LO QUE SE EMITE LA PROPIA. SE ESTARÁ A\nLO SIGUIENTE:\n1).- Registro inicial (alta).......................... 49.95 UMA\n2).- Revalidación..................................... 33.75 UMA\n3).- Multa por revalidación extemporánea adicionalmente al pago del inciso anterior...................... 16.20 UMA\nXV.- DÉFICIT DE CAJONES DE ESTACIONAMIENTO.\nA.- Los propietarios o arrendatarios de locales de comercios y servicios que, al regularizar el uso de suelo, resulten con déficit en cantidad de cajones de estacionamiento respecto al reglamento correspondiente, deberán obtener la autorización escrita de la Dirección de Administración Urbana, y pagar una tarifa por uso de vías públicas, hasta en tanto habiliten los cajones de estacionamiento en un terreno de su propiedad o en arrendamiento público, de acuerdo a la tabla siguiente:\na) En la zona comercial a los laterales de la carretera transpeninsular de la zona urbana...................................... 47.25 UMA por cajón\nb) En la zona comprendida fuera del perímetro descrito en el inciso anterior.............. 32.40 UMA por cajón\nc) En cualquier zona tratándose de giros determinados en el de Apertura Rápida de\nEmpresas durante el primer año.............. 13.50 UMA por cajón\nB.- Las renovaciones deberán hacerse aplicando la tarifa conforme a la tabla siguiente:\na) En la zona comercial a los laterales de la carretera transpeninsular de la zona urbana.. 23.63 UMA por cajón\nb) En la zona comprendida fuera del perímetro descrito en el inciso anterior.............. 16.20 UMA por cajón\nc) En cualquier zona tratándose de giros determinados en el Sistema de Apertura Rápida de Empresas durante el primer año............ 13.50 UMA por cajón\nEn caso de excederse en el término para la renovación de los conceptos comprendidos en el\nApartado A de la fracción XIV de este artículo, se considerará el trámite como licencia nueva.\nEn caso de regularización de los conceptos del\nApartado A, de la fracción XV de este artículo, ingresado a partir del mes de julio, podrá considerarse la tarifa por los meses restantes.\nXVI.- DÉFICIT DE ESPACIO PARA CONTENEDOR.\nA).- Los propietarios o arrendatarios de locales de comercios y servicios que al regularizarse resulten con déficit en espacio para alojar contenedor para basura, deberán obtener la autorización escrita de la Dirección de\nAdministración Urbana, y pagar una tarifa por uso de vías públicas, hasta en tanto habiliten espacio para alojar el contenedor en un terreno de su propiedad o en arrendamiento, de acuerdo a la siguiente tabla:\na).- En la zona comercial a los laterales de la carretera transpeninsular de la zona urbana.. 33.75 UMA por pieza\nb).- En zona comprendida fuera del perímetro descrito en el inciso a).- anterior.......... 27.00 UMA por pieza\nB).- Las renovaciones deberán hacerse en los meses de julio a diciembre, aplicando la tarifa de acuerdo a la tabla siguiente:\na).- En la zona comercial a los laterales de la carretera transpeninsular de la zona urbana.. 20.25 UMA por pieza\nb).- En zona comprendida fuera del perímetro descrito en el inciso a) anterior............ 13.50 UMA por pieza\nEn caso de excederse de este plazo, se tratará el trámite como licencia nueva.\nSolamente cuando la regularización se inicie en un mes intermedio del año, se podrá considerar la tarifa por los meses restantes al ejercicio fiscal.\nCERTIFICADO DE MEJORAMIENTO DE LA IMAGEN URBANA\nARTÍCULO 34.- Es el documento expedido por la Dirección de\nAdministración Urbana, en el que se hace constar el estado físico de un predio urbano no edificado o baldío; conforme se determina en\nEnsenada, Baja California. la Imagen Urbana conforme a las bases para su otorgamiento, tendrán\nPredial.\nA).- Predios no Edificados o Baldíos:\nI.- Los predios no edificados o baldíos deberán: estar libre de basura, maleza, escombro, cascajo o cualquier otro residuo, desecho o desperdicio........... 20%\nII.- Contar con guarniciones y banquetas en buen estado que permitan el libre tránsito peatonal o con iluminación dentro del inmueble................................... 10%\nIII.- Tener en sus colindancias barda, cerco de malla ciclónica, estructura metálica o similar debidamente rigidizados, con elementos estructurales uniformes. Libre de grafiti en muros propios o ajenos.......... 10%\nIV.- Tener cerco similar a lo anterior en sus colindancias............................... 5%\nTOTAL...................................... 45%\nB).- Para predios no edificados o baldíos, que se localicen dentro de las zonas comerciales o industriales, además de lo anterior, deberá contener:\nI.- Si se ubica en esquina, contar con adecuaciones para personas con discapacidad............................... 5%\nII.- Si se usa como bodega al aire libre para cualquier tipo de material, contar con barda de mampostería, concreto o similar al frente y en sus colindancias, pintada y en buen estado................................ 5%\nIII.- Contar con árboles al frente del predio, con espacio de seis metros entre cada uno....... 5%\nIV.- En caso de contar con anuncios espectaculares, cumplir con lo dispuesto por la normatividad que resulte aplicable. 5%\nTOTAL 20%\nMejoramiento de la Imagen Urbana:\nI.- Acreditar ser propietario o poseedor de un inmueble urbano que se encuentre no edificado o baldío.\nII.- Al momento de inscribirse para adquirir el\nCertificado de Mejoramiento de la Imagen Urbana, pagar la tarifa correspondiente, conforme a la siguiente tabla:\nCOSTO DEL CERTIFICADO\nVALOR CATASTRAL UNIDAD DE MEDIDA Y\nACTUALIZACIÓN\nDE A (UMA) VIGENTE\n$ 0 $37,200 0.34\n37,201 93,000 0.68\n93,001 186,000 2.03\n186,001 279,000 3.38\n279,001 372,000 5.40\n372,001 558,000 8.10\n558,001 744,000 10.80\n744,001 1’116,000 16.20\n1’116,001 1’488,000 20.25\n1’488,001 1’860,000 27.00\n1’860,001 2’232,000 33.75\n2’232,001 2’604,000 39.15\n2’604,001 2’976,000 43.88\n2’976,001 3’348,000 50.63\n3’348,001 3’720,000 57.38\n3’720,001 4’464,000 64.13\n4’464,001 5’208,000 74.25\n5’208,001 5’902,000 87.75\n5’902,001 6’696,000 97.88\n6’696,001 7’440,000 108.00\n7’440,001 8’164,000 118.13\n8’164,001 8’928,000 121.50\n8’928,001 9’672,000 124.88\n9’672,001 10’416,000 128.25\n10’416,001 11’160,000 131.63\n11’160,001 En adelante 135.00\nIII.- En caso de haber cumplido con los requisitos señalados en los incisos A) o B), para obtener el estímulo fiscal correspondiente, la autoridad de la Dirección de Administración Urbana realizará una inspección, otorgando en su caso, el Certificado de Mejoramiento de la Imagen\nUrbana.\nARTÍCULO 35.- Los propietarios de giros comerciales e industriales o aquellos que necesiten por razones propias del desarrollo de la actividad que ejerza, ocupar sitios exclusivos de estacionamiento o para el ingreso y salida de vehículos, deberán obtener autorización escrita de la autoridad municipal, debiendo pagar anualmente los derechos por este concepto, de acuerdo a la siguiente clasificación:\nA).- Con señalamiento de cordones para sitios exclusivos de estacionamiento de vehículos en zonas de tiempo limitado por espacio de automóvil, se entenderá zonas de tiempo limitado:\nUNIDAD DE MEDIDA Y ACTUALIZACIÓN (UMA) VIGENTE\na).- En batería......................... 0.19 UMA POR DÍA\nb).- En cordón.......................... 0.26 UMA POR DÍA\nB).- Con señalamiento de cordones para sitios exclusivos ilimitado, deberán pagar el 75.00% de la cuota del inciso A) anterior, por espacio de un automóvil.\nC).- Con señalamiento de cordones para sitios exclusivos de estacionamiento de vehículos en zonas habitacionales de tiempo ilimitado, deberán pagar el 50.00% de la cuota del inciso A) anterior, por espacio de un automóvil.\nD).- Por el estacionamiento de vehículos en zona de tiempo limitado:\n1.- Comprobante de pago por el Derecho de estacionarse en zonas de tiempo limitado, hasta de un máximo de dos horas consecutivas, para vehículos con placas nacionales, una cuota de 1.65 UMA por año.\nEl pago del Derecho antes referido es obligatorio, respecto de la zona urbana del\nMunicipio de San Quintín, Baja California.\nLos estacionamientos exclusivos para vehículos no serán utilizados para talleres de reparación o renta de cualquier clase de vehículos; así mismo queda prohibido el ejercicio comercial en estos espacios.\nEl pago de estos derechos deberá efectuarse por el interesado al momento en que se solicite el servicio.\nE).- Infracciones por excederse de dos horas consecutivas, si se liquida dentro de los 15 días siguientes....................................... 0.25 UMA\nF).- Infracciones por excederse de dos horas consecutivas, si se liquida después de los 15 días siguientes........................................ 0.50 UMA\nG).- Ocupación de rampas por cada metro lineal que exceda de seis metros, pagarán.................. 0.05 UMA\nH).- Zona exclusiva de carga y descarga por cada metro lineal, pagarán.................................. 0.05 UMA\nI).- Por ruptura o demolición de pavimentos, cordones y banquetas, sondeos de tuberías e instalaciones; gas, agua, cable, comunicaciones, en general de instalaciones subterráneas, instalación de señalamientos, topes y otras municipal, pagando por anticipado por metro lineal........................................... 0.50 UMA\nJ).- Por pintar o colocar señales que indiquen vigente.......................................... 1.00 UMA por día por metro lineal\nK).- Los propietarios de giros comerciales e industriales o aquellos que gocen de sitios exclusivos de estacionamiento en vía pública tendrán como fecha límite el día 31 de enero y/o el último día hábil del mes de enero, para realizar su renovación, de lo contrario se harán acreedores a una sanción.......................... 4.00 UMA por metro lineal\nL).- Los propietarios de giros comerciales e industriales o aquellos que gocen de sitios exclusivos de estacionamiento o para el ingreso o salida de vehículos en vía pública, que cuenten con autorización escrita de la autoridad municipal, deberán pagar solo por este ejercicio fiscal 2025, los derechos por los sitios autorizados durante el mes de julio........................... 12.00 UMA por metro lineal\nL.1).- Si el propietario pinta por su propia cuenta metros lineales de más, se hará acreedor a una sanción por no contar con el permiso del excedente................................. 1.00 UMA por día por metro lineal\nM).- Por recepción, análisis y emisión de opiniones técnicas de ocupación de la vía pública.......... 4.00 UMA\nN).- Por recepción, análisis y emisión de opiniones técnicas de ocupación de la vía pública, por altos de disco, topes, vados y otros elementos disparadores de velocidad......................... 2.00 UMA\nO).- Por la canalización de instalaciones subterráneas, tales como: cable conductor, fibra óptica, tuberías, instalación de casetas telefónicas y postes de luz o similar. Los se determinarán de acuerdo a las siguientes cuotas o tarifas: se calcularán, determinarán y cubrirán por los sujetos obligados, por construcción de tuberías, tendido de cables, fibras ópticas o similares y conducciones, aéreas de uso público y privado, sean eléctricas, telefónicas, telecomunicaciones, de transportación de gas domiciliario o industrial u otros, se pagará por metro lineal:\na).- Líneas aéreas................................ 0.90 UMA\nb).- Líneas subterráneas.......................... 0.10 UMA\nc).- Casetas telefónicas.......................... 1.21 UMA\nd).- Postes de luz y teléfono..................... 1.21 UMA\nESTACIONAMIENTOS PÚBLICOS FIJOS\nARTÍCULO 36.- El pago de derechos por permiso y/o licencia de\nEstacionamientos Públicos Fijos, se cobrará de la siguiente manera:\nTARIFA\nUNIDAD DE MEDIDA Y ACTUALIZACIÓN (UMA) VIGENTE\nI.- Licencias para estacionamiento público fijo, se cobrará de acuerdo a la capacidad del estacionamiento, conforme a la siguiente tarifa:\na).- De 1 a 25 vehículos........................ 182.25 UMA\nb).- De 26 a 50 vehículos....................... 229.50 UMA\nc).- De 51 a 75 vehículos....................... 270.00 UMA\nd).- De 76 a 100 vehículos...................... 324.00 UMA\ne).- De 101 vehículos en adelante................ 371.25 UMA\nII.- La revalidación de la licencia anual, se cobrará de acuerdo a la capacidad del estacionamiento, conforme a la siguiente tarifa:\na).- De 1 a 25 vehículos........................ 40.50 UMA\nb).- De 26 a 50 vehículos....................... 54.00 UMA\nc).- De 51 a 75 vehículos....................... 67.50 UMA\nd).- De 76 a 100 vehículos...................... 81.00 UMA\ne).- De 101 vehículos en adelante................ 94.50 UMA\nIII.- Las multas a los estacionamientos no regulados, se cobrarán conforme a lo siguiente:\na).- De 1 a 25 vehículos........................ 62.68 UMA\nb).- De 26 a 50 vehículos....................... 75.21 UMA\nc).- De 51 a 75 vehículos....................... 100.28 UMA\nd).- De 76 a 100 vehículos...................... 112.82 UMA\ne).- De 101 vehículos en adelante................ 125.37 UMA\nIV.- Las multas a los estacionamientos públicos permanentes y transitorios, por incumplimiento de cada uno de los requisitos operativos y lineamientos técnicos, se cobrarán de acuerdo a la siguiente tarifa:\na).- De 1 a 25 vehículos........................ 62.68 UMA\nb).- De 26 a 50 vehículos....................... 75.21 UMA\nc).- De 51 a 75 vehículos....................... 100.28 UMA\nd).- De 76 a 100 vehículos...................... 112.82 UMA\ne).- De 101 vehículos en adelante................ 125.37 UMA\nESTACIONAMIENTOS PÚBLICOS TRANSITORIOS\nARTÍCULO 37.- El pago de derechos por permiso de estacionamientos públicos transitorios, se cobrará de la siguiente manera:\nTARIFA\nUNIDAD DE MEDIDA Y ACTUALIZACIÓN (UMA) VIGENTE\nI.- Licencias para estacionamiento público transitorio, se cobrarán de acuerdo a la capacidad del estacionamiento, conforme en la siguiente tarifa:\na).- De 1 a 25 vehículos........................ 13.50 UMA\nb).- De 26 a 50 vehículos....................... 27.00 UMA\nc).- De 51 a 75 vehículos....................... 54.00 UMA\nd).- De 76 a 100 vehículos...................... 67.50 UMA\ne).- De 101 vehículos en adelante................ 81.00 UMA\nII.- Las multas a los estacionamientos no regulados, se cobrarán conforme a lo siguiente:\na).- De 1 a 25 vehículos........................ 62.68 UMA\nb).- De 26 a 50 vehículos....................... 75.21 UMA\nc).- De 51 a 75 vehículos....................... 100.28 UMA\nd).- De 76 a 100 vehículos...................... 112.82 UMA\ne).- De 101 vehículos en adelante................ 125.37 UMA\nIII.- Las multas a los estacionamientos públicos permanente y transitorios por incumplimiento de cada uno de los requisitos operativos y lineamientos técnicos, se cobrarán de acuerdo a la siguiente tarifa:\na).- De 1 a 25 vehículos........................ 62.68 UMA\nb).- De 26 a 50 vehículos....................... 75.21 UMA\nc).- De 51 a 75 vehículos....................... 100.28 UMA\nd).- De 76 a 100 vehículos...................... 112.82 UMA\ne).- De 101 vehículos en adelante................ 125.37 UMA\nARTÍCULO 38.- Los propietarios de vehículos de transporte público de pasajeros que necesitan la ocupación de la vía pública, para sitios exclusivos, deberán obtener autorización escrita de la autoridad municipal, y deberán pagar la tarifa siguiente.\nEn batería y en cordón................................. 33.75 UMA\nECOLOGÍA Y MEDIO AMBIENTE\nARTÍCULO 39.- Los servicios en esta materia se cobrarán conforme a la siguiente tarifa:\n1. Por verificación e inspección de solicitud de licencia ambiental................................ 4.05 UMA\n1.1. Por recepción y evaluación de informe preventivo (Construcción y Operación):\na) De 1.00 a 250.00 m²................... 37.70 UMA\nb) De 251.00 a 500.00 m²................. 54.00 UMA\nc) De 501.00 a 1,000.00 m²............... 114.75 UMA\nd) De 1,001.00 a 2,000.00 m²............. 128.25 UMA\ne) De 2,001.00 a 3,000.00 m²............. 141.75 UMA\nf) De 3,001.00 a 4,000.00 m2............. 155.25 UMA\ng) De Mayor de 4,001.00 m²............... 162.00 UMA\n2.- Por recepción y evaluación de Manifiesto de Impacto\nAmbiental (MIA) modalidad específico.............. 162.00 UMA\n3.- Cambio de Propietario y/o razón social, Fusión, Transferencia de derechos......................... 47.25 UMA\n4.- Regularización de actividades de obra civil, comercio y servicios y otros...................... 40.50 UMA\n5.- Análisis de prórroga para presentar información adicional en Materia de Impacto Ambiental (Por única vez)........................................ 13.50 UMA\n6.- Registro de emisiones a la atmósfera por fuente fija............................................. 27.00 UMA\n6.1.- Revalidación de registro de emisiones a la atmósfera por fuente fija................. 13.50 UMA\n7.- Registro de fuentes fijas de descarga de aguas residuales comerciales y servicios............... 27.00 UMA\n7.1.- Revalidación de registro de fuentes fijas de descarga de aguas residuales comerciales y servicios............................... 13.50 UMA\n8.- Por permiso para la remoción, trasplante o poda de árboles:\na).- Por cada árbol por motivo de presentar riesgo a infraestructura.................... 4.05 UMA\nb).- Por cada árbol por motivo de construcción.... 67.50 UMA\nc).- Por cada árbol por motivos de daños a particulares................................. 1.35 UMA\nd).- La verificación e inspección por cada solicitud de remoción, poda o trasplante de árbol........................................ 0.27 UMA\ne).- Por cada árbol que se encuentra en la vía pública por motivos de remoción.............. 33.75 UMA\nf).- Por cada árbol por motivos de poda........... 0.68 UMA\ng).- Por cada árbol por motivo de trasplante...... 13.50 UMA\n9.- Licencia de prestador de servicios de recolección y transporte de residuos sólidos urbanos y de manejo especial, por unidad y anual. 101.25 UMA\n10.- Licencia de prestadores de servicios para el transporte de agua residual doméstica y comercial:\na) Doméstica.................................. 67.50 UMA\nb) Comercial.................................. 101.25 UMA\n11.- Licencia de prestador de servicios de transporte de materiales pétreos........................... 101.25 UMA\n12.- Licencia de prestador de servicios de transporte de materiales pétreos producto de la construcción.................................... 33.75 UMA\n13.- Licencia Ambiental ingresada a través del Sistema de Apertura Rápida de Empresas SARE, hasta\n200m² de superficie de operación.\n1) Hasta 50 m² en superficie de operación..... 16.20 UMA\n2) Desde 51 m² hasta 100 m² en superficie de operación.................................. 20.25 UMA\n3) Desde 101 m² hasta 150 m² en superficie de operación.................................. 24.30 UMA\n4) Desde 151 m² hasta 200 m² en superficie de operación.................................. 27.00 UMA\n14.- Licencia Ambiental para el manejo, transporte y disposición final de residuos producto de la demolición (residuos especiales) parcial o total de inmuebles.................................... 20.25 UMA\n15).- Por Licencia Ambiental temporal (90 días):\na).- Circos\nb).- Teatro de carpa\nc).- Ventas de artículos navideños en cualquier modalidad\nd).- Mercados sobre ruedas\nPor cada uno de los incisos anteriores.......... 33.75 UMA\n16.- Licencia Ambiental para autorización de eventos temporales:\na) De 1 a 500 personas......................... 33.75 UMA\nb) De 501 a 1,000 personas..................... 54.00 UMA\nc) Mayor a 1,000 personas...................... 81.00 UMA\nd) Evento temporal sin fines de lucro.......... 0.00 UMA\n17.- Licencia Ambiental para la evaluación de obra civil para casa habitación...................... 27.00 UMA\n18.- Licencia Ambiental para la construcción y operación de antenas de telecomunicaciones...... 101.25 UMA\n19.- Licencia Ambiental para la evaluación de proyectos de áreas verdes de fraccionamientos.............. 67.50 UMA\n20.- Licencia Ambiental para comercio ambulante fijo y semifijo........................................ 13.50 UMA\n21.- Licencia Ambiental para la operación de pantallas electrónicas o digitales........................ 108.00 UMA\n22.- Licencia Ambiental para autorización de aprovechamiento del terreno en predios sin vegetación nativa............................... 47.25 UMA\n23.- Modificación de proyectos autorizados............ 40.50 UMA\n24.- Prórroga para dar cumplimiento a condiciones de impacto ambiental............................... 6.75 UMA\n25.- Licencia Ambiental para funcionamiento de domésticos...................................... 6.75 UMA\n26.- Cuando se realice el pago correspondiente de los derechos indicados en el numeral 9 y 12, durante el primer trimestre del año, se hará un descuento del 15% del costo del servicio.\n27.- Licencia Ambiental por construcción y operación de anuncios espectaculares...................... 162.00 UMA\n28.- Revalidación anual de la licencia ambiental de operación....................................... 20.25 UMA\n29.- Módulos informativos y/o de venta (hasta 90 días naturales)...................................... 20.25 UMA\n30.- Licencia Ambiental para centro de acopio de doméstico, con finalidad de servicio comunitario, no comercial.................................... 0.00 UMA\n31.- Licencia Ambiental para recolección de residuos sólidos urbanos reciclables de origen doméstico, con finalidad de servicio comunitario, no comercial....................................... 0.00 UMA\n32.- Licencia Ambiental para la construcción y operación de vallas publicitarias por metro cuadrado........................................ 1.35 UMA\n33.- Licencia Ambiental para operación de negocio ecoresponsable..................................... 20.25 UMA\n34.- Licencia de prestador de servicios de recolección y transporte de residuos sólidos urbanos de origen doméstico:\na) Primera unidad............................. 40.50 UMA\nb) Por unidad adicional....................... 20.25 UMA\n35.- Licencia Ambiental de operación para asociaciones civiles registradas, que prestan servicio comunitario en actividades sin fines de lucro... 0.00 UMA\n36.- Licencia Ambiental de comercios y servicios para la compra venta de autopartes nuevas y usadas:\na) De 1.00 a 500.00 m²........................ 54.00 UMA\nb) De 501.00 a 1,000.00 m²...................... 114.75 UMA\nc) De 1,001.00 a 2,000.00 m².................. 128.25 UMA\nd) De 2,001.00 a 3,000.00 m².................. 141.75 UMA\ne) De 3,001.00 a 4,000.00 m².................. 155.25 UMA\nf) De Mayor de 4,001.00 m².................... 162.00 UMA\n37.- Licencia Ambiental de comercios y servicios para talleres (mecánicos, carrocería, pintura, alineación y balanceo, afinación, frenos y mantenimiento, etc.):\na) De 1.00 a 500.00 m²........................ 54.00 UMA\nb) De 501.00 a 1,000.00 m²...................... 114.75 UMA\nc) De 1,001.00 a 2,000.00 m².................. 128.25 UMA\nd) De 2,001.00 a 3,000.00 m².................. 141.75 UMA\ne) De 3,001.00 a 4,000.00 m².................. 155.25 UMA\nf) De Mayor de 4,001.00 m².................... 162.00 UMA\nCAPÍTULO VI\nARTÍCULO 40.- Los Derechos por los servicios que presta la\nCoordinación de Infraestructura.\nI.- POR PARTICIPAR EN UN PADRÓN:\n1).- Inscripción contratistas................... 50.00 UMA\n2).- Inscripción proveedores.................... 50.00 UMA\n3).- Revalidación contratistas................... 43.00 UMA\n4).- Revalidación proveedores................... 23.00 UMA\nA partir de la fecha de expedición de la convocatoria, se encontrará vigente durante dos meses, después del transcurso de este periodo, tendrá que considerarse inscripción.\nII.- POR PARTICIPAR EN CONCURSOS:\n1).- Invitación a cuando menos 3 contratistas o proveedores................................ 10.00 UMA\n2).- Licitación de obra pública................. 40.00 UMA\n3).- Licitación de arrendamiento o servicio:\nEl costo será fijado en razón de la recuperación de las erogaciones por publicación de la convocatoria y reproducción de los documentos.\nIII.- PAGO DE DERECHOS POR INSPECCIÓN Y OPINIÓN TÉCNICA:\n1).- De altos en vía pública.................... 13.00 UMA\n2).- De rupturas de banquetas y pavimentos...... 13.00 UMA\n2.1) Depósito en garantía............... DE 18.20 A\n187.20 UMA\n2.2) Por inspección para devolución de garantía........................... 5.20 UMA\n3).- De valoración de daños en vía pública...... 13.00 UMA\nEn el caso de contar con registro y no revalidar; al actualizar su registro, se deberá considerar como alta. mayor de 80 km, fuera de la mancha urbana, se cobrará en un 100% sobre el costo estipulado para la inspección que corresponda.\nCAPÍTULO VII\nSERVICIOS QUE PRESTA LA COORDINACIÓN DE SERVICIOS PÚBLICOS, A TRAVÉS\nDE:\n1.- SERVICIOS QUE PRESTA EL DEPARTAMENTO DE MANTENIMIENTO DE BIENES\nMUNICIPALES, PARQUES, JARDINES, ÁREAS VERDES Y PANTEONES\nARTÍCULO 41.- Los derechos por estos servicios se pagarán de acuerdo a la siguiente:\nUNIDAD DE MEDIDA Y ACTUALIZACIÓN (UMA) VIGENTE\na).- Inhumaciones a perpetuidad........................ 20.25 UMA\nb).- Inhumaciones y apertura de fosa, refrendo (cada 7 años)............................................ 27.00 UMA\nc).- Pago por derecho de exhumación.................... 8.10 UMA\nd).- Apertura de fosa.................................. 4.05 UMA\ne).- Reinhumación..................................... 2.70 UMA\nf).- Inhumación a perpetuidad de cenizas............... 6.75 UMA\ng).- Inhumaciones y refrendo de cenizas (cada 5 años). 1.35 UMA\nh).- Reinhumación de Cenizas........................... 1.35 UMA\nEn las oficinas por trámite:\ni).- Lápida........................................... 4.05 UMA\nj).- Permiso por cabezal.(40x60x8 cm.)................. 4.05 UMA\nk).- Sobre caja........................................ 4.05 UMA\nl).- Plancha.......................................... 4.05 UMA\nm).- Cordón........................................... 4.05 UMA\nn).- Boleta de perpetuidad............................. 4.05 UMA ñ).- Cerco metálico.................................... 4.05 UMA\no).- Otros servicios................................... 4.05 UMA\np).- Construcción sobre caja cabezal en el panteón.... 33.75 UMA\nq).- Caja e inscripción de cabezal en caso de reinhumación en el panteón....................... 27.00 UMA\nr).- Refrendo por única vez (7 años)................... 6.75 UMA\ns).- Permiso de construcción (En área de 2m de profundidad 2.20m de largo y 1.00m de ancho)..... 6.75 UMA realice el área que se determine para este efecto.\na).- Son solidariamente responsables del pago de los derechos referidos, las personas físicas, morales o unidades económicas que presten este servicio fúnebre.\nb).- Por inhumaciones de cadáveres en tiempo extraordinario después de los horarios fijados por el Ayuntamiento de San Quintín para el servicio de panteones, se pagará el doble de las cuotas establecidas en éste Artículo.\n2.- COORDINACIÓN DE SERVICIOS PÚBLICOS (RASTRO).\nARTÍCULO 42.- Los derechos por este servicio serán cubiertos por el introductor o propietario, al solicitar el sacrificio de ganado\n(incluyendo el servicio de refrigeración por las primeras 24 horas, servicio de báscula y el lavado de menudo).\nARTÍCULO 43.- Los derechos por cabeza de ganado sacrificado en el\nRastro o en las Delegaciones (El Mármol, Bahía de los Ángeles, Punta\nPrieta y Villa de Jesús María), se pagarán de acuerdo con la siguiente tarifa:\nUNIDAD DE MEDIDA Y ACTUALIZACIÓN (UMA) VIGENTE\nI.- Ganado Vacuno................................... 6.50 UMA\nII.- Ganado Porcino.................................. 4.00 UMA\nIII.- Ganado Caprino o Lanar.......................... 2.50 UMA\nIV.- Ganado Caballar................................. 5.50 UMA\nV.- Otro tipo de animales........................... 3.00 UMA dentro de las 24 horas siguientes a la matanza. El Ayuntamiento de San Quintín quedará relevado de toda responsabilidad, en establecido.\nARTÍCULO 44.- En las Delegaciones Municipales (El Mármol, Bahía de los Ángeles, Punta Prieta y Villa de Jesús María) en que no exista\nRastro, se pagará por expedición de permiso de matanza por cabeza de ganado sacrificado, de acuerdo a la siguiente:\nUNIDAD DE MEDIDA Y ACTUALIZACIÓN (UMA) VIGENTE\nI.- Ganado Vacuno................................... 1.00 UMA\nII.- Ganado Porcino.................................. 1.00 UMA\nIII.- Ganado Caprino o Lanar.......................... 1.00 UMA\nIV.- Ganado Caballar................................. 1.00 UMA\nARTÍCULO 45.- Derechos por otros servicios que presta el Rastro o las Delegaciones Municipales (El Mármol, Bahía de los Ángeles, Punta\nPrieta y Villa de Jesús María).\nA).- Después de 24 horas siguientes de la matanza por cada día de refrigeración, se cobrará por cada animal sacrificado, de acuerdo a la siguiente:\nUNIDAD DE MEDIDA Y ACTUALIZACIÓN (UMA) VIGENTE\nI.- Ganado Vacuno...................... 5.50 UMA por cada\n24 horas adicionales\nII.- Ganado Porcino...................... 4.50 UMA por cada\n24 horas adicionales\nIII.- Ganado Caprino o Lanar............. 3.10 UMA por cada\n24 horas adicionales\nIV.- Ganado Caballar...................... 6.60 UMA por cada\n24 horas adicionales\nV.- Otro tipo de animales................ 2.00 UMA por cada\n24 horas adicionales\nB).- Por la estancia de un animal en los corrales del\nRastro, después de las primeras 24 horas se pagará por cada día, por cabeza (no incluye alimento)... 1.00 UMA\nC).- Por el sacrificio ocasional de ganado fuera del horario establecido, por animal................... 1.00 UMA\nD).- Por guía de traslado de animales.................. 1.00 UMA\n3.- SERVICIOS QUE PRESTA EL DEPARTAMENTO DE RECOLECCIÓN DE BASURA Y\nLIMPIA\nARTÍCULO 46.- Los Derechos que por el servicio de recolección y disposición de residuos sólidos urbanos que sean contratados por personas físicas o morales, deberá pagarse conforme a la siguiente:\nUNIDAD DE MEDIDA Y ACTUALIZACIÓN (UMA) VIGENTE\na) Por levante de residuos sólidos que no exceda 1 tonelada......................................... 18.00 UMA\nb) Por levante de residuos sólidos que exceda 1 tonelada, 18.00 UMA por cada tonelada y por fracción que exceda dicha medida.\nc) Limpia y recolección de residuos sólidos en domicilios particulares, terrenos baldíos, unidades habitacionales, vía pública y otros..... 30.00 UMA\nPOR TONELADA efecto realice el Departamento de Recolección de Basura y Limpia, en proporción al servicio prestado.\nARTÍCULO 47.- Los derechos por recepción de basura comercial, industrial, de prestadores de servicios y demás similares, en el relleno sanitario municipal, deberá pagarse conforme a lo siguiente:\nPor cada tonelada..................................... 6.00 UMA propiedad en el relleno sanitario municipal.\n4.- DERECHOS POR SERVICIO DE MANTENIMIENTO continuación, y que sean propiedad del Municipio de San Quintín, serán fijados por la dirección, de acuerdo con el catálogo de precios unitarios emitido.\na) Por daños al alumbrado público, serán fijados en cada caso, de acuerdo al valor del mercado al momento del daño.\nb) Por daños a los semáforos, serán fijados en cada caso, de acuerdo al valor del mercado al momento del daño.\nc) Por daños a las áreas verdes y camellones centrales, serán fijados en cada caso, de acuerdo al valor del mercado al momento del daño.\nd) Por daños a monumentos, serán fijados en cada caso, de acuerdo al valor del mercado al momento del daño.\ne) Por daños al señalamiento vial, serán fijados en cada caso, de acuerdo al valor del mercado al momento del daño.\nf) Por grafiti, serán fijados en cada caso, de acuerdo al valor del mercado al momento del daño.\ng) Por daños a los vehículos utilitarios, serán fijados en cada caso, de acuerdo al valor del mercado al momento del daño.\nCAPÍTULO VIII\nSERVICIOS QUE PRESTAN LAS DIRECCIONES DE SEGURIDAD PÚBLICA,\nPROTECCIÓN CIVIL Y BOMBEROS A TRAVÉS DE:\n1.- SERVICIOS QUE PRESTA LA COORDINACIÓN DE POLICÍA Y TRÁNSITO\nUNIDAD DE MEDIDA Y ACTUALIZACIÓN (UMA) VIGENTE\nARTÍCULO 48.- Las empresas dedicadas a la prestación de servicios y monitoreo de alarmas, deberán cubrir un importe anual, por los servicios de asistencia que brinde la Dirección de Seguridad Pública, con motivo de respuesta a los llamados de los sistemas de alarmas instalados en comercios, industrias y casa habitación... 137.70 UMA\nARTÍCULO 49.- Análisis de factibilidad para la prestación de\nServicios de la Dirección de Seguridad Pública, en proyectos de estudios de factibilidad solicitados por la Dirección de Comercio, Alcoholes y Espectáculos Públicos...................... 44.55 UMA\nARTÍCULO 50.- Los particulares que soliciten de manera individual o tránsito y capacitaciones, deberán cubrir los derechos por los servicios que brinde la Coordinación de Policía y Tránsito:\na).- Por persona...................................... 5.00 UMA\nb).- Por grupo de 10 personas......................... 32.00 UMA\n2.- SERVICIOS DE VIGILANCIA POLICÍACA\nARTÍCULO 51.- Los servicios que preste el Ayuntamiento de San Quintín se prestan a domicilios particulares, giros comerciales e instituciones de servicio u otros que lo soliciten, así como los servicios de escolta, se deberán cubrir de acuerdo a lo siguiente:\nUNIDAD DE MEDIDA Y ACTUALIZACIÓN (UMA) VIGENTE\nI.- SERVICIOS DE VIGILANCIA EN PUNTOS FIJOS:\n1.- Por agente armado, por turno de ocho horas....... 20.00 UMA\n2.- Por agente armado en vigilancia comunitaria en zonas habitacionales (contratadas por asociaciones civiles) por cada elemento, por turno de ocho horas............................................ 20.00 UMA\n3.- Por agente armado en vigilancia a instituciones gubernamentales por cada elemento, por turno de ocho horas............................................ 20.00 UMA\n4.- Por agente armado en contrato celebrado por más de\n90 días naturales, contratando 5 o más elementos, por turno de ocho horas.......................... 20.00 UMA\n5.- Agente armado en eventos masivos por turno de hasta ocho horas........................................ 20.00 UMA\n6.- Agente para servicios protección personal a particulares por elemento armado de ocho horas.... 20.00 UMA\nII.- Servicio de vigilancia a cargo de inspectores de Seguridad\nCiudadana:\n1.- En punto fijo por elemento desarmado, por turno de ocho horas........................................ 11.48 UMA\n2.- Por vigilancia comunitaria en zonas habitacionales\n(contratados por asociaciones civiles) por elemento desarmado por turno de ocho horas................ 10.13 UMA\n3.- Por vigilancia a instituciones gubernamentales por cada elemento desarmado, por turnos de ocho horas............................................ 10.13 UMA\n4.- Por contrato celebrado por más de 90 días naturales contratando 5 o más elementos desarmados por turno de ocho horas..................................... 10.80 UMA\n5.- Por elemento desarmado en eventos masivos por turno de seis horas............................. 11.48 UMA\nIII.- Por la renta de una unidad patrulla:\n1.- Renta de unidad patrulla con elemento armado por turno de hasta ocho horas....................... 37.00 UMA\nIV.- Por la renta de una unidad motocicleta:\n1.- Servicios de agentes funerales, desfiles, carreras atléticas y/o eventos deportivos, por turno de hasta ocho horas…............................... 37.00 UMA\nV.- Derechos por búsqueda o localización judicial o administrativa:\n1.- Búsqueda o localización de personas y/o domicilios a solicitud de autoridades judiciales y/o administrativas…............................ 6.75 UMA\nCuando la solicitud de búsqueda o localización de personas y/o domicilios, realizada por autoridades judiciales y/o administrativas sea a petición de alguna dependencia de la administración pública municipal centralizada, desconcentrada o sus entidades auxiliares, dentro de procesos, estas sean parte, no se cobrarán los derechos correspondientes.\n2.- Por cada hora adicional de servicio contratado, de acuerdo al tipo de servicio, se pagará…......... 1.35 UMA\nALMACENAJE DE VEHÍCULOS\nARTÍCULO 52.- Los derechos por almacenaje de vehículos en predios propiedad del Municipio o del concesionario, causarán después de las primeras 24 horas una cuota diaria de.................. 0.74 UMA\nTratándose de vehículos robados que ingresen al depósito Municipal, competente, se exentará del pago de los derechos de almacenaje de vehículos, siempre y cuando el robo sea reportado dentro de las primeras 72 horas subsecuentes al hecho.\nARRASTRE DE VEHÍCULOS\nARTÍCULO 53.- Los derechos por servicios de grúa que sean prestados por la autoridad municipal, para el arrastre de vehículos incluido el uso de patines, deberán cubrirse de acuerdo a la siguiente:\nI.- POR ARRASTRE\nUNIDAD DE MEDIDA Y ACTUALIZACIÓN (UMA) VIGENTE\na).- Automóviles, Camionetas y Pick-ups............... 10.13 UMA\nb).- Camiones de Pasajeros............................ 13.50 UMA\nc).- Remolques (tráilers)............................. 16.20 UMA\nd).- Remolque de tracto camiones de tres o más ejes, con una o dos cajas.................................. 29.70 UMA\ne).- Autotractores o tractocamión solos o con remolques........................................ 29.70 UMA\nf).- Motocicletas..................................... 10.80 UMA\ng).- Bicicletas....................................... 1.35 UMA\nII.- POR MANIOBRAS lo siguiente:\nA).- Maniobras extras (volcaduras, choques y desperfectos en el sistema de rodamiento):\nA.1).- En caso de volcadura de vehículos ligeros o de carga y/o autobuses.\n1) Volcaduras en áreas planas y aceras de carril de rodamiento.\n2) Volcadura cuando el vehículo sale del camino y cae en un desbarrancamiento a menos de 10 M. de distancia del carril de arrodillamiento.\n3) Volcadura cuando el vehículo sale del camino y cae en un desbarrancamiento a más de 10 M. de distancia del carril de arrodillamiento.\n1).- Automóviles, camionetas y pick-ups.......... 16.20 UMA\n1.1) Cuando el vehículo que se va a remolcar no cuenta con llantas y/o se encuentra imposibilitado de rodar utilizándose el jalón (dolly), así como en camiones y tractocamiones, desatirado en los frenos, de aire volcaduras, salidas de carretera utilización de dos o más ocasiones de equipo para arrastre.\n1.2) Uso de grúa para vehículo con defensa adaptada a la original (spoiler).\n1.3) Uso de maniobra por parte del operador para retirar vehículo de cajón de estacionamiento con alto grado de dificultad.\n1.4) Uso de maniobras con alto grado de dificultad cuando sea necesario retirar el cambio de la transmisión, siendo éste de tracción trasera y/o conlleve un alto riesgo para el operador de grúa.\n2).- Camiones de pasajeros de servicio público particular o de carga...................... 22.95 UMA\n3).- Remolques (tráilers) y autobuses de pasaje.. 29.70 UMA\n4).- Remolque de tracto camiones de tres o más ejes, solo o con remolque.................. 44.55 UMA\nB).- Maniobras inconclusas de grúa, por el evento de presentarse el reglamentado, con la infracción por escrito pero no se realice de grúa se pagarán por vehículo las cuotas siguientes:\n1).- Automóviles, camionetas y pick-ups.......... 5.40 UMA\n2).- Camiones de pasajeros (microbús)............ 8.10 UMA\n3).- Remolques (tráilers) y autobuses de pasaje.. 9.45 UMA\n4).- Remolque de tracto camiones de tres o más ejes, con una o más cajas................... 16.20 UMA\n5).- Motocicletas................................ 5.40 UMA\n6).- Bicicletas.................................. 1.35 UMA\nPara efectos del cobro de los derechos de arrastre y almacenaje así como las maniobras adicionales y para efectos del cobro, el operador deberá señalar en el inventario del vehículo el tipo de servicio y maniobras extraordinarias.\nEn los casos donde el infractor necesite la almacenaje, así como la infracción o multa de que se trate. depósito Municipal, previa comprobación con documentos oficiales de autoridad competente, se vehículo, siempre y cuando el robo sea reportado dentro de las primeras 72 horas subsecuentes al hecho.\n3.- SERVICIOS QUE PRESTAN LAS DIRECCIONES DE PROTECCIÓN CIVIL Y DE\nBOMBEROS.\nI.- LA DIRECCIÓN DE PROTECCIÓN CIVIL:\nEsta Dirección se formaliza en el Artículo 146 del Reglamento de la\nAdministración Pública para el Municipio de San Quintín, publicado en el Periódico Oficial del Estado No. 53 de fecha 8 de septiembre de 2023.\nARTÍCULO 54.- Los servicios que presta la Dirección de Protección\nCivil, a giros comerciales, industriales, de servicios, los sectores públicos y sociales, se causarán conforme a la siguiente:\nUNIDAD DE MEDIDA Y ACTUALIZACIÓN (UMA) VIGENTE\nI.- POR FACTIBILIDAD DE PROYECTOS O POR REVISIÓN DE PROYECTOS DE\nCONSTRUCCIÓN:\nCONSTRUCCIÓN REGULARIZACIÓN\n1).- Casa habitación.................. 13.50 UMA 27.00 UMA\n2).- Fraccionamientos (por edificación)............................ 18.90 UMA 37.80 UMA\n3).- Condominios:\na).- De 1 a 5 viviendas.......... 27.00 UMA 54.00 UMA\nb).- De 6 a 10 viviendas......... 54.00 UMA 110.00 UMA\nc).- De 11 a 20 viviendas........ 81.00 UMA 180.00 UMA\nd).- De 21 viviendas en adelante.................... 121.50 UMA 270.00 UMA\n4).- Departamentos habitacionales:\na).- De 1 a 10 viviendas......... 20.25 UMA 40.50 UMA\nb).- Más de 10 viviendas......... 40.50 UMA 81.00 UMA\n5).- Comercial (por metro cuadrado):\na).- Hasta 200m²................. 0.16 UMA 0.34 UMA\nb).- De 201 hasta 400m².......... 0.18 UMA 0.35 UMA\nc).- De 401 hasta 700m².......... 0.19 UMA 0.38 UMA\nd).- De 701 hasta 1,000m²........ 0.22 UMA 0.43 UMA\ne).- De 1,001 hasta 2,000m²...... 0.24 UMA 0.49 UMA\nf).- De más de 2,000m²........... 0.27 UMA 0.54 UMA\n6).- Mixto:\na).- Habitacional-comercial (por metro cuadrado)............. 0.14 UMA 0.27 UMA\nb).- Industrial–comercial (por metro cuadrado)............. 0.18 UMA 0.35 UMA\n7).- Comercio o industrial de alto riesgo........................... 270.00 UMA 540.00 UMA\n8).- Industrial:\na).- De hasta 2,500m²............ 67.50 UMA 150.00 UMA\nb).- Mayor de 2,500m²............ 135.00 UMA 270.00 UMA\n9).- Casas de asistencia, estancias infantiles....................... 13.50 UMA 27.00 UMA\n10).- Escuelas primarias, secundarias por metro cuadrado............... 0.27 UMA 0.47 UMA\n11).- Preparatorias, Universidades, por metro cuadrado................... 0.54 UMA 0.68 UMA\n12).- Anuncios:\na).- Espectaculares.............. 20.25 UMA 27.00 UMA\nb).- Tipo pantalla............... 33.75 UMA 47.25 UMA\n13).- Antena de radiocomunicación y telecomunicaciones............... 270.00 UMA 337.50 UMA\n14).- Otros no especificados........... 27.00 UMA 37.13 UMA\nII.- REGISTRO DE EMPRESAS QUE MANEJAN MATERIALES PELIGROSOS, CON UNA\nVIGENCIA DE UN AÑO:\nREGISTRO REVALIDACIÓN\n1).- Micro industria, de 1 a 25 empleados........................ 13.50 UMA 30.00 UMA\n2).- Pequeña industria, de 26 a 100 empleados........................ 27.00 UMA 60.00 UMA\n3).- Pequeña industria, de 101 empleados en adelante............ 40.50 UMA 90.00 UMA\nIII.- INSPECCIONES DE MEDIDAS DE SEGURIDAD EN EDIFICACIONES, A\nPETICIÓN DE PARTE:\nEN ZONA EN ZONA RURAL\nURBANA (MÁS DE 80 KM.)\n1).- Solicitudes a través de Sistema de\nApertura Rápida de Empresas (SARE):\na).- De 1 a 50 m² de Operación......................... 6.75 UMA 13.50 UMA\nb).- De 51 a 100 m² de Operación......................... 10.13 UMA 20.25 UMA\nc).- De 101 a 150 m² de Operación......................... 13.50 UMA 27.00 UMA\nd).- De 151 a 200 m² de Operación........................ 16.88 UMA 33.75 UMA\n2).- Comercio en pequeño, hasta 50 m² de superficie:\na) Sin venta de bebidas alcohólicas.................. 10.13 UMA 20.25 UMA\nb) Con venta de bebidas alcohólicas.................. 16.88 UMA 33.75 UMA\n3).- Despachos de profesionistas, zapaterías, neverías, casas de cambio y giros de servicios...... 9.45 UMA 18.90 UMA\n4).- Desmanteladoras, recicladoras, panaderías, lavanderías, clínicas, ferreterías, pizzerías, tiendas de ropa, misceláneas, farmacias, papelerías, librerías, telefonía y templos religiosos................ 13.50 UMA 27.50 UMA\n5).- Café Internet, centros de copiado y/o impresión, videojuegos........ 10.80 UMA 21.60 UMA\n6).- Fonda, loncherías, coctelería, cocina económica:\na) Sin venta de bebidas alcohólicas.................. 13.50 UMA 20.25 UMA\nb) Con venta de bebidas alcohólicas.................. 27.00 UMA 40.25 UMA\n7).- Restaurante:\na) Sin venta de bebidas alcohólicas.................. 27.00 UMA 30.25 UMA\nb) Con venta de bebidas alcohólicas.................. 40.50 UMA 67.50 UMA\n8).- Abarrotes, tienda de autoservicio, billares:\na) Sin venta de bebidas alcohólicas.................. 13.50 UMA 20.25 UMA\nb) Con venta de bebidas alcohólicas.................. 40.50 UMA 54.00 UMA\n9).- Mercado, supermercado, bodega de distribución:\na) Sin venta de bebidas alcohólicas.................. 27.00 UMA 40.50 UMA\nb) Con venta de bebidas alcohólicas.................. 60.75 UMA 81.00 UMA\n10).- Establecimientos vitivinícolas o de cervecería artesanal:\na).- Microcervecería............. 16.20 UMA 21.60 UMA\nb).- Cervecería artesanal:\nI).- De hasta 50 personas de ocupación.............. 20.25 UMA 27.00 UMA\nII).- De más de 50 personas de ocupación.............. 40.50 UMA 54.00 UMA\nc).- Establecimientos vitivinícolas:\nI).- Cavas.................. 20.25 UMA 40.50 UMA\nII).- Sala de degustación, boutique.............. 27.00 UMA 40.50 UMA\nIII).- Colectivos.......... 40.50 UMA 54.00 UMA\nd).- Industria y conceptos no especificados............... 54.00 UMA 67.50 UMA\n11).- Licorerías, expendio, centro botanero, agencia, subagencia, depósito.......................... 40.50 UMA 54.00 UMA\n12).- Bar turístico, restaurant-bar, bar terraza........................... 60.75 UMA 81.00 UMA\n13).- Café cantante..................... 60.75 UMA 81.00 UMA\n14).- Discotecas........................ 94.50 UMA 108.00 UMA\n15).- Tiendas departamentales........... 33.75 UMA 43.20 UMA\n16).- Hospital, cines, teatros.......... 27.00 UMA 40.50 UMA\n17).- Centros deportivos, gimnasios:\na).- De 1 hasta 200 personas...... 20.25 UMA 37.80 UMA\nb).- De 201 hasta 500 personas.... 40.50 UMA 54.00 UMA\nc).- De 501 hasta 1,000 personas.. 45.00 UMA 56.00 UMA\nd).- De 1,001 hasta 2,500 personas..................... 55.00 UMA 66.00 UMA\ne).- De 2,501 hasta 5,000 personas..................... 65.00 UMA 75.00 UMA\nf).- De 5,001 personas en adelante..................... 75.00 UMA 85.00 UMA\n18).- Centros Recreativos:\na).- Albercas:\nI).- Sin consumo de bebidas alcohólicas............ 27.00 UMA 40.50 UMA\nII).- Con consumo de bebidas alcohólicas............ 40.50 UMA 47.25 UMA\nb).- Balnearios:\nI).- Sin consumo de bebidas alcohólicas............ 27.00 UMA 51.30 UMA\nII).- Con consumo de bebidas alcohólicas............ 54.00 UMA 60.75 UMA\n19).- Salón para eventos, con capacidad:\na).- De 1 hasta 100 personas:\nI).- Sin consumo de alcohol:\na).- En área abierta... 13.50 UMA 20.25 UMA\nb).- En área cerrada o mixta............. 12.50 UMA 17.50 UMA\nII).- Con consumo de alcohol:\na).- En área abierta... 16.00 UMA 21.00 UMA\nb).- En área cerrada o mixta............. 18.50 UMA 23.50 UMA\nb).- De 101 hasta 200 personas:\nI).- Sin consumo de alcohol:\na).- En área abierta... 20.25 UMA 30.38 UMA\nb).- En área cerrada o mixta............. 23.97 UMA 34.09 UMA\nII).- Con consumo de alcohol:\na).- En área abierta... 28.35 UMA 38.48 UMA\nb).- En área cerrada o mixta............. 32.07 UMA 31.75 UMA\nc).- De 201 hasta 300 personas:\nI).- Sin consumo de alcohol:\na).- En área abierta... 27.00 UMA 40.50 UMA\nb).- En área cerrada o mixta............. 31.05 UMA 44.55 UMA\nII).- Con consumo de alcohol:\na).- En área abierta... 35.10 UMA 48.60 UMA\nb).- En área cerrada o mixta............. 39.15 UMA 52.65 UMA\nd).- De 301 hasta 400 personas:\nI).- Sin consumo de alcohol:\na).- En área abierta... 33.75 UMA 50.63 UMA\nb).- En área cerrada o mixta............. 39.15 UMA 56.03 UMA\nII).- Con consumo de alcohol:\na).- En área abierta... 41.85 UMA 58.73 UMA\nb).- En área cerrada o mixta............. 47.25 UMA 64.13 UMA\ne).- De 401 hasta 500 personas:\nI).- Sin consumo de alcohol:\na).- En área abierta... 40.50 UMA 57.38 UMA\nb).- En área cerrada o mixta............. 47.25 UMA 64.13 UMA\nII).- Con consumo de alcohol:\na).- En área abierta... 48.60 UMA 65.48 UMA\nb).- En área cerrada o mixta............. 41.00 UMA 53.50 UMA\nf).- De 501 hasta 600 personas:\nI).- Sin consumo de alcohol:\na).- En área abierta... 47.25 UMA 68.18 UMA\nb).- En área cerrada o mixta............. 54.00 UMA 74.93 UMA\nII).- Con consumo de alcohol:\na).- En área abierta... 55.35 UMA 76.28 UMA\nb).- En área cerrada o mixta............. 62.10 UMA 83.03 UMA\ng).- De 601 hasta 800 personas:\nI).- Sin consumo de alcohol:\na).- En área abierta... 54.00 UMA 75.60 UMA\nb).- En área cerrada o mixta............. 62.10 UMA 83.70 UMA\nII).- Con consumo de alcohol:\na).- En área abierta... 63.45 UMA 85.05 UMA\nb).- En área cerrada o mixta............. 72.90 UMA 94.50 UMA\nh).- De 801 personas en adelante:\nI).- Sin consumo de alcohol:\na).- En área abierta... 60.75 UMA 83.70 UMA\nb).- En área cerrada o mixta............. 70.20 UMA 93.15 UMA\nII).- Con consumo de alcohol:\na).- En área abierta... 71.55 UMA 94.50 UMA\nb).- En área cerrada o mixta............. 81.00 UMA 103.95 UMA\n20).- Hoteles y moteles:\nA) Sin venta de bebidas alcohólicas:\na).- De 1 a 10 habitaciones. 20.25 UMA 29.70 UMA\nb).- De 11 a 20 habitaciones 27.00 UMA 40.50 UMA\nc).- De 21 a 30 habitaciones 40.50 UMA 56.70 UMA\nd).- De 31 a 40 habitaciones 56.70 UMA 76.95 UMA\ne).- De 41 a 50 habitaciones 72.90 UMA 93.15 UMA\nf).- De 51 a 60 habitaciones 89.10 UMA 109.35 UMA\ng).- De 61 habitaciones en adelante................ 105.30 UMA 125.55 UMA\nB) Con venta de bebidas alcohólicas:\na).- De 1 a 10 habitaciones. 27.00 UMA 36.45 UMA\nb).- De 11 a 20 habitaciones 33.75 UMA 47.25 UMA\nc).- De 21 a 30 habitaciones 47.25 UMA 63.45 UMA\nd).- De 31 a 40 habitaciones 63.45 UMA 83.70 UMA\ne).- De 41 a 50 habitaciones 79.65 UMA 99.90 UMA\nf).- De 51 a 60 habitaciones 129.40 UMA 116.10 UMA\ng).- De 61 habitaciones en adelante................ 112.05 UMA 132.30 UMA\n21).- Instituciones educativas y/o de asistencia privadas:\nA).- Instituciones educativas privadas:\na).- Jardín de niños........ 10.13 UMA 13.50 UMA\nb).- Escuela Primaria....... 10.13 UMA 13.50 UMA\nc).- Escuela Secundaria..... 6.75 UMA 13.50 UMA\nd).- Escuela Preparatoria y/o técnica................ 10.13 UMA 13.50 UMA\ne).- Colegios............... 20.25 UMA 33.75 UMA\nf).- Universidad............ 20.25 UMA 33.75 UMA\ng).- Otros no especificados. 13.50 UMA 27.00 UMA\nB).- Guarderías y estancias infantiles, de acuerdo a su capacidad:\na).- De 1 hasta 10 niños..... 5.07 UMA 10.80 UMA\nb).- De 11 hasta 50 niños.... 10.13 UMA 13.50 UMA\nc).- De 51 hasta 100 niños... 20.25 UMA 33.75 UMA\nd).- Más de 101 niños....... 30.38 UMA 40.50 UMA\nC).- Casa de cuidado y centros de tareas....................... 5.07 UMA 13.50 UMA\nD).- Albergues.................... 10.13 UMA 13.50 UMA\nE).- Casa hogar de asistencia.... 10.13 UMA 13.50 UMA\nF).- Centros de rehabilitación física y de adicciones...... 31.90 UMA 51.03 UMA\n22).- Instalaciones industriales:\na).- Microindustria, hasta 50 empleados.................... 27.00 UMA 40.50 UMA\nb).- Pequeña industria, de 51 a 200 empleados.................... 40.50 UMA 100.00 UMA\nc).- Mediana industria, de 201 a\n500 empleados............... 60.75 UMA 120.00 UMA\nd).- Megaindustria, de 501 a 1,000 empleados.................... 81.00 UMA 150.00 UMA\ne).- Macroindustria, de 1,001 empleados en adelante (por cada 100 empleados o fracción).................... 8.10 UMA 10.00 UMA\n23).- Giros de alto riesgo:\na).- Estaciones de gasolina y gas para carburación............ 81.00 UMA 101.25 UMA\nb).- Distribuidores de gases y químicos..................... 148.50 UMA 180.00 UMA\nc).- Distribuidores de combustible y lubricantes............... 148.50 UMA 168.75 UMA\nd).- Almacenes de materiales peligrosos................... 148.50 UMA 168.75 UMA\ne).- Lugares con venta de pirotecnia................... 81.00 UMA 101.25 UMA\nf).- Polvorines................... 148.50 UMA 168.75 UMA\ng).- Centros de apuestas, apuestas remotas, salas de sorteos de número y/o casinos, dictamen de operación................ 297.00 UMA 324.00 UMA\nh).- Industria de alto riesgo.... 81.00 UMA 101.25 UMA\ni).- Otros de alto riesgo........ 148.50 UMA 168.75 UMA\n24).- Casas de empeño................... 27.00 UMA 47.25 UMA\n25).- Instituciones bancarias y similares......................... 40.50 UMA 60.75 UMA\n26).- Refaccionarias, autopartes, venta de pinturas, venta de productos de limpieza.......................... 23.63 UMA 37.80 UMA\n27).- Mercados comunes o públicos:\na).- En vía o área pública:\nI) De 1 hasta 50 puestos.. 13.50 UMA 20.25 UMA\nII) De 51 hasta 100 puestos................ 20.25 UMA 27.00 UMA\nIII) De 101 hasta 150 puestos................ 27.00 UMA 33.75 UMA\nIV) De 151 hasta 200 puestos................ 33.75 UMA 40.50 UMA\nV) De 201 hasta 250 puestos................ 40.50 UMA 47.25 UMA\nVI) De 251 hasta 300 puestos................ 47.25 UMA 54.00 UMA\nVII) De más de 300 puestos.. 54.00 UMA 60.75 UMA\nb).- En propiedad privada:\nI) De 1 hasta 50 puestos.. 27.00 UMA 33.75 UMA\nII) De 51 hasta 100 puestos................ 33.75 UMA 40.50 UMA\nIII) De 101 hasta 150 puestos................ 40.50 UMA 47.25 UMA\nIV) De 151 hasta 200 puestos................ 47.25 UMA 54.00 UMA\nV) De 201 hasta 250 puestos................ 54.00 UMA 60.75 UMA\nVI) De 251 hasta 300 puestos................ 60.75 UMA 67.50 UMA\nVII) De más de 300 puestos.. 67.50 UMA 91.13 UMA\n28).- Otros giros menores no especificados..................... 20.25 UMA 20.25 UMA\n29).- Otros giros mayores no especificados..................... 47.25 UMA 47.25 UMA\nIV.- INSPECCIONES DE MEDIDAS DE SEGURIDAD EN EDIFICACIONES, DE\nOFICIO:\nSe cobrarán las UMA Vigentes, Unidad de Medida y Actualización, indicado en el apartado anterior, más el 40% del mismo.\nV.- POR SEGUNDA O POSTERIOR VERIFICACIÓN DE CUMPLIMIENTO DE MEDIDAS\nDICTAMINADAS:\nSe cobrarán a razón del 30% del monto establecido en la fracción\nIII anterior.\nVI.- POR REVISIÓN DE PROGRAMA INTERNO DE PROTECCIÓN CIVIL Y/O PLAN\nDE CONTINGENCIAS SUJETO A APROBACIÓN:\nAPROBACIÓN REVALIDACIÓN\n1).- Instituciones educativas y de asistencia:\nA).- Instituciones educativas:\na).- Jardín de niños......... 13.50 UMA 9.45 UMA\nb).- Escuela primaria........ 13.50 UMA 9.45 UMA\nc).- Escuela secundaria...... 16.20 UMA 10.80 UMA\nd).- Escuela preparatoria y/o técnica................. 20.25 UMA 13.50 UMA\ne).- Colegios................ 20.25 UMA 13.50 UMA\nf).- Universidad............. 24.30 UMA 16.20 UMA\ng).- Centros de investigación y desarrollo............ 27.00 UMA 20.25 UMA\nh).- Otros no especificados.. 27.00 UMA 20.25 UMA\nB).- Guarderías y estancias infantiles, de acuerdo a su capacidad:\na).- De 1 hasta 10 niños..... 10.13 UMA 7.09 UMA\nb).- De 11 hasta 50 niños.... 12.15 UMA 8.10 UMA\nc).- De 51 hasta 100 niños... 15.19 UMA 10.13 UMA\nd).- Más de 101 niños........ 20.25 UMA 15.19 UMA\nC).- Casas de cuidado y centros de tareas....................... 13.50 UMA 9.45 UMA\nD).- Albergues.................... 16.20 UMA 10.80 UMA\nE).- Casa hogar o de asistencia... 13.50 UMA 9.45 UMA\nF).- Centros de rehabilitación:\na).- Física.................. 20.25 UMA 13.50 UMA\nb).- De adicciones........... 27.00 UMA 20.25 UMA\nG).- Otros no especificados....... 27.00 UMA 20.25 UMA\n2).- Comercios y de servicios:\nA).- Librerías, papelerías, ferreterías, oficinas, misceláneas, tiendas de ropa, restaurantes, billares, panaderías, lavanderías, farmacias, expendios de comida....................... 13.50 UMA 9.45 UMA\nB).- Bar turístico, café-cantante, autoservicios, restaurantbar, discotecas, expendios de bebidas alcohólicas, moteles, mercados, hoteles............ 24.30 UMA 16.20 UMA\nC).- Salas cinematográficas, lugares para eventos sociales, templos religiosos, centros de convenciones, teatros, salas de exposiciones, bodega de distribución, supermercados, tienda departamental......... 34.40 UMA 24.30 UMA\nD).- Otros giros no especificados:\na).- De menos de 150.00 m² de construcción............ 16.20 UMA 10.80 UMA\nb).- De 150.01 a 300.00 m² de construcción............ 20.25 UMA 13.50 UMA\nc).- De más de 300.00 a 500.00 m² de construcción...... 27.00 UMA 20.25 UMA\nd).- De más de 500.00 m² de construcción............ 33.75 UMA 27.00 UMA\n3).- Instituciones de salud:\nA).- Clínicas y centros de salud.. 13.50 UMA 9.45 UMA\nB).- Centros médicos.............. 16.20 UMA 10.80 UMA\nC).- Hospitales................... 27.00 UMA 20.25 UMA\n4).- Instalaciones industriales:\nA).- Microindustria, hasta 50 empleados.................... 20.25 UMA 13.50 UMA\nB).- Pequeña industria, de 51 a 200 empleados.................... 37.80 UMA 24.98 UMA\nC).- Mediana industria, de 201 a\n500 empleados................ 67.50 UMA 47.25 UMA\nD).- Mega industria, de 501 a 1,000 empleados.................... 81.00 UMA 54.00 UMA\nE).- Macro industria, de más de\n1,000 empleados.............. 94.50 UMA 62.10 UMA\n5).- Giros considerados de alto riesgo:\nA).- Estaciones de gasolina y gas para carburación............. 33.75 UMA 27.00 UMA\nB).- Distribuidores de gas........ 40.50 UMA 33.75 UMA\nC).- Distribuidores de combustibles y lubricantes... 40.50 UMA 33.75 UMA\nD).- Almacenes de materiales peligrosos................... 54.00 UMA 43.20 UMA\nE).- Lugares con venta de pirotecnia................... 40.50 UMA 33.75 UMA\nF).- Centros de apuestas, apuestas remotas, salas de sorteos de números y/o casino........... 270.00 UMA 270.00 UMA\nG).- Otros de alto riesgo......... 40.50 UMA 33.75 UMA\n6).- Otros giros no especificados...... 27.00 UMA 20.25 UMA\nVII.- POR SEGUNDA O POSTERIOR REVISIÓN DE PROGRAMAS INTERNOS\nDE PROTECCIÓN CIVIL Y/O PLAN DE CONTINGENCIAS PARA SU APROBACIÓN:\nSe cobrarán a razón del 50% del monto establecido en el apartado anterior, la segunda y posteriores revisiones al programa interno de Protección\nCivil.\nVIII.- CERTIFICACIÓN DE DAÑOS POR BIENES SINIESTRADOS:\n1).- Todos los daños en general... De 6.75 UMA a 67.50 UMA\nQuedan exceptuados del pago de este derecho, aseguradas al ocurrir el siniestro.\nIX.- POR DETERMINACIÓN DE LAS MEDIDAS DE SEGURIDAD Y DE PROTECCIÓN\nCIVIL NECESARIAS PARA LA REALIZACIÓN DE ACTIVIDADES TEMPORALES:\n1).- Circos:\na).- Chicos (Una pista)...... 10.13 UMA\nb).- Grandes (De dos o más pistas)................. 20.25 UMA\n2).- Juegos mecánicos:\nEn zona Zona Rural urbana (Más de 80 km.)\na).- Chicos: hasta 10 atracciones............. 13.50 UMA 20.25 UMA\nb).- Grandes: más de 10 atracciones............. 27.00 UMA 33.75 UMA\n3).- Exposiciones, ferias y kermeses............. 6.75 UMA\n4).- Exhibición de autos, motos.................. 20.25 UMA\n5).- Carreras o competencias de vehículos (área urbana)..................................... 27.00 UMA\n6).- Carreras de caballos, peleas de gallos...... 27.00 UMA\n7).- Rodeos, jaripeos, charreadas................ 40.50 UMA\n8).- Paseo, caminata rural o turística........... 13.50 UMA\n9).- Eventos deportivos:\nA).- De bajo riesgo:\na).- De 1 hasta 500 asistentes......... 10.80 UMA\nb).- De 501 hasta 1,000 asistentes..... 13.50 UMA\nB).- De alto riesgo:\na).- De 1 hasta 500 asistentes......... 40.50 UMA\nb).- De 501 hasta 1,000 asistentes..... 81.00 UMA\nc).- De 1,001 hasta 2,500 asistentes... 87.75 UMA\nd).- De 2,501 hasta 5,000 asistentes... 94.50 UMA\ne).- De 5,001 hasta 7,500 asistentes... 101.25 UMA\nf).- De 7,501 hasta 10,000 asistentes.. 108.00 UMA\ng).- De 10,001 hasta 15,000 asistentes. 121.50 UMA\nh).- De más de 15,000 asistentes....... 135.00 UMA\n10).- Eventos gastronómicos....................... 13.50 UMA\n11).- Espectáculos:\nEN LUGAR EN LUGAR\nCERRADO ABIERTO\na).- De 1 hasta 500 asistentes.............. 13.50 UMA 13.50 UMA\nb).- De 501 hasta 1,000 asistentes.............. 27.00 UMA 24.30 UMA\nc).- De 1,001 hasta 2,500 asistentes.............. 40.50 UMA 35.10 UMA\nd).- De 2,501 hasta 5,000 asistentes.............. 60.75 UMA 51.30 UMA\ne).- De 5,001 hasta 7,500 asistentes.............. 81.00 UMA 67.50 UMA\nf).- De 7,501 hasta 10,000 asistentes.............. 108.00 UMA 87.75 UMA\ng).- De 10,001 hasta 15,000 asistentes.............. 135.00 UMA 108.00 UMA\nh).- De más de 15,000 asistentes.............. 162.00 UMA 141.75 UMA\n12).- Giros de alto riesgo:\na).- Distribuidores de combustible y lubricantes............................ 40.50 UMA\nb).- Otros giros de riesgo no especificados. 33.75 UMA\n13).- Otros eventos menores, no especificados..... 13.50 UMA\n14).- Otros eventos mayores no especificados...... 40.50 UMA\nLos servicios a los que hace referencia este inciso, quedarán exentos de pago únicamente, cuando sean o humanitarias y no lucrativas, así como las paramunicipales con la finalidad de apoyar su actividad.\nTodo trámite presentado con menos de 15 días naturales a la fecha de realización del evento, pagará un 200% del monto especificado y quedará fuera de la exención referida, de ser el caso.\nX.- SERVICIOS ESPECIALES:\n1).- Cálculo de ocupación para aforo máximo permitido:\nEn Zona Zona Rural\nUrbana (Más de 80 km.) construcción............. 20.25 UMA 27.00 UMA\nb).- De 151 a 500 m² de construcción............. 33.75 UMA 40.50 UMA\nc).- De 501 a 750 m² de construcción............. 40.50 UMA 47.25 UMA\nd).- De 751 a 1,000 m² de construcción............ 47.25 UMA 54.00 UMA\ne).- De 1,001 a 1,500 m² de construcción............ 60.75 UMA 67.50 UMA\nf).- De 1,501 a 2,000 m² de construcción............ 74.25 UMA 81.00 UMA\ng).- De 2,001 a 2,500 m² de construcción............ 87.75 UMA 94.50 UMA\nh).- Más de 2,500 m² de construcción............ 101.25 UMA 108.00 UMA\n2).- Opinión Técnica sobre Análisis de Riesgo:\na).- De acuerdo al uso del predio:\n1).- Casa habitación unifamiliar........ 1.35 UMA por cada 25m² o fracción\n2).- Multifamiliar:\nI) De 1 hasta 4 viviendas...... 13.50 UMA\nII) De 5 hasta 12 viviendas..... 40.50 UMA\nIII) De más de 12 viviendas...... 3.38 UMA por vivienda\n3).- Servicios:\nI) De baja vulnerabilidad...... 10.80 UMA\nII) De media vulnerabilidad..... 27.00 UMA\nIII) De alta vulnerabilidad...... 43.20 UMA\n4).- Comercial:\nI) De 1 hasta 50 personas de ocupación................... 13.50 UMA\nII) De 51 hasta 100 personas de ocupación................... 33.75 UMA\nIII) De 101 hasta de 150 personas de ocupación................ 54.00 UMA\nIV) Más de 150 personas de ocupación................... 67.50 UMA\n5).- Industrial:\nI) De 1 hasta 500 m²........... 20.25 UMA\nII) De 501 hasta 1,000 m²....... 40.50 UMA\nIII) De 1,001 hasta 2,500 m²..... 81.00 UMA\nIV) De 2,501 hasta 10,000 m².... 135.00 UMA\nV) De más de 10,000 m²......... 202.50 UMA\n6).- Mixto: Comercial-habitacional..... 1.35 UMA por cada 20m² o fracción\n7).- Mixto: Industrial-Comercial........ 1.35 UMA por cada 16m² o fracción\n8).- Educativo:\nI) Guarderías y/o preescolares. 13.50 UMA\nII) Primaria y/o secundaria..... 16.20 UMA\nIII) Preparatoria y/o universidad 27.00 UMA\nIV) Mixto....................... 20.25 UMA\n9).- Agrícola, pecuario o forestal.... 1.35 UMA por cada 50m² o fracción\n10).- Alto riesgo........................ 1.35 UMA por cada 12m² o fracción\n3).- Cursos y talleres (por hora):\nEn zona Zona Rural\nUrbana (Más de 80 km.)\nA).- Programa Interno de\nProtección Civil......... 20.25 UMA 27.00 UMA\nB).- Análisis de riesgo y recursos................. 27.00 UMA 40.50 UMA\nC).- Evacuación de Inmuebles.. 20.25 UMA 27.00 UMA\nD).- Señales y avisos de protección civil......... 20.25 UMA 27.00 UMA\nE).- Otros no especificados... 20.25 UMA 27.00 UMA\n4).- Pláticas informativas (por hora):\nA).- Sismos, incendios, ¿Qué hacer en caso de emergencia?.............. 16.20 UMA 27.00 UMA\nB).- Brigadas comunitarias y/o escolares................ 16.20 UMA 27.00 UMA\nC).- Planeación y evaluación de simulacros............... 16.20 UMA 27.00 UMA\nD).- Otros no especificados... 16.20 UMA 27.00 UMA\n5).- Evaluación técnica de simulacros de emergencia:\nEn zona en Zona rural\nUrbana (Más de 80 km.)\nA).- Comercial................ 9.45 UMA 16.20 UMA\nB).- Industrial hasta 2,500\nm²....................... 16.20 UMA 22.95 UMA\nC).- Industrial mayor de 2,500\nm²....................... 24.30 UMA 31.05 UMA\nD).- Casas de asistencia, guarderías............... 6.75 UMA 13.50 UMA\nE).- Giros de alto riesgo..... 29.70 UMA 36.45 UMA\nF).- Otros no especificados... 10.80 UMA 17.55 UMA fuera de horario laboral de la dependencia, deberán cubrir un monto de 6.75 UMA, además del referido en el presente inciso.\n6).- Prórroga para dar cumplimiento a observaciones referidas en acta de inspección:\nA).- Por evaluación de solicitud............. 0.68 UMA\nB).- Por otorgamiento de prórroga en 1ra. ocasión de hasta 30 días naturales...... 50% del monto de la inspección\nC).- Por otorgamiento de prórroga en 2da. ocasión de hasta 30 días naturales...... 200% del monto de la inspección\n7).- Por copia simple de documentos (por hoja).... 0.09 UMA\nLos servicios a que hacen referencia los incisos 3 y\n4, cuando se trate de instituciones públicas, quedarán exentos de pago, siempre y cuando sea en institución. Así como las pláticas informativas que vulnerable en general.\nXI.- REVISIÓN DE EXPLOSIVOS:\n1).- Revisión de polvorines, instalaciones de compra-venta de explosivos, como requisito\nDefensa Nacional (SEDENA).................... 94.50 UMA\n2).- Utilización de explosivos en espectáculos de pirotecnia.................................. 81.00 UMA\nXII.- SANCIONES ECONÓMICAS QUE PODRÁ IMPONER LA DIRECCIÓN DE\nPROTECCIÓN CIVIL:\n1).- Por no contar las empresas con el Programa\nInterno de Protección Civil, vigente y/o por no aplicarlo.............................. De 40.50 a\n405.00 UMA\n2).- Por utilizar, vender, almacenar y/o distribuir materiales peligrosos, sin contar con los permisos respectivos....... De 135.00 a\n405.00 UMA\n3).- Por no registrarse las empresas que manejan materiales peligrosos, ante la Dirección de\nProtección Civil.......................... De 40.50 a\n135.00 UMA\n4).- Por seguir realizando actividades las empresas que manejan materiales peligrosos, sin renovar el permiso correspondiente... De 40.50 a\n135.00 UMA\n5).- Por no informar las empresas de cualquier incidente ocurrido, en actividades que involucran materiales peligrosos.......... De 40.50 a\n135.00 UMA\n6).- Por almacenar materiales peligrosos en áreas, lugares o ambientes, que no reúnen las condiciones de seguridad necesarias................................ De 135.00 a\n405.00 UMA\n7).- Cuando se realice el traslado de materiales peligrosos, dentro de la ciudad, sin observar las medidas de seguridad necesarias................................ De 40.50 a\n135.00 UMA\n8).- Por almacenar o utilizar materiales peligrosos, sin autorización de la Dirección de Protección Civil....................... De 40.50 a\n135.00 UMA\n9).- Por no registrarse los cuerpos de emergencias, ante la Dirección de Protección\nCivil..................................... De 40.50 a\n135.00 UMA\n10).- Por no informar a las empresas, a la\nDirección de Protección Civil, de las actividades que pudieran constituir algún riesgo.................................... De 40.50 a\n135.00 UMA\n11).- Por negar el acceso al inspector de la\nDirección de Protección Civil, donde se realizará una inspección o donde haya ocurrido un siniestro o desastre.......... De 40.50 a\n135.00 UMA\n12).- Cuando no se hayan ejecutado las medidas de seguridad ordenadas por la Dirección de\nProtección Civil, derivadas de una inspección................................ De 40.50 a\n135.00 UMA\n13).- Por sobrepasar capacidad permitida y/o poner en riesgo a los ocupantes de un inmueble.................................. De 40.50 a\n135.00 UMA\n14).- Por realizar eventos masivos sin medidas de seguridad y/o supervisión de la Dirección de Protección Civil....................... De 81.00 a\n135.00 UMA\n15).- Por no activar las empresas, procedimientos de respuesta ante una emergencia que ponga en peligro a trabajadores, usuarios y/o vecinos................................... De 135.00 a\n405.00 UMA\n16).- Por infracciones al Reglamento Municipal de\nProtección Civil y Gestión Integral de\nRiesgos de Ensenada, no contempladas en los anteriores incisos........................ De 20.25 a\n675.00 UMA\n17).- Por mantener obstaculizadas rutas de evacuación y/o salidas de emergencia (por cada una)................................. De 135.00 a\n405.00 UMA\n18).- Por retirar sin autorización y/o violar sellos de clausura o suspensión instalados\n(por sello)............................... 135.00 UMA\n19).- Por no observar medidas de seguridad al realizar transporte de materiales y/o equipos................................... 135.00 UMA\n20).- Por realizar actividades consideradas como riesgo, sin observar medidas de seguridad personal y/o a terceros................... 135.00 UMA\n21).- Por realizar obras de edificación o instalación, sin contar con la factibilidad de la Dirección de Protección Civil........ 135.00 UMA\n22).- Por no presentar informes solicitados sobre las actividades emprendidas, los asesores registrados............................... 27.00 UMA\n23).- Por seguir ejerciendo funciones de asesor sin contar con el registro respectivo..... 67.50 UMA\n24).- Por no contar las albercas no particulares, con salvavidas y equipo de emergencia..... De 67.50 a\n135.00 UMA\n25).- Por obstruir caudales, causes y/o afectar propiedades normales del suelo generando riesgo a la población..................... De 135.00 a\n405.00 UMA\n26).- Por negligencia o irresponsabilidad del propietario, poseedor, encargado u ocupante, en el manejo de personas, uso de material o por no haber atendido las recomendaciones de la autoridad correspondiente........................... De 135.00 a\n405.00 UMA\n27).- Por realizar falsa alarma y/o bromas que conlleve a la alerta y/o acción de las autoridades de protección civil........... De 13.50 a\n135.00 UMA\n28).- Por ayudar o facilitar a los propietarios, poseedores, administradores, representantes, organizadores y demás personas involucradas en violaciones al\nReglamento Municipal de Protección Civil.. De 67.50 a\n202.00 UMA\n29).- En caso de reincidencia 200% del monto aplicado en la primera sanción.\nARTÍCULO 55.- Los servicios prestados por la Dirección de Bomberos, a giros comerciales, industriales, de servicios, los sectores públicos y sociales, se causarán conforme a la siguiente:\nUNIDAD DE MEDIDA Y ACTUALIZACIÓN (UMA) VIGENTE\nI.- ANÁLISIS DE FACTIBILIDAD PARA LA PRESTACIÓN DE SERVICIOS EN LA\nDIRECCIÓN DE BOMBEROS, EN PROYECTOS DE CONSTRUCCIÓN Y REGULARIZACIÓN\nDE DESARROLLOS URBANOS (POR M²):\nCONSTRUCCIÓN REGULARIZACIÓN\n1).- Desarrollo Habitacional............ 0.07 UMA 0.09 UMA\n2).- Desarrollo Comercial.............. 0.11 UMA 0.12 UMA\n3).- Desarrollo Industrial.............. 0.13 UMA 0.14 UMA\n4).- Otro tipo de instalaciones......... 0.10 UMA 0.11 UMA\nII.- INSPECCIONES DE DISPOSITIVOS DE SEGURIDAD, PREVENCIÓN,\nA PETICIÓN DE PARTE:\n1).- Comercio ambulante y puestos semifijos............ 5.40 UMA\n2).- Despachos de profesionistas y giros de servicios. 13.50 UMA\n3).- Billares, expendios, autoservicios, loncherías, panaderías, lavanderías, clínicas, ferreterías, desmanteladoras, talleres mecánicos, tiendas de ropa, misceláneas, farmacias, papelerías, templos religiosos, casas de empeño, tortillerías y teatros:\n3.1).- De 1 hasta 50 m²........................... 6.75 UMA\n3.2).- De 51 m² hasta 150 m²...................... 13.50 UMA\n3.3).- De 151 m² hasta 500 m²..................... 29.70 UMA\n3.4).- De 501 m² hasta 1,000 m²................... 54.00 UMA\n3.5).- De 1,001 m² hasta 3,000 m²................. 67.50 UMA\n4).- Bar turístico, café cantante, restaurante, mercado, supermercado, bodegas de distribución, salón de renta, hospital, salas cinematográficas e instituciones bancarias:\n4.1).- De 1 hasta 50 m²........................... 20.25 UMA\n4.2).- De 51 m² hasta 150 m²...................... 24.30 UMA\n4.3).- De 151 m² hasta 500 m²..................... 32.40 UMA\n4.4).- De 501 m² hasta 1,000 m²................... 64.80 UMA\n4.5).- De 1,001 m² hasta 3,000 m²................. 75.60 UMA\n5).- Discotecas, tiendas departamentales, centros de entretenimiento, balnearios y/o albercas:\n5.1).- De 1 hasta 150 m².......................... 32.40 UMA\n5.2).- De 151 m² hasta 500 m²..................... 40.50 UMA\n5.3).- De 501 m² hasta 1,000 m²................... 70.20 UMA\n5.4).- De 1,001 m² hasta 3,000 m²................. 86.40 UMA\n5.5).- De 3,001 m² en adelante.................... 105.30 UMA\n6).- Moteles:\n6.1).- De 1 hasta 10 habitaciones................. 18.90 UMA\n6.2).- De 11 a 20 habitaciones.................... 24.30 UMA\n6.3).- De 21 habitaciones en adelante............. 32.40 UMA\n7).- Hoteles:\n7.1).- De 1 hasta 30 habitaciones................. 56.70 UMA\n7.2).- De 31 habitaciones hasta 50 habitaciones... 81.00 UMA\n7.3).- De 51 habitaciones en adelante............. 108.00 UMA\n8).- Edificios educativos, asilos, guarderías y estancias infantiles:\n8.1).- Edificios educativos públicos.............. 13.50 UMA\n8.2).- Edificios educativos privados:\n8.2.1).- De 1 a 10 aulas.................. 16.20 UMA\n8.2.2).- De 11 a 20 aulas................. 24.30 UMA\n8.2.3).- De 21 aulas en adelante.......... 32.40 UMA\n8.3).- Asilos, guarderías y estancias infantiles.. 16.20 UMA\n9).- Giros de alto riesgo:\n9.1).- Distribuidores de gases, químicos, combustibles y lubricantes, oxígenos y acetilenos, polvorines, gasolineras y depósitos de combustibles y lubricantes, y demás de alto riesgo....................... 189.00 UMA\n10).- Clubes deportivos, gimnasios, escuelas de danza y ballet:\n10.1).- De 1 m² hasta 100 m².................... 10.80 UMA\n10.2).- De 101 m² hasta 200 m².................. 13.50 UMA\n10.3).- De 201 m² hasta 400 m².................. 18.50 UMA\n10.4).- De 401 m² en adelante................... 27.00 UMA\n11).- Edificios industriales:\n11.1).- Micro industria, de 1 a 50 empleados.... 24.30 UMA\n11.2).- Pequeña industria, de 51 a 200 empleados.............................. 40.50 UMA\n11.3).- Mediana industria, de 201 a 500 empleados............................... 81.00 UMA\n11.4).- Megaindustria, de 501 empleados a 1,000 empleados............................... 108.00 UMA\n11.5).- Macro industria, de 1,001 empleados en adelante................................ 135.00 UMA\n12).- Centros de apuestas, apuestas remotas, salas de sorteos de número y/o casinos.................... 270.00 UMA\n13).- Solicitudes a través del Sistema de Apertura Rápida de Empresas (SARE):\n13.1).- De 1 a 50 m² de Operación............... 6.75 UMA\n13.2).- De 51 a 100 m² de Operación............. 10.13 UMA\n13.3).- De 101 a 150 m² de Operación............ 13.50 UMA\n13.4).- De 151 a 200 m² de Operación............ 16.88 UMA\n14).- Otros giros no especificados.................... 40.50 UMA\nLas reinspecciones que deban realizarse en cualquiera de los casos contenidos en esta fracción, se realizarán por el 50% del costo estipulado para la inspección que corresponda.\nLas inspecciones o reinspecciones que se realicen a una distancia mayor de 80 km. fuera de la mancha urbana se cobrará en un 100% más sobre el costo estipulado para la inspección o reinspección que corresponda.\nIII.- ANÁLISIS DE RIESGO:\n1).- Abarrotes, licorerías, sub-agencia, expendio, billares y autoservicio.......................... 37.80 UMA\n2).- Restaurante-bar, bar turístico, café cantante, mercado, supermercado, y bodega de distribución.. 54.00 UMA\n3).- Discotecas, tiendas departamentales, hoteles y moteles.......................................... 97.20 UMA\nIV.- REVISIÓN DE LAS CONDICIONES DE SEGURIDAD Y PREVENCIÓN EN\nINSTALACIONES TEMPORALES, PARA LA ANUENCIA CORRESPONDIENTE:\n1).- Circos:\n1.1).- Chicos (una pista)........................ 18.90 UMA\n1.2).- Medianos (dos pistas)..................... 24.30 UMA\n1.3).- Grandes (tres o más pistas)............... 28.35 UMA\n2).- Juegos mecánicos:\n2.1).- Por juego mecánico........................ 2.03 UMA\n2.2).- Por puesto de comida...................... 2.03 UMA\n3).- Exposiciones, ferias y kermeses................... 20.25 UMA\n4).- Eventos deportivos:\n4.1).- De 1 persona a 300 personas................ 13.50 UMA\n4.2).- De 301 personas a 1,000 personas........... 20.25 UMA\n4.3).- De 1,001 personas a 3,000 personas......... 40.50 UMA\n4.4).- De 3,001 personas en adelante.............. 54.00 UMA\n5).- Eventos masivos:\n5.1).- De 1 asistente hasta 1,000 asistentes...... 30.00 UMA\n5.2).- De 1,001 a 3,000 asistentes................ 60.00 UMA\n5.3).- De 3,001 a 5,000 asistentes................ 85.00 UMA\n5.4).- De 5,001 asistentes en adelante............ 110.00 UMA\n6).- Venta de combustible de alto octanaje para carreras......................................... 160.00 UMA\n7).- Otros eventos no especificados.................... 33.75 UMA\nV.- CONSTANCIA DE DAÑOS EN BIENES SINIESTRADOS POR INCENDIO O\nEXPLOSIÓN:\n1.- Casa habitación................................... 13.50 UMA\nQuedan exceptuados del pago de este Derecho, aseguradas al ocurrir el siniestro.\n2.- Desarrollo comercial.............................. 40.50 UMA\n3.- Desarrollo industrial............................. 60.75 UMA\n4.- Otros tipos de instalaciones...................... 202.50 UMA\n5.- Vehículos automotores:\n5.1.- Automóviles................................ 13.50 UMA\n5.2.- Camiones de transporte/pasajeros........... 24.30 UMA\n5.3.- Tracto camiones............................ 32.40 UMA\n5.4.- Embarcaciones pequeñas (botes, yates, lanchas)................................... 13.50 UMA\n5.5.- Embarcaciones medianas (barcos pesqueros)................................. 24.30 UMA\n5.6.- Embarcaciones grandes (cruceros, carga, etc.)...................................... 32.40 UMA\n6.- Vehículos de tracción humana o animal............. 13.50 UMA una distancia mayor de 80 km. fuera de la mancha urbana se cobrará en un 100% más sobre el costo estipulado para el concepto que corresponda.\nLos sujetos a quienes les sea aplicable el segundo párrafo del numeral 1 de esta fracción, quedarán exentos también del cobro que estipula el párrafo anterior.\nVI.- CERTIFICACIÓN DE EQUIPO DE DISPOSITIVOS DE SEGURIDAD:\n1.- Vivienda unifamiliar.............................. 1.35 UMA\n2.- Comercio (portátiles)............................. 2.70 UMA\n3.- Industria (portátiles)............................ 5.40 UMA\n4.- Certificación de sistemas hidráulicos contra incendios (fijos)................................ 40.50 UMA\n5.- Transportes de todo tipo que se encuentren dentro del municipio.................................... 9.45 UMA\nVII.- AUTORIZACIÓN O CERTIFICACIÓN PARA REGISTRO Y/O EMPADRONAMIENTO DE EMPRESAS:\n1.- Personas físicas o morales dedicadas a la venta, renta, mantenimiento y recarga de extintores portátiles....................................... 30.00 UMA\n1.1).- Suministro de etiquetas para verificación de la calidad del agente extintor, por etiqueta.................................. 0.14 UMA\n2.- Personas físicas o morales dedicadas a sistemas contra incendios, sistemas especiales para extinción, sistemas de rociadores automáticos, alarmas contra incendios.......................... 81.00 UMA\n3.- Organizaciones civiles, empresas e instructores independientes que presten servicios de control de siniestros............................. 40.50 UMA\nVIII.- SERVICIOS ESPECIALES:\nA.- CURSOS POR HORA:\n1.- Combate de incendios........................ 27.00 UMA\n2.- Uso y manejo de equipo contra incendio...... 27.00 UMA\n3.- Identificación de materiales peligrosos..... 27.00 UMA\n4.- Conocimientos básicos de rescate............ 27.00 UMA\n5.- Otros no especificados relativos a incendios................................... 27.00 UMA\nLos cursos a que hace referencia este apartado, cuando se trate de instituciones públicas, quedarán exentos de pago, siempre y cuando sea en horas hábiles y en las instalaciones de la misma institución.\nB.- USO DE EQUIPO Y PERSONAL POR HORA:\n1.- Máquina extinguidora........................ 40.50 UMA\n2.- Máquina de iluminación....................... 40.50 UMA\n3.- Máquina escala.............................. 40.50 UMA\n4.- Auto cisterna (con agua)..................... 54.00 UMA\n5.- Unidad de rescate o ambulancia............... 40.50 UMA\nC.- PRÓRROGAS PARA DAR CUMPLIMIENTO A OBSERVACIONES DE LAS ACTAS\nDE INSPECCIÓN, POR LOS CONCEPTOS DE:\n1.- Extintores y detector de humo hasta por 5 días........................................ 3.38 UMA\n2.- Instalación eléctrica y de gas hasta por 10 días........................................ 6.75 UMA\n3.- Capacitación hasta por 15 días............... 10.13 UMA\n4.- Dictámenes eléctricos y de gas hasta por 20 días........................................ 13.50 UMA\n5.- PAECI, Sistemas de alarma contra incendios hasta 30 días................................ 20.25 UMA\n6).- Sistemas fijo contra incendios hasta 60 días 40.50 UMA\n7).- Aprobación de Plan de Atención a Emergencias\nContra Incendios PAECI....................... 27.00 UMA\nIX.- REVISIÓN DE EXPLOSIVOS:\n1.- Revisión de equipos contra incendio en instalaciones para venta de artificios pirotécnicos............. 40.50 UMA\n2.- Revisión de equipos contra incendio para anuencias de explosivos y polvorines............. 94.50 UMA\nX.- SANCIONES ECONÓMICAS QUE PODRÁN IMPONERSE EN LA DIRECCIÓN DE\nBOMBEROS:\n1).- Por negar el acceso al inspector de Bomberos, donde se realizará una inspección o donde haya ocurrido un incendio, fuga o explosión.................... 40.50 a\n135.00 UMA\n2).- Por iniciar las empresas actividades sin la autorización de la Dirección de Bomberos.......... 40.50 a\n135.00 UMA\n3).- Por infracciones al reglamento no contempladas en los incisos anteriores........................... 40.50 a\n135.00 UMA\n4).- Por no cumplir con las medidas ordenadas derivadas de un acta de inspección.......................... 40.50 a\n135.00 UMA\n5).- En caso de reincidencia.......................... 40.50 a\n135.00 UMA\n6).- Por utilizar, vender, almacenar y/o distribuir materiales peligrosos, sin contar con los permisos respectivos...................................... 40.50 a\n135.00 UMA\n7).- Por no informar las empresas de cualquier incidente ocurrido, en actividades que involucran materiales peligrosos....................................... 40.50 a\n135.00 UMA\n8).- Por almacenar materiales peligrosos en áreas, lugares o ambientes, que no reúnen las condiciones de seguridad necesarias........................... 40.50 a\n135.00 UMA\n9).- Por no informar las empresas, a la Dirección de\nBomberos, de las actividades que pudieran constituir algún riesgo.......................... 40.50 a\n135.00 UMA\n10).- Por no activar las empresas, procedimientos de respuesta ante una emergencia que ponga en peligro a trabajadores, usuarios y/o vecinos............ 40.50 a\n135.00 UMA\n11).- Por retirar sin autorización y/o violar, sellos de clausura o suspensión instalados (por sello). 135.00 UMA\n12).- Por seguir ejerciendo funciones de asesor sin contar con el registro respectivo............... 67.50 UMA\n13).- Por realizar falsa alarma y/o bromas que conlleve a la alerta y/o acción de las unidades de la\nDirección de Bomberos............................ 40.50 a\n135.00 UMA\nXI.- DICTAMEN DE DAÑOS EN BIENES SINIESTRADOS POR INCENDIO Y\nEXPLOSIÓN:\n1.- Desarrollo habitacional......... De 67.50 UMA a 270.00 UMA\n2.- Desarrollo comercial............ De 135.00 UMA a 270.00 UMA\n3.- Desarrollo industrial........... De 135.00 UMA a 270.00 UMA\n4.- Otro tipo de instalaciones...... De 135.00 UMA a 405.00 UMA\n5.- Vehículos automotores........... De 13.50 UMA a 135.00 UMA\n6.- Vehículos de tracción humana o animal.......................... De 13.50 UMA a 135.00 UMA\nCAPÍTULO IX\nARTÍCULO 56.- Ninguna contribución podrá recaudarse si no está prevista en la presente Ley de Ingresos Municipal.\n1.- SERVICIOS PRESTADOS EN LA DIRECCIÓN DE ADMINISTRACIÓN URBANA,\nSE PAGARÁN CONFORME A LO SIGUIENTE:\nUNIDAD DE MEDIDA Y ACTUALIZACIÓN (UMA) VIGENTE\n1.- Otros servicios, en formato varios............... 8.00 UMA\n2.- Elaboración de estudio de impacto urbano modalidad ponderación de densidad.......................... 500.00 UMA\n3.- Elaboración de estudio de impacto urbano modalidad incorporación urbana............................. 600.00 UMA\n2.- LOS SERVICIOS PRESTADOS POR LA DIRECCIÓN DE BIENESTAR SOCIAL, SE\nPAGARÁN CONFORME A LO SIGUIENTE:\n1.- Cuotas coordinación psicológica:\nMínima Máxima\na).- Asesoría psicológica......... 0.30 UMA 2.20 UMA\nSesión\nb).- Pláticas pre-matrimoniales... 3.50 UMA\nSesión\nc).- Maestros Sombras............. 2.96 UMA 9.47 UMA\nSemanal\nd).- Conferencias:\n1).- De 1 hasta 10 personas................. 5.75 UMA\n2).- De 11 hasta 25 personas................ 14.39 UMA\n3).- De 26 hasta 50 personas................ 28.78 UMA\n4).- Más de 50 personas..................... 57.56 UMA\ne).- Evaluaciones psicológicas..... 5.92 UMA 23.68 UMA\nEvaluación\nf).- Pláticas prematrimoniales urgentes.......... 8.50 UMA\nSesión\ng).- Inscripción capacitación Maestro Sombra..... 2.37 UMA\nh).- Visita supervisada............ 2.32 UMA 3.50 UMA\ni).- Certificación Maestro Sombra................ 5.75 UMA\n2.- Registro y revalidación a estancias infantiles:\nUNIDAD DE MEDIDA Y ACTUALIZACIÓN (UMA) VIGENTE\nREGISTRO REVALIDACIÓN\na).- De 1 hasta 10 niños.......... 20.00 UMA 10.00 UMA\nb).- De 11 hasta 25 niños......... 30.00 UMA 15.00 UMA\nc).- De 26 hasta 50 niños......... 40.00 UMA 20.00 UMA\nd).- Más de 50 niños.............. 50.00 UMA 25.00 UMA\nPara los registros y revalidación a estancias infantiles, por pago oportuno en los primeros tres meses, se hará un descuento del 10%.\nEn caso de exceder los 180 días sin haber revalidado, se aplicará una sanción del 50% adicional de la cuota de revalidación correspondiente.\n3.- Credencial y Tarjetón de Discapacidad:\na).- Credencial de Discapacidad, primera vez..... EXENTO\nb).- Expedición de tarjetón para uso de estacionamiento en personas con discapacidad, primera vez................................. 1.19 UMA\nc).- Por reposición por extravío, mutilación o daño al tarjetón de discapacidad........... 1.78 UMA\nd).- Por reposición por extravío, mutilación o daño a la credencial de discapacidad............. 1.19 UMA\ne).- Renovación de la credencial de discapacidad. EXENTO\nf).- Renovación del tarjetón de discapacidad..... 0.95 UMA presta la Dirección de Bienestar Social, mediará un estudio socioeconómico realizado.\n3.- SERVICIOS PRESTADOS EN LA COORDINACIÓN DE EDUCACIÓN Y CULTURA.\n1.- Los derechos por los talleres impartidos en la Casa de la Cultura San Quintín:\nI.- Por concepto de inscripción a grupo, será cubierto por persona, de acuerdo a la siguiente tabla:\na) Inscripción............................ 2.00 UMA\nb) Cuando se inscriban dos o más miembros de una misma familia, a partir del segundo alumno................................. 1.00 UMA\nc) Tratándose de personas con discapacidad, empleados de Cultura y Desarrollo Humano de San Quintín.......................... 0.00 UMA\nd) Tratándose de personas adultas mayores, jubilados o pensionados y empleados del\nMunicipio de San Quintín................ 1.62 UMA\nII.- Por concepto de mensualidad, será cubierto por persona de acuerdo a lo siguiente:\na) Mensualidad............................ 2.00 UMA\nb) Cuando se trate de dos o más miembros de una misma familia, a partir del segundo alumno.......................... 1.00 UMA\nc) Tratándose de personas adultas mayores, jubilados o pensionados................ EXENTO\nSe exentará del cobro de todos los incisos anteriores, cuando se compruebe que las personas o grupos, se encuentren en una situación de vulnerabilidad, lo cual se sustentará con un\nBienestar Social.\n2.- Los talleres impartidos en las Delegaciones del\nMunicipio de San Quintín B.C., serán cubiertos de acuerdo a la siguiente tabla:\na) Inscripción................................. 1.54 UMA\nb) Cuando se inscriben dos o más miembros de una misma familia, los subsecuentes........ 0.77 UMA\nc) Tratándose de personas con discapacidad..... EXENTO\nd) Tratándose de personas adultas mayores, jubilados o pensionados..................... EXENTO\nI.- Por concepto de mensualidad en las\nDelegaciones, será cubierto de acuerdo a la siguiente:\na) Mensualidad............................ 2.00 UMA\nb) Cuando se trate de dos o más miembros de una misma familia, a partir del segundo alumno................................. 1.00 UMA\nc) Tratándose de personas con discapacidad 0.00 UMA\nd) Tratándose de personas adultas mayores, jubilados o pensionados................ EXENTO\n3.- Cobro de entradas para eventos de promoción y difusión cultural:\na) Clausuras o cierres casa de la cultura........................... 0.00 a 1.32 UMA\nb) Clausuras o cierres casa de la cultura extensiones............... 0.00 a 1.32 UMA\nc) Presentaciones artísticas............... 1.19 UMA\nd) Presentaciones musicales y/o conciertos............................. 1.78 UMA\ne) Presentaciones artísticas dirigidas a una población de hasta 500 personas.... 2.40 UMA\nSe exentará del cobro de todos los incisos anteriores, cuando se compruebe que las personas o grupos, se encuentren en una situación de vulnerabilidad, lo cual se sustentará con un\nBienestar Social.\n4.- Participación en espacios para venta en eventos de promoción y difusión cultural:\na) Venta de alimentos.................. 7.10 a 12.42 UMA\nb) Artesanías.......................... 4.73 a 7.10 UMA\nc) Venta de bebidas con graduación alcohólica\n(excepto cerveza)........................... 53.26 UMA\nd) Venta de cerveza............................. 56.81 UMA\ne) Venta de vino................................ 30.77 UMA\nf) Venta de cerveza artesanal................... 30.77 UMA\ng) Todas las anteriores, para venta y uso\nCoordinación de Educación y Cultura......... 0.00 UMA\n5.- Los derechos por los cursos de verano impartidos en de Educación y Cultura:\na) Cursos de verano por paquete................. 6.91 UMA\nb) Cursos de verano por taller.................. 3.90 UMA\nc) Cursos de verano en extensiones por paquete.. 4.10 UMA\nd) Curso de verano en extensiones por taller.... 1.95 UMA\n6.- Los derechos por reinscripción o renovación al padrón de promotores culturales locales de Casa de\nCultura a través de la Coordinación de Educación y\nCultura.......................................... 2.00 UMA\n7.- Capacitaciones en general.......... 0.92 UMA a 4.60 UMA\n8.- Venta de playeras y/o sudaderas de\nCasa de la Cultura................ 0.92 UMA a 5.80 UMA\n9.- Cursos extra curriculares.......... 4.61 UMA a 11.51 UMA\n4.- OTROS SERVICIOS PRESTADOS POR LA DIRECCIÓN DE ADMINISTRACIÓN\nURBANA, SE COBRARÁN CONFORME A:\n1.- Expedición de títulos, constancias o copias de documentos, legalización de firmas y demás servicios administrativos prestados:\na) Copia(s) cotejada(s) de 1 a 5 hojas.......... 2.32 UMA a.1) Copia cotejada a partir de la hoja número 6 en adelante................. 0.31 UMA\n(Copias de: Números oficiales, Medidas y Colindancias, Títulos de\nPropiedad, Contratos, Adendums, Convenios).\nb) Cesión de derechos................... 10.39 UMA\nc) Carta de instrucción sin cesión de derechos (inmuebles con superficie de\n1 a 500m²).......................... 40.66 a 44.73 UMA\nd) Carta de instrucción con cesión de derechos (inmuebles con superficie de\n1 a 500m²).......................... 48.48 a 53.33 UMA\ne) Carta de instrucción para escrituración por medio de notaría pública: e.1) Inmuebles con superficie de\n501 a 1,000m²................ 71.40 a 78.54 UMA e.2) Inmuebles con superficie de\n1,001 a 1,500m².............. 102.13 a 112.34 UMA e.3) Inmuebles con superficie de\n1,501 a 2,000m².............. 148.23 a 163.05 UMA e.4) Inmuebles con superficie de\n2,001 a 3,000m².............. 194.33 a 213.76 UMA e.5) Inmuebles con superficie de\n3,001 a 4,000m²............... 278.84 a 306.72 UMA e.6) Inmuebles con superficie mayor de\n4,001m²............................... 408.14 UMA e.7) Firma del fiduciario por escrituración................ 9.60 a 10.56 UMA\nf) Renovación de carta instrucción..... 16.88 a 18.57 UMA\ng) Elaboración de Adendum o Convenios a beneficiarios....................... 3.50 a 6.00 UMA g.1) Elaboración de adendum a las\nAsociaciones Público Privada 20.00 a 40.00 UMA g.2) Elaboración de convenios a las\nAsociaciones Público Privadas 40.00 a 80.00 UMA\nh) Servicio de entrega de deslinde físico posterior a la venta......................... 35.00 UMA\ni) Otros servicios:\nSe cobrarán derechos de conformidad al servicios que presta la Dirección de\nAdministración Urbana, los que en todo caso serán proporcionales al costo del servicio.\nj) Gastos operativos por contratación de inmuebles................................... 2.5%\nSe cobrará un recargo moratorio del 1% mensual por cada mensualidad en que el beneficiario incumpla en sus obligaciones de pago.\nk).- Recargos por concepto de mora a Asociaciones\nPúblico Privadas.\n5.- SERVICIOS PRESTADOS EN LA DIRECCIÓN DE DEPORTE, SE COBRARÁN DE\nLA MANERA SIGUIENTE:\n1.- ENTRADAS EN GENERAL:\nTARIFA\na) Público en General........................ $ 5.00 PESOS\nb) Futbolistas............................... $ 5.00 PESOS\nc) Campo empastado........................... $10.00 PESOS\nd) Campo fútbol americano.................... $15.00 PESOS\ne) Box en evento amateur realizado en las instalaciones de unidades municipales..... $15.00 PESOS\nA) UNIDAD DEPORTIVA:\na) Público en general........................ $ 5.00 PESOS\nb) Deportistas de fútbol rápido.............. $ 5.00 PESOS\nc) Béisbol................................... $ 5.00 PESOS\nd) Béisbol eventos especiales................ $10.00 PESOS\nB) GIMNASIO MUNICIPAL:\na) Entradas básquetbol y voleibol............ $ 5.00 PESOS\nC) GIMNASIO EN LA CALI SAN QUINTÍN:\na) Público en general........................ $ 5.00 PESOS\nD) UNIDAD DEPORTIVA:\na) Público en general........................ $ 5.00 PESOS\nE) UNIDAD DEPORTIVA VICENTE GUERRERO:\na) Público en general........................ $ 5.00 PESOS\nb) Deportistas............................... $ 5.00 PESOS\nF) UNIDAD DEPORTIVA LÁZARO CÁRDENAS:\na) Deportistas............................... $10.00 PESOS\nG) UNIDAD DEPORTIVA LAS MISIONES (CAMPO EMPASTADO)\nEN DELEGACIÓN VICENTE GUERRERO:\na) Público en general........................ $10.00 PESOS\nH) GIMNASIO DE ACONDICIONAMIENTO FÍSICO EN COL. NUEVA\nERA SAN QUINTÍN:\na) Público en general............... $20.00 PESOS(POR HORA)\n$200.00 PESOS (MENSUAL)\nb) Personas de escasos recursos..... $10.00 PESOS(POR HORA)\n$100.00 PESOS (MENSUAL)\nc) Estudiantes...................... $ 5.00 PESOS(POR HORA)\n$100.00 PESOS (MENSUAL)\nd) Grupos escolares programados.............. GRATUITO\ne) Entrenamientos deportistas seleccionados.. GRATUITO\nf) Bomberos y Seguridad Pública.............. GRATUITO\nI.- OTRAS UNIDADES:\na) Público en general........................ $ 3.00 PESOS\n2.- PROGRAMA VACACIONAL DE VERANO 2025:\nDelegaciones Municipales. (El Mármol, Bahía de los Ángeles, Punta Prieta, Villa de Jesús\nMaría)......................................... 3.57 UMA\n3.- DESCUENTOS PROGRAMA VACACIONAL:\nTIPO: COSTO UMA COSTO UMA COSTO UMA\n2 MESES 1 MES 2 SEMANAS\nHermanos 1 9.40 UMA 6.49 UMA 3.57 UMA\nHermanos 2 8.08 UMA 5.03 UMA 2.78 UMA\nHermanos 3 6.75 UMA 4.23 UMA 2.11 UMA\nHermanos 4 5.43 UMA 2.78 UMA 1.45 UMA\n4.- ESPACIOS DE CAFETERÍA Y OTROS:\na) Unidad deportiva en Delegación Vicente Gro... 16.35 UMA\nb) Gimnasio de acondicionamiento físico en Col.\nNueva Era.................................... 22.30 UMA\nc) Otros espacios............................... 16.35 UMA\n5.- COBRO DE USO DE INSTALACIONES DEPORTIVAS, POR\nEVENTO:\na) Gimnasio para Box sin ring................... 148.72 UMA\nb) Gimnasio para Box con ring................... 190.72 UMA\nc) Ring para función de box..................... 42.00 UMA\nNOTA: ESTE NÚMERO CON SUS INCISOS TAMBIÉN APLICA\nPARA LUCHA LIBRE Y ARTES MARCIALES MIXTAS.\n6.- COBRO POR HORA:\na) Futbol 7 infantil, empastado con fines de lucro....................................... 0.59 UMA a.1) Sin fines de lucro................... 0.00 UMA\n7.- COBRO DE ESPACIOS DEPORTIVOS (EVENTOS ESPECIALES):\na) Gimnasio............................ De 0.01 a 89.23 UMA\nb) Gimnasio en Delegación Vicente\nGuerrero............................ De 0.01 a 74.36 UMA\nc) Gimnasio en La Cali, San Quintín.... De 0.01 a 74.36 UMA\n8.- OTROS SERVICIOS.\nUNIDAD DE MEDIDA Y ACTUALIZACIÓN (UMA) VIGENTE\n1.- CURSOS DE CAPACITACIÓN.\nCUOTA TRIMESTRAL\na) Jóvenes de entre 12 y 29 años de edad........ 8.30 UMA\n6.- OTROS SERVICIOS, SE COBRARÁN DE LA MANERA SIGUIENTE:\nUNIDAD DE MEDIDA Y ACTUALIZACIÓN (UMA) VIGENTE\n1.- POR TIPO DE CONSULTA PÚBLICA:\nA) CAMBIO DE USO DE SUELO:\n1.- Publicación de la consulta pública en el diario de mayor circulación del Municipio........... 150.00 UMA\n2.- Diagnóstico de la consulta pública entregada por escrito o virtual......... 100.00 UMA\n3.- Celebración de la sesión de la consulta pública..................................... 100.00 UMA\n4.- Dictamen por escrito de la consulta pública. 250.00 UMA\nB) CONSULTA VECINAL:\n1.- A realizarse en las instalaciones del\nMunicipio de San Quintín.................... 120.00 UMA\n2.- A realizarse en el sitio donde se desarrolla la actividad................................... 150.00 UMA\n3.- Las consultas que se realicen en el sitio, y de población, por kilómetro excedente........ 0.50 UMA\nC) PROGRAMAS SECTORIALES:\n1.- Publicación de la consulta pública en el diario de mayor circulación del Municipio........... 150.00 UMA\n2.- Diagnóstico de la consulta pública entregada por escrito o virtual......... 100.00 UMA\n3.- Celebración de la sesión de la consulta pública..................................... 100.00 UMA\n4.- Dictamen por escrito de la consulta pública. 250.00 UMA\n5.- Las consultas que se realicen en el sitio, y se encuentren fuera de los límites del centro de población por cada kilómetro excedente... 1.00 UMA\n2.- CURSOS RELACIONADOS CON LA UNIDAD MUNICIPAL DE\nTRANSPARENCIA Y ACCESO A LA INFORMACIÓN PARA AL\nMENOS 5 PERSONAS POR HORA/PERSONA................ 3.20 UMA\nServicios solicitados por las dependencias municipales estarán exentos del cobro por los servicios brindados por Unidad Municipal de\nTransparencia y Acceso a la Información, siempre y cuando sea en beneficio de la propia dependencia y sean solicitados a través de la Dirección de\nAdministración Urbana. Así mismo, las solicitudes\nDirección de Bienestar Social, a la Unidad\nInformación, estarán exentos del cobro por los servicios brindados.\nUNIDAD DE MEDIDA Y ACTUALIZACIÓN (UMA) VIGENTE\n1.- MÓDULO DE BAÑOS:\na) Entrada general.............................. 0.058 UMA\nCAPÍTULO X\nEXPEDICIÓN DE CERTIFICADOS, TÍTULOS, CONSTANCIAS O COPIAS DE\nDOCUMENTOS\nARTÍCULO 57.- Los certificados, títulos, constancias, copias fotostáticas certificadas, legalización de firmas y demás servicios administrativos prestados por las oficinas municipales, deberán pagarse conforme a la siguiente:\nUNIDAD DE MEDIDA Y ACTUALIZACIÓN (UMA) VIGENTE\na).- Certificados de residencia y legalización de firmas........................................... 1.62 UMA\nb).- Copia adicional certificada....................... 0.34 UMA\nc).- Certificados de productos de origen............... 1.02 UMA\nd).- Derechos por titulación de terrenos............... 5.40 UMA\ne).- Certificados de peritaje.......................... 1.35 UMA\nf).- Certificados de obras públicas............... 2.70 a 8.10 UMA\ng).- Certificaciones, constancias de archivos municipales...................................... 1.35 UMA\nh).- Certificación de avalúo........................... 8.10 UMA h.1) Certificación de avalúo urgente, (se tiene que presentar antes de las 10:00 hrs.) se entrega a las 14:00 hrs. del mismo día..... 16.20 UMA h.2) Certificación de avalúo extra urgente, (se tiene que presentar antes de las 13:00 hrs.) se entrega de 1 a 2 horas después de la recepción.................................. 21.60 UMA h.3) Copia certificada de avalúo................ 5.40 UMA h.4) Por modificación de hoja en avalúo ya certificado................................ 4.05 UMA tendrá vigencia de uso por 30 días naturales y hasta\n2 reingresos.\nREINGRESOS: a partir del pago de certificación de avalúo tendrá la oportunidad de 2 reingresos dentro de un período de 30 días naturales. mencionado tendrán un costo del 50% del valor del primer ingreso.\ni).- Certificado de opinión para establecimiento de maquiladoras de acuerdo a clasificación federal de la Secretaría de Comercio y Fomento Industrial: i.1) Industria micro........................... 6.75 UMA i.2) Industria mediana......................... 20.25 UMA i.3) Industria grande.......................... 33.75 UMA\nj).- Constancias de autoconstrucción hasta 120 m²..... 5.40 UMA\nk).- Certificaciones a particulares, por hoja......... 2.03 UMA\nl).- Dispensa de edad.................................. 1.76 UMA\nm).- Carta de residencia............................... 2.03 UMA\nn).- Constancia de supervivencia....................... 1.35 UMA ñ).- Constancia de explosivos.......................... 6.75 UMA\no).- Dictámenes a particulares......................... 6.75 UMA\np).- Emisión de documentos simples..................... 0.33 UMA\nq).- Fotocopia de Leyes, reglamentos que se tienen en la dependencia, por hoja......................... 0.34 UMA\nr).- Derechos por cartas y certificaciones expedidos por la Sindicatura Municipal: r.1) Carta de antecedentes administrativos...... 2.70 UMA r.2) Copias certificadas de 1 a 20.............. 2.03 UMA r.3) Copia adicional certificada................ 0.07 UMA r.4) Expedición de copias fotostáticas simples.. 0.00 UMA\ns).- Constancia de ratificación de firmas.............. 27.00 UMA\nt).- Modificación de la constancia de ratificación, costo por hoja.................................... 1.35 UMA\nu).- Expedición de constancia y registro de las\nAsociaciones Religiosas.......................... 4.05 UMA\nv).- Renovación de constancia y registro de las\nAsociaciones Religiosas.......................... 1.35 UMA\nLas personas físicas de escasos recursos que utilicen los servicios de la Defensoría de Oficio en la tramitación de procedimientos judiciales, civiles y penales, previo estudio socioeconómico que elabore la Dirección de Bienestar Social, se les exentará del pago de los Derechos por el servicio de Certificado de Residencia y Certificado de Libertad de Gravámenes, a solicitud expresa del titular de la Defensoría de Oficio, esta exención será otorgada al interesado por única ocasión.\nCAPÍTULO XI\nDERECHOS NO COMPRENDIDOS EN LAS FRACCIONES DE LA LEY DE INGRESOS\nO PAGO.\nARTÍCULO 58.- Los derechos no pagados en el ejercicio fiscal en que se causaron, se cobrarán como ingresos causados en ejercicios fiscales anteriores, pendientes de liquidación o pago, aplicando en cuanto al fondo, las Leyes vigentes en la fecha en que se generaron y en cuanto a la forma, mediante el procedimiento administrativo de\nBaja California o en su caso, el procedimiento judicial que corresponda.\nTÍTULO CUARTO\nPRODUCTOS\n1.- CONTRAPRESTACIÓN DE CONCESIONES, EXPLOTACIÓN O ARRENDAMIENTO DE\nBIENES MUEBLES E INMUEBLES PROPIEDAD DEL GOBIERNO MUNICIPAL.\nARTÍCULO 59.- La renta o contraprestación de las concesiones de los locales internos o externos de los mercados, será fijada en cada caso por las autoridades fiscales, dependiendo de su ubicación y superficie ocupada o en su caso, de acuerdo al contrato de arrendamiento respectivo. su importe deberá ser liquidado en el Departamento de Recaudación del Ayuntamiento de San Quintín, Baja California, dentro de los primeros cinco días de cada mes en forma anticipada.\n2.- OTRAS ACTIVIDADES DEL AYUNTAMIENTO DE SAN QUINTÍN, BAJA\nCALIFORNIA, QUE NO CORRESPONDAN A SUS FUNCIONES PROPIAS DE DERECHO\nPÚBLICO.\nARTÍCULO 60.- Las rentas que produzcan los bienes propiedad del\nMunicipio y que sean susceptibles de ser arrendados, se pagarán con base en los contratos de arrendamientos que se celebren con cada uno de los inquilinos y la Autoridad Municipal, cubriéndose el importe de correspondiente.\n3.- SUMINISTRO DE FORMAS DIVERSAS PARA TRÁMITES ADMINISTRATIVOS.\nARTÍCULO 61.- Ingresos obtenidos por el suministro de formas impresas tales como formatos para pago de Impuestos, Derechos y cualquier otra contribución, así como solicitudes que se utilizan en trámites del Ayuntamiento de San Quintín, Baja California, se pagarán a razón de 0.10 UMA por forma impresa, en el Departamento de Recaudación de dicha Autoridad Municipal.\n4.- DEL PISO.\nARTÍCULO 62.- Las personas físicas o morales que previa autorización de la autoridad del Ayuntamiento de San Quintín, Baja California, nombrado en el Decreto de Creación No. 46 publicado en el diario\nOficial del Estado de Baja California el 27 de febrero del 2020 correspondiente hagan uso del piso, de instalaciones subterráneas o temporal, pagarán los productos correspondientes conforme a lo siguiente:\nI.- Casetas telefónicas, diariamente, por cada una; debiendo realizar el pago anualizado dentro de los primeros 60 días del ejercicio fiscal........... 0.10 UMA\nII.- Instalaciones de infraestructura, por metro lineal, anualmente:\na).- Redes subterráneas de:\n1.- Telefonía............................. 0.015 UMA\n2.- Transmisión de datos.................. 0.015 UMA\n3.- Transmisión de señales de televisión por cable............................. 0.015 UMA\n4.- Distribución de gas................... 0.015 UMA\n5.- Energía eléctrica..................... 0.015 UMA\nb).- Redes visibles de:\n1.- Telefonía............................. 0.030 UMA\n2.- Transmisión de datos.................. 0.030 UMA\n3.- Transmisión de señales de televisión por cable............................. 0.030 UMA\n4.- Energía eléctrica..................... 0.030 UMA\n5.- BIENES MOSTRENCOS.\nARTÍCULO 63.- Ingresos obtenidos por los bienes mostrencos que se rematen o vendan de acuerdo a las disposiciones relativas.\n6.- LOS PRODUCTOS DE LA GACETA MUNICIPAL.\nARTÍCULO 64.- Se regirán por las siguientes tarifas:\nI.- SUSCRIPCIONES Y EJEMPLARES:\na).- Suscripción anual.......................... 15.00 UMA\nb).- Ejemplar mensual........................... 2.00 UMA\nc).- Ejemplar atrasado del año en curso......... 1.50 UMA\nd).- Ejemplar de ediciones especiales, reglamentos, bandos, etc.................. 2.50 UMA\nII.- INSERCIONES:\na).- Publicación a particulares, por plana...... 90.00 UMA\nb).- Publicación a particulares, por media de plana...................................... 45.00 UMA\nc).- Publicación a particulares, por cuarto de plana...................................... 25.00 UMA\n7.- ENAJENACIÓN DE BIENES MUEBLES E INMUEBLES PROPIEDAD DEL GOBIERNO\nMUNICIPAL.\n8.- ORGANISMOS DESCENTRALIZADOS, PARAMUNICIPALES Y/O FIDEICOMISOS.\nARTÍCULO 65.- Los rendimientos producidos por organismos descentralizados y empresas de participación municipal, se percibirán cuando lo decreten y exhiben, conforme a sus respectivos regímenes interiores.\nARTÍCULO 66.- Trámite de pasaporte mexicano:\nTrámite de citas para pasaporte:\na).- Cita ordinaria................................... 4.00 UMA\nARTÍCULO 67.- Pago de derechos por recepción y revisión de documentos, por trámite y solicitudes de donación al municipio o adquisición de predios................................. 2.00 UMA\n10.- PRODUCTOS NO COMPRENDIDOS EN LAS FRACCIONES EN LA LEY DE\nLIQUIDACIÓN O PAGO.\nARTÍCULO 68.- Los productos no pagados en el ejercicio fiscal en que se causaron, se cobrarán como ingresos causados en ejercicios fiscales anteriores, pendientes de liquidación o pago, aplicando en cuanto al fondo, las Leyes vigentes a la fecha en que se generaron y en cuanto a la forma, mediante el procedimiento administrativo de\nBaja California o en su caso, el procedimiento judicial que corresponda.\n11.- PRODUCTOS FINANCIEROS DE LAS CUENTAS BANCARIAS ADMINISTRADAS\nPOR EL AYUNTAMIENTO DE SAN QUINTÍN, BAJA CALIFORNIA.\nARTÍCULO 69.- Los rendimientos e intereses producidos por los diferentes ingresos recaudados que se encuentran en las cuentas bancarias.\nTÍTULO QUINTO\nAPROVECHAMIENTOS\n1.- RECARGOS.\nARTÍCULO 70.- La tasa de recargos en caso de prórroga, será del 2.00% mensual y será incrementada en un 50% tratándose de mora.\nLos recargos se causarán hasta por 5 años.\n2.- GASTOS DE EJECUCIÓN.\nARTÍCULO 71.- Los gastos de ejecución se cobrarán a quien se le requiera, por haber incurrido en incumplimiento de obligaciones fiscales no satisfechas dentro de los plazos legales, una vez\nLey de Hacienda Municipal del Estado de Baja California. En ningún equivalente a 0.25 veces del valor diario de la Unidad de Medida y\nActualización Vigente, ni excederán del equivalente a 20.00 veces del valor diario de la Unidad de Medida y Actualización Vigente, los honorarios del ejecutor o ejecutores que intervengan, cualquiera que sea el número, la naturaleza y la importancia de las diligencias que practiquen. Las oficinas exactoras bajo la revisión de la Dirección de Administración y Finanzas, determinarán la proporción que corresponda a cada Ejecutor, siempre que en un mismo expediente hubieren actuado varios.\nI. Por el requerimiento.\nII. Por el embargo.\nIII. Por el remate, enajenación fuera de remate o adjudicación del Municipio.\nLos gastos por impresiones, publicaciones, avalúos de inmuebles o cualquier otra erogación que, con el carácter de extraordinario, sea necesaria para el éxito del procedimiento administrativo de ejecución se liquidarán por separado.\nLos honorarios de los interventores con cargo a la caja y de los administradores se determinarán discrecionalmente por las autoridades fiscales, tomando en consideración el monto del crédito fiscal adecuado y la situación económica del deudor.\n3.- MULTAS.\nARTÍCULO 72.- Las multas por infracciones a las disposiciones fiscales y a otras leyes y reglamentos de jurisdicción municipal se para el Estado de Baja California, esta Ley de Ingresos, los ordenamientos legales correspondientes y, en su defecto, con multa de hasta 100.00 UMA, el importe.\nConcepto de Impuesto Predial, lo establecido en el Artículo 89\nFracción I inciso l) de la Ley de Hacienda Municipal del Estado de\nBaja California, se establece en este Artículo, los mínimos y máximos de aplicación en lo referente a dichas multas, tomando en consideración los principios constitucionales, de legalidad, obligatoriedad, proporcionalidad y equidad. Para quedar de la siguiente manera:\nSe aplicará, de acuerdo a la determinación líquida del Impuesto\nPredial, que para ellos se realice de conformidad con el Artículo 7 de trate.\nDESDE: HASTA:\n$100.00 $2,000.00................... 2.00 UMA\n$2,001.00 $12,000.00................... 5.00 UMA\n$12,001.00 $21,000.00................... 15.00 UMA\n$21,001.00 $49,999.00................... 40.00 UMA\n$50,000.00 en adelante.................. 75.00 UMA\n4.- VENTA DE SUBPRODUCTOS.\nARTÍCULO 73.- Venta de subproductos de la Coordinación de Servicios\nPúblicos (Rastro) que se regirá bajo la siguiente:\na).- Sangre................................... $0.375 por litro\nb).- Cebos-grasas............................. $0.100 por kilo\n5.- REINTEGROS E INDEMNIZACIONES.\na) En caso de pago de contribuciones por medio de cheque recibido en las cajas de la Recaudación, en tiempo, y no sea acreditado por la Institución\nBancaria, dará lugar al cobro del monto e indemnización del 20% del valor del mismo.\nLa indemnización mencionada, el monto del cheque y en su caso de los recargos, se cobrarán mediante el procedimiento administrativo de ejecución, falta de pago no le es imputable.\nb) Indemnización derivada de daños o deterioros en las instalaciones, infraestructura vial, hidráulica, de servicios públicos y demás bienes de propiedad municipal, que se cobrarán de acuerdo a su costo, que aprobará el Órgano de Control\nInterno.\n6.- DONACIONES, CESIONES, HERENCIAS Y LEGADOS A FAVOR DEL MUNICIPIO.\n7.- OTORGAMIENTO Y USUFRUCTO DE DERECHOS.\n8.- RECUPERACIÓN PARCIAL DE PRIMAS DE SEGUROS DE VIDA.\n9.- CAUCIONES DE FIANZAS Y DEPÓSITOS CUYA PÉRDIDA SE DECLARE POR\nRESOLUCIÓN FIRME.\n10.- SUBSIDIOS QUE OTORGUE EL GOBIERNO DEL ESTADO.\n11.- SUBSIDIOS QUE OTORGUE EL GOBIERNO FEDERAL.\n12.- APROVECHAMIENTOS NO COMPRENDIDOS EN LAS FRACCIONES DE LA LEY\nDE INGRESOS CAUSADAS EN EJERCICIOS FISCALES ANTERIORES\nPENDIENTES DE LIQUIDACIÓN O PAGO.\nARTÍCULO 74.- Los aprovechamientos no pagados en el ejercicio fiscal en que se causaron, se cobrarán como ingresos causados en ejercicios fiscales anteriores, pendientes de liquidación o pago, aplicando en cuanto al fondo, las Leyes vigentes a la fecha en que se generaron y en cuanto a la forma, mediante el procedimiento administrativo de\nBaja California o en su caso, el procedimiento judicial que corresponda.\nLos pagos que se hagan, se aplicarán a los créditos más antiguos principal, a los accesorios en el siguiente orden:\n1.- Gastos de ejecución.\n2.- Recargos.\n3.- Multas.\n4.- Crédito fiscal, suerte principal.\nTÍTULO SEXTO\nPARTICIPACIONES, APORTACIONES, CONVENIOS, INCENTIVOS DERIVADOS DE\nARTÍCULO 75.- Las participaciones en Impuestos Federales y Estatales así como aportaciones que perciba el Municipio, serán las que fijen las Leyes, Convenios y Acuerdos Federales y Estatales respectivos.\n1).- PARTICIPACIONES EN IMPUESTOS FEDERALES\n2).- PARTICIPACIONES EN IMPUESTOS ESTATALES:\na).- Por convenios con el Gobierno del Estado para la realización de obras.\nb).- Por otros impuestos o ingresos del Estado, que señalen las\nLeyes, acuerdos o convenios que las regulen.\nc).- Por convenios de los Organismos Públicos Descentralizados realización de obras.\n3).- APORTACIONES: para obras y servicios públicos, o programas especiales, Paramunicipales.\nb) Aportaciones federales del Ramo 33:\nMunicipal.\nMunicipios.\n4.- CONVENIOS:\nIncluye lo referente a otros ingresos por convenios federales, municipales.\n5.- INCENTIVOS DERIVADOS DE LA COLABORACIÓN FISCAL.\nTÍTULO SÉPTIMO\n1.- CRÉDITOS OTORGADOS AL MUNICIPIO.\n2.- APORTACIONES EXTRAORDINARIAS ESTATALES Y FEDERALES.\n3.- OTROS.\nCAPÍTULO ÚNICO DISPOSICIONES GENERALES\nARTÍCULO 76.- La validez de las licencias y permisos otorgados por el Ayuntamiento de San Quintín, está condicionada al exacto cumplimiento de los ordenamientos legales.\nARTÍCULO 77.- Las cuotas de Impuestos y Derechos, serán proporcionales en los casos de apertura, siempre que el período sea menor de seis meses, a excepción de los correspondientes a los contribuyentes eventuales.\nARTÍCULO 78.- Los gravámenes que prevé la presente Ley, no serán municipales, salvo por autorización expresa del Congreso del Estado de Baja California; con excepción de los recargos, que podrán condonarse total o parcialmente, conforme al Artículo 110 de la Ley de Hacienda Municipal del Estado de Baja California.\nARTÍCULO 79.- Se entiende como fecha de iniciación de operaciones de las personas físicas y de las unidades económicas, aquella en que ingreso. En caso de personas morales, el día de su constitución, aun fecha en que se obtenga el primer ingreso.\nARTÍCULO 80.- Las personas físicas, morales o unidades económicas ambulantes, agentes de ventas, comisionistas, repartidores, concesionarios, ambulantes o cualquier otro nombre que se le da al expendedor, serán solidariamente responsables del pago del impuesto, derecho o multa que origine el motivo de las actividades que ejerzan, para lo cual se constituirán en retenedores de los créditos fiscales, debiendo enterarlos a la Recaudación de Rentas, dentro de los plazos que fijan las Leyes Fiscales de este ejercicio fiscal 2025 será semestral.\nARTÍCULO 81.- Cuando se establezca un plazo específico para el pago de un derecho o impuesto, ya sea en esta Ley o en otra disposición normativa de la cual derivaren aquellos, vencido este término se causará un recargo económico independientemente de las sanciones administrativas a que hubiere lugar.\nLas dudas y/o aclaraciones que pudieran presentarse con relación a los términos, plazos, condiciones o formas, en las que deban de cumplirse las contribuciones previstas en esta Ley, se resolverán, por la autoridad administrativa en lo que resultare aplicable.\nARTÍCULO 82.- Para la autorización de trámites ante las autoridades municipales, tales como permisos, licencias, revalidaciones, inspecciones, constancias, certificados o similares solicitados a las siguientes direcciones: Dirección de Protección Civil, Dirección de Bomberos, Dirección de Administración Urbana y Dirección de\nComercio, Alcoholes y Espectáculos Públicos, es requisito de la actividad comercial. Esta disposición no aplicará para los\nImpuesto Predial.\nARTÍCULO 83.- Espectáculos públicos con fines culturales, sociales establecido en los artículos 12 y 13 de la presente Ley en tasa 0%, no incluya venta directa o indirecta de alcohol y sea sin fines de lucro.\nTRANSITORIOS\nARTÍCULO PRIMERO.- La presente Ley entrará en vigor el día primero de enero del año dos mil veinticinco.\nARTÍCULO SEGUNDO.- Para las contribuciones previstas en esta Ley y en lo que resulte aplicable, se reconocerán los efectos de los reglamentos, acuerdos, circulares planes, programas y demás normatividad que rige dichas contribuciones, que hubieren sido emitidos por las autoridades del Ayuntamiento de Ensenada, Baja\nCalifornia, en ejercicio de sus atribuciones y ajustados a la legalidad, hasta en tanto se emitan los propios por el Ayuntamiento de San Quintín y/o sus autoridades.\nARTÍCULO TERCERO.- Para las contribuciones previstas en esta Ley y en lo que resulte aplicable, se reconocerán los efectos de los convenios de colaboración y/o coordinación, actos, acuerdos y demás\nQuintín, Baja California.\nARTÍCULO CUARTO.- Los actos que se hubieren suscrito entre contribuyentes y/o particulares comprendidos dentro de la demarcación territorial del Municipio de San Quintín, Baja\nCalifornia, se reconocerán sus efectos, condiciones y alcances, en\nSan Quintín, conforme a la legislación que les resultare aplicable al momento de su generación, las que necesariamente deberán quedar a favor del mismo; siempre y cuando estén ajustados a la legalidad.\nARTÍCULO QUINTO.- Para los efectos de la revalidación de permisos y licencias, así como sus prórrogas, las autoridades del Municipio de\nSan Quintín, Baja California, tomarán en consideración el registro establecido en esta Ley.\nARTÍCULO SEXTO.- Los adeudos de ejercicios anteriores a cargo de los contribuyentes por créditos fiscales correspondientes a la demarcación territorial del Municipio de San Quintín, Baja\nCalifornia, generados con anterioridad a la entrada en vigor del\nDecreto No. 46, publicado en el Periódico Oficial del Estado de Baja\nCalifornia, de fecha 27 de febrero de 2020, por el que se crea el\nMunicipio de San Quintín, Baja California, deberán ingresarse a la\nDirección de Administración y Finanzas del Ayuntamiento de San\nQuintín, Baja California.\nARTÍCULO SÉPTIMO.- Las consecuencias generadas con motivo de las contribuciones o actos que indebidamente, por error u omisión, sean cobrados o ejecutados por parte de las autoridades del Municipio de\nEnsenada, Baja California, que guarden relación con la demarcación territorial del Municipio de San Quintín, Baja California, a partir de la entrada en vigor de la presente Ley, serán responsabilidad de aquel.\nARTÍCULO OCTAVO.- Las consecuencias generadas con motivo de la aplicación y cobro indebido de las contribuciones que se\nCalifornia, que guarden relación con la demarcación territorial del\nMunicipio de San Quintín, Baja California, deberán quedar en favor de este último.\nARTÍCULO NOVENO.- Las consecuencias de los actos que sean ventilados ante autoridades judiciales o administrativas, relacionados con la aplicación de las Leyes de Ingresos del Municipio de Ensenada, Baja\nCalifornia, que guarden relación con la demarcación territorial del\nMunicipio de San Quintín, Baja California, deberán correr a cargo del Municipio de Ensenada.\nARTÍCULO DÉCIMO.- Los actos judiciales o administrativos que se autoridades del Municipio de Ensenada, Baja California, relacionada con la demarcación territorial del Municipio de San Quintín, Baja\nCalifornia, seguirán siendo responsabilidad de este hasta su conclusión.\nARTÍCULO DÉCIMO PRIMERO.- Los reglamentos, convenios, acuerdos y demás emitidos y/o celebrados por el Municipio de Ensenada, Baja\nCalifornia, con la Federación, el Estado u otros Entes Públicos relativos a las contribuciones y sus accesorios, se aplicará por el\nMunicipio de San Quintín, conforme al Transitorio Decimoquinto del\nDecreto No. 46, publicado en el Periódico Oficial del Estado de Baja\nCalifornia del 27 de Febrero de 2020, mientras se emitan los propios.\nARTÍCULO DÉCIMO SEGUNDO.- Para el apoyo de las acciones afirmativas de las políticas públicas para la transversalidad de la perspectiva de género, el Ayuntamiento de San Quintín, se destinará un 15%\n(quince por ciento) sobre el pago de derechos por permiso nuevo, cambios a permisos y revalidación anual del permiso de establecimientos para la venta, almacenaje y consumo público de bebidas alcohólicas, o por el pago de derechos por horarios extraordinarios, así como, sobre el pago de derechos por revalidación anual del permiso de operación, de centros de apuestas, apuestas remotas, salas de sorteos de números y/o casinos.\nARTÍCULO DÉCIMO TERCERO.- Para efectos de esta Ley, se considera como:\nZONA URBANA: Son las delegaciones de Camalú, Vicente Guerrero, San\nQuintín, El Rosario, que cuenten con acciones de urbanización y que se encuentren dentro de la mancha urbana o zona de transición.\nZONA SUB-URBANA: Zonas dentro y/o al límite de la mancha urbana que no han recibido acción de urbanización, pero es factible de contar con ello.\nZONA RURAL: Son los asentamientos ubicados en las delegaciones El\nMármol, Punta Prieta, Bahía de Los Ángeles y Villa Jesús María.\nZONA TURÍSTICA:\n- Zonas Costeras del Pacifico, de norte a sur: Ejido Rubén Jaramillo, Ejido Mesa de San Jacinto, Ejido Capricornio, Colonia Michoacán;\nParcelas: VG-059-129, VG-059-016, VG-P59-049, VG-059-130, VG-N59-040, VG-059-072, VG-S59-013, VG-059-027 (Fraccionamiento Costa Brava);\nZona Costera Vicente Guerrero, Ejido Zarahemla, Laguna Figueroa, Ejido\nPadre Kino, Ejido General Leandro Valle, Ejido Chapala, La Chorera, Punta Mazo, Zona Costera Ejido El Papalote, Fraccionamiento Monte\nCeniza, San Marcos, San Rafael, Zona Costera Colonia Juan María\nSalvatierra, Punta Azufre, Cielito Lindo (VG-P55-059), Venustiano\nCarranza, Ejido Nueva Odisea, Ejido Valle Tranquilo, La Bocana del\nRosario, Ejido Reforma Agraria, Ejido Revolución, Ejido San José de las Palomas, Ejido Juárez, Ejido Nuevo Rosarito, Ejido Villa Jesús\nMaría.\n- Zonas costeras del Golfo de California (Mar de Cortez), sur a norte:\nEjido Villa Jesús María, Ejido el Barril, Bahía San José, Bahía Santa\nTeresa, Bahía San Francisquito, Bahía San Rafael, Bahía Las Animas, Bahía Ángeles, Bahía de Los Remedios e Isla Ángel de la Guarda.\nZONA DE FESTEJOS PÚBLICOS MUNICIPALES: Las áreas donde se realiza la feria de San Quintín, fiestas de Santo Domingo, Parques Públicos.\nARTÍCULO DÉCIMO CUARTO. – En caso de que, durante la vigencia de la presente Ley, alguna de las autoridades, o unidades administrativas sufriera alguna modificación o cambiara su denominación, los servicios y atribuciones a su cargo, se entenderán referidos y prestados por la que la sustituya.\nARTÍCULO DÉCIMO QUINTO.- El Impuesto Predial se pagará por los últimos cinco años, independientemente que se encuentre requerido o embargado, siempre y cuando el pago se realice en una sola exhibición, pudiendo tener este beneficio las claves catastrales que se encuentren en proceso judicial (siempre y cuando se desistan para obtener este beneficio), el periodo de vigencia será el ejercicio fiscal 2025.\nARTÍCULO DÉCIMO SEXTO.- Con el propósito de ayudar a la economía y patrimonio de las familias, propietarios o poseedores de predios ejidales o privados que durante el ejercicio fiscal 2025 concluyan ante las autoridades competentes; la obligación de cubrir el monto ejercicio fiscal 2025.\nARTÍCULO DÉCIMO SÉPTIMO.- Para los beneficiarios del Derecho por\nServicio de Alumbrado Público en el ejercicio fiscal 2025, en los en un 10% o más al respecto del monto pagado en el año 2024, la tarifa a cubrir no excederá de $ 7.00 pesos adicionales mensuales más en comparación con lo pagado en el ejercicio fiscal 2024.\nARTÍCULO DÉCIMO OCTAVO.- Se podrá, previa solicitud presentada ante\nPresidencia, exentar los montos de derechos establecidos en el\nArtículo 30 de la presente Ley relativo a los derechos por la expedición y/o revalidación de permisos para el uso u ocupación de las vías públicas, por comerciantes ambulantes o con puestos fijos o semifijos, siempre que sea solicitado en los meses de enero, febrero o marzo por la persona que desee ser titular del permiso que se emita.\nARTÍCULO DÉCIMO NOVENO.- Se exenta a las personas físicas y morales inscritas en el Programa Estatal de Vivienda 2022-2027, del pago de derechos que se causen por; factibilidades, dictámenes, certificados, autorizaciones, licencias y en general, por trámites relacionados con la construcción de vivienda social, exclusivamente para los proyectos habitacionales que cuenten con certificado expedido por el Titular de la Secretaría de Infraestructura, Desarrollo Urbano y Reordenación Territorial del Estado de Baja\nCalifornia, y se lleven a cabo en términos de los Lineamientos\nGenerales para la inscripción en el Programa Estatal de Vivienda publicado en el Periódico Oficial del Estado en fecha 21 de octubre de 2022 y actualizaciones posteriores, así como del Programa de de la coordinación de SEDATU, CONVAI, INSUS, INFONAVIT y cualquier el proceso de ejecución del mismo.\nLos derechos a exentar se enuncian a continuación:\nI. Factibilidad de uso del suelo\nII. Certificado de libertad de gravamen\nIII. Dictamen de uso del suelo\nIV. Manifestación de impacto ambiental\nV. Movimiento de tierras\nVI. Deslinde catastral\nVII. Licencia de construcción\nVIII. Régimen de Propiedad en Condominio\nIX. Licencia de Fraccionamiento\nX. Certificado de numero oficial\nXI. Constancia de obra terminada\nXII. Cambio de propietario\nXIII. Impuesto sobre adquisición de bienes inmuebles\nArtículo Transitorio Adicionado\nCalifornia, a los veinte días del mes de diciembre del dos mil veinticuatro.\nC. EVELYN SÁNCHEZ SÁNCHEZ\nDIPUTADA PRESIDENTA\nC. MICHELLE ALEJANDRA TEJEDA MEDINA\nDIPUTADA SECRETARIA\nARTÍCULO ÚNICO TRANSITORIO DEL DECRETO No. 71, POR EL QUE SE\nTRANSITORIO A LA LEY DE INGRESOS DEL MUNICIPIO DE SAN QUINTÍN, BAJA\nCALIFORNIA PARA EL EJERCICIO FISCAL 2025; PUBLICADO EN EL PERIÓDICO\nPOR LA H. XXV LEGISLATURA; SIENDO GOBERNADORA CONSTITUCIONAL LA C.\nMARINA DEL PILAR ÁVILA OLMEDA 2021-2027.\nTRANSITORIOS\nÚNICO. La presente reforma entrará en vigor al día siguiente de su publicación en el\nPeriódico Oficial del Estado de Baja California.\nDADO en Sesión Ordinaria de la XXV Legislatura en la Ciudad de Tijuana, B.C., a los veintisiete días del mes de marzo del año dos mil veinticinco.\nDIP. EVELYN SÁNCHEZ SÁNCHEZ\nPRESIDENTA\n(RÚBICA)\nDIP. MICHELLE ALEJANDRA TEJEDA MEDINA\nSECRETARIA\n(RÚBICA)\nDE CONFORMIDAD CON LO DISPUESTO POR LA FRACCIÓN I DEL ARTÍCULO\nCALIFORNIA, IMPRÍMASE Y PUBLÍQUESE.\nMEXICALI, BAJA CALIFORNIA, A LOS 31 DÍAS DEL MES DE MARZO DEL AÑO\nDOS MIL VEINTICINCO.\nMARINA DEL PILAR ÁVILA OLMEDA\nGOBERNADORA DEL ESTADO\nDE BAJA CALIFORNIA\n(RÚBRICA)\nALFREDO ÁLVAREZ CÁRDENAS\nSECRETARIO GENERAL DE GOBIERNO\nDEL ESTADO DE BAJA CALIFORNIA\n(RÚBRICA)",
  "ordenamiento": "REGLAMENTO",
  "jurisdiccion": "BAJA CALIFORNIA",
  "fuente_oficial": "Periódico Oficial",
  "FECHA PER OFIC": "2025/04/11",
  "ESTATUS": "VIGENTE",
  "TOMO": "TOMO_II",
  "URL": "https://www.congresobc.gob.mx/Documentos/ProcesoParlamentario/Leyes/TOMO_II/20250411_LEYINGRESOSANQUINTIN2025.PDF",
  "es_escaneado": false,
  "tiene_tablas": false,
  "materia": [
    "financiero",
    "fiscal",
    "económico"
  ]
}