{
  "titulo": "Ley QUE REGLAMENTA EL SERVICIO DE AGUA POTABLE EN EL ESTADO DE BAJA CALIFORNIA",
  "Contenido": "EN EL ESTADO DE BAJA CALIFORNIA\nPublicada en Periódico Oficial No. 4, Número Especial, de fecha\nARTICULO 1.- La proyección, dirección y ejecución de las obras de captación, conducción y distribución de los Sistemas de Agua Potable para el servicio público de las poblaciones del Estado, estará a cargo de los Organismos que designen las leyes respectivas y se efectuarán de acuerdo con las necesidades que demande el servicio y con sujeción a las disposiciones legales sobre la materia.\nSentencia de Acción de Inconstitucionalidad 119/2021 y su acumulada 128/2021\nARTICULO 2.- La operación, conservación, vigilancia y reparación de los Sistemas de\nAgua Potable, las obras de ampliación, la recaudación de los ingresos por la prestación de los mismos, así como la imposición de sanciones por infracción a las disposiciones de esta\nLey, estará igualmente a cargo de los Organismos a que se refiere el artículo anterior.\nArtículo Reformado\nDE LA OBLIGACION DE SURTIRSE DE AGUA POTABLE DEL SERVICIO PUBLICO\nARTICULO 3.- Están obligados a contar con los servicios de agua potable y alcantarillado sanitario, en los lugares donde existan dichos servicios:\nI.- Los propietarios o poseedores de predios edificados.\nII.- Los propietarios o poseedores de giros mercantiles e industriales y de cualquier otro establecimiento que por naturaleza, o de acuerdo con las leyes y reglamentos, estén obligados al uso del agua.\nIII.- Los propietarios o poseedores de predios no edificados, en los que sea obligatorio conforme a las leyes y reglamentos, hacer uso de agua.\nIV.- Los poseedores de predios, cuando la posesión se derive de contratos de compra-venta en que los propietarios se hubieren reservado el dominio del predio.\nARTICULO 4.- Es potestativo contar con los servicios de agua potable y alcantarillado sanitario, para los dueños o poseedores de predios no edificados, en los casos en que no sea obligatorio conforme a las leyes y reglamentos.\nLey que Reglamenta el Servicio de Agua Potable en el Estado de Baja California. Página 1\nARTICULO 5.- La prestación de los servicios de agua potable y alcantarillado sanitario, deberá solicitarse por los propietarios o poseedores:\nI.- Dentro de los tres meses siguientes a la fecha en que se notifique que ha quedado establecido el servicio público en la calle en que se encuentren sus predios, giros o establecimientos.\nII.- Con 15 días de anticipación a la fecha de la apertura de sus giros o establecimientos, si existe el servicio público.\nIII.- Antes de iniciar edificaciones sobre predios que carezcan de los servicios de agua potable y alcantarillado sanitario. No se prestarán los servicios públicos a que se refiere este artículo, sin haberse suscrito previamente el contrato respectivo.\nLos usuarios que por cualquier motivo tuvieran que solicitar en términos de las disposiciones fiscales, el pago a plazos por adeudos relacionados con los servicios de agua, estarán obligados a formalizar la prestación de dicho servicio a través del contrato a que se refiere el presente artículo, en caso de que éste no se hubiere suscrito con anterioridad.\nARTICULO 6.- Para cada predio, giro o establecimiento se requiere una toma por separado, salvo los casos en que a juicio del Organismo encargado del servicio, no haya inconveniente en autorizar la contratación de la derivación respectiva.\nARTICULO 7.- Se considera como un solo predio, aquél respecto de cual concurran las siguientes circunstancias:\nI.- Que pertenezca a una sola persona, física o moral, o que si pertenece a varias, la propiedad sea pro-indiviso.\nII.- Si se trata de predio edificado, que los diversos departamentos, viviendas o locales de que se componga, por su distribución y uso releven claramente la intención de constituir con ellos un solo edificio, o si son varios edificios, que tengan patios, pasillos u otros servicios comunes.\nIII.- Que si se trata de un predio no edificado, no se encuentre dividido en forma que hagan independientes unas partes de otras, y\nIV.- En todas las demás circunstancias análogas a las señaladas que revelen que se trata de un solo predio.\nARTICULO 8.- Para los efectos de esta Ley, se considera como predio edificado, todo terreno sobre el que existan construcciones permanentes o provisionales; y como no edificado, el que carezca de ellas o en el que las construcciones se reduzcan a las tapias que lo cerquen.\nLey que Reglamenta el Servicio de Agua Potable en el Estado de Baja California. Página 2\nARTICULO 9.- No se consideran edificados los predios en que haya construcciones transitorias, como carpas de espectáculos, campamentos de trabajo y otras análogas, conforme a las leyes o reglamentos, no tengan necesidad de hacer uso de agua.\nARTICULO 10.- Se considerará como un sólo predio, giro o establecimiento aquel que llene los siguientes requisitos:\nI.- Que pertenezca a una sola persona, física o moral o a varias pro-indiviso;\nII.- Que sus diversos locales estén comunicados entre sí, siempre que las comunicaciones sean necesarias para su uso y no tengan simplemente el objeto de hacer aparecer que existe relación de dependencia entre ellos;\nIII.- Que el objeto de la empresa sea a explotación de una sola industria o comercio o que siendo varios, sean de naturaleza similar y complementaria unos de otros. Si se trata de giros cuyo funcionamiento este reglamentado, deberán hallarse amparados por una misma licencia;\nIV.- Que esté bajo una sola administración; y\nV.- Que existan todas las demás circunstancias análogas a las señaladas, que demuestren que se trata de un solo giro o establecimiento.\nARTICULO 11.- Para los efectos de esta Ley, el Organismo encargado del servicio determinará, en caso de duda, si se trata de uno o varios predios, giros o establecimientos, tomando en consideración la información y la documentación correspondiente.\nARTICULO 12.- De toda subdivisión o manifestación de apertura de giros y establecimientos obligados a contar con los servicios de agua, deberá informarse al\nOrganismo encargado del servicio que corresponda dentro del plazo de diez días hábiles contados a partir de que esta tenga lugar, enviando copia de la documentación respectiva.\nIgualmente deberá enviarse al referido Organismo, copia de la manifestación de traspaso, traslado o clausura de los mencionados giros o establecimientos, dentro del plazo antes señalado.\nLos Ayuntamientos, en el ámbito de su competencia, deberán remitir al Organismo encargado del servicio que corresponda, la información a que hace referencia este artículo, en los términos de los acuerdos que en su caso celebren.\nARTICULO 13.- En los casos de construcción de edificios sujetos al régimen de propiedad en condominio, el Organismo encargado del servicio determinará la forma en que deberán instalarse las redes interiores de distribución de agua; por lo tanto, para que la autoridad competente expida la licencia de construcción, será indispensable que\nLey que Reglamenta el Servicio de Agua Potable en el Estado de Baja California. Página 3 encargado del servicio.\nARTICULO 14.- Los propietarios o poseedores de predios o giros están obligados a pagar el costo de las obras a que se refieren los artículos 1 y 2 de esta Ley, en los términos y forma que señalen las leyes respectivas.\nSentencia de Acción de Inconstitucionalidad 119/2021 y su acumulada 128/2021\nARTICULO 15.- La prestación de los servicios de agua, causarán los derechos que se establezcan en las disposiciones fiscales aplicables.\nSentencia de Acción de Inconstitucionalidad 119/2021 y su acumulada 128/2021\nARTICULO 16.- Están obligados al pago de los derechos por servicio de agua:\nI.- Los propietarios de los predios o giros que tengan instaladas tomas.\nII.- Los poseedores de predios o giros que tengan instaladas tomas:\na).- Cuando la posesión se derive de contratos de promesa de venta o de contratos de compra-venta con reserva de dominio, mientras esos contratos estén en vigor, y\nb).- Cuando no se conozca el propietario.\nIII.- En forma solidaria, los arrendadores y arrendatarios de predios locales que tengan instaladas tomas.\nLas personas obligadas a pagar los derechos por servicios de agua, deberán cubrirlos en las oficinas recaudadoras o en establecimientos autorizados por las autoridades fiscales, dentro de los quince días naturales posteriores al periodo facturado.\nARTICULO 17.- Cuando no se cubran los derechos a que se refiere el artículo 15, en el plazo que señala el artículo anterior, su pago y el de los accesorios legales respectivos, se\nEstado de Baja California. Sin embargo, el suministro de agua potable y alcantarillado básica y servicios de salud pública, no podrán reducirse ni suspenderse.\nPárrafo Reformado\nLey que Reglamenta el Servicio de Agua Potable en el Estado de Baja California. Página 4 doméstico, ante la falta de pago de más de tres meses, únicamente podrá reducirse el suministro de agua en un 50% del diámetro de la toma contratada y ante la falta de pago de más de seis meses, sólo podrá reducirse el suministro de agua en un 70% del diámetro de la toma contratada, en tanto el usuario cubra el importe correspondiente, o en su caso, celebre el convenio respectivo, en términos de las disposiciones fiscales, en el que se considerará su capacidad de pago.\nArtículo Reformado\nSentencia de Acción de Inconstitucionalidad 119/2021 y su acumulada 128/2021\nARTICULO 18.- Los ingresos que recauden los Organismos encargados de los anteriores servicios, se invertirán íntegramente en todo lo relacionado a los Sistemas de\nAgua y en ningún caso podrán ser afectados a otro fin distinto.\nARTICULO 19.- En el caso de edificios sujetos al régimen de propiedad en condominio, los propietarios de cada piso, departamento, vivienda o local, pagarán los derechos de acuerdo con el aparato medidor que se instale en cada una de tales propiedades y además cubrirán por medio de la administración del edificio, la cuota que proporcionalmente les corresponda por el consumo de agua potable que se haga para el servicio común del propio edificio.\nDe este último pago responden solidariamente todos los propietarios y en consecuencia, por su adeudo se podrá embargar la totalidad del inmueble. Mientras no se instalen aparatos medidores, los derechos se causarán conforme a lo dispuesto en la tarifa respectiva de la Ley de Ingresos del Estado, de acuerdo al consumo que determine el\nOrganismo encargado del servicio, estando el pago a cargo de la administración del edificio.\nSentencia de Acción de Inconstitucionalidad 119/2021 y su acumulada 128/2021\nARTICULO 20.- Tienen responsabilidad objetiva para el pago de las cuotas por consumo de agua que establece la Ley de Ingresos del Estado, las personas que adquieran con anterioridad a la adquisición.\nSentencia de Acción de Inconstitucionalidad 119/2021 y su acumulada 128/2021\nDE LA INSTALACION DEL SERVICIO\nARTICULO 21.- El costo de las obras relativas a agua potable y alcantarillado sanitario que ejecuten los Organismos encargados del servicio, deberán ser pagados proporcionalmente por los beneficiarios de las mismas.\nLey que Reglamenta el Servicio de Agua Potable en el Estado de Baja California. Página 5\nLos beneficiarios de las obras ejecutadas o en ejecución, deberán acudir ante el\nOrganismo encargado del servicio para celebrar los contratos o convenios respectivos, estableciéndose en ellos las condiciones de pago. En aquellos casos en que la contratación o el convenio se realice después de doce meses de ejecutados los trabajos, el costo que le corresponda al beneficiario de la obra se actualizará mensualmente, con el factor que se obtenga de dividir el Índice Nacional de Precios al Consumidor, que publique el Banco de\nMéxico, del último mes inmediato anterior al mes por el cual se efectué el pago, entre el citado índice del último mes inmediato anterior al del mes que se debió efectuar el pago. En los casos en que el índice Nacional de Precios al Consumidor del mes anterior al mes de la contratación o el convenio respectivo, no haya sido publicado por el Banco de México, la actualización de que se trate se realizará aplicando el último Índice mensual publicado. Los\nOrganismos podrán también ejecutar y derramar las obras a que se refiere este artículo, en los términos de la Ley de Urbanización del Estado de Baja California.\nARTICULO 22.- Dentro de los plazos fijados en el artículo 5 de esta Ley, los propietarios o poseedores de predios, giros y establecimientos obligados a contar con el servicio de agua potable y alcantarillado sanitario, o sus legítimos representantes, deberán presentar un escrito al Organismo encargado del servicio solicitando la instalación de la toma correspondiente. En dicho escrito se hará constar:\na).- Nombre y domicilio del solicitante y carácter con que promueve.\nb).- Nombre y domicilio del propietario del predio, giro o establecimiento y ubicación de éstos.\nc).- Número del lote, manzana y colonia.\nd).- Nombre de las calles que limiten la manzana en que se halle ubicado el predio.\ne).- Distancia del lugar en donde haya de instalarse la toma (eje de la toma) a la esquina más próxima, expresando cual es ésta.\nf).- Destino del predio o naturaleza y nombre si lo tiene, del giro o establecimiento de que se trate.\ng).- Diámetro de la toma que se solicite.\nh).- Fecha y firma del solicitante. señala al predio para el que se solicita la instalación de la toma, es el que oficialmente le ha sido fijado.\nARTICULO 23.- Cuando soliciten las tomas los representantes de los propietarios o poseedores de los predios, giros o establecimientos en donde aquellas hayan de instalarse, Ley que Reglamenta el Servicio de Agua Potable en el Estado de Baja California. Página 6 deberán acreditar su personalidad, pudiendo hacerlo por carta poder. Además, tratándose de giros mercantiles o industriales para cuyo funcionamiento se requiera licencia oficial, inconveniente en que se proporcione el servicio de agua, por llenar el giro los requisitos que fijen las leyes o reglamentos respectivos.\nARTICULO 24.- Cuando el Organismo encargado del servicio lo considere necesario, podrá exigir la ratificación ante él, de las cartas poder y la presentación de los documentos que acrediten la propiedad del predio, giro o establecimiento en que haya de instalarse la toma.\nARTICULO 25.- Los propietarios o poseedores de predios, giros o establecimientos, que sin estar legalmente obligados a contar con los servicios de agua potable y alcantarillado sanitario, deseen que se les proporcione estos servicios de acuerdo con la facultad que les concede el artículo 4 de esta Ley, deberán presentar una solicitud en los términos en que señala el artículo 22, acompañada en su caso, de los documentos que menciona el artículo 23.\nARTICULO 26.- Cuando la solicitud no lleve los requisitos que fija el Artículo 22, se prevendrá al interesado que satisfaga los que falten dentro de los diez días hábiles siguientes a la fecha en que quede notificado. No llenándose los requisitos omitidos dentro del plazo señalado, se tendrá por no presentada la solicitud.\nARTICULO 27.- Presentada la solicitud debidamente acordada, se practicará la inspección al predio, giro o establecimiento de que se trate, dentro del término de cinco días, contados a partir de la fecha en que el Organismo encargado del servicio acuerde dicha solicitud, con el objeto de comprobar la veracidad de los datos proporcionados por el promovente y de que se proporcionen los demás que considere necesario dicho Organismo, así como los que sean indispensables para que se formule el presupuesto correspondiente.\nARTICULO 28.- Si del informe que se rinda como resultado de la inspección llevada a cabo de acuerdo con lo dispuesto en el Artículo anterior, no aparece inconveniente legal para la instalación de la toma, dentro de los cinco días siguientes a la fecha en que se rinda dicho informe, se formulará el presupuesto del material necesario, de la mano de obra y de a la fecha en que se formule, para que dentro del término de quince días, contados a partir del siguiente al en que quede notificado el presupuesto, cubra su importe en la oficina\nRecaudadora correspondiente.\nARTICULO 29.- Celebrado el contrato y comprobado el pago del importe del presupuesto a que se refiere el artículo anterior, el Organismo encargado del servicio ordenará la instalación de la toma, que se llevará a cabo dentro de los diez días siguientes.\nLey que Reglamenta el Servicio de Agua Potable en el Estado de Baja California. Página 7\nARTICULO 30.- En los casos de clausura, traspaso o traslado de un giro mercantil o industrial, o de cambio de negocio, tanto el propietario del giro como del predio de que forme parte el local en que se halle instalado el servicio de agua potable y alcantarillado sanitario, anotaciones procedentes en el registro y padrón.\nARTICULO 31.- Las tomas y los medidores deberán instalarse en la forma que determine el Organismo encargado del servicio, de manera que sin dificultad se puedan llevar a cabo las lecturas de consumo, las pruebas de funcionamiento del aparato o bien, su reparación o sustitución.\nARTICULO 32.- Instalada la toma y hecha la conexión que permita el consumo del agua, dentro den los diez días siguientes se comunicará a la oficina de contabilidad respectiva para la apertura de la cuenta correspondiente. Al mismo tiempo se harán las anotaciones en el registro que establece el Artículo 39. En los casos en que, con motivo de la instalación de la toma, se destruya el pavimento, el Organismo encargado del servicio ordenará su reparación en un plazo que no excederá de sesenta días.\nARTICULO 33.- La instalación de ramales, desde la tubería de distribución hasta la llave de paso, se hará por el personal autorizado. El costo de la mano de obra, de los materiales y de la reparación del pavimento, será a cargo de los propietarios o poseedores de los predios, giros o establecimientos; pero una vez hecha la instalación, parcial o totalmente, pasará a propiedad del Organismo encargado del servicio.\nARTICULO 34.- Las tuberías de alimentación, de tinacos o depósitos de almacenamiento de predios, giros o establecimientos que se abastezcan del servicio público de agua potable, deben descargar en la parte superior de dichos tinacos o depósitos, sin que haya posibilidad de que los mismos puedan vaciarse por esas tuberías de alimentación.\nARTICULO 35.- En las tuberías de las instalaciones interiores de los predios, conectadas directamente con las generales de distribución de las redes públicas, no deberán usarse llaves de cierre brusco.\nARTICULO 36.- Cuando tengan que ejecutarse obras de construcción o de reconstrucción de un edificio, o cuando por cualquier otra causa, se haga necesario modificar las instalaciones hidráulicas para el servicio de agua, los interesados deberán solicitar previamente el cambio de lugar de la toma o instalación, expresando las causas que lo motiven, fijando con toda precisión el lugar en que está ubicada y proponiendo el lugar en que debe quedar. El Organismo encargado del servicio resolverá lo conducente.\nSi con la modificación no se infringen las disposiciones de esta Ley, se ordenará el cambio de la toma o instalación, el que deberá hacerse a costa del interesado, por el\nLey que Reglamenta el Servicio de Agua Potable en el Estado de Baja California. Página 8 personal del Organismo encargado del servicio o por el que éste determine. En los casos a que se refiere este artículo se aplicarán, en lo conducente, las disposiciones de los artículos\n23, 24, 25, 26, 28, 29 y 31.\nARTICULO 37.- En los casos en que proceda la supresión de una toma, de acuerdo con las disposiciones de esta Ley, el interesado la solicitará al Organismo encargado del servicio.\nARTICULO 38.- En caso del Artículo anterior, la toma será suprimida siempre y cuando estén al corriente los pagos y si de las investigaciones que al respecto mande practicar el Organismo encargado del servicio, resulta procedente.\nARTICULO 39.- El Organismo encargado del servicio, llevará un registro de tomas en el que consten los siguientes datos:\na).- Ubicación del predio, giro o establecimiento en que se halle instalada.\nb).- El nombre del propietario o poseedor de ellos.\nc).- Número del lote, manzana y colonia.\nd).- Fecha de solicitud de la toma.\ne).- Nombre del solicitante.\nf).- Fecha de instalación de la toma.\ng).- Diámetro de la toma.\nh).- Número y Diámetro de los medidores.\ni).- Fecha en que el medidor sea cambiado y motivos del cambio.\nj).- Fecha en que se retire el medidor y su causa, y\nk).- Los demás que estime necesarios el Organismo encargado del servicio.\nARTICULO 40.- Los propietarios o poseedores de predios, giros o establecimientos, que pretendan que se les autorice una derivación, deberán presentar una solicitud al\nOrganismo encargado del servicio, en la que hagan constar:\na).- El nombre y domicilio del solicitante y carácter con que promueve.\nb).- Ubicación del predio de donde pretenda hacerse la derivación, y la del predio, giro o establecimiento para el que se solicite, expresando el nombre de las calles que limiten la manzana en que se hallen ubicados.\nc).- El destino del predio, u objeto y nombre si lo tiene, del giro o establecimiento para que se solicite la derivación.\nLey que Reglamenta el Servicio de Agua Potable en el Estado de Baja California. Página 9\nd).- Linderos del predio para el que se solicite la derivación, expresando si es limítrofe al en que se halle instalada la toma de la que pretenda hacerse, cuando se trate de derivar agua de un predio para otro.\ne).- Nombre y domicilio del propietario o poseedor del predio de cuya toma se pretenda hacer la derivación.\nf).- Nombre y domicilio del propietario o poseedor del predio, giro o establecimiento para el que se pretende hacer la derivación.\ng).- Fecha y firma del solicitante y del propietario del predio de donde pretenda hacer la derivación. En la misma solicitud, hará constar la oficina correspondiente si el número que en ella se señala al predio para el que se solicita la derivación es el que oficialmente le ha sido fijado.\nARTICULO 41.- Son aplicables a los casos de solicitud de derivaciones de agua, en lo conducente, las disposiciones de los Artículos 23, 24, 25, y 26 de esta Ley.\nARTICULO 42.- Recibida la solicitud para hacer una derivación, se investigará la veracidad de los datos que en ella se proporcionen, y si no hay inconveniente legal se autorizará la derivación, fijando en el contrato respectivo las condiciones y plazo en que deba hacerse.\nARTICULO 43.- Terminada la instalación para derivar el agua, se dará aviso al\nOrganismo encargado del servicio a fin de que éste se cerciore, por medio de inspección, si se ejecutó de acuerdo con la autorización concedida.\nEn el caso de que la instalación no se haya hecho en la forma autorizada, se dará al interesado un plazo que no excederá de quince días para que haga las reformas que procedan, y en caso de no hacerlas se le impondrá la sanción correspondiente.\nARTICULO 44.- Cuando no se haga la derivación dentro del plazo señalado de acuerdo con lo que dispone el Artículo 42, se considerará al interesado como desistido de su solicitud y en caso de insistir en ella posteriormente, deberán repetirse los trámites que señalan dicho Artículo y el anterior.\nARTICULO 45.- Cuando se trate de giros que estén obligados a contar con los necesaria para la derivación dentro del plazo que se les fije en la autorización, fenecido dicho plazo, están obligados a solicitar la toma correspondiente y se harán acreedores a la imposición de las sanciones respectivas.\nARTICULO 46.- Hecha una derivación, el Organismo encargado del servicio, Ley que Reglamenta el Servicio de Agua Potable en el Estado de Baja California. Página 10 permitido hacer uso del agua y en su caso, la instalación del aparato medidor, para los efectos del Artículo 32.\nARTICULO 47.- No se autorizarán derivaciones si existe servicio público de agua potable en la calle donde se encuentren ubicados los predios para los que se solicitan, a excepción de los casos en que la derivación se pida para giros mercantiles o industriales.\nARTICULO 48.- El Organismo encargado del servicio, retirará la autorización concedida para hacer uso de una derivación en los siguientes casos:\nI.- Cuando se inicie la prestación de los servicios de agua potable y alcantarillado sanitario en la calle en donde se encuentre el predio que se surta por medio de la derivación.\nII.- Cuando la derivación cause deficiencias al servicio de agua del predio que proceda.\nIII.- Cuando lo solicite el interesado.\nARTICULO 49.- Cancelada la autorización, se comunicará al interesado a fin de que, en el caso de la fracción I del artículo anterior, gestione la instalación de la toma correspondiente dentro del término que señala el artículo 5 de esta Ley, o en el caso de las fracciones II y III, proceda a abastecerse de agua por otro medio, o en su caso, permita el acceso al local o predio para que pueda cortarse la derivación, lo que deberá hacerse dentro del plazo de treinta días, contados a partir de la fecha de la notificación.\nARTICULO 50.- En los supuestos previstos en el artículo 48 de esta Ley, el\nOrganismo encargado del servicio procederá a la supresión de la derivación y a la cancelación de la cuenta respectiva. En caso de que existan adeudos pendientes a cargo de la cuenta de la derivación suprimida, éstos se cargarán a la de la toma principal.\nARTICULO 51.- La suspensión del suministro de agua potable de una derivación, se sujetará a lo establecido por los artículos 17 y 98 de esta Ley, según sea el caso.\nARTICULO 52.- El costo de los trabajos necesarios para la supresión de tomas principales o derivaciones, será a cargo del usuario y podrá ser cobrado a través del procedimiento administrativo de ejecución señalado en el Código Fiscal del Estado.\nSentencia de Acción de Inconstitucionalidad 119/2021 y su acumulada 128/2021\nARTICULO 53.- Al tomar posesión de predios, giros o establecimientos de donde partan derivaciones de agua, o que reciban los beneficios de las mismas, sus propietarios o\nLey que Reglamenta el Servicio de Agua Potable en el Estado de Baja California. Página 11 existencia de la derivación, dentro de los términos de treinta días contados a partir de la fecha en que tomen posesión.\nDE LA VERIFICACION DEL CONSUMO\nARTICULO 54.- La verificación del consumo de agua potable en los predios, giros o establecimientos que lo reciban, se hará por medio de aparatos medidores.\nARTICULO 55.- Los aparatos medidores sólo podrán ser instalados y retirados por personal del Organismo encargado del servicio o por el que este determine, previa la verificación de su correcto funcionamiento, y retirados por el mismo personal cuando hayan sufrido daños, funcionen defectuosamente o exista cualquiera otra causa justificada que amerite su retiro.\nARTICULO 56.- Una vez instalado un aparato medidor, no podrá variarse su colocación o cambiarse de lugar, sin la previa autorización del Organismo encargado del servicio.\nARTICULO 57.- Los propietarios o poseedores de giros mercantiles o industriales, cualesquiera que estos sean, deberán garantizar por medio de depósito o en la forma que determine dicho Organismo, antes de la contratación del servicio de agua potable y alcantarillado sanitario, el importe de los derechos correspondiente a tres meses de consumo real o estimado, según sea el caso, para cuyo efecto se aplicará la tarifa que establece la Ley de Ingresos del Estado.\nSentencia de Acción de Inconstitucionalidad 119/2021 y su acumulada 128/2021\nARTICULO 58.- Los que por cualquier título ocupen predios, giros o establecimientos en donde se encuentren instalados aparatos medidores, en todo tiempo estarán obligados a permitir su lectura.\nARTICULO 59.- La lectura de los medidores para determinar la facturación por el consumo del servicio de agua potable en cada predio, giro o establecimiento, se hará por éste determine.\nARTICULO 60.- La factura por el consumo de agua será entregada en el domicilio que corresponda al predio, giro o establecimiento de la cuenta respectiva, a través de cualquier medio que el Organismo encargado del servicio determine. Los usuarios que por cualquier motivo no reciban las facturas a que se refiere este artículo, deberán solicitarlas en las oficinas recaudadoras adscritas a los Organismos encargados del servicio.\nLey que Reglamenta el Servicio de Agua Potable en el Estado de Baja California. Página 12\nARTICULO 61.- Las facturas deberán contener como mínimo los siguientes datos:\nI).- Nombre del usuario y domicilio del predio, giro o establecimiento en que se preste el servicio;\nII).- Fecha de expedición;\nIII).- Número de cuenta;\nIV).- Lectura actual y anterior del aparato medidor;\nV).- Consumo registrado por el aparato medidor;\nVI).- Importe del consumo registrado; y\nVII).- Fecha de vencimiento.\nARTICULO 62.- Cuando el usuario del servicio de agua potable y alcantarillado sanitario no esté conforme con el consumo de agua potable registrado en la factura o con el importe del mismo, podrá inconformarse por escrito ante el Organismo encargado del servicio, en los formatos que para tal efecto proporcione el mismo, sin necesidad de formalidad adicional alguna, dentro de los quince días naturales posteriores a la fecha del vencimiento del pago de la factura, aportando en su caso las pruebas que estime pertinentes para acreditar su inconformidad. Si la inconformidad no se presenta dentro de dicho plazo, la factura quedará firme para todos los efectos legales.\nEl Organismo encargado del servicio, dentro del término de treinta días naturales, a partir de la fecha en que se haya presentado la inconformidad, y previa valoración de las pruebas que obren en el expediente, resolverá si deben o no regir los consumos registrados o su importe, imponiendo en su caso, las sanciones que correspondan conforme a la presente Ley.\nLa resolución que se emita deberá notificarse al usuario, así como a las autoridades competentes, para los efectos legales a que haya lugar. Cuando la resolución resulte favorable a los intereses del usuario, no se generarán recargos o accesorios por el consumo o importe impugnado.\nARTICULO 63.- Cuando al practicarse una inspección se advierta que un aparato medidor presenta algún daño o alteración, o cuando el usuario del servicio no esté conforme con el consumo registrado en la factura o con el importe del mismo, en virtud del funcionamiento del aparato medidor, el Organismo encargado del servicio procederá a su retiro de considerarlo necesario.\nARTICULO 64.- Una vez retirado el aparato medidor, se tomarán las medidas necesarias a fin de que se conserve en el mismo estado, y se depositará en los talleres del\nLey que Reglamenta el Servicio de Agua Potable en el Estado de Baja California. Página 13 funcionamiento, cuando éstas sean necesarias.\nARTICULO 65.- Las pruebas relativas al funcionamiento de un aparato medidor, se harán con citación del usuario.\nOrganismo encargado del servicio mediante simple oficio, así como por el perito que en su caso designe el propio usuario.\nARTICULO 66.- Realizadas las pruebas se levantará acta en la que se hará una relación de las mismas y de los resultados obtenidos, en vista de los cuales los peritos del\nOrganismo encargado del servicio, dictaminarán si el medidor funciona correctamente y en caso contrario, describirán el daño o alteración que tenga, y si este fue causado de manera intencional, imprudencial o bien, por el desgaste natural producido por su uso, debiendo fijar en todo caso el monto por la reparación o sustitución del medidor. Enseguida se harán costar las observaciones que desee hacer el usuario, sus representantes o los peritos que les asesoren, si concurrieron, así como su opinión relativa a los puntos a que se refiere el dictamen oficial. Dicha acta será firmada por los que concurran al acto, y si el usuario o sus representantes y peritos no quisieren o no supieren firmar, se hará constar tal circunstancia, sin que ello afecte la validez del acto.\nARTICULO 67.- El monto de los daños causados a un aparato medidor, por alteración o cualquier otra causa, se determinará atendiendo al costo real de reparación o sustitución, mismo que será a cargo del Organismo encargado del servicio; a excepción en el caso de que se compruebe que el propietario o poseedor del inmueble en que se encontraba instalado haya sido el responsable de los daños causados; pudiendo ser cobrado a través del procedimiento administrativo de ejecución señalado en el Código Fiscal del Estado.\nSentencia de Acción de Inconstitucionalidad 119/2021 y su acumulada 128/2021\nARTICULO 68.- El acta que se levante sobre las pruebas relativas al funcionamiento de un aparato medidor, se agregará al expediente tramitado con motivo de visita de inspección o de la inconformidad a que se refiere el artículo 62 de esta Ley, la cual deberá tomarse en cuenta por el Titular del Organismo encargado del servicio, al momento de emitir la resolución que en su caso corresponda.\nARTICULO 69.- El Organismo encargado del servicio podrá estimar presuntivamente el pago de los derechos a que esta Ley se refiere, sin perjuicio de las sanciones correspondientes, cuando los usuarios:\nI. Impidan u obstaculicen a la autoridad competente la iniciación o desarrollo de sus facultades de inspección y verificación o medición;\nLey que Reglamenta el Servicio de Agua Potable en el Estado de Baja California. Página 14\nII. No proporcionen la documentación, informes o datos que se le soliciten o los presenten alterados, falsificados o existan vicios o irregularidades en los mismos;\nIII. Efectúen, encubran o consientan en que se lleven a cabo, sin contar con la autorización correspondiente, instalaciones a efecto de conectarse a las redes de agua potable, drenaje o alcantarillado sanitario;\nIV. Modifiquen las conexiones o instalaciones originalmente aprobadas sin contar con la autorización correspondiente;\nV. No tengan instalado medidor, en caso de estar obligados a ello por la presente ley;\nVI. Ocasionen o permitan la descompostura o mal funcionamiento de los medidores que cuantifican el suministro de agua potable;\nVII. No informen la descompostura o deterioro de los medidores dentro de los cinco días hábiles siguientes a que suceda la misma;\nVIII. Rompan o alteren los sellos del medidor;\nIX. Retiren el aparato medidor o varíen su colocación ya sea de manera provisional o definitiva;\nX. En general, realicen actos por medio de los cuales, usen, aprovechen o se beneficien de los servicios objeto de esta Ley, omitiendo el pago de los derechos que correspondan; y\nXI. Incurran en cualquier acto u omisión distintos de los enumerados en las fracciones que anteceden, que en alguna forma infrinjan las disposiciones de esta Ley, omitiendo lo que ordenen o haciendo lo que prohíban.\nARTICULO 70.- Para los efectos de la estimación presuntiva a que se refiere el artículo anterior, se utilizará el procedimiento que mejor se ajuste, siendo los siguientes:\nI.- Calcular la cantidad de agua que el usuario pudo obtener o aprovechar en forma diámetro de tubería utilizada para conectarse a la red de distribución;\nEn el supuesto de que el usuario no sea doméstico, el periodo por el cual se efectúe dictamen identifique que el usuario tuvo acceso al servicio, y en caso de que no fuere posible determinar fecha cierta, la estimación se realizará hasta por un máximo de 10 años o bien a partir de la fecha en que el usuario compruebe el inicio de operaciones.\nPárrafo Adicionado\nLey que Reglamenta el Servicio de Agua Potable en el Estado de Baja California. Página 15\nII.- Calcular la cantidad de agua residual que el usuario pudo descargar o desalojar en sanitario; y en el caso de las aguas residuales provenientes de las actividades productivas, también se tomara en cuenta el tipo de contaminación de las mismas;\nIII.- Calcular la cantidad de agua que el usuario pudo obtener, aprovechar o descargar, con la información obtenida mediante métodos y medidas técnicas establecidas por el Organismo encargado del servicio;\nIV.- Calcular la cantidad de agua que el usuario pudo descargar, con el volumen que señale el contrato de servicios o el permiso de descarga respectivo, de acuerdo a las características de sus instalaciones; y,\nV.- Calcular la cantidad de agua considerando la lectura mensual más alta reportada dentro de los últimos doce meses.\nArtículo Reformado\nARTICULO 71.- Los propietarios o poseedores de predios, giros y establecimientos donde se instalen aparatos medidores, serán responsables del cuidado de éstos.\nAsimismo los propietarios o poseedores de predios, giros o establecimientos en que se hallen instalados aparatos medidores, así como sus encargados u ocupantes, estarán obligados a hacer del conocimiento del Organismo encargado del servicio, todo daño o alteración causada al medidor.\nARTICULO 72.- Cuando por cualquier medio se tenga conocimiento que las instalaciones hidráulicas públicas presentan algún daño, o que funciona irregularmente, el\nOrganismo encargado del servicio procederá a repararlas, sustituirlas o bien, a realizar cualquier acción tendiente a regularizar su funcionamiento.\nTratándose de instalaciones hidráulicas de los usuarios estos estarán obligados a repararlas o sustituirlas a su costa.\nARTICULO 73.- Podrán practicarse inspecciones:\nI.- Para conocer si las instalaciones interiores de un predio, giro o establecimiento que reciba el servicio de agua potable y alcantarillado sanitario, funcionan adecuadamente, o se encargado del servicio;\nII.- Para comprobar si los medidores funcionan correctamente;\nIII.- Para verificar los diámetros de las tomas y demás información que obre en los registros del Organismo encargado del servicio; y, Ley que Reglamenta el Servicio de Agua Potable en el Estado de Baja California. Página 16\nIV.- Para investigar si se cumplen debidamente las disposiciones de esta Ley.\nARTICULO 74.- Los empleados del Organismo encargado del servicio que por ley deberán informarlo al propio Organismo, para que éste determine lo conducente.\nARTICULO 75.- Las inspecciones deberán ser practicadas por empleados del\nOrganismo encargado del servicio, debidamente autorizados.\nAntes de practicar una inspección y como requisito previo para llevarlo a cabo, los empleados autorizados por el Organismo deberán notificar la orden escrita en que se funde y motive.\nLa notificación deberá hacerse de manera personal en el domicilio en que haya de practicarse la inspección, o en el último domicilio que haya señalado la persona a quien deba notificarse, debiendo el empleado autorizado por el Organismo, identificarse con la credencial o documento que lo acredite con tal carácter. En caso de no encontrarse el usuario o su representante legal, el empleado autorizado por el Organismo encargado del servicio dejará citatorio con cualquier persona mayor de edad que se encuentre en el domicilio, para que lo espere el día hábil siguiente, a la hora que se señale en el citatorio. Si el domicilio se encontrare cerrado y nadie respondiere al llamado del empleado autorizado por el Organismo encargado del servicio, se dejará el citatorio con el vecino más cercano.\nARTICULO 76.- De la entrega del citatorio se levantará constancia que deberá ser firmada por el empleado autorizado por el Organismo encargado del servicio y por la persona con quien se entienda la diligencia, si esta se niega o no supiere hacerlo, se asentará tal circunstancia, sin que ello afecte su validez.\nARTICULO 77.- Si la persona a quien haya de notificarse no atiende el citatorio, la notificación se le hará por conducto de cualquier persona mayor de edad que se encuentre en el domicilio en que se realice la diligencia, y de negarse ésta a recibirla o de no encontrarse persona alguna, la notificación se practicará por instructivo que se fijará en la puerta del domicilio o en lugar visible del mismo, en presencia de dos testigos o de la fuerza pública.\nEn todos los casos, el empleado autorizado por el Organismo encargado del servicio deberá levantar constancia de la diligencia de notificación.\nARTICULO 78.- Con excepción de la notificación de la orden de inspección, y si no se encuentra en el domicilio al interesado o su representante legal, las ulteriores notificaciones, aun las de carácter personal, serán practicadas sin necesidad de que se entregue citatorio, con cualquier persona que se encuentre en el domicilio, y de negarse ésta a recibirla, se realizará por instructivo que se fijará en la puerta del domicilio o en lugar visible del mismo.\nLey que Reglamenta el Servicio de Agua Potable en el Estado de Baja California. Página 17\nARTICULO 79.- Una vez realizada la notificación, se procederá a practicar la inspección.\nARTICULO 80.- En caso de que no pudiera practicarse la inspección por negarse las personas que se encuentren en el domicilio, el empleado autorizado levantará razón de tal circunstancia, informando al Organismo encargado del servicio a efecto de que proceda legalmente ante la autoridad competente o facultada de dicho ente administrativo, para que funde y motive la causa legal del procedimiento a efecto de llevar a cabo el acto de inspección que en derecho corresponda.\nARTICULO 81.- En la práctica de una visita de inspección, las autoridades municipales y estatales de seguridad pública estarán obligadas a prestar el auxilio que se les requiera.\nARTICULO 82.- En la orden de visita se expresará, con toda claridad, el objeto de la inspección, el lugar en que deba practicarse y las causas por las que se mande llevar a cabo, así como los fundamentos legales del procedimiento.\nARTICULO 83.- Las visitas se limitarán exclusivamente al objeto indicado en la orden respectiva y por ningún motivo podrá extenderse a objetos distintos, aún cuando se relacionen con los servicios de agua potable y alcantarillado sanitario, salvo el caso de que, en el momento de la visita, se descubra accidentalmente una infracción a las disposiciones de la Ley, en cuyo caso el inspector se limitará a hacerlo constar en el acta correspondiente.\nARTICULO 84.- En los casos en que tengan que fracturarse cerraduras para la práctica de visitas, terminadas éstas, volverán a asegurarse las puertas convenientemente.\nARTICULO 85.- De toda visita de inspección se levantará acta por triplicado, en la que se hará constar:\nI.- Fecha en que se practique la visita;\nII.- Ubicación del predio, giro o establecimiento en que se lleve a cabo;\nIII.- Nombre y domicilio del propietario o poseedor del predio, giro o establecimiento y nombre comercial de éste si lo tiene;\nIV.- Nombres y domicilios de las personas con quienes se entienda la visita;\nV.- Nombres y domicilios de los testigos, en caso de haberse designado;\nVI.- Objeto de la visita;\nVII.- Desarrollo de la visita; y\nVIII.- Lo que el interesado exponga en su caso, con relación a la visita.\nLey que Reglamenta el Servicio de Agua Potable en el Estado de Baja California. Página 18 infractores.\nARTICULO 86.- Para la mejor comprensión del desarrollo de la inspección, el empleado autorizado por el Organismo encargado del servicio agregará al acta, cuando así lo estime conveniente, una descripción gráfica del lugar en que se lleve a cabo.\nARTICULO 87.- Al inicio de una inspección, el empleado autorizado por el Organismo encargado del servicio hará saber a la persona con quien la entienda, que deberá designar a dos testigos que presencien el desarrollo de la misma.\nEn caso de que la persona con quien se entienda la visita no designare testigos, o que habiéndolo hecho alguno de ellos o ambos se nieguen a fungir como tal, o no se encuentren presentes al momento de practicarse la visita, se continuará con el desarrollo de la misma, sin que ello afecte su validez, debiendo asentarse tal circunstancia en el acta.\nARTICULO 88.- La persona con quien se entienda la visita y los testigos que en su caso se hubieren designado, deberán firmar el acta que al efecto levante el empleado autorizado por el Organismo encargado del servicio. En caso de que se negaren o no supieren hacerlo, se asentará tal circunstancia en el acta, sin que ello afecte su validez.\nEl empleado autorizado por el Organismo encargado del servicio deberá, en todo caso, firmar el acta respectiva, entregando una copia de la misma a la persona con quien haya entendido la visita de inspección.\nARTICULO 89.- El acta de visita de inspección hace prueba plena respecto de los hechos u omisiones consignados en la misma.\nARTICULO 90.- Se considerarán infractores, aún cuando no sean quienes hayan practicado o mandado practicar las derivaciones a que se hace mención en la Fracción I del\nArtículo 95 a los que al tomar posesión de un predio, giro o establecimiento, no cumplan con lo que proviene el Artículo 53 de esta Ley.\nIgualmente se considerarán infractores a los que, al entrar en posesión de un predio, giro o establecimiento, sigan proporcionando o recibiendo el servicio de agua potable en la forma prevista en la Fracción II del artículo 94.\nARTICULO 91.- De toda acta de inspección se remitirá un ejemplar al Titular del\nOrganismo encargado del servicio, para efecto de que determine lo conducente, aplicando en su caso, las sanciones pecuniarias y administrativas que correspondan, así como las demás previstas en la legislación fiscal del Estado de Baja California. Dichas sanciones se\nFiscal del Estado.\nLey que Reglamenta el Servicio de Agua Potable en el Estado de Baja California. Página 19\nLa resolución que en su caso se emita deberá notificarse al usuario, así como a las autoridades competentes, para los efectos legales a que haya lugar.\nSentencia de Acción de Inconstitucionalidad 119/2021 y su acumulada 128/2021\nDE LAS SANCIONES\nARTICULO 92.- A los que debiendo contar con los servicios de agua potable y alcantarillado sanitario, no los soliciten dentro del plazo que fija el artículo 5, fracciones II y III de esta Ley, o impidan su instalación, se les impondrá una multa de 20 a 40 UMA diarias vigentes.\nArtículo Reformado\nARTICULO 93.- Cuando ni el propietario de un giro, ni el del predio en que esté establecido, cumplan con la obligación que señala el Artículo 30, pero el Organismo encargado del servicio tenga conocimiento por cualquier otro medio de la clausura, del traspaso o traslado del giro, ordenará cuando proceda, la supresión de la toma así como las anotaciones correspondientes en el registro y padrón, sin perjuicio de que se impongan las sanciones respectivas.\nARTICULO 94.- Se impondrán las siguientes multas:\nI.- A los que practiquen o manden practicar derivaciones de las tuberías generales de distribución, de los ramales de éstas o de las cajas de válvulas, para surtir de agua a un predio o establecimiento, sin apegarse a lo dispuesto en esta Ley:\na) Si la derivación se utiliza para una toma de uso doméstico, multa de 10 a 100 UMA diarias vigentes;\nInciso Reformado\nb) Si la derivación se destina a una toma de uso comercial, industrial u otro que implique lucro, multa de 100 a 500 UMA diarias vigentes.\nInciso Reformado\nII.- A los que, contraviniendo lo dispuesto en el Artículo 6°, practiquen, manden practicar o consientan que se lleven a cabo en forma provisional o permanente, sin la autorización del Organismo encargado del servicio derivaciones de agua:\na) De un predio con toma doméstica a otro u otros con tomas semejantes, multa de 10 a 20 UMA diarias vigentes;\nInciso Reformado\nLey que Reglamenta el Servicio de Agua Potable en el Estado de Baja California. Página 20\nb) De un predio con toma doméstica a otro u otros, con tomas de uso comercial o industrial, si los establecimientos están obligados a tener un sistema especial, conforme a lo dispuesto en la fracción II del artículo 3, multa de 100 a 500 UMA diarias vigentes;\nInciso Reformado\nc) De una toma comercial o industrial a otro u otros establecimientos con tomas de la misma índole, ya sea que estén en el mismo predio u otros predios, multa de 50 a 200 UMA diarias vigentes, y\nInciso Reformado\nd) De una toma comercial o industrial a un predio al que corresponde una toma doméstica, multa de 20 a 100 UMA diarias vigentes. Cuando la derivación de agua a otros predios se haga a título oneroso, la multa podrá duplicarse.\nInciso Reformado\nExistirá infracción al Artículo 6° en los casos a que se refieren los incisos a), b), c), y\nd) de esta Fracción, aún cuando los predios, giros o establecimientos que reciban el servicio de agua como consecuencia de las derivaciones, sean del mismo propietario que aquellos de donde parten dichas derivaciones, y no obstante que el consumo se registre por el aparato medidor.\nIII.- A los que, en cualquiera forma distinta de las señaladas en las dos fracciones anteriores, proporcionen servicio de agua permanente, ya sea a título gratuito u oneroso, a los propietarios, poseedores u ocupantes por cualquier concepto, de predios, giros y establecimientos que conforme a las disposiciones de esta Ley, están obligados a surtirse de agua del servicio público:\na) Si se hace a título gratuito, multa de 5 a 10 UMA diarias vigentes, y\nInciso Reformado\nb) Si se hace a título oneroso, multa de 20 a 100 UMA diarias vigentes.\nInciso Reformado\nIV.- Asimismo en los siguientes casos:\na) A quienes impidan que los empleados del Organismo encargado del servicio, autorizados y debidamente identificados, el examen de los aparatos medidores para la toma de lectura del consumo de agua, multa de 40 a 200 UMA diarias vigentes. En caso de reincidencia, la multa podrá duplicarse;\nInciso Reformado\nb) A quien cause daño intencional a un aparato medidor multa de 40 a 200 UMA diarias vigentes. En caso de reincidencia, la multa podrá duplicarse;\nLey que Reglamenta el Servicio de Agua Potable en el Estado de Baja California. Página 21\nInciso Reformado\nc) A quien viole los sellos de un aparato medidor, multa de 40 a 200 UMA diarias vigentes. En caso de reincidencia, la multa podrá duplicarse;\nInciso Reformado\nd) Al que, por cualquier medio, altere el consumo marcado en los medidores, multa de\n40 a 200 UMA diarias vigentes. En caso de reincidencia, la multa podrá duplicarse;\nInciso Reformado\ne) Al que, por cualquier medio, haga que el aparato medidor no registre el consumo; multa de 40 a 200 UMA diarias vigentes. En caso de reincidencia, la multa podrá duplicarse;\nInciso Reformado\nf) Al que por sí o por medio de otro sin estar legalmente autorizado para hacerlo, retire transitoria o definitivamente un medidor, por cualquier causa, varíe su colocación o lo cambie de lugar, multa de 20 a 100 UMA diarias vigentes. Si retira el medidor de manera definitiva o por más de 15 días, la multa podrá duplicarse;\nInciso Reformado\ng) Al que, personalmente o valiéndose de otro, cambie de lugar o haga modificaciones o manipulaciones en cualquier forma a los ramales de las tuberías de distribución comprendidos entre la llave de inserción y la llave de retención interior del predio o establecimiento, colocada después del aparato medidor, 20 a 100 UMA diarias vigentes;\nInciso Reformado\nh) A los propietarios, encargados o arrendatarios de predios, giros o establecimientos, o sus familiares, allegados o dependientes o cualquier otra persona que se encuentre en ellos, por no permitir la inspección de instalaciones interiores, a los empleados autorizados y debidamente identificados del Organismo encargado del servicio, multa de 20 a 100 UMA diarias vigentes;\nInciso Reformado\ni) A los que se nieguen a proporcionar, sin causa justificada, los informes que el\nOrganismo encargado del servicio les pida en relación con el servicio de agua potable, multa de 10 a 20 UMA diarias vigentes;\nInciso Reformado\nj) A los funcionarios o empleados que concedan licencia para construcciones, sin que predio en que vaya a construirse, multa de 20 a 50 UMA diarias vigentes;\nInciso Reformado\nLey que Reglamenta el Servicio de Agua Potable en el Estado de Baja California. Página 22\nk) Al que, por emplear mecanismos para succionar agua de las tuberías de distribución, ocasione o no deficiencias en el servicio o daños en las instalaciones, multa de\n20 a 100 UMA diarias vigentes;\nInciso Reformado\nl) A los notarios que autoricen contratos relativos a bienes inmuebles, contraviniendo lo que dispone el artículo 104, multa de 50 a 100 UMA diarias vigentes;\nInciso Reformado\nm) A los funcionarios o empleados que inscriban en el Registro Público de la\nPropiedad y de Comercio, algún contrato de los mencionados en el artículo 105 sin que se cumpla la condición que el mismo establece, multa de 20 a 50 UMA diarias vigentes;\nInciso Reformado\nn) A los funcionarios o empleados que autoricen el traspaso o traslado de giros mercantiles o industriales, sin que cumplan con lo que preceptúa el artículo 106, multa de 20 a 50 UMA diarias vigentes;\nInciso Reformado\no) A los que cometan cualquier otra infracción a las disposiciones de esta Ley, no especificada en las fracciones que anteceden, multa de 20 a 100 UMA diarias vigentes.\nInciso Reformado\nV. A quienes teniendo servicio de agua de uso doméstico lo destinen para uso comercial, industrial o cualquier otro no doméstico, multa de 50 a 200 UMA diarias vigentes, sin perjuicio de que el Organismo encargado del servicio efectúe el registro del uso que corresponda.\nFracción Reformada\nArtículo Reformado\nARTICULO 95.- En los casos de las fracciones I y II del artículo 94 además de las sanciones que en dicho artículo se establecen, los propietarios o poseedores de los predios que hayan recibido el servicio de agua potable como consecuencia de esas infracciones, están obligados:\nI.- A cubrir el importe de los derechos causados por el servicio de agua potable conforme a las tarifas aplicables, a partir de la fecha en que hubieren practicado la derivación. Si no es posible precisar esa fecha, se cobrarán los derechos correspondientes a partir de la fecha de su apertura, o bien, a cinco años anteriores al descubrimiento de la domésticos;\nFracción Reformada\nLey que Reglamenta el Servicio de Agua Potable en el Estado de Baja California. Página 23\nII.- A solicitar la instalación de la toma correspondiente de acuerdo con las prevenciones de esta Ley, si existe el servicio, dentro de los diez días siguientes al descubrimiento de la infracción.\nArtículo Reformado\nARTICULO 96.- Tratándose de giros mercantiles o industriales, se podrá ordenar la clausura del negocio o la suspensión del servicio de agua:\nI.- Por falta de cumplimiento a lo que dispone el artículo 49.\nII.- Por no cubrir o garantizar, por medio de depósito o fianza, dentro del término de treinta días contados a partir de la fecha de la notificación respectiva, el importe de las sanciones pecuniarias que establece esta Ley;\nIII.- Por falta de pago de las cuotas por servicio de agua por un mes o más.\nFracción Reformada\nIV.- De manera inmediata, cuando intencionalmente el propietario del giro, se suministre el servicio de agua potable sin autorización del Organismo, mediante toma directa o derivación o cuando dolosamente retire, manipule, destruya o altere el medidor que determina la facturación del consumo de agua o retire cualquier aditamento instalado para el control del suministro del agua potable.\nFracción Reformada\nV.- Por falta de pago de derechos de conexión al sistema de agua potable y alcantarillado sanitario en los términos de la legislación fiscal aplicable.\nFracción Adicionada\nVI.- Por falta de pago por las obras de introducción de las redes de agua potable y alcantarillado sanitario en los términos de las disposiciones fiscales y hacendarias.\nFracción Adicionada\nCuando el usuario impida por cualquier medio la toma de la lectura, las comisiones podrán solicitar y hacerse acompañar de la fuerza pública. En el caso de que para la toma vía pública para llegar a la toma, éstas podrán realizarlas sin la autorización previa de los municipios, debiendo de informar al municipio al término de éstas, mediante escrito debidamente fundado y motivado sobre las acciones realizadas en la vía pública. En estos pública afectada.\nPárrafo Reformado\nArtículo Reformado\nLey que Reglamenta el Servicio de Agua Potable en el Estado de Baja California. Página 24\nARTICULO 97.- Cuando no se cumpla con las obligaciones señaladas en la fracción\nIII del artículo 5° de esta Ley, las autoridades competentes deberán, a solicitud del\nOrganismo encargo del servicio, ordenar la suspensión de las construcciones, hasta que se instale la toma correspondiente.\nARTICULO 98.- Las sanciones que correspondan de acuerdo con el Artículo 94, se impondrán cuando se comprueben las infracciones.\nARTICULO 99.- Las sanciones pecuniarias que se impongan de acuerdo con lo que dispone esta Ley, deberán ser cubiertas dentro del término de 15 días, contados a partir de la fecha en que sean notificadas a los responsables las resoluciones respectivas. Pasado dicho término sin que sean cubiertas, se exigirá su pago por medio de la facultad económico-coactiva.\nARTICULO 100.- Cuando los hechos que infrinjan las disposiciones de esta Ley pudieran ser constitutivos de delito, se harán del conocimiento de la autoridad competente, sin perjuicio de aplicar las sanciones pecuniarias y administrativas que procedan.\nDISPOSICIONES GENERALES\nARTICULO 101.- Para los efectos de esta Ley, se aplicará supletoriamente la Ley del\nProcedimiento para los Actos de la Administración Pública del Estado de Baja California.\nSentencia de Acción de Inconstitucionalidad 119/2021 y su acumulada 128/2021\nARTICULO 102.- Los Notarios no podrán autorizar ningún contrato de compra venta, hipoteca o cualquier otro relativo a bienes inmuebles, sin que previamente los interesados comprueben estar al corriente en el pago de los derechos por servicio de agua y obras de cooperación relativas al predio objeto del contrato.\nARTICULO 103.- El Organismo encargado del servicio podrá facultar el otorgamiento de escrituras, aún cuando exista adeudo de derechos por servicios de agua, siempre que su pago se garantice previamente por medio de depósito.\nARTICULO 104.- Al celebrarse los contratos a que se refiere el Artículo 102 de esta\nLey, los interesados deberán acreditar ante el Notario con los certificados respectivos, estar contrato o en su caso, que no existe el servicio.\nARTICULO 105.- No deberá inscribirse en el Registro Público de la Propiedad, ningún los mismos, mientras no se acredite estar al corriente en el pago de los derechos por servicio de agua, y de las obras de cooperación que graven dichos bienes.\nLey que Reglamenta el Servicio de Agua Potable en el Estado de Baja California. Página 25\nEl Organismo encargado del servicio, podrá autorizar la inscripción aún cuando exista adeudo de derechos por servicio de agua, siempre que su pago se garantice previamente por medio de depósito.\nARTICULO 106.- Las oficinas fiscales no autorizarán el traspaso o traslado de giros mercantiles e industriales, sin que previamente se compruebe estar al corriente en el pago de los derechos relativos al servicio de agua correspondiente a esos giros y obras de cooperación, salvo que se hayan garantizado dichos pagos por medio de depósito.\nARTICULO 107.- En los casos en que esta Ley no señale el término para el cumplimiento de las obligaciones que establece en materia de agua, tales obligaciones deberán cumplirse dentro del término de treinta días.\nARTICULO 108.- Contra los actos de las autoridades que se originen con motivo de la aplicación de esta Ley, los interesados podrán recurrir en los términos que señala el Código\nFiscal del Estado de Baja California.\nEn materia de prescripción y cancelación de créditos, se estará a lo dispuesto por la legislación fiscal del Estado y demás disposiciones aplicables.\nSentencia de Acción de Inconstitucionalidad 119/2021 y su acumulada 128/2021\nDEL TRATAMIENTO DE AGUAS RESIDUALES Y SU REÚSO\nARTICULO 109.- Corresponde a la Secretaría para el Manejo, Saneamiento y\nProtección del Agua en coordinación con los Organismos encargados del servicio:\nPárrafo Reformado\nI.- Vigilar el cumplimiento de las Normas Oficiales Mexicanas vigentes para regular las descargas de aguas residuales en los sistemas de drenaje y alcantarillado en el Estado, y en su caso, aplicar las sanciones establecidas en esta Ley en los siguientes supuestos:\na).- Por daños a la infraestructura de los sistemas de alcantarillado;\nb).- Por azolves en tuberías y cárcamos;\nc).- Por el vertido de contaminantes por arriba de los límites permisibles requeridos por la Norma Oficial Mexicana aplicable; y\nd).- Por afectación del proceso de depuración en las plantas de tratamiento que operan los Organismos.\nII. Establecer los criterios técnicos, reglas y procedimientos para el control y la alcantarillado, con base en las Normas Oficiales Mexicanas y las normas ambientales del\nEstado;\nLey que Reglamenta el Servicio de Agua Potable en el Estado de Baja California. Página 26\nIII. Vigilar el cumplimiento de las disposiciones en materia de calidad de las descargas de aguas residuales;\nIV. Monitorear la calidad de las aguas tratadas;\nV. Revisar y aprobar los proyectos de los sistemas de tratamiento de aguas residuales públicos y privados;\nVI. Establecer y vigilar las condiciones específicas de operación de los sistemas de pretratamiento y tratamiento para asegurar el cumplimiento en la remoción y reducción de la concentración de contaminantes previo a su descarga;\nVII. Otorgar los permisos de descarga de aguas residuales provenientes de usuarios no domésticos, y en su caso constancias de cumplimiento acorde a la normatividad aplicable,\nVIII. Revisar los proyectos de las obras de los sistemas de tratamiento que se pretenden construir por parte de los particulares, que descarguen a los sistemas de drenaje y, en su caso, recomendar las modificaciones que se estimen convenientes, y,\nIX. Las que expresamente se le otorguen por esta Ley y demás disposiciones que resulten aplicables.\nArtículo Reformado\nARTICULO 110.- Corresponde a los Organismos encargados del servicio realizar el tratamiento de aguas residuales, así como a los particulares en los términos previstos en la presente Ley. El tratamiento de aguas residuales deberá cumplir con las disposiciones contenidas en las Normas Oficiales Mexicanas y las normas ambientales del Estado.\nARTÍCULO 111.- Los Organismos encargados del servicio llevarán un inventario de las descargas de aguas residuales que se vierten al sistema de drenaje, así como los permisos de descarga que en su caso otorguen.\nARTÍCULO 112.- Corresponde a los usuarios no domésticos que efectúen descargas de aguas residuales a los sistemas de drenaje y alcantarillado, cumplir con lo estipulado en las Normas Oficiales Mexicanas correspondientes, con las normas ambientales del Estado y servicio.\nARTÍCULO 113.- Se prohíbe descargar a los sistemas de drenaje y alcantarillado, ríos, manantiales, arroyos, corrientes, colectores o canales localizados en el territorio del\nEstado, desechos tóxicos, sólidos o líquidos, productos de procesos industriales u otros aplicables.\nLey que Reglamenta el Servicio de Agua Potable en el Estado de Baja California. Página 27\nARTÍCULO 114.- Cuando los usuarios no domésticos contravengan lo dispuesto en el artículo anterior, o efectúen descargas de aguas residuales a los sistemas de drenaje y alcantarillado, sin cumplir con lo estipulado en esta ley, en las Normas Oficiales Mexicanas correspondientes, con las normas ambientales del Estado o condiciones particulares de descarga, podrán optar por un tratamiento conjunto con el Organismo operador con cargo al usuario de los costos que deriven de ello hasta en tanto los usuarios instalen el sistema de tratamiento para el cumplimiento de la ley en la materia.\nARTÍCULO 115.- En los sistemas de tratamiento de aguas residuales particulares, invariablemente se deberán considerar y realizar los proyectos para el manejo y disposición final de lodos, en los términos de las disposiciones respectivas. Asimismo, se deberán construir las trampas de sólidos y las desnatadoras de grasas que se requieran para cumplir con las condiciones especiales de descarga que determine el Organismo prestador del servicio.\nARTÍCULO 116.- La Secretaría para el Manejo, Saneamiento y Protección del Agua en coordinación con los Organismos encargados del servicio, promoverán el ahorro y el uso eficiente del agua potable, así como el reúso de las aguas residuales procedentes de las plantas de tratamiento si su calidad así lo permite de acuerdo con la normatividad aplicable.\nArtículo Reformado\nARTÍCULO 117.- La Secretaría para el Manejo, Saneamiento y Protección del Agua en coordinación con los Organismos encargados del servicio vigilarán que el reúso de las aguas se ajuste a los términos establecidos en las Normas Oficiales Mexicanas, las normas ambientales del Estado y demás disposiciones que resulten aplicables.\nArtículo Reformado\nARTÍCULO 118.- Se impulsarán medidas que incentiven, principalmente a los usuarios no domésticos, a desarrollar infraestructura que permita el tratamiento de aguas residuales y su reúso.\nARTÍCULO 119.- Los Organismos encargados del servicio, desarrollarán infraestructura que permita el aprovechamiento de las aguas residuales tratadas, donde así se justifique técnica, económica y ambientalmente.\nARTÍCULO 120.- Se impulsarán medidas que incentiven a los desarrolladores de vivienda y/o fraccionadores, para crear la infraestructura necesaria con el objeto de que en las áreas verdes y demás actividades que resulten procedentes, se reúsen aguas provenientes de uso doméstico en los términos que establezca la normatividad aplicable.\nLey que Reglamenta el Servicio de Agua Potable en el Estado de Baja California. Página 28\nARTÍCULO 121.- Es obligatorio utilizar agua residual tratada, donde exista la establecidos por las Normas Oficiales Mexicanas aplicables, en los casos siguientes:\nI.- Para las actividades de limpieza de instalaciones, parque vehicular y en los establecimientos industriales, comerciales y de servicios, así como en las instalaciones del sector público, para el riego de áreas verdes públicas;\nII.- Para los sistemas industriales de enfriamiento, lavado y procesos productivos que no requieran necesariamente agua potable, conforme a las normas y especificaciones técnicas aplicables;\nIII.- Para las obras en construcciones, así como para la construcción de terracerías y la compactación de suelos;\nIV.- Para el lavado de vehículos a nivel comercial;\nV.- Para la agricultura;\nVI.- Para hidrantes contra incendios;\nVII.- Para fuentes públicas de ornato;\nVIII.- Áreas verdes de campos deportivos;\nIX.- Riego de terrenos particulares;\nX.- En la industria, en edificios corporativos, escuelas públicas y privadas y en oficinas públicas y privadas y giros mercantiles: se deberá utilizar agua residual tratada para la limpieza y aseo de áreas de servicios, en mingitorios y muebles sanitarios; y\nXI.- En los demás casos previstos en este y en otras disposiciones aplicables.\nDE LOS ORGANISMOS ENCARGADOS DEL SERVICIO\nSentencia de Acción de Inconstitucionalidad 119/2021 y su acumulada 128/2021\nARTÍCULO 122.- Para la prestación de los servicios públicos de agua potable, drenaje, alcantarillado, tratamiento y disposición final de sus aguas residuales, a que se refiere la presente Ley, los Municipios contarán con Organismos paramunicipales con personalidad jurídica y patrimonio propios, así como autonomía técnica y administrativa, con las atribuciones que establece esta Ley, los ordenamientos municipales y sus instrumentos de creación. comprobados en el manejo y administración de sistemas de agua o hídricos, y será\nLey que Reglamenta el Servicio de Agua Potable en el Estado de Baja California. Página 29 propuesta del Presidente Municipal\nSentencia de Acción de Inconstitucionalidad 119/2021 y su acumulada 128/2021\nARTÍCULO 123.- Serán atribuciones de los Organismos encargados del servicio de agua:\nI. Todo lo relativo al cumplimiento y realización de los sistemas de agua potable, alcantarillado y tratamiento de aguas negras de cada uno de los Municipios a que correspondan;\nII. La ejecución directa o por contratación de las obras a que se refieren dichos sistemas;\nIII. La operación y mantenimiento de los sistemas de que se trata;\nIV. La prestación a los usuarios de los servicios mencionados;\nV. La determinación de créditos fiscales y recaudación de los derechos, aprovechamientos y contribuciones de mejoras que conforme a las Leyes aplicables y a los\nConvenios que celebren, les correspondan;\nVI. La implementación de programas de apoyo a los usuarios para el financiamiento en la adquisición de tecnologías, así como aditamentos y dispositivos ahorradores de agua;\nVII. El desarrollo de actividades que directa o indirectamente conduzcan a lograr los objetivos indicados,\nVIII. Las demás previstas en la presente Ley, así como en sus instrumentos de creación y demás disposiciones aplicables.\nSentencia de Acción de Inconstitucionalidad 119/2021 y su acumulada 128/2021\nARTÍCULO 124.- Los Municipios, podrán coordinarse y asociarse para la más eficaz prestación de los servicios a que se refiere esta Ley.\nSentencia de Acción de Inconstitucionalidad 119/2021 y su acumulada 128/2021\nARTÍCULOS TRANSITORIOS\nPRIMERO.- Se abroga la Ley del Agua para el Estado de Baja California, publicada el\nSEGUNDO.- El presente Decreto mediante el que se expide la Ley que Reglamenta el\nServicio del Agua Potable en el Estado de Baja California, entrará en vigor el día de su publicación en el Periódico Oficial del Estado.\nLey que Reglamenta el Servicio de Agua Potable en el Estado de Baja California. Página 30\nTERCERO.- El Ejecutivo del Estado, por conducto de sus dependencias y entidades, presente. del Estado de Baja California, en la Ciudad de Mexicali, B.C., a los diecinueve días del mes de enero del año dos mil diecisiete.\nDIP. MTRO. RAÚL CASTAÑEDA POMPOSO\nPRESIDENTE\n(RÚBRICA)\nDIP. MARCO A. CORONA BOLAÑOS CACHO\nSECRETARIO\n(RÚBRICA)\nDE CONFORMIDAD CON LO DISPUESTO POR LA FRACCION I DEL ARTÍCULO 49\nMEXICALI, BAJA CALIFORNIA, A LOS DIECINUEVE DÍAS DEL MES DE ENERO\nDEL AÑO DOS MIL SIETE.\nFRANCISCO ARTURO VEGA DE LAMADRID\nGOBERNADOR DEL ESTADO\n(RÚBRICA)\nFRANCISCO RUEDA\nSECRETARIO GENERAL DE GOBIERNO\n(RUBRICA)\nLey que Reglamenta el Servicio de Agua Potable en el Estado de Baja California. Página 31\nARTÍCULO 1.- Fue reformado mediante Decreto No. 289, publicado en el Periódico la H. XXIII Legislatura, siendo Gobernador Constitucional el C. Jaime Bonilla Valdez 2019 –\n2021; mediante Sentencia de Acción de Inconstitucionalidad 119/2021 y su acumulada en los Términos de su Resolutivo Tercero, se declara la invalidez del Decreto No. 289, publicado en el Periódico Oficial No. 52, Número Especial, de fecha 29 de julio de 2022, Tomo CXXVIII, expedido por la H. XXIII Legislatura, siendo Gobernador Constitucional el C.\nJaime Bonilla Valdez 2019 – 2021;\nARTÍCULO 2.- Fue reformado mediante Decreto No. 51, publicado en el Periódico\nOficial No. 16, de fecha 20 de marzo de 2020, Sección III, Tomo CXXVII, expedido por la H.\nXXIII Legislatura, siendo Gobernador Constitucional el C. Jaime Bonilla Valdez 2019 – 2021;\nARTÍCULO 14.- Fue reformado mediante Decreto No. 289, publicado en el Periódico\nOficial No. 52, de fecha 29 de julio de 2021, Número Especial, Tomo CXXVIII, expedido por la H. XXIII Legislatura, siendo Gobernador Constitucional el C. Jaime Bonilla Valdez 2019 –\n2021; mediante Sentencia de Acción de Inconstitucionalidad 119/2021 y su acumulada\n128/2021, notificada al Congreso del Estado de Baja California el día 17 de agosto de 2022, en los Términos de su Resolutivo Tercero, se declara la invalidez del Decreto No. 289, publicado en el Periódico Oficial No. 52, Número Especial, de fecha 29 de julio de 2022, Tomo CXXVIII, expedido por la H. XXIII Legislatura, siendo Gobernador Constitucional el C.\nJaime Bonilla Valdez 2019 – 2021;\nARTÍCULO 15.- Fue reformado mediante Decreto No. 289, publicado en el Periódico\nOficial No. 52, de fecha 29 de julio de 2021, Número Especial, Tomo CXXVIII, expedido por la H. XXIII Legislatura, siendo Gobernador Constitucional el C. Jaime Bonilla Valdez 2019 –\n2021; mediante Sentencia de Acción de Inconstitucionalidad 119/2021 y su acumulada\n128/2021, notificada al Congreso del Estado de Baja California el día 17 de agosto de 2022, en los Términos de su Resolutivo Tercero, se declara la invalidez del Decreto No. 289, Tomo CXXVIII, expedido por la H. XXIII Legislatura, siendo Gobernador Constitucional el C.\nJaime Bonilla Valdez 2019 – 2021;\nARTÍCULO 17.- Fue reformado mediante Decreto No. 51, publicado en el Periódico\nXXIII Legislatura, siendo Gobernador Constitucional el C. Jaime Bonilla Valdez 2019 – 2021; fue reformado mediante Decreto No. 289, publicado en el Periódico Oficial No. 52, de fecha siendo Gobernador Constitucional el C. Jaime Bonilla Valdez 2019 – 2021; mediante\nLey que Reglamenta el Servicio de Agua Potable en el Estado de Baja California. Página 32\nSentencia de Acción de Inconstitucionalidad 119/2021 y su acumulada 128/2021, notificada su Resolutivo Tercero, se declara la invalidez del Decreto No. 289, publicado en el Periódico la H. XXIII Legislatura, siendo Gobernador Constitucional el C. Jaime Bonilla Valdez 2019 –\n2021;\nARTÍCULO 19.- Fue reformado mediante Decreto No. 289, publicado en el Periódico\nOficial No. 52, de fecha 29 de julio de 2021, Número Especial, Tomo CXXVIII, expedido por la H. XXIII Legislatura, siendo Gobernador Constitucional el C. Jaime Bonilla Valdez 2019 –\n2021; mediante Sentencia de Acción de Inconstitucionalidad 119/2021 y su acumulada\n128/2021, notificada al Congreso del Estado de Baja California el día 17 de agosto de 2022, en los Términos de su Resolutivo Tercero, se declara la invalidez del Decreto No. 289, publicado en el Periódico Oficial No. 52, Número Especial, de fecha 29 de julio de 2022, Tomo CXXVIII, expedido por la H. XXIII Legislatura, siendo Gobernador Constitucional el C.\nJaime Bonilla Valdez 2019 – 2021;\nARTÍCULO 20.- Fue reformado mediante Decreto No. 289, publicado en el Periódico\nOficial No. 52, de fecha 29 de julio de 2021, Número Especial, Tomo CXXVIII, expedido por la H. XXIII Legislatura, siendo Gobernador Constitucional el C. Jaime Bonilla Valdez 2019 –\n2021; mediante Sentencia de Acción de Inconstitucionalidad 119/2021 y su acumulada\n128/2021, notificada al Congreso del Estado de Baja California el día 17 de agosto de 2022, en los Términos de su Resolutivo Tercero, se declara la invalidez del Decreto No. 289, publicado en el Periódico Oficial No. 52, Número Especial, de fecha 29 de julio de 2022, Tomo CXXVIII, expedido por la H. XXIII Legislatura, siendo Gobernador Constitucional el C.\nJaime Bonilla Valdez 2019 – 2021;\nARTÍCULO 52.- Fue reformado mediante Decreto No. 289, publicado en el Periódico\nOficial No. 52, de fecha 29 de julio de 2021, Número Especial, Tomo CXXVIII, expedido por la H. XXIII Legislatura, siendo Gobernador Constitucional el C. Jaime Bonilla Valdez 2019 –\n2021; mediante Sentencia de Acción de Inconstitucionalidad 119/2021 y su acumulada en los Términos de su Resolutivo Tercero, se declara la invalidez del Decreto No. 289, Tomo CXXVIII, expedido por la H. XXIII Legislatura, siendo Gobernador Constitucional el C.\nJaime Bonilla Valdez 2019 – 2021;\nARTÍCULO 57.- Fue reformado mediante Decreto No. 289, publicado en el Periódico la H. XXIII Legislatura, siendo Gobernador Constitucional el C. Jaime Bonilla Valdez 2019 –\nLey que Reglamenta el Servicio de Agua Potable en el Estado de Baja California. Página 33\n2021; mediante Sentencia de Acción de Inconstitucionalidad 119/2021 y su acumulada en los Términos de su Resolutivo Tercero, se declara la invalidez del Decreto No. 289, Tomo CXXVIII, expedido por la H. XXIII Legislatura, siendo Gobernador Constitucional el C.\nJaime Bonilla Valdez 2019 – 2021;\nARTÍCULO 67.- Fue reformado mediante Decreto No. 289, publicado en el Periódico\nOficial No. 52, de fecha 29 de julio de 2021, Número Especial, Tomo CXXVIII, expedido por la H. XXIII Legislatura, siendo Gobernador Constitucional el C. Jaime Bonilla Valdez 2019 –\n2021; mediante Sentencia de Acción de Inconstitucionalidad 119/2021 y su acumulada\n128/2021, notificada al Congreso del Estado de Baja California el día 17 de agosto de 2022, en los Términos de su Resolutivo Tercero, se declara la invalidez del Decreto No. 289, publicado en el Periódico Oficial No. 52, Número Especial, de fecha 29 de julio de 2022, Tomo CXXVIII, expedido por la H. XXIII Legislatura, siendo Gobernador Constitucional el C.\nJaime Bonilla Valdez 2019 – 2021;\nARTÍCULO 70.- Fue reformado mediante Decreto No. 76, publicado en el Periódico\nOficial No. 36, de fecha 22 de junio de 2020, Número Especial, Tomo CXXVII, expedido por la H. XXIII Legislatura, siendo Gobernador Constitucional el C. Jaime Bonilla Valdez 2019 –\n2021;\nARTÍCULO 91.- Fue reformado mediante Decreto No. 289, publicado en el Periódico\nOficial No. 52, de fecha 29 de julio de 2021, Número Especial, Tomo CXXVIII, expedido por la H. XXIII Legislatura, siendo Gobernador Constitucional el C. Jaime Bonilla Valdez 2019 –\n2021; mediante Sentencia de Acción de Inconstitucionalidad 119/2021 y su acumulada\n128/2021, notificada al Congreso del Estado de Baja California el día 17 de agosto de 2022, en los Términos de su Resolutivo Tercero, se declara la invalidez del Decreto No. 289, publicado en el Periódico Oficial No. 52, Número Especial, de fecha 29 de julio de 2022, Tomo CXXVIII, expedido por la H. XXIII Legislatura, siendo Gobernador Constitucional el C.\nJaime Bonilla Valdez 2019 – 2021;\nARTÍCULO 92.- Fue reformado mediante Decreto No. 76, publicado en el Periódico la H. XXIII Legislatura, siendo Gobernador Constitucional el C. Jaime Bonilla Valdez 2019 –\n2021;\nARTÍCULO 94.- Fue reformado mediante Decreto No. 76, publicado en el Periódico la H. XXIII Legislatura, siendo Gobernador Constitucional el C. Jaime Bonilla Valdez 2019 –\n2021;\nLey que Reglamenta el Servicio de Agua Potable en el Estado de Baja California. Página 34\nARTÍCULO 95.- Fue reformado mediante Decreto No. 76, publicado en el Periódico la H. XXIII Legislatura, siendo Gobernador Constitucional el C. Jaime Bonilla Valdez 2019 –\n2021;\nARTÍCULO 96.- Fue reformado mediante Decreto No. 51, publicado en el Periódico\nOficial No. 16, de fecha 20 de marzo de 2020, Sección III, Tomo CXXVII, expedido por la H.\nXXIII Legislatura, siendo Gobernador Constitucional el C. Jaime Bonilla Valdez 2019 – 2021; fue reformado mediante Decreto No. 76, publicado en el Periódico Oficial No. 36, de fecha\n22 de junio de 2020, Número Especial, Tomo CXXVII, expedido por la H. XXIII Legislatura, siendo Gobernador Constitucional el C. Jaime Bonilla Valdez 2019 – 2021;\nARTÍCULO 101.- Fue reformado mediante Decreto No. 289, publicado en el\nPeriódico Oficial No. 52, de fecha 29 de julio de 2021, Número Especial, Tomo CXXVIII, expedido por la H. XXIII Legislatura, siendo Gobernador Constitucional el C. Jaime Bonilla\nValdez 2019 – 2021; mediante Sentencia de Acción de Inconstitucionalidad 119/2021 y su acumulada 128/2021, notificada al Congreso del Estado de Baja California el día 17 de agosto de 2022, en los Términos de su Resolutivo Tercero, se declara la invalidez del\nDecreto No. 289, publicado en el Periódico Oficial No. 52, Número Especial, de fecha 29 de julio de 2022, Tomo CXXVIII, expedido por la H. XXIII Legislatura, siendo Gobernador\nConstitucional el C. Jaime Bonilla Valdez 2019 – 2021;\nARTÍCULO 108.- Fue reformado mediante Decreto No. 289, publicado en el\nPeriódico Oficial No. 52, de fecha 29 de julio de 2021, Número Especial, Tomo CXXVIII, expedido por la H. XXIII Legislatura, siendo Gobernador Constitucional el C. Jaime Bonilla\nValdez 2019 – 2021; mediante Sentencia de Acción de Inconstitucionalidad 119/2021 y su acumulada 128/2021, notificada al Congreso del Estado de Baja California el día 17 de agosto de 2022, en los Términos de su Resolutivo Tercero, se declara la invalidez del\nDecreto No. 289, publicado en el Periódico Oficial No. 52, Número Especial, de fecha 29 de julio de 2022, Tomo CXXVIII, expedido por la H. XXIII Legislatura, siendo Gobernador\nConstitucional el C. Jaime Bonilla Valdez 2019 – 2021;\nARTÍCULO 109.- Fue reformado mediante Decreto No. 67, publicado en el Periódico por la H. XXIII Legislatura, siendo Gobernador Constitucional el C. Jaime Bonilla Valdez\n2019 – 2021;\nARTÍCULO 116.- Fue reformado mediante Decreto No. 67, publicado en el Periódico por la H. XXIII Legislatura, siendo Gobernador Constitucional el C. Jaime Bonilla Valdez\n2019 – 2021;\nLey que Reglamenta el Servicio de Agua Potable en el Estado de Baja California. Página 35\nARTÍCULO 117.- Fue reformado mediante Decreto No. 67, publicado en el Periódico por la H. XXIII Legislatura, siendo Gobernador Constitucional el C. Jaime Bonilla Valdez\n2019 – 2021;\nFue adicionada esta denominación mediante Decreto No. 289, publicado en el\nPeriódico Oficial No. 52, de fecha 29 de julio de 2021, Número Especial, Tomo CXXVIII, expedido por la H. XXIII Legislatura, siendo Gobernador Constitucional el C. Jaime Bonilla\nValdez 2019 – 2021; mediante Sentencia de Acción de Inconstitucionalidad 119/2021 y su acumulada 128/2021, notificada al Congreso del Estado de Baja California el día 17 de agosto de 2022, en los Términos de su Resolutivo Tercero, se declara la invalidez del\nDecreto No. 289, publicado en el Periódico Oficial No. 52, Número Especial, de fecha 29 de julio de 2022, Tomo CXXVIII, expedido por la H. XXIII Legislatura, siendo Gobernador\nConstitucional el C. Jaime Bonilla Valdez 2019 – 2021;\nDE LOS ORGANISMOS ENCARGADOS DEL SERVICIO\nARTÍCULO 122.- Fue reformado mediante Decreto No. 289, publicado en el\nPeriódico Oficial No. 52, de fecha 29 de julio de 2021, Número Especial, Tomo CXXVIII, expedido por la H. XXIII Legislatura, siendo Gobernador Constitucional el C. Jaime Bonilla\nValdez 2019 – 2021; mediante Sentencia de Acción de Inconstitucionalidad 119/2021 y su acumulada 128/2021, notificada al Congreso del Estado de Baja California el día 17 de agosto de 2022, en los Términos de su Resolutivo Tercero, se declara la invalidez del\nDecreto No. 289, publicado en el Periódico Oficial No. 52, Número Especial, de fecha 29 de julio de 2022, Tomo CXXVIII, expedido por la H. XXIII Legislatura, siendo Gobernador\nConstitucional el C. Jaime Bonilla Valdez 2019 – 2021;\nARTÍCULO 123.- Fue reformado mediante Decreto No. 289, publicado en el\nPeriódico Oficial No. 52, de fecha 29 de julio de 2021, Número Especial, Tomo CXXVIII, expedido por la H. XXIII Legislatura, siendo Gobernador Constitucional el C. Jaime Bonilla\nValdez 2019 – 2021; mediante Sentencia de Acción de Inconstitucionalidad 119/2021 y su acumulada 128/2021, notificada al Congreso del Estado de Baja California el día 17 de\nDecreto No. 289, publicado en el Periódico Oficial No. 52, Número Especial, de fecha 29 de\nConstitucional el C. Jaime Bonilla Valdez 2019 – 2021;\nARTÍCULO 124.- Fue reformado mediante Decreto No. 289, publicado en el expedido por la H. XXIII Legislatura, siendo Gobernador Constitucional el C. Jaime Bonilla\nLey que Reglamenta el Servicio de Agua Potable en el Estado de Baja California. Página 36\nValdez 2019 – 2021; mediante Sentencia de Acción de Inconstitucionalidad 119/2021 y su acumulada 128/2021, notificada al Congreso del Estado de Baja California el día 17 de\nDecreto No. 289, publicado en el Periódico Oficial No. 52, Número Especial, de fecha 29 de\nConstitucional el C. Jaime Bonilla Valdez 2019 – 2021;\nLey que Reglamenta el Servicio de Agua Potable en el Estado de Baja California. Página 37\nARTÍCULO ÚNICO TRANSITORIO DEL DECRETO No. 51, POR EL QUE SE\nREFOMAN LOS ARTÍCULOS 2 Y 17; Y ADICIÓN DE UNA FRACCIÓN IV AL ARTÍCULO\n96; PUBLICADO EN EL PERIÓDICO OFICIAL No. 16, SECCIÓN III, TOMO CXXVII, DE\nGOBERNADOR CONSTITUCIONAL EL C. JAIME BONILLA VALDEZ 2019-2021.\nARTÍCULOS TRANSITORIOS\nPRIMERO.- El presente Decreto entrará en vigor al día siguiente de su publicación en el\nPeriódico Oficial del Estado.\nSEGUNDO.- Los procedimientos administrativos de reducción de suministro de agua, que a la entrada en vigor del presente Decreto se encuentren en trámite, continuarán substanciados por la autoridad y términos bajo los cuales fueron iniciados.\nDADO en el Salón de Sesiones “Lic. Benito Juárez García” del H. Poder Legislativo del\nEstado de Baja California, en la Ciudad de Mexicali, B.C., a los dieciocho días del mes de marzo del año dos mil veinte.\nDIP. VÍCTOR MANUEL MORÁN HERNÁNDEZ\nPRESIDENTE\n(RÚBRICA)\nDIP. CARMEN LETICIA HERNÁNDEZ CARMONA\nSECRETARIA\n(RÚBRICA)\nDE CONFORMIDAD CON LO DISPUESTO POR LA FRACCIÓN I DEL ARTÍCULO 49 DE\nMEXICALI, BAJA CALIFORNIA, A LOS DIECINUEVE DÍAS DEL MES DE MARZO DEL\nAÑO DOS MIL VEINTE.\nJAIME BONILLA VALDEZ\nGOBERNADOR DEL ESTADO\n(RÚBRICA)\nAMADOR RODRÍGUEZ LOZANO\nSECRETARIO GENERAL DE GOBIERNO\n(RÚBRICA)\nLey que Reglamenta el Servicio de Agua Potable en el Estado de Baja California. Página 38\nARTÍCULO CUARTO TRANSITORIO DEL DECRETO No. 67, POR EL QUE SE\nREFOMAN LOS ARTÍCULOS 109, 116 Y 117; PUBLICADO EN EL PERIÓDICO OFICIAL\nEXPEDIDO POR LA H. XXIII LEGISLATURA, SIENDO GOBERNADOR CONSTITUCIONAL\nEL C. JAIME BONILLA VALDEZ 2019-2021.\nARTÍCULOS TRANSITORIOS\nÚNICO.- El presente Decreto entrará en vigor al día siguiente de su publicación en el\nPeriódico Oficial del Estado.\nDADO en el Salón de Sesiones “Lic. Benito Juárez García” del H. Poder Legislativo del\nEstado de Baja California, en la Ciudad de Mexicali, B.C., a los once días del mes de mayo del año dos mil veinte.\nDIP. LUIS MORENO HERNÁNDEZ\nPRESIDENTE\n(RÚBRICA)\nDIP. EVA GRICELDA RODRÍGUEZ\nSECRETARIA\n(RÚBRICA)\nDE CONFORMIDAD CON LO DISPUESTO POR LA FRACCIÓN I DEL ARTÍCULO 49 DE\nMEXICALI, BAJA CALIFORNIA, A LOS DOCE DÍAS DEL MES DE MAYO DEL AÑO DOS\nMIL VEINTE.\nJAIME BONILLA VALDEZ\nGOBERNADOR DEL ESTADO\n(RÚBRICA)\nAMADOR RODRÍGUEZ LOZANO\nSECRETARIO GENERAL DE GOBIERNO\n(RÚBRICA)\nLey que Reglamenta el Servicio de Agua Potable en el Estado de Baja California. Página 39\nARTÍCULO SEGUNDO TRANSITORIO DEL DECRETO No. 76, POR EL QUE SE\nREFOMAN LOS ARTÍCULOS 70, 92, 94 Y 96; PUBLICADO EN EL PERIÓDICO OFICIAL\nEXPEDIDO POR LA H. XXIII LEGISLATURA, SIENDO GOBERNADOR CONSTITUCIONAL\nEL C. JAIME BONILLA VALDEZ 2019-2021.\nARTÍCULOS TRANSITORIOS\nPRIMERO. El presente Decreto entrará en vigor al día siguiente de su publicación en el\nPeriódico Oficial del Estado.\nSEGUNDO. Los Organismos Operadores del Agua dentro de un plazo que no excederá de noventa días naturales contados a partir de la entrada en vigor de la presente reforma, realizarán las adecuaciones administrativas y reglamentarias necesarias para la implementación de la presente reforma.\nDADO en el Salón de Sesiones “Lic. Benito Juárez García” del H. Poder Legislativo del\nEstado de Baja California, en la Ciudad de Mexicali, B.C., a los diecisiete días del mes de junio del año dos mil veinte.\nDIP. JULIO CÉSAR VÁZQUEZ CASTILLO\nVICEPRESIDENTE\n(RÚBRICA)\nDIP. EVA GRICELDA RODRÍGUEZ\nSECRETARIA\n(RÚBRICA)\nDE CONFORMIDAD CON LO DISPUESTO POR LA FRACCIÓN I DEL ARTÍCULO 49 DE\nMEXICALI, BAJA CALIFORNIA, A LOS DIECINUEVE DÍAS DEL MES DE JUNIO DEL AÑO\nDOS MIL VEINTE.\nJAIME BONILLA VALDEZ\nGOBERNADOR DEL ESTADO\n(RÚBRICA)\nAMADOR RODRÍGUEZ LOZANO\nSECRETARIO GENERAL DE GOBIERNO\n(RÚBRICA)\nLey que Reglamenta el Servicio de Agua Potable en el Estado de Baja California. Página 40\nARTÍCULO PRIMERO TRANSITORIO DEL DECRETO No. 289, POR EL QUE SE\nREFOMAN LOS ARTÍCULOS 1, 14, 15, 17, 19, 20, 52, 57, 67, 91, 101 y 108, ASÍ COMO LA\nADICIÓN DE LOS ARTÍCULOS 122, 123 y 124; PUBLICADO EN EL PERIÓDICO OFICIAL\nEXPEDIDO POR LA H. XXIII LEGISLATURA, SIENDO GOBERNADOR CONSTITUCIONAL\nEL C. JAIME BONILLA VALDEZ 2019-2021.\nSentencia de Acción de Inconstitucionalidad 119/2021 y su acumulada 128/2021\nARTÍCULOS TRANSITORIOS\nPRIMERO.- La presente reforma entrará en vigor al día siguiente de su publicación en el\nPeriódico Oficial del Estado.\nSEGUNDO.- Dentro de los treinta días naturales siguientes contados a partir de la entrada en vigor del presente decreto, se instalará una Comisión Especial integrada por la Secretaría\nGeneral de Gobierno, la Secretaría de Hacienda y la Secretaría para el Manejo, Saneamiento y Protección del Agua, así como por representantes de las Comisiones\nEstatales de Servicios Públicos y un representante de los Municipios, para dar seguimiento y consolidar la transferencia los recursos, materiales, financieros, administrativos y humanos de las comisiones a los municipios, así como para resolver lo conducente respecto de la instrumentación del presente Decreto.\nTERCERO.- Dentro de los seis meses siguientes contados a partir de la entrada en vigor de la presente reforma, los municipios deberán expedir las normas, reglamentos municipales y demás normas administrativas necesarias para la armonización normativa con el presente decreto. Hasta en tanto se expidan la normativa reglamentaria se aplicará de manera supletoria las disposiciones de orden estatal.\nCUARTO.- Los Municipios contarán con 60 días naturales contados a partir de la entrada en vigor del presente Decreto para crear los Organismos municipales que se encargados de la prestación de los servicios públicos de agua potable, drenaje, alcantarillado, tratamiento y disposición final de sus aguas residuales, debiendo notificar al Ejecutivo del Estado, a efecto de iniciar el proceso de transferencia de los recursos financieros, materiales y humanos del organismo estatal operador del agua que corresponda a favor del organismos paramunicipal.\nHasta en tanto no se culmine el proceso de transferencia de recursos antes mencionado, las de agua en los Municipios que les correspondan, en los términos de la presente Ley, su Ley reglamentaria y los ordenamientos estatales correspondientes.\nQUINTO.- El Ejecutivo del Estado en conjunto con la Comisión Estatal de Servicios Públicos que corresponda, transferirá todos los recursos financieros, materiales y humanos al\nOrganismo paramunicipal encargado del servicio del Municipio respectivo, las acciones de\nLey que Reglamenta el Servicio de Agua Potable en el Estado de Baja California. Página 41 al estado de la creación del organismo municipal.\nSEXTO.- En los casos de los municipios de Playas de Rosarito, San Quintín y San Felipe, contaran con un año para crear su organismo paramunicipal. Las Comisiones de Servicios\nPúblicos de Tijuana, Ensenada y Mexicali, transferirán de manera equitativa y proporcional al número de usuarios de cada municipio, así como a la necesidad de infraestructura de los nuevos organismos paramunicipales en la demarcación territorial de dichos municipios.\nHasta en tanto no se realice la transferencia, seguirán siendo responsables de su administración.\nSÉPTIMO.- Los recursos humanos del personal adscrito a las Comisiones Estatales de\nServicios Públicos será transferido a los Organismos paramunicipales encargados del servicio de agua, salvaguardando sus derechos laborales.\nOCTAVO.- Las concesiones otorgadas por la Comisión Nacional del Agua a favor del\nGobierno del Estado o sus entidades paraestatales, continuarán siendo administradas por el\nEjecutivo Estatal, por lo que para el uso y aprovechamiento del agua comprendida en las mismas. Los Organismos Paramunicipales encargados del servicio deberán celebrar convenios con el Ejecutivo Estatal.\nNOVENO.- Los procesos judiciales, administrativos y laborales, así como los demás asuntos jurídicos que se encuentren en proceso, incluyendo los derivados de la determinación y cobro de contribuciones derechos y sanciones a nombre de las Comisiones Estatales de\nServicios Públicos de Mexicali, Ensenada, Tecate y Tijuana, a partir de la entrada en vigor del presente Decreto, corresponderá atenderlos a las actuales comisiones estatales de servicios públicos, según corresponda, en tanto se crean los Organismos paramunicipales.\nDÉCIMO.- Se instruye a la Secretaria de Hacienda para que lleve a cabo las acciones necesarias, a efecto de que los créditos fiscales generados a favor de las Comisiones\nEstatales de Servicios Públicos de Mexicali, Ensenada, Tecate y Tijuana, que a la fecha de la entrada del presente Decreto queden sin cubrir, derivados de la prestación de servicios públicos así como del convenio de adeudos sean cobrados y recaudados por conducto de sus instancias recaudadoras.\nDÉCIMO PRIMERA.- Para los efectos legales y de funcionamiento de las Comisiones\nEstatales de Servicios Públicos quedarán vigentes los contratos, fideicomisos, empréstitos, acuerdos, convenios y cada uno de los instrumentos jurídicos que existan en dichos\nDecreto, conservando dichas Comisiones la administración de los mismos en tanto no se servicios.\nRespecto de los contratos con instituciones bancarias o financieras, a través de los cuales las Comisiones Estatales de Servicios Públicos hayan adquirido deuda pública, se realizarán\nLey que Reglamenta el Servicio de Agua Potable en el Estado de Baja California. Página 42 deuda como deudor sustituto, y en el supuesto de que el Ejecutivo del Estado se encuentre como garante o aval, este será sustituido por el Municipio que corresponda.\nDÉCIMO SEGUNDA.- Los adeudos generados y el patrimonio a favor de los organismos\nMexicali, Ensenada, Tecate y Tijuana se transferirán a favor de los Organismos paramunicipales encargados del servicio de agua, en términos de este decreto.\nDÉCIMO TERCERA.- Las referencias que se hagan a las Comisiones Estatales de Servicios\nPúblicos de Baja California o a los organismos estatales encargados del servicio de agua en la normatividad estatal se entenderán realizadas a los Organismos paramunicipales encargados del servicio de agua.\nAl termino del proceso de transferencia de recursos entre el Ejecutivo Estatal y los\nMunicipios, quedará abrogada la Ley de las Comisiones Estatales de Servicios Públicos de\nBaja California, así como las demás disposiciones reglamentarias de dicha Ley.\nDADO en el Salón de Sesiones Benito Juárez García en Sesión Ordinaria de la XXIII\nLegislatura en la Ciudad de Mexicali, B.C., a los veintiocho días del mes de julio del año dos mil veintiuno.\nDIP. EVA GRICELDA RODRÍGUEZ\nPRESIDENTA\n(RÚBRICA)\nDIP. MARÍA LUISA VILLALOBOS ÁVILA\nSECRETARIA\n(RÚBRICA)\nDE CONFORMIDAD CON LO DISPUESTO POR LA FRACCIÓN I DEL ARTÍCULO 49 DE\nCALIFORNIA, IMPRÍMASE Y PUBLÍQUESE.\nMEXICALI, BAJA CALIFORNIA, A LOS VEINTIOCHO DÍAS DEL MES DE JULIO DEL AÑO\nDOS MIL VEINTIUNO.\nJAIME BONILLA VALDEZ\nGOBERNADOR DEL ESTADO\n(RÚBRICA)\nAMADOR RODRÍGUEZ LOZANO\nLey que Reglamenta el Servicio de Agua Potable en el Estado de Baja California. Página 43\nSECRETARIO GENERAL DE GOBIERNO\n(RÚBRICA)\nSENTENCIA DE ACCIÓN DE INCONSTITUCIONALIDAD 119/2021 Y SU ACULADA\n128/2021, NOTIFICADA AL CONGRESO DEL ESTADO DE BAJA CALIFORNIA EL DÍA 17\nTERCERO, SE DECLARA LA INVALIDEZ DEL DECRETO NO. 289, PUBLICADO EN EL\nEXPEDIDO POR LA H. XXIII LEGISLATURA, SIENDO GOBERNADOR CONSTITUCIONAL\nEL C. JAIME BONILLA VALDEZ 2019-2021.\nLey que Reglamenta el Servicio de Agua Potable en el Estado de Baja California. Página 44",
  "ordenamiento": "REGLAMENTO",
  "jurisdiccion": "BAJA CALIFORNIA",
  "fuente_oficial": "Periódico Oficial",
  "FECHA PER OFIC": "2021/07/29",
  "ESTATUS": "VIGENTE",
  "TOMO": "TOMO_VII",
  "URL": "https://www.congresobc.gob.mx/Documentos/ProcesoParlamentario/Leyes/TOMO_VII/20210729_LEYREGAGUAPOTABLE-2.PDF",
  "es_escaneado": false,
  "tiene_tablas": false,
  "materia": [
    "ambiental",
    "urbanismo",
    "infraestructura"
  ]
}