{
  "titulo": "Ley DE INSTITUCIONES DE ASISTENCIA SOCIAL PRIVADA PARA NIÑAS, NIÑOS y ADOLESCENTES PARA EL ESTADO DE",
  "Contenido": "LEY DE INSTITUCIONES DE ASISTENCIA SOCIAL PRIVADA PARA NIÑAS, Publicada en el Periódico Oficial No. 18, Sección I, Tomo CXXII,\nTÍTULO PRIMERO\nDISPOSICIONES GENERALES\nArtículo 1.- La presente Ley es de orden público e interés social y tiene por objeto regular y vigilar el funcionamiento de las Instituciones de Asistencia Social Privada, que tengan bajo su guarda, custodia o ambas a niñas, niños y adolescentes en el Estado de Baja\nCalifornia; estableciendo las bases y directrices necesarias para tutelar el pleno goce de los derechos de éstos y garantizar su seguridad física y jurídica, atendiendo al interés superior de la niñez.\nArtículo 2.- Corresponde al Sistema para el Desarrollo Integral de la Familia de Baja\nCalifornia por conducto de la Procuraduría de Protección de Niñas, Niños y Adolescentes del\nEstado, la aplicación de la presente Ley observando para tal efecto los derechos del menor consagrados en la Constitución Política de los Estados Unidos Mexicanos, en la Convención\nSobre los Derechos del Niño, la Ley General de los Derechos de Niñas, Niños y legales aplicables, vigilando que prevalezca siempre el interés superior del menor y su reintegración familiar.\nArtículo 3.- A falta de disposición expresa en esta Ley, se aplicará en forma supletoria el Código Civil para el Estado de Baja California, el Código de Procedimientos\nCiviles para el Estado de Baja California, la Ley de Asistencia Social para el Estado de Baja\nCalifornia, la Ley para la Protección y Defensa de los Derechos de las Niñas, Niños y\nAdolescentes del Estado de Baja California; y demás ordenamientos aplicables en la materia.\nSocial para el Estado de Baja California, la Ley para la Protección y Defensa de los\nDerechos de las Niñas, Niños y Adolescentes del Estado de Baja California; y otros ordenamientos aplicables.\nArtículo Reformado\nLey de Instituciones de Asistencia Social Privada para Niñas, Página 1\nArtículo 4.- Para los efectos de la presente Ley se entenderá por:\nI. Instituciones de Asistencia Social Privada: Las casas hogar, casas cuna, albergues, internados o cualquier otra institución social privada cualquiera que sea su denominación, en la que residan y tengan bajo su guarda, custodia o ambas a niñas, niños y adolescentes;\nII. Niñas, niños y adolescentes: Las personas menores de dieciocho años de edad que se encuentren internos en una Institución de Asistencia Social Privada en calidad de abandonados, expósitos, repatriados, maltratados, sujetos a asistencia social, víctimas de la comisión de delitos o migrantes y en razón de la guarda temporal otorgada voluntariamente por quienes ejerzan la patria potestad o la tutela, o bien por mandato de autoridad competente;\nIII. Procuraduría de Protección: Procuraduría de Protección de Niñas, Niños y\nAdolescentes del Estado;\nIV. Coordinación: La Coordinación de Asistencia Privada dependiente de la\nProcuraduría de Protección de Niñas, Niños y Adolescentes del Estado;\nV. Consejo Consultivo: El Consejo Consultivo en materia de asistencia social privada previsto en Ley de Asistencia Social para el Estado de Baja California\nVI. Guarda: Circunstancia de facto mediante la cual las niñas, niños y adolescentes se encuentran bajo el cuidado de una Institución de Asistencia Social Privada, cuando ésta se responsabiliza temporalmente de la salvaguarda personal, física y psicológica de los mismos, mediante autorización voluntaria por escrito de quien o quienes ejerzan su patria potestad o tutela, y con formal conocimiento de la Procuraduría de Protección;\nVII. Custodia: Figura jurídica mediante la cual las niñas, niños y adolescentes se encuentran a cargo de una Institución de Asistencia Social Privada cuando dicho cuidado deriva de un mandato de autoridad competente o de una autorización otorgada, en su caso, por la Procuraduría de Protección, con permiso expreso para ejercer los derechos de posesión o tenencia material, crianza, formación, educación, atención a la salud, protección, socialización y demás necesarios para el desarrollo integral de las niñas, niños y adolescentes;\nVIII. Integración: Proceso mediante el cual, la titularidad de la Dirección, representante o encargado de una Institución de Asistencia Social Privada permite, cubiertos previamente los requisitos de Ley, la salida temporal de una niña, niño o adolescente, a fin de que éste\nLey de Instituciones de Asistencia Social Privada para Niñas, Página 2 autoridad competente, y con el objeto de integrarlo paulatinamente a su ámbito familiar nuclear, extenso, substituto o adoptivo.\nFracción Reformada\nArtículo Reformado\nArtículo 5.- Las Instituciones de Asistencia Social Privada deberán privilegiar en todo momento el derecho de las niñas, niños y adolescentes a vivir en familia y promoverán preferentemente el restablecimiento, integración y preservación de sus vínculos familiares tomando en cuenta que éstos no resulten en su perjuicio, teniendo como norma rectora el principio del interés superior de la niñez, garantizando en el diseño, implementación y lineamientos el acceso igualitario a quienes tengan bajo su cuidado a niñas, niños y adolescentes aplicando en todo momento los principios de igualdad y no discriminación.\nArtículo Reformado\nTÍTULO SEGUNDO\nDEL CONSEJO CONSULTIVO\nArtículo 6.- Para efectos de esta Ley, el Consejo Consultivo tendrá por objeto la promoción, asesoría y apoyo de las Instituciones de Asistencia Social Privada, el cual emitirá directrices para el mejor funcionamiento de las mismas, privilegiando en todo momento el interés superior de la niñez.\nArtículo 7.- Además de las atribuciones previstas en la Ley de Asistencia Social para el Estado de Baja California, el Consejo Consultivo tendrá las siguientes:\nI. Elaborar análisis, diagnósticos, evaluaciones, políticas, planes, programas y acciones tendientes a mejorar el funcionamiento de las Instituciones de Asistencia Social\nPrivada, y proponerlas a la Procuraduría de Protección;\nII. Facilitar por conducto de la Procuraduría de Protección a las distintas áreas del\nSistema para el Desarrollo Integral de la Familia del Estado de Baja California y las\nDependencias y entidades que considere necesarias, asesoría profesional en materia jurídica, psicológica, de sanidad, de competencia de su personal y de trabajo social, según sea el caso;\nIII. Gestionar recursos, servicios y apoyos ante las Autoridades Federales, Estatales, Municipales y los diversos sectores de la sociedad, para destinarlos al cumplimiento del objeto social de las Instituciones de Asistencia Social Privada, canalizándolos a las mismas;\nIV. Promover la capacitación continua y preponderantemente gratuita a las personas responsables y el personal de las Instituciones de Asistencia Social Privada, mediante la\nLey de Instituciones de Asistencia Social Privada para Niñas, Página 3 organización de cursos, talleres, exhibiciones, seminarios, conferencias, mesas de diálogos y diplomados;\nFracción Reformada\nV. Apoyar a las Instituciones de asistencia social privada, cuando éstas así lo soliciten las niñas, niños y adolescentes a la educación, cultura, deporte y salud, dichas acciones y apoyos se proporcionarán con los principios de igualdad y no discriminación y con ello se otorgará acceso igualitario;\nFracción Reformada\nVI. Promover acciones tendientes a incentivar el buen funcionamiento de las\nInstituciones de Asistencia Social Privada; y\nVII. Las demás necesarias para el cumplimiento de su objeto.\nArtículo Reformado\nTÍTULO TERCERO\nFACULTADES Y OBLIGACIONES\nCAPÍTULO PRIMERO\nATRIBUCIONES DE LA AUTORIDAD\nArtículo 8.- Son atribuciones de la Procuraduría de Protección, en la aplicación de la presente Ley, las siguientes:\nI. Otorgar la licencia de operación a las Instituciones de Asistencia Social Privada, previo cumplimiento de los requisitos establecidos por esta Ley y otros ordenamientos legales relacionados con la materia;\nII. Constituir el registro de las Instituciones de Asistencia Social Privada que operan en el Estado de Baja California, y actualizarlo cada seis meses;\nIII. Constituir el registro de niñas, niños y adolescentes ingresados y egresados en\nInstituciones de Asistencia Social Privada, y actualizarlo periódicamente;\nIV. Realizar visitas a las Instituciones de Asistencia Social Privada para supervisar su correcta operación; las condiciones en que se encuentran las niñas, niños y adolescentes ingresados, la infraestructura del inmueble, su menaje, así como las condiciones de sanidad y del personal que presta sus servicios en ellos, debiendo auxiliarse para tal efecto con las autoridades coadyuvantes correspondientes;\nLey de Instituciones de Asistencia Social Privada para Niñas, Página 4\nV. Emitir observaciones a las Instituciones de Asistencia Social Privada, a fin de mejorar su servicio y garantizar la adecuada estancia y desarrollo de las niñas, niños y adolescentes ingresados;\nVI. Presentar denuncia ante el Ministerio Público de inmediato por las conductas que puedan ser constitutivas de delito;\nVII. Solicitar las opiniones o dictámenes necesarios a las Autoridades Federales, Estatales o Municipales para el cumplimiento de lo dispuesto en la presente Ley, así como de las determinaciones del Sistema Estatal de Asistencia Social;\nVIII. Solicitar a la autoridad competente información o antecedentes del personal que labore o preste servicios voluntarios en las Instituciones de Asistencia Social Privada, con el fin de garantizar la debida guarda, custodia y en general el desarrollo integral de las niñas, niños y adolescentes a cargo de las mismas;\nIX. Aplicar las sanciones correspondientes por las infracciones o inobservancia a la presente Ley;\nX. Dar puntual seguimiento de manera permanente a los traslados de las niñas, niños y adolescentes;\nXI. Autorizar la salida por motivo de integración o entrega a quien detente la custodia legal de las niñas, niños y adolescentes que estén a cargo de las Instituciones de Asistencia\nSocial Privada; y\nXII. Las demás que le correspondan de conformidad con las leyes, decretos, acuerdos, reglamentos, circulares y demás disposiciones legales aplicables.\nCAPÍTULO SEGUNDO\nArtículo 9.- Son obligaciones de las Instituciones de Asistencia Social Privada, las siguientes:\nI. Contar con licencia de operación vigente y formar parte del Registro de Instituciones de Asistencia Social Privada;\nII. Llevar un registro de las niñas, niños y adolescentes ingresados y egresados y mantenerlo actualizado, así como una bitácora donde se consigne las salidas y retornos\nLey de Instituciones de Asistencia Social Privada para Niñas, Página 5 ordinariamente programados en razón de actividades familiares, educativas, sanitarias, deportivas, culturales, formativas o de recreación;\nIII. Notificar a la Procuraduría de Protección dentro de las 24 horas posteriores sobre los ingresos y egresos de las niñas, niños y adolescentes de las Instituciones de Asistencia\nSocial Privada, sin perjuicio de la causa que lo origine, debiendo dejar registro de los mismos en el expediente respectivo;\nIV. Privilegiar en todo momento el derecho de las niñas, niños y adolescentes a vivir en familia, teniendo como principio rector el interés superior de la niñez. En tal sentido, permitirán y promoverán que sus ingresados estén en contacto con sus familiares y reciban visitas de éstos, salvo que exista un mandamiento de autoridad competente que lo prohíba;\nV. Promover el restablecimiento y la preservación, en coordinación con la\nProcuraduría de Protección, de los vínculos familiares de las niñas, niños y adolescentes, tomando en cuenta que no resulten en su perjuicio;\nVI. Contar con las instalaciones y el personal adecuado para garantizar la seguridad integral de las niñas, niños y adolescentes ingresados;\nVII. Tener en un lugar visible en la recepción de las instalaciones de la Instituciones de Asistencia Social Privada, copia del documento que acredite la licencia vigente expedida por la Procuraduría de Protección;\nVIII. Contar con un Reglamento Interno, autorizado por la Procuraduría de Protección;\nIX. Facilitar las tareas de vigilancia, inspección y protección de las niñas, niños y adolescentes, debiendo permitir el acceso al interior de las instalaciones de las Instituciones de Asistencia Social Privada a las personas que para tal efecto y por escrito designe la\nProcuraduría de Protección, así como facilitar para consulta los registros, expedientes y bitácoras que se les requieran;\nX. Informar inmediatamente a la autoridad correspondiente, cuando tengan conocimiento de que peligre la integridad física, psicológica y en general la seguridad de alguna niña, niño o adolescente;\nFracción Reformada\nXI. Contar con asesoría profesional en materia psicológica, de sanidad, y de trabajo social;\nLey de Instituciones de Asistencia Social Privada para Niñas, Página 6\nXII. Proporcionar a las niñas, niños y adolescentes ingresados la protección, atención y cuidado que sean necesarios para su bienestar;\nXIII. Proporcionar a las niñas, niños y adolescentes ingresados educación, actividades recreativas, culturales y deportivas, así como programas de integración familiar o social;\nXIV. Notificar a la Procuraduría de Protección con cinco días de anticipación a la contratación del personal que prestará sus servicios en Instituciones de Asistencia Social\nPrivada así como de aquellos que presten servicios en forma voluntaria, temporal o permanentemente en dichas instituciones, con el objeto de conocer el perfil y antecedentes respectivos; así como dar aviso dentro de los cinco días posteriores sobre las bajas del personal y las causas que las hayan generado;\nXV. Tomar las medidas pertinentes, o en su caso, separar o impedir el ingreso o estancia al interior de las instalaciones de las Instituciones de Asistencia Social Privada cuando la Procuraduría de Protección les haya notificado que el personal que labore o preste sus servicios voluntarios no cumple con los requisitos para ello;\nXVI. Dar a conocer a los padres o tutores y a las niñas, niños y adolescentes mayores de siete años de edad su situación legal, sus derechos, obligaciones y orientarlos para la toma de decisiones implementadas para su desarrollo y asistencia social, debiendo otorgarse bajo los principios de igualdad y no discriminación;\nFracción Reformada\nXVII. Garantizar el acceso de las niñas, niños y adolescentes, en coordinación con la\nProcuraduría de Protección, a una asistencia médica en cumplimiento a las normas oficiales mexicanas en materia de salud;\nXVIII. Cumplir con las observaciones que le emita la Procuraduría de Protección; y\nXIX. Cumplir con lo dispuesto por esta Ley y otros ordenamientos aplicables.\nArtículo Reformado\nArtículo 10.- Las niñas, niños y adolescentes a cargo de las Instituciones de\nAsistencia Social Privada bajo ninguna circunstancia o motivo podrán ser confiados, puestos detente su custodia, patria potestad o tutela.\nLey de Instituciones de Asistencia Social Privada para Niñas, Página 7 con las niñas, niños y adolescentes internos, deberán ser supervisados en todo momento por el personal administrativo o voluntario que previamente haya sido designado para tal fin.\nLa relación de guarda, custodia y en general de atención a las niñas, niños y persona alguna sobre los menores a su cargo.\nArtículo 11.- El Reglamento Interno de las Instituciones de Asistencia Social Privada deberá contener cuando menos:\nI. Los requisitos de admisión de las niñas, niños y adolescentes;\nII. Las obligaciones para los padres, tutores o personas que tengan bajo su cuidado a las niñas, niños y adolescentes ingresados;\nIII. El establecimiento de programas formativos, educativos, de valores, de integración familiar o sociales, culturales, deportivos y recreativos;\nIV. El horario de actividades para las niñas, niños y adolescentes bajo su guarda, custodia o ambas;\nV. Los derechos, obligaciones y medidas de disciplina para las niñas, niños y adolescentes ingresados; y\nVI. Las medidas de disciplina para el personal administrativo y voluntario.\nArtículo 12.- Las Instituciones de Asistencia Social Privada llevarán un expediente individualizado de cada una de las niñas, niños y adolescentes que tengan bajo su cuidado, el cual contendrá como mínimo:\nI. Nombre, datos de identificación, acta de nacimiento, Cédula Única de Registro de\nPoblación, cédula de identidad, fotografías de frente y de perfil actualizadas semestralmente por lo menos, cartilla de vacunación, registro dactilar, expediente médico incluyendo tipo sanguíneo, y evaluaciones psicológicas;\nII. Motivo y fecha de ingreso, y en su caso, de egreso;\nIII. Tipo y modalidad de la violencia y su seguimiento;\nFracción Adicionada, recorriéndose las subsecuentes\nLey de Instituciones de Asistencia Social Privada para Niñas, Página 8\nIV. Nombre, domicilio, copia de una identificación oficial con fotografía de la persona física o de la autoridad que materialmente hace entrega de la niña, niño o adolescente; entrega de la niña, niño o adolescente, deberán ser fotografiados por el personal de la\nInstituciones de Asistencia Social Privada;\nPárrafo Reformado\nV. Nombre, domicilio y copia de una identificación oficial con fotografía de la o las personas que ejerzan la custodia, tutela o patria potestad sobre las niñas, niños y adolescentes;\nLas personas que carezcan de identificación oficial con fotografía al momento de la entrega de la niña, niño o adolescente, deberán ser fotografiados por el personal de la\nInstituciones de Asistencia Social Privada;\nPárrafo Adicionado\nVI. Nombre, domicilio y copia de una identificación oficial con fotografía de la o las personas que visiten y hubieren estado en convivencia por cualquier circunstancia con la niña, niño o adolescente;\nFracción Reformada\nVII. Datos escolares y boleta de calificaciones de las niñas, niños y adolescentes;\nVIII. Situación legal de la niña, niño o adolescente ingresado y documentos de lo anterior; y,\nFracción Reformada\nIX. Las demás que la Procuraduría de Protección, y las Instituciones de Asistencia\nSocial Privada consideren necesarias.\nArtículo Reformado\nTÍTULO CUARTO\nPRIVADA\nCAPÍTULO ÚNICO\nREQUISITOS PARA OBTENER LA LICENCIA\nArtículo 13.- Las Instituciones de Asistencia Social Privada para su operación y legal\nLey de Instituciones de Asistencia Social Privada para Niñas, Página 9\nProcuraduría de Protección.\nArtículo 14.- La Procuraduría de Protección expedirá la licencia de operación, o su revalidación, y constancia de registro de la Institución de Asistencia Social Privada dentro de un plazo que no podrá exceder de treinta días hábiles, contados a partir del día siguiente de la fecha en que se emita la determinación de integración del expediente, o en su caso, el cumplimiento de los requisitos para su revalidación.\nArtículo 15.- Para obtener la licencia a que se refiere el artículo anterior, las\nInstituciones de Asistencia Social Privada deberán cumplir con los requisitos siguientes:\nI. Llenar la solicitud oficial proporcionada por la Procuraduría de Protección;\nII. Presentar la documentación que acredite la personalidad jurídica, y legal constitución de la Instituciones de Asistencia Social Privada;\nIII. Autorización de constitución como Institución de Asistencia Social Privada emitido por la Secretaría de Desarrollo Social del Estado, en los términos que disponga la Ley de\nAsistencia Social para el Estado de Baja California y demás ordenamientos aplicables;\nIV. Copia de la licencia de uso de suelo de sus instalaciones;\nV. Presentar sus programas de promoción para la integración familiar, formación, educación, recreación, cultura y deporte de las niñas, niños y adolescentes; asegurando en el diseño, implementación y cumplimiento, el trato igualitario a quienes los tengan bajo su cuidado, cerciorándose que se aplican los principios de igualdad y no discriminación;\nFracción Reformada\nVI. Permitirlas inspecciones necesarias por parte del personal de la Procuraduría de\nProtección en conjunto con las autoridades coadyuvantes que para tal efecto determine, con de las niñas, niños y adolescentes, así como las condiciones generales sobre infraestructura, personal, población e higiene, debiendo solventarlas satisfactoriamente;\nVII. Presentar esquema de financiamiento y programa de allegamiento de recursos que permitan una atención adecuada a las niñas, niños y adolescentes; y\nVIII. Presentar el padrón y expediente personal de cada uno del personal directivo, Privada.\nLey de Instituciones de Asistencia Social Privada para Niñas, Página 10\nArtículo Reformado\nArtículo 16.- La licencia establecida en este capítulo, deberá de renovarse obligatoriamente cada dos años.\nArtículo 17.- La renovación de la licencia se expedirá siempre y cuando se siga cumpliendo con los requisitos exigidos para su obtención, y además se acrediten los siguientes requisitos:\nI. Acreditar las evaluaciones permanentes, periódicas y obligatorias establecidas por esta Ley y aplicadas por la Procuraduría de Protección a través de la Coordinación para comprobar el cumplimiento de las disposiciones normativas;\nII. Copia del registro de las niñas, niños y adolescentes ingresados; y\nIII. La actualización del padrón del personal directivo, administrativo y voluntario.\nTÍTULO QUINTO\nDEL FUNCIONAMIENTO DE LAS INSTITUCIONES DE ASISTENCIA SOCIAL PRIVADA\nCAPÍTULO PRIMERO\nDE LAS INSTALACIONES\nArtículo 18.- Los inmuebles que sean destinados como establecimientos de las\nInstituciones de Asistencia Social Privada deberán contar con los servicios indispensables para proporcionar a las niñas, niños o adolescentes el bienestar, la comodidad, seguridad y gestión necesarias conforme a su edad, incluyendo productos de gestión menstrual.\nArtículo Reformado\nArtículo 19.- Las instalaciones de los establecimientos de las Instituciones de\nAsistencia Social Privada tendrán espacios divididos para ser utilizados para un fin específico. En tal sentido, obligatoriamente deberán contar con las áreas y especificaciones materia.\nArtículo 20.- Las Instituciones de Asistencia Social Privada deberán someterse a las inspecciones que lleve a cabo la Dirección de Protección Civil del Estado, contar un Plan de\nProtección Civil, así como con los dispositivos y equipamientos de seguridad con la Ley en la materia.\nLey de Instituciones de Asistencia Social Privada para Niñas, Página 11\nArtículo 21.- Los establecimientos de las Instituciones de Asistencia Social Privada contingencia que se suscite.\nArtículo 22.- Las Instituciones de Asistencia Social Privada deberán de realizar simulacros periódicamente en sus establecimientos, de acuerdo a las disposiciones de la\nLey en la materia, en la que podrán participar elementos de la Dirección Estatal de\nProtección Civil del Estado.\nCAPÍTULO SEGUNDO\nDEL PERSONAL\nArtículo 23.- El personal administrativo o voluntario de las Instituciones de Asistencia\nSocial Privada, independientemente de su categoría y con el objeto del mejoramiento constante de sus funciones, deberá asistir a cursos, capacitaciones, exhibiciones, seminarios, conferencias, mesas de diálogo o diplomados, que en relación con cada una de sus áreas de trabajo organicen las Instituciones de Asistencia Social Privada y la\nProcuraduría de Protección.\nArtículo 24.- Para pertenecer al personal directivo, administrativo o voluntario de las\nInstituciones de Asistencia Social Privada será obligatorio cubrir los siguientes requisitos:\nPárrafo Reformado\nI. Contar con una edad mínima de 18 años cumplidos y un modo honesto de vivir;\nII. En caso de ser extranjero, comprobar legal estancia en el país de acuerdo a la función que desempeña dentro de la Institución de Asistencia Social Privada;\nIII. Acreditar el grado de estudios que solicite la propia Institución de Asistencia Social\nPrivada;\nIV. Acreditar evaluación de confiabilidad llevada a cabo por la Procuraduría de\nProtección o la institución o profesional que dicha dependencia designe, con el fin de integridad de niñas niños y adolescentes, bajo los principios de igualdad y no discriminación;\nFracción Reformada\nV. Presentar carta de no antecedentes penales; y\nVI. Las demás que requiera la propia Institución de Asistencia Social Privada.\nArtículo Reformado\nLey de Instituciones de Asistencia Social Privada para Niñas, Página 12\nArtículo 25.- Los directores, encargados y demás personal administrativo o voluntario seguridad física, psicológica y social de las niñas, niños y adolescentes que tengan bajo su guarda o custodia, así como del cumplimiento de las obligaciones a que se refiere esta Ley.\nArtículo 26.- La Procuraduría de Protección notificará a la Institución de Asistencia\nSocial Privada, cuando se estime que alguna persona que labore o preste servicios voluntarios no cuenta con los requisitos para ello, a fin de que tome las medidas pertinentes.\nEn dichos casos las Instituciones de Asistencia Social Privada a partir de la referida notificación impedirán al sujeto permanecer o ingresar al interior de las instalaciones y en general contacto alguno con las niñas, niños y adolescentes.\nTÍTULO SEXTO\nSITUACIÓN JURÍDICA Y EDUCACION DE LAS NIÑAS, NIÑOS Y ADOLESCENTES\nCAPÍTULO PRIMERO\nDE LA PROTECCIÓN Y SITUACIÓN JURÍDICA DE LOS NIÑAS NIÑOS Y\nADOLESCENTES\nArtículo 27.- En todo momento la Procuraduría de Protección tendrá el deber de velar por la atención y protección integral de las niñas, niños y adolescentes que estén a cargo de las Instituciones de Asistencia Social Privada.\nPara ello, las Instituciones de Asistencia Social Privada tendrán la obligación de notificar a la Procuraduría de Protección dentro de las 24 horas posteriores sobre los ingresos y egresos de las niñas, niños y adolescentes, sin perjuicio de la causa que lo origine.\nArtículo 28.- La Procuraduría de Protección ejercerá la tutela pública de las niñas, niños y adolescentes que se consideren expósitos o abandonados en los términos previstos del Código Civil para el Estado de Baja California, y demás disposiciones legales aplicables. administrativos que sean necesarios para regularizar la situación jurídica de las niñas, niños y adolescentes.\nArtículo Reformado\nArtículo 29.- Las personas que funjan como directores, titulares o encargados de las\nInstituciones de Asistencia Social Privada, están obligados a garantizar el efectivo cumplimiento de los derechos de las niñas, niños y adolescentes que estén bajo su guarda o\nLey de Instituciones de Asistencia Social Privada para Niñas, Página 13 custodia, de conformidad con lo establecido en esta Ley y demás ordenamientos aplicables, bajo los principios de igualdad y no discriminación.\nArtículo Reformado\nArtículo 30.- Cuando se ingrese a un menor a una Institución de Asistencia Social que medie autorización de la autoridad competente o por mandato judicial.\nExcepcionalmente, se concederá la entrega del menor sin orden judicial a quien detente la legal custodia, y previa autorización de la Procuraduría de Protección, sólo en los casos en que el ingreso del menor hubiere sido por solicitud voluntaria de quien tuviere la potestad legal para hacerlo, y para cuidado temporal de la Institución de Asistencia Social\nPrivada.\nArtículo 31.- En el caso de que una autoridad judicial o de procuración de justicia con residencia distinta a la del Estado pero dentro del territorio nacional requiera u ordene la presentación de un menor ingresado en una Institución de Asistencia Social Privada, ésta deberá previamente enterar a la Procuraduría de Protección para efecto de autentificar la referida orden, y una vez hecho lo anterior, podrá autorizar su traslado, debiéndosele asignar al menor la compañía de un adulto quien será responsable de su seguridad e integridad durante el tiempo que medie entre su salida y retorno a la Institución de Asistencia Social\nPrivada, y debiendo notificar a la Procuraduría de Protección dentro del plazo de setenta y dos horas, el debido cumplimiento de la medida.\nCAPÍTULO SEGUNDO\nDE LA EDUCACIÓN\nArtículo 32.- Las niñas, niños y adolescentes ingresados a las Instituciones de\nAsistencia Social Privada deberán ser inscritos y asistir al grado escolar que les corresponda.\nLos directores, responsables o encargados de las Instituciones de Asistencia Social planteles educativos que les asignen. La Procuraduría de Protección a través de la deberá coadyuvar y en su caso verificar el cumplimiento de esta disposición.\nArtículo 33.- Cuando las niñas, niños y adolescentes deba recibir educación especial, los directores, responsables o encargados de las Instituciones de Asistencia Social Privada, Ley de Instituciones de Asistencia Social Privada para Niñas, Página 14 requerida.\nTÍTULO SÉPTIMO\nArtículo 34.- La Procuraduría de Protección a través de la Coordinación vigilará e inspeccionará de manera periódica y en cualquier momento de manera extraordinaria cuando lo estime conveniente, el funcionamiento, en cumplimiento de ésta Ley, de los establecimientos pertenecientes a las Instituciones de Asistencia Social Privada, por medio del personal que para tal efecto autorice la propia Procuraduría de Protección.\nQuienes practiquen las diligencias de inspección y vigilancia deberán:\nI. Identificarse por medio del documento expedido por la Autoridad para tal fin; y dejar oficio de comisión correspondiente;\nII. Levantar el acta de visita domiciliaria e inspección, en la que se harán constar, en su caso, las irregularidades o violaciones a la presente Ley, a las Normas Oficiales\nMexicanas y demás ordenamientos aplicables;\nIII. Dictar las medidas cautelares de protección necesarias en los casos de que se adviertan irregularidades, omisiones o posibles actos delictivos;\nIV. Requerir al director o representante de la Institución de Asistencia Social Privada donde se practique la diligencia, que designe dos personas que funjan como testigos en el desarrollo de la misma, apercibiéndosele que en caso de no hacerlo, éstos serán designados por quien practique la misma;\nV. Entregar una copia legible del acta a la persona con quien se entienda la diligencia; y\nVI. Entregar a la Procuraduría de Protección la relación de actas de visita.\nArtículo 35.- Las medidas cautelares de protección que en el desarrollo de las visitas la Procuraduría de Protección podrá dictar, serán las siguientes:\nI. Sustraer de la custodia o guarda de la Institución de Asistencia Social Privada a uno o varias niñas, niños o adolescentes.\nLey de Instituciones de Asistencia Social Privada para Niñas, Página 15\nII. Ordenar que la Institución de Asistencia Social Privada suspenda temporalmente la relación del personal administrativo o voluntario.\nIII. Suspender la operación de la Institución de Asistencia Social Privada.\nIV. Intervención de la Institución de Asistencia Social Privada, la cual consistirá en temporal y solo podrá subsistir hasta en tanto se concluya la visita domiciliaria.\nEstas medidas deberán dictarse por escrito, de manera fundada y motivada y deberán ser proporcionales a la gravedad de la irregularidad, omisión o hechos advertidos en la visita.\nLa Procuraduría de Protección podrá solicitar el auxilio de la fuerza pública cuando se estime conveniente para cumplir con estas medidas.\nArtículo 36.- Las inspecciones periódicas deberán llevarse a cabo de conformidad con la planeación que para tales efectos determine la Procuraduría de Protección, la cuales deberán programarse por lo menos cada tres meses.\nArtículo Reformado\nArtículo 37.- Las actas de visita domiciliaria contendrán:\nI. Fecha en que se practique;\nII. Nombre o razón social y domicilio de la Institución de Asistencia Social Privada;\nIII. Fundamento legal y motivo de la misma;\nIV. Nombre y firma del representante legal; y\nV. Testigos y de quien la practique, quienes deberán estar plenamente identificados.\nConcluida la visita de inspección, debe darse oportunidad a la persona con la que se entendió la diligencia para manifestar lo que a su derecho convenga, en relación con los hechos asentados en el acta.\nSe procederá a la firma del acta con todos los que intervinieron en la diligencia, entregándose copia de la misma con quien se haya entendido la visita, en el entendido de que si alguna de las partes se negase a firmar o recibir el acta, tales circunstancias deberán asentarse en la misma, sin que tal omisión invalide el documento.\nLey de Instituciones de Asistencia Social Privada para Niñas, Página 16\nTÍTULO OCTAVO\nDE LAS SANCIONES\nArtículo 38.- En caso de incumplimiento por parte de las Instituciones de Asistencia\nSocial Privada de cualquiera de las disposiciones previstas en la presente Ley, la\nProcuraduría de Protección podrá aplicar las siguientes sanciones:\nI. Amonestación por escrito: Cuando las Instituciones de Asistencia Social Privada incumpla con cualquiera de las obligaciones establecidas en las fracciones II, III, IV, V, VII, VIII, XI, XIII, XIV, XV, XVI y XVIII del Artículo 9 de esta Ley;\nII. Clausura Temporal: Consistente en la suspensión de la operación y funcionamiento de Instituciones de Asistencia Social Privada y consecuentemente el retiro de las niñas, niños y adolescentes ingresados en las mismas por un lapso de hasta de seis meses como consecuencia del incumplimiento de cualquiera de las obligaciones establecidas en las fracciones I, VI, IX y X del Artículo 9 de esta Ley; así como por la acumulación de tres amonestaciones por escrito en un lapso de un año; y\nIII. Revocación de licencia: Consistente en la clausura definitiva de la operación de las\nInstituciones de Asistencia Social Privada como consecuencia del incumplimiento en cualquiera de las obligaciones establecidas en las fracciones XII y XVII del Artículo 9 de esta\nLey, así como por acumulación de dos clausuras temporales en un lapso de tres años.\nArtículo 39.- La determinación de las sanciones establecidas en el artículo anterior, la\nProcuraduría de Protección tomará en cuenta la gravedad de la infracción, las consecuencias derivadas de la misma, las circunstancias y antecedentes de las Instituciones de Asistencia Social Privada, la reincidencia en el incumplimiento de las obligaciones y el daño o perjuicio derivado del incumplimiento, tomando en cuenta los siguientes principios especiales:\nI. Debido procedimiento.- Las sanciones se aplicarán sujetándose al procedimiento establecido respetando las garantías del debido proceso.\nII. Razonabilidad.- Las autoridades deben prever que la comisión de la conducta asumir la sanción.\nIII. Reincidencia por incumplimiento de obligaciones derivadas de una sanción.- Para\nSocial Privada incurra en forma continua, se requiere que hayan transcurrido por lo menos\nLey de Instituciones de Asistencia Social Privada para Niñas, Página 17 treinta días hábiles desde la fecha de imposición de la última sanción, y se acredite haber solicitado al director, titular o responsable de la Institución de Asistencia Social Privada que demuestre que han cesado los motivos de la infracción dentro de dicho plazo.\nArtículo 40.- Para la aplicación de las sanciones establecidas en este título la\nProcuraduría de Protección iniciará de oficio el siguiente procedimiento:\nI. Con el acta de visita de inspección se dará la iniciación del procedimiento sancionador. La Procuraduría de Protección notificará a la Institución de Asistencia Social\nPrivada para que presente sus pruebas por escrito dentro de un plazo de cinco días hábiles;\nII. La Ley reconoce como medios de prueba:\na) Confesión y declaración de parte;\nb) Documentos públicos;\nc) Documentos privados;\nd) Dictámenes periciales;\ne) Reconocimiento o inspección de las Instalaciones de la Institución de Asistencia\nSocial Privada;\nf) Testigos;\ng) Fotografías, copias fotostáticas, cintas de vídeo, dispositivos de archivos electrónicos o magnéticos, y en general, todos aquellos elementos derivados de los avances de la ciencia y la tecnología; y\nh) Presunciones.\nIII. La Institución de Asistencia Social Privada tendrá la obligación de presentar sus propios testigos a lo cual deberá señalar sus domicilios. En caso de no asistir el testigo al desahogo de la prueba, sin causa justificada, ésta se declarará desierta;\nIV. Vencido dicho plazo de ofrecimiento de pruebas, la Procuraduría de Protección realizará de oficio todas las actuaciones necesarias para el desahogo de las pruebas, recabando los datos e informaciones que sean relevantes para determinar, en su caso, la existencia de responsabilidad susceptible de sanción;\nLey de Instituciones de Asistencia Social Privada para Niñas, Página 18\nV. Una vez concluido el desahogo de pruebas, se le dará vista a la Institución de alegatos, y concluido dicho plazo la Procuraduría de Protección resolverá en un término no mayor a quince días hábiles, la imposición de una sanción o la no existencia de infracción;\nVI. La resolución que aplique la sanción o la decisión de archivar el procedimiento será notificada al Director, titular o responsable de la Institución de Asistencia Social Privada;\nVII. La resolución será ejecutada de manera inmediata, incluso con el auxilio de la fuerza pública.\nTÍTULO NOVENO\nDE LA DEFENSA JURÍDICA DE LOS PARTICULARES\nArtículo 41.- Las resoluciones dictadas por la Procuraduría de Protección con motivo de la aplicación de la presente Ley podrán ser impugnadas ante el Tribunal de lo\nContencioso Administrativo del Estado.\nARTÍCULOS TRANSITORIOS\nPRIMERO.- El presente Decreto entrará en vigor a los 30 días siguientes al de su publicación en el Periódico Oficial del Estado.\nSEGUNDO.- Las Instituciones de Asistencia Social Privada que operen en el Estado de Baja California al momento de la entrada en vigor de este Decreto, deberán solicitar la licencia a que refiere el artículo 13 de esta Ley, en un plazo no mayor a 60 días naturales contados a partir del día siguiente de la entrada en vigor de este Decreto.\nAsimismo, las instituciones solicitantes tendrán hasta el 31 de diciembre de 2016 para cumplir con los requisitos exigidos por esta ley para la expedición de dichas licencias, cuando así lo hubiese requerido la autoridad, pudiendo concederse después de esa fecha hasta 90 días más, cuando excepcionalmente así lo determine la Procuraduría. instituciones solicitantes los requerimientos ordenados por la autoridad para su expedición.\nArtículo Transitorio Reformado\nTERCERO.- Para la implementación de esta Ley deberán realizarse las previsiones presupuestales necesarias.\nLey de Instituciones de Asistencia Social Privada para Niñas, Página 19 del Estado de Baja California, en la Ciudad de Mexicali, B.C., a los dieciséis días del mes de abril del año dos mil quince.\nDIP. LAURA LUISA TORRES RAMÍREZ\nVICEPRESIDENTE\n(RÚBRICA)\nDIP. ROSALBA LÓPEZ REGALADO\nSECRETARIA\n(RÚBRICA)\nDE CONFORMIDAD CON LO DISPUESTO POR LA FRACCION I DEL ARTÍCULO 49\nMEXICALI, BAJA CALIFORNIA, A LOS DIECISEIS DÍAS DEL MES DE ABRIL DEL\nAÑO DOS MIL QUINCE.\nFRANCISCO ARTURO VEGA DE LAMADRID\nGOBERNADOR DEL ESTADO\n(RÚBRICA)\nFRANCISCO RUEDA GOMEZ\nSECRETARIO GENERAL DE GOBIERNO\n(RÚBRICA)\nLey de Instituciones de Asistencia Social Privada para Niñas, Página 20\nArtículo 3.- Fue reformado mediante Decreto No. 418, publicado en el Periódico\nH. XXI Legislatura, siendo Gobernador Constitucional el C. Francisco Arturo Vega de\nLamadrid 2013-2019;\nArtículo 4.- Fue reformado por Decreto No. 277, publicado en el Periódico Oficial No.\n53, de fecha 08 de septiembre de 2023, Sección III, Tomo CXXX; expedido por la H. XXIV\nLegislatura, siendo Gobernadora Constitucional la C. Marina del Pilar Ávila Olmeda 20212027;\nArtículo 5.- Fue reformado por Decreto No. 277, publicado en el Periódico Oficial No.\n53, de fecha 08 de septiembre de 2023, Sección III, Tomo CXXX; expedido por la H. XXIV\nLegislatura, siendo Gobernadora Constitucional la C. Marina del Pilar Ávila Olmeda 20212027;\nArtículo 7.- Fue reformado por Decreto No. 277, publicado en el Periódico Oficial No.\n53, de fecha 08 de septiembre de 2023, Sección III, Tomo CXXX; expedido por la H. XXIV\nLegislatura, siendo Gobernadora Constitucional la C. Marina del Pilar Ávila Olmeda 20212027;\nArtículo 9.- Fue reformado por Decreto No. 277, publicado en el Periódico Oficial No.\n53, de fecha 08 de septiembre de 2023, Sección III, Tomo CXXX; expedido por la H. XXIV\nLegislatura, siendo Gobernadora Constitucional la C. Marina del Pilar Ávila Olmeda 20212027;\nArtículo 12.- Fue reformado por Decreto No. 374, publicado en el Periódico Oficial No.\n7, de fecha 09 de febrero de 2024, Índice, Tomo CXXXI, expedido por la H. XXIV\nLegislatura, siendo Gobernadora Constitucional la C. Marina del Pilar Ávila Olmeda, 20212027;\nArtículo 15.- Fue reformado por Decreto No. 277, publicado en el Periódico Oficial No.\nLegislatura, siendo Gobernadora Constitucional la C. Marina del Pilar Ávila Olmeda 20212027;\nArtículo 18.- Fue reformado mediante Decreto No. 198, publicado en el Periódico\nLegislatura, siendo Gobernadora Constitucional la C. Marina del Pilar Ávila Olmeda 20212027; fue reformado por Decreto No. 277, publicado en el Periódico Oficial No. 53, de fecha\nLey de Instituciones de Asistencia Social Privada para Niñas, Página 21 siendo Gobernadora Constitucional la C. Marina del Pilar Ávila Olmeda 2021-2027;\nArtículo 24.- Fue reformado por Decreto No. 277, publicado en el Periódico Oficial No.\nLegislatura, siendo Gobernadora Constitucional la C. Marina del Pilar Ávila Olmeda 20212027; fue reformado por Decreto No. 374, publicado en el Periódico Oficial No. 7, de fecha\n09 de febrero de 2024, Índice, Tomo CXXXI, expedido por la H. XXIV Legislatura, siendo\nGobernadora Constitucional la C. Marina del Pilar Ávila Olmeda, 2021-2027;\nArtículo 28.- Fue reformado mediante Decreto No. 418, publicado en el Periódico\nOficial No. 58, de fecha 18 de diciembre de 2015, Sección IV, Tomo CXXII, expedido por la\nH. XXI Legislatura, siendo Gobernador Constitucional el C. Francisco Arturo Vega de\nLamadrid 2013-2019;\nArtículo 29.- Fue reformado por Decreto No. 277, publicado en el Periódico Oficial No.\n53, de fecha 08 de septiembre de 2023, Sección III, Tomo CXXX; expedido por la H. XXIV\nLegislatura, siendo Gobernadora Constitucional la C. Marina del Pilar Ávila Olmeda 20212027;\nArtículo 36.- Fue reformado mediante Decreto No. 291, publicado en el Periódico expedido por la H. XXIII Legislatura, siendo Gobernador Constitucional el C. Jaime Bonilla\nValdez 2019-2021;\nARTÍCULO SEGUNDO TRANSITORIO DE LA LEY.- Fue reformado mediante\nDecreto No. 537, publicado en el Periódico Oficial No. 40, de fecha 02 de septiembre de\n2016, Tomo CXXIII, Sección I, expedido por la H. XXI Legislatura, siendo Gobernador\nConstitucional el C. Francisco Arturo Vega de Lamadrid 2013-2019;\nLey de Instituciones de Asistencia Social Privada para Niñas, Página 22\nARTÍCULO UNICO TRANSITORIO DEL DECRETO No. 418, POR EL QUE SE\nREFORMAN LOS ARTÍCULOS 3 Y 28, PUBLICADO EN EL PERIÓDICO OFICIAL No. 58,\nH. XXI LEGISLATURA, SIENDO GOBERNADOR CONSTITUCIONAL EL C. FRANCISCO\nARTURO VEGA DE LAMADRID 2013-2019.\nARTÍCULO TRANSITORIO\nÚNICO.- El presente Decreto entrará en vigor al día siguiente de su publicación en el\nPeriódico Oficial del Estado.\nDADO en el Salón de Sesiones “Lic. Benito Juárez García” del H. Poder Legislativo del Estado de Baja California, en la Ciudad de Mexicali, B.C., a los tres días del mes de diciembre del año dos mil quince.\nDIP. IRMA MARTÍNEZ MANRÍQUEZ\nPRESIDENTA\n(RÚBRICA)\nDIP. MARIO OSUNA JIMÉNEZ\nSECRETARIO\n(RÚBRICA)\nDE CONFORMIDAD CON LO DISPUESTO POR LA FRACCION I DEL ARTÍCULO 49\nMEXICALI, BAJA CALIFORNIA, A LOS ONCE DÍAS DEL MES DE DICIEMBRE DEL\nAÑO DOS MIL QUINCE.\nFRANCISCO ARTURO VEGA DE LAMADRID\nGOBERNADOR DEL ESTADO\n(RÚBRICA)\nFRANCISCO RUEDA GOMEZ\nSECRETARIO GENERAL DE GOBIERNO\n(RÚBRICA)\nLey de Instituciones de Asistencia Social Privada para Niñas, Página 23\nARTÍCULO ÚNICO TRANSITORIO DEL DECRETO No. 537, POR EL QUE SE\nREFORMA EL ARTÍCULO SEGUNDO TRANSITORIO; PUBLICADO EN EL PERIÓDICO\nEXPEDIDO POR LA H. XXI LEGISLATURA, SIENDO GOBERNADOR CONSTITUCIONAL\nEL C. FRANCISCO ARTURO VEGA DE LA MADRID 2013-2019.\nARTÍCULO TRANSITORIO\nÚNICO.- El presente Decreto entrará al día siguiente de su publicación en el Periódico\nOficial del Estado.\nDADO en el Salón de Sesiones “Lic. Benito Juárez García” del H. Poder Legislativo del Estado de Baja California, en la Ciudad de Mexicali, B.C., a los catorce días del mes de julio del año dos mil dieciséis.\nDIP. MÓNICA BEDOYA SERNA\nPRESIDENTA\n(RÚBRICA)\nDIP. ROSA ISELA PERALTA CASILLAS\nSECRETARIA\n(RÚBRICA)\nDE CONFORMIDAD CON LO DISPUESTO POR LA FRACCIÓN I DEL ARTÍCULO 49\nMEXICALI, BAJA CALIFORNIA, A LOS 11 DÍAS DEL MES DE AGOSTO DEL AÑO\nDOS MIL DIECISÉIS.\nFRANCISCO ARTURO VEGA DE LAMADRID\nGOBERNADOR DEL ESTADO\n(RÚBRICA)\nFRANCISCO RUEDA\nSECRETARIO GENERAL DE GOBIERNO\n(RÚBRICA)\nARTÍCULO ÚNICO TRANSITORIO DEL DECRETO No. 291, POR EL QUE SE\nREFORMA EL ARTÍCULO 36; PUBLICADO EN EL PERIÓDICO OFICIAL No. 69, Ley de Instituciones de Asistencia Social Privada para Niñas, Página 24\nEXPEDIDO POR LA H. XXIII LEGISLATURA, SIENDO GOBERNADOR CONSTITUCIONAL\nEL C. JAIME BONILLA VALDEZ 2019-2021.\nARTÍCULO TRANSITORIO\nÚNICO.- La presente reforma entrará al día siguiente de su publicación en el\nPeriódico Oficial del Estado.\nDADO en el Salón de Sesiones Benito Juárez García en Sesión Ordinaria de la XIII\nLegislatura en la Ciudad de Mexicali, B.C., a los veintiocho días del mes de julio del año dos mil veintiuno.\nDIP. EVA GRICELDA RODRÍGUEZ\nPRESIDENTA\n(RÚBRICA)\nDIP. MARÍA LUISA VILLALOBOS ÁVILA\nSECRETARIA\n(RÚBRICA)\nDE CONFORMIDAD CON LO DISPUESTO POR LA FRACCIÓN I DEL ARTÍCULO 49\nCALIFORNIA, IMPRÍMASE Y PUBLÍQUESE.\nMEXICALI, BAJA CALIFORNIA, A LOS TRES DÍAS DEL MES DE AGOSTO DEL\nAÑO DOS MIL VEINTIUNO.\nJAIME BONILLA VALDEZ\nGOBERNADOR DEL ESTADO\n(RÚBRICA)\nAMADOR RODRÍGUEZ LOZANO\nSECRETARIO GENERAL DE GOBIERNO\n(RÚBRICA)\nARTÍCULO QUINTO TRANSITORIO DEL DECRETO No. 198, POR EL QUE SE\nREFORMA EL ARTÍCULO 18; PUBLICADO EN EL PERIÓDICO OFICIAL No. 6, ÍNDICE,\nLEGISLATURA, SIENDO GOBERNADORA CONSTITUCIONAL LA C. MARINA DEL PILAR\nÁVILA OLMEDA 2021-2027.\nLey de Instituciones de Asistencia Social Privada para Niñas, Página 25\nTRANSITORIOS\nÚNICO. El presente Decreto entrará en vigor al día siguiente de su publicación en el\nPeriódico Oficial del Estado.\nDADO en Sesión Ordinaria de la XXIV Legislatura en la Ciudad de Mexicali, B.C., a los doce días del mes de enero del año dos mil veintitrés.\nDIP. MARÍA DEL ROCÍO ADAME MUÑOZ\nPRESIDENTA\n(RÚBRICA)\nDIP. DUNNIA MONTSERRAT MURILLO LÓPEZ\nSECRETARIA\n(RÚBRICA)\nDE CONFORMIDAD CON LO DISPUESTO POR LA FRACCIÓN I DEL ARTÍCULO 49\nCALIFORNIA, IMPRÍMASE Y PUBLÍQUESE.\nMEXICALI, BAJA CALIFORNIA, A LOS TRECE DÍAS DEL MES DE ENERO DEL\nAÑO DOS MIL VEINTITRÉS.\nMARINA DEL PILAR ÁVILA OLMEDA\nGOBERNADORA DEL ESTADO\nDE BAJA CALIFORNIA\n(RÚBRICA)\nCATALINO ZAVALA MÁRQUEZ\nSECRETARIO GENERAL DE GOBIERNO\nDEL ESTADO DE BAJA CALIFORNIA\n(RÚBRICA)\nARTÍCULO ÚNICO TRANSITORIO DEL DECRETO No. 277, POR EL QUE SE\nREFORMA A LOS ARTÍCULOS 4, 5, 7, 9, 15, 18, 24 y 29; PUBLICADO EN EL PERIÓDICO\nEXPEDIDO POR LA H. XXIV LEGISLATURA, SIENDO GOBERNADORA\nCONSTITUCIONAL LA C. MARINA DEL PILAR ÁVILA OLMEDA 2021-2027.\nTRANSITORIO\nÚNICO. El presente decreto entrará en vigor el día siguiente al de su publicación en el\nPeriódico Oficial del Estado de Baja California.\nLey de Instituciones de Asistencia Social Privada para Niñas, Página 26\nDADO en Sesión Ordinaria de la XXIV Legislatura en la Ciudad de Mexicali, B.C., a los veinticuatro días del mes de agosto del año dos mil veintitrés.\nDIP. MANUEL GUERRERO LUNA\nPRESIDENTE\n(RÚBRICA)\nDIP. DUNNIA MONTSERRAT MURILLO LÓPEZ\nSECRETARIA\n(RÚBRICA)\nDE CONFORMIDAD CON LO DISPUESTO POR LA FRACCIÓN I DEL ARTÍCULO 49\nBAJA CALIFORNIA, IMPRÍMASE Y PUBLÍQUESE.\nMEXICALI, BAJA CALIFORNIA, A LOS VEINTIOCHO DÍAS DEL MES DE AGOSTO\nDEL AÑO DOS MIL VEINTITRÉS.\nMARINA DEL PILAR ÁVILA OLMEDA\nGOBERNADOR DEL ESTADO\nDE BAJA CALIFORNIA\n(RÚBRICA)\nCATALINO ZAVALA MÁRQUEZ\nSECRETARIO GENERAL DE GOBIERNO\nDEL ESTADO DE BAJA CALIFORNIA\n(RÚBRICA)\nARTÍCULO ÚNICO TRANSITORIO DEL DECRETO No. 374, POR EL QUE SE\nAPRUEBAN LAS REFORMAS A LOS ARTÍCULOS 12 Y 24; PUBLICADO EN EL\nPERIÓDICO OFICIAL No. 7, DE FECHA 09 DE FEBRERO DE 2024, ÍNDICE, TOMO\nCXXXI, EXPEDIDO POR LA H. XXIV LEGISLATURA, SIENDO GOBERNADORA\nCONSTITUCIONAL LA C. MARINA DEL PILAR ÁVILA OLMEDA 2021-2027.\nTRANSITORIOS\nÚNICO.- El presente decreto entrará en vigor al día siguiente de su publicación en el\nPeriódico Oficial del Estado de Baja California.\nDADO en Sesión Ordinaria de la XXIV Legislatura en la Ciudad de Mexicali, B.C., a los veinticinco días del mes de enero del año dos mil veinticuatro.\nDIP. ARACELI GERALDO NÚÑEZ\nPRESIDENTA\n(RÚBRICA)\nLey de Instituciones de Asistencia Social Privada para Niñas, Página 27\nDIP. MANUEL GUERRERO LUNA\nSECRETARIO\n(RÚBRICA)\nDE CONFORMIDAD CON LO DISPUESTO POR LA FRACCIÓN I DEL ARTÍCULO 49 DE\nCALIFORNIA, IMPRÍMASE Y PUBLÍQUESE.\nMEXICALI, BAJA CALIFORNIA, A LOS VEINTINUEVE DÍAS DEL MES DE ENERO\nDEL AÑO DOS MIL VEINTICUATRO.\nMARINA DEL PILAR ÁVILA OLMEDA\nGOBERNADORA DEL ESTADO\nDE BAJA CALIFORNIA\n(RÚBRICA)\nALFREDO ÁLVAREZ CÁRDENAS\nSECRETARIO GENERAL DE GOBIERNO\nDEL ESTADO DE BAJA CALIFORNIA\n(RÚBRICA)\nLey de Instituciones de Asistencia Social Privada para Niñas, Página 28",
  "ordenamiento": "REGLAMENTO",
  "jurisdiccion": "BAJA CALIFORNIA",
  "fuente_oficial": "Periódico Oficial",
  "FECHA PER OFIC": "2024/02/09",
  "ESTATUS": "VIGENTE",
  "TOMO": "TOMO_VI",
  "URL": "https://www.congresobc.gob.mx/Documentos/ProcesoParlamentario/Leyes/TOMO_VI/20240209_LEYINSASISOCPRIV.PDF",
  "es_escaneado": false,
  "tiene_tablas": false,
  "materia": [
    "social",
    "salud",
    "educación",
    "cultura"
  ]
}