{
  "titulo": "Ley DE LA POLICÍA ESTATAL PREVENTIVA DE BAJA CALIFORNIA",
  "Contenido": "LEY DE LA POLICÍA ESTATAL PREVENTIVA\nDE BAJA CALIFORNIA\nPublicado en el Periódico Oficial No. 41, Tomo CXVII, Sección IV,\nCAPÍTULO PRIMERO\nDISPOSICIONES GENERALES\nArtículo 1.- La presente Ley es de orden público, interés general y de aplicación en todo el territorio del Estado de Baja California y tiene por objeto regular la organización y funcionamiento de la Policía Estatal Preventiva, en los términos de la Constitución Política de los Estados Unidos Mexicanos, de la\nGeneral del Sistema Nacional de Seguridad Pública, la Ley de Seguridad Pública del Estado de Baja California y demás relativas.\nArtículo 2.- La Policía Estatal Preventiva, es una institución policial dependiente de la Secretaría de Seguridad Pública del Estado de Baja California y sus objetivos serán los siguientes:\nI.- Salvaguardar la vida, la integridad, la seguridad y los derechos de las personas, como preservar las libertades, el orden y la paz públicos;\nII.- Aplicar y operar la política policial de seguridad pública en materia de prevención y combate de delitos, que diseñe la Secretaría;\nIII.- Prevenir la comisión de los delitos, y\nIV.- Investigar la comisión de delitos bajo la conducción y mando del\nMinisterio Público en los términos de las disposiciones aplicables.\nArtículo 3.- Serán principios rectores en el ejercicio de las funciones y acciones que en materia de prevención, combate e investigación de los delitos le competen a la Policía Estatal Preventiva, los de legalidad, objetividad, eficiencia, Mexicanos.\nArtículo 4.- Para los efectos de esta Ley, se entenderá por:\nI.- Academia: La Academia de Seguridad Pública del Estado de Baja\nCalifornia;\nLey de la Policía Estatal Preventiva de Baja California Página 1\nII.- Aspirante: Persona física que tramite su ingreso como Miembro a la nombramiento respectivo, quien podrá ser considerado a ingresar a dicha institución policial, siempre y cuando cumpla con los requisitos y demás\nCalifornia, la presente Ley, su Reglamento y demás disposiciones aplicables;\nIII.- Centro de Control de Confianza: El Centro de Evaluación y Control de\nConfianza del Estado de Baja California;\nIV.- Comisión: La Comisión de Desarrollo Policial de la Secretaría de\nSeguridad Pública del Estado de Baja California;\nV.- Comisario General: Quien ejerce el mando y dirección en la organización jerárquica de la Policía Estatal Preventiva de Baja California;\nVI.- Carrera Policial: El servicio de carrera policial de la Policía Estatal\nPreventiva de Baja California;\nVII.- Institución Policial: La Policía Estatal Preventiva de Baja California;\nVIII.- Ley: Ley de la Policía Estatal Preventiva de Baja California;\nIX.- Ley de Seguridad Pública: Ley de Seguridad Pública del Estado de Baja\nCalifornia;\nX.- Ley General: La Ley General del Sistema Nacional de Seguridad\nPública;\nXI.- Miembro: Elemento de la Policía Estatal Preventiva de Baja California;\nXII.- Reglamento: El Reglamento de la presente Ley;\nXIII.- Secretaría: Secretaría de Seguridad Pública del Estado de Baja\nCalifornia, y\nXIV.- Secretario: El titular de la Secretaría de Seguridad Pública del Estado de Baja California.\nArtículo 5.- La investigación para la prevención de los delitos, en términos de los artículos 16 y 21 de la Constitución Política de los Estados Unidos\nMexicanos, es el conjunto sistematizado de acciones y procedimientos encaminados a la planeación, obtención, procesamiento y aprovechamiento de la información, con el propósito exclusivo de evitar la comisión de delitos, con base en los principios de legalidad, objetividad, eficiencia, profesionalismo, honradez y\nLey de la Policía Estatal Preventiva de Baja California Página 2\nConstitución referida.\nArtículo 6.- Para el mejor ejercicio de sus atribuciones, la Institución\nPolicial, por conducto del Secretario, podrá suscribir convenios o instrumentos organizaciones no gubernamentales en el marco de la ley, así también, con autoridades o instituciones extranjeras.\nCAPÍTULO SEGUNDO\nDE LAS ATRIBUCIONES DE LA INSTITUCIÓN POLICIAL\nArtículo 7.- La Institución Policial tendrá las atribuciones y obligaciones siguientes:\nI.- Implementar las políticas, programas y estrategias para la prevención del delito que para tal efecto diseñe la Secretaría;\nII.- Prevenir la comisión de delitos y las faltas administrativas que determinen las leyes estatales y federales;\nIII.- Implementar programas de inteligencia y prevención en las zonas de mayor incidencia delictiva;\nIV.- Intervenir en materia de seguridad pública, en coadyuvancia con las autoridades competentes, en la observancia y cumplimiento de las leyes;\nV.- Salvaguardar la integridad de las personas, así como garantizar, mantener y restablecer el orden y la paz públicos;\nVI.- Realizar investigación para la prevención de los delitos en los términos de las disposiciones aplicables;\nVII.- Recabar información en lugares públicos, para evitar el fenómeno delictivo, mediante la utilización de medios e instrumentos y cualquier herramienta que resulten necesarias para la generación de inteligencia preventiva. En el derechos humanos;\nVIII.- Llevar a cabo operaciones encubiertas para la prevención de delitos. ejercicio de esta atribución;\nIX.- Realizar análisis técnico táctico o estratégico de la información obtenida para la generación de inteligencia;\nLey de la Policía Estatal Preventiva de Baja California Página 3\nX.- Realizar bajo la conducción y mando del Ministerio Público las investigaciones de los delitos cometidos, así como las actuaciones que le instruya éste o la autoridad jurisdiccional conforme a las normas aplicables;\nXI.- Informar a la persona al momento de su detención sobre los derechos\nMexicanos;\nXII.- Poner, sin demora, a disposición de las autoridades competentes, a personas y bienes en los casos en que por motivo de sus funciones se practique alguna detención o se lleve a cabo algún aseguramiento de bienes, observando en todo momento el cumplimiento de los plazos constitucionales y legales establecidos;\nXIII.- Verificar la información que reciba sobre hechos que puedan ser constitutivos de delito para, en su caso, remitirla al Ministerio Público;\nXIV.- Recibir las denuncias sobre hechos que puedan ser constitutivos de delitos, en términos de lo dispuesto por la normatividad aplicable;\nXV.- Participar en la investigación ministerial, en la detención de personas y en el aseguramiento de bienes que el Ministerio Público considere se encuentren relacionados con los hechos delictivos, así como practicar las diligencias necesarias que permitan el esclarecimiento de los delitos y la identidad de los probables responsables, en cumplimiento de los mandatos del Ministerio Público;\nXVI.- Efectuar las detenciones conforme lo dispuesto en el artículo 16 de la aplicables;\nXVII.- Inscribir de inmediato la detención que realice en el Registro\nAdministrativo de Detenciones, en los términos de la Ley de Seguridad Pública, así como remitir sin demora y por cualquier medio, la información al Ministerio\nPúblico;\nXVIII.- Preservar el lugar de los hechos y la integridad de los indicios, huellas o vestigios del hecho delictuoso, así como los instrumentos, objetos o productos del delito, dando aviso de inmediato al Ministerio Público. Las unidades facultadas para el procesamiento del lugar de los hechos, deberán fijar, señalar, levantar, embalar y entregar la evidencia física al Ministerio Público, conforme al aplicables;\nXIX.- Solicitar al Ministerio Público que requiera a las autoridades competentes, informes y documentos para fines de la investigación;\nLey de la Policía Estatal Preventiva de Baja California Página 4\nXX.- Garantizar que se asiente constancia de cada una de sus actuaciones, así como llevar un control y seguimiento de éstas. Durante el curso de la y rendirlos al Ministerio Público, sin perjuicio de los informes que éste le requiera;\nXXI.- Emitir los informes, partes policiales y demás documentos que se generen, con los requisitos de fondo y forma que establezcan las disposiciones aplicables, para tal efecto se podrán apoyar en los conocimientos que resulten necesarios;\nXXII.- Proporcionar atención a víctimas, ofendidos o testigos del delito; para tal efecto deberá:\na) Prestar protección y auxilio inmediato, de conformidad con las disposiciones legales aplicables;\nb) Procurar que reciban atención médica cuando sea necesaria;\nc) Adoptar las medidas que se consideren necesarias tendentes a evitar que se ponga en peligro su integridad física y psicológica, en el ámbito de su competencia;\nd) Preservar los indicios y elementos de prueba que la víctima y ofendido aporten en el momento de la intervención policial y remitirlos sin demora al\nMinisterio Público encargado del asunto para que éste acuerde lo conducente, y\ne) Asegurar que los Miembros puedan llevar a cabo la identificación del imputado sin riesgo para ellos.\nXXIII.- Dar cumplimiento a las órdenes de aprehensión y demás mandatos ministeriales y jurisdiccionales de que tenga conocimiento con motivo de sus funciones;\nXXIV.- Entrevistar a las personas que pudieran aportar algún dato o elemento para la investigación en caso de flagrancia o por mandato del Ministerio\nPúblico, en términos de las disposiciones aplicables. De las entrevistas que se investigación, que para tener valor probatorio, deberán ser ratificadas ante la autoridad ministerial o judicial que corresponda;\nXXV.- Reunir la información que pueda ser útil al Ministerio Público que conozca del asunto, para acreditar el cuerpo del delito y la probable responsabilidad del imputado, conforme a las instrucciones de aquél;\nXXVI.- Incorporar y consultar en las bases de datos de la Institución Policial y del Sistema Estatal de Información sobre Seguridad Pública, la información que\nLey de la Policía Estatal Preventiva de Baja California Página 5 desempeño de sus atribuciones, en términos de la normatividad aplicable;\nXXVII.- Coordinarse en los términos que señala la Ley General y la Ley de\nSeguridad Pública, con las autoridades de los tres órdenes de gobierno, para el intercambio de información en materia de seguridad pública, con las limitaciones establecidas en las leyes correspondientes;\nXXVIII.- Colaborar, cuando sean formalmente requerida, de conformidad con los ordenamientos constitucionales y legales aplicables, con las autoridades locales y municipales competentes, en la protección de la integridad física de las personas y en la preservación de sus bienes, en situaciones de peligro, cuando se vean amenazadas por situaciones que impliquen violencia o riesgo inminente;\nXXIX.- Participar en operativos conjuntos con autoridades federales, locales o municipales, que se lleven a cabo conforme a lo dispuesto en la normatividad aplicable;\nXXX.- Obtener, analizar y procesar información, así como realizar las acciones que, conforme a las disposiciones aplicables, resulten necesarias para la prevención de delitos, sea directamente o mediante los sistemas de coordinación previstos en esta Ley y otras leyes;\nXXXI.- Vigilar, supervisar, asegurar y custodiar, a solicitud de la autoridad competente, las instalaciones de los centros dependientes de la Subsecretaría del\nSistema Estatal Penitenciario de la Secretaría; así como en el traslado de internos, con apego a los derechos humanos reconocidos en la Constitución Política de los\nEstados Unidos Mexicanos;\nXXXII.- Estudiar, planificar y ejecutar los métodos y técnicas de combate a la delincuencia;\nXXXIII.- Realizar acciones de vigilancia, identificación, monitoreo y rastreo en la Red Pública de Internet sobre sitios web con el fin de prevenir conductas delictivas;\nXXXIV.- Desarrollar, mantener y supervisar fuentes de información en la sociedad, que permitan obtener datos sobre actividades relacionadas con fenómenos delictivos;\nXXXV.- Integrar en el Registro Administrativo de Detenciones y demás\nSeguridad Pública a que se refiere la Ley de Seguridad Pública, las huellas dactilares y cualquier otro medio de identificación de una persona, solicitando a las cuenten, así como de organismos no gubernamentales;\nLey de la Policía Estatal Preventiva de Baja California Página 6\nXXXVI.- Solicitar a la autoridad competente en los términos del artículo 16 permisionarios, operadoras telefónicas y todas aquellas comercializadoras de satélite, la información con que cuenten así como georeferenciación de los equipos de comunicación móvil en tiempo real, para el cumplimiento de sus fines de prevención de los delitos;\nXXXVII.- Solicitar a la autoridad competente en los términos del artículo 16 de la Constitución Política de los Estados Unidos Mexicanos, la autorización para la intervención de comunicaciones privadas para la investigación de los delitos;\nXXXVIII.- Resguardar, proteger y supervisar las acciones necesarias para la vigilancia de las instalaciones, inmuebles, muebles, equipos y demás bienes destinados al funcionamiento y operación de las actividades de la Secretaría, a efecto de garantizar su integridad y operación, y\nXXXIX. Las demás que le confieran ésta y otras leyes.\nArtículo 8.- La Institución Policial ejercerá las atribuciones que establece esta Ley en todo el territorio del Estado de Baja California, con estricto respeto a las que corresponden a las competencias de las demás instituciones policiales a que se refiere la Ley General y Ley de Seguridad Pública.\nCAPÍTULO TERCERO\nDE LA COMISARÍA GENERAL\nArtículo 9.- El Comisario General tendrá el más alto rango en la organización jerárquica de la Institución Policial, sobre la cual ejercerá las atribuciones de mando, dirección y disciplina. Será nombrado y removido libremente por el Secretario.\nArtículo 10.- Para ser Comisario General se deberán reunir los siguientes requisitos:\nI.- Ser ciudadano mexicano por nacimiento, que no tenga otra nacionalidad, en pleno ejercicio de sus derechos políticos y civiles;\nII.- Tener cuando menos treinta años el día de la designación;\nIII.- Contar con título de estudios superiores debidamente registrado;\nIV.- Acreditar los procedimientos de evaluación y control de confianza;\nLey de la Policía Estatal Preventiva de Baja California Página 7\nV.- Tener reconocida capacidad y probidad, no haber sido sentenciado por delito doloso, ni estar sujeto a proceso penal o averiguación previa;\nVI.- Comprobar una experiencia mínima de cinco años en labores vinculadas con la seguridad pública;\nVII.- No estar o haber estado suspendido o inhabilitado, ni haber sido destituido por resolución firme como servidor público, y\nVIII.- Las demás que señalen las Leyes y Reglamentos correspondientes.\nArtículo 11.- Son facultades y obligaciones del Comisario General:\nI.- Acatar las instrucciones que al efecto le gire el Secretario;\nII.- Tener el mando directo de la Institución Policial;\nIII.- Ejecutar las correcciones disciplinarias y de control de la Institución\nPolicial;\nIV.- Proponer al Secretario la adopción de políticas, programas y estrategias en materia policial, que ayuden a la prevención del delito;\nV.- Informar periódicamente al Secretario o cuando sea requerido por este, sobre el desempeño de las atribuciones de la Institución Policial y de los resultados alcanzados;\nVI.- Vigilar, en el área de su competencia, el cumplimiento de las disposiciones legales y administrativas en materia de protección de derechos humanos;\nVII.- Autorizar, previo acuerdo con el Secretario, operaciones encubiertas para desarrollar labores de inteligencia para la prevención de delitos, en los términos de esta Ley y las demás disposiciones aplicables;\nVIII.- Solicitar al titular del Ministerio Público del Estado, previo acuerdo con el Secretario, la intervención de comunicaciones privadas; así como, a la autoridad competente, información de los concesionarios permisionarios, operadoras telecomunicaciones de sistemas de comunicación vía satélite, así como georeferenciación de los equipos de comunicación móvil en tiempo real, para el cumplimiento de sus fines de prevención de los delitos, en los términos de la presente Ley y las demás disposiciones aplicables;\nIX.- Ejercer debidamente, los recursos que se asignen para la operación y funcionamiento de la Institución Policial;\nLey de la Policía Estatal Preventiva de Baja California Página 8\nX.- Coordinarse con la Academia, para la promoción y realización de cursos, seminarios o eventos que redunden en la capacitación permanente de sus\nMiembros;\nXI.- Promover con instituciones policiales, nacionales y extranjeras, el intercambio de experiencias, estrategias y capacitación;\nXII.- Proponer al Secretario, los anteproyectos de reglamentos, acuerdos y demás normas administrativas para el buen funcionamiento de la Institución\nPolicial;\nXIII.- Proponer al Secretario, los nombramientos de los demás Comisarios de la Institución Policial, de acuerdo a lo establecido en la Ley de Seguridad\nPública, esta Ley y demás normatividad aplicable;\nXIV.- Proponer al Secretario, a los Miembros en cargos administrativos o de dirección de la estructura orgánica de la Institución Policial y relevarlos libremente de los mismos, respetando su grado policial y derechos inherentes a la carrera policial;\nFracción Reformada\nXV.- Verificar que las patrullas de la Institución Policial:\na) Se utilicen correctamente;\nb) Se encuentren debidamente balizadas;\nc) Cuenten con copia de la tarjeta de circulación y con la póliza de seguro respectiva;\nd) Porten las placas de circulación que les correspondan;\ne) Cumplan con las demás disposiciones que resulten aplicables; y\nFracción Adicionada Recorriéndose la subsecuente\nXVI.- Las demás que las leyes y otras disposiciones aplicables le confieran.\nFracción Adicionada\nArtículo Reformado\nCAPĺTULO CUARTO\nSECCIÓN I\nDE LA ORGANIZACIÓN JERÁRQUICA\nArtículo 12.- La Institución Policial considerará para su organización jerárquica, al menos las siguientes categorías:\nI. Comisarios;\nLey de la Policía Estatal Preventiva de Baja California Página 9\nII. Inspectores;\nIII. Oficiales, y\nIV. Escala básica.\nArtículo 13.- Las categorías previstas en el artículo anterior considerarán, al menos, las siguientes jerarquías:\nI. Comisarios:\na) Comisario General;\nb) Comisario Jefe, y\nc) Comisario.\nII. Inspectores:\na) Inspector General;\nb) Inspector Jefe, y\nc) Inspector.\nIII. Oficiales:\na) Subinspector;\nb) Oficial, y\nc) Suboficial.\nIV. Escala básica:\na) Policía Primero;\nb) Policía Segundo;\nc) Policía Tercero, y\nd) Policía.\nLey de la Policía Estatal Preventiva de Baja California Página 10\nArtículo 14.- La categoría de Comisarios y sus jerarquías, serán de libre designación y remoción por parte del Secretario, para asegurar la adecuada coordinación con los altos mandos, a partir de principios de confianza y experiencia.\nArtículo 15.- La Institución Policial se organizará operativamente bajo un esquema de jerarquización terciaria, cuya célula básica se compondrá invariablemente por tres elementos, de acuerdo a la normatividad aplicable.\nLa Institución Policial deberá de satisfacer, como mínimo, el mando correspondiente al octavo grado ascendente de la organización jerárquica.\nLos titulares de las categorías jerárquicas estarán facultados para ejercer la autoridad y mando policial en los diversos cargos o comisiones.\nSECCIÓN II\nDEL MANDO\nArtículo 16.- Se entenderá por mando a la autoridad ejercida por un superior jerárquico en servicio activo, sobre sus inferiores o iguales en jerarquía, cuando estos se encuentren subordinados a él en razón de su grado, cargo o comisión.\nArtículo 17.- El mando podrá ser ejercido en las formas siguientes:\nI. Titular.- Que es ejercido por medio de nombramiento oficial expedido por la autoridad correspondiente;\nII. Circunstancial.- En los casos siguientes: a. Interino.- El designado con ese carácter por la superioridad correspondiente hasta en tanto se nombra titular; b. Accidental.- El que se ejerce por ausencia temporal del titular que le impida desempeñarlo, en caso de enfermedad, licencias, vacaciones, comisiones fuera de su adscripción u otros motivos, y c. Incidental.- El que se desempeña en casos imprevistos por ausencia momentánea del titular o de quien ejerza el mando. mando, salvo en aquellas situaciones especiales.\nSECCIÓN III\nDE LA ESTRUCTURA FUNCIONAL\nLey de la Policía Estatal Preventiva de Baja California Página 11\nArtículo 18.- La Institución Policial, para el mejor cumplimiento de sus objetivos, establecerá cuando menos, las siguientes funciones:\nI.- Investigación, que será la encargada de la investigación a través de sistemas homologados de recolección, clasificación, registro, análisis y evaluación de información;\nII.- Prevención, que será la encargada de prevenir la comisión de delitos e infracciones administrativas, realizar las acciones de inspección, vigilancia y vialidad en su circunscripción; y\nIII.- Reacción, que será la encargada de garantizar, mantener y restablecer el orden y la paz públicos.\nArtículo 19.- La Institución Policial, para el cumplimiento de lo establecido en el artículo que antecede, contará con las unidades operativas y agrupamientos que se determinen en el Reglamento de la presente Ley.\nSECCIÓN IV\nDE LA ORGANIZACIÓN TERRITORIAL\nArtículo 20.- Para el adecuado funcionamiento de la Institución Policial, se establecerán en el territorio del Estado, bases operativas, destacamentos, delegaciones o aquellas instalaciones que determine el Reglamento, de acuerdo a las necesidades del servicio y disponibilidad presupuestal.\nArtículo 21.- Las instalaciones tendrán carácter estratégico, por lo que dispondrán de los sistemas de vigilancia y seguridad permanente.\nArtículo 22.- La Institución Policial en cualquier tiempo podrá hacer las modificaciones que estime convenientes a su organización territorial, de acuerdo a las necesidades del servicio.\nCAPÍTULO QUINTO\nDEL AUXILIO A LA INSTITUCIÓN POLICIAL\nArtículo 23.- En los casos en que resulte necesario, la Institución Policial podrá auxiliarse con:\nI. El personal técnico especializado de la Secretaría;\nII. Las instituciones policiales a que se refiere el artículo 7 de la Ley de\nSeguridad Pública, y\nIII. Los auxiliares de las instituciones policiales, a que se refiere el artículo 8 de la Ley de Seguridad Pública.\nLey de la Policía Estatal Preventiva de Baja California Página 12\nCAPÍTULO SEXTO\nDE LA COORDINACIÓN Y COOPERACIÓN\nCON EL MINISTERIO PÚBLICO\nArtículo 24.- En sus funciones de investigación y combate a los delitos, la\nInstitución Policial actuará bajo el mando y conducción del Ministerio Público, con las formalidades necesarias para que los resultados de tales actuaciones puedan presentarse como evidencia ante los tribunales.\nArtículo 25.- Cuando durante el desarrollo de la investigación ministerial la\nInstitución Policial estime necesaria la realización de diligencias que requieran una tramitación especial o la autorización de la autoridad jurisdiccional, lo comunicará sin demora al Ministerio Público quien resolverá lo conducente.\nArtículo 26.- Si se tratare de delito flagrante, la Institución Policial dictará las medidas y providencias necesarias para el debido cumplimiento de lo que en materia de preservación de indicios dispone el Código de Procedimientos Penales para el Estado de Baja California; en todos los casos, y bajo su más estricta responsabilidad, informará de inmediato de lo acaecido al Ministerio Público y pondrá a su disposición las personas, bienes u objetos relacionados con los hechos.\nEn estos casos, la Institución Policial actuará de conformidad con los protocolos que al efecto se establezcan conforme a las disposiciones legales aplicables.\nCAPÍTULO SÉPTIMO\nINTERVENCIÓN E INFORMACIÓN DE\nCOMUNICACIONES PRIVADAS\nArtículo 27.- En concordancia con los artículos 16 y 21 de la Constitución\nPolítica de los Estados Unidos Mexicanos y este ordenamiento, el Comisario\nGeneral, previo acuerdo con el Secretario, podrá solicitar la intervención de comunicaciones al titular del Ministerio Público, cuando se constate la existencia delitos señalados en el artículo 30 de esta Ley. delito, se dará vista de inmediato al Ministerio Público.\nArtículo 28.- La Institución Policial al efectuar la intervención a que se refiere la fracción XXXVII del artículo 7 de esta Ley, deberá regirse por los principios de legalidad, objetividad, eficiencia, profesionalismo, imparcialidad, Ley de la Policía Estatal Preventiva de Baja California Página 13 reconocidos en la Constitución.\nArtículo 29.- El Comisario General será responsable de que la intervención se realice en los términos de la autorización judicial. fundan, el razonamiento por el que se considera procedente, el tipo de comunicaciones, periodo durante el cual se llevarán a cabo las intervenciones, los sujetos y lugares que serán intervenidos.\nArtículo 30.- La intervención de comunicaciones a que se refiere esta Ley, se solicitará al Ministerio Público en los delitos previstos en los ordenamientos legales que a continuación se enlistan:\nI.- Del Código de Procedimientos Penales para el Estado de Baja California, los delitos calificados como graves;\nII.- De la Ley Contra la Delincuencia Organizada para el Estado de Baja\nCalifornia, en los términos y por las conductas establecidas en el artículo 4.\nArtículo 31.- El Comisario General, al concluir cada intervención de comunicaciones privadas, levantará un acta que contendrá un inventario pormenorizado de la información de audio o video que contengan los sonidos o imágenes captadas, así como un informe sobre sus resultados, a efecto de que sea posible constatar el debido cumplimiento de la autorización otorgada.\nArtículo 32.- La reserva de las intervenciones de comunicaciones privadas, autorizadas al Comisario General, será bajo su estricta responsabilidad y, en caso de incumplimiento, será sancionado en términos de la legislación aplicable.\nArtículo 33.- Sólo podrán dar cumplimiento a las intervenciones autorizadas por la autoridad judicial competente, aquellos Miembros que cumplan los siguientes requisitos:\na) Pertenezcan a las áreas de investigación de la Institución Policial,\nb) Cuenten con certificación de control de confianza vigente y\nc) Tengan un grado policial mínimo de subinspector.\nArtículo 34.- En el caso de la solicitud de información dispuesta en la fracción XXXVI del artículo 7 de esta Ley, se aplicará en lo conducente el procedimiento a que se refiere este Capítulo.\nCAPÍTULO OCTAVO\nDEL PERSONAL DE LA INSTITUCIÓN POLICIAL\nLey de la Policía Estatal Preventiva de Baja California Página 14\nArtículo 35.- La relación entre la Institución Policial y sus Miembros se regulará por lo dispuesto en la fracción XIII, apartado B, del artículo 123 de la\nSeguridad Pública, la presente Ley y las demás disposiciones aplicables.\nInstitución Policial o incurran en cualquiera de las hipótesis contenidas en la fracción I del artículo 180 de dicho ordenamiento legal o removidos por incurrir en responsabilidad administrativa grave en el desempeño de sus funciones, sin que proceda su reinstalación o restitución, cualquiera que sea el juicio o medio de defensa para combatir la separación o remoción.\nEl Miembro que llegare a obtener resolución favorable en contra de la separación definitiva por falta de requisitos de permanencia y demás casos previstos en la Ley de Seguridad Pública y esta Ley o remoción por incurrir en responsabilidad administrativa grave en el desempeño de sus funciones o incumplimiento de sus deberes y obligaciones, sólo recibirá el pago de la indemnización y de las condiciones del servicio que de manera proporcional le correspondan; sin que sea procedente el pago de percepción, retribución o remuneración alguna, que hubiere dejado de percibir por motivo de la separación definitiva o remoción del cargo.\nArtículo 36.- La actuación de los Miembros de la Institución Policial se sujetará invariablemente a los principios rectores establecidos en el artículo 3 de la presente Ley.\nArtículo 37.- Las condiciones de servicio establecidas en la Ley de\nSeguridad Pública, a favor de los Miembros, serán determinadas reglamentariamente por el titular del Poder Ejecutivo.\nArtículo 38.- Los deberes y obligaciones de los Miembros, así como el procedimiento para la aplicación de sanciones al régimen disciplinario, se determinarán en la Ley de Seguridad Pública y demás disposiciones aplicables.\nReglamento.\nCAPÍTULO NOVENO\nDE LA CARRERA POLICIAL\nArtículo 39.- La carrera policial comprende el grado policial, la antigüedad, las insignias, condecoraciones, estímulos y reconocimientos obtenidos, el resultado de los procesos de promoción, así como el registro de las correcciones disciplinarias y sanciones que, en su caso, haya acumulado el Miembro. Se regirá por las normas siguientes:\nLey de la Policía Estatal Preventiva de Baja California Página 15\nI. La Institución Policial deberá consultar los antecedentes de los aspirantes autorice su ingreso a la misma;\nII. Todo aspirante deberá tramitar, obtener y mantener actualizado el\nCertificado Único Policial, que expedirá el Centro de Control de Confianza, de Confianza;\nIII. Ninguna persona podrá ingresar a la Institución Policial si no ha sido debidamente certificada e inscrita en el Registro Nacional de Personal de\nSeguridad Pública;\nIV. Sólo ingresarán y permanecerán en la Institución Policial aquellos aspirantes y Miembros que cursen y aprueben los programas de formación, capacitación, actualización, profesionalización y demás que establezca la\nAcademia;\nV. La permanencia de los Miembros está condicionada al cumplimiento de los requisitos que determine la Ley de Seguridad Pública y demás disposiciones aplicables;\nVI. Los méritos de los Miembros serán evaluados por la instancia colegiada, encargada de determinar las promociones y verificar que se cumplan los requisitos de permanencia, de acuerdo a las disposiciones aplicables;\nVII. El Reglamento establecerá los criterios para la promoción de los\nMiembros de la Institución Policial, por lo menos, los resultados obtenidos en los programas de profesionalización, los méritos demostrados en el desempeño de sus funciones y sus aptitudes de mando y liderazgo;\nVIII. El Reglamento de esta Ley, establecerá un régimen de condecoraciones, estímulos y promociones que corresponda a las funciones de los Miembros;\nIX. Los Miembros podrán ser cambiados de adscripción, con base en las necesidades del servicio, sin que esa adscripción implique inamovilidad en la sede a la que fueron destinados;\nX. El cambio de un Miembro de un área operativa a otra de distinta especialidad, solo podrá ser autorizado por el titular de la Institución Policial;\nXI. Las sanciones que se apliquen a los Miembros, se determinarán en los correspondientes. En el procedimiento de aplicación de sanciones se salvaguardará en todo tiempo la garantía de audiencia;\nLey de la Policía Estatal Preventiva de Baja California Página 16\nXII. Los procedimientos para el reclutamiento, certificación, selección, ingreso, formación, permanencia, antigüedad, evaluación, promoción y reconocimiento, así como la remoción o baja del servicio de los Miembros serán establecidos en las disposiciones reglamentarias que al efecto, se expidan, y\nXIII. Las demás que establezca esta Ley, otras leyes y reglamentos.\nArtículo 40.- La carrera policial es independiente de los nombramientos para desempeñar cargos administrativos o de dirección que el Miembro llegue a desempeñar en la Institución Policial. En ningún caso los derechos adquiridos en la carrera policial implicarán inamovilidad en cargo alguno.\nEn términos de las disposiciones aplicables, el Secretario, a propuesta del\nComisario General, podrá designar a Miembros en cargos administrativos o de dirección en la estructura orgánica de la Institución Policial; asimismo, podrá relevarlos libremente, respetando su grado policial y sus derechos inherentes a la carrera policial.\nCAPÍTULO DÉCIMO\nDE LA PLANEACIÓN\nArtículo 41.- La planeación permite determinar las necesidades cuantitativas y cualitativas del personal que requiere la carrera policial, así como su plan de carrera para el eficiente ejercicio de sus funciones, de acuerdo con el\nPlan Estatal de Desarrollo y los diversos programas oficiales en materia de seguridad pública en el Estado.\nLa planeación tiene como objeto establecer y coordinar los diversos procesos de reclutamiento; selección de aspirantes; formación inicial; ingreso; formación continua y especializada; evaluación para la permanencia; desarrollo y promoción; condecoraciones y estímulos; régimen disciplinario; separación y retiro que determinen las necesidades de la carrera policial, de conformidad a la Ley de\nSeguridad Pública y demás disposiciones aplicables.\nEl plan de carrera policial, deberá comprender la ruta profesional desde el ingreso hasta su separación, en el que se fomentará su sentido de pertenencia a la Institución Policial, conservando la categoría o jerarquía que vaya obteniendo a fin de infundirle certeza y certidumbre.\nCAPÍTULO UNDÉCIMO\nDEL INGRESO Y PERMANENCIA\nArtículo 42.- Los aspirantes que hubieren aprobado la etapa de formación inicial en la Academia, podrán ser considerados por la Secretaría para ingresar a la Institución Policial, siempre y cuando cumplan con los requisitos y demás\nLey de la Policía Estatal Preventiva de Baja California Página 17 condiciones establecidas en la Ley de Seguridad Pública, esta Ley, el Reglamento de la Academia y las demás disposiciones aplicables.\nEl ingreso de aspirantes a la Institución Policial, además estará sujeto a las\nArtículo 43.- En los procesos de selección e ingreso de aspirantes, no podrá existir distinción por razón de género, religión, estado civil, origen étnico o condición social para la pertenencia al servicio.\nArtículo 44.- La permanencia es el resultado del cumplimiento constante de los requisitos establecidos en la Ley de Seguridad Pública y demás disposiciones aplicables, para continuar en el servicio activo en la Institución Policial.\nEn los términos de los artículos 117, inciso B, fracción XXII y 133, fracción\nLIV, de la Ley de Seguridad Pública, así como el Reglamento de la presente Ley, se podrán determinar requisitos de permanencia y obligaciones adicionales.\nCAPÍTULO DUODÉCIMO\nDE LAS CONDECORACIONES, ESTÍMULOS Y PROMOCIONES\nArtículo 45.- Los Miembros tendrán derecho a que se les otorguen las condecoraciones, estímulos y promociones, a que se refiere la Ley de Seguridad\nPública.\nArtículo 46.- Los procedimientos para otorgar condecoraciones, estímulos y promociones a los Miembros, se determinarán en el Reglamento de la presente\nLey y demás normatividad aplicable.\nCAPÍTULO DÉCIMOTERCERO\nDE LA CONCLUSIÓN DEL SERVICIO\nArtículo 47.- La conclusión del servicio de un Miembro es la terminación de su nombramiento o la cesación de sus efectos legales por las siguientes causas:\nI. Separación, por incumplimiento a cualquiera de los requisitos de permanencia, o cuando en los procesos de promoción concurran las siguientes circunstancias:\na) Si hubiere sido convocado a tres procesos consecutivos de promoción sin que haya participado en los mismos, o que habiendo participado en dichos por causas imputables a él;\nb) Que haya alcanzado la edad máxima correspondiente a su jerarquía, de acuerdo con lo establecido en las disposiciones aplicables.\nLey de la Policía Estatal Preventiva de Baja California Página 18\nII. Remoción, por incurrir en responsabilidad en el desempeño de sus funciones o incumplimiento de sus deberes, de conformidad con las disposiciones relativas al régimen disciplinario, o\nIII. Baja, tratándose de:\na) Renuncia;\nb) Muerte, o incapacidad permanente o\nc) Jubilación o retiro.\nArtículo 48.- Al concluir el servicio el Miembro deberá entregar al funcionario designado para tal efecto, toda la información, documentación, equipo reglamentario, materiales, identificaciones, valores u otros recursos que hayan sido puestos bajo su responsabilidad o custodia mediante acta de entrega recepción.\nCAPÍTULO DÉCIMOCUARTO\nDE LAS INSIGNIAS, DIVISAS, UNIFORME Y EQUIPO REGLAMENTARIO\nArtículo 49.- Los Miembros durante el servicio deberán portar insignias, divisas, uniforme, armas y demás equipo reglamentario correspondiente; salvo disposición legal o reglamentaria en contrario.\nArtículo 50.- La entrega y portación de las insignias, divisas, uniforme, armas y demás equipo reglamentario correspondiente, se determinará en los términos establecidos en el Reglamento de la Ley.\nCAPÍTULO DÉCIMOQUINTO\nDE LAS CORRECCIONES DISCIPLINARIAS\nArtículo 51.- Las correcciones disciplinarias que se apliquen a los\nMiembros consistirán en amonestación, arresto y cambio de adscripción, disposiciones aplicables. directo sobre la Institución Policial, por el jefe inmediato del Miembro o por quien\nArtículo 52.- El procedimiento para la sustanciación y aplicación de las\nCAPÍTULO DÉCIMOSEXTO\nDEL ESCUDO OFICIAL\nLey de la Policía Estatal Preventiva de Baja California Página 19\nArtículo 53.- El diseño del Escudo Oficial de la Institución Policial estará compuesto en los términos previstos en el reglamento de la presente Ley.\nARTÍCULOS TRANSITORIOS\nPRIMERO.- La presente Ley abroga a la Ley de la Policía Estatal\nPreventiva, publicada en el Periódico Oficial del Estado No. 47, de fecha treinta y uno del mes de Octubre del año dos mil uno, salvo lo establecido en el artículo tercero transitorio.\nSEGUNDO.- La presente Ley entrará en vigor al día siguiente de su publicación en el Periódico Oficial del Estado, salvo lo previsto en el artículo transitorio siguiente.\nTERCERO.- La estructura jerárquica y administrativa de la Policía Estatal\nPreventiva de Baja California, seguirá funcionando en la forma y términos previstos en la Ley de la Policía Estatal Preventiva publicada en el Periódico\nOficial del Estado No. 47, de fecha treinta y uno del mes de Octubre del año dos mil uno y el Reglamento Interno de la Policía Estatal Preventiva, publicado en el\nPeriódico Oficial del Estado No. 19, de fecha ocho de Mayo del año dos mil seis; hasta en tanto, las categorías y jerarquías de la Policía Estatal Preventiva de Baja\nCalifornia, previstas en esta Ley, sean homologadas al servicio de carrera policial, en los términos del artículo cuarto transitorio de la Ley de Seguridad Pública del\nEstado de Baja California.\nCUARTO.- Las disposiciones reglamentarias derivadas de la presente Ley, se expedirán a más tardar dentro de ciento ochenta días siguientes a la entrada en vigor del presente ordenamiento legal.\nQUINTO.- Se derogan todas las disposiciones legales que se opongan a la presente Ley.\nDADO en el Salón de Sesiones “Lic. Benito Juárez García” del H. Poder\nLegislativo del Estado de Baja California, en la Ciudad de Mexicali, B.C., a los siete días del mes de septiembre del año dos mil diez.\nDIP. JUAN MANUEL GASTÉLUM BUENROSTRO\nPRESIDENTE\nDIP. CARLOS ALONSO ANGULO RENTERIA\nSECRETARIO\nLey de la Policía Estatal Preventiva de Baja California Página 20\nPUBLIQUESE.\nMEXICALI, BAJA CALIFORNIA, A LOS QUINCE DÍAS DEL MES DE\nSEPTIEMBRE DEL AÑO DOS MIL DIEZ.\nGOBERNADOR DEL ESTADO\nJOSE GUADALUPE OSUNA MILLAN\nSECRETARIO GENERAL DE GOBIERNO\nCUAUHTEMOC CARDONA BENAVIDES\nLey de la Policía Estatal Preventiva de Baja California Página 21\nArtículo 11.- Fue reformado por Decreto No. 481, publicado en el Periódico\nLegislatura, siendo Gobernador Constitucional el C. José Guadalupe Osuna Millán\n2007-2013;\nLey de la Policía Estatal Preventiva de Baja California Página 22\nARTÍCULO UNICO TRANSITORIO DEL DECRETO No. 481, POR EL QUE\nSE REFORMAN LAS XIV Y XV; ASÍ COMO LA ADICIÓN DE UNA FRACCIÓN\nXVI AL ARTÍCULO 11, PUBLICADO EN EL PERIÓDICO OFICIAL No. 29, TOMO\nLEGISLATURA, SIENDO GOBERNADOR CONSTITUCIONAL EL C. JOSÉ\nGUADALUPE OSUNA MILLÁN 2007-2013;\nARTÍCULO TRANSITORIO\nÚNICO.- La presente reforma entrará en vigor al día siguiente de su publicación en el Periódico Oficial del Estado de Baja California.\nDADO en el Salón de Sesiones “Lic. Benito Juárez García” del H. Poder\nLegislativo del Estado de Baja California, en la Ciudad de Mexicali, B.C., a los veintiocho días del mes de mayo del año dos mil trece.\nDIP. JULIO FELIPE GARCÍA MUÑOZ\nPRESIDENTE\n(RÚBRICA)\nDIP. MARCO ANTONIO VIZCARRA CALDERÓN\nSECRETARIO\n(RÚBRICA)\nDE CONFORMIDAD CON LO DISPUESTO POR LA FRACCION I DEL\nPUBLIQUESE.\nMEXICALI, BAJA CALIFORNIA, A LOS CUATRO DÍAS DEL MES DE\nJUNIO DEL AÑO DOS MIL TRECE.\nGOBERNADOR DEL ESTADO\nJOSE GUADALUPE OSUNA MILLAN\nSECRETARIO GENERAL DE GOBIERNO\nCUAUHTEMOC CARDONA BENAVIDES\nLey de la Policía Estatal Preventiva de Baja California Página 23",
  "ordenamiento": "REGLAMENTO",
  "jurisdiccion": "BAJA CALIFORNIA",
  "fuente_oficial": "Periódico Oficial",
  "FECHA PER OFIC": "2013/06/28",
  "ESTATUS": "VIGENTE",
  "TOMO": "TOMO_V",
  "URL": "https://www.congresobc.gob.mx/Documentos/ProcesoParlamentario/Leyes/TOMO_V/LEYPOLPREVENTIVA_28JUN2013.PDF",
  "es_escaneado": false,
  "tiene_tablas": false,
  "materia": [
    "penal",
    "seguridad",
    "justicia"
  ]
}