{
  "titulo": "Ley ELECTORAL DEL ESTADO DE BAJA CALIFORNIA",
  "Contenido": ".\nActualización Legislativa.\nÚltima reforma P. O. No. 60, Índice, 03-Oct-2025\nLEY ELECTORAL DEL ESTADO DE BAJA CALIFORNIA\nPublicada en el Periódico Oficial No. 28, Sección II, Tomo CXXII, de fecha 12 de junio de 2015\nLIBRO PRIMERO\nDisposiciones Generales\nTÍTULO PRIMERO\nDel objeto, ejecución y aplicación de esta ley\nCAPÍTULO PRIMERO\nDel objeto de la ley\nArtículo 1.- Las disposiciones de esta Ley son de orden público, de observancia general en el Estado de Baja California y tienen por objeto dar certeza, legalidad, independencia, imparcialidad, máxima publicidad, objetividad y austeridad, así como garantizar la paridad de género y el principio de igualdad sustantiva, al ejercicio de la función pública electoral.\nArtículo Reformado\nArtículo 2.- La presente Ley reglamenta las normas constitucionales relativas a:\nI. El ejercicio de los derechos, prerrogativas y obligaciones político electorales de las ciudadanas y los ciudadanos;\nFracción Reformada\nII. La integración y funcionamiento del Instituto Estatal Electoral;\nIII. La función pública de organizar las elecciones ordinarias y extraordinarias para la integración de los Poderes Legislativo y Ejecutivo del Estado, y de los Ayuntamientos de la Entidad;\nIV. El Sistema de Medios de Impugnación para garantizar la legalidad de los actos y resoluciones de las autoridades electorales, y\nV. Las faltas y sanciones administrativas, así como el Régimen de\nResponsabilidades y sanciones de los servidores públicos del Instituto Estatal Electoral.\nArtículo Reformado\nArtículo 3.- Para los efectos de esta Ley, se entiende por:\nI. Actos Anticipados de Campaña: Los actos de expresión que se realicen bajo cualquier modalidad y en cualquier momento fuera de la etapa de campañas, que contengan\nLey Electoral del Estado de Baja California. Página 1\n.\nActualización Legislativa.\nÚltima reforma P. O. No. 60, Índice, 03-Oct-2025 expresiones solicitando cualquier tipo de apoyo para contender en el proceso electoral por alguna candidatura o para un partido;\nII. Actos Anticipados de Precampaña: Las expresiones que se realicen bajo cualquier modalidad y en cualquier momento durante el lapso que va desde el inicio del proceso electoral hasta antes del plazo legal para el inicio de las precampañas, que contengan llamados expresos al voto en contra o a favor de una precandidatura;\nIII. Candidato independiente: El ciudadano mexicano residente en el Estado que obtenga por parte del Instituto Estatal la constancia de registro, habiendo cumplido los requisitos que para tal efecto establece la presente Ley y demás disposiciones aplicables.\nIV. Ciudadanos o Ciudadanas: Las personas que teniendo la calidad de mexicanas reúnan los requisitos determinados en el artículo 34 de la Constitución Política de los Estados Unidos Mexicanos.\nFracción Adicionada, recorriéndose las subsecuentes\nV. Constitución Federal: a la Constitución Política de los Estados Unidos\nMexicanos.\nSoberano de Baja California.\nVII. Consejo General: al Consejo General Electoral del Instituto Estatal Electoral del Estado de Baja California.\nIX. Instituto Estatal o Instituto: al Instituto Estatal Electoral de Baja California.\nX. Instituto Nacional: al Instituto Nacional Electoral.\nXI. Ley: a la Ley Electoral del Estado de Baja California.\nXII. Ley de Acceso: Ley de Acceso de las Mujeres a una Vida Libre de Violencia para el Estado de Baja California.\nFracción Adicionada, recorriéndose las subsecuentes\nXIII. Ley General: la Ley General de Instituciones y Procedimientos Electorales.\nXIV. Paridad de género: Igualdad política entre mujeres y hombres que se garantiza con la asignación del 50% a mujeres y 50% a hombres en candidaturas a cargos de elección popular y en nombramientos de cargos por designación.\nFracción Adicionada, recorriéndose las subsecuentes\nXV. Partidos Políticos: Los partidos políticos nacionales y locales, constituidos conforme a las leyes de la materia.\nXVI. Tribunal o Tribunal Electoral: al Tribunal de Justicia Electoral del Estado de\nBaja California.\nLey Electoral del Estado de Baja California. Página 2\n.\nActualización Legislativa.\nÚltima reforma P. O. No. 60, Índice, 03-Oct-2025\nXVII. Unidad Técnica de lo Contencioso: Unidad Técnica de lo Contencioso\nElectoral de la Secretaria Ejecutiva.\nXVIII. Violencia política contra las mujeres en razón de género: es toda acción u omisión, incluida la tolerancia, basada en elementos de género y ejercida dentro de la esfera pública o privada, que tenga por objeto o resultado limitar, anular o menoscabar el ejercicio efectivo de los derechos políticos y electorales de una o varias mujeres, el acceso al pleno ejercicio de las atribuciones inherentes a su cargo, labor o actividad, el libre desarrollo de la función pública, la toma de decisiones, la libertad de organización, así como el acceso y ejercicio a las prerrogativas, tratándose de precandidaturas, candidaturas, funciones o cargos públicos del mismo tipo.\nSe entenderá que las acciones u omisiones se basan en elementos de género, cuando se dirijan a una mujer por ser mujer; le afecten desproporcionadamente o tengan un impacto diferenciado en ella.\nPuede manifestarse en cualquiera de los tipos de violencia reconocidos en la Ley de\nAcceso y puede ser perpetrada indistintamente por agentes estatales, por superiores jerárquicos, colegas de trabajo, personas dirigentes de partidos políticos, militantes, simpatizantes, precandidatas, precandidatos, candidatas o candidatos postulados por los partidos políticos o representantes de los mismos; medios de comunicación y sus integrantes, por algún particular o por un grupo de personas particulares.\nFracción con sus Párrafos Adicionada\nXIX. Principio de igualdad sustantiva: Paridad de oportunidades en el goce y ejercicio real de los derechos político-electorales de todas las personas.\nFracción Adicionada\nArtículo Reformado\nCAPÍTULO SEGUNDO\nDe la ejecución y aplicación de la ley\nArtículo 4.- Corresponde la ejecución y aplicación de las normas contenidas en esta\nLey, dentro de su respectivo ámbito de competencia, al Instituto Estatal y al Tribunal\nElectoral, quienes tendrán la obligación de velar su estricta observancia y cumplimiento.\nArtículo 5.- Los órganos electorales, en el ámbito de sus respectivas competencias, tienen a su cargo:\nI. La preparación y desarrollo del proceso electoral;\nII. Vigilar que los partidos políticos o coaliciones realicen sus actividades con apego a la Ley;\nIII. Garantizar la efectividad del sufragio y la autenticidad e imparcialidad de las elecciones en los términos que establece la Constitución Federal, y la Constitución del\nEstado, y\nIV. Las demás que establezcan las Leyes.\nLey Electoral del Estado de Baja California. Página 3\n.\nActualización Legislativa.\nÚltima reforma P. O. No. 60, Índice, 03-Oct-2025\nArtículo 6.- En el desempeño de sus funciones, las autoridades y órganos electorales establecidos por la Constitución del Estado y esta Ley, contarán con el apoyo de las autoridades federales, estatales y municipales, en sus respectivos ámbitos de competencia.\nLos Notarios Públicos del Estado auxiliarán a las autoridades electorales en forma gratuita, cuando así lo soliciten durante el proceso electoral.\nArtículo 7.- La interpretación de las disposiciones de esta Ley, se hará tomando en cuenta los fines que señala el artículo 1 y atendiendo indistintamente a los criterios gramatical, sistemático y funcional, observando lo dispuesto en el último párrafo del artículo\n14 de la Constitución Federal.\nLas sanciones administrativas o jurisdiccionales en materia electoral deben ser aplicadas bajo el principio de estricto derecho. No podrán imponerse por simple analogía o por mayoría de razón.\nPárrafo Adicionado\nLas autoridades electorales, administrativas y jurisdiccionales, no podrán condicionar el ejercicio de derechos o prerrogativas político-electorales de la ciudadanía solicitando mayores requisitos que los que expresamente determinan la Constitución y esta ley.\nPárrafo Adicionado\nArtículo Reformado\nArtículo 8.- A falta de disposición expresa en esta Ley, se estará a lo dispuesto en la\nConstitución Federal, en la Constitución del Estado, Ley General, Ley General del Sistema de Medios de Impugnación en Materia Electoral, en los criterios obligatorios que dicte el\nTribunal Electoral, la Jurisprudencia del Tribunal Electoral del Poder Judicial de la\nFederación, en los acuerdos del Instituto Nacional o del Consejo General dictados dentro del ámbito de sus competencias, y a los principios generales del derecho.\nArtículo Reformado\nTÍTULO SEGUNDO\nDe los derechos y obligaciones político electorales de los ciudadanos\nCAPÍTULO ÚNICO\nArtículo 9.- Votar en las elecciones constituye un derecho y una obligación de las ciudadanas y los ciudadanos, que se ejerce para integrar los órganos de elección popular del Estado. También es su derecho, y obligación para los partidos políticos la igualdad de popular.\nPárrafo Reformado\nEl voto es universal, libre, secreto, directo, personal e intransferible. ciudadanos, tendientes a vulnerar la libertad y el secreto del sufragio. Las autoridades en el\nLey Electoral del Estado de Baja California. Página 4\n.\nActualización Legislativa.\nÚltima reforma P. O. No. 60, Índice, 03-Oct-2025 ámbito de su competencia, serán responsables de garantizar las condiciones que propicien el ejercicio voluntario del voto.\nPárrafo Reformado\nLos derechos político-electorales, se ejercerán sin discriminación por origen étnico o nacional, género, edad, discapacidades, condición social, condiciones de salud, religión, opiniones, preferencias sexuales, estado civil o cualquier otra que atente contra la dignidad humana o tenga por objeto anular o menoscabar los derechos y libertades de las personas, y también se ejercerán libres de violencia política contra las mujeres en razón de género.\nPárrafo Adicionado\nArtículo Reformado\nArtículo 10.- Es derecho de los ciudadanos residentes en el Estado organizarse en partidos políticos estatales y afiliarse a ellos en forma individual y libre, en los términos de la\nLey General de Partidos Políticos y la Ley de Partidos Políticos del Estado.\nArtículo 11.- Ejercerá el derecho de voto, en los términos de la Constitución Federal, la Constitución del Estado, Ley General y esta Ley, el ciudadano mexicano, residente en\nBaja California que goce del pleno ejercicio de sus derechos político electorales y que además cumpla con los siguientes requisitos:\nI. Tener vecindad en el Estado, con residencia efectiva de por lo menos seis meses;\nII. Estar inscrito en el Padrón Electoral, y aparecer en el Listado Nominal de\nElectores con fotografía, que expida el Instituto Nacional, y\nIII. Tener credencial para votar que expida el Instituto Nacional.\nArtículo 12.- No podrán ejercer el derecho de voto los ciudadanos que se encuentren comprendidos dentro de los supuestos siguientes:\nI. Sujeto a proceso penal por delito que merezca pena privativa de la libertad, desde que se dicte el auto de formal prisión o de vinculación al proceso;\nII. Compurgando pena privativa de la libertad;\nIII. Sujeto a interdicción o incapacidad judicial declarada;\nIV. Ser prófugo de la justicia, en los términos que establezca la Ley correspondiente;\nV. Condenado por sentencia ejecutoriada a la suspensión o pérdida de los derechos político electorales, hasta en tanto no se le hayan restituido, o\nVI. Encontrarse en los demás casos que expresamente señalen las leyes.\nArtículo 13.- Es derecho exclusivo de los ciudadanos mexicanos participar como observadores de los actos de preparación y desarrollo del proceso electoral, así como de los que se lleven a cabo el día de la jornada electoral, en la forma y términos en que determine el Instituto Nacional para cada proceso electoral, de acuerdo con las bases de la Ley\nGeneral.\nLey Electoral del Estado de Baja California. Página 5\n.\nActualización Legislativa.\nÚltima reforma P. O. No. 60, Índice, 03-Oct-2025\nArtículo 14.- Son obligaciones de los ciudadanos residentes en el Estado:\nI. Inscribirse en el Padrón Electoral y obtener su credencial para votar que expida el Instituto Nacional;\nII. Votar en las elecciones en la casilla de la sección electoral que corresponda a su domicilio, salvo las excepciones que establece esta Ley;\nIII. Ejercer los cargos de elección popular para los que fueren electos;\nIV. Desempeñar en forma obligatoria y gratuita las funciones electorales para las que sean requeridos;\nV. Participar en la preparación y desarrollo de las elecciones a través de los órganos electorales competentes, y\nVI. Las demás que señale esta Ley.\nLIBRO SEGUNDO\nDe la elección e integración de los poderes\nLegislativo y Ejecutivo y de los Ayuntamientos\nTÍTULO PRIMERO\nDe las elecciones\nCAPÍTULO PRIMERO\nDe las elecciones ordinarias\nArtículo 15.- Las elecciones ordinarias deberán celebrarse el primer domingo del mes de junio del año que corresponda, para elegir:\nI. Gobernador Constitucional, cada seis años;\nII. Diputados al Congreso del Estado, cada tres años, y\nIII. Munícipes a los Ayuntamientos, cada tres años. laborable en todo el territorio de la entidad.\nArtículo 16.- A cada elección ordinaria precederá una convocatoria expedida por el\nConsejo General, cuya publicación en el Periódico Oficial del Estado y en los diarios de mayor circulación en la entidad, deberá hacerse a más tardar el día cinco de enero del año de la elección, cuando corresponda a la elección de gobernador, y a más tardar el día cinco de febrero cuando sólo se elijan diputados y munícipes.\nCAPÍTULO SEGUNDO\nDe las elecciones extraordinarias\nLey Electoral del Estado de Baja California. Página 6\n.\nActualización Legislativa.\nÚltima reforma P. O. No. 60, Índice, 03-Oct-2025\nArtículo 17.- Las elecciones extraordinarias deberán celebrarse cuando sean convocadas por:\nI. El Congreso del Estado, cuando existan vacantes de diputaciones de mayoría relativa por falta de propietarios y suplentes para cubrirlas, o se declare nula la elección y haya causado estado, o los candidatos electos de la fórmula no reúnan los requisitos para ocupar el cargo;\nII. El Gobernador Provisional, en caso de falta absoluta de Gobernador\nConstitucional, ocurrida durante los dos primeros años del período, o se declare nula la elección y haya causado estado, y\nIII. El Congreso del Estado, en caso de que se declare nula la elección de munícipes y haya causado estado.\nLa convocatoria a que se refieren los supuestos contenidos en las fracciones I y III, deberá expedirse en un plazo que no excederá de cuarenta días, contados a partir del día siguiente en que se actualicen las hipótesis de elecciones extraordinarias, en estos casos dichas elecciones deberán efectuarse en un plazo que no exceda de sesenta días contados a partir de la expedición de la convocatoria. Para efecto de lo dispuesto en la fracción II, deberá observarse los plazos dispuestos en el artículo 46 de la Constitución del Estado.\nArtículo 18.- La convocatoria que se expida para el caso de elecciones extraordinarias, no podrá restringir los derechos que la Constitución del Estado, la Ley\nGeneral, la Ley General de Partidos Políticos, y la presente Ley otorgan a los ciudadanos y partidos políticos acreditados o registrados ante el Consejo General, ni alterar los procedimientos y formalidades instituidas en esta Ley.\nArtículo 19.- Los partidos políticos estatales que tuvieren su registro suspendido o cancelado con anterioridad a la fecha en que deban realizarse elecciones ordinarias o extraordinarias, no podrán participar en ellas. En caso de que hubieran participado con candidatos en la elección anulada, podrán participar en la elección extraordinaria.\nTÍTULO SEGUNDO\nDel Poder Legislativo\nCAPÍTULO PRIMERO\nDe la elección e integración del Congreso\nArtículo 20.- El Congreso del Estado estará integrado por diputados que se elegirán cada tres años, mediante sufragio universal, libre, secreto, directo, personal e intransferible; diecisiete serán electos en forma directa mediante el principio de mayoría relativa, uno por cada distrito electoral en que se divide el territorio del Estado, y en su caso, hasta ocho estatal, de conformidad con la Constitución del Estado y el procedimiento previsto en el presente Título. Cada Diputado propietario tendrá un suplente.\nLey Electoral del Estado de Baja California. Página 7\n.\nActualización Legislativa.\nÚltima reforma P. O. No. 60, Índice, 03-Oct-2025\nArtículo 21.- Las y los diputados podrán ser electos hasta por cuatro periodos consecutivos.\nPárrafo Reformado\nLas y los diputados interesados en la elección consecutiva deberán manifestarlo por escrito a su partido político. Para el caso de que manifiesten su deseo de reelegirse deberán, además, señalar el principio por el que desean hacerlo, de tratarse del principio de mayoría relativa, deberán señalar el distrito o su equivalente por el que lo harán, de no hacerse en los términos antes señalados, se entenderá que la diputada o diputado no está interesado en la elección consecutiva. El escrito que contenga las manifestaciones antes señaladas, deberá presentarse al partido político correspondiente, con veinte días de anticipación al inicio de las precampañas, en virtud de lo cual, los partidos políticos en la determinación de los criterios para garantizar la paridad de género en sus métodos de selección de candidaturas deberán respetar el principio de paridad de género en su aspecto cualitativo y cuantitativo.\nPárrafo Adicionado\nPárrafo Reformado\nLos partidos políticos en plena autodeterminación seleccionarán a sus candidatos, el distrito por el cual competirán, así como el principio de mayoría relativa o de representación proporcional, según sea el caso, observando al efecto las reglas que sobre equidad de género que dispone la Constitución Política Federal, la Ley General de Instituciones y\nProcedimientos Electorales, la Ley General de Partidos Políticos, esta Constitución y demás normatividad aplicable.\nPárrafo Adicionado\nPara efecto de lo previsto en el artículo 16, párrafo quinto de la Constitución Política del Estado, se tendrá por equivalente cualquier distrito cuya conformación se integre mayoritariamente por secciones del distrito electoral por el que fueron electos.\nPárrafo Adicionado\nCuando un diputado no pueda contender por el mismo distrito por el que accedió al cargo o su equivalente, podrá participar en la reelección, ya sea por el principio de mayoría relativa por cualquier demarcación territorial que conserve por lo menos una sección electoral del distrito por el que fue electo o por el principio de representación proporcional.\nPárrafo Adicionado igualdad sustantiva. [Las autoridades electorales sólo podrán intervenir en los asuntos partidos].\nPárrafo Adicionado\nLey Electoral del Estado de Baja California. Página 8\n.\nActualización Legislativa.\nÚltima reforma P. O. No. 60, Índice, 03-Oct-2025\nPárrafo Reformado\nPorción normativa invalidada por Sentencia a Acción de Inconstitucionalidad 198/2023 y su acumulada 200/2023\nLa postulación solo podrá ser realizada por el mismo partido o por cualquiera de los partidos integrantes de la coalición que los hubieren postulado; salvo que hayan renunciado o perdido su militancia antes de la mitad de su mandato.\nEn el caso de diputados electos como candidatos independientes solo podrán postularse para la reelección con la misma calidad de candidato independiente, salvo que se afilie y demuestre su militancia en un partido político antes de la mitad de su periodo, caso en el que si podrá postularse para reelección por dicho partido.\nLos diputados que hayan ocupado su cargo público por la vía de una candidatura independiente y pretendan su elección consecutiva por la misma vía, para obtener el registro de su candidatura deben cumplir con los requisitos señalados en los artículos 14, 26 y 27 de la Ley que Reglamenta las Candidaturas Independientes.\nPárrafo Adicionado\nArticulo Reformado\nCAPÍTULO SEGUNDO\nDe la asignación de diputaciones de representación proporcional\nDenominación Modificada\nArtículo 22.- Para que los partidos políticos tengan derecho a la asignación de diputaciones por el principio de representación proporcional, deberán reunir los siguientes requisitos:\nPárrafo Reformado\nI. Participar con candidatos a diputaciones por el principio de mayoría relativa en por lo menos el cincuenta por ciento de los distritos electorales, y\nFracción Reformada\nII. Haber obtenido por lo menos el tres por ciento de la votación valida emitida en la elección de Diputados por el principio de representación proporcional.\nFracción Reformada\nIII. Derogada.\nFracción Derogada representación proporcional, es aquella que resulte de sumar la que se obtuviere en las casillas especiales para esta elección, a la suma obtenida en la elección de Diputados por el principio de mayoría relativa en cada uno de los distritos electorales, deduciendo los votos nulos y los correspondientes a los candidatos no registrados.\nArtículo Reformado\nArtículo 23.- El Instituto Estatal una vez verificados los requisitos del artículo anterior, asignará un Diputado a cada partido político que tenga derecho a ello.\nLey Electoral del Estado de Baja California. Página 9\n.\nActualización Legislativa.\nÚltima reforma P. O. No. 60, Índice, 03-Oct-2025\nEn caso de que el número de partidos políticos sea mayor que el de diputaciones por asignar, éstas se otorgarán a los que tengan mayor porcentaje en orden descendente hasta agotarse.\nArtículo 24.- Ningún partido político podrá tener más de diecisiete diputaciones por ambos principios.\nPárrafo Reformado\nEn ningún caso, un partido político podrá contar con un número de diputaciones por ambos principios que representen un porcentaje del total de la legislatura que exceda en ocho puntos su porcentaje de votación emitida. Esta base no se aplicará al partido político que por sus triunfos en distritos uninominales obtenga un porcentaje de curules del total de la legislatura, superior a la suma del porcentaje de su votación emitida más el ocho por ciento.\nPárrafo Reformado\nAsimismo, en la integración de la legislatura, el porcentaje de representación de un partido político no podrá ser menor al porcentaje de votación que hubiere recibido menos ocho puntos porcentuales. Esta fórmula se aplicará una vez que le sea asignada una diputación por la vía de representación proporcional a los partidos políticos que hayan obtenido el porcentaje de votación mínima para conservar su registro de conformidad con la normativa electoral.\nPárrafo Reformado\nArtículo Reformado\nArtículo 25.- Se determinará si es el caso de aplicar a algún partido político el o los límites establecidos en los párrafos primero y segundo del artículo anterior, para lo cual al partido político cuyo número de diputados por ambos principios exceda de diecisiete, o su porcentaje de curules del total del Congreso exceda en ocho puntos a su porcentaje de votación emitida, le serán deducidos el número de diputados de representación proporcional hasta ajustarse a los límites establecidos, asignándose las diputaciones excedentes a los demás partidos políticos que no se ubiquen en estos supuestos.\nArtículo 26.- Si después de asignadas las diputaciones señaladas en artículo 23 de esta Ley, aún quedasen diputaciones por asignar, se otorgarán a los partidos políticos, en los siguientes términos:\nI. Se obtendrá el porcentaje de votación de los partidos políticos que reúnan los requisitos que señala el artículo 22 de esta Ley, mediante el siguiente procedimiento:\na) Realizará la sumatoria de los votos obtenidos por los partidos políticos, en la elección de diputados por el principio de representación proporcional, que reúnan los requisitos, y\nb) La votación de cada partido se dividirá entre la sumatoria obtenida en el inciso anterior y se multiplicará por cien;\nLey Electoral del Estado de Baja California. Página 10\n.\nActualización Legislativa.\nÚltima reforma P. O. No. 60, Índice, 03-Oct-2025\nII. Se procederá a multiplicar el porcentaje de votación obtenido en la elección de\nDiputados por el principio de representación proporcional de cada partido político, por veinticinco;\nIII. Al resultado obtenido en la fracción anterior se le restarán las diputaciones obtenidas de mayoría y la asignada conforme al artículo anterior;\nIV. Se asignará una diputación de representación proporcional por cada número entero que se haya obtenido en la operación señalada en la fracción anterior, procediendo en estricto orden de prelación conforme al porcentaje obtenido por cada partido político, éstas se otorgarán a los que tengan mayor porcentaje en orden descendente hasta agotarse el número de enteros que corresponda al partido político, en los términos de la fracción I de este artículo, y\nV. Hechas las asignaciones anteriores, si aún existieren diputaciones por asignar, éstas se otorgarán a los que conserven los restos mayores, una vez deducidas las que se asignaron en la fracción anterior.\nArtículo 27.- El Consejo General hará la asignación de diputaciones a cada partido político conforme al resultado obtenido en los artículos anteriores, en los siguientes términos:\nPárrafo Reformado\nI. Determinará que candidatos a Diputados de cada partido político no obtuvieron la constancia de mayoría; debiendo identificar, en el caso de coalición, a qué partido político pertenece el candidato en coalición.\nII. Elaborará una lista en orden descendente de cada partido político con los candidatos que no hayan obtenido la constancia de mayoría, de acuerdo a su porcentaje de votación válida en el distrito respectivo. El porcentaje se tomará hasta diezmilésimas, sin redondear la última cifra.\nSe entenderá por votación valida, la sumatoria de los votos obtenidos por los partidos políticos en el ámbito territorial de que se trate;\nIII. Si dos o más candidatos de un partido político tienen el mismo porcentaje en la lista, hasta antes del séptimo lugar, el Consejo General le solicitará al partido político, para que dentro de las veinticuatro horas siguientes a que sea notificado, determine el lugar que le corresponderá;\nIV. Si dentro del plazo señalado en la fracción anterior el partido político no da respuesta, el Consejo General procederá a determinarlo mediante sorteo; y\nFracción Reformada\nV. Derogada.\nFracción Derogada\nVI. En caso de que la asignación recaiga en quien este inhabilitado o no reúna los respectiva. Si éste último también resulta inhabilitado o no reúne los requisitos para ser\nLey Electoral del Estado de Baja California. Página 11\n.\nActualización Legislativa.\nÚltima reforma P. O. No. 60, Índice, 03-Oct-2025 electo, se asignará aquella fórmula de candidatos del mismo partido político que siga en el orden de la lista.\nLas vacantes de propietarios de Diputados por el principio de representación proporcional, deberá ser cubiertas por los suplentes de la fórmula respectiva. Si la vacante se presenta respecto de la fórmula completa será cubierta por aquella fórmula del mismo partido que sigue en el orden de la lista que para efectos de asignación haya elaborado el\nConsejo General.\nArtículo Reformado\nArtículo 27 BIS.- El Consejo General integrará un sistema de listas, una para mujeres y otra para hombres respecto a las candidatas y candidatos que se encuentren en el supuesto del artículo anterior. La asignación de diputaciones por el principio de representación se hará de manera alternada garantizando en todo momento la paridad de género.\nPárrafo Reformado\nLa primera asignación, según el partido político de que se trate, iniciará con el género femenino o masculino con mayor porcentaje de votación válida en el distrito, a que se refiere el artículo anterior.\nPárrafo Adicionado\nArtículo Adicionado\nArtículo Reformado\nTÍTULO TERCERO\nDel Poder Ejecutivo\nCAPÍTULO ÚNICO\nDe la elección del titular del Poder Ejecutivo del Estado\nArtículo 28.- La elección de Gobernador será cada seis años, en todo el territorio del\nEstado, mediante sufragio universal, libre, secreto, directo, personal e intransferible y por mayoría relativa.\nTÍTULO CUARTO\nDe los ayuntamientos\nCAPÍTULO PRIMERO\nArtículo 29.- El Gobierno del Municipio se deposita en un cuerpo colegiado que se denomina Ayuntamiento, compuesto de munícipes electos mediante sufragio universal, libre, secreto, directo, personal e intransferible, por los principios de mayoría relativa y de representación proporcional. Los integrantes de los Ayuntamientos contarán con sus respectivos suplentes.\nLey Electoral del Estado de Baja California. Página 12\n.\nActualización Legislativa.\nÚltima reforma P. O. No. 60, Índice, 03-Oct-2025\nArtículo 30.- El Ayuntamiento se integra por una Presidencia Municipal, una\nSindicatura Procuradora, por Regidurías de mayoría relativa y de representación proporcional, en el número que dispone la Constitución del Estado.\nPárrafo Reformado\nLos Presidentes Municipales, regidores y síndicos podrán ser postulados, al mismo cargo, para el periodo inmediato siguiente. A los suplentes de los anteriores, que no entren en funciones, no se les computará dicho periodo para efectos de la reelección inmediata.\nLos presidentes municipales, regidores y síndicos únicamente pueden ser electos consecutivamente para el mismo cargo que ostentan y siendo parte de una planilla integrada de conformidad con la fracción II del artículo 136 de la presente ley.\nPárrafo Adicionado\nLas Presidentas o Presidentes Municipales, Regidoras o Regidores y Síndicas o\nSíndicos interesados en la elección consecutiva en términos de lo dispuesto en el párrafo anterior, deberán manifestarlo a su partido político por escrito y con veinte días de anticipación al inicio de las precampañas, de no hacerse en los términos antes señalados, se entenderá que no están interesados en la elección consecutiva. En virtud de lo anterior, los partidos políticos en la determinación de los criterios para garantizar la paridad de género en sus métodos de selección de candidatos deberán respetar el criterio de paridad de género en su aspecto cualitativo y cuantitativo, así como el principio de igualdad sustantiva para personas pertenecientes a una comunidad indígena o afromexicanas.\nPárrafo Adicionado\nPárrafo Reformado\nPara los efectos de lo previsto en la última parte del párrafo anterior, las y los candidatos a las Presidencias Municipales, Regidurías y Sindicaturas, interesados en la elección consecutiva deberán acreditar con documentación actualizada al proceso electoral al que deseen participar su pertenencia a una comunidad indígena o afromexicana.\nPárrafo Adicionado\nEn caso de que un munícipe pretenda ser candidato a un cargo de elección popular diverso al que fue electo no se considera elección consecutiva.\nPárrafo Adicionado\nLa postulación solo podrá ser realizada por el mismo partido o por cualquiera de los partidos integrantes de la coalición que los hubieren postulado; salvo que hayan renunciado o perdido su militancia antes de la mitad de su mandato. independiente y pretendan su elección consecutiva por la misma vía, para obtener el registro de su candidatura deberán cumplir con los requisitos señalados en los artículos 14, 26 y 27 de la Ley que Reglamenta las Candidaturas Independientes del Estado de Baja California.\nPárrafo Adicionado postularse para la reelección con la misma calidad de candidato independiente, salvo que se\nLey Electoral del Estado de Baja California. Página 13\n.\nActualización Legislativa.\nÚltima reforma P. O. No. 60, Índice, 03-Oct-2025 afilie y demuestre su militancia en un partido político antes de la mitad de su periodo, caso en el que si podrá postularse para reelección por dicho partido.\nLas personas que por elección indirecta o por nombramiento o designación de alguna autoridad desempeñen las funciones propias de esos cargos, cualquiera que sea la denominación que se les dé, podrán ser electas en el período inmediato.\nArtículo Reformado\nArtículo 31.- Para que los partidos políticos o candidaturas independientes tengan derecho a la asignación de Regidurías por el principio de representación proporcional, deberán cumplir los siguientes presupuestos:\nPárrafo Reformado\nI. Haber registrado planilla completa de candidatos a munícipes en el Municipio que corresponda;\nII. Haber obtenido por lo menos el tres por ciento de la votación emitida en la elección de munícipes correspondiente, y\nIII. No haber obtenido la constancia de mayoría respectiva.\nArtículo Reformado\nArtículo 32.- El Consejo General, hará la asignación de regidores mediante el principio de representación proporcional, conforme al siguiente procedimiento:\nI. Determinará qué partidos políticos o candidatos independientes cumplen con lo establecido en el artículo anterior;\nFracción Reformada\nII. Primeramente asignará un Regidor a cada partido político o candidato independiente con derecho.\nFracción Reformada\nEn el caso que el número de partidos políticos o candidatos independientes sea mayor que el de regidurías por asignar, éstas se otorgarán a los que tengan mayor porcentaje en orden descendente hasta agotarlas;\nPárrafo Reformado\nIII. Si después de efectuada la operación indicada en la fracción anterior, aún hubieren regidurías por asignar, realizará las siguientes operaciones:\na).- Sumará los votos de los partidos políticos o candidatos independientes con derecho a ello, que servirá como base para obtener los nuevos porcentajes de participación a que se refiere el inciso siguiente;\nInciso Reformado\nb).- Determinará el nuevo porcentaje de cada partido político o candidato independiente que tenga derecho a la asignación, mediante el cociente natural que se\nLey Electoral del Estado de Baja California. Página 14\n.\nActualización Legislativa.\nÚltima reforma P. O. No. 60, Índice, 03-Oct-2025 independiente por cien, dividiendo el resultado entre la suma de los votos de los partidos políticos o candidatos independientes participantes;\nInciso Reformado\nc).- Obtendrá la expectativa de integración al Ayuntamiento de cada partido político o candidato independiente con derecho a ello, mediante el cociente natural que se obtiene multiplicando el porcentaje obtenido en el inciso anterior, de cada partido político o candidato independiente, por el número de regidurías de representación proporcional que corresponda, conforme al artículo 79, fracción I, de la Constitución del Estado y dividiéndolo entre cien; y\nInciso Reformado\nd).- Restará de la expectativa de integración al Ayuntamiento a cada partido político o candidato independiente, la asignación efectuada conforme a la fracción II de este artículo;\nInciso Reformado\nIV. Asignará a cada partido político o candidato independiente alternadamente, tantas regidurías como números enteros se hayan obtenido de la operación realizada en el inciso d) de la fracción anterior;\nFracción Reformada\nV. En caso de que aún hubieren regidurías por repartir, las asignará a los partidos políticos o candidatos independientes que conserven los restos mayores, después de deducir las asignaciones efectuadas en la fracción anterior;\nFracción Reformada\nVI. La asignación de regidurías de representación proporcional, se hará de la planilla de candidatos a Regidores que haya registrado cada partido político o candidato independiente, en el orden que los mismos fueron registrados. Si por alguna causa a los partidos coaligados no se les pudiera repartir las regidurías correspondientes, solo se les asignarán, en su caso, las regidurías que conforme al convenio de coalición le correspondan; las sobrantes por este motivo se asignarán a los partidos políticos que conforme la fórmula del presente artículo tengan ese derecho, observando lo dispuesto en la fracción IV de este precepto.\nFracción Reformada\nVII. En caso de que la asignación recaiga en quien esté inhabilitado o no reúna los requisitos para ser electo, la asignación deberá ser cubierta por el suplente de la planilla respectiva. Si éste último resulta también inhabilitado o no reúne los requisitos para ser electo, se asignará a aquel candidato del mismo partido político o candidato independiente que siga en el orden de la lista.\nFracción Reformada proporcional, deberán ser cubiertas por los suplentes de la planilla respectiva.\nArtículo Reformado\nLIBRO TERCERO\nLey Electoral del Estado de Baja California. Página 15\n.\nActualización Legislativa.\nÚltima reforma P. O. No. 60, Índice, 03-Oct-2025\nDel Instituto Estatal Electoral\nTÍTULO PRIMERO\nNaturaleza Jurídica\nCapítulo Único\nArtículo 33.- El Instituto Estatal Electoral es un organismo público, autónomo en su funcionamiento e independiente en sus decisiones, de carácter permanente, con personalidad jurídica y patrimonio propio. Se regirá en su organización, funcionamiento y control, por las disposiciones contenidas en la Constitución del Estado, en la Ley General y en esta Ley.\nEl Instituto, es depositario de la autoridad electoral y responsable del ejercicio de la función pública de organizar las elecciones, así como los procesos de plebiscito, referéndum y consulta popular, en los términos de la Ley de la materia.\nEl Instituto administrará los recursos públicos a su cargo con austeridad y conforme a los principios de eficiencia, eficacia, economía, transparencia y honradez y de acuerdo con los criterios establecidos en el artículo 134 de la Constitución Federal. Para ello, está obligado a cumplir lo dispuesto en las Leyes aplicables en materia de adquisiciones, arrendamientos y servicios, y en materia de obras públicas, equipamientos, suministros y servicios.\nPárrafo Adicionado\nArtículo Reformado\nArtículo 34.- El patrimonio del Instituto Estatal se integra con los bienes muebles e inmuebles que se destinen al cumplimiento de su objeto y las partidas que anualmente se les señalen en el presupuesto de egresos del Estado, para la organización de los procesos electorales locales y para el financiamiento de los partidos políticos.\nArtículo 35.- Son fines del Instituto Estatal:\nI. Contribuir al desarrollo de la vida democrática en el Estado;\nII. Asegurar a los ciudadanos el ejercicio de los derechos político electorales y el cumplimiento de sus obligaciones;\nIII. Garantizar la celebración periódica y pacífica de las elecciones para renovar la integración de los Poderes Legislativo y Ejecutivo, y los Ayuntamientos del Estado;\nIV. Preservar la autenticidad y efectividad del sufragio;\nV. Realizar los procesos de consulta popular, plebiscito y referéndum en los términos de la ley de la materia, y\nVI. Llevar a cabo la promoción del voto y coadyuvar al fortalecimiento y difusión de la cultura cívica y política.\nLey Electoral del Estado de Baja California. Página 16\n.\nActualización Legislativa.\nÚltima reforma P. O. No. 60, Índice, 03-Oct-2025\nVII. Garantizar la paridad de género y el respeto de los derechos humanos de las mujeres en el ámbito político y electoral.\nFracción Adicionada\nVIII. Garantizar el principio de igualdad sustantiva.\nFracción Adicionada\nLas actividades del Instituto se llevarán a cabo con perspectiva de género y regirán por los principios de certeza, legalidad, independencia, imparcialidad, máxima publicidad, objetividad austeridad, paridad y se realizarán con perspectiva de género. Para el desempeño de sus actividades, el Instituto contará con un cuerpo de servidores públicos en sus órganos ejecutivos y técnicos, integrados en un Servicio Profesional Electoral conforme lo establecido en Ley General y el Estatuto que apruebe el Instituto Nacional.\nPárrafo Reformado\nAdicionalmente, el Instituto contará con personal adscrito a una rama administrativa, para el óptimo desempeño de las funciones institucionales.\nArtículo Reformado\nArtículo 36.- El Instituto Estatal tendrá su sede en la capital del Estado y ejercerá sus funciones en todo su territorio, y se integrará por:\nI. Un órgano de dirección, que es el Consejo General del Instituto;\nII. Órganos ejecutivos, que son:\na) La Presidencia del Consejo General;\nb) La Junta General Ejecutiva, y\nc) La Secretaría Ejecutiva.\nIII. Órganos técnicos, que son:\na) Las comisiones permanentes del Consejo General;\nb) La Unidad Técnica de lo Contencioso Electoral de la Secretaría Ejecutiva, y\nc) El Departamento de Control Interno adscrito a la Presidencia del Consejo General.\nIV. Los Consejos Distritales Electorales, órganos operativos.\nTÍTULO SEGUNDO\nCAPÍTULO PRIMERO\nDel Consejo General\nArtículo 37.- El Consejo General es el órgano superior de dirección, responsable de vigilar el cumplimiento de las disposiciones constitucionales y legales en materia electoral, aplicando en su desempeño la perspectiva de género, así como de velar que los principios\nLey Electoral del Estado de Baja California. Página 17\n.\nActualización Legislativa.\nÚltima reforma P. O. No. 60, Índice, 03-Oct-2025 de certeza, legalidad, independencia, imparcialidad, igualdad sustantiva, máxima publicidad, objetividad, paridad de género y guíen todas las actividades del Instituto Estatal. En su desempeño aplicará la perspectiva género.\nArtículo Reformado\nArtículo 38.- El Consejo General se integra por un Consejero Presidente, seis\nConsejeros Electorales, con derecho a voz y voto; y por representantes de los partidos políticos y el Secretario Ejecutivo, con derecho a voz.\nLa duración del cargo, requisitos de elegibilidad, elección, vacantes y remoción del\nConsejero Presidente y los Consejeros Electorales se rigen por la Constitución Federal, la\nLey General y demás leyes aplicables.\nArtículo 39.- El Consejero Presidente y los Consejeros Electorales, no podrán tener otro empleo, cargo o comisión, con excepción de los no remunerados en actividades docentes, científicas, culturales, de investigación o de beneficencia. Tampoco podrán asumir un cargo público en los órganos emanados de las elecciones en cuya organización y desarrollo hubieren participado, ni ser postulados para un cargo de elección popular o asumir un cargo de dirigencia partidista, durante los dos años posteriores al término de su encargo.\nArtículo 40.- El quórum válido para sesionar se integrará con más de la mitad de los consejeros electorales y de los representantes de los partidos políticos.\nEn caso de que no se reúna la mayoría que se señala en el párrafo anterior, la sesión tendrá lugar dentro de las veinticuatro horas siguientes, con los consejeros y representantes que asistan, mismo procedimiento se seguirá cuando iniciada una sesión, por cualquier razón desaparezca el quórum.\nEn todos los casos, deberán estar presentes por lo menos tres consejeros electorales y el Consejero Presidente.\nEl Consejero Presidente, será suplido en sus ausencias momentáneas en las sesiones por el consejero que él mismo designe. En el supuesto de que el Consejero\nPresidente no asista o se ausente en forma definitiva de la sesión, el Presidente de la\nComisión Permanente que corresponda en el orden de las fracciones del artículo 45 de esta ley, presidira la sesión.\nArtículo 41.- Las resoluciones se tomarán por mayoría de votos de los presentes, salvo los casos en que se requiera mayoría calificada. En caso de persistir el empate después de una segunda ronda de votaciones, el Consejero Presidente o quien lo supla decidirá, debiendo razonar su voto, “en favor” o “en contra”.\nArtículo 42.- La Secretaría Ejecutiva del Consejo General estará a cargo del\nSecretario Ejecutivo del Instituto Estatal. En caso de ausencia del Secretario Ejecutivo a la sesión, sus funciones serán realizadas por algún coordinador adscrito a éste, que al efecto designe el Consejo General para esa sesión.\nLey Electoral del Estado de Baja California. Página 18\n.\nActualización Legislativa.\nÚltima reforma P. O. No. 60, Índice, 03-Oct-2025\nArtículo 43.- El Consejo General se reunirá en la fecha que señala el artículo 5 de la\nConstitución del Estado para el inicio del proceso electoral, a efecto de celebrar sesión pública en la que procederá a:\nI. Hacer la declaración formal de inicio del proceso electoral, y\nII. Acordar el calendario de sesiones ordinarias.\nA partir de este acto y hasta que los resultados electorales causen estado, el Consejo\nGeneral sesionará por lo menos una vez al mes. En los períodos comprendidos entre procesos electorales ordinarios, sesionará por lo menos cada dos meses.\nArtículo 44.- El Consejo General sesionará previa convocatoria del Consejero\nPresidente.\nPara las sesiones ordinarias los integrantes del Consejo General serán citados cuando menos con cuarenta y ocho horas de anticipación y en las extraordinarias, con veinticuatro horas, debiéndose acompañar invariablemente los documentos que sustenten los asuntos a tratar.\nEl Consejero Presidente convocará a sesión extraordinaria cuando lo estime necesario o a solicitud que le formulen la mayoría de los representantes acreditados de los partidos políticos o de la mayoría de los consejeros electorales, señalándose en estos casos el motivo de la cita y los asuntos a tratar.\nRecibida la solicitud a que se refiere el párrafo anterior, el Consejo General celebrará sesión extraordinaria dentro de las cuarenta y ocho horas siguientes, previa convocatoria del\nConsejero Presidente.\nArtículo 45.- El Consejo General funcionará en pleno o en comisiones. Las comisiones permanentes serán:\nI. Comisión del Régimen de Partidos Políticos y Financiamiento;\nII. Comisión de Reglamentos y Asuntos Jurídicos;\nIII. Comisión de Procesos Electorales;\nIV. Comisión de Participación Ciudadana y Educación Cívica;\nV. Comisión de Control Interno;\nFracción Reformada\nVI. Comisión de Quejas y Denuncias, y\nFracción Reformada\nVII. Comición de Igualdad Sustantiva y No Discriminación.\nFracción Adicionada renueve parcialmente el Consejo General.\nLey Electoral del Estado de Baja California. Página 19\n.\nActualización Legislativa.\nÚltima reforma P. O. No. 60, Índice, 03-Oct-2025\nEl Consejo General, podrá integrar las comisiones especiales que considere necesarias para el desempeño de sus atribuciones. Reglamentará las atribuciones que le corresponderán a cada una de ellas, además de las previstas en la presenten Ley.\nLas comisiones se integrarán con un máximo de tres consejeros electorales designados por el Pleno, quienes serán los únicos con voto. De entre ellos nombrarán a su\nPresidente y contarán con un Secretario Técnico que será el titular del área que corresponda.\nLas ausencias de los secretarios técnicos en las reuniones de trabajo o sesiones, serán cubiertas por quien designe el Presidente de la Comisión, de entre el personal del\nInstituto Estatal.\nEn todos los asuntos que les encomienden, las comisiones deberán presentar un informe, opinión, punto de acuerdo o dictamen, según sea la naturaleza del asunto turnado, fundando y motivándolos, en el que consideren las opiniones de los partidos políticos y las pruebas que se hubiesen presentado, cuando sea el caso. Los representantes de los partidos políticos deberán ser convocados a las reuniones de trabajo y a las sesiones que celebren las comisiones.\nArtículo Reformado\nSección Primera\nDe sus atribuciones\nArtículo 46.- El Consejo General tendrá las siguientes atribuciones:\nI. Aprobar las iniciativas de Ley o Decreto en materia electoral para ser enviadas al Congreso del Estado;\nII. Expedir los reglamentos y acuerdos necesarios para hacer efectivo el cumplimiento de las disposiciones de esta Ley; así como, los reglamentos interiores, circulares y lineamientos necesarios para el funcionamiento del Instituto Estatal, y fijar las políticas y programas de éste;\nIII. Garantizar la oportuna integración, instalación y adecuado funcionamiento de los órganos del Instituto, así como conocer de los informes específicos que estime necesario solicitarles;\nIV. Designar o remover por el voto de las dos terceras partes de sus integrantes con derecho a ello, al Secretario Ejecutivo del Instituto Estatal, conforme a la propuesta del\nConsejero Presidente;\nV. Designar o remover a los consejeros electorales numerarios y supernumerarios de los Consejos Distritales Electorales, mediante el voto de las dos terceras partes de sus integrantes con derecho a ello, a propuesta de la comisión respectiva, así como al Consejero\nPresidente de cada uno de los Consejos Distritales Electorales, de entre los propios consejeros, a propuesta del Consejero Presidente del Consejo General;\nLey Electoral del Estado de Baja California. Página 20\n.\nActualización Legislativa.\nÚltima reforma P. O. No. 60, Índice, 03-Oct-2025\nVI. Designar o remover a los titulares de los Departamentos de Procesos\nElectorales, Administración, de Control Interno, y de la Unidad Tecnica de lo Contencioso\nElectoral, conforme a la propuesta que presente el Consejero Presidente;\nVII. Designar o remover al Coordinador de Comunicación Social del Consejo\nGeneral a propuesta del Consejero Presidente, así como expedir el Reglamento para el funcionamiento de la Coordinación;\nVIII. Integrar las comisiones permanentes y especiales del Consejo General, a propuesta del Consejero Presidente, o en su caso, de la mayoría de los consejeros electorales numerarios.\nIX. Aprobar, a propuesta de la Secretaría Ejecutiva del Instituto, dentro de cada uno de los Distritos Electorales, el domicilio que les servirá de cabecera, a los Consejos\nDistritales Electorales;\nX. Resolver sobre el otorgamiento o la cancelación del registro de los partidos políticos locales o el otorgamiento o la cancelación de la acreditación de los partidos políticos nacionales, en los términos de la legislacion aplicable;\nXI. Aprobar anualmente las ministraciones para la entrega del financiamiento público a los partidos políticos, y el calendario mensual correspondiente;\nXII. Determinar los topes máximos de gastos de precampaña y campaña que puedan erogarse en las elecciones de Gobernador, Munícipes y Diputados;\nXIII. Registrar la plataforma electoral que para cada proceso electoral deben presentar los candidatos independientes, partidos políticos y coaliciones en los términos de esta Ley;\nXIV. Resolver sobre los convenios de coalición o fusión que celebren los partidos políticos;\nXV. Imprimir los documentos y producir los materiales electorales, en términos de los lineamientos que al efecto emita el Instituto Nacional;\nXVI. Registrar las candidaturas a Gobernador del Estado y Munícipes.\nFracción Reformada\nXVII. Recibir supletoriamente las solicitudes de registro de fórmulas de candidatos a diputados por el principio de mayoría relativa, cuando exista imposibilidad por parte de la autoridad distrital electoral competente de recibirlas, para su posterior remisión al órgano correspondiente;\nXVIII. Realizar el cómputo estatal de la elección de Diputados por el principio de representación proporcional y asignar las diputaciones correspondientes;\nXIX. Informar al Congreso del Estado sobre el otorgamiento de las constancias de asignación de diputados por el principio de representación proporcional;\nLey Electoral del Estado de Baja California. Página 21\n.\nActualización Legislativa.\nÚltima reforma P. O. No. 60, Índice, 03-Oct-2025\nXX. Realizar el cómputo municipal de la elección de munícipes, declarar la validez de la misma y expedir la constancia de mayoría correspondiente;\nXXI. Asignar Regidores de representación proporcional de cada municipio, según corresponda, informando al Ayuntamiento respectivo, y al Congreso del Estado;\nXXII. Realizar el cómputo estatal de la elección de Gobernador, declarar la validez de la misma y expedir la constancia de mayoría correspondiente, informando al Congreso del\nEstado;\nXXIII. Aprobar anualmente el proyecto de presupuesto de egresos del Instituto\nEstatal, para su inclusión en el proyecto de presupuesto de egresos del Estado, que el\nEjecutivo proponga al Congreso del Estado;\nXXIV. Conocer de las infracciones y faltas, en el ámbito de su competencia, y en su caso, imponer las sanciones que correspondan, en los términos establecidos en la esta Ley;\nXXV. Conocer y acordar lo conducente respecto del informe anual que deba rendir el\nSecretario Ejecutivo del Instituto;\nXXVI. Autorizar la celebración de convenios de apoyo y colaboración con las autoridades federales o estatales electorales en materia electoral;\nXXVII. Expedir las convocatorias para las elecciones ordinarias, las cuales se sujetarán a las bases que contenga la misma y a las disposiciones de esta Ley;\nXXVIII. Aprobar el proyecto para la realización del proceso electoral extraordinario, consulta popular, plebiscito y referéndum, a propuesta del Secretario Ejecutivo; convocando en su caso, a los Consejos Distritales Electorales necesarios;\nXXIX. Procurar que las actividades de los partidos políticos se desarrollen con apego a esta Ley y cumplan con las obligaciones a que están sujetos;\nXXX. Procurar que en lo relativo a las prerrogativas de los partidos políticos se actúe con apego a esta Ley y demás disposiciones aplicables;\nXXXI. Ampliar o modificar los plazos y términos del proceso electoral establecidos en esta Ley, tanto para elecciones ordinarias como extraordinarias, cuando exista imposibilidad material para realizar las actividades previstas, y resulte necesario para el cumplimiento de las diversas etapas del proceso electoral. Las convocatorias para estas elecciones se\nXXXII. Ordenar la publicación en el Periódico Oficial del Estado, en los diarios de mayor circulación y en aquellos medios que se consideren convenientes, las modificaciones a los plazos y términos del proceso electoral, a más tardar dentro de los cinco días siguientes a la fecha de su aprobación;\nXXXIII. Verificar el cumplimiento de los criterios generales que emita el Instituto estudios en el Estado;\nLey Electoral del Estado de Baja California. Página 22\n.\nActualización Legislativa.\nÚltima reforma P. O. No. 60, Índice, 03-Oct-2025\nXXXIV. Desarrollar las actividades que se requieran para garantizar el derecho de los ciudadanos a realizar labores de observación electoral en la entidad de que se trate, de acuerdo con los lineamientos y criterios que emita el Instituto Nacional;\nXXXV. Ordenar la realización de conteos rápidos basados en las actas de escrutinio y cómputo de casilla a fin de conocer las tendencias de los resultados el día de la jornada electoral, de conformidad con los lineamientos emitidos por el Instituto Nacional;\nXXXVI. Aprobar las solicitudes de transferencias, ampliación, creación o supresión de partidas presupuestales que le sean presentadas, cuando así proceda, ordenando su remisión al Congreso del Estado para su autorización, de conformidad con la normatividad aplicable;\nXXXVII. Aprobar anualmente, previo informe del Secretario Ejecutivo, el cierre del ejercicio presupuestal y programático, autorizando su publicación en el Periódico Oficial del\nEstado; cierre que deberá integrarse a la cuenta pública que se turna al Congreso del\nEstado, para los efectos legales correspondientes, y\nXXXVIII. Las demás que disponga esta Ley.\nArtículo Reformado\nSección Segunda\nDel Consejero Presidente y del Secretario del Consejo General\nArtículo 47.- Son atribuciones del Consejero Presidente del Consejo General:\nI. Preservar la unidad y cohesión de las actividades de los órganos del Instituto\nElectoral;\nII. Establecer los vínculos y celebrar los convenios entre el Instituto y las autoridades federales, estatales y municipales, centros de enseñanza para el apoyo y colaboración en sus respectivos ámbitos, cuando sea necesario para el cumplimiento de los fines del Instituto haciéndolo del conocimiento del Consejo General. En caso de convenios con organismos electorales se estará a lo dispuesto en la fracción XXVI del artículo anterior;\nIII. Convocar y conducir las sesiones del Consejo General, declarando el quórum;\nIV. Informar oportunamente al Instituto Nacional, las vacantes que se originen entre los consejeros electorales del Consejo General, para los efectos de sus correspondientes sustituciones;\nV. Vigilar y proveer lo necesario para el cumplimiento de los acuerdos adoptados por el Consejo General;\nVI. Proponer al Consejo General el nombramiento o remoción del Secretario\nEjecutivo; a los titulares de los Departamentos de Procesos Electorales, Administración, Control Interno, y de la Unidad Tecnica de lo Contencioso Electoral; de los Consejeros\nPresidentes de los Consejos Distritales, y al Coordinador de Comunicación Social del\nConsejo General, en los términos dispuestos en esta Ley;\nLey Electoral del Estado de Baja California. Página 23\n.\nActualización Legislativa.\nÚltima reforma P. O. No. 60, Índice, 03-Oct-2025\nVII. Proponer anualmente al Consejo General el anteproyecto de presupuesto del\nInstituto Estatal, para su aprobación;\nVIII. Remitir a los Poderes Ejecutivo y Legislativo, el proyecto de presupuesto del\nInstituto aprobado por el Consejo General, en los términos de la ley de la materia;\nIX. Presidir la Junta General Ejecutiva e informar al Consejo General de los trabajos de la misma;\nX. Someter a consideración del Consejo General las propuestas para la creación de áreas o unidades técnicas, para el mejor funcionamiento del Instituto, que le formule el\nSecretario Ejecutivo;\nXI. Turnar a la Comisión competente aquellos asuntos que por la urgencia de su resolución así lo requieran;\nXII. Ordenar la publicación en el Periódico Oficial del Estado de los acuerdos o resoluciones que establezca esta Ley y los que determine el Consejo General;\nXIII. Remitir al Congreso del Estado las Iniciativas de Ley o Decreto aprobadas por el Consejo General;\nXIV. Firmar, junto con el Secretario Ejecutivo, todos los acuerdos, certificaciones y resoluciones que emita el Consejo General;\nXV. Representar legalmente al Consejo General, cuando se interponga algún recurso en contra de sus actos o resoluciones, y\nXVI. Las demás que disponga esta Ley.\nArtículo 48.- En el caso de ausencia definitiva del Consejero Presidente del Consejo\nGeneral, los Consejeros Electorales nombrarán, de entre ellos mismos, a quien deba sustituirlo provisionalmente, comunicando de inmediato al Instituto Nacional a fin de que se designe su sustituto en los términos de la Ley General.\nArtículo 49.- Corresponden al Secretario del Consejo General, las siguientes atribuciones: atribuciones;\nII. Preparar el orden del día de las sesiones del Consejo General, pasar lista de asistencia, dar fe de lo actuado en las sesiones y levantar el acta correspondiente;\nIII. Informar sobre el cumplimiento de los acuerdos del Consejo General;\nIV. Dar cuenta de la correspondencia recibida y despachada;\nV. Llevar el archivo del Consejo;\nVI. Con relación a los partidos políticos, llevar los archivos de los partidos políticos correspondientes a: registro o acreditación; convenios de fusión o coalición; candidatos a los\nLey Electoral del Estado de Baja California. Página 24\n.\nActualización Legislativa.\nÚltima reforma P. O. No. 60, Índice, 03-Oct-2025 cargos de elección popular, e integrantes de los órganos directivos y sus representantes acreditados ante los Consejos del Instituto;\nVII. Recibir y dar el trámite previsto en esta ley, a los medios de impugnación que se interpongan en contra de los actos o resoluciones del Consejo General;\nVIII. Expedir los documentos que acrediten la personalidad de los consejeros y de los representantes de los partidos políticos;\nIX. Firmar, junto con el Presidente del Consejo General, todos los acuerdos, certificaciones y resoluciones que emita el Consejo;\nX. Expedir las certificaciones que se requieran;\nXI. Integrar los expedientes con las actas de los cómputos distritales de las elecciones de gobernador, munícipes y diputados por el principio de representación proporcional;\nXII. Cumplir las instrucciones del Presidente del Consejo General y auxiliarlo en sus tareas, y\nXIII. Las demás que le sean conferidas en esta Ley, o por el Consejo General y su\nPresidente.\nCAPÍTULO SEGUNDO\nDe la Junta General Ejecutiva\nArtículo 50.- La Junta General Ejecutiva será presidida por el Presidente del Consejo\nGeneral y se integrará con el Secretario Ejecutivo y con los titulares de los Departamentos de Procesos Electorales, de Administración, de la Unidad Técnica de lo Contencioso\nElectoral, así como por el Coordinador de Partidos Políticos y Financiamiento.\nEl Titular del Departamento de Control Interno, y los coordinadores Jurídico, y de\nInformática y Estadística Electoral podrán participar, a convocatoria del Consejero\nPresidente, en las sesiones de la Junta General Ejecutiva.\nArtículo 51.- La Junta General Ejecutiva se reunirá por lo menos una vez al mes, siendo sus atribuciones las siguientes:\nI. Proponer al Consejo General las políticas y los programas generales del\nInstituto Estatal;\nII. Fijar los procedimientos administrativos, conforme a las políticas y programas generales del Instituto;\nIII. Supervisar el cumplimiento de las normas aplicables a los partidos políticos;\nIV. Supervisar el cumplimiento de los programas de educación cívica del Instituto;\nV. Desarrollar las acciones necesarias para asegurar que los consejos distritales, sesionen y funcionen en los términos previstos por la presente Ley;\nLey Electoral del Estado de Baja California. Página 25\n.\nActualización Legislativa.\nÚltima reforma P. O. No. 60, Índice, 03-Oct-2025\nVI. Integrar los expedientes relativos a las faltas administrativas cometidas por funcionarios electorales en materia electoral y, en su caso, hacer del conocimiento a la\nComisión de Control Interno, para los efectos conducentes;\nVII. Recibir informes del Titular del Departamento de Control Interno respecto de los expedientes relativos a las faltas administrativas y en su caso, sobre imposición de sanciones a los servidores públicos del Instituto Estatal y en términos de la Ley General; y\nVIII. Las demás que le encomienden esta Ley, el Consejo General o su presidente.\nCAPÍTULO TERCERO\nDel Secretario Ejecutivo y de los Departamentos\nSección Primera\nDel Secretario Ejecutivo\nArtículo 52.- El Secretario Ejecutivo coordina la Junta General, conduce la administración y supervisa el desarrollo adecuado de las actividades de los órganos ejecutivos, técnicos y operativos del Instituto. Al Secretario Ejecutivo, le es aplicable lo establecido en el artículo 39 de esta Ley.\nArtículo 53.- El Secretario Ejecutivo investido de fe pública para actos de naturaleza electoral, será nombrado por el Consejo General a propuesta del Consejero Presidente, con la aprobación de las dos terceras partes de sus integrantes, durará en su encargo cuatro años y podrá ser reelecto una sola vez; en el supuesto de que transcurridas dos rondas de votación, el aspirante propuesto no alcanzare la votación requerida, la designación se hará por mayoría simple del Consejo General.\nArtículo 54.- El Secretario Ejecutivo del Instituto, deberá satisfacer los mismos requisitos que se establecen para los consejeros electorales del Consejo General, salvo el estipulado en el inciso k), del parráfo 2, del artículo 100, de la Ley General; siendo designado bajo el siguiente procedimiento:\nI. El Consejero Presidente del Consejo General propondrá al aspirante al cargo de Secretario Ejecutivo, para ser designado mediante la votación aprobatoria de las dos terceras partes de los integrantes del mismo; en el supuesto de que transcurridas dos rondas de votación, el aspirante no alcanzare la votación requerida, la designación se hará por mayoría simple del Consejo General;\nII. En el supuesto de que el aspirante propuesto no alcanzaré la votación requerida en la fracción anterior, dentro de los cinco días siguientes se procederá a integrar una propuesta por el Consejero Presidente.\nIII. Corresponderá en todos los casos, a la Comisión de Reglamentos y Asuntos\nJurídicos del Consejo General, dictaminar sobre los requisitos de elegibilidad de los candidatos que se propongan.\nIV. Para la reelección del Secretario Ejecutivo, se estará a lo siguiente:\nLey Electoral del Estado de Baja California. Página 26\n.\nActualización Legislativa.\nÚltima reforma P. O. No. 60, Índice, 03-Oct-2025\na) Tres meses antes de que concluya el cargo, el titular respectivo deberá solicitar al Presidente del Consejo General, inicie el proceso de ratificación exponiendo los motivos por los cuales considere debe ser reelecto. De no presentarse la solicitud en el plazo indicado, se entenderá por renunciado el derecho de ser ratificado;\nb) Recibida la solicitud, será turnada inmediatamente a la Comisión de\nReglamentos y Asuntos Jurídicos a efecto de que inicie el proceso de reelección, debiendo integrar al expediente los elementos que considere idóneos para resolver lo conducente, para lo cual tendrá un plazo de treinta días naturales improrrogables;\nc) Integrado el expediente, se dará vista al titular respectivo para que en un plazo de diez días naturales contados a partir del día siguiente al de la notificación, manifieste lo que a su derecho convenga;\nd) Recibida la manifestación o en su caso transcurrido el plazo referido en el inciso anterior, la Comisión en un plazo de treinta días naturales improrrogables, deberá emitir el Dictamen que conforme a derecho corresponda, precisando si el Secretario\nEjecutivo sujeto a proceso de ratificación, durante su desempeño ha ejercido el cargo con excelencia profesional, honestidad, diligencia, que goza de buena reputación y buena fama en la función pública electoral, además de precisar si conserva los requisitos requeridos para su nombramiento, y\ne) El Dictamen será turnado al Consejo General para que dentro de los cinco días hábiles de recibido resuelva lo conducente.\nArtículo 55.- Son atribuciones del Secretario Ejecutivo:\nI. Representar legalmente al Instituto Electoral, y otorgar previa autorización del\nConsejo General poderes a nombre de éste para actos de administración y para ser representado ante cualquier autoridad administrativa, judicial o ante particulares;\nII. Actuar como Secretario del Consejo General;\nIII. Cumplir y hacer cumplir, en los asuntos de su competencia, los acuerdos del\nConsejo General;\nIV. Informar oportunamente al Consejo General, las vacantes que se originen entre los consejeros electorales de los Consejos Distritales, para los efectos de sus correspondientes sustituciones;\nV. Someter al conocimiento y, en su caso, a la aprobación del Consejo General los asuntos de su competencia;\nVI. Ejercer y atender oportunamente la función de oficialía electoral por sí, o por conducto de los Secretarios Fedatarios de los Consejos Distritales, u otros servidores exclusivamente de naturaleza electoral. El Secretario Ejecutivo podrá delegar la atribución en servidores públicos a su cargo;\nLey Electoral del Estado de Baja California. Página 27\n.\nActualización Legislativa.\nÚltima reforma P. O. No. 60, Índice, 03-Oct-2025\nVII. Designar o remover al Coordinador de Partidos Políticos y Financiamiento, Coordinador Jurídico, Coordinador de Informática y Estadística Electoral, y al Notificador de la Secreataría Ejecutiva.\nVIII. Orientar y coordinar las acciones de los Departamentos de la Junta General\nEjecutiva, Coordinaciones y Unidades Técnicas a su cargo; así como presentar ante el\nConsejo General, todos aquellos asuntos de las mismas, que requieran de su aprobación;\nIX. Coadyuvar con la Comisión de Control Interno y el Departamento respectivo, en los procedimientos para la determinación de responsabilidades e imposición de sanciones a los servidores públicos del Instituto;\nX. Aprobar las estructuras de los Departamentos, Coordinaciones y Unidades\nTécnicas del Instituto, conforme a las necesidades del servicio y los recursos presupuestales autorizados;\nXI. Proveer a los órganos del Instituto de los elementos necesarios para el cumplimiento de sus funciones;\nXII. Actuar como secretario de la Junta General Ejecutiva y preparar el orden del día de sus sesiones;\nXIII. Administrar los bienes muebles e inmuebles, inversiones y rendimientos financieros, y ejercer el presupuesto del Instituto Electoral;\nXIV. Proporcionar la información presupuestal, contable y financiera, que para los efectos de revisión de la Cuenta Pública lo requiera el Congreso del Estado;\nXV. Presentar al Consejo General, un informe anual por escrito del ejercicio presupuestal de la Dirección a su cargo, así como informe anual de actividades durante los primeros diez días del mes de noviembre;\nXVI. Integrar y publicar la memoria del proceso electoral conteniendo la estadística electoral por Estado, Municipio, Distrito y Sección, una vez concluido el proceso electoral;\nXVII. Recabar, para efectos de información y estadísticas electorales, copias de los expedientes de todas las elecciones;\nXVIII. Administrar el Padrón Electoral y los Listados Nominales que le sean proporcionados por el Instituto Nacional;\nXIX. Elaborar el anteproyecto de presupuesto de egresos del Instituto Electoral, atendiendo, en su caso, los programas que fije el Consejero Presidente del Consejo\nGeneral;\nXX. Preparar el anteproyecto de presupuesto para la realización de elecciones extraordinarias, plebiscito, referéndum y consulta popular y someterlo a la aprobación del\nConsejo General;\nXXI. Elaborar manuales de organización de los Departamentos, Coordinaciones y\nUnidades Técnicas del Instituto;\nLey Electoral del Estado de Baja California. Página 28\n.\nActualización Legislativa.\nÚltima reforma P. O. No. 60, Índice, 03-Oct-2025\nXXII. Elaborar los proyectos de reglamento interno de la Secretaría Ejecutiva y de los\nConsejos Distritales Electorales, para someterlos a consideración del Consejo General, y\nXXIII. Las demás que le encomienden el Consejo General, su Presidente, y esta Ley.\nArtículo 56.- Las ausencias temporales del Secretario Ejecutivo, serán suplidas por alguno de los integrantes de la Junta General Ejecutiva que designe el Consejero Presidente del Consejo General. Se entenderá por ausencia temporal, aquella que exceda el plazo de tres días en proceso electoral, y de quince días fuera de éste.\nDe igual forma serán suplidas las ausencias definitivas, hasta en tanto el Consejo\nGeneral designe al titular en los términos señalados en esta Ley.\nArtículo 57.- La Secretaría Ejecutiva tendrá adscrita las siguientes áreas:\nI. La Unidad Técnica de lo Contencioso Electoral que será competente para la tramitación de los procedimientos sancionadores y demás que determine esta Ley y las disposiciones aplicables;\nII. La Coordinación de Partidos Políticos y Financiamiento que tendrá como funciones:\na) Prestar la asesoría legal correspondiente a la Secretaría, a la Comisión del\nRégimen de Partidos Políticos, y en su caso, a los representantes de los partidos políticos o coaliciones;\nb) Coordinar y supervisar la elaboración de dictámenes, puntos de acuerdo, informes u opiniones de la Comisión del Régimen de Partidos Políticos;\nc) Coordinar y supervisar la integración de los archivos de los partidos políticos correspondientes a su registro, convenios de fusión o coalición y candidatos a los cargos de elección popular;\nd) Mantener actualizado el directorio de los integrantes de los órganos directivos y sus representantes acreditados ante los Consejos del Instituto Electoral;\ne) Coordinar y supervisar la recepción y seguimiento a las solicitudes que formulen los ciudadanos que pretendan constituirse como partidos políticos locales;\nf) Las demás que le encomienden el Consejero Presidente del Consejo General, el Secretario Ejecutivo, esta Ley y demás disposiciones aplicables.\nIII. La Coordinación Jurídica, que tendrá como funciones:\na) Coordinar y supervisar la asesoría jurídica y la asistencia técnica en las\nReglamentos y Asuntos Jurídicos;\nb) Coordinar y supervisar la recepción, trámite y substanciación de los requerimientos formulados por las autoridades administrativas y jurisdiccionales;\nc) Coordinar y supervisar la elaboración y revisión de los convenios que requiera\nLey Electoral del Estado de Baja California. Página 29\n.\nActualización Legislativa.\nÚltima reforma P. O. No. 60, Índice, 03-Oct-2025 jurisdiccionales, con las autoridades federales, estatales y municipales, y con los centros de enseñanza, y\nd) Las demás que le encomienden el Consejero Presidente del Consejo General, el Secretario Ejecutivo, esta Ley y demás disposiciones aplicables.\nIV. La Coordinación de Informática y Estadística Electoral, que tendrá como funciones:\na) Apoyar en su funcionamiento a todos los órganos del Instituto Estatal, en el manejo de los equipos de cómputo y del sistema de información del proceso electoral;\nb) Diseñar las políticas adecuadas para el uso del equipo de cómputo disponible en el Instituto;\nc) Proveer lo necesario para el diseño e impresión de la documentación y material electoral autorizado;\nd) Diseñar y mantener permanente actualizado y modernizado los programas y procedimientos que integran el sistema de información del proceso electoral;\ne) Elaborar los estudios, estadísticas electorales y la memoria del proceso electoral;\nf) Administrar y mantener actualizada la página electrónica del Instituto Estatal, y\ng) Las demás que le encomienden el Consejero Presidente del Consejo General, el Secretario Ejecutivo, esta Ley y demás disposiciones aplicables.\nV.- La Unidad de Igualdad Sustantiva y No Discriminación, que tendrá como funciones:\na) Prestar asesoría legal correspondiente a la Secretaría, a la Comisión de Igualdad\nSustantiva y No Discriminación, y en su caso a los representantes de los partidos políticos o coaliciones.\nb) Coordinar y supervisar la elaboración de dictámenes, puntos de acuerdo, informes u opiniones de la Comisión de Igualdad Sustantiva y No Discriminación y fungir como\nSecretaría Técnica.\nc) Coadyuvar en la vigilancia de los procedimientos para la participación paritaria entre los géneros en las candidaturas a cargos de elección popular del estado.\nd) Impulsar acciones para promover la participación política de acuerdo con los principios de igualdad de género y no discriminación a grupos en situación de vulnerabilidad.\ne) Las demás que le encomiende el Consejero Presidente del Consejo General, el\nSecretario Ejecutivo, la Comisión de Igualdad Sustantiva, esta Ley, los acuerdos que emita el Consejo General y las demás disposiciones aplicables.\nFracción con sus incisos Adicionada\nLey Electoral del Estado de Baja California. Página 30\n.\nActualización Legislativa.\nÚltima reforma P. O. No. 60, Índice, 03-Oct-2025\nAsimismo, contará con un notificador que será el encargado de llevar a cabo las notificaciones que requiera el Consejo General, así como las diligencias que le sean instruidas por el Secretario Ejecutivo; estará investido de fe pública, exclusivamente, en las actuaciones que realice en el ejercicio de sus funciones.\nPárrafo Reformado\nArtículo Reformado\nArtículo 58.- Para ser designado en alguno de los cargos que se mencionan en el artículo anterior, se requiere reunir los mismos requisitos que para ser Secretario Ejecutivo, salvo el de la edad y años de titulación, para lo cual se deberá:\nI Ser mayor de veinticinco años de edad, y\nII. Poseer al día de la designación, con antigüedad mínima de tres años, título profesional y contar con los conocimientos y experiencia que le permita el desempeño de sus funciones. Tratándose de los titulares de la Unidad Técnica de lo Contencioso Electoral, de la Coordinación Jurídica y del Notificador, el título profesional deberá ser de licenciatura en derecho.\nSección Segunda\nDe la Oficialía Electoral\nArtículo 59.- El Instituto Estatal cumplirá la función de oficialía electoral con fe pública, a través de la Secretaría Ejecutiva y de los Secretario Fedatarios de los Consejos\nDistritales, para actos de naturaleza electoral, de conformidad con las normas contenidas en la Ley General, la presente Ley y demás reglamentación aplicable.\nSolo el Secretario Ejecutivo podrá delegar esta función, entre el personal adscrito a su cargo, cuando las necesidades del servicio lo requieran.\nLos Secretarios Fedatarios de los Consejos Distritales, solo podrá dar fe de los actos de naturaleza electoral, dentro de la demarcación territorial que competa al Consejo a que pertenezcan.\nArtículo 60.- Los servidores públicos investidos de fe pública, deberán ejercer esta función oportunamente y tendrán entre otras, las siguientes atribuciones:\nI. A petición de los partidos políticos, dar fe de la realización de actos y hechos locales;\nII. A petición de los órganos que integran el Instituto, constatar hechos influyan o afecten la organización del proceso electoral.\nIII. Solicitar la colaboración de los notarios públicos para el auxilio de la función electoral durante el desarrollo de la jornada electoral en los procesos locales, y\nIV. Las demás que establezca la Ley y disposiciones aplicables.\nLey Electoral del Estado de Baja California. Página 31\n.\nActualización Legislativa.\nÚltima reforma P. O. No. 60, Índice, 03-Oct-2025\nSección Tercera\nDe los Departamentos\nArtículo 61.- Al frente del Departamento de Procesos Electorales y del Departamento de administración de la Junta General, habrá un Titular Ejecutivo, que será nombrado por mayoría de votos de los integrantes del Consejo General, debiendo reunir los requisitos éstablecidos en el artículo 58 de esta Ley.\nCorresponderá en todos los casos, a la Comisión de Reglamentos y Asuntos Jurídicos del Consejo General, dictaminar sobre los requisitos de elegibilidad de los candidatos que se propongan.\nDe no aprobarse la designación por el Consejo General, su Consejero Presidente deberá presentar ante éste, dentro de los tres días siguientes otra propuesta; procedimiento que se realizará las veces necesarias hasta la designación del titular respectivo.\nLos Departamentos contarán con el personal necesario para el ejercicio de sus funciones.\nArtículo 62.- El Departamento de Procesos Electorales, tendrá a su cargo las siguientes atribuciones:\nI. Fungir como Secretario Técnico de las Comisiones de Procesos Electorales y de Participación Ciudadana y Educación Cívica;\nII. Proveer lo necesario para la distribución de la documentación y material electoral autorizado;\nIII. Coadyuvar en la Instalación, funcionamiento y clausura de los Consejos\nDistritales Electorales;\nIV. Recabar de los Consejos Distritales Electorales copias certificadas de las actas de sus sesiones y demás documentos relacionados con el proceso electoral;\nV. Desarrollar, coordinar y ejecutar los programas de capacitación electoral, y proponer la ubicación de las Mesas Directivas de Casillas, cuando esta función se encuentre delegada por el Instituto Nacional a favor del Instituto Estatal;\nVI. Recabar la documentación necesaria e integrar los expedientes a fin de que el\nConsejo General efectúe el cómputo que conforme a esta Ley debe realizar;\nVII. Promover y orientar en forma permanente a los ciudadanos en el ejercicio de sus derechos y cumplimiento de sus obligaciones político electorales;\nVIII. Elaborar los anteproyectos del material didáctico e instructivos para el programa de educación cívica;\nIX. Desarrollar, coordinar y ejecutar los programas de educación cívica, dirigidos al\nX. Impartir los cursos de capacitación a los funcionarios de Mesa Directiva de\nCasilla, cuando ésta función corresponda al Instituto por delegación del Instituto Nacional;\nLey Electoral del Estado de Baja California. Página 32\n.\nActualización Legislativa.\nÚltima reforma P. O. No. 60, Índice, 03-Oct-2025 así como los cursos de capacitación a los observadores electorales acorde a los lineamientos del Instituto Nacional;\nXI. Acordar con el Secretario Ejecutivo los asuntos de su competencia, y\nXII. Las demás que disponga esta Ley y disposiciones aplicables.\nPara el cumplimiento de sus atribuciones en proceso electoral contará con un delegado en cada uno de los distritos electorales del Estado.\nArtículo 63.- El Departamento de Administración tiene las atribuciones siguientes:\nI. Aplicar las políticas, normas y procedimientos para la administración de los recursos financieros y materiales del Instituto Estatal;\nII. Llevar a cabo los programas de reclutamiento, selección, formación, capacitación y adiestramiento del personal del Instituto;\nIII. Organizar, dirigir y supervisar la administración de los recursos humanos, materiales y financieros;\nIV. Atender las necesidades administrativas de los órganos del Instituto;\nV. Formular el anteproyecto anual del presupuesto del Instituto Electoral, para someterlo a la consideración del Secretario Ejecutivo, así como el proyecto de cuenta pública;\nVI. Proporcionar los recursos económicos y materiales necesarios previamente autorizados, para la debida instalación, funcionamiento y clausura de los Consejos Distritales\nElectorales;\nVII. Establecer y operar los sistemas administrativos para el ejercicio y control presupuestal;\nVIII. Acordar con el Secretario Ejecutivo los asuntos de su competencia, y\nIX. Las demás que disponga esta Ley.\nDurante el proceso electoral podrá contar con delegados en los municipios que se consideren necesarios.\nCAPÍTULO CUARTO\nDe los Consejos Distritales Electorales\nSección Primera\nDe su Funcionamiento y atribuciones\nArtículo 64.- Los Consejos Distritales Electorales, son órganos operativos y dependientes del Consejo General, responsables en el ámbito de su competencia, de la preparación, organización, desarrollo, vigilancia y cómputo de las elecciones de Gobernador, munícipes y diputados, por ambos principios.\nLey Electoral del Estado de Baja California. Página 33\n.\nActualización Legislativa.\nÚltima reforma P. O. No. 60, Índice, 03-Oct-2025\nEn cada Distrito Electoral en que se divida el territorio del Estado funcionará un\nConsejo, con residencia en la cabecera del mismo.\nArtículo 65.- Los Consejos Distritales Electorales funcionarán durante el proceso electoral local, y se integrarán por:\nCinco consejeros electorales numerarios con voz y voto, designados por el Consejo\nGeneral de acuerdo con el procedimiento señalado en esta Ley. El Consejero Presidente, será electo de entre los mismos cinco consejeros electorales numerarios, en los términos que señala la Ley;\nI. Un representante propietario por cada uno de los partidos políticos registrados o acreditados ante el Instituto Estatal, con derecho a voz, y quien contará con un suplente, y\nII. Un Secretario Fedatario con derecho a voz en los asuntos de su competencia, quien será designado por la mayoría calificada del Consejo Distrital Electoral respectivo, a propuesta del Consejero Presidente y que será distinto a ellos.\nSe elegirán por el Consejo General, dos consejeros electorales supernumerarios, exclusivamente para que suplan a los consejeros electorales numerarios en sus inasistencias a las sesiones ordinarias y extraordinarias del Consejo, en orden de prelación.\nEn caso de falta permanente de un Consejero Electoral Numerario, la persona que sea designada en su lugar por el Consejo General, fungirá en el cargo el tiempo que le faltare para cumplir el período correspondiente a quien sustituye, pudiendo ser reelecto para el período inmediato.\nArtículo 66.- El Consejo General, designará a los consejeros electorales de los\nConsejos Distritales Electorales, mediante el siguiente procedimiento:\nI. En la tercer semana del mes de diciembre del año anterior al de la elección, emitirá convocatoria pública en la que se establezcan las bases y requisitos para participar garantizando un plazo de treinta días naturales para el registro de aspirantes;\nFracción Reformada\nII. Corresponderá a la Comisión de Reglamentos y Asuntos Jurídicos revisar la documentación correspondiente, desahogar las entrevistas del caso y elaborar el dictamen respectivo, y\nIII. Con base en el dictamen que se le turne, los elegirá mediante las dos terceras partes de los votos.\nDurarán en su encargo tres años, en los términos de esta Ley, pudiendo ser ratificados, para un período inmediato. El Consejero Presidente podrá ser reelecto hasta por un período inmediato.\nArtículo Reformado\nArtículo 67.- Los requisitos para ocupar cargo de Consejero Electoral, Consejero\nPresidente y Secretario Fedatario en los Consejos Distritales, son los siguientes:\nI. Para Consejero Electoral Numerario o Supernumerario:\nLey Electoral del Estado de Baja California. Página 34\n.\nActualización Legislativa.\nÚltima reforma P. O. No. 60, Índice, 03-Oct-2025\na) Ser ciudadano mexicano por nacimiento, además de estar en pleno goce de sus derechos civiles y políticos;\nb) Estar inscrito en el Registro Federal de Electores y contar con credencial para votar vigente;\nc) Tener más de 23 años de edad al día de la designación;\nd) Gozar de buena reputación y no haber sido condenado por delito alguno, salvo que hubiese sido de carácter no intencional o imprudencial;\ne) Tener residencia en el municipio donde se encuentre ubicado el distrito de que se trate, durante los últimos cinco años\nf) No haber sido registrado como candidato ni haber desempeñado cargo alguno de elección popular en los cuatro años anteriores a la designación;\ng) No desempeñar ni haber desempeñado cargo de dirección nacional, estatal o municipal en algún partido político en los cuatro años anteriores a la designación;\nh) No estar inhabilitado para ejercer cargos públicos en cualquier institución pública federal o local;\ni) No haberse desempeñado durante los cuatro años previos a la designación cargo de primer y segundo nivel en la administración pública federal, estatal o municipal; y\nj) Contar con conocimientos para el desempeño adecuado de sus funciones\nII. Para ser Consejero Presidente, además de los requisitos previstos en la fracción anterior:\na) Tener más de 28 años de edad al día de la designación, y\nb) Poseer al día de la designación, con antigüedad mínima de cinco años, título profesional de nivel licenciatura.\nIII. Para Secretario Fedatario, además de los requisitos previstos en la fracción I del presente artículo:\na) Tener más de 25 años de edad al día de la designación, y\nb) Poseer al día de la designación, con antigüedad mínima de dos años, título profesional de Licenciado en Derecho.\nArtículo 68.- El Consejo General a más tardar la primera semana del mes de marzo del año de la elección, celebrará sesión a efecto de tomar protesta de Ley correspondiente al\nConsejero Presidente de cada uno de los Consejos Distritales Electorales, expidiéndose la\nConstancia correspondiente.\nArtículo Reformado\nArtículo 69.- Los Consejos Distritales durante la tercera semana de marzo del año de la elección celebrarán Sesión de Instalación, previa convocatoria de su Consejero\nPresidente, con el objeto de preparar el proceso electoral procediendo, previa recepción de\nLey Electoral del Estado de Baja California. Página 35\n.\nActualización Legislativa.\nÚltima reforma P. O. No. 60, Índice, 03-Oct-2025 las acreditaciones de los consejeros electorales y representantes de partidos políticos, en dicha sesión a:\nPárrafo Reformado\nI. Tomar la protesta de Ley a los consejeros electorales numerarios y supernumerarios; así como a los representantes de los partidos políticos;\nII. Lista de asistencia y declaración de quórum;\nIII. Declarar formalmente instalado el Consejo Distrital Electoral;\nIV. Designar al Secretario Fedatario, y\nV. Aprobar el calendario de sesiones ordinarias.\nArtículo Reformado\nArtículo 70.- Instalados los Consejos Distritales Electorales, sesionarán cuando menos una vez al mes, previa convocatoria de su Consejero Presidente, y en forma extraordinaria cuando éste lo estime necesario o a petición que formule la mayoría de los consejeros electorales o los representantes acreditados de los partidos políticos.\nArtículo 71.- Los Consejos Distritales Electorales entrarán en receso a más tardar el día treinta y uno de julio del año de la elección, salvo el caso de aquellos en que existan impugnaciones por resolver, que entrarán en receso dentro de los cinco días posteriores a que cause estado la resolución.\nAl entrar en receso de sus funciones, el Consejero Presidente hará entrega mediante acta circunstanciada al Departamento de Procesos Electorales de la documentación del proceso electoral.\nArtículo 72.- Para que los Consejos Distritales Electorales sesionen validamente, es necesaria la presencia de la mayoría de sus integrantes, entre los que deberá estar el\nConsejero Presidente. En caso de que no se reúna la mayoría solicitada, se citará de nuevo a sesión que deberá celebrarse dentro de las veinticuatro horas siguientes con los consejeros y representantes que asistan, en ambos casos deberá estar presente el\nConsejero Presidente, o el que éste designe para el caso de ausencias momentáneas en las sesiones.\nLas faltas temporales del Consejero Presidente, serán sustituidas por el Consejero\nElectoral numerario, en el orden de prelación, que para tal efecto se realice mediante sorteo.\nLos consejeros electorales y los representantes de los partidos políticos acreditados, anticipación, y a las sesiones extraordinarias con veinticuatro horas de anticipación.\nLas resoluciones que se tomen serán por mayoría de votos, salvo los casos previstos en esta Ley que requieran de mayoría calificada y en caso de empate en segunda ronda, será de calidad el voto del Consejero Presidente.\nEl Secretario Ejecutivo o los titulares de los Departamentos, podrán asistir a las sesiones de los Consejos Distritales, para tratar asuntos de su competencia, previa petición\nLey Electoral del Estado de Baja California. Página 36\n.\nActualización Legislativa.\nÚltima reforma P. O. No. 60, Índice, 03-Oct-2025 que le hagan al Consejero Presidente del Consejo Distrital que corresponda, o que éste así lo solicite.\nPara su operación y funcionamiento los Consejos Distritales Electorales se sujetarán a las disposiciones del reglamento y acuerdos que expida el Consejo General.\nArtículo 73.- Los consejos distritales electorales tendrán, dentro del ámbito de su competencia, las siguientes atribuciones:\nI. Cumplir y hacer cumplir esta Ley, los acuerdos y resoluciones que dicten las autoridades y órganos electorales;\nII. Designar o remover por el voto de las dos terceras partes de sus integrantes con derecho a ello, al Secretario Fedatario del Consejo Distrital Electoral, conforme a la propuesta del Consejero Presidente;\nIII. Designar en caso de ausencia del Secretario Fedatario, de entre el personal del\nInstituto Estatal, a la persona que fungirá como Secretario del Consejo en la sesión;\nIV. Aprobar el registro de las fórmulas de candidatos a diputados por el principio de mayoría relativa;\nV. Registrar los nombramientos de los representantes de los partidos políticos, ante el Consejo;\nVI. Registrar los nombramientos de los representantes que los partidos políticos acrediten para la jornada electoral;\nVII. Derogada;\nFracción Derogada\nVIII. Aprobar la integración y ubicación de las Mesas Directivas de Casillas, cuando esta función se encuentre delegada por el Instituto Nacional a favor del Instituto Estatal;\nIX. Ordenar la entrega a los Presidentes de las Mesas Directivas de Casilla, de la documentación, materiales y útiles necesarios, para el debido cumplimiento de sus funciones;\nX. Recibir los paquetes electorales y la documentación relativa a las elecciones de\nGobernador, munícipes y diputados;\nXI. Realizar el cómputo distrital de las elecciones de Gobernador, munícipes y diputados;\nXII. Hacer la declaración de validez de la elección y consecuentemente autorizar la mayoría relativa, así como informar de esta actividad al Consejo General;\nXIII. Enviar al Consejo General las actas levantadas sobre el cómputo distrital de las elecciones de Gobernador, munícipes y diputados, por ambos principios;\nLey Electoral del Estado de Baja California. Página 37\n.\nActualización Legislativa.\nÚltima reforma P. O. No. 60, Índice, 03-Oct-2025\nXIV. Preparar la memoria técnica del proceso electoral en el Distrito Electoral correspondiente, remitiéndola a la Dirección General del Instituto Electoral, antes de la entrada en receso del Consejo Distrital respectivo, y\nXV. Las demás que disponga esta Ley.\nArtículo Reformado\nSección Segunda\nDe las atribuciones y obligaciones de los consejeros presidentes y secretarios fedatarios\nArtículo 74.- El Consejero Presidente del Consejo Distrital tendrá las siguientes atribuciones y obligaciones:\nI. Convocar, conducir y presidir las sesiones del Consejo y declarar la existencia del quórum;\nII. Convocar a sesiones cuando lo estime necesario o lo soliciten formalmente la mayoría de los consejeros electorales o de los representantes de los partidos políticos acreditados;\nIII. Representar legalmente al Consejo, ante los órganos jurisdiccionales electorales, cuando se interponga algún recurso en contra de sus actos o resoluciones;\nIV. Dar cuenta al Consejo General de los cómputos correspondientes, del desarrollo de las elecciones, y de los recursos interpuestos;\nV. Expedir la constancia de mayoría a la fórmula de candidatos a diputados que haya obtenido la mayoría de votos conforme al cómputo;\nVI. Colocar en el exterior de la sede del Consejo, los resultados de los cómputos distritales;\nVII. Turnar al Consejo General el original y copias certificadas del expediente de los cómputos distritales relativos a las elecciones de Gobernador, munícipes y diputados;\nVIII. Mantener en custodia la documentación de las elecciones de Gobernador, munícipes y diputados hasta que hayan causado estado los resultados del proceso electoral correspondiente;\nIX. Cumplir y hacer cumplir las resoluciones dictadas por el Consejo, así como del\nConsejo General;\nX. Coordinarse y dar cuenta al Secretario Ejecutivo de las actividades e informes sobre el desarrollo del proceso electoral;\nXI. Informar al Consejo General y al Secretario Ejecutivo, las vacantes que se originen de consejeros electorales de su distrito;\nXII. Proponer al Consejo la designación del Secretario Fedatario, y\nXIII. Las demás que disponga esta Ley.\nLey Electoral del Estado de Baja California. Página 38\n.\nActualización Legislativa.\nÚltima reforma P. O. No. 60, Índice, 03-Oct-2025\nArtículo 75.- Corresponde a los secretarios fedatarios de los consejos distritales, las atribuciones y obligaciones siguientes:\nI. Cumplir las instrucciones del Consejo Distrital;\nII. Preparar el orden del día de la sesión del Consejo, previo acuerdo con el\nConsejero Presidente, pasar lista de asistencia, dar fe de lo actuado en las sesiones y levantar las actas correspondientes;\nIII. Dar cuenta de la correspondencia recibida y despachada;\nIV. Expedir las constancias que acrediten a los consejeros electorales y a los representantes de los partidos políticos o coaliciones como miembros del Consejo;\nV. Prestar asistencia jurídica al Consejo Distrital;\nVI. Firmar junto con el Consejero Presidente, los acuerdos, certificaciones y resoluciones que emita el Consejo;\nVII. Formar el libro de acuerdos del Consejo y, expedir copia certificada de las constancias que obren en sus archivos, y\nVIII. Las demás que disponga esta Ley.\nCAPITULO QUINTO\nDe las Mesas Directivas de Casilla\nArtículo 76.- Las mesas directivas de casilla por mandato constitucional, son los órganos electorales formados por ciudadanos, facultados para recibir la votación y realizar el escrutinio y cómputo en cada una de las secciones electorales. Como autoridad electoral tienen a su cargo, durante la jornada electoral, respetar y hacer respetar la libre emisión y efectividad del sufragio, garantizar el secreto del voto y asegurar la autenticidad del escrutinio y cómputo.\nLas mesas directivas de casilla se integrarán con un presidente, un secretario, dos escrutadores, y tres suplentes generales.\nArtículo 77.- En el caso de elecciones concurrentes la integración, ubicación y designación de integrantes de mesas directivas de casilla a instalar para la recepción de la votación, se realizará con base en las disposiciones de la Ley General. Asimismo, se deberá del Instituto Nacional.\nArtículo 78.- Para ser integrante de mesa directiva de casilla se requiere:\nI. Ser ciudadano mexicano por nacimiento que no adquiera otra nacionalidad;\nII. Ser residente en la sección electoral que comprenda a la casilla; salvo cuando se trate de casilla especial cuya residencia será en el Distrito en que se instale;\nIII. Estar inscrito en el Registro Federal de Electores;\nLey Electoral del Estado de Baja California. Página 39\n.\nActualización Legislativa.\nÚltima reforma P. O. No. 60, Índice, 03-Oct-2025\nIV. Contar con credencial para votar;\nV. Estar en ejercicio de sus derechos políticos;\nVI. Tener un modo honesto de vivir;\nVII. Haber participado en el curso de capacitación electoral impartido por la junta distrital ejecutiva correspondiente;\nVIII. No ser servidor público de confianza con mando superior, ni tener cargo de dirección partidista de cualquier jerarquía, y\nIX. Saber leer y escribir y no tener más de 70 años al día de la elección.\nSección Única\nDe sus Atribuciones\nArtículo 79.- Son atribuciones de los integrantes de las mesas directivas de casilla:\nI. Instalar y clausurar la casilla en los términos de este esta Ley;\nII. Recibir la votación;\nIII. Efectuar el escrutinio y cómputo de la votación;\nIV. Permanecer en la casilla desde su instalación hasta su clausura, y\nV. Las demás que les confieran esta Ley y disposiciones relativas.\nArtículo 80.- Son atribuciones de los presidentes de las mesas directivas de casilla:\nI. Como autoridad electoral, presidir los trabajos de la mesa directiva y velar por el cumplimiento de las disposiciones contenidas en esta Ley, a lo largo del desarrollo de la jornada electoral;\nII. Recibir de los consejos distritales la documentación, útiles y elementos necesarios para el funcionamiento de la casilla, y conservarlos bajo su responsabilidad hasta la instalación de la misma;\nIII. Identificar a los electores en el caso previsto en el artículo 212 de esta Ley;\nIV. Mantener el orden en la casilla y en sus inmediaciones, con el auxilio de la fuerza pública si fuese necesario;\nV. Suspender, temporal o definitivamente, la votación en caso de alteración del sufragio, el secreto del voto o que atenten contra la seguridad personal de los electores, de los representantes de los partidos o de los miembros de la mesa directiva;\nVI. Retirar de la casilla a cualquier persona que incurra en alteración grave del orden, impida la libre emisión del sufragio, viole el secreto del voto, realice actos que afecten la autenticidad del escrutinio y cómputo, intimide o ejerza violencia sobre los electores, los representantes de los partidos o de los miembros de la mesa directiva;\nLey Electoral del Estado de Baja California. Página 40\n.\nActualización Legislativa.\nÚltima reforma P. O. No. 60, Índice, 03-Oct-2025\nVII. Practicar, con auxilio del secretario y de los escrutadores y ante los representantes de los partidos políticos presentes, el escrutinio y cómputo;\nVIII. Concluidas las labores de la casilla, turnar oportunamente al consejo distrital la documentación y los expedientes respectivos en los términos del artículo 240 de esta Ley;\nIX. Fijar en un lugar visible al exterior de la casilla los resultados del cómputo de cada una de las elecciones,\nX. Las demás que disponga esta Ley.\nArtículo 81.- Son atribuciones de los secretarios de las mesas directivas de casilla:\nI. Levantar durante la jornada electoral las actas que ordena esta Ley y distribuirlas en los términos que el mismo establece;\nII. Contar, inmediatamente antes del inicio de la votación y ante los representantes de partidos políticos que se encuentren presentes, las boletas electorales recibidas y anotar el número de folios de las mismas en el acta de instalación;\nIII. Comprobar que el nombre del elector figure en la lista nominal correspondiente;\nIV. Recibir los escritos de protesta que presenten los representantes de los candidatos independientes y de los partidos políticos;\nV. Inutilizar las boletas sobrantes de conformidad con lo dispuesto en esta Ley, y\nVI. Las demás que les confieran esta Ley.\nArtículo 82.- Son atribuciones de los escrutadores de las mesas directivas de casilla:\nI. Contar la cantidad de boletas depositadas en cada urna, y el número de electores que votaron conforme a las marcas asentadas en la lista nominal de electores, cerciorándose de que ambas cifras sean coincidentes y, en caso de no serlo, consignar el hecho;\nII. Contar el número de votos emitidos en favor de cada candidato, fórmula o planilla;\nIII. Auxiliar al presidente o al secretario en las actividades que les encomienden, y\nIV. Las demás que les confiera esta Ley.\nCAPÍTULO SEXTO\nDe las disposiciones complementarias\nArtículo 83.- No podrán ser consejeros electorales distritales, ni representantes de los partidos políticos ante los órganos del Instituto Estatal, quienes se encuentren en los siguientes supuestos:\nII. Ser magistrado electoral o secretario del Tribunal Electoral;\nLey Electoral del Estado de Baja California. Página 41\n.\nActualización Legislativa.\nÚltima reforma P. O. No. 60, Índice, 03-Oct-2025\nIII. Ser titular de algún órganos constitucional autónomo;\nIV. Ser titular de algún órgano técnico del Congreso del Estado;\nV. Los servidores públicos del Instituto Estatal y del Tribunal Electoral, salvo que se separen de manera definitivamente del cargo que desempeñen;\nVI. Ser miembro en servicio activo de cualquier fuerza armada o policiaca, o\nVII. Ser agente del Ministerio Público federal o local.\nArtículo 84.- Los integrantes de los Consejos del Instituto Estatal deberán rendir protesta de guardar y hacer guardar la Constitución Federal, la Constitución del Estado y las\nLeyes que de ellas emanen y cumplir con esta Ley en el desempeño de la función electoral que se les ha encomendado.\nRendida la protesta de Ley, el Consejero Presidente del Consejo General, dispondrá la publicación del Acuerdo de la integración de los Consejos Electorales del Instituto\nElectoral en el Periódico Oficial del Estado y en los diarios de mayor circulación en la entidad.\nArtículo 85.- Los partidos políticos deberán acreditar a sus representantes ante los\nConsejos Distritales, a más tardar dentro de los veinte días siguientes a la fecha de la sesión de instalación del Consejo Distrital de que se trate. Vencido este plazo, los partidos políticos que no hayan acreditado a sus representantes, no formarán parte del Consejo respectivo durante el proceso electoral.\nArtículo 86.- Los partidos políticos podrán sustituir en todo tiempo a sus representantes propietario o suplente acreditados ante los Consejos del Instituto Electoral, mediante escrito que presenten ante el Consejero Presidente del Consejo Electoral correspondiente.\nArtículo 87.- Los consejeros presidentes de los Consejos Electorales informarán por escrito a los partidos políticos de cada inasistencia de sus representantes a las sesiones; a la segunda falta se requerirá al representante para que concurra a la sesión y se dará aviso al partido político a fin de que tome las medidas pertinentes.\nCuando el representante propietario de un partido político o su suplente, dejen de asistir sin causa justificada, por tres veces consecutivas a las sesiones del Consejo Electoral ante el cual se encuentren acreditados, el partido político dejará de formar parte del mismo durante el proceso electoral de que se trate. Cuando la resolución corresponda a un Consejo\nDistrital Electoral, se notificará al Consejo General y al partido político de que se trate.\nArtículo 88.- Durante el proceso electoral, los órganos del Instituto Electoral podrán notificar sus actos, acuerdos o resoluciones a cualquier día y hora. Los partidos políticos deberán ante cada Consejo Electoral del Instituto Electoral, acreditar domicilio para oír y recibir notificaciones, dentro del municipio sede del Consejo Electoral de que se trate, en caso contrario serán notificados por estrados.\nLey Electoral del Estado de Baja California. Página 42\n.\nActualización Legislativa.\nÚltima reforma P. O. No. 60, Índice, 03-Oct-2025\nLos Consejos Electorales del Instituto Electoral, podrán notificar sus convocatorias, actos, acuerdos o resoluciones por medio electrónico, cuando exista manifestación expresa del representante del partido político, quien deberá proporcionar la dirección de correo electrónico que cuente con mecanismos de confirmación de los envíos de las notificaciones.\nNotificación que surtirá efectos a partir de que se tenga constancia de la recepción de la misma o, en su caso, se cuente con el acuse de recibo correspondiente.\nPara efectos de esta Ley, se entenderá notificado el partido político del acto o resolución de que se trate, cuando su representante haya estado presente en la sesión en que el órgano electoral del Instituto Estatal lo haya emitido. En caso de inasistencia de éste a la sesión en que se dictó el acto o resolución, se le hará personalmente en el domicilio que hubiere señalado, o en su defecto por estrados.\nArtículo 89.- Los consejeros presidentes de los Consejos Distritales Electorales informarán oportunamente por escrito a la Secretaría Ejecutiva de las asistencias e inasistencias de los consejeros electorales a las sesiones, así como de la falta definitiva de los mismos.\nArtículo 90.- Las sesiones de los Consejos del Instituto Estatal serán públicas. El público asistente deberá guardar el debido orden en el recinto donde se celebren y no participará en ellas.\nArtículo 91.- Los consejeros presidentes de los consejos del Instituto Estatal, podrán imponer las correcciones disciplinarias para mantener el orden en el desarrollo de las sesiones y exigir que se guarde el respeto y la consideración debidos.\nLas correcciones disciplinarias que pueden imponerse son:\nI. Amonestación, y\nII. Expulsión del local del Consejo. En caso de rebeldía la persona será desalojada con el auxilio de la fuerza pública.\nCuando de los hechos que motiven la imposición de una corrección disciplinaria, se desprenda la probable comisión de un delito, se levantará acta circunstanciada, turnándose a la autoridad competente.\nArtículo 92.- Las autoridades estatales y municipales están obligadas a proporcionar informes, certificaciones y el auxilio de la fuerza pública, a los órganos del Instituto para el cumplimiento de sus funciones, previa solicitud que le formulen sus respectivos titulares.\nArtículo 93.- Los Consejos Distritales Electorales, remitirán al Consejero Presidente del Consejo General y al Secretario Ejecutivo, dentro de las veinticuatro horas siguientes, copia certificada de los acuerdos tomados en cada una de las sesiones.\nArtículo 94.- El Consejo General, a propuesta de la Secretaría Ejecutiva, determinará los horarios de labores del personal, teniendo en cuenta que dentro del proceso electoral todos los días y horas son hábiles.\nLey Electoral del Estado de Baja California. Página 43\n.\nActualización Legislativa.\nÚltima reforma P. O. No. 60, Índice, 03-Oct-2025\nArtículo 95.- Los consejeros electorales distritales numerarios y supernumerarios, para el desempeño de sus funciones tendrán derecho a disfrutar de las facilidades necesarias en sus trabajos o empleos habituales.\nArtículo 96.- Los titulares de los Departamentos de Procesos Electorales, Administración, de Control Interno; de la Unidad Tecnica de lo Contencioso Electoral; los coodinadores de Partidos Políticos y Financiamiento, Jurídico, de Informática y Estadística\nElectoral, y el Notificador no podrán tener otro empleo, cargo o comisión, con excepción de las actividades docentes, científicas, culturales, de investigación o de beneficencia, siempre y cuando no interfieran en el ejercicio de sus funciones.\nArtículo 97.- La retribución del Consejero Presidente y de los Consejeros Electorales del Consejo General, será establecida en el presupuesto de egresos del Instituto Estatal y aprobada por el Congreso del Estado, en términos del artículo 127 de la Constitución\nFederal, las cuales no podrán disminuirse durante el tiempo que dure su encargo. [Las y los\nConsejeros Electorales del Consejo General y de los Consejos Distritales Electorales, no tendrán derecho a las prestaciones que por ley les corresponden a los trabajadores del\nInstituto Estatal, salvo la atención del servicio médico en institución pública de salud].\nPorción Normativa invalidada por Sentencia a Acción de Inconstitucionalidad 128/2020 y sus acumuladas 147/2020, 163/2020 Y\n228/2020\nLos Consejeros Electorales Distritales, recibirán desde su instalación y hasta la entrada en receso, una dieta de asistensia mensual para cubrir los gastos que se generen por el desempeño de su encargo, la que se calculara diariamente a razón de:\nPárrafo Reformado\nI.- Para el Consejero Presidente doce Unidades de Medida y Actualización diarias;\nFracción Adicionada\nII.- Para las y los Consejeros Distritales Numerarios seis Unidades de Medida y\nActualización diarias, y\nFracción Adicionada\nIII.- Para las y los Consejeros Supernumerarios tres Unidades de Medida y\nActualización diarias. Solo en el mes de junio del año de la elección, la dieta se igualará en los mismos trérminos que la fracción anterior.\nFracción Adicionada que incurran a los principios rectores de la función electoral.\nPárrafo Adicionado\nArtículo Reformado\nSección Única\nLey Electoral del Estado de Baja California. Página 44\n.\nActualización Legislativa.\nÚltima reforma P. O. No. 60, Índice, 03-Oct-2025\nArtículo 98.- Las relaciones laborales entre el Instituto Estatal y su personal, se regirá por lo dispuesto en este Ley, y en lo no previsto por ésta, en la Ley del Servicio Civil de los\nTrabajadores al Servicio de los Poderes del Estado y Municipios de Baja California. Se considerarán servidores públicos de confianza, todo el personal del Instituto.\nLos trabajadores incorporados al Servicio Profesional Electoral Nacional, regirán sus relaciones laborales por las disposiciones aplicables.\nLa selección, ingreso, capacitación, profesionalización, promoción, evaluación, rotación, permanencia y disciplina de los servidores públicos en el Servicio Profesional\nElectoral Nacional, será en los términos en que se regule por el Instituto Nacional Electoral.\nArtículo 99.- Se entiende por jornada de trabajo el tiempo durante el cual el personal está a disposición del Instituto, para prestar el servicio objeto de la presente Ley.\nEs jornada diurna la comprendida entre las seis y las veinte horas; nocturna la comprendida entre las veinte y las seis horas, y mixta la que comprende periodos de la diurna y la nocturna siempre que la nocturna sea menor de tres horas y media, pues en caso contrario se considerará como jornada nocturna.\nLas jornadas se clasifican en continuas, discontinuas y especiales.\nI. Serán jornadas continuas:\na) La que se desarrolle durante siete horas sin interrupción.\nb) La que se desarrolle durante siete horas y media, con interrupción de hasta treinta minutos.\nII. Serán jornadas discontinuas las que se desarrollen durante ocho horas y se interrumpan por una o dos horas.\nArtículo 100.- El personal del Instituto Estatal por cada seis meses de servicio consecutivo de manera anual, gozará de diez días hábiles de vacaciones, conforme al programa de vacaciones que para tal efecto apruebe la Secretaría Ejecutiva.\nCuando por las necesidades del servicio, el personal del Instituto no pueda hacer uso de las vacaciones en los periodos que correspondan, disfrutará de ellas una vez que haya desaparecido la causa que impidió el disfrute de éstas. Las vacaciones no podrán compensarse con una remuneración.\nArtículo 101.- Los servidores públicos del Instituto Estatal, gozarán de descanso los días de asueto que apruebe el Consejo General, siempre y cuando no afecte el cumplimiento en tiempo y forma de las funciones electorales.\nArtículo 102.- Los servidores públicos del Instituto, estarán obligados a prestar sus servicios durante las horas que acuerde el Consejo General, tomando en cuenta que durante los procesos electorales todos los días y horas son hábiles.\nLIBRO CUARTO\nLey Electoral del Estado de Baja California. Página 45\n.\nActualización Legislativa.\nÚltima reforma P. O. No. 60, Índice, 03-Oct-2025\nDel Proceso Electoral\nTÍTULO PRIMERO\nDisposiciones Preliminares\nArtículo 103.- El proceso electoral, es el conjunto de actos ordenados por la\nConstitución del Estado y esta Ley, realizados por los órganos y las autoridades electorales, los partidos políticos y los ciudadanos, que tienen por objeto la renovación periódica de los integrantes de los Poderes Legislativo y Ejecutivo, así como de los Ayuntamientos. En la elección e integración de los Ayuntamientos existirá la paridad de género tanto vertical como horizontal.\nArtículo Reformado\nArtículo 104.- El proceso electoral se inicia con la sesión pública que celebre el\nConsejo General, en los términos del artículo 43 de esta Ley, y concluye una vez entregadas las constancias de asignación de representación proporcional correspondientes.\nEl proceso electoral, para los efectos de esta Ley, comprende las etapas siguientes:\nI. Preparación de la elección;\nII. Jornada electoral;\nIII. Resultados y declaraciones de validez de las elecciones de diputados y munícipes, y\nIV. Dictamen y declaración de validez de la elección de Gobernador.\nArtículo 105.- La preparación de la elección, se inicia con la sesión pública que celebre el Consejo General para declarar el inicio formal del proceso electoral, y concluye al iniciarse la jornada electoral.\nArtículo 106.- La jornada electoral, se inicia a las 8:00 horas del primer domingo de junio y concluye con la clausura de casilla.\nArtículo 107.- La etapa de resultados y declaración de validez de las elecciones de\nDiputados y munícipes se inicia con la recepción de los paquetes y materiales electorales por los consejos distritales y concluye con los cómputos y declaraciones de validez de las elecciones que celebren estos y el Consejo General, o con las resoluciones jurisdiccionales que en su caso se pronuncien en última instancia.\nArtículo 108.- La etapa de resultados, declaración de validez y calificación de la emita el Consejo General, o con las resoluciones jurisdiccionales que en su caso se pronuncien en última instancia.\nArtículo 109.- Concluido el proceso electoral, el Consejo General, deberá dar aviso, al Congreso del Estado de los resultados de las elecciones, para los efectos que señala el artículo 27 fracciones VII y VIII de la Constitución del Estado.\nLey Electoral del Estado de Baja California. Página 46\n.\nActualización Legislativa.\nÚltima reforma P. O. No. 60, Índice, 03-Oct-2025\nArtículo 110.- Atendiendo al principio de definitividad de las distintas etapas del proceso electoral, a la conclusión de cualquiera de las mismas, los Consejeros Presidentes de los Consejos Electorales del Instituto Estatal, darán a conocer su conclusión en los estrados de las oficinas que ocupen los mismos y de ser posible presupuestalmente, la difundirán en los medios de comunicación que estimen pertinentes.\nTÍTULO SEGUNDO\nDe las precampañas\nCAPÍTULO PRIMERO\nDisposiciones comunes\nArtículo 111.- Corresponde exclusivamente a los partidos políticos autorizar a sus militantes o simpatizantes la realización de actividades proselitistas en busca de su nominación a un puesto de elección popular, de manera previa al evento de postulación o designación de candidatos, conforme a sus estatutos, acuerdos de sus órganos de representación y prescripciones de esta Ley.\nPara que los partidos políticos puedan otorgar la autorización a que se refiere el párrafo anterior, es necesario que existan dos o más precandidatos en busca de la nominación a un mismo cargo de elección popular; ello sin perjuicio del derecho de los propios partidos políticos consignado en la parte final de la fracción I del artículo siguiente.\nArtículo 112.- Para los fines de la presente Ley, se entenderá por:\nI. Precampaña Electoral: es el conjunto de actividades reguladas por esta Ley, y los estatutos, acuerdos y lineamientos emanados de los partidos políticos de conformidad con aquella, que realizan las personas precandidatas a ser postuladas por un partido político a un cargo de elección popular, dentro de un proceso de elección interna convocado por aquel, con la finalidad de promover su imagen y capacidad como la mejor para obtener la candidatura; así como aquellas que realicen de manera institucional los partidos políticos para la difusión de sus procesos de selección interna, en radio y televisión.\nFracción Reformada\nII. Actos de Precampaña: son las acciones que tienen por objeto mejorar la imagen de quienes ocupen las precandidaturas, con el fin de obtener la nominación como candidata o candidato del partido político, para contender en una elección constitucional.\nEntre otras, quedan comprendidas las siguientes:\nPárrafo Reformado\na) Reuniones públicas o privadas;\nb) Asambleas;\nc) Debates;\nd) Entrevistas en los medios;\nLey Electoral del Estado de Baja California. Página 47\n.\nActualización Legislativa.\nÚltima reforma P. O. No. 60, Índice, 03-Oct-2025\ne) Visitas domiciliarias, y\nf) Demás actividades que realicen los precandidatos;\nFracción Reformada\nIII. Propaganda de precampaña electoral: el conjunto de escritos, publicaciones, imágenes, grabaciones, proyecciones y expresiones que durante la precampaña electoral producen y difunden los precandidatos y sus simpatizantes, con el propósito de presentar y difundir sus propuestas ante los militantes del partido por el que aspiran ser nominados, y\nIV. Precandidatura: Aquella que ostentan las y los ciudadanos que deciden contender al interior de un partido político con el fin de alcanzar su nominación como candidata o candidato a un puesto de elección popular.\nFracción Reformada\nNingún ciudadano podrá participar simultáneamente en procesos de selección interna de candidaturas a cargos de elección popular por diferentes partidos políticos, salvo que entre ellos medie convenio para participar en coalición. Durante las precampañas está prohibido el otorgamiento de artículos promocionales utilitarios.\nPárrafo Reformado\nEn la propaganda de precampaña electoral que realicen las personas precandidatas, deberán abstenerse de expresiones que calumnien a las personas, discriminen o constituyan actos de violencia política contra las mujeres en razón de género en términos de esta Ley.\nPárrafo Adicionado\nArtículo Reformado\nArtículo 113.- Las precampañas electorales iniciarán:\nI. Cuando se celebren elecciones para elegir Gobernador del Estado, diputados y munícipes, el día veintidós de enero del año de la elección, y\nII. Cuando se celebren elecciones para elegir sólo diputados al Congreso del\nEstado y munícipes a los ayuntamientos, el día dos de marzo del año de la elección.\nTodas las precampañas deberán concluir, a más tardar, un día antes del inicio del periodo de la solicitud de registro de candidatos.\nArtículo 114.- El partido político deberá a más tardar veinte días previos al inicio del periodo de precampaña a que se refiere el artículo anterior, informar por escrito al Consejo periodo de precampaña.\nArtículo 115.- Los lineamientos o acuerdos referidos en el artículo anterior, deberán contener por lo menos:\nI. Los cargos de elección popular sujetos a precampaña;\nII. El plazo de duración de la precampaña electoral, acorde a lo dispuesto en el artículo 113 de esta Ley;\nLey Electoral del Estado de Baja California. Página 48\n.\nActualización Legislativa.\nÚltima reforma P. O. No. 60, Índice, 03-Oct-2025\nIII. El plazo o término para acreditarse los precandidatos ante el partido político;\nIV. La forma de elección del candidato en términos de los estatutos correspondientes;\nV. El órgano interno responsable de la organización del proceso de precampaña;\nVI. La fecha de celebración de la asamblea estatal, municipal, distrital, o en su caso, de realización de la jornada comicial interna;\nCuando un partido político tenga prevista la celebración de una jornada de consulta directa, ésta se realizará simultáneamente para todas sus candidaturas;\nVII. En el caso de la elección de diputados por el principio de representación, la determinación a que se refiere el inciso c) de la fracción I del artículo 15 de la Constitución del Estado, y\nVIII. Las obligaciones y prohibiciones para los precandidatos.\nArtículo 116.- El Consejo General procederá a la revisión de los lineamientos o acuerdos a los que estarán sujetos los precandidatos, por conducto de la Comisión del\nRégimen de Partidos Políticos y Financiamiento, observando el siguiente procedimiento:\nI. Recibido en el Consejo General el escrito y lineamientos respectivos, el\nConsejero Presidente los turnará de manera inmediata a la Comisión;\nII. La Comisión en un plazo de cinco días verificará que los lineamientos o acuerdos, reúnan los requisitos establecidos en el artículo anterior;\nIII. Si los lineamientos reúnen los requisitos, la Comisión en el plazo señalado en la fracción anterior, informará al Consejo General de ello, así como al partido político de que se trate, y\nIV. En caso de que los lineamientos no se ajusten a lo dispuesto en el artículo precedente, la Comisión en el plazo referido en la fracción II de este numeral, notificará al partido político de que se trate, para que en el término de tres días contados a partir de la notificación, los modifique, apercibiéndolo de que en caso de no hacerlo el Consejo General a propuesta de la Comisión hará las modificaciones necesarias.\nLos lineamientos o acuerdos que se presenten fuera del plazo establecido en el artículo 114 de esta Ley, serán desechados de plano por el Consejo General, en base al dictamen o acuerdo que emita la Comisión. En consecuencia los precandidatos del partido político y el partido de que se trate, no podrán realizar procesos, actos o propaganda de precampaña electoral.\nQuienes fueren designados como candidatos a cargos de elección popular, en forma directa, sin que mediare proceso democrático de selección interna, no podrán realizar actos o propaganda de precampaña electoral.\nArtículo 117.- El partido político deberá informar al Consejo General sobre la acreditación de los precandidatos, dentro de los tres días siguientes al cierre del plazo del\nLey Electoral del Estado de Baja California. Página 49\n.\nActualización Legislativa.\nÚltima reforma P. O. No. 60, Índice, 03-Oct-2025 registro a que se refiere la fracción III del artículo 115 de esta Ley, acompañando la siguiente información:\nI. Copia del escrito de solicitud;\nII. Copia de la exposición de motivos;\nIII. Copia del programa de trabajo;\nIV. Nombre del representante del precandidato;\nV. Nombre del responsable de la obtención, administración y gasto de los recursos recabados, del precandidato, y\nVI. Domicilio para oír y recibir notificaciones del precandidato o su representante.\nEn el caso de los munícipes, los partidos políticos sólo estarán obligados a dar el aviso y proporcionar la información anterior respecto de los precandidatos a presidente municipal, salvo que autoricen la realización de actos de precampaña en forma individual para integrar las planillas respectivas.\nArtículo 118.- Los precandidatos podrán impugnar, ante el órgano interno competente, los reglamentos y convocatorias; la integración de los órganos responsables de conducir los procesos internos, los acuerdos y resoluciones que adopten, y en general los actos que realicen los órganos directivos, o sus integrantes, cuando de los mismos se desprenda la violación de las normas que rijan los procesos de selección de candidatos a cargos de elección popular. Cada partido emitirá un reglamento interno en el que se normarán los procedimientos y plazos para la resolución de tales controversias.\nLos medios de impugnación internos que se interpongan con motivo de los resultados de los procesos de selección interna de candidatos a cargos de elección popular deberán quedar resueltos en definitiva a más tardar diez días después de la fecha de realización de la consulta mediante voto directo, o de la asamblea en que se haya adoptado la decisión sobre candidaturas.\nLos medios de impugnación que presenten los precandidatos debidamente registrados en contra de los resultados de elecciones internas, o de la asamblea en que se hayan adoptado decisiones sobre candidaturas, se presentarán ante el órgano interno competente a más tardar dentro de los tres días siguientes a la emisión del resultado o a la conclusión de la asamblea. participado.\nArtículo 119.- Es competencia directa de cada partido político, a través del órgano establecido por sus Estatutos, o por el reglamento o convocatoria correspondiente, negar o confirmar o modificar sus resultados, o declarar la nulidad de todo el proceso interno de selección, aplicando en todo caso los principios legales y las normas establecidas en sus\nLey Electoral del Estado de Baja California. Página 50\n.\nActualización Legislativa.\nÚltima reforma P. O. No. 60, Índice, 03-Oct-2025\nEstatutos o en los reglamentos y convocatorias respectivas. Las decisiones que adopten los órganos competentes de cada partido podrán ser recurridas por los aspirantes o precandidatos ante el Tribunal Electoral, una vez agotados los procedimientos internos de justicia partidaria.\nArtículo 120.- Los partidos políticos dispondrán lo necesario a fin de que los precandidatos sean reconocidos como tales, extendiéndole las constancias de registro respectivas, si cumple con los requisitos y resulte procedente, conforme a esta ley, los estatutos y acuerdos del partido político. En los formatos de registro, se hará mención de la fidelidad de los datos proporcionados, bajo protesta de decir verdad por parte de los precandidatos.\nCAPÍTULO SEGUNDO\nDe los precandidatos\nArtículo 121.- Los precandidatos deberán observar lo siguiente:\nI. Respetar los estatutos, lineamientos o acuerdos del partido político, respecto de la postulación de candidatos, así como lo prescrito en la presente Ley;\nII. Informar por escrito al partido político de su aspiración, acompañándolo con una exposición de motivos y el programa de trabajo que se propone llevar a cabo, como posible representante de elección popular;\nIII. Cumplir con el tope de gastos de precampaña;\nIV. Señalar domicilio legal;\nV. Designar a su representante y al responsable de la obtención, administración y gasto de los recursos recabados;\nVI. Propiciar la exposición, desarrollo y discusión del programa y acciones fijadas, conforme a lo establecido en los documentos básicos y, en su caso, de la plataforma electoral del partido político o coalición, y\nVII. Las demás que establezca la Ley.\nArtículo 122.- En el caso de que se trate de precandidatos que sean servidores públicos, además de cumplir con lo que establece la Constitución del Estado y esta Ley, se actos proselitistas a favor de su precandidatura o la de otros, si no ha informado de ello a su partido y éste a su vez no le ha otorgado la constancia correspondiente, ni notificado al\nInstituto Estatal sobre su aspiración.\nArtículo 122 BIS.- Quienes aspiren a ser electos de forma consecutiva a los cargos de Diputados, Presidentes Municipales, Regidores y Síndicos se sujetarán a las bases contenidas en esta ley, aplicables para el resto de precandidatos o candidatos, según sea el caso.\nArtículo Adicionado\nLey Electoral del Estado de Baja California. Página 51\n.\nActualización Legislativa.\nÚltima reforma P. O. No. 60, Índice, 03-Oct-2025\nArtículo 123.- Queda prohibido a los precandidatos lo siguiente:\nI. Recibir cualquiera de las aportaciones prohibidas a que se refieren la Ley\nGeneral, la Ley General de Partidos Políticos y la presente ley;\nII. Realizar actos de precampaña electoral antes de la expedición de la constancia de registro correspondiente u obtener recursos, cualquiera que sea su origen, antes de que aquella inicie;\nIII. Utilizar para fines personales los recursos recabados al amparo de actos proselitistas de precampaña, salvo viáticos, alimentos y transportación, relacionados de manera directa;\nIV. La contratación de propaganda o cualquier otra forma de promoción personal en radio y televisión;\nV. Hacer uso de la infraestructura pública, incluidos, entre otros, teléfonos, faxes y herramientas de Internet, para la obtención de financiamiento o en apoyo a la realización de cualquier otro acto de precampaña, y\nVI. Las demás que establezca esta Ley.\nCAPÍTULO TERCERO\nDe la fiscalización de las precampañas\nArtículo 124.- La fiscalización de los egresos e ingresos en la precampaña, se realizará en los términos y conforme a los procedimientos previstos en la Ley General y en la\nLey General de Partidos Políticos.\nArtículo 125.- A más tardar el quince de diciembre del año previo al de la elección, el\nConsejo General determinará los montos de los topes de gastos de precampañas por precandidato y tipo de elección para la que pretenda ser postulado. El tope será equivalente al veinte por ciento del establecido para las campañas inmediatas anteriores, según la elección de que se trate.\nArtículo 126.- Si un precandidato incumple la obligación de entregar el informe de ingresos y gastos de precampaña y hubiese obtenido la mayoría de votos en la consulta interna o en la asamblea respectiva, no será registrado legalmente como candidato. Los de la Ley General.\nArtículo 127.- Los precandidatos que rebasen el tope de gastos de precampaña establecido por el Consejo General serán sancionados con la cancelación de su registro, o en su caso, con la pérdida de la candidatura que hayan obtenido. En el último supuesto, los partidos conservan el derecho de realizar las sustituciones que procedan.\nArtículo 128.- Quedarán comprendidos dentro de los topes de gasto de precampaña los conceptos señalados en el artículo 153 de esta Ley.\nLey Electoral del Estado de Baja California. Página 52\n.\nActualización Legislativa.\nÚltima reforma P. O. No. 60, Índice, 03-Oct-2025\nArtículo 129.- A las precampañas y a los precandidatos que en ellas participen les serán aplicables, en lo conducente, las normas previstas en las leyes generales aplicables y en esta Ley respecto de los actos de campaña y propaganda electoral.\nLos partidos políticos, precandidatos y simpatizantes están obligados a retirar su propaganda electoral de precampaña para su reciclaje, por lo menos tres días antes al inicio del plazo para el registro de candidatos de la elección de que se trate. De no retirarse, el\nConsejo General tomará las medidas necesarias para su retiro con cargo a la ministración del financiamiento público que corresponda al partido, además de la imposición de la sanción que al respecto establezca esta Ley.\nArtículo 130.- El Consejo General emitirá los demás reglamentos y acuerdos que sean necesarios para la debida regulación de los procesos de precampañas, de conformidad con lo establecido en las leyes aplicables y en este Código.\nTÍTULO TERCERO\nDe la preparación de la elección\nCAPÍTULO PRIMERO\nDe los requisitos e impedimentos para ser candidato\nArtículo 131.- Para ser candidato a Diputado Propietario o Suplente al Congreso del\nEstado, se deberán de reunir los requisitos que establece el artículo 17 de la Constitución del Estado.\nArtículo 132.- Para ser candidato a Munícipe de un Ayuntamiento del Estado, se deberán reunir los requisitos que establece el artículo 80 de la Constitución del Estado.\nArtículo 133.- Para ser candidato a Gobernador del Estado, se deberán reunir los requisitos que establece el artículo 41 de la Constitución del Estado.\nArtículo 134.- Son impedimentos para ocupar los cargos de Gobernador, munícipes o diputados, además de los que en forma específica se señalen para cada caso de ellos en la\nConstitución Federal y en la Constitución del Estado, los siguientes:\nI. Ser Consejero Electoral o funcionario electoral del Instituto Estatal o del Instituto\nNacional, Magistrado o Secretario del Tribunal Electoral, salvo que se separe del cargo tres años antes de la fecha de inicio del proceso electoral de que se trate;\nFracción Reformada\nFederación, salvo que se separe del cargo tres años antes de la fecha de inicio del proceso electoral de que se trate; y,\nFracción Reformada\nIII. Tener sentencia firme por la comisión intencional de delitos contra la vida y la integridad corporal; contra la libertad y seguridad sexuales, el normal desarrollo psicosexual; por violencia familiar, violencia familiar equiparada o doméstica, violación a la intimidad\nLey Electoral del Estado de Baja California. Página 53\n.\nActualización Legislativa.\nÚltima reforma P. O. No. 60, Índice, 03-Oct-2025 sexual; por violencia política contra las mujeres en razón de género, en cualquiera de sus modalidades y tipos; o que las declare como persona deudora alimentaria morosa.\nFracción Adicionada\nArtículo Reformado\nCAPÍTULO SEGUNDO\nDel procedimiento de registro de candidatos\nArtículo 135.- Corresponde a los partidos políticos el derecho de solicitar el registro de candidatos a cargos de elección popular, sin perjuicio de las candidaturas independientes, en los términos de esta Ley.\nArtículo 136.- El registro de candidaturas a los distintos cargos de elección popular se hará de la forma siguiente:\nI. Para las Diputaciones, se hará por fórmulas integradas por propietario y suplente del mismo género, para el caso de la elección consecutiva, el candidato suplente podrá ser diverso que el registrado en la fórmula anterior.\nFracción Reformada\nII. La de munícipes se hará por planillas completas integradas por propietarios y suplentes del mismo género, de los cargos de Presidente Municipal, que encabezará la planilla; Síndico Procurador, que ocupará la segunda posición en la planilla; y Regidores, estos últimos en orden de prelación, para el caso de la elección consecutiva, el candidato suplente podrá ser diverso que el registrado en la fórmula anterior, y\nFracción Reformada\nIII. La de Gobernador del Estado, será unipersonal.\nLos propietarios y suplentes de la fórmula de diputaciones, y de la planilla de munícipes, a elegirse por el principio de mayoría relativa y por el principio de representación proporcional, serán considerados separadamente, salvo para los efectos del voto válidamente emitidos.\nPárrafo Reformado\nArtículo Reformado\nArtículo 137.- En el caso de que para un mismo cargo de elección popular sean registrados diferentes candidatos por un mismo partido político, el Consejero Presidente del\nConsejo que corresponda, una vez detectada esta situación, requerirá al partido político a efecto de que informe, en un plazo de veinticuatro horas, qué candidato o fórmula prevalece. presentados, quedando sin efecto los demás.\nArtículo 138.- Ningún partido político o coalición podrá solicitar el registro como candidato a un cargo de elección popular, a aquel ciudadano que previamente hubiera sido solicitado su registro por otro partido político o coalición.\nLey Electoral del Estado de Baja California. Página 54\n.\nActualización Legislativa.\nÚltima reforma P. O. No. 60, Índice, 03-Oct-2025\nArtículo 139.- Los partidos políticos promoverán y garantizarán la paridad entre los géneros, así como el principio de igualdad sustantiva, en la postulación de candidatos a los cargos de elección popular para la integración del Congreso y Ayuntamientos del Estado.\nPárrafo Reformado\nAdemás, conforme a los lineamientos que expida la autoridad electoral los partidos políticos deberán incluir entre las candidaturas descritas en el párrafo anterior, al menos una fórmula de las siguientes poblaciones de atención prioritaria: personas jóvenes de entre 18 a\n29 años de edad; personas de la diversidad sexual y de género, y personas con discapacidad.\nPárrafo Adicionado, recorriéndose el subsecuente\nSentencia a Acción de Inconstitucionalidad 198/2023 y su acumulada 200/2023\nPárrafo Reformado\nEl Consejo General tendrá facultades para rechazar el registro del número de candidaturas de un género que exceda la paridad, fijando al partido un plazo improrrogable para la sustitución de las mismas. En caso de que no sean sustituidas no se aceptarán dichos registros.\nArtículo Reformado\nArtículo 140.- De la totalidad de solicitudes de registro de las candidaturas a\nDiputaciones por el principio de mayoría relativa que presenten los partidos políticos o las coaliciones ante el Instituto, deberá salvaguardar la paridad entre los géneros mandatada en la Constitución del Estado. Cuando el partido político o coalición participe con candidaturas en la totalidad de los distritos, ocho serán de un mismo género.\nPárrafo Reformado\nLas listas de Diputaciones por el principio de representación proporcional se integrarán por fórmulas de candidatos compuestas cada una por un propietario y un suplente del mismo género, y se alternarán las fórmulas de distinto género para garantizar el principio de paridad hasta agotar cada lista.\nPárrafo Reformado\nLas planillas de munícipes se integrarán alternando candidatos de género distinto, conforme a la fracción II del artículo 136 de esta Ley; asimismo, las candidaturas para el entre ambos géneros.\nPárrafo Reformado\nArtículo Reformado\nArtículo 140 BIS.- De la totalidad de solicitudes de registro de las candidaturas a\nInstituto, deberán salvaguardar el principio de igualdad sustantiva. candidaturas a diputaciones, por lo menos dos fórmulas integradas por personas de la\nLey Electoral del Estado de Baja California. Página 55\n.\nActualización Legislativa.\nÚltima reforma P. O. No. 60, Índice, 03-Oct-2025 comunidad indígena o afromexicana; así como una formula en cada una de las plantillas de munícipes.\nEl Instituto reglamentara a las formas, procedimientos o métodos para acreditar, que las y los candidatos postulados bajo el principio de igualdad sustantiva, pertenecen al pueblo indígena o afromexicano que manifiestan.\nSera obligación de los partidos políticos o de los titulares de las candidaturas independientes, acreditar de acuerdo con la reglamentación expedida por el Instituto, el que pertenecen al pueblo indígena o afromexicano que manifiestan.\nLa postulación de las candidaturas que se establecen en este artículo no son limitativas, por lo que adicionalmente los partidos políticos podrán incluir más candidaturas en razón del principio de igualdad sustantiva.\nLas postulaciones acreditadas y que sean procedentes para sus registros, que garantizan el principio de igualdad sustantiva serán dadas a conocer mediante dictamen público expedido por la autoridad electoral, además se realizará la publicación de las lenguas originarias en la entidad y se les dará la máxima difusión para el conocimiento de las comunidades y pueblos indígenas.\nArtículo Adicionado\nArtículo 141.- Hecho el cierre de registro de candidaturas, si un partido político o coalición no cumple con lo establecido en los artículos 139 140 y 140 BIS que anteceden, el\nConsejo General le requerirá en primera instancia para que un plazo de cuarenta y ocho horas, contadas a partir de la notificación, rectifique la solicitud de registro de candidaturas y le apercibirá de que, en caso de no hacerlo le hará una amonestación pública.\nPárrafo Reformado\nTranscurrido el plazo a que se refiere el párrafo anterior, el partido político o coalición que no realice la sustitución de candidatos, será acreedor a una amonestación pública y el\nConsejo General le requerirá, de nueva cuenta, para que en un plazo de veinticuatro horas, contadas a partir de la notificación, haga la corrección. En caso de reincidencia se sancionará con la negativa del registro de las candidaturas a diputaciones o en su caso a la planilla de munícipes correspondiente.\nPárrafo Reformado\nArtículo Reformado\nArtículo 142.- Para el registro de candidaturas a todo cargo de elección popular, el que los candidatos sostendrán en las campañas políticas, dentro de los primeros quince días del mes de febrero del año de la elección. De cualquier cambio o modificación, los partidos políticos deberán dar aviso, antes del inicio de las campañas.\nArtículo 143.- Los partidos políticos o coaliciones no podrán registrar en el mismo proceso electoral, a un mismo ciudadano para diferentes cargos de elección popular.\nArtículo 144.- Los partidos políticos o coaliciones, y los aspirantes a Candidatos\nLey Electoral del Estado de Baja California. Página 56\n.\nActualización Legislativa.\nÚltima reforma P. O. No. 60, Índice, 03-Oct-2025 artículo 26 de la Ley de Candidaturas Independientes en el Estado, deberán presentar la solicitud de registro de candidaturas, en los plazos y ante los órganos competentes, en los siguientes términos:\nI. Para las candidaturas a Titular de Poder Ejecutivo estatal, todas las solicitudes de registro se harán ante el Consejo General, entre el veinte al veintisiete de marzo.\nFracción Reformada\nII. Para las candidaturas a diputados y munícipes por ambos principios, que tengan como fin la renovación del Congreso del Estado y los Ayuntamientos, las solicitudes de registro se harán entre el treinta y uno de marzo al once de abril, ante los siguientes órganos:\nFracción Reformada\na) Las fórmulas de candidatos a diputados por el principio de mayoría relativa, deberán registrarse ante el Consejo Distrital Electoral correspondiente, y\nb) Las planillas completas de munícipes, ante el Consejo General.\nInciso Reformado\nFracción Reformada\nLos partidos políticos o coaliciones, dentro del plazo señalado en este artículo, podrán modificar o sustituir las solicitudes presentadas.\nDe la solicitud de registro de candidatos a diputados por el principio de mayoría relativa, se enviará copia al Consejo General.\nEn ningún caso, un partido político o coalición podrá registrar más de dos candidatos a diputados por ambos principios.\nArtículo Reformado\nArtículo 145.- La solicitud de registro de candidaturas deberá señalar, en su caso, el partido político o coalición que las postulen y los siguientes datos de los candidatos:\nI. Apellidos paterno, materno y nombre completo;\nII. Lugar y fecha de nacimiento;\nIII. Domicilio y tiempo de residencia efectiva;\nIV. Ocupación;\nV. Clave de la credencial para votar;\nVI. Cargo para el que se les postule, y reelegirse en sus cargos, deberán acompañar una carta que especifique los periodos para establecidos por la Constitución en materia de reelección.\nArtículo Reformado\nLey Electoral del Estado de Baja California. Página 57\n.\nActualización Legislativa.\nÚltima reforma P. O. No. 60, Índice, 03-Oct-2025\nArtículo 146.- La solicitud de registro de candidaturas deberá acompañarse de lo siguiente:\nI. Escrito de aceptación de la candidatura por parte del ciudadano propuesto;\nII. Copia certificada del acta de nacimiento, de reconocimiento de hijo o de adopción, según el caso;\nIII. Copia de la credencial para votar;\nIV. Constancia de residencia expedida por la autoridad municipal competente, y\nV. Certificado de nacionalidad mexicana expedido por autoridad federal competente, en el caso de mexicanos nacidos en el extranjero.\nVI.- Escrito mediante el cual se compromete a registrar por lo menos con quince días de anticipación a la celebración de la jornada electoral, sus compromisos de campaña ante el Instituto Estatal;\nFracción Reformada\nVII. Escrito mediante el cual se compromete a presentar el examen para la detección de drogas de abuso, de conformidad con el artículo 5 de la Constitución del Estado. El\nInstituto Estatal Ciudadana celebrará convenio con alguna institución de Salud Pública en el\nEstado para practicar estos exámenes;\nFracción Reformada\nVIII. Escrito mediante el cual manifiesta bajo protesta de decir verdad no tener sentencia firme por la comisión intencional de delitos contra la vida y la integridad corporal; contra la libertad y seguridad sexuales, el normal desarrollo psicosexual; por violencia familiar, violencia familiar equiparada o doméstica, violación a la intimidad sexual; por violencia política contra las mujeres en razón de género, en cualquiera de sus modalidades y tipos, o que las declare como persona deudora alimentaria morosa; y,\nFracción Adicionada\nIX. Certificado de no inscripción en el Registro Nacional de Obligaciones Alimentarias.\nFracción Adicionada\nArtículo Reformado\nArtículo 147.- Para el registro de candidatos de coalición deberá acreditarse que se cumplió con lo dispuesto en la Ley General de Partidos y las disposiciones de esta Ley, de acuerdo con la elección de que se trate.\nArtículo 148.- Las autoridades municipales competentes, una vez reunidos los partidos políticos, las constancias que acrediten la residencia y tiempo de la misma.\nArtículo 149.- El procedimiento para resolver sobre las solicitudes de registro de candidaturas ante los Consejos Electorales, se sujetará a lo siguiente:\nI. Deberá ser presentada ante el Consejo Electoral correspondiente, en la forma y términos que señalan los artículos 144 al 147 de esta Ley;\nLey Electoral del Estado de Baja California. Página 58\n.\nActualización Legislativa.\nÚltima reforma P. O. No. 60, Índice, 03-Oct-2025\nII. Cualquier solicitud o documentación presentada fuera de los plazos a que se refiere el artículo 144 de esta Ley, será desechada de plano y, en su caso, no procederá el registro de la candidatura o candidaturas;\nIII. El Consejero Presidente y el Secretario Fedatario del Consejo Electoral correspondiente, una vez recibidas las solicitudes de registro de candidaturas, revisarán si se cumplen con los requisitos a que se refieren los artículos 145 al 147 de esta Ley; si de esta revisión se advierte que se omitió el cumplimiento de uno o varios requisitos, se notificara de inmediato al partido político o coalición solicitante, para que hasta la conclusión del plazo correspondiente contenido en el artículo 144 de esta Ley subsane el o los requisitos;\nFracción Reformada\nEn caso de que la solicitud de registro de candidaturas se presente el último día para ello, de existir observaciones, la autoridad competente deberá notificarlas al solicitante para que las subsane en un plazo de veinticuatro horas.\nIV. Los Consejos Electorales, al tercer día del vencimiento del plazo a que se refiere el artículo 144 de esta Ley, celebrarán sesión para resolver, a propuesta de sus\nConsejeros Presidentes, sobre las solicitudes planteadas y, en su caso, otorgar la constancia de registro correspondiente, y\nV. Los Consejeros Presidentes de los Consejos Distritales Electorales, comunicarán de inmediato al Consejero Presidente del Consejo General, el acuerdo relativo al registro de candidaturas que hayan realizado y copia certificada de la constancia de registro correspondiente.\nArtículo Reformado\nArtículo 150.- El Consejero Presidente del Consejo General una vez hechos los registros por los órganos correspondientes, ordenará la publicación de la relación de nombres de los candidatos y los partidos políticos o coaliciones que los hayan postulado, en el Periódico Oficial del Estado y en los diarios de mayor circulación. En la misma forma se publicarán las cancelaciones de registro o sustituciones de candidatos.\nArtículo 151.- Para la sustitución de candidatos, los partidos políticos y coaliciones lo solicitarán por escrito al Consejo Distrital o al Consejo General según corresponda, observando las siguientes disposiciones:\nI. Dentro del plazo establecido para el registro de candidatos podrán sustituirlos libremente, debiendo observar las reglas, el principio de paridad entre los géneros y el principio de igualdad sustantiva, establecido en esta Ley;\nFracción Reformada\nII. Vencido el plazo a que se refiere el inciso anterior, exclusivamente podrán sustituirlos por causas de fallecimiento, inhabilitación, incapacidad o renuncia. En este último caso, no podrán sustituirlos cuando la renuncia se presente dentro de los treinta días\nLey Electoral del Estado de Baja California. Página 59\n.\nActualización Legislativa.\nÚltima reforma P. O. No. 60, Índice, 03-Oct-2025 anteriores al de la elección. Para la corrección o sustitución, en su caso, de las boletas electorales se estará a lo dispuesto en el artículo 191 de esta Ley, y\nIII. En los casos en que la renuncia del candidato fuera notificada por éste al\nConsejo General, se hará del conocimiento del partido político que lo registró para que proceda, en su caso, a su sustitución.\nArtículo Reformado\nCAPÍTULO TERCERO\nDe las campañas electorales\nArtículo 152.- La campaña electoral, es el conjunto de actividades llevadas a cabo por los partidos políticos, las coaliciones y los candidatos registrados para la difusión de sus respectivas plataformas electorales y la obtención del voto.\nLas actividades que comprenden la campaña electoral, son:\nI. Actos de campaña: las reuniones públicas, debates, asambleas, visitas domiciliarias, marchas y en general aquellos en que los candidatos o voceros de los partidos políticos o coaliciones se dirigen al electorado para promover sus candidaturas, y\nII. Propaganda electoral: el conjunto de escritos, publicaciones, imágenes, grabaciones, proyecciones y expresiones que durante la campaña electoral producen y difunden los partidos políticos o coaliciones, los candidatos registrados y sus simpatizantes, con el propósito de presentar ante la ciudadanía las candidaturas registradas.\nLa propaganda electoral señalada en el párrafo anterior, quedará prohibida a los partidos políticos, las coaliciones y los candidatos registrados, cuando se trate de colocar, colgar, fijar, proyectar, adherir y pintar propaganda electoral en bardas, publivallas, espectaculares, pantallas electrónicas, postes o similares, ya sean éstos de uso común o privado, así como en unidades de servicio público de transporte de pasajeros o de carga.\nPárrafo Adicionado\nEl Consejo General está facultado para ordenar el retiro o la suspensión inmediata de la propaganda electoral que incumpla lo señalado en este artículo.\nPárrafo Adicionado\nTanto los actos de campaña, como la propaganda electoral deberán propiciar la exposición, desarrollo y discusión ante el electorado de los programas y acciones fijados por los partidos políticos o coaliciones en sus documentos básicos y, particularmente, en la plataforma electoral que para la elección en cuestión hubieren registrado.\nSe prohíbe la contratación por parte de terceros, de propaganda electoral a favor o en contra de algún partido político, coalición o candidato.\nPara los efectos de lo dispuesto por el párrafo quinto del artículo 100 de la\nConstitución del Estado, y el párrafo octavo del artículo 134 de la Constitución Federal, el informe anual de labores o gestión de los servidores públicos, así como los mensajes que para darlos a conocer se difundan en los medios de comunicación social, no serán\nLey Electoral del Estado de Baja California. Página 60\n.\nActualización Legislativa.\nÚltima reforma P. O. No. 60, Índice, 03-Oct-2025 considerados como propaganda, siempre que la difusión se limite a una vez al año en estaciones y canales con cobertura regional correspondiente al ámbito geográfico de responsabilidad del servidor público y no exceda de los siete días anteriores y cinco posteriores a la fecha en que se rinda el informe. En ningún caso la difusión de tales informes podrá tener fines electorales, ni realizarse dentro del periodo de campaña electoral.\nArtículo Reformado\nArtículo 153.- Los recursos que destinen los partidos políticos, las coaliciones y sus candidatos, en propaganda electoral y en actos de campaña, no podrán rebasar los topes que para cada elección determine el Consejo General.\nPara los efectos de este artículo quedarán comprendidos dentro de los topes de gasto los siguientes conceptos:\nI. Gastos de propaganda, que comprenden los realizados en bardas, mantas, volantes, pancartas, equipos de sonido, eventos políticos realizados en lugares alquilados, propaganda utilitaria, redes sociales y otros similares;\nFracción Reformada\nII. Gastos operativos de la campaña, que comprenden los sueldos y salarios del personal eventual, arrendamiento eventual de bienes muebles e inmuebles, gastos de transporte de material y personal, viáticos y otros similares;\nIII. Gastos de propaganda en diarios, revistas y otros medios impresos, que comprenden los realizados en cualquiera de esos medios, tales como inserciones pagadas, anuncios publicitarios y sus similares, tendentes a la obtención del voto. En todo caso, tanto el partido y candidato contratante, como el medio impreso, deberán identificar con toda claridad que se trata de propaganda o inserción pagada, y\nIV. Gastos de producción de los mensajes para radio y televisión, que comprenden los realizados para el pago de servicios profesionales; uso de equipo técnico, locaciones o estudios de grabación y producción, así como los demás inherentes al mismo objetivo.\nNo se considerarán dentro de los topes de campaña los gastos que realicen los partidos para su operación ordinaria y para el sostenimiento de sus órganos directivos y de sus organizaciones.\nArtículo Reformado\nArtículo 154.- El Consejo General, a más tardar el día veinte de febrero del año de la elección, aprobará los topes máximos de gastos de campaña que pueda erogar cada partido político o coalición, en cada una de las elecciones, de la propuesta que le haya presentado la Comisión de Partidos Políticos y Financiamientos, bajo las siguientes reglas:\nI. Determinará el valor unitario del voto, mediante el siguiente procedimiento:\na) Obtendrá un factor de actualización, dividiendo el Índice Nacional de Precios al\nConsumidor del mes de marzo del año del proceso electoral inmediato anterior, y\nLey Electoral del Estado de Baja California. Página 61\n.\nActualización Legislativa.\nÚltima reforma P. O. No. 60, Índice, 03-Oct-2025\nb) El factor, resultado del inciso anterior, se multiplicara por el valor unitario del voto que su hubiere determinado en el proceso electoral inmediato anterior;\nII. Una vez determinado el valor unitario del voto se obtendrá el tope máximo de gastos de campaña para la elección de diputados por el principio de mayoría relativa, para cada uno de los distritos, mediante las siguientes operaciones:\na) Determinará la extensión territorial de cada distrito en kilómetros cuadrados, asignando a cada uno de ellos, según corresponda, los siguientes valores: hasta 1,000 kilómetros cuadrados 0.50, más de 1,000 y hasta 2,000 kilómetros cuadrados 0.75 y más de\n2,000 kilómetros cuadrados 1.00;\nb) Determinará la densidad poblacional de cada uno de los distritos electorales, dividiendo el número de habitantes entre la extensión territorial del distrito, calculada en kilómetros cuadrados, y asignando de acuerdo a los resultados, a cada uno de los distritos, según corresponda, los siguientes valores: hasta 2,000 habitantes por kilómetro cuadrado\n1.00, de 2001 a 6,000 habitantes por kilómetro cuadrado 0.75 y los distritos con más de\n6,000 habitantes por kilómetro cuadrado 0.50;\nc) Determinará las condiciones de acceso de cada uno de los distritos electorales, asignando, según corresponda, los siguientes valores: distritos urbanos 0.50, distritos mixtos\n0.75 y distritos rurales 1.00;\nd) De los valores obtenidos en los incisos anteriores, se obtendrá un promedio para cada uno de los distritos;\ne) El promedio obtenido en el inciso anterior se multiplicará por el número de electores inscritos en el Padrón que corresponda a cada distrito al quince de enero del año de la elección, y éste a su vez por el valor unitario del voto, determinado por el Consejo\nGeneral, y\nf) El resultado obtenido en el inciso anterior, de cada uno de los distritos, será el tope máximo de gastos de campaña que corresponda a cada uno de ellos;\nIII. Para la elección de munícipes, el Consejo General fijará el tope máximo de gastos de campaña para dicha elección, sumando la cantidad que se haya fijado como topes máximos de gastos de campaña correspondiente a cada distrito que contenga cada\nMunicipio. Esta cantidad constituirá el tope máximo de gastos de campaña, en la elección de munícipes, en el municipio de que se trate.\nCuando la extensión territorial de un distrito ocupe más de un municipio, el tope máximo de gastos de campaña de éste, se distribuirá en forma proporcional al número de electores que corresponda, de ese distrito, a cada municipio.\nEn ningún caso, el tope de gastos de campaña de un municipio podrá ser inferior al veinte por ciento del más alto que corresponda a otro municipio, y\nIV. Para la elección de Gobernador del Estado, el Consejo General fijará el tope máximo de gastos para dicha elección, sumando los topes máximos de gastos de campaña de cada uno de los distritos electorales, que conforman el Estado.\nLey Electoral del Estado de Baja California. Página 62\n.\nActualización Legislativa.\nÚltima reforma P. O. No. 60, Índice, 03-Oct-2025\nArtículo 155.- Las reuniones públicas realizadas por los partidos políticos, coaliciones o por los candidatos registrados se regirán por lo dispuesto en el artículo 9 de la Constitución\nFederal y no tendrán más límite que el respeto a los derechos de terceros, en particular de otros partidos políticos y candidatos, así como las disposiciones que para el ejercicio de la garantía de reunión y preservación del orden público, dicte la autoridad administrativa competente.\nArtículo 156.- Cuando las autoridades pretendan facilitar a los partidos políticos, coaliciones o a los candidatos el uso de locales de propiedad pública, deberán considerar lo siguiente:\nI. Dar un trato equitativo a todos los que participen en la elección, y\nII. Atender en orden de prelación las solicitudes, evitando que los actos de los partidos políticos o coaliciones o candidatos coincidan en un mismo tiempo y lugar.\nArtículo 157.- La solicitud de los partidos políticos, coaliciones o candidatos registrados para que se les proporcione el uso de los locales deberán hacerla por escrito a la autoridad de que se trate con la debida anticipación, debiendo señalar los siguientes datos:\nI. La naturaleza del acto a realizar;\nII. El número de ciudadanos que se estima habrán de concurrir;\nIII. Las horas necesarias para la preparación y realización del evento, y\nIV. El nombre del ciudadano autorizado por el partido político, coalición o candidato que se responsabilice del uso del local y sus instalaciones.\nArtículo 158.- El Consejero Presidente del Consejo General previa solicitud por escrito del partido político, coalición o candidato que lo requiera, gestionará ante las autoridades competentes, las medidas de seguridad personal para sus candidatos, desde el momento en que obtengan su registro.\nArtículo 159.- Los partidos políticos o coaliciones, precandidatos o candidatos que durante la campaña electoral, pretendan realizar marchas o reuniones que impliquen interrupción temporal de la vialidad, deberán oportunamente hacer del conocimiento a la autoridad competente, el itinerario, día, hora y tiempo de duración, a fin de que ésta provea lo necesario para el libre desarrollo del evento.\nArtículo 160.- La propaganda electoral se sujetará invariablemente a las siguientes disposiciones:\nI. Se prohíbe la utilización de símbolos, signos, expresiones, alusiones o fundamentaciones de carácter religioso;\nII. Se prohíben las expresiones verbales o alusiones ofensivas a las personas, candidatos y partidos políticos y aquellas contrarias a la moral, a las buenas costumbres y de los diversos partidos o coaliciones, que contiendan en la elección, y\nLey Electoral del Estado de Baja California. Página 63\n.\nActualización Legislativa.\nÚltima reforma P. O. No. 60, Índice, 03-Oct-2025\nFracción Reformada\nIII. Propiciará la exposición, desarrollo y discusión ante el electorado de los programas y acciones propuestas por los partidos políticos o coaliciones, en sus documentos básicos y particularmente de la plataforma electoral.\nArtículo Reformado\nArtículo 161.- Toda la propaganda electoral impresa deberá ser reciclable, fabricada con materiales biodegradables que no contengan sustancias tóxicas o nocivas para la salud o el medio ambiente. Los partidos políticos y candidatos independientes deberán presentar un plan de reciclaje de la propaganda que utilizarán durante su campaña.\nPara efectos de esta Ley se entenderá por artículos promocionales utilitarios aquellos que contengan imágenes, signos, emblemas y expresiones que tengan por objeto difundir la imagen y propuestas del partido político, coalición o candidato que lo distribuye.\nLos artículos promocionales utilitarios sólo podrán ser elaborados con material textil.\nArtículo 162.- La propaganda electoral impresa que utilice el candidato, deberá contener identificación precisa del partido político o coalición que lo postula.\nArtículo 163.- Los partidos políticos, los precandidatos y candidatos podrán ejercer el derecho de réplica que establece el primer párrafo del artículo 6o. de la Constitución respecto de la información que presenten los medios de comunicación, cuando consideren que la misma ha deformado hechos o situaciones referentes a sus actividades. Este derecho se ejercitará sin perjuicio de aquéllos correspondientes a las responsabilidades o al daño moral que se ocasionen en términos de la ley que regule la materia de imprenta y de las disposiciones civiles y penales aplicables.\nEl derecho a que se refiere el párrafo anterior se ejercerá en la forma y términos que determine la ley de la materia.\nArtículo 164.- La propaganda que los partidos políticos, las coaliciones y los candidatos realicen en la vía pública, a través de grabaciones y, en general, por cualquier otro medio, se sujetará a lo previsto por el artículo 160 de esta Ley, así como a las disposiciones administrativas expedidas en materia de prevención de la contaminación por\nArtículo 165.- En la colocación de propaganda electoral los partidos políticos, coaliciones y candidatos, observarán las reglas siguientes:\nI. No podrá colgarse en elementos del equipamiento urbano, ni obstaculizar en orientarse dentro de los centros de población. Las autoridades electorales competentes ordenarán el retiro de la propaganda electoral contraria a esta norma;\nII. Podrá colgarse o fijarse en inmuebles de propiedad privada, siempre que medie autorización, conforme a los lineamientos que en su caso emita el Instituto Nacional;\nLey Electoral del Estado de Baja California. Página 64\n.\nActualización Legislativa.\nÚltima reforma P. O. No. 60, Índice, 03-Oct-2025\nIII. Podrá colgarse o fijarse en los bastidores y mamparas de uso común que determine el Consejo General, previo acuerdo con las autoridades correspondientes; los bastidores y mamparas de uso común serán repartidos por sorteo en forma equitativa de conformidad a lo que corresponda a los partidos políticos registrados, conforme al procedimiento acordado por el Consejo General, durante el mes de febrero. Previo al inicio de las campañas electorales, los Consejos Distritales realizarán el sorteo a que se refiere la presente fracción;\nIV. No podrá fijarse o pintarse en elementos del equipamiento urbano, carretero o ferroviario, ni en accidentes geográficos cualquiera que sea su régimen jurídico, tales como cerros, colinas, montañas y en general cuando se modifique el paisaje natural y urbano o perjudique el entorno ecológico;\nV. Derogada\nFracción Derogada\nVI. No podrá colgarse, fijarse o pintarse en monumentos históricos, arqueológicos, artísticos y construcciones de valor cultural.\nArtículo Reformado\nArtículo 166.- Se prohíbe a los partidos políticos, coaliciones y candidatos la sobreposición, destrucción o alteración de cualquier modalidad de propaganda electoral de otros partidos y candidatos.\nArtículo Reformado\nArtículo 167.- Los partidos políticos, coaliciones o candidatos denunciarán al Consejo\nGeneral aquello que obstaculice la libre y pacífica celebración de los actos de las campañas electorales, y de los que destruyan o inutilicen su propaganda o material, y en su caso, adoptará las medidas a que hubiere lugar.\nLos particulares que de manera indebida destruyan propaganda electoral serán sancionados conforme a las disposiciones legales correspondientes.\nArtículo 168.- El Instituto Estatal bajo los lineamientos y directrices que determine el los cargos de elección popular.\nPárrafo Reformado\nLos debates tendrán por objeto el contenido de las respectivas plataformas, que hayan registrado los partidos políticos, coaliciones y Candidatos Independientes.\nEl Consejo General definirá las reglas, fechas y sede de los debates, respetando el partidos políticos y candidaturas independientes.\nPárrafo Reformado\nLey Electoral del Estado de Baja California. Página 65\n.\nActualización Legislativa.\nÚltima reforma P. O. No. 60, Índice, 03-Oct-2025\nEl Instituto dispondrá lo necesario para la producción técnica y difusión de los debates. En la disposición de las señales de radio y televisión se estará a lo dispuesto en los párrafos 4 y 5 del artículo 218 de la Ley General.\nPárrafo Reformado\nEl Instituto informará a la sociedad, en el tiempo de radio y televisión asignado para sus fines, la realización de los debates a que se refiere el presente artículo.\nArtículo Reformado\nArtículo 169.- Las campañas electorales de los partidos políticos, coaliciones y candidatos registrados iniciarán al día siguiente del otorgamiento del registro de candidaturas para la elección respectiva por el Consejo Electoral correspondiente, y concluirán tres días antes del día de la elección, durante los cuales no se permitirá la celebración de reuniones o actos públicos de campaña, de propaganda o de proselitismo electorales.\nQueda prohibido realizar actos de campaña y de propaganda electoral, antes de la fecha de expedición de constancias del registro de candidaturas.\nDurante el tiempo que comprendan las campañas electorales y hasta la conclusión de la respectiva jornada comicial, deberá suspenderse la difusión en los medios de comunicación social de toda propaganda gubernamental, tanto de los poderes del estado, como de los municipios, entidades paraestatales, organismos constitucionales autónomos y cualquier otro ente público. Las únicas excepciones a lo anterior serán las campañas de información de las autoridades electorales, las relativas a servicios educativos y de salud, o las necesarias para la protección civil en casos de emergencia.\nA los servidores públicos que sean candidatos, ya sea por primera vez o de elección consecutiva, se le prohíbe en el transcurso de las campañas electorales asistir a eventos públicos o privados relacionados con la entrega de beneficios de programas sociales u obras públicas ejecutadas con financiamiento de gobierno, así como el uso de recursos humanos o materiales que tengan asignados por motivos de su cargo.\nPárrafo Adicionado\nEn caso de que dentro del plazo señalado en el presente artículo, la propaganda de los partidos políticos, coaliciones o candidatos contenga datos falsos o imprecisiones, respecto de los programas o actividades institucionales, las autoridades podrán hacer uso de los medios de comunicación para hacer las aclaraciones pertinentes.\nArtículo Reformado\nArtículo 170.- De conformidad con las reglas, lineamientos y criterios, que emita el\nConsejo General del Instituto Nacional, las personas físicas o morales deberán adoptarlas para realizar encuestas o sondeos de opinión durante el proceso electoral local, así como el\nInstituto Estatal para realizar las funciones en la materia.\nDurante los tres días previos a la elección y hasta la hora de cierre de las casillas, queda estrictamente prohibido publicar, difundir o dar a conocer por cualquier medio de\nLey Electoral del Estado de Baja California. Página 66\n.\nActualización Legislativa.\nÚltima reforma P. O. No. 60, Índice, 03-Oct-2025 comunicación, los resultados de las encuestas o sondeos de opinión, que tengan como fin dar a conocer las preferencias electorales.\nLas personas físicas o morales que difundan encuestas o sondeos de opinión deberán presentar al Instituto Estatal un informe sobre los recursos aplicados en su realización en los términos que disponga la autoridad electoral correspondiente.\nLa metodología, costos, personas responsables y resultados de las encuestas o sondeos serán difundidas en su página de Internet, por el Instituto Estatal en el ámbito de su competencia.\nArtículo 171.- La distribución o colocación de la propaganda electoral deberá respetar los tiempos legales que se establezcan para cada caso, su retiro o fin de su distribución deberá efectuarse tres días antes de la jornada electoral. En el caso de la propaganda colocada en vía pública, deberá retirarse durante los siete días posteriores a la conclusión de la jornada electoral; en caso contrario, las autoridades municipales correspondientes procederán a retirar la propaganda de los lugares públicos, por cuenta de los partidos políticos o coaliciones.\nLa autoridad municipal, una vez que retire la propaganda electoral, presentará al\nInstituto Electoral el costo correspondiente a cada partido político, mismo que deberá cubrirse dentro de los quince días posteriores a la notificación que se le haga, y en su caso, le será deducido del financiamiento público estatal que les corresponda, independientemente a las sanciones administrativas a que se hagan acreedores.\nLa notificación a los partidos políticos y Candidatos Independientes del costo respectivo, se realizará por el Instituto Estatal dentro de los tres días siguientes a que la reciba.\nCualquier infracción a las disposiciones relativas, a la propaganda electoral será sancionada en los términos de esta Ley.\nCAPÍTULO CUARTO\nDe los procedimientos para la integración y ubicación de las mesas directivas de casilla\nArtículo 172.- [En las elecciones locales concurrentes con la federal, la integración, recepción de la votación, se realizará con base en las disposiciones de la Ley General.\nTratándose de elecciones locales extraordinarias la integración, ubicación y esta Ley. capacitación electoral, así como la ubicación de casillas y la designación de los funcionarios\nLey Electoral del Estado de Baja California. Página 67\n.\nActualización Legislativa.\nÚltima reforma P. O. No. 60, Índice, 03-Oct-2025 de la mesa directiva de casillas en los procesos electorales locales, se estará a lo dispuesto en la Ley General.]\nArtículo 172 invalidado por Sentencia de Acción de Inconstitucional 42/2015 y sus acumuladas 43/2015 y 44/2015\nArtículo 173.- Las secciones en que se dividen los distritos uninominales tendrán como máximo 3,000 electores.\nEn toda sección electoral por cada 750 electores o fracción se instalará una Mesa\nDirectiva de Casilla, para recibir la votación de los ciudadanos residentes en la misma; de ser dos o más se colocarán en forma contigua, de manera que no se interfiera la actividad de una con otras, y se dividirá la lista nominal de electores en orden alfabético.\nCuando el crecimiento demográfico de las secciones lo exija, se estará a lo siguiente:\nI. En caso de que el número de ciudadanos inscritos en la lista nominal de electores correspondiente a una sección, sea superior a 3,000 electores, se instalarán en un mismo sitio o local tantas casillas como que resulten de dividir alfabéticamente el número de ciudadanos restantes de la Lista entre 750, y\nII. No existiendo un local que permita la instalación de las casillas necesarias en un mismo sitio, éstas se ubicarán en lugares diversos, atendiendo a la concentración y distribución de los electores en la sección.\nCuando las condiciones geográficas de una sección hagan difícil el acceso de todos los electores residentes en ella a un mismo sitio, podrá acordarse la instalación de varias casillas extraordinarias, en lugares que ofrezcan un fácil acceso a los electores.\nEn cada casilla se instalarán mamparas, donde los votantes puedan decidir en secreto el sentido de su voto. El diseño y ubicación de estas mamparas en las casillas se hará de manera que garanticen plenamente el secreto del voto.\nArtículo 174.- Los procedimientos para determinar la ubicación de las casillas y para la integración de la mesa directiva se aplicarán las reglas establecidas en la Ley General.\nArtículo 175.- Las casillas deberán ubicarse en lugares que reúnan los requisitos siguientes:\nI. Fácil y libre acceso para los electores;\nII. Aseguren la instalación de canceles o elementos modulares que garanticen el secreto en la emisión del voto;\nIII. No ser casa habitada por servidores públicos de confianza, federales, estatales o municipales;\nIV. No ser inmuebles habitados o propiedad de dirigentes de partidos políticos o candidatos registrados en la elección de que se trate;\nV. No ser establecimientos fabriles, templos o locales destinados al culto, o locales de partidos políticos, y\nVI. No ser locales ocupados por cantinas, centros de vicio o similares.\nLey Electoral del Estado de Baja California. Página 68\n.\nActualización Legislativa.\nÚltima reforma P. O. No. 60, Índice, 03-Oct-2025\nPara la ubicación de las casillas se preferirán, en caso de reunir los requisitos señalados por las fracciones I y II del párrafo anterior, los locales ocupados por escuelas y oficinas públicas.\nPara la ubicación de las mesas directivas de casilla, los consejos electorales que correspondan deberán observar que en un perímetro de cincuenta metros al lugar propuesto no existan oficinas de órganos de partidos políticos, agrupaciones políticas o casas de campaña de los candidatos.\nArtículo 176.- Las listas de integrantes de las mesas directivas y ubicación de casillas, se fijarán en los edificios y lugares públicos más concurridos del municipio y en los medios electrónicos de que disponga el Instituto Estatal.\nEl Consejero Presidente del Consejo Distrital, entregará una copia impresa y en medio magnético de la lista de cada uno de los representantes de los partidos políticos y de los candidatos independientes, haciendo constar la entrega.\nLos consejos electorales vigilarán que las listas permanezcan en sus lugares de publicación por un plazo de por lo menos siete días.\nArtículo 177.- En cada Municipio del Estado se instalará una casilla especial, únicamente para la recepción del voto de los electores en las elecciones de Gobernador y de diputados por el principio de representación proporcional, que se encuentren transitoriamente fuera del Municipio correspondiente a su domicilio.\nPara la integración de la mesa directiva y de la ubicación de las casillas especiales, se aplicarán las reglas establecidas en la Ley General.\nCAPÍTULO QUINTO\nDel registro de representantes ante las mesas directivas de casilla\nArtículo 178.- Los partidos políticos, una vez registrados sus candidatos, planillas, fórmulas y las listas, y hasta trece días antes del día de la elección, tendrán derecho a nombrar dos representantes propietarios y un suplente, ante cada mesa directiva de casilla, y representantes generales propietarios. Este mismo derecho lo tendrán los candidatos independientes.\nEn los casos de elecciones concurrentes con la federal, cada partido político o candidato independiente, según sea el caso, podrá acreditar un representante propietario y un suplente. electorales ubicadas en zonas urbanas y uno por cada cinco casillas rurales. mesas directivas de casilla y generales, podrán firmar sus nombramientos hasta antes de acreditarse en la casilla; así mismo, deberán portar en lugar visible durante todo el día de la\nLey Electoral del Estado de Baja California. Página 69\n.\nActualización Legislativa.\nÚltima reforma P. O. No. 60, Índice, 03-Oct-2025 jornada electoral, un distintivo de hasta 2.5 por 2.5 centímetros, con el emblema del partido político al que pertenezcan o al que representen y con la leyenda visible de \"representante\".\nLos representantes de los partidos políticos y de Candidatos Independientes recibirán una copia legible de las actas a que se refiere la fracción II del artículo 181 de esta Ley. En caso de no haber representante en las mesas directivas de casilla, las copias serán entregadas al representante general que así lo solicite.\nLa entrega de las copias legibles a que se refiere el párrafo anterior se hará en el orden de antigüedad del registro por partido político.\nArtículo 179.- Los ciudadanos propuestos para fungir como representantes generales, o como representantes ante las mesas directivas de casilla, deberán reunir los siguientes requisitos:\nI. Estar inscritos en el Padrón Electoral;\nII. Contar con credencial para votar, y\nIII. No haber sido designado funcionario de casilla para el proceso electoral vigente.\nArtículo 180.- La actuación de los representantes generales de los partidos políticos y de los candidatos independientes, estará sujeta a las normas siguientes:\nI. Ejercerán su cargo exclusivamente ante las mesas directivas de casilla, instaladas en el distrito electoral o municipio para el que fueron acreditados;\nII. Deberán actuar individualmente, y en ningún caso podrá hacerse presente al mismo tiempo en las casillas más de un representante general de un mismo partido político;\nIII. Podrán actuar en representación del partido político, y de ser el caso de la candidatura independiente que los acreditó, indistintamente para las elecciones que se celebren en la fecha de la jornada electoral;\nIV. No sustituirán en sus funciones a los representantes de los partidos políticos y de candidatos independientes ante las mesas directivas de casilla, sin embargo, podrán coadyuvar en sus funciones y en el ejercicio de los derechos de éstos ante las propias mesas directivas de casilla;\nV. En ningún caso ejercerán o asumirán las funciones de los integrantes de las mesas directivas de casilla;\nVI. No obstaculizarán el desarrollo normal de la votación en las casillas en las que se presenten;\nVII. En todo tiempo podrán presentar escritos de incidentes que se susciten durante el desarrollo de la jornada electoral, pero sólo podrán presentar escritos de protesta al término independiente ante la mesa directiva de casilla no estuviere presente, y\nLey Electoral del Estado de Baja California. Página 70\n.\nActualización Legislativa.\nÚltima reforma P. O. No. 60, Índice, 03-Oct-2025\nVIII. Podrán comprobar la presencia de los representantes de su partido político en las mesas directivas de casilla y recibir de ellos los informes relativos a su desempeño.\nArtículo 181.- Los representantes de los partidos políticos y de los candidatos independientes debidamente acreditados ante las mesas directivas de casilla, tendrán los siguientes derechos:\nI. Participar en la instalación de la casilla y contribuir al buen desarrollo de sus actividades hasta su clausura. Tendrán el derecho de observar y vigilar el desarrollo de la elección;\nII. Recibir copia legible de las actas que se levante en la casilla, previo acuse de recibo;\nIII. Presentar escritos relacionados con incidentes ocurridos durante la votación;\nIV. Presentar al término del escrutinio y del cómputo escritos de protesta;\nV. Acompañar al presidente de la mesa directiva de casilla, al consejo distrital correspondiente, para hacer entrega de la documentación y el expediente electoral, y\nVI. Los demás que establezca esta Ley.\nLos representantes vigilarán el cumplimiento de las disposiciones de esta Ley y deberán firmar todas las actas que se levanten, pudiéndolo hacer bajo protesta con mención de la causa que la motiva.\nArtículo 182.- El registro de los nombramientos de los representantes ante las mesas directivas de casilla y de los representantes generales se hará ante el consejo distrital correspondiente, y se sujetará a las reglas siguientes:\nI. A partir del día siguiente al de la publicación de las listas de casilla y hasta trece días antes del día de la elección, los partidos políticos y los Candidatos Independientes deberán registrar en su propia documentación y ante el consejo distrital correspondiente, a sus representantes generales y de casilla. La documentación de que se trata deberá reunir los requisitos que establezca el Consejo General;\nII. Los consejos distritales devolverán a los partidos políticos el original de los nombramientos respectivos, debidamente sellados y firmados por el presidente y el secretario del mismo, conservando un ejemplar, y\nIII. Los partidos políticos y los Candidatos Independientes podrán sustituir a sus representantes hasta con diez días de anterioridad a la fecha de la elección, devolviendo con el nuevo nombramiento, el original del anterior.\nArtículo 183.- La solicitud de registro o sustitución de nombramientos de representantes, se sujetará a lo siguiente:\nI. Se hará mediante escrito firmado por el dirigente o representante del partido político ante el Consejo Distrital Electoral correspondiente, o por el representante del Candidato\nIndependiente, y\nLey Electoral del Estado de Baja California. Página 71\n.\nActualización Legislativa.\nÚltima reforma P. O. No. 60, Índice, 03-Oct-2025\nII. Se anexará una relación con los nombres de los representantes y tipo de representación, el carácter de propietario o suplente, la clave de la credencial para votar de cada uno de ellos y el número del distrito electoral tratándose de representantes generales, y en el caso de los representantes ante las mesas directivas de casilla, el número de sección y tipo de casilla en que actuará.\nLas solicitudes de registro que no reúnan uno o varios de los requisitos se regresarán al partido político o Candidato Independiente solicitante, para que dentro de los tres días siguientes, subsane las omisiones. Vencido el término señalado sin corregirse la omisión, no se registrará el nombramiento.\nArtículo 184.- Los nombramientos de los representantes ante las mesas directivas de casilla, deberán contener los siguientes datos:\nI. Denominación del partido político o nombre completo del candidato independiente;\nII. Nombre del representante;\nIII. Indicación de su carácter de propietario o suplente;\nIV. Número del distrito electoral, sección y casilla en que actuarán;\nV. Clave de la credencial para votar;\nVI. Lugar y fecha de la expedición, y\nVII. Firma del dirigente o representante del partido político, o del candidato independiente que haga el nombramiento.\nPara garantizar a los representantes ante la mesa directiva de casilla el ejercicio de los derechos que les otorga esta Ley, se imprimirá al reverso del nombramiento el texto de los artículos que correspondan.\nArtículo 185.- En caso de que el Consejero Presidente del Consejo Distrital no resuelva dentro de las 48 horas siguientes a la solicitud o niegue el registro, el partido político interesado podrá solicitar al Consejero Presidente del Consejo General, registre a los representantes de manera supletoria.\nArtículo 186.- Para garantizar a los representantes de los partidos políticos y de\nCandidatos Independientes su debida acreditación ante la mesa directiva de casilla, el\nConsejero Presidente del Consejo Distrital entregará al Presidente de cada Mesa, una relación de los que tengan derecho de actuar en la casilla de que se trate. Asimismo, entregará una lista con los nombramientos de los representantes generales.\nArtículo 187.- Los nombramientos de los representantes generales deberán contener casilla, con excepción del número de casilla. presidentes de las mesas directivas de casilla.\nLey Electoral del Estado de Baja California. Página 72\n.\nActualización Legislativa.\nÚltima reforma P. O. No. 60, Índice, 03-Oct-2025\nPara garantizar a los representantes generales el ejercicio de los derechos que les otorga esta Ley, se imprimirá al reverso del nombramiento el texto de los artículos que correspondan.\nCAPÍTULO SEXTO\nDe la documentación y el material electoral\nArtículo 188.- En la impresión de documentos y producción de materiales electorales, se deberán observar las características indicadas en el artículo 216 de La Ley General.\nArtículo 189.- Para la emisión del voto, se imprimirán las boletas electorales para cada elección, las que se harán conforme al modelo que apruebe las autoridades competentes, tomando en cuenta las medidas de certeza que estime pertinentes.\nLas características de la documentación y material electoral se determinarán en términos de lo señalado en las reglas, lineamientos, criterios y formatos aprobados por el\nInstituto Nacional.\nArtículo 190.- Las boletas para cada una de las elecciones, contendrán:\nI. Municipio y distrito correspondientes;\nII. Cargo para el que se postula al candidato o candidatos;\nIII. Emblema a color de cada uno de los partidos políticos que participan con candidatos propios, o en coalición, en la elección de que se trate;\nIV. Las boletas tendrán un talón con folio, del cual serán desprendibles. La información que contendrá el talón será la relativa al municipio, distrito y elección que corresponda. El número de folio será progresivo;\nV. Apellidos paterno, materno y nombre completo del candidato o candidatos;\nVI. En la elección de Diputados, aparecerá en el anverso un recuadro que contenga el nombre y fotografía a color del candidato o candidata a Diputado o Diputada por el principio de mayoría relativa a propietario y el nombre de su suplente, postulado por cada partido político; al reverso los recuadros que contengan el logo y denominación de los partidos políticos con la leyenda “elección de diputados por el principio de representación proporcional”;\nFracción Reformada\nVII. En la elección de Munícipes, aparecerá en el anverso un recuadro que nombre de su suplente, postulado por cada partido político; al reverso el nombre de los candidatos a Síndico Procurador y el de los Regidores, señalando el carácter de propietarios y suplentes;\nFracción Reformada\nVIII. En la elección de Gobernador del Estado, un solo espacio para cada partido político, candidato o candidata y fotografía a color;\nFracción Reformada\nLey Electoral del Estado de Baja California. Página 73\n.\nActualización Legislativa.\nÚltima reforma P. O. No. 60, Índice, 03-Oct-2025\nIX. Las firmas impresas del Consejero Presidente del Consejo General y del\nSecretario Ejecutivo del Instituto Estatal;\nX. Espacio para candidatos no registrados, y\nXI. Espacios para candidatos Independientes.\nLos emblemas a color de los partidos políticos, así como las fotografías a color de las candidatas y los candidatos aparecerán en igual tamaño en la boleta y en el orden que les corresponde de acuerdo a la fecha de su registro. En el caso de que el registro a dos o más partidos políticos haya sido otorgado en la misma fecha, los emblemas de los partidos políticos aparecerán en la boleta en el orden descendente que les corresponda de acuerdo al porcentaje de votación obtenido en la última elección de diputados locales.\nPárrafo Reformado\nEn caso de existir coaliciones, los emblemas de los partidos coaligados, los nombres y fotografías de los candidatos aparecerán con el mismo tamaño y en un espacio de las mismas dimensiones que aquéllos que se destinen en la boleta a los partidos que participan por sí mismos. En ningún caso podrán aparecer emblemas conjuntos de los partidos coaligados en un mismo recuadro, ni utilizar emblemas distintos para la coalición.\nPárrafo Reformado\nEl Instituto Estatal establecerá las especificaciones y lineamientos técnicos sobre las fotografías a color de las y los candidatos a los que hace referencia el presente artículo.\nPárrafo Adicionado\nArtículo Reformado\nArtículo 191.- No habrá modificación a las boletas en caso de cancelación del registro o sustitución de uno o más candidatos, si éstas ya estuvieran impresas. En todo caso, los votos contarán para los partidos políticos y los candidatos que estuviesen legalmente registrados ante los consejos electorales correspondientes.\nArtículo 192.- Las boletas deberán estar en poder de los consejos distritales, quince días antes de la jornada electoral.\nPara el control de las boletas se adoptarán las siguientes medidas:\nI. Los consejos distritales deberán designar con la oportunidad debida, el lugar que elecciones;\nII. El personal autorizado por el Consejo General entregará las boletas en el día, hora y lugar preestablecidos, al Presidente del Consejo Distrital correspondiente, quien estará acompañado de los demás integrantes del propio órgano que así lo deseen;\nIII. El Secretario del Consejo Distrital levantará acta circunstanciada de la entrega y recepción de las boletas, asentando en ella los datos relativos al número de boletas, las presentes;\nLey Electoral del Estado de Baja California. Página 74\n.\nActualización Legislativa.\nÚltima reforma P. O. No. 60, Índice, 03-Oct-2025\nIV. A continuación, los miembros presentes del Consejo Distrital que así lo deseen, acompañarán al Presidente para depositar la documentación recibida, en el local previamente autorizado, debiendo asegurar la integridad de dicha documentación mediante fajillas selladas y firmadas por los concurrentes. Estos pormenores se asentarán en el acta respectiva;\nV. En el mismo día o a más tardar el siguiente, el Presidente, el Secretario y los consejeros electorales del Consejo correspondiente, procederán a contar las boletas para precisar la cantidad recibida, sellarlas al dorso y agruparlas en razón del número de electores que corresponda a cada una de las casillas a instalar, según el número que acuerde el Consejo General para tal efecto. El Secretario registrará los datos de esta distribución;\nVI. Estas operaciones se realizarán con la presencia de los representantes de los partidos políticos o candidatos independientes que decidan asistir.\nLos representantes de los partidos bajo su más estricta responsabilidad, si lo desearen, podrán firmar las boletas, levantándose un acta en la que consten el número de boletas que se les dio a firmar, el número de las firmadas y, en su caso, el número de boletas faltantes después de haber realizado el procedimiento de firma. En este último caso se dará noticia de inmediato a la autoridad competente.\nLa falta de la firma de dichos representantes en las boletas, no impedirá su oportuna distribución.\nArtículo 193.- Los Consejeros Presidentes de los Consejos Distritales Electorales, con el apoyo del Departamento de Procesos Electorales, entregarán a cada presidente de mesa directiva de casilla, dentro de los cinco días previos al anterior de la elección y contra el recibo detallado correspondiente:\nI. La Lista Nominal de Electores con fotografía de la sección electoral, según corresponda;\nII. La relación de los representantes de los partidos y Candidatos Independientes registrados para la casilla en el consejo distrital electoral;\nIII. La relación de los representantes generales acreditados por cada partido político en el distrito en que se ubique la casilla en cuestión;\nIV. Las boletas para cada elección, en número igual al de los electores que figuren en la Lista Nominal de Electores con fotografía para cada casilla de la sección electoral;\nV. Las urnas para recibir la votación, una para cada elección de que se trate;\nVI. El líquido indeleble;\nVII. La documentación, formas aprobadas, útiles de escritorio y demás elementos necesarios;\nVIII. Los instructivos que indiquen las atribuciones y responsabilidades de los funcionarios de la casilla, y\nLey Electoral del Estado de Baja California. Página 75\n.\nActualización Legislativa.\nÚltima reforma P. O. No. 60, Índice, 03-Oct-2025\nIX. Los canceles o elementos modulares que garanticen que el elector pueda emitir su voto en secreto.\nArtículo 194.- A los presidentes de mesas directivas de las casillas especiales les será entregada la documentación y materiales a que se refiere el artículo anterior, con excepción de la lista nominal de electores con fotografía, en lugar de la cual recibirán los medios informáticos necesarios para verificar que los electores que acudan a votar se encuentren inscritos en la lista nominal de electores que corresponde al domicilio consignado en su credencial para votar. El número de boletas que reciban no será superior a\n1,500.\nEn la elección de munícipes, serán igual al número de funcionarios propietarios de la casilla, así como de los representantes acreditados por los partidos políticos y Candidatos\nIndependientes ante la misma.\nAsimismo recibirá un sello especial con la leyenda “Representación Proporcional” o\n“R.P.”, para los efectos de lo dispuesto en la fracción III del artículo 223 de esta Ley. La tinta que se utilice para fijar el sello, será de color que contraste con el del marcador para votar.\nArtículo 195.- El líquido indeleble seleccionado deberá garantizar plenamente su eficacia. Los envases que lo contengan deberán contar con elementos que identifiquen el producto.\nArtículo 196.- Las urnas en que los electores depositen las boletas, una vez emitido el sufragio, deberán construirse de un material transparente, plegable o armable.\nLas urnas llevarán en el exterior y en lugar visible, impresa o adherida en el mismo color de la boleta que corresponda, la denominación de la elección de que se trate.\nArtículo 197.- La recepción de la documentación, material y útiles a que se refiere este Capítulo, se hará con la participación de los integrantes de los Consejos Distritales\nElectorales que decidan asistir.\nArtículo 198.- Los presidentes de las mesas directivas de casilla conservarán bajo su responsabilidad, hasta la instalación de la casilla, el material, documentación y útiles que hayan recibido de los Consejos Distritales Electorales para el desarrollo de la jornada electoral.\nArtículo 199.- El presidente y el secretario de cada casilla cuidarán las condiciones materiales del local en que ésta haya de instalarse para facilitar la votación, garantizar la libertad y el secreto del voto, y asegurar el orden en la elección. En el local de la casilla y en su exterior no deberá haber propaganda partidaria; de haberla, la mandarán retirar.\nTÍTULO CUARTO\nDe la Jornada Electoral\nCAPÍTULO PRIMERO\nDisposiciones Generales\nLey Electoral del Estado de Baja California. Página 76\n.\nActualización Legislativa.\nÚltima reforma P. O. No. 60, Índice, 03-Oct-2025\nArtículo 200.- La Jornada Electoral en los procesos electorales locales concurrentes con los federales, se ajustará a lo dispuesto para su desarrollo por la Ley General.\nFuera de los casos previstos en el párrafo anterior, la Jornada Electoral de las elecciones locales se realizará en los términos previstos por la presente Ley.\nLas facultades que tendrán los funcionarios de las mesas directivas de casilla designados para las elecciones del Estado en los procesos electorales locales concurrentes con los federales, de acuerdo a la integración prevista por la Ley General, se sujetará a lo determinado por la misma y por los acuerdos generales o lineamientos que al efecto emita el\nInstituto Nacional.\nCAPÍTULO SEGUNDO1\nDe la instalación y apertura de casillas\nArtículo 201.- Durante el día de la elección se levantará el acta de la jornada electoral, que contendrá los datos comunes a todas las elecciones y las actas relativas al escrutinio y cómputo de cada una de las elecciones.\nArtículo 202.- El primer domingo de junio del año de la elección ordinaria, a las 7:30 horas, los ciudadanos presidente, secretario y escrutadores de las mesas directivas de las casillas nombrados como propietarios deberán presentarse para iniciar con los preparativos para la instalación de la casilla en presencia de los representantes de partidos políticos y de\nCandidatos Independientes que concurran.\nArtículo 203.- A solicitud de un partido político, las boletas electorales podrán ser rubricadas o selladas por uno de los representantes partidistas o de candidatos ante la casilla designado por sorteo, quien podrá hacerlo por partes para no obstaculizar el desarrollo de la votación. En el supuesto de que el representante que resultó facultado en el sorteo se negare a firmar o sellar las boletas, el representante que en un principio lo haya solicitado tendrá ese derecho. La falta de rúbrica o sello en las boletas no será motivo para anular los sufragios recibidos. Acto continuo, se iniciará el levantamiento del acta de la jornada electoral, llenándose y firmándose el apartado correspondiente a la instalación de la casilla.\nArtículo 204.- En ningún caso se podrán instalar casillas antes de las 07:30 horas. En ningún caso se podrán recibir votos antes de las 08:00 horas. sea clausurada.\nArtículo 205.- El acta de la jornada electoral constará de los siguientes apartados:\nII. El de cierre de votación.\nLey Electoral del Estado de Baja California. Página 77\n.\nActualización Legislativa.\nÚltima reforma P. O. No. 60, Índice, 03-Oct-2025\nEn el apartado correspondiente a la instalación, se hará constar:\na) El lugar, la fecha y la hora en que se inicia el acto de instalación;\nb) El nombre completo y firma autógrafa de las personas que actúan como funcionarios de casilla;\nc) El número de boletas recibidas para cada elección en la casilla que corresponda, consignando en el acta los números de folios;\nd) Que las urnas se armaron o abrieron en presencia de los funcionarios y representantes presentes para comprobar que estaban vacías y que se colocaron en una mesa o lugar adecuado a la vista de los electores y representantes de los partidos políticos y de Candidatos Independientes;\ne) Una relación de los incidentes suscitados, si los hubiere, y\nf) En su caso, la causa por la que se cambió de ubicación la casilla.\nArtículo 206.- De no instalarse la casilla, a las 8:15 horas conforme los artículos 202 y 204 anteriores, se estará a lo siguiente:\nI. Si estuviera el presidente, éste designará a los funcionarios necesarios para su integración, recorriendo, en primer término y, en su caso, el orden para ocupar los cargos de los funcionarios ausentes con los propietarios presentes y habilitando a los suplentes presentes para los faltantes, y en ausencia de los funcionarios designados, de entre los electores que se encuentren en la casilla;\nII. Si no estuviera el presidente, pero estuviera el secretario, éste asumirá las funciones de presidente de la casilla y procederá a integrarla en los términos señalados en el inciso anterior;\nIII. Si no estuvieran el presidente ni el secretario, pero estuviera alguno de los escrutadores, éste asumirá las funciones de presidente y procederá a integrar la casilla de conformidad con lo señalado en la fracción I;\nIV. Si sólo estuvieran los suplentes, uno de ellos asumirá las funciones de presidente, los otros las de secretario y primer escrutador, procediendo el primero a instalar la casilla nombrando a los funcionarios necesarios de entre los electores presentes, verificando previamente que se encuentren inscritos en la lista nominal de electores de la sección correspondiente y cuenten con credencial para votar;\nV. Si no asistiera ninguno de los funcionarios de la casilla, el Consejo Distrital tomará de ejecutarlas y cerciorarse de su instalación;\nVI. Si llegada las 10:00 horas y aún no se ha instalado la casilla, y se cuenta con la presencia del presidente y el secretario o de quienes asumieron sus funciones, estos procederá a su instalación;\nVII. Cuando por razones de distancia o de dificultad de las comunicaciones, no sea posible la intervención oportuna del personal del Instituto designado o del Instituto Nacional, Ley Electoral del Estado de Baja California. Página 78\n.\nActualización Legislativa.\nÚltima reforma P. O. No. 60, Índice, 03-Oct-2025 a las 11:00 horas, los representantes de los partidos políticos y de Candidatos\nIndependientes ante las mesas directivas de casilla designarán, por mayoría, a los funcionarios necesarios para integrar las casillas de entre los electores presentes, verificando previamente que se encuentren inscritos en la lista nominal de electores de la sección correspondiente y cuenten con credencial para votar. En este supuesto se requerida:\na) La presencia de un juez o notario público, quien tiene la obligación de acudir y dar fe de los hechos, y\nb) En ausencia del juez o notario público, bastará que los representantes expresen su conformidad para designar, de común acuerdo, a los miembros de la mesa directiva.\nNo podrán instalarse las mesas directivas de casilla, después de las 13:00 horas.\nEn todo caso, integrada conforme a los anteriores supuestos, la mesa directiva de casilla, iniciará sus actividades, recibirá válidamente la votación y funcionará hasta su clausura.\nArtículo 207.- Los nombramientos que se hagan conforme a lo dispuesto en el artículo anterior, deberán recaer en electores que se encuentren en la casilla para emitir su voto; en ningún caso podrán recaer los nombramientos en los representantes de los partidos políticos o representantes de los Candidatos Independientes.\nArtículo 208.- Los funcionarios y representantes que actuaron en la casilla, deberán, sin excepción, firmar las actas.\nArtículo 209.- Se considera que existe causa justificada para la instalación de una casilla en lugar distinto al señalado, cuando:\nI. No exista el local indicado en las publicaciones respectivas;\nII. El local se encuentre cerrado o clausurado y no se pueda realizar la instalación;\nIII. Se advierta, al momento de la instalación de la casilla, que ésta se pretende realizar en lugar prohibido por la ley;\nIV. Las condiciones del local no permitan asegurar la libertad o el secreto del voto o el fácil y libre acceso de los electores o bien, no garanticen la realización de las operaciones electorales en forma normal. En este caso, será necesario que los funcionarios y representantes presentes tomen la determinación de común acuerdo, y\nV. El consejo distrital así lo disponga por causa de fuerza mayor o caso fortuito y se lo notifique al presidente de la casilla. la misma sección y en el lugar adecuado más próximo, debiéndose dejar aviso de la nueva ubicación en el exterior del lugar original que no reunió los requisitos.\nCAPÍTULO TERCERO\nLey Electoral del Estado de Baja California. Página 79\n.\nActualización Legislativa.\nÚltima reforma P. O. No. 60, Índice, 03-Oct-2025\nDe la Votación\nArtículo 210.- Una vez llenada y firmada el acta de la jornada electoral en el apartado correspondiente a la instalación, el presidente de la mesa anunciará el inicio de la votación.\nArtículo 211.- Iniciada la votación no podrá suspenderse sino por causa de fuerza mayor. En este caso, corresponde al presidente dar aviso de inmediato al consejo distrital a través del medio de comunicación a su alcance para dar cuenta de la causa de suspensión, la hora en que ocurrió y la indicación de los votantes que al momento habían ejercido su derecho de voto, lo que será consignado en el acta.\nEl aviso de referencia deberá ser constatado por dos testigos, que lo serán preferentemente, los integrantes de la mesa directiva o los representantes.\nRecibida la comunicación que antecede, el consejo distrital decidirá si se reanuda la votación, para lo cual tomará las medidas que estime necesarias.\nArtículo 212.- Los electores votarán en el orden en que se presenten ante la mesa directiva de casilla, debiendo mostrar su credencial para votar o en su caso, la resolución del\nTribunal Electoral del Poder Judicial de la Federación que les otorga el derecho de votar sin aparecer en la lista nominal o sin contar con credencial para votar o en ambos casos.\nLos presidentes de casilla permitirán emitir su voto a aquellos ciudadanos cuya credencial para votar contenga errores de seccionamiento, siempre que aparezcan en la lista nominal de electores con fotografía correspondiente a su domicilio.\nEn el caso referido en el párrafo anterior, los presidentes de casilla, además de identificar a los electores en los términos de esta Ley, se cerciorarán de su residencia en la sección correspondiente por el medio que estimen más efectivo.\nArtículo 213.- El presidente de la casilla recogerá las credenciales para votar que tengan muestras de alteración o no pertenezcan al ciudadano, poniendo a disposición de las autoridades a quienes las presenten.\nEl secretario de la mesa directiva anotará el incidente en el acta respectiva, con mención expresa del nombre del ciudadano o ciudadanos presuntamente responsables.\nArtículo 214.- Una vez comprobado que el elector aparece en las listas nominales y que haya exhibido su credencial para votar, el presidente de la mesa directiva de casilla le que sufraga, o anote el nombre del candidato no registrado por el que desea emitir su voto. marcar sus boletas de voto, podrán hacerse asistir por una persona de su confianza que les acompañe.\nActo seguido, el elector doblará sus boletas y se dirigirá a depositarlas en la urna correspondiente.\nLey Electoral del Estado de Baja California. Página 80\n.\nActualización Legislativa.\nÚltima reforma P. O. No. 60, Índice, 03-Oct-2025\nEl secretario de la casilla, auxiliado en todo tiempo por uno de los escrutadores, deberá anotar, con el sello que le haya sido entregado para tal efecto, la palabra \"votó\" en la lista nominal correspondiente y procederá a:\nI. Marcar la credencial para votar del elector que ha ejercido su derecho de voto;\nII. Impregnar con líquido indeleble el dedo pulgar derecho del elector, y\nIII. Devolver al elector su credencial para votar.\nArtículo 215.- Los representantes de los partidos políticos y de Candidatos\nIndependientes ante las mesas directivas, podrán ejercer su derecho de voto en la casilla en la que estén acreditados, para lo cual se seguirá el procedimiento señalado en éste y el anterior artículo, anotando el nombre completo y la clave de la credencial para votar de los representantes al final de la lista nominal de electores.\nArtículo 216.- Corresponde al presidente de la mesa directiva, en el lugar en que se haya instalado la casilla, el ejercicio de la autoridad para preservar el orden, asegurar el libre acceso de los electores, garantizar en todo tiempo el secreto del voto y mantener la estricta observancia de esta Ley.\nLos miembros de la mesa directiva deberán permanecer en la casilla a lo largo de la votación, pero en ningún caso podrán interferir con la libertad y secreto del voto de los electores.\nArtículo 217.- Tendrán derecho de acceso a las casillas:\nI. Los electores que hayan sido admitidos por el presidente de la mesa directiva de casilla en los términos que fija el artículo 214 de esta Ley;\nII. Los representantes de los partidos políticos y de Candidatos Independientes debidamente acreditados en los términos que fija esta Ley;\nIII. Los notarios públicos y los jueces que deban dar fe de cualquier acto relacionado con la integración de la mesa directiva, la instalación de la casilla y, en general, con el desarrollo de la votación siempre y cuando se hayan identificado ante el presidente de la mesa directiva y precisada la índole de la diligencia a realizar, misma que en ningún caso podrá oponerse al secreto de la votación, y\nIV. Los funcionarios del Instituto que fueren enviados por el Consejo General o\nDistrital, o llamados por el presidente de la mesa directiva.\nArtículo 218.- Los representantes generales permanecerán en las casillas el tiempo necesario para cumplir con las funciones que les fija el artículo 180 de esta Ley; no podrán integrantes de la mesa directiva. El presidente de la mesa directiva podrá conminarlos a cumplir con sus funciones y, en su caso, podrá ordenar su retiro cuando el representante deje de cumplir su función, coaccione a los electores, o en cualquier forma afecte el desarrollo normal de la votación.\nLey Electoral del Estado de Baja California. Página 81\n.\nActualización Legislativa.\nÚltima reforma P. O. No. 60, Índice, 03-Oct-2025\nArtículo 219.- En ningún caso se permitirá el acceso a las casillas a personas que se encuentren privadas de sus facultades mentales, intoxicadas, bajo el influjo de enervantes, embozadas o armadas.\nTampoco tendrán acceso a las casillas, salvo que sea para ejercer su derecho de voto, miembros de corporaciones o fuerzas de seguridad pública, dirigentes de partidos políticos, candidatos o representantes populares.\nArtículo 220.- El presidente de la mesa directiva podrá solicitar, en todo tiempo, el auxilio de las fuerzas de seguridad pública a fin de preservar el orden en la casilla y la normalidad de la votación, ordenando el retiro de cualquier persona que indebidamente interfiera o altere el orden.\nEn estos casos, el secretario de la casilla hará constar las causas del quebranto del orden y las medidas acordadas por el presidente de la mesa directiva de casilla, en un acta especial que deberá firmarse por los funcionarios de la casilla y los representantes de los partidos acreditados ante la misma. Si algún funcionario o representante se negase a firmar, el secretario hará constar la negativa.\nArtículo 221.- Los representantes de los partidos políticos y de Candidatos\nIndependientes podrán presentar al secretario de la mesa directiva escritos sobre cualquier incidente que en su concepto constituya una infracción a lo dispuesto por esta Ley.\nEl secretario recibirá tales escritos y los incorporará al expediente electoral de la casilla sin que pueda mediar discusión sobre su admisión.\nArtículo 222.- Ninguna autoridad podrá detener a los integrantes de las mesas directivas de casilla o a los representantes de los partidos y Candidatos Independientes durante la jornada electoral, salvo en el caso de delito flagrante.\nArtículo 223.- En las casillas especiales se recibirá la votación de Gobernador y de diputados por el principio de representación proporcional, de los electores que transitoriamente se encuentren fuera de su Municipio, y se aplicarán, además de las reglas establecidas en los artículos anteriores de este Capítulo, las siguientes:\nI. El ciudadano además de exhibir su credencial para votar a requerimiento del\nPresidente de la Mesa Directiva de Casilla, deberá mostrar el pulgar izquierdo para constatar que no ha votado en otra casilla;\nII. El Secretario de la Mesa Directiva, verificará la vigencia de la credencial para procederá a asentar en el acta de electores en tránsito, los datos de la misma, y\nIII. Una vez asentados los datos anteriores, se procederá a entregarle la boleta correspondiente a la elección Gobernador, y en su caso, para la de diputados, esta última deberá ser sellada previamente con la leyenda “Representación Proporcional” o “R. P.”, recabando la firma del elector.\nLey Electoral del Estado de Baja California. Página 82\n.\nActualización Legislativa.\nÚltima reforma P. O. No. 60, Índice, 03-Oct-2025\nAdicionalmente se recibirá la votación de munícipes y diputados por el principio de mayoría relativa que emitan los funcionarios y los representantes de los partidos políticos o\nCandidatos Independientes, designados y acreditados para la casilla especial.\nArtículo 224.- La votación se cerrará a las 18:00 horas. Podrá cerrarse antes de la hora señalada, sólo cuando el presidente y el secretario certifiquen que hubieren votado todos los electores incluidos en la lista nominal correspondiente.\nSólo permanecerá abierta después de las 18:00 horas, aquella casilla en la que aún se encuentren electores formados para votar. En este caso, se cerrará una vez que quienes estuviesen formados a las 18:00 horas hayan votado.\nArtículo 225.- El presidente declarará cerrada la votación al cumplirse con los extremos previstos en el artículo anterior.\nActo seguido, el secretario llenará el apartado correspondiente al cierre de votación del acta de la jornada electoral, el cual deberá ser firmado por los funcionarios y representantes.\nEn todo caso, el apartado correspondiente al cierre de votación contendrá la hora de cierre y la causa por la que, si es el caso, se cerró antes o después de las 18:00 horas.\nCAPÍTULO CUARTO\nDel Escrutinio y Cómputo en la Casilla\nArtículo 226.- Una vez cerrada la votación y llenado y firmado el apartado correspondiente del acta de la jornada electoral, los integrantes de la mesa directiva procederán al escrutinio y cómputo de los votos sufragados en la casilla.\nArtículo 227.- El escrutinio y cómputo es el procedimiento por el cual los integrantes de cada una de las mesas directivas de casilla, determinan:\nI. El número de electores que votó en la casilla;\nII. El número de votos emitidos en favor de cada uno de los partidos políticos o candidatos;\nIII. El número de votos nulos, y\nIV. El número de boletas sobrantes de cada elección.\nArtículo 228.- Para los efectos de este Capítulo se entiende por votos nulos:\nI. Aquél expresado por un elector en una boleta que depositó en la urna, sin haber candidatura independiente, y\nII. Cuando el elector marque dos o más cuadros sin existir coalición entre los partidos cuyos emblemas hayan sido marcados.\nLey Electoral del Estado de Baja California. Página 83\n.\nActualización Legislativa.\nÚltima reforma P. O. No. 60, Índice, 03-Oct-2025\nCuando el elector marque en la boleta dos o más cuadros y exista coalición entre los partidos cuyos emblemas hayan sido marcados, el voto contará para el candidato de la coalición y se registrará por separado en el espacio correspondiente del acta de escrutinio y cómputo de casilla.\nSe entiende por boletas sobrantes aquéllas que habiendo sido entregadas a la mesa directiva de casilla no fueron utilizadas por los electores.\nArtículo 229.- El orden en que se llevará el escrutinio y cómputo, será el siguiente:\nI. De Gobernador;\nII. De munícipes;\nIII. De diputados de mayoría relativa, y\nIV. Para el caso de las casillas especiales, el de diputados de representación proporcional.\nArtículo 230.- El escrutinio y cómputo de cada elección se realizará conforme a las reglas siguientes:\nI. El secretario de la mesa directiva de casilla contará las boletas sobrantes y las inutilizará por medio de dos rayas diagonales con tinta, las guardará en un sobre especial el cual quedará cerrado y anotará en el exterior del mismo el número de boletas que se contienen en él;\nII. Los escrutadores contará en dos ocasiones, el número de ciudadanos que aparezca que votaron conforme a la lista nominal de electores de la sección, sumando, en su caso, el número de electores que votaron por resolución del Tribunal Electoral del Poder\nJudicial de la Federación, y además del número de representantes de partidos políticos o coaliciones que votaron en la casilla sin aparecer en la lista nominal;\nIII. El presidente de la mesa directiva abrirá la urna, sacará las boletas y mostrará a los presentes que la urna quedó vacía;\nIV. Los escrutadores contará las boletas extraídas de la urna;\nV. Los escrutadores bajo la supervisión del presidente, clasificarán las boletas para determinar:\na) El número de votos emitidos a favor de cada uno de los partidos políticos o candidatos, y\nb) El número de votos que sean nulos, y\nVI. El secretario anotará en hojas dispuestas al efecto los resultados de cada una de las operaciones señaladas en las fracciones anteriores, los que, una vez verificados por los demás integrantes de la mesa, transcribirá en las respectivas actas de escrutinio y cómputo de cada elección.\nEn el caso del escrutinio y cómputo de la elección de diputados, en las casillas\nLey Electoral del Estado de Baja California. Página 84\n.\nActualización Legislativa.\nÚltima reforma P. O. No. 60, Índice, 03-Oct-2025 términos de la fracción III del artículo 223 de esta Ley, asentándose los resultados, en los términos de la fracción VI de este Artículo.\nTratándose de partidos coaligados, si apareciera cruzado más de uno de sus respectivos emblemas, se asignará el voto al candidato de la coalición, lo que deberá consignarse en el apartado respectivo del acta de escrutinio y cómputo correspondiente.\nArtículo 231.- Para determinar la validez o nulidad de los votos se observarán las reglas siguientes:\nI. Se contará un voto válido por la marca que haga el elector en un solo cuadro en el que se contenga el emblema de un partido político, atendiendo lo dispuesto en el último párrafo del artículo inmediato anterior;\nII. Se contará como nulo cualquier voto emitido en forma distinta a la señalada, y\nIII. Los votos emitidos a favor de candidatos no registrados se asentarán en el acta por separado.\nArtículo 232.- Si se encontrasen boletas de una elección en la urna correspondiente a otra, se separarán y se computarán en la elección respectiva.\nArtículo 233.- Se levantará un acta de escrutinio y cómputo para cada elección. Cada acta contendrá, por lo menos:\nI. El número de votos emitidos a favor de cada partido político o candidato;\nII. El número total de las boletas sobrantes que fueron inutilizadas;\nIII. El número de votos nulos;\nIV. El número de representantes de partidos que votaron en la casilla sin estar en el listado nominal de electores;\nV. Una relación de los incidentes suscitados, si los hubiere, y\nVI. La relación de escritos de protesta presentados por los representantes de los partidos políticos y de Candidatos Independientes al término del escrutinio y cómputo.\nEn todo caso se asentarán los datos anteriores en las formas aprobadas por la autoridad electoral competente. inutilizadas.\nLos funcionarios de las mesas directivas de casilla, con el auxilio de los representantes de los partidos políticos y de Candidatos Independientes, verificarán la exactitud de los datos que consignen en el acta de escrutinio y cómputo.\nArtículo 234.- Concluido el escrutinio y el cómputo de todas las votaciones se levantarán las actas correspondientes de cada elección, las que deberán firmar, sin excepción, todos los funcionarios y los representantes que actuaron en la casilla.\nLey Electoral del Estado de Baja California. Página 85\n.\nActualización Legislativa.\nÚltima reforma P. O. No. 60, Índice, 03-Oct-2025\nLos representantes de los partidos políticos y de Candidatos Independientes ante las casillas tendrán derecho a firmar el acta bajo protesta, señalando los motivos de la misma.\nSi se negaran a firmar, el hecho deberá consignarse en el acta.\nArtículo 235.- Al término del escrutinio y cómputo de cada una de las elecciones, se formará un expediente de casilla con la documentación siguiente:\nI. Un ejemplar del acta de la jornada electoral;\nII. Un ejemplar del acta final de escrutinio y cómputo, y\nIII. Los escritos de protesta que se hubieren recibido.\nSe remitirán también, en sobres por separado, las boletas sobrantes inutilizadas y las que contengan los votos válidos y los votos nulos para cada elección.\nLa lista nominal de electores se remitirá en sobre por separado.\nArtículo 236.- Para garantizar la inviolabilidad de la documentación anterior, con el expediente de cada una de las elecciones y los sobres, se formará un paquete en cuya envoltura firmarán los integrantes de la mesa directiva de casilla y los representantes que desearan hacerlo.\nLa denominación expediente de casilla corresponderá al que se hubiese formado con las actas y los escritos de protesta referidos en el artículo anterior.\nArtículo 237.- De las actas de las casillas asentadas en la forma o formas que al efecto apruebe la autoridad electoral competente, se entregará una copia legible a los representantes de los partidos políticos y de Candidatos Independientes, recabándose el acuse de recibo correspondiente. La primera copia de cada acta de escrutinio y cómputo será destinada al programa de resultados electorales preliminares.\nPor fuera del paquete a que se refiere el párrafo primero del artículo anterior, se adherirá un sobre que contenga un ejemplar del acta en que se contengan los resultados del escrutinio y cómputo de cada una de las elecciones, para su entrega al presidente del consejo distrital correspondiente.\nArtículo 238.- Cumplidas las acciones a que se refiere el artículo anterior, los presidentes de las mesas directivas de casilla, fijarán avisos en lugar visible del exterior de las mismas con los resultados de cada una de las elecciones, los que serán firmados por el presidente y los representantes que así deseen hacerlo.\nCAPÍTULO QUINTO\nArtículo 239.- Concluidas por los funcionarios de la mesa directiva de casilla las operaciones establecidas en los artículos anteriores, el secretario levantará constancia de la entrega del paquete que contenga los expedientes. La constancia será firmada por los\nLey Electoral del Estado de Baja California. Página 86\n.\nActualización Legislativa.\nÚltima reforma P. O. No. 60, Índice, 03-Oct-2025 funcionarios de la casilla y los representantes de los partidos y de Candidatos\nIndependientes que desearen hacerlo.\nArtículo 240.- A partir de la hora de clausura de las casillas los presidentes de las mesas directivas de casilla, bajo su responsabilidad, entregarán al Consejo Distrital Electoral que corresponda, los paquetes y expedientes dentro de los plazos siguientes:\nI. Inmediatamente cuando se trate de casillas urbanas, y\nII. Hasta seis horas cuando se trate de casillas rurales.\nArtículo 241.- El Consejo Distrital Electoral que corresponda, previamente al día de la elección, podrá determinar la ampliación de los plazos de recepción de paquetes y expedientes de casilla, para aquellas que lo justifiquen.\nLos Consejos Distritales adoptarán previamente al día de la elección, las medidas necesarias para que los paquetes con los expedientes de las elecciones sean entregados dentro de los plazos establecidos y para que puedan ser recibidos en forma simultánea.\nArtículo 242.- Se considerará que existe causa justificada para que los paquetes con los expedientes de casilla sean entregados al Consejo Distrital Electoral fuera de los plazos establecidos, cuando medie caso fortuito o fuerza mayor.\nArtículo 243.- Los Consejos Distritales Electorales, podrán acordar un mecanismo para la recolección y recepción de los paquetes electorales de las casillas cuando fuere necesario, lo cual se realizará bajo la vigilancia de los representantes de los partidos políticos que así desearen hacerlo.\nCAPÍTULO SEXTO\nDisposiciones Complementarias\nArtículo 244.- Para asegurar el orden y garantizar el desarrollo de la jornada electoral, los cuerpos de seguridad pública del Estado y de los Municipios, deberán prestar el auxilio que les requieran los Consejos del Instituto Estatal y los presidentes de las mesas directivas de casilla. encargados del orden, que se encuentren en servicio.\nArtículo 245.- Las autoridades estatales y municipales, con relación a la jornada lo siguiente:\nI. La información que obre en su poder, relacionada con la jornada electoral;\nII. Las certificaciones de los hechos que les consten o de los documentos que existan en los archivos a su cargo, relacionados con el proceso electoral;\nLey Electoral del Estado de Baja California. Página 87\n.\nActualización Legislativa.\nÚltima reforma P. O. No. 60, Índice, 03-Oct-2025\nIII. El apoyo necesario para practicar las diligencias que les sean demandadas para fines electorales, y\nIV. La información de los hechos que puedan influir o alterar el resultado de las elecciones.\nEl día de la elección permanecerán abiertas las oficinas de los Juzgados del Fuero\nComún, de los Juzgados Calificadores, Agencias del Ministerio Público y de las autoridades administrativas habilitadas para realizar esas funciones.\nArtículo 246.- Los notarios públicos mantendrán abiertas sus oficinas el día de la jornada electoral desde las 7:30 hasta las 24:00 horas, y deberán atender en forma gratuita las solicitudes que les hagan las autoridades electorales, los funcionarios de casilla, los ciudadanos y los representantes de partidos políticos y de Candidatos Independientes, para dar fe de hechos o certificar documentos concernientes a la elección.\nArtículo 247.- En el caso de que el Instituto Estatal, por delegación del Instituto\nNacional, ejerza las funciones de capacitación electoral, ubicación de casillas y la designación de los funcionarios de la mesa directiva de casillas en los procesos electorales locales, corresponde a los Consejos Distritales designar a un número suficiente de supervisores y capacitadores asistentes electorales, conforme a los requisitos establecidos en el artículo 303 de la Ley General.\nTÍTULO QUINTO\nDe los Actos Posteriores a la Elección y los Resultados Electorales\nCAPÍTULO PRIMERO\nDe la Disposición Preliminar\nArtículo 248.- La recepción, depósito y custodia de los paquetes en que se contengan los expedientes de casilla, por parte de los Consejos Distritales Electorales, se hará conforme al procedimiento siguiente:\nI. Se recibirán en el orden en que vayan llegando;\nII. El Consejero Presidente o funcionario autorizado del Consejo Distrital Electoral, extenderá el recibo señalando la hora en que fueron entregados;\nIII. El Consejero Presidente del Consejo Distrital Electoral dispondrá su depósito en un lugar dentro del local del Consejo, atendiendo el orden numérico de la casilla, y en su caso, colocará por separado la especial, y\nIV. El Consejero Presidente del Consejo Distrital Electoral bajo su responsabilidad, los depositados, en presencia de los integrantes del Consejo.\nLey Electoral del Estado de Baja California. Página 88\n.\nActualización Legislativa.\nÚltima reforma P. O. No. 60, Índice, 03-Oct-2025\nDe la recepción de los paquetes que contengan los expedientes de casilla, se levantará acta circunstanciada en la que se haga constar, en su caso, los que hubieren sido recibidos sin reunir los requisitos o fuera de los plazos que señale esta Ley.\nCAPÍTULO SEGUNDO\nDe la información preliminar de los resultados\nArtículo 249.- El Programa de Resultados Electorales Preliminares es el mecanismo de información electoral encargado de proveer los resultados preliminares y no definitivos, de carácter estrictamente informativo a través de la captura, digitalización y publicación de los datos asentados en las Actas de Escrutinio y Cómputo de las casillas que se reciben en los Centros de Acopio y Transmisión de Datos autorizados por el Instituto Estatal.\nEl Instituto Estatal se sujetará a las reglas, lineamientos y criterios en materia de resultados preliminares que emita el Instituto Nacional.\nArtículo 250.- Los consejos distritales electorales anotarán los resultados contenidos en el acta de la jornada electoral, conforme éstas se vayan recibiendo y hasta el vencimiento del plazo legal para la entrega de los paquetes que contengan los expedientes electorales, de acuerdo a las siguientes reglas:\nI. Los consejos distritales autorizarán al personal para la recepción continua y simultánea de los paquetes electorales. Los partidos políticos y candidatos independientes podrán acreditar a sus representantes suplentes para que estén presentes durante dicha recepción;\nII. El presidente del distrital, recibirá las actas de escrutinio y cómputo, y de inmediato dará lectura en voz alta al resultado de la votación que aparezca en ellas;\nIII. El secretario anotará esos resultados en el lugar que les corresponda en la forma destinada para ello, conforme al orden numérico de las casillas;\nIV. El secretario efectuará la suma correspondiente al total de las casillas computadas, y\nV. El presidente informará de inmediato, al Consejo General, sobre estos resultados.\nLos representantes de los partidos políticos y candidatos independientes, acreditados ante el consejo electoral competente, contarán con las formas adecuadas para anotar en ellas los resultados de la votación en las casillas.\nArtículo 251.- Para hacer del conocimiento de los ciudadanos los resultados iniciales de las elecciones en el Distrito, una vez concluido el procedimiento a que se refiere el artículo anterior de esta Ley, los consejeros presidentes deberán fijarlos en el exterior del local de los consejos distritales electorales.\nArtículo 252.- El Instituto Estatal determinará la viabilidad en la realización de conteos rápidos, de conformidad con los lineamientos que emita el Instituto Nacional.\nLey Electoral del Estado de Baja California. Página 89\n.\nActualización Legislativa.\nÚltima reforma P. O. No. 60, Índice, 03-Oct-2025\nDe igual manera, las personas físicas o morales que realicen estos conteos pondrán a consideración del Instituto Estatal, las metodologías y el financiamiento para su elaboración y términos para dar a conocer los resultados.\nCAPÍTULO TERCERO\nDe los Cómputos de las Elecciones en los Consejos Distritales\nArtículo 253.- El cómputo distrital de una elección es la suma que realiza el Consejo\nDistrital, de los resultados anotados en las actas de escrutinio y cómputo de las casillas en un distrito electoral.\nArtículo 254.- Los consejos distritales electorales tendrán, a partir de las 8:00 horas del miércoles siguiente al día de la jornada electoral y hasta siete días, inclusive, para hacer el cómputo de las elecciones de Diputaciones por el principio de mayoría relativa, Munícipes, Gubernatura y Diputaciones por el principio de representación proporcional, en los términos del artículo 256 de esta Ley.\nPárrafo Reformado\nLas sesiones de cómputo de las elecciones mencionadas, serán video grabadas y transmitidas en tiempo real por los medios que el Consejo General del Instituto Estatal determine en cada jornada electoral, debiendo captarse tanto el trabajo del consejo como el asentamiento de resultados en las formas o sabanas correspondientes, para cumplir con el principio de máxima publicidad. Las grabaciones deberán resguardarse, para su posterior revisión si fuese necesario de oficio o a petición de parte acreditada.\nArtículo Reformado\nArtículo 255.- Los consejos distritales electorales, en sesión previa a la jornada electoral podrán acordar, a efecto de que la sesión de cómputo sea ininterrumpida, que:\nI. Los consejeros electorales numerarios se alternen con los supernumerarios;\nII. Se designe a los consejeros electorales que sustituirán al Consejero Presidente y al Secretario Fedatario, en las ausencias;\nIII. Los representantes de los partidos políticos acrediten en sus ausencias a suplentes, y\nIV. El personal de apoyo designado por el Instituto Estatal, para que puedan sustituirse o alternarse entre sí.\nLos consejos distritales deberán contar con los elementos humanos, materiales, técnicos y financieros, necesarios para la realización del cómputo en forma permanente.\nArtículo 256.- El cómputo distrital de las elecciones de diputaciones por el principio de mayoría relativa, Munícipes, Gubernatura o Diputaciones por el principio de representación proporcional, se realizará simultáneamente, bajo el procedimiento siguiente:\nPárrafo Reformado\nLey Electoral del Estado de Baja California. Página 90\n.\nActualización Legislativa.\nÚltima reforma P. O. No. 60, Índice, 03-Oct-2025\nI. Primeramente, se abrirá el paquete que contenga los expedientes de la elección que no tengan muestras de alteración y siguiendo el orden numérico de las casillas; se cotejará el resultado anotado en el apartado correspondiente del acta de la jornada electoral contenida en el expediente de casilla con los resultados que de la misma obre en poder de la o el consejero presidente del consejo distrital electoral, en el orden siguiente, Gubernatura, Munícipes y Diputaciones por el principio de mayoría relativa. Si los resultados coinciden, se asentará en las formas establecidas para ello;\nFracción Reformada\nII. Si los resultados no coinciden, o no se encuentra el acta de la jornada electoral en el expediente de la casilla, ni obrare un ejemplar en poder del Consejero Presidente, se procederá a realizar nuevamente el escrutinio y cómputo de la casilla, levantándose el acta correspondiente. Los resultados se anotarán en la forma establecida para ello, dejándose constancia en el acta circunstanciada correspondiente; de igual manera, se harán constar en dicha acta las objeciones que hubiesen manifestado cualquiera de los representantes de los partidos políticos o de los Candidatos Independientes ante el Consejo, para los efectos conducentes. En ningún caso se podrá obstaculizar la realización de los cómputos;\nIII. En su caso, se sumarán los votos que hayan sido emitidos a favor de dos o más partidos coaligados y que por esa causa hayan sido consignados por separado en el apartado correspondiente del acta de escrutinio y cómputo de casilla. La suma distrital de tales votos se distribuirá igualitariamente entre los partidos que integran la coalición; de existir fracción, los votos correspondientes se asignarán a los partidos de más alta votación.\nIV. Además de los supuestos señalados en la fracción II del presente artículo, el consejo distrital deberá realizar nuevamente el escrutinio y cómputo, cuando:\na) Existan errores aritméticos en el acta de la jornada electoral, y estos sean determinantes para el resultado de la votación en la casilla.\nSerá determinante el error aritmético, cuando éste sea igual o mayor a la diferencia en casilla.\nb) Existan irregularidades o alteraciones evidentes, en el acta de la jornada electoral;\nc) El número de votos nulos sea mayor a la diferencia entre los votos que obtuvieron los candidatos que ocuparon el primero y segundo lugar, y\nd) Todos los votos hayan sido depositados a favor de un mismo partido político o\nCandidato Independiente.\nLey Electoral del Estado de Baja California. Página 91\n.\nActualización Legislativa.\nÚltima reforma P. O. No. 60, Índice, 03-Oct-2025\nV. Posteriormente, se abrirán los paquetes con muestras de alteración y se realizarán, según sea el caso, las operaciones señaladas en las fracciones anteriores, haciéndose constar lo procedente en el acta circunstanciada respectiva, y\nVI. La suma de los resultados, después de realizar las operaciones indicadas en las fracciones anteriores, constituirá el cómputo distrital de la elección de Diputaciones, Munícipes o Gubernatura, según se trate, y se asentará en el acta correspondiente.\nFracción Reformada\nEn caso del cómputo de la elección de diputaciones por el principio de representación proporcional, en los distritos donde se haya instalado una casilla especial, se procederá a añadir al resultado del cómputo de Diputaciones por el principio de mayoría relativa, el resultado que se tuviere en la casilla especial para aquélla elección; la sumatoria constituirá el cómputo distrital de la elección de diputaciones por el principio de representación proporcional. El acta para esta elección deberá contener los apartados para la sumatoria respectiva.\nPárrafo Reformado\nSe harán constar en el acta circunstanciada de la sesión, los resultados del cómputo de la elección de Diputaciones por el principio de mayoría relativa, Munícipes o Gubernatura, y en su caso la de diputaciones por el principio de representación proporcional, así como los incidentes que ocurrieren durante la misma.\nPárrafo Reformado\nArtículo Reformado\nArtículo 257.- El recuento total de votos procederá sólo si al término del cómputo a que se refiere el artículo anterior, se establece que la diferencia entre el candidato presuntamente ganador y el ubicado en segundo lugar es igual o menor a un punto porcentual, y existe la petición expresa del representante del partido o del Candidato\nIndependiente que postuló al segundo de los candidatos antes señalados, el Consejo\nDistrital deberá proceder a realizar el recuento de votos en la totalidad de las casillas. En todo caso, se excluirán del procedimiento anterior las casillas que ya hubiesen sido objeto de recuento.\nArtículo 258.- En los casos en que se ordene el recuento total de votos, el Presidente del Consejo Distrital dará aviso inmediato al Consejo General, ordenará la creación de hasta tres grupos de trabajo integrados por los consejeros electorales, los representantes de los partidos políticos y Candidatos Independientes, y los delegados del Instituto Estatal. Los los paquetes que cada uno tendrá bajo su responsabilidad. Los partidos políticos y\nCandidatos Independientes tendrán derecho a nombrar a un representante en cada grupo, con su respectivo suplente. distinta, se contabilizarán para la elección de que se trate.\nLey Electoral del Estado de Baja California. Página 92\n.\nActualización Legislativa.\nÚltima reforma P. O. No. 60, Índice, 03-Oct-2025\nEl consejero electoral que presida cada grupo levantará un acta circunstanciada en la que consignará el resultado del recuento de cada casilla y el resultado final que arroje la suma de votos por cada partido y candidato.\nEl presidente del Consejo Distrital realizará en sesión plenaria la suma de los resultados consignados en el acta de cada grupo de trabajo y asentará el resultado en el acta final de escrutinio y cómputo de la elección de que se trate.\nLos errores contenidos en las actas originales de escrutinio y cómputo de casilla que sean corregidos por los Consejos Distritales siguiendo el procedimiento establecido en este artículo, y en las fracciones II y III del artículo 256 de esta Ley, no podrán invocarse como causa de nulidad ante el Tribunal Electoral. En ningún caso podrá solicitarse a las autoridades judiciales que realice recuento de votos respecto de las casillas que hayan sido objeto de dicho procedimiento en los Consejos Distritales.\nArtículo 259.- Concluido el cómputo para la elección de diputados por el principio de mayoría relativa, se emitirá la declaración de validez y acto seguido, el Consejero Presidente del Consejo Distrital Electoral, expedirá la constancia de mayoría a quién hubiese obtenido el triunfo.\nEl Consejo Distrital Electoral, una vez concluidos los cómputos distritales de las elecciones de Munícipes, en su caso de Gobernador y de Diputados por el principio de representación proporcional, enviará copia de las actas de cómputo respectivas, al Consejo\nGeneral.\nArtículo 260.- Los consejeros presidentes de los consejos distritales electorales, fijarán en el exterior de los locales en que se ubiquen éstos últimos, al término del cómputo, los resultados de la elección de Diputados por el principio de mayoría relativa, Munícipes, Gobernador y de Diputados por el principio de representación proporcional, en el distrito.\nArtículo 261.- Los consejeros presidentes de los consejos distritales electorales, integrarán el expediente del cómputo distrital de la elección de diputados de mayoría relativa, con los siguientes documentos originales:\nI. Actas de las casillas;\nII. Acta del cómputo distrital;\nIII. Acta circunstanciada de la sesión de cómputo distrital;\nIV. Copia certificada de la constancia de mayoría y acuse de recibo correspondiente, y\nV. Informe sobre el desarrollo del proceso electoral.\nArtículo 262.- El Consejero Presidente del Consejo Distrital Electoral respectivo, integrará los expedientes del cómputo distrital de la elección de Munícipes, Gobernador y\nDiputados por el principio de representación proporcional, con los siguientes documentos:\nI. Actas de los cómputos distritales, y\nII. Actas circunstanciadas de las sesiones de cómputo.\nLey Electoral del Estado de Baja California. Página 93\n.\nActualización Legislativa.\nÚltima reforma P. O. No. 60, Índice, 03-Oct-2025\nArtículo 263.- Los consejos distritales electorales, una vez resueltos todos los medios de impugnación locales de la elección de Diputaciones de mayoría relativa, enviarán los expedientes correspondientes al Consejo General, para efectos de la asignación de diputaciones por el principio de representación proporcional.\nPárrafo Reformado\nLas y los Consejeros Presidentes de los Consejos Distritales Electorales, remitirán al\nCongreso del Estado copia certificada de las constancias de mayoría de la fórmula de candidatos a Diputaciones que la hubiesen obtenido.\nPárrafo Reformado\nArtículo Reformado\nArtículo 264.- Los consejeros presidentes de los consejos distritales correspondientes, conservarán en su poder una copia certificada de todas las actas y documentación de los expedientes de cómputo distrital y tomarán las medidas necesarias para el depósito en el lugar señalado para tal efecto, de los sobres que contengan la documentación a que se refiere el artículo 235 de esta Ley, hasta la conclusión del proceso electoral.\nCAPÍTULO CUARTO\nDe los Cómputos de las Elecciones en el Consejo General\nArtículo 265.- El cómputo para Munícipes, Gobernador y Diputados por el principio de representación proporcional, es el, procedimiento por el cual el Consejo General determina, mediante la suma de los resultados anotados en las actas de los cómputos distritales, la votación obtenida para cada una de esas elecciones.\nEl Consejo General celebrará sesión a más tardar quince días posteriores a la jornada electoral, para hacer el cómputo de las elecciones de Munícipes y Gobernador. El cómputo de la elección de diputados por el principio de representación proporcional deberá realizarse una vez resueltos todos los medios de impugnación locales de la elección de diputados de mayoría relativa.\nPárrafo Reformado\nArtículo Reformado\nArtículo 266.- Concluido el cómputo de las elecciones, el Consejo General procederá a:\nI. Emitir la declaración de validez de la elección de munícipes y extender la constancia de mayoría a la planilla que haya obtenido el mayor número de votos;\nII. Dictaminar y declarar la validez de la elección de Gobernador y extender la constancia de mayoría al candidato que haya obtenido mayor número de votos, y\nIII. Declarar la validez de la elección de diputados por el principio de representación proporcional y extender las constancias de asignación proporcional.\nLey Electoral del Estado de Baja California. Página 94\n.\nActualización Legislativa.\nÚltima reforma P. O. No. 60, Índice, 03-Oct-2025\nArtículo 267.- El Consejero Presidente del Consejo General, integrará para cada elección un expediente de cómputo de la elección de munícipes, de Gobernador y de diputados por el principio de representación proporcional, con los siguientes documentos originales o copias certificadas, según el caso:\nI. Las actas de las sesiones de cómputo;\nII. Las actas circunstanciadas de las sesiones de cómputo;\nIII. Las constancias de mayoría expedidas, y de las de asignación proporcional, y\nIV. Su informe sobre el desarrollo del proceso electoral.\nEl Consejo General, notificará al Congreso del Estado la expedición de las constancias de mayoría de las elecciones de munícipes y de Gobernador y de las constancias de asignación proporcional.\nArtículo 268.- El Consejero Presidente del Consejo General, fijará en el exterior del local, al término de la sesión de los cómputos, los resultados de cada una de las elecciones de munícipes, de Gobernador y de diputados por el principio de representación proporcional.\nArtículo 269.- Durante el mes de enero del año siguiente a la elección, la Secretaría\nEjecutiva del Instituto Estatal expondrá al público la documentación a que se refiere el artículo 264 de esta Ley, para proceder posteriormente a la elaboración de la estadística electoral y los estudios del proceso electoral.\nEl Consejo General, acordará la fecha y modo en que habrán de ser destruidos.\nCAPÍTULO QUINTO\nDe las Constancias de Asignación Proporcional\nArtículo 270.- En los términos de los artículos 15 y 79 de la Constitución del Estado, el Consejo General procederá a la asignación de diputados y munícipes electos por el principio de representación proporcional, conforme a lo dispuesto en esta Ley.\nEn caso de presentarse impugnaciones de las elecciones de diputados y munícipes de mayoría relativa, el Consejo General hará la asignación correspondiente, una vez resueltos todos los medios de impugnación locales de la respectiva elección.\nPárrafo Reformado\nArtículo Reformado\nArtículo 271.- El Consejero Presidente del Consejo General, expedirá a cada partido político las constancias de asignación por el principio de representación proporcional, de las que informará al Congreso del Estado.\nLIBRO QUINTO\nLey Electoral del Estado de Baja California. Página 95\n.\nActualización Legislativa.\nÚltima reforma P. O. No. 60, Índice, 03-Oct-2025\nTÍTULO PRIMERO\nDe las nulidades\nCAPÍTULO ÚNICO\nDisposiciones comunes\nArtículo 272.- La nulidad de los resultados obtenidos en las casillas electorales, decretada por el Tribunal Electoral, afectará los siguientes actos:\nI. Los resultados del cómputo de la elección impugnada;\nII. La elección en un Distrito Electoral para la fórmula de diputados de mayoría relativa;\nIII. La elección de diputados por el principio de representación proporcional;\nIV. La elección en un Municipio para Ayuntamiento, y\nV. La elección en el Estado para Gobernador.\nArtículo 273.- La votación recibida en una casilla será nula cuando se acredite alguno de los siguientes supuestos:\nI. Instalar la casilla en lugar distinto al señalado por la autoridad electoral correspondiente, y se ubique en una distancia mayor a cien metros, salvo cuando exista cualquiera de las causas justificadas que se establecen en esta Ley;\nII. Recibir la votación en día y hora distintas a las señaladas por esta Ley;\nIII. Recibir la votación por personas u órganos distintos a los facultados por esta\nLey;\nIV. Permitir sufragar a quien no presente su credencial para votar o no aparezca en el Listado Nominal de Electores con fotografía, siempre que ello sea determinante para el resultado de la votación, salvo los casos señalados por esta Ley;\nV. Utilizar para la recepción del voto un Listado Nominal de Electores con fotografía que contenga datos distintos, a aquel que hubiere proporcionado el Instituto\nNacional, siempre que ello sea determinante para el resultado de la votación;\nVI. Impedir el ejercicio del voto a los ciudadanos sin causa justificada, y que esto sea determinante para el resultado de la votación;\nVII. Impedir el acceso a los representantes de los partidos políticos o haberlos expulsado, sin causa justificada, siempre que ello sea determinante para el resultado de la votación;\nVIII. Realizar, sin causa justificada, el escrutinio y cómputo en local diferente al determinado por el Consejo respectivo;\nLey Electoral del Estado de Baja California. Página 96\n.\nActualización Legislativa.\nÚltima reforma P. O. No. 60, Índice, 03-Oct-2025\nIX. Haber mediado dolo o error en la computación de los votos siempre que ello sea determinante para el resultado de la votación, y no haya sido corregido en la sesión de cómputo correspondiente;\nX. Entregar, sin causa justificada, el paquete que contenga los expedientes electorales al Consejo Distrital Electoral, fuera de los plazos señalados en esta Ley;\nXI. Ejercer violencia física o presión sobre los miembros de la Mesa Directiva de\nCasilla o sobre los electores y siempre que esos hechos sean determinantes para el resultado de la votación, y\nXII. Existir irregularidades graves, sustanciales, de forma generalizada, plenamente acreditadas y no reparables durante la jornada electoral o en las actas de escrutinio y cómputo, que en forma evidente pongan en duda la certeza de la votación y estas sean determinantes para el resultado de la misma.\nArtículo 274.- Procede la nulidad de la elección de diputados por el principio de mayoría relativa en un distrito electoral, cuando:\nI. Alguna o algunas de las causas señaladas en el artículo anterior se acrediten en por lo menos el veinte por ciento de las casillas instaladas en el distrito;\nII. No se instale el veinte por ciento de las casillas en el distrito, y\nIII. Por causas supervenientes, los dos integrantes de la fórmula de diputados electos dejen de reunir los requisitos para ocupar el cargo.\nArtículo 275.- Procede la nulidad en la elección de munícipes, en los siguientes supuestos:\nI. Cuando alguna o algunas de las causas señaladas en el artículo 273 de esta\nLey, se acrediten en por lo menos el veinte por ciento de las casillas en el Municipio;\nII. Cuando no se instalen el veinte por ciento de las casillas en el Municipio, y\nIII. Cuando por causas supervenientes la mitad más uno de los munícipes electos, dejen de reunir los requisitos para ocupar los diferentes cargos.\nArtículo 276.- Procede la nulidad en la elección de Gobernador, en los siguientes supuestos:\nI. Cuando alguna o algunas de las causas señaladas en el artículo 273 de esta\nLey, se acrediten en por lo menos el veinte por ciento de las casillas correspondientes a cada uno de los municipios en la Entidad;\nII. Cuando no se instalen el veinte por ciento de las casillas correspondientes a cada uno de los municipios de la entidad, y\nIII. Cuando por causas supervenientes el Gobernador electo deje de reunir los requisitos para ocupar el cargo.\nArtículo 277.- Además de las causales de nulidad para las elecciones de diputados por el principio de mayoría relativa, munícipes y Gobernador previstas en los artículos\nLey Electoral del Estado de Baja California. Página 97\n.\nActualización Legislativa.\nÚltima reforma P. O. No. 60, Índice, 03-Oct-2025 anteriores, respectivamente, las elecciones locales serán nulas por violaciones graves, dolosas y determinantes en los casos previstos en la Base VI del artículo 41 de la\nPara los efectos del párrafo anterior, se estará a lo dispuesto en el artículo 78 Bis de la Ley General del Sistema de Medios de Impugnación en Materia Electoral.\nArtículo 278.- En caso de que a un partido político o coalición se le asignen diputados o regidores de representación proporcional y éstos no reúnan los requisitos para ocupar el cargo, los suplentes, según sea el caso, tomarán su lugar.\nArtículo 279.- Los efectos de las nulidades decretadas por el Tribunal Electoral, respecto de la votación emitida en una casilla o de una elección en un distrito electoral o\nMunicipio, se contraen exclusivamente a la votación o elección para la que expresamente se haya hecho valer el recurso correspondiente.\nArtículo 280.- Los partidos políticos o coaliciones, no podrán invocar en su favor, medio de impugnación alguno, causales de nulidad, hechos o circunstancias que ellos mismos, sus candidatos o militantes hayan provocado.\nTÍTULO SEGUNDO\nDel sistema de medios de impugnación\nCAPÍTULO PRIMERO\nDisposiciones preliminares\nArtículo 281.- El sistema de medios de impugnación regulado por esta Ley tiene por objeto garantizar:\nI. Que los actos y resoluciones de las autoridades electorales se sujeten al principio de legalidad.\nFracción Reformada\nII. La definitividad de los distintos actos y etapas de los procesos electorales.\nFracción Reformada\nIII. La protección de los derechos político-electorales del ciudadano, como lo son el derecho a votar y ser votado para todos los cargos de elección popular, así como la\nAsociación libre y pacífica para tomar parte en los asuntos políticos, afiliación libre e individual a los partidos políticos.\nFracción Adicionada impugnadas.\nArtículo Reformado\nLey Electoral del Estado de Baja California. Página 98\n.\nActualización Legislativa.\nÚltima reforma P. O. No. 60, Índice, 03-Oct-2025\nArtículo 282.- El sistema de medios de impugnación se integra por:\nI. El recurso de inconformidad;\nII. El recurso de apelación;\nFracción Reformada\nIII. El recurso de revisión; y,\nFracción Reformada\nIV. El Juicio para la protección de los derechos político-electorales del ciudadano.\nFracción Adicionada\nCompete al Pleno del Tribunal Electoral conocer y resolver los medios de impugnación previstos en las fracciones anteriores, en la forma y términos establecidos por esta Ley.\nArtículo Reformado\nCAPÍTULO SEGUNDO\nDe los recursos\nArtículo 283.- El recurso de inconformidad se podrá hacer valer, por:\nI. Los partidos políticos, por conducto de sus representantes legítimos, para impugnar los actos o resoluciones de los órganos electorales, que no tengan el carácter de irrevocables o bien, que no proceda otro recurso señalado en esta Ley;\nII. Los Candidato Independiente, cuando se consideren afectados por los actos o resoluciones de los órganos electorales, y\nIII. Las personas o entidades que se consideren afectados por la resolución emitida en los procedimientos de responsabilidad que establece esta Ley.\nIV. Los partidos políticos, por conducto de sus dirigentes o candidatos, en contra de actos relativos al proceso de liquidación.\nFracción Adicionada\nArtículo Reformado\nArtículo 284.- El recurso de apelación se podrá hacer valer por:\nI. Derogado;\nFracción Derogada\nII. Los Aspirante a Candidato Independiente, cuando se consideren afectados por reglamenta las candidaturas independientes en el Estado.\nIII. Por los militantes de los partidos políticos estatales para impugnar los actos o resoluciones de éstos, con relación a los asuntos internos a que se refieren la Ley de\nPartidos Políticos del Estado, y\nLey Electoral del Estado de Baja California. Página 99\n.\nActualización Legislativa.\nÚltima reforma P. O. No. 60, Índice, 03-Oct-2025\nIV. Derogado.\nFracción Derogada\nArtículo Reformado\nArtículo 285.- Los partidos políticos y las coaliciones, por conducto de sus representantes legítimos, o los candidatos por sí, podrán interponer el recurso de revisión para impugnar:\nI. El Cómputo del Consejo Distrital Electoral de la elección de diputados, por nulidad de la votación recibida en una o varias casillas;\nII. El cómputo del Consejo General de las elecciones de munícipes o Gobernador, por nulidad de la votación recibida en una o varias casillas;\nIII. El cómputo, por error aritmético, en los Consejos respectivos, de la elección de diputados por el principio de mayoría relativa o de representación proporcional, munícipes y\nGobernador;\nIV. La declaración de validez y el otorgamiento de la constancia de mayoría, por nulidad de la elección de diputados, munícipes o Gobernador, por los supuestos previstos en esta Ley;\nV. La declaración de validez de la elección de diputados y el otorgamiento de la constancia de mayoría efectuado por el Consejo Distrital Electoral correspondiente;\nVI. La declaración de validez de la elección de munícipes y el otorgamiento de las constancias de mayoría que realice el Consejo General;\nVII. La declaración de validez de la elección de Gobernador y el otorgamiento de la constancia de mayoría, que realice el Consejo General;\nVIII. La constancia de asignación de diputados por el principio de representación proporcional y la declaración de validez de esta elección, que realice el Consejo General; y\nIX. La asignación de munícipes por el principio de representación proporcional, que efectúe el Consejo General.\nLos candidatos independientes por sí o a través de sus representantes legítimos, podrán promover el recurso de revisión, salvo lo estipulado en las fracciones VIII que anteceden o las relacionadas con la representación proporcional de diputados.\nPárrafo Reformado\nArtículo Reformado\nArtículo 286.- El escrito de protesta es un medio para establecer la existencia de presuntas violaciones durante el día de la jornada electoral, cuando se hagan valer las causales de nulidad previstas en el artículo 273 de esta Ley.\nNo se requerirá de la presentación del escrito de protesta, como requisito de procedibilidad del recurso de revisión. Podrá presentarse ante el Consejo Distrital que corresponda antes de que inicien las sesiones de cómputo a que se refiere esta Ley, debiendo contener:\nLey Electoral del Estado de Baja California. Página 100\n.\nActualización Legislativa.\nÚltima reforma P. O. No. 60, Índice, 03-Oct-2025\nI. El candidato independiente, el partido político o coalición que lo presenta;\nII. La elección que se protesta;\nIII. La causa por la que se presenta la protesta;\nIV. La identificación individual de la casilla o casillas que se impugnan, y\nV. El nombre, firma y cargo partidario, cuando proceda, de quien lo presenta.\nArtículo 287.- Las elecciones cuyos cómputos, declaraciones de validez y otorgamiento de constancias de mayoría o de asignación que no sean impugnadas en tiempo y forma, causarán estado.\nTÍTULO TERCERO\nDel procedimiento\nCAPÍTULO PRIMERO\nDisposiciones preliminares\nArtículo 288.- Los medios de impugnación deberán presentarse por escrito ante la autoridad responsable que realizó el acto o resolución que se recurre, el cual deberá contener los siguientes requisitos:\nI. El nombre del recurrente y el domicilio para recibir notificaciones y, en su caso, a quien en su nombre se puede imponer;\nII. Identificar el acto o resolución impugnado y la autoridad electoral responsable;\nIII. Mencionar de manera expresa y clara los hechos en que se basa la impugnación y los agravios que cause el acto o resolución impugnada;\nIV. Ofrecer y relacionar las pruebas;\nV. Los puntos petitorios, y\nVI. El nombre y la firma del promovente.\nAdemás, deberá anexar a la promoción los documentos con los que acredite la personería y aportar los medios probatorios que obren en su poder, en caso contrario, agregará el escrito en el que conste la solicitud hecha al órgano competente.\nCuando el o los agravios versen exclusivamente sobre puntos de derecho, no será necesario aportar pruebas.\nArtículo 288 BIS.- El Juicio para la protección de los derechos político-electorales del ciudadano, se podrá hacer valer por: legales, haciendo valer presuntas violaciones a sus derechos de votar y ser votado en las\nLey Electoral del Estado de Baja California. Página 101\n.\nActualización Legislativa.\nÚltima reforma P. O. No. 60, Índice, 03-Oct-2025 elecciones populares, de asociarse individual y libremente para tomar parte en forma pacífica en los asuntos políticos y de afiliarse libre e individualmente a los partidos políticos.\nII. En el supuesto de haberse asociado con otros ciudadanos para tomar parte en forma pacífica en asuntos políticos, conforme a leyes aplicables, que consideren que se les negó indebidamente su registro como partido político, la demanda deberá presentarse por conducto de quien ostente la representación legítima de la asociación agraviada.\nIII. Asimismo, resultará procedente para impugnar los actos y resoluciones por quien, teniendo interés jurídico, considere que indebidamente se afecta su derecho por parte de los órganos y autoridades electorales en el Estado.\nEl juicio podrá ser promovido por la ciudadana o el ciudadano cuando: a. Considere que se violó su derecho político-electoral de ser votado cuando, habiendo sido propuesto por un partido político, le sea negado indebidamente su registro como candidato a un cargo de elección popular; b. Habiéndose asociado con otros ciudadanos para tomar parte en forma pacífica en asuntos políticos, conforme a las leyes aplicables, consideren que se les negó indebidamente su registro como partido político; c. Considere que un acto o resolución de la autoridad es violatorio de cualquier otro de los derechos político-electorales a que se refiere el presente artículo; d. Considere que los actos o resoluciones del partido político al que está afiliado violan alguno de sus derechos político-electorales. Lo anterior es aplicable a las personas precandidatas y candidatas a cargos de elección popular aun cuando no estén afiliadas al partido señalado como responsable; y, e. Considere que se actualiza algún supuesto de violencia política contra las mujeres en razón de género, en los términos establecidos en la Ley que lo regula.\nEl juicio sólo será procedente cuando el actor haya agotado todas las instancias político–electoral presuntamente violado, en la forma y en los plazos que las leyes respectivas establezcan para tal efecto.\nEn los casos previstos en el inciso d) del párrafo segundo de este artículo, el quejoso normas internas del partido de que se trate, salvo que los órganos partidistas competentes no estuvieren integrados e instalados con antelación a los hechos litigiosos, o dichos órganos incurran en violaciones graves de procedimiento que dejen sin defensa al quejoso.\nArtículo Adicionado\nLey Electoral del Estado de Baja California. Página 102\n.\nActualización Legislativa.\nÚltima reforma P. O. No. 60, Índice, 03-Oct-2025\nArtículo 289.- La autoridad que reciba un medio de impugnación, en contra de un acto emitido o resolución dictada por ella, bajo su más estricta responsabilidad, deberá:\nI. Por la vía más expedita, remitir copia del mismo junto con su anexo y dar aviso de su presentación al Tribunal Electoral, precisando: actor, acto o resolución impugnado, fecha y hora exactas de su recepción, y\nFracción Reformada\nII. Dentro de las tres horas posteriores a la recepción del escrito, hacerlo del conocimiento público mediante cédula que fijarán en los estrados durante un plazo de setenta y dos horas.\nCuando algún órgano del Instituto reciba un medio de impugnación por el cual se pretenda combatir un acto o resolución que no le es propio, lo remitirá de inmediato, sin trámite adicional alguno, al órgano del Instituto Estatal competente para tramitarlo. La presentación de un medio de impugnación ante autoridad distinta a la responsable no interrumpe el plazo previsto en el artículo 295 de esta ley.\nEl incumplimiento de las obligaciones a que se refieren los párrafos anteriores, será sancionado en términos de esta Ley y de las que resulten aplicables.\nArtículo Reformado\nArtículo 290.- Dentro del plazo de publicidad a que se refiere la fracción II del artículo anterior, los terceros interesados podrán comparecer mediante los escritos que consideren pertinentes, mismos que deberán cumplir los requisitos siguientes:\nI. Presentarse ante la autoridad responsable del acto o resolución impugnado;\nII. Hacer constar el nombre del tercero interesado;\nIII. Señalar domicilio para oír notificaciones;\nIV. Exhibir los documentos que acrediten la personería del compareciente, cuando no la tenga reconocida ante la autoridad responsable;\nV. Precisar la razón del interés jurídico y las pretensiones concretas del compareciente;\nVI. Ofrecer las pruebas que junto con el escrito se aporten y solicitar las que deban requerirse, cuando el compareciente justifique que habiéndolas solicitado por escrito oportunamente, no le fueron entregadas, y\nVII. La firma autógrafa del compareciente.\nArtículo 291.- Vencido el plazo de publicidad referido en la fracción II del artículo 289, Electoral, dentro de las veinticuatro horas siguientes, adjuntando:\nI. El escrito original mediante el cual se interpuso, y la demás documentación que se haya acompañado;\nLey Electoral del Estado de Baja California. Página 103\n.\nActualización Legislativa.\nÚltima reforma P. O. No. 60, Índice, 03-Oct-2025\nII. La copia certificada del documento en que conste el acto o resolución impugnada, y las demás que se relacionen;\nIII. Las pruebas aportadas;\nIV. Los escritos de los terceros interesados que se hayan presentado;\nV. Informe circunstanciado sobre el acto o resolución impugnado, que será rendido por la autoridad electoral señalada como responsable, el cual deberá contener:\na) En su caso, la mención de si el promovente o el compareciente, tienen reconocida su personería;\nb) La veracidad del acto, omisión o resolución impugnados;\nc) La existencia de causas de improcedencia;\nd) Los motivos y fundamentos jurídicos que se consideren pertinentes, para sostener la legalidad del acto o resolución impugnado, y\ne) Firma del funcionario legitimado que lo rinde;\nVI. En el caso del recurso de revisión, el expediente completo con todas las actas y las hojas de incidentes levantadas por la autoridad correspondiente y de los escritos de incidentes que se hubieren presentado, y\nVII. Los demás elementos que se estimen necesarios para la sustanciación y resolución del recurso.\nArtículo 292.- En el caso del recurso de revisión, además de los requisitos establecidos en el artículo 288 de esta Ley, deberán señalarse los siguientes:\nI. La elección que se impugna, precisando si se objeta el cómputo de la elección, la declaración de validez y consecuentemente, el otorgamiento de las constancias respectivas;\nII. La mención individualizada del acta de cómputo y, en su caso, la asignación que se impugna;\nIII. La mención individualizada de las casillas cuya votación se solicita que se anule en cada caso y la causal que se invoca, así como la narrativa expresa de los hechos y agravios para cada una de ella.\nFracción Reformada\nIV. En su caso, si se solicita recuento total o parcial de votos.\nArtículo Reformado\nArtículo 293.- El recuento total o parcial de votos se substanciará incidentalmente, y sólo procederá cuando el nuevo escrutinio y cómputo solicitado no haya sido desahogado, sin causa justificada, en la sesión de cómputo correspondiente, en términos de lo dispuesto por el artículo 258 de esta Ley.\nLey Electoral del Estado de Baja California. Página 104\n.\nActualización Legislativa.\nÚltima reforma P. O. No. 60, Índice, 03-Oct-2025\nEl Pleno del Tribunal Electoral deberá establecer previamente si las inconsistencias pueden ser corregidas o subsanadas con algunos otros datos o elementos que obren en el expediente o puedan ser requeridos por el propio Tribunal sin necesidad de recontar los votos. De resolver la procedencia del recuento total o parcial de votos, el Tribunal determinará si lo lleva a cabo por sí mismo, o en su caso, ordena a los Consejos Distritales respectivos su realización.\nNo procederá el incidente señalado en este artículo, en el caso de casillas en las que se hubiere realizado nuevo escrutinio y cómputo en la sesión de cómputo respectiva.\nCAPÍTULO SEGUNDO\nDe los plazos\nArtículo 294.- Durante el proceso electoral todos los días y horas son hábiles. Los plazos se computarán de momento a momento; si están señalados por días éstos se considerarán de veinticuatro horas.\nEl cómputo de los plazos se hará a partir del día siguiente de aquel en que se hubiere notificado el acto o la resolución correspondiente.\nCuando el acto reclamado se produzca durante el tiempo que transcurra entre dos procesos electorales, el cómputo de los plazos se hará contando solo los días hábiles, debiendo entenderse por tales todos los días a excepción de los sábados, domingos y los días inhábiles, en términos de Ley.\nArtículo 295.- Los recursos deberán interponerse dentro de los cinco días siguientes al que se tenga conocimiento o se hubiese notificado el acto o la resolución que se impugna.\nCAPÍTULO TERCERO\nDe las partes\nArtículo 296.- Son partes en el procedimiento de los medios de impugnación, las siguientes:\nI. El actor o recurrente, que será quien estando legitimado presente el recurso por sí mismo, o en su caso, a través de representante en los términos de este ordenamiento;\nII. La autoridad responsable, que será el órgano que se señale como responsable del acto o la resolución impugnada.\n284 de esta Ley, los partidos políticos serán considerados, autoridad responsable, y\nIII. El tercero interesado, que será quien tenga un interés legítimo en la causa, derivado de un derecho incompatible con el que pretende el actor o recurrente.\nCAPÍTULO CUARTO\nLey Electoral del Estado de Baja California. Página 105\n.\nActualización Legislativa.\nÚltima reforma P. O. No. 60, Índice, 03-Oct-2025\nDe la legitimación y personería\nArtículo 297.- Están legitimados para interponer los recursos que prevé esta Ley:\nI. Los ciudadanos, militantes, y las entidades a que se refieren los artículos 283 y\n284 de esta Ley;\nII. Los partidos políticos, a través de sus representantes legítimos;\nIII. Las asociaciones políticas, a través de quien se ostente como su representante al momento de presentar la solicitud de registro, y\nIV. Los candidatos independientes, por sí o a través de sus representantes legítimos, entendiéndose por éstos a los que se encuentren acreditados ante el Instituto\nEstatal.\nArtículo 298.- Es representante legítimo del partido político estatal o nacional, o de la coalición:\nI. El Presidente o Secretario General del órgano directivo estatal o municipal, o sus equivalentes; cuando se trate de coalición, los señalados en el convenio respectivo. En estos casos deberán acreditar su personalidad en los términos previstos en esta Ley;\nII. Los representantes propietario y suplente acreditados ante el Consejo General o\nConsejo Distrital que corresponda. Sólo podrán actuar en los asuntos de la competencia del órgano en el cual estén acreditados, y\nIII. Las personas autorizadas para representarlo ante cualquier autoridad administrativa o jurisdiccional electoral, mediante poder otorgado en escritura pública.\nCAPÍTULO QUINTO\nDe la Improcedencia y Sobreseimiento\nArtículo 299.- Serán improcedentes los recursos previstos en esta Ley, cuando:\nI. El escrito recursal no esté firmado autógrafamente por quien lo promueva;\nII. Sean interpuestos por quién no tenga personería, legitimación o interés jurídico en los términos de esta Ley;\nIII. Hayan transcurrido los plazos que señala esta Ley, para su interposición;\nIV. No ofrezca ni aporte pruebas en los plazos señalados en esta Ley, salvo que se señalen las razones justificadas por las que no obren en poder del promovente;\nV. Se impugnen actos o resoluciones respecto de las cuales hubiere consentimiento expreso o tácito; entendiéndose éste último cuando no se haya promovido medio de defensa en los términos de esta Ley;\nLey Electoral del Estado de Baja California. Página 106\n.\nActualización Legislativa.\nÚltima reforma P. O. No. 60, Índice, 03-Oct-2025\nVI. Se pretenda impugnar actos o resoluciones que se hayan consumado de un modo irreparable;\nVII. No se expresen agravios o los que se expongan no tengan relación directa con el acto o resolución que se impugne;\nVIII. No se hayan agotado previamente las instancias internas del partido político de que se trate, en caso del recurso de apelación;\nFracción Reformada\nIX. No reúnan los requisitos que señala esta Ley para que proceda el recurso de revisión, y\nFracción Reformada\nX. Resulten evidentemente frívolos.\nFracción Adicionada\nArtículo Reformado\nArtículo 300.- Procede el sobreseimiento de los recursos, cuando:\nI. El actor o recurrente se desista expresamente por escrito;\nII. De las constancias que obren en autos, apareciera claramente demostrado que no existe el acto o resolución impugnada;\nIII. Desaparecieran las causas que motivaron la interposición del recurso;\nIV. Durante el procedimiento sobrevenga una de las causas de improcedencia previstas en el artículo anterior;\nV. Durante la sustanciación de un recurso de inconformidad o apelación, el ciudadano recurrente fallezca o sea suspendido o privado de sus derechos político electorales, y\nVI. La autoridad responsable modifique o revoque el acto o la resolución impugnada, de tal manera que quede sin materia el recurso.\nEl sobreseimiento no prejuzga sobre la responsabilidad en que haya incurrido la autoridad electoral al ordenar o ejecutar el acto o resolución impugnada.\nCAPÍTULO SEXTO\nDe la acumulación\nArtículo 301.- Para la resolución pronta y expedita de los recursos previstos en esta\nLey, se podrá decretar su acumulación.\nPodrán acumularse al inicio, durante la substanciación o para resolución de los recursos, aquellos expedientes en que se impugnen simultáneamente, por dos o más partidos políticos o coaliciones, el mismo acto o resolución o actos o resoluciones conexas.\nCAPÍTULO SÉPTIMO\nLey Electoral del Estado de Baja California. Página 107\n.\nActualización Legislativa.\nÚltima reforma P. O. No. 60, Índice, 03-Oct-2025\nDe las notificaciones\nArtículo 302.- Las notificaciones se podrán hacer:\nI. Personalmente;\nII. Por estrados;\nIII. Por oficio;\nIV. Por correo certificado o por telegrama con acuse de recibo;\nV. A través del Periódico Oficial del Estado, diarios o periódicos de mayor circulación estatal o regional, en los términos de esta Ley, y\nVI. Por medio electrónico.\nSerán notificaciones personales las que establezca esta Ley.\nEn caso de que el promovente o compareciente omita señalar domicilio, el señalado no resulte cierto o se ubique fuera del municipio sede del Tribunal Electoral, las notificaciones se harán por estrados.\nLos estrados son los lugares destinados en las oficinas de los órganos electorales y del Tribunal Electoral para que sean colocados para su notificación, cédulas, copia del escrito de interposición del recurso y de los autos y resoluciones que le recaigan para su notificación y publicidad.\nArtículo 303.- Las notificaciones personales se harán al interesado a más tardar al día siguiente de que se dictó el acto, resolución o sentencia. Las demás notificaciones se harán a más tardar tres días después de que se dictó el acto, resolución o sentencia.\nArtículo 304.- Las cédulas de notificación personal, deberán contener:\nI. La descripción del acto o resolución que se notifica;\nII. Lugar, hora y fecha en que se realice;\nIII. Nombre de la persona a quién se notifica, y\nIV. Firma del Actuario o Notificador.\nAl notificar personalmente, se levantará el acta correspondiente haciendo constar el nombre de la persona con la que se entienda la diligencia, quien deberá firmar de recibida la cédula y en caso de que ésta se niegue a hacerlo, se hará constar ésta circunstancia.\nArtículo 305.- Si no estuviera presente el interesado en su domicilio, se le dejará citatorio para hora fija del día siguiente. En caso de que no espere, se le hará notificación por cédula con la persona que se encuentre en el domicilio. Si éste se encuentra cerrado o la persona con la que se entiende la diligencia se niegue a recibir la cédula, el Actuario o\nNotificador la fijará junto con la copia del auto o resolución, en un lugar visible del domicilio, después de que se haya cerciorado de que ahí tiene su domicilio, asentando razón en autos.\nArtículo 306.- La notificación por correo electrónico procederá en los casos en que exista manifestación expresa de las partes para ello, quienes deberán proporcionar dirección\nLey Electoral del Estado de Baja California. Página 108\n.\nActualización Legislativa.\nÚltima reforma P. O. No. 60, Índice, 03-Oct-2025 de correo electrónico que cuente con mecanismos de confirmación de los envíos de las notificaciones. Notificación que surtirá efectos a partir de que se tenga constancia de la recepción de la misma o, en su caso, se cuente con el acuse de recibo correspondiente.\nArtículo 307.- Las sentencias del Tribunal Electoral, recaídas a los recursos de inconformidad y apelación, se notificará de la siguiente manera:\nI. Personalmente, a quién haya interpuesto el recurso, siempre y cuando haya señalado domicilio en la sede del Tribunal Electoral, y\nII. Por oficio, correo certificado o telegrama a la autoridad responsable y a los terceros interesados.\nEn todos los casos, el Tribunal Electoral, deberá adjuntar a la notificación copia de la resolución respectiva.\nArtículo 308.- La sentencia que recaiga al recurso de revisión, será notificada de la siguiente manera:\nI. Al candidato independiente, partido político o la coalición que interpuso el recurso y a los terceros interesados, personalmente, siempre y cuando hayan señalado domicilio ubicado en la ciudad sede del Tribunal Electoral; en caso contrario por estrados;\nII. Al Consejo General y consejos distritales respectivos, la notificación se hará por oficio, acompañando copia certificada de la sentencia, y\nIII. En su caso, al Congreso del Estado, en los términos de la fracción anterior.\nArtículo 308 BIS.- Las sentencias recaídas a los juicios para la protección de los derechos político–electorales de los ciudadanos serán notificadas:\na) Al actor que promovió el juicio, y en su caso, a los terceros interesados, a más tardar dentro de los dos días siguientes al en que se dictó la sentencia, personalmente siempre y cuando haya señalado domicilio ubicado en la ciudad sede de la Sala competente.\nEn cualquier otro caso, la notificación se hará por correo certificado, por telegrama o por estrados; y,\nb) A la autoridad u órgano partidista responsable, a más tardar dentro de los dos días siguientes al en que se dictó la sentencia, por oficio acompañado de la copia certificada de la sentencia.\nArtículo Adicionado\nArtículo 309.- Durante el proceso electoral, el Tribunal Electoral podrá notificar sus actos, resoluciones o sentencias a cualquier día y hora.\nArtículo 310.- No requerirán de notificación personal y surtirán sus efectos al día siguiente de su publicación o fijación, los actos o resoluciones que se hagan públicos a estatal o regional, o mediante la fijación de cédulas en los estrados de los órganos\nLey Electoral del Estado de Baja California. Página 109\n.\nActualización Legislativa.\nÚltima reforma P. O. No. 60, Índice, 03-Oct-2025 electorales y del Tribunal Electoral, en los términos de esta Ley, excepto los casos que esta misma señale como notificaciones personales.\nCAPÍTULO OCTAVO\nDe las pruebas, ofrecimiento y valoración\nArtículo 311.- Son medios probatorios en el proceso jurisdiccional electoral, los siguientes:\nI. Documentales públicas;\nII. Documentales privadas;\nIII. Técnicas;\nIV. Periciales;\nV. Reconocimiento o inspección judicial;\nVI. Presuncionales, y\nVII. Instrumental de actuaciones.\nArtículo 312.- Son pruebas documentales públicas:\nI. Las actas oficiales de las Mesas Directivas de Casilla, así como las de los cómputos de los Consejos Electorales y las actas levantadas con motivo de las sesiones que éstos celebren dentro del ámbito de su competencia. Serán actas oficiales, las originales autógrafas o las copias certificadas que deben constar en los expedientes de cada elección;\nII. Los demás documentos originales expedidos por los órganos del Instituto\nEstatal o funcionarios electorales, dentro del ámbito de su competencia;\nIII. Los documentos expedidos, dentro del ámbito de su competencia, por las autoridades federales, estatales y municipales, y\nIV. Los documentos expedidos, por quienes estén investidos de fe pública de acuerdo con la Ley, siempre y cuando en ellos se consignen hechos que les consten.\nArtículo 313.- Son pruebas documentales privadas, todos aquellos escritos, documentos e instrumentos, que aporten las partes, siempre que resulten pertinentes y relacionados con sus pretensiones.\nArtículo 314.- Son pruebas técnicas, las fotografías u otros medios de reproducción de imágenes que puedan ser desahogados sin necesidad de peritos, instrumentos o objeto crear convicción en el juzgador acerca de los hechos controvertidos. En estos casos, el aportante deberá señalar concretamente lo que pretende acreditar, identificando a las personas, los lugares y las circunstancias de modo y tiempo que reproduce la prueba.\nLey Electoral del Estado de Baja California. Página 110\n.\nActualización Legislativa.\nÚltima reforma P. O. No. 60, Índice, 03-Oct-2025\nArtículo 315.- Son pruebas periciales, los dictámenes u opiniones de persona titulada o práctica versada en cierta profesión, arte u oficio, sobre algún hecho u objeto que requiera conocimientos especiales, y que le aporta elementos al órgano jurisdiccional electoral para que resuelva.\nLa pericial sólo podrá ser ofrecida y admitida en aquellos recursos no vinculados al proceso electoral y a sus resultados, siempre y cuando su desahogo sea posible en los plazos establecidos.\nPara su ofrecimiento deberán cumplirse los siguientes requisitos:\nI. Ser ofrecida junto con el escrito de impugnación;\nII. Señalar la materia sobre la que versará la prueba, exhibiendo el cuestionario con copia para cada una de las partes;\nIII. Especificarse lo que pretenda acreditarse con la misma, y\nIV. Señalar el nombre del perito que se proponga y exhibir su acreditación técnica.\nArtículo 316.- Son pruebas de reconocimiento o inspección judicial, todo aquel examen que practica el órgano jurisdiccional electoral sobre lugares u objetos relacionados con el recurso.\nEl reconocimiento o inspección podrá practicarse a petición de parte o por disposición del órgano jurisdiccional electoral, mediante la oportuna citación a las partes para que si lo desean, puedan concurrir a la diligencia. Sólo procederá su desahogo, cuando la violación reclamada lo amerite, los plazos lo permitan y se estime determinante para que se pueda modificar, revocar o anular el acto o resolución impugnada.\nArtículo 317.- Son pruebas presuncionales, las consecuencias que la Ley o el\nTribunal Electoral deduzcan de un hecho conocido para averiguar la verdad de otro desconocido.\nEs presunción legal, cuando la Ley la establece expresamente.\nEs presunción humana, cuando de un hecho debidamente probado, se deduce otro que es consecuencia de aquél.\nArtículo 318.- La prueba instrumental de actuaciones, la constituyen todas las constancias que el órgano jurisdiccional electoral hubiere integrado en el expediente, en base al recurso que se haya interpuesto.\nArtículo 319.- Son objeto de prueba los hechos controvertidos. No lo será el derecho, los hechos notorios, ni aquellos que hayan sido reconocidos.\nArtículo 320.- El que afirma está obligado a probar. También lo está el que niega, cuando su negación envuelve la afirmación expresa de un hecho.\nArtículo 321.- El promovente aportará con su escrito inicial o dentro del plazo para la interposición de los recursos, las pruebas que obren en su poder.\nLey Electoral del Estado de Baja California. Página 111\n.\nActualización Legislativa.\nÚltima reforma P. O. No. 60, Índice, 03-Oct-2025\nEn ningún caso se tomarán en cuenta para resolver, las pruebas ofrecidas o aportadas fuera de los plazos. La única excepción será la de las pruebas supervenientes, siempre y cuando se aporten antes del cierre de la instrucción.\nSerán pruebas supervenientes, los medios de convicción surgidos después del plazo en que deban aportarse los elementos probatorios, y aquellos existentes desde entonces, pero que el promovente o el órgano electoral no pudieron ofrecer o aportar por desconocerlos o por existir obstáculos que no estaban a su alcance superar.\nArtículo 322.- Las pruebas admitidas serán valoradas, atendiendo a las reglas de la lógica, de la sana crítica y de la experiencia, y tomando en cuenta las reglas especiales señaladas en este Capítulo.\nArtículo 323.- Las documentales públicas tendrán valor probatorio pleno, salvo prueba en contrario, respecto de su autenticidad o de la veracidad de los hechos a que se refieran.\nLos demás medios probatorios, sólo harán prueba plena cuando a juicio del Tribunal\nElectoral, los elementos que obran en el expediente, los hechos afirmados, la verdad conocida y el recto raciocinio de la relación que guardan entre sí, generen convicción sobre la veracidad de los hechos afirmados.\nCAPÍTULO NOVENO\nDe la substanciación\nArtículo 324.- Cuando en el escrito de interposición del recurso, se omita señalar el requisito previsto en la fracción II del artículo 288 de esta Ley, el Magistrado del Tribunal\nElectoral que conozca del recurso, requerirá por medio de estrados al promovente para que lo cumpla en un plazo de cuarenta y ocho horas, contadas a partir de que se fije en los estrados el requerimiento, bajo el apercibimiento que de no hacerlo se tendrá por no interpuesto el recurso.\nArtículo 325.- Cuando el recurrente omita señalar en su escrito, los preceptos legales presuntamente violados o los cite de manera equivocada, el Tribunal Electoral podrá invocados o los que resulten aplicables al caso concreto.\nArtículo 326.- Cuando exista deficiencia en la argumentación de los agravios, pero éstos puedan ser deducidos claramente de los hechos expuestos en el recurso, el Tribunal\nElectoral no lo desechará y lo resolverá con los elementos que obren en el expediente.\nArtículo 327.- La substanciación de los recursos se sujetará a lo siguiente:\nI. Una vez recibido por el Tribunal Electoral, será turnado de inmediato a un\nMagistrado, quién tendrá la obligación de revisar que reúna todos los requisitos señalados en el presente Libro y cumplir con lo dispuesto en los artículos anteriores;\nLey Electoral del Estado de Baja California. Página 112\n.\nActualización Legislativa.\nÚltima reforma P. O. No. 60, Índice, 03-Oct-2025\nII. En los casos en que el promovente haya indicado que presentará pruebas dentro del plazo de interposición del recurso, se reservará la admisión del mismo, hasta la presentación de las señaladas o el vencimiento del plazo;\nIII. Si de la revisión que realice la Magistratura encuentra que el recurso encuadra en alguna de las causas de improcedencia, someterá a la consideración del Pleno del\nTribunal Electoral el acuerdo plenario de desechamiento correspondiente a más tardar cuarenta y ocho horas antes de celebrarse la sesión pública de resolución respectiva;\nFracción Reformada\nIV. En cuanto al informe circunstanciado, si la autoridad no lo envía dentro del plazo señalado en esta ley, el medio de impugnación se resolverá con los elementos a que se refiere el artículo 291 del ordenamiento, y que obren en autos; lo anterior, sin perjuicio de la sanción que deba ser impuesta de conformidad con el presente ordenamiento y las leyes aplicables;\nV. Si el medio de impugnación reúne todos los requisitos establecidos por este ordenamiento, el Magistrado dictará el auto de admisión que corresponda; una vez sustanciado el expediente se declarará cerrada la instrucción pasando el asunto a sentencia.\nEn estos casos, se ordenará fijar copia de los autos respectivos en los estrados, y\nVI. Cerrada la instrucción, la Magistratura ponente procederá a formular el proyecto de sentencia de sobreseimiento o de fondo, según sea el caso, y lo someterá a la consideración del Pleno del Tribunal, a más tardar cuarenta y ocho horas antes de celebrarse la sesión pública de resolución respectiva.\nArtículo 328.- Las sesiones de resolución del Pleno del Tribunal serán públicas y se desarrollarán de forma presencial en el recinto establecido para ello. En caso de emergencia sanitaria o causa justificada, así decretadas por la autoridad competente, que imposibilite sesionar de manera segura, en vivo y presencialmente, la presidencia previo acuerdo\n[unánime] del Pleno podrá convocar a sesión pública de resolución en su modalidad virtual, con apoyo de los medios tecnológicos.\nPárrafo Reformado\nPorción normativa invalidada por Sentencia a Acción de Inconstitucionalidad 198/2023 y su acumulada 200/2023\nEn las sesiones públicas de resolución se discutirán los asuntos en el orden en que se hayan listado, de acuerdo con el procedimiento siguiente:\nPárrafo Adicionado\nI. La Secretaría General de Acuerdos dará cuenta de los asuntos enlistados para resolución;\nFracción Reformada\nII. La Magistratura ponente por su conducto o de su Secretariado de Estudio y\nCuenta, o de la Secretaría General de Acuerdos, presentará el caso y el sentido del proyecto de resolución, señalando las consideraciones jurídicas y los preceptos en que la funda;\nFracción Reformada\nLey Electoral del Estado de Baja California. Página 113\n.\nActualización Legislativa.\nÚltima reforma P. O. No. 60, Índice, 03-Oct-2025\nIII. Las Magistraturas podrán discutir en igualdad de participación el proyecto de resolución en turno; y,\nFracción Reformada\nIV. Las y Los Magistrados podrán presentar voto particular que se agregará al expediente.\nFracción Reformada\nSolamente en casos extraordinarios, debidamente justificados, el Tribunal Electoral podrá diferir la resolución de un asunto listado.\nPárrafo Reformado\nArtículo Reformado\nArtículo 329.- Los Magistrados Electorales podrán requerir a los órganos del Instituto\nEstatal, a las autoridades o entes públicos estatales o municipales, a los partidos políticos, así como a los particulares, o solicitar a las autoridades federales, cualquier informe o elemento, que obrando en su poder, pueda servir para la sustanciación o resolución de los expedientes en los que sean ponentes, siempre que ello no sea obstáculo para resolver el recurso dentro de los plazos establecidos en esta Ley.\nLas autoridades proporcionarán oportunamente los informes o elementos a que se refiere el párrafo anterior.\nArtículo Reformado\nCAPÍTULO DÉCIMO\nDe las resoluciones y sentencias\nArtículo 330.- Las resoluciones o sentencias deberán hacerse constar por escrito y contendrán lo siguiente:\nI. Fecha y lugar en que se dicta;\nII. Resumen de los hechos o puntos de derecho controvertidos;\nIII. Análisis de los agravios, así como el examen y valoración de las pruebas admitidas, en su caso;\nIV. Fundamentos jurídicos;\nV. Puntos resolutivos, y\nVI. En su caso, el plazo para su cumplimiento.\nEn los casos relacionados con derechos de pueblos, comunidades y personas indígenas y afromexicanas, el Tribunal deberá juzgar con perspectiva intercultural conforme a la Constitución Federal, los instrumentos internacionales de los que México es parte y la\nFederación y de la Suprema Corte de Justicia de la Nación. El Tribunal también estará obligado a juzgar con perspectiva de género.\nPárrafo Adicionado\nLey Electoral del Estado de Baja California. Página 114\n.\nActualización Legislativa.\nÚltima reforma P. O. No. 60, Índice, 03-Oct-2025\nArtículo Reformado\nArtículo 331.- Los recursos serán resueltos por mayoría de los integrantes del\nTribunal Electoral, dentro de los treinta días siguientes a aquel en que fue recibido por el\nTribunal.\nLos recursos de revisión previstos en esta Ley, se resolverán conforme a los siguientes plazos:\nPárrafo Reformado\nI. A más tardar el 13 de julio del año de la elección, los relativos a la elección de diputados por el principio de mayoría relativa;\nII. Dentro de los 12 días siguientes a aquel en que fueron recibidos por el Tribunal\nElectoral, cuando se impugne el cómputo de la elección de diputados por el principio de representación proporcional y la asignación que realice el Consejo General;\nIII. A más tardar el 31 de agosto del año de la elección, los relativos a la elección de munícipes;\nIV. Dentro de los 15 días siguientes a aquel en que fueron recibidos por el Tribunal electoral, cuando - se impugne la asignación de munícipes por el principio de representación proporcional, y\nV. A más tardar el 22 de septiembre del año de la elección, el relativo a la elección de\nGobernador del Estado.\nArtículo Reformado\nArtículo 332.- Los recursos de inconformidad interpuestos por los candidatos independientes, partidos políticos o coaliciones dentro de los cinco días anteriores a la elección, serán resueltos junto con los recursos de revisión con los que guarden relación. El recurrente deberá señalar la conexidad de la causa con el recurso de revisión.\nArtículo 333.- Las sentencias que recaigan a los recursos de inconformidad y apelación, tendrán como efecto la confirmación, modificación o revocación del acto o resolución impugnado.\nArtículo 334.- Las sentencias que recaigan a los recursos de revisión, podrán tener los siguientes efectos:\nI. Anular los resultados de la votación emitida en la casilla, cuando se surta alguno de los supuestos previstos en el artículo 273 de esta Ley, y modificar, en consecuencia, el acta de cómputo distrital o estatal respectiva;\nII. Anular el cómputo del Consejo Distrital de las elecciones de diputados, munícipes y Gobernador, y en consecuencia, ordenar se lleve a cabo;\nIII. Anular el cómputo del Consejo General de las elecciones de munícipes y\nGobernador, y en consecuencia, ordenar se lleve a cabo;\nLey Electoral del Estado de Baja California. Página 115\n.\nActualización Legislativa.\nÚltima reforma P. O. No. 60, Índice, 03-Oct-2025\nIV. Anular las elecciones de diputados de mayoría relativa, de munícipes o de\nGobernador, cuando se surta alguno o algunos de los supuestos previstos en esta Ley;\nV. Revocar la declaración de validez de la elección de diputados y la expedición de la constancia de mayoría expedida a favor de la formula correspondiente;\nVI. Revocar la declaración de validez de la elección de munícipes y la constancia de mayoría expedida en favor de la planilla correspondiente;\nVII. Revocar la declaración de validez de la elección de Gobernador y la constancia de mayoría otorgada al candidato respectivo;\nVIII. Modificar la asignación de diputados por el principio de representación proporcional;\nIX.- Modificar la asignación de munícipes por el principio de representación proporcional, y;\nX. Confirmar o revocar el acto impugnado.\nArtículo 334 BIS.- Las sentencias que resuelvan el fondo del juicio para la protección de los derechos político– electorales del ciudadano, serán definitivas e inatacables y podrán tener los efectos siguientes:\na) Confirmar el acto o resolución impugnado; y,\nb) Revocar o modificar el acto o resolución impugnado y restituir al promovente en el uso y goce del derecho político–electoral que le haya sido violado.\nArtículo Adicionado\nCAPÍTULO DÉCIMO PRIMERO\nDe los medios de apremio y de las correcciones disciplinarias\nArtículo 335.- El Tribunal Electoral, para hacer cumplir las disposiciones del presente ordenamiento y las sentencias que dicte, así como para mantener el orden y exigir que se le guarde el respeto y la consideración debida, podrá hacer uso, discrecionalmente, de los medios de apremio y las correcciones disciplinarias siguientes:\nI. Apercibimiento;\nII. Amonestación;\nIII. Multa hasta por cien veces el valor diario de la Unidad de Medida y\nActualización vigente;\nFracción Reformada\nIV. Auxilio de la fuerza pública, y\nV. Arresto hasta por treinta y seis horas.\nArtículo Reformado\nLey Electoral del Estado de Baja California. Página 116\n.\nActualización Legislativa.\nÚltima reforma P. O. No. 60, Índice, 03-Oct-2025\nArtículo 336.- Los medios de apremio y las correcciones disciplinarias serán aplicados por el Presidente del Tribunal Electoral, o con el apoyo de la autoridad competente, en su caso.\nLIBRO SEXTO\nDe las Faltas y Sanciones Administrativas\nTÍTULO PRIMERO\nDe las Faltas Electorales y su Sanción\nCAPÍTULO PRIMERO\nSujetos y Conductas Sancionables\nArtículo 337.- Son sujetos de responsabilidad por infracciones cometidas a las disposiciones electorales contenidas en esta Ley:\nI. Los partidos políticos;\nII. Los aspirantes, precandidatos, candidatos y Candidatos Independientes a cargos de elección popular;\nIII. Los ciudadanos, o cualquier persona física o moral;\nIV. Las autoridades públicas;\nV. Los notarios públicos;\nVI. Los extranjeros;\nVII. Las organizaciones de ciudadanos que pretendan formar un partido político local;\nVIII. Las organizaciones sindicales, laborales o patronales, o de cualquier otra agrupación con objeto social diferente a la creación de partidos políticos estatales, así como sus integrantes o dirigentes, en lo relativo a la creación y registro de partidos políticos;\nIX. Los ministros de culto, asociaciones, iglesias o agrupaciones de cualquier religión, y\nX. Los demás sujetos obligados en los términos de la presente Ley. conductas relacionadas por violencia política contra las mujeres en razón de género, contenidas en el artículo 337 BIS, así como en la Ley de Acceso, será sancionado en en los artículos 338 al 353.\nPárrafo Adicionado\nLas quejas o denuncias por violencia política contra las mujeres en razón de género, se sustanciarán a través del Procedimiento Especial Sancionador.\nLey Electoral del Estado de Baja California. Página 117\n.\nActualización Legislativa.\nÚltima reforma P. O. No. 60, Índice, 03-Oct-2025\nPárrafo Adicionado\nArtículo Reformado\nArtículo 337 BIS.- La violencia política contra las mujeres en razón de género, dentro del proceso electoral o fuera de éste, constituye una infracción a la presente Ley por parte de los sujetos de responsabilidad señalados en el artículo 337 de esta Ley, y se manifiesta, entre otras, a través de las siguientes conductas:\nI. Obstaculizar a las mujeres, los derechos de asociación o afiliación política;\nII. Ocultar información a las mujeres, con el objetivo de impedir la toma de decisiones y el desarrollo de sus funciones y actividades;\nIII. Ocultar la convocatoria para el registro de precandidaturas o candidaturas, o información relacionada con ésta, con la finalidad de impedir la participación de las mujeres;\nIV. Proporcionar a las mujeres que aspiran a ocupar un cargo de elección popular, información falsa, incompleta o imprecisa, para impedir su registro;\nV. Obstaculizar la precampaña o campaña política de las mujeres, impidiendo que la competencia electoral se desarrolle en condiciones de igualdad, y\nVI. Cualquiera otra acción que lesione o dañe la dignidad, integridad o libertad de las mujeres en el ejercicio de sus derechos políticos y electorales.\nArtículo Adicionado\nArtículo 338.- Constituyen infracciones de los partidos políticos, cuando:\nI. El incumplimiento de las obligaciones señaladas en la Ley de Partidos Políticos del Estado, y demás disposiciones aplicables de esta Ley;\nII. Incumplan con las resoluciones o acuerdos del Instituto Estatal o del Tribunal\nElectoral;\nIII. Habiendo postulado candidatos a diputados, munícipes o Gobernador, estos resulten electos y acuerden no desempeñar el cargo;\nIV. Provoquen violencia por conducto de sus candidatos, simpatizantes o dirigentes;\nV. Participen en la toma de edificios públicos estatales y municipales o les causen daño; así como cuando, por ese motivo originen daño a los bienes particulares;\nVI. La realización anticipada de actos de precampaña o campaña atribuible a los propios partidos;\nVII. La realización de actos de precampaña o campaña en territorio extranjero cuando se acredite que se hizo con consentimiento de aquellos, sin perjuicio de que se determine la responsabilidad de quien hubiese cometido la infracción;\nLey Electoral del Estado de Baja California. Página 118\n.\nActualización Legislativa.\nÚltima reforma P. O. No. 60, Índice, 03-Oct-2025\nVIII. La difusión de propaganda política o electoral que contenga expresiones que denigren a las instituciones y a los propios partidos, o que calumnien a las personas o constituyan actos de violencia política contra las mujeres en razón de género;\nFracción Reformada\nIX. El incumplimiento de las demás disposiciones previstas en la presente Ley en materia de precampañas y campañas electorales;\nX. El incumplimiento de las demás disposiciones previstas en la Ley de Partidos\nPolíticos del Estado, en materia de transparencia y acceso a la información;\nXI. La omisión o el incumplimiento de la obligación de proporcionar en tiempo y forma, la información que les sea solicitada por los órganos del Instituto;\nFracción Reformada\nXII. El incumplimiento a las obligaciones para prevenir, atender y erradicar la violencia política contra las mujeres en razón de género;\nFracción Adicionada\nFracción Reformada\nXIII. Postulen candidatas o candidatos bajo el principio de igualdad sustantiva sin pertenecer a los pueblos indígenas o afromexicanos que protege dicho principio; y,\nFracción Adicionada, recorriéndose la subsecuente\nXIV. La comisión de cualquier otra falta de las previstas en esta Ley.\nArtículo Reformado\nArtículo 339.- Constituyen infracciones de los aspirantes, precandidatos o candidatos a cargos de elección popular a la presente Ley:\nI. La realización de actos anticipados de campaña.\nFracción Reformada\nII. Quien se atribuya con dolo o mala identidad para ser candidata o candidato bajo el principio de igualdad sustantiva.\nFracción Adicionada, recorriéndose la subsecuente\nIII. El incumplimiento de cualquiera de las disposiciones contenidas en esta Ley.\nArtículo Reformado\nArtículo 340.- Constituyen infracciones de los aspirantes y Candidatos\nIndependientes a cargos de elección popular las establecidas en el artículo 63 de la Ley que\nReglamenta las Candidaturas Independientes en el Estado.\nArtículo 341.- Constituyen infracciones de los ciudadanos, de los dirigentes y afiliados a partidos políticos, o en su caso de cualquier persona física o moral, a esta Ley:\nI. La negativa a entregar la información requerida por el Instituto Estatal, entregarla en forma incompleta o con datos falsos, o fuera de los plazos que señale el\nLey Electoral del Estado de Baja California. Página 119\n.\nActualización Legislativa.\nÚltima reforma P. O. No. 60, Índice, 03-Oct-2025 requerimiento, respecto de cualquier acto que los vincule con los partidos políticos, los precandidatos o candidatos a cargos de elección popular;\nII. La promoción de quejas o denuncias frívolas, y\nIII. El incumplimiento de cualquiera de las disposiciones contenidas en esta Ley.\nArtículo 342.- Constituyen infracciones a la presente Ley, de las autoridades o de las servidoras y los servidores públicos, según sea el caso, de cualquiera de los Poderes\nEjecutivo, Legislativo y Judicial; órganos de gobierno municipales; órganos autónomos y cualquier otro ente público:\nPárrafo Reformado\nI. La omisión o el incumplimiento de la obligación de prestar colaboración y auxilio o de proporcionar, en tiempo y forma, la información que les sea solicitada por los órganos del Instituto;\nII. La difusión, por cualquier medio distinto a la de radio y televisión, de propaganda gubernamental dentro del periodo que comprende desde el inicio de las campañas electorales hasta el día de la jornada electoral local inclusive, con excepción de la información relativa a servicios educativos y de salud, o la necesaria para la protección civil en casos de emergencia;\nIII. El incumplimiento del principio de imparcialidad establecido por el artículo 134 de la Constitución Federal que incidan en el proceso electoral local respectivo, cuando tal conducta afecte la equidad de la competencia entre los partidos políticos, entre las personas aspirantes, precandidatas y candidatas durante los procesos electorales;\nFracción Reformada\nIV. Durante los procesos electorales locales, la difusión de propaganda, en cualquier medio de comunicación social distinto a la de radio y televisión, que contravenga lo dispuesto por el párrafo octavo del artículo 134 de la Constitución Federal;\nFracción Reformada\nV. Menoscabar, limitar o impedir el ejercicio de derechos políticos electorales, o incurrir en actos u omisiones constitutivos de violencia política contra las mujeres en razón de género, en los términos de esta Ley y de la Ley de Acceso, y\nFracción Adicionada, recorriéndose la subsecuente\nVI. El incumplimiento de cualquiera de las disposiciones contenidas en esta Ley.\nArtículo Reformado\nArtículo 343.- Constituyen infracciones a la presente Ley de los notarios públicos, el de atender las solicitudes que les hagan las autoridades electorales, los funcionarios de casilla, los ciudadanos y los representantes de partidos políticos, para dar fe de hechos o certificar documentos concernientes a la elección.\nLey Electoral del Estado de Baja California. Página 120\n.\nActualización Legislativa.\nÚltima reforma P. O. No. 60, Índice, 03-Oct-2025\nArtículo 344.- Constituyen infracciones a la presente Ley de los extranjeros, las conductas que violen lo dispuesto por el artículo 33 de la Constitución federal y las leyes aplicables, que incidan en el proceso electoral local.\nArtículo 345.- Constituyen infracciones a la presente Ley de las organizaciones de ciudadanos que pretendan constituir partidos políticos:\nI. El incumplimiento de las obligaciones señaladas en la Ley de Partidos Políticos del Estado, y demás disposiciones aplicables de esta Ley;\nII. Permitir que en la creación del partido político intervengan organizaciones gremiales u otras con objeto social diferente a dicho propósito, y\nIII. Realizar o promover la afiliación colectiva de ciudadanos a la organización o al partido para el que se pretenda registró.\nArtículos 346.- Constituyen infracciones a esta Ley, de las organizaciones sindicales, laborales o patronales, o de cualquier otra agrupación con objeto social diferente a la creación de partidos políticos, así como de sus integrantes o dirigentes, cuando actúen o se ostenten con tal carácter, o cuando dispongan de los recursos patrimoniales de su organización, con el objeto de intervenir en la creación y registro de un partido político estatal o en actos de afiliación colectiva a los mismos, así como el incumplimiento, en lo conducente, de cualquiera de las disposiciones contenidas en esta Ley.\nArtículo 347.- Constituyen infracciones a la presente Ley de los ministros de culto, asociaciones, iglesias o agrupaciones de cualquier religión, cuando incida en el proceso electoral local:\nI. La inducción a la abstención, a votar por un candidato o partido político, o a no hacerlo por cualquiera de ellos, en los lugares destinados al culto, en locales de uso público o en los medios de comunicación;\nII. Realizar o promover aportaciones económicas a un partido político, aspirante o candidato a cargo de elección popular, y\nIII. El incumplimiento, en lo conducente, de cualquiera de las disposiciones contenidas en esta Ley.\nArtículo 348.- Cuando el Consejo General conozca del incumplimiento por parte de los notarios públicos a las obligaciones que la presente Ley les impone, la Unidad Técnica aplicable; estos últimos deberán comunicar al Consejo General, las medidas que haya adoptado y las sanciones impuestas. En todo caso, la autoridad competente ordenará las medidas cautelares a fin de que la conducta infractora cese de inmediato.\nArtículo 349.- El Consejo General conocerá de las infracciones en que incurran los extranjeros que pretendan inmiscuirse o se inmiscuyan en asuntos políticos locales. En este supuesto, el Consejero Presidente del Consejo General, procederá a informar de inmediato a la Secretaría de Gobernación, para los efectos previstos en la Ley aplicable. Si el infractor\nLey Electoral del Estado de Baja California. Página 121\n.\nActualización Legislativa.\nÚltima reforma P. O. No. 60, Índice, 03-Oct-2025 se encuentra fuera del territorio nacional, el Presidente del Consejo General procederá a informar a la Secretaria de Relaciones Exteriores para los efectos a que haya lugar.\nArtículo 350.- El Consejo General informará a la autoridad competente de los casos en que los ministros de culto, asociaciones, iglesias o agrupaciones religiosas, contravengan las disposiciones previstas en esta Ley.\nArtículo 351.- Cuando las autoridades públicas cometan alguna infracción prevista en esta Ley, incumplan los mandatos de la autoridad electoral, no proporcionen en tiempo y forma la información que les sea solicitada, o no presten el auxilio y colaboración que les sea requerida por los órganos del Instituto, se dará vista al superior jerárquico y, en su caso, presentará la queja ante la autoridad competente por hechos que pudieran constituir responsabilidades administrativas o las denuncias o querellas ante el agente del Ministerio\nPúblico que deba conocer de ellas, a fin de que se proceda en los términos de las leyes aplicables.\nArtículo 352.- Cuando las autoridades públicas incumplan los mandatos de la autoridad electoral, no proporcionen en tiempo y forma la información que les sea solicitada, o no presten el auxilio y colaboración que les sea requerida por los órganos del Instituto, se estará a lo siguiente:\nConocida la infracción, la Unidad Técnica de lo Contencioso Electoral de la Secretaría\nEjecutiva integrará un expediente que será remitido al superior jerárquico de la autoridad infractora, para que éste proceda en los términos de ley.\nEl superior jerárquico a que se refiere el párrafo anterior deberá comunicar al Instituto las medidas que haya adoptado en el caso.\nArtículo 353.- Constituyen infracciones para los efectos de esta Ley, las demandas o promociones que se formulen por motivo de quejas o denuncias frívolas, entendiéndose como tales:\nI. Las demandas o promociones en las cuales se formulen pretensiones que no se pueden alcanzar jurídicamente, por ser notorio y evidente que no se encuentran al amparo del derecho;\nII. Aquellas que refieran hechos que resulten falsos o inexistentes de la sola lectura cuidadosa del escrito y no se presenten las pruebas mínimas para acreditar su veracidad;\nIII. Aquellas que se refieran a hechos que no constituyan una falta o violación electoral, o\nIV. Aquellas que únicamente se fundamenten en notas de opinión periodística o de carácter noticioso, que generalicen una situación, sin que por otro medio se pueda acreditar su veracidad.\nLa sanción que se imponga, en su caso, deberá de valorar el grado de frivolidad de la organismos electorales.\nLey Electoral del Estado de Baja California. Página 122\n.\nActualización Legislativa.\nÚltima reforma P. O. No. 60, Índice, 03-Oct-2025\nCAPÍTULO SEGUNDO\nDe las Sanciones\nArtículo 354.- Las infracciones cometidas a las disposiciones electorales contenidas en esta Ley serán sancionadas conforme a lo siguiente:\nI. Respecto de los partidos políticos, con independencia de la responsabilidad personal en que incurran sus dirigentes, miembros o simpatizantes:\na) Con amonestación pública;\nb) Con multa de cincuenta a cinco mil veces el valor diario de la Unidad de\nMedida y Actualización vigente;\nInciso Reformado\nc) Con la reducción de hasta el cincuenta por ciento de las ministraciones de financiamiento público que les corresponde, por el período que señale la resolución correspondiente;\nTratándose de infracciones relacionadas con el incumplimiento de las obligaciones para prevenir, atender y erradicar la violencia política contra las mujeres en razón de género, según la gravedad de la falta, podrá sancionarse con la reducción de hasta el 50% de las ministraciones del financiamiento público que les corresponda, por el periodo que señale la resolución.\nPárrafo Adicionado\nInciso Reformado\nd) Con la supresión total de la entrega de las ministraciones del financiamiento público que les corresponda, por el período que señale la resolución;\ne) En los casos de graves y reiteradas conductas violatorias de la Constitución y de esta Ley, especialmente en cuanto a sus obligaciones en materia de origen y destino de sus recursos, así como las relacionadas con el incumplimiento de las obligaciones para prevenir, atender y erradicar la violencia política contra las mujeres en razón de género, con la cancelación de su registro como partido político local;\nInciso Reformado\nf) Tratándose de partidos políticos nacionales, la suspensión del derecho a participar en los procesos electorales locales.\nFracción Reformada\nII. Respecto de las personas aspirantes, precandidatas o candidatas a cargos de elección popular:\nPárrafo Reformado\na) Con amonestación pública;\nLey Electoral del Estado de Baja California. Página 123\n.\nActualización Legislativa.\nÚltima reforma P. O. No. 60, Índice, 03-Oct-2025\nb) Con multa de hasta mil veces el valor diario de la Unidad de Medida y\nActualización vigente, y\nInciso Reformado\nc) Con la pérdida del derecho de las personas precandidatas infractoras a ser registradas como candidatas o, en su caso, si ya está hecho el registro, con la cancelación del mismo. Cuando las infracciones cometidas por las personas aspirantes o precandidatas a cargos de elección popular, cuando sean imputables exclusivamente a aquellos, no procederá sanción alguna en contra del partido político de que se trate. Cuando la persona precandidata resulte electo en el proceso interno, el partido político no podrá registrarlo como candidato.\nInciso Reformado\nFracción Reformada\nIII. Respecto de las personas aspirantes, Candidatas y Candidatos\nIndependientes, conforme a las sanciones previstas artículo 64 de la Ley que Reglamenta las Candidaturas Independientes en el Estado;\nFracción Reformada\nIV. Respecto de los ciudadanos, de los dirigentes y afiliados a los partidos políticos, o de cualquier persona física o moral:\na) Con amonestación pública;\nb) Respecto de los ciudadanos, o de los dirigentes y afiliados a los partidos políticos, con multa de hasta doscientos veces el valor diario de la Unidad de Medida y\nActualización vigente;\nInciso Reformado\nc) Respecto de las personas morales con multa de hasta mil veces el valor diario de la Unidad de Medida y Actualización vigente.\nInciso Reformado\nd) Respecto de los ciudadanos, de los dirigentes y afiliados a los partidos políticos, o cualquier persona física o moral, con amonestación pública y, en caso de reincidencia, con multa de hasta mil veces el valor diario de la Unidad de Medida y\nActualización vigente, en el caso de que promuevan una denuncia frívola.\nInciso Reformado\nFracción Reformada\nV. Respecto de las organizaciones de ciudadanos que pretendan constituir partidos políticos:\na) Con amonestación pública;\nb) Con multa de hasta mil veces el valor diario de la Unidad de Medida y\nActualización vigente, según la gravedad de la falta, y\nInciso Reformado\nLey Electoral del Estado de Baja California. Página 124\n.\nActualización Legislativa.\nÚltima reforma P. O. No. 60, Índice, 03-Oct-2025\nc) Con la cancelación del procedimiento tendente a obtener el registro como partido político nacional, y\nFracción Reformada\nVI. Respecto de las organizaciones sindicales, laborales o patronales, o de cualquier otra agrupación con objeto social diferente a la creación de partidos políticos, así como sus integrantes o dirigentes, en lo relativo a la creación y registro de partidos políticos estatales:\na) Con amonestación pública, y\nb) Con multa de hasta mil veces el valor diario de la Unidad de Medida y\nActualización vigente, según la gravedad de la falta.\nInciso Reformado\nFracción Reformada\nArtículo Reformado\nArtículo 354 BIS.- A quien incumpla lo dispuesto en el artículo 152, fracción II, segundo párrafo de esta Ley, se le aplicará una multa de cincuenta a cinco mil veces al valor diario de la unidad de medida y actualización vigente.\nArtículo Adicionado\nArticulo 355.- Ninguna sanción podrá imponerse, sin que previamente se oiga en defensa al interesado.\nLa facultad de la autoridad electoral para fincar responsabilidades por infracciones administrativas prescribe en el término de tres años; plazo que se interrumpe con el inicio del procedimiento sancionador respectivo.\nArticulo 356.- Para la individualización de las sanciones a que se refiere este Libro, una vez acreditada la existencia de una infracción y su imputación, la autoridad electoral deberá tomar en cuenta las circunstancias que rodean la contravención de la norma administrativa, entre otras, las siguientes:\nI. La gravedad de la responsabilidad en que se incurra y la conveniencia de suprimir prácticas que infrinjan, en cualquier forma, las disposiciones de este ordenamiento, en atención al bien jurídico tutelado, o las que se dicten con base en él;\nII. Las circunstancias de modo, tiempo y lugar de la infracción;\nIII. Las condiciones socioeconómicas del infractor;\nIV. Las condiciones externas y los medios de ejecución;\nV. La reincidencia en el incumplimiento de obligaciones, y\nVI. En su caso, el monto del beneficio, lucro, daño o perjuicio derivado del incumplimiento de obligaciones.\nArtículo 357.- Las multas que se apliquen en los términos de esta Ley, que no hubiesen sido recurridas, o bien que fuesen confirmadas por la autoridad judicial electoral, Ley Electoral del Estado de Baja California. Página 125\n.\nActualización Legislativa.\nÚltima reforma P. O. No. 60, Índice, 03-Oct-2025 se pagarán en la caja de recaudación de la Secretaría de Planeación y Finanzas del Estado, en un plazo improrrogable de quince días contados a partir de que causen estado.\nTranscurrido el plazo que se menciona en el párrafo anterior, sin que el pago se hubiese efectuado, el Secretario Ejecutivo procederá a deducir el monto de la multa, de las siguientes ministraciones del financiamiento público ordinario que corresponda, y enterarlo a la Secretaría de Planeación y Finanzas del Estado.\nEn los casos, en que no se pueda realizar la deducción, le corresponderá a la autoridad competente la aplicación del procedimiento económico coactivo, para su ejecución.\nArtículo 358.- Todo lo relacionado a infracciones en materia de fiscalización de recursos públicos y privados serán sancionadas bajo los supuestos, términos y condiciones que señala la Constitución Política de los Estados Unidos Mexicanos, La Ley General de\nInstituciones y Procedimientos Electorales y demás disposiciones aplicables.\nCAPÍTULO TERCERO\nDel Procedimiento Sancionador, disposiciones generales\nArtículo 359.- Son órganos competentes para la tramitación y resolución del procedimiento sancionador:\nI. El Consejo General;\nII. La Comisión de Quejas y Denuncias;\nIII. La Unidad Técnica de lo Contencioso Electoral de la Secretaria Ejecutiva;\nIV. Los Consejos Distritales y\nV. El Tribunal Electoral.\nArtículo 360.- Los órganos que tramiten o sustancien el procedimiento sancionador, podrán hacer uso, discrecionalmente, de los medios de apremio y las correcciones disciplinarias previstas en el artículo 355 de esta Ley.\nArtículo 361.- Para la resolución expedita de las quejas o denuncias y con el objeto de determinar en una sola resolución sobre dos o más de ellas, los órganos competentes procedimientos por que existan varias quejas o denuncias contra un mismo denunciado, respecto de una misma conducta y provengan de una misma causa.\nArtículo 362.- Los procedimientos ordinarios y especiales, relacionados con la difusión de propaganda que denigre o calumnie, así como aquella que constituya violencia política en razón de género, sólo podrán iniciar a instancia de parte afectada.\nArtículo Reformado\nLey Electoral del Estado de Baja California. Página 126\n.\nActualización Legislativa.\nÚltima reforma P. O. No. 60, Índice, 03-Oct-2025\nArtículo 363.- Las notificaciones se harán a más tardar dentro de los tres días hábiles siguientes al en que se dicten las resoluciones que las motiven y surtirán sus efectos el mismo día de su realización.\nPárrafo Reformado\nCuando la resolución entrañe una citación o un plazo para la práctica de una diligencia se notificará personalmente, al menos con tres días hábiles de anticipación al día y hora en que se haya de celebrar la actuación o audiencia. Las demás se harán por cédula que se fijará en los estrados del Instituto Estatal o del Consejo Distrital que emita la resolución de que se trate. En todo caso, las que se dirijan a una autoridad u órgano partidario se notificarán por oficio.\nPárrafo Adicionado\nLas notificaciones personales se realizarán en días y horas hábiles a la persona interesada o por conducto de la persona que esta haya autorizado para el efecto.\nPárrafo Adicionado\nLas notificaciones serán personales cuando así se determine, pero en todo caso, la primera notificación a alguna de las partes se llevará de forma personal.\nPárrafo Adicionado\nCuando deba realizarse una notificación personal, la o el notificador deberá cerciorarse, por cualquier medio, que la persona que deba ser notificada tiene su domicilio en el inmueble designado y, después de ello, practicará la diligencia entregando copia autorizada de la resolución correspondiente, de todo lo cual se asentará razón en autos.\nPárrafo Adicionado\nSi no se encuentra a la persona interesada en su domicilio se le dejará con cualquiera de las personas que allí se encuentren un citatorio que contendrá:\nI. Denominación del órgano que dictó la resolución que se pretende notificar;\nII. Datos del expediente en el cual se dictó;\nIII. Extracto de la resolución que se notifica;\nIV. Día y hora en que se deja el citatorio y nombre de la persona a la que se le entrega, y\nV. El señalamiento de la hora a la que, al día siguiente, deberá esperar la notificación.\nPárrafo con sus Fracciones Adicionado\nAl día siguiente, en la hora fijada en el citatorio, la o el notificador se constituirá nuevamente en el domicilio y si el interesado no se encuentra, se hará la notificación por estrados, de todo lo cual se asentará la razón correspondiente.\nPárrafo Adicionado\nLey Electoral del Estado de Baja California. Página 127\n.\nActualización Legislativa.\nÚltima reforma P. O. No. 60, Índice, 03-Oct-2025\nSi a quien se busca se niega a recibir la notificación, o las personas que se encuentran en el domicilio se rehúsan a recibir el citatorio, o no se encuentra nadie en el lugar, éste se fijará en la puerta de entrada, procediéndose a realizar la notificación por estrados, asentándose razón de ello en autos.\nPárrafo Adicionado\nLas notificaciones personales podrán realizarse por comparecencia de la persona interesada, de su representante, o de su autorizado ante el órgano que corresponda.\nPárrafo Adicionado\nLa notificación de las resoluciones que pongan fin al procedimiento de investigación será personal, se hará a más tardar dentro de los tres días hábiles siguientes a aquél en que se dicten, entregando al denunciante y a la denunciada copia certificada de la resolución.\nPárrafo Adicionado\nLos plazos se contarán de momento a momento y si están señalados por días, éstos se considerarán de veinticuatro horas. Durante los procesos electorales todos los días y horas son hábiles. En el caso de las quejas que se inicien antes del proceso electoral, los plazos se computarán por días hábiles, respecto de las que se presenten una vez iniciado aquél, por días naturales.\nPárrafo Adicionado\nArtículo Reformado\nArtículo 363 BIS.- Son objeto de prueba los hechos controvertidos. No lo será el derecho, los hechos notorios o imposibles, ni aquéllos que hayan sido reconocidos. Tanto la\nUnidad Técnica de lo Contencioso como el Consejo General podrán invocar los hechos notorios, aunque no hayan sido alegados por la o el denunciado o por la o el quejoso. En todo caso, una vez que se haya apersonado la o el denunciado al procedimiento de investigación, en el desahogo de las pruebas se respetará el principio contradictorio de la prueba, siempre que ello no signifique la posibilidad de demorar el proceso, o el riesgo de que se oculte o destruya el material probatorio.\nLas pruebas deberán ofrecerse en el primer escrito que presenten las partes en el procedimiento, expresando con toda claridad cuál es el hecho o hechos que se tratan de acreditar con las mismas, así como las razones por las que se estima que demostrarán las afirmaciones vertidas.\nSólo serán admitidas las siguientes pruebas:\nI. Documentales públicas;\nII. Documentales privadas;\nIII. Técnicas;\nIV. Pericial contable;\nV. Presunción legal y humana, e\nLey Electoral del Estado de Baja California. Página 128\n.\nActualización Legislativa.\nÚltima reforma P. O. No. 60, Índice, 03-Oct-2025\nVI. Instrumental de actuaciones.\nLa confesional y la testimonial podrán ser admitidas cuando se ofrezcan en acta levantada ante fedatario público que las haya recibido directamente de las personas declarantes, y siempre que estas últimas queden debidamente identificadas y asienten la razón de su dicho. La autoridad que sustancie el procedimiento podrá ordenar el desahogo de reconocimientos o inspecciones judiciales, así como de pruebas periciales, cuando la violación reclamada lo amerite, los plazos permitan su desahogo y se estimen determinantes para el esclarecimiento de los hechos denunciados.\nLa o el quejoso o el denunciado podrán aportar pruebas supervenientes hasta antes del cierre de la instrucción. Admitida una prueba superveniente, se dará vista a la o el quejoso o denunciado, según corresponda, para que en el plazo de cinco días manifieste lo que a su derecho convenga.\nLa Unidad Técnica de lo Contencioso o el Consejo General podrán admitir aquellas pruebas que habiendo sido ofrecidas en el escrito por el que se comparezca al procedimiento y que hayan sido solicitadas a las instancias correspondientes, no se hubiesen aportado antes de la aprobación del proyecto de resolución y se aporten hasta veinticuatro horas antes del inicio de la sesión respectiva. El Consejo General apercibirá a las autoridades, en caso de que estas no atiendan en tiempo y forma el requerimiento de las pruebas.\nAsimismo, el Consejo General podrá admitir aquellos elementos probatorios que, habiendo sido solicitados por los órganos del Instituto Estatal dentro de la investigación correspondiente, no se hubiesen recibido sino hasta veinticuatro horas antes de la sesión respectiva. En estos casos el Consejo General ordenará la devolución del expediente a la\nUnidad Técnica de lo Contencioso para que la investigación de los hechos se realice de forma seria, congruente, idónea, eficaz, expedita, completa y exhaustiva.\nArtículo Adicionado\nArtículo 363 TER.- Las pruebas admitidas y desahogadas serán valoradas en su conjunto, atendiendo a las reglas de la lógica, la experiencia y de la sana crítica, así como a los principios rectores de la función electoral, con el objeto de que produzcan convicción sobre los hechos denunciados.\nLas documentales públicas tendrán valor probatorio pleno, salvo prueba en contrario respecto de su autenticidad o de la veracidad de los hechos a que se refieran.\nLas documentales privadas, técnicas, periciales, e instrumental de actuaciones, así persona debidamente identificada, sólo harán prueba plena cuando a juicio del órgano competente para resolver generen convicción sobre la veracidad de los hechos alegados, al concatenarse con los demás elementos que obren en el expediente, las afirmaciones de las partes, la verdad conocida y el recto raciocinio de la relación que guardan entre sí. obren en el expediente, éstas tendrán únicamente el valor de un indicio.\nLey Electoral del Estado de Baja California. Página 129\n.\nActualización Legislativa.\nÚltima reforma P. O. No. 60, Índice, 03-Oct-2025\nArtículo Adicionado\nArtículo 363 QUATER.- A falta de disposición expresa en el presente Titulo, serán de aplicación supletoria, en lo conducente, las reglas precisadas para los procedimientos sancionadores en la Ley General.\nArtículo Adicionado\nSección Primera\nDel Procedimiento Sancionador Ordinario\nArtículo 364.- El procedimiento sancionador ordinario tiene por objeto sancionar las infracciones cometidas a las disposiciones electorales, dentro y fuera del proceso electoral local.\nArtículo 365.- El procedimiento podrá iniciar a instancia de parte, o de oficio cuando cualquier órgano del Instituto Estatal tenga conocimiento de la comisión de conductas infractoras.\nArtículo 366.- La queja o denuncia deberá presentarse por escrito, en forma oral o por medios de comunicación electrónicos, ante cualquier órgano del Instituto, cumpliendo los siguientes requisitos:\nPárrafo Reformado\nI. Nombre del quejoso o denunciante, con firma autógrafa o huella digital;\nII. Domicilio para oír y recibir notificaciones;\nIII. Los documentos que sean necesarios para acreditar la personería; tratándose de partidos políticos, si los representantes no acreditan su personería, la queja o denuncia se tendrá por no presentada;\nIV. Narración expresa y clara de los hechos en que se basa la queja o denuncia y, de ser posible, los preceptos presuntamente violados, y\nV. Ofrecer y aportar las pruebas con que cuente; o en su caso, mencionar las que habrán de requerirse, cuando el promovente acredite que oportunamente las solicitó por escrito al órgano competente, y no le hubieren sido entregadas. El denunciante deberá relacionar las pruebas con cada uno de los hechos.\nLa queja o denuncia presentada, deberá ser remitida dentro del término de cuarenta y ocho horas a la Unidad Técnica de lo Contencioso para su trámite.\nAnte la omisión de cualquiera de los requisitos antes señalados, la Unidad Técnica de improrrogable de tres días. De la misma forma lo prevendrá para que aclare su denuncia, cuando ésta sea imprecisa, vaga o genérica. En caso de no enmendar la omisión que se le requiera, la denuncia se tendrá por no presentada.\nLey Electoral del Estado de Baja California. Página 130\n.\nActualización Legislativa.\nÚltima reforma P. O. No. 60, Índice, 03-Oct-2025\nPárrafo Adicionado\nLa autoridad que tome conocimiento de la interposición de una queja o denuncia en forma oral, por medios de comunicación electrónicos, deberá hacerla constar en acta, requiriendo la ratificación por parte de la o el denunciante. En caso de no acudir a ratificar la denuncia o queja dentro del término de tres días contados a partir de que se le notifique la citación, se tendrá por no formulada la denuncia.\nPárrafo Adicionado\nArtículo Reformado\nArtículo 367.- Son causas de improcedencia o sobreseimiento de la queja o denuncia, además de los supuestos contenidos en el presente capítulo, las siguientes:\nI. De improcedencia, cuando:\na) El escrito no contenga firma autógrafa o huella digital de quien lo promueva;\nb) Por actos o hechos imputados a la misma persona que hayan sido materia de otra queja o denuncia que cuente con resolución definitiva;\nc) Se denuncien actos de los que la autoridad electoral resulte incompetente para conocer; o cuando los actos, hechos u omisiones denunciados no constituyan violaciones a la presente Ley, y\nd) Se trate de quejas o denuncias frívolas.\ne) La o el quejoso o denunciante no agote previamente las instancias internas del partido denunciado si la queja versa sobre presuntas violaciones a su normatividad interna;\nInciso Adicionado\nf) Tratándose de quejas o denuncias que versen sobre presuntas violaciones a la normatividad interna de un partido político, la o el quejoso o denunciante no acredite su pertenencia al partido de que se trate o su interés jurídico.\nInciso Adicionado\nFracción Reformada\nII. De sobreseimiento, cuando:\na) Habiendo sido admitida la queja o denuncia, sobrevenga alguna de las causales de improcedencia;\nb) El denunciado sea un partido político que, con posterioridad a la admisión de la queja o denuncia, haya perdido su acreditación o registro, y\nc) El denunciante presente escrito de desistimiento, siempre y cuando lo exhiba antes de la aprobación del proyecto de resolución por parte del Tribunal Electoral.\nEl estudio de las causas de improcedencia o sobreseimiento se realizará de oficio.\nEn caso de advertir que se actualiza una de ellas, la Unidad Técnica de lo sobreseimiento, según corresponda.\nLey Electoral del Estado de Baja California. Página 131\n.\nActualización Legislativa.\nÚltima reforma P. O. No. 60, Índice, 03-Oct-2025\nPárrafo Adicionado\nArtículo Reformado\nArtículo 368.- La tramitación o substanciación de las quejas o denuncias, se sujetará a lo siguiente:\nI. Una vez recibida por la Unidad Técnica de lo Contencioso, ésta verificará que se hubieren cumplido los requisitos señalados en el presente Libro y cumplir con lo dispuesto en los artículos anteriores.\nSi de la revisión que realice Unidad Técnica de lo Contencioso, se advierte la actualización de alguna causa de improcedencia, elaborará el acuerdo de desechamiento, que remitirá a la Comisión de Quejas y Denuncias para los efectos previstos en la presente sección.\nSi la Unidad Técnica de lo Contencioso Electoral advierte que la queja o denuncia no contiene los requisitos indicados en las fracciones III, IV y V del artículo 366 de esta Ley, prevendrá al promovente para que la subsane dentro del término improrrogable de dos días, apercibiéndole de que si no lo hace se le desechará de plano;\nII. La Unidad Técnica de lo Contencioso contará con un plazo de cinco días para emitir el acuerdo de admisión o propuesta de desechamiento, contados a partir del día en que reciba la queja o denuncia. En caso de que se hubiese prevenido al promovente, a partir de la recepción del desahogo de la prevención o de la fecha en la que termine el plazo sin que se hubiese desahogado la misma.\nSi dentro del plazo fijado para la admisión de la queja o denuncia, la Unidad Técnica de lo Contencioso valora que deben dictarse medidas cautelares lo propondrá a la Comisión de Quejas y Denuncias para que ésta resuelva en un plazo de veinticuatro horas lo conducente, a fin de lograr la cesación de los actos o hechos que constituyan la infracción, evitar la producción de daños irreparables, la afectación de los principios que rigen los procesos electorales, o la vulneración de los bienes jurídicos tutelados por las disposiciones contenidas en esta Ley.\nIII. Si la queja o denuncia reúne los requisitos establecidos en el presente Libro, la\nUnidad Técnica de lo Contencioso dictará la admisión correspondiente, ordenando el emplazamiento a la persona que se señale como presunta infractora, corriéndole traslado con una copia de la queja, así como de las pruebas que, en su caso, haya aportado la o el denunciante, concediéndole un plazo de cinco días contados a partir del día siguiente al de la notificación, para que conteste por escrito lo que a su derecho convenga, ofreciendo las pruebas que acrediten su defensa.\nPárrafo Reformado\nEn la admisión, o en su caso, al decretar el inicio del procedimiento oficioso, la Unidad el esclarecimiento de los hechos controvertidos, partiendo de los elementos de pruebas que obren en su poder;\nFracción Reformada\nLey Electoral del Estado de Baja California. Página 132\n.\nActualización Legislativa.\nÚltima reforma P. O. No. 60, Índice, 03-Oct-2025\nIV. La Unidad Técnica de lo Contencioso Electoral al admitir la contestación resolverá sobre la admisión de las pruebas ofrecidas por las partes dentro de los dos días siguientes, ordenando la preparación y desahogo de las mismas, para lo cual contará con un período de quince días. En los casos en que la Unidad Técnica de lo Contencioso Electoral hubiere ordenado de oficio la práctica de diligencias para el esclarecimiento de los hechos, el plazo anterior se prorrogar por quince días más;\nConcluido el desahogo de pruebas y, en su caso, agotada la investigación, la Unidad\nTécnica de lo Contencioso pondrá el expediente a la vista de la o el quejoso y de la o el denunciado para que, en un plazo de cinco días, manifiesten lo que a su derecho convenga.\nPárrafo Adicionado\nFracción Reformada\nV. En el plazo señalado en la fracción anterior, la Unidad Técnica de lo\nContencioso Electoral cerrará instrucción, y procederá dentro de los diez días siguientes a elaborar el proyecto de resolución el cual remitirá dentro del término de cinco días, conjuntamente con el expediente original formado con motivo de la queja o denuncia, a la\nComisión de Quejas y Denuncias para su conocimiento y estudio.\nFracción Reformada\nArtículo Reformado\nArtículo 369.- Cuando durante la sustanciación del procedimiento sancionador la\nUnidad Técnica de lo Contencioso Electoral advierta hechos distintos al objeto de ese procedimiento que puedan constituir distintas violaciones electorales, o la responsabilidad de actores diversos a los denunciados, podrá ordenar el inicio, de oficio, de un nuevo procedimiento.\nLa Unidad Técnica de lo Contencioso Electoral llevara un registro y control de las quejas y denuncias que reciba, de las admitidas, de las desechadas y de las que de oficio inicie, informando de ello al Consejo General.\nArtículo 370.- El presidente de la Comisión de Quejas y Denuncias, a más tardar al día siguiente de la recepción del proyecto de resolución, convocará a los demás integrantes de la misma a sesión, la que deberá tener lugar no antes de veinticuatro horas de la fecha de la convocatoria, con la finalidad de que dicho órgano colegiado analice y valore el referido proyecto, atendiendo a lo siguiente:\nI. Si el primer proyecto de la Unidad Técnica de lo Contencioso propone el desechamiento o sobreseimiento del procedimiento, o la imposición de una sanción y la\nComisión de Quejas y Denuncias está de acuerdo con el sentido del mismo, será turnado al\nConsejo General para su estudio y votación.\nII. En caso de no aprobarse el desechamiento o sobreseimiento, o la imposición de una sanción, la Comisión de Quejas y Denuncias devolverá el proyecto a la Unidad\nTécnica de lo Contencioso, exponiendo las razones de su devolución, o sugiriendo, en su caso, las diligencias que estime pertinentes para el perfeccionamiento de la investigación, y\nLey Electoral del Estado de Baja California. Página 133\n.\nActualización Legislativa.\nÚltima reforma P. O. No. 60, Índice, 03-Oct-2025\nIII. En un plazo no mayor a quince días después de la devolución del proyecto y las consideraciones al respecto, la Unidad Técnica de lo Contencioso emitirá un nuevo proyecto de resolución, debiendo considerar los razonamientos y argumentos que formule la\nComisión de Quejas y Denuncias.\nArtículo 371.- Una vez que el presidente del Consejo General reciba el proyecto correspondiente, convocara a sesión, remitiendo copias del mismo a los integrantes de dicho órgano por lo menos tres días antes de la fecha de la sesión.\nEn la sesión en que conozca del proyecto de resolución, el Consejo General determinará:\nI. Aprobarlo en los términos en que se le presente;\nII. Aprobarlo, ordenando a la Secretaría Ejecutiva realizar el engrose de la resolución en el sentido de los argumentos, consideraciones y razonamiento expresados por la mayoría;\nIII. Modificarlo, procediendo aprobarlo dentro de la misma sesión, siempre y cuando se considere que puede hacerse y que no contradice lo establecido en el cuerpo del dictamen.\nIV. Rechazarlo y ordenar a la Unidad Técnica de lo Contencioso elaborar un nuevo proyecto en el sentido de los argumentos, consideraciones y razonamientos expresados por la mayoría, y\nV. Rechazado un proyecto de resolución se entiende que se aprueba un acuerdo de devolución.\nEl Consejero Electoral que disienta de la mayoría podrá formular voto particular, el cual se insertara en el proyecto respectivo si se remite al Secretario dentro de los días siguientes a la fecha de su aprobación.\nEn el desahogo de los puntos de la orden del día en que el Consejo General deba resolver sobre los proyectos de resolución relativos a quejas o denuncias, estos se agruparan y votaran en un solo acto, salvo que alguno de sus integrantes proponga su discusión por separado.\nSección Segunda\nDel Procedimiento Especial Sancionador\nArticulo 372.- Dentro de los procesos electorales, la Secretaría Ejecutiva del Instituto, por conducto de la Unidad Técnica de lo Contencioso, instruirá el procedimiento especial establecido en la presente sección, cuando se denuncie la comisión de conductas, no relacionadas con radio y televisión, que:\nI. Violen lo establecido en el párrafo cuarto del artículo 5 de la Constitución del\nEstado, así como aquellas que violen el octavo párrafo del artículo 134 de la Constitución respectivo;\nLey Electoral del Estado de Baja California. Página 134\n.\nActualización Legislativa.\nÚltima reforma P. O. No. 60, Índice, 03-Oct-2025\nII. Contravengan las normas sobre propaganda política o electoral, o\nIII. Constituyan actos anticipados de precampaña o campaña.\nLa Secretaría Ejecutiva por conducto de la Unidad Técnica de lo Contencioso, instruirá el procedimiento especial establecido en la presente sección, en cualquier momento cuando se presenten denuncias, o de oficio por hechos relacionados con violencia política contra las mujeres en razón de género.\nPárrafo Adicionado\nArtículo Reformado\nArtículo 373.- Cuando la conducta infractora esté relacionada con propaganda política o electoral en radio y televisión, la queja o denuncia y sus anexos se remitirán inmediatamente al Instituto Nacional, para su conocimiento y estudio.\nArtículo Reformado\nArtículo 373 BIS.- En los procedimientos relacionados con violencia política contra las mujeres en razón de género, la Unidad Técnica de lo Contencioso, ordenará en forma sucesiva iniciar el procedimiento, así como resolver sobre las medidas cautelares y de protección que fueren necesarias. Cuando las medidas de protección sean competencia de otra autoridad, la Secretaría Ejecutiva dará vista de inmediato para que proceda a otorgarlas conforme a sus facultades y competencias.\nCuando la conducta infractora sea del conocimiento de los Consejos Distritales\nElectorales, de inmediato la remitirán, a la Secretaría Ejecutiva del Instituto para que ordene iniciar el procedimiento correspondiente.\nCuando las denuncias presentadas sean en contra de algún servidor o servidora pública, la Secretaría Ejecutiva dará vista de las actuaciones, así como de su resolución, a las autoridades competentes en materia de responsabilidades administrativas, para que en su caso apliquen las sanciones que correspondan en términos de la Ley aplicable.\nLa denuncia deberá contener lo siguiente:\nI. Nombre de la persona denunciante, con firma autógrafa o huella digital;\nII. Domicilio para oír y recibir notificaciones;\nIII. Narración expresa de los hechos en que se basa la denuncia;\nIV. Ofrecer y exhibir las pruebas con que se cuente; o en su caso, mencionar las que habrán de requerirse, por no tener posibilidad de recabarlas, y\nV. En su caso, las medidas cautelares y de protección que se soliciten. plazo no mayor a veinticuatro horas posteriores a su recepción; tal resolución deberá ser confirmada por escrito y se informará al Tribunal Electoral, para su conocimiento.\nLa Unidad Técnica de lo Contencioso desechará la denuncia cuando:\nI. No se aporten u ofrezcan pruebas.\nLey Electoral del Estado de Baja California. Página 135\n.\nActualización Legislativa.\nÚltima reforma P. O. No. 60, Índice, 03-Oct-2025\nII. Sea notoriamente frívola o improcedente.\nCuando la Unidad Técnica de lo Contencioso admita la denuncia, emplazará a las partes, para que comparezcan a una audiencia de pruebas y alegatos, que tendrá lugar dentro del plazo de cuarenta y ocho horas posteriores a la admisión. En el escrito respectivo se le informará a la persona denunciada de la infracción que se le imputa y se le correrá traslado de la denuncia con sus anexos.\nEn lo procedente, el desarrollo de la audiencia de pruebas y alegatos y su traslado al\nTribunal Electoral, se desarrollarán conforme lo dispuesto en los artículos 378 y 379 de esta\nLey.\nArtículo Adicionado\nArtículo 374.- La denuncia deberá reunir los siguientes requisitos:\nI. Nombre del quejoso o denunciante, con firma autógrafa o huella digital;\nII. Domicilio para oír y recibir notificaciones;\nIII. Los documentos que sean necesarios para acreditar la personería;\nIV. Narración expresa y clara de los hechos en que se basa la denuncia;\nV. Ofrecer y exhibir las pruebas con que se cuente; o en su caso, mencionar las que habrán de requerirse, por no tener posibilidad de recabarlas, y\nVI. En su caso, las medidas cautelares que se soliciten.\nEl órgano del Instituto que reciba o promueva la denuncia la remitirá inmediatamente a la Unidad Técnica de lo Contencioso, para que ésta la examine junto con las pruebas aportadas.\nLa unidad Técnica de lo Contencioso informará al Tribunal Electoral, por la vía más expedita, de la denuncia presentada, remitiendo copia de la misma y sus anexos.\nPárrafo Adicionado\nArtículo Reformado\nArtículo 375.- La denuncia será desechada de plano por la Unidad Técnica de lo\nContencioso, sin prevención alguna, cuando:\nI. No reúna los requisitos indicados en el artículo anterior;\nII. Los hechos denunciados no constituyan una violación en materia de propaganda político-electoral;\nIII. El denunciante no aporte ni ofrezca prueba alguna de sus dichos, o\nIV. La queja o denuncia sea evidentemente frívola.\nArtículo 376.- La Unidad Técnica de lo Contencioso deberá admitir o desechar la denuncia en un plazo no mayor a veinticuatro horas posteriores a su recepción. En caso de desechamiento, notificará a la persona denunciante, su resolución, por el medio más\nLey Electoral del Estado de Baja California. Página 136\n.\nActualización Legislativa.\nÚltima reforma P. O. No. 60, Índice, 03-Oct-2025 expedito a su alcance dentro del plazo de doce horas; tal resolución deberá ser confirmada por escrito y se informará al Tribunal Estatal, para su conocimiento.\nArtículo Reformado\nArtículo 377.- Cuando la Unidad Técnica de lo Contencioso admita la denuncia, emplazará a la persona denunciante y a la persona denunciada para que comparezcan a una audiencia de pruebas y alegatos, que tendrá lugar dentro del plazo de cuarenta y ocho horas posteriores a la admisión. En el escrito respectivo se le informará a la persona denunciada de la infracción que se le imputa y se le correrá traslado de la denuncia con sus anexos.\nPárrafo Reformado\nSi la Unidad Técnica de lo Contencioso considera necesaria la adopción de medidas cautelares, las propondrá a la Comisión de Quejas y Denuncias dentro del mismo plazo de cuarenta y ocho horas, en los términos establecidos en la fracción II del artículo 368 de esta\nLey. Esta decisión podrá ser impugnada ante el Tribunal Electoral.\nArtículo Reformado\nArtículo 377 BIS.- Las medidas cautelares que podrán ser ordenadas por infracciones que constituyan violencia política contra las mujeres en razón de género, son las siguientes:\nI. Realizar análisis de riesgos y un plan de seguridad;\nII. Retirar la campaña violenta contra la víctima, haciendo públicas las razones;\nIII. Cuando la conducta sea reiterada por lo menos en una ocasión, suspender el uso de las prerrogativas asignadas a la persona agresora;\nIV. Ordenar la suspensión del cargo partidista, de la persona agresora, y\nV. Cualquier otra requerida para la protección de la mujer víctima, o quien ella solicite.\nArtículo Adicionado\nArtículo 378.- La audiencia de pruebas y alegatos se llevará a cabo de manera ininterrumpida, en forma oral y será conducida por la Unidad Técnica de lo Contencioso, debiéndose levantar constancia de su desarrollo. técnica, esta última será desahogada siempre y cuando la persona oferente aporte los medios para tal efecto en el curso de la audiencia.\nPárrafo Reformado día y hora señalados. La audiencia se desarrollará en los siguientes términos:\nLey Electoral del Estado de Baja California. Página 137\n.\nActualización Legislativa.\nÚltima reforma P. O. No. 60, Índice, 03-Oct-2025\nI. Abierta la audiencia, se dará el uso de la voz a la persona denunciante a fin de que, en una intervención no mayor a treinta minutos, resuma el hecho que motivó la denuncia y haga una relación de las pruebas que a su juicio la corroboran. En caso de que el procedimiento se haya iniciado en forma oficiosa la Unidad Técnica de lo Contencioso actuará como denunciante;\nFracción Reformada\nII. Acto seguido, se dará el uso de la voz a la persona denunciada, a fin de que, en un tiempo no mayor a treinta minutos, responda a la denuncia, ofreciendo las pruebas que a su juicio desvirtúen la imputación que se realiza;\nFracción Reformada\nIII. La Unidad Técnica de lo Contencioso resolverá sobre la admisión de pruebas y acto seguido procederá a su desahogo, y\nIV. Concluido el desahogo de las pruebas, la Unidad Técnica de lo Contencioso\nElectoral concederá en forma sucesiva el uso de la voz a la persona denunciante y a la persona denunciada, o a sus representantes, quienes podrán alegar en forma escrita, o verbal por una sola vez y en tiempo no mayor a quince minutos cada uno.\nFracción Reformada\nArtículo Reformado\nArtículo 379.- Celebrada la audiencia, la Unidad Técnica de lo Contencioso deberá turnar de forma inmediata el expediente completo, exponiendo en su caso, las medidas cautelares y demás diligencias que se hayan llevado a cabo, al Tribunal Electoral, así como un informe circunstanciado.\nEl informe circunstanciado deberá contener por lo menos, lo siguiente:\nI. La relatoría de los hechos que dieron motivo a la queja o denuncia;\nII. Las diligencias que se hayan realizado por la autoridad;\nIII. Las pruebas aportadas por las partes;\nIV. Las demás actuaciones realizadas, y\nV. Las conclusiones sobre la queja o denuncia.\nDenuncias del Instituto para su conocimiento.\nArtículo 380.- Será competente para resolver sobre el procedimiento especial sancionador referido en el presente Capitulo, el Tribunal Electoral.\nArtículo 381.- Recibido el expediente en el Tribunal Electoral, la presidencia de éste lo asignará preliminarmente a una Magistrada o Magistrado del Pleno, para que dentro de resultado, para proceder al turno correspondiente.\nPárrafo Reformado\nLey Electoral del Estado de Baja California. Página 138\n.\nActualización Legislativa.\nÚltima reforma P. O. No. 60, Índice, 03-Oct-2025\nLa Ponencia correspondiente, una vez decretado el turno, deberá:\nPárrafo Reformado\nI. Radicar la denuncia, pronunciándose sobre el cumplimiento por parte del Instituto, de los requisitos previstos en esta Ley.\nII. Si advierte que el expediente está debidamente integrado, emitirá el acuerdo respectivo y dentro de los seis días posteriores a su turno, deberá poner a consideración del\nPleno del Tribunal, el proyecto de resolución que resuelva el procedimiento especial sancionador.\nIII. Si advierte omisiones o deficiencias en la integración del expediente o en su tramitación, así como violación a las reglas establecidas en esta Ley, deberá ordenar al\nInstituto la realización de diligencias para mejor proveer, determinando las que deban realizarse y el plazo para llevarlas a cabo, las cuales deberá desahogar en la forma más expedita. Asimismo, la ponencia respectiva podrá emitir los proveídos que se requieran para la debida integración del expediente.\nIV. Una vez devuelto el expediente por la autoridad administrativa electoral, la ponencia correspondiente revisará el cumplimiento de las diligencias ordenadas para mejor proveer.\nDe persistir la violación procesal, podrá emitir nuevo requerimiento, o en su caso, corresponderá a la Ponencia el desahogo de las diligencias faltantes. Lo anterior, con independencia de la responsabilidad administrativa su caso pudiera exigirse a las o los servidores públicos electorales.\nPárrafo Reformado\nLa ponencia correspondiente procederá con amplias facultades para llevar a cabo las diligencias para mejor proveer que se deriven de las omisiones e irregularidades que se adviertan en la reposición del procedimiento, así como para el desahogo de diligencias que se deriven de datos nuevos que éstas arrojen.\nFracción Reformada\nV. El Pleno en sesión pública, resolverá el asunto en un plazo de veinticuatro horas contadas a partir de que se haya distribuido el proyecto de resolución.\nArtículo Reformado\nArtículo 382.- Las sentencias que resuelvan el procedimiento especial sancionador podrán tener los efectos siguientes:\nI. Declarar la inexistencia de la violación objeto de la queja o denuncia y, en su caso, revocar las medidas cautelares que se hubieren impuesto, o\nII. Imponer las sanciones que resulten procedentes en términos de lo dispuesto en esta Ley.\nLey Electoral del Estado de Baja California. Página 139\n.\nActualización Legislativa.\nÚltima reforma P. O. No. 60, Índice, 03-Oct-2025\nArtículo 382 BIS.- En la resolución de los procedimientos sancionadores, por violencia política en contra de las mujeres por razón de género, la autoridad resolutora deberá considerar ordenar las medidas de reparación integral que correspondan considerando al menos las siguientes:\nI. Indemnización de la víctima;\nII. Restitución inmediata en el cargo al que fue obligada a renunciar por motivos de violencia;\nIII. Disculpa pública, y\nIV. Medidas de no repetición.\nArtículo Adicionado\nArtículo 383.- Cuando las denuncias a que se refiere este Capítulo tengan como motivo la comisión de conductas referidas a la ubicación física o al contenido de propaganda política o electoral impresa, de aquélla pintada en bardas, o de cualquier otra diferente a la transmitida por radio o televisión, así como cuando se refieran a actos anticipados de precampaña o campaña en que la conducta infractora esté relacionada con ese tipo de propaganda se estará a lo siguiente:\nI. La denuncia será presentada ante el Consejero Presidente del Consejo Distrital del Instituto que corresponda a la demarcación territorial en donde haya ocurrido la conducta denunciada o del cargo que se elija, y deberá reunir en lo conducente los requisitos señalados en el artículo 374 de la presente Ley.\nII. El Consejero Presidente del Consejo Distrital ejercerá, en lo conducente, las facultades señaladas en la presente sección para la Unidad Técnica de lo Contencioso, conforme al procedimiento y dentro de los plazos que se señalan en la misma, y\nIII. Celebrada la audiencia, el Consejero Presidente deberá turnar al Tribunal\nElectoral, de forma inmediata, el expediente completo, exponiendo las medidas cautelares y demás diligencias que se hayan llevado a cabo así como un informe circunstanciado en términos de lo dispuesto en esta Ley.\nArtículo 384.- Durante el procedimiento, el Consejo Distrital en el ámbito territorial que le corresponda, podrá imponer, entre otras medidas cautelares la orden del retiro de la propaganda, para lo cual al admitir la denuncia o tener conocimiento de los hechos, procederá en los siguientes términos:\nI. Verificara los hechos, por conducto del Secretario Fedatario del Consejo\nDistrital, quien deberá levantar el acta correspondiente;\nII. De resultar ciertos los hechos, notificará al partido político o coalición para que en un plazo de veinticuatro horas manifieste lo que a su derecho convenga;\nLey Electoral del Estado de Baja California. Página 140\n.\nActualización Legislativa.\nÚltima reforma P. O. No. 60, Índice, 03-Oct-2025\nIII. Recibida la contestación o vencido el plazo a que se refiere la fracción anterior, el Consejero Presidente someterá a la aprobación del Consejo Distrital el proyecto de resolución respecto a la medida cautelar solicitada; y\nIV. De ordenarse el retiro de la propaganda, el partido político o coalición contará con un plazo de veinticuatro horas para ello. En caso de incumplimiento, el Consejero\nPresidente del Consejo Distrital, solicitará a la autoridad municipal el retiro inmediato; el costo que determine la autoridad municipal se deducirá del financiamiento público estatal del partido político o coalición responsable.\nEl resultado del procedimiento anterior, se informará a la Secretaría Ejecutiva, para los efectos conducentes.\nArticulo 385.- En los casos de denuncias o quejas dentro del proceso electoral, que sean competencia de los Consejos Distritales, y que estos no estuvieren instalados, corresponderá a la Unidad Técnica de lo Contencioso la tramitación correspondiente.\nTÍTULO SEGUNDO\nResponsabilidades de los servidores públicos del\nInstituto Electoral\nCAPÍTULO PRIMERO\nDe las responsabilidades administrativas\nArtículo 386.- Para los efectos de esta Ley, se consideran servidores públicos del\nInstituto Electoral los Consejeros Presidentes, Consejeros Electorales, Secretarios\nFedatarios de los Consejos Distritales, el Secretario Ejecutivo, los jefes de departamento, los funcionarios y empleados, y en general, toda persona que desempeñe un empleo, cargo o comisión de cualquier naturaleza en el Instituto, quienes serán responsables por los actos u omisiones en que incurran en el desempeño de sus respectivas funciones.\nLos Consejeros Electorales Estatales estarán sujetos al régimen de responsabilidades de los servidores públicos en los términos del Título Cuarto de la Constitución Política de los\nEstados Unidos Mexicanos y solo podrán ser removidos de su cargo de conformidad con lo dispuesto por la Ley General de Instituciones y Procedimientos Electorales.\nLos servidores públicos integrantes del Servicio Profesional Electoral Local, estarán\nEstatuto del Servicio Profesional Electoral respectivo. referidos en el artículo anterior, así como aplicar las sanciones en los términos dispuestos en el presente Título.\nArtículo 388.- Serán causas de responsabilidad para los servidores públicos del\nInstituto Electoral:\nLey Electoral del Estado de Baja California. Página 141\n.\nActualización Legislativa.\nÚltima reforma P. O. No. 60, Índice, 03-Oct-2025\nI. Realizar conductas que atenten contra la independencia de la función electoral, o cualquier acción que genere o implique subordinación respecto de terceros;\nII. Tener notoria negligencia, ineptitud o descuido en el desempeño de las funciones o labores que deban realizar;\nIII. No cumplir o preservar los principios que rigen el funcionamiento del Instituto\nElectoral en el desempeño de sus labores;\nIV. Aceptar empleo, cargo o comisión que resulte incompatible con su función;\nV. Utilizar los recursos asignados para un fin distinto;\nVI. Manifestar públicamente su inclinación o animadversión por algún partido político, coalición o sus candidatos;\nVII. Inmiscuirse indebidamente en cuestiones que competan a otros órganos del\nInstituto Electoral;\nVIII. Dejar de asistir hasta en dos ocasiones a las sesiones del Consejo del que forme parte, en un periodo de treinta días, si causa suficientemente justificada;\nIX. Utilizar indebidamente para sí o por interpósita persona, la documentación e información que por razón de su función, conozca o conserve bajo sus cuidados o a la cual tenga acceso, así como sustraer, destruir, ocultar o inutilizar la misma;\nX. Conocer de algún asunto o participar en algún acto para el cual se encuentren impedidos;\nXI. Realizar nombramientos, promociones o ratificaciones infringiendo las disposiciones generales correspondientes;\nXII. No poner en conocimiento del Consejo General del Instituto Electoral todo acto tendiente a vulnerar la independencia de la función electoral;\nXIII. Emitir opinión pública que implique prejuzgar sobre un asunto de su conocimiento;\nXIV. Dejar de desempeñar las funciones o las labores que tenga a su cargo;\nXV. Las previstas, en lo conducente, en los artículos 46 y 47 de la Ley de\nResponsabilidades de los Servidores Públicos del Estado de Baja California, y\nXVI. Las demás que determine la presente Ley y los ordenamientos que resulten aplicables.\nCAPÍTULO SEGUNDO\nArtículo 389.- El procedimiento para determinar las responsabilidades de los petición de parte, por queja o denuncia, presentada por cualquier persona, por el servidor\nLey Electoral del Estado de Baja California. Página 142\n.\nActualización Legislativa.\nÚltima reforma P. O. No. 60, Índice, 03-Oct-2025 público que tenga conocimiento de los hechos o, en su caso por el Ministerio Público. Las responsabilidades administrativas a que se refiere este artículo, prescribirán en tres años; plazo que se interrumpe con el inicio del procedimiento sancionador respectivo.\nCuando la responsabilidad se atribuya al Consejero Presidente y Consejeros\nElectorales del Consejo General, o a cualquier servidor público integrante del Servicio\nProfesional Electoral Local, la queja, denuncia o investigación correspondiente se remitirá al\nInstituto Nacional Electoral para los efectos conducentes.\nArtículo 390.- A falta de disposición expresa en el presente capítulo, serán de aplicación supletoria, en lo conducente, la Ley de Responsabilidades Administrativa del\nEstado de Baja California.\nArtículo Reformado\nArtículo 391.- Para el cumplimiento de sus atribuciones, la Comisión de Control\nInterno, a través del Departamento de Control Interno, podrá llevar a cabo investigaciones debidamente motivadas o auditorías respecto de las conductas de los servidores públicos que puedan constituir responsabilidades administrativas, para lo cual éstos, deberán proporcionar la información y documentación que le sean requeridas.\nArtículo 392.- Las quejas o denuncias que se presenten de oficio o a petición de parte, deberán estar apoyadas en elementos probatorios suficientes para establecer la existencia de la infracción y presumir la responsabilidad del servidor público denunciado. No serán admisibles quejas o denuncias anónimas.\nArtículo 393.- Son causas de improcedencia o sobreseimiento de la queja o denuncia, las siguientes:\nI. De improcedencia, cuando:\na) Se trate de actos u omisiones imputados a una misma persona que hayan sido materia de otra queja o denuncia ante la Comisión de Control Interno y que cuenten con resolución definitiva;\nb) Se denuncien actos u omisiones de los que la Comisión de Control Interno resulte incompetente para conocer, y\nc) Los actos u omisiones denunciados no constituyan causas de responsabilidad en los términos de este ordenamiento.\nII. De sobreseimiento, cuando:\na) Habiendo sido recibida la queja o denuncia, sobrevenga una causa de improcedencia, y\nb) Cuando el denunciante presente escrito de desistimiento, siempre y cuando se exhiba antes de que se dicte resolución. En ningún caso procederá el sobreseimiento cuando se trate de infracciones graves. será de oficio.\nLey Electoral del Estado de Baja California. Página 143\n.\nActualización Legislativa.\nÚltima reforma P. O. No. 60, Índice, 03-Oct-2025\nArtículo 394.- La recepción, trámite y resolución de las quejas y denuncias que se presenten en contra de cualquier servidor público del Instituto Electoral, por incumplimiento de sus obligaciones, se sujetará a las siguientes normas:\nI. Deberán presentarse por escrito ante la Comisión de Control Interno; si encuadra en alguna de las causas de improcedencia y sobreseimiento referidas en el artículo anterior, dictará el acuerdo correspondiente;\nII. La investigación administrativa, se iniciará de oficio, mediante queja o denuncia que se haga por parte de cualquier persona o como resultado de las revisiones o auditorías que se practiquen por la autoridad competente;\nIII. En el auto de inicio se ordenará la práctica de todas las diligencias necesarias tendientes a la integración de la investigación administrativa correspondiente, recabando los medios de prueba que sean bastantes y suficientes y la práctica de diligencias, inclusive de aquellas necesarias para la integración de la misma, constituyendo ambas fases el período de investigación administrativa;\nIV. Concluida la etapa de investigación administrativa y de existir elementos suficientes que establezcan la presunción de que el acto u omisión constituye una infracción administrativa y la presunta responsabilidad del servidor público por incumplimiento en las obligaciones y prohibiciones establecidas en la presente Ley, se iniciará el procedimiento previsto en el artículo siguiente; en caso contrario la Comisión de Control Interno dictará el acuerdo de no inicio de procedimiento administrativo y se archivará el asunto como totalmente concluido, y\nV. El acuerdo de inicio de procedimiento, improcedencia, sobreseimiento, o de no inicio, deberá notificarse al quejoso o a la autoridad por la cual se haya tenido conocimiento de la queja o denuncia.\nArtículo 395.- El procedimiento administrativo de responsabilidad estará a cargo del\nDepartamento de Control Interno y se sujetará, además de las normas previstas en el artículo anterior, a lo siguiente:\nI. Se iniciará con el acuerdo que dicte la Comisión de Control Interno, teniendo por radicada la queja, el acta administrativa o el instrumento correspondiente en el que consten los hechos que presuman la responsabilidad administrativa;\nII. El Departamento de Control Interno, citará al presunto responsable a una audiencia, haciéndole saber la responsabilidad o responsabilidades que se le imputen, el lugar, día y hora en que tendrá verificativo dicha audiencia, y su derecho a ofrecer pruebas y alegar en la misma lo que a su derecho convenga, por sí o por medio de un defensor. Entre quince días hábiles;\nIII. El Departamento de Control Interno, dentro de los dos días siguientes a que concluya la audiencia referida en la fracción anterior, deberá calificar las pruebas, Ley Electoral del Estado de Baja California. Página 144\n.\nActualización Legislativa.\nÚltima reforma P. O. No. 60, Índice, 03-Oct-2025 diligencia para ello; mismas que deberán desahogarse en un plazo no mayor de treinta días naturales;\nIV. Si del resultado de la audiencia no se desprenden elementos suficientes para resolver o se advierten otros que impliquen nueva responsabilidad administrativa a cargo del presunto responsable o de otras personas, se podrá disponer la práctica de investigaciones y acordar, en su caso, la celebración de otra u otras diligencias, y\nV. Cuando no existan pruebas pendientes de desahogo, el Departamento de Control\nInterno declarará cerrado el periodo de instrucción, y procederá a remitir el expediente a la\nComisión de Control Interno quien dictara la resolución dentro de los veinte días naturales siguientes, sobre la existencia o no de responsabilidad administrativa, y en su caso, impondrá al servidor público responsable la sanción que corresponda.\nLa audiencia establecida en la fracción II de este artículo, será privada. La resolución que se emita se notificará de manera personal al servidor público sujeto a procedimiento, y por oficio al órgano que corresponda cumplimentar las resoluciones.\nArtículo 396.- Con excepción del Secretario Ejecutivo, Consejeros Presidentes y\nConsejeros Electorales de los Consejos Distritales, la Comisión de Control Interno podrá determinar la suspensión temporal del presunto responsable de su cargo, empleo o comisión, siempre que así convenga para la conducción o continuación de las investigaciones y se trate de conductas graves; la suspensión cesará cuando así lo resuelva la propia Comisión de Control Interno. La suspensión temporal no prejuzga sobre la responsabilidad que se impute al servidor público, lo cual se hará constar expresamente en la resolución respectiva.\nSi el servidor público suspendido temporalmente no resultare responsable de la falta que se le imputa, será restituido en el goce de sus derechos y se le cubrirán las percepciones que debió haber recibido durante el tiempo suspendido.\nArtículo 397.- Cuando se compruebe la existencia de la infracción motivo de la denuncia, la Comisión de Control Interno impondrá la sanción que corresponda y dictará las medidas para su corrección o remedio inmediato.\nArtículo 398.- Las sanciones que podrá imponer la Comisión de Control Interno, atendiendo a la gravedad de la falta, consistirán en:\nI. Amonestación privada o pública;\nII. Sanción económica o pecuniaria, en los términos de la Ley de\nResponsabilidades de los Servidores Públicos, aplicable en el Estado;\nIII. Suspensión del encargo hasta por sesenta días, sin goce de salario o contraprestación que reciba con motivo de su encargo; propuesta de la Comisión de Control Interno, sobre la aplicación de las sanciones de los Servidores Públicos de aplicación en el Estado.\nLey Electoral del Estado de Baja California. Página 145\n.\nActualización Legislativa.\nÚltima reforma P. O. No. 60, Índice, 03-Oct-2025\nEl Consejo General del Instituto Electoral podrá modificar la propuesta de la Comisión de Control Interno ordenando en su caso la imposición de cualquiera de las sanciones contempladas en la fracciones I, II y III.\nArtículo 399.- Las faltas serán valoradas y, en su caso sancionadas, de conformidad con los criterios establecidos, en lo conducente, en la Ley de Responsabilidades de los\nServidores Públicos de aplicación en el estado.\nEn todo caso, se considerarán como faltas graves, el incumplimiento a lo dispuesto por las fracciones IV, V, X, y XVI del artículo 46, el incumplimiento a lo dispuesto por las fracciones II, IV, V, VI, VII, VIII, IX, XIII y XVI del artículo 47, ambos de la Ley de\nResponsabilidades de los Servidores Públicos de aplicación en el estado, así como las causas señaladas en las fracciones I a la VI, IX y XI, del artículo 388 de esta Ley.\nArtículo 400.- La ejecución de las sanciones previstas en el artículo 398 de esta Ley, se realizará de la siguiente manera:\nI.- La amonestación, ya sea pública o privada, y la inhabilitación en todos los casos, serán aplicadas por el Presidente de la Comisión de Control Interno;\nII.- Las correspondientes a las de sanción económica o pecuniaria, suspensión del encargo y destitución del puesto, se aplicarán por:\na) El Consejero Presidente del Consejo General, cuando el servidor público sancionado sea:\n1. Consejeros electorales de los Consejos Distritales;\n2. Consejero Presidente o Secretario Fedatario de algún Consejo Distrital\nElectoral;\n3. Secretario Ejecutivo del Instituto Electoral;\n4. Demás personal adscrito a las oficinas del Consejo General.\nb) El Secretario Ejecutivo del Instituto Electoral, cuando el servidor público sancionado esté adscrito a éste;\nc) El Presidente de la Comisión de Control Interno, cuando se trate de personal a su cargo.\nIII.- El Presidente de la Comisión de Control Interno podrá ejecutar las sanciones impuestas, cuando quien esté obligado a hacerlo en los términos de la fracción que antecede no lo haga, sin perjuicio de la sanción que corresponda.\nLa ejecución de las sanciones se realizará de inmediato por ser de orden público, en los términos de las resoluciones que las contengan. quien deba ejecutarla, debiendo dar cuenta este último del cumplimiento a lo ordenado, con las constancias respectivas.\nLey Electoral del Estado de Baja California. Página 146\n.\nActualización Legislativa.\nÚltima reforma P. O. No. 60, Índice, 03-Oct-2025\nLa ejecución de la suspensión temporal a que se refiere el artículo 396 de esta Ley, se llevará a cabo por quien está facultado para ejecutar la sanción prevista en la fracción III del artículo 398.\nLas resoluciones por las que se impongan sanciones administrativas podrán ser impugnadas a través del recurso de inconformidad previsto en esta Ley.\nCAPÍTULO TERCERO\nDisposiciones complementarias\nArtículo 401.- La Comisión de Control Interno del Consejo General, para los efectos de esta Ley y la Ley de Responsabilidades de los Servidores Públicos de aplicación en el estado, es el órgano de control interno del Instituto Electoral, con las funciones y atribuciones que de ellas deriven.\nArtículo 402.- El Titular del Departamento de Control Interno fungirá como Secretario\nTécnico de la Comisión de Control Interno, contará con el personal necesario para el ejercicio de sus funciones. En su desempeño la Comisión y el Departamento de Control\nInterno se sujetarán a los principios de imparcialidad, legalidad, objetividad, certeza, honestidad, exhaustividad y transparencia.\nArtículo 403.- Corresponde al Departamento de Control Interno, recibir y resguardar las declaraciones patrimoniales que deban presentar los servidores públicos del Instituto\nElectoral, a partir del nivel de jefe de departamento, conforme a los formatos y procedimientos que establezca la propia Comisión de Control Interno. Serán aplicables en lo conducente las normas establecidas en la Ley de Responsabilidad aplicable.\nArtículo 404.- El Titular del Departamento de Control Interno deberá intervenir en los procesos de entrega y recepción por inicio o conclusión de encargo de los servidores públicos que corresponda.\nArtículo 405.- Los servidores públicos del Instituto Electoral estarán obligados a proporcionar la información, permitir la revisión y atender los requerimientos que les presente la Comisión o el Departamento de Control Interno, sin que dicha revisión interfiera u obstaculice el ejercicio de las funciones o atribuciones que esta Ley les confieren.\nArtículos Transitorios\nPrimero.- La presente Ley entrará en vigor al día siguiente de su publicación en el\nPeriódico Oficial del Estado.\nSegundo.- Se abroga la Ley de Instituciones y Procedimientos Electorales de Baja como sus reformas y adiciones.\nLey Electoral del Estado de Baja California. Página 147\n.\nActualización Legislativa.\nÚltima reforma P. O. No. 60, Índice, 03-Oct-2025\nTercero.- En el caso, de que al inicio de vigencia de la presente Ley, aun no se hubiera instalado el Instituto Estatal Electoral conforme el Decreto 112 mediante el cual se reforman diversas disposiciones de la Constitución del Estado, publicado en el Periódico\nOficial del Estado el 17 de octubre de 2014, las menciones que en esta Ley se hacen en relación al Instituto Estatal Electoral, se entenderán hechas al Instituto Electoral y de\nParticipación Ciudadana del Estado.\nCuarto. El personal del Instituto Electoral y de Participación Ciudadana que con motivo del presente Decreto deba ser objeto de cambios en su adscripción de trabajo, conservará sus derechos laborales, con las previsiones siguientes:\nI. La Dirección General del Instituto Electoral y de Participación Ciudadana y el\nSecretario Fedatario del Consejo General, una vez designado el Secretario Ejecutivo, deberán de manera inmediata entregar a éste, los archivos, bienes y recursos materiales que tenga asignados.\nII. La Dirección Ejecutiva del Registro Estatal de Electores, vigente con motivo de la Ley que se abroga, deberá una vez instalado el Instituto Estatal Electoral, entregar los archivos, bienes y recursos materiales de la misma, al Consejero Presidente del Consejo\nGeneral Electoral.\nIII. Las Direcciones Ejecutivas de Proceso Electorales, de Administración, de\nInformática y Estadística Electoral, vigentes con motivo de la Ley que se abroga, deberán en un plazo de cinco días contados a partir de la instalación del Instituto Estatal Electoral, entregar los archivos, bienes y recursos materiales de las mismas, al Secretario Ejecutivo del Instituto.\nEl Consejero Presidente del Consejo General, bajo su más estricta responsabilidad, garantizará el cumplimiento de este artículo.\nQuinto.- La conformación de la estructura orgánica del Instituto Estatal Electoral que dispone esta Ley, se hará a partir de su instalación en términos del transitorio tercero.\nSexto.- Hasta en tanto el Instituto Nacional Electoral emita el Estatuto del Servicio cargos y puestos del personal ejecutivo y técnico, así como los requisitos de selección, ingreso, capacitación, profesionalización, promoción, evaluación, rotación, permanencia y disciplina, el Instituto Estatal aplicará la estructura orgánica prevista en el Libro Tercero de esta Ley.\nSéptimo.- El Consejo General del Instituto Estatal dictará los acuerdos necesarios\nLey Electoral del Estado de Baja California. Página 148\n.\nActualización Legislativa.\nÚltima reforma P. O. No. 60, Índice, 03-Oct-2025\nLas disposiciones generales emitidas por el Instituto Electoral y de Participación\nCiudadana del Estado, con antelación a la entrada en vigor de este Decreto seguirán vigentes, en lo que no se opongan a la Constitución del Estado y la presente Ley.\nOctavo.- Lo dispuesto en el párrafo in fine del artículo 152 de esta Ley, en relación con los informes de labores o de gestión de los servidores públicos, estará vigente hasta en tanto no se expida y entre en vigor la Ley Reglamentaria del párrafo octavo del artículo 134 de la Constitución General de la República, que con carácter de general expida el Congreso de la Unión.\nNoveno.- Los medios de impugnación, denuncias o quejas que a la entrada en vigor del presente Decreto se encuentren en trámite, deberán substanciarse o resolverse conforme a la Ley que se abroga.\nDécimo.- Los asuntos que se encuentren en trámite a la entrada en vigor del presente\nDecreto, serán resueltos conforme a las normas vigentes al momento de su inicio.\nDécimo Primero.- Para la elección de 2016, los recursos de revisión previstos en esta Ley, se resolverán conforme a los siguientes plazos:\nI. A más tardar el 30 de julio del año de la elección, tratándose de la elección de diputados por el principio de mayoría relativa;\nII. Dentro de los 12 días siguientes a aquel en que fue recibido por el Tribunal\nElectoral, cuando se impugne el cómputo de la elección de diputados por el principio de representación proporcional y la asignación que realice el Consejo General;\nIII. A más tardar el 15 de septiembre del año de la elección, cuando se impugne la elección de munícipes;\nIV. Dentro de los 15 días siguientes a aquel en que fue recibido por el Tribunal\nElectoral, cuando se impugne la asignación de munícipes por el principio de representación proporcional, y\nV. En todos los demás supuestos, dentro de los 30 días siguientes a aquel en que fue recibido por el Tribunal Electoral.\nDécimo Segundo.- La presente Ley será aplicable en cuanto no se oponga con los periodos, plazos y fechas dispuestos en los artículos transitorios sexto, séptimo y octavo de referente a la concurrencia de elecciones locales y federales; reformado mediante Decreto\nNo. 112, publicado en el Periódico Oficial del Estado No. 50 Tomo CXXI de fecha 17 de\nDécimo Tercero.- Se derogan todas las disposiciones que se opongan al presente\nDecreto.\nLey Electoral del Estado de Baja California. Página 149\n.\nActualización Legislativa.\nÚltima reforma P. O. No. 60, Índice, 03-Oct-2025\nDADO en el Salón de Sesiones “Lic. Benito Juárez García” del H. Poder Legislativo del Estado de Baja California, en la Ciudad de Mexicali, B.C., a los once del mes de junio del año dos mil quince.\nDIP. JULIO CÉSAR VÁZQUEZ CASTILLO\nPRESIDENTE\n(RUBRICA)\nDIP. RODOLFO OLIMPO HERNÁNDEZ BOJÓRQUEZ\nSECRETARIA\n(RUBRICA)\nDE CONFORMIDAD CON LO DISPUESTO POR LA FRACCION I DEL ARTÍCULO 49\nMEXICALI, BAJA CALIFORNIA, A LOS DOCE DÍAS DEL MES DE JUNIO DEL AÑO\nDOS MIL QUINCE.\nFRANCISCO RUEDA GOMEZ\nSECRETARIO GENERAL DE GOBIERNO\nEn suplencia por la ausencia del Gobernador del Estado, con fundamento en el artículo 45 y 52 fracción II, de la\n(RÚBRICA)\nLORETO QUINTERO QUINTERO\nOFICIAL MAYOR DE GOBIERNO\nEn suplencia del Secretario General de Gobierno, Con fundamento en el artículo 54 de la Constitución Política\n(RÚBRICA)\nLey Electoral del Estado de Baja California. Página 150\n.\nActualización Legislativa.\nÚltima reforma P. O. No. 60, Índice, 03-Oct-2025\nARTÍCULO 1.- Fue reformado por Decreto No. 102, publicado en el Periódico Oficial\nNo. 54, de fecha 02 de septiembre de 2020, Tomo CXXVII, NÚMERO ESPECIAL, expedido por la H. XXIII Legislatura, siendo Gobernador Constitucional el C. Jaime Bonilla Valdez, 2019-2021; fue reformado por Decreto No. 262, publicado en el Periódico Oficial No. 42, Número Especial, de fecha 19 de julio de 2023, Tomo CXXIX, expedido por la H. XXIV\nLegislatura, siendo Gobernadora Constitucional la C. Marina del Pilar Ávila Olmeda, 20212027;\nARTÍCULO 2.- Fue reformado por Decreto No. 102, publicado en el Periódico Oficial\nNo. 54, de fecha 02 de septiembre de 2020, Tomo CXXVII, NÚMERO ESPECIAL, expedido por la H. XXIII Legislatura, siendo Gobernador Constitucional el C. Jaime Bonilla Valdez, 2019-2021;\nARTÍCULO 3.- Fue reformado por Decreto No. 102, publicado en el Periódico Oficial\nNo. 54, de fecha 02 de septiembre de 2020, Tomo CXXVII, NÚMERO ESPECIAL, expedido por la H. XXIII Legislatura, siendo Gobernador Constitucional el C. Jaime Bonilla Valdez, 2019-2021; fue reformado por Decreto No. 262, publicado en el Periódico Oficial No. 42, Número Especial, de fecha 19 de julio de 2023, Tomo CXXIX, expedido por la H. XXIV\nLegislatura, siendo Gobernadora Constitucional la C. Marina del Pilar Ávila Olmeda, 20212027;\nARTÍCULO 7.- Fue reformado mediante Decreto No. 288, publicado en el Periódico\nOficial No. 52, de fecha 02 de septiembre de 2023, Número Especial, Tomo CXXX, expedido por la H. XXIV Legislatura, siendo Gobernadora Constitucional la C. Marina del Pilar Ávila\nOlmeda 2021-2027;\nARTÍCULO 8.- Fue reformado por Decreto No. 244, publicado en el Periódico Oficial\nNo. 28, de fecha 09 de junio de 2018, Tomo CXXV, NÚMERO ESPECIAL, expedido por la\nH. XXII Legislatura, siendo Gobernador Constitucional el C. Francisco Arturo Vega de\nLamadrid, 2013-2019;\nARTÍCULO 9.- Fue reformado por Decreto No. 102, publicado en el Periódico Oficial por la H. XXIII Legislatura, siendo Gobernador Constitucional el C. Jaime Bonilla Valdez, 2019-2021;\nARTÍCULO 21.- Fue reformado por Decreto No. 244, publicado en el Periódico Oficial\nH. XXII Legislatura, siendo Gobernador Constitucional el C. Francisco Arturo Vega de\nLamadrid, 2013-2019; fue reformado por Decreto No. 102, publicado en el Periódico Oficial por la H. XXIII Legislatura, siendo Gobernador Constitucional el C. Jaime Bonilla Valdez, Ley Electoral del Estado de Baja California. Página 151\n.\nActualización Legislativa.\nÚltima reforma P. O. No. 60, Índice, 03-Oct-2025\n2019-2021; fue reformado por Decreto No. 262, publicado en el Periódico Oficial No. 42, Número Especial, de fecha 19 de julio de 2023, Tomo CXXIX, expedido por la H. XXIV\nLegislatura, siendo Gobernadora Constitucional la C. Marina del Pilar Ávila Olmeda, 20212027; fue reformado mediante Decreto No. 288, publicado en el Periódico Oficial No. 52, de fecha 02 de septiembre de 2023, Número Especial, Tomo CXXX, expedido por la H. XXIV\nLegislatura, siendo Gobernadora Constitucional la C. Marina del Pilar Ávila Olmeda 20212027; de conformidad con lo estipulado en su Punto Resolutivo Quinto de la Sentencia de\nAcción de Inconstitucionalidad 198/2023 y su acumulada 200/2023, notificada a este\nCongreso del Estado de Baja California en fecha 26 de febrero de 2024, mediante la cual se declara la invalidez del artículo 21, párrafo sexto, en su porción normativa ‘Las autoridades electorales sólo podrán intervenir en los asuntos internos de los partidos políticos para efecto de reposición de procedimientos por violaciones a la Constitución Federal, a su normativa interna o a derechos de la ciudadanía. En ningún caso podrán resolver nombrando dirigentes y candidatos o determinando cualquier acto que interfiera injustificadamente en forma directa en las decisiones de la vida interna de los partidos’;\nFue modificada la denominación por Decreto No. 85, publicado en el Periódico Oficial No.\n43, de fecha 24 de julio de 2020, Tomo CXXVII, Sección II, expedido por la H. XXIII\nLegislatura, siendo Gobernador Constitucional el C. Jaime Bonilla Valdez, 2019-2021;\nCAPÍTULO SEGUNDO\nDe la asignación de diputaciones de representación proporcional\nARTÍCULO 22.- Fue reformado por Decreto No. 85, publicado en el Periódico Oficial\nNo. 43, de fecha 24 de julio de 2020, Tomo CXXVII, Sección II, expedido por la H. XXIII\nLegislatura, siendo Gobernador Constitucional el C. Jaime Bonilla Valdez, 2019-2021;\nARTÍCULO 24.- Fue reformado por Decreto No. 102, publicado en el Periódico Oficial\nNo. 54, de fecha 02 de septiembre de 2020, Tomo CXXVII, NÚMERO ESPECIAL, expedido por la H. XXIII Legislatura, siendo Gobernador Constitucional el C. Jaime Bonilla Valdez, 2019-2021;\nARTÍCULO 27.- Fue reformado por Decreto No. 85, publicado en el Periódico Oficial\nLegislatura, siendo Gobernador Constitucional el C. Jaime Bonilla Valdez, 2019-2021;\nARTÍCULO 27 BIS.- Fue adicionado por Decreto No. 85, publicado en el Periódico\nXXIII Legislatura, siendo Gobernador Constitucional el C. Jaime Bonilla Valdez, 2019-2021; fue reformado mediante Decreto No. 288, publicado en el Periódico Oficial No. 52, de fecha\nLegislatura, siendo Gobernadora Constitucional la C. Marina del Pilar Ávila Olmeda 20212027;\nLey Electoral del Estado de Baja California. Página 152\n.\nActualización Legislativa.\nÚltima reforma P. O. No. 60, Índice, 03-Oct-2025\nARTÍCULO 30.- Fue reformado por Decreto No. 244, publicado en el Periódico Oficial\nNo. 28, de fecha 09 de junio de 2018, Tomo CXXV, NÚMERO ESPECIAL, expedido por la\nH. XXII Legislatura, siendo Gobernador Constitucional el C. Francisco Arturo Vega de\nLamadrid, 2013-2019; fue reformado por Decreto No. 102, publicado en el Periódico Oficial\nNo. 54, de fecha 02 de septiembre de 2020, Tomo CXXVII, NÚMERO ESPECIAL, expedido por la H. XXIII Legislatura, siendo Gobernador Constitucional el C. Jaime Bonilla Valdez, 2019-2021; fue reformado por Decreto No. 262, publicado en el Periódico Oficial No. 42, Número Especial, de fecha 19 de julio de 2023, Tomo CXXIX, expedido por la H. XXIV\nLegislatura, siendo Gobernadora Constitucional la C. Marina del Pilar Ávila Olmeda, 20212027;\nARTÍCULO 31.- Fue reformado por Decreto No. 244, publicado en el Periódico Oficial\nNo. 28, de fecha 09 de junio de 2018, Tomo CXXV, NÚMERO ESPECIAL, expedido por la\nH. XXII Legislatura, siendo Gobernador Constitucional el C. Francisco Arturo Vega de\nLamadrid, 2013-2019; fue reformado por Decreto No. 102, publicado en el Periódico Oficial\nNo. 54, de fecha 02 de septiembre de 2020, Tomo CXXVII, NÚMERO ESPECIAL, expedido por la H. XXIII Legislatura, siendo Gobernador Constitucional el C. Jaime Bonilla Valdez, 2019-2021;\nARTÍCULO 32.- Fue reformado por Decreto No. 244, publicado en el Periódico Oficial\nNo. 28, de fecha 09 de junio de 2018, Tomo CXXV, NÚMERO ESPECIAL, expedido por la\nH. XXII Legislatura, siendo Gobernador Constitucional el C. Francisco Arturo Vega de\nLamadrid, 2013-2019;\nARTÍCULO 33.- Fue reformado mediante Decreto No. 288, publicado en el Periódico\nOficial No. 52, de fecha 02 de septiembre de 2023, Número Especial, Tomo CXXX, expedido por la H. XXIV Legislatura, siendo Gobernadora Constitucional la C. Marina del Pilar Ávila\nOlmeda 2021-2027;\nARTÍCULO 35.- Fue reformado por Decreto No. 52, publicado en el Periódico Oficial\nNo. 17, de fecha 27 de marzo de 2020, Tomo CXXVII, Sección II, expedido por la H. XXIII\nLegislatura, siendo Gobernador Constitucional el C. Jaime Bonilla Valdez, 2019-2021; fue reformado por Decreto No. 102, publicado en el Periódico Oficial No. 54, de fecha 02 de septiembre de 2020, Tomo CXXVII, NÚMERO ESPECIAL, expedido por la H. XXIII\nLegislatura, siendo Gobernador Constitucional el C. Jaime Bonilla Valdez, 2019-2021; fue reformado por Decreto No. 262, publicado en el Periódico Oficial No. 42, Número Especial, Gobernadora Constitucional la C. Marina del Pilar Ávila Olmeda, 2021-2027;\nARTÍCULO 37.- Fue reformado por Decreto No. 102, publicado en el Periódico Oficial por la H. XXIII Legislatura, siendo Gobernador Constitucional el C. Jaime Bonilla Valdez, 2019-2021; fue reformado por Decreto No. 262, publicado en el Periódico Oficial No. 42, Ley Electoral del Estado de Baja California. Página 153\n.\nActualización Legislativa.\nÚltima reforma P. O. No. 60, Índice, 03-Oct-2025\nLegislatura, siendo Gobernadora Constitucional la C. Marina del Pilar Ávila Olmeda, 20212027;\nARTÍCULO 45.- Fue reformado por Decreto No. 102, publicado en el Periódico Oficial\nNo. 54, de fecha 02 de septiembre de 2020, Tomo CXXVII, NÚMERO ESPECIAL, expedido por la H. XXIII Legislatura, siendo Gobernador Constitucional el C. Jaime Bonilla Valdez, 2019-2021;\nARTÍCULO 46.- Fue reformado por Decreto No. 85, publicado en el Periódico Oficial\nNo. 43, de fecha 24 de julio de 2020, Tomo CXXVII, Sección II, expedido por la H. XXIII\nLegislatura, siendo Gobernador Constitucional el C. Jaime Bonilla Valdez, 2019-2021;\nARTÍCULO 57.- Fue reformado por Decreto No. 102, publicado en el Periódico Oficial\nNo. 54, de fecha 02 de septiembre de 2020, Tomo CXXVII, NÚMERO ESPECIAL, expedido por la H. XXIII Legislatura, siendo Gobernador Constitucional el C. Jaime Bonilla Valdez, 2019-2021;\nARTÍCULO 66.- Fue reformado por Decreto No. 52, publicado en el Periódico Oficial\nNo. 17, de fecha 27 de marzo de 2020, Tomo CXXVII, Sección II, expedido por la H. XXIII\nLegislatura, siendo Gobernador Constitucional el C. Jaime Bonilla Valdez, 2019-2021;\nARTÍCULO 68.- Fue reformado por Decreto No. 52, publicado en el Periódico Oficial\nNo. 17, de fecha 27 de marzo de 2020, Tomo CXXVII, Sección II, expedido por la H. XXIII\nLegislatura, siendo Gobernador Constitucional el C. Jaime Bonilla Valdez, 2019-2021;\nARTÍCULO 69.- Fue reformado por Decreto No. 52, publicado en el Periódico Oficial\nNo. 17, de fecha 27 de marzo de 2020, Tomo CXXVII, Sección II, expedido por la H. XXIII\nLegislatura, siendo Gobernador Constitucional el C. Jaime Bonilla Valdez, 2019-2021;\nARTÍCULO 73.- Fue reformado por Decreto No. 276, publicado en el Periódico Oficial\nNo. 60, de fecha 13 de agosto de 2021, Tomo CXXVIII, Sección IV, expedido por la H. XXIII\nLegislatura, siendo Gobernador Constitucional el C. Jaime Bonilla Valdez, 2019-2021;\nARTÍCULO 97.- Fue reformado por Decreto No. 52, publicado en el Periódico Oficial\nNo. 17, de fecha 27 de marzo de 2020, Tomo CXXVII, Sección II, expedido por la H. XXIII\nLegislatura, siendo Gobernador Constitucional el C. Jaime Bonilla Valdez, 2019-2021; De\nInconstitucionalidad 128/2020 y sus acumuladas 147/2020, 163/2020 y 228/2020 publicada siendo Gobernador Constitucional el C. Jaime Bonilla Valdez 2019-2021, mediante la cual en los términos de su Resolutivo Quinto, se declara la invalidez del Artículo 97, párrafo primero, en su porción normativa “Las y los Consejeros Electorales del Consejo General y de los\nConsejos Distritales Electorales, no tendrán derecho a las prestaciones que por ley les corresponden a los trabajadores del Instituto Estatal, salvo la atención del servicio médico en\nLey Electoral del Estado de Baja California. Página 154\n.\nActualización Legislativa.\nÚltima reforma P. O. No. 60, Índice, 03-Oct-2025 institución pública de salud”, reformado por Decreto No. 52 publicado en el Periódico Oficial\nNo. 17, de fecha 27 de marzo de 2020, Sección II, Tomo CXXVII, expedido por la H. XXIII\nLegislatura;\nARTÍCULO 103.- Fue reformado por Decreto No. 102, publicado en el Periódico\nOficial No. 54, de fecha 02 de septiembre de 2020, Tomo CXXVII, NÚMERO ESPECIAL, expedido por la H. XXIII Legislatura, siendo Gobernador Constitucional el C. Jaime Bonilla\nValdez, 2019-2021;\nARTÍCULO 112.- Fue reformado por Decreto No. 102, publicado en el Periódico\nOficial No. 54, de fecha 02 de septiembre de 2020, Tomo CXXVII, NÚMERO ESPECIAL, expedido por la H. XXIII Legislatura, siendo Gobernador Constitucional el C. Jaime Bonilla\nValdez, 2019-2021;\nARTÍCULO 122 BIS.- Fue adicionado por Decreto No. 244, publicado en el Periódico\nOficial No. 28, de fecha 09 de junio de 2018, Tomo CXXV, NÚMERO ESPECIAL, expedido por la H. XXII Legislatura, siendo Gobernador Constitucional el C. Francisco Arturo Vega de\nLamadrid, 2013-2019;\nARTÍCULO 134.- Fue reformado mediante Decreto No. 288, publicado en el Periódico\nOficial No. 52, de fecha 02 de septiembre de 2023, Número Especial, Tomo CXXX, expedido por la H. XXIV Legislatura, siendo Gobernadora Constitucional la C. Marina del Pilar Ávila\nOlmeda 2021-2027;\nARTÍCULO 136.- Fue reformado por Decreto No. 244, publicado en el Periódico\nOficial No. 28, de fecha 09 de junio de 2018, Tomo CXXV, NÚMERO ESPECIAL, expedido por la H. XXII Legislatura, siendo Gobernador Constitucional el C. Francisco Arturo Vega de\nLamadrid, 2013-2019; fue reformado por Decreto No. 85, publicado en el Periódico Oficial\nNo. 43, de fecha 24 de julio de 2020, Tomo CXXVII, Sección II, expedido por la H. XXIII\nLegislatura, siendo Gobernador Constitucional el C. Jaime Bonilla Valdez, 2019-2021; fue reformado por Decreto No. 102, publicado en el Periódico Oficial No. 54, de fecha 02 de septiembre de 2020, Tomo CXXVII, NÚMERO ESPECIAL, expedido por la H. XXIII\nLegislatura, siendo Gobernador Constitucional el C. Jaime Bonilla Valdez, 2019-2021;\nARTÍCULO 139.- Fue reformado por Decreto No. 262, publicado en el Periódico\nH. XXIV Legislatura, siendo Gobernadora Constitucional la C. Marina del Pilar Ávila Olmeda, 2021-2027; fue reformado mediante Decreto No. 288, publicado en el Periódico Oficial No.\nXXIV Legislatura, siendo Gobernadora Constitucional la C. Marina del Pilar Ávila Olmeda\n2021-2027; fue reformado mediante Decreto No. 145, publicado en el Periódico Oficial No.\nLegislatura, siendo Gobernadora Constitucional la C. Marina del Pilar Ávila Olmeda 20212027;\nLey Electoral del Estado de Baja California. Página 155\n.\nActualización Legislativa.\nÚltima reforma P. O. No. 60, Índice, 03-Oct-2025\nARTÍCULO 140.- Fue reformado por Decreto No. 244, publicado en el Periódico\nOficial No. 28, de fecha 09 de junio de 2018, Tomo CXXV, NÚMERO ESPECIAL, expedido por la H. XXII Legislatura, siendo Gobernador Constitucional el C. Francisco Arturo Vega de\nLamadrid, 2013-2019; fue reformado por Decreto No. 102, publicado en el Periódico Oficial\nNo. 54, de fecha 02 de septiembre de 2020, Tomo CXXVII, NÚMERO ESPECIAL, expedido por la H. XXIII Legislatura, siendo Gobernador Constitucional el C. Jaime Bonilla Valdez, 2019-2021;\nARTÍCULO 140 BIS.- Fue adicionado por Decreto No. 262, publicado en el Periódico\nOficial No. 42, Número Especial, de fecha 19 de julio de 2023, Tomo CXXIX, expedido por la\nH. XXIV Legislatura, siendo Gobernadora Constitucional la C. Marina del Pilar Ávila Olmeda, 2021-2027;\nARTÍCULO 141.- Fue reformado por Decreto No. 262, publicado en el Periódico\nOficial No. 42, Número Especial, de fecha 19 de julio de 2023, Tomo CXXIX, expedido por la\nH. XXIV Legislatura, siendo Gobernadora Constitucional la C. Marina del Pilar Ávila Olmeda, 2021-2027;\nARTÍCULO 144.- Fue reformado por Decreto No. 244, publicado en el Periódico\nOficial No. 28, de fecha 09 de junio de 2018, Tomo CXXV, NÚMERO ESPECIAL, expedido por la H. XXII Legislatura, siendo Gobernador Constitucional el C. Francisco Arturo Vega de\nLamadrid, 2013-2019; fue reformado por Decreto No. 85, publicado en el Periódico Oficial\nNo. 43, de fecha 24 de julio de 2020, Tomo CXXVII, Sección II, expedido por la H. XXIII\nLegislatura, siendo Gobernador Constitucional el C. Jaime Bonilla Valdez, 2019-2021;\nARTÍCULO 145.- Fue reformado por Decreto No. 85, publicado en el Periódico Oficial\nNo. 43, de fecha 24 de julio de 2020, Tomo CXXVII, Sección II, expedido por la H. XXIII\nLegislatura, siendo Gobernador Constitucional el C. Jaime Bonilla Valdez, 2019-2021;\nARTÍCULO 146.- Fue reformado mediante Decreto No. 288, publicado en el Periódico\nOficial No. 52, de fecha 02 de septiembre de 2023, Número Especial, Tomo CXXX, expedido por la H. XXIV Legislatura, siendo Gobernadora Constitucional la C. Marina del Pilar Ávila\nOlmeda 2021-2027;\nARTÍCULO 149.- Fue reformado por Decreto No. 244, publicado en el Periódico por la H. XXII Legislatura, siendo Gobernador Constitucional el C. Francisco Arturo Vega de\nLamadrid, 2013-2019;\nARTÍCULO 151.- Fue reformado por Decreto No. 262, publicado en el Periódico\nH. XXIV Legislatura, siendo Gobernadora Constitucional la C. Marina del Pilar Ávila Olmeda, 2021-2027;\nLey Electoral del Estado de Baja California. Página 156\n.\nActualización Legislativa.\nÚltima reforma P. O. No. 60, Índice, 03-Oct-2025\nARTÍCULO 152.- Fue reformado por Decreto No. 276, publicado en el Periódico\nOficial No. 60, de fecha 13 de agosto de 2021, Tomo CXXVIII, Sección IV, expedido por la H.\nXXIII Legislatura, siendo Gobernador Constitucional el C. Jaime Bonilla Valdez, 2019-2021;\nARTÍCULO 153.- Fue reformado por Decreto No. 276, publicado en el Periódico\nOficial No. 60, de fecha 13 de agosto de 2021, Tomo CXXVIII, Sección IV, expedido por la H.\nXXIII Legislatura, siendo Gobernador Constitucional el C. Jaime Bonilla Valdez, 2019-2021;\nARTÍCULO 160.- Fue reformado por Decreto No. 102, publicado en el Periódico\nOficial No. 54, de fecha 02 de septiembre de 2020, Tomo CXXVII, NÚMERO ESPECIAL, expedido por la H. XXIII Legislatura, siendo Gobernador Constitucional el C. Jaime Bonilla\nValdez, 2019-2021;\nARTÍCULO 165.- Fue reformado por Decreto No. 276, publicado en el Periódico\nOficial No. 60, de fecha 13 de agosto de 2021, Tomo CXXVIII, Sección IV, expedido por la H.\nXXIII Legislatura, siendo Gobernador Constitucional el C. Jaime Bonilla Valdez, 2019-2021;\nARTÍCULO 166.- Fue reformado por Decreto No. 276, publicado en el Periódico\nOficial No. 60, de fecha 13 de agosto de 2021, Tomo CXXVIII, Sección IV, expedido por la H.\nXXIII Legislatura, siendo Gobernador Constitucional el C. Jaime Bonilla Valdez, 2019-2021;\nARTÍCULO 168.- Fue reformado mediante Decreto No. 288, publicado en el Periódico\nOficial No. 52, de fecha 02 de septiembre de 2023, Número Especial, Tomo CXXX, expedido por la H. XXIV Legislatura, siendo Gobernadora Constitucional la C. Marina del Pilar Ávila\nOlmeda 2021-2027;\nARTÍCULO 169.- Fue reformado por Decreto No. 244, publicado en el Periódico\nOficial No. 28, de fecha 09 de junio de 2018, Tomo CXXV, NÚMERO ESPECIAL, expedido por la H. XXII Legislatura, siendo Gobernador Constitucional el C. Francisco Arturo Vega de\nLamadrid, 2013-2019;\nARTÍCULO 190.- Fue reformado por Decreto No. 85, publicado en el Periódico Oficial\nLegislatura, siendo Gobernador Constitucional el C. Jaime Bonilla Valdez, 2019-2021; fue reformado por Decreto No. 120, publicado en el Periódico Oficial No. 56, de fecha 19 de\nGobernadora Constitucional la C. Marina del Pilar Ávila Olmeda, 2021-2027;\nARTÍCULO 254.- Fue reformado por Decreto No. 102, publicado en el Periódico expedido por la H. XXIII Legislatura, siendo Gobernador Constitucional el C. Jaime Bonilla\nValdez, 2019-2021;\nLey Electoral del Estado de Baja California. Página 157\n.\nActualización Legislativa.\nÚltima reforma P. O. No. 60, Índice, 03-Oct-2025\nARTÍCULO 256.- Fue reformado por Decreto No. 102, publicado en el Periódico\nOficial No. 54, de fecha 02 de septiembre de 2020, Tomo CXXVII, NÚMERO ESPECIAL, expedido por la H. XXIII Legislatura, siendo Gobernador Constitucional el C. Jaime Bonilla\nValdez, 2019-2021;\nARTÍCULO 263.- Fue reformado por Decreto No. 244, publicado en el Periódico\nOficial No. 28, de fecha 09 de junio de 2018, Tomo CXXV, NÚMERO ESPECIAL, expedido por la H. XXII Legislatura, siendo Gobernador Constitucional el C. Francisco Arturo Vega de\nLamadrid, 2013-2019; fue reformado por Decreto No. 102, publicado en el Periódico Oficial\nNo. 54, de fecha 02 de septiembre de 2020, Tomo CXXVII, NÚMERO ESPECIAL, expedido por la H. XXIII Legislatura, siendo Gobernador Constitucional el C. Jaime Bonilla Valdez, 2019-2021;\nARTÍCULO 265.- Fue reformado por Decreto No. 244, publicado en el Periódico\nOficial No. 28, de fecha 09 de junio de 2018, Tomo CXXV, NÚMERO ESPECIAL, expedido por la H. XXII Legislatura, siendo Gobernador Constitucional el C. Francisco Arturo Vega de\nLamadrid, 2013-2019;\nARTÍCULO 270.- Fue reformado por Decreto No. 244, publicado en el Periódico\nOficial No. 28, de fecha 09 de junio de 2018, Tomo CXXV, NÚMERO ESPECIAL, expedido por la H. XXII Legislatura, siendo Gobernador Constitucional el C. Francisco Arturo Vega de\nLamadrid, 2013-2019;\nARTÍCULO 281.- Fue reformado por Decreto No. 184, publicado en el Periódico\nOficial No. 76, de fecha 30 de diciembre de 2022, Tomo CXXIX, Sección III, expedido por la\nH. XXIV Legislatura, siendo Gobernadora Constitucional la C. Marina del Pilar Ávila Olmeda, 2021-2027;\nARTÍCULO 282.- Fue reformado por Decreto No. 184, publicado en el Periódico\nOficial No. 76, de fecha 30 de diciembre de 2022, Tomo CXXIX, Sección III, expedido por la\nH. XXIV Legislatura, siendo Gobernadora Constitucional la C. Marina del Pilar Ávila Olmeda, 2021-2027;\nARTÍCULO 283.- Fue reformado por Decreto No. 244, publicado en el Periódico por la H. XXII Legislatura, siendo Gobernador Constitucional el C. Francisco Arturo Vega de\nLamadrid, 2013-2019;\nARTÍCULO 284.- Fue reformado por Decreto No. 184, publicado en el Periódico\nH. XXIV Legislatura, siendo Gobernadora Constitucional la C. Marina del Pilar Ávila Olmeda, 2021-2027;\nLey Electoral del Estado de Baja California. Página 158\n.\nActualización Legislativa.\nÚltima reforma P. O. No. 60, Índice, 03-Oct-2025\nARTÍCULO 285.- Fue reformado por Decreto No. 244, publicado en el Periódico\nOficial No. 28, de fecha 09 de junio de 2018, Tomo CXXV, NÚMERO ESPECIAL, expedido por la H. XXII Legislatura, siendo Gobernador Constitucional el C. Francisco Arturo Vega de\nLamadrid, 2013-2019;\nARTÍCULO 288 BIS.- Fue adicionado por Decreto No. 184, publicado en el Periódico\nOficial No. 76, de fecha 30 de diciembre de 2022, Tomo CXXIX, Sección III, expedido por la\nH. XXIV Legislatura, siendo Gobernadora Constitucional la C. Marina del Pilar Ávila Olmeda, 2021-2027;\nARTÍCULO 289.- Fue reformado por Decreto No. 244, publicado en el Periódico\nOficial No. 28, de fecha 09 de junio de 2018, Tomo CXXV, NÚMERO ESPECIAL, expedido por la H. XXII Legislatura, siendo Gobernador Constitucional el C. Francisco Arturo Vega de\nLamadrid, 2013-2019;\nARTÍCULO 292.- Fue reformado por Decreto No. 244, publicado en el Periódico\nOficial No. 28, de fecha 09 de junio de 2018, Tomo CXXV, NÚMERO ESPECIAL, expedido por la H. XXII Legislatura, siendo Gobernador Constitucional el C. Francisco Arturo Vega de\nLamadrid, 2013-2019;\nARTÍCULO 299.- Fue reformado por Decreto No. 244, publicado en el Periódico\nOficial No. 28, de fecha 09 de junio de 2018, Tomo CXXV, NÚMERO ESPECIAL, expedido por la H. XXII Legislatura, siendo Gobernador Constitucional el C. Francisco Arturo Vega de\nLamadrid, 2013-2019;\nARTÍCULO 308 BIS.- Fue adicionado por Decreto No. 184, publicado en el Periódico\nOficial No. 76, de fecha 30 de diciembre de 2022, Tomo CXXIX, Sección III, expedido por la\nH. XXIV Legislatura, siendo Gobernadora Constitucional la C. Marina del Pilar Ávila Olmeda, 2021-2027;\nARTÍCULO 327.- Fue reformado mediante Decreto No. 288, publicado en el Periódico\nOficial No. 52, de fecha 02 de septiembre de 2023, Número Especial, Tomo CXXX, expedido por la H. XXIV Legislatura, siendo Gobernadora Constitucional la C. Marina del Pilar Ávila\nOlmeda 2021-2027;\nARTÍCULO 328.- Fue reformado mediante Decreto No. 288, publicado en el Periódico por la H. XXIV Legislatura, siendo Gobernadora Constitucional la C. Marina del Pilar Ávila\nOlmeda 2021-2027; de conformidad con lo estipulado en su Punto Resolutivo Quinto de la\nSentencia de Acción de Inconstitucionalidad 198/2023 y su acumulada 200/2023, notificada cual se declara la invalidez del artículo 328, párrafo primero, en su porción normativa\n‘unánime’;\nLey Electoral del Estado de Baja California. Página 159\n.\nActualización Legislativa.\nÚltima reforma P. O. No. 60, Índice, 03-Oct-2025\nARTÍCULO 329.- Fue reformado por Decreto No. 244, publicado en el Periódico\nOficial No. 28, de fecha 09 de junio de 2018, Tomo CXXV, NÚMERO ESPECIAL, expedido por la H. XXII Legislatura, siendo Gobernador Constitucional el C. Francisco Arturo Vega de\nLamadrid, 2013-2019;\nARTÍCULO 330.- Fue reformado mediante Decreto No. 288, publicado en el Periódico\nOficial No. 52, de fecha 02 de septiembre de 2023, Número Especial, Tomo CXXX, expedido por la H. XXIV Legislatura, siendo Gobernadora Constitucional la C. Marina del Pilar Ávila\nOlmeda 2021-2027;\nARTÍCULO 331.- Fue reformado por Decreto No. 244, publicado en el Periódico\nOficial No. 28, de fecha 09 de junio de 2018, Tomo CXXV, NÚMERO ESPECIAL, expedido por la H. XXII Legislatura, siendo Gobernador Constitucional el C. Francisco Arturo Vega de\nLamadrid, 2013-2019;\nARTÍCULO 334 BIS.- Fue adicionado por Decreto No. 184, publicado en el Periódico\nOficial No. 76, de fecha 30 de diciembre de 2022, Tomo CXXIX, Sección III, expedido por la\nH. XXIV Legislatura, siendo Gobernadora Constitucional la C. Marina del Pilar Ávila Olmeda, 2021-2027;\nARTÍCULO 335.- Fue reformado por Decreto No. 281, publicado en el Periódico\nOficial No. 55, de fecha 30 de noviembre de 2018, Tomo CXXV, Sección IV, expedido por la\nHonorable Legislatura XXII, siendo Gobernador Constitucional el C. Francisco Arturo Vega de Lamadrid 2013-2019;\nARTÍCULO 337.- Fue reformado por Decreto No. 102, publicado en el Periódico\nOficial No. 54, de fecha 02 de septiembre de 2020, Tomo CXXVII, NÚMERO ESPECIAL, expedido por la H. XXIII Legislatura, siendo Gobernador Constitucional el C. Jaime Bonilla\nValdez, 2019-2021;\nARTÍCULO 337 BIS.- Fue reformado por Decreto No. 102, publicado en el Periódico\nOficial No. 54, de fecha 02 de septiembre de 2020, Tomo CXXVII, NÚMERO ESPECIAL, expedido por la H. XXIII Legislatura, siendo Gobernador Constitucional el C. Jaime Bonilla\nValdez, 2019-2021;\nARTÍCULO 338.- Fue reformado por Decreto No. 102, publicado en el Periódico expedido por la H. XXIII Legislatura, siendo Gobernador Constitucional el C. Jaime Bonilla\nValdez, 2019-2021; fue reformado por Decreto No. 262, publicado en el Periódico Oficial No.\nLegislatura, siendo Gobernadora Constitucional la C. Marina del Pilar Ávila Olmeda, 20212027;\nLey Electoral del Estado de Baja California. Página 160\n.\nActualización Legislativa.\nÚltima reforma P. O. No. 60, Índice, 03-Oct-2025\nARTÍCULO 339.- Fue reformado por Decreto No. 262, publicado en el Periódico\nOficial No. 42, Número Especial, de fecha 19 de julio de 2023, Tomo CXXIX, expedido por la\nH. XXIV Legislatura, siendo Gobernadora Constitucional la C. Marina del Pilar Ávila Olmeda, 2021-2027;\nARTÍCULO 342.- Fue reformado por Decreto No. 102, publicado en el Periódico\nOficial No. 54, de fecha 02 de septiembre de 2020, Tomo CXXVII, NÚMERO ESPECIAL, expedido por la H. XXIII Legislatura, siendo Gobernador Constitucional el C. Jaime Bonilla\nValdez, 2019-2021;\nARTÍCULO 354.- Fue reformado por Decreto No. 281, publicado en el Periódico\nOficial No. 55, de fecha 30 de noviembre de 2018, Tomo CXXV, Sección IV, expedido por la\nHonorable Legislatura XXII, siendo Gobernador Constitucional el C. Francisco Arturo Vega de Lamadrid 2013-2019; fue reformado por Decreto No. 102, publicado en el Periódico\nOficial No. 54, de fecha 02 de septiembre de 2020, Tomo CXXVII, NÚMERO ESPECIAL, expedido por la H. XXIII Legislatura, siendo Gobernador Constitucional el C. Jaime Bonilla\nValdez, 2019-2021;\nARTÍCULO 354 BIS.- Fue reformado por Decreto No. 276, publicado en el Periódico\nOficial No. 60, de fecha 13 de agosto de 2021, Tomo CXXVIII, Sección IV, expedido por la H.\nXXIII Legislatura, siendo Gobernador Constitucional el C. Jaime Bonilla Valdez, 2019-2021;\nARTÍCULO 362.- Fue reformado por Decreto No. 102, publicado en el Periódico\nOficial No. 54, de fecha 02 de septiembre de 2020, Tomo CXXVII, NÚMERO ESPECIAL, expedido por la H. XXIII Legislatura, siendo Gobernador Constitucional el C. Jaime Bonilla\nValdez, 2019-2021;\nARTÍCULO 363.- Fue reformado por Decreto No. 102, publicado en el Periódico\nOficial No. 54, de fecha 02 de septiembre de 2020, Tomo CXXVII, NÚMERO ESPECIAL, expedido por la H. XXIII Legislatura, siendo Gobernador Constitucional el C. Jaime Bonilla\nValdez, 2019-2021;\nARTÍCULO 363 BIS.- Fue reformado por Decreto No. 102, publicado en el Periódico expedido por la H. XXIII Legislatura, siendo Gobernador Constitucional el C. Jaime Bonilla\nValdez, 2019-2021;\nARTÍCULO 363 TER.- Fue reformado por Decreto No. 102, publicado en el Periódico expedido por la H. XXIII Legislatura, siendo Gobernador Constitucional el C. Jaime Bonilla\nValdez, 2019-2021;\nARTÍCULO 363 QUATER.- Fue reformado por Decreto No. 102, publicado en el\nLey Electoral del Estado de Baja California. Página 161\n.\nActualización Legislativa.\nÚltima reforma P. O. No. 60, Índice, 03-Oct-2025\nESPECIAL, expedido por la H. XXIII Legislatura, siendo Gobernador Constitucional el C.\nJaime Bonilla Valdez, 2019-2021;\nARTÍCULO 366.- Fue reformado por Decreto No. 102, publicado en el Periódico\nOficial No. 54, de fecha 02 de septiembre de 2020, Tomo CXXVII, NÚMERO ESPECIAL, expedido por la H. XXIII Legislatura, siendo Gobernador Constitucional el C. Jaime Bonilla\nValdez, 2019-2021;\nARTÍCULO 367.- Fue reformado por Decreto No. 102, publicado en el Periódico\nOficial No. 54, de fecha 02 de septiembre de 2020, Tomo CXXVII, NÚMERO ESPECIAL, expedido por la H. XXIII Legislatura, siendo Gobernador Constitucional el C. Jaime Bonilla\nValdez, 2019-2021;\nARTÍCULO 368.- Fue reformado por Decreto No. 102, publicado en el Periódico\nOficial No. 54, de fecha 02 de septiembre de 2020, Tomo CXXVII, NÚMERO ESPECIAL, expedido por la H. XXIII Legislatura, siendo Gobernador Constitucional el C. Jaime Bonilla\nValdez, 2019-2021;\nARTÍCULO 372.- Fue reformado por Decreto No. 102, publicado en el Periódico\nOficial No. 54, de fecha 02 de septiembre de 2020, Tomo CXXVII, NÚMERO ESPECIAL, expedido por la H. XXIII Legislatura, siendo Gobernador Constitucional el C. Jaime Bonilla\nValdez, 2019-2021;\nARTÍCULO 373.- Fue reformado por Decreto No. 102, publicado en el Periódico\nOficial No. 54, de fecha 02 de septiembre de 2020, Tomo CXXVII, NÚMERO ESPECIAL, expedido por la H. XXIII Legislatura, siendo Gobernador Constitucional el C. Jaime Bonilla\nValdez, 2019-2021;\nARTÍCULO 373 BIS.- Fue reformado por Decreto No. 102, publicado en el Periódico\nOficial No. 54, de fecha 02 de septiembre de 2020, Tomo CXXVII, NÚMERO ESPECIAL, expedido por la H. XXIII Legislatura, siendo Gobernador Constitucional el C. Jaime Bonilla\nValdez, 2019-2021;\nARTÍCULO 374.- Fue reformado por Decreto No. 244, publicado en el Periódico por la H. XXII Legislatura, siendo Gobernador Constitucional el C. Francisco Arturo Vega de\nLamadrid, 2013-2019;\nARTÍCULO 376.- Fue reformado por Decreto No. 102, publicado en el Periódico expedido por la H. XXIII Legislatura, siendo Gobernador Constitucional el C. Jaime Bonilla\nValdez, 2019-2021;\nLey Electoral del Estado de Baja California. Página 162\n.\nActualización Legislativa.\nÚltima reforma P. O. No. 60, Índice, 03-Oct-2025\nARTÍCULO 377.- Fue reformado por Decreto No. 102, publicado en el Periódico\nOficial No. 54, de fecha 02 de septiembre de 2020, Tomo CXXVII, NÚMERO ESPECIAL, expedido por la H. XXIII Legislatura, siendo Gobernador Constitucional el C. Jaime Bonilla\nValdez, 2019-2021;\nARTÍCULO 377BIS.- Fue reformado por Decreto No. 102, publicado en el Periódico\nOficial No. 54, de fecha 02 de septiembre de 2020, Tomo CXXVII, NÚMERO ESPECIAL, expedido por la H. XXIII Legislatura, siendo Gobernador Constitucional el C. Jaime Bonilla\nValdez, 2019-2021;\nARTÍCULO 378.- Fue reformado por Decreto No. 102, publicado en el Periódico\nOficial No. 54, de fecha 02 de septiembre de 2020, Tomo CXXVII, NÚMERO ESPECIAL, expedido por la H. XXIII Legislatura, siendo Gobernador Constitucional el C. Jaime Bonilla\nValdez, 2019-2021;\nARTÍCULO 381.- Fue reformado por Decreto No. 244, publicado en el Periódico\nOficial No. 28, de fecha 09 de junio de 2018, Tomo CXXV, NÚMERO ESPECIAL, expedido por la H. XXII Legislatura, siendo Gobernador Constitucional el C. Francisco Arturo Vega de\nLamadrid, 2013-2019; fue reformado por Decreto No. 102, publicado en el Periódico Oficial\nNo. 54, de fecha 02 de septiembre de 2020, Tomo CXXVII, NÚMERO ESPECIAL, expedido por la H. XXIII Legislatura, siendo Gobernador Constitucional el C. Jaime Bonilla Valdez, 2019-2021;\nARTÍCULO 382 BIS.- Fue reformado por Decreto No. 102, publicado en el Periódico expedido por la H. XXIII Legislatura, siendo Gobernador Constitucional el C. Jaime Bonilla\nValdez, 2019-2021;\nARTÍCULO 390.- Fue reformado por Decreto No. 102, publicado en el Periódico expedido por la H. XXIII Legislatura, siendo Gobernador Constitucional el C. Jaime Bonilla\nValdez, 2019-2021;\nLey Electoral del Estado de Baja California. Página 163\n.\nActualización Legislativa.\nÚltima reforma P. O. No. 60, Índice, 03-Oct-2025\nSENTENCIA DE LA ACCIÓN DE INCONSTITUCIONALIDAD 42/2015 Y SUS\nACUMULADAS 43/2015 Y 44/2015, MEDIANTE LA CUAL SE RESUELVE:\n“PRIMERO.- Es procedente y fundada la acción de inconstitucionalidad 42/2015 promovida por el Partido de la Revolución Democrática.\nSEGUNDO.- Es procedente, pero parcialmente fundada la acción de inconstitucionalidad 43/2015 promovida por el Partido Nueva Alianza.\nTERCERO.- Es procedente, pero parcialmente fundada la acción de inconstitucionalidad 44/2015 promovida por el Partido Morena.\nCUARTO.- Se reconoce la validez del Decreto 289 mediante el cual se reforman los artículos 5, 12, 15, 17, 27, 28, 59, 64, 79 y 81; y se adiciona un segundo párrafo, de Baja California; se suprime la expresión “TÍTULO QUINTO” en el capítulo III de dicho título y se adiciona al mismo Capítulo IV denominado Del Ministerio Público, publicado en el Periódico Oficial del Estado el doce de junio de dos mil quince, en términos del apartado VI de este fallo.\nQUINTO.- Se reconoce la validez de los artículos 15, fracciones I, inciso c) y II, 79, fracciones II, inciso b), y III, incisos c), numeral 2, y f), párrafo último, de la\nII, de la Ley Electoral del Estado de Baja California, en términos del apartado VI de esta sentencia.\nSEXTO.- Se declara la invalidez del párrafo segundo del artículo 14 de la de Partidos Políticos del Estado de Baja California; y, del artículo 172 de la Ley\nElectoral del Estado de Baja California en términos del apartado VI de esta sentencia, sentencia al Congreso del Estado de Baja California.\nEstado de Baja California.\nNotifíquese, haciéndolo por medio de oficio a las partes y, en su oportunidad, archívese el expediente como asunto concluido.”\nLey Electoral del Estado de Baja California. Página 164\n.\nActualización Legislativa.\nÚltima reforma P. O. No. 60, Índice, 03-Oct-2025\nARTÍCULO SEGUNDO TRANSITORIO DEL DECRETO No. 244, POR EL QUE SE\nAPRUEBA LA REFORMA A LOS ARTÍCULOS 8, 21, 30, 31, 32, ADICIÓN DEL 122 BIS,\n136, 144, 149, 169, 263, 265, 270, 283, 285, 292, 329, 331, 374 Y 381; PUBLICADO EN EL\nPERIÓDICO OFICIAL No. 28, NÚMERO ESPECIAL, TOMO CXXV, DE FECHA 09 DE\nJUNIO DE 2018, EXPEDIDO POR LA H. XXII LEGISLATURA, SIENDO GOBERNADOR\nCONSTITUCIONAL EL C. FRANCISCO ARTURO VEGA DE LAMADRID 2013-2019.\nARTÍCULO TRANSITORIO\nÚNICO.- La presente reforma entrará en vigor al día siguiente de su publicación en el\nPeriódico Oficial del Estado.\nDADO en el Salón de Sesiones “Lic. Benito Juárez García” del H. Poder Legislativo del Estado de Baja California, en la Ciudad de Mexicali, B.C., a los siete días del mes de junio del año dos mil dieciocho.\nDIP. MARCO ANTONIO CORONA BOLAÑOS CACHO\nPRESIDENTE\n(RÚBRICA)\nDIP. VICTORIA BENTLEY DUARTE\nSECRETARIA\n(RÚBRICA)\nDE CONFORMIDAD CON LO DISPUESTO POR LA FRACCIÓN I DEL ARTÍCULO 49\nMEXICALI, BAJA CALIFORNIA, A LOS NUEVE DÍAS DEL MES DE JUNIO DEL AÑO\nDOS MIL DIECIOCHO.\nFRANCISCO ARTURO VEGA DE LAMADRID\nGOBERNADOR DEL ESTADO\n(RÚBRICA)\nFRANCISCO RUEDA GÓMEZ\nSECRETARIO GENERAL DE GOBIERNO\n(RÚBRICA)\nLey Electoral del Estado de Baja California. Página 165\n.\nActualización Legislativa.\nÚltima reforma P. O. No. 60, Índice, 03-Oct-2025\nARTÍCULO TRIGÉSIMO PRIMERO TRANSITORIO DEL DECRETO No. 281, POR\nEL QUE SE REFORMA A LOS ARTÍCULOS 335 Y 354, PUBLICADO EN EL PERIÓDICO\nOFICIAL No. 55, SECCION IV, TOMO CXXV, DE FECHA 30 DE NOVIEMBRE DE 2018,\nEXPEDIDO POR LA H. XXII LEGISLATURA, SIENDO GOBERNADOR CONSTITUCIONAL\nEL C. FRANCISCO ARTURO VEDA DE LAMADRID 2013-2019.\nARTÍCULOS TRANSITORIOS\nARTÍCULO PRIMERO.- El presente decreto entrará en vigor al día siguiente al de su publicación en el Periódico Oficial del Estado de Baja California.\nARTÍCULO SEGUNDO.- El valor diario de la Unidad de Medida y Actualización a la fecha de entrada en vigor, se tomará el valor publicado en el Diario Oficial de la Federación por el INEGI. El valor de la Unidad de Medida y Actualización a la fecha de entrada en vigor del presente Decreto, será producto de multiplicar el valor referido en el párrafo anterior por\n30.4. Por su parte, el valor anual será el producto de multiplicar el valor inicial mensual por\n12.\nARTÍCULO TERCERO. - Todas las menciones al salario mínimo como unidad de cuenta, índice, base, medida o referencia para determinar la cuantía de las obligaciones, sanciones, multas administrativas, conceptos de pago y montos de referencia, se entenderán referidas a la Unidad de Medida y Actualización.\nDADO en el Salón de Sesiones “Lic. Benito Juárez García” del H. Poder Legislativo del Estado de Baja California, en la Ciudad de Mexicali, B.C., a los veinticinco días del mes de octubre del año dos mil dieciocho.\nDIP. ROCÍO LÓPEZ GOROSAVE\nPRESIDENTA\n(RÚBRICA)\nDIP. MÓNICA HERNÁNDEZ ÁLVAREZ\nSECRETARIA\n(RÚBRICA)\nDE CONFORMIDAD CON LO DISPUESTO POR LA FRACCIÓN I DEL ARTÍCULO 49\nMEXICALI, BAJA CALIFORNIA, A LOS TREINTA DÍAS DEL MES DE NOVIEMBRE\nDEL AÑO DOS MIL DIECIOCHO.\nFRANCISCO ARTURO VEGA DE LAMADRID\nGOBERNADOR DEL ESTADO\nLey Electoral del Estado de Baja California. Página 166\n.\nActualización Legislativa.\nÚltima reforma P. O. No. 60, Índice, 03-Oct-2025\n(RÚBRICA)\nFRANCISCO RUEDA GÓMEZ\nSECRETARIO GENERAL DE GOBIERNO\n(RÚBRICA)\nARTÍCULO SEGUNDO TRANSITORIO DEL DECRETO No. 52, POR EL QUE SE\nREFORMA A LOS ARTÍCULOS 35, 66, 68, 69 Y 97, PUBLICADO EN EL PERIÓDICO\nOFICIAL No. 17, SECCION II, TOMO CXXVII, DE FECHA 27 DE MARZO DE 2020,\nEXPEDIDO POR LA H. XXIII LEGISLATURA, SIENDO GOBERNADOR CONSTITUCIONAL\nEL C. JAIME BONILLA VALDEZ 2019-2021.\nARTÍCULOS TRANSITORIOS\nPRIMERO.- Publíquese el contenido de la presente reforma en el Periódico Oficial del\nEstado.\nSEGUNDO.- La presente reforma entrará en vigor hasta en tanto sea publicada la\nSoberano de Baja California, así como el párrafo segundo del APARTADO B, del mismo artículo.\nTERCERO. – Remítase el contenido del presente Decreto al Instituto Estatal Electoral del\nEstado de Baja California, para los efectos legales correspondientes.\nDADO en el Salón de Sesiones “Lic. Benito Juárez García” del H. Poder Legislativo del\nEstado de Baja California, en la Ciudad de Mexicali, B.C., a los veinticinco días del mes de marzo del año dos mil veinte.\nDIP. VÍCTOR MANUEL MORÁN HERNÁNDEZ\nPRESIDENTE\n(RÚBRICA)\nDIP. CARMEN LETICIA HERNÁNDEZ CARMONA\nSECRETARIA\n(RÚBRICA)\nDE CONFORMIDAD CON LO DISPUESTO POR LA FRACCIÓN I DEL ARTÍCULO 49\nMEXICALI, BAJA CALIFORNIA, A LOS VEINTISIETE DÍAS DEL MES DE MARZO\nDEL AÑO DOS MIL VEINTE.\nLey Electoral del Estado de Baja California. Página 167\n.\nActualización Legislativa.\nÚltima reforma P. O. No. 60, Índice, 03-Oct-2025\nJAIME BONILLA VELDEZ\nGOBERNADOR DEL ESTADO\n(RÚBRICA)\nAMADOR RODRÍGUEZ LOZANO\nSECRETARIO GENERAL DE GOBIERNO\n(RÚBRICA)\nARTÍCULO SEGUNDO TRANSITORIO DEL DECRETO No. 85, POR EL QUE SE\nREFORMA A LOS ARTÍCULOS 22, 27, 46, 136, 144, 145 Y 190 Y LA ADICIÓN DEL\nARTÍCULO 27 BIS, PUBLICADO EN EL PERIÓDICO OFICIAL No. 43, SECCION II, TOMO\nCXXVII, DE FECHA 24 DE JULIO DE 2020, EXPEDIDO POR LA H. XXIII LEGISLATURA,\nSIENDO GOBERNADOR CONSTITUCIONAL EL C. JAIME BONILLA VALDEZ 2019-2021.\nARTÍCULOS TRANSITORIOS\nPRIMERO.- Publíquese la presente reforma en el Periódico Oficial del Estado.\nSEGUNDO.- La presente reforma entrará en vigor hasta en tanto sea publicada la\nCalifornia, materia del presente Decreto y serán aplicables al siguiente proceso electoral ordinario que se celebre en la entidad.\nTERCERO. – El Consejo General Electoral del Instituto Estatal Electoral del Estado de Baja\nCalifornia, deberá en su caso, adecuar la reglamentación interna correspondiente, antes del inicio del proceso electoral 2020-2021.\nDADO en el Salón de Sesiones “Lic. Benito Juárez García” del H. Poder Legislativo del\nEstado de Baja California, en la Ciudad de Mexicali, B.C., a los dieciséis días del mes de julio del año dos mil veinte.\nDIP. JULIO CÉSAR VÁZQUEZ CASTILLO\nVICEPRESIDENTE\n(RÚBRICA)\nDIP. EVA GRICELDA RODRÍGUEZ\nSECRETARIA\n(RÚBRICA)\nDE CONFORMIDAD CON LO DISPUESTO POR LA FRACCIÓN I DEL ARTÍCULO 49\nLey Electoral del Estado de Baja California. Página 168\n.\nActualización Legislativa.\nÚltima reforma P. O. No. 60, Índice, 03-Oct-2025\nMEXICALI, BAJA CALIFORNIA, A LOS DIECISIETE DÍAS DEL MES DE JULIO DEL\nAÑO DOS MIL VEINTE.\nJAIME BONILLA VELDEZ\nGOBERNADOR DEL ESTADO\n(RÚBRICA)\nAMADOR RODRÍGUEZ LOZANO\nSECRETARIO GENERAL DE GOBIERNO\n(RÚBRICA)\nARTÍCULO SEGUNDO TRANSITORIO DEL DECRETO No. 102, POR EL QUE SE\nREFORMAN LOS ARTÍCULOS 1, 2, 3, 9, 21, 24, 30, 31,35, 37, 45, 57, 103, 112, 136, 140,\n160, 254, 256, 263, 337, 337 BIS, 338, 342, 354, 362, 363, 363 BIS, 363 TER, 363\nQUATER, 366, 367, 368, 372, 373, 373 BIS, 376, 377, 377 BIS, 378, 381, 382 BIS Y 390;\nPUBLICADO EN EL PERIÓDICO OFICIAL NO. 54, NÚMERO ESPECIAL, TOMO CXXVII,\nDE FECHA 02 DE SEPTIEMBRE DE 2020, EXPEDIDO POR LA H. XXIII LEGISLATURA,\nSIENDO GOBERNADOR CONSTITUCIONAL EL C. JAIME BONILLA VALDEZ 2019-2021.\nARTÍCULOS TRANSITORIOS\nPRIMERO. El presente Decreto entrará en vigor al día siguiente de su publicación en el\nPeriódico Oficial del Estado de Baja California.\nSEGUNDO. El Instituto Estatal Electoral, contará con un plazo de 30 días naturales contados a partir de la vigencia del presente Decreto, para adecuar sus disposiciones reglamentarias conforme a lo dispuesto en el mismo.\nTERCERO. Los procedimientos sancionadores iniciados con anterioridad a la entrada en vigor del presente Decreto, continuarán rigiéndose por las disposiciones vigentes al momento de su inicio.\nDADO en Sesión Ordinaria Virtual, en la Ciudad de Mexicali, B.C., a los veintiséis días del mes de agosto del año dos mil veinte.\nDIP. JULIO CÉSAR VÁZQUEZ CASTILLO\nPRESIDENTE\n(RÚBRICA)\nDIP. EVA GRICELDA RODRÍGUEZ\nSECRETARIA\n(RÚBRICA)\nLey Electoral del Estado de Baja California. Página 169\n.\nActualización Legislativa.\nÚltima reforma P. O. No. 60, Índice, 03-Oct-2025\nDE CONFORMIDAD CON LO DISPUESTO POR LA FRACCIÓN I DEL ARTÍCULO 49\nMEXICALI, BAJA CALIFORNIA, A LOS VEINTIOCHO DÍAS DEL MES DE AGOSTO DEL\nAÑO DOS MIL VEINTE.\nJAIME BONILLA VALDEZ\nGOBERNADOR DEL ESTADO\n(RÚBRICA)\nAMADOR RODRÍGUEZ LOZANO\nSECRETARIO GENERAL DE GOBIERNO\n(RÚBRICA)\nSENTENCIA DE ACCIÓN DE INCONSTITUCIONALIDAD 128/2020 Y SUS\nACUMULADAS 147/2020, 163/2020 Y 228/2020, PUBLICADA EN EL PERIÓDICO OFICIAL\nNo. 43, DE FECHA 18 DE JUNIO DE 2021, SECCIÓN III, TOMO CXXVIII, SIENDO\nGOBERNADOR CONSTITUCIONAL EL C. JAIME BONILLA VALDEZ 2019-2021.\nACCIÓN DE INCONSTITUCIONALIDAD 128/2020 Y\nSUS ACUMULADAS 147/2020, 163/2020 Y 228/2020\nPROMOVENTES: PARTIDO ACCIÓN NACIONAL,\nPARTIDO DE BAJA CALIFORNIA, PARTIDO\nREVOLUCIONARIO INSTITUCIONAL Y\nMOVIMIENTO CIUDADANO\nPONENTE: MINISTRA NORMA LUCÍA PIÑA HERNÁNDEZ\nSECRETARIOS DE ESTUDIO Y CUENTA: SANTIAGO JOSÉ VÁZQUEZ CAMACHO Y\nJORGE FRANCISCO CALDERÓN GAMBOA\nCOLABORÓ: EDGAR MEDINA PÉREZ\nVISTO BUENO\nSRA. MINISTRA correspondiente a la sesión del día siete de septiembre de dos mil veinte.\nMediante la que se resuelven la acción de inconstitucionalidad 128/2020 y sus acumuladas 147/2020, 163/2020 y 228/2020, promovidas por el Partido Acción Nacional\n(PAN), el Partido de Baja California, el Partido Revolucionario Institucional (PRI) y\nMovimiento Ciudadano, en contra del Decreto número 52, mediante el cual se reformaron los\nLey Electoral del Estado de Baja California. Página 170\n.\nActualización Legislativa.\nÚltima reforma P. O. No. 60, Índice, 03-Oct-2025\n(Constitución Política local o Constitución local); 35, 66, 68, 69 y 97 de la Ley Electoral del\nEstado de Baja California (Ley Electoral local); así como 9, 11 y 25 de la Ley que\nReglamenta las Candidaturas Independientes en el Estado de Baja California (Ley de\nCandidaturas Independientes local), publicado en el Periódico Oficial del Estado de Baja\nCalifornia, No.17, en la sección II, del veintisiete de marzo de dos mil veinte (Decreto 52).\n……….\nXIV. PUNTOS RESOLUTIVOS\n173. Por lo expuesto y fundado, se resuelve:\nPRIMERO. Es procedente, pero infundada la acción de inconstitucionalidad 128/2020; procedente y parcialmente fundada la acción de inconstitucionalidad 147/2020; y parcialmente procedentes y parcialmente fundadas las acciones de inconstitucionalidad\n163/2020 y 228/2020.\nSEGUNDO. Se sobresee en las acciones de inconstitucionalidad 163/2020 y 228/2020 respecto del artículo 35 de la Ley Electoral del Estado de Baja California, reformado mediante el Decreto No. 52, publicado en el Periódico Oficial de dicha entidad federativa el veintisiete de marzo de dos mil veinte, en términos del apartado VI de esta decisión.\nTERCERO. Se desestiman la acción de inconstitucionalidad 128/2020 y sus acumuladas\n147/2020, 163/2020 y 228/2020 respecto de la invalidez del procedimiento legislativo que culminó en el Decreto No. 52, mediante el cual se aprueba la reforma al artículo 5 de la reformas a la Ley Electoral del Estado de Baja California y a la Ley que Reglamenta las\nCandidaturas Independientes en el Estado de Baja California, publicado en el Periódico\nOficial de dicha entidad federativa el veintisiete de marzo de dos mil veinte, de conformidad con el apartado VIII de esta determinación.\nCUARTO. Se reconoce la validez del artículo 5, párrafo quinto, en su porción normativa “El proceso electoral dará inicio el primer domingo de diciembre del año anterior a la elección”, y apartado B, párrafo segundo, en su porción normativa “y austeridad”, de la Constitución\n52, publicado en el Periódico Oficial de dicha entidad federativa el veintisiete de marzo de\nQUINTO. Se declara la invalidez del artículo 97, párrafo primero, en su porción normativa\n“Las y los Consejeros Electorales del Consejo General y de los Consejos Distritales\nElectorales, no tendrán derecho a las prestaciones que por ley les corresponden a los trabajadores del Instituto Estatal, salvo la atención del servicio médico en institución pública de salud”, de la Ley Electoral del Estado de Baja California, reformado mediante el Decreto\nNo. 52, publicado en el Periódico Oficial de dicha entidad federativa el veintisiete de marzo\nLey Electoral del Estado de Baja California. Página 171\n.\nActualización Legislativa.\nÚltima reforma P. O. No. 60, Índice, 03-Oct-2025 de dos mil veinte, en atención a lo expuesto en el apartado XII de esta ejecutoria, la cual surtirá sus efectos a partir de la notificación de estos puntos resolutivos al Congreso del\nEstado de Baja California, como se precisa en el apartado XIII de este fallo.\nSEXTO. Publíquese esta resolución en el Diario Oficial de la Federación, en el Periódico\nOficial del Estado de Baja California, así como en el Semanario Judicial de la Federación y su Gaceta.\nNotifíquese; haciéndolo por medio de oficio a las partes y, en su oportunidad, archívese el expediente como asunto concluido.\nAsí lo resolvió el Pleno de la Suprema Corte de Justicia de la Nación:\n………\nFirman el señor Ministro Presidente y la señora Ministra Ponente con el Secretario\nGeneral de Acuerdos que da fe.\nMINISTRO PRESIDENTE\nARTURO ZALDÍVAR LELO DE LARREA\n(RÚBRICA)\nMINISTRA PONENTE\nNORMA LUCÍA PIÑA HERNÁNDEZ\n(RÚBRICA)\nSECRETARIO GENERAL DE ACUERDOS\nRAFAEL COELLO CETINA\n(RÚBRICA)\nARTÍCULO ÚNICO TRANSITORIO DEL DECRETO No. 276, POR EL QUE SE\nREFORMAN LOS ARTÍCULOS 73, 152, 153, 165 y 166, ASÍ COMO LA ADICIÓN DEL\nARTÍCULO 354 BIS; PUBLICADO EN EL PERIÓDICO OFICIAL NO. 60, SECCIÓN IV,\nLEGISLATURA, SIENDO GOBERNADOR CONSTITUCIONAL EL C. JAIME BONILLA\nVALDEZ 2019-2021.\nARTÍCULOS TRANSITORIOS\nPRIMERO. La presente reforma entrará en vigor al día siguiente de su publicación en el\nPeriódico Oficial del Estado de Baja California, y serán aplicables en el Proceso Electoral\nLocal 2023- 2024.\nLey Electoral del Estado de Baja California. Página 172\n.\nActualización Legislativa.\nÚltima reforma P. O. No. 60, Índice, 03-Oct-2025\nSEGUNDO. La autoridad Electoral realizará las adecuaciones reglamentarias y administrativas para que la presente reforma se implemente a partir del Proceso Electoral\nLocal 2023- 2024 en el Estado de Baja California.\nDADO en el Salón de Sesiones Benito Juárez García en Sesión Ordinaria de la XXIII\nLegislatura en la Ciudad de Mexicali, B.C., a los veintiún días del mes de julio del año dos mil veintiuno.\nDIP. EVA GRICELDA RODRÍGUEZ\nPRESIDENTA\n(RÚBRICA)\nDIP. MARÍA LUISA VILLALOBOS ÁVILA\nSECRETARIA\n(RÚBRICA)\nDE CONFORMIDAD CON LO DISPUESTO POR LA FRACCIÓN I DEL ARTÍCULO 49\nCALIFORNIA, IMPRÍMASE Y PUBLÍQUESE.\nMEXICALI, BAJA CALIFORNIA, A LOS VEINTITRÉS DÍAS DEL MES DE JULIO DEL AÑO\nDOS MIL VEINTIUNO.\nJAIME BONILLA VALDEZ\nGOBERNADOR DEL ESTADO\n(RÚBRICA)\nAMADOR RODRÍGUEZ LOZANO\nSECRETARIO GENERAL DE GOBIERNO\n(RÚBRICA)\nARTÍCULO ÚNICO TRANSITORIO DEL DECRETO No. 120, POR EL QUE SE\nREFORMA EL ARTÍCULO 190; PUBLICADO EN EL PERIÓDICO OFICIAL NO. 56,\nLA H. XXIV LEGISLATURA, SIENDO GOBERNADORA CONSTITUCIONAL LA C. MARINA\nDEL PILAR ÁVILA OLMEDA 2021-2027.\nTRANSITORIOS\nÚNICO. El presente Decreto entrará en vigor al día siguiente de su publicación en el\nPeriódico Oficial del Estado.\nLey Electoral del Estado de Baja California. Página 173\n.\nActualización Legislativa.\nÚltima reforma P. O. No. 60, Índice, 03-Oct-2025\nDADO en Sesión Ordinaria de la XXIV Legislatura en la Ciudad de Mexicali, B.C., a los veinticinco días del mes de agosto del año dos mil veintidós.\nDIP. ALEJANDRA MARÍA ANG HERNÁNDEZ\nPRESIDENTA\n(RÚBRICA)\nDIP. DUNNIA MONTSERRAT MURILLO LÓPEZ\nSECRETARIA\n(RÚBRICA)\nDE CONFORMIDAD CON LO DISPUESTO POR LA FRACCIÓN I DEL ARTÍCULO 49\nCALIFORNIA, IMPRÍMASE Y PUBLÍQUESE.\nMEXICALI, BAJA CALIFORNIA, A LOS CINCO DÍAS DEL MES DE SEPTIEMBRE DEL AÑO\nDOS MIL VEINTIDÓS.\nMARINA DEL PILAR ÁVILA OLMEDA\nGOBERNADORA DEL ESTADO\nDE BAJA CALIFORNIA\n(RÚBRICA)\nCATALINO ZAVALA MÁRQUEZ\nSECRETARIO GENERAL DE GOBIERNO\nDEL ESTADO DE BAJA CALIFORNIA\n(RÚBRICA)\nARTÍCULO ÚNICO TRANSITORIO DEL DECRETO No. 184, POR EL QUE SE\nREFORMA A LOS ARTÍCULOS 281, 282 y 284, COMO TAMBIÉN, LA ADICIÓN DE LOS\nARTÍCULOS 288 BIS, 308 BIS y 334 BIS; PUBLICADO EN EL PERIÓDICO OFICIAL NO.\nLA H. XXIV LEGISLATURA, SIENDO GOBERNADORA CONSTITUCIONAL LA C. MARINA\nDEL PILAR ÁVILA OLMEDA 2021-2027.\nTRANSITORIOS\nÚNICO. La presente reforma entrará en vigor al día siguiente de su publicación en el\nPeriódico Oficial del Estado.\nDADO en Sesión Extraordinaria de la XXIV Legislatura en la Ciudad de Mexicali, B.C., a los trece días del mes de diciembre del año dos mil veintidós.\nLey Electoral del Estado de Baja California. Página 174\n.\nActualización Legislativa.\nÚltima reforma P. O. No. 60, Índice, 03-Oct-2025\nDIP. MARÍA DEL ROCÍO ADAME MUÑOZ\nPRESIDENTA\n(RÚBRICA)\nDIP. DUNNIA MONTSERRAT MURILLO LÓPEZ\nSECRETARIA\n(RÚBRICA)\nDE CONFORMIDAD CON LO DISPUESTO POR LA FRACCIÓN I DEL ARTÍCULO 49\nCALIFORNIA, IMPRÍMASE Y PUBLÍQUESE.\nMEXICALI, BAJA CALIFORNIA, A LOS VEINTIÚN DÍAS DEL MES DE DICIEMBRE DEL\nAÑO DOS MIL VEINTIDÓS.\nMARINA DEL PILAR ÁVILA OLMEDA\nGOBERNADORA DEL ESTADO\nDE BAJA CALIFORNIA\n(RÚBRICA)\nCATALINO ZAVALA MÁRQUEZ\nSECRETARIO GENERAL DE GOBIERNO\nDEL ESTADO DE BAJA CALIFORNIA\n(RÚBRICA)\nARTÍCULO ÚNICO TRANSITORIO DEL DECRETO No. 262, POR EL QUE SE\nREFORMA A LOS ARTÍCULOS 1, 3, 21, 30, 35, 37, 139, 141, 151, 338 y 339, COMO\nTAMBIÉN LA ADICIÓN DEL ARTÍCULO 140 BIS; PUBLICADO EN EL PERIÓDICO OFICIAL\nNO. 42, NÚMERO ESPECIAL, DE FECHA 19 DE JULIO DE 2023, TOMO CXXX,\nEXPEDIDO POR LA H. XXIV LEGISLATURA, SIENDO GOBERNADORA\nCONSTITUCIONAL LA C. MARINA DEL PILAR ÁVILA OLMEDA 2021-2027.\nTRANSITORIOS\nÚNICO. El presente Decreto entrará en vigor al día siguiente de su publicación en el\nPeriódico Oficial del Estado.\nDADO en Sesión Ordinaria de la XXIV Legislatura en la Ciudad de Mexicali, B.C., a los seis días del mes de julio del año dos mil veintitrés.\nDIP. MANUEL GUERRERO LUNA\nPRESIDENTE\n(RÚBRICA)\nLey Electoral del Estado de Baja California. Página 175\n.\nActualización Legislativa.\nÚltima reforma P. O. No. 60, Índice, 03-Oct-2025\nDIP. ALEJANDRA MARÍA ANG HERNÁNDEZ\nSECRETARIA\n(RÚBRICA)\nDE CONFORMIDAD CON LO DISPUESTO POR LA FRACCIÓN I DEL ARTÍCULO 49\nCALIFORNIA, IMPRÍMASE Y PUBLÍQUESE.\nMEXICALI, BAJA CALIFORNIA, A LOS SIETE DÍAS DEL MES DE JULIO DEL AÑO DOS\nMIL VEINTITRÉS.\nMARINA DEL PILAR ÁVILA OLMEDA\nGOBERNADORA DEL ESTADO\nDE BAJA CALIFORNIA\n(RÚBRICA)\nCATALINO ZAVALA MÁRQUEZ\nSECRETARIO GENERAL DE GOBIERNO\nDEL ESTADO DE BAJA CALIFORNIA\n(RÚBRICA)\nARTÍCULO PRIMERO TRANSITORIO DEL DECRETO No. 288, POR EL QUE SE\nREFORMAN LOS ARTÍCULOS 7, 21, 27 BIS, 33, 134, 139, 146, 168, 327, 328 y 330;\nPUBLICADO EN EL PERIÓDICO OFICIAL No. 52, NÚMERO ESPECIAL, TOMO CXXX, DE\nFECHA 02 DE SEPTIEMBRE DE 2023, EXPEDIDO POR LA H. XXIV LEGISLATURA,\nSIENDO GOBERNADORA CONSTITUCIONAL LA C. MARINA DEL PILAR ÁVILA OLMEDA\n2021-2027.\nTRANSITORIOS\nPRIMERO.- La presente reforma entrará en vigor el día de su publicación en el Periódico\nOficial del Estado de Baja California.\nSEGUNDO.- El Tribunal de Justicia Electoral del Estado de Baja California deberá realizar las adecuaciones reglamentarias necesarias en concordancia con el presente Decreto, antes del inicio del proceso electoral local de 2023-2024.\nTERCERO.- El requisito al que se hace referencia en el artículo 146, fracción IX de la Ley\nElectoral del Estado de Baja California, relativo a contar con el certificado de no inscripción en el Registro Nacional de Obligaciones Alimentarias, solo será exigible hasta que se implemente dicho registro a nivel nacional.\nLey Electoral del Estado de Baja California. Página 176\n.\nActualización Legislativa.\nÚltima reforma P. O. No. 60, Índice, 03-Oct-2025\nDADO en Sesión Extraordinaria de la XXIV Legislatura en la Ciudad de Mexicali, B.C., a los dos días del mes de septiembre del año dos mil veintitrés.\nDIP. MARÍA DEL ROCÍO ADAME MUÑOZ\nVICEPRESIDENTA\nEn suplencia por ausencia del Presidente del\nCongreso del Estado con fundamento en el artículo 44 de la Ley Orgánica del Poder\nLegislativo del Estado de Baja California\n(RÚBRICA)\nDIP. DUNNIA MONTSERRAT MURILLO LÓPEZ\nSECRETARIA\n(RÚBRICA)\nDE CONFORMIDAD CON LO DISPUESTO POR LA FRACCIÓN I DEL ARTÍCULO 49\nCALIFORNIA, IMPRÍMASE Y PUBLÍQUESE.\nMEXICALI, BAJA CALIFORNIA, A LOS DOS DÍAS DEL MES DE SEPTIEMBRE DEL\nAÑO DOS MIL VEINTITRÉS.\nMARINA DEL PILAR ÁVILA OLMEDA\nGOBERNADORA DEL ESTADO\nDE BAJA CALIFORNIA\n(RÚBRICA)\nCATALINO ZAVALA MÁRQUEZ\nSECRETARIO GENERAL DE GOBIERNO\nDEL ESTADO DE BAJA CALIFORNIA\n(RÚBRICA)\nSENTENCIA DE ACCIÓN DE INCONSTITUCIONALIDAD 198/2023 Y SU\nACUMULADA 200/2023, NOTIFICADOS LOS PUNTOS RESOLUTIVOS A ESTE\nOFICIO NÚM. SGA/MOKM/70/2024\nSEÑOR LICENCIADO EDUARDO ARANDA MARTÍNEZ\nSECRETARIO DE LA SECCIÓN DE TRÁMITE DE\nCONTROVERSIAS CONSTITUCIONALES Y DE\nACCIONES DE INCONSTITUCIONALIDAD DE LA\nLey Electoral del Estado de Baja California. Página 177\n.\nActualización Legislativa.\nÚltima reforma P. O. No. 60, Índice, 03-Oct-2025\nSUPREMA CORTE DE JUSTICIA DE LA NACIÓN\nEl Tribunal Pleno, en su sesión celebrada el veinte de febrero de dos mil veinticuatro, resolvió la acción de inconstitucionalidad 198/2023 y su acumulada 200/2023, promovidas por la Comisión Nacional de los derechos Humanos y el Partido Político Movimiento\nCiudadano, en los términos siguientes:\n“PRIMERO. Es procedente y parcialmente fundada la presente acción de inconstitucionalidad y su acumulada.\nSEGUNDO. Se desestima en la acción de inconstitucionalidad 200/2023 respecto de los artículos 6, párrafo cuarto, en su porción normativa ‘sin la intervención indebida de ninguna autoridad electoral’, y 21, fracción VI, en su porción normativa\n‘sin la intervención indebida de ninguna autoridad electoral o de cualquier otra índole’, de la Ley de Partidos Políticos del Estado de Baja California.\nTERCERO. Se reconoce la validez del procedimiento legislativo que culminó con el Decreto NO. 288 por el que se reforman y adicionan diversas disposiciones de la Ley Electoral, la Ley de Partidos Políticos, la Ley del Tribunal de Justicia Electoral, la Ley de Asistencia Social y la Ley de Participación Ciudadana, todas del Estado de\nBaja California, publicado en el Periódico Oficial de dicha entidad federativa el dos de septiembre de dos mil veintitrés.\nCUARTO. Se reconoce la validez de los artículos 7, párrafo segundo, 168, 327, fracciones III y VI, y 328, párrafo segundo, fracciones I, II, III y IV, de la Ley Electoral del Estado de Baja California y 6, fracciones III, X y XI, 7, (con la salvedad precisada en el resolutivo quinto), 10, fracciones IV, VII, IX, XXXIII, XXXIV y XXXV, 14, fracciones IX, XXII, XXIII y XXIV, 22 BIS y 22 TER de la Ley del Tribunal de Justicia Electoral del\nEstado de Baja California, reformados y adicionados, respectivamente, mediante el\nDecreto NO. 288, publicado en el Periódico Oficial de dicha entidad federativa el dos de septiembre de dos mil veintitrés.\nQUINTO. Se declara la invalidez de los artículos 21, párrafo sexto, en su porción normativa ‘Las autoridades electorales sólo podrán intervenir en los asuntos internos la vida interna de los partidos’, 139, párrafo segundo, en su porción normativa ‘y personas con discapacidad’, y 328, párrafo primero, en su porción normativa\n‘unánime’, de la Ley Electoral del Estado de Baja California y 6, fracción XVI, párrafos\nLey Electoral del Estado de Baja California. Página 178\n.\nActualización Legislativa.\nÚltima reforma P. O. No. 60, Índice, 03-Oct-2025 primero, en su porción normativa ‘por unanimidad’ y segundo, en su porción normativa ‘unánime’, y 7, párrafo segundo, en su porción normativa ‘unánime’, de la\nLey del Tribunal de Justicia Electoral del Estado de Baja California, reformados y adicionados, respectivamente, mediante el Decreto NO. 288, publicado en el Periódico\nOficial de dicha entidad federativa el dos de septiembre de dos mil veintitrés, la cual surtirá sus efectos, con la salvedad indicada en el resolutivo siguiente, a partir de la notificación de estos puntos resolutivos al Congreso del Estado de Baja California.\nSEXTO. La declaratoria de invalidez del artículo 139, párrafo segundo, en su porción normativa ‘y personas con discapacidad’, de la Ley Electoral del Estado de\nBaja California surtirá sus efectos a los doce meses siguientes a la notificación de estos resolutivos al Congreso del Estado de Baja California, en la inteligencia de que, dentro del referido plazo, ese órgano legislativo deberá llevar a cabo, conforme a los parámetros fijados en esta decisión, la consulta a las personas con discapacidad y emitir la regulación correspondiente.\nSÉPTIMO. Publíquese esta resolución en el Diario Oficial de la Federación, en el\nPeriódico Oficial del Estado de Baja California, así como en el Semanario Judicial de la Federación y su Gaceta.”\nCabe señalar que el Tribunal Pleno determinó que la declaratoria de invalidez de un artículo impugnado surtirá sus efectos a los doce meses siguientes a partir de la notificación de estos puntos resolutivos al Congreso del Estado de Baja california y, la de los restantes, a partir de la referida notificación, por lo que le solicito que gire instrucciones para que, a la brevedad, se practique la citada notificación, inclusive al titular del Poder ejecutivo de dicha entidad federativa.\nAsimismo, con el objeto de dar cumplimiento a lo determinado por el Tribunal Pleno en su sesión privada celebrada el doce de abril de dos mil diez, le solicito que remita a esta\nSecretaría General de Acuerdos únicamente copia certificada del documento en el que conste la notificación que se realice al Congreso del Estado de Baja California\nAtentamente\nLICENCIADO RAFAEL COELLO CETINA\n(RÚBRICA)\nARTÍCULO ÚNICO TRANSITORIO DEL DECRETO No. 145, POR EL QUE SE\nAPRUEBA LA REFORMA AL ARTÍCULO 139; PUBLICADO EN EL PERIÓDICO OFICIAL\nLA H. XXV LEGISLATURA, SIENDO GOBERNADORA CONSTITUCIONAL LA C. MARINA\nDEL PILAR ÁVILA OLMEDA 2021-2027.\nLey Electoral del Estado de Baja California. Página 179\n.\nActualización Legislativa.\nÚltima reforma P. O. No. 60, Índice, 03-Oct-2025\nTRANSITORIO\nÚNICO.- La presente reforma entrará en vigor al día siguiente al de su publicación en el\nPeriódico Oficial del Estado de Baja California.\nDADO en Sesión Ordinaria de la XXV Legislatura en la Ciudad de Mexicali, B.C., a los once días del mes de septiembre del año dos mil veinticinco.\nDIP. JAIME EDUARDO CANTÓN ROCHA\nPRESIDENTE\n(RÚBRICA)\nDIP. MICHELLE ALEJANDRA TEJEDA MEDINA\nSECRETARIA\n(RÚBRICA)\nDE CONFORMIDAD CON LO DISPUESTO POR LA FRACCIÓN I DEL ARTÍCULO 49\nCALIFORNIA, IMPRÍMASE Y PUBLÍQUESE.\nMEXICALI, BAJA CALIFORNIA, A LOS 17 DÍAS DEL MES DE SEPTIEMBRE DEL\nAÑO DOS MIL VEINTICINCO.\nMARINA DEL PILAR ÁVILA OLMEDA\nGOBERNADORA DEL ESTADO\nDE BAJA CALIFORNIA\n(RÚBRICA)\nALFREDO ÁLVAREZ CÁRDENAS\nSECRETARIO GENERAL DE GOBIERNO\nDEL ESTADO DE BAJA CALIFORNIA\n(RÚBRICA)\nLey Electoral del Estado de Baja California. Página 180",
  "ordenamiento": "REGLAMENTO",
  "jurisdiccion": "BAJA CALIFORNIA",
  "fuente_oficial": "Periódico Oficial",
  "FECHA PER OFIC": "2025/10/03",
  "ESTATUS": "VIGENTE",
  "TOMO": "TOMO_I",
  "URL": "https://www.congresobc.gob.mx/Documentos/ProcesoParlamentario/Leyes/TOMO_I/20251003_LEYELECTORAL.PDF",
  "es_escaneado": false,
  "tiene_tablas": true,
  "materia": [
    "administrativo",
    "legislativo",
    "gobernanza"
  ]
}