{
  "titulo": "Ley DE LOS DERECHOS, PROTECCIÓN E INTEGRACIÓN DE LAS PERSONAS ADULTAS MAYORES EN EL ESTADO DE BAJA C",
  "Contenido": "Ley de los Derechos, Protección e Integración de las Personas\nPublicada en el Periódico Oficial No. 2, Tomo CXIX, Sección II,\nTÍTULO PRIMERO\nCAPÍTULO ÚNICO\nDISPOSICIONES GENERALES\nArtículo 1.- Esta Ley es de orden público e interés social, y de observancia general en el Estado de Baja California. Tiene por objeto garantizar y reconocer los derechos de las personas adultas mayores, para propiciarles una plena protección, bienestar y calidad de vida, así como para lograr su integración al desarrollo social, económico, político y cultural; estableciendo las bases y disposiciones para su cumplimiento, mediante la regulación de:\nPárrafo Reformado\nI. La política pública estatal para la observancia de los derechos de las personas adultas mayores;\nFracción Adicionado\nII. Los principios, objetivos, programas, responsabilidades e instrumentos que la administración pública estatal y municipal, deberán observar en la planeación y aplicación de la política pública estatal; y,\nFracción Adicionado\nIII. El Consejo Estatal para la Protección e Integración de las Personas Adultas\nMayores.\nFracción Adicionado\nArtículo Reformado\nArtículo 2.- La aplicación, responsabilidad de vigilancia y seguimiento de esta Ley corresponde:\nI. Al Ejecutivo Estatal, a través de las dependencias y entidades que integran la\nAdministración Pública, así como por los órganos descentralizados y entidades paraestatales, en el ámbito de sus respectivas competencias y jurisdicción;\nFracción Reformada\nIII. A los Ayuntamientos de los Municipios del Estado, por conducto de las dependencias y entidades de la Administración Pública;\nFracción Reformada\nLey de los Derechos, Protección e Integración de las Personas Adultas Mayores Página 1\nIV. La familia de las personas adultas mayores vinculada por el parentesco, de conformidad con lo dispuesto por los ordenamientos jurídicos aplicables;\nFracción Adicionada\nV. Los ciudadanos y la sociedad civil organizada; y,\nFracción Adicionada\nVI. El Consejo Estatal para la Protección e Integración de las Personas Adultas\nMayores.\nFracción Adicionada\nLos sectores público, social y privado, en términos de lo dispuesto por este artículo, celebrarán los convenios o acuerdos de colaboración entre sí, y con las instancias federales correspondientes que realicen alguna o varias actividades que constituyen el objeto de esta\nLey.\nArtículo Reformada\nArtículo 3.- La Administración Pública Municipal, en el ámbito de su competencia, quedará sujeta a las disposiciones establecidas en la presente ley, sin prejuicio de las obligaciones que en la misma materia se prevean en otros ordenamientos aplicables.\nArtículo 4.- El Ejecutivo Estatal y los Ayuntamientos deberán prever, en su Proyecto de\nPresupuesto de Egresos, los recursos necesarios para la atención integral de las personas adultas mayores.\nArtículo 5.- En el Proyecto de Ley de Ingresos Estatal y Municipal, se considerarán descuentos, exenciones y beneficios a favor de las personas adultas mayores, de conformidad con las disposiciones fiscales aplicables.\nArtículo 6.- Para los efectos de este ordenamiento se entenderá por:\nI. Asistencia Social: Al conjunto de acciones tendientes a modificar y mejorar las circunstancias de carácter social que impidan al individuo su desarrollo integral, así como la protección física, mental y social de personas en estado de necesidad, desprotección o desventaja física o mental; propiciando su incorporación plena a la sociedad.\nII. Atención integral: Satisfacción de las necesidades físicas, materiales, biológicas, emocionales, sociales, laborales, culturales, recreativas, productivas y espirituales de las personas adultas mayores, considerando sus hábitos, capacidades funcionales, usos, costumbres y preferencias, para facilitarles una vejez plena y sana;\nIII. Calidad del servicio: Conjunto de características que confieren al servicio la capacidad de satisfacer tanto las necesidades como las demandas actuales y potenciales;\nFracción Adicionada, recorriéndose las subsecuentes\nLey de los Derechos, Protección e Integración de las Personas Adultas Mayores Página 2\nIV. Consejo Estatal para la Protección e Integración de las Personas Adultas\nMayores: Es un órgano honorario de consulta, asesoría y evaluación de las acciones de concertación, coordinación, planeación y promoción necesarias para favorecer la plena integración social y desarrollo de las personas adultas mayores;\nV. Cuidador: Aquella persona mayor de edad que preste sus servicios, ya sea de forma temporal o permanente en los centros de salud, asilos y albergues reconocidos por la\nSecretaría de Bienestar, asista o cuide a un adulto mayor afectado, o no, por cualquier tipo de discapacidad o incapacidad que le dificulte o impida el desarrollo normal de sus actividades vitales o de sus relaciones sociales;\nFracción Reformada\nVI. Desarrollo Integral: El conjunto de acciones que realizan las dependencias y entidades de la Administración Pública del Gobierno del Estado y de los Municipios y la sociedad organizada, encaminadas al desarrollo de todos sus potenciales humanos en los campos tanto físico, como psíquico, emocional, espiritual, de relaciones humanas y aumento de la capacidad económica y productiva de las personas adultas mayores;\nVII. Envejecimiento: Proceso gradual que se desarrolla durante el curso de vida y que conlleva cambios biológicos, fisiológicos, psico-sociales y funcionales de variadas consecuencias, las cuales se asocian con interacciones dinámicas y permanentes entre el sujeto y su medio;\nFracción Adicionada\nVIII. Envejecimiento activo y saludable: Proceso por el cual se optimizan las oportunidades de bienestar físico, mental y social, de participar en actividades sociales, económicas, culturales, espirituales y cívicas, y de contar con protección, seguridad y atención, con el objetivo de ampliar la esperanza de vida saludable y la calidad de vida de todos los individuos en la vejez, y permitirles así seguir contribuyendo activamente a sus familias, amigos, comunidades y naciones. El concepto de envejecimiento activo y saludable se aplica tanto a individuos como a grupos de población;\nFracción Adicionada, recorriéndose las subsecuentes\nIX. Familia: Los parientes de las personas adultas mayores, atendiendo lo dispuesto por la normatividad estipulada en el Código Civil para el Estado de Baja California, así como el matrimonio y concubinato;\nX. Género: Conjunto de papeles, atribuciones y representaciones de hombres y mujeres en nuestra cultura que toman como base la diferencia sexual;\nFracción Adicionada, recorriéndose las subsecuentes\nXI. Geriatría: Es la especialidad médica dedicada al estudio de las enfermedades propias de las personas adultas mayores;\nLey de los Derechos, Protección e Integración de las Personas Adultas Mayores Página 3\nXII. Gerontología: Es el estudio integral del envejecimiento, sus causas, efectos y consecuencias en el ser humano;\nXIII. Integración social: Es el resultado de las acciones que realizan las dependencias y entidades de la Administración Pública Estatal y Municipal, las familias y la sociedad organizada, orientadas a modificar y superar las condiciones que impidan a las personas adultas mayores su desarrollo integral, así como la protección física o mental y social de personas en estado de necesidad, desprotección o desventaja física y mental, hasta lograr su incorporación a una vida plena y productiva;\nXIV. Ley: La presente Ley de los Derechos, Protección e Integración de las Personas\nAdultas Mayores en el Estado de Baja California;\nXV. Personas adultas mayores: Las personas que cuentan con sesenta años o más de edad y que se encuentran domiciliadas o de paso en el Estado, mismas que podrán estar en las siguientes condiciones:\na) Independientes: cuando sean aptas para desarrollar actividades físicas, mentales o ambas sin ayuda permanente;\nb) Semidependiente: cuando sus condiciones físicas y mentales aún les permiten valerse por sí mismas, aunque con ayuda permanente parcial;\nc) Dependientes absolutos: cuando sufran de una enfermedad crónica o degenerativa por la que requieran ayuda permanente total o la canalización a alguna institución de asistencia; y,\nd) En situación de riesgo o desamparo: cuando por problemas de salud, abandono, carencia de apoyos económicos, familiares, contingencias ambientales o desastres naturales, requieran de asistencia y protección del Gobierno del Estado y de la Sociedad civil\nOrganizada.\nXVI. Vejez: Construcción social de la última etapa del curso de vida; y,\nFracción Adicionada, recorriéndose la subsecuente\nXVII. Violencia Contra las Personas Adultas Mayores. Cualquier acción u omisión que les cause daño o sufrimiento psicológico, físico, patrimonial, económico, sexual o la muerte tanto en el ámbito privado como en el público.\nFracción Adicionada\nArtículo Reformado\nArtículo 6 BIS.- Los tipos de violencia contra las Personas Adultas Mayores, son:\nI. La violencia psicológica. Es cualquier acto u omisión que dañe la estabilidad psicológica, que puede consistir en: negligencia, abandono, descuido reiterado, insultos, Ley de los Derechos, Protección e Integración de las Personas Adultas Mayores Página 4 humillaciones, devaluación, marginación, indiferencia, comparaciones destructivas, rechazo, restricción a la autodeterminación y amenazas, las cuales conllevan a la víctima a la depresión, al aislamiento, a la devaluación de su autoestima e incluso al suicidio;\nII. La violencia física. Es cualquier acto que inflige daño no accidental, usando la fuerza física o algún tipo de arma u objeto que pueda provocar o no lesiones ya sean internas, externas o ambas;\nIII. La violencia patrimonial. Es cualquier acto u omisión que afecta la supervivencia de la víctima. Se manifiesta en: la transformación, sustracción, destrucción, retención o distracción de objetos, documentos personales, bienes y valores, derechos patrimoniales o recursos económicos destinados a satisfacer sus necesidades y puede abarcar los daños a los bienes comunes o propios de la víctima; hecha excepción de que medie acto de autoridad fundado o motivado;\nIV. La violencia económica. Es toda acción u omisión del agresor que afecta la supervivencia económica de la víctima. Se manifiesta a través de limitaciones encaminadas a controlar el ingreso de sus percepciones económicas, así como la percepción de un salario menor por igual trabajo, dentro de un mismo centro laboral;\nV. La violencia sexual. Es cualquier acto que degrada o daña el cuerpo y/o sexualidad de la víctima y que por tanto atenta contra su libertad, dignidad e integridad física. Es una expresión de abuso de poder;\nFracción Reformada\nVI. La violencia institucional. Son los actos u omisiones de las y los servidores públicos que discriminen o tengan como fin dilatar, obstaculizar o impedir el goce y ejercicio de los derechos humanos de las personas adultas mayores, así como su acceso al disfrute de políticas públicas; y,\nFracción Adicionada, recorriéndose la subsecuente\nVII. Cualesquiera otras formas análogas que lesionen o sean susceptibles de dañar la dignidad, integridad o libertad de las Personas Adultas Mayores, como son de manera enunciativa más no limitativa, las siguientes:\nPárrafo de la Fracción Reformado\na) Abandono: La falta de acción deliberada o no para atender de manera integral las necesidades de una persona mayor que ponga en peligro su vida o su integridad física, psíquica o moral;\nInciso Adicionado\nb) Discriminación: Cualquier distinción, exclusión, restricción que tenga como objetivo o efecto anular o restringir el reconocimiento, goce o ejercicio en igualdad de condiciones de los derechos humanos y las libertades fundamentales en la esfera política, económica, social, cultural o en cualquier otra esfera de la vida pública y privada;\nInciso Adicionado\nLey de los Derechos, Protección e Integración de las Personas Adultas Mayores Página 5\nc) Discriminación múltiple: Cualquier distinción, exclusión o restricción hacia la persona adulta mayor fundada en dos o más factores de discriminación;\nInciso Adicionado\nd) Discriminación por edad en la vejez: Cualquier distinción, exclusión o restricción basada en la edad que tenga como objetivo o efecto anular o restringir el reconocimiento, goce o ejercicio en igualdad de condiciones de los derechos humanos y libertades fundamentales en la esfera política, económica, social, cultural o en cualquier otra esfera de la vida pública y privada;\nInciso Adicionado\ne) Maltrato: Acción u omisión, única o repetida, contra una persona mayor que produce daño a su integridad física, psíquica y moral y que vulnera el goce o ejercicio de sus derechos humanos y libertades fundamentales, independientemente de que ocurra en una relación de confianza; y,\nInciso Adicionado\nf) Negligencia: Error involuntario o falta no deliberada, incluido entre otros, el descuido, omisión, desamparo e indefensión que le causa un daño o sufrimiento a una persona mayor, tanto en el ámbito público como privado, cuando no se hayan tomado las precauciones normales necesarias de conformidad con las circunstancias.\nInciso Adicionado\nFracción Reformada\nArtículo Adicionado\nArtículo Reformado\nTÍTULO SEGUNDO\nPRINCIPIOS Y DERECHOS\nCAPÍTULO I\nDE LOS PRINCIPIOS\nArtículo 7.- Para la aplicación, observación y cumplimiento de esta ley, son principios rectores los siguientes:\nI. Autonomía y autorrealización: Las acciones que se realicen en beneficio de las personas adultas mayores para desarrollar y mantener su capacidad decisoria, fortalecer su autosuficiencia, controlar su vida, y su desarrollo personal y productivo;\nFracción Reformada\nII. Heterogeneidad: Visión que toma en cuenta características particulares de las personas adultas mayores como un grupo plural, determinada por diferencias socioeconómicas, culturales, de edad, sexo, origen étnico, condición migratoria o de desplazamiento y residencia urbana o rural, sin menoscabo de los beneficios otorgados por esta Ley;\nLey de los Derechos, Protección e Integración de las Personas Adultas Mayores Página 6\nIII. La participación: La inserción o incorporación, intervención de las personas adultas mayores en todos los órdenes de la vida pública, y en los asuntos y aspectos que los vinculen directamente deberán ser consultados y promover su participación;\nIV. Calidad en el trato: Es el trato justo y proporcional en las condiciones de acceso y disfrute de los satisfactores necesarios para el bienestar de las personas adultas mayores, sin distinción;\nV. Corresponsabilidad: Concurrencia de los sectores público, privado y social, así como de la comunidad y la familia para la consecución del objeto de esta Ley;\nVI. Solidaridad intergeneracional: Construcción o fortalecimiento de relaciones de respeto, apoyo, estímulo e intercambio de experiencias y conocimientos entre las personas adultas mayores y el resto de los grupos que forman la sociedad;\nVII. Atención diferenciada: La obligación de las dependencias y entidades estatales y municipales dentro de sus respectivas atribuciones y competencias, a formular e implementar programas acordes a diferentes etapas, necesidades, características y circunstancias de las personas adultas mayores;\nVIII. Atención preferente: La obligación de la familia, iniciativa privada, y de las de las dependencias de los distintos órdenes de gobierno, a dar a las personas adultas mayores un trato preferencial en el turno y la atención por sobre los demás grupos de edad, para que de esta forma, las personas adultas mayores accedan a los servicios sin dificultad y que brindan las dependencias;\nFracción Reformada\nIX. Dignificación: El derecho de las personas adultas mayores a que se respete su integridad física, emocional y moral, así como la protección de su imagen, autonomía, pensamiento, dignidad y valores, los cuales deberán ser considerados en la formulación de planes y programas de las dependencias de gobierno y en las acciones que emprendan las organizaciones civiles y privadas;\nFracción Reformada\nX. Equidad: Es el trato justo y proporcional en las condiciones de acceso y disfrute de los satisfactores necesarios para el bienestar de las personas adultas mayores, sin distinción por sexo, situación económica, identidad étnica, fenotipo, credo, religión o cualquier otra circunstancia.\nFracción Adicionada\nXI. Igualdad Sustantiva: Es el acceso al mismo trato y oportunidades para el reconocimiento, goce o ejercicio de los derechos humanos y las libertades fundamentales.\nFracción Adicionada\nArtículo Reformado\nLey de los Derechos, Protección e Integración de las Personas Adultas Mayores Página 7\nCAPÍTULO II\nDE LOS DERECHOS\nArtículo 8.- Son derechos de las personas adultas mayores, además de aquellos que les reconozcan otras leyes y ordenamientos jurídicos, los siguientes:\nI. Disfrutar plenamente, sin discriminación o distinción alguna, de los derechos que ésta\nLey consagra, así como de disfrutar de una vida libre de violencia física y moral;\nII. Vivir en una sociedad sensibilizada respecto a sus problemas, sus necesidades, sus méritos, sus responsabilidades, sus capacidades y experiencias;\nIII. Recibir protección por parte de su familia, así como del gobierno estatal y de los municipales dentro de sus respectivas atribuciones y competencias y de la sociedad en general.\nIV. Acceder en igualdad de oportunidades, a los programas sociales, y a los servicios de salud, que para tal efecto establezcan las instituciones públicas y privadas;\nV. Disfrutar de una vida con calidad, siendo obligación de la familia, de los órganos estatales y municipales de gobierno de acuerdo a sus respectivas competencias y de la sociedad en general, garantizar a las personas adultas mayores, no sólo su supervivencia sino una existencia digna con el acceso efectivo a los mecanismos necesarios para ello;\nVI. Ser respetados en su persona y en su integridad física, psicoemocional y sexual, así como de ser protegidos de toda forma de explotación;\nVII. Gozar de oportunidades, para mejorar progresivamente las capacidades que les faciliten el ejercicio de sus derechos en condiciones de igualdad;\nVIII. Vivir en entornos seguros y dignos que cumplan con sus necesidades y requerimientos y en donde ejerzan libremente sus derechos;\nIX. Vivir en el seno de su Familia o a mantener relaciones personales y contacto directo con ella aún en el caso de estar separados;\nX. Expresar su opinión libremente, conocer sus derechos y participar en el ámbito familiar y comunitario, así como en todo procedimiento administrativo o judicial que afecte sus esferas personal, familiar y social;\nXI. Acceso a la justicia en cualquier procedimiento judicial o administrativo que involucre a las personas adultas mayores, garantizando se les dé una atención preferente;\nFracción Reformada\nXII. Recibir el apoyo del gobierno estatal y de los municipales de acuerdo a sus respectivas competencias en lo relativo al ejercicio y respeto de sus derechos, a través de las instituciones creadas para tal efecto;\nXIII. Tener acceso a los satisfactores necesarios, considerando alimentos, bienes, servicios y las condiciones humanas o materiales, para su atención integral;\nLey de los Derechos, Protección e Integración de las Personas Adultas Mayores Página 8\nXIV. Tener acceso preferente a los servicios de salud, en los términos del párrafo cuarto del artículo 4 de la Constitución Política de los Estados Unidos Mexicanos, con el objeto de que gocen cabalmente de bienestar físico, mental, psicoemocional y sexual;\nXV. Recibir por parte de especialistas médicos Valoración Geriátrica Integral, además de orientación y capacitación en materia de salud, nutrición e higiene, así como a todo aquello que favorezca su capacidad personal;\nFracción Reformada\nXVI. Conformar organizaciones para promover su desarrollo e incidir en las acciones dirigidas a este sector;\nXVII. Recibir información sobre las instituciones que prestan servicios para su atención integral;\nXVIII. Recibir de manera preferente, educación conforme lo señala el artículo 3º de la\nXIX. Participar en la vida cultural, deportiva y recreativa de su comunidad;\nXX. Participar en los procesos productivos, de educación y capacitación de su comunidad;\nXXI. Gozar de oportunidades de acceso al trabajo que les permitan un ingreso, a recibir una capacitación adecuada, a recibir la protección de las disposiciones de la Ley\nFederal del Trabajo y de otros ordenamientos de carácter laboral, así como a laborar en condiciones óptimas y en instalaciones que garanticen su seguridad e integridad física, y\nXXII. Ser sujeto de programas de asistencia social cuando se encuentren en caso de desamparo, discapacidad o pérdida de sus medios de subsistencia.\nArtículo Reformado\nSECCIÓN I\nDERECHO A LA PENSIÓN ALIMENTARIA\nArtículo 9.- Las personas adultas mayores residentes en el Estado de Baja California, que no reciban ningún tipo de ingreso permanente por concepto de remuneración, jubilación, pensión o dividendos producto de inversión, tienen derecho a recibir una pensión diaria no menor a la mitad del salario mínimo vigente en el Estado.\nArtículo 10.- La pensión es de carácter público, su objetivo es superar y solventar condiciones de inseguridad social, pobreza de capacidades, oportunidades o patrimonial y no está condicionada a la participación, colaboración o cooperación del Adulto Mayor en actividades políticas. políticos, electorales, de lucro y otros distintos a los establecidos. Quien haga uso indebido de\nLey de los Derechos, Protección e Integración de las Personas Adultas Mayores Página 9 acuerdo a las disposiciones legales aplicables.\nArtículo 11.- Los adultos mayores tendrán derecho a obtener información suficiente y beneficio establecido por esta Ley. Recibirán un trato digno, solidario, subsidiario, respetuoso y equitativo.\nArtículo 12.- El Ejecutivo Estatal y los Ayuntamientos deberán incluir en sus Proyectos de Presupuesto de Egresos, la asignación que garantice, efectivamente, el derecho a la pensión alimentaria de las personas adultas mayores.\nArtículo 13.- El Congreso del Estado deberá aprobar, en el Decreto de Presupuesto anual, el monto suficiente para hacer efectivo el derecho a la pensión alimentaria de las personas adultas mayores residentes en el Estado de Baja California.\nArtículo 14.- La forma como se hará valer la pensión alimentaria, será a través de una tarjeta electrónica, que será expedida por el Gobierno del Estado a través de la Secretaría de\nBienestar, y la cual podrá ser utilizada en los principales centros comerciales y establecimientos autorizados.\nArtículo Reformado\nArtículo 15.- Son requisitos mínimos para obtener la pensión mensual los siguientes:\nI. Tener sesenta años o más, al momento de solicitar su inscripción al padrón de beneficiarios de la pensión;\nII. Contar con una residencia mínima en el Estado de seis meses al momento de solicitar su inscripción al padrón de beneficiarios de la pensión;\nIII. No contar con pensión derivada de algún sistema de seguridad social; y\nIV. Que se encuentre en situación de riesgo o desamparo en términos de la presente\nLey.\nLa verificación de la residencia, la elaboración y actualización permanente del padrón esta Ley, se fijarán en el Reglamento de esta Ley.\nArtículo 16- La atención, servicio, trámites y gestiones necesarias para cumplir con conforme a la normatividad aplicable a quien incumpla con esta disposición.\nTÍTULO TERCERO\nDEBERES DEL ESTADO, LOS AYUNTAMIENTOS, LAS INSTITUCIONES, Y LA FAMILIA\nCAPÍTULO I\nLey de los Derechos, Protección e Integración de las Personas Adultas Mayores Página 10\nDE LOS DEBERES DEL ESTADO\nArtículo 17.- El Estado garantizará las condiciones óptimas de salud, educación, nutrición, desarrollo integral, y seguridad social a las personas adultas mayores, domiciliadas en el\nEstado. Igualmente promoverá:\nI. Que toda institución pública o privada que brinde servicios a las personas adultas mayores deberá contar con la infraestructura, mobiliario y equipo adecuado, así como con los recursos humanos necesarios para que se realicen los trámites administrativos;\nII. Que ninguna persona adulta mayor sea socialmente marginada o discriminada en ningún espacio público o privado por razón de su origen étnico o nacional, el género, la edad, las discapacidades, la condiciones de salud, la religión, las opiniones, las preferencias sexuales, el estado civil o cualquier otra que atente contra la dignidad humana y tenga por objeto anular o menoscabar sus derechos y libertades.\nIII. La celebración de acuerdos de concertación con la iniciativa privada, a fin de que la atención preferencial para las personas adultas mayores, también sea proporcionada en instituciones bancarias, tiendas de autoservicio y otras empresas mercantiles;\nIV. La existencia de condiciones adecuadas para las personas adultas mayores tanto en el transporte público como en los espacios arquitectónicos;\nV. Brindará las asesorías necesarias a las asociaciones civiles cuya finalidad ulterior resulte en una mayor integración, en todos los ámbitos, de las personas adultas mayores;\nVI. Que los organismos de los diferentes órdenes de gobierno, trabajen para la integración social y económica y la rehabilitación física de los adultos mayores;\nVII. Que las asociaciones civiles trabajen en la capacitación laboral, integración social y rehabilitación física de los adultos mayores;\nVIII. La coordinación con los Ayuntamientos, para el establecimiento de casas hogar, albergues, residencias, centros de estancia, o cualquier otro centro de atención de personas adultas mayores; cuyo objeto sea el de prestarles servicios de protección, asistencia, cuidados físicos, psicológicos y sociales;\nIX. Visitas de inspección y vigilancia por parte de las dependencias estatales, a casas hogar, albergues, residencias, centros de estancia, o cualquier otro centro de atención de personas adultas mayores, para verificar las condiciones de funcionamiento, capacitación de su personal, modelo de atención y las condiciones de la calidad de vida;\nX. Programas en los que las personas adultas mayores sean beneficiarias de créditos a bajas tasas o sean beneficiarios de subsidios, para la adquisición o mejoramiento de sus viviendas;\nXI. La difusión de esta ley para que la sociedad y las familias respeten a los adultos mayores e invariablemente otorguen el reconocimiento a su dignidad;\nXII. A través del Ejecutivo Estatal, en el ámbito de su competencia y de conformidad\nLey de los Derechos, Protección e Integración de las Personas Adultas Mayores Página 11 con las disposiciones legales, aportará los recursos materiales, humanos, técnicos y financieros que sean necesarios y su disponibilidad presupuestal le permita, para la integración social de las personas adultas mayores; y\nXIII. Promover de manera coordinada con la Secretaria de Turismo las Actividades diseñadas para personas adultas mayores, particularmente las que se refieren al rescate y transmisión de la cultura y de la historia; así mismo promoverá actividades de recreación turística con tarifas preferentes, diseñadas para personas adultas mayores;\nXIV. Suscitar convenios con las empresas del ramo para ofrecer a las personas adultas mayores, tarifas preferenciales y/o gratuitas en los centros públicos o privados de entretenimiento, recreación, cultura, deporte, y hospedaje en hoteles.\nXV. La celebración de convenios con el Sistema Estatal de Salud, a fin de promover descuentos o tarifas preferenciales en los bienes y servicios que presta la iniciativa privada en materia de salud, específicamente en materia de atención hospitalaria.\nArtículo Reformado\nArtículo 18.- El Estado garantizará que el personal que preste servicios en instituciones públicas y privadas que brinden asistencia social a las personas adultas mayores, sea seleccionado previo estudio desde los puntos de vista médico, psicológico, social y académico, y que determinen la calidad del aspirante y su aptitud para el trabajo que de él se espere.\nArtículo 19.- El Estado garantizará que las instituciones públicas y privadas dedicadas a la asistencia de las personas adultas mayores, en coordinación con las dependencias de los distintos órdenes de gobierno y las universidades, implementen programas de servicio social a fin de que la comunidad estudiantil de las distintas áreas puedan compenetrarse en la atención de las personas adultas mayores.\nCAPÍTULO II\nDE LOS AYUNTAMIENTOS\nArtículo 20.- Son deberes y facultades de los Ayuntamientos en materia de protección a las personas adultas mayores:\nI. Garantizar el cumplimiento de esta Ley, así como formular, definir, conducir, articular y evaluar el padrón de adultos mayores con residencia dentro de su jurisdicción.\nII. Formular y desarrollar programas municipales de atención a personas adultas mayores conforme a los principios y objetivos de los Planes Estatal y Municipal de Desarrollo;\nIII. Celebrar convenios de colaboración en la materia de protección de personas adultas mayores con los Gobiernos Estatal y de otros Municipios de la entidad, así como con entidades de los sectores público, social, privado y con particulares;\nLey de los Derechos, Protección e Integración de las Personas Adultas Mayores Página 12\nIV. Dar cumplimiento en la esfera de su competencia a la presente Ley, así como de las demás disposiciones legales y reglamentarias aplicables en la materia;\nV. Destinar en los estacionamientos públicos, los espacios necesarios para el ascenso y descenso de los adultos mayores;\nVI. Promover en coordinación con el Gobierno Estatal, el establecimiento de casas hogar, albergues, residencias, centros de estancia, o cualquier otro centro de atención de personas adultas mayores; cuyo objeto sea el de prestarles servicios de protección, asistencia, cuidados físicos, psicológicos y sociales;\nVII. Realizar visitas de inspección y vigilancia a casas hogar, albergues, residencias, centros de estancia, o cualquier otro centro de atención de personas adultas mayores, para verificar las condiciones de funcionamiento, capacitación de su personal, modelo de atención y las condiciones de la calidad de vida;\nVIII. Denunciar ante las autoridades competentes, las irregularidades de las cuales se percate, como resultado de la inspección y vigilancia, mencionadas en la fracción anterior;\nIX. Impulsar exenciones fiscales permitidas conforme a la ley de la materia, dirigidas a las personas adultas mayores, y a las personas que efectúen donaciones en especie o en efectivo a casas hogar, albergues, residencias, guarderías o cualquier otro centro de atención de personas adultas mayores; cuyo objeto sea el de prestarles servicios de protección, asistencia, cuidados físicos, psicológicos y sociales;\nX. Implementar en las dependencias y entidades que presten servicios al público, una ventanilla de atención preferente para las personas adultas mayores; y\nXI. Las demás que le confieran esta ley y otros ordenamientos legales y reglamentarios sobre la materia.\nArtículo Reformado\nArtículo 21.- Las bases y modalidades del ejercicio coordinado de las atribuciones de los gobiernos Estatal y Municipales, se establecerá en los convenios correspondientes que al de la presente Ley, de la Ley del Régimen Municipal para el Estado de Baja California, de las políticas públicas en la materia, y demás ordenamientos legales aplicables a la materia.\nCAPÍTULO III\nDE LOS DEBERES DE LAS INSTITUCIONES\nArtículo 22.- Se consideran instituciones de atención a las personas adultas mayores, aquellas instituciones públicas, privadas o sociales constituidas exclusivamente para su\nLey de los Derechos, Protección e Integración de las Personas Adultas Mayores Página 13 beneficio.\nArtículo 23.- Todas las instituciones públicas, privadas o sociales que atienden a las personas adultas mayores, están obligadas a observar y respetar los derechos que ésta y otras Leyes les reconozcan.\nArtículo 24.- El personal que labore, así como aquellos que presten servicios voluntarios en instituciones públicas, privadas y sociales dedicadas a la atención y asistencia de las personas adultas mayores, deberán recibir cursos de capacitación a efecto de poder contar con la vocación, capacidad y conocimientos en materia de geriatría, gerontología y tanatología; asimismo, deberán conducirse con absoluto respeto a la dignidad humana y derechos inherentes a las personas adultas mayores con estricto apego a esta legislación y demás aplicables.\nLa Secretaría de Salud en coordinación con la Secretaría de Educación, serán las autoridades encargadas de capacitar a las y los cuidadores para que puedan desempeñar a cabalidad dichas funciones, debiendo abordarse como mínimo los siguientes rubros:\nPárrafo Reformado\na) Información básica sobre el proceso de envejecimiento;\nb) Información básica sobre los derechos de las personas adultas mayores;\nc) Información básica sobre primeros auxilios.\nEstos rubros se deberán desplegar en detalle en el reglamento correspondiente.\nLa Secretaría de Bienestar, el Sistema para el Desarrollo Integral de la Familia, la\nSecretaría de Educación y la Secretaría de Salud, todas del Estado y en coordinación, promoverán que las instituciones de educación superior firmen un convenio, a fin de que los estudiantes que hayan terminado sus estudios y que presten sus servicios como cuidadores en los centros de salud, asilos y albergues que estén reconocidos por dichas instituciones del\nEstado, liberen de esta forma su servicio social obligatorio.\nPárrafo Reformado\nArtículo Reformado\nArtículo 25.- Cuando una institución pública, privada o social, se haga cargo de una persona adulta mayor, está obligada a:\nI. Atender adecuadamente su alimentación, habitación y asistencia médica;\nII. Otorgar los cuidados integrales que requiera su salud física y mental;\nIII. Proporcionar actividades culturales y recreativas;\nIV. Integrar un expediente personal con la historia clínica y un registro con los datos de\nLey de los Derechos, Protección e Integración de las Personas Adultas Mayores Página 14 identificación, estado de salud, tratamientos, entre otros;\nV. Dar seguimiento a la evolución y evaluación de los casos atendidos, registrando los datos en los expedientes personales correspondientes;\nVI. Obtener en caso de ser posible, los nombres, domicilios y teléfonos de sus familiares; y\nVII. Expedir copia del expediente a los familiares autorizados, a las autoridades judiciales o a las instituciones que continúen la atención de las personas adultas mayores, cuando lo soliciten.\nArtículo 26.- Cuando la institución pública, privada o social, otorgue su atención a una persona adulta mayor, examinará, en primer término, la posibilidad de su reintegración familiar, procurando en todo momento evitar circunstancias que pongan en riesgo a la persona adulta mayor.\nArtículo Reformado\nCAPÍTULO IV\nDE LOS DEBERES DE LA FAMILIA\nArtículo 27.- Se reconoce a la familia como la institución fundamental en la que debe tener lugar la protección y desarrollo de la persona adulta mayor, así como procurar su bienestar emocional y que deberá cumplir su función social, por lo tanto, de manera constante y permanente deberá velar por cada una de las personas adultas mayores que formen parte de ella, siendo responsable de proporcionar los satisfactores necesarios para su atención y desarrollo integral.\nArtículo Reformado\nArtículo 28.- Sólo en caso de enfermedad, decisión personal de la persona adulta mayor o por causas de fuerza mayor, podrá solicitar su ingreso en alguna institución asistencial pública o privada dedicada al cuidado de personas adultas mayores.\nArtículo 29.- La familia de la persona adulta mayor tendrá respecto de ésta, los siguientes deberes:\nI. Conocer los derechos de las personas adultas mayores, previstos en la presente demás ordenamientos para su debida observancia;\nII. Evitar que alguno de sus integrantes cometa cualquier acto de discriminación, abuso, explotación, aislamiento, violencia y actos jurídicos que pongan en riesgo su persona, bienes y derechos;\nIII. Proporcionar oportuna y adecuadamente alimentación, vestido, habitación y el cuidado de la salud física y mental, de acuerdo a sus posibilidades económicas, conforme a lo\nLey de los Derechos, Protección e Integración de las Personas Adultas Mayores Página 15 dispuesto por el Código Civil para el Estado de Baja California, así como asistencia permanente y oportuna;\nIV. Las personas adultas mayores tendrán el derecho de ser examinados cuando menos una vez al año, para mantener la estabilidad de su salud y recibir los tratamientos que requieran en caso de enfermedad;\nV. Fomentar la convivencia familiar cotidiana, donde la persona adulta mayor participe activamente, y promover al mismo tiempo, los valores que incidan en sus necesidades afectivas, de protección y de apoyo;\nVI. Fomentar su independencia, respetar sus decisiones y mantener su privacidad;\nVII. Gestionar ante las dependencias e instituciones del Estado y los Municipios, así como de las organizaciones civiles e iniciativa privada, el reconocimiento y respeto de los derechos de los adultos mayores;\nVIII. Contribuir a que la persona adulta mayor se mantenga productiva y socialmente integrada; y\nIX. Abstenerse de forzar a la persona adulta mayor a realizar actos de mendicidad que atenten contra su dignidad o que impliquen un esfuerzo tal, que vaya en perjuicio de su salud física y mental.\nArtículo 30.- Cuando ninguno de los integrantes de la familia pueda encargarse del cuidado personal de la persona adulta mayor, se dará aviso al Sistema para el Desarrollo\nIntegral de la Familia del Estado de Baja California, quien inmediatamente tomará las medidas pertinentes, asegurando con los mecanismos a su alcance, el bienestar de la persona adulta mayor.\nArtículo 31.- Todas las instituciones públicas y privadas que desarrollen Programas de atención a las personas adultas mayores, deberán tomar las medidas de prevención para que la familia participe en la atención de este sector de la población.\nCAPÍTULO V\nArtículo 32.- La cancelación de la pensión tendrá lugar por las siguientes causas:\nI.- Cuando el beneficiario no sea localizado en el domicilio reportado como residencia del mismo, habiéndose agotado cuando menos tres visitas consecutivas;\nII.- Cuando se compruebe la duplicidad del beneficiario en el padrón;\nLey de los Derechos, Protección e Integración de las Personas Adultas Mayores Página 16\nIII.- Cuando se acredite fehacientemente que el beneficiario ha dejado de cumplir con los compromisos y requisitos dispuestos en el artículo 9 de esta Ley.\nIV.- Cuando el adulto mayor haya fallecido.\nArtículo 33.- La negativa al derecho a la pensión solo será procedente cuando el fundada y motivada.\nArtículo 34.- El acto que niegue el derecho a la pensión o que la cancele, podrá ser impugnado por el interesado ante el Tribunal de lo Contencioso Administrativo del Estado, en los términos de la Ley respectiva.\nTÍTULO CUARTO\nPOLÍTICAS PÚBLICAS, FACULTADES Y OBLIGACIONES DE LAS AUTORIDADES\nCAPÍTULO I\nDE LAS POLÍTICAS PÚBLICAS\nArtículo 35.- Las políticas públicas que formulen el Ejecutivo Estatal, a través de las dependencias a su cargo, y los Ayuntamientos, en sus respectivos ámbitos de competencia en materia de personas adultas mayores, deberán sustentarse en el Plan de Desarrollo respectivo y estarán orientadas a:\nI. Vigilar y garantizar la defensa y el pleno ejercicio de sus derechos.\nII. Propiciar las condiciones para generar un mayor bienestar físico, psicoemocional y mental de las personas adultas mayores, a fin de que puedan ejercer plenamente sus capacidades en el seno de la familia y de la sociedad;\nFracción Reformada\nIII. Establecer las bases para la planeación e implementación de acciones de manera integral entre las distintas dependencias del Ejecutivo Estatal y los Ayuntamientos, para lograr con la problemática y necesidades de las personas adultas mayores;\nIV. Fomentar en la sociedad una cultura de aprecio a las personas adultas mayores para lograr una revalorización de sus capacidades y de lo que puede aportar a la sociedad, y así procurar una mayor sensibilidad de conciencia social, respeto, y convivencia, evitando toda forma de discriminación, violencia, explotación, aislamiento, abandono, engaño, y olvido por motivo de su edad;\nFracción Reformada\nLey de los Derechos, Protección e Integración de las Personas Adultas Mayores Página 17\nV. Impulsar acciones y medidas compensatorias dirigidas a que las personas adultas mayores se integren a la sociedad en materias de salud, educación, laboral, deporte, accesibilidad, cultural y recreativas.\nVI. Establecer las bases dentro de los programas, para la asignación de beneficios sociales, descuentos y estímulos para las personas adultas mayores, de conformidad con las disposiciones jurídicas aplicables;\nVII. Promover la participación activa de las personas adultas mayores en la formulación e implementación de las políticas públicas que les afecten;\nVIII. Promover que las personas adultas mayores realicen una actividad productiva de manera permanente, para que gocen plenamente de su integración en la sociedad, incrementando de esta forma su autoestima y preservando su potencialidad;\nIX. Impulsar el fortalecimiento de redes familiares, sociales e institucionales de apoyo a los adultos mayores y garantizar la asistencia social para todas aquellas que por sus circunstancias requieran de protección especial por parte de las instituciones públicas y privadas;\nX. Fomentar que las instituciones educativas establezcan las disciplinas para la formación de especialistas en geriatría, gerontología y tanatología, a fin de garantizar la cobertura de los servicios de salud en las instituciones públicas y privadas, requeridos por las personas adultas mayores;\nXI. Fomentar la realización de estudios e investigaciones sobre la problemática inherente a la vejez y que sirvan como herramienta de trabajo a las instituciones del sector público y privado para desarrollar programas en beneficio de las personas adultas mayores;\nXII. Promover la difusión de los derechos y valores de las personas adultas mayores, con el propósito de sensibilizar a las familias y a la sociedad respecto a las necesidades de este sector;\nFracción Reformada\nXIII. Deberán contener información sobre la población objetivo, metas específicas, así como las evaluaciones de impacto, integralidad, eficiencia y eficacia; y,\nFracción Reformada\nXIV. Promover la capacitación para el acceso y uso responsable de las tecnologías de información y comunicación.\nFracción Adicionada\nArtículo Reformado\nCAPÍTULO II\nFACULTADES Y OBLIGACIONES DE LAS AUTORIDADES\nLey de los Derechos, Protección e Integración de las Personas Adultas Mayores Página 18\nSECCIÓN I\nI. En el Proyecto de Ley de Ingresos Estatal y Municipal, se consideren descuentos, exenciones y beneficios a favor de las personas adultas mayores, de conformidad con las disposiciones fiscales aplicables;\nII. En el Proyecto de Presupuesto de Egresos Estatal y Municipal, se asignen los recursos suficientes y las medidas administrativas pertinentes para garantizar el cabal ejercicio de sus atribuciones y deberes en esta materia; y\nIII. Las disposiciones contenidas en los diversos cuerpos normativos sean congruentes con los preceptos establecidos en la presente Ley.\nSECCIÓN II\nDE LA SECRETARÍA GENERAL DE GOBIERNO\nArtículo 37.- Corresponde a la Secretaría General de Gobierno:\nI. Gestionar ante los notarios públicos, el otorgamiento de descuentos y facilidades en los trámites que realicen ente ellos, las personas adultas mayores;\nII. Realizar campañas de regularización del estado civil y de otorgamiento de la Clave\nÚnica de Registro Poblacional para las personas adultas mayores;\nIII. Implementar, en coordinación con las dependencias competentes, las medidas de protección civil adecuadas para las personas adultas mayores, en los centros educativos, culturales y recreativos, así como acciones preventivas con la participación de la comunidad.\nSECCIÓN III\nDE LA SECRETARÍA DE BIENESTAR\nDenominación Modificada\nArtículo 38.- Corresponde a la Secretaría de Bienestar:\nPárrafo Reformado\nI.- Coordinar e implementar las acciones que se requieran, para promover la asistencia social y atención integral a los que se refiere esta Ley, realizando el padrón de las\nLey de los Derechos, Protección e Integración de las Personas Adultas Mayores Página 19 personas adultas mayores que requieran y soliciten estos apoyos, así como la pensión contemplada en el artículo 9 de esta Ley;\nFracción Reformada\nII. Fomentar la participación de los sectores público, social y privado en la promoción, seguimiento y financiamiento de los programas de atención a las personas adultas mayores;\nIII. Suscribir con los sectores público, social y privado, los convenios que se requieran para la implementación de programas de defensa, protección, provisión, orientación alimentaria, participación y atención a los derechos de las personas adultas mayores;\nIV. Organizar campañas de orientación e información nutricional de acuerdo a las condiciones físicas de las personas adultas mayores; y\nV. Establecer una base de información sobre las condiciones socioeconómicas, cobertura e impacto de los programas y acciones en beneficio de las personas adultas mayores, y que contribuya al mejor diseño y planeación de los programas y políticas públicas en la materia.\nArtículo Reformado\nSECCIÓN IV\nDE LA SECRETARÍA DE SALUD\nArtículo 39.- Corresponde a la Secretaría de Salud:\nI. Garantizar el acceso a la atención médica en las clínicas y hospitales públicos con una orientación especializada para las personas adultas mayores;\nII. Promover la atención especial, que deberán recibir los programas de detección oportuna y tratamiento temprano de enfermedades crónicas y neoplasias entre las personas adultas mayores, así como de atención y asistencia a quienes sufran de discapacidades funcionales. Asimismo, los programas de salud incorporarán medidas de prevención y promoción de la salud a fin de contribuir a prevenir discapacidades y favorecer un envejecimiento activo y saludable;\nFracción Reformada\nIII. Realizar Valoración Geriátrica Integral, además, proveer a las personas adultas mayores de una cartilla médica de salud y autocuidado, misma que será utilizada indistintamente en las instituciones públicas y privadas; en la cual se especificará el estado general de salud, enfermedades crónicas, tipo de sangre, medicamentos y dosis administradas, reacciones e implementos para ingerirlos, alimentación o tipo de dieta suministrada, consultas médicas y asistencias a grupos de autocuidado;\nFracción Reformada\nLey de los Derechos, Protección e Integración de las Personas Adultas Mayores Página 20\nIV. Diseñar y ejecutar programas de asesoría en materia de alimentación y nutrición adecuados para las personas adultas mayores;\nV. Implementar programas de prevención de enfermedades y accidentes que se\nEstado;\nVI. Dar orientación, información y capacitación a las familias, con el objeto de que brinden una adecuada atención a las personas adultas mayores;\nVII. Proporcionar, en coordinación con la Secretaría de Bienestar, orientación y apoyo técnico a los Ayuntamientos que lo soliciten, en materia de planes y programas relacionados con la atención de las personas adultas mayores;\nFracción Reformada\nVIII. Establecer mecanismos bajo el principio de coordinación interinstitucional, para proporcionar medicamentos, previo estudio socioeconómico, que determine su distribución sin costo alguno, en caso de estado de necesidad o abandono de las personas adultas mayores;\nIX. Realizar acciones de prevención que induzcan a la sociedad a conocer y tomar las medidas pertinentes para acceder a un envejecimiento activo y saludable;\nFracción Reformada\nX. Fomentar la capacitación en materia de primeros auxilios, terapias de rehabilitación, técnicas de alimentación y tratamiento de las personas adultas mayores, para aquellas personas que tengan a éstas a su cuidado;\nXI. Vigilar que las instituciones públicas, privadas y sociales que presten servicios de atención médica, cuenten con personal que posea vocación, capacidad y conocimientos en el cuidado de las personas adultas mayores;\nXII. Implementar programas y concertar convenios con las instituciones de salud del gobierno federal y las de iniciativa privada, a fin de que las personas adultas mayores puedan tener acceso a los servicios de atención médica que proporcione el Sistema de Salud; y\nXIII. Celebrar convenios con universidades públicas y privadas para recibir prestadores de servicio social en las áreas de trabajo social, psicología, medicina, odontología adultas mayores.\nArtículo Reformado\nArtículo 40.- La Secretaría de Salud podrá efectuar visitas a las instituciones públicas, privadas o sociales, encargadas de la atención de las personas adultas mayores, a efecto de verificar su buen funcionamiento, debiendo ordenar la corrección inmediata de las\nLey de los Derechos, Protección e Integración de las Personas Adultas Mayores Página 21 irregularidades de las cuales se percate, mediante la adopción de las medidas que correspondan, o en su caso, comunicar dicha situación a la autoridad competente.\nSECCIÓN V\nDE LA SECRETARÍA DE EDUCACIÓN\nDenominación Modificada\nArtículo 41.- Corresponde a la Secretaría de Educación:\nPárrafo Reformado\nI. Fomentar el acceso de las personas adultas mayores a programas de educación y capacitación continua;\nII. Promover y elaborar por sí, o en coordinación con los gobiernos estatal y municipal, la creación de programas permanentes de educación para la alfabetización de las personas adultas mayores; así como incorporar a las personas adultas mayores que tengan preparación académica, como instructores en los programas dirigidos a la capacitación y difusión de algún tema de interés social, en especial los programas dirigidos hacia las personas protegidas por esta Ley;\nIII. Elaborar programas especiales de capacitación y educación para las personas adultas mayores, en coordinación con la Secretaría del Trabajo y Previsión Social, con la finalidad de que puedan incorporarse a la actividad económica del Estado;\nIV. Fomentar, en coordinación con las universidades, programas de posgrado y de investigación en las especialidades de geriatría, gerontología y tanatología, en todos los niveles de atención en salud, así como de atención integral a las personas adultas mayores, dirigidos a personal técnico asistencial;\nV. Proponer ante las autoridades correspondientes, la incorporación de contenidos sobre procesos de envejecimiento en los planes y programas de estudios de todos los niveles educativos; y\nVI. Facilitar el uso de las bibliotecas públicas que les otorguen préstamo a domicilio del material de las mismas, con la presentación de su identificación personal, credencial de jubilado o pensionado.\nArtículo Reformado\nSECCIÓN VI\nDE LA SECRETARÍA DE HACIENDA\nDenominación Modificada\nArtículo 42.- Corresponde a la Secretaría de Hacienda:\nLey de los Derechos, Protección e Integración de las Personas Adultas Mayores Página 22\nPárrafo Reformado\nI. Desarrollar programas de condonación o de reducción de contribuciones estatales a favor de las personas adultas mayores;\nII. Promover entre los municipios de la entidad, la condonación, reducción o estímulos de contribuciones a favor de las personas adultas mayores;\nIII. Apoyar a las personas adultas mayores en la realización de gestiones ante las autoridades competentes para que se les otorguen condonaciones, reducciones o exenciones en el pago de derechos por los servicios que presten las dependencias y entidades de la administración pública federal, estatal y municipal, de conformidad con las disposiciones fiscales aplicables; y\nIV. Realizar campañas de difusión de la condonación, reducción o estímulos de contribuciones a favor de las personas adultas mayores.\nArtículo Reformado\nSECCIÓN VII\nDE LA SECRETARÍA DEL TRABAJO Y PREVISIÓN SOCIAL\nArtículo 43.- Corresponde a la Secretaría del Trabajo y Previsión Social:\nI. La promoción empleos como actividades lucrativas o voluntarias, conforme a su oficio, habilidad o profesión, sin más restricción que su limitación física o mental declarada por la autoridad médica o legal competente;\nII. El fomento a la creación de organizaciones productivas de las personas adultas mayores;\nIII. La capacitación a las personas adultas mayores, para que adquieran conocimientos y destrezas en actividades productivas;\nIV. La organización de una bolsa de trabajo mediante la cual se identifiquen actividades laborales que puedan ser desempeñadas por las personas adultas mayores y orientarlas para que presenten ofertas de trabajo;\nV. La asesoría jurídica gratuita a las personas adultas mayores que decidan retirarse de sus actividades laborales;\nFracción Reformada\nVI. La creación de mecanismos de autoempleo mediante capacitación y financiamiento formulación y ejecución de proyectos productivos; y,\nFracción Reformada\nVII.- Fomentar el trabajo digno para las personas adultas mayores, en un plano de igualdad de oportunidades, generando los mecanismos de seguimiento y vigilancia que\nLey de los Derechos, Protección e Integración de las Personas Adultas Mayores Página 23 garanticen se cumplan con las disposiciones legales en materia laboral, con la finalidad de erradicar la discriminación.\nFracción Adicionada\nArtículo Reformado\nSECCIÓN VIII\nDE LA SECRETARÍA DE TURISMO\nArtículo 44.- Corresponde a la Secretaría de turismo:\nI. Impulsar la promoción de actividades y participación de los adultos mayores en actividades turísticas;\nII. Promover acciones a fin de que en lugares públicos destinados a la recreación, se cuente con los espacios y actividades que faciliten la integración de los adultos mayores;\nIII.- Establecer convenios de coordinación con empresas del ramo, para ofrecer tarifas especiales, en su caso gratuitas, en los centros públicos y privados de entretenimiento, recreación, cultura y deporte, hospedaje en hoteles y asistencia a centros históricos y turísticos;\nIV.- Fomentar la participación de las personas adultas mayores en el rescate y transmisión oral de la cultura e historia del Estado, como parte de la promoción turística de nuestra entidad; y\nV.- Para garantizar el derecho a la recreación y turismo, difundirá permanentemente a través de los medios masivos de comunicación, las actividades turísticas que se realizan a favor de las personas adultas mayores.\nArtículo Reformado\nSECCIÓN IX\nDE LA SECRETARÍA DE ECONOMÍA E INNOVACIÓN\nSección Adicionada\nDenominación Modificada\nArtículo 44 BIS.- Corresponde a la Secretaría de Economía e Innovación:\nPárrafo Reformado\nI.- Proponer la implementación de medidas fiscales y no fiscales que incentiven la contratación de personas adultas mayores;\nII.- Promover que en los proyectos de inversión a que se refiere la Ley de Fomento a la\nCompetitividad y Desarrollo Económico para el Estado, se comprenda la contratación de personas adultas mayores; y\nIII.- Impulsar cualquier tipo de medida con el fin de que el sector empresarial otorgue más y mejores prestaciones laborales para las personas adultas mayores.\nArtículo Adicionado\nLey de los Derechos, Protección e Integración de las Personas Adultas Mayores Página 24\nArtículo Reformado\nTÍTULO QUINTO\nADULTAS MAYORES\nCAPÍTULO I\nDE SU NATURALEZA, OBJETO Y FUNCIONES\nArtículo 45.- Se crea el Consejo Estatal para la Protección e Integración de las\nPersonas Adultas Mayores, como un órgano honorario de consulta, asesoría y evaluación de las acciones de concertación, coordinación, planeación y promoción necesarias para favorecer la plena integración social y desarrollo de las personas adultas mayores.\nArtículo 46.- En el ejercicio de sus funciones, el Consejo Estatal deberá atender los siguientes criterios:\nI. Integralidad en las políticas públicas a cargo de las distintas dependencias, organismos auxiliares y entidades de la administración pública Estatal y Municipal, a partir de la ejecución de programas y acciones coordinadas;\nII. Vigilar el cumplimiento y desarrollo de los programas y actividades para el fortalecimiento institucional de las dependencias responsables de la aplicación de las disposiciones jurídicas que regulen la materia en la entidad y los municipios; y\nIII. Coadyuvar en el fortalecimiento de los vínculos con las demás instancias del sector público federal y municipal, así como con el Poder Legislativo del Estado, con el fin de cumplir con los objetivos de esta Ley.\nArtículo 47.- El Consejo Estatal estará integrado por:\nI. Presidente, que será la persona Titular de la Secretaría de Bienestar;\nFracción Reformada\nII. Secretario Ejecutivo, que será la persona Titular de la Dirección General del Sistema para el Desarrollo Integral de la Familia de Baja California, con derecho a voz;\nFracción Reformada\nIII. Secretario Técnico, que será la persona Titular de la Secretaría de Salud;\nFracción Reformada\nIV. Personas titulares de las siguientes dependencias:\nPárrafo de la Fracción Reformado\na) La Secretaría de Educación.\nInciso Reformado\nLey de los Derechos, Protección e Integración de las Personas Adultas Mayores Página 25\nb) La Secretaría de Hacienda.\nInciso Reformado\nc) La Secretaría del Trabajo y Previsión Social.\nd) La Secretaría de Turismo.\ne) La Secretaría de Economía e Innovación.\nInciso Adicionado\nFracción Reformada\nV. Las y los Diputados Presidentes de cada una de las Comisiones de Asuntos\nIndígenas y Bienestar Social; de Educación, Cultura, Ciencia y Tecnología; de Hacienda y\nPresupuesto; y de Salud, conforme a la temática e integración en cada Legislatura del\nCongreso del Estado y temática en la materia; y,\nFracción Reformada\nVI. Las y los Presidentes Municipales del Estado de Baja California.\nFracción Reformada\nArtículo Reformado\nArtículo 48.- El Consejo Estatal, a través de su Presidente, invitará a formar parte del mismo, con derecho a voz, a los delegados en el Estado del Instituto Nacional de las\nPersonas Adultas Mayores, del Instituto Mexicano del Seguro Social, del Instituto de\nSeguridad y Servicios Sociales de los Trabajadores del Estado y del Instituto del Fondo\nNacional para la Vivienda de los Trabajadores.\nArtículo 49.- El Consejo podrá invitar a que asistan a las sesiones que celebre a:\nI.- Representantes de otras instancias locales, federales e internacionales.\nII.- Académicos, especialistas o empresarios encargados de desarrollar programas, actividades o investigaciones relacionadas con la población de personas adultas mayores.\nIII.- Personas adultas mayores relacionadas o que estén en condiciones de coadyuvar a toma de decisiones del Consejo;\nIV.- Representantes de instituciones de educación superior, públicas o privadas que cuenten con áreas de geriatría, gerontología y/o de estudios sociales;\nFracción Reformada\nV.- Empresarios encargados de desarrollar programas, actividades o investigaciones relacionadas con la población de personas adultas mayores; y,\nFracción Reformada\nVI.- Organizaciones de la sociedad civil relacionadas o que estén en condiciones de coadyuvar a toma de decisiones del consejo.\nFracción Adicionada sin voto.\nArtículo Reformado\nLey de los Derechos, Protección e Integración de las Personas Adultas Mayores Página 26\nArtículo 50.- Tendrán el carácter de vocales los que se encuentran enunciados en las fracciones IV, V y VI del artículo 47 de esta Ley.\nArtículo 51.- Los vocales podrán designar a un suplente ante el Consejo Estatal, que cubra sus ausencias, para lo cual deberán previamente a las sesiones del Consejo Estatal, exhibir el documento en el que se informe su designación.\nArtículo 52.- En los Municipios deberán formarse Consejos Municipales para la\nProtección e Integración de las Personas Adultas Mayores, para fomentar la participación de la población y dar a conocer en sus jurisdicciones y al Consejo Estatal, las necesidades y demandas de las personas adultas mayores.\nEn los Consejos Municipales a que se refiere el párrafo anterior, también deberá preverse la participación como invitados, con derecho a voz pero sin voto a:\nI.- Representantes de otras instancias locales, federales e internacionales.\nII.- Académicos, especialistas o empresarios encargados de desarrollar programas, actividades o investigaciones relacionadas con la población de personas adultas mayores.\nIII.- Personas adultas mayores relacionadas o que estén en condiciones de coadyuvar a toma de decisiones del Consejo;\nIV.- Representantes de instituciones de educación superior, públicas o privadas que cuenten con áreas de geriatría, gerontología y/o de estudios sociales, y\nV.- Empresarios encargados de desarrollar programas, actividades o investigaciones relacionadas con la población de personas adultas mayores.\nArtículo Reformado\nArtículo 53.- El Consejo Estatal tendrá las siguientes funciones:\nI. Formular las políticas públicas y planes en materia de las personas adultas mayores, conforme al artículo 8 de esta Ley;\nII. Coordinar con las dependencias, organismos auxiliares y entidades de la administración pública Estatal y Municipal, así como con el sector social y privado, las acciones en pro del bienestar, desarrollo, protección e integración social de las personas adultas mayores;\nIII. Coordinar la implementación, seguimiento y evaluación de los programas y acciones establecidos en beneficio de las personas adultas mayores, tratando de unificar públicos;\nIV. Impulsar alternativas ocupacionales productivas, tanto en el medio urbano como en el rural, encaminadas a mejorar el nivel de vida de las personas adultas mayores;\nV. Fomentar la creación, continuidad y accesibilidad de las acciones, programas y servicios relativos a la atención integral de las personas adultas mayores;\nLey de los Derechos, Protección e Integración de las Personas Adultas Mayores Página 27\nVI. Propiciar la colaboración y participación de instituciones públicas y privadas en las personas adultas mayores;\nVII. Proponer la realización de estudios que contribuyan a mejorar la planeación e personas adultas mayores;\nVIII. Fomentar la elaboración, publicación y distribución de material informativo para dar a conocer la situación de la población de personas adultas mayores en el Estado de Baja\nCalifornia, así como alternativas de participación, solución de problemas y mejora de servicios y programas;\nIX. Promover la creación de fundaciones, asociaciones e instituciones privadas que tengan por objeto la protección y atención de las personas adultas mayores;\nX. Recibir y canalizar a las instituciones competentes, las quejas y sugerencias sobre la atención que éstas brinden a las personas adultas mayores;\nXI. Promover el establecimiento de programas, en coordinación con las autoridades competentes, dirigidos a la promoción de créditos accesibles para las personas adultas mayores que deseen adquirir una vivienda propia o realicen mejoras en caso de contar con una;\nXII. Promover, ante las autoridades competentes, la condonación o reducción de contribuciones estatales y municipales a favor de las personas adultas mayores;\nXIII. Promover, en coordinación con las autoridades competentes, descuentos en servicios públicos, establecimientos comerciales, centros hospitalarios y otros prestadores de servicios técnicos y profesionales, en beneficio de las personas adultas mayores;\nXIV. Promover la implementación de programas de incentivos y becas para las personas adultas mayores que estudien;\nXV. Promover el establecimiento y otorgamiento de incentivos o estímulos fiscales estatales o municipales para las personas físicas o morales que contraten o consideren un mínimo de empleos para las personas adultas mayores, en los términos de las disposiciones fiscales disponibles.\nXVI. Establecer vínculos de colaboración entre los poderes del Estado, que permitan cumplir con los objetivos de la presente Ley;\nXVII. Gestionar fondos ante organizaciones públicas y privadas, nacionales e internacionales, para la ejecución de programas de atención a las personas adultas mayores;\nXVIII. Elaborar un informe anual que se remitirá a las Comisiones correspondientes del Congreso del Estado para su conocimiento;\nXIX. Proveer los mecanismos de participación necesarios para que los adultos mayores colaboren en el diseño, elaboración y ejecución de programas y proyectos que traten\nLey de los Derechos, Protección e Integración de las Personas Adultas Mayores Página 28 sobre ellos, con valoración especial sobre su experiencia y conocimientos en el desarrollo social, económico, cultural y político del Estado;\nXX. Aprobar y expedir su reglamento interno; y\nXXI. Las demás funciones que se acuerden en el Pleno del Consejo Estatal.\nArtículo Reformado\nCAPÍTULO II\nDE LA ORGANIZACIÓN\nArtículo 54.- Para el mejor desempeño de las funciones, el Consejo Estatal deberá organizar grupos de trabajo bajo la coordinación del titular de la Secretaría de Bienestar, y conforme al reglamento que al efecto se expida.\nArtículo Reformado\nArtículo 55.- Los integrantes del Consejo Estatal tendrán voz y voto, con excepción del\nSecretario Ejecutivo, quien sólo tendrá voz. Las decisiones del Consejo Estatal se tomarán por mayoría de votos de sus integrantes, en caso de empate el Presidente tendrá voto de calidad.\nArtículo 56.- El Consejo Estatal sesionará de forma ordinaria trimestralmente y extraordinaria, cuando convoque el Presidente o la mayoría de los vocales.\nArtículo 57.- Para que el Consejo Estatal pueda sesionar válidamente, se requerirá de la asistencia de la mitad más uno de sus integrantes, siempre que asista el Presidente y el\nSecretario Técnico, o sus suplentes debidamente acreditados.\nArtículo 58.- Las dependencias, organismos auxiliares y entidades de la administración pública Estatal y Municipal, están obligadas a suministrar la información requerida por el\nConsejo Estatal, para el cumplimiento de sus fines.\nArtículo 59.- Al Presidente del Consejo Estatal le corresponde:\nI. Representar al Consejo Estatal ante las distintas autoridades e instituciones públicas y privadas;\nII. Convocar a sesiones a los integrantes del Consejo Estatal;\nIII. Presidir las reuniones del Consejo Estatal;\nIV. Dirigir y moderar los debates durante las sesiones;\nV. Dictar las políticas necesarias para mejorar la operación del Consejo Estatal; y\nVI. Someter a consideración del Consejo Estatal, los estudios, propuestas y opiniones que emitan los grupos de trabajo.\nArtículo 60.- Al Secretario Técnico del Consejo Estatal le corresponde:\nLey de los Derechos, Protección e Integración de las Personas Adultas Mayores Página 29\nI. Coordinar las actividades del Consejo Estatal y de los grupos de trabajo;\nII. Por instrucciones previas del Presidente, citar a sesión a los integrantes del Consejo\nEstatal;\nIII. Formular la orden del día para las sesiones del Consejo Estatal;\nIV. Someter a consideración del Consejo Estatal los programas de trabajo;\nV. Difundir y dar seguimiento a las resoluciones y el trabajo del Consejo Estatal;\nVI. Proporcionar asesoría técnica al Consejo Estatal;\nVII. Verificar el quórum legal para dar inicio y durante las sesiones del Consejo Estatal;\nVIII. Suplir al Presidente del Consejo Estatal, en caso de ausencia de éste o su representante;\nIX. Levantar las actas de cada una de las sesiones del Consejo Estatal y registrarlas con su firma;\nX. Leer el Acta de la sesión anterior;\nXI. Llevar el control de la agenda temática; y\nXII. Realizar los trabajos que le encomiende el Presidente del Consejo estatal.\nTÍTULO SEXTO\nDE LAS DENUNCIAS Y SANCIONES\nCAPÍTULO ÚNICO\nDEL PROCEDIMIENTO\nArtículo 61.- Toda persona física, grupo social, organización no gubernamental, asociación o sociedad civil, podrá denunciar ante los órganos y autoridades competentes, todo hecho, acto u omisión que produzca o pueda producir daño o afectación a los derechos y garantías de las personas adultas mayores, independientemente de las que establece la presente Ley; en el caso de que estos actos pongan en peligro la vida de la persona adulta mayor, deberán informar de manera inmediata al Ministerio Público.\nArtículo Reformado\nArtículo. 62.- Cuando los responsables del daño o afectación de los derechos de la persona adulta mayor, sean servidores públicos en ejercicio de sus funciones, se deberá dar aviso al superior jerárquico de manera inmediata para su conocimiento, sujetándolos al\nAdministrativas del Estado de Baja California.\nArtículo Reformado\nArtículo 63.- La inobservancia a las disposiciones de esta Ley, serán sancionadas de\nLey de los Derechos, Protección e Integración de las Personas Adultas Mayores Página 30\nBaja California, así como en las leyes civiles, penales y demás ordenamientos legales aplicables.\nArtículo Reformado\nArtículo 64.- El incumplimiento de las disposiciones que establece esta Ley, en el ámbito de la salud, tratándose de negligencia médica, se pondrán a consideración de las autoridades competentes.\nTRANSITORIOS\nPRIMERO.- El presente Decreto entrará en vigor al día siguiente de su publicación en el Periódico Oficial del Estado.\nSEGUNDO.- El Ejecutivo del Estado expedirá el Reglamento de la Ley de los\nDerechos, Protección e Integración de las Personas Adultas Mayores en el Estado de Baja\nCalifornia, dentro del plazo de noventa días naturales, a partir de la fecha que entre en vigor este ordenamiento.\nTERCERO.- El reglamento correspondiente a la pensión alimentaria de las personas adultas mayores, será emitido por la Secretaría de Desarrollo Social, dentro del plazo de noventa días naturales, a partir de la fecha que entre en vigor este ordenamiento.\nCUARTO.- El Consejo Estatal para la Integración y Protección de las Personas Adultas\nMayores, deberá constituirse en un plazo no mayor a los noventa días naturales, a partir de la entrada en vigor de la presente Ley.\nQUINTO.- El Consejo Municipal para la Integración y Protección de las Personas\nAdultas Mayores, deberá constituirse en un plazo no mayor a los noventa días naturales, a partir de la entrada en vigor de la presente Ley.\nSEXTO.- El Ejecutivo del Estado y los Ayuntamientos, en el ámbito de sus respectivas competencias, dentro de un plazo de ciento veinte días, a partir de la entrada en vigor de la presente Ley, adecuarán las disposiciones reglamentarias y aplicables, y conforme a la disposición presupuestaria disponible, adoptarán las medidas necesarias, acciones e implementación de programas orientados a dar cumplimiento a lo establecido en la misma.\nEstado de Baja California, en la Ciudad de Mexicali, B.C., a los veintinueve días del mes de diciembre del año dos mil once.\nLIC. MÁXIMO GARCÍA LÓPEZ\nDIPUTADO PRESIDENTE\n(RUBRICA)\nPROFR. ALFONSO GARZÓN ZATARAIN\nDIPUTADO SECRETARIO\nLey de los Derechos, Protección e Integración de las Personas Adultas Mayores Página 31\n(RUBRICA)\nDE CONFORMIDAD CON LO DISPUESTO POR LA FRACCIÓN I DEL ARTÍCULO 49\nCALIFORNIA, IMPRÍMASE Y PUBLÍQUESE.\nMEXICALI, BAJA CALIFORNIA, A LOS TREINTA DÍAS DEL MES DE DICIEMBRE\nDEL AÑO DOS MIL DOCE.\nGOBERNADOR DEL ESTADO\nJOSE GUADALUPE OSUNA MILLAN\n(RÚBRICA)\nSECRETARIO GENERAL DE GOBIERNO\nCUAUHTEMOC CARDONA BENAVIDES\n(RUBRICA)\nLey de los Derechos, Protección e Integración de las Personas Adultas Mayores Página 32\nArtículo 1.- Fue reformado por Decreto No. 279, publicado en el Periódico Oficial No.\nLegislatura, siendo Gobernadora Constitucional la C. Marina del Pilar Ávila Olmeda 20212027;\nArtículo 2.- Fue reformado por Decreto No. 279, publicado en el Periódico Oficial No.\n53, de fecha 08 de septiembre de 2023, Sección III, Tomo CXXX; expedido por la H. XXIV\nLegislatura, siendo Gobernadora Constitucional la C. Marina del Pilar Ávila Olmeda 20212027;\nArtículo 6.- Fue reformado mediante Decreto No. 415, publicado en el Periódico Oficial\nNo. 58, de fecha 18 de diciembre de 2015, Sección IV, Tomo CXXII; expedido por la H. XXI\nLegislatura, siendo Gobernador constitucional el C. Francisco Arturo Vega de Lamadrid 20132019; fue reformado por Decreto No. 279, publicado en el Periódico Oficial No. 53, de fecha\n08 de septiembre de 2023, Sección III, Tomo CXXX; expedido por la H. XXIV Legislatura, siendo Gobernadora Constitucional la C. Marina del Pilar Ávila Olmeda 2021-2027; fue reformado por Decreto No. 77, publicado en el Periódico Oficial No. 22, Índice, de fecha 11 de abril de 2025, Tomo CXXXII, expedido por la H. XXV Legislatura, siendo Gobernadora\nConstitucional la C. Marina del Pilar Ávila Olmeda 2021-2027;\nArtículo 6 BIS.- Fue reformado por Decreto No. 279, publicado en el Periódico Oficial\nNo. 53, de fecha 08 de septiembre de 2023, Sección III, Tomo CXXX; expedido por la H. XXIV\nLegislatura, siendo Gobernadora Constitucional la C. Marina del Pilar Ávila Olmeda 20212027; fue reformado por Decreto No. 53, publicado en el Periódico Oficial No. 15, Índice, de fecha 14 de marzo de 2025, Tomo CXXXII; expedido por la H. XXV Legislatura, siendo\nGobernadora Constitucional la C. Marina del Pilar Ávila Olmeda 2021-2027; fue reformado por\nDecreto No. 77, publicado en el Periódico Oficial No. 22, Índice, de fecha 11 de abril de 2025, Tomo CXXXII, expedido por la H. XXV Legislatura, siendo Gobernadora Constitucional la C.\nMarina del Pilar Ávila Olmeda 2021-2027;\nArtículo 7.- Fue reformado por Decreto No. 279, publicado en el Periódico Oficial No.\n53, de fecha 08 de septiembre de 2023, Sección III, Tomo CXXX; expedido por la H. XXIV\nLegislatura, siendo Gobernadora Constitucional la C. Marina del Pilar Ávila Olmeda 20212027;\nArtículo 8.- Fue reformado mediante Decreto No. 415, publicado en el Periódico Oficial\nLegislatura, siendo Gobernador constitucional el C. Francisco Arturo Vega de Lamadrid 20132019; fue reformado por Decreto No. 450, publicado en el Periódico Oficial No. 14, Sección IV, Gobernador Constitucional el C. Francisco Arturo Vega de Lamadrid 2013-2019; fue reformado por Decreto No. 73, publicado en el Periódico Oficial No. 36, Número Especial, Gobernador Constitucional el C. Jaime Bonilla Valdez 2019-2021; fue reformado por Decreto\nLey de los Derechos, Protección e Integración de las Personas Adultas Mayores Página 33\nTomo CXXXI; expedido por la H. XXIV Legislatura, siendo Gobernadora Constitucional la C.\nMarina del Pilar Ávila Olmeda 2021-2027;\nArtículo 14.- Fue reformado por Decreto No. 279, publicado en el Periódico Oficial No.\nLegislatura, siendo Gobernadora Constitucional la C. Marina del Pilar Ávila Olmeda 20212027;\nArtículo 17.- Fue reformado mediante Decreto No. 457, publicado en el Periódico Oficial\nNo. 25, de fecha 31 de mayo de 2013, Sección I, Tomo CXX, expedido por la H. XX\nLegislatura, siendo Gobernador Constitucional el C. José Guadalupe Osuna Millán 2007-2013; fue reformado mediante Decreto No. 586, publicado en el Periódico Oficial No. 46, de fecha\n18 de octubre de 2013, Sección III, Tomo CXX, expedido por la H. XX Legislatura, siendo\nGobernador Constitucional el C. José Guadalupe Osuna Millán 2007-2013; fue reformado mediante Decreto No. 417, publicado en el Periódico Oficial No. 58, de fecha 18 de diciembre de 2015, Sección IV, Tomo CXXII; expedido por la H. XXI Legislatura, siendo Gobernador constitucional el C. Francisco Arturo Vega de Lamadrid 2013-2019; fue reformado mediante\nDecreto No. 130, publicado en el Periódico Oficial No. 50, de fecha 10 de noviembre de 2017,\nSección III, Tomo CXXIV; expedido por la H. XXII Legislatura, siendo Gobernador constitucional el C. Francisco Arturo Vega de Lamadrid 2013-2019;\nArtículo 20.- Fue reformado mediante Decreto No. 457, publicado en el Periódico Oficial\nNo. 25, de fecha 31 de mayo de 2013, Sección I, Tomo CXX, expedido por la H. XX\nLegislatura, siendo Gobernador Constitucional el C. José Guadalupe Osuna Millán 2007-2013;\nArtículo 24.- Fue reformado mediante Decreto No. 415, publicado en el Periódico Oficial\nNo. 58, de fecha 18 de diciembre de 2015, Sección IV, Tomo CXXII; expedido por la H. XXI\nLegislatura, siendo Gobernador constitucional el C. Francisco Arturo Vega de Lamadrid 20132019;\nArtículo 26.- Fue reformado mediante Decreto No. 130, publicado en el Periódico Oficial\nNo. 56, de fecha 19 de septiembre de 2022, Sección III, Tomo CXXIX; expedido por la H.\nXXIV Legislatura, siendo Gobernadora Constitucional la C. Marina del Pilar Ávila Olmeda\n2021-2027;\nArtículo 27.- Fue reformado mediante Decreto No. 317, publicado en el Periódico Oficial\nLegislatura, siendo Gobernador constitucional el C. Francisco Arturo Vega de Lamadrid 20132019;\nArtículo 35.- Fue reformado mediante Decreto No. 317, publicado en el Periódico Oficial\nLegislatura, siendo Gobernador constitucional el C. Francisco Arturo Vega de Lamadrid 20132019; fue reformado mediante Decreto No. 314, publicado en el Periódico Oficial No. 67, de\nLey de los Derechos, Protección e Integración de las Personas Adultas Mayores Página 34 siendo Gobernadora Constitucional la C. Marina del Pilar Ávila Olmeda 2021-2027;\nFue modificada la denominación de esta Sección por Decreto No. 279, publicado en el expedido por la H. XXIV Legislatura, siendo Gobernadora Constitucional la C. Marina del Pilar\nÁvila Olmeda 2021-2027;\nSECCIÓN III\nDE LA SECRETARÍA DE BIENESTAR\nArtículo 38.- Fue reformado por Decreto No. 279, publicado en el Periódico Oficial No.\n53, de fecha 08 de septiembre de 2023, Sección III, Tomo CXXX; expedido por la H. XXIV\nLegislatura, siendo Gobernadora Constitucional la C. Marina del Pilar Ávila Olmeda 20212027;\nArtículo 39.- Fue reformado por Decreto No. 73, publicado en el Periódico Oficial No.\n36, Número Especial, Tomo CXXVII, de fecha 22 de junio de 2020, expedido por la H. XXIII\nLegislatura, siendo Gobernador Constitucional el C. Jaime Bonilla Valdez 2019-2021; fue reformado por Decreto No. 77, publicado en el Periódico Oficial No. 22, Índice, de fecha 11 de abril de 2025, Tomo CXXXII, expedido por la H. XXV Legislatura, siendo Gobernadora\nConstitucional la C. Marina del Pilar Ávila Olmeda 2021-2027;\nFue modificada la denominación de esta Sección por Decreto No. 279, publicado en el\nPeriódico Oficial No. 53, de fecha 08 de septiembre de 2023, Sección III, Tomo CXXX; expedido por la H. XXIV Legislatura, siendo Gobernadora Constitucional la C. Marina del Pilar\nÁvila Olmeda 2021-2027;\nSECCIÓN V\nDE LA SECRETARÍA DE EDUCACIÓN\nArtículo 41.- Fue reformado mediante Decreto No. 415, publicado en el Periódico\nOficial No. 58, de fecha 18 de diciembre de 2015, Sección IV, Tomo CXXII; expedido por la H.\nXXI Legislatura, siendo Gobernador constitucional el C. Francisco Arturo Vega de Lamadrid\n2013-2019; fue reformado por Decreto No. 279, publicado en el Periódico Oficial No. 53, de fecha 08 de septiembre de 2023, Sección III, Tomo CXXX; expedido por la H. XXIV\nLegislatura, siendo Gobernadora Constitucional la C. Marina del Pilar Ávila Olmeda 20212027;\nFue modificada la denominación de esta Sección por Decreto No. 279, publicado en el expedido por la H. XXIV Legislatura, siendo Gobernadora Constitucional la C. Marina del Pilar\nÁvila Olmeda 2021-2027;\nSECCIÓN VI\nDE LA SECRETARÍA DE HACIENDA\nLey de los Derechos, Protección e Integración de las Personas Adultas Mayores Página 35\nArtículo 42.- Fue reformado por Decreto No. 279, publicado en el Periódico Oficial No.\nLegislatura, siendo Gobernadora Constitucional la C. Marina del Pilar Ávila Olmeda 20212027;\nArtículo 43.- Fue reformado por Decreto No. 394, publicado en el Periódico Oficial No.\n14, Índice, de fecha 15 de marzo de 2024, Tomo CXXXI; expedido por la H. XXIV Legislatura, siendo Gobernadora Constitucional la C. Marina del Pilar Ávila Olmeda 2021-2027;\nArtículo 44.- Fue reformado por Decreto No. 653, publicado en el Periódico Oficial No.\n52, Sección V, de fecha 25 de noviembre de 2016, Tomo CXXIII, expedido por la H. XXI\nLegislatura, siendo Gobernador Constitucional el C. Francisco Arturo Vega de Lamadrid 20132019;\nFue adicionada esta Sección mediante Decreto No. 457, publicado en el Periódico Oficial No.\n25, de fecha 31 de mayo de 2013, Sección I, Tomo CXX, expedido por la\nH. XX Legislatura, siendo Gobernador Constitucional el C. José Guadalupe Osuna Millán 2007-2013;\nSECCIÓN IX\nDE LA SECRETARÍA DE DESARROLLO ECONÓMICO\nFue modificada la denominación de esta Sección por Decreto No. 279, publicado en el\nPeriódico Oficial No. 53, de fecha 08 de septiembre de 2023, Sección III, Tomo CXXX; expedido por la H. XXIV Legislatura, siendo Gobernadora Constitucional la C. Marina del Pilar\nÁvila Olmeda 2021-2027;\nSECCIÓN IX\nDE LA SECRETARÍA DE ECONOMÍA E INNOVACIÓN\nArtículo 44 BIS.- Fue adicionado mediante Decreto No. 457, publicado en el Periódico\nOficial No. 25, de fecha 31 de mayo de 2013, Sección I, Tomo CXX, expedido por la H. XX\nLegislatura, siendo Gobernador Constitucional el C. José Guadalupe Osuna Millán 2007-2013; fue reformado por Decreto No. 279, publicado en el Periódico Oficial No. 53, de fecha 08 de septiembre de 2023, Sección III, Tomo CXXX; expedido por la H. XXIV Legislatura, siendo\nGobernadora Constitucional la C. Marina del Pilar Ávila Olmeda 2021-2027;\nArtículo 47.- Fue reformado por Decreto No. 279, publicado en el Periódico Oficial No.\nLegislatura, siendo Gobernadora Constitucional la C. Marina del Pilar Ávila Olmeda 20212027;\nArtículo 49.- Fue reformado mediante Decreto No. 330, publicado en el Periódico Oficial siendo Gobernador Constitucional el C. Francisco Arturo Vega de Lamadrid 2013-2019; fue\nLey de los Derechos, Protección e Integración de las Personas Adultas Mayores Página 36 reformado por Decreto No. 140, publicado en el Periódico Oficial No. 60, Índice, de fecha 03\nConstitucional la C. Marina del Pilar Ávila Olmeda 2021-2027;\nArtículo 52.- Fue reformado mediante Decreto No. 330, publicado en el Periódico Oficial siendo Gobernador Constitucional el C. Francisco Arturo Vega de Lamadrid 2013-2019;\nArtículo 53.- Fue reformado mediante Decreto No. 415, publicado en el Periódico Oficial\nNo. 58, de fecha 18 de diciembre de 2015, Sección IV, Tomo CXXII; expedido por la H. XXI\nLegislatura, siendo Gobernador constitucional el C. Francisco Arturo Vega de Lamadrid 20132019;\nArtículo 54.- Fue reformado por Decreto No. 279, publicado en el Periódico Oficial No.\n53, de fecha 08 de septiembre de 2023, Sección III, Tomo CXXX; expedido por la H. XXIV\nLegislatura, siendo Gobernadora Constitucional la C. Marina del Pilar Ávila Olmeda 20212027;\nArtículo 61.- Fue reformado mediante Decreto No. 330, publicado en el Periódico Oficial\nNo. 54, de fecha 27 de noviembre de 2015, Tomo CXXII, expedido por la H. XXI Legislatura, siendo Gobernador Constitucional el C. Francisco Arturo Vega de Lamadrid 2013-2019;\nArtículo 62.- Fue reformado por Decreto No. 140, publicado en el Periódico Oficial No.\nLegislatura, siendo Gobernadora Constitucional la C. Marina del Pilar Ávila Olmeda 20212027;\nArtículo 63.- Fue reformado por Decreto No. 140, publicado en el Periódico Oficial No.\nLegislatura, siendo Gobernadora Constitucional la C. Marina del Pilar Ávila Olmeda 20212027;\nLey de los Derechos, Protección e Integración de las Personas Adultas Mayores Página 37\nARTÍCULO PRIMERO TRANSITORIO DEL DECRETO No. 457, POR EL QUE SE\nREFORMAN LAS FRACCIONES XI, XII Y LA ADICIÓN DE UNA FRACCIÓN XIII AL\nARTÍCULO 17; LA REFORMA A LAS FRACCIONES IX, X Y LA ADICIÓN DE UNA\nFRACCIÓN XI AL ARTÍCULO 20; LA ADICIÓN DE UNA SECCIÓN IX DEL TÍTULO CUARTO\nDENOMINADO “DE LA SECRETARÍA DE DESARROLLO ECONÓMICO”, ASÍ COMO UN\nARTÍCULO 44 BIS, PUBLICADO EN EL PERIÓDICO OFICIAL No. 25, TOMO CXX,\nSECCION I, DE FECHA 31 DE MAYO DE 2013, EXPEDIDO POR LA H. XX LEGISLATURA,\nSIENDO GOBERNADOR CONSTITUCIONAL EL C. JOSÉ GUADALUPE OSUNA MILLÁN\n2007-2013.\nARTÍCULO TRANSITORIO\nÚNICO: Las presentes reformas entrarán en vigor al día siguiente de su publicación en el Periódico Oficial del Estado.\nDADO en el Salón de Sesiones “Lic. Benito Juárez García” del H. Poder Legislativo del\nEstado de Baja California, en la Ciudad de Mexicali, B.C., a los dos días del mes de mayo del año dos mil trece.\nDIP. JULIO FELIPE GARCÍA MUÑOZ\nPRESIDENTE\n(RÚBRICA)\nDIP. MARCO ANTONIO VIZCARRA CALDERÓN\nSECRETARIO\n(RÚBRICA)\nDE CONFORMIDAD CON LO DISPUESTO POR LA FRACCIÓN I DEL ARTÍCULO 49\nMEXICALI, BAJA CALIFORNIA, A LOS VEINTE DÍAS DEL MES DE MAYO DEL AÑO\nDOS MIL TRECE.\nJOSÉ GUADALUPE OSUNA MILLÁN\nGOBERNADOR DEL ESTADO\n(RÚBRICA)\nFRANCISCO ANTONIO GARCÍA BURGOS\nSECRETARIO GENERAL DE GOBIERNO\n(RÚBRICA)\nARTÍCULO UNICO TRANSITORIO DEL DECRETO No. 586, POR EL QUE SE\nADICIONA UNA FRACCIÓN XIII Y XIV AL ARTÍCULO 17, PUBLICADO EN EL PERIÓDICO\nLey de los Derechos, Protección e Integración de las Personas Adultas Mayores Página 38\nEXPEDIDO POR LA H. XX LEGISLATURA, SIENDO GOBERNADOR CONSTITUCIONAL EL\nC. JOSÉ GUADALUPE OSUNA MILLÁN 2007-2013.\nARTÍCULOS TRANSITORIOS\nPrimero.- El presente decreto entrará en vigor al día siguiente de su publicación en el\nPeriódico Oficial del Estado.\nSegundo.- Túrnese el presente Decreto al Titular del Poder Ejecutivo del Estado para los efectos de publicación en el Periódico Oficial del Estado de Baja California.\nDADO en el Salón de Sesiones “Lic. Benito Juárez García” del H. Poder egislativo del\nEstado de Baja California, en la Ciudad de Mexicali, B.C., a los veinticinco días del mes de septiembre del año dos mil trece.\nDIP. GREGORIO CARRANZA HERNÁNDEZ\nPRESIDENTE\n(RÚBRICA)\nDIP. MARCO ANTONIO VIZCARRA CALDERÓN\nSECRETARIO\n(RÚBRICA)\nDE CONFORMIDAD CON LO DISPUESTO POR LA FRACCIÓN I DEL ARTÍCULO 49\nMEXICALI, BAJA CALIFORNIA, A LOS TREINTA DÍAS DEL MES DE SEPTIEMBRE\nDEL AÑO DOS MIL TRECE.\nJOSÉ GUADALUPE OSUNA MILLÁN\nGOBERNADOR DEL ESTADO\n(RÚBRICA)\nFRANCISCO ANTONIO GARCÍA BURGOS\nSECRETARIO GENERAL DE GOBIERNO\n(RÚBRICA)\nARTÍCULO UNICO TRANSITORIO DEL DECRETO No. 330, POR EL QUE SE\nREFORMAN LOS ARTÍCULOS 49, 52 Y 61, PUBLICADO EN EL PERIÓDICO OFICIAL No.\nLEGISLATURA, SIENDO GOBERNADOR CONSTITUCIONAL EL C. FRANCISCO ARTURO\nVEGA DE LAMADRID 2013-2019.\nLey de los Derechos, Protección e Integración de las Personas Adultas Mayores Página 39\nPRIMERO.- Las presentes reformas entrarán en vigor al día siguiente de su publicación en el Periódico Oficial del Estado.\nSEGUNDO.- El Consejo Estatal y los consejos municipales, en el ámbito de sus respectivas atribuciones y dentro de un plazo no mayor al de noventa días, contados a partir de la entrada en vigor de las presentes reformas, emitirán o modificarán en su caso, las disposiciones reglamentarias que sean necesarias para dar cumplimiento al presente Decreto.\nDADO en el Salón de Sesiones “Lic. Benito Juárez García” del H. Poder Legislativo del\nEstado de Baja California, en la Ciudad de Mexicali, B.C., a los veinticuatro días del mes de septiembre del año dos mil quince.\nDIP. IRMA MARTÍNEZ MANRÍQUEZ\nPRESIDENTA\n(RUBRICA)\nDIP. MARIO OSUNA JIMÉNEZ\nSECRETARIO\n(RUBRICA)\nDE CONFORMIDAD CON LO DISPUESTO POR LA FRACCIÓN I DEL ARTÍCULO 49\nMEXICALI, BAJA CALIFORNIA, A LOS DIECISEIS DÍAS DEL MES DE OCTUBRE\nDEL AÑO DOS MIL QUINCE.\nFRANCISCO ARTURO VEGA DE LAMADRID\nGOBERNADOR DEL ESTADO\n(RÚBRICA)\nFRANCISCO RUEDA GÓMEZ\nSECRETARIO GENERAL DE GOBIERNO\n(RÚBRICA)\nARTÍCULO UNICO TRANSITORIO DEL DECRETO No. 415, POR EL QUE SE\nADICIONA LA FRACCIÓN IV AL ARTÍCULO 6, Y FRACCIÓN XIX AL ARTÍCULO 53,\nRECORRIÉNDOSE EN SU ORDEN LAS SUBSECUENTES; ASÍ MISMO SE REFORMA LA\nFRACCIÓN XXI DEL ARTÍCULO 8, EL ARTÍCULO 24 Y LA FRACCIÓN II DEL NUMERAL 41,\nPUBLICADO EN EL PERIÓDICO OFICIAL No. 58, SECCION IV, TOMO CXXII, DE FECHA\nGOBERNADOR CONSTITUCIONAL EL C. FRANCISCO ARTURO VEGA DE LAMADRID\n2013-2019.\nARTÍCULO TRANSITORIO\nLey de los Derechos, Protección e Integración de las Personas Adultas Mayores Página 40\nÚNICO.- Las presentes reformas entrarán en vigor al día siguiente de su publicación en el Periódico Oficial del Estado.\nEstado de Baja California, en la Ciudad de Mexicali, B.C., a los tres días del mes de diciembre del año dos mil quince.\nDIP. IRMA MARTÍNEZ MANRÍQUEZ\nPRESIDENTA\n(RUBRICA)\nDIP. MARIO OSUNA JIMÉNEZ\nSECRETARIO\n(RUBRICA)\nDE CONFORMIDAD CON LO DISPUESTO POR LA FRACCION I DEL ARTÍCULO 49\nMEXICALI, BAJA CALIFORNIA, A LOS ONCE DÍAS DEL MES DE DICIEMBRE DEL\nAÑO DOS MIL QUINCE.\nFRANCISCO ARTURO VEGA DE LAMADRID\nGOBERNADOR DEL ESTADO\n(RÚBRICA)\nFRANCISCO RUEDA GOMEZ\nSECRETARIO GENERAL DE GOBIERNO\n(RÚBRICA)\nARTÍCULO UNICO TRANSITORIO DEL DECRETO No. 417, POR EL QUE SE\nREFORMA LA FRACCIÓN II DEL ARTÍCULO 17, PUBLICADO EN EL PERIÓDICO OFICIAL\nNo. 58, SECCION IV, TOMO CXXII, DE FECHA 18 DE DICIEMBRE DE 2015, EXPEDIDO\nPOR LA H. XXI LEGISLATURA, SIENDO GOBERNADOR CONSTITUCIONAL EL C.\nFRANCISCO ARTURO VEGA DE LAMADRID 2013-2019.\nARTÍCULO TRANSITORIO\nÚNICO.- El presente decreto entrara en vigor al día siguiente de su publicación en el\nPeriódico Oficial del Estado.\nEstado de Baja California, en la Ciudad de Mexicali, B.C., a los tres días del mes de diciembre del año dos mil quince.\nLey de los Derechos, Protección e Integración de las Personas Adultas Mayores Página 41\nDIP. IRMA MARTÍNEZ MANRÍQUEZ\nPRESIDENTA\n(RUBRICA)\nDIP. MARIO OSUNA JIMÉNEZ\nSECRETARIO\n(RUBRICA)\nDE CONFORMIDAD CON LO DISPUESTO POR LA FRACCION I DEL ARTÍCULO 49\nMEXICALI, BAJA CALIFORNIA, A LOS ONCE DÍAS DEL MES DE DICIEMBRE DEL\nAÑO DOS MIL QUINCE.\nFRANCISCO ARTURO VEGA DE LAMADRID\nGOBERNADOR DEL ESTADO\n(RÚBRICA)\nFRANCISCO RUEDA GOMEZ\nSECRETARIO GENERAL DE GOBIERNO\n(RÚBRICA)\nARTÍCULO UNICO TRANSITORIO DEL DECRETO No. 450, POR EL QUE SE\nREFORMA LA FRACCIÓN XXI, DEL ARTÍCULO 8; PUBLICADO EN EL PERIÓDICO\nOFICIAL No. 14, SECCION IV, TOMO CXXIII, DE FECHA 18 DE MARZO DE 2016,\nEXPEDIDO POR LA H. XXI LEGISLATURA, SIENDO GOBERNADOR CONSTITUCIONAL\nEL C. FRANCISCO ARTURO VEGA DE LAMADRID 2013-2019.\nTRANSITORIO\nARTÍCULO ÚNICO.- El presente Decreto entrará en vigor al día siguiente de su publicación en el Periódico Oficial del Estado.\nDADO en el Salón de Sesiones “Lic. Benito Juárez García” del H. Poder Legislativo del\nEstado de Baja California, en la Ciudad de Mexicali, B.C., a los once días del mes de febrero del año dos mil dieciséis.\nDIP. RODOLFO OLIMPO HERNÁNDEZ BOJÓRQUEZ\nPRESIDENTE\n(RUBRICA)\nDIP. ARMANDO REYES LEDESMA\nSECRETARIO\n(RUBRICA)\nDE CONFORMIDAD CON LO DISPUESTO POR LA FRACCION I DEL ARTÍCULO 49\nLey de los Derechos, Protección e Integración de las Personas Adultas Mayores Página 42\nMEXICALI, BAJA CALIFORNIA, A LOS DOS DÍAS DEL MES DE MARZO DEL AÑO\nDOS MIL DIECISÉIS.\nFRANCISCO ARTURO VEGA DE LAMADRID\nGOBERNADOR DEL ESTADO\n(RÚBRICA)\nFRANCISCO RUEDA GOMEZ\nSECRETARIO GENERAL DE GOBIERNO\n(RÚBRICA)\nARTÍCULO ÚNICO TRANSITORIO DEL DECRETO No. 130, POR EL QUE SE\nAPRUEBA LA REFORMA Y ADICIÓN DE LA FRACCIÓN XV AL ARTÍCULO 17; PUBLICADO\nEN EL PERIÓDICO OFICIAL No. 50, SECCIÓN III, TOMO CXXIV, DE FECHA 10 DE\nNOVIEBRE DE 2017, EXPEDIDO POR LA H. XXII LEGISLATURA, SIENDO GOBERNADOR\nCONSTITUCIONAL EL C. FRANCISCO ARTURO VEGA DE LAMADRID 2013-2019.\nARTÍCULO TRANSITORIO\nÚNICO.- El presente reforma entrará en vigor al día siguiente de su publicación en el\nPeriódico Oficial del Estado de Baja California.\nDADO en el Salón de Sesiones “Lic. Benito Juárez García” del H. Poder Legislativo del\nEstado de Baja California, en la Ciudad de Mexicali, B.C., a los veintinueve días del mes de septiembre del año dos mil diecisiete.\nDIP. EDGAR BENJAMÍN GÓMEZ MACÍAS\nPRESIDENTE\n(RÚBRICA)\nDIP. EVA MARÍA VÁSQUEZ HERNÁNDEZ\nSECRETARIA\n(RÚBRICA)\nDE CONFORMIDAD CON LO DISPUESTO POR LA FRACCIÓN I DEL ARTÍCULO 49\nMEXICALI, BAJA CALIFORNIA, A LOS DIECIOCHO DÍAS DE OCTUBRE DEL AÑO\nDOS MIL DIECISIETE.\nLey de los Derechos, Protección e Integración de las Personas Adultas Mayores Página 43\nFRANCISCO ARTURO VEGA DE LAMADRID\nGOBERNADOR DEL ESTADO\n(RÚBRICA)\nFRANCISCO RUEDA GÓMEZ\nSECRETARIO GENERAL DE GOBIERNO\n(RÚBRICA)\nARTÍCULO ÚNICO TRANSITORIO DEL DECRETO No. 317, POR EL QUE SE\nAPRUEBA LA REFORMA A LOS ARTÍCULOS 27 Y 35; PUBLICADO EN EL PERIÓDICO\nOFICIAL No. 10, SECCIÓN III, TOMO CXXVI, DE FECHA 22 DE FEBRERO DE 2019,\nEXPEDIDO POR LA H. XXII LEGISLATURA, SIENDO GOBERNADOR CONSTITUCIONAL\nEL C. FRANCISCO ARTURO VEGA DE LAMADRID 2013-2019.\nARTÍCULO TRANSITORIO\nÚNICO.- El presente Decreto entrará en vigor al día siguiente de su publicación en el\nPeriódico Oficial del Estado.\nDADO en el Salón de Sesiones “Lic. Benito Juárez García” del H. Poder Legislativo del\nEstado de Baja California, en la Ciudad de Mexicali, B.C., a los diez días del mes de enero del año dos mil diecinueve.\nDIP. CARLOS ALBERTO TORRES TORRES\nPRESIDENTE\n(RÚBRICA)\nDIP. MARÍA TRINIDAD VACA CHACÓN\nSECRETARIA\n(RÚBRICA)\nDE CONFORMIDAD CON LO DISPUESTO POR LA FRACCIÓN I DEL ARTÍCULO 49\nMEXICALI, BAJA CALIFORNIA, A LOS VEINTIDOS DÍAS DEL MES DE FEBRERO\nDEL AÑO DOS MIL DIECINUEVE.\nFRANCISCO ARTURO VEGA DE LAMADRID\nGOBERNADOR DEL ESTADO\n(RÚBRICA)\nFRANCISCO RUEDA GÓMEZ\nSECRETARIO GENERAL DE GOBIERNO\nLey de los Derechos, Protección e Integración de las Personas Adultas Mayores Página 44\n(RÚBRICA)\nARTÍCULO ÚNICO TRANSITORIO DEL DECRETO No. 73, POR EL QUE SE\nAPRUEBA LA REFORMA A LOS ARTÍCULOS 8 Y 39; PUBLICADO EN EL PERIÓDICO\nEXPEDIDO POR LA H. XXIII LEGISLATURA, SIENDO GOBERNADOR CONSTITUCIONAL\nEL C. JAIME BONILLA VALDEZ 2019-2021.\nARTÍCULO TRANSITORIO\nPRIMERO.- El presente Decreto entrará en vigor al día siguiente de su publicación en el Periódico Oficial del Estado.\nSEGUNDO.- Las presentes reformas serán aplicadas acorde a los convenios federales de la materia y la disponibilidad presupuestaria del sector de salud.\nDADO en el Salón de Sesiones “Lic. Benito Juárez García” del H. Poder Legislativo del\nEstado de Baja California, en la Ciudad de Mexicali, B.C., a los doce días del mes de junio del año dos mil veinte.\nDIP. JULIO CÉSAR VÁZQUEZ CASTILLO\nVICEPRESIDENTE\n(RÚBRICA)\nDIP. EVA GRICELDA RODRÍGUEZ\nSECRETARIA\n(RÚBRICA)\nDE CONFORMIDAD CON LO DISPUESTO POR LA FRACCIÓN I DEL ARTÍCULO 49\nMEXICALI, BAJA CALIFORNIA, A LOS DIECINUEVE DÍAS DEL MES DE JUNIO DEL\nAÑO DOS MIL VEINTE.\nJAIME BONILLA VALDEZ\nGOBERNADOR DEL ESTADO\n(RÚBRICA)\nAMADOR RODRÍGUEZ LOZANO\nSECRETARIO GENERAL DE GOBIERNO\n(RÚBRICA)\nLey de los Derechos, Protección e Integración de las Personas Adultas Mayores Página 45\nARTÍCULO ÚNICO TRANSITORIO DEL DECRETO No. 130, POR EL QUE SE\nAPRUEBA LA REFORMA AL ARTÍCULO 26; PUBLICADO EN EL PERIÓDICO OFICIAL No.\nLA H. XXIV LEGISLATURA, SIENDO GOBERNADORA CONSTITUCIONAL LA C. MARINA\nDEL PILAR ÁVILA OLMEDA 2021-2027.\nARTÍCULO TRANSITORIO\nÚNICO.- La presente reforma entrará en vigor al día siguiente de su publicación en el\nPeriódico Oficial del Estado de Baja California.\nDADO en Sesión Ordinaria de la XXIV Legislatura en la Ciudad de Mexicali, B.C., a los veinticinco días del mes de agosto del año dos mil veintidós.\nDIP. ALEJANDRA MARÍA ANG HERNÁNDEZ\nPRESIDENTA\n(RÚBRICA)\nDIP. DUNNIA MONTSERRAT MURILLO LÓPEZ\nSECRETARIA\n(RÚBRICA)\nDE CONFORMIDAD CON LO DISPUESTO POR LA FRACCIÓN I DEL ARTÍCULO 49\nCALIFORNIA, IMPRÍMASE Y PUBLÍQUESE.\nMEXICALI, BAJA CALIFORNIA, A LOS CINCO DÍAS DEL MES DE SEPTIEMBRE DEL\nAÑO DOS MIL VEINTIDÓS.\nMARINA DEL PILAR ÁVILA OLMEDA\nGOBERNADORA DEL ESTADO\nDE BAJA CALIFORNIA\n(RÚBRICA)\nCATALINO ZAVALA MÁRQUEZ\nSECRETARIO GENERAL DE GOBIERNO\nDEL ESTADO DE BAJA CALIFORNIA\n(RÚBRICA)\nARTÍCULO ÚNICO TRANSITORIO DEL DECRETO No. 279, POR EL QUE SE\nREFORMA A LOS ARTÍCULOS 1, 2, 6, 7, 38, 41, 42, 44 BIS, 47 y 54, ASÍ COMO LA\nADICIÓN DEL ARTÍCULO 6 BIS; PUBLICADO EN EL PERIÓDICO OFICIAL No. 53,\nH. XXIV LEGISLATURA, SIENDO GOBERNADORA CONSTITUCIONAL LA C. MARINA DEL\nPILAR ÁVILA OLMEDA 2021-2027.\nLey de los Derechos, Protección e Integración de las Personas Adultas Mayores Página 46\nTRANSITORIO\nÚNICO. El presente Decreto entrará en vigor al día siguiente de su publicación en el Periódico\nOficial del Estado.\nDADO en Sesión Ordinaria de la XXIV Legislatura en la Ciudad de Mexicali, B.C., a los veinticuatro días del mes de agosto del año dos mil veintitrés.\nDIP. MANUEL GUERRERO LUNA\nPRESIDENTE\n(RÚBRICA)\nDIP. DUNNIA MONTSERRAT MURILLO LÓPEZ\nSECRETARIA\n(RÚBRICA)\nDE CONFORMIDAD CON LO DISPUESTO POR LA FRACCIÓN I DEL ARTÍCULO 49\nBAJA CALIFORNIA, IMPRÍMASE Y PUBLÍQUESE.\nMEXICALI, BAJA CALIFORNIA, A LOS VEINTIOCHO DÍAS DEL MES DE AGOSTO\nDEL AÑO DOS MIL VEINTITRÉS.\nMARINA DEL PILAR ÁVILA OLMEDA\nGOBERNADOR DEL ESTADO\nDE BAJA CALIFORNIA\n(RÚBRICA)\nCATALINO ZAVALA MÁRQUEZ\nSECRETARIO GENERAL DE GOBIERNO\nDEL ESTADO DE BAJA CALIFORNIA\n(RÚBRICA)\nARTÍCULO ÚNICO TRANSITORIO DEL DECRETO No. 314, POR EL QUE SE\nAPRUEBA LA ADICIÓN DE LA FRACCIÓN XIV AL ARTÍCULO 35; PUBLICADO EN EL\nCXXX, EXPEDIDO POR LA H. XXIV LEGISLATURA, SIENDO GOBERNADORA\nCONSTITUCIONAL LA C. MARINA DEL PILAR ÁVILA OLMEDA 2021-2027.\nTRANSITORIO\nÚNICO.- La presente reforma entrará en vigor al día siguiente de su publicación en el\nPeriódico Oficial del Estado de Baja California.\nLey de los Derechos, Protección e Integración de las Personas Adultas Mayores Página 47\nDADO en Sesión Ordinaria de la XXIV Legislatura en la Ciudad de Mexicali, B.C., a los nueve días del mes de noviembre del año dos mil veintitrés.\nDIP. MANUEL GUERRERO LUNA\nPRESIDENTE\n(RÚBRICA)\nDIP. DUNNIA MONTSERRAT MURILLO LÓPEZ\nSECRETARIA\n(RÚBRICA)\nDE CONFORMIDAD CON LO DISPUESTO POR LA FRACCIÓN I DEL ARTÍCULO 49\nCALIFORNIA, IMPRÍMASE Y PUBLÍQUESE.\nMEXICALI, BAJA CALIFORNIA, A LOS CATORCE DÍAS DEL MES DE NOVIEMBRE\nDEL AÑO DOS MIL VEINTITRÉS.\nMARINA DEL PILAR ÁVILA OLMEDA\nGOBERNADORA DEL ESTADO\nDE BAJA CALIFORNIA\n(RÚBRICA)\nCATALINO ZAVALA MÁRQUEZ\nSECRETARIO GENERAL DE GOBIERNO\nDEL ESTADO DE BAJA CALIFORNIA\n(RÚBRICA)\nARTÍCULO ÚNICO TRANSITORIO DEL DECRETO No. 393, POR EL QUE SE\nAPRUEBA LA REFORMA A LA FRACCIÓN XI AL ARTÍCULO 8; PUBLICADO EN EL\nEXPEDIDO POR LA H. XXIV LEGISLATURA, SIENDO GOBERNADORA CONSTITUCIONAL\nLA C. MARINA DEL PILAR ÁVILA OLMEDA 2021-2027.\nTRANSITORIO\nÚNICO.- La presente reforma entrará en vigor al día siguiente de su publicación en el\nPeriódico Oficial del Estado de Baja California.\nDADO en Sesión Ordinaria de la XXIV Legislatura en la Ciudad de Mexicali, B.C., a los quince días del mes de febrero del año dos mil veinticuatro.\nLey de los Derechos, Protección e Integración de las Personas Adultas Mayores Página 48\nDIP. ARACELI GERALDO NÚÑEZ\nPRESIDENTA\n(RÚBRICA)\nDIP. MANUEL GUERRERO LUNA\nSECRETARIO\n(RÚBRICA)\nDE CONFORMIDAD CON LO DISPUESTO POR LA FRACCIÓN I DEL ARTÍCULO 49\nCALIFORNIA, IMPRÍMASE Y PUBLÍQUESE.\nMEXICALI, BAJA CALIFORNIA, A LOS CATORCE DÍAS DEL MES DE MARZO DEL\nAÑO DOS MIL VEINTICUATRO.\nMARINA DEL PILAR ÁVILA OLMEDA\nGOBERNADORA DEL ESTADO\nDE BAJA CALIFORNIA\n(RÚBRICA)\nALFREDO ÁLVAREZ CÁRDENAS\nSECRETARIO GENERAL DE GOBIERNO\nDEL ESTADO DE BAJA CALIFORNIA\n(RÚBRICA)\nARTÍCULO ÚNICO TRANSITORIO DEL DECRETO No. 394, POR EL QUE SE\nAPRUEBA LA REFORMA AL ARTÍCULO 43; PUBLICADO EN EL PERIÓDICO OFICIAL No.\n14, ÍNDICE, DE FECHA 15 DE MARZO DE 2024, TOMO CXXXI, EXPEDIDO POR LA H.\nXXIV LEGISLATURA, SIENDO GOBERNADORA CONSTITUCIONAL LA C. MARINA DEL\nPILAR ÁVILA OLMEDA 2021-2027.\nTRANSITORIO\nÚNICO.- La presente reforma entrará en vigor al día siguiente de su publicación en el\nPeriódico Oficial del Estado.\nDADO en Sesión Ordinaria de la XXIV Legislatura en la Ciudad de Mexicali, B.C., a los quince días del mes de febrero del año dos mil veinticuatro.\nDIP. ARACELI GERALDO NÚÑEZ\nPRESIDENTA\n(RÚBRICA)\nLey de los Derechos, Protección e Integración de las Personas Adultas Mayores Página 49\nDIP. MANUEL GUERRERO LUNA\nSECRETARIO\n(RÚBRICA)\nDE CONFORMIDAD CON LO DISPUESTO POR LA FRACCIÓN I DEL ARTÍCULO 49\nCALIFORNIA, IMPRÍMASE Y PUBLÍQUESE.\nMEXICALI, BAJA CALIFORNIA, A LOS CATORCE DÍAS DEL MES DE MARZO DEL\nAÑO DOS MIL VEINTICUATRO.\nMARINA DEL PILAR ÁVILA OLMEDA\nGOBERNADORA DEL ESTADO\nDE BAJA CALIFORNIA\n(RÚBRICA)\nALFREDO ÁLVAREZ CÁRDENAS\nSECRETARIO GENERAL DE GOBIERNO\nDEL ESTADO DE BAJA CALIFORNIA\n(RÚBRICA)\nARTÍCULO ÚNICO TRANSITORIO DEL DECRETO No. 53, POR EL QUE SE\nAPRUEBA LA REFORMA AL ARTÍCULO 6 BIS; PUBLICADO EN EL PERIÓDICO OFICIAL\nNo. 15, ÍNDICE, DE FECHA 14 DE MARZO DE 2025, TOMO CXXXII, EXPEDIDO POR LA H.\nXXV LEGISLATURA, SIENDO GOBERNADORA CONSTITUCIONAL LA C. MARINA DEL\nPILAR ÁVILA OLMEDA 2021-2027.\nTRANSITORIO\nÚNICO.- La presente reforma entrará en vigor al día siguiente de su publicación en el\nPeriódico Oficial del Estado de Baja California.\nDADO en Sesión Ordinaria de la XXV Legislatura en la Ciudad de Mexicali, B.C., a los veintisiete días del mes de febrero del año dos mil veinticinco.\nDIP. EVELYN SÁNCHEZ SÁNCHEZ\nPRESIDENTA\n(RÚBRICA)\nDIP. MICHELLE ALEJANDRA TEJEDA MEDINA\nSECRETARIA\n(RÚBRICA)\nLey de los Derechos, Protección e Integración de las Personas Adultas Mayores Página 50\nDE CONFORMIDAD CON LO DISPUESTO POR LA FRACCIÓN I DEL ARTÍCULO 49\nCALIFORNIA, IMPRÍMASE Y PUBLÍQUESE.\nMEXICALI, BAJA CALIFORNIA, A LOS TRES DÍAS DEL MES DE MARZO DEL AÑO\nDOS MIL VEINTICINCO.\nMARINA DEL PILAR ÁVILA OLMEDA\nGOBERNADORA DEL ESTADO\nDE BAJA CALIFORNIA\n(RÚBRICA)\nALFREDO ÁLVAREZ CÁRDENAS\nSECRETARIO GENERAL DE GOBIERNO\nDEL ESTADO DE BAJA CALIFORNIA\n(RÚBRICA)\nARTÍCULO ÚNICO TRANSITORIO DEL DECRETO No. 77, POR EL QUE SE\nAPRUEBA LA REFORMA A LOS ARTÍCULOS 6, 6 BIS Y 39; PUBLICADO EN EL\nPERIÓDICO OFICIAL No. 22, ÍNDICE, DE FECHA 11 DE ABRIL DE 2025, TOMO CXXXII;\nEXPEDIDO POR LA H. XXV LEGISLATURA, SIENDO GOBERNADORA CONSTITUCIONAL\nLA C. MARINA DEL PILAR ÁVILA OLMEDA 2021-2027.\nTRANSITORIO\nÚNICO.- El presente Decreto entrará en vigor al día siguiente de su publicación en el\nPeriódico Oficial del Estado.\nDADO en Sesión Ordinaria de la XXV Legislatura en la Ciudad de Tijuana, B.C., a los veintisiete días del mes de marzo del año dos mil veinticinco.\nDIP. EVELYN SÁNCHEZ SÁNCHEZ\nPRESIDENTA\n(RÚBRICA)\nDIP. MICHELLE ALEJANDRA TEJEDA MEDINA\nSECRETARIA\n(RÚBRICA)\nDE CONFORMIDAD CON LO DISPUESTO POR LA FRACCIÓN I DEL ARTÍCULO 49\nCALIFORNIA, IMPRÍMASE Y PUBLÍQUESE.\nMEXICALI, BAJA CALIFORNIA, A LOS 31 DÍAS DEL MES DE MARZO DEL AÑO DOS MIL\nVEINTICINCO.\nLey de los Derechos, Protección e Integración de las Personas Adultas Mayores Página 51\nMARINA DEL PILAR ÁVILA OLMEDA\nGOBERNADORA DEL ESTADO\nDE BAJA CALIFORNIA\n(RÚBRICA)\nALFREDO ÁLVAREZ CÁRDENAS\nSECRETARIO GENERAL DE GOBIERNO\nDEL ESTADO DE BAJA CALIFORNIA\n(RÚBRICA)\nARTÍCULO ÚNICO TRANSITORIO DEL DECRETO No. 140, POR EL QUE SE\nAPRUEBA LA REFORMA A LOS ARTÍCULOS 49, 62 Y 63; PUBLICADO EN EL PERIÓDICO\nOFICIAL No. 60, ÍNDICE, DE FECHA 03 DE OCTUBRE DE 2025, TOMO CXXXII; EXPEDIDO\nPOR LA H. XXV LEGISLATURA, SIENDO GOBERNADORA CONSTITUCIONAL LA C.\nMARINA DEL PILAR ÁVILA OLMEDA 2021-2027.\nTRANSITORIO\nÚNICO. La presente reforma entrará en vigor al día siguiente al de su publicación en el\nPeriódico Oficial del Estado.\nDADO en Sesión Ordinaria de la XXV Legislatura en la Ciudad de Mexicali, B.C., a los once días del mes de septiembre del año dos mil veinticinco.\nDIP. JAIME EDUARDO CANTÓN ROCHA\nPRESIDENTE\n(RÚBRICA)\nDIP. MICHELLE ALEJANDRA TEJEDA MEDINA\nSECRETARIA\n(RÚBRICA)\nDE CONFORMIDAD CON LO DISPUESTO POR LA FRACCIÓN I DEL ARTÍCULO 49\nCALIFORNIA, IMPRÍMASE Y PUBLÍQUESE.\nMEXICALI, BAJA CALIFORNIA, A LOS 17 DÍAS DEL MES DE SEPTIEMBRE DEL\nAÑO DOS MIL VEINTICINCO.\nMARINA DEL PILAR ÁVILA OLMEDA\nGOBERNADORA DEL ESTADO\nDE BAJA CALIFORNIA\n(RÚBRICA)\nLey de los Derechos, Protección e Integración de las Personas Adultas Mayores Página 52\nALFREDO ÁLVAREZ CÁRDENAS\nSECRETARIO GENERAL DE GOBIERNO\nDEL ESTADO DE BAJA CALIFORNIA\n(RÚBRICA)\nLey de los Derechos, Protección e Integración de las Personas Adultas Mayores Página 53",
  "ordenamiento": "REGLAMENTO",
  "jurisdiccion": "BAJA CALIFORNIA",
  "fuente_oficial": "Periódico Oficial",
  "FECHA PER OFIC": "2025/10/03",
  "ESTATUS": "VIGENTE",
  "TOMO": "TOMO_III",
  "URL": "https://www.congresobc.gob.mx/Documentos/ProcesoParlamentario/Leyes/TOMO_III/20251003_LEYPERSONASADULTAS.PDF",
  "es_escaneado": false,
  "tiene_tablas": false,
  "materia": [
    "familiar",
    "civil",
    "adopción"
  ]
}