{
  "titulo": "Ley DE FOMENTO A LA LECTURA y EL LIBRO DEL ESTADO DE BAJA CALIFORNIA",
  "Contenido": "CALIFORNIA\nPublicada en el Periódico Oficial No. 47, Tomo CXIX, Sección I, de fecha\nCAPÍTULO I\nDISPOSICIONES GENERALES\nArtículo 1. La presente Ley es de orden público y de interés social, sus disposiciones se aplicarán en todo el territorio del Estado.\nLo establecido en esta Ley se aplicará sin perjuicio de lo ordenado en cualquier otro ordenamiento en la materia, siempre y cuando no contravengan lo que en esta se dispone.\nArtículo 2. La presente Ley tendrá por objeto:\nI. Fomentar el hábito de la lectura entre los habitantes del Estado;\nII. Impulsar la producción, edición, publicación y difusión de libros y facilitar su acceso a la población;\nIII. Promover políticas, programas y acciones relacionadas con el fomento a la lectura y el libro;\nIV. Promover la participación social y de los sectores público y privado en las actividades de fomento a la lectura y el libro;\nV. Determinar la integración, facultades y ámbito de competencia del Consejo Estatal y de los Consejos Municipales;\nVI. Implementar las bases técnicas para la elaboración de los programas Estatal y\nMunicipales para el Fomento a la Lectura y el Libro;\nVII. Garantizar el fomento de la lectura y de producción literaria entre la población, este sentido, conforme a lo establecido en la normatividad aplicable;\nVIII. Regular las actividades relacionadas con el fomento a la lectura y el libro, en los medios de comunicación de los Poderes del Estado, órganos autónomos y ayuntamientos;\nIX. Promover el desarrollo de sistemas integrales de información sobre el libro, su distribución, la lectura y los derechos de autor, así como crear una base de datos que contemple: catálogos y directorios colectivos de autores, obras, editoriales, industria grafica, bibliotecas y librerías disponibles para la consulta en red desde cualquier parte del Estado;\nX. Apoyar las actividades en defensa de los derechos de autor, el traductor y del editor, dentro y fuera del territorio nacional;\nXI. Impulsar el incremento y mejora de la producción editorial nacional y estatal que de respuesta a los requerimientos culturales y educativos en condiciones adecuadas de cantidad, calidad, precio y variedad;\nXII. Difundir a los creadores literarios locales y regionales, así como exposiciones, ferias y festivales del libro y la lectura;\nXIII. Promover la formación e integración de promotores de lectura en cada uno de los municipios;\nXIV. Promover la creación y mantenimiento de bibliotecas populares y de centros públicos de lectura, en todos los municipios; y\nXV. Prever los mecanismos financieros necesarios para la obtención de los ingresos públicos o privados que se requieran, a efecto de hacer posible el cumplimiento de los objetivos establecidos en la presente Ley.\nArtículo 3.- El fomento a la lectura y el libro se establece en esta Ley en el marco de las garantías constitucionales de libertad de escribir, editar y publicar libros sobre cualquier materia, propiciando el acceso a la lectura y el libro a toda la población.\nNinguna autoridad estatal o municipal podrá prohibir, restringir ni obstaculizar la creación, edición, producción, distribución, promoción o difusión de libros y de las publicaciones periódicas en el Estado de Baja California.\nArtículo 4. Para los fines de la presente Ley se entenderá por:\nLey: La Ley de Fomento a la Lectura y el Libro del Estado de Baja California;\nEstado: El Estado de Baja California;\nSecretario de Educación y Bienestar Social;\nMunicipios: Los municipios del Estado;\nPrograma Estatal: Programa Estatal para el Fomento de la Lectura y el Libro;\nPrograma Municipal: Programa Municipal para el Fomento de la Lectura y el Libro;\nConsejo Estatal: El Consejo Estatal para el Fomento a la Lectura y el Libro;\nConsejos Municipales: Los Consejos Municipales para el Fomento a la Lectura y el\nLibro;\nBibliotecas Populares: Los lugares públicos, de acceso gratuito, donde se conserva y administra el acervo bibliográfico de un lugar determinado, propiedad del Estado o del\nMunicipio;\nSalas de Lectura: Espacios dotados con libros, en donde se promueva, fomente y estimule el hábito de la lectura a través de un promotor capacitado.\nEdición: Proceso de formación del libro a partir de la selección de textos y otros contenidos para ofrecerlo después de su producción al lector.\nEditor: Persona física o moral que selecciona o concibe una edición y realiza por sí o a través de terceros su elaboración.\nDistribución: Actividad de intermediación entre el editor y el vendedor de libros al menudeo, que facilita el acceso al libro propiciando su presencia en el mercado.\nDistribuidor: Persona física o moral legalmente constituida, dedicada a la distribución de libros y revistas.\nLibro: Toda publicación unitaria, no periódica, de carácter literario, artístico, científico, técnico, educativo, informativo o recreativo, impresa en cualquier soporte, cuya edición se fascículos. Comprenderá también los materiales complementarios en cualquier tipo de soporte, incluido el electrónico, que conformen, conjuntamente con el libro, un todo unitario que no pueda comercializarse separadamente.\nRevista: Publicación de periodicidad no diaria, generalmente ilustrada, encuadernada, con escritos sobre varias materias o especializada. Para el objeto de esta\nLey, las revistas gozarán de las mismas prerrogativas que se señalen para el libro.\nLibro mexicano: Toda publicación unitaria no periódica que tenga ISBN que lo identifique como mexicano.\nRevista mexicana: Publicación de periodicidad no diaria que tenga ISSN que la identifique como mexicana.\nAutor: Persona que realiza alguna obra destinada a ser difundida en forma de libro.\nSe considera como autor, sin perjuicio de los requisitos establecidos en la legislación vigente, al traductor respecto de su traducción, al compilador y a quien extracta o adapta obras originales, así como al ilustrador y al fotógrafo, respecto de sus correspondientes trabajos.\nPrecio único de venta al público: Valor de comercialización establecido libremente por el editor o importador para cada uno de sus títulos; y\nVendedores de libros al menudeo: Aquellas personas, físicas o morales, que comercializan libros al público.\nCAPÍTULO II\nDE LA COORDINACIÓN SOCIAL E INTERINSTITUCIONAL PARA EL FOMENTO DE LA\nLECTURA Y EL LIBRO\nArtículo 5. Para el alcance de los objetivos y para la efectiva aplicación de las políticas, programas y acciones que el Ejecutivo del Estado desarrolle a favor del fomento a la lectura y el libro, entre los habitantes de la Entidad, éste llevará a cabo diversas acciones de coordinación con las organizaciones de madres y padres de familia, las instituciones públicas, privadas y sociales, los organismos culturales, los clubes de lectura privados, los círculos literarios, los gremios de intelectuales y con cualquier otra organización de la sociedad civil que contribuya a elevar el nivel cultural en el Estado.\nArtículo 6. En el ámbito de sus respectivas competencias y facultades, el Ejecutivo responsables de la aplicación de las políticas, programas y acciones de fomento a la lectura y el libro en el Estado.\nArtículo 7. Con el fin de garantizar que las políticas, programas y acciones que el con eficiencia en todo el territorio de la Entidad, deberá coordinar sus acciones con los gobiernos municipales y, en su caso, con los Consejos Municipales, a efecto de hacer efectivo el ejercicio de este derecho.\nArtículo 8. Será responsabilidad del Ejecutivo del Estado y de los gobiernos de los municipios, en el ámbito de sus respectivas competencias y jurisdicciones, garantizar a la fomento a la lectura y la producción, edición, distribución y difusión de cualquier obra literaria.\nAdemás, y de acuerdo a su capacidad presupuestaria deberá fomentar y facilitar el acceso a libros, revistas, artículos y todas las variedades de textos en dialectos indígenas de la región, de igual forma la producción de publicaciones en sistema braille, audio libros o cualquier otro mecanismo que facilite el acceso a la lectura para personas con alguna discapacidad.\nAdicionado\nLas autoridades encargadas del fomento a la lectura y el libro, también deberán garantizar que en los Centros Penitenciarios del Estado se establezcan acervos bibliográficos o bibliotecas, que comprendan material instructivo y recreativo, así como las leyes y textos jurídicos a los que puedan tener acceso quienes ahí se encuentran recluidos.\nAdicionado\nCAPÍTULO III\nDE LAS AUTORIDADES\nArtículo 9. Son autoridades para los fines de la presente Ley:\nI. El Ejecutivo del Estado;\nII. El Instituto de Cultura de Baja California\nIII. El Consejo Estatal;\nIV. Los Consejos Municipales; y,\nV. Las unidades administrativas responsables de la operación del Programa Estatal y del Programa Municipal.\nCAPÍTULO IV\nArtículo 10. El Consejo Estatal es el órgano regulador de las políticas, programas y acciones que promuevan en el Estado el fomento a la lectura y la producción, edición, distribución y difusión de cualquier obra literaria, que contribuya a elevar el nivel cultural de la población.\nArtículo 11. El Consejo Estatal se integrará por:\nI.- Un Presidente que será el titular de la Secretaría de Educación y Bienestar Social;\nII. El Secretario Técnico, que será el titular del Instituto de Cultura de Baja California;\nIII. El Presidente de la Comisión de Educación, Cultura, Ciencia y Tecnología del H.\nCongreso del Estado;\nLos cargos del Consejo Estatal serán honoríficos, además los integrantes podrán nombre un suplente para asistir en su representación.\nArtículo 12. Son facultades del Consejo Estatal:\nI. Elaborar el Programa Estatal;\nII. Determinar la estructura operativa y administrativa necesaria para su funcionamiento;\nIII. Sesionar de forma ordinaria o extraordinaria, de acuerdo con la programación anual establecida por el propio Consejo, en los tiempos fijados por la presente Ley;\nIV. Aprobar el análisis programático presupuestal, propuesto por las unidades administrativas responsables de la ejecución del Programa Estatal;\nV. Aprobar las reglas y convenios de coordinación de acciones que el Consejo Estatal celebre con el Gobierno Federal y los municipios en materia de fomento a la lectura y el libro;\nVI. Coordinar y llevar a cabo la celebración anual de festivales de lectura y ferias del libro en todo el Estado;\nVII. Autorizar la edición, publicación y difusión de los libros producidos con fondos del\nPrograma Estatal;\nVIII. Apoyar todo tipo de eventos y actividades que promuevan y estimulen la práctica de la lectura y la producción literaria;\nIX. Establecer la política y reglamentación editorial del Consejo;\nX. Autorizar el proyecto de presupuesto e informe de labores de los responsables de la administración del Programa Estatal;\nXI. Fomentar la apertura de bibliotecas y salas de lectura públicas en el Estado; y,\nXII. Todas las demás que se encuentren establecidas en otras legislaciones aplicables y el Reglamento respectivo.\nArtículo 13. El Consejo Estatal sesionará cada tres meses de forma ordinaria, y cuantas veces se requiera en sesiones de carácter extraordinario.\nEl Presidente del Consejo Estatal o el Secretario Técnico en su caso, emitirá la carácter ordinario y con cinco días de anticipación en asuntos urgentes que demanden la celebración de una sesión extraordinaria.\nLa convocatoria deberá enviarse a cada miembro del Consejo, acompañada del orden del día de la sesión correspondiente y de una carpeta que contenga los documentos o asuntos más relevantes que deban ser tratados, y en su caso aprobados por el Consejo\nEstatal.\nArtículo 14. Las decisiones del Consejo Estatal se tomarán por acuerdo de la mayoría de sus integrantes, y en caso de empate, su Presidente contará con voto de calidad. Habrá quórum legal con la mitad más uno de los integrantes del Consejo Estatal.\nEl Secretario Técnico del Consejo Estatal deberá verificar el quórum legal y lo asentará en el acta de la sesión respectiva. En los casos en los que no se cuente con el quórum legal requerido, el Secretario Técnico igualmente lo asentará en el acta respectiva y lo notificará al Presidente del Consejo Estatal para que emita nueva convocatoria.\nCAPÍTULO V\nDE LOS CONSEJOS MUNICIPALES DE FOMENTO A LA\nLECTURA Y EL LIBRO\nArtículo 15. En cada municipio del Estado podrán crearse los Consejos Municipales de Fomento a la Lectura y el Libro, como los órganos responsables de dar seguimiento en el ámbito de su competencia y jurisdicción respectivas a las políticas, programas y acciones que promuevan en el Estado el fomento a la lectura y la producción, edición, distribución y difusión de cualquier obra literaria que contribuya a elevar el nivel cultural de la población, Consejo Estatal.\nArtículo 16. Los Consejos Municipales se podrán integrar en cada municipio por:\nI. El Presidente Municipal, quien lo presidirá;\nII. El Secretario del Ayuntamiento como Secretario Técnico del Consejo;\nIII. El Síndico Procurador;\nIV. El Regidor de la comisión permanente de Educación, Cultura y Asuntos Indígenas del Ayuntamiento;\nV. El Director del Instituto Municipal del Arte y Cultura;\nVI. Un representante del sector social, a invitación del Presidente.\nLos cargos de los Consejos Municipales serán honoríficos, y podrán nombrar suplentes para asistir en su representación.\nArtículo 17. Los Consejos Municipales podrán:\nI. Elaborar el Programa Municipal, de acuerdo con las políticas, objetivos, acciones y metas, establecidos en el Programa Estatal;\nII. Determinar la estructura operativa y administrativa necesaria para su funcionamiento, de acuerdo con las posibilidades financieras del Municipio;\nIII. Sesionar de forma ordinaria o extraordinaria, de acuerdo con la programación anual establecida por el propio Consejo Municipal para el Fomento a la lectura y el libro, en los tiempos consignados en el presente Capítulo;\nIV. Aprobar el análisis programático presupuestal, propuesto por las unidades administrativas responsables de la ejecución del Programa Municipal;\nV. Aprobar las reglas, acuerdos y convenios de coordinación de acciones que los\nConsejos Municipales celebren con los gobiernos Federal, Estatal y de otros municipios, así lectura y el libro;\nVI. Coordinar la celebración de festivales de lectura y actividades de impulso, promoción y difusión del libro en el Municipio;\nVII. Enviar al Consejo Estatal para aprobación correspondiente, la edición, publicación\nMunicipal;\nVIII. Apoyar todo tipo de eventos y actividades organizadas por el Consejo Estatal o lectura, y la producción literaria en el Municipio;\nIX. En el ámbito de su competencia, promover las políticas y reglamentación editorial que emita el Consejo Estatal;\nX. Autorizar el proyecto de presupuesto e informe de labores de los responsables de la administración del Programa Municipal;\nXI. Promover la apertura de bibliotecas y salas de lectura de carácter municipal; y,\nXII. Las demás que se encuentren establecidas en otras legislaciones aplicables y en el Reglamento respectivo, así como aquellas que sean determinadas en calidad de facultades u obligaciones por el Consejo Estatal.\nArtículo 18. Los Consejos Municipales sesionarán por lo menos cada tres meses de forma ordinaria y cuantas veces se requiera de modo extraordinario.\nPara los fines de la emisión y términos de la convocatoria, integración del quórum legal, elaboración del orden del día y desarrollo de las sesiones de éstos Consejos, se aplicarán las mismas disposiciones que para el Consejo Estatal.\nArtículo 19. Las decisiones de los Consejos Municipales podrán tomarse por acuerdo de la mayoría de sus integrantes, y en caso de empate, su Presidente contará con voto de calidad.\nCAPÍTULO VI\nDE LOS PROGRAMAS ESTATAL Y MUNICIPALES DE FOMENTO A LA LECTURA Y EL\nLIBRO\nArtículo 20. Para el cumplimiento de sus funciones y demás disposiciones contenidas en la presente Ley, el Consejo Estatal y los Consejos Municipales elaborarán y aprobarán en sesión ordinaria, en el ámbito de su competencia y jurisdicción respectiva, los programas estatal y municipal correspondientes, los cuales deberán conformarse por lo menos de las siguientes partes:\nI. Introducción;\nII. Diagnóstico estatal y municipal de la lectura y la producción de libros;\nIII. Misión;\nIV. Visión;\nV. Políticas del Programa;\nVI. Objetivos del fomento a la lectura y el libro;\nVII. Estrategias para el desarrollo de la lectura y la producción literaria;\nVIII. Metas y acciones para el fomento a la lectura y el libro. Esto exigirá la participación del Ejecutivo del Estado, los municipios y los sectores público, social y privado en el diseño y realización de las actividades siguientes:\na) Elaborar paquetes didácticos para la formación de lectores;\nb) Realizar campañas de difusión y concientización de la población sobre la importancia de la lectura y la producción de libros;\nc) Establecer incentivos y premios sobre acciones relacionadas con el fomento, promoción de la lectura y la producción literaria;\nd) Organizar talleres, diplomados y cursos de capacitación para promotores de lectura;\ne) Crear talleres literarios y salas de lectura;\nf) Realizar actividades de fomento y difusión de la lectura en medios masivos de comunicación social;\ng) Buscar financiamiento para la compra de libros, materiales de lectura y equipamiento de bibliotecas públicas;\nh) Llevar a cabo campañas de donación de libros, materiales de lectura a las salas de lectura, bibliotecas estatales, municipales y demás instituciones que promuevan el fomento de la lectura y la producción literaria;\ni) Promover la participación de la sociedad y de las instituciones públicas de manera a la lectura y el libro entre la población;\nj) Impulsar y promover la creación de puntos de lectura, en las colonias y fraccionamientos en donde existan comités de vecinos.\nInciso Adicionado\nFracción Reformada\nIX. Integrar y administrar el fondo económico estatal y municipal, en su caso, para el financiamiento de las acciones de fomento a la lectura y el libro;\nX. Integrar las unidades administrativas y técnicas necesarias para la operación de los programas Estatal y Municipales, en correspondencia con lo que se establezca en el\nReglamento respectivo;\nXI. Programar y presupuestar los recursos para la operación de acciones de los programas Estatal y Municipales;\nXII. Establecer mecanismos de vinculación y coordinación interinstitucional de los programas Estatal y Municipales;\nXIII. Establecer mecanismos de evaluación y reprogramación de acciones de los programas Estatal y Municipales; y,\nXIV. Todas aquellas que se relacionen con las establecidas en la Ley de Planeación del Estado de Baja California.\nArtículo Reformado\nCAPÍTULO VII\nDE LA DISPONIBILIDAD Y ACCESO EQUITATIVO AL LIBRO\nArtículo 21.- En todo libro editado en el Estado, deberán constar los siguientes datos: título de la obra, nombre del autor, editor, número de la edición, lugar y fecha de la impresión, nombre y domicilio del editor en su caso; ISBN y código de barras. El libro que no reúna estas características no gozará de los beneficios fiscales y de otro tipo que otorguen las disposiciones jurídicas en la materia.\nArtículo 22.- Toda persona física o moral que edite o importe libros estará obligada a fijar un precio de venta al público para los libros que edite o importe. El editor o importador fijará libremente el precio de venta al público, que regirá como precio único.\nArtículo 23.- Los vendedores de libros al menudeo deben aplicar el precio único de venta al público sin ninguna variación, excepto en lo establecido en el artículo 24 y 25 de la presente Ley.\nArtículo 24.- El precio único establecido en el artículo 22 de la presente Ley, no se aplica a las compras que para sus propios fines, excluyendo la reventa, hagan el Estado, las bibliotecas que ofrezcan atención al público o préstamo, los establecimientos de enseñanza y de formación profesional o de investigación.\nArtículo 25.- Los vendedores de libros podrán aplicar precios inferiores al precio de venta al público mencionado en el artículo 22 de la presente Ley, cuando se trate de libros editados o importados con más de dieciocho meses de anterioridad, así como los libros antiguos, los usados, los descatalogados, los agotados y los artesanales.\nARTÍCULOS TRANSITORIOS\nPRIMERO.- La presente Ley entrará en vigor al día siguiente de su publicación en el\nPeriódico Oficial del Estado de Baja California.\nSEGUNDO.- Se crea el Consejo Estatal de Fomento a la Lectura y el Libro del Estado de Baja California y contará con un plazo de noventa días para su integración y funcionamiento a partir de la entrada en vigencia de la presente Ley, y a los setenta días de integrado éste, deberá expedir su Reglamento.\nTERCERO.- Para el cumplimiento de los objetivos de esta Ley, los Consejos\nMunicipales de Fomento a la Lectura y el Libro, podrán ser integrados para su funcionamiento en un plazo de noventa días, a partir de la entrada en vigor de la presente\nLey.\nCUARTO.- Los programas Estatal y Municipales de Fomento a la Lectura y el Libro deberán elaborarse en un término de noventa días posteriores a la integración y funcionamiento de los consejos a que se refieren los artículos tercero y cuarto transitorios de esta Ley.\nDADO en el Salón de Sesiones “Lic. Benito Juárez García” del H. Poder Legislativo del Estado de Baja California, en la Ciudad de Mexicali, B.C., a los dieciocho días del mes de septiembre del año dos mil doce.\nDIP. ALFONSO GARZÓN ZATARAIN\nPRESIDENTE\n(RÚBRICA)\nDIP. FAUSTO ZÁRATE ZEPEDA\nSECRETARIO\n(RÚBRICA)\nDE CONFORMIDAD CON LO DISPUESTO POR LA FRACCIÓN I DEL ARTÍCULO 49\nMEXICALI, BAJA CALIFORNIA, A LOS VEINTISIETE DÍAS DEL MES DE\nSEPTIEMBRE DEL AÑO DOS MIL DOCE.\nJOSÉ GUADALUPE OSUNA MILLÁN\nGOBERNADOR DEL ESTADO\n(RÚBRICA)\nFRANCISCO ANTONIO GARCÍA BURGOS\nSECRETARIO GENERAL DE GOBIERNO\n(RÚBRICA)\nARTÍCULO 8.- Fue reformado por Decreto No. 189, publicado en el Periódico Oficial\nLegislatura, siendo Gobernador Constitucional el C. Francisco Arturo Vega de Lamadrid\n2013-2019;\nARTÍCULO 20.- Fue reformado por Decreto No. 400, publicado en el Periódico Oficial\nLegislatura, siendo Gobernadora Constitucional la C. Marina del Pilar Ávila Olmeda 20212027;\nARTÍCULO ÚNICO TRANSITORIO DEL DECRETO No. 189, POR EL QUE SE\nREFORMA EL ARTÍCULO 8, PUBLICADO EN EL PERIÓDICO OFICIAL No. 10, SECCIÓN\nLEGISLATURA, SIENDO GOBERNADOR CONSTITUCIONAL EL C. FRANCISCO\nARTURO VEGA DE LAMADRID 2013-2019.\nARTÍCULO TRANSITORIO\nÚNICO.- La presente reforma entrará en vigor al día siguiente de su publicación en el\nPeriódico Oficial del Estado de Baja California.\nDADO en el Salón de Sesiones “Lic. Benito Juárez García” del H. Poder Legislativo del Estado de Baja California, en la Ciudad de Mexicali, B.C., a los veinticinco días del mes de enero del año dos mil dieciocho.\nDIP. MTRO. RAÚL CASTAÑEDA POMPOSO\nPRESIDENTE\n(RÚBRICA)\nDIP. ROCÍO LÓPEZ GOROSAVE\nSECRETARIA\n(RÚBRICA)\nDE CONFORMIDAD CON LO DISPUESTO POR LA FRACCIÓN I DEL ARTÍCULO 49\nMEXICALI, BAJA CALIFORNIA, A LOS DOS DÍAS DEL MES DE MARZO DEL AÑO DOS\nMIL DIECIOCHO.\nFRANCISCO ARTURO VEGA DE LAMADRID\nGOBERNADOR DEL ESTADO\n(RÚBRICA)\nFRANCISCO RUEDA GÓMEZ\nSECRETARIO GENERAL DE GOBIERNO\n(RÚBRICA)\nARTÍCULO ÚNICO TRANSITORIO DEL DECRETO No. 400, POR EL QUE SE\nAPRUEBA LA ADICIÓN DEL INCISO j) A LA FRACCIÓN VIII DEL ARTÍCULO 20;\nÍNDICE, TOMO CXXXI, EXPEDIDO POR LA H. XXIV LEGISLATURA, SIENDO\nGOBERNADORA CONSTITUCIONAL LA C. MARINA DEL PILAR ÁVILA OLMEDA 2021-\n2027.\nTRANSITORIO\nÚNICO. La presente reforma entrará en vigor al día siguiente de su publicación en el\nPeriódico Oficial del Estado de Baja California.\nDADO en Sesión Ordinaria de la XXIV Legislatura en la Ciudad de Mexicali, B.C., a los veintinueve días del mes de febrero del año dos mil veinticuatro.\nDIP. ARACELI GERALDO NÚÑEZ\nPRESIDENTA\n(RÚBRICA)\nDIP. MANUEL GUERRERO LUNA\nSECRETARIO\n(RÚBRICA)\nDE CONFORMIDAD CON LO DISPUESTO POR LA FRACCIÓN I DEL ARTÍCULO 49\nCALIFORNIA, IMPRÍMASE Y PUBLÍQUESE.\nMEXICALI, BAJA CALIFORNIA, A LOS DOCE DÍAS DEL MES DE MARZO DEL AÑO\nDOS MIL VEINTICUATRO.\nMARINA DEL PILAR ÁVILA OLMEDA\nGOBERNADORA DEL ESTADO\nDE BAJA CALIFORNIA\n(RÚBRICA)\nALFREDO ÁLVAREZ CÁRDENAS\nSECRETARIO GENERAL DE GOBIERNO\nDEL ESTADO DE BAJA CALIFORNIA\n(RÚBRICA)",
  "ordenamiento": "REGLAMENTO",
  "jurisdiccion": "BAJA CALIFORNIA",
  "fuente_oficial": "Periódico Oficial",
  "FECHA PER OFIC": "2024/04/05",
  "ESTATUS": "VIGENTE",
  "TOMO": "TOMO_VI",
  "URL": "https://www.congresobc.gob.mx/Documentos/ProcesoParlamentario/Leyes/TOMO_VI/20240405_LEYFOMLECTURA.PDF",
  "es_escaneado": false,
  "tiene_tablas": false,
  "materia": [
    "social",
    "salud",
    "educación",
    "cultura"
  ]
}