{
  "titulo": "Ley ORGÁNICA DE LA DEFENSORÍA PÚBLICA DEL ESTADO DE BAJA CALIFORNIA",
  "Contenido": ".\nActualización Legislativa.\nÚltima Reforma P.O. No. 57, Sección I, 22-Nov-2024\nLEY ORGÁNICA DE LA DEFENSORÍA PÚBLICA DEL\nESTADO DE BAJA CALIFORNIA\nPublicado en el Periódico Oficial No. 24, de fecha 22 de mayo de 2009, Tomo CXVI, Sección I\nCAPÍTULO PRIMERO\nDISPOSICIONES GENERALES\nARTÍCULO 1.- La presente Ley tiene por objeto regular la organización y funcionamiento de la Defensoría.\nARTÍCULO 2.- La Defensoría es una Institución que tiene como fin garantizar a las personas el acceso a la defensa jurídica, patrocinio y asesoría gratuita, en los términos que señala la Constitución Federal, la Constitución Local, Tratados Internacionales ratificados por el Estado Mexicano y las demás leyes aplicables, para una adecuada defensa de sus derechos fundamentales, a través de los siguientes servicios:\nI.- Defensa técnica en materia penal en los supuestos y condiciones que dispongan las leyes;\nII.- Defensa técnica a los adolescentes acusados de conductas tipificadas como delitos y asesoría a quien ejerza la patria potestad o tutores, conforme a la Ley de la materia;\nIII.- Patrocinio en materia familiar y civil a las personas que no cuenten con los recursos económicos necesarios para contratar o continuar con los servicios de una persona abogada particular;\nFracción Reformada\nIV.- Orientación en materia jurídica a las personas que lo soliciten;\nV.- Defensa jurídica, al personal de los cuerpos de seguridad en el Estado, cuando no cuenten con una persona defensora, en los términos de la Ley aplicable;\nFracción Reformada\nVI.- Proporcionar asesoría y representación legal, a las personas sentenciadas ante los Tribunales en materia penal del orden común, así como en el Sistema Integral de Justicia y demás normatividad aplicable;\nFracción Adicionada\nVII.- Defensa técnica en materia laboral, competencia de los Juzgados Laborales de\nBaja California, a las personas trabajadoras o sus beneficiarias en términos de las leyes y demás normatividad aplicable;\nFracción Adicionada\nLey Orgánica de la Defensoría Pública del Estado de Baja California. Página 1\n.\nActualización Legislativa.\nÚltima Reforma P.O. No. 57, Sección I, 22-Nov-2024\nVIII.- Defensa técnica a las personas servidoras públicas del Poder Ejecutivo del\nEstado y a las personas presuntas responsables en materia de responsabilidad administrativa; y,\nFracción Adicionada\nIX.- Los demás que otros ordenamientos señalen.\nFracción Recorrida\nArtículo Reformado\nARTÍCULO 3.- Para efectos de esta Ley se entenderá por:\nI.- Defensoría: A la Defensoría Pública del Estado de Baja California.\nII.- Persona Defensora Pública: A la Persona que presta el servicio de defensa pública en términos de esta ley.\nFracción Reformada\nIII.- Persona Titular de la Dirección: A la persona Titular de la Defensoría Pública.\nFracción Reformada\nIV.- Ley: A la Ley Orgánica de la Defensoría Pública del Estado de Baja California.\nV.- Reglamento: Al Reglamento de esta Ley.\nVI.- Consejería: A la Consejería Jurídica.\nFracción Reformada\nVII.- Persona Titular de la Consejería: A la Persona Titular de la Consejería Jurídica.\nFracción Reformada\nVIII.- Persona Titular de la Subdirección: A la Persona Titular de la Subdirección de la Defensoría.\nFracción Reformada\nArtículo Reformado\nARTÍCULO 4.- La Defensoría dependerá de la Consejería, la que coordinará y supervisará su funcionamiento, de acuerdo con las disposiciones de esta Ley y demás ordenamientos aplicables.\nArtículo Reformado\nCAPÍTULO SEGUNDO\nDE LA ESTRUCTURA ORGÁNICA\nARTÍCULO 5.- La Defensoría, para el cumplimiento de sus atribuciones estará integrada por:\nI.- La Persona Titular de la Dirección;\nFracción Reformada\nLey Orgánica de la Defensoría Pública del Estado de Baja California. Página 2\n.\nActualización Legislativa.\nÚltima Reforma P.O. No. 57, Sección I, 22-Nov-2024\nII.- La Persona Titular de la Subdirección;\nFracción Reformada\nIII.- Las Personas Titulares de las Coordinaciones;\nFracción Reformada\nIV.- Las Personas Defensoras Públicas;\nFracción Reformada\nV.- Las Personas Auxiliares Jurídicas; y,\nFracción Adicionada, Recorriéndose la subsecuente\nFracción Reformada\nVI.- El demás personal que determine el Reglamento.\nPara efectos laborales, las personas servidoras públicas que se señalan en las fracciones I, II, III, IV y V de este artículo serán consideradas personas trabajadoras de confianza.\nPárrafo Reformado\nArtículo Reformado\nARTÍCULO 6.- Para asumir la titularidad de la Dirección se requiere:\nPárrafo Reformado\nI.- Tener la ciudadanía mexicana y estar en pleno goce de sus derechos civiles;\nFracción Reformada\nII.- Poseer el día del nombramiento, con antigüedad mínima de diez años, título profesional de Licenciatura en Derecho; expedido por la autoridad o institución legalmente facultada para ello, debidamente registrado y por lo menos diez años de ejercicio profesional;\nFracción Reformada\nIII.- Ser una persona de notoria buena conducta y no estar sujeta o vinculada a proceso penal, ni haber sido condenada por sentencia ejecutoriada como responsable de delito doloso;\nFracción Reformada\nIV.- No estar suspendida, ni haber sido destituida o inhabilitada por resolución firme como persona servidora pública, en los términos de las normas aplicables;\nFracción Reformada\nV.- Haber residido en el Estado durante los cinco años anteriores al día de la designación;\nVI.- No haber ocupado el cargo de titular en una Secretaría o cargo de elección popular, durante dos años previos al día de la designación;\nVII.- Presentar un programa integral de trabajo para la Defensoría; y\nLey Orgánica de la Defensoría Pública del Estado de Baja California. Página 3\n.\nActualización Legislativa.\nÚltima Reforma P.O. No. 57, Sección I, 22-Nov-2024\nVIII.- Aprobar examen de salud y toxicológico de una Institución Pública de Salud.\nArtículo Reformado\nARTÍCULO 7.- La persona titular de la dirección tendrá las siguientes facultades:\nPárrafo Reformado\nI.- Planear, organizar, dirigir, coordinar, controlar, supervisar y evaluar los servicios de defensa, patrocinio y asesoría jurídica que se establecen en esta Ley;\nII.- Dictar acuerdos, circulares, manuales de organización y procedimientos y en general las medidas necesarias, para mejorar los servicios que ofrece la Defensoría;\nIII.- Dirigir y coordinar la óptima utilización de los recursos humanos, financieros y materiales asignados a la Defensoría, para el cumplimiento de sus objetivos;\nIV.- Autorizar las licencias que solicite el personal de la Defensoría, con o sin goce de sueldo, en los términos de las normas aplicables;\nV.- Proponer a su superior jerárquico sistemas de formación, capacitación, actualización y especialización profesional, para la prestación del servicio;\nVI.- Fijar y modificar la adscripción de las personas defensoras públicas y demás personal a su cargo, conforme a esta Ley, el Reglamento y las demás disposiciones normativas aplicables;\nFracción Reformada\nVII.- Vigilar que en la aplicación de la presente Ley sean estrictamente respetados los derechos fundamentales de sus defendidos y patrocinados;\nVIII.- Ejecutar las sanciones administrativas impuestas por el órgano competente, a las personas servidoras públicas de la Defensoría;\nFracción Reformada\nIX.- Hacer del conocimiento a las autoridades competentes en su caso, las violaciones a los derechos humanos que se detecten durante la defensa, patrocinio o asesoría jurídica prestada por la Defensoría;\nX.- Calificar los casos en que procedan las excusas de las personas defensoras públicas, y la suspensión del servicio;\nFracción Reformada\nXI.- Implementar un sistema de control y registro de los asuntos atendidos por la\nDefensoría;\nXII.- Proponer a la o él superior jerárquico proyecto de iniciativa de reformas a las leyes, así como a los reglamentos que considere apropiadas para el mejor desarrollo de los trabajos de la Defensoría; programas y estrategias para la difusión de los servicios que presta la Defensoría a la comunidad; así como la creación de plazas de las personas\nLey Orgánica de la Defensoría Pública del Estado de Baja California. Página 4\n.\nActualización Legislativa.\nÚltima Reforma P.O. No. 57, Sección I, 22-Nov-2024 defensoras públicas y auxiliares jurídicas que sean necesarias para un mejor servicio público;\nFracción Reformada\nXIII.- Establecer mecanismos de coordinación con instituciones públicas o privadas para la atención de las personas de escasos recursos económicos, que requieran de orientación psicológica;\nXIV.- Promover la concertación de convenios con instituciones de educación superior, colegios o asociaciones de abogacía para su colaboración gratuita, en la atención de casos encomendados por la Defensoría;\nFracción Reformada\nXV.- Promover la celebración de convenios con instituciones de educación superior para la prestación de servicio social de estudiantes, en las diversas áreas de la Defensoría, en los términos y condiciones que establezca el Reglamento;\nXVI.- Asumir labores de persona defensora pública en asuntos concretos; y,\nFracción Reformada\nXVII.- Las demás que el Reglamento y otras disposiciones le señalen.\nArtículo Reformado\nARTÍCULO 8.- La persona titular de la dirección podrá delegar a la o el titular de la subdirección las facultades establecidas en el artículo anterior con excepción de las contenidas en las fracciones I, II, VI, X, XII y XVII.\nArtículo Reformado\nARTÍCULO 9.- Las licencias que solicite la persona titular de la dirección, con o sin goce de sueldo, deberán ser autorizadas en los términos del Reglamento de la Consejería y las disposiciones normativas aplicables.\nArtículo Reformado\nARTÍCULO 10.- La persona titular de la dirección será suplida en sus ausencias por la o el titular de la subdirección.\nArtículo Reformado\nARTÍCULO 11.- Para ser titular de la subdirección se requiere cumplir los requisitos establecidos en el artículo 6 de esta Ley, con excepción de la fracción VII.\nArtículo Reformado\nARTÍCULO 12.- La persona titular de la subdirección, además de las que le sean delegadas por la o él titular de la dirección, tendrá las siguientes facultades:\nPárrafo Reformado\nI.- Proponer a la persona titular de la dirección acuerdos, circulares, manuales de organización y procedimientos y en general las medidas necesarias, para mejorar los servicios que ofrece la Defensoría;\nLey Orgánica de la Defensoría Pública del Estado de Baja California. Página 5\n.\nActualización Legislativa.\nÚltima Reforma P.O. No. 57, Sección I, 22-Nov-2024\nFracción Reformada\nII.- Sugerir a la persona titular de la dirección acciones para lograr la óptima utilización de los recursos humanos, financieros y materiales asignados a la Defensoría;\nFracción Reformada\nIII.- Asumir labores de persona defensora pública en asuntos concretos que le instruya la persona titular de la dirección;\nFracción Reformada\nIV.- Servir de enlace con las personas titulares de las coordinaciones, defensoras públicas y empleadas administrativas;\nFracción Reformada\nV.- Vigilar el cumplimiento de los criterios a seguir en el funcionamiento de la\nDefensoría;\nVI.- Solicitar informes a las personas titulares de las coordinaciones respecto de asuntos especiales planteados por la persona titular de la dirección;\nFracción Reformada\nVII.- Realizar por instrucciones de la persona titular de la dirección, visitas de supervisión a las distintas oficinas de la Defensoría, informando el resultado de las mismas;\nFracción Reformada\nVIII.- Recibir las quejas sobre el funcionamiento de las personas titulares de las coordinaciones, informando a la persona titular de la dirección; y,\nFracción Reformada\nIX.- Las que determine el reglamento.\nArtículo Reformado\nARTÍCULO 13.- Para asumir la titularidad de una Coordinación deberán cumplirse los requisitos establecidos en el artículo 17 de esta Ley, con excepción de la fracción III tratándose de la Coordinación Administrativa, donde se deberá contar con título de\nLicenciatura en Contabilidad, Administración de Empresas o carrera afín.\nArtículo Reformado\nARTÍCULO 14.- Las personas titulares de las coordinaciones tendrán las funciones que establezca el Reglamento.\nArtículo Reformado\nARTÍCULO 15.- El personal de la Defensoría será designado y removido de normativas aplicables.\nArtículo Reformado\nLey Orgánica de la Defensoría Pública del Estado de Baja California. Página 6\n.\nActualización Legislativa.\nÚltima Reforma P.O. No. 57, Sección I, 22-Nov-2024\nARTÍCULO 15 BIS.- La Defensoría asignará a las personas defensoras públicas, para la atención de los servicios jurídicos que presta, de conformidad a lo dispuesto en el\nReglamento de esta Ley.\nArtículo Adicionado\nARTÍCULO 16.- El personal de la Defensoría será suplido conforme lo determine la o él superior jerárquico del área correspondiente.\nArtículo Reformado\nCAPÍTULO TERCERO\nDE LAS PERSONAS DEFENSORAS PÚBLICAS\nDenominación del Capítulo Modificada\nARTÍCULO 17.- Para ser Persona Defensora Pública se requiere:\nPárrafo Reformado\nI.- Tener la ciudadanía mexicana y estar en pleno goce de sus derechos civiles;\nFracción Reformada\nII.- Contar con una experiencia no menor de tres años en el ejercicio profesional; al momento de su nombramiento;\nIII.- Contar con Licenciatura en Derecho, con título legalmente expedido y registrado ante la autoridad competente, y con la correspondiente cédula profesional;\nFracción Reformada\nIV.- No ser una persona sujeta o vinculada a proceso penal; ni haber sido condenada por sentencia ejecutoriada como responsable de delito doloso;\nFracción Reformada\nV.- No estar suspendida ni haber sido destituida o inhabilitada por resolución firme como persona servidora pública, en los términos de las normas aplicables;\nFracción Reformada\nVI.- Aprobar los exámenes de ingreso y oposición correspondientes;\nVII.- Aprobar examen de salud y toxicológico de una Institución Pública de Salud.\nArtículo Reformado\nARTÍCULO 18.- El nombramiento de las personas defensoras públicas establecerá su área de especialización.\nArtículo Reformado\nARTÍCULO 19.- La Defensoría contará con personas defensoras públicas en:\nPárrafo Reformado\nCiviles, Familiares, Laborales y Tribunal de Justicia Electoral;\nFracción Reformada\nLey Orgánica de la Defensoría Pública del Estado de Baja California. Página 7\n.\nActualización Legislativa.\nÚltima Reforma P.O. No. 57, Sección I, 22-Nov-2024\nII.- La Fiscalía General del Estado de Baja California; y,\nFracción Reformada\nIII.- Los Centros Penitenciarios del Estado y Centros de internamiento para adolescentes del Estado.\nFracción Reformada\nLa Defensoría podrá contar con personas defensoras públicas en otros órganos, de acuerdo a su disponibilidad presupuestal y cuando se justifique la necesidad del servicio.\nFracción Reformada\nLa adscripción de las personas defensoras públicas se fijará en los términos del\nReglamento.\nPárrafo Reformado\nArtículo Reformado\nARTÍCULO 20.- Son obligaciones de las personas defensoras públicas, atendiendo a su área de especialización:\nPárrafo Reformado\nI.- Defender técnicamente en materia penal, a las personas en los supuestos y condiciones que dispongan las leyes;\nII.- Defender técnicamente a los adolescentes acusados de conductas tipificadas como delitos y/o a sus representantes legales, conforme a la Ley de la materia;\nIII.- Otorgar asesoría y representación legal, a las personas sentenciadas ante los\nTribunales en materia penal del orden común, así como en el Sistema Integral de Justicia para adolescentes, de conformidad con lo establecido por la Ley Nacional de Ejecución\nPenal y demás normatividad aplicable;\nFracción Adicionada\nIV.- Defender técnicamente a las personas trabajadoras o sus beneficiarias, en asuntos competencia de los Juzgados Laborales de Baja California, en términos de las leyes y demás normatividad aplicable;\nFracción Adicionada\nResponsabilidades Administrativas del Estado de Baja California;\nFracción Adicionada\nVI- Asumir el patrocinio de los asuntos del orden civil y familiar que les sean asignados;\nFracción Reformada\nVII.- Proponer y promover la producción de todas las pruebas necesarias, así como realizar todas las gestiones legales inherentes a su encomienda;\nLey Orgánica de la Defensoría Pública del Estado de Baja California. Página 8\n.\nActualización Legislativa.\nÚltima Reforma P.O. No. 57, Sección I, 22-Nov-2024\nVIII.- Tramitar los recursos correspondientes en contra de resoluciones dictadas en materia penal, civil, familiar, laboral, administrativa y de justicia para adolescentes, expresando oportunamente los agravios que procedan;\nFracción Reformada\nIX.- Solicitar la inmediata comunicación con la persona detenida a la persona titular del Juzgado competente, ministerio público, juzgados calificadores o comandancias de las direcciones de seguridad pública municipal, cuando sea requerido para asistir a una persona que se encuentra detenida por la posible comisión de un delito;\nFracción Reformada\nX.- Visitar al menos una vez por semana, a las personas a quienes representa en los procesos penales en los centros de detención donde se encuentren, con el fin de entrevistarlas e informarles del estado de su asunto, así como también para auxiliarlas en el trámite de las quejas administrativas que tuvieren;\nFracción Reformada\nXI.- Informar oportunamente a quienes patrocinen sobre la marcha de sus asuntos;\nFracción Reformada\nXII.- Conceder audiencias a quienes patrocinen y/o defiendan;\nFracción Reformada\nXIII.- Hacer del conocimiento de la o él superior jerárquico, las quejas de las personas defendidas por malos tratos, torturas, golpes, amenazas y cualquiera otra violación a sus derechos humanos que provengan de una persona servidora pública;\nFracción Reformada\nXIV.- Representar con el debido profesionalismo, eficacia, honestidad, responsabilidad y buen trato a quienes representen;\nFracción Reformada\nXV.- Cumplir el Código de Ética para Servidores Públicos de la Defensoría;\nXVI.- Llevar un libro de registro de los asuntos a su cargo, así como un expediente de cada uno de los asuntos que patrocinen;\nXVII.- Proponer a la o él superior jerárquico las medidas que tiendan a mejorar la defensa de quienes defiendan o patrocinen;\nFracción Reformada\nXVIII.- Rendir mensualmente informe sobre las actuaciones efectuadas, requerido por la o él superior jerárquico;\nFracción Reformada\nLey Orgánica de la Defensoría Pública del Estado de Baja California. Página 9\n.\nActualización Legislativa.\nÚltima Reforma P.O. No. 57, Sección I, 22-Nov-2024\nXIX.- Solicitar la inmediata designación de una persona traductora o intérprete a cargo del Estado, cuando la persona patrocinada pertenezca a alguna comunidad indígena o tenga alguna discapacidad que le impida comprender sus derechos sin la ayuda de una persona traductora especializada;\nFracción Adicionada, recorriéndose las subsecuentes\nFracción Reformada\nXX.- Aquellas que sean necesarias para la prestación de los servicios de la\nDefensoría; y,\nXXI.- Las demás que señalen las leyes y reglamentos.\nArtículo Reformado\nARTÍCULO 21.- Las autoridades administrativas del Estado y Municipios tienen la obligación de prestar auxilio a las personas defensoras públicas, facilitando el ejercicio de sus funciones y proporcionando de manera expedita la información que requieran, así como las certificaciones, constancias y copias indispensables para el servicio que realicen.\nArtículo Reformado\nCAPÍTULO CUARTO\nDE LAS PROHIBICIONES\nARTÍCULO 22.- Son prohibiciones para la persona titular de la dirección, subdirección, las personas titulares de las coordinaciones, defensoras públicas y auxiliares jurídicas, las siguientes:\nPárrafo Reformado\nI.- Desempeñar otro empleo, cargo o comisión en alguno de los tres órdenes de gobierno, con excepción de actividades relacionadas con la docencia.\nII.- Aceptar o solicitar dadivas, cualquier tipo de servicios, beneficios o promesas para sí o para cualquier persona, por parte de quienes defiendan, patrocinen, asesoren, de la persona ofendida o de la contraparte como consecuencia de sus servicios profesionales.\nFracción Reformada\nIII.- Asistir durante la tramitación del asunto a algún convite que lo costee la persona ofendida o la contraparte.\nFracción Reformada\nIV.- Ejercer la abogacía, salvo que se trate de:\na) Causa propia.\nb) Su Cónyuge.\nInciso Reformado\nc) La persona con la que viva en Concubinato.\nLey Orgánica de la Defensoría Pública del Estado de Baja California. Página 10\n.\nActualización Legislativa.\nÚltima Reforma P.O. No. 57, Sección I, 22-Nov-2024\nInciso Reformado\nd) Sus hermanas o hermanos.\nInciso Reformado\ne) La persona adoptada y la persona adoptante.\nInciso Reformado\nf) Parientes consanguíneos en línea recta sin límite de grado.\nFracción Reformada\nV.- Instigar o sugerir a su defenso que incurra en actos ilegales dentro del proceso;\nVI.- Conocer de asuntos en los que en lo individual o bien su cónyuge o sus parientes consanguíneos en línea recta sin limitación de grado, o colaterales hasta el cuarto grado, tengan un interés personal directo o indirecto, así como en asuntos en los que mantengan relaciones de afecto o amistad con la parte contraria de quien solicite.\nFracción Reformada\nVII.- Ejercer como persona apoderada judicial, tutora, curadora o albacea, a menos que sean personas herederas o legatarias; tampoco podrán ser personas depositarias judiciales, síndicas, administradoras, interventoras en quiebra o concurso, ni personas corredoras, comisionistas o árbitras, ni ejercer las demás actividades incompatibles con sus funciones.\nFracción Reformada\nVIII.- Las demás que le señalen otros ordenamientos.\nArtículo Reformado\nCAPÍTULO QUINTO\nDE LAS EXCUSAS, ABSTENCIONES Y SUSPENSIÓN DEL SERVICIO\nARTÍCULO 23.- La persona titular de la dirección, de la subdirección, las personas titulares de las coordinaciones y las defensoras públicas deberán excusarse cuando:\nPárrafo Reformado\nI.- Tengan parentesco sin limitación de grado o relación de amistad con la persona víctima, ofendida o la contraparte.\nFracción Reformada\nII.- Hayan presentado por sí, o su cónyuge o parientes, querella o denuncia en contra de alguna de las partes o la persona imputada.\nFracción Reformada\nIII.- Tengan pendiente un juicio contra quien patrocinen, la persona imputada o sus representantes.\nFracción Reformada\nLey Orgánica de la Defensoría Pública del Estado de Baja California. Página 11\n.\nActualización Legislativa.\nÚltima Reforma P.O. No. 57, Sección I, 22-Nov-2024\nIV.- Sean personas deudoras, socias, arrendadoras dependientes de la persona víctima, ofendida o la contraparte.\nFracción Reformada\nV.- Sean o hayan sido personas tutoras, curadoras o administradoras de los bienes de la persona víctima, imputada o la contraparte; o sus personas herederas, legatarias, donatarias o fiadoras.\nFracción Reformada\nVI.- Sean cónyuge de la persona defensora o alguno de sus ascendientes o descendientes en primer grado; sean personas acreedoras, deudoras o fiadoras de la persona víctima, ofendida o la contraparte.\nFracción Reformada\nVII.- Hayan sido personas abogadas, procuradoras, peritas o que dieren testimonio de la persona víctima, ofendida o la contraparte.\nFracción Reformada\nVIII.- Se presenten reiteradas muestras de desconfianza de parte de la persona imputada o patrocinada, o reciba de su parte ofensas que afecten la objetividad en la defensa.\nFracción Reformada\nArtículo Reformado\nARTÍCULO 24.- Si existe un motivo para que la persona defensora pública se excuse y no lo hace, la persona titular de la dirección le aplicará la medida disciplinaria correspondiente y la sustituirá por otra en el conocimiento de la causa o expediente de que se trate, independientemente de la responsabilidad en que pudiera incurrir.\nArtículo Reformado\nARTÍCULO 25.- Se abstendrá de proporcionar el servicio de Defensoría en asuntos del orden civil y familiar, en los casos siguientes:\nPárrafo Reformado\nI.- Cuando por las condiciones socioeconómicas de quien solicita no requiera la prestación del servicio, conforme a lo dispuesto en el Reglamento.\nFracción Reformada\nII.- Cuando la finalidad de quien solicita sea obtener un lucro o beneficio económico, salvo en los casos de juicio de otorgamiento de pensiones alimenticias, o bien, cualquier juicio, jurisdicción voluntaria o interdicto, respecto de la titularidad de derechos o bienes que conformen el único patrimonio de quien solicite.\nFracción Reformada\nIII.- Cuando exista un abuso en la defensa o representación.\nLey Orgánica de la Defensoría Pública del Estado de Baja California. Página 12\n.\nActualización Legislativa.\nÚltima Reforma P.O. No. 57, Sección I, 22-Nov-2024\nIV.- Cuando quien solicite haya sido previamente contraparte de la Defensoría en el asunto en el que se solicite el servicio, a excepción de los asuntos de carácter penal.\nFracción Reformada\nArtículo Reformado\nARTÍCULO 26.- Cuando dos partes en un mismo conflicto soliciten el servicio de la\nDefensoría, ésta tratará de avenirlas, de no lograrse un acuerdo, se le prestará a la que lo haya solicitado en primer término, y se le recomendará a la otra, para que acuda a instituciones académicas, asociaciones o colegios de profesionistas.\nARTÍCULO 27.- Tratándose de asuntos civiles y familiares estos serán tramitados, cuando la persona que solicite el servicio, acuda directamente a las instalaciones de la\nDefensoría, salvo que se acredite su incapacidad física.\nArtículo Reformado\nARTÍCULO 28.- Para la prestación de los servicios de la Defensoría en materia civil o familiar, quienes soliciten deberán acreditar que se encuentran imposibilitados para pagar honorarios a un abogado particular, a través del estudio socioeconómico que practique la\nDefensoría en los términos del Reglamento.\nArtículo Reformado\nARTÍCULO 29.- La Defensoría podrá suspender en forma definitiva el servicio en los asuntos del orden civil y familiar, cuando:\nPárrafo Reformado\nI.- La persona usuaria manifieste en forma fehaciente que no tiene interés en que se le siga prestando el servicio de Defensoría.\nFracción Reformada\nII.- Quien solicite el servicio incurra en falsedad en los datos proporcionados.\nFracción Reformada\nIII.- La persona usuaria cometa actos de violencia, amenazas o injurias en contra de la persona defensora pública o del personal de la Defensoría, o se presente en aparente estado de ebriedad o bajo el influjo de alguna droga o enervante.\nFracción Reformada\nIV.- En el transcurso del procedimiento se acredite que la persona usuaria cuenta con los servicios de abogado particular para el patrocinio de su asunto.\nFracción Reformada\nV.- Cuando la persona patrocinada deje de asistir injustificadamente a la oficina de\nDefensoría que le esté realizando algún trámite, con la frecuencia que se ha requerido.\nFracción Reformada\nVI.- Cuando dejen de aportar los elementos base de su acción o las pruebas necesarias para su juicio o trámite.\nLey Orgánica de la Defensoría Pública del Estado de Baja California. Página 13\n.\nActualización Legislativa.\nÚltima Reforma P.O. No. 57, Sección I, 22-Nov-2024\nVII.- Cuando desaparezcan las causas socioeconómicas que dieron origen a la prestación del servicio.\nArtículo Reformado\nARTÍCULO 30.- En caso de que se presenten las situaciones descritas en las fracciones II a la VII del artículo anterior, la persona defensora pública lo hará del conocimiento de la o él superior jerárquico, quien levantará un acta circunstanciada donde se exprese la causa que haya generado la suspensión del servicio, dándole el uso de la voz a la persona patrocinada cuando esté presente. En dicha acta se deberá resolver sobre la suspensión del servicio, debiendo hacer del conocimiento de la persona patrocinada la resolución en ese momento, pudiendo la persona titular de la dirección revisar dicha resolución.\nPárrafo Reformado\nEn caso de la fracción I del citado artículo, la suspensión, será declarada de plano por el superior jerárquico, debiéndose observar, en lo conducente, los mismos requisitos señalados en el párrafo anterior.\nArtículo Reformado\nARTÍCULO 31.- La Defensoría podrá suspender el servicio en los asuntos del orden penal, administrativo y laboral cuando se acredite dentro del procedimiento que el usuario cuenta con defensa técnica particular.\nArtículo Reformado\nCAPÍTULO SEXTO\nDE LAS FIANZAS DE ASISTENCIA SOCIAL\nARTÍCULO 32.- La Defensoría podrá apoyar a las personas imputadas con el trámite para el otorgamiento de fianzas con los organismos no gubernamentales de asistencia social que proporcione dicho beneficio, con base en los convenios que previamente realice para tal fin.\nArtículo Reformado\nARTÍCULO 33.- Para que una persona imputada pueda beneficiarse con el otorgamiento de una fianza de asistencia social, deberá satisfacer los requisitos que señalen en los convenios celebrados con los organismos no gubernamentales.\nArtículo Reformado\nCAPÍTULO SÉPTIMO\nDE LAS SANCIONES ADMINISTRATIVAS\nARTÍCULO 34.- Para efectos de esta Ley son faltas administrativas en las que incurre la persona titular de la dirección, de la subdirección, las personas titulares de las coordinaciones, defensoras públicas o las auxiliares jurídicas, las siguientes:\nPárrafo Reformado\nLey Orgánica de la Defensoría Pública del Estado de Baja California. Página 14\n.\nActualización Legislativa.\nÚltima Reforma P.O. No. 57, Sección I, 22-Nov-2024\nI.- Negar, sin causa justificada, el patrocinio y defensa en los asuntos que por su cargo le correspondan.\nII.- Demorar sin razón justificable, las defensas o asuntos que se le hubieren encomendado.\nIII.- Solicitar o aceptar dádivas.\nIV.- Incurrir en negligencia en la presentación de pruebas que favorezcan a quienes defiendan o patrocinen, o no promover oportunamente los recursos legales que procedan.\nFracción Reformada\nV.- Ejecutar actos o incurrir en omisiones que tengan como consecuencia traspapelar expedientes, extraviar escritos o dificultar la práctica de diligencias procesales.\nVI.- Brindar asesoría a personas abogadas particulares que se hagan cargo de la defensa en materia penal y patrocinio jurídico en materias civil, familiar, laboral y administrativo, o recabar información para terceras personas que no tienen acceso a ella.\nFracción Reformada\nVII.- Faltar o llegar tarde, por un periodo de tres días consecutivos, o cinco días dentro de un término de treinta días sin motivo justificado al área de su adscripción; o no permanecer durante el tiempo de su jornada laboral en la oficina asignada para el despacho de sus asuntos.\nVIII.- Incurrir en alguna de las prohibiciones o dejar de cumplir cualquiera de las obligaciones o disposiciones contempladas en la Ley, el Reglamento o demás leyes aplicables.\nIX.- Incumplir con las obligaciones, que les impone la Ley de Responsabilidades\nAdministrativas del Estado de Baja California o encuadrar dentro de los supuestos de prohibiciones, que establece el mismo ordenamiento jurídico.\nFracción Reformada\nArtículo Reformado\nARTÍCULO 35.- Las demás personas servidoras públicas de la Defensoría, estarán sujetas a lo dispuesto por el ordenamiento jurídico que se señala en la fracción IX del artículo anterior.\nArtículo Reformado\nARTÍCULO 36.- Los procedimientos de responsabilidad administrativa de las personas servidoras públicas de la Defensoría, así como las autoridades competentes para aplicar las sanciones respectivas, serán los que establece la Ley de Responsabilidades\nAdministrativas del Estado de Baja California.\nArtículo Reformado\nCAPÍTULO OCTAVO\nDEL SERVICIO PROFESIONAL DE CARRERA\nLey Orgánica de la Defensoría Pública del Estado de Baja California. Página 15\n.\nActualización Legislativa.\nÚltima Reforma P.O. No. 57, Sección I, 22-Nov-2024\nARTÍCULO 37.- El ingreso y la promoción de las personas servidoras públicas de la\nDefensoría se hará mediante un Sistema Profesional de Carrera a que se refiere el presente\nCapítulo, el cual se regirá por los principios de profesionalismo, objetividad, independencia, antigüedad, calidad y eficiencia.\nArtículo Reformado\nARTÍCULO 38.- El Servicio Profesional de Carrera de la Defensoría garantizará la igualdad de oportunidades laborales, así como la estabilidad, permanencia, remuneración adecuada, capacitación y garantías de seguridad social para las personas defensoras públicas, en los términos que señalen las disposiciones normativas aplicables.\nArtículo Reformado\nARTÍCULO 39.- Los procedimientos para la selección, ingreso, formación, capacitación, actualización, especialización, ascenso, adscripción, rotación, reingreso, estímulos, reconocimientos y retiro de las personas defensoras públicas, serán regulados por las disposiciones normativas aplicables.\nArtículo Reformado\nCAPÍTULO NOVENO\nDE LA CAPACITACIÓN\nCapítulo Adicionado\nARTÍCULO 40.- Las defensoras y defensores públicos contarán con cursos de capacitación, que tengan relación con sus funciones y según lo permitan las necesidades del servicio.\nArtículo Adicionado\nARTÍCULO 41.- Los cursos de capacitaciones se desarrollarán bajo:\nI.- Programas académicos.\nII.- Cursos-Talleres de formación de competencias en defensa y representación legal.\nIII.- Seminarios de actualización.\nArtículo Adicionado\nARTÍCULOS TRANSITORIOS\nPRIMERO.- Inicio de Vigencia.- La presente ley entrará en vigor a las cero horas del\nArtículo Reformado\nSEGUNDO.- Hasta en tanto entre en vigor esta Ley, seguirá vigente la ley de la el Periódico Oficial del Estado.\nLey Orgánica de la Defensoría Pública del Estado de Baja California. Página 16\n.\nActualización Legislativa.\nÚltima Reforma P.O. No. 57, Sección I, 22-Nov-2024\nTERCERO.- A la entrada en vigor de esta Ley, todos los Defensores en funciones, salvo los que se adscriban al área penal para el nuevo sistema de justicia penal que se contiene en el Código al que alude el primer artículo transitorio de este Decreto, seguirán considerándose trabajadores de confianza de libre designación y remoción, en tanto se practiquen las evaluaciones que determine la Secretaría, para su ingreso al sistema profesional de carrera.\nPara estos efectos, la Secretaría deberá impartir cursos de capacitación en las materias objeto del cargo que desempeñen.\nLos Defensores adscritos al nuevo sistema de justicia penal que aprueben las evaluaciones que practique la Secretaría, tendrán calida de trabajadores de confianza adscritos al servicio profesional de carrera.\nDADO en el Salón de Sesiones “Lic. Benito Juárez García” del H. Poder Legislativo del Estado de Baja California, en la Ciudad de Mexicali, B.C., a los veintiséis días del mes de febrero del año dos mil nueve.\nDIP. ENRIQUE MÉNDEZ JUÁREZ\nPRESIDENT E\n(RUBRICA)\nDIP. GLORIA MARÍA LOZA GALVÁN\nSECRETARIA\n(RUBRICA)\nDE CONFORMIDAD CON LO DISPUESTO POR LA FRACCIÓN I DEL ARTÍCULO 49\nMEXICALI, BAJA CALIFORNIA, A LOS ONCE DÍAS DEL MES DE MAYO DEL AÑO\nDOS MIL NUEVE\nGOBERNADOR DEL ESTADO\nJOSE GUADALUPE OSUNA MILLÁN\n(RUBRICA)\nSECRETARIO GENERAL DE GOBIERNO\nJOSÉ FRANCISCO BLAKE MORA\n(RUBRICA)\nLey Orgánica de la Defensoría Pública del Estado de Baja California. Página 17\n.\nActualización Legislativa.\nÚltima Reforma P.O. No. 57, Sección I, 22-Nov-2024\nARTÍCULO PRIMERO.- Fue reformado por Decreto No. 348, publicado en el\nPeriódico Oficial No. 05, de fecha 22 de enero de 2010, Tomo CXVII, Sección II, expedido por la H. XIX Legislatura, siendo Gobernador Constitucional el C. José Guadalupe Osuna\nMillán 2007-2013; Fue reformado por Decreto No. 360, publicado en el Periódico Oficial No.\n18, de fecha 22 de abril de 2010, Tomo CXVII, Sección III, expedido por la H. XIX\nLegislatura, siendo Gobernador Constitucional el C. José Guadalupe Osuna Millán 20072013;\nARTÍCULO 2.- Fue reformado por Decreto No. 17, publicado en el Periódico Oficial\nNo. 57, Sección I, de fecha 22 de noviembre de 2024, Tomo CXXXI, publicado en el\nPeriódico Oficial No. 57, Sección I, de fecha 22 de noviembre de 2024, Tomo CXXXI, expedido por la H. Legislatura XXV, siendo Gobernadora Constitucional la C. Marina del\nPilar Ávila Olmeda 2021-2027;\nARTÍCULO 3.- Fue reformado por Decreto No. 17, publicado en el Periódico Oficial\nNo. 57, Sección I, de fecha 22 de noviembre de 2024, Tomo CXXXI, expedido por la H.\nLegislatura XXV, siendo Gobernadora Constitucional la C. Marina del Pilar Ávila Olmeda\n2021-2027;\nARTÍCULO 4.- Fue reformado por Decreto No. 17, publicado en el Periódico Oficial\nNo. 57, Sección I, de fecha 22 de noviembre de 2024, Tomo CXXXI, expedido por la H.\nLegislatura XXV, siendo Gobernadora Constitucional la C. Marina del Pilar Ávila Olmeda\n2021-2027;\nARTÍCULO 5.- Fue reformado por Decreto No. 246, publicado en el Periódico Oficial\nNo. 24, de fecha 22 de mayo de 2015, Sección I, Tomo CXXII, expedido por la H. XXI\nLegislatura, siendo Gobernador Constitucional el C. Francisco Arturo Vega de Lamadrid\n2013-2019; fue reformado por Decreto No. 17, publicado en el Periódico Oficial No. 57,\nSección I, de fecha 22 de noviembre de 2024, Tomo CXXXI, expedido por la H. Legislatura\nXXV, siendo Gobernadora Constitucional la C. Marina del Pilar Ávila Olmeda 2021-2027;\nARTÍCULO 6.- Fue reformado por Decreto No. 17, publicado en el Periódico Oficial\nLegislatura XXV, siendo Gobernadora Constitucional la C. Marina del Pilar Ávila Olmeda\n2021-2027;\nARTÍCULO 7.- Fue reformado por Decreto No. 17, publicado en el Periódico Oficial\nLegislatura XXV, siendo Gobernadora Constitucional la C. Marina del Pilar Ávila Olmeda\n2021-2027;\nARTÍCULO 8.- Fue reformado por Decreto No. 17, publicado en el Periódico Oficial\nLey Orgánica de la Defensoría Pública del Estado de Baja California. Página 18\n.\nActualización Legislativa.\nÚltima Reforma P.O. No. 57, Sección I, 22-Nov-2024\nLegislatura XXV, siendo Gobernadora Constitucional la C. Marina del Pilar Ávila Olmeda\n2021-2027;\nARTÍCULO 9.- Fue reformado por Decreto No. 17, publicado en el Periódico Oficial\nNo. 57, Sección I, de fecha 22 de noviembre de 2024, Tomo CXXXI, expedido por la H.\nLegislatura XXV, siendo Gobernadora Constitucional la C. Marina del Pilar Ávila Olmeda\n2021-2027;\nARTÍCULO 10.- Fue reformado por Decreto No. 17, publicado en el Periódico Oficial\nNo. 57, Sección I, de fecha 22 de noviembre de 2024, Tomo CXXXI, expedido por la H.\nLegislatura XXV, siendo Gobernadora Constitucional la C. Marina del Pilar Ávila Olmeda\n2021-2027;\nARTÍCULO 11.- Fue reformado por Decreto No. 17, publicado en el Periódico Oficial\nNo. 57, Sección I, de fecha 22 de noviembre de 2024, Tomo CXXXI, expedido por la H.\nLegislatura XXV, siendo Gobernadora Constitucional la C. Marina del Pilar Ávila Olmeda\n2021-2027;\nARTÍCULO 12.- Fue reformado por Decreto No. 17, publicado en el Periódico Oficial\nNo. 57, Sección I, de fecha 22 de noviembre de 2024, Tomo CXXXI, expedido por la H.\nLegislatura XXV, siendo Gobernadora Constitucional la C. Marina del Pilar Ávila Olmeda\n2021-2027;\nARTÍCULO 13.- Fue reformado por Decreto No. 17, publicado en el Periódico Oficial\nNo. 57, Sección I, de fecha 22 de noviembre de 2024, Tomo CXXXI, expedido por la H.\nLegislatura XXV, siendo Gobernadora Constitucional la C. Marina del Pilar Ávila Olmeda\n2021-2027;\nARTÍCULO 14.- Fue reformado por Decreto No. 17, publicado en el Periódico Oficial\nNo. 57, Sección I, de fecha 22 de noviembre de 2024, Tomo CXXXI, expedido por la H.\nLegislatura XXV, siendo Gobernadora Constitucional la C. Marina del Pilar Ávila Olmeda\n2021-2027;\nARTÍCULO 15.- Fue reformado por Decreto No. 17, publicado en el Periódico Oficial\nLegislatura XXV, siendo Gobernadora Constitucional la C. Marina del Pilar Ávila Olmeda\n2021-2027;\nARTÍCULO 15 BIS.- Fue adicionado por Decreto No. 17, publicado en el Periódico\nH. Legislatura XXV, siendo Gobernadora Constitucional la C. Marina del Pilar Ávila Olmeda\n2021-2027;\nLey Orgánica de la Defensoría Pública del Estado de Baja California. Página 19\n.\nActualización Legislativa.\nÚltima Reforma P.O. No. 57, Sección I, 22-Nov-2024\nARTÍCULO 16.- Fue reformado por Decreto No. 17, publicado en el Periódico Oficial\nNo. 57, Sección I, de fecha 22 de noviembre de 2024, Tomo CXXXI, expedido por la H.\nLegislatura XXV, siendo Gobernadora Constitucional la C. Marina del Pilar Ávila Olmeda\n2021-2027;\nFue modificada la denominación de este Capítulo Tercero por Decreto No. 17, publicado en el Periódico Oficial No. 57, Sección I, de fecha 22 de noviembre de 2024, Tomo CXXXI, expedido por la H. Legislatura XXV, siendo Gobernadora Constitucional la C. Marina del\nPilar Ávila Olmeda 2021-2027;\nCAPÍTULO TERCERO\nDE LAS PERSONAS DEFENSORAS PÚBLICAS\nARTÍCULO 17.- Fue reformado por Decreto No. 17, publicado en el Periódico Oficial\nNo. 57, Sección I, de fecha 22 de noviembre de 2024, Tomo CXXXI, expedido por la H.\nLegislatura XXV, siendo Gobernadora Constitucional la C. Marina del Pilar Ávila Olmeda\n2021-2027;\nARTÍCULO 18.- Fue reformado por Decreto No. 17, publicado en el Periódico Oficial\nNo. 57, Sección I, de fecha 22 de noviembre de 2024, Tomo CXXXI, expedido por la H.\nLegislatura XXV, siendo Gobernadora Constitucional la C. Marina del Pilar Ávila Olmeda\n2021-2027;\nARTÍCULO 19.- Fue reformado por Decreto No. 17, publicado en el Periódico Oficial\nNo. 57, Sección I, de fecha 22 de noviembre de 2024, Tomo CXXXI, expedido por la H.\nLegislatura XXV, siendo Gobernadora Constitucional la C. Marina del Pilar Ávila Olmeda\n2021-2027;\nARTÍCULO 20.- Fue reformado por Decreto No. 296, publicado en el Periódico Oficial\nNo. 7, de fecha 01 de febrero de 2019, Sección III, Tomo CXXVI, expedido por la H. XXII\nLegislatura, siendo Gobernador Constitucional el C. Francisco Arturo Vega de Lamadrid\n2013-2019; fue reformado por Decreto No. 17, publicado en el Periódico Oficial No. 57, XXV, siendo Gobernadora Constitucional la C. Marina del Pilar Ávila Olmeda 2021-2027;\nARTÍCULO 21.- Fue reformado por Decreto No. 17, publicado en el Periódico Oficial\nLegislatura XXV, siendo Gobernadora Constitucional la C. Marina del Pilar Ávila Olmeda\n2021-2027;\nARTÍCULO 22.- Fue reformado por Decreto No. 246, publicado en el Periódico Oficial\nLey Orgánica de la Defensoría Pública del Estado de Baja California. Página 20\n.\nActualización Legislativa.\nÚltima Reforma P.O. No. 57, Sección I, 22-Nov-2024\nLegislatura, siendo Gobernador Constitucional el C. Francisco Arturo Vega de Lamadrid\n2013-2019; fue reformado por Decreto No. 17, publicado en el Periódico Oficial No. 57,\nSección I, de fecha 22 de noviembre de 2024, Tomo CXXXI, expedido por la H. Legislatura\nXXV, siendo Gobernadora Constitucional la C. Marina del Pilar Ávila Olmeda 2021-2027;\nARTÍCULO 23.- Fue reformado por Decreto No. 17, publicado en el Periódico Oficial\nNo. 57, Sección I, de fecha 22 de noviembre de 2024, Tomo CXXXI, expedido por la H.\nLegislatura XXV, siendo Gobernadora Constitucional la C. Marina del Pilar Ávila Olmeda\n2021-2027;\nARTÍCULO 24.- Fue reformado por Decreto No. 17, publicado en el Periódico Oficial\nNo. 57, Sección I, de fecha 22 de noviembre de 2024, Tomo CXXXI, expedido por la H.\nLegislatura XXV, siendo Gobernadora Constitucional la C. Marina del Pilar Ávila Olmeda\n2021-2027;\nARTÍCULO 25.- Fue reformado por Decreto No. 17, publicado en el Periódico Oficial\nNo. 57, Sección I, de fecha 22 de noviembre de 2024, Tomo CXXXI, expedido por la H.\nLegislatura XXV, siendo Gobernadora Constitucional la C. Marina del Pilar Ávila Olmeda\n2021-2027;\nARTÍCULO 27.- Fue reformado por Decreto No. 17, publicado en el Periódico Oficial\nNo. 57, Sección I, de fecha 22 de noviembre de 2024, Tomo CXXXI, expedido por la H.\nLegislatura XXV, siendo Gobernadora Constitucional la C. Marina del Pilar Ávila Olmeda\n2021-2027;\nARTÍCULO 28.- Fue reformado por Decreto No. 17, publicado en el Periódico Oficial\nNo. 57, Sección I, de fecha 22 de noviembre de 2024, Tomo CXXXI, expedido por la H.\nLegislatura XXV, siendo Gobernadora Constitucional la C. Marina del Pilar Ávila Olmeda\n2021-2027;\nARTÍCULO 29.- Fue reformado por Decreto No. 17, publicado en el Periódico Oficial\nLegislatura XXV, siendo Gobernadora Constitucional la C. Marina del Pilar Ávila Olmeda\n2021-2027;\nARTÍCULO 30.- Fue reformado por Decreto No. 17, publicado en el Periódico Oficial\nLegislatura XXV, siendo Gobernadora Constitucional la C. Marina del Pilar Ávila Olmeda\n2021-2027;\nARTÍCULO 31.- Fue reformado por Decreto No. 17, publicado en el Periódico Oficial\nLey Orgánica de la Defensoría Pública del Estado de Baja California. Página 21\n.\nActualización Legislativa.\nÚltima Reforma P.O. No. 57, Sección I, 22-Nov-2024\nLegislatura XXV, siendo Gobernadora Constitucional la C. Marina del Pilar Ávila Olmeda\n2021-2027;\nARTÍCULO 32.- Fue reformado por Decreto No. 17, publicado en el Periódico Oficial\nNo. 57, Sección I, de fecha 22 de noviembre de 2024, Tomo CXXXI, expedido por la H.\nLegislatura XXV, siendo Gobernadora Constitucional la C. Marina del Pilar Ávila Olmeda\n2021-2027;\nARTÍCULO 33.- Fue reformado por Decreto No. 17, publicado en el Periódico Oficial\nNo. 57, Sección I, de fecha 22 de noviembre de 2024, Tomo CXXXI, expedido por la H.\nLegislatura XXV, siendo Gobernadora Constitucional la C. Marina del Pilar Ávila Olmeda\n2021-2027;\nARTÍCULO 34.- Fue reformado por Decreto No. 246, publicado en el Periódico Oficial\nNo. 24, de fecha 22 de mayo de 2015, Sección I, Tomo CXXII, expedido por la H. XXI\nLegislatura, siendo Gobernador Constitucional el C. Francisco Arturo Vega de Lamadrid\n2013-2019; fue reformado por Decreto No. 17, publicado en el Periódico Oficial No. 57,\nSección I, de fecha 22 de noviembre de 2024, Tomo CXXXI, expedido por la H. Legislatura\nXXV, siendo Gobernadora Constitucional la C. Marina del Pilar Ávila Olmeda 2021-2027;\nARTÍCULO 35.- Fue reformado por Decreto No. 17, publicado en el Periódico Oficial\nNo. 57, Sección I, de fecha 22 de noviembre de 2024, Tomo CXXXI, expedido por la H.\nLegislatura XXV, siendo Gobernadora Constitucional la C. Marina del Pilar Ávila Olmeda\n2021-2027;\nARTÍCULO 36.- Fue reformado por Decreto No. 17, publicado en el Periódico Oficial\nNo. 57, Sección I, de fecha 22 de noviembre de 2024, Tomo CXXXI, expedido por la H.\nLegislatura XXV, siendo Gobernadora Constitucional la C. Marina del Pilar Ávila Olmeda\n2021-2027;\nARTÍCULO 37.- Fue reformado por Decreto No. 17, publicado en el Periódico Oficial\nLegislatura XXV, siendo Gobernadora Constitucional la C. Marina del Pilar Ávila Olmeda\n2021-2027;\nARTÍCULO 38.- Fue reformado por Decreto No. 17, publicado en el Periódico Oficial\nLegislatura XXV, siendo Gobernadora Constitucional la C. Marina del Pilar Ávila Olmeda\n2021-2027;\nARTÍCULO 39.- Fue reformado por Decreto No. 17, publicado en el Periódico Oficial\nLey Orgánica de la Defensoría Pública del Estado de Baja California. Página 22\n.\nActualización Legislativa.\nÚltima Reforma P.O. No. 57, Sección I, 22-Nov-2024\nLegislatura XXV, siendo Gobernadora Constitucional la C. Marina del Pilar Ávila Olmeda\n2021-2027;\nFue adicionado este Capítulo Noveno por Decreto No. 412, publicado en el Periódico\nOficial No. 19, de fecha 12 de abril de 2024, Sección I, Tomo CXXXI, expedido por la H.\nXXIV Legislatura, siendo Gobernadora Constitucional la C. Marina del Pilar Ávila Olmeda\n2021-2027;\nCAPÍTULO NOVENO\nDE LA CAPACITACIÓN\nARTÍCULO 40.- Fue adicionado por Decreto No. 412, publicado en el Periódico Oficial\nLegislatura, siendo Gobernadora Constitucional la C. Marina del Pilar Ávila Olmeda 20212027;\nARTÍCULO 41.- Fue adicionado por Decreto No. 412, publicado en el Periódico Oficial\nLegislatura, siendo Gobernadora Constitucional la C. Marina del Pilar Ávila Olmeda 20212027;\nLey Orgánica de la Defensoría Pública del Estado de Baja California. Página 23\n.\nActualización Legislativa.\nÚltima Reforma P.O. No. 57, Sección I, 22-Nov-2024\nARTICULO TERCERO TRANSITORIO DEL DECRETO No. 348, POR EL QUE SE\nREFORMA DEL ARTÍCULO PRIMERO TRANSITORIO, PUBLICADO EN EL PERIODICO\nOFICIAL No. 05, TOMO CXVII, SECCIÓN II, DE FECHA 22 DE ENERO DE 2010,\nEXPEDIDO POR LA H. XIX LEGISLATURA, SIENDO GOBERNADOR CONSTITUCIONAL\nEL C. JOSE GUADALUPE OSUNA MILLAN 2007-2013.\nDADO en el Salón de Sesiones “Lic. Benito Juárez García” del H. Poder Legislativo del Estado de Baja California, en la ciudad de Mexicali, B.C., a los veintiún dias del mes de enero del dos mil diez.\nDIP. ANTONIO RICARDO CANO JIMÉNEZ\nPRESIDENTE\n(RUBRICA)\nDIP. RUBÉN ERNESTO ARMENTA ZANABIA\nSECRETARIO\n(RUBRICA)\nDE CONFORMIDAD CON LO DISPUESTO POR LA FRACCION I DEL ARTÍCULO 49\nMEXICALI, BAJA CALIFORNIA, A LOS VEINTIDOS DIAS DEL MES DE ENERO DEL\nAÑO DOS MIL DIEZ.\nGOBERNADOR DEL ESTADO\nJOSE GUADALUPE OSUNA MILLAN\n(RÚBRICA)\nSECRETARIO GENERAL DE GOBIERNO\nJOSE FRANCISCO BLAKE MORA\n(RUBRICA)\nARTICULO TERCERO TRANSITORIO DEL DECRETO No. 360, POR EL QUE SE\nAPRUEBA LA REFORMA EL ARTÍCULO PRIMERO TRANSITORIO, PUBLICADO EN EL\nPERIODICO OFICIAL No. 18, TOMO CXVII, SECCIÓN III, DE FECHA 23 DE ABRIL DE\n2010, EXPEDIDO POR LA H. XIX LEGISLATURA, SIENDO GOBERNADOR\nCONSTITUCIONAL EL C. JOSE GUADALUPE OSUNA MILLAN 2007-2013.\nLey Orgánica de la Defensoría Pública del Estado de Baja California. Página 24\n.\nActualización Legislativa.\nÚltima Reforma P.O. No. 57, Sección I, 22-Nov-2024\nDADO en el Salón de Sesiones “Lic. Benito Juárez García” del H. Poder Legislativo del Estado de Baja California, en la Ciudad de Mexicali, B.C., a los veintidos días del mes de abril del dos mil diez.\nDIP. OSCAR ROMÁN MARTÍNEZ GARZA\nPRESIDENTE\n(RUBRICA)\nDIP. JUAN MANUEL MOLINA GARCÍA\nSECRETARIO\n(RUBRICA)\nDE CONFORMIDAD CON LO DISPUESTO POR LA FRACCION I DEL ARTÍCULO 49\nMEXICALI, BAJA CALIFORNIA, A LOS VEINTITRÉS DIAS DEL MES DE ABRIL DEL\nAÑO DOS MIL DIEZ.\nGOBERNADOR DEL ESTADO\nJOSE GUADALUPE OSUNA MILLAN\n(RÚBRICA)\nSECRETARIO GENERAL DE GOBIERNO\nJOSE FRANCISCO BLAKE MORA\n(RUBRICA)\nARTÍCULO NOVENO TRANSITORIO DEL DECRETO No. 246, POR EL QUE SE\nREFORMAN LOS ARTÍCULOS 5, 22 y 34, PUBLICADO EN EL PERIÓDICO OFICIAL No.\n24, SECCION I, TOMO CXXII, DE FECHA 22 DE MAYO DE 2015, EXPEDIDO POR LA H.\nXXI LEGISLATURA, SIENDO GOBERNADOR CONSTITUCIONAL EL C. FRANCISCO\nARTURO VEDA DE LAMADRID 2013-2019.\nARTÍCULOS TRANSITORIOS\nPRIMERO.- Publíquense las presentes reformas en el Periódico Oficial del Estado de\nBaja California.\nSEGUNDO.- Las presentes reformas entrarán en vigor de manera gradual, en las fechas en que inicie vigencia el Código Nacional de Procedimientos Penales, de del artículo segundo transitorio del mencionado Código Nacional. Lo anterior, sin perjuicio de lo siguiente:\n1.- Las reformas a la Ley de Atención y Protección a la Víctima o el Ofendido del\nDelito para el Estado de Baja California, y la reforma a los artículos 19, 22 y 23 de la Ley\nOrgánica de la Administración Pública del Estado, entrarán en vigor al día siguiente de su publicación en el Periódico Oficial del Estado.\nLey Orgánica de la Defensoría Pública del Estado de Baja California. Página 25\n.\nActualización Legislativa.\nÚltima Reforma P.O. No. 57, Sección I, 22-Nov-2024\n2.- Las reformas a la Ley Orgánica de la Defensoría Pública del Estado de Baja\nCalifornia, entrarán en vigor al día siguiente de su publicación en el Periódico Oficial del\nEstado, y su cumplimiento estará sujeto a la disponibilidad presupuestal.\n3.- Las reformas a la Ley del Sistema Integral de Justicia para Adolescentes del\nEstado de Baja California, entrarán en vigor al momento en que inicie vigencia dicha Ley conforme a su artículo transitorio primero.\n4.- Las reformas a la Ley Contra la Delincuencia Organizada para el Estado de Baja\nCalifornia, iniciarán vigencia a los noventa días después de su publicación en el Periódico\nOficial del Estado.\nTERCERO.- Las menciones que en otras leyes, ordenamientos reglamentarios o acuerdos se haga respecto a la Subprocuraduría contra la Delincuencia Organizada, se entenderán hechas a la Subprocuraduría de Investigaciones Especiales de la Procuraduría\nGeneral de Justicia del Estado.\nCUARTO.- Quienes se encuentren ejerciendo el cargo de Juez de Garantía en el\nPartido Judicial de Mexicali, al momento de la entrada en vigor del presente Decreto conforme al transitorio segundo, pasarán a ejercer el cargo de Juez de Control a que se refiere la presente reforma, conservando sus derechos adquiridos por el periodo que fueron designados.\nLos jueces de control del Partido Judicial de Mexicali, fungirán como jueces de garantías para el trámite o substanciación de los asuntos en donde se aplique el Código de\nProcedimientos Penales para el Estado de Baja California publicado en el Periódico Oficial del Estado el 19 de octubre de 2007.\nQUINTO.- La designación de los jueces de ejecución a que se refiere este Decreto, será de conformidad con la gradualidad prevista en el primer párrafo del artículo segundo transitorio de la presente reforma.\nHasta en tanto no se realice el nombramiento de jueces de ejecución en cada partido judicial, según sea el caso, los jueces de garantía, control o de primer instancia atendiendo la naturaleza del proceso penal que dio lugar a la sentencia, continuarán conociendo y resolviendo los procedimientos competencia de los jueces de ejecución. del Estado de Baja California, en la Ciudad de Mexicali, B.C., a los veintitrés días del mes de abril del año dos mil quince.\nDIP. FCO. ALCIBÍADES GARCÍA LIZARDI\nPRESIDENTE\n(RUBRICA)\nDIP. ROSALBA LÓPEZ REGALADO\nSECRETARIA\n(RUBRICA)\nLey Orgánica de la Defensoría Pública del Estado de Baja California. Página 26\n.\nActualización Legislativa.\nÚltima Reforma P.O. No. 57, Sección I, 22-Nov-2024\nDE CONFORMIDAD CON LO DISPUESTO POR LA FRACCION I DEL ARTÍCULO 49\nMEXICALI, BAJA CALIFORNIA, A LOS CINCO DÍAS DEL MES DE MAYO DEL AÑO DOS\nMIL QUINCE.\nFRANCISCO ARTURO VEGA DE LAMADRID\nGOBERNADOR DEL ESTADO\n(RÚBRICA)\nFRANCISCO RUEDA GOMEZ\nSECRETARIO GENERAL DE GOBIERNO\n(RÚBRICA)\nARTÍCULO ÚNICO TRANSITORIO DEL DECRETO No. 296, POR EL QUE SE\nADICIONA LA FRACCIÓN XVI Y EL RECORRIDO DE LAS SUBSECUENTES\nFRACCIONES DEL ARTÍCULO 20, PUBLICADO EN EL PERIÓDICO OFICIAL No. 7,\nSECCION III, TOMO CXXVI, DE FECHA 01 DE FEBRERO DE 2019, EXPEDIDO POR LA\nH. XXII LEGISLATURA, SIENDO GOBERNADOR CONSTITUCIONAL EL C. FRANCISCO\nARTURO VEDA DE LAMADRID 2013-2019.\nARTÍCULOS TRANSITORIOS\nÚNICO.- La presente reforma entrará en vigor al día siguiente de su publicación en\nPeriódico Oficial del Estado de Baja California.\nDADO en el Salón de Sesiones “Lic. Benito Juárez García” del H. Poder Legislativo del Estado de Baja California, en la Ciudad de Mexicali, B.C., a los doce días del mes de diciembre del año dos mil dieciocho.\nDIP. CARLOS ALBERTO TORRES TORRES\nPRESIDENTE\n(RUBRICA)\nDIP. MARÍA TRINIDAD VACA CHACÓN\nSECRETARIA\n(RUBRICA)\nDE CONFORMIDAD CON LO DISPUESTO POR LA FRACCION I DEL ARTÍCULO 49\nLey Orgánica de la Defensoría Pública del Estado de Baja California. Página 27\n.\nActualización Legislativa.\nÚltima Reforma P.O. No. 57, Sección I, 22-Nov-2024\nMEXICALI, BAJA CALIFORNIA, A LOS TREINTA Y UN DÍAS DEL MES DE ENERO DEL\nAÑO DOS MIL DIECINUEVE.\nFRANCISCO ARTURO VEGA DE LAMADRID\nGOBERNADOR DEL ESTADO\n(RÚBRICA)\nFRANCISCO RUEDA GÓMEZ\nSECRETARIO GENERAL DE GOBIERNO\n(RÚBRICA)\nARTÍCULO ÚNICO TRANSITORIO DEL DECRETO No. 412, POR EL QUE SE\nAPRUEBA LA ADICIÓN DEL CAPÍTULO NOVENO “DE LA CAPACITACIÓN”, ASÍ COMO\nLA ADICIÓN DE LOS ARTÍCULOS 40 Y 41; PUBLICADO EN EL PERIÓDICO OFICIAL No.\n19, SECCION I, TOMO CXXXI, DE FECHA 12 DE ABRIL DE 2024, EXPEDIDO POR LA H.\nXXIV LEGISLATURA, SIENDO GOBERNADORA CONSTITUCIONAL LA C. MARINA DEL\nPILAR ÁVILA OLMEDA 2021-2027.\nARTÍCULOS TRANSITORIOS\nPRIMERO. La presente reforma entrará en vigor al día siguiente de su publicación en el\nPeriódico Oficial del Estado de Baja California.\nSEGUNDO. Las erogaciones que se generen a la entrada en vigor del presente Decreto, se realizarán con cargo a la disponibilidad presupuestal que se apruebe para tal fin, en el ejercicio correspondiente.\nDADO en Sesión de Clausura de la XXIV Legislatura en la Ciudad de Mexicali, B.C., a los treinta y un días del mes de marzo del año dos mil veinticuatro.\nDIP. ARACELI GERALDO NÚÑEZ\nPRESIDENTA\n(RÚBRICA)\nDIP. MANUEL GUERRERO LUNA\nSECRETARIO\n(RÚBRICA)\nDE CONFORMIDAD CON LO DISPUESTO POR LA FRACCIÓN I DEL ARTÍCULO 49\nCALIFORNIA, IMPRÍMASE Y PUBLÍQUESE.\nLey Orgánica de la Defensoría Pública del Estado de Baja California. Página 28\n.\nActualización Legislativa.\nÚltima Reforma P.O. No. 57, Sección I, 22-Nov-2024\nMEXICALI, BAJA CALIFORNIA, A LOS CUATRO DÍAS DEL MES DE ABRIL DEL\nAÑO DOS MIL VEINTICUATRO.\nMARINA DEL PILAR ÁVILA OLMEDA\nGOBERNADORA DEL ESTADO\nDE BAJA CALIFORNIA\n(RÚBRICA)\nALFREDO ÁLVAREZ CÁRDENAS\nSECRETARIO GENERAL DE GOBIERNO\nDEL ESTADO DE BAJA CALIFORNIA\n(RÚBRICA)\nARTÍCULO ÚNICO TRANSITORIO DEL DECRETO No. 17, POR EL QUE SE\nAPRUEBA LA REFORMA DE LOS ARTÍCULOS 2, 3, 4, 5, 6, 7, 8, 9, 10, 11, 12, 13, 14, 15,\n16, 17, 18, 19, 20, 21, 22, 23, 24, 25, 27, 28, 29, 30, 31, 32, 33, 34, 35, 36, 37, 38, 39 Y LA\nDENOMINACIÓN DEL CAPÍTULO TERCERO PARA DENOMINARSE “DE LAS PERSONAS\nDEFENSORAS PÚBLICAS” Y ADICIÓN DEL ARTÍCULO 15 BIS; PUBLICADO EN EL\nPERIÓDICO OFICIAL No. 57, SECCIÓN I, DE FECHA 22 DE NOVIEMBRE DE 2024, TOMO\nCXXXI, EXPEDIDO POR LA H. XXV LEGISLATURA, SIENDO GOBERNADORA\nCONSTITUCIONAL LA C. MARINA DEL PILAR ÁVILA OLMEDA 2021-2027.\nTRANSITORIOS\nPRIMERO. Las presentes reformas entrarán en vigor al día siguiente de su publicación en el\nPeriódico Oficial del Estado.\nSEGUNDO. Se derogan todas aquellas disposiciones legales y normativas que se opongan a lo dispuesto en esta Ley.\nTERCERO. El Ejecutivo del Estado, deberá realizar las adecuaciones normativas necesarias, dentro de los 90 día hábiles siguientes a la publicación de este decreto.\nDADO en Sesión Ordinaria de la XXV Legislatura en la Ciudad de Mexicali, B.C., a los siete días del mes de noviembre del año dos mil veinticuatro.\nDIP. DUNNIA MONTSERRAT MURILLO LÓPEZ\nPRESIDENTA\n(RÚBRICA)\nDIP. ALEJANDRA MARÍA ANG HERNÁNDEZ\nSECRETARIA\n(RÚBRICA)\nLey Orgánica de la Defensoría Pública del Estado de Baja California. Página 29\n.\nActualización Legislativa.\nÚltima Reforma P.O. No. 57, Sección I, 22-Nov-2024\nDE CONFORMIDAD CON LO DISPUESTO POR LA FRACCIÓN I DEL ARTÍCULO\nCALIFORNIA, IMPRÍMASE Y PUBLÍQUESE.\nMEXICALI, BAJA CALIFORNIA, A LOS OCHO DÍAS DEL MES DE NOVIEMBRE DEL\nAÑO DOS MIL VEINTICUATRO.\nMARINA DEL PILAR ÁVILA OLMEDA\nGOBERNADORA DEL ESTADO\nDE BAJA CALIFORNIA\n(RÚBRICA)\nALFREDO ÁLVAREZ CÁRDENAS\nSECRETARIO GENERAL DE GOBIERNO\nDEL ESTADO DE BAJA CALIFORNIA\n(RÚBRICA)\nLey Orgánica de la Defensoría Pública del Estado de Baja California. Página 30",
  "ordenamiento": "REGLAMENTO",
  "jurisdiccion": "BAJA CALIFORNIA",
  "fuente_oficial": "Periódico Oficial",
  "FECHA PER OFIC": "2024/11/22",
  "ESTATUS": "VIGENTE",
  "TOMO": "TOMO_V",
  "URL": "https://www.congresobc.gob.mx/Documentos/ProcesoParlamentario/Leyes/TOMO_V/20241122_LEYORGDEFENPUB.PDF",
  "es_escaneado": false,
  "tiene_tablas": true,
  "materia": [
    "penal",
    "seguridad",
    "justicia"
  ]
}