{
  "titulo": "Ley DE DESARROLLO SOCIAL PARA EL ESTADO DE BAJA CALIFORNIA",
  "Contenido": ".\nActualización Legislativa.\nÚltima Reforma P.O. No. 37, Índice, 26-Jul-2024\nLEY DE DESARROLLO SOCIAL PARA EL ESTADO DE BAJA CALIFORNIA\nPublicada en el Periódico Oficial No. 60, Número Especial, Sección XI, de fecha 31 de diciembre de 2015, Tomo CXXII\nTÍTULO I\nDISPOSICIONES GENERALES\nCAPÍTULO ÚNICO\nNaturaleza, objeto, principios y definiciones de la ley\nArtículo 1.- Las disposiciones de esta Ley son de orden de público, interés social y de observancia general en el Estado de Baja California y tienen por objeto:\nI. Garantizar el pleno ejercicio de los derechos sociales consagrados en la desarrollo social.\nII. Establecer el Sistema Estatal de Desarrollo Social con la participación de las dependencias y entidades de la administración pública estatal y municipal vinculadas al desarrollo social;\nIII. Coordinar y armonizar la política estatal y municipal en materia de desarrollo social en el marco de la política nacional;\nIV. Establecer las bases y los mecanismos para la planeación, instrumentación, ejecución, seguimiento y evaluación de las políticas públicas estatal y municipal en materia de desarrollo social, promoviendo la participación ciudadana;\nV. Garantizar la calidad de los programas de desarrollo social a cargo del Gobierno del Estado y de los Municipios, así como la aplicación eficiente, equitativa y justa de los mismos;\nVI. Fortalecer el sector social de la economía, definiendo sus características y modalidades;\nVII. Impulsar el desarrollo económico de las Zonas de Atención Prioritaria en el\nEstado; y\nVIII. Promover la denuncia popular y el ejercicio de Contraloría Social.\nArtículo Reformado\nArtículo 2.- La aplicación de la presente Ley corresponde al Ejecutivo del Estado por respectivas competencias.\nLey de Desarrollo Social para el Estado de Baja California. Página 1\n.\nActualización Legislativa.\nÚltima Reforma P.O. No. 37, Índice, 26-Jul-2024\nEn lo no previsto, se aplicarán en forma supletoria, en lo conducente y en el siguiente orden:\nI. La Ley General de Desarrollo Social;\nII. La Ley de Planeación; y\nIII. Las demás leyes aplicables.\nArtículo Reformado\nArtículo 3.- En el diseño, instrumentación, ejecución y evaluación de la política de desarrollo social estatal y municipal se observarán los siguientes principios:\nI.- Armonización normativa: Espíritu de impulso y fortalecimiento de esta y otras leyes con el propósito de mantener un orden jurídico estatal eficiente;\nII.- Corresponsabilidad: Es la responsabilidad compartida entre el Gobierno y todos los sectores de la sociedad;\nIII.- Diálogo sostenido: Proceso permanente que crea espacios para la deliberación comunitaria con las instancias públicas, con el propósito de encontrar soluciones conjuntas para los problemas identificados con el desarrollo social;\nIV.- Efectividad: Es la obligación de la autoridad encargada de ejecutar los programas sociales de manera austera, con el menor costo administrativo, con eficacia y celeridad;\nV.- Perspectiva de género: La plena igualdad de derechos y oportunidades entre mujeres y hombres, la eliminación de toda forma de desigualdad, exclusión o subordinación basada en los roles de género y una nueva relación de convivencia social entre mujeres y hombres desprovista de relaciones de dominación, estigmatización, y sexismo;\nVI.- Integralidad: Articulación y complementariedad de programas y acciones que conjunten a los diferentes beneficios sociales, en el marco de la Política Nacional, Estatal y\nMunicipal de Desarrollo Social;\nVII.- Justicia distributiva: Procura que toda región o comunidad reciba de manera equitativa los beneficios del desarrollo conforme a sus méritos, sus necesidades, sus posibilidades y las de las demás personas, dando prioridad a los grupos que se encuentran excluidos del desarrollo y en desigualdad social;\nVIII.- Libertad: Concebida como la capacidad de las personas para elegir los medios para su desarrollo personal así como participar en el desarrollo social;\nIX.- Libre determinación de los pueblos indígenas: Reconocimiento a las formas internas de convivencia y de organización; ámbito de aplicación de sus propios sistemas normativos; elección de sus autoridades o representantes; medios para preservar y enriquecer sus lenguas y cultura; medios para conservar y mejorar su hábitat; acceso preferente a sus recursos naturales y acceso pleno a la jurisdicción del Estado;\nLey de Desarrollo Social para el Estado de Baja California. Página 2\n.\nActualización Legislativa.\nÚltima Reforma P.O. No. 37, Índice, 26-Jul-2024\nX.- Participación social: Intervención e integración de las personas y de las organizaciones de la sociedad civil en la formulación, operación y evaluación de las políticas, programas y acciones de desarrollo social;\nXI.- Respeto a la diversidad: Reconocimiento de los derechos constitucionales de las personas en términos de su origen étnico, género, edad, discapacidad, condición social, condiciones de salud, religión, opiniones, preferencias, estado civil o cualquier otra, para superar toda forma de discriminación y promover un desarrollo con equidad y respeto a las diferencias;\nXII.- Solidaridad: Colaboración entre personas, grupos sociales, dependencias y entidades de gobierno que de manera corresponsable luchan por mejorar la calidad de vida de la sociedad;\nXIII.- Subsidiariedad: Es el reconocimiento de los derechos y obligaciones que permiten a una persona o comunidad con mayor grado de desarrollo que otro, proteger, apoyar y ayudar a éste último en sus tareas para que supere su situación de marginación, pobreza o vulnerabilidad y alcance su desarrollo integral;\nXIV.- Sustentabilidad: Preservación del equilibrio ecológico, protección del ambiente y aprovechamiento de recursos naturales para mejorar la calidad de vida y la productividad de las personas, sin comprometer la satisfacción de las necesidades de las generaciones futuras;\nXV.- Transparencia: La información relativa al desarrollo social es de carácter público en los términos de las leyes en la materia;\nXVI.- Universalidad: Es el compromiso de la autoridad responsable de la ejecución de los programas sociales de procurar el desarrollo social sin distinción alguna;\nEstos principios regirán la Política de Desarrollo Social en las siguientes vertientes:\na) Salud: orientada a proporcionar los servicios básicos de salud a la población no derechohabiente de la seguridad social en el Estado de Baja California; prevención y rehabilitación de adicciones, promover la cultura de prevención de enfermedades en general y en especial las de mayor gravedad o incidencia de casos, la aplicación gratuita de vacunas y los demás servicios que requieran para el óptimo desarrollo social;\nb) Educación: orientada a otorgar estímulos como becas a estudiantes con mejor aprovechamiento, becas a quienes destaquen en proyectos de ciencia y tecnología, becas a estudiantes de bajos recursos económicos, desayunos escolares, el establecimiento de escuelas para personas con capacidades diferentes, promover la capacitación para el empleo y oficios, crear conciencia de la necesidad de valores éticos y de cultura de la desarrollo social;\nc) Trabajo: orientado a la prestación de asesoría gratuita a la clase obrera, la promoción del empleo a través de bolsas de trabajo, creación de nuevos empleos, impulsando las estrategias que fomenten el autoempleo y el desarrollo local;\nLey de Desarrollo Social para el Estado de Baja California. Página 3\n.\nActualización Legislativa.\nÚltima Reforma P.O. No. 37, Índice, 26-Jul-2024\nd) Vivienda y obra social: orientada al acceso de vivienda a personas de escasos recursos, así como la promoción y realización de obras necesarias en colonias populares, delegaciones o poblaciones lejanas a las cabeceras municipales, entre otras;\ne) Medio ambiente: orientado a generar un medio ambiente ecológico adecuado para el sano crecimiento y desarrollo de los seres humanos, así como su esparcimiento; y\nf) Prevención Integral: entendiéndose como el conjunto de acciones y medidas con el propósito de suprimir, reducir, contrarrestar o evitar las causas de la problemática social, desarrollando actitudes, hábitos positivos y constructivos y al mismo tiempo crear espacios y ambientes saludables que fomenten el desarrollo humano.\nArtículo Reformado\nArtículo 4. Para los efectos de esta Ley se entiende por:\nI. Beneficiarios: Personas que forman parte de la población atendida por los programas de desarrollo social por cumplir con los requisitos de la normatividad correspondiente;\nII. Comisión Estatal: La Comisión Estatal para el Desarrollo Social;\nIII. CONEVAL: Consejo Nacional de Evaluación de la Política de Desarrollo Social.\nIV. Consejo: El Consejo Consultivo para el Desarrollo Social del Estado de Baja\nCalifornia.\nV. Desarrollo Social: El proceso mediante el cual se amplían las capacidades y las opciones de las personas y comunidades con el propósito de reducir las desigualdades en ingreso, garantizar el acceso a servicios y en general a aumentar la calidad de vida de los habitantes del Estado de Baja California;\nVI. Ejecutivo del Estado: El Poder Ejecutivo del Gobierno del Estado de Baja\nCalifornia;\nVII. Grupos sociales en situación de vulnerabilidad: Aquellos núcleos de población y personas que por diferentes factores o por la combinación de ellos, enfrentan situaciones de riesgo o discriminación que les impiden alcanzar mejores niveles de vida, y por lo tanto requieren de la atención e inversión del Gobierno para lograr su bienestar;\nVIII. La Ley: Ley de Desarrollo Social para el Estado de Baja California:\nIX. La Secretaría: La Secretaría de Desarrollo Social del Estado de Baja California;\nX. Las Secretarías: Las dependencias así reconocidas en la Ley Orgánica de la\nAdministración Pública del Estado de Baja California;\nXI. Ley de Planeación: Ley de Planeación del Estado de Baja California; para el Estado de Baja California;\nXIII. Ley General: Ley General de Desarrollo Social;\nLey de Desarrollo Social para el Estado de Baja California. Página 4\n.\nActualización Legislativa.\nÚltima Reforma P.O. No. 37, Índice, 26-Jul-2024\nXIV. Organizaciones: Agrupaciones civiles y sociales legalmente constituidas en las que participan personas o grupos sociales con el propósito de realizar actividades relacionadas con el desarrollo social;\nXV. Padrón: La relación oficial de beneficiarios que incluye a las personas atendidas por los programas estatales de desarrollo social cuyo perfil socioeconómico se establece en la normatividad correspondiente;\nXVI. Periódico Oficial: El Periódico Oficial del Estado de Baja California;\nXVII. Reglamento: El Reglamento de la Ley de Desarrollo Social para el Estado de\nBaja California;\nXVIII. Reglas de operación: Disposición administrativa que establece las bases en forma ordenada y sistemática que deberá seguir cada programa en su planeación, ejecución, control, seguimiento y evaluación.\nXIX. Sector social de la economía: Subsector de la economía, constituido por el conjunto de entidades sociales organizadas, bajo un régimen democrático participativo y en donde se ha adoptado la forma autogestionaria de trabajo y que define a las personas y comunidades como principio y fin del desarrollo.\nArtículo Reformado\nTÍTULO II\nDE LAS AUTORIDADES COMPETENTES\nCAPÍTULO I\nAtribuciones del Poder Ejecutivo del Estado\nArtículo 5. En su respectivo ámbito de competencia el titular del Poder Ejecutivo será la autoridad rectora del desarrollo social en el Estado a través de la planeación y ejecución de las políticas y programas en la materia.\nI. Realizar la medición de la pobreza en el Estado para la ejecución de la política estatal y municipal de desarrollo social;\nII. Formular y expedir el Programa Sectorial así como ordenar su ejecución;\nIII. Expedir las reglas de operación de los programas y subprogramas sociales sujetos a ellas, así como las bases de coordinación entre sus dependencias y entidades;\nIV. Promover la congruencia y vinculación de la política estatal de desarrollo social con la políticas nacional y municipales en la materia;\nV. Coordinar el Sistema Estatal de Desarrollo Social;\nLey de Desarrollo Social para el Estado de Baja California. Página 5\n.\nActualización Legislativa.\nÚltima Reforma P.O. No. 37, Índice, 26-Jul-2024\nVI. Evaluar anualmente el impacto social de los programas estatales de desarrollo social, midiendo el avance en la solución de la problemática que les dio origen;\nVII. Modificar o ampliar los programas de acuerdo a los resultados de las evaluaciones;\nVIII. Realizar gestiones interinstitucionales para que los programas de desarrollo social en que participe el Ejecutivo del Estado, alcancen los objetivos previstos;\nIX. Participar en el Sistema Nacional de Desarrollo Social y en la Comisión Nacional de Desarrollo Social, en los términos que señala la Ley General;\nX. Vigilar que los recursos públicos que se destinan al desarrollo social se ejerzan con honradez, transparencia y equidad, fomentando los mecanismos de participación social relacionados con el mismo propósito;\nXI. Promover el desarrollo y fortalecimiento del sector social de la economía;\nXII. Fomentar la participación de las organizaciones y de la sociedad en general, en la planeación, ejecución y evaluación de la Política Estatal de Desarrollo Social;\nXIII. Expedir los Lineamientos Normativos y Operativos para el Ejercicio Ciudadano de la Contraloría Social en coordinación con la Dirección de Evaluación y Control\nGubernamental;\nXIV. Determinar las zonas de atención prioritaria en el Estado de conformidad con lo previsto en el artículo 65 de esta Ley; y\nXV. Las demás que señalen las disposiciones legales aplicables.\nArtículo Reformado\nCAPÍTULO II\nAtribuciones de los Municipios\nArtículo 7.- Corresponden a los Municipios, en el ámbito de su competencia, las siguientes atribuciones:\nI. Formular, dirigir, implementar y evaluar la política de desarrollo social municipal, relacionados con el desarrollo social municipal;\nII. Formular y ejecutar el Programa Municipal de Desarrollo Social como parte del\nPlan Municipal de Desarrollo;\nLey de Desarrollo Social para el Estado de Baja California. Página 6\n.\nActualización Legislativa.\nÚltima Reforma P.O. No. 37, Índice, 26-Jul-2024\nIII. Expedir y publicar las reglas de operación de los programas sociales municipales sujetos a las mismas;\nIV. Realizar gestiones interinstitucionales para que los programas de desarrollo social en que participe el Gobierno Municipal, alcancen los objetivos previstos;\nV. Evaluar los programas sociales municipales y hacer públicos sus resultados;\nVI. Fomentar la participación de las organizaciones en la planeación, ejecución y evaluación de la Política Municipal de Desarrollo Social;\nVII. Participar en el Sistema Nacional de Desarrollo Social en los términos de la Ley\nGeneral;\nVIII. Concertar acciones con los sectores social y privado en materia de desarrollo social;\nIX. Vigilar que los recursos públicos que se destinan al Desarrollo Social se ejerzan con honradez, transparencia y equidad;\nX. Integrar un padrón de beneficiarios de los programas sociales a su cargo;\nXI. Impulsar prioritariamente la prestación de servicios públicos en las comunidades más necesitadas y evitar el crecimiento de zonas de pobreza; y\nXII. Las demás que resulten de las disposiciones legales aplicables en materia de desarrollo social.\nArtículo Reformado\nCAPÍTULO III\nDe los convenios de desarrollo social\nArtículo 8. El Poder Ejecutivo y los Ayuntamientos del Estado podrán suscribir convenios para acordar el destino y los criterios del gasto en materia de desarrollo social, en los que se buscará la coordinación de recursos, obras y acciones para la óptima ejecución de los programas sociales. compromisos específicos entre las partes o con un tercero, podrán suscribirse los anexos de ejecución que resulten necesarios.\nTÍTULO III\nDE LOS SUJETOS DEL DESARROLLO SOCIAL\nLey de Desarrollo Social para el Estado de Baja California. Página 7\n.\nActualización Legislativa.\nÚltima Reforma P.O. No. 37, Índice, 26-Jul-2024\nCAPÍTULO I\nDerechos y obligaciones de los beneficiarios\nArtículo 9. Sin perjuicio de lo que señalen otras disposiciones legales, en el Estado de Baja California se reconocen y consideran como derechos inherentes al desarrollo social los siguientes:\nI. El derecho a la salud;\nII. El derecho a la educación;\nIII. El derecho a ser informado;\nIV. El derecho a la alimentación y nutrición adecuadas;\nV.- El derecho a una vivienda digna y decorosa;\nVI. El derecho a un medio ambiente sano;\nVII. El derecho al trabajo y la seguridad social; y\nVIII. El derecho a la equidad y la igualdad.\nArtículo 10. Las personas en condiciones de pobreza o marginación social, así como los grupos en situación de vulnerabilidad extrema, tienen derecho a solicitar acciones y apoyos tendientes a disminuir su condición de desventaja.\nArtículo 11. Queda prohibida toda práctica discriminatoria en la prestación de bienes y servicios derivada de las políticas, programas y acciones de desarrollo social.\nArtículo 12. El Ejecutivo Estatal y los Ayuntamientos, en sus respectivos ámbitos de competencia y con sus recursos presupuestales, con los recursos federales en la forma que establece la ley general, tienen a su cargo la obligación de formular y aplicar de manera integral las políticas asistenciales, así como oportunidades y programas de desarrollo social en los términos de esta ley.\nArtículo 13. Para garantizar el cumplimiento de los derechos sociales universales, el\nEjecutivo del Estado, a través de la Secretaría, formulará, divulgará y aplicará mecanismos social a su cargo.\nArtículo 14. Los beneficiarios tendrán los siguientes derechos:\nI. Recibir un trato respetuoso, digno, oportuno y con calidad;\nII. Acceder a la información sobre los programas de desarrollo social que promuevan el Ejecutivo del Estado y los Municipios, así como su normatividad, reglas de operación, recursos, cobertura y beneficios;\nLey de Desarrollo Social para el Estado de Baja California. Página 8\n.\nActualización Legislativa.\nÚltima Reforma P.O. No. 37, Índice, 26-Jul-2024\nIII. Tener la garantía de reserva y privacidad de la información personal que manejen las dependencias y entidades en los términos de la legislación de la materia;\nIV. Recibir los servicios, prestaciones y apoyos de los programas de desarrollo social conforme a sus reglas de operación y previo cumplimiento de los requisitos aplicables, salvo que les sean suspendidos por resolución administrativa o judicial debidamente fundada y motivada;\nV. Presentar su solicitud de inclusión en el padrón de beneficiarios;\nVI. Participar de manera corresponsable en los programas de desarrollo social; y\nVII. Las demás que establezcan los programas de desarrollo social, así como otras disposiciones legales aplicables.\nArtículo Reformado\nArtículo 15. Son obligaciones de los beneficiarios:\nI. Participar de manera responsable en los programas y acciones de desarrollo social a que tengan acceso;\nII. Proporcionar de forma veraz y oportuna la información socioeconómica que soliciten las autoridades, de conformidad con las reglas de operación de los programas de desarrollo social;\nIII. Informar a las autoridades correspondientes si se es beneficiario de dos o más programas de desarrollo social, ya sean federales, estatales o municipales;\nIV. Cumplir con la normatividad y requisitos de los programas de desarrollo social e informar a la instancia correspondiente cuando haya desaparecido la causa o condición que generó el otorgamiento del beneficio;\nV. Mantenerse al margen de cualquier condicionamiento de tipo político partidista en la ejecución de los programas de desarrollo social, y\nVI. Las demás que establezcan los programas de desarrollo social, así como otras disposiciones legales aplicables.\nCAPÍTULO II\nDel padrón de beneficiarios\nArtículo 16. Con el propósito de asegurar la transparencia, la equidad y la eficacia de los programas sociales, el Ejecutivo del Estado y los Ayuntamientos, en el ámbito de sus competencias, instrumentarán mecanismos de coordinación para la integración de un padrón\nLey de Desarrollo Social para el Estado de Baja California. Página 9\n.\nActualización Legislativa.\nÚltima Reforma P.O. No. 37, Índice, 26-Jul-2024 de beneficiarios de los programas sociales que les correspondan, mismo que estará a disposición de la ciudadanía en los términos previstos por la Ley de Transparencia.\nArtículo 17. El Ejecutivo del Estado, a través de la Secretaría y los Ayuntamientos por conducto del área correspondiente podrán coordinarse con las autoridades federales que ejecuten programas de desarrollo social en el territorio del Estado a efecto de integrar la información de sus programas al padrón.\nArtículo 18. Para la administración y actualización del padrón de beneficiarios, la\nSecretaría realizará las siguientes acciones:\nI. Emitir a más tardar el 30 de noviembre de cada año, las reglas de operación para la integración y actualización;\nII. Depurarlo y actualizarlo trimestralmente, así como publicarlo en los términos de que disponga la Ley de Transparencia;\nIII. Solicitar a las dependencias y organismos de la administración pública estatal y a los Municipios, dentro de los cinco días previos al término de cada trimestre, el padrón de beneficiarios de los programas de desarrollo social que aplican en la entidad, en medio impreso y magnético;\nIV. Asesorar a los Municipios que lo soliciten en las actividades tendientes a la emisión de las reglas de operación e integración de su padrón de beneficiarios; y,\nV. Convenir ante las entidades y dependencias federales mecanismos de coordinación, a efecto de integrar un sistema de información común de los beneficiarios de los programas sociales.\nArtículo Reformado\nCAPÍTULO III\nDe las organizaciones sociales y civiles\nArtículo 19. El Ejecutivo del Estado y los Ayuntamientos garantizarán el derecho de la sociedad, y de las organizaciones sociales y civiles, a participar de manera activa y corresponsable en la planeación, ejecución y evaluación de la política de desarrollo social.\nArtículo 20. El Ejecutivo del Estado y los Municipios estimularán la organización de personas, familias y grupos sociales, destinando recursos públicos para promover proyectos productivos; identificar oportunidades de inversión y brindar capacitación, asistencia técnica estas actividades.\nArtículo 21. Las organizaciones sociales y civiles que tengan por objeto impulsar el bienestar y el desarrollo social y humano en el estado en sus diversas modalidades, podrán participar en la elaboración, promoción, ejecución y evaluación de los programas.\nLey de Desarrollo Social para el Estado de Baja California. Página 10\n.\nActualización Legislativa.\nÚltima Reforma P.O. No. 37, Índice, 26-Jul-2024\nTÍTULO IV\nDE LA POLÍTICA DE DESARROLLO SOCIAL\nCAPÍTULO I\nDe los objetivos y prioridades\nArtículo 22. La Política de Desarrollo Social del Estado y sus Municipios tiene los siguientes objetivos:\nI. Propiciar las condiciones para que las personas y grupos en situación de pobreza aseguren el disfrute de los derechos sociales, individuales o colectivos, garantizando el acceso a los programas sociales y la igualdad de oportunidades, así como la superación de la marginación y la pobreza, la discriminación y la exclusión social;\nII. Promover un desarrollo económico con sentido social que propicie y conserve el empleo, eleve el nivel de ingreso y mejore su distribución;\nIII. Fortalecer el desarrollo regional equilibrado;\nIV. Garantizar formas de participación social en la formulación, ejecución, instrumentación, evaluación y control de los programas sociales; y\nV. Hacer accesible el derecho a un medio ambiente sano a través del impulso del desarrollo sustentable.\nArtículo 23. La Política de Desarrollo Social debe encaminarse a concentrar los recursos físicos, humanos y financieros de las instituciones públicas y sociales con el fin lograr la reducción de las desigualdades sociales entre las personas, grupos sociales y comunidades mediante la orientación de líneas de acción y programas para desarrollar y aprovechar sus capacidades y para a ampliar el acceso a un patrimonio físico, a la atención y seguridad de las instituciones del Estado, al acceso a redes sociales y comunitarias.\nArtículo 24. La Política de Desarrollo Social tendrá como prioridad proporcionar de manera oportuna y subsidiaria ayuda económica o en bienes y servicios básicos a las personas, familias, grupos, etnias, migrantes, personas en contexto de movilidad y comunidades en situación de pobreza.\nArtículo Reformado\nArtículo 25. Las acciones y programas derivados de la Política de Desarrollo Social se formularán, instrumentarán, ejecutarán y evaluarán atendiendo las necesidades básicas para ampliar el acceso a los recursos públicos, privados y sociales que promuevan condiciones de igualdad de oportunidades para satisfacer el bienestar social.\nArtículo 26. La Política de Desarrollo Social promoverá la participación ciudadana programas de bienestar y superación de la pobreza, así como de investigación y evaluación.\nLey de Desarrollo Social para el Estado de Baja California. Página 11\n.\nActualización Legislativa.\nÚltima Reforma P.O. No. 37, Índice, 26-Jul-2024\nCAPÍTULO II\nDe la planeación del desarrollo social\nArtículo 27. La planeación es el proceso por el cual se fijarán los objetivos, instrumentos, estrategias, metas, indicadores, evaluaciones y controles mediante las cuales se llevará el adecuado funcionamiento de la Política Estatal de Desarrollo Social.\nLa planeación de desarrollo social incluirá los programas municipales; planes y programas estatales; programas institucionales, regionales y especiales; el Programa Estatal de Desarrollo Social y el Plan Estatal de Desarrollo.\nArtículo 28. El Estado y los Municipios, en sus respectivas competencias, elaborarán la planeación de la política estatal y municipal de desarrollo social; conforme a las bases que establece la Ley de Planeación.\nArtículo 29. La planeación del desarrollo social en el Estado estará a cargo del Poder\nEjecutivo a través de la Secretaría y deberá estar en concordancia con la Política Nacional de Desarrollo Social de conformidad con las disposiciones contenidas en esta Ley y se establecerá dentro del Plan Estatal de Desarrollo.\nArtículo 30. En el caso de los Municipios la planeación del desarrollo social estará a cargo del Ayuntamiento y en congruencia con los principios y términos establecidos en esta\nLey.\nArtículo 31. La planeación del desarrollo social será clara y concisa, para que permita vincular la operación e instrumentación de los programas específicos con los objetivos generales establecidos en el Programa.\nLa planeación se concretará a través del Programa Estatal de Desarrollo Social y los\nProgramas Municipales de Desarrollo Social que en su conjunto constituyen el instrumento rector de la planeación en esta materia.\nArtículo 32. Dentro del Plan Estatal de Desarrollo y los Planes Municipales de\nDesarrollo existirá un apartado para el plan sectorial que contendrá, lo siguiente:\nI. El diagnóstico del desarrollo social y de la situación económica así como de los índices de pobreza en el Estado o en el municipio, considerando factores de sexo, edad y entorno socioeconómico;\nII. Los programas de Desarrollo Social que se tiene planeado implementar;\nIII. Los programas operativos anuales, en los cuales quedaran asentados los métodos, formas y líneas de acción para la aplicación de los programas de desarrollo social;\nLey de Desarrollo Social para el Estado de Baja California. Página 12\n.\nActualización Legislativa.\nÚltima Reforma P.O. No. 37, Índice, 26-Jul-2024\nIV. Los esquemas de atención para los grupos sociales en situación de vulnerabilidad;\nV. Las metas y objetivos que se pretende alcanzar en el corto, mediano y largo plazo;\nVI. Los criterios y estrategias de colaboración y corresponsabilidad con la sociedad y las organizaciones;\nVII. Las prioridades en materia de Desarrollo Social, así como, las condiciones mínimas aceptables en las áreas de educación, salud, nutrición e infraestructura social básica, que requieren los habitantes del Estado;\nVIII. La inclusión de unidades administrativas responsables de la operación de los programas;\nIX. Las reglas de operación y términos de referencia para la implementación, seguimiento y evaluación de los programas para el Desarrollo Social; y\nX. Los demás que señalen las disposiciones legales aplicables.\nArtículo 33. Los Municipios serán entes primordiales en la ejecución de los programas de desarrollo social, que en coordinación con los gobiernos federal y estatal, establecerán las líneas de acción y celebrarán los acuerdos o convenios que sean necesarios.\nCAPITULO III\nDel Consejo Consultivo\nArtículo 34. El Consejo Consultivo para el Desarrollo Social es un órgano colegiado de consulta, análisis y opinión en materia de desarrollo social en el Estado, encargado de vincular la participación de especialistas, sociedad civil organizada e investigadores del área social y tendrá por objeto investigar, analizar y evaluar el impacto y avance de las políticas y programas de desarrollo social estatales y municipales que ejecuten la Secretaría y los\nMunicipios del Estado y sugerir a la Secretaría los lineamientos y criterios para la definición, identificación y medición de la pobreza, garantizando la transparencia, objetividad y rigor técnico en dicha actividad.\nArtículo Reformado\nArtículo 35. El Consejo sesionará de manera ordinaria cuatro veces al año y tantas de manera extraordinaria como sea necesario para cumplir con su objetivo, según las convocatorias que al efecto deberá lanzar su Presidente. Sus resoluciones serán tomadas por mayoría de votos.\nArtículo 36. El Consejo se integrará de la siguiente forma:\nLey de Desarrollo Social para el Estado de Baja California. Página 13\n.\nActualización Legislativa.\nÚltima Reforma P.O. No. 37, Índice, 26-Jul-2024\nII. El secretario de Educación y Bienestar Social;\nIII. El secretario de Salud;\nIV. El secretario de Infraestructura y Desarrollo Urbano;\nV. Un investigador representante de la Universidad Autónoma de Baja California;\nVI. Un representante de cada uno de los municipios del Estado, vinculado con el desarrollo social;\nVII. Un representante del Consejo Estatal de Fomento a las Actividades de Bienestar y Desarrollo Social; y;\nVIII. Un representante del Consejo Coordinador Empresarial de la Entidad;\nIX. Un representante de cada uno de los municipios del Estado, vinculado con el desarrollo social;\nX. Un representante del Consejo Estatal de Fomento a las Actividades de Bienestar y Desarrollo Social; y\nXI. Un representante del Consejo Coordinador Empresarial de la Entidad.\nCada integrante propietario designará un suplente, quien asistirá a las sesiones del\nConsejo en ausencia del primero con todas las facultades y derechos que a este correspondan.\nLos integrantes del Consejo distintos a las autoridades formarán parte de este órgano colegiado por un periodo de hasta tres años; concluido ese lapso deberán ser sustituidos o confirmados en sus funciones en los términos que determine el Reglamento.\nEl Consejo contará con un Secretario Técnico, quien será designado por el\nPresidente.\nArtículo Reformado\nArtículo 37. Los investigadores deberán ser ciudadanos mexicanos de reconocido prestigio en los ámbitos académico, profesional, científico o cultural, vinculados con el desarrollo social.\nArtículo 38. El Consejo tendrá las atribuciones siguientes:\nI. Definir los lineamientos metodológicos para la evaluación de la política estatal y municipal de desarrollo social;\nII. Proponer lineamientos y criterios para la definición, identificación y medición de la pobreza en la ejecución de la política estatal y municipal de desarrollo social;\nIII. Proponer políticas públicas de desarrollo social bajo una perspectiva de género;\nLey de Desarrollo Social para el Estado de Baja California. Página 14\n.\nActualización Legislativa.\nÚltima Reforma P.O. No. 37, Índice, 26-Jul-2024\nIV. Emitir opiniones sobre la aplicación de la política de desarrollo social y formular propuestas de reorientación;\nV. Impulsar la participación ciudadana en el seguimiento, operación y evaluación de la política de Desarrollo Social Estatal y Municipal;\nVI. Supervisar la transparencia, equidad y objetividad en la aplicación de los programas estatales y municipales de desarrollo social;\nVII. Establecer lineamientos para realizar estudios y diagnósticos relacionados al desarrollo social del Estado y Municipios;\nVIII. Proponer y propiciar la colaboración de organismos públicos y privados, nacionales y extranjeros, en el desarrollo de la investigación en materia de Desarrollo Social;\nIX. Asesorar en materia social, cuando así lo soliciten las dependencias y entidades de la administración pública estatal y municipal;\nX. Conformar comisiones y grupos de trabajo para la realización y seguimiento de tareas específicas en materia de su competencia; y\nXI. Aprobar y expedir sus normas de organización y operación interna; y (sic)\nArtículo Reformado\nArtículo 39. El Consejo podrá coordinarse con otras dependencias y entidades de la administración pública federal, estatal y municipal, de organizaciones civiles y de investigación internacional, para el cumplimiento de sus objetivos.\nCAPITULO IV\nDe la evaluación de la Política de Desarrollo Social\nArtículo 40. Para los fines de la presente Ley, la evaluación es el análisis sistemático los siguientes aspectos:\nI. Cobertura y número de beneficiarios;\nII. Calidad en los servicios;\nIII. Conocimiento de la población de los programas;\nIV. Mejoras en la calidad de vida de las familias;\nV. Oportunidad de acceso a los programas;\nVI. Disminución de los índices de marginación;\nVII. Opinión de los beneficiados, y\nLey de Desarrollo Social para el Estado de Baja California. Página 15\n.\nActualización Legislativa.\nÚltima Reforma P.O. No. 37, Índice, 26-Jul-2024\nVIII. Los criterios generales que emita el CONEVAL, cuando sean aplicables.\nArtículo 41. La evaluación de la Política de Desarrollo Social estará a cargo del\nConsejo y tendrá como finalidad determinar la pertinencia y el logro de sus objetivos y metas, así como su eficiencia, eficacia, calidad, resultados, impacto y sostenibilidad a fin de presentar al titular del Ejecutivo del Estado propuestas para corregirlos, modificarlos, adicionarlos, reorientarlos o suspenderlos total o parcialmente.\nArtículo 42. La evaluación de la política de desarrollo social podrá ser de carácter interno o externo. La evaluación interna es la que regularmente realizan las ejecutoras de los programas de desarrollo social. La evaluación externa es la que se realiza por instituciones u organismos externos a la ejecutora, conforme a los lineamientos de evaluación emitidos por el Consejo.\nArtículo 43. Toda evaluación externa de la política, programas y subprogramas de desarrollo social, estará a cargo del Consejo, que podrá realizarla por sí mismo o a través de uno o varios organismos independientes del ejecutor del programa y subprogramas que deriven del mismo.\nArtículo 44. Las evaluaciones a que se refiere el presente Capítulo, se realizarán en dos etapas:\nI. La primera correspondiente a los 9 meses iníciales del ejercicio fiscal, para que sus resultados sirvan de apoyo para la programación y presupuestación del siguiente año fiscal y para la corrección y mejoramiento de los programas sociales en operación; y\nII. La segunda cubrirá el ejercicio completo y sus resultados serán complementarios para la programación y presupuestación de los siguientes ejercicios fiscales.\nArtículo 45. Para la evaluación de resultados, de manera invariable los programas sociales deberán incluir los indicadores para medir su cobertura, calidad e impacto. Las dependencias u organismos estatales o municipales ejecutores de los programas a evaluar, proporcionarán al Consejo toda la información y las facilidades necesarias para la realización de la evaluación.\nArtículo 46. Los indicadores de gestión y servicios que se establezcan deberán reflejar los procedimientos y la calidad de los servicios de los programas, metas y acciones de la Política Estatal de Desarrollo Social.\nArtículo 47. El Consejo, antes de aprobar los indicadores de desempeño a que se refiere el presente capítulo, los someterá a la consideración de la Secretaría de Planeación y que, en su caso, estime pertinentes. De no recibir observaciones, en un lapso de treinta días naturales, el Consejo procederá a realizar las evaluaciones que corresponda.\nArtículo 48. La evaluación de los programas y subprogramas se realizará de forma anual, definiendo como periodo del primero de julio al treinta y uno de julio, para que sus\nLey de Desarrollo Social para el Estado de Baja California. Página 16\n.\nActualización Legislativa.\nÚltima Reforma P.O. No. 37, Índice, 26-Jul-2024 las Reglas de Operación de los programas que le acompañan. Podrá también ser multianual en los casos que así se determine por autoridad competente.\nArtículo 49. El Reglamento determinará los tipos, plazos y modalidades que resulten necesarias para la plena evaluación de la Política Estatal de Desarrollo Social en su conjunto y la orientada a evaluar programas y subprogramas específicos.\nArtículo 50. Los resultados de las evaluaciones serán entregados a la Secretaría y a las Comisiones de Fiscalización del Gasto Público y de Desarrollo Social del Congreso del\nEstado por conducto del Órgano de Fiscalización Superior. Serán publicados en el Periódico\nOficial, en el portal de internet del Poder Ejecutivo y en los medios masivos de información.\nArtículo 51. De acuerdo con los resultados de las evaluaciones, el Consejo podrá emitir las sugerencias y recomendaciones que considere pertinentes a las dependencias y entidades de la administración pública estatal y municipal que tengan a su cargo programas sociales.\nTÍTULO V\nDEL SISTEMA ESTATAL DE DESARROLLO SOCIAL\nCAPÍTULO I\nDe su objeto e integración\nArtículo 52. El Sistema Estatal para el Desarrollo Social es el mecanismo de coordinación, concurrencia y ordenamiento de las acciones y programas federales, estatales y municipales, en los términos previstos en la Ley General.\nArtículo Reformado\nArtículo 53. El Sistema Estatal tiene como objeto:\nI. Coordinar el proceso de planeación, en sus niveles institucional, global, sectorial, regional y municipal, de las políticas, programas y acciones de los sectores público, social y privado, para impulsar el desarrollo social y la superación de la pobreza en la entidad de manera armónica, coordinada, complementaria y convenida, evitando la desarticulación, duplicidad y dispersión de esfuerzos;\nII. Coordinar la planeación de acciones de los sectores público, social y privado, para garantizar su participación institucional, solidaria y legal en las acciones y programas para el desarrollo social y superación de la pobreza en la entidad;\nIII. Coordinar el proceso de la planeación en sus etapas de formulación, instrumentación y ejecución de planes, programas y proyectos concertados entre los tres entidad;\nIV. Organizar sustantivamente el proceso de la planeación de la Política Estatal de\nDesarrollo Social, de acuerdo a la estrategia para el desarrollo social y superación de la pobreza definida por esta Ley; y\nLey de Desarrollo Social para el Estado de Baja California. Página 17\n.\nActualización Legislativa.\nÚltima Reforma P.O. No. 37, Índice, 26-Jul-2024\nV. Evaluar los resultados de los programas estatales, municipales y en general de las acciones en materia de desarrollo social, para sugerir su reorientación a las instancias estatales y municipales responsables de su ejecución.\nArtículo Reformado\nCAPÍTULO II\nDe su estructura\nArtículo 54. Forman la estructura del Sistema Estatal: la Comisión Estatal, el Consejo\nConsultivo, los Municipios, así como organismos y entidades del sector social de la economía y en general las dependencias y entidades del gobierno estatal que inciden en el desarrollo social en sus respectivos ámbitos de competencia.\nCAPÍTULO III\nDe la Comisión Estatal para el Desarrollo Social\nArtículo 55. La Comisión es un instrumento de coordinación de los programas, acciones e inversiones que para el cumplimiento de los objetivos, estrategias y prioridades de la Política Estatal de Desarrollo Social lleven a cabo, en el ámbito de sus competencias, las dependencias y entidades estatales, ya sea de manera directa o en concurrencia con gobiernos municipales y la Federación, o en concertación con los sectores social y privado.\nArtículo 56. La Comisión Estatal tiene por objeto la coordinación de los programas y proyectos que las autoridades lleven a cabo en el ámbito de sus respectivas competencias, para garantizar la integralidad y concurrencia en el diseño y ejecución de la Política Estatal de Desarrollo Social.\nArtículo 57. La Comisión Estatal estará integrada por:\nII. El titular de la Secretaría, quien fungirá como Coordinador Ejecutivo y suplirá al presidente en caso de ausencia;\nIII. Un Secretario Técnico designado por el presidente;\nIV. Los titulares de las secretarías de la administración pública estatal y los de las entidades paraestatales que determine el presidente;\nV. El Presidente de la Comisión de Desarrollo Social del Congreso del Estado;\nVI. Los ayuntamientos, representados por sus respectivos presidentes municipales; y\nLey de Desarrollo Social para el Estado de Baja California. Página 18\n.\nActualización Legislativa.\nÚltima Reforma P.O. No. 37, Índice, 26-Jul-2024\nVII. La persona que designe el Consejo Consultivo como representante, quien tendrá el carácter de honorario.\nArtículo 58. La Comisión Estatal celebrará dos sesiones ordinarias por año, en los términos que señale el reglamento. Se podrán celebrar sesiones extraordinarias, previa convocatoria de su Presidente.\nArtículo 59. Podrán participar en la Comisión Estatal los titulares o delegados de las dependencias y entidades de la administración pública federal, así como las demás personas que se estime necesario a invitación expresa del Presidente.\nArtículo 60. La Comisión Estatal estará facultada para atender la solicitud de colaboración de los sectores social y privado cuando se traten asuntos de su interés o competencia, y sus funciones son las siguientes:\nI. Proponer políticas públicas de desarrollo social con criterios de integralidad y transversalidad;\nII. Proponer criterios para la planeación y ejecución de las políticas y programas de desarrollo social en los ámbitos estatal y municipal;\nIII. Recomendar la celebración de convenios de coordinación y colaboración entre los tres órdenes de gobierno.\nIV. Proponer programas estatales, municipales y regionales, así como proyectos de inversión en el marco de la Política Estatal;\nV. Proponer acciones de capacitación para servidores públicos estatales, y municipales en materia de desarrollo social;\nVI. Plantear mecanismos de financiamiento y distribución de recursos estatales para el desarrollo social en los municipios;\nVII. Analizar y proponer esquemas alternativos de financiamiento para los programas de desarrollo social y superación de la pobreza;\nVIII. Revisar el marco normativo y, en su caso, recomendar modificaciones ante las instancias competentes; y\nIX. Las demás que establece esta ley, su reglamento y los ordenamientos legales aplicables.\nTÍTULO VI\nLey de Desarrollo Social para el Estado de Baja California. Página 19\n.\nActualización Legislativa.\nÚltima Reforma P.O. No. 37, Índice, 26-Jul-2024\nDE LOS PROGRAMAS Y ACCIONES PRIORITARIAS, DE LAS ZONAS DE ATENCIÓN\nPRIORITARIA Y DE LA DEFINICIÓN Y MEDICIÓN DE LA POBREZA.\nCAPÍTULO I\nDe los programas y acciones prioritarias\nArtículo 61. Son prioritarios y de interés público:\nI. Los programas de educación obligatoria;\nII. Las campañas de prevención y control de enfermedades transmisibles y los programas de atención médica;\nIII. Los programas dirigidos a las personas en condiciones de pobreza, marginación o en situación de vulnerabilidad;\nIV. Los programas dirigidos a zonas de atención prioritaria;\nV. Los programas y acciones públicas para asegurar la alimentación y nutrición materno-infantil;\nVI. Los programas de abasto social de productos básicos;\nVII. Los programas de vivienda, para tal efecto, el titular del Poder Ejecutivo del\nEstado, se coordinará con las autoridades federales competentes con el fin de implementar acciones de vivienda y obra social, entre dichas acciones se buscará comprender a aquellas que tengan por objeto otorgar casas abandonadas que hayan sido recuperadas por el\nInstituto del Fondo Nacional de la Vivienda para los Trabajadores, el Fondo de la Vivienda del Instituto de Seguridad y Servicios Sociales de los Trabajadores del Estado u otras instituciones dedicadas al otorgamiento de créditos para la vivenda.\nVIII. Los programas y fondos públicos destinados a la generación y conservación del empleo, a las actividades productivas sociales y a las empresas del sector social de la economía;\nFracción Reformada\nIX. Los programas y obras de infraestructura para agua potable, drenaje, electrificación, caminos y otras vías de comunicación, saneamiento ambiental y equipamiento urbano; y,\nFracción Reformada\nX. Los programas de apoyo económico y alimentario a mujeres en condiciones de pobreza y madres jefas de familia.\nFracción Adicionada\nArtículo Reformado\nArtículo 62. La distribución de los fondos de aportaciones federales y estatales, relativas a los programas sociales de educación, salud, alimentación, infraestructura social, equidad y transparencia, conforme a la normatividad aplicable.\nArtículo Reformado\nLey de Desarrollo Social para el Estado de Baja California. Página 20\n.\nActualización Legislativa.\nÚltima Reforma P.O. No. 37, Índice, 26-Jul-2024\nArtículo 63. La planeación, aplicación y distribución de los recursos destinados a financiar los programas de desarrollo social, estarán orientados a aumentar el gasto social per cápita, a la promoción de un desarrollo regional equilibrado y se basarán en los indicadores y lineamientos generales de eficacia, eficiencia y calidad en la prestación de los servicios.\nArtículo 64. El Congreso del Estado de conformidad con sus atribuciones, procurará que se destinen los recursos suficientes para financiar los Programas de Desarrollo Social\nEstatales.\nCAPITULO II\nDe las Zonas de Atención Prioritaria\nArtículo 65. Para efectos de la presente Ley y en la aplicación de los programas y política de desarrollo estatal y municipal, se considerarán como zonas de atención prioritaria, además de las así determinadas en los términos de la Ley General, las siguientes áreas, regiones o grupos que por su condición merecen especial atención en la elaboración, ejecución, seguimiento y evaluación de la Política de Desarrollo Social:\nI. Las regiones, municipios, micro regiones, polígonos y zonas de atención prioritaria e inmediata que muestren altos índices de marginación respecto de los objetivos de la Política de Desarrollo Social;\nII. La población que se encuentre en situación de pobreza o vulnerabilidad; incluidas las comunidades indígenas asentadas en el Estado, y\nIII. Los grupos ubicados en polígonos y zonas de riesgo considerando criterios demográficos y geofísicos para la definición de estrategias de prevención y atención a la población, con énfasis en aquellos asentamientos precarios y vulnerables que se encuentran bajo riesgo de desastres.\nArtículo Reformado\nArtículo 66. Para lograr una mejor asignación de recursos y una mayor eficiencia en el abatimiento de la pobreza y atención a grupos vulnerables, los programas, planes y acciones en materia de Desarrollo Social Estatal serán diseñados y puestos en práctica en situación de pobreza, así como de los territorios en los que ellos están localizados, entendidos estos como zonas de atención prioritaria.\nArtículo Reformado\nArtículo 67. Las zonas de atención prioritaria tendrán como referente las misma mediante la identificación de polígonos de pobreza.\nArtículo 68. Los programas de desarrollo social destinarán acciones y medidas específicas para atender a las zonas de atención prioritaria.\nLey de Desarrollo Social para el Estado de Baja California. Página 21\n.\nActualización Legislativa.\nÚltima Reforma P.O. No. 37, Índice, 26-Jul-2024\nPara su ejecución, el Estado asignará los recursos humanos, técnicos y financieros necesarios para lograr el desarrollo de las personas y las familias que forman parte de estas áreas.\nArtículo 69. La Secretaría, en coordinación con otras instituciones competentes, será responsable de elaborar y mantener actualizados los sistemas de información georeferenciados, que se relacionen con las condiciones sociales y económicas de los hogares\nBajacalifornianos, y permitan formular estrategias orientadas a la lucha contra la pobreza con el fin de lograr las metas propuestas en materia de Desarrollo Social.\nArtículo 70. Las acciones del Consejo, en las zonas de atención prioritaria tendrá como objeto:\nI. Lograr una mejor calidad y expectativas de vida personal, familiar y social a través de acciones educativas, proyectos productivos, fomento de la participación comunitaria y corresponsabilidad social que permitan crear conciencia de la dignidad humana;\nII. Generar un desarrollo social integral familiar y humano, así como beneficios para las generaciones presentes y futuras del Estado de Baja California;\nIII. Procurar que toda persona reciba los beneficios del desarrollo y de las políticas y programas de desarrollo social; y\nIV. Prever los recursos financieros necesarios para dar atención especial a los grupos de personas que por su situación de pobreza y vulnerabilidad la necesiten, promoviendo su plena integración al desarrollo y preservando y fortaleciendo en su favor la vigencia de los valores y principios de igualdad, equidad y libertad.\nCAPÍTULO III\nDe la definición y medición de la pobreza\nArtículo 71. La Secretaría y los Ayuntamientos deberán prestarse mutua colaboración institucional para el intercambio de información y la asesoría y transferencia de técnicas, así como a la recopilación de datos y presentación de informes para mejorar el conocimiento y la ordenación del desarrollo social en el Estado, atendiendo a la naturaleza multisectorial y multifactorial de la pobreza, que se encuentra relacionada con numerosos aspectos del desarrollo.\nArtículo 72. A efecto de establecer la definición, identificación y medición de la pobreza en el Estado, la Secretaría utilizará los lineamientos y criterios que sugiera el\nConsejo; independientemente de otros datos que estime conveniente.\nArtículo Reformado\nTÍTULO VII\nDE LA PARTICIPACIÓN SOCIAL, TRANSPARENCIA Y RENDICIÓN DE CUENTAS\nCAPÍTULO I\nDe la participación social\nLey de Desarrollo Social para el Estado de Baja California. Página 22\n.\nActualización Legislativa.\nÚltima Reforma P.O. No. 37, Índice, 26-Jul-2024\nArtículo 73. El Ejecutivo del Estado, a través de la Secretaría, y los Ayuntamientos en el ámbito de su competencia, fomentarán la participación de la sociedad de manera activa y corresponsable en la planeación, diseño, evaluación y supervisión de la Política de\nDesarrollo Social. De igual forma publicarán en sus portales de internet, información trascendente y adicional a que los obliga la Ley de Transparencia y Acceso a la Información\nPública para el Estado de Baja California.\nArtículo 74. Cualquier persona podrá hacer del conocimiento de la Secretaría, del\nConsejo o de la autoridad municipal, según corresponda, sobre aquellos grupos, familias o individuos que se hallen en situación de pobreza y vulnerabilidad en cualquiera de sus formas.\nArtículo 75. Los ciudadanos de Baja California podrán participar corresponsablemente en las políticas de desarrollo social, así como generar iniciativas de proyectos y programas.\nAsí mismo, los ciudadanos podrán presentar solicitudes de información en la materia, debiendo observar la autoridad dentro de los procedimientos de acceso a la información, el principio de máxima publicidad e instituciones como la prueba de daño.\nArtículo 76. Las Organizaciones podrán recibir y administrar recursos o fondos públicos para operar programas para el desarrollo social, quedando sujetas a la supervisión y vigilancia de la Secretaria y de los Ayuntamientos según sea el caso, sin perjuicio de las facultades de fiscalización que correspondan al Congreso del Estado.\nArtículo 77. El Ejecutivo del Estado, a través de la Secretaría, fomentará el apoyo a la organización, promoción y participación social mediante:\nI. La creación de condiciones que estimulen la realización de programas, estrategias y orientación de recursos;\nII. La regulación de mecanismos transparentes de información, coordinación, concertación, participación y consulta de la información pública que permita vincular los programas, estrategias y recursos para el Desarrollo Social;\nIII. El establecimiento de procedimientos documentados, ágiles y sencillos; y\nIV. El otorgamiento de constancias, apoyos, estímulos públicos, asesoría y capacitación para implementar programas y proyectos para el desarrollo social.\nCAPÍTULO II\nDe la denuncia popular\nArtículo 78. La denuncia popular es la facultad individual y colectiva que poseen las personas, de recurrir ante el órgano competente a interponer toda queja o denuncia contra todo hecho, acto u omisión que atente en contra de los sujetos beneficiarios de esta ley.\nArtículo Reformado\nLey de Desarrollo Social para el Estado de Baja California. Página 23\n.\nActualización Legislativa.\nÚltima Reforma P.O. No. 37, Índice, 26-Jul-2024\nArtículo 79. La Dirección de Control y Evaluación Gubernamental del Ejecutivo del\nEstado es el órgano competente para conocer de las quejas y denuncias ciudadanas en materia de desarrollo social y las resoluciones que emita en favor o en contra se realizará en los términos y con los requisitos que establece la normativa aplicable.\nArtículo 80. Toda persona física o moral podrá presentar denuncia ante la autoridad competente sobre cualquier hecho, acto u omisión, que produzca o pueda producir daños al ejercicio de los derechos establecidos en esta Ley o contravengan sus disposiciones y de los demás ordenamientos que regulen materias relacionadas con el desarrollo social.\nArtículo 81. La denuncia popular podrá ejercitarse por cualquier persona, bastando que se presente por escrito y contenga:\nI. El nombre o razón social, domicilio y demás datos que permitan la identificación del denunciante y, en su caso, de su representante legal;\nII. Los actos, hechos u omisiones denunciados;\nIII. Los datos que permitan identificar a la presunta autoridad infractora; y\nIV. Las pruebas que en su caso ofrezca el denunciante.\nArtículo 82. La interposición de las quejas y denuncias obligan a la autoridad competente a responder por escrito de conformidad con la normativa aplicable.\nCAPÍTULO III\nDe la Contraloría Social\nArtículo 83. Se reconoce a la contraloría social como el mecanismo de los beneficiarios, de manera organizada para el cumplimiento de las metas y la correcta aplicación de los recursos públicos asignados a los programas de desarrollo social.\nArtículo 84. Son principios de la contraloría social:\nI. Respeto y libertad de organización de la población: sin distinción de clases sociales, políticas, religiosas o de cualquier otro tipo.\nII. Participación organizada de la comunidad: para asegurar que la inversión se destine a alcanzar los objetivos y metas previstos en condiciones de economía, eficiencia y eficacia.\nIII. Corresponsabilidad entre Gobierno y sociedad civil: que requiere ser fortalecida para lograr la solución de los problemas más graves de las mayorías.\nIV. Propiciar transparencia, honestidad y eficiencia: en la administración de los recursos humanos, materiales, financieros,\nArtículo 85. Las autoridades competentes para la aplicación de esta ley, impulsarán\nLey de Desarrollo Social para el Estado de Baja California. Página 24\n.\nActualización Legislativa.\nÚltima Reforma P.O. No. 37, Índice, 26-Jul-2024 municipales, los cuales contendrán las medidas necesarias para que sea ejercida plenamente la función de contraloría social, conforme a lo establecido en los Lineamientos\nNormativos y Operativos para el Ejercicio Ciudadano de la Contraloría Social.\nArtículo 86. Son funciones de la contraloría social:\nI. Solicitar información a las autoridades estatales y municipales responsables de los programas sociales que considere necesaria para el desempeño de sus funciones;\nII. Vigilar el ejercicio de los recursos públicos y la aplicación de los programas sociales, conforme a la ley;\nIII. Emitir informes sobre el desempeño de los programas sociales y la ejecución de los recursos públicos;\nIV. Atender e investigar las quejas y denuncias presentadas sobre la aplicación de los recursos y la ejecución de los programas sociales; y\nV. Presentar ante la autoridad competente, las quejas y denuncias que puedan constituir responsabilidades administrativas, civiles o penales relacionadas con los programas sociales.\nArtículo 87. Las autoridades competentes en materia de desarrollo social promoverán y facilitarán el libre acceso a la información a los ciudadanos y organizaciones civiles en ejercicio de las diversas modalidades de contraloría social y promoverán la capacitación necesaria para el cumplimiento de sus funciones, destinando los recursos necesarios para ello.\nArtículo 88. Los contralores sociales de los programas y acciones de desarrollo social, ejercerán su derecho a ser capacitados para el mejor desempeño de sus funciones.\nCon ese propósito, el órgano de control y evaluación del Ejecutivo Estatal y el Órgano de\nFiscalización Superior de manera conjunta o por separado, realizarán al menos dos encuentros anuales de carácter estatal en los que se informe, capacite y proporcione documentación, instructivos, manuales y formatos para el mejor cumplimiento de sus funciones. La organización de los encuentros y los gastos operativos en que se incurra, serán a cuenta de la Secretaría.\nArtículo 89. Los encuentros de contralores sociales a que se refiere el artículo anterior, se realizarán:\nI. Durante los siguientes treinta días de aprobado por el Congreso del Estado el\nII. Durante los siguientes treinta días de conocidos los resultados de las evaluaciones a que se refiere el artículo 50 de esta Ley.\nArtículo 90. Las autoridades competentes darán el debido cumplimiento a lo social en materia de impulso de la contraloría social.\nTÍTULO VIII\nLey de Desarrollo Social para el Estado de Baja California. Página 25\n.\nActualización Legislativa.\nÚltima Reforma P.O. No. 37, Índice, 26-Jul-2024\nDE LA PUBLICACIÓN Y PUBLICIDAD DE LOS PROGRAMAS DE DESARROLLO\nSOCIAL\nCAPÍTULO I\nDe la publicación\nArtículo 91. El Ejecutivo del Estado, al tener aprobado su presupuesto de egresos, deberá publicar en el Periódico Oficial y en el portal de internet de la Secretaría, las reglas de operación de los programas de desarrollo social estatales, así como, la distribución que se haga de los recursos federales para el desarrollo social, ello una vez que el gobierno federal haga la publicación correspondiente en los términos de la Ley General, en un plazo máximo de 30 días.\nArtículo 92. Los Ayuntamientos, en el mismo plazo que señala el artículo anterior, deberán enviar para su publicación en el Periódico Oficial, los programas de desarrollo social de los que puedan ser beneficiados sus habitantes, así como el monto y la distribución de los recursos que les fueron entregados para la implementación de estos programas. En el mismo plazo publicarán dicha información en sus portales de internet.\nArtículo 93. Además de las obligaciones que señalan los artículos anteriores, el\nEjecutivo del Estado y los Ayuntamientos implementarán campañas de difusión masiva para que toda la población se entere del contenido, reglas de operación y beneficios de los programas de desarrollo social que se aplican en el estado de Baja California.\nCAPÍTULO II\nDe la publicidad\nArtículo 94. La publicidad e información relativa a los programas de desarrollo social estatales o municipales deberán identificarse con el escudo oficial de la o de las instituciones participantes, en los términos que señalen las leyes y reglamentos en la materia y tendrá la siguiente leyenda: “Este programa es público, ajeno a cualquier partido político. Queda prohibido su uso para fines distintos al desarrollo social”.\nArtículo Reformado\nArtículo 95. Cuando en un municipio exista población indígena, las autoridades competentes deberán difundir en su lengua o dialecto el contenido, las reglas de operación y\nMunicipio.\nArtículo 96. La Secretaría publicará en sistema braile los programas de desarrollo social en los pueda ser beneficiada una persona con discapacidad visual, de igual forma, con discapacidad auditiva.\nTÍTULO IX\nINFRACCIONES, SANCIONES Y RECURSOS\nCAPÍTULO I\nLey de Desarrollo Social para el Estado de Baja California. Página 26\n.\nActualización Legislativa.\nÚltima Reforma P.O. No. 37, Índice, 26-Jul-2024\nDe las infracciones y sanciones\nArtículo 97. El beneficiario que contravenga las disposiciones de la presente Ley o de la normatividad de algún programa, independientemente de lo dispuesto por otros ordenamientos jurídicos, podrá ser suspendido de manera temporal o definitiva del padrón de beneficiarios.\nArtículo 98. Las infracciones a lo dispuesto en esta Ley por servidores públicos estatales o municipales serán sancionadas de conformidad con lo establecido en la Ley de\nResponsabilidades de los Servidores Públicos del Estado de Baja California. En el caso de que fuesen cometidas por particulares, serán investigadas y sancionadas en términos de la legislación que résulte aplicable.\nCAPÍTULO II\nDel Recurso de Revocación\nArtículo 99. Los afectados por los actos o resoluciones definitivas dictadas con motivo de la aplicación de esta Ley, su Reglamento y ordenamientos que de ella emanen, podrán interponer el recurso de revocación previsto en la Ley del Procedimiento para los\nActos de la Administración Pública del Estado de Baja California.\nARTÍCULOS TRANSITORIOS\nARTÍCULO PRIMERO.- La presente Ley entrará en vigor sesenta días naturales posteriores al de su publicación en el Periódico Oficial del Estado de Baja California.\nARTÍCULO SEGUNDO.- Se derogan todas las disposiciones legales de igual o menor jerarquía que se contraponga a la presente Ley.\nARTÍCULO TERCERO.- El titular del Poder Ejecutivo del Estado deberá expedir los\nReglamentos que deriven de esta Ley, dentro de los sesenta días naturales siguientes a la entrada en vigor del presente ordenamiento.\nARTÍCULO CUARTO.- La Comisión Estatal de Desarrollo Social deberá instalarse dentro de los noventa días naturales a partir de la entrada en vigor de esta Ley. del Estado de Baja California, en la Ciudad de Mexicali, B.C., a los diez días del mes de septiembre del año dos mil quince.\nDIP. JULIO CÉSAR VÁZQUEZ CASTILLO\nPRESIDENTE\n(RÚBRICA)\nDIP. RODOLFO OLIMPO HERNÁNDEZ BOJÓRQUEZ\nSECRETARIO\nLey de Desarrollo Social para el Estado de Baja California. Página 27\n.\nActualización Legislativa.\nÚltima Reforma P.O. No. 37, Índice, 26-Jul-2024\n(RÚBRICA)\nDE CONFORMIDAD CON LO DISPUESTO POR LA FRACCION I DEL ARTÍCULO 49\nMEXICALI, BAJA CALIFORNIA, A LOS DIECISIETE DÍAS DEL MES DE\nSEPTIEMBRE DEL AÑO DOS MIL QUINCE.\nFRANCISCO ARTURO VEGA DE LAMADRID\nGOBERNADOR DEL ESTADO\n(RÚBRICA)\nFRANCISCO RUEDA GOMEZ\nSECRETARIO GENERAL DE GOBIERNO\n(RÚBRICA)\nLey de Desarrollo Social para el Estado de Baja California. Página 28\n.\nActualización Legislativa.\nÚltima Reforma P.O. No. 37, Índice, 26-Jul-2024\nArtículo 1.- Fue reformado por Decreto No. 652, publicado en el Periódico Oficial No.\n47, Sección V, de fecha 28 de octubre de 2016, Tomo CXXIII, expedido por la H. XXI\nLegislatura, siendo Gobernador Constitucional el C. Francisco Arturo Vega de Lamadrid\n2013-2019;\nArtículo 2.- Fue reformado por Decreto No. 652, publicado en el Periódico Oficial No.\n47, Sección V, de fecha 28 de octubre de 2016, Tomo CXXIII, expedido por la H. XXI\nLegislatura, siendo Gobernador Constitucional el C. Francisco Arturo Vega de Lamadrid\n2013-2019;\nArtículo 3.- Fue reformado por Decreto No. 652, publicado en el Periódico Oficial No.\n47, Sección V, de fecha 28 de octubre de 2016, Tomo CXXIII, expedido por la H. XXI\nLegislatura, siendo Gobernador Constitucional el C. Francisco Arturo Vega de Lamadrid\n2013-2019;\nArtículo 4.- Fue reformado por Decreto No. 652, publicado en el Periódico Oficial No.\n47, Sección V, de fecha 28 de octubre de 2016, Tomo CXXIII, expedido por la H. XXI\nLegislatura, siendo Gobernador Constitucional el C. Francisco Arturo Vega de Lamadrid\n2013-2019;\nArtículo 6.- Fue reformado por Decreto No. 652, publicado en el Periódico Oficial No.\n47, Sección V, de fecha 28 de octubre de 2016, Tomo CXXIII, expedido por la H. XXI\nLegislatura, siendo Gobernador Constitucional el C. Francisco Arturo Vega de Lamadrid\n2013-2019;\nArtículo 7.- Fue reformado por Decreto No. 652, publicado en el Periódico Oficial No.\n47, Sección V, de fecha 28 de octubre de 2016, Tomo CXXIII, expedido por la H. XXI\nLegislatura, siendo Gobernador Constitucional el C. Francisco Arturo Vega de Lamadrid\n2013-2019;\nArtículo 14.- Fue reformado por Decreto No. 652, publicado en el Periódico Oficial No.\n47, Sección V, de fecha 28 de octubre de 2016, Tomo CXXIII, expedido por la H. XXI\nLegislatura, siendo Gobernador Constitucional el C. Francisco Arturo Vega de Lamadrid\n2013-2019;\nArtículo 18.- Fue reformado por Decreto No. 652, publicado en el Periódico Oficial No.\n47, Sección V, de fecha 28 de octubre de 2016, Tomo CXXIII, expedido por la H. XXI\nLegislatura, siendo Gobernador Constitucional el C. Francisco Arturo Vega de Lamadrid\n2013-2019;\nArtículo 24.- Fue reformado por Decreto No. 446, publicado en el Periódico Oficial No. siendo Gobernadora Constitucional la C. Marina del Pilar Ávila Olmeda 2021-2027;\nArtículo 34.- Fue reformado por Decreto No. 652, publicado en el Periódico Oficial No.\nLegislatura, siendo Gobernador Constitucional el C. Francisco Arturo Vega de Lamadrid\n2013-2019;\nLey de Desarrollo Social para el Estado de Baja California. Página 29\n.\nActualización Legislativa.\nÚltima Reforma P.O. No. 37, Índice, 26-Jul-2024\nArtículo 36.- Fue reformado por Decreto No. 652, publicado en el Periódico Oficial No.\n47, Sección V, de fecha 28 de octubre de 2016, Tomo CXXIII, expedido por la H. XXI\nLegislatura, siendo Gobernador Constitucional el C. Francisco Arturo Vega de Lamadrid\n2013-2019;\nArtículo 38.- Fue reformado por Decreto No. 652, publicado en el Periódico Oficial No.\n47, Sección V, de fecha 28 de octubre de 2016, Tomo CXXIII, expedido por la H. XXI\nLegislatura, siendo Gobernador Constitucional el C. Francisco Arturo Vega de Lamadrid\n2013-2019;\nArtículo 52.- Fue reformado por Decreto No. 652, publicado en el Periódico Oficial No.\n47, Sección V, de fecha 28 de octubre de 2016, Tomo CXXIII, expedido por la H. XXI\nLegislatura, siendo Gobernador Constitucional el C. Francisco Arturo Vega de Lamadrid\n2013-2019;\nArtículo 53.- Fue reformado por Decreto No. 652, publicado en el Periódico Oficial No.\n47, Sección V, de fecha 28 de octubre de 2016, Tomo CXXIII, expedido por la H. XXI\nLegislatura, siendo Gobernador Constitucional el C. Francisco Arturo Vega de Lamadrid\n2013-2019;\nArtículo 61.- Fue reformado por Decreto No. 157, publicado en el Periódico Oficial No.\n04, Sección IV, de fecha 19 de enero de 2018, Tomo CXXV, expedido por la H. XXII\nLegislatura, siendo Gobernador Constitucional el C. Francisco Arturo Vega de Lamadrid\n2013-2019; fue reformado por Decreto No. 447, publicado en el Periódico Oficial No. 37, Índice, de fecha 26 de julio de 2024, Tomo CXXXI, expedido por la H. XXIV Legislatura, siendo Gobernadora Constitucional la C. Marina del Pilar Ávila Olmeda 2021-2027;\nArtículo 62.- Fue reformado por Decreto No. 652, publicado en el Periódico Oficial No.\n47, Sección V, de fecha 28 de octubre de 2016, Tomo CXXIII, expedido por la H. XXI\nLegislatura, siendo Gobernador Constitucional el C. Francisco Arturo Vega de Lamadrid\n2013-2019;\nArtículo 65.- Fue reformado por Decreto No. 652, publicado en el Periódico Oficial No.\n47, Sección V, de fecha 28 de octubre de 2016, Tomo CXXIII, expedido por la H. XXI\nLegislatura, siendo Gobernador Constitucional el C. Francisco Arturo Vega de Lamadrid\n2013-2019;\nArtículo 66.- Fue reformado por Decreto No. 652, publicado en el Periódico Oficial No.\nLegislatura, siendo Gobernador Constitucional el C. Francisco Arturo Vega de Lamadrid\n2013-2019;\nArtículo 72.- Fue reformado por Decreto No. 652, publicado en el Periódico Oficial No.\nLegislatura, siendo Gobernador Constitucional el C. Francisco Arturo Vega de Lamadrid\n2013-2019;\nArtículo 78.- Fue reformado por Decreto No. 652, publicado en el Periódico Oficial No.\nLey de Desarrollo Social para el Estado de Baja California. Página 30\n.\nActualización Legislativa.\nLegislatura, siendo Gobernador Constitucional el C. Francisco Arturo Vega de Lamadrid\n2013-2019;\nArtículo 94.- Fue reformado por Decreto No. 652, publicado en el Periódico Oficial No.\nLegislatura, siendo Gobernador Constitucional el C. Francisco Arturo Vega de Lamadrid\n2013-2019;\nLey de Desarrollo Social para el Estado de Baja California. Página 31\n.\nActualización Legislativa.\nÚltima Reforma P.O. No. 37, Índice, 26-Jul-2024\nARTÍCULO ÚNICO TRANSITORIO DEL DECRETO No. 652, POR EL QUE SE\nREFORMAN LOS ARTÍCULOS 1, 2, 3, 4, 6, 7, 14, 18, 34, 36, 38, 52, 53, 62, 65, 66, 72, 78 y\n94; PUBLICADO EN EL PERIÓDICO OFICIAL No. 48, SECCIÓN V, TOMO CXXIII, DE\nFECHA 28 DE OCTUBRE DE 2016, EXPEDIDO POR LA H. XXI LEGISLATURA, SIENDO\nGOBERNADOR CONSTITUCIONAL EL C. FRANCISCO ARTURO VEGA DE LAMADRID\n2013-2019.\nARTÍCULO TRANSITORIO\nÚNICO.- Las presentes reformas entrarán en vigor al día siguiente al de su publicación en el Periódico Oficial del Estado de Baja California.\nDADO en el Salón de Sesiones “Lic. Benito Juárez García” del H. Poder Legislativo del Estado de Baja California, en la Ciudad de Mexicali, B.C., a los veintidós días del mes de septiembre del año dos mil dieciséis.\nDIP. MÓNICA BEDOYA SERNA\nPRESIDENTA\n(RÚBRICA)\nDIP. ROSA ISELA PERALTA CASILLAS\nSECRETARIA\n(RÚBRICA)\nDE CONFORMIDAD CON LO DISPUESTO POR LA FRACCIÓN I DEL ARTÍCULO 49\nMEXICALI, BAJA CALIFORNIA, A LOS TRES DÍAS DEL MES DE OCTUBRE DEL\nAÑO DOS MIL DIECISÉIS.\nFRANCISCO ARTURO VEGA DE LAMADRID\nGOBERNADOR DEL ESTADO\n(RÚBRICA)\nFRANCISCO RUEDA GOMEZ\nSECRETARIO GENERAL DE GOBIERNO\n(RÚBRICA)\nLey de Desarrollo Social para el Estado de Baja California. Página 32\n.\nActualización Legislativa.\nÚltima Reforma P.O. No. 37, Índice, 26-Jul-2024\nARTÍCULO ÚNICO TRANSITORIO DEL DECRETO No. 157, POR EL QUE SE\nREFORMAN LA FRACCIÓN VII, DEL ARTÍCULO 61; PUBLICADO EN EL PERIÓDICO\nOFICIAL No. 04, SECCIÓN IV, TOMO CXXV, DE FECHA 19 DE ENERO DE 2018,\nEXPEDIDO POR LA H. XXII LEGISLATURA, SIENDO GOBERNADOR CONSTITUCIONAL\nEL C. FRANCISCO ARTURO VEGA DE LAMADRID 2013-2019.\nARTÍCULO TRANSITORIO\nÚNICO.- La presente reforma entrará en vigor al día siguiente de su publicación en el\nPeriódico Oficial del Estado de Baja California.\nDADO en el Salón de Sesiones “Lic. Benito Juárez García” del H. Poder Legislativo del Estado de Baja California, en la Ciudad de Mexicali, B.C., a los nueve días del mes de noviembre del año dos mil diecisiete.\nDIP. EDGAR BENJAMÍN GÓMEZ MACÍAS\nPRESIDENTE\n(RÚBRICA)\nDIP. EVA MARÍA VÁSQUEZ HERNÁNDEZ\nSECRETARIA\n(RÚBRICA)\nDE CONFORMIDAD CON LO DISPUESTO POR LA FRACCIÓN I DEL ARTÍCULO 49\nMEXICALI, BAJA CALIFORNIA, A LOS QUINCE DÍAS DEL MES DE ENERO DEL\nAÑO DOS MIL DIECIOCHO.\nFRANCISCO ARTURO VEGA DE LAMADRID\nGOBERNADOR DEL ESTADO\n(RÚBRICA)\nFRANCISCO RUEDA GÓMEZ\nSECRETARIO GENERAL DE GOBIERNO\n(RÚBRICA)\nARTÍCULO ÚNICO TRANSITORIO DEL DECRETO No. 446, POR EL QUE SE\nAPRUEBA LA REFORMA AL ARTÍCULO 24, PUBLICADDO EN EL PERIÓDICO OFICIAL\nXXIV LEGISLATURA, SIENDO GOBERNADORA CONSTITUCIONAL LA C. MARINA DEL\nPILAR ÁVILA OLMEDA 2021-2027.\nLey de Desarrollo Social para el Estado de Baja California. Página 33\n.\nActualización Legislativa.\nÚltima Reforma P.O. No. 37, Índice, 26-Jul-2024\nTRANSITORIO\nPRIMERO.- El presente Decreto entrará en vigor al día siguiente de su publicación en el\nPeriódico Oficial del Estado de Baja California.\nSEGUNDO.- La aplicación de esta política social estará sujeta para su implementación a la disponibilidad presupuestal, debiendo preverse en el presupuesto de egresos las partidas conducentes.\nDADO en Sesión Ordinaria de la XXIV Legislatura en la Ciudad de Mexicali, B.C., a los veintisiete días del mes de junio del año dos mil veinticuatro.\nDIP. RAMÓN VÁZQUEZ VALADEZ\nPRESIDENTE\n(RÚBRICA)\nDIP. MANUEL GUERRERO LUNA\nSECRETARIO\n(RÚBRICA)\nDE CONFORMIDAD CON LO DISPUESTO POR LA FRACCIÓN I DEL ARTÍCULO 49\nCALIFORNIA, IMPRÍMASE Y PUBLÍQUESE.\nMEXICALI, BAJA CALIFORNIA, A LOS TRES DÍAS DEL MES DE JULIO DEL AÑO\nDOS MIL VEINTICUATRO.\nMARINA DEL PILAR ÁVILA OLMEDA\nGOBERNADORA DEL ESTADO\nDE BAJA CALIFORNIA\n(RÚBRICA)\nALFREDO ÁLVAREZ CÁRDENAS\nSECRETARIO GENERAL DE GOBIERNO\nDEL ESTADO DE BAJA CALIFORNIA\n(RÚBRICA)\nARTÍCULO ÚNICO TRANSITORIO DEL DECRETO No. 447, POR EL QUE SE\nAPRUEBA LA REFORMA AL ARTÍCULO 61, PUBLICADDO EN EL PERIÓDICO OFICIAL\nXXIV LEGISLATURA, SIENDO GOBERNADORA CONSTITUCIONAL LA C. MARINA DEL\nPILAR ÁVILA OLMEDA 2021-2027.\nLey de Desarrollo Social para el Estado de Baja California. Página 34\n.\nActualización Legislativa.\nÚltima Reforma P.O. No. 37, Índice, 26-Jul-2024\nTRANSITORIOS\nPRIMERO.- El presente decreto entrará en vigor al día siguiente de su publicación en el\nPeriódico Oficial del Estado de Baja California.\nSEGUNDO.- La aplicación de esta política social estará sujeta para su implementación a la disponibilidad o viabilidad financiera correspondiente, debiendo preverse en el presupuesto de egresos las partidas conducentes.\nDADO en Sesión Ordinaria de la XXIV Legislatura en la Ciudad de Mexicali, B.C., a los veintisiete días del mes de junio del año dos mil veinticuatro.\nDIP. RAMÓN VÁZQUEZ VALADEZ\nPRESIDENTE\n(RÚBRICA)\nDIP. MANUEL GUERRERO LUNA\nSECRETARIO\n(RÚBRICA)\nDE CONFORMIDAD CON LO DISPUESTO POR LA FRACCIÓN I DEL ARTÍCULO 49\nCALIFORNIA, IMPRÍMASE Y PUBLÍQUESE.\nMEXICALI, BAJA CALIFORNIA, A LOS DOS DÍAS DEL MES DE JULIO DEL AÑO\nDOS MIL VEINTICUATRO.\nMARINA DEL PILAR ÁVILA OLMEDA\nGOBERNADORA DEL ESTADO\nDE BAJA CALIFORNIA\n(RÚBRICA)\nALFREDO ÁLVAREZ CÁRDENAS\nSECRETARIO GENERAL DE GOBIERNO\nDEL ESTADO DE BAJA CALIFORNIA\n(RÚBRICA)\nLey de Desarrollo Social para el Estado de Baja California. Página 35",
  "ordenamiento": "REGLAMENTO",
  "jurisdiccion": "BAJA CALIFORNIA",
  "fuente_oficial": "Periódico Oficial",
  "FECHA PER OFIC": "2024/07/26",
  "ESTATUS": "VIGENTE",
  "TOMO": "TOMO_VI",
  "URL": "https://www.congresobc.gob.mx/Documentos/ProcesoParlamentario/Leyes/TOMO_VI/20240726_LEYDESOE.PDF",
  "es_escaneado": false,
  "tiene_tablas": false,
  "materia": [
    "social",
    "salud",
    "educación",
    "cultura"
  ]
}