{
  "titulo": "Ley DE EDUCACIÓN DEL ESTADO DE BAJA CALIFORNIA",
  "Contenido": "Sección X, Tomo CXXVII\nTÍTULO PRIMERO\nDel Derecho a la Educación\nCapítulo I\nDisposiciones Generales\nArtículo 1. La presente Ley garantiza el derecho a la educación reconocido en el artículo 3o. de la Constitución Política de los Estados Unidos Mexicanos, en los Tratados\nInternacionales de los que el Estado Mexicano sea parte y en la Constitución Política del bienestar de todas las personas. Sus disposiciones son de orden público, interés social y de observancia general en todo el Estado.\nSu objeto es regular la educación impartida en el Estado de Baja California, por parte de la autoridad educativa estatal, sus Organismos Descentralizados, los Municipios y los particulares con autorización o con reconocimiento de validez oficial de estudios, la cual se considera un servicio público y estará sujeto a la rectoría del Estado en términos de la\nConstitución del Estado, los principios contenidos en la presente Ley, los reglamentos y demás disposiciones que emanen de estas, así como los convenios en materia de educación que acuerde el Estado.\nArtículo 2. La autoridad educativa estatal fomentará la participación de los educandos, madres y padres de familia o tutores, maestras y maestros, así como de los distintos actores involucrados en el proceso educativo y, en general, de todo el Sistema\nEducativo Estatal, para asegurar que éste extienda sus beneficios a todos los sectores sociales y regiones del Estado, a fin de garantizar que todas las personas reciban las mismas oportunidades de acceso a la educación, desde la inicial hasta la profesional, ofrecerá a las personas las mismas oportunidades de aprendizaje, así como de acceso, tránsito, permanencia, avance académico y, en su caso, egreso oportuno en el Sistema\nEducativo Estatal, con sólo satisfacer los requisitos que establezcan las instituciones educativas con base en las disposiciones aplicables.\nArtículo 3. La aplicación y la vigilancia de la observancia de esta Ley corresponde al\nEjecutivo del Estado por conducto de las autoridades educativas Estatal y Municipal.\nPara efectos de la presente Ley, se entenderá por:\nLey de Educación del Estado de Baja California. Página 1\nI. Autoridad Educativa Federal: a la Secretaría de Educación Pública de la\nAdministración Pública Federal;\nII. Autoridad Educativa Estatal: a la Secretaría de Educación del Estado de Baja\nCalifornia;\nIII. Autoridad Educativa Municipal: al Ayuntamiento de cada Municipio del Estado;\nIV. Autoridades Educativas del Estado: a la autoridad educativa estatal, autoridad educativa municipal, los organismos públicos descentralizados;\nV. Autoridades escolares: al personal que lleva a cabo funciones de dirección, inspección o supervisión en los sectores, zonas o centros escolares;\nVI. Estado: al Estado de Baja California;\nVII. Ejecutivo Estatal: al Gobernador del Estado de Baja California;\nVIII. Ley: Ley de Educación del Estado de Baja California, y\nIX. Ley General: Ley General de Educación.\nArtículo 4. La autoridad educativa estatal y municipal, en el ámbito de su competencia, podrán establecer convenios de coordinación interestatal e intermunicipal para el desarrollo de proyectos regionales educativos que contribuyan a los principios y fines establecidos en esta Ley.\nPara tal efecto, la autoridad educativa, remitirá al Congreso del Estado y al Cabildo\nMunicipal, respectivamente, un informe sobre el proyecto regional a desarrollar, así como de los avances y resultados obtenidos desde su implementación hasta la conclusión del mismo.\nArtículo 5. Para el cumplimiento de los fines y criterios previstos en esta Ley y de conformidad con las necesidades de la población en su contexto local, contextual y situacional del proceso de enseñanza y aprendizaje, la autoridad educativa estatal podrá llevar a cabo una regionalización en la prestación del servicio público educativo, garantizando a las personas el acceso a una educación con inclusión, equidad y excelencia.\nArtículo 6. La autoridad educativa estatal y municipal, prestarán servicios educativos con inclusión, equidad y excelencia a través de los lineamientos de la nueva escuela mexicana. Las medidas que adopten para tal efecto estarán dirigidas, de manera prioritaria, a quienes pertenezcan a grupos y regiones con mayor rezago educativo, dispersos o que\nLey de Educación del Estado de Baja California. Página 2 socioeconómico, físico, mental, de identidad cultural, origen étnico o nacional, situación migratoria o bien, relacionadas con aspectos de género, preferencia sexual o prácticas culturales.\nPara tal efecto realizarán entre otras, las siguientes acciones:\nI. Establecer políticas incluyentes, transversales y con perspectiva de género, para otorgar becas, apoyos y estímulos económicos que prioricen a los educandos de excelencia académica o con alguna discapacidad y estudiantes destacados en la cultura, deporte o que enfrenten condiciones socioeconómicas que les impidan ejercer su derecho a la educación básica y media superior;\nSentencia de Acción de Inconstitucionalidad 18/2021\nFracción Reformada\nII. Establecer de acuerdo con la suficiencia presupuestal, programas de entrega gratuita de uniformes y útiles escolares, calzado, anteojos y productos sanitarios de gestión menstrual para las niñas, mujeres y personas menstruantes, estudiantes de educación básica, que funcionará de acuerdo a las normas y lineamientos de operación que la autoridad educativa estatal, municipal y los organismos descentralizados emitan, en el ámbito de su competencia; de igual manera, el Ejecutivo deberá cuidar que no exista discriminación o interrupción del servicio educativo para aquellos que no puedan o no cuenten con los recursos para adquirir uniformes. Ninguna alumna ni alumno podrá ser condicionado por su vestimenta;\nFracción Reformada\nIII. Proporcionar apoyos a educandos cuya madre, padre o tutor haya fallecido o sufrido algún accidente que le ocasione invalidez o incapacidad permanente;\nIV. Garantizar el acceso a los servicios educativos a las víctimas y promover su permanencia en el sistema educativo estatal cuando como consecuencia de algún delito o violación de sus derechos humanos exista interrupción en los estudios;\nV. Promover la instalación de aires acondicionados en aulas de los planteles educativos que, por sus condiciones climáticas, lo requieran;\nVI. Impulsar, en coordinación con las autoridades en la materia, programas de acceso gratuito a eventos culturales para educandos en vulnerabilidad social;\nVII. Apoyar conforme a las disposiciones que, para tal efecto emitan las autoridades educativas competentes, a estudiantes de educación media superior y de educación superior académico en el país o en el extranjero;\nLey de Educación del Estado de Baja California. Página 3\nVIII. Otorgarán facilidades de acceso, reingreso o permanencia a educandos adolescentes y jóvenes que se conviertan en madres o padres, con el propósito de que concluyan su educación, además de celebrar convenios para que las instituciones que estudiantes que lo requieran, con el objeto de que no interrumpan o abandonen sus estudios;\nFracción Reformada\nIX. Dar a conocer y, en su caso, fomentar diversas opciones educativas, como la educación abierta y a distancia, mediante el aprovechamiento de las plataformas digitales, la televisión educativa y las tecnologías de la información, comunicación, conocimiento y aprendizaje digital;\nX. Celebrar convenios de colaboración interinstitucional con las autoridades de los tres órdenes de gobierno, a fin de impulsar acciones que mejoren las condiciones de vida de los educandos, con énfasis en las de carácter alimentario, para que las niñas y niños en Baja\nCalifornia tengan acceso a una alimentación sana y de calidad mediante un desayuno caliente diario en escuelas públicas de nivel básico del Estado, preferentemente en aquellas escuelas que lo necesiten, conforme a los índices de pobreza, marginación y condición alimentaria;\nXl. Fomentar programas de incentivos dirigidos a las maestras y los maestros que presten sus servicios en localidades aisladas, zonas urbanas marginadas y de alta conflictividad social, para fomentar el arraigo en sus comunidades y cumplir con el calendario escolar;\nXII. Establecer, de forma gradual y progresiva de acuerdo con la suficiencia presupuestal, escuelas con horario completo en educación básica, con jornadas de entre 6 y\n8 horas diarias, para promover un mejor aprovechamiento del tiempo disponible, generar un mayor desempeño académico y desarrollo integral de los educandos;\nXIII. Facilitar el acceso a la educación básica y media superior, previo cumplimiento de los requisitos que para tal efecto se establezcan, aun cuando los solicitantes carezcan de documentos académicos o de identidad; esta obligación se tendrá por satisfecha con el ofrecimiento de servicios educativos;\nXIV. Las autoridades educativas ofrecerán opciones que faciliten la obtención de los competentes para la obtención de los documentos de identidad, asimismo, en el caso de la educación básica y media superior, se les ubicará en el nivel y grado que corresponda, conforme a la edad, el desarrollo cognitivo, la madurez emocional y, en su caso, los conocimientos que demuestren los educandos mediante la evaluación correspondiente.\nLey de Educación del Estado de Baja California. Página 4 de la educación superior;\nXV. Adoptar las medidas para que, con independencia de su nacionalidad o condición migratoria, las niñas, niños, adolescentes o jóvenes que utilicen los servicios educativos públicos, ejerzan los derechos y gocen de los beneficios con los que cuentan los educandos nacionales, instrumentando estrategias para facilitar su incorporación y permanencia en el\nSistema Educativo Estatal;\nXVI. Promover medidas para facilitar y garantizar la incorporación y permanencia a los servicios educativos públicos a las niñas, niños, adolescentes y jóvenes que hayan sido repatriados a nuestro país, regresen voluntariamente o enfrenten situaciones de desplazamiento o migración interna;\nXVII. Proporcionar a los educandos los libros de texto gratuitos y materiales educativos impresos o en formatos digitales para la educación básica, garantizando su distribución;\nXVIII. Fomentar programas que coadyuven a la mejora de la educación para alcanzar su excelencia;\nFracción Reformada\nXIX. Promoverá el desarrollo de programas asistenciales, de prevención de riesgos y accidentes, conocimiento en primeros auxilios, la educación vial, campañas de salubridad, así como programas de seguridad escolar; los cuales, incluso, pueden implicar revisiones a las pertenencias de las y los educandos, siempre y cuando dichos esquemas respeten sus derechos, justificándose las respectivas medidas proporcionales que deban considerarse a fin de salvaguardarlos y, en general, a la comunidad educativa a la que pertenecen; y,\nFracción Reformada\nXX. Promover la educación intercultural en pro de la paz y el entendimiento entre las expresiones culturales compartidas.\nFracción Adicionada\nArtículo Reformado\nTítulo Segundo\nDel Sistema Educativo Estatal\nCapítulo I\nArtículo 7. El Sistema Educativo Estatal es el conjunto de actores, instituciones y procesos para la prestación del servicio público de la educación que se imparta en el Estado, desde la educación básica hasta la superior, así como por las relaciones institucionales de dichas estructuras y su vinculación con la sociedad, sus organizaciones, comunidades, pueblos, sectores y familias.\nLey de Educación del Estado de Baja California. Página 5\nArtículo 8. A través del Sistema Educativo Estatal se articularán y coordinarán los esfuerzos de las autoridades educativas estatal y municipal, de los sectores social y privado, para el cumplimiento de los principios, fines y criterios de la educación establecidos en esta\nLey.\nArtículo 9. En el Sistema Educativo Estatal participarán, con sentido de responsabilidad social, los actores, instituciones y procesos que lo componen y será constituido por:\nI. Los educandos;\nII. Las maestras y los maestros;\nIII. Las madres y padres de familia o tutores, así como sus asociaciones;\nIV. Las autoridades educativas del Estado;\nV. Las autoridades escolares;\nVI. Las personas que tengan relación laboral con las autoridades educativas del\nEstado en la prestación del servicio público de educación;\nVII. Las instituciones educativas del Estado, los Sistemas y Subsistemas establecidos en la presente Ley y demás disposiciones aplicables en materia educativa del Estado;\nVIII. Las instituciones de los particulares con autorización o con reconocimiento de validez oficial de estudios;\nIX. Las instituciones de educación superior a las que la ley otorga autonomía;\nX. Los planes y programas de estudio;\nXI. Los muebles e inmuebles, servicios o instalaciones destinados a la prestación del servicio público de educación;\nXII. Los Consejos de Participación Escolar o sus equivalentes creados conforme a esta Ley;\nXIII. Los Comités Escolares de Administración Participativa que se conformen de acuerdo con las disposiciones aplicables, y\nLey de Educación del Estado de Baja California. Página 6\nXIV. Todos los actores que participen en la prestación del servicio público de educación en el Estado.\nEl Ejecutivo Estatal, por conducto de la autoridad educativa estatal, presidirá el\nSistema Educativo Estatal; los lineamientos para su funcionamiento y operación se determinarán en las disposiciones reglamentarias correspondientes.\nArtículo 10. La educación que se imparta en el Sistema Educativo Estatal se organizará en tipos, niveles, modalidades y opciones educativas, conforme a lo siguiente:\nI. Tipos, los de educación básica, media superior y superior;\nII. Niveles, los que se indican para cada tipo educativo en esta Ley;\nIII. Modalidades, la escolarizada, no escolarizada y mixta, y\nIV. Opciones educativas, las que se determinen para cada nivel educativo en los términos de esta Ley y las disposiciones que de ella deriven, entre las que se encuentran la educación abierta y a distancia.\nAdemás de lo anterior, se consideran parte del Sistema Educativo Estatal la formación para el trabajo, la educación para personas adultas, la educación física, la educación artística e indígena, la educación ambiental, educación inclusiva y la educación tecnológica.\nSentencia de Acción de Inconstitucionalidad 18/2021\nFracción Reformada\nLa educación especial buscará la equidad y la inclusión, la cual deberá estar disponible para todos los tipos, niveles, modalidades y opciones educativas establecidas en esta Ley.\nSentencia de Acción de Inconstitucionalidad 18/2021\nFracción Reformada\nDe acuerdo con las necesidades educativas específicas de la población, podrá impartirse educación comunitaria con programas o contenidos particulares para ofrecerle una oportuna atención.\nArtículo Reformado\nArtículo 11. La educación en sus distintos tipos, niveles, modalidades y opciones educativas responderá a la diversidad lingüística, regional, sociocultural y biocultural del\nEstado, así como de la población rural dispersa y grupos migratorios, además de las características y necesidades de los distintos sectores de la población del Estado.\nARTÍCULO 11 BIS.- La educación financiera contempla la promoción del emprendimiento, el fomento de la cultura del ahorro y se impulsará en cada nivel educativo.\nArtículo Adicionado\nLey de Educación del Estado de Baja California. Página 7\nArtículo 12. La educación física, artística e idioma inglés como materias permanentes y obligatorias al desarrollo armónico e integral del individuo en el proceso escolar, se aplicarán todos los niveles de educación básica y media superior, sin distinción alguna por motivos de discapacidad.\nSentencia de Acción de Inconstitucionalidad 18/2021\nArtículo Reformado\nCapítulo II\nDel tipo de Educación Básica\nArtículo 13. La educación básica está compuesta por el nivel inicial, preescolar, primaria y secundaria incluyendo la educación física, artística e idioma inglés.\nLos servicios que comprende este tipo de educación, entre otros, son:\nI. Inicial escolarizada y no escolarizada;\nII. Preescolar general, indígena y comunitario;\nSentencia de Acción de Inconstitucionalidad 18/2021\nFracción Reformada\nIII. Primaria general, indígena y comunitaria;\nSentencia de Acción de Inconstitucionalidad 18/2021\nFracción Reformada\nIV. Secundaria, entre las que se encuentran la general, técnica, comunitaria o las modalidades regionales autorizadas por la autoridad educativa federal;\nV. Secundaria para trabajadores, y\nVI. Telesecundaria.\nDe manera adicional, se considerarán aquellos para impartir educación especial, incluidos los Centros de Atención Múltiple y los Centro de Atención Infantil (CAI), que son los que atienden a niños y niñas de 0 a 3 años edad.\nSentencia de Acción de Inconstitucionalidad 18/2021\nPárrafo Reformado\nLa autoridad educativa estatal a través del área que determine, será la responsable de la aplicación de los programas y guías metodológicas oficiales en cada una de sus áreas, en los diferentes niveles educativos.\nArtículo Reformado\nArtículo 14. En educación inicial, el Estado, de manera progresiva, generará las condiciones para la prestación universal de este servicio.\nLey de Educación del Estado de Baja California. Página 8 educativa federal en términos de la Ley General de Educación.\nAdemás, fomentarán una cultura a favor de la educación inicial con base en programas, campañas, estrategias y acciones de difusión y orientación, con el apoyo de los sectores social y privado, organizaciones de la sociedad civil y organismos internacionales.\nPara tal efecto, promoverán diversas opciones educativas para ser impartidas, como las desarrolladas en el seno de las familias y a nivel comunitario, en las cuales se proporcionará orientación psicopedagógica, incluyendo orientación a madres y padres de familia o tutores para la educación de sus hijas, hijos o pupilos y serán apoyadas por las instituciones encargadas de la protección y defensa de la niñez.\nLa política de educación inicial integrará y dará coherencia a las acciones, programas y modalidades que distintos agentes desarrollan en materia de educación inicial bajo la rectoría de la autoridad educativa federal con el objeto de garantizar la provisión de los modelos de este nivel educativo adaptables a los distintos contextos y sensibles a la diversidad cultural y social del Estado.\nArtículo 15. Las autoridades educativas estatal y municipal impartirán la educación multigrado, la cual se ofrecerá, dentro de un mismo grupo, a estudiantes de diferentes grados académicos, niveles de desarrollo y de conocimientos, en centros educativos en zonas de alta y muy alta marginación.\nPara dar cumplimiento a esta disposición, las autoridades educativas estatal y municipal atenderán los criterios establecidos en el artículo 43 de la Ley General de\nEducación.\nArtículo 16. La educación preescolar tendrá como propósito fundamental la sociabilización de la niña o niño a partir de los tres años de edad cumplidos al 31 de diciembre del año de inicio del ciclo escolar, atendiendo, mediante personal especializado con título académico del nivel o acreditación como licenciado en educación preescolar; aspectos psicológicos, pedagógicos, cognoscitivos, afectivos y psicomotrices que le permitan crecer en un ambiente de libertad, cooperación y progreso, procurando que adquieran los conocimientos básicos sobre la naturaleza, la vida y la sociedad y se oriente su desarrollo hacia la creatividad, además de la orientación a las madres y padres de familia o tutores. inglés.\nArtículo 17. La educación primaria persigue esencialmente el desarrollo y adaptación de los educandos al medio que les es propio, capacitándolos para un desarrollo afectivo, Ley de Educación del Estado de Baja California. Página 9 cognoscitivo, psicomotriz; para una vida social y de cooperación que asegure su bienestar y progreso, procurando que adquieran los conocimientos básicos sobre la naturaleza, la vida y la sociedad, y se oriente a la investigación y al trabajo. del nivel o de licenciado en educación primaria.\nLa edad mínima para ingresar a la educación primaria es de seis años, cumplidos al\n31 de diciembre del año de inicio del ciclo escolar.\nLa educación primaria se enfocará además al conocimiento y desarrollo del idioma inglés.\nArtículo 18. La educación secundaria tiene como propósito alentar el proceso de madurez de la personalidad de jóvenes adolescentes, orientar sus opciones vocacionales y favorecer su integración comunitaria mediante un impulso pedagógico que le permita su propia superación académica.\nLa educación secundaria se sujetará a los planes y programas que determine la autoridad, educativa federal y será atendida por personal que acredite previamente el título académico del nivel o la licenciatura en Normal Superior para las asignaturas de tipo académico; para las materias técnicas, deberán satisfacer los requisitos que, en su caso, señalen las autoridades educativas competentes.\nLa educación secundaria se enfocará además al dominio del idioma inglés.\nCapítulo III\nDel tipo de Educación Media Superior\nArtículo 19. La educación media superior comprende los niveles de bachillerato, de profesional técnico bachiller y los equivalentes a éste, así como la educación profesional que educación básica.\nEl Estado, por conducto de sus autoridades educativas, podrán ofrecer, entre otros, los siguientes servicios educativos:\nI. Bachillerato General;\nII. Bachillerato Tecnológico;\nIII. Bachillerato Intercultural;\nLey de Educación del Estado de Baja California. Página 10\nIV. Bachillerato Artístico;\nV. Profesional Técnico Bachiller;\nVI. Telebachillerato Comunitario;\nVII. Educación Media Superior a Distancia, y\nVIII. Tecnólogo.\nEstos servicios se podrán impartir en las modalidades y opciones educativas señaladas en la presente Ley, como la educación dual con formación en escuela y empresa.\nLa modalidad no escolarizada estará integrada, entre otros servicios, por la educación en línea y aquellos que operen con base en la certificación por evaluaciones parciales.\nArtículo 20. Las autoridades educativas del Estado, en el ámbito de sus competencias, establecerán, de manera progresiva, políticas para garantizar la inclusión, igualdad de género, permanencia y continuidad en este tipo educativo, poniendo énfasis en las y los jóvenes, a través de medidas tendientes a fomentar oportunidades de acceso para las personas que así lo decidan, puedan ingresar a este tipo educativo, así como disminuir la deserción y abandono escolar, como puede ser el establecimiento de apoyos económicos.\nDe igual forma, implementarán un programa de capacitación y evaluación para la certificación que otorga la instancia competente, para egresados de bachillerato, profesional técnico bachiller o sus equivalentes, que no hayan ingresado a educación superior, con la finalidad de proporcionar herramientas que les permitan integrarse al ámbito laboral.\nArtículo 21. El tipo de educación media superior en el Estado se organizará en un sistema estatal. Dicho sistema responderá, en términos de la Ley General de Educación, al\nMedia Superior del Estado de Baja California.\nEl Sistema Estatal de Educación Media Superior del Estado se integrará por:\nI. Colegio de Bachilleres del Estado de Baja California COBACH BC;\nII. Colegio de Estudios Científicos y Tecnológicos de Baja California CECYTE BC;\nIII. Colegio Nacional de Educación Profesional Técnica de Baja California CONALEP\nBC;\nLey de Educación del Estado de Baja California. Página 11\nIV. Preparatoria abierta;\nV. Preparatoria en Línea, y\nVI. Las Instituciones que cuenten con Reconocimiento de Validez Oficial de Estudios para impartir educación media superior.\nArtículo 22. Con la finalidad de formular políticas, estrategias, programas y metas en materia de educación media superior, se crea la Comisión Estatal de Planeación y\nCoordinación del Sistema de Educación Media Superior del Estado de Baja California.\nEl Ejecutivo Estatal emitirá los lineamientos de su integración y su funcionamiento.\nCapítulo IV\nDel Tipo de Educación Superior\nArtículo 23. La educación superior está compuesta por la licenciatura, la especialidad, la maestría y el doctorado, así como por opciones terminales previas a la conclusión de la licenciatura, en cualesquier modalidad y opción educativa que determinen las autoridades educativas, incluidas la dual, que se lleva a cabo de manera combinada tanto en las instituciones educativas, como en contextos reales en el sector productivo. La educación superior comprende también la educación normal en todos sus niveles y especialidades, así como la opción de técnico superior universitario y cursos de actualización posteriores a la licenciatura.\nLa educación superior tiene como propósito formar profesionistas e investigadores, al servicio de la sociedad; organizar y realizar investigaciones científicas de las condiciones y problemas regionales, estatales y nacionales; difundir la cultura e impartir educación para formar conciencia y responsabilidad social, asegurando el uso de medios tecnológicos y multiplataformas digitales para la comunicación, el aprendizaje, emprendimiento y participación.\nTratándose de instituciones educativas particulares de tipo superior con reconocimiento estatal de validez oficial de estudios, con el propósito de impulsar la mejora continua en la calidad de los servicios educativos que brindan, la categoría de Institución de\nExcelencia, de conformidad con la reglamentación que para tal efecto expida el Ejecutivo\nEstatal.\nArtículo 24. En el ámbito de su competencia, las autoridades educativas estatal y educación en este tipo educativo de manera gradual, comenzando con el nivel de licenciatura y, progresivamente, con los demás niveles de este tipo educativo, en los términos que establezca la ley de la materia, priorizando la inclusión de las comunidades\nLey de Educación del Estado de Baja California. Página 12 servicio educativo en todo el Estado. En todo momento se respetará el carácter de las instituciones a las que la ley otorga autonomía.\nSentencia de Acción de Inconstitucionalidad 18/2021\nArtículo Reformado\nArtículo 25. La autoridad educativa estatal establecerá el Registro Estatal de\nOpciones para Educación Superior, el cual tendrá por objetivo dar a conocer a la población los espacios disponibles en las instituciones de educación superior públicas y particulares con reconocimiento de validez oficial de estudios del Estado, así como los requisitos para su acceso.\nPara tal efecto, la autoridad educativa estatal dispondrá las medidas para que las instituciones de educación superior públicas y particulares con reconocimiento de validez oficial de estudios del Estado proporcionen los datos para alimentar el Registro Estatal de\nOpciones para Educación Superior.\nLa información del registro al que se refiere este artículo será pública y difundida de manera electrónica e impresa, a través de los medios de comunicación determinados por la autoridad educativa estatal.\nArtículo 26. Las autoridades educativas estatal y municipal, en el ámbito de sus competencias, establecerán políticas para fomentar la inclusión, continuidad y egreso oportuno de estudiantes inscritos en educación superior, poniendo énfasis en los jóvenes.\nDeterminarán medidas que amplíen el ingreso y permanencia a toda aquella persona que, en los términos que señale la ley en la materia, decida cursar este tipo de estudios, tales como el establecimiento de mecanismos de apoyo académico y económico que responda a las necesidades de la población estudiantil.\nLas instituciones educativas podrán incluir, además, opciones de formación continua y actualización para responder a las necesidades de la transformación del conocimiento y cambio tecnológico; asimismo podrán reconocer las competencias, conocimientos, habilidades, actitudes y destrezas que los educandos hayan adquirido a través del aprendizaje informal, con relación a las requeridas conforme a sus planes y programas con reconocimiento de validez oficial, mediante la aplicación de evaluaciones.\nArtículo 27. Las autoridades educativas del Estado respetarán el régimen jurídico de las universidades a las que la ley les otorga autonomía, en los términos establecidos en la fracción VII del artículo 3o. de la Constitución Política de los Estados Unidos Mexicanos, lo que implica, entre otros, reconocer su facultad para ejercer la libertad de cátedra e investigación, crear su propio marco normativo, la libertad para elegir sus autoridades, gobernarse a sí mismas, y administrar su patrimonio y recursos.\nLey de Educación del Estado de Baja California. Página 13\nCapítulo V\nDel fomento de la Investigación, la Ciencia, las Humanidades, la Tecnología y la Innovación\nArtículo 28. En el Estado se reconoce el derecho de toda persona a gozar de los beneficios del desarrollo científico, humanístico, tecnológico y de la innovación, considerados como elementos fundamentales de la educación y la cultura.\nLas autoridades educativas estatal y municipal, en el ámbito de su competencia, promoverán el desarrollo, la vinculación y divulgación de la investigación científica para el beneficio social y el desarrollo de las actividades productivas del Estado.\nArtículo 29. El fomento de la investigación, la ciencia, las humanidades, la tecnología y la innovación que realicen las autoridades educativas estatales y municipales se realizará de conformidad con lo establecido en la Ley de Impulso al Conocimiento Científico y\nTecnológico en la Innovación.\nArtículo 30. El desarrollo tecnológico y la innovación, asociados a la actualización, a la excelencia educativa y a la expansión de las fronteras del conocimiento se apoyará en las nuevas tecnologías de la información, comunicación, conocimiento y aprendizaje digital o televisivo, mediante el uso de plataformas de acceso abierto.\nCapítulo VI\nDe la Educación Indígena\nArtículo 31. El Estado garantizará el ejercicio de los derechos en materia de educación, cultura y lengua a todas las personas, pueblos y comunidades indígenas, así como afromexicanas.\nLas acciones en materia educativa de las autoridades respectivas contribuirán al conocimiento, aprendizaje, reconocimiento, valoración, revitalización, preservación y desarrollo de las lenguas indígenas, en su forma oral y escrita, como medio de comunicación, de enseñanza, objeto y fuente de conocimiento. intercultural plurilingüe con equidad e inclusión; de los niveles inicial, preescolar, primaria, secundaria y media superior con pertinencia cultural, social, lingüística, tradiciones, usos y costumbres, basada en el respeto a la cosmovisión, promoción, preservación y revitalización del patrimonio cultural e histórico de los pueblos y comunidades indígenas, así como afromexicanas que radican en el estado.\nSentencia de Acción de Inconstitucionalidad 18/2021\nArtículo Reformado\nLey de Educación del Estado de Baja California. Página 14\nArtículo 32. Las autoridades educativas del Estado consultarán de buena fe, de manera previa, libre e informada, de acuerdo con las disposiciones legales nacionales e internacionales en la materia, cada vez que prevean medidas en materia educativa, relacionadas con los pueblos y comunidades indígenas, así como afromexicanas, respetando su autodeterminación en los términos del artículo 2o. de la Constitución Política de los Estados Unidos Mexicanos.\nSentencia de Acción de Inconstitucionalidad 18/2021\nArtículo Reformado\nArtículo 33. En materia de educación indígena, las autoridades educativas estatal y municipal mediante una estructura especializada deberá realizar lo siguiente, entre otras acciones:\nI. Fortalecer y dotar escuelas de educación indígena, centros educativos integrales y albergues escolares indígenas, con infraestructura necesaria para que, de manera enunciativa y no limitativa, puedan desarrollar sus usos y costumbres, ceremonias, artesanías, medicina tradicional, huertos, deportes, practicas socioculturales, juegos autóctonos, actividades físicas organizadas y artísticas, con equipamiento óptimo y tecnológico, acorde al contexto de cada comunidad, bibliotecas escolares, garantizando la equidad de todos los centros educativos.\nII. Desarrollar programas y proyectos educativos que integren los saberes comunitarios y prácticas socioculturales de los pueblos y comunidades indígenas así como afromexicanas y que se reconozca la herencia cultural, cosmovisión, trabajo colectivo a favor de la comunidad indígena, respeto a la naturaleza, vestimenta originaria, lenguas indígenas, usos y costumbres, materiales didácticos y lúdicos en lenguas indígenas, medicina tradicional, artesanías, que sirvan de apoyo para los contextos de diversidad cultural y lingüísticos y de educación física.\nIII. Elaborar, actualizar, distribuir material educativo, didáctico, multimedia, lúdico, libros de texto gratuitos en las diversas lenguas indígenas, de los pueblos y comunidades, así como afromexicanas que viven en el Estado;\nIV. Fortalecer las instituciones públicas de formación docente, con una visión intercultural plurilingüe, donde se dé a conocer la cosmovisión de la diversidad cultural del\nEstado y del país, en los usos y costumbres, lenguas, formas de convivir, de elegir a representantes, que sirvan de herramienta, para la formación, actualización y certificación de maestras y maestros de las diferentes etnias y afromexicanas que viven en el Estado; educativa acorde a las necesidades formativas de docentes indígenas;\nV. Tomar en consideración las aportaciones que emitan los docentes de escuelas indígenas, así como los padres de familia y sabios de los pueblos y comunidades indígenas\nLey de Educación del Estado de Baja California. Página 15 y afromexicanas para la elaboración de planes y programas de estudio, que permitan la preservación de su cosmovisión y cosmogonía, respetando los usos y costumbres;\nVI. Elaborar mecanismos y estrategias, para que el educando pueda formarse, desarrollarse, con un enfoque intercultural, plurilingüe con respeto a sus usos y costumbres;\nVII. Establecer convenios de colaboración y coordinación entre las diferentes instancias educativas y gubernamentales para que existan programas de intercambio, nacional e internacional, donde se apoye a estudiantes y personal educativo de comunidades indígenas y afromexicanas, respetando sus usos y costumbres, permitiendo la inclusión y enriquecimiento de la diversidad de culturas;\nVIII. Impulsar la vinculación con las autoridades educativas de los Estados Unidos de\nAmérica y de otros países con presencia industrial, comercial y empresarial en el Estado, para la formación de maestros y alumnos indígenas y afromexicanas bilingües y binacionales, mediante becas o estímulos para ello; y,\nIX. Garantizar la participación, formación y actualización de personas con conocimiento de la lengua y cultura indígena y afromexicana para que formen parte de la modalidad educativa indígena en el Estado.\nSentencia de Acción de Inconstitucionalidad 18/2021\nArtículo Reformado\nCapítulo VII\nDe la Educación Humanista\nArtículo 34. En la educación que se imparta en el Estado se promoverá un enfoque humanista, el cual favorecerá en el educando sus habilidades socioemocionales que le permitan adquirir y generar conocimientos, fortalecer la capacidad para aprender a pensar, sentir, actuar y desarrollarse como persona integrante de una comunidad y en armonía con la naturaleza.\nDe igual forma, para resolver situaciones problemáticas de manera autónoma y colectivamente, aplicar los conocimientos aprendidos a situaciones concretas de su realidad y desarrollar sus actitudes y habilidades para su participación en los procesos productivos, democráticos y comunitarios.\nArtículo 35. La autoridad educativa estatal generará mecanismos para apoyar y promover la creación y difusión artística, propiciar el conocimiento crítico, así como la difusión del arte y las culturas para la educación básica y media superior. En coordinación con la autoridad educativa federal, adoptará medidas para que, dentro de la orientación integral del educando, se promuevan métodos de enseñanza aprendizaje, con la finalidad de\nLey de Educación del Estado de Baja California. Página 16 desarrollo cultural y cognoscitivo de las personas: debiendo cumplir con los siguientes propósitos generales de la educación artística:\nPárrafo Reformado\nI. Se orientará a potenciar en los niños la sensibilidad, la iniciativa, la curiosidad, la espontaneidad, la imaginación, el gusto estético y la creatividad, para que expresen sus sentimientos mediante el arte y la experimentación de sensaciones de logro;\nII. Tenderá a que los educandos progresen en sus habilidades motoras y las fortalezcan al utilizar materiales, herramientas y recursos diversos, desarrollando las habilidades perceptivas como resultado de lo que observan, escuchan, palpan, bailan y expresan a partir del arte;\nIII. Los educandos aprenderán a reconocer que entre ellos mismos se pueden manifestar diferentes puntos de vista y formas de expresión, aprendiendo a valorar la diversidad de opiniones bajo un esquema de respeto y tolerancia;\nIV. El enriquecimiento de su lenguaje y desarrollo de la memoria, que permitan mejorar la atención, la escucha, la corporeidad favoreciendo mayores oportunidades de interacción con los demás;\nV. Se buscará que los educandos amplíen sus conocimientos en una disciplina artística y la practiquen habitualmente mediante la apropiación de técnicas y procesos que les permitan expresarse artísticamente;\nVI. Facilitar la interacción con distintos códigos, que les permita reconocer la diversidad de relaciones entre los elementos estéticos y simbólicos, pudiendo interpretar los significados de esos elementos para otorgarles un sentido social, que les permita disfrutar la experiencia de formar parte del quehacer artístico;\nVII. Desarrollo de la competencia artística y cultural a partir de la apropiación de lenguajes, procesos y recursos de las artes, con base en el trabajo pedagógico diseñado para potenciar sus capacidades, atender sus intereses y satisfacer sus necesidades socioculturales;\nVIII. Que se adquieran por los alumnos los conocimientos y las habilidades propios de los lenguajes artísticos: artes visuales, expresión corporal y danza, música y teatro, que permitan desarrollar su pensamiento artístico, paralelamente a sus actitudes y valores, mediante experiencias estéticas que favorezcan su creatividad;\nIX. Instruya y oriente como valorar la importancia de la diversidad y la riqueza del patrimonio artístico y cultural, por medio del descubrimiento y la experimentación de los diferentes aspectos del arte, al vivenciar actividades cognitivas, afectivas y estéticas;\nLey de Educación del Estado de Baja California. Página 17\nX. Aprecien las cualidades estéticas de diversas manifestaciones y representaciones y valorar su importancia dentro de las artes;\nXl. Exploren la dimensión estética de las imágenes, las cualidades del sonido y el uso de cuerpo y voz, estructura dramática y creación teatral, para enriquecer las concepciones personales y sociales que se tienen del arte;\nXII. Conozcan los procesos de creación artística de diseñadores, artesanos y en general de los miembros creativos de la comunidad, y\nXIII. Distingan diferentes profesiones e instituciones que se desarrollan en diferentes entornos culturales relacionadas con la creación, investigación, conservación y difusión de las artes.\nPara ser docente de Educación Artística, se requiere haber obtenido el título de\nMaestro Normalista de Educación Artística, de Licenciado en Educación Artística, de\nLicenciado en Actividad Artística; o profesión afín que cuente con reconocimiento oficial.\nArtículo Reformado\nArtículo 36. Para el ejercicio y desarrollo de lo dispuesto por esta Ley en materia de educación ambiental, las autoridades educativas del Estado, deberán además fomentar la educación ambiental como una práctica educativa integrada, continua y permanente en todos los niveles y modalidades de enseñanza, incorporando contenidos sobre ética ambiental vinculados a aspectos prácticos.\nAsimismo, deberán:\nI. Propiciar la participación de educandos, educadores y organizaciones no gubernamentales n la formación y ejecución de programas y actividades vinculadas a la educación ambiental;\nII. Promover programas de vinculación escuela — empresa y comunidad, con ambiente, y\nIII. Impulsar programas y prácticas en materia de respeto y cuidado del medio ambiente en vinculación con empresas prestadoras de servicios turísticos.\nCapítulo VIII\nDe la Educación Inclusiva\nArtículo 37. La educación inclusiva se refiere al conjunto de acciones orientadas a identificar, prevenir y reducir las barreras que limitan el acceso, permanencia, participación y\nLey de Educación del Estado de Baja California. Página 18 aprendizaje de todos los educandos, al eliminar prácticas de discriminación, exclusión y segregación.\nLa educación inclusiva se basa en la valoración de la diversidad, adaptando el sistema para responder con equidad a las características, necesidades, intereses, capacidades, habilidades y estilos de aprendizaje de todos y cada uno de los educandos, así como eliminar cualquier forma de exclusión, discriminación y cualquier condición que se erija en una barrera al aprendizaje y la participación.\nSentencia de Acción de Inconstitucionalidad 18/2021\nArtículo Reformado\nArtículo 38. El Estado asegurará la educación inclusiva en todos los tipos y niveles, con el fin de favorecer el aprendizaje de todos los estudiantes, con énfasis en los que están excluidos, marginados o en riesgo de estarlo, para lo cual buscará:\nI. Favorecer el máximo logro de aprendizaje de los educandos con respeto a su dignidad, derechos humanos y libertades fundamentales, reforzando su autoestima y aprecio por la diversidad humana;\nII. Desarrollar al máximo la personalidad, los talentos y la creatividad de los educandos;\nIII. Favorecer la plena participación de los educandos, su educación y facilitar la continuidad de sus estudios en la educación obligatoria;\nIV. Instrumentar acciones para que ninguna persona quede excluida del Sistema\nEducativo Estatal por motivos de origen étnico o nacional, creencias religiosas, convicciones éticas, de conciencia o ideológicas, sexo, orientación sexual o de género, así como por sus características, necesidades, intereses, capacidades, habilidades y estilos de aprendizaje, entre otras;\nV. Realizar los ajustes razonables en función de las necesidades de las personas y otorgar los apoyos necesarios para facilitar su formación, libre desarrollo e integración en su entorno mediante el uso de la tecnología en salón de clase; y,\nVI. Proporcionar a las personas con discapacidad la posibilidad de aprender y desarrollar habilidades para la vida, que favorezcan su inclusión laboral, a fin de propiciar su participación plena y en igualdad de condiciones en la educación y en la sociedad, con capacitación del docente y demás personal, incluyendo en las cartas descriptivas la metodología a aplicar a personas con discapacidad.\nSentencia de Acción de Inconstitucionalidad 18/2021\nArtículo Reformado\nLey de Educación del Estado de Baja California. Página 19\nArtículo 39. En la aplicación de esta Ley, se garantizará el derecho a la educación a los educandos con condiciones especiales transitorias o definitivas, aptitudes sobresalientes o que enfrenten barreras para el aprendizaje y la participación.\nI. Prestar educación especial en condiciones necesarias, con personal docente capacitado, auxiliares de aulas, previa decisión y valoración por parte de los educandos, madres y padres de familia o tutores, personal docente y en su caso, derivados por una condición de salud, para garantizar el derecho a la educación de los educandos que enfrentan barreras para el aprendizaje y la participación;\nII. Ofrecer formatos accesibles para prestar educación especial, procurando en la medida de lo posible su incorporación a todos los servicios educativos, sin que esto cancele su posibilidad de acceder al servicio escolarizado;\nIII. Prestar educación especial para apoyar a los educandos con alguna discapacidad o aptitudes sobresalientes en los niveles de educación preescolar, primaria, secundaria y media superior;\nIV. Establecer un sistema de diagnóstico temprano y atención especializada para la eliminación de barreras para el aprendizaje y la participación;\nV. Garantizar la formación de todo el personal docente para que, en el ámbito de sus competencias, contribuyan a identificar y eliminar las barreras para el aprendizaje y la participación, y preste los apoyos que los educandos requieran en colaboración de auxiliares de aula;\nVI. Garantizar la satisfacción de las necesidades básicas de aprendizaje de los educandos con alguna discapacidad, su bienestar y máximo desarrollo para la autónoma inclusión a la vida social y productiva; y,\nVII. Promover actitudes, prácticas y políticas incluyentes para la eliminación de las barreras del aprendizaje en todos los actores sociales involucrados en educación.\nSentencia de Acción de Inconstitucionalidad 18/2021\nArtículo Reformado\nArtículo 40. Para garantizar la educación inclusiva, las autoridades educativas del\nEstado, en el ámbito de su competencia, ofrecerán las medidas pertinentes, entre ellas:\nI. Facilitar el aprendizaje del sistema Braille, otros modos, medios y formatos de comunicación aumentativos o alternativos y habilidades de orientación y de movilidad, así como la tutoría y el apoyo necesario;\nII. Facilitar la adquisición y el aprendizaje de la Lengua de Señas dependiendo de las capacidades del educando y la enseñanza del español para las personas sordas;\nLey de Educación del Estado de Baja California. Página 20\nIII. Asegurar que los educandos ciegos, sordos o sordociegos reciban educación en cada persona y en entornos que permitan alcanzar su máximo desarrollo académico, productivo y social;\nIV. Asegurar que se realicen ajustes razonables para las personas con discapacidad, en relación a la infraestructura de las aulas, tecnología, y todo el equipamiento necesario para que puedan integrarse; y,\nV. Proporcionar a los educandos con aptitudes sobresalientes la atención que requieran de acuerdo con sus capacidades, intereses y necesidades.\nSentencia de Acción de Inconstitucionalidad 18/2021\nArtículo Reformado\nArtículo 41. En el Sistema Educativo Estatal se atenderán las disposiciones en materia de accesibilidad señaladas en la presente Ley, la Ley General de Educación, la Ley\nGeneral para la Inclusión de las Personas con Discapacidad, Reglamento de la Ley General para la Inclusión de las Personas con Discapacidad, la Ley Federal para Prevenir y Eliminar la Discriminación, la Ley para las Personas con Discapacidad en Estado de Baja California, Ley para Prevenir y Erradicar el Acoso Escolar para el Estado de Baja California y en las demás normas aplicables.\nSentencia de Acción de Inconstitucionalidad 18/2021\nArtículo Reformado\nCapítulo IX\nDe la Educación para Personas Adultas\nArtículo 42. Las autoridades educativas del Estado, en el ámbito de su competencia ofrecerá acceso a programas y servicios educativos para personas adultas en distintas modalidades que consideren sus contextos familiares, comunitarios, laborales y sociales.\nEsta educación proporcionará los medios para erradicar el rezago educativo y analfabetismo a través de diversos tipos y modalidades de estudio, así como una orientación integral para la vida que posibilite a las personas adultas formar parte activa de la sociedad, a través de las habilidades, conocimientos y aptitudes que adquiera con el proceso de fin.\nArtículo 43. La educación para personas adultas será considerada una educación a cursado o concluido la educación primaria y secundaria; además de fomentar su inclusión a la educación media superior y superior. Se presta a través de servicios de alfabetización, educación primaria y secundaria, así como de formación para el trabajo, con las\nLey de Educación del Estado de Baja California. Página 21 particularidades adecuadas a dicha población. Esta educación se apoyará en la participación y la solidaridad social en los términos que establezca la autoridad educativa federal.\nArtículo 44. Las personas beneficiarias de la educación referida en este Capítulo podrán acreditar los conocimientos adquiridos, mediante evaluaciones parciales o globales, conforme a los procedimientos a que aluden los artículos 83 y 145 de la Ley General de\nEducación. Cuando al presentar una evaluación no acrediten los conocimientos, habilidades, capacidades y destrezas, recibirán un informe que indique las asignaturas y unidades de aprendizaje en las que deban profundizar y tendrán derecho a presentar nuevas evaluaciones hasta lograr la acreditación respectiva.\nLas autoridades educativas estatal y municipal, en el ámbito de su competencia organizarán servicios permanentes de promoción y asesoría de educación para personas adultas. Promoverá ante las instancias competentes, se darán facilidades necesarias a trabajadores y sus familiares para estudiar y acreditar la educación primaria, secundaria y media superior.\nQuienes participen voluntariamente proporcionando asesoría en tareas relativas a esta educación tendrán derecho, en su caso, a que se les acredite como servicio social.\nCapítulo X\nDe la Educación Física\nArtículo 45. La educación física que impartan las autoridades educativas del Estado tendrá los siguientes propósitos generales:\nI. Mejorar la capacidad coordinativa, relacionadas con la orientación, el equilibrio, la agilidad, la coordinación sentido-movimiento y la reacción; y las capacidades condicionales, que refieren la fuerza, la velocidad, la resistencia y la flexibilidad, con la finalidad de que el educando adquiera el dominio y manifestaciones eficientes del movimiento, que repercutan en la resolución de problemas en los ámbitos cognoscitivos, motriz, afectivo y social;\nII. Estimular, desarrollar y conservar la condición física del educando a través de la ejercitación sistemática de las capacidades físicas, atendiendo a las características individuales del mismo;\nIII. Propiciar la manifestación de habilidades motrices a partir de la práctica de actividades físico-deportivas y recreativas que le permitan integrarse a interactuar con los demás;\nIV. Propiciar en el educando la confianza y seguridad en sí mismo, mediante la en diferentes situaciones;\nLey de Educación del Estado de Baja California. Página 22\nV. Promover la formación y estimular la adquisición de hábitos, de ejercicio diario, de la higiene, de higiene durante el periodo menstrual, la compatibilidad del deporte y ejercicio durante la menstruación, alimentación, descanso y conservación del medio ambiente con la individual y colectiva;\nFracción Reformada\nVI. Fomentar la manifestación de actividades positivas, individuales y grupales, así como la adquisición de valores a partir de aquellas actividades que utilicen al movimiento como una forma de expresión;\nVII. Incrementar las actividades sociales favorables de respeto, cooperación y confianza en los demás mediante las actividades físicas grupales que promuevan su integración al medio y su relación interpersonal;\nVIII. Incluir en la medida de sus posibilidades a las y los alumnos que cuentan con alguna discapacidad con la finalidad de integrarlos al medio y promover las relaciones interpersonales; y, Sentencia de Acción de Inconstitucionalidad 18/2021\nFracción Reformada\nIX. Promover de la práctica de estilos de vida saludables en los educandos, con la finalidad de que las instituciones educativas públicas y privadas promuevan la práctica del deporte y actividades físicas en sus planteles educativos.\nPara ser docente de educación física, se requiere haber obtenido el título de Maestro\nNormalista de Educación Física, de Licenciado en Educación Física, de Licenciado en\nActividad Física y Deporte; o profesión afín que cuente con reconocimiento oficial de estudios.\nArtículo Reformado\nCapítulo XI\nDe la Formación para el Trabajo\nArtículo 46. La formación para el trabajo deberá estar enfocada en la adquisición de conocimientos, habilidades, destrezas y actitudes, que permitan a la persona desempeñar una actividad productiva, mediante alguna ocupación o algún oficio calificado. Se realizará capacidades para su inclusión laboral.\nSentencia de Acción de Inconstitucionalidad 18/2021\nPárrafo Reformado\nPara la acreditación de conocimientos, habilidades, destrezas y capacidades intermedios o terminales- de manera parcial y acumulativa, independientemente de la forma\nLey de Educación del Estado de Baja California. Página 23 en que hayan sido adquiridos, se estará al régimen de certificación establecido por la autoridad educativa federal en términos de la Ley General de Educación, así como a los lineamientos generales que para tales efectos emita.\nAdicionalmente, las autoridades educativas del Estado podrán disposiciones específicas atendiendo a los requerimientos del Estado, pudiendo establecer procedimientos que permitan considerar las necesidades, propuestas y opiniones de los diversos sectores productivos, a nivel nacional, estatal o municipal.\nPodrán celebrarse convenios para que la formación para el trabajo se imparta por las autoridades educativas del Estado, las instituciones privadas, las organizaciones sindicales, los patrones y demás particulares. La formación para el trabajo que se imparta en términos del presente artículo será adicional y complementaria a la capacitación prevista en la fracción XIII del Apartado A del artículo 123 de la Constitución Política de los Estados Unidos\nMexicanos.\nArtículo Reformado\nArtículo 47. Las negociaciones o empresas a que se refiere la fracción XII del\nApartado A del artículo 123 de la Constitución Política de los Estados Unidos Mexicanos están obligadas a establecer y sostener escuelas cuando el número de educandos que las requiera sea mayor de veinte. Estos planteles educativos quedarán bajo la dirección administrativa de la autoridad educativa estatal.\nLas escuelas que se establezcan en cumplimiento de la obligación prevista en el párrafo anterior contarán con edificio, instalaciones accesibles y demás elementos necesarios para realizar su función, en los términos que señalen las disposiciones aplicables.\nEl sostenimiento de dichas escuelas comprende la obligación patronal de proporcionar las aportaciones para la remuneración del personal y las prestaciones que dispongan las leyes y reglamentos, que no serán inferiores a las que otorgue la autoridad educativa estatal en igualdad de circunstancias. cumplimiento de las obligaciones que señala el presente artículo.\nCapítulo XII\nDel Aprendizaje Informal\nArtículo 48. El aprendizaje informal a que se refiere el presente capítulo podrá desarrollar a través de la educación informal la cual no es curricular, se adquiere en los diferentes espacios sociales e influye en el desarrollo personal y social de los individuos.\nLey de Educación del Estado de Baja California. Página 24 informal a través de las siguientes acciones:\nI. Misiones culturales;\nII. Programas de educación, integración familiar, prevención de riesgos y accidentes, conocimiento en primeros auxilios, educación vial, protección, salud, deporte, defensa legal y fortalecimiento de la cultura de la prevención del delito y la legalidad;\nFracción Reformada\nIII. Programas de mejoramiento del medio ambiente y preservación ecológica;\nIV. Fomento al desarrollo artístico y artesanal;\nV. Procurar el conocimiento de la historia y geografía del Estado;\nVI. Rescate y conservación del patrimonio cultural comunitario;\nVII. Fomento del servicio a la comunidad en una participación social comprometida, y\nVIII. Las demás que tiendan al bienestar individual y social.\nPara impulsar la educación informal las autoridades educativas estatal y municipal harán uso de los avances de la tecnología a su alcance.\nArtículo Reformado\nTítulo Tercero\nDel Proceso Educativo\nCapítulo I\nArtículo 49. La orientación integral en el proceso educativo comprende la formación para la vida de los educandos, así como los contenidos de los planes y programas de estudio, la vinculación de la escuela con la comunidad y la adecuada formación de las maestras y maestros en los procesos de enseñanza aprendizaje, acorde con este criterio.\nArtículo 50. La orientación integral, en la formación de las y los educandos, considerará lo siguiente:\nPárrafo Reformado\nI. El pensamiento lógico matemático y la alfabetización numérica;\nLey de Educación del Estado de Baja California. Página 25\nII. La comprensión lectora, la expresión oral y escrita, con elementos de la lengua que favorezcan la interrelación entre ellos;\nIII. El conocimiento tecnológico, con el empleo de tecnologías de la información, comunicación, conocimiento y aprendizaje digital, manejo de diferentes lenguajes y herramientas de sistemas informáticos, y de comunicación;\nIV. El conocimiento científico, a través de la apropiación de principios, modelos y conceptos científicos fundamentales, empleo de procedimientos experimentales y de comunicación;\nV. El pensamiento filosófico, histórico y humanístico;\nVI. Las habilidades socioemocionales, como el desarrollo de la imaginación y la creatividad de contenidos y formas; el respeto por los otros; la colaboración y el trabajo en equipo; la comunicación; el aprendizaje informal; la productividad; capacidad de iniciativa, resiliencia, responsabilidad; trabajo en red y empatía; gestión y organización;\nVII. El pensamiento crítico, como una capacidad de identificar, analizar, cuestionar y valorar fenómenos, información, acciones e ideas, así como tomar una posición frente a los hechos y procesos para solucionar distintos problemas de la realidad;\nVIII. El logro de los educandos de acuerdo con sus capacidades, circunstancias, necesidades, estilos y ritmo de aprendizaje diversos;\nIX. Los conocimientos, habilidades motrices y creativas, a través de la activación física, la práctica del deporte y la educación física vinculadas con la salud, la cultura, la recreación y la convivencia en comunidad;\nX. La apreciación y creación artística, a través de conocimientos conceptuales y habilidades creativas para su manifestación en diferentes formas, y\nXI. Los valores para la responsabilidad ciudadana y social, como el respeto por los otros, la solidaridad, la justicia, la libertad, la igualdad, la honradez, la gratitud y la participación democrática con base a una educación cívica.\nArtículo Reformado\nArtículo 51. Las maestras y los maestros acompañarán a los educandos en sus trayectorias formativas en los distintos tipos, niveles, modalidades y opciones educativas, propiciando la construcción de aprendizajes interculturales, tecnológicos, científicos, humanísticos, sociales, biológicos, comunitarios y plurilingües, para acercarlos a la realidad, a efecto de interpretarla y participar en su transformación positiva.\nLey de Educación del Estado de Baja California. Página 26\nArtículo 52. La evaluación de los educandos será integral y comprenderá la valoración de los conocimientos, las habilidades, las destrezas y, en general, el logro de los propósitos establecidos en los planes y programas de estudio.\nLas instituciones educativas establecidas por las autoridades educativas del Estado, reconocimiento de validez oficial de estudios, a través de las autoridades escolares, deberán informar periódicamente a los educandos y a las madres y padres de familia o tutores, los resultados de las evaluaciones parciales y finales, así como las observaciones sobre el desempeño académico y conducta de los educandos que les permitan lograr un mejor aprovechamiento.\nLa obligación de informar a las madres y padres de familia o tutores, anterior no será aplicable para la educación superior.\nCapítulo II\nDe los Planes y Programas de Estudio\nArtículo 53. Los planes y programas de estudio de la educación preescolar, primaria, secundaria, la educación normal y demás aplicables para la formación de maestras y maestros de educación básica, serán los que determine la autoridad educativa federal, de conformidad a los fines y criterios establecidos en los artículos 15 y 16 de la Ley General.\nDe conformidad a las disposiciones que la autoridad educativa federal emita, la autoridad educativa estatal emitirá su opinión para que se considere en los planes y programas de estudio el contenido de los proyectos y programas educativos que contemplen las realidades y contextos, regionales y locales del Estado.\nLa autoridad educativa estatal podrá solicitar a la autoridad educativa federal actualizaciones y modificaciones de los planes y programas de estudio, para atender el carácter regional, local, contextual y situacional del proceso de enseñanza aprendizaje.\nSuperior del Estado de Baja California, con el propósito de contextualizarlos a sus realidades regionales. La elaboración de planes y programas de estudio de los bachilleratos correspondientes. artículo, se podrán fomentar acciones para que emitan su opinión las maestras y los\nLey de Educación del Estado de Baja California. Página 27 maestros, así como las niñas, niños, adolescentes y jóvenes. De igual forma, serán del servicio educativo y respondan a los enfoques humanista, social, crítico, comunitario e integral de la educación, entre otros, para la recuperación de los saberes locales.\nArtículo 54. Los planes y programas que la autoridad educativa federal determine en cumplimiento de la Ley General, así como sus modificaciones, se publicarán en el Periódico\nOficial del Estado y, previo a su aplicación, se deberá capacitar a las maestras y los maestros respecto de su contenido y métodos, así como generar espacios para el análisis y la comprensión de los referidos cambios.\nEn el caso de los planes y programas para la educación media superior, podrán publicarse en Portal de Transparencia del Ejecutivo Estatal y en su caso de los organismos descentralizados estatales correspondientes, creándose para tal efecto una Comisión\nCoordinadora.\nCapítulo III\nDe las Tecnologías de la Información, Comunicación, Conocimiento y Aprendizaje Digital en el proceso educativo\nArtículo 55. En la educación que se imparta en el Estado, se utilizará el avance de las tecnologías de la información, comunicación, conocimiento, aprendizaje digital o televisivo, con la finalidad de fortalecer los modelos pedagógicos de enseñanza aprendizaje, la innovación educativa, el desarrollo de habilidades y saberes digitales de los educandos, además del establecimiento de programas de educación en línea y semi presencial para cerrar la brecha digital y las desigualdades en la población.\nLas tecnologías de la información, comunicación, conocimiento y aprendizaje digital o televisivo serán utilizadas como un complemento de los demás materiales educativos, incluidos los libros de texto gratuitos.\nArtículo 56. La autoridad educativa estatal, en el ámbito de su competencia, habilidades necesarias en el uso de las tecnologías de la información, comunicación, investigación e innovación científica y tecnológica, procurando la vinculación con el sector productivo.\nCapítulo IV\nLey de Educación del Estado de Baja California. Página 28\nArtículo 57. La autoridad educativa estatal, en el ámbito de su competencia, emitirá\nBásica y Media Superior, el cual será un documento de carácter operativo y normativo que tendrá la finalidad de apoyar la planeación, organización y ejecución de las actividades docentes, pedagógicas, directivas, administrativas y de supervisión, que como mínimas debe tener cada plantel educativo enfocadas a la mejora escolar, atendiendo al contexto regional de la prestación de los servicios educativos en el Estado, pudiendo las instituciones educativas exceder las disposiciones de la Guía Operativa para la Organización y\nFuncionamiento de los Servicios de Educación Básica y Media Superior, en beneficio de los educandos.\nArtículo 58. Para el proceso de mejora escolar, se constituirán Consejos Técnicos\nEscolares en los tipos de educación básica y media superior, como órganos colegiados de decisión técnico- pedagógica de cada plantel educativo, los cuales tendrán a su cargo adoptar e implementar las decisiones para contribuir al máximo logro de aprendizaje de los educandos, el desarrollo de su pensamiento crítico y el fortalecimiento de los lazos entre escuela y comunidad.\nDichos Consejos Técnicos Escolares se regirán conforme a los lineamientos que para su integración, operación y funcionamiento emita la autoridad educativa federal.\nArtículo 59. Cada Consejo Técnico Escolar contará con un Comité de Planeación y\nEvaluación, el cual tendrá a su cargo formular un programa de mejora continua que contemple, de manera integral, la infraestructura, el equipamiento, el avance de los planes y programas educativos, la formación y prácticas docentes, la carga administrativa, la asistencia de los educandos, el aprovechamiento académico, el desempeño de las autoridades educativas y los contextos socioculturales.\nDicho programa tendrá un carácter plurianual, definirá objetivos y metas, los cuales serán evaluados por el referido Comité.\nLas facultades de este Comité, en materia de infraestructura y equipamiento de los planteles educativos, se referirán a los aportes que haga sobre mejora escolar y serán cumplimiento de sus funciones. lineamientos respectivos emitidos por la autoridad educativa federal.\nArtículo 60. La elaboración de la Guía a la que se refiere este Capítulo se apegará a federal. En dicha Guía se establecerán los elementos de normalidad mínima de la operación\nLey de Educación del Estado de Baja California. Página 29 escolar, cuyo objetivo es dar a conocer las normas y los procedimientos institucionales y, con ello, facilitar la toma de decisiones para fortalecer la mejora escolar.\nPrimero de esta Ley, en la Guía se establecerán únicamente los parámetros y estándares mínimos de mejora continua que deben cumplirse en todos los niveles educativos, pudiendo los particulares cumplir con parámetros y estándares superiores a los mínimos.\nCapítulo V\nDel Calendario Escolar\nArtículo 61. El calendario escolar aplicable para cada ciclo lectivo de la educación básica y normal y demás para la formación de maestras y maestros de educación básica, necesarios para cubrir los planes y programas aplicables, será el que determine la autoridad educativa federal.\nLas autoridades escolares, previa autorización de la autoridad educativa estatal y de conformidad con los lineamientos que expida la autoridad educativa federal, podrán ajustar el calendario escolar al que se refiere el párrafo anterior. Dichos ajustes deberán prever las medidas para cubrir los planes y programas aplicables.\nArtículo 62. En días escolares, las horas de labor escolar se dedicarán a la orientación integral del educando, a través de la práctica docente, actividades educativas y otras que contribuyan a los principios, fines y criterios de la educación, conforme a lo previsto en los planes y programas de estudio aplicables.\nLas actividades no previstas en los planes y programas de estudio, o bien la suspensión de clases, de la educación básica, normal y demás para la formación de maestras y maestros de educación básica, sólo podrán ser autorizadas por la autoridad que haya establecido o, en su caso, ajustado el correspondiente calendario escolar. Estas autorizaciones únicamente podrán concederse en casos extraordinarios y si no implican incumplimiento de los planes y programas ni, en su caso, del calendario señalado por la autoridad educativa federal.\nDe presentarse interrupciones por caso extraordinario o fuerza mayor, las autoridades perdidos.\nArtículo 63. La autoridad educativa estatal publicará en el Periódico Oficial del\nEstado, las autorizaciones de ajustes al calendario escolar determinado por la autoridad educativa federal.\nTítulo Cuarto\nDel Educando\nLey de Educación del Estado de Baja California. Página 30\nCapítulo I\nArtículo 64. En la educación impartida en el Estado se priorizará el interés superior de niñas, niños, adolescentes y jóvenes en el ejercicio de su derecho a la educación. Para tal efecto, la autoridad educativa estatal garantizará el desarrollo de programas y políticas públicas que hagan efectivo ese principio constitucional.\nArtículo 65. Los educandos son los sujetos más valiosos de la educación con pleno derecho a desarrollar todas sus potencialidades de forma activa, transformadora y autónoma.\nComo parte del proceso educativo, los educandos tendrán derecho a:\nI. Recibir una educación de excelencia;\nII. Ser respetados en su integridad, identidad y dignidad, además de la protección contra cualquier tipo de agresión física o moral;\nIII. Recibir una orientación integral como elemento para el pleno desarrollo de su personalidad;\nIV. Ser respetados por su libertad de convicciones éticas, de conciencia, de religión e ideológicas;\nV. Recibir una orientación educativa y vocacional;\nVI. Tener permanentemente un docente frente a grupo que contribuya al logro de su aprendizaje y desarrollo integral;\nVII. Participar de los procesos que se deriven en los planteles educativos como centros de aprendizaje comunitario;\nVIII. Recibir becas, productos higiénicos de gestión menstrual como toallas sanitarias, compresas de tela, tampones, copas menstruales y demás apoyos económicos priorizando a derecho a la educación;\nFracción Reformada\nIX. Participar en los Comités Escolares de Administración Participativa en los términos de las disposiciones respectivas;\nFracción Reformada\nLey de Educación del Estado de Baja California. Página 31\nX. Recibir las facilidades administrativas cuando participen en competencias deportivas a nivel local, nacional e internacional, sin menoscabo de sus intereses educativos; y,\nFracción Adicionada, recorriéndose la subsecuente\nXI. Los demás que sean reconocidos en la Constitución Política de los Estados\nUnidos Mexicanos, la Ley General de Educación, esta Ley y demás disposiciones aplicables.\nLa autoridad educativa estatal establecerá los mecanismos que contribuyan a su formación integral, tomando en cuenta los contextos sociales, territoriales, económicos, lingüísticos y culturales específicos en la elaboración y aplicación de las políticas educativas en sus distintos tipos y modalidades.\nArtículo Reformado\nArtículo 66. La autoridad educativa estatal creará para cada educando desde educación inicial hasta media superior, un expediente único en el que se contengan los datos sobre su trayectoria académica. En todo momento, las autoridades educativas del\nEstado deberán atender las disposiciones aplicables en materia de transparencia y protección de datos personales.\nLa información del expediente al que se refiere este artículo se proporcionará a la autoridad educativa federal en los términos que señale para actualizar el Sistema de\nInformación y Gestión Educativa previsto en la Ley General de Educación.\nArtículo 67. Las autoridades educativas del Estado, en el ámbito de sus respectivas competencias, ofrecerán servicios de orientación educativa, de trabajo social y de psicología desde la educación básica hasta la educación superior, de acuerdo con la suficiencia presupuestal y a las necesidades de cada plantel, a fin de fomentar una conciencia crítica que perfile a los educandos en la selección de su formación a lo largo de la vida para su desarrollo personal y contribuir al bienestar de sus comunidades.\nAsimismo, las autoridades educativas del Estado, en coordinación con la Secretaría de Salud del Estado, deberán emitir programas o protocolos de promoción, prevención y abordaje de la salud mental de las y los estudiantes, mismos que se deberán revisar y actualizar periódicamente conforme el plazo que las autoridades determinen, el cual no podrá ser mayor de cinco años.\nPárrafo Adicionado los cursos, que les permita obtener conocimientos mínimos de actuación en situaciones donde la o el estudiante requiera apoyo respecto su salud mental.\nPárrafo Adicionado\nLey de Educación del Estado de Baja California. Página 32\nLas áreas especializadas en psicología a que se refiere el artículo 73 de esta Ley, coadyuvarán con los centros escolares que así lo soliciten, en la capacitación y/o aplicación del programa o protocolos de salud mental.\nPárrafo Adicionado\nArtículo Reformado\nCapítulo II\nDel Fomento de Estilos de Vida Saludables en el Entorno Escolar\nArtículo 68. Las autoridades educativas del Estado, en el ámbito de su competencia, aplicará y vigilará el cumplimiento de los lineamientos que emita la autoridad educativa federal sobre la distribución de los alimentos y bebidas preparados y procesados dentro de toda escuela.\nLas autoridades educativas del Estado realizarán acciones de vigilancia para que los alimentos y bebidas que se preparen y procesen al interior de las escuelas cumplan con el valor nutritivo para la salud de los educandos.\nArtículo 69. Dentro de las escuelas queda prohibida la distribución y comercialización de los alimentos que no favorezcan la salud de los educandos, así como las bebidas energizantes.\nLas autoridades educativas estatal y municipal promoverán ante las autoridades correspondientes, la prohibición de la venta de alimentos con bajo valor nutritivo y alto contenido calórico en las inmediaciones de los planteles educativos, así como la emisión de los lineamientos correspondientes a fin de que en las escuelas públicas de educación básica del Estado se entreguen desayunos calientes diarios, en términos de lo previsto en la\nArtículo 70. Las autoridades educativas estatal y municipal establecerán las bases para fomentar estilos de vida saludables que prevengan, atiendan y contrarresten, en su caso, el sobrepeso y la obesidad entre los educandos, como la activación física, el deporte escolar, la educación física, los buenos hábitos nutricionales, entre otros. En materia de la promoción de la salud escolar, las autoridades educativas estatal y municipal considerarán las Normas Oficiales Mexicanas respectivas; así como los programas o protocolos que se emitan relacionados con la salud mental de las y los estudiantes.\nArtículo Reformado\nArtículo 71. Las cooperativas que funcionen con la participación de la comunidad la autoridad educativa estatal.\nLey de Educación del Estado de Baja California. Página 33\nArtículo 72. La autoridad educativa estatal y municipal, de acuerdo con la suficiencia presupuestal, impulsarán programas alimentarios para los educandos a partir de microempresas locales, en escuelas ubicadas en zonas conforme a los índices de pobreza, alta marginación y vulnerabilidad social.\nArtículo 72 BIS. El incumplimiento o inobservancia a las disposiciones contenidas en el presente Capítulo, se considerarán acciones u omisiones contrarias al interés superior de la niñez.\nArtículo Adicionado\nCapítulo III\nDe la Cultura de la Paz, Convivencia Democrática en las Escuelas y Entornos\nEscolares Libres de Violencia\nArtículo 73. En la impartición de educación para menores de dieciocho años, las autoridades educativas estatal y municipal, y los organismos descentralizados que imparten educación en el Estado, en coordinación con otras áreas de gobierno competentes, tomarán medidas que aseguren a las y los educandos la protección y el cuidado necesario para preservar su integridad física, psicológica y social sobre la base del respeto a su dignidad y derechos, y que la aplicación de la disciplina escolar sea compatible con su edad y sexo, de conformidad con los lineamientos y protocolos de seguridad que para tal efecto se establezcan.\nPárrafo Reformado\nPara tal efecto, las autoridades escolares entregarán un Protocolo de Actuación para la entrega y salida de las y los alumnos, así como las medidas a tomar ante cualquier eventualidad que pudiere poner en riesgo la vida, integridad y dignidad de las y los educandos. Además, se sujetarán las escuelas públicas y privadas a las disposiciones de esta ley e indicaciones que, en cumplimiento a la misma, ordene la autoridad Educativa\nEstatal.\nPárrafo Reformado\nEl personal docente y el personal que labora en los planteles educativos de educación deberán estar capacitados para tomar las medidas que aseguren la protección, el cuidado de las y los educandos y la corresponsabilidad que tienen al estar encargados de su custodia, así como protección contra toda forma de maltrato, violencia, perjuicio, daño, agresión, abuso, trata, explotación sexual o laboral y drogas, para cuyo efecto, deberán estipulan, así como en la Ley General de Educación, respetando siempre los derechos fundamentales y constitucionales de las y los educandos.\nPárrafo Reformado\nEn caso de que el personal docente, el personal que labora en los planteles educativos, así como las autoridades educativas del Estado, tengan conocimiento de la comisión de algún hecho que la Ley señale como delito en agravio de las y los educandos, lo\nLey de Educación del Estado de Baja California. Página 34 harán del conocimiento inmediato de la autoridad correspondiente, para que sea esta la que acuda, y conforme a los procedimientos de ley actúe en consecuencia del hecho suscitado.\nPárrafo Reformado acumulados en un mes, sin que exista justificación por escrito de madres y padres de familia o tutores, las autoridades escolares de las escuelas públicas y particulares con reconocimiento de validez oficial de estudios del tipo básico informarán primeramente y de manera inmediata a las autoridades educativas estatal y municipal, la cual emitirá una Alerta\nTemprana y será remitida a la Procuraduría de Protección de Niñas, Niños y Adolescentes del Estado para los efectos correspondientes. Una vez hecho lo anterior, podrán contactar a la madre, padre o tutor como medida de seguimiento.\nPárrafo Reformado\nPor cada tres zonas que comprenden las escuelas que se encuentren en estado de vulnerabilidad, pertenecientes a la educación básica y educación media superior en el\nSistema Educativo Estatal, deberá existir un área especializada en psicología para la rápida y oportuna atención de los educandos, principalmente aquellos que sean canalizados y detectados por las autoridades escolares y que se evidencié problemas de aprendizaje, maltrato físico, psicoemocional, o presentan conductas violentas, sean o hayan sido víctimas de cualquier tipo de abuso que colocara en riesgo su desarrollo integral, así como cualquier trauma o stress postraumático. De igual manera en el área especializada en psicología deberá de ofrecer asesoría y apoyo a maestras y maestros, madres y padres de familia o tutores para la oportuna y acertada atención a los educandos dentro de los planteles educativos regulares de una manera colegiada o integral.\nEl cabal cumplimiento de esta disposición estará sujeta a la planeación o disposición presupuestaria.\nLos psicólogos y demás personal que se contrate para desempeñarse en las áreas especializadas en psicología tendrán la categoría de trabajadores de confianza adscritos a las autoridades educativas estatal y municipal o a los organismos descentralizados que imparten educación en el Estado.\nArtículo Reformado\nArtículo 73 BIS. Con la finalidad de preservar la salud mental de niñas, niños, adolescentes y jóvenes en nivel básico y medio superior, la Secretaría de Educación en coordinación con la Secretaría de Salud del Estado, en el marco de sus respectivas competencias, implementarán acciones, programas o protocolos de actuación tendientes a prevenir, detectar, identificar y canalizar necesidades especiales en niñas, niños y adolescentes y jóvenes.\nArtículo Adicionado\nArtículo Reformado\nLey de Educación del Estado de Baja California. Página 35\nArtículo 73 TER. Con la finalidad de promover la salud y estabilidad psicoemocional de niñas y adolescentes en nivel básico y media superior, la Secretaría de Educación en coordinación con la Secretaría de Salud del Estado, en el marco de sus respectivas competencias, promoverán la implementación de acciones, programas o protocolos de menstruación de niñas, mujeres y personas menstruantes, tendiente a evitar ausentismo.\nArtículo Adicionado\nArtículo 74. Las autoridades educativas estatal y municipal, en el ámbito de su competencia, promoverán la cultura de la paz y no violencia para generar una convivencia democrática en los centros escolares basada en el respeto a la dignidad de las personas y de los derechos humanos, tanto de las y los educandos, como del personal administrativo y académico. Realizarán acciones que favorezcan el sentido de comunidad, solidaridad y protección, donde se involucren las y los educandos, el personal docente, personal administrativo, madres y padres de familia o tutores, así como el personal de apoyo y asistencia a la educación, y con funciones directivas o de supervisión para prevenir y atender la violencia que se ejerza en el entorno escolar.\nPárrafo Reformado\nPara cumplir con lo establecido en este artículo, se llevarán a cabo, entre otras, las siguientes acciones:\nI. Diseñar y aplicar estrategias educativas que generen ambientes basados en una cultura de la paz, para fortalecer la cohesión comunitaria y una convivencia democrática;\nII. Promover en la formación docente, contenidos y prácticas relacionados con la cultura de la paz y la resolución pacífica de conflictos;\nIII. Proporcionar atención psicosocial y, en su caso, orientación sobre las vías legales a la persona agresora y a la víctima de violencia o maltrato escolar, ya sea psicológico, físico o cibernético, así como a las receptoras indirectas de maltrato dentro de las escuelas;\nIV. Establecer los mecanismos gratuitos de asesoría, orientación, reporte de casos y de protección para las niñas, niños, adolescentes y jóvenes que estén involucrados en violencia o maltrato escolar, ya sea psicológico, físico o cibernético, procurando ofrecer servicios remotos de atención, a través de una línea pública telefónica u otros medios electrónicos;\nV. Solicitar a la Comisión Nacional para la Mejora Continua de la Educación estudios, investigaciones, informes y diagnósticos que permitan conocer las causas y la incidencia del fenómeno de violencia o maltrato entre escolares en cualquier tipo, ya sea psicológica, física o cibernética, así como su impacto en el entorno escolar en la deserción de los centros educativos, en el desempeño académico de los educandos, en sus vínculos familiares y\nLey de Educación del Estado de Baja California. Página 36 comunitarios y el desarrollo integral de todas sus potencialidades, así como las medidas para atender dicha problemática;\nVI. Celebrar convenios de cooperación, coordinación y concertación con los sectores públicos, privados y sociales, para promover los derechos de las niñas, niños, adolescente y jóvenes, y el fomento de la cultura de la paz, resolución no violenta de conflictos, fortalecimiento de la cohesión comunitaria y convivencia armónica dentro de las escuelas;\nVII. Hacer del conocimiento de las autoridades competentes las conductas que pueden resultar constitutivas de infracciones o delitos cometidos en contra de las niñas, los niños, adolescentes y jóvenes por el ejercicio de cualquier maltrato o tipo de violencia en el entorno escolar, familiar o comunitario, así como promover su defensa en las instancias administrativas o judiciales;\nVIII. Realizar campañas, mediante el uso de las tecnologías de la información, comunicación, conocimiento y aprendizaje digital o televisivo, que concienticen sobre la importancia de una convivencia libre de violencia o maltrato, ya sea psicológico, físico o cibernético, en los ámbitos familiar, comunitario, escolar y social;\nFracción Reformada\nIX. Establecerá reglas básicas a efecto de crear protocolos, con el objeto fortalecer la cultura de la paz y la no violencia dentro de los centros escolares de nivel básico, medio y superior, garantizando el respeto a las garantías y derechos fundamentales tanto de las y los educandos como del personal administrativo y académico; y,\nFracción Adicionada, recorriéndose la subsecuente\nX. Elaborar y difundir materiales educativos para la prevención y atención de los tipos y modalidades de maltrato escolar, así como coordinar campañas de información sobre las mismas.\nArtículo Reformado\nArtículo 75. La autoridad educativa estatal y municipal, en el ámbito de su respectiva competencia, emitirá los lineamientos para los protocolos de actuación que sean necesarios para el cumplimiento del presente capítulo. Entre los protocolos que emita, deberán escolar, familiar o comunitario contra cualquier integrante de la comunidad educativa, para educativo. A su vez, determinarán los mecanismos para la mediación y resolución pacífica de controversias que se presenten entre los integrantes de la comunidad educativa.\nArtículo 76. La autoridad educativa estatal y municipal emitirán los lineamientos para cursen el tipo básico. Dichas disposiciones contendrán los esquemas de subsidios que, en su caso, contemple las autoridades educativas estatal y municipal.\nLey de Educación del Estado de Baja California. Página 37\nTítulo Quinto\nCapítulo I\nArtículo 77. Las maestras y los maestros son agentes fundamentales del proceso educativo y, por tanto, se reconoce su contribución a la transformación social. Los esfuerzos y las acciones de las autoridades educativas del Estado en la revalorización de las maestras y los maestros para efectos de esta Ley, perseguirá los siguientes fines:\nI. Priorizar su labor para el logro de metas y objetivos centrados en el aprendizaje de los educandos;\nII. Fortalecer su desarrollo y superación profesional mediante la formación, capacitación y actualización;\nIII. Fomentar el respeto a la labor docente y a su persona por parte de las autoridades educativas del Estado, de los educandos, madres y padres de familia o tutores y sociedad en general; así como fortalecer su liderazgo en la comunidad;\nIV. Reconocer su experiencia, así como su vinculación y compromiso con la comunidad y el entorno donde labora, para proponer soluciones de acuerdo con su contexto educativo;\nV. Priorizar su labor pedagógica y el máximo logro de aprendizaje de los educandos sobre la carga administrativa;\nVI. Promover su formación, capacitación y actualización de acuerdo con su evaluación diagnóstica y en el ámbito donde desarrolla su labor;\nVII. Impulsar su capacidad para la toma de decisiones cotidianas respecto a la planeación educativa;\nVIII. Otorgar, en términos de las disposiciones aplicables, un salario profesional digno, un nivel de vida decoroso para ellos y su familia; arraigarse en las comunidades en las que trabajan y disfrutar de vivienda digna; así como disponer del tiempo necesario para la personal y profesional, y\nIX. Respetar sus derechos reconocidos en las disposiciones legales aplicables.\nLey de Educación del Estado de Baja California. Página 38\nArtículo 78. La autoridad educativa estatal colaborará con la autoridad educativa federal en la revisión permanente de las disposiciones, los trámites y procedimientos, con objeto de simplificarlos, de reducir las cargas administrativas de los docentes, de alcanzar más horas efectivas de clase y de fortalecimiento académico, en general, de lograr la prestación del servicio educativo con mayor pertinencia y eficiencia.\nEn las actividades de supervisión e inspección la autoridad educativa estatal dará prioridad, respecto de los aspectos administrativos, a los apoyos técnicos, didácticos y demás para el adecuado desempeño de la función docente. Asimismo, se fortalecerá la capacidad de gestión de las autoridades escolares y la participación de las madres y padres de familia o tutores.\nArtículo 79. La autoridad educativa estatal y la autoridad educativa municipal que impartan educación básica, efectuarán las acciones necesarias para que los movimientos y pagos de ese personal, se realicen conforme a la normatividad federal y estatal aplicable.\nCapítulo II\nDe los Procesos de Admisión, Promoción y Reconocimiento en Educación Básica y en\nEducación Media Superior\nArtículo 80. Para el ingreso, la promoción en la función y en el servicio, así como para el otorgamiento de reconocimientos, del ejercicio docente en instituciones públicas del\nEstado en educación básica y media superior, se estará a lo dispuesto por Ley General del\nSistema para la Carrera de las Maestras y los Maestros.\nEn el caso de los docentes de educación indígena que no tengan licenciatura como nivel mínimo de formación, deberán participar en los programas de capacitación que diseñe la autoridad educativa estatal y certificar su bilingüismo en la lengua indígena que corresponda y el español.\nSentencia de Acción de Inconstitucionalidad 18/2021\nPárrafo Reformado\nPara el proceso de ingreso, promoción en la función y en el servicio, otorgamiento de reconocimientos, del ejercicio docente en instituciones públicas del Estado en educación básica y media superior, se deberá realizar sesiones en vivo, transmitiéndola por algún medio electrónico vía internet, de conformidad con los artículos 68, 69 y 70 de la Ley de\nPárrafo Adicionado\nArtículo Reformado\nCapítulo III\nDel Sistema Integral de Formación Actualización, Capacitación y Superación\nProfesional para Maestros\nLey de Educación del Estado de Baja California. Página 39\nArtículo 81. La autoridad educativa estatal constituirá el sistema integral de formación actualización, capacitación y superación profesional para maestros del Estado, para que las maestras y los maestros ejerzan su derecho de acceder a éste, en términos de lo establecido en la Ley Reglamentaria del artículo 3o. de la Constitución Política de los\nEstados Unidos Mexicanos, en materia de Mejora Continua de la Educación.\nLas opciones de formación, actualización, capacitación y superación profesional, tendrán contenidos con perspectiva de género, enfoque de derechos humanos, además de tomar en cuenta los contextos locales y regionales de la prestación de los servicios educativos, así como las condiciones de vulnerabilidad social.\nArtículo 82. El sistema integral de formación, actualización, capacitación y superación profesional para maestros del Estado tendrá los siguientes fines:\nI. La formación, con nivel de licenciatura, de maestras y maestros de educación básica con los conocimientos y aptitudes necesarios para el aprendizaje y el desarrollo integral de los educandos;\nII. La formación continua, la actualización de conocimientos de las humanidades, las artes, la ciencia, la tecnología e innovación y otras que contribuyan a la superación docente de las maestras y los maestros en servicio;\nIII. La promoción de programas de especialización, maestría y doctorado para una orientación integral, adecuados a las necesidades, contextos regionales y locales de la prestación de los servicios educativos y de los recursos disponibles;\nIV. La realización de programas de inducción, actualización, capacitación y superación profesional para las maestras y los maestros de educación media superior;\nV. La promoción del enfoque de derechos humanos, de igualdad sustantiva, la cultura de la paz y la integridad en la práctica de las funciones de las maestras y los maestros, y\nVI. El desarrollo de la investigación pedagógica y la difusión de la cultura educativa.\nLa implementación del sistema integral de formación actualización, capacitación y suficiencia presupuestaria del ejercicio fiscal correspondiente.\nArtículo 83. La autoridad educativa estatal podrá suscribir convenios de colaboración e instituciones de educación superior nacionales o extranjeras, para ampliar las opciones de formación, capacitación y actualización que para tal efecto establezca la Comisión Nacional para la Mejora Continua de la Educación.\nLey de Educación del Estado de Baja California. Página 40\nAsimismo, impulsarán los proyectos pedagógicos y de desarrollo de la docencia generados por las instituciones de formación docente y los sectores académicos, de conformidad con los criterios que emita la Comisión.\nCapítulo IV\nDel Fortalecimiento la Formación Docente\nArtículo 84. Las personas egresadas de las instituciones formadoras de docentes del\nEstado contarán con el conocimiento de diversos enfoques pedagógicos y didácticos que les permita atender las necesidades de aprendizaje de las niñas, los niños, adolescentes y jóvenes.\nEn los planes y programas de estudio de las instituciones formadoras de docentes, se promoverá el desarrollo de competencias en educación inicial y con enfoque de inclusión para todos los tipos educativos; asimismo, se considerarán modelos de formación docente especializada en la educación especial que atiendan los diversos tipos de discapacidad.\nSentencia de Acción de Inconstitucionalidad 18/2021\nArtículo Reformado\nArtículo 85. La autoridad educativa estatal fortalecerá a las instituciones públicas de formación docente, para lo cual, tendrá a su cargo, entre otras, las siguientes acciones:\nI. Propiciar la participación de la comunidad de las instituciones formadoras de docentes del Estado en las convocatorias de la autoridad educativa federal para la construcción colectiva de sus planes y programas de estudio, con especial atención en los contenidos regionales y locales, además de los contextos escolares, la práctica en el aula y los colectivos docentes, y la construcción de saberes para contribuir a los fines de la nueva escuela mexicana;\nII. Promover la movilidad de los docentes en los diferentes sistemas y subsistemas educativos, particularmente en aquellas instituciones que tengan amplia tradición y experiencia en la formación pedagógica y docente;\nIII. Fomentar la creación de redes académicas para el intercambio de saberes y educativos;\nIV. Proporcionar las herramientas para realizar una gestión pedagógica y curricular que priorice el máximo logro del aprendizaje y desarrollo integral de los educandos;\nV. Promover la integración de un acervo físico y digital en las instituciones formadoras de docentes, de bibliografía actualizada que permita a las maestras y los maestros acceder a las propuestas pedagógicas y didácticas innovadoras;\nLey de Educación del Estado de Baja California. Página 41\nVI. Promover la acreditación de grados académicos superiores de los docentes;\nVII. Promover la investigación educativa y su financiamiento, a través de programas investigación;\nVIII. Promover la colaboración con Instituciones Formadoras de Docentes Nacionales e Internacionales;\nFracción Reformada\nIX. Garantizar la actualización permanente, a través de la capacitación, la formación, así como programas e incentivos para su desarrollo profesional; y,\nFracción Adicionada, recorriéndose la subsecuente\nX. Promover la capacitación a las y los docentes en materia de primeros auxilios.\nArtículo Reformado\nArtículo 86. La autoridad educativa estatal emitirá los lineamientos para proporcionar la formación inicial en el Estado, los cuales atenderán la programación estratégica que se realice en el marco del Sistema Educativo Nacional prevista en la Ley General de\nEducación.\nTítulo Sexto\nDe los Planteles Educativos\nCapítulo Único\nDe las Condiciones de los Planteles Educativos para Garantizar su Idoneidad y la\nSeguridad de las Niñas, Niños, Adolescentes y Jóvenes\nArtículo 87. Los planteles educativos constituyen un espacio fundamental para el proceso de enseñanza aprendizaje, donde se presta el servicio público de educación por parte de las autoridades educativas del Estado o por los particulares con autorización o reconocimiento de validez oficial de estudios.\nCon el acuerdo de las autoridades, madres y padres de familia o tutores y la comunidad, en la medida de sus posibilidades, funcionarán como un centro de aprendizaje comunitario, donde además de educar a niñas, niños, adolescentes y jóvenes, se integrará a social y de información sobre su entorno.\nPárrafo Reformado de Educación Extraescolar.\nArtículo Reformado\nLey de Educación del Estado de Baja California. Página 42\nArtículo 88. Los muebles e inmuebles destinados a la educación impartida por las autoridades educativas estatal y municipales, organismos descentralizados y por los\nEstado, así como los servicios e instalaciones necesarios para proporcionar educación, forman parte del Sistema Educativo Estatal.\nDichos muebles e inmuebles deberán cumplir con los requisitos de calidad, seguridad, funcionalidad, oportunidad, equidad, sustentabilidad, pertinencia, integralidad, accesibilidad, inclusividad e higiene, incorporando los beneficios del desarrollo de la ciencia y la innovación tecnológica, para proporcionar educación de excelencia, con equidad e inclusión, conforme a los lineamientos que para tal efecto emita la autoridad educativa federal.\nEl Control de plagas y organismos que puedan afectar la salud de los educandos constituye uno de los requisitos higiene señalados en el párrafo precedente, por lo que la autoridad educativa deberá coordinarse con las autoridades competentes para efectos de realizar fumigaciones periódicas con plaguicidas de bajo riesgo para la salud humana.\nPárrafo Adicionado\nLa autoridad educativa estatal y municipal coadyuvarán con la autoridad educativa federal para mantener actualizado el Sistema Nacional de Información de la Infraestructura\nFísica Educativa, a fin de realizar sobre ésta diagnósticos y definir acciones de prevención en materia de seguridad, protección civil y de mantenimiento de los muebles o inmuebles que se destinen al servicio educativo.\nLos bienes muebles e inmuebles, así como las instalaciones a que se refiere este artículo, que sean propiedad de particulares, continuarán siendo propiedad de dichos particulares.\nDestinar, dentro del plantel educativo, un espacio que cuente con botiquín de primero auxilios y un área de atención para el caso de emergencia o accidente ocurrido dentro del mismo, mismo que deberá estar perfectamente identificable.\nPárrafo Adicionado\nArtículo Reformado\nArtículo 89. Con la finalidad de garantizar el cumplimiento de los requisitos de construcción, diseño, seguridad, estructura, condiciones específicas o equipamiento de la infraestructura física educativa que sean obligatorios para cada tipo de obra, las autoridades educativas estatal y municipal, los Comités Escolares de Administración Participativa o sus equivalentes, los organismos descentralizados y los particulares que impartan educación en términos de esta Ley, atenderán las disposiciones que en la materia establezca la Ley\nGeneral para la Inclusión de Personas con Discapacidad, la Ley General de Bienes\nNacionales, la Ley General de Protección Civil, la Ley General de Responsabilidades\nAdministrativas, la Ley General de Asentamientos Humanos, Ordenamiento Territorial y\nDesarrollo Urbano, la Ley Federal sobre Monumentos y Zonas Arqueológicos, Artísticos e\nLey de Educación del Estado de Baja California. Página 43\nHistóricos, la Ley Federal para Prevenir y Erradicar la Discriminación, así como aquellas que se refieran a la materia de obra pública y servicios relacionados con la misma, adquisiciones, arrendamientos y servicios, además de los lineamientos emitidos por la autoridad educativa federal a los que se refiere el artículo 103 de la Ley General de Educación y las disposiciones legales y reglamentarias aplicables a nivel federal, estatal y municipal.\nLas universidades y demás instituciones de educación superior autónomas a que se refiere la fracción VII del artículo 3o. de la Constitución Política de los Estados Unidos\nMexicanos, se regularan en materia de infraestructura por sus órganos de gobierno y su normatividad interna.\nArtículo 90. Para que en un inmueble puedan prestarse servicios educativos, deben obtenerse las licencias, autorizaciones, avisos de funcionamiento y demás relacionados para su operación a efecto de garantizar el cumplimiento de los requisitos de construcción, diseño, seguridad, estructura, condiciones específicas o equipamiento que sean obligatorios para cada tipo de obra, en los términos y las condiciones de la normatividad municipal, estatal y federal aplicable. Además de lo anterior, deberá obtenerse un certificado de seguridad y operatividad escolar expedido por las autoridades correspondientes, en los términos que para tal efecto emita la autoridad educativa federal. Los documentos que acrediten el cumplimiento de dichos requisitos, deberán publicarse de manera permanente en un lugar visible del inmueble.\nTodos los planteles educativos, públicos o privados, deben cumplir con las normas de protección civil y de seguridad que emitan las autoridades de los ámbitos federal, estatal y municipal competentes, según corresponda.\nEn la educación que impartan los particulares con autorización o con reconocimiento de validez oficial de estudios, debe demostrarse además el cumplimiento de las obligaciones señaladas en el artículo 147, fracción II de la Ley General de Educación.\nArtículo 91. La autoridad educativa tanto estatal como municipal atenderán de manera prioritaria las escuelas que, por estar en localidades aisladas, zonas urbanas marginadas o con altos índices de pobreza, rurales y comunidades indígenas, tengan mayor posibilidad de rezago o abandono escolar, estableciendo condiciones físicas y de localidades.\nSentencia de Acción de Inconstitucionalidad 18/2021\nArtículo Reformado\nEn materia de inclusión se realizarán acciones, de manera gradual, orientadas a identificar, prevenir y reducir las barreras que limitan el acceso, permanencia, participación y del inmueble escolar.\nLey de Educación del Estado de Baja California. Página 44\nA partir de los programas que emita la Autoridad Educativa Federal, se garantizará la de Salud en coordinación con la autoridad educativa federal, así como de espacios para la activación física, la recreación, la práctica del deporte y la educación física.\nArtículo 92. El Ejecutivo Estatal, a través del Instituto de la Infraestructura Física\nEducativa de Baja California (INIFE), realizará las actividades correspondientes en materia de infraestructura física educativa para efecto de ejercer sus atribuciones referidas en este\nCapítulo y demás disposiciones legales aplicables.\nArtículo 93. La autoridad educativa estatal, en el ámbito de su respectiva competencia, deberá desarrollar la planeación financiera y administrativa que contribuya a optimizar los recursos en materia de espacios educativos al servicio del Sistema Educativo\nEstatal, realizando las previsiones necesarias para que los recursos económicos destinados para ese efecto sean prioritarios y oportunos. Las respectivas obligaciones se atenderán de manera gradual y progresiva, de acuerdo con la disponibilidad presupuestal, debiendo establecer las condiciones fiscales, presupuestales, administrativas y jurídicas para facilitar y fomentar la inversión en la materia.\nAsimismo, promoverán mecanismos para acceder a fuentes alternas de financiamiento conforme lo establezcan las disposiciones aplicables.\nArtículo 94. Para el mantenimiento de los muebles e inmuebles, así como los servicios e instalaciones necesarios para proporcionar los servicios educativos, concurrirán los gobiernos federales, estatales, municipales y, de manera voluntaria, madres y padres de familia o tutores y demás integrantes de la comunidad.\nLa autoridad educativa estatal promoverá la participación directa de los municipios para dar mantenimiento y proveer de equipo básico a las escuelas públicas federales, estatales y municipales. La autoridad educativa municipal coadyuvará en el mantenimiento de los planteles educativos y de los servicios de seguridad, agua y luz.\nLos particulares, ya sea personas físicas o morales, así como los Comités Escolares de Administración Participativa, podrán coadyuvar en el mantenimiento de las escuelas públicas, previo acuerdo con la autoridad educativa estatal. Las acciones que se deriven de la aplicación de este párrafo, en ningún caso implicarán la sustitución de los servicios del personal de la escuela, tampoco generarán cualquier tipo de contraprestación a favor de los particulares.\nArtículo 95. Los planteles educativos, de cualquier nivel que formen parte del\nSistema Educativo Estatal, no deberán consignar los nombres de los funcionarios públicos y representantes populares durante el desempeño de su encargo, el de sus cónyuges o\nLey de Educación del Estado de Baja California. Página 45 parientes hasta el segundo grado, ni el de los representantes sindicales del magisterio en funciones o por haber ocupado cargos de representación gremial. valores nacionales, maestras y maestros eméritos o nombres de personas ameritadas a quienes la Nación o el Estado deba exaltar para engrandecer, nuestra esencia popular y los símbolos patrios o conceptos e instituciones coincidentes con los fines educativos o valores nacionales.\nLa comunidad educativa del plantel podrá realizar propuestas ante la autoridad educativa estatal para la designación de las denominaciones mencionadas en el párrafo anterior.\nLa imagen institucional de los inmuebles destinados al servicio público educativo que presten las autoridades educativas del Estado deberá emplear colores neutros y no podrá identificarse con colores, lemas, imágenes o logotipos que se identifiquen con partidos políticos o instituciones religiosas.\nTítulo Séptimo\nDe la Mejora Continua de la Educación\nCapítulo Único\nDel Proceso de Mejora Continua de la Educación en el Estado.\nArtículo 96. La educación tendrá un proceso de mejora continua, el cual implica el desarrollo permanente del Sistema Educativo Estatal para el incremento del logro académico de los educandos. Tendrá como eje central el aprendizaje de los educandos, de todos los tipos, niveles y modalidades educativos.\nArtículo 97. La autoridad educativa estatal en el proceso de mejora continua se regirá por lo previsto en el Ley General de Educación y en la Ley Reglamentaria del Artículo 3o. de la Constitución Política de los Estados Unidos Mexicanos, en materia de mejora continua de la educación.\nEn el proceso de mejora continua en educación superior, la autoridad educativa validez oficial del tipo superior que implemente acciones para fortalecer la calidad educativa, así como el otorgamiento de la categoría de Institución de Excelencia, en términos del\nReglamento que para tales efectos se emita el Ejecutivo Estatal.\nLey de Educación del Estado de Baja California. Página 46\nArtículo 98. Con objeto de contribuir al proceso al que se refiere este Capítulo, la bajacalifornianos. integral aspectos sobre la infraestructura educativa y su equipamiento, el avance de los planes y programas educativos, la formación y prácticas docentes, la carga administrativa, la asistencia de los educandos, el aprovechamiento académico, el desempeño de las autoridades educativas y los contextos socioculturales, entre otros\nTítulo Octavo\nDel Financiamiento a la Educación\nCapítulo Único\nDel financiamiento a la educación\nArtículo 99. El Ejecutivo Federal y el Ejecutivo Estatal, con sujeción a las disposiciones de ingresos y gasto público correspondientes que resulten aplicables, concurrirán al financiamiento de la educación pública y de los servicios educativos, en los términos del artículo 119 primer párrafo de la Ley General de Educación.\nEl Ejecutivo Estatal propondrá en el proyecto de presupuesto de egresos de la entidad, la asignación de recursos de cada uno de los niveles de educación a su cargo para cubrir los requerimientos financieros, humanos, materiales y de infraestructura, así como de su mantenimiento, con el objetivo de dar continuidad y concatenación entre dichos niveles, con el fin de que la población escolar tenga acceso a la educación, con criterios de excelencia.\nEl Ejecutivo Estatal vigilará que el presupuesto señalado en el párrafo anterior, no sea utilizado de tal forma que promueva partidos, ideologías, servidores públicos, que puedan influir u orientar las preferencias electorales o simpatías políticas de las niñas, niños y jóvenes.\nEstado de Baja California, no serán transferibles y deberán aplicarse íntegra, oportuna y entidad. El Ejecutivo Estatal publicará en el Periódico Oficial del Estado, los recursos que la\nFederación le transfiera para tal efecto, en forma desagregada por nivel, programa educativo y establecimiento escolar.\nEl Ejecutivo Estatal prestará todas las facilidades y colaboración para que, en su caso, el Ejecutivo Federal y las instancias fiscalizadoras en el marco de la ley respectiva, verifiquen la correcta aplicación de dichos recursos.\nLey de Educación del Estado de Baja California. Página 47\nLas instituciones públicas de educación superior colaborarán, de conformidad con la ley en la materia, con las instancias fiscalizadoras para verificar la aplicación de los recursos que se le destinen derivados de este artículo.\nEn el caso de que tales recursos se utilicen para fines distintos, se instará a lo previsto en la legislación aplicable sobre las responsabilidades administrativas, civiles y penales que procedan.\nPara dar cumplimiento a la obligatoriedad y la gratuidad de la educación superior, La\nLey General de Educación Superior establecerá las disposiciones en materia de financiamiento.\nArtículo 100. El Ejecutivo Estatal, de conformidad con las disposiciones aplicables, proveerá lo conducente para que cada ayuntamiento reciba recursos para el cumplimiento de las responsabilidades que en términos del artículo 116 de la Ley General de Educación estén a cargo de la autoridad municipal\nArtículo 101. El Ejecutivo Estatal en todo momento procurará fortalecer las fuentes de financiamiento a la tarea educativa y destinar recursos presupuestarios crecientes, en términos reales, para la educación pública.\nArtículo 102. La autoridad educativa estatal, incluirá en el proyecto de presupuesto que sometan a la aprobación de la legislatura local, los recursos suficientes para fortalecer las capacidades de la administración escolar. Los programas para tal efecto responderán a los lineamientos que emita la autoridad educativa federal.\nTítulo Noveno\nDe la Corresponsabilidad Social en el Proceso Educativo\nCapítulo I\nDe la participación de madres y padres de familia o tutores\nArtículo 103. Las madres y padres de familia o tutores serán corresponsables en el proceso educativo de sus hijas, hijos o pupilos menores de dieciocho años para lo cual, además de cumplir con su obligación de hacerlos asistir a los servicios educativos, apoyarán su aprendizaje, y revisarán su progreso, desempeño y conducta, velando siempre por su bienestar y desarrollo.\nArtículo 104. Las autoridades educativas estatal y municipal desarrollarán actividades crianza enmarcadas en el ejercicio de los valores, los derechos de la niñez, buenos hábitos de salud, y desde una perspectiva de género e inclusiva se fomentará la educación\nLey de Educación del Estado de Baja California. Página 48 menstrual, la importancia de una hidratación saludable, alimentación nutritiva, práctica de la actividad física, disciplina positiva, prevención de la violencia, uso responsable de las tecnologías de la información, comunicación, lectura, conocimiento y aprendizaje digital y otros temas que permitan a madres y padres de familia o tutores, proporcionar una mejor atención a sus hijas, hijos o pupilos.\nArtículo Reformado\nArtículo 105. Son derechos de quienes ejercen la patria potestad o la tutela:\nI. Obtener inscripción en escuelas públicas o particulares para que sus hijas, hijos o pupilos menores de dieciocho años, que satisfagan los requisitos aplicables, reciban la educación preescolar, la primaria, la secundaria, la media superior y, en su caso, la educación inicial, en concordancia con los espacios disponibles para cada tipo educativo;\nII. A recibir de las autoridades escolares un Protocolo de Actuación para la entrega y salida de los alumnos, así como las medidas a tomar ante cualquier eventualidad que pudiere poner en riesgo la vida, integridad y dignidad del educando;\nIII. Participar activamente con las autoridades de la escuela en la que estén inscritos sus hijas, hijos o pupilos menores de dieciocho años, en cualquier problema relacionado con la educación de éstos, a fin de que, en conjunto, se aboquen a su solución;\nIV. Colaborar con las autoridades escolares, al menos una vez al mes, para la superación de los educandos y en el mejoramiento de los establecimientos educativos;\nV. Formar parte de las asociaciones de madres y padres de familia y de los consejos de participación escolar o su equivalente a que se refiere esta Ley;\nVI. Opinar, en los casos de la educación que impartan los particulares, en relación con las contraprestaciones que las escuelas fijen;\nVII. Conocer el nombre del personal docente y empleados adscritos en la escuela en la que estén inscritos sus hijas, hijos o pupilos, misma que será proporcionada por la autoridad escolar;\nVIII. Conocer los criterios y resultados de las evaluaciones de la escuela a la que asistan sus hijas, hijos o pupilos;\nIX. Conocer de los planes y programas de estudio proporcionados por el plantel educativo, sobre los cuales podrán emitir su opinión;\nX. Conocer el presupuesto asignado a cada escuela, así como su aplicación y los resultados de su ejecución;\nLey de Educación del Estado de Baja California. Página 49\nXl. Conocer la situación académica y conducta de sus hijas, hijos o pupilos en la vida escolar;\nXII. Manifestar, de ser el caso, su inconformidad ante las autoridades educativas correspondientes, sobre cualquier irregularidad dentro del plantel educativo donde estén inscritas sus hijas, hijos o pupilos menores de dieciocho años y sobre las condiciones físicas de las escuelas, y\nXIII. Las demás establecidas en la leyes y reglamentos respectivos.\nArtículo 106. Son obligaciones de quienes ejercen la patria potestad o la tutela:\nI. Como agente natural o primario de la educación, elegir para sus hijos o pupilos la\nInstitución Educativa pública o particular que les convenga;\nII. Hacer que sus hijas, hijos o pupilos menores de dieciocho años, reciban la educación preescolar, la primaria, la secundaria, la media superior y, en su caso, la inicial;\nIII. Participar en el proceso educativo de sus hijas, hijos o pupilos menores de dieciocho años, al revisar su progreso, desempeño y conducta, velando siempre por su bienestar y desarrollo;\nIV. Colaborar con las instituciones educativas en las que estén inscritos sus hijas, hijos o pupilos, en las actividades que dichas instituciones realicen;\nV. Informar a las autoridades educativas, los cambios que se presenten en la conducta y actitud de los educandos, para que se apliquen los estudios correspondientes, con el fin de determinar las posibles causas;\nVI. Acudir a los llamados de las autoridades educativas y escolares relacionados con la revisión del progreso, desempeño y conducta de sus hijas, hijos o pupilos menores de dieciocho años;\nVII. Promover la participación de sus hijas, hijos o pupilos menores de dieciocho años en la práctica de actividades físicas, de recreación, deportivas y de educación física dentro y fuera de los planteles educativos, como un medio de cohesión familiar y comunitaria, y\nVIII. Las demás establecidas en las leyes y reglamentos respectivos. artículo por parte de madres y padres de familia o tutores, las autoridades educativas podrán dar aviso a las instancias encargadas de la protección de los derechos de niñas, niños y adolescentes para los efectos correspondientes en términos de la legislación aplicable.\nLey de Educación del Estado de Baja California. Página 50\nArtículo 107. Las asociaciones de madres y padres de familia tendrán por objeto:\nI. Representar ante las autoridades escolares los intereses que en materia educativa sean comunes a los asociados;\nII. Colaborar para una mejor integración de la comunidad escolar, así como en el mejoramiento de los planteles educativos;\nIII. Informar a las autoridades educativas y escolares sobre cualquier irregularidad de que sean objeto los educandos;\nIV. Propiciar la colaboración de los docentes, madres y padres de familia o tutores, para salvaguardar la integridad de la comunidad educativa;\nV. Conocer de las acciones educativas y de prevención que realicen las autoridades para que los educandos, conozcan y detecten la posible comisión de hechos delictivos que les puedan perjudicar;\nVI. Sensibilizar a la comunidad, mediante la divulgación de material que prevenga la comisión de delitos en agravio de los educandos. Así como también, de elementos que procuren la defensa de los derechos de las víctimas de tales delitos;\nVII. Estimular, promover y apoyar actividades extraescolares que complementen y respalden la formación de los educandos;\nVIII. Gestionar el mejoramiento de las condiciones de los planteles educativos ante las autoridades correspondientes;\nIX. Alentar el interés familiar y comunitario para el desempeño del educando;\nFracción Reformada\nX. Proponer las medidas que estimen conducentes para alcanzar los objetivos señalados en las fracciones anteriores; y,\nFracción Reformada\nXI. Convenir con las instituciones de educación pública y con los particulares, sobre el cambio en el modelo de los uniformes escolares, con base al reglamento que determine la\nFracción Adicionada aspectos pedagógicos y laborales de los establecimientos educativos.\nLey de Educación del Estado de Baja California. Página 51 familia, en lo concerniente a sus relaciones con las autoridades escolares, se sujetarán a las disposiciones que la autoridad educativa federal y estatal señalen.\nArtículo Reformado\nCapítulo II\nDe los Consejos de Participación Escolar\nArtículo 108. Las autoridades educativas del Estado podrán promover, de conformidad con los lineamientos que establezca la autoridad educativa federal, la participación de la sociedad en actividades que tengan por objeto garantizar el derecho a la educación\nArtículo 109. Será decisión de cada escuela la instalación y operación del consejo de participación escolar o su equivalente el cual será integrado por las asociaciones de madres y padres de familia, maestras y maestros. Este consejo podrá:\nI. Coadyuvar para que los resultados de las evaluaciones al Sistema Educativo\nNacional contribuyan a la mejora continua de la educación, en los términos del artículo 136 de la Ley General de Educación;\nII. Proponer estímulos y reconocimientos de carácter social a alumnos, docentes, directivos y empleados de la escuela, que propicien la vinculación con la comunidad, con independencia de los que se prevean en la Ley General del Sistema para la Carrera de las\nMaestras y los Maestros;\nIII. Coadyuvar en temas que permitan la salvaguarda del libre desarrollo de la personalidad, integridad y derechos humanos de la comunidad educativa;\nIV. En coordinación con la Secretaría de Salud del Estado, promoverán y organizarán acciones de prevención para la salud a efecto de detectar oportunamente dentro de los planteles escolares la aparición y proliferación de enfermedades trasmisibles y no trasmisibles, con el objeto de dar aviso a la autoridad sanitaria para su control y tratamiento.\nAsimismo, difundirán campañas de vacunación y acciones de salubridad pública;\nV. Contribuir a reducir las condiciones sociales adversas que influyan en la educación, a través de proponer acciones específicas para su atención;\nVI. Llevar a cabo las acciones de participación, coordinación y difusión necesarias para la protección civil y la emergencia escolar, considerando las características y necesidades de las personas con discapacidad, así como el desarrollo de planes personales encuentren;\nSentencia de Acción de Inconstitucionalidad 18/2021\nFracción Reformada\nVII. Promover cooperativas con la participación de la comunidad educativa, las cuales\nLey de Educación del Estado de Baja California. Página 52 educandos. Su funcionamiento se apegará a los criterios de honestidad, integridad, transparencia y rendición de cuentas en su administración. La autoridad educativa estatal emitirá los lineamientos para su operación, de conformidad con las disposiciones aplicables;\nVIII. Coadyuvar en la dignificación de los planteles educativos, a través del Comité\nEscolar de Administración Participativa, de acuerdo con los lineamientos que emita la autoridad educativa federal, y\nIX. Realizar actividades encaminadas al beneficio de la propia escuela.\nEn caso de incumplimiento de alguna de las obligaciones a las que se refiere este artículo por parte de madres y padres de familia o tutores, las autoridades educativas podrán dar aviso a las instancias encargadas de la protección de los derechos de niñas, niños y adolescentes para los efectos correspondientes en términos de la legislación aplicable.\nArtículo Reformado\nArtículo 110. En cada municipio del Estado de Baja California, se podrá instalar y operar un consejo municipal de participación escolar en la educación, integrado por las autoridades municipales, asociaciones de madres y padres de familia, maestras y maestros.\nEste consejo, ante el ayuntamiento y la autoridad educativa respectiva, podrá:\nI. Gestionar el mejoramiento de los servicios educativos, la construcción y ampliación de escuelas públicas, tomando en cuenta las necesidades de accesibilidad para las personas con discapacidad, y demás proyectos de desarrollo educativo en el municipio;\nSentencia de Acción de Inconstitucionalidad 18/2021\nFracción Reformada\nII. Estimular, promover y apoyar actividades de intercambio, colaboración y participación interescolar en aspectos culturales, cívicos, deportivos y sociales;\nIII. Promover en la escuela y en coordinación con las autoridades, los programas de bienestar comunitario, particularmente con aquellas autoridades que atiendan temas de Niñas, Niños y Adolescentes;\nIV. Realizar propuestas que contribuyan a la formulación de contenidos locales para la elaboración de los planes y programas de estudio, las cuales serán entregadas a la autoridad educativa correspondiente;\nV. Coadyuvar a nivel municipal en actividades de seguridad, protección civil y emergencia escolar;\nVI. Promover la superación educativa en el ámbito municipal mediante certámenes interescolares;\nLey de Educación del Estado de Baja California. Página 53\nVII. Promover actividades de orientación, capacitación y difusión dirigidas a madres y padres de familia o tutores, para que cumplan cabalmente con sus obligaciones en materia educativa;\nVIII. Proponer la entrega de estímulos y reconocimientos de carácter social a los educandos, maestras y maestros, directivos y empleados escolares que propicien la vinculación con la comunidad;\nIX. Procurar la obtención de recursos complementarios, para el mantenimiento y equipamiento básico de cada escuela pública, y\nX. En general, realizar actividades para apoyar y fortalecer la educación en el municipio. Será responsabilidad de la persona titular de la presidencia municipal que, en el consejo se alcance una efectiva participación social que contribuya a elevar la excelencia en educación, así como, la difusión de programas preventivos de delitos que se puedan cometer en contra de niñas, niños y adolescentes o de quienes no tienen capacidad para comprender el significado del hecho o para resistirlo.\nArtículo Reformado\nArtículo 111. En el Estado de Baja California, operará un consejo estatal de participación social en la educación, como órgano de consulta, orientación y apoyo. En dicho\nConsejo se asegurará la participación de padres de familia y representantes de sus asociaciones, trabajadores de la educación y representantes de su organización sindical, quienes acudirán como representantes de los intereses laborales de los trabajadores, instituciones formadoras de docentes, autoridades educativas estatales y municipales, organizaciones de la sociedad civil cuyo objeto sea la educación, así como de sectores sociales y productivos del Estado especialmente interesados en la educación.\nPara tal efecto, el Consejo Estatal se integrará y operará de conformidad con los lineamientos que emita la autoridad educativa federal y las disposiciones que establezca la autoridad educativa estatal.\nEste consejo, promoverá y apoyará actividades extraescolares de carácter cultural, cívico, deportivo y de bienestar social; coadyuvar en actividades de protección civil y emergencia escolar; conocer las demandas y necesidades que emanen de los consejos escolares y municipales, gestionar ante las instancias competentes su resolución y apoyo, educación. carácter político o religioso.\nLey de Educación del Estado de Baja California. Página 54\nCapítulo III\nDel Servicio Social\nArtículo 112. Las personas beneficiadas directamente por los servicios educativos de instituciones de los tipos de educación superior y, en su caso, de media superior que así lo establezcan, deberán prestar servicio social o sus equivalentes, en los casos y términos que señalen las disposiciones legales. En éstas se preverá la prestación del servicio social o sus equivalentes como requisito previo para obtener título o grado académico correspondiente.\nLa Autoridad educativa estatal, en coordinación con las instituciones de educación respectivas, promoverán lo necesario a efecto de establecer diversos mecanismos de acreditación del servicio social o sus equivalentes y que éste sea reconocido como parte de su experiencia en el desempeño de sus labores profesionales.\nArtículo 113. La autoridad educativa estatal, en coordinación con las autoridades competentes, establecerá mecanismos para que cuente como prestación de servicio social, las tutorías y acompañamientos que realicen estudiantes a los educandos de preescolar, primaria, secundaria y media superior que lo requieran para lograr su máximo aprendizaje y desarrollo integral.\nCapítulo IV\nDe la Participación de los Medios de Comunicación\nArtículo 114. Los medios de comunicación masiva, de conformidad con el marco jurídico que les rige, en el desarrollo de sus actividades contribuirán al logro de los fines de la educación previstos en la Ley General de Educación.\nLa autoridad educativa estatal promoverá, ante las autoridades competentes, las acciones necesarias para dar cumplimiento al párrafo anterior, con apego a las disposiciones legales aplicables.\nArtículo 115. El Ejecutivo Estatal promoverá la contribución de los medios de comunicación a los fines de la educación. Para tal efecto procurará la creación de espacios y\nEstado, cuya transmisión sean en español y las diversas lenguas indígenas, en Lenguaje de\nSeñas, y empleando la descripción de imágenes, en beneficio de las personas con discapacidad visual.\nSentencia de Acción de Inconstitucionalidad 18/2021\nArtículo Reformado\nTítulo Décimo\nLey de Educación del Estado de Baja California. Página 55\nCapítulo Único\nConocimientos\nArtículo 116. Las instituciones del Sistema Educativo Estatal, de conformidad con los lineamientos que emita la autoridad educativa federal, expedirán certificados y otorgarán constancias, diplomas, títulos o grados académicos a las personas que hayan concluido estudios de conformidad con los requisitos establecidos en los planes y programas de estudio correspondientes con la tecnología avanzada utilizando mecanismos electrónicos de verificación de autenticidad para evitar falsificación. Dichos certificados, constancias, diplomas, títulos y grados deberán registrarse en el Sistema de Información y Gestión\nEducativa y tendrán validez en toda la República.\nArtículo 117. Los estudios realizados dentro del Sistema Educativo Estatal podrán, en su caso, declararse equivalentes entre sí por niveles educativos, grados o ciclos escolares, créditos académicos, asignaturas u otras unidades de aprendizaje, según lo establezca la regulación respectiva, la cual deberá facilitar el tránsito de educandos en el\nSistema Educativo Nacional.\nArtículo 118. La autoridad educativa estatal otorgará revalidaciones y equivalencias únicamente cuando estén referidas a planes y programas de estudio que se impartan en sus respectivas competencias, en los términos previstos en la Ley General de Educación.\nArtículo 119. La autoridad educativa estatal, por acuerdo de su titular y de conformidad con los lineamientos que emita la autoridad educativa federal podrá establecer procedimientos por medio de los cuales se expidan constancias, certificados, diplomas o títulos a quienes acrediten los conocimientos parciales respectivos a determinado grado escolar de educación básica o terminales que correspondan a cierto nivel educativo, adquiridos en forma autodidacta, de la experiencia laboral o a través de otros procesos educativos. adquiridos.\nTítulo Décimo Primero\nCapítulo I\nDisposiciones generales\nArtículo 120. Los particulares podrán impartir educación considerada como servicio público en términos de esta Ley, en todos sus tipos y modalidades, con la autorización o\nLey de Educación del Estado de Baja California. Página 56 autoridad educativa responsable, conforme a lo dispuestos por el artículo 3o. de la\nLey y demás disposiciones jurídicas aplicables.\nPor lo que concierne a la educación inicial, preescolar, la primaria, la secundaria, la normal y demás para la formación de maestras y maestros de educación básica, deberán obtener previamente, en cada caso, la autorización expresa del Ejecutivo Estatal por conducto de la autoridad educativa estatal, tratándose de estudios distintos a los antes mencionados podrán obtener el reconocimiento de validez oficial de estudios.\nLa autorización y el reconocimiento serán específicos para cada plan y programas de estudio; por lo que hace a educación básica y media superior, surtirá efectos a partir de su otorgamiento por parte de la autoridad correspondiente. Para impartir nuevos estudios se requerirá, según el caso, la autorización o el reconocimiento respectivos. En el tipo de educación superior, se estará a lo dispuesto en la Ley General de Educación Superior.\nLa autorización y el reconocimiento incorporan a las instituciones que los obtengan, respecto de los estudios a que la propia autorización o dicho reconocimiento se refieren al\nSistema Educativo Estatal.\nEn ningún caso, con motivo del cobro de colegiaturas o cualquier otra contraprestación, derivada de la educación que se imparta en términos de este artículo, se realizarán acciones que atenten contra la dignidad y los derechos de los educandos, de manera especial de las niñas y niños, incluyendo la retención de documentos personales y académicos.\nLa adquisición de uniformes y materiales educativos, así como de actividades extraescolares, no podrá condicionar la prestación del servicio público referido en esta Ley.\nLos educandos, las madres y padres de familia o tutores tendrán el derecho de adquirir los uniformes o materiales educativos con el proveedor de su preferencia, asimismo, a ropa adicional al uniforme que por condiciones climáticas se porte. reglamentación correspondiente, debiendo ser aprobado por la autoridad educativa.\nPárrafo Adicionado\nArtículo Reformado\nArtículo 121. Las autorizaciones y los reconocimientos de validez oficial de estudios se otorgarán cuando los solicitantes cuenten:\nI. Con personal docente que acredite la preparación adecuada para impartir educación;\nLey de Educación del Estado de Baja California. Página 57\nII. Con instalaciones que satisfagan las condiciones higiénicas, de seguridad, de protección civil, pedagógicas y de accesibilidad que la autoridad otorgante determine, en coadyuvancia con las autoridades competentes, conforme a los términos previstos en las disposiciones aplicables, y\nIII. Con planes y programas de estudio que la autoridad otorgante considere procedentes, en el caso de educación distinta de la inicial, preescolar, la primaria, la secundaria, la normal, y demás para la formación de maestros de educación básica.\nLa autoridad educativa estatal considerará como reconocido todos los planes y programas de estudio que establezcan las instituciones particulares de educación superior con categoría de Institución de Excelencia.\nAsimismo, desarrollar sus actividades conforme lo establecido por la presente Ley y demás disposiciones que deriven de ella.\nArtículo 122. Las autoridades educativas tendrán la obligación de publicar en el\nPeriódico Oficial del Estado, en su portal electrónico mediante dispositivos que faciliten la expedición de información de manera expedita y oportuna y por lo menos en uno de los periódicos impresos de mayor circulación en los Municipios de la Entidad, una relación de las instituciones a las que se haya concedido autorización o reconocimiento de validez oficial de estudios, así como aquellas a las que se hayan autorizado para revalidar o equiparar estudios. Así mismo publicarán oportunamente y en cada caso, la inclusión o supresión en dicha lista de las instituciones a las que se le otorguen, revoquen o retiren las autorizaciones o reconocimientos respectivos, así como aquellas que sean clausuradas. De igual manera el portal electrónico o la información por medio de los periódicos impresos contendrá la información y orientación a las y los estudiantes sobre los trámites a realizar para presentar denuncias ante la Secretaría en caso de haber sido víctimas de un fraude por parte de escuelas sin reconocimiento oficial.\nPárrafo Reformado\nDe igual manera indicarán en dicha publicación, los resultados una vez que apliquen las evaluaciones que, dentro del ámbito de sus atribuciones y de conformidad con lo dispuesto por esta Ley y demás disposiciones aplicables, les correspondan. evaluaciones correspondientes. validez oficial de estudios, deberán mencionar en la documentación que expidan y en la publicidad que hagan, una Leyenda que indique su calidad de incorporados, el número y fecha del acuerdo respectivo, modalidad en que se imparte, domicilio para el cual se otorgó, así como la autoridad que lo emitió.\nArtículo Reformado\nLey de Educación del Estado de Baja California. Página 58\nArtículo 123. Los particulares que impartan educación con autorización o con reconocimiento de validez oficial de estudios deberán:\nI. Cumplir con lo dispuesto en el artículo 3o. de la Constitución Política de los Estados\nUnidos Mexicanos, en la Ley General de Educación, en la presente Ley y demás disposiciones aplicables;\nII. Cumplir con los planes y programas de estudio que las autoridades educativas competentes hayan determinado o considerado procedentes y mantenerlos actualizados;\nIII. Otorgar becas que cubran la impartición del servicio educativo, las cuales no podrán ser inferiores al cinco por ciento del total de alumnos inscritos en cada plan y programa de estudios con autorización o reconocimiento de validez oficial de estudios, las cuales distribuirá por nivel educativo y su otorgamiento o renovación no podrá condicionarse a la aceptación de ningún crédito, gravamen, servicio o actividad extracurricular a cargo del becario. Debiendo procurar un porcentaje de becas a deportistas destacados y a la excelencia académica.\nLas becas que las escuelas particulares concedan a los hijos o familiares de sus trabajadores no deberán de considerarse dentro del porcentaje a otorgar. La disposición de un porcentaje mayor de becas al señalado en la presente fracción será decisión voluntaria de cada particular. El otorgamiento de estas se podrá distribuir en becas completas o parciales, no menores del veinticinco por ciento del costo de la colegiatura.\nIV. Corresponde a la autoridad educativa estatal la supervisión de la adecuada asignación de las becas a las que se refiere la fracción anterior, con la finalidad de contribuir al logro de la equidad educativa; para tal efecto atenderá los lineamientos que emita la autoridad educativa federal mediante los cuales se realizará dicha asignación en comités en educación en los términos de la presente Ley;\nV. Cumplir los requisitos previstos en el artículo 121 de esta Ley;\nVI. Cumplir y colaborar en las actividades de evaluación y vigilancia que las autoridades competentes realicen u ordenen;\nVII. Proporcionar la información que sea requerida por las autoridades competentes;\nVIII. Entregar a la autoridad educativa la documentación e información necesaria que permitan verificar el cumplimiento de los requisitos para seguir impartiendo educación, conforme a los lineamientos emitidos para tal efecto;\nLey de Educación del Estado de Baja California. Página 59\nIX. Solicitar el refrendo del reconocimiento de validez oficial de estudios al término de la vigencia que se establezca, en los términos de esta Ley y demás disposiciones aplicables;\nX. Dar aviso a la autoridad educativa competente el cambio de domicilio donde autorización o reconocimiento de validez oficial de estudios respectiva, para que conforme al procedimiento que se determine en las disposiciones aplicables, se dé inicio al procedimiento de retiro o revocación;\nFracción Reformada\nXl. No realizar prácticas nocivas de carácter económicas administrativas que perjudiquen al desarrollo educativo de los educandos o padres de familia como lo son: retención de documentos oficiales por falta de pago de colegiaturas, imposición de compra de útiles escolares, uniformes, libros de texto, materiales de aseo en comercios exclusivos; así como la obligación de realizar pagos extraordinarios para la realización de festejos ajenos a los fines de la educación; así como la compra y venta de objetos promocionales; y,\nFracción Reformada\nXII. Solicitar al personal educador, docente, profesorado y/o maestro, título profesional, cédula profesional, registro profesional estatal o en su caso la autorización provisional y tratándose de especialistas, cédula expedida por la autoridad educativa competente y certificado vigente otorgado por el Consejo de Especialidad Médica correspondiente a la rama médica de la que derive la formación educativa que imparta.\nFracción Adicionada\nArtículo Reformado\nArtículo 124. Los particulares que presten servicios por los que se impartan estudios sin reconocimiento de validez oficial, deberán mencionarlo en su correspondiente documentación y publicidad.\nCapítulo II\nDe los Mecanismos para el Cumplimiento de los Fines de la Educación impartida por los Particulares\nArtículo 125. Con la finalidad de que la educación que impartan los particulares\nMexicanos y la presente Ley; Las autoridades que otorguen autorizaciones y reconocimientos de validez oficial de estudios llevarán a cabo, dentro del ámbito de su educativa estatal, acciones de vigilancia por lo menos una vez al año, a las instituciones que reconocimientos, o que, sin estar incorporadas al Sistema Educativo Estatal, deban cumplir con las disposiciones de la presente Ley; además podrán requerir en cualquier momento información o documentación relacionada con la prestación u oferta del servicio educativo.\nLey de Educación del Estado de Baja California. Página 60\nPara efectos del presente artículo, las personas usuarias de estos servicios prestados por particulares podrán solicitar a las autoridades educativas correspondientes, la realización requisitos para impartir educación en los términos de este Título, incluido el aumento de los aplicables o que hayan sido establecidos en los instrumentos jurídicos que rigen las relaciones para la prestación de ese servicio.\nDerivado de las acciones de vigilancia, si las autoridades respectivas identifican que los particulares han aumentado los costos en la prestación de los servicios educativos sin apego a las disposiciones aplicables en la materia, darán aviso a las autoridades competentes para los efectos a los que haya lugar.\nArtículo 126. Son infracciones de quienes prestan servicios educativos:\nI. Incumplir cualesquiera de las obligaciones previstas en el artículo 123 de esta Ley;\nII. Suspender el servicio educativo sin que medie motivo justificado, caso fortuito o fuerza mayor;\nIII. Suspender actividades escolares o extraescolares en días y horas no autorizados por el calendario escolar aplicable, sin que medie motivo justificado, caso fortuito o fuerza mayor;\nIV. No utilizar los libros de texto que la autoridad educativa federal autorice y determine para la educación primaria y secundaria;\nV. Incumplir los lineamientos generales para el uso de material educativo para la educación básica;\nVI. Dar a conocer antes de su aplicación, los exámenes o cualesquiera otros instrumentos de admisión, acreditación o evaluación, a quienes habrán de presentarlos;\nVII. Expedir certificados, constancias, diplomas o títulos a quienes no cumplan los requisitos aplicables;\nVIII. Realizar o permitir la difusión de publicidad dentro del plantel escolar que no fomente la promoción de estilos de vida saludables en alimentación, así como la comercialización de bienes o servicios notoriamente ajenos al proceso educativo, con excepción de los de alimentos;\nIX. Efectuar actividades que pongan en riesgo la salud o la seguridad de los educandos o que menoscaben su dignidad;\nLey de Educación del Estado de Baja California. Página 61\nX. Ocultar a las madres y padres de familia o tutores, las conductas de los educandos menores de dieciocho años que notoriamente deban ser de su conocimiento;\nXI. Oponerse a las actividades de vigilancia, así como no proporcionar información veraz y oportuna;\nXII. Contravenir las disposiciones contempladas en los artículos 12, 13, 14, 82, párrafo tercero, por lo que corresponde a las autoridades educativas y 148, segundo párrafo de la Ley General de Educación;\nXIII. Administrar a los educandos, sin previa prescripción médica y consentimiento informado de sus madres y padres o tutores, medicamentos;\nXIV. Promover en los educandos, por cualquier medio, el uso de medicamentos que contengan sustancias psicotrópicas o estupefacientes;\nXV. Expulsar, segregar o negarse a prestar el servicio educativo a personas con discapacidad o que presenten problemas de aprendizaje o a mujeres embarazadas y personas gestantes; obligar a las y los educandos a someterse a tratamientos médicos para condicionar su aceptación o permanencia en el plantel, o bien, presionar de cualquier manera a sus madres y padres de familia o tutores para que se los realicen, salvo causa debidamente justificada a juicio de las autoridades educativas;\nSentencia de Acción de Inconstitucionalidad 18/2021\nFracción Reformada\nXVI. Incumplir con las medidas correctivas o precautorias derivadas de las visitas;\nXVII. Ostentarse como plantel incorporado sin estarlo;\nXVIII. Incumplir con lo dispuesto en el artículo 121 de esta Ley;\nXIX. Impartir la educación inicial, preescolar, primaria, secundaria, normal y demás para la formación de docentes de educación básica, sin contar con la autorización correspondiente;\nXX. Cambiar de domicilio sin la autorización previa de las autoridades educativas competentes;\nXXI. Otorgar revalidaciones o equivalencias sin observar las disposiciones aplicables;\nXXII. Retener documentos personales y académicos por falta de pago;\nLey de Educación del Estado de Baja California. Página 62\nXXIII. Condicionar la prestación del servicio público de educación a la adquisición de uniformes, materiales educativos, útiles escolares nuevos o de marcas específicas o que deban adquirirse en algún sitio exclusivo, así como de actividades extraescolares;\nFracción Reformada\nXXIV. Omitir dar a conocer por escrito a las personas usuarias de los servicios educativos, previamente a la inscripción para cada ciclo escolar, el costo total de la colegiatura o cualquier otra contraprestación;\nXXV. Difundir o transmitir datos personales sin consentimiento expreso de su titular o, en su caso, de la madre y padre de familia o tutor, y\nXXVI. Incumplir cualesquiera de los demás preceptos de esta Ley, así como las disposiciones expedidas con fundamento en ella.\nArtículo Reformado\nArtículo 127. Las infracciones enumeradas en el artículo anterior serán sancionadas de la siguiente manera:\nI. Imposición de multa, para lo cual se estará a los siguientes criterios:\na) Multa por el equivalente a un monto mínimo de cien y hasta máximo de mil veces de la Unidad de Medida y Actualización, en la fecha en que se corneta la infracción, respecto a lo señalado en las fracciones I, II, III, IV, V, VI, VIII, IX, X, XV, XVI, XXIII y XXIV del artículo\n126 de esta Ley;\nb) Multa por el equivalente a un monto mínimo de mil y hasta máximo de siete mil veces de la Unidad de Medida y Actualización, en la fecha en que se corneta la infracción, respecto a lo señalado en las fracciones XI, XII, XX, XXI, XXII, XXV y XXVI del artículo 126 de esta Ley, y\nc) Multa por el equivalente a un monto mínimo de siete mil y hasta máximo de quince mil veces de la Unidad de Medida y Actualización, en la fecha en que se corneta la infracción, respecto a lo señalado en las fracciones VII, XIII y XIV del artículo 126 de esta\nLey.\nLas multas impuestas podrán duplicarse en caso de reincidencia;\nII. Revocación de la autorización o retiro del reconocimiento de validez oficial de del artículo 126 de esta Ley. La imposición de esta sanción no excluye la posibilidad de que sea impuesta alguna multa de las señaladas en el inciso b) de la fracción anterior, o\nLey de Educación del Estado de Baja California. Página 63\nIII. Clausura del plantel, respecto a las infracciones señaladas en las fracciones XVII, XVIII y XIX del artículo 126 de esta Ley.\nSi se incurriera en las infracciones establecidas en las fracciones XIII, XIV y XXVI del artículo anterior, se aplicarán las sanciones de este artículo, sin perjuicio de las penales y de otra índole que resulten.\nPara determinar la sanción, se considerarán las circunstancias en que se cometió la infracción, los daños y perjuicios que se hayan producido o puedan producirse a los educandos, la gravedad de la infracción, las condiciones socioeconómicas del infractor, el carácter intencional o no de la infracción y si se trata de reincidencia.\nArtículo 128. Las multas que imponga la autoridad educativa estatal serán ejecutadas a través de los procedimientos y disposiciones aplicables.\nArtículo 129. La revocación de la autorización otorgada a particulares produce efectos de clausura del servicio educativo de que se trate.\nEl retiro de los reconocimientos de validez oficial de estudios producirá sus efectos a partir de la fecha en que se notifique la resolución definitiva, por lo que los estudios realizados mientras que la institución contaba con el reconocimiento, mantendrán su validez oficial para evitar perjuicios a los educandos.\nA fin de que la autoridad que dictó la resolución adopte las medidas necesarias para evitar perjuicios a los educandos; el particular deberá proporcionar la información y documentación que, en términos de las disposiciones normativas, se fijen.\nPara la aplicación de sanciones por la autoridad educativa estatal, además de lo establecido en la presente ley serán aplicables las disposiciones señaladas en el reglamento que para tal efecto emita la autoridad educativa estatal.\nArtículo 130. Las autoridades competentes harán uso de las medidas legales necesarias, incluyendo el auxilio de la fuerza pública, para lograr la ejecución de las sanciones y medidas de seguridad que procedan.\nArtículo 131. Las acciones de vigilancia a las que se refiere el artículo 125 de esta\nLey que lleven a cabo las autoridades educativas del Estado, se realizarán de conformidad con el procedimiento establecido en los artículos 152 al 179 de la Ley General de Educación la autoridad educativa federal en la materia.\nCapítulo III\nDel Recurso Administrativo\nLey de Educación del Estado de Baja California. Página 64\nArtículo 132. Cuando la autoridad educativa responsable de la prestación del servicio, o que haya otorgado la autorización o el reconocimiento de validez oficial de estudios, considere que existen causas justificadas que ameriten la imposición de sanciones, lo hará del conocimiento del presunto infractor para que, dentro de un plazo de quince días naturales, manifieste lo que a su derecho convenga y proporcione los datos y documentos que le sean requeridos.\nLa autoridad dictará resolución con base en los datos aportados por el presunto infractor y las demás constancias que obren en el expediente que se abra para tal efecto.\nArtículo 133. La negativa o revocación de la autorización otorgada a las personas físicas o morales particulares, produce efectos de clausura del servicio educativo de que se trate. El retiro de reconocimiento de validez oficial se referirá a los estudios que se impartan a partir de la fecha en que se dicte la resolución. Los realizados mientras que la institución contaba con el reconocimiento, mantendrán su validez oficial.\nLa autoridad que dicte la resolución adoptará las medidas que sean necesarias para evitar perjuicios a los educandos. En el caso de autorizaciones, cuando la revocación se dicte durante un ejercicio lectivo, la institución podrá seguir funcionando, a juicio y bajo la vigilancia de la autoridad, hasta que aquél concluya.\nArtículo 134. En contra de las resoluciones de las autoridades educativas del Estado dictadas con fundamento en las disposiciones de esta Ley y las que de ella emanen, podrá interponerse recurso de revisión dentro de los quince días hábiles siguientes a la fecha de su notificación.\nTranscurrido el plazo a que se refiere el párrafo anterior sin que el interesado interponga el recurso, la resolución tendrá el carácter de definitiva.\nAsimismo, podrá interponerse dicho recurso cuando la autoridad no dé respuesta en autorización o de reconocimiento de validez oficial de estudios.\nArtículo 135. El recurso se interpondrá por escrito, ante la autoridad inmediata superior a la que emitió el acto recurrido u omitió responder la solicitud correspondiente. fecha y hora en que se presente y el número de anexos que se acompañe, devolviendo en el mismo acto copia debidamente sellada o firmada.\nArtículo 136. Al interponer el recurso deberán expresarse el nombre y el domicilio del recurrente y los agravios, acompañándose los elementos de prueba que se consideren\nLey de Educación del Estado de Baja California. Página 65 necesarios, así como las constancias que acrediten la personalidad del promovente. En caso de que el recurrente no cumpliera con alguno de los requisitos anteriores, la autoridad educativa que conozca del recurso, deberá prevenirlo por escrito por una sola vez para que, en un plazo de diez días subsecuentes a la notificación personal, subsane la omisión. Si transcurrido este plazo el recurrente no desahoga en sus términos la prevención, el recurso se tendrá por no interpuesto.\nArtículo 137. Al interponerse el recurso podrá ofrecerse toda clase de pruebas, excepto la confesional, y acompañarse con los documentos relativos.\nSi se ofrecen pruebas que requieran desahogo, se abrirá un plazo de diez días hábiles para tal efecto. La autoridad educativa estatal que esté conociendo del recurso podrá allegarse los elementos de convicción que considere necesarios.\nArtículo 138. La autoridad educativa estatal dictará resolución dentro de los treinta días hábiles siguientes, a partir de la fecha:\nI.- Del acuerdo de admisión del recurso, cuando no se hubiesen ofrecido pruebas o las ofrecidas no requieran plazo especial de desahogo, y\nII.- De la conclusión del desahogo de las pruebas o, en su caso, cuando haya transcurrido el plazo concedido para ello y no se hubieren desahogado.\nLas resoluciones del recurso se notificarán a los interesados, o a sus representantes legales, personalmente o por correo certificado con acuse de recibo.\nArtículo 139. La interposición del recurso suspenderá la ejecución de la resolución impugnada en cuanto al pago de multas. pecuniarias, la suspensión sólo se otorgará si concurren los requisitos siguientes:\nI.- Que lo solicite el recurrente;\nII.- Que el recurso haya sido admitido;\nIII.- Que, de otorgarse, no implique la continuación o consumación de actos u omisiones que ocasionen infracciones a esta Ley, y\nIV.- Que no ocasionen daños o perjuicios a los educandos o terceros en términos de esta Ley o de las disposiciones que de ella emanen.\nLey de Educación del Estado de Baja California. Página 66\nArtículo 140. A falta de disposición expresa en este capítulo respecto a la tramitación del recurso de revisión, será aplicable el Código de Procedimientos Civiles para el Estado de\nBaja California.\nARTÍCULOS TRANSITORIOS\nPrimero. La presente Ley entrará en vigor al día siguiente de su publicación en el\nPeriódico Oficial del Estado.\nSegundo. Se abroga la Ley de Educación del Estado de Baja California, publicada el\n29 de septiembre de 1995 en el Periódico Oficial del Estado y se derogan todas las disposiciones contenidas en las leyes secundarias y quedan sin efectos los reglamentos, acuerdos y disposiciones de carácter general contrarias a este Decreto.\nTercero. La autoridad educativa estatal deberá emitir y adecuar los reglamentos, acuerdos, lineamientos y demás disposiciones de carácter general conforme a lo establecido en este Decreto, en un plazo no mayor a ciento ochenta días hábiles siguientes contados a partir de su entrada en vigor. Hasta su emisión, seguirán aplicándose para la operación y funcionamiento de los servicios que se presten y se deriven de aquellos en lo que no contravengan a este Decreto. Los procedimientos y trámites que se iniciaron con anterioridad a la entrada en vigor de este Decreto, continuarán, hasta su conclusión, regidos con los reglamentos, acuerdos y demás disposiciones de carácter general en los cuales se fundamentaron.\nCuarto. Las erogaciones que se generen con motivo de la entrada en vigor del presente Decreto, se realizarán con cargo a la disponibilidad presupuestaria que se apruebe para tal fin al sector educativo en el ejercicio fiscal de que se trate, lo cual se llevará a cabo de manera progresiva y atendiendo al principio de austeridad, con el objeto de cumplir con las obligaciones que tendrán a su cargo las autoridades competentes.\nQuinto. Las autoridades educativas, en el ámbito de su competencia, preverán de manera progresiva y de acuerdo a la disponibilidad presupuestaria, los recursos presupuestales necesarios para garantizar la prestación de educación inicial, con el fin de lograr la universalidad de dicho servicio, conforme a lo que establezca la Estrategia Nacional\nDecreto por el que se reforman, adicionan y derogan diversas disposiciones de los artículos\n3o., 31 y 73 de la Constitución Política de los Estados Unidos Mexicanos, en materia\nSexto. Las autoridades educativas, en coordinación con las autoridades correspondientes, realizarán consultas de buena fe y de manera previa libre e informada, de acuerdo con las disposiciones legales nacionales e internacionales en la materia, en pueblos y comunidades indígenas o afromexicanas relativo a la aplicación de las disposiciones que, Ley de Educación del Estado de Baja California. Página 67 en materia de educación indígena, son contempladas en este Decreto; hasta en tanto, las disposiciones.\nSentencia de Acción de Inconstitucionalidad 18/2021\nSéptimo. La Comisión Estatal de Planeación y Coordinación del Sistema de\nEducación Media Superior del Estado de Baja California prevista en el artículo 22 de este\nDecreto deberá quedar instalada en un plazo de sesenta días contados a partir de la entrada en vigor del mismo.\nOctavo. La integración de los Consejos de Participación Escolar, prevista en el artículo 109 de este Decreto deberá quedar instalada en un plazo no mayor de sesenta días contados a partir del inicio del ciclo escolar 2020-2021.\nNoveno. La integración del Consejo Municipal de Participación Escolar, prevista en el artículo 110 de este Decreto deberá quedar instalada en un plazo no mayor de ciento veinte días contados a partir del inicio del ciclo escolar 2020-2021.\nDécimo. La autoridad educativa estatal deberá emitir las disposiciones a fin de que el\nConsejo Estatal de Participación Social, quede instalado en un plazo no mayor de ciento veinte días contados a partir del inicio del ciclo escolar 2020-2021.\nDécimo Primero. El Sistema Integral de Formación, Actualización, Capacitación y\nSuperación Profesional para Maestros, previsto en el artículo 81 de este Decreto deberá instalarse antes de finalizar el año 2020.\nDécimo Segundo. El Programa Educativo Estatal previsto en el artículo 98 de este\nDecreto se presentará en un plazo no mayor a sesenta días contados a la entrada en vigor del mismo. Dicho Programa se actualizará en el caso de los cambios de administración del\nPoder Ejecutivo Estatal y observará lo establecido en la Ley de Educación del Estado de\nBaja California.\nDécimo Tercero. Todas las iniciativas de reforma o adición a la Ley de Educación del\nEstado de Baja California, que hayan sido presentadas con anterioridad a la emisión del presente Decreto, quedan jurídicamente desestimadas por ministerio de ley, debiéndose estar al contenido del presente Decreto.\nDADO en Sesión Ordinaria Virtual en la Ciudad de Mexicali, B.C., a los veintidós días del mes de diciembre del año dos mil veinte.\nDIP. EVA GRICELDA RODRÍGUEZ\nPRESIDENTA\n(RÚBRICA)\nLey de Educación del Estado de Baja California. Página 68\nDIP. MARÍA LUISA VILLALOBOS ÁVILA\nSECRETARIA\n(RÚBRICA)\nDE CONFORMIDAD CON LO DISPUESTO POR LA FRACCIÓN I DEL ARTÍCULO 49 DE\nCALIFORNIA, IMPRÍMASE Y PUBLÍQUESE.\nMEXICALI, BAJA CALIFORNIA, A LOS VEITIOCHO DÍAS DEL MES DE DICIEMBRE DEL\nAÑO DOS MIL VEITE.\nJAIME BONILLA VALDEZ\nGOBERNADOR DEL ESTADO\n(RÚBRICA)\nAMADOR RODRÍGUEZ LOZANO\nSECRETARIO GENERAL DE GOBIERNO\n(RÚBRICA)\nLey de Educación del Estado de Baja California. Página 69\nARTÍCULO 6.- De conformidad con lo estipulado en su Resolutivo Segundo y Tercero de la Sentencia de Acción de Inconstitucionalidad 18/2021, publicada en el Periódico Oficial\nC. Marina del Pilar Ávila Olmeda 2021-2027, “Se declara la invalidez de los artículos 31, 32, 33 y del 37 al 41 y por extensión la de diversos artículos de esta Ley, expedida mediante\nDecreto No. 188, publicado en el Periódico Oficial el 28 de diciembre de 2020, expedido por la H. XXIII Legislatura, siendo Gobernador Constitucional el C. Jaime Bonilla Valdez 20192021; fue reformado por Decreto No. 154, publicado en el Periódico Oficial No. 63, de fecha\n01 de noviembre de 2022, Sección I, Tomo CXXIX; expedido por la H. XXIV Legislatura, siendo Gobernadora Constitucional la C. Marina del Pilar Ávila Olmeda 2021-2027; fue reformado por Decreto No. 198, publicado en el Periódico Oficial No. 6, de fecha 27 de enero de 2023, Índice, Tomo CXXX; expedido por la H. XXIV Legislatura, siendo Gobernadora\nConstitucional la C. Marina del Pilar Ávila Olmeda 2021-2027; fue reformado por Decreto No.\n295, publicado en el Periódico Oficial No. 62, de fecha 06 de noviembre de 2023, Índice, Tomo CXXX, expedido por la H. XXIV Legislatura, atendiendo la Sentencia de Acción de\nInconstitucionalidad 18/2021, siendo Gobernadora Constitucional la C. Marina del Pilar Ávila\nOlmeda 2021-2027; fue reformado mediante Decreto No. 313, publicado en el Periódico\nOficial No. 67, de fecha 01 de diciembre de 2023, Sección I, Tomo CXXX; expedido por la H.\nXXIV Legislatura, siendo Gobernadora Constitucional la C. Marina del Pilar Ávila Olmeda\n2021-2027; fue reformado por Decreto No. 422, publicado en el Periódico Oficial No. 23, de fecha 07 de mayo de 2024, Índice, Tomo CXXXI, expedido por la H. XXIV Legislatura, siendo Gobernadora Constitucional la C. Marina del Pilar Ávila Olmeda 2021-2027; fue reformado por Decreto No. 51, publicado en el Periódico Oficial No. 15, Índice, de fecha 14 de marzo de 2025, Tomo CXXXII, expedido por la H. XXV Legislatura, siendo Gobernadora\nConstitucional la C. Marina del Pilar Ávila Olmeda 2021-2027;\nARTÍCULO 10.- De conformidad con lo estipulado en su Resolutivo Segundo y\nTercero de la Sentencia de Acción de Inconstitucionalidad 18/2021, publicada en el\nPeriódico Oficial No. 94, Sección I, Tomo CXXVIII, de fecha 19 de noviembre de 2021, siendo Gobernadora la C. Marina del Pilar Ávila Olmeda 2021-2027, “Se declara la invalidez de los artículos 31, 32, 33 y del 37 al 41 y por extensión la de diversos artículos de esta Ley, expedida mediante Decreto No. 188, publicado en el Periódico Oficial el 28 de diciembre de\n2020, expedido por la H. XXIII Legislatura, siendo Gobernador Constitucional el C. Jaime\nBonilla Valdez 2019-2021; fue reformado por Decreto No. 295, publicado en el Periódico\nXXIV Legislatura, atendiendo la Sentencia de Acción de Inconstitucionalidad 18/2021, siendo\nGobernadora Constitucional la C. Marina del Pilar Ávila Olmeda 2021-2027;\nARTÍCULO 11 BIS.- Fue adicionado por Decreto No. 424, publicado en el Periódico\nLegislatura, siendo Gobernadora Constitucional la C. Marina del Pilar Ávila Olmeda 20212027;\nLey de Educación del Estado de Baja California. Página 70\nARTÍCULO 12.- De conformidad con lo estipulado en su Resolutivo Segundo y\nTercero de la Sentencia de Acción de Inconstitucionalidad 18/2021, publicada en el siendo Gobernadora la C. Marina del Pilar Ávila Olmeda 2021-2027, “Se declara la invalidez de los artículos 31, 32, 33 y del 37 al 41 y por extensión la de diversos artículos de esta Ley, expedida mediante Decreto No. 188, publicado en el Periódico Oficial el 28 de diciembre de\n2020, expedido por la H. XXIII Legislatura, siendo Gobernador Constitucional el C. Jaime\nBonilla Valdez 2019-2021; fue reformado por Decreto No. 295, publicado en el Periódico\nOficial No. 62, de fecha 06 de noviembre de 2023, Índice, Tomo CXXX, expedido por la H.\nXXIV Legislatura, atendiendo la Sentencia de Acción de Inconstitucionalidad 18/2021, siendo\nGobernadora Constitucional la C. Marina del Pilar Ávila Olmeda 2021-2027;\nARTÍCULO 13.- De conformidad con lo estipulado en su Resolutivo Segundo y\nTercero de la Sentencia de Acción de Inconstitucionalidad 18/2021, publicada en el\nPeriódico Oficial No. 94, Sección I, Tomo CXXVIII, de fecha 19 de noviembre de 2021, siendo Gobernadora la C. Marina del Pilar Ávila Olmeda 2021-2027, “Se declara la invalidez de los artículos 31, 32, 33 y del 37 al 41 y por extensión la de diversos artículos de esta Ley, expedida mediante Decreto No. 188, publicado en el Periódico Oficial el 28 de diciembre de\n2020, expedido por la H. XXIII Legislatura, siendo Gobernador Constitucional el C. Jaime\nBonilla Valdez 2019-2021; fue reformado por Decreto No. 295, publicado en el Periódico\nOficial No. 62, de fecha 06 de noviembre de 2023, Índice, Tomo CXXX, expedido por la H.\nXXIV Legislatura, atendiendo la Sentencia de Acción de Inconstitucionalidad 18/2021, siendo\nGobernadora Constitucional la C. Marina del Pilar Ávila Olmeda 2021-2027;\nARTÍCULO 24.- De conformidad con lo estipulado en su Resolutivo Segundo y\nTercero de la Sentencia de Acción de Inconstitucionalidad 18/2021, publicada en el\nPeriódico Oficial No. 94, Sección I, Tomo CXXVIII, de fecha 19 de noviembre de 2021, siendo Gobernadora la C. Marina del Pilar Ávila Olmeda 2021-2027, “Se declara la invalidez de los artículos 31, 32, 33 y del 37 al 41 y por extensión la de diversos artículos de esta Ley, expedida mediante Decreto No. 188, publicado en el Periódico Oficial el 28 de diciembre de\n2020, expedido por la H. XXIII Legislatura, siendo Gobernador Constitucional el C. Jaime\nBonilla Valdez 2019-2021; fue reformado por Decreto No. 295, publicado en el Periódico\nOficial No. 62, de fecha 06 de noviembre de 2023, Índice, Tomo CXXX, expedido por la H.\nXXIV Legislatura, atendiendo la Sentencia de Acción de Inconstitucionalidad 18/2021, siendo\nGobernadora Constitucional la C. Marina del Pilar Ávila Olmeda 2021-2027;\nARTÍCULO 31.- De conformidad con lo estipulado en su Resolutivo Segundo y\nTercero de la Sentencia de Acción de Inconstitucionalidad 18/2021, publicada en el siendo Gobernadora la C. Marina del Pilar Ávila Olmeda 2021-2027, “Se declara la invalidez de los artículos 31, 32, 33 y del 37 al 41 y por extensión la de diversos artículos de esta Ley, expedida mediante Decreto No. 188, publicado en el Periódico Oficial el 28 de diciembre de\n2020, expedido por la H. XXIII Legislatura, siendo Gobernador Constitucional el C. Jaime\nBonilla Valdez 2019-2021; fue reformado por Decreto No. 295, publicado en el Periódico\nLey de Educación del Estado de Baja California. Página 71\nXXIV Legislatura, atendiendo la Sentencia de Acción de Inconstitucionalidad 18/2021, siendo\nGobernadora Constitucional la C. Marina del Pilar Ávila Olmeda 2021-2027;\nARTÍCULO 32.- De conformidad con lo estipulado en su Resolutivo Segundo y\nTercero de la Sentencia de Acción de Inconstitucionalidad 18/2021, publicada en el\nPeriódico Oficial No. 94, Sección I, Tomo CXXVIII, de fecha 19 de noviembre de 2021, siendo Gobernadora la C. Marina del Pilar Ávila Olmeda 2021-2027, “Se declara la invalidez de los artículos 31, 32, 33 y del 37 al 41 y por extensión la de diversos artículos de esta Ley, expedida mediante Decreto No. 188, publicado en el Periódico Oficial el 28 de diciembre de\n2020, expedido por la H. XXIII Legislatura, siendo Gobernador Constitucional el C. Jaime\nBonilla Valdez 2019-2021; fue reformado por Decreto No. 295, publicado en el Periódico\nOficial No. 62, de fecha 06 de noviembre de 2023, Índice, Tomo CXXX, expedido por la H.\nXXIV Legislatura, atendiendo la Sentencia de Acción de Inconstitucionalidad 18/2021, siendo\nGobernadora Constitucional la C. Marina del Pilar Ávila Olmeda 2021-2027;\nARTÍCULO 33.- De conformidad con lo estipulado en su Resolutivo Segundo y\nTercero de la Sentencia de Acción de Inconstitucionalidad 18/2021, publicada en el\nPeriódico Oficial No. 94, Sección I, Tomo CXXVIII, de fecha 19 de noviembre de 2021, siendo Gobernadora la C. Marina del Pilar Ávila Olmeda 2021-2027, “Se declara la invalidez de los artículos 31, 32, 33 y del 37 al 41 y por extensión la de diversos artículos de esta Ley, expedida mediante Decreto No. 188, publicado en el Periódico Oficial el 28 de diciembre de\n2020, expedido por la H. XXIII Legislatura, siendo Gobernador Constitucional el C. Jaime\nBonilla Valdez 2019-2021; fue reformado por Decreto No. 295, publicado en el Periódico\nOficial No. 62, de fecha 06 de noviembre de 2023, Índice, Tomo CXXX, expedido por la H.\nXXIV Legislatura, atendiendo la Sentencia de Acción de Inconstitucionalidad 18/2021, siendo\nGobernadora Constitucional la C. Marina del Pilar Ávila Olmeda 2021-2027;\nARTÍCULO 35.- Fue reformado por Decreto No. 113, publicado en el Periódico Oficial\nNo. 39. Índice, de fecha 27 de junio de 2025, Tomo CXXXII, expedido por la H. XXV\nLegislatura, siendo Gobernadora Constitucional la C. Marina del Pilar Ávila Olmeda 20212027;\nARTÍCULO 37.- De conformidad con lo estipulado en su Resolutivo Segundo y\nTercero de la Sentencia de Acción de Inconstitucionalidad 18/2021, publicada en el siendo Gobernadora la C. Marina del Pilar Ávila Olmeda 2021-2027, “Se declara la invalidez de los artículos 31, 32, 33 y del 37 al 41 y por extensión la de diversos artículos de esta Ley, expedida mediante Decreto No. 188, publicado en el Periódico Oficial el 28 de diciembre de\n2020, expedido por la H. XXIII Legislatura, siendo Gobernador Constitucional el C. Jaime\nBonilla Valdez 2019-2021; fue reformado por Decreto No. 295, publicado en el Periódico\nXXIV Legislatura, atendiendo la Sentencia de Acción de Inconstitucionalidad 18/2021, siendo\nGobernadora Constitucional la C. Marina del Pilar Ávila Olmeda 2021-2027;\nLey de Educación del Estado de Baja California. Página 72\nARTÍCULO 38.- De conformidad con lo estipulado en su Resolutivo Segundo y\nTercero de la Sentencia de Acción de Inconstitucionalidad 18/2021, publicada en el siendo Gobernadora la C. Marina del Pilar Ávila Olmeda 2021-2027, “Se declara la invalidez de los artículos 31, 32, 33 y del 37 al 41 y por extensión la de diversos artículos de esta Ley, expedida mediante Decreto No. 188, publicado en el Periódico Oficial el 28 de diciembre de\n2020, expedido por la H. XXIII Legislatura, siendo Gobernador Constitucional el C. Jaime\nBonilla Valdez 2019-2021; fue reformado por Decreto No. 295, publicado en el Periódico\nOficial No. 62, de fecha 06 de noviembre de 2023, Índice, Tomo CXXX, expedido por la H.\nXXIV Legislatura, atendiendo la Sentencia de Acción de Inconstitucionalidad 18/2021, siendo\nGobernadora Constitucional la C. Marina del Pilar Ávila Olmeda 2021-2027;\nARTÍCULO 39.- De conformidad con lo estipulado en su Resolutivo Segundo y\nTercero de la Sentencia de Acción de Inconstitucionalidad 18/2021, publicada en el\nPeriódico Oficial No. 94, Sección I, Tomo CXXVIII, de fecha 19 de noviembre de 2021, siendo Gobernadora la C. Marina del Pilar Ávila Olmeda 2021-2027, “Se declara la invalidez de los artículos 31, 32, 33 y del 37 al 41 y por extensión la de diversos artículos de esta Ley, expedida mediante Decreto No. 188, publicado en el Periódico Oficial el 28 de diciembre de\n2020, expedido por la H. XXIII Legislatura, siendo Gobernador Constitucional el C. Jaime\nBonilla Valdez 2019-2021; fue reformado por Decreto No. 295, publicado en el Periódico\nOficial No. 62, de fecha 06 de noviembre de 2023, Índice, Tomo CXXX, expedido por la H.\nXXIV Legislatura, atendiendo la Sentencia de Acción de Inconstitucionalidad 18/2021, siendo\nGobernadora Constitucional la C. Marina del Pilar Ávila Olmeda 2021-2027;\nARTÍCULO 40.- De conformidad con lo estipulado en su Resolutivo Segundo y\nTercero de la Sentencia de Acción de Inconstitucionalidad 18/2021, publicada en el\nPeriódico Oficial No. 94, Sección I, Tomo CXXVIII, de fecha 19 de noviembre de 2021, siendo Gobernadora la C. Marina del Pilar Ávila Olmeda 2021-2027, “Se declara la invalidez de los artículos 31, 32, 33 y del 37 al 41 y por extensión la de diversos artículos de esta Ley, expedida mediante Decreto No. 188, publicado en el Periódico Oficial el 28 de diciembre de\n2020, expedido por la H. XXIII Legislatura, siendo Gobernador Constitucional el C. Jaime\nBonilla Valdez 2019-2021; fue reformado por Decreto No. 295, publicado en el Periódico\nOficial No. 62, de fecha 06 de noviembre de 2023, Índice, Tomo CXXX, expedido por la H.\nXXIV Legislatura, atendiendo la Sentencia de Acción de Inconstitucionalidad 18/2021, siendo\nGobernadora Constitucional la C. Marina del Pilar Ávila Olmeda 2021-2027;\nARTÍCULO 41.- De conformidad con lo estipulado en su Resolutivo Segundo y\nTercero de la Sentencia de Acción de Inconstitucionalidad 18/2021, publicada en el siendo Gobernadora la C. Marina del Pilar Ávila Olmeda 2021-2027, “Se declara la invalidez de los artículos 31, 32, 33 y del 37 al 41 y por extensión la de diversos artículos de esta Ley, expedida mediante Decreto No. 188, publicado en el Periódico Oficial el 28 de diciembre de\n2020, expedido por la H. XXIII Legislatura, siendo Gobernador Constitucional el C. Jaime\nBonilla Valdez 2019-2021; fue reformado por Decreto No. 295, publicado en el Periódico\nLey de Educación del Estado de Baja California. Página 73\nXXIV Legislatura, atendiendo la Sentencia de Acción de Inconstitucionalidad 18/2021, siendo\nGobernadora Constitucional la C. Marina del Pilar Ávila Olmeda 2021-2027;\nARTÍCULO 45.- De conformidad con lo estipulado en su Resolutivo Segundo y\nTercero de la Sentencia de Acción de Inconstitucionalidad 18/2021, publicada en el\nPeriódico Oficial No. 94, Sección I, Tomo CXXVIII, de fecha 19 de noviembre de 2021, siendo Gobernadora la C. Marina del Pilar Ávila Olmeda 2021-2027, “Se declara la invalidez de los artículos 31, 32, 33 y del 37 al 41 y por extensión la de diversos artículos de esta Ley, expedida mediante Decreto No. 188, publicado en el Periódico Oficial el 28 de diciembre de\n2020, expedido por la H. XXIII Legislatura, siendo Gobernador Constitucional el C. Jaime\nBonilla Valdez 2019-2021; fue reformado por Decreto No. 198, publicado en el Periódico\nOficial No. 6, de fecha 27 de enero de 2023, Índice, Tomo CXXX; expedido por la H. XXIV\nLegislatura, siendo Gobernadora Constitucional la C. Marina del Pilar Ávila Olmeda 20212027; fue reformado por Decreto No. 295, publicado en el Periódico Oficial No. 62, de fecha\n06 de noviembre de 2023, Índice, Tomo CXXX, expedido por la H. XXIV Legislatura, atendiendo la Sentencia de Acción de Inconstitucionalidad 18/2021, siendo Gobernadora\nConstitucional la C. Marina del Pilar Ávila Olmeda 2021-2027;\nARTÍCULO 46.- De conformidad con lo estipulado en su Resolutivo Segundo y\nTercero de la Sentencia de Acción de Inconstitucionalidad 18/2021, publicada en el\nPeriódico Oficial No. 94, Sección I, Tomo CXXVIII, de fecha 19 de noviembre de 2021, siendo Gobernadora la C. Marina del Pilar Ávila Olmeda 2021-2027, “Se declara la invalidez de los artículos 31, 32, 33 y del 37 al 41 y por extensión la de diversos artículos de esta Ley, expedida mediante Decreto No. 188, publicado en el Periódico Oficial el 28 de diciembre de\n2020, expedido por la H. XXIII Legislatura, siendo Gobernador Constitucional el C. Jaime\nBonilla Valdez 2019-2021; fue reformado por Decreto No. 295, publicado en el Periódico\nOficial No. 62, de fecha 06 de noviembre de 2023, Índice, Tomo CXXX, expedido por la H.\nXXIV Legislatura, atendiendo la Sentencia de Acción de Inconstitucionalidad 18/2021, siendo\nGobernadora Constitucional la C. Marina del Pilar Ávila Olmeda 2021-2027;\nARTÍCULO 48.- Fue reformado mediante Decreto No. 313, publicado en el Periódico\nOficial No. 67, de fecha 01 de diciembre de 2023, Sección I, Tomo CXXX; expedido por la H.\nXXIV Legislatura, siendo Gobernadora Constitucional la C. Marina del Pilar Ávila Olmeda\n2021-2027;\nARTÍCULO 50.- Fue reformado por Decreto No. 318, publicado en el Periódico Oficial\nLegislatura, siendo Gobernadora Constitucional la C. Marina del Pilar Ávila Olmeda, 20212027;\nARTÍCULO 65.- Fue reformado por Decreto No. 198, publicado en el Periódico Oficial\nLegislatura, siendo Gobernadora Constitucional la C. Marina del Pilar Ávila Olmeda 2021Ley de Educación del Estado de Baja California. Página 74\n2027; fue reformado por Decreto No. 421, publicado en el Periódico Oficial No. 23, de fecha\nGobernadora Constitucional la C. Marina del Pilar Ávila Olmeda 2021-2027;\nARTÍCULO 67.- Fue reformado por Decreto No. 308, publicado en el Periódico Oficial\nLegislatura, siendo Gobernadora Constitucional la C. Marina del Pilar Ávila Olmeda 20212027;\nARTÍCULO 70.- Fue reformado por Decreto No. 308, publicado en el Periódico Oficial\nNo. 62, de fecha 06 de noviembre de 2023, Índice, Tomo CXXX, expedido por la H. XXIV\nLegislatura, siendo Gobernadora Constitucional la C. Marina del Pilar Ávila Olmeda 20212027;\nARTÍCULO 72 BIS.- Fue adicionado por Decreto No. 213, publicado en el Periódico\nOficial No. 27, de fecha 16 de abril de 2021, Índice, Tomo CXXVIII; expedido por la H. XXIII\nLegislatura, siendo Gobernador Constitucional el C. Jaime Bonilla Valdez 2019-2021;\nARTÍCULO 73.- Fue reformado por Decreto No. 399, publicado en el Periódico Oficial\nNo. 18, de fecha 05 de abril de 2024, Índice, Tomo CXXXI, expedido por la H. XXIV\nLegislatura, siendo Gobernadora Constitucional la C. Marina del Pilar Ávila Olmeda 20212027;\nARTÍCULO 73 BIS.- Fue adicionado por Decreto No. 263, publicado en el Periódico\nOficial No. 57, de fecha 06 de agosto de 2021, Sección I, Tomo CXXVIII; expedido por la H.\nXXIII Legislatura, siendo Gobernador Constitucional el C. Jaime Bonilla Valdez 2019-2021; fue reformado por Decreto No. 308, publicado en el Periódico Oficial No. 62, de fecha 06 de noviembre de 2023, Índice, Tomo CXXX, expedido por la H. XXIV Legislatura, siendo\nGobernadora Constitucional la C. Marina del Pilar Ávila Olmeda 2021-2027;\nARTÍCULO 73 TER.- Fue adicionado por Decreto No. 198, publicado en el Periódico\nOficial No. 6, de fecha 27 de enero de 2023, Índice, Tomo CXXX; expedido por la H. XXIV\nLegislatura, siendo Gobernadora Constitucional la C. Marina del Pilar Ávila Olmeda 20212027;\nARTÍCULO 74.- Fue reformado por Decreto No. 399, publicado en el Periódico Oficial\nLegislatura, siendo Gobernadora Constitucional la C. Marina del Pilar Ávila Olmeda 20212027;\nARTÍCULO 80.- De conformidad con lo estipulado en su Resolutivo Segundo y\nTercero de la Sentencia de Acción de Inconstitucionalidad 18/2021, publicada en el siendo Gobernadora la C. Marina del Pilar Ávila Olmeda 2021-2027, “Se declara la invalidez\nLey de Educación del Estado de Baja California. Página 75 de los artículos 31, 32, 33 y del 37 al 41 y por extensión la de diversos artículos de esta Ley, expedida mediante Decreto No. 188, publicado en el Periódico Oficial el 28 de diciembre de\n2020, expedido por la H. XXIII Legislatura, siendo Gobernador Constitucional el C. Jaime\nBonilla Valdez 2019-2021; fue reformado por Decreto No. 281, publicado en el Periódico\nH. XXIV Legislatura, siendo Gobernadora Constitucional la C. Marina del Pilar Ávila Olmeda\n2021-2027; fue reformado por Decreto No. 295, publicado en el Periódico Oficial No. 62, de fecha 06 de noviembre de 2023, Índice, Tomo CXXX, expedido por la H. XXIV Legislatura, atendiendo la Sentencia de Acción de Inconstitucionalidad 18/2021, siendo Gobernadora\nConstitucional la C. Marina del Pilar Ávila Olmeda 2021-2027;\nARTÍCULO 84.- De conformidad con lo estipulado en su Resolutivo Segundo y\nTercero de la Sentencia de Acción de Inconstitucionalidad 18/2021, publicada en el\nPeriódico Oficial No. 94, Sección I, Tomo CXXVIII, de fecha 19 de noviembre de 2021, siendo Gobernadora la C. Marina del Pilar Ávila Olmeda 2021-2027, “Se declara la invalidez de los artículos 31, 32, 33 y del 37 al 41 y por extensión la de diversos artículos de esta Ley, expedida mediante Decreto No. 188, publicado en el Periódico Oficial el 28 de diciembre de\n2020, expedido por la H. XXIII Legislatura, siendo Gobernador Constitucional el C. Jaime\nBonilla Valdez 2019-2021; fue reformado por Decreto No. 295, publicado en el Periódico\nOficial No. 62, de fecha 06 de noviembre de 2023, Índice, Tomo CXXX, expedido por la H.\nXXIV Legislatura, atendiendo la Sentencia de Acción de Inconstitucionalidad 18/2021, siendo\nGobernadora Constitucional la C. Marina del Pilar Ávila Olmeda 2021-2027;\nARTÍCULO 85.- Fue reformado por Decreto No. 389, publicado en el Periódico Oficial\nNo. 14, de fecha 15 de marzo de 2024, Índice, Tomo CXXXI, expedido por la H. XXIV\nLegislatura, siendo Gobernadora Constitucional la C. Marina del Pilar Ávila Olmeda, 20212027;\nARTÍCULO 87.- Fue reformado por Decreto No. 423, publicado en el Periódico Oficial\nNo. 23, de fecha 07 de mayo de 2024, Índice, Tomo CXXXI, expedido por la H. XXIV\nLegislatura, siendo Gobernadora Constitucional la C. Marina del Pilar Ávila Olmeda 20212027;\nARTÍCULO 88.- Fue reformado por Decreto No. 234, publicado en el Periódico Oficial\nLegislatura, siendo Gobernadora Constitucional la C. Marina del Pilar Ávila Olmeda, 20212027; fue reformado por Decreto No. 389, publicado en el Periódico Oficial No. 14, de fecha\nGobernadora Constitucional la C. Marina del Pilar Ávila Olmeda, 2021-2027;\nARTÍCULO 91.- De conformidad con lo estipulado en su Resolutivo Segundo y\nTercero de la Sentencia de Acción de Inconstitucionalidad 18/2021, publicada en el siendo Gobernadora la C. Marina del Pilar Ávila Olmeda 2021-2027, “Se declara la invalidez\nLey de Educación del Estado de Baja California. Página 76 de los artículos 31, 32, 33 y del 37 al 41 y por extensión la de diversos artículos de esta Ley, expedida mediante Decreto No. 188, publicado en el Periódico Oficial el 28 de diciembre de\n2020, expedido por la H. XXIII Legislatura, siendo Gobernador Constitucional el C. Jaime\nBonilla Valdez 2019-2021; fue reformado por Decreto No. 295, publicado en el Periódico\nXXIV Legislatura, atendiendo la Sentencia de Acción de Inconstitucionalidad 18/2021, siendo\nGobernadora Constitucional la C. Marina del Pilar Ávila Olmeda 2021-2027;\nARTÍCULO 104.- Fue reformado por Decreto No. 198, publicado en el Periódico\nOficial No. 6, de fecha 27 de enero de 2023, Índice, Tomo CXXX; expedido por la H. XXIV\nLegislatura, siendo Gobernadora Constitucional la C. Marina del Pilar Ávila Olmeda 20212027;\nARTÍCULO 107.- Fue reformado por Decreto No. 391, publicado en el Periódico\nOficial No. 13, de fecha 08 de marzo de 2024, Índice, Tomo CXXXI; expedido por la H. XXIV\nLegislatura, siendo Gobernadora Constitucional la C. Marina del Pilar Ávila Olmeda 20212027;\nARTÍCULO 109.- De conformidad con lo estipulado en su Resolutivo Segundo y\nTercero de la Sentencia de Acción de Inconstitucionalidad 18/2021, publicada en el\nPeriódico Oficial No. 94, Sección I, Tomo CXXVIII, de fecha 19 de noviembre de 2021, siendo Gobernadora la C. Marina del Pilar Ávila Olmeda 2021-2027, “Se declara la invalidez de los artículos 31, 32, 33 y del 37 al 41 y por extensión la de diversos artículos de esta Ley, expedida mediante Decreto No. 188, publicado en el Periódico Oficial el 28 de diciembre de\n2020, expedido por la H. XXIII Legislatura, siendo Gobernador Constitucional el C. Jaime\nBonilla Valdez 2019-2021; fue reformado por Decreto No. 295, publicado en el Periódico\nOficial No. 62, de fecha 06 de noviembre de 2023, Índice, Tomo CXXX, expedido por la H.\nXXIV Legislatura, atendiendo la Sentencia de Acción de Inconstitucionalidad 18/2021, siendo\nGobernadora Constitucional la C. Marina del Pilar Ávila Olmeda 2021-2027;\nARTÍCULO 110.- De conformidad con lo estipulado en su Resolutivo Segundo y\nTercero de la Sentencia de Acción de Inconstitucionalidad 18/2021, publicada en el\nPeriódico Oficial No. 94, Sección I, Tomo CXXVIII, de fecha 19 de noviembre de 2021, siendo Gobernadora la C. Marina del Pilar Ávila Olmeda 2021-2027, “Se declara la invalidez de los artículos 31, 32, 33 y del 37 al 41 y por extensión la de diversos artículos de esta Ley, expedida mediante Decreto No. 188, publicado en el Periódico Oficial el 28 de diciembre de\n2020, expedido por la H. XXIII Legislatura, siendo Gobernador Constitucional el C. Jaime\nBonilla Valdez 2019-2021; fue reformado por Decreto No. 295, publicado en el Periódico\nXXIV Legislatura, atendiendo la Sentencia de Acción de Inconstitucionalidad 18/2021, siendo\nGobernadora Constitucional la C. Marina del Pilar Ávila Olmeda 2021-2027;\nARTÍCULO 115.- De conformidad con lo estipulado en su Resolutivo Segundo y\nTercero de la Sentencia de Acción de Inconstitucionalidad 18/2021, publicada en el\nLey de Educación del Estado de Baja California. Página 77 siendo Gobernadora la C. Marina del Pilar Ávila Olmeda 2021-2027, “Se declara la invalidez de los artículos 31, 32, 33 y del 37 al 41 y por extensión la de diversos artículos de esta Ley, expedida mediante Decreto No. 188, publicado en el Periódico Oficial el 28 de diciembre de\n2020, expedido por la H. XXIII Legislatura, siendo Gobernador Constitucional el C. Jaime\nBonilla Valdez 2019-2021; fue reformado por Decreto No. 295, publicado en el Periódico\nOficial No. 62, de fecha 06 de noviembre de 2023, Índice, Tomo CXXX, expedido por la H.\nXXIV Legislatura, atendiendo la Sentencia de Acción de Inconstitucionalidad 18/2021, siendo\nGobernadora Constitucional la C. Marina del Pilar Ávila Olmeda 2021-2027;\nARTÍCULO 120.- Fue reformado por Decreto No. 391, publicado en el Periódico\nOficial No. 13, de fecha 08 de marzo de 2024, Índice, Tomo CXXXI; expedido por la H. XXIV\nLegislatura, siendo Gobernadora Constitucional la C. Marina del Pilar Ávila Olmeda 20212027;\nARTÍCULO 122.- Fue reformado mediante Decreto No. 317, publicado en el Periódico\nOficial No. 67, de fecha 01 de diciembre de 2023, Sección I, Tomo CXXX; expedido por la H.\nXXIV Legislatura, siendo Gobernadora Constitucional la C. Marina del Pilar Ávila Olmeda\n2021-2027;\nARTÍCULO 123.- Fue reformado por Decreto No. 234, publicado en el Periódico\nOficial No. 30, de fecha 26 de mayo de 2023, Índice, Tomo CXXX, expedido por la H. XXIV\nLegislatura, siendo Gobernadora Constitucional la C. Marina del Pilar Ávila Olmeda, 20212027;\nARTÍCULO 126.- De conformidad con lo estipulado en su Resolutivo Segundo y\nTercero de la Sentencia de Acción de Inconstitucionalidad 18/2021, publicada en el\nPeriódico Oficial No. 94, Sección I, Tomo CXXVIII, de fecha 19 de noviembre de 2021, siendo Gobernadora la C. Marina del Pilar Ávila Olmeda 2021-2027, “Se declara la invalidez de los artículos 31, 32, 33 y del 37 al 41 y por extensión la de diversos artículos de esta Ley, expedida mediante Decreto No. 188, publicado en el Periódico Oficial el 28 de diciembre de\n2020, expedido por la H. XXIII Legislatura, siendo Gobernador Constitucional el C. Jaime\nBonilla Valdez 2019-2021; fue reformado por Decreto No. 239, publicado en el Periódico\nLegislatura, siendo Gobernadora Constitucional la C. Marina del Pilar Ávila Olmeda, 20212027; fue reformado por Decreto No. 295, publicado en el Periódico Oficial No. 62, de fecha atendiendo la Sentencia de Acción de Inconstitucionalidad 18/2021, siendo Gobernadora\nConstitucional la C. Marina del Pilar Ávila Olmeda 2021-2027; fue reformado por Decreto No.\nTomo CXXX, expedido por la H. XXIV Legislatura, siendo Gobernadora Constitucional la C.\nMarina del Pilar Ávila Olmeda, 2021-2027;\nLey de Educación del Estado de Baja California. Página 78\nARTÍCULO SEXTO TRANSITRIO DE ESTA LEY.- De conformidad con lo estipulado\n18/2021, publicada en el Periódico Oficial No. 94, Sección I, Tomo CXXVIII, de fecha 19 de declara la invalidez de los artículos 31, 32, 33 y del 37 al 41 y por extensión la de diversos artículos de esta Ley, expedida mediante Decreto No. 188, publicado en el Periódico Oficial\nConstitucional el C. Jaime Bonilla Valdez 2019-2021;\nLey de Educación del Estado de Baja California. Página 79\nARTÍCULO TERCERO TRANSITORIO DEL DECRETO No. 213, POR EL QUE SE\nAPRUEBA LA ADICIÓN DEL ARTÍCULO 72 BIS, PUBLICADO EN EL PERIÓDICO OFICIAL\nXXIII LEGISLATURA, SIENDO GOBERNADOR CONSTITUCIONAL EL C. JAIME BONILLA\nVALDEZ 2019-2021.\nARTÍCULO TRANSITORIO\nÚNICO.- El presente decreto entrara en vigor el día siguiente a su publicación en el\nPeriódico Oficial del Estado.\nDADO en Sesión Extraordinaria Virtual en la Ciudad de Mexicali, B.C., a los seis días del mes de marzo del año dos mil veintiuno.\nDIP. EVA GRICELDA RODRÍGUEZ\nPRESIDENTA\n(RÚBRICA)\nDIP. MARÍA LUISA VILLALOBOS ÁVILA\nSECRETARIA\n(RÚBRICA)\nDE CONFORMIDAD CON LO DISPUESTO POR LA FRACCION I DEL ARTÍCULO 49\nCALIFORNIA, IMPRÍMASE Y PUBLÍQUESE.\nMEXICALI, BAJA CALIFORNIA, A LOS DIECISÉIS DÍAS DEL MES DE MARZO DEL\nAÑO DOS MIL VEINTIUNO.\nJAIME BONILLA VALDEZ\nGOBERNADOR DEL ESTADO\n(RÚBRICA)\nAMADOR RODRÍGUEZ LOZANO\nSECRETARIO GENERAL DE GOBIERNO\n(RÚBRICA)\nARTÍCULO ÚNICO TRANSITORIO DEL DECRETO No. 263, POR EL QUE SE\nAPRUEBA LA ADICIÓN DEL ARTÍCULO 73 BIS, PUBLICADO EN EL PERIÓDICO OFICIAL\nPOR LA H. XXIII LEGISLATURA, SIENDO GOBERNADOR CONSTITUCIONAL EL C.\nJAIME BONILLA VALDEZ 2019-2021.\nTRANSITORIOS\nÚNICO.- El presente Decreto entrará en vigor al día siguiente a su publicación en el\nPeriódico Oficial del Estado.\nLey de Educación del Estado de Baja California. Página 80\nDADO en Sesión Ordinaria Virtual en la Ciudad de Mexicali, B.C., a los treinta días del mes de junio del año dos mil veintiuno.\nDIP. EVA GRICELDA RODRÍGUEZ\nPRESIDENTA\n(RÚBRICA)\nDIP. MARÍA LUISA VILLALOBOS ÁVILA\nSECRETARIA\n(RÚBRICA)\nDE CONFORMIDAD CON LO DISPUESTO POR LA FRACCION I DEL ARTÍCULO 49\nCALIFORNIA, IMPRÍMASE Y PUBLÍQUESE.\nMEXICALI, BAJA CALIFORNIA, A LOS CINCO DÍAS DEL MES DE JULIO DEL AÑO\nDOS MIL VEINTIUNO.\nJAIME BONILLA VALDEZ\nGOBERNADOR DEL ESTADO\n(RÚBRICA)\nAMADOR RODRÍGUEZ LOZANO\nSECRETARIO GENERAL DE GOBIERNO\n(RÚBRICA)\nSENTENCIA DE ACCIÓN DE INCONSTITUCIONALIDAD 18/2021, PUBLICADA EN\nEL PERIÓDICO OFICIAL NO. 94, SECCIÓN I, TOMO CXXVIII, DE FECHA 19 DE\nNOVIEMBRE DE 2021, MEDIANTE LA CUAL SE RESUELVE:\n“PRIMERO. Es procedente y fundada la presente acción de inconstitucionalidad.\nSEGUNDO. Se declara la invalidez de los artículos 31, 32, 33 y del 37 al 41 de la Ley de Educación del Estado de Baja California, expedida mediante el Decreto No. 188, dos mil veinte, en términos del considerando quinto de esta decisión y, por extensión, la de de esta determinación.\nTERCERO. Las declaratorias de invalidez decretadas surtirán sus efectos a los\nLey de Educación del Estado de Baja California. Página 81\nEstado de Baja California, en la inteligencia de que, dentro del referido plazo, previo afromexicanas, así como a las personas con discapacidad, ese Congreso deberá legislar en las materias de educación indígena y de educación inclusiva, en los términos precisados en el considerando sexto de esta sentencia.\nCUARTO. Publíquese esta resolución en el Diario Oficial de la Federación, en el\nPeriódico Oficial del Estado de Baja California, así como en el Semanario Judicial de la\nFederación y su Gaceta.”\nNotifíquese, haciéndolo por medio de oficio a las partes y, en su oportunidad, archívese el expediente como asunto concluido.\nAsí lo resolvió el Pleno de la Suprema Corte de Justicia de la Nación:\n……\nFirman el Ministro Presidente de la Suprema Corte de Justicia de la Nación y el\nMinistro Ponente, con el Secretario General de Acuerdos, que autoriza y da fe.\nMINISTRO ARTURO ZALDÍVAR LELO DE LARREA\nPRESIDENTE DE LA SUPREMA CORTE\nDE JUSTICIA DE LA NACIÓN\nMINISTRO JOSÉ FERNANDO FRANCO GONZÁLEZ SALAS\nPONENTE\nLICENCIADO RAFAEL COELLO CETINA\nSECRETARIO GENERAL DE ACUERDOS\nARTÍCULO ÚNICO TRANSITORIO DEL DECRETO No. 154, POR EL QUE SE\nREFORMA EL ARTÍCULO 6; PUBLICADO EN EL PERIÓDICO OFICIAL No. 63, SECCIÓN\nLEGISLATURA, SIENDO GOBERNADORA CONSTITUCIONAL LA C. MARINA DEL PILAR\nÁVILA OLMEDA 2021-2027.\nTRANSITORIO\nLey de Educación del Estado de Baja California. Página 82\nPRIMERO. La presente Ley entrará en vigor al día siguiente de su publicación en el\nPeriódico Oficial del Estado de Baja California.\nSEGUNDO. En un plazo de ciento ochenta días siguientes a la entrada en vigor del presente Decreto, la autoridad educativa deberá armonizar los lineamientos y protocolos respectivos a la seguridad escolar.\nDADO en Sesión Ordinaria de la XXIV Legislatura en la Ciudad de Mexicali, B.C., a los seis días del mes de octubre del año dos mil veintidós.\nDIP. ALEJANDRA MARÍA ANG HERNÁNDEZ\nPRESIDENTA\n(RÚBRICA)\nDIP. DUNNIA MONTSERRAT MURILLO LÓPEZ\nSECRETARIA\n(RÚBRICA)\nDE CONFORMIDAD CON LO DISPUESTO POR LA FRACCIÓN I DEL ARTÍCULO 49\nCALIFORNIA, IMPRÍMASE Y PUBLÍQUESE.\nMEXICALI, BAJA CALIFORNIA, A LOS ONCE DÍAS DEL MES DE OCTUBRE DEL\nAÑO DOS MIL VEINTIDÓS.\nMARINA DEL PILAR ÁVILA OLMEDA\nGOBERNADORA DEL ESTADO\nDE BAJA CALIFORNIA\n(RÚBRICA)\nCATALINO ZAVALA MÁRQUEZ\nSECRETARIO GENERAL DE GOBIERNO\nDEL ESTADO DE BAJA CALIFORNIA\n(RÚBRICA)\nARTÍCULO PRIMERO TRANSITORIO DEL DECRETO No. 198, POR EL QUE SE\nREFORMA EL ARTÍCULO 6, 45, 65 y 104, ASÍ COMO LA ADICIÓN DEL ARTÍCULO 73\nTER; PUBLICADO EN EL PERIÓDICO OFICIAL No. 6, ÍNDICE, TOMO CXXX, DE FECHA\nGOBERNADORA CONSTITUCIONAL LA C. MARINA DEL PILAR ÁVILA OLMEDA 2021-\n2027.\nTRANSITORIO\nLey de Educación del Estado de Baja California. Página 83\nPRIMERO. EI presente Decreto entrará en vigor al día siguiente de su publicación en el Periódico Oficial del Estado.\nSEGUNDO. El suministro gratuito de productos de gestión menstrual se sujetará a la disponibilidad presupuestaria que se determine para tales fines. correspondientes, así como las normas que determinen el control y uso racional de los productos a que se refiere este artículo.\nDADO en Sesión Ordinaria de la XXIV Legislatura en la Ciudad de Mexicali, B.C., a los doce días del mes de enero del año dos mil veintitrés.\nDIP. MARÍA DEL ROCÍO ADAME MUÑOZ\nPRESIDENTA\n(RÚBRICA)\nDIP. DUNNIA MONTSERRAT MURILLO LÓPEZ\nSECRETARIA\n(RÚBRICA)\nDE CONFORMIDAD CON LO DISPUESTO POR LA FRACCIÓN I DEL ARTÍCULO 49\nCALIFORNIA, IMPRÍMASE Y PUBLÍQUESE.\nMEXICALI, BAJA CALIFORNIA, A LOS TRECE DÍAS DEL MES DE ENERO DEL AÑO DOS\nMIL VEINTITRÉS.\nMARINA DEL PILAR ÁVILA OLMEDA\nGOBERNADORA DEL ESTADO\nDE BAJA CALIFORNIA\n(RÚBRICA)\nCATALINO ZAVALA MÁRQUEZ\nSECRETARIO GENERAL DE GOBIERNO\nDEL ESTADO DE BAJA CALIFORNIA\n(RÚBRICA)\nARTÍCULO CUARTO TRANSITORIO DEL DECRETO No. 229, POR EL QUE SE\nREFORMA EL ARTÍCULO 123; PUBLICADO EN EL PERIÓDICO OFICIAL No. 30, ÍNDICE,\nLEGISLATURA, SIENDO GOBERNADORA CONSTITUCIONAL LA C. MARINA DEL PILAR\nÁVILA OLMEDA 2021-2027.\nTRANSITORIOS\nLey de Educación del Estado de Baja California. Página 84\nÚNICO.- La presente reforma entrará en vigor al día siguiente de su publicación en el\nPeriódico Oficial del Estado de Baja California.\nDADO en Sesión Ordinaria de la XXIV Legislatura en la Ciudad de Mexicali, B.C., a los veintiocho días del mes de abril del año dos mil veintitrés.\nDIP. MANUEL GUERRERO LUNA\nPRESIDENTE\n(RÚBRICA)\nDIP. ALEJANDRA MARÍA ANG HERNÁNDEZ\nSECRETARIA\n(RÚBRICA)\nDE CONFORMIDAD CON LO DISPUESTO POR LA FRACCIÓN I DEL ARTÍCULO 49\nBAJA CALIFORNIA, IMPRÍMASE Y PUBLÍQUESE.\nMEXICALI, BAJA CALIFORNIA, A LOS OCHO DÍAS DEL MES DE MAYO DEL AÑO DOS\nMIL VEINTITRÉS.\nMARINA DEL PILAR ÁVILA OLMEDA\nGOBERNADOR DEL ESTADO\nDE BAJA CALIFORNIA\n(RÚBRICA)\nCATALINO ZAVALA MÁRQUEZ\nSECRETARIO GENERAL DE GOBIERNO\nDEL ESTADO DE BAJA CALIFORNIA\n(RÚBRICA)\nARTÍCULO ÚNICO TRANSITORIO DEL DECRETO No. 234, POR EL QUE SE\nREFORMA EL ARTÍCULO 88; PUBLICADO EN EL PERIÓDICO OFICIAL No. 30, ÍNDICE,\nLEGISLATURA, SIENDO GOBERNADORA CONSTITUCIONAL LA C. MARINA DEL PILAR\nÁVILA OLMEDA 2021-2027.\nARTICULO TRANSITORIO\nLey de Educación del Estado de Baja California. Página 85\nÚNICO.- La presente reforma entrará en vigor al día siguiente de su publicación en el\nPeriódico Oficial del Estado.\nDADO en Sesión Ordinaria de la XXIV Legislatura en la Ciudad de Mexicali, B.C., a los once días del mes de mayo del año dos mil veintitrés.\nDIP. MANUEL GUERRERO LUNA\nPRESIDENTE\n(RÚBRICA)\nDIP. ALEJANDRA MARÍA ANG HERNÁNDEZ\nSECRETARIA\n(RÚBRICA)\nDE CONFORMIDAD CON LO DISPUESTO POR LA FRACCIÓN I DEL ARTÍCULO 49\nBAJA CALIFORNIA, IMPRÍMASE Y PUBLÍQUESE.\nMEXICALI, BAJA CALIFORNIA, A LOS QUINCE DÍAS DEL MES DE MAYO DEL AÑO DOS\nMIL VEINTITRÉS.\nMARINA DEL PILAR ÁVILA OLMEDA\nGOBERNADOR DEL ESTADO\nDE BAJA CALIFORNIA\n(RÚBRICA)\nCATALINO ZAVALA MÁRQUEZ\nSECRETARIO GENERAL DE GOBIERNO\nDEL ESTADO DE BAJA CALIFORNIA\n(RÚBRICA)\nARTÍCULO ÚNICO TRANSITORIO DEL DECRETO No. 239, POR EL QUE SE\nREFORMA LA FRACCIÓN XXIII DEL ARTÍCULO 126; PUBLICADO EN EL PERIÓDICO\nPOR LA H. XXIV LEGISLATURA, SIENDO GOBERNADORA CONSTITUCIONAL LA C.\nMARINA DEL PILAR ÁVILA OLMEDA 2021-2027.\nARTICULO TRANSITORIO\nLey de Educación del Estado de Baja California. Página 86\nÚNICO.- El presente Decreto entrará en vigor al día siguiente de su publicación en el\nPeriódico Oficial del Estado.\nDADO en Sesión Ordinaria de la XXIV Legislatura en la Ciudad de Mexicali, B.C., a los ocho días del mes de junio del año dos mil veintitrés.\nDIP. MANUEL GUERRERO LUNA\nPRESIDENTE\n(RÚBRICA)\nDIP. ALEJANDRA MARÍA ANG HERNÁNDEZ\nSECRETARIA\n(RÚBRICA)\nDE CONFORMIDAD CON LO DISPUESTO POR LA FRACCIÓN I DEL ARTÍCULO 49\nBAJA CALIFORNIA, IMPRÍMASE Y PUBLÍQUESE.\nMEXICALI, BAJA CALIFORNIA, A LOS NUEVE DÍAS DEL MES DE JUNIO DEL AÑO DOS\nMIL VEINTITRÉS.\nMARINA DEL PILAR ÁVILA OLMEDA\nGOBERNADOR DEL ESTADO\nDE BAJA CALIFORNIA\n(RÚBRICA)\nCATALINO ZAVALA MÁRQUEZ\nSECRETARIO GENERAL DE GOBIERNO\nDEL ESTADO DE BAJA CALIFORNIA\n(RÚBRICA)\nARTÍCULO ÚNICO TRANSITORIO DEL DECRETO No. 281, POR EL QUE SE\nREFORMA EL ARTÍCULO 80; PUBLICADO EN EL PERIÓDICO OFICIAL No. 53, SECCIÓN\nLEGISLATURA, SIENDO GOBERNADORA CONSTITUCIONAL LA C. MARINA DEL PILAR\nÁVILA OLMEDA 2021-2027.\nTRANSITORIOS\nLey de Educación del Estado de Baja California. Página 87\nÚNICO. La presente reforma entrará en vigor al día siguiente de su publicación en el\nPeriódico Oficial del Estado.\nDADO en Sesión Ordinaria de la XXIV Legislatura en la Ciudad de Mexicali, B.C., a los veinticuatro días del mes de agosto del año dos mil veintitrés.\nDIP. MANUEL GUERRERO LUNA\nPRESIDENTE\n(RÚBRICA)\nDIP. DUNNIA MONTSERRAT MURILLO LÓPEZ\nSECRETARIA\n(RÚBRICA)\nDE CONFORMIDAD CON LO DISPUESTO POR LA FRACCIÓN I DEL ARTÍCULO 49\nBAJA CALIFORNIA, IMPRÍMASE Y PUBLÍQUESE.\nMEXICALI, BAJA CALIFORNIA, A LOS VEINTIOCHO DÍAS DEL MES DE AGOSTO DEL\nAÑO DOS MIL VEINTITRÉS.\nMARINA DEL PILAR ÁVILA OLMEDA\nGOBERNADOR DEL ESTADO\nDE BAJA CALIFORNIA\n(RÚBRICA)\nCATALINO ZAVALA MÁRQUEZ\nSECRETARIO GENERAL DE GOBIERNO\nDEL ESTADO DE BAJA CALIFORNIA\n(RÚBRICA)\nARTÍCULO ÚNICO TRANSITORIO DEL DECRETO No. 295, POR EL QUE SE\nAPRUEBAN LAS REFORMAS A LOS ARTÍCULOS 6, 10, 12, 13, 24, 31, 32, 33, 37, 38, 39,\n40, 41, 45, 46, 80, 84, 91, 109, 110, 115 Y 126, (ATENDIENDO LA SENTENCIA DE\nACCIÓN DE INCONSTITUCIONALIDAD 18/2021); PUBLICADO EN EL PERIÓDICO\nEXPEDIDO POR LA H. XXIV LEGISLATURA, SIENDO GOBERNADORA\nCONSTITUCIONAL LA C. MARINA DEL PILAR ÁVILA OLMEDA 2021-2027.\nTRANSITORIOS\nPRIMERO. La presente reforma entrará en vigor al día siguiente de su publicación en el\nPeriódico Oficial del Estado.\nLey de Educación del Estado de Baja California. Página 88\nSEGUNDO. Remítase copia certificada del presente Dictamen para que obre como legalmente corresponda dentro de la Acción de Inconstitucionalidad 18/2021.\nDADO en Sesión Ordinaria de la XXIV Legislatura en la Ciudad de Mexicali, B.C., a los diecinueve días del mes de octubre del año dos mil veintitrés.\nDIP. MANUEL GUERRERO LUNA\nPRESIDENTE\n(RÚBRICA)\nDIP. DUNNIA MONTSERRAT MURILLO LÓPEZ\nSECRETARIA\n(RÚBRICA)\nDE CONFORMIDAD CON LO DISPUESTO POR LA FRACCIÓN I DEL ARTÍCULO 49\nCALIFORNIA, IMPRÍMASE Y PUBLÍQUESE.\nMEXICALI, BAJA CALIFORNIA, A LOS VEINTITRÉS DÍAS DEL MES DE OCTUBRE\nDEL AÑO DOS MIL VEINTITRÉS.\nMARINA DEL PILAR ÁVILA OLMEDA\nGOBERNADORA DEL ESTADO\nDE BAJA CALIFORNIA\n(RÚBRICA)\nCATALINO ZAVALA MÁRQUEZ\nSECRETARIO GENERAL DE GOBIERNO\nDEL ESTADO DE BAJA CALIFORNIA\n(RÚBRICA)\nARTÍCULO SEGUNDO TRANSITORIO DEL DECRETO No. 308, POR EL QUE SE\nAPRUEBAN LAS REFORMAS A LOS ARTÍCULOS 67, 70 Y 73 BIS; PUBLICADO EN EL\nCXXX, EXPEDIDO POR LA H. XXIV LEGISLATURA, SIENDO GOBERNADORA\nCONSTITUCIONAL LA C. MARINA DEL PILAR ÁVILA OLMEDA 2021-2027.\nTRANSITORIOS\nPRIMERO.- El presente Decreto entrará en vigor al día siguiente de su publicación en el\nPeriódico Oficial del Estado.\nLey de Educación del Estado de Baja California. Página 89\nSEGUNDO.- Las autoridades educativas del Estado en un plazo de seis meses contados a partir de la vigencia del presente Decreto, actualizarán y/o emitirán los programas o protocolos de promoción, prevención y abordaje de la salud mental de los estudiantes.\nDADO en Sesión Ordinaria de la XXIV Legislatura en la Ciudad de Mexicali, B.C., a los diecinueve días del mes de octubre del año dos mil veintitrés.\nDIP. MANUEL GUERRERO LUNA\nPRESIDENTE\n(RÚBRICA)\nDIP. DUNNIA MONTSERRAT MURILLO LÓPEZ\nSECRETARIA\n(RÚBRICA)\nDE CONFORMIDAD CON LO DISPUESTO POR LA FRACCIÓN I DEL ARTÍCULO 49\nCALIFORNIA, IMPRÍMASE Y PUBLÍQUESE.\nMEXICALI, BAJA CALIFORNIA, A LOS VEINTITRÉS DÍAS DEL MES DE OCTUBRE\nDEL AÑO DOS MIL VEINTITRÉS.\nMARINA DEL PILAR ÁVILA OLMEDA\nGOBERNADORA DEL ESTADO\nDE BAJA CALIFORNIA\n(RÚBRICA)\nCATALINO ZAVALA MÁRQUEZ\nSECRETARIO GENERAL DE GOBIERNO\nDEL ESTADO DE BAJA CALIFORNIA\n(RÚBRICA)\nARTÍCULO ÚNICO TRANSITORIO DEL DECRETO No. 313, POR EL QUE SE\nAPRUEBA LA REFORMA A LA FRACCIÓN XIX DEL ARTÍCULOS 6 Y LA FRACCIÓN II\nDEL ARTÍCULO 48; PUBLICADO EN EL PERIÓDICO OFICIAL No. 67, DE FECHA 01 DE\nLEGISLATURA, SIENDO GOBERNADORA CONSTITUCIONAL LA C. MARINA DEL PILAR\nÁVILA OLMEDA 2021-2027.\nTRANSITORIO\nÚNICO.- El presente Decreto entrará en vigor al día siguiente de su publicación en el\nPeriódico Oficial del Estado.\nLey de Educación del Estado de Baja California. Página 90\nDADO en Sesión Ordinaria de la XXIV Legislatura en la Ciudad de Mexicali, B.C., a los nueve días del mes de noviembre del año dos mil veintitrés.\nDIP. MANUEL GUERRERO LUNA\nPRESIDENTE\n(RÚBRICA)\nDIP. DUNNIA MONTSERRAT MURILLO LÓPEZ\nSECRETARIA\n(RÚBRICA)\nDE CONFORMIDAD CON LO DISPUESTO POR LA FRACCIÓN I DEL ARTÍCULO 49\nCALIFORNIA, IMPRÍMASE Y PUBLÍQUESE.\nMEXICALI, BAJA CALIFORNIA, A LOS CATORCE DÍAS DEL MES DE NOVIEMBRE\nDEL AÑO DOS MIL VEINTITRÉS.\nMARINA DEL PILAR ÁVILA OLMEDA\nGOBERNADORA DEL ESTADO\nDE BAJA CALIFORNIA\n(RÚBRICA)\nCATALINO ZAVALA MÁRQUEZ\nSECRETARIO GENERAL DE GOBIERNO\nDEL ESTADO DE BAJA CALIFORNIA\n(RÚBRICA)\nARTÍCULO ÚNICO TRANSITORIO DEL DECRETO No. 317, POR EL QUE SE\nREFORMA EL ARTÍCULO 122; PUBLICADO EN EL PERIÓDICO OFICIAL No. 67, DE\nXXIV LEGISLATURA, SIENDO GOBERNADORA CONSTITUCIONAL LA C. MARINA DEL\nPILAR ÁVILA OLMEDA 2021-2027.\nTRANSITORIOS\nPRIMERO. - La presente Ley entrara en vigor al día siguiente de su publicación en el\nSEGUNDO.– La autoridad educativa estatal deberá emitir y adecuar el reglamento y demás disposiciones de carácter general conforme a lo establecido en este Decreto, en un plazo no mayor a ciento ochenta días hábiles siguientes contados a partir de su entrada en vigor.\nLey de Educación del Estado de Baja California. Página 91\nTERCERO.– La persona titular de la Secretaría de Educación del Estado de Baja California publicará, en los próximos 30 días de que entre en vigor la presente reforma en el portal que no cuentan con el mismo o hayan sido clausuradas o sancionadas.\nDADO en Sesión Ordinaria de la XXIV Legislatura en la Ciudad de Mexicali, B.C., a los nueve días del mes de noviembre del año dos mil veintitrés.\nDIP. MANUEL GUERRERO LUNA\nPRESIDENTE\n(RÚBRICA)\nDIP. DUNNIA MONTSERRAT MURILLO LÓPEZ\nSECRETARIA\n(RÚBRICA)\nDE CONFORMIDAD CON LO DISPUESTO POR LA FRACCIÓN I DEL ARTÍCULO 49\nCALIFORNIA, IMPRÍMASE Y PUBLÍQUESE.\nMEXICALI, BAJA CALIFORNIA, A LOS CATORCE DÍAS DEL MES DE NOVIEMBRE\nDEL AÑO DOS MIL VEINTITRÉS.\nMARINA DEL PILAR ÁVILA OLMEDA\nGOBERNADORA DEL ESTADO\nDE BAJA CALIFORNIA\n(RÚBRICA)\nCATALINO ZAVALA MÁRQUEZ\nSECRETARIO GENERAL DE GOBIERNO\nDEL ESTADO DE BAJA CALIFORNIA\n(RÚBRICA)\nARTÍCULO PRIMERO TRANSITORIO DEL DECRETO No. 318, POR EL QUE SE\nREFORMAN LOS ARTÍCULOS 50 Y 126; PUBLICADO EN EL PERIÓDICO OFICIAL No. 70,\nXXIV LEGISLATURA, SIENDO GOBERNADORA CONSTITUCIONAL LA C. MARINA DEL\nPILAR ÁVILA OLMEDA 2021-2027.\nTRANSITORIO\nLey de Educación del Estado de Baja California. Página 92\nÚNICO.- La presente reforma entrará en vigor al día siguiente de su publicación en el\nPeriódico Oficial del Estado de Baja California.\nDADO en Sesión Ordinaria de la XXIV Legislatura en la Ciudad de Mexicali, B.C., a los nueve días del mes de noviembre del año dos mil veintitrés.\nDIP. MANUEL GUERRERO LUNA\nPRESIDENTE\n(RÚBRICA)\nDIP. DUNNIA MONTSERRAT MURILLO LÓPEZ\nSECRETARIA\n(RÚBRICA)\nDE CONFORMIDAD CON LO DISPUESTO POR LA FRACCIÓN I DEL ARTÍCULO 49\nCALIFORNIA, IMPRÍMASE Y PUBLÍQUESE.\nMEXICALI, BAJA CALIFORNIA, A LOS CATORCE DÍAS DEL MES DE NOVIEMBRE\nDEL AÑO DOS MIL VEINTITRÉS.\nMARINA DEL PILAR ÁVILA OLMEDA\nGOBERNADORA DEL ESTADO\nDE BAJA CALIFORNIA\n(RÚBRICA)\nCATALINO ZAVALA MÁRQUEZ\nSECRETARIO GENERAL DE GOBIERNO\nDEL ESTADO DE BAJA CALIFORNIA\n(RÚBRICA)\nARTÍCULO ÚNICO TRANSITORIO DEL DECRETO No. 391, POR EL QUE SE\nAPRUEBA LA REFORMA A LOS ARTÍCULOS 107 Y 120; PUBLICADO EN EL PERIÓDICO\nPOR LA H. XXIV LEGISLATURA, SIENDO GOBERNADORA CONSTITUCIONAL LA C.\nMARINA DEL PILAR ÁVILA OLMEDA 2021-2027.\nTRANSITORIOS\nPRIMERO.- El presente Decreto entrará en vigor al día siguiente de su publicación en el\nPeriódico Oficial del Estado.\nLey de Educación del Estado de Baja California. Página 93 vigor de este Decreto, deberá emitir los lineamientos para la solicitud y cambio del modelo de los uniformes en las instituciones públicas y particulares.\nDADO en Sesión Extraordinaria de la XXIV Legislatura en la Ciudad de Mexicali, B.C., a los nueve días del mes de febrero del año dos mil veinticuatro.\nDIP. ARACELI GERALDO NÚÑEZ\nPRESIDENTA\n(RÚBRICA)\nDIP. MANUEL GUERRERO LUNA\nSECRETARIO\n(RÚBRICA)\nDE CONFORMIDAD CON LO DISPUESTO POR LA FRACCIÓN I DEL ARTÍCULO 49 DE\nCALIFORNIA, IMPRÍMASE Y PUBLÍQUESE.\nMEXICALI, BAJA CALIFORNIA, A LOS VEINTE DÍAS DEL MES DE FEBRERO DEL\nAÑO DOS MIL VEINTICUATRO.\nMARINA DEL PILAR ÁVILA OLMEDA\nGOBERNADORA DEL ESTADO\nDE BAJA CALIFORNIA\n(RÚBRICA)\nALFREDO ÁLVAREZ CÁRDENAS\nSECRETARIO GENERAL DE GOBIERNO\nDEL ESTADO DE BAJA CALIFORNIA\n(RÚBRICA)\nARTÍCULO ÚNICO TRANSITORIO DEL DECRETO No. 389, POR EL QUE SE\nAPRUEBA LA ADICIÓN DE LA FRACCIÓN X AL ARTÍCULO 85, Y UN ÚLTIMO PÁRRAFO\nAL ARTÍCULO 88; PUBLICADO EN EL PERIÓDICO OFICIAL No. 14, DE FECHA 15 DE\nSIENDO GOBERNADORA CONSTITUCIONAL LA C. MARINA DEL PILAR ÁVILA OLMEDA\n2021-2027.\nTRANSITORIOS:\nPRIMERO.- Las presentes reformas entrarán en vigor al día siguiente de su publicación en el Periódico Oficial del Estado.\nLey de Educación del Estado de Baja California. Página 94\nSEGUNDO.- La aplicación del presente Decreto, estará sujeto a la disponibilidad presupuestaria.\nDADO en Sesión Extraordinaria de la XXIV Legislatura en la Ciudad de Mexicali, B.C., a los nueve días del mes de febrero del año dos mil veinticuatro.\nDIP. ARACELI GERALDO NÚÑEZ\nPRESIDENTA\n(RÚBRICA)\nDIP. MANUEL GUERRERO LUNA\nSECRETARIO\n(RÚBRICA)\nDE CONFORMIDAD CON LO DISPUESTO POR LA FRACCIÓN I DEL ARTÍCULO 49 DE\nCALIFORNIA, IMPRÍMASE Y PUBLÍQUESE.\nMEXICALI, BAJA CALIFORNIA, A LOS CUATRO DÍAS DEL MES DE MARZO DEL\nAÑO DOS MIL VEINTICUATRO.\nMARINA DEL PILAR ÁVILA OLMEDA\nGOBERNADORA DEL ESTADO\nDE BAJA CALIFORNIA\n(RÚBRICA)\nALFREDO ÁLVAREZ CÁRDENAS\nSECRETARIO GENERAL DE GOBIERNO\nDEL ESTADO DE BAJA CALIFORNIA\n(RÚBRICA)\nARTÍCULO ÚNICO TRANSITORIO DEL DECRETO No. 399, POR EL QUE SE\nAPRUEBA LA REFORMA A LOS ARTÍCULOS 73 Y 74; PUBLICADO EN EL PERIÓDICO\nPOR LA H. XXIV LEGISLATURA, SIENDO GOBERNADORA CONSTITUCIONAL LA C.\nMARINA DEL PILAR ÁVILA OLMEDA 2021-2027.\nTRANSITORIO\nÚNICO. El presente Decreto entrará en vigor al día siguiente de su publicación en el\nPeriódico Oficial del Estado de Baja California.\nLey de Educación del Estado de Baja California. Página 95\nDADO en Sesión Ordinaria de la XXIV Legislatura en la Ciudad de Mexicali, B.C., a los veintinueve días del mes de febrero del año dos mil veinticuatro.\nDIP. ARACELI GERALDO NÚÑEZ\nPRESIDENTA\n(RÚBRICA)\nDIP. MANUEL GUERRERO LUNA\nSECRETARIO\n(RÚBRICA)\nDE CONFORMIDAD CON LO DISPUESTO POR LA FRACCIÓN I DEL ARTÍCULO 49\nCALIFORNIA, IMPRÍMASE Y PUBLÍQUESE.\nMEXICALI, BAJA CALIFORNIA, A LOS DOCE DÍAS DEL MES DE MARZO DEL AÑO\nDOS MIL VEINTICUATRO.\nMARINA DEL PILAR ÁVILA OLMEDA\nGOBERNADORA DEL ESTADO\nDE BAJA CALIFORNIA\n(RÚBRICA)\nALFREDO ÁLVAREZ CÁRDENAS\nSECRETARIO GENERAL DE GOBIERNO\nDEL ESTADO DE BAJA CALIFORNIA\n(RÚBRICA)\nARTÍCULO ÚNICO TRANSITORIO DEL DECRETO No. 421, POR EL QUE SE\nAPRUEBA LA REFORMA AL ARTÍCULO 65; PUBLICADO EN EL PERIÓDICO OFICIAL No.\n23, DE FECHA 07 DE MAYO DE 2024, ÍNDICE, TOMO CXXXI, EXPEDIDO POR LA H.\nXXIV LEGISLATURA, SIENDO GOBERNADORA CONSTITUCIONAL LA C. MARINA DEL\nPILAR ÁVILA OLMEDA 2021-2027.\nTRANSITORIO\nÚNICO.- La presente reforma entrará en vigor a partir del día siguiente al de la publicación en el Periódico Oficial del Estado de Baja California.\nDADO en Sesión de Ordinaria de la XXIV Legislatura en la Ciudad de Mexicali, B.C., a los dieciocho días del mes de abril del año dos mil veinticuatro.\nDIP. RAMÓN VÁZQUEZ VALADEZ\nPRESIDENTE\n(RÚBRICA)\nLey de Educación del Estado de Baja California. Página 96\nDIP. MANUEL GUERRERO LUNA\nSECRETARIO\n(RÚBRICA)\nDE CONFORMIDAD CON LO DISPUESTO POR LA FRACCIÓN I DEL ARTÍCULO 49\nCALIFORNIA, IMPRÍMASE Y PUBLÍQUESE.\nMEXICALI, BAJA CALIFORNIA, A LOS VEINTICINCO DÍAS DEL MES DE ABRIL\nDEL AÑO DOS MIL VEINTICUATRO.\nMARINA DEL PILAR ÁVILA OLMEDA\nGOBERNADORA DEL ESTADO\nDE BAJA CALIFORNIA\n(RÚBRICA)\nALFREDO ÁLVAREZ CÁRDENAS\nSECRETARIO GENERAL DE GOBIERNO\nDEL ESTADO DE BAJA CALIFORNIA\n(RÚBRICA)\nARTÍCULO ÚNICO TRANSITORIO DEL DECRETO No. 422, POR EL QUE SE\nAPRUEBA LA REFORMA AL ARTÍCULO 6; PUBLICADO EN EL PERIÓDICO OFICIAL No.\n23, DE FECHA 07 DE MAYO DE 2024, ÍNDICE, TOMO CXXXI, EXPEDIDO POR LA H.\nXXIV LEGISLATURA, SIENDO GOBERNADORA CONSTITUCIONAL LA C. MARINA DEL\nPILAR ÁVILA OLMEDA 2021-2027.\nTRANSITORIO\nÚNICO.- La presente reforma de Ley entrará en vigor al día siguiente de su publicación en el periódico oficial del Estado de Baja California.\nDADO en Sesión de Ordinaria de la XXIV Legislatura en la Ciudad de Mexicali, B.C., a los dieciocho días del mes de abril del año dos mil veinticuatro.\nDIP. RAMÓN VÁZQUEZ VALADEZ\nPRESIDENTE\n(RÚBRICA)\nDIP. MANUEL GUERRERO LUNA\nSECRETARIO\n(RÚBRICA)\nLey de Educación del Estado de Baja California. Página 97\nDE CONFORMIDAD CON LO DISPUESTO POR LA FRACCIÓN I DEL ARTÍCULO 49\nCALIFORNIA, IMPRÍMASE Y PUBLÍQUESE.\nMEXICALI, BAJA CALIFORNIA, A LOS VEINTICINCO DÍAS DEL MES DE ABRIL\nDEL AÑO DOS MIL VEINTICUATRO.\nMARINA DEL PILAR ÁVILA OLMEDA\nGOBERNADORA DEL ESTADO\nDE BAJA CALIFORNIA\n(RÚBRICA)\nALFREDO ÁLVAREZ CÁRDENAS\nSECRETARIO GENERAL DE GOBIERNO\nDEL ESTADO DE BAJA CALIFORNIA\n(RÚBRICA)\nARTÍCULO ÚNICO TRANSITORIO DEL DECRETO No. 423, POR EL QUE SE\nAPRUEBA LA REFORMA AL ARTÍCULO 87; PUBLICADO EN EL PERIÓDICO OFICIAL No.\n23, DE FECHA 07 DE MAYO DE 2024, ÍNDICE, TOMO CXXXI, EXPEDIDO POR LA H.\nXXIV LEGISLATURA, SIENDO GOBERNADORA CONSTITUCIONAL LA C. MARINA DEL\nPILAR ÁVILA OLMEDA 2021-2027.\nTRANSITORIO\nEl presente Decreto entrará en vigor al día siguiente de su publicación en el Periódico Oficial del Estado de Baja California.\nDADO en Sesión de Ordinaria de la XXIV Legislatura en la Ciudad de Mexicali, B.C., a los dieciocho días del mes de abril del año dos mil veinticuatro.\nDIP. RAMÓN VÁZQUEZ VALADEZ\nPRESIDENTE\n(RÚBRICA)\nDIP. MANUEL GUERRERO LUNA\nSECRETARIO\n(RÚBRICA)\nDE CONFORMIDAD CON LO DISPUESTO POR LA FRACCIÓN I DEL ARTÍCULO 49\nCALIFORNIA, IMPRÍMASE Y PUBLÍQUESE.\nMEXICALI, BAJA CALIFORNIA, A LOS VEINTICINCO DÍAS DEL MES DE ABRIL\nDEL AÑO DOS MIL VEINTICUATRO.\nLey de Educación del Estado de Baja California. Página 98\nMARINA DEL PILAR ÁVILA OLMEDA\nGOBERNADORA DEL ESTADO\nDE BAJA CALIFORNIA\n(RÚBRICA)\nALFREDO ÁLVAREZ CÁRDENAS\nSECRETARIO GENERAL DE GOBIERNO\nDEL ESTADO DE BAJA CALIFORNIA\n(RÚBRICA)\nARTÍCULO ÚNICO TRANSITORIO DEL DECRETO No. 424, POR EL QUE SE\nADICIONA EL ARTÍCULO 11 BIS; PUBLICADO EN EL PERIÓDICO OFICIAL No. 23, DE\nFECHA 07 DE MAYO DE 2024, ÍNDICE, TOMO CXXXI, EXPEDIDO POR LA H. XXIV\nLEGISLATURA, SIENDO GOBERNADORA CONSTITUCIONAL LA C. MARINA DEL PILAR\nÁVILA OLMEDA 2021-2027.\nTRANSITORIO\nÚNICO.- La presente reforma entrará en vigor al día siguiente al de su publicación en el\nPeriódico Oficial del Estado de Baja California.\nDADO en Sesión de Ordinaria de la XXIV Legislatura en la Ciudad de Mexicali, B.C., a los dieciocho días del mes de abril del año dos mil veinticuatro.\nDIP. RAMÓN VÁZQUEZ VALADEZ\nPRESIDENTE\n(RÚBRICA)\nDIP. MANUEL GUERRERO LUNA\nSECRETARIO\n(RÚBRICA)\nDE CONFORMIDAD CON LO DISPUESTO POR LA FRACCIÓN I DEL ARTÍCULO 49\nCALIFORNIA, IMPRÍMASE Y PUBLÍQUESE.\nMEXICALI, BAJA CALIFORNIA, A LOS VEINTICINCO DÍAS DEL MES DE ABRIL\nDEL AÑO DOS MIL VEINTICUATRO.\nMARINA DEL PILAR ÁVILA OLMEDA\nGOBERNADORA DEL ESTADO\nDE BAJA CALIFORNIA\n(RÚBRICA)\nLey de Educación del Estado de Baja California. Página 99\nALFREDO ÁLVAREZ CÁRDENAS\nSECRETARIO GENERAL DE GOBIERNO\nDEL ESTADO DE BAJA CALIFORNIA\n(RÚBRICA)\nARTÍCULO ÚNICO TRANSITORIO DEL DECRETO No. 51, POR EL QUE SE\nREFORMA EL ARTÍCULO 6; PUBLICADO EN EL PERIÓDICO OFICIAL No. 15, ÍNDICE, DE\nFECHA 14 DE MARZO DE 2025, TOMO CXXXII, EXPEDIDO POR LA H. XXV\nLEGISLATURA, SIENDO GOBERNADORA CONSTITUCIONAL LA C. MARINA DEL PILAR\nÁVILA OLMEDA 2021-2027.\nTRANSITORIOS\nÚNICO.- La presente reforma entrará en vigor al día hábil siguiente de su publicación en el\nPeriódico Oficial del Estado de Baja California.\nDADO en Sesión Ordinaria de la XXV Legislatura en la Ciudad de Mexicali, B.C., a los veintisiete días del mes de febrero del año dos mil veinticinco.\nDIP. EVELYN SÁNCHEZ SÁNCHEZ\nPRESIDENTA\n(RÚBRICA)\nDIP. MICHELLE ALEJANDRA TEJEDA MEDINA\nSECRETARIA\n(RÚBRICA)\nDE CONFORMIDAD CON LO DISPUESTO POR LA FRACCIÓN I DEL ARTÍCULO 49\nCALIFORNIA, IMPRÍMASE Y PUBLÍQUESE.\nMEXICALI, BAJA CALIFORNIA, A LOS TRES DÍAS DEL MES DE MARZO DEL AÑO\nDOS MIL VEINTICINCO.\nMARINA DEL PILAR ÁVILA OLMEDA\nGOBERNADORA DEL ESTADO\nDE BAJA CALIFORNIA\n(RÚBRICA)\nALFREDO ÁLVAREZ CÁRDENAS\nSECRETARIO GENERAL DE GOBIERNO\nDEL ESTADO DE BAJA CALIFORNIA\n(RÚBRICA)\nLey de Educación del Estado de Baja California. Página 100\nARTÍCULO ÚNICO TRANSITORIO DEL DECRETO No. 113, POR EL QUE SE\nAPRUEBA LA REFORMA AL ARTÍCULO 35; PUBLICADO EN EL PERIÓDICO OFICIAL No.\nXXV LEGISLATURA, SIENDO GOBERNADORA CONSTITUCIONAL LA C. MARINA DEL\nPILAR ÁVILA OLMEDA 2021-2027.\nTRANSITORIO\nÚNICO. La presente reforma entrará en vigor al día siguiente al de su publicación en el\nPeriódico Oficial del Estado.\nDADO en Sesión Ordinaria de la XXV Legislatura en la Ciudad de Mexicali, B.C., a los diecinueve días del mes de junio del año dos mil veinticinco.\nDIP. MICHELLE ALEJANDRA TEJEDA MEDINA\nPRESIDENTA\n(RÚBRICA)\nDIP. NORMA ANGELICA PEÑALOZA ESCOBEDO\nSECRETARIA\n(RÚBRICA)\nDE CONFORMIDAD CON LO DISPUESTO POR LA FRACCIÓN I DEL ARTÍCULO 49\nCALIFORNIA, IMPRÍMASE Y PUBLÍQUESE.\nMEXICALI, BAJA CALIFORNIA, A LOS 20 DÍAS DEL MES DE JUNIO DEL AÑO DOS\nMIL VEINTICINCO.\nMARINA DEL PILAR ÁVILA OLMEDA\nGOBERNADORA DEL ESTADO\nDE BAJA CALIFORNIA\n(RÚBRICA)\nALFREDO ÁLVAREZ CÁRDENAS\nSECRETARIO GENERAL DE GOBIERNO\nDEL ESTADO DE BAJA CALIFORNIA\n(RÚBRICA)\nLey de Educación del Estado de Baja California. Página 101",
  "ordenamiento": "REGLAMENTO",
  "jurisdiccion": "BAJA CALIFORNIA",
  "fuente_oficial": "Periódico Oficial",
  "FECHA PER OFIC": "2025/06/27",
  "ESTATUS": "VIGENTE",
  "TOMO": "TOMO_VI",
  "URL": "https://www.congresobc.gob.mx/Documentos/ProcesoParlamentario/Leyes/TOMO_VI/20250627_LEYEDUCACION.PDF",
  "es_escaneado": false,
  "tiene_tablas": false,
  "materia": [
    "social",
    "salud",
    "educación",
    "cultura"
  ]
}