{
  "titulo": "Ley DEL SISTEMA ESTATAL DE SEGURIDAD CIUDADANA DE BAJA CALIFORNIA",
  "Contenido": ".\nActualización Legislativa.\nÚltima Reforma P.O. No. 54, Índice, 05-Sep-2025\nLEY DEL SISTEMA ESTATAL DE SEGURIDAD CIUDADANA\nDE BAJA CALIFORNIA\nDenominación de Ley Reformada\nPublicada en el Periódico Oficial No. 84, Tomo CXXVII, Sección XI, de fecha 28 de diciembre de 2020\nTÍTULO PRIMERO\nDISPOSICIONES GENERALES\nCAPÍTULO I\nOBJETO DE LA LEY\nARTÍCULO 1.- La presente Ley es de orden público, interés social y de observancia obligatoria, y tiene por objeto establecer las bases, mecanismos e instrumentos para garantizar la paz y la seguridad de las personas que habitan y transitan en el Estado de Baja\nCalifornia, con pleno respeto a los derechos humanos, a través del establecimiento de los siguientes elementos:\nI.- Las atribuciones y bases de coordinación que corresponden al Estado y Municipios conforme al Sistema Nacional de Seguridad Pública y a los convenios que en la materia se celebren;\nII.- Regular la integración, coordinación, organización y funcionamiento del Sistema\nEstatal de Seguridad Ciudadana;\nIII.- Las atribuciones que en materia de seguridad ciudadana corresponden al Poder\nEjecutivo y las que ejercerá a través de la Secretaría de Seguridad Ciudadana y la Comisión del Sistema Penitenciario;\nIV.- Las disposiciones que regulan la relación administrativa de los Miembros de las\nInstituciones Policiales y la Agencia Estatal de Investigación con el órgano público y las dependencias o entidades a las que pertenezcan ya sean estatales o municipales, con motivo de la prestación de sus servicios, de conformidad con las bases de la Ley General del\nSistema Nacional de Seguridad Pública.\nLos municipios, atendiendo a su autonomía y conforme a su propia organización, podrán reglamentar las disposiciones de esta Ley en el ámbito de su competencia.\nArtículo Reformado en el ámbito de su respectiva competencia, con la colaboración y participación de la ciudadanía, comprendiendo los siguientes fines:\nLey del Sistema Estatal de Seguridad Ciudadana de Baja California. Página 1\n.\nActualización Legislativa.\nÚltima Reforma P.O. No. 54, Índice, 05-Sep-2025\nI.- Garantizar el goce y ejercicio de los derechos humanos;\nII.- Preservar las libertades, el orden y la paz públicos;\nIII.- La prevención especial y general de los delitos;\nIV.- La prevención social de las violencias;\nV.- La protección a la dignidad, libertad, seguridad y demás derechos de las personas en riesgo de sufrir hechos violentos o como víctimas de los mismos, en los términos de esta\nLey;\nVI.- La inteligencia preventiva de hechos violentos y delitos, y\nVII.- La reinserción social de sentenciados.\nArtículo Reformado\nARTÍCULO 3.- Las Instituciones de Seguridad desarrollarán políticas en materia de prevención social de las violencias y del delito; sobre las causas estructurales de su origen, así como programas y acciones para fomentar en la sociedad valores culturales y cívicos, el respeto a la legalidad y la protección de las personas. El desarrollo de dichas políticas y programas debe incluir la colaboración y participación ciudadana.\nAsimismo, realizarán acciones en materia de seguridad, promoviendo en el ámbito de su competencia acciones de coordinación con los sectores público, social y privado.\nEstas acciones tendrán como eje central a las personas, asegurando en todo momento, sus libertades y derechos humanos, así como propiciar condiciones que permitan a los habitantes del Estado la convivencia y el fomento de una cultura de paz en democracia.\nEn los casos de desastres y emergencias en el Estado, las Instituciones de Seguridad se coordinarán con las de protección civil, para salvaguardar con mayor oportunidad los intereses de la colectividad.\nLas Instituciones de Seguridad serán de carácter civil, disciplinado y profesional, su actuación se regirá además, por los principios de legalidad, objetividad, eficacia, profesionalismo, honradez y respeto a los derechos humanos reconocidos en la Constitución\nPolítica de los Estados Unidos Mexicanos.\nArtículo Reformado\nARTÍCULO 4.- Además de los derechos que en materia de seguridad señalan otras disposiciones normativas aplicables, el Estado tiene la obligación de garantizar a las personas los siguientes:\nI.- Convivencia pacífica y solidaria;\nLey del Sistema Estatal de Seguridad Ciudadana de Baja California. Página 2\n.\nActualización Legislativa.\nÚltima Reforma P.O. No. 54, Índice, 05-Sep-2025\nII.- Vivir libre de amenazas generadas por el ejercicio de las violencias y delitos;\nIII.- No violencia interpersonal o social;\nIV.- Integridad física;\nV.- Libertad personal;\nVI.- Uso pacífico de los bienes;\nVII.- Privacidad;\nVIII.- Libertad de expresión;\nIX.- Libertad de reunión y asociación;\nX.- Participar en el logro de los fines de la seguridad ciudadana, y\nXI.- Los demás que le señalen las leyes, reglamentos y disposiciones normativas aplicables.\nLas acciones para proteger los derechos en materia de seguridad deberán ejecutarse con enfoque diferencial y perspectiva de género frente a las violencias y el delito.\nArtículo Reformado\nARTÍCULO 5.- Para efectos de esta Ley, además de los conceptos contenidos en la\nLey General del Sistema Nacional de Seguridad Pública, se entenderá por:\nI.- Comisión: La instancia colegiada de las Instituciones de Seguridad de orden estatal o municipal, y de la Fiscalía General, responsable de conocer y resolver los\nInstituciones Policiales a su cargo;\nII.- Comisión Estatal: La Comisión Estatal del Sistema Penitenciario de Baja\nCalifornia;\nIII.- Consejo Estatal: El Consejo Estatal de Seguridad Ciudadana;\nIV.- Consejo Ciudadano: El Consejo Ciudadano de Seguridad, la instancia colegiada de consulta y participación ciudadana en materia de seguridad ciudadana del Estado;\nV.- Consejo Nacional: El Consejo Nacional de Seguridad Pública;\nLey del Sistema Estatal de Seguridad Ciudadana de Baja California. Página 3\n.\nActualización Legislativa.\nÚltima Reforma P.O. No. 54, Índice, 05-Sep-2025\nVI.- Contraloría Interna: El órgano de la Institución de Seguridad, Fiscalía o aquél que en los respectivos reglamentos se designe, encargado de la investigación administrativa, de solicitar a la Comisión el inicio del procedimiento de remoción del cargo o separación definitiva y demás facultades a que refiere la Ley y los reglamentos respectivos;\nVII.- Elementos de Apoyo: Los servidores públicos de las Instituciones de Seguridad que no pertenecen a la Carrera Policial, Ministerial o Pericial;\nVIII.- Evaluación: El mecanismo para estimar los conocimientos, aptitudes y rendimiento de los Miembros, Agentes del Ministerio Público, Peritos, Elementos de apoyo de las Instituciones de Seguridad Ciudadana y de la Fiscalía General;\nIX.- Fiscalía General: La Fiscalía General del Estado de Baja California;\nX.- Formación: El proceso mediante el cual se desarrollan las capacidades, se amplían los conocimientos y las destrezas que el aspirante requiere para el ejercicio profesional en un área específica de las Instituciones de Seguridad;\nXI.- Instituto: El Instituto de Estudios de Prevención y Formación Interdisciplinaria;\nXII.- Instituciones de Seguridad: La Secretaría de Seguridad Ciudadana, la Fiscalía\nGeneral, la Comisión Estatal del Sistema Penitenciario y las dependencias o unidades administrativas a cargo de la seguridad en los municipios, las Instituciones Policiales y la\nAgencia Estatal de Investigación;\nXIII.- Institutos de Seguridad Social: El Instituto de Seguridad Social que preste los servicios de seguridad social reconocidos en esta Ley a favor de los Miembros y de quienes forman parte de la Agencia Estatal de Investigación.\nXIV.- Ley: La Ley del Sistema Estatal de Seguridad Ciudadana del Estado de Baja\nCalifornia;\nXV.- Ley General: La Ley General del Sistema Nacional de Seguridad Pública;\nXVI.- Miembro: El o los elementos de las Instituciones Policiales que cuenten con nombramiento policial otorgado por autoridad competente;\nXVII.- Municipios: Los Municipios del Estado de Baja California;\nGobernador Constitucional del Estado de Baja California;\nXIX.- Programa: El Programa Estatal de Seguridad Ciudadana;\nLey del Sistema Estatal de Seguridad Ciudadana de Baja California. Página 4\n.\nActualización Legislativa.\nÚltima Reforma P.O. No. 54, Índice, 05-Sep-2025\nXX.- Programa Rector: El conjunto de contenidos encaminados a la profesionalización de los servidores públicos de las Instituciones Policiales y de la Agencia\nEstatal de Investigación, respectivamente;\nXXI.- Secretaría: La Secretaría de Seguridad Ciudadana del Estado de Baja\nCalifornia;\nXXII.- Secretariado Ejecutivo: El Secretariado Ejecutivo del Sistema Estatal de\nSeguridad Ciudadana;\nXXIII.- Sistema Estatal: El Sistema Estatal de Seguridad Ciudadana de Baja\nCalifornia;\nXXIV.- Sistema Nacional: El Sistema Nacional de Seguridad Pública;\nXXV.- Sistema Estatal de Información: El Sistema Estatal de Información sobre\nSeguridad Ciudadana;\nXXVI.- Separación definitiva: La terminación de la relación administrativa entre los\nMiembros y las Instituciones de Seguridad con motivo de la prestación de sus servicios por falta de requisitos de permanencia y por cualquiera otro de los casos previstos en esta Ley.\nArtículo Reformado\nTÍTULO SEGUNDO\nDEL SISTEMA ESTATAL DE SEGURIDAD CIUDADANA Y BASES DE\nCOORDINACIÓN\nDenominación Modificada\nCAPÍTULO I\nDISPOSICIONES GENERALES\nDenominación Modificada\nARTÍCULO 6.- El Sistema Estatal tendrá como instrumento rector el Programa y se conformará además con las políticas públicas, bases de coordinación, planes, servicios, programas, acciones, tecnología, bases de datos y sistemas de información, así como las en la presente Ley, el cual formará parte del Sistema Nacional y se conducirá en coordinación y de conformidad con las instancias, instrumentos, políticas, acciones y servicios previstos en la Ley General.\nEl desarrollo, ejecución o uso de los componentes del Sistema Estatal se realizará de manera conjunta, ordenada y sistémica, a través de las Instituciones de Seguridad, órganos de coordinación, municipios y ciudadanos en sus respectivos ámbitos de competencia y participación, responsables de articular y dar seguimiento a las estrategias para cumplir los alcances, fines y objetivos de la seguridad.\nLey del Sistema Estatal de Seguridad Ciudadana de Baja California. Página 5\n.\nActualización Legislativa.\nÚltima Reforma P.O. No. 54, Índice, 05-Sep-2025\nEl Consejo Estatal es el órgano colegiado rector del Sistema Estatal.\nArtículo Reformado\nARTÍCULO 7.- Son autoridades del Sistema Estatal:\nI.- El Poder Ejecutivo por conducto de la Secretaría de Seguridad Ciudadana y la\nComisión Estatal del Sistema Penitenciario;\nII.- La Fiscalía General del Estado de Baja California;\nIII. Los municipios;\nIV.- Las Instituciones Policiales del Estado y sus auxiliares, y\nV.- Las dependencias y entidades estatales y municipales, órganos autónomos y demás instituciones públicas que directa o indirectamente coadyuven en temas relacionados con la seguridad.\nArtículo Reformado\nARTÍCULO 8.- El Sistema Estatal tiene por objeto:\nI.- Contribuir al desarrollo y ejecución del Programa y el desarrollo de políticas públicas de prevención que brinden protección y seguridad a la ciudadanía frente a riesgos y amenazas;\nII.- Dar seguimiento a la incidencia delictiva, y tomar decisiones respecto de las acciones preventivas y correctivas en materia de seguridad en el Estado;\nIII.- Promover y elaborar acciones que fomenten la convivencia pacífica y solidaria, la cultura de la paz para la solución no violenta de conflictos;\nIV.- Proponer y desarrollar políticas de carácter integral en materia de prevención social de las violencias y el delito; las causas estructurales que generen la comisión de delitos y conductas antisociales, así como programas y acciones para fomentar en la protección de las víctimas de hechos violentos y el delito, y\nV.- Aquellos que determine la Ley General y el Sistema Nacional. participación organizada de la sociedad y sus niveles de actuación en la materia.\nArtículo Reformado\nLey del Sistema Estatal de Seguridad Ciudadana de Baja California. Página 6\n.\nActualización Legislativa.\nÚltima Reforma P.O. No. 54, Índice, 05-Sep-2025\nARTÍCULO 9.- Las Instituciones de Seguridad se regirán, para la debida coordinación en la implementación de sus acciones, bajo las bases siguientes:\nI.- Establecer políticas, programas y acciones complementarias de los distintos órdenes de gobierno en la materia que corresponda, de acuerdo a su competencia, a efecto de eficientizar la aplicación, destino e impacto de los recursos públicos;\nII.- Articular acciones interinstitucionales con las autoridades y auxiliares del Sistema\nEstatal, a fin de ampliar la cobertura de servicios, de atención a la ciudadanía y la interconexión de los aspectos tecnológicos;\nIII.- Propiciar la participación ciudadana;\nIV.- Garantizar el respeto a los derechos humanos y su protección con enfoque diferencial y perspectiva de género;\nV.- Salvaguardar y compartir la información sobre seguridad, que en el ámbito de su competencia o participación, deba formar parte del Sistema Estatal de Información, y\nVI.- Las demás que para el cumplimiento de los fines de la seguridad dispongan la\nLey General y la Ley General para la Prevención Social de la Violencia y Delincuencia; los acuerdos del Sistema Nacional y las disposiciones normativas en la materia.\nArtículo Reformado\nARTÍCULO 10.- La coordinación de las Instituciones de Seguridad a que se refiere esta Ley, comprende las acciones inherentes a la consecución de los fines de la seguridad, el desarrollo policial, la integración, uso y control de los registros del Sistema Estatal de\nInformación, así como las relativas a la evaluación y control de confianza que correspondan al ámbito de sus atribuciones, las cuales abarcan lo siguiente:\nI.- Suministro, intercambio y sistematización de todo tipo de información sobre seguridad;\nII.- Coordinación en la planeación y ejecución de programas y estrategias contra la comisión de hechos violentos y la realización de operativos policiales conjuntos;\nIII.- Realizar acciones y operativos conjuntos entre las Instituciones de Seguridad\nPública estatales y municipales, así como de otras entidades federativas y sus municipios;\nIV.- Coordinación y participación en la atención de incidentes de alto impacto derivados de actos delictivos, accidentes o desastres naturales, a través de las instancias y operatividad establecidas para tal efecto;\nV.- Verificar la debida aplicación de los lineamientos, procedimientos, protocolos y perfiles determinados por el Centro Nacional de Certificación y Acreditación, para los\nLey del Sistema Estatal de Seguridad Ciudadana de Baja California. Página 7\n.\nActualización Legislativa.\nÚltima Reforma P.O. No. 54, Índice, 05-Sep-2025 procedimientos de evaluación y control de confianza de los Miembros, Agentes del Ministerio\nPúblico, Peritos y elementos de apoyo;\nVI.- Intercambio académico y de experiencias para robustecer la formación profesional de los Miembros;\nVII.- Procedimientos de formación, reglas de ingreso, permanencia, promoción y retiro de los miembros;\nVIII.- Sistema disciplinario y de estímulos a los Miembros;\nIX.- Mecanismos y lineamientos conforme a los cuales las Instituciones Policiales y prestadores de servicio de seguridad privada, actuarán en coadyuvancia con las\nInstituciones de Seguridad;\nX.- Regulación, control y sanción de los prestadores de servicios de seguridad privada;\nXI.- Participación de las Instituciones Policiales del Estado y sus auxiliares, en la prestación del servicio de asistencia telefónica y en la atención y seguimiento de las denuncias anónimas de la población que prevé esta Ley, a través del Centro de Control, Comando, Comunicación, Cómputo, Calidad y de Contacto Ciudadano del Estado, y del\nCentro de Denuncia Anónima sin perjuicio de lo que las leyes y reglamentos señalen adicionalmente;\nXII.- Participación de la comunidad y fomento a la cultura de la prevención de delitos y de conductas cometidas por adolescentes tipificadas como delito por las leyes;\nXIII.- Coordinación en la planeación y ejecución de programas en materia de prevención de las violencias y delitos, y\nXIV.- Las demás que determine el Consejo Estatal para lograr los fines de seguridad.\nArtículo Reformado\nCAPÍTULO II\nDEL PROGRAMA ESTATAL DE SEGURIDAD CIUDADANA\nCapítulo Adicionado\nARTÍCULO 11.- El Programa constituye un instrumento del Sistema Estatal de deberán realizar las Instituciones de Seguridad, así como aquellas dependencias y entidades estatales y municipales, órganos autónomos y demás instituciones públicas que directa o indirectamente coadyuven en temas relacionados con la seguridad, en el corto, mediano y largo plazo. Su contenido deberá ser congruente con los programas y estrategias\nLey del Sistema Estatal de Seguridad Ciudadana de Baja California. Página 8\n.\nActualización Legislativa.\nÚltima Reforma P.O. No. 54, Índice, 05-Sep-2025 nacionales conforme al Sistema Nacional y cumplir con los objetivos y estrategias planteados en el Plan Estatal de Desarrollo.\nEl Programa tendrá carácter prioritario y su ejecución se ajustará a la disponibilidad presupuestal anual, así como a los lineamientos que sobre el particular dicte el Consejo\nEstatal.\nEn su elaboración se deberá contar con la participación de las Instituciones de\nSeguridad, el Consejo Ciudadano y de los Comités Ciudadanos Municipales de Seguridad\nCiudadana en el ámbito de sus respectivas competencias.\nArtículo Reformado\nARTÍCULO 12.- La aprobación del Programa corresponde a la persona titular del\nPoder Ejecutivo del Estado. El Programa deberá comprender como mínimo, los siguientes aspectos:\nI.- Justificación;\nII.- Diagnóstico de la situación que presenta la seguridad ciudadana en el Estado y municipios, así como su relación con el contexto nacional;\nIII.- Objetivos generales y específicos;\nIV.- Estrategias para el logro de sus objetivos;\nV.- Subprogramas específicos, así como las acciones y metas operativas correspondientes, incluyendo aquellas que sean objeto de coordinación con dependencias y organismos de la administración pública federal o con los gobiernos de otras entidades federativas y aquellas que requieran de concertación con los grupos sociales;\nVI.- Dependencias, órganos o unidades administrativas responsables de su ejecución;\nVII.- Metas;\nVIII.- Alineación con los instrumentos de planeación de la Entidad, así como con los establecidos por el Sistema Nacional;\nIX.- Los indicadores necesarios para el seguimiento y evaluación, y\nX.- Evaluación de acciones.\nArtículo Reformado\nARTÍCULO 13.- El Programa se revisará anualmente respecto al logro de sus objetivos.\nLey del Sistema Estatal de Seguridad Ciudadana de Baja California. Página 9\n.\nActualización Legislativa.\nÚltima Reforma P.O. No. 54, Índice, 05-Sep-2025\nEn la evaluación del cumplimiento del Programa se considerará la situación que guarda la seguridad en los ámbitos estatal y municipal al momento de su emisión, respecto del avance en el cumplimiento del mismo. El resumen de la evaluación se publicará en el\nPeriódico Oficial del Estado de Baja California.\nLas Instituciones de Seguridad darán amplia difusión al Programa destacando la manera en que la ciudadanía participará en el cumplimiento del mismo.\nEl Poder Ejecutivo del Estado, la Fiscalía General y los municipios informarán anualmente al Congreso del Estado los resultados y avances del Programa, y por separado de cualquier otro informe que legalmente deban rendir, sin perjuicio de la atribución que le asiste de recabar información sobre casos o materias concretas en los términos de Ley. El\nCongreso del Estado evaluará los avances y remitirá sus observaciones a dichas autoridades.\nArtículo Reformado\nCAPÍTULO III\nDEL CONSEJO ESTATAL DE SEGURIDAD CIUDADANA\nCapítulo Adicionado\nARTÍCULO 14.- El Consejo Estatal es la instancia para la coordinación de los tres órdenes de gobierno que tiene por finalidad principal la coordinación, planeación e implementación del Sistema Nacional en la Entidad, mediante la ejecución de las líneas de acción que establezca el Consejo Nacional.\nEl Consejo Estatal se coordinará por la persona titular de la Secretaría y estará integrado por:\nII.- La persona titular de la Secretaría de Seguridad Ciudadana;\nIII.- La persona titular del Secretariado Ejecutivo, quien fungirá como Secretario\nTécnico del Consejo Estatal;\nIV.- La persona titular de la Secretaría General de Gobierno;\nV.- La persona titular de la Fiscalía General;\nVI. La persona titular de la Comisión Estatal del Sistema Penitenciario;\nVII.- La persona titular de la Presidencia Municipal de cada Municipio del Estado;\nVIII.- Una representación de la Secretaría de la Defensa Nacional;\nLey del Sistema Estatal de Seguridad Ciudadana de Baja California. Página 10\n.\nActualización Legislativa.\nÚltima Reforma P.O. No. 54, Índice, 05-Sep-2025\nIX.- Una representación de la Secretaría de Marina;\nX.- Una representación de la Fiscalía General de la República, y\nXI.- Una representación de la Secretaría de Seguridad y Protección Ciudadana.\nLa persona titular de la Presidencia del Consejo Estatal será suplida en sus ausencias por la persona titular de la Secretaría.\nLas personas integrantes del Consejo Estatal deberán nombrar un suplente en caso de no poder asistir a las sesiones, quien contará al menos con la jerarquía inmediata inferior al titular que corresponda, debiendo autorizarlo mediante oficio previo a la reunión convocada.\nLa persona Titular de la Presidencia del Consejo Estatal invitará a participar permanentemente en las sesiones a las personas titulares de la Presidencia de la Comisión\nEstatal de los Derechos Humanos de Baja California; de la Presidencia de la Comisión del\nCongreso del Estado cuyas funciones se relacionen con la seguridad y de la Presidencia del\nConsejo Ciudadano, con derecho a voz pero sin voto.\nArtículo Reformado\nARTÍCULO 15.- El Consejo Estatal tendrá a su cargo los asuntos siguientes:\nI.- Proponer el contenido del Programa; los objetivos y las metas estatales en materia de seguridad, así como las políticas, estrategias y acciones necesarias para su cumplimiento;\nII.- Dar seguimiento y evaluar el cumplimiento de los objetivos y las metas estatales en materia de seguridad, así como de los acuerdos y las disposiciones emitidas por el\nConsejo Nacional;\nIII.- Proponer al Consejo Nacional y a las Conferencias que integran el Sistema\nNacional acuerdos, programas específicos y convenios sobre las materias de coordinación que establece la Ley General y esta Ley;\nIV.- Sugerir la elaboración de instrumentos de planeación en materia de seguridad y la definición de sus objetivos, indicadores, metas, estrategias, líneas de acción y de cualquier otra información que deban contener;\nV.- Emitir acuerdos para el mejoramiento de la organización y el funcionamiento del\nSistema Estatal o el desempeño de la seguridad en el Estado;\nVI.- Impulsar la efectiva coordinación entre las autoridades estatales en materia de seguridad y justicia;\nLey del Sistema Estatal de Seguridad Ciudadana de Baja California. Página 11\n.\nActualización Legislativa.\nÚltima Reforma P.O. No. 54, Índice, 05-Sep-2025\nVII.- Conformar mediante acuerdos las comisiones de trabajo que estime necesarias para el debido cumplimiento de sus funciones, conforme a las disposiciones que en los mismos se establezcan;\nVIII.- Fomentar la coordinación entre el Sistema Nacional y el Sistema Estatal, y formular propuestas de acuerdos o acciones específicas al Consejo Nacional o las conferencias nacionales;\nIX.- Efectuar en términos de la Ley General, propuestas para la conformación, la organización y el funcionamiento de instancias regionales o intermunicipales de coordinación, así como para la vinculación del Sistema Estatal con otros sistemas locales de seguridad;\nX.- Propiciar la participación ciudadana en el diseño, la implementación, el seguimiento y la evaluación de estrategias y acciones en materia de prevención de las violencias y del delito, así como del desempeño de las Instituciones de Seguridad;\nXI.- Designar a los Presidentes Municipales que conformarán la Conferencia Nacional de Seguridad Pública Municipal de conformidad con lo previsto en la Ley General, y\nXII.- Los demás que le asignen las leyes, el Consejo Nacional y Consejo Estatal, así como las que sean necesarias para promover en todo tiempo la efectiva coordinación y funcionamiento en materia de seguridad.\nArtículo Reformado\nARTÍCULO 16.- El Consejo Estatal sesionará de forma ordinaria, cuando menos cada tres meses y de forma extraordinaria cuantas veces se requiera, cuando quien lo preside, así lo determine.\nLos acuerdos del Consejo Estatal se tomarán con la aprobación de la mayoría de los integrantes presentes en la sesión correspondiente.\nEn caso de empate, el voto de calidad será otorgado por la persona titular de la\nPresidencia del Consejo Estatal. asistencia de la mitad más uno de los integrantes, y esté presente la persona titular del disposiciones normativas que resulten aplicables.\nArtículo Reformado\nARTÍCULO 17.- Corresponderá a la persona titular de la Presidencia del Consejo\nEstatal, las siguientes funciones:\nLey del Sistema Estatal de Seguridad Ciudadana de Baja California. Página 12\n.\nActualización Legislativa.\nÚltima Reforma P.O. No. 54, Índice, 05-Sep-2025\nI.- Convocar y conducir las sesiones del Consejo Estatal;\nII.- Proponer el orden del día de la sesión respectiva;\nIII.- Proponer la instalación de comisiones para evaluar políticas y acciones en materia de seguridad y designar a los responsables de las mismas;\nIV.- Promover, suscribir y vigilar el cumplimiento de los acuerdos, convenios y demás resoluciones del Consejo Estatal;\nV.- Coordinar acciones entre las policías estatales y municipales, y\nVI.- Las demás que le asignen las leyes y reglamentos, así como las que sean necesarias para promover en todo tiempo la efectiva coordinación y funcionamiento en materia de seguridad.\nArtículo Reformado\nCAPÍTULO IV\nDE LA SECRETARÍA DE SEGURIDAD CIUDADANA\nCapítulo Adicionado\nARTÍCULO 18.- La Secretaría es la dependencia de la administración pública estatal encargada de la preservación de la seguridad y convivencia ciudadana, de los espacios destinados al uso y disfrute público, así como de la prevención de las violencias y delitos, con la participación activa de la ciudadanía, la cual se regirá por lo dispuesto en esta Ley y demás ordenamientos aplicables.\nArtículo Reformado\nARTÍCULO 19.- Además de las atribuciones previstas en la Constitución Política del de Baja California, en materia de seguridad ciudadana, corresponden a la Secretaría, las siguientes:\nI.- Garantizar que los fines de la seguridad ciudadana se cumplan;\nII.- Proponer al Consejo Estatal las medidas necesarias para garantizar el adecuado funcionamiento del Sistema Estatal;\nIII.- Ejecutar y dar seguimiento a los acuerdos, resoluciones y bases de colaboración\nPresidencia del Consejo Estatal;\nIV.- Verificar que los programas, estrategias, acciones, políticas y servicios que se adopten por el Consejo Estatal, se coordinen entre sí, y que cumplan con los lineamientos y acuerdos generales que éste dicte;\nLey del Sistema Estatal de Seguridad Ciudadana de Baja California. Página 13\n.\nActualización Legislativa.\nÚltima Reforma P.O. No. 54, Índice, 05-Sep-2025\nV.- Promover las acciones de coordinación, colaboración y concertación necesarias entre las Instituciones de Seguridad y los ciudadanos para el cumplimiento de los fines del\nSistema Estatal;\nVI.- Presentar al Consejo Nacional los informes que den seguimiento a los acuerdos y resoluciones adoptados por dicho Consejo y sus Conferencias;\nVII.- Celebrar con la autorización de la persona titular del Poder Ejecutivo del Estado los convenios que resulten necesarios para el cumplimiento de sus atribuciones o fines del\nSistema Estatal;\nVIII.- Informar periódicamente al Consejo Estatal y a la persona titular del Poder\nEjecutivo del Estado de sus actividades;\nIX.- Publicar los informes de actividades del Consejo Estatal;\nX.- Conducir la operación policial de las Instituciones de Seguridad, respetando sus respectivos ámbitos de competencia, y de conformidad con las políticas y lineamientos del\nConsejo Estatal y el Programa;\nXI.- Desarrollar los procesos de selección de aspirantes, ingreso, permanencia, desarrollo, evaluación, certificación y promoción de los miembros, Elementos de Apoyo y personal operativo de los Prestadores de Servicios de Seguridad Privada a cargo de la\nSecretaría;\nXII.- Tramitar, administrar y controlar las acciones necesarias para la autorización y el correcto funcionamiento de la Licencia Oficial Colectiva respectiva para la portación de armas;\nXIII.- Implementar en caso de ser necesario y con independencia de que otras\nInstituciones de Seguridad desarrollen programas educativos para el cumplimiento de sus atribuciones, programas de nivel medio superior y superior en sus diferentes tipos y modalidades, ajustándose a lo dispuesto en la normatividad en la materia;\nXIV.- Gestionar ante las autoridades competentes, la ministración de los fondos de seguridad, de conformidad con los criterios aprobados por el Consejo Estatal y las demás disposiciones aplicables;\nXV.- Supervisar, en coordinación con las demás instancias competentes, la correcta aplicación de los recursos de los fondos por las Instituciones de Seguridad;\nXVI.- Presentar quejas o denuncias ante las autoridades competentes por el incumplimiento de la Ley, los acuerdos generales, los convenios y demás disposiciones\nLey del Sistema Estatal de Seguridad Ciudadana de Baja California. Página 14\n.\nActualización Legislativa.\nÚltima Reforma P.O. No. 54, Índice, 05-Sep-2025 aplicables, así como por el uso ilícito o indebido de los recursos a que se refiere el artículo\n142 de la Ley General;\nXVII.- Dictar los lineamientos para la coordinación de las Instituciones de Seguridad y las dependencias y entidades estatales y municipales, órganos autónomos y demás instituciones públicas que directa o indirectamente coadyuven en temas relacionados con la seguridad, a efecto de integrar el Sistema Estatal de Información;\nXVIII.- Disponer la ejecución de las medidas de seguridad necesarias a fin de proteger la vida de la población, sus bienes y el entorno, brindándoles oportuno y eficaz auxilio, en los casos previstos en la Ley General de Protección Civil y demás disposiciones aplicables;\nFracción Reformada\nXIX.- Procurar e impulsar la celebración de convenios de coordinación con la autoridad federal competente para realizar actividades de reparación de armamento de las instituciones policiales; y,\nFracción Adicionada, recorriéndose la subsecuente\nXX.- Las demás que para el cumplimiento de los fines de la seguridad dispongan la\nLey General, la Ley General para la Prevención Social de la Violencia y Delincuencia; los acuerdos del Sistema Nacional y las disposiciones normativas en la materia.\nArtículo Reformado\nCAPÍTULO V\nDEL SECRETARÍADO EJECUTIVO\nCapítulo Adicionado\nARTÍCULO 20.- El Secretariado Ejecutivo es un órgano desconcentrado dependiente de la Secretaría con autonomía técnica y de gestión, cuya función es el análisis de los fenómenos generadores de violencia, su comportamiento e incidencia, así como la proposición, seguimiento y evaluación de las estrategias a cargo de las Instituciones de\nSeguridad y sus resultados.\nArtículo Reformado\nARTÍCULO 21.- Corresponden al Secretariado Ejecutivo las siguientes atribuciones:\nI.- En materia de análisis y planeación: a.- Realizar estudios especializados sobre las materias de seguridad y formular recomendaciones a los órganos de coordinación, Instituciones de Seguridad, organismos privados y particulares, que forman parte del Sistema Estatal; b.- Analizar los fenómenos generadores de violencia, desde la perspectiva de su origen, comportamiento e incidencia y el riesgo o afectación que provocan a los derechos de las personas en materia de seguridad;\nLey del Sistema Estatal de Seguridad Ciudadana de Baja California. Página 15\n.\nActualización Legislativa.\nÚltima Reforma P.O. No. 54, Índice, 05-Sep-2025 c.- Impulsar mejoras para los instrumentos de información del Sistema Estatal de\nInformación; d.- Formular propuestas para los contenidos del Programa y el Programa Rector; e.- Promover la ejecución de las acciones conjuntas que se acuerden en el Consejo\nEstatal, de conformidad con las bases y reglas que emita el mismo y con respeto a las atribuciones de las instancias vinculadas; f.- Auxiliar a la persona titular del Consejo Estatal en la conducción de las sesiones y ejercer las funciones de Secretario Técnico del Consejo Estatal; g.- Elaborar los informes de actividades del Consejo; h.- Compilar los acuerdos que se tomen en el Consejo Estatal, llevar el archivo de éstos y de los instrumentos jurídicos que deriven, y expedir constancia de los mismos; i.- Verificar el cumplimiento de las disposiciones de esta Ley, los convenios generales y específicos en la materia, así como las demás disposiciones aplicables e informar lo conducente al Consejo Estatal; j.- Proponer al Consejo Estatal las políticas, lineamientos, protocolos y acciones para el buen desempeño de las Instituciones de Seguridad; k.- Proponer los criterios de evaluación de las Instituciones de Seguridad en los términos de la Ley; l.- Preparar la evaluación del cumplimiento de las políticas, estrategias y acciones del\nSistema Estatal en los términos de Ley; m.- Presentar un informe mensual del estado que guarda la seguridad en el Estado, que deberá contener cuando menos mapas de zonas de incidencia delictiva, los índices delictivos, los resultados de las acciones de prevención y del Programa a la persona\nPresidente del Consejo Estatal, y n.- Las demás que para el cumplimiento de los fines de la seguridad dispongan la Ley\nGeneral, la Ley General para la Prevención Social de la Violencia y Delincuencia; los acuerdos del Sistema Nacional y las disposiciones normativas en la materia.\nII.- Como Secretario Técnico del Consejo Estatal: a.- Proponer las disposiciones normativas que resulten necesarias para la operación y funcionamiento del Consejo Estatal.\nLey del Sistema Estatal de Seguridad Ciudadana de Baja California. Página 16\n.\nActualización Legislativa.\nÚltima Reforma P.O. No. 54, Índice, 05-Sep-2025 b.- Elaborar y certificar los acuerdos que se tomen en el Consejo Estatal, llevando su archivo y el de los instrumentos jurídicos que se generen en el seno del mismo; c.- Realizar las acciones necesarias para la debida ejecución y seguimiento de los acuerdos del Consejo Estatal e informar de lo conducente a la Secretaría; d.- Elaborar los informes de actividades que ordene el Consejo Estatal; e.- Solicitar la información que requiera el Consejo Estatal a las dependencias estatales y municipales; f.- Promover en todo tiempo el efectivo desarrollo de las sesiones del Consejo Estatal, g.- Las demás que le encomiende la persona titular de la Secretaría, de la Presidencia del Consejo Estatal y el propio Consejo Estatal, y que sean necesarias para cumplir las anteriores.\nArtículo Reformado\nCAPÍTULO VI\nDE LA OPERACIÓN POLICIAL, LAS INSTITUCIONES POLICIALES, LA AGENCIA\nESTATAL DE INVESTIGACIÓN Y SUS AUXILIARES\nCapítulo Adicionado\nARTÍCULO 22.- La operación policial es el conjunto de acciones coordinadas entre las Instituciones Policiales y la Agencia Estatal de Investigación para el cumplimiento de objetivos, programas y metas relacionados con los fines de la seguridad, con estricto apego a los derechos humanos, para preservar la libertad, el orden y la paz pública.\nLa persona titular del Poder Ejecutivo del Estado podrá asumir el mando en aquellos casos que juzgue como de fuerza mayor o alteración grave del orden público.\nLa operación policial de los miembros de las Instituciones Policiales y la Agencia\nEstatal de Investigación, atenderá a los principios establecidos en la Constitución Federal, la\nLey General, esta Ley y demás disposiciones legales y reglamentarias correspondientes para cumplir con sus funciones de prevención de hechos violentos, investigación del delito, reacción o custodia, asegurando la protección de los ciudadanos y el servicio a la comunidad.\nSobre el Uso de la Fuerza, conforme a los protocolos establecidos y el pleno respeto a los derechos humanos. Cualquier abuso será sancionado conforme a la legislación penal aplicable.\nArtículo Reformado\nLey del Sistema Estatal de Seguridad Ciudadana de Baja California. Página 17\n.\nActualización Legislativa.\nÚltima Reforma P.O. No. 54, Índice, 05-Sep-2025\nARTÍCULO 23.- Son Instituciones Policiales en el Estado, las siguientes:\nI.- La Fuerza Estatal de Seguridad Ciudadana;\nII.- La Fuerza Estatal de Seguridad y Custodia Penitenciaria;\nIII.- La Policía Municipal; y,\nIV.- Las demás que se constituyan con estricto apego a la Ley.\nLas Instituciones Policiales estarán facultadas para desarrollar las funciones establecidas en el artículo 77 de la Ley General, en términos de lo previsto en su último párrafo.\nLas Instituciones Policiales, de acuerdo a su ámbito competencial, y para la consecución del orden, la paz y tranquilidad públicos; desplegarán acciones de proximidad, comunicación y participación directa con los ciudadanos.\nArtículo Reformado\nARTÍCULO 24. Son auxiliares de las Instituciones Policiales y de la Agencia Estatal de Investigación en el Estado:\nI.- Los Cuerpos Operativos de la Dirección de Protección Civil del Estado y los\nÓrganos Municipales Encargados de la Materia de Protección Civil;\nII.- Los Cuerpos de Bomberos y Rescate;\nIII.- Los prestadores de servicios de seguridad privada y de similar naturaleza que operen o se instalen en el Estado;\nIV.- Los cuerpos de asistencia médica o de primeros auxilios, y\nV.- Las demás que se constituyan con estricto apego a la Ley.\nArtículo Reformado\nARTÍCULO 25.- La Agencia Estatal de Investigación es la Unidad Administrativa conducida por el Ministerio Público que ejerce funciones de policía de investigación, la cual de Baja California.\nArtículo Reformado\nCAPÍTULO VII\nDE LA EVALUACIÓN Y CONTROL DE CONFIANZA\nCapítulo Adicionado\nLey del Sistema Estatal de Seguridad Ciudadana de Baja California. Página 18\n.\nActualización Legislativa.\nÚltima Reforma P.O. No. 54, Índice, 05-Sep-2025\nARTÍCULO 26.- Las evaluaciones en los procesos de selección de aspirantes, ingreso, permanencia, desarrollo, evaluación, certificación y promoción de los miembros de la Agencia Estatal de Investigación, Agentes del Ministerio Público, Peritos y Elementos de\nApoyo, estará a cargo del Centro de Evaluación y Control de Confianza el cual se organizará y funcionará de conformidad con la Ley Orgánica de la Fiscalía General del Estado y el\nReglamento que al efecto se expida.\nTratándose de los procesos de selección de aspirantes, ingreso, permanencia, desarrollo, evaluación, certificación y promoción de los miembros de las Instituciones\nPoliciales, Elementos de Apoyo y personal operativo de los Prestadores de Servicios de\nSeguridad Privada a cargo de la Secretaría, las evaluaciones de estos se llevarán a cabo por la Unidad Administrativa que esta dependencia determine, lo anterior sin perjuicio de que se celebren con la Fiscalía General del Estado convenios de colaboración para tales fines.\nArtículo Reformado\nARTÍCULO 27.- Para la evaluación y control de confianza, se deberá observar lo siguiente:\nI.- Aplicar los procedimientos de evaluación y de control de confianza conforme a los criterios expedidos por el Centro Nacional de Certificación y Acreditación. En la aplicación de estos procedimientos, se deberán respetar los derechos humanos reconocidos en la\nConstitución Federal y en los tratados internacionales;\nII.- Proponer lineamientos para la verificación y control de certificación;\nIII.- Proponer los lineamientos para la aplicación de los exámenes médicos, toxicológicos, psicológicos, poligráficos, socioeconómicos y demás necesarios que se consideren de conformidad con la normatividad aplicable;\nIV.- Establecer un sistema de registro y control, que permita preservar la confidencialidad y resguardo de expedientes;\nV.- Verificar el cumplimiento de los perfiles médico, ético y de personalidad;\nVI.- Comprobar los niveles de escolaridad;\nVII.- Aplicar el procedimiento de certificación aprobado por el Centro Nacional de\nCertificación y Acreditación;\nVIII.- Expedir y actualizar los certificados conforme a los formatos autorizados por el\nCentro Nacional de Certificación y Acreditación;\nIX.- Informar a las autoridades competentes sobre los resultados de las evaluaciones que practiquen;\nLey del Sistema Estatal de Seguridad Ciudadana de Baja California. Página 19\n.\nActualización Legislativa.\nÚltima Reforma P.O. No. 54, Índice, 05-Sep-2025\nX.- Solicitar que se efectúe el seguimiento individual de los evaluados, en los que se identifiquen factores de riesgo que interfieran o pongan en riesgo el desempeño de sus funciones;\nXI.- Detectar áreas de oportunidad para establecer programas de prevención y atención que permitan solucionar la problemática identificada;\nXII.- Proporcionar a las Instituciones de Seguridad la asesoría y apoyo técnico que requieran sobre información de su competencia;\nXIII.- Proporcionar a las autoridades competentes la información contenida en los expedientes de los evaluados, que se requieran en procesos administrativos o judiciales, con las reservas previstas en las leyes aplicables;\nXIV.- Elaborar los informes de resultados para la aceptación o rechazo de los aspirantes;\nXV.- Proponer la celebración de convenios con otras Instituciones de Seguridad, así como otras autoridades, cuyos fines se relacionen con el desarrollo de los procesos de evaluación y control de confianza de su personal, y\nXVI.- Las demás que en el ámbito de su función, disponga la Ley General y los acuerdos del Sistema Nacional y las disposiciones normativas en la materia.\nEl Estado y los municipios implementarán medidas de registro y seguimiento para quienes sean separados del servicio por no obtener el certificado referido en esta Ley.\nArtículo Reformado\nCAPÍTULO VIII\nDEL INSTITUTO DE ESTUDIOS DE PREVENCIÓN Y FORMACIÓN\nINTERDISCIPLINARIA\nCapítulo Adicionado\nARTÍCULO 28.- El Instituto es una unidad administrativa de la Secretaría que tiene y de la Agencia Estatal de Investigación, de conformidad con el Programa Rector que establece la Ley General y esta Ley.\nAsimismo, promoverá, facilitará, desarrollará y coordinará la profesionalización de los adscritos a la misma.\nArtículo Reformado\nARTÍCULO 29.- El Instituto tendrá las funciones siguientes:\nLey del Sistema Estatal de Seguridad Ciudadana de Baja California. Página 20\n.\nActualización Legislativa.\nÚltima Reforma P.O. No. 54, Índice, 05-Sep-2025\nI.- Aplicar los procedimientos homologados del Sistema Nacional impulsando una doctrina policial civil en la que la formación y el desempeño de los integrantes de las\nInstituciones Policiales y la Agencia Estatal de Investigación del Estado se rijan por el servicio a la sociedad, la disciplina, el respeto a los derechos humanos, al imperio de la ley, al mando superior y, en lo conducente, a la perspectiva de género;\nII.- Capacitar en materia de investigación científica y técnica a los aspirantes y\nMiembros de las Instituciones Policiales de la Secretaría;\nIII.- Actualizar a los servidores públicos de la Secretaría respecto de las leyes, reglamentos, bandos y la normatividad vigente a la que se deban sujetar en su desempeño;\nIV.- Proponer y desarrollar los programas de investigación académica en materia policial, de conformidad con lo dispuesto en esta Ley y demás disposiciones aplicables;\nV.- Proponer los tipos y modalidades de los niveles de escolaridad para la profesionalización de los Miembros, así como a todo servidor público de las instituciones policiales;\nVI.- Promover y prestar servicios educativos;\nVII.- Aplicar las estrategias para la profesionalización de los Miembros de las\nInstituciones Policiales del Estado y de los servidores públicos de la Secretaría;\nVIII.- Proponer y aplicar los contenidos de los planes y programas para la profesionalización de los servidores públicos de la Secretaría a que se refiere el Programa\nRector;\nIX.- Garantizar la equivalencia de los contenidos mínimos de planes y programas de\nProfesionalización;\nX.- Revalidar y otorgar equivalencias de estudios de Profesionalización;\nXI.- Colaborar en el diseño y actualización de políticas y normas para el reclutamiento y selección de aspirantes y vigilar su aplicación;\nXII.- Realizar los estudios para detectar las necesidades de capacitación para los miembros de las Instituciones Policiales del Estado y servidores públicos de la Secretaría, proponiendo los cursos correspondientes para su formación, capacitación y profesionalización, con énfasis al respeto a los derechos humanos y su protección con enfoque diferencial y perspectiva de género. Dentro de los cursos se comprenderá la prestación de los primeros auxilios, para lo cual se deberá contar con el equipo necesario para tal efecto.\nPárrafo de la Fracción Reformado\nLey del Sistema Estatal de Seguridad Ciudadana de Baja California. Página 21\n.\nActualización Legislativa.\nÚltima Reforma P.O. No. 54, Índice, 05-Sep-2025\nDentro de los cursos se comprenderá la prestación de los primeros auxilios, para lo cual se deberá contar con el equipo necesario para tal efecto.\nFracción Reformada\nXIII.- Emitir las convocatorias para el ingreso al servicio de los Miembros de las\nInstituciones Policiales del Estado y de la Agencia Estatal de Investigación;\nXIV.- Tramitar los registros, autorizaciones y reconocimiento de los planes y programas de estudio ante las autoridades competentes;\nXV.- Expedir documentos de las actividades para la profesionalización que impartan;\nXVI.- Proponer la celebración de convenios con instituciones educativas nacionales y extranjeras, públicas y privadas, con objeto de brindar formación académica de excelencia, y\nXVII.- Las demás que establezcan las disposiciones legales aplicables.\nArtículo Reformado\nCAPÍTULO IX\nDEL CENTRO ESTATAL DE INTELIGENCIA PREVENTIVA\nArtículo Reformado\nARTÍCULO 30.- El Centro Estatal Inteligencia Preventiva es la unidad administrativa de la Secretaría encargada de llevar a cabo la inteligencia preventiva de las violencias y delitos, a través del análisis de la información contenida en el Sistema Estatal de\nInformación.\nArtículo Reformado\nARTÍCULO 31.- El Centro Estatal de Inteligencia Preventiva desarrollará las siguientes funciones:\nI.- Administrar y vigilar la integración del Sistema Estatal de Información y la debida operación de la plataforma tecnológica;\nII.- Supervisar el cumplimiento de las obligaciones de los entes que conforman el\nSistema Estatal de Información;\nIII.- Garantizar que se cumplan las disposiciones de la Ley General en materia de integración del Sistema Estatal de Información con el Sistema Nacional;\nIV.- Desarrollar acciones sistematizadas para planear, recopilar, analizar y aprovechar la información del Sistema Estatal de Información, para prevenir las violencias y delitos; sea\nGeneral;\nLey del Sistema Estatal de Seguridad Ciudadana de Baja California. Página 22\n.\nActualización Legislativa.\nÚltima Reforma P.O. No. 54, Índice, 05-Sep-2025\nV.- Realizar acciones de vigilancia, identificación, monitoreo y rastreo en la Red\nPública de Internet sobre sitios web con el fin de prevenir conductas delictivas y hechos violentos;\nVI.- Consolidar estrategias y mantener vínculos de inteligencia y cooperación en materia de información sobre seguridad ciudadana;\nVII.- Coordinar y ejecutar análisis de información para generar inteligencia operacional, que permita identificar a personas, grupos delictivos, con el fin de prevenir la comisión de delitos y hechos violentos;\nVIII.- Recabar información en lugares públicos para evitar el fenómeno delictivo o hechos de violencia, mediante la utilización de medios e instrumentos y cualquier herramienta que resulten necesarias con fines de inteligencia preventiva;\nIX.- Realizar procesos técnicos, tácticos o estratégicos de la información obtenida para la generación de inteligencia preventiva;\nX.- Efectuar la coordinación en los términos que señala el Sistema Nacional, con las autoridades de los tres órdenes de gobierno, para el intercambio de información contenida en documentos bases de datos o sistemas de información que sea útil al desempeño de sus funciones, sin menoscabo del cumplimiento de las limitaciones que establece el Código\nNacional de Procedimientos Penales y las demás disposiciones aplicables, y\nXI.- Las demás que en el ámbito de su función dispongan la Ley General y la Ley\nGeneral para la Prevención Social de la Violencia y Delincuencia; los acuerdos del Sistema\nNacional y las disposiciones normativas en la materia.\nArtículo Reformado\nTÍTULO TERCERO\nDE LA INTELIGENCIA PREVENTIVA Y EL SISTEMA ESTATAL DE INFORMACIÓN\nPARA LA SEGURIDAD CIUDADANA\nDenominación Modificada\nCAPÍTULO I\nDISPOSICIONES GENERALES\nDenominación Modificada\nARTÍCULO 32.- La inteligencia preventiva está encaminada a identificar y evitar la comisión de hechos violentos y delitos, a través de la recopilación, clasificación, registro, análisis, aprovechamiento y evaluación de datos e información del Sistema Estatal de\nInformación. su función de investigación para prevenir las violencias y delitos, será proporcionada al\nLey del Sistema Estatal de Seguridad Ciudadana de Baja California. Página 23\n.\nActualización Legislativa.\nÚltima Reforma P.O. No. 54, Índice, 05-Sep-2025\nSistema Estatal de Información mediante la plataforma tecnológica que al efecto se establezca.\nArtículo Reformado\nARTÍCULO 33.- El Sistema Estatal de Información se integra por los registros estatales previstos en esta Ley, así como por la información de actividades generadas por las Instituciones de Seguridad, dependencias y entidades estatales, municipales, órganos autónomos y demás instituciones públicas que directa o indirectamente coadyuven en temas relacionados con la seguridad con el fin de prevenir conductas delictivas y cualquier forma de violencia.\nEl Sistema Estatal de Información será dirigido por la Secretaría, a través del Centro\nEstatal de Inteligencia Preventiva, en coordinación con las disposiciones del Sistema\nNacional, la Ley General, la presente Ley y demás normatividad aplicable; por lo que dicha unidad administrativa deberá coordinarse con las autoridades e instancias necesarias para su conformación, utilización y actualización permanente.\nLos Municipios, los Prestadores de Servicios de Seguridad Privada, las Instituciones de Seguridad, así como aquellas dependencias y entidades estatales y municipales, órganos autónomos y demás instituciones públicas que directa o indirectamente coadyuven en temas relacionados con la seguridad, están obligados a proporcionar y mantener actualizada la información necesaria para integrar el Sistema Estatal de Información y el Sistema Nacional mediante los sistemas e instrumentos tecnológicos respectivos.\nEl incumplimiento a esta obligación por parte de las autoridades a que se refiere el párrafo anterior será sancionado conforme a la Ley de Responsabilidades Administrativas del Estado.\nArtículo Reformado\nARTÍCULO 34.- Para la debida operación de la plataforma tecnológica que sustenta el Sistema Estatal de Información, el Centro Estatal de Inteligencia Preventiva tendrá las siguientes funciones:\nI.- Establecer lineamientos para la funcionalidad, operación, respaldo, reconstrucción y seguridad de la información que integra el Sistema Estatal de Información;\nII.- Proponer acciones y mecanismos de coordinación entre las Instituciones de\nSeguridad, para el desarrollo tecnológico y soporte técnico;\nIII.- Realizar las acciones necesarias para garantizar a las Instituciones de Seguridad, las condiciones de acceso e interconexión al Sistema Estatal de Información;\nIV.- Proponer al Consejo Estatal los acuerdo relacionados con la planeación anual del desarrollo y modernización tecnológica, en los términos de la Ley General;\nLey del Sistema Estatal de Seguridad Ciudadana de Baja California. Página 24\n.\nActualización Legislativa.\nÚltima Reforma P.O. No. 54, Índice, 05-Sep-2025\nV.- Diseñar, implementar y evaluar los programas de capacitación de los sistemas de la plataforma tecnológica;\nVI.- Evaluar la calidad del servicio de la plataforma tecnológica y emitir, en su caso, las recomendaciones pertinentes, y\nVII.- Las demás que en el ámbito de su función dispongan la Ley General, la Ley\nGeneral para la Prevención Social de la Violencia y Delincuencia; los acuerdos del Sistema\nNacional y las disposiciones normativas en la materia.\nArtículo Reformado\nARTÍCULO 35.- La Secretaría establecerá los lineamientos para que las Instituciones de Seguridad puedan tener acceso a la plataforma tecnológica de acuerdo a su perfil o competencia, así como certificar y reproducir cualquier información impresa o digital que se genere a partir de la base de datos con la que cuenta éste, vigilando siempre la confidencialidad, reserva de la información y demás disposiciones aplicables.\nLas Instituciones de Seguridad tendrán acceso ilimitado a la información que generen y requieran conforme a sus atribuciones. En el caso de que alguna requiera información diversa o adicional a su competencia, deberá solicitarlo a la Secretaría, a través del Centro\nEstatal de Inteligencia Preventiva.\nArtículo Reformado\nARTÍCULO 36.- La utilización del Sistema Estatal de Información se regirá en términos de la Ley General de Transparencia y Acceso a la Información Pública y Ley\nGeneral de Protección de Datos Personales en Posesión de Sujetos Obligados y demás disposiciones aplicables leyes de la materia.\nLa información de interés público o que ponga en riesgo la seguridad o los derechos de seguridad ciudadana de las personas, será clasificada como reservada.\nSin perjuicio de lo anterior, el uso indebido del Sistema Estatal de Información será sancionado con base a lo dispuesto en la presente Ley, sin perjuicio de las responsabilidades de otra naturaleza en que se pudiera incurrir.\nArtículo Reformado\nCAPÍTULO II\nCapítulo Adicionada\nARTÍCULO 37.- Los integrantes del Sistema Estatal conformarán la Red Estatal de\nComunicaciones de Seguridad, como una herramienta de comunicación que les permita intercambiar, suministrar y sistematizar los datos que se generen diariamente en el ámbito de sus respectivas competencias, mediante los sistemas e instrumentos tecnológicos respectivos, cuyos registros comprenderán lo establecido por esta Ley y las disposiciones aplicables. Dicha Red Estatal de Comunicaciones tendrá como finalidad:\nLey del Sistema Estatal de Seguridad Ciudadana de Baja California. Página 25\n.\nActualización Legislativa.\nÚltima Reforma P.O. No. 54, Índice, 05-Sep-2025\nI.- Realizar la comunicación efectiva entre las Instituciones de Seguridad;\nII.- Supervisar y garantizar la interconexión de los aspectos tecnológicos de la plataforma;\nIII.- Generar la planeación y ejecución de estrategias preventivas;\nIV.- Profesionalizar la toma de decisiones en materia de seguridad;\nV.- Mejorar la capacidad de respuesta ante situaciones de riesgo;\nVI.- Generar indicadores confiables que apoyen el desarrollo de diagnósticos, la identificación de tendencias y la creación de escenarios para la planeación de las políticas de seguridad;\nVII.- Difundir de acuerdo a las condiciones y restricciones que establezcan las disposiciones jurídicas aplicables, las tendencias y resultados que arroje el propio Sistema\nEstatal de Información, a través de reportes y publicaciones oficiales que informen a la sociedad y hagan visible la gestión de los organismos públicos y privados relacionados con la seguridad;\nVIII.- Coadyuvar en la coordinación interinstitucional de las autoridades en materia de seguridad, y\nIX.- Auxiliar en la prevención de cualquier forma de violencia y conductas delictivas.\nLa Secretaría adoptará las medidas pertinentes a efecto de instalar, actualizar y mantener una infraestructura tecnológica moderna y sofisticada que permita el procesamiento útil y ágil del suministro, intercambio y sistematización de la información a que se refiere este ordenamiento.\nArtículo Reformado\nARTÍCULO 38.- EL Centro Estatal de Inteligencia Preventiva tendrá acceso a la Red\nEstatal de Comunicaciones de Seguridad, para el intercambio de la información que integra el Sistema Estatal de Información, al cual deberán estar enlazadas las Instituciones de\nSeguridad y aquellas con carácter de auxiliar previstos en la presente Ley, así como otras servicio de asistencia telefónica y en general los servicios de seguridad en el Estado.\nArtículo Reformado\nARTÍCULO 39.- La Secretaría, en coordinación con el Sistema Nacional, establecerá los criterios para la utilización en el Estado, de las frecuencias de radiocomunicación\nInstituciones Policiales en el Estado y la Agencia Estatal de Investigación.\nLey del Sistema Estatal de Seguridad Ciudadana de Baja California. Página 26\n.\nActualización Legislativa.\nÚltima Reforma P.O. No. 54, Índice, 05-Sep-2025\nAsimismo, la Secretaría en conjunto con la Federación, los municipios y las diversas\nInstituciones de Seguridad, realizará los trabajos necesarios con el fin de lograr la compatibilidad de los servicios de su red pública de telecomunicaciones local, con el Sistema\nNacional de Información, en términos de lo previsto en la Ley General.\nEl servicio de llamadas de emergencia y el servicio de denuncia anónima operarán con un número único de atención a la ciudadanía, respectivamente. La Secretaría adoptará las medidas necesarias para la operación e interconexión de estos servicios con el Sistema\nEstatal de Información y el Sistema Nacional de Información.\nArtículo Reformado\nARTÍCULO 40.- La Red Estatal de Comunicaciones de Seguridad contará con un sistema de video vigilancia encaminado a auxiliar a las Instituciones de Seguridad en vialidades y puntos estratégicos, cuyo objetivo primordial es mejorar la vigilancia y seguridad apoyado en una red de cámaras que permitan identificar, detectar y reportar los eventos de emergencia, actos vandálicos o delincuencia en el instante de su comisión.\nArtículo Reformado\nCAPÍTULO III\nDE LOS REGISTROS ESTATALES DE INFORMACIÓN\nCapítulo Adicionado\nARTÍCULO 41.- El Sistema Estatal de Información contará con registros estatales que serán conformados por la información resultado de la gestión operativa y de trámite de las\nInstituciones de Seguridad, los cuales deberán ser utilizados exclusivamente para la consecución de los objetivos previstos esta Ley, integrándose por lo menos, con los siguientes registros:\nI.- Del personal adscrito a las Instituciones de Seguridad, Fiscalía General, Instituciones de Seguridad de los municipios, así como el personal a que se refiere el\nReglamento que regula la prestación de servicios de seguridad privada en el Estado;\nII.- Del armamento, vehículos y equipo de las Instituciones de Seguridad, de la\nFiscalía General y prestadores de servicios de seguridad privada;\nIII.- Del padrón vehicular y de licencias de conducir;\nIV.- De los imputados, acusados y sentenciados;\nV.- De los Registros Administrativos de las Detenciones;\nVI.- De los Informes Policiales Homologados;\nLey del Sistema Estatal de Seguridad Ciudadana de Baja California. Página 27\n.\nActualización Legislativa.\nÚltima Reforma P.O. No. 54, Índice, 05-Sep-2025\nVII.- De los mandamientos administrativos o judiciales, mismos que se integrarán por órdenes de comparecencia, aprehensión, reaprehensión, presentación ejecutadas y pendientes de ejecutar, y medidas u órdenes de protección;\nFracción Reformada\nVIII.- Del registro de voz de los Miembros, del personal que prevé el Reglamento que regula la prestación de servicios de seguridad privada para el Estado, y de los imputados, acusados y sentenciados;\nIX.- Del tipo sanguíneo y de ácido desoxirribonucleico (ADN) del personal de las\nInstituciones de Seguridad, así como de personas se sentenciadas, detenidas e identificadas administrativamente;\nX.- De huellas dactilares;\nXI.- Del mapa de zonas de incidencia delictiva;\nXII.- Del padrón inmobiliario;\nXIII.- De vehículos robados, recuperados, asegurados y decomisados;\nXIV.- De la estadística;\nXV.- De los antecedentes penales;\nXVI.- De agentes generadores de violencia y condiciones criminógenas, reincidencia, o cualquier otra causa o factor que favorezca o genere violencia y delincuencia, en términos de la Ley para la Prevención Social de la Violencia y la Delincuencia del Estado de Baja\nCalifornia, y\nXVII.- Los demás registros que se constituyan en términos de la Ley General.\nArtículo Reformado\nSECCIÓN PRIMERA\nDEL PERSONAL, ARMAMENTO, VEHÍCULOS Y EQUIPOS DE COMUNICACIÓN\nSección Adicionada\nARTÍCULO 42.- Las Instituciones de Seguridad y los Prestadores de Servicios de\nSeguridad Privada, proporcionarán la información del personal que tengan adscrito, independientemente de la función que desempeñen. Dicha información deberá contener por lo menos:\nI.- Las altas y bajas;\nLey del Sistema Estatal de Seguridad Ciudadana de Baja California. Página 28\n.\nActualización Legislativa.\nÚltima Reforma P.O. No. 54, Índice, 05-Sep-2025\nII.- Los datos generales que permitan identificar plenamente y localizar al servidor público o prestador del servicio;\nIII.- Las huellas digitales, fotografías de frente y perfiles, registro de voz y tipo sanguíneo;\nIV.- Escolaridad y antecedentes laborales o administrativos;\nV.- Trayectoria en los servicios desempeñados de seguridad o en la prestación de servicios de seguridad privada, las promociones, reconocimientos o sanciones a que se haya hecho acreedor el servidor público o prestador de servicios privados;\nVI.- Descripción del equipo a su encargo, en su caso, casquillo y proyectil del arma de fuego que porte;\nVII.- Cualquier cambio de adscripción, actividad o rango de servidor público, así como las razones que lo motivaron;\nVIII.- La información relativa a cualquier auto de procesamiento, sentencia, sanción administrativa o resolución que modifique, confirme o revoque dichos actos, que se dicte respecto de Miembros, elementos de apoyo o servidores públicos de las Instituciones de\nSeguridad, o al personal de los prestadores de servicios de seguridad privada, la cual se notificará inmediatamente a la Institución de Seguridad según corresponda, y\nIX.- Las órdenes de aprehensión, de reaprehensión, de comparecencia, de presentación o arresto administrativo, las cuales se notificarán cuando no se ponga en riesgo la investigación o la causa procesal.\nArtículo Reformado\nARTÍCULO 43.- Los titulares de las Instituciones Policiales y los Prestadores de\nServicios de Seguridad Privada deberán registrar y mantener actualizados los datos relativos a sus integrantes, en los términos de la presente Ley y su Reglamento.\nPara garantizar la efectividad en las actividades de seguridad, previo al ingreso a\nPrivada, es obligación de sus titulares o responsables consultar el Sistema Estatal de\nInformación. Las personas aspirantes deberán de presentarse ante la Secretaría para la consulta e identificación correspondiente. Con los resultados de dicha consulta, la autoridad o prestador de servicios procederá de conformidad con las normas aplicables en la materia.\nArtículo Reformado\nARTÍCULO 44.- Las identificaciones de los Miembros, Agentes del Ministerio Público, Peritos, elementos de apoyo y el personal operativo de los prestadores de servicios de seguridad privada, deberán contener al menos nombre, cargo, fotografía, huella digital y\nLey del Sistema Estatal de Seguridad Ciudadana de Baja California. Página 29\n.\nActualización Legislativa.\nÚltima Reforma P.O. No. 54, Índice, 05-Sep-2025 clave de inscripción en el Registro Nacional de Personal de Seguridad Pública, así como las medidas de seguridad que garanticen su autenticidad.\nTodo servidor público tiene la obligación de identificarse salvo los casos de excepción que prevean los ordenamientos que se expidan al efecto, a fin de que el ciudadano se cerciore de que cuenta con el registro correspondiente.\nArtículo Reformado\nARTÍCULO 45.- Además de cumplir con lo dispuesto en otras leyes, las Instituciones de Seguridad, así como los prestadores de servicios de seguridad privada y otros auxiliares, deberán informar:\nI.- Los vehículos que tuvieren asignados con el número de matrícula, las placas de circulación, la marca, modelo, tipo, número de serie y motor;\nII.- Las armas y municiones que les hayan sido autorizadas por las autoridades competentes, aportando el número de registro, la marca, modelo, calibre, matrícula, huella balística y demás elementos de identificación;\nIII.- Previo a la entrega de las armas a las Instituciones de Seguridad, la Secretaría tendrá la obligación de recabar por lo menos los datos generales del arma, fotografías y recolección de elementos testigo, y\nIV.- Los equipos de comunicación que les hayan sido autorizados por las autoridades competentes, aportando en su caso el número de registro, la marca, modelo, en su caso el nombre del funcionario o servidor público a quien se le hubiere asignado, y demás elementos para su identificación.\nArtículo Reformado\nARTÍCULO 46.- Cualquier persona que ejerza funciones de seguridad, sólo podrá portar las armas de cargo que hayan sido autorizadas individualmente, o que hubiesen sido asignadas y registradas colectivamente para la Institución de Seguridad Ciudadana a que pertenezcan y para la Fiscalía General, de conformidad con la Ley de la materia. Las armas\nInstitución. El incumplimiento a la presente disposición, será sancionado conforme a las disposiciones legales aplicables.\nLas Instituciones de Seguridad, en el caso de que aseguren armas, municiones o vehículos, lo comunicarán de inmediato a la Secretaría, señalando los datos de identificación de los mismos.\n[Asimismo, los miembros que ejerzan funciones de seguridad podrán portar su arma de fuego estando fuera del servicio, siempre que lo soliciten a la persona titular de la institución de seguridad del Estado y se cumplan con los siguientes requisitos:\nLey del Sistema Estatal de Seguridad Ciudadana de Baja California. Página 30\n.\nActualización Legislativa.\nÚltima Reforma P.O. No. 54, Índice, 05-Sep-2025\nI.- Realizar solicitud por escrito ante la persona titular de la institución de seguridad a la que pertenezca donde se justifique los motivos para portar su arma de fuego fuera de servicio.\nII.- Someterse a la evaluación de control de confianza correspondiente.\nIII.- No estar sujeto o vinculado a proceso penal, o haber sido condenado por delito doloso.\nIV.- No estar suspendido ni haber sido destituido o inhabilitado por causa grave mediante resolución firme como servidor público, en términos de las normas aplicables.\nV.- No contar con denuncias por violencia familiar.\nVI.- Que la licencia colectiva correspondiente así lo permita.]\nPárrafo Adicionado junto con las Fracciones que lo integran\nQueda invalidado este Párrafo tercero junto con sus fracciones que lo integran por Sentencia dictada en la\nControversia Constitucional 505/2023\nArtículo Reformado\nARTÍCULO 47.- Los prestadores de servicios de seguridad privada y otros auxiliares, además de aportar los datos relativos del Sistema Estatal de Información, deberán presentar en forma mensual a la Secretaría, un reporte detallado de la información a que se refiere el presente capítulo. El incumplimiento a esta disposición será sancionado conforme a los ordenamientos legales aplicables.\nArtículo Reformado\nARTÍCULO 48.- La Secretaría de Hacienda del Estado deberá proporcionar los datos actualizados de manera permanente del Padrón Estatal Vehicular y de licencias de conducir, para integrar el Sistema Estatal de Información.\nArtículo Reformado\nSECCIÓN SEGUNDA\nDEL REGISTRO DE DETENCIONES E INFORME POLICIAL HOMOLOGADO\nSección Adicionada\nARTÍCULO 49.- Los Miembros que realicen detenciones deberán dar aviso\nHomologado, a fin de conformar el Registro Administrativo de Detenciones, de conformidad\nDetenciones.\nLey Nacional del Registro de Detenciones. Asimismo, señalará el modo en que se hizo del conocimiento de la persona detenida, los derechos constitucionales y legales que le asisten.\nArtículo Reformado\nLey del Sistema Estatal de Seguridad Ciudadana de Baja California. Página 31\n.\nActualización Legislativa.\nÚltima Reforma P.O. No. 54, Índice, 05-Sep-2025\nARTÍCULO 50.- Los Miembros están obligados a llenar un Informe Policial homologado, el cual contendrá la siguiente información:\nI.- El área que lo emite;\nII.- El usuario capturista;\nIII.- Los datos generales de registro;\nIV.- Motivo, que se clasifica en: a.- Tipo de evento, y b.- Subtipo de evento.\nV.- La ubicación del evento y en su caso, los caminos;\nVI.- La descripción de hechos, que deberá detallar modo, tiempo y lugar, entre otros datos;\nVII.- Entrevistas realizadas, y\nVIII.- En caso de detenciones: a.- Señalar los motivos de la detención; b.- Descripción de la persona; c.- El nombre del detenido y apodo, en su caso; d.- Descripción de estado físico aparente; e.- Idioma en el que habla, y modo en que le fueron hechos saber los derechos constitucionales y legales que le asisten; f.- Objetos que le fueron encontrados; g.- Autoridad a la que fue puesto a disposición; h.- Lugar en el que fue puesto a disposición.\nEl informe debe ser completo, los hechos deben describirse con continuidad, cronológicamente y resaltando lo importante; no deberá contener afirmaciones sin el soporte\nLey del Sistema Estatal de Seguridad Ciudadana de Baja California. Página 32\n.\nActualización Legislativa.\nÚltima Reforma P.O. No. 54, Índice, 05-Sep-2025 de datos o hechos reales, por lo que deberá evitar información de oídas, conjeturas o conclusiones ajenas a la investigación.\nArtículo Reformado\nSECCIÓN TERCERA\nDEL REGISTRO E IDENTIFICACIÓN DE PERSONAS Y GENERADORES DE VIOLENCIA\nSección Adicionada\nARTÍCULO 51.- En los términos de la Ley General se integrará la información estatal de datos al Sistema Nacional de Información, sobre personas vinculadas con hechos violentos, probables responsables de delitos, indiciadas, imputadas, detenidas, procesadas, sentenciadas e identificadas administrativamente, y en su caso, el estado que guarda el proceso penal, de consulta obligatoria en las actividades de seguridad, donde se incluyen sus características criminales, medios de identificación, recursos y modos de operación.\nEsta base de datos se integrará dentro del Sistema Nacional de Información, la cual se actualizará permanentemente y se conformará con la información que ingresen y aporten las Instituciones de Seguridad.\nTales datos deberán ser capturados en los registros del Sistema Nacional de\nInformación que para tal efecto establezca el Sistema Nacional debiendo informar de manera mensual a la Secretaría las actividades realizadas al respecto.\nEl Sistema Estatal de Información también contará con información penitenciaria, la cual es la base de datos que contiene, administra y controla los registros de la población penitenciaria del Estado, cumpliendo al efecto las disposiciones de la Ley General y la Ley\nNacional de Ejecución Penal.\nLa base de datos deberá contar, al menos, con el reporte de la ficha de identificación personal de cada interno con fotografía, evaluaciones de riesgo objetivo y razonable, datos de los procesos penales y demás información necesaria para la integración de dicho sistema.\nArtículo Reformado\nSECCIÓN CUARTA\nLIBERTAD\nSección Adicionada\nARTÍCULO 52.- La Fiscalía General integrará una base de datos con las medidas relativas a mandamientos administrativos y judiciales, que contenga la información de las órdenes de aprehensión, reaprehensión, comparecencia, de presentaciones y de protección giradas por la autoridad competente, misma que será integrada al Sistema Estatal de\nInformación y contendrá por lo menos:\nI.- Datos de la instancia ejecutora;\nLey del Sistema Estatal de Seguridad Ciudadana de Baja California. Página 33\n.\nActualización Legislativa.\nÚltima Reforma P.O. No. 54, Índice, 05-Sep-2025\nII.- Datos generales que permitan identificar a la persona;\nIII.- Datos del mandato;\nIV.- Datos de la autoridad que emite el mandamiento;\nV.- Datos del amparo, en su caso;\nVI.- Datos del delito;\nVII.- Otros nombres del presunto responsable o responsables;\nVIII.- Domicilio conocido;\nIX.- Otro mandamiento relacionado o relacionados, y\nX.- La demás información que establezca el Sistema Nacional.\nFracción Reformada\nLa información a que se refiere este artículo deberá actualizarse de manera permanente, y será obligación tenerla disponible para su consulta.\nArtículo Reformado\nSECCIÓN QUINTA\nDEL MAPA DE ZONAS DE INCIDENCIA DELICTIVA Y DEL PADRÓN INMOBILIARIO\nSección Adicionada\nARTÍCULO 53.- La Secretaría realizará mapas de zonas de incidencia delictiva con el propósito facilitar una base de información que favorezca la visualización y análisis de la violencia en el territorio del Estado, a efecto de contribuir a las políticas de prevención social de las violencias y las delincuencias. digitales e interactivos donde se muestren datos, cifras e indicadores que permitan describir determinado, incluyendo su referencia espacial, temporal y su evolución.\nLa Secretaría emitirá los lineamientos relativos a los instrumentos, criterios y georreferencia de la incidencia criminal y de cualquier forma de violencia, su volumen, extensión e impacto social, y que permita comprender la problemática de seguridad pública en el Estado.\nLey del Sistema Estatal de Seguridad Ciudadana de Baja California. Página 34\n.\nActualización Legislativa.\nÚltima Reforma P.O. No. 54, Índice, 05-Sep-2025\nLas Instituciones de Seguridad y demás instancias auxiliares, quedan obligadas a proporcionar la información obtenida de la zona donde realicen las funciones que les competan, necesaria para georreferenciar y comprender el fenómeno delictivo y sus consecuencias.\nArtículo Reformado\nARTÍCULO 54.- Los mapas de zonas de incidencias delictivas tienen como propósito:\nI.- Identificar la ubicación geográfica de las conductas delictivas y de cualquier forma violencia, describiendo las horas, días y meses de ocurrencia de los mismos;\nII.- Analizar lugares de mayor concentración delincuencial, referidos tanto a la comisión del delito como a sus agentes;\nIII.- Identificar zonas de alto riesgo;\nIV.- Diseñar estrategias para la intervención policial;\nV.- Asociar factores criminógenos detonantes de la problemática delictiva;\nVI.- Detectar los desplazamientos delincuenciales, referidos tanto a la comisión del delito como a sus agentes;\nVII.- Focalizar la aplicación de programas de prevención del delito y formas de violencia;\nVIII.- Evidenciar la estacionalidad del delito;\nIX.- Generar indicadores que faciliten la planeación estratégica y la toma de decisiones, y\nX.- Graficar la información que se genera con la realización de estudios o encuestas de victimización.\nArtículo Reformado\nARTÍCULO 55.- El padrón inmobiliario se conformará de la relación de de delitos o infracciones en el Estado, en los términos siguientes:\nI.- La Secretaría estará obligada a conformar, administrar y mantener actualizado la relación de arrendamientos en el Estado, con el objeto de contar con una base de datos, que sea de apoyo a Instituciones de Seguridad; así como a las autoridades judiciales.\nLey del Sistema Estatal de Seguridad Ciudadana de Baja California. Página 35\n.\nActualización Legislativa.\nÚltima Reforma P.O. No. 54, Índice, 05-Sep-2025\nLas personas que deberán proporcionar la información en los términos de la presente\nLey, son el propietario del inmueble o quien se ostente como tal; el poseedor debidamente reconocido, y el apoderado legal con facultades para disponer del arrendamiento del bien inmueble.\nEl padrón de arrendamientos deberá contener por lo menos: a.- Nombre del o los arrendadores; b.- Nombre del o los arrendatarios y en caso de intervenir, nombre del fiador, garante, deudor solidario; c.- Identificación oficial de los contratantes a que se refiere los incisos anteriores; d.- Copia del Contrato de Arrendamiento; e.- En su caso la información relativa a la localización y tipo de inmueble, y f.- En su caso copia del poder notarial del apoderado legal con facultades para disponer del arrendamiento del bien inmueble.\nII.- Los municipios están obligados a conformar y a mantener un inventario de construcciones que se encuentren en estado de abandono que puedan ser utilizados por terceras personas para ejecutar actividades que puedan ser constitutivas de delitos o infracciones.\nLos municipios deberán proporcionar la información de dicho inventario a la\nSecretaría a efecto de integrar el Sistema Estatal de Información.\nEl inventario de construcciones tendrá cuando menos los datos siguientes: a.- Dirección del inmueble; b.- Nombre del propietario o posesionario; c.- Ilícitos en que es empleado el inmueble, y d.- Medidas y colindancias.\nArtículo Reformado\nSECCIÓN SEXTA\nDE LOS BIENES ROBADOS Y RECUPERADOS\nSección Adicionada\nARTÍCULO 56.- La Fiscalía General establecerá una base de datos sobre bienes robados y recuperados, la cual deberá actualizarse permanentemente, misma que será integrada al Sistema Estatal Información y contendrá al menos lo siguiente:\nI.- NUC o Averiguación previa;\nII.- Modalidad del robo;\nIII.- Lugar del robo;\nLey del Sistema Estatal de Seguridad Ciudadana de Baja California. Página 36\n.\nActualización Legislativa.\nÚltima Reforma P.O. No. 54, Índice, 05-Sep-2025\nIV.- Denunciante;\nV.- Datos del bien;\nVI.- Características del bien;\nVII.- Recuperación del bien;\nVIII.- Lugar de depósito;\nIX.- La demás información que establezca el Sistema Nacional.\nEl Centro de Control, Comando, Comunicación, Cómputo, Calidad y Contacto\nCiudadano en el Estado contará con acceso a esta base de datos cuando se requiera.\nLa Fiscalía General a través de las llamadas que se reciban, con motivo del robo de un bien, formará de inmediato un reporte de incidente, mismo que servirá como alerta a las distintas Instituciones Policiales y a la Agencia Estatal de Investigación. Esta medida preliminar, no releva al afectado en su obligación de presentar su denuncia ante la autoridad competente.\nPárrafo Reformado\nArtículo Reformado\nSECCIÓN SÉPTIMA\nDE LA ESTADÍSTICA\nARTÍCULO 57.- La Secretaría integrará y administrará la información estatal sobre la incidencia criminológica, por lo que deberá de coordinarse con las Instituciones de\nSeguridad e instancias necesarias para su conformación, utilización y actualización permanente.\nLas Instituciones de Seguridad están obligadas a proporcionar y mantener actualizada la información sobre la incidencia criminológica, necesaria para integrar al Sistema Estatal de Información. de seguridad preventiva, procuración y administración de justicia, reinserción social, sistemas de prisión preventiva, ejecución de sentencias y de adolescentes en conflicto con la\nLey, y los factores asociados a la problemática de seguridad.\nArtículo Reformado\nTÍTULO CUARTO\nDEL SISTEMA ESTATAL PENITENCIARIO\nLey del Sistema Estatal de Seguridad Ciudadana de Baja California. Página 37\n.\nActualización Legislativa.\nÚltima Reforma P.O. No. 54, Índice, 05-Sep-2025\nCAPÍTULO ÚNICO\nDE LA EJECUCIÓN DE PENAS, MEDIDAS DE SANCIÓN Y MEDIDAS JUDICIALES\nARTÍCULO 58.- La ejecución material de las penas, medidas de seguridad y medidas de sanción previstas en las leyes penales, así como la administración y operación del\nSistema Estatal Penitenciario, se desarrollará conforme a lo dispuesto en la Ley Nacional de\nEjecución Penal y la Ley Nacional del Sistema Integral de Justicia para Adolescentes, formarán parte de las políticas y estrategias del Estado en materia de seguridad ciudadana.\nLa administración y operación de los programas de reinserción social en los centros de reinserción social y de internamiento para Adolescentes en el Estado, buscarán fortalecer las capacidades de las personas sujetas a la ejecución de penas y medidas de seguridad, mediante el respeto a los derechos humanos, el trabajo, la capacitación para el mismo, la educación, la salud, la cultura y el deporte, con el objeto de restituirles los derechos restringidos, procurando que no vuelvan a delinquir y fomentar en ellos una actitud de responsabilidad social.\nEl Sistema Penitenciario Estatal como parte integrante del Sistema Estatal se encaminará a asegurar oportunidades suficientes y adecuadas para la reinserción social a las personas privadas de su libertad y de los adolescentes, a través de los siguientes objetivos:\nI.- Proveer los servicios de reinserción social de las personas privadas de su libertad con el objeto de la restitución del pleno ejercicio de sus derechos tras el cumplimiento de una sanción o medida;\nII.- Promover un proceso de reintegración suficiente y adecuado para los adolescentes en conflicto con la ley;\nIII.- Garantizar la gobernabilidad en los centros de reinserción social y de internamiento que favorezca la reinserción social.\nIV.- En materia de ejecución de penas y medidas de sanción:\na) La supervisión de la prisión preventiva y la ejecución material de las sanciones penales y medidas de seguridad; así como las medidas de sanción impuestas a adolescentes derivadas de una sentencia, de conformidad con las leyes respectivas a la materia;\nb) La supervisión y seguimiento a las personas sentenciadas que gozan de libertad condicionada;\nc) Cumplir los mandamientos judiciales relacionados con las personas sentenciadas;\nLey del Sistema Estatal de Seguridad Ciudadana de Baja California. Página 38\n.\nActualización Legislativa.\nÚltima Reforma P.O. No. 54, Índice, 05-Sep-2025\nd) Abrir un expediente de ejecución, así como establecer los requisitos necesarios con información precisa, actualizada e informatizada del cumplimiento de cada sanción o medida;\ne) Entregar a la persona titular del juzgado de ejecución la información necesaria para la realización del cómputo de penas y abono del tiempo de la prisión preventiva cumplido por la persona sentenciada;\nf) Dar aviso a la persona titular del juzgado de ejecución con la anticipación necesaria del cumplimiento de la pena, de la extinción de la pena o medida de seguridad, una vez transcurrido el plazo fijado en la sentencia ejecutoriada;\ng) Solicitar el otorgamiento de la medida de libertad anticipada de la persona sentenciada que cumpla con los requisitos previstos en la Ley Nacional de Ejecución Penal,\nh) Supervisar, orientar y vigilar la conducta de sentenciado al que se le haya impuesto una medida de seguridad consistente en vigilancia personal o monitoreo.\nV. En materia del cumplimiento o vigilancia de medidas de protección y cautelares en los siguientes términos:\na) Realizar los análisis de los perfiles de las personas imputadas con base en su entorno socioeconómico, antecedentes procesales y comportamiento a efecto de que se determine el riesgo que representa para la víctima, los testigos, la sociedad y para la continuación del proceso penal;\nb) Dar seguimiento y garantizar la efectividad de las medidas de protección dictadas por la autoridad competente en términos del Código Nacional de Procedimientos Penales;\nc) Evaluación y supervisión de las medidas cautelares distintas a la prisión preventiva y de la suspensión condicional del proceso, dictadas por la autoridad competente de conformidad con el Código Nacional de Procedimientos Penales;\nd) Llevar a cabo las obligaciones que como autoridad de supervisión le impone el\nCódigo Nacional de Procedimientos Penales;\ne) Dar cumplimiento a las órdenes de protección dictadas durante la investigación o de aquellas que, en el ámbito de su competencia, sean impuestas de conformidad con las leyes generales y locales en materia de prevención social de las violencias;\nf) Intervenir en los actos procesales de carácter penal en los que sea requerida su participación, y\nLey del Sistema Estatal de Seguridad Ciudadana de Baja California. Página 39\n.\nActualización Legislativa.\nÚltima Reforma P.O. No. 54, Índice, 05-Sep-2025\ng) Llevar el registro, por cualquier medio fidedigno, de las actividades de supervisión que permita tener certeza del cumplimiento o incumplimiento de las medidas impuestas e integrarlo al Sistema Estatal de Información.\nEl Sistema Estatal Penitenciario contará con una unidad administrativa que fungirá como autoridad de supervisión de los objetivos a que se refiere esta fracción, la cual para su debido funcionamiento y cumplimiento de sus fines tendrá adscrita un área especializada de la Fuerza Estatal de Seguridad Ciudadana que le auxiliará al cumplimiento de sus atribuciones y obligaciones.\nArtículo Reformado\nTÍTULO QUINTO\nDEL CONTACTO Y ATENCIÓN A LA CIUDADANÍA\nDenominación Modificada\nCAPÍTULO I\nDEL CENTRO DE CONTROL, COMANDO, COMUNICACIÓN, CÓMPUTO, CALIDAD Y\nCONTACTO CIUDADANO DEL ESTADO\nDenominación Modificada\nARTÍCULO 59.- El Centro de Control, Comando, Comunicación, Cómputo, Calidad y\nContacto Ciudadano del Estado de Baja California, es la unidad administrativa de la Fiscalía\nGeneral que tiene por objeto la operación de los procedimientos para la prestación de los servicios de asistencia telefónica, así como de monitoreo y vídeo vigilancia, a efecto de favorecer la coordinación estratégica y operativa de las Instituciones de Seguridad, Instituciones Policiales en el Estado y Auxiliares, y la Agencia Estatal de Investigación responsables de proporcionar seguridad a la población del Estado de Baja California.\nPárrafo Reformado\nEl personal que labore en el Centro a que se refiere el presente capítulo deberá, previo ingreso a los mismos, cumplir y aprobar los exámenes de evaluación de confianza que para tal efecto establezca la Fiscalía General.\nPárrafo Reformado\nEl Centro de Control, Comando, Comunicación, Cómputo, Calidad y Contacto\nCiudadano del Estado de Baja California, instrumentará la coordinación de las comunicaciones de seguridad para el intercambio de voz, datos e imágenes con las finalidades siguientes:\nI.- Despachar oportunamente la operación de los servicios de emergencia;\nII.- Facilitar el intercambio operativo de la información entre las diversas instituciones policiales del Estado, la Agencia Estatal de Investigación y de los municipios, incluyendo las dependencias de tránsito y vialidad, protección civil, bomberos, y de urgencias médicas y otros servicios públicos;\nLey del Sistema Estatal de Seguridad Ciudadana de Baja California. Página 40\n.\nActualización Legislativa.\nÚltima Reforma P.O. No. 54, Índice, 05-Sep-2025\nIII.- Atender y dar seguimiento a los llamados ciudadanos o en su caso denuncias anónimas, canalizándolas a las autoridades de seguridad ciudadana que sean competentes para su atención y, en su caso, resolución final;\nIV.- Proveer el uso de instrumentos de información operativa, táctica y estratégica para coordinar y facilitar el despliegue operativo policial, y\nV.- Establecer las bases para el funcionamiento del sistema de video vigilancia, así como los lineamientos o manuales de procedimiento a seguir para proporcionar la información obtenida por las videograbaciones, de conformidad con los acuerdos generales, convenios y demás disposiciones aplicables en la materia.\nArtículo Reformado\nCAPÍTULO II\nDEL SERVICIO DE ASISTENCIA TELEFÓNICA A LA CIUDADANÍA\nDenominación Modificada\nARTÍCULO 60.- Las Instituciones de Seguridad establecerán conjuntamente el\nServicio de Asistencia Telefónica, para responder y orientar a la población en casos de emergencia, coordinar rápida y eficientemente a las Instituciones Policiales, la Agencia\nEstatal de Investigación y Auxiliares, para que presten los primeros auxilios, atención médica y demás servicios a que se refiere esta Ley y las demás disposiciones legales aplicables.\nEl Servicio de Asistencia Telefónica deberá comprender, por lo menos:\nI.- La recepción de reportes por delitos, infracciones y conductas cometidas por adolescentes tipificadas como delitos por las leyes;\nII.- Auxilio en la prestación de servicios médicos de urgencia;\nIII.- Auxilio en la localización de personas, bienes y vehículos;\nIV.- Recepción de quejas por faltas y actos delictivos de Miembros;\nV.- Reportes de emergencias, y\nVI.- Aquellos servicios que establezcan la presente Ley y los reglamentos aplicables.\nArtículo Reformado\nARTÍCULO 61.- La Fiscalía General, coordinará la prestación del Servicio de\nAsistencia Telefónica a través del Centro de Control, Comando, Comunicación, Cómputo, Calidad y Contacto Ciudadano del Estado, y para su operación contará por lo menos con la participación de la Fuerza Estatal de Seguridad Ciudadana, la Agencia Estatal de\nInvestigación, las dependencias y unidades administrativas de los municipios encargados de la función de seguridad y los auxiliares previstos en el artículo 24 fracciones I, II y IV, Ley del Sistema Estatal de Seguridad Ciudadana de Baja California. Página 41\n.\nActualización Legislativa.\nÚltima Reforma P.O. No. 54, Índice, 05-Sep-2025 además del personal que se designe de forma permanente para operar en el centro de referencia que exista en cada municipio del Estado.\nPárrafo Reformado\nLa prestación del Servicio de Asistencia Telefónica tendrá carácter permanente durante los trescientos sesenta y cinco días del año, las veinticuatro horas del día.\nLas Instituciones Policiales y la Agencia Estatal de Investigación no podrán establecer centrales de mando alternas, relacionadas con la prestación del Servicio de Asistencia\nTelefónica que prevé esta Ley.\nArtículo Reformado\nARTÍCULO 62.- El servicio a que se refiere el presente Capítulo será brindado a través de una línea telefónica única, la cual será identificada con los números que integran los dígitos “911”. La marcación de dicho número será gratuita para la población.\nEl Centro de Control, Comando, Comunicación, Cómputo, Calidad y Contacto\nCiudadano del Estado deberá de establecerse por lo menos uno por cada Municipio. En el\nEstado de Baja California, no podrán establecerse números telefónicos distintos al determinado por la autoridad competente para la prestación del Servicio de Asistencia\nTelefónica previsto en esta Ley.\nLas autoridades y auxiliares de la seguridad ciudadana deberán atender los incidentes de las llamadas telefónicas que le sean canalizadas, de conformidad con los lineamientos que para ello establezca la Fiscalía General.\nPárrafo Reformado\nArtículo Reformado\nARTÍCULO 63.- El Servicio de Asistencia Telefónica funcionará de conformidad con el\nReglamento que al efecto expida la Fiscalía General, el cual, por lo menos, establecerá la estructura, atribuciones y procedimientos del Centro de Control, Comando, Comunicación, Cómputo, Calidad y Contacto Ciudadano del Estado. Las Instituciones Policiales, la Agencia\nEstatal de Investigación y sus auxiliares, tendrán comunicación directa y permanente con el\nServicio de Asistencia Telefónica a efecto de recibir, proporcionar y actualizar información de interés público, conforme a las reglas y lineamientos que se convengan.\nPárrafo Reformado\nLa coordinación operativa entre las distintas Instituciones Policiales del Estado, la\nAgencia Estatal de Investigación y sus auxiliares, deberá llevarse a cabo únicamente a través del Centro de Control, Comando, Comunicación, Cómputo, Calidad y Contacto\nCiudadano del Estado, en los cuales la Fiscalía General promoverá el uso de la información estratégica de seguridad, así como de la tecnología necesaria para la mejor prestación del servicio.\nPárrafo Reformado\nLey del Sistema Estatal de Seguridad Ciudadana de Baja California. Página 42\n.\nActualización Legislativa.\nÚltima Reforma P.O. No. 54, Índice, 05-Sep-2025\nLa Fiscalía General establecerá la coordinación necesaria con los cuerpos de protección civil nacional, estatales y municipales, así como con las instituciones necesarias para la operación del Servicio de Asistencia Telefónica.\nPárrafo Reformado\nArtículo Reformado\nCAPÍTULO III\nCENTRO DE DENUNCIA ANONIMA\nDenominación Modificada\nARTÍCULO 64.- La Fiscalía General establecerá y coordinará el servicio de denuncia anónima en el Estado, el cual será identificado con el número que integran los dígitos “089”, mismo que se proporcionará a través del Centro de Denuncia Anónima del Estado, para la recepción de las denuncias anónimas efectuadas por la población, con relación a la posible comisión de hechos delictivos o generadores de violencia que afecten la seguridad ciudadana en la entidad.\nEl Centro de Denuncia Anónima recibirá y atenderá las denuncias anónimas recibidas y en su caso canalizando la información recibida a las autoridades competentes en materia de prevención o procuración de justicia que correspondan, realizando el seguimiento de las mismas.\nEl Centro de Denuncia Anónima se organizará y funcionará de conformidad con las disposiciones normativas que al efecto expida la Fiscalía General de Baja California.\nArtículo Reformado\nARTÍCULO 65.- Las autoridades estatales y municipales, deberán dar seguimiento a las denuncias que le sean canalizadas por el Centro de Denuncia Anónima, e informarán del resultado de las mismas, en la forma y términos que se establezcan para dicho fin.\nEn todo momento, se asegurará la confidencialidad de la información obtenida en la prestación del servicio de denuncia anónima, garantizando el anonimato del denunciante.\nLa prestación del servicio de denuncia anónima “089”, tendrá carácter permanente durante los trescientos sesenta y cinco días del año, las veinticuatro horas del día. recibidas por conducto del Centro, que sean de su competencia.\nArtículo Reformado\nTÍTULO SEXTO\nCAPÍTULO ÚNICO\nARTÍCULO 66.- Se sancionará con dos a ocho años de prisión y de quinientos a mil días multa, a quien:\nLey del Sistema Estatal de Seguridad Ciudadana de Baja California. Página 43\n.\nActualización Legislativa.\nÚltima Reforma P.O. No. 54, Índice, 05-Sep-2025\nI.- Ingrese dolosamente a las bases de datos del Sistema Estatal de Información previsto en esta Ley, sin tener derecho a ello o, teniéndolo, ingrese a sabiendas información errónea, que dañe o que pretenda dañar en cualquier forma la información, las bases de datos o los equipos o sistemas que las contengan;\nFracción Reformada\nII.- Divulgue de manera ilícita información clasificada de las bases de datos o sistemas informáticos a que se refiere esta Ley;\nIII.- Inscriba o registre, como Miembro, o Agente Estatal de Investigación, Perito, Elemento de Apoyo o personal operativo de los Prestadores de Servicios de Seguridad\nPrivada a persona que no cuente con la certificación exigible conforme a la Ley, o a sabiendas de que la certificación es ilícita;\nFracción Reformada\nIV.- Al que ingrese a las Instituciones Policiales o a la Agencia Estatal de\nInvestigación, a aquellos aspirantes y miembros que no hayan cursado ni aprobado los programas de formación, capacitación y profesionalización; y\nFracción Reformada\nV.- Asigne nombramiento de Policía, Agente del Ministerio Público, Perito, Elemento de Apoyo o personal operativo de los Prestadores de Servicios de Seguridad Privada a persona que no haya sido certificada y registrada en los términos de esta Ley.\nSi el responsable es o hubiera sido servidor de la Institución de Seguridad Pública, se impondrá hasta una mitad más de la pena correspondiente.\nArtículo Reformado\nTÍTULO SÉPTIMO\nPRESTACIÓN DE SERVICIOS DE SEGURIDAD PRIVADA\nCAPÍTULO ÚNICO\nARTÍCULO 67.- Además de cumplir con las disposiciones de la Ley Federal de Armas de Fuego y Explosivos, las personas físicas o morales que pretendan prestar o presten los servicios de seguridad privada en el Estado, en cualquiera de las modalidades que prevé la presente Ley y el reglamento correspondiente, deberán obtener la autorización de la\nSecretaría, con la cual se integrará el Sistema Estatal de Información.\nPárrafo Reformado\nNinguna persona física o moral, ni grupos o individuos podrá realizar dichas actividades, si no han obtenido autorización por parte de la Secretaría.\nPárrafo Reformado\nLey del Sistema Estatal de Seguridad Ciudadana de Baja California. Página 44\n.\nActualización Legislativa.\nÚltima Reforma P.O. No. 54, Índice, 05-Sep-2025\nPrevio a la prestación de sus servicios en la entidad, los prestadores de servicios de seguridad privada que obtengan Autorización Federal para prestar sus servicios en el\nEstado, invariablemente deberán de cumplir con la presente Ley, el Reglamento de\nSeguridad Privada para el Estado de Baja California y demás normatividad aplicable.\nTratándose de los sujetos referidos en el párrafo anterior, los requisitos establecidos en esta Ley que excedan a los contenidos en la Ley Federal de Seguridad Privada, no les serán aplicables, de conformidad con lo previsto en el artículo 150 de la Ley General del\nSistema Nacional de Seguridad Pública.\nArtículo Reformado\nARTÍCULO 68.- Los prestadores de servicios de seguridad privada, son auxiliares a la función de seguridad pública, por lo que sus integrantes coadyuvarán con las autoridades y las instituciones de seguridad pública cuando así se les requiera.\nPara efectos de esta Ley, se entenderá como prestador de servicios de seguridad privada a:\nI.- Las personas físicas o morales legalmente constituidas, cuyo objeto social sea la prestación de servicios de seguridad privada, ya sea la guarda o custodia de locales o para la transportación de valores. Quedan asimiladas a este grupo las personas físicas que presten el servicio de seguridad privada por conducto de terceros empleados a su cargo;\nII.- Los grupos de seguridad que a su costa organicen los habitantes de las colonias, fraccionamientos y zonas residenciales para ejercer, en cualquier horario, la función única y exclusiva de resguardar los inmuebles o las casas habitación ubicadas en las áreas que previamente se señalen;\nIII.- Los custodios de personas, que presten servicios de seguridad personal, a costa de quienes reciben tal servicio;\nIV.- Los prestadores, que en forma independiente desempeñan la función de vigilancia sobre casas habitación, comercios o personas;\nV.- Las personas físicas o morales, que presten los servicios de seguridad electrónica en todas sus clasificaciones;\nVI.- Las personas físicas o morales que presten servicios de investigación privada;\nVII.- Las personas físicas o morales que presten servicios de seguridad privada por medio de canes;\nVIII.- Las personas físicas o morales que realicen actividades vinculadas con servicios de blindaje de vehículos automotores, y\nLey del Sistema Estatal de Seguridad Ciudadana de Baja California. Página 45\n.\nActualización Legislativa.\nÚltima Reforma P.O. No. 54, Índice, 05-Sep-2025\nIX.- En general, toda persona física o moral que realice actividades similares y auxiliares relacionadas con la seguridad privada en términos de la presente Ley y el reglamento correspondiente.\nLas obligaciones y prohibiciones que establezca el reglamento que regula los servicios de seguridad privada en el Estado, serán de observancia para las industrias; establecimientos fabriles o comerciales, que contraten a personal para realizar funciones de vigilancia interna, para la guarda o custodia de sus locales, bienes o valores, o para la transportación de estos últimos y que tengan una relación laboral de prestación de servicios con la unidad económica en la que desempeñen sus funciones.\nARTÍCULO 69.- La Secretaría deberá publicar anualmente en el Periódico Oficial del\nEstado, y en uno de los de mayor circulación en la Entidad, los requisitos que deberán cumplir los prestadores de servicios de seguridad privada para obtener su registro. Sólo podrán prestar este servicio, las personas físicas o morales de nacionalidad mexicana.\nArtículo Reformado\nARTÍCULO 70.- Previa a la autorización de servicios de seguridad privada, la\nSecretaría requerirá y dará vista para su opinión, a los municipios, debiendo emitir la misma en un plazo de treinta días posteriores a su recepción.\nArtículo Reformado\nARTÍCULO 71.- Los sujetos a que se refiere como prestador de servicios de seguridad privada en esta Ley, deberán capacitar permanentemente a su personal operativo bajo los lineamientos y programas que se establezcan en las leyes y disposiciones legales aplicables, a efecto de que éstos cuenten con los conocimientos necesarios para el eficaz desempeño de su función.\nPárrafo Reformado\nLos sujetos a que se refiere el párrafo anterior, deberán someter a su personal operativo a procedimientos de evaluación y control de confianza ante el Centro de Control de\nConfianza, previo pago de los derechos que correspondan conforme a la Ley de Ingresos respectiva por los servicios que preste dicho centro.\nLa periodicidad para los procedimientos de evaluación y control de confianza, a que refiere el párrafo anterior, se determinará en el reglamento correspondiente.\nArtículo Reformado\nARTÍCULO 72.- La Secretaría expedirá a la persona física o moral que pretenda respectivo, la autorización correspondiente en la que constará por lo menos, el número de ésta, el nombre completo y domicilio de la persona física o moral, la vigencia, la modalidad o modalidades autorizadas, y en su caso la clasificación y los límites territoriales de operación.\nPárrafo Reformado\nTambién expedirá a los prestadores independientes a que se refiere esta Ley, la\nLey del Sistema Estatal de Seguridad Ciudadana de Baja California. Página 46\n.\nActualización Legislativa.\nÚltima Reforma P.O. No. 54, Índice, 05-Sep-2025 privada, tal credencial deberá contener los elementos y características a que se refiere el reglamento correspondiente.\nArtículo Reformado\nARTÍCULO 73.- La autorización obtenida para la prestación de servicios de seguridad privada, no faculta para realizar investigaciones, intervenir o interferir en asuntos que sean competencia del Ministerio Público o de las Instituciones Policiales y demás autoridades encargadas de la seguridad pública, aún en los lugares o áreas de trabajo de los prestadores.\nEn caso de que acontezcan hechos que se presuman como constitutivos de delito o conductas cometidas por adolescentes tipificadas como delito por la ley, o conozcan pruebas o indicios que acrediten la probable responsabilidad penal de un individuo, solicitarán de inmediato la intervención de la autoridad competente.\nLa función del personal operativo de los sujetos a que se refiere esta Ley, cesará en cuanto hagan acto de presencia los Agentes del Ministerio Público o los Miembros de las\nInstituciones Policiales.\nARTÍCULO 74.- Las personas físicas o morales que presten este servicio, así como el personal que utilicen, se regirán en lo conducente por las normas que esta ley y demás ordenamientos aplicables establecen para ellos; incluyendo los principios de actuación y desempeño y la obligación de aportar los datos y proporcionar la información y documentos para integrar el Sistema Estatal de Información que le requiera la Secretaría.\nArtículo Reformado\nARTÍCULO 75.- Las personas físicas o morales que se dediquen a la prestación de servicios de seguridad privada en el Estado, deberán abstenerse de:\nI.- Realizar funciones que constitucional o legalmente sean competencia exclusiva de las Instituciones Policiales en el Estado y de la Agencia Estatal de Investigación, del\nGobierno Federal, y/o del Ejército, Armada o Fuerza Aérea Nacionales;\nFracción Reformada\nII.- Usar en su nombre, razón social o denominación, credenciales, identificaciones, papelería, documentación y demás bienes de éstos, las palabras “Policía”, “agentes investigadores” o cualquier otra que derive de las anteriores o que pueda dar a entender una relación con las autoridades o las Instituciones Policiales en el Estado, de la Agencia Estatal precedente al adjetivo “privada”.\nFracción Reformada\nIII.- Utilizar en sus gafetes, credenciales, identificaciones, documentación, insignias y demás bienes y artículos, de logotipos o nombres oficiales de las Instituciones Policiales en\nArmada o Fuerza Aérea Nacionales, el escudo o colores nacionales, estatales o municipales, así como los escudos, o banderas oficiales de otros países;\nLey del Sistema Estatal de Seguridad Ciudadana de Baja California. Página 47\n.\nActualización Legislativa.\nÚltima Reforma P.O. No. 54, Índice, 05-Sep-2025\nFracción Reformada\nIV.- Usar cualquier tipo de placas o credenciales metálicas de identidad, óvalos metálicos de identificación, o cualquier otro medio similar a los de uso oficial de las\nInstituciones Policiales en el Estado y de la Agencia Estatal de Investigación, del Gobierno\nFederal, o de las del Ejército, Armada o Fuerza Aérea Nacionales;\nFracción Reformada\nV.- Utilizar vehículos cuya estancia en el país sea ilegal, sin placas de circulación o con placas que no le correspondan, sean robados o recuperados, o sin el consentimiento de su legítimo dueño;\nVI.- Utilizar torretas que se confundan con las utilizadas por las Instituciones Policiales en el Estado, la Agencia Estatal de Investigación o el Gobierno Federal;\nVII.- Utilizar y/o instalar cualquier tipo de sirena en los vehículos que se utilicen para la prestación de los Servicios de Seguridad Privada;\nFracción Reformada\nVIII.- Utilizar uniformes, insignias, divisas, o armamento cuyo uso se encuentre reservado a las Instituciones Policiales en el Estado o del Gobierno Federal o al Ejército, Armada o Fuerza Aérea Nacionales;\nFracción Reformada\nIX.- Prestar servicios de cualquier carácter en cualquier Institución Policial en el\nEstado, en la Agencia Estatal de Investigación, o en el Gobierno Federal;\nFracción Reformada\nX.- Realizar investigaciones, intervenir o interferir en asuntos que sean competencia del Ministerio Público, aún en los lugares o áreas de trabajo del personal operativo;\nXI.- Realizar actividades de seguridad privada que no se encuentren previstas en la autorización, o en una forma distinta a la establecida en la misma;\nXII.- Prestar los servicios de seguridad privada en una circunscripción distinta a la que se encuentren prevista en la autorización;\nXIII.- Utilizar vehículos con emblemas o distintivos no autorizados; así como utilizar en sus vehículos, colores cuya combinación se asimile a los utilizados por las Instituciones\nEjército, Armada y/o Fuerza Aérea Nacionales;\nFracción Reformada\nXIV.- Presentar a la Secretaría, documentación o información falsa o alterada;\nFracción Reformada\nLey del Sistema Estatal de Seguridad Ciudadana de Baja California. Página 48\n.\nActualización Legislativa.\nÚltima Reforma P.O. No. 54, Índice, 05-Sep-2025\nXV.- Realizar actos que pongan en peligro la integridad física, la vida o los bienes de particulares, mediante el uso de armas, artefactos, animales o cualquier otro objeto cuyo uso no se encuentre autorizado por la Secretaría;\nFracción Reformada\nXVI.- Transferir o ceder la autorización;\nXVII.- Prestar los servicios de seguridad privada si el personal operativo no ha sido capacitado bajo los lineamientos y programas que establezca el Instituto o en los casos que la Ley aplicable lo disponga, la Secretaría de Seguridad Ciudadana; y,\nFracción Reformada\nXVIII.- Las demás que establezcan las leyes y reglamentos.\nArtículo Reformado\nARTÍCULO 76.- En materia de seguridad privada, corresponderá a la Secretaría:\nPárrafo Reformado\nI.- Regular, controlar y sancionar, por conducto de la unidad administrativa correspondiente la prestación de los servicios de seguridad privada en el Estado;\nII.- Fijar los requisitos para obtener la autorización para la prestación de los servicios de seguridad privada, previo pago de los derechos respectivos;\nIII.- Supervisar permanentemente al personal, los programas de capacitación profesional, el equipo y la operación de los prestadores de servicios de seguridad privada.\nPara ello, éstos tendrán la obligación de proporcionar la información que les solicite y podrá realizar las visitas de inspección y demás actuaciones que esta Ley y el Reglamento correspondiente prevea;\nIV.- Aplicar las medidas cautelares previstas en el Reglamento de la materia;\nV.- Sancionar conforme a lo dispuesto en esta Ley y el Reglamento correspondiente, a los prestadores de servicios de seguridad privada, cuando por acción u omisión incumplan lo dispuesto en dichos ordenamientos;\nVI.- En cuanto a los grupos de seguridad privada y grupos de seguridad que organicen los habitantes de las colonias, fraccionamientos y zonas residenciales, expedir la constancia que certifique que cuentan con autorización para prestar el servicio; a la\nVII.- Las demás previstas en esta Ley, el Reglamento correspondiente y otras disposiciones aplicables.\nArtículo Reformado\nLey del Sistema Estatal de Seguridad Ciudadana de Baja California. Página 49\n.\nActualización Legislativa.\nÚltima Reforma P.O. No. 54, Índice, 05-Sep-2025\nARTÍCULO 77.- En ningún caso los Miembros de las Instituciones Policiales en el\nEstado o los Agentes de la Agencia Estatal de Investigación, podrán ser propietarios, socios, asociados, administradores, comisionistas, personal operativo o asesor, por sí o por interpósita persona, de una empresa o negociación que preste servicios de seguridad privada en el Estado.\nArtículo Reformado\nARTÍCULO 78.- Los casos, condiciones, requisitos y lugares para la portación de armas de fuego, por parte del personal de los prestadores de servicios de seguridad privada a que se refiere el presente título, se ajustarán a lo dispuesto por la Ley Federal de Armas de Fuego y Explosivos, y su reglamento.\nARTÍCULO 79.- El incumplimiento por parte de los prestadores de servicios de seguridad privada en el Estado, a las obligaciones establecidas en esta ley, el Reglamento de Seguridad Privada para el Estado de Baja California y demás disposiciones aplicables, dará lugar a las siguientes sanciones:\nI.- Amonestación por escrito;\nII. Multa por el equivalente de hasta cinco mil veces la Unidad de Medida y\nActualización;\nIII.- Suspensión de la autorización hasta por noventa días naturales;\nIV.- Cancelación de la autorización. En este caso, la Secretaría notificará la cancelación a las autoridades correspondientes, a efecto de que realicen, en los términos de sus competencias, los actos que legalmente procedan;\nFracción Reformada\nV.- Clausura provisional, y\nVI.- Clausura definitiva del establecimiento.\nEl Reglamento de Seguridad Privada para el Estado de Baja California, determinará los casos y condiciones en que se aplicarán las presentes sanciones.\nLa Secretaría notificará la imposición de sanciones a la Secretaría de Hacienda, autoridad municipal correspondiente de la circunscripción territorial de los prestadores, a la a las demás autoridades que estime conveniente.\nPárrafo Reformado\nLa Secretaría, independientemente de la sanción impuesta, apercibirá a los prestadores respecto de las consecuencias en caso de reincidencia.\nPárrafo Reformado\nArtículo Reformado\nLey del Sistema Estatal de Seguridad Ciudadana de Baja California. Página 50\n.\nActualización Legislativa.\nÚltima Reforma P.O. No. 54, Índice, 05-Sep-2025\nARTÍCULO 80.- La Secretaría podrá solicitar al municipio que corresponda el auxilio para la supervisión del funcionamiento de las personas físicas o morales prestadoras de servicios de seguridad privada y de similar naturaleza.\nArtículo Reformado\nTÍTULO OCTAVO\nPARTICIPACIÓN DE LA COMUNIDAD Y LA PREVENCIÓN DEL DELITO\nCAPÍTULO I\nPARTICIPACIÓN DE LA COMUNIDAD\nARTÍCULO 81.- En el Estado de Baja California, se establecerá y organizará un\nConsejo Ciudadano de Seguridad como instancia colegiada de consulta y participación ciudadana. En cada uno de los municipios se deberá establecer un Comité Ciudadano de\nSeguridad con la misma naturaleza.\nPárrafo Reformado\nLos Presidentes de los Comités, integrarán el Consejo Ciudadano de Seguridad en calidad de Consejeros Ciudadanos, en representación de sus respectivos Municipios.\nPárrafo Reformado\nEl Consejo Ciudadano de Seguridad y Comités se integrarán mayoritariamente por ciudadanos y con la representación del Estado y el municipio respectivo, que determine el reglamento correspondiente.\nPárrafo Reformado\nEl Ejecutivo del Estado, elegirá por insaculación a tres consejeros ciudadanos que integrarán el Consejo Ciudadano de Seguridad, de entre las propuestas que presenten las asociaciones, agrupaciones profesionales y organismos no gubernamentales, empresariales, o instituciones de educación superior. Dicha insaculación se realizará ante la presencia de la\nComisión del Congreso del Estado cuyas funciones se relacionen con la seguridad. Sólo podrán ser insaculados aquellos ciudadanos que cumplan con los requisitos que determine el reglamento.\nPárrafo Reformado\nEl Presidente del Consejo Ciudadano de Seguridad será electo de entre los\nConsejeros Ciudadanos, con la aprobación de las dos terceras partes de éstos; en los mismos términos se elegirá al Presidente del Comité correspondiente.\nPárrafo Reformado\nEl Reglamento determinará la organización, coordinación y funcionamiento del\nConsejo Ciudadano de Seguridad Pública.\nPárrafo Reformado\nLos municipios podrán establecer, la organización y coordinación de los Comités\nCiudadanos de Seguridad municipales, que consideren pertinentes.\nPárrafo Reformado\nArtículo Reformado\nLey del Sistema Estatal de Seguridad Ciudadana de Baja California. Página 51\n.\nActualización Legislativa.\nÚltima Reforma P.O. No. 54, Índice, 05-Sep-2025\nARTÍCULO 82.- Los municipios y demás dependencias de la Administración Pública\nEstatal, deberán de coordinarse con la Secretaría la implementación y ejecución de los diversos planes, programas y acciones en materia de prevención del delito, bajo la conducción de esta última, privilegiando en todo momento la homologación en su ejecución.\nPárrafo Reformado\nLa Secretaría asignará los recursos necesarios para la difusión de los programas en prevención del delito. Los programas que se diseñen deberán considerar la participación de otras instancias tales como el sector salud, educativo, desarrollo económico y social.\nPárrafo Reformado\nArtículo Reformado\nARTÍCULO 83.- Corresponde al Consejo Ciudadano de Seguridad y a los Comités\nCiudadanos Municipales de Seguridad:\nPárrafo Reformado\nI.- Ser órganos de consulta, análisis y opinión en materia de seguridad pública;\nII. Emitir opiniones y sugerencias, para la actualización, elaboración y evaluación del programa y evaluar la ejecución del mismo;\nIII.- Informar ante las autoridades competentes, sobre las zonas que en su concepto tengan mayor índice de delincuencia dentro de la circunscripción territorial de cada una de los Comités;\nIV.- Proponer a las Instituciones de Seguridad Pública, mecanismos de coordinación y desconcentración de funciones, para la mejor cobertura y calidad en los servicios encomendados;\nV.- Evaluar el cumplimiento del o los programas preventivos;\nVI.- Promover programas a fin de arraigar y vincular al policía con la comunidad, que conlleve un sentido de integración y participación social;\nVII.- Proponer anualmente a los Titulares y a quienes ejerzan el mando directo de las\nInstituciones Policiales y de la Agencia Estatal de Investigación, la entrega de la servicios a la comunidad, sin perjuicio de la facultad de sugerir otros estímulos;\nFracción Reformada\nVIII.- Turnar ante la Contraloría Interna que tenga a su cargo una Institución Policial y la Agencia Estatal de Investigación, aquellos casos en que a su juicio constituyan faltas graves a los principios de actuación previstos en la Ley, por parte de los Miembros y los agentes de la Agencia Estatal de Investigación;\nFracción Reformada\nLey del Sistema Estatal de Seguridad Ciudadana de Baja California. Página 52\n.\nActualización Legislativa.\nÚltima Reforma P.O. No. 54, Índice, 05-Sep-2025\nIX.- Proponer modificaciones a normas y procedimientos, que permitan mejorar la atención de las quejas que formulen la ciudadanía contra abusos y actuaciones en que incurran los Miembros y los Agentes de la Agencia Estatal de Investigación;\nFracción Reformada\nX.- Proponer a las Instituciones Policiales y a la Agencia Estatal de Investigación, las acciones a emprender para prevenir la comisión de delitos y su impunidad;\nFracción Reformada\nXI.- Fomentar la cooperación y participación de la comunidad en los siguientes aspectos:\na) La difusión amplia del Programa, con participación vecinal;\nInciso Reformado\nb) La aportación de equipo complementario, el cual será destinado al servicio exclusivo de la demarcación correspondiente;\nc) El establecimiento de mecanismos de auto seguridad ciudadana y\nd) La difusión de programas de reclutamiento;\nFracción Reformada\nXII.- Realizar labores de seguimiento en el ejercicio de sus atribuciones;\nXIII.- Proponer a las autoridades competentes, de conformidad con las facultades que le concede este capítulo, programas de participación de la comunidad en las actividades que no sean confidenciales o pongan en riesgo el buen desempeño en la función de seguridad ciudadana;\nFracción Reformada\nXIV.- Asistir, previa invitación, a las sesiones de los Comités Técnicos u órganos de administración, respecto de los Fideicomisos que se constituyan para el manejo de los pública;\nXV.- Promover, impulsar y difundir la cultura de la legalidad y prevención del delito, así como la seguridad escolar en escuelas públicas y privadas en niveles básico, bachillerato y profesional;\nXVI.- Promover, impulsar, y difundir la cultura de la denuncia ciudadana y la denuncia anónima;\nXVII.- Difundir e impulsar políticas y acciones destinadas en materia de salud pública a la prevención de adicciones y\nLey del Sistema Estatal de Seguridad Ciudadana de Baja California. Página 53\n.\nActualización Legislativa.\nÚltima Reforma P.O. No. 54, Índice, 05-Sep-2025\nXVIII.- Las demás que establezca la Ley y los Reglamentos.\nArtículo Reformado\nARTÍCULO 84.- El Consejo Ciudadano y los Comités Ciudadanos Municipales de\nSeguridad, tendrán derecho a recibir la información que les permita participar adecuadamente, en el ámbito de sus atribuciones; en la seguridad de su respectiva demarcación. Igualmente, tendrán derecho a recibir respuestas por escrito a sus peticiones o comentarios, por parte de la autoridad correspondiente, siempre y cuando no esté clasificada como reservada o como confidencial por las disposiciones legales aplicables.\nArtículo Reformado\nCAPÍTULO II\nPREVENCIÓN DEL DELITO\nARTÍCULO 85.- La Secretaría será la encargada de diseñar, difundir, dar seguimiento y evaluar periódicamente la política y programas en materia de prevención del delito en el\nEstado, tomando en consideración la estadística delictiva en la entidad, las conductas antisociales y para social que pudieran ser un factor en la comisión de delitos, así como la opinión de la comunidad y de los organismos de la sociedad civil.\nPárrafo Reformado\nEn la elaboración de la política y programas en materia de prevención del delito se deberá vincular con los programas sectoriales de salud, educación, desarrollo económico y social, así como con todas aquellas materias que atañen a la seguridad pública, para lograr armonía en las políticas públicas, tanto en el Ejecutivo Estatal como en los Municipios.\nEn la prevención del delito se dará particular énfasis en el diseño de programas que involucren a niñas, niños y adolescentes, estudiantes y personas en estado de marginación social.\nPara la atención de la prevención del delito la Secretaría gestionará la asignación de recursos suficientes para su cumplimiento.\nPárrafo Reformado\nArtículo Reformado\nARTÍCULO 86.- Los municipios y demás dependencias de la Administración Pública\nEstatal, deberán de coordinarse con la Secretaría para la implementación y ejecución de los diversos planes, programas y acciones en materia de prevención del delito, bajo la conducción de esta última, privilegiando en todo momento la homologación en su ejecución.\nPárrafo Reformado prevención del delito. Los programas que se diseñen deberán considerar la participación de otras instancias tales como el sector salud, educativo, desarrollo económico y social.\nPárrafo Reformado\nArtículo Reformado\nLey del Sistema Estatal de Seguridad Ciudadana de Baja California. Página 54\n.\nActualización Legislativa.\nÚltima Reforma P.O. No. 54, Índice, 05-Sep-2025\nCAPÍTULO III\nPREVENCIÓN SOCIAL DE LA VIOLENCIA Y LA DELINCUENCIA\nARTÍCULO 87.- La prevención social de la violencia y la delincuencia es el conjunto de políticas públicas, programas y acciones orientados a reducir factores de riesgo que genera violencia y delincuencia, así como combatir las distintas causas y factores que la generan.\nARTÍCULO 88.- La prevención social de la violencia y delincuencia comprende los siguientes ámbitos:\nI.- Social.- El cual llevará a cabo mediante:\na) La formulación de programas integrales de desarrollo social, cultural y económico que no produzcan estigmatización, incluidos los de salud, educación, vivienda, empleo, deporte y desarrollo urbano;\nb) La promoción de actividades que eliminen la marginación y la exclusión;\nc) El fomento de la solución pacífica de conflictos;\nd) Estrategias de educación y sensibilización de la población para promover la cultura de la legalidad y tolerancia respetando al mismo tiempo las diversas identidades culturales.\nIncluyendo tanto programas generales como aquellos enfocados a grupos sociales y comunidades en altas condiciones de vulnerabilidad;\ne) El establecimiento de programas que modifiquen las condiciones sociales de la comunidad y generen oportunidades de desarrollo especialmente para los grupos en situación de riesgo, vulnerabilidad, o afectación.\nII.- Comunitario.- El cual pretende atender los factores que generan violencia y delincuencia mediante la participación ciudadana y comunitaria y comprende:\na) La participación ciudadana y comunitaria en acciones tendientes a establecer las prioridades de la prevención, mediante diagnósticos participativos, el mejoramiento de las cultura de prevención, autoprotección, denuncia ciudadana y de utilización de los mecanismos alternativos de solución de controversias;\nb) El mejoramiento de acceso de la comunidad a los servicios básicos;\nc) Fomentar el desarrollo comunitario, la convivencia y la cohesión social entre las comunidades frente a los problemas locales;\nLey del Sistema Estatal de Seguridad Ciudadana de Baja California. Página 55\n.\nActualización Legislativa.\nÚltima Reforma P.O. No. 54, Índice, 05-Sep-2025\nd) La participación ciudadana y comunitaria, a través de mecanismos que garanticen su efectiva intervención ciudadana en el diseño e implementación de planes y programas, su evaluación y sostenibilidad; y\ne) El fomento de las actividades de las organizaciones de la sociedad civil.\nARTÍCULO 89.- Las Instituciones de Seguridad, en el ámbito de sus atribuciones y en el marco del Sistema Nacional, deberán:\nPárrafo Reformado\nI.- Proporcionar información a las comunidades para enfrentar los problemas derivados de la delincuencia; siempre que no vulnere los principios confidencialidad y reserva;\nII.- Apoyar el intercambio de experiencia, investigación académica y aplicación práctica de conocimientos basados en evidencias;\nIII.- Apoyar la organización y la sistematización de experiencias exitosas en el combate a los delitos.\nArtículo Reformado\nARTÍCULO 90.- Se entiende por participación ciudadana y comunitaria a la colaboración de diferentes sectores y grupos de la sociedad civil, organizada y no organizada, así como de la comunidad académica; se hace efectiva a través de la actuación de las personas en las comunidades, en las redes vecinales, las organizaciones para la prevención social de la violencia y la delincuencia, mediante los diversos mecanismos de participación locales o legales, creados en virtud de sus necesidades.\nTÍTULO NOVENO\nDESARROLLO POLICIAL\nCAPÍTULO I\nDISPOSICIONES GENERALES\nARTÍCULO 91.- El desarrollo policial es un conjunto integral de reglas y procesos debidamente estructurados y enlazados entre sí que comprenden la carrera policial, los esquemas de profesionalización, la certificación y el régimen disciplinario de los Miembros de las Instituciones Policiales y tiene por objeto garantizar el desarrollo institucional, la estabilidad, seguridad e igualdad de oportunidades de los mismos; elevar la profesionalización, fomentar la vocación de servicio, y garantizar el cumplimiento de los principios constitucionales y de la Ley General.\nPárrafo Reformado\nInstituciones Policiales en materia de carrera policial.\nPárrafo Adicionado\nLey del Sistema Estatal de Seguridad Ciudadana de Baja California. Página 56\n.\nActualización Legislativa.\nÚltima Reforma P.O. No. 54, Índice, 05-Sep-2025\nLas reglas y procesos en materia de carrera policial y régimen disciplinario de la\nAgencia Estatal de Investigación, serán aplicados, operados y supervisados por la Fiscalía\nGeneral.\nPárrafo Adicionado\nArtículo Reformado\nARTÍCULO 92.- Cuando la titularidad, el ejercicio del mando directo o cargo inmediato inferior recaiga en un policía de carrera, al momento que concluya su función, podrá ser reintegrado al grado que conservaba en el momento de la designación.\nLas faltas administrativas en que incurran en el ejercicio de sus funciones se sujetarán a los procedimientos que dispongan las leyes aplicables.\nARTÍCULO 93.- Para la aplicación de esta Ley, tendrán fe pública:\nI.- El titular de la dependencia de que se trate, de la Fiscalía General, de la Secretaría, de la Comisión Estatal del Sistema Penitenciario y los que ejerzan el mando directo de las\nInstituciones Policiales;\nFracción Reformada\nII.- El titular de la Contraloría Interna,\nIII.- Las Comisiones; y\nIV.- El personal encargado de auxiliar a las autoridades responsables en el procedimiento de la separación definitiva o sanción de los Miembros por infringir las disposiciones de esta Ley y sus reglamentos.\nArtículo Reformado\nARTÍCULO 94.- Se excluyen del ámbito de aplicación de este Título:\nI.- Los Titulares y los que ejerzan el mando directo, de las Instituciones Policiales, de conformidad con su estructura orgánica;\nII.- Aquellas personas que desempeñen el cargo inmediato inferior a quienes ejerzan el mando directo de la Institución Policial, de conformidad con su estructura orgánica;\nIII.- El personal encargado de auxiliar a las autoridades responsables de la separación reglamentos;\nIV.- Tratándose de los municipios, éstos determinarán en sus respectivos reglamentos, quienes, en su caso, serán excluidos de la aplicación de las disposiciones contenidas en esta Ley.\nFracción Reformada\nArtículo Reformado\nLey del Sistema Estatal de Seguridad Ciudadana de Baja California. Página 57\n.\nActualización Legislativa.\nÚltima Reforma P.O. No. 54, Índice, 05-Sep-2025\nARTÍCULO 95.- En lo no previsto por este título, se aplicará supletoriamente el\nCódigo de Procedimientos Civiles para el Estado de Baja California.\nARTÍCULO 96.- Las Instituciones Policiales y la Agencia Estatal de Investigación serán de carácter civil, disciplinado y profesional. Deberán fomentar la participación de la comunidad y rendir cuentas en términos de ley.\nArtículo Reformado\nARTÍCULO 97.- Las Instituciones Policiales, para el mejor cumplimiento de sus objetivos, establecerán, cuando menos, las siguientes áreas operativas:\nI.- Investigación, que será la encargada de la investigación a través de sistemas homologados de recolección, clasificación, registro, análisis, evaluación y explotación de información.\nFracción Reformada\nII.- Prevención, que será la encargada de prevenir la comisión de hechos violentos, la comisión de delitos e infracciones administrativas, realizar las acciones de inspección, vigilancia y vialidad en su circunscripción, así como proporcionar medidas u órdenes de protección inmediatas en términos de lo dispuesto por la Ley General de Acceso de las\nMujeres a una Vida Libre de Violencia y la Ley de Acceso de las Mujeres a una Vida Libre de\nViolencia para el Estado de Baja California;\nFracción Reformada\nIII.- Reacción, que será la encargada de garantizar, mantener y restablecer el orden y la paz públicos;\nIV.- Proximidad social, como una actividad auxiliar a las funciones de prevención, a través de la proactividad y la colaboración con otros actores sociales, bajo una política de colaboración interna e interinstitucional que fortalezca la gobernabilidad local y\nV.- La atribución de la investigación para disuasión y prevención de los delitos corresponde a la Fuerza Estatal de Seguridad Ciudadana.\nFracción Reformada\nArtículo Reformado\nARTÍCULO 98.- Las unidades de policía encargadas de la investigación científica de los delitos se ubicarán en la estructura orgánica de la Fiscalía General, en cuyo caso se desempeño de dichas funciones.\nArtículo Reformado\nARTÍCULO 99.- Las Instituciones Policiales, considerarán para su organización jerárquica interna al menos las categorías siguientes:\nI.- Comisarios;\nLey del Sistema Estatal de Seguridad Ciudadana de Baja California. Página 58\n.\nActualización Legislativa.\nÚltima Reforma P.O. No. 54, Índice, 05-Sep-2025\nII.- Inspectores;\nIII.- Oficiales y\nIV.- Escala Básica.\nEn la Agencia Estatal de Investigación se establecerán al menos niveles jerárquicos equivalentes a las primeras tres fracciones del presente artículo, con las respectivas categorías, conforme al modelo policial previsto en esta Ley.\nARTÍCULO 100.- Las categorías previstas en el artículo anterior considerarán, al menos, las siguientes jerarquías:\nI.- Comisarios: a. Comisario General; b. Comisario Jefe, y c. Comisario.\nII.- Inspectores: a. Inspector General; b. Inspector Jefe, y c. Inspector.\nIII.- Oficiales: a. Subinspector; b. Oficial, y c. Suboficial.\nIV.- Escala Básica: a. Policía Primero; b. Policía Segundo;\nLey del Sistema Estatal de Seguridad Ciudadana de Baja California. Página 59\n.\nActualización Legislativa.\nÚltima Reforma P.O. No. 54, Índice, 05-Sep-2025 c. Policía Tercero, y d. Policía.\nARTÍCULO 101.- Las Instituciones Policiales se organizarán bajo un esquema de jerarquización terciaria, cuya célula básica se compondrá invariablemente por tres elementos.\nCon base en las categorías jerárquicas señaladas en el artículo precedente, los titulares de las instituciones municipales, deberán cubrir, al menos, el mando correspondiente al quinto nivel ascendente de organización en la jerarquía.\nLas Instituciones Policiales deberán satisfacer, como mínimo, el mando correspondiente al octavo grado de organización jerárquica.\nLos titulares de las categorías jerárquicas estarán facultados para ejercer la autoridad y mando policial en los diversos cargos o comisiones.\nARTÍCULO 102.- El orden de las categorías jerárquicas y grados tope del personal de las Instituciones Policiales con relación a las áreas operativas y de servicios será:\nI.- Para las áreas operativas, de policía a Comisario General, y\nII.- Para los servicios, de policía a Comisario Jefe.\nCAPÍTULO II\nCOMISIÓN\nARTÍCULO 103.- La Secretaría, la Fiscalía General y los Municipios establecerán instancias colegiadas para conocer y resolver toda controversia que se suscite con relación a los procedimientos de la Carrera Policial y el Régimen Disciplinario de los Miembros de las\nInstituciones Policiales.\nArtículo Reformado\nARTÍCULO 104.- En aquellas Instituciones de Seguridad Pública en las que se tenga bajo su mando a más de un cuerpo policial, deberá constituirse una sola Comisión de\nCarrera Policial y el Régimen Disciplinario de los Miembros de las Instituciones Policiales.\nLa Comisión llevará un registro de datos de los Miembros de sus instituciones, los\nSeguridad Pública.\nARTÍCULO 105.- La Comisión tendrá las funciones siguientes:\nLey del Sistema Estatal de Seguridad Ciudadana de Baja California. Página 60\n.\nActualización Legislativa.\nÚltima Reforma P.O. No. 54, Índice, 05-Sep-2025\nI.- Una vez recibida la investigación administrativa practicada por la Contraloría\nInterna; conocer y resolver los procedimientos de separación definitiva por falta de requisitos de permanencia y por cualquiera otro de los casos previstos en esta ley o remoción del cargo, por incurrir en responsabilidad administrativa;\nII.- Resolver sobre la suspensión preventiva del Miembro al inicio del procedimiento de separación definitiva o de remoción del cargo; o en su caso confirmar la decretada por la\nContraloría Interna;\nIII.- Otorgar condecoraciones, promociones y estímulos conforme a la disponibilidad presupuestal y\nIV.- Las demás que sean necesarias para el cumplimiento de sus atribuciones.\nARTÍCULO 106.- La Comisión velará por la honorabilidad y reputación de las\nInstituciones Policiales y combatirá con energía las conductas lesivas que afecten a la comunidad, a la Institución Policial o a su imagen ante la comunidad.\nPara tal efecto gozará de la más amplia facultad para examinar los expedientes u hojas de servicio de los Miembros y practicar las diligencias que le permitan allegarse de elementos necesarios al dictar resolución en los procedimientos de separación definitiva por falta de requisitos de permanencia y demás casos previstos en esta ley o de remoción del cargo, por responsabilidad administrativa.\nARTÍCULO 107.- La integración, organización y funcionamiento de la Comisión se establecerá en el reglamento que expida el Ejecutivo Estatal, la Secretaría, la Fiscalía\nGeneral y los municipios, en sus respectivos ámbitos de competencia.\nPárrafo Reformado\nLa Comisión deberá contemplar representantes de las unidades operativas de investigación, prevención, reacción de las Instituciones Policiales así como de los Órganos\nInternos de Control de las instituciones de seguridad pública previstas en la presente Ley.\nArtículo Reformado\nCAPÍTULO III\nSECCIÓN PRIMERA\nARTÍCULO 108.- Los fines de la Carrera Policial son:\nI.- Garantizar el desarrollo institucional y asegurar la estabilidad en el empleo, con integrantes de las Instituciones Policiales;\nLey del Sistema Estatal de Seguridad Ciudadana de Baja California. Página 61\n.\nActualización Legislativa.\nÚltima Reforma P.O. No. 54, Índice, 05-Sep-2025\nII.- Promover la responsabilidad, honradez, diligencia, eficiencia y eficacia en el desempeño de las funciones y en la óptima utilización de los recursos de las Instituciones;\nIII.- Fomentar la vocación de servicio y el sentido de pertenencia mediante la motivación y el establecimiento de un adecuado sistema de promociones que permita satisfacer las expectativas de desarrollo profesional y reconocimiento de los integrantes de las Instituciones Policiales;\nIV.- Instrumentar e impulsar la capacitación y profesionalización permanente de los\nIntegrantes de las Instituciones Policiales para asegurar la lealtad institucional en la prestación de los servicios; y\nV.- Los demás que establezcan las disposiciones que deriven de esta Ley.\nARTÍCULO 109.- La Carrera Policial es el sistema de carácter obligatorio y permanente, conforme al cual se establecen los lineamientos que definen los procedimientos de reclutamiento, selección, ingreso, formación, certificación, permanencia, evaluación, promoción y reconocimiento; así como la separación o baja del servicio de los integrantes de las Instituciones Policiales.\nARTÍCULO 110.- El servicio policial de carrera es el mecanismo institucional para garantizar la igualdad de oportunidades con base en el mérito y con el fin de impulsar el desarrollo de la función pública para beneficio de la sociedad, constituyéndose en un instrumento de profesionalización de la seguridad pública.\nARTÍCULO 111.- La Carrera Policial comprende el grado policial, la antigüedad, las insignias, condecoraciones, estímulos y reconocimientos obtenidos, el resultado de los procesos de promoción, así como el registro de las correcciones disciplinarias y sanciones que, en su caso, haya acumulado el integrante. Se regirá por las normas mínimas siguientes:\nI.- Las Instituciones Policiales deberán consultar los antecedentes de cualquier aspirante en el Registro Nacional y en el Registro Estatal, antes de que se autorice su ingreso a las mismas;\nConstituye, asimismo, impedimento particular para el ingreso, contar con antecedentes penales de Violencia Familiar, Agresión Sexual o de Deudor Alimentario\nMoroso;\nII.- Todo aspirante deberá tramitar, obtener y mantener actualizado el Certificado\nÚnico Policial, que expedirán los Centros de Control de Confianza del Estado;\nLey del Sistema Estatal de Seguridad Ciudadana de Baja California. Página 62\n.\nActualización Legislativa.\nÚltima Reforma P.O. No. 54, Índice, 05-Sep-2025\nIII.- Ninguna persona podrá ingresar a las Instituciones Policiales si no ha sido debidamente certificado y registrado en el Sistema Nacional;\nFracción Reformada\nIV.- Sólo ingresarán y permanecerán en las Instituciones Policiales, aquellos aspirantes e integrantes que cursen y aprueben los programas de formación, capacitación y profesionalización;\nEs requisito de ingreso particular haber cursado y aprobado al menos un curso en materia de derechos humanos, con énfasis en perspectiva de género y de prevención de violencia contra la mujer.\nV.- La permanencia de los integrantes en las Instituciones Policiales está condicionada al cumplimiento de los requisitos que determine esta Ley y demás disposiciones aplicables;\nVI.- Los méritos de los integrantes de las Instituciones Policiales serán evaluados por las Comisiones para determinar las promociones;\nVII.- Para la promoción de los integrantes de las Instituciones Policiales se deberán considerar, por lo menos, los resultados obtenidos en los programas de profesionalización, los méritos demostrados en el desempeño de sus funciones y sus aptitudes de mando y liderazgo;\nVIII.- Se determinará un régimen de estímulos y previsión social que corresponda a las funciones de los integrantes de las Instituciones Policiales;\nIX.- Los Miembros podrán ser cambiados de adscripción, con base en las necesidades del servicio, en los términos que se prevean el reglamento de la presente ley y demás reglamentos respectivos;\nEl cambio de adscripción o funciones de los Miembros estará sujeto al cumplimiento de las condiciones y requisitos siguientes:\nPárrafo Adicionado\na) Solicitud por escrito del superior jerárquico que requiere el cambio de adscripción o de funciones por necesidades del servicio;\nInciso Adicionado\nb) Observar en el cambio de adscripción las previsiones siguientes:\nLa notificación por escrito a los Miembros del cambio de adscripción cuando:\nPárrafo Adicionado\n1. Sea a una distancia mayor de 80 kilómetros del centro de trabajo al que se encuentre adscrito y preste sus servicios, y\nLey del Sistema Estatal de Seguridad Ciudadana de Baja California. Página 63\n.\nActualización Legislativa.\nÚltima Reforma P.O. No. 54, Índice, 05-Sep-2025\nNumeral Adicionado\n2. Sea por más de 30 días o más o, en forma permanente.\nNumeral Adicionado\nEl oficio de notificación de cambio de adscripción deberá contener en todos los casos el tiempo de duración.\nPárrafo Adicionado\nInciso Adicionado\nc) Se preferirá hacer el cambio de adscripción de los Miembros al centro de trabajo más cercano;\nInciso Adicionado\nd) Los supuestos y el procedimiento de revisión de Miembros para ser objeto de cambios de adscripción deberán establecerse en el reglamento de esta Ley, así como en los que expidan las autoridades competentes en esta materia, procurando en todos los casos afectar lo menos posible su entorno familiar;\nInciso Adicionado\ne) La ayudantía o apoyo económico para solventar los gastos que represente el cambio de adscripción por tiempo determinado, así como de traslado, hospedaje y alimentación cuando sea a más de 80 kilómetros del centro de trabajo donde se encuentre adscrito y preste sus servicios, y\nInciso Adicionado\nf) La petición de los Miembros de cambio de adscripción solo se podrá realizar por permuta o vacante, siempre y cuando sea a un mismo puesto y función que se desempeña.\nInciso Adicionado\nLas disposiciones reglamentarias que emitan las demás autoridades en la materia deberán prever los requisitos y el procedimiento de cambio de adscripción a partir de las condiciones establecidas en esta Ley.\nPárrafo Adicionado\nFracción Reformada\nX. El cambio de un Miembro de un área operativa a otra de distinta especialidad, requerirá autorización del titular de la Institución Policial, y\nPoliciales. En ningún caso habrá inamovilidad en los cargos administrativos y de dirección.\nEn términos de las disposiciones aplicables, los titulares de las Instituciones Policiales orgánica de las instituciones a su cargo; asimismo, podrán relevarlos libremente, respetando sus grados policiales y derechos inherentes a la Carrera Policial.\nArtículo Reformado\nLey del Sistema Estatal de Seguridad Ciudadana de Baja California. Página 64\n.\nActualización Legislativa.\nÚltima Reforma P.O. No. 54, Índice, 05-Sep-2025\nARTÍCULO 112.- Dentro del Servicio de Carrera de la Policía sólo se podrá ingresar, permanecer y ascender a la categoría o jerarquía inmediata superior y ser separado, en los términos y las condiciones que establecen la Ley General, esta Ley, y el Reglamento correspondiente.\nSECCIÓN SEGUNDA\nSELECCIÓN\nARTÍCULO 113.- La selección es el proceso que consiste en elegir, de entre los aspirantes que hayan aprobado el reclutamiento, a quienes cubran el perfil y la formación requeridos para ingresar a las Instituciones Policiales.\nDicho proceso comprende el periodo de los cursos de formación o capacitación y concluye con la resolución de las instancias correspondientes sobre los aspirantes aceptados.\nSECCIÓN TERCERA\nINGRESO Y PERMANENCIA\nARTÍCULO 114.- El ingreso es el procedimiento de integración de los candidatos a la estructura institucional y tendrá verificativo con el Certificado Único Policial que obtenga al terminar la etapa de formación inicial o capacitación que impartirá el Instituto, el período de prácticas correspondiente y acrediten el cumplimiento de los requisitos previstos en la presente Ley.\nARTÍCULO 115.- La permanencia es el resultado del cumplimiento constante de los requisitos establecidos en la presente Ley para continuar en el servicio activo de las\nInstituciones Policiales.\nARTÍCULO 116.- Son requisitos de ingreso y permanencia en las Instituciones\nPoliciales, los siguientes:\nA. De Ingreso:\nI. Ser ciudadano mexicano por nacimiento en pleno ejercicio de sus derechos políticos y civiles, sin tener otra nacionalidad;\nII. Ser de notoria buena conducta, no haber sido condenado por sentencia irrevocable por delito doloso, ni estar sujeto a proceso penal;\nIII. No tener antecedentes penales por delito doloso en el país o por aquellos que se consideren como tales en el extranjero, ni estar sujeto a proceso penal por delito doloso;\nIV. No estar sujeto a investigación, averiguación previa\nLey del Sistema Estatal de Seguridad Ciudadana de Baja California. Página 65\n.\nActualización Legislativa.\nÚltima Reforma P.O. No. 54, Índice, 05-Sep-2025\nV. En su caso, tener acreditado el Servicio Militar Nacional;\nVI. Acreditar que ha concluido, al menos, los estudios siguientes:\na) En el caso de aspirantes a las áreas de investigación, enseñanza superior o equivalente;\nb) Tratándose de aspirantes a las áreas de prevención, enseñanza media superior o equivalente;\nc) En caso de aspirantes a las áreas de reacción, los estudios correspondientes a la enseñanza media básica;\nVII. Aprobar el concurso de ingreso y los cursos de formación;\nVIII. Contar con los requisitos de edad y el perfil físico, médico y de personalidad que exijan las disposiciones aplicables;\nIX.- Contar con la residencia mínima en el Estado que exijan el reglamento de la\nAcademia;\nX. Aprobar los procesos de evaluación de control de confianza;\nXI. Abstenerse de consumir sustancias psicotrópicas, estupefacientes u otras que produzcan efectos similares;\nXII. No ser afecto al consumo de sustancias psicotrópicas, estupefacientes u otras que produzcan efectos similares;\nXIII. No padecer alcoholismo;\nXIV. Someterse a exámenes para comprobar la ausencia de alcoholismo o el no uso de sustancias psicotrópicas, estupefacientes u otras que produzcan efectos similares;\nXV. No estar suspendido o inhabilitado, ni haber sido destituido por resolución firme como servidor público;\nXVI. No haber sido inhabilitado, separado o removido del cargo de la misma u otra institución policial;\nXVII. Cumplir con los deberes establecidos en esta Ley, y demás disposiciones que deriven de la misma;\nLey del Sistema Estatal de Seguridad Ciudadana de Baja California. Página 66\n.\nActualización Legislativa.\nÚltima Reforma P.O. No. 54, Índice, 05-Sep-2025\nXVIII. Los demás que establezcan otras disposiciones legales aplicables.\nB. De Permanencia:\nI. Ser de notoria buena conducta, no haber sido condenado por sentencia irrevocable por delito doloso;\nII. Estar en pleno ejercicio de sus derechos políticos y civiles;\nIII. No tener antecedentes penales por delito doloso en el país o por aquellos que se consideren delitos en el extranjero;\nFracción Reformada\nIV. Mantener actualizado su Certificado Único Policial;\nV. No superar la edad máxima de retiro y jubilación que establezcan las disposiciones aplicables;\nVI. Acreditar que ha concluido, al menos, los estudios siguientes:\na) En el caso de integrantes de las áreas de investigación, enseñanza superior, equivalente u homologación por desempeño, a partir de bachillerato;\nb) Tratándose de integrantes de las áreas de prevención, enseñanza media superior o equivalente;\nc) En caso de integrantes de las áreas de reacción, los estudios correspondientes a la enseñanza media básica;\nVII. Asistir y aprobar los cursos de formación, capacitación y profesionalización;\nVIII. Aprobar los procesos de evaluación de control de confianza;\nIX. Aprobar las evaluaciones del desempeño;\nX.- No acumular más de dos sanciones administrativas en un año de servicio;\nXI. Participar en los procesos de promoción o ascenso que se convoquen, conforme a las disposiciones aplicables;\nXII. Abstenerse de consumir sustancias psicotrópicas, estupefacientes u otras que produzcan efectos similares, durante o fuera de la prestación del servicio; salvo los casos en médica, avalada por los servicios médicos de las Instituciones;\nLey del Sistema Estatal de Seguridad Ciudadana de Baja California. Página 67\n.\nActualización Legislativa.\nÚltima Reforma P.O. No. 54, Índice, 05-Sep-2025\nXIII. Abstenerse de acudir al servicio con aliento alcohólico, estado de ebriedad, o bien, consumir bebidas alcohólicas durante la prestación del servicio;\nXIV. No padecer adicción a substancias psicotrópicas, estupefacientes u otras que produzcan efectos similares;\nXV. No padecer alcoholismo;\nXVI. Someterse a exámenes para comprobar la ausencia de alcoholismo;\nXVII. Someterse a exámenes médicos, físicos, de personalidad, de conocimientos, de laboratorio, para comprobar el no uso de sustancias psicotrópicas, enervantes, depresivas, estupefacientes u otras que produzcan efectos similares, así como aquéllos que sean necesarios para la debida prestación del servicio;\nXVIII. No estar suspendido preventivamente o inhabilitado, ni haber sido destituido por resolución firme como servidor público;\nXIX.- No ausentarse del servicio sin causa justificada, por un periodo de tres días consecutivos o de cinco días dentro de un término de treinta días;\nXX. No prestar simultáneamente servicios de cualquier carácter en un cuerpo de seguridad pública y privada;\nXXI. No desempeñar otro empleo, cargo, profesión o comisión de cualquier naturaleza en la administración pública de cualquier nivel, así como trabajos o servicios remunerados en instituciones privadas que sean compatibles con la función que se desempeñe; y\nXXII. Las demás que establezcan las disposiciones legales aplicables.\nArtículo Reformado\nARTÍCULO 117.- Las instancias responsables del servicio de carrera policial\nMiembros.\nSECCIÓN CUARTA\nCONDECORACIONES Y ESTÍMULOS\nARTÍCULO 118.- Los Miembros, tendrán derecho a las condecoraciones siguientes:\nI. Al Valor Policial;\nII. A la Perseverancia, y\nLey del Sistema Estatal de Seguridad Ciudadana de Baja California. Página 68\n.\nActualización Legislativa.\nÚltima Reforma P.O. No. 54, Índice, 05-Sep-2025\nIII. Al Mérito.\nIV. En cada caso se otorgará un estímulo económico adicional, ajustándose a las disponibilidades presupuestales y la autorización de portación de la condecoración o distintivo correspondiente.\nARTÍCULO 119.- La Condecoración al Valor Policial consiste en medalla y diploma, se conferirá a quienes salven la vida de una o varias personas o realicen funciones encomendadas por la ley con grave riesgo para su vida o salud.\nARTÍCULO 120.- La Condecoración a la Perseverancia consiste en medalla y diploma, se otorgará a los Miembros que hayan mantenido un expediente ejemplar y cumplan 10, 15, 20 y 25 años de servicio en la Institución Policial.\nARTÍCULO 121.- La Condecoración al Mérito se conferirá a los Miembros, en los siguientes casos:\nI. Al Mérito Tecnológico, cuando se invente, diseñe o mejore algún instrumento, aparato, sistema o método de utilidad para las Instituciones Policiales o para el país;\nII. Al Mérito Ejemplar, cuando se sobresalga en alguna disciplina científica, cultural o artística o deportiva que enaltezca el prestigio y la dignidad de la institución policial, y\nIII. Al Mérito Social, cuando el Miembro se distinga en la prestación de servicios en favor de la comunidad, que mejoren la imagen de la institución policial.\nARTÍCULO 122.- El régimen de estímulos es el mecanismo por el cual las\nInstituciones Policiales otorgan el reconocimiento público a sus Miembros por su asistencia, puntualidad, buena conducta, antigüedad, disposición y eficiencia en el desempeño de sus funciones. constancia que acredite el otorgamiento del mismo, la cual deberá ser integrada a su expediente.\nLas retribuciones económicas, se determinarán en el Reglamento y se otorgarán por acuerdo de la Comisión.\nARTÍCULO 123.- Los estímulos se ajustarán a lo establecido en el Decreto de\nPresupuesto de Egresos y se otorgarán a los Miembros que se hayan distinguido.\nSECCIÓN QUINTA\nPROMOCIÓN\nLey del Sistema Estatal de Seguridad Ciudadana de Baja California. Página 69\n.\nActualización Legislativa.\nÚltima Reforma P.O. No. 54, Índice, 05-Sep-2025\nARTÍCULO 124.- La promoción es el acto mediante el cual se otorga a los Miembros de las Instituciones Policiales, el grado inmediato superior al que ostenten, dentro del orden jerárquico previsto en las disposiciones legales aplicables.\nLas promociones sólo podrán conferirse atendiendo a la normatividad aplicable y cuando exista una vacante para la categoría jerárquica superior inmediato correspondiente a su grado.\nAl Miembro que sea promovido, le será ratificada su nueva categoría jerárquica mediante la expedición de la constancia de grado correspondiente.\nPara ocupar un grado dentro de las Instituciones Policiales se deberán reunir los requisitos establecidos por esta Ley y las disposiciones normativas aplicables.\nARTÍCULO 125.- El titular de cada institución de seguridad pública tramitará las promociones de los miembros del servicio de carrera, considerando los expedientes u hojas de servicios, respetando los derechos adquiridos.\nARTÍCULO 126.- La promoción al grado inmediato superior sólo se considerará dentro de la misma especialidad o servicio, excepto en los casos en los que no haya interesados para cubrir la vacante. Únicamente se concederá la promoción cuando haya plaza disponible. Los beneficios provenientes de una promoción sólo pueden ser renunciados por aquellos a quienes corresponda el derecho a ser promovidos. La renuncia a la promoción no implica la pérdida del empleo, cargo o comisión que desempeñe.\nARTÍCULO 127.- Por ningún motivo se concederán ascensos a los individuos que se encuentren:\nI. Inhabilitados por sentencia judicial ejecutoriada;\nII. Disfrutando de licencia para asuntos particulares;\nIII. No aptos para ejercer el cargo motivo de la promoción, considerando los resultados de las evaluaciones aplicadas, en los términos de esta Ley;\nIV. Sujetos a un proceso penal;\nV. Desempeñando un cargo de elección popular; y\nVI. En cualquier otro supuesto previsto en otras Leyes.\nARTÍCULO 128.- Las promociones se concederán, teniendo en cuenta las circunstancias siguientes:\nLey del Sistema Estatal de Seguridad Ciudadana de Baja California. Página 70\n.\nActualización Legislativa.\nÚltima Reforma P.O. No. 54, Índice, 05-Sep-2025\nI. Perfil y capacidad;\nII. Antigüedad en la corporación;\nIII. Conducta;\nIV. Antigüedad como servidor público;\nV. Los resultados de la evaluación del desempeño y de las pruebas de control de confianza;\nVI. Méritos especiales;\nVII. Cursos de ascenso correspondiente;\nVIII. Cuando haya igualdad en las dos primeras, la antigüedad será las que se tomen en cuenta.\nARTÍCULO 129.- La antigüedad para los elementos se contará desde la fecha en que hayan causado alta en forma ininterrumpida.\nARTÍCULO 130.- No se computará como tiempo de servicio:\nI. El de las licencias ordinarias y extraordinarias, cuando se concedieron para asuntos particulares;\nII. El de las comisiones fuera del servicio de la Institución Policial, y\nFracción Reformada\nIII. El de las suspensiones, en los casos en que éstas sean obstáculos para la concesión del ascenso.\nArtículo Reformado\nSECCIÓN SEXTA\nANTIGÜEDAD\nARTÍCULO 131.- La antigüedad se clasificará y computará para cada uno de los\nMiembros de las Instituciones Policiales, de la siguiente forma:\nI. Antigüedad en el servicio, a partir de la fecha de su ingreso a las Instituciones\nPoliciales, y\nII. Antigüedad en el grado, a partir de la fecha señalada en la constancia de grado correspondiente.\nLey del Sistema Estatal de Seguridad Ciudadana de Baja California. Página 71\n.\nActualización Legislativa.\nÚltima Reforma P.O. No. 54, Índice, 05-Sep-2025\nLa antigüedad contará hasta el momento en que esta calidad deba determinarse para los efectos de la Carrera Policial.\nSECCIÓN SÉPTIMA\nCERTIFICACIÓN\nARTÍCULO 132.- La certificación es el proceso mediante el cual los Miembros de las\nInstituciones Policiales se someten a las evaluaciones periódicas de control y confianza, para comprobar el cumplimiento de los perfiles de personalidad, éticos, socioeconómicos y médicos, en los procedimientos de ingreso, promoción y permanencia. Las Instituciones\nPoliciales contratarán únicamente al personal que cuente con el requisito de certificación expedido conforme a la Ley.\nArtículo Reformado\nARTÍCULO 133.- La certificación tiene por objeto:\nA. Reconocer habilidades, destrezas, actitudes, conocimientos generales y específicos para desempeñar sus funciones, conforme a los perfiles aprobados por el\nConsejo Nacional.\nB. Identificar los factores de riesgo que interfieran, repercutan o pongan en peligro el desempeño de las funciones policiales, con el fin de garantizar la calidad de los servicios, enfocándose a los siguientes aspectos de los Miembros de las Instituciones Policiales:\nI. Cumplimiento de los requisitos de edad y el perfil físico, médico y de personalidad que exijan las disposiciones aplicables;\nII. Observancia de un desarrollo patrimonial justificado, en el que sus egresos guarden adecuada proporción con sus ingresos;\nIII. Ausencia de alcoholismo o el no uso de sustancias psicotrópicas, estupefacientes u otras que produzcan efectos similares;\nIV. Ausencia de vínculos con organizaciones delictivas;\nV. Notoria buena conducta, no haber sido condenado por sentencia irrevocable por delito doloso o no estar sujeto a averiguación previa, investigación, proceso penal o administrativo, ni haber sido inhabilitado, suspendido preventivamente o destituido por resolución firme como servidor, y\nVI. Cumplimiento de los deberes establecidos en esta Ley.\nSECCIÓN OCTAVA\nPROFESIONALIZACIÓN\nLey del Sistema Estatal de Seguridad Ciudadana de Baja California. Página 72\n.\nActualización Legislativa.\nÚltima Reforma P.O. No. 54, Índice, 05-Sep-2025\nARTÍCULO 134.- La Profesionalización es el proceso permanente y progresivo de formación que se integra por las etapas de formación inicial, actualización, promoción, especialización y alta dirección, para desarrollar al máximo las competencias, capacidades y habilidades de los Miembros de las Instituciones Policiales.\nLos planes de estudio para la Profesionalización se integrarán por el conjunto de contenidos estructurados en unidades didácticas de enseñanza y aprendizaje con perspectivas de género, interés superior de la niñez, interculturalidad e interseccionalidad, de acuerdo al programa rector que apruebe el Sistema Nacional.\nPárrafo Reformado\nArtículo Reformado\nCAPÍTULO IV\nCONDICIONES DEL SERVICIO\nARTÍCULO 135.- Las condiciones del servicio de los Miembros consisten en:\nI. Tiempo de la prestación del servicio: Es el lapso durante el cual el Miembro se encuentra a disposición de la Instituciones Policial a fin de atender y cumplir, de manera directa con el ejercicio de la función de seguridad;\nII.- Remuneración: Es la retribución económica que recibe el Miembro con motivo de la prestación del servicio.\nLa remuneración de los Miembros será acorde con la responsabilidad, calidad y riesgo de las funciones en sus rangos y puestos, las comisiones que cumplan y el lugar geográfico donde la realicen; dicha remuneración no podrá ser disminuida durante el ejercicio de su encargo;\nIII. Días de descanso, semanal y periódicos: Es el tiempo durante el cual el Miembro no se encuentra obligado a prestar el servicio. El descanso semanal será con base a la jornada de servicio que haya prestado, acorde al lugar donde preste su servicio o comisión, el descanso periódico será fijado en forma proporcional a la antigüedad, con el goce de los derechos que le otorga esta Ley;\nIV.- Licencias: El permiso concedido al Miembro para ausentarse temporalmente de la prestación del servicio, por algún motivo justificado, con o sin derecho a remuneración.\nV.- Seguridad Social: Comprende todas aquellas prerrogativas de salud y las demás\nMiembros, así como a sus familias y dependientes, en los términos del título décimo de la presente ley y demás disposiciones que resulten aplicable.\nLey del Sistema Estatal de Seguridad Ciudadana de Baja California. Página 73\n.\nActualización Legislativa.\nÚltima Reforma P.O. No. 54, Índice, 05-Sep-2025\nLa persona titular del Poder Ejecutivo, la Secretaría, la Fiscalía General y los\nMunicipios, en sus respectivos ámbitos de competencias, reglamentarán las condiciones del servicio.\nPárrafo Reformado\nArtículo Reformado\nCAPÍTULO V\nDERECHOS Y OBLIGACIONES DE LOS MIEMBROS\nSECCIÓN PRIMERA\nDERECHOS\nARTÍCULO 136.- Son derechos de los Miembros de las Instituciones Policiales del\nEstado y de los Municipios las siguientes:\nI.- Percibir una remuneración por la prestación efectiva del servicio y acorde a las características del mismo;\nII.- En su caso, percibir una retribución económica extraordinaria a la remuneración que le corresponda por la prestación del servicio en determinada comisión, la cual será otorgada únicamente durante el periodo de la misma;\nLa retribución económica extraordinaria, no formará parte de la remuneración que le corresponda por la prestación del servicio habitual y será establecida de conformidad con la disponibilidad presupuestal asignada para este rubro, así como la disponibilidad de horario, funciones desempeñadas y el grado jerárquico del Miembro;\nIII.- Ser merecedor de respeto por parte de sus superiores jerárquicos;\nIV.- Recibir la dotación de armas, municiones, uniformes y diversos equipos que deberán portar en el ejercicio de sus funciones, procurando mantenerlos en un estado apropiado para su uso y manejo; independientemente del desgaste y su periodo de vida útil del propio material o equipo.\nV.- Recibir asesoría y defensa jurídica de la Defensoría Pública del Estado, cuando así lo solicite el Miembro, en caso de ser sujeto a los procedimientos de separación definitiva, de aplicación de responsabilidad administrativa o jurisdiccionales;\nVI.- Ser recluido en áreas que garanticen su integridad física, tratándose de prisión preventiva. En el caso de compurgación de penas, las autoridades competentes tomarán las como Miembro, Ley del Sistema Estatal de Seguridad Ciudadana de Baja California. Página 74\n.\nActualización Legislativa.\nÚltima Reforma P.O. No. 54, Índice, 05-Sep-2025\nVII.- Contar con los servicios de seguridad social que las instituciones de seguridad publica establezcan en favor de los Miembros, de sus familiares o personas que dependan económicamente de ellos;\nVIII.- Recibir apoyo terapéutico, médico, psicológico, psiquiátrico, de trabajo social o de cualquier disciplina o especialidad que requiera por afectaciones o alteraciones que sufra a consecuencia del desempeño de sus funciones, a través de programas, tratamientos, terapias y seguimiento en periodos semestrales permanentes con motivo de la prestación del servicio.\nIX.- Obtener beneficios sociales, culturales, deportivos, recreativos y de cualquier especie que contribuyan a mejorar sus condiciones de vida personal y al fortalecimiento de los lazos de unión familiar;\nX.- Participar en los concursos de promociones para ascensos y obtener estímulos económicos, reconocimientos y condecoraciones, así como gozar de un trato digno y decoroso por parte de sus superiores jerárquicos;\nXI.- Participar, a invitación de instituciones educativas públicas como instructores técnicos; así como, en la formulación de programas de capacitación, acondicionamiento y adiestramiento, de acuerdo con sus aptitudes, habilidades y competencias;\nXII.- Gozar de los apoyos necesarios para contar con una adecuada preparación académica y de facilidades para proseguir con sus estudios desde el nivel básico hasta el de carácter profesional;\nXIII.- Los demás que les confieran las Leyes y reglamentos de la materia.\nSECCIÓN SEGUNDA\nOBLIGACIONES\nARTÍCULO 137.- Con el objeto de garantizar el cumplimiento de los principios constitucionales de legalidad, objetividad, eficiencia, profesionalismo, honradez y respeto a los derechos humanos, los integrantes de las Instituciones Policiales se sujetarán a las siguientes obligaciones:\nI.- Conducirse siempre con dedicación y disciplina, así como con apego al orden\nII.- Observar un trato respetuoso con todas las personas, debiendo abstenerse de ejercicio de sus derechos constitucionales y con carácter pacífico realice la población;\nLey del Sistema Estatal de Seguridad Ciudadana de Baja California. Página 75\n.\nActualización Legislativa.\nÚltima Reforma P.O. No. 54, Índice, 05-Sep-2025\nIII.- Actualizarse en el empleo de métodos de investigación que garanticen la recopilación técnica y científica de evidencias;\nIV.- Participar en operativos y mecanismos de coordinación con otras Instituciones de\nSeguridad Pública, así como brindarles, en su caso, el apoyo que conforme a derecho proceda;\nV.- Informar al superior jerárquico, de manera inmediata, las omisiones, actos indebidos o constitutivos de delito, de sus subordinados o iguales en categoría jerárquica;\nVI.- Fomentar la disciplina, responsabilidad, decisión, integridad, espíritu de cuerpo y profesionalismo, en sí mismo y en el personal bajo su mando;\nVII.- Abstenerse de realizar conductas que desacrediten su persona o la imagen de las Instituciones, dentro o fuera del servicio;\nVIII.- Obedecer las órdenes de los superiores jerárquicos o de quienes ejerzan sobre él funciones de mando y cumplir con todas sus obligaciones, realizándolas conforme a derecho;\nIX.- Participar en operativos de coordinación con otras corporaciones policiales, así como brindarles, en su caso, el apoyo que conforme a derecho proceda;\nX.- Mantener en buen estado el armamento, material, municiones y equipo que se le asigne con motivo de sus funciones, haciendo uso racional de ellos sólo en el desempeño del servicio;\nXI.- Abstenerse de asistir uniformado a bares, cantinas, centros de apuestas o juegos, u otros centros de este tipo, si no media orden expresa para el desempeño de funciones o en casos de flagrancia;\nXII.- Guardar el respeto debido a todo superior jerárquico, subordinado, de igual jerarquía, y demás personal dentro y fuera del servicio;\nXIII.- Acatar las instrucciones, requerimientos y resoluciones que reciba de la\nContraloría Interna o de la Comisión;\nXIV.- No usar vehículos de motor de estancia ilegal en el país, que no tengan la documentación oficial vigente para circular en el Estado, en el cumplimiento de su servicio;\nXV.- Portar la credencial médica de identificación correspondiente;\nLey del Sistema Estatal de Seguridad Ciudadana de Baja California. Página 76\n.\nActualización Legislativa.\nÚltima Reforma P.O. No. 54, Índice, 05-Sep-2025\nXVI.- Dar aviso por escrito a la Institución Policial de cualquier cambio de domicilio en un plazo no mayor a quince días de que ello acontezca;\nXVII.- Portar el uniforme e identificación oficial durante la prestación del servicio;\nXVIII.- No portar ni utilizar aparatos de radiocomunicación o cualquier otro aparato de comunicación diverso al asignado oficialmente durante la prestación del servicio; la portación y uso de teléfono celular en la prestación del servicio solo estará permitido cuando sea para los efectos previstos en el artículo 17 de la Ley Nacional del Registro de Detenciones; los miembros que en la prestación del servicio hagan una utilización indebida podrán ser sujetos de responsabilidades ulteriores;\nFracción Reformada\nXIX.- Acreditar que conoce esta Ley, su reglamento y demás leyes aplicables y relativas al servicio de Seguridad Pública;\nXX.- Atender con diligencia la solicitud de informe, queja o auxilio de la ciudadanía, o de sus propios subordinados, excepto cuando la petición rebase su competencia, en cuyo caso deberá turnarlo al área que corresponda;\nXXI.- Preservar la secrecía de los asuntos que por razón del desempeño de su función conozcan, en términos de las disposiciones aplicables;\nXXII.- Prestar auxilio a las personas amenazadas por algún peligro o que hayan sido víctimas u ofendidos de algún delito, así como brindar protección a sus bienes y derechos.\nSu actuación será congruente, oportuna y proporcional al hecho. Tratándose de las mujeres, adolescentes, niñas y niños víctimas, el auxilio se prestará con perspectiva de género y con la debida diligencia, lo cual implica actuar oportunamente y salvaguardando en todo momento su seguridad para evitar el contacto del o las personas agresoras. Las acciones para su resguardo y protección se implementarán de conformidad con la Ley General de\nAcceso de las Mujeres a una Vida Libre de Violencia, la Ley de Acceso de las Mujeres a una\nVida Libre de Violencia para el Estado de Baja California y el Código Nacional de\nProcedimientos Penales;\nFracción Reformada\nXXIII.- Cumplir sus funciones con absoluta imparcialidad y sin discriminación alguna;\nXXIV.- Abstenerse en todo momento de infligir o tolerar actos de tortura, aún cuando se trate de una orden superior o se argumenten circunstancias especiales, tales como amenaza a la Seguridad Pública, urgencia de las investigaciones o cualquier otra; al conocimiento de ello, lo denunciará inmediatamente ante la autoridad competente;\nXXV.- Desempeñar su misión sin solicitar ni aceptar compensaciones, dadivas, pagos o gratificaciones distintas a las previstas legalmente. En particular se opondrán a\nLey del Sistema Estatal de Seguridad Ciudadana de Baja California. Página 77\n.\nActualización Legislativa.\nÚltima Reforma P.O. No. 54, Índice, 05-Sep-2025 cualquier acto de corrupción y, en caso de tener conocimiento de alguno, deberán denunciarlo;\nXXVI.- Abstenerse de ordenar o realizar la detención de persona alguna sin cumplir con los requisitos previstos en los ordenamientos constitucionales y legales aplicables;\nXXVII.- Velar por la vida e integridad física de las personas detenidas;\nXXVIII.- Utilizar los protocolos de investigación y de cadena de custodia adoptados por las Instituciones de Seguridad Pública;\nXXIX.- Preservar, conforme a las disposiciones aplicables, las pruebas e indicios de probables hechos delictivos o de faltas administrativas de forma que no pierdan su calidad probatoria y se facilite la correcta tramitación del procedimiento correspondiente;\nXXX.- Abstenerse de disponer de los bienes asegurados para beneficio propio o de terceros;\nXXXI.- Someterse a evaluaciones periódicas para acreditar el cumplimiento de sus requisitos de permanencia, así como obtener y mantener vigente la certificación respectiva;\nXXXII.- Cumplir y hacer cumplir con diligencia las órdenes que reciba con motivo del desempeño de sus funciones, evitando todo acto u omisión que produzca deficiencia en su cumplimiento;\nXXXIII.- Inscribir las detenciones en el Registro Administrativo de Detenciones conforme a las disposiciones aplicables;\nXXXIV.- Abstenerse de sustraer, ocultar, alterar o dañar información o bienes en perjuicio de las Instituciones o patrimonio público;\nXXXV.- Abstenerse, conforme a las disposiciones aplicables, de dar a conocer por cualquier medio a quien no tenga derecho, documentos, registros, imágenes, constancias, estadísticas, reportes o cualquier otra información reservada o confidencial de la que tenga conocimiento en ejercicio y con motivo de su empleo, cargo o comisión;\nXXXVI.- Abstenerse de introducir a las instalaciones de sus instituciones bebidas embriagantes, sustancias psicotrópicas, estupefacientes u otras sustancias adictivas de carácter ilegal, prohibido o controlado, salvo cuando sean producto de detenciones, cateos, aseguramientos u otros similares, y que previamente exista la autorización correspondiente;\nXXXVII.- Abstenerse de consumir, dentro o fuera del servicio, sustancias psicotrópicas, estupefacientes u otras sustancias adictivas de carácter ilegal, prohibido o controlado, salvo los casos en que el consumo de los medicamentos controlados sea\nLey del Sistema Estatal de Seguridad Ciudadana de Baja California. Página 78\n.\nActualización Legislativa.\nÚltima Reforma P.O. No. 54, Índice, 05-Sep-2025 autorizado mediante prescripción médica, avalada por los servicios médicos de las\nInstituciones;\nXXXVIII.- Abstenerse de consumir en las instalaciones de sus instituciones o en actos del servicio, bebidas embriagantes;\nXXXIX.- No permitir que personas ajenas a sus instituciones realicen actos inherentes a las atribuciones que tenga encomendadas. Asimismo, no podrá hacerse acompañar de dichas personas al realizar actos del servicio, y\nXL. Registrar en el Informe Policial Homologado los datos de las actividades e investigaciones que realice;\nXLI.- Remitir a la instancia que corresponda la información recopilada, en el cumplimiento de sus misiones o en el desempeño de sus actividades, para su análisis y registro.\nAsimismo, entregar la información que le sea solicitada por otras Instituciones de\nSeguridad Pública, en los términos de las leyes correspondientes;\nXLII.- Apoyar a las autoridades que así se lo soliciten en la investigación y persecución de delitos, así como en situaciones de grave riesgo, catástrofes o desastres; ejecutar los mandamientos judiciales y ministeriales;\nXLIII.- Obtener y mantener actualizado su Certificado Único Policial;\nXLIV.- Responder, sobre la ejecución de las órdenes directas que reciba, a un solo superior jerárquico, por regla general, respetando preponderantemente la línea de mando;\nXLV.- No poner en peligro a cualquier persona que preste sus servicios para la de imprudencia, descuido y negligencia;\nXLVI.- No usar vehículos que no le hayan sido asignados oficialmente para el cumplimiento del servicio, sin placas o con placas que no le correspondan, robados o recuperados, o cuya estancia en el país sea ilegal;\nXLVII.- Abstenerse de presentar documentación, información falsa o alterada ante cualquier autoridad en el desempeño de su función;\nXLVIII.- No desempeñar ningún otro empleo o comisión pública o privada o que por su naturaleza le impida prestar debidamente el servicio;\nLey del Sistema Estatal de Seguridad Ciudadana de Baja California. Página 79\n.\nActualización Legislativa.\nÚltima Reforma P.O. No. 54, Índice, 05-Sep-2025\nXLIX.- Impedir que los hechos delictuosos de que tuviere conocimiento, dentro o fuera del ejercicio de sus funciones, se lleven a consecuencias ulteriores;\nL.- Recabar los datos de los testigos, de la víctima u ofendido del delito, del presunto responsable, y terceros que tuvieren relación con los probables hechos delictivos o con las faltas administrativas;\nLI.- Hacer entrega inmediata de los asuntos bajo su responsabilidad, uniforme, placa, y demás equipo de cargo recibido para el desempeño de sus funciones, en los casos de suspensión, remoción y separación del cargo;\nLII.- Hacer uso racional del armamento, material, municiones y equipo asignado en el desempeño de sus funciones;\nLIII.- En los casos de flagrancia, detener al presunto responsable de los hechos presuntamente delictuosos;\nFracción Reformada\nLIV. Proporcionar y cumplimentar medidas u órdenes de protección de las mujeres, adolescentes, niñas y niños, en términos de lo dispuesto en la Ley General de Acceso de las\nMujeres a una Vida Libre de Violencia, la Ley de Acceso de las Mujeres a una Vida Libre de\nViolencia para el Estado de Baja California y el Código Nacional de Procedimientos Penales; y,\nFracción Adicionada, recorriéndose la subsecuente\nLV.- Las demás que establezcan las disposiciones legales aplicables.\nArtículo Reformado\nCAPÍTULO VI\nRÉGIMEN DISCIPLINARIO\nSECCIÓN PRIMERA\nPRINCIPIOS DE ACTUACIÓN\nARTÍCULO 138.- La actuación de los Miembros de las Instituciones Policiales se regirá por los principios previstos en el artículo 21 de la Constitución Política de los Estados\nUnidos Mexicanos y en la Ley General.\nPárrafo Reformado\nLa disciplina comprende el aprecio de sí mismo, la pulcritud, los buenos modales, el rechazo a los vicios, la puntualidad en el servicio, la exactitud en la obediencia, el escrupuloso respeto a las leyes y reglamentos, así como a los derechos humanos.\nPoliciales, por lo que sus Miembros deberán sujetar su conducta a la observancia de las\nLey del Sistema Estatal de Seguridad Ciudadana de Baja California. Página 80\n.\nActualización Legislativa.\nÚltima Reforma P.O. No. 54, Índice, 05-Sep-2025 leyes, órdenes y jerarquías, así como a la obediencia y al alto concepto del honor, de la justicia y de la ética.\nLa disciplina demanda respeto y consideración mutua entre quien ostente un mando y sus subordinados.\nArtículo Reformado\nARTÍCULO 139.- Las Instituciones Policiales ejercerán entre otras las siguientes atribuciones:\nI.- Implementar acciones de prevención de las violencias, faltas administrativas y delitos, manteniendo el orden y paz públicos, fomentando con su actuar la observancia de los principios establecidos por la Constitución Política de los Estados Unidos Mexicanos, la humanos;\nFracción Reformada\nII.- Proteger en todo momento la integridad, propiedades, garantías individuales, derechos y libertades de las personas, así como respetar los derechos humanos;\nIII.- Auxiliar a las autoridades, órganos y organismos de la administración pública, cuando así lo soliciten, para el cumplimiento de sus atribuciones;\nIV.- Auxiliar al Ministerio Público en sus tareas de conformidad con la legislación aplicable;\nV.- Proceder a la detención en los casos de flagrancia del delito y poner inmediatamente a disposición de las autoridades competentes a las personas detenidas, los bienes, objetos o instrumentos que se hayan asegurado y que se encuentren bajo su custodia; lo anterior, en los términos que dispone el artículo 16 de la Constitución Política de los Estados Unidos Mexicanos;\nVI.- Realizar la investigación para la prevención y disuasión de infracciones a la ley;\nVII.- Brindar apoyo y auxilio a la ciudadanía en labores de protección civil cuando así se requiera, así como brindar orientación a víctimas de delito;\nVIII.- Dar cumplimiento a lo dispuesto en el Programa, observando las recomendaciones y sugerencias del Consejo Estatal;\nFracción Reformada\nIX.- Llevar el registro y control estadístico de los delitos contenidos en las leyes;\nX.- Instrumentar los programas, proyectos o acciones para garantizar la seguridad pública, la prevención del delito y de las infracciones administrativas en los municipios;\nLey del Sistema Estatal de Seguridad Ciudadana de Baja California. Página 81\n.\nActualización Legislativa.\nÚltima Reforma P.O. No. 54, Índice, 05-Sep-2025\nXI.- Promover, con el ejemplo, una cultura de la legalidad, de la denuncia ciudadana y de la prevención o autoprotección del delito; y\nXII.- Las demás que establezcan las disposiciones jurídicas aplicables.\nArtículo Reformado\nARTÍCULO 140.- Le corresponde a los Municipios expedir la reglamentación que contenga las disposiciones jerárquicas, de estructura normativa, operativas, administrativas, principios de organización y funcionamiento, de organización territorial, mandos administrativos y operativos, patrullaje, vigilancia, dirección y disciplina del régimen interno de la Policía Municipal, con sujeción a las disposiciones contenidas en esta Ley.\nARTÍCULO 141.- Las Instituciones Policiales exigirán de sus Miembros el más estricto cumplimiento del deber, a efecto de salvaguardar la integridad y los derechos de las personas, prevenir las violencias y la comisión de delitos, y preservar las libertades, el orden y la paz públicos.\nArtículo Reformado\nARTÍCULO 142.- El régimen disciplinario se ajustará a los principios establecidos en la Constitución Política de los Estados Unidos Mexicanos, la presente Ley y los ordenamientos legales aplicables y comprenderá los deberes, las sanciones y los procedimientos para su aplicación.\nSECCIÓN SEGUNDA\nSANCIONES\nARTÍCULO 143.- Los Miembros de las Instituciones Policiales serán objeto de aplicación de las sanciones cuando incumplan con alguna de sus obligaciones.\nARTÍCULO 144.- Las sanciones serán:\nI. Apercibimiento. - Consiste en la llamada de atención que el superior jerárquico realice al elemento de la institución policial responsable de la falta, exhortándolo a que evite la repetición de la misma, debiendo constar por escrito en el expediente del sancionado;\nII. Amonestación: Es el acto por el cual se advierte de manera escrita a un elemento de la institución policial, que incumplió con alguna obligación exhortándolo a corregirse;\nIII. Arresto: Es la privación temporal de la libertad hasta por treinta y seis horas, que sufre el Miembro que incumplió con alguna obligación. El arresto deberá emitirse por escrito, especificando el motivo, duración y lugar en que deberá cumplirse;\nIV. Cambio de adscripción y funciones: Consiste en el cambio del lugar donde el\nMiembro presta el servicio en forma permanente, y en su caso, las funciones a realizar. No\nLey del Sistema Estatal de Seguridad Ciudadana de Baja California. Página 82\n.\nActualización Legislativa.\nÚltima Reforma P.O. No. 54, Índice, 05-Sep-2025 será considerada como corrección disciplinaria, el cambio de adscripción y de funciones decretado por razón de las necesidades propias del servicio;\nV. Suspensión temporal: Es la interrupción de funciones impuesta al Miembro de quince días hasta tres meses. El Miembro debe hacer entrega del equipo de cargo puesto a su disposición y de los asuntos bajo su responsabilidad. El Miembro será privado de su derecho a recibir remuneración, ser sujeto de promociones, ascensos o reconocimientos, así como a prestar el servicio;\nVI. Remoción del cargo: Que consiste en la terminación de la relación administrativa entre los Miembros y las Instituciones de Seguridad Pública decretada mediante el procedimiento de responsabilidad administrativa y\nVII. Inhabilitación: Consiste en el impedimento para desempeñar cualquier cargo público hasta por diez años.\nARTÍCULO 145.- El incumplimiento a las fracciones XXI a la LIII del artículo 137 dará lugar a responsabilidad administrativa y se sancionarán con suspensión temporal, remoción del cargo o inhabilitación.\nLa inhabilitación procederá en los casos de:\nI. No acreditar los exámenes de control de confianza y\nII. Ser condenado mediante sentencia que haya causado ejecutoria como responsable en la comisión de algún delito doloso.\nLas sanciones de suspensión temporal y remoción del cargo se aplicarán por las\nComisiones una vez acreditados los hechos y valorados, conforme a derecho, los medios\nLey, registrándose en el expediente personal del infractor la sanción que se le aplique. por responsabilidad civil, penal o administrativa, en que incurran los Miembros de las\nInstituciones Policiales de conformidad con la legislación aplicable. será sancionado con cualquiera de las correcciones disciplinarias previstas en esta Ley. fracciones I, II, III y IV del artículo 137 de la Ley.\nLey del Sistema Estatal de Seguridad Ciudadana de Baja California. Página 83\n.\nActualización Legislativa.\nÚltima Reforma P.O. No. 54, Índice, 05-Sep-2025\nLas correcciones disciplinarias se aplicarán por quien ejerce el mando directo sobre la\nInstitución Policial, por el jefe inmediato del Miembro o por quien se determine en los reglamentos en su caso.\nEl procedimiento mediante el cual se sustanciarán y aplicarán las correcciones disciplinarias será determinado vía reglamento.\nDichos reglamentos podrán prever las medidas preventivas que se estimen necesarias durante su desahogo, los casos en que se ordenará y levantará su aplicación, así como las consecuencias que se generarán cuando se haya o no acreditado el incumplimiento de la obligación por parte del Miembro.\nARTÍCULO 147.- Para aplicar las sanciones a que refiere el artículo 144 se deberá tomar en cuenta lo siguiente:\nI. Nivel jerárquico y los antecedentes del Miembro;\nII. Las causas y condiciones que generaron el incumplimiento de la obligación y los medios de ejecución;\nIII. La reincidencia en el incumplimiento de sus obligaciones;\nIV. Daños causados a la Institución policial, a la ciudadanía, a otros miembros, así como al material o equipo de cargo;\nV. Intencionalidad o negligencia; y\nVI. Los demás elementos, circunstancias, condiciones y consecuencias que afecten la debida prestación del servicio.\nSECCIÓN TERCERA\nINVESTIGACIÓN ADMINISTRATIVA\nARTÍCULO 148.- La Contraloría Interna, de manera previa a la substanciación del procedimiento de separación definitiva o de responsabilidad administrativa, deberá realizar preventiva al miembro cuando así lo considere conveniente, a efecto de realizar las diligencias para allegarse de elementos que le permitan, en su caso, solicitar a la Comisión, iniciar el procedimiento correspondiente.\nSECCIÓN CUARTA\nSUSPENSIÓN PREVENTIVA\nLey del Sistema Estatal de Seguridad Ciudadana de Baja California. Página 84\n.\nActualización Legislativa.\nÚltima Reforma P.O. No. 54, Índice, 05-Sep-2025\nARTÍCULO 149.- La Comisión podrá suspender, negar, decretar o ratificar la suspensión preventiva declarada por la Contraloría Interna contra un Miembro que se encuentre sujeto a procedimiento, por los actos u omisiones de los que pueda derivarse responsabilidad administrativa grave o falta de requisitos de permanencia o alguna otra causa de separación definitiva y cuya permanencia en el servicio puedan afectar el procedimiento, institución policial o a la sociedad en general.\nARTÍCULO 150.- Cuando un Miembro se encuentre sujeto a alguna investigación, averiguación previa o procedimiento penal de orden local o federal, órgano de control interno que sea competente, podrá ordenar la suspensión preventiva, a fin de no afectar la investigación, el proceso penal, la Institución Policial, o a la sociedad.\nARTÍCULO 151.- La suspensión preventiva no prejuzga sobre la falta de algún requisito de permanencia o sobre la responsabilidad administrativa o penal que se le imputa al Miembro.\nARTÍCULO 152.- La suspensión preventiva se levantará, cuando así lo resuelva la\nContraloría Interna o la Comisión, según corresponda.\nLa suspensión preventiva declarada por la Contraloría Interna será por el tiempo estrictamente para llevar a cabo investigación administrativa.\nPárrafo Reformado\nLa declarada por la Comisión no podrá extenderse más allá de la citación para la resolución que corresponda o hasta por un plazo de doce meses.\nPárrafo Reformado\nArtículo Reformado\nARTÍCULO 153.- La suspensión preventiva trae como consecuencia separar temporalmente al Miembro de su cargo, así como privarlo de los derechos establecidos en las fracciones I, IV, VI y VIII del artículo 136 de esta Ley.\nPárrafo Reformado\nLa Contraloría Interna y la Comisión están obligadas a informar y notificar servicio, de la suspensión preventiva para los efectos legales correspondientes; igual obligación subsiste cuando se determine levantar la suspensión decretada.\nMiembros el mínimo vital equivalente al 30 % (treinta por ciento) de su ingreso real, el cual que se pertenezca.\nPárrafo Reformado\nArtículo Reformado\nLey del Sistema Estatal de Seguridad Ciudadana de Baja California. Página 85\n.\nActualización Legislativa.\nÚltima Reforma P.O. No. 54, Índice, 05-Sep-2025\nARTÍCULO 154.- En caso de que no se acredite la falta de un requisito de permanencia o se incurra en cualquiera de las hipótesis contenidas en la fracción I del artículo 185 de la Ley, se determine el no ejercicio de la acción penal o la no responsabilidad penal o administrativa, o bien, en cualquiera de estos se declare el sobreseimiento de la causa, se reintegrará al Miembro todos los derechos y percepciones que se le hubiesen privado con motivo de la suspensión preventiva.\nPárrafo Reformado\nNo existirá el derecho del Miembro de percibir remuneración, cuando no preste sus servicios durante el tiempo en que haya sido privado de su libertad, con motivo de una investigación, averiguación previa o procedimiento penal de orden local, federal, u otro similar en el extranjero.\nArtículo Reformado\nARTÍCULO 155.- Le corresponde a la Secretaría verificar que las sanciones descritas en los artículos anteriores y que sean impuestos a los miembros sean debidamente integradas al registro del personal de seguridad Pública, procurando que dicha información conste por escrito y sea actualizada permanentemente.\nPárrafo Reformado\nLas autoridades que apliquen sanciones conforme a lo previsto en esta ley, deberán remitir la información al respecto, de manera inmediata, a la Secretaría.\nPárrafo Reformado\nArtículo Reformado\nSECCIÓN QUINTA\nPROCEDIMIENTO DE SEPARACIÓN DEFINITIVA O DE RESPONSABILIDAD\nADMINISTRATIVA\nARTÍCULO 156.- Los Miembros serán separados definitivamente cuando dejen de reunir alguno de los requisitos de permanencia o incurra en cualquiera de las hipótesis de separación que establece la presente Ley, o suspendidos temporalmente o removidos del cargo cuando incurran en responsabilidad administrativa.\nARTÍCULO 157.- La Contraloría Interna será la encargada de la investigación procedimiento de separación definitiva o de responsabilidad administrativa, remitiéndole el expediente del presunto infractor.\nARTÍCULO 158.- El procedimiento iniciará por acuerdo de la Comisión correspondiente, de acuerdo a lo previsto en la Ley y las disposiciones reglamentarias que correspondan.\nARTÍCULO 159.- Todos los días y horas serán hábiles para la substanciación del procedimiento de separación definitiva o de responsabilidad administrativa.\nLey del Sistema Estatal de Seguridad Ciudadana de Baja California. Página 86\n.\nActualización Legislativa.\nÚltima Reforma P.O. No. 54, Índice, 05-Sep-2025\nARTÍCULO 160.- El acuerdo de inicio del procedimiento de separación definitiva o de responsabilidad administrativa deberá contener por lo menos lo siguiente:\nI.- Lugar, fecha y hora para la celebración de la audiencia, misma que deberá efectuarse dentro de los quince días siguientes a la fecha en que se dicte el acuerdo;\nII.- Motivos que dan origen al procedimiento, y el derecho del Miembro a imponerse de autos a fin de que conozca las imputaciones que se le fincan, y pueda defenderse por sí, o por persona de su confianza; además de los documentales base de la acción, en los que descanse o se funde el procedimiento.\nIII.- El derecho del Miembro a ofrecer pruebas y alegar a lo que su derecho convenga;\nIV.- El apercibimiento, en caso de que en la audiencia el Miembro no señale domicilio en la ciudad para oír y recibir notificaciones, las notificaciones subsecuentes, aún las de carácter personal, se realizarán en los estrados de la Institución Policial y de las Comisiones.\nEn el mismo acuerdo, decretar o ratificar en su caso, la suspensión preventiva declarada por la Contraloría Interna, asimismo ordenará notificar a ésta y al Miembro, cuando menos con cinco días de anticipación, el lugar, fecha y hora para la celebración de la audiencia, apercibiéndosele a este último que, en caso de no comparecer sin causa justificada, se le tendrá por confeso del hecho que se le imputa.\nLa falta de notificación en los términos indicados, obliga a la Comisión a señalar nuevo día y hora para la celebración de la audiencia, misma que deberá realizarse dentro de los quince días siguientes a la fecha que inicialmente se hubiere fijado.\nARTÍCULO 161.- En caso de que en el día de la celebración de la audiencia, el\nMiembro no pueda defenderse por sí o por persona de su confianza, se le asignará un\nDefensor Público.\nArtículo Reformado\nARTÍCULO 162.- Si el Miembro no señala en la audiencia, domicilio en la ciudad para oír y recibir notificaciones, al finalizar ésta, se le hará efectivo el apercibimiento contenido en administrativa en el sentido de que las notificaciones subsecuentes, aún las de carácter personal, se realizarán en los estrados de la Institución Policial de su adscripción.\nARTÍCULO 163.- El Miembro deberá comparecer a la audiencia en forma personal, la Comisión, el Miembro comparecerá al procedimiento en forma escrita, sin necesidad de ratificación.\nARTÍCULO 164.- La celebración de la audiencia constará de cuatro etapas:\nLey del Sistema Estatal de Seguridad Ciudadana de Baja California. Página 87\n.\nActualización Legislativa.\nÚltima Reforma P.O. No. 54, Índice, 05-Sep-2025\nI.- Declaración, ofrecimiento y admisión de pruebas del Miembro;\nII.- Desahogo de pruebas;\nIII.- Alegatos; y\nIV.- Citación para la resolución.\nEn la etapa de declaración, el Miembro rendirá su declaración en forma verbal, tomándose razón de la misma, o por escrito, misma que deberá ratificar en el mismo acto, y deberá versar sobre los hechos que se le imputan.\nEn la declaración que rinda el Miembro, la Comisión tendrá la más amplia facultad para formular las preguntas que estime conducentes para el esclarecimiento de los hechos que se le imputan.\nUna vez rendida la declaración, ofrecerá los medios de prueba que convengan a su defensa; mismos que la autoridad resolverá sobre su admisión o desechamiento.\nARTÍCULO 165.- Las pruebas deben relacionarse en forma precisa con las imputaciones; además, debe expresarse claramente los puntos que se pretenden demostrar con las mismas. Si las pruebas que se ofrecen no cumplen con las condiciones señaladas, no guarden relación inmediata y directa con los hechos que se le imputan, o resulten notoriamente intrascendentes, serán desechadas de plano.\nARTÍCULO 166.- Serán admisibles todos los medios de prueba, excepto la confesional o declaración de parte de las autoridades, así como aquellas contrarias a derecho.\nARTÍCULO 167.- Tratándose de pruebas testimoniales se observará lo siguiente:\nI.- Se podrá admitir hasta tres testigos por cada hecho que se le impute al Miembro, sin embargo, dependiendo de la complejidad o características del caso en concreto, la autoridad a petición de parte interesada podrá admitir un número distinto;\nII.- Cuando el testigo tenga carácter de autoridad, rendirá su testimonio por escrito dentro de un plazo no mayor de 15 días contados a partir del día siguiente en que reciba el interrogatorio;\nIII.- El Miembro estará obligado a presentar directamente a la audiencia a los testigos que para el caso ofrezca, debiendo acompañar el interrogatorio correspondiente y\nLey del Sistema Estatal de Seguridad Ciudadana de Baja California. Página 88\n.\nActualización Legislativa.\nÚltima Reforma P.O. No. 54, Índice, 05-Sep-2025\nIV.- La Comisión podrá desechar las preguntas que, a su juicio, sean capciosas, inconducentes e insidiosas, o aquellas que no tengan relación con el hecho que se le imputa.\nARTÍCULO 168.- La Comisión tendrá la más amplia facultad de formular a los testigos las preguntas que estime conducentes para llegar a la veracidad de los hechos que motivaron el procedimiento.\nARTÍCULO 169.- La prueba pericial versará sobre cuestiones de carácter técnico, científico o artístico. El perito deberá tener título en la especialidad sobre la que deba rendirse el peritaje, si estuviese legalmente reglamentada, si no lo estuviese, o estándolo no fuera posible obtenerlo, podrá nombrarse una persona con conocimientos en la materia.\nARTÍCULO 170.- El Miembro ofrecerá su propio perito, exhibiendo el cuestionario correspondiente, debiendo rendirse el dictamen por escrito dentro de un plazo no mayor de quince días.\nARTÍCULO 171.- Los órganos estatales y municipales estarán obligados a auxiliar a la Comisión en la rendición de dictámenes periciales.\nARTÍCULO 172.- Las pruebas supervenientes podrán presentarse en cualquier etapa del procedimiento hasta antes de dictar resolución, dentro del término de tres días posteriores a que se tuvo conocimiento de la misma. Se admitirán como tales exclusivamente las documentales.\nARTÍCULO 173.- En la etapa de desahogo de pruebas, se tendrán por desahogadas aquellas que no ameriten preparación alguna; y en el caso de aquellas que requieran de diligencia especial, se señalará día y hora para su desahogo.\nEl Miembro tendrá la obligación de proporcionar los medios necesarios para facilitar el desahogo de las pruebas ofrecidas de su parte.\nEsta etapa no excederá del término de veinte días.\nARTÍCULO 174.- Una vez desahogadas las pruebas, se pasará a la etapa de alegatos, que podrán producirse por escrito o en forma verbal del Miembro; y se citará para resolución, la cual deberá dictarse dentro de un plazo de treinta días.\nARTÍCULO 175.- La resolución que emita la Comisión se notificará al órgano de control interno y al Miembro conforme a lo dispuesto en esta Ley.\nARTÍCULO 176.- La Comisión, una vez notificado el Miembro, está obligada a\nLey del Sistema Estatal de Seguridad Ciudadana de Baja California. Página 89\n.\nActualización Legislativa.\nÚltima Reforma P.O. No. 54, Índice, 05-Sep-2025 corresponda, así como al Sistema Estatal de Información, para los efectos legales correspondientes.\nArtículo Reformado\nARTÍCULO 177.- Para hacer cumplir sus determinaciones, la Contraloría Interna y la\nComisión podrán aplicar cualquiera de los medios de apremio siguientes:\nI.- Amonestación;\nII.- Multa hasta por el equivalente a 30 veces la Unidad de Medida y Actualización;\nIII.- Auxilio de la fuerza pública, y\nIV.- Arresto hasta por 36 horas.\nARTÍCULO 178.- La Contraloría Interna y la Comisión podrán disponer la práctica de las diligencias necesarias para garantizar el debido desarrollo de la investigación administrativa y del procedimiento de separación definitiva o de responsabilidad administrativa respectivamente; asimismo, podrá allegarse de todos los medios de prueba que considere necesarios para mejor proveer.\nLa valoración de las pruebas se sujetará a las disposiciones del Código de\nProcedimientos Civiles para el Estado de Baja California.\nSECCIÓN SEXTA\nNOTIFICACIONES\nARTÍCULO 179.- Las notificaciones y citaciones se harán personalmente, por cédula o por estrados.\nSon notificaciones personales:\nI.- La aplicación de correcciones disciplinarias;\nII.- El acuerdo que ordene y aquel que levante la suspensión preventiva;\nIII.- El acuerdo de inicio del procedimiento de separación definitiva o de responsabilidad administrativa;\nIV.- La citación para el desahogo de pruebas;\nV.- La resolución definitiva que recaiga al procedimiento de remoción y de separación definitiva y\nLey del Sistema Estatal de Seguridad Ciudadana de Baja California. Página 90\n.\nActualización Legislativa.\nÚltima Reforma P.O. No. 54, Índice, 05-Sep-2025\nVI.- Las demás que ordene la Contraloría Interna o quien ejerza el mando directo sobre la Institución Policial.\nARTÍCULO 180.- El acuerdo de inicio del procedimiento de separación definitiva, responsabilidad administrativa y la suspensión preventiva, podrá notificarse al Miembro en las instalaciones de las Instituciones Policiales, o en el lugar en que se encuentre.\nEn caso de que el Miembro se niegue a recibir la notificación, se hará constar esta circunstancia asentándose en el acta respectiva, misma que se fijará en los estrados de la\nInstitución Policial y de la Contraloría Interna.\nARTÍCULO 181.- Cuando el notificador no encontrare persona alguna en el domicilio en la primera visita, levantará constancia del hecho, y regresará dentro de las veinticuatro horas siguientes; en el caso de que en la segunda visita, tampoco encuentre persona alguna, se fijará la cédula de notificación en lugar visible del domicilio, y en los estrados de la\nInstitución Policial y de los órganos de control interno que corresponda.\nSi habiéndose levantado constancia de la primera visita, el notificador encontrare al\nMiembro dentro del término concedido para la espera, procederá a entender la diligencia de notificación.\nARTÍCULO 182.- Si el Miembro no vive en el domicilio señalado en el expediente personal o este fuere inexistente, se hará constar esta circunstancia asentándose en el acta respectiva y se realizará la notificación por estrados de la Institución de Seguridad Pública y de la Contraloría Interna.\nARTÍCULO 183.- Las notificaciones que se tengan que realizar a personas diversas a los Miembros, se harán en los términos del Código de Procedimientos Civiles para el Estado de Baja California. Las notificaciones que se deban realizar a los Miembros, diversas y posteriores a las del acuerdo de inicio del procedimiento de remoción y suspensión preventiva, se realizarán en el domicilio que para tales efectos se hubiere señalado por aquellos, siguiendo las reglas establecidas por los artículos 179, 180, 181 y 182. ciudad, las notificaciones subsecuentes, aún las de carácter personal, se realizarán en los estrados de la Institución de Seguridad Pública y de la Contraloría Interna.\nARTÍCULO 184.- Las notificaciones surtirán sus efectos al día siguiente al que se practiquen.\nCAPÍTULO VII\nCONCLUSIÓN DEL SERVICIO E INDEMNIZACIÓN\nLey del Sistema Estatal de Seguridad Ciudadana de Baja California. Página 91\n.\nActualización Legislativa.\nÚltima Reforma P.O. No. 54, Índice, 05-Sep-2025\nARTÍCULO 185.- La conclusión del servicio de un Miembro es la terminación de su nombramiento o la cesación de sus efectos legales por las siguientes causas:\nI.- Separación, por incumplimiento a cualquiera de los requisitos de permanencia, o cuando en los procesos de promoción concurran las siguientes circunstancias:\na) Si hubiere sido convocado a tres procesos consecutivos de promoción sin que haya participado en los mismos, o que habiendo participado en dichos procesos, no hubiese obtenido el grado inmediato superior que le correspondería por causas imputables a él;\nb) Que haya alcanzado la edad máxima correspondiente a su jerarquía, de acuerdo con lo establecido en las disposiciones aplicables.\nII.- Remoción, por incurrir en responsabilidad en el desempeño de sus funciones o incumplimiento de sus deberes, de conformidad con las disposiciones relativas al régimen disciplinario, o\nIII.- Baja, por:\na) Renuncia;\nb) Muerte, o incapacidad permanente, o\nc) Jubilación o retiro.\nAl concluir el servicio el Miembro deberá entregar al funcionario designado para tal efecto, toda la información, documentación, equipo, materiales, identificaciones, valores u otros recursos que hayan sido puestos bajo su responsabilidad o custodia mediante acta de entrega recepción.\nARTÍCULO 186.- En ningún caso procederá la reincorporación, restitución o reinstalación en el servicio del Miembro, cualquiera que sea el resultado del juicio o medio de defensa que hubiera promovido.\nEl Miembro que llegare a obtener resolución que considere injustificada la separación remoción, baja o cualquier otra forma de terminación del servicio o separación definitiva por falta de requisitos de permanencia o por responsabilidad administrativa, recibirá el pago de correspondan, lo que incluirá el pago de la remuneración diaria, beneficios, recompensas, estipendios, dietas, compensaciones o cualquier otro concepto que percibía el Miembro por la prestación de sus servicios, desde que se concretó su separación, remoción, baja o correspondiente.\nPárrafo Reformado\nLey del Sistema Estatal de Seguridad Ciudadana de Baja California. Página 92\n.\nActualización Legislativa.\nÚltima Reforma P.O. No. 54, Índice, 05-Sep-2025\nLa indemnización consiste en la cantidad equivalente a tres meses de la remuneración que gozaba hasta antes de su separación definitiva o remoción del cargo.\nArtículo Reformado\nARTÍCULO 187.- En caso de separación voluntaria, los Miembros tendrán derecho a recibir las condiciones del servicio que se hubieran generado, en los términos de los reglamentos correspondientes.\nCAPÍTULO VIII\nPRESCRIPCIÓN\nARTÍCULO 188.- Prescribirá en un año la facultad para la aplicación de correcciones disciplinarias, contado a partir de que por cualquier medio se tenga conocimiento de que el\nMiembro incumplió alguna de sus obligaciones en los términos de esta Ley.\nARTÍCULO 189.- Prescribe en un año la facultad de la Contraloría Interna para solicitar a la Comisión el inicio del procedimiento respectivo, contado a partir del día en que por cualquier medio se tenga conocimiento de hechos que hagan presumir que algún\nMiembro ha dejado de cumplir con alguno de los requisitos de permanencia previstos en esta Ley y demás casos contemplados en la misma o que pudiese haber incurrido en responsabilidad administrativa.\nPrescribe en dos años la facultad de la Comisión, para dictar la resolución definitiva y notificarla al afectado contados a partir de la notificación del acuerdo de inicio del procedimiento correspondiente.\nARTÍCULO 190.- La prescripción a que alude el segundo párrafo del artículo anterior se interrumpirá en los siguientes casos:\nI.- Con la celebración de la audiencia administrativa, y\nII.- Con la interposición de algún juicio o medio de defensa en contra de la resolución que se hubiese emitido dentro del Procedimiento.\nCAPÍTULO IX\nCERTIFICACIÓN\nARTÍCULO 191.- En los procesos de evaluación y control de confianza se deberá emitir el Certificado y registro correspondiente a los aspirantes, a los Miembros, Agentes del\nMinisterio Público, Peritos y Elementos de apoyo de la Fiscalía General, así como al personal perteneciente a la Comisión Estatal del Sistema Penitenciario, de conformidad con lo establecido por esta Ley.\nArtículo Reformado\nLey del Sistema Estatal de Seguridad Ciudadana de Baja California. Página 93\n.\nActualización Legislativa.\nÚltima Reforma P.O. No. 54, Índice, 05-Sep-2025\nARTÍCULO 192.- Ninguna persona podrá ingresar o permanecer en la institución de seguridad pública sin contar con el Certificado y registro vigentes.\nARTÍCULO 193.- El Certificado tendrá por objeto acreditar que los servidores públicos son aptos para ingresar o permanecer en cada institución, y que cuentan con los conocimientos, el perfil, las habilidades y las aptitudes necesarias para el desempeño de su cargo.\nARTÍCULO 194.- El Certificado para su validez, deberá otorgarse en un plazo no mayor a sesenta días naturales contados a partir de la conclusión del proceso de certificación, a efecto de que sea ingresado en el Registro Nacional de Personal de las\nInstituciones de Seguridad Pública y al Sistema Estatal de Información. Dicha certificación y registro tendrán una vigencia de tres años.\nArtículo Reformado\nARTÍCULO 195.- Los Miembros, Agentes del Ministerio Público, Peritos y Elementos de apoyo de la Fiscalía General, así como al personal perteneciente a la Comisión Estatal del Sistema Penitenciario, deberán someterse a los procesos de evaluación en los términos de la normatividad correspondiente, con seis meses de anticipación a la expiración de la validez de su certificado y registro, a fin de obtener la revalidación de los mismos.\nPárrafo Reformado\nLa revalidación del certificado será requisito indispensable para la permanencia y deberá registrarse para los efectos a que se refiere el artículo anterior.\nArtículo Reformado\nARTÍCULO 196.- La Fiscalía General, para efectos de incorporar a la institución a personas que hayan formado parte de los sistemas de desarrollo profesional de la Fiscalía\nGeneral de la República o de las demás Instituciones de Procuración de Justicia del país, podrá decidir discrecionalmente, el reconocer la vigencia de los certificados expedidos por dichas instituciones o someter a los aspirantes a los procesos de evaluación que establece esta Ley.\nEn todos los casos, se deberán realizar las inscripciones que correspondan en el\nRegistro Nacional del Personal de Seguridad Pública.\nARTÍCULO 197.- La cancelación del certificado de los Miembros, Agentes del\nMinisterio Público, Peritos y Elementos de apoyo, así como al personal perteneciente a la\nComisión Estatal del Sistema Penitenciario procederá:\nPárrafo Reformado\nI.- Al ser separados de su encargo por incumplir con alguno de los requisitos de ingreso o permanencia a que se refiere esta Ley y demás disposiciones aplicables;\nII.- Al ser removidos de su encargo;\nLey del Sistema Estatal de Seguridad Ciudadana de Baja California. Página 94\n.\nActualización Legislativa.\nÚltima Reforma P.O. No. 54, Índice, 05-Sep-2025\nIII.- Por no obtener la revalidación de su Certificado y\nIV.- Por las demás causas que establezcan las disposiciones aplicables.\nArtículo Reformado\nARTÍCULO 198.- Las Instituciones de Seguridad Pública al recibir la notificación de la cancelación de algún certificado deberán hacer la anotación respectiva en el Registro\nNacional correspondiente.\nTÍTULO DÉCIMO\nBASES GENERALES DE LOS SISTEMAS DE SEGURIDAD SOCIAL EN FAVOR DE LOS\nMIEMBROS\nCAPÍTULO I\nDISPOSICIONES GENERALES\nARTÍCULO 199.- La persona titular del Poder Ejecutivo, la Secretaría, la Fiscalía\nGeneral y los Municipios generarán, de acuerdo a sus necesidades y con cargo a sus presupuestos, una normatividad de régimen de seguridad social, de acuerdo a lo previsto en el artículo 123, apartado B, fracción XIII, segundo párrafo, de la Constitución Política de los\nEstados Unidos Mexicanos, atendiendo las bases generales previstas en el presente título.\nPárrafo Reformado\nLas Instituciones de Seguridad Pública deberán garantizar a los Miembros y a la\nAgencia Estatal de Investigación al menos, las prestaciones previstas como mínimas para los trabajadores al servicio del Estado.\nPárrafo Reformado\nArtículo Reformado\nARTÍCULO 200.- Las Instituciones de Seguridad Pública, conforme a lo dispuesto en esta Ley y la Ley General, realizarán y someterán a las autoridades que corresponda, los estudios técnicos pertinentes para la revisión, actualización y fijación de sus tabuladores y las zonas en que éstos deberán regir.\nARTÍCULO 201.- Sin perjuicio de que se establezcan otra clase de medidas dentro de sus respectivos ámbitos de competencia, los municipios del Estado, la persona titular del coparticipación de recursos con la federación, con el fin de implementar y fortalecer el derecho a la seguridad social de los Miembros, sus familiares y dependientes económicos; con lo que se garantice la entrega de manera directa y oportuna, en los porcentajes o formas dispuestos en la normatividad aplicable, respecto a los plazos establecidos para el beneficio de los Miembros.\nArtículo Reformado\nARTÍCULO 202.- Las instituciones de Seguridad Pública podrán determinar vía convenio con la institución de seguridad social correspondiente, el otorgamiento de las\nLey del Sistema Estatal de Seguridad Ciudadana de Baja California. Página 95\n.\nActualización Legislativa.\nÚltima Reforma P.O. No. 54, Índice, 05-Sep-2025 prestaciones de seguridad social en los términos de esta Ley y la demás normatividad aplicable.\nARTÍCULO 203.- El Ejecutivo del Estado podrá celebrar convenios con los Municipios y para subsidiar, en su caso, el pago de remuneraciones a los Miembros.\nARTÍCULO 204.- La persona titular del Poder Ejecutivo, la Secretaría, la Comisión del\nSistema Estatal Penitenciario, Fiscalía General y los Municipios podrán celebrar convenios de coordinación con la finalidad de lograr la homologación en las remuneraciones entre los\nMiembros, considerando que deberá ser proporcional a sus responsabilidades.\nArtículo Reformado\nARTÍCULO 205.- Sólo podrán hacerse retenciones, descuentos o deducciones a la remuneración de los Miembros cuando se trate:\nI.- De deudas contraídas con las instituciones públicas por concepto de anticipo de remuneraciones, pagos hechos con exceso, errores o pérdidas debidamente compradas imputables a los Miembros;\nII.- De los descuentos ordenados por la Institución de Seguridad Social correspondiente;\nIII.- De descuentos ordenados por la autoridad judicial competente que fueren exigidos a los Miembros;\nIV.- Del pago de impuestos consignados en las Leyes Fiscales, Federales y Estatales en atención a la remuneración a su trabajo, el monto total de los descuentos no podrá ser mayor del 30% de la remuneración total, excepto cuando se trate de abonos por créditos, obligaciones alimenticias o anticipos de remuneraciones concedidas por las autoridades públicas correspondientes. En cuyo caso se estará a lo ordenado por la autoridad judicial, tratándose de alimentos o a lo pactado en el acto jurídico respectivo, por el Miembro.\nCAPÍTULO II\nPRESTACIONES DE SEGURIDAD SOCIAL\nARTÍCULO 206.- La Seguridad Social comprende, cuando menos, lo siguiente:\nI.- La afiliación del Miembro, su familia y dependientes económicos a un Instituto de\nSeguridad Social;\nII.- Otorgamiento, colocación, injerto o implantación de piezas, aparatos o prótesis en cumplimiento de su deber o con motivo del desempeño del servicio o comisión; además exigibles, aun fuera del servicio;\nLey del Sistema Estatal de Seguridad Ciudadana de Baja California. Página 96\n.\nActualización Legislativa.\nÚltima Reforma P.O. No. 54, Índice, 05-Sep-2025\nIII.- Tratamiento psicológico, psiquiátrico o neurológico gratuito cuando así lo requiera el Miembro; con independencia de los programas de terapias, asistencia y apoyo especializado que deberán recibir en periodos bimestrales o semestrales permanentes, con motivo de la prestación del servicio;\nIV.- El otorgamiento a los familiares y dependientes que designe el Miembro como beneficiarios, de un seguro de vida o pago póstumo único por muerte en cualquiera de los casos en que éste se encuentre, ya sea por virtud del cumplimiento del servicio, por jubilación, pensión o en retiro; con independencia de las condecoraciones y estímulos económicos que se deban otorgar para el caso de que el Miembro haya fallecido en el desempeño de su labor, salvando o protegiendo la vida de una o varias personas o con motivo de sus funciones;\nV.- Apoyo para elaboración de testamento notarial;\nVI.- El otorgamiento a los familiares y dependientes que designe el Miembro, de un importe por concepto de apoyo para cubrir el total de los gastos funerales; además de la entrega inmediata de los beneficios, prestaciones o estímulos económicos que le correspondan, por motivo del fallecimiento y la terminación de la relación de servicio con la institución policial a la cual se encontraba adscrito;\nVII.- Licencias al Miembro con derecho a remuneración por accidentes y enfermedades profesionales, enfermedades no profesionales y maternidad, paternidad y por contagio en virtud del desempeño de sus funciones o aquellas que se presenten siendo\nMiembro;\nLa licencia sin goce de sueldo y las concedidas en casos de enfermedad o por suspensión de los efectos del nombramiento, se computará como tiempo de servicios en los siguientes casos:\na) Cuando las licencias sean concedidas por un periodo que no exceda de seis meses;\nb) Cuando las licencias se concedan para el desempeño de cargos de elección popular y siempre que los mismos sean remunerados mientras duren dichos cargos, siendo incompatible la acumulación de derechos y computándose sólo el sueldo base del Miembro;\nc) Cuando el Miembro sufra prisión preventiva seguida de sentencia absolutoria, mientras dure la privación de la libertad, y\nd) Cuando el Miembro que tenga encomendado el manejo de fondos, valores o bienes, fuere suspendido por haber aparecido alguna irregularidad en su gestión y que de la\nLey del Sistema Estatal de Seguridad Ciudadana de Baja California. Página 97\n.\nActualización Legislativa.\nÚltima Reforma P.O. No. 54, Índice, 05-Sep-2025 investigación se desprenda una resolución absolutoria, por todo el tiempo que dure la suspensión.\nEn los casos señalados el Miembro deberá pagar la totalidad de las cuotas que establece esta Ley, más los recargos calculados de acuerdo a la Ley de Ingresos vigente, y si falleciere antes de reanudar su servicio y sus beneficiarios tuvieren derecho a pensión, éstos deberán cubrir el importe de esas cuotas y de los recargos respectivos para poder disfrutar de la misma.\nVIII.- En su caso, otorgamiento de una pensión económica vitalicia por jubilación, retiro por edad y tiempo de servicio, invalidez y fallecimiento para el Miembro o para los familiares y dependientes que para tal efecto designe como beneficiarios; con independencia de aquellos beneficios que le sean otorgados por el Instituto de Seguridad Social al cual se encuentre adscrito.\nEsta prestación será otorgada en la forma y términos previstos en el capítulo III de este título.\nIX.- En caso de fallecimiento del Miembro, el otorgamiento a sus descendientes y dependientes menores de dieciocho años de edad el acceso a la educación básica, media superior y superior Pública, a través de becas de estudio;\nX.- El otorgamiento de créditos para que el Miembro pueda obtener vivienda o la obtención de polígonos, espacios, terrenos o predios para pie de casa, que le permita acceder a la construcción de una vivienda. Los cuales podrán ser financiados a partir de aportaciones realizadas de manera bimestral por el Miembro, las cuales no podrán ser mayores al 5% del total de sus percepciones;\nXI.- Cuando tengan hijos cursando la educación básica, al inicio de cada ciclo escolar, los Miembros tienen derecho a recibir una ayuda global anual para útiles escolares, cuyo monto mínimo será de siete días de Salario Mínimo General Vigente y\nXII.- Remuneración anual que deberá pagarse en la primera quincena de diciembre cuarenta días y veinte días durante la primera quincena de enero.\nARTÍCULO 207.- Si con motivo del inicio de un procedimiento de separación definitiva o responsabilidad administrativa se ordena la suspensión preventiva del Miembro, éste, sus aplicables.\nGeneral y Municipios cubrirán al Instituto de Seguridad Social que corresponda, las aportaciones sobre la remuneración base de cotización, asimismo todo Miembro deberá\nLey del Sistema Estatal de Seguridad Ciudadana de Baja California. Página 98\n.\nActualización Legislativa.\nÚltima Reforma P.O. No. 54, Índice, 05-Sep-2025 aportar al Instituto de Seguridad Social que corresponda la cuota obligatoria de la remuneración base, dichas aportaciones se aplicarán en los rubros siguientes:\nPárrafo Reformado\nI.- Para cubrir seguros de enfermedades no profesionales y de Maternidad;\nII.- Para cubrir íntegramente el seguro de accidentes del Servicio y Enfermedades\nProfesionales y\nIII.- El régimen de pensiones.\nArtículo Reformado\nARTÍCULO 209.- La remuneración que se tomará en cuenta para los efectos de esta\nLey, será la remuneración base para cada uno de los puestos de los Miembros, en sus diferentes niveles, consignados en el catálogo general de puestos de la Institución Policial de su adscripción y fijado en el tabulador respectivo.\nLa remuneración base de cotización no será menor a dos ni mayor a veinticinco veces del Salario Mínimo General vigente en la entidad, y se tomarán en cuenta para la determinación del monto de los Seguros, Pensiones y Préstamos que la misma establece.\nCAPITULO III\nPENSIONES\nARTÍCULO 210.- Los Miembros o sus beneficiarios, en su caso, tendrán derecho al acceso de pensiones por jubilación, retiro por edad y tiempo de servicio, invalidez y por fallecimiento.\nARTÍCULO 211.- Tienen derecho a pensión:\nI.- Por jubilación: En los términos previstos por las leyes que regulen el sistema de protección social al que pertenezcan. artículo, sin haber disfrutado de su jubilación, sus beneficiarios disfrutarán a través de la pensión que por Ley les corresponda.\nII.- De retiro por edad y tiempo de servicio: En los términos previstos por las leyes que regulen el sistema de protección social al que pertenezcan, el monto de la pensión se fijará según los años de servicio y los porcentajes del promedio del último sueldo base. El pensiones por jubilación.\nLey del Sistema Estatal de Seguridad Ciudadana de Baja California. Página 99\n.\nActualización Legislativa.\nÚltima Reforma P.O. No. 54, Índice, 05-Sep-2025\nIII.- Por Invalidez: al Miembro que se inhabilite física o mentalmente, de manera permanente o temporal, por causas ajenas al desempeño de su cargo, cualquiera que sea su edad, teniendo por lo menos cinco años de contribuir al Fondo de Pensiones. El otorgamiento de la pensión por invalidez queda condicionado al cumplimiento de los requisitos que establezca la Ley. Si desaparece la invalidez, el Miembro deberá reincorporarse a su servicio, el cual será preferentemente el que resulte acorde a su recuperación. En este último supuesto, si el Miembro es dado de alta se suspenderá la pensión que estuviere disfrutando.\nIV.- Por fallecimiento: Cuando un Miembro fallezca a consecuencia del servicio, sus beneficiarios gozarán de los beneficios que comprende el seguro de vida.\nLos beneficiarios del Miembro que falleciere tendrán derecho a la pensión que le hubiere correspondido a éste por jubilación o edad y tiempo de servicio, a la fecha de su fallecimiento, en el orden señalado en esta Ley, siempre que el Miembro haya cubierto los requisitos a que se refiere este artículo.\nCuando fallezca un jubilado o pensionado, se entregará a sus deudos o a la persona que se encargue de los gastos funerarios, la cantidad equivalente a tres meses de su pensión para gastos de funeral, o en su caso lo que se haya establecido en el seguro de vida.\nAl fallecimiento de un jubilado o pensionado, el beneficiario que haya designado en el testamento o en su caso en el seguro de vida, podrá solicitar el pago del seguro de vida, previo cumplimiento de los requisitos de ley.\nARTÍCULO 212.- No se tomará en cuenta para los efectos de esta Ley, la inhabilitación, invalidez o muerte que provenga de las causas siguientes:\nI.- La que hubiere sido provocada voluntariamente por el integrante, y\nII.- La que resulte a consecuencia del uso o consumo por parte del miembro de bebidas alcohólicas o drogas enervantes o estupefacientes, sin prescripción médica.\nARTÍCULO 213.- Las cuantías de las pensiones aumentarán en los términos del aumento del Índice Nacional de Precios al Consumidor.\nARTÍCULO 214.- Las pensiones sólo podrán ser afectadas por mandato judicial. Será nula toda cesión, enajenación o gravamen sobre las pensiones que esta Ley establece. El\nMiembro que se retire del servicio o sea dado de baja, podrá solicitar la devolución de las aportaciones que haya realizado.\nLey del Sistema Estatal de Seguridad Ciudadana de Baja California. Página 100\n.\nActualización Legislativa.\nÚltima Reforma P.O. No. 54, Índice, 05-Sep-2025\nARTÍCULO 215.- Para el cómputo de los años de servicio, se considerará solamente el tiempo efectivo que el Miembro haya prestado sus servicios a la Institución de Seguridad\nPública de su adscripción.\nARTÍCULO 216.- El tiempo de contribución se acreditará con la constancia que expida el Instituto de Seguridad Social que corresponda, encargado de administrar el Fondo de Pensiones, previa consulta del expediente personal y del sistema de registro que para tal efecto se tenga.\nARTÍCULO 217.- El derecho a disfrutar de pensión concluye:\nI.- Al fallecer el jubilado, pensionado o pensionista.\nII.- Para los hijos de los Miembros, que hayan pasado a ser pensionistas, al cumplir dieciocho años de edad; a menos que se trate de incapacitados, o continúen sus estudios;\nIII. Para la viuda o viudo, si vuelve a contraer nupcias o viviera en concubinato y\nIV.- Para la concubina o concubino si contraen nupcias, viven en nuevo concubinato o por resolución judicial.\nCAPÍTULO IV\nRESPONSABILIDAD Y OBLIGACIONES A CARGO DE LAS INSTITUCIONES\nPOLICIALES\nARTÍCULO 218.- Corresponde a la Institución Policial:\nI.- Mantener actualizada la plantilla de integrantes adscritos a la Institución Policial;\nII.- Informar el nombre de beneficiarios señalados por el Miembro, por orden de prelación;\nIII.- Informar el nombre de los Miembros que se inhabilitan por riesgo, por causas ajenas al servicio, por cesantía, jubilación y muerte a más tardar diez días naturales posteriores al hecho;\nIV.- Enterar a los Institutos de Seguridad Social de las cuotas para pensión retenidas a los Miembros de instituciones policiales;\nV.- Enterar sin dilación las cuotas y aportaciones patronales derivados de la aplicación de esta Ley;\nVI.- Archivar los recibos e importes de las retenciones que debieron hacerse;\nLey del Sistema Estatal de Seguridad Ciudadana de Baja California. Página 101\n.\nActualización Legislativa.\nÚltima Reforma P.O. No. 54, Índice, 05-Sep-2025\nVII.- Las que le señalen la presente Ley y demás disposiciones normativas aplicables.\nARTÍCULO 219.- La Institución de Seguridad Publica deberá remitir al Instituto respectivo, la relación de los Miembros sujetos al pago de cuotas actualizada en los meses de enero y julio correspondientes.\nAsimismo, la Institución de Seguridad Pública enterará al Instituto de Seguridad Social respectivo, de las cuotas y aportaciones dentro de los 10 días naturales posteriores al pago de prestaciones habituales del Miembro y en la fecha en que ocurran:\nI.- Las altas y bajas de los Miembros;\nII.- Las modificaciones de la remuneración base sujeto a descuentos;\nIII.- La iniciación de los descuentos, así como, su terminación y, en su caso, los motivos y justificaciones por los que se haya suspendido el descuento, informando en forma inmediata a la Oficina de Pensiones sobre cualquier circunstancia que impida o retarde el cumplimiento de las órdenes de descuento; y\nIV.- Los nombres de los familiares que los Miembros deben señalar a fin de que disfruten de los beneficios que esta Ley les concede.\nEn todo tiempo, la Institución de Seguridad Pública proporcionará a la Oficina de\nPensiones los datos que le requiera y designará a quien se encargue del cumplimiento de estas obligaciones.\nEl incumplimiento de lo previsto en el presente artículo, será considerado causa de responsabilidad administrativa y se aplicarán las sanciones que al efecto señale la Ley de\nResponsabilidades Administrativas del Estado.\nARTÍCULO 220.- Las Instituciones de Seguridad Pública contarán con un Comité de\nGénero, que vigilará el respeto a los derechos de las mujeres policías y que las mujeres miembros de Instituciones de Seguridad Pública sujetas de la Ley, durante su embarazo, no salud o la del producto de la concepción. Dicho Comité funcionará en los términos que dispongan las disposiciones reglamentarias correspondientes.\nPárrafo Reformado\nLas mujeres embarazadas, disfrutarán de un periodo de incapacidad de noventa días naturales, contados a partir de la fecha de expedición del certificado médico de incapacidad; parto y sesenta después del mismo.\nLey del Sistema Estatal de Seguridad Ciudadana de Baja California. Página 102\n.\nActualización Legislativa.\nÚltima Reforma P.O. No. 54, Índice, 05-Sep-2025\nEn caso de adopción, con fines de adaptación con su menor hijo, la mujer Miembro de\nInstitución Policial, gozará de una licencia de cuarenta y cinco días naturales.\nEn ambos supuestos conservarán el pago íntegro de su remuneración, su cargo o comisión, y en general, no les podrán ser suspendidos o disminuidos sus derechos de seguridad social previstos en la presente Ley.\nArtículo Reformado\nARTÍCULO 221.- Las madres policías durante los seis meses siguientes al vencimiento de la incapacidad por maternidad, disfrutarán de un periodo de lactancia de tres horas distribuidas a lo largo de su rol de servicio o jornada para alimentar a sus hijos; las instituciones de seguridad deben designar sala de lactancia.\nPárrafo Reformado\nCorresponde al Comité de Género, vigilar que se cumpla en todos sus términos lo dispuesto por el presente artículo.\nPárrafo Adicionado\nArtículo Reformado\nCAPÍTULO V\nOTROS BENEFICIOS COMPLEMENTARIOS DE SEGURIDAD SOCIAL\nARTÍCULO 222.- Los Miembros podrán disfrutar de los servicios que brinde el\nInstituto de Seguridad Social respectivo, el cual otorgará todas las facilidades y promoverá con la Institución de Seguridad Pública respectiva los Convenios de Incorporación necesarios para que puedan acceder efectivamente a los beneficios que otorga.\nARTÍCULO 223.- Se podrá conferir a los miembros de Instituciones Policiales una compensación o ayudantía por el riesgo del servicio la cual será determina en la forma y términos que precisen las instituciones de seguridad pública en términos de las disposiciones reglamentarias aplicables.\nARTÍCULO 224.- Las Instituciones de Seguridad Pública podrán celebrar Convenios con personas del sector público, social y privado con el objeto de que los Miembros reciban pases de acceso gratuito o descuentos en actividades sociales, culturales y deportivas. En estos casos, las áreas de recursos humanos en las Instituciones Obligadas darán a conocer los beneficios respectivos, por lo menos cada seis meses.\nCAPÍTULO VI\nCONTROVERSIAS EN LA APLICACIÓN DE LA LEY\nARTÍCULO 225.- Las controversias que se generen con motivo de las prestaciones de seguridad social serán competencia del Tribunal Estatal de Justicia Administrativo, quien\nCalifornia.\nLey del Sistema Estatal de Seguridad Ciudadana de Baja California. Página 103\n.\nActualización Legislativa.\nÚltima Reforma P.O. No. 54, Índice, 05-Sep-2025\nLos acuerdos por los cuales se nieguen, modifiquen, suspendan o revoquen las pensiones a que se refiere esta Ley, podrán recurrirse por los interesados ante el Tribunal\nEstatal de Justicia Administrativa, dentro del término de 15 días hábiles, contados a partir de que se les notifique o se hagan sabedores de dicha resolución. El recurso se desarrollará y resolverá conforme a lo señalado en la legislación aplicable en la materia.\nTRANSITORIOS\nPRIMERO. La presente Ley entrará en vigor al día siguiente de su publicación en el\nPeriódico Oficial del Estado de Baja California, salvo las excepciones previstas en los artículos transitorios subsecuentes.\nSEGUNDO. Se abroga la Ley de Seguridad Pública del Estado de Baja California, publicada en el Periódico Oficial del Estado de Baja California número 38, Tomo CXVI,\nSección I, de fecha 21 de agosto de 2009.\nTERCERO. El Ejecutivo del Estado contará con un plazo de noventa días hábiles, contados a partir de la entrada en vigor del presente Decreto, para expedir el Reglamento de la Ley de Seguridad Pública del Estado de Baja California, excepto en las materias que resulten de competencia reglamentaria a cargo de la Fiscalía General y Ayuntamientos.\nCUARTO. La Fiscalía General, dentro del término de noventa días contados a partir de la entra en vigor del presente Decreto, deberá emitir las disposiciones reglamentarias que en la esfera de su competencia le permitan dar cumplimiento al mismo.\nQUINTO. Los Ayuntamientos contarán con un plazo de noventa días, contados a partir de la entrada en vigor del presente Decreto, para expedir o actualizar los Reglamento\nMunicipales que en la esfera de su competencia le permitan dar cumplimiento al mismo.\nSEXTO. Las disposiciones reglamentarias vigentes a la entrada en vigor del presente\nDecreto seguirán vigentes hasta que se expidan las nuevas siempre que no contravengan al presente Decreto.\nSÉPTIMO. Dentro del plazo de treinta días, contados a partir de la entrada en vigor del presente Decreto, el Ejecutivo del Estado debe instalar el Consejo Estatal de Seguridad\nPública y Paz.\nOCTAVO. Las instituciones de seguridad pública deberán expedir las disposiciones reglamentarias pertinentes, así como cualquier otra normativa idónea para instrumentar un sistema de seguridad social para el retiro, jubilación y demás prestaciones que establece la presente Ley a favor de los Miembros de las Instituciones Policiales Estatales y Municipales, en el plazo de noventa días a partir de la entrada en vigor de este Decreto.\nLey del Sistema Estatal de Seguridad Ciudadana de Baja California. Página 104\n.\nActualización Legislativa.\nÚltima Reforma P.O. No. 54, Índice, 05-Sep-2025\nLas disposiciones reglamentarias deberán prever un apartado especial relativo a la regulación del cambio de adscripción de los miembros de las instituciones policiales que deberán contemplar cuando menos los siguientes aspectos:\nA) La solicitud por escrito del superior jerárquico que lo requiere el cambio de adscripción;\nB) La previsión de que el personal que se cambiara de adscripción, sea del centro de trabajo más cercano.\nC) La previsión de supuestos y procedimiento de revisión de candidatos en los cuales, el cambio de adscripción, afecta en lo menos posible su entorno familiar.\nD) La previsión del derecho de notificación por escritos de cambios de adscripción que sea a más de 80 km del centro de trabajo original donde el elemento presta su servicio por un tiempo, o sea por 30 días o más, o en forma permanente, tendrá que ser determinado, especificando, el tiempo del mismo.\nE) La previsión de la ayudantía para solventar los gastos, de traslado, hospedaje y alimentación de cambios de adscripción que sea a más de 80 km del centro de trabajo original donde el elemento presta su servicio por un tiempo.\nF) La previsión del cambio de adscripción por petición del interesado, siempre y cuando sea, por permuta o una vacante, del mismo puesto que desempeña.\nNOVENO. La Fiscalía General y la Comisión Estatal del Sistema Penitenciario contarán con un plazo de noventa días, contados a partir de la entrada en vigor del presente\nDecreto, para expedir el ordenamiento para la integración, organización y funcionamiento de las instancias encargadas del conocimiento y resolución de los procedimientos de carrera policial y régimen disciplinario.\nDÉCIMO. Las instituciones de seguridad pública deberán realizar las previsiones pertinentes en el Presupuesto de Egresos correspondientes y, en su caso, realizar los presente ley.\nEn ningún caso podrán disminuir para el ejercicio fiscal 2021 los pagos que por sueldos o emolumentos se hayan realizado a policías municipales en el ejercicio anterior, presente ley.\nDÉCIMO PRIMERO. Las solicitudes de Jubilación o pensión de los miembros de instituciones policiales que, a la fecha de expedición de la presente Ley, se encuentren en trámite, se resolverán conforme a lo dispuesto en la Ley que les dio origen.\nLey del Sistema Estatal de Seguridad Ciudadana de Baja California. Página 105\n.\nActualización Legislativa.\nÚltima Reforma P.O. No. 54, Índice, 05-Sep-2025\nDÉCIMO SEGUNDO. Los juicios relacionados con las prestaciones materia de la presente Ley que, a la fecha, se ventilen ante las autoridades jurisdiccionales competentes, se resolverán conforme a lo dispuesto en la Ley que les dio origen.\nDÉCIMO TERCERO. Todas las iniciativas de reforma o adición a la Ley de Seguridad\nPública del Estado de Baja California, incluyendo las iniciativas de Ley relativa a las remuneraciones, prestaciones o condiciones de seguridad social de los cuerpos policiacos que hayan sido presentadas con anterioridad a la emisión del presente Decreto, quedan jurídicamente desestimadas por ministerio de ley, debiéndose estar las mismas al contenido del presente Decreto.\nDADO en Sesión Ordinaria Virtual en la Ciudad de Mexicali, B.C., a los veintidós días del mes de diciembre del año dos mil veinte.\nDIP. EVA GRICELDA RODRÍGUEZ\nPRESIDENTA\n(RÚBRICA)\nDIP. MARÍA LUISA VILLALOBOS ÁVILA\nSECRETARIA\n(RÚBRICA)\nDE CONFORMIDAD CON LO DISPUESTO POR LA FRACCIÓN I DEL ARTÍCULO 49\nCALIFORNIA, IMPRÍMASE Y PUBLÍQUESE.\nMEXICALI, BAJA CALIFORNIA, A LOS VEITIOCHO DÍAS DEL MES DE DICIEMBRE\nDEL AÑO DOS MIL VEITE.\nJAIME BONILLA VALDEZ\nGOBERNADOR DEL ESTADO\n(RÚBRICA)\nAMADOR RODRÍGUEZ LOZANO\nSECRETARIO GENERAL DE GOBIERNO\n(RÚBRICA)\nLey del Sistema Estatal de Seguridad Ciudadana de Baja California. Página 106\n.\nActualización Legislativa.\nÚltima Reforma P.O. No. 54, Índice, 05-Sep-2025\nFue modificada la denominación de la Ley mediante Decreto No. 66, publicado en el\nPeriódico Oficial No. 109, Índice, de fecha 31 de diciembre de 2021, Tomo CXXVIII, expedido por la H. XXIV Legislatura, siendo Gobernadora Constitucional la C. Marina del\nPilar Ávila Olmeda 2021-2027;\nLEY DEL SISTEMA ESTATAL DE SEGURIDAD CIUDADANA DE BAJA CALIFORNIA\nARTÍCULO 1.- Fue reformado mediante Decreto No. 66, publicado en el Periódico Oficial\nNo. 109, Índice, de fecha 31 de diciembre de 2021, Tomo CXXVIII, expedido por la H. XXIV\nLegislatura, siendo Gobernadora Constitucional la C. Marina del Pilar Ávila Olmeda 20212027;\nARTÍCULO 2.- Fue reformado mediante Decreto No. 66, publicado en el Periódico Oficial\nNo. 109, Índice, de fecha 31 de diciembre de 2021, Tomo CXXVIII, expedido por la H. XXIV\nLegislatura, siendo Gobernadora Constitucional la C. Marina del Pilar Ávila Olmeda 20212027;\nARTÍCULO 3.- Fue reformado mediante Decreto No. 66, publicado en el Periódico Oficial\nNo. 109, Índice, de fecha 31 de diciembre de 2021, Tomo CXXVIII, expedido por la H. XXIV\nLegislatura, siendo Gobernadora Constitucional la C. Marina del Pilar Ávila Olmeda 20212027;\nARTÍCULO 4.- Fue reformado mediante Decreto No. 66, publicado en el Periódico Oficial\nNo. 109, Índice, de fecha 31 de diciembre de 2021, Tomo CXXVIII, expedido por la H. XXIV\nLegislatura, siendo Gobernadora Constitucional la C. Marina del Pilar Ávila Olmeda 20212027;\nARTÍCULO 5.- Fue reformado mediante Decreto No. 66, publicado en el Periódico Oficial\nNo. 109, Índice, de fecha 31 de diciembre de 2021, Tomo CXXVIII, expedido por la H. XXIV\nLegislatura, siendo Gobernadora Constitucional la C. Marina del Pilar Ávila Olmeda 20212027;\nFue modificada la denominación mediante Decreto No. 66, publicado en el Periódico Oficial\nNo. 109, Índice, de fecha 31 de diciembre de 2021, Tomo CXXVIII, expedido por la H. XXIV\nLegislatura, siendo Gobernadora Constitucional la C. Marina del Pilar Ávila Olmeda\n2021-2027;\nTÍTULO SEGUNDO\nFue modificada la denominación mediante Decreto No. 66, publicado en el Periódico Oficial\nLegislatura, siendo Gobernadora Constitucional la C. Marina del Pilar Ávila Olmeda\n2021-2027;\nCAPÍTULO I\nDISPOSICIONES GENERALES\nLey del Sistema Estatal de Seguridad Ciudadana de Baja California. Página 107\n.\nActualización Legislativa.\nÚltima Reforma P.O. No. 54, Índice, 05-Sep-2025\nARTÍCULO 6.- Fue reformado mediante Decreto No. 66, publicado en el Periódico Oficial\nNo. 109, Índice, de fecha 31 de diciembre de 2021, Tomo CXXVIII, expedido por la H. XXIV\nLegislatura, siendo Gobernadora Constitucional la C. Marina del Pilar Ávila Olmeda 20212027;\nARTÍCULO 7.- Fue reformado mediante Decreto No. 66, publicado en el Periódico Oficial\nNo. 109, Índice, de fecha 31 de diciembre de 2021, Tomo CXXVIII, expedido por la H. XXIV\nLegislatura, siendo Gobernadora Constitucional la C. Marina del Pilar Ávila Olmeda 20212027;\nARTÍCULO 8.- Fue reformado mediante Decreto No. 66, publicado en el Periódico Oficial\nNo. 109, Índice, de fecha 31 de diciembre de 2021, Tomo CXXVIII, expedido por la H. XXIV\nLegislatura, siendo Gobernadora Constitucional la C. Marina del Pilar Ávila Olmeda 20212027;\nARTÍCULO 9.- Fue reformado mediante Decreto No. 66, publicado en el Periódico Oficial\nNo. 109, Índice, de fecha 31 de diciembre de 2021, Tomo CXXVIII, expedido por la H. XXIV\nLegislatura, siendo Gobernadora Constitucional la C. Marina del Pilar Ávila Olmeda 20212027;\nARTÍCULO 10.- Fue reformado mediante Decreto No. 66, publicado en el Periódico Oficial\nNo. 109, Índice, de fecha 31 de diciembre de 2021, Tomo CXXVIII, expedido por la H. XXIV\nLegislatura, siendo Gobernadora Constitucional la C. Marina del Pilar Ávila Olmeda 20212027;\nFue adicionado el Capítulo mediante Decreto No. 66, publicado en el Periódico Oficial No.\n109, Índice, de fecha 31 de diciembre de 2021, Tomo CXXVIII, expedido por la H. XXIV\nLegislatura, siendo Gobernadora Constitucional la C. Marina del Pilar Ávila Olmeda\n2021-2027;\nCAPÍTULO II\nDEL PROGRAMA ESTATAL DE SEGURIDAD CIUDADANA\nARTÍCULO 11.- Fue reformado mediante Decreto No. 66, publicado en el Periódico Oficial\nLegislatura, siendo Gobernadora Constitucional la C. Marina del Pilar Ávila Olmeda 20212027;\nARTÍCULO 12.- Fue reformado mediante Decreto No. 66, publicado en el Periódico Oficial\nLegislatura, siendo Gobernadora Constitucional la C. Marina del Pilar Ávila Olmeda 20212027;\nLey del Sistema Estatal de Seguridad Ciudadana de Baja California. Página 108\n.\nActualización Legislativa.\nÚltima Reforma P.O. No. 54, Índice, 05-Sep-2025\nARTÍCULO 13.- Fue reformado mediante Decreto No. 66, publicado en el Periódico Oficial\nNo. 109, Índice, de fecha 31 de diciembre de 2021, Tomo CXXVIII, expedido por la H. XXIV\nLegislatura, siendo Gobernadora Constitucional la C. Marina del Pilar Ávila Olmeda 20212027;\nFue adicionado el Capítulo mediante Decreto No. 66, publicado en el Periódico Oficial No.\n109, Índice, de fecha 31 de diciembre de 2021, Tomo CXXVIII, expedido por la H. XXIV\nLegislatura, siendo Gobernadora Constitucional la C. Marina del Pilar Ávila Olmeda\n2021-2027;\nCAPÍTULO III\nDEL CONSEJO ESTATAL DE SEGURIDAD CIUDADANA\nARTÍCULO 14.- Fue reformado mediante Decreto No. 66, publicado en el Periódico Oficial\nNo. 109, Índice, de fecha 31 de diciembre de 2021, Tomo CXXVIII, expedido por la H. XXIV\nLegislatura, siendo Gobernadora Constitucional la C. Marina del Pilar Ávila Olmeda 20212027;\nARTÍCULO 15.- Fue reformado mediante Decreto No. 66, publicado en el Periódico Oficial\nNo. 109, Índice, de fecha 31 de diciembre de 2021, Tomo CXXVIII, expedido por la H. XXIV\nLegislatura, siendo Gobernadora Constitucional la C. Marina del Pilar Ávila Olmeda 20212027;\nARTÍCULO 16.- Fue reformado mediante Decreto No. 66, publicado en el Periódico Oficial\nNo. 109, Índice, de fecha 31 de diciembre de 2021, Tomo CXXVIII, expedido por la H. XXIV\nLegislatura, siendo Gobernadora Constitucional la C. Marina del Pilar Ávila Olmeda 20212027;\nARTÍCULO 17.- Fue reformado mediante Decreto No. 66, publicado en el Periódico Oficial\nNo. 109, Índice, de fecha 31 de diciembre de 2021, Tomo CXXVIII, expedido por la H. XXIV\nLegislatura, siendo Gobernadora Constitucional la C. Marina del Pilar Ávila Olmeda 20212027;\nFue adicionado el Capítulo mediante Decreto No. 66, publicado en el Periódico Oficial No.\nLegislatura, siendo Gobernadora Constitucional la C. Marina del Pilar Ávila Olmeda\n2021-2027;\nCAPÍTULO IV\nDE LA SECRETARÍA DE SEGURIDAD CIUDADANA\nARTÍCULO 18.- Fue reformado mediante Decreto No. 66, publicado en el Periódico Oficial\nLey del Sistema Estatal de Seguridad Ciudadana de Baja California. Página 109\n.\nActualización Legislativa.\nÚltima Reforma P.O. No. 54, Índice, 05-Sep-2025\nLegislatura, siendo Gobernadora Constitucional la C. Marina del Pilar Ávila Olmeda 20212027;\nARTÍCULO 19.- Fue reformado mediante Decreto No. 66, publicado en el Periódico Oficial\nNo. 109, Índice, de fecha 31 de diciembre de 2021, Tomo CXXVIII, expedido por la H. XXIV\nLegislatura, siendo Gobernadora Constitucional la C. Marina del Pilar Ávila Olmeda 20212027; fue reformado mediante Decreto No. 292, publicado en el Periódico Oficial No. 55,\nSección I, de fecha 25 de septiembre de 2023, Tomo CXXX, expedido por la H. XXIV\nLegislatura, siendo Gobernadora Constitucional la C. Marina del Pilar Ávila Olmeda 20212027;\nFue adicionado el Capítulo mediante Decreto No. 66, publicado en el Periódico Oficial No.\n109, Índice, de fecha 31 de diciembre de 2021, Tomo CXXVIII, expedido por la H. XXIV\nLegislatura, siendo Gobernadora Constitucional la C. Marina del Pilar Ávila Olmeda\n2021-2027;\nCAPÍTULO V\nDEL SECRETARÍADO EJECUTIVO\nARTÍCULO 20.- Fue reformado mediante Decreto No. 66, publicado en el Periódico Oficial\nNo. 109, Índice, de fecha 31 de diciembre de 2021, Tomo CXXVIII, expedido por la H. XXIV\nLegislatura, siendo Gobernadora Constitucional la C. Marina del Pilar Ávila Olmeda 20212027;\nARTÍCULO 21.- Fue reformado mediante Decreto No. 66, publicado en el Periódico Oficial\nNo. 109, Índice, de fecha 31 de diciembre de 2021, Tomo CXXVIII, expedido por la H. XXIV\nLegislatura, siendo Gobernadora Constitucional la C. Marina del Pilar Ávila Olmeda 20212027;\nFue adicionado el Capítulo mediante Decreto No. 66, publicado en el Periódico Oficial No.\n109, Índice, de fecha 31 de diciembre de 2021, Tomo CXXVIII, expedido por la H. XXIV\nLegislatura, siendo Gobernadora Constitucional la C. Marina del Pilar Ávila Olmeda\n2021-2027;\nCAPÍTULO VI\nDE LA OPERACIÓN POLICIAL, LAS INSTITUCIONES POLICIALES, LA AGENCIA\nESTATAL DE INVESTIGACIÓN Y SUS AUXILIARES\nARTÍCULO 22.- Fue reformado mediante Decreto No. 66, publicado en el Periódico Oficial\nLegislatura, siendo Gobernadora Constitucional la C. Marina del Pilar Ávila Olmeda 20212027;\nLey del Sistema Estatal de Seguridad Ciudadana de Baja California. Página 110\n.\nActualización Legislativa.\nÚltima Reforma P.O. No. 54, Índice, 05-Sep-2025\nARTÍCULO 23.- Fue reformado mediante Decreto No. 66, publicado en el Periódico Oficial\nNo. 109, Índice, de fecha 31 de diciembre de 2021, Tomo CXXVIII, expedido por la H. XXIV\nLegislatura, siendo Gobernadora Constitucional la C. Marina del Pilar Ávila Olmeda 20212027;\nARTÍCULO 24.- Fue reformado mediante Decreto No. 66, publicado en el Periódico Oficial\nNo. 109, Índice, de fecha 31 de diciembre de 2021, Tomo CXXVIII, expedido por la H. XXIV\nLegislatura, siendo Gobernadora Constitucional la C. Marina del Pilar Ávila Olmeda 20212027;\nARTÍCULO 25.- Fue reformado mediante Decreto No. 66, publicado en el Periódico Oficial\nNo. 109, Índice, de fecha 31 de diciembre de 2021, Tomo CXXVIII, expedido por la H. XXIV\nLegislatura, siendo Gobernadora Constitucional la C. Marina del Pilar Ávila Olmeda 20212027;\nFue adicionado el Capítulo mediante Decreto No. 66, publicado en el Periódico Oficial No.\n109, Índice, de fecha 31 de diciembre de 2021, Tomo CXXVIII, expedido por la H. XXIV\nLegislatura, siendo Gobernadora Constitucional la C. Marina del Pilar Ávila Olmeda\n2021-2027;\nCAPÍTULO VII\nDE LA EVALUACIÓN Y CONTROL DE CONFIANZA\nARTÍCULO 26.- Fue reformado mediante Decreto No. 66, publicado en el Periódico Oficial\nNo. 109, Índice, de fecha 31 de diciembre de 2021, Tomo CXXVIII, expedido por la H. XXIV\nLegislatura, siendo Gobernadora Constitucional la C. Marina del Pilar Ávila Olmeda 20212027;\nARTÍCULO 27.- Fue reformado mediante Decreto No. 66, publicado en el Periódico Oficial\nNo. 109, Índice, de fecha 31 de diciembre de 2021, Tomo CXXVIII, expedido por la H. XXIV\nLegislatura, siendo Gobernadora Constitucional la C. Marina del Pilar Ávila Olmeda 20212027;\nFue adicionado el Capítulo mediante Decreto No. 66, publicado en el Periódico Oficial No.\nLegislatura, siendo Gobernadora Constitucional la C. Marina del Pilar Ávila Olmeda\n2021-2027;\nCAPÍTULO VIII\nARTÍCULO 28.- Fue reformado mediante Decreto No. 66, publicado en el Periódico Oficial\nLegislatura, siendo Gobernadora Constitucional la C. Marina del Pilar Ávila Olmeda 20212027;\nLey del Sistema Estatal de Seguridad Ciudadana de Baja California. Página 111\n.\nActualización Legislativa.\nÚltima Reforma P.O. No. 54, Índice, 05-Sep-2025\nARTÍCULO 29.- Fue reformado mediante Decreto No. 66, publicado en el Periódico\nOficial No. 109, Índice, de fecha 31 de diciembre de 2021, Tomo CXXVIII, expedido por la H.\nXXIV Legislatura, siendo Gobernadora Constitucional la C. Marina del Pilar Ávila Olmeda\n2021-2027; fue reformado mediante Decreto No. 120; publicado en el Periódico Oficial No.\n54, Índice, de fecha 05 de septiembre de 2025, Tomo CXXXII, expedido por la H. XXV\nLegislatura, siendo Gobernadora Constitucional la C. Marina del Pilar Ávila Olmeda 20212027;\nFue adicionado el Capítulo mediante Decreto No. 66, publicado en el Periódico Oficial No.\n109, Índice, de fecha 31 de diciembre de 2021, Tomo CXXVIII, expedido por la H. XXIV\nLegislatura, siendo Gobernadora Constitucional la C. Marina del Pilar Ávila Olmeda\n2021-2027;\nCAPÍTULO IX\nDEL CENTRO ESTATAL DE INTELIGENCIA PREVENTIVA\nARTÍCULO 30.- Fue reformado mediante Decreto No. 66, publicado en el Periódico Oficial\nNo. 109, Índice, de fecha 31 de diciembre de 2021, Tomo CXXVIII, expedido por la H. XXIV\nLegislatura, siendo Gobernadora Constitucional la C. Marina del Pilar Ávila Olmeda 20212027;\nARTÍCULO 31.- Fue reformado mediante Decreto No. 66, publicado en el Periódico Oficial\nNo. 109, Índice, de fecha 31 de diciembre de 2021, Tomo CXXVIII, expedido por la H. XXIV\nLegislatura, siendo Gobernadora Constitucional la C. Marina del Pilar Ávila Olmeda 20212027;\nFue modificada la denominación mediante Decreto No. 66, publicado en el Periódico Oficial\nNo. 109, Índice, de fecha 31 de diciembre de 2021, Tomo CXXVIII, expedido por la H. XXIV\nLegislatura, siendo Gobernadora Constitucional la C. Marina del Pilar Ávila Olmeda\n2021-2027;\nTÍTULO TERCERO\nDE LA INTELIGENCIA PREVENTIVA Y EL SISTEMA ESTATAL DE INFORMACIÓN PARA\nLA SEGURIDAD CIUDADANA\nFue modificada la denominación mediante Decreto No. 66, publicado en el Periódico Oficial\nLegislatura, siendo Gobernadora Constitucional la C. Marina del Pilar Ávila Olmeda\n2021-2027;\nCAPÍTULO I\nDISPOSICIONES GENERALES\nARTÍCULO 32.- Fue reformado mediante Decreto No. 66, publicado en el Periódico Oficial\nLegislatura, siendo Gobernadora Constitucional la C. Marina del Pilar Ávila Olmeda 20212027;\nLey del Sistema Estatal de Seguridad Ciudadana de Baja California. Página 112\n.\nActualización Legislativa.\nÚltima Reforma P.O. No. 54, Índice, 05-Sep-2025\nARTÍCULO 33.- Fue reformado mediante Decreto No. 66, publicado en el Periódico Oficial\nNo. 109, Índice, de fecha 31 de diciembre de 2021, Tomo CXXVIII, expedido por la H. XXIV\nLegislatura, siendo Gobernadora Constitucional la C. Marina del Pilar Ávila Olmeda 20212027;\nARTÍCULO 34.- Fue reformado mediante Decreto No. 66, publicado en el Periódico Oficial\nNo. 109, Índice, de fecha 31 de diciembre de 2021, Tomo CXXVIII, expedido por la H. XXIV\nLegislatura, siendo Gobernadora Constitucional la C. Marina del Pilar Ávila Olmeda 20212027;\nARTÍCULO 35.- Fue reformado mediante Decreto No. 66, publicado en el Periódico Oficial\nNo. 109, Índice, de fecha 31 de diciembre de 2021, Tomo CXXVIII, expedido por la H. XXIV\nLegislatura, siendo Gobernadora Constitucional la C. Marina del Pilar Ávila Olmeda 20212027;\nARTÍCULO 36.- Fue reformado mediante Decreto No. 66, publicado en el Periódico Oficial\nNo. 109, Índice, de fecha 31 de diciembre de 2021, Tomo CXXVIII, expedido por la H. XXIV\nLegislatura, siendo Gobernadora Constitucional la C. Marina del Pilar Ávila Olmeda 20212027;\nFue adicionado el Capítulo mediante Decreto No. 66, publicado en el Periódico Oficial No.\n109, Índice, de fecha 31 de diciembre de 2021, Tomo CXXVIII, expedido por la H. XXIV\nLegislatura, siendo Gobernadora Constitucional la C. Marina del Pilar Ávila Olmeda\n2021-2027;\nCAPÍTULO II\nDE LA RED ESTATAL DE COMUNICACIONES DE SEGURIDAD\nARTÍCULO 37.- Fue reformado mediante Decreto No. 66, publicado en el Periódico Oficial\nNo. 109, Índice, de fecha 31 de diciembre de 2021, Tomo CXXVIII, expedido por la H. XXIV\nLegislatura, siendo Gobernadora Constitucional la C. Marina del Pilar Ávila Olmeda 20212027;\nARTÍCULO 38.- Fue reformado mediante Decreto No. 66, publicado en el Periódico Oficial\nLegislatura, siendo Gobernadora Constitucional la C. Marina del Pilar Ávila Olmeda 20212027;\nARTÍCULO 39.- Fue reformado mediante Decreto No. 66, publicado en el Periódico Oficial\nLegislatura, siendo Gobernadora Constitucional la C. Marina del Pilar Ávila Olmeda 20212027;\nLey del Sistema Estatal de Seguridad Ciudadana de Baja California. Página 113\n.\nActualización Legislativa.\nÚltima Reforma P.O. No. 54, Índice, 05-Sep-2025\nARTÍCULO 40.- Fue reformado mediante Decreto No. 66, publicado en el Periódico Oficial\nNo. 109, Índice, de fecha 31 de diciembre de 2021, Tomo CXXVIII, expedido por la H. XXIV\nLegislatura, siendo Gobernadora Constitucional la C. Marina del Pilar Ávila Olmeda 20212027;\nFue adicionado el Capítulo mediante Decreto No. 66, publicado en el Periódico Oficial No.\n109, Índice, de fecha 31 de diciembre de 2021, Tomo CXXVIII, expedido por la H. XXIV\nLegislatura, siendo Gobernadora Constitucional la C. Marina del Pilar Ávila Olmeda\n2021-2027;\nCAPÍTULO III\nDE LOS REGISTROS ESTATALES DE INFORMACIÓN\nARTÍCULO 41.- Fue reformado mediante Decreto No. 66, publicado en el Periódico Oficial\nNo. 109, Índice, de fecha 31 de diciembre de 2021, Tomo CXXVIII, expedido por la H. XXIV\nLegislatura, siendo Gobernadora Constitucional la C. Marina del Pilar Ávila Olmeda 20212027; fue reformado mediante Decreto No. 119, publicado en el Periódico Oficial No. 43, Número Especial, de fecha 21 de julio de 2025, Tomo CXXXII, expedido por la H. XXV\nLegislatura, siendo Gobernadora Constitucional la C. Marina del Pilar Ávila Olmeda 20212027;\nFue adicionada la Sección mediante Decreto No. 66, publicado en el Periódico Oficial No.\n109, Índice, de fecha 31 de diciembre de 2021, Tomo CXXVIII, expedido por la H. XXIV\nLegislatura, siendo Gobernadora Constitucional la C. Marina del Pilar Ávila Olmeda\n2021-2027;\nSECCIÓN PRIMERA\nDEL PERSONAL, ARMAMENTO, VEHÍCULOS Y EQUIPOS DE COMUNICACIÓN\nARTÍCULO 42.- Fue reformado mediante Decreto No. 66, publicado en el Periódico Oficial\nNo. 109, Índice, de fecha 31 de diciembre de 2021, Tomo CXXVIII, expedido por la H. XXIV\nLegislatura, siendo Gobernadora Constitucional la C. Marina del Pilar Ávila Olmeda 20212027;\nARTÍCULO 43.- Fue reformado mediante Decreto No. 66, publicado en el Periódico Oficial\nLegislatura, siendo Gobernadora Constitucional la C. Marina del Pilar Ávila Olmeda 20212027;\nARTÍCULO 44.- Fue reformado mediante Decreto No. 66, publicado en el Periódico Oficial\nLegislatura, siendo Gobernadora Constitucional la C. Marina del Pilar Ávila Olmeda 20212027;\nARTÍCULO 45.- Fue reformado mediante Decreto No. 66, publicado en el Periódico Oficial\nLey del Sistema Estatal de Seguridad Ciudadana de Baja California. Página 114\n.\nActualización Legislativa.\nÚltima Reforma P.O. No. 54, Índice, 05-Sep-2025\nLegislatura, siendo Gobernadora Constitucional la C. Marina del Pilar Ávila Olmeda 20212027;\nARTÍCULO 46.- Fue reformado mediante Decreto No. 66, publicado en el Periódico Oficial\nNo. 109, Índice, de fecha 31 de diciembre de 2021, Tomo CXXVIII, expedido por la H. XXIV\nLegislatura, siendo Gobernadora Constitucional la C. Marina del Pilar Ávila Olmeda 20212027; fue reformado mediante Decreto No. 292, publicado en el Periódico Oficial No. 55,\nSección I, de fecha 25 de septiembre de 2023, Tomo CXXX, expedido por la H. XXIV\nLegislatura, siendo Gobernadora Constitucional la C. Marina del Pilar Ávila Olmeda 20212027;\nARTÍCULO 47.- Fue reformado mediante Decreto No. 66, publicado en el Periódico Oficial\nNo. 109, Índice, de fecha 31 de diciembre de 2021, Tomo CXXVIII, expedido por la H. XXIV\nLegislatura, siendo Gobernadora Constitucional la C. Marina del Pilar Ávila Olmeda 20212027;\nARTÍCULO 48.- Fue reformado mediante Decreto No. 66, publicado en el Periódico Oficial\nNo. 109, Índice, de fecha 31 de diciembre de 2021, Tomo CXXVIII, expedido por la H. XXIV\nLegislatura, siendo Gobernadora Constitucional la C. Marina del Pilar Ávila Olmeda 20212027;\nFue adicionada la Sección mediante Decreto No. 66, publicado en el Periódico Oficial No.\n109, Índice, de fecha 31 de diciembre de 2021, Tomo CXXVIII, expedido por la H. XXIV\nLegislatura, siendo Gobernadora Constitucional la C. Marina del Pilar Ávila Olmeda\n2021-2027;\nSECCIÓN SEGUNDA\nDEL REGISTRO DE DETENCIONES E INFORME POLICIAL HOMOLOGADO\nARTÍCULO 49.- Fue reformado mediante Decreto No. 66, publicado en el Periódico Oficial\nNo. 109, Índice, de fecha 31 de diciembre de 2021, Tomo CXXVIII, expedido por la H. XXIV\nLegislatura, siendo Gobernadora Constitucional la C. Marina del Pilar Ávila Olmeda 20212027;\nARTÍCULO 49 BIS.- El texto de este artículo fue recorrido con modificaciones al artículo 55 de esta Ley mediante Decreto No. 66, publicado en el Periódico Oficial No. 109, Índice, de\nGobernadora Constitucional la C. Marina del Pilar Ávila Olmeda 2021-2027;\nARTÍCULO 49 TER.- El texto de este artículo fue recorrido con modificaciones al artículo 55 de esta Ley mediante Decreto No. 66, publicado en el Periódico Oficial No. 109, Índice, de\nGobernadora Constitucional la C. Marina del Pilar Ávila Olmeda 2021-2027;\nLey del Sistema Estatal de Seguridad Ciudadana de Baja California. Página 115\n.\nActualización Legislativa.\nÚltima Reforma P.O. No. 54, Índice, 05-Sep-2025\nARTÍCULO 50.- Fue reformado mediante Decreto No. 66, publicado en el Periódico Oficial\nNo. 109, Índice, de fecha 31 de diciembre de 2021, Tomo CXXVIII, expedido por la H. XXIV\nLegislatura, siendo Gobernadora Constitucional la C. Marina del Pilar Ávila Olmeda 20212027;\nFue adicionada la Sección mediante Decreto No. 66, publicado en el Periódico Oficial No.\n109, Índice, de fecha 31 de diciembre de 2021, Tomo CXXVIII, expedido por la H. XXIV\nLegislatura, siendo Gobernadora Constitucional la C. Marina del Pilar Ávila Olmeda\n2021-2027;\nSECCIÓN TERCERA\nDEL REGISTRO E IDENTIFICACIÓN DE PERSONAS Y GENERADORES DE VIOLENCIA\nARTÍCULO 51.- Fue reformado mediante Decreto No. 66, publicado en el Periódico Oficial\nNo. 109, Índice, de fecha 31 de diciembre de 2021, Tomo CXXVIII, expedido por la H. XXIV\nLegislatura, siendo Gobernadora Constitucional la C. Marina del Pilar Ávila Olmeda 20212027;\nFue adicionada la Sección mediante Decreto No. 66, publicado en el Periódico Oficial No.\n109, Índice, de fecha 31 de diciembre de 2021, Tomo CXXVIII, expedido por la H. XXIV\nLegislatura, siendo Gobernadora Constitucional la C. Marina del Pilar Ávila Olmeda\n2021-2027;\nSECCIÓN CUARTA\nDEL REGISTRO DE MEDIDAS JUDICIALES Y DE PERSONAS PRIVADAS DE LA\nLIBERTAD\nARTÍCULO 52.- Fue reformado mediante Decreto No. 66, publicado en el Periódico Oficial\nNo. 109, Índice, de fecha 31 de diciembre de 2021, Tomo CXXVIII, expedido por la H. XXIV\nLegislatura, siendo Gobernadora Constitucional la C. Marina del Pilar Ávila Olmeda 20212027;\nFue adicionada la Sección mediante Decreto No. 66, publicado en el Periódico Oficial No.\n109, Índice, de fecha 31 de diciembre de 2021, Tomo CXXVIII, expedido por la H. XXIV\nLegislatura, siendo Gobernadora Constitucional la C. Marina del Pilar Ávila Olmeda\n2021-2027;\nSECCIÓN QUINTA\nARTÍCULO 53.- Fue reformado mediante Decreto No. 66, publicado en el Periódico Oficial\nLegislatura, siendo Gobernadora Constitucional la C. Marina del Pilar Ávila Olmeda 20212027;\nARTÍCULO 54.- Fue reformado mediante Decreto No. 66, publicado en el Periódico Oficial\nLey del Sistema Estatal de Seguridad Ciudadana de Baja California. Página 116\n.\nActualización Legislativa.\nÚltima Reforma P.O. No. 54, Índice, 05-Sep-2025\nLegislatura, siendo Gobernadora Constitucional la C. Marina del Pilar Ávila Olmeda 20212027;\nARTÍCULO 55.- Fue reformado mediante Decreto No. 66, publicado en el Periódico Oficial\nNo. 109, Índice, de fecha 31 de diciembre de 2021, Tomo CXXVIII, expedido por la H. XXIV\nLegislatura, siendo Gobernadora Constitucional la C. Marina del Pilar Ávila Olmeda 20212027;\nFue adicionada la Sección mediante Decreto No. 66, publicado en el Periódico Oficial No.\n109, Índice, de fecha 31 de diciembre de 2021, Tomo CXXVIII, expedido por la H. XXIV\nLegislatura, siendo Gobernadora Constitucional la C. Marina del Pilar Ávila Olmeda 20212027;\nSECCIÓN SEXTA\nDE LOS BIENES ROBADOS Y RECUPERADOS\nARTÍCULO 56.- Fue reformado mediante Decreto No. 66, publicado en el Periódico Oficial\nNo. 109, Índice, de fecha 31 de diciembre de 2021, Tomo CXXVIII, expedido por la H. XXIV\nLegislatura, siendo Gobernadora Constitucional la C. Marina del Pilar Ávila Olmeda 20212027; fue reformado mediante Decreto No. 48, publicado en el Periódico Oficial No. 9,\nSección III, de fecha 31 de enero de 2025, Tomo CXXXII, expedido por la H. XXV\nLegislatura, siendo Gobernadora Constitucional la C. Marina del Pilar Ávila Olmeda 20212027;\nFue adicionada la Sección mediante Decreto No. 66, publicado en el Periódico Oficial No.\n109, Índice, de fecha 31 de diciembre de 2021, Tomo CXXVIII, expedido por la H. XXIV\nLegislatura, siendo Gobernadora Constitucional la C. Marina del Pilar Ávila Olmeda\n2021-2027;\nSECCIÓN SÉPTIMA\nDE LA ESTADÍSTICA\nARTÍCULO 57.- Fue reformado mediante Decreto No. 66, publicado en el Periódico Oficial\nLegislatura, siendo Gobernadora Constitucional la C. Marina del Pilar Ávila Olmeda 20212027;\nFue modificada la denominación mediante Decreto No. 66, publicado en el Periódico Oficial\nLegislatura, siendo Gobernadora Constitucional la C. Marina del Pilar Ávila Olmeda\n2021-2027;\nTÍTULO CUARTO\nDEL SISTEMA ESTATAL PENITENCIARIO\nLey del Sistema Estatal de Seguridad Ciudadana de Baja California. Página 117\n.\nActualización Legislativa.\nÚltima Reforma P.O. No. 54, Índice, 05-Sep-2025\nFue modificada la denominación mediante Decreto No. 66, publicado en el Periódico Oficial\nNo. 109, Índice, de fecha 31 de diciembre de 2021, Tomo CXXVIII, expedido por la H. XXIV\nLegislatura, siendo Gobernadora Constitucional la C. Marina del Pilar Ávila Olmeda\n2021-2027;\nCAPÍTULO ÚNICO\nDE LA EJECUCIÓN DE PENAS, MEDIDAS DE SANCIÓN Y MEDIDAS JUDICIALES\nARTÍCULO 58.- Fue reformado mediante Decreto No. 66, publicado en el Periódico Oficial\nNo. 109, Índice, de fecha 31 de diciembre de 2021, Tomo CXXVIII, expedido por la H. XXIV\nLegislatura, siendo Gobernadora Constitucional la C. Marina del Pilar Ávila Olmeda 20212027;\nFue modificada la denominación mediante Decreto No. 66, publicado en el Periódico Oficial\nNo. 109, Índice, de fecha 31 de diciembre de 2021, Tomo CXXVIII, expedido por la H. XXIV\nLegislatura, siendo Gobernadora Constitucional la C. Marina del Pilar Ávila Olmeda\n2021-2027;\nTÍTULO QUINTO\nDEL CONTACTO Y ATENCIÓN A LA CIUDADANÍA\nFue modificada la denominación mediante Decreto No. 66, publicado en el Periódico Oficial\nNo. 109, Índice, de fecha 31 de diciembre de 2021, Tomo CXXVIII, expedido por la H. XXIV\nLegislatura, siendo Gobernadora Constitucional la C. Marina del Pilar Ávila Olmeda\n2021-2027;\nCAPÍTULO I\nDEL CENTRO DE CONTROL, COMANDO, COMUNICACIÓN, CÓMPUTO, CALIDAD Y\nCONTACTO CIUDADANO DEL ESTADO\nARTÍCULO 59.- Fue reformado mediante Decreto No. 66, publicado en el Periódico Oficial\nNo. 109, Índice, de fecha 31 de diciembre de 2021, Tomo CXXVIII, expedido por la H. XXIV\nLegislatura, siendo Gobernadora Constitucional la C. Marina del Pilar Ávila Olmeda 20212027; fue reformado mediante Decreto No. 48, publicado en el Periódico Oficial No. 9,\nSección III, de fecha 31 de enero de 2025, Tomo CXXXII, expedido por la H. XXV\nLegislatura, siendo Gobernadora Constitucional la C. Marina del Pilar Ávila Olmeda 20212027;\nFue modificada la denominación mediante Decreto No. 66, publicado en el Periódico Oficial\nLegislatura, siendo Gobernadora Constitucional la C. Marina del Pilar Ávila Olmeda\n2021-2027;\nCAPÍTULO II\nARTÍCULO 60.- Fue reformado mediante Decreto No. 66, publicado en el Periódico Oficial\nLey del Sistema Estatal de Seguridad Ciudadana de Baja California. Página 118\n.\nActualización Legislativa.\nÚltima Reforma P.O. No. 54, Índice, 05-Sep-2025\nLegislatura, siendo Gobernadora Constitucional la C. Marina del Pilar Ávila Olmeda 20212027;\nARTÍCULO 61.- Fue reformado mediante Decreto No. 66, publicado en el Periódico Oficial\nNo. 109, Índice, de fecha 31 de diciembre de 2021, Tomo CXXVIII, expedido por la H. XXIV\nLegislatura, siendo Gobernadora Constitucional la C. Marina del Pilar Ávila Olmeda 20212027; fue reformado mediante Decreto No. 48, publicado en el Periódico Oficial No. 9,\nSección III, de fecha 31 de enero de 2025, Tomo CXXXII, expedido por la H. XXV\nLegislatura, siendo Gobernadora Constitucional la C. Marina del Pilar Ávila Olmeda 20212027;\nARTÍCULO 62.- Fue reformado mediante Decreto No. 66, publicado en el Periódico Oficial\nNo. 109, Índice, de fecha 31 de diciembre de 2021, Tomo CXXVIII, expedido por la H. XXIV\nLegislatura, siendo Gobernadora Constitucional la C. Marina del Pilar Ávila Olmeda 20212027; fue reformado mediante Decreto No. 48, publicado en el Periódico Oficial No. 9,\nSección III, de fecha 31 de enero de 2025, Tomo CXXXII, expedido por la H. XXV\nLegislatura, siendo Gobernadora Constitucional la C. Marina del Pilar Ávila Olmeda 20212027;\nARTÍCULO 63.- Fue reformado mediante Decreto No. 66, publicado en el Periódico Oficial\nNo. 109, Índice, de fecha 31 de diciembre de 2021, Tomo CXXVIII, expedido por la H. XXIV\nLegislatura, siendo Gobernadora Constitucional la C. Marina del Pilar Ávila Olmeda 20212027; fue reformado mediante Decreto No. 48, publicado en el Periódico Oficial No. 9,\nSección III, de fecha 31 de enero de 2025, Tomo CXXXII, expedido por la H. XXV\nLegislatura, siendo Gobernadora Constitucional la C. Marina del Pilar Ávila Olmeda 20212027;\nFue modificada la denominación mediante Decreto No. 66, publicado en el Periódico Oficial\nNo. 109, Índice, de fecha 31 de diciembre de 2021, Tomo CXXVIII, expedido por la H. XXIV\nLegislatura, siendo Gobernadora Constitucional la C. Marina del Pilar Ávila Olmeda\n2021-2027;\nCAPÍTULO III\nCENTRO DE DENUNCIA ANONIMA\nARTÍCULO 64.- Fue reformado mediante Decreto No. 66, publicado en el Periódico Oficial\nLegislatura, siendo Gobernadora Constitucional la C. Marina del Pilar Ávila Olmeda 20212027;\nARTÍCULO 65.- Fue reformado mediante Decreto No. 66, publicado en el Periódico Oficial\nLegislatura, siendo Gobernadora Constitucional la C. Marina del Pilar Ávila Olmeda 20212027;\nLey del Sistema Estatal de Seguridad Ciudadana de Baja California. Página 119\n.\nActualización Legislativa.\nÚltima Reforma P.O. No. 54, Índice, 05-Sep-2025\nFue modificada la denominación mediante Decreto No. 66, publicado en el Periódico Oficial\nNo. 109, Índice, de fecha 31 de diciembre de 2021, Tomo CXXVIII, expedido por la H. XXIV\nLegislatura, siendo Gobernadora Constitucional la C. Marina del Pilar Ávila Olmeda\n2021-2027;\nTÍTULO SEXTO\nDELITOS CONTRA EL SISTEMA ESTATAL DE SEGURIDAD CIUDADANA\nARTÍCULO 66.- Fue reformado mediante Decreto No. 66, publicado en el Periódico Oficial\nNo. 109, Índice, de fecha 31 de diciembre de 2021, Tomo CXXVIII, expedido por la H. XXIV\nLegislatura, siendo Gobernadora Constitucional la C. Marina del Pilar Ávila Olmeda 20212027;\nARTÍCULO 67.- Fue reformado mediante Decreto No. 66, publicado en el Periódico Oficial\nNo. 109, Índice, de fecha 31 de diciembre de 2021, Tomo CXXVIII, expedido por la H. XXIV\nLegislatura, siendo Gobernadora Constitucional la C. Marina del Pilar Ávila Olmeda 20212027;\nARTÍCULO 69.- Fue reformado mediante Decreto No. 66, publicado en el Periódico Oficial\nNo. 109, Índice, de fecha 31 de diciembre de 2021, Tomo CXXVIII, expedido por la H. XXIV\nLegislatura, siendo Gobernadora Constitucional la C. Marina del Pilar Ávila Olmeda 20212027;\nARTÍCULO 70.- Fue reformado mediante Decreto No. 66, publicado en el Periódico Oficial\nNo. 109, Índice, de fecha 31 de diciembre de 2021, Tomo CXXVIII, expedido por la H. XXIV\nLegislatura, siendo Gobernadora Constitucional la C. Marina del Pilar Ávila Olmeda 20212027;\nARTÍCULO 71.- Fue reformado mediante Decreto No. 225, publicado en el Periódico Oficial\nNo. 26, Número Especial, de fecha 09 de mayo de 2023, Tomo CXXX, expedido por la H.\nXXIV Legislatura, siendo Gobernadora Constitucional la C. Marina del Pilar Ávila Olmeda\n2021-2027;\nARTÍCULO 72.- Fue reformado mediante Decreto No. 66, publicado en el Periódico Oficial\nLegislatura, siendo Gobernadora Constitucional la C. Marina del Pilar Ávila Olmeda 20212027;\nARTÍCULO 74.- Fue reformado mediante Decreto No. 66, publicado en el Periódico Oficial\nLegislatura, siendo Gobernadora Constitucional la C. Marina del Pilar Ávila Olmeda 20212027;\nARTÍCULO 75.- Fue reformado mediante Decreto No. 66, publicado en el Periódico Oficial\nLey del Sistema Estatal de Seguridad Ciudadana de Baja California. Página 120\n.\nActualización Legislativa.\nÚltima Reforma P.O. No. 54, Índice, 05-Sep-2025\nLegislatura, siendo Gobernadora Constitucional la C. Marina del Pilar Ávila Olmeda 20212027; fue reformado mediante Decreto No. 225, publicado en el Periódico Oficial No. 26, Número Especial, de fecha 09 de mayo de 2023, Tomo CXXX, expedido por la H. XXIV\nLegislatura, siendo Gobernadora Constitucional la C. Marina del Pilar Ávila Olmeda 20212027;\nARTÍCULO 76.- Fue reformado mediante Decreto No. 66, publicado en el Periódico Oficial\nNo. 109, Índice, de fecha 31 de diciembre de 2021, Tomo CXXVIII, expedido por la H. XXIV\nLegislatura, siendo Gobernadora Constitucional la C. Marina del Pilar Ávila Olmeda 20212027;\nARTÍCULO 77.- Fue reformado mediante Decreto No. 66, publicado en el Periódico Oficial\nNo. 109, Índice, de fecha 31 de diciembre de 2021, Tomo CXXVIII, expedido por la H. XXIV\nLegislatura, siendo Gobernadora Constitucional la C. Marina del Pilar Ávila Olmeda 20212027;\nARTÍCULO 79.- Fue reformado mediante Decreto No. 66, publicado en el Periódico Oficial\nNo. 109, Índice, de fecha 31 de diciembre de 2021, Tomo CXXVIII, expedido por la H. XXIV\nLegislatura, siendo Gobernadora Constitucional la C. Marina del Pilar Ávila Olmeda 20212027;\nARTÍCULO 80.- Fue reformado mediante Decreto No. 66, publicado en el Periódico Oficial\nNo. 109, Índice, de fecha 31 de diciembre de 2021, Tomo CXXVIII, expedido por la H. XXIV\nLegislatura, siendo Gobernadora Constitucional la C. Marina del Pilar Ávila Olmeda 20212027;\nARTÍCULO 81.- Fue reformado mediante Decreto No. 66, publicado en el Periódico Oficial\nNo. 109, Índice, de fecha 31 de diciembre de 2021, Tomo CXXVIII, expedido por la H. XXIV\nLegislatura, siendo Gobernadora Constitucional la C. Marina del Pilar Ávila Olmeda 20212027;\nARTÍCULO 82.- Fue reformado mediante Decreto No. 66, publicado en el Periódico Oficial\nLegislatura, siendo Gobernadora Constitucional la C. Marina del Pilar Ávila Olmeda 20212027;\nARTÍCULO 83.- Fue reformado mediante Decreto No. 66, publicado en el Periódico Oficial\nLegislatura, siendo Gobernadora Constitucional la C. Marina del Pilar Ávila Olmeda 20212027;\nARTÍCULO 84.- Fue reformado mediante Decreto No. 66, publicado en el Periódico Oficial\nLey del Sistema Estatal de Seguridad Ciudadana de Baja California. Página 121\n.\nActualización Legislativa.\nÚltima Reforma P.O. No. 54, Índice, 05-Sep-2025\nLegislatura, siendo Gobernadora Constitucional la C. Marina del Pilar Ávila Olmeda 20212027;\nARTÍCULO 85.- Fue reformado mediante Decreto No. 66, publicado en el Periódico Oficial\nNo. 109, Índice, de fecha 31 de diciembre de 2021, Tomo CXXVIII, expedido por la H. XXIV\nLegislatura, siendo Gobernadora Constitucional la C. Marina del Pilar Ávila Olmeda 20212027;\nARTÍCULO 86.- Fue reformado mediante Decreto No. 66, publicado en el Periódico Oficial\nNo. 109, Índice, de fecha 31 de diciembre de 2021, Tomo CXXVIII, expedido por la H. XXIV\nLegislatura, siendo Gobernadora Constitucional la C. Marina del Pilar Ávila Olmeda 20212027;\nARTÍCULO 89.- Fue reformado mediante Decreto No. 66, publicado en el Periódico Oficial\nNo. 109, Índice, de fecha 31 de diciembre de 2021, Tomo CXXVIII, expedido por la H. XXIV\nLegislatura, siendo Gobernadora Constitucional la C. Marina del Pilar Ávila Olmeda 20212027;\nARTÍCULO 91.- Fue reformado mediante Decreto No. 66, publicado en el Periódico Oficial\nNo. 109, Índice, de fecha 31 de diciembre de 2021, Tomo CXXVIII, expedido por la H. XXIV\nLegislatura, siendo Gobernadora Constitucional la C. Marina del Pilar Ávila Olmeda 20212027;\nARTÍCULO 93.- Fue reformado mediante Decreto No. 66, publicado en el Periódico Oficial\nNo. 109, Índice, de fecha 31 de diciembre de 2021, Tomo CXXVIII, expedido por la H. XXIV\nLegislatura, siendo Gobernadora Constitucional la C. Marina del Pilar Ávila Olmeda 20212027;\nARTÍCULO 94.- Fue reformado mediante Decreto No. 66, publicado en el Periódico Oficial\nNo. 109, Índice, de fecha 31 de diciembre de 2021, Tomo CXXVIII, expedido por la H. XXIV\nLegislatura, siendo Gobernadora Constitucional la C. Marina del Pilar Ávila Olmeda 20212027;\nARTÍCULO 96.- Fue reformado mediante Decreto No. 66, publicado en el Periódico Oficial\nLegislatura, siendo Gobernadora Constitucional la C. Marina del Pilar Ávila Olmeda 20212027;\nARTÍCULO 97.- Fue reformado mediante Decreto No. 66, publicado en el Periódico Oficial\nLegislatura, siendo Gobernadora Constitucional la C. Marina del Pilar Ávila Olmeda 20212027; fue reformado mediante Decreto No. 119, publicado en el Periódico Oficial No. 43, Ley del Sistema Estatal de Seguridad Ciudadana de Baja California. Página 122\n.\nActualización Legislativa.\nÚltima Reforma P.O. No. 54, Índice, 05-Sep-2025\nLegislatura, siendo Gobernadora Constitucional la C. Marina del Pilar Ávila Olmeda 20212027;\nARTÍCULO 98.- Fue reformado mediante Decreto No. 66, publicado en el Periódico Oficial\nNo. 109, Índice, de fecha 31 de diciembre de 2021, Tomo CXXVIII, expedido por la H. XXIV\nLegislatura, siendo Gobernadora Constitucional la C. Marina del Pilar Ávila Olmeda 20212027;\nARTÍCULO 99.- Forma parte del resolutivo, pero el texto de este artículo en el decreto es igual que el texto de origen en esta Ley, por lo que no existe reforma a este artículo en el\nDecreto No. 66, publicado en el Periódico Oficial No. 109, Índice, de fecha 31 de diciembre de 2021, Tomo CXXVIII, expedido por la H. XXIV Legislatura, siendo Gobernadora\nConstitucional la C. Marina del Pilar Ávila Olmeda 2021-2027;\nARTÍCULO 103.- Fue reformado mediante Decreto No. 66, publicado en el Periódico Oficial\nNo. 109, Índice, de fecha 31 de diciembre de 2021, Tomo CXXVIII, expedido por la H. XXIV\nLegislatura, siendo Gobernadora Constitucional la C. Marina del Pilar Ávila Olmeda 20212027;\nARTÍCULO 107.- Fue reformado mediante Decreto No. 66, publicado en el Periódico Oficial\nNo. 109, Índice, de fecha 31 de diciembre de 2021, Tomo CXXVIII, expedido por la H. XXIV\nLegislatura, siendo Gobernadora Constitucional la C. Marina del Pilar Ávila Olmeda 20212027;\nARTÍCULO 111.- Fue reformado mediante Decreto No. 66, publicado en el Periódico Oficial\nNo. 109, Índice, de fecha 31 de diciembre de 2021, Tomo CXXVIII, expedido por la H. XXIV\nLegislatura, siendo Gobernadora Constitucional la C. Marina del Pilar Ávila Olmeda 20212027;\nARTÍCULO 116.- Fue reformado mediante Decreto No. 66, publicado en el Periódico Oficial\nNo. 109, Índice, de fecha 31 de diciembre de 2021, Tomo CXXVIII, expedido por la H. XXIV\nLegislatura, siendo Gobernadora Constitucional la C. Marina del Pilar Ávila Olmeda 20212027;\nARTÍCULO 130.- Fue reformado mediante Decreto No. 66, publicado en el Periódico Oficial\nLegislatura, siendo Gobernadora Constitucional la C. Marina del Pilar Ávila Olmeda 20212027;\nARTÍCULO 132.- Fue reformado mediante Decreto No. 66, publicado en el Periódico Oficial\nLegislatura, siendo Gobernadora Constitucional la C. Marina del Pilar Ávila Olmeda 20212027;\nLey del Sistema Estatal de Seguridad Ciudadana de Baja California. Página 123\n.\nActualización Legislativa.\nÚltima Reforma P.O. No. 54, Índice, 05-Sep-2025\nARTÍCULO 134.- Fue reformado mediante Decreto No. 66, publicado en el Periódico Oficial\nNo. 109, Índice, de fecha 31 de diciembre de 2021, Tomo CXXVIII, expedido por la H. XXIV\nLegislatura, siendo Gobernadora Constitucional la C. Marina del Pilar Ávila Olmeda 20212027; fue reformado mediante Decreto No. 119, publicado en el Periódico Oficial No. 43, Número Especial, de fecha 21 de julio de 2025, Tomo CXXXII, expedido por la H. XXV\nLegislatura, siendo Gobernadora Constitucional la C. Marina del Pilar Ávila Olmeda 20212027;\nARTÍCULO 135.- Fue reformado mediante Decreto No. 66, publicado en el Periódico Oficial\nNo. 109, Índice, de fecha 31 de diciembre de 2021, Tomo CXXVIII, expedido por la H. XXIV\nLegislatura, siendo Gobernadora Constitucional la C. Marina del Pilar Ávila Olmeda 20212027;\nARTÍCULO 137.- Fue reformado mediante Decreto No. 66, publicado en el Periódico Oficial\nNo. 109, Índice, de fecha 31 de diciembre de 2021, Tomo CXXVIII, expedido por la H. XXIV\nLegislatura, siendo Gobernadora Constitucional la C. Marina del Pilar Ávila Olmeda 20212027; fue reformado mediante Decreto No. 119, publicado en el Periódico Oficial No. 43, Número Especial, de fecha 21 de julio de 2025, Tomo CXXXII, expedido por la H. XXV\nLegislatura, siendo Gobernadora Constitucional la C. Marina del Pilar Ávila Olmeda 20212027;\nARTÍCULO 138.- Fue reformado mediante Decreto No. 66, publicado en el Periódico Oficial\nNo. 109, Índice, de fecha 31 de diciembre de 2021, Tomo CXXVIII, expedido por la H. XXIV\nLegislatura, siendo Gobernadora Constitucional la C. Marina del Pilar Ávila Olmeda 20212027;\nARTÍCULO 139.- Fue reformado mediante Decreto No. 66, publicado en el Periódico Oficial\nNo. 109, Índice, de fecha 31 de diciembre de 2021, Tomo CXXVIII, expedido por la H. XXIV\nLegislatura, siendo Gobernadora Constitucional la C. Marina del Pilar Ávila Olmeda 20212027;\nARTÍCULO 141.- Fue reformado mediante Decreto No. 66, publicado en el Periódico Oficial\nLegislatura, siendo Gobernadora Constitucional la C. Marina del Pilar Ávila Olmeda 20212027;\nARTÍCULO 152.- Fue reformado mediante Decreto No. 66, publicado en el Periódico Oficial\nLegislatura, siendo Gobernadora Constitucional la C. Marina del Pilar Ávila Olmeda 20212027;\nARTÍCULO 153.- Fue reformado mediante Decreto No. 66, publicado en el Periódico Oficial\nLey del Sistema Estatal de Seguridad Ciudadana de Baja California. Página 124\n.\nActualización Legislativa.\nÚltima Reforma P.O. No. 54, Índice, 05-Sep-2025\nLegislatura, siendo Gobernadora Constitucional la C. Marina del Pilar Ávila Olmeda 20212027;\nARTÍCULO 154.- Fue reformado mediante Decreto No. 221, publicado en el Periódico Oficial\nNo. 16, Índice, de fecha 31 de marzo de 2023, Tomo CXXX, expedido por la H. XXIV\nLegislatura, siendo Gobernadora Constitucional la C. Marina del Pilar Ávila Olmeda 20212027;\nARTÍCULO 155.- Fue reformado mediante Decreto No. 66, publicado en el Periódico Oficial\nNo. 109, Índice, de fecha 31 de diciembre de 2021, Tomo CXXVIII, expedido por la H. XXIV\nLegislatura, siendo Gobernadora Constitucional la C. Marina del Pilar Ávila Olmeda 20212027;\nARTÍCULO 161.- Fue reformado mediante Decreto No. 66, publicado en el Periódico Oficial\nNo. 109, Índice, de fecha 31 de diciembre de 2021, Tomo CXXVIII, expedido por la H. XXIV\nLegislatura, siendo Gobernadora Constitucional la C. Marina del Pilar Ávila Olmeda 20212027;\nARTÍCULO 176.- Fue reformado mediante Decreto No. 66, publicado en el Periódico Oficial\nNo. 109, Índice, de fecha 31 de diciembre de 2021, Tomo CXXVIII, expedido por la H. XXIV\nLegislatura, siendo Gobernadora Constitucional la C. Marina del Pilar Ávila Olmeda 20212027;\nARTÍCULO 186.- Fue reformado mediante Decreto No. 66, publicado en el Periódico Oficial\nNo. 109, Índice, de fecha 31 de diciembre de 2021, Tomo CXXVIII, expedido por la H. XXIV\nLegislatura, siendo Gobernadora Constitucional la C. Marina del Pilar Ávila Olmeda 20212027;\nARTÍCULO 191.- Fue reformado mediante Decreto No. 66, publicado en el Periódico Oficial\nNo. 109, Índice, de fecha 31 de diciembre de 2021, Tomo CXXVIII, expedido por la H. XXIV\nLegislatura, siendo Gobernadora Constitucional la C. Marina del Pilar Ávila Olmeda 20212027;\nARTÍCULO 194.- Fue reformado mediante Decreto No. 66, publicado en el Periódico Oficial\nLegislatura, siendo Gobernadora Constitucional la C. Marina del Pilar Ávila Olmeda 20212027;\nARTÍCULO 195.- Fue reformado mediante Decreto No. 66, publicado en el Periódico Oficial\nLegislatura, siendo Gobernadora Constitucional la C. Marina del Pilar Ávila Olmeda 20212027;\nLey del Sistema Estatal de Seguridad Ciudadana de Baja California. Página 125\n.\nActualización Legislativa.\nÚltima Reforma P.O. No. 54, Índice, 05-Sep-2025\nARTÍCULO 197.- Fue reformado mediante Decreto No. 66, publicado en el Periódico Oficial\nNo. 109, Índice, de fecha 31 de diciembre de 2021, Tomo CXXVIII, expedido por la H. XXIV\nLegislatura, siendo Gobernadora Constitucional la C. Marina del Pilar Ávila Olmeda 20212027;\nARTÍCULO 198.- Fue reformado mediante Decreto No. 66, publicado en el Periódico Oficial\nNo. 109, Índice, de fecha 31 de diciembre de 2021, Tomo CXXVIII, expedido por la H. XXIV\nLegislatura, siendo Gobernadora Constitucional la C. Marina del Pilar Ávila Olmeda 20212027;\nARTÍCULO 199.- Fue reformado mediante Decreto No. 66, publicado en el Periódico Oficial\nNo. 109, Índice, de fecha 31 de diciembre de 2021, Tomo CXXVIII, expedido por la H. XXIV\nLegislatura, siendo Gobernadora Constitucional la C. Marina del Pilar Ávila Olmeda 20212027;\nARTÍCULO 201.- Fue reformado mediante Decreto No. 66, publicado en el Periódico Oficial\nNo. 109, Índice, de fecha 31 de diciembre de 2021, Tomo CXXVIII, expedido por la H. XXIV\nLegislatura, siendo Gobernadora Constitucional la C. Marina del Pilar Ávila Olmeda 20212027;\nARTÍCULO 204.- Fue reformado mediante Decreto No. 66, publicado en el Periódico Oficial\nNo. 109, Índice, de fecha 31 de diciembre de 2021, Tomo CXXVIII, expedido por la H. XXIV\nLegislatura, siendo Gobernadora Constitucional la C. Marina del Pilar Ávila Olmeda 20212027;\nARTÍCULO 208.- Fue reformado mediante Decreto No. 66, publicado en el Periódico Oficial\nNo. 109, Índice, de fecha 31 de diciembre de 2021, Tomo CXXVIII, expedido por la H. XXIV\nLegislatura, siendo Gobernadora Constitucional la C. Marina del Pilar Ávila Olmeda 20212027;\nARTÍCULO 220.- Fue reformado mediante Decreto No. 66, publicado en el Periódico Oficial\nLegislatura, siendo Gobernadora Constitucional la C. Marina del Pilar Ávila Olmeda 20212027;\nARTÍCULO 221.- Fue reformado por Decreto No. 375, publicado en el Periódico Oficial No.\nLegislatura, siendo Gobernadora Constitucional la C. Marina del Pilar Ávila Olmeda, 20212027;\nLey del Sistema Estatal de Seguridad Ciudadana de Baja California. Página 126\n.\nActualización Legislativa.\nÚltima Reforma P.O. No. 54, Índice, 05-Sep-2025\nARTÍCULO PRIMERO TRANSITORIO DEL DECRETO No. 66, POR EL QUE SE\nREFORMA LA DENOMINACIÓN DE LA LEY DE SEGURIDAD PÚBLICA DEL ESTADO DE\nBAJA CALIFORNIA, ASÍ COMO DE LA DENOMINACIÓN DEL TÍTULO SEGUNDO\n“CENTRO DE EVALUACIÓN Y CONTROL DE CONFIANZA”; DEL TÍTULO TERCERO\n“INSTITUTO ESTATAL DE INVESTIGACIÓN Y FORMACIÓN INTERDISCIPLINARIA”;\nTÍTULO CUARTO “INFORMACIÓN ESTATAL SOBRE SEGURIDAD PÚBLICA”; TÍTULO\nQUINTO “CENTRO DE CONTROL, COMANDO, COMUNICACIÓN Y CÓMPUTO DEL\nESTADO” Y SUS RESPECTIVOS CAPÍTULOS Y NUMERALES DEL 1 AL 65; ASÍ COMO\nLOS ARTÍCULOS 66, 67, 69, 70, 72, 74, 75, 76, 77, 79, 80, 81, 82, 83, 84, 85, 86, 89, 91, 93, 94, 96, 97, 98, 99, 103, 107, 111, 116, 130, 132, 134, 135, 137, 138, 139, 141, 152, 153,\n155, 161, 176, 186, 191, 194, 195, 197, 198, 199, 201, 204, 208 Y 220; PUBLICADO EN EL\nPERIÓDICO OFICIAL No. 109, ÍNDICE, TOMO CXXVIII, DE FECHA 31 DE DICIEMBRE DE\n2021, EXPEDIDO POR LA H. XXIV LEGISLATURA, SIENDO GOBERNADORA\nCONSTITUCIONAL LA C. MARINA DEL PILAR ÁVILA OLMEDA 2021-2027.\nTRANSITORIOS\nPRIMERO.- Las presentes deberán publicarse en el Periódico Oficial del Estado de\nBaja California, y entrarán en vigor el primero de enero de 2022.\nSEGUNDO.- Dentro de los noventa días siguientes a la entrada en vigor de las presentes reformas, el Poder Ejecutivo del Estado, la Fiscalía General y los Municipios en el ámbito de sus respectivas competencias deberán emitir o realizar las adecuaciones necesarias a las disposiciones reglamentarias correspondientes, a fin de garantizar su cumplimiento.\nTERCERO.- La Licencia Oficial Colectiva que a la entrada en vigor del presente\nDecreto esté a cargo del Poder Ejecutivo del Estado, será administrada por la Secretaría.\nCUARTO.- En virtud del cambio de denominación de la Guardia Estatal de Seguridad y la Policía Estatal de Seguridad y Custodia Penitenciaria, las referencias hechas en actos o disposiciones legales y normativas a dicha Institución Policial o sus miembros, se entenderán aplicables en lo que no contravengan al presente decreto, a la Fuerza Estatal de miembros respectivamente.\nQUINTO.- Tratándose del Convenio de Coordinación celebrado entre el Secretaríado\nEjecutivo del Sistema Nacional de Seguridad Pública y el Estado de Baja California, relativo derivadas del mismo, que trasciendan a su vigencia, así como las previstas en la fracción V\nLey del Sistema Estatal de Seguridad Ciudadana de Baja California. Página 127\n.\nActualización Legislativa.\nÚltima Reforma P.O. No. 54, Índice, 05-Sep-2025 de la CLÁUSULA TERCERA de dicho Convenio, en términos del artículo 17 de la Ley de\nDisciplina Financiera de las Entidades Federativas y los Municipios.\nSEXTO.- El cumplimiento y pago de las obligaciones económicas o de cualquier índole derivadas de resoluciones judiciales y jurisdiccionales con motivos de procesos y procedimientos en los que sea o haya sido parte la Fiscalía General del Estado hasta el 31 de diciembre de 2021, quedará bajo su cargo y responsabilidad, así como la consecución de los procedimientos de ejecución que de las mismas deriven, hasta su total cumplimiento.\nSÉPTIMO.- El cumplimiento de las obligaciones que la Fiscalía General del Estado haya adquirido a través de créditos, préstamos y otros actos jurídicos que impliquen compromisos económicos hasta el 31 de diciembre de 2021, será asumido por este ente hasta su total terminación.\nDADO en Sesión Extraordinaria de la XXIV Legislatura en la Ciudad de Mexicali, B.C., a los veintisiete días del mes de diciembre del año dos mil veintiuno.\nDIP. JUAN MANUEL MOLINA GARCÍA\nPRESIDENTE\n(RÚBRICA)\nDIP. AMINTHA GUADALUPE BRICEÑO CINCO\nPROSECRETARIA\n(RÚBRICA)\nDE CONFORMIDAD CON LO DISPUESTO POR LA FRACCIÓN I DEL ARTÍCULO 49\nCALIFORNIA, IMPRÍMASE Y PUBLÍQUESE.\nMEXICALI, BAJA CALIFORNIA, A LOS VEINTINUEVE DÍAS DEL MES DE\nDICIEMBRE DEL AÑO DOS MIL VEINTIUNO.\nMARINA DEL PILAR ÁVILA OLMEDA\nGOBERNADORA DEL ESTADO\nDE BAJA CALIFORNIA\n(RÚBRICA)\nCATALINO ZAVALA MÁRQUEZ\nSECRETARIO GENERAL DE GOBIERNO\nDEL ESTADO DE BAJA CALIFORNIA\n(RÚBRICA)\nLey del Sistema Estatal de Seguridad Ciudadana de Baja California. Página 128\n.\nActualización Legislativa.\nÚltima Reforma P.O. No. 54, Índice, 05-Sep-2025\nARTÍCULO ÚNICO TRANSITORIO DEL DECRETO No. 221, POR EL QUE SE\nREFORMA EL ARTÍCULO 154; PUBLICADO EN EL PERIÓDICO OFICIAL No. 16, DE\nFECHA 31 DE MARZO DE 2023, ÍNDICE, TOMO CXXX, EXPEDIDO POR LA H. XXIV\nLEGISLATURA, SIENDO GOBERNADORA CONSTITUCIONAL LA C. MARINA DEL PILAR\nÁVILA OLMEDA 2021-2027.\nTRANSITORIOS\nÚNICO. El presente Decreto entrará en vigor al día siguiente de su publicación en el\nPeriódico Oficial del Estado\nDADO en Sesión Ordinaria de la XXIV Legislatura en la Ciudad de Mexicali, B.C., a los dieciséis días del mes de marzo del año dos mil veintitrés.\nDIP. MARÍA DEL ROCÍO ADAME MUÑOZ\nPRESIDENTA\n(RÚBRICA)\nDIP. DUNNIA MONTSERRAT MURILLO LÓPEZ\nSECRETARIA\n(RÚBRICA)\nDE CONFORMIDAD CON LO DISPUESTO POR LA FRACCIÓN I DEL ARTÍCULO 49\nCALIFORNIA, IMPRÍMASE Y PUBLÍQUESE.\nMEXICALI, BAJA CALIFORNIA, A LOS DIECISIETE DÍAS DEL MES DE MARZO DEL\nAÑO DOS MIL VEINTITRÉS.\nMARINA DEL PILAR ÁVILA OLMEDA\nGOBERNADORA DEL ESTADO\nDE BAJA CALIFORNIA\n(RÚBRICA)\nCATALINO ZAVALA MÁRQUEZ\nSECRETARIO GENERAL DE GOBIERNO\nDEL ESTADO DE BAJA CALIFORNIA\n(RÚBRICA)\nARTÍCULO SEGUNDO TRANSITORIO DEL DECRETO No. 225, POR EL QUE SE\nAPRUEBA LA REFORMA A LOS ARTÍCULOS 71 Y 75, PUBLICADO EN EL PERIÓDICO\nLey del Sistema Estatal de Seguridad Ciudadana de Baja California. Página 129\n.\nActualización Legislativa.\nÚltima Reforma P.O. No. 54, Índice, 05-Sep-2025\nEXPEDIDO POR LA H. XXIV LEGISLATURA, SIENDO GOBERNADORA\nCONSTITUCIONAL LA C. MARINA DEL PILAR ÁVILA OLMEDA 2021 – 2027.\nTRANSITORIOS\nÚNICO.- Las presentes reformas entrarán en vigor al día siguiente al de su publicación en el Periódico Oficial del Estado.\nDADO en Sesión Extraordinaria de la XXIV Legislatura en la Ciudad de Mexicali, B.C., a los veintiocho días del mes de abril del año dos mil veintitrés.\nDIP. MANUEL GUERRERO LUNA\nPRESIDENTE\n(RÚBRICA)\nDIP. ALEJANDRA MARÍA ANG HERNÁNDEZ\nSECRETARIA\n(RÚBRICA)\nDE CONFORMIDAD CON LO DISPUESTO POR LA FRACCION I DEL ARTÍCULO 49\nCALIFORNIA, IMPRÍMASE Y PUBLÍQUESE.\nMEXICALI, BAJA CALIFORNIA, A LOS DOS DÍAS DEL MES DE MAYO DEL AÑO\nDOS MIL VEINTITRÉS.\nMARINA DEL PILAR ÁVILA OLMEDA\nGOBERNADORA DEL ESTADO\nDE BAJA CALIFORNIA\n(RÚBRICA)\nCATALINO ZAVALA MÁRQUEZ\nSECRETARIO GENERAL DE GOBIERNO\nDEL ESTADO DE BAJA CALIFORNIA\n(RÚBRICA)\nARTÍCULO ÚNICO TRANSITORIO DEL DECRETO No. 292, POR EL QUE SE\nAPRUEBA LA REFORMA A LOS ARTÍCULOS 19 Y 46; PUBLICADO EN EL PERIÓDICO\nEXPEDIDO POR LA H. XXIV LEGISLATURA, SIENDO GOBERNADORA\nCONSTITUCIONAL LA C. MARINA DEL PILAR ÁVILA OLMEDA 2021 – 2027.\nLey del Sistema Estatal de Seguridad Ciudadana de Baja California. Página 130\n.\nActualización Legislativa.\nÚltima Reforma P.O. No. 54, Índice, 05-Sep-2025\nTRANSITORIOS\nÚNICO.- La presente reforma entrará en vigor al día siguiente de su publicación en el\nPeriódico Oficial del Estado.\nDADO en Sesión Ordinaria de la XXIV Legislatura en la Ciudad de Mexicali, B.C., a los siete días del mes de septiembre del año dos mil veintitrés.\nDIP. MANUEL GUERRERO LUNA\nPRESIDENTE\n(RÚBRICA)\nDIP. DUNNIA MONTSERRAT MURILLO LÓPEZ\nSECRETARIA\n(RÚBRICA)\nDE CONFORMIDAD CON LO DISPUESTO POR LA FRACCION I DEL ARTÍCULO 49\nCALIFORNIA, IMPRÍMASE Y PUBLÍQUESE.\nMEXICALI, BAJA CALIFORNIA, A LOS ONCE DÍAS DEL MES DE SEPTIEMBRE\nDEL AÑO DOS MIL VEINTITRÉS.\nMARINA DEL PILAR ÁVILA OLMEDA\nGOBERNADORA DEL ESTADO\nDE BAJA CALIFORNIA\n(RÚBRICA)\nCATALINO ZAVALA MÁRQUEZ\nSECRETARIO GENERAL DE GOBIERNO\nDEL ESTADO DE BAJA CALIFORNIA\n(RÚBRICA)\nARTÍCULO ÚNICO TRANSITORIO DEL DECRETO No. 379, POR EL QUE SE\nAPRUEBA LA REFORMA AL ARTÍCULO 221; PUBLICADO EN EL PERIÓDICO OFICIAL\nH. XXIV LEGISLATURA, SIENDO GOBERNADORA CONSTITUCIONAL LA C. MARINA\nDEL PILAR ÁVILA OLMEDA 2021-2027.\nTRANSITORIOS\nPRIMERO. El presente Decreto entrará en vigor al día siguiente de su publicación en el\nPeriódico Oficial del Estado.\nLey del Sistema Estatal de Seguridad Ciudadana de Baja California. Página 131\n.\nActualización Legislativa.\nÚltima Reforma P.O. No. 54, Índice, 05-Sep-2025\nSEGUNDO. Se contará para la instalación de las salas de lactancia, con un plazo de 90 días naturales, siguientes a la publicación de la presente reforma.\nTERCERO. La aplicación del presente Decreto estará sujeta a la disponibilidad presupuestal.\nDADO en Sesión Ordinaria de la XXIV Legislatura en la Ciudad de Mexicali, B.C., a los veinticinco días del mes de enero del año dos mil veinticuatro.\nDIP. ARACELI GERALDO NÚÑEZ\nPRESIDENTA\n(RÚBRICA)\nDIP. MANUEL GUERRERO LUNA\nSECRETARIO\n(RÚBRICA)\nDE CONFORMIDAD CON LO DISPUESTO POR LA FRACCIÓN I DEL ARTÍCULO 49\nCALIFORNIA, IMPRÍMASE Y PUBLÍQUESE.\nMEXICALI, BAJA CALIFORNIA, A LOS VEINTINUEVE DÍAS DEL MES DE ENERO\nDEL AÑO DOS MIL VEINTICUATRO.\nMARINA DEL PILAR ÁVILA OLMEDA\nGOBERNADORA DEL ESTADO\nDE BAJA CALIFORNIA\n(RÚBRICA)\nALFREDO ÁLVAREZ CÁRDENAS\nSECRETARIO GENERAL DE GOBIERNO\nDEL ESTADO DE BAJA CALIFORNIA\n(RÚBRICA)\nARTÍCULO SEGUNDO TRANSITORIO DEL DECRETO No. 48, POR EL QUE SE\nREFORMAN LOS ARTÍCULOS 56, 59, 61, 62 y 63; PUBLICADO EN PERIÓDICO OFICIAL\nLA H. XXV LEGISLATURA, SIENDO GOBERNADORA CONSTITUCIONAL LA C. MARINA\nDEL PILAR ÁVILA OLMEDA 2021-2027.\nARTÍCULOS TRANSITORIOS\nPrimero.- Las presentes reformas entrarán en vigor al día siguiente de su publicación en el\nPeriódico Oficial del Estado.\nLey del Sistema Estatal de Seguridad Ciudadana de Baja California. Página 132\n.\nActualización Legislativa.\nÚltima Reforma P.O. No. 54, Índice, 05-Sep-2025\nSegundo.- Dentro de un plazo de 90 días naturales contados a partir de la entrada en vigor de la presente reforma, se deberá adecuar el Reglamento Interno de la Secretaría de\nSeguridad Ciudadana.\nTercero.- Los derechos laborales de las personas servidoras públicas y demás personal del\nCentro de Control, Comando, Comunicación, Cómputo, Calidad y Contacto Ciudadano del\nEstado de Baja California serán respetados en su totalidad. Los recursos materiales con que cuente el citado Centro, serán transferidos a la Fiscalía General del Estado.\nCuarto.- Los recursos humanos, materiales, presupuestales y demás que estén asignados para la operación del Centro de Control, Comando, Comunicación, Cómputo, Calidad y\nContacto Ciudadano del Estado y el Servicio de Asistencia Telefónica, pasarán a cargo de la\nFiscalía General del Estado de Baja California y se continuarán realizando las funciones sustantivas correspondientes.\nDADO en Sesión Ordinaria de la XXV Legislatura en la Ciudad de Mexicali, B.C., a los treinta días del mes de enero del año dos mil veinticinco.\nDIP. EVELYN SÁNCHEZ SÁNCHEZ\nPRESIDENTA\n(RÚBRICA)\nDIP. MICHELLE ALEJANDRA TEJEDA MEDINA\nSECRETARIA\n(RÚBRICA)\nDE CONFORMIDAD CON LO DISPUESTO POR LA FRACCIÓN I DEL ARTÍCULO 49\nCALIFORNIA, IMPRÍMASE Y PUBLÍQUESE.\nMEXICALI, BAJA CALIFORNIA A LOS 31 DÍAS DEL MES DE ENERO DEL AÑO\nDOS MIL VEINTICINCO.\nMARINA DEL PILAR ÁVILA OLMEDA\nGOBERNADORA DEL ESTADO DE\nBAJA CALIFORNIA\n(RÚBRICA)\nALFREDO ÁLVAREZ CÁRDENAS\nSECRETARIO GENERAL DE GOBIERNO\nDEL ESTADO DE BAJA CALIFORNIA\n(RÚBRICA)\nLey del Sistema Estatal de Seguridad Ciudadana de Baja California. Página 133\n.\nActualización Legislativa.\nÚltima Reforma P.O. No. 54, Índice, 05-Sep-2025\nSENTENCIA DICTADA A CONTROVERCIA CONSTITUCIONAL 505/2023,\nNOTIFICADA AL CONGRESO DEL ESTADO DE BAJA CALIFORNIA EL DÍA 25 DE\nMARZO DE 2025, MEDIANTE LA CUAL SE RESOLVIÓ EN LOS TÉRMINOS SIGUIENTES:\n“PRIMERO. Es procedente y fundada la presente controversia constitucional.\nSEGUNDO. Se declara la invalidez del artículo 46 de la Ley del Sistema Estatal de Seguridad Ciudadana de Baja California, reformado mediante el DECRETO No. 292, publicado en el Periódico Oficial de dicha entidad federativa el veinticinco de septiembre de dos mil veintitrés, la cual surtirá sus efectos generales a partir de la notificación de estos puntos resolutivos al Congreso de dicho Estado.\nTERCERO. Publíquese esta resolución en el Diario Oficial de la Federación, en el Periódico Oficial del Estado de Baja California, así como en el Semanario Judicial de la Federación y su Gaceta.”\n…\n…\nAtentamente\nCiudad de México; 24 de marzo de 2025\nLICENCIADO RAFAEL COELLO CETINA\n(RÚBRICA)\nARTÍCULO QUINTO TRANSITORIO DEL DECRETO No. 119, POR EL QUE SE\nAPRUEBA LA REFORMA A LOS ARTÍCULOS 41, 97, 134 Y 137; PUBLICADO EN\nPERIÓDICO OFICIAL No. 43, NÚMERO ESPECIAL, DE FECHA 21 DE JULIO DE 2025,\nTOMO CXXXII, EXPEDIDO POR LA H. XXV LEGISLATURA, SIENDO GOBERNADORA\nCONSTITUCIONAL LA C. MARINA DEL PILAR ÁVILA OLMEDA 2021-2027.\nARTÍCULO TRANSITORIO\nÚNICO.- Las presentes reformas entrarán en vigor al día siguiente de su publicación en el\nPeriódico Oficial del Estado de Baja California.\nDADO en Sesión Ordinaria de la XXV Legislatura en la Ciudad de Mexicali, B.C., a los diez días del mes de julio del año dos mil veinticinco.\nDIP. MICHELLE ALEJANDRA TEJEDA MEDINA\nPRESIDENTA\n(RÚBRICA)\nDIP. MARÍA TERESA MÉNDEZ VÉLEZ\nPROSECRETARIA\n(RÚBRICA)\nLey del Sistema Estatal de Seguridad Ciudadana de Baja California. Página 134\n.\nActualización Legislativa.\nÚltima Reforma P.O. No. 54, Índice, 05-Sep-2025\nDE CONFORMIDAD CON LO DISPUESTO POR LA FRACCIÓN I DEL ARTÍCULO 49\nCALIFORNIA, IMPRÍMASE Y PUBLÍQUESE.\nMEXICALI, BAJA CALIFORNIA A LOS 10 DÍAS DEL MES DE JULIO DEL AÑO DOS\nMIL VEINTICINCO.\nMARINA DEL PILAR ÁVILA OLMEDA\nGOBERNADORA DEL ESTADO DE\nBAJA CALIFORNIA\n(RÚBRICA)\nALFREDO ÁLVAREZ CÁRDENAS\nSECRETARIO GENERAL DE GOBIERNO\nDEL ESTADO DE BAJA CALIFORNIA\n(RÚBRICA)\nARTÍCULO SEGUNDO TRANSITORIO DEL DECRETO No. 120, POR EL QUE SE\nAPRUEBA LA REFORMA AL ARTÍCULO 29, PUBLICADO EN EL PERIÓDICO OFICIAL No.\n54, ÍNDICE, DE FECHA 05 DE SEPTIEMBRE DE 2025, TOMO CXXXII; EXPEDIDO POR\nLA H. XXV LEGISLATURA, SIENDO GOBERNADORA CONSTITUCIONAL LA C. MARINA\nDEL PILAR ÁVILA OLMEDA 2021-2027.\nTRANSITORIO\nÚnico. La presente reforma entrará en vigor al día siguiente al de su publicación en el\nPeriódico Oficial del Estado.\nDADO en Sesión Ordinaria de la XXV Legislatura en la Ciudad de Mexicali, B.C., a los catorce días del mes de agosto del año dos mil veinticinco.\nDIP. JAIME EDUARDO CANTÓN ROCHA\nPRESIDENTE\n(RÚBLICA)\nDIP. MICHELLE ALEJANDRA TEJEDA MEDINA\nSECRETARIA\n(RÚBLICA)\nDE CONFORMIDAD CON LO DISPUESTO POR LA FRACCIÓN I DEL ARTÍCULO 49\nCALIFORNIA, IMPRÍMASE Y PUBLÍQUESE.\nMEXICALI, BAJA CALIFORNIA, A LOS 18 DÍAS DEL MES DE AGOSTO DEL AÑO\nDOS MIL VEINTICINCO.\nLey del Sistema Estatal de Seguridad Ciudadana de Baja California. Página 135\n.\nActualización Legislativa.\nMARINA DEL PILAR ÁVILA OLMEDA\nGOBERNADORA DEL ESTADO\nDE BAJA CALIFORNIA\n(RÚBRICA)\nALFREDO ÁLVAREZ CÁRDENAS\nSECRETARIO GENERAL DE GOBIERNO\nDEL ESTADO DE BAJA CALIFORNIA\n(RÚBRICA)\nLey del Sistema Estatal de Seguridad Ciudadana de Baja California. Página 136",
  "ordenamiento": "REGLAMENTO",
  "jurisdiccion": "BAJA CALIFORNIA",
  "fuente_oficial": "Periódico Oficial",
  "FECHA PER OFIC": "2025/08/05",
  "ESTATUS": "VIGENTE",
  "TOMO": "TOMO_V",
  "URL": "https://www.congresobc.gob.mx/Documentos/ProcesoParlamentario/Leyes/TOMO_V/20250905_LEYSEGCIUDADANA.PDF",
  "es_escaneado": false,
  "tiene_tablas": false,
  "materia": [
    "penal",
    "seguridad",
    "justicia"
  ]
}