{
  "titulo": "Ley DE ATENCIÓN y PREVENCIÓN DE LA VIOLENCIA FAMILIAR PARA EL ESTADO DE BAJA CALIFORNIA",
  "Contenido": "EL ESTADO DE BAJA CALIFORNIA\nPublicado en el Periódico Oficial No. 31,\nCAPITULO PRIMERO\nDISPOSICIONES GENERALES\nARTICULO 1.- Las disposiciones contenidas en la presente Ley son de orden público e interés social y tienen por objeto establecer las bases y procedimientos tendientes a salvaguardar la integridad física, psicológica, sexual, económica y patrimonial de los miembros de la familia, mediante la atención y prevención de la violencia familiar en el\nEstado de Baja California.\nArtículo Reformado\nARTICULO 2.- Se considera como violencia familiar, todo acto de poder u omisión intencional, dirigido a dominar, someter, controlar o agredir física, verbal, psicológica, económica, sexual o patrimonialmente a cualquier miembro de la familia, dentro o fuera del domicilio y que tiene por efecto causar daño en cualquiera de los aspectos entendidos por esta Ley como:\nPárrafo Reformado\nI.- Físico: todo acto de agresión intencional en el que se utilice alguna parte del cuerpo, algún objeto, arma o sustancia para sujetar, inmovilizar o causar daño a la integridad física del otro\nFracción Reformada\nII.- Psicológico: es la acción u omisión que provoca, en quien lo recibe alteraciones psicológicas o trastornos psiquiátricos;\nIII.- Sexual: es la acción mediante la cual se induce o se impone la realización de prácticas sexuales no deseadas o respecto de las cuales se tiene incapacidad para consentir, y\nIV.- Económico: toda omisión por la cual no se logre cubrir las necesidades básicas de las víctimas a efecto de ejercer control a través de recursos económicos.\nV.- Verbal: toda palabra o series de palabras proferidas con las cuales se busque menoscabar la integridad moral de la víctima.\nVI.- Patrimonial: Todo acto u omisión que ocasionen daño directo o indirecto, a bienes muebles o inmuebles, tales como perturbación en la propiedad o posesión, sustracción, destrucción, menoscabo, desaparición, ocultamiento o retención de objetos, documentos personales, bienes o valores, derechos patrimoniales o recursos económicos.\nFracción Adicionada\nLey de Atención y Prevención de la Violencia Familiar para el Estado de Baja California. Página 1\nVII.- Cualquiera otra forma análoga que lesione o sea susceptibles de dañar la dignidad, integridad o libertad de las personas.\nFracción Adicionada\nArtículo Reformado\nARTÍCULO 3.- Son autoridades responsables de la aplicación de esta Ley:\nI.- El Ejecutivo del Estado por conducto de:\na) La Secretaría General de Gobierno;\nb) La Secretaría de Seguridad Ciudadana;\nTexto del Inciso Recorrido y Reformado\nc) La Secretaría de Salud;\nTexto del Inciso Recorrido\nd) Secretaría de Inclusión Social e Igualdad de Género;\nTexto del Inciso Recorrido y Reformado\ne) La Secretaría de Educación;\nTexto del Inciso Recorrido y Reformado\nf) Dirección de Comunicación Social;\nTexto del Inciso Recorrido\ng) El Instituto de la Mujer;\nTexto del Inciso Recorrido\nh) El Instituto de la Juventud;\nTexto del Inciso Recorrido\ni) El Sistema para el Desarrollo Integral de la Familia;\nTexto del Inciso Recorrido\nj) La Procuraduría de Protección de Niñas, Niños y Adolescentes del Estado, Texto del Inciso Recorrido y Reformado\nFracción Reformada\nII. Los ayuntamientos; y,\nFracción Reformada\nIII. La Fiscalía General del Estado.\nFracción Adicionada\nArtículo Reformado\nARTICULO 4.- Para los efectos de esta Ley, se entiende por:\nI. Atención: Todas aquellas acciones que tienen por objeto salvaguardar la integridad y derechos de la víctima de la violencia familiar, así como el tratamiento integral de quien la genere;\nLey de Atención y Prevención de la Violencia Familiar para el Estado de Baja California. Página 2\nII. Prevención: Las acciones encaminadas a la promoción de una cultura que favorezca la creación de un marco objetivo de libertad, equidad e igualdad entre los miembros de la familia, eliminando las causas y patrones de conducta que generan y refuerzan la violencia familiar;\nIII. Concertación: A la conjunción de medios y esfuerzos de manera armónica, eficiente, rápida e imparcial entre las autoridades y la sociedad organizada para la realización de actividades encaminadas a la erradicación de la violencia familiar del Estado de Baja California;\nIV. Coordinación: A la unión de medios y esfuerzos de manera armónica, eficiente, rápida e imparcial entre la Administración Pública Estatal y la sociedad organizada para la realización de actividades encaminadas a la erradicación de la Violencia Familiar del Estado de Baja California;\nV. Víctima de la Violencia Familiar: A la persona o personas que sufran cualquiera de los actos u omisiones de naturaleza física, psicológica, sexual y económica, en su perjuicio, y que se encuentren contempladas por el artículo 2º de esta Ley;\nVI. Generador de la Violencia Familiar: Es la persona que realiza cualquier acto u omisión señalados en el Artículo 2º, en perjuicio de la persona con la que tenga o haya tenido algún vínculo familiar;\nVII. Miembros de la Familia: Aquellas personas que conforman o conformaron una familia, quedando comprendidos descendientes, ascendientes y parientes colaterales sin limitación de grado o afines hasta el cuarto grado y, el adoptante o adoptado;\nVIII. Ley: A la Ley de Atención y Prevención de la Violencia Familiar para el Estado de\nBaja California;\nIX. Procuraduría: La Procuraduría de Protección de Niñas, Niños y Adolescentes del\nEstado;\nFracción Reformada\nX. Programa: Al Programa para la Atención y Prevención de la Violencia Familiar, y\nXI. Consejo: Al Consejo para la Atención y Prevención de la Violencia Familiar en el\nEstado de Baja California.\nArtículo Reformado\nARTICULO 5.- La presente Ley reconoce como derechos de la víctima de la violencia familiar la atención y prevención; y del generador de la misma la atención integral que deban recibir, conforme a esta Ley, sin menoscabo de los derechos establecidos por la demás ordenamientos que tengan por objeto proteger los derechos de la mujer, de niñas, niños y adolescentes, de personas que no tienen la capacidad para comprender el significado del hecho, de las personas adultas mayores de sesenta años de edad y personas\nLey de Atención y Prevención de la Violencia Familiar para el Estado de Baja California. Página 3 con condición de discapacidad, así como la organización, desarrollo y armonía del orden familiar.\nArtículo Reformado\nARTICULO 6.- La aplicación de esta Ley no afectará el ejercicio de los derechos que en materia civil y penal en la entidad, así como tampoco afectará los principios procesales aplicables en controversias del orden familiar.\nCAPITULO SEGUNDO\nCONSEJO PARA LA ATENCION Y PREVENCION\nDE LA VIOLENCIA FAMILIAR\nARTICULO 7.- Se crea el Consejo como órgano de apoyo, evaluación, coordinación y concertación en materia de atención y prevención de la violencia familiar en el Estado. El\nConsejo tendrá carácter honorario.\nARTÍCULO 8.- El Consejo se integrará por:\nI. Una Presidencia, encabezada por la persona titular de la Procuraduría;\nFracción Reformada\nII. Una Secretaría, encabezada por la persona titular de la Fiscalía General del\nEstado;\nFracción Reformada\nIII. Seis Vocales, que serán las personas titulares o representantes de:\nFracción Reformada\na) La Secretaría General de Gobierno;\nb) La Secretaría de Educación;\nInciso Reformado\nc) La Secretaría de Inclusión Social e Igualdad de Género;\nInciso Reformado\nd) La Secretaría de Salud;\ne) La Secretaría de Seguridad Ciudadana;\nInciso Reformado\nf) El Instituto de la Mujer; y,\nIV. Una persona representante por cada municipio, que será electa por la persona\nTitular del Ejecutivo Estatal mediante insaculación, a propuesta de las y los ciudadanos y violencia familiar.\nFracción Reformada\nLey de Atención y Prevención de la Violencia Familiar para el Estado de Baja California. Página 4\nPodrán ser invitadas a las reuniones del Consejo, la Presidencia del Congreso del\nEstado o del Tribunal Superior de Justicia, respectivamente, así como el personal del servicio público, las y los investigadores o representantes de las instituciones públicas o privadas que estén relacionadas con el objeto y materia de esta Ley.\nPárrafo Reformado\nEl Consejo designará una Secretaría Técnica, que tendrá las facultades y obligaciones establecidas en el Reglamento Interno.\nPárrafo Reformado\nArtículo Reformado\nARTÍCULO 9.- El Consejo tendrá las atribuciones siguientes:\nI. Acorde al contenido de los lineamientos e instrumentos internacionales en materia de no violencia, diseñar y proponer al Ejecutivo Estatal y a los Ayuntamientos en el ámbito de sus respectivas competencias, el Programa para la Atención y Prevención de la Violencia\nFamiliar, así como los mecanismos para medir la eficacia de las acciones que este prevea;\nFracción Reformada\nII. Fomentar la coordinación, concertación, colaboración e información entre las instituciones públicas y privadas que se ocupen de la violencia familiar;\nIII. Vigilar la aplicación y cumplimiento del Programa;\nIV. Promover la capacitación y sensibilización de las personas operadoras del sistema judicial, del personal profesional auxiliar, del policial, del sistema de salud y en general, de cualquiera que preste servicios en materia de violencia familiar, a efecto de mejorar la atención a las víctimas que requieran de su intervención, con base en los principios de igualdad de género y no discriminación;\nFracción Reformada\nV. Fomentar la realización de estudios tendientes a conocer las causas y los impactos de la violencia familiar; cuyos resultados servirán para diseñar modelos tendientes a la atención y prevención de la violencia familiar en el Estado;\nVI. Difundir los contenidos de esta Ley y de los derechos en materia de violencia familiar, cuyos resultados servirán para diseñar modelos tendientes a la atención y prevención de la violencia familiar en el Estado;\nVII. Gestionar con los medios de comunicación, a fin de que participen en la difusión de los programas, de campañas públicas encaminadas a sensibilizar y concientizar a la población sobre el problema de violencia familiar y, de las medidas de atención y prevención de la violencia familiar;\nFracción Reformada\nVIII. Proponer al Ejecutivo del Estado el proyecto de Reglamento Interno;\nFracción Reformada\nLey de Atención y Prevención de la Violencia Familiar para el Estado de Baja California. Página 5\nIX. Proponer ante los Municipios las políticas públicas de prevención basadas en los trabajos realizados por el consejo; y,\nFracción Reformada\nX. Conforme al resultado de la evaluación de las acciones del programa, proponer a recomendaciones necesarias para el eficaz cumplimiento de las acciones a su cargo, en materia de atención y prevención de la violencia familiar.\nFracción Adicionada\nArtículo Reformado\nARTICULO 10.- El Consejo deberá sesionar en forma ordinaria por lo menos una vez cada dos meses, y de manera extraordinaria cuando lo estime necesario.\nARTÍCULO 11.- Las personas integrantes del Consejo tendrán voz y voto en las sesiones y asuntos, mientras que las y los invitados únicamente el derecho a voz.\nArtículo Reformado\nARTÍCULO 12.- Las personas integrantes del Consejo enunciados en el Artículo 8, fracción IV, de esta Ley durarán tres años en su ejercicio.\nArtículo Reformado\nARTÍCULO 13.- La organización y el funcionamiento del Consejo, así como las facultades y suplencias de las personas integrantes, se establecerán en el Reglamento\nInterno.\nArtículo Reformado\nCAPITULO TERCERO\nPROGRAMA PARA LA ATENCION Y PREVENCION\nDE LA VIOLENCIA FAMILIAR\nARTICULO 14.- E Programa, establecerá las estrategias, acciones y objetivos a que deberán sujetarse las dependencias y entidades de la administración pública estatal y municipal en el ámbito de su competencia, con la participación que corresponda de los sectores privado y social, para propiciar la atención y prevención de la violencia familiar. con las autoridades competentes. presupuestal, así como a las disposiciones y lineamientos que sobre el particular dicten las autoridades competentes.\nArtículo Reformado\nLey de Atención y Prevención de la Violencia Familiar para el Estado de Baja California. Página 6\nARTÍCULO 15.- El Programa, deberá ser aprobado por la persona Titular del\nArtículo Reformado\nARTÍCULO 16.- Los ayuntamientos deberán procurar la concordancia de las estrategias, acciones y objetivos que aprueben con el Programa, sin perjuicio de incorporar otras acciones que estimen necesarias para la consecución de los fines del mismo.\nARTÍCULO 17.- La ejecución del Programa quedará a cargo de las dependencias y entidades de la administración pública estatal o municipal en sus respectivos ámbitos de competencia.\nCAPITULO CUARTO\nDE LA ATENCION\nARTICULO 18.- La atención de la violencia familiar tiene como finalidad salvaguardar la dignidad, la libertad, la igualdad, la integridad física y los derechos de la víctima de la violencia familiar y proporcionar el tratamiento integral a quien la genere.\nArtículo Reformado\nARTICULO 19.- La atención será de carácter especializado, teniendo las características siguientes:\nI. Tenderán a la resolución de la violencia familiar, respetando la dignidad y la diferencia de las personas involucradas a través de acciones de tipo:\na) Terapéutico, a efecto de evitar que nuevos episodios de violencia ocurran en la familia, esto se logrará a través de diferentes estrategias. En la víctima, habrá de fomentarse la superación de las secuelas psicológicas derivadas de la situación de maltrato y recuperación de la autoestima, así como el aprendizaje de habilidades que permitan identificar las fases iniciales de la violencia, a efecto de prevenirla. En el agresor, habrá de fomentarse el aprendizaje del control de sus impulsos y del manejo de sus emociones.\nb) Educativo, para difundir la adopción de prácticas familiares democráticas, orientadas a la distribución igualitaria de derechos y obligaciones.\nII. Será libre de prejuicios de género, raza, condición biopsicosocial, religión o credo, nacionalidad o de cualquier otro tipo;\nIII. Se abstendrá de asumir patrones estereotipados de comportamientos o prácticas socio-culturales basadas en conceptos de inferioridad o de subordinación entre las personas, y\nIV. Se basará en modelos psicoterapéuticos específicos para personas con perfiles definidos y contendrá acciones susceptibles de evaluación.\nArtículo Reformado\nLey de Atención y Prevención de la Violencia Familiar para el Estado de Baja California. Página 7\nARTÍCULO 20.- La atención se podrá hacer extensiva en instituciones públicas a quienes cuenten con ejecutoria relacionada con eventos de violencia familiar, a solicitud de especializado en violencia familiar contra las mujeres, penal, familiar, o especializado para adolescentes; o bien, a solicitud de la persona interesada.\nArtículo Reformado\nARTICULO 21.- La atención será proporcionada por personal especializado y en la medida de lo posible de forma multidisciplinaria.\nARTÍCULO 22.- Los órganos jurisdiccionales a través de las personas titulares, y una vez que conozcan de juicios o procesos, en donde se desprenda que existe violencia familiar, podrán solicitar a las instituciones debidamente registradas en la Procuraduría de\nProtección de Niñas, Niños y Adolescentes la realización de estudios o investigaciones, o bien que emitan informes o dictámenes respecto de procesos psicoterapéuticos de generadores y víctimas de la violencia familiar, cuando sea necesario para allegarse elementos al emitir sentencia o en general le sean de utilidad, conforme a los Códigos de\nProcedimientos Civiles y Penales para el Estado de Baja California y demás leyes aplicables.\nArtículo Reformado\nARTÍCULO 23.- La atención en materia de violencia familiar se proporcionará a través de las autoridades enunciadas en el Artículo 3, fracción I, inciso j) y fracción III.\nArtículo Reformado\nARTÍCULO 24.- Corresponde a la Procuraduría, en su ámbito de atención lo siguiente:\nI. Prestar en forma gratuita los servicios de atención psicológica, legal, educativa y social a la víctima de la violencia familiar, así como a los miembros de la familia involucrados, pudiendo gestionar aquella que no este en posibilidades de proporcionar;\nII. Cuidar que la atención, sea especializada, con personal capacitado y mediante procedimientos que cuiden la dignidad humana;\nIII. Vigilar que la asistencia proporcionada esté libre de prejuzgar sexo, orientación o preferencia sexual, raza, condición socioeconómica, de discapacidad, religión o credo, nacionalidad o de cualquier otro tipo;\nFracción Reformada\nIV. Hacer del conocimiento del Ministerio Público aquellos casos de violencia familiar que pudieran constituir un delito que se persiga de oficio;\nV. Brindar modelos psicoterapéuticos y reeducativos integrales para la víctima de la violencia familiar y del generador de la misma;\nVI. Rendir en caso de que se solicite por las autoridades competentes, informes relacionados con asuntos de violencia familiar de los que se tengan registros;\nLey de Atención y Prevención de la Violencia Familiar para el Estado de Baja California. Página 8\nVII. Gestionar ante las instituciones públicas o privadas el resguardo a la víctima de la violencia familiar;\nVIII. Elaborar estadísticas del número de víctimas de la violencia familiar atendidas, de generadores de violencia familiar canalizados, del grado de violencia familiar, su incidencia, y en general de cualquier dato relacionado con la problemática;\nIX. Llevar un registro de los procedimientos conciliatorios instaurados a efecto de tener seguimiento de los mismos y conocer su estado;\nX. Llevar un registro de las instituciones públicas, privadas y organismos sociales que proporcionen asistencia en materia de violencia familiar, y\nXI. Las demás que le señalen ésta u otras leyes.\nArtículo Reformado\nARTÍCULO 25.- Corresponde a la Fiscalía General del Estado, para el debido cumplimiento de esta Ley:\nPárrafo Reformado\nI. Proporcionar a la víctima de la violencia familiar, la protección y auxilio derivado del artículo 20 apartado C de la Constitución Política de los Estados Unidos Mexicanos, pudiendo gestionar ante otras autoridades aquella que no esté en posibilidades de proporcionar;\nII. Brindar asistencia a la víctima de violencia familiar, cuando así lo solicite a través de la unidad administrativa competente, y\nIII. Coadyuvar con los distintos organismos sociales que participan en la protección de las víctimas de la violencia familiar, en las actividades de aquellos centros o sistemas que brindan atención, protección y auxilio a la víctima de la violencia familiar.\nIV.- Llevar el registro de los delitos que se cometan como consecuencia de violencia familiar, mismo que deberá de remitir semestralmente al Consejo para la Atención y\nPrevención de la Violencia Familiar en el Estado de Baja California.\nArtículo Reformado\nCAPITULO QUINTO\nDE LA PREVENCIÓN\nARTICULO 26.- La prevención de la violencia familiar estará orientada a propiciar una que integran la familia, eliminando las causas y patrones que generan y refuerzan la violencia familiar con el propósito de erradicarla, mediante la promoción de valores a través de la elaboración y ejecución de políticas públicas.\nARTÍCULO 27.- Se establecen como políticas públicas de prevención las siguientes:\nLey de Atención y Prevención de la Violencia Familiar para el Estado de Baja California. Página 9\nI. Promoción del estudio e investigación de las causas y consecuencias de la violencia familiar, y con base en los resultados, adopción de las actuaciones necesarias para su erradicación;\nII. Impulso del proceso de modificación de patrones socio-culturales de conducta de mujeres y hombres bajo la perspectiva de género, incluyendo el diseño de programas de educación apropiados a todos los niveles, para contrarrestar prejuicios, costumbres y practicas basadas en la supuesta superioridad o inferioridad de los géneros; así como la impartición de educación sexual integral y reproductiva que implique en sus contenidos el ejercicio responsable de la sexualidad, la planeación familiar, la maternidad y la paternidad responsable, la prevención de los embarazos adolescentes y de las infecciones de transmisión sexual;\nFracción Reformada\nIII. Impulso a la formación de personas promotoras comunitarias cuya función básica sea estimular el programa para la atención y prevención de la violencia familiar;\nFracción Reformada\nIV. Promoción de estrategias de capacitación y difusión para el conocimiento, detección y prevención de la violencia familiar;\nV. Diseño de programas de capacitación para servidores públicos y de los organismos sociales que participen en la protección de las víctimas de la violencia familiar, a efecto de que su labor se sujete a los lineamientos de esta Ley, y\nVI. Elaboración de las estadísticas correspondientes que permitan conocer la diversa información que se pueda registrar en materia de Violencia Familiar.\nArtículo Reformado\nARTICULO 28.- Las políticas públicas de prevención se implementarán a través de las autoridades enunciadas en el Artículo 3º, fracción I, por lo que al Estado le corresponden\nARTICULO 29.- Para la implementación de las políticas públicas de prevención, el personal de las instituciones a quienes corresponda la orientación, investigación, y prevención de la violencia familiar deberá contar con la capacitación correspondiente, así como con antecedentes personales de eficiencia, honradez, profesionalismo y respeto a la familiar, deberá participar en los programas de capacitación y actualización que se diseñen, basados en los principios de equidad, igualdad y con perspectiva de género. sensibilización y compresión de la complejidad y multicausalidad de la violencia familiar, a la\nLey de Atención y Prevención de la Violencia Familiar para el Estado de Baja California. Página 10 compromiso de servicio acorde al objeto de esta Ley.\nARTÍCULO 30.- Los organismos sociales, las autoridades, dependencias e instituciones señaladas en la Ley, deberán coordinarse en forma eficiente, rápida e imparcial a través de convenios de colaboración o mediante los mecanismos legales conducentes, a efecto de instrumentar y ejecutar las políticas públicas de prevención que prevé esta Ley.\nAsimismo, deberán coordinarse, considerando la disponibilidad presupuestaria, para la realización de campañas de difusión e información a las y los habitantes del Estado sobre los programas de atención, asistencia y prevención de la violencia familia, debiendo priorizar el interés superior de la niñez y la familia.\nArtículo Reformado\nCAPITULO SEXTO\nPROCEDIMIENTO CONCILIATORIO Y SU SEGUIMIENTO\nARTÍCULO 31.- Derogado.\nArtículo Derogado\nARTÍCULO 32.- Derogado.\nArtículo Derogado\nCAPITULO SEPTIMO\nPROCEDIMIENTO PARA APLICAR SANCIONES\nARTÍCULO 33.- La Procuraduría impondrá las sanciones previstas en el Título\nSéptimo de la Ley de Protección y Defensa de los Derechos de las Niñas, Niños y\nAdolescentes del Estado de Baja California, cuando se cometa alguna de las infracciones previstas en dicho ordenamiento.\nArtículo Reformado\nARTÍCULO 34.- Las sanciones se determinarán tomando en cuenta los elementos siguientes:\nI. Derogado.\nFracción Derogada\nII. Derogado.\nFracción Derogada\nIII. Los daños que se hayan producido o puedan producirse en la salud de las victimas de la violencia familiar;\nIV. Las condiciones personales y socioeconómicas del generador de la violencia familiar; y\nLey de Atención y Prevención de la Violencia Familiar para el Estado de Baja California. Página 11\nV. El carácter o condición de reincidente del generador de la violencia familiar.\nArtículo Reformado\nARTÍCULO 35.- Derogado.\nArtículo Reformado\nArtículo Derogado\nARTÍCULO 36.- La Procuraduría, sin perjuicio de la sanción, apercibirá al infractor para que no reincida en la comisión de las infracciones que prevé en el Título Séptimo de la\nLey de Protección y Defensa de los Derechos de las Niñas, Niños y Adolescentes del Estado de Baja California, haciéndole saber las consecuencias legales de su conducta.\nArtículo Reformado\nARTÍCULO 37.- La autoridad podrá abstenerse de sancionar a la persona infractora, por una sola vez, cuando lo ameriten los antecedentes y circunstancias de la persona infractora.\nArtículo Reformado\nARTICULO 38.- Las sanciones económicas que se impongan constituirán créditos fiscales a favor del erario estatal, y se harán efectivas mediante el procedimiento de ejecución correspondiente. Tendrán la prelación prevista para dichos créditos y se sujetarán a las disposiciones fiscales aplicables en esta materia.\nEl monto de las sanciones se destinará a la ejecución del Programa.\nARTICULO 39.- La facultad de aplicar las sanciones económicas prescribe en seis meses, plazo que contará a partir del día siguiente a aquél en que se hubiere cometido la infracción.\nARTICULO 40.- El incumplimiento de las obligaciones, facultades o funciones que, por omisión o comisión, hagan las autoridades consideradas como competentes en la aplicación de esta Ley, serán sancionadas en los términos de la Ley de Responsabilidades\nAdministrativas del Estado de Baja California, con independencia de los supuestos normativos que en materia penal pueda actualizar su conducta.\nArtículo Adicionado\nArtículo Reformado\nARTÍCULOS TRANSITORIOS\nARTICULO PRIMERO.- La presente Ley entrará en vigor al día siguiente de su publicación en el Periódico Oficial del Estado de Baja California.\nARTICULO SEGUNDO.- El Ejecutivo del Estado dentro de los treinta días siguientes a la entrada en vigor de esta Ley, convocara por única ocasión y por medio de los tres periódicos de mayor circulación en el Estado, a los ciudadanos y organizaciones sociales relacionados con la atención y prevención de la violencia familiar de cada municipio, a que\nLey de Atención y Prevención de la Violencia Familiar para el Estado de Baja California. Página 12\nAtención y Prevención de la Violencia Familiar en el Estado de Baja California. Las subsecuentes elecciones para integrar dicho Consejo, se harán en los plazos que se determinen en el Reglamento Interno.\nARTÍCULO TERCERO.- El Ejecutivo de Estado dentro de los sesenta días a partir de la entrada en vigor de esta Ley, deberá instalar el Consejo para la Atención y Prevención de la Violencia Familiar en el Estado de Baja California.\nARTICULO CUARTO.- El Consejo para la Atención y Prevención de la Violencia\nFamiliar en el Estado de Baja California dentro de los sesenta días siguientes a su instalación, deberá proponer el Programa para la Prevención y Atención de la Violencia\nFamiliar al Ejecutivo del Estado para su aprobación.\nARTICULO QUINTO.- El Ejecutivo del Estado dentro de los ciento veinte días siguientes a la entrada en vigor de esta Ley, deberá expedir el Reglamento Interno del\nConsejo para la Atención y Prevención de la Violencia Familiar en el Estado de Baja\nCalifornia.\nARTICULO SEXTO.- El Ejecutivo del Estado incluirá en el Presupuesto de Egresos para cada ejercicio, los recursos económicos suficientes para que las Dependencias y\nEntidades señaladas en esta Ley cumplan el objeto de la misma.\nARTICULO SEPTIMO.- Las Dependencias y Entidades, tendrán la obligación de implementar dentro de su ámbito competencial, las adecuaciones normativas que contribuyan a dar cumplimiento a las políticas públicas de prevención, establecidas en esta\nLey.\nARTICULO OCTAVO.- Se derogan todas aquellas disposiciones que en lo conducente se opongan al contenido de esta Ley.\nDADO en el Patio Central del Palacio Municipal de Tijuana, Baja California, declarado\nRecinto Oficial a los veintinueve días del mes de mayo del año dos mil tres.\nDIP. LAURA SANCHEZ MEDRANO\nPRESIDENTA\nDIP. JESUS ALEJANDRO RUIZ URIBE\nSECRETARIO\nDE CONFORMIDAD CON LO DISPUESTO POR LA FRACCION I DEL ARTICULO 49\nDE LA CONSTITUCION POLITICA DEL ESTADO, IMPRIMASE Y PUBLIQUESE.\nMEXICALI, BAJA CALIFORNIA, A LOS SEIS DIAS DEL MES DE JUNIO DEL AÑO\nDOS MIL TRES.\nGOBERNADOR DEL ESTADO\nLey de Atención y Prevención de la Violencia Familiar para el Estado de Baja California. Página 13\nEUGENIO ELORDUY WALTHER\nSECRETARIO GENERAL DE GOBIERNO\nBERNARDO H. MARTINEZ AGUIRRE\nLey de Atención y Prevención de la Violencia Familiar para el Estado de Baja California. Página 14\nARTICULO 1.- Fue reformado por Decreto No. 421, publicado en el Periódico Oficial\nLegislatura, siendo Gobernador Constitucional el C. Eugenio Elorduy Walther 2001-2007; fue reformado por Decreto No. 101, publicado en el Periódico Oficial No. 39. Índice, de fecha 27\nConstitucional la C. Marina del Pilar Ávila Olmeda 2021-2027;\nARTICULO 2.- Fue reformado por Decreto No. 166, publicado en el Periódico Oficial\nNo. 04, Sección IV, Tomo CXXV, de fecha 19 de enero de 2018, expedido por la H. XXII\nLegislatura, siendo Gobernador Constitucional el C. Francisco Arturo Vega de Lamadrid\n2013-2019; fue reformado por Decreto No. 268, publicado en el Periódico Oficial No. 48,\nSección II, Tomo CXXV, de fecha 19 de octubre de 2018, expedido por la H. XXII\nLegislatura, siendo Gobernador Constitucional el C. Francisco Arturo Vega de Lamadrid\n2013-2019; fue reformado por Decreto No. 101, publicado en el Periódico Oficial No. 39.\nÍndice, de fecha 27 de junio de 2025, Tomo CXXXII, expedido por la H. XXV Legislatura, siendo Gobernadora Constitucional la C. Marina del Pilar Ávila Olmeda 2021-2027;\nARTICULO 3.- Fue reformado por Decreto No. 125, publicado en el Periódico Oficial\nNo. 51, de fecha 18 de noviembre de 2005, Sección II, Tomo CXII, expedido por la H. XVIII\nLegislatura, siendo Gobernador Constitucional el C. Eugenio Elorduy Walther 2001-2007; fue reformado por Decreto No. 296, publicado en el Periódico Oficial No. 62, de fecha 06 de noviembre de 2023, Índice, Tomo CXXX, expedido por la H. XXIV Legislatura, siendo\nGobernadora Constitucional la C. Marina del Pilar Ávila Olmeda 2021-2027;\nARTICULO 4.- Fue reformado por Decreto No. 125, publicado en el Periódico Oficial\nNo. 51, de fecha 18 de noviembre de 2005, Sección II, Tomo CXII, expedido por la H. XVIII\nLegislatura, siendo Gobernador Constitucional el C. Eugenio Elorduy Walther 2001-2007; fue reformado por Decreto No. 296, publicado en el Periódico Oficial No. 62, de fecha 06 de noviembre de 2023, Índice, Tomo CXXX, expedido por la H. XXIV Legislatura, siendo\nGobernadora Constitucional la C. Marina del Pilar Ávila Olmeda 2021-2027;\nARTICULO 5.- Fue reformado por Decreto No. 125, publicado en el Periódico Oficial\nNo. 51, de fecha 18 de noviembre de 2005, Sección II, Tomo CXII, expedido por la H. XVIII\nLegislatura, siendo Gobernador Constitucional el C. Eugenio Elorduy Walther 2001-2007; fue reformado por Decreto No. 296, publicado en el Periódico Oficial No. 62, de fecha 06 de noviembre de 2023, Índice, Tomo CXXX, expedido por la H. XXIV Legislatura, siendo\nGobernadora Constitucional la C. Marina del Pilar Ávila Olmeda 2021-2027;\nARTICULO 8.- Fue reformado por Decreto No. 125, publicado en el Periódico Oficial\nLegislatura, siendo Gobernador Constitucional el C. Eugenio Elorduy Walther 2001-2007; fue reformado por Decreto No. 296, publicado en el Periódico Oficial No. 62, de fecha 06 de\nGobernadora Constitucional la C. Marina del Pilar Ávila Olmeda 2021-2027;\nARTICULO 9.- Fue reformado por Decreto No. 421, publicado en el Periódico Oficial\nLey de Atención y Prevención de la Violencia Familiar para el Estado de Baja California. Página 15\nLegislatura, siendo Gobernador Constitucional el C. Eugenio Elorduy Walther 2001-2007; fue reformado por Decreto No. 166, publicado en el Periódico Oficial No. 04, Sección IV, Tomo\nGobernador Constitucional el C. Francisco Arturo Vega de Lamadrid 2013-2019; fue reformado por Decreto No. 296, publicado en el Periódico Oficial No. 62, de fecha 06 de noviembre de 2023, Índice, Tomo CXXX, expedido por la H. XXIV Legislatura, siendo\nGobernadora Constitucional la C. Marina del Pilar Ávila Olmeda 2021-2027; fue reformado por Decreto No. 413, publicado en el Periódico Oficial No. 23, de fecha 07 de mayo de 2024, Índice, Tomo CXXXI, expedido por la H. XXIV Legislatura, siendo Gobernadora\nConstitucional la C. Marina del Pilar Ávila Olmeda 2021-2027;\nARTÍCULO 11.- Fue reformado por Decreto No. 296, publicado en el Periódico Oficial\nNo. 62, de fecha 06 de noviembre de 2023, Índice, Tomo CXXX, expedido por la H. XXIV\nLegislatura, siendo Gobernadora Constitucional la C. Marina del Pilar Ávila Olmeda 20212027;\nARTÍCULO 12.- Fue reformado por Decreto No. 296, publicado en el Periódico Oficial\nNo. 62, de fecha 06 de noviembre de 2023, Índice, Tomo CXXX, expedido por la H. XXIV\nLegislatura, siendo Gobernadora Constitucional la C. Marina del Pilar Ávila Olmeda 20212027;\nARTÍCULO 13.- Fue reformado por Decreto No. 296, publicado en el Periódico Oficial\nNo. 62, de fecha 06 de noviembre de 2023, Índice, Tomo CXXX, expedido por la H. XXIV\nLegislatura, siendo Gobernadora Constitucional la C. Marina del Pilar Ávila Olmeda 20212027;\nARTÍCULO 14.- Fue reformado por Decreto No. 166, publicado en el Periódico Oficial\nNo. 04, Sección IV, Tomo CXXV, de fecha 19 de enero de 2018, expedido por la H. XXII\nLegislatura, siendo Gobernador Constitucional el C. Francisco Arturo Vega de Lamadrid\n2013-2019;\nARTÍCULO 15.- Fue reformado por Decreto No. 166, publicado en el Periódico Oficial\nNo. 04, Sección IV, Tomo CXXV, de fecha 19 de enero de 2018, expedido por la H. XXII\nLegislatura, siendo Gobernador Constitucional el C. Francisco Arturo Vega de Lamadrid\n2013-2019; fue reformado por Decreto No. 296, publicado en el Periódico Oficial No. 62, de fecha 06 de noviembre de 2023, Índice, Tomo CXXX, expedido por la H. XXIV Legislatura, siendo Gobernadora Constitucional la C. Marina del Pilar Ávila Olmeda 2021-2027;\nARTICULO 18.- Fue reformado por Decreto No. 421, publicado en el Periódico Oficial\nLegislatura, siendo Gobernador Constitucional el C. Eugenio Elorduy Walther 2001-2007;\nARTICULO 19.- Fue reformado por Decreto No. 421, publicado en el Periódico Oficial\nLegislatura, siendo Gobernador Constitucional el C. Eugenio Elorduy Walther 2001-2007;\nARTICULO 20.- Fue reformado por Decreto No. 247, publicado en el Periódico Oficial\nLey de Atención y Prevención de la Violencia Familiar para el Estado de Baja California. Página 16 siendo Gobernador Constitucional el C. Eugenio Elorduy Walter 2001-2007, fue reformado por Decreto No. 296, publicado en el Periódico Oficial No. 62, de fecha 06 de noviembre de\n2023, Índice, Tomo CXXX, expedido por la H. XXIV Legislatura, siendo Gobernadora\nConstitucional la C. Marina del Pilar Ávila Olmeda 2021-2027;\nARTICULO 22.- Fue reformado por Decreto No. 125, publicado en el Periódico Oficial\nNo. 51, de fecha 18 de noviembre de 2005, Sección II, Tomo CXII, expedido por la H. XVIII\nLegislatura, siendo Gobernador Constitucional el C. Eugenio Elorduy Walther 2001-2007; fue reformado por Decreto No. 247, publicado en el Periódico Oficial No. 45 de fecha 27 de octubre de 2006, Tomo CXIII, expedido por la H. XVIII Legislatura siendo Gobernador\nConstitucional el C. Eugenio Elorduy Walter 2001-2007, fue reformado por Decreto No. 296, publicado en el Periódico Oficial No. 62, de fecha 06 de noviembre de 2023, Índice, Tomo\nCXXX, expedido por la H. XXIV Legislatura, siendo Gobernadora Constitucional la C. Marina del Pilar Ávila Olmeda 2021-2027;\nARTICULO 23.- Fue reformado por Decreto No. 296, publicado en el Periódico Oficial\nNo. 62, de fecha 06 de noviembre de 2023, Índice, Tomo CXXX, expedido por la H. XXIV\nLegislatura, siendo Gobernadora Constitucional la C. Marina del Pilar Ávila Olmeda 20212027;\nARTICULO 24.- Fue reformado por Decreto No. 125, publicado en el Periódico Oficial\nNo. 51, de fecha 18 de noviembre de 2005, Sección II, Tomo CXII, expedido por la H. XVIII\nLegislatura, siendo Gobernador Constitucional el C. Eugenio Elorduy Walther 2001-2007; fue reformado por Decreto No. 296, publicado en el Periódico Oficial No. 62, de fecha 06 de noviembre de 2023, Índice, Tomo CXXX, expedido por la H. XXIV Legislatura, siendo\nGobernadora Constitucional la C. Marina del Pilar Ávila Olmeda 2021-2027;\nARTICULO 25.- Fue reformado por Decreto No. 421, publicado en el Periódico Oficial\nNo. 43, de fecha 19 de octubre de 2007, Sección I, Tomo CXIV, expedido por la H. XVIII\nLegislatura, siendo Gobernador Constitucional el C. Eugenio Elorduy Walther 2001-2007;\nFue reformado por Decreto No. 404, publicado en el Periódico Oficial No. 39, de fecha 10 de septiembre de 2010, Tomo CXVII, expedido por la Honorable XIX Legislatura, siendo\nGobernador Constitucional del Estado, el C. José Guadalupe Osuna Millán 2007-2013; fue reformado por Decreto No. 296, publicado en el Periódico Oficial No. 62, de fecha 06 de noviembre de 2023, Índice, Tomo CXXX, expedido por la H. XXIV Legislatura, siendo\nGobernadora Constitucional la C. Marina del Pilar Ávila Olmeda 2021-2027;\nARTICULO 27.- Fue reformado por Decreto No. 421, publicado en el Periódico Oficial\nLegislatura, siendo Gobernador Constitucional el C. Eugenio Elorduy Walther 2001-2007; fue reformado por Decreto No. 296, publicado en el Periódico Oficial No. 62, de fecha 06 de\nGobernadora Constitucional la C. Marina del Pilar Ávila Olmeda 2021-2027; fue reformado por Decreto No. 318, publicado en el Periódico Oficial No. 70, de fecha 08 de diciembre de\n2023, Sección I, Tomo CXXX, expedido por la H. XXIV Legislatura, siendo Gobernadora\nConstitucional la C. Marina del Pilar Ávila Olmeda 2021-2027;\nLey de Atención y Prevención de la Violencia Familiar para el Estado de Baja California. Página 17\nARTICULO 30.- Fue reformado por Decreto No. 564, publicado en el Periódico Oficial\nLegislatura, siendo Gobernador Constitucional el C. Francisco Arturo Vega de Lamadrid\n2013-2019; fue reformado por Decreto No. 296, publicado en el Periódico Oficial No. 62, de siendo Gobernadora Constitucional la C. Marina del Pilar Ávila Olmeda 2021-2027;\nARTICULO 31.- Fue reformado por Decreto No. 125, publicado en el Periódico Oficial\nNo. 51, de fecha 18 de noviembre de 2005, Sección II, Tomo CXII, expedido por la H. XVIII\nLegislatura, siendo Gobernador Constitucional el C. Eugenio Elorduy Walther 2001-2007; fue derogado por Decreto No. 296, publicado en el Periódico Oficial No. 62, de fecha 06 de noviembre de 2023, Índice, Tomo CXXX, expedido por la H. XXIV Legislatura, siendo\nGobernadora Constitucional la C. Marina del Pilar Ávila Olmeda 2021-2027;\nARTICULO 32.- Fue reformado por Decreto No. 125, publicado en el Periódico Oficial\nNo. 51, de fecha 18 de noviembre de 2005, Sección II, Tomo CXII, expedido por la H. XVIII\nLegislatura, siendo Gobernador Constitucional el C. Eugenio Elorduy Walther 2001-2007; fue derogado por Decreto No. 296, publicado en el Periódico Oficial No. 62, de fecha 06 de noviembre de 2023, Índice, Tomo CXXX, expedido por la H. XXIV Legislatura, siendo\nGobernadora Constitucional la C. Marina del Pilar Ávila Olmeda 2021-2027;\nARTICULO 33.- Fue reformado por Decreto No. 125, publicado en el Periódico Oficial\nNo. 51, de fecha 18 de noviembre de 2005, Sección II, Tomo CXII, expedido por la H. XVIII\nLegislatura, siendo Gobernador Constitucional el C. Eugenio Elorduy Walther 2001-2007; fue reformado por Decreto No. 296, publicado en el Periódico Oficial No. 62, de fecha 06 de noviembre de 2023, Índice, Tomo CXXX, expedido por la H. XXIV Legislatura, siendo\nGobernadora Constitucional la C. Marina del Pilar Ávila Olmeda 2021-2027;\nARTÍCULO 34.- Fue reformado por Decreto No. 421, publicado en el Periódico Oficial\nNo. 43, de fecha 19 de octubre de 2007, Sección I, Tomo CXIV, expedido por la H. XVIII\nLegislatura, siendo Gobernador Constitucional el C. Eugenio Elorduy Walther 2001-2007; fue reformado por Decreto No. 296, publicado en el Periódico Oficial No. 62, de fecha 06 de noviembre de 2023, Índice, Tomo CXXX, expedido por la H. XXIV Legislatura, siendo\nGobernadora Constitucional la C. Marina del Pilar Ávila Olmeda 2021-2027;\nARTICULO 35.- Fue reformado por Decreto No. 125, publicado en el Periódico Oficial\nLegislatura, siendo Gobernador Constitucional el C. Eugenio Elorduy Walther 2001-2007; fue derogado por Decreto No. 296, publicado en el Periódico Oficial No. 62, de fecha 06 de\nGobernadora Constitucional la C. Marina del Pilar Ávila Olmeda 2021-2027;\nARTICULO 36.- Fue reformado por Decreto No. 125, publicado en el Periódico Oficial\nLegislatura, siendo Gobernador Constitucional el C. Eugenio Elorduy Walther 2001-2007; fue reformado por Decreto No. 296, publicado en el Periódico Oficial No. 62, de fecha 06 de\nLey de Atención y Prevención de la Violencia Familiar para el Estado de Baja California. Página 18\nGobernadora Constitucional la C. Marina del Pilar Ávila Olmeda 2021-2027;\nARTICULO 37.- Fue reformado por Decreto No. 296, publicado en el Periódico Oficial\nLegislatura, siendo Gobernadora Constitucional la C. Marina del Pilar Ávila Olmeda 20212027;\nARTICULO 40.- Fue adicionado por Decreto No. 354, publicado en el Periódico Oficial siendo Gobernador Constitucional el C. José Guadalupe Osuna Millán 2007-2013; fue reformado por Decreto No. 296, publicado en el Periódico Oficial No. 62, de fecha 06 de\nGobernadora Constitucional la C. Marina del Pilar Ávila Olmeda 2021-2027;\nLey de Atención y Prevención de la Violencia Familiar para el Estado de Baja California. Página 19\nARTICULO OCTAVO TRANSITORIO DEL DECRETO NO. 125, POR EL QUE SE\nAPRUEBAN LAS REFORMAS A LOS ARTÍCULOS 3, 4, 5, 8, 22, 24, 31, 32, 33, 35 Y 36,\nPUBLICADO EN EL PERIODICO OFICIAL NO. 51, DE FECHA 18 DE NOVIEMBRE DE\n2005, SECCIÓN II, TOMO CXII, EXPEDIDO POR LA H. XVIII LEGISLATURA, SIENDO\nGOBERNADOR CONSTITUCIONAL EL C. EUGENIO ELORDUY WALTHER 2001-2007.\nARTICULOS TRANSITORIOS\nPRIMERO.- Las presentes reformas entrarán en vigor el día siguiente de su públicación en el Periódico Oficial del Estado de Baja California.\nSEGUNDO.- Se derogan todas las disposiciones que se opongan a las presentes reformas.\nDADO.- En el Salón de Sesiones “Lic. Benito Juárez García” del Honorable Poder\nLegislativo, en la Ciudad de Mexicali, Baja California, a los tres días del mes de noviembre del año dos mil cinco.\nDIP. ELVIRA LUNA PINEDA\nPRESIDENTA\n(RÚBRICA)\nDIP. ELÍAS LÓPEZ MENDOZA\nSECRETARIO\n(RÚBRICA)\nDE CONFORMIDAD CON LO DISPUESTO POR LA FRACCION I DEL ARTICULO 49\nDE LA CONSTITUCION POLITICA DEL ESTADO, IMPRIMASE Y PUBLIQUESE.\nMEXICALI, BAJA CALIFORNIA, A LOS ONCE DIAS DEL MES DE NOVIEMBRE DEL\nAÑO DOS MIL CINCO.\nGOBERNADOR DEL ESTADO.\nEUGENIO ELORDUY WALTHER\nSECRETARIO GENERAL DE GOBIERNO\nBERNARDO H. MARTINEZ AGUIRRE\nARTICULO SEPTIMO TRANSITORIO DEL DECRETO NO. 247, POR EL QUE SE\nREFORMAN LOS ARTÍCULOS 20 Y 22, PUBLICADO EN EL PERIODICO OFICIAL NO. 45, Ley de Atención y Prevención de la Violencia Familiar para el Estado de Baja California. Página 20\nLEGISLATURA, SIENDO GOBERNADOR CONSTITUCIONAL EL C. EUGENIO ELORDUY\nWALTHER 2001-2007.\nUNICO.- Las presentes reformas entrarán en vigor a partir del primero de marzo del año dos mil siete, previa publicación en el Periódico Oficial del Estado.\nDADO en el Salón Casino del Centro Social, Cívico y Cultura Riviera de la Ciudad de Ensenada, Baja California, a los doce días del mes de septiembre del año dos mil seis.\nDIP. JORGE NÚÑEZ VERDUGO\nPRESIDENTE\n(RÚBRICA)\nDIP. CARLOS ENRIQUE JIMÉNEZ RUIZ\nSECRETARIO.\n(RÚBRICA)\nDE CONFORMIDAD CON LO DISPUESTO POR LA FRACCION I DEL ARTÍCULO 49\nMEXICALI, BAJA CALIFORNIA, A LOS DIECISIETE DIAS DEL MES DE OCTUBRE\nDEL AÑO DOS MIL SEIS.\nGOBERNADOR DEL ESTADO\nEUGENIO ELORDUY WALTER\nSECRETARIO GENERAL DE GOBIERNO\nBERNARDO H. MARTINEZ AGUIRRE.\nARTICULO TRANSITORIO DEL DECRETO NO. 421, POR EL QUE SE REFORMAN\nLOS ARTICULOS 1, 9, 18, 19, 25, 27 y 34, PUBLICADO EN EL PERIODICO OFICIAL NO.\nH. XVIII LEGISLATURA, SIENDO GOBERNADOR CONSTITUCIONAL EL C. EUGENIO\nELORDUY WALTHER 2001-2007.\nLey de Atención y Prevención de la Violencia Familiar para el Estado de Baja California. Página 21\nARTÍCULOS TRANSITORIOS\nPRIMERO.- Las presentes reformas entrarán en vigor el día siguiente de su publicación en el Periódico Oficial del Estado.\nSEGUNDO.- derogan todas las disposiciones que se opongan a la presente reforma.\nDADO.- En el Salón de Sesiones “Lic. Benito Juárez García”, en la Ciudad de\nMexicali, Baja California”, a los veinticinco días del mes de septiembre del año dos mil siete.\nDIP. RAÚL LÓPEZ MORENO\nPRESIDENTE\n(RÚBRICA)\nDIP. ABRAHAM CORREA ACEVEDO\nSECRETARIO\n(RÚBRICA)\nDE CONFORMIDAD CON LO DISPUESTO POR LA FRACCION I DEL ARTICULO 49\nDE LA CONSTITUCION POLITICA DEL ESTADO, IMPRIMASE Y PUBLÍQUESE.\nMEXICALI, BAJA CALIFORNIA, AL PRIMER DIA DEL MES DE OCTUBRE DEL AÑO\nDOS MIL SIETE.\nGOBERNADOR DEL ESTADO\nEUGENIO ELORDUY WALTHER\n(RÚBRICA)\nSECRETARIO GENERAL DE GOBIERNO\nBERNARDO H. MARTINEZ AGUIRRE\n(RÚBRICA)\nARTICULO PRIMERO TRANSITORIO DEL DECRETO No. 404, POR EL QUE SE\nREFORMA EL ARTICULO 25, PUBLICADO EN EL PERIODICO OFICIAL No. 39, DE\nLEGISLATURA, SIENDO GOBERNADOR CONSTITUCIONAL EL C. JOSE GUADALUPE\nOSUNA MILLAN 2007-2013.\nTRANSITORIOS:\nÚNICO.- Las presentes reformas entrarán en vigor al día siguiente de su publicación en el Periódico Oficial del Estado en la Ciudad de Mexicali, y en forma sucesiva en los demás Municipios, del Estado de Baja California, conforme al siguiente orden:\nLey de Atención y Prevención de la Violencia Familiar para el Estado de Baja California. Página 22\nI.- Ensenada, a partir de las cero horas del día tres de mayo del año dos mil doce.\nII.- Tijuana, Tecate y Playas de Rosarito, a partir de las cero horas del día tres de mayo del año dos mil trece. del Estado de Baja California, en la Ciudad de Mexicali, B.C., a los dieciséis días del mes de agosto del año dos mil diez.\nDIP. JUAN MANUEL GASTÉLUM BUENROSTRO\nPRESIDENTE\n(RÚBRICA)\nDIP. CARLOS ALONSO ANGULO RENTERIA\nSECRETARIO\n(RÚBRICA)\nDE CONFORMIDAD CON LO DISPUESTO POR LA FRACCIÓN I DEL ARTÍCULO 49\nMEXICALI, BAJA CALIFORNIA, A LOS TREINTA DÍAS DEL MES DE AGOSTO DEL\nAÑO DOS MIL DIEZ.\nGOBERNADOR DEL ESTADO\nJOSÉ GUADALUPE OSUNA MILLÁN\n(RÚBRICA)\nSECRETARIO GENERAL\nCUAUHTÉMOC CARDONA BENAVIDES\nARTICULO ÚNICO TRANSITORIO DEL DECRETO No. 354, POR EL QUE SE\nADICIONA EL ARTICULO 40, PUBLICADO EN EL PERIODICO OFICIAL No. 55, DE\nLEGISLATURA, SIENDO GOBERNADOR CONSTITUCIONAL EL C. JOSE GUADALUPE\nOSUNA MILLÁN 2007-2013.\nARTÍCULO TRANSITORIO:\nÚNICO.- La presente reforma entrará en vigor al día siguiente de su publicación en el\nPeriódico Oficial del Estado de Baja California.\nLey de Atención y Prevención de la Violencia Familiar para el Estado de Baja California. Página 23 del Estado de Baja California, en la Ciudad de Mexicali, B.C., a los trece días del mes de noviembre del año dos mil doce.\nDIP. ELISA ROSANA SOTO AGÜERO\nVICEPRESIDENTE\n(RÚBRICA)\nDIP. FAUSTO ZÁRATE ZEPEDA\nSECRETARIO\n(RÚBRICA)\nDE CONFORMIDAD CON LO DISPUESTO POR LA FRACCIÓN I DEL ARTÍCULO 49\nMEXICALI, BAJA CALIFORNIA, A LOS CATORCE DÍAS DEL MES DE NOVIEMBRE\nDEL AÑO DOS MIL DOCE.\nJOSÉ GUADALUPE OSUNA MILLÁN\nGOBERNADOR DEL ESTADO\n(RÚBRICA)\nFRANCISCO ANTONIO GARCÍA BURGOS\nSECRETARIO GENERAL DE GOBIERNO\n(RÚBRICA)\nARTÍCULO UNICO TRANSITORIO DEL DECRETO No. 564, POR EL QUE SE\nREFORMA EL ARTÍCULO 30, PUBLICADO EN EL PERIÓDICO OFICIAL No. 43, SECCION\nV, TOMO CXXIII, DE FECHA 23 DE SEPTIEMBRE DE 2016, EXPEDIDO POR LA H. XXI\nLEGISLATURA, SIENDO GOBERNADOR CONSTITUCIONAL EL C. FRANCISCO ARTURO\nVEGA DE LAMADRID 2013-2019.\nTRANSITORIO\nÚNICO.- El presente Decreto entrará en vigor al día siguiente de su publicación en el\nPeriódico Oficial del Estado. del Estado de Baja California, en la Ciudad de Mexicali, B.C., a los veinticinco días del mes de agosto del año dos mil dieciséis.\nDIP. MÓNICA BEDOYA SERNA\nPRESIDENTE\nLey de Atención y Prevención de la Violencia Familiar para el Estado de Baja California. Página 24\nDIP. ROSA ISELA PERALTA CASILLAS\nSECRETARIO\n(RÚBRICA)\nDE CONFORMIDAD CON LO DISPUESTO POR LA FRACCION I DEL ARTÍCULO 49\nMEXICALI, BAJA CALIFORNIA, A LOS CINCO DÍAS DEL MES DE SEPTIEMBRE DEL AÑO\nDOS MIL DIECISÉIS.\nFRANCISCO ARTURO VEGA DE LAMADRID\nGOBERNADOR DEL ESTADO\n(RÚBRICA)\nFRANCISCO RUEDA GOMEZ\nSECRETARIO GENERAL DE GOBIERNO\n(RÚBRICA)\nARTÍCULO ÚNICO TRANSITORIO DEL DECRETO No. 166, POR EL QUE SE\nREFORMAN LOS ARTÍCULOS 2, 9, 14 Y 15, PUBLICADO EN EL PERIÓDICO OFICIAL No.\n04, SECCION IV, TOMO CXXV, DE FECHA 19 DE ENERO DE 2018, EXPEDIDO POR LA\nH. XXII LEGISLATURA, SIENDO GOBERNADOR CONSTITUCIONAL EL C. FRANCISCO\nARTURO VEGA DE LAMADRID 2013-2019.\nTRANSITORIO\nARTÍCULO PRIMERO.- Se derogan todas las disposiciones que se opongan al presente decreto.\nARTÍCULO SEGUNDO.- La presente reforma entrará en vigor al día siguiente de su publicación en el Periódico Oficial del Estado de Baja California. del Estado de Baja California, en la Ciudad de Mexicali, B.C., a los veintitrés días del mes de noviembre del año dos mil diecisiete.\nDIP. EDGAR BENJAMÍN GÓMEZ MACÍAS\nPRESIDENTE\nLey de Atención y Prevención de la Violencia Familiar para el Estado de Baja California. Página 25\nDIP. EVA MARÍA VÁSQUEZ HERNÁNDEZ\nSECRETARIA\n(RÚBRICA)\nDE CONFORMIDAD CON LO DISPUESTO POR LA FRACCION I DEL ARTÍCULO 49\nMEXICALI, BAJA CALIFORNIA, A LOS QUINCE DÍAS DEL MES DE ENERO DEL AÑO\nDOS MIL DIECIOCHO.\nFRANCISCO ARTURO VEGA DE LAMADRID\nGOBERNADOR DEL ESTADO\n(RÚBRICA)\nFRANCISCO RUEDA GÓMEZ\nSECRETARIO GENERAL DE GOBIERNO\n(RÚBRICA)\nARTÍCULO ÚNICO TRANSITORIO DEL DECRETO No. 268, POR EL QUE SE\nREFORMA LA FRACCIÓN I DEL ARTÍCULO 2, PUBLICADO EN EL PERIÓDICO OFICIAL\nNo. 48, SECCION II, TOMO CXXV, DE FECHA 19 DE OCTUBRE DE 2018, EXPEDIDO\nPOR LA H. XXII LEGISLATURA, SIENDO GOBERNADOR CONSTITUCIONAL EL C.\nFRANCISCO ARTURO VEGA DE LAMADRID 2013-2019.\nTRANSITORIO\nARTÍCULO PRIMERO.- La presente reforma entrará en vigor al día siguiente de su publicación en el Periódico Oficial del Estado. del Estado de Baja California, en la Ciudad de Mexicali, B.C., a los veintisiete días del mes de septiembre del año dos mil dieciocho.\nDIP. ROCÍO LÓPEZ GOROSAVE\nPRESIDENTA\nLey de Atención y Prevención de la Violencia Familiar para el Estado de Baja California. Página 26\nDIP. MÓNICA HERNÁNDEZ ÁLVAREZ\nSECRETARIA\n(RÚBRICA)\nDE CONFORMIDAD CON LO DISPUESTO POR LA FRACCION I DEL ARTÍCULO 49\nMEXICALI, BAJA CALIFORNIA, A LOS QUINCE DÍAS DEL MES DE OCTUBRE DEL AÑO\nDOS MIL DIECIOCHO.\nFRANCISCO ARTURO VEGA DE LAMADRID\nGOBERNADOR DEL ESTADO\n(RÚBRICA)\nFRANCISCO RUEDA GÓMEZ\nSECRETARIO GENERAL DE GOBIERNO\n(RÚBRICA)\nARTÍCULO ÚNICO TRANSITORIO DEL DECRETO No. 296, POR EL QUE SE\nAPRUEBAN LAS REFORMAS A LOS ARTÍCULOS 3, 4, 5, 8, 9, 11, 12, 13, 15, 20, 22, 23,\n24, 25, 27, 30, 33, 36, 37 y 40 Y SE DEROGAN LOS ARTÍCULOS 31, 32, Y LAS\nFRACCIONES I Y II DEL ARTÍCULO 34 Y EL ARTÍCULO 35; PUBLICADO EN EL\nPERIÓDICO OFICIAL No. 62, DE FECHA 06 DE NOVIEMBRE DE 2023, ÍNDICE, TOMO\nCXXX, EXPEDIDO POR LA H. XXIV LEGISLATURA, SIENDO GOBERNADORA\nCONSTITUCIONAL LA C. MARINA DEL PILAR ÁVILA OLMEDA 2021-2027.\nTRANSITORIO\nÚNICO.- El presente Decreto entrará en Vigor el día siguiente al de su publicación en el\nPeriódico Oficial del Gobierno del Estado.\nDADO en Sesión Ordinaria de la XXIV Legislatura en la Ciudad de Mexicali, B.C., a los diecinueve días del mes de octubre del año dos mil veintitrés.\nDIP. MANUEL GUERRERO LUNA\nPRESIDENTE\nDIP. DUNNIA MONTSERRAT MURILLO LÓPEZ\nSECRETARIA\nDE CONFORMIDAD CON LO DISPUESTO POR LA FRACCIÓN I DEL ARTÍCULO 49\nCALIFORNIA, IMPRÍMASE Y PUBLÍQUESE.\nLey de Atención y Prevención de la Violencia Familiar para el Estado de Baja California. Página 27\nMEXICALI, BAJA CALIFORNIA, A LOS VEINTITRÉS DÍAS DEL MES DE OCTUBRE\nDEL AÑO DOS MIL VEINTITRÉS.\nMARINA DEL PILAR ÁVILA OLMEDA\nGOBERNADORA DEL ESTADO\nDE BAJA CALIFORNIA\n(RÚBRICA)\nCATALINO ZAVALA MÁRQUEZ\nSECRETARIO GENERAL DE GOBIERNO\nDEL ESTADO DE BAJA CALIFORNIA\n(RÚBRICA)\nARTÍCULO SEGUNDO TRANSITORIO DEL DECRETO No. 318, POR EL QUE SE\nAPRUEBA LA REFORMA AL ARTÍCULOS 27; PUBLICADO EN EL PERIÓDICO OFICIAL\nNo. 70, DE FECHA 08 DE DICIEMBRE DE 2023, SECCIÓN I, TOMO CXXX, EXPEDIDO\nPOR LA H. XXIV LEGISLATURA, SIENDO GOBERNADORA CONSTITUCIONAL LA C.\nMARINA DEL PILAR ÁVILA OLMEDA 2021-2027.\nTRANSITORIOS\nPRIMERO.- La presente reforma entrará en vigor al día siguiente de su publicación en el\nPeriódico Oficial del Estado de Baja California.\nSEGUNDO.- El Ejecutivo del Estado expedirá las disposiciones reglamentarias correspondientes para la aplicación de la reforma a la presente Ley, dentro de los noventa días siguientes a la publicación del presente Decreto.\nDADO en Sesión Ordinaria de la XXIV Legislatura en la Ciudad de Mexicali, B.C., a los nueve días del mes de noviembre del año dos mil veintitrés.\nDIP. MANUEL GUERRERO LUNA\nPRESIDENTE\nDIP. DUNNIA MONTSERRAT MURILLO LÓPEZ\nSECRETARIA\nDE CONFORMIDAD CON LO DISPUESTO POR LA FRACCIÓN I DEL ARTÍCULO 49\nCALIFORNIA, IMPRÍMASE Y PUBLÍQUESE.\nLey de Atención y Prevención de la Violencia Familiar para el Estado de Baja California. Página 28\nMEXICALI, BAJA CALIFORNIA, A LOS CATORCE DÍAS DEL MES DE NOVIEMBRE\nDEL AÑO DOS MIL VEINTITRÉS.\nMARINA DEL PILAR ÁVILA OLMEDA\nGOBERNADORA DEL ESTADO\nDE BAJA CALIFORNIA\n(RÚBRICA)\nCATALINO ZAVALA MÁRQUEZ\nSECRETARIO GENERAL DE GOBIERNO\nDEL ESTADO DE BAJA CALIFORNIA\n(RÚBRICA)\nARTÍCULO ÚNICO TRANSITORIO DEL DECRETO No. 413, POR EL QUE SE\nAPRUEBA LA REFORMA AL ARTÍCULO 9; PUBLICADO EN EL PERIÓDICO OFICIAL No.\n23, DE FECHA 07 DE MAYO DE 2024, ÍNDICE, TOMO CXXXI, EXPEDIDO POR LA H.\nXXIV LEGISLATURA, SIENDO GOBERNADORA CONSTITUCIONAL LA C. MARINA DEL\nPILAR ÁVILA OLMEDA 2021-2027.\nTRANSITORIO\nÚNICO.- La presente reforma entrará en vigor al día siguiente de su publicación en el\nPeriódico Oficial del Estado de Baja California.\nDADO en Sesión Ordinaria de la XXIV Legislatura en la Ciudad de Mexicali, B.C., a los dieciocho días del mes de abril del año dos mil veinticuatro.\nDIP. RAMÓN VÁZQUEZ VALADEZ\nPRESIDENTE\nDIP. MANUEL GUERRERO LUNA\nSECRETARIO\nDE CONFORMIDAD CON LO DISPUESTO POR LA FRACCIÓN I DEL ARTÍCULO 49\nCALIFORNIA, IMPRÍMASE Y PUBLÍQUESE.\nMEXICALI, BAJA CALIFORNIA, A LOS VEINTICINCO DÍAS DEL MES DE ABRIL\nDEL AÑO DOS MIL VEINTICUATRO.\nLey de Atención y Prevención de la Violencia Familiar para el Estado de Baja California. Página 29\nMARINA DEL PILAR ÁVILA OLMEDA\nGOBERNADORA DEL ESTADO\nDE BAJA CALIFORNIA\n(RÚBRICA)\nALFREDO ÁLVAREZ CÁRDENAS\nSECRETARIO GENERAL DE GOBIERNO\nDEL ESTADO DE BAJA CALIFORNIA\n(RÚBRICA)\nARTÍCULO ÚNICO TRANSITORIO DEL DECRETO No. 101, POR EL QUE SE\nAPRUEBA LA REFORMA A LOS ARTÍCULOS 1 Y 2; PUBLICADO EN EL PERIÓDICO\nOFICIAL No. 39, ÍNDICE, DE FECHA 27 DE JUNIO DE 2025, TOMO CXXXII; EXPEDIDO\nPOR LA H. XXV LEGISLATURA, SIENDO GOBERNADORA CONSTITUCIONAL LA C.\nMARINA DEL PILAR ÁVILA OLMEDA 2021-2027.\nTRANSITORIO\nÚNICO.- La presente reforma entrará en vigor al día siguiente de su publicación en el\nPeriódico Oficial del Estado de Baja California.\nDADO en Sesión Ordinaria de la XXV Legislatura en la Ciudad de Mexicali, B.C., a los diecinueve días del mes de junio del año dos mil veinticinco.\nDIP. MICHELLE ALEJANDRA TEJEDA MEDINA\nPRESIDENTA\n(RÚBRICA)\nDIP. NORMA ANGELICA PEÑALOZA ESCOBEDO\nSECRETARIA\nDE CONFORMIDAD CON LO DISPUESTO POR LA FRACCIÓN I DEL ARTÍCULO 49\nCALIFORNIA, IMPRÍMASE Y PUBLÍQUESE.\nMEXICALI, BAJA CALIFORNIA, A LOS 20 DÍAS DEL MES DE JUNIO DEL AÑO DOS\nMIL VEINTICINCO.\nMARINA DEL PILAR ÁVILA OLMEDA\nGOBERNADORA DEL ESTADO\nLey de Atención y Prevención de la Violencia Familiar para el Estado de Baja California. Página 30\nDE BAJA CALIFORNIA\nALFREDO ÁLVAREZ CÁRDENAS\nSECRETARIO GENERAL DE GOBIERNO\nDEL ESTADO DE BAJA CALIFORNIA\nLey de Atención y Prevención de la Violencia Familiar para el Estado de Baja California. Página 31",
  "ordenamiento": "REGLAMENTO",
  "jurisdiccion": "BAJA CALIFORNIA",
  "fuente_oficial": "Periódico Oficial",
  "FECHA PER OFIC": "2025/06/27",
  "ESTATUS": "VIGENTE",
  "TOMO": "TOMO_VI",
  "URL": "https://www.congresobc.gob.mx/Documentos/ProcesoParlamentario/Leyes/TOMO_VI/20250627_LEYPREVIOFAMI.PDF",
  "es_escaneado": false,
  "tiene_tablas": false,
  "materia": [
    "social",
    "salud",
    "educación",
    "cultura"
  ]
}