{
  "titulo": "Ley DE HACIENDA DEL ESTADO DE BAJA CALIFORNIA",
  "Contenido": ".\nActualización Legislativa.\nÚltima reforma P.O. No. 72, Índice, 22-Dic-2023\nLEY DE HACIENDA DEL ESTADO DE BAJA CALIFORNIA\nPublicada en el Periódico Oficial No. 37, de fecha 31 de diciembre de 1972, Sección XIII, Tomo LXXIX\nTITULO PRIMERO\nGENERALIDADES\nCAPITULO UNICO\nDISPOSICIONES GENERALES\nARTICULO 1.- La Hacienda Pública del Estado de Baja California, para cubrir los gastos de su administración y demás obligaciones a su cargo, percibirá en cada ejercicio fiscal los ingresos por concepto de impuestos, derechos, productos y aprovechamientos que anualmente establezcan las leyes Fiscales correspondientes, las participaciones en ingresos federales y municipales, y contribuciones de mejoras.\nARTICULO 2.- Las personas físicas, morales o unidades económicas domiciliadas en el Estado o fuera de él, que tuvieren bienes en su territorio o celebren actos que surtan efectos en el mismo, están obligados a contribuir para los gastos públicos de la entidad de la manera que dispongan las leyes y a cumplir con las disposiciones que establezca el Código\nFiscal del Estado.\nARTICULO 3.- Los ingresos se dividen en ordinarios y extraordinarios. Son ordinarios los ingresos señalados en el Artículo 1o. de esta Ley. Son extraordinarios los que se decreten excepcionalmente.\nARTICULO 4.- Ninguna contribución podrá recaudarse si no está prevista por la Ley anual de ingresos correspondiente, o por una ley posterior que lo establezca. Las obligaciones fiscales derivadas de la Ley de Ingresos o de otras leyes, se originarán cuando se realicen las situaciones que coincidan con las que las leyes señalen, aún cuando dichas situaciones constituyan infracciones a otras disposiciones legales.\nEn este último caso, la exigibilidad o cumplimiento de las obligaciones fiscales no legitimará estos hechos o circunstancias.\nARTÍCULO 4-1.- Las contribuciones que perciban los Organismos Descentralizados, Concesionarios, Empresas de Participación Estatal o Paraestatales, por la prestación de un servicio público, ya sea de los establecidos como Derechos o cualquier otra denominación hacendaria, se fijarán mediante cuotas o tarifas que en su caso corresponda. Ninguna\nLey anual de ingresos correspondientes, o por una ley posterior que lo establezca.\nLey de Hacienda del Estado de Baja California. Página 1\n.\nActualización Legislativa.\nÚltima reforma P.O. No. 72, Índice, 22-Dic-2023\nAsimismo, deberán incluir las Entidades mencionadas en el párrafo anterior, todos los servicios que generen una obligación de cobro.\nArtículo Reformado\nTITULO SEGUNDO\nIMPUESTOS\nCAPITULO I\nARTICULO 5.- Derogado.\nArtículo Derogado\nARTICULO 6.- Derogado.\nArtículo Derogado\nARTICULO 7.- Derogado.\nArtículo Derogado\nARTICULO 8.- Derogado.\nArtículo Derogado\nARTICULO 9.- Derogado.\nArtículo Derogado\nARTICULO 10.- Derogado.\nArtículo Derogado\nARTICULO 11.- Derogado.\nArtículo Derogado\nARTICULO 12.- Derogado.\nArtículo Derogado\nARTICULO 13.- Derogado.\nArtículo Derogado\nARTICULO 14.- Derogado.\nArtículo Derogado\nARTICULO 15.- Derogado.\nArtículo Derogado\nARTICULO 16.- Derogado.\nArtículo Derogado\nARTICULO 17.- Derogado.\nArtículo Derogado\nARTICULO 18.- Derogado.\nLey de Hacienda del Estado de Baja California. Página 2\n.\nActualización Legislativa.\nÚltima reforma P.O. No. 72, Índice, 22-Dic-2023\nArtículo Derogado\nARTICULO 19.- Derogado.\nArtículo Derogado\nARTICULO 20.- Derogado.\nArtículo Derogado\nARTICULO 21.- Derogado.\nArtículo Derogado\nARTICULO 22.- Derogado.\nArtículo Derogado\nARTICULO 23.- Derogado.\nArtículo Derogado\nARTICULO 24.- Derogado.\nArtículo Derogado\nARTICULO 25.- Derogado.\nArtículo Derogado\nARTICULO 26.- Derogado.\nArtículo Derogado\nARTICULO 27.- Derogado.\nArtículo Derogado\nCAPITULO II\nIMPUESTO SOBRE TRANSMISION\nDE DOMINIO\nARTICULO 28.- Derogado.\nArtículo Derogado\nARTICULO 29.- Derogado.\nArtículo Derogado\nARTICULO 30.- Derogado.\nArtículo Derogado\nARTICULO 31.- Derogado.\nArtículo Derogado\nARTICULO 32.- Derogado.\nArtículo Derogado\nARTICULO 33.- Derogado.\nArtículo Derogado\nLey de Hacienda del Estado de Baja California. Página 3\n.\nActualización Legislativa.\nÚltima reforma P.O. No. 72, Índice, 22-Dic-2023\nARTICULO 34.- Derogado.\nArtículo Derogado\nARTICULO 34-BIS.- Derogado.\nArtículo Derogado\nARTICULO 35.- Derogado.\nArtículo Derogado\nARTICULO 36.- Derogado.\nArtículo Derogado\nARTICULO 37.- Derogado.\nArtículo Derogado\nARTICULO 38.- Derogado.\nArtículo Derogado\nARTICULO 39.- Derogado.\nArtículo Derogado\nARTICULO 40.- Derogado.\nArtículo Derogado\nARTICULO 41.- Derogado.\nArtículo Derogado\nCAPITULO III\nIMPUESTOS SOBRE ACTIVIDADES MERCANTILES E INDUSTRIALES\nARTICULO 42.- Son objeto del Impuesto sobre Actividades Mercantiles e\nIndustriales, los ingresos provenientes de actos o actividades que no paguen el Impuesto al\nValor Agregado, siempre y cuando éstos sean obtenidos por establecimientos, negociaciones o giros comerciales e industriales, por los conceptos siguientes:\nI.- Enajenación, promesa de venta y opción de venta de bienes muebles;\nII.- Arrendamiento de bienes muebles;\nIII.- Prestación de servicios;\nIV.- Comisiones y mediaciones mercantiles;\nV.- Derogada.\nFracción Derogada\nNo quedan comprendidos dentro del objeto del Impuesto, los actos y actividades a que se refieren los Artículos 2o.- A y 2o.- C, de la Ley del Impuesto al Valor Agregado.\nArtículo Reformado\nLey de Hacienda del Estado de Baja California. Página 4\n.\nActualización Legislativa.\nÚltima reforma P.O. No. 72, Índice, 22-Dic-2023\nARTICULO 43.- Es ingreso para los efectos de este Impuesto, toda percepción en efectivo, en bienes, en servicios, en valores, en títulos de crédito, en libros o en cualquier otra forma que se obtenga por los sujetos de este Impuesto, como resultado de las operaciones a que se refiere el Artículo anterior.\nARTICULO 44.- El impuesto se causa sobre el ingreso total de las operaciones señaladas en el Artículo 42, en el momento en que se realicen aún cuando sean a plazos, a crédito o con reserva de dominio, de acuerdo con lo siguiente:\nI.- El pago inicial o anticipos se considerarán para los efectos del impuesto, como ingreso percibido, aún cuando se cubran con documentos o mediante crédito en libros;\nII.- Cuando la actividad del causante consista en la venta de inmuebles y realice operaciones en abonos, difiriéndose el pago del precio en un plazo de 5 años o mayor, declarará sus ingresos tomando en cuenta los abonos recibidos, incluyendo además del capital amortizado, los intereses devengados y cobrados; y\nIII.- Son ingresos gravables:\nA) El sobreprecio, los intereses o cualquier otra prestación que aumente el ingreso gravado.\nB) El ingreso determinado por la autoridad fiscal, en uso de sus facultades.\nC) Derogado.\nInciso Derogado\nD) Derogado.\nInciso Derogado\nE) Los ingresos estimados provenientes de compras o adquisiciones no declaradas.\nFracción Reformada\nArtículo Reformado\nARTICULO 45.- Para los efectos de este Impuesto la enajenación de bienes, promesas de venta y opción de venta son las de naturaleza mercantil por las cuales se perciba un ingreso.\nARTICULO 46.- Se entiende por arrendamiento de bienes para los efectos de este\nImpuesto, la concesión del uso o goce temporal de un bien que produzca un ingreso al arrendador.\nARTICULO 47.- La prestación de servicios, objeto de este Impuesto, es la de índole mercantil.\nARTICULO 48.- Comisión mercantil es el mandato otorgado al comisionista para efectuar actos de comercio por cuenta del comitente, y mediación mercantil es la actividad que desarrolla el mediador para relacionar a los contratantes.\nLey de Hacienda del Estado de Baja California. Página 5\n.\nActualización Legislativa.\nÚltima reforma P.O. No. 72, Índice, 22-Dic-2023\nQuedan comprendidos en este precepto entre otras, las actividades que desarrollan por cuenta ajena los consignatarios, agentes, representantes, corredores y distribuidores, quienes deberán cumplir los requisitos que señala el Artículo siguiente; de no satisfacerlos, causarán el Impuesto sobre el total de la operación.\nARTICULO 49.- El ingreso de los comisionistas estará formado por la cantidad que perciban por concepto de remuneración por la comisión desempeñada, siempre que satisfagan los requisitos siguientes:\nI.- Que exista contrato o comprobación escrita en el que se estipule la comisión, ya sea una cantidad fija o en un porcentaje sobre el precio de la operación.\nII.- Que el comisionista se encuentre registrado como tal en la Recaudación de\nRentas correspondiente.\nIII.- Que el comisionista ponga a disposición de las autoridades fiscales, cuando éstas lo soliciten, los comprobantes de las cuentas rendidas a su comitente, y de las comisiones percibidas.\nDe no satisfacer los requisitos anteriores, se estimará que el comisionista ha operado en su nombre y por cuenta propia y el Impuesto se causará sobre el ingreso total de la operación.\nEl ingreso gravable del propietario de las mercancías estará formado por el total de los ingresos obtenidos con motivo de las operaciones celebradas por el comisionista, agente, consignatario, representante, corredor o distribuidor, sin que sea deducible para este efecto la retribución estipulada a éstos últimos.\nARTICULO 50.- Son causantes de este Impuesto, las personas físicas o morales que obtengan ingresos provenientes de cualquier operación mercantil que se realice o surta sus efectos en el Estado de Baja California.\nArtículo Reformado\nARTICULO 51.- Para los efectos de este Impuesto, se considera percibido el ingreso en el lugar donde el contribuyente establezca su negocio, industria o comercio o el lugar donde se encuentre.\nSe considera que el ingreso se ha percibido en el Territorio del Estado:\nI.- Cuando se obtengan ingresos, objeto de este Impuesto, de bienes que en el momento de efectuarse la operación se encuentren dentro del Territorio del Estado, cualquiera que sea el domicilio de las partes y el destino de la mercancía;\nII.- Cuando se obtengan ingresos, objeto de este Impuesto, de bienes que en el momento de efectuarse la operación se encuentren dentro del Territorio del Estado, aún cuando el domicilio de alguna de las partes se encuentre fuera del mismo;\nLey de Hacienda del Estado de Baja California. Página 6\n.\nActualización Legislativa.\nÚltima reforma P.O. No. 72, Índice, 22-Dic-2023\nIII.- Cuando el ingreso se obtenga como resultado de operaciones mencionadas en el\nArtículo 42 fracción I de esta Ley y celebradas con la intervención directa o indirecta de sucursales, agencias, dependencias o comisionistas, establecidos en el Estado de Baja\nCalifornia, de negocios cuya matriz o sucursal proveedora esté radicada fuera del Estado.\nEn este caso, se considera gravable el monto total de los ingresos resultantes de todas las operaciones en que haya intervenido la sucursal, agencia, dependencia o comisionista, aún cuando las mercancías se encuentren fuera del Estado y se remitan directamente al comprador; y\nIV.- Cuando el ingreso se obtenga por servicios prestados, comisiones devengadas o intereses causados en el Estado, cualquiera que sea el domicilio de la persona que preste el servicio o el de aquella que lo reciba.\nARTICULO 52.- Los contribuyentes que tengan sucursales, despachos, bodegas, o dependencias que operen en lugares distintos al de la ubicación de la casa matriz, están obligados a efectuar el pago en la oficina Recaudadora de su jurisdicción conforme a las reglas siguientes:\nI.- La matriz declarará y pagará el Impuesto exclusivamente respecto de los ingresos que perciba directamente, es decir, sin mediación de ninguna de sus sucursales, despachos, bodegas o dependencias obligadas a pagar el gravamen;\nII.- Las sucursales, despachos, bodegas o dependencias que perciban ingresos, cubrirán el Impuesto que se cause sobre esos ingresos, en la oficina en que estén empadronados;\nIII.- Los almacenes o bodegas que no perciban ingresos, presentarán por una sola vez una declaración manifestando que no obtienen ingresos gravables, al momento de su registro en la Oficina Recaudadora correspondiente.\nARTICULO 53.- El impuesto se causará y pagará conforme a las tasas y cuotas que fije la Ley de Ingresos del Estado.\nArtículo Reformado\nARTICULO 54.- El impuesto se causará y pagará mensualmente en razón de los ingresos gravables que obtengan los causantes. Tratándose de ventas de primera mano de gasolina y otros productos derivados del petróleo distintos del gas doméstico, el impuesto se pagará en el momento en que el causante adquiera los productos, siendo recaudado por\nPetróleos Mexicanos en los términos del Reglamento del Artículo 21 de la Ley del Impuesto\nSobre Consumo de Gasolina.\nArtículo Reformado\nARTICULO 55.- Para los efectos del pago de este impuesto, regirán las tasas que señala la Ley de Ingresos del Estado.\nArtículo Reformado\nLey de Hacienda del Estado de Baja California. Página 7\n.\nActualización Legislativa.\nÚltima reforma P.O. No. 72, Índice, 22-Dic-2023\nARTICULO 56.- Están exentos del pago del impuesto sobre Actividades Mercantiles e\nIndustriales:\nI.- Los ingresos obtenidos por las Sociedades Cooperativas de Consumo, únicamente con motivo de las ventas hechas a sus socios.\nII.- Los ingresos obtenidos por establecimientos penitenciarios, de beneficencia y los de enseñanza pública o privada, reconocidos por la autoridad competente.\nIII.- Los ingresos que procedan de la prestación de servicios profesionales. No favorece esta exención a las empresas formadas por socios profesionistas que se encuentren organizados en forma mercantil.\nIV.- Los ingresos por ventas de productos alimenticios para el género humano, excepto los que se obtengan en restaurantes y demás establecimientos donde se sirvan comidas.\nV.- Los ingresos que procedan de la venta de bienes que representen inversiones en activo fijo, salvo cuando esos bienes pertenezcan al género de artículos propios del giro; de aportaciones de capital, de la enajenación de partes sociales en las sociedades de personas y de la distribución entre los socios del haber social en los casos de disolución de sociedades.\nVI.- Los ingresos provenientes de las operaciones de segunda o ulteriores manos de varilla corrugada.\nVII.- Los ingresos que obtengan por venta de cemento, los productores y distribuidores de cemento debidamente establecidos y registrados en el Estado.\nVIII.- Enajenación de títulos de crédito.\nIX.- Las percepciones obtenidas por las Editoras, exclusivamente en lo concerniente a la producción, distribución y venta de periódicos.\nArtículo Reformado\nARTICULO 57.- En los casos en que los causantes se amparen en las exenciones señaladas en esta Ley u otorgadas por decreto, y obtengan ingresos gravables sin presentar sus declaraciones ni pagar el Impuesto que a ellos corresponde, se presumirá que el la fecha de vigencia de la exención, y deberán pagar el Impuesto sobre la totalidad de sus ingresos, incluyendo los que pudieron haber estado exentos.\nARTICULO 58.- Los causantes que gocen de exención total o parcial del Impuesto\nSobre Actividades Mercantiles e Industriales, quedan obligados a presentar mensualmente las declaraciones de ingresos que para el pago de este Impuesto señala este Capítulo, en la forma y dentro de los plazos que el mismo fija.\nARTICULO 59.- Para los efectos de este Capítulo, no se consideran ingresos gravables, en los términos de la Fracción I del Artículo 42:\nLey de Hacienda del Estado de Baja California. Página 8\n.\nActualización Legislativa.\nÚltima reforma P.O. No. 72, Índice, 22-Dic-2023\nI.- Los reembolsos de pagos hechos a terceros por concepto de gastos por seguros, acarreos, fletes, empaques, envolturas, envases exteriores, impuestos, derechos y otros semejantes que haga el vendedor con motivo del envío de las mercancías, siempre que éstos se carguen al comprador, sin que se altere su monto y siempre que los importes se expresen específicamente en las facturas o notas de ventas que se expidan. No se aplicará lo dispuesto en esta Fracción cuando el precio se pacte libre de gastos para el comprador.\nSe considerarán ingresos gravables los derivados de la enajenación de empaques, envolturas y envases que sean necesarios para la venta de mercancías al detalle;\nII.- Los descuentos y bonificaciones hechos por el vendedor al comprador; y\nIII.- Los que se reintegren con motivo de la devolución de mercancías, en los casos en que las enajenaciones se rescindan total o parcialmente.\nARTICULO 60.- Los causantes que, como consecuencia de las operaciones que realicen, registren en sus libros autorizados, asientos que comprueben aumentos o disminuciones de los ingresos declarados y, consecuentemente, afecten el monto del\nImpuesto pagado, podrán hacer el aumento a su cargo o la disminución a su favor del impuesto rectificado en la declaración mensual siguiente al mes en que efectivamente hayan registrado dichos asientos.\nTambién podrán hacer rectificaciones cuando descubran errores en las declaraciones presentadas que motiven una diferencia de menos en el Impuesto pagado.\nARTICULO 61.- Cuando los contribuyentes no hayan hecho uso de las prerrogativas que les concede el Artículo anterior, si al finalizar su ejercicio fiscal determinan diferencias de impuestos pagados tanto de más como de menos, podrán hacer las compensaciones correspondientes y si de ellas resulta diferencia a su cargo, la cubrirán mediante declaración complementaria, con los recargos de Ley; si por el contrario, la diferencia fuere a su favor, podrán solicitar su devolución.\nArtículo Reformado\nARTICULO 62.- Los contribuyentes por iniciativa propia no podrán hacer las rectificaciones a que se refieren los Artículos anteriores, cuando se descubra falsedad en los asientos de su contabilidad, cuando la omisión del Impuesto haya sido descubierta de antemano por alguna autoridad, funcionario o empleado, cuando con anterioridad se haya de alguna prestación fiscal derivada de la aplicación de este Impuesto.\nARTICULO 63.- Los causantes de este Impuesto están obligados a registrarse en las\nRecaudaciones de Rentas de su jurisdicción. Cuando un mismo causante tenga diversos giros, sucursales, bodegas o dependencias deberá empadronarse cada uno de ellos por separado.\nLey de Hacienda del Estado de Baja California. Página 9\n.\nActualización Legislativa.\nÚltima reforma P.O. No. 72, Índice, 22-Dic-2023\nARTICULO 64.- Los causantes presentarán sus solicitudes de empadronamiento dentro de los diez días siguientes a la fecha de iniciación de sus operaciones, haciendo uso de las formas oficialmente aprobadas, con los datos que en ellas se exijan.\nArtículo Reformado\nARTICULO 65.- Derogado.\nArtículo Derogado\nARTICULO 66.- Los causantes de este Impuesto deberán manifestar por escrito a la\nRecaudación de Rentas correspondiente dentro de los diez días posteriores al en que ocurran los siguientes hechos:\nI.- Cambio de nombre o razón social.\nII.- Modificación del Capital.\nIII.- Cambio de domicilio.\nIV.- Cambio de giros de la negociación o establecimiento; y\nV.- Clausura.\nEn caso de traspaso, la manifestación deberá hacerse con diez días de anticipación, No podrá efectuarse éste sin que previamente se compruebe que el establecimiento o negociación está al corriente en el pago de sus obligaciones fiscales.\nARTICULO 67.- Los causantes y retenedores de este impuesto estarán obligados a presentar sus declaraciones y a efectuar su pago correspondiente, a más tardar el día veinticinco del mes siguiente a aquel al que corresponda el impuesto causado.\nArtículo Reformado\nARTICULO 68.- La autoridad fiscal verificará la exactitud y veracidad de la declaración, exigiendo el pago que realmente corresponda e imponiendo las sanciones respectivas.\nARTICULO 69.- Las declaraciones deberán hacerse en las formas aprobadas por la\nArtículo Reformado\nARTICULO 70.- Las declaraciones deberán ser firmadas:\nI.- Por el propietario o su apoderado y por el Contador si lo hubiere, cuando se trate de negociaciones propiedad de personas físicas.\nII.- Por el contador de la empresa y por el gerente, o por el director o administrador, y a falta de éstos, por el funcionario de la empresa autorizado por el Consejo de\nAdministración, o si no existe Consejo por el Administrador Unico, cuando se trate de sociedades, y\nLey de Hacienda del Estado de Baja California. Página 10\n.\nActualización Legislativa.\nÚltima reforma P.O. No. 72, Índice, 22-Dic-2023\nIII.- Por el gerente o encargado de la sucursal y por el contador si lo hubiere, cuando se trate de sucursales ubicadas en jurisdicción fiscal distinta a la de la matriz. Si la sucursal se encuentra en la misma jurisdicción fiscal de la matriz, las declaraciones serán firmadas, en su caso, por las personas a que se refieren las dos Fracciones anteriores.\nARTICULO 71.-Derogado.\nArtículo Derogado\nARTICULO 72.- Los causantes del Impuesto sobre Actividades Mercantiles e\nIndustriales en el Estado de Baja California deberán observar las siguientes medidas de control de sus ingresos:\nI.- Expedir diariamente facturas, notas de venta o cintas de máquina registradora que comprueben la totalidad de sus ingresos provenientes de sus operaciones. El documento fuente de contabilización deberá llenar los siguientes requisitos:\nA) Nombre y Razón social del causante.\nB) Domicilio y Fecha.\nC) Número de cuenta Estatal.\nD) Registro Federal de Causantes.\nE) Número Progresivo Prenumerario.\nF) Valor de la operación especificado en Moneda Nacional.\nII.- Cuando se utilice únicamente máquina registradora y que expida comprobante al cliente, éste deberá llenar los mismos requisitos anteriores;\nIII.- Cuando no se utilice máquina registradora, o ésta no expida comprobante al cliente y el monto de la operación sea superior a $ 50.00, la expedición de facturas o notas de venta con los requisitos mencionados en la Fracción I, será obligatoria;\nPor las operaciones de $ 50.00 que no hayan sido facturadas deberá formularse una nota de venta o factura global al final de cada día.\nIV.- Las facturas o notas de venta deberán expedirse cuando menos por duplicado y deberán conservarse las copias en orden numérico y sin interrupción;\nV.- Podrán usarse una o varias series de facturas, las cuales deberán identificarse por medio de letras y prenumerarse progresivamente. Si no se usa la totalidad, o alguna se cancela, se incluirán los originales con la anotación \"NO SE USARÁN\" o \"CANCELADAS\" en su caso;\nVI.- Las sucursales o dependencias de empresas del interior del país que realicen operaciones en el Estado de Baja California, deberán cumplir con los requisitos mencionados anteriormente y conservar en el domicilio de la sucursal o dependencia, las copias de las facturas o notas de venta expedidas, las cuales deberán contener folio\nLey de Hacienda del Estado de Baja California. Página 11\n.\nActualización Legislativa.\nÚltima reforma P.O. No. 72, Índice, 22-Dic-2023 progresivo independiente del que se lleve en la matriz u otros establecimientos de la misma negociación.\nEs obligación de las personas que obtengan los bienes o servicios consignados en el\nArtículo 42 de esta Ley, recabar los documentos correspondientes que deberán reunir los requisitos antes mencionados.\nEn los casos de compras de mercancías facturadas en el extranjero, éstas deberán estar amparadas con la correspondiente relación aduanal de importación o boletas en su caso, a nombre del causante.\nEn los casos en que no se recabe la documentación de referencia, el comprador deberá comunicarlo de inmediato a la Secretaría de Hacienda, y en caso de no hacerlo será solidariamente responsable del impuesto omitido.\nPárrafo Reformado\nArtículo Reformado\nARTICULO 73.- Los causantes a que se refiere la Fracción Segunda del Artículo 44, tendrán además de las obligaciones señaladas en otros preceptos de esta Ley, las siguientes:\nI.- Presentar para su autorización, ante la Recaudación de Rentas del Estado, los contratos debidamente prenumerados;\nII.- Conservar copia de los contratos, facturas y recibos de cobranzas que originan las ventas; y\nIII.- Llevar un registro por cada operación que consigne como mínimo los siguiente datos:\nA) Nombre del comprador.\nB) Domicilio.\nC) Número de Contrato.\nD) Manzana y Lote.\nE) Monto de la operación e importe de las mensualidades en moneda nacional. En caso de operaciones pactadas en moneda extranjera, se deberá consignar además la utilidad o pérdida en cambios obtenidos al recibir cada abono.\nF) Fecha y número del recibo de abono.\nG) Saldo por amortizar, incluyendo capital e intereses, determinado mensualmente.\nArtículo Reformado\nARTICULO 74.- Los causantes que obtengan ingresos exentos y gravados, deberán tratamiento fiscal y en sus declaraciones mensuales:\nLey de Hacienda del Estado de Baja California. Página 12\n.\nActualización Legislativa.\nÚltima reforma P.O. No. 72, Índice, 22-Dic-2023\nI.- Manifestarán el total de sus ingresos;\nII.- Deducirán del total de sus ingresos;\nA) Los descuentos, devoluciones y bonificaciones, y\nB) Los ingresos exentos.\nARTICULO 75.- En caso de que los causantes no lleven la separación de ingresos a que se refiere el Artículo anterior, el impuesto se causará sobre la totalidad de los ingresos sin la deducción de los exentos a la tasa más alta que causan sus ingresos gravables.\nArtículo Reformado\nARTICULO 76.- Las actividades mercantiles e industriales que requieran licencia o permiso del Ejecutivo, no podrán iniciarse sin haberlo obtenido previamente; los que deberán revalidarse por la autoridad que los expidió durante el mes de junio de cada año, previa comprobación de que subsisten los requisitos que exigen las leyes y reglamentos respectivos.\nARTICULO 77.- Son retenedores y solidariamente responsables del pago del\nImpuesto:\nI.- Las personas físicas, morales o unidades económicas sobre las remuneraciones que cubran a sus comisionistas, agentes, consignatarios, representantes, corredores o distribuidores.\nII.- Los comisionistas, agentes, consignatarios, representantes, corredores o distribuidores del pago del impuesto que causa el propietario de las mercancías a que se refiere el Artículo 45 de esta Ley, en el caso de que el enajenante tenga el domicilio fuera del\nEstado de Baja California.\nIII.- Los usuarios de servicios técnicos, cuando los ingresos se perciban por causantes radicados fuera del Territorio del Estado y dichos ingresos provengan de operaciones realizadas o que surtan sus efectos dentro del mismo.\nLos retenedores enterarán el Impuesto mediante una declaración adicional, en la que manifestarán los datos correspondientes a la operación y al causante directo del Impuesto.\nARTICULO 78.- Derogado.\nArtículo Derogado\nARTICULO 79.- Derogado.\nArtículo Derogado\nARTICULO 80.- Derogado.\nArtículo Derogado\nLey de Hacienda del Estado de Baja California. Página 13\n.\nActualización Legislativa.\nÚltima reforma P.O. No. 72, Índice, 22-Dic-2023\nARTICULO 81.- Los contadores, al firmar o rendir dictamen sobre el balance de los contribuyentes, harán constar si el ingreso ha sido declarado en los términos de esta Ley. En caso de falsedad, se harán acreedores a las sanciones correspondientes.\nARTICULO 82.- En el caso de translación de dominio, por cualquier título, de establecimientos en los cuales perciban ingresos gravados con este impuesto, con los mismos negocios se responderá objetivamente de los créditos fiscales insolutos.\nARTICULO 83.- Las personas físicas o morales que tengan relaciones mercantiles con alguno o algunos de los causantes de este Impuesto, deberán auxiliar a la Secretaría de\nHacienda y a sus Dependencias, suministrándoles los informes y datos que soliciten en relación con la aplicación de este mismo Impuesto.\nArtículo Reformado\nARTICULO 84.- Las personas físicas o morales que mantengan o hayan tenido relaciones mercantiles con los contribuyentes de este Impuesto, están obligados a exhibir su contabilidad, la documentación y la correspondencia que se refiere a las operaciones realizadas con dichos causantes.\nARTICULO 85.- Son actividades mercantiles o industriales eventuales, aquellas que se realizan esporádicamente o en forma evidentemente transitoria, así como las que por su propia naturaleza o características deban durar por un término menor de tres meses.\nARTICULO 86.- Para el ejercicio eventual de actividades que generan ingresos gravados por este impuesto se requerirá:\nI.- Dar aviso con 24 horas de anticipación a las autoridades fiscales correspondientes, indicando:\nA) Nombre y domicilio del causante.\nB) Naturaleza de la operación.\nC) Monto probable de los ingresos que se deriven de ella.\nII.- Garantizar el interés fiscal; y\nIII.- Obtener licencia previa del Gobernador del Estado cuando se trate de bebidas con graduación alcohólica en envase abierto o cerrado, para consumo dentro del establecimiento.\nArtículo Reformado\nARTICULO 87.- Los causantes eventuales que efectúen ventas de bebidas con graduación alcohólica en ferias, kermesses y diversiones análogas de carácter transitorio, causarán y pagarán el Impuesto diariamente. No causan el Impuesto los negocios que en forma exclusiva vendan cerveza.\nArtículo Reformado\nLey de Hacienda del Estado de Baja California. Página 14\n.\nActualización Legislativa.\nÚltima reforma P.O. No. 72, Índice, 22-Dic-2023\nARTICULO 88.- Derogado.\nArtículo Derogado\nARTICULO 88-BIS.- Derogado.\nArtículo Derogado\nARTICULO 89.- Cuando se solicite la suspención provisional o definitiva de orden de clausura, deberá garantizarse el interés fiscal en algunas de las formas que establece el\nArtículo 78 del Código Fiscal del Estado.\nArtículo Reformado\nARTICULO 90.- Derogado.\nArtículo Derogado\nARTICULO 91.- Derogado.\nArtículo Derogado\nARTICULO 92.- Derogado.\nArtículo Derogado\nARTICULO 93.- Derogado.\nArtículo Derogado\nARTICULO 94.- Derogado.\nArtículo Derogado\nARTICULO 95.- Derogado.\nArtículo Derogado\nARTICULO 96.- Derogado.\nArtículo Derogado\nCAPITULO IV\nIMPUESTO SOBRE PRODUCCION AGROPECUARIA\nARTICULO 97.- SUSPENDIDO.\nArtículo Suspendido\nARTICULO 98.- SUSPENDIDO.\nArtículo Suspendido\nARTICULO 99.- SUSPENDIDO.\nArtículo Suspendido\nARTICULO 100.- SUSPENDIDO.\nArtículo Suspendido\nARTICULO 101.- SUSPENDIDO.\nArtículo Suspendido\nLey de Hacienda del Estado de Baja California. Página 15\n.\nActualización Legislativa.\nÚltima reforma P.O. No. 72, Índice, 22-Dic-2023\nARTICULO 102.- SUSPENDIDO.\nArtículo Suspendido\nARTICULO 103.- SUSPENDIDO.\nArtículo suspendido\nARTICULO 104.- SUSPENDIDO.\nArtículo Suspendido\nARTICULO 105.- SUSPENDIDO.\nArtículo Suspendido\nARTICULO 106.- SUSPENDIDO.\nArtículo Suspendido\nCAPITULO V\nIMPUESTO SOBRE VENTA DE PRODUCTOS AGROPECUARIOS\nARTICULO 107.- SUSPENDIDO.\nArtículo Reformado\nARTICULO 108.- SUSPENDIDO.\nArtículo Reformado\nARTICULO 109.- SUSPENDIDO.\nArtículo Reformado\nARTICULO 110.- SUSPENDIDO.\nArtículo Reformado\nARTICULO 111.- SUSPENDIDO.\nArtículo Reformado\nARTICULO 112.- SUSPENDIDO.\nArtículo Reformado\nARTICULO 113.- SUSPENDIDO.\nArtículo Reformado\nARTICULO 114.- SUSPENDIDO.\nArtículo Reformado\nARTICULO 114-1.- SUSPENDIDO.\nArtículo Reformado\nCAPITULO VI\nIMPUESTO SOBRE DESPEPITE DE ALGODON\nLey de Hacienda del Estado de Baja California. Página 16\n.\nActualización Legislativa.\nÚltima reforma P.O. No. 72, Índice, 22-Dic-2023\nARTICULO 115.- Es objeto del Impuesto Sobre Despepite de Algodón, el servicio de despepite de algodón que se realice en el Estado.\nARTICULO 116.- Derogado.\nArtículo Derogado\nARTICULO 117.- Son sujetos de este Impuesto las personas físicas, morales o unidades económicas que presten el servicio de despepite de algodón.\nARTICULO 118.- Este Impuesto se causará con base en el volumen de algodón despepitado y se pagará conforme a la cuota que fije la Ley de Ingresos del Estado.\nARTICULO 119.- Los causantes de este impuesto deberán pagarlo mensualmente dentro de los días del primero al veinte de cada mes, conforme al volumen despepitado en el mes inmediato anterior mediante la presentación de una declaración en las formas autorizadas por la Secretaría de Hacienda en la Recaudación de Rentas correspondiente, la que deberá contener el dato de los kilos de algodón en pluma despepitados y el tonelaje de la semilla de algodón obtenida.\nArtículo Reformado\nARTICULO 120.- Las operaciones que grava este impuesto, no causan el de actividades mercantiles e industriales a que se refiere el Capítulo III de esta Ley.\nArtículo Reformado\nARTICULO 120-1.- Este impuesto no será repercutible.\nArtículo Reformado\nCAPITULO VII\nIMPUESTO SOBRE ADQUISICION DE ALGODON\nARTICULO 121.- SUSPENDIDO.\nArtículo Suspendido\nARTICULO 122.- SUSPENDIDO.\nArtículo Suspendido\nARTICULO 123.- SUSPENDIDO.\nArtículo Suspendido\nARTICULO 124.- SUSPENDIDO.\nArtículo Suspendido\nARTICULO 125.- SUSPENDIDO.\nArtículo Suspendido\nARTICULO 126.- SUSPENDIDO.\nArtículo Suspendido\nLey de Hacienda del Estado de Baja California. Página 17\n.\nActualización Legislativa.\nÚltima reforma P.O. No. 72, Índice, 22-Dic-2023\nCAPITULO VIII\nIMPUESTO SOBRE SERVICIOS DE HOSPEDAJE\nARTICULO 127.- Es objeto de este impuesto, los servicios de hospedaje que se reciban en el territorio del Estado, independientemente del nombre del acto que les dé origen.\nPara efectos de este impuesto, se consideran servicios de hospedaje, el otorgamiento de alojamiento o albergue temporal de personas a cambio de una contraprestación, proporcionados en hoteles, moteles, villas, cabañas, campamentos, paraderos de casas rodantes, marinas turísticas, y en cualquier otro establecimiento destinado a dar hospedaje, incluyendo los que se presten bajo la modalidad de tiempo compartido y aquellos que brinden hospedaje temporal en casas y departamentos mediante aplicaciones y plataformas digitales.\nArtículo Reformado\nARTICULO 128.- Son sujetos de este impuesto, las personas que reciban los servicios a que se refiere el artículo anterior.\nArtículo Reformado\nARTICULO 129.- La base del impuesto será el valor de la contraprestación pactada por el servicio de hospedaje, sin incluir las demás cantidades que se carguen al usuario por cualquier otro concepto o por otros servicios relacionados con el objeto de este impuesto, siempre y cuando en el comprobante fiscal se haga constar en forma expresa y por separado el importe del servicio de hospedaje, así como el desglose de los demás servicios prestados.\nCuando en los servicios de hospedaje, se incluyan servicios accesorios tales como alimentación, transportación, uso de instalaciones u otros similares y el comprobante fiscal no reúna los requisitos a que se refiere el párrafo anterior, se entenderá que la base gravable se integra con el costo de todos los servicios.\nArtículo Reformado\nARTICULO 130.- Este impuesto se determinará aplicando a la base gravable a que se refiere el artículo anterior, la tasa que al efecto señale la Ley de Ingresos del Estado.\nIngresos del Estado vigente, y será determinado por el Ejecutivo Estatal, a través de la\nPárrafo Reformado\nCuando los servicios a que se refiere el Artículo 127 de esta Ley, se reciban con y de cualquier tipo, incluyendo promotores y facilitadores, con el propósito de dar alojamiento\nLey de Hacienda del Estado de Baja California. Página 18\n.\nActualización Legislativa.\nÚltima reforma P.O. No. 72, Índice, 22-Dic-2023 o albergue a terceras personas, se tendrá obligación de enterar el impuesto en el momento en que sean exigibles las contraprestaciones a favor de quien preste los servicios de hospedaje y sobre el monto de los mismos.\nEn cualquiera de los supuestos previstos en el artículo 127 de esta Ley, cuando intervenga de cualquier manera una persona física o moral en su carácter de intermediario, promotor o facilitador en el cobro de las contraprestaciones por servicios de hospedaje y en caso de que se cubra a través de ella lo correspondiente al Impuesto Sobre Servicios de\nHospedaje, ésta deberá ser quien entere el pago del impuesto correspondiente. En este último supuesto donde la persona física o moral en su carácter de intermediario, promotor o facilitador sea quien entere el pago del Impuesto Sobre Servicios de Hospedaje, se liberará al contribuyente del impuesto correspondiente y a las personas que presten los servicios de hospedaje de las obligaciones establecidas en el primer párrafo del presente artículo, así como de las establecidas en el artículo 132 de esta Ley.\nArtículo Reformado\nARTICULO 131.- Quienes presten los servicios señalados en este capítulo tendrán el carácter de retenedores y deberán enterarlo mensualmente, a más tardar el día veinticinco del mes siguiente a aquel al que corresponda el impuesto causado, mediante las formas aprobadas por la Secretaría de Hacienda; debiendo constar en la declaración correspondiente, la información y demás datos relativos a los actos y operaciones objeto de este impuesto, que se hayan realizado en el mes inmediato anterior.\nPárrafo Reformado\nTratándose de intermediarios que reciban el pago por el servicio de hospedaje y el\nImpuesto Sobre Servicios de Hospedaje, deberán enterar los impuestos que se hayan recaudado en el mes inmediato anterior, en los mismos plazos señalados en el párrafo anterior y presentar la declaración del impuesto en los términos del mismo párrafo.\nArtículo Reformado\nARTICULO 132.- Las personas que presten los servicios de hospedaje, serán responsables solidarios de este impuesto, además de las obligaciones señaladas en el\nCódigo Fiscal del Estado; estarán obligados a lo siguiente:\nPárrafo Reformado\nI.- Estar inscritos en el Registro Estatal de Causantes, mediante la forma oficial correspondiente, y proporcionar la información relacionada con su identidad, su domicilio y aquella que le sea solicitada;\nII.- Retener y enterar el impuesto, aún cuando no hubieren hecho la retención o no hayan recibido el pago de las contraprestaciones del servicio prestado.\nIII.- Llevar los controles contables necesarios que acrediten en forma fehaciente cada uno de los actos y operaciones objeto de este impuesto.\nLey de Hacienda del Estado de Baja California. Página 19\n.\nActualización Legislativa.\nÚltima reforma P.O. No. 72, Índice, 22-Dic-2023\nDentro de estos controles se incluye la separación expresa en el comprobante fiscal expedido del monto de las contraprestaciones correspondientes a los servicios de hospedaje, servicios accesorios, transportación, alimentación y otros similares.\nLos intermediarios, promotores o facilitadores a los que hace referencia el artículo 130 de la presente Ley, estarán obligados a cumplir con las fracciones señaladas anteriormente, en los términos de las reglas de carácter general que para tal efecto deberá emitir la\nSecretaría de Hacienda.\nPárrafo Reformado\nArtículo Reformado\nARTICULO 132 BIS.- No causarán este impuesto, los servicios de hospedaje que se reciban en hospitales, clínicas, asilos, conventos, seminarios e internados.\nArtículo Adicionado\nCAPÍTULO IX\nIMPUESTO AMBIENTAL POR LA EMISIÓN DE GASES A LA ATMÓSFERA\nCapítulo Reformado\nARTÍCULO 133.- El objeto de este impuesto son las emisiones a la atmósfera de determinadas sustancias que se generan por la utilización de bienes o consumo de productos contaminantes en el Estado y que afecten el territorio del mismo.\nPárrafo Reformado\nPara los efectos de este impuesto se considera emisión a la atmósfera, la expulsión directa o indirecta de bióxido de carbono, metano, óxido nitroso, hidrofluoro-carbonos, perfluoro-carbonos y hexafluoruro de azufre, ya sea unitariamente o de cualquier combinación de ellos que afecten la calidad del aire, los componentes de la atmósfera y que constituyen gases de efecto invernadero que impactan en deterioro ambiental por provocar calentamiento global.\nPárrafo Adicionado\nArtículo Reformado\nArtículo Invalidado por Sentencia a Controversia Constitucional 119/2020\nARTÍCULO 134.- Son sujetos de este impuesto, las personas físicas, las personas morales y las unidades económicas residentes en el Estado o los residentes fuera del\nEstado, que tengan instalaciones o fuentes fijas en las que se expendan al consumidor final territorio del Estado.\nArtículo Reformado\nArtículo Invalidado por Sentencia a Controversia Constitucional 119/2020\nARTÍCULO 135.- La base del Impuesto es el total de kilogramos de sustancias contaminantes a la atmósfera por los bienes o productos adquiridos por el consumidor final, conforme a lo establecido en la presente Ley.\nArtículo Reformado\nArtículo Invalidado por Sentencia a Controversia Constitucional 119/2020\nLey de Hacienda del Estado de Baja California. Página 20\n.\nActualización Legislativa.\nÚltima reforma P.O. No. 72, Índice, 22-Dic-2023\nARTÍCULO 136.- Para la determinación de la base gravable y pago del impuesto, el contribuyente se estará a la siguiente tabla de equivalencias:\nPárrafo Reformado\nBien o Producto Factor de Emisión\nGasolina 2.196 kg CO /litro\nDiésel 2.471 kg CO /litro\nGas Natural 2.690 kg CO /kilogramo\nGas Lp 3.000 kg CO /kilogramo\nEl impuesto a pagar se determina aplicando la cuota de $0.17 pesos por cada litro o kilogramo de CO, según corresponda conforme al factor de emisión previsto en la tabla del presente artículo.\nPárrafo Adicionado\nArtículo Reformado\nArtículo Invalidado por Sentencia a Controversia Constitucional 119/2020\nARTÍCULO 136-1.- El impuesto no deberá trasladarse a las personas que adquieran los bienes referidos en el artículo anterior.\nArtículo Adicionado\nArtículo Invalidado por Sentencia a Controversia Constitucional 119/2020\nARTÍCULO 136-2.- Los contribuyentes del presente impuesto, pagarán el mismo, sin que proceda acreditamiento alguno contra dicho pago.\nArtículo Adicionado\nArtículo Invalidado por Sentencia a Controversia Constitucional 119/2020\nARTÍCULO 136-3.- El impuesto se calculará mensualmente y se enterará al Estado a más tardar el día 25 del mes siguiente a aquél al que corresponda el pago. Los pagos en el Código Fiscal del Estado de Baja California, y tendrán el carácter de definitivos.\nArtículo Adicionado\nArtículo Invalidado por Sentencia a Controversia Constitucional 119/2020\nLey de Hacienda del Estado de Baja California. Página 21\n.\nActualización Legislativa.\nÚltima reforma P.O. No. 72, Índice, 22-Dic-2023\nARTÍCULO 136-4.- El impuesto se causa en el momento de la entrega material del bien o producto contaminante cuya utilización o consumo genera emisiones a la atmósfera objeto de este impuesto.\nArtículo Adicionado\nArtículo Invalidado por Sentencia a Controversia Constitucional 119/2020\nARTÍCULO 136-5.- Los contribuyentes de este impuesto tienen, además de las obligaciones señaladas en este capítulo y en las demás disposiciones fiscales, las siguientes:\nI.- Llevar la contabilidad de conformidad con el Código Fiscal del Estado, y conforme a las Reglas de Carácter General que en su caso emita la Secretaría de Hacienda. Asimismo, se deberán identificar las operaciones por las que deba pagarse este impuesto.\nII.- Presentar las declaraciones relativas al impuesto previsto en el presente capítulo.\nSi un contribuyente tuviera varios establecimientos en el Estado, presentará una declaración por cada establecimiento, o bien una concentrada por todo el Estado.\nIII.- Proporcionar la información que en relación con este impuesto se les solicite en las declaraciones respectivas.\nIV.- Registrar la obligación de pago del presente impuesto y los establecimientos en los que se realicen las actividades gravadas, ante la Recaudación de Rentas del Estado respectiva, dentro de los 15 días siguientes a que inicie operaciones o a que empiece a enajenar los bienes referidos en este capítulo.\nArtículo Adicionado\nArtículo Invalidado por Sentencia a Controversia Constitucional 119/2020\nARTÍCULO 136-6.- Derogado.\nArtículo Adicionado\nArtículo Derogado\nARTÍCULO 136-7.- De la Recaudación obtenida por concepto de este impuesto, corresponde el 20% a los Municipios del Estado, distribuyéndose en proporción a la recaudación del mismo obtenida en cada uno de los Municipios en el ejercicio fiscal anterior, programas en favor del medio ambiente. En virtud de ello, este impuesto no se considerará para la determinación de las participaciones a que se refiere el artículo 7 de la Ley de\nCoordinación Fiscal del Estado de Baja California, ni para el fondo compensatorio a que se refiere el artículo 7 Bis de la citada ley.\nEl Estado destinará de manera preferente el 80% de la recaudación de este Impuesto para la promoción y desarrollo de programas en favor del medio ambiente.\nArtículo Adicionado\nArtículo Invalidado por Sentencia a Controversia Constitucional 119/2020\nLey de Hacienda del Estado de Baja California. Página 22\n.\nActualización Legislativa.\nÚltima reforma P.O. No. 72, Índice, 22-Dic-2023\nCAPITULO X\nIMPUESTO SOBRE DIVERSIONES Y ESPECTACULOS PUBLICOS\nARTICULO 137.- Son objeto del Impuesto sobre Diversiones y Espectáculos\nPúblicos, los ingresos derivados de la explotación de las siguientes actividades, por la cuota de admisión, siempre que dichas actividades no estén gravadas por el Impuesto al Valor\nAgregado: Teatro, Cine, Circo y Espectáculos de Carpa, Corridas de Toros, Espectáculos de\nBox, Lucha y Deportivos, Apuestas permitidas de todo tipo, apuestas sobre carreras y frontones, audiencias musicales y espectáculos de cualquier tipo, con cuota de admisión.\nArtículo Reformado\nARTICULO 138.- Son sujetos de este impuesto las personas físicas o morales que obtengan ingresos por la explotación de las actividades señaladas en el Artículo anterior.\nArtículo Reformado\nARTICULO 139.- Este impuesto se causará con base en los ingresos que se obtengan por la explotación de las actividades que señala el Artículo 137 de esta Ley, y se pagará conforme a las tarifas y cuotas que señala la Ley de Ingresos del Estado.\nArtículo Reformado\nARTICULO 140.- El Impuesto deberá pagarse al término de cada función, por conducto del Interventor que al efecto designe la Recaudación de Rentas del Estado. La liquidación del impuesto deberá hacerse en las formas aprobadas por la Secretaría de\nHacienda.\nPárrafo Reformado\nLa Secretaría de Hacienda podrá autorizar al contribuyente, para enterar el impuesto causado, ante la Oficina de Recaudación de Rentas de cuya jurisdicción corresponda, al siguiente día hábil de aquel en que se celebre la función o funciones.\nPárrafo Reformado\nArtículo Reformado\nARTICULO 141.- Los ingresos serán supervisados por un interventor que designará la autoridad fiscal correspondiente, con las facultades que le otorga esta Ley.\nArtículo Reforma\nARTICULO 142.- Ninguna de las actividades que señala el Artículo 137 de esta Ley, aunque sea en forma eventual, podrá practicarse sin avisar por escrito a la Recaudación de\nRentas correspondiente, con 24 horas de anticipación a su celebración, indicando la naturaleza y características de aquellas.\nARTICULO 143.- Las facultades del interventor a que se refiere el Artículo 141 de esta Ley, son las siguientes:\nI.- Determinar el boletaje vendido, y el importe de los ingresos.\nII.- Formular liquidación que deberá ser firmada por un representante de la empresa.\nLey de Hacienda del Estado de Baja California. Página 23\n.\nActualización Legislativa.\nÚltima reforma P.O. No. 72, Índice, 22-Dic-2023\nIII.- Recaudar el impuesto que se cause con motivo de la celebración de las actividades que señala el artículo 137 de esta Ley.\nArtículo Reformado\nARTICULO 143-1.- Este impuesto, en ningún caso, deberá ser trasladado al espectador.\nArtículo Adicionado\nARTICULO 143-2.- Los honorarios de los Interventores de los eventos a que se refiere el Artículo 137 de esta Ley se determinarán discrecionalmente por el Recaudador de\nRentas del Estado, y en ningún caso será menor al equivalente de cuatro salarios mínimos general vigente en el Estado.\nArtículo Adicionado\nARTICULO 143-3.- Los contribuyentes de este impuesto tienen, además las siguientes obligaciones:\nI.- Presentar ante la Recaudación de Rentas de cuya jurisdicción corresponda, para su resello, el boletaje y el programa que corresponda a cada función, en el mismo término que establece el Artículo 142 de esta Ley.\nII.- No vender boletos en tanto no estén resellados por las Autoridades Fiscales.\nIII.- Permitir a los Interventores que designe la Secretaría de Hacienda o sus Oficinas de Recaudación de Rentas, la verificación y determinación del pago del impuesto, dándole las facilidades que requieran para su cumplimiento.\nFracción Reformado\nIV.- Los contribuyentes de este impuesto que exploten espectáculos en forma eventual, tendrán además las siguientes obligaciones:\nA) Dar aviso de la iniciación de las actividades a que se refiere el Artículo 137 de esta\nLey.\nB) Dar el aviso a que se refiere el Artículo 142 de esta Ley, señalando además la fecha en que habrán de concluir las actividades en cada jurisdicción.\nC) Dar el aviso correspondiente en los casos de ampliación del período de explotación, ante la Oficina de Recaudación de Rentas de su jurisdicción, a más tardar el día último que comprenda el aviso, cuya vigencia se vaya ampliar y,\nD) Previamente a la iniciación de actividades, otorgar garantías a satisfacción de la impuesto estimado correspondiente a un día de actividades, ni superior al que pudiera corresponder también estimativamente a tres días.\nInciso Reformado\nArtículo Adicionado\nArtículo Reformado\nLey de Hacienda del Estado de Baja California. Página 24\n.\nActualización Legislativa.\nÚltima reforma P.O. No. 72, Índice, 22-Dic-2023\nARTICULO 143-4.- Cuando los sujetos de este impuesto, obligados a otorgar garantía de acuerdo con lo dispuesto en la Fracción V Inciso D) del Artículo anterior, no hubieran cumplido con tal obligación, la Secretaría de Hacienda podrá suspender el espectáculo, hasta en tanto no se garantice el pago del impuesto, para lo cual, el interventor que se designe solicitará el auxilio de la fuerza pública.\nArtículo Adicionado\nArtículo Reformado\nARTICULO 143-5.- Quedan preferentemente afectos a garantizar el pago de este impuesto:\nI.- Los bienes inmuebles en que se exploten espectáculos públicos o diversiones, cuando sean propiedad de los contribuyentes de este impuesto; y\nII.- El equipo y las instalaciones que se utilicen en el espectáculo público.\nArtículo Adicionado\nCAPITULO XI\nIMPUESTO SOBRE COMPRA-VENTA\nY OPERACIONES SIMILARES\nARTICULO 144.- Son objeto del Impuesto sobre Compraventa y Operaciones\nSimilares, los actos civiles siguientes:\nI.- Compra de vehículos automotores usados;\nII.- Venta de bienes muebles usados; y\nIII.- Operaciones Similares.\nPara efectos de este impuesto, se considera como Operaciones Similares, todas aquellas que impliquen el cambio de propietario de bienes muebles usados, con independencia del nombre que les asignen las leyes que rijan el acto que les dé origen, incluyendo la dación en pago.\nArtículo Reformado\nARTICULO 145.- Son sujetos de este impuesto, las personas físicas o morales que celebren las operaciones mencionadas en el Artículo anterior, que no estén gravadas por el\nImpuesto sobre Actividades Mercantiles e Industriales.\nArtículo Reformado\nARTICULO 146.- Para los efectos de este impuesto la base gravable será:\nI.- Tratándose de vehículos automotores, los valores que señale al Tabulador Oficial de Valores mínimos que expida la Secretaría de Hacienda;\nFracción Reformada\nII.- En los demás casos, el valor de la operación.\nLey de Hacienda del Estado de Baja California. Página 25\n.\nActualización Legislativa.\nÚltima reforma P.O. No. 72, Índice, 22-Dic-2023\nCuando el valor de la operación sea notoriamente bajo en relación con el precio comercial, la Secretaría de Hacienda procederá a efectuar avalúo pericial para determinar su valor real.\nPárrafo Reformado\nArtículo Reformado\nTASAS Y PAGO\nARTICULO 147.- El Impuesto se causará conforme las tasas que fije la Ley de\nIngresos del Estado y deberá pagarse su importe en el momento de celebrarse la operación, en la Oficina Recaudadora correspondiente, mediante la presentación de una manifestación en las formas aprobadas por la Secretaría de Hacienda.\nArtículo Reformado\nARTICULO 148.- Para los efectos de la Fracción I del Artículo 144 de esta Ley se considerará efectuada la operación, objeto de este gravamen al darse de alta los vehículos en la Dirección de Tránsito y Transportes del Estado.\nARTICULO 149.- Los bienes transmitidos o adquiridos, quedan afectos preferentemente al pago del Impuesto a que se refiere este Capítulo.\nCAPITULO XII\nIMPUESTO SOBRE PRODUCCION, AMPLIACION, ENVASAMIENTO O\nTRANSFORMACION DE ALCOHOL Y BEBIDAS ALCOHOLICAS\nARTICULO 150.- Este Impuesto se regulará por las disposiciones que al efecto señala la Ley del Impuesto Sobre Alcoholes y Bebidas Alcohólicas vigentes en el Estado.\nCAPITULO XIII\nIMPUESTO SOBRE COMPRAVENTA DE ALCOHOL Y BEBIDAS ALCOHOLICAS\nARTICULO 151.- Este Impuesto se regulará por las disposiciones que al efecto señala la Ley del Impuesto sobre Alcoholes y Bebidas Alcohólicas vigente en el Estado.\nCAPITULO XIV\nCapítulo Adicionado\nARTICULO 151-1.- Son objeto de este Impuesto las percepciones de Ingresos que no los siguientes bienes:\nI.- El suelo;\nII.- Inmuebles destinados o utilizados exclusivamente para casa habitación; y\nIII.- Fincas dedicadas o utilizadas sólo a fines agrícolas o ganaderos.\nArtículo Adicionado\nLey de Hacienda del Estado de Baja California. Página 26\n.\nActualización Legislativa.\nÚltima reforma P.O. No. 72, Índice, 22-Dic-2023\nArtículo Reformado\nARTICULO 151-2.- Son ingresos para los efectos de este impuesto, las rentas que se devenguen por concepto de arrendamiento y subarrendamiento de bienes inmuebles.\nArtículo Adicionado\nARTICULO 151-3.- Son sujetos de este impuesto las personas físicas, jurídicas o unidades económicas que obtengan los ingresos a que se refiere el artículo anterior.\nArtículo Adicionado\nARTICULO 151-4.- La base de este impuesto será:\nA) El monto de las rentas devengadas mensualmente independientemente de la fecha en que se cobren.\nB) El valor de las construcciones realizadas por el arrendatario o subarrendatario sobre el inmueble arrendado que queden en beneficio del arrendador o subarrendador; cuando éstas impliquen un aumento a la superficie construida objeto del contrato original.\nEste valor será el que figure en la contabilidad del arrendatario o subarrendatario o en su defecto el que determine la Dirección de Catastro del Estado, debiendo dividirse entre el número de meses contratados o entre doce meses si los contratos fueren por tiempo indefinido.\nC) Cualquier cantidad que el arrendador o subarrendador cobre al arrendatario o subarrendatario en relación al bien arrendado, como quiera que se le denomine, aún cuando no se encuentre pactada en el contrato.\nArtículo Adicionado\nARTICULO 151-5.- Este impuesto se liquidará y pagará trimestralmente durante los meses de Marzo, Junio, Septiembre y Diciembre de cada año por los ingresos devengados en el trimestre correspondiente, conforme a las tasas que fije la Ley de Ingresos del Estado.\nArtículo Adicionado\nARTICULO 151-6.- Cuando de las manifestaciones del arrendador se infiera que las rentas que produce el inmueble arrendado son inferiores a las que debe producir el predio objeto del contrato, la Secretaría de Hacienda podrá proceder a determinarlas para fines fiscales a razón de 1 % mensual del valor comercial que establezca para cada caso en particular la Dirección de Catastro del Estado o sus dependencias en cada Municipio.\nArtículo Adicionado\nArtículo Reformado\nARTICULO 151-7.- Los causantes de este impuesto están obligados a presentar las ubicación de los inmuebles, en las formas aprobadas por la Secretaría de Hacienda.\nArtículo Adicionado\nArtículo Reformado\nLey de Hacienda del Estado de Baja California. Página 27\n.\nActualización Legislativa.\nÚltima reforma P.O. No. 72, Índice, 22-Dic-2023\nARTICULO 151-8.- Para los efectos del pago de este impuesto se equipará al arrendamiento, cualquier acto o contrato que con distinta denominación origine el derecho de percibir ingresos por la concesión del uso y goce de un inmueble.\nArtículo Adicionado\nARTICULO 151-9.- Son obligaciones de los sujetos de este impuesto:\nI.- Empadronarse en la Secretaría de Hacienda, por conducto de la Oficina\nRecaudadora correspondiente, dentro de los quince días siguientes a aquel en que celebre su primer contrato de arrendamiento, haciendo uso de las formas aprobadas.\nFracción Reformada\nCuando un mismo causante tenga bienes inmuebles arrendados en jurisdicción de distintas Oficinas Recaudadoras, deberá empadronarse en cada una de ellas separadamente;\nII.- Registrar cada uno de los contratos que celebren para el arrendamiento de inmuebles, en la oficina recaudadora de su jurisdicción, dentro de los quince días naturales siguientes a la fecha de su celebración;\nIII.- Adoptar las medidas de control que para el correcto pago del impuesto establezca la Secretaría de Hacienda.\nFracción Reformada\nArtículo Adicionado\nArtículo Reformado\nARTICULO 151-10.- El arrendatario o subarrendatario que hubiese realizado obras de construcción a beneficio de inmuebles objeto del contrato deberá dar aviso a la\nSecretaría de Hacienda al término de la obra y especificar el valor de la misma.\nArtículo Adicionado\nArtículo Reformado\nARTICULO 151-11.- Estarán exentos del pago de este impuesto las personas físicas que perciban como ingreso total por concepto de rentas mensuales hasta $ 3,000.00 debiendo cumplir con lo dispuesto por el Artículo 151-9 Fracción I.\nArtículo Adicionado\nARTICULO 151-12.- Este impuesto no es repercutible.\nArtículo Adicionado\nCAPITULO XV\nDE LOS IMPUESTOS SOBRE PRODUCTOS DEL TRABAJO\nCapítulo Adicionado y Reubicado\nDenominación Modificada\nSECCION PRIMERA\nSección Adicionada\nLey de Hacienda del Estado de Baja California. Página 28\n.\nActualización Legislativa.\nÚltima reforma P.O. No. 72, Índice, 22-Dic-2023\nARTICULO 151-13.- Es objeto de este Impuesto, la realización de pagos por concepto de remuneraciones al trabajo personal, prestado dentro del territorio del Estado, bajo la dirección o dependencia de un tercero.\nArtículo Adicionado\nArtículo Reformado\nARTICULO 151-14.- La base del impuesto es el monto total de los pagos que se efectúen bajo las condiciones establecidas en el Artículo anterior, aún cuando dichos pagos no excedan del valor diario de la Unidad de Medida y Actualización vigente, en base a los términos siguientes:\nPárrafo Adicionado\nPárrafo Reformado\nI.- Para los contribuyentes personas físicas o contribuyentes personas morales que en el ejercicio inmediato anterior les hayan prestado servicios subordinados hasta veinticinco trabajadores como promedio mensual, comprenderá el monto total de los pagos efectuados trimestralmente. La misma periodicidad aplicará para el primer ejercicio de operaciones independientemente del número de trabajadores que tengan a su servicio.\nII.- Para los demás contribuyentes, comprenderá el monto total de los pagos efectuados mensualmente.\nSi quien efectúa los pagos está domiciliado fuera del Estado, y no tiene dentro de éste, sucursal, agencia o representación, la base del impuesto será el monto total de las percepciones que obtenga el trabajador.\nArtículo Adicionado\nArtículo Reformado\nARTICULO 151-15.- Son sujetos del impuesto las personas físicas y morales que se encuentran domiciliadas en el Estado, o tengan en éste agencias, sucursales o representación y realicen los pagos por remuneración al trabajo personal prestado bajo la dirección y dependencia de un tercero. Así como las personas que no se encuentren domiciliados en el Estado, ni tengan en éste agencias, sucursales o representación y realicen pagos por remuneraciones al trabajo a personas que presten sus servicios de carácter personal en el Estado.\nArtículo Reformado\nARTICULO 151-16.- Este Impuesto se liquidará y pagará a una tasa del 4.25%, aplicada al total de los pagos efectuados por el empleador, según los períodos establecidos por el Artículo 151-14 o al total de las percepciones que en el mismo período obtengan fuera del Estado, quienes presten servicios de carácter personal dentro del mismo.\nPárrafo Reformado\nLa cantidad destinada por concepto de recaudación de este impuesto, así como los objetivos del mismo, se regularán por las disposiciones que al efecto señala la Ley de\nIngresos del Estado de Baja California vigente.\nPárrafo Reformado\nArtículo Reformado\nLey de Hacienda del Estado de Baja California. Página 29\n.\nActualización Legislativa.\nÚltima reforma P.O. No. 72, Índice, 22-Dic-2023\nARTICULO 151-17.- Están obligados a enterar el Impuesto quienes perciban remuneraciones en los términos del Artículo 151-15, cuando quien los pague resida fuera del\nEstado, sin tener en el mismo agencia, sucursal o representación.\nArtículo Adicionado\nArtículo Reformado\nARTICULO 151-18.- Para efectos de este impuesto, se consideran erogaciones destinadas a remunerar el trabajo personal subordinado, los salarios y demás cantidades que se entreguen al trabajador, como contraprestación por su trabajo.\nNo quedan comprendidas dentro de las remuneraciones objeto del impuesto, las prestaciones de previsión social, las participaciones de los trabajadores en las utilidades de las empresas, ni las indemnizaciones por terminación de la relación laboral.\nPara los efectos de este impuesto, se considera previsión social, las erogaciones efectuadas por los patrones de manera general a favor de sus trabajadores que tengan por objeto satisfacer contingencias o necesidades presentes o futuras, así como el otorgar beneficios a favor de dichos trabajadores, tendientes a su superación física, social, económica o cultural, que les permitan el mejoramiento en su calidad de vida y en la de su familia.\nArtículo Adicionado\nArtículo Reformado\nARTICULO 151-19.- Este Impuesto se enterará en efectivo mediante declaración que presentarán los contribuyentes o responsables solidarios según sea el caso, a más tardar los días veinticinco, del mes siguiente al período correspondiente en que hagan o reciban los pagos base del gravamen, o de los meses de abril, julio, octubre y enero del año siguiente, tratándose de pagos trimestrales.\nArtículo Adicionado\nArtículo Reformado\nARTICULO 151-20.- Son obligaciones a cargo de los sujetos que realizan los pagos gravados por este impuesto, y de los responsables solidarios:\nI.- Empadronarse en la oficina de Recaudación de Rentas del Estado de su jurisdicción, dentro de los diez días siguientes a la fecha en que se efectúen las operaciones gravadas por este impuesto, tratándose de los responsables solidarios;\nII.- Presentar la declaración mensual o trimestral según corresponda, para el pago del\nImpuesto; y\nIII.- Las demás que impongan otras disposiciones fiscales.\nArtículo Adicionado\nArtículo Reformado\nSECCION SEGUNDA\nSección Adicionada\nLey de Hacienda del Estado de Baja California. Página 30\n.\nActualización Legislativa.\nÚltima reforma P.O. No. 72, Índice, 22-Dic-2023\nARTICULO 151-21.- Son objeto del Impuesto sobre Profesiones y Ejercicios\nLucrativos, los ingresos que se perciban con motivo del libre ejercicio de las profesiones y oficios derivados de los siguientes servicios:\nI.- El transporte público de personas;\nII.- Los de carácter profesional, cuando su prestación requiera título conforme a la Ley de Profesiones del Estado y su Reglamento;\nIII.- Los prestados por artistas, locutores, toreros, o deportistas, cuando realicen actividades cinematográficas, teatrales, de radiodifusión, de variedades, taurinas o deportivas; y\nIV.- Otros que no paguen el Impuesto al Valor Agregado.\nIgualmente lo serán los ingresos que obtengan quienes posean título de escuela superior, técnica o universitaria, derivados de su trabajo personal prestado bajo la dirección y dependencia de un tercero dentro del territorio del Estado, cuando quien realice los pagos no cause el Impuesto Sobre Remuneraciones al Trabajo Personal.\nEn este caso, quienes efectúen los pagos están obligados a retener y enterar el impuesto en los términos del Artículo 151-25.\nArtículo Adicionado\nArtículo Reformado\nARTICULO 151-22.- Son sujetos de este Impuesto las personas físicas, jurídicas o unidades económicas, que habitual o eventualmente obtengan los ingresos a que se refiere el Artículo anterior.\nArtículo Adicionado\nArtículo Reformado\nARTICULO 151-23.- La base de este Impuesto es el monto total de los ingresos a que se refiere el Artículo 151-21.\nArtículo Adicionado\nArtículo Reformado\nARTICULO 151-24.- Este Impuesto se liquidará y pagará de conformidad con la tasa que estipule la Ley de Ingresos del Estado.\nArtículo Adicionado\nArtículo Reformado\nARTICULO 151-25.- El pago de este Impuesto se hará bimestralmente ante la Oficina\nRecaudadora de la jurisdicción del causante, dentro de los meses de Enero, Marzo, Mayo, Julio, Septiembre y Noviembre de cada año, por los ingresos obtenidos en el bimestre inmediato anterior, haciendo uso de las formas aprobadas por la Secretaría de Hacienda.\nArtículo Adicionado\nArtículo Reformado\nLey de Hacienda del Estado de Baja California. Página 31\n.\nActualización Legislativa.\nÚltima reforma P.O. No. 72, Índice, 22-Dic-2023\nARTICULO 151-26.- Los sujetos de este Impuesto que habitualmente ejerzan las actividades a que se refiere el Artículo 151-21, están obligados a:\nI.- Empadronarse en la Secretaría de Hacienda por conducto de la Oficina\nRecaudadora de su jurisdicción, dentro de los diez días hábiles siguientes a aquél en que inicien sus actividades, utilizando las formas aprobadas por la misma Secretaría;\nFracción Reformada\nII.- Dar aviso a la Oficina Recaudadora correspondiente, en los casos de cambio de domicilio, así como en los de suspensión o cambio de actividades dentro de los diez días hábiles siguientes contados a partir de la fecha en que ocurra el cambio;\nIII.- Proporcionar a las Autoridades Fiscales los datos e informes que les sean solicitados dentro del plazo que para ello se les fije;\nIV.- Recibir las visitas de inspección y proporcionar a las Autoridades Fiscales comisionadas para el efecto, todos los informes y documentos que soliciten para el desempeño de sus funciones; y\nV.- Expedir la documentación comprobatoria de sus ingresos, que deberá ser prenumerada, señalando como mínimo, nombre, dirección, actividad y número de registro.\nArtículo Adicionado\nArtículo Reformado\nARTICULO 151-27.- Las personas físicas, jurídicas o unidades económicas que hagan pagos a causantes que eventualmente sean sujetos de este Impuesto dentro del\nTerritorio del Estado, deberán retenerlo y enterarlo en la Oficina Recaudadora correspondiente; utilizando, las formas aprobadas por la Secretaría de Hacienda, dentro de los tres días siguientes al en que se cause, siendo en todo caso solidariamente responsable del pago del mismo.\nArtículo Adicionado\nArtículo Reformado\nARTICULO 151-28.- De los ingresos que obtenga el causante mensualmente, se considerará ingreso exento para los efectos del pago de este Impuesto, la cantidad equivalente hasta el doble del valor mensual de la Unidad de Medida y Actualización vigente.\nArtículo Adicionado\nArtículo Reformado\nARTICULO 151-29.- La Secretaría de Hacienda podrá estimar los ingresos de los sujetos de este Impuesto en los siguientes casos:\nPárrafo Reformado\nI.- Cuando no presenten sus declaraciones, o no expidan la documentación comprobatoria a que están obligados; y\nII.- Cuando por las pruebas que se obtengan, se pongan de manifiesto la percepción de un ingreso superior, cuando menos en un tres por ciento, al declarado por el causante, en cualquiera de los bimestres del período de revisión.\nLey de Hacienda del Estado de Baja California. Página 32\n.\nActualización Legislativa.\nÚltima reforma P.O. No. 72, Índice, 22-Dic-2023\nPara practicar las estimaciones a que se refieren las Fracciones I y II de este Artículo, se podrán tomar en cuenta las actividades realizadas por el causante, los honorarios usuales por servicios similares, la renta del local que ocupa, sueldos y honorarios pagados, gastos y otros que puedan utilizarse.\nPara practicar la estimación a que se refiere la Fracción II de este Artículo, se podrán tomar en cuenta los ingresos declarados por el causante, y el porcentaje de omisión que resulte entre éstos y los estimados se podrá aplicar a los manifestados, determinando la diferencia sobre la cual se calculará el impuesto respectivo.\nEl período a que debe referirse el por ciento, será como mínimo de un bimestre y se presumirá que el causante ha omitido ingresos en la misma proporción durante todo el período revisado.\nArtículo Adicionado\nArtículo Reformado\nCAPITULO XVI\nIMPUESTO SOBRE PRODUCTOS DE CAPITALES\nCapítulo Adicionado\nARTICULO 151-30.- Son causantes del Impuesto Sobre Productos de Capitales las personas físicas, jurídicas o las unidades económicas que obtengan en el Estado o de fuentes ubicadas en el Estado o de créditos garantizados con bienes ubicados en el Estado, ingresos en efectivo, en crédito o en cualquier otra forma, por concepto de:\nI.- Intereses sobre toda clase de préstamos;\nII.- Intereses sobre cantidades que se adeuden como precio de operaciones de compra-venta, en los casos que no estén gravados por el Impuesto sobre Actividades\nMercantiles e Industriales y el Impuesto Federal sobre Ingresos Mercantiles;\nIII.- Intereses provenientes del contrato de cuenta corriente, cuando el Ingreso no esté gravado por el Impuesto sobre Actividades Mercantiles e Industriales y el Impuesto Federal sobre Ingresos Mercantiles;\nIV.- Descuento de títulos o documentos;\nV.- Usufructo de capitales impuesto a rédito;\nVI.- Premios, primas, regalías y retribuciones de todas clases provenientes de la explotación de patentes o de marcas comerciales o industriales, uso de moldes, matrices, planos y diagramas.\nTambién se consideran como percepciones de las enumeradas en esta Fracción, las mercancías amparadas por éstas;\nVII.- Constitución de depósitos;\nVIII.- Otorgamiento de Fianzas; y\nLey de Hacienda del Estado de Baja California. Página 33\n.\nActualización Legislativa.\nÚltima reforma P.O. No. 72, Índice, 22-Dic-2023\nIX.- Operaciones o inversiones de capital cualquiera que sea la denominación que se les dé a los ingresos obtenidos, siempre que éstos no sean objeto de algún otro impuesto del Estado o que no estén expresamente exceptuados por una Ley local aplicable.\nArtículo Adicionado\nARTICULO 151-31.- El Impuesto sobre Productos de Capitales, se causa sin deducción alguna, sobre los ingresos que el causante obtenga, por los conceptos señalados en el Artículo anterior, con las tasas que señale la Ley de Ingresos del Estado.\nArtículo Adicionado\nARTICULO 151-32.- Si en el documento en que conste cualquier operación de la cual se obtenga alguno de los ingresos comprendidos en las Fracciones I a V, inclusive, VII y IX del Artículo 151-30, no se determina el interés, tipo del descuento o rédito que percibe el acreedor o se señala uno inferior al 12% anual, o se estipula que el acreedor no percibirá interés, salvo prueba en contrario, las autoridades fiscales podrán estimar el ingreso gravable tomando en consideración los siguientes elementos:\nA) Importe de la operación realizada.\nB) Condiciones económicas de las partes que intervengan en la operación.\nC) Todos los elementos que al efecto puedan recabarse.\nArtículo Adicionado\nARTICULO 151-33.- El Impuesto que establece este capítulo es a cargo del acreedor o persona que obtenga a nombre propio los ingresos gravables siendo responsable solidario quien efectúe los pagos a nombre propio, a menos que el acreedor le demuestre haber manifestado la operación en los términos del Artículo siguiente, o el mismo deudor solidario lo ponga en conocimiento de las autoridades fiscales.\nLos mandatarios tendrán la obligación de señalar el domicilio del mandante ante la\nRecaudación de Rentas, cuando efectúen cobros o reciban pagos a nombre de éstos, en el término de 15 días siguientes a la operación.\nQuienes los efectúen a través de demandas judiciales, cumplirán con la anterior obligación con el hecho de señalarlo en las mismas.\nArtículo Adicionado\nARTICULO 151-34.- Los causantes o los retenedores en su caso, deberán presentar\nImpuesto en la Oficina Recaudadora de su jurisdicción, dentro del mes siguiente a aquél en que se hubieren obtenido o pagado los ingresos gravados.\nArtículo Adicionado\nARTICULO 151-35.- Cuando los ingresos gravables pertenezcan a causantes domiciliados fuera del Estado, los deudores están obligados a retener el impuesto causado, descontándolo del pago que hagan al acreedor, y a enterar las cantidades retenidas en la\nOficina Recaudadora, en los términos que señala el Artículo anterior.\nLey de Hacienda del Estado de Baja California. Página 34\n.\nActualización Legislativa.\nÚltima reforma P.O. No. 72, Índice, 22-Dic-2023\nArtículo Adicionado\nARTICULO 151-36.- El pago del Impuesto sobre Productos de Capitales deberá hacerse mientras el crédito o inversión de capital de que derive el ingreso gravable no se extinga.\nArtículo Adicionado\nARTICULO 151-37.- No causan el Impuesto:\nI.- Los intereses que paguen u obtengan las Instituciones de Crédito, de Seguros o de\nFianzas, que operen en el país conforme a las Leyes respectivas, siempre que dichos intereses se deriven de operaciones propias del objeto de dichas Instituciones;\nII.- Los ingresos gravados por este Impuesto que perciban las entidades públicas y personas comprendidas en el Artículo 33 del Código Fiscal del Estado, en los términos de ese precepto; y\nIII.- Ingresos por intereses en cajas de ahorro de los empleados, derivados de préstamos que se otorguen a ellos mismos.\nArtículo Adicionado\nARTICULO 151-38.- Los causantes de este Impuesto tienen las siguientes obligaciones:\nI.- Presentar ante las Oficinas Recaudadoras de su jurisdicción, dentro de los 15 días del mes siguiente a la celebración de las operaciones gravadas, una manifestación con los siguientes datos:\nA) Naturaleza de la operación y monto gravado.\nB) Fecha de celebración.\nC) Fecha de vencimiento.\nD) Fecha de las amortizaciones.\nE) Tasa de interés.\nF) Nombre y domicilio de las partes que intervengan en la operación.\nII.- Pagar el Impuesto dentro del siguiente a aquél en que se hayan obtenido los ingresos gravables; y\nIII.- Dar aviso a la Oficina Recaudadora de Rentas correspondiente a su domicilio, dentro de los 15 días siguientes a la fecha en que ocurra cualquiera de los siguientes hechos:\nA) De iniciación de operaciones.\nB) De cambio o baja.\n1.- Cambio de denominación o razón social.\nLey de Hacienda del Estado de Baja California. Página 35\n.\nActualización Legislativa.\nÚltima reforma P.O. No. 72, Índice, 22-Dic-2023\n2.- Cambio de actividad.\n3.- Cambio de domicilio.\n4.- Traspaso de la negociación.\n5.- Suspensión temporal de actividades, y\n6.- Clausura definitiva o cesación de actividades.\nArtículo Adicionado\nARTICULO 151-39.- Los Notarios y los Jueces que actúen por receptoría, dentro de los quince días siguientes a la fecha en que se autoricen las escrituras en que consten operaciones, actos, contratos de los que se derive el derecho a percibir ingresos gravables con este Impuesto, o los que modifiquen esas escrituras, o por las que se extingan las obligaciones contraídas en dichas operaciones o contratos, darán aviso de su otorgamiento a la Oficina Recaudadora de su residencia.\nEstos funcionarios están obligados a permitir la vistas a sus protocolos y archivos conexos, ordenadas por la Autoridad Fiscal competente.\nArtículo Adicionado\nARTICULO 151-40.- Los Titulares del Registro Público de la Propiedad y de\nComercio no inscribirán los títulos, contratos o documentos en que se haga constar operaciones generadoras de ingresos gravables por este impuesto, si no se les acredita previamente, con la copia sellada por la Autoridad Fiscal competente o con otra constancia expedida por ésta, que tales operaciones fueron manifestadas en los términos de la Fracción\nI del Artículo 151-33.\nLos citados funcionarios no podrán cancelar las inscripciones relativas a esos títulos, contratos o documentos, si no se les acredita con los recibos oficiales, respectivos, o con otra constancia expedida por autoridad fiscal competente, que se está al corriente en el pago de este impuesto. En tratándose del deudor o fiado, bastará que compruebe haber manifestado la operación en los términos de la Fracción I del Artículo 151-33.\nArtículo Adicionado\nARTICULO 151-41.- Las Autoridades Judiciales tendrán obligación de dar aviso a la\nRecaudación de Rentas de su adscripción, de las demandas, reconvenciones, transacciones y convenios judiciales, sentencias ejecutoriadas y de cualquier promoción que implique desistimiento de alguna de las partes, si los actos ocurren dentro de un procedimiento gravables en relación con este Impuesto.\nArtículo Adicionado\nCAPITULO XVII\nLey de Hacienda del Estado de Baja California. Página 36\n.\nActualización Legislativa.\nÚltima reforma P.O. No. 72, Índice, 22-Dic-2023\nARTICULO 152.- Derogado.\nArtículo Derogado\nARTICULO 153.- Derogado.\nArtículo Derogado\nARTICULO 154.- Derogado.\nArtículo Derogado\nARTICULO 155.- Derogado.\nArtículo Derogado\nARTICULO 156.- Derogado.\nArtículo Derogado\nCAPITULO XVIII\nIMPUESTO PARA LA EDUCACION MEDIA Y SUPERIOR SOBRE LA ADQUISICION DE\nBIENES Y SERVICIOS\nARTICULO 156-1.- Es objeto de este impuesto la adquisición de bienes y servicios.\nArtículo Adicionado\nArtículo Reformado\nARTICULO 156-2.- Son sujetos de este impuesto los adquirentes de bienes y servicios.\nArtículo Adicionado\nArtículo Reformado\nARTICULO 156-3.- La base del impuesto será el 45% del importe del Impuesto sobre\nIngresos Mercantiles que resulte de aplicar la tasa general del 4 % y especiales del 5 %, 10\n%, 15% y 30% sobre los ingresos que señala la Ley Federal del Impuesto Sobre Ingresos\nMercantiles.\nArtículo Adicionado\nArtículo Reformado\nARTICULO 156-4.- Este impuesto se causará y pagará conforme a la tasa que señale la Ley de Ingresos del Estado.\nArtículo Adicionado\nARTICULO 156-5.- Los causantes de éste impuesto deberán pagarlo al momento de liquidar el importe de los bienes y servicios, siendo solidariamente responsables del pago del impuesto y retenedores del mismo, los que vendan los bienes o servicios señalados en el\nArtículo 156-1 del presente Capítulo.\nArtículo Adicionado\nARTICULO 156-6.- Los retenedores de este impuesto deberán enterarlo en la\nRecaudación de Rentas del Estado correspondiente dentro de los días del 1ro. al 20 del mes\nLey de Hacienda del Estado de Baja California. Página 37\n.\nActualización Legislativa.\nÚltima reforma P.O. No. 72, Índice, 22-Dic-2023 siguiente a aquél en que haya sido retenido mediante la presentación de una declaración en las formas aprobadas por la Secretaría de Hacienda.\nArtículo Adicionado\nArtículo Reformado\nARTICULO 156-7.- No causarán este Impuesto los causantes del Impuesto Sobre\nHospedaje.\nArtículo Adicionado\nCAPÍTULO XIX\nCapítulo Adicionado\nCapítulo Reformado\nSECCIÓN PRIMERA\nDEL IMPUESTO A LAS EROGACIONES EN JUEGOS CON APUESTAS\nSección Adicionada\nARTÍCULO 156-8.- Están obligados al pago del impuesto previsto en esta Sección las personas que realicen erogaciones dentro del territorio del Estado de Baja California, para participar en juegos con apuestas.\nPárrafo Reformado\nPara los efectos de este impuesto, se incluyen dentro de los juegos con apuestas independientemente del nombre con el que se les designe, aquellos en los que el premio se pueda obtener por la destreza del participante en el uso de máquinas, que en su desarrollo utilicen imágenes visuales electrónicas como números, cartas, símbolos, figuras u otras similares, independientemente de que en alguna etapa de su desarrollo intervenga directa o indirectamente el azar.\nPárrafo Reformado\nIgualmente se consideran juegos con apuestas aquellos en los que el participante deba estar presente en el juego, activamente o como espectador, y aquellos juegos en los que el participante haga uso de máquinas que utilicen algoritmos desarrollados en sistemas electrónicos o cualquier otro método mecánico, electrónico o electromagnético en el que el resultado no dependa de factores controlables o susceptibles de ser conocidos o dominados por el participante.\nPárrafo Reformado\nAsimismo, quedan comprendidos en los juegos con apuestas, los de apuestas remotas, también conocidos como libros foráneos, autorizados por autoridad competente, para captar y operar cruces de apuestas en eventos, competencias deportivas y juegos permitidos por la Ley, realizados en el extranjero o en territorio nacional, transmitidos en tiempo real y de forma simultánea en video o audio o ambos.\nPárrafo Adicionado\nIgualmente, quedan comprendidos en los juegos con apuestas, aquellos establecimientos autorizados por autoridad competente, en los que se reciban, capten, Ley de Hacienda del Estado de Baja California. Página 38\n.\nActualización Legislativa.\nÚltima reforma P.O. No. 72, Índice, 22-Dic-2023 crucen o exploten apuestas, así como a los establecimientos o agencias que reciban información con fines de lucro en los que se apuesten sobre carreras de caballos, galgos o cualquier otro evento.\nPárrafo Adicionado\nSe incluyen como erogaciones para participar en juegos con apuestas, las cantidades que entreguen a operadores de los establecimientos por concepto de acceso y utilización de máquinas o instalaciones relacionados con los juegos con apuestas y sorteos, cualquiera que sea el nombre con el que se les designe.\nPárrafo Adicionado\nPara los efectos de este impuesto, se considera apuesta el monto susceptible de apreciarse en Moneda Nacional que se arriesga en un juego de los que requieran permiso de conformidad con lo dispuesto en la Ley Federal de Juegos y Sorteos y su Reglamento, con la posibilidad de obtener o ganar un premio, cuyo monto, sumado a la cantidad arriesgada deberá ser superior a ésta.\nPárrafo Adicionado\nArtículo Adicionado\nArtículo Reformado\nARTÍCULO 156-8 BIS.- El impuesto se calculará aplicando la tasa del 10% al monto de las erogaciones efectuadas por la persona que participe en juegos con apuestas, ya sean pagos en efectivo, en especie o por cualquier otro medio que permita participar en los mismos.\nLas erogaciones a que se refiere el párrafo anterior incluyen la carga y cualquier recarga adicional que se realice mediante tarjetas, bandas magnéticas, dispositivos electrónicos, fichas, contraseñas, comprobantes o cualquier otro medio que permitan participar en los juegos con apuestas a que se refiere el artículo 156-8 o el uso o acceso a las máquinas a que se refiere el propio artículo, ya sea que dichos medios o dispositivos se usen en la fecha en que se efectúe el pago o en una posterior.\nArtículo Adicionado\nARTÍCULO 156-8 TER.- El impuesto se causará en el momento en que el sujeto pague al operador del establecimiento los montos o contraprestaciones que le permitan\nArtículo Adicionado\nARTÍCULO 156-8 QUATER.- El operador del establecimiento en el que se realicen o contraprestación correspondiente, y deberá enterarlo ante las oficinas autorizadas a más tardar el día 25 del mes de calendario siguiente a la fecha de su recaudación o el día hábil siguiente si aquel no lo fuere.\nLey de Hacienda del Estado de Baja California. Página 39\n.\nActualización Legislativa.\nÚltima reforma P.O. No. 72, Índice, 22-Dic-2023\nCuando el pago o contraprestación a favor del operador del establecimiento se realice en especie, el contribuyente deberá proveer de recursos en efectivo al operador del establecimiento para que éste pueda recaudar el impuesto. La omisión del contribuyente a lo previsto en este párrafo, no libera al operador de la responsabilidad solidaria prevista en este capítulo.\nArtículo Adicionado\nARTÍCULO.156-9.- El impuesto previsto en esta sección se causará y pagará con independencia de los impuestos a que se refiere la Sección Segunda de este Capítulo.\nArtículo Adicionado\nArtículo Reformado\nARTÍCULO 156-9 BIS.- Los operadores de los establecimientos en los que se realicen los juegos con apuestas o en los que se instalen las máquinas de juegos, en adición a la obligación de recaudar y enterar el impuesto a que se refiere el artículo 156-8 QUATER, están obligados a expedir comprobantes por cada contraprestación que cobren, incluyendo la carga y recarga, que otorguen a quienes utilicen las máquinas de juegos, en la que conste expresamente y por separado el importe recaudado.\nArtículo Adicionado\nARTÍCULO 156-9 TER.- Serán responsables solidarios del impuesto, en adición al operador del establecimiento en el que se realicen los juegos y concursos o en los que se instalen las máquinas de juegos, cualquiera de las siguientes personas físicas o morales, cuando no sean ellas quienes reciban los pagos del contribuyente:\nI. Las que organicen, administren, exploten o patrocinen los juegos referidos en el artículo 156-8;\nII.Los arrendatarios de los establecimientos en los que se realicen los juegos o concursos a que se refiere el artículo 156-8;\nIII.Las que reciban cantidades a fin de permitir a terceros la participación en los juegos objeto del presente impuesto, y\nIV.Los propietarios o legítimos poseedores de las máquinas de juegos a que se refiere esta Sección.\nArtículo Adicionado\nSECCIÓN SEGUNDA\nDEL IMPUESTO POR LA REALIZACIÓN DE\nJUEGOS CON APUESTAS Y SORTEOS\nSección Adicionada\nARTÍCULO 156-10.- Es objeto de este impuesto la realización de juegos con apuestas y sorteos, independientemente del nombre con el que se les designe, que\nLey de Hacienda del Estado de Baja California. Página 40\n.\nActualización Legislativa.\nÚltima reforma P.O. No. 72, Índice, 22-Dic-2023 su Reglamento, así como la realización de juegos o concursos en los que el premio se obtenga por la destreza del participante en el uso de máquinas, que en el desarrollo de aquéllos utilicen imágenes visuales electrónicas como números, símbolos, figuras u otras similares, que se efectúen en el territorio del Estado.\nPárrafo Reformado\nQuedan comprendidos en los juegos con apuestas, aquéllos en los que solo se reciban, capten, crucen o exploten apuestas. Asimismo, quedan comprendidos en los sorteos, los concursos en los que se ofrezcan premios y en alguna etapa de su desarrollo intervenga directa o indirectamente el azar.\nPárrafo Reformado\nArtículo Adicionado\nArtículo Reformado\nARTÍCULO 156-10 BIS.- Son sujetos de este impuesto las personas físicas, morales o unidades económicas que realicen los actos o actividades a que se refiere el artículo anterior, ya sea que organicen, administren, exploten o celebren juegos con apuestas y sorteos.\nArtículo Adicionado\nARTÍCULO 156-10 TER.- El impuesto se calculará aplicando la tasa del 6% al valor de los actos o actividades realizados, a que se refiere el artículo 156-10.\nSe considerará como valor el total de las cantidades efectivamente percibidas de los participantes por dichas actividades. En los juegos o sorteos en los que se apueste, se considerará como valor el monto total de las apuestas.\nTratándose de los juegos o sorteos en los que la apuesta se realice mediante fichas, tarjetas, contraseñas o cualquier otro comprobante, así como a través de bandas magnéticas, dispositivos electrónicos u objetos similares, que se utilicen para apostar en sustitución de cantidades de dinero y sean aceptadas para esos fines por la persona que realice el juego o sorteo de que se trate, se considerará como valor el total de las cantidades equivalentes en Moneda Nacional que amparen dichos medios. sorteo, se considerará como valor el precio en el que la persona que lo realice haya enajenado todos los bienes que participen en ese sorteo.\nTratándose de sorteos en los que los participantes obtengan dicha calidad, incluso a título gratuito, por el hecho de adquirir un bien o contratar un servicio, recibiendo para ello un comprobante, se considerará como valor el monto total nominal por el que se entregue cada comprobante que otorgue el derecho a participar, conforme a las condiciones del sorteo establecidas en el permiso otorgado por la autoridad competente.\nLey de Hacienda del Estado de Baja California. Página 41\n.\nActualización Legislativa.\nÚltima reforma P.O. No. 72, Índice, 22-Dic-2023\nCuando además de adquirir un bien o contratar un servicio, se pague una cantidad adicional para participar en el sorteo de que se trate, el impuesto además de calcularse en los términos ya señalados también se calculará sobre dicha cantidad.\nLos valores a que se refiere este artículo se podrán disminuir con el monto de los siguientes conceptos:\nI. Los premios efectivamente pagados o entregados conforme a las disposiciones aplicables. Tratándose de premios diversos al efectivo, el monto que se podrá disminuir será el que corresponda al valor estipulado en el permiso otorgado por la autoridad competente o, en su defecto, el valor de mercado.\nII. Las cantidades efectivamente devueltas a los participantes, siempre que las devoluciones se efectúen previo a la realización del evento y éstas se encuentren debidamente registradas en contabilidad y, tratándose de juegos o sorteos en los que se apueste, también se registren en el sistema central de apuestas. Cuando el premio incluya la devolución de la cantidad efectivamente percibida del participante, dicho concepto se disminuirá únicamente como premio.\nCuando el monto de los conceptos mencionados en las fracciones anteriores sea superior a los valores de las actividades a que se refiere el artículo 156-10 de esta Ley, correspondientes al mes de que se trate, la diferencia se podrá disminuir en los meses siguientes hasta agotarse.\nSe considerará también como valor de los actos o actividades realizados, el total de las cantidades efectivamente percibidas por los operadores de los establecimientos de los participantes por dichas actividades, por concepto de acceso y utilización de máquinas o instalaciones relacionados con los juegos con apuestas y sorteos, cualquiera que sea el nombre con el que se les designe.\nArtículo Adicionado\nARTÍCULO 156-10 QUATER.- El impuesto se calculará mensualmente y se pagará a más tardar el día 25 del mes siguiente al en que corresponda dicho pago. Los pagos mensuales se realizarán mediante la presentación de una declaración en la Oficina\nRecaudadora correspondiente, en las formas oficialmente aprobadas y tendrán el carácter de definitivos.\nArtículo Adicionado\nARTÍCULO 156-11.- No se pagará el impuesto a que se refiere el artículo 156-10, en los siguientes supuestos:\nPárrafo Reformado\nI. Cuando se lleven a cabo por personas morales sin fines de lucro autorizadas para recibir donativos deducibles para los efectos de la Ley del Impuesto sobre la Renta, a que se refiere el artículo 79, fracciones VI, X y XVII de dicha Ley, siempre que destinen la totalidad\nLey de Hacienda del Estado de Baja California. Página 42\n.\nActualización Legislativa.\nÚltima reforma P.O. No. 72, Índice, 22-Dic-2023 de sus ingresos, una vez descontados los premios efectivamente pagados, a los fines para los cuales fueron constituidas;\nFracción Adicionada\nII. Tratándose de sorteos, cuando todos los participantes obtengan dicha calidad sin sujetarse a pago, a la adquisición de un bien o a la contratación de un servicio, y\nFracción Adicionada\nIII. Tratándose de sorteos, cuando todos los participantes obtengan dicha calidad a título gratuito por el solo hecho de adquirir un bien o contratar un servicio, siempre que el realizador cumpla los requisitos siguientes:\nFracción Adicionada\na) No obtenga más de diez permisos para celebrar sorteos en un año de calendario.\nInciso Adicionado\nb) El monto total de los premios ofrecidos en un año de calendario no exceda el 3% de los ingresos obtenidos en el año inmediato anterior.\nInciso Adicionado\nQuienes realicen sorteos en el ejercicio de inicio de actividades, podrán estimar sus ingresos en dicho ejercicio para los efectos de lo dispuesto en este inciso. En el supuesto de que el monto de los premios ofrecidos exceda el por ciento a que se refiere el párrafo anterior, se pagará el impuesto que corresponda de conformidad con lo dispuesto en este capítulo con la actualización y los recargos respectivos.\nPárrafo Reformado\nArtículo Adicionado\nArtículo Reformado\nSECCIÓN TERCERA\nDEL IMPUESTO POR OBTENCIÓN DE PREMIOS\nSección Adicionada\nARTÍCULO 156-12.- Es objeto de este Impuesto la percepción de premios en el territorio de Estado, derivados de la celebración de loterías, rifas, sorteos y concursos de toda clase.\nPárrafo Reformado celebración de juegos con apuestas. Para los efectos de este impuesto, se incluyen dentro de los juegos con apuestas, independientemente del nombre con el que se les designe, máquinas, que en su desarrollo utilicen imágenes visuales electrónicas como números, cartas, símbolos, figuras u otras similares, independientemente de que en alguna etapa de su desarrollo intervenga directa o indirectamente el azar.\nPárrafo Reformado\nLey de Hacienda del Estado de Baja California. Página 43\n.\nActualización Legislativa.\nÚltima reforma P.O. No. 72, Índice, 22-Dic-2023\nIgualmente se consideran juegos con apuestas aquellos en los que el participante deba estar presente en el juego, activamente o como espectador, y aquellos juegos en los que el participante haga uso de máquinas que utilicen algoritmos desarrollados en sistemas electrónicos o cualquier otro método mecánico, electrónico o electromagnético en el que la obtención del premio no dependa de factores controlables o susceptibles de ser conocidos o dominados por el participante.\nPárrafo Adicionado\nAsimismo, quedan comprendidos en los juegos con apuestas, los de apuestas remotas, también conocidos como libros foráneos, autorizados por autoridad competente, para captar y operar cruces de apuestas en eventos, competencias deportivas y juegos permitidos por la Ley, realizados en el extranjero o en territorio nacional, transmitidos en tiempo real y de forma simultánea en video y audio.\nPárrafo Adicionado\nIgualmente, quedan comprendidos en los juegos con apuestas, aquéllos establecimientos autorizados por autoridad competente, en los que se reciban, capten, crucen o exploten apuestas, así como a los establecimientos o agencias que reciban información con fines de lucro, en los que se apuesten sobre carreras de caballos, galgos, gallos o cualquier otro evento.\nPárrafo Adicionado\nPara los efectos de este impuesto, se considera apuesta el monto susceptible de apreciarse en moneda nacional que se arriesga en un juego de los que requieran permiso de conformidad con lo dispuesto en la Ley Federal de Juegos y Sorteos y su Reglamento, con la posibilidad de obtener o ganar un premio, cuyo monto, sumado a la cantidad arriesgada deberá ser superior a ésta.\nPárrafo Adicionado\nArtículo Adicionado\nArtículo Reformado\nARTÍCULO 156-12 BIS.- Son sujetos de este impuesto las personas físicas, morales o unidades económicas que obtengan los ingresos referidos en el artículo anterior.\nArtículo Adicionado\nARTÍCULO 156-12 TER.- El impuesto por los premios derivados de loterías, rifas, sorteos, concursos y juegos con apuestas se calculará sobre el valor del premio correspondiente a cada boleto o billete, sin deducción alguna, aplicando tasa del 6%. impuesto que esta ley establece, el importe de dicho impuesto se considerará como ingreso de los comprendidos en este capítulo. No se pagará el impuesto establecido en este capítulo por la obtención de reintegros.\nArtículo Adicionado\nLey de Hacienda del Estado de Baja California. Página 44\n.\nActualización Legislativa.\nÚltima reforma P.O. No. 72, Índice, 22-Dic-2023\nARTÍCULO 156-13.- El impuesto que resulte de aplicar la tasa indicada en el artículo anterior, será retenido por las personas que paguen los premios, quienes deberán enterarlo a la Secretaría de Hacienda del Estado, dentro de los 25 días siguientes al en que realicen la retención. Lo anterior independientemente de que se trate de administradores, organizadores o anfitriones de algún establecimiento donde se lleven a cabo algunos de los juegos mencionados en el artículo anterior.\nPárrafo Reformado\nLos Organismos Públicos Descentralizados de la Administración Pública Federal aunque conforme a otras Leyes o Decretos no causen impuestos locales o estén exentos de ellos, deberán efectuar las retenciones de este impuesto y enterarlo de acuerdo al párrafo anterior.\nPárrafo Adicionado\nArtículo Adicionado\nArtículo Reformado\nARTÍCULO 156-14.- Quienes entreguen los premios a que se refiere este capítulo, además de efectuar las retenciones de este impuesto, tendrán las siguientes obligaciones:\nPárrafo Reformado\nI. Solicitar su inscripción en el Registro Estatal de Contribuyentes de la Secretaría de\nHacienda del Estado, en su carácter de retenedores, utilizando para tales efectos las formas aprobadas. Las personas morales estarán obligadas a entregar una copia del acta o documento constitutivo;\nFracción Adicionada\nII. Proporcionar, cuando así lo solicite el interesado, constancia de retención del impuesto a la persona que obtenga el premio, y\nFracción Adicionada\nIII. Conservar la documentación relacionada con las constancias y las retenciones de este impuesto, por plazo de cinco años, a disposición de la Secretaría de Hacienda del\nEstado.\nFracción Adicionada\nArtículo Adicionado\nArtículo Reformado\nCAPITULO XX\nCapítulo Adicionado, Derogado y Modificado\nARTICULO 156-15.- Es objeto de este impuesto la tenencia o uso de los siguientes nueve años modelo anteriores al de aplicación de la presente Ley:\na) Vehículos de personas físicas y morales tenedoras o usuarias, que estén afectos a una actividad empresarial, como lo es la comercial, industrial y/o de servicios;\nLey de Hacienda del Estado de Baja California. Página 45\n.\nActualización Legislativa.\nÚltima reforma P.O. No. 72, Índice, 22-Dic-2023\nb) Vehículos de personas físicas y morales tenedoras o usuarias, considerados caros o de lujo conforme a lo establecido en este Capítulo.\nPara efectos de este impuesto, se considerarán vehículos caros o de lujo, aquellos cuyo valor determinado en base a este capítulo sea de quinientos mil pesos o más.\nPara efectos de esta Ley, se presume que el propietario de un vehículo es tenedor o usuario del mismo, cuando:\na) Se inscriba en el registro estatal vehicular de Baja California;\nb) El tenedor o usuario del vehículo tenga domicilio en el Estado, y\nc) El domicilio fiscal o algún establecimiento del tenedor o usuario del vehículo se encuentre en el Estado, respecto de los vehículos utilizados en dicho domicilio o establecimiento y de los que se inscriban en el registro estatal vehicular de Baja California.\nArtículo Adicionado, Derogado y Reformado\nARTICULO 156-16.- Están obligadas al pago del impuesto estatal sobre tenencia o uso de vehículos las personas físicas y morales, tenedoras o usuarias de vehículos en el territorio del Estado de acuerdo a lo establecido en este Capítulo.\nPara los efectos de este Capítulo, tratándose de vehículos afectos al patrimonio de un fideicomiso, se considerará tenedora o usuaria de los mismos y por tanto sujeta de este impuesto y obligada al pago del mismo, a la fiduciaria que se encuentre administrando dicho patrimonio.\nEn los casos en que exista copropiedad respecto del vehículo, cada uno de los copropietarios se presumirán tenedores o usuarios del mismo.\nArtículo Adicionado, Derogado y Reformado\nARTICULO 156-17.- Cualquier persona física o moral que encuadre en los supuestos de causación del impuesto estatal sobre tenencia o uso de vehículos, deberá pagar dicho impuesto, con las excepciones que en este Capítulo se señalan, aún cuando de conformidad con otras leyes no estén obligados a pagar contribuciones estatales o estén exentos de ellas.\nArtículo Adicionado, Derogado y Reformado\nARTICULO 156-18.- Para efectos de este impuesto, se entiende por:\nI.- Vehículo: los automóviles, omnibuses, minibuses, autobuses integrales, camiones y tractores no agrícolas tipo quinta rueda, las embarcaciones, veleros, esquís acuáticos motorizados, motocicleta acuática, tabla de oleaje con motor, motocicletas y aeronaves.\nII.- Vehículo nuevo:\na) El que se enajena por primera vez al consumidor por el fabricante, ensamblador o año de aplicación del mismo.\nLey de Hacienda del Estado de Baja California. Página 46\n.\nActualización Legislativa.\nÚltima reforma P.O. No. 72, Índice, 22-Dic-2023\nb) El que sea importado definitivamente por primera vez al país que corresponda al año modelo siguiente al de aplicación de este Capítulo o al año de aplicación del mismo.\nIII.- Vehículo usado: Aquel que no se encuentre comprendido en la fracción anterior, y cuya antigüedad sea de hasta nueve años modelo anteriores al de aplicación de la presente Ley.\nIV.- Valor total del vehículo: El precio de origen de enajenación por parte del fabricante, ensamblador o distribuidor autorizado, incluyendo el equipo que provenga de fábrica o el que el enajenante le adicione a solicitud del consumidor, sin incluir el impuesto al valor agregado.\nEn el valor total del vehículo a que hace referencia el párrafo anterior, no se incluirán los intereses derivados de créditos otorgados para la adquisición del mismo.\nV.- Marca: Las denominaciones y distintivos que los fabricantes dan a sus vehículos para diferenciarlos de los demás.\nVI.- Año Modelo: El año de fabricación o el que le asigne el fabricante o ensamblador de conformidad con las normas aplicables.\nVII.- Modelo: Todas aquellas versiones de la carrocería básica con dos, tres, cuatro o cinco puertas que se deriven de una misma línea. Por carrocería básica se entenderá, el conjunto de piezas metálicas o de plástico, que configuran externamente a un vehículo y de la que derivan los diversos modelos.\nVIII.- Versión: Cada una de las distintas presentaciones comerciales que tiene un modelo.\nIX.- Peso Bruto Vehicular: Es el peso del vehículo totalmente equipado incluyendo chasis, cabina, carrocería, unidad de arrastre con el equipo y carga transportable.\nArtículo Adicionado, Derogado y Reformado\nARTICULO 156-19.- El pago del impuesto estatal sobre tenencia o uso de vehículos deberá calcularse y enterarse por año de calendario durante los tres primeros meses del mismo, salvo en el caso de vehículos nuevos, supuesto en el que el impuesto deberá calcularse y enterarse dentro del plazo de diez días hábiles siguientes de haber adquirido o importado el vehículo.\nTratándose de permisos de traslado, el impuesto a que hace referencia el presente\nCapítulo, se pagará al momento de solicitar dicho permiso, siempre que no hayan transcurrido los diez días hábiles señalados en el párrafo anterior; en caso contrario el impuesto deberá pagarse dentro de dicho periodo.\nRentas del Estado, instituciones o establecimientos autorizados para ello, o bien mediante los medios electrónicos que autorice para tal efecto la Secretaría de Hacienda.\nPárrafo Reformado\nLey de Hacienda del Estado de Baja California. Página 47\n.\nActualización Legislativa.\nÚltima reforma P.O. No. 72, Índice, 22-Dic-2023\nLos contribuyentes de este impuesto no están obligados a presentar, por dicha contribución, la solicitud de inscripción ni los avisos del registro estatal de causantes. No obstante lo anterior, los contribuyentes que se encuentren inscritos en el citado registro para efectos del pago de otras contribuciones, deberán anotar su clave correspondiente en los formatos de pago de este impuesto.\nLos contribuyentes comprobarán el pago del impuesto con el recibo o forma original autorizado por medio del cual lo hayan efectuado.\nLos fabricantes, ensambladores o distribuidores que enajenen vehículos por primera vez al consumidor, podrán recaudar y enterar a las Recaudaciones de Rentas del Estado el impuesto a que se refiere este Capítulo, en los términos que se establezcan en los convenios que en su caso se celebren con la citada dependencia.\nLas personas físicas o morales cuya actividad sea la enajenación de vehículos nuevos o importados, que asignen dichos vehículos a su servicio o al de sus funcionarios o empleados, deberán pagar el impuesto por el ejercicio en que hagan la asignación, en los términos previstos en el primer párrafo de este artículo.\nEn la enajenación o importación de vehículos nuevos de año modelo posterior al de la aplicación de este Capítulo, se pagará el impuesto correspondiente al año de calendario en que se enajene o importe, según corresponda. El impuesto para dichos vehículos se determinará en el siguiente año de calendario bajo el criterio de vehículo nuevo.\nArtículo Adicionado, Derogado y Reformado\nARTICULO 156-20.- Son solidariamente responsables del pago del impuesto establecido en este Capítulo:\nI.- Quienes por cualquier título, adquieran la propiedad del vehículo, por el adeudo del impuesto que en su caso existiera por el mismo, aún cuando se trate de personas que no están obligadas al pago de este impuesto.\nII.- Quienes reciban en consignación o comisión para su enajenación vehículos, por el adeudo del impuesto que en su caso existiera.\nIII.- Las autoridades y funcionarios que autoricen el registro de vehículos, permisos provisionales para circulación en traslado, altas, cambios o bajas de placas o efectúen la renovación de los mismos, sin haberse cerciorado que no existan adeudos por este impuesto correspondiente a los últimos cinco años, salvo en los casos en que el contribuyente acredite que se encuentra liberado de esta obligación.\nIV.- Las autoridades competentes para expedir los certificados de aeronavegabilidad aeronaves, cuando al expedirlos el propietario, tenedor o usuario del vehículo no compruebe\nCapítulo, a excepción de los casos en que se encuentre liberado de este pago. De no comprobarse que se ha cumplido con la obligación de pago, dichas oficinas lo harán del conocimiento de las autoridades fiscales correspondientes.\nLey de Hacienda del Estado de Baja California. Página 48\n.\nActualización Legislativa.\nÚltima reforma P.O. No. 72, Índice, 22-Dic-2023\nV.- Las empresas que otorguen el servicio de alojamiento o albergue temporal de embarcaciones en los sitios denominados “marinas turísticas” o en cualquier otro establecimiento destinado a la prestación de este tipo de servicio, cuando omitan informar a la autoridad fiscal que el propietario, tenedor o usuario del vehículo no comprobó el pago del impuesto estatal sobre tenencia o uso de vehículos a que se refiere este capítulo, a excepción de los casos en que se encuentre liberado de ese pago.\nArtículo Adicionado, Derogado y Reformado\nARTICULO 156-21.- Tratándose de vehículos nuevos el impuesto estatal sobre tenencia o uso de vehículos se pagará de la siguiente manera:\nI.- En el caso de automóviles destinados al transporte hasta de 15 pasajeros, el impuesto será la cantidad que resulte de aplicar al valor total del vehículo, la siguiente:\nTARIFA\n{\"tabla_1\":{\"columnas\":[\"Límite Inferior\\n$\",\"Límite Superior\\n$\",\"Cuota Fija\\n$\",\"Tasa para aplicarse\\nsobre el excedente\\ndel Límite Inferior\\n%\"],\"filas\":[{\"columna_1\":\"0.01\",\"columna_2\":\"526,657.78\",\"columna_3\":\"0.00\",\"columna_4\":\"3.0\"},{\"columna_1\":\"526,657.79\",\"columna_2\":\"1,013,523.64\",\"columna_3\":\"15,799.73\",\"columna_4\":\"8.7\"},{\"columna_1\":\"1,013,523.65\",\"columna_2\":\"1,362,288.13\",\"columna_3\":\"58,157.06\",\"columna_4\":\"13.3\"},{\"columna_1\":\"1,362,288.14\",\"columna_2\":\"1,711,052.62\",\"columna_3\":\"104,542.74\",\"columna_4\":\"16.8\"},{\"columna_1\":\"1´711,052.63\",\"columna_2\":\"En adelante\",\"columna_3\":\"163,135.16\",\"columna_4\":\"19.1\"}]}}\nPara la aplicación de la citada tarifa se deberá seguir el siguiente procedimiento:\n1.- Identificar el rango de la tarifa en la que encuadre el valor total del vehículo;\n2.- A dicho valor se le disminuirá el límite inferior del rango correspondiente;\n3.- El importe obtenido se multiplicará por la tasa que le corresponda según rango en el que se ubica;\n4.- A la cantidad que resulte se le sumará la cuota fija establecida en el rango;\n5.- El resultado será el impuesto correspondiente.\nTratándose de automóviles blindados, excepto camiones, la tarifa a que se refiere esta fracción, se aplicará sobre el valor total del vehículo, sin incluir el valor del material utilizado para el blindaje. En ningún caso, el impuesto que se tenga que pagar por dichos vehículos, será mayor al que tendrían que pagarse por la versión de mayor precio de enajenación de un automóvil sin blindaje del mismo modelo y año. Cuando no exista\nLey de Hacienda del Estado de Baja California. Página 49\n.\nActualización Legislativa.\nÚltima reforma P.O. No. 72, Índice, 22-Dic-2023 vehículo sin blindar que corresponda al mismo modelo, año o versión del automóvil blindado, el impuesto para este último, será la cantidad que resulte de aplicar al valor total del vehículo, la tarifa establecida en esta fracción, multiplicando el resultado por el factor de\n0.80.\nII.- Para vehículos destinados al transporte de más de 15 pasajeros o de carga cuyo peso bruto vehicular sea menor a 15 toneladas y para automóviles nuevos que cuenten con placas de servicio público de transporte de pasajeros y los denominados “taxis” el impuesto será la cantidad que resulte de aplicar al valor total del vehículo, la tasa del 0.245%.\nPara efectos de este artículo se entenderá por vehículos destinados al transporte de más de 15 pasajeros, los camiones, tractores no agrícolas tipo quinta rueda, así como minibuses, omnibuses, microbuses y autobuses integrales, cualquiera que sea su tipo y peso bruto vehicular, sin incluir a los denominados Pick Up´s.\nPara vehículos cuyo peso bruto vehicular sea de 15 a 35 toneladas, el impuesto se calculará multiplicando la cantidad que resulte de aplicar el 0.50% al valor total del vehículo, por el factor fiscal que resulte de dividir el peso bruto máximo vehicular expresado en toneladas, entre 30. En el caso de que peso sea mayor a 35 toneladas se tomará como peso bruto máximo vehicular esta cantidad.\nIII.-Tratándose de embarcaciones, veleros, esquís acuáticos motorizados, motocicletas acuáticas y tablas de oleaje con motor, el impuesto será la cantidad que resulte de aplicar al valor total del vehículo de que se trate el 1.5%.\nIV.-Tratándose de aeronaves el impuesto será la cantidad que resulte de aplicar al valor total del vehículo el 1%.\nArtículo Adicionado, Derogado y Reformado\nARTÍCULO 156-22.- Tratándose de vehículos usados el impuesto a que hace referencia el presente Capítulo se pagará de la siguiente manera:\nI.-Tratándose de automóviles de fabricación nacional o importados, destinados al transporte hasta de 15 pasajeros, el impuesto será el que resulte de aplicar el procedimiento siguiente:\na) El valor total del vehículo se multiplicará por el factor de depreciación, de acuerdo al año modelo del vehículo, de conformidad con la siguiente:\nTABLA\nAños de Factor de antigüedad Depreciación\n1 0.850\n2 0.725\n3 0.600\n4 0.500\n5 0.400\nLey de Hacienda del Estado de Baja California. Página 50\n.\nActualización Legislativa.\nÚltima reforma P.O. No. 72, Índice, 22-Dic-2023\n6 0.300\n7 0.225\n8 0.150\n9 0.075\nb) La cantidad obtenida, conforme al inciso anterior, se multiplicará por el factor de actualización a que se refiere esta fracción, y al resultado se le aplicará la tarifa a que hace referencia la fracción I, del artículo 156-21 de esta Ley.\nEl factor de actualización a que se refiere el párrafo anterior, será el correspondiente al período comprendido desde el último mes del año inmediato anterior a aquel en que se adquirió el automóvil de que se trate, hasta el último mes del año inmediato anterior a aquel por el que se debe efectuar el pago, mismo que se obtendrá de conformidad con el artículo\n17-A del Código Fiscal de la Federación.\nII.- Para vehículos de fabricación nacional o importados de más de 15 pasajeros o de carga cuyo peso bruto vehicular sea menor a 15 toneladas, así como aeronaves, el impuesto será el que resulte de multiplicar el importe del impuesto causado en el ejercicio fiscal inmediato anterior por el factor de ajuste.\nEl factor de ajuste será el que resulte de multiplicar el factor de actualización por el factor que le corresponda conforme a los años de antigüedad del vehículo, de acuerdo con la siguiente:\nTABLA\nAños de\nFactor antigüedad\n1 0.900\n2 0.889\n3 0.875\n4 0.857\n5 0.833\n6 0.800\n7 0.750\n8 0.667\n9 0.500\nEl factor de actualización a que se refiere esta fracción, será el correspondiente al diciembre inmediato anterior a aquél por el cual se efectúa la actualización, mismo que se obtendrá de conformidad con el artículo 17-A del Código Fiscal de la Federación.\nIII.- Tratándose de vehículos de servicio particular que pasen a ser de servicio público para transporte de pasajeros y los denominados “taxis”, el impuesto estatal sobre tenencia o uso de vehículos se calculará, para el ejercicio fiscal siguiente a aquél en que se dé esta circunstancia conforme al siguiente procedimiento:\nLey de Hacienda del Estado de Baja California. Página 51\n.\nActualización Legislativa.\nÚltima reforma P.O. No. 72, Índice, 22-Dic-2023\na) El valor total del vehículo se multiplicará por el factor de depreciación de acuerdo al año modelo del vehículo, de conformidad con la tabla establecida en la fracción I de este artículo, y\nb) La cantidad obtenida, conforme al inciso anterior, se actualizará de conformidad con lo dispuesto en la fracción I de este artículo; y el resultado obtenido se multiplicará por el\n0.245%.\nIV.-Tratándose de embarcaciones, veleros, esquís acuáticos motorizados, motocicletas acuáticas y tablas de oleaje con motor, el impuesto será el que resulte de multiplicar el importe del impuesto causado en el ejercicio fiscal inmediato anterior por el factor de ajuste.\nEl factor de ajuste será el que resulte de multiplicar el factor de actualización por el factor que le corresponda conforme a los años de antigüedad del vehículo, de acuerdo con la siguiente:\nTABLA\n{\"tabla_2\":{\"columnas\":[\"Años de\\nantigüedad\",\"Factor de\\nDepreciación\"],\"filas\":[{\"columna_1\":\"1\",\"columna_2\":\"0.9250\"},{\"columna_1\":\"2\",\"columna_2\":\"0.8500\"},{\"columna_1\":\"3\",\"columna_2\":\"0.7875\"},{\"columna_1\":\"4\",\"columna_2\":\"0.7250\"},{\"columna_1\":\"5\",\"columna_2\":\"0.6625\"},{\"columna_1\":\"6\",\"columna_2\":\"0.6000\"},{\"columna_1\":\"7\",\"columna_2\":\"0.5500\"},{\"columna_1\":\"8\",\"columna_2\":\"0.5000\"},{\"columna_1\":\"9\",\"columna_2\":\"0.4500\"}]}}\nEl factor de actualización a que se refiere esta fracción, será el correspondiente al período comprendido desde el mes de diciembre del penúltimo año hasta el mes de diciembre inmediato anterior a aquél por el cual se efectúa la actualización, mismo que se obtendrá de conformidad con el artículo 17-A del Código Fiscal de la Federación.\nPara los efectos de este Capítulo, los años de antigüedad se calcularán con base en el número de años transcurridos a partir del año modelo al que corresponda el vehículo.\nArtículo Adicionado\nARTÍCULO 156-23.- Para determinar el impuesto estatal sobre tenencia o uso de vehículos del año en que los vehículos usados sean importados por primera vez al país, se aplicará el siguiente procedimiento:\nI. Tratándose de vehículos destinados al transporte hasta de 15 pasajeros, es decir de los comprendidos en la fracción I, del artículo 156-22, el impuesto será el que resulte de aplicar al valor total del vehículo, el factor de depreciación y actualización de la citada\nLey de Hacienda del Estado de Baja California. Página 52\n.\nActualización Legislativa.\nÚltima reforma P.O. No. 72, Índice, 22-Dic-2023 fracción, y al resultado se aplica la tarifa establecida en la fracción I del artículo 156-21 de esta Ley.\nII. Tratándose de los vehículos a que hace referencia la fracción II y IV, del artículo\n156-22 de esta Ley, el impuesto será el que resulte de aplicar el siguiente procedimiento:\na) El valor total del vehículo se depreciará de conformidad con la tabla que corresponda para cada tipo de vehículo según lo establecido en la fracciones II y IV, del artículo 156-22;\nb) El resultado se actualizará de conformidad con la fracción I, del artículo 156-22;\nc) A la cantidad obtenida conforme al inciso anterior, se le aplicará la tasa o tarifa que corresponda según el tipo de vehículo de que se trate, de conformidad con el artículo\n156-21 del presente Capítulo.\nArtículo Adicionado\nARTÍCULO 156-24.- Cuando la enajenación o importación de vehículos nuevos se efectúe después del primer mes del año de calendario, el impuesto por dicho año se pagará en la proporción que resulte de aplicar el factor correspondiente:\n{\"tabla_3\":{\"columnas\":[\"Mes de\\nadquisición\",\"Factor\\naplicable al\\nimpuesto\"],\"filas\":[{\"columna_1\":\"Febrero\",\"columna_2\":\"0.92\"},{\"columna_1\":\"Marzo\",\"columna_2\":\"0.83\"},{\"columna_1\":\"Abril\",\"columna_2\":\"0.75\"},{\"columna_1\":\"Mayo\",\"columna_2\":\"0.67\"},{\"columna_1\":\"Junio\",\"columna_2\":\"0.58\"},{\"columna_1\":\"Julio\",\"columna_2\":\"0.50\"},{\"columna_1\":\"Agosto\",\"columna_2\":\"0.42\"},{\"columna_1\":\"Septiembre\",\"columna_2\":\"0.33\"},{\"columna_1\":\"Octubre\",\"columna_2\":\"0.25\"},{\"columna_1\":\"Noviembre\",\"columna_2\":\"0.17\"},{\"columna_1\":\"Diciembre\",\"columna_2\":\"0.08\"}]}}\nArtículo Adicionado\nARTÍCULO 156-25.- Cuando el contribuyente del impuesto estatal sobre tenencia o uso de vehículos sufra el robo o pérdida total por accidente, pagará el impuesto correspondiente en proporción al número de meses transcurridos hasta dicha circunstancia, siempre y cuando quede debidamente acreditada la misma ante la autoridad competente; sin impuesto, en caso de haberse cubierto el mismo con anterioridad al robo o pérdida total del vehículo.\nArtículo Adicionado\nLey de Hacienda del Estado de Baja California. Página 53\n.\nActualización Legislativa.\nÚltima reforma P.O. No. 72, Índice, 22-Dic-2023\nARTÍCULO 156-26.- En los casos en que los contribuyentes obligados a realizar el pago en el Estado de Baja California, demuestren haber cubierto el impuesto estatal sobre tenencia o uso de vehículos correspondiente al año de calendario de que se trate en otra entidad federativa, cuyo objeto grave la tenencia o uso, o bien la propiedad de vehículos, podrá solicitar se acredite el importe cubierto, debiendo pagar, en su caso, la parte proporcional que quede pendiente una vez realizado el cálculo correspondiente al de esta\nEntidad.\nNo será sujeto de devolución o compensación, el importe cubierto en exceso en otra\nEntidad Federativa.\nArtículo Adicionado\nARTÍCULO 156-27.- En caso de que no puedan comprobarse los años de antigüedad del vehículo, el impuesto a que se refiere este capítulo, se pagará como si éste fuese nuevo.\nArtículo Adicionado\nARTÍCULO 156-28.- No se pagará el impuesto que se establece en el presente\nCapítulo respecto de los siguientes vehículos:\nI.- Los importados temporalmente en los términos de la legislación aduanera.\nII.- Los vehículos de los gobiernos centrales de la Federación, Estado o Municipios y aquellos que sean utilizados para la prestación de los servicios públicos de rescate, patrullas, transportes de limpia, pipas de agua, servicios funerarios, y las ambulancias dependientes de entidades públicas o de instituciones de beneficencia autorizadas por las leyes de la materia y los destinados a los cuerpos de bomberos.\nIII.- Los automóviles al servicio de misiones Diplomáticas y Consulares de carrera extranjeras y de sus agentes diplomáticos y consulares de carrera, excluyendo a los cónsules generales honorarios, cónsules y vicecónsules honorarios, siempre que sea exclusivamente para uso oficial y exista reciprocidad.\nIV.- Las embarcaciones dedicadas al transporte mercante o a la pesca comercial.\nV.- Las aeronaves monomotoras de una plaza, fabricadas o adaptadas para fumigar, rociar o esparcir líquidos o sólidos, con tolva de carga.\nVI.- Las aeronaves con capacidad de más de 20 pasajeros, destinadas al aerotransporte al público en general.\nVII.- Los que tengan para su venta los fabricantes, las plantas ensambladoras, sus distribuidores y los comerciantes en el ramo de vehículos, siempre que carezcan de placas de circulación.\nVIII.- Los automóviles eléctricos nuevos y usados, así como aquellos que además cuenten con motor de combustión interna o con motor accionado por hidrógeno.\nIX.- Los automóviles propiedad de personas con discapacidad debidamente acreditada en los términos que establezca la Secretaría de Hacienda. Un vehículo por persona.\nLey de Hacienda del Estado de Baja California. Página 54\n.\nActualización Legislativa.\nÚltima reforma P.O. No. 72, Índice, 22-Dic-2023\nFracción Reformada\nX.- Los Automóviles propiedad de asociaciones civiles que no persigan fines de lucro y de asociaciones religiosas constituidas en los términos de la Ley respectiva, con domicilio en Baja California.\nXI.- Las motocicletas.\nXII.- Los automóviles propiedad de partidos políticos debidamente registrados conforme a las leyes respectivas.\nCuando por cualquier motivo un vehículo deje de estar comprendido en los supuestos a que se refieren las fracciones anteriores, el propietario del mismo deberá pagar el impuesto correspondiente dentro de los 10 días hábiles siguientes a aquel en que tenga lugar el hecho de que se trate.\nArtículo Adicionado\nARTÍCULO 156-29.- Los tenedores o usuarios de los vehículos a que se refieren las fracciones I, II, IX, X y XII, del artículo anterior, para gozar del beneficio que el mismo establece, deberán comprobar ante la Secretaría de Hacienda que se encuentran comprendidos en dichos supuestos, cumpliendo los lineamientos que para tal efecto emita la citada Secretaría.\nArtículo Adicionado\nArtículo Reformado\nARTÍCULO 156-30.- De la contribución obtenida por concepto del impuesto estatal sobre tenencia o uso de vehículos, corresponderá el 20% a los Municipios del Estado, distribuyéndose en proporción a la recaudación de este impuesto obtenida en cada uno de los Municipios en el ejercicio fiscal anterior. En virtud de ello, este impuesto no se considerará para la determinación de las participaciones a que se refiere el artículo 7º de la\nLey de Coordinación Fiscal del Estado de Baja California, ni para el fondo compensatorio a que se refiere el artículo 7º BIS de la citada ley.\nArtículo Adicionado\nARTÍCULO 156-31.- Los fabricantes, ensambladores y distribuidores autorizados, así como los comerciantes en el ramo de vehículos, tendrán la obligación de proporcionar a la inmediato anterior, a través de los dispositivos electromagnéticos procesados en los términos que señale dicha Secretaría mediante disposiciones de carácter general.\nPárrafo Reformado\nLos que tengan más de un establecimiento, deberán presentar la información a que se refiere este artículo, haciendo la separación por cada uno de los establecimientos.\nArtículo Adicionado\nArtículo Reformado\nLey de Hacienda del Estado de Baja California. Página 55\n.\nActualización Legislativa.\nÚltima reforma P.O. No. 72, Índice, 22-Dic-2023\nARTÍCULO 156-32.- Los importes señalados en este capítulo, se actualizarán anualmente en los meses de enero, considerando el factor que se obtenga de dividir el índice nacional de precios al consumidor del mes de diciembre del año inmediato anterior, entre el citado índice correspondiente al mes de diciembre del penúltimo año. La Secretaría de Hacienda publicará los importes actualizados.\nArtículo Adicionado\nArtículo Reformado\nCAPÍTULO XXI\nDEL IMPUESTO ESTATAL A LA VENTA FINAL DE BEBIDAS CON CONTENIDO\nALCOHÓLICO\nCapítulo Adicionado\nARTÍCULO 156-33.- Es objeto de este impuesto la venta final de bebidas con contenido alcohólico en envase cerrado, llevada a cabo en territorio del Estado de Baja\nCalifornia, excepto cerveza.\nPara efecto de este Capítulo, se considerarán bebidas con contenido alcohólico aquellas definidas con tal carácter en la Ley del Impuesto Especial Sobre Producción y\nServicios.\nSe entiende que la venta se efectúa en territorio del Estado, si en él se lleva a cabo la entrega material de las bebidas.\nArtículo Adicionado\nARTÍCULO 156-34.- Son sujetos de este impuesto, las personas físicas o morales que realicen en territorio del Estado de Baja California la venta final en envase cerrado de bebidas con contenido alcohólico, excepto cerveza.\nArtículo Adicionado\nARTÍCULO 156-35.- La base del impuesto es el precio percibido por la venta de las bebidas señaladas en el artículo 156-33, sin incluir los impuestos al valor agregado ni especial sobre producción y servicios.\nArtículo Adicionado\nARTÍCULO 156-36.- El impuesto deberá incluirse en el precio correspondiente, sin que se considere que forma parte del precio de venta al público, ni se entienda violatorio de precios o tarifas, incluyendo en su caso precios oficiales. Por lo que el impuesto no deberá bebidas.\nArtículo Adicionado\nARTÍCULO 156-37.- Los contribuyentes del presente impuesto, pagarán el mismo, sin que proceda acreditamiento alguno contra dicho pago.\nLey de Hacienda del Estado de Baja California. Página 56\n.\nActualización Legislativa.\nÚltima reforma P.O. No. 72, Índice, 22-Dic-2023\nCuando la contraprestación que perciba el contribuyente por la venta de las bebidas no sea en dinero, sino total o parcialmente en otros bienes o servicios, se considerará como valor de éstos el de mercado o, en su defecto, el de avalúo. Los mismos valores se tomarán en cuenta en caso de donación, cuando por ella se deba pagar el impuesto establecido en este capítulo.\nArtículo Adicionado\nARTÍCULO 156-38.- El impuesto se calculará mensualmente y se enterará al Estado a más tardar el día 25 del mes siguiente a aquél al que corresponda el pago. Los pagos mensuales se realizarán en los términos que para el pago de contribuciones se establecen en el Código Fiscal del Estado, y tendrán el carácter de definitivos.\nArtículo Adicionado\nARTÍCULO 156-39.- Los distribuidores o comerciantes que enajenen las bebidas a que se refiere el artículo 156-33, a quienes a su vez venderán en envase cerrado las citadas bebidas, estarán obligados a llevar un registro mensual de estas personas, debiendo recabar de ellos y conservar una copia del registro ante el Estado de la obligación a que se refiere el artículo 156-42 fracción IV.\nQuienes no cumplan con la obligación señalada en el párrafo anterior, serán responsables solidarios del impuesto que se dejare de pagar respecto de las bebidas enajenadas por ellos.\nArtículo Adicionado\nARTÍCULO 156-40.- Para los efectos de este impuesto, también se considerará venta final, el faltante de inventario o el consumo propio de las bebidas referidas en el artículo 156-\n33.\nArtículo Adicionado\nARTÍCULO 156-41.- El impuesto se causa en el momento en el que se perciban los ingresos derivados de la venta y sobre el monto de lo pagado. Cuando las contraprestaciones se paguen parcialmente, el impuesto se calculará aplicando a la parte de la contraprestación pagada, la tasa respectiva.\nArtículo Adicionado\nARTÍCULO 156-42.- Los contribuyentes de este impuesto tienen, además de las obligaciones señaladas en este capítulo y en las demás disposiciones fiscales, las siguientes:\nI. Llevar contabilidad de conformidad con el Código Fiscal del Estado, y conforme a las Reglas de Carácter General que en su caso emita la Secretaría de Hacienda. Asimismo, se deberán identificar las operaciones por las que deba pagarse este impuesto.\nFracción Reformada\nII. Presentar las declaraciones relativas al impuesto previsto en el presente capítulo.\nSi un contribuyente tuviera varios establecimientos en el Estado, presentará una declaración por cada establecimiento, o bien una concentrada por todo el Estado.\nLey de Hacienda del Estado de Baja California. Página 57\n.\nActualización Legislativa.\nÚltima reforma P.O. No. 72, Índice, 22-Dic-2023\nIII. Proporcionar la información que en relación con este impuesto se les solicite en las declaraciones respectivas.\nIV. Registrar la obligación de pago del presente impuesto y los establecimientos en los que se realicen las actividades gravadas, ante la Recaudación de Rentas del Estado respectiva, dentro de los 15 días siguientes a que inicie operaciones o a que empiece a enajenar las bebidas señaladas en el artículo 156-33.\nArtículo Adicionado\nARTÍCULO 156-43.- La tasa del impuesto será del 4.5 por ciento sobre el ingreso percibido por la venta de las bebidas objeto de este impuesto.\nArtículo Adicionado\nARTÍCULO 156-44.- Derogado.\nArtículo Derogado\nARTÍCULO 156-45.- De la recaudación obtenida por concepto de este impuesto, corresponderá el 20% a los Municipios del Estado, distribuyéndose en proporción a la recaudación del mismo obtenida en cada uno de los Municipios en el ejercicio fiscal anterior.\nEn virtud de ello, este impuesto no se considerará para la determinación de las participaciones a que se refiere el artículo 7º de la Ley de Coordinación Fiscal del Estado de\nBaja California, ni para el fondo compensatorio a que se refiere el artículo 7º BIS de la citada ley.\nArtículo Adicionado\nCAPÍTULO XXII\nCapítulo Adicionado\nSECCIÓN PRIMERA\nIMPUESTO A CASAS DE EMPEÑO\nDE LOS SUJETOS Y EL OBJETO\nSección Adicionada\nARTÍCULO 156-46. Están obligadas al pago del impuesto establecido en este capítulo las personas físicas y morales que en el territorio del Estado de Baja California, en forma habitual o profesional, realicen u oferten al público contrataciones u operaciones de mutuo con interés y garantía prendaria no reguladas por leyes y autoridades financieras, prendario y sean posteriormente enajenados. El impuesto se causará en la fecha en la que el bien dado en prenda se enajene al público en general.\nArtículo Adicionado\nSECCIÓN SEGUNDA\nDE LA BASE GRAVABLE, TASA Y ÉPOCA DE PAGO\nSección Adicionada\nLey de Hacienda del Estado de Baja California. Página 58\n.\nActualización Legislativa.\nÚltima reforma P.O. No. 72, Índice, 22-Dic-2023\nARTÍCULO 156-47.- El impuesto se calculará aplicando la tasa del 20% a la diferencia entre el monto del avalúo que sirve de base para el otorgamiento del crédito prendario y el monto de la enajenación del bien otorgado en garantía prendaria que celebren los sujetos de este impuesto con el público en general.\nEl monto del avalúo es la valoración del bien mueble dado en prenda, que queda consignado en la boleta o billete de empeño, contrato o cualquier otra denominación que se otorgue al documento en el que se formalice el préstamo otorgado, los intereses pactados y cualquier otro gasto por parte del prestamista, así como el plazo para la recuperación del bien dado en prenda.\nArtículo Adicionado\nARTÍCULO 156-48.- El pago de este impuesto se efectuará mediante declaración mensual definitiva que presentarán los contribuyentes en las oficinas autorizadas por la\nSecretaría de Hacienda del Estado, a más tardar el día 25 del mes siguiente a aquél en que se haya producido la enajenación de la prenda de que se trate.\nArtículo Adicionado\nArtículo Reformado\nSECCIÓN TERCERA\nDE LAS OBLIGACIONES DE LOS CONTRIBUYENTES\nSección Adicionada\nARTÍCULO 156-49.- Son obligaciones de los sujetos del impuesto:\nI. Llevar y conservar los registros contables y administrativos de conformidad con las leyes y demás disposiciones aplicables.\nII. Mantener en los establecimientos o sucursales en los cuales se realicen las operaciones o contrataciones materia de este impuesto, las boletas o billetes de empeño y contratos, o cualquier otro documento que sustenten tales operaciones o contrataciones y permitan la plena identificación del deudor prendario incluyendo su domicilio y número telefónico, así como exhibirlos cuando las autoridades competentes lo requieran.\nArtículo Adicionado\nCAPÍTULO XXIII\nIMPUESTO A EMPRESAS DE REDES DE TRANSPORTE\nCapítulo Adicionado\nARTÍCULO 156-50.- El objeto de este impuesto es el ingreso o contraprestaciones pago electrónico, en efectivo o en algorítmicos de fidelidad, por cada traslado iniciado dentro del territorio del Estado de Baja California.\nSe entenderán como empresas de redes de transporte, aquellas personas físicas o morales cuyo servicio se limita exclusivamente a intermediar vía electrónica la oferta, Ley de Hacienda del Estado de Baja California. Página 59\n.\nActualización Legislativa.\nÚltima reforma P.O. No. 72, Índice, 22-Dic-2023 contratación y pago de servicios de transporte público o privado de pasajeros, vinculado a través de dicha aplicación a usuarios con prestadores del servicio en cualquiera de sus modalidades autorizadas y registradas ante el Instituto de Movilidad Sustentable del Estado de Baja California.\nTambién podrán ser considerados como Empresas de Redes de Transportes aquellas sociedades mercantiles nacionales o extranjeras que, por virtud de acuerdos comerciales vigentes, promuevan el uso de tecnológicas o aplicaciones tecnológicas, propias o de terceros que permitan a usuarios del estado acceder al servicio de transporte de pasajeros bajo demanda mediante aplicaciones móviles.\nArtículo Adicionado\nARTÍCULO 156-51.- Son sujetos de este impuesto las empresas de redes de transporte que promuevan, administren u operen traslados dentro del territorio del Estado de\nBaja California.\nArtículo Adicionado\nARTÍCULO 156-52.- La base del impuesto lo constituyen los ingresos o contraprestaciones de todo tipo y las tarifas cobradas por las empresas de redes de transporte al usuario o beneficiario del servicio de transporte por cualesquier medio de pago, sea este electrónico, en efectivo o algorítmico de fidelidad que inicie un traslado dentro del\nEstado de Baja California. Se aplicará a la base del impuesto una tasa del 1.50% (uno y medio por ciento).\nNo se considera para la base del presente impuesto, el Impuesto al Valor Agregado que se hubiere trasladado según la legislación fiscal.\nArtículo Adicionado\nARTÍCULO 156-53.- Los causantes, deberán presentar declaración mensual en las formas aprobadas por la Secretaría, pudiendo ser estos por medios electrónicos en los formatos aprobados por esta misma, y se enterará el impuesto causado a más tardar el día\n25 del mes siguiente a aquél en que se hubieren obtenido o pagado los ingresos gravados.\nArtículo Adicionado\nARTÍCULO 156-54.- Quienes se encuentren dentro de los supuestos del presente\nCapítulo, además de efectuar el cálculo y entero de este impuesto, tendrán las siguientes obligaciones:\nI. Solicitar su inscripción ante el Registro Estatal de Causantes de la Secretaría de\nHacienda del Estado como causante o retenedor, utilizando para tales efectos las formas o medios aprobados por la Secretaría.\nII. Entregar una copia del acta o documento constitutivo, así como los datos de momento con un domicilio fiscal y físico.\nLey de Hacienda del Estado de Baja California. Página 60\n.\nActualización Legislativa.\nÚltima reforma P.O. No. 72, Índice, 22-Dic-2023\nIII. Conservar la documentación relacionada con las cantidades calculadas de las tarifas efectivamente cobradas de este impuesto, por un plazo no menor a cinco años.\nArtículo Adicionado\nCAPÍTULO XXIV\nIMPUESTO AMBIENTAL SOBRE LA EXTRACCIÓN Y\nAPROVECHAMIENTO DE MATERIALES PÉTREOS\nCapítulo Adicionado\nARTÍCULO 156-55. - Es objeto de este impuesto, la extracción y aprovechamiento de\nMaterial pétreo que se realice en el Estado, incluyendo en el régimen de propiedad privada o ejidal.\nPara efectos de este impuesto se considerarán materiales pétreos, los minerales o sustancias no reservadas a la Federación, que constituyan depósitos de naturaleza similar a los componentes de los terrenos, como pueden ser la arena, arcilla, limos, materiales en greña, grava, las rocas o demás productos de su descomposición.\nArtículo Adicionado\nARTÍCULO 156-56.- Son sujetos de este impuesto las personas físicas o morales, que con fines de lucro, realicen las actividades señaladas en el presente capítulo.\nArtículo Adicionado\nARTÍCULO 156-57.- La base del impuesto será el volumen mensual determinado en metros cúbicos, de extracción y aprovechamiento de material pétreo.\nArtículo Adicionado\nARTÍCULO 156-58.- La cuota a enterar por concepto del presente impuesto será la que se establezca para tal efecto en la Ley de Ingresos del Estado de Baja California vigente.\nArtículo Adicionado\nARTÍCULO 156-59.- El impuesto se pagará mensualmente ante las oficinas de la\nRecaudación de Rentas del Estado, mediante las formas aprobadas por la Secretaría de\nHacienda, dentro de los cinco primeros días del mes siguiente al de la extracción y aprovechamiento.\nArtículo Adicionado\nARTÍCULO 156-60.- Son obligaciones a cargo de los sujetos de este impuesto, además de las señaladas en los ordenamientos fiscales estatales, las siguientes:\na) Registrarse como sujeto de este impuesto ante la Recaudación de Rentas del\nEstado cuya jurisdicción corresponda a su domicilio fiscal.\nb) Contar con la autorización en materia de impacto ambiental otorgada por la aprovechamiento de materiales pétreos, en términos de las disposiciones legales aplicables.\nLey de Hacienda del Estado de Baja California. Página 61\n.\nActualización Legislativa.\nÚltima reforma P.O. No. 72, Índice, 22-Dic-2023\nPara efectos del presente capítulo, se presume que la persona física o moral que cuenta con la autorización referida en este inciso es quien realiza la extracción y aprovechamiento de materiales pétreos.\nc) Llevar un registro diario de los volúmenes extraídos en el formato que para tal efecto autorice y expida la Secretaría de Medio Ambiente y Desarrollo Sustentable, el cual deberá conservarse en los términos que ésta determine mediante disposiciones de carácter general.\nd) Presentar declaración mensual de pago en los términos del presente artículo anexando para tal efecto, el registro a que se refiere el inciso c).\nArtículo Adicionado\nTITULO III\nDERECHOS\nARTICULO 157.- Los servicios que el Gobierno del Estado proporcione en forma directa o a través de sus organismos descentralizados o concesionarios, al realizar una actividad de interés público, obligan a quien los reciba, al pago de los derechos correspondientes.\nEn el caso de los Organismos Descentralizados, Concesionarios, Empresas de\nParticipación Estatal o Paraestatales, deberán sujetarse a lo establecido en el artículo 4-1 del presente ordenamiento.\nArtículo Reformado\nARTICULO 158.- Los derechos se causarán y pagarán de conformidad con las tasas, cuotas y tarifas que establezca la Ley de Ingresos del Estado.\nPara la recaudación del pago de Derechos por los Organismos Descentralizados, Concesionarios, Empresas de Participación Estatal o Paraestatales, deberán sujetarse a lo establecido en el artículo 4-1 del presente ordenamiento.\nArtículo Reformado\nARTICULO 159.- Los derechos se causan en el momento en que se presten los servicios, o en la forma que determina la Ley de Ingresos del Estado.\nARTICULO 160.- Sólo podrán cobrarse los derechos que expresamente autorice la\nLey de Ingresos del Estado.\nArtículo Reformado\nTITULO IV\nPRODUCTOS\nARTICULO 161.- Derogado.\nArtículo Derogado\nLey de Hacienda del Estado de Baja California. Página 62\n.\nActualización Legislativa.\nÚltima reforma P.O. No. 72, Índice, 22-Dic-2023\nARTICULO 162.- Derogado.\nArtículo Derogado\nARTICULO 163.- Los productos provenientes de las ventas o arrendamientos de muebles e inmuebles del Estado u otros actos sobre los mismos, se originarán en los contratos que se celebren o en las concesiones que se otorguen al efecto por el Ejecutivo del Estado, en uso de sus atribuciones legales.\nARTICULO 164.- Los productos de los establecimientos dependientes del Gobierno del Estado, en los que se ejerzan actividades económicas lucrativas, que no correspondan a las funciones de Derecho Público, se regirán por las bases generales que fije el Ejecutivo del\nEstado y su cobro se sujetará a lo que en las mismas bases se disponga.\nARTICULO 165.- Los capitales impuestos a réditos, así como toda clase de acciones y valores que formen parte de la Hacienda Pública del Estado y los intereses o productos de los mismos, se regirán por los contratos o actos jurídicos de que se deriven.\nEn caso de que se incurra en mora en el pago de los créditos, éstos se harán efectivos en la forma convenida en los propios actos o contratos, y a falta de estos, en la vía judicial.\nArtículo Reformado\nARTICULO 166.- Los rendimientos producidos por organismos descentralizados y empresas de participación estatal, se percibirán cuando lo decreten y exhiban, conforme a sus respectivos regímenes interiores, los organismos y empresas que los produzcan.\nTITULO V\nAPROVECHAMIENTOS\nARTICULO 167.- Los aprovechamientos que perciba el Estado se regirán por las estipulaciones de los actos, convenios o contratos que se celebren o por las disposiciones que al respecto señalen esta Ley o la Ley de Ingresos del Estado; su importe deberá enterarse en la Recaudación de Rentas correspondiente en los plazos, términos y condiciones que se establezcan en los mismos o en las disposiciones legales.\nTITULO VI\nPARTICIPACIONES\nARTICULO 168.- Las participaciones se regirán por las disposiciones que al respecto celebren.\nTITULO VII\nCONTRIBUCIONES DE MEJORAS\nARTICULO 169.- Las contribuciones de mejoras que establezcan las leyes\nLey de Hacienda del Estado de Baja California. Página 63\n.\nActualización Legislativa.\nÚltima reforma P.O. No. 72, Índice, 22-Dic-2023 especiales, se causarán y pagarán en la forma y términos que las mismas leyes dispongan.\nArtículo Reformado\nTITULO VIII\nINGRESOS EXTRAORDINARIOS\nARTICULO 170.- Los ingresos extraordinarios se regirán por las leyes que los establezcan o en su caso, por los decretos o contratos respectivos.\nArtículo Reformado\nARTICULO 171.- Los ingresos a que se refiere el Artículo anterior, podrán ser los siguientes:\nI.- Empréstitos;\nII.- Impuestos Extraordinarios;\nIII.- Derechos extraordinarios por la prestación de servicios;\nIV.- Expropiaciones;\nV.- Aportaciones extraordinarias de los Entes Públicos.\nTITULO NOVENO\nDE LOS ESTIMULOS Y LAS EXENCIONES DE PAGO\nTítulo Adicionado\nDenominación Modificada\nARTICULO 172.- Los jubilados, pensionados e indigentes mayores de sesenta años, personas viudas en situación de indigencia mayores de cincuenta años, personas con discapacidad, personas que tengan a su cargo un familiar con alguna discapacidad, Madres\nJefas de Familia, y empresas, quedarán exentas del pago de contribuciones a que se refiere este Título, en los términos y condiciones que en el mismo se establecen.\nPara efectos de esta Ley se consideran:\nI.- Jubilados o Pensionados: aquellas personas que acreditan la calidad de Seguridad Social que a continuación se señalan:\na) Instituto de Seguridad y Servicios Sociales de los Trabajadores del Gobierno y\nMunicipios del Estado de Baja California.\nb) Instituto Mexicano del Seguro Social.\nc) Instituto de Seguridad y Servicios Sociales de los Trabajadores del Estado.\nd) Institutos de Seguridad y Servicios Sociales de las Fuerzas Armadas Mexicanas, de Petróleos Mexicanos, de la Comisión Federal de Electricidad y de Ferrocarriles\nLey de Hacienda del Estado de Baja California. Página 64\n.\nActualización Legislativa.\nÚltima reforma P.O. No. 72, Índice, 22-Dic-2023\ne) Otras instituciones de seguridad social que presten estos servicios en las diversas entidades federativas del país, o a diversas agrupaciones sindicales.\nII. Indigentes mayores de 60 años y personas viudas en situación de indigencia mayores de 50 años: las que comprueben su edad con acta de nacimiento, o bien que se identifiquen con credencial expedida por el Instituto Nacional de las Personas Adultas\nMayores; la viudez con el acta de defunción del cónyuge, y la indigencia, previo estudio socioeconómico con vigencia anual que realice el Sistema Estatal para el Desarrollo Integral de la Familia.\nIII. Personas con discapacidad: Las personas que acrediten su discapacidad mediante certificado médico, expedido por cualquier institución pública de salud con domicilio en el\nEstado. El Sistema Estatal para el Desarrollo Integral de la Familia, expedirá la constancia para acreditar que no son económicamente activas o que siéndolo, sus ingresos no rebasan el equivalente a 5 veces el salario mínimo diario general vigente en el Estado.\nIV. Empresa: La definida como tal en la Ley de Fomento a la Competitividad y\nDesarrollo Económico para el Estado de Baja California.\nV. Personas que tengan a su cargo un familiar con alguna discapacidad: Las personas que acrediten tener a su cargo y sostenimiento económico a un familiar discapacitado en los términos de la fracción III, residan en el mismo domicilio y se encuentren registradas como responsables en la credencial o constancia oficial con la que se acredite la discapacidad; además que su parentesco sea consanguíneo hasta el cuarto grado; por afinidad hasta el segundo grado ó civil, debidamente acreditados. El Sistema\nEstatal para el Desarrollo Integral de la Familia, expedirá la constancia de estudio socioeconómico para acreditar que sus ingresos no rebasan el equivalente a 5 veces el salario mínimo diario general vigente en el Estado.\nVI. Madres Jefas de Familia: Madres de familia, sin cónyuge o pareja en aptitud de trabajar, que son el único sostén del hogar, con hijo o hijos menores de edad y cuyos ingresos no excedan de 5 veces el salario mínimo diario general vigente en el Estado. Para acreditar esta condición el Sistema Estatal para el Desarrollo Integral de la Familia, expedirá la constancia correspondiente previo estudio socioeconómico.\nArtículo Adicionado\nArtículo Reformado\nARTICULO 173.- Las exenciones que este Título otorga a los jubilados y pensionados, así como a las personas con discapacidad que realicen alguna actividad económicamente activa, siempre que sus ingresos no excedan de 5 veces el valor diario de la Unidad de Medida y Actualización vigente, personas que tengan a su cargo un familiar con alguna discapacidad, así como las Madres Jefas de Familia, serán del 50% del monto del crédito fiscal de las contribuciones reguladas por esta Ley, que a continuación se detallan y, se otorgarán dentro de los lineamientos siguientes:\nPárrafo Reformado\nI.- impuesto sobre compra venta y operaciones similares que excedan del valor anual de la Unidad de Medida y Actualización vigente;\nLey de Hacienda del Estado de Baja California. Página 65\n.\nActualización Legislativa.\nÚltima reforma P.O. No. 72, Índice, 22-Dic-2023\nFracción Reformada\nII.- Derogada;\nFracción Derogada\nIII.- Derogada:\nFracción Derogada\nIV.- DERECHOS POR SERVICIOS DE CONTROL VEHICULAR:\nA.- LICENCIAS PARA CONDUCIR.\nB.- PLACAS O CALCOMANIAS, para un solo vehículo de su propiedad.\nC.- OTROS SERVICIOS.\nV.- DERECHOS POR SERVICIOS DE LA DIRECCIÓN DEL REGISTRO PUBLICO\nDE LA PROPIEDAD Y DEL COMERCIO; únicamente a los servicios que preste el Registro\nPúblico de la Propiedad.\nVI.- DERECHOS POR LEGALIZACION DE FIRMAS, EXPEDICION DE\nCERTIFICADOS Y CERTIFICACIONES.\nVII.- Impuesto sobre servicios de hospedaje.\nArtículo Adicionado\nArtículo Reformado\nARTICULO 174.- En el caso de las personas indigentes mayores de 60 años, personas viudas en situación de indigencia mayores de 50 años, y de las Personas con discapacidad, que no desempeñen actividades productivas, respecto a las contribuciones estatales señaladas en el artículo 173 de esta Ley, estarán exentas al 100%.\nPara los efectos de las contribuciones de mejoras, se estará a lo dispuesto en el artículo 9 de la Ley de Urbanización del Estado de Baja California.\nArtículo Adicionado\nArtículo Reformado\nARTÍCULO 174 BIS.- En el caso de las actas de nacimiento, estará exento al 100% del cobro de derechos, la expedición de la primera copia certificada del acta de registro de nacimiento.\nArtículo Adicionado\nARTICULO 175.- Las Empresas que con motivo de la realización de un proyecto de inversión, y en términos de los rubros y esquemas previstos en la Ley de Fomento a la\nCompetitividad y Desarrollo Económico para el Estado de Baja California, obtengan la exentas del pago de las contribuciones que a continuación se especifican, conforme a los porcentajes, períodos y lineamientos siguientes:\nI. Impuesto sobre remuneraciones al trabajo personal:\nLey de Hacienda del Estado de Baja California. Página 66\n.\nActualización Legislativa.\nÚltima reforma P.O. No. 72, Índice, 22-Dic-2023\na) De 28 a 29 puntos, en un 100% respecto del impuesto que le corresponda cubrir durante el primer año del estímulo fiscal, por los empleos nuevos que se generen con motivo del proyecto de inversión.\n1. En un 100%, respecto del impuesto que le corresponda cubrir periódicamente, durante el primer año del estímulo fiscal por los empleos nuevos que se generen con motivo del proyecto de inversión, y\n2. En un 50%, respecto del impuesto que le corresponda cubrir periódicamente, durante el segundo año del estímulo fiscal por los empleos nuevos que se generen con motivo del proyecto de inversión.\nc) De 32 a 44 puntos, o más:\nPárrafo del Inciso Reformado\n1. En un 100% respecto del impuesto que le corresponda cubrir durante el primer año del estímulo fiscal por los empleos nuevos que se generen con motivo del proyecto de inversión;\nNumeral Reformado\n2. En un 75% respecto del impuesto que le corresponda cubrir durante el segundo año del estímulo fiscal por los empleos nuevos que se generen con motivo del proyecto de inversión, y\nNumeral Reformado\n3. En un 50% respecto del impuesto que le corresponda cubrir durante el tercer año del estímulo fiscal por los empleos nuevos que se generen con motivo del proyecto de inversión.\nNumeral Reformado\nInciso Reformado\nd) Derogado.\nInciso Derogado\ne) Derogado.\nInciso Derogado\nLos empleos nuevos, se determinarán de acuerdo a los trabajadores que contrate la\nEmpresa derivado del proyecto de inversión, adicionales a los que contaba con anterioridad al citado proyecto. subordinado que corresponde a los empleos nuevos, se considerará el salario promedio manifestado por la Empresa para su proyecto de inversión, sin perjuicio de las facultades de la autoridad fiscal para verificar y comprobar la veracidad de dicha manifestación.\nII. Derogado.\nFracción Derogada\nLey de Hacienda del Estado de Baja California. Página 67\n.\nActualización Legislativa.\nÚltima reforma P.O. No. 72, Índice, 22-Dic-2023\nLos sujetos de exención de pago del impuesto sobre remuneraciones al trabajo personal a que se refiere este artículo, deberán cumplir con las demás obligaciones fiscales relativas al mismo, como es la de presentar las declaraciones periódicas que correspondan en las formas que establezca la Secretaría de Hacienda, así como la demás información que en las mismas se establezcan\nPárrafo Reformado\nCon independencia de los requisitos señalados en la Ley de Fomento a la\nCompetitividad y Desarrollo Económico para el Estado de Baja California y su Reglamento, la empresa solicitante de estímulo fiscal, deberá anexar con su solicitud que presente ante la\nSecretaría de Economía e Innovación, su Constancia de Situación Fiscal actualizada.\nPárrafo Adicionado\nPara que las Empresas puedan hacerse acreedoras de los estímulos fiscales previstos en este artículo, además de las condiciones estipuladas, deberán encontrarse al corriente de sus obligaciones fiscales.\nArtículo Adicionado\nArtículo Reformado\nARTICULO 176.- Para la solicitud y extinción de los estímulos fiscales a que se refiere el articulo anterior, se estará a lo dispuesto en la Ley de Fomento a la competitividad y Desarrollo Económico para el Estado de Baja California y demás disposiciones aplicables.\nLos estímulos fiscales corresponderán a aquellos que la Empresa solicite y que la\nAutoridad resuelva procedentes, e iniciarán a partir de la fecha que dicha Empresa indique en la solicitud a que se refiere el Artículo 14 de la Ley de Fomento a la Competitividad y\nDesarrollo Económico para el Estado de Baja California o en su defecto a partir del día siguiente de la notificación de la resolución de procedencia por la autoridad competente. La fecha que señale la empresa no podrá ser mayor a un año, contado a partir de la presentación de dicha solicitud.\nEn caso de que la fecha de inicio indicada por la empresa solicitante, sea anterior a la notificación de la resolución de procedencia, el estímulo fiscal iniciará a partir del día siguiente a aquel en que se haya realizado dicha notificación.\nArtículo Adicionado\nArtículo Reformado\nARTÍCULO 177.- Las Empresas que contraten personas productivas con discapacidad, personas adultas mayores y/o personas egresadas de albergue, casa hogar o instituciones de asistencia social para niñas, niños y adolescentes, consideradas como tales\nCalifornia, estarán exentas del pago del impuesto sobre remuneraciones al trabajo personal empleados, siempre que la empresa no se encuentre recibiendo una exención sobre este impuesto en los términos del artículo 175 de esta Ley.\nArtículo Adicionado\nArtículo Reformado\nLey de Hacienda del Estado de Baja California. Página 68\n.\nActualización Legislativa.\nÚltima reforma P.O. No. 72, Índice, 22-Dic-2023\nARTICULO 178.- A las empresas que operen plantas para el tratamiento de aguas residuales, las reutilicen y/o dispongan de ellas de conformidad con la normatividad aplicable al cuerpo receptor en donde se descarguen tales aguas, siempre que ello no se realice en el sistema de alcantarillado, se les otorgará una exención de hasta el 30% en el pago mensual de los derechos que por consumo de agua deban cubrir a la Comisión Estatal de Servicios\nPúblicos que corresponda.\nPara determinar la exención se considerará el importe que represente el porcentaje del agua tratada respecto del total del agua suministrada, al cual se le aplicará el por ciento referido en el párrafo anterior.\nPara efectos de esta Ley, se entiende por:\nI. Cuerpo Receptor.- La corriente o depósito natural de agua, presas, cauces, zonas marinas o bienes nacionales donde se descargan aguas residuales, así como los terrenos en donde se infiltran o inyectan dichas aguas.\nII. Aguas Residuales.- Las aguas de composición variada provenientes de las descargas de usos comerciales, de servicios, agrícolas, pecuarios, domésticos y en general cualquier otro uso, así como la mezcla de ellas.\nIII. Aguas Residuales Tratadas.- Son aquellas que mediante procesos industriales o combinados de tipo fisicoquímicos, químicos, biológicos u otros, se han adecuado para hacerlas aptas para su reutilización.\nLas Comisiones Estatales de Servicios Público del Estado, tendrán facultades para verificar, inspeccionar y dictaminar, el cumplimiento de las condiciones establecidas en este artículo, así como determinar la base sobre la cual se aplicará la exención citada.\nLa Secretaría de Hacienda, considerando la opinión de la Comisión Estatal del Agua, podrá emitir reglas de carácter general relativas a los aspectos regulados en este artículo.\nPárrafo Reformado\nLa vigencia de este estímulo fiscal, iniciará a partir de que la autoridad competente, después de seguir el procedimiento respectivo, determine la procedencia de la exención, de acuerdo a lo establecido en el artículo 15 de la Ley de Fomento a la Competitividad y\nDesarrollo Económico para el Estado de Baja California.\nArtículo Adicionado\nArtículo Reformado\nARTICULO 179.- Los recargos y gastos de ejecución originados por la falta de pago del crédito fiscal por infracciones o las disposiciones fiscales, a cargo de jubilados, pensionados e indigentes mayores de 60 años, personas viudas en situación de indigencia mayores de 50 años, personas con discapacidad, personas que tengan a su cargo un familiar con alguna discapacidad, se causará sobre la cantidad que éstos deban de cubrir, según lo estipulado en los artículos 173 y 174 de esta Ley.\nLey de Hacienda del Estado de Baja California. Página 69\n.\nActualización Legislativa.\nÚltima reforma P.O. No. 72, Índice, 22-Dic-2023\nArtículo Adicionado\nArtículo Reformado\nARTICULO 180.- Derogado.\nArtículo Adicionado\nArtículo Reformado\nArtículo Derogado\nARTÍCULO 181.- Derogado.\nArtículo Adicionado\nArtículo Derogado\nPRIMERO.- Quienes a la fecha de publicación del presente Decreto perciban ingresos por concepto de arrendamiento o subarrendamiento de bienes inmuebles, deberá empadronarse en la Recaudación de Rentas del Estado y registrar los contratos vigentes a la fecha, debiendo así mismo, quienes estén percibiendo ingresos en especie derivados de contratos celebrados con anterioridad a esta fecha, manifiestan a la recaudación de Rentas de la ubicación del inmueble, los hechos que motiven sus ingresos detallando lo que señala el Artículo 151-4 incisos b) y c) de la Ley de Hacienda del Estado.\nEl plazo para dar cumplimiento a lo dispuesto en este Artículo no excederá de sesenta días.\nArtículo Transitorio Reformado\nSEGUNDO.- Las personas físicas, jurídicas o unidades económicas que al entrar en vigor el presente Decreto se encuentren comprendidas dentro de los supuestos que establecen el artículo 151-18, están obligadas a empadronarse en la Secretaría de Finanzas por conducto de la oficina recaudadora de la jurisdicción, en un plazo que vence el 28 de\nFebrero de 1975.\nArtículo Transitorio Reformado\nTERCERO.- Las personas físicas, jurídicas o unidades económicas que al entrar en vigor este decreto tengan a su servicio sujetos de los mencionados en la fracción II del\nArtículo 151-13 estarán obligados a inscribirse mediante la presentación de la “Relación\nArtículo Transitorio Adicionado\nCUARTO.- La vigencia del presente Decreto empezará a partir del día siguiente al de\nArtículo Adicionado\nBaja California, a los veintiocho días del mes de Diciembre de mil novecientos setenta y dos.\nLIC. ROMAN CARDENAS GONZALEZ, Ley de Hacienda del Estado de Baja California. Página 70\n.\nActualización Legislativa.\nÚltima reforma P.O. No. 72, Índice, 22-Dic-2023\nDIPUTADO PRESIDENTE.\n(RÚBRICA)\nFERNANDO CANO MEDINA,\nDIPUTADO SECRETARIO.\n(RÚBRICA)\nDe conformidad con lo dispuesto por la Fracción I del Artículo 49 de la Constitución\nMexicali, Capital del Estado de Baja California, a los treinta y un días del mes de\nDiciembre de mil novecientos setenta y dos.\nEL GOBERNADOR CONSTITUCIONAL DEL\nESTADO,\nLIC. MILTON CASTELLANOS EVERARDO.\n(Firmado)\nEL SECRETARIO GENERAL DE GOBIERNO,\nFRANCISCO SANTANA PERALTA.\n(Firmado)\nLey de Hacienda del Estado de Baja California. Página 71\n.\nActualización Legislativa.\nÚltima reforma P.O. No. 72, Índice, 22-Dic-2023\nPRIMERO.- Fue modificado por Decreto No. 22, publicado en el Periódico Oficial No.\n36, de fecha 31 de diciembre de 1974, Sección XI, expedido por la Honorable VIII\nLegislatura, siendo Gobernador Constitucional el C. Lic. Milton Castellanos Everardo, 19711977;\nSEGUNDO.- Fue modificado por Decreto No. 85, publicado en el Periódico Oficial No.\n6, Sección I de fecha 28 de Febrero de 1973, expedido por la Honorable VII Legislatura, siendo Gobernador Constitucional el C. Lic. Milton Castellanos Everardo, 1971-1977; fue modificado por Decreto No. 22, publicado en el Periódico Oficial No. 36, de fecha 31 de diciembre de 1974, Sección XI, expedido por la Honorable VIII Legislatura, siendo\nGobernador Constitucional el C. Lic. Milton Castellanos Everardo, 1971-1977;\nTERCERO.- Fue adicionado por Decreto No. 22, publicado en el Periódico Oficial No.\n36, de fecha 31 de diciembre de 1974, Sección XI, expedido por la Honorable VIII\nLegislatura, siendo Gobernador Constitucional el C. Lic. Milton Castellanos Everardo, 19711977;\nCUARTO.- Fue adicionado por Decreto No. 22, publicado en el Periódico Oficial No.\n36, de fecha 31 de diciembre de 1974, Sección XI, expedido por la Honorable VIII\nLegislatura, siendo Gobernador Constitucional el C. Lic. Milton Castellanos Everardo, 19711977;\nFue derogado por Decreto 139, publicado en el Periódico Oficial No. 36, Sección XI de fecha\n31 de diciembre de 1988, expedido por la Honorable XII Legislatura, siendo Gobernador\nConstitucional el C. Lic. Xicoténcalt Leyva Mortera 1983-enero de 1989;\nCAPITULO I\nARTÍCULO 4-1.- Fue adicionado por Decreto No. 409, publicado en el Periódico\nOficial No. 11, de fecha 22 de febrero de 2013, Tomo CXX, expedido por la Honorable XX\nLegislatura, siendo Gobernador Constitucional el C. Lic. José Guadalupe Osuna Millán, 2007-2013; fue reformado por Decreto No. 56, publicado en el Periódico Oficial No. 58, de fecha 30 de diciembre de 2016, Sección II, Tomo CXXIII, expedido por la H. XXI Legislatura, siendo Gobernador Constitucional el C. Francisco Arturo Vega de Lamadrid 2013-2019; fue reformado por Decreto No. 66, publicado en el Periódico Oficial No. 4, de fecha 19 de enero de 2017, Número Especial, Tomo CXXIV, expedido por la H. XXII Legislatura, siendo\nGobernador Constitucional el C. Francisco Arturo Vega de Lamadrid 2013-2019;\nARTICULO 5.- Fue reformado por Decreto No. 179, publicado en el Periódico Oficial siendo Gobernador Constitucional el C. Lic. Milton Castellanos Everardo, 1971-1977; fue suspendido por Decreto No. 11, publicado en el Periódico Oficial No. 36, Sección XI de fecha\nConstitucional el C. Lic. Roberto de la Madrid Romandía, 1977-1983; fue derogado por\nDecreto 139, publicado en el Periódico Oficial No. 36, Sección XI de fecha 31 de diciembre\nLey de Hacienda del Estado de Baja California. Página 72\n.\nActualización Legislativa.\nÚltima reforma P.O. No. 72, Índice, 22-Dic-2023 de 1988, expedido por la Honorable XII Legislatura, siendo Gobernador Constitucional el C.\nLic. Xicoténcalt Leyva Mortera 1983-enero de 1989;\nARTICULO 6.- Fue reformado por Decreto No. 179, publicado en el Periódico Oficial\nNo. 6, Sección I de fecha 28 de Febrero de 1974, expedido por la Honorable VII Legislatura, siendo Gobernador Constitucional el C. Lic. Milton Castellanos Everardo 1971-1977; fue modificado por Decreto No. 22, publicado en el periódico Oficial No. 36, Sección XI de fecha\n31 de Diciembre de 1974, expedido por la Honorable VIII Legislatura, siendo Gobernador\nConstitucional el C. Lic Milton Castellanos Everardo, 1971-1977; fue derogado por Decreto\n139, publicado en el Periódico Oficial No. 36, Sección XI de fecha 31 de diciembre de 1988, expedido por la Honorable XII Legislatura, siendo Gobernador Constitucional el C. Lic.\nXicoténcalt Leyva Mortera 1983-enero de 1989;\nARTICULO 7.- Fue reformado por Decreto No. 179, publicado en el Periódico Oficial\nNo. 6, Sección I de fecha 28 de Febrero de 1974, expedido por la Honorable VII Legislatura, siendo Gobernador Constitucional el C. Lic. Milton Castellanos Everardo, 1971-1977; fue reformado por Decreto No. 170, publicado en el Periódico Oficial No. 7 de fecha 10 de Marzo de 1974, expedido por la Honorable VII Legislatura, siendo Gobernador Constitucional el C.\nLic. Milton Castellanos Everardo, 1971-1977; fue reformado por Decreto No. 206, publicado en el Periódico Oficial No. 4 de fecha 10 de Febrero de 1977, expedido por la Honorable VIII\nLegislatura, siendo Gobernador Constitucional el C. Lic. Milton Castellanos Everardo 19711977; fue reformado por Decreto No. 95, publicado en el Periódico Oficial No. 36, Sección XI de fecha 31 de diciembre de 1978, expedido por la Honorable IX Legislatura, siendo\nGobernador Constitucional el C. Roberto de la Madrid Romandía, 1977-1983; fue suspendido por Decreto No. 11, publicado en el Periódico Oficial No. 36, Sección XI de fecha\n31 de Diciembre de 1980, expedido por la Honorable X Legislatura, siendo Gobernador\nConstitucional el C. Lic. Roberto de la Madrid Romandía, 1977-1983; fue reformado por\nDecreto No. 76, publicado en el Periódico Oficial No. 34, Sección I de fecha 10 de Diciembre de 1981, expedido por la Honorable X Legislatura, siendo Gobernador Constitucional el C.\nLic. Roberto de la Madrid Romandía, 1977-1983; fue reformado por Fe de Erratas, publicado en el Periódico oficial No. 36, de fecha 31 de Diciembre de 1981; fue reformado por Fe de\nErratas, publicado en el Periódico Oficial No. 2, de fecha 20 de Enero de 1982; fue derogado por Decreto 139, publicado en el Periódico Oficial No. 36, Sección XI de fecha 31 de diciembre de 1988, expedido por la Honorable XII Legislatura, siendo Gobernador\nARTICULO 8.- Fue reformado por Decreto No. 179, publicado en el Periódico Oficial siendo Gobernador Constitucional el C. Lic. Milton Castellanos Everardo, 1971-1977; fue modificado por Decreto No. 22, publicado en el Periódico Oficial No. 36, Sección XI de fecha\nEverardo, 1971-1977; fue modificado por Decreto No. 100, publicado en el Periódico Oficial encargado del despacho del Gobierno el C. Secretario General Francisco Santana Peralta, Ley de Hacienda del Estado de Baja California. Página 73\n.\nActualización Legislativa.\nÚltima reforma P.O. No. 72, Índice, 22-Dic-2023 siendo Gobernador Constitucional el C. Lic. Milton Castellanos Everardo, 1971-1977; fue derogado por Decreto 139, publicado en el Periódico Oficial No. 36, Sección XI de fecha 31 de diciembre de 1988, expedido por la Honorable XII Legislatura, siendo Gobernador\nConstitucional el C. Lic. Xicoténcalt Leyva Mortera 1983-enero de 1989;\nARTICULO 9.- Fue reformado por Decreto No. 179, publicado en el Periódico Oficial\nNo. 6, Sección I de fecha 28 de Febrero 1974, expedido por la Honorable VII Legislatura, siendo Gobernador Constitucional el C. Lic. Milton Castellanos Everardo, 1971-1977; fue modificado por Decreto No. 22, publicado en el Periódico Oficial No. 36, Sección XI de fecha\n31 de Diciembre de 1974, expedido por la Honorable VIII Legislatura, siendo Gobernador\nConstitucional el C. Lic. Milton Castellanos Everardo, 1971-1977; fue reformado por Decreto\nNo. 95, publicado en el Periódico Oficial No. 36, Sección XI de fecha 31 de diciembre de\n1978, expedido por la Honorable IX Legislatura, siendo Gobernador Constitucional el C.\nRoberto de la Madrid Romandía, 1977-1983; fue derogado por Decreto 139, publicado en el\nPeriódico Oficial No. 36, Sección XI de fecha 31 de diciembre de 1988, expedido por la\nHonorable XII Legislatura, siendo Gobernador Constitucional el C. Lic. Xicoténcalt Leyva\nMortera 1983-enero de 1989;\nARTICULO 10.- Fue derogado por Decreto 139, publicado en el Periódico Oficial No.\n36, Sección XI de fecha 31 de diciembre de 1988, expedido por la Honorable XII Legislatura, siendo Gobernador Constitucional el C. Lic. Xicoténcalt Leyva Mortera 1983-enero de 1989;\nARTICULO 11.- Fue reformado por Decreto No. 206, publicado en el Periódico Oficial\nNo. 4 de fecha 10 de Febrero de 1977, expedido por la Honorable VIII Legislatura, siendo\nGobernador Constitucional el C. Lic. Milton Castellanos Everardo, 1971-1977; fue suspendido por Decreto No. 11, publicado en el Periódico Oficial No. 36, Sección XI de fecha\n31 de Diciembre de 1980, expedido por la Honorable X Legislatura, siendo Gobernador\nConstitucional el C. Lic. Roberto de la Madrid Romandía, 1977-1983; fue derogado por\nDecreto 139, publicado en el Periódico Oficial No. 36, Sección XI de fecha 31 de diciembre de 1988, expedido por la Honorable XII Legislatura, siendo Gobernador Constitucional el C.\nLic. Xicoténcalt Leyva Mortera 1983-enero de 1989;\nARTICULO 12.- Fue suspendido por Decreto No. 11, publicado en el Periódico Oficial\nNo. 36, Sección XI de fecha 31 de Diciembre de 1980, expedido por la Honorable X\nLegislatura, siendo Gobernador Constitucional el C. Lic. Roberto de la Madrid Romandía, 1977-1983; fue derogado por Decreto 139, publicado en el Periódico Oficial No. 36, Sección\nARTICULO 13.- Fue reformado por Decreto No. 206, publicado en el Periódico Oficial\nGobernador Constitucional el C. Lic. Milton Castellanos Everardo, 1971-1977; fue reformado por Decreto No. 95, publicado en el Periódico Oficial No. 36, Sección XI de fecha 31 de\nLey de Hacienda del Estado de Baja California. Página 74\n.\nActualización Legislativa.\nÚltima reforma P.O. No. 72, Índice, 22-Dic-2023\nConstitucional el C. Roberto de la Madrid Romandía, 1977-1983; fue suspendido por Decreto\nNo. 11, publicado en el Periódico Oficial No. 36, Sección XI de fecha 31 de Diciembre de\n1980, expedido por la Honorable X Legislatura, siendo Gobernador Constitucional el C. Lic.\nRoberto de la Madrid Romandía, 1977-1983; fue derogado por Decreto 139, publicado en el\nPeriódico Oficial No. 36, Sección XI de fecha 31 de diciembre de 1988, expedido por la\nHonorable XII Legislatura, siendo Gobernador Constitucional el C. Lic. Xicoténcalt Leyva\nMortera 1983-enero de 1989;\nARTICULO 14.- Fue reformado por Decreto No. 179, publicado en el Periódico Oficial\nNo. 6 de fecha 28 de Febrero 1974, expedido por la Honorable VII Legislatura, siendo\nGobernador Constitucional el C. Lic. Milton Castellanos Everardo, 1971-1977; fue derogado por Decreto 139, publicado en el Periódico Oficial No. 36, Sección XI de fecha 31 de diciembre de 1988, expedido por la Honorable XII Legislatura, siendo Gobernador\nConstitucional el C. Lic. Xicoténcalt Leyva Mortera 1983-enero de 1989;\nARTICULO 15.- Fue reformado por Decreto No. 100, publicado en el Periódico Oficial\nNo. 3 de fecha 31 de Enero de 1976, expedido por la honorable VIII Legislatura, estando encargado del Despacho del Gobierno el C. Secretario General Francisco Santana Peralta, siendo Gobernador Constitucional el C. Lic. Milton Castellanos Everardo, 1971-1977; fue reformado por Decreto No. 206. publicado en el Periódico Oficial No. 4 de fecha 10 de\nFebrero de 1977, expedido por la Honorable VIII Legislatura, siendo Gobernador\nConstitucional el C. Lic. Milton Castellanos Everardo, 1971-1977; fue suspendido por\nDecreto No. 11, publicado en el Periódico Oficial No. 36, Sección XI de fecha 31 de\nDiciembre de 1980, expedido por la Honorable X Legislatura, siendo Gobernador\nConstitucional el C. Lic. Roberto de la Madrid Romandía, 1977-1983; fue derogado por\nDecreto 139, publicado en el Periódico Oficial No. 36, Sección XI de fecha 31 de diciembre de 1988, expedido por la Honorable XII Legislatura, siendo Gobernador Constitucional el C.\nLic. Xicoténcalt Leyva Mortera 1983-enero de 1989;\nARTICULO 16.- Fue suspendido por Decreto No. 11, publicado en el Periódico Oficial\nNo. 36, Sección XI de fecha 31 de Diciembre de 1980, expedido por la Honorable X\nLegislatura, siendo Gobernador Constitucional el C. Lic. Roberto de la Madrid Romandía, 1977-1983; fue derogado por Decreto 139, publicado en el Periódico Oficial No. 36, Sección\nARTICULO 17.- Fue derogado por Decreto 139, publicado en el Periódico Oficial No.\nARTICULO 18.- Fue reformado por Decreto No. 206, publicado en el Periódico Oficial\nGobernador Constitucional el C. Lic. Milton Castellanos Everardo, 1971-1977; fue derogado por Decreto 139, publicado en el Periódico Oficial No. 36, Sección XI de fecha 31 de\nLey de Hacienda del Estado de Baja California. Página 75\n.\nActualización Legislativa.\nÚltima reforma P.O. No. 72, Índice, 22-Dic-2023 diciembre de 1988, expedido por la Honorable XII Legislatura, siendo Gobernador\nConstitucional el C. Lic. Xicoténcalt Leyva Mortera 1983-enero de 1989;\nARTICULO 19.- Fue reformado por Decreto No. 206, publicado en el Periódico Oficial\nNo. 4 de fecha 10 de Febrero de 1977, expedido por la Honorable VIII Legislatura, siendo\nGobernador Constitucional el C. Lic. Milton Castellanos Everardo, 1971-1977; fue derogado por Decreto 139, publicado en el Periódico Oficial No. 36, Sección XI de fecha 31 de diciembre de 1988, expedido por la Honorable XII Legislatura, siendo Gobernador\nConstitucional el C. Lic. Xicoténcalt Leyva Mortera 1983-enero de 1989;\nARTICULO 20.- Fue reformado por Decreto No. 206, publicado en el Periódico Oficial\nNo. 4 de fecha 10 de Febrero de 1977, expedido por la Honorable VIII Legislatura, siendo\nGobernador Constitucional el C. Lic. Milton Castellanos Everardo, 1971-1977; fue derogado por Decreto 139, publicado en el Periódico Oficial No. 36, Sección XI de fecha 31 de diciembre de 1988, expedido por la Honorable XII Legislatura, siendo Gobernador\nConstitucional el C. Lic. Xicoténcalt Leyva Mortera 1983-enero de 1989;\nARTICULO 21.- Fue reformado por Decreto No. 206, publicado en el Periódico Oficial\nNo. 4 de fecha 10 de Febrero de 1977, expedido por la Honorable VIII Legislatura, siendo\nGobernador Constitucional el C. Lic. Milton Castellanos Everardo, 1971-1977; fue derogado por Decreto 139, publicado en el Periódico Oficial No. 36, Sección XI de fecha 31 de diciembre de 1988, expedido por la Honorable XII Legislatura, siendo Gobernador\nConstitucional el C. Lic. Xicoténcalt Leyva Mortera 1983-enero de 1989;\nARTICULO 22.- Fue derogado por Decreto 139, publicado en el Periódico Oficial No.\n36, Sección XI de fecha 31 de diciembre de 1988, expedido por la Honorable XII Legislatura, siendo Gobernador Constitucional el C. Lic. Xicoténcatl Leyva Mortera 1983-enero de 1989;\nARTICULO 23.- Fue reformado por Decreto No. 100, publicado en el Periódico Oficial\nNo. 3 de fecha 31 de Enero de 1976, expedido por la Honorable VIII Legislatura, estando\nEncargado del Despacho de Gobierno el C. Francisco Santana Peralta, siendo Gobernador\nConstitucional el C. Lic. Milton Castellanos Everardo, 1971-1977; fue derogado por Decreto\n139, publicado en el Periódico Oficial No. 36, Sección XI de fecha 31 de diciembre de 1988, expedido por la Honorable XII Legislatura, siendo Gobernador Constitucional el C. Lic.\nARTICULO 24.- Fue reformado por Decreto No. 95, publicado en el Periódico Oficial\nLegislatura, siendo Gobernador Constitucional el C. Roberto de la Madrid Romandía, 19771983; fue derogado por Decreto 139, publicado en el Periódico Oficial No. 36, Sección XI de\nARTICULO 25.- Fue reformado por Decreto No. 95, publicado en el Periódico Oficial\nLey de Hacienda del Estado de Baja California. Página 76\n.\nActualización Legislativa.\nÚltima reforma P.O. No. 72, Índice, 22-Dic-2023\nLegislatura, siendo Gobernador Constitucional el C. Roberto de la Madrid Romandía, 19771983; fue derogado por Decreto 139, publicado en el Periódico Oficial No. 36, Sección XI de fecha 31 de diciembre de 1988, expedido por la Honorable XII Legislatura, siendo\nGobernador Constitucional el C. Lic. Xicoténcatl Leyva Mortera 1983-enero de 1989;\nARTICULO 26.- Fue derogado por Decreto 139, publicado en el Periódico Oficial No.\n36, Sección XI de fecha 31 de diciembre de 1988, expedido por la Honorable XII Legislatura, siendo Gobernador Constitucional el C. Lic. Xicoténcatl Leyva Mortera 1983-enero de 1989;\nARTICULO 27.- Fue derogado por Decreto 139, publicado en el Periódico Oficial No.\n36, Sección XI de fecha 31 de diciembre de 1988, expedido por la Honorable XII Legislatura, siendo Gobernador Constitucional el C. Lic. Xicoténcatl Leyva Mortera 1983-enero de 1989;\nFue derogado este Capítulo por Decreto 139, publicado en el Periódico Oficial No. 36,\nSección XI de fecha 31 de diciembre de 1988, expedido por la Honorable XII Legislatura, siendo Gobernador Constitucional el C. Lic. Xicoténcatl Leyva Mortera 1983-enero de 1989;\nCAPITULO II\nIMPUESTO SOBRE TRANSMISION\nDE DOMINIO\nARTICULO 28.- Fue reformado por Decreto No. 22, publicado en el Periódico Oficial\nNo. 36, Sección XI de fecha 31 de Diciembre de 1974, expedido por la Honorable VIII\nLegislatura, siendo Gobernador Constitucional el C. Lic. Milton Castellanos Everardo, 19711977; fue reformado por Decreto No. 95, publicado en el Periódico Oficial No. 36, Sección XI de fecha 31 de diciembre de 1978, expedido por la Honorable IX Legislatura, siendo\nGobernador Constitucional el C. Roberto de la Madrid Romandía, 1977-1983; fue modificado por Decreto No. 167, publicado en el Periódico Oficial No. 4 de fecha 10 de Febrero de 1980, expedido por la Honorable X Legislatura, siendo Gobernador Constitucional el C. Roberto de la Madrid Romandía, 1977-1983; fue reformado por Decreto No. 165, publicado en el\nPeriódico Oficial No. 11 de fecha 20 de Abril de 1983, expedido por la Honorable X\nLegislatura, siendo Gobernador Constitucional el C. Roberto de la Madrid Romandía, 19771983; fue modificado por Decreto NO. 200, publicado en el Periódico Oficial No. 20 de fecha\n20 de Julio de 1983, expedido por la Honorable X Legislatura, siendo Gobernador\nConstitucional el C. Roberto de la Madrid Romandía, 1977-1983; fue derogado por Decreto expedido por la Honorable XII Legislatura, siendo Gobernador Constitucional el C. Lic.\nARTICULO 29.- Fue reformado por Decreto No. 22, publicado en el Periódico Oficial\nLegislatura, siendo Gobernador Constitucional el C. Lic. Milton Castellanos Everardo, 19711974; fue reformado por Decreto No. 95, publicado en el Periódico Oficial No. 36, Sección XI\nLey de Hacienda del Estado de Baja California. Página 77\n.\nActualización Legislativa.\nÚltima reforma P.O. No. 72, Índice, 22-Dic-2023\nGobernador Constitucional el C. Roberto de la Madrid Romandía, 1977-1983; fue reformado por Decreto No. 165, publicado en el Periódico Oficial No. 11 de fecha 20 de Abril de 1983, expedido por la Honorable X Legislatura, siendo Gobernador Constitucional el C. Roberto de la Madrid Romandía, 1977-1983; fue modificado por Decreto NO. 200, publicado en el\nPeriódico Oficial No. 20 de fecha 20 de Julio de 1983, expedido por la Honorable X\nLegislatura, siendo Gobernador Constitucional el C. Roberto de la Madrid Romandía, 19771983; fue derogado por Decreto 139, publicado en el Periódico Oficial No. 36, Sección XI de fecha 31 de diciembre de 1988, expedido por la Honorable XII Legislatura, siendo\nGobernador Constitucional el C. Lic. Xicoténcatl Leyva Mortera 1983-enero de 1989;\nARTICULO 30.- Fue reformado por Decreto No. 179, publicado en el Periódico Oficial\nNo. 6 de fecha 28 de Febrero 1974, expedido por la Honorable VII Legislatura, siendo\nGobernador Constitucional el C. Lic. Milton Castellanos Everardo, 1971-1977; fue reformado por Decreto No. 100, publicado en el Periódico Oficial No. 3 de fecha de 31 de Enero de\n1976, expedido por la Honorable VIII Legislatura, estando Encargado del Despacho de\nGobierno el C. Secretario General Francisco Santana Peralta, siendo Gobernador\nConstitucional el C. Lic. Milton Castellanos Everardo, 1971-1977; fue reformado por Decreto\nNo. 95, publicado en el Periódico Oficial No. 36, Sección XI de fecha 31 de diciembre de\n1978, expedido por la Honorable IX Legislatura, siendo Gobernador Constitucional el C.\nRoberto de la Madrid Romandía, 1977-1983; fue reformado por Decreto No. 165, publicado en el Periódico Oficial NO. 11 de fecha 20 de Abril de 1983, expedido por la Honorable X\nLegislatura, siendo Gobernador Constitucional el C. Roberto de la Madrid Romandía, 19771983; fue derogado por Decreto 139, publicado en el Periódico Oficial No. 36, Sección XI de fecha 31 de diciembre de 1988, expedido por la Honorable XII Legislatura, siendo\nGobernador Constitucional el C. Lic. Xicoténcatl Leyva Mortera 1983-enero de 1989;\nARTICULO 31.- Fue reformado por Decreto No. 165, publicado en el Periódico Oficial\nNo. 11 de fecha 20 de Abril de 1983, expedido por la Honorable X Legislatura, siendo\nGobernador Constitucional el C. Roberto de la Madrid Romandía, 1977-1983; fue derogado por Decreto 139, publicado en el Periódico Oficial No. 36, Sección XI de fecha 31 de diciembre de 1988, expedido por la Honorable XII Legislatura, siendo Gobernador\nConstitucional el C. Lic. Xicoténcatl Leyva Mortera 1983-enero de 1989;\nARTICULO 32.- Fue reformado por Decreto No. 165, publicado en el Periódico Oficial\nGobernador Constitucional el C. Roberto de la Madrid Romandía, 1977-1983; fue derogado por Decreto 139, publicado en el Periódico Oficial No. 36, Sección XI de fecha 31 de\nARTICULO 33.- Fue reformado por Decreto No. 95, publicado en el Periódico Oficial\nLegislatura, siendo Gobernador Constitucional el C. Roberto de la Madrid Romandía, 19771983; fue reformado por Decreto No. 165, publicado en el Periódico Oficial No. 11 de fecha\nLey de Hacienda del Estado de Baja California. Página 78\n.\nActualización Legislativa.\nÚltima reforma P.O. No. 72, Índice, 22-Dic-2023\n20 de Abril de 1983, expedido por la Honorable X Legislatura, siendo Gobernador\nConstitucional el C. Roberto de la Madrid Romandía, 1977-1983; fue derogado por Decreto\n139, publicado en el Periódico Oficial No. 36, Sección XI de fecha 31 de diciembre de 1988, expedido por la Honorable XII Legislatura, siendo Gobernador Constitucional el C. Lic.\nXicoténcatl Leyva Mortera 1983-enero de 1989;\nARTICULO 34.- Fue adicionado por Decreto No. 22, publicado en el Periódico Oficial\nNo. 36, Sección XI de fecha 31 de Diciembre de 1974, expedido por la Honorable VIII\nLegislatura, siendo Gobernador Constitucional el C. Lic. Milton Castellanos Everardo, 19711974; fue reformado por Decreto No. 95, publicado en el Periódico Oficial No. 36, Sección XI de fecha 31 de diciembre de 1978, expedido por la Honorable IX Legislatura, siendo\nGobernador Constitucional el C. Roberto de la Madrid Romandía, 1977-1983; fue reformado por Decreto No. 165, publicado en el Periódico Oficial No. 11 de fecha 20 de Abril de 1983, expedido por la Honorable X Legislatura, siendo Gobernador el C. Roberto de la Madrid\nRomandía, 1977-1983; fue modificado por Decreto NO. 200, publicado en el Periódico Oficial\nNo. 20 de fecha 20 de Julio de 1983, expedido por la Honorable X Legislatura, siendo\nGobernador Constitucional el C. Roberto de la Madrid Romandía, 1977-1983; fue derogado por Decreto 139, publicado en el Periódico Oficial No. 36, Sección XI de fecha 31 de diciembre de 1988, expedido por la Honorable XII Legislatura, siendo Gobernador\nConstitucional el C. Lic. Xicoténcatl Leyva Mortera 1983-enero de 1989;\nARTICULO 34-BIS.- Fue adicionado por Decreto No. 62, publicado en el Periódico\nOficial No. 17 de fecha 20 de Junio de 1975, expedido por la Honorable VIII Legislatura, siendo Gobernador Constitucional el C. Lic. Milton Castellanos Everardo, 1971-1977; fue reformado por Decreto No. 95, publicado en el Periódico Oficial No. 36, Sección XI de fecha\n31 de diciembre de 1978, expedido por la Honorable IX Legislatura, siendo Gobernador\nConstitucional el C. Roberto de la Madrid Romandía, 1977-1983; fue derogado por Decreto\n139, publicado en el Periódico Oficial No. 36, Sección XI de fecha 31 de diciembre de 1988, expedido por la Honorable XII Legislatura, siendo Gobernador Constitucional el C. Lic.\nXicoténcatl Leyva Mortera 1983-enero de 1989;\nARTICULO 35.- Fue reformado por Decreto No. 165, publicado en el Periódico Oficial\nNo. 11 de fecha 20 de Abril de 1983, expedido por la Honorable X Legislatura, siendo\nGobernador el C. Roberto de la Madrid Romandía, 1977-1983; fue modificado por Decreto la Honorable X Legislatura, siendo Gobernador Constitucional el C. Roberto de la Madrid\nRomandía, 1977-1983; fue derogado por Decreto 139, publicado en el Periódico Oficial No.\nARTICULO 36.- Fue reformado por Decreto No. 165, publicado en el Periódico Oficial\nGobernador el C. Roberto de la Madrid Romandía, 1977-1983; fue derogado por Decreto\nLey de Hacienda del Estado de Baja California. Página 79\n.\nActualización Legislativa.\nÚltima reforma P.O. No. 72, Índice, 22-Dic-2023 expedido por la Honorable XII Legislatura, siendo Gobernador Constitucional el C. Lic.\nXicoténcatl Leyva Mortera 1983-enero de 1989;\nARTICULO 37.- Fue reformado por Decreto No. 165, publicado en el Periódico Oficial\nNo. 11 de fecha 20 de Abril de 1983, expedido por la Honorable X Legislatura, siendo\nGobernador el C. Roberto de la Madrid Romandía, 1977-1983; fue derogado por Decreto\n139, publicado en el Periódico Oficial No. 36, Sección XI de fecha 31 de diciembre de 1988, expedido por la Honorable XII Legislatura, siendo Gobernador Constitucional el C. Lic.\nXicoténcatl Leyva Mortera 1983-enero de 1989;\nARTICULO 38.- Fue reformado por Decreto No. 179, publicado en el Periódico Oficial\nNo. 6 de fecha 28 de Febrero 1974, expedido por la Honorable VII Legislatura, siendo\nGobernador Constitucional el C. Lic. Milton Castellanos Everardo, 1971-1977; fue reformado por Decreto No. 165, publicado en el Periódico Oficial No. 11 de fecha 20 de Abril de 1983, expedido por la Honorable X Legislatura, siendo Gobernador el C. Roberto de la Madrid\nRomandía, 1977-1983; fue modificado por Decreto NO. 200, publicado en el Periódico Oficial\nNo. 20 de fecha 20 de Julio de 1983, expedido por la Honorable X Legislatura, siendo\nGobernador Constitucional el C. Roberto de la Madrid Romandía, 1977-1983; fue derogado por Decreto 139, publicado en el Periódico Oficial No. 36, Sección XI de fecha 31 de diciembre de 1988, expedido por la Honorable XII Legislatura, siendo Gobernador\nConstitucional el C. Lic. Xicoténcatl Leyva Mortera 1983-enero de 1989;\nARTICULO 39.- Fue reformado por Decreto No. 206. publicado en el Periódico Oficial\nNo. 4 de fecha 10 de Febrero de 1977, expedido por la Honorable VIII Legislatura, siendo\nGobernador Constitucional el C. Lic. Milton Castellanos Everardo, 1971-1977; fue reformado por Decreto No. 165, publicado en el Periódico Oficial No. 11 de fecha 20 de Abril de 1983, expedido por la Honorable X Legislatura, siendo Gobernador el C. Roberto de la Madrid\nRomandía, 1977-1983; fue derogado por Decreto 139, publicado en el Periódico Oficial No.\n36, Sección XI de fecha 31 de diciembre de 1988, expedido por la Honorable XII Legislatura, siendo Gobernador Constitucional el C. Lic. Xicoténcatl Leyva Mortera 1983-enero de 1989;\nARTICULO 40.- Fue reformado por Decreto No. 22, publicado en el Periódico Oficial\nNo. 36, Sección XI de fecha 31 de Diciembre de 1974, expedido por la Honorable VIII\nLegislatura, siendo Gobernador Constitucional el C. Lic. Milton Castellanos Everardo, 19711974; fue reformado por Decreto No. 165, publicado en el Periódico Oficial No. 11 de fecha\nRoberto de la Madrid Romandía, 1977-1983; fue derogado por Decreto 139, publicado en el\nHonorable XII Legislatura, siendo Gobernador Constitucional el C. Lic. Xicoténcatl Leyva\nARTICULO 41.- Fue reformado por Decreto No. 165, publicado en el Periódico Oficial\nGobernador el C. Roberto de la Madrid Romandía, 1977-1983; fue derogado por Decreto\nLey de Hacienda del Estado de Baja California. Página 80\n.\nActualización Legislativa.\nÚltima reforma P.O. No. 72, Índice, 22-Dic-2023\n139, publicado en el Periódico Oficial No. 36, Sección XI de fecha 31 de diciembre de 1988, expedido por la Honorable XII Legislatura, siendo Gobernador Constitucional el C. Lic.\nXicoténcatl Leyva Mortera 1983-enero de 1989;\nCAPITULO III\nIMPUESTOS SOBRE ACTIVIDADES MERCANTILES E INDUSTRIALES\nARTICULO 42.- Fue reformado por Decreto No. 206, publicado en el Periódico Oficial\nNo. 4 de fecha 10 de Febrero de 1977, expedido por la Honorable VIII Legislatura, siendo\nGobernador Constitucional el C. Lic. Milton Castellanos Everardo, 1971-1977; fue suspendida la vigencia de este artículo en lo que pague el IVA e Impuestos Federales, por\nDecreto No. 164, publicado en el Periódico Oficial No. 36, Sección XI de fecha 31 de\nDiciembre de 1979, expedido por la Honorable IX Legislatura, siendo Gobernador\nConstitucional el C. Roberto de la Madrid Romandía, 1977-1983; fue reformado por Decreto\nNo. 84, publicado en el Periódico Oficial No. 36, Sección XI de fecha 31 de Diciembre de\n1981, expedido por la Honorable X Legislatura, siendo Gobernador Constitucional el C.\nRoberto de la Madrid Romandía, 1977-1983; fue reformado por Decreto No. 129, publicado en el Periódico Oficial No. 14 de fecha 10 de mayo de 1992, expedido por la Honorable XIII\nLegislatura, siendo Gobernador Constitucional el C. L. A. E. Ernesto Ruffo Appel, 1989-1995; fue reformado por Decreto No. 284, publicado en el Periódico Oficial No. 15, de fecha 02 de abril de 2004, Sección II, Tomo CXI, expedido por la Honorable XVII Legislatura, siendo\nGobernador Constitucional el C. Lic. Eugenio Elorduy Walther, 2001-2007;\nARTICULO 44.- Fue reformado por Decreto No. 206, publicado en el Periódico Oficial\nNo. 4 de fecha 10 de Febrero de 1977, expedido por la Honorable VIII Legislatura, siendo\nGobernador Constitucional el C. Lic. Milton Castellanos Everardo, 1971-1977; fue reformado por Decreto No. 139, publicado en el Periódico Oficial No. 36, Sección XI de fecha 31 de\nDiciembre de 1988, expedido por la Honorable XII Legislatura, siendo Gobernador\nConstitucional el C. Lic. Xicoténcatl Leyva Mortera, 1983-Enero de 1989, ARTICULO 50.- Fue reformado por Decreto No. 139, publicado en el Periódico Oficial\nNo. 36, Sección XI de fecha 31 de Diciembre de 1988, expedido por la Honorable XII\nLegislatura, siendo Gobernador Constitucional el C. Lic. Xicoténcatl Leyva Mortera, 1983Enero de 1989;\nARTICULO 53.- Fue reformado por Decreto No. 100, publicado en el Periódico Oficial encargado del Despacho de Gobierno el C. Secretario General Francisco Santana Peralta, siendo Gobernador Constitucional el C. Lic. Milton Castellanos Everardo, 1971-1977;\nARTICULO 54.- Fue reformado por Decreto No. 82, publicado en el Periódico Oficial siendo Gobernador Constitucional el C. Lic. Milton Castellanos Everardo, 1971-1977; fue reformado por Decreto No. 100, publicado en el Periódico Oficial No. 3 de fecha 31 de Enero de 1976, expedido por la Honorable VIII Legislatura, estando encargado del Despacho el C.\nLey de Hacienda del Estado de Baja California. Página 81\n.\nActualización Legislativa.\nÚltima reforma P.O. No. 72, Índice, 22-Dic-2023\nSecretario General de Gobierno, Francisco Santana Peralta, siendo Gobernador\nConstitucional el C. Lic. Milton Castellanos Everardo, 1971-1977;\nARTICULO 55.- Fue reformado por Decreto No. 82, publicado en el Periódico Oficial\nNo. 6, Sección I de fecha 28 de Febrero de 1973, expedido por la Honorable VII Legislatura, siendo Gobernador Constitucional el C. Lic. Milton Castellanos Everardo, 1971-1977;\nARTICULO 56.- Fue reformado por Decreto No. 82, publicado en Periódico Oficial No.\n6, Sección I de fecha 28 de Febrero de 1973, expedido por la Honorable VII Legislatura, siendo Gobernador Constitucional el C. Lic. Milton Castellanos Everardo, 1971-1977; fue adicionado por Decreto No. 113, publicado en el Periódico Oficial No. 18 de fecha 30 de\nJunio de 1973, expedido por la Honorable VII Legislatura, estando encargado del Despacho el C. Secretario General de Gobierno Francisco Santana Peralta y siendo Gobernador\nConstitucional el C. Lic. Milton Castellanos Everardo, 1971-1977; fue reformado por Decreto\nNo. 206, publicado en el Periódico Oficial No. 4, de fecha 10 de Febrero de 1977, expedido por la Honorable VIII Legislatura, siendo Gobernador Constitucional el C. Lic. Milton\nCastellanos Everardo, 1971-1977; fue reformado por Decreto No. 229, publicado en el\nPeriódico Oficial No. 15, de fecha 31 de Mayo de 1977, expedido por la Honorable VIII\nLegislatura, estando encargado del despacho de Gobierno el Secretario General Rafael\nMartínez Retes, siendo Gobernador Constitucional el C. Lic. Milton Castellanos Everardo, 1971-1977;\nARTICULO 61.- Fue reformado por Decreto No. 139, publicado en el Periódico Oficial\nNo. 36, Sección XI de fecha 31 de Diciembre de 1988, expedido por la Honorable XII\nLegislatura, siendo Gobernador Constitucional el C. Lic. Xicoténcatl Leyva Mortera, 1983Enero de 1989;\nARTICULO 64.- Fue reformado por Decreto No. 139, publicado en el Periódico Oficial\nNo. 36, Sección XI de fecha 31 de Diciembre de 1988, expedido por la Honorable XII\nLegislatura, siendo Gobernador Constitucional el C. Lic. Xicoténcatl Leyva Mortera, 1983\nEnero de 1989;\nARTICULO 65.- Fue reformado por Decreto No. 206, publicado en el Periódico Oficial\nNo. 4 de fecha 10 de Febrero de 1977, expedido por la Honorable VIII Legislatura, siendo\nGobernador Constitucional el C. Lic. Milton Castellanos Everardo, 1971-1977; fue derogado por Decreto No. 139, publicado en el Periódico Oficial No. 36, Sección XI de fecha 31 de\nARTICULO 67.- Fue reformado por Decreto No. 170, publicado en el Periódico Oficial\nGobernador Constitucional el C. Lic. Milton Castellanos Everardo, 1971-1977; fue reformado por Decreto No. 139, publicado en el Periódico Oficial No. 36, Sección XI de fecha 31 de\nLey de Hacienda del Estado de Baja California. Página 82\n.\nActualización Legislativa.\nÚltima reforma P.O. No. 72, Índice, 22-Dic-2023\nDecreto No. 133, publicado en el Periódico Oficial No. 57, de fecha 31 de diciembre de 2002,\nSección VIII, Tomo CIX, expedido por la Honorable XVII Legislatura, siendo Gobernador\nConstitucional el C. Lic. Eugenio Elorduy Walther, 2001-2007;\nARTICULO 69.- Fue reformado por Decreto No. 240, publicado en el Periódico Oficial\nNo. 52 de fecha 4 de diciembre de 2000, expedido por la Honorable XVI Legislatura del\nEstado, siendo Gobernador Constitucional el C. Lic. Alejandro González Alcocer, octubre de\n1998-2001; fue reformado por Decreto No. 361, publicado en el Periódico Oficial No. 72, de fecha 22 de diciembre de 2023, Índice, Tomo CXXX, expedido por la H. XXIV Legislatura, siendo Gobernadora Constitucional la C. Marina del Pilar Ávila Olmeda 2021-2027;\nARTICULO 71.- Fue reformado por Decreto No. 133, publicado en el Periódico Oficial\nNo. 13 de fecha 10 de Mayo de 1976, expedido por la Honorable VIII Legislatura, siendo\nGobernador Constitucional el C. Lic. Milton Castellanos Everardo, 1971-1977; fue derogado por Decreto No. 139, publicado en el Periódico Oficial No. 36, Sección XI de fecha 31 de\nDiciembre de 1988, expedido por la Honorable XII Legislatura, siendo Gobernador\nConstitucional el C. Lic. Xicoténcatl Leyva Mortera, 1983 Enero de 1989;\nARTICULO 72.- Fue reformado por Decreto No. 100, publicado en el Periódico Oficial\nNo. 3 de fecha 31 de Enero de 1976, expedido por la Honorable VIII Legislatura, estando encargado del Despacho de Gobierno el C. Secretario General Francisco Santana Peralta, siendo Gobernador Constitucional el C. Lic. Milton Castellanos Everardo, 1971-1977; fue reformado por Decreto No. 206, publicado en el Periódico Oficial No. 4 de fecha 10 de\nFebrero de 1977, expedido por la Honorable VIII Legislatura, siendo Gobernador\nConstitucional el C. Lic. Milton Castellanos Everardo, 1971-1977; Fue reformado por Decreto\nNo. 240, publicado en el Periódico Oficial No. 52 de fecha 4 de Diciembre de 2000, expedido por la Honorable XVI Legislatura del Estado, siendo Gobernador Constitucional el C. Lic.\nAlejandro González Alcocer, Octubre de 1998-2001; fue reformado por Decreto No. 361, publicado en el Periódico Oficial No. 72, de fecha 22 de diciembre de 2023, Índice, Tomo\nCXXX, expedido por la H. XXIV Legislatura, siendo Gobernadora Constitucional la C. Marina del Pilar Ávila Olmeda 2021-2027;\nARTICULO 73.- Fue reformado por Decreto No. 206, publicado en el Periódico Oficial\nGobernador Constitucional el C. Lic. Milton Castellanos Everardo, 1971-1977;\nARTICULO 75.- Fue reformado por Decreto No. 206, publicado en el Periódico Oficial\nGobernador Constitucional el C. Lic. Milton Castellanos Everardo, 1971-1977;\nARTICULO 78.- Fue derogado por Decreto No. 139, publicado en el Periódico Oficial\nLegislatura, siendo Gobernador Constitucional el Lic. Xicoténcatl Leyva Mortera, 1983 Enero de 1989;\nLey de Hacienda del Estado de Baja California. Página 83\n.\nActualización Legislativa.\nÚltima reforma P.O. No. 72, Índice, 22-Dic-2023\nARTICULO 79.- Fue derogado por Decreto No. 139, publicado en el Periódico Oficial\nNo. 36, Sección XI de fecha 31 de Diciembre de 1988, expedido por la Honorable XII\nLegislatura, siendo Gobernador Constitucional el C. Lic. Xicoténcatl Leyva Mortera, 1983enero de 1989;\nARTICULO 80.- Fue derogado por Decreto No. 139, publicado en el Periódico Oficial\nNo. 36, Sección XI de fecha 31 de Diciembre de 1988, expedido por la Honorable XII\nLegislatura, siendo Gobernador Constitucional el C. Lic. Xicoténcatl Leyva Mortera, 1983enero de 1989;\nARTICULO 83.- Fue reformado por Decreto No. 240, publicado en el Periódico Oficial\nNo. 52 de fecha 4 de Diciembre de 2000, expedido por la Honorable XVI Legislatura del\nEstado, siendo Gobernador Constitucional el C. Lic. Alejandro González Alcocer, Octubre de\n1998-2001; fue reformado por Decreto No. 361, publicado en el Periódico Oficial No. 72, de fecha 22 de diciembre de 2023, Índice, Tomo CXXX, expedido por la H. XXIV Legislatura, siendo Gobernadora Constitucional la C. Marina del Pilar Ávila Olmeda 2021-2027;\nARTICULO 86.- Fue reformado por Decreto No. 22, publicado en el Periódico Oficial\nNo. 36, Sección XI de fecha 31 de Diciembre de 1974, expedido por la Honorable VIII\nLegislatura, siendo Gobernador Constitucional el C. Lic. Milton Castellanos Everardo, 19711977;\nARTICULO 87.- Fue reformado por Decreto No. 170, publicado en el Periódico Oficial\nNo. 7 de fecha 10 de Marzo de 1974, expedido por la Honorable VII Legislatura, siendo\nGobernador Constitucional el C. Lic. Milton Castellanos Everardo, 1971-1977;\nARTICULO 88.- Fue derogado por Decreto No. 139, publicado en el Periódico Oficial\nNo. 36, Sección XI de fecha 31 de Diciembre de 1988, expedida por la Honorable XII\nLegislatura, siendo Gobernador Constitucional el C. Lic. Xicoténcatl Leyva Mortera, 1983\nEnero de 1989;\nARTICULO 88-BIS.- Fue adicionado por Decreto No. 108, publicado en `l Periódico\nOficial No. 3, Sección I de fecha 31 de Enero de 1976, expedido por la Honorable VIII\nLegislatura, siendo Gobernador Constitucional el C. Lic. Milton Castellanos Everardo, 19711977; fue derogado por Decreto No. 139, publicado en el Periódico Oficial No. 36, Sección\nARTICULO 89.- Fue reformado por Decreto No. 139, publicado en el Periódico Oficial\nLegislatura, siendo Gobernador Constitucional el C. Lic. Xicoténcatl Leyva Mortera, 1983\nARTICULO 90.- Fue reformado por Decreto No. 22, publicado en el Periódico Oficial\nLey de Hacienda del Estado de Baja California. Página 84\n.\nActualización Legislativa.\nÚltima reforma P.O. No. 72, Índice, 22-Dic-2023\nLegislatura, siendo Gobernador Constitucional el C. Lic. Milton Castellanos Everardo, 19711977; fue reformado por Decreto No. 95, publicado en el Periódico Oficial No. 36, Sección\nXI, de fecha 31 de Diciembre de 1978, expedido por la Honorable IX Legislatura, siendo\nGobernador Constitucional el C. Roberto de la Madrid Romandía, 1977-1983; fue derogado por Decreto No. 139, publicado en el Periódico Oficial No. 36, de fecha 31 de Diciembre de\n1988, expedido por la Honorable XII Legislatura, siendo Gobernador Constitucional el C. Lic.\nXicoténcatl Leyva Mortera, 1983 Enero de 1989;\nARTICULO 91.- Fue derogado por Decreto No. 139, publicado en el Periódico Oficial\nNo 36, Sección XI de fecha 31 de Diciembre de 1988, expedido por la Honorable XII\nLegislatura, siendo Gobernador Constitucional el C. Lic. Xicoténcatl Leyva Mortera, 1983\nEnero de 1989;\nARTICULO 92.- Fue modificado por Decreto No. 165, publicado en el Periódico\nOficial No. 23 de fecha 20 de Agosto de 1976, expedido por la Honorable VIII Legislatura, siendo Gobernador Constitucional el C. Lic. Milton Castellanos Everardo, 1971-1977; fue derogado por Decreto No. 139, publicado en el Periódico Oficial No. 36, Sección XI de fecha\n31 de Diciembre de 1988, expedido por la Honorable XII Legislatura, siendo Gobernador\nConstitucional el C. Lic. Xicoténcatl Leyva Mortera, 1983-Enero de 1989;\nARTICULO 93.- Fue derogado por Decreto No. 139, publicado en el Periódico Oficial\nNo. 36, Sección XI de fecha 31 de Diciembre de 1988, expedido por la Honorable XII\nLegislatura, siendo Gobernador Constitucional el C. Lic. Xicoténcatl Leyva Mortera, 1983\nEnero de 1989;\nARTICULO 94.- Fue derogado por Decreto No. 139, publicado en el Periódico Oficial\nNo. 36, de fecha 31 de Diciembre de 1988, expedido por la Honorable XII Legislatura, siendo\nGobernador Constitucional el C. Lic. Xicoténcatl Leyva Mortera, 1983 Enero de 1989;\nARTICULO 95.- Fue derogado por Decreto No. 139, publicado en el Periódico Oficial\nNo. 36, Sección XI de fecha 31 de Diciembre de 1988, expedido por la Honorable XII\nLegislatura, siendo Gobernador Constitucional el C. Lic. Xicoténcatl Leyva Mortera, 1983\nARTICULO 96.- Fue derogado por Decreto No. 139, publicado en el Periódico Oficial\nLegislatura, siendo Gobernador Constitucional el C. Lic. Xicoténcatl Leyva Mortera, 1983\nCAPITULO IV\nIMPUESTO SOBRE PRODUCCION AGROPECUARIA\nARTICULO 97.- Fue suspendido por Decreto No. 11, publicado en el Periódico Oficial\nLey de Hacienda del Estado de Baja California. Página 85\n.\nActualización Legislativa.\nÚltima reforma P.O. No. 72, Índice, 22-Dic-2023 retroactivamente a partir del día primero de noviembre de 1980, expedido por la Honorable X\nLegislatura, siendo Gobernador Constitucional el C. Roberto de la Madrid Romandía, 19771983;\nARTICULO 98.- Fue suspendido por Decreto No. 11, publicado en el Periódico Oficial\nNo. 36, Sección XI de fecha 31 de diciembre de 1980, cuyos efectos se aplicaron retroactivamente a partir del día primero de noviembre de 1980, expedido por la Honorable X\nLegislatura, siendo Gobernador Constitucional el C. Roberto de la Madrid Romandía, 19771983;\nARTICULO 99.- Fue suspendido por Decreto No. 11, publicado en el Periódico Oficial\nNo. 36, Sección XI de fecha 31 de diciembre de 1980, cuyos efectos se aplicaron retroactivamente a partir del día primero de noviembre de 1980, expedido por la Honorable X\nLegislatura, siendo Gobernador Constitucional el C. Roberto de la Madrid Romandía, 19771983;\nARTICULO 100.- Fue reformado por Decreto No. 170, publicado en el Periódico\nOficial No. 7 de fecha 10 de marzo de 1974, expedido por la Honorable VII Legislatura, siendo Gobernador Constitucional el C. Lic. Milton Castellanos Everardo, 1971-1977; fue suspendido por Decreto No. 11, publicado en el Periódico Oficial No. 36, Sección XI, de fecha 31 de diciembre de 1980, cuyos efectos se aplicaron retroactivamente a partir del día primero de noviembre de 1980, expedido por la Honorable X Legislatura, siendo Gobernador\nConstitucional el C. Roberto de la Madrid Romandía, 1977-1983;\nARTICULO 101.- Fue reformado por Decreto No. 206, publicado en el Periódico\nOficial No. 4, de fecha 10 de febrero de 1977, expedido por la Honorable VIII Legislatura, siendo Gobernador Constitucional el C. Lic. Milton Castellanos Everardo, 1971-1977; fue suspendido por Decreto No. 11 publicado en el Periódico Oficial No. 36, Sección XI, de fecha\n31 de diciembre de 1980, cuyos efectos se aplicaron retroactivamente a partir del día primero de noviembre de 1980, expedido por la Honorable X Legislatura, siendo Gobernador\nConstitucional el C. Roberto de la Madrid Romandía, 1977-1983;\nARTICULO 102.- Fue reformado por Decreto No. 100, publicado en el Periódico\nOficial No. 3 de fecha 31 de enero de 1976, expedido por la Honorable VIII Legislatura, estando encargado del Despacho de Gobierno el C. Secretario General Francisco Santana\nPeralta, siendo Gobernador Constitucional el C. Lic. Milton Castellanos Everardo, 19711977; fue suspendido por Decreto No. 11, publicado en el Periódico Oficial No. 36, Sección\nGobernador Constitucional el C. Roberto de la Madrid Romandía, 1977-1983;\nARTICULO 103.- Fue suspendido por Decreto No. 11, publicado en el Periódico\nLey de Hacienda del Estado de Baja California. Página 86\n.\nActualización Legislativa.\nÚltima reforma P.O. No. 72, Índice, 22-Dic-2023\nLegislatura, siendo Gobernador Constitucional el C. Roberto de la Madrid Romandía, 19771983;\nARTICULO 104.- Fue reformado por Decreto No. 170, publicado en el Periódico\nOficial No. 7 de fecha 10 de marzo de 1974, expedido por la Honorable VII Legislatura, siendo Gobernador Constitucional el C. Lic. Milton Castellanos Everardo, 1971-1977; fue reformado por Decreto No. 100, publicado en el Periódico Oficial No. 3 de fecha 31 de enero de 1976, expedido por la Honorable VIII Legislatura estando encargado del Despacho de\nGobierno el C. Secretario General Francisco Santana Peralta, siendo Gobernador\nConstitucional el C. Lic. Milton Castellanos Everardo, 1971-1977; fue suspendido por\nDecreto No. 11 publicado en el Periódico Oficial No. 36, Sección XI, de fecha 31 de diciembre de 1980, cuyos efectos se aplicaron retroactivamente a partir del día primero de\nNoviembre de 1980, expedido por la Honorable X Legislatura, siendo Gobernador\nConstitucional el C. Roberto de la Madrid Romandía, 1977-1983;\nARTICULO 105.- Fue reformado por Decreto No. 100, publicado en el Periódico\nOficial No. 3 de fecha 31 de Enero de 1976, expedido por la Honorable VIII Legislatura, estando encargado del Despacho de Gobierno el C. Secretario General Francisco Santana\nPeralta, siendo Gobernador Constitucional el C. Lic. Milton Castellanos Everardo, 19711977; fue suspendido por Decreto No. 11, publicado en el Periódico Oficial No. 36, Sección\nXI, de fecha 31 de Diciembre de 1980, cuyos efectos se aplicaron retroactivamente a partir del día primero de Noviembre de 1980, expedido por la Honorable X Legislatura, siendo\nGobernador Constitucional el C. Roberto de la Madrid Romandía, 1977-1983;\nARTICULO 106.- Fue suspendido por Decreto No. 11, publicado en el Periódico\nOficial No. 36, Sección XI, de fecha 31 de Diciembre de 1980, cuyos efectos se aplicaron retroactivamente a partir del día primero de Noviembre de 1980, expedido por la Honorable\nX Legislatura, siendo Gobernador Constitucional el C. Roberto de la Madrid Romandía, 1977-1983;\nCAPITULO V\nIMPUESTO SOBRE VENTA DE PRODUCTOS AGROPECUARIOS\nARTICULO 107.- Fue suspendido por Decreto No. 11, publicado en el Periódico\nX Legislatura, siendo Gobernador Constitucional el C. Roberto de la Madrid Romandía, 1977-1983;\nARTICULO 108.- Fue suspendido por Decreto No. 11, publicado en el Periódico\nLegislatura, siendo Gobernador Constitucional el C. Roberto de la Madrid Romandía, 19771983, Ley de Hacienda del Estado de Baja California. Página 87\n.\nActualización Legislativa.\nÚltima reforma P.O. No. 72, Índice, 22-Dic-2023\nARTICULO 109.- Fue suspendido por Decreto No. 11 publicado en el Periódico\nOficial No. 36, Sección XI, de fecha 31 de Diciembre de 1980, cuyos efectos se aplicaron retroactivamente a partir del día primero de noviembre de 1980, expedido por la Honorable X\nLegislatura, siendo Gobernador Constitucional el C. Roberto de la Madrid Romandía, 19771983;\nARTICULO 110.- Fue reformado por Decreto No. 206, publicado en el Periódico\nOficial No. 4 de fecha 10 de Febrero de 1977, expedido por la Honorable VIII Legislatura, siendo Gobernador Constitucional el C. Lic. Milton Castellanos Everardo, 1971-1977; fue suspendido por Decreto No. 11, publicado en el Periódico Oficial No. 36, Sección XI de fecha\n31 de Diciembre de 1980, cuyos efectos se aplicaron retroactivamente a partir del día primero de noviembre de 1980, expedido por la Honorable X Legislatura, siendo Gobernador\nConstitucional el C. Roberto de la Madrid Romandía, 1977-1983;\nARTICULO 111.- Fue reformado por Decreto No. 206, publicado en el Periódico\nOficial No. 4 de fecha 10 de Febrero de 1977, expedido por la Honorable VIII Legislatura, siendo Gobernador Constitucional el C. Lic. Milton Castellanos Everardo, 1971-1977; fue suspendido por Decreto No. 11, publicado en el Periódico Oficial No. 36, Sección XI, de fecha 31 de Diciembre de 1980, cuyos efectos se aplicaron retroactivamente a partir del día primero de noviembre de 1980, expedido por la Honorable X Legislatura, siendo Gobernador\nConstitucional el C. Roberto de la Madrid Romandía, 1977-1983;\nARTICULO 112.- Fue reformado por Decreto No. 100, publicado en el Periódico\nOficial No. 3 de fecha 31 de Enero de 1976, expedido por la Honorable VII Legislatura, estando encargado del Despacho de Gobierno el C. Secretario General Francisco Santana\nPeralta, siendo Gobernador Constitucional el C. Lic. Milton Castellanos Everardo, 19711977; fue suspendido por Decreto No. 11, publicado en el Periódico Oficial No. 36, Sección\nXI, de fecha 31 de Diciembre de 1980, cuyos efectos se aplicaron retroactivamente a partir del día primero de noviembre de 1980, expedido por la Honorable X Legislatura, siendo\nGobernador Constitucional el C. Roberto de la Madrid Romandía, 1977-1983;\nARTICULO 113.- Fue suspendido por Decreto No. 11, publicado en el Periódico\nOficial No. 36, Sección XI, de fecha 31 de Diciembre de 1980, cuyos efectos se aplicaron retroactivamente a partir del día primero de noviembre de 1980, expedido por la Honorable X\nLegislatura, siendo Gobernador Constitucional el C. Roberto de la Madrid Romandía 19771983;\nARTICULO 114.- Fue reformado por Decreto No. 100, publicado en el Periódico estando encargado del Despacho de Gobierno el C. Secretario General Francisco Santana\nPeralta, siendo Gobernador Constitucional el C. Lic. Milton Castellanos Everardo, 19711977; fue reformado por Decreto No. 206, publicado en el Periódico Oficial No. 4 de fecha 10\nConstitucional el C. Lic. Milton Castellanos Everardo, 1971-1977; fue suspendido por\nLey de Hacienda del Estado de Baja California. Página 88\n.\nActualización Legislativa.\nÚltima reforma P.O. No. 72, Índice, 22-Dic-2023\nDecreto No. 11, publicado en el Periódico Oficial No. 36, Sección XI, de fecha 31 de\nDiciembre de 1980, cuyos efectos se aplicaron retroactivamente a partir del día primero de\nNoviembre de 1980, expedido por la Honorable X Legislatura, siendo Gobernador\nConstitucional el C. Roberto de la Madrid Romandía, 1977-1983;\nARTICULO 114-1.- Fue adicionado por Decreto No. 22, publicado en el Periódico\nOficial No. 36, Sección XI de fecha 31 de Diciembre de 1974, expedido por la Honorable VIII\nLegislatura, siendo Gobernador Constitucional el C. Lic. Milton Castellanos Everardo, 19711977; fue suspendido por Decreto No. 11, publicado en el Periódico Oficial No. 36, Sección\nXI, de fecha 31 de Diciembre de 1980, cuyos efectos se aplicaron retroactivamente a partir del día primero de noviembre de 1980, expedido por la Honorable X Legislatura, siendo\nGobernador Constitucional el C. Roberto de la Madrid Romandía, 1977-1983;\nCAPITULO VI\nIMPUESTO SOBRE DESPEPITE DE ALGODON\nARTICULO 116.- Fue derogado por Decreto No. 22, publicado en el Periódico Oficial\nNo. 36, Sección XI de fecha 31 de Diciembre de 1974, expedido por la Honorable VIII\nLegislatura, siendo Gobernador Constitucional el C. Lic. Milton Castellanos Everardo 19711977;\nARTICULO 119.- Fue reformado por Decreto No. 170, publicado en el Periódico\nOficial No. 7 de fecha 10 de Marzo de 1974, expedido por la Honorable VII Legislatura, siendo Gobernador Constitucional el C. Lic. Milton Castellanos Everardo, 1971-1977; fue reformado por Decreto No. 100, publicado en el Periódico Oficial No. 3 de fecha 31 de Enero de 1976, expedido por la Honorable VII Legislatura, estando encargado del Despacho de\nGobierno el C. Secretario General Francisco Santana Peralta, siendo Gobernador\nConstitucional el C. Lic. Milton Castellanos Everardo, 1971-1977; Fue reformado por Decreto\nNo. 240, publicado en el Periódico Oficial No. 52 de fecha 4 de Diciembre de 2000, expedido por la Honorable XVI Legislatura del Estado, siendo Gobernador Constitucional el\nC. Lic. Alejandro González Alcocer, Octubre de 1998-2001; fue reformado por Decreto No.\n361, publicado en el Periódico Oficial No. 72, de fecha 22 de diciembre de 2023, Índice, Tomo CXXX, expedido por la H. XXIV Legislatura, siendo Gobernadora Constitucional la C.\nMarina del Pilar Ávila Olmeda 2021-2027;\nARTICULO 120.- Fue reformado por Decreto No. 22, publicado en el Periódico Oficial\nLegislatura, siendo Gobernador Constitucional el C. Lic. Milton Castellanos Everardo, 19711977; fue reformado por Decreto No. 100, publicado en el Periódico Oficial No. 3 de fecha 31\nDespacho de Gobierno el C. Secretario General Francisco Santana Peralta, siendo\nGobernador Constitucional el C. Lic. Milton Castellanos Everardo, 1971-1977;\nARTICULO 120-1.- Fue adicionado por Decreto No. 100, publicado en el Periódico\nLey de Hacienda del Estado de Baja California. Página 89\n.\nActualización Legislativa.\nÚltima reforma P.O. No. 72, Índice, 22-Dic-2023 estando encargado del Despacho de Gobierno el C. Secretario General Francisco Santana\nPeralta, siendo Gobernador Constitucional el C. Lic. Milton Castellanos Everardo, 19711977;\nARTICULO 121.- Fue reformado por Decreto No. 100, publicado en el Periódico\nOficial No. 3 de fecha 31 de Enero de 1976, expedido por la Honorable VIII Legislatura, estando encargado del Despacho de Gobierno el C. Secretario General Francisco Santana\nPeralta, siendo Gobernador Constitucional el C. Lic. Milton Castellanos Everardo 1971-1977; fue reformado por Decreto No. 95, publicado en el Periódico Oficial No. 36, Sección XI, de fecha 31 de Diciembre de 1978, expedido por la Honorable IX Legislatura, siendo\nGobernador Constitucional el C. Roberto de la Madrid Romandía, 1977-1983; fue suspendido por Decreto No. 11, publicado en el Periódico Oficial No. 36, Sección XI de fecha\n31 de Diciembre de 1980, cuyos efectos se aplicaron retroactivamente a partir del día primero de noviembre de 1980, expedido por la Honorable X Legislatura, siendo Gobernador\nConstitucional el C. Roberto de la Madrid Romandía, 1977-1983;\nARTICULO 122.- Fue suspendido por Decreto No. 11, publicado en el Periódico\nOficial No. 36, Sección XI, de fecha 31 de Diciembre de 1980, cuyos efectos se aplicaron retroactivamente a partir del día primero de noviembre de 1980, expedido por la Honorable X\nLegislatura, siendo Gobernador Constitucional el C. Roberto de la Madrid Romandía, 19771983;\nARTICULO 123.- Fue suspendido por Decreto No. 11, publicado en el Periódico\nOficial No. 36, Sección XI de fecha 31 de Diciembre de 1980, cuyos efectos se aplicaron retroactivamente a partir del día primero de noviembre de 1980, expedido por la Honorable X\nLegislatura, siendo Gobernador Constitucional el C. Roberto de la Madrid Romandía, 19771983;\nARTICULO 124.- Fue reformado por Decreto No. 100, publicado en el Periódico\nOficial No. 3 de fecha 31 de Enero de 1976, expedido por la Honorable VIII Legislatura, estando encargado del Despacho de Gobierno el C. Secretario General Francisco Santana\nPeralta, siendo Gobernador Constitucional el C. Lic. Milton Castellanos Everardo, 19711977; fue suspendido por Decreto No. 11, publicado en el Periódico Oficial No. 36, Sección\nXI de fecha 31 de Diciembre de 1980, cuyos efectos se aplicaron retroactivamente a partir\nGobernador Constitucional el C. Roberto de la Madrid Romandía, 1977-1983;\nARTICULO 125.- Fue reformado por Decreto No. 22, publicado en el Periódico Oficial\nLegislatura, siendo Gobernador Constitucional el C. Lic. Milton Castellanos Everardo, 19711977; fue reformado por Decreto No. 100 publicado en el Periódico Oficial No. 3 de fecha 31\nDespacho de Gobierno el C. Secretario General Francisco Santana Peralta, siendo\nGobernador Constitucional el C. Milton Castellanos Everardo, 1971-1977; fue suspendido\nLey de Hacienda del Estado de Baja California. Página 90\n.\nActualización Legislativa.\nÚltima reforma P.O. No. 72, Índice, 22-Dic-2023 por Decreto No. 11 publicado en el Periódico Oficial No. 36, Sección XI de fecha 31 de\nDiciembre de 1980, cuyos efectos se aplicaron retroactivamente a partir del día primero de noviembre de 1980, expedido por la Honorable X Legislatura, siendo Gobernador\nConstitucional el C. Roberto de la Madrid Romandía, 1977-1983, ARTICULO 126.- Fue suspendido por Decreto No. 11 publicado en el Periódico\nOficial No. 36, Sección XI de fecha 31 de Diciembre de 1980, cuyos efectos se aplicaron retroactivamente a partir del día primero de noviembre de 1980, expedido por la Honorable X\nLegislatura, siendo Gobernador Constitucional el C. Roberto de la Madrid Romandía, 19771983, Fue reformada la denominación del Capítulo VIII por Decreto No. 63, publicado en el\nPeriódico Oficial No. 62, Tomo CIII, de fecha 31 de diciembre de 1996, expedido por la\nHonorable XV Legislatura, siendo Gobernador Constitucional el C. Lic. Héctor Terán Terán, 1995-1998;\nCAPITULO VIII\nIMPUESTO SOBRE SERVICIOS DE HOSPEDAJE\nARTICULO 127.- Fue reformado por Decreto No. 63, publicado en el Periódico Oficial\nNo. 62, Tomo CIII, de fecha 31 de diciembre de 1996, expedido por la Honorable XV\nLegislatura, siendo Gobernador Constitucional el C. Lic. Héctor Terán Terán, 1995-1998; fue reformado por Decreto No. 180, publicado en el Periódico Oficial No. 04, de fecha 19 de enero de 2018, Tomo XXV, Sección IV, expedido por la Honorable XXII Legislatura del\nEstado, siendo Gobernador Constitucional el C. Francisco Arturo Vega de Lamadrid, 20132019;\nARTICULO 128.- Fue reformado por Decreto No. 63, publicado en el Periódico Oficial\nNo. 62, Tomo CIII, de fecha 31 de diciembre de 1996, expedido por la Honorable XV\nLegislatura, siendo Gobernador Constitucional el C. Lic. Héctor Terán Terán, 1995-1998;\nARTICULO 129.- Fue reformado por Decreto No. 63, publicado en el Periódico Oficial\nNo. 62, Tomo CIII, de fecha 31 de diciembre de 1996, expedido por la Honorable XV\nLegislatura, siendo Gobernador Constitucional el C. Lic. Héctor Terán Terán, 1995-1998;\nARTICULO 130.- Fue reformado por Decreto No. 63, publicado en el Periódico Oficial\nLegislatura, siendo Gobernador Constitucional el C. Lic. Héctor Terán Téran, 1995-1998;\nFue reformado por Decreto No. 240, publicado en el Periódico Oficial No. 52 de fecha 4 de reformado por Decreto No. 180, publicado en el Periódico Oficial No. 04, de fecha 19 de\nEstado, siendo Gobernador Constitucional el C. Francisco Arturo Vega de Lamadrid, 20132019; fue reformado por Decreto No. 84, publicado en el Periódico Oficial No. 17, de fecha\nLey de Hacienda del Estado de Baja California. Página 91\n.\nActualización Legislativa.\nÚltima reforma P.O. No. 72, Índice, 22-Dic-2023\n04 de marzo de 2022, Tomo CXXIX, Sección I, expedido por la H. XXIV Legislatura, siendo\nGobernadora Constitucional la C. Marina del Pilar Ávila Olmeda 2021-2027;\nARTICULO 131.- Fue modificado por Decreto No. 215, publicado en el Periódico\nOficial No. 24 de fecha 31 de Agosto de 1974, expedido por la Honorable VII Legislatura, estando encargado del Despacho el C. Secretario General de Gobierno, Francisco Santana\nPeralta y siendo Gobernador Constitucional el C. Lic. Milton Castellanos Everardo, 19711977; fue reformado por Decreto No. 63, publicado en el Periódico Oficial No. 62, Tomo CIII, de fecha 31 de diciembre de 1996, expedido por la Honorable XV Legislatura, siendo\nGobernador Constitucional el C. Lic. Héctor Terán Terán, 1995-1998; fue reformado por\nDecreto No. 240, publicado en el Periódico Oficial No. 52 de fecha 4 de Diciembre de 2000, expedido por la Honorable XVI Legislatura del Estado, siendo Gobernador Constitucional el\nC. Lic. Alejandro González Alcocer, Octubre de 1998-2001; fue reformado por Decreto No.\n133, publicado en el Periódico Oficial No. 57, de fecha 31 de diciembre de 2002, Sección\nVIII, Tomo CIX, expedido por la Honorable XVII Legislatura, siendo Gobernador\nConstitucional el C. Lic. Eugenio Elorduy Walther, 2002-2007; fue reformado por Decreto No.\n297, publicado en el Periódico Oficial No. 45, de fecha 05 de octubre de 2012, Tomo CXIX,\nSección II, expedido por la Honorable XX Legislatura, siendo Gobernador Constitucional el\nC. Lic. José Guadalupe Osuna Millán, 2007-2013; fue reformado por Decreto No. 462, publicado en el Periódico Oficial No. 26, de fecha 07 de junio de 2013, Tomo CXX, Sección I, expedido por la Honorable XX Legislatura, siendo Gobernador Constitucional el C. Lic. José\nGuadalupe Osuna Millán, 2007-2013; fue reformado por Decreto No. 180, publicado en el\nPeriódico Oficial No. 04, de fecha 19 de enero de 2018, Tomo XXV, Sección IV, expedido por la Honorable XXII Legislatura del Estado, siendo Gobernador Constitucional el C.\nFrancisco Arturo Vega de Lamadrid, 2013-2019; fue reformado por Decreto No. 361, publicado en el Periódico Oficial No. 72, de fecha 22 de diciembre de 2023, Índice, Tomo\nCXXX, expedido por la H. XXIV Legislatura, siendo Gobernadora Constitucional la C. Marina del Pilar Ávila Olmeda 2021-2027;\nARTICULO 132.- Fue reformado por Decreto No. 63, publicado en el Periódico Oficial\nNo. 62, Tomo CIII, de fecha 31 de diciembre de 1996, expedido por la Honorable XV\nLegislatura, siendo Gobernador Constitucional el C. Lic. Héctor Terán Terán, 1995-1998; fue reformado por Decreto No. 297, publicado en el Periódico Oficial No. 45, de fecha 05 de octubre de 2012, Tomo CXIX, Sección II, expedido por la Honorable XX Legislatura, siendo\nGobernador Constitucional el C. Lic. José Guadalupe Osuna Millán, 2007-2013; fue reformado por Decreto No. 462, publicado en el Periódico Oficial No. 26, de fecha 07 de\nGobernador Constitucional el C. Lic. José Guadalupe Osuna Millán, 2007-2013; fue reformado por Decreto No. 180, publicado en el Periódico Oficial No. 04, de fecha 19 de\nEstado, siendo Gobernador Constitucional el C. Francisco Arturo Vega de Lamadrid, 20132019; fue reformado por Decreto No. 361, publicado en el Periódico Oficial No. 72, de fecha\nGobernadora Constitucional la C. Marina del Pilar Ávila Olmeda 2021-2027;\nLey de Hacienda del Estado de Baja California. Página 92\n.\nActualización Legislativa.\nÚltima reforma P.O. No. 72, Índice, 22-Dic-2023\nARTICULO 132 BIS.- Fue adicionado por Decreto No. 63, publicado en el Periódico\nOficial No. 62, Tomo CIII, expedido por la Honorable XV Legislatura, siendo Gobernador\nConstitucional el C. Lic. Héctor Terán Terán, 1995-1998;\nFue reformado por Decreto No. 39, publicado en el Periódico Oficial No. 67, de fecha 31 de diciembre de 2019, Tomo CXXVI, Sección VIII, expedido por la Honorable XXIII Legislatura del Estado, siendo Gobernador Constitucional el C. Jaime Bonilla Valdez, 2019-2021; fue reformado por Decreto No. 62, publicado en el Periódico Oficial No. 22, de fecha 30 de abril de 2020, Tomo CXXVII, NÚMERO ESPECIAL, expedido por la Honorable XXIII Legislatura del Estado, siendo Gobernador Constitucional el C. Jaime Bonilla Valdez, 2019-2021;\nCAPÍTULO IX\nIMPUESTO AMBIENTAL POR LA EMISIÓN DE GASES A LA ATMÓSFERA\nCAPITULO IX\nIMPUESTO SOBRE VENTA DE PRIMERA MANO DE GASOLINA\nY DEMAS DERIVADOS DEL PETROLEO POR AFECTACIÓN AL MEDIO AMBIENTE\nCAPITULO IX\nIMPUESTO SOBRE VENTA DE PRIMERA MANO DE GASOLINA Y DEMAS\nDERIVADOS DEL PETROLEO\nARTICULO 133.- Fue derogado por Decreto No. 100, publicado en el Periódico\nOficial No. 3 de fecha 31 de Enero de 1976, expedido por la Honorable VIII Legislatura, estando encargado del Despacho de Gobierno el C. Secretario General Francisco Santana\nPeralta, siendo Gobernador Constitucional el C. Lic. Milton Castellanos Everardo, 19711977; fue reformado por Decreto No. 39, publicado en el Periódico Oficial No. 67, de fecha\n31 de diciembre de 2019, Tomo CXXVI, Sección VIII, expedido por la Honorable XXIII\nLegislatura del Estado, siendo Gobernador Constitucional el C. Jaime Bonilla Valdez, 20192021; fue reformado por Decreto No. 62, publicado en el Periódico Oficial No. 22, de fecha\n30 de abril de 2020, Tomo CXXVII, NÚMERO ESPECIAL, expedido por la Honorable XXIII\nLegislatura del Estado, siendo Gobernador Constitucional el C. Jaime Bonilla Valdez, 20192021; de conformidad con lo estipulado en su Resolutivo Tercero de la Sentencia a\nControversia Constitucional 119/2020, notificada a este Congreso del Estado de Baja\nCalifornia en fecha 15 de marzo de 2024, mediante la cual se declara la invalidez de este artículo;\nARTICULO 134.- Fue derogado por Decreto No. 100, publicado en el Periódico Oficial encargado del Despacho de Gobierno el C. Secretario General Francisco Santana Peralta, siendo Gobernador Constitucional el C. Lic. Milton Castellanos Everardo, 1971-1977; fue reformado por Decreto No. 39, publicado en el Periódico Oficial No. 67, de fecha 31 de del Estado, siendo Gobernador Constitucional el C. Jaime Bonilla Valdez, 2019-2021; fue reformado por Decreto No. 62, publicado en el Periódico Oficial No. 22, de fecha 30 de abril de 2020, Tomo CXXVII, NÚMERO ESPECIAL, expedido por la Honorable XXIII Legislatura\nLey de Hacienda del Estado de Baja California. Página 93\n.\nActualización Legislativa.\nÚltima reforma P.O. No. 72, Índice, 22-Dic-2023 del Estado, siendo Gobernador Constitucional el C. Jaime Bonilla Valdez, 2019-2021; de conformidad con lo estipulado en su Resolutivo Tercero de la Sentencia a Controversia\nConstitucional 119/2020, notificada a este Congreso del Estado de Baja California en fecha\n15 de marzo de 2024, mediante la cual se declara la invalidez de este artículo;\nARTICULO 135.- Fue derogado por Decreto No. 100, publicado en el Periódico Oficial\nNo. 3 de fecha 31 de Enero de 1976, expedido por la Honorable VIII Legislatura, estando encargado del Despacho de Gobierno el C. Secretario General Francisco Santana Peralta, siendo Gobernador Constitucional el C. Lic. Milton Castellanos Everardo, 1971-1977; fue reformado por Decreto No. 39, publicado en el Periódico Oficial No. 67, de fecha 31 de diciembre de 2019, Tomo CXXVI, Sección VIII, expedido por la Honorable XXIII Legislatura del Estado, siendo Gobernador Constitucional el C. Jaime Bonilla Valdez, 2019-2021; fue reformado por Decreto No. 62, publicado en el Periódico Oficial No. 22, de fecha 30 de abril de 2020, Tomo CXXVII, NÚMERO ESPECIAL, expedido por la Honorable XXIII Legislatura del Estado, siendo Gobernador Constitucional el C. Jaime Bonilla Valdez, 2019-2021; de conformidad con lo estipulado en su Resolutivo Tercero de la Sentencia a Controversia\nConstitucional 119/2020, notificada a este Congreso del Estado de Baja California en fecha\n15 de marzo de 2024, mediante la cual se declara la invalidez de este artículo;\nARTICULO 136.- Fue derogado por Decreto No. 100, publicado en el Periódico Oficial\nNo. 3 de fecha 31 de Enero de 1976, expedido por la Honorable VIII Legislatura, estando encargado del Despacho de Gobierno el C. Secretario General Francisco Santana Peralta, siendo Gobernador Constitucional el C. Lic. Milton Castellanos Everardo, 1971-1977; fue reformado por Decreto No. 39, publicado en el Periódico Oficial No. 67, de fecha 31 de diciembre de 2019, Tomo CXXVI, Sección VIII, expedido por la Honorable XXIII Legislatura del Estado, siendo Gobernador Constitucional el C. Jaime Bonilla Valdez, 2019-2021; fue reformado por Decreto No. 62, publicado en el Periódico Oficial No. 22, de fecha 30 de abril de 2020, Tomo CXXVII, NÚMERO ESPECIAL, expedido por la Honorable XXIII Legislatura del Estado, siendo Gobernador Constitucional el C. Jaime Bonilla Valdez, 2019-2021; de conformidad con lo estipulado en su Resolutivo Tercero de la Sentencia a Controversia\nConstitucional 119/2020, notificada a este Congreso del Estado de Baja California en fecha\n15 de marzo de 2024, mediante la cual se declara la invalidez de este artículo;\nARTICULO 136-1.- Fue adicionado por Decreto No. 62, publicado en el Periódico por la Honorable XXIII Legislatura del Estado, siendo Gobernador Constitucional el C. Jaime\nBonilla Valdez, 2019-2021; de conformidad con lo estipulado en su Resolutivo Tercero de la\nSentencia a Controversia Constitucional 119/2020, notificada a este Congreso del Estado de este artículo;\nARTICULO 136-2.- Fue adicionado por Decreto No. 62, publicado en el Periódico por la Honorable XXIII Legislatura del Estado, siendo Gobernador Constitucional el C. Jaime\nLey de Hacienda del Estado de Baja California. Página 94\n.\nActualización Legislativa.\nÚltima reforma P.O. No. 72, Índice, 22-Dic-2023\nBonilla Valdez, 2019-2021; de conformidad con lo estipulado en su Resolutivo Tercero de la\nSentencia a Controversia Constitucional 119/2020, notificada a este Congreso del Estado de\nBaja California en fecha 15 de marzo de 2024, mediante la cual se declara la invalidez de este artículo;\nARTICULO 136-3.- Fue adicionado por Decreto No. 62, publicado en el Periódico\nOficial No. 22, de fecha 30 de abril de 2020, Tomo CXXVII, NÚMERO ESPECIAL, expedido por la Honorable XXIII Legislatura del Estado, siendo Gobernador Constitucional el C. Jaime\nBonilla Valdez, 2019-2021; de conformidad con lo estipulado en su Resolutivo Tercero de la\nSentencia a Controversia Constitucional 119/2020, notificada a este Congreso del Estado de\nBaja California en fecha 15 de marzo de 2024, mediante la cual se declara la invalidez de este artículo;\nARTICULO 136-4.- Fue adicionado por Decreto No. 62, publicado en el Periódico\nOficial No. 22, de fecha 30 de abril de 2020, Tomo CXXVII, NÚMERO ESPECIAL, expedido por la Honorable XXIII Legislatura del Estado, siendo Gobernador Constitucional el C. Jaime\nBonilla Valdez, 2019-2021; de conformidad con lo estipulado en su Resolutivo Tercero de la\nSentencia a Controversia Constitucional 119/2020, notificada a este Congreso del Estado de\nBaja California en fecha 15 de marzo de 2024, mediante la cual se declara la invalidez de este artículo;\nARTICULO 136-5.- Fue adicionado por Decreto No. 62, publicado en el Periódico\nOficial No. 22, de fecha 30 de abril de 2020, Tomo CXXVII, NÚMERO ESPECIAL, expedido por la Honorable XXIII Legislatura del Estado, siendo Gobernador Constitucional el C. Jaime\nBonilla Valdez, 2019-2021; de conformidad con lo estipulado en su Resolutivo Tercero de la\nSentencia a Controversia Constitucional 119/2020, notificada a este Congreso del Estado de\nBaja California en fecha 15 de marzo de 2024, mediante la cual se declara la invalidez de este artículo;\nARTICULO 136-6.- Fue adicionado por Decreto No. 62, publicado en el Periódico\nOficial No. 22, de fecha 30 de abril de 2020, Tomo CXXVII, NÚMERO ESPECIAL, expedido por la Honorable XXIII Legislatura del Estado, siendo Gobernador Constitucional el C. Jaime\nBonilla Valdez, 2019-2021; fue derogado por Decreto No. 361, publicado en el Periódico\nOficial No. 72, de fecha 22 de diciembre de 2023, Índice, Tomo CXXX, expedido por la H.\nXXIV Legislatura, siendo Gobernadora Constitucional la C. Marina del Pilar Ávila Olmeda\n2021-2027;\nARTICULO 136-7.- Fue adicionado por Decreto No. 62, publicado en el Periódico por la Honorable XXIII Legislatura del Estado, siendo Gobernador Constitucional el C. Jaime\nBonilla Valdez, 2019-2021; de conformidad con lo estipulado en su Resolutivo Tercero de la\nSentencia a Controversia Constitucional 119/2020, notificada a este Congreso del Estado de este artículo;\nLey de Hacienda del Estado de Baja California. Página 95\n.\nActualización Legislativa.\nÚltima reforma P.O. No. 72, Índice, 22-Dic-2023\nARTICULO 137.- Fue suspendida la vigencia de este artículo en lo que pague el IVA e Impuestos Federales, por Decreto No. 164, publicado en el Periódico Oficial No. 36,\nSección IX de fecha 31 de Diciembre de 1979, Sección XI, expedido por la Honorable IX\nLegislatura, siendo Gobernador Constitucional el C. Roberto de la Madrid Romandía, 19771983; fue reformado por Decreto No. 139, publicado en el Periódico Oficial No. 36, Sección\nXI de fecha 31 de Diciembre de 1988, expedido por la Honorable XII Legislatura, siendo\nGobernador Constitucional el c. Lic. Xicoténcatl Leyva Mortera, 1983 Enero de 1989;\nARTICULO 138.- Fue reformado por Decreto No. 139, publicado en el Periódico\nOficial No. 36, Sección XI de fecha 31 de Diciembre de 1988, expedido por la Honorable XII\nLegislatura, siendo Gobernador Constitucional el C. Lic. Xicoténcatl Leyva Mortera, 1983\nEnero de 1989, ARTICULO 139.- Fue reformado por Decreto No. 139, publicado en el Periódico\nOficial No. 36, Sección XI de fecha 31 de Diciembre de 1988, expedido por la Honorable XII\nLegislatura, siendo Gobernador Constitucional el C. Lic. Xicoténcatl Leyva Mortera, 1983Enero de 1989;\nARTICULO 140.- Fue reformado por Decreto No. 55, publicado en el Periódico Oficial\nNo. 44, de fecha 29 de octubre de 1993, expedido por la Honorable XIV Legislatura, siendo\nGobernador Constitucional el C. L.A.E. Ernesto Ruffo Appel, 1989-1995; Fue reformado por\nDecreto No. 240, publicado en el Periódico Oficial No. 52 de fecha 4 de Diciembre de 2000, expedido por la Honorable XVI Legislatura del Estado, siendo Gobernador Constitucional el\nC. Lic. Alejandro González Alcocer, Octubre de 1998-2001; fue reformado por Decreto No.\n361, publicado en el Periódico Oficial No. 72, de fecha 22 de diciembre de 2023, Índice, Tomo CXXX, expedido por la H. XXIV Legislatura, siendo Gobernadora Constitucional la C.\nMarina del Pilar Ávila Olmeda 2021-2027;\nARTICULO 141.- Fue reformado por Decreto No. 139, publicado en el Periódico\nOficial No. 36, Sección XI de fecha 31 de Diciembre de 1988, expedido por la Honorable XII\nLegislatura, siendo Gobernador Constitucional el C. Lic. Xicoténcatl Leyva Mortera, 1983Enero de 1989;\nARTICULO 143.- Fue reformado por Decreto No. 55, publicado en el Periódico Oficial\nGobernador Constitucional el C. L.A.E. Ernesto Ruffo Appel, 1989-1995;\nARTICULO 143-1.- Fue adicionado por Decreto No. 55, publicado en el Periódico siendo Gobernador Constitucional el C. L.A.E. Ernesto Ruffo Appel, 1989-1995;\nARTICULO 143-2.- Fue adicionado por Decreto No. 55, publicado en el Periódico siendo Gobernador Constitucional el C. L.A.E. Ernesto Ruffo Appel, 1989-1995;\nLey de Hacienda del Estado de Baja California. Página 96\n.\nActualización Legislativa.\nÚltima reforma P.O. No. 72, Índice, 22-Dic-2023\nARTICULO 143-3.- Fue adicionado por Decreto No. 55, publicado en el Periódico\nOficial No. 44, de fecha 29 de octubre de 1993, expedido por la Honorable XIV Legislatura, siendo Gobernador Constitucional el C. L.A.E. Ernesto Ruffo Appel, 1989-1995; Fue reformado por Decreto No. 240, publicado en el Periódico Oficial No. 52 de fecha 4 de\nDiciembre de 2000, expedido por la Honorable XVI Legislatura del Estado, siendo\nGobernador Constitucional el C. Lic. Alejandro González Alcocer, Octubre de 1998-2001; fue reformado por Decreto No. 361, publicado en el Periódico Oficial No. 72, de fecha 22 de diciembre de 2023, Índice, Tomo CXXX, expedido por la H. XXIV Legislatura, siendo\nGobernadora Constitucional la C. Marina del Pilar Ávila Olmeda 2021-2027;\nARTICULO 143-4.- Fue adicionado por Decreto No. 55, publicado en el Periódico\nOficial No. 44, de fecha 29 de octubre de 1993, expedido por la Honorable XIV Legislatura, siendo Gobernador Constitucional el C. L.A.E. Ernesto Ruffo Appel, 1989-1995; Fue reformado por Decreto No. 240, publicado en el Periódico Oficial No. 52 de fecha 4 de\nDiciembre de 2000, expedido por la Honorable XVI Legislatura del Estado, siendo\nGobernador Constitucional el C. Lic. Alejandro González Alcocer, Octubre de 1998-2001; fue reformado por Decreto No. 361, publicado en el Periódico Oficial No. 72, de fecha 22 de diciembre de 2023, Índice, Tomo CXXX, expedido por la H. XXIV Legislatura, siendo\nGobernadora Constitucional la C. Marina del Pilar Ávila Olmeda 2021-2027;\nARTICULO 143-5.- Fue adicionado por Decreto No. 55, publicado en el Periódico\nOficial No. 44, de fecha 29 de octubre de 1993, expedido por la Honorable XIV Legislatura, siendo Gobernador Constitucional el C. L.A.E. Ernesto Ruffo Appel, 1989-1995;\nCAPITULO XI\nIMPUESTO SOBRE COMPRA-VENTA\nY OPERACIONES SIMILARES\nARTICULO 144.- Fue reformado por Decreto No. 170, publicado por el Periódico\nOficial No. 7 de fecha 10 de Marzo de 1974, expedido por la Honorable VII Legislatura, siendo Gobernador Constitucional el C. Lic. Milton Castellanos Everardo, 1971-1977; fue suspendida la vigencia de este artículo en lo que pague el IVA e Impuestos Federales, por\nDecreto No. 164, publicado en el Periódico Oficial No. 36, Sección XI de fecha 31 de\nConstitucional el C. Roberto de la Madrid Romandía, 1977-1983; fue reformado por Decreto\nNo. 139, publicado en el Periódico Oficial No. 36, Sección XI de fecha 31 de Diciembre 1988, expedido por la Honorable XII Legislatura, siendo Gobernador Constitucional el C. Lic.\nARTICULO 145.- Fue reformado por Decreto No. 139, publicado en el Periódico\nLegislatura, siendo Gobernador Constitucional el C. Lic. Xicoténcatl Leyva Mortera, 1983Ley de Hacienda del Estado de Baja California. Página 97\n.\nActualización Legislativa.\nÚltima reforma P.O. No. 72, Índice, 22-Dic-2023\nARTICULO 146.- Fue reformado por Decreto No. 139, publicado en el Periódico\nOficial No. 36, Sección XI de fecha 31 de Diciembre de 1988, expedido por la Honorable XII\nLegislatura, siendo Gobernador Constitucional el C. Lic. Xicoténcatl Leyva Mortera, 1983\nEnero de 1989; Fue reformado por Decreto No. 240, publicado en el Periódico Oficial No. 52 de fecha 4 de Diciembre de 2000, expedido por la Honorable XVI Legislatura del Estado, siendo Gobernador Constitucional el C. Lic. Alejandro González Alcocer, Octubre de 19982001; fue reformado por Decreto No. 361, publicado en el Periódico Oficial No. 72, de fecha\n22 de diciembre de 2023, Índice, Tomo CXXX, expedido por la H. XXIV Legislatura, siendo\nGobernadora Constitucional la C. Marina del Pilar Ávila Olmeda 2021-2027;\nARTICULO 147.- Fue reformado por Decreto No. 240, publicado en el Periódico\nOficial No. 52 de fecha 4 de Diciembre de 2000, expedido por la Honorable XVI Legislatura del Estado, siendo Gobernador Constitucional el C. Lic. Alejandro González Alcocer, Octubre de 1998-2001; fue reformado por Decreto No. 361, publicado en el Periódico Oficial No. 72, de fecha 22 de diciembre de 2023, Índice, Tomo CXXX, expedido por la H. XXIV Legislatura, siendo Gobernadora Constitucional la C. Marina del Pilar Ávila Olmeda 2021-2027;\nFue adicionado este Capítulo por Decreto No. 22, publicado en el Periódico Oficial No. 36,\nSección XI de fecha 31 de Diciembre de 1974, expedido por la Honorable VIII Legislatura, siendo Gobernador Constitucional el C. Lic. Milton Castellanos Everardo, 1971-1977;\nCAPITULO XIV\nIMPUESTO SOBRE ARRENDAMIENTO SUBARRENDAMIENTO DE BIENES INMUEBLES\nARTICULO 151- 1.- Fue adicionado por Decreto No. 22, publicado en el Periódico\nOficial No. 36, Sección XI de fecha 31 de Diciembre de 1974, expedido por la Honorable VIII\nLegislatura, siendo Gobernador Constitucional el C. Lic. Milton Castellanos Everardo, 19711977; fue suspendida la vigencia de este artículo en lo que pague el IVA e Impuestos\nFederales, por Decreto No. 164, publicado en el Periódico Oficial No. 36, Sección XI de fecha 31 de Diciembre de 1979, expedido por la Honorable IX Legislatura, siendo\nGobernador Constitucional el C. Roberto de la Madrid Romandía, 1977-1983;\nARTICULO 151-2.- Fue adicionado por Decreto No. 22, publicado en el Periódico\nOficial No. 36, Sección XI de fecha 31 de Diciembre de 1974, expedido por la Honorable VIII\nLegislatura, siendo Gobernador Constitucional el C. Lic. Milton Castellanos Everardo, 19711977;\nARTICULO 151-3.- Fue adicionado por Decreto No. 22, publicado en el Periódico\nLegislatura, siendo Gobernador Constitucional el C. Lic. Milton Castellanos Everardo, 19711977;\nARTICULO 151-4.- Fue adicionado por Decreto No. 22, publicado en el Periódico\nLegislatura, siendo Gobernador Constitucional el C. Lic. Milton Castellanos Everardo, 19711977;\nLey de Hacienda del Estado de Baja California. Página 98\n.\nActualización Legislativa.\nÚltima reforma P.O. No. 72, Índice, 22-Dic-2023\nARTICULO 151-5.- Fue adicionado por Decreto No. 22, publicado en el Periódico\nOficial No. 36, Sección XI de fecha 31 de Diciembre de 1974, expedidos por la Honorable\nVIII Legislatura, siendo Gobernador Constitucional el C. Lic. Milton Castellanos Everardo, 1971-1977;\nARTICULO 151-6.- Fue adicionado por Decreto No. 22, publicado en el Periódico\nOficial No. 36, Sección XI de fecha 31 de Diciembre de 1974, expedido por la Honorable VIII\nLegislatura, siendo Gobernador Constitucional el C. Lic. Milton Castellanos Everardo, 19711977; Fue reformado por Decreto No. 240, publicado en el Periódico Oficial No. 52 de fecha\n4 de Diciembre de 2000, expedido por la Honorable XVI Legislatura del Estado, siendo\nGobernador Constitucional el C. Lic. Alejandro González Alcocer, Octubre de 1998-2001; fue reformado por Decreto No. 361, publicado en el Periódico Oficial No. 72, de fecha 22 de diciembre de 2023, Índice, Tomo CXXX, expedido por la H. XXIV Legislatura, siendo\nGobernadora Constitucional la C. Marina del Pilar Ávila Olmeda 2021-2027;\nARTICULO 151-7.- Fue adicionado por Decreto No. 22, publicado en el Periódico\nOficial No. 36, Sección XI de fecha 31 de Diciembre 1974, expedido por la Honorable VIII\nLegislatura, siendo Gobernador Constitucional el C. Lic. Milton Castellanos Everardo, 19711977; fue reformado por Decreto No. 240, publicado en el Periódico Oficial No. 52 de fecha 4 de Diciembre de 2000, expedido por la Honorable XVI Legislatura del Estado, siendo\nGobernador Constitucional el C. Lic. Alejandro González Alcocer, Octubre de 1998-2001; fue reformado por Decreto No. 361, publicado en el Periódico Oficial No. 72, de fecha 22 de diciembre de 2023, Índice, Tomo CXXX, expedido por la H. XXIV Legislatura, siendo\nGobernadora Constitucional la C. Marina del Pilar Ávila Olmeda 2021-2027;\nARTICULO 151-8.- Fue adicionado por Decreto No. 22, publicado en el Periódico\nOficial No. 36, Sección XI de fecha 31 de Diciembre de 1974, expedido por la Honorable VIII\nLegislatura, siendo Gobernador Constitucional el C. Lic. Milton Castellanos Everardo, 19711977;\nARTICULO 151-9.- Fue adicionado por Decreto No. 22, publicado en el Periódico\nOficial No. 36, Sección XI de fecha 31 de Diciembre de 1974, expedido por la Honorable VIII\nLegislatura, siendo Gobernador Constitucional el C. Lic. Milton Castellanos Everardo, 19711977; fue reformado por Decreto No. 240, publicado en el Periódico Oficial No. 52 de fecha reformado por Decreto No. 361, publicado en el Periódico Oficial No. 72, de fecha 22 de\nGobernadora Constitucional la C. Marina del Pilar Ávila Olmeda 2021-2027;\nARTICULO 151-10.- Fue adicionado por Decreto No. 22, publicado en el Periódico\nLegislatura, siendo Gobernador Constitucional el C. Lic. Milton Castellanos Everardo, 19711977; fue reformado por Decreto No. 240, publicado en el Periódico Oficial No. 52 de fecha 4\nLey de Hacienda del Estado de Baja California. Página 99\n.\nActualización Legislativa.\nÚltima reforma P.O. No. 72, Índice, 22-Dic-2023 de Diciembre de 2000, expedido por la Honorable XVI Legislatura del Estado, siendo\nGobernador Constitucional el C. Lic. Alejandro González Alcocer, Octubre de 1998-2001; fue reformado por Decreto No. 361, publicado en el Periódico Oficial No. 72, de fecha 22 de diciembre de 2023, Índice, Tomo CXXX, expedido por la H. XXIV Legislatura, siendo\nGobernadora Constitucional la C. Marina del Pilar Ávila Olmeda 2021-2027;\nARTICULO 151-11.- Fue adicionado por Decreto No. 22, publicado en el Periódico\nOficial No. 36, Sección XI de fecha 31 de Diciembre de 1974, expedido por la Honorable VIII\nLegislatura, siendo Gobernador Constitucional el C. Lic. Milton Castellanos Everardo, 19711977;\nARTICULO 151-12.- Fue adicionado por Decreto No. 22, publicado en el Periódico\nOficial No. 36, Sección XI de fecha 31 de Diciembre de 1974, expedido por la Honorable VIII\nLegislatura, siendo Gobernador Constitucional el C. Lic. Milton Castellanos Everardo, 19711977;\nFue adicionado este Capítulo por Decreto No. 98, publicado en el Periódico Oficial\nNo. 12, de fecha 30 de abril de 1973, expedido por la Honorable VII Legislatura, siendo\nGobernador Constitucional el C. Lic. Milton Castellanos Everardo 1971-1977; fue reformado reubicándolo y modificando su denominación por Decreto No. 22, publicado en el Periódico\nOficial No. 36, Sección XI de fecha 31 de Diciembre de 1974, expedido por la Honorable VIII\nLegislatura, siendo Gobernador Constitucional el C. Lic. Milton Castellanos Everardo, 19711977; fue modificada la denominación de este Capítulo por Decreto No. 95, publicado en el\nPeriódico Oficial No. 36, Sección XI de fecha 31 de Diciembre de 1978, expedido por la\nHonorable IX Legislatura, siendo Gobernador Constitucional el C. Lic. Roberto de la Madrid\nRomandía, 1977-1983;\nCAPITULO XV\nDE LOS IMPUESTOS SOBRE PRODUCTOS DEL TRABAJO\nFue adicionada la denominación de la Sección Primera del Capítulo XV, por Decreto\nNo. 95, publicado en el Periódico Oficial No. 36, Sección XI, de fecha 31 de Diciembre de\n1978, expedido por la Honorable IX Legislatura, siendo Gobernador Constitucional el C.\nRoberto de la Madrid Romandía, 1977-1983,\nSECCION PRIMERA\nARTICULO 151-13.- Fue adicionado por Decreto No. 22, publicado en el Periódico\nLegislatura, siendo Gobernador Constitucional el C. Lic. Milton Castellanos Everardo, 19711977; fue reformado por Decreto No. 206, publicado en el Periódico Oficial No. 4, de fecha\nConstitucional el C. Lic. Milton Castellanos Everardo, 1971-1977; fue reformado por Decreto\nNo. 95, publicado en el Periódico Oficial No. 36, Sección XI, de fecha 31 de Diciembre de\n1978, expedido por la Honorable IX Legislatura, siendo Gobernador Constitucional el C.\nLey de Hacienda del Estado de Baja California. Página 100\n.\nActualización Legislativa.\nÚltima reforma P.O. No. 72, Índice, 22-Dic-2023\nRoberto de la Madrid Romandía, 1977-1983; fue reformado por Decreto No. 182, publicado en el Periódico Oficial No. 16, Sección I de fecha 10 de Junio de 1980, expedido por la\nHonorable IX Legislatura, siendo Gobernador Constitucional el C. Roberto de la Madrid\nRomandía, 1977-1983; fue reformado por Decreto No. 93, publicado en el Periódico Oficial\nNo. 5 de fecha 20 de Febrero de 1988, expedido por la Honorable XII Legislatura, siendo\nGobernador Constitucional el C. Lic. Xicoténcatl Leyva Mortera, 1983-Enero 1989; fue reformado por Decreto No. 139, publicado en el Periódico Oficial No. 36, Sección XI de fecha\n31 de Diciembre de 1988, expedido por la Honorable XII Legislatura, siendo Gobernador\nConstitucional el C. Lic. Xicoténcatl Leyva Mortera, 1983-Enero de 1989; fue reformado por\nDecreto No. 55, publicado en el Periódico Oficial No. 44, de fecha 29 de octubre de 1993, expedido por la Honorable XIV Legislatura, siendo Gobernador Constitucional el C. L.A.E.\nErnesto Ruffo Appel, 1989-1995; fue reformado por Decreto No. 122, publicado en el\nPeriódico Oficial No. 8, de fecha 20 de febrero de 1998, Tomo CV, expedido por la\nHonorable XV Legislatura del Estado, siendo Gobernador Constitucional el C. Lic. Héctor\nTerán Terán, 1995-1998; fue reformado por Decreto No. 284, publicado en el Periódico\nOficial No. 15, de fecha 02 de abril de 2004, Sección II, Tomo CXI, expedido por la\nHonorable XVII Legislatura, siendo Gobernador Constitucional el C. Lic. Eugenio Elorduy\nWalther, 2001-2007; fue reformada por Decreto No. 55, publicado en el Periódico Oficial No.\n27, de fecha 10 de Junio de 2005, Tomo CXII, expedido por la H. XVIII Legislatura siendo\nGobernador Constitucional el C. Eugenio Elorduy Walter 2001-2007;\nARTICULO 151-14.- Fue adicionado por Decreto No. 22, publicado en el Periódico\nOficial No. 36, Sección XI, de fecha 31 de Diciembre de 1974, expedido por la Honorable VIII\nLegislatura, siendo Gobernador Constitucional el C. Lic. Milton Castellanos Everardo, 19711977; fue reformado por Decreto No. 95, publicado en el Periódico Oficial No. 36, Sección\nXI, de fecha 31 de Diciembre de 1978 expedido por la Honorable IX Legislatura, siendo\nGobernador Constitucional el C. Roberto de la Madrid Romandía, 1977-1983; fue reformado por Decreto No. 122, publicado en el Periódico Oficial No. 8, de fecha 20 de febrero de 1998, Tomo CV, expedido por la Honorable XV Legislatura del Estado, siendo Gobernador\nConstitucional el C. Lic. Héctor Terán Terán, 1995-1998; fue reformado por Decreto No. 284, publicado en el Periódico Oficial No. 15, de fecha 02 de abril de 2004, Sección II, Tomo CXI, expedido por la Honorable XVII Legislatura, siendo Gobernador Constitucional el C. Lic.\nEugenio Elorduy Walther, 2001-2007; fue reformado por Decreto No. 281, publicado en el\nPeriódico Oficial No. 55, de fecha 30 de noviembre de 2018, Tomo CXXV, Sección IV, expedido por la Honorable Legislatura XXII, siendo Gobernador Constitucional el C.\nFrancisco Arturo Vega de Lamadrid 2013-2019;\nARTICULO 151-15.- Fue adicionado por Decreto No. 22, publicado en el Periódico\nLegislatura, siendo Gobernador Constitucional el C. Lic. Milton Castellanos Everardo 19711977; fue reformado por Decreto No. 95, publicado en el Periódico Oficial No. 36, Sección\nGobernador Constitucional el C. Roberto de la Madrid Romandía, 1977-1983, fue reformado\nLey de Hacienda del Estado de Baja California. Página 101\n.\nActualización Legislativa.\nÚltima reforma P.O. No. 72, Índice, 22-Dic-2023\nSección II, Tomo CXI, expedido por la Honorable XVII Legislatura, siendo Gobernador\nConstitucional el C. Lic. Eugenio Elorduy Walther, 2001-2007;\nARTICULO 151-16.- Fue adicionado por Decreto No. 22, publicado en el Periódico\nOficial No. 36, Sección XI de fecha 31 de Diciembre de 1974, expedido por la Honorable VIII\nLegislatura, siendo Gobernador Constitucional el C. Lic. Milton Castellanos Everardo, 19711977; fue reformado por Decreto No. 95, publicado en el Periódico Oficial No. 36, Sección\nIX, de fecha 31 de Diciembre de 1978, expedido por la Honorable IX Legislatura, siendo\nGobernador Constitucional el C. Roberto de la Madrid Romandía, 1977-1983; fue reformado por Decreto No. 122, publicado en el Periódico Oficial No. 8, de fecha 20 de febrero de 1998, Tomo CV, expedido por la Honorable XV Legislatura del Estado, siendo Gobernador\nConstitucional el C. Lic. Héctor Terán Terán, 1995-1998; fue adicionado por Decreto No. 34, publicado en el Periódico Oficial No. 8, de fecha 22 de febrero de 2002, Sección II, expedido por la H. XVII Legislatura, siendo Gobernador Constitucional el C. Eugenio Elorduy Walther\n2001-2007; fue reformado por Decreto No. 486, publicado en el Periódico Oficial No. 30, de fecha 05 de julio de 2013, Tomo CXX, Sección II, expedido por la Honorable XX Legislatura, siendo Gobernador Constitucional el C. Lic. José Guadalupe Osuna Millán, 2007-2013; fue reformado mediante Decreto No. 29, publicado en el Periódico Oficial No. 60, Sección VIII, Tomo CXX, de fecha 31 de diciembre de 2013, expedido por la H. XXI Legislatura, siendo\nGobernador Constitucional el C. Francisco Arturo Vega de la Madrid 2013-2019; fue reformado por Decreto No. 84, publicado en el Periódico Oficial No. 17, de fecha 04 de marzo de 2022, Tomo CXXIX, Sección I, expedido por la H. XXIV Legislatura, siendo\nGobernadora Constitucional la C. Marina del Pilar Ávila Olmeda 2021-2027; fue reformado por Decreto No. 361, publicado en el Periódico Oficial No. 72, de fecha 22 de diciembre de\n2023, Índice, Tomo CXXX, expedido por la H. XXIV Legislatura, siendo Gobernadora\nConstitucional la C. Marina del Pilar Ávila Olmeda 2021-2027;\nARTICULO 151-17.- Fue adicionado por Decreto No. 22, publicado en el Periódico\nOficial No. 36, Sección XI, de fecha 31 de Diciembre de 1974, expedido por la Honorable VIII\nLegislatura, siendo Gobernador Constitucional el C. Lic. Milton Castellanos Everardo, 19711977; fue reformado por Decreto No. 95, publicado en el Periódico Oficial No. 36, Sección XI de fecha 31 de Diciembre de 1978, expedido por la Honorable IX Legislatura, siendo\nGobernador Constitucional el C. Roberto de la Madrid Romandía, 1977-1983; fue reformado por Decreto No. 284, publicado en el Periódico Oficial No. 15 de fecha 02 de abril de 2004,\nSección II, Tomo CXI, expedido por la Honorable XVII Legislatura, siendo Gobernador\nConstitucional el C. Lic. Eugenio Elorduy Walther, 2001-2007;\nARTICULO 151-18.- Fue adicionado por Decreto No. 22, publicado en el Periódico\nLegislatura, siendo Gobernador Constitucional el C. Lic. Milton Castellanos Everardo, 19711977; fue reformado por Decreto No. 95, publicado en el Periódico Oficial No. 36, Sección\nGobernador Constitucional el C. Roberto de la Madrid Romandía, 1977-1983; fue derogado por Decreto No. 165, publicado en el Periódico Oficial No. 36, Sección XI, de fecha 31 de\nLey de Hacienda del Estado de Baja California. Página 102\n.\nActualización Legislativa.\nÚltima reforma P.O. No. 72, Índice, 22-Dic-2023\nDiciembre de 1979, expedido por la Honorable IX Legislatura, siendo Gobernador\nConstitucional el C. Roberto de la Madrid Romandía, 1977-1983; fue reformado por Decreto\nNo. 55, publicado en el Periódico Oficial No. 44, de fecha 29 de octubre de 1993, expedido por la Honorable XIV Legislatura, siendo Gobernador Constitucional el C. L.A.E. Ernesto\nRuffo Appel, 1989-1995; fue reformado por Decreto No. 122, publicado en el Periódico\nOficial No. 8, de fecha 20 de febrero de 1998, Tomo CV, expedido por la Honorable XV\nLegislatura del Estado, siendo Gobernador Constitucional el C. Lic. Héctor Terán Terán, 1995-1998; fue reformado por Decreto No. 284, publicado en el Periódico Oficial No. 15, de fecha 02 de abril de 2004, Sección II, Tomo CXI, expedido por la Honorable XVII Legislatura, siendo Gobernador Constitucional el C. Lic. Eugenio Elorduy Walther, 2001-2007;\nARTICULO 151-19.- Fue adicionado por Decreto No. 22, publicado en el Periódico\nOficial No. 36, Sección XI, de fecha 31 de Diciembre de 1974, expedido por la Honorable VIII\nLegislatura, siendo Gobernador Constitucional el C. Lic. Milton Castellanos Everardo, 19711977; fue reformado por Decreto No. 95, publicado en el Periódico Oficial No. 36, Sección\nXI, de fecha 31 de Diciembre de 1978, expedido por la Honorable IX Legislatura, siendo\nGobernador Constitucional el C. Roberto de la Madrid Romandía, 1977-1983; fue reformado por Decreto No. 122, publicado en el Periódico Oficial No. 8, de fecha 20 de febrero de 1998, Tomo CV, expedido por la Honorable XV Legislatura del Estado, siendo Gobernador\nConstitucional el C. Lic. Héctor Terán Terán, 1995-1998; fue reformado por Decreto No. 133, publicado en el Periódico Oficial No. 57, de fecha 31 de diciembre de 2002, Sección VIII, Tomo CIX, expedido por la Honorable XVII Legislatura, siendo Gobernador Constitucional el\nC. Lic. Eugenio Elorduy Walther, 2001-2007, ARTICULO 151-20.- Fue adicionado por Decreto No. 22, publicado en el Periódico\nOficial No. 36, Sección XI, de fecha 31 de Diciembre de 1974, expedido por la Honorable VIII\nLegislatura, siendo Gobernador Constitucional el C. Lic. Milton Castellanos Everardo, 19711977; fue reformado por Decreto No. 95, publicado en el Periódico Oficial No. 36, Sección XI de fecha 31 de Diciembre de 1978, expedido por la Honorable IX Legislatura, siendo\nGobernador Constitucional el C. Roberto de la Madrid Romandía, 1977-1983; fue reformado por Decreto No. 122, publicado en el Periódico Oficial No. 8, de fecha 20 de febrero de 1998, Tomo CV, expedido por la Honorable XV Legislatura del Estado, siendo Gobernador\nConstitucional el C. Lic. Héctor Terán Terán, 1995-1998; fue reformado por Decreto No. 284, publicado en el Periódico Oficial No. 15 de fecha 02 de abril de 2004, expedido por la\nHonorable XVII Legislatura, siendo Gobernador Constitucional el C. Lic. Eugenio Elorduy\nWalther, 2001-2007; fue reformado por Decreto No. 284, publicado en el Periódico Oficial\nLegislatura, siendo Gobernador Constitucional el C. Lic. Eugenio Elorduy Walther, 20012007;\nFue adicionada la denominación de la Sección Segunda del Capítulo XV, por Decreto No. expedido por la Honorable IX Legislatura, siendo Gobernador Constitucional el C. Roberto de la Madrid Romandía, 1977-1983;\nLey de Hacienda del Estado de Baja California. Página 103\n.\nActualización Legislativa.\nÚltima reforma P.O. No. 72, Índice, 22-Dic-2023\nSECCION SEGUNDA\nIMPUESTOS SOBRE PROFESIONES Y EJERCICIOS LUCRATIVOS\nARTICULO 151-21.- Fue adicionado por Decreto No. 22, publicado en el Periódico\nOficial No. 36, de fecha 31 de Diciembre de 1974, expedido por la Honorable VIII\nLegislatura, siendo Gobernador Constitucional el C. Lic. Milton Castellanos Everardo, 19711977; fue reformado por Decreto No. 95, publicado en el Periódico Oficial No. 36, Sección\nXI, de fecha 31 de Diciembre de 1978, expedido por la Honorable IX Legislatura, siendo\nGobernador Constitucional el C. Roberto de la Madrid Romandía, 1977-1983; fue suspendida la vigencia de este artículo en lo que pague el IVA e Impuestos Federales, por\nDecreto No. 164, publicado en el Periódico Oficial No. 36, Sección XI de fecha 31 de\nDiciembre de 1979, expedido por la Honorable IX Legislatura, siendo Gobernador\nConstitucional el C. Roberto de la Madrid Romandía, 1977-1983;\nARTICULO 151-22.- Fue adicionado por Decreto No. 22, publicado en el Periódico\nOficial No. 36, Sección XI, de fecha 31 de Diciembre de 1974, expedido por la Honorable VIII\nLegislatura, siendo Gobernador Constitucional el C. Lic. Milton Castellanos Everardo, 19711977; fue reformado por Decreto No. 95, publicado en el Periódico Oficial No. 36, Sección XI de fecha 31 de Diciembre de 1978, expedido por la Honorable IX Legislatura, siendo\nGobernador Constitucional el C. Roberto de la Madrid Romandía, 1977-1983;\nARTICULO 151-23.- Fue adicionado por Decreto No. 22, publicado en el Periódico\nOficial No. 36, Sección XI, de fecha 31 de Diciembre de 1974, expedido por la Honorable VIII\nLegislatura siendo Gobernador Constitucional el C. Lic. Milton Castellanos Everardo, 19711977; fue reformado por Decreto No. 100, publicado en el Periódico Oficial No. 3 de fecha 31 de Enero de 1976, expedido por la Honorable VIII Legislatura, estando encargado del\nDespacho de Gobierno el C. Secretario General Francisco Santana Peralta, siendo\nGobernador Constitucional el C. Lic. Milton Castellanos Everardo, 1971-1977; fue reformado por Decreto No. 95, publicado en el Periódico Oficial No. 36, Sección XI, de fecha 31 de\nDiciembre de 1978, expedido por la Honorable IX Legislatura, siendo Gobernador\nConstitucional el C. Roberto de la Madrid Romandía, 1977-1983;\nARTICULO 151-24.- Fue adicionado por Decreto No. 22, publicado en el Periódico\nOficial No. 36, Sección XI, de fecha 31 de Diciembre de 1974, expedido por la Honorable VIII\nLegislatura, siendo Gobernador Constitucional el C. Lic. Milton Castellanos Everardo, 19711977; fue reformado por Decreto No. 95, publicado en el Periódico Oficial No. 36, Sección\nGobernador Constitucional el C. Roberto de la Madrid Romandía, 1977-1983;\nARTICULO 151-25.- Fue adicionado por Decreto No. 95, publicado en el Periódico\nLegislatura, siendo Gobernador Constitucional el C. Roberto de la Madrid Romandía, 19771983; Fue reformado por Decreto No. 240, publicado en el Periódico Oficial No. 52 de fecha\nLey de Hacienda del Estado de Baja California. Página 104\n.\nActualización Legislativa.\nÚltima reforma P.O. No. 72, Índice, 22-Dic-2023\nGobernador Constitucional el C. Lic. Alejandro González Alcocer, Octubre de 1998-2001; fue reformado por Decreto No. 361, publicado en el Periódico Oficial No. 72, de fecha 22 de diciembre de 2023, Índice, Tomo CXXX, expedido por la H. XXIV Legislatura, siendo\nGobernadora Constitucional la C. Marina del Pilar Ávila Olmeda 2021-2027;\nARTICULO 151-26.- Fue adicionado por Decreto No. 95, publicado en el Periódico\nOficial No. 36, Sección XI, de fecha 31 de Diciembre de 1978, expedido por la Honorable IX\nLegislatura, siendo Gobernador Constitucional el C. Roberto de la Madrid Romandía, 19771983; Fue reformado por Decreto No. 240, publicado en el Periódico Oficial No. 52 de fecha\n4 de Diciembre de 2000, expedido por la Honorable XVI Legislatura del Estado, siendo\nGobernador Constitucional el C. Lic. Alejandro González Alcocer, Octubre de 1998-2001; fue reformado por Decreto No. 361, publicado en el Periódico Oficial No. 72, de fecha 22 de diciembre de 2023, Índice, Tomo CXXX, expedido por la H. XXIV Legislatura, siendo\nGobernadora Constitucional la C. Marina del Pilar Ávila Olmeda 2021-2027;\nARTICULO 151-27.- Fue adicionado por Decreto No. 95, publicado en el Periódico\nOficial No. 36, Sección XI, de fecha 31 de Diciembre de 1978, expedido por la Honorable IX\nLegislatura, siendo Gobernador Constitucional el C. Roberto de la Madrid Romandía, 19771983; Fue reformado por Decreto No. 240, publicado en el Periódico Oficial No. 52 de fecha\n4 de Diciembre de 2000, expedido por la Honorable XVI Legislatura del Estado, siendo\nGobernador Constitucional el C. Lic. Alejandro González Alcocer, Octubre de 1998-2001; fue reformado por Decreto No. 361, publicado en el Periódico Oficial No. 72, de fecha 22 de diciembre de 2023, Índice, Tomo CXXX, expedido por la H. XXIV Legislatura, siendo\nGobernadora Constitucional la C. Marina del Pilar Ávila Olmeda 2021-2027;\nARTICULO 151-28.- Fue adicionado por Decreto No. 95, publicado en el Periódico\nOficial No. 36, Sección XI, de fecha 31 de Diciembre de 1978, expedido por la Honorable IX\nLegislatura, siendo Gobernador Constitucional el C. Roberto de la Madrid Romandía, 19771983, fue reformado por Decreto No. 281, publicado en el Periódico Oficial No. 55, de fecha\n30 de noviembre de 2018, Tomo CXXV, Sección IV, expedido por la Honorable Legislatura\nXXII, siendo Gobernador Constitucional el C. Francisco Arturo Vega de Lamadrid 2013-2019;\nARTICULO 151-29.- Fue adicionado por Decreto No. 95, publicado en el Periódico\nOficial No. 36, Sección XI, de fecha 31 de Diciembre de 1978, expedido por la Honorable IX\nLegislatura, siendo Gobernador Constitucional el C. Roberto de la Madrid Romandía, 19771983, Fue reformado por Decreto No. 240, publicado en el Periódico Oficial No. 52 de fecha reformado por Decreto No. 361, publicado en el Periódico Oficial No. 72, de fecha 22 de\nGobernadora Constitucional la C. Marina del Pilar Ávila Olmeda 2021-2027;\nFue adicionada la denominación de este Capítulo, por Decreto No. 95, publicado en el\nLey de Hacienda del Estado de Baja California. Página 105\n.\nActualización Legislativa.\nÚltima reforma P.O. No. 72, Índice, 22-Dic-2023\nHonorable IX Legislatura, siendo Gobernador Constitucional el C. Roberto de la Madrid\nRomandía, 1977-1983,\nCAPITULO XVI\nIMPUESTO SOBRE PRODUCTOS DE CAPITALES\nARTICULO 151-30.- Fue adicionado por Decreto No. 95, publicado en el Periódico\nOficial No. 36, Sección XI de fecha 31 de Diciembre de 1978, expedido por la Honorable IX\nLegislatura, siendo Gobernador Constitucional el C. Roberto de la Madrid Romandía, 19771983, ARTICULO 151-31.- Fue adicionado por Decreto No. 95, publicado en el Periódico\nOficial No. 36, Sección XI de fecha 31 de Diciembre de 1978, expedido por la Honorable IX\nLegislatura, siendo Gobernador Constitucional el C. Roberto de la Madrid Romandía, 19771983, ARTICULO 151-32.- Fue adicionado por Decreto No. 95, publicado en el Periódico\nOficial No. 36, Sección XI de fecha 31 de Diciembre de 1978, expedido por la Honorable IX\nLegislatura, siendo Gobernador Constitucional el C. Roberto de la Madrid Romandía, 19771983, ARTICULO 151-33.- Fue adicionado por Decreto No. 95, publicado en el Periódico\nOficial No. 36, Sección XI de fecha 31 de Diciembre de 1978, expedido por la Honorable IX\nLegislatura, siendo Gobernador Constitucional el C. Roberto de la Madrid Romandía, 19771983, ARTICULO 151-34.- Fue adicionado por Decreto No. 95, publicado en el Periódico\nOficial No. 36, Sección XI de fecha 31 de Diciembre de 1978, expedido por la Honorable IX\nLegislatura, siendo Gobernador Constitucional el C. Roberto de la Madrid Romandía, 19771983, ARTICULO 151-35.- Fue adicionado por Decreto No. 95, publicado en el Periódico\nOficial No. 36, Sección XI de fecha 31 de Diciembre de 1978, expedido por la Honorable IX\nLegislatura, siendo Gobernador Constitucional el C. Roberto de la Madrid Romandía, 19771983, ARTICULO 151-36.- Fue adicionado por Decreto No. 95, publicado en el Periódico\nLegislatura, siendo Gobernador Constitucional el C. Roberto de la Madrid Romandía, 19771983, ARTICULO 151-37.- Fue adicionado por Decreto No. 95, publicado en el Periódico\nLegislatura, siendo Gobernador Constitucional el C. Roberto de la Madrid Romandía, 19771983, Ley de Hacienda del Estado de Baja California. Página 106\n.\nActualización Legislativa.\nÚltima reforma P.O. No. 72, Índice, 22-Dic-2023\nARTICULO 151-38.- Fue adicionado por Decreto No. 95, publicado en el Periódico\nOficial No. 36, Sección XI de fecha 31 de Diciembre de 1978, expedido por la Honorable IX\nLegislatura, siendo Gobernador Constitucional el C. Roberto de la Madrid Romandía, 19771983, ARTICULO 151-39.- Fue adicionado por Decreto No. 95, publicado en el Periódico\nOficial No. 36, Sección XI de fecha 31 de Diciembre de 1978, expedido por la Honorable IX\nLegislatura, siendo Gobernador Constitucional el C. Roberto de la Madrid Romandía, 19771983, ARTICULO 151-40.- Fue adicionado por Decreto No. 95, publicado en el Periódico\nOficial No. 36, Sección XI de fecha 31 de Diciembre de 1978, expedido por la Honorable IX\nLegislatura, siendo Gobernador Constitucional el C. Roberto de la Madrid Romandía, 19771983, ARTICULO 151-41.- Fue adicionado por Decreto No. 95, publicado en el Periódico\nOficial No. 36, Sección XI de fecha 31 de Diciembre de 1978, expedido por la Honorable IX\nLegislatura, siendo Gobernador Constitucional el C. Roberto de la Madrid Romandía, 19771983, Fue adicionada la denominación de este Capítulo, por Decreto No. 95, publicado en el\nPeriódico Oficial No. 36, de fecha 31 de Diciembre de 1978, expedido por la Honorable IX\nLegislatura, siendo Gobernador Constitucional el C. Roberto de la Madrid Romandía, 19771983;\nCAPITULO XVII\nIMPUESTO ADICIONAL PARA LA EDUCACION MEDIA Y SUPERIOR\nARTICULO 152.- Fue suspendida la vigencia de este artículo en lo que pague el IVA e Impuestos Federales, por Decreto No. 164, publicado en el Periódico Oficial No. 36,\nSección XI de fecha 31 de Diciembre de 1979, expedido por la Honorable IX Legislatura, siendo Gobernador Constitucional el C. Roberto de la Madrid Romandía, 1977-1983; fue reformado por Decreto No. 139, publicado en el Periódico Oficial No. 36, Sección XI de fecha\n31 de Diciembre de 1988, expedido por la Honorable XII Legislatura, siendo Gobernador\nConstitucional el C. Lic. Xicoténcatl Leyva Mortera, 1983 Enero de 1989; fue derogado por\nÍndice, Tomo CXXX, expedido por la H. XXIV Legislatura, siendo Gobernadora\nConstitucional la C. Marina del Pilar Ávila Olmeda 2021-2027;\nARTICULO 153.- Fue reformado por Decreto No. 139, publicado en el Periódico\nLegislatura, siendo Gobernador Constitucional el C. Lic. Xicoténcatl Leyva Mortera, 1983 siendo Gobernadora Constitucional la C. Marina del Pilar Ávila Olmeda 2021-2027;\nLey de Hacienda del Estado de Baja California. Página 107\n.\nActualización Legislativa.\nÚltima reforma P.O. No. 72, Índice, 22-Dic-2023\nARTICULO 154.- Fue derogado por Decreto No. 361, publicado en el Periódico Oficial\nNo. 72, de fecha 22 de diciembre de 2023, Índice, Tomo CXXX, expedido por la H. XXIV\nLegislatura, siendo Gobernadora Constitucional la C. Marina del Pilar Ávila Olmeda 20212027;\nARTICULO 155.- Fue reformado por Decreto No. 139, publicado en el Periódico\nOficial No. 36, Sección XI de fecha 31 de Diciembre de 1988, expedido por la Honorable XII\nLegislatura, siendo Gobernador Constitucional el C. Lic. Xicoténcatl Leyva Mortera, 1983\nEnero de 1989, fue reformado por Decreto No. 462, publicado en el Periódico Oficial No. 26, de fecha 07 de junio de 2013, Tomo CXX, Sección I, expedido por la Honorable XX\nLegislatura, siendo Gobernador Constitucional el C. Lic. José Guadalupe Osuna Millán, 2007-2013; fue derogado por Decreto No. 361, publicado en el Periódico Oficial No. 72, de fecha 22 de diciembre de 2023, Índice, Tomo CXXX, expedido por la H. XXIV Legislatura, siendo Gobernadora Constitucional la C. Marina del Pilar Ávila Olmeda 2021-2027;\nARTICULO 156.- Fue reformado por Decreto No. 82, publicado en el Periódico Oficial\nNo. 6, Sección I de fecha 28 de Febrero de 1973, expedido por la Honorable VII Legislatura, siendo Gobernador Constitucional el C. Lic. Milton Castellanos Everardo, 1971-1977; fue modificado por Decreto No. 62, publicado en el Periódico Oficial No. 17, de fecha 20 de\nJunio de 1975, expedido por la Honorable VIII Legislatura, siendo Gobernador Constitucional el C. Lic. Milton Castellanos Everardo, 1971-1977; fue reformado por Decreto No. 11, publicado en el Periódico Oficial No. 36, Sección XI de fecha 31 de Diciembre de 1980, expedido por la Honorable X Legislatura, siendo Gobernador Constitucional el C. Roberto de la Madrid Romandía, 1977-1983; fue reformado por Decreto No. 168, publicado en el\nPeriódico Oficial No. 60, de fecha 30 de diciembre de 2011, Tomo CXVIII, Sección II, expedido por la Honorable XX Legislatura, siendo Gobernador Constitucional el C. Lic. José\nGuadalupe Osuna Millán, 2007-2013; fue reformado por Decreto No. 462, publicado en el\nPeriódico Oficial No. 26, de fecha 07 de junio de 2013, Tomo CXX, Sección I, expedido por la Honorable XX Legislatura, siendo Gobernador Constitucional el C. Lic. José Guadalupe\nOsuna Millán, 2007-2013; fue derogado por Decreto No. 361, publicado en el Periódico\nOficial No. 72, de fecha 22 de diciembre de 2023, Índice, Tomo CXXX, expedido por la H.\nXXIV Legislatura, siendo Gobernadora Constitucional la C. Marina del Pilar Ávila Olmeda\n2021-2027;\nFue adicionada la denominación de este Capítulo, por Decreto No. 95, publicado en el\nLegislatura, siendo Gobernador Constitucional el C. Roberto de la Madrid Romandía, 19771983;\nCAPITULO XVIII\nBIENES Y SERVICIOS\nARTICULO 156-1.- Fue adicionado por Decreto No. 83, publicado en el Periódico\nLey de Hacienda del Estado de Baja California. Página 108\n.\nActualización Legislativa.\nÚltima reforma P.O. No. 72, Índice, 22-Dic-2023\nLegislatura, siendo Gobernador Constitucional el C. Lic. Milton Castellanos Everardo, 19711977; fue reformado por Decreto No. 22, publicado en el Periódico Oficial No. 36, de fecha\n31 de Diciembre de 1974, expedido por la Honorable VIII Legislatura, siendo Gobernador\nConstitucional el C. Lic. Milton Castellanos Everardo, 1971-1977;\nARTICULO 156-2.- Fue adicionado por Decreto No. 83, publicado en el Periódico\nOficial No. 6, Sección I de fecha 28 de Febrero de 1973, expedido por la Honorable VII\nLegislatura, siendo Gobernador Constitucional el C. Lic. Milton Castellanos Everardo 19711977; fue reformado por Decreto No. 22, publicado en el Periódico Oficial No. 36, de fecha\n31 de Diciembre de 1974, expedido por la Honorable VIII Legislatura, siendo Gobernador\nConstitucional el C. Lic. Milton Castellanos Everardo, 1971-1977;\nARTICULO 156-3.- Fue adicionado por Decreto No. 83, publicado en el Periódico\nOficial No. 6, Sección I de fecha 28 de Febrero de 1973, expedido por la Honorable VII\nLegislatura, siendo Gobernador Constitucional el C. Lic. Milton Castellanos Everardo, 19711977; fue reformado por Decreto No. 22, publicado en el Periódico Oficial No. 36, de fecha\n31 de Diciembre de 1974, expedido por la Honorable VIII Legislatura, siendo Gobernador\nConstitucional el C. Lic. Milton Castellanos Everardo, 1971-1977;\nARTICULO 156-4.- Fue adicionado por Decreto No. 83, publicado en el Periódico\nOficial No. 6, Sección I de fecha 28 de Febrero de 1973, expedido por la Honorable VII\nLegislatura, siendo Gobernador Constitucional, el C. Lic. Milton Castellanos Everardo, 19711977;\nARTICULO 156-5.- Fue adicionado por Decreto No. 83, publicado en el Periódico\nOficial No. 6, Sección I de fecha 28 de Febrero de 1973, expedido por la Honorable VII\nLegislatura, siendo Gobernador Constitucional el C. Lic. Milton Castellanos Everardo, 19711977;\nARTICULO 156-6.- Fue adicionado por Decreto No. 83, publicado en el Periódico\nOficial No. 6, Sección I de fecha 28 de Febrero de 1973, expedido por la Honorable VII\nLegislatura, siendo Gobernador Constitucional el C. Lic. Milton Castellanos Everardo, 19711977; Fue reformado por Decreto No. 240, publicado en el Periódico Oficial No. 52 de fecha\n4 de Diciembre de 2000, expedido por la Honorable XVI Legislatura del Estado, siendo reformado por Decreto No. 361, publicado en el Periódico Oficial No. 72, de fecha 22 de\nGobernadora Constitucional la C. Marina del Pilar Ávila Olmeda 2021-2027;\nARTICULO 156-7.- Fue adicionado por Decreto No. 98, publicado en el Periódico estando encargado del Despacho del Gobierno el C. Secretario General de Gobierno\nFrancisco Santana Peralta, y siendo Gobernador Constitucional el C. Lic. Milton Castellanos\nEverardo, 1971-1977;\nLey de Hacienda del Estado de Baja California. Página 109\n.\nActualización Legislativa.\nÚltima reforma P.O. No. 72, Índice, 22-Dic-2023\nFue adicionado este Capítulo por Decreto No. 108, publicado en el Periódico Oficial No. 1 de fecha 10 de Enero de 1992, expedido por la Honorable XIII Legislatura, estando encargado del despacho de Gobierno el C. Fortunato Álvarez Enríquez y siendo Gobernador\nConstitucional el C. L.A.E. Ernesto Ruffo Appel, 1989-1995; fue reformado eliminando la denominación de este Capítulo por Decreto No. 23, publicado en el Periódico Oficial No. 59, de fecha 06 de diciembre de 2019, Tomo CXXVI, Sección I, expedido por la H. XXIII\nLegislatura, siendo Gobernador Constitucional el C. Jaime Bonilla Valdez, 2019-2021;\nCAPITULO XIX\nFue adicionado por Decreto No. 23, publicado en el Periódico Oficial No. 59, de fecha 06 de diciembre de 2019, Tomo CXXVI, Sección I, expedido por la H. XXIII Legislatura, siendo\nGobernador Constitucional el C. Jaime Bonilla Valdez, 2019-2021;\nSECCIÓN PRIMERA\nDEL IMPUESTO A LAS EROGACIONES EN JUEGOS CON APUESTAS\nARTICULO 156-8.- Fue adicionado por Decreto No. 108, publicado en el Periódico\nOficial No. 1 de fecha 10 de Enero de 1992, expedido por la Honorable XIII Legislatura, estando encargado del despacho de Gobierno el C. Fortunato Álvarez Enríquez y siendo\nGobernador Constitucional el C. L.A.E. Ernesto Ruffo Appel, 1989-1995; fue reformado por\nDecreto No. 17, publicado en el Periódico Oficial No. 43, sección I, de fecha 31 de diciembre de 1992, expedido por la Honorable XIV Legislatura, siendo Gobernador Constitucional el C.\nL.A.E. Ernesto Ruffo Appel, 1989-1995; fue reformado por Decreto No. 23, publicado en el\nPeriódico Oficial No. 59, de fecha 06 de diciembre de 2019, Tomo CXXVI, Sección I, expedido por la H. XXIII Legislatura, siendo Gobernador Constitucional el C. Jaime Bonilla\nValdez, 2019-2021;\nARTÍCULO 156-8 BIS.- Fue adicionado por Decreto No. 23, publicado en el Periódico\nOficial No. 59, de fecha 06 de diciembre de 2019, Tomo CXXVI, Sección I, expedido por la\nH. XXIII Legislatura, siendo Gobernador Constitucional el C. Jaime Bonilla Valdez, 20192021;\nARTÍCULO 156-8 TER.- Fue adicionado por Decreto No. 23, publicado en el expedido por la H. XXIII Legislatura, siendo Gobernador Constitucional el C. Jaime Bonilla\nValdez, 2019-2021;\nARTÍCULO 156-8 QUATER.- Fue adicionado por Decreto No. 23, publicado en el expedido por la H. XXIII Legislatura, siendo Gobernador Constitucional el C. Jaime Bonilla\nValdez, 2019-2021;\nARTICULO 156-9.- Fue adicionado por Decreto No. 108, publicado en el Periódico\nLey de Hacienda del Estado de Baja California. Página 110\n.\nActualización Legislativa.\nÚltima reforma P.O. No. 72, Índice, 22-Dic-2023 estando encargado del despacho de Gobierno el C. Fortunato Álvarez Enríquez y siendo\nGobernador Constitucional el C. L.A.E. Ernesto Ruffo Appel, 1989-1995; fue reformado por\nDecreto No. 23, publicado en el Periódico Oficial No. 59, de fecha 06 de diciembre de 2019, Tomo CXXVI, Sección I, expedido por la H. XXIII Legislatura, siendo Gobernador\nConstitucional el C. Jaime Bonilla Valdez, 2019-2021; fue reformado por Decreto No. 62, publicado en el Periódico Oficial No. 22, de fecha 30 de abril de 2020, Tomo CXXVII, NÚMERO ESPECIAL, expedido por la Honorable XXIII Legislatura del Estado, siendo\nGobernador Constitucional el C. Jaime Bonilla Valdez, 2019-2021; fue reformado por\nDecreto No. 361, publicado en el Periódico Oficial No. 72, de fecha 22 de diciembre de 2023, Índice, Tomo CXXX, expedido por la H. XXIV Legislatura, siendo Gobernadora\nConstitucional la C. Marina del Pilar Ávila Olmeda 2021-2027;\nARTÍCULO 156-9 BIS.- Fue adicionado por Decreto No. 23, publicado en el Periódico\nOficial No. 59, de fecha 06 de diciembre de 2019, Tomo CXXVI, Sección I, expedido por la\nH. XXIII Legislatura, siendo Gobernador Constitucional el C. Jaime Bonilla Valdez, 20192021;\nARTÍCULO 156-9 TER.- Fue adicionado por Decreto No. 23, publicado en el\nPeriódico Oficial No. 59, de fecha 06 de diciembre de 2019, Tomo CXXVI, Sección I, expedido por la H. XXIII Legislatura, siendo Gobernador Constitucional el C. Jaime Bonilla\nValdez, 2019-2021;\nFue adicionado por Decreto No. 23, publicado en el Periódico Oficial No. 59, de fecha 06 de diciembre de 2019, Tomo CXXVI, Sección I, expedido por la H. XXIII Legislatura, siendo\nGobernador Constitucional el C. Jaime Bonilla Valdez, 2019-2021;\nSECCIÓN SEGUNDA\nDEL IMPUESTO POR LA REALIZACIÓN DE\nJUEGOS CON APUESTAS Y SORTEOS\nARTICULO 156-10.- Fue adicionado por Decreto No. 108, publicado en el Periódico\nOficial No. 1 de fecha 10 de Enero de 1992, expedido por la Honorable XIII Legislatura, estando encargado del despacho de Gobierno el C. Fortunato Álvarez Enríquez y siendo\nGobernador Constitucional el C. L.A.E. Ernesto Ruffo Appel, 1989-1995; fue reformado por\nDecreto No. 17, publicado en el Periódico Oficial No. 43, sección I, de fecha 31 de diciembre de 1992, expedido por la Honorable XIV Legislatura, siendo Gobernador Constitucional el C.\nL.A.E. Ernesto Ruffo Appel, 1989-1995; fue reformado por Decreto No. 23, publicado en el expedido por la H. XXIII Legislatura, siendo Gobernador Constitucional el C. Jaime Bonilla\nValdez, 2019-2021;\nARTÍCULO 156-10 BIS.- Fue adicionado por Decreto No. 23, publicado en el\nLey de Hacienda del Estado de Baja California. Página 111\n.\nActualización Legislativa.\nÚltima reforma P.O. No. 72, Índice, 22-Dic-2023 expedido por la H. XXIII Legislatura, siendo Gobernador Constitucional el C. Jaime Bonilla\nValdez, 2019-2021;\nARTÍCULO 156-10 TER.- Fue adicionado por Decreto No. 23, publicado en el\nPeriódico Oficial No. 59, de fecha 06 de diciembre de 2019, Tomo CXXVI, Sección I, expedido por la H. XXIII Legislatura, siendo Gobernador Constitucional el C. Jaime Bonilla\nValdez, 2019-2021;\nARTÍCULO 156-10 QUATER.- Fue adicionado por Decreto No. 23, publicado en el\nPeriódico Oficial No. 59, de fecha 06 de diciembre de 2019, Tomo CXXVI, Sección I, expedido por la H. XXIII Legislatura, siendo Gobernador Constitucional el C. Jaime Bonilla\nValdez, 2019-2021;\nARTICULO 156-11.- Fue adicionado por Decreto No. 108, publicado en el Periódico\nOficial No. 1 de fecha 10 de Enero de 1992, expedido por la Honorable XIII Legislatura, estando encargado del despacho de Gobierno el C. Fortunato Álvarez Enríquez y siendo\nGobernador Constitucional el C. L.A.E. Ernesto Ruffo Appel, 1989-1995; fue reformado por\nDecreto No. 17, publicado en el Periódico Oficial No. 43, sección I, de fecha 31 de diciembre de 1992, expedido por la Honorable XIV Legislatura, siendo Gobernador Constitucional el C.\nL.A.E. Ernesto Ruffo Appel, 1989-1995; fue reformado por Decreto No. 23, publicado en el\nPeriódico Oficial No. 59, de fecha 06 de diciembre de 2019, Tomo CXXVI, Sección I, expedido por la H. XXIII Legislatura, siendo Gobernador Constitucional el C. Jaime Bonilla\nValdez, 2019-2021;\nFue adicionado por Decreto No. 23, publicado en el Periódico Oficial No. 59, de fecha 06 de diciembre de 2019, Tomo CXXVI, Sección I, expedido por la H. XXIII Legislatura, siendo\nGobernador Constitucional el C. Jaime Bonilla Valdez, 2019-2021;\nSECCIÓN TERCERA\nDEL IMPUESTO POR OBTENCIÓN DE PREMIOS\nARTICULO 156-12.- Fue adicionado por Decreto No. 108, publicado en el Periódico estando encargado del despacho de Gobierno el C. Fortunato Álvarez Enríquez y siendo\nGobernador Constitucional el C. L.A.E. Ernesto Ruffo Appel, 1989-1995; fue reformado por\nDecreto No. 17, publicado en el Periódico Oficial No. 43, sección I, de fecha 31 de diciembre de 1992, expedido por la Honorable XIV Legislatura, siendo Gobernador Constitucional el C.\nL.A.E. Ernesto Ruffo Appel, 1989-1995; fue reformado por Decreto No. 23, publicado en el expedido por la H. XXIII Legislatura, siendo Gobernador Constitucional el C. Jaime Bonilla\nValdez, 2019-2021;\nLey de Hacienda del Estado de Baja California. Página 112\n.\nActualización Legislativa.\nÚltima reforma P.O. No. 72, Índice, 22-Dic-2023\nARTÍCULO 156-12 BIS.- Fue adicionado por Decreto No. 23, publicado en el\nPeriódico Oficial No. 59, de fecha 06 de diciembre de 2019, Tomo CXXVI, Sección I, expedido por la H. XXIII Legislatura, siendo Gobernador Constitucional el C. Jaime Bonilla\nValdez, 2019-2021;\nARTÍCULO 156-12 TER.- Fue adicionado por Decreto No. 23, publicado en el\nPeriódico Oficial No. 59, de fecha 06 de diciembre de 2019, Tomo CXXVI, Sección I, expedido por la H. XXIII Legislatura, siendo Gobernador Constitucional el C. Jaime Bonilla\nValdez, 2019-2021;\nARTICULO 156-13.- Fue adicionado por Decreto No. 108, publicado en el Periódico\nOficial No. 1 de fecha 10 de Enero de 1992, expedido por la Honorable XIII Legislatura, estando encargado del despacho de Gobierno el C. Fortunato Álvarez Enríquez y siendo\nGobernador Constitucional el C. L.A.E. Ernesto Ruffo Appel, 1989-1995; fue reformado por\nDecreto No. 17, publicado en el Periódico Oficial No. 43, sección I, de fecha 31 de diciembre de 1992, expedido por la Honorable XIV Legislatura, siendo Gobernador Constitucional el C.\nL.A.E. Ernesto Ruffo Appel, 1989-1995; Fue reformado por Decreto No. 240, publicado en el\nPeriódico Oficial No. 52 de fecha 4 de Diciembre de 2000, expedido por la Honorable XVI\nLegislatura del Estado, siendo Gobernador Constitucional el C. Lic. Alejandro González\nAlcocer, Octubre de 1998-2001; fue reformado por Decreto No. 133, publicado en el\nPeriódico Oficial No. 57, de fecha 31 de diciembre de 2002, Sección VIII, Tomo CIX, expedido por la Honorable XVII Legislatura, siendo Gobernador Constitucional el C. Lic.\nEugenio Elorduy Walther, 2001-2007, fue reformado por Decreto No. 23, publicado en el\nPeriódico Oficial No. 59, de fecha 06 de diciembre de 2019, Tomo CXXVI, Sección I, expedido por la H. XXIII Legislatura, siendo Gobernador Constitucional el C. Jaime Bonilla\nValdez, 2019-2021;\nARTICULO 156-14.- Fue adicionado por Decreto No. 108, publicado en el Periódico\nOficial No. 1, de fecha 10 de Enero de 1992, expedido por la Honorable XIII Legislatura, estando encargado del despacho de Gobierno el C. Fortunato Álvarez Enríquez y siendo\nGobernador Constitucional el C. L.A.E. Ernesto Ruffo Appel, 1989-1995; fue reformado por\nDecreto No. 23, publicado en el Periódico Oficial No. 59, de fecha 06 de diciembre de 2019, Tomo CXXVI, Sección I, expedido por la H. XXIII Legislatura, siendo Gobernador\nConstitucional el C. Jaime Bonilla Valdez, 2019-2021;\nFue adicionado este Capítulo por Decreto No. 144, publicado en el Periódico Oficial No. 57, Legislatura, siendo Gobernador Constitucional el C. Eugenio Elorduy Walther 2001-2007;\nFue derogado este Capítulo por Decreto 241, publicado en el Periódico Oficial No. 01, de\nGobernador Constitucional el C. Lic Eugenio Elorduy Walther 2001-2007; fue modificada la denominación de este Capítulo mediante Decreto No. 18, publicado en el Periódico Oficial\nLey de Hacienda del Estado de Baja California. Página 113\n.\nActualización Legislativa.\nÚltima reforma P.O. No. 72, Índice, 22-Dic-2023\nLegislatura, siendo Gobernador Constitucional el C. José Guadalupe Osuna Millán 20072013;\nCAPITULO XX\nDEL IMPUESTO ESTATAL SOBRE TENENCIA O USO DE VEHÍCULOS\nARTICULO 156-15.- Fue adicionado este Capítulo por Decreto No. 144, publicado en el Periódico Oficial No. 57, de fecha 31 de diciembre de 2002, Sección VIII, Tomo CIX, expedido por la H. XVII Legislatura, siendo Gobernador Constitucional el C. Eugenio Elorduy\nWalther 2001-2007; fue derogado por Decreto 241, publicado en el Periódico Oficial No. 01, de fecha 02 de enero de 2004, Tomo CXI expedido por la Honorable XVII Legislatura, siendo\nGobernador Constitucional el C. Lic. Eugenio Elorduy Walther 2001-2007; fue reformado por\nDecreto No. 18, publicado en el Periódico Oficial No. 58, de fecha 31 diciembre de 2010, Tomo CXVII, Sección VIII, expedido por la H. XX Legislatura, siendo Gobernador\nConstitucional el C. José Guadalupe Osuna Millán 2007-2013; fue reformado por Decreto\nNo. 168, publicado en el Periódico Oficial No. 60, de fecha 30 de diciembre de 2011, Tomo\nCXVIII, Sección II, expedido por la Honorable XX Legislatura, siendo Gobernador\nConstitucional el C. Lic. José Guadalupe Osuna Millán, 2007-2013;\nARTICULO 156-16.- Fue adicionado este Capítulo por Decreto No. 144, publicado en el Periódico Oficial No. 57, de fecha 31 de diciembre de 2002, Sección VIII, Tomo CIX, expedido por la H. XVII Legislatura, siendo Gobernador Constitucional el C. Eugenio Elorduy\nWalther 2001-2007; fue derogado por Decreto 241, publicado en el Periódico Oficial No. 01, de fecha 02 de enero de 2004, Tomo CXI expedido por la Honorable XVII Legislatura, siendo\nGobernador Constitucional el C. Lic. Eugenio Elorduy Walther 2001-2007; fue reformado por\nDecreto No. 18, publicado en el Periódico Oficial No. 58, de fecha 31 diciembre de 2010, Tomo CXVII, Sección VIII, expedido por la H. XX Legislatura, siendo Gobernador\nConstitucional el C. José Guadalupe Osuna Millán 2007-2013;\nARTICULO 156-17.- Fue adicionado este Capítulo por Decreto No. 144, publicado en el Periódico Oficial No. 57, de fecha 31 de diciembre de 2002, Sección VIII, Tomo CIX, expedido por la H. XVII Legislatura, siendo Gobernador Constitucional el C. Eugenio Elorduy\nWalther 2001-2007; fue derogado por Decreto 241, publicado en el Periódico Oficial No. 01, de fecha 02 de enero de 2004, Tomo CXI expedido por la Honorable XVII Legislatura, siendo\nGobernador Constitucional el C. Lic. Eugenio Elorduy Walther 2001-2007; fue reformado por\nTomo CXVII, Sección VIII, expedido por la H. XX Legislatura, siendo Gobernador\nConstitucional el C. José Guadalupe Osuna Millán 2007-2013;\nARTICULO 156-18.- Fue adicionado este Capítulo por Decreto No. 144, publicado en expedido por la H. XVII Legislatura, siendo Gobernador Constitucional el C. Eugenio Elorduy\nWalther 2001-2007; fue derogado por Decreto 241, publicado en el Periódico Oficial No. 01, de fecha 02 de enero de1 2004, Tomo CXI expedido por la Honorable XVII Legislatura, siendo Gobernador Constitucional el C. Lic. Eugenio Elorduy Walther 2001-2007; fue\nLey de Hacienda del Estado de Baja California. Página 114\n.\nActualización Legislativa.\nÚltima reforma P.O. No. 72, Índice, 22-Dic-2023 reformado por Decreto No. 18, publicado en el Periódico Oficial No. 58, de fecha 31 diciembre de 2010, Tomo CXVII, Sección VIII, expedido por la H. XX Legislatura, siendo\nGobernador Constitucional el C. José Guadalupe Osuna Millán 2007-2013;\nARTICULO 156-19.- Fue adicionado este Capítulo por Decreto No. 144, publicado en el Periódico Oficial No. 57, de fecha 31 de diciembre de 2002, Sección VIII, Tomo CIX, expedido por la H. XVII Legislatura, siendo Gobernador Constitucional el C. Eugenio Elorduy\nWalther 2001-2007; Fue reformado por Decreto No. 18, publicado en el Periódico Oficial No.\n58, de fecha 31 diciembre de 2010, Tomo CXVII, Sección VIII, expedido por la H. XX\nLegislatura, siendo Gobernador Constitucional el C. José Guadalupe Osuna Millán 20072013; fue reformado por Decreto No. 361, publicado en el Periódico Oficial No. 72, de fecha\n22 de diciembre de 2023, Índice, Tomo CXXX, expedido por la H. XXIV Legislatura, siendo\nGobernadora Constitucional la C. Marina del Pilar Ávila Olmeda 2021-2027;\nARTICULO 156-20.- Fue adicionado este Capítulo por Decreto No. 144, publicado en el Periódico Oficial No. 57, de fecha 31 de diciembre de 2002, Sección VIII, Tomo CIX, expedido por la H. XVII Legislatura, siendo Gobernador Constitucional el C. Eugenio Elorduy\nWalther 2001-2007; fue derogado por Decreto 241, publicado en el Periódico Oficial No. 01, de fecha 02 de enero de1 2004, Tomo CXI expedido por la Honorable XVII Legislatura, siendo Gobernador Constitucional el C. Lic. Eugenio Elorduy Walther 2001-2007; fue reformado por Decreto No. 18, publicado en el Periódico Oficial No. 58, de fecha 31 diciembre de 2010, Tomo CXVII, Sección VIII, expedido por la H. XX Legislatura, siendo\nGobernador Constitucional el C. José Guadalupe Osuna Millán 2007-2013;\nARTICULO 156-21.- Fue adicionado este Capítulo por Decreto No. 144, publicado en el Periódico Oficial No. 57, de fecha 31 de diciembre de 2002, Sección VIII, Tomo CIX, expedido por la H. XVII Legislatura, siendo Gobernador Constitucional el C. Eugenio Elorduy\nWalther 2001-2007; fue derogado por Decreto 241, publicado en el Periódico Oficial No. 01, de fecha 02 de enero de1 2004, Tomo CXI expedido por la Honorable XVII Legislatura, siendo Gobernador Constitucional el C. Lic. Eugenio Elorduy Walther 2001-2007; fue reformado por Decreto No. 18, publicado en el Periódico Oficial No. 58, de fecha 31 diciembre de 2010, Tomo CXVII, Sección VIII, expedido por la H. XX Legislatura, siendo\nGobernador Constitucional el C. José Guadalupe Osuna Millán 2007-2013;\nARTICULO 156-22.- Fue adicionado por Decreto No. 18, publicado en el Periódico\nXX Legislatura, siendo Gobernador Constitucional el C. José Guadalupe Osuna Millán 20072013;\nARTICULO 156-23.- Fue adicionado por Decreto No. 18, publicado en el Periódico\nXX Legislatura, siendo Gobernador Constitucional el C. José Guadalupe Osuna Millán 20072013;\nLey de Hacienda del Estado de Baja California. Página 115\n.\nActualización Legislativa.\nÚltima reforma P.O. No. 72, Índice, 22-Dic-2023\nARTICULO 156-24.- Fue adicionado por Decreto No. 18, publicado en el Periódico\nOficial No. 58, de fecha 31 diciembre de 2010, Tomo CXVII, Sección VIII, expedido por la H.\nXX Legislatura, siendo Gobernador Constitucional el C. José Guadalupe Osuna Millán 20072013;\nARTICULO 156-25.- Fue adicionado por Decreto No. 18, publicado en el Periódico\nOficial No. 58, de fecha 31 diciembre de 2010, Tomo CXVII, Sección VIII, expedido por la H.\nXX Legislatura, siendo Gobernador Constitucional el C. José Guadalupe Osuna Millán 20072013;\nARTICULO 156-26.- Fue adicionado por Decreto No. 18, publicado en el Periódico\nOficial No. 58, de fecha 31 diciembre de 2010, Tomo CXVII, Sección VIII, expedido por la H.\nXX Legislatura, siendo Gobernador Constitucional el C. José Guadalupe Osuna Millán 20072013;\nARTICULO 156-27.- Fue adicionado por Decreto No. 18, publicado en el Periódico\nOficial No. 58, de fecha 31 diciembre de 2010, Tomo CXVII, Sección VIII, expedido por la H.\nXX Legislatura, siendo Gobernador Constitucional el C. José Guadalupe Osuna Millán 20072013;\nARTICULO 156-28.- Fue adicionado por Decreto No. 18, publicado en el Periódico\nOficial No. 58, de fecha 31 diciembre de 2010, Tomo CXVII, Sección VIII, expedido por la H.\nXX Legislatura, siendo Gobernador Constitucional el C. José Guadalupe Osuna Millán 20072013; fue reformado por Decreto No. 361, publicado en el Periódico Oficial No. 72, de fecha\n22 de diciembre de 2023, Índice, Tomo CXXX, expedido por la H. XXIV Legislatura, siendo\nGobernadora Constitucional la C. Marina del Pilar Ávila Olmeda 2021-2027;\nARTICULO 156-29.- Fue adicionado por Decreto No. 18, publicado en el Periódico\nOficial No. 58, de fecha 31 diciembre de 2010, Tomo CXVII, Sección VIII, expedido por la H.\nXX Legislatura, siendo Gobernador Constitucional el C. José Guadalupe Osuna Millán 20072013; fue reformado por Decreto No. 361, publicado en el Periódico Oficial No. 72, de fecha\n22 de diciembre de 2023, Índice, Tomo CXXX, expedido por la H. XXIV Legislatura, siendo\nGobernadora Constitucional la C. Marina del Pilar Ávila Olmeda 2021-2027;\nARTICULO 156-30.- Fue adicionado por Decreto No. 18, publicado en el Periódico\nXX Legislatura, siendo Gobernador Constitucional el C. José Guadalupe Osuna Millán 20072013;\nARTICULO 156-31.- Fue adicionado por Decreto No. 18, publicado en el Periódico\nXX Legislatura, siendo Gobernador Constitucional el C. José Guadalupe Osuna Millán 20072013; fue reformado por Decreto No. 361, publicado en el Periódico Oficial No. 72, de fecha\nGobernadora Constitucional la C. Marina del Pilar Ávila Olmeda 2021-2027;\nLey de Hacienda del Estado de Baja California. Página 116\n.\nActualización Legislativa.\nÚltima reforma P.O. No. 72, Índice, 22-Dic-2023\nARTICULO 156-32.- Fue adicionado por Decreto No. 18, publicado en el Periódico\nOficial No. 58, de fecha 31 diciembre de 2010, Tomo CXVII, Sección VIII, expedido por la H.\nXX Legislatura, siendo Gobernador Constitucional el C. José Guadalupe Osuna Millán 20072013; fue reformado por Decreto No. 361, publicado en el Periódico Oficial No. 72, de fecha\n22 de diciembre de 2023, Índice, Tomo CXXX, expedido por la H. XXIV Legislatura, siendo\nGobernadora Constitucional la C. Marina del Pilar Ávila Olmeda 2021-2027;\nFue adicionado por Decreto No. 169, publicado en el Periódico Oficial No. 60, de fecha 30 diciembre de 2011, Tomo CXVIII, Sección II, expedido por la H. XX Legislatura, siendo\nGobernador Constitucional el C. José Guadalupe Osuna Millán 2007-2013;\nCAPÍTULO XXI\nDEL IMPUESTO ESTATAL A LA VENTA FINAL DE BEBIDAS CON CONTENIDO\nALCOHÓLICO\nARTICULO 156-33.- Fue adicionado por Decreto No. 169, publicado en el Periódico\nOficial No. 60, de fecha 30 diciembre de 2011, Tomo CXVIII, Sección II, expedido por la H.\nXX Legislatura, siendo Gobernador Constitucional el C. José Guadalupe Osuna Millán 20072013;\nARTICULO 156-34.- Fue adicionado por Decreto No. 169, publicado en el Periódico\nOficial No. 60, de fecha 30 diciembre de 2011, Tomo CXVIII, Sección II, expedido por la H.\nXX Legislatura, siendo Gobernador Constitucional el C. José Guadalupe Osuna Millán 20072013;\nARTICULO 156-35.- Fue adicionado por Decreto No. 169, publicado en el Periódico\nOficial No. 60, de fecha 30 diciembre de 2011, Tomo CXVIII, Sección II, expedido por la H.\nXX Legislatura, siendo Gobernador Constitucional el C. José Guadalupe Osuna Millán 20072013;\nARTICULO 156-36.- Fue adicionado por Decreto No. 169, publicado en el Periódico\nOficial No. 60, de fecha 30 diciembre de 2011, Tomo CXVIII, Sección II, expedido por la H.\nXX Legislatura, siendo Gobernador Constitucional el C. José Guadalupe Osuna Millán 20072013;\nARTICULO 156-37.- Fue adicionado por Decreto No. 169, publicado en el Periódico\nXX Legislatura, siendo Gobernador Constitucional el C. José Guadalupe Osuna Millán 20072013;\nARTICULO 156-38.- Fue adicionado por Decreto No. 169, publicado en el Periódico\nXX Legislatura, siendo Gobernador Constitucional el C. José Guadalupe Osuna Millán 20072013;\nLey de Hacienda del Estado de Baja California. Página 117\n.\nActualización Legislativa.\nÚltima reforma P.O. No. 72, Índice, 22-Dic-2023\nARTICULO 156-39.- Fue adicionado por Decreto No. 169, publicado en el Periódico\nOficial No. 60, de fecha 30 diciembre de 2011, Tomo CXVIII, Sección II, expedido por la H.\nXX Legislatura, siendo Gobernador Constitucional el C. José Guadalupe Osuna Millán 20072013;\nARTICULO 156-40.- Fue adicionado por Decreto No. 169, publicado en el Periódico\nOficial No. 60, de fecha 30 diciembre de 2011, Tomo CXVIII, Sección II, expedido por la H.\nXX Legislatura, siendo Gobernador Constitucional el C. José Guadalupe Osuna Millán 20072013;\nARTICULO 156-41.- Fue adicionado por Decreto No. 169, publicado en el Periódico\nOficial No. 60, de fecha 30 diciembre de 2011, Tomo CXVIII, Sección II, expedido por la H.\nXX Legislatura, siendo Gobernador Constitucional el C. José Guadalupe Osuna Millán 20072013;\nARTICULO 156-42.- Fue adicionado por Decreto No. 169, publicado en el Periódico\nOficial No. 60, de fecha 30 diciembre de 2011, Tomo CXVIII, Sección II, expedido por la H.\nXX Legislatura, siendo Gobernador Constitucional el C. José Guadalupe Osuna Millán 20072013; fue reformado por Decreto No. 361, publicado en el Periódico Oficial No. 72, de fecha\n22 de diciembre de 2023, Índice, Tomo CXXX, expedido por la H. XXIV Legislatura, siendo\nGobernadora Constitucional la C. Marina del Pilar Ávila Olmeda 2021-2027;\nARTICULO 156-43.- Fue adicionado por Decreto No. 169, publicado en el Periódico\nOficial No. 60, de fecha 30 diciembre de 2011, Tomo CXVIII, Sección II, expedido por la H.\nXX Legislatura, siendo Gobernador Constitucional el C. José Guadalupe Osuna Millán 20072013;\nARTICULO 156-44.- Fue adicionado por Decreto No. 169, publicado en el Periódico\nOficial No. 60, de fecha 30 diciembre de 2011, Tomo CXVIII, Sección II, expedido por la H.\nXX Legislatura, siendo Gobernador Constitucional el C. José Guadalupe Osuna Millán 20072013; fue derogado por Decreto No. 361, publicado en el Periódico Oficial No. 72, de fecha\n22 de diciembre de 2023, Índice, Tomo CXXX, expedido por la H. XXIV Legislatura, siendo\nGobernadora Constitucional la C. Marina del Pilar Ávila Olmeda 2021-2027;\nARTICULO 156-45.- Fue adicionado por Decreto No. 169, publicado en el Periódico\nXX Legislatura, siendo Gobernador Constitucional el C. José Guadalupe Osuna Millán 20072013;\nFue adicionado por Decreto No. 39, publicado en el Periódico Oficial No. 67, de fecha 31 de del Estado, siendo Gobernador Constitucional el C. Jaime Bonilla Valdez, 2019-2021;\nCAPITULO XXII\nSECCIÓN PRIMERA\nIMPUESTO A CASAS DE EMPEÑO\nLey de Hacienda del Estado de Baja California. Página 118\n.\nActualización Legislativa.\nÚltima reforma P.O. No. 72, Índice, 22-Dic-2023\nDE LOS SUJETOS Y EL OBJETO\nARTICULO 156-46.- Fue adicionado por Decreto No. 39, publicado en el Periódico\nOficial No. 67, de fecha 31 de diciembre de 2019, Tomo CXXVI, Sección VIII, expedido por la Honorable XXIII Legislatura del Estado, siendo Gobernador Constitucional el C. Jaime\nBonilla Valdez, 2019-2021;\nFue adicionado por Decreto No. 39, publicado en el Periódico Oficial No. 67, de fecha 31 de diciembre de 2019, Tomo CXXVI, Sección VIII, expedido por la Honorable XXIII Legislatura del Estado, siendo Gobernador Constitucional el C. Jaime Bonilla Valdez, 2019-2021;\nSECCIÓN SEGUNDA\nDE LA BASE GRAVABLE, TASA Y ÉPOCA DE PAGO\nARTICULO 156-47.- Fue adicionado por Decreto No. 39, publicado en el Periódico\nOficial No. 67, de fecha 31 de diciembre de 2019, Tomo CXXVI, Sección VIII, expedido por la Honorable XXIII Legislatura del Estado, siendo Gobernador Constitucional el C. Jaime\nBonilla Valdez, 2019-2021;\nARTICULO 156-48.- Fue adicionado por Decreto No. 39, publicado en el Periódico\nOficial No. 67, de fecha 31 de diciembre de 2019, Tomo CXXVI, Sección VIII, expedido por la Honorable XXIII Legislatura del Estado, siendo Gobernador Constitucional el C. Jaime\nBonilla Valdez, 2019-2021; fue reformado por Decreto No. 62, publicado en el Periódico\nOficial No. 22, de fecha 30 de abril de 2020, Tomo CXXVII, NÚMERO ESPECIAL, expedido por la Honorable XXIII Legislatura del Estado, siendo Gobernador Constitucional el C. Jaime\nBonilla Valdez, 2019-2021;\nFue adicionado por Decreto No. 39, publicado en el Periódico Oficial No. 67, de fecha 31 de diciembre de 2019, Tomo CXXVI, Sección VIII, expedido por la Honorable XXIII Legislatura del Estado, siendo Gobernador Constitucional el C. Jaime Bonilla Valdez, 2019-2021;\nSECCIÓN TERCERA\nDE LAS OBLIGACIONES DE LOS CONTRIBUYENTES\nARTICULO 156-49.- Fue adicionado por Decreto No. 39, publicado en el Periódico la Honorable XXIII Legislatura del Estado, siendo Gobernador Constitucional el C. Jaime\nBonilla Valdez, 2019-2021;\nFue adicionado por Decreto No. 63, publicado en el Periódico Oficial No. 22, de fecha\nLegislatura del Estado, siendo Gobernador Constitucional el C. Jaime Bonilla Valdez, 20192021;\nCAPÍTULO XXIII\nIMPUESTO A EMPRESAS DE REDES DE TRANSPORTE\nLey de Hacienda del Estado de Baja California. Página 119\n.\nActualización Legislativa.\nÚltima reforma P.O. No. 72, Índice, 22-Dic-2023\nARTÍCULO 156-50.- Fue adicionado por Decreto No. 63, publicado en el Periódico\nOficial No. 22, de fecha 30 de abril de 2020, Tomo CXXVII, NÚMERO ESPECIAL, expedido por la Honorable XXIII Legislatura del Estado, siendo Gobernador Constitucional el C. Jaime\nBonilla Valdez, 2019-2021;\nARTÍCULO 156-51.- Fue adicionado por Decreto No. 63, publicado en el Periódico\nOficial No. 22, de fecha 30 de abril de 2020, Tomo CXXVII, NÚMERO ESPECIAL, expedido por la Honorable XXIII Legislatura del Estado, siendo Gobernador Constitucional el C. Jaime\nBonilla Valdez, 2019-2021;\nARTÍCULO 156-52.- Fue adicionado por Decreto No. 63, publicado en el Periódico\nOficial No. 22, de fecha 30 de abril de 2020, Tomo CXXVII, NÚMERO ESPECIAL, expedido por la Honorable XXIII Legislatura del Estado, siendo Gobernador Constitucional el C. Jaime\nBonilla Valdez, 2019-2021;\nARTÍCULO 156-53.- Fue adicionado por Decreto No. 63, publicado en el Periódico\nOficial No. 22, de fecha 30 de abril de 2020, Tomo CXXVII, NÚMERO ESPECIAL, expedido por la Honorable XXIII Legislatura del Estado, siendo Gobernador Constitucional el C. Jaime\nBonilla Valdez, 2019-2021;\nARTÍCULO 156-54.- Fue adicionado por Decreto No. 63, publicado en el Periódico\nOficial No. 22, de fecha 30 de abril de 2020, Tomo CXXVII, NÚMERO ESPECIAL, expedido por la Honorable XXIII Legislatura del Estado, siendo Gobernador Constitucional el C. Jaime\nBonilla Valdez, 2019-2021;\nFue adicionado por Decreto No. 84, publicado en el Periódico Oficial No. 17, de fecha 04 de marzo de 2022, Tomo CXXIX, Sección I, expedido por la H. XXIV Legislatura, siendo\nGobernadora Constitucional la C. Marina del Pilar Ávila Olmeda 2021-2027;\nCAPÍTULO XXIV\nIMPUESTO AMBIENTAL SOBRE LA EXTRACCIÓN Y\nAPROVECHAMIENTO DE MATERIALES PÉTREOS\nARTÍCULO 156-55.- Fue adicionado por Decreto No. 84, publicado en el Periódico\nXXIV Legislatura, siendo Gobernadora Constitucional la C. Marina del Pilar Ávila Olmeda\n2021-2027;\nARTÍCULO 156-56.- Fue adicionado por Decreto No. 84, publicado en el Periódico\nXXIV Legislatura, siendo Gobernadora Constitucional la C. Marina del Pilar Ávila Olmeda\n2021-2027;\nLey de Hacienda del Estado de Baja California. Página 120\n.\nActualización Legislativa.\nÚltima reforma P.O. No. 72, Índice, 22-Dic-2023\nARTÍCULO 156-57.- Fue adicionado por Decreto No. 84, publicado en el Periódico\nOficial No. 17, de fecha 04 de marzo de 2022, Tomo CXXIX, Sección I, expedido por la H.\nXXIV Legislatura, siendo Gobernadora Constitucional la C. Marina del Pilar Ávila Olmeda\n2021-2027;\nARTÍCULO 156-58.- Fue adicionado por Decreto No. 84, publicado en el Periódico\nOficial No. 17, de fecha 04 de marzo de 2022, Tomo CXXIX, Sección I, expedido por la H.\nXXIV Legislatura, siendo Gobernadora Constitucional la C. Marina del Pilar Ávila Olmeda\n2021-2027;\nARTÍCULO 156-59.- Fue adicionado por Decreto No. 84, publicado en el Periódico\nOficial No. 17, de fecha 04 de marzo de 2022, Tomo CXXIX, Sección I, expedido por la H.\nXXIV Legislatura, siendo Gobernadora Constitucional la C. Marina del Pilar Ávila Olmeda\n2021-2027;\nARTÍCULO 156-60.- Fue adicionado por Decreto No. 84, publicado en el Periódico\nOficial No. 17, de fecha 04 de marzo de 2022, Tomo CXXIX, Sección I, expedido por la H.\nXXIV Legislatura, siendo Gobernadora Constitucional la C. Marina del Pilar Ávila Olmeda\n2021-2027;\nARTICULO 157.- Fue reformado por Decreto No. 206, publicado en el Periódico\nOficial No. 4, de fecha 10 de Febrero de 1977, expedido por la Honorable VIII Legislatura, siendo Gobernador Constitucional el C. Lic. Milton Castellanos Everardo, 1971-1977; fue reformado por Decreto No. 124, publicado en el Periódico Oficial No. 21 de fecha 31 de Julio de 1982, expedido por la Honorable X Legislatura, siendo Gobernador Constitucional el C.\nRoberto de la Madrid Romandía, 1977-1983; fue reformado por Decreto No. 139, publicado en el Periódico Oficial No. 36, Sección XI de fecha 31 de Diciembre de 1988, expedido por la\nHonorable XII Legislatura, siendo Gobernador Constitucional el C. Lic. Xicoténcatl Leyva\nMortera, 1983-Enero de 1989, fue reformado por Decreto No. 409, publicado en el Periódico\nOficial No. 11, de fecha 22 de febrero de 2013, Tomo CXX, expedido por la Honorable XX\nLegislatura, siendo Gobernador Constitucional el C. Lic. José Guadalupe Osuna Millán, 2007-2013;\nARTICULO 158.- Fue reformado por Decreto No. 139, publicado en el Periódico\nLegislatura, siendo Gobernador Constitucional el C. Lic. Xicoténcatl Leyva Mortera, 1983siendo Gobernador Constitucional el C. Lic. José Guadalupe Osuna Millán, 2007-2013; fue reformado por Decreto No. 56, publicado en el Periódico Oficial No. 58, de fecha 30 de\nGobernador Constitucional el C. Francisco Arturo Vega de Lamadrid 2013-2019; fue reformado por Decreto No. 66, publicado en el Periódico Oficial No. 4, de fecha 19 de enero\nLey de Hacienda del Estado de Baja California. Página 121\n.\nActualización Legislativa.\nÚltima reforma P.O. No. 72, Índice, 22-Dic-2023 de 2017, Número Especial, Tomo CXXIV, expedido por la H. XXII Legislatura, siendo\nGobernador Constitucional el C. Francisco Arturo Vega de Lamadrid 2013-2019;\nARTICULO 160.- Fue reformado por Decreto No. 124, publicado en el Periódico\nOficial No. 21 de fecha 31 de Julio de 1982, expedido por la Honorable X Legislatura, siendo\nGobernador Constitucional el C. Roberto de la Madrid Romandía, 1977-1983; fue reformado por Decreto No. 139, publicado en el Periódico Oficial No. 36, Sección XI de fecha 31 de\nDiciembre de 1988, expedido por la Honorable XII Legislatura, siendo Gobernador\nConstitucional el C. Lic. Xicoténcatl Leyva Mortera, 1983-Enero de 1989, ARTICULO 161.- Fue derogado por Decreto No. 139, publicado en el Periódico Oficial\nNo. 36, Sección XI de fecha 31 de Diciembre de 1988, expedido por la Honorable XII\nLegislatura, siendo Gobernador Constitucional el C. Lic. Xicoténcatl Leyva Mortera, 1983enero de 1989, ARTICULO 162.- Fue derogado por Decreto No. 139, publicado en el Periódico Oficial\nNo. 36, Sección XI de fecha 31 de Diciembre de 1988, expedido por la Honorable XII\nLegislatura, siendo Gobernador Constitucional el C. Lic. Xicoténcatl Leyva Mortera, 1983enero de 1989, ARTICULO 165.- Fue reformado por Decreto No. 139, publicado en el Periódico\nOficial No. 36, Sección XI de fecha 31 de Diciembre de 1988, expedido por la Honorable XII\nLegislatura, siendo Gobernador Constitucional el C. Lic. Xicoténcatl Leyva Mortera, 1983enero de 1989, ARTICULO 169.- Fue reformado por Decreto No. 139, publicado en el Periódico\nOficial No. 36, Sección XI de fecha 31 de Diciembre de 1988, expedido por la Honorable XII\nLegislatura, siendo Gobernador Constitucional el C. Lic. Xicoténcatl Leyva Mortera, 1983Enero de 1989, ARTICULO 170.- Fue reformado por Decreto No. 139, publicado en el Periódico\nOficial No. 36, Sección XI de fecha 31 de Diciembre de 1988, expedido por la Honorable XII\nLegislatura, siendo Gobernador Constitucional el C. Lic. Xicoténcatl Leyva Mortera, 1983Enero de 1989;\nFue adicionado este Título por Decreto No. 93, Publicado en el Periódico Oficial No. 30, de\nConstitucional el C. L.A.E. Ernesto Ruffo Appel 1989-1995, fue modificada la denominación de este Capítulo por Decreto No. 45, Publicado en el Periódico Oficial No. 61, Tomo CIII, de\nConstitucional el C. Lic. Héctor Terán Terán, 1995-1998; fue adicionada la denominación por\nDecreto No. 170, publicado en el Periódico Oficial No. 8, de fecha 25 de febrero del 2000, Tomo CVII, expedido por la H. XVI Legislatura, siendo Gobernado Constitucional el C. Lic.\nTITULO NOVENO\nLey de Hacienda del Estado de Baja California. Página 122\n.\nActualización Legislativa.\nÚltima reforma P.O. No. 72, Índice, 22-Dic-2023\nDE LOS ESTIMULOS Y LAS EXENCIONES DE PAGO\nARTICULO 172.- Fue adicionado por Decreto No. 93, Publicado en el Periódico\nOficial No. 30, de fecha 31 de Octubre de 1991, expedido por la Honorable XIII Legislatura, siendo Gobernador Constitucional el C. L.A.E. Ernesto Ruffo Appel, 1989-1995; fue reformado por Decreto No. 53; publicado en el Periódico Oficial No. 38, de fecha 17 de septiembre de 1993, expedido por la Honorable XIV Legislatura, siendo Gobernador\nConstitucional el C. L.A.E. Ernesto Ruffo Appel, 1989-1995; fue reformado por Decreto No.\n45; publicado en el Periódico Oficial No. 61, Tomo CIII, de fecha 27 de diciembre de 1996, expedido por la Honorable XV Legislatura, siendo Gobernador Constitucional el C. Lic.\nHéctor Terán Terán, 1995-1998 fue reformada por Decreto No. 170, publicado en el\nPeriódico Oficial No. 8, de fecha 25 de febrero del 2000, Tomo CVII, expedido por la H. XVI\nLegislatura, siendo Gobernador Constitucional el C. Lic. Alejandro González Alcocer 7 de octubre de 1998-2001, fue reformada por Decreto No. 55, publicado en el Periódico Oficial\nNo. 27, de fecha 10 de Junio de 2005, Tomo CXII, expedido por la H. XVIII Legislatura siendo Gobernador Constitucional el C. Eugenio Elorduy Walter 2001-2007; fue reformado por Decreto No. 101, publicado en el Periódico Oficial No. 51, de fecha 28 de octubre de\n2011, Tomo CXVIII, Sección II, expedido por la H. XX Legislatura, siendo Gobernador\nConstitucional el C. José Guadalupe Osuna Millán 2007-2013; fue reformado por Decreto\nNo. 168, publicado en el Periódico Oficial No. 60, de fecha 30 de diciembre de 2011, Tomo\nCXVIII, Sección II, expedido por la Honorable XX Legislatura, siendo Gobernador\nConstitucional el C. Lic. José Guadalupe Osuna Millán, 2007-2013;\nARTICULO 173.- Fue adicionado por Decreto No. 93, Publicado en el Periódico\nOficial No. 30, de fecha 31 de Octubre de 1991, expedido por la Honorable XIII Legislatura, siendo Gobernador Constitucional el C. L.A.E. Ernesto Ruffo Appel, 1989-1995; fue reformado por Decreto No. 45; publicado en el Periódico Oficial No. 61, Tomo CIII, de fecha\n27 de diciembre de 1996, expedido por la Honorable XV Legislatura, siendo Gobernador\nConstitucional el C. Lic. Héctor Terán Terán, 1995-1998; fue reformado por Decreto No. 63, publicado en el Periódico Oficial No. 62, Tomo CIII, de fecha 31 de diciembre de 1996, expedido por la Honorable XV Legislatura, siendo Gobernador Constitucional el C. Lic.\nHéctor Terán Terán, 1995-1998; fue reformada por Decreto No. 170, publicado en el\nPeriódico Oficial No. 8, de fecha 25 de febrero del 2000, Tomo CVII, expedido por la H. XVI\nLegislatura, siendo Gobernador Constitucional el C. Lic. Alejandro González Alcocer 7 de octubre de 1998-2001; Fue reformado por Decreto No. 369, publicado en el Periódico Oficial siendo Gobernador Constitucional el c. Lic. Alejandro González Alcocer 1998-2001; fue reformada por Decreto No. 55, publicado en el Periódico Oficial No. 27, de fecha 10 de Junio de 2005, Tomo CXII, expedido por la H. XVIII Legislatura siendo Gobernador Constitucional el C. Eugenio Elorduy Walter 2001-2007; fue reformado por Decreto No. 101, publicado en el por la H. XX Legislatura, siendo Gobernador Constitucional el C. José Guadalupe Osuna\nMillán 2007-2013; fue reformado por Decreto No. 168, publicado en el Periódico Oficial No.\nLey de Hacienda del Estado de Baja California. Página 123\n.\nActualización Legislativa.\nÚltima reforma P.O. No. 72, Índice, 22-Dic-2023\nXX Legislatura, siendo Gobernador Constitucional el C. Lic. José Guadalupe Osuna Millán, 2007-2013; reformado por Decreto No. 363, publicado en el Periódico Oficial No. 57, de fecha 21 de diciembre de 2012, Tomo CXIX, expedido por la Honorable XX Legislatura, siendo Gobernador Constitucional el C. Lic. José Guadalupe Osuna Millán, 2007-2013; fue reformado por Decreto No. 282, publicado en el Periódico Oficial No. 25, de fecha 29 de mayo de 2015, Sección I, Tomo CXXII, expedido por la H. XXI Legislatura, siendo\nGobernador Constitucional el C. Francisco Arturo Vega de Lamadrid 2013-2019; fue reformado por Decreto No. 281, publicado en el Periódico Oficial No. 55, de fecha 30 de noviembre de 2018, Tomo CXXV, Sección IV, expedido por la Honorable Legislatura XXII, siendo Gobernador Constitucional el C. Francisco Arturo Vega de Lamadrid 2013-2019;\nARTICULO 174.- Fue adicionado por Decreto No. 93, Publicado en el Periódico\nOficial No. 30, de fecha 31 de Octubre de 1991, expedido por la Honorable XIII Legislatura, siendo Gobernador Constitucional el C. L.A.E. Ernesto Ruffo Appel, 1989-1995; fue reformado por Decreto No. 45; publicado en el Periódico Oficial No. 61, Tomo CIII, de fecha\n27 de diciembre de 1996, expedido por la Honorable XV Legislatura, siendo Gobernador\nConstitucional el C. Lic. Héctor Terán Terán, 1995-1998; fue reformada por Decreto No. 170, publicado en el Periódico Oficial No. 8, de fecha 25 de febrero del 2000, Tomo CVII, expedido por la H. XVI Legislatura, siendo Gobernador Constitucional el C. Lic. Alejandro\nGonzález Alcocer 7 de octubre de 1998-2001; fue reformada por Decreto No. 55, publicado en el Periódico Oficial No. 27, de fecha 10 de Junio de 2005, Tomo CXII, expedido por la H.\nXVIII Legislatura siendo Gobernador Constitucional el C. Eugenio Elorduy Walter 2001-2007; fue reformado por Decreto No. 101, publicado en el Periódico Oficial No. 51, de fecha 28 de octubre de 2011, Tomo CXVIII, Sección II, expedido por la H. XX Legislatura, siendo\nGobernador Constitucional el C. José Guadalupe Osuna Millán 2007-2013;\nARTÍCULO 174 BIS.- Fue adicionado por Decreto No. 258, publicado en el Periódico\nOficial No. 28, de fecha 12 de junio de 2015, Tomo CXXII, expedido por la H. XXI\nLegislatura, siendo Gobernador Constitucional el C. Francisco Arturo Vega de Lamadrid\n2013-2019;\nARTICULO 175.- Fue adicionado por Decreto No. 93, Publicado en el Periódico\nOficial No. 30, de fecha 31 de Octubre de 1991, expedido por la Honorable XIII Legislatura, siendo Gobernador Constitucional el C. L.A.E. Ernesto Ruffo Appel, 1989-1995; fue reformado por Decreto No. 45; publicado en el Periódico Oficial No. 61, Tomo CIII, de fecha\nConstitucional el C. Lic. Héctor Terán Terán, 1995-1998; fue reformada por Decreto No. 170, publicado en el Periódico Oficial No. 8, de fecha 25 de febrero del 2000, Tomo CVII, expedido por la H. XVI Legislatura, siendo Gobernador Constitucional el C. Lic. Alejandro\nXVIII Legislatura siendo Gobernador Constitucional el C. Eugenio Elorduy Walter 2001-2007; fue reformado por Decreto No. 185, publicado en el Periódico Oficial No. 9, de fecha 24 de\nLey de Hacienda del Estado de Baja California. Página 124\n.\nActualización Legislativa.\nÚltima reforma P.O. No. 72, Índice, 22-Dic-2023\nConstitucional el C. Eugenio Elorduy Walther 2001-2007; fue reformado por Decreto No.\n361, publicado en el Periódico Oficial No. 72, de fecha 22 de diciembre de 2023, Índice, Tomo CXXX, expedido por la H. XXIV Legislatura, siendo Gobernadora Constitucional la C.\nMarina del Pilar Ávila Olmeda 2021-2027;\nARTICULO 176.- Fue Adicionado por Decreto No. 55, publicado en el Periódico\nOficial No. 27, de fecha 10 de Junio de 2005, Tomo CXII, expedido por la H. XVIII\nLegislatura siendo Gobernador Constitucional el C. Eugenio Elorduy Walter 2001-2007; Fue reformado por Decreto No. 409, publicado en el Periódico Oficial No. 27, de fecha 27 de agosto de 2010, Tomo CXVII, Sección II, expedido por la H. XIX Legislatura siendo gobernador Constitucional el C. José Guadalupe Osuna Millán 2007-2013;\nARTICULO 177.- Fue Adicionado por Decreto No. 55, publicado en el Periódico\nOficial No. 27, de fecha 10 de Junio de 2005, Tomo CXII, expedido por la H. XVIII\nLegislatura siendo Gobernador Constitucional el C. Eugenio Elorduy Walter 2001-2007; fue reformado por Decreto No. 101, publicado en el Periódico Oficial No. 51, de fecha 28 de octubre de 2011, Tomo CXVIII, Sección II, expedido por la H. XX Legislatura, siendo\nGobernador Constitucional el C. José Guadalupe Osuna Millán 2007-2013; fue reformado por Decreto No. 280, publicado en el Periódico Oficial No. 4, de fecha 18 de enero de 2019, Tomo CXXVI, expedido por la H. XXII Legislatura, siendo Gobernador Constitucional el C.\nFrancisco Arturo Vega de Lamadrid 2013-2019;\nARTICULO 178.- Fue Adicionado por Decreto No. 55, publicado en el Periódico\nOficial No. 27, de fecha 10 de Junio de 2005, Tomo CXII, expedido por la H. XVIII\nLegislatura siendo Gobernador Constitucional el C. Eugenio Elorduy Walter 2001-2007; fue reformado por Decreto No. 185, publicado en el Periódico Oficial No. 9, de fecha 24 de febrero de 2006, Tomo CXIII, expedido por la H. XVIII Legislatura siendo Gobernador\nConstitucional el C. Eugenio Elorduy Walther 2001-2007; fue reformado por Decreto No.\n361, publicado en el Periódico Oficial No. 72, de fecha 22 de diciembre de 2023, Índice, Tomo CXXX, expedido por la H. XXIV Legislatura, siendo Gobernadora Constitucional la C.\nMarina del Pilar Ávila Olmeda 2021-2027;\nARTICULO 179.- Fue Adicionado por Decreto No. 55, publicado en el Periódico\nLegislatura siendo Gobernador Constitucional el C. Eugenio Elorduy Walter 2001-2007; fue reformado por Decreto No. 101, publicado en el Periódico Oficial No. 51, de fecha 28 de\nGobernador Constitucional el C. José Guadalupe Osuna Millán 2007-2013; fue reformado por Decreto No. 361, publicado en el Periódico Oficial No. 72, de fecha 22 de diciembre de\n2023, Índice, Tomo CXXX, expedido por la H. XXIV Legislatura, siendo Gobernadora\nConstitucional la C. Marina del Pilar Ávila Olmeda 2021-2027;\nLey de Hacienda del Estado de Baja California. Página 125\n.\nActualización Legislativa.\nÚltima reforma P.O. No. 72, Índice, 22-Dic-2023\nARTICULO 180.- Fue adicionado por Decreto No. 185, publicado en el Periódico\nOficial No. 9, de fecha 24 de febrero de 2006, Tomo CXIII, expedido por la H. XVIII\nLegislatura siendo Gobernador Constitucional el C. Eugenio Elorduy Walther 2001-2007; fue adicionado por Decreto No. 235, publicado en el Periódico Oficial No. 26, de fecha 05 de junio de 2009, Tomo CXVI, expedido por la H. XIX Legislatura siendo Gobernador\nConstitucional el C. Guadalupe Osuna Millan 2007-2013; fue reformado por Decreto No. 99, publicado en el Periódico Oficial No. 51, de fecha 28 de octubre de 2011, Tomo CXVIII,\nSección II, expedido por la H. XX Legislatura, siendo Gobernador Constitucional el C. José\nGuadalupe Osuna Millán 2007-2013; fue derogado por Decreto No. 361, publicado en el\nPeriódico Oficial No. 72, de fecha 22 de diciembre de 2023, Índice, Tomo CXXX, expedido por la H. XXIV Legislatura, siendo Gobernadora Constitucional la C. Marina del Pilar Ávila\nOlmeda 2021-2027;\nARTICULO 181.- Fue adicionado por Decreto No. 356, publicado en el Periódico\nOficial No. 36, de fecha 31 de agosto de 2007, Tomo CXIV, expedido por la H. XVIII\nLegislatura siendo Gobernador Constitucional el C. Eugenio Elorduy Walther 2001-2007; fue derogado por Decreto No. 361, publicado en el Periódico Oficial No. 72, de fecha 22 de diciembre de 2023, Índice, Tomo CXXX, expedido por la H. XXIV Legislatura, siendo\nGobernadora Constitucional la C. Marina del Pilar Ávila Olmeda 2021-2027;\nARTÍCULO PRIMERO.- TRANSITORIO DEL DECRETO No. 18, fue reformado por\nDecreto No. 168, publicado en el Periódico Oficial No. 60, de fecha 30 de diciembre de 2011, Tomo CXVIII, Sección II, expedido por la Honorable XX Legislatura, siendo Gobernador\nConstitucional el C. Lic. José Guadalupe Osuna Millán, 2007-2013;\nARTÍCULO SEGUNDO.- TRANSITORIO DEL DECRETO No. 55, Fue derogado\nSección I, Tomo CXIII, expedido por la XVIII Legislatura, siendo Gobernador Constitucional el C. Eugenio Elorduy Walther 2001-2007;\nARTÍCULO TERCERO.- TRANSITORIO DEL DECRETO No. 39, Fue derogado por Decreto No. 62, publicado en el Periódico Oficial No. 22, número especial, de fecha 30\nConstitucional el C. Jaime Bonilla Valdez 2019-2021;\nLey de Hacienda del Estado de Baja California. Página 126\n.\nActualización Legislativa.\nÚltima reforma P.O. No. 72, Índice, 22-Dic-2023\nARTICULO TRANSITORIO DEL DECRETO No. 82, POR EL QUE SE MODIFICAN\nLOS ARTICULOS 54, 55, 56 Y 156, PUBLICADO EN EL PERIODICO OFICIAL No. 6,\nSECCION I, DE FECHA 28 DE FEBRERO DE 1973, EXPEDIDO POR LA H. VII\nLEGISLATURA Y SIENDO GOBERNADOR CONSTITUCIONAL EL C. LIC. MILTON\nCASTELLANOS EVERARDO, 1971-1977.\nUNICO.- El presente Decreto entrará en vigor el día siguiente al de su publicación en el Periódico Oficial, Organo del Gobierno del Estado.\nDADO en el Salón de Sesiones del H. Poder Legislativo, en la ciudad de Mexicali, Baja California, a los veintidós días del mes de febrero de 1973.\nFERNANDO CANO MEDINA, Diputado Presidente.\n(RÚBRICA)\nPROFR. JOSE MA. MARQUEZ CASTRO, Diputado Secretario.\n(RÚBRICA)\nDe conformidad con lo dispuesto por la Fracción I del Artículo 49 de la Constitución\nMexicali, Capital del Estado de Baja California, a los veintisiete días del mes de febrero de 1973.\nEL GOBERNADOR CONSTITUCIONAL DEL ESTADO,\nLIC. MILTON CASTELLANOS EVERARDO.\n(RÚBRICA)\nEL SECRETARIO GENERAL DE GOBIERNO,\nFRANCISCO SANTANA PERALTA.\nARTICULO TRANSITORIO DEL DECRETO No. 83, POR EL QUE SE ADICIONAN\nLOS ARTICULOS 156-1, 156-2, 156-3, 156-4, 156-5 Y 156-6, PUBLICADO EN EL\nEXPEDIDO POR LA H. VII LEGISLATURA Y SIENDO GOBERNADOR CONSTITUCIONAL\nEL C. LIC. MILTON CASTELLANOS EVERARDO, 1971-1977.\nUNICO.- El presente Decreto entrará en vigor, el día siguiente al de su publicación en\nLey de Hacienda del Estado de Baja California. Página 127\n.\nActualización Legislativa.\nÚltima reforma P.O. No. 72, Índice, 22-Dic-2023\nDADO en el Salón de Sesiones del H. Poder Legislativo, en la ciudad de Mexicali, Baja California, a los 22 días del mes de febrero de 1973.\nFERNANDO CANO MEDINA,\nDIPUTADO PRESIDENTE.\n(RÚBRICA)\nPROFR. JOSE MARIA MARQUEZ CASTRO,\nDIPUTADO SECRETARIO.\n(RÚBRICA)\nDe conformidad con lo dispuesto por la Fracción I del Artículo 49 de la Constitución\nMexicali, Capital del Estado de Baja California, a los veintisiete días del mes de febrero de 1973.\nEL GOBERNADOR CONSTITUCIONAL DEL ESTADO,\nLIC. MILTON CASTELLANOS EVERARDO.\n(RÚBRICA)\nEL SECRETARIO GENERAL DE GOBIERNO,\nFRANCISCO SANTANA PERALTA.\n(RÚBRICA)\nARTICULO TRANSITORIO DEL DECRETO No. 85, POR EL QUE SE REFORMA EL\nARTICULO 2o. TRANSITORIO Y SE DEROGA LA LEY DE HACIENDA DEL 31 DE\nDICIEMBRE DE 1953, PUBLICADO EN EL PERIODICO OFICIAL No. 6, SECCION I, DE\nFECHA 28 DE FEBRERO DE 1973, EXPEDIDO POR LA H. VII LEGISLATURA Y SIENDO\nGOBERNADOR CONSTITUCIONAL EL C. LIC. MILTON CASTELLANOS EVERARDO, 1971-1977.\nUNICO.- Este Decreto entrará en vigor al día siguiente al de su publicación en el\nFERNANDO CANO MEDINA, Diputado Presidente.\nLey de Hacienda del Estado de Baja California. Página 128\n.\nActualización Legislativa.\nÚltima reforma P.O. No. 72, Índice, 22-Dic-2023\nPROFR. JOSE MA. MARQUEZ CASTRO, Diputado Secretario.\n(RÚBRICA)\nDe conformidad con lo dispuesto por la Fracción I del Artículo 49 de la Constitución\nMexicali, Capital del Estado de Baja California, a los veintisiete días del mes de febrero de 1973.\nEL GOBERNADOR CONSTITUCIONAL DEL ESTADO,\nLIC. MILTON CASTELLANOS EVERARDO.\n(RÚBRICA)\nEL SECRETARIO GENERAL DE GOBIERNO,\nFRANCISCO SANTANA PERALTA.\n(RÚBRICA)\nARTICULO TRANSITORIO DEL DECRETO No. 98, POR EL QUE SE ADICIONA EN\nEL TÍTULO SEGUNDO, CON EL CAPÍTULO XV Y EL ARTICULO 156-7, PUBLICADO EN\nEL PERIODICO OFICIAL No. 12, DE FECHA 30 DE ABRIL DE 1973, EXPEDIDO POR LA\nH. VII LEGISLATURA Y SIENDO SECRETARIO GENERAL DE GOBIERNO ENCARGADO\nDEL DESPACHO DEL GOBIERNO EL C. FRANCISCO SANTANA PERALTA, SIENDO\nGOBERNADOR CONSTITUCIONAL EL C. LIC. MILTON CASTELLANOS EVERARDO, 1971-1977.\nUNICO.- Este Decreto entrará en vigor a partir de la fecha de su publicación en el\nPeriódico Oficial, Organo del Gobierno del Estado.\nDADO en el Salón de Sesiones del H. Poder Legislativo, en la ciudad de Mexicali,\nFERNANDO CANO MEDINA, Diputado Presidente.\nPABLO LEON QUINTERO, Diputado Secretario.\nDe conformidad con lo dispuesto por la Fracción I del Artículo 49 de la Constitución\nLey de Hacienda del Estado de Baja California. Página 129\n.\nActualización Legislativa.\nÚltima reforma P.O. No. 72, Índice, 22-Dic-2023\nMexicali, Capital del Estado de Baja California, a los veintiséis días del mes de abril de 1973.\nEL SECRETARIO GENERAL DE GOBIERNO ENC. DEL DESPACHO P.M.L.,\nFRANCISCO SANTANA PERALTA.\n(RÚBRICA)\nEL OFICIAL MAYOR DE GOBIERNO ENC. DE LA SECRETARIA GENERAL P.M.L.,\nING. OSCAR BAYLON CHACON.\n(RÚBRICA)\nARTICULO TRANSITORIO DEL DECRETO No. 113, POR EL QUE SE REFORMA\nEL ARTICULO 56, PUBLICADO EN EL PERIODICO OFICIAL No. 18, DE FECHA 30 DE\nJUNIO DE 1973, EXPEDIDO POR LA H. VII LEGISLATURA Y SIENDO SECRETARIO\nGENERAL ENCARGADO DEL DESPACHO DEL GOBIERNO.\nUNICO.- Este Decreto entrará en vigor a partir de la fecha de su publicación en el\nPeriódico Oficial, Organo del Gobierno del Estado.\nBaja California a los trece días del mes de junio de 1973.\nFERNANDO CANO MEDINA, Diputado Presidente.\n(RÚBRICA)\nPABLO LEON QUINTERO, Diputado Secretario.\n(RÚBRICA)\nDe conformidad con lo dispuesto por la Fracción I del Artículo 49 de la Constitución\nMexicali, Capital del Estado de Baja California, a los veinte días del mes de junio de\n1973.\nEL SECRETARIO GENERAL DE GOBIERNO ENC. DEL DESPACHO P.M.L.,\nFRANCISCO SANTANA PERALTA.\nEL OFICIAL MAYOR DE GOBIERNO ENC. DE LA SECRETARIA GENERAL P.M.L.,\nING. OSCAR BAYLON CHACON.\nLey de Hacienda del Estado de Baja California. Página 130\n.\nActualización Legislativa.\nÚltima reforma P.O. No. 72, Índice, 22-Dic-2023\nARTICULO TRANSITORIO DEL DECRETO No. 179, POR EL QUE SE REFORMAN\nLOS ARTICULOS 5, 6, 7, 8, 9, 14, 30 Y 38, PUBLICADO EN EL PERIODICO OFICIAL No.\n6, SECCION I, DE FECHA 28 DE FEBRERO DE 1974, EXPEDIDO POR LA H. VII\nLEGISLATURA Y SIENDO GOBERNADOR CONSTITUCIONAL EL C. LIC. MILTON\nCASTELLANOS EVERARDO, 1971-1977.\nUNICO.- Este Decreto entrará en vigor, al día siguiente de su publicación en el\nPeriódico Oficial, Organo del Gobierno del Estado.\nDADO en la Sala de Sesiones del H. Poder Legislativo, en la Ciudad de Mexicali, Baja\nCalifornia, a los veintiocho días del mes de febrero de 1974.\nDR. CARLOS CEVALLOS NAVA, Diputado Presidente.\n(RÚBRICA)\nMERCEDES MARTINEZ VDA. DE LIZARRAGA, Diputado Secretario.\n(RÚBRICA)\nDe conformidad con lo dispuesto por la Fracción I del Artículo 49 de la Constitución\nMexicali, Capital del Estado de Baja California, a los veintiocho días del mes de febrero de 1974.\nEL GOBERNADOR CONSTITUCIONAL DEL ESTADO,\nLIC. MILTON CASTELLANOS EVERARDO.\n(RÚBRICA)\nEL SECRETARIO GENERAL DE GOBIERNO,\nFRANCISCO SANTANA PERALTA.\nARTICULO TRANSITORIO DEL DECRETO No. 170, POR EL QUE SE REFORMAN\nLOS ARTICULOS 7o, 67, 87, 100, 104, 119 Y 144, PUBLICADO EN EL PERIODICO\nLEGISLATURA Y SIENDO GOBERNADOR CONSTITUCIONAL EL C. LIC. MILTON\nCASTELLANOS EVERARDO, 1971-1977.\nRODOLFO FIERRO MARQUEZ, Ley de Hacienda del Estado de Baja California. Página 131\n.\nActualización Legislativa.\nÚltima reforma P.O. No. 72, Índice, 22-Dic-2023\nDiputado Presidente.\n(RÚBRICA)\nFERNANDO CANO MEDINA, Diputado Secretario.\n(RÚBRICA)\nDe conformidad con lo dispuesto por la Fracción I del Artículo 49 de la Constitución\nMexicali, Capital del Estado de Baja California, a los seis días del mes de febrero de\n1974.\nEL GOBERNADOR CONSTITUCIONAL DEL ESTADO,\nLIC. MILTON CASTELLANOS EVERARDO.\n(RÚBRICA)\nEL SECRETARIO GENERAL DE GOBIERNO,\nFRANCISCO SANTANA PERALTA.\n(RÚBRICA)\nARTICULO TRANSITORIO DEL DECRETO No. 215, POR EL QUE SE REFORMA\nEL ARTICULO 131, PUBLICADO EN EL PERIODICO OFICIAL No. 24, DE FECHA 31 DE\nAGOSTO DE 1974, EXPEDIDO POR LA H. VII LEGISLATURA Y SIENDO SECRETARIO\nGENERAL DE GOBIERNO ENCARGADO DEL DESPACHO DEL GOBIERNO, SIENDO\nGOBERNADOR CONSTITUCIONAL EL C. LIC. MILTON CASTELLANOS EVERARDO, 1971-1977.\nUNICO.- Este Decreto Entrará en vigor a partir de la fecha de su publicación en el\nDR. CARLOS CEVALLOS NAVA, Diputado Presidente.\nMARTINIANO VALDEZ ESCOBEDO, Diputado Secretario.\nLey de Hacienda del Estado de Baja California. Página 132\n.\nActualización Legislativa.\nÚltima reforma P.O. No. 72, Índice, 22-Dic-2023\nDe conformidad con lo dispuesto por la Fracción I del Artículo 49 de la Constitución\nMexicali, Capital del Estado de Baja California, a los veintitrés días del mes de agosto de 1974.\nEL SECRETARIO GENERAL DE GOBIERNO\nENC. DEL DESPACHO P.M.L.,\nFRANCISCO SANTANA PERALTA.\n(RÚBRICA)\nEL OFICIAL MAYOR DE GOBIERNO\nENC. DE LA SECRETARIA GENERAL P.M.L.,\nING. OSCAR BAYLON CHACON.\n(RÚBRICA)\nARTICULOS TRANSITORIOS DEL DECRETO No. 22, POR EL QUE SE MODIFICA,\nDEROGA, REFORMA Y ADICIONAN LOS ARTICULOS 6o, 8o, 9o, 28, 29, 34, 40, 86, 90, 114-1, 116, 120, 125, 151-1, 151-2, 151-3, 151-4, 151-5, 151-6, 151-7, 151-8, 151-9, 151-10, 151-11, 151-12, 151-13, 151-14, 151-15, 151-16, 151-17, 151-18, 155-19, 151-20, 151-21,\n151-22, 151-23, 151-24, 156-1, 156-2, 156-3, PUBLICADO EN EL PERIODICO OFICIAL No.\n36, SECCION XI, DE FECHA 31 DE DICIEMBRE DE 1974, EXPEDIDO POR LA H. VIII\nLEGISLATURA Y SIENDO GOBERNADOR CONSTITUCIONAL EL C. LIC. MILTON\nCASTELLANOS EVERARDO, 1971-1977.\nPRIMERO.- Quienes a la fecha de publicación del presente Decreto perciban ingresos por concepto de arrendamiento o subarrendamiento de bienes inmuebles, deberá empadronarse en la Recaudación de Rentas del Estado y registrar los contratos vigentes a la fecha, debiendo así mismo, quienes estén percibiendo ingresos en especie derivados de contratos celebrados con anterioridad a esta fecha, manifiestan a la Recaudación de Rentas de la ubicación del inmueble, los hechos que motiven sus ingresos detallando lo que señala el artículo 151-4 incisos b) y c) de la Ley de Hacienda del Estado. días.\nSEGUNDO.- Las personas físicas, jurídicas o unidades económicas que al entrar en establece el Artículo 151-18, están obligadas a empadronarse en la Secretaría de Finanzas por conducto de la Oficina Recaudadora de la jurisdicción, en un plazo que vence el 28 de\nTERCERO.- Las personas físicas, jurídicas o unidades económicas que al entrar en\nLey de Hacienda del Estado de Baja California. Página 133\n.\nActualización Legislativa.\nÚltima reforma P.O. No. 72, Índice, 22-Dic-2023 artículo 151-13 estarán obligados a inscribirse mediante la presentación de la \" Relación bimestral de Retenciones \" en el mes de marzo de 1975.\nCUARTO.- La vigencia del presente Decreto empezará a partir del día siguiente al de su publicación en el Periódico Oficial, Organo del Gobierno del Estado.\nBaja California, a los treinta días del mes de diciembre de 1974.\nJUAN VILLALPANDO CUEVAS, Diputado Presidente.\n(RÚBRICA)\nMANUEL TRASVIÑA PEREZ, Diputado Secretario.\n(RÚBRICA)\nDe conformidad con lo dispuesto por la Fracción I del Artículo 49 de la Constitución\nMexicali, Capital del Estado de Baja California, a los treinta y un días del mes de diciembre de 1974.\nEL GOBERNADOR CONSTITUCIONAL DEL ESTADO,\nLIC. MILTON CASTELLANOS EVERARDO.\n(RÚBRICA)\nEL SECRETARIO GENERAL DE GOBIERNO,\nFRANCISCO SANTANA PERALTA.\n(RÚBRICA)\nARTICULO TRANSITORIO DEL DECRETO No. 62, POR EL QUE SE ADICIONA EL\nARTICULO 34-BIS Y SE REFORMA EL 156, PUBLICADO EN EL PERIODICO OFICIAL No.\nSIENDO GOBERNADOR CONSTITUCIONAL EL C. LIC. MILTON CASTELLANOS\nEVERARDO, 1971-1977.\nSALVADOR SOLORIO AGUILAR, Diputado Presidente.\nLey de Hacienda del Estado de Baja California. Página 134\n.\nActualización Legislativa.\nÚltima reforma P.O. No. 72, Índice, 22-Dic-2023\nMARGARITA ORTEGA VILLA, Diputado Secretario.\n(RÚBRICA)\nDe conformidad con lo dispuesto por la Fracción I del Artículo 49 de la Constitución\nMexicali, Capital del Estado de Baja California, a los diecisiete días del mes de junio de 1975.\nEL GOBERNADOR CONSTITUCIONAL DEL ESTADO,\nLIC. MILTON CASTELLANOS EVERARDO.\n(RÚBRICA)\nEL SECRETARIO GENERAL DE GOBIERNO,\nFRANCISCO SANTANA PERALTA.\n(RÚBRICA)\nARTICULO TRANSITORIO DEL DECRETO NO. 100, POR EL QUE SE REFORMAN\nLOS ARTICULOS 8o., 15, 23, 30, 53, 54, 72, 102, 104, 105, 112, 114, 119, 120, 120-1, 121,\n124, 125, 151-23 Y SE DEROGAN LOS ARTICULOS 133, 134, 135 Y 136, PUBLICADO EN\nEL PERIODICO OFICIAL No. 3, DE FECHA 31 DE ENERO DE 1976, EXPEDIDO POR LA\nH. VIII LEGISLATURA Y SIENDO SECRETARIO GENERAL DE GOBIERNO ENCARGADO\nDEL DESPACHO DEL GOBIERNO EL C. FRANCISCO SANTANA PERALTA, SIENDO\nGOBERNADOR CONSTITUCIONAL EL C. LIC. MILTON CASTELLANOS EVERARDO, 1971-1977.\nUNICO.- El presente Decreto entrará en vigor el día siguiente al de su publicación en el Periódico Oficial, Organo del Gobierno del Estado.\nDADO en el Salón de Sesiones del H. Poder Legislativo, en la ciudad de Mexicali,\nMARGARITA ORTEGA VILLA,\nDIPUTADO PRESIDENTE.\nFRANCISCO FIGUEROA MENDEZ,\nDIPUTADO SECRETARIO.\nDe conformidad con lo dispuesto por la Fracción I del Artículo 49 de la Constitución\nLey de Hacienda del Estado de Baja California. Página 135\n.\nActualización Legislativa.\nÚltima reforma P.O. No. 72, Índice, 22-Dic-2023\nMexicali, Capital del Estado de Baja California, a los veintiún días del mes de enero de 1976.\nEL SECRETARIO GENERAL DE GOBIERNO ENC. DEL DESPACHO P.M.L.,\nFRANCISCO SANTANA PERALTA.\n(RÚBRICA)\nEL OFICIAL MAYOR DE GOBIERNO ENC. DE LA SECRETARIA GENERAL P.M.L.,\nING. OSCAR BAYLON CHACON.\n(RÚBRICA)\nARTICULO TRANSITORIO DEL DECRETO No. 108, POR EL QUE SE ADICIONA EL\nARTICULO 88-BIS, PUBLICADO EN EL PERIODICO OFICIAL No. 3, SECCION I, DE\nFECHA 31 DE ENERO DE 1976, EXPEDIDO POR LA H. VIII LEGISLATURA Y SIENDO\nGOBERNADOR CONSTITUCIONAL EL C. LIC. MILTON CASTELLANOS EVERARDO, 1971-1977.\nUNICO.- Este Decreto entrará en vigor al día siguiente de su publicación en el\nPeriódico Oficial, Organo del Gobierno del Estado.\nDADO en el Salón de Sesiones del H. Poder Legislativo, en la ciudad de Mexicali, Baja California, a los treinta días del mes de enero de 1976.\nMARGARITA ORTEGA VILLA,\nDIPUTADO PRESIDENTE.\n(RÚBRICA)\nFRANCISCO FIGUEROA MENDEZ,\nDIPUTADO SECRETARIO.\n(RÚBRICA)\nDe conformidad con lo dispuesto por la Fracción I del Artículo 49 de la Constitución\nMexicali, Capital del Estado de Baja California, a los treinta y un días del mes de\nEL GOBERNADOR CONSTITUCIONAL DEL ESTADO,\nLIC. MILTON CASTELLANOS EVERARDO.\nEL SECRETARIO GENERAL DE GOBIERNO,\nFRANCISCO SANTANA PERALTA.\nLey de Hacienda del Estado de Baja California. Página 136\n.\nActualización Legislativa.\nÚltima reforma P.O. No. 72, Índice, 22-Dic-2023\nARTICULO TRANSITORIO DEL DECRETO No. 133, POR EL QUE SE REFORMA\nEL ARTICULO 71, PUBLICADO EN EL PERIODICO OFICIAL No. 13, DE FECHA 10 DE\nMAYO DE 1976, EXPEDIDO POR LA H. VIII LEGISLATURA Y SIENDO GOBERNADOR\nCONSTITUCIONAL EL C. LIC. MILTON CASTELLANOS EVERARDO, 1971-1977.\nDADO en el Salón de Sesiones del H. Poder Legislativo, en la ciudad de Mexicali, Baja California, a los veintisiete días del mes de abril de 1976.\nDAVID OJEDA OCHOA, Diputado Presidente.\n(RÚBRICA)\nMARGARITA ORTEGA VILLA, Diputado Secretario.\n(RÚBRICA)\nDe conformidad con lo dispuesto por la Fracción I del Artículo 49 de la Constitución\nMexicali, Capital del Estado de Baja California, a los cuatro días del mes de mayo de\n1976.\nEL GOBERNADOR CONSTITUCIONAL DEL ESTADO,\nLIC. MILTON CASTELLANOS EVERARDO.\n(RÚBRICA)\nEL SECRETARIO GENERAL DE GOBIERNO,\nFRANCISCO SANTANA PERALTA.\n(RÚBRICA)\nARTICULO TRANSITORIO DEL DECRETO No. 165, POR EL QUE SE REFORMA\nEL ARTICULO 92, PUBLICADO EN EL PERIODICO OFICIAL No. 23, DE FECHA 20 DE\nCONSTITUCIONAL EL C. LIC. MILTON CASTELLANOS EVERARDO, 1971-1977.\nUNICO.- Este Decreto entrará en vigor el día siguiente al de su publicación en el\nSALVADOR CASTELLANOS CARDENAS, Diputado Presidente.\nLey de Hacienda del Estado de Baja California. Página 137\n.\nActualización Legislativa.\nÚltima reforma P.O. No. 72, Índice, 22-Dic-2023\nSALVADOR SOLORIO AGUILAR, Diputado Secretario.\n(RÚBRICA)\nDe conformidad con lo dispuesto por la Fracción I del Artículo 49 de la Constitución\nMexicali, Capital del Estado de Baja California, a los dieciocho días del mes de agosto de 1976.\nEL GOBERNADOR CONSTITUCIONAL DEL ESTADO,\nLIC. MILTON CASTELLANOS EVERARDO.\n(RÚBRICA)\nEL SECRETARIO GENERAL DE GOBIERNO,\nFRANCISCO SANTANA PERALTA.\n(RÚBRICA)\nARTICULO TRANSITORIO DEL DECRETO No. 206, POR EL QUE SE REFORMAN\nLOS ARTICULOS 7o., 11, 13, 15, 18, 19, 20, 21, 39, 42, 44, 56, 65, 72, 73, 75, 101, 110,\n111, 114, 151-13 Y 157, PUBLICADOS EN EL PERIODICO OFICIAL No. 4, DE FECHA 10\nDE FEBRERO DE 1977, EXPEDIDO POR LA H. VIII LEGISLATURA Y SIENDO\nGOBERNADOR CONSTITUCIONAL EL C. LIC. MILTON CASTELLANOS EVERARDO, 1971-1977.\nUNICO.- El presente Decreto entrará en vigor el día siguiente al de su publicación en el Periódico Oficial, Organo del Gobierno del Estado.\nDADO en el Salón de Sesiones del H. Poder Legislativo, en la Ciudad de Mexicali, Baja California, a los treinta y un días del mes de enero de 1977.\nLIC. PRAXEDIS PADILLA GONZALEZ, Diputado Presidente.\nFRANCISCO FIGUEROA MENDEZ, Diputado Secretario.\nDe conformidad con lo dispuesto por la Fracción I del Artículo 49 de la Constitución\nMexicali, Capital del Estado de Baja California, a los treinta y un días del mes de\nLey de Hacienda del Estado de Baja California. Página 138\n.\nActualización Legislativa.\nÚltima reforma P.O. No. 72, Índice, 22-Dic-2023\nEL GOBERNADOR CONSTITUCIONAL DEL ESTADO,\nLIC. MILTON CASTELLANOS EVERARDO.\n(RÚBRICA)\nEL SECRETARIO GENERAL DE GOBIERNO,\nLIC. RAFAEL MORENO HENRIQUEZ.\n(RÚBRICA)\nARTICULO TRANSITORIO DEL DECRETO No. 229, POR EL QUE SE REFORMA\nEL ARTICULO 56, PUBLICADO EN EL PERIODICO OFICIAL No. 15, DE FECHA 31 DE\nMAYO DE 1977, EXPEDIDO POR LA H. VIII LEGISLATURA Y SIENDO SECRETARIO\nGENERAL DE GOBIERNO ENCARGADO DEL DESPACHO DEL GOBIERNO EL C. LIC.\nRAFAEL MARTINEZ RETES.\nUNICO.- Este Decreto entrará en vigor a partir de su fecha de publicación en el\nPeriódico Oficial, Organo del Gobierno del Estado.\nDADO en el Salón de Sesiones del H. Poder Legislativo, en la Ciudad de Mexicali, Baja California, a los diez días del mes de mayo de 1977.\nLIC. PRAXEDIS PADILLA GONZALEZ, Diputado Presidente.\n(RÚBRICA)\nMARGARITA ORTEGA VILLA, Diputado Secretario.\n(RÚBRICA)\nDe conformidad con lo dispuesto por la Fracción I del Artículo 49 de la Constitución\nMexicali, Capital del Estado de Baja California, a los diecinueve días del mes de mayo de mil novecientos setenta y siete.\nEL SECRETARIO GENERAL DE GOBIERNO ENC. DEL DESPACHO P.M.L.,\nLIC. RAFAEL MARTINEZ RETES.\nEL OFICIAL MAYOR DE GOBIERNO ENC. DE LA SECRETARIA GENERAL P.M.L.,\nPROFR. FELIPE DE LA GARZA Y CAMACHO.\nARTICULOS TRANSITORIOS DEL DECRETO No. 95, POR EL QUE SE\nREFORMAN LOS ARTICULOS 7o, 9o, 13, 24, 25, 28, 29, 30, 33, 34, 34-BIS, 90, 121, 15113, 151-14, 151-15, 151-16, 151-17, 151-18, 151-19, 151-20, 151-21, 151-22, 151-23, 151-\n24, 151-25, 151-26, 151-27, 151-28, 151-29, 151-30, 151-31, 151-32, 151-33, 151-34, 15135, 151-36, 151-37, 151-38, 151-39, 151-40, 151-41, 156-1 AL 156-7, PUBLICADOS EN EL\nLey de Hacienda del Estado de Baja California. Página 139\n.\nActualización Legislativa.\nÚltima reforma P.O. No. 72, Índice, 22-Dic-2023\nPERIODICO OFICIAL No. 36, DE FECHA 31 DE DICIEMBRE DE 1978, EXPEDIDO POR\nLA H. IX LEGISLATURA Y SIENDO GOBERNADOR CONSTITUCIONAL EL C. ROBERTO\nDE LA MADRID ROMANDIA, 1977-1983.\nPRIMERO.- Las disposiciones que establece el presente Decreto entrarán en vigor a partir del día siguiente al de su publicación en el Periódico Oficial del Gobierno del Estado.\nSEGUNDO.- Se derogan todas las disposiciones que se opongan al presente\nDecreto.\nTERCERO.- Para los efectos del Artículo 25 de la Ley de Hacienda, se concede un plazo que vencerá el día 28 de febrero de 1979, para que todos los causantes del Impuesto\nPredial presenten ante la Oficina de Recaudación de Rentas de la jurisdicción del predio, la manifestación relativa a su domicilio. Quienes en este plazo no cumplan con esta obligación podrán ser notificados en el lugar que se les localice y en defecto de éste, en la ubicación del predio si no es baldío; de serlo podrán ser notificados por edictos, en los términos del inciso b) de la Fracción I del Artículo 81 del Código Fiscal, de cualquier resolución relativa al\nImpuesto Predial.\nCUARTO.- Es obligación de los sujetos y responsables solidarios del Impuesto sobre remuneraciones al trabajo personal, el empadronarse en la Oficina de Recaudación de\nRentas de su jurisdicción, dentro del mes siguiente a la fecha de publicación del presente\nDecreto.\nQUINTO.- Es obligación de los sujetos y responsables solidarios del Impuesto Sobre\nProducto de Capitales, el empadronarse en la Oficina de Recaudación de Rentas de su jurisdicción, dentro del mes siguiente a la fecha de su publicación del presente Decreto.\nDADO en la Sala de Sesiones del H. Poder Legislativo, en la ciudad de Mexicali, Baja\nCalifornia, a los veintiocho días del mes de diciembre de 1978.\nPROFR. JOSE LUIS GONZALEZ PIMENTEL, Diputado Presidente.\nFAUSTO CEDILLO LOPEZ, Diputado Secretario.\nDe conformidad con lo dispuesto por la Fracción I del Artículo 49 de la Constitución\nMexicali, Capital del Estado de Baja California, a los veintinueve días del mes de diciembre de mil novecientos setenta y ocho.\nEL GOBERNADOR CONSTITUCIONAL DEL ESTADO, Ley de Hacienda del Estado de Baja California. Página 140\n.\nActualización Legislativa.\nÚltima reforma P.O. No. 72, Índice, 22-Dic-2023\nC. ROBERTO DE LA MADRID ROMANDIA.\n(RÚBRICA)\nEL SECRETARIO GENERAL DE GOBIERNO,\nC. ARMANDO GALLEGO MORENO.\n(RÚBRICA)\nARTICULO TRANSITORIO DEL DECRETO No. 164, POR EL QUE SE SUSPENDE\nTOTALMENTE LA VIGENCIA DE LOS ARTÍCULOS 42,137,144,151-1, 151-21 Y 152,\nPUBLICADO EN EL PERIÓDICO OFICIAL No. 36, DE FECHA 31 DE DICIEMBRE DE 1979,\nSECCIÓN XI, EXPEDIDO POR LA H. IX LEGISLATURA Y SIENDO GOBERNADOR\nCONSTITUCIONAL EL C. ROBERTO DE LA MADRID ROMANDIA, 1977-1983.\nUNICO.- Las disposiciones que establece el presente Decreto surtirán sus efectos a partir de la fecha en que entren en vigor la Ley del Impuesto al Valor Agregado y la Ley de\nCoordinación Fiscal, y durante el Período en que el Estado de Baja California se encuentre adherido al Sistema Nacional de Coordinación Fiscal en los términos de estas Leyes\nFederales.\nDADO en la Sala de Sesiones de la H. Poder Legislativo, en la ciudad de Mexicali, Baja California, a los 27 días del mes de diciembre de 1979.\nPROFRA. AIDA BALTAZAR MARTINEZ,\nDIPUTADA PRESIDENTE.\n(RÚBRICA)\nLIC. MANUEL MARTINEZ MERCADO,\nDIPUTADO SECRETARIO.\n(RÚBRICA)\nDE CONFORMIDAD CON LO DISPUESTO POR LA FRACCION I DEL ARTICULO\n49 DE LA CONSTITUCION POLITICA DEL ESTADO, MANDO SE IMPRIMA, PUBLIQUE,\nOBSERVE Y SE LE DE EL DEBIDO CUMPLIMIENTO.\nMEXICALI, CAPITAL DEL ESTADO DE BAJA CALIFORNIA, A LOS 31 DIAS DEL\nMES DE DICIEMBRE DE MIL NOVECIENTOS SETENTA Y NUEVE.\nEL GOBERNADOR CONSTITUCIONAL DEL ESTADO,\nC. ROBERTO DE LA MADRID ROMANDIA.\nEL SECRETARIO GENERAL DE GOBIERNO,\nC. ARMANDO GALLEGO MORENO.\nLey de Hacienda del Estado de Baja California. Página 141\n.\nActualización Legislativa.\nÚltima reforma P.O. No. 72, Índice, 22-Dic-2023\nARTICULO TRANSITORIO DEL DECRETO No. 167, POR EL QUE SE REFORMA\nEL ARTICULO 28, PUBLICADO EN EL PERIODICO OFICIAL No.4, DE FECHA 10 DE\nFEBRERO DE 1980, EXPEDIDO EN LA H. IX LEGISLATURA Y SIENDO GOBERNADOR\nCONSTITUCIONAL EL C. ROBERTO DE LA MADRID ROMANDIA, 1977-1983.\nUNICO.- Las disposiciones que establece el presente Decreto entrarán en vigor a partir del día siguiente al de su publicación en el Periódico Oficial, Organo del Gobierno del\nEstado.\nCapital del Estado de Baja California, a los quince días del mes de enero de 1980.\nPROFRA. AIDA BALTAZAR MARTINEZ,\nDIPUTADO PRESIDENTE.\n(RÚBRICA)\nLIC. MANUEL MARTINEZ MERCADO,\nDIPUTADO SECRETARIO.\n(RÚBRICA)\nDE CONFORMIDAD CON LO DISPUESTO POR LA FRACCION I DEL ARTICULO\n49 DE LA CONSTITUCION POLITICA DEL ESTADO, MANDO SE IMPRIMA, PUBLIQUE,\nOBSERVE Y SE LE DE EL DEBIDO CUMPLIMIENTO.\nMEXICALI, CAPITAL DEL ESTADO DE BAJA CALIFORNIA, A LOS VEINTIOCHO\nDIAS DEL MES DE ENERO DE MIL NOVECIENTOS OCHENTA.\nEL GOBERNADOR CONSTITUCIONAL DEL ESTADO,\nC. ROBERTO DE LA MADRID ROMANDIA.\n(RÚBRICA)\nEL SECRETARIO GENERAL DE GOBIERNO,\nC. ARMANDO GALLEGO MORENO.\nARTICULO TRANSITORIO DEL DECRETO No. 182, POR EL QUE SE REFORMA\nEL ARTICULO 151-13, PUBLICADO EN EL PERIODICO OFICIAL No. 16, DE FECHA 10\nCONSTITUCIONAL EL C. ROBERTO DE LA MADRID ROMANDIA, 1977-1983.\nUNICO.- El presente Decreto tendrá vigencia a partir del día 1o. de junio del año en\nCalifornia.\nLey de Hacienda del Estado de Baja California. Página 142\n.\nActualización Legislativa.\nÚltima reforma P.O. No. 72, Índice, 22-Dic-2023\nCapital del Estado de Baja California, a los diez días del mes de junio de 1980.\nFAUSTO CEDILLO LOPEZ,\nDIPUTADO PRESIDENTE,\n(RÚBRICA)\nPROFRA. AIDA BALTAZAR MARTINEZ,\nDIPUTADO SECRETARIO,\n(RÚBRICA)\nDE CONFORMIDAD CON LO DISPUESTO POR LA FRACCION I DEL ARTICULO\n49 DE LA CONSTITUCION POLITICA DEL ESTADO, MANDO SE IMPRIMA, PUBLIQUE,\nOBSERVE Y SE LE DE EL DEBIDO CUMPLIMIENTO.\nMEXICALI, CAPITAL DEL ESTADO DE BAJA CALIFORNIA, A LOS DIEZ DIAS DEL\nMES DE JUNIO DE MIL NOVECIENTOS OCHENTA.\nEL GOBERNADOR CONSTITUCIONAL DEL ESTADO,\nC. ROBERTO DE LA MADRID ROMANDIA.\n(RÚBRICA)\nEL SECRETARIO GENERAL DE GOBIERNO,\nC. ARMANDO GALLEGO MORENO.\n(RÚBRICA)\nARTICULOS TRANSITORIOS DEL DECRETO No. 11, POR EL QUE SE\nREFORMAN LOS ARTICULOS 5o, 7o, 11, 12, 13, 15, 16, 97 AL 106, 107 AL 114-1, 121 AL\n126 Y 156, PUBLICADO EN EL PERIODICO OFICIAL No. 36, DE FECHA 31 DE\nDICIEMBRE DE 1980, SECCIÓN XI, EXPEDIDO POR LA H. X LEGISLATURA Y SIENDO\nGOBERNADOR CONSTITUCIONAL EL C. ROBERTO DE LA MADRID ROMANDIA, 1977-\n1983.\nPRIMERO.- Los efectos del presente Decreto se consideran a partir del día 1o de\nBaja California.\nLIC. RENE TREVIÑO ARREDONDO,\nDIPUTADO PRESIDENTE.\nLey de Hacienda del Estado de Baja California. Página 143\n.\nActualización Legislativa.\nÚltima reforma P.O. No. 72, Índice, 22-Dic-2023\nLIC. JOSE ENRIQUE MEJIA PANCARDO,\nDIPUTADO SECRETARIO.\n(RÚBRICA)\nDE CONFORMIDAD CON LO DISPUESTO POR LA FRACCION I DEL ARTICULO\n49 DE LA CONSTITUCION POLITICA DEL ESTADO, MANDO SE IMPRIMA, PUBLIQUE,\nOBSERVE Y SE LE DE EL DEBIDO CUMPLIMIENTO.\nMEXICALI, CAPITAL DEL ESTADO DE BAJA CALIFORNIA, A LOS TREINTA Y UN\nDIAS DEL MES DE DICIEMBRE DE MIL NOVECIENTOS OCHENTA.\nEL GOBERNADOR CONSTITUCIONAL DEL ESTADO,\nC. ROBERTO DE LA MADRID ROMANDIA.\n(RÚBRICA)\nEL SECRETARIO GENERAL DE GOBIERNO,\nC. ARMANDO GALLEGO MORENO.\n(RÚBRICA)\nARTICULO TRANSITORIO DEL DECRETO No. 76, POR EL QUE SE REFORMA EL\nARTICULO 7o., PUBLICADO EN EL PERIODICO OFICIAL No. 34, DE FECHA 10 DE\nDICIEMBRE DE 1981, EXPEDIDO POR LA H. X LEGISLATURA Y SIENDO\nGOBERNADOR CONSTITUCIONAL EL C. ROBERTO DE LA MADRID ROMANDIA, 1977-\n1983.\nUNICO.- El presente Decreto entrará en vigor el día siguiente de su publicación en el\nPeriódico Oficial y deroga todas aquellas disposiciones que se opongan a la misma.\nDADO en la Sala de Sesiones del H. Poder Legislativo, en la ciudad de Mexicali, Capital del Estado de Baja California, a los diez días del mes de diciembre de 1981.\nLIC. JOSE ENRIQUE PANCARDO,\nDIPUTADO PRESIDENTE.\nJOSE MANUEL DIAZ MARTINEZ,\nDIPUTADO SECRETARIO.\n49 DE LA CONSTITUCION POLITICA DEL ESTADO, MANDO SE IMPRIMA, PUBLIQUE,\nOBSERVE Y SE LE DE EL DEBIDO CUMPLIMIENTO.\nMEXICALI, CAPITAL DEL ESTADO DE BAJA CALIFORNIA, A LOS NUEVE DIAS\nDEL MES DE DICIEMBRE DE MIL NOVECIENTOS OCHENTA Y UNO.\nLey de Hacienda del Estado de Baja California. Página 144\n.\nActualización Legislativa.\nÚltima reforma P.O. No. 72, Índice, 22-Dic-2023\nEL GOBERNADOR CONSTITUCIONAL DEL ESTADO,\nC. ROBERTO DE LA MADRID ROMANDIA.\n(RÚBRICA)\nEL SECRETARIO GENERAL DE GOBIERNO,\nPROFR. MARCO ANTONIO BOLAÑOS CACHO.\n(RÚBRICA)\nARTICULO TRANSITORIO DEL DECRETO No. 84, POR EL QUE SE REFORMA EL\nARTICULO 42, PUBLICADO EN EL PERIODICO OFICIAL No. 36, DE FECHA 31 DE\nDICIEMBRE DE 1981, EXPEDIDO POR LA H. X LEGISLATURA Y SIENDO SECRETARIO\nGENERAL DE GOBIERNO ENC. DEL DESPACHO P.M.L., EL C. MARCO ANTONIO\nBOLAÑOS CACHO.\nUNICO.- Las disposiciones que establece el presente Decreto surten sus efectos a partir del 1o de enero del presente año, y durante el período en que el Estado de Baja\nCalifornia se encuentra adherido al SISTEMA NACIONAL DE COORDINACION FISCAL en los términos de la LEY DEL IMPUESTO AL VALOR AGREGADO Y LEY DE\nCOORDINACION FISCAL.\nDADO en la Sala de Sesiones del H. Poder Legislativo, en la ciudad de Mexicali, Capital del Estado de Baja California, a los diecisiete días del mes de diciembre de 1981.\nLIC. JOSE ENRIQUE MEJIA PANCARDO,\nDIPUTADO PRESIDENTE.\n(RÚBRICA)\nJOSE MANUEL DIAZ MARTINEZ,\nDIPUTADO SECRETARIO.\n(RÚBRICA)\nDE CONFORMIDAD CON LO DISPUESTO POR LA FRACCION I DEL ARTICULO\n49 DE LA CONSTITUCION POLITICA DEL ESTADO, MANDO SE IMPRIMA, PUBLIQUE,\nOBSERVE Y SE LE DE EL DEBIDO CUMPLIMIENTO.\nMEXICALI, CAPITAL DEL ESTADO DE BAJA CALIFORNIA, A LOS VEINTIOCHO\nDIAS DEL MES DE DICIEMBRE DE MIL NOVECIENTOS OCHENTA Y UNO.\nEL SECRETARIO GENERAL DE GOBIERNO ENC. DEL DESPACHO P.M.L.,\nPROFR. MARCO ANTONIO BOLAÑOS CACHO.\nEL OFICIAL MAYOR DE GOBIERNO ENC. DE LA SECRETARIA GENERAL P.M.L.,\nLIC. RAUL POMPA VICTORIA.\nLey de Hacienda del Estado de Baja California. Página 145\n.\nActualización Legislativa.\nÚltima reforma P.O. No. 72, Índice, 22-Dic-2023\nARTICULO TRANSITORIO DEL DECRETO No. 104, POR EL QUE SE ABROGAN\nLAS TABLAS DE VALORES UNITARIOS ESTABLECIDOS EN EL ARTICULO 12 DE LA\nLEY DE CATASTRO, PUBLICADO EN EL PERIODICO OFICIAL 12, DE FECHA 30 DE\nABRIL DE 1982, EXPEDIDO POR LA H. X LEGISLATURA Y SIENDO GOBERNADOR\nCONSTITUCIONAL EL C. LIC. ROBERTO DE LA MADRID ROMANDIA, 1977-1983.\nDADO en el Salón de Sesiones del H. Poder Legislativo, en la ciudad de Mexicali, Baja California, a los dos días del mes de abril de mil novecientos ochenta y dos.\nLIC. RENE TREVIÑO ARREDONDO, Diputado Presidente.\n(RÚBRICA)\nOSCAR GARZON GARATE, Diputado Secretario.\n(RÚBRICA)\nDE CONFORMIDAD CON LO DISPUESTO POR LA FRACCION I DEL ARTICULO\n49 DE LA CONSTITUCION POLITICA DEL ESTADO, MANDO SE IMPRIMA, PUBLIQUE,\nOBSERVE Y SE LE DE EL DEBIDO CUMPLIMIENTO.\nMEXICALI, CAPITAL DEL ESTADO DE BAJA CALIFORNIA, A LOS VEINTE DIAS\nDEL MES DE ABRIL DE MIL NOVECIENTOS OCHENTA Y DOS.\nEL GOBERNADOR CONSTITUCIONAL DEL ESTADO,\nC. ROBERTO DE LA MADRID ROMANDIA.\n(RÚBRICA)\nEL SECRETARIO GENERAL DE GOBIERNO,\nPROFR. MARCO ANTONIO BOLAÑOS CACHO.\n(RÚBRICA)\nARTICULO TRANSITORIO DEL DECRETO No. 124, POR EL QUE SE REFORMAN\nLOS ARTICULOS 157 Y 160, PUBLICADOS EN EL PERIODICO OFICIAL No. 21, DE\nGOBERNADOR CONSTITUCIONAL EL C. ROBERTO DE LA MADRID ROMANDIA, 1977-\n1983.\nUNICO.- El presente Decreto entrará en vigor el día siguiente al de su publicación en\nLIC. RENE TREVIÑO ARREDONDO,\nDIPUTADO PRESIDENTE, Ley de Hacienda del Estado de Baja California. Página 146\n.\nActualización Legislativa.\nÚltima reforma P.O. No. 72, Índice, 22-Dic-2023\n(RÚBRICA)\nOSCAR GARZON GARATE,\nDIPUTADO SECRETARIO,\n(RÚBRICA)\nDE CONFORMIDAD CON LO DISPUESTO POR LA FRACCION I DEL ARTICULO\n49 DE LA CONSTITUCION POLITICA DEL ESTADO, MANDO SE IMPRIMA, PUBLIQUE,\nOBSERVE Y SE LE DE EL DEBIDO CUMPLIMIENTO.\nMEXICALI, CAPITAL DEL ESTADO DE BAJA CALIFORNIA, A LOS CATORCE DIAS\nDEL MES DE JULIO DE MIL NOVECIENTOS OCHENTA Y DOS.\nEL GOBERNADOR CONSTITUCIONAL DEL ESTADO,\nC. ROBERTO DE LA MADRID ROMANDIA.\n(RÚBRICA)\nEL SECRETARIO GENERAL DE GOBIERNO,\nPROFR. MARCO ANTONIO BOLAÑOS CACHO.\n(RÚBRICA)\nARTICULO TRANSITORIO DEL DECRETO No. 165, POR LE QUE SE REFORMAN\nLOS ARTICULOS 28, 29, 30, 31, 32, 33, 34, 35, 36, 37, 38, 39, 40 Y 41, PUBLICADOS EN\nEL PERIODICO OFICIAL No. 11, DE FECHA 20 DE ABRIL DE 1983, EXPEDIDO POR LA\nH. X LEGISLATURA Y SIENDO GOBERNADOR CONSTITUCIONAL EL C. ROBERTO DE\nLA MADRID ROMANDIA, 1977-1983.\nUNICO.- El presente Decreto entrará en vigor al día siguiente de su publicación en el\nPeriódico Oficial del Estado.\nDADO en el Salón de Sesiones del H. Poder Legislativo, en la ciudad de Mexicali, Capital del Estado de Baja California, a los siete días del mes de abril de 1983.\nJOSE MANUEL DIAZ MARTINEZ,\nDIPUTADO PRESIDENTE.\nPROFRA. MA. DE LA LUZ MANGAS DE AGUNDEZ,\nDIPUTADO SECRETARIO.\n49 DE LA CONSTITUCION POLITICA DEL ESTADO, MANDO SE IMPRIMA, PUBLIQUE,\nOBSERVE Y SE LE DE EL DEBIDO CUMPLIMIENTO.\nMEXICALI, CAPITAL DEL ESTADO DE BAJA CALIFORNIA, A LOS DIECIOCHO\nDIAS DEL MES DE ABRIL DE MIL NOVECIENTOS OCHENTA Y TRES.\nLey de Hacienda del Estado de Baja California. Página 147\n.\nActualización Legislativa.\nÚltima reforma P.O. No. 72, Índice, 22-Dic-2023\nEL GOBERNADOR CONSTITUCIONAL DEL ESTADO,\nC. ROBERTO DE LA MADRID ROMANDIA.\n(RÚBRICA)\nEL SECRETARIO GENERAL DE GOBIERNO,\nPROFR. MARCO ANTONIO BOLAÑOS CACHO.\n(RÚBRICA)\nARTICULOS TRANSITORIOS DEL DECRETO No. 200, POR EL QUE SE\nREFORMAN LOS ARTICULOS 28, 29,34, 35 Y 38, PUBLICADOS EN EL PERIODICO\nOFICIAL No. 20, DE FECHA 20 DE JULIO DE 1983, EXPEDIDO POR LA H. X\nLEGISLATURA Y SIENDO GOBERNADOR CONSTITUCIONAL EL C. ROBERTO DE LA\nMADRID ROMANDIA, 1977-1983.\nPRIMERO.- El presente Decreto entrará en vigor el día siguiente al de su publicación en el Periódico Oficial, Organo del Gobierno del Estado.\nSEGUNDO.- Cuando con posterioridad a la vigencia del Impuesto Sobre Adquisición de Inmuebles y Transmisión de Dominio, se protocolicen o inscriba el reconocimiento\nJudicial de una prescripción positiva, la adjudicación de inmuebles en sucesión, remate judicial, administrativo o laboral, que se hubieren efectuado con anterioridad a esa fecha, los contribuyentes podrán determinar y pagar el Impuesto correspondiente en los términos de las disposiciones fiscales vigentes o conforme a las que regían en la fecha en que se realizaron los actos a que se refiere este Artículo.\nTERCERO.- Tratándose de los contratos a que se refiere la Fracción III del Artículo\n34 de la Ley de Hacienda del Estado, celebrados con anterioridad a la vigencia del Impuesto\nSobre Adquisición de Inmuebles y Transmisión de Dominio, se causará este impuesto al celebrarse el contrato prometido, a menos que se hubiere pagado con anticipación el\nImpuesto Federal Sobre Adquisición de Inmuebles.\nDADO en el Salón de Sesiones del H. Poder Legislativo, en la ciudad de Mexicali, Baja California, a los veintinueve días del mes de junio de 1983.\nJOSE MANUEL DIAZ MARTINEZ,\nDIPUTADO PRESIDENTE.\nPROFRA. MA. DE LA LUZ MANGAS DE AGUNDEZ,\nDIPUTADO SECRETARIO.\n49 DE LA CONSTITUCION POLITICA DEL ESTADO, MANDO SE IMPRIMA, PUBLIQUE,\nOBSERVE Y SE LE DE EL DEBIDO CUMPLIMIENTO.\nLey de Hacienda del Estado de Baja California. Página 148\n.\nActualización Legislativa.\nÚltima reforma P.O. No. 72, Índice, 22-Dic-2023\nMEXICALI, CAPITAL DEL ESTADO DE BAJA CALIFORNIA, A LOS QUINCE DIAS\nDEL MES DE JUNIO DE MIL NOVECIENTOS OCHENTA Y TRES.\nEL GOBERNADOR CONSTITUCIONAL DEL ESTADO,\nC. ROBERTO DE LA MADRID ROMANDIA.\n(RÚBRICA)\nEL SECRETARIO GENERAL DE GOBIERNO,\nPROFR. MARCO ANTONIO BOLAÑOS CACHO.\n(RÚBRICA)\nARTICULOS TRANSITORIOS DEL DECRETO No. 93, POR EL QUE SE REFORMA\nEL ARTICULO 151-13, PUBLICADO EN EL PERIODICO OFICIAL No. 5, DE FECHA 20 DE\nFEBRERO DE 1988, EXPEDIDO POR LA H. XII LEGISLATURA Y SIENDO GOBERNADOR\nCONSTITUCIONAL EL C. LIC. XICOTENCATL LEYVA MORTERA, 1983 ENE-1989.\nPRIMERO.- El Presente Decreto entrará en vigor el día siguiente al de su publicación, en el Periódico Oficial, Organo del Gobierno del Estado.\nSEGUNDO.- Se derogan todas las disposiciones Leyes o Acuerdos en lo que se contraponga con lo dispuesto en el presente Decreto.\nTERCERO.- Las personas físicas o morales, que se dediquen a las actividades señaladas en el inciso b), del Artículo 151-13 que hayan iniciado operaciones durante 1987, cumplirán con todas las obligaciones y quedarán sujetas a este Decreto a partir del 1o de enero de 1989.\nDADO en el Salón de Sesiones del H. Poder Legislativo, en la ciudad de Mexicali, Baja California, a los treinta y un días del mes de enero de mil novecientos ochenta y ocho.\nLIC. JESUS ARMANDO HERNANDEZ MONTAÑO,\nDIPUTADO PRESIDENTE.\nMANUEL TRASVIÑA PEREZ,\nDIPUTADO SECRETARIO.\n49 DE LA CONSTITUCION POLITICA DEL ESTADO, MANDO SE IMPRIMA, PUBLIQUE,\nOBSERVE Y SE LE DE EL DEBIDO CUMPLIMIENTO.\nMEXICALI, CAPITAL DEL ESTADO DE BAJA CALIFORNIA, A LOS DOS DIAS DEL\nMES DE FEBRERO DE MIL NOVECIENTOS OCHENTA Y TRES.\nLey de Hacienda del Estado de Baja California. Página 149\n.\nActualización Legislativa.\nÚltima reforma P.O. No. 72, Índice, 22-Dic-2023\nEL GOBERNADOR CONSTITUCIONAL DEL ESTADO,\nXICOTENCATL LEYVA MORTERA.\n(RÚBRICA)\nSECRETARIO GENERAL DE GOBIERNO,\nLIC. HUGO FELIX GARCIA.\n(RÚBRICA)\nARTICULOS TRANSITORIOS DEL DECRETO No. 139, POR EL QUE SE DEROGAN\nLOS ARTICULOS 65, 71,78, 79, 80, 88,88 BIS, 90 AL 96, 161 Y 162 Y SE REFORMAN LOS\nARTICULOS 44, 50, 61, 64, 67, 89, 137, 138, 141, 144, AL 146, 151-13, 152, 153, 155, 157,\n158, 160, 165, 169 Y 170, PUBLICADOS EN EL PERIODICO OFICIAL No. 36, DE FECHA\n31 DE DICIEMBRE DE 1986, EXPEDIDO POR LA H. XII LEGISLATURA Y SIENDO\nGOBERNADOR CONSTITUCIONAL EL C. LIC. XICOTENCATL LEYVA MORTERA, 1983\nENE-1989.\nUNICO.- Las Reformas y Adiciones a que se refiere el presente Decreto, entrarán en vigor al día siguiente de su publicación en el Periódico Oficial del Gobierno del Estado de\nBaja California.\nDADO en el Salón de Sesiones del H. Poder Legislativo, en la ciudad de Mexicali, Capital del Estado de Baja California, a los veintiocho días del mes de diciembre de 1988.\nMA. ELVIA VALENZUELA BARRAGAN,\nDIPUTADA PRESIDENTE.\n(RÚBRICA)\nMARIO ALFONSO VINDIOLA VELAZQUEZ,\nDIPUTADO SECRETARIO.\n(RÚBRICA)\n49 DE LA CONSTITUCION POLITICA DEL ESTADO, MANDO SE IMPRIMA, PUBLIQUE,\nOBSERVE Y SE LE DE EL DEBIDO CUMPLIMIENTO.\nMEXICALI, CAPITAL DEL ESTADO DE BAJA CALIFORNIA, A LOS TREINTA DIAS\nDEL MES DE DICIEMBRE DE MIL NOVECIENTOS OCHENTA Y OCHO.\nEL GOBERNADOR CONSTITUCIONAL DEL ESTADO,\nXICOTENCATL LEYVA MORTERA.\nSECRETARIO GENERAL DE GOBIERNO, Ley de Hacienda del Estado de Baja California. Página 150\n.\nActualización Legislativa.\nÚltima reforma P.O. No. 72, Índice, 22-Dic-2023\nLIC. HUGO FELIX GARCIA.\n(RÚBRICA)\nARTICULO TRANSITORIO DEL DECRETO No. 93, POR EL QUE SE REFORMAN\nLOS ARTICULO 172, 173, 174, 175 Y EL ARTICULO 9o., PUBLICADOS EN EL\nPERIODICO OFICIAL No. 30, DE FECHA 31 DE OCTUBRE DE 1991, EXPEDIDO POR LA\nH. XIII LEGISLATURA Y SIENDO GOBERNADOR CONSTITUCIONAL EL C. LIC.\nERNESTO RUFFO APPEL, 1989-1995.\nEl presente Decreto entrará en vigor el día siguiente al de su publicación en el\nPeriódico Oficial, Organo del Gobierno del Estado.\nDADO en el Salón de Sesiones Lic. Benito Juárez García del Honorable Poder\nLegislativo, en la Ciudad de Mexicali, Baja California, a los diez días del mes de Octubre de mil novecientos noventa y uno.\nCUAUHTEMOC CARDONA BENAVIDES,\nDIPUTADO PRESIDENTE.\n(RÚBRICA)\nCATALINO ZAVALA MARQUEZ,\nDIPUTADO SECRETARIO.\n(RÚBRICA)\nDE CONFORMIDAD CON LO DISPUESTO POR LA FRACCION I DEL ARTICULO\n49 DE LA CONSTITUCION POLITICA DEL ESTADO, MANDO SE IMPRIMA, PUBLIQUE,\nOBSERVE Y SE LE DE EL DEBIDO CUMPLIMIENTO.\nMEXICALI, BAJA CALIFORNIA, A LOS DIECISIETE DIAS DEL MES DE OCTUBRE\nDE MIL NOVECIENTOS NOVENTA Y UNO.\nEL GOBERNADOR CONSTITUCIONAL DEL ESTADO,\nLIC. ERNESTO RUFFO APPEL.\nEL SECRETARIO GENERAL DE GOBIERNO,\nC.P. FORTUNATO ALVAREZ ENRIQUEZ.\nARTICULO TRANSITORIO DEL DECRETO No. 108, POR EL QUE SE REFORMAN\nLOS ARTICULOS 156-8 AL 156-14, PUBLICADOS EN EL PERIODICO OFICIAL No. 1, DE\nSECRETARIO GENERAL DE GOBIERNO ENCARGADO DEL DESPACHO P.M.L. EL C.\nC.P. FORTUNATO ALVAREZ ENRIQUEZ.\nLey de Hacienda del Estado de Baja California. Página 151\n.\nActualización Legislativa.\nÚltima reforma P.O. No. 72, Índice, 22-Dic-2023\nUNICO.- El presente Decreto entrará en vigor el día siguiente al de su publicación en el Periódico Oficial, Organo del Gobierno del Estado.\nDADO en el Salón de Sesiones Lic. Benito Juárez García del Honorable Poder\nLegislativo, en la Ciudad de Mexicali, Baja California, a los veintiséis días del mes de diciembre de mil novecientos noventa y uno.\nCUAUHTEMOC CARDONA BENAVIDES,\nDIPUTADO PRESIDENTE.\n(RÚBRICA)\nCATALINO ZAVALA MARQUEZ,\nDIPUTADO SECRETARIO.\n(RÚBRICA)\nDE CONFORMIDAD CON LO DISPUESTO POR LA FRACCION I DEL ARTICULO\n49 DE LA CONSTITUCION POLITICA DEL ESTADO, MANDO SE IMPRIMA, PUBLIQUE,\nOBSERVE Y SE LE DE EL DEBIDO CUMPLIMIENTO.\nMEXICALI, BAJA CALIFORNIA, A LOS TREINTA DIAS DEL MES DE DICIEMBRE\nDE MIL NOVECIENTOS NOVENTA Y UNO.\nEL SECRETARIO GENERAL DE GOBIERNO\nENCARGADO DEL DESPACHO POR MINISTERIO DE LEY.\nC.P. FORTUNATO ALVAREZ ENRIQUEZ.\n(RÚBRICA)\nEL OFICIAL MAYOR DE GOBIERNO\nENCARGADO DE LA SECRETARIA GENERAL\nDE GOBIERNO POR MINISTERIO DE LEY.\nLIC. RENE A. CORELLA GIL SAMANIEGO.\n(RÚBRICA)\nARTICULO TRANSITORIO DEL DECRETO No. 129, POR EL QUE SE REFORMA\nEL ARTICULO 42, PUBLICADO EN EL PERIODICO OFICIAL No. 14, DE FECHA 10 DE\nCONSTITUCIONAL EL C. LIC. ERNESTO RUFFO APPEL, 1989-1995.\nUNICO.- El presente Decreto entrará en vigor, el día siguiente al de su publicación en\nLegislativo, en la Ciudad de Mexicali, Baja California, a los nueve días del mes de abril de mil novecientos noventa y dos.\nROSENDO MONTOYA LUGO, Ley de Hacienda del Estado de Baja California. Página 152\n.\nActualización Legislativa.\nÚltima reforma P.O. No. 72, Índice, 22-Dic-2023\nDIPUTADO PRESIDENTE.\n(RÚBRICA)\nDOLORES DE MA. MANUELL GOMEZ DE MENDEZ,\nDIPUTADO SECRETARIO.\n(RÚBRICA)\nDE CONFORMIDAD CON LO DISPUESTO POR LA FRACCION I DEL ARTICULO\n49 DE LA CONSTITUCION POLITICA DEL ESTADO, MANDO SE IMPRIMA, PUBLIQUE,\nOBSERVE Y SE LE DE EL DEBIDO CUMPLIMIENTO.\nMEXICALI, BAJA CALIFORNIA, A LOS VEINTISIETE DIAS DEL MES DE ABRIL DE\nMIL NOVECIENTOS NOVENTA Y DOS.\nEL GOBERNADOR CONSTITUCIONAL DEL ESTADO,\nLIC. ERNESTO RUFFO APPEL,\n(RÚBRICA)\nEL SECRETARIO GENERAL DE GOBIERNO,\nC.P. FORTUNATO ALVAREZ ENRIQUEZ.\n(RÚBRICA)\nARTICULO TRANSITORIO DEL DECRETO No. 53, POR EL QUE SE REFORMA EL\nARTICULO 172, PUBLICADO EN EL PERIODICO OFICIAL No. 38, DE FECHA 17 DE\nSEPTIEMBRE DE 1993, EXPEDIDO POR LA H. XIV LEGISLATURA Y SIENDO\nGOBERNADOR CONSTITUCIONAL EL C. LIC. ERNESTO RUFFO APPEL, 1989-1995.\nUNICO.- El presente Decreto entrará en vigor, el día siguiente al de su publicación en el Periódico Oficial, Organo del Gobierno del Estado.\nLegislativo, en la Ciudad de Mexicali, Baja California, a los veinticinco días del mes de agosto de mil novecientos noventa y tres.\nFRANCISCO JAVIER REYNOSO NUÑO,\nDIPUTADO PRESIDENTE.\nCESAR ALEJANDRO MONRAZ SUSTAITA,\nDIPUTADO SECRETARIO.\n49 DE LA CONSTITUCION POLITICA DEL ESTADO, MANDO SE IMPRIMA, PUBLIQUE,\nOBSERVE Y SE LE DE EL DEBIDO CUMPLIMIENTO.\nLey de Hacienda del Estado de Baja California. Página 153\n.\nActualización Legislativa.\nÚltima reforma P.O. No. 72, Índice, 22-Dic-2023\nMEXICALI, BAJA CALIFORNIA, A LOS TRES DIAS DEL MES DE SEPTIEMBRE DE\nMIL NOVECIENTOS NOVENTA Y TRES.\nEL GOBERNADOR CONSTITUCIONAL DEL ESTADO,\nLIC. ERNESTO RUFFO APPEL.\n(RÚBRICA)\nEL SECRETARIO GENERAL DE GOBIERNO,\nC.P. FORTUNATO ALVAREZ ENRIQUEZ.\n(RÚBRICA)\nARTICULO TRANSITORIO DEL DECRETO No. 55, PUBLICADO EN EL PERIODICO\nOFICIAL No. 44, DE FECHA 29 DE OCTUBRE DE 1993, EXPEDIDO POR LA\nHONORABLE XIV LEGISLATURA, POR EL QUE SE REFORMAN LOS ARTICULOS 140,\n143 Y SE ADICIONAN EL 143-1, 143-2, 143-3, 143-4, 143-5, 151-13, 151-18, SIENDO\nGOBERNADOR CONSTITUCIONAL EL CIUDADANO L.A.E. ERNESTO RUFFO APPEL, 1989-1995.\nARTICULO UNICO.- El presente Decreto entrará en vigor el día siguiente al de su publicación en el Periódico Oficial, Organo del Gobierno del Estado.\nDADO en el Salón de Sesiones Lic. Benito Juárez García del H. Poder Legislativo del\nEstado, en la ciudad de Mexicali, Baja California, a los siete días del mes de octubre de mil novecientos noventa y tres.\nPROFR. CARLOS FLORES REYES,\nDIPUTADO PRESIDENTE.\n(RÚBRICA)\nFRANCISCO JAVIER ZEPEDA VILLASEÑOR,\nDIPUTADO SECRETARIO.\n(RÚBRICA)\n49 DE LA CONSTITUCION POLITICA DEL ESTADO, MANDO SE IMPRIMA, PUBLIQUE,\nOBSERVE Y SE LE DE EL DEBIDO CUMPLIMIENTO.\nMEXICALI, BAJA CALIFORNIA, A LOS QUINCE DIAS DEL MES DE OCTUBRE DE\nMIL NOVECIENTOS NOVENTA Y TRES.\nEL GOBERNADOR CONSTITUCIONAL DEL ESTADO,\nLIC. ERNESTO RUFFO APPEL.\nEL SECRETARIO GENERAL DE GOBIERNO, Ley de Hacienda del Estado de Baja California. Página 154\n.\nActualización Legislativa.\nÚltima reforma P.O. No. 72, Índice, 22-Dic-2023\nC.P. FORTUNATO ALVAREZ ENRIQUEZ.\n(RÚBRICA)\nARTICULO TRANSITORIO DEL DECRETO No. 45, POR EL QUE SE MODIFICA LA\nDENOMINACION DEL TITULO NOVENO Y LOS ARTICULOS 172, 173, 174 Y 175,\nPUBLICADO EN EL PERIODICO OFICIAL No. 61, TOMO CIII, DE FECHA 27 DE\nDICIEMBRE DE 1996, EXPEDIDO POR LA H. XV LEGISLATURA Y SIENDO\nGOBERNADOR CONSTITUCIONAL EL C. LIC. HECTOR TERAN TERAN 1995-1998.\nARTICULO UNICO.- El presente Decreto entrará en vigor el siguiente día al de su publicación en el Periódico Oficial Gobierno del Estado.\nLegislativo en la Ciudad de Mexicali, Baja California, a los treinta y un días del mes de octubre de mil novecientos noventa y seis.\nDR. ENRIQUE JOSE ECHEGARAY LEDESMA,\nDIPUTADO PRESIDENTE.\n(RÚBRICA)\nLIC. MA. DE LA LUZ OCAÑA RODRIGUEZ,\nDIPUTADO SECRETARIO.\n(RÚBRICA)\nDE CONFORMIDAD CON LO DISPUESTO POR LA FRACCION I DEL ARTICULO\n49 DE LA CONSTITUCION POLITICA DEL ESTADO, MANDO SE IMPRIMA, PUBLIQUE,\nOBSERVE Y SE LE DE EL DEBIDO CUMPLIMIENTO.\nMEXICALI, BAJA, CALIFORNIA, A LOS DOCE DIAS DEL MES DE DICIEMBRE DE\nMIL NOVECIENTOS NOVENTA Y SEIS.\nEL GOBERNADOR CONSTITUCIONAL DEL ESTADO,\nLIC. HECTOR TERAN TERAN.\nEL SECRETARIO GENERAL DE GOBIERNO,\nLIC. RODOLFO VALDEZ GUTIERREZ.\nARTICULO TRANSITORIO DEL DECRETO No. 63, PUBLICADO EN EL PERIODICO\nHONORABLE XV LEGISLATURA, POR EL QUE SE REFORMA EL ARTICULO PRIMERO\nDEL DECRETO No. 164, PUBLICADO EN EL PERIODICO OFICIAL DE FECHA 31 DE\nLey de Hacienda del Estado de Baja California. Página 155\n.\nActualización Legislativa.\nÚltima reforma P.O. No. 72, Índice, 22-Dic-2023\nDICIEMBRE DE 1979, ASI COMO REFORMA A LA DENOMINACION DEL CAPITULO VIII,\nY SUS ARTICULOS 127, 128, 129, 130, 131, 132 Y SE ADICIONA EL ARTICULO 132 BIS\nY LA FRACCION VII AL ARTICULO 173, SIENDO GOBERNADOR CONSTITUCIONAL EL\nC. LIC. HECTOR TERAN TERAN 1995-1998.\nARTICULO UNICO.- El presente Decreto entrará en vigor el día siguiente al de su publicación en el Periódico Oficial del Gobierno del Estado de Baja California.\nDADO en el Salón de Sesiones Lic. Benito Juárez García del honorable Poder\nLegislativo, en la Ciudad de Mexicali, Baja California, a los diecinueve días del mes de diciembre de mil novecientos noventa y seis.\nDR. ENRIQUE JOSE ECHEGARAY LEDESMA.\nDIPUTADO PRESIDENTE.\n(RÚBRICA)\nLIC. MA. DE LA LUZ OCAÑA RODRIGUEZ.\nDIPUTADO SECRETARIO.\n(RÚBRICA)\nDE CONFORMIDAD CON LO DISPUESTO POR LA FRACCION I DEL ARTICULO\n49 DE LA CONSTITUCION POLITICA DEL ESTADO, MANDO SE IMPRIMA, PUBLIQUE,\nOBSERVE Y SE LE DE EL DEBIDO CUMPLIMIENTO.\nMEXICALI, BAJA CALIFORNIA, A LOS VEINTISEIS DIAS DEL MES DE DICIEMBRE\nDE MIL NOVECIENTOS NOVENTA Y SEIS.\nEL GOBERNADOR CONSTITUCIONAL DEL ESTADO\nLIC. HECTOR TERAN TERAN\n(RÚBRICA)\nEL SECRETARIO GENERAL DE GOBIERNO.\nLIC. RODOLFO VALDEZ GUTIERREZ.\nARTICULO TRANSITORIO DEL DECRETO No. 122, DONDE SE REFORMAN LOS\nARTICULOS 151-13 EN EL SEGUNDO PARRAFO DEL INCISO B), Y EN SU PENULTIMO\nPARRAFO; 151-14; 151-16; 151-18 EN SU SEGUNDO PARRAFO; 151-19 Y 151-20\nFRACCION II, TODOS DE LA LEY DE HACIENDA DEL ESTADO DE BAJA CALIFORNIA;\nTOMO CV, EXPEDIDO POR LA HONORABLE XV LEGISLATURA DEL ESTADO, SIENDO\nGOBERNADOR CONSTITUCIONAL EL C. LIC. HECTOR TERAN TERAN, 1995-1998.\nLey de Hacienda del Estado de Baja California. Página 156\n.\nActualización Legislativa.\nÚltima reforma P.O. No. 72, Índice, 22-Dic-2023\nUNICO.- El presente Decreto entrará en vigor el día primero de enero de 1998.\nDADO en el Salón de Sesiones Lic. Benito Juárez García del Honorable Poder\nLegislativo, en la Ciudad de Mexicali, Baja California, a los veintisiete días del mes de noviembre de mil novecientos noventa y siete.\nLIC. JAVIER JULIAN CASTAÑEDA POMPOSO\nDIPUTADO PRESIDENTE\n(RÚBRICA)\nPROFR. ROGELIO APPEL CHACON\nDIPUTADO SECRETARIO\n(RÚBRICA)\nDE CONFORMIDAD CON LO DISPUESTO POR LA FRACCION I DEL ARTICULO\n49 DE LA CONSTITUCION POLITICA DEL ESTADO, MANDO SE IMPRIMA Y PUBLIQUE.\nMEXICALI, BAJA CALIFORNIA, A LOS CUATRO DIAS DEL MES DE FEBRERO DE\nMIL NOVECIENTOS NOVENTA Y OCHO.\nEL GOBERNADOR CONSTITUCIONAL DEL ESTADO\nHECTOR TERAN TERAN.\n(RÚBRICA)\nEL SECRETARIO GENERAL DE GOBIERNO\nRODOLFO VALDEZ GUTIERREZ\n(RÚBRICA)\nARTICULO TRANSITORIO UNICO DEL DECRETO NO. 170, POR EL QUE SE\nADICIONA LA DENOMINACION DEL TITULO NOVENO Y REFORMA LOS ARTICULOS\n172, 173, 174 Y 175, PUBLICADO EN EL PERIODICO OFICIAL NO. 8, DE FECHA 25 DE\nFEBRERO DEL 2000, TOMO CVII, EXPEDIDO POR LA H. XVI LEGISLATURA, SIENDO\nGOBERNADOR CONSTITUCIONAL EL C. LIC. ALEJANDRO GONZALEZ ALCOCER 7 DE\nPRIMERO.- El presente Decreto, entrará en vigor al día siguiente de su publicación en el Periódico Oficial del Estado de Baja California.\nSEGUNDO.- Se derogan todas las disposiciones que se opongan al presente\nDecreto.\nDADO en el Salón de Sesiones “Benito Juárez García”, del Honorable Poder\nLegislativo, en la Ciudad de Mexicali, Baja California, a los treinta y un días del mes de enero del año dos mil.\nDR. EFREN MACIAS LEZAMA\nLey de Hacienda del Estado de Baja California. Página 157\n.\nActualización Legislativa.\nÚltima reforma P.O. No. 72, Índice, 22-Dic-2023\nDIPUTADO PRESIDENTE\n(RÚBRICA)\nPROFRA. OLIVIA VILLALAZ BECERRA\nDIPUTADA SECRETARIA\n(RÚBRICA)\nDE CONFORMIDAD CON LO DISPUESTO POR LA FRACCION I DEL ARTICULO\n49 DE LA CONSTITUCION POLITICA DEL ESTADO MANDO SE IMPRIMA Y PUBLIQUE.\nMEXICALI, BAJA CALIFORNIA A LOS DIEZ DIAS DEL MES DE FEBRERO DEL\nAÑO DOS MIL.\nEL GOBERNADOR CONSTITUCIONAL DEL ESTADO\nLIC. ALEJANDRO GONZALEZ ALCOCER\n(RÚBRICA)\nEL SECRETARIO GENERAL DE GOBIERNO\nC.P. JORGE RAMOS\n(RÚBRICA)\nARTICULO TRANSITORIO DEL DECRETO No. 240, POR EL QUE SE REFORMAN\nLOS ARTICULOS 69, 72 ÚLTIMO PARRAFO, 83, 119, 130 SEGUNDO PARRAFO, 131,\n140, 143-3 FRACCION III Y IV INCISO D), 143-4, 146 FRACCION I Y ULTIMO PARRAFO,\n147, 151-6, 151-7, 151-9 FRACCION I Y III, 151-10, 151-25, 151-26 FRACCION I, 151-27,\n151-29 PRIMER PARRAFO, 156-6 Y 156-13 FRACCION III DE LA LEY DE HACIENDA DEL\nESTADO DE BAJA CALIFORNIA, PUBLICADO EN EL PERIODICO OFICIAL No. 52, DE\nFECHA 4 DE DICIEMBRE DE 2000, TOMO CVII, EXPEDIDA POR LA HONORABLE XVI\nLEGISLATURA DEL ESTADO, SIENDO GOBERNADOR CONSTITUCIONAL EL C. LIC.\nALEJANDRO GONZALEZ ALCOCER, OCTUBRE DE 1998-2001.\nUNICO.- Las presentes reformas entrarán en vigor al día siguiente de su publicación en el Periódico Oficial del Estado de Baja California.\nDADO en el Salón de Sesiones “Lic. Benito Juárez García” del Honorable Poder\nLegislativo, en la Ciudad de Mexicali, Baja California, a los diecinueve días del mes de octubre del año dos mil.\nDIP. JUAN MANUEL MOLINA RODRIGUEZ\nPRESIDENTE\nDIP. DR. EFREN MACIAS LEZAMA\nSECRETARIO\nLey de Hacienda del Estado de Baja California. Página 158\n.\nActualización Legislativa.\nÚltima reforma P.O. No. 72, Índice, 22-Dic-2023\nDE CONFORMIDAD CON LO DISPUESTO POR LA FRACCION I DEL ARTICULO\n49 DE LA CONSTITUCION POLITICA DEL ESTADO, MANDO SE IMPRIMA Y PUBLIQUE.\nMEXICALI, BAJA CALIFORNIA, A LOS OCHO DIAS DEL MES DE NOVIEMBRE DEL\nAÑO DOS MIL.\nEL GOBERNADOR CONSTITUCIONAL DEL ESTADO.\nLIC. ALEJANDRO GONZALEZ ALCOCER\n(RÚBRICA)\nEL SECRETARIO GENERAL DE GOBIERNO\nC.P. JORGE RAMOS\n(RÚBRICA)\nARTICULO UNICO TRANSITORIO DEL DECRETO NO. 369, POR EL QUE SE\nREFORMA EL ARTICULO 173, PUBLICADO EN EL PERIODICO OFICIAL NO. 49, DE\nFECHA 9 DE NOVIEMBRE DE 2001, TOMO CVIII, EXPEDIDO POR LA H. XVI\nLEGISLATURA, SIENDO GOBERNADOR CONSTITUCIONAL EL C. LIC. ALEJANDRO\nGONZALEZ ALCOCER 1998-2001.\nPRIMERO.- El presente Decreto entrará en vigor al día siguiente a su publicación en el Periódico Oficial del Estado\nSEGUNDO.- Hasta en tanto no e concrete la asunción de facultades y funciones por parte de los Ayuntamientos, se seguirán aplicando las disposiciones legales anteriores a la presente reforma.\nDADO en el Salón de Sesiones “Lic. Benito Juárez García” del Honorable Poder\nLegislativo, en la Ciudad de Mexicali, Baja California, a los dieciocho días del mes de septiembre del año dos mil uno.\nDIP. ALEJANDRO PEDRIN MARQUEZ\nPRESIDENTE\nDIP. GILBERTO FLOREZ MUÑOZ\nSECRETARIO\n49 DE LA CONSTITUCION POLITICA DEL ESTADO, MANDO SE IMPRIMA Y PUBLIQUE.\nMEXICALI, BAJA CALIFORNIA, A LOS ONCE DIAS DEL MES DE OCTUBRE DEL\nAÑO DOS MIL UNO.\nEL GOBERNADOR CONSTITUCIONAL DEL ESTADO\nLey de Hacienda del Estado de Baja California. Página 159\n.\nActualización Legislativa.\nÚltima reforma P.O. No. 72, Índice, 22-Dic-2023\nLIC. ALEJANDRO GONZALEZ ALCOCER\n(RÚBRICA)\nEL SECRETARIO GENERAL DE GOBIERNO\nC.P. JORGE RAMOS\n(RÚBRICA)\nARTICULO UNICO TRANSITORIO DEL DECRETO NO. 34, POR EL QUE SE\nADICIONA UN SEGUNDO PARRAFO AL ARTICULO 151-16, PUBLICADO EN EL\nPERIODICO OFICIAL NO. 8, DE FECHA 22 DE FEBRERO DE 2002, SECCION II,\nEXPEDIDO POR LA H. XVII LEGISLATURA, SIENDO GOBERNADOR CONSTITUCIONAL\nEL C. EUGENIO ELORDUY WALTHER 2001-2007.\nUNICO.- La presente reforma, entrará en vigor al día siguiente de su publicación en el\nPeriódico Oficial del Estado de Baja California.\nDADO en el Salón de Sesiones “Lic. Benito Juárez García” del Honorable Poder\nLegislativo, en la Ciudad de Mexicali, Baja California, a los diecisiete días del mes de enero del año dos mil dos.\nDIP. RAUL FELIPE RUIZ\nPRESIDENTE\n(RÚBRICA)\nDIP. ISMAEL QUINTERO PEÑA\nSECRETARIO\n(RÚBRICA)\nDE CONFORMIDAD CON LO DISPUESTO POR LA FRACCION I DEL ARTICULO\n49 DE LA CONSTITUCION POLITICA DEL ESTADO, MANDO SE IMPRIMA Y PUBLIQUE.\nMEXICALI, BAJA CALIFORNIA, A LOS VEINTIUN DIAS DEL MES DE FEBRERO\nDEL AÑO DOS MIL DOS.\nEL GOBERNADOR DEL ESTADO\nEUGENIO ELORDUY WALTHER\nEL SECRETARIO GENERAL DE GOBIERNO\nBERNARDO BORBON VILCHES.\nARTICULO UNICO TRANSITORIO DEL DECRETO No. 133, POR EL QUE SE\nREFORMAN LOS ARTICULOS 67, 131, 151-19 y 156-13, PUBLICADO EN EL PERIODICO\nLey de Hacienda del Estado de Baja California. Página 160\n.\nActualización Legislativa.\nÚltima reforma P.O. No. 72, Índice, 22-Dic-2023\nOFICIAL No. 57, DE FECHA 31 DE DICIEMBRE DE 2002, SECCION VIII, TOMO CIX,\nEXPEDIDO POR LA H. XVII LEGISLATURA, SIENDO GOBERNADOR CONSTITUCIONAL\nEL C. EUGENIO ELORDUY WALTHER 2001-2007.\nPRIMERO.- Las presentes reformas, entrarán en vigor el día primero de enero del dos mil tres.\nSEGUNDO.- El entero de los impuestos que se causen hasta el mes de diciembre del ejercicio fiscal del 2002, y cuyo plazo se modifica en el presente\nDecreto, deberá efectuarse en términos de las disposiciones legales que se encontraban vigentes al momento de su causación.\nDADO en el Salón de Sesiones “Lic. Benito Juárez García” del Honorable\nPoder Legislativo, en la ciudad de Mexicali, Baja California, a los veintitrés días del mes de diciembre del año dos mil dos.\nDIP. MARIA ROSALVA MARTIN NAVARRO\nPRESIDENTA\n(RÚBRICA)\nDIP. JUAN MANUEL SALAZAR CASTRO\nSECRETARIO\n(RÚBRICA)\nDE CONFORMIDAD CON LO DISPUESTO POR LA FRACCION I DEL ARTICULO\n49 DE LA CONSTITUCION POLITICA DEL ESTADO, MANDO SE IMPRIMA Y PUBLIQUE.\nMEXICALI, BAJA CALIFORNIA, A LOS TREINTA Y UN DIAS DEL MES DE\nDICIEMBRE DEL AÑO DOS MIL DOS.\nGOBERNADOR DEL ESTADO\nEUGENIO ELORDUY WALTHER\nSECRETARIO GENERAL DE GOBIERNO\nBERNARDO H. MARTINEZ AGUIRRE\nARTICULO UNICO TRANSITORIO DEL DECRETO No. 144, POR EL QUE SE\nADICIONA UN CAPITULO XX DE IMPUESTO AMBIENTAL, Y LOS ARTICULOS 156-15,\n156-16, 156-17, 156-18, 156-19, 156-20, 156-21, PUBLICADO EN EL PERIODICO OFICIAL\nLey de Hacienda del Estado de Baja California. Página 161\n.\nActualización Legislativa.\nÚltima reforma P.O. No. 72, Índice, 22-Dic-2023\nNo. 57, DE FECHA 31 DE DICIEMBRE DE 2002, SECCION VIII, TOMO CIX, EXPEDIDO\nPOR LA H. XVII LEGISLATURA, SIENDO GOBERNADOR CONSTITUCIONAL EL C.\nEUGENIO ELORDUY WALTHER 2001-2007.\nUNICO.- La presente adición entrará en vigor el día primero de Enero del año dos mil tres.\nDADO en el Salón de Sesiones “Lic. Benito Juárez García” del Honorable\nPoder Legislativo, en la ciudad de Mexicali, Baja California, a los veintitrés días del mes de diciembre del año dos mil dos.\nDIP. MARIA ROSALVA MARTIN NAVARRO\nPRESIDENTA\n(RÚBRICA)\nDIP. JESUS ALEJANDRO RUIZ URIBE\nPROSECRETARIO\n(RÚBRICA)\nDE CONFORMIDAD CON LO DISPUESTO POR LA FRACCION I DEL ARTICULO\n49 DE LA CONSTITUCION POLITICA DEL ESTADO, MANDO SE IMPRIMA Y PUBLIQUE.\nMEXICALI, BAJA CALIFORNIA, A LOS TREINTA Y UN DIAS DEL MES DE\nDICIEMBRE DEL AÑO DOS MIL DOS.\nGOBERNADOR DEL ESTADO\nEUGENIO ELORDUY WALTHER\n(RÚBRICA)\nSECRETARIO GENERAL DE GOBIERNO\nBERNARDO H. MARTINEZ AGUIRRE\nARTICULO UNICO TRANSITORIO DEL DECRETO No. 241, POR EL QUE SE\nDEROGA EL CAPITULO XX DE IMPUESTO AMBIENTAL, Y LOS ARTICULOS 156-15, 15616, 156-17, 156-18, 156-19, 156-20, 156-21, PUBLICADO EN EL PERIODICO OFICIAL No.\nLEGISLATURA, SIENDO GOBERNADOR CONSTITUCIONAL EL C. EUGENIO ELORDUY\nWALTHER 2001-2007.\nUNICO.- Las presentes reformas entrarán en vigor al día siguiente de su publicación en el Periódico Oficial del Estado.\nLey de Hacienda del Estado de Baja California. Página 162\n.\nActualización Legislativa.\nÚltima reforma P.O. No. 72, Índice, 22-Dic-2023\nDADO en el Salón de Sesiones “Lic. Benito Juárez García” del Honorable\nPoder Legislativo, en la ciudad de Mexicali, Baja California, a los diecinueve días del mes de noviembre del año dos mil tres.\nDIP. LEOPOLDO MORAN DIAZ\nPRESIDENTE\n(RÚBRICA)\nDIP. ARTURO ALVARADO GONZALEZ\nPROSECRETARIO\n(RÚBRICA)\nDE CONFORMIDAD CON LO DISPUESTO POR LA FRACCION I DEL ARTICULO\n49 DE LA CONSTITUCION POLITICA DEL ESTADO, IMPRIMASE Y PUBLIQUE.\nMEXICALI, BAJA CALIFORNIA, A LOS CUATRO DIAS DEL MES DE DICIEMBRE\nDEL AÑO DOS MIL TRES.\nGOBERNADOR DEL ESTADO\nEUGENIO ELORDUY WALTHER\n(RÚBRICA)\nSECRETARIO GENERAL DE GOBIERNO\nBERNARDO H. MARTINEZ AGUIRRE\n(RÚBRICA)\nARTICULO PRIMERO TRANSITORIO DEL DECRETO No. 284, POR EL QUE SE\nREFORMAN LOS ARTICULOS 42, 151-13, 151-14, 155-15, 155-17, 151-18 y 151-20\nPUBLICADO EN EL PERIODICO OFICIAL No. 15, DE FECHA 02 DE ABRIL DE 2004,\nSECCION II, TOMO CXI, EXPEDIDO POR LA H. XVII LEGISLATURA, SIENDO\nGOBERNADOR CONSTITUCIONAL EL C. EUGENIO ELORDUY WALTHER 2001-2007.\nARTICULO PRIMERO.- El presente Decreto entrará en vigor al día siguiente al de su publicación en el Periódico Oficial del Estado de Baja California.\nARTICULO SEGUNDO.- Los procedimientos, trámites y recursos administrativos, que se hubieren iniciado antes de la entrada en vigor de este Decreto, continuarán su se iniciaron.\nARTICULO TERCERO.- Las infracciones cometidas antes de la entrada en vigor de este Decreto, se sancionarán en los términos preceptuados por las disposiciones vigentes\nLey de Hacienda del Estado de Baja California. Página 163\n.\nActualización Legislativa.\nÚltima reforma P.O. No. 72, Índice, 22-Dic-2023 en la época en que se cometieron. En caso de que las disposiciones vigentes prevean una multa distinta, se sancionará con la que resulte más benéfica para el contribuyente.\nDADO.- En el Salón de Sesiones “Lic. Benito Juárez García” del Honorable Poder\nLegislativo, en la Ciudad de Mexicali, Baja California, a los veinticuatro días del mes de marzo del año dos mil cuatro.\nDIP. FRANCISCO RUEDA GÓMEZ\nPRESIDENTE\n(RÚBRICA)\nDIP. JOSÉ ANTONIO ARAIZA REGALADO\nSECRETARIO\n(RÚBRICA)\nDE CONFORMIDAD CON LO DISPUESTO POR LA FRACCION I DEL ARTICULO\n49 DE LA CONSTITUCION POLITICA DEL ESTADO, MANDO SE IMPRIMA Y PUBLIQUE.\nMEXICALI, BAJA CALIFORNIA, A LOS VEINTISÉIS DIAS DEL MES DE MARZO\nDEL AÑO DOS MIL CUATRO.\nGOBERNADOR DEL ESTADO\nEUGENIO ELORDUY WALTHER\n(RÚBRICA)\nSECRETARIO GENERAL DE GOBIERNO\nBERNARDO H. MARTINEZ AGUIRRE\n(RÚBRICA)\nARTICULO UNICO TRANSITORIO DEL DECRETO No. 55, POR EL QUE SE\nREFORMAN LOS ARTICULOS 151-13, 172, 173, 174, 175, Y ADICIONAN ARTICULOS\n176, 177, 178 Y 179, PUBLICADOS EN EL PERIODICO OFICIAL NO. 27 DE FECHA 10 DE\nJUNIO DEL 2005, TOMO CXII, EXPEDIDO POR LA H. XVIII LEGISLATURA, SIENDO\nGOBERNADOR CONSTITUCIONAL EL C. EUGENIO ELORDUY WALTHER 2001-2007.\nARTÍCULO PRIMERO.- Las presentes reformas entrarán en vigor al día siguiente de su publicación en el Periódico Oficial del Estado de Baja California.\nARTÍCULO SEGUNDO.- Derogado.\nArtículo Transitorio Derogado\nLey de Hacienda del Estado de Baja California. Página 164\n.\nActualización Legislativa.\nÚltima reforma P.O. No. 72, Índice, 22-Dic-2023\nARTÍCULO TERCERO.- Las personas físicas y morales, que con anterioridad a la entrada en vigor de las presentes reformas hubieren sido sujetas del beneficio que se encontraba previsto en el inciso b) del artículo 151-13 de esta Ley, continuarán gozando de este hasta en tanto concluya el período por el cual se hicieron acreedores al mismo, siempre y cuando continúen realizando las operaciones por las que les correspondió, y no reciban un estímulo fiscal en los términos del artículo 175 de las presentes reformas.\nARTÍCULO CUARTO.- Las Empresas que inicien la ejecución de un Proyecto de\nInversión durante el ejercicio fiscal en el que entre en vigor las presentes reformas, podrán ser sujetas al otorgamiento de un Estímulo fiscal, siempre y cuando obtengan la puntuación requerida para tal efecto.\nARTÍCULO QUINTO.- Asimismo las empresas que estén tratando aguas residuales y las reutilicen totalmente, durante el ejercicio fiscal en el que entre en vigor las presentes reformas, podrán ser sujetas al otorgamiento del Estímulo fiscal, previsto en el artículo 178 de esta Ley.\nDADO en el Salón de Sesiones “Lic. Benito Juárez García” del Honorable Poder\nLegislativo, en la Ciudad de Mexicali, Baja California, a los diecinueve días del mes de mayo del año dos mil cinco.\nDIP. ABRAHAM CORREA ACEVEDO\nPRESIDENTE\n(RÚBRICA)\nDIP. GILBERTO DANIEL GONZÁLEZ SOLÍS\nSECRETARIO\n(RÚBRICA)\nDE CONFORMIDAD CON LO DISPUESTO POR LA FRACCION I DEL ARTICULO 49\nMEXICALI, BAJA CALIFORNIA, A LOS TRES DIAS DEL MES DE JUNIO DEL AÑO\nDOS MIL CINCO.\nGOBERNADOR CONSTITUCIONAL DEL ESTADO\nEUGENIO ELORDUY WALTER\nSECRETARIO GENERAL DE GOBIERNO\nBERNARDO H. MARTINEZ AGUIRRE.\nLey de Hacienda del Estado de Baja California. Página 165\n.\nActualización Legislativa.\nÚltima reforma P.O. No. 72, Índice, 22-Dic-2023\nARTICULO ÚNICO TRANSITORIO DEL DECRETO NO. 185, POR EL QUE SE\nREFORMAN LOS ARTÍCULOS 175 Y 178 Y ADICIONA EL ARTICULO 180, PUBLICADO\nEN EL PERIODICO OFICIAL NO. 9, DE FECHA 24 DE FEBRERO DE 2006, SECCIÓN I,\nTOMO CXIII, EXPEDIDO POR LA H. XVIII LEGISLATURA, SIENDO GOBERNADOR\nCONSTITUCIONAL EL C. EUGENIO ELORDUY WALTHER 2001-2007.\nARTÍCULO PRIMERO.- Las presentes reformas entrarán en vigor al día siguiente de su publicación en el Periódico Oficial del Estado de Baja California.\nARTÍCULO SEGUNDO.- Las personas físicas y morales, que con anterioridad a la entrada en vigor de las presentes reformas, hubieren sido sujetas de los beneficios que se encontraban previstos en el Artículo Segundo Transitorio, del Decreto No. 55, publicado en el Periódico Oficial del Estado, en fecha 10 de junio de 2005 seguirán gozando de los mismos, siempre y cuando continúen realizando las operaciones por las que les correspondió dicho beneficio, en los siguientes porcentajes:\nI. Durante el ejercicio fiscal 2006 en un 90%;\nII. Durante el ejercicio fiscal 2007 en un 80%, y\nIII. Durante el ejercicio fiscal 2008 en un 70%.\nEstos beneficios no serán aplicables a las Empresas que reciban un estímulo fiscal, en los términos del artículo 175 de la Ley de Hacienda del Estado de Baja California.\nSe condona a los contribuyentes a que se refiere este artículo, del pago del impuesto sobre remuneraciones al trabajo personal causado del primero de enero de 2006 hasta la entrada en vigor de la presente reforma, en el porcentaje que sea necesario para alcanzar la exención establecida en la fracción I.\nARTÍCULO TERCERO.- Se deroga el Artículo Segundo Transitorio, del Decreto No.\n55, publicado en el Periódico Oficial del Estado, en fecha 10 de junio de 2005.\nARTÍCULO CUARTO.- Las empresas que se encontraban gozando de la exención señalada en el artículo 178 del ordenamiento materia de esta reforma, deberán presentar dentro de los noventa días siguientes a la entrada en vigor del presente Decreto, la solicitud señalada en el artículo 14 de la Ley de Fomento a la Competitividad y Desarrollo Económico para el Estado de Baja California, para efecto de que la autoridad competente determine en su caso, la procedencia del estímulo fiscal en los términos de las disposiciones contenidas en el artículo 178 que se modifica mediante este Decreto. En tanto se resuelve la solicitud referida, las empresas continuarán gozando de la exención señalada.\nUna vez transcurrido el plazo de noventa días previstos en el párrafo anterior, se presentado la solicitud correspondiente.\nLey de Hacienda del Estado de Baja California. Página 166\n.\nActualización Legislativa.\nÚltima reforma P.O. No. 72, Índice, 22-Dic-2023\nARTÍCULO QUINTO.- Se condona a los contribuyentes a que se refiere el artículo\n180 de esta reforma, del pago del impuesto sobre remuneraciones al trabajo personal causado del primero de enero de 2006 hasta la entrada en vigor de este Decreto, en los mismos términos y porcentajes que se establecen en dicho artículo.\nDADO en el Salón de Sesiones “Lic. Benito Juárez García” del Honorable Poder\nLegislativo, en la Ciudad de Mexicali, Baja California, a los treinta y un días del mes de enero del año dos mil seis.\nDIP. ELVIRA LUNA PINEDA\nPRESIDENTA\n(RÚBRICA)\nDIP. ELIAS LOPEZ MENDOZA\nSECRETARIO\n(RÚBRICA)\nDE CONFORMIDAD CON LO DISPUESTO POR LA FRACCION I DEL ARTICULO\n49 DE LA CONSTITUCION POLITICA DEL ESTADO, IMPRIMASE Y PUBLIQUESE.\nMEXICALI, BAJA CALIFORNIA, A CATORCE DE FEBRERO DEL AÑO DOS MIL\nSEIS.\nGOBERNADOR DEL ESTADO.\nEUGENIO ELORDUY WALTHER\n(RÚBRICA)\nSECRETARIO GENERAL DE GOBIERNO\nBERNARDO H. MARTINEZ AGUIRRE\n(RÚBRICA)\nARTICULO PRIMERO TRANSITORIO DEL DECRETO NO. 356, POR EL QUE SE\nADICIONA EL ARTÍCULO 181, PUBLICADO EN EL PERIODICO OFICIAL No. 36, DE\nLEGISLATURA, SIENDO GOBERNADOR CONSTITUCIONAL EL C. EUGENIO ELORDUY\nWALTHER 2001-2007.\nTRANSITORIOS\nARTÍCULO PRIMERO.- Las presentes reformas entrarán en vigor al día siguiente de su publicación en el Periódico Oficial del Estado de Baja California.\nARTÍCULO SEGUNDO.- Durante el ejercicio fiscal del año 2007, se aplicará el porcentaje de 80% (ochenta por ciento), para la exención del impuesto sobre\nLey de Hacienda del Estado de Baja California. Página 167\n.\nActualización Legislativa.\nÚltima reforma P.O. No. 72, Índice, 22-Dic-2023 remuneraciones al trabajo personal, que prevé el artículo 181 que se adiciona a la Ley de\nHacienda del Estado de Baja California.\nARTÍCULO TERCERO.- Se condona a los contribuyentes a que se refiere el artículo 181 que se adiciona a la Ley de Hacienda del Estado de Baja California, del pago del impuesto sobre remuneraciones al trabajo personal causado desde el primero de enero de 2007 hasta la entrada en vigor de este Decreto, en el porcentaje previsto en el artículo que antecede.\nARTÍCULO CUARTO.- Se deroga el artículo segundo transitorio del Decreto número 185, publicado en el Periódico Oficial del Estado, el día 24 de febrero de 2006.”\nDADO.- En el Salón de Sesiones “Lic. Benito Juárez García”, en la Ciudad de\nMexicali, Baja California”, a los doce días del mes de julio del año dos mil siete.\nDIP. MANUEL PONS AGÚNDEZ\nPRESIDENTE\n(RÚBRICA)\nDIP. ELÍAS LÓPEZ MENDOZA\nSECRETARIO\n(RÚBRICA)\nDE CONFORMIDAD CON LO DISPUESTO POR LA FRACCION I DEL ARTICULO\n49 DE LA CONSTITUCION POLITICA DEL ESTADO, IMPRIMASE Y PUBLIQUESE.\nMEXICALI, BAJA CALIFORNIA, A TRECE DE AGOSTO DEL AÑO DOS MIL SIETE.\nGOBERNADOR DEL ESTADO.\nEUGENIO ELORDUY WALTHER\nSECRETARIO GENERAL DE GOBIERNO\nBERNARDO H. MARTINEZ AGUIRRE\nARTICULO TRANSITORIO DEL DECRETO No. 235, POR EL QUE SE REFORMA\nEL ARTÍCULO 180, PUBLICADO EN EL PERIODICO OFICIAL NO. 26, DE FECHA 5 DE\nGOBERNADOR CONSTITUCIONAL EL C. GUADALUPE OSUNA MILLAN 2001-2007.\nLey de Hacienda del Estado de Baja California. Página 168\n.\nActualización Legislativa.\nÚltima reforma P.O. No. 72, Índice, 22-Dic-2023\nUNICO.- Se aprueba la Iniciativa que Reforma el Artículo 151-13 de la Ley de\nHacienda del Estado de Baja California; sin embargo, por técnica legislativa, se considera idóneo plasmar la intención de la Iniciativa a través de las adecuaciones propuestas, incorporándose en el Artículo 180 de la Ley de Hacienda en comento, en virtud de que su contenido promoverá y estimulará en los bajacalifornianos actitudes que fortalezcan su desarrollo y colaboración con el Gobierno del Estado, a fin de que se apoye y facilite la participación en el sector filantrópico, sin que se afecte una fuente importante de ingresos del Estado, como es la recaudación del Impuesto Sobre Remuneraciones al Trabajo\nPersonal. Preservando a su vez la congruencia de la estructura normativa en estudio y sin descuidar la claridad en el precepto que exima del pago del Impuesto Sobre\nRemuneraciones al Trabajo Personal a las Instituciones de Asistencia Social Privada, que sean reconocidas por el Estado como Auxiliares de la Asistencia Social, sustentándose además en los términos de la Ley de Asistencia Social para el Estado de Baja California.\nLa presente reforma entrará en vigor el día siguiente al de su publicación en el\nPeriódico Oficial del Estado de Baja California.\nDADO en el Salón de Sesiones “Lic. Benito Juárez García” del H. Poder Legislativo del Estado de Baja California, en la Ciudad de Mexicali, B. C., a los veintinueve días del mes de abril del año dos mil nueve.\nDIP. ENRIQUE MÉNDEZ JUÁREZ\nPRESIDENTE\n(RÚBRICA)\nDIP. GLORIA MARÍA LOZA GALVÁN\nSECRETARIO\n(RÚBRICA)\nDE CONFORMIDAD CON LO DISPUESTO POR LA FRACCION I DEL ARTICULO\n49 DE LA CONSTITUCION POLITICA DEL ESTADO, IMPRIMASE Y PUBLIQUESE.\nMEXICALI, BAJA CALIFORNIA, A LOS QUINCE DIAS DEL MES DE MAYO DEL\nAÑO DOS MIL NUEVE.\nJOSE GUADALUPE OSUNA MILLAN\nEUGENIO ELORDUY WALTHER\nJOSE FRANCISCO BLAKE MORA\nSECRETARIO GENERAL DE GOBIERNO\nLey de Hacienda del Estado de Baja California. Página 169\n.\nActualización Legislativa.\nÚltima reforma P.O. No. 72, Índice, 22-Dic-2023\nARTICULO SEGUNDO DEL DECRETO NO. 409, POR EL QUE SE REFORMA EL\nSEGUNDO PÁRRAFO DEL ARTÍCULO 176, PUBLICADO EN EL PERIODICO OFICIAL No.\n37, DE FECHA 27 DE AGOSTO DE 2010, TOMO CXVII, SECCION II, EXPEDIDO POR LA\nH. XIX LEGISLATURA, SIENDO GOBERNADOR CONSTITUCIONAL EL C. JOSE\nGUADALUPE OSUNA MILLAN 2007-2013.\nARTÍCULO TRANSITORIO\nÚNICO.- La presente reforma entrará en vigor al día siguiente de su publicación en el\nPeriódico Oficial del Estado de Baja California.\nDADO en el Salón de Sesiones “Lic. Benito Juárez García” del H. Poder Legislativo del\nEstado de Baja California, en la Ciudad de Mexicali, B.C., a los dieciséis días del mes de agosto del año dos mil diez.\nDIP. JUAN MANUEL GASTÉLUM BUENROSTRO\nPRESIDENTE\n(RÚBRICA)\nDIP. CARLOS ALONSO ANGULO RENTERIA\nSECRETARIO\n(RÚBRICA)\nDE CONFORMIDAD CON LO DISPUESTO POR LA FRACCION I DEL ARTÍCULO 49\nMEXICALI, BAJA CALIFORNIA, A LOS VEINTICUATRO DIAS DEL MES DE\nAGOSTO DEL AÑO DOS MIL DIEZ.\nGOBERNADOR DEL ESTADO\nJOSE GUADALUPE OSUNA MILLAN\n(RÚBRICA)\nCUAUHTEMOC CARDONA BENAVIDEZ\nSECRETARIO GENERAL DE GOBIERNO\nARTICULO SEGUNDO TRANSITORIO DEL DECRETO No. 18, POR EL QUE SE\nMODIFICA LA DENOMINACIÓN DEL CAPÍTULO XX DEL TÍTULO SEGUNDO, SE\nREFORMAN LOS ARTÍCULOS 156-15, 156-16, 156-17, 156-18, 156-19, 156-20, 156-21, Y\nSE ADICIONAN LOS ARTÍCULOS 156-22, 156-23, 156-24, 156-25, 156-26, 156-27, 156-28,\n156-29, 156-30, 156-31 Y 156-32, PUBLICADO EN EL PERIODICO OFICIAL No. 58, Ley de Hacienda del Estado de Baja California. Página 170\n.\nActualización Legislativa.\nÚltima reforma P.O. No. 72, Índice, 22-Dic-2023\nH. XX LEGISLATURA, SIENDO GOBERNADOR CONSTITUCIONAL EL C. JOSE\nGUADALUPE OSUNA MILLAN 2007-2013.\nARTÍCULO PRIMERO.- El presente Decreto entrará en vigor al día siguiente de su publicación en el Periódico Oficial del Estado.\nEn virtud de lo anterior, de conformidad con lo establecido en el segundo párrafo del artículo cuarto transitorio del Decreto que reforma diversas disposiciones fiscales, publicado en el Diario Oficial de la Federación de fecha 21 de diciembre de 2007, a partir del primero de enero de dos mil once se suspenderá la aplicación del impuesto contenido en la Ley del\nImpuesto Sobre Tenencia o Uso de Vehículos.\nArtículo Transitorio Reformado\nARTÍCULO SEGUNDO.- Los pagos del impuesto sobre tenencia o uso de vehículos de ejercicios fiscales de 2010 y anteriores, se realizarán conforme a las disposiciones vigentes en el momento de causación del impuesto.\nARTÍCULO TERCERO.- Para efectos del artículo 156-20, fracción III, contenido en el presente Decreto, mientras no se cumplan cinco años de haber entrado en vigor el impuesto estatal sobre tenencia o uso de vehículos, las autoridades y funcionarios a que hace referencia la citada fracción, deberán verificar además el cumplimiento en el pago del impuesto sobre tenencia o uso de vehículos federal que se haya causado en su momento.\nARTÍCULO CUARTO.- Para efecto de la distribución a los Municipios, durante el\n2011, del fondo derivado de este impuesto a que se refiere el artículo 156-30, se considerará para esta única ocasión la recaudación del impuesto sobre tenencia o uso de vehículos durante el ejercicio fiscal de 2010.\nARTÍCULO QUINTO.- Publíquese el presente Decreto en el Periódico Oficial del\nGobierno del Estado. del Estado de Baja California, en la Ciudad de Mexicali, B.C., a los veintitrés días del mes de diciembre del año dos mil diez.\nDIP. NANCY G. SÁNCHEZ ARREDONDO\nPRESIDENTA\nDIP. VÍCTOR HUGO NAVARRO GUTIÉRREZ\nSECRETARIA\nLey de Hacienda del Estado de Baja California. Página 171\n.\nActualización Legislativa.\nÚltima reforma P.O. No. 72, Índice, 22-Dic-2023\nDE CONFORMIDAD CON LO DISPUESTO POR LA FRACCION I DEL ARTÍCULO 49\nMEXICALI, BAJA CALIFORNIA, A LOS VEINTISIETE DÍAS DEL MES DE\nDICIEMBRE DEL AÑO DOS MIL DIEZ.\nGOBERNADOR DEL ESTADO\nJOSE GUADALUPE OSUNA MILLAN\n(RÚBRICA)\nSECRETARIO GENERAL DE GOBIERNO\nCUAUHTEMOC CARDONA BENAVIDES\n(RÚBRICA)\nARTICULO UNICO TRANSITORIO DEL DECRETO NO. 101, POR EL QUE SE\nAPRUEBA LA REFORMA Y ADICIÓN A LOS ARTÍCULOS 172, 173, 174, 177 Y 179,\nPUBLICADO EN EL PERIODICO OFICIAL NO. 51, TOMO CXVIII, DE FECHA 28 DE\nOCTUBRE DE 2011, SECCION II, EXPEDIDO POR LA H. XX LEGISLATURA, SIENDO\nGOBERNADOR CONSTITUCIONAL EL C. JOSE GUADALUPE OSUNA MILLAN 2007-\n2013.\nARTÍCULOS TRANSITORIOS\nUNICO.- La presente reforma entrará en vigor el día siguiente de su publicación en el\nPeriódico Oficial del Estado de Baja California.\nSEGUNDO.- No se aprueba la Adición de un Rubro y de los Artículos 202 y 203 de la\nLey de Hacienda Municipal del Estado de Baja California.\nDADO en el Teatro Universitario ¨Rubén Vizcaíno Valencia¨, de la Universidad\nAutónoma de Baja California, en la Ciudad de Tijuana, B.C., a los veintidos días del mes de septiembre del año dos mil once.\nDIP. CARLOS MURGUÍA MEJÍA\nDIPUTADO PRESIDENTE\nDIP. VIRGINIA NORIEGA RÍOS\nDIPUTADA SECRETARIA\nLey de Hacienda del Estado de Baja California. Página 172\n.\nActualización Legislativa.\nÚltima reforma P.O. No. 72, Índice, 22-Dic-2023\nDE CONFORMIDAD CON LO DISPUESTO POR LA FRACCION I DEL ARTÍCULO 49\nMEXICALI, BAJA CALIFORNIA, A LOS CINCO DÍAS DEL MES DE OCTUBRE DEL\nAÑO DOS MIL ONCE.\nGOBERNADOR DEL ESTADO\nJOSE GUADALUPE OSUNA MILLAN\n(RÚBRICA)\nSECRETARIO GENERAL DE GOBIERNO\nCUAUHTEMOC CARDONA BENAVIDES\n(RÚBRICA)\nARTICULO UNICO TRANSITORIO DEL DECRETO NO. 108, POR EL QUE SE\nAPRUEBA LA REFORMA AL ARTÍCULO 180, PUBLICADO EN EL PERIODICO OFICIAL\nNO. 51, TOMO CXVIII, DE FECHA 28 DE OCTUBRE DE 2011, SECCION II, EXPEDIDO\nPOR LA H. XX LEGISLATURA, SIENDO GOBERNADOR CONSTITUCIONAL EL C. JOSE\nGUADALUPE OSUNA MILLAN 2007-2013.\nARTÍCULO TRANSITORIO\nPRIMERO.- Las presentes reformas entrarán en vigor al día siguiente de su publicación en el Periódico Oficial del Estado de Baja California.\nDADO en el Salón de Sesiones “Lic. Benito Juárez García” del H. Poder Legislativo del Estado de Baja California, en la Ciudad de Mexicali, B.C., a los treinta días del mes de septiembre del año dos mil once.\nLIC. MÁXIMO GARCÍA LÓPEZ\nDIPUTADO PRESIDENTE\nLIC. ALFONSO GARZÓN ZATARAIN\nDIPUTADO SECRETARIO\nDE CONFORMIDAD CON LO DISPUESTO POR LA FRACCION I DEL ARTÍCULO 49\nMEXICALI, BAJA CALIFORNIA, A LOS SEIS DÍAS DEL MES DE OCTUBRE DEL\nAÑO DOS MIL ONCE.\nLey de Hacienda del Estado de Baja California. Página 173\n.\nActualización Legislativa.\nÚltima reforma P.O. No. 72, Índice, 22-Dic-2023\nGOBERNADOR DEL ESTADO\nJOSE GUADALUPE OSUNA MILLAN\n(RÚBRICA)\nSECRETARIO GENERAL DE GOBIERNO\nCUAUHTEMOC CARDONA BENAVIDES\n(RÚBRICA)\nARTÍCULOS PRIMERO, SEGUNDO Y TERCEROS TRANSITORIOS DEL DECRETO\nNO. 168, POR EL QUE SE APRUEBA LA REFORMA A LOS ARTÍCULOS 156, 156-15, ASI\nCOMO EL ARTÍCULO PRIMERO TRANSITORIO DEL DECRETO No. 18, PUBLICADO EL\n31 DE DICIEMBRE DE 2010, LOS ARTÍCULOS 172 Y 173, PUBLICADO EN EL\nPERIODICO OFICIAL NO. 60, TOMO CXVIII, SECCION II, DE FECHA 30 DE DICIEMBRE\nDE 2011, EXPEDIDO POR LA H. XX LEGISLATURA, SIENDO GOBERNADOR\nCONSTITUCIONAL EL C. JOSE GUADALUPE OSUNA MILLAN 2007-2013.\nARTÍCULO TRANSITORIO\nÚNICO.- Las presentes reformas entrarán en vigor al día siguiente al de su publicación en el Periódico Oficial del Estado de Baja California.\nDADO en el Salón de Sesiones “Lic. Benito Juárez García” del H. Poder Legislativo del Estado de Baja California, en la Ciudad de Mexicali, B.C., a los treinta días del mes de diciembre del año dos mil once.\nLIC. MÁXIMO GARCÍA LÓPEZ\nDIPUTADO PRESIDENTE\n(RÚBRICA)\nPROFR. ALFONSO GARZÓN ZATARAIN\nDIPUTADO SECRETARIO\n(RÚBRICA)\nDE CONFORMIDAD CON LO DISPUESTO POR LA FRACCION I DEL ARTÍCULO 49\nMEXICALI, BAJA CALIFORNIA, A LOS TREINTA DÍAS DEL MES DE DICIEMBRE\nDEL AÑO DOS MIL ONCE.\nGOBERNADOR DEL ESTADO\nJOSE GUADALUPE OSUNA MILLAN\nSECRETARIO GENERAL DE GOBIERNO\nCUAUHTEMOC CARDONA BENAVIDES\nLey de Hacienda del Estado de Baja California. Página 174\n.\nActualización Legislativa.\nÚltima reforma P.O. No. 72, Índice, 22-Dic-2023\n(RÚBRICA)\nARTÍCULOS ÚNICO TRANSITORIOS DE DECRETO NO. 169, POR EL QUE SE\nADICIONA EL CAPÍTULO XXI DEL TÍTULO SEGUNDO, Y LOS ARTÍCULOS 156-33, 15634, 156-35, 156-36, 156-37, 156-38, 156-39, 156-40, 156-41, 156-42, 156-43 156-44 Y 156-\n45, PUBLICADO EN EL PERIÓDICO OFICIAL NO. 60, TOMO CXVIII, SECCIÓN II, DE\nFECHA 30 DE DICIEMBRE DE 2011, EXPEDIDO POR LA H. XX LEGISLATURA, SIENDO\nGOBERNADOR CONSTITUCIONAL EL C. JOSÉ GUADALUPE OSUNA MILLÁN 2007-\n2013.\nARTÍCULO PRIMERO.- El presente Decreto entrará en vigor el día primero de febrero del año dos mil doce.\nARTÍCULO SEGUNDO.- Los pagos de este impuesto relativos a los dos primeros meses de vigencia del mismo, podrán presentarse por esta única ocasión en forma bimestral, dentro de los 25 días del mes siguiente a que termine dicho bimestre.\nARTÍCULO TERCERO.- Para efecto de la distribución a los Municipios, durante el\n2012, del fondo derivado de este impuesto a que se refiere el artículo 156-45, se considerará para esta única ocasión la recaudación del Impuesto sobre Remuneraciones al Trabajo\nPersonal del Ejercicio Fiscal 2011.\nARTÍCULO CUARTO.- Las personas que a la entrada en vigor del presente Decreto lleven a cabo las actividades señaladas en el artículo 156-34, deberán presentar el alta a que se refiere la fracción IV del artículo 156-42, a más tardar el 30 de marzo de 2012.\nARTÍCULO QUINTO.- Publíquese el presente Decreto en el Periódico Oficial del\nGobierno del Estado. del Estado de Baja California, en la Ciudad de Mexicali, B.C., a los treinta días del mes de diciembre del año dos mil once.\nLIC. MÁXIMO GARCÍA LÓPEZ\nDIPUTADO PRESIDENTE\nPROFR. ALFONSO GARZÓN ZATARAIN\nDIPUTADO SECRETARIO\nLey de Hacienda del Estado de Baja California. Página 175\n.\nActualización Legislativa.\nÚltima reforma P.O. No. 72, Índice, 22-Dic-2023\nDE CONFORMIDAD CON LO DISPUESTO POR LA FRACCION I DEL ARTÍCULO 49\nMEXICALI, BAJA CALIFORNIA, A LOS TREINTA DÍAS DEL MES DE DICIEMBRE\nDEL AÑO DOS MIL ONCE.\nGOBERNADOR DEL ESTADO\nJOSE GUADALUPE OSUNA MILLAN\n(RÚBRICA)\nSECRETARIO GENERAL DE GOBIERNO\nCUAUHTEMOC CARDONA BENAVIDES\n(RÚBRICA)\nARTÍCULO UNICO TRANSITORIO DEL DECRETO No. 297, POR EL QUE SE\nREFORMAN LOS ARTÍCULOS 131 Y 132, PRIMER PÁRRAFO Y FRACCIONES II Y III,\nPUBLICADO EN EL PERIÓDICO OFICIAL NO. 45, TOMO CXIX, DE FECHA 05 DE\nOCTUBRE DE 2012, EXPEDIDO POR LA H. XX LEGISLATURA, SIENDO GOBERNADOR\nCONSTITUCIONAL EL C. JOSÉ GUADALUPE OSUNA MILLÁN 2007-2013.\nARTÍCULO TRANSITORIO\nÚNICO.- La presente reforma entrará en vigor al día siguiente de su publicación en el\nPeriódico Oficial del Estado.\nDADO en el Salón de Sesiones “Lic. Benito Juárez García” del H. Poder Legislativo del Estado de Baja California, en la Ciudad de Mexicali, B.C., a los dieciocho días del mes de septiembre del año dos mil doce.\nDIP. ALFONSO GARZÓN ZATARAIN\nPRESIDENTE\nDIP. FAUSTO ZÁRATE ZEPEDA\nSECRETARIO\nDE CONFORMIDAD CON LO DISPUESTO POR LA FRACCIÓN I DEL ARTÍCULO 49\nMEXICALI, BAJA CALIFORNIA, A LOS VEINTICUATRO DÍAS DEL MES DE\nSEPTIEMBRE DEL AÑO DOS MIL DOCE.\nLey de Hacienda del Estado de Baja California. Página 176\n.\nActualización Legislativa.\nÚltima reforma P.O. No. 72, Índice, 22-Dic-2023\nJOSÉ GUADALUPE OSUNA MILLÁN\nGOBERNADOR DEL ESTADO\n(RÚBRICA)\nFRANCISCO ANTONIO GARCÍA BURGOS\nSECRETARIO GENERAL DE GOBIERNO\n(RÚBRICA)\nARTÍCULO UNICO TRANSITORIO DEL DECRETO No. 363, POR EL QUE SE\nREFORMA EL ARTÍCULO 173, PUBLICADO EN EL PERIÓDICO OFICIAL NO. 45, TOMO\nCXIX, DE FECHA 21 DE DICIEMBRE DE 2012, EXPEDIDO POR LA H. XX LEGISLATURA,\nSIENDO GOBERNADOR CONSTITUCIONAL EL C. JOSÉ GUADALUPE OSUNA MILLÁN\n2007-2013.\nARTÍCULO TRANSITORIO\nÚNICO.- El presente Decreto entrará en vigor al día siguiente al de su publicación en el Periódico Oficial del Estado.\nDADO en el Salón de Sesiones “Lic. Benito Juárez García” del H. Poder Legislativo del Estado de Baja California, en la Ciudad de Mexicali, B.C., a los veintisiete días del mes de noviembre del año dos mil doce.\nDIP. CLAUDIA JOSEFINA AGATÓN MUÑÍZ\nPRESIDENTE\n(RÚBRICA)\nDIP. FAUSTO ZÁRATE ZEPEDA\nSECRETARIO\n(RÚBRICA)\nDE CONFORMIDAD CON LO DISPUESTO POR LA FRACCIÓN I DEL ARTÍCULO 49\nMEXICALI, BAJA CALIFORNIA, A LOS CUATRO DÍAS DEL MES DE DICIEMBRE\nDEL AÑO DOS MIL DOCE.\nJOSÉ GUADALUPE OSUNA MILLÁN\nGOBERNADOR DEL ESTADO\nFRANCISCO ANTONIO GARCÍA BURGOS\nSECRETARIO GENERAL DE GOBIERNO\nLey de Hacienda del Estado de Baja California. Página 177\n.\nActualización Legislativa.\nÚltima reforma P.O. No. 72, Índice, 22-Dic-2023\n(RÚBRICA)\nARTÍCULO PRIMERO TRANSITORIO DEL DECRETO No. 409, POR EL QUE SE\nADICIONA UN ARTÍCULO 4-1, ADEMÁS DE UN SEGUNDO PÁRRAFO A LOS\nARTÍCULOS 157 Y 158, PUBLICADO EN EL PERIÓDICO OFICIAL NO. 11, TOMO CXX,\nDE FECHA 22 DE FEBRERO DE 2013, EXPEDIDO POR LA H. XX LEGISLATURA,\nSIENDO GOBERNADOR CONSTITUCIONAL EL C. JOSÉ GUADALUPE OSUNA MILLÁN\n2007-2013.\nARTÍCULOS TRANSITORIOS\nARTÍCULO PRIMERO.- Las presentes Reformas de Ley entrarán en vigor al día siguiente de su publicación en el Periódico Oficial del Estado.\nARTÍCULO SEGUNDO.- Túrnese las presentes Reformas de Ley al Titular del Poder\nEjecutivo del Estado para los efectos de publicación en el Periódico Oficial del Estado de\nBaja California.\nDADO en el Salón de Sesiones “Lic. Benito Juárez García” del H. Poder Legislativo del Estado de Baja California, en la Ciudad de Mexicali, B.C., a los veinticuatro días del mes de enero del año dos mil trece.\nDIP. CLAUDIA JOSEFINA AGATÓN MUÑÍZ\nPRESIDENTE\n(RÚBRICA)\nDIP. FAUSTO ZÁRATE ZEPEDA\nSECRETARIO\n(RÚBRICA)\nDE CONFORMIDAD CON LO DISPUESTO POR LA FRACCIÓN I DEL ARTÍCULO 49\nMEXICALI, BAJA CALIFORNIA, A LOS SEIS DÍAS DEL MES DE FEBRERO DEL\nAÑO DOS MIL TRECE.\nJOSÉ GUADALUPE OSUNA MILLÁN\nGOBERNADOR DEL ESTADO\nFRANCISCO ANTONIO GARCÍA BURGOS\nSECRETARIO GENERAL DE GOBIERNO\nLey de Hacienda del Estado de Baja California. Página 178\n.\nActualización Legislativa.\nÚltima reforma P.O. No. 72, Índice, 22-Dic-2023\nARTÍCULO UNICO TRANSITORIO DEL DECRETO No. 462, POR EL QUE SE\nREFORMAN LOS 131, 132, 155 Y 156, PUBLICADO EN EL PERIÓDICO OFICIAL NO. 26,\nTOMO CXX, DE FECHA 07 DE JUNIO DE 2013, EXPEDIDO POR LA H. XX\nLEGISLATURA, SIENDO GOBERNADOR CONSTITUCIONAL EL C. JOSÉ GUADALUPE\nOSUNA MILLÁN 2007-2013.\nARTÍCULO TRANSITORIO\nÚNICO.- Las presentes Reformas entrarán en vigor al día siguiente de su publicación en el Periódico Oficial del Estado de Baja California.\nDADO en el Salón de Sesiones “Lic. Benito Juárez García” del H. Poder Legislativo del Estado de Baja California, en la Ciudad de Mexicali, B.C., a los catorce días del mes de mayo del año dos mil trece.\nDIP. JULIO FELIPE GARCÍA MUÑOZ\nPRESIDENTE\n(RÚBRICA)\nDIP. MARCO ANTONIO VIZCARRA CALDERÓN\nSECRETARIO\n(RÚBRICA)\nDE CONFORMIDAD CON LO DISPUESTO POR LA FRACCIÓN I DEL ARTÍCULO 49\nMEXICALI, BAJA CALIFORNIA, A LOS QUINCE DÍAS DEL MES DE MAYO DEL\nAÑO DOS MIL TRECE.\nJOSÉ GUADALUPE OSUNA MILLÁN\nGOBERNADOR DEL ESTADO\nFRANCISCO ANTONIO GARCÍA BURGOS\nSECRETARIO GENERAL DE GOBIERNO\nARTÍCULO UNICO TRANSITORIO DEL DECRETO No. 486, POR EL QUE SE\nREFORMA EL ARTÍCULO 151-16, PUBLICADO EN EL PERIÓDICO OFICIAL No. 30, Ley de Hacienda del Estado de Baja California. Página 179\n.\nActualización Legislativa.\nÚltima reforma P.O. No. 72, Índice, 22-Dic-2023\nLEGISLATURA, SIENDO GOBERNADOR CONSTITUCIONAL EL C. JOSÉ GUADALUPE\nOSUNA MILLÁN 2007-2013.\nTRANSITORIOS\nARTÍCULO PRIMERO.- La presente reforma entrará en vigor el primero de enero de\n2014.\nARTÍCULO SEGUNDO.- El Ejecutivo del Estado en el proyecto de Ley de Ingresos para el ejercicio fiscal 2014, deberá incluir las modificaciones pertinentes para la viabilidad de la presente reforma.\nAbrogado\nDADO en el Salón de Sesiones “Lic. Benito Juárez García” del H. Poder Legislativo del Estado de Baja California, en la Ciudad de Mexicali, B.C., a los once días del mes de junio del año dos mil trece.\nDIP. GREGORIO CARRANZA HERNÁNDEZ\nPRESIDENTE\n(RÚBRICA)\nDIP. MARCO ANTONIO VIZCARRA CALDERÓN\nSECRETARIO\n(RÚBRICA)\nDE CONFORMIDAD CON LO DISPUESTO POR LA FRACCIÓN I DEL ARTÍCULO 49\nMEXICALI, BAJA CALIFORNIA, A LOS DIEZ DÍAS DEL MES DE JUNIO DEL AÑO\nDOS MIL TRECE.\nJOSÉ GUADALUPE OSUNA MILLÁN\nGOBERNADOR DEL ESTADO\nFRANCISCO ANTONIO GARCÍA BURGOS\nSECRETARIO GENERAL DE GOBIERNO\nARTÍCULO UNICO TRANSITORIO DEL DECRETO No. 29, POR EL QUE SE\nREFORMA EL ARTÍCULO 151-16; PUBLICADO EN EL PERIÓDICO OFICIAL No. 60, Ley de Hacienda del Estado de Baja California. Página 180\n.\nActualización Legislativa.\nÚltima reforma P.O. No. 72, Índice, 22-Dic-2023\nH. XXI LEGISLATURA, SIENDO GOBERNADOR CONSTITUCIONAL EL C. FRANCISCO\nARTURO VEGA DE LA MADRID 2013-2019.\nARTÍCULOS TRANSITORIOS\nPRIMERO: La presente reforma entrará en vigor al día siguiente de su publicación en el Periódico Oficial del Estado de Baja California.\nSEGUNDO: Se abroga el Decreto 486, mediante el cual se aprueba la reforma al artículo 151-16 de la Ley de Hacienda del Estado de Baja California, publicado el 05 de julio de 2013 en el Periódico Oficial del Estado de Baja California.\nTERCERO.- En cumplimiento a lo establecido en el Considerando Décimo Octavo, esta Comisión adquiere el compromiso de analizar la posibilidad de un incremento razonable, efectivo para el ejercicio fiscal de 2015, al porcentaje previsto en el Artículo 15116 de le Ley de Hacienda del Estado de Baja California.\nDADO en el Salón de Sesiones “Lic. Benito Juárez García” del H. Poder Legislativo del Estado de Baja California, en la Ciudad de Mexicali, B.C., a los veinticuatro días del mes de diciembre del año dos mil trece.\nDIP. CUAUHTÉMOC CARDONA BENAVIDES\nPRESIDENTE\n(RÚBRICA)\nDIP. JOSÉ ALBERTO MARTINEZ CARRILLO\nSECRETARIO\n(RÚBRICA)\nDE CONFORMIDAD CON LO DISPUESTO POR LA FRACCIÓN I DEL ARTÍCULO 49\nMEXICALI, BAJA CALIFORNIA, A LOS VEINTISÉIS DÍAS DEL MES DE DICIEMBRE\nDEL AÑO DOS MIL TRECE.\nFRANCISCO ARTURO VEGA DE LA MADRID\nGOBERNADOR DEL ESTADO\nGUILLERMO TREJO DOZAL\nSECRETARIO GENERAL DE GOBIERNO\nLey de Hacienda del Estado de Baja California. Página 181\n.\nActualización Legislativa.\nÚltima reforma P.O. No. 72, Índice, 22-Dic-2023\nARTÍCULO TERCERO TRANSITORIO DEL DECRETO No. 282, POR EL QUE SE\nREFORMA EL ARTÍCULO 173; PUBLICADO EN EL PERIÓDICO OFICIAL No. 24,\nSECCION I, TOMO CXXII, DE FECHA 22 DE MAYO DE 2015, EXPEDIDO POR LA H. XXI\nLEGISLATURA, SIENDO GOBERNADOR CONSTITUCIONAL EL C. FRANCISCO\nARTURO VEGA DE LAMADRID 2013-2019.\nARTÍCULOS TRANSITORIOS\nPRIMERO.- Las presentes reformas entrarán en vigor al día siguiente de su publicación en el Periódico Oficial del Estado.\nTratándose de la Reforma al artículo 173 de la Ley de Hacienda, ésta entrará en vigor el primero de enero del ejercicio fiscal siguiente al de publicación del presente Decreto en el\nPeriódico Oficial del Estado.\nTratándose de la reforma al párrafo primero del artículo 2191 del Código Civil del\nEstado, a los artículos 145 de la Ley del Notariado del Estado y 48 de la Ley del Registro\nPúblico de la Propiedad y de Comercio para el Estado, éstas entrarán en vigor a los 120 días siguientes al de la publicación del presente Decreto.\nSEGUNDO.- Aquellos testamentos públicos cerrados, públicos simplificados, privados, militares, marítimos o hechos en país extranjero que hayan sido otorgados con anterioridad al presente decreto, subsistirán en sus términos y para su apertura, declaración de ser formal testamento y demás tramitación correspondiente se substanciarán de conformidad con las disposiciones vigentes al momento de su otorgamiento.\nTratándose de los testamentos ológrafos otorgados con anterioridad al presente\nDecreto, estos subsistirán en sus términos y para su apertura, declaración de ser formal testamento y demás trámites que correspondan, las personas interesadas podrán optar ante el juez, siempre que no hubiere controversia alguna, menores de edad, menores emancipados o mayores incapacitados, entre seguir la substanciación conforme a las disposiciones vigentes al momento de su otorgamiento, o tramitar la sucesión ante Notario\nPúblico.\nTERCERO.- El Ejecutivo del Estado deberá emitir las disposiciones reglamentarias conducentes derivadas de las modificaciones a la Ley del Notariado, en un plazo no mayor de doscientos cuarenta días a partir de la de la entrada en vigor de las presentes reformas.\nLos notarios contarán con un plazo de ciento veinte días, a partir de la vigencia de las mismas, para realizar las adecuaciones necesarias que de conformidad con estas correspondan.\nCUARTO.- Los procedimientos instaurados en contra de notarios por quejas presentadas con anterioridad a la entrada en vigor de las presentes reformas, se tramitarán conforme a las disposiciones vigentes en aquel momento.\nQUINTO.- Quienes se encuentren realizando la práctica notarial en cualquiera de sus\nLey de Hacienda del Estado de Baja California. Página 182\n.\nActualización Legislativa.\nÚltima reforma P.O. No. 72, Índice, 22-Dic-2023 pero no hayan obtenido patente de aspirante, seguirán el trámite conforme al presente\nDecreto.\nSEXTO.- El Ejecutivo del Estado deberá emitir las modificaciones necesarias al\nArancel de Notarios para el Estado de Baja California derivado de las reformas al Código\nCivil y al Código de Procedimientos Civiles, así como realizar los ajustes que correspondan por la intervención de los notarios en los testamentos.\nSÉPTIMO.- Las garantías otorgadas por los notarios con anterioridad a la entrada en vigor de las presentes reformas deberán ajustarse al artículo 155 de este Decreto, en la actualización anual que corresponda.\nOCTAVO.-Dentro del mes siguiente a la publicación del presente Decreto, la\nDirección del Archivo General de Notarías programará la entrega por parte de los Notarios, de los volúmenes de su protocolo y apéndices que se encuentren en el supuesto contenido en el artículo 99 de esta reforma. La Dirección del Archivo General de Notarías, mediante oficio notificará a los Notarios de la obligación de entregar los volúmenes, conforme a la programación que emita, lo que deberá cumplimentarse a más tardar un año a partir de la vigencia del presente Decreto.\nNOVENO.- A los Notarios que se les haya expedido la patente respectiva con anterioridad a la entrada en vigor de las presentes reformas única y exclusivamente, no les será aplicable el plazo de vigencia de patentes, a que se refieren los artículos 53 Bis y 56 del presente Decreto.\nDADO en el Salón de Sesiones “Lic. Benito Juárez García” del H. Poder Legislativo del Estado de Baja California, en la Ciudad de Mexicali, B.C., a los 21 días del mes de mayo del año dos mil quince.\nDIP. FCO. ALCIBÍADES GARCÍA LIZARDI\nPRESIDENTE\n(RÚBRICA)\nDIP. ROSALBA LÓPEZ REGALADO\nSECRETARIA\nDE CONFORMIDAD CON LO DISPUESTO POR LA FRACCION I DEL ARTÍCULO 49\nMEXICALI, BAJA CALIFORNIA, A LOS VEINTISIETE DÍAS DEL MES DE MAYO DEL AÑO\nDOS MIL QUINCE.\nFRANCISCO ARTURO VEGA DE LAMADRID\nGOBERNADOR DEL ESTADO\nLey de Hacienda del Estado de Baja California. Página 183\n.\nActualización Legislativa.\nÚltima reforma P.O. No. 72, Índice, 22-Dic-2023\nFRANCISCO RUEDA GOMEZ\nSECRETARIO GENERAL DE GOBIERNO\n(RÚBRICA)\nARTÍCULO PRIMERO TRANSITORIO DEL DECRETO No. 258, POR EL QUE SE\nREFORMA EL ARTÍCULO 174 BIS, PUBLICADO EN EL PERIÓDICO OFICIAL No. 28,\nTOMO CXXII, DE FECHA 12 DE JUNIO DE 2015, EXPEDIDO POR LA H. XXI\nLEGISLATURA, SIENDO GOBERNADOR CONSTITUCIONAL EL C. FRANCISCO\nARTURO VEGA DE LAMADRID 2013-2019.\nARTÍCULO TRANSITORIO\nPRIMERO.- Las presentes reformas entrarán en vigor al día siguiente de su publicación en el Periódico Oficial del Estado de Baja California.\nDADO en el Salón de Sesiones “Lic. Benito Juárez García” del H. Poder Legislativo del Estado de Baja California, en la Ciudad de Mexicali, B.C., a los 07 días del mes de mayo del año dos mil quince.\nDIP. FCO. ALCIBÍADES GARCÍA LIZARDI\nPRESIDENTE\n(RÚBRICA)\nDIP. ROSALBA LÓPEZ REGALADO\nSECRETARIA\n(RÚBRICA)\nDE CONFORMIDAD CON LO DISPUESTO POR LA FRACCION I DEL ARTÍCULO 49\nMEXICALI, BAJA CALIFORNIA, A LOS VEINTISIETE DÍAS DEL MES DE MAYO DEL\nAÑO DOS MIL QUINCE.\nFRANCISCO ARTURO VEGA DE LAMADRID\nGOBERNADOR DEL ESTADO\nFRANCISCO RUEDA GOMEZ\nSECRETARIO GENERAL DE GOBIERNO\nARTÍCULO CUARTO TRANSITORIO DEL DECRETO No. 590, POR EL QUE SE NO\nSE REFORMA EL ARTÍCULO 173, PUBLICADO EN EL PERIÓDICO OFICIAL No. 45, Ley de Hacienda del Estado de Baja California. Página 184\n.\nActualización Legislativa.\nÚltima reforma P.O. No. 72, Índice, 22-Dic-2023\nSECCION V, TOMO CXXIII, DE FECHA 07 DE OCTUBRE DE 2016, EXPEDIDO POR LA H.\nXXI LEGISLATURA, SIENDO GOBERNADOR CONSTITUCIONAL EL C. FRANCISCO\nARTURO VEGA DE LAMADRID 2013-2019.\nARTÍCULO TRANSITORIO\nÚNICO.- El presente Decreto entrará en vigor al día siguiente de su publicación en el\nPeriódico Oficial del Estado.\nDADO en el Salón de Sesiones “Lic. Benito Juárez García” del H. Poder Legislativo del Estado de Baja California, en la Ciudad de Mexicali, B.C., a los ocho días del mes de septiembre del año dos mil dieciséis.\nDIP. MÓNICA BEDOYA SERNA\nPRESIDENTE\n(RÚBRICA)\nDIP. ROSA ISELA PERALTA CASILLAS\nSECRETARIA\n(RÚBRICA)\nDE CONFORMIDAD CON LO DISPUESTO POR LA FRACCION I DEL ARTÍCULO 49\nMEXICALI, BAJA CALIFORNIA, A LOS VEINTIÚN DÍAS DEL MES DE SEPTIEMBRE\nDEL AÑO DOS MIL DIECISÉIS.\nFRANCISCO ARTURO VEGA DE LAMADRID\nGOBERNADOR DEL ESTADO\n(RÚBRICA)\nFRANCISCO RUEDA GÓMEZ\nSECRETARIO GENERAL DE GOBIERNO\nARTÍCULO ÚNICO TRANSITORIO DEL DECRETO No. 56, POR EL QUE SE\nREFORMAN LOS ARTÍCULOS 4-1 Y 158, PUBLICADO EN EL PERIÓDICO OFICIAL No.\nLA H. XXII LEGISLATURA, SIENDO GOBERNADOR CONSTITUCIONAL EL C.\nFRANCISCO ARTURO VEGA DE LAMADRID 2013-2019.\nTRANSITORIO\nLey de Hacienda del Estado de Baja California. Página 185\n.\nActualización Legislativa.\nÚltima reforma P.O. No. 72, Índice, 22-Dic-2023\nARTÍCULO ÚNICO - Las presentes reformas entrarán en vigor al día siguiente de su publicación en el Periódico Oficial del Estado de Baja California.\nDADO en el Salón de Sesiones “Lic. Benito Juárez García” del H. Poder Legislativo del Estado de Baja California, en la Ciudad de Mexicali, B.C., a los veinte días del mes de diciembre del año dos mil dieciséis.\nDIP. MTRO. RAÚL CASTAÑEDA POMPOSO\nPRESIDENTE\n(RÚBRICA)\nDIP. MARCO A. CORONA BOLAÑOS CACHO\nSECRETARIO\n(RÚBRICA)\nDE CONFORMIDAD CON LO DISPUESTO POR LA FRACCION I DEL ARTÍCULO 49\nMEXICALI, BAJA CALIFORNIA, A LOS VEINTIÚN DÍAS DEL MES DE DICIEMBRE\nDEL AÑO DOS MIL SEIS.\nFRANCISCO ARTURO VEGA DE LAMADRID\nGOBERNADOR DEL ESTADO\n(RÚBRICA)\nFRANCISCO RUEDA GOMEZ\nSECRETARIO GENERAL DE GOBIERNO\n(RÚBRICA)\nARTÍCULO ÚNICO TRANSITORIO DEL DECRETO No. 66, POR EL QUE SE\nREFORMAN LOS ARTÍCULOS 4-1 Y 158, PUBLICADO EN EL PERIÓDICO OFICIAL No. 4,\nNÚMERO ESPECIAL, TOMO CXXIV, DE FECHA 19 DE ENERO DE 2017, EXPEDIDO POR\nLA H. XXII LEGISLATURA, SIENDO GOBERNADOR CONSTITUCIONAL EL C.\nFRANCISCO ARTURO VEGA DE LAMADRID 2013-2019.\nTRANSITORIO\nÚNICO.- El presente Decreto mediante el que se reforman los artículos 4-1 y 158 de la Ley de Hacienda del Estado de Baja California, entrará en vigor el día de su publicación en el Periódico Oficial del Estado. del Estado de Baja California, en la Ciudad de Mexicali, B.C., a los diecinueve días del mes de enero del año dos mil diecisiete.\nLey de Hacienda del Estado de Baja California. Página 186\n.\nActualización Legislativa.\nÚltima reforma P.O. No. 72, Índice, 22-Dic-2023\nDIP. MTRO. RAÚL CASTAÑEDA POMPOSO\nPRESIDENTE\n(RÚBRICA)\nDIP. MARCO A. CORONA BOLAÑOS CACHO\nSECRETARIO\n(RÚBRICA)\nDE CONFORMIDAD CON LO DISPUESTO POR LA FRACCION I DEL ARTÍCULO 49\nMEXICALI, BAJA CALIFORNIA, A LOS DIECINUEVE DÍAS DEL MES DE ENERO\nDEL AÑO DOS MIL SEIS.\nFRANCISCO ARTURO VEGA DE LAMADRID\nGOBERNADOR DEL ESTADO\n(RÚBRICA)\nFRANCISCO RUEDA GÓMEZ\nSECRETARIO GENERAL DE GOBIERNO\n(RÚBRICA)\nARTÍCULO ÚNICO TRANSITORIO DEL DECRETO No. 180, POR EL QUE SE\nREFORMAN LOS ARTÍCULOS 127, 130, 131 y 132, PUBLICADO EN EL PERIÓDICO\nOFICIAL No. 04, SECCIÓN IV, TOMO CXXV, DE FECHA 19 DE ENERO DE 2018,\nEXPEDIDO POR LA H. XXII LEGISLATURA, SIENDO GOBERNADOR CONSTITUCIONAL\nEL C. FRANCISCO ARTURO VEGA DE LAMADRID 2013-2019.\nTRANSITORIO\nARTÍCULO ÚNICO.- Las presentes reformas entrarán en vigor a los 90 días siguientes de su publicación en el Periódico Oficial del Estado de Baja California. del Estado de Baja California, en la Ciudad de Mexicali, B.C., a los catorce días del mes de diciembre del año dos mil diecisiete.\nDIP. MTRO. RAÚL CASTAÑEDA POMPOSO\nPRESIDENTE\nDIP. ROCÍO LÓPEZ GOROSAVE\nSECRETARIA\nLey de Hacienda del Estado de Baja California. Página 187\n.\nActualización Legislativa.\nÚltima reforma P.O. No. 72, Índice, 22-Dic-2023\n(RÚBRICA)\nDE CONFORMIDAD CON LO DISPUESTO POR LA FRACCIÓN I DEL ARTÍCULO 49\nMEXICALI, BAJA CALIFORNIA, A LOS QUINCE DÍAS DEL MES DE ENERO DEL\nAÑO DOS MIL DIECIOCHO.\nFRANCISCO ARTURO VEGA DE LAMADRID\nGOBERNADOR DEL ESTADO\n(RÚBRICA)\nFRANCISCO RUEDA GÓMEZ\nSECRETARIO GENERAL DE GOBIERNO\n(RÚBRICA)\nARTÍCULO DÉSIMO TERCERO TRANSITORIO DEL DECRETO No. 281, POR EL\nQUE SE REFORMA EL ARTÍCULO 151-14, 151-28, 173, PUBLICADO EN EL PERIÓDICO\nOFICIAL No. 55, SECCION IV, TOMO CXXV, DE FECHA 30 DE NOVIEMBRE DE 2018,\nEXPEDIDO POR LA H. XXII LEGISLATURA, SIENDO GOBERNADOR CONSTITUCIONAL\nEL C. FRANCISCO ARTURO VEDA DE LAMADRID 2013-2019.\nARTÍCULOS TRANSITORIOS\nARTÍCULO PRIMERO.- El presente decreto entrará en vigor al día siguiente al de su publicación en el Periódico Oficial del Estado de Baja California.\nARTÍCULO SEGUNDO.- El valor diario de la Unidad de Medida y Actualización a la fecha de entrada en vigor, se tomará el valor publicado en el Diario Oficial de la Federación por el INEGI. El valor de la Unidad de Medida y Actualización a la fecha de entrada en vigor del presente Decreto, será producto de multiplicar el valor referido en el párrafo anterior por\n30.4. Por su parte, el valor anual será el producto de multiplicar el valor inicial mensual por\n12.\nARTÍCULO TERCERO.- Todas las menciones al salario mínimo como unidad de cuenta, índice, base, medida o referencia para determinar la cuantía de las obligaciones, sanciones, multas administrativas, conceptos de pago y montos de referencia, se entenderán referidas a la Unidad de Medida y Actualización. del Estado de Baja California, en la Ciudad de Mexicali, B.C., a los veinticinco días del mes de octubre del año dos mil dieciocho.\nLey de Hacienda del Estado de Baja California. Página 188\n.\nActualización Legislativa.\nÚltima reforma P.O. No. 72, Índice, 22-Dic-2023\nDIP. ROCÍO LÓPEZ GOROSAVE\nPRESIDENTA\n(RÚBRICA)\nDIP. MÓNICA HERNÁNDEZ ÁLVAREZ\nSECRETARIA\n(RÚBRICA)\nDE CONFORMIDAD CON LO DISPUESTO POR LA FRACCIÓN I DEL ARTÍCULO 49\nMEXICALI, BAJA CALIFORNIA, A LOS TREINTA DÍAS DEL MES DE NOVIEMBRE\nDEL AÑO DOS MIL DIECIOCHO.\nFRANCISCO ARTURO VEGA DE LAMADRID\nGOBERNADOR DEL ESTADO\n(RÚBRICA)\nFRANCISCO RUEDA GÓMEZ\nSECRETARIO GENERAL DE GOBIERNO\n(RÚBRICA)\nARTÍCULO SEGUNDO TRANSITORIO DEL DECRETO No. 280, POR EL QUE SE\nREFORMAN EL ARTÍCULO 177, PUBLICADO EN EL PERIÓDICO OFICIAL No. 04,\nSECCIÓN II, TOMO CXXVI, DE FECHA 18 DE ENERO DE 2019, EXPEDIDO POR LA H.\nXXII LEGISLATURA, SIENDO GOBERNADOR CONSTITUCIONAL EL C. FRANCISCO\nARTURO VEGA DE LAMADRID 2013-2019.\nTRANSITORIO\nARTÍCULO ÚNICO.- Las presentes reformas entrarán en vigor al día siguiente al de su publicación en el Periódico Oficial del Estado. del Estado de Baja California, en la Ciudad de Mexicali, B.C., a los veinticinco días del mes de octubre del año dos mil dieciocho.\nDIP. ROCÍO LÓPEZ GOROSAVE\nPRESIDENTA\nLey de Hacienda del Estado de Baja California. Página 189\n.\nActualización Legislativa.\nÚltima reforma P.O. No. 72, Índice, 22-Dic-2023\nDIP. MÓNICA HERNÁNDEZ ÁLVAREZ\nSECRETARIA\n(RÚBRICA)\nDE CONFORMIDAD CON LO DISPUESTO POR LA FRACCIÓN I DEL ARTÍCULO 49\nMEXICALI, BAJA CALIFORNIA, A LOS CATORCE DÍAS DEL MES DE DICIEMBRE\nDEL AÑO DOS MIL DIECIOCHO.\nFRANCISCO ARTURO VEGA DE LAMADRID\nGOBERNADOR DEL ESTADO\n(RÚBRICA)\nFRANCISCO RUEDA GÓMEZ\nSECRETARIO GENERAL DE GOBIERNO\n(RÚBRICA)\nARTÍCULO ÚNICO TRANSITORIO DEL DECRETO No. 23, POR EL QUE SE\nREFORMA EL CAPÍTULO XIX, SE ADICIONAN LAS SECCIONES PRIMERA, SEGUNDA,\nTERCERA Y LOS ARTÍCULOS 156-8 BIS, 156-8 TER, 156-8 QUATER, 156-9 BIS, 156-9\nTER, 156-10 BIS, 156-10 TER, 156-10 QUATER, 156-12 BIS, 156-12 TER Y SE\nREFORMAN LOS ARTÍCULOS 156-8, 156-9, 156-10, 156-11, 156-12, 156-13, 156-14,\nPUBLICADO EN EL PERIÓDICO OFICIAL No. 59, SECCIÓN I, TOMO CXXVI, DE FECHA\n06 DE DICIEMBRE DE 2019, EXPEDIDO POR LA H. XXIII LEGISLATURA, SIENDO\nGOBERNADOR CONSTITUCIONAL EL C. JAIME BONILLA VALDEZ 2019-2021.\nARTÍCULOS TRANSITORIOS\nARTÍCULO PRIMERO.- La presente iniciativa de decreto deberá de ser publicada en el\nPeriódico Oficial del Estado y entrará en vigor el 01 de Enero del 2020.\nARTÍCULO SEGUNDO.- La Secretaría de Hacienda del Estado realizará las acciones decreto.\nARTÍCULO TERCERO.- La Secretaría de Hacienda, preverá en la Ley de Ingresos de\nEstado para el ejercicio fiscal 2020, los impuestos previstos por la presente iniciativa de decreto, así como los ingresos proyectados.\nLey de Hacienda del Estado de Baja California. Página 190\n.\nActualización Legislativa.\nÚltima reforma P.O. No. 72, Índice, 22-Dic-2023\nARTÍCULO CUARTO.- La Secretaría de Hacienda preverá en el presupuesto de egresos del ejercicio fiscal 2020 una campaña informativa respecto a las nuevas obligaciones fiscales en el Estado derivadas de la presente iniciativa de decreto, un programa integral de capacitación al personal responsable en el estado respecto al procedimiento de entero y cobro de los impuestos previsto por la presente iniciativa de decreto.\nARTÍCULO QUINTO.- La Secretaría de Hacienda realizará las prevenciones financieras necesarias en el ejercicio fiscal 2020, para contar con una plataforma digital eficiente de cobro de los impuestos previstos en la presente iniciativa de decreto.\nDADO en el Salón de Sesiones “Lic. Benito Juárez García” del H. Poder Legislativo del Estado de Baja California, en la Ciudad de Mexicali, B.C., a los cinco días del mes de diciembre del año dos mil diecinueve.\nDIP. VÍCTOR MANUEL MORÁN HERNÁNDEZ\nPRESIDENTE\n(RÚBRICA)\nDIP. CARMEN LETICIA HERNÁNDEZ CARMONA\nSECRETARIA\n(RÚBRICA)\nDE CONFORMIDAD CON LO DISPUESTO POR LA FRACCIÓN I DEL ARTÍCULO 49\nMEXICALI, BAJA CALIFORNIA, A LOS SEIS DÍAS DEL MES DE DICIEMBRE DEL\nAÑO DOS MIL DIECINUEVE.\nJAIME BONILLA VALDEZ\nGOBERNADOR DEL ESTADO\n(RÚBRICA)\nAMADOR RODRÍGUEZ LOZANO\nSECRETARIO GENERAL DE GOBIERNO\nARTÍCULO ÚNICO TRANSITORIO DEL DECRETO No. 39, POR EL QUE SE\nREFORMAN LOS ARTÍCULOS 133, 134, 135, 136 Y SE REFORMA EL TÍTULO\nSEGUNDO Y ADICIONA EL CAPÍTULO XXII, LAS SECCIÓNES PRIMERA, SEGUNDA,\nTERCERA Y LOS ARTÍCULOS 156-46, 156-47, 156-48 Y 156-49, PUBLICADO EN EL\nPERIÓDICO OFICIAL No. 67, SECCIÓN VIII, TOMO CXXVI, DE FECHA 31 DE DICIEMBRE\nDE 2019, EXPEDIDO POR LA H. XXIII LEGISLATURA, SIENDO GOBERNADOR\nCONSTITUCIONAL EL C. JAIME BONILLA VALDEZ 2019-2021.\nLey de Hacienda del Estado de Baja California. Página 191\n.\nActualización Legislativa.\nÚltima reforma P.O. No. 72, Índice, 22-Dic-2023\nARTICULOS TRANSITORIOS\nARTÍCULO PRIMERO.- La presente iniciativa de decreto deberá de ser publicada en el Periódico Oficial del Estado y entrará en vigor el día siguiente de su publicación.\nARTÍCULO SEGUNDO.- La Secretaría de Hacienda del Estado realizara las acciones administrativas pertinentes para efecto de elaborar los formatos institucionales a través de los cuales los sujetos obligados enteraran los impuestos previstos en la presente iniciativa de decreto.\nARTÍCULO TERCERO.- Derogado.\nArtículo Transitorio Derogado\nARTÍCULO CUARTO.- La Secretaría de Hacienda preverá en el presupuesto de egresos del ejercicio fiscal 2020 una campaña informativa respecto a las nuevas obligaciones fiscales en el estado derivadas de la presente iniciativa de decreto, así como un programa de capacitación al personal responsable en el estado respecto al procedimiento de entero y cobro de los impuestos previsto por la presente iniciativa de decreto.\nARTÍCULO QUINTO.- La Secretaría de Hacienda realizará las prevenciones financieras necesarias en el ejercicio fiscal 2020, para contar con una plataforma digital eficiente de cobro del impuesto previsto en la presente iniciativa de Decreto.\nDADO en el Salón de Sesiones “Lic. Benito Juárez García” del H. Poder Legislativo del Estado de Baja California, en la Ciudad de Mexicali, B.C., a los 31 días del mes de diciembre del año dos mil diecinueve.\nDIP. VÍCTOR MANUEL MORÁN HERNÁNDEZ\nPRESIDENTE\n(RÚBRICA)\nDIP. CARMEN LETICIA HERNÁNDEZ CARMONA\nSECRETARIA\nDE CONFORMIDAD CON LO DISPUESTO POR LA FRACCIÓN I DEL ARTÍCULO 49\nMEXICALI, BAJA CALIFORNIA, A LOS TREINTA Y UN DÍAS DEL MES DE\nDICIEMBRE DEL AÑO DOS MIL DIECINUEVE.\nJAIME BONILLA VALDEZ\nGOBERNADOR DEL ESTADO\nLey de Hacienda del Estado de Baja California. Página 192\n.\nActualización Legislativa.\nÚltima reforma P.O. No. 72, Índice, 22-Dic-2023\n(RÚBRICA)\nAMADOR RODRÍGUEZ LOZANO\nSECRETARIO GENERAL DE GOBIERNO\n(RÚBRICA)\nARTÍCULO ÚNICO TRANSITORIO DEL DECRETO No. 62, POR EL QUE SE\nREFORMA EL TÍTULO SEGUNDO, CAPÍTULO IX, ARTÍCULOS 133, 134, 135 Y 136, Y SE\nADICIONAN LOS ARTÍCULOS 136-1, 136-2, 136-3, 136-4, 136-5, 136-6, Y 136-7, Y SE\nREFORMA EL CAPÍTULO XIX, ARTÍCULO 156-9, CAPÍTULO XXII, ARTÍCULO 156-48,\nPUBLICADO EN EL PERIÓDICO OFICIAL No. 22, NÚMERO ESPECIAL, TOMO CXXVII,\nDE FECHA 30 DE ABRIL DE 2020, EXPEDIDO POR LA H. XXIII LEGISLATURA, SIENDO\nGOBERNADOR CONSTITUCIONAL EL C. JAIME BONILLA VALDEZ 2019-2021.\nTRANSITORIOS\nARTÍCULO PRIMERO. - La presente reforma entrará en vigor al día siguiente de su publicación en el Periódico Oficial del Estado de Baja California.\nARTÍCULO SEGUNDO. - A la entrada en vigor de la presente reforma, se derogan los artículos 8 BIS y 8-TER de la Ley de Ingresos del Estado de Baja California para el ejercicio fiscal del año 2020, mismos que fueron incorporados mediante Decreto número 40 publicado en fecha 31 de diciembre de 2019, en el Periódico Oficial del Estado de Baja California.\nARTÍCULO TERCERO. - A la entrada en vigor de la presente reforma, se deroga artículo TERCERO TRANSITORIO del Decreto número 39 mediante el cual se reforman los artículos 133, 134, 135, 136 y se reforma el Título Segundo y adiciona el Capítulo XXII, las\nSecciones Primera, Segunda, Tercera y los Artículos 156-46, 156-47, 156-48 y 156-49 de la\nLey de Hacienda del Estado de Baja California, publicado en fecha 31 de diciembre de 2019 en el Periódico Oficial del Estado de Baja California. del Estado de Baja California, en la Ciudad de Mexicali, B.C., a los veinticuatro días del mes de abril del año dos mil veinte.\nDIP. LUIS MORENO HERNÁNDEZ\nPRESIDENTE\nDIP. EVA GRICELDA RODRÍGUEZ\nSECRETARIA\nLey de Hacienda del Estado de Baja California. Página 193\n.\nActualización Legislativa.\nÚltima reforma P.O. No. 72, Índice, 22-Dic-2023\nDE CONFORMIDAD CON LO DISPUESTO POR LA FRACCIÓN I DEL ARTÍCULO 49\nMEXICALI, BAJA CALIFORNIA, A LOS VEINTIOCHO DÍAS DEL MES DE ABRIL DEL\nAÑO DOS MIL VEINTE.\nJAIME BONILLA VALDEZ\nGOBERNADOR DEL ESTADO\n(RÚBRICA)\nAMADOR RODRÍGUEZ LOZANO\nSECRETARIO GENERAL DE GOBIERNO\n(RÚBRICA)\nARTÍCULO ÚNICO TRANSITORIO DEL DECRETO No. 63, POR EL QUE SE\nAPRUEBA LA REFORMA QUE ADICIONA EL CAPÍTULO XXIII DENOMINADO\n“IMPUESTO A EMPRESAS DE REDES DE TRANSPORTE”, Y ARTÍCULOS 156-50, 15651, 156-52, 156-53 Y 156-54, PUBLICADO EN EL PERIÓDICO OFICIAL No. 22, NÚMERO\nESPECIAL, TOMO CXXVII, DE FECHA 30 DE ABRIL DE 2020, EXPEDIDO POR LA H.\nXXIII LEGISLATURA, SIENDO GOBERNADOR CONSTITUCIONAL EL C. JAIME BONILLA\nVALDEZ 2019-2021.\nTRANSITORIOS\nARTÍCULO ÚNICO. - La presente reforma entrará en vigor al día siguiente de su publicación en el Periódico Oficial del Estado de Baja California.\nDADO en el Salón de Sesiones “Lic. Benito Juárez García” del H. Poder Legislativo del Estado de Baja California, en la Ciudad de Mexicali, B.C., a los veinticuatro días del mes de abril del año dos mil veinte.\nDIP. LUIS MORENO HERNÁNDEZ\nPRESIDENTE\nDIP. EVA GRICELDA RODRÍGUEZ\nSECRETARIA\nDE CONFORMIDAD CON LO DISPUESTO POR LA FRACCIÓN I DEL ARTÍCULO 49\nLey de Hacienda del Estado de Baja California. Página 194\n.\nActualización Legislativa.\nÚltima reforma P.O. No. 72, Índice, 22-Dic-2023\nMEXICALI, BAJA CALIFORNIA, A LOS VEINTIOCHO DÍAS DEL MES DE ABRIL DEL\nAÑO DOS MIL VEINTE.\nJAIME BONILLA VALDEZ\nGOBERNADOR DEL ESTADO\n(RÚBRICA)\nAMADOR RODRÍGUEZ LOZANO\nSECRETARIO GENERAL DE GOBIERNO\n(RÚBRICA)\nARTÍCULO ÚNICO TRANSITORIO DEL DECRETO No. 84, POR EL QUE SE\nREFORMAN LOS ARTÍCULOS 130 Y 151-16; SE ADICIONA UN CAPÍTULO XXIV EN EL\nTÍTULO SEGUNDO, DENOMINADO IMPUESTO AMBIENTAL SOBRE LA EXTRACCIÓN Y\nAPROVECHAMIENTO DE MATERIALES PÉTREOS, ASÍ COMO LOS ARTÍCULOS 156-55,\n156-56, 156-57, 156-58, 156-59 Y 156-60, PUBLICADO EN EL PERIÓDICO OFICIAL No.\n17, SECCIÓN I, TOMO CXXIX, DE FECHA 04 DE MARZO DE 2022, EXPEDIDO POR LA H.\nXXIV LEGISLATURA, SIENDO GOBERNADORA CONSTITUCIONAL LA C. MARINA DEL\nPILAR ÁVILA OLMEDA 2021-2027.\nTRANSITORIOS\nPRIMERO.- La presente reforma entrará en vigor el día siguiente de su publicación en el Periódico Oficial del Estado de Baja California.\nSEGUNDO.- La Secretaría de Hacienda realizará las acciones administrativas pertinentes para efecto de elaborar los formatos institucionales a través de los cuales los sujetos obligados enterarán los impuestos previstos en la presente reforma.\nDADO en Sesión Ordinaria Virtual de la XXIV Legislatura en la Ciudad de Mexicali, B.C., a los veinticuatro días del mes de febrero del año dos mil veintidós.\nDIP. JUAN MANUEL MOLINA GARCÍA\nPRESIDENTE\nDIP. AMINTHA GUADALUPE BRICEÑO CINCO\nPROSECRETARIA\nDE CONFORMIDAD CON LO DISPUESTO POR LA FRACCIÓN I DEL ARTÍCULO 49\nCALIFORNIA, IMPRÍMASE Y PUBLÍQUESE.\nLey de Hacienda del Estado de Baja California. Página 195\n.\nActualización Legislativa.\nÚltima reforma P.O. No. 72, Índice, 22-Dic-2023\nMEXICALI, BAJA CALIFORNIA, AL DÍA PRIMERO DEL MES DE MARZO DEL AÑO\nDOS MIL VEINTIDÓS.\nMARINA DEL PILAR ÁVILA OLMEDA\nGOBERNADORA DEL ESTADO\nDE BAJA CALIFORNIA\n(RÚBRICA)\nCATALINO ZAVALA MÁRQUEZ\nSECRETARIO GENERAL DE GOBIERNO\nDEL ESTADO DE BAJA CALIFORNIA\n(RÚBRICA)\nARTÍCULO PRIMERO TRANSITORIO DEL DECRETO No. 361, POR EL QUE SE\nREFORMAN LOS ARTÍCULOS 69, 72, 83, 119, 131, 132, 136-6, 140, 143-3, 143-4, 146, 147, 151-6, 151-7, 151-9, 151-10, 151-16, 151-25, 151-26, 151-27, 151-29, 152, 153, 154, 155, 156, 156-6, 156-9, 156-19, 156-28, 156-29, 156-31, 156-32, 156-42, 156-44, 175, 178,\n179, 180 Y 181; PUBLICADO EN EL PERIÓDICO OFICIAL No. 72, ÍNDICE, DE FECHA 22\nDE DICIEMBRE DE 2023, TOMO CXXX, EXPEDIDO POR LA H. XXIV LEGISLATURA,\nSIENDO GOBERNADORA CONSTITUCIONAL LA C. MARINA DEL PILAR ÁVILA OLMEDA\n2021-2027.\nTRANSITORIOS\nPRIMERO. La presente reforma entrará en vigor el día primero de enero del año dos mil veinticuatro.\nSEGUNDO. La Secretaría de Economía e Innovación, deberá coordinarse con la\nSecretaría de Hacienda a fin de remitir en el transcurso de los siguientes 20 días hábiles a la entrada en vigor de la presente reforma, las solicitudes que hayan recibido por estímulos fiscales hasta antes de la publicación de este Decreto, y relacionadas con lo establecido en la Ley de Fomento a la Competitividad y Desarrollo Económico para el Estado de Baja\nCalifornia; salvaguardando el derecho de obtener la resolución que corresponda por conducto de la Procuraduría Fiscal de la Secretaría de Hacienda.\nTERCERO. La Secretaría de Hacienda por conducto de la Procuraduría Fiscal, de la Secretaría de Economía e Innovación, respecto de las solicitudes de estímulos fiscales que hayan sido presentadas por proyecto de inversión nueva, ampliación o tecnología hasta próximos 60 días hábiles.\nLey de Hacienda del Estado de Baja California. Página 196\n.\nActualización Legislativa.\nÚltima reforma P.O. No. 72, Índice, 22-Dic-2023\nCUARTO. Las resoluciones emitidas con motivo de las solicitudes de estímulos fiscales con fundamento en el artículo 175 de esta Ley, antes de la entrada en vigor de la presente reforma, seguirán surtiendo sus efectos y continuarán vigentes en los términos señalados en el supuesto en que fue otorgado.\nAsimismo, el estímulo fiscal otorgado previo a la publicación de la presente reforma para la exención del Impuesto Sobre Remuneraciones al Trabajo Personal, seguirá aplicándose a la base del impuesto que resulte de acuerdo al artículo 151-14 de la presente\nLey, a la misma proporción de la tasa del 1.80% a la que fue otorgado, hasta que cumpla el término de su vigencia, quede sin efectos, o sea cancelado de conformidad con lo señalado en la Ley de Fomento a la Competitividad y Desarrollo Económico para el Estado de Baja\nCalifornia.\nQUINTO. Para los casos que venían ejerciendo la aplicación de los estímulos fiscales señalados en los artículos 180 y 181 de esta Ley hasta antes de la entrada en vigor de la presente reforma; será aplicable por última vez respecto al Impuesto Sobre Remuneraciones al Trabajo Personal causado hasta el mes de diciembre de 2023 o de aquellos causados hasta el cuarto trimestre del 2023.\nDADO en Sesión Ordinaria de la XXIV Legislatura en la Ciudad de Mexicali, B.C., a los diecinueve días del mes de diciembre del año dos mil veintitrés.\nDIP. ARACELI GERALDO NÚÑEZ\nPRESIDENTA\n(RÚBRICA)\nDIP. MANUEL GUERRERO LUNA\nSECRETARIO\n(RÚBRICA)\nSENTENCIA DE CONTROVERSIA CONSTITUCIONAL119/2020, NOTIFICADOS\nLOS PUNTOS RESOLUTIVOS A ESTE CONGRESO DE BAJA CALIFORNIA EN FECHA 15\nOFICIO NÚM. SGA/MOKM/105/2024\nSEÑOR LICENCIADO EDUARDO ARANDA MARTÍNEZ\nSECRETARIO DE LA SECCIÓN DE TRÁMITE DE\nCONTROVERSIAS CONSTITUCIONALES Y DE\nACCIONES DE INCONSTITUCIONALIDAD DE LA\nSUPREMA CORTE DE JUSTICIA DE LA NACIÓN\nLey de Hacienda del Estado de Baja California. Página 197\n.\nActualización Legislativa.\nÚltima reforma P.O. No. 72, Índice, 22-Dic-2023\nEl Tribunal Pleno, en su sesión celebrada el catorce de marzo de dos mil veinticuatro, resolvió la controversia constitucional 119/2020, promovida por el Poder Ejecutivo Federal, en los términos siguientes:\n“PRIMERO. Es parcialmente procedente y fundada la presente controversia constitucional.\nSEGUNDO. Se sobresee en la presente controversia constitucional respecto del artículo 136-6 de la Ley de Hacienda del Estado de Baja California, adicionado mediante el DECRETO No. 62, publicado en el Periódico Oficial de dicha entidad federativa el treinta de abril de dos mil veinte.\nTERCERO. Se declara la invalidez, con efectos generales, de los artículos del\n133 al 136-5 y 136-7 de la ley de Hacienda del Estado de Baja California, reformados y adicionados mediante el DECRETO No. 62 publicado en el Periódico Oficial de dicha entidad federativa el treinta de abril de dos mil veinte, la cual surtirá sus efectos a partir de la notificación de estos puntos resolutivos al Congreso del Estado de Baja\nCalifornia.\nCUATRO. Publíquese esta resolución en el Diario Oficial de la federación, en el\nPeriódico Oficial del Estado de Baja California, así como en el Semanario Judicial de la Federación y su Gaceta.”\nCabe señalar que el Tribunal Pleno determinó que la declaratoria de invalidez surtirá efectos generales a partir de la notificación de estos puntos resolutivos al Congreso del\nEstado de Baja California, por lo que le solicito que gire instrucciones para que, a la brevedad, se practique la citada notificación, inclusive al titular del poder Ejecutivo de dicha entidad federativa.\nAsimismo, con el objeto de dar cumplimiento a lo determinado por el Tribunal Pleno en su sesión privada celebrada el doce de abril de dos mil diez, le solicito que remita a esta conste la notificación que se realice al Congreso del Estado de Baja California.\nAtentamente\nLICENCIADO RAFAEL COELLO CETINA\n(RÚBLICA)\nLey de Hacienda del Estado de Baja California. Página 198",
  "ordenamiento": "REGLAMENTO",
  "jurisdiccion": "BAJA CALIFORNIA",
  "fuente_oficial": "Periódico Oficial",
  "FECHA PER OFIC": "2023/12/22",
  "ESTATUS": "VIGENTE",
  "TOMO": "TOMO_II",
  "URL": "https://www.congresobc.gob.mx/Documentos/ProcesoParlamentario/Leyes/TOMO_II/20231222_LEYHACES-2.PDF",
  "es_escaneado": false,
  "tiene_tablas": true,
  "materia": [
    "financiero",
    "fiscal",
    "económico"
  ]
}