{
  "titulo": "Ley DE LA JUVENTUD DEL ESTADO DE BAJA CALIFORNIA",
  "Contenido": "Publicada en el Periódico Oficial No. 33, Tomo CXVIII, Número Especial, de fecha 11 de julio del año 2011\nTÍTULO PRIMERO\nDISPOSICIONES GENERALES\nCAPÍTULO I\nGENERALIDADES\nARTÍCULO 1.- Las disposiciones contenidas en la presente Ley son de orden público, interés social y de observancia general en el Estado de Baja California, y tiene por objeto normar las medidas y acciones que contribuyan al desarrollo integral de los jóvenes, garantizando el respeto de sus derechos fundamentales en todo el territorio del Estado de\nBaja California, así como regular la organización y el funcionamiento del organismo público descentralizado denominado Instituto de la Juventud del Estado de Baja California.\nARTÍCULO 2.- Son sujetos de aplicación de la presente Ley, todas las personas que se encuentren comprendidas entre los 12 a los 29 años de edad en el Estado, y sus normas se les aplicarán, de manera independiente a su género, condición familiar, social, cultural, religiosa, económica, étnica, de discapacidad, ideológicas o preferenciales, con la finalidad de contribuir a su desarrollo integral, mediante su inclusión social plena al proceso del desarrollo estatal.\nPárrafo Reformado\nEl límite de edad previsto en el párrafo anterior, no sustituye los límites de edad establecidos en otras leyes e instrumentos internacionales.\nArtículo Reformado\nARTÍCULO 3.- El Estado y los municipios en el ámbito de su competencia, dispondrán los recursos económicos, materiales, técnicos y humanos necesarios, y expedirán las disposiciones reglamentarias necesarias para el cumplimiento de la presente\nLey.\nARTÍCULO 4.- Para los efectos de esta Ley se entiende por:\nI.- Alteraciones del desarrollo: a todos aquellos factores, eventos, conductas y situaciones que afecten el entorno de las y los jóvenes, incrementando la posibilidad de sufrir daños que limiten su capacidad física, mental, emocional o profesional, colocándolos en riesgo, desventaja o vulnerabilidad que atentan contra el desarrollo integral, o en se inserción a la sociedad;\nFracción Reformada\nLey de la Juventud del Estado de Baja California. Página 1\nII.- Carnet: a la Tarjeta Carnet Joven;\nIII.- Comisión: a la Comisión encargada de los temas de Juventud en el Congreso del\nEstado;\nFracción Reformada\nIV.- Consejo: Consejo Estatal de Atención a la Juventud;\nV.- Dirección.- Cargo que ocupa una persona como Directora o Director General del\nInstituto de la Juventud del Estado de Baja California;\nFracción Reformada\nVI.- Desarrollo integral: A todos aquellos factores y elementos que construyen a maximizar las capacidades de las y los jóvenes para vivir dignamente y en armonía consigo mismos, con el medio ambiente, con el medio social, en cualquiera de los contextos en que se desarrolle dicha etapa de la vida;\nFracción Reformada\nVII.- Gobernador: al Titular del Poder Ejecutivo del Estado de Baja California;\nVIII.- Instituto: al Instituto de la Juventud del Estado de Baja California;\nIX.- Instituto, Dirección o Dependencia Municipal: a los organismos de la Juventud de las administraciones públicas municipales de Baja California;\nX.- Jóvenes: a las personas cuya edad comprenden el rango entre los 12 y los 29 años de edad;\nXI.- Junta Directiva: Autoridad administrativa superior del Instituto;\nXII.- Juventud: Al conjunto de jóvenes del Estado de Baja California;\nXIII.- Ley: a la Ley de la Juventud del Estado de Baja California;\nXIV.- Parlamento: al Parlamento de la Juventud del Estado de Baja California;\nXV.- Premio: al Premio Estatal de la Juventud;\nXVI.- Primer Empleo: Al proceso de integración de una o un joven por primera ocasión al mercado laboral, sea en el sector público o privado;\nFracción Reformada\nXVII.- Programa: al Programa Estatal de Atención a la Juventud;\nXVIII.- Plataforma Digital: Sistema Electrónico de información;\nFracción Reformada\nXIX.- Adolescencia: Las personas de entre doce años cumplidos y menos de dieciocho años de edad;\nFracción Adicionada, recorriéndose las subsecuentes\nXX.- Igualdad Sustantiva. - El acceso al mismo trato y oportunidades para el reconocimiento, goce o ejercicio de los derechos humanos y las libertades fundamentales;\nFracción Adicionada, recorriéndose las subsecuentes\nLey de la Juventud del Estado de Baja California. Página 2\nFracción Reformada\nXXII.- Sistema: Al Sistema Estatal de Atención a la Juventud.\nFracción Reformada\nArtículo Reformado\nARTÍCULO 5.- Esta Ley reconoce todos los derechos y garantías establecidos en la recoge íntegramente el contenido de las Convenciones y Tratados Internacionales suscritos y reconocidos por México en relación con la juventud y derechos humanos, así como las demás disposiciones legales federales y locales aplicables.\nLos derechos y garantías previstos en esta Ley hacia los jóvenes, se establecen de manera enunciativa, más no limitativa.\nARTÍCULO 6.- Las disposiciones de esta Ley, son complementarias a las establecidas para las personas que se encuentren en las edades comprendidas entre los 12 años de edad, hasta los 18 años de edad cumplidos, previstas en la Ley para la Protección y\nDefensa de Niñas, Niños y Adolescentes.\nPárrafo Reformado\nEn caso de controversia sobre la aplicación e interpretación de las disposiciones de esta Ley con otra legislación aplicable en materia de juventud, prevalecerá aquella que más favorezca los derechos de los jóvenes.\nArtículo Reformado\nARTÍCULO 7.- Son principios rectores en la observancia, interpretación y aplicación de esta Ley, los siguientes:\nI.- Civilidad: entendida como el desarrollo de valores democráticos en la persona, tendientes a potenciar la convivencia, la libertad y la tolerancia en sociedad;\nII.- Concurrencia: entendida como la distribución de competencias de los diferentes órdenes de gobierno en la tutela y atención integral de la juventud;\nIII.- Corresponsabilidad: entendida como la responsabilidad compartida de las instituciones del Estado, la sociedad y la familia en la atención integral de la juventud;\nIV.- Identidad: entendida como un ideal de la juventud en la formación de su personalidad, procurando otorgar un sentido de pertenencia con las costumbres y tradiciones propias del Estado;\nV.- Igualdad: Entendida como la posibilidad de obtener oportunidades para la juventud en forma equitativa, eliminando desventajas para asegurar la paridad entre las y los jóvenes;\nFracción Reformada\nLey de la Juventud del Estado de Baja California. Página 3\nVI.- Inclusión: entendida como la inserción o introducción de la juventud en el proceso de desarrollo político, económico, social y cultural del país;\nVII.- Interés Superior: entendido como una prioridad en las acciones que se dirijan a los jóvenes para fortalecer su bienestar, su desarrollo integral y la protección de sus derechos;\nVIII.- No discriminación: Entendida como el combate a conductas excluyentes por condición social o económica, de salud, condición de discapacidad, preferencia, género, edad, origen étnico, afiliación partidista, religión u otra reconocida por la Ley;\nFracción Reformada\nIX.- Participación: Entendida como la intervención libre, constante y democrática de la juventud en los procesos de toma de decisiones que afecten su entorno;\nFracción Reformada\nX.- Respeto: entendido como el reconocimiento a la diversidad de la juventud;\nXI.- Seguridad: Entendida como el disfrute de una vida libre de violencia y alejada de factores de riesgo psicosociales y/o alteraciones del desarrollo en la juventud;\nFracción Reformada\nXII.- Solidaridad: entendida como las relaciones entre la juventud y los grupos sociales, con la finalidad de superar las condiciones que crean marginación y desigualdades;\nXIII.- Transversalidad: Entendida como la directriz para articular políticas públicas entre los diversos órdenes de gobierno a partir de la visión integral de los derechos civiles, políticos, económicos, sociales y culturales de la juventud, considerando las distintas etapas y la necesidad de establecer estrategias específicas para cada una de ellas, y\nFracción Reformada\nXIV.- Universalidad: Entendida como el beneficio de la generalidad de las y los jóvenes sin distinción de origen étnico o nacional, género, edad, discapacidad, condición social, salud, religión, preferencias, estado civil o cualquier otra que atente contra la dignidad humana.\nFracción Reformada\nArtículo Reformado\nTÍTULO SEGUNDO\nDE LOS DERECHOS Y DEBERES DE LA JUVENTUD\nCAPÍTULO PRIMERO\nDE LOS DERECHOS DE LA JUVENTUD\nARTÍCULO 8.- Los derechos y garantías de los jóvenes, son inherentes a su condición de persona humana, por consiguiente, serán de máxima prioridad, indivisibles e irrenunciables.\nLey de la Juventud del Estado de Baja California. Página 4\nARTÍCULO 9.- Los jóvenes gozan, sin restricción alguna, de la protección efectiva de\nLey.\nARTÍCULO 10.- Los jóvenes como miembros de la sociedad y como habitantes del\nEstado de Baja California, tienen como derecho de acceso y disfrute de los servicios y beneficios socio-económicos, políticos, culturales, informativos, de desarrollo y de convivencia que les permitan una vida digna en el Estado.\nARTÍCULO 11.- Para los efectos de esta Ley, los derechos de la juventud, se clasifican de la siguiente forma:\nI.- Derechos civiles y políticos;\na) Derecho a una vida digna;\nb) Derecho a la identidad e integridad personal;\nc) Derecho de acceso a la justicia;\nd) Derecho a vivir en familia;\ne) Derecho a la libertad de expresión, opinión y religión;\nf) Derecho de reunión, organización y asociación;\nInciso Reformado\ng) Derecho a la participación social y política; y,\nInciso Reformado\nh) Derecho de acceso a la información.\nInciso Adicionado\nFracción Reformada\nII.- Derechos económicos, sociales y culturales:\na) Derecho a la salud;\nb) Derecho a la educación;\nc) Derecho a un trabajo digno;\nd) Derecho a la cultura y al arte;\ne) Derecho a un medio ambiente sano y sustentable;\nf) Derecho de recreación, descanso y esparcimiento; y,\nInciso Reformado\ng) Derecho a la práctica del deporte;\nInciso Adicionado\nh) Derechos de los jóvenes con discapacidad; y, Ley de la Juventud del Estado de Baja California. Página 5\nInciso Adicionado\ni) Derecho a la movilidad.\nInciso Adicionado\nFracción Reformada\nArtículo Reformado\nCAPÍTULO SEGUNDO\nDERECHOS CIVILES Y POLÍTICOS\nSECCIÓN PRIMERA\nDERECHO A UNA VIDA DIGNA\nARTÍCULO 12.- La dignidad de los jóvenes es inviolable y deberá ser protegida de los efectos nocivos de la violencia, asegurando su desarrollo físico, moral e intelectual acorde a sus capacidades, para permitir su incorporación como actores estratégicos de la vida colectiva con niveles óptimos de madurez.\nArtículo Reformado\nARTÍCULO 13.- El Estado y los Municipios promoverán mediante los medios disponibles, propuestas, espacios, instancias y estrategias para que las y los jóvenes tengan las oportunidades necesarias para asegurar una vida digna con calidad, creatividad, vitalidad, e impregnada de valores que contribuyan a su pleno desarrollo y la expresión de su potencialidad y capacidad humana.\nArtículo Reformado\nARTÍCULO 14.- Las y los jóvenes tienen derecho a su propia identidad, entendida como un ideal de la juventud en la formación de su personalidad, procurando otorgar un sentido de pertenencia con las costumbres y tradiciones propios del Estado, en atención a sus especificidades y características de sexo, condición de discapacidad, filiación, preferencias, orientación sexual, creencias y cultura.\nPárrafo Reformado\nEl Estado y los Municipios garantizarán la libre expresión de los diferentes elementos entre sí.\nArtículo Reformado\nARTÍCULO 15.- El Estado y los Municipios adoptarán medidas de protección a la integridad personal, seguridad física y mental de los jóvenes, salvaguardando un trato digno verificaciones que involucren sus pertenencias.\nSECCIÓN SEGUNDA\nDERECHO DE ACCESO A LA JUSTICIA\nLey de la Juventud del Estado de Baja California. Página 6\nARTÍCULO 16.- Las y los jóvenes tienen el derecho de acceder a la justicia por medio de los tribunales instaurados para tal fin, contando con la garantía de audiencia que le permite formular su denuncia o defensa, asegurando el desahogo de todas las etapas del debido proceso.\nArtículo Reformado\nARTÍCULO 17.- A las y los jóvenes que se les atribuya la comisión de una conducta ilícita, deberán recibir un trato justo, digno y humano, tomando en cuenta su condición juvenil y la aplicación estricta de la legislación específica para su edad.\nArtículo Reformado\nARTÍCULO 18.- Ninguna autoridad podrá establecer algún tipo de sanción en contra de alguna o algún joven en lo individual o como grupo identificado con motivo de su apariencia, su personalidad, pertenencia a una tribu urbana o por sus preferencias.\nArtículo Reformado\nARTÍCULO 18 BIS. - Las y los jóvenes tendrán derecho a recibir orientación, apoyo y protección de las autoridades estatales y municipales, cuando su integridad se encuentre en riesgo por verse involucrados en relaciones de noviazgo que impliquen algún tipo de violencia.\nArtículo Adicionado\nSECCIÓN TERCERA\nDERECHO A VIVIR EN FAMILIA\nARTÍCULO 19.- Las y los jóvenes tienen el derecho a formar parte de una familia donde se desarrollen relaciones de igualdad, de afecto, respeto, tolerancia, responsabilidad, solidaridad y comprensión mutua entre sus miembros, alejados de cualquier tipo de maltrato, violencia, desprecio o discriminación.\nArtículo Reformado\nARTÍCULO 20.- El Estado y los Municipios fomentaran entre la juventud, los valores de la familia, la cohesión y fortaleza de la vida familiar, el sano desarrollo de todos sus integrantes, así como la inculcación de principios de respeto, solidaridad subsidiariedad entre padres e hijos, así como el resto de los integrantes de la familia, a través de estrategias publicas transversales.\nArtículo Reformado\nSECCIÓN CUARTA\nDERECHO A LA LIBERTAD DE EXPRESIÓN, OPINIÓN Y RELIGIÓN\nARTÍCULO 21.- Los jóvenes tienen derecho a la libertad de expresión, opinión y religión, prohibiéndose cualquier forma de persecución o represión por el ejercicio de dichos derechos.\nLey de la Juventud del Estado de Baja California. Página 7\nARTÍCULO 22.- La única limitación a estos derechos, será en casos de ataque a la moral, afectación de los derechos de terceros, comisión de delitos o perturbación del orden público, de conformidad con las disposiciones aplicables para cada caso concreto.\nSECCIÓN QUINTA\nDERECHO DE REUNIÓN, ORGANIZACIÓN Y ASOCIACIÓN\nARTÍCULO 23.- Las y los jóvenes tienen el derecho de reunirse, organizarse y asociarse libremente en forma licita y pacífica, en tanto no afecten o perturben los derechos de terceros en la búsqueda de hacer realidad sus aspiraciones, proyectos individuales y colectivos, así como para atender los temas de su interés y proponer soluciones a los problemas que recienten ante las instancias competentes.\nArtículo Reformado\nARTÍCULO 24.- El Estado y los Municipios deberán coadyuvar con las agrupaciones juveniles a facilitar su organización para asociarse cuando estas lo deseen, respetando su independencia y autonomía, contando con el reconocimiento y apoyo de otros actores involucrados, sin importar cuál sea el fin que buscan, siempre que sea lícito.\nSECCIÓN SEXTA\nDERECHO A LA PARTICIPACIÓN SOCIAL Y POLÍTICA\nARTÍCULO 25.- La juventud tiene el derecho de participación social y política como manera de mejorar sus condiciones de vida, involucrándose en la toma de decisiones de los sectores social, público y privado.\nArtículo Reformado\nARTÍCULO 26.- El Estado y los Municipios impulsarán acciones que hagan efectiva la participación de los jóvenes de todos los sectores de la sociedad, alentando su inclusión en organizaciones, e incentivando su derecho de adherirse en agrupaciones políticas, sociales o académicas.\nSECCIÓN SÉPTIMA\nDERECHO DE ACCESO A LA INFORMACIÓN PÚBLICA\nSección Adicionada\nARTÍCULO 26 BIS.- Las y los jóvenes tendrán derecho de acceso a la información pública, por lo que podrán solicitar, investigar, difundir, buscar y recibir información en los términos que dispongan las Leyes de la materia.\nArtículo Adicionado\nARTÍCULO 26 TER.- Las y los jóvenes tendrán acceso a la información pública, de forma completa, oportuna y accesible, en los términos que dispongan las Leyes de la materia.\nArtículo Adicionado\nLey de la Juventud del Estado de Baja California. Página 8\nCAPÍTULO TERCERO\nDE LOS DERECHOS ECONÓMICOS, SOCIALES Y CULTURALES\nSECCIÓN PRIMERA\nDERECHO A LA SALUD\nARTÍCULO 27.- Las y los jóvenes tienen el derecho a la salud integral, que se traduce en su bienestar físico, mental y social debiendo tomarse en cuenta sus características y condición de discapacidad.\nArtículo Reformado\nARTICULO 28.- Las autoridades sanitarias velaran por la plena efectividad del derecho a la salud juvenil, adoptando políticas, programas y campañas de salud orientados a la prevención de enfermedades, combate al consumo de drogas o alcohol, salud sexual y reproductiva, trastornos alimenticios, higiene, salud mental, promoción estilos de vida saludables, así como todo aquello que favorezca el cuidado y salud personal de los jóvenes.\nArtículo Reformado\nARTÍCULO 29.- El Estado y el Municipio diseñaran políticas públicas dirigidas a las y los jóvenes para la prevención, atención y control de embarazos y adolescentes, maternidad y paternidad responsable, y para inhibir las consecuencias personales que originan a la juventud en cuanto a su desarrollo escolar, familiar y laboral.\nArtículo Reformado\nSECCIÓN SEGUNDA\nDERECHO A LA EDUCACIÓN\nARTÍCULO 30.- La juventud tiene el derecho de acceder a la educación, incluyendo la libertad de participar en forma activa dentro de la institución en que se encuentre cursando sus estudios.\nArtículo Reformado\nARTÍCULO 31.- Se entenderá y comprenderá por educación integral para la juventud:\nI.- El desarrollo pleno de sus capacidades a través de la orientación vocacional;\nII.- La educación sexual como fuente de desarrollo personal, afectividad y expresión comunicativa, así como la información de los aspectos y riesgos de su práctica, que incluyen la adquisición de enfermedades o embarazo no deseados;\nFracción Reformada\nIII.- Para promover el ejercicio responsable de la sexualidad, el desarrollo de para concluir la educación básica obligatoria;\nFracción Reformada\nLey de la Juventud del Estado de Baja California. Página 9\nIV.- Mecanismos para garantizar el acceso a una educación media superior y superior;\nVI.- Métodos para contribuir con el cuidado e impulso del medio ambiente;\nVII.- Mecanismos de ingreso a las diferentes formas de educación para la inserción de una vida laboral, y\nVIII.- La atención integral para los jóvenes con discapacidad que incluirá apoyos de acceder a la educación básica, media superior y superior, así como la implementación de ajustes razonables.\nFracción Reformada\nArtículo Reformado\nARTÍCULO 32.- El Estado y los Municipios reconocen su obligación de garantizar una educación básica y media superior en forma gratuita, integral, continua, pertinente y de calidad para consolidar el desarrollo de la juventud.\nTambién impulsarán estrategias para estimular el acceso de los jóvenes a la educación superior y posgrado, y establecerán campañas de difusión permanente sobre los programas de financiamiento, crédito y apoyo educativos.\nARTÍCULO 33.- Los jóvenes tienen el derecho de fortalecer y expresar sus diferentes vocaciones y elementos de identidad que los distinguen de otros sectores y grupos sociales.\nEl Gobierno deberá crear, promover y apoyar, por todos los medios a su alcance, iniciativas e instancias para que los jóvenes tengan la posibilidad y la oportunidad de identificar sus vocaciones y fortalecer las acciones para desarrollar su vocación a plenitud.\nSECCIÓN TERCERA\nDERECHO A UN TRABAJO DIGNO\nARTÍCULO 34.- Los jóvenes tienen derecho a un trabajo digno, bien remunerado y a una protección especial del mismo, de acuerdo con su vocación, aptitudes y destrezas, de forma que les permita elevar su calidad de vida en la sociedad, de conformidad con las disposiciones laborales aplicables.\nLo anterior bajo las consideraciones de la igualdad de oportunidades y trato, en lo relativo a la inserción, remuneración sin discriminación, promoción y condiciones en el trabajo para hacer compatible el tiempo de estudio con la vida laboral, tomando en cuenta la edad de los jóvenes.\nARTÍCULO 35.- El Estado y los Municipios contemplarán en sus planes y programas de gobierno estrategias y líneas de acción para impulsar el empleo juvenil, bolsas de trabajo, capacitación laboral, financiamiento para proyectos productivos, el autoempleo, así como\nLey de la Juventud del Estado de Baja California. Página 10 de trabajo para los jóvenes. comunitarias.\nArtículo Reformado\nARTÍCULO 36.- Las políticas de empleo juvenil que formulen el Estado y los\nMunicipios dirigidas a jóvenes menores de edad, deberán observar las normas de protección especial y supervisión exhaustiva que impone la legislación nacional e internacional.\nBajo ninguna circunstancia se permitirá a los jóvenes menores de edad desempeñar un empleo que obstaculice o retarde su desarrollo físico, mental, emocional o profesional.\nARTÍCULO 37.- El Estado y los Municipios fomentaran el desarrollo de políticas públicas que permitirán a los jóvenes acceder a su primer empleo, atendiendo de manera especial a quienes se encuentren temporalmente desocupados.\nLas funciones que desempeñe un empleado joven en su primer empleo deberán ser adecuadas al nivel de formación y preparación académica.\nLas empresas que contraten a jóvenes en la modalidad de primer empleo recibirán los beneficios y estímulos económicos que señale la normatividad fiscal y económica.\nDe igual forma se proporcionarán los beneficios económicos y estímulos que al efecto señale la normatividad fiscal y económica, a las empresas que proporcionen empleos temporales a jóvenes estudiantes durante sus periodos vacacionales.\nArtículo Reformado\nARTÍCULO 38.- Los Poderes del Estado, los Municipios, los Organismos\nConstitucionales Autónomos, en el ámbito de su competencia, así como el sector social y privado, deberán impulsar el servicio social y las prácticas profesionales del sector educativo, como vínculo para generar el desarrollo profesional y laboral de los jóvenes, acercándolos a la oportunidad de conseguir su primer empleo.\nSECCIÓN CUARTA\nDERECHO A LA CULTURA Y AL ARTE\nARTÍCULO 39.- Las y los jóvenes tienen derecho a disfrutar libremente de su cultura, lengua, usos, costumbre, religión y formas específicas de organización social en razón de su edad y características.\nPárrafo Reformado\nLey de la Juventud del Estado de Baja California. Página 11\nTambién tienen el derecho a la libre creación artística, así como el acceso a espacios expectativas. integral.\nArtículo Reformado\nARTÍCULO 40.- El Estado y los Municipios fomentarán la creación artística y cultural impulsada por los jóvenes, así como su intercambio a nivel nacional e internacional.\nSECCIÓN QUINTA\nDERECHO A UN MEDIO AMBIENTE SANO Y SUSTENTABLE\nARTÍCULO 41.- Los jóvenes tienen derecho a vivir y disfrutar un medio ambiente sano, ecológicamente equilibrado y sustentable, que sea óptimo para su desarrollo integral y bienestar social.\nARTÍCULO 42.- El Estado y los Municipios promoverán la coordinación con las autoridades ambientales del Gobierno Federal, así como con el sector social y privado para favorecer la participación de los jóvenes en acciones orientadas en el cuidado y protección del medio ambiente.\nARTÍCULO 43.- El Estado y los Municipios desarrollaran estrategias de educación ambiental para fortalecer la cultura ambiental y ecológica entre los jóvenes.\nSECCIÓN SEXTA\nDERECHO DE RECREACIÓN, DESCANSO Y ESPARCIMIENTO\nARTÍCULO 44.- Los jóvenes tienen derecho al descanso, a la recreación y al esparcimiento, los cuales deberán ser respetados como elementos fundamentales de su desarrollo integral.\nARTÍCULO 45.- Los jóvenes tienen derecho a contar con tiempo libre en beneficio de su enriquecimiento personal y disfrute de la vida en forma individual o colectiva, que tiene como objetivos básicos la diversión, la socialización, la liberación del trabajo y la recuperación física y mental.\nSECCIÓN SÉPTIMA\nDERECHO A LA PRÁCTICA DEL DEPORTE\nARTÍCULO 46.- Los jóvenes tienen derecho a la educación física, a la práctica del deporte y la cultura física, de acuerdo a su libre elección y aptitudes, así como al disfrute de espectáculos deportivos.\nLey de la Juventud del Estado de Baja California. Página 12\nARTÍCULO 47.- El Estado y los Municipios promoverán la actividad física y deportiva la delincuencia, además de difundir permanentemente los beneficios que trae consigo su práctica cotidiana o como profesión.\nSECCIÓN OCTAVA\nDERECHOS DE LOS JÓVENES CON DISCAPACIDAD\nARTÍCULO 48.- Los jóvenes con discapacidad tiene derecho a disfrutar de todos los derechos establecidos en esta Ley, y, además, las autoridades competentes deberán realizar las accione afirmativas necesarias, así como los ajustes razonables para garantizar que se disfruten a plenitud promoviendo su plena inclusión en la sociedad.\nArtículo Reformado\nARTÍCULO 49.- Las y los jóvenes con discapacidad, son aquellos que cuentan con una deficiencia o limitación en su persona, que al interactuar con las barreras que le impone el entorno social, le impide su inclusión plena y efectiva en la sociedad, en igualdad de condiciones con los demás. La discapacidad puede ser física, mental, intelectual o sensorial.\nArtículo Reformado\nARTÍCULO 50.- El programa debe establecer lineamientos que permita asegurar el diseño e implementación de acciones afirmativas y ajustes razonables para buscar su plena inclusión en la sociedad.\nArtículo Reformado\nSECCIÓN NOVENA\nDERECHO A LA MOVILIDAD\nDenominación Adicionada\nARTÍCULO 50 BIS.- Las y los jóvenes tienen derecho de movilidad, por lo tanto, el\nEstado promoverá y fomentará los medios para que puedan desplazarse, a través de las distintas modalidades del transporte público o privado, garantizando vialidades, accesos, dando prioridad a políticas de inclusión para las personas con discapacidad, asimismo el\nEstado y los Municipios normarán este derecho.\nArtículo Adicionado\nCAPÍTULO CUARTO\nDEBERES DE LOS JÓVENES\nARTÍCULO 51.- Las y los jóvenes tienen los siguientes deberes a observar en relación a su persona:\nPárrafo Reformado\nI.- Asumir el proceso de su propia formación académica, aprovechando en forma\nLey de la Juventud del Estado de Baja California. Página 13 superarse en forma continua, concluyendo como mínimo la educación básica obligatoria prestando un servicio social y el desarrollo de prácticas profesionales efectivas;\nII.- Preservar su salud a través del auto cuidado, prácticas de vida sana, ejecución de buenos hábitos y deporte como medios de bienestar físico y mental. El joven comunicará a su familia cualquier tipo de alteración del desarrollo que presente en su salud física o mental;\nIII.- Procurar el aprendizaje y practicar los valores más altos del ser humano, que contribuyan a darle su verdadera dimensión ética y moral como persona individual y como parte de una sociedad;\nIV.- Tener conocimiento en materia de sexualidad los riesgos de las enfermedades de trasmisión sexual, la salud reproductiva, planificación familiar, violencia de género; y,\nFracción Reformada\nV.- Conocer las repercusiones legales y daños irreversibles a la salud que producen el alcohol, el tabaco y las drogas.\nArtículo Reformado\nARTÍCULO 52.- Los jóvenes tienen los siguientes deberes a observar en relación a su familia:\nI.- Contribuir a la economía familiar, cuando las necesidades así lo demanden, respetando la protección que la legislación laboral brinda a los jóvenes menores de edad;\nII.- Participar en el cuidado, educación y enseñanza de otros miembros de la familia que lo requieran, cuando las necesidades así lo demanden;\nIII.- Evitar dentro de sus hogares cualquier acto de discriminación, abuso, aislamiento, prepotencia o violencia familiar, contra cualquier miembro de la familia, y\nIV.- Atender las recomendaciones de sus padres cuando éstas sean para su beneficio y no atenten contra su dignidad e integridad personal.\nARTÍCULO 53.- Las y los jóvenes tienen los siguientes deberes a observar en relación con la sociedad:\nPárrafo Reformado\nI.- Actuar con criterio de solidaridad social, contribuyendo a la realización de acciones para el desarrollo comunitario;\nII.- Participar activamente en la vida cívica, política, económica, cultural y social de su comunidad y del Estado;\nIII.- No atentar contra los derechos de terceros, evitando cualquier conducta o actitud sancionable por las Leyes;\nLey de la Juventud del Estado de Baja California. Página 14\nIV.- Contribuir a la conservación y mejoramiento del medio ambiente, evitando la contaminación y desempeñando un papel activo en aquello que esté a su alcance, y\nV.- Promover la convivencia pacífica e igualitaria, así como la unidad entre los jóvenes.\nFracción Reformada\nArtículo Reformado\nARTÍCULO 54.- Las y los jóvenes tienen los siguientes deberes a observar en relación con el Estado:\nPárrafo Reformado\nI.- Respetar y cumplir con lo dispuesto en la Constitución Política de los Estados\nUnidos Mexicanos, la particular del Estado, las leyes que de ellas deriven y reglamentos de las mismas, en concordancia con el respeto irrestricto de los derechos de los demás grupos y segmentos de la sociedad, todo ello a través de la convivencia pacífica, la no discriminación la tolerancia, la democracia, el compromiso y la participación social.\nFracción Reformada\nII.- Ejercer sus derechos con responsabilidad y cumplir cabalmente con las obligaciones que le confieren la presente Ley y cualquier otra disposición;\nIII.- Guardar el debido respeto a las autoridades legalmente constituidas, así como a los símbolos patrios que forman parte de la identidad nacional y bajacaliforniana;\nIV.- Contribuir al avance de la vida democrática del Estado participando en los procesos que tengan lugar para la elección de las distintas autoridades y cargos de elección popular, y\nV.- Mantener dentro y fuera del territorio del Estado actitudes que dignifiquen el nombre de Baja California.\nArtículo Reformado\nTÍTULO TERCERO\nCAPÍTULO PRIMERO\nARTÍCULO 55.- La Política estatal de atención a la juventud, contará con una estrategia de desarrollo integral, con igualdad de género, trasversal y permanente, que estará dirigida al logro de los siguientes objetivos:\nPárrafo Reformado\nLey de la Juventud del Estado de Baja California. Página 15\nI.- Avanzar en el establecimiento de las condiciones que aseguren el disfrute y ejercicio efectivo de los derechos civiles, políticos, económicos, sociales, culturales, reproductivos y sexuales de la juventud;\nFracción Reformada\nII.- Promover el desarrollo integral de los jóvenes, maximizando sus capacidades para vivir dignamente y en armonía con sus dimensiones biológicas, psicológicas, sociales y espirituales que, articuladas coherentemente, garantizan el ejercicio pleno de sus derechos y deberes en cualquiera de los contextos en que se desarrolle su etapa juvenil;\nIII.- Facilitar la participación de los jóvenes en el diseño, planeación, programación, ejecución, seguimiento y evaluación de las políticas, planes, programas y acciones dirigidas a la juventud;\nIV.- Articular la coordinación interinstitucional de los distintos órdenes de gobierno para lograr la consolidación de las políticas, acciones y programas que se lleven a cabo en beneficio de los jóvenes;\nV.- Asegurar la inclusión, aplicación, respeto y cumplimiento de los principios que señala la presente Ley, y\nVI.- Respetar las directrices de la política nacional de juventud.\nArtículo Reformado\nARTÍCULO 56.- El Estado y los Municipios promoverán políticas en favor de las y los jóvenes en situación de riesgo, vulnerabilidad o desventaja social para crear condiciones de igualdad real y efectiva.\nPárrafo Reformado\nEn las acciones que se desarrollen para el cumplimiento del párrafo anterior, se deberá poner especial énfasis a los jóvenes:\nPárrafo Reformado\nI.- Embarazadas o esperando un hijo, en el caso de los jóvenes;\nFracción Reformada\nII.- Madres solteras;\nIII.- Víctimas de cualquier delito;\nIV.- En situación de calle o en desocupación por circunstancias que impiden que ni estudien ni trabajen y que obstaculizan su inserción a la sociedad;\nV.- Sufriendo de exclusión social o privación de la libertad;\nFracción Reformada\nVI.- Que cuentan con alguna discapacidad;\nLey de la Juventud del Estado de Baja California. Página 16\nFracción Reformada\nVII.- Con enfermedades crónicas;\nFracción Reformada\nVIII.- Pertenecientes a alguna comunidad indígena; y,\nFracción Reformada\nIX.- Que pertenezcan a algún grupo vulnerable en consecuencia a su género, preferencias y orientación sexual.\nFracción Adicionada\nArtículo Reformado\nCAPÍTULO SEGUNDO\nDEL SISTEMA ESTATAL DE ATENCIÓN A LA JUVENTUD\nARTÍCULO 57.- El Sistema es el conjunto de instituciones, políticas públicas, programas, organismos auxiliares y de consulta, así como registros de información en materia de juventud, que promueven, protegen y difunden los derechos de los jóvenes en\nBaja California.\nLa implementación del Sistema estará coordinada por el Instituto, en el ámbito de su competencia.\nARTÍCULO 58.- El Sistema funcionará como instrumento base para la coordinación funcional, administrativa e institucional entre los tres órdenes de Gobierno, organismos autónomos, instituciones privadas, sociales y educativas, organismos no gubernamentales y organizaciones juveniles para la formulación de acciones en beneficio de los jóvenes en el\nEstado.\nARTÍCULO 59.- El sistema tiene por objeto garantizar la inclusión y participación de los sectores público, social y privado en las acciones para la promoción, protección y respeto de los derechos de la juventud en la Entidad.\nArtículo Reformado\nARTÍCULO 60.- El Sistema se integrará por:\nI.- La persona que ocupe el cargo de Gobernador del Estado, como representante del\nFracción Reformada\nII.- Secretaría General de Gobierno;\nIII.- Secretaría de Integración y Bienestar Social;\nFracción Reformada\nLey de la Juventud del Estado de Baja California. Página 17\nIV.- Secretaría de Salud;\nV.- Secretaría de Trabajo y Previsión Social;\nFracción Reformada\nVI.- La Secretaria de Cultura;\nFracción Adicionada, recorriéndose las subsecuentes\nVII.- Instituto del Deporte y la Cultura Física;\nVIII.- El Instituto;\nIX.- Institutos Municipales o dependencias encargadas de la atención a la juventud;\nX.- El Programa;\nXI.- El Consejo;\nXII.- La Red; y,\nXIII.- El informe de la situación que guarda el tema de juventud en el Estado.\nArtículo Reformado\nCAPÍTULO TERCERO\nDEL PROGRAMA ESTATAL DE ATENCIÓN A LA JUVENTUD\nARTÍCULO 61.- El Programa es el instrumento rector de la Política Estatal de\nAtención a la Juventud, y establecerá los objetivos, estrategias y acciones para promover el desarrollo integral de los jóvenes, en los términos de las Leyes federales y estatales así como los tratados internacionales.\nARTÍCULO 62.- El Programa deberá contener al menos las siguientes acciones:\nI.- Fomentar el conocimiento y la observancia de los derechos y deberes de los jóvenes;\nII.- Contemplar un diagnóstico integral de la situación del sector juvenil en el Estado, señalando sus principales problemas y tendencias, la descripción de las fortalezas y oportunidades para su desarrollo integral, así como los obstáculos que generan alteraciones del desarrollo, mismo que se tomara en cuenta para la definición e implementación de\nProgramas y Proyectos juveniles;\nIII.- Implementar un sistema de empleo juvenil, mediante bolsas de trabajo, capacitación laboral, autoempleo, financiamiento para proyectos juveniles, incubadora de\nLey de la Juventud del Estado de Baja California. Página 18 empresas y negocios, y estímulos fiscales para las empresas del sector público y privado que incentiven la modalidad del primer empleo;\nIV.- Medidas de apoyo para el acceso a guarderías para aquellas madres estudiantes con el fin de evitar su deserción educativa;\nV.- Lograr que los jóvenes puedan adquirir conocimientos prácticos sin suspender estudios;\nVI.- Consolidar su incorporación a la actividad económica mediante una ocupación específica, y también promover su Educación Financiera como herramienta para mejorar las condiciones de la juventud;\nFracción Reformada\nVII.- Establecer mecanismos para garantizar los derechos de los jóvenes en el área laboral sin discriminación alguna, así como la determinación de normas para la protección al empleo para los jóvenes menores de edad y una supervisión exhaustiva de las mismas;\nVIII.- Promover el acceso y permanencia de los jóvenes a la educación, así como facilitar el acceso a becas e intercambios académicos nacionales y extranjeros que promuevan, apoyen y fortalezcan el desarrollo educativo de la juventud;\nIX.- Promover el acceso de los jóvenes a las tecnologías de la información y comunicación, así como los mecanismos de trasparencia, como medio para facilitar la obtención, procesamiento, intercambio y difusión de información juvenil actualizada;\nFracción Reformada\nX.- Diseñar mecanismos para la obtención de descuentos y estímulos económicos para jóvenes que contraten bienes y servicios públicos y privados, a través de la Carnet;\nXI.- Impulsar campañas de difusión e información sobre la atención y prevención de problemáticas juveniles de interés y prioritarias, como las adicciones, salud sexual y reproductiva, infecciones de trasmisión sexual como el VIH-SIDA, entre otras, nutrición y salud pública, culturales y comunitarias;\nFracción Reformada\nXII.- Diseñar mecanismos para el acceso de los jóvenes a actividades físicas y deportivas, así como al disfrute de espectáculos deportivos;\nXIII- Promover la creación de espacios culturales dedicados a los jóvenes, donde puedan difundir sus expresiones artísticas y culturales, así como el intercambio cultural a nivel nacional e internacional;\nXIV.- Diseñar mecanismos para proteger a los jóvenes en situación de riesgo, desventaja, vulnerabilidad o en desocupación por circunstancias que impiden que ni estudien ni trabajen, impulsando su reinserción a la sociedad;\nLey de la Juventud del Estado de Baja California. Página 19\nXV.- Promover alternativas de turismo juvenil para la recreación, el uso del tiempo libre y un medio de identidad para los jóvenes;\nXVI.- Establecer mecanismos para fomentar la participación organizada, autónoma, democrática y comprometida de los jóvenes en el proceso de desarrollo estatal;\nXVII.- Impulsar el gusto de los jóvenes por la conservación, vigilancia y uso responsable de los recursos naturales y la protección del medio ambiente;\nXVIII.- Recopilar y sistematizar información estadística que permita conocer y comprender la problemática que viven los jóvenes en el Estado;\nXIX.- Acciones que apoyen en el fortalecimiento de las organizaciones juveniles autónomas, para que los jóvenes del Estado tengan oportunidades y posibilidades para construirse una vida digna;\nXX.- Actividades de estímulo y reconocimiento a jóvenes del Estado que hayan destacado en diversos ámbitos de la comunidad;\nXXI.- Estrategias que contemplen mecanismos para el estudio, sistematización, la promoción y el fortalecimiento de las vocaciones juveniles;\nXXII.- En general, toda política y criterios que el Gobierno del Estado observara en sus programas de la juventud establecidos a nivel nacional, y\nXXIII.- Establecer la coordinación con las dependencias y las entidades de la\nAdministración Pública Estatal y Municipal, para el impulso de programas y cursos de orientación e información sobre nutrición, derechos humanos, cultura de la no violencia y no discriminación, medio ambiente, prevención del suicidio, derechos y responsabilidad legal de los jóvenes y participación social comunitaria;\nFracción Adicionada\nXXIV.- Acciones de acompañamiento y Vinculación Comunitaria para jóvenes que viven en comunidades vulnerables o de alta incidencia de violencia, adicciones o desintegración familiar.\nFracción Adicionada\nXXV.- Establecer de uso de tecnologías y plataformas digitales para la difusión de\nProgramas en beneficio de los jóvenes.\nFracción Adicionada\nXXVI.- Las demás que sean necesarias para el desarrollo integral de los jóvenes.\nFracción Recorrida\nArtículo Reformado\nLey de la Juventud del Estado de Baja California. Página 20\nARTÍCULO 63.- El Programa será formulado, instrumentado y evaluado de conformidad con los términos, plazos y vigencia que dispone la Ley de Planeación para el\nEstado de Baja California.\nEl instituto a través de la persona que ocupe la Dirección, será a autoridad responsable de elaborar el Programa, en coordinación con la Junta, de conformidad con los términos, plazos y vigencia que dispone la Ley de Planeación para el Estado de Baja\nCalifornia, con la más amplia participación de las autoridades en materia de atención a la juventud, y de las propuestas u opiniones emitidas por los jóvenes.\nPárrafo Reformado\nEn la elaboración del Programa se deberá garantizar la colaboración de especialistas, instituciones académicas, organizaciones no gubernamentales, asociaciones juveniles, instituciones de asistencia social, representantes populares, así como de los demás sectores sociales que estudian y analizan los problemas de la juventud.\nArtículo Reformado\nCAPÍTULO CUARTO\nDE LA RED DE INTERCAMBIO DE INFORMACIÓN JUVENIL\nARTÍCULO 64.- La Plataforma Digital, es un sistema virtual de recopilación y sistematización de información relativa a los jóvenes, así como de acceso a programas de apoyo para jóvenes.\nArtículo Reformado\nARTÍCULO 65.- La Plataforma Digital, deberá contener como mínimo la siguiente información:\nPárrafo Reformado\nI.- Un padrón de las organizaciones y agrupaciones juveniles del Estado;\nII.- El directorio actualizado de dependencias y entidades de los tres órdenes de gobierno en materia de juventud, así como de organizaciones de los sectores social, académico y privado que realicen actividades en favor de jóvenes del Estado;\nIII.- Un catálogo de programas, servicios, opciones de financiamiento, ofertas de empleo y beneficios que ofrecen el sector público y privado hacia los jóvenes del Estado;\nIV.- Los estudios e investigaciones realizadas, así como la información estadística generada en materia de juventud por los sectores social, público y privado;\nV.- La difusión de información sobre los principales problemas de la juventud, y los obstáculos que generan alteraciones del desarrollo;\nVI.- Los resultados de los intercambios de experiencias con otros Estados y Naciones, sobre temas de interés para la juventud;\nLey de la Juventud del Estado de Baja California. Página 21\nVII.- Los informes, quejas, denuncias y opiniones que formulen los jóvenes en materia de juventud;\nVIII.- La difusión permanente de los derechos de los jóvenes en el Estado, y\nIX.- Accesos directos a instituciones y dependencias que brinden programas y servicios a jóvenes en el Estado;\nFracción Adicionada\nX.- Formatos de acceso y requisitos necesarios para el acceso de programas de apoyo a jóvenes;\nFracción Adicionada\nXI.- Asistencia y orientación en Línea digital para atención de situaciones de crisis para los jóvenes;\nFracción Adicionada\nXII.- Cualquier otra información que se considere trascendente para la vida de los jóvenes\nFracción Recorrida\nToda la información que se concentre en la Plataforma Digital, deberá actualizarse en forma permanente y publicarse en el portal electrónico oficial del Instituto, así como a través de los medios y estrategias que permitan las tecnologías de la información y comunicación disponibles.\nPárrafo Reformado\nLos Municipios, en el ámbito de su competencia, coadyuvarán a la integración y actualización de la Red.\nArtículo Reformado\nARTÍCULO 65 BIS.-Para el cumplimiento de los fines de la Red, así como el fortalecimiento de la Política y del Programa Estatal de Atención a la Juventud, el Instituto, Ayuntamientos, organizarán y desarrollarán los trabajos de la Audiencia Pública Juvenil, la cual será convocada, de manera enunciativa mas no limitativa, por lo menos una vez al año. inclusión, consulta y participación de los jóvenes como parte de las prácticas de Gobierno\nAbierto. El Estado y los Municipios procurarán la participación más amplia posible de los jóvenes de la entidad en los trabajos de las audiencias públicas juveniles. juveniles serán considerados para:\nLey de la Juventud del Estado de Baja California. Página 22\nI. El cumplimiento a la participación de los jóvenes en el diseño, planeación, programación, ejecución, seguimiento y evaluación de las políticas, planes, programas y acciones dirigidas a la juventud que estipula la fracción III del artículo 55 de la presente ley;\nII. La elaboración del informe que se integra al Sistema Estatal respecto a la situación que guarda el tema de la juventud en el Estado, previsto en el artículo 60 de la presente Ley;\nIII. La recepción de las propuestas y opiniones de los jóvenes establecidas por el artículo 63 de la presente Ley para la elaboración del Programa Estatal; y\nIV. La integración de la información con la cual debe contar la Red prevista en el artículo anterior.\nArtículo Adicionado\nCAPÍTULO QUINTO\nDEL CONSEJO ESTATAL DE ATENCIÓN A LA JUVENTUD\nARTÍCULO 66.- El Consejo es un órgano colegiado de deliberación, de consulta, asesoría y participación social, con carácter interinstitucional, coadyuvante en el diseño, planeación, programación, instrumentación, seguimiento y evaluación de la Política Estatal de Atención a la Juventud.\nARTÍCULO 67.- El Consejo tiene las siguientes funciones:\nI.- Emitir recomendaciones, sugerencias y propuestas hacia el Instituto para la elaboración y ejecución del Programa, así como para la realización de investigaciones, estudios y diagnósticos en materia de juventud;\nII.- Servir como órgano de análisis y consulta en la planeación y elaboración de políticas y acciones relacionadas con el desarrollo integral de la juventud;\nIII.- Realizar recomendaciones, sugerencias y propuestas legislativas al Congreso del\nEstado para modificar la legislación estatal en beneficio de la juventud;\nIV.- Promover la coordinación de los sectores social, público y privado, a efecto de apoyar los planes y programas implementados para la atención de los jóvenes;\nV.- Recomendar la celebración de acuerdos y convenios en materia de juventud entre las dependencias y entidades de la administración pública estatal, con las del Ejecutivo\nFederal, de otras entidades federativas y de los ayuntamientos, así como con las organizaciones del sector social y privado;\nLey de la Juventud del Estado de Baja California. Página 23\nVI.- Fungir como órgano de vinculación entre las personas jóvenes, las organizaciones del sector social y el Instituto, recabando sugerencias y propuestas para la elaboración de programas de desarrollo juvenil;\nVII.- Dar seguimiento a las acciones de los programas que se ejecuten a través del\nEstado y los Municipios en materia de juventud, y\nVIII.- Las demás que resulten necesarias para el cumplimiento de su objeto.\nARTÍCULO 68.- El Consejo se integrará de la siguiente forma:\nI.- Un Presidente, que será quien ocupe la Dirección del Instituto;\nFracción Reformada\nII.- Una o un Secretario técnico designado por la Dirección del Instituto;\nFracción Reformada\nIII.- Quien presida la Comisión del Poder Legislativo del Estado que conozca de los temas de juventud;\nFracción Reformada\nIV.- Una representación de la Secretaría General de Gobierno;\nFracción Reformada\nV.- Una representación de las siguientes Secretarías:\na) Secretaría del Trabajo y Previsión Social;\nb) Secretaría de Integración y Bienestar Social;\nc) Secretaría de Salud;\nd) Secretaría de Educación;\ne) Secretaría de Economía Sustentable y Turismo;\nf) Secretaría de Hacienda; y,\ng) Secretaría de Cultura.\nFracción Reformada, adicionando sus incisos\nVI.- Una representación del Instituto del Deporte y la Cultura Física;\nFracción Reformada\nVII.- Una representación de cada uno de Municipios;\nFracción Reformada\nLey de la Juventud del Estado de Baja California. Página 24\nVIII.- Tres representantes de instituciones académicas de los niveles medio superior y superior de los sectores público y privado que deseen participar;\nFracción Ascendida\nIX.- Cinco representantes de organizaciones juveniles del Estado;\nFracción Ascendida\nX.- Una representación del sector económico y productivo que tenga participación activa en el desarrollo de políticas y programas para jóvenes;\nFracción Reformada\nXI.- Tres representantes de organismos de la sociedad civil organizada que realicen actividades de respaldo, impulso, apoyo o fortalecimiento a la juventud; y,\nFracción Reformada\nXII.- Dos jóvenes que se hayan destacados en cualquiera de los ámbitos artístico, educativo, cultural, deportivo, social, profesional o ambiental.\nFracción Reformada\nA las sesiones del Consejo podrán asistir como invitados con derecho a voz, otras instancias de gobierno, organismos privados y estudiantes, así como especialistas e investigadores en materia d juventud que por sus conocimientos y aportaciones puedan contribuir al cumplimiento de sus funciones, previa convocatoria por la Dirección.\nPárrafo Reformado\nArtículo Reformado\nARTÍCULO 69.- El Consejo sesionará cuando menos dos veces al año de manera ordinaria y de manera extraordinaria las veces que sean necesarias, y para que sesione válidamente se requiere la presencia de la mitad más uno de los integrantes.\nLos acuerdos del Consejo se tomarán por mayoría de los representantes en caso de empate, la presidencia ejercerá su voto de calidad, de cada sesión del Consejo se levantará el acta correspondiente.\nPárrafo Reformado\nArtículo Reformado\nARTÍCULO 70.- Para la elección de los consejeros previstos en las fracciones VIII, IX, X, XI y XII del artículo 68 de la presente Ley, el Instituto emitirá una convocatoria pública que establezca las bases, lineamientos y requisitos que regirán dicha elección, atendiendo a criterios de representatividad y desempeño.\nPárrafo Reformado removidos por faltar sin causa justificada a tres sesiones continuas.\nPárrafo Reformado\nEl cargo de Consejero será honorífico, por lo que no se percibirá remuneración alguna por su desempeño.\nLey de la Juventud del Estado de Baja California. Página 25\nArtículo Reformado\nARTÍCULO 71.- El Director coordinará los trabajos del Consejo y proporcionará todos los elementos técnicos, administrativos humanos y financieros para buen funcionamiento.\nReglamento.\nTÍTULO CUARTO\nCONCURRENCIA DE LAS AUTORIDADES DEL ESTADO Y\nMUNICIPIOS Y SUS ATRIBUCIONES EN MATERIA DE\nATENCIÓN A LA JUVENTUD\nCAPÍTULO PRIMERO\nDE LAS AUTORIDADES EN MATERIA DE ATENCIÓN A LA\nJUVENTUD\nARTÍCULO 72.- Son autoridades en materia de atención a la juventud:\nI. La persona que ocupe el cargo de Gobernador del Estado, como representante del\nPoder Ejecutivo;\nFracción Reformada\nII.- Secretaría General de Gobierno;\nIII. Secretaría de Integración y Bienestar Social;\nFracción Reformada\nIV. Secretaría de Salud;\nV. Secretaría del Trabajo y Previsión Social;\nVI. El Instituto del Deporte y la Cultura Física para el Estado de Baja California;\nVII. El Instituto, y\nVIII. Los Municipios.\nArtículo Reformado\nCAPÍTULO SEGUNDO\nJUVENTUD sus dependencias y entidades:\nPárrafo Reformado\nLey de la Juventud del Estado de Baja California. Página 26\nI.- Conducir la Política Estatal de Atención a la Juventud en congruencia con la\nPolítica Nacional en la materia;\nII.- Garantizar el pleno ejercicio de los derechos que esta Ley reconoce a favor de los jóvenes;\nIII.- Publicar el Programa en el Periódico Oficial del Estado;\nIV.- Designar libremente al Director;\nV.- Gestionar y promover ante organismos públicos, privados, estatales, nacionales e internacionales, financiamiento para proyectos juveniles;\nVI.- Impulsar estrategias, acciones y proyectos para prevenir, combatir y erradicar las alteraciones del desarrollo en los jóvenes;\nVII.- Celebrar convenios con: la Federación, entidades federativas, municipios y organizaciones sociales o privadas, nacionales o internacionales, para concretar acciones que tengan por objeto la promoción, difusión, fomento, investigación, ejecución y evaluación de proyectos en beneficio de los jóvenes;\nVIII.- Apoyar el fortalecimiento de las organizaciones juveniles constituidas legalmente en cualquier nivel de Gobierno;\nIX.- Apoyo a las organizaciones juveniles o de cualquier índole, para la participación y aprobación de proyectos en áreas de interés para los jóvenes;\nX.- Garantizar, a través de la creación de proyectos específicos, el acceso a programas de vivienda, empleo, educación y créditos, con especial énfasis en estrategias dirigidas a jóvenes en desocupación por circunstancias que impiden que ni estudien ni trabajen y que obstaculizan su inserción a la sociedad;\nXI.- Actuar en colaboración con el Consejo Nacional para Prevenir la Discriminación injustificado;\nXII.- Proponer en el Proyecto de Presupuesto de Egresos del Estado una partida esta Ley;\nXIII.- Apoyar las iniciativas de las y los jóvenes y canalizarlas a las instancias adecuadas;\nFracción Reformada\nLey de la Juventud del Estado de Baja California. Página 27\nXIV.- Crear mecanismos para que las y los jóvenes reciban a través de las personas servidoras públicas capacitadas, la atención, orientación e información respecto de sus derechos en todas las instituciones públicas del Estado; y,\nFracción Adicionada, recorriéndose la subsecuente\nXV.- Realizar las gestiones necesarias para el cumplimiento de esta Ley.\nArtículo Reformado\nARTÍCULO 74.- Corresponde a la Secretaría General de Gobierno:\nI.- Fomentar la coordinación entre los órdenes de gobierno en materia de juventud;\nII.- Fortalecer el marco normativo del Estado en materia de juventud, y\nIII.- Las demás que le establezca esta Ley u otras normatividades.\nARTÍCULO 75.- Corresponde a la Secretaría de Integración y Bienestar Social:\nPárrafo Reformado\nI.- Contar con programas para la atención integral de los jóvenes en situación de vulnerabilidad que les permita integrarse a la sociedad y tener oportunidades que les permitan acceder a servicios y beneficios sociales que mejoren su calidad de vida;\nII.- Otorgar subsidios dependiendo de la capacidad presupuestaria, siempre que sean los jóvenes quienes realicen dicha actividad en forma directa, y se observe la sustentabilidad del proyecto;\nIII.- Promover en coordinación con el Instituto, políticas sociales dirigidas a jóvenes en desocupación por circunstancias que impiden que ni estudien ni trabajen y que obstaculizan su inserción a la sociedad; y\nIV.- Las demás que le confieren esta Ley u otros ordenamientos aplicables.\nArtículo Reformado\nARTÍCULO 76.- Corresponde a la Secretaría de Salud:\nI.- Establecer módulos de información y orientación dirigido a los jóvenes, en los que se den a conocer temáticas relacionadas con la salud mental, sexual y reproductiva, métodos seguros, eficaces y económicos de planificación familiar;\nII.- Prestar atención integral que promueva la recuperación física y psicológica a las jóvenes víctimas de violencia familiar, escolar, sexual, por condición de género, o cuando sean víctimas de cualquier tipo de discriminación;\nFracción Reformada\nIII.- Dar cuenta en forma inmediata a las autoridades competentes, cuando en el ejercicio de sus funciones se percate de un caso de violencia;\nLey de la Juventud del Estado de Baja California. Página 28\nIV.- Realizar campañas permanentes para la prevención del uso de drogas y adoptar estilos de vida saludables y libres del consumo de dichas sustancias;\nV.- Trabajar junto con el Instituto del Deporte y la Cultura Física estableciendo módulos de información y orientación dirigida a los jóvenes, en los que se den a conocer temáticas relacionadas con los problemas de salud física tales como el sobrepeso u obesidad, realizando convenios con centros deportivos, universidades y gimnasios del\nEstado, para que las y los jóvenes puedan asistir a ejercitarse y practicar cualquier deporte gratuitamente, solamente presentando credencial expedida por la Secretaría de Salud y el\nInstituto, donde haga mención de dicho convenio, y\nVI.- Las demás que le confieren esta Ley u otros ordenamientos aplicables.\nArtículo Reformado\nARTÍCULO 77.- Corresponde a la Secretaría de Educación:\nPárrafo Reformado\nI.- Establecer programas de capacitación con el objeto de fomentar el sentido de responsabilidad social entre los jóvenes, con miras a fortalecer su compromiso con la sociedad y el cumplimiento de sus obligaciones cívicas;\nII.- Elaborar un programa de actividades para el desarrollo de la Educación física y el deporte en las escuelas;\nIII.- Crear y apoyar todas las actividades juveniles con igualdad de género que fomenten la cultura de la paz, estimulen la creatividad, el espíritu emprendedor, la formación de valores como la tolerancia, la amistad, la solidaridad y la no discriminación.\nFracción Reformada\nIV.- Prestar servicios de orientación vocacional, conforme lo requiera el nivel de educación a cursar;\nV.- Promover la educación extraescolar y complementaria en los jóvenes, que les permita desarrollar habilidades y aptitudes;\nVI.- Garantizar el acceso de los jóvenes a la educación básica de calidad en las zonas marginadas;\nVII.- Ampliar el acceso de los jóvenes en igualdad de condiciones a la educación media superior y superior, a fin de mejorar la calidad de esta;\nLey de la Juventud del Estado de Baja California. Página 29\nVIII.- Fomentar la Protección al ambiente, incluyendo a los jóvenes en la realización de actividades dirigidas al cuidado y preservación de este;\nIX.- Garantizar que los sistemas de educación y formación estén en congruencia con la realidad económica, social y empresarial, sobre la base de las necesidades individualizadas y los avances tecnológicos;\nX.- Promover, en coordinación con el Instituto, políticas educativas dirigidas a jóvenes en desocupación por circunstancias que impiden que ni estudien ni trabajen y que obstaculizan su inserción a la sociedad; y\nXI.- Las demás que le confieren esta Ley u otros ordenamientos aplicables.\nArtículo Reformado\nARTÍCULO 78.- Corresponde a la Secretaría del Trabajo y Previsión Social:\nI.- Establecer programas de formación y capacitación para el trabajo dirigidos a los jóvenes;\nII.- Establecer las bases del Primer Empleo de la juventud del Estado;\nIII.- Crear programas de capacitación técnica que garanticen a los jóvenes mayores oportunidades de acceso al ámbito laboral y a su crecimiento personal;\nIV.- Otorgar incentivos para las empresas que contraten jóvenes;\nV.- Promover, en coordinación con el Instituto, políticas laborales dirigidas a jóvenes en desocupación por circunstancias que impiden que ni estudien ni trabajen y que obstaculizan su inserción a la sociedad; y\nVI.- Las demás que le confieren esta Ley u otros ordenamientos aplicables.\nArtículo Reformado\nARTÍCULO 79.- Corresponde a la Secretaría de Economía Sustentable y Turismo, incluir en sus diferentes programas la participación activa de la juventud en el cuidado, preservación y fomento del medio ambiente.\nArtículo Reformado\nARTÍCULO 80.- Corresponde al Instituto del Deporte y la Cultura Física:\nI.- Desarrollar la infraestructura necesaria y de calidad para posibilitar la práctica de los diferentes deportes a todos los jóvenes, desde su etapa adolescente;\nFracción Reformada\nII.- Garantizar a los jóvenes talentos deportivos, los medios económicos y humanos que les permita desarrollar sus habilidades;\nLey de la Juventud del Estado de Baja California. Página 30\nIII.- Establecer y desarrollar actividades deportivas y recreativas para la juventud, con el objeto de promover y fortalecer el intercambio deportivo en los planos estatal, nacional e internacional;\nFracción Reformada\nIV.- Colaborar junto con la Secretaría de Salud estableciendo módulos de información y orientación dirigida a los jóvenes, en los que se den a conocer temáticas relacionadas con los problemas de salud física tales como el sobrepeso u obesidad;\nV.- Realizar convenios con centros deportivos, universidades y gimnasios del Estado, para que los jóvenes puedan asistir a ejercitarse y practicar deporte de manera gratuita o preferencial, y\nVI.- Las demás que le confieren esta Ley u otros ordenamientos aplicables.\nArtículo Reformado\nARTÍCULO 81.- Corresponde a los Ayuntamientos en el ámbito de su jurisdicción, lo siguiente:\nI.- Colaborar en la elaboración del Programa y establecer un rubro propio en su Plan\nMunicipal de Desarrollo;\nII.- Conducir y diseñar la política municipal de atención a la Juventud en congruencia con la política federal y estatal en la materia;\nIII.- Garantizar en el ámbito de su competencia, el pleno ejercicio de los derechos que esta ley reconoce a favor de los jóvenes;\nIV.- Formular un Programa Municipal de atención a la juventud, así como las demás estrategias y acciones que consideren necesarias para el Desarrollo Integral de los jóvenes en el ámbito de su competencia, tomando en cuenta las necesidades de cada Municipio;\nV.- Contar con un Instituto, Dirección o Dependencia Municipal encargada de vigilar y cumplir con la atención de la juventud; la o el titular de dicha instancia no deberá tener más de 29 años cumplidos el día de su designación y deberá contar con experiencia en temas relacionados con la juventud;\nFracción Reformada\nVI.- Promover la participación de la juventud en el quehacer de la administración pública;\nVII.- Diseñar en el ámbito de su competencia y jurisdicción, acciones que permitan dar cumplimiento a programas nacionales y estatales;\nLey de la Juventud del Estado de Baja California. Página 31\nVIII.- Fomentar la construcción de espacios públicos y preservarlos, para aplicar programas de esparcimiento, tomando en cuenta las medidas de seguridad debidas conforme a sus posibilidades y los planes de desarrollo urbano;\nIX.- Emitir los reglamentos y disposiciones administrativas de observancia general, para regular lo relativo a la juventud, según lo señalado por esta Ley;\nX.- Impulsar estrategias, investigaciones y proyectos para prevenir, combatir y erradicar las alteraciones del desarrollo en los jóvenes;\nXI.- Promover ante organismos públicos, privados, estatales, nacionales e internacionales, financiamiento para proyectos juveniles;\nXII.- Fomentar y estimular el desarrollo y fortalecimiento de organización de la sociedad civil que trabajen en beneficio de la juventud;\nXIII.- Celebrar acuerdos o convenios de coordinación con la Federación, el Estado, ayuntamientos, organismos sociales o privados, para el mejor cumplimiento de esta ley;\nXIV.- Promover, en coordinación con el Instituto, políticas municipales dirigidas a jóvenes en desocupación por circunstancias que impiden que ni estudien ni trabajen y que obstaculizan su inserción a la sociedad; y\nXV.- Las demás que le confieren esta Ley u otros ordenamientos aplicables.\nArtículo Reformado\nTÍTULO QUINTO\nDEL INSTITUTO DE LA JUVENTUD DEL ESTADO DE BAJA CALIFORNIA\nCAPÍTULO PRIMERO\nDE LA NATURALEZA Y OBJETO DEL INSTITUTO\nARTÍCULO 82.- El Instituto de la Juventud del Estado de Baja California, es un organismo público descentralizado, con personalidad jurídica y patrimonio propio cuyo propósito es asesorar y auxiliar al Ejecutivo del Estado en la fijación, instrumentación, ejecución y evaluación de la Política Estatal de Atención la Juventud en la entidad.\nEl Instituto tendrá su domicilio en la ciudad de Mexicali, y contará para la eficiente atención de sus asuntos con las unidades administrativas necesarias, a través de las cuales operará los programas y prioridades que señalan en esta Ley.\nCAPÍTULO SEGUNDO\nDE LAS ATRIBUCIONES DEL INSTITUTO\nLey de la Juventud del Estado de Baja California. Página 32\nARTÍCULO 83.- El Instituto para el cumplimiento de su objeto tendrá las siguientes atribuciones:\nI.- Concertar acuerdos y convenios de colaboración y coordinación con el Instituto\nMexicano de la Juventud, así como las autoridades de todos los niveles de gobierno, para promover con la participación en su caso de los sectores social y privado, las políticas, acciones y programas tendientes al desarrollo integral de la juventud;\nII.- Formular, diseñar, promover y ejecutar la política, planes y programas estatales de atención a la juventud, en congruencia con la política nacional y el Plan Estatal de\nDesarrollo, permitiendo incorporar plenamente a la juventud en el desarrollo del Estado; adecuándola a las características y necesidades de la región y de la entidad.\nFracción Reformada\nIII.- Asesorar al Gobernador en la planeación, programación e instrumentación de las políticas y acciones relacionadas con el desarrollo integral de la juventud;\nIV.- Actuar como órgano de consulta y asesoría de las dependencias y entidades de la Administración Pública Estatal en la materia, así como de las autoridades federales, municipales y de los sectores social y privado cuando así lo requieran;\nV.- Promover, coordinadamente con las dependencias y entidades de la\nAdministración Pública Estatal, las acciones destinadas a mejorar el nivel de vida de la\nJuventud, así como sus expectativas sociales, culturales, laborales y de recreación;\nVI.- Fungir como representante del Ejecutivo del Estado en materia de la juventud, ante los órdenes de Gobierno Federal y Municipal, organizaciones privadas, sociales y organismos internacionales; así como en foros, convenciones, encuentros y demás reuniones en las que el Gobernador solicite su participación;\nVII.- Difundir y promover el respeto y cumplimiento de los derechos y deberes de la juventud, así como la promoción de los servicios, programas y logros para su atención;\nFracción Reformada\nVIII.- Crear un padrón de organizaciones juveniles y estudiantiles que promuevan la participación de la juventud en los distintos ámbitos de la sociedad;\nFracción Reformada\nIX.- Realizar, promover y difundir estudios, diagnósticos e investigaciones sobre la problemática y características juveniles, tendientes a construir políticas encaminadas al integral de la juventud;\nFracción Reformada\nX.- Fomentar y estimular el desarrollo y fortalecimiento de organizaciones de la sociedad civil que trabajen en beneficio de la juventud;\nLey de la Juventud del Estado de Baja California. Página 33\nXI.- Fomentar el establecimiento de vínculos de amistad y de cooperación nacional e internacional en materia de juventud;\nXII.- Impulsar ante las autoridades educativas, el ingreso de las y los jóvenes a la educación básica, media superior y superior, alentando y estimulando su permanencia a través de la gestión de becas, créditos y apoyos que les permitan dar continuidad a su formación educativa;\nFracción Reformada\nEn la gestión de becas y apoyos se observarán los criterios que aseguren la transparencia, la ayuda preferente a grupos vulnerables, así como la no discrecionalidad.\nPárrafo Reformado\nXIII.- Organizar la entrega del Premio bajo las clasificaciones y modalidades establecidas en esta ley y el Reglamento, así como promover el reconocimiento público y estimulo de actividades sobresalientes de jóvenes en distintos ámbitos del acontecer municipal, estatal, nacional e internacional;\nXIV.- Realizar las gestiones necesarias con organismos públicos y privados para la operación efectiva del Carnet, así como la obtención de beneficios económicos para los jóvenes;\nXV.- Promover en coordinación con las autoridades laborales, el autoempleo, bolsas de trabajo, capacitación para el empleo juvenil, el primer empleo, como alternativas de acceso a la actividad profesional y laboral;\nXVI.- Apoyar el desarrollo de actividades culturales, artísticas, recreativas y de expresión creativa para la juventud;\nFracción Reformada\nXVII.- Prestar servicios de orientación y asesoría jurídica para las y los jóvenes, orientados a la defensa de sus intereses;\nFracción Reformada\nXVIII.- Fomentar la atención de los problemas de salud de la juventud, principalmente mediante preventivas de orientación y asesoramiento en el campo de la sexualidad, planificación familiar, adicciones y salud mental;\nFracción Reformada\nXIX.- Desarrollar programas específicos para asegurar que las y los jóvenes que cuenten con alguna discapacidad o pertenezcan a algún sector vulnerable, tengan pleno acceso a los derechos contemplados en esta Ley;\nFracción Reformada\nLey de la Juventud del Estado de Baja California. Página 34\nXX.- Promover el uso óptimo del tiempo libre de la juventud, ampliando sus espacios de encuentro y reconocimiento entre los distintos sectores sociales a los que pertenezca, para fortalecer la convivencia y el intercambio cultural;\nFracción Reformada\nXXI.- Recibir y canalizar propuestas y sugerencias e inquietudes de la juventud a los organismos públicos, privados y sociales que correspondan;\nXXII.- Impulsar ante las autoridades educativas, el ingreso de las y los jóvenes a la educación básica, media superior y superior, alentando y estimulando su permanencia a través de la gestión de becas y apoyos que les permitan dar continuidad a su formación educativa;\nFracción Reformada\nXXIII.- Fomentar y difundir entre los jóvenes el acceso a nuevas tecnologías de información y comunicación;\nXXIV.- Coadyuvar con cada Instituto, Dirección o Dependencia municipal en las actividades relacionadas con el desarrollo integral de la juventud;\nXXV.- Planear y coordinar cursos de actualización y capacitación para los servidores públicos encargados de la aplicación de los programas de atención a la juventud;\nXXVI.- Implementar campañas juveniles de prevención de delitos, corrección disciplinaria, problemas de adicciones, alcoholismo y tabaquismo, entre otras alteraciones del desarrollo, y en su caso, canalizar ante las instancias adecuadas a los jóvenes afectados para su rehabilitación;\nXXVII.- Constituirse en una instancia de diálogo y cauce de participación juvenil, así como de consulta, propuesta, evaluación y asesoramiento;\nXXVIII.- Elaborar el Programa;\nXXIX.- Formular y ejecutar planes y programas de atención a la juventud que se lleven a cabo en el Estado;\nXXX.- Prestar los servicios que se establezcan en los programas que formulen el\nInstituto, a través de las siguientes acciones y servicios;\nXXXI.- Planear, colaborar, apoyar o favorecer el desarrollo de actividades artísticas, culturales y la expresión creativa de los jóvenes;\nXXXII.- Favorecer la capacitación de los jóvenes en sus empleos e incentivar una actitud empresarial, así como vincular a jóvenes con fuentes de empleo;\nLey de la Juventud del Estado de Baja California. Página 35\nXXXIII.- Desarrollar programas para la adecuada orientación vocacional y profesional, el cabal aprovechamiento del servicio social y la diversificación de los servicios educativos;\nXXXIV.- Promover la salud mental de las juventudes incluyendo programas de atención y asesoría psicológica profesional, por medios electrónicos o digitales, así como a través de una línea telefónica de orientación psicológica.\nFracción Reformada\nXXXV.- Impulsar la participación del sector privado y social, para apoyar, encauzar, motivar y promover a los jóvenes en actividades de educación académica, capacitación laboral, rehabilitación de adicciones, educación sexual, desenvolvimiento de sus aptitudes en las artes, la ciencia y el deporte, y\nXXXVI.- Promover, coordinadamente con las dependencias y entidades de la\nAdministración Pública Estatal y Municipal, las políticas públicas dirigidas a jóvenes en desocupación por circunstancias que impiden que ni estudien ni trabajen y que obstaculizan su inserción a la sociedad, así como realizar la compilación de información, diagnósticos y estadísticas vinculadas a esta problemática; y\nXXXVII.- Las demás que le otorgue la presente Ley y el Reglamento Interno del\nInstituto.\nArtículo Reformado\nCAPÍTULO TERCERO\nESTRUCTURA ORGÁNICA DEL INSTITUTO\nARTÍCULO 84.- El Instituto de la Juventud de Baja California, contará con los siguientes órganos de administración:\nI.- Junta Directiva;\nII.- Dirección;\nIII.- El Titular del Órgano Interno de Control;\nFracción Reformada\nIV.- Delegaciones, y\nV.- Las estructuras administrativas que se establezcan en el Reglamento Interno del\nInstituto.\nArtículo Reformado\nARTÍCULO 85.- La Junta Directiva será la autoridad administrativa superior del\nInstituto, y quedará integrada por una presidencia, que será quien tenga a su cargo la\nSecretaria Coordinadora del Sector y siete vocales titulares de las siguientes dependencias:\nPárrafo Reformado\nLey de la Juventud del Estado de Baja California. Página 36\nI.- Secretaria de Hacienda;\nFracción Reformada\nII.- Secretaría de Educación;\nFracción Reformada\nIII.- Secretaría del Trabajo y Previsión Social;\nIV.- Secretaría de Salud;\nV.- Fiscalía General;\nFracción Reformada\nVI.- Sistema Estatal para el Desarrollo Integral de la Familia, y\nVII.- Instituto del Deporte y la Cultura Física de Baja California;\nPor cada integrante de la Junta Directiva, el titular podrá nombrar a un suplente.\nA la Junta se incorporaran cinco miembros más, y serán los representantes de cada\nMunicipio del Estado, designados por los titulares de los Ayuntamientos correspondientes.\nLos miembros integrantes de la Junta Directiva, tendrán derecho a voz y a voto.\nQuien ocupe la Dirección estará a cargo de la Secretaría Técnica de la Junta Directiva con voz, pero sin derecho a voto.\nPárrafo Reformado\nEn representación de la Secretaría de la Honestidad y la Función Pública, participare el o la Titular del Órgano de Control, quien tendrá derecho a voz, pero no a voto.\nPárrafo Reformado\nA la Junta Directiva podrá participar con invitación permanente, una o un integrante del Parlamento Juvenil, quien tendrá derecho a voz, pero no a voto.\nPárrafo Adicionado y Reformado\nArtículo Reformado\nARTÍCULO 86.- En cada sesión se levantará acta, la cual, previa aprobación de la misma en la sesión siguiente, será firmada por quien la haya presidido y por la Secretaría\nTécnica, así como por aquellos que hayan participado y así quieran hacerlo.\nArtículo Reformado\nARTÍCULO 87.- La Junta Directiva tendrá las siguientes atribuciones:\nI.- Otorgar a favor del Director, la representación legal del Instituto con todas las facultades que correspondan al mandato general para pleitos y cobranzas, así como las de Baja California;\nLey de la Juventud del Estado de Baja California. Página 37\nII.- Aprobar y evaluar el programa anual de trabajo y el programa institucional del organismo;\nIII.- Establecer la congruencia con los programas sectoriales, las políticas generales y su objeto y administración general;\nIV.- Conocer y aprobar en su caso los informes que rinda la Dirección;\nFracción Reformada\nV.- Aprobar los presupuestos de ingresos y egresos del Instituto, así como sus modificaciones;\nVI.- Analizar y aprobar, en su caso, los estados financieros y el informe anual de actividades que deberá presentar la Dirección;\nFracción Reformada\nVII.- Aprobar los proyectos de inversión que le sean presentados por la Dirección;\nFracción Reformada\nVIII.- Aprobar la estructura organización del Instituto;\nIX.- Expedir el Reglamento Interno del Instituto y aprobar la organización administrativa del Instituto;\nX.- Promover las donaciones, legados y demás liberalidades que se otorguen a favor del Instituto;\nXI.- En general, realizar todos los actos y operaciones que sean necesarios para cumplir con su objeto general en los términos de la presente Ley, y\nXII.- Las demás que se le atribuyan esta Ley, otros ordenamientos y el Reglamento\nInterno del Instituto.\nArtículo Reformado\nARTÍCULO 88.- La Junta Directiva sesionara de manera ordinaria cada tres meses y extraordinariamente cuando así lo requiera, previa convocatoria de la Presidencia o por dos de los integrantes de la Junta o de la Secretaria Técnica, cuando existan que por su importancia lo ameriten.\nPárrafo Reformado integrantes.\nLas resoluciones se tomarán por mayoría de las o los integrantes presentes, teniendo el presidente voto de calidad en caso de empate.\nPárrafo Reformado\nLey de la Juventud del Estado de Baja California. Página 38\nArtículo Reformado\nARTÍCULO 89.- Los cargos de la Junta Directiva son honoríficos y por su desempeño no se percibirá retribución, emolumento o compensación alguna.\nARTÍCULO 90.- En el Reglamento Interno se determinará los requisitos para emitir la convocatoria y los demás términos y condiciones relativas a las sesiones de la junta.\nARTÍCULO 91.- El Instituto estará a cargo de una o un Director, que se designara y removerá libremente por quien ocupe la Gubernatura del Estado, debiendo recaer tal nombramiento en persona que reúna los siguientes requisitos:\nPárrafo Reformado\nI.- Ser ciudadana o ciudadano mexicano en pleno ejercicio de sus derechos;\nFracción Reformada\nII.- No tener más de veintinueve años cumplidos al día de su designación;\nIII.- Tener residencia mínima de cinco años en el Estado;\nIV.- No ser titular de algún organismo descentralizado;\nV.- No tener litigio pendiente en contra o ser acreedor del Instituto;\nVI.- No encontrarse inhabilitado para ejercer el comercio o para desempeñar un empleo, cargo o comisión en el servicio público;\nVII.- No ser titular y servidor público del Poder Legislativo y Judicial del Estado de\nBaja California, y\nVIII.- Haber destacado por su labor a favor de la juventud, contar con carrera técnica o profesional a fin al cargo, y tener experiencia en actividades relacionadas con la atención a la problemática de la juventud.\nArtículo Reformado\nARTÍCULO 92.- La o el Director, será responsable de la administración y funcionamiento del Instituto y tendrá las siguientes facultades y obligaciones:\nPárrafo Reformado\nI.- Administrar y representar legalmente al Instituto;\nII.- Ejecutar, instrumentar y vigilar el cumplimiento de los acuerdos de la Junta\nDirectiva;\nLey de la Juventud del Estado de Baja California. Página 39\nIV.- Formular anualmente el anteproyecto de presupuesto del Instituto, para someterlo a la aprobación de la Junta Directiva;\nIV (sic).- Proponer a la Junta Directiva el nombramiento del personal que corresponda\nInstituto;\nVI.- Recabar información y elementos estadísticos sobre las funciones del Instituto, para mejorar su desempeño, y\nVII.- Las que le confieran las demás disposiciones jurídicas aplicables.\nArtículo Reformado\nARTÍCULO 93.- El Instituto contara con un Órgano Interno de Control, encargado de la vigilancia del Instituto. Este será designado y removido libremente por la o el titular de la\nSecretaría de la Honestidad y la Función Pública.\nArtículo Reformado\nARTÍCULO 94.- El La o el titular del Órgano Interno de Control, tendrá las siguientes atribuciones:\nPárrafo Reformado\nI.- Implementar los mecanismos internos que prevengan actos u omisiones que pudieran constituir responsabilidades administrativas, en los términos establecidos por el\nSistema Estatal Anticorrupción;\nFracción Reformada\nII.- Revisar el ingreso, egreso, manejo, custodia y aplicación de recursos públicos, según corresponda en el ámbito de su competencia;\nFracción Reformada\nIII.- Presentar denuncias por hechos que las leyes señalen como delitos ante la\nFiscalía Especializada en Combate a la Corrupción;\nFracción Reformada\nIV.- Solicitar la información y documentación y efectuar los actos que se requieran para el adecuado cumplimiento de sus funciones;\nV.- Asistir a las sesiones de la Junta Directiva solo con derecho a voz; y,\nFracción Reformada\nVI.- Las demás que le confieran esta Ley u otras disposiciones aplicables.\nArtículo Reformado\nCAPÍTULO CUARTO\nDEL PATRIMONIO DEL INSTITUTO\nLey de la Juventud del Estado de Baja California. Página 40\nARTÍCULO 95.- El patrimonio del Instituto se integrará por:\nI.- Los bienes y derechos que aporten los gobiernos federal, estatal o municipal;\nIII.- Los bienes muebles e inmuebles que adquiera con base a cualquier título legal;\nIV.- Las donaciones, legados, herencias que le sean otorgados por las instituciones o personas físicas o morales;\nV.- Los ingresos que obtenga por servicios que preste, los productos y rentas de sus bienes;\nVI.- Las concesiones, permisos y autorizaciones que se les otorguen conforme a los fines de esta Ley, y\nVII.- Los que adquiera por otros conceptos.\nCAPÍTULO QUINTO\nDE LA EXTINCIÓN O FUSIÓN\nARTÍCULO 96.- Cuando el Instituto deje de cumplir con el objeto para el que fue creado o su funcionamiento no resulte ya conveniente desde el punto de vista de la economía del Estado o del interés público, la Secretaria de Hacienda ateniendo la opinión de la dependencia\nCoordinadora del Sector a la cual se adscribe el mismo, propondrá al Ejecutivo Estatal la extinción o fusión de este organismo, de conformidad con la Ley de las Entidades\nParaestatales del Estado de Baja California.\nArtículo Reformado\nTÍTULO SEXTO\nDE LOS ESTÍMULOS Y RECONOCIMIENTOS\nCAPÍTULO PRIMERO\nDEL DÍA ESTATAL DE LA JUVENTUD\nARTÍCULO 97.- El 12 de agosto de cada año, se celebrará la conmemoración del Día\nInternacional de la Juventud, fecha en que el Instituto organizará la realización de eventos, foros, conferencias, concursos, entrega de premios y reconocimientos, así como las demás la sociedad de nuestro Estado.\nARTÍCULO 98.- El Instituto, celebrara durante el mes de agosto actos, conferencias, concursos, eventos, foros y ceremonias conmemorativas al Dia, promoviendo la\nLey de la Juventud del Estado de Baja California. Página 41 participación de las y los jóvenes en dichas actividades, de conformidad con la disponibilidad presupuestal.\nArtículo Reformado\nARTÍCULO 99.- El Instituto solicitará de las dependencias y entidades de los tres órdenes de Gobierno, la colaboración en los actos de conmemoración del Día, así como convenir con los Institutos Municipales y los sectores social, académico y privado, las actividades que habrán de celebrarse en cada Municipio.\nCAPÍTULO SEGUNDO\nDEL PREMIO ESTATAL DE LA JUVENTUD\nARTÍCULO 100.- Se instituye el Premio para reconocer la trayectoria de jóvenes con talento, capacidad e iniciativa en el área social, cívica, educativa, tecnológica, científica, cultural, deportiva, profesional, económica, ambiental, en el fortalecimiento a la Diversidad\nSexual y de Género, fortalecimiento y promoción a la cultura y las lenguas indígenas nativas y nacionales asentadas; fortalecimiento de la cultura afromexicana; defensa y reconocimiento de los derechos humanos, discapacidad e integración y, por haber realizado servicios y acciones relevantes en beneficio de la juventud.\nArtículo Reformado\nARTÍCULO 101.- La convocatoria para participar en los concursos y eventos con motivo de la entrega del Premio, será emitida por el Instituto y establecerá las bases, requisitos, procedimiento, modalidades y categorías para el otorgamiento, y se publicará en dos diarios de circulación estatal, en el periódico oficial del Estado, en el portal de internet del Instituto, y se difundirá en las instituciones educativas del Estado.\nLa cuantía, el tipo de premios, la composición del jurado de premiación, así como las bases para su funcionamiento se determinarán por la Dirección.\nPárrafo Reformado\nLa convocatoria por lo menos contemplará dos categorías por grupo etario, una para las y los jóvenes de 12 a 17 años y otra de 18 a 29 años.\nPárrafo Adicionado\nArtículo Reformado\nCAPÍTULO TERCERO\nDE LA TARJETA CARNET JOVEN\nARTÍCULO 102.- El Carnet es un instrumento de participación, apoyo y atención a la juventud de Baja California, para la obtención de descuentos y beneficios económicos en la adquisición de bienes y servicios públicos y privados.\nARTÍCULO 103.- La operación del Carnet será instrumentada por el Instituto, para lo la Federación y los Municipios, así como con los sectores empresarial y productivo de la\nLey de la Juventud del Estado de Baja California. Página 42 jóvenes.\nLo relativo al funcionamiento y operación del Carnet será regulado por el Reglamento.\nCAPÍTULO CUARTO\nDEL PARLAMENTO DE LA JUVENTUD\nARTÍCULO 104.- El Parlamento es un mecanismo de participación ciudadana y espacio de expresión política de las y los jóvenes promovido por el Congreso del Estado de\nBaja California, a través de la Comisión que para tales efectos determine con el objeto de promover la democracia, el diálogo y la pluralidad, así como la capacitación y vinculación con autoridades del Estado y los municipios, para fomentar que las y los jóvenes se conviertan en actores de cambio en sus comunidades.\nPárrafo Reformado\nEste espacio les permitirá manifestar plenamente sus pensamientos, ideas, opiniones y propuestas sobre los temas y problemas que consideren de mayor impacto en la sociedad y en la vida de la juventud Bajacaliforniana.\nArtículo Reformado\nARTÍCULO 104 BIS. - Para cumplir con la Paridad de manera plena el Comité deberá elegir a 13 mujeres con suplentes del mismo género y 12 hombres que pueden ser acompañados con suplentes de cualquier género.\nAsimismo, se procurará que el Parlamento se encuentre integrado con representación de todos los municipios del Estado.\nPárrafo Adicionado\nAdemás, se establecerán acciones afirmativas en favor de las y los jóvenes indígenas nativos y asentados, afromexicanos, de la diversidad sexual, con discapacidad, que hayan estado bajo la tutela del Estado y/o organización de asistencia social pública o privada, y migrantes nacionales y extranjeros residentes en el Estado.\nPárrafo Adicionado\nArtículo Adicionado\nArtículo Reformado\nARTÍCULO 105.- La Comisión, en coordinación y colaboración con el Instituto y el\nInstituto Estatal Electoral de Baja California, cada año convocará a la elección de la nueva integración del parlamento, emitiendo una convocatoria que deberá señalar los requisitos de selección y plazos para el concurso de las y los aspirantes.\nPárrafo Reformado siguientes:\nPárrafo con Fracciones Adicionado\nLey de la Juventud del Estado de Baja California. Página 43\nI. Etapa de Planificación, en la que la Comisión determinará la integración del Comité\nOrganizador y el Comité Seleccionador, y realizará una propuesta de convocatoria que someterá a aprobación del primero de los comités;\nII. Etapa de convocatoria y difusión, que iniciará al momento de su publicación en el mes de agosto y culminará con el cierre del registro;\nIII. Etapa de selección, consistirá en la evaluación de los proyectos, selección y publicación de resultados;\nIV. Etapa de capacitación, una vez que las y los parlamentarios seleccionados como titulares y suplentes hayan manifestado su deseo de conformar el parlamento, se dará inicio a una serie de capacitaciones en técnica legislativa, derecho parlamentario, democracia, derechos humanos, igualdad de género, debate, y todos aquellos temas que tengan como fin el promover la cultura democrática y legislativa, así como en dotarles de las herramientas para que se conviertan en factores de cambio social en sus comunidades;\nV. Etapa de ejecución, consistente en la suscripción del código interno de ética y conducta, la celebración de la sesión previa para la selección de la mesa directiva, sesión de toma de protesta y exposición de proyectos, entre otras; y,\nVI. Etapa e clausura, consistente en la sesión de clausura y entrega del proyecto de las memorias del parlamento de las juventudes.\nLa instalación y clausura del Parlamento de las juventudes se realizará en la Sala de\nPleno Benito Juárez García, y de forma subsecuente, sus sesiones y actividades se celebran en la Sala Mujeres de Baja California, Forjadoras de la Patria, o de forma virtual.\nPárrafo Adicionado\nPárrafo Reformado y Reubicado\nLa sesión toma de instalación y toma de protesta del Parlamento deberá de llevarse a cabo de la siguiente manera:\nPárrafo con Fracciones Adicionado\nI. La Presidencia de la Comisión tomará protesta a la Mesa Directiva del Parlamento elegida en la sesión previa;\nII. La Presidencia de la Mesa Directiva del Parlamento tomará la protesta a las y los\nParlamentarios juveniles;\nIII. La sesión no podrá exceder de tres horas para su conclusión;\nIV. Para el desarrollo de las participaciones de los oradores deberán de ajustarse al número de los que podrán subir a tribuna y contemplar la existencia de los debates, el\nProcesos Parlamentarios previo a la realización del Parlamento de que se trate; y,\nV. Deberá finalizar con un mensaje de la Presidencia de la Mesa Directiva del\nParlamento.\nLey de la Juventud del Estado de Baja California. Página 44\nAl finalizar la sesión señalada en el presente artículo, se entregará a cada parlamentaria y parlamentario su nombramiento.\nPárrafo Adicionado juveniles.\nPárrafo Adicionado\nLas faltas al código interno de ética del parlamento serán calificadas por la Comisión y las sanciones serán:\nPárrafo con Fracciones Adicionado\nI. Amonestación privada por escrito;\nII. Suspensión de uno a veinte días de las actividades del parlamento; y,\nIII. Revocación del nombramiento juvenil.\nEn los casos previstos por las fracciones II y III del párrafo anterior se procederá a llamar a la persona suplente.\nPárrafo Adicionado\nArtículo Reformado\nARTÍCULO 105 BIS.- La Comisión creará un archivo documental consistente en actas, listas de asistencia, acuerdos y demás documentos del comité organizador, de igual forma se contará con un registro documental de las actividades de los parlamentos juveniles y el memorial de sus trabajos durante la legislatura, los cuales al finalizar la legislatura serán entregados y resguardados por la Dirección de Procesos Parlamentarios para su consulta por parte de las legislaturas posteriores y el público en general.\nLas memorias contendrán los proyectos legislativos y sociales con los que fueron seleccionados las y los parlamentarios juveniles, así como un registro fotográfico de sus principales actividades para que sirvan de consulta y orientación para la legislatura en funciones y posteriores.\nArtículo Adicionado\nARTÍCULO 106.- Para la instalación del Parlamento, la Comisión designará las personas que integrarán en Comité Organizador, los cuales serán cargos honoríficos.\nPárrafo Reformado\nAdemás, se invitará a una persona representante de cada una de las instancias municipales de la Juventud para integrar dicho Comité.\nPárrafo Adicionado\nArtículo Reformado\nARTÍCULO 107.- Los requisitos para ser Parlamentaria o Parlamentario Juvenil, son los siguientes:\nPárrafo Reformado\nLey de la Juventud del Estado de Baja California. Página 45\nI.- Contar con ciudadanía mexicana y con residencia en el Estado de Baja California;\nFracción Reformada\nII.- Tener una edad máxima de hasta 29 años, a la fecha que establezca la convocatoria y las demás disposiciones aplicables;\nIII.- Presentar un Proyecto Legislativo con los requisitos que establezca la convocatoria correspondiente y las demás disposiciones aplicables;\nIV.- No ser servidora o servidor público al momento de la elección; y,\nFracción Adicionada, recorriéndose la subsecuente\nFracción Reformada\nV.- Los demás que establezca la convocatoria correspondiente y las demás disposiciones aplicables.\nPara efectos de la fracción III del presente artículo, los proyectos serán evaluados considerando su originalidad, así como su desarrollo con perspectiva de juventudes, derechos humanos, inclusión e igualdad de género, además de los criterios previstos por la convocatoria.\nPárrafo Adicionado\nArtículo Reformado\nARTÍCULO 108.- La integración de cada nuevo Parlamento se realizará en el mes de octubre. El cargo de Parlamentaria o Parlamentario Juvenil tendrá la misma duración y será de naturaleza honorifica.\nArtículo Reformado\nARTÍCULO 108 BIS.- En sesión previa a la Toma de Protesta, las y los parlamentarios elegirán a su Mesa Directiva con Paridad de Género, mediante la votación de la mayoría calificada de sus integrantes.\nDicha sesión no deberá de extenderse por más de dos horas, en caso de no haber un acuerdo se procederá a elegir a las personas mejor evaluadas de dos listas, una de mujeres y otra de hombres, de forma alternadas para garantizar la paridad de género. En dicha\nParlamentarios.\nPárrafo Adicionado\nArtículo Adicionado\nArtículo Reformado\nTÍTULO SÉPTIMO\nCAPÍTULO PRIMERO\nRÉGIMEN DE TRABAJO\nLey de la Juventud del Estado de Baja California. Página 46\nARTÍCULO 109.- Las relaciones laborales entre el Instituto y sus trabajadores se regirán por el apartado “A” del artículo 123 de la Constitución Política de los Estados Unidos Mexicanos.\nCAPÍTULO SEGUNDO\nRESPONSABILIDADES Y SANCIONES\nARTÍCULO 110.- Las autoridades, servidoras y servidores públicos considerados en la presente Ley que incumplan con la misma serán sujetos de responsabilidad con la Ley de\nResponsabilidades Administrativas de los Servidores Públicos del Estado.\nArtículo Reformado\nTRANSITORIOS\nARTÍCULO PRIMERO.- Publíquese el presente Decreto en el Periódico oficial del\nEstado de Baja California.\nARTÍCULO SEGUNDO.- El presente Decreto iniciará su vigencia el día siguiente de su publicación en el Periódico Oficial del Estado de Baja California.\nARTÍCULO TERCERO.- La Junta Directiva del Instituto deberá quedar constituida en un plazo no mayor al de treinta días a partir de la vigencia de este Decreto, mismo plazo en el que deberá designar al Director del Propio Instituto.\nARTÍCULO CUARTO.- La Secretaría de Educación y Bienestar Social, transferirá los recursos financieros asignados para desempeñar funciones en materia de juventud en el\nEstado, para el inicio de actividades del Instituto.\nARTÍCULO QUINTO.- Las atribuciones que en materia de atención a la Juventud correspondan actualmente a la Secretaría de Educación y Bienestar Social, conforme a la\nLey Orgánica de la Administración Pública del Estado, la Ley de Educación del Estado y su\nReglamento Interno, las asumirá el Instituto, una vez que se instituya en los términos de la presente Ley; dejando a salvo los derechos de los trabajadores encargados de llevar a cabo las actividades y labores destinadas a la atención a la juventud.\nARTÍCULO SEXTO.- El primer Consejo Estatal de Atención a la Juventud, deberá\nInstituto. días siguientes al inicio de la vigencia del presente Decreto; en el cual se determine la estructura orgánica, el gobierno, la sectorización, la operación, la vigilancia, el patrimonio y las demás disposiciones necesarias para el funcionamiento del Instituto.\nARTÍCULO OCTAVO.- Los Municipios deberán actualizar su reglamentación municipal dentro de los 150 días siguientes al inicio de la vigencia del presente Decreto.\nLey de la Juventud del Estado de Baja California. Página 47\nARTÍCULO NOVENO.- Se derogan todos los acuerdos y demás disposiciones expedidas por el Gobernador que se opongan a la presente Ley. del Estado de Baja California, en la Ciudad de Mexicali, B.C., a los quince días del mes de junio del año dos mil once.\nLIC. CARLOS MURGUÍA MEJÍA\nDIPUTADO PRESIDENTE\n(RUBRICA)\nLIC. VIRGINIA NORIEGA RÍOS\nDIPUTADA SECRETARIA\n(RUBRICA)\nDE CONFORMIDAD CON LO DISPUESTO POR LA FRACCION I DEL ARTÍCULO 49\nMEXICALI, BAJA CALIFORNIA, A LOS TREINTA DÍAS DEL MES DE JUNIO DEL\nAÑO DOS MIL ONCE.\nGOBERNADOR DEL ESTADO\nJOSE GUADALUPE OSUNA MILLAN\n(RÚBRICA)\nSECRETARIO GENERAL DE GOBIERNO\nCUAUHTEMOC CARDONA BENAVIDES\n(RUBRICA)\nLey de la Juventud del Estado de Baja California. Página 48\nARTÍCULO 2.- Fue reformado por Decreto No. 217, publicado en el Periódico Oficial\nLegislatura, siendo Gobernador Constitucional el C. Jaime Bonilla Valdez 2019-2021;\nARTÍCULO 4.- Fue reformado por Decreto No. 472, publicado en el Periódico Oficial\nLegislatura, siendo Gobernador Constitucional el C. José Guadalupe Osuna Millán 200720013; fue reformado por Decreto No. 228, publicado en el Periódico Oficial No. 24, Sección\nI, Tomo CXXV, de fecha 18 de mayo de 2018, expedido por la H. XXII Legislatura, siendo\nGobernador Constitucional el C. Francisco Arturo Vega de Lamadrid 20013-2016; fue reformado por Decreto No. 341, publicado en el Periódico Oficial No. 26, Sección III, Tomo\nCXXVI, de fecha 14 de junio de 2019, expedido por la H. XXII Legislatura, siendo\nGobernador Constitucional el C. Francisco Arturo Vega de Lamadrid 20013-2016; fue reformado por Decreto No. 217, publicado en el Periódico Oficial No. 27, Índice, Tomo\nCXXVIII, de fecha 16 de abril de 2021, expedido por la H. XXIII Legislatura, siendo\nGobernador Constitucional el C. Jaime Bonilla Valdez 2019-2021;\nARTÍCULO 6.- Fue reformado por Decreto No. 217, publicado en el Periódico Oficial\nNo. 27, Índice, Tomo CXXVIII, de fecha 16 de abril de 2021, expedido por la H. XXIII\nLegislatura, siendo Gobernador Constitucional el C. Jaime Bonilla Valdez 2019-2021;\nARTÍCULO 7.- Fue reformado por Decreto No. 217, publicado en el Periódico Oficial\nNo. 27, Índice, Tomo CXXVIII, de fecha 16 de abril de 2021, expedido por la H. XXIII\nLegislatura, siendo Gobernador Constitucional el C. Jaime Bonilla Valdez 2019-2021;\nARTÍCULO 11.- Fue reformado por Decreto No. 217, publicado en el Periódico Oficial\nNo. 27, Índice, Tomo CXXVIII, de fecha 16 de abril de 2021, expedido por la H. XXIII\nLegislatura, siendo Gobernador Constitucional el C. Jaime Bonilla Valdez 2019-2021; fue reformado por Decreto No. 258, publicado en el Periódico Oficial No. 57, Sección I, Tomo\nCXXVIII, de fecha 06 de agosto de 2021, expedido por la H. XXIII Legislatura, siendo\nGobernador Constitucional el C. Jaime Bonilla Valdez 2019-2021;\nARTÍCULO 12.- Fue reformado por Decreto No. 217, publicado en el Periódico Oficial\nNo. 27, Índice, Tomo CXXVIII, de fecha 16 de abril de 2021, expedido por la H. XXIII\nLegislatura, siendo Gobernador Constitucional el C. Jaime Bonilla Valdez 2019-2021;\nARTÍCULO 13.- Fue reformado por Decreto No. 217, publicado en el Periódico Oficial\nLegislatura, siendo Gobernador Constitucional el C. Jaime Bonilla Valdez 2019-2021;\nARTÍCULO 14.- Fue reformado por Decreto No. 217, publicado en el Periódico Oficial\nLegislatura, siendo Gobernador Constitucional el C. Jaime Bonilla Valdez 2019-2021;\nARTÍCULO 16.- Fue reformado por Decreto No. 217, publicado en el Periódico Oficial\nLegislatura, siendo Gobernador Constitucional el C. Jaime Bonilla Valdez 2019-2021;\nLey de la Juventud del Estado de Baja California. Página 49\nARTÍCULO 17.- Fue reformado por Decreto No. 217, publicado en el Periódico Oficial\nLegislatura, siendo Gobernador Constitucional el C. Jaime Bonilla Valdez 2019-2021;\nARTÍCULO 18.- Fue reformado por Decreto No. 217, publicado en el Periódico Oficial\nLegislatura, siendo Gobernador Constitucional el C. Jaime Bonilla Valdez 2019-2021;\nARTÍCULO 18 BIS.- Fue reformado por Decreto No. 217, publicado en el Periódico\nOficial No. 27, Índice, Tomo CXXVIII, de fecha 16 de abril de 2021, expedido por la H. XXIII\nLegislatura, siendo Gobernador Constitucional el C. Jaime Bonilla Valdez 2019-2021;\nARTÍCULO 19.- Fue reformado por Decreto No. 217, publicado en el Periódico Oficial\nNo. 27, Índice, Tomo CXXVIII, de fecha 16 de abril de 2021, expedido por la H. XXIII\nLegislatura, siendo Gobernador Constitucional el C. Jaime Bonilla Valdez 2019-2021;\nARTÍCULO 20.- Fue reformado por Decreto No. 217, publicado en el Periódico Oficial\nNo. 27, Índice, Tomo CXXVIII, de fecha 16 de abril de 2021, expedido por la H. XXIII\nLegislatura, siendo Gobernador Constitucional el C. Jaime Bonilla Valdez 2019-2021;\nARTÍCULO 23.- Fue reformado por Decreto No. 217, publicado en el Periódico Oficial\nNo. 27, Índice, Tomo CXXVIII, de fecha 16 de abril de 2021, expedido por la H. XXIII\nLegislatura, siendo Gobernador Constitucional el C. Jaime Bonilla Valdez 2019-2021;\nARTÍCULO 25.- Fue reformado por Decreto No. 217, publicado en el Periódico Oficial\nNo. 27, Índice, Tomo CXXVIII, de fecha 16 de abril de 2021, expedido por la H. XXIII\nLegislatura, siendo Gobernador Constitucional el C. Jaime Bonilla Valdez 2019-2021;\nFue reformado por Decreto No. 217, publicado en el Periódico Oficial No. 27, Índice, Tomo CXXVIII, de fecha 16 de abril de 2021, expedido por la H. XXIII Legislatura, siendo\nGobernador Constitucional el C. Jaime Bonilla Valdez 2019-2021;\nSECCIÓN SÉPTIMA\nDERECHO DE ACCESO A LA INFORMACIÓN PÚBLICA\nARTÍCULO 26 BIS.- Fue reformado por Decreto No. 217, publicado en el Periódico\nLegislatura, siendo Gobernador Constitucional el C. Jaime Bonilla Valdez 2019-2021;\nARTÍCULO 26 TER.- Fue reformado por Decreto No. 217, publicado en el Periódico\nLegislatura, siendo Gobernador Constitucional el C. Jaime Bonilla Valdez 2019-2021;\nARTÍCULO 27.- Fue reformado por Decreto No. 217, publicado en el Periódico Oficial\nLegislatura, siendo Gobernador Constitucional el C. Jaime Bonilla Valdez 2019-2021;\nLey de la Juventud del Estado de Baja California. Página 50\nARTÍCULO 28.- Fue reformado por Decreto No. 217, publicado en el Periódico Oficial\nLegislatura, siendo Gobernador Constitucional el C. Jaime Bonilla Valdez 2019-2021;\nARTÍCULO 29.- Fue reformado por Decreto No. 217, publicado en el Periódico Oficial\nLegislatura, siendo Gobernador Constitucional el C. Jaime Bonilla Valdez 2019-2021;\nARTÍCULO 30.- Fue reformado por Decreto No. 217, publicado en el Periódico Oficial\nNo. 27, Índice, Tomo CXXVIII, de fecha 16 de abril de 2021, expedido por la H. XXIII\nLegislatura, siendo Gobernador Constitucional el C. Jaime Bonilla Valdez 2019-2021;\nARTÍCULO 31.- Fue reformado por Decreto No. 217, publicado en el Periódico Oficial\nNo. 27, Índice, Tomo CXXVIII, de fecha 16 de abril de 2021, expedido por la H. XXIII\nLegislatura, siendo Gobernador Constitucional el C. Jaime Bonilla Valdez 2019-2021;\nARTÍCULO 35.- Fue reformado por Decreto No. 514, publicado en el Periódico Oficial\nNo. 34, de fecha 29 de julio de 2016, Sección VI, Tomo CXXIII, expedido por la H. XXI\nLegislatura, siendo Gobernador Constitucional el C. Francisco Arturo Vega de Lamadrid\n2013-2019;\nARTÍCULO 37.- Fue reformado por Decreto No. 514, publicado en el Periódico Oficial\nNo. 34, de fecha 29 de julio de 2016, Sección VI, Tomo CXXIII, expedido por la H. XXI\nLegislatura, siendo Gobernador Constitucional el C. Francisco Arturo Vega de Lamadrid\n2013-2019;\nARTÍCULO 39.- Fue reformado por Decreto No. 217, publicado en el Periódico Oficial\nNo. 27, Índice, Tomo CXXVIII, de fecha 16 de abril de 2021, expedido por la H. XXIII\nLegislatura, siendo Gobernador Constitucional el C. Jaime Bonilla Valdez 2019-2021;\nARTÍCULO 48.- Fue reformado por Decreto No. 217, publicado en el Periódico Oficial\nNo. 27, Índice, Tomo CXXVIII, de fecha 16 de abril de 2021, expedido por la H. XXIII\nLegislatura, siendo Gobernador Constitucional el C. Jaime Bonilla Valdez 2019-2021;\nARTÍCULO 49.- Fue reformado por Decreto No. 217, publicado en el Periódico Oficial\nNo. 27, Índice, Tomo CXXVIII, de fecha 16 de abril de 2021, expedido por la H. XXIII\nLegislatura, siendo Gobernador Constitucional el C. Jaime Bonilla Valdez 2019-2021;\nARTÍCULO 50.- Fue reformado por Decreto No. 217, publicado en el Periódico Oficial\nLegislatura, siendo Gobernador Constitucional el C. Jaime Bonilla Valdez 2019-2021;\nFue adicionado por Decreto No. 258, publicado en el Periódico Oficial No. 57, Sección siendo Gobernador Constitucional el C. Jaime Bonilla Valdez 2019-2021;\nSECCIÓN NOVENA\nDERECHO A LA MOVILIDAD\nLey de la Juventud del Estado de Baja California. Página 51\nARTÍCULO 50 BIS.- Fue adicionado por Decreto No. 258, publicado en el Periódico\nXXIII Legislatura, siendo Gobernador Constitucional el C. Jaime Bonilla Valdez 2019-2021;\nARTÍCULO 51.- Fue reformado por Decreto No. 217, publicado en el Periódico Oficial\nLegislatura, siendo Gobernador Constitucional el C. Jaime Bonilla Valdez 2019-2021;\nARTÍCULO 53.- Fue reformado por Decreto No. 217, publicado en el Periódico Oficial\nNo. 27, Índice, Tomo CXXVIII, de fecha 16 de abril de 2021, expedido por la H. XXIII\nLegislatura, siendo Gobernador Constitucional el C. Jaime Bonilla Valdez 2019-2021;\nARTÍCULO 54.- Fue reformado por Decreto No. 217, publicado en el Periódico Oficial\nNo. 27, Índice, Tomo CXXVIII, de fecha 16 de abril de 2021, expedido por la H. XXIII\nLegislatura, siendo Gobernador Constitucional el C. Jaime Bonilla Valdez 2019-2021;\nARTÍCULO 55.- Fue reformado por Decreto No. 217, publicado en el Periódico Oficial\nNo. 27, Índice, Tomo CXXVIII, de fecha 16 de abril de 2021, expedido por la H. XXIII\nLegislatura, siendo Gobernador Constitucional el C. Jaime Bonilla Valdez 2019-2021;\nARTÍCULO 56.- Fue reformado por Decreto No. 472, publicado en el Periódico Oficial\nNo. 29, Sección I, Tomo CXX, de fecha 28 de junio de 2013, expedido por la H. XX\nLegislatura, siendo Gobernador Constitucional el C. José Guadalupe Osuna Millán 200720013; fue reformado por Decreto No. 217, publicado en el Periódico Oficial No. 27, Índice, Tomo CXXVIII, de fecha 16 de abril de 2021, expedido por la H. XXIII Legislatura, siendo\nGobernador Constitucional el C. Jaime Bonilla Valdez 2019-2021;\nARTÍCULO 59.- Fue reformado por Decreto No. 217, publicado en el Periódico Oficial\nNo. 27, Índice, Tomo CXXVIII, de fecha 16 de abril de 2021, expedido por la H. XXIII\nLegislatura, siendo Gobernador Constitucional el C. Jaime Bonilla Valdez 2019-2021;\nARTÍCULO 60.- Fue reformado por Decreto No. 217, publicado en el Periódico Oficial\nNo. 27, Índice, Tomo CXXVIII, de fecha 16 de abril de 2021, expedido por la H. XXIII\nLegislatura, siendo Gobernador Constitucional el C. Jaime Bonilla Valdez 2019-2021;\nARTÍCULO 62.- Fue reformado por Decreto No. 472, publicado en el Periódico Oficial\nLegislatura, siendo Gobernador Constitucional el C. José Guadalupe Osuna Millán 200720013; fue reformado por Decreto No. 341, publicado en el Periódico Oficial No. 26, Sección\nGobernador Constitucional el C. Francisco Arturo Vega de Lamadrid 20013-2016; fue reformado por Decreto No. 217, publicado en el Periódico Oficial No. 27, Índice, Tomo\nGobernador Constitucional el C. Jaime Bonilla Valdez 2019-2021;\nLey de la Juventud del Estado de Baja California. Página 52\nARTÍCULO 63.- Fue reformado por Decreto No. 217, publicado en el Periódico Oficial\nLegislatura, siendo Gobernador Constitucional el C. Jaime Bonilla Valdez 2019-2021;\nARTÍCULO 64.- Fue reformado por Decreto No. 341, publicado en el Periódico Oficial\nLegislatura, siendo Gobernador Constitucional el C. Francisco Arturo Vega de Lamadrid\n20013-2016;\nARTÍCULO 65.- Fue reformado por Decreto No. 341, publicado en el Periódico Oficial\nNo. 26, Sección III, Tomo CXXVI, de fecha 14 de junio de 2019, expedido por la H. XXII\nLegislatura, siendo Gobernador Constitucional el C. Francisco Arturo Vega de Lamadrid\n20013-2016;\nARTÍCULO 65 BIS.- Fue reformado por Decreto No. 228, publicado en el Periódico\nOficial No. 24, Sección I, Tomo CXXV, de fecha 18 de mayo de 2018, expedido por la H.\nXXII Legislatura, siendo Gobernador Constitucional el C. Francisco Arturo Vega de Lamadrid\n20013-2016;\nARTÍCULO 68.- Fue reformado por Decreto No. 514, publicado en el Periódico Oficial\nNo. 34, de fecha 29 de julio de 2016, Sección VI, Tomo CXXIII, expedido por la H. XXI\nLegislatura, siendo Gobernador Constitucional el C. Francisco Arturo Vega de Lamadrid\n2013-2019; fue reformado por Decreto No. 228, publicado en el Periódico Oficial No. 24,\nSección I, Tomo CXXV, de fecha 18 de mayo de 2018, expedido por la H. XXII Legislatura, siendo Gobernador Constitucional el C. Francisco Arturo Vega de Lamadrid 20013-2016; fue reformado por Decreto No. 217, publicado en el Periódico Oficial No. 27, Índice, Tomo\nCXXVIII, de fecha 16 de abril de 2021, expedido por la H. XXIII Legislatura, siendo\nGobernador Constitucional el C. Jaime Bonilla Valdez 2019-2021;\nARTÍCULO 69.- Fue reformado por Decreto No. 217, publicado en el Periódico Oficial\nNo. 27, Índice, Tomo CXXVIII, de fecha 16 de abril de 2021, expedido por la H. XXIII\nLegislatura, siendo Gobernador Constitucional el C. Jaime Bonilla Valdez 2019-2021;\nARTÍCULO 70.- Fue reformado por Decreto No. 514, publicado en el Periódico Oficial\nNo. 34, de fecha 29 de julio de 2016, Sección VI, Tomo CXXIII, expedido por la H. XXI\nLegislatura, siendo Gobernador Constitucional el C. Francisco Arturo Vega de Lamadrid\n2013-2019; fue reformado por Decreto No. 217, publicado en el Periódico Oficial No. 27, siendo Gobernador Constitucional el C. Jaime Bonilla Valdez 2019-2021;\nARTÍCULO 72.- Fue reformado por Decreto No. 217, publicado en el Periódico Oficial\nLegislatura, siendo Gobernador Constitucional el C. Jaime Bonilla Valdez 2019-2021;\nARTÍCULO 73.- Fue reformado por Decreto No. 472, publicado en el Periódico Oficial\nLegislatura, siendo Gobernador Constitucional el C. José Guadalupe Osuna Millán 200720013; fue reformado por Decreto No. 440, publicado en el Periódico Oficial No. 33, Índice, Ley de la Juventud del Estado de Baja California. Página 53\nGobernadora Constitucional la C. Marina del Pilar Ávila Olmeda 2021-2027;\nARTÍCULO 75.- Fue reformado por Decreto No. 472, publicado en el Periódico Oficial\nLegislatura, siendo Gobernador Constitucional el C. José Guadalupe Osuna Millán 200720013; fue reformado por Decreto No. 217, publicado en el Periódico Oficial No. 27, Índice, Tomo CXXVIII, de fecha 16 de abril de 2021, expedido por la H. XXIII Legislatura, siendo\nGobernador Constitucional el C. Jaime Bonilla Valdez 2019-2021;\nARTÍCULO 76.- Fue reformado por Decreto No. 217, publicado en el Periódico Oficial\nNo. 27, Índice, Tomo CXXVIII, de fecha 16 de abril de 2021, expedido por la H. XXIII\nLegislatura, siendo Gobernador Constitucional el C. Jaime Bonilla Valdez 2019-2021;\nARTÍCULO 77.- Fue reformado por Decreto No. 472, publicado en el Periódico Oficial\nNo. 29, Sección I, Tomo CXX, de fecha 28 de junio de 2013, expedido por la H. XX\nLegislatura, siendo Gobernador Constitucional el C. José Guadalupe Osuna Millán 20072013; fue reformado por Decreto No. 217, publicado en el Periódico Oficial No. 27, Índice, Tomo CXXVIII, de fecha 16 de abril de 2021, expedido por la H. XXIII Legislatura, siendo\nGobernador Constitucional el C. Jaime Bonilla Valdez 2019-2021;\nARTÍCULO 78.- Fue reformado por Decreto No. 472, publicado en el Periódico Oficial\nNo. 29, Sección I, Tomo CXX, de fecha 28 de junio de 2013, expedido por la H. XX\nLegislatura, siendo Gobernador Constitucional el C. José Guadalupe Osuna Millán 20072013;\nARTÍCULO 79.- Fue reformado por Decreto No. 217, publicado en el Periódico Oficial\nNo. 27, Índice, Tomo CXXVIII, de fecha 16 de abril de 2021, expedido por la H. XXIII\nLegislatura, siendo Gobernador Constitucional el C. Jaime Bonilla Valdez 2019-2021;\nARTÍCULO 80.- Fue reformado por Decreto No. 217, publicado en el Periódico Oficial\nNo. 27, Índice, Tomo CXXVIII, de fecha 16 de abril de 2021, expedido por la H. XXIII\nLegislatura, siendo Gobernador Constitucional el C. Jaime Bonilla Valdez 2019-2021;\nARTÍCULO 81.- Fue reformado por Decreto No. 472, publicado en el Periódico Oficial\nNo. 29, Sección I, Tomo CXX, de fecha 28 de junio de 2013, expedido por la H. XX\nLegislatura, siendo Gobernador Constitucional el C. José Guadalupe Osuna Millán 200720013; fue reformado por Decreto No. 217, publicado en el Periódico Oficial No. 27, Índice, Gobernador Constitucional el C. Jaime Bonilla Valdez 2019-2021;\nARTÍCULO 83.- Fue reformado por Decreto No. 472, publicado en el Periódico Oficial\nLegislatura, siendo Gobernador Constitucional el C. José Guadalupe Osuna Millán 200720013; fue reformado por Decreto No. 514, publicado en el Periódico Oficial No. 34, de fecha\nGobernador Constitucional el C. Francisco Arturo Vega de Lamadrid 2013-2019; fue reformado por Decreto No. 578, publicado en el Periódico Oficial No. 44, Sección III, Tomo\nLey de la Juventud del Estado de Baja California. Página 54\nGobernador Constitucional el C. Francisco Arturo Vega de Lamadrid 2013-2016; fue reformado por Decreto No. 217, publicado en el Periódico Oficial No. 27, Índice, Tomo\nGobernador Constitucional el C. Jaime Bonilla Valdez 2019-2021; fue reformado por Decreto\nNo. 93, publicado en el Periódico Oficial No. 30, Número Especial, de fecha 13 de mayo de\n2025, Tomo CXXXII, expedido por la H. XXV Legislatura, siendo Gobernadora Constitucional la C. Marina del Pilar Ávila Olmeda 2021-2027;\nARTÍCULO 84.- Fue reformado por Decreto No. 217, publicado en el Periódico Oficial\nNo. 27, Índice, Tomo CXXVIII, de fecha 16 de abril de 2021, expedido por la H. XXIII\nLegislatura, siendo Gobernador Constitucional el C. Jaime Bonilla Valdez 2019-2021;\nARTÍCULO 85.- Fue reformado por Decreto No. 228, publicado en el Periódico Oficial\nNo. 24, Sección I, Tomo CXXV, de fecha 18 de mayo de 2018, expedido por la H. XXII\nLegislatura, siendo Gobernador Constitucional el C. Francisco Arturo Vega de Lamadrid\n2013-2016; fue reformado por Decreto No. 217, publicado en el Periódico Oficial No. 27, Índice, Tomo CXXVIII, de fecha 16 de abril de 2021, expedido por la H. XXIII Legislatura, siendo Gobernador Constitucional el C. Jaime Bonilla Valdez 2019-2021;\nARTÍCULO 86.- Fue reformado por Decreto No. 217, publicado en el Periódico Oficial\nNo. 27, Índice, Tomo CXXVIII, de fecha 16 de abril de 2021, expedido por la H. XXIII\nLegislatura, siendo Gobernador Constitucional el C. Jaime Bonilla Valdez 2019-2021;\nARTÍCULO 87.- Fue reformado por Decreto No. 217, publicado en el Periódico Oficial\nNo. 27, Índice, Tomo CXXVIII, de fecha 16 de abril de 2021, expedido por la H. XXIII\nLegislatura, siendo Gobernador Constitucional el C. Jaime Bonilla Valdez 2019-2021;\nARTÍCULO 88.- Fue reformado por Decreto No. 217, publicado en el Periódico Oficial\nNo. 27, Índice, Tomo CXXVIII, de fecha 16 de abril de 2021, expedido por la H. XXIII\nLegislatura, siendo Gobernador Constitucional el C. Jaime Bonilla Valdez 2019-2021;\nARTÍCULO 91.- Fue reformado por Decreto No. 217, publicado en el Periódico Oficial\nNo. 27, Índice, Tomo CXXVIII, de fecha 16 de abril de 2021, expedido por la H. XXIII\nLegislatura, siendo Gobernador Constitucional el C. Jaime Bonilla Valdez 2019-2021;\nARTÍCULO 92.- Fue reformado por Decreto No. 217, publicado en el Periódico Oficial\nLegislatura, siendo Gobernador Constitucional el C. Jaime Bonilla Valdez 2019-2021;\nARTÍCULO 93.- Fue reformado por Decreto No. 217, publicado en el Periódico Oficial\nLegislatura, siendo Gobernador Constitucional el C. Jaime Bonilla Valdez 2019-2021;\nARTÍCULO 94.- Fue reformado por Decreto No. 217, publicado en el Periódico Oficial\nLegislatura, siendo Gobernador Constitucional el C. Jaime Bonilla Valdez 2019-2021;\nLey de la Juventud del Estado de Baja California. Página 55\nARTÍCULO 96.- Fue reformado por Decreto No. 217, publicado en el Periódico Oficial\nLegislatura, siendo Gobernador Constitucional el C. Jaime Bonilla Valdez 2019-2021;\nARTÍCULO 98.- Fue reformado por Decreto No. 217, publicado en el Periódico Oficial\nLegislatura, siendo Gobernador Constitucional el C. Jaime Bonilla Valdez 2019-2021;\nARTÍCULO 100.- Fue reformado mediante Decreto No. 161, publicado en el Periódico\nOficial No. 66, de fecha 11 de noviembre de 2022, Tomo CXXIX, Índice, expedido por la H.\nXXIV Legislatura, siendo Gobernadora Constitucional la C. Marina del Pilar Ávila Olmeda\n2021-2027; fue reformado por Decreto No. 272, publicado en el Periódico Oficial No. 53, de fecha 08 de septiembre de 2023, Sección III, Tomo CXXX; expedido por la H. XXIV\nLegislatura, siendo Gobernadora Constitucional la C. Marina del Pilar Ávila Olmeda 20212027;\nARTÍCULO 101.- Fue reformado por Decreto No. 217, publicado en el Periódico\nOficial No. 27, Índice, Tomo CXXVIII, de fecha 16 de abril de 2021, expedido por la H. XXIII\nLegislatura, siendo Gobernador Constitucional el C. Jaime Bonilla Valdez 2019-2021; fue reformado por Decreto No. 272, publicado en el Periódico Oficial No. 53, de fecha 08 de septiembre de 2023, Sección III, Tomo CXXX; expedido por la H. XXIV Legislatura, siendo\nGobernadora Constitucional la C. Marina del Pilar Ávila Olmeda 2021-2027;\nFue reformada la denominación de este Capítulo por Decreto No. 276, publicado en el\nPeriódico Oficial No. 53, de fecha 08 de septiembre de 2023, Sección III, Tomo CXXX; expedido por la H. XXIV Legislatura, siendo Gobernadora Constitucional la C. Marina del\nPilar Ávila Olmeda 2021-2027;\nCAPÍTULO CUARTO\nDEL PARLAMENTO DE LAS JUVENTUDES\nARTÍCULO 104.- Fue reformado por Decreto No. 228, publicado en el Periódico\nOficial No. 24, Sección I, Tomo CXXV, de fecha 18 de mayo de 2018, expedido por la H.\nXXII Legislatura, siendo Gobernador Constitucional el C. Francisco Arturo Vega de Lamadrid\n2013-2016; fue reformado por Decreto No. 217, publicado en el Periódico Oficial No. 27, siendo Gobernador Constitucional el C. Jaime Bonilla Valdez 2019-2021; fue reformado por\nDecreto No. 276, publicado en el Periódico Oficial No. 53, de fecha 08 de septiembre de\n2023, Sección III, Tomo CXXX; expedido por la H. XXIV Legislatura, siendo Gobernadora\nConstitucional la C. Marina del Pilar Ávila Olmeda 2021-2027;\nARTÍCULO 104 BIS.- Fue reformado por Decreto No. 217, publicado en el Periódico\nLegislatura, siendo Gobernador Constitucional el C. Jaime Bonilla Valdez 2019-2021; fue reformado por Decreto No. 276, publicado en el Periódico Oficial No. 53, de fecha 08 de\nLey de la Juventud del Estado de Baja California. Página 56\nGobernadora Constitucional la C. Marina del Pilar Ávila Olmeda 2021-2027;\nARTÍCULO 105.- Fue reformado por Decreto No. 470, publicado en el Periódico\nLegislatura, siendo Gobernador Constitucional el C. Francisco Arturo Vega de Lamadrid\n2013-2016; fue reformado por Decreto No. 342, publicado en el Periódico Oficial No. 26,\nSección III, Tomo CXXVI, de fecha 14 de junio de 2019, expedido por la H. XXII Legislatura, siendo Gobernador Constitucional el C. Francisco Arturo Vega de Lamadrid 2013-2016; fue reformado por Decreto No. 217, publicado en el Periódico Oficial No. 27, Índice, Tomo\nCXXVIII, de fecha 16 de abril de 2021, expedido por la H. XXIII Legislatura, siendo\nGobernador Constitucional el C. Jaime Bonilla Valdez 2019-2021; fue reformado por Decreto\nNo. 276, publicado en el Periódico Oficial No. 53, de fecha 08 de septiembre de 2023,\nSección III, Tomo CXXX; expedido por la H. XXIV Legislatura, siendo Gobernadora\nConstitucional la C. Marina del Pilar Ávila Olmeda 2021-2027;\nARTÍCULO 105 BIS.- Fue adicionado por Decreto No. 276, publicado en el Periódico\nOficial No. 53, de fecha 08 de septiembre de 2023, Sección III, Tomo CXXX; expedido por la\nH. XXIV Legislatura, siendo Gobernadora Constitucional la C. Marina del Pilar Ávila Olmeda\n2021-2027;\nARTÍCULO 106.- Fue reformado por Decreto No. 470, publicado en el Periódico\nOficial No. 17, Sección V, Tomo CXXIII, de fecha 8 de abril de 2016, expedido por la H. XXI\nLegislatura, siendo Gobernador Constitucional el C. Francisco Arturo Vega de Lamadrid\n2013-2016; fue reformado por Decreto No. 228, publicado en el Periódico Oficial No. 24,\nSección I, Tomo CXXV, de fecha 18 de mayo de 2018, expedido por la H. XXII Legislatura, siendo Gobernador Constitucional el C. Francisco Arturo Vega de Lamadrid 2013-2016; fue reformado por Decreto No. 217, publicado en el Periódico Oficial No. 27, Índice, Tomo\nCXXVIII, de fecha 16 de abril de 2021, expedido por la H. XXIII Legislatura, siendo\nGobernador Constitucional el C. Jaime Bonilla Valdez 2019-2021;\nARTÍCULO 107.- Fue reformado por Decreto No. 470, publicado en el Periódico\nOficial No. 17, Sección V, Tomo CXXIII, de fecha 8 de abril de 2016, expedido por la H. XXI\nLegislatura, siendo Gobernador Constitucional el C. Francisco Arturo Vega de Lamadrid\n2013-2016; fue reformado por Decreto No. 217, publicado en el Periódico Oficial No. 27, siendo Gobernador Constitucional el C. Jaime Bonilla Valdez 2019-2021; fue reformado por\nDecreto No. 276, publicado en el Periódico Oficial No. 53, de fecha 08 de septiembre de\n2023, Sección III, Tomo CXXX; expedido por la H. XXIV Legislatura, siendo Gobernadora\nConstitucional la C. Marina del Pilar Ávila Olmeda 2021-2027;\nARTÍCULO 108.- Fue reformado por Decreto No. 470, publicado en el Periódico\nLegislatura, siendo Gobernador Constitucional el C. Francisco Arturo Vega de Lamadrid\n2013-2016; fue reformado por Decreto No. 342, publicado en el Periódico Oficial No. 26, Ley de la Juventud del Estado de Baja California. Página 57 siendo Gobernador Constitucional el C. Francisco Arturo Vega de Lamadrid 2013-2016; fue reformado por Decreto No. 217, publicado en el Periódico Oficial No. 27, Índice, Tomo\nGobernador Constitucional el C. Jaime Bonilla Valdez 2019-2021; fue reformado por Decreto\nNo. 276, publicado en el Periódico Oficial No. 53, de fecha 08 de septiembre de 2023,\nSección III, Tomo CXXX; expedido por la H. XXIV Legislatura, siendo Gobernadora\nConstitucional la C. Marina del Pilar Ávila Olmeda 2021-2027;\nARTÍCULO 108 BIS.- Fue reformado por Decreto No. 217, publicado en el Periódico\nLegislatura, siendo Gobernador Constitucional el C. Jaime Bonilla Valdez 2019-2021; fue reformado por Decreto No. 276, publicado en el Periódico Oficial No. 53, de fecha 08 de\nGobernadora Constitucional la C. Marina del Pilar Ávila Olmeda 2021-2027;\nARTÍCULO 110.- Fue reformado por Decreto No. 217, publicado en el Periódico\nLegislatura, siendo Gobernador Constitucional el C. Jaime Bonilla Valdez 2019-2021;\nLey de la Juventud del Estado de Baja California. Página 58\nARTÍCULO UNICO TRANSITORIO DEL DECRETO No. 472, POR EL QUE SE\nREFORMAN LOS ARTÍCULOS 4 FRACCIÓN I, 56 FRACCIÓN IV, 62 FRACCIÓN XIV, 73\nFRACCIÓN X, 75 FRACCIÓN II, III Y SE ADICIONA LA FRACCIÓN IV, 77 FRACCIÓN IX, X\nY SE ADICIONA LA FRACCIÓN XI, 78 FRACCIÓN IV, V Y SE ADICIONA LA FRACCIÓN\nVI, 81 FRACCIÓN XIII, XIV Y SE ADICIONA LA FRACCIÓN XV; Y 83 FRACCIÓN XXXVI Y\nSE ADICIONA LA FRACCIÓN XXXVII, PUBLICADO EN EL PERIÓDICO OFICIAL No. 29,\nSECCIÓN I, TOMO CXX, DE FECHA 28 DE JUNIO DE 2013, EXPEDIDO POR LA H. XX\nLEGISLATURA, SIENDO GOBERNADOR CONSTITUCIONAL EL C. JOSÉ GUADALUPE\nOSUNA MILLÁN 2007-20013;\nTRANSITORIOS\nARTÍCULO PRIMERO.- Publíquese el presente Decreto en el Periódico oficial del\nEstado de Baja California.\nARTÍCULO SEGUNDO.- El presente Decreto iniciará su vigencia el día siguiente de su publicación en el Periódico Oficial del Estado de Baja California.\nDADO en el Salón de Sesiones “Lic. Benito Juárez García” del H. Poder Legislativo del Estado de Baja California, en la Ciudad de Mexicali, B.C., a los veintiocho días del mes de mayo del año dos mil trece.\nDIP. JULIO FELIPE GARCÍA MUÑOZ\nPRESIDENTE\n(RÚBRICA)\nDIP. MARCO ANTONIO VIZCARRA CALDERÓN\nSECRETARIO\n(RÚBRICA)\nDE CONFORMIDAD CON LO DISPUESTO POR LA FRACCION I DEL ARTÍCULO 49\nMEXICALI, BAJA CALIFORNIA, A LOS DIEZ DÍAS DEL MES DE JUNIO DEL AÑO\nDOS MIL TRECE.\nGOBERNADOR DEL ESTADO\nJOSE GUADALUPE OSUNA MILLAN\n(RÚBRICA)\nSECRETARIO GENERAL DE GOBIERNO\nCUAUHTEMOC CARDONA BENAVIDES\n(RUBRICA)\nLey de la Juventud del Estado de Baja California. Página 59\nARTÍCULO UNICO TRANSITORIO DEL DECRETO No. 470, POR EL QUE SE\nREFORMAN LOS ARTÍCULOS 105, 106, 107 y 108, PUBLICADO EN EL PERIÓDICO\nPOR LA H. XXI LEGISLATURA, SIENDO GOBERNADOR CONSTITUCIONAL EL C.\nFRANCISCO ARTURO VEGA DE LAMADRID 2013-2019.\nTRANSITORIOS\nARTÍCULO PRIMERO.- El presente Decreto entrará en vigor el día siguiente de su publicación en el Periódico Oficial del Estado de Baja California.\nARTÍCULO SEGUNDO.- El presente Decreto no tendrá aplicación retroactiva para el\nSegundo Parlamento de la Juventud de Baja California ni para sus integrantes, quienes concluyen su cargo en el presente año, una vez concluida la duración del año, computado a partir de su instalación.\nDADO en el Salón de Sesiones “Lic. Benito Juárez García” del H. Poder Legislativo del Estado de Baja California, en la Ciudad de Mexicali, B.C., a los diez días del mes de marzo del año dos mil dieciséis.\nDIP. JOSÉ ALBERTO MARTÍNEZ CARRILLO\nVICEPRESIDENTE\n(RUBRICA)\nDIP. CUAUHTÉMOC CARDONA BENAVIDES\nPROSECRETARIO\n(RUBRICA)\nDE CONFORMIDAD CON LO DISPUESTO POR LA FRACCION I DEL ARTÍCULO 49 DE\nMEXICALI, BAJA CALIFORNIA, A LOS VEINTIOCHO DÍAS DEL MES DE MARZO DEL\nAÑO DOS MIL DIECISÉIS.\nFRANCISCO ARTURO VEGA DE LAMADRID\nGOBERNADOR DEL ESTADO\n(RÚBRICA)\nFRANCISCO RUEDA GOMEZ\nSECRETARIO GENERAL DE GOBIERNO\n(RÚBRICA)\nLey de la Juventud del Estado de Baja California. Página 60\nARTÍCULO ÚNICO TRANSITORIO DEL DECRETO No. 514, POR EL QUE SE\nREFORMAN LOS ARTÍCULOS 35, 37, 68, 70 Y 83; PUBLICADO EN EL PERIÓDICO\nEXPEDIDO POR LA H. XXI LEGISLATURA, SIENDO GOBERNADOR CONSTITUCIONAL\nEL C. FRANCISCO ARTURO VEGA DE LA MADRID 2013-2019.\nARTÍCULOS TRANSITORIOS\nPRIMERO.- El presente Decreto entrará en vigor al día siguiente de su publicación en el Periódico Oficial del Estado.\nSEGUNDO.- Dentro de un plazo no mayor al de seis meses, el Instituto de la\nJuventud del Estado emitirá los criterios para la gestión de becas, créditos y apoyos a que se refiere el presente Decreto.\nDADO en el Salón de Sesiones “Lic. Benito Juárez García” del H. Poder Legislativo del Estado de Baja California, en la Ciudad de Mexicali, B.C., a los veintitrés días del mes de junio del año dos mil dieciséis.\nDIP. MÓNICA BEDOYA SERNA\nPRESIDENTA\n(RUBRICA)\nDIP. ROSA ISELA PERALTA CASILLAS\nSECRETARIO\n(RUBRICA)\nDE CONFORMIDAD CON LO DISPUESTO POR LA FRACCIÓN I DEL ARTÍCULO 49\nMEXICALI, BAJA CALIFORNIA, A LOS SEIS DÍAS DEL MES DE JULIO DEL AÑO\nDOS MIL DIECISÉIS.\nFRANCISCO RUEDA GÓMEZ\nSECRETARIO GENERAL DE GOBIERNO\nEn suplencia por la ausencia del Gobernador del\nEstado, con fundamento en los artículos 45 y 52\n(RÚBRICA)\nLORETO QUINTERO QUINTERO\nOFICIAL MAYOR DE GOBIERNO de Gobierno, con fundamento en los artículos 54 de la\n(RÚBRICA)\nLey de la Juventud del Estado de Baja California. Página 61\nARTÍCULO ÚNICO TRANSITORIO DEL DECRETO No. 578, POR EL QUE SE\nREFORMA EL ARTÍCULO 83, PUBLICADO EN EL PERIÓDICO OFICIAL No. 44, SECCION\nLEGISLATURA, SIENDO GOBERNADOR CONSTITUCIONAL EL C. FRANCISCO ARTURO\nVEGA DE LAMADRID 2013-2019.\nTRANSITORIO\nÚNICO.- La presente reforma entrará en vigor al día siguiente de su publicación en el\nPeriódico Oficial del Estado.\nDADO en el Salón de Sesiones “Lic. Benito Juárez García” del H. Poder Legislativo del Estado de Baja California, en la Ciudad de Mexicali, B.C., al primer día del mes de septiembre del año dos mil dieciséis.\nDIP. MÓNICA BEDOYA SERNA\nPRESIDENTE\n(RUBRICA)\nDIP. ROSA ISELA PERALTA CASILLAS\nSECRETARIO\n(RUBRICA)\nDE CONFORMIDAD CON LO DISPUESTO POR LA FRACCION I DEL ARTÍCULO 49\nMEXICALI, BAJA CALIFORNIA, A LOS NUEVE DÍAS DEL MES DE SEPTIEMBRE DEL\nAÑO DOS MIL DIECISÉIS.\nFRANCISCO ARTURO VEGA DE LAMADRID\nGOBERNADOR DEL ESTADO\n(RÚBRICA)\nFRANCISCO RUEDA GOMEZ\nSECRETARIO GENERAL DE GOBIERNO\n(RÚBRICA)\nARTÍCULO ÚNICO TRANSITORIO DEL DECRETO No. 228, POR EL QUE SE\nREFORMA A LOS ARTÍCULOS 4 FRACCIÓN III, 68 FRACCIÓN III, 85, 104 Y 106,\nPUBLICADO EN EL PERIÓDICO OFICIAL No. 24, SECCION I, TOMO CXXV, DE FECHA\nGOBERNADOR CONSTITUCIONAL EL C. FRANCISCO ARTURO VEGA DE LAMADRID\n2013-2019.\nLey de la Juventud del Estado de Baja California. Página 62\nTRANSITORIO\nPRIMERO.- Las presentes reformas entrarán en vigor al día siguiente de su publicación en el Periódico Oficial del Estado.\nSEGUNDO.- Dentro de los 90 días siguientes al inicio de la vigencia del presente\nDecreto, se deberá adecuar los Reglamentos de la Ley de la Juventud del Estado de Baja\nCalifornia, así como el Reglamento Interno del Parlamento de la Juventud del Estado de\nBaja California.\nDADO en el Salón de Sesiones “Lic. Benito Juárez García” del H. Poder Legislativo del Estado de Baja California, en la Ciudad de Mexicali, B.C., a los ocho días del mes de marzo del año dos mil dieciocho.\nDIP. MTRO. RAÚL CASTAÑEDA POMPOSO\nPRESIDENTE\n(RÚBRICA)\nDIP. ROCÍO LÓPEZ GOROSAVE\nSECRETARIA\n(RÚBRICA)\nDE CONFORMIDAD CON LO DISPUESTO POR LA FRACCION I DEL ARTÍCULO 49\nMEXICALI, BAJA CALIFORNIA, A LOS ONCE DÍAS DEL MES DE MARZO DEL AÑO DOS\nMIL DIECIOCHO.\nFRANCISCO ARTURO VEGA DE LAMADRID\nGOBERNADOR DEL ESTADO\n(RÚBRICA)\nFRANCISCO RUEDA GÓMEZ\nSECRETARIO GENERAL DE GOBIERNO\n(RÚBRICA)\nARTÍCULO ÚNICO TRANSITORIO DEL DECRETO No. 230, POR EL QUE SE\nADICIONA UN ARTÍCULO 65 BIS, PUBLICADO EN EL PERIÓDICO OFICIAL No. 24,\nLEGISLATURA, SIENDO GOBERNADOR CONSTITUCIONAL EL C. FRANCISCO ARTURO\nVEGA DE LAMADRID 2013-2019.\nTRANSITORIO\nPRIMERO.- La presente reforma entrará en vigor al día siguiente de su publicación en el Periódico Oficial del Estado.\nLey de la Juventud del Estado de Baja California. Página 63\nSEGUNDO.- Una vez publicado en el Periódico Oficial, el Ejecutivo del Estado así como los Ayuntamiento tendrán un plazo de 60 días hábiles para adecuar sus reglamentos a fin de dar cumplimiento al presente Decreto. del Estado de Baja California, en la Ciudad de Mexicali, B.C., a los ocho días del mes de marzo del año dos mil dieciocho.\nDIP. MTRO. RAÚL CASTAÑEDA POMPOSO\nPRESIDENTE\n(RÚBRICA)\nDIP. ROCÍO LÓPEZ GOROSAVE\nSECRETARIA\n(RÚBRICA)\nDE CONFORMIDAD CON LO DISPUESTO POR LA FRACCION I DEL ARTÍCULO 49\nMEXICALI, BAJA CALIFORNIA, A LOS ONCE DÍAS DEL MES DE MARZO DEL AÑO DOS\nMIL DIECIOCHO.\nFRANCISCO ARTURO VEGA DE LAMADRID\nGOBERNADOR DEL ESTADO\n(RÚBRICA)\nFRANCISCO RUEDA GÓMEZ\nSECRETARIO GENERAL DE GOBIERNO\n(RÚBRICA)\nARTÍCULO ÚNICO TRANSITORIO DEL DECRETO No. 341, POR EL QUE SE\nREFORMA A LOS ARTÍCULOS 4 FRACCIÓN XVIII, REFORMA AL CAPÍTULO CUARTO,\nADICIÓN DE LAS FRACCIONES XXIII, XXIV, XXV Y XXVI AL ARTÍCULO 62, Y REFORMA\nDE LOS ARTÍCULOS 64 Y 65, PUBLICADO EN EL PERIÓDICO OFICIAL No. 26, SECCION\nLEGISLATURA, SIENDO GOBERNADOR CONSTITUCIONAL EL C. FRANCISCO ARTURO\nVEGA DE LAMADRID 2013-2019.\nTRANSITORIO\nPRIMERO.- Las presentes reformas entrarán en vigor al día siguiente de su publicación en el Periódico Oficial del Estado.\nSEGUNDO.- El Instituto de la Juventud del Estado de Baja California, dentro de los\n180 días naturales a la entrada en vigor de la presente reforma, realizará los ajustes al\nLey de la Juventud del Estado de Baja California. Página 64 esta reforma, así como hacer las adecuaciones administrativas y tecnológicas y acuerdos interinstitucionales necesarios para el cumplimiento de la presente reforma. del Estado de Baja California, en la Ciudad de Mexicali, B.C., a los diez días del mes de abril del año dos mil diecinueve.\nDIP. EDGAR BENJAMÍN GÓMEZ MACÍAS\nPRESIDENTE\n(RÚBRICA)\nDIP. ROCÍO LÓPEZ GOROSAVE\nPROSECRETARIA\n(RÚBRICA)\nDE CONFORMIDAD CON LO DISPUESTO POR LA FRACCION I DEL ARTÍCULO 49\nMEXICALI, BAJA CALIFORNIA, A LOS SIETE DÍAS DEL MES DE JUNIO DEL AÑO DOS\nMIL DIECINUEVE.\nFRANCISCO ARTURO VEGA DE LAMADRID\nGOBERNADOR DEL ESTADO\n(RÚBRICA)\nFRANCISCO RUEDA GÓMEZ\nSECRETARIO GENERAL DE GOBIERNO\n(RÚBRICA)\nTRANSITORIO\nPRIMERO.- Las presentes reformas entrarán en vigor al día siguiente al de su publicación en el Periódico Oficial del Estado.\nSEGUNDO.- El Parlamento de la juventud deberá realizar las reformas correspondientes a sus reglamentos correspondientes, dentro del plazo de 60 días siguientes a la entrada en vigor de las presentes reformas.\nTERCERO.- Terminando el periodo en curso, se continuará anualmente con la elección de nuevos parlamentarios, así como la instalación del parlamento. del Estado de Baja California, en la Ciudad de Mexicali, B.C., a los diez días del mes de abril del año dos mil diecinueve.\nLey de la Juventud del Estado de Baja California. Página 65\nDIP. EDGAR BENJAMÍN GÓMEZ MACÍAS\nPRESIDENTE\n(RÚBRICA)\nDIP. ROCÍO LÓPEZ GOROSAVE\nPROSECRETARIA\n(RÚBRICA)\nDE CONFORMIDAD CON LO DISPUESTO POR LA FRACCION I DEL ARTÍCULO 49\nMEXICALI, BAJA CALIFORNIA, A LOS SIETE DÍAS DEL MES DE JUNIO DEL AÑO DOS\nMIL DIECINUEVE.\nFRANCISCO ARTURO VEGA DE LAMADRID\nGOBERNADOR DEL ESTADO\n(RÚBRICA)\nFRANCISCO RUEDA GÓMEZ\nSECRETARIO GENERAL DE GOBIERNO\n(RÚBRICA)\nARTÍCULO PRIMERO TRANSITORIO DEL DECRETO No. 217, POR EL QUE SE\nAPRUEBA LA REFORMA A LOS ARTÍCULOS 2, 4, 6, 7, 11, 12, 13, 14, 16, 17, 18, 19, 20, 23, 25, 27, 28, 29, 30, 31, 39, 48, 50, 51, 53, 54, 55, 56, 59, 60, 62, 63, 68, 69, 70, 72, 75, 76, 77, 79, 80, 81, 83, 84, 85, 86, 87, 88, 91, 92, 93, 94, 96, 98, 101, 104, 105, 106, 107, 108\nY 110; LA ADICIÓN DE UNA SECCIÓN SÉPTIMA AL CAPÍTULO SEGUNDO DEL TÍTULO\nSEGUNDO DENOMINADA DERECHO DE ACCESO A LA INFORMACIÓN PÚBLICA, ASÍ\nCOMO LA ADICIÓN DE LOS ARTÍCULOS 18 BIS, 26 BIS, 26 TER, 104 BIS y 108 BIS;\nPUBLICADO EN EL PERIÓDICO OFICIAL No. 27, ÍNDICE, TOMO CXXVIII, DE FECHA 16\nCONSTITUCIONAL EL C. JAIME BONILLA VALDEZ 2019-2021\nARTÍCULO TRANSITORIO\nPrimero. La presente reforma entrara en vigor al día siguiente de su publicación en el\nPeriódico Oficial del Estado.\nSegundo. Como consecuencia de las medidas sanitarias generadas por el virus SARSCOV2 (COVID-19), no se generará proceso de selección para integrar nuevo Parlamento de\nJuventud, hasta en tanto las condiciones de salubridad lo permitan y así lo establezcan las autoridades competentes de la materia.\nLey de la Juventud del Estado de Baja California. Página 66\nLA REFORMA AL ARTÍCULO 49.\nARTÍCULO TRANSITORIO\nÚNICO. La presente reforma entrará en vigor al día siguiente de su publicación en el\nPeriódico Oficial del Estado.\nDADO en Sesión Ordinaria Virtual en la Ciudad de Mexicali, B.C., a los diez días del mes de marzo del año dos mil veintiuno.\nDIP. EVA GRICELDA RODRÍGUEZ\nPRESIDENTA\n(RÚBRICA)\nDIP. MARÍA LUISA VILLALOBOS ÁVILA\nSECRETARIA\n(RÚBRICA)\nDE CONFORMIDAD CON LO DISPUESTO POR LA FRACCION I DEL ARTÍCULO 49\nCALIFORNIA, IMPRÍMASE Y PUBLÍQUESE.\nMEXICALI, BAJA CALIFORNIA, A LOS VEINTITRÉS DÍAS DEL MES DE MARZO\nDEL AÑO DOS MIL VEINTIUNO.\nJAIME BONILLA VALDEZ\nGOBERNADOR DEL ESTADO\n(RÚBRICA)\nAMADOR RODRÍGUEZ LOZANO\nSECRETARIO GENERAL DE GOBIERNO\n(RÚBRICA)\nARTÍCULO ÚNICO TRANSITORIO DEL DECRETO No. 258, POR EL QUE SE\nREFORMA AL ARTÍCULO 11; LA ADICIÓN DE LA SECCIÓN NOVENA DENOMINADA\nDERECHO A LA MOVILIDAD, ASÍ COMO LA ADICIÓN DE UN ARTÍCULO 50 BIS,\nPUBLICADO EN EL PERIÓDICO OFICIAL No. 57, SECCIÓN I, TOMO CXXVIII, DE FECHA\nGOBERNADOR CONSTITUCIONAL EL C. JAIME BONILLA VALDEZ 2019-2021\nTRANSITORIO\nLey de la Juventud del Estado de Baja California. Página 67\nÚNICO. La presente reforma entrará en vigor al día siguiente de su publicación en el\nPeriódico Oficial del Estado.\nDADO en Sesión Ordinaria Virtual en la Ciudad de Mexicali, B.C., a los dieciséis días del mes de junio del año dos mil veintiuno.\nDIP. EVA GRICELDA RODRÍGUEZ\nPRESIDENTA\n(RÚBRICA)\nDIP. MARÍA LUISA VILLALOBOS ÁVILA\nSECRETARIA\n(RÚBRICA)\nDE CONFORMIDAD CON LO DISPUESTO POR LA FRACCION I DEL ARTÍCULO 49\nCALIFORNIA, IMPRÍMASE Y PUBLÍQUESE.\nMEXICALI, BAJA CALIFORNIA, A LOS TREINTA DÍAS DEL MES DE JUNIO DEL\nAÑO DOS MIL VEINTIUNO.\nJAIME BONILLA VALDEZ\nGOBERNADOR DEL ESTADO\n(RÚBRICA)\nAMADOR RODRÍGUEZ LOZANO\nSECRETARIO GENERAL DE GOBIERNO\n(RÚBRICA)\nARTÍCULO ÚNICO TRANSITORIO DEL DECRETO No. 161, POR EL QUE SE\nREFORMA EL ARTÍCULO 100; PUBLICADO EN EL PERIÓDICO OFICIAL No. 66, ÍNDICE,\nLEGISLATURA, SIENDO GOBERNADORA CONSTITUCIONAL LA C. MARINA DEL PILAR\nÁVILA OLMEDA 2021-2027.\nTRANSITORIOS\nÚNICO. El presente Decreto entrará en vigor al día siguiente de su publicación en el\nPeriódico Oficial del Estado de Baja California.\nDADO en Sesión Ordinaria de la XXIV Legislatura en la Ciudad de Mexicali, B.C., a los veinte días del mes de octubre del año dos mil veintidós.\nLey de la Juventud del Estado de Baja California. Página 68\nDIP. ALEJANDRA MARÍA ANG HERNÁNDEZ\nPRESIDENTA\n(RÚBRICA)\nDIP. DUNNIA MONTSERRAT MURILLO LÓPEZ\nSECRETARIA\n(RÚBRICA)\nDE CONFORMIDAD CON LO DISPUESTO POR LA FRACCIÓN I DEL ARTÍCULO 49\nCALIFORNIA, IMPRÍMASE Y PUBLÍQUESE.\nMEXICALI, BAJA CALIFORNIA, A LOS VEINTISIETE DÍAS DEL MES DE OCTUBRE\nDEL AÑO DOS MIL VEINTIDÓS.\nMARINA DEL PILAR ÁVILA OLMEDA\nGOBERNADORA DEL ESTADO\nDE BAJA CALIFORNIA\n(RÚBRICA)\nCATALINO ZAVALA MÁRQUEZ\nSECRETARIO GENERAL DE GOBIERNO\nDEL ESTADO DE BAJA CALIFORNIA\n(RÚBRICA)\nARTÍCULO ÚNICO TRANSITORIO DEL DECRETO No. 272, POR EL QUE SE\nREFORMA A LOS ARTÍCULOS 100 Y 101; PUBLICADO EN EL PERIÓDICO OFICIAL No.\n53, SECCIÓN III, DE FECHA 08 DE SEPTIEMBRE DE 2023, TOMO CXXX, EXPEDIDO\nPOR LA H. XXIV LEGISLATURA, SIENDO GOBERNADORA CONSTITUCIONAL LA C.\nMARINA DEL PILAR ÁVILA OLMEDA 2021-2027.\nTRANSITORIO:\nÚNICO. La presente reforma entrará en vigor el día siguiente a su publicación en el\nPeriódico Oficial del Estado de Baja California.\nDADO en Sesión Ordinaria de la XXIV Legislatura en la Ciudad de Mexicali, B.C., a los veinticuatro días del mes de agosto del año dos mil veintitrés.\nDIP. MANUEL GUERRERO LUNA\nPRESIDENTE\n(RÚBRICA)\nLey de la Juventud del Estado de Baja California. Página 69\nDIP. DUNNIA MONTSERRAT MURILLO LÓPEZ\nSECRETARIA\n(RÚBRICA)\nDE CONFORMIDAD CON LO DISPUESTO POR LA FRACCIÓN I DEL ARTÍCULO 49\nBAJA CALIFORNIA, IMPRÍMASE Y PUBLÍQUESE.\nMEXICALI, BAJA CALIFORNIA, A LOS VEINTIOCHO DÍAS DEL MES DE AGOSTO DEL\nAÑO DOS MIL VEINTITRÉS.\nMARINA DEL PILAR ÁVILA OLMEDA\nGOBERNADOR DEL ESTADO\nDE BAJA CALIFORNIA\n(RÚBRICA)\nCATALINO ZAVALA MÁRQUEZ\nSECRETARIO GENERAL DE GOBIERNO\nDEL ESTADO DE BAJA CALIFORNIA\n(RÚBRICA)\nARTÍCULO ÚNICO TRANSITORIO DEL DECRETO No. 276, POR EL QUE SE\nREFORMA A LOS ARTÍCULOS 104, 104 BIS, 105, 107, 108 y 108 BIS, LA ADICIÓN DE UN\nARTÍCULO 105 BIS, Y LA MODIFICACIÓN DEL NOMBRE DEL CAPÍTULO CUARTO DEL\nTÍTULO SEXTO; PUBLICADO EN EL PERIÓDICO OFICIAL No. 53, SECCIÓN III, DE\nFECHA 08 DE SEPTIEMBRE DE 2023, TOMO CXXX, EXPEDIDO POR LA H. XXIV\nLEGISLATURA, SIENDO GOBERNADORA CONSTITUCIONAL LA C. MARINA DEL PILAR\nÁVILA OLMEDA 2021-2027.\nTRANSITORIO\nÚNICO. El presente decreto entrará en vigor al día siguiente de su publicación en el\nPeriódico Oficial del Estado de Baja California.\nDADO en Sesión Ordinaria de la XXIV Legislatura en la Ciudad de Mexicali, B.C., a los veinticuatro días del mes de agosto del año dos mil veintitrés.\nDIP. MANUEL GUERRERO LUNA\nPRESIDENTE\n(RÚBRICA)\nDIP. DUNNIA MONTSERRAT MURILLO LÓPEZ\nSECRETARIA\n(RÚBRICA)\nLey de la Juventud del Estado de Baja California. Página 70\nDE CONFORMIDAD CON LO DISPUESTO POR LA FRACCIÓN I DEL ARTÍCULO 49\nBAJA CALIFORNIA, IMPRÍMASE Y PUBLÍQUESE.\nMEXICALI, BAJA CALIFORNIA, A LOS VEINTIOCHO DÍAS DEL MES DE AGOSTO DEL\nAÑO DOS MIL VEINTITRÉS.\nMARINA DEL PILAR ÁVILA OLMEDA\nGOBERNADOR DEL ESTADO\nDE BAJA CALIFORNIA\n(RÚBRICA)\nCATALINO ZAVALA MÁRQUEZ\nSECRETARIO GENERAL DE GOBIERNO\nDEL ESTADO DE BAJA CALIFORNIA\n(RÚBRICA)\nARTÍCULO ÚNICO TRANSITORIO DEL DECRETO No. 440, POR EL QUE SE\nAPRUEBA LA REFORMA AL ARTÍCULO 73; PUBLICADO EN EL PERIÓDICO OFICIAL No.\n33, DE FECHA 28 DE JUNIO DE 2024, ÍNDICE, TOMO CXXXI, EXPEDIDO POR LA H.\nXXIV LEGISLATURA, SIENDO GOBERNADORA CONSTITUCIONAL LA C. MARINA DEL\nPILAR ÁVILA OLMEDA 2021-2027.\nTRANSITORIO\nÚNICO. La presente reforma entrará en vigor al día siguiente de su publicación en el\nPeriódico Oficial del Estado de Baja California.\nDADO en Sesión Ordinaria de la XXIV Legislatura en la Ciudad de Mexicali, B.C., a los veinte días del mes de junio del año dos mil veinticuatro.\nDIP. RAMÓN VÁZQUEZ VALADEZ\nPRESIDENTE\n(RÚBRICA)\nDIP. MANUEL GUERRERO LUNA\nSECRETARIO\n(RÚBRICA)\nDE CONFORMIDAD CON LO DISPUESTO POR LA FRACCIÓN I DEL ARTÍCULO 49\nCALIFORNIA, IMPRÍMASE Y PUBLÍQUESE.\nLey de la Juventud del Estado de Baja California. Página 71\nMEXICALI, BAJA CALIFORNIA, A LOS VEINTICUATRO DÍAS DEL MES DE JUNIO\nDEL AÑO DOS MIL VEINTICUATRO.\nMARINA DEL PILAR ÁVILA OLMEDA\nGOBERNADORA DEL ESTADO\nDE BAJA CALIFORNIA\n(RÚBRICA)\nALFREDO ÁLVAREZ CÁRDENAS\nSECRETARIO GENERAL DE GOBIERNO\nDEL ESTADO DE BAJA CALIFORNIA\n(RÚBRICA)\nARTÍCULO ÚNICO TRANSITORIO DEL DECRETO No. 93, POR EL QUE SE\nAPRUEBA LA REFORMA AL ARTÍCULO 83; PUBLICADO EN EL PERIÓDICO OFICIAL No.\n30, NÚMERO ESPECIAL, DE FECHA 13 DE MAYO DE 2025, TOMO CXXXII; EXPEDIDO\nPOR LA H. XXIV LEGISLATURA, SIENDO GOBERNADORA CONSTITUCIONAL LA C.\nMARINA DEL PILAR ÁVILA OLMEDA 2021-2027.\nTRANSITORIO\nÚNICO. El presente decreto entrará en vigor al día siguiente de su publicación en el\nPeriódico Oficial del Estado de Baja California.\nDADO en Sesión Ordinaria de la XXV Legislatura en la Ciudad de Mexicali, B.C., a los ocho días del mes de mayo del año dos mil veinticinco.\nDIP. MICHELLE ALEJANDRA TEJEDA MEDINA\nPRESIDENTA\n(RÚBRICA)\nDIP. NORMA ANGELICA PEÑALOZA ESCOBEDO\nSECRETARIA\n(RÚBRICA)\nDE CONFORMIDAD CON LO DISPUESTO POR LA FRACCIÓN I DEL ARTÍCULO 49\nCALIFORNIA, IMPRÍMASE Y PUBLÍQUESE.\nMEXICALI, BAJA CALIFORNIA, A LOS 09 DÍAS DEL MES DE MAYO DEL AÑO DOS\nMIL VEINTICUATRO.\nMARINA DEL PILAR ÁVILA OLMEDA\nGOBERNADORA DEL ESTADO\nDE BAJA CALIFORNIA\n(RÚBRICA)\nALFREDO ÁLVAREZ CÁRDENAS\nSECRETARIO GENERAL DE GOBIERNO\nLey de la Juventud del Estado de Baja California. Página 72\nDEL ESTADO DE BAJA CALIFORNIA\n(RÚBRICA)\nLey de la Juventud del Estado de Baja California. Página 73",
  "ordenamiento": "REGLAMENTO",
  "jurisdiccion": "BAJA CALIFORNIA",
  "fuente_oficial": "Periódico Oficial",
  "FECHA PER OFIC": "2025/05/13",
  "ESTATUS": "VIGENTE",
  "TOMO": "TOMO_VI",
  "URL": "https://www.congresobc.gob.mx/Documentos/ProcesoParlamentario/Leyes/TOMO_VI/20250513_LEYJUVENTUD.PDF",
  "es_escaneado": false,
  "tiene_tablas": false,
  "materia": [
    "social",
    "salud",
    "educación",
    "cultura"
  ]
}