{
  "titulo": "Ley PARA PREVENIR y ERRADICAR LA DISCRIMINACIÓN EN EL ESTADO DE BAJA CALIFORNIA",
  "Contenido": ".\nActualización Legislativa.\nÚltima Reforma P.O. No. 60, Índice, 03-Oct-2025\nLEY PARA PREVENIR Y ERRADICAR LA DISCRIMINACIÓN EN EL\nESTADO DE BAJA CALIFORNIA\nPublicada en el Periódico Oficial No. 38, Tomo CXIX, Sección I, de fecha 31 de agosto de 2012\nCAPÍTULO PRIMERO\nDISPOSICIONES GENERALES\nArtículo 1.- Las disposiciones de esta ley son de orden público, de interés social y de observancia general en la entidad.\nArtículo 2.- El objeto de la presente ley es prevenir y erradicar toda forma de discriminación que se ejerza o se pretenda ejercer contra cualquier individuo que habite transitoria o permanentemente en el territorio estatal o se encuentre en tránsito por el mismo. Asimismo, la presente ley promueve la igualdad de oportunidades y de trato, a efecto de que sean reales, efectivas y permanentes las acciones y políticas públicas derivadas del presente ordenamiento.\nArtículo 3.- Corresponde al Estado promover las condiciones para que la libertad y la igualdad de las personas sean reales y efectivas. Los poderes públicos del Estado deberán eliminar aquellos obstáculos que limiten en los hechos su ejercicio e impidan el pleno desarrollo de las personas así como su efectiva participación en la vida política, económica, cultural y social del país y promoverán la participación de las autoridades de los demás órdenes de Gobierno y de los particulares en la eliminación de dichos obstáculos.\nArtículo 4.- Es obligación de todas las autoridades del Estado, en colaboración con los demás entes públicos, garantizar que todas las personas gocen, sin discriminación alguna, de todos los derechos fundamentales reconocidos en la Constitución Política de los\nEstados Unidos Mexicanos, en los tratados internacionales firmados y ratificados por los\nEstados Unidos Mexicanos, en la presente y demás leyes y en general los derechos fundamentales del ser humano.\nArtículo 5.- Queda prohibida toda discriminación motivada por el origen étnico, nacional o regional, el género, la edad, las capacidades diferentes, la condición social o económica, las condiciones de salud, la religión, las opiniones, las preferencias, orientación sexual, identidad y expresiones de género, el estado civil, el trabajo desempeñado, las costumbres, la raza, las ideologías o creencias, o cualquier otra que atente contra la personas.\nPárrafo Reformado\nLey para Prevenir y Erradicar la Discriminación Página 1\n.\nActualización Legislativa.\nÚltima Reforma P.O. No. 60, Índice, 03-Oct-2025\nLos poderes públicos del Estado y los Ayuntamientos implementarán las medidas necesarias para garantizar la igualdad y combatir la discriminación, debiendo garantizar la prevención de conflictos, inhibir la revictimización, prestando especial atención en los derechos de las mujeres, las personas jóvenes, personas con discapacidad, personas adultas mayores, personas integrantes de la diversidad sexual y orientación de género, personas indígenas y comunidades afromexicanas.\nPárrafo Adicionado\nArtículo Reformado\nArtículo 6.- Para los efectos de esta ley se entiende por discriminación toda distinción, exclusión o restricción que, basada en el origen étnico, nacional o regional, el género, la edad, por condición de discapacidad, la condición social o económica, las condiciones de salud física o mental, el embarazo, la lengua, la religión, las opiniones, las preferencias, el estado civil, el trabajo desempeñado, las costumbres, la raza, las ideologías o creencias, o cualquier otra, tenga por efecto impedir, menoscabar o anular el reconocimiento o el ejercicio de los derechos y libertades fundamentales de las personas y la igualdad real de oportunidades de los individuos.\nPárrafo Reformado\nSe considera discriminatoria toda ley o acto que, siendo de aplicación idéntica para todas las personas, produzca consecuencias perjudiciales para las personas en situación de vulnerabilidad.\nTambién se entenderá como discriminación la xenofobia y el antisemitismo en cualquiera de sus manifestaciones.\nDe igual manera, se considera discriminación el prohibir, limitar o restringir el acto de amamantar en espacios públicos.\nPárrafo Adicionado\nArtículo Reformado\nArtículo 7.- No se considerarán conductas discriminatorias las siguientes:\nI. Las acciones legislativas, educativas o de políticas públicas positivas o compensatorias que sin afectar derechos de terceros establezcan tratos diferenciados con el objeto de promover la igualdad real de oportunidades;\nII. Las distinciones basadas en capacidades o conocimientos especializados para desempeñar una actividad determinada;\nIII. La distinción establecida por las instituciones públicas de seguridad social entre sus asegurados y la población en general;\nIV. En el ámbito educativo, los requisitos académicos, pedagógicos y de evaluación;\nV. Las que se establezcan como requisitos de ingreso o permanencia para el desempeño del servicio público y cualquier otro señalado en los ordenamientos legales;\nLey para Prevenir y Erradicar la Discriminación Página 2\n.\nActualización Legislativa.\nÚltima Reforma P.O. No. 60, Índice, 03-Oct-2025\nVI. El trato diferenciado que en su beneficio reciba una persona que padezca alguna enfermedad mental;\nVII.- Las distinciones, exclusiones, restricciones o preferencias que se hagan entre ciudadanos y no ciudadanos, y\nVIII.- En general, todas las que no tengan el propósito de anular o menoscabar los derechos y libertades o la igualdad de oportunidades de las personas ni de atentar contra la dignidad humana.\nCAPÍTULO SEGUNDO\nDE LA APLICACIÓN E INTERPRETACIÓN DE LA LEY\nArtículo 8.- Se instituye como política pública del Gobierno del Estado de Baja\nCalifornia y de todas las autoridades en la entidad, que el principio de igualdad y no discriminación regirá en todas las acciones, medidas y estrategias que implementen en el ámbito de sus respectivas competencias.\nArtículo 9.- Es obligación de las autoridades en la Entidad en el ámbito de sus atribuciones y de las personas servidoras públicas adoptar todas las medidas para el exacto cumplimiento de la presente ley, así como diseñar e instrumentar políticas públicas que tengan como objetivo prevenir y eliminar la discriminación, mismas que se sustentarán en los principios de: a. Igualdad; b. No discriminación; c. Justicia social; d. Reconocimiento de las diferencias; e. Interseccionalidad;\nInciso Adicionado, recorriéndose los subsecuentes f. Respeto a la dignidad; g. Integración en todos los ámbitos de la vida; h. Accesibilidad i. Equidad, y\nArtículo Reformado\nArtículo 10.- Corresponde la aplicación de esta ley:\nInciso Reformado\nLey para Prevenir y Erradicar la Discriminación Página 3\n.\nActualización Legislativa.\nÚltima Reforma P.O. No. 60, Índice, 03-Oct-2025\nb) Al Poder Legislativo del Estado;\nc) Al Tribunal Superior de Justicia del Estado;\nd) A la Secretaría General de Gobierno;\ne) A las Secretarías del Ejecutivo estatal;\nf) A la Fiscalía General del Estado;\nInciso Reformado\ng) A los Ayuntamientos del Estado;\nh) A la Comisión Estatal de los Derechos Humanos; y\nInciso Reformado\ni) A los Organismos Constitucionalmente Autónomos.\nArtículo Reformado\nArtículo 11.- La interpretación del contenido de esta Ley, así como la actuación de las autoridades federales será congruente con los instrumentos internacionales aplicables en materia de discriminación de los que México sea parte, así como con las recomendaciones y resoluciones adoptadas por los organismos multilaterales y regionales y demás legislación aplicable.\nArtículo Reformado\nArtículo 12.- Para los efectos del artículo anterior, cuando se presenten diferentes interpretaciones, se deberá preferir aquella que proteja con mayor eficacia a las personas o a los grupos que sean afectados por conductas discriminatorias.\nArtículo 13.- En la aplicación de la presente ley las autoridades previstas por el\nArtículo 10 del presente ordenamiento, en el ámbito de sus respectivas competencias, deberán tomar en cuenta lo siguiente:\nI. La protección de los derechos fundamentales,\nII. La aplicación de la disposición, tratado internacional, principio que establezca un trato más favorable para las personas, grupos o comunidades en situación de discriminación.\nIII. Las normas de derechos humanos como criterios orientadores de las políticas públicas, programas, planes, estrategias y acciones de la Administración Pública, a efecto de hacerlos más eficaces, sostenibles, no excluyentes y equitativos. la dignidad de todas las personas; y\nIV. Los instrumentos nacionales e internacionales aplicables en materia de derechos humanos y no discriminación firmados y ratificados por los Estados Unidos Mexicanos.\nArtículo Reformado\nLey para Prevenir y Erradicar la Discriminación Página 4\n.\nActualización Legislativa.\nÚltima Reforma P.O. No. 60, Índice, 03-Oct-2025\nArtículo 14.- Las autoridades en el ámbito de sus atribuciones deberán vincular el diseño de las acciones de sus programas y presupuestos, según sea el caso, para el cumplimiento del objeto de esta Ley.\nPara lo anterior deberán, sin menoscabo de otras acciones:\nI. Incorporar en sus programas, actividades y ámbitos de competencia mecanismos que tutelen y garanticen el derecho humano a la igualdad y a la no discriminación;\nII. Aplicar el criterio de interseccionalidad en el diseño y desarrollo de sus programas y actividades para atender de forma simultánea todos los factores identitarios de la discriminación;\nFracción Adicionada, recorriéndose las subsecuentes\nIII. Diseñar y ejecutar programas permanentes de sensibilización e información para todas las personas servidoras públicas sobre el derecho a la igualdad y a la no discriminación; y,\nFracción Reformada\nIV. Las demás que determine la presente ley.\nArtículo Reformado\nCAPÍTULO TERCERO\nDE LA PREVENCIÓN\nArtículo 15.- Ningún órgano público, estatal o municipal, autoridad, servidor público, persona física o moral, realizará actos o desplegará conductas que discriminen a las mujeres, incluyendo, entre otras, las conductas siguientes:\na) Impedir el acceso a la educación, así como a becas e incentivos para la permanencia en los centros educativos;\nb) Establecer contenidos, métodos o instrumentos pedagógicos en que se asignen papeles a hombres y mujeres contrarios a la igualdad, o que difundan una condición de subordinación para éstas;\nc) Prohibir la libre elección de empleo;\nd) Restringir las oportunidades de acceso, permanencia y ascenso en el empleo, especialmente por razón de edad o estado civil;\ne) Establecer diferencias en la remuneración, las prestaciones y las condiciones laborales para trabajo de igual valor;\nf) Limitar el acceso a los programas de capacitación y de formación profesional;\ng) Negar información sobre sus derechos reproductivos o impedir el libre ejercicio de la determinación del número y espaciamiento de los hijos;\nLey para Prevenir y Erradicar la Discriminación Página 5\n.\nActualización Legislativa.\nÚltima Reforma P.O. No. 60, Índice, 03-Oct-2025\nh) Negar o condicionar los servicios de asistencia médica;\ni) Impedir la participación, en condiciones equitativas, en asociaciones civiles, políticas o de cualquier otra índole;\nj) Negar o condicionar el derecho de participación política y, especialmente, el derecho al sufragio activo o pasivo, la elegibilidad y el acceso a cualquier cargo público;\nk) Impedir el ejercicio de sus derechos de propiedad, administración y disposición de bienes, incluyendo los de régimen ejidal y comunal;\nl) Impedir el acceso a la justicia o generar cualquier tipo de violencia contra ellas en las instituciones de seguridad pública y de Justicia;\nm) Aplicar cualquier tipo de uso o costumbre que atente contra su dignidad e integridad;\nn) Impedir la libre elección del cónyuge, y\no) Ofender, ridiculizar, hostigar o promover la violencia en su contra a través de mensajes e imágenes en los medios de comunicación.\nArtículo 16.- Ninguna autoridad estatal o municipal, servidor público, persona física o moral, realizará actos o desplegará conductas que discriminen a las mujeres con motivo del embarazo, incluyendo, entre otras, las siguientes:\na) Ejercer violencia física o moral, contra la mujer, sin demerito de las sanciones administrativas, civiles o penales que procedan;\nb) Restringir, impedir o negar el derecho al trabajo o sujetar, terminar o condicionar la relación laboral por razón del embarazo o solicitar en cualquier momento la realización de pruebas de gravidez;\nc) Restringir, impedir o vedar el acceso a la educación y las instituciones del sistema educativo estatal;\nd) Realizar jornadas nocturnas de trabajo y\ne) Realizar labores que la expongan al contacto con agentes infectocontagiosos o la inhalación de sustancias toxicas volátiles, o laboral en aéreas donde existan emanaciones radioactivas o se tengan conducto con sustancias, materiales o fluidos explosivos o peligrosos.\nArtículo I7.- Ninguna autoridad estatal o municipal, autoridad, servidor público, persona física o moral, realizará actos o desplegará conductas que discriminen a cualquier persona por razón de su edad, incluyendo, entre otras, las conductas siguientes:\nI. Respecto de los menores de edad:\na) Limitar la libre expresión de sus ideas en todos los asuntos que les afecten;\nLey para Prevenir y Erradicar la Discriminación Página 6\n.\nActualización Legislativa.\nÚltima Reforma P.O. No. 60, Índice, 03-Oct-2025\nb) Impedir que se les escuche en todo procedimiento judicial o administrativo en que se vean involucrados;\nc) Restringir el acceso a la información, salvo en aquellos supuestos que sean establecidos por las leyes y reglamentos nacionales, estatales o municipales, o en los ordenamientos jurídicos internacionales para preservar su adecuado desarrollo;\nd) Impedir la libertad de pensamiento, de conciencia o de religión;\ne) Limitar su derecho de asociación;\nf) Negar su derecho a crecer y desarrollarse saludablemente;\ng) Impedir el acceso a la seguridad social y a sus beneficios;\nh) Limitar el derecho a la alimentación, la vivienda, la recreación y los servicios médicos adecuados;\ni) Negar el derecho a una educación gratuita de calidad en los niveles preescolar, primaria, secundaria y media superior;\nj) Impedir el acceso al sistema educativo por enfermedad o discapacidad;\nk) Hacer distinciones en los actos y documentos del Registro Civil, por razón de su filiación;\nl) Explotarlos comercialmente en actividades deportivas de alto rendimiento o en espectáculos;\nm) Promover la violencia en su contra a través de mensajes e imágenes en los medios de comunicación; y\nn) Ofender, ridiculizar, hostigar o promover la violencia en su contra, en razón de su comportamiento, apariencia o discapacidad.\nII. Respecto de las personas adultas mayores de sesenta años:\na) Impedir el acceso al empleo y la permanencia en el mismo, en igualdad de condiciones, salvo en los casos expresamente determinados por la ley;\nb) Impedir el acceso a cualquier servicio público o institución privada que preste servicios al público;\nc) Negar una retribución justa por su contribución laboral en el pasado;\nd) Impedir el acceso a cualquier servicio de salud o tratamiento médico,\ne) Negar el acceso a la educación en cualquier nivel; y\nf) Ofender, ridiculizar, hostigar o promover la violencia en su contra a través de mensajes e imágenes en los medios de comunicación.\nArtículo Reformado\nArtículo 18.- Ninguna autoridad estatal o municipal, autoridad, servidor público, persona física o moral, realizará actos o desplegará conductas que discriminen a cualquier\nLey para Prevenir y Erradicar la Discriminación Página 7\n.\nActualización Legislativa.\nÚltima Reforma P.O. No. 60, Índice, 03-Oct-2025 persona por razón de su origen étnico, nacional, o regional, incluyendo, entre otras, las conductas siguientes:\na) Impedir el acceso a la educación en cualquier nivel;\nb) Negar el acceso o la prestación de cualquier servicio público o que se ofrezca al público, o establecer medidas de diferenciación o segregación en los mismos;\nc) Restringir el uso de su lengua, tanto en actividades públicas como privadas;\nd) Impedir la asignación de nombres en el Registro Civil;\ne) Limitar el derecho de asociación;\nf) Restringir el acceso al empleo, incluidos los empleos calificados y las medidas de promoción y ascenso;\ng) Negar una igual remuneración por un trabajo de igual valor;\nh) Limitar o negar el otorgamiento de concesiones, permisos o autorizaciones para el aprovechamiento, administración o usufructo de recursos naturales, una vez satisfechos los requisitos establecidos en la legislación aplicable;\ni) Negar la prestación de servicios de salud física y mental, así como cualquier servicio público;\nj) Ofender, ridiculizar, hostigar o promover la violencia en su contra a través de mensajes e imágenes en los medios de comunicación.\nArtículo Reformado\nArtículo 19.- Ninguna autoridad estatal o municipal, servidor público, persona física o moral, realizará actos o desplegará conductas que discriminen a persona alguna por padecer cualquier tipo de enfermedad física o mental, incluyendo entre otras, las conductas siguientes:\nPárrafo Reformado\na) Explotar o dar un trato abusivo o degradante;\nb) Impedir la asistencia individual preventiva y el tratamiento de la enfermedad, así como la rehabilitación completa o parcial;\nc) Negar o condicionar cualquier servicio de salud, incluyendo la detección temprana de cualquier tipo de enfermedad, la intervención, el tratamiento, la rehabilitación y el suministro de servicios médicos que aseguren un nivel adecuado para su calidad de vida;\nd) Negar asistencia de calidad a las personas que padezcan alguna infección de tipo psiquiátrico o una enfermedad terminal;\ne) Impedir la participación en las decisiones sobre su tratamiento médico o terapéutico;\nf) Efectuar pruebas de detección de cualquier tipo de enfermedad, sin el previo consentimiento de la persona interesada;\nLey para Prevenir y Erradicar la Discriminación Página 8\n.\nActualización Legislativa.\nÚltima Reforma P.O. No. 60, Índice, 03-Oct-2025\ng) Limitar o negar información sobre el padecimiento;\nh) Suspender la atención médica o el tratamiento, en especial cuando de estos servicios dependa la supervivencia y la calidad de vida de la persona;\ni) Negar el acceso o separar de los centros educativos públicos o privados en cualquier nivel, así como impedir becas o incentivos para la permanencia en los centros educativos o negar el acceso a programas de capacitación y de formación profesional;\nj) Restringir su participación en actividades deportivas, recreativas o culturales;\nk) Aplicar cualquier tipo de uso o costumbre que atente contra su dignidad e integridad;\nInciso Reformado\nl) Ofender, ridiculizar, hostigar o promover la violencia en su contra a través de mensajes o imágenes en los medios de comunicación;\nInciso Reformado\nm) Negar la prestación de servicios financieros a personas por motivo de su condición de salud física o mental;\nInciso Adicionado\nn) Difundir, por cualquier forma o medio de comunicación físico o digital, sin consentimiento de la persona agraviada información sobre su condición y antecedentes de salud física o mental, o sobre cualquier otro dato personal sensible; y,\nInciso Adicionado\nInciso Reformado\no) Estigmatizar y negar derechos a personas por cualquier condición o antecedente de salud física o mental.\nInciso Adicionado\nArtículo Reformado\nArtículo 20.- Ninguna autoridad estatal o municipal, autoridad, servidor público, persona física o moral, realizará actos o desplegará conductas que discriminen a cualquier persona por motivos religiosos ni efectuar, entre otras, las conductas siguientes:\nCoartar la libertad de profesar la religión que se elija;\na) Limitar el acceso y permanencia en cualquier nivel educativo;\nArtículo Reformado\nArtículo 21.- Ninguna autoridad estatal o municipal, autoridad, servidor público, persona física o moral, realizará actos o desplegará conductas que discriminen a cualquier persona por razón de su preferencia, orientación sexual, identidad y expresiones de género, ni efectuar, entre otras, las conductas siguientes:\nPárrafo Reformado\nLey para Prevenir y Erradicar la Discriminación Página 9\n.\nActualización Legislativa.\nÚltima Reforma P.O. No. 60, Índice, 03-Oct-2025 a la persecución o a la exclusión;\nb) Promover el maltrato físico, psicológico o verbal por la apariencia física, forma de vestir, hablar, gesticular o por asumir públicamente su preferencia;\nc) Impedir o negar la prestación de cualquier servicio público, o que se ofrezca al público;\nd) Hostigar, ridiculizar o agredir en toda institución pública;\ne) Impedir o negar la participación en la toma de decisiones de política pública;\nf) Negar cualquier servicio de salud;\ng) Impedir o negar el acceso a la educación en cualquier nivel, a la seguridad social, a las prestaciones, a los créditos y a la vivienda;\nh) Negar o establecer limitaciones en los contratos de prestación de servicios como seguros médicos, arrendamientos inmobiliarios o de otro tipo;\ni) Negar el acceso, permanencia y ascenso en el empleo;\nj) Impedir la participación en asociaciones civiles, políticas o de cualquier otra índole;\nk) Realizar actos que limiten sus derechos de propiedad, de sucesión, administración o disposición de bienes muebles e inmuebles, tanto en régimen de propiedad privada como ejidal o comunal;\nl) Obligar a un tratamiento médico o psiquiátrico;\nm) Promover la violencia en su contra en los centros de detención o reclusión;\nFracción Reformada\nn) Ofender, ridiculizar, hostigar o promover la violencia en su contra a través de los medios de comunicación; y\nFracción Reformada\no) Obligar o someter a una o más personas a tratamientos o terapias de conversión o cualquier otra denominación que se les dé, con la intención de modificar la orientación sexual, identidad o expresión de género.\nFracción Reformada\nArtículo Reformado\nCAPÍTULO CUARTO\nOPORTUNIDADES\nArtículo 22.- Las autoridades estatales o municipales, en el ámbito de su competencia, llevarán a cabo, entre otras, las siguientes medidas positivas y compensatorias a favor de la igualdad de oportunidades para las mujeres:\nI.- Incentivar la educación mixta, fomentando la permanencia en el sistema educativo\nLey para Prevenir y Erradicar la Discriminación Página 10\n.\nActualización Legislativa.\nÚltima Reforma P.O. No. 60, Índice, 03-Oct-2025 de las niñas y las mujeres en todos los niveles escolares;\nII.-Ofrecer información completa y actualizada, así como asesoramiento personalizado sobre salud reproductiva y métodos anticonceptivos;\nIII.- Crear mecanismos que aseguren una mayor presencia de mujeres en todos los puestos administrativos y como candidatas a cargos de elección popular;\nIV.- Garantizar el derecho a decidir sobre el número y espaciamiento de sus hijas e hijos, estableciendo en las instituciones de salud y seguridad social las condiciones para la atención obligatoria de las mujeres que lo soliciten, y\nV.- Procurar la creación de centros de desarrollo infantil y guarderías asegurando el acceso a los mismos para sus hijas e hijos cuando ellas lo soliciten.\nArtículo 23.- Las autoridades estatales o municipales en el ámbito de su competencia, llevarán a cabo, entre otras, las siguientes medidas positivas y compensatorias a favor de la igualdad de oportunidades para las mujeres embarazadas:\na) Facilitar el acceso a las instituciones de protección de la salud para la realización de consultas médicas, exámenes de laboratorio y ultrasonido, atención ginecológica, orientación psicológica y psiquiátrica, orientación nutricional y, en general, las atenciones y cuidados médicos necesarios, de conformidad con la Ley de Salud Pública para el Estado;\nb) Disfrutar de estabilidad en el empleo, cargo u ocupación que desarrolle;\nc) Acceder a las oportunidades de empleo en igualdad de condiciones con los varones y con las mujeres que no estén embarazadas;\nd) Acceder a los servicios de orientación y de asesoría legal en las instituciones públicas estatales, conforme a la materia de los derechos que pretenda ejercer;\ne) Acceder en forma preferente al disfrute de los beneficios de los programas sociales del Gobierno del Estado, sin demérito de los derechos de otras personas en condiciones de vulnerabilidad social.\nArtículo 24.- Las autoridades estatales o municipales, en el ámbito de su competencia, llevarán a cabo, entre otras, las siguientes medidas positivas y compensatorias a favor de la igualdad de oportunidades de las niñas y los niños:\nI. Instrumentar programas de atención médica y sanitaria para combatir la mortalidad y la desnutrición infantiles;\nII. Impartir educación para la preservación de la salud, el conocimiento integral de la sexualidad, la planificación familiar, la paternidad responsable y el respeto a los derechos supervisión de sus padres;\nIII. Promover el acceso a centros de desarrollo infantil, incluyendo a menores con discapacidad;\nLey para Prevenir y Erradicar la Discriminación Página 11\n.\nActualización Legislativa.\nÚltima Reforma P.O. No. 60, Índice, 03-Oct-2025\nIV. Promover las condiciones necesarias para que los menores puedan convivir con sus padres o tutores, incluyendo políticas públicas de reunificación familiar para migrantes y personas privadas de la libertad;\nV. Preferir, en igualdad de circunstancias, a las personas que tengan a su cargo menores de edad en el otorgamiento de becas, créditos u otros beneficios;\nVI. Alentar la producción y difusión de libros para niños y niñas;\nVII. Promover la creación de instituciones que tutelen a los menores privados de su medio familiar, incluyendo hogares de guarda y albergues para estancias temporales;\nVIII. Promover la recuperación física, psicológica y la integración social de todo menor víctima de abandono, explotación, malos tratos o conflictos armados,\nIX. Proporcionar, en los términos de la legislación en la materia, asistencia legal y psicológica gratuita e intérprete en los procedimientos judiciales o administrativos, en que sea procedente, y\nX. Promover campañas de prevención de la violencia infantil, para garantizar la protección contra abusos sexuales, el derecho a la propia identidad, la libertad y la seguridad personal.\nArtículo Reformado\nArtículo 25.- Las autoridades estatales o municipales, en el ámbito de su competencia, llevarán a cabo, entre otras, las siguientes medidas positivas y compensatorias a favor de la igualdad de oportunidades de las y los jóvenes:\nI. Prevenir, atender y disminuir los factores de riesgo a los que están expuestos las personas jóvenes, generando condiciones para el ejercicio de sus derechos y su pleno desarrollo;\nII. Crear programas de capacitación para el empleo, para la inserción en el mercado laboral de jóvenes estudiantes o personas recién egresadas, y para la permanencia y ascenso en el trabajo, así como para la creación de empresas;\nIII. Eliminar la violencia laboral y discriminación ejercida hacia la población juvenil;\nIV. Fomentar las actividades deportivas y crear espacios accesibles y públicos para la realización de dichas actividades;\nV. Ofrecer información completa y actualizada, así como asesoramiento personalizado y educación sobre salud, salud sexual y reproductiva, incluyendo VIH, Sida e infecciones de transmisión sexual, con respeto a la edad, identidad, intimidad, libertad y seguridad personal de las y los jóvenes;\nVI. Fortalecer los servicios médicos de salud sexual y salud reproductiva, considerando la accesibilidad, calidad y disponibilidad de métodos anticonceptivos para las y los jóvenes;\nLey para Prevenir y Erradicar la Discriminación Página 12\n.\nActualización Legislativa.\nÚltima Reforma P.O. No. 60, Índice, 03-Oct-2025\nVII. Dar atención prioritaria a jóvenes embarazadas en todo lo relacionado con salud sexual, reproductiva, materna y perinatal;\nVIII. Generar programas y acciones de información, educación y asesoría relativa al derecho a la libre elección de cónyuges, así como a la prevención y atención de la violencia en la pareja y en su caso escuela para padres;\nIX. Garantizar el acceso a programas para la detección temprana y el tratamiento de las adicciones causadas por el consumo de estupefacientes, sustancias psicotrópicas y otras susceptibles de producir dependencia;\nX. Promover y difundir su participación informada en los asuntos públicos;\nXI. Aumentar y mejorar los mecanismos de participación, autonomía, e incidencia efectivos, de acceso a la información y la libertad de expresión de las y los jóvenes.\nXII. Fomentar e incentivar sus expresiones culturales en todas sus manifestaciones, así como fomentar el respeto a las mismas; y\nXIII. Promover campañas de prevención de la violencia juvenil, para garantizar la protección contra abusos sexuales, la libre manifestación de las ideas, el derecho a la propia identidad, la libertad y la seguridad personal.\nArtículo 26.- Las autoridades estatales o municipales, en el ámbito de su competencia, llevarán a cabo, entre otras, las siguientes medidas positivas y compensatorias a favor de la igualdad de oportunidades para las personas mayores de sesenta años:\nI. Garantizar el acceso a los servicios de atención médica y seguridad social, según lo dispuesto en la normatividad en la materia;\nII. Procurar un nivel mínimo y decoroso de ingresos a través de programas, conforme a las reglas de operación que al efecto se establezcan:\na) De apoyo financiero directo y ayudas en especie y\nb) De capacitación para el trabajo y de fomento a la creación de empleos, y\nIII. Garantizar, conforme a la legislación aplicable, asesoría jurídica gratuita así como la asistencia de un representante legal cuando el afectado lo requiera.\nArtículo Reformado\nArtículo 27.- Las autoridades estatales o municipales, en el ámbito de su competencia, llevarán a cabo, entre otras, las siguientes medidas positivas y compensatorias a favor de la igualdad de oportunidades para las personas con discapacidad:\nI. Promover un entorno que permita el libre acceso y desplazamiento;\nII. Procurar su incorporación, permanencia y participación en las actividades educativas regulares en todos los niveles;\nLey para Prevenir y Erradicar la Discriminación Página 13\n.\nActualización Legislativa.\nÚltima Reforma P.O. No. 60, Índice, 03-Oct-2025\nIII. Promover el otorgamiento, en los niveles de educación obligatoria, de las ayudas técnicas necesarias para cada discapacidad;\nIV. Crear programas permanentes de capacitación para el empleo y fomento a la integración laboral;\nV. Crear espacios de recreación adecuados;\nVI. Procurar la accesibilidad en los medios de transporte público de uso general;\nVII. Promover que todos los espacios e inmuebles públicos o que presten servicios al público, tengan las adecuaciones físicas y de señalización para su acceso, libre desplazamiento y uso;\nVIII. Procurar que las vías generales de comunicación cuenten con señalamientos adecuados para permitirles el libre tránsito;\nIX. Informar y asesorar a los profesionales de la construcción acerca de los requisitos para facilitar el acceso y uso de inmuebles, y\nX. Promover que en las unidades del sistema nacional de salud y de seguridad social reciban regularmente el tratamiento y medicamentos necesarios para mantener y aumentar su capacidad funcional y su calidad de vida.\nArtículo 28.- Las autoridades estatales o municipales, en el ámbito de su competencia, llevarán a cabo, entre otras, las siguientes medidas positivas y compensatorias a favor de la igualdad de oportunidades para la población indígena:\nI. Crear programas permanentes de capacitación y actualización para los funcionarios públicos sobre la diversidad cultural;\nII. Emprender campañas permanentes de información en los medios de comunicación que promuevan el respeto a las culturas indígenas en el marco de los derechos humanos y las garantías individuales;\nIII. En el marco de las leyes aplicables, cuando se fijen sanciones penales a indígenas, procurar que tratándose de penas alternativas, se imponga aquella distinta a la privativa de la libertad, así como promover la aplicación de sustitutivos penales y beneficios de pre liberación, de conformidad con las normas aplicables.\nIV. Garantizar que en todos los juicios y procedimientos en que sean parte, individual o colectivamente, se tomen en cuenta sus costumbres y especificidades culturales, respetando los preceptos de la Constitución, y\nV. Garantizar, a lo largo de cualquier proceso legal, el derecho a ser asistidos, si así lo solicitan, por intérpretes y defensores que tengan conocimiento de su lengua.\nArtículo 29.- Las autoridades estatales o municipales, en el ámbito de su competencia, llevarán a cabo, entre otras, las siguientes medidas positivas y compensatorias a favor de la igualdad de oportunidades para las personas migrantes:\nLey para Prevenir y Erradicar la Discriminación Página 14\n.\nActualización Legislativa.\nÚltima Reforma P.O. No. 60, Índice, 03-Oct-2025\nI. Revisar y en su caso corregir las prácticas de las y los funcionados públicos que prestan la atención a las personas migrantes, refugiadas y solicitantes de asilo, que pueden consistir en un trato indigno o en la petición de documentos de identificación diferentes al pasaporte y la forma migratoria a fin de prevenir y eliminar conductas discriminatorias y la limitación o negación al acceso a los programas y servicios;\nII. Diseñar, implementar y evaluar tanto el programa como las campañas de difusión para la prevención y atención relacionadas con la trata de personas y la explotación sexual que sufran las personas migrantes;\nCAPÍTULO QUINTO\nDE LA COMISIÓN ESTATAL DE LOS DERECHOS HUMANOS DE BAJA CALIFORNIA\nDenominación Modificada\nArtículo 30.- Corresponde a la Comisión Estatal de los Derechos Humanos de Baja\nCalifornia, prevenir toda forma de discriminación e intolerancia y promover las políticas públicas para la igualdad de oportunidades y de trato a favor de todas las personas.\nPárrafo Reformado\nLos procedimientos para el cumplimiento de la presente ley se ceñirán a los establecidos para la actuación de la Comisión Estatal de los Derechos Humanos de Baja\nCalifornia, en el ordenamiento que la rige.\nPárrafo Reformado\nCompete a la Comisión Estatal de los Derechos Humanos de Baja California, integrar y resolver los expedientes de queja o denuncias sobre la materia, con base en sus atribuciones, principios y procedimientos, proporcionando además, la asesoría necesaria y suficiente y los medios idóneos para hacer prevalecer el respeto a los derechos y libertades consagrados en la Constitución Política de los Estados Unidos Mexicanos.\nPárrafo Reformado\nEn caso de que las conductas o prácticas discriminatorias sean imputables a los particulares, personas físicas o morales, la Comisión Estatal de los Derechos Humanos, desplegará su procedimiento de investigación y atención de quejas, con el señalamiento de que el presente ordenamiento es obligatorio para toda persona y no sólo para los órganos públicos, autoridades o servidores públicos. Al efecto, la Comisión Estatal de los Derechos\nHumanos de Baja California, podrá concluir el procedimiento con la formulación de la recomendación procedente.\nPárrafo Reformado\nArtículo Reformado\nArtículo 31.- La Comisión Estatal de los Derechos Humanos de Baja California, independientemente de sus funciones, ejercerá las acciones necesarias en torno a la prevención y eliminación de toda forma de discriminación o intolerancia, debiendo integrar en forma sistemática la información sobre los fenómenos, prácticas y actos discriminatorios.\nPárrafo Reformado\nLey para Prevenir y Erradicar la Discriminación Página 15\n.\nActualización Legislativa.\nÚltima Reforma P.O. No. 60, Índice, 03-Oct-2025\nEn particular la Comisión Estatal de los Derechos Humanos, tendrá las siguientes atribuciones en la materia:\nPárrafo Reformado\na) Elaborar, fomentar y difundir estudios sobre prácticas discriminatorias;\nb) Realizar estudios sobre ordenamientos jurídicos vigentes y alentar la formulación de iniciativas para la modificación de los preceptos que estime contrarios al tercer párrafo del artículo 1º de la Constitución Política de los Estados Unidos Mexicanos;\nc) Difundir y promover contenidos para prevenir y eliminar las prácticas discriminatorias en cualquier orden;\nd) Conocer e investigar presuntos actos o prácticas discriminatorias;\ne) Tutelar los derechos de las personas o grupos que sufran discriminación, brindando asesoría y todo tipo de ayuda a su alcance; asimismo, proponer a las partes la conciliación, cuando estime que así proceda; y\nf) Solicitar a cualquier institución pública o a los particulares, la información necesaria para verificar el cumplimiento de esta ley.\nArtículo Reformado\nArtículo 32.- La Comisión Estatal de los Derechos Humanos proporcionará a las personas que presuntamente hayan sido discriminadas, asesoría respecto de los derechos que les asisten y los medios para hacerlos valer.\nPárrafo Reformado\nSiempre que las partes en conflicto manifiesten su conformidad, se procurará la conciliación de intereses.\nLa conciliación no estará sujeta a formalidad alguna, pudiéndose celebrar mediante convenio.\nEn caso de no prosperar la conciliación, se continuará la investigación hasta su conclusión, procediéndose conforme a la Ley de la Comisión Estatal de los Derechos\nHumanos de Baja California.\nPárrafo Reformado\nArtículo Reformado\nCAPITULO SEXTO\nDE LAS MEDIDAS ADMINISTRATIVAS.\nArtículo 33.- La Comisión Estatal de los Derechos Humanos de Baja California, discriminación:\nPárrafo Reformado\nLey para Prevenir y Erradicar la Discriminación Página 16\n.\nActualización Legislativa.\nÚltima Reforma P.O. No. 60, Índice, 03-Oct-2025\na) La impartición, a las personas o a las instituciones que sean objeto de una recomendación, de cursos o seminarios que promuevan la igualdad de oportunidades;\nb) La fijación de carteles en cualquier establecimiento de quienes incumplan alguna disposición de esta ley, en los que se promueva la modificación de las conductas discriminatorias, además de su publicación y difusión en el sitio de internet, las redes sociales y las plataformas digitales oficiales de la Comisión;\nInciso Reformado\nc) La presencia del personal de la Comisión para promover y verificar la adopción de medidas a favor de la igualdad de oportunidades y la eliminación de toda forma de discriminación en cualquier establecimiento de quienes sean objeto de una disposición, por el tiempo que disponga la determinación correspondiente;\nInciso Reformado\nd) La publicación íntegra de la recomendación emitida en el órgano de difusión de la Comisión; y\nInciso Reformado\ne) La publicación o difusión de una síntesis de la recomendación en los medios impresos o electrónicos de comunicación.\nArtículo Reformado\nArtículo 34.- Para determinar el alcance y la forma de adopción de las medidas administrativas dispuestas por la Comisión, se tendrán en consideración:\nPárrafo Reformado\na) El carácter intencional de la conducta discriminatoria;\nb) La gravedad del hecho, el acto, la práctica o el fenómeno discriminatorio; y\nc) La reincidencia.\nSe entiende que existe reincidencia cuando la misma persona incurra en dos o más violaciones en el transcurso de un año a la prohibición de discriminar. El plazo se contará a partir del día de la publicación de la recomendación correspondiente.\nArtículo Reformado\nArtículo 35.- La Comisión Estatal de los Derechos Humanos de Baja California, podrá otorgar un reconocimiento a las instituciones públicas o privadas, así como a los particulares sus prácticas, instrumentos organizativos y presupuestos.\nPárrafo Reformado interesada.\nEl reconocimiento será de carácter honorífico y tendrá una vigencia de un año.\nArtículo Reformado\nLey para Prevenir y Erradicar la Discriminación Página 17\n.\nActualización Legislativa.\nÚltima Reforma P.O. No. 60, Índice, 03-Oct-2025\nARTÍCULOS TRANSITORIOS\nPRIMERO.- La presente Ley entrará en vigor al día siguiente de su publicación en el\nPeriódico Oficial del Estado de Baja California.\nSEGUNDO.- Las autoridades previstas por esta Ley deberán adecuar sus normatividades internas conformes a las prevenciones de este ordenamiento.\nDADO en el Salón de Sesiones “Lic. Benito Juárez García” del H. Poder Legislativo del Estado de Baja California, en la Ciudad de Mexicali, B.C., a los catorce días del mes de agosto del año dos mil doce.\nDIP. ALFONSO GARZÓN ZATARAIN\nPRESIDENTE\n(RÚBRICA)\nDIP. FAUSTO ZÁRATE ZEPEDA\nSECRETARIO\n(RÚBRICA)\nDE CONFORMIDAD CON LO DISPUESTO POR LA FRACCIÓN I DEL ARTÍCULO 49\nMEXICALI, BAJA CALIFORNIA, A LOS VEINTIÚN DÍAS DEL MES DE AGOSTO DEL\nAÑO DOS MIL DOCE.\nGOBERNADOR DEL ESTADO\nJOSÉ GUADALUPE OSUNA MILLÁN\n(RÚBRICA)\nSECRETARIO GENERAL DE GOBIERNO\nFRANCISCO ANTONIO GARCÍA BURGOS\n(RÚBRICA)\nLey para Prevenir y Erradicar la Discriminación Página 18\n.\nActualización Legislativa.\nÚltima Reforma P.O. No. 60, Índice, 03-Oct-2025\nArtículo 5.- Fue reformado mediante Decreto No. 75, publicado en el Periódico Oficial\nNo. 11, de fecha 11 de febrero de 2022, Tomo CXXIX, Sección IV, expedido por la H. XXIV\nLegislatura, siendo Gobernadora Constitucional la C. Marina del Pilar Ávila Olmeda 20212027; fue reformado mediante Decreto No. 87, publicado en el Periódico Oficial No. 25, Índice, de fecha 25 de abril de 2025, Tomo CXXXII, expedido por la H. XXV Legislatura, siendo Gobernadora Constitucional la C. Marina del Pilar Ávila Olmeda 2021-2027;\nArtículo 6.- Fue reformado mediante Decreto No. 75, publicado en el Periódico Oficial\nNo. 11, de fecha 11 de febrero de 2022, Tomo CXXIX, Sección IV, expedido por la H. XXIV\nLegislatura, siendo Gobernadora Constitucional la C. Marina del Pilar Ávila Olmeda 20212027; fue reformado mediante Decreto No. 159, publicado en el Periódico Oficial No. 66, de fecha 11 de noviembre de 2022, Tomo CXXIX, Índice, expedido por la H. XXIV Legislatura, siendo Gobernadora Constitucional la C. Marina del Pilar Ávila Olmeda 2021-2027; fue reformado por Decreto No. 309, publicado en el Periódico Oficial No. 62, de fecha 06 de noviembre de 2023, Índice, Tomo CXXX, expedido por la H. XXIV Legislatura, siendo\nGobernadora Constitucional la C. Marina del Pilar Ávila Olmeda 2021-2027;\nArtículo 9.- Fue reformado por Decreto No. 426, publicado en el Periódico Oficial No.\n23, de fecha 07 de mayo de 2024, Índice, Tomo CXXXI, expedido por la H. XXIV Legislatura, siendo Gobernadora Constitucional la C. Marina del Pilar Ávila Olmeda 2021-2027;\nArtículo 10.- Fue reformado mediante Decreto No. 359, publicado en el Periódico\nOficial No. 53, de fecha 20 de noviembre de 2015, Tomo CXXII, Sección I, expedido por la\nH. XXI Legislatura, siendo Gobernador Constitucional el C. Francisco Arturo Vega de\nLamadrid 2013-2019; fue reformado mediante Decreto No. 75, publicado en el Periódico\nOficial No. 11, de fecha 11 de febrero de 2022, Tomo CXXIX, Sección IV, expedido por la H.\nXXIV Legislatura, siendo Gobernadora Constitucional la C. Marina del Pilar Ávila Olmeda\n2021-2027;\nArtículo 11.- Fue modificado por Fe de Erratas, publicada en el Periódico Oficial No.\n48, de fecha 26 de octubre de 2012, Sección II, Tomo CXIX, expedida por la H. XX\nLegislatura, siendo Gobernador Constitucional el C. José Guadalupe Osuna Millán 20072013;\nArtículo 13.- Fue modificado por Fe de Erratas, publicada en el Periódico Oficial No.\nLegislatura, siendo Gobernador Constitucional el C. José Guadalupe Osuna Millán 20072013;\nArtículo 14.- Fue reformado por Decreto No. 426, publicado en el Periódico Oficial No. siendo Gobernadora Constitucional la C. Marina del Pilar Ávila Olmeda 2021-2027;\nLey para Prevenir y Erradicar la Discriminación Página 19\n.\nActualización Legislativa.\nÚltima Reforma P.O. No. 60, Índice, 03-Oct-2025\nArtículo 17.- Fue modificado por Fe de Erratas, publicada en el Periódico Oficial No.\n48, de fecha 26 de octubre de 2012, Sección II, Tomo CXIX, expedida por la H. XX\nLegislatura, siendo Gobernador Constitucional el C. José Guadalupe Osuna Millán 20072013;\nArtículo 18.- Fue modificado por Fe de Erratas, publicada en el Periódico Oficial No.\n48, de fecha 26 de octubre de 2012, Sección II, Tomo CXIX, expedida por la H. XX\nLegislatura, siendo Gobernador Constitucional el C. José Guadalupe Osuna Millán 20072013;\nArtículo 19.- Fue reformado por Decreto No. 309, publicado en el Periódico Oficial No. 62, de fecha 06 de noviembre de 2023, Índice, Tomo CXXX, expedido por la H. XXIV Legislatura, siendo Gobernadora Constitucional la C. Marina del Pilar Ávila Olmeda 2021-2027; fue reformado por Decreto No. 80, publicado en el Periódico Oficial No. 22, Índice, de fecha 11 de abril de 2025, Tomo CXXXII,expedido por la H. XXV Legislatura, siendo Gobernadora\nConstitucional la C. Marina del Pilar Ávila Olmeda 2021-2027;\nArtículo 20.- Fue modificado por Fe de Erratas, publicada en el Periódico Oficial No.\n48, de fecha 26 de octubre de 2012, Sección II, Tomo CXIX, expedida por la H. XX\nLegislatura, siendo Gobernador Constitucional el C. José Guadalupe Osuna Millán 20072013;\nArtículo 21.- Fue modificado por Fe de Erratas, publicada en el Periódico Oficial No.\n48, de fecha 26 de octubre de 2012, Sección II, Tomo CXIX, expedida por la H. XX\nLegislatura, siendo Gobernador Constitucional el C. José Guadalupe Osuna Millán 20072013; fue reformado mediante Decreto No. 75, publicado en el Periódico Oficial No. 11, de fecha 11 de febrero de 2022, Tomo CXXIX, Sección IV, expedido por la H. XXIV Legislatura, siendo Gobernadora Constitucional la C. Marina del Pilar Ávila Olmeda 2021-2027; fue reformado mediante Decreto No. 109, publicado en el Periódico Oficial No. 37, de fecha 03 de junio de 2022, Tomo CXXIX, Sección V, expedido por la H. XXIV Legislatura, siendo\nGobernadora Constitucional la C. Marina del Pilar Ávila Olmeda 2021-2027;\nArtículo 24.- Fue modificado por Fe de Erratas, publicada en el Periódico Oficial No.\n48, de fecha 26 de octubre de 2012, Sección II, Tomo CXIX, expedida por la H. XX\nLegislatura, siendo Gobernador Constitucional el C. José Guadalupe Osuna Millán 20072013;\nArtículo 26.- Fue modificado por Fe de Erratas, publicada en el Periódico Oficial No.\nLegislatura, siendo Gobernador Constitucional el C. José Guadalupe Osuna Millán 20072013;\nFue modificada la denominación de este Capítulo Quinto mediante Decreto No. 359,\nSección I, expedido por la H. XXI Legislatura, siendo Gobernador Constitucional el C.\nLey para Prevenir y Erradicar la Discriminación Página 20\n.\nActualización Legislativa.\nÚltima Reforma P.O. No. 60, Índice, 03-Oct-2025\nFrancisco Arturo Vega de Lamadrid 2013-2019; fue modificada la denominación mediante\nDecreto No. 75, publicado en el Periódico Oficial No. 11, de fecha 11 de febrero de 2022, Tomo CXXIX, Sección IV, expedido por la H. XXIV Legislatura, siendo Gobernadora\nConstitucional la C. Marina del Pilar Ávila Olmeda 2021-2027;\nCAPÍTULO QUINTO\nDE LA COMISIÓN ESTATAL DE LOS DERECHOS HUMANOS\nArtículo 30.- Fue reformado mediante Decreto No. 359, publicado en el Periódico\nOficial No. 53, de fecha 20 de noviembre de 2015, Tomo CXXII, Sección I, expedido por la\nH. XXI Legislatura, siendo Gobernador Constitucional el C. Francisco Arturo Vega de\nLamadrid 2013-2019; fue reformado mediante Decreto No. 75, publicado en el Periódico\nOficial No. 11, de fecha 11 de febrero de 2022, Tomo CXXIX, Sección IV, expedido por la H.\nXXIV Legislatura, siendo Gobernadora Constitucional la C. Marina del Pilar Ávila Olmeda\n2021-2027;\nArtículo 31.- Fue modificado por Fe de Erratas, publicada en el Periódico Oficial No.\n48, de fecha 26 de octubre de 2012, Sección II, Tomo CXIX, expedida por la H. XX\nLegislatura, siendo Gobernador Constitucional el C. José Guadalupe Osuna Millán 20072013; fue reformado mediante Decreto No. 359, publicado en el Periódico Oficial No. 53, de fecha 20 de noviembre de 2015, Tomo CXXII, Sección I, expedido por la H. XXI Legislatura, siendo Gobernador Constitucional el C. Francisco Arturo Vega de Lamadrid 2013-2019; fue reformado mediante Decreto No. 75, publicado en el Periódico Oficial No. 11, de fecha 11 de febrero de 2022, Tomo CXXIX, Sección IV, expedido por la H. XXIV Legislatura, siendo\nGobernadora Constitucional la C. Marina del Pilar Ávila Olmeda 2021-2027;\nArtículo 32.- Fue modificado por Fe de Erratas, publicada en el Periódico Oficial No.\n48, de fecha 26 de octubre de 2012, Sección II, Tomo CXIX, expedida por la H. XX\nLegislatura, siendo Gobernador Constitucional el C. José Guadalupe Osuna Millán 20072013; fue reformado mediante Decreto No. 359, publicado en el Periódico Oficial No. 53, de fecha 20 de noviembre de 2015, Tomo CXXII, Sección I, expedido por la H. XXI Legislatura, siendo Gobernador Constitucional el C. Francisco Arturo Vega de Lamadrid 2013-2019; fue reformado mediante Decreto No. 75, publicado en el Periódico Oficial No. 11, de fecha 11 de febrero de 2022, Tomo CXXIX, Sección IV, expedido por la H. XXIV Legislatura, siendo\nGobernadora Constitucional la C. Marina del Pilar Ávila Olmeda 2021-2027;\nArtículo 33.- Fue reformado mediante Decreto No. 359, publicado en el Periódico\nH. XXI Legislatura, siendo Gobernador Constitucional el C. Francisco Arturo Vega de\nLamadrid 2013-2019; fue reformado mediante Decreto No. 75, publicado en el Periódico\nXXIV Legislatura, siendo Gobernadora Constitucional la C. Marina del Pilar Ávila Olmeda\n2021-2027; fue reformado mediante Decreto No. 141, publicado en el Periódico Oficial No.\nLey para Prevenir y Erradicar la Discriminación Página 21\n.\nActualización Legislativa.\nÚltima Reforma P.O. No. 60, Índice, 03-Oct-2025\nLegislatura, siendo Gobernadora Constitucional la C. Marina del Pilar Ávila Olmeda 20212027;\nArtículo 34.- Fue reformado mediante Decreto No. 359, publicado en el Periódico\nOficial No. 53, de fecha 20 de noviembre de 2015, Tomo CXXII, Sección I, expedido por la\nH. XXI Legislatura, siendo Gobernador Constitucional el C. Francisco Arturo Vega de\nLamadrid 2013-2019;\nArtículo 35.- Fue reformado mediante Decreto No. 359, publicado en el Periódico\nH. XXI Legislatura, siendo Gobernador Constitucional el C. Francisco Arturo Vega de\nLamadrid 2013-2019; fue reformado mediante Decreto No. 75, publicado en el Periódico\nXXIV Legislatura, siendo Gobernadora Constitucional la C. Marina del Pilar Ávila Olmeda\n2021-2027;\nLey para Prevenir y Erradicar la Discriminación Página 22\n.\nActualización Legislativa.\nÚltima Reforma P.O. No. 60, Índice, 03-Oct-2025\nFE DE ERRATAS AL DECRETO No. 254, PUBLICADA EN EL PERIÓDICO OFICIAL\nNo. 48, SECCION II, DE FECHA 26 DE OCTUBRE DE 2012.\nMexicali, Baja California, a 25 de septiembre de 2012\nALFONSO GARZÓN ZATARAÍN\nPRESIDENTE\n(RÚBRICA)\nFAUSTO ZÁRATE ZEPEDA\nSECRETARIO\n(RÚBRICA)\nARTÍCULO PRIMERO TRANSITORIO DEL DECRETO No. 359, POR EL QUE SE\nREFORMA EL ARTÍCULO 10, LA DENOMINACIÓN DEL CAPÍTULO QUINTO, ASÍ COMO\nLOS ARTÍCULOS 30, 31, 32, 33, 34 Y 35; PUBLICADO EN EL PERIÓDICO OFICIAL No.\n53, SECCIÓN I, TOMO CXXII, DE FECHA 20 DE NOVIEMBRE DE 2015, EXPEDIDO POR\nLA H. XXI LEGISLATURA, SIENDO GOBERNADOR CONSTITUCIONAL EL C.\nFRANCISCO ARTURO VEGA DE LA MADRID 2013-2019.\nÚNICO.- Las presentes reformas entrarán en vigor al día siguiente de su publicación en el Periódico Oficial del Estado de Baja California.\nDADO en el Salón de Sesiones “Lic. Benito Juárez García” del H. Poder Legislativo del Estado de Baja California, en la Ciudad de Mexicali, B.C., a los veintidós días del mes de octubre del año dos mil quince.\nDIP. IRMA MARTÍNEZ MANRÍQUEZ\nPRESIDENTA\n(RÚBRICA)\nDIP. MARIO OSUNA JIMÉNEZ\nSECRETARIO\n(RÚBRICA)\nDE CONFORMIDAD CON LO DISPUESTO POR LA FRACCIÓN I DEL ARTÍCULO 49\nMEXICALI, BAJA CALIFORNIA, A LOS TREINTA DÍAS DEL MES DE OCTUBRE\nDEL AÑO DOS MIL QUINCE.\nFRANCISCO ARTURO VEGA DE LAMADRID\nGOBERNADOR DEL ESTADO\n(RÚBRICA)\nLey para Prevenir y Erradicar la Discriminación Página 23\n.\nActualización Legislativa.\nÚltima Reforma P.O. No. 60, Índice, 03-Oct-2025\nFRANCISCO RUEDA GÓMEZ\nSECRETARIO GENERAL DE GOBIERNO\n(RÚBRICA)\nARTÍCULO SEXTO TRANSITORIO DEL DECRETO No. 75, POR EL QUE SE\nREFORMAN LOS ARTÍCULOS 5, 6, 10, 21, 30, 31, 32, 33, 35, ASÍ COMO EL CAMBIO DE\nDOMINACIÓN AL CAPÍTULO QUINTO; PUBLICADO EN EL PERIÓDICO OFICIAL No. 11,\nSECCIÓN IV, TOMO CXXIX, DE FECHA 11 DE FEBRERO DE 2022, EXPEDIDO POR LA\nH. XXIV LEGISLATURA, SIENDO GOBERNADORA CONSTITUCIONAL LA C. MARINA\nDEL PILAR ÁVILA OLMEDA 2021-2027.\nTRANSITORIOS\nÚNICO. El presente Decreto entrará en vigor al día siguiente de su publicación en el\nPeriódico Oficial del Estado.\nDADO en Sesión Ordinaria Virtual de la XXIV Legislatura en la Ciudad de Mexicali, B.C., a los veintisiete días del mes de enero del año dos mil veintidós.\nDIP. JUAN MANUEL MOLINA GARCÍA\nPRESIDENTE\n(RÚBRICA)\nDIP. ARACELI GERALDO NÚÑEZ\nSECRETARIA\n(RÚBRICA)\nDE CONFORMIDAD CON LO DISPUESTO POR LA FRACCIÓN I DEL ARTÍCULO 49\nCALIFORNIA, IMPRÍMASE Y PUBLÍQUESE.\nMEXICALI, BAJA CALIFORNIA, A LOS DOS DÍAS DEL MES DE FEBRERO DEL\nAÑO DOS MIL VEINTIDÓS.\nMARINA DEL PILAR ÁVILA OLMEDA\nGOBERNADORA DEL ESTADO\nDE BAJA CALIFORNIA\n(RÚBRICA)\nCATALINO ZAVALA MÁRQUEZ\nSECRETARIO GENERAL DE GOBIERNO\nDEL ESTADO DE BAJA CALIFORNIA\n(RÚBRICA)\nLey para Prevenir y Erradicar la Discriminación Página 24\n.\nActualización Legislativa.\nÚltima Reforma P.O. No. 60, Índice, 03-Oct-2025\nARTÍCULO SEGUNDO TRANSITORIO DEL DECRETO No. 109, POR EL QUE SE\nREFORMA EL ARTÍCULO 21; PUBLICADO EN EL PERIÓDICO OFICIAL No. 37, SECCIÓN\nV, TOMO CXXIX, DE FECHA 03 DE JUNIO DE 2022, EXPEDIDO POR LA H. XXIV\nLEGISLATURA, SIENDO GOBERNADORA CONSTITUCIONAL LA C. MARINA DEL PILAR\nÁVILA OLMEDA 2021-2027.\nTRANSITORIOS\nÚNICO. El presente Decreto entrará en vigor al día siguiente al de su publicación en el\nPeriódico Oficial del Estado.\nDADO en Sesión Ordinaria Virtual de la XXIV Legislatura en la Ciudad de Mexicali, B.C., a los veintiséis días del mes de mayo del año dos mil veintidós.\nDIP. JULIA ANDREA GONZÁLEZ QUIROZ\nPRESIDENTA\n(RÚBRICA)\nDIP. MANUEL GUERRERO LUNA\nSECRETARIO\n(RÚBRICA)\nDE CONFORMIDAD CON LO DISPUESTO POR LA FRACCIÓN I DEL ARTÍCULO 49\nCALIFORNIA, IMPRÍMASE Y PUBLÍQUESE.\nMEXICALI, BAJA CALIFORNIA, A LOS TREINTA DÍAS DEL MES DE MAYO DEL\nAÑO DOS MIL VEINTIDÓS.\nMARINA DEL PILAR ÁVILA OLMEDA\nGOBERNADORA DEL ESTADO\nDE BAJA CALIFORNIA\n(RÚBRICA)\nCATALINO ZAVALA MÁRQUEZ\nSECRETARIO GENERAL DE GOBIERNO\nDEL ESTADO DE BAJA CALIFORNIA\n(RÚBRICA)\nARTÍCULO ÚNICO TRANSITORIO DEL DECRETO No. 159, POR EL QUE SE\nREFORMA EL ARTÍCULO 6; PUBLICADO EN EL PERIÓDICO OFICIAL No. 66, ÍNDICE, Ley para Prevenir y Erradicar la Discriminación Página 25\n.\nActualización Legislativa.\nÚltima Reforma P.O. No. 60, Índice, 03-Oct-2025\nLEGISLATURA, SIENDO GOBERNADORA CONSTITUCIONAL LA C. MARINA DEL PILAR\nÁVILA OLMEDA 2021-2027.\nTRANSITORIOS\nÚNICO. El presente Decreto entrará en vigor al día siguiente al de su publicación en el\nPeriódico Oficial del Estado.\nDADO en Sesión Ordinaria de la XXIV Legislatura en la Ciudad de Mexicali, B.C., a los veinte días del mes de octubre del año dos mil veintidós.\nDIP. ALEJANDRA MARÍA ANG HERNÁNDEZ\nPRESIDENTA\n(RÚBRICA)\nDIP. DUNNIA MONTSERRAT MURILLO LÓPEZ\nSECRETARIA\n(RÚBRICA)\nDE CONFORMIDAD CON LO DISPUESTO POR LA FRACCIÓN I DEL ARTÍCULO 49\nCALIFORNIA, IMPRÍMASE Y PUBLÍQUESE.\nMEXICALI, BAJA CALIFORNIA, A LOS VEINTISIETE DÍAS DEL MES DE OCTUBRE\nDEL AÑO DOS MIL VEINTIDÓS.\nMARINA DEL PILAR ÁVILA OLMEDA\nGOBERNADORA DEL ESTADO\nDE BAJA CALIFORNIA\n(RÚBRICA)\nCATALINO ZAVALA MÁRQUEZ\nSECRETARIO GENERAL DE GOBIERNO\nDEL ESTADO DE BAJA CALIFORNIA\n(RÚBRICA)\nARTÍCULO ÚNICO TRANSITORIO DEL DECRETO No. 309, POR EL QUE SE\nAPRUEBAN LAS REFORMAS A LOS ARTÍCULOS 6 Y 19; PUBLICADO EN EL\nCXXX, EXPEDIDO POR LA H. XXIV LEGISLATURA, SIENDO GOBERNADORA\nCONSTITUCIONAL LA C. MARINA DEL PILAR ÁVILA OLMEDA 2021-2027.\nTRANSITORIO\nÚNICO.- El presente decreto entrará en vigor a partir del día siguiente de su publicación en el Periódico Oficial del Estado de Baja California.\nLey para Prevenir y Erradicar la Discriminación Página 26\n.\nActualización Legislativa.\nÚltima Reforma P.O. No. 60, Índice, 03-Oct-2025\nDADO en Sesión Ordinaria de la XXIV Legislatura en la Ciudad de Mexicali, B.C., a los diecinueve días del mes de octubre del año dos mil veintitrés.\nDIP. MANUEL GUERRERO LUNA\nPRESIDENTE\n(RÚBRICA)\nDIP. DUNNIA MONTSERRAT MURILLO LÓPEZ\nSECRETARIA\n(RÚBRICA)\nDE CONFORMIDAD CON LO DISPUESTO POR LA FRACCIÓN I DEL ARTÍCULO 49\nCALIFORNIA, IMPRÍMASE Y PUBLÍQUESE.\nMEXICALI, BAJA CALIFORNIA, A LOS VEINTITRÉS DÍAS DEL MES DE OCTUBRE\nDEL AÑO DOS MIL VEINTITRÉS.\nMARINA DEL PILAR ÁVILA OLMEDA\nGOBERNADORA DEL ESTADO\nDE BAJA CALIFORNIA\n(RÚBRICA)\nCATALINO ZAVALA MÁRQUEZ\nSECRETARIO GENERAL DE GOBIERNO\nDEL ESTADO DE BAJA CALIFORNIA\n(RÚBRICA)\nARTÍCULO TERCERO TRANSITORIO DEL DECRETO No. 426, POR EL QUE SE\nAPRUEBA LA REFORMA A LOS ARTÍCULOS 9 Y 14; PUBLICADO EN EL PERIÓDICO\nOFICIAL No. 23, DE FECHA 07 DE MAYO DE 2024, ÍNDICE, TOMO CXXXI, EXPEDIDO\nPOR LA H. XXIV LEGISLATURA, SIENDO GOBERNADORA CONSTITUCIONAL LA C.\nMARINA DEL PILAR ÁVILA OLMEDA 2021-2027.\nTRANSITORIOS\nPRIMERO. El presente decreto entrará en vigor al día siguiente de su publicación en el\nPeriódico Oficial del Estado de Baja California.\nSEGUNDO. Las autoridades sujetas a la observancia y aplicación de la presente Ley, en un plazo no mayor a 180 días naturales contados a partir del día siguiente de la publicación del presente Decreto, deberán realizar las adecuaciones necesarias a sus reglamentos para su debida implementación.\nLey para Prevenir y Erradicar la Discriminación Página 27\n.\nActualización Legislativa.\nÚltima Reforma P.O. No. 60, Índice, 03-Oct-2025\nDIP. RAMÓN VÁZQUEZ VALADEZ\nPRESIDENTE\n(RÚBRICA)\nDIP. MANUEL GUERRERO LUNA\nSECRETARIO\n(RÚBRICA)\nDE CONFORMIDAD CON LO DISPUESTO POR LA FRACCIÓN I DEL ARTÍCULO 49\nCALIFORNIA, IMPRÍMASE Y PUBLÍQUESE.\nMEXICALI, BAJA CALIFORNIA, A LOS VEINTICINCO DÍAS DEL MES DE ABRIL\nDEL AÑO DOS MIL VEINTICUATRO.\nMARINA DEL PILAR ÁVILA OLMEDA\nGOBERNADORA DEL ESTADO\nDE BAJA CALIFORNIA\n(RÚBRICA)\nALFREDO ÁLVAREZ CÁRDENAS\nSECRETARIO GENERAL DE GOBIERNO\nDEL ESTADO DE BAJA CALIFORNIA\n(RÚBRICA)\nARTÍCULO ÚNICO TRANSITORIO DEL DECRETO No. 80, POR EL QUE SE\nAPRUEBA LA REFORMA AL INCISO N) DEL ARTÍCULO 19; PUBLICADO EN EL\nPERIÓDICO OFICIAL No. 22, ÍNDICE, DE FECHA 11 DE ABRIL DE 2025, TOMO CXXXII;\nEXPEDIDO POR LA H. XXIV LEGISLATURA, SIENDO GOBERNADORA\nCONSTITUCIONAL LA C. MARINA DEL PILAR ÁVILA OLMEDA 2021-2027.\nTRANSITORIOS\nÚNICO.- El presente decreto entrará en vigor al día siguiente de su publicación en el\nPeriódico Oficial del Estado.\nDADO en Sesión Ordinaria de la XXV Legislatura en la Ciudad de Tijuana, B.C., a los veintisiete días del mes de marzo del año dos mil veinticinco.\nDIP. EVELYN SÁNCHEZ SÁNCHEZ\nPRESIDENTA\n(RÚBRICA)\nDIP. MICHELLE ALEJANDRA TEJEDA MEDINA\nSECRETARIA\n(RÚBRICA)\nLey para Prevenir y Erradicar la Discriminación Página 28\n.\nActualización Legislativa.\nÚltima Reforma P.O. No. 60, Índice, 03-Oct-2025\nDE CONFORMIDAD CON LO DISPUESTO POR LA FRACCIÓN I DEL ARTÍCULO 49\nCALIFORNIA, IMPRÍMASE Y PUBLÍQUESE.\nMEXICALI, BAJA CALIFORNIA, A LOS 31 DÍAS DEL MES DE MARZO DEL AÑO\nDOS MIL VEINTICINCO.\nMARINA DEL PILAR ÁVILA OLMEDA\nGOBERNADORA DEL ESTADO\nDE BAJA CALIFORNIA\n(RÚBRICA)\nALFREDO ÁLVAREZ CÁRDENAS\nSECRETARIO GENERAL DE GOBIERNO\nDEL ESTADO DE BAJA CALIFORNIA\n(RÚBRICA)\nARTÍCULO ÚNICO TRANSITORIO DEL DECRETO No. 87, POR EL QUE SE\nAPRUEBA LA REFORMA AL ARTÍCULO 5; PUBLICADO EN EL PERIÓDICO OFICIAL No.\n25, ÍNDICE, DE FECHA 25 DE ABRIL DE 2025, TOMO CXXXII; EXPEDIDO POR LA H.\nXXIV LEGISLATURA, SIENDO GOBERNADORA CONSTITUCIONAL LA C. MARINA DEL\nPILAR ÁVILA OLMEDA 2021-2027.\nTRANSITORIO\nÚNICO.- La presente reforma entrara en vigor al día siguiente de su publicación en el\nPeriódico Oficial del Estado.\nDADO en Sesión Ordinaria de la XXV Legislatura en la Ciudad de Mexicali, B.C., a los diez días del mes de abril del año dos mil veinticinco.\nDIP. MICHELLE ALEJANDRA TEJEDA MEDINA\nPRESIDENTA\n(RÚBRICA)\nDIP. NORMA ANGELICA PEÑALOZA ESCOBEDO\nSECRETARIA\n(RÚBRICA)\nDE CONFORMIDAD CON LO DISPUESTO POR LA FRACCIÓN I DEL ARTÍCULO 49\nCALIFORNIA, IMPRÍMASE Y PUBLÍQUESE.\nLey para Prevenir y Erradicar la Discriminación Página 29\n.\nActualización Legislativa.\nÚltima Reforma P.O. No. 60, Índice, 03-Oct-2025\nMEXICALI, BAJA CALIFORNIA, A LOS 14 DÍAS DEL MES DE ABRIL DEL AÑO DOS\nMIL VEINTICINCO.\nMARINA DEL PILAR ÁVILA OLMEDA\nGOBERNADORA DEL ESTADO\nDE BAJA CALIFORNIA\n(RÚBRICA)\nALFREDO ÁLVAREZ CÁRDENAS\nSECRETARIO GENERAL DE GOBIERNO\nDEL ESTADO DE BAJA CALIFORNIA\n(RÚBRICA)\nARTÍCULO ÚNICO TRANSITORIO DEL DECRETO No. 141, POR EL QUE SE\nAPRUEBA LA REFORMA AL ARTÍCULO 33; PUBLICADO EN EL PERIÓDICO OFICIAL No.\n60, ÍNDICE, DE FECHA 03 DE OCTUBRE DE 2025, TOMO CXXXII; EXPEDIDO POR LA H.\nXXV LEGISLATURA, SIENDO GOBERNADORA CONSTITUCIONAL LA C. MARINA DEL\nPILAR ÁVILA OLMEDA 2021-2027.\nTRANSITORIO\nÚNICO.- El presente decreto entrará en vigor al día siguiente al de su publicación en el\nPeriódico Oficial del Estado de Baja California.\nDADO en Sesión Ordinaria de la XXV Legislatura en la Ciudad de Mexicali, B.C., a los once días del mes de septiembre del año dos mil veinticinco.\nDIP. JAIME EDUARDO CANTÓN ROCHA\nPRESIDENTE\n(RÚBRICA)\nDIP. MICHELLE ALEJANDRA TEJEDA MEDINA\nSECRETARIA\n(RÚBRICA)\nDE CONFORMIDAD CON LO DISPUESTO POR LA FRACCIÓN I DEL ARTÍCULO 49\nCALIFORNIA, IMPRÍMASE Y PUBLÍQUESE.\nMEXICALI, BAJA CALIFORNIA, A LOS 17 DÍAS DEL MES DE SEPTIEMBRE DEL\nAÑO DOS MIL VEINTICINCO.\nMARINA DEL PILAR ÁVILA OLMEDA\nGOBERNADORA DEL ESTADO\nDE BAJA CALIFORNIA\n(RÚBRICA)\nLey para Prevenir y Erradicar la Discriminación Página 30\n.\nActualización Legislativa.\nALFREDO ÁLVAREZ CÁRDENAS\nSECRETARIO GENERAL DE GOBIERNO\nDEL ESTADO DE BAJA CALIFORNIA\n(RÚBRICA)\nLey para Prevenir y Erradicar la Discriminación Página 31",
  "ordenamiento": "REGLAMENTO",
  "jurisdiccion": "BAJA CALIFORNIA",
  "fuente_oficial": "Periódico Oficial",
  "FECHA PER OFIC": "2025/10/03",
  "ESTATUS": "VIGENTE",
  "TOMO": "TOMO_VI",
  "URL": "https://www.congresobc.gob.mx/Documentos/ProcesoParlamentario/Leyes/TOMO_VI/20251003_LEYDISCRIMIN.PDF",
  "es_escaneado": false,
  "tiene_tablas": false,
  "materia": [
    "social",
    "salud",
    "educación",
    "cultura"
  ]
}