{
  "titulo": "Ley DE PROTECCIÓN CIVIL y GESTIÓN INTEGRAL DE RIESGOS DEL ESTADO DE BAJA CALIFORNIA",
  "Contenido": "DE BAJA CALIFORNIA\nTomo CCXXIV, Sección III\nTITULO PRIMERO\nDISPOSICIONES GENERALES\nCapítulo Único\nObjeto y Definiciones\nArtículo 1.- Las disposiciones de esta Ley son de orden público, interés social y de observancia general en el Estado de Baja California, y tienen por objeto:\nI. Establecer las bases de integración, coordinación y funcionamiento de los Sistemas\nEstatal y Municipales de Protección Civil.\nII. La prevención, mitigación, auxilio y salvaguarda de las personas, sus bienes y entorno, así como el restablecimiento y funcionamiento de los servicios públicos indispensables y sistemas estratégicos en casos de emergencia y desastre, provocados por factores geológicos, hidrometereológicos, químicos, sanitarios y socioorganizativos.\nIII. Promover la participación de los sectores privado y social en la consecución de los objetivos de esta Ley, en los términos y condiciones que la misma establece.\nArtículo 2.- Para los efectos de esta Ley se entiende por:\nI. Agente regulador: Lo constituyen las acciones, instrumentos, normas, obras y en general todo aquello destinado a proteger a las personas, bienes, infraestructura estratégica, efectos adversos de un agente perturbador;\nLey de Protección Civil y Gestión Integral de Riesgos del Estado de Baja California Página 1\nII. Albergado: Persona que en forma temporal recibe asilo, amparo, alojamiento y resguardo ante la amenaza, inminencia u ocurrencia de un agente perturbador;\nIII. Albergue: Instalación que se establece para brindar resguardo a las personas en donde permanecen hasta que se da la recuperación o reconstrucción de sus viviendas;\nIV. Atlas Estatal y Municipales de Riesgos: Sistema integral de información sobre los agentes perturbadores y daños esperados, resultado de un análisis espacial y temporal sobre la interacción entre los peligros, la vulnerabilidad y el grado de exposición de los agentes afectables;\nV. Auxilio: Respuesta de ayuda a las personas en riesgo o las víctimas de un siniestro, emergencia o desastre, por parte de grupos especializados públicos o privados, o por las unidades internas de protección civil, así como las acciones para salvaguardar los demás agentes afectables;\nVI. Brigada: Grupo de personas que se organizan dentro de un inmueble, capacitadas y adiestradas en funciones básicas de respuesta a emergencias tales como: primeros auxilios, combate a conatos de incendio, evacuación, búsqueda y rescate; designados en la Unidad Interna de Protección Civil como encargados del desarrollo y ejecución de acciones de prevención, auxilio y recuperación, con base en lo estipulado en el Programa\nInterno de Protección Civil del inmueble;\nVII. Cambio Climático: Cambio en el clima, atribuible directa o indirectamente a la actividad humana, que altera la composición de la atmósfera mundial y que se suma a la variabilidad climática natural observada durante períodos comparables;\nVIII. Consejo Estatal: Consejo Estatal de Protección Civil;\nIX. Continuidad de Operaciones: Proceso de planeación, documentación y actuación que garantiza que las actividades sustantivas de las instituciones públicas, privadas y sociales, afectadas por un agente perturbador, puedan recuperarse y regresar a la normalidad en un tiempo mínimo. Esta planeación deberá estar contenida en un documento o serie de documentos cuyo contenido se dirija hacia la prevención, respuesta inmediata, recuperación y restauración, todas ellas avaladas por sesiones de capacitación continua y realización de simulacros;\nLey de Protección Civil y Gestión Integral de Riesgos del Estado de Baja California Página 2\nX. Coordinación Estatal: Coordinación Estatal de Protección Civil de Baja\nCalifornia;\nXI. Damnificado: Persona afectada por un agente perturbador, ya sea que haya sufrido daños en su integridad física o un perjuicio en sus bienes, de tal manera que requiere asistencia externa para su subsistencia; considerándose con esa condición en tanto no se concluya la emergencia o se restablezca la situación de normalidad previa al desastre;\nXII. Declaratoria estatal de emergencia: Es el acto mediante el cual la Secretaría reconoce que uno o varios municipios o delegaciones de una o más municipios se encuentran ante la inminencia, alta probabilidad o presencia de una situación anormal generada por un agente natural perturbador y por ello se requiere prestar auxilio inmediato a la población cuya seguridad e integridad está en riesgo;\nXIII. Declaratoria estatal de desastre natural: Es el acto mediante el cual la\nSecretaría reconoce la presencia de un agente natural perturbador severo en determinados municipios o delegaciones de uno o más municipios, cuyos daños rebasan la capacidad financiera y operativa local para su atención, para efectos de poder acceder a recursos del instrumento financiero de atención de desastres naturales;\nXIV. Desastre: Resultado de la ocurrencia de uno o más agentes perturbadores severos y/o extremos, concatenados o no, de origen natural, de la actividad humana o aquellos provenientes del espacio exterior, que cuando acontecen en un tiempo y en una zona determinada, causan daños y que por su magnitud exceden la capacidad de respuesta de la comunidad afectada;\nXV. Donativo: Aportación en dinero o en especie que realizan las diversas personas físicas o morales, nacionales o internacionales, a través de los centros de acopio autorizados o en las instituciones de crédito, para ayudar a la entidad federativa, municipios o comunidades en emergencia o desastre;\nXVI. Emergencia: Situación anormal que puede causar un daño a la sociedad y propiciar un riesgo excesivo para la seguridad e integridad de la población en general, generada o asociada con la inminencia, alta probabilidad o presencia de un agente perturbador;\nXVII. Evacuado: Persona que, con carácter preventivo y provisional ante la posibilidad o certeza de una emergencia o desastre, se retira o es retirado de su lugar de alojamiento usual, para garantizar su seguridad y supervivencia;\nLey de Protección Civil y Gestión Integral de Riesgos del Estado de Baja California Página 3\nXVIII. Fenómeno Antropogénico: Agente perturbador producido por la actividad humana;\nXIX. Fenómeno Astronómico: Eventos, procesos o propiedades a los que están sometidos los objetos del espacio exterior incluidos estrellas, planetas, cometas y meteoros.\nAlgunos de éstos fenómenos interactúan con la tierra, ocasionándole situaciones que generan perturbaciones que pueden ser destructivas tanto en la atmósfera como en la superficie terrestre, entre ellas se cuentan las tormentas magnéticas y el impacto de meteoritos.\nXX. Fenómeno Natural Perturbador: Agente perturbador producido por la naturaleza;\nXXI. Fenómeno Geológico: Agente perturbador que tiene como causa directa las acciones y movimientos de la corteza terrestre. A esta categoría pertenecen los sismos, las erupciones volcánicas, los tsunamis, la inestabilidad de laderas, los flujos, las caídas o derrumbes, los hundimientos, la subsidencia y los agrietamientos;\nXXII. Fenómeno Hidrometeorológico: Agente perturbador que se genera por la acción de los agentes atmosféricos, tales como: huracanes, ciclones tropicales, lluvias extremas, inundaciones pluviales, fluviales, costeras y lacustres; tormentas de nieve, granizo, polvo y electricidad; heladas; sequías; ondas cálidas y gélidas; y tornados;\nXXIII. Fenómeno Químico-Tecnológico: Agente perturbador que se genera por la acción violenta de diferentes sustancias derivadas de su interacción molecular o nuclear.\nComprende fenómenos destructivos tales como: incendios de todo tipo, explosiones, fugas tóxicas, radiaciones y derrames;\nXXIV. Fenómeno Sanitario-Ecológico: Agente perturbador que se genera por la acción patógena de agentes biológicos que afectan a la población, a los animales y a las cosechas, causando su muerte o la alteración de su salud. Las epidemias o plagas constituyen un desastre sanitario en el sentido estricto del término. En esta clasificación también se ubica la contaminación del aire, agua, suelo y alimentos;\nXXV. Fenómeno Socio-Organizativo: Agente perturbador que se genera con motivo de errores humanos o por acciones premeditadas, que se dan en el marco de grandes concentraciones o movimientos masivos de población, tales como: demostraciones de inconformidad social, concentración masiva de población, terrorismo, sabotaje, vandalismo, accidentes aéreos, marítimos o terrestres, e interrupción o afectación de los servicios básicos o de infraestructura estratégica;\nLey de Protección Civil y Gestión Integral de Riesgos del Estado de Baja California Página 4\nXXVI. Gestión Integral de Riesgos: El conjunto de acciones encaminadas a la identificación, análisis, evaluación, control y reducción de los riesgos, considerándolos por su origen multifactorial y en un proceso permanente de construcción, que involucra a los tres niveles de gobierno, así como a los sectores de la sociedad, lo que facilita la realización de acciones dirigidas a la creación e implementación de políticas públicas, estrategias y procedimientos integrados al logro de pautas de desarrollo sostenible, que combatan las causas estructurales de los desastres y fortalezcan las capacidades de resiliencia o resistencia de la sociedad. Involucra las etapas de: identificación de los riesgos y/o su proceso de formación, previsión, prevención, mitigación, preparación, auxilio, recuperación y reconstrucción;\nXXVII. Grupos Voluntarios: Personas morales o personas físicas, que se han acreditado ante las autoridades competentes, y que cuentan con personal, conocimientos, experiencia y equipo necesarios, para prestar de manera altruista y comprometida, sus servicios en acciones de protección civil;\nXXVIII. Hospital Seguro: Establecimiento de servicios de salud que debe permanecer accesible y funcionando a su máxima capacidad, con la misma estructura, bajo una situación de emergencia o de desastre;\nXXIX. Identificación de Riesgos: Reconocer y valorar las pérdidas o daños probables sobre los agentes afectables y su distribución geográfica, a través del análisis de los peligros y la vulnerabilidad;\nXXX. Infraestructura Estratégica: Aquella que es indispensable para la provisión de bienes y servicios públicos, y cuya destrucción o inhabilitación es una amenaza en contra de la seguridad nacional;\nXXXI. Instrumentos Financieros de Gestión de Riesgos: Son aquellos programas y para apoyar a las instancias públicas federales y entidades federativas, en la ejecución de proyectos y acciones derivadas de la gestión integral de riesgos, para la prevención y atención de situaciones de emergencia y/o desastre de origen natural;\nXXXII. Instrumentos de Administración y Transferencia de Riesgos: Son aquellos órdenes de gobierno, compartir o cubrir sus riesgos catastróficos, transfiriendo el costo total o parcial a instituciones financieras nacionales o internacionales;\nLey de Protección Civil y Gestión Integral de Riesgos del Estado de Baja California Página 5\nXXXIII. Ley General: Ley General de Protección Civil;\nXXXIV. Mitigación: Toda acción orientada a disminuir el impacto o daños ante la presencia de un agente perturbador sobre un agente afectable;\nXXXV. Peligro: Probabilidad de ocurrencia de un agente perturbador potencialmente dañino de cierta intensidad, durante un cierto periodo y en un sitio determinado;\nXXXVI. Preparación: Actividades y medidas tomadas anticipadamente para asegurar una respuesta eficaz ante el impacto de un fenómeno perturbador en el corto, mediano y largo plazo;\nXXXVII. Prevención: Conjunto de acciones y mecanismos implementados con antelación a la ocurrencia de los agentes perturbadores, con la finalidad de conocer los peligros o los riesgos, identificarlos, eliminarlos o reducirlos; evitar o mitigar su impacto destructivo sobre las personas, bienes, infraestructura, así como anticiparse a los procesos sociales de construcción de los mismos;\nXXXVIII. Previsión: Tomar conciencia de los riesgos que pueden causarse y las necesidades para enfrentarlos a través de las etapas de identificación de riesgos, prevención, mitigación, preparación, atención de emergencias, recuperación y reconstrucción;\nXXXIX. Programa Interno de Protección Civil: Instrumento de planeación y operación, circunscrito al ámbito de una dependencia, entidad, institución u organismo del sector público, privado o social; que se compone por el plan operativo para la Unidad Interna de\nProtección Civil, el plan para la continuidad de operaciones y el plan de contingencias, y tiene como propósito mitigar los riesgos previamente identificados y definir acciones emergencia o desastre;\nXL. Programa Estatal: Programa Estatal de Protección Civil de Baja California;\nXLI. Protección Civil: Acción solidaria y participativa, que en consideración tanto de perturbadores, prevé la coordinación y concertación de los sectores público, privado y social en el marco del Sistema Estatal, con el fin de crear un conjunto de disposiciones, planes, programas, estrategias, mecanismos y recursos para que de manera corresponsable, y privilegiando la Gestión Integral de Riesgos y la Continuidad de Operaciones, se apliquen las\nLey de Protección Civil y Gestión Integral de Riesgos del Estado de Baja California Página 6 medidas y acciones que sean necesarias para salvaguardar la vida, integridad y salud de la población, así como sus bienes; la infraestructura, la planta productiva y el medio ambiente;\nXLII. Reconstrucción: Acción transitoria orientada a alcanzar el entorno de producidos por un agente perturbador en un determinado espacio o jurisdicción. Este proceso debe buscar en la medida de lo posible la reducción de los riesgos existentes, asegurando la no generación de nuevos riesgos y mejorando para ello las condiciones preexistentes;\nXLIII. Recuperación: Proceso que inicia durante la emergencia, consistente en acciones encaminadas al retorno a la normalidad de la comunidad afectada;\nXLIV. Reducción de Riesgos: Intervención preventiva de individuos, instituciones y comunidades que nos permite eliminar o reducir, mediante acciones de preparación y mitigación, el impacto adverso de los desastres. Contempla la identificación de riesgos y el análisis de vulnerabilidades, resiliencia y capacidades de respuesta, el desarrollo de una cultura de la protección civil, el compromiso público y el desarrollo de un marco institucional, la implementación de medidas de protección del medio ambiente, uso del suelo y planeación urbana, protección de la infraestructura crítica, generación de alianzas y desarrollo de instrumentos financieros y transferencia de riesgos, y el desarrollo de sistemas de alertamiento;\nXLV. Refugio Temporal: Instalación física habilitada para brindar temporalmente protección y bienestar a las personas que no tienen posibilidades inmediatas de acceso a una habitación segura en caso de un riesgo inminente, una emergencia, siniestro o desastre;\nXLVI. Reglamento. Reglamento de la Ley de Protección Civil del Estado de Baja\nCalifornia;\nXLVII. Resiliencia: Capacidad de un sistema, comunidad o sociedad potencialmente expuesta a un peligro para resistir, asimilar, adaptarse y recuperarse de sus efectos en un corto plazo y de manera eficiente, a través de la preservación y restauración de sus estructuras básicas y funcionales, logrando una mejor protección futura y mejorando las medidas de reducción de riesgos;\nXLVIII. Riesgo: Daños o pérdidas probables sobre un agente afectable, resultado de la interacción entre su vulnerabilidad y la presencia de un agente perturbador;\nXLIX. Riesgo Inminente: Aquel riesgo que, según la opinión de una instancia técnica especializada, debe considerar la realización de acciones inmediatas en virtud de existir\nLey de Protección Civil y Gestión Integral de Riesgos del Estado de Baja California Página 7 agente afectable;\nLI. Seguro: Instrumento de Administración y Transferencia de Riesgos;\nLII. Simulacro: Representación mediante una simulación de las acciones de respuesta previamente planeadas con el fin de observar, probar y corregir una respuesta eficaz ante posibles situaciones reales de emergencia o desastre. Implica el montaje de un escenario en terreno específico, diseñado a partir de la identificación y análisis de riesgos y la vulnerabilidad de los sistemas afectables;\nLIII. Sistema Estatal: Sistema Estatal de Protección Civil de Baja California;\nLIV. Tecnologías de la Información y la Comunicación: Todos aquellos recursos, herramientas y programas que se utilizan para procesar, administrar y compartir la información mediante diversos soportes tecnológicos, tales como: computadoras, teléfonos móviles, televisores, reproductores portátiles de audio y video o consolas de juego.\nLV. Transversalidad: Estrategia y criterio de gestión enfocado al fortalecimiento de los puntos de contacto entre las diferentes áreas gubernamentales y actores públicos, en función de la satisfacción de una necesidad concreta de la ciudadanía y atendiendo a la complejidad de los problemas sociales, que es también estrategia de organización interna y de operación de los Sistemas Estatal y Municipales de Protección Civil;\nLVI. Seguridad de Trayecto: Se entiende por el desplazamiento entre puntos o destinos de los habitantes de una localidad, de tal forma que garantice los derechos a la libre circulación, a la seguridad e integridad física de las personas y que asegure a su vez la óptima respuesta de las dependencias de auxilio en caso algún siniestro.\nFracción Adicionada\nLVII. Siniestro: Situación crítica y dañina generada por la incidencia de uno o más fenómenos perturbadores en un inmueble o instalación afectando a su población y equipo, con posible afectación a instalaciones circundantes;\nLVIII. Unidad Interna de Protección Civil: Órgano normativo y operativo responsable de desarrollar y dirigir las acciones de protección civil, así como elaborar, actualizar, operar y móviles de una dependencia, institución o entidad perteneciente a los sectores público, privado y social; también conocidas como Brigadas Institucionales de Protección Civil;\nLey de Protección Civil y Gestión Integral de Riesgos del Estado de Baja California Página 8\nLIX. Unidades de protección civil: Organismos de la administración pública del\nEstado y de los Municipios encargados de la organización, coordinación y operación del\nSistema Estatal y Nacional, en su demarcación territorial;\nLX. Vulnerabilidad: Susceptibilidad o propensión de un agente afectable a sufrir daños o pérdidas ante la presencia de un agente perturbador, determinado por factores físicos, sociales, económicos y ambientales;\nLXI. Zona de Desastre: Espacio territorial determinado en el tiempo por la declaración formal de la autoridad competente, en virtud del desajuste que sufre en su estructura social, impidiéndose el cumplimiento normal de las actividades de la comunidad.\nPuede involucrar el ejercicio de recursos públicos a través del Fondo de Desastres;\nLXII. Zona de Riesgo: Espacio territorial determinado en el que existe la probabilidad de que se produzca un daño, originado por un fenómeno perturbador, y\nLXIII. Zona de Riesgo Grave: Asentamiento humano que se encuentra dentro de una zona de grave riesgo, originado por un posible fenómeno perturbador.\nTÍTULO SEGUNDO\nESTRUCTURA INSTITUCIONAL\nCAPÍTULO I\nCOMPETENCIAS\nArtículo 3.- La organización y la prestación de la política pública estatal de protección civil corresponden al Poder Ejecutivo del Estado, quien deberá realizarlas en los términos de esta Ley y de su Reglamento, por conducto de las dependencias de la administración pública estatal, y los municipios en sus respectivos ámbitos de competencia. información, a fin de impulsar acciones a favor del aprendizaje y práctica de conductas seguras, mediante el aprovechamiento de las tecnologías de la información y comunicación, así como de los medios masivos de comunicación.\nArtículo 4.- Los Poderes Legislativo y Judicial del Estado, los municipios, entidades paraestatales, los organismos constitucionales autónomos y los sectores privado y social, así como la población en general, deberán coadyuvar para que las acciones de protección civil se realicen en forma coordinada y eficaz.\nLey de Protección Civil y Gestión Integral de Riesgos del Estado de Baja California Página 9 de colaboración para el debido cumplimiento de esta Ley.\nArtículo 6.- Son autoridades en materia de Protección Civil en el Estado:\nI. El Gobernador Constitucional del Estado;\nII. El Consejo Estatal de Protección Civil;\nIII. El Secretario General de Gobierno;\nIV. El titular de la Coordinación Estatal;\nV. El Presidente Municipal de cada Ayuntamiento;\nVI. Los Consejos Municipales de Protección Civil y\nVII. Las unidades de protección civil municipal que determinen los\nReglamentos Interiores de cada Ayuntamiento.\nArtículo 7.- Los programas y estrategias que el Poder Ejecutivo del Estado y los gobiernos municipales lleven a cabo para el fortalecimiento de los instrumentos de organización y funcionamiento de las instituciones de protección civil se sustentarán en un enfoque de Gestión Integral del Riesgo.\nArtículo 8.- Las políticas públicas del Estado y de los Municipios en materia de protección civil, se ceñirán al Plan Estatal de Desarrollo y al Programa Estatal de Protección\nCivil, identificando para ello las siguientes prioridades:\nI. La identificación y análisis de riesgos como sustento para la implementación de medidas de prevención y mitigación;\nII. Promoción, desde la niñez, de una cultura de responsabilidad social dirigida a peligros que representan los agentes perturbadores y su vulnerabilidad;\nIII. Obligación del gobierno estatal y los gobiernos municipales, para reducir los identificación y el reconocimiento de la vulnerabilidad de las zonas bajo su jurisdicción;\nIV. El fomento de la participación social para crear comunidades resilientes, y por ello capaces de resistir los efectos negativos de los desastres, mediante una acción\nLey de Protección Civil y Gestión Integral de Riesgos del Estado de Baja California Página 10 solidaria, y recuperar en el menor tiempo posible sus actividades productivas, económicas y sociales;\nV. Incorporación de la gestión integral del riesgo, como aspecto fundamental en la generación de riesgos;\nVI. Incorporar el concepto de transversalidad en todos los procesos que lleven a cabo las dependencias de la administración pública estatal y municipal, en concordancia con las acciones que realicen los sectores privado y social;\nVII. El establecimiento de un sistema de certificación de competencias, que garantice un perfil adecuado en el personal responsable de la protección civil en el gobierno estatal y los gobiernos municipales y\nVIII. El conocimiento y la adaptación al cambio climático, y en general a las consecuencias y efectos del calentamiento global provocados por el ser humano y la aplicación de las tecnologías.\nArtículo 9.- Las autoridades estatales y municipales de protección civil deberán actuar con base en los siguientes principios:\nI. Prioridad en la protección a la vida, la salud y la integridad de las personas;\nII. Inmediatez, equidad, profesionalismo, eficacia y eficiencia en la prestación del auxilio y entrega de recursos a la población en caso de emergencia o desastre;\nIII. Subsidiariedad, complementariedad, transversalidad y proporcionalidad en las funciones asignadas a las diversas instancias del gobierno;\nIV. Máxima publicidad y participación social en todas las fases de la protección civil, pero particularmente en la de prevención;\nV. Establecimiento y desarrollo de una cultura de la protección civil, con énfasis en la prevención en la población en general;\nVI. Legalidad, control, eficacia, racionalidad, equidad, transparencia y rendición de cuentas en la administración de los recursos públicos;\nVII. Corresponsabilidad entre sociedad y gobierno y\nLey de Protección Civil y Gestión Integral de Riesgos del Estado de Baja California Página 11\nVIII. Respeto a los derechos humanos antes, durante y después de cualquier agente perturbador.\nArtículo 10.- Corresponde al Ejecutivo del Estado en materia de protección civil:\nI. Asegurar el correcto funcionamiento del Sistema Estatal y dictar los lineamientos generales para coordinar las labores de protección civil en beneficio de la población, sus bienes y entorno, induciendo y conduciendo la participación de los diferentes sectores y grupos de la sociedad en el marco de la Gestión Integral de Riesgos;\nII. Promover la incorporación de la Gestión Integral de Riesgos en el desarrollo estatal estableciendo estrategias y políticas basadas en el análisis de los riesgos, con el fin de evitar la construcción de riesgos futuros y la realización de acciones de intervención para reducir los riesgos existentes;\nIII. Contemplar, en el proyecto de Presupuesto de Egresos del Estado de cada ejercicio fiscal, recursos con el fin de promover y apoyar la realización de acciones de orden preventivo; así como las orientadas tanto al auxilio de la población en situación de emergencia, como la atención de los daños provocados por los desastres de origen natural;\nIV. Emitir, en su caso, declaratorias de emergencia y desastre natural, en los términos presente Ley, sin detrimento de las disposiciones aplicables de la Ley General;\nV. Disponer la utilización y destino de los recursos de los Instrumentos\nFinancieros de Gestión de Riesgos, con apego a lo dispuesto por la normatividad administrativa en la materia;\nVI. Promover, ante la eventualidad de los desastres de origen natural, la realización de acciones dirigidas a una estrategia integral de transferencia de riesgos, a través de herramientas tales como la identificación de la infraestructura por asegurar, el análisis de los riesgos, las medidas para su reducción y la definición de los esquemas de retención y aseguramiento, entre otros y\nVII. Vigilar, mediante las dependencias y entidades competentes y conforme a las disposiciones legales aplicables, que no se autoricen centros de población en zonas de riesgo y, de ser el caso, se notifique a las autoridades competentes para que proceda a su desalojo, así como al deslinde de las responsabilidades en las que se incurran por la omisión y complacencia ante dichas irregularidades.\nLey de Protección Civil y Gestión Integral de Riesgos del Estado de Baja California Página 12\nArtículo 11.- La coordinación y aplicación de esta Ley, se hará con respeto absoluto a en el Sistema Estatal y en los Sistemas Municipales.\nCAPÍTULO II\nSISTEMA ESTATAL DE PROTECCIÓN CIVIL\nArtículo 12.- El Sistema Estatal de Protección Civil es parte integrante del Sistema\nNacional y se articula con el Sistema Municipal.\nEl Sistema Estatal es un conjunto orgánico y articulado de estructuras, relaciones funcionales, métodos, normas, instancias, principios, instrumentos, políticas, procedimientos, servicios y acciones, que establecen corresponsablemente las dependencias y entidades del sector público entre sí, con las organizaciones de los diversos grupos voluntarios, sociales, privados y con los Poderes Legislativo, Ejecutivo y Judicial, de los organismos constitucionales autónomos, y de los municipios a fin de efectuar acciones coordinadas, en materia de protección civil.\nArtículo 13.- El objetivo general del Sistema Estatal es el de proteger a la persona y a la sociedad y su entorno ante la eventualidad de los riesgos y peligros que representan los agentes perturbadores y la vulnerabilidad en el corto, mediano o largo plazo, provocada por fenómenos naturales o antropogénicos, a través de la Gestión Integral de Riesgos y el fomento de la capacidad de adaptación, auxilio y restablecimiento en la población.\nArtículo 14.- El Sistema Estatal se encuentra integrado por todas las dependencias y entidades de la administración pública estatal, por los sistemas de protección civil de los municipios; por los grupos voluntarios, vecinales y organizaciones de la sociedad civil, los cuerpos de bomberos, así como por los representantes de los sectores privado y social, los medios de comunicación y los centros de investigación, educación y desarrollo tecnológico. solicite y justifique su utilidad, la información de carácter técnico, ya sea impresa, electrónica, digital o en tiempo real relativa a los sistemas y/o redes de alerta, detección, monitoreo, pronóstico y medición de riesgos.\nArtículo 15.- El Gobernador del Estado y los presidentes municipales tendrán dentro de\nProtección Civil, conforme a lo que establezca la presente Ley y la Ley General de\nProtección Civil.\nLey de Protección Civil y Gestión Integral de Riesgos del Estado de Baja California Página 13 instituciones registradas en la Escuela Nacional Protección Civil.\nArtículo 16.- La Coordinación Estatal, con sustento en las Leyes y disposiciones locales, propiciará una distribución estratégica de las tareas, entre los centros regionales ubicados con criterios basados en la localización de los riesgos, las necesidades y los recursos disponibles.\nCAPÍTULO III\nCONSEJO ESTATAL DE PROTECCIÓN CIVIL\nArtículo 17.- El Consejo Estatal es un órgano de consulta, opinión y coordinación de acciones en la materia, en el que se integran en forma multidisciplinaria e interinstitucional, dependencias de los Gobiernos Estatal y Municipales y estará conformado por:\nI. El Gobernador Constitucional del Estado, quien lo presidirá;\nII. Secretario General de Gobierno;\nIII. Los titulares de las Secretarías de Estado;\nIV. Los Presidentes Municipales de los Ayuntamientos del Estado;\nV. El Presidente de la Comisión de la materia, del Congreso del Estado y\nVI. El titular de la Coordinación Estatal.\nPor cada miembro propietario se nombrará un suplente.\nAl Gobernador del Estado lo suplirá el Secretario General de Gobierno, a quien lo suplirá el titular de la Coordinación Estatal; en el caso de servidores públicos federales, inferior; el Presidente de la Comisión respectiva del Congreso del Estado será suplido por el\nSecretario de la propia Comisión.\nEl Presidente del Consejo, convocará y presidirá las sesiones ordinarias, extraordinarias y permanentes; y, de acuerdo a los asuntos a tratar, podrá invitar a las\nLey de Protección Civil y Gestión Integral de Riesgos del Estado de Baja California Página 14 dependencias o entidades públicas y privadas, asociaciones y organizaciones sociales, así como a las agrupaciones e instituciones académicas y profesionales.\nEl Presidente del Consejo, de acuerdo a los asuntos a tratar podrá invitar a las dependencias o entidades públicas y privadas, asociaciones y organizaciones sociales, así como a las agrupaciones e instituciones académicas y profesionales. Asimismo, podrá invitar a los titulares de Delegaciones Estatales de las Dependencias y Entidades de la\nAdministración Pública Federal, que atiendan ramos de actividad relacionados con la ejecución de los programas de prevención, auxilio y apoyo en materia de protección civil, en los términos que establezcan los convenios de colaboración o de coordinación que al respecto se celebren.\nArtículo 18.- El Consejo Estatal tendrá las siguientes atribuciones:\nI. Orientar las políticas y acciones de Protección Civil;\nII. Hacer propuestas al titular del Poder Ejecutivo del Estado al programa anual de\nProtección Civil que formule la Coordinación Estatal;\nIII. Promover la investigación científica en materia de Protección Civil, a través de las instituciones de educación superior;\nIV. Proponer el establecimiento de los instrumentos y políticas públicas integrales, sistemáticas, continuas y evaluables, tendientes a cumplir los objetivos y fines de la protección civil;\nV. Proponer la emisión de acuerdos y resoluciones generales, para el funcionamiento del Sistema Estatal;\nVI. Celebrar convenios con otras entidades federativas entre autoridades de primera respuesta en la zona fronteriza;\nVII. Promover la efectiva coordinación de las instancias que integran el Sistema\nEstatal y dar seguimiento de las acciones que para tal efecto se establezcan;\nVIII. Proponer el establecimiento de medidas para vincular al Sistema Estatal y los\nSistemas Municipales con el Sistema Nacional de protección civil;\nLey de Protección Civil y Gestión Integral de Riesgos del Estado de Baja California Página 15\nIX. Fomentar la participación comprometida y corresponsable de todos los sectores de la sociedad, en la formulación y ejecución de los programas destinados a satisfacer las necesidades de protección civil en el territorio estatal;\nX. En situaciones de declaratoria de emergencia o desastre ante el gobierno federal, dirigir las acciones estratégicas, decidir las políticas a tomar y determinar los recursos necesarios para la respuesta y reconstrucción;\nXI. Procurar la continuidad de operaciones de los servicios vitales, los sistemas estratégicos y la planta productiva en caso de emergencias mayores o desastres;\nXII. Convocar, coordinar y armonizar la participación de los municipios y de los diversos grupos sociales locales organizados, en la definición y ejecución de las acciones que se convenga realizar en materia de protección civil;\nXIII. Promover capacitación en materia de protección civil, identificando sus problemas y tendencias, y proponiendo las normas y programas que permitan su solución;\nXIV. Promover el desarrollo y la consolidación de una cultura estatal de protección civil;\nXV. Instalar el Comité Estatal de Certificación de Instructores en Rescate y\nAtención de Emergencias en Materia de Protección Civil y Bomberos, al Comité Estatal para la Atención Integral de Servicios de Emergencias y Rescate, al Equipo Estatal de Búsqueda y Rescate en Zonas Agrestes y al Equipo Estatal de Búsqueda y Rescate en Zonas\nUrbanas, con la finalidad de homologar los conocimientos, procedimientos y protocolos de atención de emergencias, búsqueda y rescates en materia de protección civil, así como responder de manera coordinada y homologada en dichos procedimientos y protocolos, ya sea en zonas agrestes o urbanas del Estado. Las funciones de dichos comités y equipos serán en los términos del reglamento de esta ley;\nXVI. Crear grupos de trabajo para el apoyo de sus funciones;\nXVII. Promover junto con el Sistema Estatal para el Desarrollo Integral de la Familia,\nXVIII. Las demás que se establezcan en otras disposiciones normativas y las que sean necesarias para el funcionamiento del Sistema Estatal.\nLey de Protección Civil y Gestión Integral de Riesgos del Estado de Baja California Página 16\nArtículo 19.- El Consejo Estatal se reunirá en sesiones ordinarias, extraordinarias o permanentes, en comités o en Pleno, a convocatoria de su Presidente, en los plazos y formas que establezca el reglamento.\nArtículo 20.- La facultad de declarar la situación de emergencia, en todo o en parte del territorio del Estado, corresponde al titular del Ejecutivo Estatal.\nArtículo 21.- El Consejo Estatal sesionará permanentemente cuando ocurra un desastre, formulando un diagnóstico y evaluación de la situación de emergencia y, decidir las acciones a tomar, así como determinar los recursos necesarios para la respuesta.\nArtículo 22.- El Secretario General de Gobierno será el Secretario Ejecutivo del\nConsejo Estatal. El Secretario Técnico será el Coordinador Estatal.\nArtículo 23.- El Consejo Estatal sesionará ordinariamente en pleno, por lo menos, dos veces al año y extraordinariamente cuando sea convocado por el Gobernador del Estado.\nArtículo 24.- Corresponde al Secretario Ejecutivo:\nI. Presentar anualmente a la consideración del Consejo Estatal el Informe del Avance del Programa Estatal;\nII. Concertar con los Poderes Legislativo y Judicial del Estado, así como con los municipios y con las organizaciones voluntarias, privadas y sociales el cumplimiento del\nPrograma Estatal;\nIII. Proporcionar a la población en general la información pública que se genere en materia de protección civil relacionada con la autoprotección y el autocuidado;\nIV. Ejecutar y dar seguimiento a los acuerdos y resoluciones del Consejo Estatal y de su Presidente;\nV. Compilar los acuerdos que se tomen en el Consejo Estatal, llevar el archivo de éstos y de los instrumentos jurídicos que deriven y expedir constancia de los mismos;\nVI. Rendir un informe semestral sobre los trabajos del Consejo;\nVII. Celebrar convenios de coordinación, colaboración y concertación necesarios para el cumplimiento de los fines del Sistema Estatal;\nLey de Protección Civil y Gestión Integral de Riesgos del Estado de Baja California Página 17\nVIII. Verificar el cumplimiento de las disposiciones de esta Ley, los convenios generales y específicos en la materia, así como las demás disposiciones aplicables e informar lo conducente al Consejo Estatal;\nIX. Presentar al Consejo Estatal los informes respecto al seguimiento de los acuerdos y resoluciones que se adopten en su seno;\nX. Colaborar con las instituciones que integran el Sistema Estatal, para fortalecer y hacer eficientes los mecanismos de coordinación;\nXI. Coadyuvar con las instancias federales y estatales de fiscalización, proporcionando la información con la que cuente respecto del ejercicio de los recursos de los fondos de ayuda federal y estatal, así como del cumplimiento de esta Ley;\nXII. Supervisar, en coordinación con las demás instancias competentes, la correcta aplicación de los recursos de los fondos de ayuda federal y estatal, y\nXIII. Las demás que le otorga esta Ley y demás disposiciones aplicables, así como las que le encomiende el Consejo Estatal o su Presidente.\nArtículo 25.- Corresponde al Secretario Técnico:\nI. Suplir al Secretario Ejecutivo en sus ausencias;\nII. Elaborar y someter a la consideración del Secretario Ejecutivo, el proyecto de calendario de sesiones del Consejo Estatal y el proyecto de orden del día de cada sesión, para que en su momento sean sometidos a la aprobación del Consejo Estatal;\nIII. Coordinar la realización de los trabajos específicos y acciones que determine el\nConsejo Estatal;\nIV. Coordinar la realización de estudios especializados sobre las materias de protección civil;\nV. Verificar que los programas, estrategias, acciones y políticas que se adopten acuerdos generales que dicte el Consejo Estatal;\nLey de Protección Civil y Gestión Integral de Riesgos del Estado de Baja California Página 18\nVI. Preparar la evaluación de cumplimiento del Programa Estatal de Protección\nCivil, y\nVII. Las demás funciones que se señalen en el Reglamento de esta Ley o que le sean encomendadas por el Presidente o el Secretario Ejecutivo del Consejo Estatal.\nArtículo 26.- Las sesiones del Consejo Estatal serán públicas y podrán transmitirse en directo a través de las tecnologías de la información y la comunicación, salvo que ello comprometa la protección de datos personales o información confidencial en términos de la ley de la materia.\nCAPÍTULO IV\nCOORDINACIÓN ESTATAL DE PROTECCIÓN CIVIL\nArtículo 27.- Para la aplicación de lo dispuesto por la presente Ley, el Ejecutivo del\nEstado contará con una Coordinación Estatal de Protección Civil, la cual dependerá de la\nSecretaría General de Gobierno, tendrá nivel de Dirección General y gozará de autonomía de operación y gestión, teniendo funciones de autoridad en todo lo relativo a la prevención y mitigación ante las amenazas de riesgo geológico, hidrometeoro lógico, químico, sanitario y socio organizativo.\nArtículo 28.- La Coordinación Ejecutiva del Sistema Estatal recaerá en la Secretaría\nGeneral de Gobierno por conducto de la Coordinación Estatal, la cual tiene las atribuciones siguientes en materia de protección civil:\nI. Garantizar el correcto funcionamiento del Sistema Estatal a través de la supervisión y la coordinación de acciones de protección civil que realicen los diversos órdenes de gobierno, mediante la adecuada gestión integral de los riesgos, incorporando la participación activa y comprometida de la sociedad, tanto en lo individual como en lo colectivo;\nII. Asesorar cuando así lo requiera el Consejo Estatal de Protección Civil en temas de materia de Protección Civil, Gestión Integral del Riesgo, Resiliencia y Reducción del Riesgo de Destres;\nIII. Realizar todo tipo de monitoreo que permita evaluar la situación de emergencia en el Estado para su solución;\nIV. Recomendar al Sistema Educativo Estatal la suspensión de clases cuando así lo considere necesario ante una emergencia o desastre que así lo requiera;\nLey de Protección Civil y Gestión Integral de Riesgos del Estado de Baja California Página 19\nV. Difundir la cultura de la protección civil a las dependencias y entidades de la\nAdministración Pública del Estado;\nVI. Atender solicitudes de verificación u opiniones de riesgos por parte de dependencias y entidades de la Administración Pública del Estado, de acuerdo a lo dispuesto en el reglamento de la presente Ley;\nVII. Integrar un catálogo de recursos humanos y materiales de las dependencias y entidades de los tres órdenes de gobierno y del sector social y privado, necesarios de movilizar en caso de desastre;\nVIII. Notificar a dependencias o entidades municipales, estatales o federales sobre cualquier riesgo en materia de protección civil que detecte o le sea notificado;\nIX. Documentar todo tipo de fenómeno perturbador que impacte en el Estado y se considere relevante por la pérdida de vidas humanas, daños a la propiedad privada, infraestructura, equipamiento urbano y al medio ambiente;\nX. Otorgar capacitación y/o asesoría a dependencias y entidades de la\nAdministración Pública del Estado y a la sociedad en general;\nXI. Verificar los avances en el cumplimiento del Programa Estatal;\nXII. Proponer políticas y estrategias para el desarrollo de programas internos, especiales y regionales de protección civil;\nXIII. Promover y apoyar la creación de las instancias, mecanismos, instrumentos y procedimientos de carácter técnico operativo, de servicios y logística que permitan prevenir y la vulnerabilidad;\nXIV. Investigar, estudiar y evaluar riesgos, peligros y vulnerabilidades, integrando y dependencias responsables;\nXV. Difundir, a través de las tecnologías de la información y la comunicación, entre realice, así como toda aquella información pública que tienda a la generación, desarrollo y\nLey de Protección Civil y Gestión Integral de Riesgos del Estado de Baja California Página 20 consolidación de una cultura estatal en la materia, con las reservas que correspondan en materia de transparencia y de seguridad nacional;\nXVI. Gestionar ante la Secretaría de Hacienda y Crédito Público la asesoría y el riesgos a que se refiere el artículo 128 de esta ley;\nXVII. Instrumentar y, en su caso, operar redes de detección, monitoreo, pronóstico y sistemas de alertamiento, en coordinación con las dependencias responsables e incorporando los esfuerzos de otras redes de monitoreo públicas o privadas;\nXVIII. Suscribir convenios en materia de protección civil y de Gestión Integral de\nRiesgos en el ámbito nacional e internacional, en coordinación con las autoridades competentes en la materia;\nXIX. Proteger a personas ante el conocimiento de riesgo inminente de impacto de un fenómeno perturbador, cuando la autoridad competente en el ramo no actúe oportunamente, sin deslindar a ésta de su responsabilidad o ante el conocimiento de algún riesgo inminente que pueda afectar a dos o más municipios del Estado, o en un municipio cuando la autoridad municipal no haya realizado la acción de protección o auxilio a su debido tiempo;\nXX. Ordenar la evacuación o desalojo temporal en propiedad privada de menores de edad, personas con discapacidad o personas vulnerables y, en su totalidad en establecimientos públicos, comercios, servicios o industrias, así como la suspensión temporal de servicios públicos, o suspensión temporal de obras en construcción que pongan en peligro a la población, sus bienes, la infraestructura y/o el medio ambiente;\nXXI. Aprobar los programas internos de protección civil de los establecimientos que conforme a esta ley sean de competencia Estatal;\nXXII. Registrar, supervisar y capacitar a organismos civiles o asociaciones civiles y/o desastres en el tema de protección civil, que operan en más de un municipio, o en zonas rurales.\nXXIII. Inspeccionar y vigilar establecimientos que conforme a esta ley sean de competencia Estatal;\nLey de Protección Civil y Gestión Integral de Riesgos del Estado de Baja California Página 21\nXXIV. Recomendar y notificar por escrito a toda dependencia, sin importar el nivel de gobierno o función que desarrolle, cuando por acción u omisión en materia de protección civil se pone en riesgo a una o más personas, sus bienes, la infraestructura o al medio ambiente; con otras entidades federativas en materia de prevención y atención de emergencias y desastres;\nXXVI. Gestionar ante la Coordinación Nacional de Protección Civil asesoría en la aplicación de los Instrumentos Financieros de Gestión de Riesgos;\nXXVII. Atender y aplicar las disposiciones contenidas en las Normas Oficiales\nMexicanas en materia de Protección Civil;\nXXVIII. Gestionar ante las autoridades correspondientes, la incorporación y ampliación de contenidos de protección civil con un enfoque de Gestión Integral de Riesgos en el\nSistema Educativo Estatal en todos los niveles, desde educación preescolar, primaria y secundaria, hasta los niveles superiores;\nXXIX. Fomentar en la población una cultura de protección civil que le brinde herramientas que en un momento dado le permitan salvaguardar su vida, sus posesiones y su entorno frente a los riesgos derivados de fenómenos naturales y humanos. Para esta tarea, debe considerarse el apoyo de las instituciones y organizaciones de la sociedad civil que cuenten con una certificación de competencia y que esté capacitada para esta actividad;\nXXX. Promover el establecimiento de programas básicos de seguridad por regiones y municipios, para hacer frente a agentes perturbadores recurrentes o imprevistos;\nXXXI. Promover entre las instancias competentes de los distintos órdenes de gobierno, la generación de información relativa a la protección civil, que por su oportunidad, calidad y cantidad fortalezca los procesos de toma de decisiones;\nXXXII. Promover la instrumentación de un Subsistema de Información de Riesgos, Peligros y Vulnerabilidades que permita mantener informada oportunamente a la población;\nXXXIII. Elaborar y mantener actualizado el Atlas Estatal de Riesgos;\nLey de Protección Civil y Gestión Integral de Riesgos del Estado de Baja California Página 22\nXXXIV. Coordinar el apoyo y asesoría a las dependencias y entidades de la constitucionales autónomos en la prevención de emergencias y desastres y, con base en la suscripción de convenios, a los gobiernos de los municipios, así como a las instituciones de carácter social y privado;\nXXXV. Promover y apoyar la capacitación de los profesionales, especialistas y técnicos en materia de protección civil;\nXXXVI. Promover entre los gobiernos estatal y municipales la creación y construcción de infraestructura y la distribución de equipamiento de protección civil, tendientes a fortalecer las herramientas de gestión del riesgo;\nXXXVII. Promover que los gobiernos estatal y municipales elaboren y mantengan actualizados sus respectivos programas de protección civil y formen parte de sus planes de desarrollo;\nXXXVIII. Proponer, en coordinación con la Secretaría de Planeación y Finanzas, los modelos de contratación de seguros e Instrumentos Financieros de Gestión de Riesgos, que garanticen al Estado las mejores condiciones en cuanto a precio, calidad, financiamiento, oportunidad y demás circunstancias pertinentes y\nXXXIX. En los términos de esta Ley, revisar, autorizar y en su caso supervisar mediante las plataformas y sistemas que al efecto establezca, todo tipo de evento o actividades en zonas abiertas que puedan implicar un riesgo para quienes lo realicen, procurando la coordinación de esfuerzos con los tres niveles de gobierno, corporaciones y asociaciones civiles necesarias para cumplir con estos fines;\nXL.- Conformar y coordinar equipos de búsqueda y rescate agreste, así como ante las autoridades competentes, gestionar y aplicar fondos para su ejercicio en caso de emergencias con la finalidad de brindar auxilio y apoyo a grupos voluntarios, en las condiciones que establece esta Ley.\nXLI.- Inspeccionar en forma periódica los establecimientos para plantas de almacenamiento, centros de distribución y estaciones de carburación de gas licuado de petróleo, a fin de verificar si estos han cumplido con los simulacros, programas internos y procedimientos en materia de protección civil, así como si estos cuentan con sistemas de prevención y mitigación de emergencias; y,\nFracción Adicionada\nXLII.- Las demás que señalen los ordenamientos aplicables\nLey de Protección Civil y Gestión Integral de Riesgos del Estado de Baja California Página 23\nArtículo 29.- Para el mejor cumplimiento de sus funciones, la Coordinación Estatal podrá integrar Comités Interinstitucionales para los diferentes agentes perturbadores, riesgo, a fin de reducir al máximo los posibles daños que pudiesen generar. Dichos Comités\nInterinstitucionales, podrán ser técnicamente apoyados por otras instancias técnicas.\nEn el caso de los fenómenos astronómicos, la Coordinación Estatal trabajará conjuntamente con el Centro Nacional de Prevención de Desastres y la Agencia Espacial\nMexicana a fin de crear y promover, en el marco de sus atribuciones, las políticas públicas en materia de prevención o atención de desastres ocasionados por objetos que provengan del espacio exterior.\nAsimismo, el Sistema Estatal coadyuvará a realizar las acciones necesarias de protección civil, de forma coordinada y eficaz, entre los Gobiernos Federal, Estatal y\nMunicipales, los sectores privado y social, así como la población en general, ante el peligro o riesgo específico derivado de un agente perturbador espacial.\nArtículo 30.- La Coordinación Estatal, para efectos presupuestarios, dependerá del presupuesto de la Secretaría, la cual contemplará en cada ejercicio presupuestario los recursos necesarios para que la Coordinación Estatal realice sus tareas y objetivos.\nLos recursos asignados dentro del Presupuesto de Egresos del Estado a la\nCoordinación Estatal no podrán sufrir reducciones a lo largo de un ejercicio fiscal pero sí podrán ser ampliado en la medida de las necesidades supervinientes y de acuerdo a la disponibilidad financiera del Estado.\nArtículo 31.- La Coordinación Estatal tendrá a su cargo el Centro de Operaciones de\nEmergencia para vigilar, notificar y administrar cualquier emergencia o desastre en el estado. El centro deberá cumplir con los requerimientos que prevea el reglamento de la presente Ley.\nCAPÍTULO V\nSISTEMA MUNICIPAL DE PROTECCIÓN CIVIL\nArtículo 32.- Es obligación de los Ayuntamientos establecer el Sistema Municipal de\nProtección Civil.\nAl efecto, los presidentes municipales deberán ejecutar las determinaciones del\nAyuntamiento en materia de Protección Civil e integrar, coordinar y supervisar el Sistema\nMunicipal para la prevención, auxilio, recuperación y apoyo de la población en situaciones de\nLey de Protección Civil y Gestión Integral de Riesgos del Estado de Baja California Página 24 desastre, para lo cual deberán coordinarse con las autoridades de los gobiernos Estatal y\nFederal y, concertar con las instituciones y organismos de los sectores privado y social las acciones conducentes para el logro del mismo objetivo.\nArtículo 33.- El Sistema Municipal es parte integrante del Sistema Estatal, y tiene como fin prevenir y proteger a las personas, su patrimonio y entorno, ante la posibilidad de un desastre producido por causas de origen natural o humano.\nArtículo 34.- El Sistema Municipal será el primer nivel de respuesta ante cualquier fenómeno destructor, que afecte a la población y, será el Presidente Municipal el responsable de coordinar la intervención del Sistema para el auxilio que se requiera.\nArtículo 35.- El Sistema Municipal estará integrado por:\nI. El Consejo Municipal;\nII. La unidad de protección civil municipal;\nIII. Los representantes de los sectores público, social y privado, grupos voluntarios, instituciones educativas y, expertos en diferentes áreas;\nIV. Las Unidades Internas de Protección Civil y\nV. El Centro Municipal de Operaciones.\nArtículo 36.- El Sistema Municipal contará para su adecuado funcionamiento con los siguientes documentos:\nI. Los programas Estatal, Municipal, Internos y Especiales de Protección Civil;\nII. Atlas Nacional, Estatal y Municipal de Riesgos, y\nIII. Inventarios y directorios de recursos humanos y materiales.\nArtículo 37.- La estructura del Sistema Municipal de Protección Civil es parte del\nSistema Estatal de la materia y será determinada por cada ayuntamiento, tomando en consideración la densidad de población y la extensión de su territorio, así como la disponibilidad de recursos humanos, materiales y financieros con que cuente.\nLey de Protección Civil y Gestión Integral de Riesgos del Estado de Baja California Página 25\nEn todo caso, el Presidente Municipal, el Secretario del Ayuntamiento y el Coordinador\nMunicipal fungirán como Presidente, Secretario Ejecutivo y Secretario Técnico, respectivamente, del Consejo Municipal de Protección Civil.\nCAPÍTULO VI\nCONSEJO MUNICIPAL DE PROTECCIÓN CIVIL\nArtículo 38.- El Consejo Municipal es un órgano consultivo de coordinación de acciones y de participación social para la planeación de la protección en el territorio municipal, y será el conducto formal para convocar a los sectores de la sociedad en la integración del Sistema\nMunicipal.\nArtículo 39.- Los Presidentes Municipales, deberán constituir su Consejo Municipal dentro de los sesenta días naturales posteriores a la toma de protesta del Ayuntamiento.\nArtículo 40.- El Consejo Municipal estará integrado por:\nI. El Presidente Municipal, quien lo presidirá;\nII. El Secretario del Ayuntamiento, quien será el Secretario Ejecutivo;\nIII. El titular de la unidad de protección civil municipal, quien será el Secretario\nTécnico;\nIV. Un Regidor designado para atender los asuntos de protección civil;\nV. Los titulares y representantes de las dependencias y entidades de la\nSistema Municipal, con carácter de vocales, y\nVI. Los representantes de las organizaciones social y privada e instituciones académicas radicadas en el Municipio y los grupos voluntarios, previa convocatoria del\nPresidente del Consejo Municipal, con carácter de vocales. conveniente, según el asunto de que se trate, o cuando corresponda a su circunscripción territorial.\nLey de Protección Civil y Gestión Integral de Riesgos del Estado de Baja California Página 26\nArtículo 41.- Son atribuciones del Consejo Municipal:\nI. Fungir como órgano consultivo de planeación, de coordinación y concertación del\nSistema Municipal a fin de orientar las políticas, acciones y objetivos del Sistema;\nII. Hacer propuestas al Ayuntamiento al programa municipal de protección civil y los programas especiales que de él se deriven;\nIII. Supervisar, dar seguimiento y evaluar el funcionamiento de las acciones que en materia de protección civil realice la unidad de protección civil municipal;\nIV. Promover y fomentar entre las instituciones académicas y científicas el estudio e investigación en materia de protección civil;\nV. Evaluar las situaciones de riesgo, con base al análisis que presente la unidad de protección civil municipal y preparar las acciones a tomar en caso de emergencia;\nVI. Sesionar permanentemente cuando ocurra un desastre y apoyar la instalación del Centro Municipal de Operaciones;\nVII. Requerir la ayuda a la Coordinación Estatal, en caso de que sea superada la capacidad de respuesta de la unidad de protección civil municipal;\nVIII. Fomentar la participación activa de todos los sectores de la población, en la integración y ejecución de los programas preventivos;\nIX. Proponer normas y estrategias encaminadas al cumplimiento de los programas municipales, especiales e internos de protección civil;\nX. Establecer y promover la capacitación y actualización permanente de los grupos e individuos que participen en el Sistema Municipal;\nXI. Practicar auditorias operacionales para determinar la aplicación adecuada de los recursos que se asignen al Sistema Municipal, tanto en situación normal, como en estados de emergencia;\nLey de Protección Civil y Gestión Integral de Riesgos del Estado de Baja California Página 27\nXII. Establecer una adecuada coordinación del Sistema Municipal, con los sistemas de los municipios colindantes, así como con los sistemas estatales y nacional;\nXIII. Las demás que señalen las leyes y reglamentos.\nArtículo 42.- El Consejo Municipal se reunirá en sesiones ordinarias y extraordinarias, en comités o en Pleno, a convocatoria del Presidente, trimestralmente. Cuando se ausente el Presidente, serán dirigidas por el Secretario Ejecutivo.\nCAPÍTULO VII\nUNIDAD DE PROTECCIÓN CIVIL MUNICIPAL\nArtículo 43.- Cada municipio integrará dentro de su estructura orgánica una unidad de protección civil municipal, de nivel no menor a Dirección General, dependiente de la\nSecretaría del Ayuntamiento, que realizará sus acciones con un enfoque de Gestión Integral de Riesgos y de Continuidad de Operaciones, debiendo desarrollar sus programas en concordancia con la Coordinación Estatal.\nArtículo 44.- Corresponde al Presidente Municipal:\nI. Nombrar al Coordinador Municipal de Protección Civil;\nII. Dirigir las acciones necesarias para enfrentar, en primera instancia, las emergencias y/o desastres que se presenten en el municipio;\nIII. Administrar los albergues temporales para la atención de población afectada por emergencias o desastres;\nIV. Coordinar y supervisar la elaboración del Atlas Municipal de Riesgos, programa municipal de protección civil, planes de contingencia por temporada y programas especiales\nV. Las demás que le sean conferidas por acuerdo del Consejo Estatal.\nArtículo 45.- La unidad de protección civil municipal gozará de autonomía de operación y gestión, siendo responsable dentro de su ámbito competencial de elaborar, instrumentar, dirigir y operar la ejecución de los programas en la materia, coordinando sus acciones con las dependencias, instituciones y organismos de los sectores público, social, privado y académico, grupos voluntarios y con la población en general.\nLey de Protección Civil y Gestión Integral de Riesgos del Estado de Baja California Página 28\nArtículo 46.- La unidad de protección civil municipal se integrará con las unidades administrativas que establezca el reglamento municipal respectivo.\nArtículo 47.- Las atribuciones de la unidad de protección civil municipal serán las siguientes:\nI. Identificar y diagnosticar los riesgos a los que está expuesto el territorio del Municipio de que se trate, y elaborar el Atlas Municipal de Riesgos;\nII. Elaborar, instrumentar, operar y coordinar el Programa Municipal de Protección\nCivil;\nIII. Elaborar y operar programas especiales de Protección Civil y el Plan Municipal de Contingencias;\nIV. Instrumentar un sistema de seguimiento y autoevaluación del Programa\nMunicipal de Protección Civil e informar al Consejo Municipal sobre su funcionamiento y avances;\nV. Establecer y mantener la coordinación con dependencias, instituciones y organismos del sector público, social y privado involucrados en tareas de protección civil, así como con los de los municipios colindantes del Estado;\nVI. Promover la participación social e integración de grupos voluntarios al Sistema\nMunicipal;\nVII. Promover el establecimiento de las unidades internas y programas de protección civil, especiales y de alerta respectivos en las dependencias estatales y municipales establecidas en el área;\nVIII. Establecer un sistema de información que comprenda los directorios de personas e instituciones, los inventarios de recursos humanos y materiales disponibles en caso de emergencia; así como mapas de riesgos y archivos históricos sobre desastres ocurridos en el municipio;\nIX. Establecer un sistema de comunicación con organismos especializados que realicen acciones de monitoreo, para vigilar permanentemente la posible ocurrencia de fenómenos destructores;\nLey de Protección Civil y Gestión Integral de Riesgos del Estado de Baja California Página 29\nX. Formular, en caso de emergencia, el análisis y evaluación primaria de la magnitud de la misma, y presentar de inmediato esta información al Consejo Municipal sobre su evolución, tomando en cuenta la clasificación de los niveles de la emergencia de prealerta, alerta y alarma;\nXI. Participar en el Centro Municipal de Operaciones;\nXII. Establecer los mecanismos de comunicación tanto en situación normal, como en caso de emergencia, con la Coordinación Estatal y con el Centro de Comunicaciones de la Coordinación Nacional de Protección Civil de la Secretaría de Gobernación;\nXIII. Promover la realización de cursos, ejercicios y simulacros que permitan mejorar la capacidad de respuesta de los participantes en el Sistema Municipal;\nXIV. Fomentar la cultura de protección civil, a través de la realización de eventos, campañas de difusión y capacitación;\nXV. Elaborar y presentar para su aprobación al Ayuntamiento, el Plan Municipal de\nContingencias y\nXVI. Las demás que establezcan las leyes, reglamentos y el Consejo Municipal.\nArtículo 48.- La unidad de protección civil municipal operará coordinadamente con la\nCoordinación Estatal y en su caso, con la Coordinación Nacional de Protección Civil de la\nSecretaría de Gobernación.\nCAPÍTULO VIII\nCENTRO MUNICIPAL DE OPERACIONES\nArtículo 49.- Corresponde al Presidente Municipal coordinar y dirigir técnica y operativamente la atención de emergencias, para lo cual contará con el apoyo del Centro\nMunicipal de Operaciones.\nArtículo 50.- El Centro Municipal de Operaciones se instalará en el domicilio de la unidad de protección civil municipal que corresponda, donde se llevarán a cabo acciones de dirección y coordinación.\nArtículo 51.- El Centro Municipal de Operaciones se integra por:\nI. Un Coordinador, que será el Presidente Municipal o la persona que éste designe y\nLey de Protección Civil y Gestión Integral de Riesgos del Estado de Baja California Página 30\nII. Los titulares o representantes de las demás dependencias públicas estatales y municipales cuyas actividades estén relacionadas con protección civil, y los representantes de los grupos voluntarios y organismos especializados en atención de emergencias.\nArtículo 52.- Compete al Centro Municipal de Operaciones:\nI. Realizar la planeación táctica y logística en cuanto a los recursos necesarios disponibles y las acciones a seguir;\nII. Aplicar el plan de emergencia o los programas establecidos por el Consejo\nMunicipal y establecer la coordinación de las acciones que realicen los participantes en el mismo;\nIII. Concertar con los poseedores de redes de comunicación existentes en el municipio, su eficaz participación en las acciones de protección civil y\nIV. Coordinarse con el Consejo Municipal, en las acciones, personas y recursos disponibles para la atención del desastre, con base en la identificación de riesgos, preparación de la comunidad y capacidad de respuesta municipal, considerando que en caso de que su capacidad de respuesta sea rebasada, se solicitará la intervención estatal.\nArtículo 53.- El Gobierno Municipal, a través de su Coordinador, activará el Centro\nMunicipal de Operaciones con base en la gravedad del impacto producido por una calamidad.\nCAPÍTULO IX\nBOMBEROS\nArtículo 54.- Cada municipio contará con una corporación de bomberos, la cual para efectos de esta ley y sin detrimento de la reglamentación municipal, tendrá las siguientes atribuciones:\nI.- Responder y atender todo tipo de emergencias en materia de protección civil con la finalidad de salvaguardar la vida de las personas, la propiedad privada, la infraestructura, el equipamiento urbano y el medio ambiente;\nII. Revisar, y en su caso aprobar todas las medidas de seguridad de acuerdo a lo químicos-tecnológicos y, de seguridad acuática en todo tipo de giro que así lo requiera;\nLey de Protección Civil y Gestión Integral de Riesgos del Estado de Baja California Página 31\nIII. Contar con personal y equipamiento especializado en rescate de personas;\nIV. Contar con personal y equipamiento especializado en emergencias con materiales y/o residuos peligrosos y\nV. Proveer información a la población en general sobre prevención, mitigación y preparación en temas de riesgo químico-tecnológico y seguridad acuática, privilegiando a los sectores gubernamentales y sociales.\nArtículo 55.- Los derechos generados por cursos o capacitaciones en materia de protección civil que impartan las corporaciones de bomberos deberán estar contemplado en la ley de ingresos del Municipio que corresponda.\nArtículo 56.- Las corporaciones de bomberos nombrarán un responsable que se coordine con el Centro de Operaciones de Emergencia correspondiente, ya sea estatal o municipal.\nArtículo 57.- Las corporaciones de bomberos tendrán la facultad de otorgar los permisos y certificaciones siguientes en materia de protección civil:\nI. Certificado de medidas de seguridad contra incendios;\nII. Certificado de medidas de seguridad contra riesgos químicos;\nIII. Certificado a brigadas contra incendios en empresas que utilicen trajes estructurales de protección personal para combatir incendios de cualquier tipo;\nIV. Certificado a empresas de servicio de extinguidores y/o prevención y supresión de incendios;\nV. Aprobación de todo tipo de proyectos de sistemas y seguridad contra incendios;\nVI. Aprobación en la ubicación e instalación de hidrantes y\nVII. Certificado de proyecto de obra en todo lo relativo a la seguridad contra incendios.\nTÍTULO TERCERO\nLey de Protección Civil y Gestión Integral de Riesgos del Estado de Baja California Página 32\nPLANEACIÓN Y PROGRAMAS\nCAPÍTULO I\nPLANEACIÓN\nArtículo 58.- La Planeación de la Protección Civil deberá llevarse a cabo, como medio\nMunicipal en la materia.\nArtículo 59.- La Planeación de la Protección Civil estará a cargo del Poder Ejecutivo del\nEstado y se fundamentará en:\nI. Plan Nacional de Desarrollo;\nII. Programa Nacional de Protección Civil;\nIII. Planes Estatales y Municipales de Desarrollo\nIV. Planes Estatales y Municipales de Desarrollo Urbano;\nV. Programa Estatal de Protección Civil;\nVI. Programas Municipales de Protección Civil;\nVII. Programas Especiales de Protección Civil, y\nVIII. Programas Internos de Protección Civil.\nEstatal y Municipal, y para los habitantes del Estado.\nCAPÍTULO II\nPROGRAMAS ESTATAL Y MUNICIPALES\nArtículo 60.- Los Programas Estatal y Municipales son el conjunto de objetivos particulares, políticas, líneas de acción y metas que tienen por objeto proteger a la población, sus bienes, servicios estratégicos y su entorno, así como asegurar su\nLey de Protección Civil y Gestión Integral de Riesgos del Estado de Baja California Página 33 funcionamiento mediante las acciones específicas, coordinadas y delimitadas que realicen los sectores público, social y privado en la materia.\nArtículo 61.- El Programa Estatal deberá ser congruente con el Programa Nacional y formará parte del Plan Estatal de Desarrollo.\nArtículo 62.- El Programa Municipal se elaborará conforme a los lineamientos señalados por los instrumentos señalados en el artículo anterior.\nArtículo 63.- Los Programas Especiales de Protección Civil son el instrumento de planeación y operación que se implementa con la participación corresponsable de diversas dependencias e instituciones, ante un peligro o riesgo específico derivado de un agente perturbador en un área o región determinada, que involucran a grupos de población específicos y vulnerables, y que por las características previsibles de los mismos, permiten un tiempo adecuado de planeación, con base en las etapas consideradas en la Gestión\nIntegral de Riesgos.\nArtículo 64.- Los Programas Estatal y Municipales, así como los Internos y Específicos de Protección Civil, serán de cumplimiento obligatorio para la Administración Pública Estatal y Municipal, y, en los términos de las normas federales aplicables, para los servidores públicos de la administración pública federal adscritos en el Estado, así como para las organizaciones civiles, los sectores social y privado y para todos los habitantes en Baja\nCalifornia.\nArtículo 65.- Los objetivos, políticas, líneas de acción, metas y demás aspectos que deban contener los Programas Estatal y Municipales, así como los Internos y Específicos de\nProtección Civil serán establecidos en el Reglamento.\nArtículo 66.- En todo lo relativo a protección civil, las unidades de protección civil municipal, en el ámbito de sus competencias y, en su caso, con el auxilio, de las autoridades federales, estatales y municipales, inspeccionarán, controlarán y vigilarán la debida descritos en este capítulo.\nCAPÍTULO III\nPROGRAMAS INTERNOS DE PROTECCIÓN CIVIL\nArtículo 67.- Es responsabilidad del propietario, responsable legal o titular de dependencia, entidad, institución u organismo del sector público, privado o social, presentar el programa interno de protección civil ante las autoridades competentes para su aprobación.\nLey de Protección Civil y Gestión Integral de Riesgos del Estado de Baja California Página 34 conformidad con esta ley y las disposiciones reglamentarias correspondientes.\nArtículo 68.- Los programas internos de protección civil deberán ser revisados, condicionados y/o aprobados por unidades de protección civil municipal o la Coordinación\nEstatal, según lo especifique la legislación especial que rija a la dependencia, entidad, institución organismo o sujeto obligado a su presentación o en su defecto, en los términos que disponga el reglamento de esta ley.\nArtículo Reformado\nArtículo 69.- Los programas internos señalados en las fracciones I, II, III y IV del artículo 74 de la presente Ley deberán ser desarrollados por personas acreditadas ante la\nCoordinación Estatal.\nArtículo 70.- Los planes de contingencia contra incendios, materiales peligrosos y seguridad acuática solicitados por las corporaciones de bomberos de los municipios deberán formar parte de los programas internos de protección civil y estar sujetos a los requisitos estipulados en el reglamento de la presente ley.\nArtículo 71.- No se podrá condicionar ningún permiso de operación municipal con la obligación de la presentación del programa interno de protección civil, cuando las instalaciones relacionadas con el programa interno no están debidamente terminadas y listas para operar o ser utilizadas.\nArtículo 72.- La capacitación en temas de protección civil que realice la Coordinación\nEstatal sólo se podrá otorgar a los organismos de la sociedad civil registrados en el Estado, a las dependencias de gobierno federal establecidas en el Estado y a las propias dependencias del gobierno estatal, cuando tengan aprobado el programa interno de protección civil de acuerdo a la presente Ley, o solo se podrá otorgar capacitación en los temas propios para poder cumplir con el desarrollo del programa interno de protección civil.\nArtículo 73.- Toda organización de la sociedad civil deberá cumplir con el programa interno de protección civil previsto por esta Ley; las autoridades brindarán subsidiariamente el apoyo necesario para el cumplimiento de esta obligación.\nPárrafo Reformado\nLas entidades, dependencias u organismos de gobierno incentivarán a las organizaciones de la sociedad civil que cumplan con el programa interno de protección civil.\nPárrafo Reformado\nLey de Protección Civil y Gestión Integral de Riesgos del Estado de Baja California Página 35 anteceden, los organismos de la sociedad civil que no cuenten con su programa interno de protección civil aprobado, deberán acreditar estar en vías de cumplimiento de los trámites correspondientes ante las autoridades municipales o estatales según sea el caso. Lo anterior deriven.\nPárrafo Reformado\nArtículo 74.- Los obligados a elaborar un programa interno de protección civil se clasificarán de la siguiente manera:\nI.- Edificios y servicios a personas vulnerables, sin importar las dimensiones del lugar o la cantidad de personas atendidas:\na) Centros de Asistencia Social a que refiere la Ley para la Protección y Defensa de los Derechos de Niñas, Niños y Adolescentes del Estado;\nb) Centros de Atención que presten servicios para la atención, cuidado y desarrollo integral infantil;\nc) Centros para atención a personas con sesenta años o más de edad;\nd) Hospitales y clínicas;\ne) Centros de atención a personas con discapacidad;\nf) Escuelas de educación preescolar;\ng) Escuelas de educación especial;\nh) Centros de atención a personas con adicciones;\ni) Todo tipo de albergue para personas.\nII.- Industrias consideradas como de alto riesgo por las cantidades o volúmenes de materiales peligrosos que manejan, de acuerdo con lo estipulado por las autoridades federales y estatales responsables del ramo, y las que la propia Coordinación Estatal considere, incluyendo las plantas de almacenamiento, centros de distribución y estaciones pirotécnicos.\nFracción Reformada\nIII.- Edificios y servicios considerados prioritarios y estratégicos para otorgar servicios vitales y de gobierno:\na) Hospitales y clínicas con servicio de quirófano;\nLey de Protección Civil y Gestión Integral de Riesgos del Estado de Baja California Página 36\nb) Edificios de la administración pública de todo tipo, de los tres órdenes de gobierno;\nc) Centros de Comunicación, Cómputo, Control y Comando;\nd) Estaciones de Bomberos;\ne) Edificios de la Cruz Roja;\nf) Estaciones de policía;\ng) Todo tipo y niveles de escuelas del Sistema Educativo Estatal;\nh) Potabilizadoras de agua de la Comisión Estatal de Servicios Públicos;\ni) Empresas generadoras de energía eléctrica que ofrecen su servicio para el territorio nacional;\nj) Empresas de telefonía;\nk) Aeropuertos civiles;\nl) Puertos navales;\nm) Almacenes de hidrocarburos; así como plantas de almacenamiento, centros de distribución y estaciones de carburación de gas licuado de petróleo.\nInciso Reformado\nn) Estaciones de radio y/o televisión que cuentan con plantas de energía eléctrica autónoma;\no) Estaciones de gasolina que cuentan con plantas de energía autónoma.\np) Presas.\nIV.- Establecimientos comerciales y de servicios de esparcimiento o actos religiosos o de culto en áreas cerradas, sin importar dimensiones del lugar:\na) Cines;\nb) Teatros;\nc) Museos;\nd) Centros nocturnos;\ne) Bares;\nf) Salones de fiesta y de baile;\ng) Restaurantes;\nh) Cafés;\ni) Casinos;\nj) Auditorios;\nk) Centros de espectáculos y convenciones;\nl) Parques de diversiones con juegos mecánicos;\nm) Palenques;\nLey de Protección Civil y Gestión Integral de Riesgos del Estado de Baja California Página 37\nn) Estadios;\no) Parques y/o deportivos con gradas;\np) Iglesias, templos y en general establecimientos de culto religioso.\nq) Albercas.\nV. Las demás que no se encuentren clasificadas en este artículo y que disponga la legislación aplicable.\nFracción Adicionada\nArtículo 75.- Toda instalación o servicio deberá contar con el permiso de operaciones del ayuntamiento donde se encuentre desarrollando sus actividades, para tal efecto, la autoridad municipal respectiva, deberá solicitar al interesado o responsable de la instalación, establecimiento o servicio, el programa interno de protección civil debidamente aprobado por la o las autoridades correspondientes según sea el giro de acuerdo al reglamento de la presente Ley.\nArtículo 76.- Los establecimientos a que refiere la fracción IV del artículo 74 deberán especificar en el programa interno de protección civil los tipos de eventos que se podrán llevar a cabo en su instalación y éstos deberán ser acordes con el permiso de operaciones que el ayuntamiento le otorgó.\nArtículo 77.- Si el programa interno de protección civil no define el tipo de espectáculo o evento que se pretenda realizar en el inmueble, el interesado deberá pedir anuencia especial para el evento y revisión especial de las medidas de seguridad, por escrito, a las autoridades de protección civil, tanto municipal como estatal.\nArtículo 78.- Previo a la realización de eventos públicos y en espacios de concentración masiva, deberán elaborarse programas específicos de protección civil, los cuales serán entregados oportunamente a las autoridades de protección civil para su aprobación y coordinación con otras instancias de seguridad. del evento o al inicio del mismo.\nArtículo 79.- Los promotores, organizadores o responsables de la realización de eventos o espectáculos públicos de afluencia masiva deberán, con anticipación mínima de cinco días hábiles, presentar a la Coordinación Estatal un programa específico de protección civil, acorde a las características de tales eventos o espectáculos y dar aviso a la unidad de protección civil municipal.\nLey de Protección Civil y Gestión Integral de Riesgos del Estado de Baja California Página 38\nReglamento.\nArtículo 80.- Para los efectos de esta Ley y los reglamentos que de ella deriven, se consideran de alto riesgo, los inmuebles y eventos o espectáculos públicos de afluencia masiva:\nI. Que cuenten con un aforo o capacidad mayor a 1,000 personas.\nII. Que se realicen en espacio cerrado con un aforo o capacidad mayor a 500 personas.\nIII. Con una construcción mayor a 3,000 metros cuadrados, o\nIV. Donde se realicen actividades que por su naturaleza pongan en peligro la integridad de las personas.\nEn atención a lo que dispone la fracción IV de este artículo, se considerará como actividades que por su naturaleza representen un peligro a la población, a las instalaciones que lleven a cabo labores de almacenamiento, distribución y comercialización de gas licuado de petróleo, de conformidad al Sistema Estatal de Protección Civil del Estado.\nPárrafo Adicionado\nLa Coordinación Estatal deberá diseñar los padrones de registro de las instalaciones de gas licuado de petróleo, en los términos del Reglamento.\nPárrafo Adicionado\nTodos los casos anteriores serán responsabilidad de la Coordinación Estatal, salvo que correspondiente.\nEl Ejecutivo del Estado y los Municipios inspeccionarán, regularán y vigilarán respectivamente que los inmuebles, espacios e instalaciones móviles a su cargo o de su competencia cumplan con las disposiciones en materia de protección civil, así como aquellos eventos que en el ejercicio de sus atribuciones organicen.\nEn aquellos eventos con aforo o capacidad de más de 10,000 personas, será responsabilidad exclusiva de la Coordinación Estatal.\nLey de Protección Civil y Gestión Integral de Riesgos del Estado de Baja California Página 39\nArtículo 80 BIS. - Están prohibidas las acciones de almacenamiento de recipientes transportables de gas licuado de petróleo, en sus diversas capacidades y de consumo en los aplicable.\nArtículo Adicionado\nArtículo 80 TER. - Para mitigar los riesgos de transportación, cada vehículo de autotanques de reparto y de distribución de gas licuado de petróleo deberá atender las disposiciones que señale la normatividad aplicable.\nArtículo Adicionado\nArtículo 80 QUATER. - Las personas físicas o morales que cuenten con la titularidad de algún permiso de distribución de gas licuado de petróleo, tendrán prohibido por sí o a través de su personal, realizar acciones de trasiego en la vía pública, así como también en lugares o instalaciones sin autorización para ello conforme a la normatividad aplicable.\nArtículo Adicionado\nArtículo 80 QUINQUIES. - Quienes operen vehículos de auto-tanques, reparto y distribución de gas licuado de petróleo tienen la obligación de cumplir con las Normas\nOficiales Mexicanas y demás normatividad aplicable, y deberán portar en el vehículo los siguientes documentos:\nArtículo Adicionado\nI. Copia del permiso de distribución vigente otorgado por la Secretaría de Energía;\nII. Constancia de capacitación personal, expedida por personas, instituciones u organismos reconocidos por la Coordinación Estatal, en los siguientes temas:\na) Manejo de fugas.\nb) Manejo y combate de incendios.\nc) Primeros auxilios.\nIII. Póliza de seguro de responsabilidad civil vigente.\nIV. Copia del dictamen técnico vigente emitido por la Coordinación Estatal, mismo que deberá ser aprobado por la autoridad federal correspondiente.\nArtículo 81.- En el reglamento de esta Ley se establecerán los procedimientos para dar cumplimiento a los preceptos del presente capítulo por parte de la Coordinación Estatal.\nLey de Protección Civil y Gestión Integral de Riesgos del Estado de Baja California Página 40\nCAPÍTULO IV\nUNIDADES INTERNAS DE PROTECCIÓN CIVIL\nArtículo 82.- Las dependencias, instituciones o entidades pertenecientes a los sectores público, privado y social integrarán a su estructura orgánica Unidades Internas de Protección protección civil, así como elaborar, actualizar, operar y vigilar el Programa Interno de\nProtección Civil y realizar simulacros por lo menos tres veces al año, en coordinación con la\nCoordinación Estatal o la unidad de protección civil municipal, según corresponda.\nArtículo 83.- La Coordinación Estatal y las unidades de protección civil municipal, de conformidad a sus atribuciones, asesorarán a las empresas, así como los centros laborales, asociaciones, organismos y entidades de los sectores privado y social, para integrar sus\nUnidades Internas de Protección Civil.\nArtículo 84.- De conformidad con la Ley General, una brigada es un grupo de personas que se organiza dentro de un inmueble, capacitadas y adiestradas en funciones básicas de respuesta a emergencias tales como primeros auxilios, combate a conatos de incendio, evacuación, búsqueda y rescate; designados en la Unidad Interna de Protección Civil como encargados del desarrollo y ejecución de acciones de prevención, auxilio y recuperación, con base en lo estipulado en el Programa Interno de Protección Civil del inmueble.\nArtículo 85.- Los brigadistas deberán contar con todas las facilidades para su capacitación y desarrollo del entrenamiento y actividades relacionadas con dicha actividad.\nArtículo 86.- Ningún brigadista deberá arriesgar, ante ninguna circunstancia, su integridad física y/o su salud en el desarrollo de sus labores.\nArtículo 87.- A ningún brigadista se le considerará como bombero profesional o voluntario, por lo que no deberá realizar ninguna actividad relativa al combate de incendios estructurales dentro de su centro de trabajo; así mismo, no deberá portar o utilizar el equipo de protección personal para dicha actividad fuera del centro de trabajo, a menos que el\nCorporación de Bomberos del municipio donde se encuentra laborando.\nArtículo 88.- La primera instancia de actuación especializada, corresponde a las\nUnidades Internas de Protección Civil de cada instalación pública o privada, así como a la autoridad municipal que conozca de la situación de emergencia. Además, corresponderá en vigilancia y aplicación de medidas de seguridad.\nLey de Protección Civil y Gestión Integral de Riesgos del Estado de Baja California Página 41\nArtículo 89.- En caso de que la emergencia o desastre supere la capacidad de respuesta del municipio, acudirá a la instancia estatal, en los términos de la legislación aplicable. Si ésta resulta insuficiente, se procederá a informar a las instancias federales correspondientes, las que actuarán de acuerdo con los programas establecidos al efecto, en los términos de esta Ley y de las demás disposiciones jurídicas aplicables.\nCAPÍTULO V\nCAPACITACIÓN Y PROFESIONALIZACIÓN DE LA PROTECCIÓN CIVIL\nArtículo 90.- Para que los particulares o dependencias públicas puedan ejercer la actividad de asesoría y capacitación deberán contar con el registro expedido por la\nCoordinación Estatal, se les denominará agentes consultores capacitadores y deberán renovar sus registros cada dos años, estarán sujetos a lo especificado en el reglamento de la presente Ley.\nIgualmente será obligatorio para los sujetos señalados en el párrafo anterior obtener el registro en tratándose de actividades de evaluación, elaboración de programas internos de protección civil, de continuidad de operaciones y estudios de vulnerabilidad y riesgos en materia de protección civil.\nArtículo 91.- Los agentes consultores capacitadores con especialidad en rescate y atención de emergencias en materia de protección civil y bomberos, tanto externos como gubernamentales deberán estar certificados por el Comité Estatal de Certificación a que refiere la presente ley.\nArtículo 92.- Los agentes consultores capacitadores que deseen realizar estudios o evaluaciones sobre riesgo sísmico y/o hidrometeorológico, deberán tener un certificado especial al respecto emitido por la Coordinación Estatal de acuerdo a lo estipulado en el reglamento de la presente ley.\nArtículo 93.- La profesionalización de los integrantes del Sistema Nacional será permanente y tendrá por objeto lograr una mejor y más eficaz prestación del servicio, así civil de carrera cuando se trate de servidores públicos de los tres órdenes de gobierno, de conformidad a lo que se establezca en la Ley de la materia.\nArtículo 94.- Para los efectos del artículo anterior, los gobiernos estatal y municipales haga sus veces, en la que se deberá regular el ingreso, formación, permanencia, promoción, Ley de Protección Civil y Gestión Integral de Riesgos del Estado de Baja California Página 42 estímulos a los miembros del Sistema Estatal, conforme a las características que le son propias, y a los requerimientos de la sociedad y del Estado.\nTÍTULO CUARTO\nRECURSOS PARA LA PROTECCIÓN CIVIL\nCAPÍTULO I\nFONDO ESTATAL DE PROTECCIÓN CIVIL\nArtículo 95.- El Poder Ejecutivo del Estado creará y administrará un Fondo Estatal de\nProtección Civil cuya finalidad será la de promover la capacitación, equipamiento y sistematización de las unidades de protección civil.\nArtículo 96.- El patrimonio del fondo será constituido por los recursos anuales aprobados por el H. Congreso del Estado al Poder Ejecutivo del Estado y, en su caso, con las aportaciones de los municipios, las donativos de personas físicas, morales y organizaciones nacionales e internacionales, además de lo que se recaude de las sanciones económicas aplicadas por la Coordinación Estatal, y con los demás recursos que se obtengan por las aportaciones establecidas en otras disposiciones en materia de protección civil.\nEl Ejecutivo Estatal gestionará ante el Gobierno Federal los subsidios a dicho Fondo\nEstatal de Protección Civil, conforme a los recursos que, en su caso, sean aprobados para dicho fin en el Presupuesto de Egresos de la Federación.\nEl Fondo Estatal de Protección Civil operará según se establezca el reglamento de esta ley y en el caso de los recursos federales, en términos de los convenios de coordinación que se celebren, precisando para ello los requisitos para el acceso, ejercicio y comprobación de los recursos, así como las obligaciones en el manejo y mantenimiento de los equipos adquiridos. administrará y operará el Fondo Estatal de Protección Civil. informe amplio, detallado y actualizado sobre los recursos económicos ingresados, así como su manejo y destino; lo anterior, sin perjuicio de la fiscalización de que sea objeto por parte\nLey de Protección Civil y Gestión Integral de Riesgos del Estado de Baja California Página 43\nCAPÍTULO II\nDONATIVOS PARA AUXILIAR A LA POBLACIÓN de competencia, establecerán en las disposiciones reglamentarias correspondientes las bases y lineamientos para emitir las convocatorias, recepción, administración, control y distribución de los donativos que se aporten con fines altruistas para atención de emergencias o desastres ocasionados por cualquier fenómeno natural perturbador o antropogénico, con apego a lo establecido en la presente Ley.\nAsimismo, determinarán con apego a la legislación local aplicable, los criterios de uso y destino de los donativos, debiendo en todos los casos rendir un informe detallado a la entidad fiscalizadora del Estado.\nLas personas físicas o morales que deseen colaborar con la captación de donativos en especie deberán obtener la autorización de la Coordinación Estatal, conforme a los requisitos y criterios que establezca el Reglamento de esta Ley.\nArtículo 99.- Sin menoscabo de lo que expresa el artículo anterior, el Ejecutivo Estatal deberá promover al interior del Consejo Estatal un mecanismo ágil, transparente y efectivo de control y coordinación para que los recursos donados sean administrados y entregados en beneficio de la población en situación de emergencia o desastre.\nArtículo 100.- Los donativos se sujetarán al tratamiento fiscal en materia de aportaciones previsto en el Código Fiscal del Estado de Baja California y en las demás disposiciones normativas aplicables.\nArtículo 101.- Las autoridades correspondientes deberán verificar que en todo la emergencia y/o desastre con nivel económico y social bajo, a los grupos vulnerables, así como, en su caso, a favor de programas de apoyo específicos a microempresarios y pequeños productores.\nTÍTULO QUINTO\nPARTICIPACIÓN SOCIAL Y PRIVADA\nCAPÍTULO I\nPARTICIPACIÓN CIUDADANA\nLey de Protección Civil y Gestión Integral de Riesgos del Estado de Baja California Página 44 participación corresponsable de la sociedad en la formulación, ejecución y evaluación de los programas y acciones de protección civil que se emprendan en la entidad.\nArtículo 103.- Los habitantes del Estado, de forma libre, organizada y voluntaria, podrán coadyuvar con las autoridades en las acciones de protección civil, previstas en los programas y acciones a que se refiere esta Ley.\nArtículo 104.- Toda persona tiene el derecho y la obligación de denunciar ante la autoridad estatal o municipal, cualquier hecho, acto u omisión que cause o pueda causar situaciones de peligro o emergencia para la población, por la eminencia o eventualidad de algún desastre o calamidad pública, que pueda representar perjuicio en su persona o la de terceros, en sus bienes o en su entorno.\nEl reglamento indicará la forma, plazos y términos en que se deberá presentar la denuncia.\nLo anterior se hará sin perjuicio de que la autoridad tome las medidas urgentes necesarias para evitar que se ponga en riesgo la seguridad de la población, sus bienes y entorno.\nLos grupos vulnerables de la población que se encuentren expuestos a un peligro, tienen derecho a estar informados de ello y a contar con las vías adecuadas de opinión y participación en la gestión del riesgo.\nArtículo 105.- Las autoridades competentes, en términos de esta Ley, atenderán de manera permanente al público en general en el ejercicio de la denuncia popular. Para ello difundirán ampliamente, a través de los medios de comunicación, así como el mecanismo, domicilio, números telefónicos y correo electrónico destinados a recibir las denuncias, para lo cual deberán contar con diferentes plataformas digitales.\nArtículo 106.- Dentro de las acciones que promuevan las unidades de protección civil, en términos de esta Ley, para la participación social en materia de protección civil, se observará lo siguiente:\nI. Convocarán a representantes de organizaciones sociales, empresariales, de instituciones educativas públicas y privadas, para que manifiesten su opinión y propuesta;\nII. Otorgarán reconocimientos a los esfuerzos más destacados de la sociedad para promover la prevención, mitigación y auxilio en caso de desastre, y\nLey de Protección Civil y Gestión Integral de Riesgos del Estado de Baja California Página 45\nIII. Impulsarán el desarrollo de la cultura de protección civil, a través de la realización de acciones conjuntas con la comunidad para la prevención, mitigación y auxilio en caso de desastre.\nCAPÍTULO II\nGRUPOS VOLUNTARIOS\nArtículo 107.- Los habitantes del Estado podrán participar, de manera libre y organizada, en grupos voluntarios para apoyar en las acciones de protección civil, siempre bajo la supervisión de la Coordinación Estatal o unidad de protección civil municipal, según corresponda.\nLas personas que deseen desempeñar labores de rescate y auxilio, deberán integrarse o constituirse preferentemente en grupos voluntarios.\nAquellos que no deseen integrarse a un grupo voluntario podrán registrarse individualmente en las unidades de protección civil correspondientes, precisando su actividad, oficio o profesión, así como su especialidad aplicable a tareas de protección civil.\nArtículo 108.- El Consejo Estatal y los Consejos Municipales, promoverán la participación de los grupos voluntarios debidamente organizados, para que manifiesten sus propuestas y participen en la elaboración de planes, programas y políticas en la materia.\nArtículo 109.- La organización de los grupos voluntarios podrá integrarse por municipios y podrán celebrar convenios de concertación a fin de prevenir y controlar situaciones de emergencia provocadas por cualquier fenómeno natural perturbador o antropogénico.\nArtículo 110.- Es obligación de los grupos voluntarios ya constituidos o que se integren en la entidad, registrarse en la unidad de protección civil municipal correspondiente, a fin de recibir información, participar en programas de capacitación, prevención y difusión. de los grupos voluntarios registrados en el municipio.\nArtículo 111.- El representante de cada grupo voluntario deberá integrarse al Centro\nMunicipal de Operaciones cuando se ordene la activación de éste.\nArtículo 112.- Corresponde a los Grupos Voluntarios:\nLey de Protección Civil y Gestión Integral de Riesgos del Estado de Baja California Página 46\nI. Acatar la organización y supervisión de la unidad de protección civil municipal de cada\nAyuntamiento, para las tareas de prevención, auxilio y recuperación en casos de desastre por la presencia de cualquier fenómeno natural perturbador o antropogénico;\nII. Cooperar en la preparación y difusión de planes y programas de protección civil;\nIII. Comunicar a la unidad de protección civil municipal correspondiente, en su caso, la presencia de cualquier situación de probable o inminente riesgo, con el objeto de que se verifique la información y en su caso, se tomen las medidas que correspondan;\nIV. Participar en los programas de capacitación a la población, para que pueda auto protegerse en caso de desastre y\nV. Participar en otras actividades que les sean requeridas y que estén en capacidad de desarrollar.\nArtículo 113.- Los servicios prestados por cualquier grupo voluntario serán gratuitos.\nArtículo 114.- Las empresas que realicen labores de instalación, carga, recarga y mantenimiento de sistemas de extinción de incendios en más de un municipio del Estado deberán estar registradas ante la Coordinación Estatal, debiendo contar con un domicilio fiscal en cualquiera de los municipios del Estado; tener la autorización del municipio, tanto de administración urbana como de bomberos donde ofrezcan sus servicios, y del municipio donde se encuentre el taller de inspección, mantenimiento, carga y recarga de extintores, así como cumplir con las normas oficiales mexicanas correspondientes.\nPara que la empresa pueda prestar el servicio de capacitación en uso de extinguidores y ataque a incendios, deberán contar con personal debidamente certificados por la\nCorporación de Bomberos del municipio donde se encuentra operando.\nArtículo 115.- Todo grupo u organización dedicada a la atención de emergencias relacionadas con la Protección Civil que preste su servicios en un solo municipio, deberá opera, y la unidad de protección civil municipal deberá notificar por escrito a la Coordinación\nEstatal sobre el registro en mención en un término menor a 10 días hábiles.\nArtículo 116.- Grupos o empresas de cualquier tipo de atención pre- hospitalaria o de\nLey de Protección Civil y Gestión Integral de Riesgos del Estado de Baja California Página 47\nArtículo 117.- Los instructores internos de los grupos voluntarios de rescate deberán\nAtención de Emergencias en Materia de Protección Civil y Bomberos.\nArtículo 118.- Los requisitos para obtener el registro ante la Coordinación Estatal y las obligaciones de los grupos voluntarios se establecerán en el reglamento de la presente ley.\nCAPÍTULO III\nFAMILIA Y CULTURA DE PROTECCIÓN CIVIL\nArtículo 119.- La familia deberá cumplir su función social de manera constante y permanente, debiendo instrumentar un Plan Familiar de Protección Civil al interior del seno familiar, responsabilizándose de contar con lo necesario para prevenir o, en su caso, enfrentar cualquier situación de riesgo por la presencia de cualquier fenómeno natural perturbador o antropogénico.\nArtículo 120.- En una situación de emergencia, provocada por cualquier fenómeno natural perturbador o antropogénico, el auxilio a las familias debe constituirse en una función prioritaria de la protección civil, por lo que las instancias de coordinación deberán actuar en forma conjunta y ordenada, en los términos de esta Ley y de las demás disposiciones aplicables.\nArtículo 121.- Las autoridades estatales y municipales, fomentarán la cultura de protección civil entre la sociedad, de manera individual, familiar y colectiva.\nLas autoridades en la materia, establecerán mecanismos idóneos para que la sociedad, de manera individual, familiar y colectiva participe en la planeación y supervisión de la protección civil, en los términos de esta Ley, su Reglamento y los demás ordenamientos aplicables.\nArtículo 122.- Corresponde a la Coordinación Estatal dictar los lineamientos generales y diseñar formas para inducir y conducir la formación de una cultura de protección civil.\nArtículo 123.- A fin de fomentar dicha cultura, las unidades de protección civil, dentro de sus respectivos ámbitos de competencia, deberán:\nLey de Protección Civil y Gestión Integral de Riesgos del Estado de Baja California Página 48\nI. Fomentar las actividades de protección civil;\nII. Impulsar programas dirigidos a la población en general que le permita conocer de forma clara mecanismos de prevención y autoprotección;\nIII. Elaborar, estructurar y promocionar campañas de difusión sobre temas de su\nIV. Promover la celebración de convenios con los sectores público, social, privado y académico con el objeto de difundir la cultura de protección civil.\nArtículo 124.- Los integrantes del Sistema Estatal promoverán mecanismos para motivar y facilitar la participación de sus dependencias de forma activa, real, concreta y responsable en acciones específicas que reflejen una cultura de protección civil.\nTÍTULO SEXTO\nPREVENCIÓN\nCAPÍTULO I\nGESTIÓN INTEGRAL DE RIESGOS\nArtículo 125.- La Gestión Integral de Riesgos considera, entre otras, las siguientes antropogénico:\nI. Conocimiento del origen y naturaleza de los riesgos, además de los procesos de construcción social de los mismos;\nII. Identificación de peligros, vulnerabilidades y riesgos, así como sus escenarios;\nIII. Análisis y evaluación de los posibles efectos;\nIV. Revisión de controles para la mitigación del impacto;\nV. Acciones y mecanismos para la prevención y mitigación de riesgos;\nVI. Desarrollo de una mayor comprensión y concientización de los riesgos, y\nLey de Protección Civil y Gestión Integral de Riesgos del Estado de Baja California Página 49\nVII. Fortalecimiento de la resiliencia de la sociedad. competencia, deberán establecer los lineamientos generales en materia de protección civil\nOperaciones, sean un valor de política pública y una tarea transversal para que con ello se realicen acciones de orden preventivo, con especial énfasis en aquellas que tienen relación directa con la salud, la educación, el ordenamiento territorial, la planeación urbano-regional, la conservación y empleo de los recursos naturales, la gobernabilidad y la seguridad.\nArtículo 127.- Corresponde al Poder Ejecutivo del Estado promover, ante la eventualidad de los desastres de origen natural, la realización de acciones dirigidas a una estrategia integral de transferencia de riesgos, a través de la identificación de la infraestructura por asegurar, el análisis de los riesgos, las medidas para su reducción y la definición de los esquemas de retención y aseguramiento, entre otros.\nPara el cumplimiento de lo dispuesto en el párrafo anterior, las dependencias y entidades estatales ejecutoras deberán identificar las obras que formarán parte del inventario estatal de infraestructura para su aseguramiento. Dicho inventario se integrará con base en los lineamientos que emita la Secretaria de Planeación y Finanzas.\nArtículo 128.- Es responsabilidad del Poder Ejecutivo y de los Municipios, conforme a su disponibilidad presupuestaria, la contratación de seguros y demás instrumentos de administración y transferencia de riesgos para la cobertura de daños causados por un desastre natural en los bienes y servicios estratégicos del Estado.\nPara el cumplimiento de esta obligación, el Poder Ejecutivo del Estado podrá solicitar que los Instrumentos de Administración y Transferencia de Riesgos que contraten sean complementados con los Instrumentos Financieros de Gestión de Riesgos Federales conforme a lo establecido en los lineamientos que para tal efecto se emitan. cumplieron con los principios de economía, eficacia, eficiencia, imparcialidad, honradez y transparencia que aseguren las mejores condiciones para el Estado.\nArtículo 129.- Los fenómenos antropogénicos son en esencia provocados por la actividad humana y no por un fenómeno natural. Generan un marco de responsabilidad civil, previstos en esta Ley.\nLey de Protección Civil y Gestión Integral de Riesgos del Estado de Baja California Página 50 reducir o mitigar los riesgos antropogénicos, así como de atención a la población en caso de contingencias derivadas de tales fenómenos.\nLas instalaciones de almacenamiento, centros de distribución y estaciones de carburación del rubro de gas licuado de petróleo, están obligadas a contar con póliza de seguro vigente, autorizada por la Comisión Nacional de Seguros y Fianzas, como garantía de daños parciales y totales a terceros o sus bienes, previendo que estas actividades representan por su propia naturaleza un riesgo para la población.\nPárrafo Adicionado\nArtículo 130.- Toda emergencia relacionada con materiales o residuos peligrosos será atendida por la Corporación de Bomberos del ayuntamiento donde ocurre.\nArtículo 131.- El equipo de protección personal y los instrumentos que utilicen las corporaciones de bomberos deberán estar certificados por normas nacionales o internacionales y su personal deberá estar certificado por instructores reconocidos por el\nComité Estatal para la Certificación de Instructores de Rescate y Atención de Emergencias y en Materia de Protección Civil y Bomberos, con la finalidad de responder de manera eficiente y con la mejor preparación posible y adecuada a las emergencias donde se involucren materiales y residuos químicos peligrosos.\nCAPÍTULO II\nSIMULACROS\nArtículo 132.- Las dependencias y organismos de la administración pública estatal y de los ayuntamientos, así como las empresas comerciales, industriales y de servicios, centros laborales, asociaciones, organismos y entidades de los sectores privado y social, deberán perturbador o antropogénico, de acuerdo a su Programa Interno de Protección Civil.\nArtículo 133.- En todos los simulacros se deberá contar con un aviso por escrito a las autoridades de protección civil correspondientes, el cual se hará con un mínimo de quince días hábiles previos a su realización.\nArtículo 134.- El escenario simulado a elegir deberá plantearse con base en el análisis actuación deberán coincidir con el mismo.\nLey de Protección Civil y Gestión Integral de Riesgos del Estado de Baja California Página 51\nArtículo 135.- Los simulacros se deberán llevar a cabo con una periodicidad de dos veces al año y, una vez concluidos, deberán contar con una evaluación por escrito, emitida por la Unidad Interna de Protección Civil.\nArtículo 136.- La autoridad de protección civil correspondiente, podrá solicitar en considere necesario.\nArtículo 137.- Toda Unidad Interna de Protección Civil deberá contar con evidencia documental de los simulacros realizados, que contenga, por lo menos, personal participante, material fotográfico, copia de oficios girados a las autoridades correspondientes, así como acta de resultados firmada por un representante de cada brigada.\nCAPÍTULO III\nDETECCIÓN DE ZONAS DE RIESGO\nArtículo 138.- El Gobierno Estatal, con la participación de los gobiernos municipales, deberá buscar concentrar la información climatológica, geológica, meteorológica y astronómica de que se disponga a nivel nacional, relacionada con el Estado.\nArtículo 139.- El Gobierno Estatal, con la participación de los gobiernos municipales, promoverá la creación de las bases que permitan la identificación y registro en los Atlas\nEstatal y Municipales de Riesgos de las zonas en el Estado con riesgo para la población, el patrimonio público y privado, que posibilite a las autoridades competentes regular la edificación de asentamientos.\nArtículo 140.- Son autoridades competentes para aplicar lo dispuesto por este Capítulo, dentro del ámbito de sus respectivas atribuciones conforme a la Ley:\nI. Las distintas Dependencias del Ejecutivo estatal;\nII. La Procuraduría General de Justicia del Estado;\nIII. Los Gobiernos de los Municipios;\nArtículo 141.- En el Atlas Estatal de Riesgos y en los respectivos Atlas Municipales de\nRiesgos, deberán establecerse los diferentes niveles de peligro y riesgo, para todos los fenómenos que influyan en las distintas zonas. Dichos instrumentos deberán ser tomados en consideración por las autoridades competentes, para la planeación urbana y el establecimiento de políticas de desarrollo y acciones de prevención; así como para la autorización o no de cualquier tipo de construcciones, obras de infraestructura o asentamientos humanos.\nLey de Protección Civil y Gestión Integral de Riesgos del Estado de Baja California Página 52\nArtículo 142.- En el caso de asentamientos humanos ya establecidos en Zonas de Alto\nRiesgo, las autoridades competentes con base en estudios de riesgos específicos, el riesgo a que están expuestas o, de ser el caso, deberán formular un plan a fin de determinar cuáles de ellos deben ser reubicados, proponiendo mecanismos financieros que permitan esta acción.\nArtículo 143.- El Poder Ejecutivo del Estado buscará y propondrá mecanismos para la transferencia de riesgos a través de la contratación de seguros o de otros instrumentos financieros.\nArtículo 144.- Las autoridades estatales y las de los municipios determinarán qué autoridad bajo su estricta responsabilidad, tendrá competencia y facultades para autorizar la utilización de una extensión territorial en consistencia con el uso de suelo permitido, una vez consideradas las acciones de prevención o reducción de riesgo a que se refieren los artículos de este Capítulo.\nArtículo 145.- La autorización de permisos de uso de suelo o de utilización por parte de servidores públicos de cualquiera de los tres niveles de gobierno, que no cuenten con la aprobación correspondiente, se considerará una conducta grave, la cual se sancionará de acuerdo con la Ley de Responsabilidad de los Servidores Públicos respectiva.\nCAPÍTULO IV\nATENCIÓN A LA POBLACIÓN RURAL AFECTADA POR CONTINGENCIAS\nCLIMATOLÓGICAS\nArtículo 146.- El Gobierno Estatal y los Gobiernos Municipales deberán concurrir, tanto en acciones como en la aportación de recursos, para la instrumentación de programas que coadyuven a la reincorporación de los productores agrícolas, pecuarios, acuícolas y pesqueros a sus actividades productivas.\nArtículo 147.- El Gobierno Estatal deberá crear una reserva especial para el sector agrícola, pecuario, acuícola y pesquero con el propósito de proveer de recursos en forma expedita para atender contingencias climatológicas, cuando los recursos asignados en el\nPresupuesto de Egresos del Estado se hubiesen agotado.\nTÍTULO SÉPTIMO\nSANCIONES Y DEL RECURSO DE REVISIÓN\nCAPÍTULO I\nLey de Protección Civil y Gestión Integral de Riesgos del Estado de Baja California Página 53\nSANCIONES\nArtículo 148.- Las violaciones y el incumplimiento de preceptos de esta Ley, su administrativamente por las unidades de protección civil, según corresponda, con las siguientes sanciones:\nI. Amonestación;\nII. Multa equivalente de veinte a mil UMA;\nIII. Clausura temporal o definitiva, total o parcial de los establecimientos, obras, instalaciones o servicios;\nIV. Suspensión o revocación de autorizaciones que se hubieren otorgado por la\nCoordinación Estatal o por la unidad de protección civil municipal y\nV. Arresto administrativo hasta por 36 horas.\nPara el caso de reincidencia, la sanción podrá ser hasta por dos veces el monto de la multa inicialmente impuesta, sin exceder del doble del máximo permitido.\nArtículo 149.- La imposición de sanciones se hará sin perjuicio de la responsabilidad que conforme a otras leyes corresponda al infractor.\nArtículo 150.- Al imponerse una sanción se tomará en cuenta:\nII. La gravedad de la infracción;\nIII. Las condiciones socioeconómicas del infractor y\nIV. La reincidencia. impliquen infracciones a un mismo precepto, en un período de dos años, contados a partir de la fecha en que se levante el acta en que se hizo constar la primera infracción, siempre que esta no hubiese sido desvirtuada.\nLey de Protección Civil y Gestión Integral de Riesgos del Estado de Baja California Página 54\nArtículo 151.- En los casos en que se defina la clausura temporal o definitiva, total o parcial de una obra, instalación o establecimiento, la Coordinación Estatal o la unidad de protección civil municipal, según corresponda, podrá solicitar a la autoridad competente la suspensión o cancelación de cualquier permiso o licencia que se hubiere otorgado.\nArtículo 152.- Cuando se imponga como sanción la suspensión de una obra, instalación o servicio, se ordenará al infractor que realice los actos o subsane las omisiones que motivaron la misma, fijando un plazo prudente para ello a juicio de la Coordinación Estatal o de la unidad de protección civil municipal, según corresponda, en la inteligencia de que la suspensión continuará hasta en tanto no se cumpla con lo ordenado.\nArtículo 153.- Tratándose de clausura temporal o definitiva, el personal encargado de ejecutarla deberá levantar acta circunstanciada observando las formalidades establecidas para las inspecciones.\nArtículo 154.- En el caso de que la unidad de protección civil municipal correspondiente, además de la sanción determine la necesidad de demolición, retiro, construcción o modificación de obras e instalaciones, ordenará al infractor su realización. Si éste no cumple en el plazo que para ello se le haya fijado, la unidad de protección civil municipal que corresponda lo comunicará a la autoridad municipal respectiva, para que proceda a su realización con cargo al infractor.\nArtículo 155.- Independientemente de las sanciones administrativas que se impongan al infractor, las unidades de protección civil municipal, en su caso, harán del conocimiento del Ministerio Público los hechos que pudieran constituir conductas delictivas.\nCAPÍTULO II\nRECURSO DE REVISIÓN\nArtículo 156.- Contra las sanciones que impongan las unidades de protección civil procede el recurso de revisión.\nSerá optativo agotar este recurso, o bien, intentar directamente el juicio ante el Tribunal de lo Contencioso Administrativo.\nArtículo 157.- El recurso administrativo de revisión tiene por objeto que el superior jerárquico examine si en el acto o actos recurridos se aplicó correctamente la ley, si se violaron las formalidades del procedimiento o si se alteraron los hechos que lo motivaron, a fin de confirmarlo, modificarlo o revocarlo, según proceda.\nLey de Protección Civil y Gestión Integral de Riesgos del Estado de Baja California Página 55\nEl superior jerárquico de la Coordinación Estatal es el Ejecutivo del Estado, y en el caso de las unidades de protección civil municipal, es el Presidente Municipal correspondiente.\nArtículo 158.- El recurso de revisión se interpondrá por escrito ante la autoridad que emitió el proveído que se impugna en un plazo perentorio de cinco días hábiles, contados a partir de la fecha de notificación.\nPara los efectos del presente capítulo y tratándose de los actos emitidos por la\nCoordinación Estatal, se aplicará el recurso previsto en la Ley del Procedimiento para los\nActos de la Administración Pública.\nEn el caso de actos emitidos por las unidades de protección civil municipal, el recurso de revisión contemplado en esta ley se substanciará en los términos de las disposiciones reglamentarias municipales.\nPRIMERO.- La presente Ley entrará en vigor al día siguiente de su publicación en el\nPeriódico Oficial del Estado.\nSEGUNDO.- Se abroga la Ley de Protección Civil del Estado de Baja California, TERCERO.- El Ejecutivo Estatal emitirá el Reglamento de esta Ley en un plazo no mayor a 180 días a partir de su publicación.\nCUARTO.- Los sujetos obligados por esta ley tendrán un plazo de 180 días a partir de protección civil.\nQUINTO.- Para efectos de lo previsto en el artículo 148, fracción II, el valor de la unidad\nMedida y Actualización.\nLey de Protección Civil y Gestión Integral de Riesgos del Estado de Baja California Página 56\nEstado de Baja California, en la Ciudad de Mexicali, B.C., a los treinta y uno días del mes de agosto del año dos mil diecisiete.\nDIP. EDGAR BENJAMÍN GÓMEZ MACÍAS\nPRESIDENTE\n(RÚBRICA)\nDIP. EVA MARÍA VÁSQUEZ HERNÁNDEZ\nSECRETARIA\n(RÚBRICA)\nDE CONFORMIDAD CON LO DISPUESTO POR LA FRACCIÓN I DEL ARTÍCULO 49 DE\nMEXICALI, BAJA CALIFORNIA, A LOS SIETE DÍAS DE SEPTIEMBRE DEL AÑO DOS MIL\nDIECISIETE.\nFRANCISCO ARTURO VEGA DE LAMADRID\nGOBERNADOR DEL ESTADO\n(RÚBRICA)\nFRANCISCO RUEDAS GÓMEZ\nSECRETARIO GENERAL DE GOBIERNO\n(RÚBRICA)\nLey de Protección Civil y Gestión Integral de Riesgos del Estado de Baja California Página 57\nLey de Protección Civil y Gestión Integral de Riesgos del Estado de Baja California Página 58\nArtículo 2.- Fue reformado mediante Decreto No. 248, publicado en Periódico Oficial No. 33, de fecha 13 de julio 2018, Sección III, Tomo CXXV, expedido por la H. XXII Legislatura, siendo Gobernador Constitucional el C. Francisco Arturo Vega de Lamadrid 2013-2019;\nArtículo 28.- Fue reformado mediante Decreto No. 248, publicado en Periódico Oficial No.\n33, de fecha 13 de julio 2018, Sección III, Tomo CXXV, expedido por la H. XXII Legislatura, siendo Gobernador Constitucional el C. Francisco Arturo Vega de Lamadrid 2013-2019;\nArtículo 68.- Fue reformado mediante Decreto No. 236, publicado en Periódico Oficial No.\n33, de fecha 20 de abril 2018, Sección X, Tomo CXXV, expedido por la H. XXII Legislatura, siendo Gobernador Constitucional el C. Francisco Arturo Vega de Lamadrid 2013-2019;\nArtículo 73.- Fue reformado mediante Decreto No. 234, publicado en Periódico Oficial No.\n20, de fecha 20 de abril 2018, Sección X, Tomo CXXV, expedido por la H. XXII Legislatura, siendo Gobernador Constitucional el C. Francisco Arturo Vega de Lamadrid 2013-2019;\nArtículo 74.- Fue reformado mediante Decreto No. 248, publicado en Periódico Oficial No.\n33, de fecha 13 de julio 2018, Sección III, Tomo CXXV, expedido por la H. XXII Legislatura, siendo Gobernador Constitucional el C. Francisco Arturo Vega de Lamadrid 2013-2019;\nArtículo 80.- Fue reformado mediante Decreto No. 248, publicado en Periódico Oficial No.\n33, de fecha 13 de julio 2018, Sección III, Tomo CXXV, expedido por la H. XXII Legislatura, siendo Gobernador Constitucional el C. Francisco Arturo Vega de Lamadrid 2013-2019;\nArtículo 80 BIS.- Fue adicionado mediante Decreto No. 248, publicado en Periódico Oficial\nNo. 33, de fecha 13 de julio 2018, Sección III, Tomo CXXV, expedido por la H. XXII\nLegislatura, siendo Gobernador Constitucional el C. Francisco Arturo Vega de Lamadrid\n2013-2019;\nArtículo 80 TER.- Fue adicionado mediante Decreto No. 248, publicado en Periódico Oficial\nNo. 33, de fecha 13 de julio 2018, Sección III, Tomo CXXV, expedido por la H. XXII\nLegislatura, siendo Gobernador Constitucional el C. Francisco Arturo Vega de Lamadrid\n2013-2019;\nArtículo 80 QUATER.- Fue adicionado mediante Decreto No. 248, publicado en Periódico\nOficial No. 33, de fecha 13 de julio 2018, Sección III, Tomo CXXV, expedido por la H. XXII\nLegislatura, siendo Gobernador Constitucional el C. Francisco Arturo Vega de Lamadrid\n2013-2019;\nArtículo 80 QUINQUIES.- Fue adicionado mediante Decreto No. 248, publicado en Periódico\nOficial No. 33, de fecha 13 de julio 2018, Sección III, Tomo CXXV, expedido por la H. XXII\nLegislatura, siendo Gobernador Constitucional el C. Francisco Arturo Vega de Lamadrid\n2013-2019;\nLey de Protección Civil y Gestión Integral de Riesgos del Estado de Baja California Página 59\nArtículo 129.- Fue reformado mediante Decreto No. 248, publicado en Periódico Oficial No.\n33, de fecha 13 de julio 2018, Sección III, Tomo CXXV, expedido por la H. XXII Legislatura, siendo Gobernador Constitucional el C. Francisco Arturo Vega de Lamadrid 2013-2019;\nARTÍCULO ÚNICO TRANSITORIO DEL DECRETO No. 234, POR EL QUE SE\nAPRUEBA LA REFORMA AL ARTÍCULO 73; PUBLICADO EN EL PERIÓDICO OFICIAL No.\n20, TOMO CXXV, SECCIÓN X, DE FECHA 20 DE ABRIL DE 2018, EXPEDIDO POR LA H.\nXXII LEGISLATURA, SIENDO GOBERNADOR CONSTITUCIONAL EL C. FRANCISCO\nARTURO VEGA DE LAMADRID 2013-2019.\nTRANSITORIOS\nPRIMERO. - Las presentes reformas entrarán en vigor al día siguiente de su publicación en el Periódico Oficial del Estado de Baja California.\nSEGUNDO. - La autoridad estatal y municipales previstas por esta Ley, impulsarán a las organizaciones de la sociedad civil para que cumplan con el programa interno de protección civil, brindándoles la asesoría necesaria. Cuando conforme a los estudios socioeconómicos que la autoridad les practique requieran del apoyo para solventar su programa interno de protección civil, la autoridad competente, subsidiariamente les apoyará con los dictámenes que formen parte del Programa.\nDADO en el Teatro Universitario Rubén Vizcaíno Valencia, de la Universidad\nAutónoma de Baja California (UABC), en la Ciudad de Tijuana, B.C., a los veintidós días del mes de marzo del año dos mil dieciocho.\nDIP. MTRO. RAÚL CASTAÑEDA POMPOSO\nPRESIDENTE\n(RÚBRICA)\nDIP. ROCÍO LÓPEZ GOROSAVE\nSECRETARIA\n(RÚBRICA)\nDE CONFORMIDAD CON LO DISPUESTO POR LA FRACCIÓN I DEL ARTÍCULO 49\nMEXICALI, BAJA CALIFORNIA, A LOS DIEZ Y NUEVE DÍAS DEL MES DE ABRIL\nDEL AÑO DOS MIL DIECIOCHO.\nFRANCISCO ARTURO VEGA DE LAMADRID\nGOBERNADOR DEL ESTADO\n(RÚBRICA)\nLey de Protección Civil y Gestión Integral de Riesgos del Estado de Baja California Página 60\nFRANCISCO RUEDA GÓMEZ\nSECRETARIO GENERAL DE GOBIERNO\n(RÚBRICA)\nARTÍCULO ÚNICO TRANSITORIO DEL DECRETO No. 236, POR EL QUE SE\nAPRUEBA LA REFORMA AL ARTÍCULO 68; PUBLICADO EN EL PERIÓDICO OFICIAL No.\n33, TOMO CXXV, SECCIÓN II, DE FECHA 13 DE JULIO DE 2018, EXPEDIDO POR LA H.\nXXII LEGISLATURA, SIENDO GOBERNADOR CONSTITUCIONAL EL C. FRANCISCO\nARTURO VEGA DE LAMADRID 2013-2019.\nTRANSITORIOS\nPRIMERO. - La presente reforma entrara en vigor al día siguiente de su publicación en el\nPeriódico Oficial del Estado de Baja California.\nSEGUNDO. – Hasta en tanto entre en vigor la reglamentación a que se hace referencia el artículo 68 reformado, los programas internos cuya revisión no esté encomendada a esta\nLey a una autoridad determinada, deberán ser revisados y aprobados por la unidad de\nProtección Civil Municipal del domicilio del sujeto obligado o la Coordinación Estatal, según corresponda al orden del Gobierno Municipal o Estatal la competencia para el conocimiento, supervisión, inspección, vigilancia o en su caso, la aplicación de sanciones para la operación de la dependencia, entidad, institución, organismo o sujeto obligado a su presentación.\nDADO en el Salón de Sesiones “Lic. Benito Juárez García” del H. Poder Legislativo del\nEstado de Baja California, en la Ciudad de Mexicali, B.C., a los doce días del mes de abril del año dos mil dieciocho.\nDIP. MARCO A. CORONA BOLAÑOS CACHO\nPRESIDENTE\n(RÚBRICA)\nDIP. VICTORIA BENTLEY DUARTE\nSECRETARIA\n(RÚBRICA)\nDE CONFORMIDAD CON LO DISPUESTO POR LA FRACCIÓN I DEL ARTÍCULO 49\nMEXICALI, BAJA CALIFORNIA, A LOS TRECE DÍAS DEL MES DE JULIO DEL AÑO\nDOS MIL DIECIOCHO.\nFRANCISCO ARTURO VEGA DE LAMADRID\nGOBERNADOR DEL ESTADO\n(RÚBRICA)\nLey de Protección Civil y Gestión Integral de Riesgos del Estado de Baja California Página 61\nFRANCISCO RUEDA GÓMEZ\nSECRETARIO GENERAL DE GOBIERNO\n(RÚBRICA)\nARTÍCULO TERCERO TRANSITORIO DEL DECRETO No. 248, POR EL QUE SE\nREFORMA EL ARTÍCULO 2, 28, 74, 80, 129 Y SE ADICIONAN LOS ARTÍCULOS 80 BIS,\n80 TER, 80 QUATER Y 80 QUINQUIES; PUBLICADO EN EL PERIÓDICO OFICIAL No. 33,\nTOMO CXXV, SECCIÓN III, DE FECHA 13 DE JULIO DE 2018, EXPEDIDO POR LA H. XXII\nLEGISLATURA, SIENDO GOBERNADOR CONSTITUCIONAL EL C. FRANCISCO ARTURO\nVEGA DE LAMADRID 2013-2019.\nTRANSITORIOS\nPRIMERO. - Las presentes reformas entrarán en vigor al día siguiente de su publicación en el Periódico Oficial del Estado.\nDADO en el Salón de Sesiones “Lic. Benito Juárez García” del H. Poder Legislativo del\nEstado de Baja California, en la Ciudad de Mexicali, B.C., a los doce días del mes de julio del año dos mil dieciocho.\nDIP. MARCO A. CORONA BOLAÑOS CACHO\nPRESIDENTE\n(RÚBRICA)\nDIP. VICTORIA BENTLEY DUARTE\nSECRETARIA\n(RÚBRICA)\nDE CONFORMIDAD CON LO DISPUESTO POR LA FRACCIÓN I DEL ARTÍCULO 49\nMEXICALI, BAJA CALIFORNIA, A LOS TRECE DÍAS DEL MES DE JULIO DEL AÑO\nDOS MIL DIECIOCHO.\nFRANCISCO ARTURO VEGA DE LAMADRID\nGOBERNADOR DEL ESTADO\n(RÚBRICA)\nFRANCISCO RUEDA GÓMEZ\nSECRETARIO GENERAL DE GOBIERNO\n(RÚBRICA)\nLey de Protección Civil y Gestión Integral de Riesgos del Estado de Baja California Página 62",
  "ordenamiento": "REGLAMENTO",
  "jurisdiccion": "BAJA CALIFORNIA",
  "fuente_oficial": "Periódico Oficial",
  "FECHA PER OFIC": "2018/07/13",
  "ESTATUS": "VIGENTE",
  "TOMO": "TOMO_VII",
  "URL": "https://www.congresobc.gob.mx/Documentos/ProcesoParlamentario/Leyes/TOMO_VII/13072018_LEYPROCIV.PDF",
  "es_escaneado": false,
  "tiene_tablas": false,
  "materia": [
    "ambiental",
    "urbanismo",
    "infraestructura"
  ]
}