{
  "titulo": "Ley DE PRESERVACIÓN DEL PATRIMONIO CULTURAL DEL ESTADO DE BAJA CALIFORNIA",
  "Contenido": ".\nActualización Legislativa.\nÚltima Reforma P. O. No. 37, Índice, 20-Jun-2025\nFue modificada la denominación de la Ley de Patrimonio Cultural del Estado de Baja\nCalifornia por Decreto No. 233, publicado en el Periódico Oficial No. 45, Tomo CV, de fecha\n06 de noviembre de 1998, expedido por la Honorable XV Legislatura, siendo Gobernador\nConstitucional el c. Lic. Héctor Terán Terán 1995-2001;\nLEY DE PRESERVACION DEL PATRIMONIO CULTURAL DEL\nESTADO DE BAJA CALIFORNIA\nPublicado en el Periódico Oficial No. 39, de fecha 18 de agosto de 1995, Tomo CII.\nCAPITULO I\nDISPOSICIONES GENERALES\nARTICULO 1.- Las disposiciones de esta Ley, son de orden público e interés social y tienen por objeto:\nI.- Establecer las bases para preservar el patrimonio cultural del Estado de Baja\nCalifornia.\nII.- Establecer funciones de identificación, evaluación, conservación y difusión del conocimiento de los bienes culturales\nArtículo Reformado\nARTICULO 2.- Derogado;\nArtículo Derogado\nARTICULO 3.- Para efectos de esta ley, se considera como patrimonio cultural del\nEstado, previa declaratoria correspondiente, al conjunto de bienes y expresiones artísticas e intelectuales desarrollados en la entidad; la suma de obras de relevancia histórica, estética, arquitectónica, urbanística, científica y tecnológica; el compendio de manifestaciones y prácticas sociales significativas desde el punto de vista de los valores y tradiciones populares, así como los bienes y zonas paleontológicas, arqueológicas, históricas y naturales de importancia para los habitantes del Estado.\nArtículo Reformado\nARTICULO 4.- El patrimonio cultural de Baja California estará integrado por los siguientes bienes que se localicen en su territorio:\nI.- Edificios;\nII.- Sitios;\nIII.- Estructuras;\nIV.- Objetos;\nLey de Preservación del Patrimonio Cultural del Estado de Baja California. Página 1\n.\nActualización Legislativa.\nÚltima Reforma P. O. No. 37, Índice, 20-Jun-2025\nV.- Zonas de entorno;\nVI.- Zonas protegidas;\nVII.- Valores Culturales;\nVIII.- Obras y expresiones artísticas, científicas y tecnológicas, y\nIX.- Acervos contenidos en museos, bibliotecas y archivos del Estado.\nArtículo Reformado\nARTICULO 5.- Para efectos de esta Ley se entiende por:\nI.- Edificios: Construcciones creadas principalmente para cobijar o permitir el desarrollo de cualquier actividad humana, que se encuentren vinculadas a la historia social, política, económica, cultural, artística y religiosa del Estado, o que tengan más de cuarenta y nueve años de construido, así como aquellas relacionadas con la vida de un personaje de la historia de la entidad.\nII.- Sitios: Se refiere a lugares o localidades donde ocurrieron o se descubran hechos o acontecimientos significativos, una ocupación o actividad histórica o prehistórica, existan edificios o estructuras en pie, ruinas o vestigios que, por sí mismos posean valor histórico, cultural, paleontológico o arqueológico\nIII.- Estructuras: Se distinguen entre edificios y objetos, y se refiere a una construcción hecha para un propósito funcional, estético o simbólico.\nIV.- Objetos: Se refiere a bienes muebles que son principalmente de naturaleza artística, asociados como un entorno, un lugar específico y un tiempo determinado.\nV.- Zona de entorno: Area territorial arquitectónica, urbanística o natural, que colinda perimetralmente, que conduce hacia un monumento o zona de bienes paleontológicos, arqueológicos, históricos o artísticos, que hayan sido declarados por la autoridad federal o por disposición de la ley de la materia. También se incluyen las áreas que rodean un bien cultural declarado por el Gobierno del Estado.\nVI.- Zonas protegidas: Areas geográficas unificadas que contengan una concentración de edificios, estructuras, sitios o elementos naturales con significado histórico, cultural y artístico, y cuya preservación sea de interés para los habitantes del Estado.\nEstas zonas se dividen en:\na) Centro histórico: Área que delimita los espacios urbanos donde se originaron los centros de población.\nb) Distritos urbanos y rurales: Las regiones, ciudades, pueblos, colonias, localidades o parte de ellos, que por haber conservado en gran proporción la forma y la unidad de su trazo urbano o sus patrones de asentamiento rural, edificaciones, estructuras y jardines, así como sus tradiciones, costumbres y otros elementos, posean valores históricos culturales y artísticos.\nLey de Preservación del Patrimonio Cultural del Estado de Baja California. Página 2\n.\nActualización Legislativa.\nÚltima Reforma P. O. No. 37, Índice, 20-Jun-2025\nc) Zonas de belleza natural y cultural: Los sitios o las regiones geográficas que contengan recursos humanos y culturales asociados con acontecimientos históricos o que posean relevancia por sus valores estéticos, plásticos o tradicionales. Además de la topografía, la flora y la fauna, estas zonas pueden incluir estanques, corrientes de agua, fuentes, veredas, escalones, muros, edificios, bancas y objetos escultóricos.\nVII.- Valores culturales: El conjunto de conocimientos, representaciones y visiones del mundo cuyas manifestaciones posean interés desde el punto de vista de las tradiciones, las costumbres, la creación artística e intelectual, y los conocimientos científicos y tecnológicos propios de los habitantes de Baja California, pudiendo ser cualquiera de los siguientes:\na) Manifestaciones de interés cultural: Aquellas manifestaciones que sean representativas de la creatividad, del desarrollo intelectual y espiritual, y de los valores culturales de los habitantes del Estado.\nb) Festividades Populares: El conjunto de actividades recreativas, conmemorativas, religiosas, cívicas o laicas que expresen las tradiciones y fomenten los valores de convivencia, tolerancia e identidad nacional y regional de y entre los grupos sociales residentes en el Estado.\nc) Los idiomas de Baja California: El español, los idiomas y dialectos de las etnias de\nBaja California, y los idiomas y dialectos de los migrantes radicados en el Estado.\nd) Toponimia regional: El nombre de Baja California, así como los nombres y designaciones originales otorgadas a los lugares y accidentes geográficos de Baja\nCalifornia.\nVIII.- Obras y expresiones artísticas, científicas y tecnológicas: El conjunto de obras, bienes muebles e inmuebles y todas las expresiones derivadas del campo de producción artística y tecnológica, relevantes para el desarrollo cultural de los habitantes del Estado.\nIX.- Acervos contenidos en los museos, bibliotecas y archivos en el Estado: El conjunto de textos y registros históricos, bibliográficos, hemerográficos, fotográficos y audiovisuales en medios magnéticos, digitales y cinematográficos.\nArtículo Reformado\nARTICULO 6.- Quedan excluidos del régimen de esta ley los monumentos o zonas de monumentos arqueológicos, históricos o artísticos del dominio federal, que lo sean por declaratoria de autoridad competente o por disposición de Ley, en los términos de legislación federal aplicable.\nArtículo Reformado\nARTICULO 7.- Las condiciones necesarias para la operación, administración, mantenimiento, utilización, exhibición, preservación y, en general, la adecuada protección de los bienes señalados en las fracciones VIII y IX del artículo 4 de este ordenamiento legal, se ajustarán a lo señalado en esta Ley y la legislación federal de la materia.\nARTICULO 8.- Son supletorias de esta ley, a falta de disposición expresa:\nLey de Preservación del Patrimonio Cultural del Estado de Baja California. Página 3\n.\nActualización Legislativa.\nÚltima Reforma P. O. No. 37, Índice, 20-Jun-2025\nI.- El Código Civil y el de Procedimientos Civiles de Baja California; y\nII.- Las demás leyes locales, relacionadas con las materias que regula esta ley.\nCAPITULO II\nDE LAS AUTORIDADES Y\nORGANOS DE APOYO\nDenominación Modificada\nARTICULO 9.- La aplicación de esta Ley corresponde a:\nI.- La persona titular del Poder Ejecutivo del Estado;\nFracción Reformada\nII.- La Secretaría General de Gobierno;\nIII.- La Secretaría de Infraestructura, Desarrollo Urbano y Reordenación Territorial;\nFracción Reformada\nIV.- La Secretaría de Cultura;\nFracción Reformada\nV.- El Consejo del Patrimonio Cultural de Baja California;\nVI.- Las Comisiones de preservación del Patrimonio Cultural en cada Municipio del\nEstado;\nVII.- Las demás autoridades estatales, en el ámbito de su competencia.\nVIII.- Las autoridades municipales, en el ámbito de su competencia.\nArtículo Reformado\nARTICULO 10.- Son órganos de apoyo para la aplicación de esta ley:\nI.- Los organismos y asociaciones civiles que tengan como fin o interés, la defensa y protección del patrimonio cultural y que estén debidamente acreditados ante la Secretaría;\nFracción Reformada\nII.- Los colegios y las asociaciones de profesionistas a las que las disposiciones jurídicas les den ese carácter, previo registro ante la Secretaría;\nFracción Reformada\nIII.- Las instituciones de educación e investigación superior en el Estado;\nIV.- Las autoridades federales en el ámbito de su competencia.\nArtículo Reformado\nSECCIÓN PRIMERA\nDenominación Modificada\nLey de Preservación del Patrimonio Cultural del Estado de Baja California. Página 4\n.\nActualización Legislativa.\nÚltima Reforma P. O. No. 37, Índice, 20-Jun-2025\nARTICULO 11.- Corresponderá a la persona titular del Poder Ejecutivo del Estado las siguientes facultades:\nPárrafo Reformado\nI.- Dirigir la administración de los bienes que integran el Patrimonio Cultural del\nEstado, en la esfera de su competencia;\nII.- Publicar las declaratorias de los bienes comprendidos en el artículo 5 de esta ley;\nIII.- Autorizar los programas de preservación del Patrimonio Cultural de Baja California a que se refiere el Capítulo décimo segundo de esta Ley;\nIV.- Ejercer las facultades en materia de desarrollo urbano que le corresponda, en los términos de la legislación aplicable, con el objeto de preservar cualquiera de los bienes comprendidos en las fracciones V, VI y VII del artículo 4 de esta Ley;\nV.- Reglamentar y publicar las disposiciones reglamentarias necesarias para la preservación del Patrimonio Cultural del Estado, en el ámbito de sus facultades;\nVI.- Presidir el Consejo del Patrimonio Cultural de Baja California;\nVII.-Derogada;\nVIII.- Ejercer todas las demás facultades conferidas por las disposiciones federales y estatales relacionadas con la protección del Patrimonio Cultural de Baja California.\nArtículo Reformado\nSECCION SEGUNDA\nDE LA SECRETARIA GENERAL DE GOBIERNO\nARTICULO 12.- La Consejería Jurídica será la encargada de formular las iniciativas que deban convertirse en decretos del Ejecutivo del Estado según convenga para su aplicación conforme a la ley, en base a los expedientes integrados por la Secretaría de\nCultura.\nArtículo Reformado\nSECCION TERCERA\nDE LA SECRETARÍA DE INFRAESTRUCTURA, DESARROLLO URBANO Y\nREORDENAMIENTO TERRITORIAL\nDenominación Modificada\nARTICULO 13.- La Secretaría de Infraestructura, Desarrollo Urbano y efecto de que, dentro del marco de su competencia, se preserve el valor cultural de los bienes y zonas señaladas en la presente ley.\nArtículo Reformado\nSECCION CUARTA\nDE LAS AUTORIDADES ESTATALES Y MUNICIPALES\nLey de Preservación del Patrimonio Cultural del Estado de Baja California. Página 5\n.\nActualización Legislativa.\nÚltima Reforma P. O. No. 37, Índice, 20-Jun-2025\nARTICULO 14.- Las autoridades estatales y municipales actuarán en el ámbito de su propia competencia, conforme a las facultades que les sean expresamente conferidas por la legislación federal, estatal o municipal y por esta misma ley.\nARTICULO 15.- Los ayuntamientos deberán constituir en el ámbito de su competencia, organismos que tiendan a preservar la cultura, y promoverán la formación de asociaciones civiles, comisiones vecinales, patronatos, fundaciones, fideicomisos, así como la organización de los representantes de los sectores más significativos de la población, como órganos auxiliares para impedir el deterioro o destrucción del patrimonio y promover su adecuado desarrollo.\nArtículo Reformado\nARTICULO 16.- Derogado;\nArtículo Derogado\nSECCION QUINTA\nSECRETARÍA DE CULTURA\nDenominación Modificada\nARTICULO 17.- La Secretaría de Cultura será la autoridad competente en materia de protección del Patrimonio Cultural del Estado. En el articulado de esta Ley y su Reglamento se referirá a esta autoridad, indistintamente, con su denominación completa o como “la\nSecretaría”.\nArtículo Reformado\nARTICULO 18.- Serán atribuciones de la Secretaría las siguientes:\nPárrafo Reformado\nI.- Administrar los bienes que conformen el Patrimonio Cultural del Estado;\nII.- Coordinar con las autoridades municipales, estatales y federales las acciones inherentes a la preservación del Patrimonio Cultural del Estado;\nIII.- Actuar como órgano de enlace entre las autoridades y de las demás entidades federativas para coordinar las acciones de preservación del Patrimonio Cultural Estado;\nBaja California;\nFracción Reformada proyectos de las declaratorias de adscripción de bienes, programas de preservación, reglamentos y demás disposiciones relativas al patrimonio cultural del Estado;\nFracción Reformada\nLey de Preservación del Patrimonio Cultural del Estado de Baja California. Página 6\n.\nActualización Legislativa.\nÚltima Reforma P. O. No. 37, Índice, 20-Jun-2025\nVI.- Representar al Ejecutivo del Estado ante las autoridades culturales federales o de cualquier otra Entidad Federativa, en asuntos relacionados con la preservación del\nPatrimonio Cultural de Baja California;\nFracción Reformada\nVII.- Actuar como Secretaría Técnica del Consejo del Patrimonio Cultural de Baja\nCalifornia, y en caso de ausencia de la Persona Titular del Poder Ejecutivo del Estado, presidir las reuniones del mismo;\nFracción Reformada\nVIII.- Cumplir y vigilar que las demás autoridades cumplan y hagan cumplir las disposiciones de esta Ley;\nIX.- Elaborar y difundir un informe detallado en el que dará a conocer los bienes que forman parte del patrimonio cultural de la Entidad, los alcances y logros obtenidos por el\nConsejo del Patrimonio Cultural de Baja California y las Comisiones de Preservación del\nPatrimonio Cultural Municipales, así como los recursos presupuestales ejercidos en relación a las atribuciones que les confiere esta ley.\nEl informe a que hace mención esta fracción deberá estar publicado permanentemente en la página de internet de la Secretaría; adicionalmente, podrá difundir dicho informe, o un resumen del mismo, por otros medios de comunicación de acuerdo a la disponibilidad presupuestal; esta información estará disponible de oficio en los términos que establece la Ley de Transparencia y Acceso a la Información Pública para el Estado de Baja\nCalifornia y se deberá actualizar al menos una vez cada tres meses.\nPárrafo de la Fracción Reformado\nFracción Reformada\nX.- Expedir las aprobaciones a las que hace referencia el capítulo décimo primero de esta ley;\nXI.- Ejercer todas aquellas facultades que le sean conferidas por esta ley o la legislación estatal;\nXII.- La Secretaría podrá delegar cualquiera de las facultades que le otorga esta ley, al Consejo del Patrimonio Cultural de Baja California o a las comisiones de preservación de cada uno de los municipios, según sea el ámbito de su competencia;\nFracción Reformada\nXIII.- Ejercer las funciones de las Comisiones de Preservación, cuando un bien declarado patrimonio cultural, éstas no se hubieren constituido;\nXIV.- Recibir y sellar las denuncias o solicitudes por escrito, de los tramites presentados, y en su momento oportuno, notificar el inicio del procedimiento al propietario, poseedor o poseedores del bien susceptible de declararse patrimonio cultural o en su caso, al representante de la comunidad donde se encuentre el bien, a fin de que participe con voz directamente en la sesión deliberatoria del Consejo durante el proceso.\nXV.- Recibir y sustanciar el recurso de revisión interpuesto contra una declaratoria;\nLey de Preservación del Patrimonio Cultural del Estado de Baja California. Página 7\n.\nActualización Legislativa.\nÚltima Reforma P. O. No. 37, Índice, 20-Jun-2025\nXVI.- Realizar visitas de verificación a bienes inmuebles que se pretendan o propongan incorporar al Patrimonio Cultural del Estado;\nXVII.- Promover en coordinación con el Consejo del Patrimonio cultural, estímulos fiscales y en su caso, de apoyos económicos para propietarios o poseedores de bienes culturales, para su mantenimiento, conservación, y preservación.\nXVIII.- Vigilar el cumplimiento de esta ley a particulares y autoridades;\nXIX.- Recibir y sustanciar el recurso de revocación, emitiendo la resolución correspondiente;\nXX.- Realizar visitas de verificación sobre bienes culturales en general, así como solicitar la realización de dichas visitas al Consejo del patrimonio cultural y a las comisiones de preservación en los casos que proceda, y\nXXI.- Todas aquellas que señale esta Ley y demás ordenamientos relacionados con la preservación del Patrimonio Cultural.\nArtículo Reformado\nSECCION SEXTA\nDEL CONSEJO DEL PATRIMONIO\nCULTURAL DE BAJA CALIFORNIA\nARTICULO 19.- Se constituye el Consejo del Patrimonio Cultural de Baja California, como un órgano pericial y de consulta de la Secretaría de Cultura.\nArtículo Reformado\nARTICULO 20.- Son atribuciones del Consejo del Patrimonio Cultural de Baja\nCalifornia las siguientes:\nI.- Elaborar el dictamen técnico para la elaboración y en su caso, revocación de las declaratorias que incorporan un bien al Patrimonio Cultural de la entidad, en los términos previstos en esta Ley;\nII.- Elaborar opinión técnica respectiva en cualquier asunto relacionado con la preservación del patrimonio cultural del Estado;\nIII.- Elaborar dictámenes con base en los artículos 68 y 69 de esta Ley, cuando se trate de los siguientes casos:\na) Para la aprobación o demolición del inmueble que hayan sido declarados bienes adscritos al patrimonio cultural, de acuerdo a las disposiciones contenidas en las fracciones I a VI del artículo 4 de la presente Ley;\nb) Para el otorgamiento de autorización de extracción de objetos diversos en un\nc) Para la modificación total o parcial de planes y programas de desarrollo urbano en como centros históricos, distritos urbanos y rurales y zonas de belleza natural y cultural;\nLey de Preservación del Patrimonio Cultural del Estado de Baja California. Página 8\n.\nActualización Legislativa.\nÚltima Reforma P. O. No. 37, Índice, 20-Jun-2025\nIV.- Elaborar el dictamen técnico para las declaratorias de bienes adscritos al patrimonio cultural y la revocación de las mismas;\nV.- Elaborar opinión técnica sobre cualquier asunto relacionado con el patrimonio cultural a solicitud de la Secretaría y las Comisiones de Preservación;\nFracción Reformada\nVI.- Proponer a la Secretaría, acuerdos y normas técnicas de selección y calidad de materiales y procedimientos relacionados con la preservación de bienes culturales del\nEstado;\nFracción Reformada\nVII.- Coordinar con los Ayuntamientos la concepción de planes y programas de desarrollo de sitios declarados patrimonio cultural;\nVIII.- Las demás que le otorgue esta Ley y las disposiciones reglamentarias.\nArtículo Reformado\nARTICULO 21.- El Consejo del Patrimonio Cultural de Baja California deberá proponer a la Secretaría acuerdos y normas técnicas respecto a la calidad de materiales y procedimientos más adecuados para la preservación de los bienes comprendidos en las fracciones I a VI del artículo 4 de la presente ley.\nFracción Reformado\nLa Secretaría emitirá y turnará a la Secretaría General de Gobierno para su publicación en el Periódico Oficial del Estado la declaratoria de vigencia de los acuerdos y el contenido de estos. El cumplimiento de las especificaciones de dichos acuerdos deberá ser de carácter obligatorio, de conformidad con los términos que en ellas mismas se indiquen.\nFracción Reformado\nArtículo Reformado\nARTICULO 22.- El Consejo del Patrimonio Cultural estará conformado por las personas titulares o personas representantes de las siguientes entidades; quienes a su vez podrán nombrar a una persona suplente, cada uno de los miembros del consejo tiene derecho a voz y voto:\nPárrafo Reformado\nFracción Reformada\nII.- La persona titular de la Secretaría, quien además ejercerá funciones de secretaría\nFracción Reformada\nIII.- La persona titular de la Secretaría de Educación;\nFracción Reformada\nIV.- La persona titular de la Secretaría de Hacienda;\nLey de Preservación del Patrimonio Cultural del Estado de Baja California. Página 9\n.\nActualización Legislativa.\nÚltima Reforma P. O. No. 37, Índice, 20-Jun-2025\nFracción Reformada\nV.- La persona titular de la Secretaría de Infraestructura, Desarrollo Urbano y\nReordenación Territorial;\nFracción Reformada\nVI.- La persona titular de la Secretaría de Turismo;\nFracción Reformada\nVII.- Un representante de cada Ayuntamiento del Estado;\nVIII.- Un representante de la Universidad Autónoma de Baja California;\nIX.- Una persona representante de cada uno de los Colegios de Arquitectura registrados ante el Departamento de Profesiones de la Secretaría de Educación, que designe el gremio de profesionistas en el Municipio al que pertenezcan;\nFracción Reformada\nX.- Una persona representante de cada uno de los Colegios de Ingeniería Civil registrados ante el Departamento de Profesiones de la Secretaría de Educación, que designe el gremio de profesionistas en el Municipio al que pertenezcan;\nFracción Reformada\nXI.- Una persona representante de los organismos y asociaciones civiles legalmente constituidas, que tengan como fin o interés la defensa y preservación del Patrimonio Cultural y que estén debidamente acreditados ante la Secretaría;\nFracción Reformada\nXII.- La diputación que presida la Comisión de Cultura y Deporte del Congreso del\nEstado de Baja California;\nFracción Reformado\nXIII.- La persona titular de la Secretaría de Medio Ambiente y Desarrollo Sustentable.\nFracción Reformada\nPodrán participar como personas invitadas permanentes con derecho a voz, mas no\nOrganismos Internacionales y nacionales de la materia, públicos y privados.\nPárrafo Reformado\nArtículo Reformado\nARTICULO 23.- El Consejo sesionará una vez cada tres meses, en la fecha que se\nGeneral de la Secretaría. Las sesiones se podrán celebrar en los distintos municipios del\nEstado, en forma rotativa.\nPárrafo Reformado\nLey de Preservación del Patrimonio Cultural del Estado de Baja California. Página 10\n.\nActualización Legislativa.\nÚltima Reforma P. O. No. 37, Índice, 20-Jun-2025\nPara sesionar es necesario que asista la mayoría simple de los integrantes con derecho a voz y voto; en caso de no existir quórum en primera convocatoria, se realizará la reunión en segunda convocatoria con los miembros presentes.\nPodrán celebrarse reuniones extraordinarias, cuando se considere necesario.\nArtículo Reformado\nSECCION SEPTIMA\nDE LAS COMISIONES DE PRESERVACION DEL PATRIMONIO CULTURAL\nARTICULO 24.- Las Comisiones de Preservación del Patrimonio Cultural, que en lo sucesivo se denominará las Comisiones, son órganos que estarán domiciliados en los\nMunicipios del Estado, coordinados por la Secretaría, quienes tendrán las siguientes atribuciones:\nPárrafo Reformado\nI.- Realizar todas las acciones tendientes a impedir el deterioro de los bienes declarados patrimonio cultural del Estado en el ámbito de su competencia;\nII.- Investigar sobre posibles bienes susceptibles de ser declarados Patrimonio\nCultural del Estado y comunicarlo a la Secretaría;\nFracción Reformada\nIII.- Solicitar opinión técnica y dictamen técnico al Consejo sobre cualquier asunto relacionado con el Patrimonio Cultural.\nIV.- Supervisar la demolición de obras o la restauración de su autenticidad, procurando que se realice debidamente;\nV.- Proponer medidas de preservación que se juzguen pertinentes a la Secretaría;\nFracción Reformada\nVI.- Realizar visitas de verificación sobre bienes declarados, y sobre aquellos susceptibles de incorporarse al patrimonio cultural;\nVII.- Cumplir con todas aquellas actividades o acciones que la Secretaría le encomiende dentro de la municipalidad en que se hubiere constituido, y\nFracción Reformada\nVIII.- Las demás que le otorgue esta Ley y las disposiciones reglamentarias.\nArtículo Reformado\nARTICULO 25.- Las Comisiones de Preservación de cada Municipio estarán integradas de la siguiente manera:\nI.- Una persona representante del Instituto de Cultura en la municipalidad, quien fungirá como Coordinador de la Comisión de Preservación;\nFracción Reformada\nLey de Preservación del Patrimonio Cultural del Estado de Baja California. Página 11\n.\nActualización Legislativa.\nÚltima Reforma P. O. No. 37, Índice, 20-Jun-2025\nII.- Una persona representante del Ayuntamiento en el área de Planeación y Control\nUrbano o de expedición de licencias de construcción;\nFracción Reformada\nIII.- Tres personas integrantes del Consejo del Patrimonio Cultural de Baja California, designadas por dicho Consejo, que radiquen en el municipio y que se hayan distinguido por su trayectoria e interés en materias relacionadas con la preservación del Patrimonio Cultural; el nombramiento será por el término de tres años, pudiendo ratificarse por acuerdo del\nConsejo mediante mayoría de votos;\nFracción Reformada\nIV.- Una persona representante del Departamento de Cultura Municipal u organismo equivalente; y\nFracción Reformada\nV.- Una persona en el cargo de regiduría del ramo de Educación y Cultura.\nFracción Reformada\nArtículo Reformado\nARTICULO 26.- Derogado;\nArtículo Derogado\nARTICULO 27.- Las autoridades estatales y municipales deberán solicitar dictamen a la Comisión de Preservación para otorgar licencia de cualquier tipo de obras en los bienes adscritos al patrimonio cultural o bienes susceptibles de preservación, quien a su vez lo recabará del Consejo del Patrimonio Cultural.\nArtículo Reformado\nARTICULO 28.- Cuando las recomendaciones de la Comisión de Preservación no sean debidamente atendidas en los términos y condiciones señalados, se dará aviso a las autoridades competentes para que, conforme a las disposiciones de esta Ley, exijan su observancia y en su caso apliquen las sanciones correspondientes a los infractores.\nArtículo Reformado\nCAPITULO III\nDE LA DECLARATORIA\nARTICULO 29.- Las disposiciones contenidas en el presente capítulo serán aplicables para los bienes comprendidos en todas las fracciones del artículo 4 de esta ley.”\nArtículo Reformado\nARTICULO 30.- La declaratoria de que un bien se encuentra adscrito al Patrimonio\nCultural del Estado o la revocación de este acto, se hará mediante decreto de la persona\nCalifornia.\nPárrafo Reformado\nLey de Preservación del Patrimonio Cultural del Estado de Baja California. Página 12\n.\nActualización Legislativa.\nÚltima Reforma P. O. No. 37, Índice, 20-Jun-2025\nLa emisión de una declaratoria podrá ser promovida de oficio, por acuerdo económico mediante exhorto del Poder Legislativo o del cabildo según sea el caso, o a petición de parte, deberá presentarse mediante escrito dirigido a la Secretaría, el cual contendrá:\nPárrafo Adicionado con texto Reubicado y Reformado (antes parte del párrafo primero)\nI.- Nombre y domicilio del promovente;\nII.- Descripción del bien o zona objeto de la solicitud, y\nIII.- Exposición de los motivos en los que se funde su petición.\nArtículo Reformado\nARTICULO 31.- Una vez recibida y admitida dicha promoción, la Secretaría, notificará personalmente sobre la instauración del procedimiento al promovente con interés, al propietario o poseedor, o al representante de la comunidad en su caso, del bien o bienes que fueran o estuvieran incluidos en una zona objeto de declaratoria, conforme a lo dispuesto por la fracción XIV del artículo 18 de esta Ley.\nPárrafo Reformado\nTendrán participación directa en la sesión de estudio y análisis del consejo o comisión municipal con voz pero sin voto en las decisiones, para que manifiesten lo que a su derecho convenga, debiendo citarse previamente al efecto.\nEn caso de desconocerse el domicilio del propietario o poseedor del bien o bienes objeto del procedimiento, las notificaciones se practicarán mediante dos publicaciones, con diferencia entre una y otra de cinco días hábiles, en el Periódico Oficial del Estado y en un diario de circulación amplia en la cabecera municipal que corresponda. La segunda publicación tendrá el efecto de notificación personal.\nArtículo Reformado\nARTICULO 32.- La persona interesada tendrá la posibilidad de manifestar lo que a su derecho convenga mediante escrito dirigido a la Secretaría, el cual deberá presentarse dentro de los quince días hábiles siguientes a la fecha de notificación.\nArtículo Reformado\nARTICULO 33.- Una vez transcurrido el término señalado en el artículo anterior, la\nSecretaría turnará el expediente respectivo al Consejo del Patrimonio Cultural del Estado, para que, previo estudio de las constancias que obren en el mismo, proceda en un término no mayor de 60 días naturales posteriores a la fecha de recepción del expediente, a emitir el dictamen técnico respectivo.\nArtículo Reformado\nARTICULO 34.- En caso de que el dictamen técnico del Consejo sea positivo, la siguientes puntos:\nPárrafo Reformado\nLey de Preservación del Patrimonio Cultural del Estado de Baja California. Página 13\n.\nActualización Legislativa.\nÚltima Reforma P. O. No. 37, Índice, 20-Jun-2025\nI.- Fundamentación y motivación de acuerdo a las disposiciones legales aplicables;\nII.- Planos, delimitaciones y localización de los bienes objeto de la declaratoria; y, en su caso, descripción de las características de las obras,\nIII.- Hechos y valores en los que se fundó el inicio del procedimiento;\nIV.- Síntesis de los argumentos vertidos por los propietarios o poseedores del bien cultural;\nV.- Citación completa del dictamen emitido por el Consejo del Patrimonio Cultural del\nEstado.\nArtículo Reformado\nARTICULO 35.- La persona titular del Poder Ejecutivo del Estado ordenará publicar una sola vez la declaratoria, en el Periódico Oficial del Estado. La declaratoria surtirá sus efectos a partir del día hábil siguiente a su publicación.\nPárrafo Reformado\nLa declaratoria será inscrita ante la Secretaría y en el Registro Público de la\nPropiedad y de Comercio del Estado de Baja California en la municipalidad que corresponda.\nPárrafo Reformado\nEn cualquier documento que expida el Registro Público de la Propiedad con respecto de un bien que haya sido objeto de declaratoria, deberá hacerse la anotación clara de esta circunstancia.\nArtículo Reformado\nARTICULO 36.- La persona afectada podrán interponer el recurso de revisión en contra de la declaratoria, mediante escrito dirigido a la Secretaría, el cual deberá contener los siguientes requisitos:\nPárrafo Reformado\nI.- Nombre y domicilio de la persona que promueve;\nFracción Reformada\nII.- La persona interesada deberá acreditar su calidad de persona propietaria o poseedora del bien afectado mediante documental pública o privada;\nFracción Reformada\nIII.- Argumentos de hechos o de derechos que demuestren ilegalidad del acto, y\nIV.- Pruebas que demuestren lo señalado en el punto anterior. Se admitirán todos los medios probatorios salvo la confesional. las pruebas ofrecidas por el afectado o los afectados, la Secretaría deberá desahogar las pruebas, investigar el recurso y resolver lo conducente.\nPárrafo Reformado\nLey de Preservación del Patrimonio Cultural del Estado de Baja California. Página 14\n.\nActualización Legislativa.\nÚltima Reforma P. O. No. 37, Índice, 20-Jun-2025\nArtículo Reformado\nARTICULO 37.- El destino o cambio de destino de inmuebles propiedad del Estado adscritos al patrimonio cultural, deberá hacerse por decreto que expida el Titular del\nEjecutivo, oyendo previamente la opinión del Consejo del Patrimonio Cultural y observando en su caso y en lo que corresponda, lo dispuesto en la Ley General de Bienes del Estado de\nBaja California.\nArtículo Reformado\nARTICULO 38.- El Titular del Ejecutivo mediante decreto y previo dictamen aprobatorio del Consejo, podrá revocar la declaratoria de un bien adscrito al Patrimonio\nCultural del Estado, cuando exista razón fundada para ello.\nARTICULO 39.- En todo lo que no se encuentre contemplado en el presente capítulo, se aplicará supletoriamente el Código de Procedimientos Civiles para el Estado de Baja\nCalifornia.\nCAPITULO IV\nPATRIMONIO CULTURAL POR\nDISPOSICION DE LEY\nARTICULO 40.- Por disposición de esta Ley, queda adscrito al Patrimonio Cultural de\nBaja California:\nI.- Los idiomas de las etnias originarias de Baja California;\nII.- El idioma español;\nIII.- El idioma de las etnias de migrantes radicados en Baja California;\nIV.- El nombre de Baja California como topónimo del Estado de Baja California para fines oficiales.\nV.- La toponimia bajacaliforniana de: asentamientos humanos, orografía, hidrografía continental, costera y marítima contenida en el nomenclátor de Baja California de la\nSecretaría de Desarrollo Social y en el Instituto Nacional de Estadística y Geografía, así como toda aquella toponimia, que existía en la entidad y no este contenida en el documento citado.\nVI.- Todo archivo oficial de cualquiera de los tres poderes, oficinas, municipios o entidades descentralizadas del Estado.\nArtículo Reformado\nCAPITULO V\nDE LAS ZONAS DE ENTORNO ARQUITECTONICO, URBANISTICO O NATURAL\nDenominación Modificada\nARTICULO 41.- Para efectos de esta ley se considera zona de entorno arquitectónico, urbanístico o natural el espacio colindante perimetralmente a cualquier\nLey de Preservación del Patrimonio Cultural del Estado de Baja California. Página 15\n.\nActualización Legislativa.\nÚltima Reforma P. O. No. 37, Índice, 20-Jun-2025 monumento o zona de monumentos declarados por la autoridad estatal o federal, o enumerados por la Ley Federal sobre Monumentos y Zonas Arqueológicos, Artísticos e\nHistóricos y que no formen parte del mismo. También se incluyen áreas que rodean un edificio, sitio, estructura, objeto o área de preservacióm declarados por esta ley.\nArtículo Reformado\nARTICULO 42.- Los Ayuntamientos del Estado en coordinación con el Consejo del\nPatrimonio Cultural de Baja California, en los términos de la Legislación aplicable, deberán expedir un plan o programa de desarrollo urbano para cualquier zona de entorno arquitectónico o natural declarada, a partir de la entrada en vigor de la declaratoria respectiva.\nARTICULO 43.- En el plan a que se hace referencia en el artículo anterior, deberán tomarse en cuenta, cuando menos los siguientes puntos:\nI.- Determinación del uso del suelo autorizado;\nII.- Especificaciones técnicas de las construcciones, y\nIII.- Uso de la vía pública.\nARTICULO 44.- Derogado;\nArtículo Derogado\nCAPITULO VI\nDE LAS ZONAS PROTEGIDAS\nARTICULO 45.- En la declaratoria de una zona protegida, la Secretaría deberá acreditar que la misma cumple con cualquiera de las cualidades culturales que se mencionan en la fracción VI del artículo 5 de esta Ley.\nArtículo Reformado\nARTICULO 46.- Son aplicables, en lo conducente, al presente capítulo las disposiciones contenidas en los artículos 42, 43 y 44 de esta ley.\nARTICULO 47.- En las zonas protegidas queda prohibida la instalación visible de hilos telegráficos y telefónicos, conductores eléctricos, transformadores, postes y en general cualquier instalación eléctrica o electrónica. Las antenas de todo tipo deberán quedar ocultas dentro de la finca de su ubicación.\nArtículo Reformado\nARTICULO 48.- Los elementos de publicidad visual exterior que se pretendan instalar en las zonas protegidas, deberán ser autorizadas previamente por la Secretaría.\nArtículo Reformado\nARTICULO 49.- Los propietarios, poseedores del inmueble o vecinos de la comunidad, ubicados en las zonas protegidas, deberán mantenerlos en buen estado, de\nLey de Preservación del Patrimonio Cultural del Estado de Baja California. Página 16\n.\nActualización Legislativa.\nÚltima Reforma P. O. No. 37, Índice, 20-Jun-2025 acuerdo a los términos que dicte esta Ley y los acuerdos técnicos emitidos por el consejo que resulten aplicables.\nArtículo Reformado\nARTICULO 50.- Los inmuebles del patrimonio cultural del Estado no podrán ser usados para fines diferentes a los señalados en el Decreto de declaratoria que les haya dado ese carácter, cualquier acto contrario a esta disposición será sancionado conforme a esta Ley y demás ordenamientos legales aplicables.\nArtículo Reformado\nCAPITULO VII\nDE LOS VALORES CULTURALES, FESTIVIDADES POPULARES, MANIFESTACIONES\nDE INTERES CULTURAL, Y DE LOS IDIOMAS Y TOPONOMIA REGIONAL\nDenominación Modificada\nARTICULO 51.- En la declaratoria de un valor cultural, la Secretaría deberá acreditar que el mismo cumple con cualquiera de los principios tradicionales, estéticos o culturales de una población o grupo étnico que posea originalidad cultural, valor artístico, alto contenido simbólico con respecto a la celebración de festivales religiosos o populares, o relevancia etnográfica.\nArtículo Reformado\nARTICULO 52.- Las autoridades estatales y municipales, de oficio o a petición de los comités organizadores de las festividades populares, establecerán las medidas necesarias para la promoción, estímulo, fomento, investigación y difusión de las mismas, como un factor de integración, identidad y desarrollo cultural de la población de la entidad.\nArtículo Reformado\nCAPITULO VIII\nDEL REGISTRO PUBLICO, INVENTARIO Y CATALOGO DEL PATRIMONIO CULTURAL\nDenominación Modificada\nARTICULO 53.- La Secretaría, en colaboración con otras instituciones tanto del sector público como privado, promoverá la identificación, evaluación, investigación, difusión y preservación de las manifestaciones culturales, ya sean aquellas representativas de la creatividad y el desarrollo intelectual, así como de los valores artísticos y culturales de los habitantes del Estado.\nArtículo Reformado\nARTICULO 54.- La Secretaría, en coordinación con el Consejo del Patrimonio\nEstado, con base en el artículo 5 fracción VII, inciso c) de esta Ley.\nArtículo Reformado\nLey de Preservación del Patrimonio Cultural del Estado de Baja California. Página 17\n.\nActualización Legislativa.\nÚltima Reforma P. O. No. 37, Índice, 20-Jun-2025\nARTICULO 55.- La Secretaría promoverá la difusión de los nombres y designaciones originales otorgadas a los lugares y accidentes geográficos de Baja California y el estudio de sus significados culturales de acuerdo al artículo 5 fracción VII, inciso d) de esta Ley.\nArtículo Reformado\nARTICULO 56.- Se crea dentro del Registro Público de la Propiedad y de Comercio del Estado de Baja California, una sección que se denominará \"Registro Público del\nPatrimonio Cultural\", en el que se inscribirán la declaratoria y demás actos jurídicos relacionados con los bienes que sean objeto de regulación por la presente ley.\nLa información del Registro Público del Patrimonio Cultural deberá ser accesible en forma permanente desde la página de internet del Registro Público de la Propiedad y del\nComercio; además de los que establezca la Ley del Registro Público de la Propiedad y de\nComercio del Estado de Baja California.\nArtículo Reformado\nARTICULO 57.- Los bienes propiedad privada de las personas físicas o morales declarados como bienes adscritos al patrimonio cultural del Estado, deberán ser inscritos, previo decreto y publicación en el periódico oficial del Estado, en el Registro del Patrimonio Cultural a efecto de que puedan recibir los estímulos y apoyos mencionados en la fracción XVII del artículo 18 que estipula ésta Ley.\nArtículo Reformado\nARTICULO 58.- La inscripción en los registros se hará de oficio o a petición de la parte interesada.\nArtículo Reformado\nARTICULO 59.- Los actos traslativos de dominio sobre inmuebles adscritos al\nPatrimonio Cultural del Estado, deberán constar en escritura pública. Quien transmita el dominio, deberá manifestar, bajo protesta de decir verdad y en base a la exhibición de la declaratoria que el bien materia de la operación es bien cultural.\nLos notarios públicos insertarán en la escritura respectiva, el texto de la declaratoria que corresponda al bien objeto de la declaración, debiendo además, dar aviso al Registro\nPúblico del Patrimonio Cultural del acto realizado en un plazo no mayor de treinta días siguientes contados a partir de la fecha de la celebración de la operación.\nArtículo Reformado\nARTICULO 60.- Todo aquel que adquiera por cualquier título la propiedad de un bien mueble adscrito al Patrimonio Cultural del Estado, deberá dar aviso al Registro Público del\nPatrimonio Cultural, en un plazo no mayor de treinta días siguientes, contados a partir de la fecha de celebración de la operación.\nArtículo Reformado\nARTICULO 61.- La Secretaría formulará un inventario de los bienes culturales que se encuentren localizados en el estado, noventa días siguientes de emitida la declaratoria que\nLey de Preservación del Patrimonio Cultural del Estado de Baja California. Página 18\n.\nActualización Legislativa.\nÚltima Reforma P. O. No. 37, Índice, 20-Jun-2025 los incorpora como bienes del patrimonio cultural, mismo que estará en constante actualización.\nPárrafo Reformado\nEl Registro Público de la Propiedad y de Comercio del Estado, deberá proporcionar un informe relativo a las inscripciones realizadas en las secciones referidas en este Capítulo cuando se lo requiera la Secretaría.\nPárrafo Reformado\nArtículo Reformado\nARTICULO 62.- La Secretaría elaborará y difundirá un catálogo estatal que contenga la descripción ilustrada y detallada de las tradiciones, costumbres, alimentos y trajes típicos propios del Estado; así como los sitios históricos de interés por sus edificios, monumentos, museos, pinturas, vestigios y estructuras; zonas protegidas y zonas de entorno del territorio de Baja California que sean parte de su patrimonio cultural.\nPárrafo Reformado\nEl catálogo al que hace mención este artículo deberá estar publicado permanentemente en la página de la Secretaría.\nPárrafo Reformado\nArtículo Reformado\nCAPITULO IX\nDE LAS AUTORIZACIONES DE LA OBRA\nDenominación Modificada\nARTICULO 63.- Toda acción de preservación, conservación, restauración, rehabilitación, exhibición, utilización, reestructuración, adaptación, extracción, demolición o cualquier otro acto que afecte la estructura o zonas de entorno de un inmueble arquitectónico, urbanístico o natural que afecte la estructura, autenticidad o imagen de un bien comprendido en las fracciones I, II, III y IV, V, VI y VIII del artículo 4 de esta Ley, requerirá la autorización de la Secretaría.\nArtículo Reformado\nARTICULO 64.- Para la realización de cualquier trabajo de los referidos en el artículo anterior en un bien inmueble, el interesado deberá presentar solicitud de autorización, por escrito, que cumpla los siguientes requisitos:\nI.- Nombre y domicilio del solicitante;\nII.- Nombre y domicilio del propietario o poseedor del bien objeto de la autorización. El interesado deberá presentar documentos de comprobación de propiedad o titularidad.\nIII.- Planos, especificaciones y características de la obra;\nIV.- Plano, descripción y fotografías del inmueble en el Estado que se encuentra antes de la ejecución de los trabajos;\nLey de Preservación del Patrimonio Cultural del Estado de Baja California. Página 19\n.\nActualización Legislativa.\nÚltima Reforma P. O. No. 37, Índice, 20-Jun-2025\nV.- Derogada;\nFracción Derogada\nVI.- Número de inscripción en el Registro de Bienes Culturales del Estado.\nArtículo Reformado\nARTICULO 65.- Para realizar cualquier trabajo de los referidos en el artículo 63 en un bien mueble, el interesado deberá presentar solicitud de autorización, por escrito, que cumpla los siguientes requisitos:\nI.- Nombre y domicilio del solicitante;\nII.- Nombre y domicilio del propietario o poseedor del bien objeto de la autorización. El interesado deberá presentar documentos de comprobación de propiedad o titularidad.\nIII.- Especificaciones y características de la obra;\nIV.- Descripción y fotografías del objeto en el estado que se encuentre antes de la ejecución de los trabajos;\nV.- Derogada;\nFracción Derogada\nVI.- Autorización escrita del creador o productor del bien mueble o, en su caso, del poseedor de los derechos de autor, y\nArtículo Reformado\nARTICULO 66.- La Secretaría resolverá lo conducente en un plazo no mayor de treinta días hábiles contados a partir de la fecha de recepción de la solicitud.\nArtículo Reformado\nARTICULO 67.- Para el otorgamiento de la autorización correspondiente, la\nSecretaría deberá solicitar al Consejo la emisión de un dictamen.\nPárrafo Reformado\nEn caso de que la información proporcionada no sea suficiente para determinar la viabilidad del proyecto, podrá requerirse al interesado por una sola vez para que, en un término no mayor de veinte días hábiles a partir de la fecha de notificación del requerimiento, aclare o complemente los puntos solicitados. Si transcurrido dicho término, el solicitante no cumple con la prevención formulada, el trámite se considerará abandonado.\nArtículo Reformado\nARTICULO 68.- Será necesaria la emisión de un dictamen técnico del Consejo del\nPatrimonio Cultural de Baja California para la emisión de la aprobación correspondiente, en los casos que se mencionan en el artículo 20 de esta Ley.\nARTICULO 69.- En los casos mencionados en el artículo anterior, el Consejo del de la obra.\nArtículo Reformado\nLey de Preservación del Patrimonio Cultural del Estado de Baja California. Página 20\n.\nActualización Legislativa.\nÚltima Reforma P. O. No. 37, Índice, 20-Jun-2025\nARTICULO 70.- En los casos comprendidos en los artículos 67 y 68 de esta ley, la\nSecretaría deberá expedir la resolución definitiva en un término no mayor de diez días hábiles contados a partir de la recepción del dictamen del Consejo del Patrimonio Cultural de\nBaja California.\nArtículo Reformado\nARTICULO 71.- La autorización deberá contener los siguientes requisitos:\nI.- Nombre y domicilio del solicitante;\nII.- Descripción del Bien Cultural y de la obra a ejecutar;\nIII.- Formulación de los requerimientos técnicos necesarios para cubrir la obra;\nIV.- Nombramiento de perito asesor, y\nV.- Mandamiento de inscripción de la aprobación en el Registro Público del\nPatrimonio Cultural dentro de los siguientes diez días hábiles a su notificación, con la prevención, de que en caso de no cumplir la aprobación quedará sin efecto.\nArtículo Reformado\nARTICULO 72.- En el caso de los bienes protegidos por esta Ley, la autorización otorgada por la Secretaría, no excluye al solicitante de cumplir con los requerimientos establecidos por otras autoridades competentes. Sin embargo, esta aprobación será siempre un requisito previo indispensable para la tramitación de las demás autorizaciones.\nArtículo Reformado\nARTICULO 72 BIS.- Se establecerán medidas de preservación en casos de cambio de uso de suelo, demoliciones, alteraciones y modificaciones a edificios, sitios, objetos y áreas de valor cultural declarados o susceptibles de declaratoria, que formen parte de los inventarios o catálogos elaborados o acreditados por la Secretaría. Esta medida se aplica también para todos aquellos bienes culturales declarados patrimonio cultural de Baja\nCalifornia, que tengan más de cincuenta años de haberse producido. Estas medidas son:\nPárrafo Reformado\nI.- Las personas propietarias o poseedoras de bienes declarados patrimonio cultural de Baja California deberán notificar con tres meses de anticipación a la Secretaría sobre el cambio de uso de suelo, demolición, venta, modificación o alteración por realizar, y\nFracción Reformada\nII.- En caso necesario, la Secretaría promoverá la realización de un diagnóstico o estudio de impacto en torno a la posible afectación de un bien cultural declarado, como medida de preservación. El costo de dicho estudio será cubierto ya sea por el Gobierno del\nEstado, los Ayuntamientos, el sector privado o la persona propietaria o poseedora del bien, según se trate de la instancia responsable, y será realizado por especialistas acreditados por la Secretaría.\nFracción Reformada\nArtículo Reformado\nLey de Preservación del Patrimonio Cultural del Estado de Baja California. Página 21\n.\nActualización Legislativa.\nÚltima Reforma P. O. No. 37, Índice, 20-Jun-2025\nARTICULO 72 TER.- El Gobierno del Estado y los Ayuntamientos incluirán en sus planes de desarrollo y programas de inversión, la compra, restauración y utilización de edificios históricos abandonados, en la medida en que estos puedan resolver sus necesidades de espacio antes de proceder a construir nuevos inmuebles.\nArtículo Reformado\nARTICULO 72 QUARTER.- La Secretaría promoverá la adquisición, por medio de comodato, donación expropiación o transferencia de derechos, de edificios, estructuras y zonas de valor histórico y natural para su preservación, de acuerdo a lo dispuesto en la presente ley.\nArtículo Reformado\nARTICULO 72 QUINQUIES.- La Secretaría aplicará medidas de emergencia para evitar demoliciones, alteraciones o modificaciones en inmuebles o bienes susceptibles de declararse patrimonio cultural del Estado, siempre que reúnan valores históricos, artísticos o culturales de acuerdo a los criterios establecidos por la Secretaría en coordinación, con el\nConsejo del Patrimonio Cultural.\nPárrafo Reformado\nLa emisión de una orden de preservación inmediata podrá ser promovida de oficio o a petición de parte. Esta medida detendrá el proceso de demolición o afectación hasta por tres meses a partir de su emisión, durante los cuales se iniciará el procedimiento ordinario para la emisión de la declaratoria, con base en las disposiciones contempladas en el artículo treinta de esta Ley.\nQuedan exentos de esta medida aquellos edificios, estructuras y objetos que amenacen con derrumbarse, mediante dictaminación de una asesora o un asesor con acreditación de la\nSecretaría.\nPárrafo Reformado\nArtículo Reformado\nCAPITULO X\nDEL PROGRAMA DE PRESERVACION DEL PATRIMONIO\nCULTURAL DE BAJA CALIFORNIA\nDenominación Modificada través de la Secretaría, la planeación de las acciones conducentes para la preservación del\nPatrimonio Cultural de Baja California, que incluirá acciones, políticas y estrategias a seguir elaborado conjuntamente con el Consejo del Patrimonio Cultural de Baja California.\nArtículo Reformado\nLey de Preservación del Patrimonio Cultural del Estado de Baja California. Página 22\n.\nActualización Legislativa.\nÚltima Reforma P. O. No. 37, Índice, 20-Jun-2025\nARTICULO 74.- El programa de preservación del Patrimonio Cultural deberá quedar incluido en el presupuesto establecido anualmente por la persona titular del Poder Ejecutivo del Estado, siendo corresponsabilidad del Consejo la formulación e instrucción del mismo.\nArtículo Reformado\nARTICULO 75.- El programa a que se hace referencia en los artículos 73 y 74 de esta ley deberá contemplar, cuando menos los siguientes datos:\nI.- Diagnóstico de la situación que guarde la preservación del Patrimonio Cultural del\nEstado;\nII.- Objetivos;\nIII.- Estrategias generales;\nIV.- Líneas de estrategias especificas, entre las que se deben de encontrar las siguientes medidas:\nV.- Diseño e instrumentación de acciones y medidas para preservar el patrimonio cultural del Estado en caso de desastres naturales;\nVI.- Actividades de formación y capacitación de recursos humanos en materia de preservación del patrimonio cultural, y\nVII.- Establecimiento del Fondo para la Preservación del Patrimonio Cultural de Baja\nCalifornia, con la participación de recursos federales, estatales, municipales y del sector privado.\nArtículo Reformado\nARTICULO 76.- El programa de preservación del Patrimonio Cultural de Baja\nCalifornia, será publicado en el Periódico Oficial del Estado.\nArtículo Reformado\nCAPITULO XI\nDEL APOYO DE LAS AUTORIDADES ESTATALES Y MUNICIPALES\nEN LA PRESERVACION DE LOS MONUMENTOS Y ZONAS ARQUEOLOGICAS,\nHISTORICOS Y ARTISTICOS\nDenominación Modificada\nARTICULO 77.- Las disposiciones contenidas en el presente capítulo tienen por\nFederales en la Preservación del Patrimonio Cultural del Estado. Por lo tanto, las mismas no sobre Monumentos y Zonas Arqueológicos, Artísticos e Históricos.\nArtículo Reformado\nARTICULO 78.- Corresponderá a las autoridades estatales y municipales apoyar a\nLey de Preservación del Patrimonio Cultural del Estado de Baja California. Página 23\n.\nActualización Legislativa.\nÚltima Reforma P. O. No. 37, Índice, 20-Jun-2025\nMonumentos Arqueológicos, Artísticos e Históricos, en términos de la legislación federal respectiva.\nArtículo Reformado\nCAPITULO XII\nDE LA PARTICIPACION POPULAR\nARTICULO 79.- Se reconoce la acción popular a todo habitante del Estado de Baja\nCalifornia para:\nI.- Proponer la adscripción de un bien valor al Patrimonio Cultural del Estado de Baja\nCalifornia;\nII.- Proponer de manera fundamentada que se excluya un bien valor adscrito al citado\nPatrimonio;\nIII.- Proponer acciones a la Secretaría sobre cualquier asunto o tema relacionado con el Patrimonio Cultural, y\nFracción Reformada\nIV.- Denunciar toda falta, acción u omisión de cualquier persona física, moral o autoridad en perjuicio del Patrimonio Cultural del Estado de Baja California.\nArtículo Reformado\nSECCION PRIMERA\nDE LAS PERSONAS FISICAS Y MORALES\nARTICULO 80.- Derogado.\nArtículo Derogado\nARTICULO 81.- Derogado.\nArtículo Derogado\nARTICULO 82.- Derogado.\nArtículo Derogado\nARTICULO 83.- Derogado.\nArtículo Derogado\nSECCION SEGUNDA\nESTIMULOS FISCALES Y APOYOS ECONÓMICOS.\nDenominación Modificada\nARTICULO 84.- La Secretaría en coordinación con el Consejo del patrimonio cultural de Baja California, promoverá ante las autoridades estatales y municipales, estímulos fiscales y apoyos económicos según su naturaleza, para la persona\nLey de Preservación del Patrimonio Cultural del Estado de Baja California. Página 24\n.\nActualización Legislativa.\nÚltima Reforma P. O. No. 37, Índice, 20-Jun-2025 propietaria, persona poseedora de bienes o a la persona representante de la comunidad donde se ubique la zona del inmueble según sea el caso, declarados patrimonio cultural de la entidad, que les permita su remozamiento, conservación, o mantenimiento.\nArtículo Reformado\nARTICULO 84 BIS.- La Secretaría en coordinación con el Consejo del Patrimonio\nCultural de Baja California, podrá promover y concertar con la Iniciativa privada, un esquema financiero y de participación mixta para la investigación, preservación, promoción y desarrollo de los bienes y valores artísticos y culturales declarados o susceptibles de declararse adscritos al patrimonio cultural de la entidad.\nArtículo Adicionado\nArtículo Reformado\nSECCION TERCERA\nDE LAS CAMPAÑAS ANUALES DE PROMOCIÓN Y FOMENTO\nDenominación Modificada\nARTICULO 85.- Corresponderá al Ejecutivo del Estado a través de la Secretaría, establecer campañas anuales de sensibilización, difusión y fomento a nivel escolar y masivo, respecto de la importancia de proteger las manifestaciones que constituyan el Patrimonio\nCultural de la entidad.\nArtículo Reformado\nARTICULO 86.- La Secretaría y las Comisiones de Preservación en coordinación con autoridades estatales y municipales, así como con diversos sectores de la sociedad, realizarán campañas permanentes para fomentar y difundir el conocimiento, respeto y enriquecimiento del Patrimonio Cultural del Estado.\nArtículo Reformado\nCAPITULO XIII\nDE LA VIGILANCIA, RECURSOS, SANCIONES Y DELITOS\nSECCION PRIMERA\nDE LA VIGILANCIA\nARTICULO 87.- Corresponderá a la Secretaría ejercer la vigilancia respecto del cumplimiento por parte de particulares y autoridades, de las disposiciones contenidas en la presente ley.\nArtículo Reformado\nARTICULO 88.- Para la práctica de una visita de verificación, se seguirán las siguientes reglas;\nI.- El inspector deberá acreditarse e identificarse ente el interesado y proporcionarle una copia del oficio de comisión emitido por la autoridad competente. En caso de no\nLey de Preservación del Patrimonio Cultural del Estado de Baja California. Página 25\n.\nActualización Legislativa.\nÚltima Reforma P. O. No. 37, Índice, 20-Jun-2025 encontrarse el propietario o poseedor del bien objeto de la inspección, el inspector dejará con la persona que lo atienda un citatorio señalando el día y la hora para la celebración de la diligencia. De no presentarse el interesado la visita se efectuará con quien se encuentre en el domicilio del mismo.\nII.- El interesado deberá identificarse ante el inspector y tendrá la facultad de nombrar dos testigos que deberán estar presentes en el transcurso de la visita. En caso de que el interesado se niegue a ejercer este derecho, el inspector los nombrará en su rebeldía.\nIII.- El interesado deberá proporcionar al inspector toda la información, documentación y facilidades que sean necesarias para la comprobación de los hechos que sean objeto de la visita.\nIV.- En caso de que el inspector detecte actividades que pongan en peligro inminente la integridad del bien, procederá a dictar las medidas de seguridad respectivas, las cuales podrán consistir en la suspensión de las obras o el aseguramiento del objeto. El inspector podrá solicitar el auxilio de la fuerza pública para la ejecución de dichas medidas.\nV.- Se levantará un acta, señalando en su caso, las irregularidades cometidas, los elementos necesarios para calificar la infracción y las medidas de seguridad adoptadas. El acta será firmada por todos los participantes de la visita y se entregará copia de la misma al interesado. Si alguno de los participantes se negare a firmar, el inspector así lo asentará en el acta, la falta de firma no afectará la validez del documento.\nVI.- El inspector remitirá en un plazo de setenta y dos horas el acta a la autoridad competente para que proceda conforme a lo que se señala en los artículos subsecuentes.\nARTICULO 89.- El interesado contará con un término de quince días hábiles para manifestar lo que a su derecho convenga. La autoridad competente emitirá y notificará la resolución definitiva en un término no mayor de treinta días hábiles contados a partir de la fecha de recepción del acta.\nSECCION SEGUNDA\nDEL RECURSO DE REVOCACION\nARTICULO 90.- En contra de cualquier acto que no prevea la interposición de un medio de defensa especial procederá el recurso de revocación, el cual deberá ser promovido acto impugnado.\nARTICULO 91.- El escrito que contenga el recurso de revocación deberá ser dirigido a la Secretaría y cumplir con los siguientes requisitos:\nPárrafo Reformado\nI.- Nombre y domicilio de la persona que promueve;\nFracción Reformada\nII.- Acreditación del interés jurídico;\nLey de Preservación del Patrimonio Cultural del Estado de Baja California. Página 26\n.\nActualización Legislativa.\nÚltima Reforma P. O. No. 37, Índice, 20-Jun-2025\nIII.- Acompañar el original del documento que contenga el acto impugnado y de la constancia de notificación;\nIV.- Relación de los hechos motivo del procedimiento;\nV.- Agravios, y\nVI.- Documentos y pruebas en los que funde su petición. Se admitirán todos los medios probatorios a excepción de la confesional.\nArtículo Reformado\nARTICULO 92.- Recibido el recurso, la Secretaría verificará que el mismo cumpla con los requisitos señalados en el artículo anterior. En caso contrario, podrá prevenir por una sola vez a quien promueve para que aclare o subsane las irregularidades detectadas en un plazo no mayor de cinco días hábiles contados a partir de la fecha de notificación del requerimiento. Si la persona interesada no cumple con los términos establecidos la\nSecretaría desechará el recurso por improcedente.\nArtículo Reformado\nARTICULO 93.- La Secretaría contará con treinta días hábiles para emitir la resolución correspondiente, contados a partir de la fecha de recepción del recurso o del escrito que cumpla con el requerimiento a que hace referencia el artículo anterior. La persona interesada podrá recurrir al Tribunal Estatal de Justicia Administrativa de Baja\nCalifornia para impugnar dicha resolución.\nArtículo Reformado\nARTICULO 94.- La interposición del recurso no suspende los efectos del acto. En el caso de sanciones pecuniarias, podrá suspenderse el procedimiento administrativo de ejecución si se cumplen con las disposiciones contenidas en la legislación aplicable.\nARTICULO 95.- Será aplicable supletoriamente el Código de Procedimientos Civiles para el Estado de Baja California, en todo lo que no esté expresamente contemplado en este capítulo.\nSECCION TERCERA\nDE LAS SANCIONES Y DELITOS\nARTICULO 96.- La imposición de las sanciones administrativas compete a la\nSecretaría.\nPárrafo Reformado delitos, es facultad exclusiva de los juzgados de lo penal competentes.\nPárrafo Adicionado con texto Reubicado (antes parte del párrafo primero)\nArtículo Reformado\nARTICULO 97.- Se impondrá prisión de seis meses a diez años y multa hasta por el\nLey de Preservación del Patrimonio Cultural del Estado de Baja California. Página 27\n.\nActualización Legislativa.\nÚltima Reforma P. O. No. 37, Índice, 20-Jun-2025 destrucción o deterioro de bienes culturales contemplados en las fracciones I a VI; VIII y IX del artículo 4 de esta ley. La anterior sanción se aplicará independientemente de la comisión de otros delitos contemplados por la legislación penal del Estado.\nArtículo Reformado\nARTICULO 98.- Derogado;\nArtículo Derogado\nARTICULO 99.- El Ministerio Público que lleve a cabo una averiguación previa o el juez encargado de un proceso penal podrá ordenar el aseguramiento de bienes adscritos al\nPatrimonio Cultural del Estado, comprendidos en las fracciones I a VI; VIII y IX del artículo 4 en relación con el artículo 5 fracciones I a VI; VIII, y IX de esta ley, que hayan sido confiscados como producto de una diligencia judicial o policíaca.\nLos bienes asegurados se entregarán para su custodia a la Secretaría o al organismo que determine el Ejecutivo del Estado conforme a la Ley, en tanto la autoridad o entidad que dictó la orden de aseguramiento respectiva, determine fehaciente y legalmente la identidad de la persona propietaria o poseedora de éstos, a quienes le serán restituidos.\nPárrafo Reformado\nArtículo Reformado\nARTICULO 100.- Las violaciones que no constituyan un delito serán sancionadas administrativamente mediante la imposición de las siguientes medidas:\nI.- Clausura temporal;\nII.- Clausura definitiva;\nIII.- Demolición y/o reparación del daño causado.\nAdicionalmente se impondrá multa cuyo monto puede variar de doscientas hasta mil veces el valor diario de la Unidad de Medida y Actualización vigente.\nPárrafo Reformado\nArtículo Reformado\nARTICULO 101.- Procederá la clausura temporal cuando tratándose de un inmueble, la ejecución de la obra no cumpla con las especificaciones establecidas en la autorización respectiva. correspondiente hasta en tanto no se obtenga.\nProcederá la demolición o reparación del daño causado, cuando el propietario o poseedor agregue o construya adicionalmente y sin el permiso respectivo, elementos artículo 4 de esta Ley. causado serán a cargo del infractor. En caso de rebeldía será el Municipio respectivo quien\nLey de Preservación del Patrimonio Cultural del Estado de Baja California. Página 28\n.\nActualización Legislativa.\nÚltima Reforma P. O. No. 37, Índice, 20-Jun-2025 los realice, constituyendo un crédito fiscal a cargo del infractor, en los términos de la legislación tributaria aplicable.\nPara la ejecución de cualquiera de estas sanciones, la Secretaría, en coordinación con los cuerpos de Seguridad Pública y Tránsito podrá solicitar el auxilio de la fuerza pública.\nPárrafo Reformado\nArtículo Reformado\nARTICULO 102.- Las sanciones establecidas en esta sección se impondrá a quienes por su negligencia provoquen el deterioro o pérdida de bienes comprendidos en las fracciones I a VI del artículo 4 del presente ordenamiento legal. De igual forma en la resolución que se emita por dicho concepto se especificarán los trabajos a realizar para garantizar la integridad del bien, en caso de que el mismo no se haya perdido definitivamente.\nArtículo Reformado\nARTICULO 103.- La persona infractora podrá evitar la imposición de cualquier sanción económica derivada de la violación a cualquier de los preceptos señalados en la presente ley, podrá celebrar un convenio de coordinación con la Secretaría para realizar las obras que se requieran.\nPárrafo Reformado\nPara tal efecto, se acordará un programa de trabajo, mismo que se ejecuta bajo la asesoría de la autoridad.\nSi el interesado demuestra fehacientemente que no cuenta con las condiciones económicas para llevar a cabo los trabajos, la autoridad podrá optar, a su entera discreción, por cualquiera de las siguientes opciones:\nI.- Realizar por su cuenta las obras, si el bien en cuestión ostenta cualidades culturales de gran importancia para el Patrimonio Cultural del Estado, o,\nII.- Llevar a cabo las obras constituyendo un crédito fiscal a cargo del infractor, cuyo pago se pactaría, previo acuerdo con las autoridades fiscales correspondientes.\nSi el interesado se negara a aceptar la propuesta señalada en la fracción II de este artículo, se procederá a realizar los trabajos y será el Ayuntamiento quien lo realice, constituyéndose un crédito fiscal a cargo del interesado, en los términos de la legislación tributaria aplicable. Así mismo, la Autoridad impondrá la multa que corresponda.\nArtículo Reformado\nARTICULO 104.- En la imposición de sanciones administrativas, la Secretaría con el apoyo del Consejo del Patrimonio Cultural de Baja California, deberá acreditar:\nPárrafo Reformado\nI.- La adecuada y pormenorizada fundamentación y motivación de los hechos;\nII.- La gravedad de la infracción.\nLey de Preservación del Patrimonio Cultural del Estado de Baja California. Página 29\n.\nActualización Legislativa.\nÚltima Reforma P. O. No. 37, Índice, 20-Jun-2025\nArtículo Reformado\nARTICULO 105.- Cuando la sanción consista en la demolición de la obra realizada sin autorización o de la restauración de la autenticidad de la obra serán las Comisiones de\nPreservación correspondientes a quienes supervisen dichos trabajos, en coordinación con el autor, realizador o quien posea los derechos de la obra.\nArtículo Reformado\nARTICULO 106.- La imposición de sanciones por parte de la Secretaría, no excluye a las autoridades estatales y municipales de sancionar las violaciones cometidas a la legislación correspondiente.\nArtículo Reformado\nARTICULO 107.- Para los efectos de este capítulo serán solidariamente responsables de las violaciones a las disposiciones de esta ley:\nI.- Los propietarios de los inmuebles involucrados en las citadas violaciones; y\nII.- Quienes ordenen, dirijan o realicen las acciones constitutivas de la violación.\nARTICULOS TRANSITORIOS:\nARTICULO PRIMERO.- La presente ley entrará en vigor al día siguiente al de su publicación en el Periódico Oficial del Estado:\nARTICULO SEGUNDO.- El Consejo del Patrimonio Cultural del Estado deberá de quedar integrado dentro de los sesenta días siguientes a la entrada en vigor de la presente ley y dentro de ese término, iniciará sus sesiones y elaborará su reglamento interno y el programa de protección del Patrimonio Cultural de Baja California.\nARTICULO TERCERO.- A partir de la fecha de inicio de vigencia del presente ordenamiento, quedarán derogadas todas las disposiciones legales y reglamentarias que se opongan al mismo.\nLegislativo, en la Ciudad de Mexicali, Baja California, a los veintisiete días del mes de julio de mil novecientos noventa y cinco.\nLUIS VIZCARRA VIZCARRA,\nDIPUTADO PRESIDENTE.\nRUBRICA.\nFRANCISCO JAVIER REYNOSO NUÑO,\nDIPUTADO SECRETARIO.\nRUBRICA.\nLey de Preservación del Patrimonio Cultural del Estado de Baja California. Página 30\n.\nActualización Legislativa.\nÚltima Reforma P. O. No. 37, Índice, 20-Jun-2025\nDE CONFORMIDAD CON LO DISPUESTO POR LA FRACCIÓN I DEL ARTÍCULO 49\nOBSERVE Y SE LE DE EL DEBIDO CUMPLIMIENTO.\nMEXICALI, BAJA CALIFORNIA, A LOS TRES DÍAS DEL MES DE AGOSTO DE MIL\nNOVECIENTOS NOVENTA Y CINCO.\nEL GOBERNADOR CONSTITUCIONAL DEL ESTADO,\nLIC. ERNESTO RUFFO APPEL.\nRÚBRICA.\nEL SECRETARIO GENERAL DE GOBIERNO,\nLIC. RODOLFO VALDEZ GUTIERREZ.\nRÚBRICA.\nLey de Preservación del Patrimonio Cultural del Estado de Baja California. Página 31\n.\nActualización Legislativa.\nÚltima Reforma P. O. No. 37, Índice, 20-Jun-2025\nARTICULO 1.- Fue reformado por Decreto No. 233, publicado en el Periódico Oficial\nNo. 45, Tomo CV, de fecha 06 de noviembre de 1998, expedido por la H. XV Legislatura, siendo Gobernador Constitucional el C. Lic. Héctor Terán Terán 1995-2001;\nARTICULO 2.- Fue derogado por Decreto No. 233, publicado en el Periódico Oficial\nNo. 45, Tomo CV, de fecha 06 de noviembre de 1998, expedido por la H. XV Legislatura, siendo Gobernador Constitucional el C. Lic. Héctor Terán Terán 1995-2001;\nARTICULO 3.- Fue reformado por Decreto No. 233, publicado en el Periódico Oficial\nNo. 45, Tomo CV, de fecha 06 de noviembre de 1998, expedido por la H. XV Legislatura, siendo Gobernador Constitucional el C. Lic. Héctor Terán Terán 1995-2001;\nARTICULO 4.- Fue reformado por Decreto No. 233, publicado en el Periódico Oficial\nNo. 45, Tomo CV, de fecha 06 de noviembre de 1998, expedido por la H. XV Legislatura, siendo Gobernador Constitucional el C. Lic. Héctor Terán Terán 1995-2001;\nARTICULO 5.- Fue reformado por Decreto No. 233, publicado en el Periódico Oficial\nNo. 45, Tomo CV, de fecha 06 de noviembre de 1998, expedido por la H. XV Legislatura, siendo Gobernador Constitucional el C. Lic. Héctor Terán Terán 1995-2001;\nARTICULO 6.- Fue reformado por Decreto No. 233, publicado en el Periódico Oficial\nNo. 45, Tomo CV, de fecha 06 de noviembre de 1998, expedido por la H. XV Legislatura, siendo Gobernador Constitucional el C. Lic. Héctor Terán Terán 1995-2001;\nARTICULO 7.- Fue reformado por Decreto No. 233, publicado en el Periódico Oficial\nNo. 45, Tomo CV, de fecha 06 de noviembre de 1998, expedido por la H. XV Legislatura, siendo Gobernador Constitucional el C. Lic. Héctor Terán Terán 1995-2001;\nFue modificada la denominación de este Capítulo II, en la Sección Séptima, por\nDecreto No. 233, publicado en el Periódico Oficial No. 45, Tomo CV, de fecha 06 de noviembre de 1998, expedido por la Honorable XV Legislatura, siendo Gobernador\nConstitucional el c. Lic. Héctor Terán Terán 1995-2001;\nCAPITULO II\nDE LAS AUTORIDADES Y\nORGANOS DE APOYO\nARTICULO 9.- Fue reformado por Decreto No. 233, publicado en el Periódico Oficial siendo Gobernador Constitucional el C. Lic. Héctor Terán Terán 1995-2001; fue reformado mediante Decreto No. 529, publicado en el Periódico Oficial No. 35, de fecha 05 de agosto de 2016, Tomo CXXIII, Sección IV, expedido por la H. XXI Legislatura, siendo Gobernador\nConstitucional el C. Francisco Arturo Vega de Lamadrid 2013-2019; fue reformado mediante\nLey de Preservación del Patrimonio Cultural del Estado de Baja California. Página 32\n.\nActualización Legislativa.\nÚltima Reforma P. O. No. 37, Índice, 20-Jun-2025\nTomo CXXXI, expedido por la H. XXIV Legislatura, siendo Gobernadora Constitucional la C.\nMarina del Pilar Ávila Olmeda 2021-2027;\nARTICULO 10.- Fue reformado mediante Decreto 435, publicado en el Periódico\nOficial No. 28, Índice, de fecha 31 de mayo de 2024, Tomo CXXXI, expedido por la H. XXIV\nLegislatura, siendo Gobernadora Constitucional la C. Marina del Pilar Ávila Olmeda 20212027;\nFue modificada la denominación de esta Sección mediante Decreto 435, publicado en el Periódico Oficial No. 28, Índice, de fecha 31 de mayo de 2024, Tomo CXXXI, expedido por la H. XXIV Legislatura, siendo Gobernadora Constitucional la C. Marina del Pilar Ávila\nOlmeda 2021-2027;\nSECCIÓN PRIMERA\nDE LA PERSONA TITULAR DEL PODER EJECUTIVO DEL ESTADO\nARTICULO 11.- Fue reformado por Decreto No. 233, publicado en el Periódico Oficial\nNo. 45, Tomo CV, de fecha 06 de noviembre de 1998, expedido por la H. XV Legislatura, siendo Gobernador Constitucional el C. Lic. Héctor Terán Terán 1995-2001; fue reformado mediante Decreto 435, publicado en el Periódico Oficial No. 28, Índice, de fecha 31 de mayo de 2024, Tomo CXXXI, expedido por la H. XXIV Legislatura, siendo Gobernadora\nConstitucional la C. Marina del Pilar Ávila Olmeda 2021-2027;\nARTICULO 12.- Fue reformado mediante Decreto 435, publicado en el Periódico\nOficial No. 28, Índice, de fecha 31 de mayo de 2024, Tomo CXXXI, expedido por la H. XXIV\nLegislatura, siendo Gobernadora Constitucional la C. Marina del Pilar Ávila Olmeda 20212027;\nFue modificada la denominación de esta Sección mediante Decreto 435, publicado en el Periódico Oficial No. 28, Índice, de fecha 31 de mayo de 2024, Tomo CXXXI, expedido por la H. XXIV Legislatura, siendo Gobernadora Constitucional la C. Marina del Pilar Ávila\nSECCION TERCERA\nDE LA SECRETARÍA DE INFRAESTRUCTURA, DESARROLLO URBANO Y\nREORDENAMIENTO TERRITORIAL\nARTICULO 13.- Fue reformado por Decreto No. 233, publicado en el Periódico Oficial siendo Gobernador Constitucional el C. Lic. Héctor Terán Terán 1995-2001; fue reformado mediante Decreto No. 529, publicado en el Periódico Oficial No. 35, de fecha 05 de agosto de 2016, Tomo CXXIII, Sección IV, expedido por la H. XXI Legislatura, siendo Gobernador\nConstitucional el C. Francisco Arturo Vega de Lamadrid 2013-2019; fue reformado mediante\nTomo CXXXI, expedido por la H. XXIV Legislatura, siendo Gobernadora Constitucional la C.\nMarina del Pilar Ávila Olmeda 2021-2027;\nLey de Preservación del Patrimonio Cultural del Estado de Baja California. Página 33\n.\nActualización Legislativa.\nÚltima Reforma P. O. No. 37, Índice, 20-Jun-2025\nARTICULO 15.- Fue reformado por Decreto No. 233, publicado en el Periódico Oficial\nNo. 45, Tomo CV, de fecha 06 de noviembre de 1998, expedido por la H. XV Legislatura, siendo Gobernador Constitucional el C. Lic. Héctor Terán Terán 1995-2001; fue reformado por Decreto No. 261, publicado en el Periódico Oficial No. 42, de fecha 21 de septiembre de\n2012, Tomo CXIX, Sección I, expedido por la H. XX Legislatura, siendo Gobernador\nConstitucional el C. José Guadalupe Osuna Millán 2007-2013;\nARTICULO 16.- Fue derogado por Decreto No. 233, publicado en el Periódico Oficial\nNo. 45, Tomo CV, de fecha 06 de noviembre de 1998, expedido por la H. XV Legislatura, siendo Gobernador Constitucional el C. Lic. Héctor Terán Terán 1995-2001;\nFue modificada la denominación de esta Sección mediante Decreto 435, publicado en el Periódico Oficial No. 28, Índice, de fecha 31 de mayo de 2024, Tomo CXXXI, expedido por la H. XXIV Legislatura, siendo Gobernadora Constitucional la C. Marina del Pilar Ávila;\nSECCION QUINTA\nSECRETARÍA DE CULTURA\nARTICULO 17.- Fue reformado por Decreto No. 233, publicado en el Periódico Oficial\nNo. 45, Tomo CV, de fecha 06 de noviembre de 1998, expedido por la H. XV Legislatura, siendo Gobernador Constitucional el C. Lic. Héctor Terán Terán 1995-2001; fue reformado mediante Decreto 435, publicado en el Periódico Oficial No. 28, Índice, de fecha 31 de mayo de 2024, Tomo CXXXI, expedido por la H. XXIV Legislatura, siendo Gobernadora\nConstitucional la C. Marina del Pilar Ávila Olmeda 2021-2027;\nARTICULO 18.- Fue reformado por Decreto No. 233, publicado en el Periódico Oficial\nNo. 45, Tomo CV, de fecha 06 de noviembre de 1998, expedido por la H. XV Legislatura, siendo Gobernador Constitucional el C. Lic. Héctor Terán Terán 1995-2001; fue reformado por Decreto No. 261, publicado en el Periódico Oficial No. 42, de fecha 21 de septiembre de\n2012, Tomo CXIX, Sección I, expedido por la H. XX Legislatura, siendo Gobernador\nConstitucional el C. José Guadalupe Osuna Millán 2007-2013; fue reformado mediante\nDecreto No. 529, publicado en el Periódico Oficial No. 35, de fecha 05 de agosto de 2016, Tomo CXXIII, Sección IV, expedido por la H. XXI Legislatura, siendo Gobernador\nConstitucional el C. Francisco Arturo Vega de Lamadrid 2013-2019; fue reformado mediante\nTomo CXXXI, expedido por la H. XXIV Legislatura, siendo Gobernadora Constitucional la C.\nMarina del Pilar Ávila Olmeda 2021-2027;\nARTICULO 19.- Fue reformado mediante Decreto 435, publicado en el Periódico\nLegislatura, siendo Gobernadora Constitucional la C. Marina del Pilar Ávila Olmeda 20212027;\nLey de Preservación del Patrimonio Cultural del Estado de Baja California. Página 34\n.\nActualización Legislativa.\nÚltima Reforma P. O. No. 37, Índice, 20-Jun-2025\nARTICULO 20.- Fue reformado por Decreto No. 233, publicado en el Periódico Oficial\nNo. 45, Tomo CV, de fecha 06 de noviembre de 1998, expedido por la H. XV Legislatura, siendo Gobernador Constitucional el C. Lic. Héctor Terán Terán 1995-2001; fue reformado mediante Decreto 435, publicado en el Periódico Oficial No. 28, Índice, de fecha 31 de mayo de 2024, Tomo CXXXI, expedido por la H. XXIV Legislatura, siendo Gobernadora\nConstitucional la C. Marina del Pilar Ávila Olmeda 2021-2027;\nARTICULO 21.- Fue reformado por Decreto No. 233, publicado en el Periódico Oficial\nNo. 45, Tomo CV, de fecha 06 de noviembre de 1998, expedido por la H. XV Legislatura, siendo Gobernador Constitucional el C. Lic. Héctor Terán Terán 1995-2001; fue reformado mediante Decreto 435, publicado en el Periódico Oficial No. 28, Índice, de fecha 31 de mayo de 2024, Tomo CXXXI, expedido por la H. XXIV Legislatura, siendo Gobernadora\nConstitucional la C. Marina del Pilar Ávila Olmeda 2021-2027;\nARTICULO 22.- Fue reformado por Decreto No. 233, publicado en el Periódico Oficial\nNo. 45, Tomo CV, de fecha 06 de noviembre de 1998, expedido por la H. XV Legislatura, siendo Gobernador Constitucional el C. Lic. Héctor Terán Terán 1995-2001; fue reformado por Decreto No. 261, publicado en el Periódico Oficial No. 42, de fecha 21 de septiembre de\n2012, Tomo CXIX, Sección I, expedido por la H. XX Legislatura, siendo Gobernador\nConstitucional el C. José Guadalupe Osuna Millán 2007-2013; fue reformado mediante\nDecreto No. 529, publicado en el Periódico Oficial No. 35, de fecha 05 de agosto de 2016, Tomo CXXIII, Sección IV, expedido por la H. XXI Legislatura, siendo Gobernador\nConstitucional el C. Francisco Arturo Vega de Lamadrid 2013-2019; fue reformado mediante\nDecreto 435, publicado en el Periódico Oficial No. 28, Índice, de fecha 31 de mayo de 2024, Tomo CXXXI, expedido por la H. XXIV Legislatura, siendo Gobernadora Constitucional la C.\nMarina del Pilar Ávila Olmeda 2021-2027; fue reformado mediante Decreto 96, publicado en el Periódico Oficial No. 37, Índice, de fecha 20 de junio de 2025, Tomo CXXXII, expedido por la H. XXV Legislatura, siendo Gobernadora Constitucional la C. Marina del Pilar Ávila\nOlmeda 2021-2027;\nARTICULO 23.- Fue reformado por Decreto No. 233, publicado en el Periódico Oficial\nNo. 45, Tomo CV, de fecha 06 de noviembre de 1998, expedido por la H. XV Legislatura, siendo Gobernador Constitucional el C. Lic. Héctor Terán Terán 1995-2001; fue reformado mediante Decreto 435, publicado en el Periódico Oficial No. 28, Índice, de fecha 31 de mayo de 2024, Tomo CXXXI, expedido por la H. XXIV Legislatura, siendo Gobernadora\nConstitucional la C. Marina del Pilar Ávila Olmeda 2021-2027;\nARTICULO 24.- Fue reformado por Decreto No. 233, publicado en el Periódico Oficial siendo Gobernador Constitucional el C. Lic. Héctor Terán Terán 1995-2001; fue reformado mediante Decreto 435, publicado en el Periódico Oficial No. 28, Índice, de fecha 31 de mayo de 2024, Tomo CXXXI, expedido por la H. XXIV Legislatura, siendo Gobernadora\nConstitucional la C. Marina del Pilar Ávila Olmeda 2021-2027;\nLey de Preservación del Patrimonio Cultural del Estado de Baja California. Página 35\n.\nActualización Legislativa.\nÚltima Reforma P. O. No. 37, Índice, 20-Jun-2025\nARTICULO 25.- Fue reformado por Decreto No. 233, publicado en el Periódico Oficial\nNo. 45, Tomo CV, de fecha 06 de noviembre de 1998, expedido por la H. XV Legislatura, siendo Gobernador Constitucional el C. Lic. Héctor Terán Terán 1995-2001; fue reformado mediante Decreto 435, publicado en el Periódico Oficial No. 28, Índice, de fecha 31 de mayo de 2024, Tomo CXXXI, expedido por la H. XXIV Legislatura, siendo Gobernadora\nConstitucional la C. Marina del Pilar Ávila Olmeda 2021-2027;\nARTICULO 26.- Fue derogado por Decreto No. 233, publicado en el Periódico Oficial\nNo. 45, Tomo CV, de fecha 06 de noviembre de 1998, expedido por la H. XV Legislatura, siendo Gobernador Constitucional el C. Lic. Héctor Terán Terán 1995-2001;\nARTICULO 27.- Fue reformado por Decreto No. 233, publicado en el Periódico Oficial\nNo. 45, Tomo CV, de fecha 06 de noviembre de 1998, expedido por la H. XV Legislatura, siendo Gobernador Constitucional el C. Lic. Héctor Terán Terán 1995-2001;\nARTICULO 28.- Fue reformado por Decreto No. 233, publicado en el Periódico Oficial\nNo. 45, Tomo CV, de fecha 06 de noviembre de 1998, expedido por la H. XV Legislatura, siendo Gobernador Constitucional el C. Lic. Héctor Terán Terán 1995-2001;\nARTICULO 29.- Fue reformado por Decreto No. 233, publicado en el Periódico Oficial\nNo. 45, Tomo CV, de fecha 06 de noviembre de 1998, expedido por la H. XV Legislatura, siendo Gobernador Constitucional el C. Lic. Héctor Terán Terán 1995-2001;\nARTICULO 30.- Fue reformado por Decreto No. 261, publicado en el Periódico Oficial\nNo. 42, de fecha 21 de septiembre de 2012, Tomo CXIX, Sección I, expedido por la H. XX\nLegislatura, siendo Gobernador Constitucional el C. José Guadalupe Osuna Millán 20072013; fue reformado mediante Decreto 435, publicado en el Periódico Oficial No. 28, Índice, de fecha 31 de mayo de 2024, Tomo CXXXI, expedido por la H. XXIV Legislatura, siendo\nGobernadora Constitucional la C. Marina del Pilar Ávila Olmeda 2021-2027;\nARTICULO 31.- Fue reformado por Decreto No. 261, publicado en el Periódico Oficial\nNo. 42, de fecha 21 de septiembre de 2012, Tomo CXIX, Sección I, expedido por la H. XX\nLegislatura, siendo Gobernador Constitucional el C. José Guadalupe Osuna Millán 20072013; fue reformado mediante Decreto 435, publicado en el Periódico Oficial No. 28, Índice, de fecha 31 de mayo de 2024, Tomo CXXXI, expedido por la H. XXIV Legislatura, siendo\nGobernadora Constitucional la C. Marina del Pilar Ávila Olmeda 2021-2027;\nARTICULO 32.- Fue reformado mediante Decreto 435, publicado en el Periódico\nLegislatura, siendo Gobernadora Constitucional la C. Marina del Pilar Ávila Olmeda 20212027;\nARTICULO 33.- Fue reformado mediante Decreto 435, publicado en el Periódico\nLegislatura, siendo Gobernadora Constitucional la C. Marina del Pilar Ávila Olmeda 20212027;\nLey de Preservación del Patrimonio Cultural del Estado de Baja California. Página 36\n.\nActualización Legislativa.\nÚltima Reforma P. O. No. 37, Índice, 20-Jun-2025\nARTICULO 34.- Fue reformado por Decreto No. 233, publicado en el Periódico Oficial\nNo. 45, Tomo CV, de fecha 06 de noviembre de 1998, expedido por la H. XV Legislatura, siendo Gobernador Constitucional el C. Lic. Héctor Terán Terán 1995-2001; fue reformado mediante Decreto 435, publicado en el Periódico Oficial No. 28, Índice, de fecha 31 de mayo de 2024, Tomo CXXXI, expedido por la H. XXIV Legislatura, siendo Gobernadora\nConstitucional la C. Marina del Pilar Ávila Olmeda 2021-2027;\nARTICULO 35.- Fue reformado por Decreto No. 233, publicado en el Periódico Oficial\nNo. 45, Tomo CV, de fecha 06 de noviembre de 1998, expedido por la H. XV Legislatura, siendo Gobernador Constitucional el C. Lic. Héctor Terán Terán 1995-2001; fue reformado mediante Decreto 435, publicado en el Periódico Oficial No. 28, Índice, de fecha 31 de mayo de 2024, Tomo CXXXI, expedido por la H. XXIV Legislatura, siendo Gobernadora\nConstitucional la C. Marina del Pilar Ávila Olmeda 2021-2027;\nARTICULO 36.- Fue reformado por Decreto No. 233, publicado en el Periódico Oficial\nNo. 45, Tomo CV, de fecha 06 de noviembre de 1998, expedido por la H. XV Legislatura, siendo Gobernador Constitucional el C. Lic. Héctor Terán Terán 1995-2001; fue reformado mediante Decreto 435, publicado en el Periódico Oficial No. 28, Índice, de fecha 31 de mayo de 2024, Tomo CXXXI, expedido por la H. XXIV Legislatura, siendo Gobernadora\nConstitucional la C. Marina del Pilar Ávila Olmeda 2021-2027;\nARTICULO 37.- Fue reformado por Decreto No. 233, publicado en el Periódico Oficial\nNo. 45, Tomo CV, de fecha 06 de noviembre de 1998, expedido por la H. XV Legislatura, siendo Gobernador Constitucional el C. Lic. Héctor Terán Terán 1995-2001;\nARTICULO 40.- Fue reformado por Decreto No. 233, publicado en el Periódico Oficial\nNo. 45, Tomo CV, de fecha 06 de noviembre de 1998, expedido por la H. XV Legislatura, siendo Gobernador Constitucional el C. Lic. Héctor Terán Terán 1995-2001; fue reformado mediante Decreto No. 529, publicado en el Periódico Oficial No. 35, de fecha 05 de agosto de 2016, Tomo CXXIII, Sección IV, expedido por la H. XXI Legislatura, siendo Gobernador\nConstitucional el C. Francisco Arturo Vega de Lamadrid 2013-2019;\nFue modificada la denominación de este Capítulo, por Decreto No. 233, publicado en\nHonorable XV Legislatura, siendo Gobernador Constitucional el c. Lic. Héctor Terán Terán\n1995-2001;\nCAPITULO V\nDE LAS ZONAS DE ENTORNO ARQUITECTONICO, URBANISTICO O NATURAL\nARTICULO 41.- Fue reformado por Decreto No. 233, publicado en el Periódico Oficial siendo Gobernador Constitucional el C. Lic. Héctor Terán Terán 1995-2001;\nLey de Preservación del Patrimonio Cultural del Estado de Baja California. Página 37\n.\nActualización Legislativa.\nÚltima Reforma P. O. No. 37, Índice, 20-Jun-2025\nARTICULO 44.- Fue derogado por Decreto No. 233, publicado en el Periódico Oficial\nNo. 45, Tomo CV, de fecha 06 de noviembre de 1998, expedido por la H. XV Legislatura, siendo Gobernador Constitucional el C. Lic. Héctor Terán Terán 1995-2001;\nARTICULO 45.- Fue reformado por Decreto No. 233, publicado en el Periódico Oficial\nNo. 45, Tomo CV, de fecha 06 de noviembre de 1998, expedido por la H. XV Legislatura, siendo Gobernador Constitucional el C. Lic. Héctor Terán Terán 1995-2001; fue reformado mediante Decreto 435, publicado en el Periódico Oficial No. 28, Índice, de fecha 31 de mayo de 2024, Tomo CXXXI, expedido por la H. XXIV Legislatura, siendo Gobernadora\nConstitucional la C. Marina del Pilar Ávila Olmeda 2021-2027;\nARTICULO 47.- Fue reformado por Decreto No. 233, publicado en el Periódico Oficial\nNo. 45, Tomo CV, de fecha 06 de noviembre de 1998, expedido por la H. XV Legislatura, siendo Gobernador Constitucional el C. Lic. Héctor Terán Terán 1995-2001;\nARTICULO 48.- Fue reformado mediante Decreto 435, publicado en el Periódico\nOficial No. 28, Índice, de fecha 31 de mayo de 2024, Tomo CXXXI, expedido por la H. XXIV\nLegislatura, siendo Gobernadora Constitucional la C. Marina del Pilar Ávila Olmeda 20212027;\nARTICULO 49.- Fue reformado por Decreto No. 261, publicado en el Periódico Oficial\nNo. 42, de fecha 21 de septiembre de 2012, Tomo CXIX, Sección I, expedido por la H. XX\nLegislatura, siendo Gobernador Constitucional el C. José Guadalupe Osuna Millán 20072013;\nARTICULO 50.- Fue reformado por Decreto No. 233, publicado en el Periódico Oficial\nNo. 45, Tomo CV, de fecha 06 de noviembre de 1998, expedido por la H. XV Legislatura, siendo Gobernador Constitucional el C. Lic. Héctor Terán Terán 1995-2001;\nFue modificada la denominación de este Capítulo por Decreto No. 233, publicado en el Periódico Oficial No. 45, Tomo CV, de fecha 06 de noviembre de 1998, expedido por la\nHonorable XV Legislatura, siendo Gobernador Constitucional el c. Lic. Héctor Terán Terán\n1995-2001;\nCAPITULO VII\nDE LOS VALORES CULTURALES, FESTIVIDADES POPULARES, MANIFESTACIONES\nDE INTERES CULTURAL, Y DE LOS IDIOMAS Y TOPONOMIA REGIONAL\nARTICULO 51.- Fue reformado por Decreto No. 233, publicado en el Periódico Oficial siendo Gobernador Constitucional el C. Lic. Héctor Terán Terán 1995-2001; fue reformado mediante Decreto 435, publicado en el Periódico Oficial No. 28, Índice, de fecha 31 de mayo de 2024, Tomo CXXXI, expedido por la H. XXIV Legislatura, siendo Gobernadora\nConstitucional la C. Marina del Pilar Ávila Olmeda 2021-2027;\nLey de Preservación del Patrimonio Cultural del Estado de Baja California. Página 38\n.\nActualización Legislativa.\nÚltima Reforma P. O. No. 37, Índice, 20-Jun-2025\nARTICULO 52.- Fue reformado por Decreto No. 233, publicado en el Periódico Oficial\nNo. 45, Tomo CV, de fecha 06 de noviembre de 1998, expedido por la H. XV Legislatura, siendo Gobernador Constitucional el C. Lic. Héctor Terán Terán 1995-2001;\nFue modificada la denominación de este Capítulo por Decreto No. 233, publicado en el\nPeriódico Oficial No. 45, de fecha 06 de noviembre de 1998, Tomo CV, siendo Gobernador\nConstitucional el C. Lic. Héctor Terán Terán 1995-2001;\nCAPITULO VIII\nDEL REGISTRO PUBLICO, INVENTARIO Y CATALOGO DEL PATRIMONIO CULTURAL\nARTICULO 53.- Fue reformado por Decreto No. 233, publicado en el Periódico Oficial\nNo. 45, Tomo CV, de fecha 06 de noviembre de 1998, expedido por la H. XV Legislatura, siendo Gobernador Constitucional el C. Lic. Héctor Terán Terán 1995-2001; fue reformado mediante Decreto 435, publicado en el Periódico Oficial No. 28, Índice, de fecha 31 de mayo de 2024, Tomo CXXXI, expedido por la H. XXIV Legislatura, siendo Gobernadora\nConstitucional la C. Marina del Pilar Ávila Olmeda 2021-2027;\nARTICULO 54.- Fue reformado por Decreto No. 233, publicado en el Periódico Oficial\nNo. 45, Tomo CV, de fecha 06 de noviembre de 1998, expedido por la H. XV Legislatura, siendo Gobernador Constitucional el C. Lic. Héctor Terán Terán 1995-2001; fue reformado mediante Decreto 435, publicado en el Periódico Oficial No. 28, Índice, de fecha 31 de mayo de 2024, Tomo CXXXI, expedido por la H. XXIV Legislatura, siendo Gobernadora\nConstitucional la C. Marina del Pilar Ávila Olmeda 2021-2027;\nARTICULO 55.- Fue reformado por Decreto No. 233, publicado en el Periódico Oficial\nNo. 45, Tomo CV, de fecha 06 de noviembre de 1998, expedido por la H. XV Legislatura, siendo Gobernador Constitucional el C. Lic. Héctor Terán Terán 1995-2001; fue reformado mediante Decreto 435, publicado en el Periódico Oficial No. 28, Índice, de fecha 31 de mayo de 2024, Tomo CXXXI, expedido por la H. XXIV Legislatura, siendo Gobernadora\nConstitucional la C. Marina del Pilar Ávila Olmeda 2021-2027;\nARTICULO 56.- Fue reformado por Decreto No. 261, publicado en el Periódico Oficial\nNo. 42, de fecha 21 de septiembre de 2012, Tomo CXIX, Sección I, expedido por la H. XX\nLegislatura, siendo Gobernador Constitucional el C. José Guadalupe Osuna Millán 20072013; fue reformado mediante Decreto No. 529, publicado en el Periódico Oficial No. 35, de siendo Gobernador Constitucional el C. Francisco Arturo Vega de Lamadrid 2013-2019;\nARTICULO 57.- Fue reformado por Decreto No. 233, publicado en el Periódico Oficial siendo Gobernador Constitucional el C. Lic. Héctor Terán Terán 1995-2001; fue reformado por Decreto No. 261, publicado en el Periódico Oficial No. 42, de fecha 21 de septiembre de\n2012, Tomo CXIX, Sección I, expedido por la H. XX Legislatura, siendo Gobernador\nConstitucional el C. José Guadalupe Osuna Millán 2007-2013;\nLey de Preservación del Patrimonio Cultural del Estado de Baja California. Página 39\n.\nActualización Legislativa.\nÚltima Reforma P. O. No. 37, Índice, 20-Jun-2025\nARTICULO 58.- Fue reformado por Decreto No. 233, publicado en el Periódico Oficial\nNo. 45, Tomo CV, de fecha 06 de noviembre de 1998, expedido por la H. XV Legislatura, siendo Gobernador Constitucional el C. Lic. Héctor Terán Terán 1995-2001;\nARTICULO 59.- Fue reformado por Decreto No. 233, publicado en el Periódico Oficial\nNo. 45, Tomo CV, de fecha 06 de noviembre de 1998, expedido por la H. XV Legislatura, siendo Gobernador Constitucional el C. Lic. Héctor Terán Terán 1995-2001;\nARTICULO 60.- Fue reformado por Decreto No. 233, publicado en el Periódico Oficial\nNo. 45, Tomo CV, de fecha 06 de noviembre de 1998, expedido por la H. XV Legislatura, siendo Gobernador Constitucional el C. Lic. Héctor Terán Terán 1995-2001;\nARTICULO 61.- Fue reformado por Decreto No. 233, publicado en el Periódico Oficial\nNo. 45, Tomo CV, de fecha 06 de noviembre de 1998, expedido por la H. XV Legislatura, siendo Gobernador Constitucional el C. Lic. Héctor Terán Terán 1995-2001; fue reformado mediante Decreto 435, publicado en el Periódico Oficial No. 28, Índice, de fecha 31 de mayo de 2024, Tomo CXXXI, expedido por la H. XXIV Legislatura, siendo Gobernadora\nConstitucional la C. Marina del Pilar Ávila Olmeda 2021-2027;\nARTICULO 62.- Fue reformado por Decreto No. 233, publicado en el Periódico Oficial\nNo. 45, Tomo CV, de fecha 06 de noviembre de 1998, expedido por la H. XV Legislatura, siendo Gobernador Constitucional el C. Lic. Héctor Terán Terán 1995-2001; fue reformado mediante Decreto No. 529, publicado en el Periódico Oficial No. 35, de fecha 05 de agosto de 2016, Tomo CXXIII, Sección IV, expedido por la H. XXI Legislatura, siendo Gobernador\nConstitucional el C. Francisco Arturo Vega de Lamadrid 2013-2019; fue reformado mediante\nDecreto 435, publicado en el Periódico Oficial No. 28, Índice, de fecha 31 de mayo de 2024, Tomo CXXXI, expedido por la H. XXIV Legislatura, siendo Gobernadora Constitucional la C.\nMarina del Pilar Ávila Olmeda 2021-2027;\nFue modificada la denominación de este Capítulo por Decreto No. 233, publicado en el\nPeriódico Oficial No. 45, de fecha 06 de noviembre de 1998, Tomo CV, siendo Gobernador\nConstitucional el C. Lic. Héctor Terán Terán 1995-2001;\nCAPITULO IX\nDE LAS AUTORIZACIONES DE LA OBRA\nARTICULO 63.- Fue reformado por Decreto No. 233, publicado en el Periódico Oficial siendo Gobernador Constitucional el C. Lic. Héctor Terán Terán 1995-2001; fue reformado mediante Decreto 435, publicado en el Periódico Oficial No. 28, Índice, de fecha 31 de mayo de 2024, Tomo CXXXI, expedido por la H. XXIV Legislatura, siendo Gobernadora\nConstitucional la C. Marina del Pilar Ávila Olmeda 2021-2027;\nARTICULO 64.- Fue reformado por Decreto No. 233, publicado en el Periódico Oficial siendo Gobernador Constitucional el C. Lic. Héctor Terán Terán 1995-2001;\nLey de Preservación del Patrimonio Cultural del Estado de Baja California. Página 40\n.\nActualización Legislativa.\nÚltima Reforma P. O. No. 37, Índice, 20-Jun-2025\nARTICULO 65.- Fue reformado por Decreto No. 233, publicado en el Periódico Oficial\nNo. 45, Tomo CV, de fecha 06 de noviembre de 1998, expedido por la H. XV Legislatura, siendo Gobernador Constitucional el C. Lic. Héctor Terán Terán 1995-2001;\nARTICULO 66.- Fue reformado por Decreto No. 233, publicado en el Periódico Oficial\nNo. 45, Tomo CV, de fecha 06 de noviembre de 1998, expedido por la H. XV Legislatura, siendo Gobernador Constitucional el C. Lic. Héctor Terán Terán 1995-2001; fue reformado mediante Decreto 435, publicado en el Periódico Oficial No. 28, Índice, de fecha 31 de mayo de 2024, Tomo CXXXI, expedido por la H. XXIV Legislatura, siendo Gobernadora\nConstitucional la C. Marina del Pilar Ávila Olmeda 2021-2027;\nARTICULO 67.- Fue reformado por Decreto No. 233, publicado en el Periódico Oficial\nNo. 45, Tomo CV, de fecha 06 de noviembre de 1998, expedido por la H. XV Legislatura, siendo Gobernador Constitucional el C. Lic. Héctor Terán Terán 1995-2001; fue reformado mediante Decreto 435, publicado en el Periódico Oficial No. 28, Índice, de fecha 31 de mayo de 2024, Tomo CXXXI, expedido por la H. XXIV Legislatura, siendo Gobernadora\nConstitucional la C. Marina del Pilar Ávila Olmeda 2021-2027;\nARTICULO 69.- Fue reformado por Decreto No. 233, publicado en el Periódico Oficial\nNo. 45, Tomo CV, de fecha 06 de noviembre de 1998, expedido por la H. XV Legislatura, siendo Gobernador Constitucional el C. Lic. Héctor Terán Terán 1995-2001;\nARTICULO 70.- Fue reformado mediante Decreto 435, publicado en el Periódico\nOficial No. 28, Índice, de fecha 31 de mayo de 2024, Tomo CXXXI, expedido por la H. XXIV\nLegislatura, siendo Gobernadora Constitucional la C. Marina del Pilar Ávila Olmeda 20212027;\nARTICULO 71.- Fue reformado por Decreto No. 233, publicado en el Periódico Oficial\nNo. 45, Tomo CV, de fecha 06 de noviembre de 1998, expedido por la H. XV Legislatura, siendo Gobernador Constitucional el C. Lic. Héctor Terán Terán 1995-2001;\nARTICULO 72.- Fue reformado por Decreto No. 233, publicado en el Periódico Oficial\nNo. 45, Tomo CV, de fecha 06 de noviembre de 1998, expedido por la H. XV Legislatura, siendo Gobernador Constitucional el C. Lic. Héctor Terán Terán 1995-2001; fue reformado por Decreto No. 261, publicado en el Periódico Oficial No. 42, de fecha 21 de septiembre de\n2012, Tomo CXIX, Sección I, expedido por la H. XX Legislatura, siendo Gobernador\nConstitucional el C. José Guadalupe Osuna Millán 2007-2013; fue reformado mediante\nTomo CXXXI, expedido por la H. XXIV Legislatura, siendo Gobernadora Constitucional la C.\nMarina del Pilar Ávila Olmeda 2021-2027;\nARTICULO 72 BIS.- Fue adicionado por Decreto No. 233, publicado en el Periódico\nLegislatura, siendo Gobernador Constitucional el C. Lic. Héctor Terán Terán 1995-2001; fue reformado por Decreto No. 261, publicado en el Periódico Oficial No. 42, de fecha 21 de\nLey de Preservación del Patrimonio Cultural del Estado de Baja California. Página 41\n.\nActualización Legislativa.\nÚltima Reforma P. O. No. 37, Índice, 20-Jun-2025\nGobernador Constitucional el C. José Guadalupe Osuna Millán 2007-2013; fue reformado mediante Decreto 435, publicado en el Periódico Oficial No. 28, Índice, de fecha 31 de mayo de 2024, Tomo CXXXI, expedido por la H. XXIV Legislatura, siendo Gobernadora\nConstitucional la C. Marina del Pilar Ávila Olmeda 2021-2027;\nARTICULO 72 TER- Fue adicionado por Decreto No. 233, publicado en el Periódico\nOficial No. 45, Tomo CV, de fecha 06 de noviembre de 1998, expedido por la H. XV\nLegislatura, siendo Gobernador Constitucional el C. Lic. Héctor Terán Terán 1995-2001; fue reformado por Decreto No. 261, publicado en el Periódico Oficial No. 42, de fecha 21 de septiembre de 2012, Tomo CXIX, Sección I, expedido por la H. XX Legislatura, siendo\nGobernador Constitucional el C. José Guadalupe Osuna Millán 2007-2013;\nARTICULO 72 QUARTER.- Fue adicionado por Decreto No. 233, publicado en el\nPeriódico Oficial No. 45, Tomo CV, de fecha 06 de noviembre de 1998, expedido por la H.\nXV Legislatura, siendo Gobernador Constitucional el C. Lic. Héctor Terán Terán 1995-2001; fue reformado por Decreto No. 261, publicado en el Periódico Oficial No. 42, de fecha 21 de septiembre de 2012, Tomo CXIX, Sección I, expedido por la H. XX Legislatura, siendo\nGobernador Constitucional el C. José Guadalupe Osuna Millán 2007-2013; fue reformado mediante Decreto No. 529, publicado en el Periódico Oficial No. 35, de fecha 05 de agosto de 2016, Tomo CXXIII, Sección IV, expedido por la H. XXI Legislatura, siendo Gobernador\nConstitucional el C. Francisco Arturo Vega de Lamadrid 2013-2019; fue reformado mediante\nDecreto 435, publicado en el Periódico Oficial No. 28, Índice, de fecha 31 de mayo de 2024, Tomo CXXXI, expedido por la H. XXIV Legislatura, siendo Gobernadora Constitucional la C.\nMarina del Pilar Ávila Olmeda 2021-2027;\nARTICULO 72 QUINQUIES.- Fue adicionado por Decreto No. 233, publicado en el\nPeriódico Oficial No. 45, Tomo CV, de fecha 06 de noviembre de 1998, expedido por la H.\nXV Legislatura, siendo Gobernador Constitucional el C. Lic. Héctor Terán Terán 1995-2001; fue reformado por Decreto No. 261, publicado en el Periódico Oficial No. 42, de fecha 21 de septiembre de 2012, Tomo CXIX, Sección I, expedido por la H. XX Legislatura, siendo\nGobernador Constitucional el C. José Guadalupe Osuna Millán 2007-2013; fue reformado mediante Decreto No. 529, publicado en el Periódico Oficial No. 35, de fecha 05 de agosto de 2016, Tomo CXXIII, Sección IV, expedido por la H. XXI Legislatura, siendo Gobernador\nConstitucional el C. Francisco Arturo Vega de Lamadrid 2013-2019; fue reformado mediante\nTomo CXXXI, expedido por la H. XXIV Legislatura, siendo Gobernadora Constitucional la C.\nMarina del Pilar Ávila Olmeda 2021-2027;\nFue modificada la denominación de este Capítulo por Decreto No. 233, publicado en el\nConstitucional el C. Lic. Héctor Terán Terán 1995-2001;\nLey de Preservación del Patrimonio Cultural del Estado de Baja California. Página 42\n.\nActualización Legislativa.\nÚltima Reforma P. O. No. 37, Índice, 20-Jun-2025\nCAPITULO X\nDEL PROGRAMA DE PRESERVACION DEL PATRIMONIO CULTURAL DE BAJA\nCALIFORNIA\nARTICULO 73.- Fue reformado por Decreto No. 233, publicado en el Periódico Oficial\nNo. 45, Tomo CV, de fecha 06 de noviembre de 1998, expedido por la H. XV Legislatura, siendo Gobernador Constitucional el C. Lic. Héctor Terán Terán 1995-2001; fue reformado mediante Decreto 435, publicado en el Periódico Oficial No. 28, Índice, de fecha 31 de mayo de 2024, Tomo CXXXI, expedido por la H. XXIV Legislatura, siendo Gobernadora\nConstitucional la C. Marina del Pilar Ávila Olmeda 2021-2027;\nARTICULO 74.- Fue reformado por Decreto No. 233, publicado en el Periódico Oficial\nNo. 45, Tomo CV, de fecha 06 de noviembre de 1998, expedido por la H. XV Legislatura, siendo Gobernador Constitucional el C. Lic. Héctor Terán Terán 1995-2001; fue reformado mediante Decreto 435, publicado en el Periódico Oficial No. 28, Índice, de fecha 31 de mayo de 2024, Tomo CXXXI, expedido por la H. XXIV Legislatura, siendo Gobernadora\nConstitucional la C. Marina del Pilar Ávila Olmeda 2021-2027;\nARTICULO 75.- Fue reformado por Decreto No. 233, publicado en el Periódico Oficial\nNo. 45, Tomo CV, de fecha 06 de noviembre de 1998, expedido por la H. XV Legislatura, siendo Gobernador Constitucional el C. Lic. Héctor Terán Terán 1995-2001;\nARTICULO 76.- Fue reformado por Decreto No. 233, publicado en el Periódico Oficial\nNo. 45, Tomo CV, de fecha 06 de noviembre de 1998, expedido por la H. XV Legislatura, siendo Gobernador Constitucional el C. Lic. Héctor Terán Terán 1995-2001;\nFue modificada la denominación de este Capítulo por Decreto No. 233, publicado en el\nPeriódico Oficial No. 45, de fecha 06 de noviembre de 1998, Tomo CV, siendo Gobernador\nConstitucional el C. Lic. Héctor Terán Terán 1995-2001;\nCAPITULO XI\nPRESERVACION DE LOS MONUMENTOS Y ZONAS ARQUEOLOGICAS, HISTORICOS Y\nARTISTICOS\nARTICULO 77.- Fue reformado por Decreto No. 233, publicado en el Periódico Oficial siendo Gobernador Constitucional el C. Lic. Héctor Terán Terán 1995-2001; fue reformado mediante Decreto No. 529, publicado en el Periódico Oficial No. 35, de fecha 05 de agosto de 2016, Tomo CXXIII, Sección IV, expedido por la H. XXI Legislatura, siendo Gobernador\nConstitucional el C. Francisco Arturo Vega de Lamadrid 2013-2019;\nLey de Preservación del Patrimonio Cultural del Estado de Baja California. Página 43\n.\nActualización Legislativa.\nÚltima Reforma P. O. No. 37, Índice, 20-Jun-2025\nARTICULO 78.- Fue reformado por Decreto No. 233, publicado en el Periódico Oficial\nNo. 45, Tomo CV, de fecha 06 de noviembre de 1998, expedido por la H. XV Legislatura, siendo Gobernador Constitucional el C. Lic. Héctor Terán Terán 1995-2001;\nFue modificada la denominación este Capítulo por Decreto No. 233, publicado en el\nPeriódico Oficial No. 45, de fecha 06 de noviembre de 1998, Tomo CV, siendo Gobernador\nConstitucional el C. Lic. Héctor Terán Terán 1995-2001;\nCAPITULO XII\nDE LA PARTICIPACION POPULAR\nARTICULO 79.- Fue reformado por Decreto No. 233, publicado en el Periódico Oficial\nNo. 45, Tomo CV, de fecha 06 de noviembre de 1998, expedido por la H. XV Legislatura, siendo Gobernador Constitucional el C. Lic. Héctor Terán Terán 1995-2001; fue reformado mediante Decreto No. 529, publicado en el Periódico Oficial No. 35, de fecha 05 de agosto de 2016, Tomo CXXIII, Sección IV, expedido por la H. XXI Legislatura, siendo Gobernador\nConstitucional el C. Francisco Arturo Vega de Lamadrid 2013-2019; fue reformado mediante\nDecreto 435, publicado en el Periódico Oficial No. 28, Índice, de fecha 31 de mayo de 2024, Tomo CXXXI, expedido por la H. XXIV Legislatura, siendo Gobernadora Constitucional la C.\nMarina del Pilar Ávila Olmeda 2021-2027;\nSECCION PRIMERA\nDE LAS PERSONAS FISICAS Y MORALES\nARTICULO 80.- Fue reformado por Decreto No. 233, publicado en el Periódico Oficial\nNo. 45, Tomo CV, de fecha 06 de noviembre de 1998, expedido por la H. XV Legislatura, siendo Gobernador Constitucional el C. Lic. Héctor Terán Terán 1995-2001; fue derogado por Decreto No. 261, publicado en el Periódico Oficial No. 42, de fecha 21 de septiembre de\n2012, Tomo CXIX, Sección I, expedido por la H. XX Legislatura, siendo Gobernador\nConstitucional el C. José Guadalupe Osuna Millán 2007-2013;\nARTICULO 81.- Fue reformado por Decreto No. 233, publicado en el Periódico Oficial\nNo. 45, Tomo CV, de fecha 06 de noviembre de 1998, expedido por la H. XV Legislatura, siendo Gobernador Constitucional el C. Lic. Héctor Terán Terán 1995-2001; fue derogado por Decreto No. 261, publicado en el Periódico Oficial No. 42, de fecha 21 de septiembre de\n2012, Tomo CXIX, Sección I, expedido por la H. XX Legislatura, siendo Gobernador\nConstitucional el C. José Guadalupe Osuna Millán 2007-2013;\nARTICULO 82.- Fue derogado por Decreto No. 261, publicado en el Periódico Oficial\nLegislatura, siendo Gobernador Constitucional el C. José Guadalupe Osuna Millán 20072013;\nARTICULO 83.- Fue derogado por Decreto No. 261, publicado en el Periódico Oficial\nLegislatura, siendo Gobernador Constitucional el C. José Guadalupe Osuna Millán 20072013;\nLey de Preservación del Patrimonio Cultural del Estado de Baja California. Página 44\n.\nActualización Legislativa.\nÚltima Reforma P. O. No. 37, Índice, 20-Jun-2025\nSECCION SEGUNDA\nESTIMULOS FISCALES\nFue modificada la denominación de esta Sección mediante Decreto No. 261, Publicado en el Periódico Oficial No. 42, Tomo CXIX, Sección I, de fecha 21 de septiembre de 2012, expedido por la H. XX Legislatura, siendo Gobernador Constitucional el C. José\nGuadalupe Osuna Millán 2007-2013;\nSECCIÓN SEGUNDA\nESTIMULOS FISCALES Y APOYOS ECONÓMICOS.\nARTICULO 84.- Fue reformado por Decreto No. 233, publicado en el Periódico Oficial\nNo. 45, Tomo CV, de fecha 06 de noviembre de 1998, expedido por la H. XV Legislatura, siendo Gobernador Constitucional el C. Lic. Héctor Terán Terán 1995-2001; fue reformado por Decreto No. 261, publicado en el Periódico Oficial No. 42, de fecha 21 de septiembre de\n2012, Tomo CXIX, Sección I, expedido por la H. XX Legislatura, siendo Gobernador\nConstitucional el C. José Guadalupe Osuna Millán 2007-2013; fue reformado mediante\nDecreto 435, publicado en el Periódico Oficial No. 28, Índice, de fecha 31 de mayo de 2024, Tomo CXXXI, expedido por la H. XXIV Legislatura, siendo Gobernadora Constitucional la C.\nMarina del Pilar Ávila Olmeda 2021-2027;\nARTICULO 84 BIS.- Fue adicionado por Decreto No. 233, publicado en el Periódico\nOficial No. 45, Tomo CV, de fecha 06 de noviembre de 1998, expedido por la H. XV\nLegislatura, siendo Gobernador Constitucional el C. Lic. Héctor Terán Terán 1995-2001; fue reformado mediante Decreto 435, publicado en el Periódico Oficial No. 28, Índice, de fecha\n31 de mayo de 2024, Tomo CXXXI, expedido por la H. XXIV Legislatura, siendo\nGobernadora Constitucional la C. Marina del Pilar Ávila Olmeda 2021-2027;\nARTICULO 85.- Fue reformado mediante Decreto 435, publicado en el Periódico\nOficial No. 28, Índice, de fecha 31 de mayo de 2024, Tomo CXXXI, expedido por la H. XXIV\nLegislatura, siendo Gobernadora Constitucional la C. Marina del Pilar Ávila Olmeda 20212027;\nSECCION TERCERA\nPARTICIPACION DE LA INICIATIVA PRIVADA\nFue modificada la denominación de esta Sección mediante Decreto No. 261, publicado en el expedido por la H. XX Legislatura, siendo Gobernador Constitucional el C. José Guadalupe\nOsuna Millán 2007-2013;\nSECCIÓN TERCERA\nLey de Preservación del Patrimonio Cultural del Estado de Baja California. Página 45\n.\nActualización Legislativa.\nÚltima Reforma P. O. No. 37, Índice, 20-Jun-2025\nARTICULO 86.- Fue reformado por Decreto No. 233, publicado en el Periódico Oficial\nNo. 45, Tomo CV, de fecha 06 de noviembre de 1998, expedido por la H. XV Legislatura, siendo Gobernador Constitucional el C. Lic. Héctor Terán Terán 1995-2001; fue reformado mediante Decreto 435, publicado en el Periódico Oficial No. 28, Índice, de fecha 31 de mayo de 2024, Tomo CXXXI, expedido por la H. XXIV Legislatura, siendo Gobernadora\nConstitucional la C. Marina del Pilar Ávila Olmeda 2021-2027;\nFue modificada la denominación este Capítulo por Decreto No. 233, publicado en el\nPeriódico Oficial No. 45, de fecha 06 de noviembre de 1998, Tomo CV, siendo Gobernador\nConstitucional el C. Lic. Héctor Terán Terán 1995-2001;\nCAPITULO XIII\nDE LA VIGILANCIA, RECURSOS, SANCIONES Y DELITOS\nSECCION PRIMERA\nDE LA VIGILANCIA\nARTICULO 87.- Fue reformado por Decreto No. 233, publicado en el Periódico Oficial\nNo. 45, Tomo CV, de fecha 06 de noviembre de 1998, expedido por la H. XV Legislatura, siendo Gobernador Constitucional el C. Lic. Héctor Terán Terán 1995-2001; fue reformado mediante Decreto 435, publicado en el Periódico Oficial No. 28, Índice, de fecha 31 de mayo de 2024, Tomo CXXXI, expedido por la H. XXIV Legislatura, siendo Gobernadora\nConstitucional la C. Marina del Pilar Ávila Olmeda 2021-2027;\nARTICULO 91.- Fue reformado mediante Decreto 435, publicado en el Periódico\nOficial No. 28, Índice, de fecha 31 de mayo de 2024, Tomo CXXXI, expedido por la H. XXIV\nLegislatura, siendo Gobernadora Constitucional la C. Marina del Pilar Ávila Olmeda 20212027;\nARTICULO 92.- Fue reformado mediante Decreto 435, publicado en el Periódico\nOficial No. 28, Índice, de fecha 31 de mayo de 2024, Tomo CXXXI, expedido por la H. XXIV\nLegislatura, siendo Gobernadora Constitucional la C. Marina del Pilar Ávila Olmeda 20212027;\nARTICULO 93.- Fue reformado por Decreto No. 233, publicado en el Periódico Oficial siendo Gobernador Constitucional el C. Lic. Héctor Terán Terán 1995-2001; fue reformado mediante Decreto 435, publicado en el Periódico Oficial No. 28, Índice, de fecha 31 de mayo de 2024, Tomo CXXXI, expedido por la H. XXIV Legislatura, siendo Gobernadora\nConstitucional la C. Marina del Pilar Ávila Olmeda 2021-2027;\nARTICULO 96.- Fue reformado mediante Decreto 435, publicado en el Periódico\nLegislatura, siendo Gobernadora Constitucional la C. Marina del Pilar Ávila Olmeda 20212027;\nLey de Preservación del Patrimonio Cultural del Estado de Baja California. Página 46\n.\nActualización Legislativa.\nÚltima Reforma P. O. No. 37, Índice, 20-Jun-2025\nARTICULO 97.- Fue reformado por Decreto No. 233, publicado en el Periódico Oficial\nNo. 45, Tomo CV, de fecha 06 de noviembre de 1998, expedido por la H. XV Legislatura, siendo Gobernador Constitucional el C. Lic. Héctor Terán Terán 1995-2001;\nARTICULO 98.- Fue derogado por Decreto No. 233, publicado en el Periódico Oficial\nNo. 45, Tomo CV, de fecha 06 de noviembre de 1998, expedido por la H. XV Legislatura, siendo Gobernador Constitucional el C. Lic. Héctor Terán Terán 1995-2001;\nARTICULO 99.- Fue reformado por Decreto No. 233, publicado en el Periódico Oficial\nNo. 45, Tomo CV, de fecha 06 de noviembre de 1998, expedido por la H. XV Legislatura, siendo Gobernador Constitucional el C. Lic. Héctor Terán Terán 1995-2001; fue reformado mediante Decreto 435, publicado en el Periódico Oficial No. 28, Índice, de fecha 31 de mayo de 2024, Tomo CXXXI, expedido por la H. XXIV Legislatura, siendo Gobernadora\nConstitucional la C. Marina del Pilar Ávila Olmeda 2021-2027;\nARTICULO 100.- Fue reformado mediante Decreto No. 281, publicado en el Periódico\nOficial No. 55, de fecha 30 de noviembre de 2018, Tomo CXXV, Sección IV, expedido por la\nH. XXII Legislatura, siendo Gobernador Constitucional el C. Francisco Arturo Vega de\nLamadrid 2013-2019;\nARTICULO 101.- Fue reformado por Decreto No. 233, publicado en el Periódico\nOficial No. 45, Tomo CV, de fecha 06 de noviembre de 1998, expedido por la H. XV\nLegislatura, siendo Gobernador Constitucional el C. Lic. Héctor Terán Terán 1995-2001; fue reformado mediante Decreto No. 529, publicado en el Periódico Oficial No. 35, de fecha 05 de agosto de 2016, Tomo CXXIII, Sección IV, expedido por la H. XXI Legislatura, siendo\nGobernador Constitucional el C. Francisco Arturo Vega de Lamadrid 2013-2019; fue reformado mediante Decreto 435, publicado en el Periódico Oficial No. 28, Índice, de fecha\n31 de mayo de 2024, Tomo CXXXI, expedido por la H. XXIV Legislatura, siendo\nGobernadora Constitucional la C. Marina del Pilar Ávila Olmeda 2021-2027;\nARTICULO 102.- Fue reformado por Decreto No. 233, publicado en el Periódico\nOficial No. 45, Tomo CV, de fecha 06 de noviembre de 1998, expedido por la H. XV\nLegislatura, siendo Gobernador Constitucional el C. Lic. Héctor Terán Terán 1995-2001;\nARTICULO 103.- Fue reformado por Decreto No. 233, publicado en el Periódico\nLegislatura, siendo Gobernador Constitucional el C. Lic. Héctor Terán Terán 1995-2001; fue reformado mediante Decreto 435, publicado en el Periódico Oficial No. 28, Índice, de fecha\nGobernadora Constitucional la C. Marina del Pilar Ávila Olmeda 2021-2027;\nARTICULO 104.- Fue reformado mediante Decreto 435, publicado en el Periódico\nLegislatura, siendo Gobernadora Constitucional la C. Marina del Pilar Ávila Olmeda 20212027;\nLey de Preservación del Patrimonio Cultural del Estado de Baja California. Página 47\n.\nActualización Legislativa.\nARTICULO 105.- Fue reformado por Decreto No. 233, publicado en el Periódico\nLegislatura, siendo Gobernador Constitucional el C. Lic. Héctor Terán Terán 1995-2001;\nARTICULO 106.- Fue reformado mediante Decreto 435, publicado en el Periódico\nLegislatura, siendo Gobernadora Constitucional la C. Marina del Pilar Ávila Olmeda 20212027;\nLey de Preservación del Patrimonio Cultural del Estado de Baja California. Página 48\n.\nActualización Legislativa.\nÚltima Reforma P. O. No. 37, Índice, 20-Jun-2025\nARTICULOS TRANSITORIOS DEL DECRETO No. 233, POR EL QUE SE\nREFORMAN LOS ARTICULOS 1, 3, 4, 5, 6, 7, 9, 11, 13, 15, 17, 18, 20, 21, 22, 23, 24, 25, 27, 28, 29, 34, 35, 36, 37, 40, 41, 45, 47, 50, 51, 52, 53, 54, 55, 57, 58, 59, 60, 61, 62, 63, 64, 65, 66, 67, 69, 71, 72, 73, 74, 75, 76, 77, 78, 79, 80, 81, 84, 86, 87, 93, 97, 99, 101, 102,\n103 Y 105; SE ADICIONAN LOS ARTICULOS 72-A AL 72-D Y 84-BIS; SE DEROGAN LOS\nARTICULOS 2, 16, 26, 44, Y 98; SE MODIFICA LA DENOMINACION DE LA LEY DE\nPATRIMONIO CULTURAL DEL ESTADO DE BAJA CALIFORNIA; EL CAPITULO II,\nSECCION SEPTIMA Y CAPITULO V Y VII, Y SE MODIFICAN LOS CAPITULOS VIII A XV\nPARA REDUCIRSE DE VIII A XIII; Publicado en el Periódico Oficial No. 45, de fecha 6 de\nNoviembre de 1998, Tomo CV, expedido por la Honorable XV Legislatura Constitucional, siendo Gobernador del Estado el C. Lic. Alejandro González Alcocer; 7 de octubre de 1998-\n2001.\nARTICULO PRIMERO.- Las presentes reformas a la Ley del Patrimonio Cultural del\nEstado de Baja California, entrarán en vigor al día siguiente de su publicación en el Periódico\nOficial del Estado.\nARTICULO SEGUNDO.- El reglamento de la Ley del Patrimonio Cultural del Estado de Baja California y demás disposiciones administrativas, regirán en todo lo que no se oponga a las presentes reformas, hasta en tanto no se expida el nuevo reglamento.\nLegislativo, en la Ciudad de Mexicali, Baja California, a los diecisiete días del mes de septiembre de mil novecientos noventa y ocho.\nM.V.Z. JOSE MANUEL SALCEDO SAÑUDO\nDIPUTADO PRESIDENTE\nRUBRICA\nDIP. JUAN PABLO VALENZUELA GARCIA\nDIPUTADO SECRETARIO\nRUBRICA\nDE CONFORMIDAD CON LO DISPUESTO POR LA FRACCION I DEL ARTICULO 49\nDE LA CONSTITUCION POLITICA DEL ESTADO, MANDO SE IMPRIMA Y PUBLIQUE.\nMEXICALI, BAJA CALIFORNIA, A LOS VEINTE DIAS DEL MES DE OCTUBRE DE\nMIL NOVECIENTOS NOVENTA Y OCHO.\nEL GOBERNADOR CONSTITUCIONAL DEL ESTADO\nLIC. ALEJANDRO GONZALEZ ALCOCER\nRUBRICA\nEL OFICIAL MAYOR DE GOBIERNO\nLey de Preservación del Patrimonio Cultural del Estado de Baja California. Página 49\n.\nActualización Legislativa.\nÚltima Reforma P. O. No. 37, Índice, 20-Jun-2025\nENCARGADO DE LA SECRETARIA GENERAL\nDE GOBIERNO POR MINISTERIO DE LEY\nLIC. SALVADOR MORALES MUÑOZ\nRUBRICA\nARTÍCULO ÚNICO TRANSITORIO DEL DECRETO No. 261, POR EL QUE SE\nREFORMAN LOS ARTÍCULOS 15, 18 FRACCIONES IX, XIV Y XVII, ARTÍCULO 22\nFRACCIÓN XII Y SE ADICIONA LA FRACCIÓN XIII, ARTÍCULOS 30, 31, 49, 56, 57, SE\nMODIFICAN LOS ARTÍCULOS 72A, 72B, 72C, Y 72D, SE DEROGAN LOS ARTÍCULOS\n80, 81, 82 Y 83; SE MODIFICA EL NOMBRE DE LA SECCIÓN SEGUNDA; SE\nREFORMA EL ARTÍCULO 84 Y SE MODIFICA EL NOMBRE DE LA SECCIÓN\nTERCERA, PUBLICADO EN EL PERIÓDICO OFICIAL NO. 42, TOMO CXIX, SECCION I,\nDE FECHA 21 DE SEPTIEMBRE DE 2012, EXPEDIDO POR LA H. XX LEGISLATURA,\nSIENDO GOBERNADOR CONSTITUCIONAL EL C. JOSÉ GUADALUPE OSUNA MILLÁN\n2007-2013.\nARTÍCULO TRANSITORIO\nÚNICO: Las presentes reformas entraran en vigor al día siguiente de su publicación en el periódico oficial, órgano de difusión del Gobierno\nConstitucional del Estado Baja California.\nDADO en el Salón de Sesiones “Lic. Benito Juárez García” del H. Poder Legislativo del Estado de Baja California, en la Ciudad de Mexicali, B.C., a los treinta y ún días del mes de julio del año dos mil doce.\nDIP. ALFONSO GARZÓN ZATARAIN\nPRESIDENTE\n(RÚBRICA)\nDIP. FAUSTO ZÁRATE ZEPEDA\nSECRETARIO\n(RÚBRICA)\nDE CONFORMIDAD CON LO DISPUESTO POR LA FRACCIÓN I DEL ARTÍCULO 49\nMEXICALI, BAJA CALIFORNIA, A LOS CINCO DÍAS DEL MES DE SEPTIEMBRE\nDEL AÑO DOS MIL DOCE.\nJOSÉ GUADALUPE OSUNA MILLÁN\nGOBERNADOR DEL ESTADO\n(RÚBRICA)\nLey de Preservación del Patrimonio Cultural del Estado de Baja California. Página 50\n.\nActualización Legislativa.\nÚltima Reforma P. O. No. 37, Índice, 20-Jun-2025\nFRANCISCO ANTONIO GARCÍA BURGOS\nSECRETARIO GENERAL DE GOBIERNO\n(RÚBRICA)\nARTÍCULO ÚNICO TRANSITORIO DEL DECRETO No. 529, POR EL QUE SE\nREFORMAN LOS ARTÍCULOS 9 FRACCIÓN III, LA DENOMINACIÓN DE LA SECCIÓN\nTERCERA DEL CAPÍTULO II, ARTÍCULO 13, ARTÍCULO 18 FRACCIÓN IX, A LA QUE\nADEMÁS SE ADICIONA UN SEGUNDO PÁRRAFO, ARTÍCULO 22 FRACCIÓN III A LA VI Y\nXII A LA XIII, ARTÍCULO 40 Y A LA FRACCIÓN V DEL MISMO, ARTÍCULO 56 PÁRRAFOS\nPRIMERO Y SEGUNDO, ARTÍCULO 62 AL QUE SE ADICIONA UN SEGUNDO PÁRRAFO,\nARTÍCULO 72 QUARTER Y 72 QUINQUIES PÁRRAFO SEGUNDO, ARTÍCULO 77,\nARTÍCULO 79 FRACCIÓN III Y ARTÍCULO 101 CUARTO PÁRRAFO; PUBLICADO EN EL\nPERIÓDICO OFICIAL No. 32, SECCIÓN IV, TOMO CXXIII, DE FECHA 15 DE JULIO DE\n2016, EXPEDIDO POR LA H. XXI LEGISLATURA, SIENDO GOBERNADOR\nCONSTITUCIONAL EL C. FRANCISCO ARTURO VEGA DE LAMADRID 2013-2019.\nARTÍCULO TRANSITORIO\nÚNICO.- La presente reforma entrará en vigor al día siguiente de su publicación en el\nPeriódico Oficial del Estado de Baja California.\nDADO en el Salón de Sesiones “Lic. Benito Juárez García” del H. Poder Legislativo del Estado de Baja California, en la Ciudad de Mexicali, B.C., a los siete días del mes de julio del año dos mil dieciséis.\nDIP. MÓNICA BEDOYA SERNA\nPRESIDENTA\n(RUBRICA)\nDIP. ROSA ISELA PERALTA CASILLAS\nSECRETARIO\n(RUBRICA)\nDE CONFORMIDAD CON LO DISPUESTO POR LA FRACCIÓN I DEL ARTÍCULO 49\nMEXICALI, BAJA CALIFORNIA, A LOS VEINTIOCHO DÍAS DEL MES DE JULIO DEL\nAÑO DOS MIL DIECISÉIS.\nFRANCISCO ARTURO VEGA DE LAMADRID\nGOBERNADOR DEL ESTADO\n(RÚBRICA)\nFRANCISCO RUEDA GOMEZ\nSECRETARIO GENERAL DE GOBIERNO\nLey de Preservación del Patrimonio Cultural del Estado de Baja California. Página 51\n.\nActualización Legislativa.\nÚltima Reforma P. O. No. 37, Índice, 20-Jun-2025\n(RÚBRICA)\nARTÍCULO SEGUNDO TRANSITORIO DEL DECRETO No. 281, POR EL QUE SE\nREFORMA EL ARTÍCULO 100, PUBLICADO EN EL PERIÓDICO OFICIAL No. 55,\nSECCION IV, TOMO CXXV, DE FECHA 30 DE NOVIEMBRE DE 2018, EXPEDIDO POR LA\nH. XXII LEGISLATURA, SIENDO GOBERNADOR CONSTITUCIONAL EL C. FRANCISCO\nARTURO VEDA DE LAMADRID 2013-2019.\nARTÍCULOS TRANSITORIOS\nARTÍCULO PRIMERO.- El presente decreto entrará en vigor al día siguiente al de su publicación en el Periódico Oficial del Estado de Baja California.\nARTÍCULO SEGUNDO.- El valor diario de la Unidad de Medida y Actualización a la fecha de entrada en vigor, se tomará el valor publicado en el Diario Oficial de la Federación por el INEGI. El valor de la Unidad de Medida y Actualización a la fecha de entrada en vigor del presente Decreto, será producto de multiplicar el valor referido en el párrafo anterior por\n30.4. Por su parte, el valor anual será el producto de multiplicar el valor inicial mensual por\n12.\nARTÍCULO TERCERO. - Todas las menciones al salario mínimo como unidad de cuenta, índice, base, medida o referencia para determinar la cuantía de las obligaciones, sanciones, multas administrativas, conceptos de pago y montos de referencia, se entenderán referidas a la Unidad de Medida y Actualización.\nDADO en el Salón de Sesiones “Lic. Benito Juárez García” del H. Poder Legislativo del Estado de Baja California, en la Ciudad de Mexicali, B.C., a los veinticinco días del mes de octubre del año dos mil dieciocho.\nDIP. ROCÍO LÓPEZ GOROSAVE\nPRESIDENTA\n(RÚBRICA)\nDIP. MÓNICA HERNÁNDEZ ÁLVAREZ\nSECRETARIA\n(RÚBRICA)\nDE CONFORMIDAD CON LO DISPUESTO POR LA FRACCIÓN I DEL ARTÍCULO 49\nMEXICALI, BAJA CALIFORNIA, A LOS TREINTA DÍAS DEL MES DE NOVIEMBRE\nDEL AÑO DOS MIL DIECIOCHO.\nFRANCISCO ARTURO VEGA DE LAMADRID\nGOBERNADOR DEL ESTADO\nLey de Preservación del Patrimonio Cultural del Estado de Baja California. Página 52\n.\nActualización Legislativa.\nÚltima Reforma P. O. No. 37, Índice, 20-Jun-2025\n(RÚBRICA)\nFRANCISCO RUEDA GÓMEZ\nSECRETARIO GENERAL DE GOBIERNO\n(RÚBRICA)\nARTÍCULO TERCERO TRANSITORIO DEL DECRETO No. 435, POR EL QUE SE\nREFORMA LA DENOMINACIÓN DE LAS SECCIONES PRIMERA, TERCERA Y QUINTA\nDEL CAPÍTULO II, ASÍ COMO LOS ARTÍCULOS 9, 10, 11, 12, 13, 17, 18, 19, 20, 21, 22, 23, 24, 25, 30, 31, 32, 33, 34, 35, 36, 45, 48, 51, 53, 54, 55, 61, 62, 63, 66, 67, 70, 72, 72\nBIS, 72 QUATER, 72 QUINQUIES, 73, 74, 79, 84, 84 BIS, 85, 86, 87, 91, 92, 93, 96, 99,\n101, 103, 104 y 106; PUBLICADO EN PERIÓDICO OFICIAL No. 28, ÍNDICE, DE FECHA 31\nDE MAYO DE 2024, TOMO CXXXI, EXPEDIDO POR LA H. XXIV LEGISLATURA, SIENDO\nGOBERNADORA CONSTITUCIONAL LA C. MARINA DEL PILAR ÁVILA OLMEDA 2021-\n2027.\nARTÍCULOS TRANSITORIOS\nPRIMERO.- Las presentes reformas entrarán en vigor al día siguiente de su publicación en el Periódico Oficial del Estado.\nSEGUNDO.- Los expedientes que se encuentren en trámite a la entrada en vigor de la presente reforma, relativos a declaratorias de patrimonio cultural, el Instituto de Cultura de Baja California deberá remitirlos a la Secretaría de Cultura para continuar con las gestiones correspondientes dentro del plazo de 30 días.\nDADO en Sesión Extraordinaria de la XXIV Legislatura en la Ciudad de Mexicali, B.C., a los veintinueve días del mes de mayo del año dos mil veinticuatro.\nDIP. RAMÓN VÁZQUEZ VALADEZ\nPRESIDENTE\n(RÚBRICA)\nDIP. MANUEL GUERRERO LUNA\nSECRETARIO\n(RÚBRICA)\nDE CONFORMIDAD CON LO DISPUESTO POR LA FRACCIÓN I DEL ARTÍCULO 49 DE\nCALIFORNIA, IMPRÍMASE Y PUBLÍQUESE.\nMEXICALI, BAJA CALIFORNIA A LOS VEINTINUEVE DÍAS DEL MES DE MAYO DEL AÑO\nDOS MIL VEINTICUATRO.\nLey de Preservación del Patrimonio Cultural del Estado de Baja California. Página 53\n.\nActualización Legislativa.\nÚltima Reforma P. O. No. 37, Índice, 20-Jun-2025\nMARINA DEL PILAR ÁVILA OLMEDA\nGOBERNADORA CONSTITUCIONAL\nDEL ESTADO DE BAJA CALIFORNIA\nALFREDO ÁLVAREZ CÁRDENAS\nSECRETARIO GENERAL DE GOBIERNO\nDEL ESTADO DE BAJA CALIFORNIA\nARTÍCULO ÚNICO TRANSITORIO DEL DECRETO No. 96, POR EL QUE SE\nAPRUEBA LA REFORMA AL ARTÍCULO 22; PUBLICADO EN EL PERIÓDICO OFICIAL No.\n37, ÍNDICE, DE FECHA 20 DE JUNIO DE 2025, TOMO CXXXII; EXPEDIDO POR LA H.\nXXV LEGISLATURA, SIENDO GOBERNADORA CONSTITUCIONAL LA C. MARINA DEL\nPILAR ÁVILA OLMEDA 2021-2027.\nTRANSITORIO\nÚNICO.- La presente reforma entrará en vigor al día siguiente al de su publicación en el\nPeriódico Oficial del Estado.\nDADO en Sesión Ordinaria de la XXV Legislatura en la Ciudad de Mexicali, B.C., a los cinco días del mes de junio del año dos mil veinticinco.\nDIP. MICHELLE ALEJANDRA TEJEDA MEDINA\nPRESIDENTA\n(RÚBRICA)\nDIP. NORMA ANGELICA PEÑALOZA ESCOBEDO\nSECRETARIA\n(RÚBRICA)\nDE CONFORMIDAD CON LO DISPUESTO POR LA FRACCIÓN I DEL ARTÍCULO 49\nCALIFORNIA, IMPRÍMASE Y PUBLÍQUESE.\nMEXICALI, BAJA CALIFORNIA, A LOS 6 DÍAS DEL MES DE JUNIO DEL AÑO DOS\nMIL VEINTICINCO.\nMARINA DEL PILAR ÁVILA OLMEDA\nGOBERNADORA DEL ESTADO\nDE BAJA CALIFORNIA\n(RÚBRICA)\nALFREDO ÁLVAREZ CÁRDENAS\nSECRETARIO GENERAL DE GOBIERNO\nDEL ESTADO DE BAJA CALIFORNIA\n(RÚBRICA)\nLey de Preservación del Patrimonio Cultural del Estado de Baja California. Página 54",
  "ordenamiento": "REGLAMENTO",
  "jurisdiccion": "BAJA CALIFORNIA",
  "fuente_oficial": "Periódico Oficial",
  "FECHA PER OFIC": "2025/06/20",
  "ESTATUS": "VIGENTE",
  "TOMO": "TOMO_VI",
  "URL": "https://www.congresobc.gob.mx/Documentos/ProcesoParlamentario/Leyes/TOMO_VI/20250620_LEYPATCU.PDF",
  "es_escaneado": false,
  "tiene_tablas": false,
  "materia": [
    "social",
    "salud",
    "educación",
    "cultura"
  ]
}