{
  "titulo": "Ley DE DESARROLLO URBANO DEL ESTADO DE BAJA CALIFORNIA",
  "Contenido": "Publicado en el Periódico Oficial No. 26, Tomo CI, Sección I,\nTITULO PRIMERO\nCAPITULO PRIMERO\nDisposiciones Generales\nARTICULO 1.- Las disposiciones de esta Ley y sus reglamentos, así como los\nProgramas y Declaratorias que expidan las autoridades competentes conforme a sus normas, son de orden público e interés social.\nTodas las acciones de urbanización en áreas y predios que generen la transferencia de suelo rural a urbano, las fusiones, subdivisiones y fraccionamiento de terrenos, los cambios en la utilización de éstos, así como todas las obras de urbanización y edificación que se realicen en la entidad, quedan sujetas a cumplir con las disposiciones de la presente\nLey, siendo obligatoria su observancia tanto para las entidades públicas como para los particulares.\nARTICULO 2.- La presente Ley tiene por objeto:\nI. Establecer las normas que regulen la concurrencia del Estado y los Municipios que lo integran, al participar en la ordenación y regulación de los asentamientos humanos;\nII. Fijar normas básicas para planear la fundación, conservación, mejoramiento y crecimiento de los centros de población en esta entidad Federativa;\nIII. Establecer las normas conforme a las cuales el Gobierno del Estado y los\nAyuntamientos ejercerán sus atribuciones para zonificar el territorio y determinar las correspondientes provisiones, usos, destinos de áreas y predios;\nIV. Fijar las normas básicas para reglamentar, autorizar, controlar y vigilar la urbanización de áreas y predios, así como la edificación en los mismos;\nV. Definir las disposiciones que regulen toda acción inmobiliaria que emprendan las entidades de la Administración Pública Federal, Estatal y Municipal, o los particulares con el fin de ejecutar las acciones que se determinen; y,\nVI. Establecer el interés social y la utilidad pública para los casos en que proceda la expropiación de bienes de propiedad privada, a fin de dar cumplimiento a las disposiciones\nLey de Desarrollo Urbano del Estado de Baja California. Página 1\nARTICULO 3.- La ordenación y regulación de los asentamientos humanos en el\nEstado tenderá a mejorar las condiciones de vida de la población urbana y rural mediante:\nI. El aprovechamiento en beneficio social de los elementos naturales susceptibles de apropiación tomando las medidas necesarias para la conservación del equilibrio ecológico, población y lograr una distribución equitativa de la riqueza pública;\nII. El desarrollo socioeconómico sustentable del Estado, armonizando la interrelación de las ciudades y el campo y distribuyendo equitativamente los beneficios y cargas del proceso del desarrollo urbano;\nIII. La distribución equilibrada y sustentable de los centros de población en el territorio de los municipios, integrándolos en el marco del desarrollo estatal y nacional;\nIV. La adecuada interrelación socioeconómica de los centros de población de los municipios del Estado con el sistema estatal y nacional;\nV. La más eficiente interrelación entre los sistemas de convivencia y de servicios en cada centro de población, particularmente la creación y mejoramiento de condiciones favorables para la relación adecuada entre zonas industriales y de vivienda de trabajadores, el transporte entre ambas y las justas posibilidades de trabajo y descanso;\nVI. El fomento de ciudades con dimensiones adecuadas a las características regionales, a fin de evitar que por su desproporción produzca impactos económicos negativos y grave deterioro social y humano;\nVII. El mejoramiento de la calidad de vida que la comunidad demanda;\nVIII. La mayor participación ciudadana en la solución de los problemas que genera la convivencia en los asentamientos humanos;\nIX. La regulación del mercado de los terrenos dedicados a la vivienda de interés social y popular;\nX. La promoción de obras para que todos los habitantes del Estado tengan vivienda digna;\nXI. La protección del patrón de asentamiento humano rural y de las comunidades indígenas;\nXII. La estructuración interna de los centros de población y la dotación oportuna de infraestructura, equipamiento y servicios urbanos;\nXIII. La prevención, control y atención de riesgos y contingencias ambientales y urbanos en los centros de población;\nXIV. La conservación y mejoramiento del ambiente en los asentamientos humanos;\nXV. El ordenado aprovechamiento de la propiedad inmobiliaria en los centros de población;\nFracción Reformada\nLey de Desarrollo Urbano del Estado de Baja California. Página 2\nXVI. La coordinación y concertación de la inversión pública y privada con la planeación del desarrollo regional y urbano; y,\nFracción Reformada\nXVII. El desarrollo y adecuación en los centros de población de la infraestructura, el requieran las personas, en especial para mujeres, niños, niñas, personas adultas mayores y personas con discapacidad.\nFracción Reformada\nArtículo Reformado\nARTICULO 4.- Los Planes y Programas de Desarrollo Urbano y las declaratorias sobre provisiones, usos, reservas y destinos de áreas, zonas y predios, son de orden público e interés social, por lo que el ejercicio del derecho de propiedad sobre los bienes inmuebles comprendidos en ellos estará sujeto a las normas contenidas en los mismos, de acuerdo con lo previsto en los artículos 27 de la Constitución Política de los Estados Unidos Mexicanos y\n821 del Código Civil para el Estado de Baja California.\nPárrafo Reformado\nQueda prohibido utilizar como propaganda gubernamental en el equipamiento urbano y en la infraestructura expresiones, emblemas, símbolos, logotipos que impliquen promoción personalizada de cualquier servidor público o partido político, salvo en los casos de señalizaciones conforme a las normas oficiales mexicanas y demás disposiciones que resulten aplicables.\nPárrafo Reformado\nPara el otorgamiento de uso de suelo y construcción, para el establecimiento u operación de cualquier giro comercial, industrial o de servicios en zona agrícola, pecuaria, agropecuaria, forestal y ambiental que no sea de competencia federal será requisito indispensable que su operación o finalidad no contravengan el Programa de Ordenamiento\nEcológico del Estado, la planeación urbana estatal y municipal, así como planes y programas establecidos.\nPárrafo Adicionado\nQuedan prohibidos los usos de suelo y de construcción para casinos, casas, centros o cualquier establecimiento que opere juego con apuestas, apuestas remotas, salas de sorteo de números, mesas de juego, máquinas electrónicas de juego, videojuegos electrónicos susceptibles de apuestas, máquinas de videojuegos electrónicos o electromecánicas de habilidad y destreza, juegos de azar y demás similares, salvo en aquellos casos en que el ubique; o se refiera a cualquiera de dichos establecimientos que constituya en sí mismo de que se trate, siempre que ello propicie la generación de empleos, el desarrollo económico municipal.\nPárrafo Adicionado\nArtículo Reformado\nLey de Desarrollo Urbano del Estado de Baja California. Página 3\nARTICULO 5.- El derecho de propiedad, posesión o cualquier otro derecho derivado de la tenencia de áreas y predios, serán ejercidos por sus titulares en forma compatible con el aprovechamiento determinado por las correspondientes declaratorias de provisiones, usos, reservas y destinos que se expidan conforme a los dispuesto en el Plan y los\nProgramas de Desarrollo Urbano.\nARTICULO 6.- Para efectos de este Ley se entiende por:\nI. Acción de Urbanización: La adecuación física, total o progresiva que habilite al suelo rústico o del suelo previamente urbanizado para alojar actividades de habitación, educación, esparcimiento y producción de bienes y servicios;\nII. Asentamiento humano: La radicación de un conglomerado demográfico con el conjunto de sus sistemas de convivencia en un área localizada, considerando en la misma a los elementos naturales y las obras materiales que la integran;\nIII. Area Urbana: La extensión de terreno que ha sido sujeta a acciones de urbanización y edificación.\nIV.- Área Verde Urbana.- Bien inmueble del dominio público municipal ubicado dentro de los límites de los centros de población, ocupado predominantemente por vegetación, destinado al uso, disfrute o aprovechamiento colectivo y de acceso generalizado y libre tránsito;\nFracción Reformada\nV.- Centros de población: Las áreas urbanas ocupadas por las instalaciones necesarias para su vida normal; las que se reserven para su expansión futura; las constituidas por los elementos naturales que cumplen una función de preservación de sus condiciones ecológicas y, las que se dediquen a la fundación del mismo, conforme a las leyes aplicables;\nVI.- Conservación: La acción tendiente a mantener el equilibrio ecológico y el patrimonio histórico-cultural de la entidad, que requieren de su preservación;\nVII.- Conurbación: El fenómeno que se presenta cuando dos o más centros de población por su crecimiento y relaciones socioeconómicas, formen o tiendan a formar una unidad urbana;\nVIII.- Crecimiento: La expansión de los límites de las áreas ocupadas con edificios, de población;\nIX.- Desarrollo urbano: El conjunto armónico de acciones que se realicen en beneficio de la población para lograr mayor equidad en las relaciones sociales, mejores niveles de ingreso y evitar el deterioro ambiental; involucra la ordenación, regulación, adecuación y mejora tanto de los aspectos físicos como económicos y sociales de un centro de población, así como sus relaciones con el medio ambiente natural y sus recursos;\nLey de Desarrollo Urbano del Estado de Baja California. Página 4\nX.- Destinos: Los fines públicos a que se prevea dedicar determinadas zonas, áreas y predios de un centro de población;\nXI.- Equipamiento Urbano: El conjunto de espacios y edificaciones de uso predominantemente público donde se proporciona un servicio a la población, que contribuye que se clasifican en los subsistemas siguientes: educación, salud, asistencia pública, comercio y abasto, áreas verdes urbanas, recreación, deporte, comunicación y transporte, diversión, cultura, espectáculos, administración y seguridad pública;\nFracción Reformada\nXII.- Fundación: El establecimiento de un centro de población previsto en el Plan\nEstatal de Desarrollo Urbano, decretado por la Legislatura Local;\nXIII.- Infraestructura: Todos los sistemas de comunicación y transporte de personas, de organización y distribución de bienes tales como: estructura vial, distribución de aguas, combustible, drenaje, alcantarillado, electricidad y telefonía;\nXIV.- Mejoramiento: La acción tendiente a reordenar y renovar las zonas deterioradas o de incipiente desarrollo el territorio estatal o de un centro de población;\nXV.- Obras de edificación: Las acciones de adecuación física y espacial temporal o permanente hecha con el propósito de facilitar las actividades humanas que condicionan los usos y destinos del suelo;\nXVI.- Ordenamiento territorial de los asentamientos humanos: El proceso de distribución equilibrada y sustentable de la población y de las actividades económicas en el territorio nacional;\nXVII.- Ordenación de los centros de población: El conjunto de dispositivos que tienden a lograr el desarrollo físico integral de los mismos, mediante la armónica relación y jerarquización de sus elementos;\nXVIII.- Planeación y programación de los centros de población: Esfuerzo conjunto planeado y ordenado de acciones físicas, sociales y económicas, organizadas con anticipación y distribuidas en el tiempo para poder lograr un óptimo desarrollo urbano;\nXIX.- Provisiones: Las áreas que serán utilizadas para la fundación de un centro de población;\nXX.- Reservas territoriales: Las áreas de un centro de población que serán utilizadas vivienda;\nXXI.- Secretaría: La Secretaría de Desarrollo Urbano y Reordenación Territorial.\nFracción Reformada\nXXII.- Servicios urbanos: Las actividades operativas públicas prestadas directamente centros de población;\nLey de Desarrollo Urbano del Estado de Baja California. Página 5\nXXIII.- Suelo urbanizado: Todo aquel terreno que ha recibido la acción de urbanización y que es susceptible de ser incorporado o reincorporado al municipio;\nXXIV.- Zonificación: La determinación de las áreas que integran y delimitan un centro de población; sus aprovechamientos predominantes y las reservas, usos y destinos, así como la delimitación de las áreas de conservación, mejoramiento y crecimiento del mismo;\nXXV.- Usos: Los fines particulares a que podrán destinarse determinadas zonas, áreas y predios de un centro de población;\nXXVI.- Zona Metropolitana: es el espacio territorial de influencia dominante de un centro de población; pudiendo constituirse en cualquiera de los siguientes casos:\nCuando uno o más municipios, demarcaciones territoriales o asentamientos humanos en los que se localiza una ciudad de 50 mil o más habitantes, cuya área urbana, funciones y actividades rebasan el límite del centro de población, municipio o demarcación que originalmente la contenía, incorporando como parte de sí misma o de su área de influencia directa a poblados o municipios vecinos, predominantemente urbanos, con los que mantiene un alto grado de integración socioeconómica; o\nEn aquéllos poblados o municipios, demarcaciones territoriales o asentamientos humanos que cuenten con una ciudad de un millón o más de habitantes, o\nEn aquéllos poblados, municipios, demarcaciones territoriales o asentamientos humanos que cuenten con ciudades de 250 mil o más habitantes y que comparten procesos de conurbación con ciudades de Estados Unidos de América.\nXXVII.- Zona Conurbada o Metropolitana Interestatal: aquella zona conurbada o metropolitana cuyos límites colinden con otra entidad federativa. Para su planeación y desarrollo se estará, además de lo dispuesto en la presente la Ley, a lo dispuesto en la Ley\nGeneral de Asentamientos Humanos.\nXXVIII.- Polígonos: Es la unidad urbanística constituida por una superficie de terreno, delimitada para fines de valoración catastral, ordenación urbana, planificación industrial, comercial, residencial.\nXXIX.- Vivienda Digna y Adecuada: Aquella que cumpla con las disposiciones jurídicas aplicables en materia de asentamientos humanos, construcción, habitabilidad, salubridad, que cuente con los servicios públicos básicos y brinde a sus ocupantes seguridad jurídica en cuanto a su propiedad o legítima posesión. Esta deberá comprender naturales y antropogénicos que sean potencialmente agresivos.\nFracción Reformada\nPara efectos de lo dispuesto en esta fracción, la vivienda deberá contar con espacios habitables y de higiene suficiente, adecuada iluminación y ventilación, servicios públicos básicos de agua potable, drenaje, alcantarillado, energía eléctrica y acceso a vías de criterios de sustentabilidad y eficiencia energética.\nLey de Desarrollo Urbano del Estado de Baja California. Página 6\nXXX.- Seguridad de trayecto: Se entiende por el desplazamiento de ida o regreso libre circulación, a la seguridad e integridad física de las personas.\nFracción Adicionada\nXXXI.- Fraccionamiento de Nueva Creación: Aquel cuya autorización tenga de un año de antigüedad a la solicitud de cualquier acción de urbanización.\nFracción Adicionada\nXXXII.- Asentamiento Humano Irregular.- El establecimiento de un grupo de personas, sin autorización previa de la autoridad competente, en un terreno urbano o rústico no destinado para su urbanización de conformidad con los Planes y Programas estatales o municipales de desarrollo urbano.\nFracción Adicionada\nXXXIII.- Movilidad: Derecho humano que consiste en el desplazamiento de personas, bienes y cosas que se realizan en el Estado, a través de los diferentes medios, formas y modalidades de transporte que se ajuste a la jerarquía y principios que se establecen en la\nLey de Movilidad Sustentable y Transporte del Estado de Baja California, para satisfacer sus necesidades y pleno desarrollo. En todo caso la movilidad tendrá como eje central a la persona.\nFracción Adicionada\nArtículo Reformado\nCAPITULO SEGUNDO\nDe la concurrencia y competencia de las autoridades órganos auxiliares\nARTICULO 7.- Son autoridades en materia de Desarrollo Urbano:\nI. El Congreso del Estado;\nII. El Gobernador del Estado;\nIII. Los Ayuntamientos del Estado;\nIV. La Secretaría de Desarrollo Urbano y Reordenación Territorial;\nFracción Reformada\nV. La Secretaría de Economía Sustentable y Turismo;\nFracción Adicionada\nVI. La Comisión Coordinadora de Desarrollo Urbano del Estado; y,\nFracción Recorrida\nVII. La Comisión Intersecretarial de Desarrollo Integral Regional.\nFracción Reformada\nArtículo Reformado\nLey de Desarrollo Urbano del Estado de Baja California. Página 7\nARTICULO 8.- Se considerarán órganos auxiliares de participación social y de consulta, los establecidos en la Ley de Planeación del Estado de Baja California en materia de Desarrollo Urbano.\nARTICULO 9.- Corresponde al Congreso del Estado:\nI. Dictar los Decretos sobre la fundación de nuevos centros de población previstos en el Plan Estatal de Desarrollo Urbano y propuestos al Gobernador del Estado por la\nFederación o por el Ayuntamiento respectivo;\nII. Dictar los Decretos sobre los límites de los centros de población, así como su modificación a propuesta de los Ayuntamientos, previo dictamen técnico de congruencia del\nEjecutivo del Estado;\nIII. Aprobar los límites de las zonas de conurbación intermunicipales y los de las\nZonas Metropolitanas, con base en el proyecto de declaratoria que formule el Ejecutivo del\nEstado, para reconocer su existencia o el acuerdo que celebre el Ejecutivo del Estado con los Ayuntamientos involucrados, conforme a lo dispuesto en el Título Tercero, de esta Ley;\nIV. Resolver las diferencias que sobre la materia de la presente Ley existan entre las autoridades estatales y municipales; y,\nV. Las demás atribuciones que le otorgue la presente Ley, los reglamentos y sus disposiciones aplicables.\nArtículo Reformado\nARTICULO 10.- Son atribuciones del Ejecutivo Estatal:\nI. Vigilar que el Plan Estatal de Desarrollo Urbano sea congruente con las disposiciones del Plan Estatal de Desarrollo, precisando los objetivos, prioridades y políticas que regirán la acción pública en esta materia;\nII. Asegurar la congruencia del Plan Estatal de Desarrollo Urbano con el Programa\nSectorial de Desarrollo Urbano a nivel Federal, haciendo al efecto las proposiciones que se estimen convenientes para su elaboración, evaluación y revisión, así como coadyuvar con las autoridades federales para su cumplimiento dentro del territorio del Estado;\nIII. Elaborar, aprobar, publicar, ejecutar y revisar el Plan Estatal de Desarrollo Urbano, promoviendo, encauzando y garantizando la participación de los diversos grupos sociales, organizaciones e instituciones representativas conforme a las disposiciones de esta Ley, la\nLey de Planeación del Estado y las normas reglamentarias respectivas;\nIV. Participar, con la concurrencia de los Ayuntamientos involucrados, en la elaboración, ejecución, control, evaluación y revisión de los Programas Regionales de\nDesarrollo Urbano, aprobarlos y publicarlos, así como aprobar y publicar los convenios de coordinación correspondientes;\nV. Proponer ante el Congreso del Estado la fundación de nuevos centros de población, con base en los proyectos contenidos en el Plan de Desarrollo Urbano y el Plan\nLey de Desarrollo Urbano del Estado de Baja California. Página 8 de Ordenamiento Ecológico tanto estatal como municipales; atender las solicitudes del\nVI. Opinar sobre los diferentes Planes y Programas de Desarrollo Urbano en la esfera municipal, incluyendo los Programas Parciales y las declaratorias que aprueben los\nAyuntamientos, mediante un dictamen técnico de congruencia previo a su publicación, en relación con el Plan Estatal de Desarrollo Urbano y los Programas Regionales de Desarrollo\nUrbano, verificando que se cumpla con los requisitos y procedimientos establecidos en la presente Ley;\nVII. Publicar los diferentes Programas de Desarrollo Urbano de aplicación directa en el ámbito municipal y sus declaratorias de provisiones, usos, destinos y reservas aprobadas por los Ayuntamientos respectivos;\nVIII. Aprobar, ejecutar, controlar, evaluar y revisar los Programas Parciales que en forma conjunta con los Ayuntamientos y conforme a las disposiciones de esta Ley, se expidan para la utilización parcial y total de la reserva territorial y de las zonas de preservación ecológica;\nIX. Ordenar la inscripción en el Registro Público de la Propiedad y del Comercio y disponer la publicación de los Planes y Programas de Desarrollo Urbano a que se refiere el\nArtículo 24 del presente ordenamiento, las declaratorias y todas aquellas resoluciones que de acuerdo con esta Ley corresponda al Ejecutivo;\nX. Extender a los Ayuntamientos a través de la Secretaría, el dictamen técnico de congruencia correspondiente a permisos y licencias de uso del suelo y edificaciones que por sus características, impacto en el ambiente o en la estructura urbana, se consideran, en los términos de la presente Ley y demás disposiciones relativas, como de importancia estatal o se ubiquen fuera de los límites de los centros de población;\nSerán considerados de importancia estatal aquellos permisos y licencias de uso de suelo y edificaciones que pretendan tramitarse en zonas agrícola, pecuaria, agropecuaria, forestal y ambiental que no sean de competencia federal.\nPárrafo Adicionado\nFracción Reformada\nXI. Otorgar o negar a través de la Secretaría o la Secretaría de Protección al\nAmbiente del Estado, según corresponda, las autorizaciones sobre todo tipo de acciones de urbanización y edificación que se ubiquen fuera de los centros de población, o que afecten las áreas naturales protegidas declaradas así por la Federación, el Estado o los Municipios, o las que se destinen a industrias de alto riesgo, extractivas o de transformación y que puedan tener un impacto negativo en el medio ambiente, sin importar su ubicación, incluidos o no, en el Plan y los Programas de Desarrollo Urbano Estatal, Regional, Municipal o de\nCentros de Población;\nCon la finalidad de velar por el orden público y el interés social, deberán previstas en esta Ley.\nLey de Desarrollo Urbano del Estado de Baja California. Página 9\nPárrafo Adicionado\nFracción Reformada\nXII. Revisar y publicar los Acuerdos de autorización para realizar acciones de urbanización expedidos por los Ayuntamientos, o por el propio Estado, así como ordenar su registro y autorizar la enajenación de los lotes resultantes;\nXIII. Celebrar convenios con los Municipios del Estado, con otras Entidades\nFederativas o con la Federación, para apoyar los objetivos y finalidades propuestos en los diversos Planes y Programas de Desarrollo Urbano;\nXIV. Apoyar y asesorar a los Ayuntamientos en la elaboración de sus Planes y\nProgramas de Desarrollo Urbano;\nXV. Participar con los Gobiernos Municipales, las Entidades Federativas y la\nFederación en la ordenación y regulación de las conurbaciones o Zonas Metropolitanas interestatales, en los términos de la Ley General de Asentamientos Humanos;\nXVI. Reconocer mediante declaratoria, la existencia de un fenómeno de conurbación o Zona Metropolitana, respecto de los centros de población situados en el territorio de dos o más municipios de la entidad;\nXVII. Promover ante el Congreso del Estado, la fijación o modificación de los límites de las zonas conurbadas municipales y de las Zonas Metropolitanas;\nXVIII. Participar en forma conjunta y coordinada con los Ayuntamientos, en la ordenación y regulación de los centros de población ubicados en una zona conurbada intermunicipal;\nXIX. Establecer las medidas necesarias tendientes a desalentar la especulación de predios y fincas contraria al interés social;\nXX. Intervenir en la regularización de la tenencia del suelo para su incorporación al desarrollo urbano, en los términos de la legislación aplicable;\nXXI. Participar, en los términos del Acuerdo de coordinación respectivo, en la operación del Sistema Nacional de Suelo y Reservas Territoriales para el Desarrollo Urbano y la Vivienda que establece la Ley General de Asentamientos Humanos;\nXXII. Participar en la constitución y administración de reservas territoriales en la\nEntidad, en coordinación con los municipios;\nXXIII. Ejercer el derecho de preferencia a favor del Estado, para adquirir predios comprendidos en las declaratorias de reserva, conforme a las disposiciones de la Ley\nGeneral de Asentamientos Humanos y de esta Ley;\nXXIV. Elaborar, aprobar, ejecutar, evaluar y revisar los Programas Regionales y\nSectoriales que se requieran;\nXXV. Ofertar y promover terrenos y construcciones en acciones de interés social, especialmente los destinados a la vivienda popular;\nLey de Desarrollo Urbano del Estado de Baja California. Página 10\nXXVI. Coordinar las políticas y prácticas del Registro Público de la Propiedad y de\nComercio, de la Secretaría y de las Dependencias de Catastro Municipal mediante convenio con los Ayuntamientos respectivos, para hacer efectivas las disposiciones expedidas, a fin de ordenar y regular los centros de población en el Estado, expresadas en los Planes y\nProgramas de Desarrollo Urbano;\nXXVII. Promover obras para que los habitantes de la Entidad cuenten con una vivienda digna, espacios adecuados para el trabajo, áreas de esparcimiento y recreación, el equipamiento indispensable para la vida de la comunidad y los medios de comunicación y transporte que se requieran;\nXXVIII. Promover y constituir asociaciones con particulares o entidades públicas, para convenir y coordinar la realización de acciones de urbanización y vivienda de interés público y de objetivo social;\nXXIX. Convenir con los municipios para que la Secretaría asuma las funciones técnicas que les correspondan en la aplicación de esta Ley;\nXXX. Cumplir con las disposiciones de esta Ley, expidiendo los reglamentos en los aspectos que no estén encomendados expresamente a los Ayuntamientos o a otra entidad pública;\nXXXI. Determinar las infracciones y sanciones, así como adoptar y ejecutar las medidas de seguridad en el ámbito de su competencia, en los términos de la presente Ley y demás disposiciones relativas;\nXXXII. Negar o condicionar permisos de desarrollo urbano en aquellas áreas consideradas naturalmente riesgosas como lechos de arroyos y ríos, así como en aquellas cuyo suelo haya sido contaminado y alterado con substancias peligrosas, desechos radiactivos, tóxicos, inflamables, explosivos y corrosivos. La simple sospecha de la existencia de cualquiera de ellas, condicionará la liberación del permiso, previo estudio que incluya análisis químicos de suelo y mantos acuíferos; y,\nXXXIII. Las demás atribuciones que le otorguen la presente Ley y otras disposiciones legales relativas.\nEl Ejecutivo del Estado ejercerá las atribuciones que le confiere esta ley, en los términos de la Ley Orgánica de la Administración Pública del Estado de Baja California.\nArtículo Reformado\nARTICULO 11.- Son atribuciones del Ayuntamiento:\nI. Formular, aprobar, administrar, ejecutar, evaluar y actualizar el Plan Municipal de\nDesarrollo Urbano, los Programas de Desarrollo Urbano de Centros de Población, los que se hace mención en el Artículo 24, fracción II de la presente Ley;\nII. Previo dictamen técnico de congruencia con el Programa de Ordenamiento\nEcológico del Estado, Plan o los Programas Estatales, Regionales y Sectoriales de\nLey de Desarrollo Urbano del Estado de Baja California. Página 11\nDesarrollo Urbano, aprobar las declaratorias de provisiones, usos, destinos y reservas de áreas y predios, derivadas de los Planes y Programas Municipales de Desarrollo Urbano y enviarlas al Ejecutivo del Estado para su publicación e inscripción;\nFracción Reformada\nIII. Formular, aprobar y administrar la zonificación urbana de los centros de población contenida en los Programas Municipales de Desarrollo Urbano y sus declaratorias;\nIV. Participar, con la concurrencia del Estado y de los demás Municipios involucrados, en la elaboración, ejecución, control, evaluación y revisión de los Programas Regionales de\nDesarrollo Urbano y de los convenios de coordinación correspondientes;\nV. Coadyuvar con la autoridad competente en la realización del ordenamiento ecológico del Estado principalmente en lo referente a los asentamientos humanos;\nVI. Elaborar, aprobar, ejecutar, controlar, evaluar y revisar en forma conjunta con el\nGobierno del Estado y conforme al convenio de coordinación respectivo, los Programas\nParciales que se expidan para la utilización parcial o total de la reserva territorial y de las zonas sujetas a conservación ecológica;\nVII. Solicitar al Ejecutivo del Estado la publicación y registro de los Planes y\nProgramas Municipales de Desarrollo Urbano descritos en la fracción II del Artículo 24 de esta Ley y de las declaratorias de usos, destinos y reservas de áreas y predios correspondientes;\nVIII. Asegurar la congruencia de los Programas a que se refiere la fracción I de éste artículo con el Plan Estatal de Desarrollo Urbano, haciendo las proposiciones que estime pertinentes;\nIX. Proponer la fundación de nuevos centros de población solicitando al Gobernador del Estado se incluyan en el Programa Estatal de Desarrollo Urbano y se promueva ante el\nCongreso del Estado el decreto correspondiente;\nX. Solicitar ante la Legislatura del Estado la fijación o modificación de los límites de los centros de población ubicados en su territorio municipal;\nXI. Participar en la ordenación y regulación de las zonas conurbadas que incluyan centros de población de su territorio, conforme a las disposiciones legales y la declaratoria que al efecto se expida; finalidades de esta Ley en el ámbito de su jurisdicción, mediante la celebración del convenio de coordinación que corresponda;\nXIII. Solicitar a la Secretaría, la asesoría y apoyo técnico que requiera para elaborar su Plan y sus Programas de Desarrollo Urbano, aplicarlos, controlarlos, evaluarlos y revisarlos, conforme a los convenios de coordinación que celebre con el Ejecutivo Estatal; los Gobiernos de otras Entidades Federativas, los convenios que apoyen los objetivos y\nLey de Desarrollo Urbano del Estado de Baja California. Página 12 su territorio municipal, de conformidad con esta Ley y demás ordenamientos aplicables;\nXV. Coordinarse y asociarse con otros municipios de la entidad para el cumplimiento del Plan y los Programas de Desarrollo Urbano;\nXVI. Intervenir en la regularización de la tenencia del suelo para incorporarlo al desarrollo urbano en coordinación con el Gobierno del Estado, en los términos de la legislación aplicable;\nXVII. Participar en la creación y administración de las zonas sujetas a conservación ecológica y de las reservas territoriales para el crecimiento urbano, de conformidad con las disposiciones de esta Ley y con los Programas y Declaratorias que al efecto se expidan y publiquen;\nXVIII. Promover inversiones y acciones que tiendan a conservar, mejorar y regular el crecimiento de los centros de población;\nXIX. Expedir los reglamentos y disposiciones administrativas que fueren necesarias, de conformidad con los fines señalados en los Artículos 27 y 115 de la Constitución Política de los Estados Unidos Mexicanos, las bases normativas que expida el Congreso del Estado y las disposiciones de la presente Ley.\nAsí mismo deberá asegurarse que los reglamentos y disposiciones a los que se refiere el párrafo anterior, se encuentren en apego con los instrumentos de planeación urbana que para los fines citados haya autorizado la autoridad estatal.\nXX. Otorgar o negar las autorizaciones y licencias de construcción, de acciones de urbanización y de uso del suelo en los términos de esta Ley, la Ley de Edificaciones del\nEstado de Baja California, sus Reglamentos, Planes y Programas de Desarrollo Urbano y declaratorias en vigor;\nXXI. Aplicar las limitaciones y modalidades a la propiedad privada que imponga esta\nLey y demás disposiciones relativas;\nXXII. Aplicar las medidas necesarias para desalentar la especulación que respecto de predios y fincas sea contraria al interés social;\nXXIII. Convenir con el Ejecutivo del Estado, que la Secretaría por un período que no podrá exceder a su gestión constitucional, desempeñe las funciones técnicas que le corresponden en la aplicación de esta Ley;\nXXIV. Solicitar a la Secretaría el dictamen técnico de congruencia correspondiente a los permisos y licencias de uso del suelo y edificaciones, que por sus características o impacto en el ambiente o en la estructura urbana, se consideren de importancia estatal o se estén previstos en los diferentes Planes o Programas del Desarrollo Urbano Municipal, declaratorias correspondientes y demás disposiciones relativas.\nLey de Desarrollo Urbano del Estado de Baja California. Página 13 suelo y edificaciones que pretendan tramitarse en zonas agrícola, pecuaria, agropecuaria, forestal y ambiental que no sean de competencia federal.\nPárrafo Adicionado\nFracción Reformada\nXXV. Promover obras para que los habitantes de sus respectivos municipios cuenten con una vivienda digna, espacios adecuados para el trabajo, áreas y zonas de esparcimiento y recreación, el equipamiento indispensable para la vida de la comunidad y los medios de comunicación y transporte que se requieran;\nXXVI. Fomentar la organización, promover la participación y recibir las opiniones de los grupos sociales que integran su comunidad respecto a la formulación, ejecución, evaluación y actualización de los diferentes Planes y Programas Municipales de Desarrollo\nUrbano, en los términos de la Ley de Planeación del Estado;\nXXVII. Promover la participación solidaria de la población en la solución de los problemas de infraestructura y equipamiento urbano, servicios públicos y vivienda popular en los centros de población de su jurisdicción;\nXXVIII. Dar difusión al Plan Municipal de Desarrollo Urbano y a los Programas derivados del mismo;\nXXIX. Coordinar las políticas y prácticas catastrales inmobiliarias con el Plan y\nProgramas Municipales de Desarrollo Urbano;\nXXX. Asociarse con otras entidades públicas o con particulares, para coordinar y concertar la realización de acciones de urbanización de utilidad pública;\nXXXI. Acordar la incorporación o reincorporación de áreas o predios donde se hayan ejecutado acciones de urbanización;\nXXXII. Acordar la recepción de las acciones de urbanización;\nXXXIII. Convenir con el Ejecutivo del Estado, que la Secretaría de Asentamientos\nHumanos y Obras Públicas por un período que no podrá exceder a su gestión constitucional, desempeñe las funciones técnicas que le corresponden en la aplicación de esta Ley;\nXXXIV. Solicitar a la Secretaría de Asentamientos Humanos y Obras Públicas el y edificaciones, que por sus características o impacto en el ambiente o en la estructura urbana, se consideren de importancia estatal o se ubiquen fuera de los perímetros de los\nPlanes o Programas del Desarrollo Urbano Municipal, declaratorias correspondientes y demás disposiciones relativas;\nXXXV. Proveer en el ámbito de su competencia, el cumplimiento de las disposiciones de esta Ley;\nLey de Desarrollo Urbano del Estado de Baja California. Página 14\nXXXVI. Determinar las infracciones y sanciones, así como ejecutar las medidas de seguridad de su competencia, en los términos de la presente Ley y demás disposiciones relativas;\nXXXVII. Tramitar y resolver el recurso administrativo previsto en esta Ley;\nFracción Reformada\nXXXVIII. Solicitar a la Secretaría el dictamen técnico de congruencia, así como a la\nSecretaría de Economía Sustentable y Turismo la manifestación de impacto ambiental, previo a la expedición de autorización de los permisos y licencias de uso del suelo y edificaciones cuando se trate de acciones de urbanización que pretendan llevarse a cabo en zonas agrícola, pecuaria, agropecuaria, forestal y ambiental; y,\nFracción Adicionada, recorriéndose la subsecuente\nXXXIX. Las demás atribuciones que le señale esta Ley, sus normas y disposiciones reglamentarias.\nArtículo Reformado\nARTICULO 12.- La Secretaría es la dependencia de la Administración Pública Estatal, que tiene a su cargo ejecutar la política del Gobierno del Estado en el sector de desarrollo urbano y vivienda. Sus atribuciones serán las siguientes:\nI. Elaborar en los términos que fija esta Ley, el Plan Estatal de Desarrollo Urbano para someterlo al dictamen de la Comisión Coordinadora de Desarrollo Urbano del Estado;\nII. Elaborar en los términos de esta Ley con la participación de los Ayuntamientos, los\nProgramas Regionales de Desarrollo Urbano para someterlos al dictamen de la Comisión\nCoordinadora de Desarrollo Urbano del Estado;\nIII. Ejecutar, controlar, evaluar y revisar el Plan Estatal de Desarrollo Urbano y ejercer éstas mismas acciones con la participación de los Ayuntamientos en los Programas\nRegionales de Desarrollo Urbano;\nIV. Elaborar los Programas Sectoriales de Desarrollo Urbano en las materias de vivienda, reservas territoriales, transporte, infraestructura y los que le ordene el Ejecutivo del\nEstado;\nV. Ejecutar, controlar, evaluar y revisar conjuntamente con los Ayuntamientos respectivos, conforme a las disposiciones de esta Ley y observando los convenios de coordinación que al efecto se celebren, los Programas Parciales que se expidan en relación ecológica;\nVI. Integrar, operar y mantener el Registro Estatal del Sistema de Programas de\nDesarrollo Urbano del Estado, inscritos y publicados en los términos de la presente Ley;\nVII. Extender a los Ayuntamientos los dictámenes técnicos de congruencia correspondientes a permisos y licencias de uso del suelo y edificaciones, que por sus características de ubicación, impacto ambiental o estructura urbana se consideren de\nLey de Desarrollo Urbano del Estado de Baja California. Página 15 importancia estatal, en los términos de la presente Ley y demás Leyes, Reglamentos y disposiciones relativas.\nIntegral Regional, aquellos dictámenes técnicos de congruencia que en su estima sean considerados como trascendentes, así como de los que sea solicitada su remisión por parte de dicho órgano colegiado.\nPárrafo Adicionado\nFracción Reformada\nVIII. Otorgar las autorizaciones sobre todo tipo de acción de urbanización que por su ubicación, condiciones, características e impacto ambiental se consideren de importancia estatal conforme a lo dispuesto en la fracción XI del Artículo 10 de esta Ley, y de las demás\nLeyes, Reglamentos y disposiciones sobre la materia;\nIX. Auxiliar al Gobernador del Estado en la revisión, previa a su publicación, de los acuerdos de autorización para realizar acciones de urbanización;\nX. Apoyar a los Ayuntamientos que lo soliciten, en la elaboración de los distintos\nPlanes y Programas Municipales de Desarrollo Urbano;\nXI. Otorgar a la autoridad competente la información necesaria para la realización del\nPlan de Ordenamiento Ecológico del Estado;\nXII. Intervenir en la ordenación y regularización de las zonas conurbadas y metropolitanas interestatales;\nXIII. Determinar las infracciones y sanciones, adoptar y ejecutar las medidas de seguridad en el ámbito de su competencia en los términos de esta Ley y demás normas legales y reglamentos aplicables; y\nFracción Reformada\nXIV. Extender a los Ayuntamientos los dictámenes técnicos de congruencia previo a la expedición de autorización cuando se trate de acciones de urbanización que se pretendan llevar a cabo en zonas agrícola, pecuaria, agropecuaria, forestal y ambiental;\nFracción Adicionada\nXV. Denunciar ante el Ministerio Público los actos y hechos considerados como posibles delitos en los términos de la legislación aplicable; y,\nFracción Adicionada, recorriéndose la subsecuente\nXVI. Las demás atribuciones que le señale esta ley y otras normas legales y\nEjecutivo del Estado.\nArtículo Reformado\nARTICULO 13.- El titular de la Secretaría ejercerá las facultades de su competencia y podrá delegar en sus subalternos cualesquiera de éstas, salvo aquellas que expresamente\nLey de Desarrollo Urbano del Estado de Baja California. Página 16 demás Leyes relativas.\nArtículo Reformado\nARTICULO 14.- Se crea la Comisión Coordinadora de Desarrollo Urbano del Estado, quien para el mejor desempeño de sus atribuciones, coordinará sus programas de trabajo y acciones con los Ayuntamientos involucrados y con la Secretaría en el ámbito de sus respectivas competencias, con el objeto de lograr una gestión más eficaz como organismo de coordinación gubernamental.\nLa Comisión Coordinadora de Desarrollo Urbano del Estado se integrará por:\nI. El titular de la Secretaría;\nII. Un Subsecretario de la Secretaría, los Directores de los Organismos y Entidades\nParaestatales de su sector; Comisiones Estatales de Servicios Públicos, las Inmobiliarias del\nEstado, Promotora Estatal para el Desarrollo de las de Comunidades Rurales y Populares, Comisión para la Regularización de la Tenencia de la Tierra del Estado, Secretaría de\nProtección al Ambiente y Dirección de Tránsito y Transportes del Estado;\nIII. Los Presidentes Municipales del Municipio correspondiente; cuando conforme a la presente Ley se traten asuntos de Desarrollo Urbano referentes a su circunscripción territorial, éstos ocurrirán a las sesiones de la Comisión personalmente o por conducto del servidor público responsable del desarrollo urbano en su Municipio, así como el Presidente del Consejo de Urbanización del Municipio correspondiente;\nIV. El Delegado de la Secretaría de Desarrollo Social en el Estado; y\nV. Un representante de la Secretaría de Planeación y Finanzas del Estado.\nEl Gobernador del Estado podrá invitar a los representantes de la Administración\nPública Federal para que aporten su consejo en la formulación de las políticas, criterios y lineamientos que fije dicha Comisión. Por cada Consejero propietario se designará un suplente que lo sustituya en sus faltas temporales.\nArtículo Reformado\nARTICULO 15.- En los casos de conurbación intermunicipal se integrará dentro del seno de la Comisión Coordinadora de Desarrollo Urbano del Estado, una subcomisión de esta Ley.\nEn los casos de Zonas Metropolitanas el Ejecutivo del Estado, deberá constituir un\nConsejo de Desarrollo Metropolitano, cuya integración, funciones y atribuciones se determinaran en el decreto de creación que al efecto expida.\nArtículo Reformado\nARTICULO 16.- Cuando se trate de asuntos referentes a una zona de conurbación se convocará a los representantes de los Municipios involucrados en esa zona, según lo dispuesto en el Artículo 95 de esta Ley.\nLey de Desarrollo Urbano del Estado de Baja California. Página 17\nARTICULO 17.- Será Presidente de la Comisión Coordinadora de Desarrollo Urbano, el titular de la Secretaría. Las sesiones se efectuarán por lo menos cuatro veces al año, acuerdos se tomarán por mayoría de votos presentes, correspondiendo al Presidente el voto de calidad en caso de empate. En ausencia del Presidente, asumirá sus funciones quien él designe como suplente.\nArtículo Reformado\nARTICULO 18.- El Secretario Ejecutivo de la Comisión Coordinadora de Desarrollo\nUrbano será designado por el titular de la Secretaría, quien formulará la convocatoria para las sesiones.\nArtículo Reformado\nARTICULO 19.- El titular de la Secretaría será el representante legal de la Comisión\nCoordinadora de Desarrollo Urbano del Estado.\nArtículo Reformado\nARTICULO 20.- Corresponde a la Comisión Coordinadora de Desarrollo Urbano del\nEstado:\nI. Dictaminar sobre los Programas de Desarrollo Urbano Estatal;\nII. Dictaminar sobre la congruencia entre los diversos Programas Municipales de\nDesarrollo Urbano y Programas de Ordenación de Zonas Conurbadas con los Programas\nEstatal, Regionales de Desarrollo Urbano y Sectoriales en materia de transporte, vivienda, infraestructura y reserva territorial, entre otros, y someterlos a la aprobación del Gobernador del Estado quien ordenará su publicación y registro;\nIII. Dictaminar sobre las proposiciones de declaratorias de usos, reservas, destinos y provisiones de las áreas y predios de los Centros de Población, previamente a ser sometidas por los Ayuntamientos, al conocimiento del Ejecutivo Estatal para la publicación de las declaratorias correspondientes;\nIV. En ausencia de Programas de Desarrollo Urbano o de lineamientos específicos aplicables a determinadas áreas y predios, establecer las directrices generales conforme a los cuales serán autorizados los usos del suelo, localización y construcción de edificaciones\nPoblación, así como en las propuestas de anteproyecto de acciones de urbanización;\nV. Dictaminar sobre la constitución de la conurbación y de la declaratoria para su formal reconocimiento e integración en su seno, de la Subcomisión de zona conurbada;\nVI. Dictaminar sobre los Programas de Ordenación de Zonas Conurbadas, y someterlos a la aprobación del Gobernador del Estado;\nVII. Dictaminar sobre las propuestas de las declaratorias de provisiones, usos, a la aprobación del Gobernador del Estado;\nLey de Desarrollo Urbano del Estado de Baja California. Página 18\nVIII. Gestionar y promover ante las Autoridades Estatales y Municipales el cumplimiento, en el ámbito de su competencia, del Programa de Ordenación de la Zona\nConurbada y de las declaratorias correspondientes;\nIX. Elaborar su propio Reglamento interno; y\nX. Ejercer las demás atribuciones que le correspondan conforme a esta Ley y dictaminar sobre otros asuntos que por su trascendencia le encomiende el Ejecutivo del\nEstado.\nARTICULO 21.- Corresponde a la Secretaría de Protección al Ambiente del Estado:\nI. Desarrollar criterios ecológicos en la promoción del desarrollo estatal;\nII. Planeación y regulación ecológica de los asentamientos humanos;\nIII. Requerir y evaluar el estudio de impacto ambiental;\nIV. Hacer y respetar los Planes de Ordenamiento Ecológico;\nV. Notificar sobre la existencia de reservas ecológicas, áreas de desarrollo industrial a proyectos urbanos y áreas de desarrollo urbano a proyectos industriales, conforme a los\nPlanes de Ordenamiento Ecológico Estatal y Federal.\nVI. Las demás que le correspondan en los términos de la Ley de Protección al\nAmbiente para el Estado.\nArtículo Reformado\nARTICULO 22.- Los Planes y Programas de Desarrollo Urbano Estatales o\nMunicipales se formularán y revisarán en consulta permanente con los organismos e instituciones representativas que integran la comunidad, de acuerdo a los mecanismos de participación establecidos en la Ley de Planeación del Estado.\nEn dicha consulta se garantizará como mínimo la participación de:\nI. El titular de la Secretaría;\nII. La Cámara Nacional de Comercio;\nIII. La Cámara Nacional de la Industria de la Transformación;\nIV. La Cámara Nacional de la Industria de la Construcción;\nV.- La Cámara Nacional para el Fomento y Desarrollo de la Industria de la Vivienda;\nVI.- Los Colegios de Arquitectos debidamente registrados en el Departamento de\nProfesiones del Estado de Baja California;\nVII.- Los Colegios de Ingenieros Civiles debidamente registrados en el Departamento de Profesiones del Estado de Baja California;\nVIII.- El Colegio de Notarios del Estado de Baja California; y\nIX.- Los organismos promotores de vivienda y bienes inmuebles del Estado de Baja\nCalifornia.\nLey de Desarrollo Urbano del Estado de Baja California. Página 19\nArtículo Reformado\nARTICULO 22 BIS.- Se crea la Comisión Intersecretarial de Desarrollo Integral\nRegional quien, para el mejor desempeño de sus atribuciones, se encargará de aprobar los edificaciones, licencias de construcción y acciones de urbanización que por su importancia y trascendencia estatal le sean remitidos por la Secretaría.\nARTICULO 22 TER.- La Comisión Intersecretarial de Desarrollo Integral Regional se integrará por:\nI. La Secretaría General de Gobierno;\nII. La Secretaría de Infraestructura, Desarrollo Urbano y Territorial;\nIII. La Secretaría del Campo y Seguridad Alimentaria;\nIV. La Secretaría de Economía Sustentable y Turismo;\nV. La Secretaría para el Manejo, Saneamiento y Protección del Agua; y,\nVI. La Secretaría de Integración y Bienestar Social.\nLos integrantes de la Comisión podrán designar por escrito a su respectivo suplente.\nEl suplente únicamente podrá participar en las ausencias de quien lo haya designado.\nARTICULO 22 QUATER.- Será Presidente de la Comisión Intersecretarial de\nDesarrollo Integral Regional, el titular de la Secretaría General de Gobierno.\nARTICULO 22 QUINQUIES. - Las sesiones se efectuarán de manera presencial o virtual, por lo menos dos veces al año y de forma extraordinaria cuando sea necesario a juicio del Presidente o del Secretario Ejecutivo, quienes estarán facultados para convocar en ambos casos; requerirán la presencia mínima del cincuenta por ciento más uno de sus integrantes y los acuerdos se tomarán por mayoría de votos presentes, correspondiendo al\nPresidente el voto de calidad en caso de empate. En ausencia del presidente, asumirá sus funciones quien él designe como suplente.\nARTICULO 22 SEXIES.- El Secretario Ejecutivo de la Comisión Intersecretarial de\nDesarrollo Integral Regional será el titular de la Secretaría, quien formulará la convocatoria para las sesiones.\nARTICULO 22 SEPTIES.- Corresponde a la Comisión Intersecretarial de Desarrollo\nIntegral Regional:\nLey de Desarrollo Urbano del Estado de Baja California. Página 20\nI. Aprobar el dictamen técnico de congruencia al que se hace alusión en los artículos 10 fracción X, 150, 200 y demás relativos de esta Ley, mismos que por su trascendencia le sean remitidos por parte de la Secretaría;\nII. Solicitar a la Secretaría la remisión de algún dictamen técnico de congruencia colegiado, previo a ser remitido al municipio solicitante;\nIII. Recibir y encausar debidamente las peticiones relacionadas con la promoción del desarrollo urbano regional que le formulen los residentes del área directamente afectados y, quienes tengan un interés jurídico o legítimo;\nIV. Exhortar a las autoridades municipales y estatales para el efecto del cumplimiento de las leyes y disposiciones en materia de desarrollo urbano, así como exhortarlas para que en caso de ser necesario sean aplicadas de manera inmediata las medidas de seguridad a las que refiere la presente ley;\nV. Solicitar la intervención de la autoridad municipal o estatal que corresponda a efecto de que se inicie el procedimiento administrativo de aplicación y ejecución de sanciones.\nVI. Denunciar ante el Ministerio Público los actos y hechos que puedan ser considerados como posibles delitos en materia de desarrollo urbano de acuerdo a lo establecido por el Código Penal para el Estado de Baja California; y,\nVII. Las demás atribuciones que señalen las disposiciones reglamentarias correspondientes.\nTITULO SEGUNDO\nDE LA PLANEACIÓN DEL DESARROLLO URBANO\nCAPITULO PRIMERO\nARTICULO 23.- La planeación del desarrollo urbano en el Estado estará a cargo del\nGobernador a través de la Secretaría, la Comisión Coordinadora de Desarrollo Urbano del\nEstado, los Ayuntamientos en sus respectivas jurisdicciones y la participación social en los términos establecidos en la Ley de Planeación para el Estado, esta Ley y demás disposiciones aplicables.\nArtículo Reformado\nARTICULO 24.- La ordenación y regulación de los asentamientos humanos en el\nEstado se realizará a través de:\nLey de Desarrollo Urbano del Estado de Baja California. Página 21\nI.- Los Planes y Programas a nivel estatal y regional que comprenden:\n1.- El Plan Estatal de Desarrollo Urbano;\n2.- Los Programas que ordenen y regulen Zonas Metropolitanas o conurbadas interestatales en donde participe el Estado con una o más Entidades Federativas, en los términos de la Ley General de Asentamientos Humanos;\n3.- Los Programas Regionales de Desarrollo Urbano;\n4.- Los Programas que ordenen y regulen zonas conurbadas intermunicipales donde participe el Estado con dos o más Municipios del mismo; y,\n5. Los Programas Sectoriales.\n6. La vinculación de la planeación del desarrollo urbano al Programa de\nOrdenamiento Ecológico del Estado.\nNumeral Adicionado\nFracción Reformada\nII. Los Planes o Programas a nivel Municipal que comprenden:\n1. El Plan Municipal de Desarrollo Urbano;\n2. Los Programas de Desarrollo Urbano de Centros de Población;\n3. Los Programas Parciales de Conservación, Mejoramiento y Crecimiento de los\nCentros de Población;\n4. Los Programas Parciales Comunitarios; y,\n5. Los Programas Sectoriales.\nLos Planes y Programas de Desarrollo Urbano a que se refiere este artículo deberán ser congruentes con el Programa de Ordenamiento Ecológico del Estado, los objetivos, políticas y metas establecidas en el Plan Estatal de Desarrollo.\nPárrafo Reformado\nFracción Reformada\nArtículo Reformado\nARTICULO 25.- Los Planes y Programas a que se refiere el artículo anterior integran el conjunto de disposiciones y políticas definidas para alcanzar los objetivos propuestos en el\nArtículo 27 de la Constitución Política de los Estados Unidos Mexicanos, ordenar los asentamientos humanos y establecer adecuadas provisiones, usos, destinos y reservas de tierra a efecto de ejecutar obras públicas y regular la fundación, conservación, mejoramiento y crecimiento de los centros de población en el Estado.\nARTICULO 26.- Los Planes y Programas a que se refiere el Artículo 24 y las declaratorias de provisiones, usos, destinos, y reservas que se expidan para integrar las zonificaciones de los centros de población, se elaborarán considerando las disposiciones de publicarse en el portal institucional de la Secretaría y Municipio según corresponda.\nArtículo Reformado\nLey de Desarrollo Urbano del Estado de Baja California. Página 22\nARTICULO 27.- El Gobernador del Estado solamente ordenará la publicación del Plan o Programa Municipal de Desarrollo Urbano o de alguna declaratoria derivada de aquél, si nivel estatal y federal.\nEl Ejecutivo Estatal ordenará la publicación de los Planes y Programas Municipales en un término de veinte días hábiles computados a partir de la fecha en que se le solicite.\nARTICULO 28.- De cada Plan o Programa de Desarrollo Urbano y las declaratorias que ordene publicar, el Gobernador remitirá copia al Congreso del Estado para su conocimiento y ordenará su inscripción en el Registro Público de la Propiedad y del\nComercio, conforme lo dispone este mismo ordenamiento.\nAsimismo, se mantendrán a consulta pública en las oficinas en donde se lleve su registro, en la Secretaría y en las Dependencias Municipales que designen los\nAyuntamientos, según corresponda a su nivel de aplicación.\nArtículo Reformado\nARTICULO 29.- Los Planes y Programas previstos en el Artículo 24 de esta Ley tendrán la vigencia que se determine en cada caso, o en su defecto, ésta será indefinida.\nPara modificar o cancelar un Plan o Programa de Desarrollo Urbano se estará a lo dispuesto en esta Ley.\nCAPITULO SEGUNDO\nDel Plan Estatal de Desarrollo Urbano\nARTICULO 30.- Los objetivos del Plan Estatal de Desarrollo Urbano estarán dirigidos a promover el desarrollo urbano en los centros de población, conforme a las disposiciones de los artículos de esta Ley, en congruencia con el Programa de Desarrollo Urbano expedido por la Federación conforme a la Ley General de Asentamientos Humanos. Estos son:\nI. Lograr el equilibrio poblacional de la entidad, conforme a la capacidad de cada una de las regiones que la integran, considerando su extensión territorial y recursos y orientando estímulo;\nII. Alentar la permanencia y el crecimiento de la población en las ciudades que presentan condiciones favorables para el desarrollo de los asentamientos humanos;\nIII. Desalentar el crecimiento de las áreas urbanas de la entidad en donde se presenten limitaciones topográficas, físicas y ecológicas que impidan seriamente el desarrollo urbano;\nIV. Estructurar la interrelación entre los centros de población con sus regiones y los servicios que requieran, para obtener el grado óptimo de autosuficiencia regional;\nLey de Desarrollo Urbano del Estado de Baja California. Página 23\nV. Promover el asentamiento de la población dispersa en el medio rural, en centros de población que garanticen un mínimo de condiciones de infraestructura y servicios;\nVI. Salvaguardar los recursos naturales, mantener el equilibrio ecológico y mejorar las condiciones ambientales de los centros de población;\nVII. Salvaguardar el patrimonio histórico-cultural de la entidad; y\nVIII. Estimular la participación solidaria de los distintos grupos que integran la comunidad, en la realización de las acciones que se deriven del Plan Estatal de Desarrollo\nUrbano.\nARTICULO 31.- El Plan Estatal de Desarrollo Urbano deberá contener:\nI. Diagnóstico de la situación del desarrollo nacional y en especial, de la región fronteriza noroeste del país;\nII. Los requerimientos que planteen los aspectos demográficos, sociales, históricosculturales, económicos, políticos y administrativos de la entidad;\nIII. Los problemas de los centros de población de la entidad, en sus causas y consecuencias;\nIV. Las condiciones geofísicas, ecológicas y ambientales de las regiones y municipios de la entidad.\nV. Los elementos de acondicionamiento del territorio, especialmente infraestructura y equipamiento urbano básicos, medios de comunicación y servicios regionales y urbanos;\nVI. Las condiciones en que se presente o tienda a presentarse el fenómeno de conurbación en la entidad;\nVII. El régimen de la tenencia de la tierra y el uso de las áreas y predios para el desarrollo urbano;\nVIII. Las alternativas y métodos compatibles con los recursos disponibles en la entidad para la aplicación de la presente Ley.\nIX. Los convenios y acciones de inversión pública federal, estatal y municipal; y,\nX. Todos los demás aspectos que permitan la realización de las acciones previstas en dicho Plan Estatal.\nARTICULO 32.- El Plan Estatal de Desarrollo Urbano tendrá como elementos informativos complementarios, los estudios, diagnósticos y proyecciones a futuro de los siguientes aspectos:\nI. El sistema de estructuración regional del territorio de la entidad, considerando la urbano;\nII. El volumen, estructura, crecimiento, migración y distribución de la población;\nIII. La distribución territorial de las actividades económicas;\nLey de Desarrollo Urbano del Estado de Baja California. Página 24\nIV. El desarrollo de las comunicaciones y transporte de la entidad;\nV. El sistema jerarquizado de centros de población;\nVI. La identificación, clasificación y conservación de zonas naturales, históricas, artísticas, culturales y aquellos sitios que por su interés social constituyan un patrimonio para la entidad;\nVII. Los problemas de tenencia de la tierra y regularización para su integración al desarrollo urbano;\nVIII. El estudio de viabilidad económica donde se incluyan proyectos de inversión y estrategias financieras; y,\nIX. La descripción de los mecanismos de instrumentación operativa, técnica, jurídica, fiscal y de información.\nARTICULO 33.- Los objetivos del Plan Estatal de Desarrollo Urbano se realizan a través de las siguientes acciones:\nI. La fundación de centros de población;\nII. La conservación, mejoramiento y previsión del crecimiento de los centros de población existentes mediante el ordenamiento ecológico, reordenamiento, renovación y densificación de áreas urbanas; la dotación de servicios y equipamiento urbano; la celebración de convenios entre autoridades y particulares y la expropiación de predios por causa de utilidad pública, cuando las condiciones así lo requieran;\nIII. La detección y declaración del fenómeno de conurbación cuando dos o más centros de población tiendan a formar una continuidad demográfica;\nIV. La aplicación de estímulos para el desarrollo de zonas declaradas prioritarias;\nV. La constitución de provisiones territoriales para la fundación de centros de población y para el establecimiento de obras y servicios de alcance regional e interestatal;\nVI. La adquisición por parte del Estado de áreas y predios dentro y fuera de los centros de población, que satisfagan oportunamente las necesidades de tierra para el crecimiento del área urbana de los centros de población y de éstos últimos;\nVII. La realización de programas de obra pública que satisfagan las necesidades prioritarias y optimicen la relación costo-beneficio;\nVIII. La inversión en programas coordinados con la Federación y los Municipios, con recursos federales, municipales o mixtos para obra pública;\nIX. La concertación de acciones para promover la participación solidaria de los distintos grupos que integran las comunidades en la promoción del desarrollo urbano; y,\nX. En general, todas aquellas acciones que contribuyan a su realización.\nARTICULO 34.- El Plan Estatal de Desarrollo Urbano, representa el compromiso del\nLey de Desarrollo Urbano del Estado de Baja California. Página 25\nEstatal y en especial, a todas las dependencias y entidades coordinadas del sector de asentamientos humanos y obras públicas. Asimismo, el Plan servirá de referencia a las de los convenios de coordinación respectivos.\nARTICULO 35.- El Plan Estatal de Desarrollo Urbano será formulado por la Secretaría a partir de los estudios e investigaciones que realice, de las propuestas que hagan las dependencias y entidades coordinadas de ese sector de la Administración Pública Estatal representadas en la Comisión Coordinadora de Desarrollo Urbano del Estado, de las propuestas que formulen los Ayuntamientos y de la evaluación que se realice del mismo\nPlan, mediante la consulta que organice en los términos de la Ley de Planeación para el\nEstado.\nArtículo Reformado\nARTICULO 36.- Una vez elaborado el Plan Estatal de Desarrollo Urbano, el Titular de la Secretaría lo someterá a la aprobación del Gobernador del Estado, previo análisis y revisión de la Comisión Coordinadora de Desarrollo Urbano. Aprobado el Plan, el\nGobernador ordenará su publicación y registro en los términos de esta Ley.\nArtículo Reformado\nCAPITULO TERCERO\nDe los Programas Regionales de Desarrollo Urbano\nARTICULO 37.- Los Programas Regionales de Desarrollo Urbano son el conjunto de acciones definidas para promover el desarrollo de los centros de población ubicados en el territorio de dos o más municipios, identificado como una región en el Plan Estatal de\nDesarrollo Urbano y conservando el medio natural, para que en condiciones de equilibrio ecológico se propicie una armónica relación entre el medio rural y el urbano.\nEste programa se expide para promover la acción coordinada de varios municipios de la Entidad, en acciones prioritarias y estratégicas relacionadas con su desarrollo urbano.\nARTICULO 38.- Los Programas Regionales se sujetarán a las disposiciones contenidas en el Plan Estatal y especificarán los objetivos, prioridades y políticas referidas a las regiones que se consideren prioritarias o estratégicas.\nARTICULO 39.- El Programa Regional de Desarrollo Urbano deberá contener los siguientes aspectos:\nI. Hacer referencia a su área de aplicación;\nII. Determinar sus objetivos y metas;\nIII. Analizar la situación y proyecciones a futuro de sus aspectos más relevantes;\nLey de Desarrollo Urbano del Estado de Baja California. Página 26\nIV. Proponer alternativas viables para el desarrollo urbano de la región presentando su análisis comparativo; y,\nV. Presentar propuestas para el ordenamiento y regulación de las zonas y de los centros de población comprendidos en su territorio regional, que incluyan:\na). El sistema jerarquizado de centros de población y zonas preferentes de desarrollo;\nb). El esquema de ordenamiento territorial;\nc). El señalamiento de áreas para las provisiones requeridas en la fundación de nuevos centros de población;\nd). La determinación de las áreas para la conservación, mejoramiento y crecimiento de los centros de población;\ne). La determinación de equipamiento regional y de obras de infraestructura básica;\nf). Los estudios de factibilidad, incluyendo proyectos y estrategias de inversión;\ng). La definición de sistemas operativos para su ejecución, control y evaluación;\nh). Las actividades productivas; y,\ni). La protección del ambiente, el equilibrio ecológico y la provisión de áreas verdes urbanas.\nInciso Reformado\nFracción Reformada\nArtículo Reformado\nARTICULO 40.- El esquema de ordenamiento territorial de un Programa Regional de\nDesarrollo Urbano clasificará las áreas y predios en las categorías siguientes:\nI. Reserva ecológica. Que comprende las tierras, aguas y bosques en estado natural que por sus características de valor ambiental, científico o paisajístico deben ser conservadas como patrimonio ecológico;\nII. Rústico. Que comprende las tierras, aguas y bosques en estado natural que por sus características lo hacen susceptible de explotación racional, agropecuaria, piscícola, minera o forestal;\nIII. Urbanizable. Que comprende el suelo cuyas características lo hacen susceptible de ser urbanizado sin detrimento del equilibrio ecológico, para destinarlo a la fundación o crecimiento de los centros de población, por lo que se señalará para establecer las correspondientes provisiones y reservas;\nIV. Urbanizado. Que comprende el suelo ya integrado a los centros de población dentro de su perímetro urbano; y\nV. No aptas para el desarrollo urbano. Que comprende el suelo cuyas características geológicas, hidrológicas, topográficas, ecológicas o ambientales resulten altamente riesgosas para el asentamiento humano.\nLey de Desarrollo Urbano del Estado de Baja California. Página 27\nARTICULO 41.- Son acciones del Programa Regional de Desarrollo Urbano, las que permitan:\nI. La fundación de nuevos centros de población;\nII. La conservación y mejoramiento de los centros de población;\nIII. La previsión y regulación del crecimiento de los centros de población;\nIV. El aprovechamiento de las áreas y predios de los centros de población para promover su desarrollo integral;\nV. La localización y establecimiento en la región de áreas y predios necesarios para el desarrollo urbano;\nVI. La definición y promoción de los siguientes elementos:\na). La red vial interregional;\nb). La estructuración del transporte colectivo de carácter suburbano;\nc). Las instalaciones requeridas para los medios de comunicación terrestre, aérea y marítima, así como el establecimiento de zonas de restricciones;\nd). Los derechos de paso y franjas de protección para la infraestructura básica;\ne). Las zonas naturales de valor ecológico y paisajístico, así como la de protección de los acuíferos;\nf). La traza urbana y edificaciones de valor histórico, cultural y arquitectónico;\ng). Las zonas de extracción de materiales de construcción; y,\nh). Las zonas de restricción y las no aptas para el asentamiento humano.\nVII. El establecimiento de las siguientes políticas:\na). De promoción de los medios de comunicaciones y transportes.\nb). De dotación de servicios para las zonas conurbadas o metropolitanas.\nc). De promoción turística y recreativa;\nd). De protección y mejoramiento del ambiente; y,\ne). De control, consolidación y crecimiento de los centros de población.\nVIII. Todas aquellas que en adición a las anteriores, contribuyan a lograr los objetivos del Programa Regional.\nArtículo Reformado\nARTICULO 42.- El procedimiento para la elaboración del proyecto del Programa\nRegional de Desarrollo Urbano, se sujetará a las disposiciones del Artículo 35 de esta Ley.\nARTICULO 43.- Elaborado el proyecto del Programa Regional de Desarrollo Urbano, Ley de Desarrollo Urbano del Estado de Baja California. Página 28 referencia, a fin de que expresen sus opiniones en el término de treinta días a partir de la fecha en que reciban el documento. Recibidas las observaciones de los Ayuntamientos, la\nSecretaría ajustará el proyecto de Programa a las mismas, en caso de que procedan y los los Órganos Auxiliares que corresponda, en los términos de la Ley de Planeación para el\nEstado.\nPosteriormente la Comisión Coordinadora de Desarrollo Urbano lo someterá a la consideración del Gobernador del Estado, quien una vez que lo haya aprobado, procederá a establecer la coordinación con los Ayuntamientos involucrados.\nArtículo Reformado\nARTICULO 44.- Aprobado el Programa Regional y el convenio de coordinación municipal, se ordenará su publicación y registro en los términos de esta Ley.\nARTICULO 45.- El Programa Regional de Desarrollo Urbano se dará a conocer al público en las oficinas y residencias de la Secretaría, en las oficinas del Registro Público de la Propiedad y de Comercio y en los Ayuntamientos comprendidos en la región de referencia.\nArtículo Reformado\nARTICULO 46.- La Secretaría verificará el cumplimiento por parte de los servidores públicos responsables, de la correcta ejecución de los actos de registro relacionados con el\nPlan Estatal de Desarrollo Urbano y los Programas Regionales que se expidan.\nArtículo Reformado\nARTICULO 47.- En el área de aplicación de un Programa Regional de Desarrollo\nUrbano no podrá realizarse ninguna acción de urbanización que contravenga las disposiciones de dicho programa. Asimismo, no podrán realizarse acciones de urbanización sin la autorización previa de la autoridad competente.\nCAPITULO CUARTO\nDel Plan y los Programas Municipales de Desarrollo Urbano\nARTICULO 48.- El Plan Municipal de Desarrollo Urbano es el documento rector que integra el conjunto de políticas, lineamientos, estrategias, reglas técnicas y disposiciones encaminadas a ordenar y regular los centros de población en el territorio de cada municipio, mediante la determinación de provisiones, usos, destinos y reservas de áreas y predios, para la conservación, mejoramiento y crecimiento de los mismos. El Programa establecerá las directrices, lineamientos y normas conforme a las cuales las diversas personas y grupos que integren la población, participarán en el proceso de urbanización.\nARTICULO 49.- El Plan Municipal de Desarrollo Urbano, comprenderá:\nI. El análisis de su congruencia con el Plan Estatal de Desarrollo Urbano, como también con otros Programas que se hayan expedido a nivel estatal y regional;\nLey de Desarrollo Urbano del Estado de Baja California. Página 29\nII. Los requerimientos que planteen los aspectos demográficos, sociales, culturales, económicos, políticos y administrativos;\nIII. El estudio de las condiciones geofísicas, ecológicas y ambientales de los centros de población y de las medidas para su conservación y mejoramiento;\nIV. El establecimiento de las funciones intermunicipales de servicios en los centros de población;\nV. La información catastral, jurídica y de aprovechamiento del suelo en los centros de población; y,\nVI. Los programas, estrategias y proyectos de inversión y ejecución.\nARTICULO 50.- Del Plan Municipal de Desarrollo Urbano se desprenden los siguientes:\nI. Los Programas de Desarrollo Urbano de los Centros de Población;\nII. Los Programas Parciales de Desarrollo Urbano que se expidan para la conservación, mejoramiento y crecimiento de centros de población; y,\nIII. Los Programas Parciales Comunitarios.\nIV. Los Programas Sectoriales Municipales.\nARTICULO 51.- Para elaborar y aprobar el Plan Municipal de Desarrollo Urbano, se seguirá el procedimiento siguiente:\nI. El Ayuntamiento en sesión de Cabildo ordenará que se elabore el Plan, o bien, acordará proceder a la revisión del Plan vigente y a su modificación en su caso;\nII. El Ayuntamiento en los términos de la Ley de Planeación del Estado de Baja\nCalifornia convocará y coordinará las consultas, a fin de promover la participación de los distintos grupos que integran la comunidad, que serán cuando menos los indicados en las fracciones II a VIII del Artículo 22 de esta Ley;\nIII.- Formulado el proyecto de Plan, será presentado al Ayuntamiento en sesión de\nCabildo donde, en su caso, se acordará someterlo a consulta pública, publicando el anteproyecto en los estrados de la Presidencia Municipal y facilitando copias de su versión abreviada a las personas, instituciones y asociaciones de todos los sectores que lo requieran, mismos que dispondrán de treinta días contados a partir de la fecha en que se publique, para formular por escrito las observaciones, comentarios y proposiciones concretas que consideren oportunas, dirigidos a los órganos auxiliares contemplados en la\nLey de Planeación del Estado de Baja California.\nIV. Con fundamento en el Acuerdo de Cabildo que apruebe el proyecto de Plan, el\nCoordinadora de Desarrollo Urbano, para que se formulen los comentarios y recomendaciones que se consideren oportunos, en relación con la congruencia del proyecto con los Planes y Programas vigentes a nivel estatal y regional, y en general, respecto de las\nLey de Desarrollo Urbano del Estado de Baja California. Página 30\nDesarrollo Urbano para formular sus comentarios, de no hacerlo se entenderá que está de acuerdo con el mismo;\nV. Cumplidas las consultas a que se refieren las dos fracciones anteriores, se procederá a revisar el proyecto para considerar las opiniones recibidas. El Proyecto ya ajustado se someterá a dictamen de las Comisiones del Ayuntamiento relacionadas con la planeación, infraestructura y servicios públicos en los centros de población y su reglamentación.\nVI. Una vez que se dictamine el proyecto del Plan, será presentado en sesión de\nCabildo para su aprobación formal. Una vez aprobado por el Ayuntamiento, el Plan será remitido por el Presidente Municipal al Gobernador del Estado para su publicación y registro.\nLa documentación que se remitirá al Ejecutivo Estatal, contendrá:\na). El Plan Municipal de Desarrollo Urbano;\nb). La versión abreviada del mismo;\nc). La documentación que acredite la celebración de las instancias de consulta popular; y,\nd). Las recomendaciones y comentarios que haya formulado la Comisión\nCoordinadora de Desarrollo Urbano del Estado conforme a la fracción IV de este artículo, o bien, la manifestación de que no lo recibieron, expresada en escrito por el\nPresidente Municipal, acompañando copia del oficio con que se remitió el proyecto de\nPlan a esa Comisión.\nUna vez que el Gobernador del Estado reciba el Plan Municipal de Desarrollo Urbano, procederá a tramitar su publicación y registro conforme las disposiciones de esta Ley.\nCAPITULO QUINTO\nARTICULO 52.- El Programa de Desarrollo Urbano de los Centros de Población es el conjunto de políticas, lineamientos, estrategias, reglas técnicas y disposiciones establecidas en el Plan Municipal, referidas a un centro de población determinado, tendientes a promover un desarrollo armónico de su territorio.\nARTICULO 53.- Son objetivos del Programa de Desarrollo Urbano de los Centros de\nPoblación:\nI. Adecuar la distribución de la población y de las actividades económicas, de acuerdo a las condiciones de su territorio;\nLey de Desarrollo Urbano del Estado de Baja California. Página 31\nII. Alentar la radicación de la población en su medio, mejorando las condiciones de su hábitat;\nIII. Propiciar la integración socioeconómica entre las diferentes partes que componen al centro de población;\nIV. Distribuir equitativamente las cargas y beneficios del desarrollo urbano;\nV. Preservar y mejorar las áreas forestales, ríos, escurrimientos y acuíferos en el centro de población y sus áreas de apoyo;\nVI. Salvaguardar el patrimonio, preservando los edificios y conjuntos arquitectónicos de valor histórico cultural o que identifiquen la fisonomía del lugar;\nVII. Procurar que el centro de población mantenga o desarrolle de manera integral la calidad de la imagen visual;\nVIII. Distribuir adecuadamente las actividades urbanas para el óptimo funcionamiento del centro de población;\nIX. Facilitar la comunicación y los desplazamientos de la población, otorgando preferencia a los sistemas colectivos de transporte;\nFracción Reformada\nX. Incrementar el número y la superficie y mejorar el equipamiento, conservación y mantenimiento de áreas verdes urbanas; y,\nFracción Adicionada, recorriéndose la subsecuente\nXI. Todos aquellos que permitan orientar el desarrollo del centro de población a condiciones óptimas.\nArtículo Reformado\nARTICULO 54.- El Programa de Desarrollo Urbano de los Centros de Población se fundamentará en los estudios técnicos que permitan integrar en él los siguientes aspectos:\nI. Establecer la congruencia con el Plan y los Programas Estatal y Regional de\nDesarrollo Urbano y el Plan Municipal que corresponda;\nII. Determinar el área de aplicación;\nIII. Determinar sus objetivos y metas;\nIV. Tomar en cuenta los factores ecológicos y socioeconómicos del medio físico transformado;\nV. Elaborar alternativas viables para el desarrollo urbano del centro de población, atendiendo a los factores antes referidos;\nVI. Presentar propuestas para el ordenamiento y regulación del centro de población:\na). Esquema de estructuración territorial que establezca los usos, destinos y reservas de áreas y predios; el sistema de vialidad urbana, el equipamiento urbano y la\nLey de Desarrollo Urbano del Estado de Baja California. Página 32 infraestructura básica, información que estará referida a sectores y subsectores sectorización;\nb). Los estudios de factibilidad, incluyendo estrategias y proyectos de inversión; y,\nc). La definición de los sistemas operativos para su ejecución.\nARTICULO 55.- Son acciones del Programa de Desarrollo Urbano de los Centros de\nPoblación las siguientes:\nI. El ordenamiento territorial del centro de población;\nII. El establecimiento de normas y reglamentos para el control del aprovechamiento del suelo; del mejoramiento y crecimiento de los centros de población de la protección y mejoramiento del ambiente y la conservación del patrimonio histórico y cultural;\nIII. La coordinación de los niveles de gobierno federal, estatal y municipal para la ejecución de los programas de inversión;\nIV. La ejecución de los programas de inversión que satisfagan las necesidades prioritarias de la población;\nV. La concertación con los distintos grupos que integran la comunidad para la ejecución de obra pública;\nVI. El desarrollo de la infraestructura básica del centro de población;\nVII. La aplicación de un sistema equitativo de cargas y beneficios derivados del proceso de urbanización; y,\nVIII. En general, todas aquellas acciones que permitan promover los objetivos del\nPrograma.\nEn la zona de aplicación del Programa de Desarrollo Urbano de los Centros de\nPoblación solo podrán realizarse urbanizaciones o edificaciones en las áreas y predios señalados para tal efecto en las declaratorias de usos, destinos y reservas territoriales para el crecimiento o preservación ecológica y se utilizarán conforme a las disposiciones de las mismas.\nCAPITULO SEXTO\nDe los Programas Parciales de Conservación, Mejoramiento y Crecimiento\nARTICULO 56.- Los Programas Parciales de Desarrollo Urbano que regulen las acciones de conservación, mejoramiento y crecimiento de los centros de población emprendidos por los Ayuntamientos, contendrán como mínimo:\nI. La referencia al Programa de Desarrollo Urbano del Centro de Población del cual se derivan, indicando, en su caso, el aprovechamiento del suelo previsto por el mismo;\nII. Las políticas y los objetivos que se persiguen;\nLey de Desarrollo Urbano del Estado de Baja California. Página 33\nIII. La delimitación de las zonas que comprende;\nIV. La descripción del estado actual de la zona o área, de sus aprovechamientos predominantes y de la problemática que presenta;\nV. Los regímenes de tenencia de la tierra existentes en el área o zona a que se refiera;\nVI. La zonificación a que se refiere el Artículo 117 de esta Ley;\nVII. Las normas y criterios técnicos aplicables a la actualización de conservación, crecimiento o mejoramiento de que se trate;\nVIII. Los proyectos de las obras o servicios, señalando las etapas y condiciones para su ejercicio, así como los lineamientos administrativos y financieros para el aprovechamiento de las zonas comprendidas;\nIX. Los mecanismos que se utilizarán para la adquisición o asignación de inmuebles, así como los estímulos que se establezcan para orientar las actividades de las personas y grupos de los sectores social y privado;\nX. Las obligaciones y responsabilidades de las autoridades y de los usuarios, en su caso;\nXI. Los plazos para que los afectados presenten sus inconformidades;\nFracción Reformada\nXII. Las estrategias para incrementar el número y la superficie y mejorar el equipamiento, conservación y mantenimiento de áreas verdes urbanas; y,\nFracción Adicionada, recorriéndose la subsecuente\nXIII. En general, las medidas e instrumentos para la ejecución de los Programas.\nArtículo Reformado\nARTICULO 57.- Cuando además de las acciones que son objeto del Programa\nParcial, se requiera una reglamentación de los usos y destinos de las áreas o predios comprendidos en la zona de aplicación del mismo, se expedirán las declaratorias correspondientes o en forma sucesiva a dicho Programa.\nARTICULO 58.- Los Programas Parciales pueden expedirse en forma simultánea o sucesiva con el Programa de Desarrollo Urbano del Centro de Población, pero en ningún caso, podrán autorizarse estos Programas en contravención del mismo. de urbanización y edificación, que conforme a sus lineamientos sean autorizadas por el\nAyuntamiento respectivo.\nARTICULO 59.- Para elaborar y aprobar los Programas Parciales que se requieran para desarrollar por parte del Municipio, las acciones previstas en el Programa de Desarrollo\nUrbano del Centro de Población, se seguirá el procedimiento siguiente:\nLey de Desarrollo Urbano del Estado de Baja California. Página 34\nI. El Ayuntamiento en sesión de Cabildo aprobará que se elabore el Programa correspondiente, o bien, por recomendación del órgano auxiliar contemplado en la Ley de\nPlaneación del Estado de Baja California, de acuerdo a las acciones que se propongan, acordará proceder a la revisión del Programa vigente;\nII. El Presidente Municipal coordinará la elaboración del Programa Parcial, practicando las consultas y ordenando los estudios que considere necesarios;\nIII. Formulado el proyecto de Programa Parcial, el Presidente Municipal lo someterá a la opinión del órgano auxiliar que corresponda según la Ley de Planeación del Estado de\nBaja California; una vez dictaminado el proyecto del Programa, se presentará en sesión de\nCabildo para su análisis y aprobación, en su caso;\nIV. Cuando el Programa Parcial implique la expedición de declaratorias, se procederá conforme a las disposiciones de este ordenamiento; y,\nV. Aprobado el Programa Parcial por el Ayuntamiento, el Presidente Municipal lo remitirá al Ejecutivo del Estado para su publicación y registro, conforme las disposiciones de los Artículos 26, 27 y 28 de esta Ley.\nARTICULO 60.- Los Programas Parciales que se expidan para la utilización parcial o total de la reserva territorial para el crecimiento del área urbana o zonas sujetas a conservación ecológica, requerirán la aprobación del Ejecutivo del Estado previamente a su trámite de publicación y registro.\nARTICULO 61.- La elaboración, autorización y ejecución de los Programas Parciales de Desarrollo Urbano que impliquen la realización de obras de urbanización y edificación con participación de los particulares, se regularán por las normas del Título Quinto de esta Ley.\nARTICULO 62.- Cuando el Programa Parcial aprobado por el Ayuntamiento incluya obras que se propongan ejecutar mediante el sistema de plusvalía o el sistema de cooperación, con base en el Programa se procederá conforme a las disposiciones del Título\nSéptimo de esta Ley.\nARTICULO 63.- Cuando el Programa Parcial aprobado por el Ayuntamiento, incluya acciones de conservación y mejoramiento que requieran la participación de personas o instituciones particulares, se procederá a notificarles su contenido, así como las obligaciones específicas que de ellos se deriven para que les den cumplimiento. deberán cumplir con las obligaciones derivadas de los mismos; para este efecto, podrán\nARTICULO 64.- En caso de que los propietarios o poseedores no cumplan con las obligaciones a que se refiere el artículo anterior, las autoridades responsables de ejecutar las acciones previstas en los Planes y Programas correspondientes, podrán gestionar ante el social de los predios, edificaciones e instalaciones en los términos de la Ley de la materia.\nLey de Desarrollo Urbano del Estado de Baja California. Página 35\nCAPITULO SEPTIMO\nDe los Programas Parciales Comunitarios\nARTICULO 65.- Los Programas Parciales que sea necesario expedir para establecer las normas de aprovechamiento de los predios en zonas con características homogéneas, denominadas subsectores o colonias catastrales, en cuanto a uso predominante, tamaño de los predios, tipo de construcción, infraestructura urbana e índice socioeconómico de sus habitantes, requerirán el consentimiento expreso de los propietarios o poseedores de los bienes inmuebles residentes en dichas zonas, mediante una consulta directa a los mismos y se les denominará Programas Parciales Comunitarios.\nARTICULO 66.- Antes de proceder a la elaboración de los Programas Parciales mencionados en el artículo anterior, el órgano auxiliar correspondiente en los términos de la\nLey de Planeación del Estado de Baja California, citará a los propietarios de los predios ubicados en la zona para informarles de todo lo relativo a los proyectos, cumpliendo con el procedimiento que se establece en los Artículos 213 y 214 de esta Ley.\nARTICULO 67.- Se considerará que el Programa Parcial cuenta con la aprobación de los propietarios de los bienes inmuebles, cuando el 75% de estos últimos están de acuerdo con el mismo.\nARTICULO 68.- El Programa Parcial aprobado por los propietarios será enviado al\nAyuntamiento para su ratificación y remitido a la Comisión Coordinadora del Desarrollo\nUrbano del Estado para su revisión y dictamen, lo remitirá al Gobernador del Estado para su publicación y registro.\nARTICULO 69.- Las declaratorias correspondientes a usos y destinos de áreas y predios derivados de los Programas Parciales Comunitarios, requieren para su aprobación, expedición y registro la observancia de los mismos procedimientos que fueron utilizados para estos Programas Parciales.\nARTICULO 70.- Los propietarios de bienes inmuebles ubicados en una comunidad con las características enunciadas en el Artículo 65, están facultados para proponer un\nPrograma Parcial Comunitario a las autoridades municipales, a través del órgano auxiliar correspondiente según la Ley de Planeación del Estado de Baja California, que los deberá asesorar en la elaboración de su propuesta de zonificación de los usos permitidos, prohibidos, condicionados y compatibles, pudiendo incluir acciones de conservación y mejoramiento mediante la realización de obras por cooperación.\nARTICULO 71.- Para la aprobación, publicación y registro de los Programas y que se ha hecho referencia en este Capítulo.\nCAPITULO OCTAVO\nLey de Desarrollo Urbano del Estado de Baja California. Página 36\nARTICULO 72.- Los Programas Sectoriales de Desarrollo Urbano se refieren a las acciones específicas, que en materia de vivienda, aprovechamiento integral de los recursos naturales en la vivienda, infraestructura, vialidad y transporte, equipamiento urbano, ordenamiento ecológico, protección ambiental, reservas territoriales, áreas verdes urbanas, imagen urbana, patrimonio artístico y cultural, prevención y atención de emergencias urbanas, entre otros, se deban de realizar a nivel estatal, regional, municipal, centro de población o una parte de éste último.\nArtículo Reformado\nARTICULO 73.- Los programas sectoriales a nivel estatal y regional serán elaborados por la Secretaría, por instrucciones del Gobernador del Estado o por la Dependencia Estatal que designe el Ejecutivo de acuerdo a la materia que corresponda, con la participación de la\nComisión Coordinadora de Desarrollo Urbano del Estado y la opinión del órgano auxiliar correspondiente en los términos de la Ley de Planeación para el Estado. La aprobación, publicación y difusión se hará en los términos que la presente Ley señala para los\nProgramas de Desarrollo Urbano y demás disposiciones aplicables.\nArtículo Reformado\nARTICULO 74.- Los programas sectoriales a nivel municipal o de centros de población serán elaborados y aprobados por los Ayuntamientos respectivos, con la participación y opinión del órgano auxiliar correspondiente en los términos de la Ley de\nPlaneación del Estado de Baja California, y remitidos al Ejecutivo del Estado para su publicación en los términos de esta Ley, previo dictamen técnico de congruencia.\nCAPITULO NOVENO\nDe la Modificación o Cancelación de los Planes y Programas de Desarrollo Urbano\nARTICULO 75.- El Plan Estatal y los Programas Regionales y Sectoriales de\nDesarrollo Urbano deberán ser revisados, modificados o elaborados, según sea el caso, dentro de un plazo no mayor de seis meses a partir del inicio de la gestión constitucional del\nGobernador del Estado.\nARTICULO 76.- Los Planes Municipales y los Programas de Centros de Población, Parciales y Sectoriales de Desarrollo Urbano deberán ser revisados, modificados o elaborados según sea el caso, dentro de un plazo no mayor de seis meses a partir del inicio de la gestión constitucional de los Ayuntamientos.\nARTICULO 77.- Para controlar y verificar los avances obtenidos en el Plan Estatal y los Programas Regionales y Sectoriales de Desarrollo Urbano, la Secretaría evaluará cada año estos programas, presentando un informe a la Comisión Coordinadora de Desarrollo\nUrbano y al Gobernador de la entidad. En el caso de los Planes Municipales y Programas\nSectoriales de Desarrollo Urbano, el Presidente Municipal evaluará cada año estos planes y programas, presentando un informe al Ayuntamiento.\nArtículo Reformado\nLey de Desarrollo Urbano del Estado de Baja California. Página 37\nARTICULO 78.- Si como resultado de las evaluaciones los planes y programas a que se refiere el artículo anterior no están en concordancia con los requerimientos estatales, regionales o municipales, o con las circunstancias del desarrollo de los centros de población, podrán ser modificados o cancelados.\nARTICULO 79.- Los Planes y Programas de Desarrollo Urbano podrán ser modificados o cancelados cuando:\nI. Exista variación substancial de las condiciones que les dieron origen;\nII. Surjan técnicas diferentes que permitan una realización más satisfactoria;\nIII. Las tendencias del proceso de urbanización hayan tomado una orientación que no haya sido prevista; o,\nIV. Sobrevenga una causa grave que impida su ejecución.\nARTICULO 80.- La modificación o cancelación podrá ser solicitada por escrito a la autoridad que aprobó el Plan o Programa correspondiente por:\nI. El Gobernador del Estado;\nII. La Comisión Coordinadora de Desarrollo Urbano del Estado;\nIII. Los Presidentes Municipales respecto del Plan Estatal;\nIV. Las dependencias de la Administración Pública Estatal o Municipal responsables de ejecutar las acciones previstas en esos Planes o Programas;\nV. Los Organismos de participación social y consulta, integrados en los términos del\nArtículo 8 de la presente Ley; y\nVI. Los Colegios de Profesionales, las agrupaciones e instituciones privadas legalmente constituidas, que tengan interés en el desarrollo urbano del Estado.\nARTICULO 81.- En los mismos términos en que se modifican o cancelan los Planes o\nProgramas Estatales, Regionales, Municipales y Sectoriales de Desarrollo Urbano, se pueden modificar o cancelar las declaratorias de usos, reservas, destinos y provisiones que corresponda.\nARTICULO 82.- El procedimiento y términos para el trámite de la resolución de modificación o cancelación de un Plan, Programa o de una Declaratoria, serán los mismos que se observan para su formulación, aprobación, publicación y registro.\nCAPITULO DECIMO\nARTICULO 83.- Los Planes o Programas que sean aprobados, publicados e inscritos en el Registro Público de la Propiedad y del Comercio como lo establece esta Ley, serán obligatorios para los particulares y para las autoridades correspondientes.\nLey de Desarrollo Urbano del Estado de Baja California. Página 38\nARTICULO 84.- A partir de la fecha en que se inscriba el Plan o Programa en el\nRegistro Público de la Propiedad y del Comercio o su modificación, las autoridades competentes sólo podrán expedir licencias, permisos y autorizaciones de acciones de urbanización y edificación, además de usos del suelo, en áreas o predios que resulten afectados, si las solicitudes están de acuerdo con el mismo. Los que se expidan no obstante esta prohibición, serán nulos de pleno derecho.\nARTICULO 85.- Todas las obras y actividades consideradas por los Planes o\nProgramas de Desarrollo Urbano que se realicen en el territorio del Estado, deberán sujetarse a los dispuesto en los mismos. Sin este requisito, no se otorgará autorización o licencia para efectuarlas.\nARTICULO 86.- En el caso de que sea de estricta necesidad demoler total o parcialmente, las edificaciones, ampliaciones o reconstrucciones realizadas sin licencia o autorización o en contravención a lo dispuesto por el Artículo 84 de esta Ley, el costo de los trabajos será a cargo de los propietarios o poseedores, y las autoridades no tendrán obligación de pagar indemnización alguna.\nARTICULO 87.- Las obras que sean a cargo de las autoridades estatales o municipales, se ejecutarán en los términos previstos en esta Ley y demás disposiciones específicas.\nARTICULO 88.- El fenómeno de conurbación se presenta cuando dos o más centros de población formen o tiendan a formar parte de una unidad geográfica, económica y social.\nARTICULO 89.- Las conurbaciones que se presenten en los centros de población localizados dentro de los límites del territorio estatal, serán formalmente reconocidas mediante la Declaratoria que expida al efecto el Gobernador del Estado, o el Acuerdo entre éste y los Ayuntamientos respectivos.\nEn casos de zonas de conurbación en las que participe el Estado y una o más\nEntidades Federativas, se estará a lo dispuesto en la Ley General de Asentamientos\nHumanos.\nARTICULO 90.- La zona de conurbación intermunicipal es el área circular generada por un radio de 30 kilómetros. El centro de dicha área es el punto de intersección de la línea fronteriza entre los municipios, con la que resulte de unir los centros geográficos de los centros de población correspondiente. cuando lo consideren conveniente para la planeación conjunta, una dimensión mayor o menor.\nLos Ayuntamientos y el Ejecutivo del Estado, podrán acordar con los Ejecutivos de caso de que lo consideren conveniente si se presentase una conurbación interestatal.\nLey de Desarrollo Urbano del Estado de Baja California. Página 39\nTITULO TERCERO\nDE LAS CONURBACIONES\nY DE LAS ZONAS METROPOLITANAS\nCapítulo Primero\nARTICULO 91.- Las declaratorias de conurbación y de Zonas Metropolitanas, para que surtan sus efectos, serán publicadas por una sola vez en el Periódico Oficial del\nGobierno del Estado, y en dos diarios de circulación estatal, e inscritos en el Registro\nPúblico de la Propiedad y de Comercio.\nArtículo Reformado\nARTICULO 92.- La planeación y regulación de las zonas conurbadas dentro del territorio del Estado, se efectuará con la participación del Gobierno del Estado y de los\nAyuntamientos respectivos.\nARTICULO 93.- El Ejecutivo del Estado y los ayuntamientos respectivos podrán acordar que se considere la existencia de una zona de conurbación cuando:\nI. Solamente uno de los centros de población crezca sobre la zona señalada en el\nArtículo 90;\nII. Dos o más centros de población se encuentren ubicados fuera de la zona señalada en dicho artículo, pero por sus características geográficas y su tendencia socioeconómica se considere conveniente el estudio y resolución conjunta de su desarrollo urbano; o,\nIII. Se proyecte o funde un centro de población y se prevea su expansión en territorios de municipios vecinos.\nARTICULO 94.- El acuerdo que se celebre en los términos del artículo anterior, tendrá efectos de declaratoria y se publicará como lo establece esta Ley.\nARTICULO 95.- Cuando el Ejecutivo Estatal haya hecho una declaratoria de conurbación, convocará a los Presidentes Municipales correspondientes para constituir dentro de los treinta días siguientes a la publicación de la declaratoria, una Subcomisión\nIntermunicipal de Conurbación de carácter permanente dentro del seno de la Comisión\nCoordinadora de Desarrollo Urbano del Estado, que ordene y regule el desarrollo de dicha zona. La Subcomisión será presidida por el titular de la Secretaría y tendrá facultades para promover la presentación de proposiciones, captar información, realizar investigaciones y oír la opinión de distintos grupos sociales de los centros de población respectivos, a través de los organismos legalmente constituidos que los representen.\nArtículo Reformado\nARTICULO 96.- La Subcomisión expedirá su reglamento interior en un plazo no mayor de treinta días contados a partir de la fecha en que haya sido constituida, en los términos del artículo anterior.\nLey de Desarrollo Urbano del Estado de Baja California. Página 40\nARTICULO 97.- Una vez aprobado por el Gobernador del Estado el Programa que ordene y regule la zona conurbada, se expedirán las declaratorias de provisiones, reservas, usos y destinos de áreas y predios comprendidos en dicho territorio, de acuerdo con lo establecido en esta Ley.\nARTICULO 98.- Cuando se presente una Zona Metropolitana o de conurbación interestatal, se estará a lo dispuesto en el Capítulo Cuarto de la Ley General de\nAsentamientos Humanos.\nArtículo Reformado\nARTICULO 99.- Serán aplicables a los Programas de Ordenación y Regulación de\nZonas Conurbadas Intermunicipales, las mismas disposiciones en cuanto a objetivos, fundamentos, acciones y contenido que se establecen para los Programas Municipales de\nDesarrollo Urbano de Centros de Población.\nTITULO CUARTO\nDE LA REGULACION DE LA PROPIEDAD EN LOS CENTROS DE POBLACION\nCAPITULO PRIMERO\nDe las Acciones de Fundación, Conservación, Mejoramiento y Crecimiento de los\nCentros de Población\nARTICULO 100.- La ordenación de los centros de población se llevará a cabo mediante la planeación y regulación de la fundación, conservación, mejoramiento y crecimiento de los centros de población, tomando en cuenta los Planes de Ordenamiento\nEcológico Federales y Estatales de acuerdo a las acciones previstas en los Planes y\nProgramas a que se refiere esta Ley.\nARTICULO 101.- La fundación o la modificación de los límites de los centros de población que se realicen conforme a esta Ley, requerirán Decreto expedido por la\nLegislatura del Estado, que deberá contener las declaratorias procedentes sobre provisiones de tierras sujetas a preservación ecológica y determinación de usos, reservas territoriales y destinos y será publicado en el Periódico Oficial del Estado.\nARTICULO 102.- Con base en los Programas Municipales de Desarrollo Urbano de\nCentros de Población, se podrán declarar espacios dedicados a la conservación de aquellos predios en zonas urbanas que lo ameriten por su ubicación, extensión, calidad o por la influencia que tengan en el ambiente.\nARTICULO 103.- Se consideran espacios susceptibles de ser dedicados a la conservación:\nI. Los que posean características naturales, como la existencia de bosques, praderas, mantos acuíferos, especies endémicas de flora y fauna en vías de extinción, así como respetar las reservas ecológicas, parques nacionales, monumentos naturales, parques urbanos, áreas verdes y zonas sujetas a conservación ecológica y otros elementos que condicionen el equilibrio ecológico;\nLey de Desarrollo Urbano del Estado de Baja California. Página 41\nII. Los dedicados en forma habitual y adecuada a las actividades agropecuarias;\nIII. Las áreas abiertas, los promontorios, los cerros, las colinas y elevaciones o depresiones orográficas que constituyan elementos naturales del territorio municipal;\nIV. Las áreas cuyo uso pueda afectar el paisaje urbano;\nV. Las zonas cuyo subsuelo se haya visto afectado por fenómenos naturales o por explotaciones de cualquier género que representen peligros permanentes o accidentes para los asentamientos humanos. En estos espacios la urbanización será restringida y sólo se autorizarán aquellas edificaciones y obras que aseguren los servicios de beneficio social de carácter colectivo y de uso común;\nFracción Reformada\nVI. Las áreas verdes urbanas; y,\nFracción Adicionada, recorriéndose la subsecuente\nVII. Lechos de arroyos y ríos, tomando en cuenta el régimen de lluvias de desierto.\nArtículo Reformado\nARTICULO 104.- La conservación de los centros de población es la acción tendiente a mantener:\nI. El equilibrio ecológico;\nII. El buen estado de las obras materiales, de acuerdo a lo previsto en los Planes y\nProgramas de Desarrollo Urbano; y\nIII. El buen estado de edificios, monumentos, plazas públicas, parques y, en general, todo aquello que corresponda a su acervo histórico y cultural, de conformidad con las leyes vigentes; y,\nFracción Reformada\nIV. Evitar la disminución del número y superficie de las áreas verdes urbanas, así como su deterioro.\nFracción Adicionada\nArtículo Reformado\nARTICULO 105.- El mejoramiento de los centros de población es la acción tendiente a reordenar y renovar los centros de población, mediante el adecuado aprovechamiento de medio ambiente y mejorar la calidad de vida de los ciudadanos, a través de obras de uso público.\nARTICULO 106.- El mejoramiento podrá llevarse a cabo mediante convenios entre materia.\nLey de Desarrollo Urbano del Estado de Baja California. Página 42\nARTICULO 107.- Se atenderá al crecimiento de las áreas urbanas mediante la determinación de las zonas necesarias para su expansión, incorporación de porciones de reserva territorial y la adquisición, por parte del Estado y de los Municipios, de predios crecimiento de los centros de población.\nARTICULO 108.- La determinación de los espacios dedicados a la conservación, mejoramiento, provisiones para la creación de nuevos centros de población y la constitución de reservas territoriales, parques urbanos y zonas sujetas a conservación ecológica, se publicará en el Periódico Oficial del Estado y contendrá:\nI. La demarcación;\nII. Las características y condiciones del área;\nIII. Las limitaciones de uso;\nIV. La duración; y,\nV. La justificación.\nUna vez publicada la determinación, se inscribirá en el Registro Público de la\nPropiedad y del Comercio y las áreas y predios comprendidos quedan sujetos a la regulación de este Capítulo.\nARTICULO 109.- Los predios de las zonas incluidas en el artículo anterior, se podrán utilizar en forma compatible con su destino o uso previsto hasta la fecha señalada en que deberán aplicarse a dichos predios los usos y destinos que la autoridad haya determinado.\nCAPITULO SEGUNDO\nDel Ordenamiento Ecológico de los Asentamientos Humanos\nARTICULO 110.- Las políticas y acciones de conservación y mejoramiento del ambiente en los asentamientos humanos de la Entidad se llevarán a cabo a través del sistema de Programas y los instrumentos de ordenación del territorio previstos en la presente Ley.\nARTICULO 111.- Los programas a que se refiere la presente Ley contendrán el ordenamiento ecológico de los asentamientos humanos y tendrá por objeto mantener, asegurar el mejoramiento de la calidad de vida de la población.\nARTICULO 112.- En el ordenamiento ecológico de los asentamientos humanos se la Protección al Ambiente, la Ley de Protección al Ambiente para el Estado, el Plan de materia.\nArtículo Reformado\nLey de Desarrollo Urbano del Estado de Baja California. Página 43\nARTICULO 113.- Se consideran áreas naturales protegidas, en los términos de la Ley\nAmbiente para el Estado.\nArtículo Reformado\nARTICULO 114.- La reglamentación del uso y conservación de los parques urbanos corresponderá a los Ayuntamientos de la Entidad.\nEn la reglamentación a que se refiere el párrafo anterior, se incorporarán disposiciones para el logro de los objetivos previstos en el artículo 106 Ter de la Ley de\nProtección al Ambiente para el Estado de Baja California, así como para implementar el acceso gratuito a internet en las áreas verdes urbanas.\nPárrafo Reformado\nLos espacios públicos destinados a áreas verdes urbanas no podrán ser destinados a otro uso, ni su superficie podrá ser disminuida.\nPárrafo Reformado\nPara efectos de aplicación del presente ordenamiento, se entenderá por espacio público a, los espacios abiertos o predios de los asentamientos humanos destinados al use, disfrute o aprovechamiento colectivo de acceso generalizado y libre tránsito. Son considerados como bienes inmuebles de uso común en dominio del poder público, excluyendo a los destinados a un servicio público y a los bienes propios del estado cuyo use y disfrute está restringido al aparato estatal.\nPárrafo Adicionado\nArtículo Reformado\nARTÍCULO 114 BIS.- La creación, mantenimiento, mejora y crecimiento de los espacios públicos, deberá sujetarse a lo dispuesto en la NOM-001-SEDATU-2021, Espacios\nPúblicos en los Asentamientos Humanos, así como en la demás normatividad aplicable.\nArtículo Reformado\nARTICULO 115.- En el caso de obras públicas o privadas que puedan causar desequilibrios ecológicos, los requerimientos de estudios de impacto ambiental estarán coordinados conforme al Artículo 28 de la Ley General del Equilibrio Ecológico y la\nProtección al Ambiente y a lo establecido en la Ley de Protección al Ambiente para el\nEstado. Así, antes de la otorgación de un permiso, el solicitante deberá cumplir con los requerimientos y disposiciones técnicas que le marquen la Federación, el Estado y los\nMunicipios.\nArtículo Reformado\nARTICULO 116.- Cuando con fundamento en la Legislación Federal en materia dentro del territorio del Estado, el Gobernador gestionará la participación de la\nLey de Desarrollo Urbano del Estado de Baja California. Página 44 desarrollo urbano y ambiente, conforme a los Artículos 7, 38 y 66 de la Ley General del\nEquilibrio Ecológico y la Protección al Ambiente.\nCAPITULO TERCERO\nDe la Zonificación Urbana\nARTICULO 117.- A los municipios corresponderá formular, aprobar y administrar la zonificación de los centros de población ubicados en su territorio. Para ese efecto se entenderá por zonificación:\nI. La determinación de las áreas que integran y delimitan un centro de población, de conformidad con la fracción III del Artículo 6 de esta Ley;\nII. La determinación de los aprovechamientos predominantes en las áreas a que se refiere la fracción anterior; y\nIII. La reglamentación de los usos, destinos y reservas territoriales a través de las declaratorias correspondientes.\nLa determinación a que se refieren las fracciones I y II deberán estar contenidas en los programas que ordenen y regulen los centros de población, conforme las disposiciones de esta Ley.\nLa reglamentación de zonificación y usos del suelo, destinos y reservas territoriales tomará en cuenta los criterios de sectorización de los centros de población, considerando las vialidades primarias y los subsectores o colonias catastrales determinadas según su grado de homogeneidad del desarrollo urbano y socioeconómico.\nDentro de las áreas podrán establecerse polígonos de planeación urbana ajustándose a los Programas de Desarrollo Urbano Municipal, entre los cuales se encontrarán:\na) Polígonos con potencial de desarrollo;\nb) Polígonos con potencial de mejoramiento;\nc) Polígonos de conservación patrimonial; y\nd) Polígonos de integración metropolitana.\nEn el ordenamiento territorial, que comprende la zonificación de las áreas y los usos del suelo, destinos y reservas territoriales en el Estado de Baja California, se\nAbastecimiento denominadas gasolineras, así como de las instalaciones de plantas de almacenamiento, centros de distribución y estaciones de carburación de gas licuado de petróleo sujetándose a las siguientes condiciones:\nI. Los predios para el establecimiento de gasolineras o Estaciones de Servicio, así carreteras, autopistas, libramientos, vías primarias o principales, colectoras, así como en\nLey de Desarrollo Urbano del Estado de Baja California. Página 45\nUrbano Municipal;\nII. Las Estaciones de Servicio con venta directa al público o de autoconsumo, cumplirán con las disposiciones en materia de protección civil, ambiental, de seguridad, y demás legislación aplicable, y se ubicarán a una distancia de, cuando menos, 1,000 metros en forma radial una de otra, dentro de zona urbana, y de 10,000 metros cuando su ubicación sea en carreteras concesionadas, federales, estatales y secundarias;\nIII. Salvo en los casos en los casos a que se refiere el artículo 66 Quater de la Ley de\nEdificaciones del Estado, el predio deberá ubicarse a una distancia mínima de resguardo de\n300 metros radiales de centros de concentración de personas tales como escuelas, hospitales, centros de desarrollo infantil o guarderías; y de 150 metros radiales, respecto de centros comerciales, mercados, cines, teatros, centros de culto religioso, auditorios, condominios, conjuntos habitacionales, privadas residenciales, así como en cualquier otro sitio, en el que exista una concentración de cien o más personas, de manera habitual o transitoria;\nFracción Reformada\nIV. Salvo en los casos en los casos a que se refiere el artículo 66 Quater de la Ley de\nEdificaciones del Estado, el predio debe ubicarse a una distancia mínima de resguardo de\n150 metros radiales respecto de plantas de almacenamiento de gas licuado del petróleo y de aquéllos centros de despacho a sistemas de carburación automotor e industrias de alto riesgo que empleen productos químicos, soldadura, fundición, fuego, entre otros, así como del comercio que emplee gas con sistema estacionario con capacidad de almacenamiento mayor a 500 litros;\nFracción Reformada\nV. Los tanques de almacenamiento deberán ubicarse a una distancia mínima de resguardo de 30 metros con respecto a líneas eléctricas de alta tensión, de los ejes de vías férreas, así como de los ductos que transporten algún derivado del petróleo;\nVI. Las bombas expendedoras de gasolina, gas licuado de petróleo y/o carburante y sus tanques de almacenamiento, deberán quedar a una distancia mínima de 30 metros de un área residencial;\nVII. Los tanques de autoconsumo que se instalen, deberán cumplir con los requisitos y especificaciones emitidos por la Secretaría de Energía y Petróleos Mexicanos;\nVIII. Cuando el predio en el que se pretenda instalar una Estación de Servicio, se ubique entre dos vialidades, las maniobras de abastecimiento serán única y exclusivamente por el frente a la vialidad de mayor jerarquía; y\nIX. No podrán ubicarse Estaciones de Servicio dentro de las áreas consideradas como de Reserva Ecológica.\nPrevio a las obras de edificación, licencia, permiso o autorización, quienes pretendan llevar a cabo los proyectos de estaciones de servicio, deberán obtener dictamen favorable de la autoridad competente en materia de protección civil y ambiental.\nLey de Desarrollo Urbano del Estado de Baja California. Página 46\nLas estaciones de carburación, distribución y plantas de almacenamiento de gas licuado de petróleo, deberán obtener la autorización del Ejecutivo mediante el Dictamen\nTécnico de Congruencia de la Secretaría de Infraestructura y Desarrollo Urbano, en los\nPárrafo Adicionado\nLas acciones de urbanización mencionadas en el artículo 147 quedan sujetas a cumplir con las disposiciones del presente artículo y del Artículo 117 BIS, siendo obligatoria su observancia.\nArtículo Reformado\nARTÍCULO 117 BIS. - Para los usos de suelo, licencias de construcción y de operación, de actividades con manejo de gas licuado de petróleo, se respetará lo siguiente:\nI.- Para plantas de almacenamiento de gas licuado de petróleo, se otorgarán autorizaciones cuando se ubiquen en fraccionamientos industriales previamente autorizados, verificando que se encuentren fuera de fraccionamientos de uso distinto al industrial y de los centros de población que cumplan con la normatividad y con los planes y programas de desarrollo urbano, con las medidas de seguridad establecidas en las normas oficiales mexicanas y protocolos nacionales e internacionales, respetando tanto las distancias mínimas, áreas de amortiguamiento y de alto riesgo, además de la desconcentración necesaria de dichas plantas desplazándolas a zonas óptimas para su ubicación.\nLas autoridades correspondientes que emitan licencias de uso de suelo para plantas de almacenamiento del rubro de gas licuado de petróleo, deberán corroborar que el lugar donde se pretende ubicar la edificación de dichos establecimientos, cumpla con los criterios necesarios para contrarrestar posibles impactos adversos que afecten a zonas urbanas y al medio ambiente, analizando que la superficie seleccionada cuente con carreteras óptimas para el almacenamiento y distribución del hidrocarburo. suelo para plantas de almacenamiento de gas licuado de petróleo son los siguientes: a. Se ubiquen fraccionamientos industriales de nueva creación, previamente autorizados para industria pesada, de alto riesgo con las excepciones previstas en este mismo apartado; b. Que no presenten colindantes que afecten la seguridad de la planta; c. Que se ubiquen en corredores industriales, particularmente carreteras, para el abastecimiento y distribución del energético; d. Que los posibles impactos adversos no afecten a zonas urbanas ni a ecosistemas;\nLey de Desarrollo Urbano del Estado de Baja California. Página 47 e. Que el potencial del uso de suelo sea compatible con las actividades a desarrollar; f. Que se considere la vegetación y fauna existente en el predio, áreas de conservación, y especies endémicas en peligro de extinción, que pudieran verse amenazadas con el proyecto; g. Que no existan zonas urbanas o rurales cercanas, que se ubiquen dentro del área de influencia local o regional del proyecto; h. Que el área del proyecto se encuentre en zona industrial que cuente con la infraestructura de los diferentes servicios requeridos para el proyecto;\nII.- Para las estaciones de carburación y distribución de gas licuado de petróleo, únicamente podrán otorgarse en fraccionamientos de nueva creación, autorizados conforme a la normatividad aplicable de la materia, que cumplan con los planes y programas de desarrollo urbano, respetando tanto las distancias mínimas, áreas de amortiguamiento y de alto riesgo, como la desconcentración de dichas estaciones, en la medida en que se cumpla con la demanda y el abasto que satisfaga las necesidades de la población.\nEn los casos en que en términos de esta ley y sus reglamentos sea procedente el otorgamiento y licencias de uso de suelo, para las estaciones de carburación y distribución, de gas licuado de petróleo, se sujetarán a las siguientes condiciones: a. Solo podrán ubicarse en predios localizados sobre carreteras, autopistas, libramientos, vías primarias o principales. b. Que el predio donde se pretenda construir el establecimiento, considere el acceso consolidado que permita el tránsito seguro de vehículos; c. Que se ubiquen a una distancia de resguardo de 300 metros lineales a partir de los eléctrica de alta tensión, tomando como referencia la base de la misma; del eje de vías férreas; del eje de gasoductos y poliductos para productos derivados del petróleo; d. Que no colinden con usos de suelo en los que se lleven a cabo actividades tanto de riesgo como de alto riesgo, evitando efectos sinérgicos y de acumulación; y siempre que respeten las áreas de amortiguamiento, de alto riesgo y radio de influencia de los proyectos, estudios de riesgo, de actividades que previamente estuvieren instaladas en la zona; asimismo deberán ubicarse a una distancia mínima de 300 metros radiales.\nLey de Desarrollo Urbano del Estado de Baja California. Página 48 e. Que se tomen las medidas necesarias para proteger las instalaciones del establecimiento y de sus colindantes, si el predio se encuentra en zonas susceptibles de deslaves, partes bajas de lomeríos, terrenos con desniveles o terrenos bajos; f. Que los predios ubicados al margen de carretera y/o vías rápidas cuenten con carriles de aceleración y desaceleración; g. Que el terreno del establecimiento tenga las pendientes y los sistemas adecuados para desalojo de aguas pluviales; h. Que las zonas de circulación y estacionamiento tengan como mínimo una terminación superficial consolidada y amplitud suficiente para el fácil y seguro movimiento de vehículos y personas; y i. Que el perímetro del establecimiento esté delimitado en su totalidad por bardas ciegas de mampostería con altura mínima de tres metros sobre el nivel de piso terminado.\nArtículo Adicionado\nARTICULO 118.- Las declaratorias de usos, destinos y reservas deberán derivarse de los Planes y Programas de Desarrollo Urbano a nivel municipal y de centros de población de esta Ley, conforme a las siguientes reglas:\nI. Las declaratorias de provisiones se expedirán en el Decreto previsto para la fundación de centros de población;\nII. Las declaratorias de usos, destinos y reservas se expedirán siguiendo el mismo procedimiento requerido para elaborar, aprobar o revisar el programa de desarrollo urbano de donde se deriven; y\nIII. Las declaratorias de reservas territoriales requerirán la aprobación del Gobernador del Estado previamente a su trámite de publicación y registro.\nPara su vigencia deberán inscribirse y publicarse en los términos de esta misma Ley. contravención de los programas a que se refiere el primer párrafo de este artículo.\nARTICULO 119.- Las declaratorias de usos, destinos y reservas contendrán:\nI. Las razones de interés social que las motivaron;\nII. La referencia del programa de desarrollo urbano del cual se derivan;\nIII. La demarcación;\nIV. Las características y condiciones del área y la aptitud de los terrenos;\nLey de Desarrollo Urbano del Estado de Baja California. Página 49\nV. Las restricciones al aprovechamiento del suelo, según el tipo de declaratoria de que se trate;\nVI. El término de su vigencia; y\nVII. Los demás datos que determine esta Ley y sus reglamentos.\nARTICULO 120.- Las declaratorias de usos establecerán las normas de aprovechamiento de los predios para aquellas zonas de un centro de población que ordenen los programas correspondientes, indicando, conforme a los reglamentos de zonificación:\nI. Los usos permitidos, prohibidos o condicionados;\nII. Las normas aplicables a los usos condicionados;\nIII. La compatibilidad entre los usos permitidos;\nIV. El número e intensidad de construcciones; y\nV. En su caso, las normas para el alineamiento de predios y en general, de diseño urbano.\nARTICULO 121.- Las declaratorias de destinos contendrán la delimitación precisa de las áreas y predios de que se trate, así como la descripción del fin o aprovechamiento público a que éstos prevean dedicarse.\nUna vez publicada e inscrita en el Registro Público de la Propiedad y del Comercio correspondiente una declaratoria de destinos, los propietarios o poseedores de inmuebles que queden comprendidos en la misma, solo utilizarán los predios de manera que no presenten obstáculos al futuro aprovechamiento previsto.\nLas declaratorias de destinos quedarán sin efecto si en un plazo de cinco años a partir de su inscripción, las áreas y predios correspondientes no son utilizados conforme al destino previsto. En este caso, los afectados podrán solicitar a la autoridad que ordenó el registro de la declaratoria, que gire instrucciones para la cancelación de la misma y la tildación de la anotación recaída en la inscripción de la propiedad.\nARTICULO 122.- Las declaratorias de destinos se notificarán personalmente y por escrito a los propietarios, poseedores, sucesores o causahabientes afectados, cuando se conozca su domicilio conforme los registros catastrales de la propiedad inmobiliaria. En caso contrario, se les notificará por edictos que se publicarán por tres veces consecutivas en el\nPeriódico Oficial del Estado, y en los mismos términos en un periódico de circulación local. publicación.\nAsimismo, se procederá a colocar cédulas en los predios o fincas afectados, mismas que expresarán:\nI. Nombre de la persona a quien se notifica;\nII. Motivo por el cual se coloca la cédula, haciendo referencia a los fundamentos y antecedentes; y\nLey de Desarrollo Urbano del Estado de Baja California. Página 50\nIII. El tiempo por el que debe permanecer la cédula en lugar que se fije.\nARTICULO 123.- Las declaratorias de reservas contendrán la delimitación de las áreas de expansión futura del centro de población. de la Propiedad y del Comercio, los predios en ella comprendidos se utilizarán por sus propietarios o poseedores en forma que no presente obstáculo al futuro aprovechamiento determinado por el programa correspondiente.\nEn igualdad de circunstancias, dichas declaratorias comprenderán preferentemente terrenos que no sean de propiedad ejidal o comunal.\nLas declaratorias de reservas se notificarán personalmente y por escrito a los propietarios o poseedores, conforme al procedimiento previsto en el Artículo 122 de esta\nLey.\nARTICULO 124.- Cuando se haga necesaria la utilización parcial o total de las reservas, se expedirá un Programa Parcial que regule las acciones y utilización del área de que se trate y las declaratorias de usos y destinos que sean necesarias.\nEn el caso de áreas ejidales y comunales, se promoverán las expropiaciones correspondientes en los términos de la Ley Agraria.\nARTICULO 125.- La clasificación de los usos y destinos y los criterios de regulación para zonas habitacionales, comerciales, industriales, recreativas, turísticas y ecológicas, se definirán en el Reglamento Estatal de Zonificación que al efecto expida el Ejecutivo del\nEstado.\nARTICULO 126.- Cuando se expida un Programa Regional de Desarrollo Urbano con su zonificación correspondiente, tomando como referencia los criterios definidos en el\nReglamento Estatal de Zonificación, podrán estipularse criterios específicos aplicables a las áreas y predios de su territorio.\nLos Ayuntamientos al definir la zonificación de los centros de población, utilizarán los criterios de clasificación de usos y destinos establecidos en el Reglamento Estatal de zonificación, estando facultados a establecer normas específicas cuando así se requiera. acuerdo a lo previsto en el Artículo 122 de este Capítulo.\nCAPITULO CUARTO\nARTICULO 127.- Conforme lo dispone el Artículo 47 de la Ley General de preferencia para adquirir los predios comprendidos en la declaratoria de reserva, cuando\nLey de Desarrollo Urbano del Estado de Baja California. Página 51 dichos predios sean puestos a la venta o cuando, a través de cualquier acto jurídico, vayan a ser objeto de una transmisión de propiedad. adquirir los predios comprendidos en la declaratoria de reserva, en caso de remate judicial o administrativo, al precio que se fije en remate al mejor postor, mismo que deberá ser ratificado por la Comisión Estatal de Avalúos.\nARTICULO 128.- Para hacer efectivo este derecho de preferencia, los propietarios de los predios comprendidos en la declaratoria de reserva, los notarios, los jueces y las autoridades administrativas deberán notificarlo a la Secretaría y a la Presidencia Municipal correspondiente dando a conocer el monto de la operación, a fin de que éstos, en un plazo no mayor de treinta días naturales contados a partir de recibida la notificación, ejerzan el derecho de preferencia si lo consideran conveniente.\nSi en el plazo señalado en el párrafo anterior, la autoridad no emite contestación a la notificación, manifestando que es su decisión ejercer el derecho de preferencia en la adquisición del predio, se entenderá que se abstiene de ejercitarlo en ese acto.\nArtículo Reformado\nARTICULO 129.- Cuando la Secretaría y la Autoridad Municipal expresen para el mismo acto su decisión de ejercer el derecho a que refiere el Artículo 127 de esta Ley, la venta o adjudicación se hará a favor del Municipio.\nArtículo Reformado\nARTICULO 130.- Cuando el Gobierno del Estado o el Ayuntamiento ejerciten el derecho de preferencia, el precio será el mismo que el de la operación que se pretendía realizar y se liquidará dentro de los quince días siguientes al día en que se opte por el ejercicio de tal derecho.\nPara perfeccionar el acto de adquisición del predio, deberá ser ratificado por Acuerdo del Ejecutivo Estatal o del Cabildo, según corresponda.\nARTICULO 131.- Para el ejercicio del derecho consignado en este Capítulo, en aquellos casos que por la naturaleza del acto traslativo de dominio no se haya determinado el valor del inmueble, éste se fijará atendiendo al avalúo que practique la Comisión Estatal de Avalúos, sea el Estado o Municipio el adquirente.\nARTICULO 132.- El derecho de preferencia a que se refiere este Capítulo, se hayan sido urbanizadas conforme a su Programa Parcial de Desarrollo urbano.\nCAPITULO QUINTO\nARTICULO 133.- Cuando para la ejecución de los Planes y Programas de Desarrollo\nLey de Desarrollo Urbano del Estado de Baja California. Página 52 propiedad, la autoridad competente por causa de utilidad pública proveerá la expropiación de la misma de conformidad con la Ley de Expropiación del Estado.\nARTICULO 134.- Los Planes y Programas de Desarrollo Urbano y Declaratorias que establezcan provisiones, usos, reservas y destinos de áreas, zonas o predios, entrarán en dentro de los veinte días siguientes en el Registro Público de la Propiedad y de Comercio y los registros que correspondan, por razón de la materia. Los Programas de Desarrollo\nUrbano estarán a consulta del público en las oficinas de los Ayuntamientos correspondientes y en las Residencias de la Secretaría.\nSon responsables del incumplimiento de esta disposición las autoridades que expidan las citadas declaratorias y no gestionen su inscripción, así como los encargados de las oficinas del Registro Público de la Propiedad y del Comercio que se abstengan de llevarla a cabo o la realicen con deficiencia; estos incumplimientos se sancionarán conforme al Título\nOctavo de esta Ley.\nArtículo Reformado\nARTICULO 135.- No se podrá inscribir en el Registro Público de la Propiedad y del\nComercio ningún acto, convenio o contrato que no se ajuste a lo dispuesto en los Artículos\n127, 128, 137, 138 y 139 de esta Ley.\nARTICULO 136.- Las autoridades administrativas no expedirán ningún permiso, autorización o licencia que contravenga los establecido en los Programas y Declaratorias.\nLos que se expidan, no obstante esta prohibición serán nulos de pleno derecho.\nARTICULO 137.- Todos los actos, convenios y contratos relativos a la propiedad, posesión o cualquier otro derecho relacionado con la utilización de áreas y predios, deberán contener las cláusulas relativas a la utilización de dichas áreas y predios, conforme a las\nDeclaratorias correspondientes.\nARTICULO 138.- No producirán efecto legal alguno los actos, convenios y contratos relativos a la propiedad o cualquier otro derecho relacionado con la utilización de áreas y predios, que contravengan las correspondientes Declaratorias de provisiones, usos, reservas y destinos inscritos en el Registro Público de la Propiedad y del Comercio, así como los preferencia a que se refieren los Artículos 127 y 128 de este ordenamiento.\nLa nulidad a que se refiere el párrafo anterior, será declarada por las autoridades administrativas en el ámbito de sus respectivas competencias.\nARTICULO 139.- Los Notarios y cualesquiera otro fedatario solo podrán autorizar las escrituras públicas en que se cumpla lo dispuesto en los Artículos 127, 128, 137, y 138 de esta Ley, en las que se inserte el certificado del Registro Público de la Propiedad y del de que hablan dichos preceptos.\nLey de Desarrollo Urbano del Estado de Baja California. Página 53\nARTICULO 140.- En caso de que se expidan permisos, licencias y autorizaciones contraviniendo las leyes, reglamentos o Planes y Programas de Desarrollo Urbano aplicables, o de llevarse a cabo las acciones de edificación, urbanización, cambios de uso de suelo y demás relativas, que contravengan esta Ley, los reglamentos municipales, planes o de los asentamientos humanos, o que afecten las áreas naturales protegidas declaradas así por la Federación, el Estado o los Municipios, o las que se destinen a industrias de alto riesgo, extractivas o de transformación y que puedan tener un impacto negativo en el medio ambiente, sin importar su ubicación, los residentes del área directamente afectados y, quienes tengan un interés jurídico o legítimo, tendrán derecho a exigir la revocación y nulidad de dichos permisos, licencias y autorizaciones referidas, asimismo que se apliquen las medidas de seguridad pertinentes para dar el debido cumplimiento a los citados ordenamientos.\nPárrafo Reformado\nEste derecho se ejercerá ante las autoridades competentes o superiores inmediatos, quienes escucharán previamente a los interesados y, en su caso, a los afectados, mediante la admisión de petición que se formule por escrito, lo que dará inicio al procedimiento correspondiente.\nPárrafo Reformado\nAdmitido el escrito las autoridades competentes concederán un plazo de 10 días hábiles para que las partes interesadas presenten las pruebas pertinentes, concluido este plazo las autoridades que conozcan del procedimiento contarán con 15 días hábiles para practicar las diligencias probatorias que estimen necesarias y una vez concluido esto se abrirá un periodo de tres días hábiles para que las partes interesadas presenten sus alegatos. Terminado este periodo la autoridad deberá resolver dentro de los 10 días hábiles siguientes, notificando la resolución a las partes en un plazo de tres días hábiles.\nPárrafo Adicionado\nLa resolución que emita la autoridad, deberá resolver si es fundada o infundada la petición, y en su caso, deberá declarar la validez, la nulidad o la procedencia de revocación del acto, y sus efectos, y en su caso las sanciones que resulten procedentes de conformidad con el Artículo 242 de esta Ley. La resolución que se emita deberá ser de ejecución inmediata. En este procedimiento serán supletorias la Ley del Procedimiento para los Actos\nEstado de Baja California.\nPárrafo Adicionado\nSiempre procederá la declaración de invalidez y revocación de las autorizaciones, permisos y licencias, que se hubiesen otorgado sin cumplir con las disposiciones de la presente ley, de sus reglamentos y de las diferentes normas aplicables en la materia. Para ejercer estas acciones de defensa al medio ambiente y el sano desarrollo, también estarán legitimados para exigir el respeto a la legalidad, las asociaciones legalmente constituidas\nLey de Desarrollo Urbano del Estado de Baja California. Página 54 sustentable.\nPárrafo Adicionado\nArtículo Reformado\nARTICULO 141.- Las áreas, zonas y predios de un centro de población, cualquiera que sea su régimen jurídico, estarán sujetos a las disposiciones que en materia de ordenación urbana, dicten las autoridades conforme a esta Ley.\nCAPITULO SEXTO\nDe la Tierra para el Desarrollo Urbano y la Vivienda\nARTICULO 142.- Se declara de utilidad pública la adquisición de tierra para la creación de provisiones y reservas territoriales que satisfagan las necesidades de suelo urbano, para la fundación, conservación, mejoramiento y crecimiento de los centros de población, así como para la vivienda, su equipamiento e infraestructura.\nLos Gobiernos Estatal y Municipal elaborarán y ejecutarán los Programas Parciales de Desarrollo Urbano y las acciones que faciliten la adquisición de predios en áreas urbanas para la construcción de vivienda popular y de interés social.\nARTICULO 143.- Los Programas Sectoriales de Vivienda tanto estatales y municipales contendrán entre otros aspectos: los lugares y extensiones de tierra necesarios para la realización de sus Programas, beneficiarios, tipos de acciones y costos medios de financiamiento, así como su ubicación dentro del Plan Estatal o Municipal de Desarrollo\nUrbano.\nARTICULO 144.- Los Ayuntamientos podrán coordinarse entre sí, con el Estado, con el Gobierno Federal o con los particulares para la ejecución de sus Programas de reservas territoriales y construcción de vivienda popular y de interés social.\nARTICULO 145.- Las acciones que en materia de vivienda lleven a cabo los\nGobiernos Estatal y Municipal se dirigirán a los siguientes objetivos:\nI. Ampliar las posibilidades de acceso a la vivienda que permitan beneficiar al mayor número de personas, atendiendo preferentemente a la población urbana y rural de bajos ingresos económicos;\nII. Aumentar el inventario habitacional, así como crear e incrementar las reservas territoriales para la vivienda popular y de interés social;\nIII. Promover la participación activa y corresponsable de los sectores privado y social en las distintas acciones y programas habitacionales;\nIV. Promover los apoyos necesarios para reducir los costos de la vivienda y de sus materiales básicos, así como los Programas de autoconstrucción organizada y los movimientos cooperativistas para la vivienda;\nLey de Desarrollo Urbano del Estado de Baja California. Página 55\nV.- Impulsar acciones y programas en los sectores social y privado que permitan dignidad, esparcimiento y decoro para discapacitados;\nVI.- Todas aquellas acciones tendientes al mejoramiento, conservación e incremento de la vivienda popular y de interés social que se derivan de esta Ley.\nArtículo Reformado\nARTICULO 146.- Los Programas Sectoriales de Vivienda serán formulados por las\nAutoridades Estatales y Municipales en los términos de la presente Ley.\nUna vez aprobado, publicado y registrado el Programa Sectorial de Vivienda en los términos de esta Ley, la autoridad competente lo difundirá en su portal institucional de la\nSecretaría y Municipio según corresponda, asimismo, la citada autoridad lo mantendrá para consulta del público en general.\nPárrafo Reformado\nArtículo Reformado\nTITULO QUINTO\nDE LAS ACCIONES DE URBANIZACION\nCAPITULO PRIMERO\nDisposiciones Generales\nARTICULO 147.- Para los efectos de esta Ley se entiende por Acción de\nUrbanización, la adecuación del suelo rústico o del suelo previamente urbanizado, que lo habilite para alojar actividades de habitación, educación, esparcimiento y producción de bienes y servicios, tales como:\nI. El fraccionamiento, subdivisión, fusión y relotificación de predios o áreas y sus correspondientes obras físicas para dedicarlos a usos urbanos.\nII. La introducción de redes de infraestructura de servicios de agua potable, drenaje pluvial y sanitario, electrificación, alumbrado público, telefonía y otras instalaciones especiales para las actividades productivas.\nIII. La apertura de vialidades y sus elementos complementarios como andadores peatonales, entronques, enlaces y estacionamientos de vehículos.\nIV. La previsión y ubicación de las áreas dedicadas a Equipamiento Urbano;\nFracción Reformada\nV. Los componentes del paisaje urbano o en sus áreas de equipamiento urbano tales como áreas verdes, arboledas, jardines, mobiliario urbano y señalización, implementando conforme a los planes y programas de desarrollo urbano correspondientes, la incorporación de infraestructura verde.\nFracción Reformada\nLey de Desarrollo Urbano del Estado de Baja California. Página 56\nVI. La modificación de la naturaleza o topografía de un predio, para su utilización, para la intensificación o modificación de su uso.\nVII. La construcción y adecuación de la infraestructura, el equipamiento y los servicios urbanos para garantizar la seguridad y accesibilidad requeridas por las personas, en especial para mujeres, niños, niñas, personas adultas mayores y personas con discapacidad.\nArtículo Reformado\nARTICULO 148.- Toda acción de urbanización se sujetará a las disposiciones de esta\nLey y sus Reglamentos, a los Planes y Programas de Desarrollo Urbano y a las declaratorias de usos, destinos y reservas correspondientes, para garantizar su adecuada integración al contexto urbano donde se realice.\nARTICULO 149.- Las personas físicas o morales, propietarias de terrenos, quienes se desempeñen como urbanizadores, sus promotores y sus respectivos peritos, están obligadas a cumplir las disposiciones de esta Ley cuando pretendan realizar o realicen actividades relacionadas con la acción de urbanización, ya sean públicas o privadas, para la expansión o renovación urbana que se ejecuten en terrenos bajo cualquier régimen de propiedad. Asimismo las autoridades competentes, registradores y fedatarios públicos están obligados a respetar y hacer cumplir los ordenamientos de la presente Ley.\nARTICULO 150.- El otorgamiento de permisos y autorizaciones para realizar acciones de urbanización es competencia de los ayuntamientos, salvo las condiciones y excepciones siguientes:\nI. El Ejecutivo del Estado a través de la Secretaría, deberá extender un dictamen técnico de congruencia a solicitud de los ayuntamientos, previo a cualquier expedición de autorización cuando se trate de acciones de urbanización de alcance estatal tales como todo tipo de infraestructura que no haya sido considerada dentro de los Planes y Programas de\nDesarrollo Urbano Estatal, Municipal y de Centros de Población, como son:\n1. Puentes vehiculares y peatonales sobre vialidades primarias intraurbanas mayores de 25 metros de ancho a parámetros o vialidades interurbanas;\n2. Apertura y prolongación de vialidades primarias intraurbanas y vialidades interurbanas a ubicarse fuera de los límites de los centros de población;\n3. Entronques e intersecciones de vialidades nuevas con vialidades existentes primarias intraurbanas o vialidades interurbanas; e,\n4. Instalaciones de redes de servicios de agua potable, drenaje sanitario y pluvial; cárcamos, bombas, acueductos, poliductos y gasoductos, plantas de almacenamiento, centros de distribución y estaciones de carburación de gas licuado de petróleo; energía eléctrica, alumbrado público, telefonía e instalaciones especiales; estaciones y subestaciones eléctricas, nucleoeléctricas, geotérmicas; sistemas de transporte público sobre rieles metálicos interestatales o urbanos; plantas recicladoras de residuos peligrosos y rellenos sanitarios;\nNumeral Reformado\nLey de Desarrollo Urbano del Estado de Baja California. Página 57\nII. El Ejecutivo a través de la Secretaría, otorgará las autorizaciones que\nUrbano debidamente aprobados, publicados e inscritos en el Registro Público de la\nPropiedad y de Comercio;\nIII. Cuando las acciones de urbanización afecten las áreas naturales protegidas declaradas por la Federación, el Estado o los Municipios, y sean destinadas para la industria de alto riesgo o con posibilidad de un impacto negativo en el medio ambiente, para la industria extractiva y de transformación, indistintamente de su ubicación y no considerados en los Planes y Programas de Desarrollo Urbano aplicables y sus declaratorias y que requieran de la elaboración de un estudio de evaluación de impacto ambiental; los ayuntamientos verificarán el cumplimiento de la Ley de Protección al Ambiente para el\nEstado.\nIV. En las acciones de urbanización que se designen para plantas de almacenamiento, centros de distribución y estaciones de carburación de gas licuado de petróleo, los ayuntamientos realizarán las verificaciones e inspecciones pertinentes para el cumplimiento de esta Ley, de las Normas Oficiales Mexicanas correspondientes y los reglamentos municipales respectivos.\nFracción Adicionada\nV.- El Ejecutivo del Estado por conducto de la Secretaría, deberá extender un dictamen técnico de congruencia a solicitud de los ayuntamientos, previo a cualquier expedición de autorización cuando se trate de acciones de urbanización que se pretendan llevar a cabo en zonas agrícola, pecuaria, agropecuaria, forestal y ambiental que no sean de competencia federal.\nFracción Adicionada\nLa Secretaría remitirá para su aprobación a la Comisión Intersecretarial de Desarrollo\nIntegral Regional, aquellos dictámenes técnicos de congruencia que a su criterio sean considerados de importancia estatal.\nPárrafo Adicionado\nArtículo Reformado\nARTÍCULO 150 BIS.- Los ayuntamientos en relación a las instalaciones de almacenamiento, distribución y estaciones de carburación de gas licuado de petróleo, para llevar a cabo acciones de urbanización deberán atender los siguientes lineamientos:\nI. La normatividad federal en materia de ubicación, construcción, remodelación, acondicionamiento, administración y operación de dichas instalaciones.\nII. La normatividad local en materia de acciones de urbanización, debiendo llevarse a cabo en apego a las siguientes disposiciones locales:\nLey de Desarrollo Urbano del Estado de Baja California. Página 58\na) Las Direcciones de Administración Urbana o análogas de los municipios, tendrán a urbanización del rubro del gas licuado de petróleo, sólo cuando la dependencia municipal encargada de la planeación, haya evaluado las propuestas respecto a la ubicación de la infraestructura, capacidad operativa y grado de riesgo de dicho asentamiento, y se haya emitido el dictamen de congruencia en apego a lo dispuesto por el Artículo 150 de esta Ley.\nb) El interesado de la promoción del proyecto estará sujeto a presentar un programa integral en materia de transporte, procesamiento y comercialización de gas licuado de petróleo, que comprenderá lo siguiente:\n1. Estudio de Impacto Urbano.\n2. Programa de Contingencia aprobado por la Dirección de Protección Civil y\nBomberos.\n3. Programa de capacitación al personal, de amortiguamiento y de medidas de seguridad preventiva y correctiva que apliquen conforme a la normatividad vigente.\n4. Programa donde se establezcan los procedimientos generales del mantenimiento de las instalaciones.\nArtículo Adicionado\nCAPITULO SEGUNDO\nDe la Incorporación Municipal\nARTICULO 151.- Las acciones de urbanización se clasifican en:\nI. Acciones de urbanización para la expansión: son las referidas a los elementos técnicos de adecuación del suelo rústico para su incorporación urbana implicando un cambio en las relaciones de propiedad y tenencia del mismo.\nII. Acciones de urbanización para la renovación: son las relativas a los elementos técnicos de adecuación del suelo en zonas comprendidas en las áreas urbanas y las inherentes al mejoramiento y reposición de uno o varios de sus elementos, pudiendo implicar reincorporación urbana.\nARTICULO 152.- Las acciones de urbanización que se pretendan realizar en las áreas urbanas o de reserva territorial, solo podrán autorizarse cuando esté prevista su incorporación o reincorporación municipal.\nARTICULO 153.- La incorporación urbana a que se refiere esta Ley, es el predios intraurbanos no incorporados, para darles las funciones asignadas en su respectivo\nLey de Desarrollo Urbano del Estado de Baja California. Página 59\nPlan y Programa de Desarrollo Urbano, conforme a las declaratorias de usos y destinos correspondientes. se destinen para acciones de fraccionamiento, deberán contar con los derechos de uso de agua correspondiente a la superficie afectada, los cuales deberán ser transferidos gratuitamente a la autoridad o entidad gubernamental competente para garantizar y satisfacer el suministro permanente y continuo del servicio de agua potable.\nLa reincorporación de terrenos se refiere a predios ubicados en zonas ya incorporadas, en espacios determinados para el mejoramiento y que requieran de la ejecución de obras de renovación urbana.\nArtículo Reformado\nARTICULO 154.- El acuerdo de incorporación municipal conlleva la obligación de las autoridades de:\nI. Recibir las obras de urbanización, instalaciones y el equipamiento urbano, una vez que se haya cumplido lo estipulado en la autorización respectiva;\nII. Prestar los servicios públicos municipales tales como recolección de basura, seguridad pública, bomberos, etc.;\nIII. Declarar el área desarrollada como suelo urbanizado.\nARTICULO 155.-Tratándose de zonas ya incorporadas que sean sujetas a obras de renovación urbana donde se requieran áreas para equipamiento mayores a las existentes debido a un incremento en la densidad, el déficit se cubrirá de acuerdo a lo dispuesto en el\nArtículo 176 de esta Ley, al Reglamento respectivo y a las Normas Técnicas aplicables.\nARTICULO 156.- Todas las acciones de urbanización ubicadas fuera de los centros de población, así como aquellas ubicadas fuera de las áreas de reserva territorial y que no puedan ser integradas al área urbana, deben ser autosuficientes en infraestructura, equipamiento urbano y servicios que requieran, así como en mantenimiento y operación de los mismos conforme al Reglamento correspondiente, y su autorización únicamente conlleva la obligación establecida en la fracción III del Artículo 154.\nSECCION UNICA\nDel Fraccionamiento, Fusión, Subdivisión y Relotificación de Terrenos\nARTICULO 157.- Para los efectos de la presente Ley, se entenderá por:\nFRACCIONAMIENTO: a toda acción de urbanización que implique la división física o legal de un inmueble, que requiera del trazo de una o más vialidades públicas o privadas y obras de urbanización;\nLey de Desarrollo Urbano del Estado de Baja California. Página 60\nFUSION: a toda acción de urbanización de uno, dos o mas predios colindantes para formar uno solo y permitir su óptimo aprovechamiento;\nSUBDIVISION: a toda acción de urbanización que implique la partición de un terreno sin que se requiera la construcción de vías de circulación ni obras de infraestructura urbana;\nRELOTIFICACION: a toda acción de urbanización que implique la modificación total o parcial de la lotificación autorizada de un fraccionamiento, sin cambiar el tipo de éste.\nARTICULO 158.- Las autoridades competentes solo autorizarán acciones de urbanización en las zonas previstas en los Planes y Programas de Desarrollo Urbano y de acuerdo a los procedimientos establecidos en el Capítulo Tercero de este Título.\nARTICULO 159.- El Reglamento correspondiente normará la autorización y el desarrollo de las acciones de urbanización a que se refiere el Artículo 147, y deberá establecer como mínimo:\nI. La obligatoriedad de cumplir con los Planes y Programas de Desarrollo Urbano y sus Declaratorias de Usos y Destinos del Suelo;\nII. Los criterios de densidad de población, ocupación y utilización del suelo;\nIII. Las normas técnicas y la clasificación de las acciones de urbanización;\nIV. El contenido de la solicitud de autorización y los criterios para calificarla;\nV. Los procedimientos de inspección y supervisión;\nVI. Las obligaciones de los urbanizadores, promotores y peritos;\nVII. Los mecanismos de control para Publicidad y Ventas;\nVIII. Las medidas de seguridad y sanciones; y\nIX. Los mecanismos de defensa de los particulares.\nARTICULO 160.- Para los efectos de esta Ley, las acciones de urbanización autorizadas como fraccionamientos se identifican por su uso predominante, indistintamente del régimen de propiedad al que se sujeten y de acuerdo con la siguiente clasificación:\nI. Habitacional Unifamiliar: aquellos dedicados a alojar una vivienda por lote exclusivamente;\nII. Habitacional Multifamiliar: aquellos dedicados a alojar vivienda multifamiliar, sea de tipo vertical u horizontal, incluyendo dúplex;\nIII. Habitacional Social Progresiva: aquellos directamente promovidos por el Estado, Municipios o por los organismos públicos descentralizados, dedicados a la urbanización progresiva de terrenos y construcción paulatina de vivienda;\nIV. Comercial: aquellos dedicados a alojar edificaciones para actividades comerciales o de servicios;\nLey de Desarrollo Urbano del Estado de Baja California. Página 61\nV. Campestre: aquellos dedicados a la vivienda unifamiliar, con actividades agropecuarias complementarias como horticultura, apicultura, fruticultura, etc., con fines productivos o de recreo;\nVI. Turísticos: aquellos dedicados a alojar actividades recreativas y que incluyen la construcción de vivienda unifamiliar o multifamiliar, instalaciones para casas rodantes y semifijas, con fines de vivienda secundaria de carácter no permanente;\nVII. Industriales: aquellos dedicados a alojar instalaciones para actividades de manufactura y transformación de productos y bienes de consumo;\nSe entiende como uso predominante a la actividad que se presente en más del 60% de un fraccionamiento, debiendo ser el 40% restante, compatible con dichas actividades, según lo especifique el Reglamento correspondiente.\nARTÍCULO 160 BIS.- Las acciones de urbanización a que se refiere el artículo anterior, deberán incluir en su zonificación áreas destinadas a los usos y en los porcentajes siguientes:\nI.- Áreas verdes urbanas: nueve por ciento de la superficie vendible del proyecto;\nII.- Equipamiento escolar: tres por ciento de la superficie vendible del proyecto; y,\nIII.- Equipamiento urbano: cuatro por ciento de la superficie vendible del proyecto\nLas mencionadas áreas de destino indicadas en las fracciones I y III deberán ser transmitidas de forma gratuita a favor del Municipio que corresponda y en el caso del área prevista en la fracción II su transmisión será a favor del Ejecutivo Estatal.\nQuedan exceptuados de la previsión de un área de equipamiento escolar aquellos fraccionamientos cuyo uso predominante no sea habitacional, debiendo incluirse dos por ciento adicional para las áreas de equipamiento urbano.\nArtículo Adicionado\nARTÍCULO 160 TER.- La superficie de área verde urbana a que se refiere el artículo anterior deberá:\nI.- Estar ubicada en puntos que faciliten su acceso peatonal por parte de los residentes del fraccionamiento;\nII.- Contar con conexión a los servicios de agua potable, drenaje y energía eléctrica; y,\nIII.- Estar equipada en los términos que señale el Reglamento respectivo.\nArtículo Adicionado\nARTÍCULO 160 QUATER.- Los Fraccionamientos a que se refiere el artículo 160 de esta Ley, podrán autorizarse en la modalidad de acceso controlado, para lo cual, deberán contar con lo siguiente:\nI. Barda perimetral completa, cuando las características específicas de los fraccionamientos lo ameriten, con accesos suficientes para el aforo vehicular calculado;\nLey de Desarrollo Urbano del Estado de Baja California. Página 62\nII. Casetas de vigilancia, cámaras de seguridad y dispositivos seguros para efecto de regular el acceso;\nIII. Asociación Civil de Vecinos o Locatarios con Reglamento Interior, aprobado por la asamblea e inscrito en el Registro Público de la Propiedad y de Comercio; y,\nIV. Cumplir con la reglamentación que establezca la Autoridad Municipal correspondiente, de la cual será coadyuvante.\nPara los efectos de este artículo, la solicitud de autorización podrá ser presentada por el urbanizador, o bien, por el comité de vecinos del fraccionamiento respectivo.\nLa autorización a que refiere este artículo será resuelta por la autoridad municipal de conformidad con esta Ley y lo previsto en el reglamento aplicable.\nArtículo Adicionado\nCAPITULO TERCERO\nDe los Procedimientos para Autorizar y Realizar Acciones de Urbanización\nARTICULO 161.- Las acciones de urbanización mencionadas en el Artículo 147, solo se autorizarán cuando se cumplan las siguientes condiciones:\nI. Que el uso del suelo propuesto no sea diferente al previsto en los Programas de\nDesarrollo Urbano aplicables y las declaratorias respectivas;\nII. Que no se afecten las zonas arboladas, de preservación ecológica, paisajística, o que por sus características topográficas, hidrológicas o geológicas, sean riesgosas para la ejecución de acciones de urbanización;\nIII. Que las modificaciones topográficas no alteren las condiciones naturales de escurrimiento y características propias de la naturaleza del suelo de tal manera que afecten negativamente a la zona de influencia;\nIV. Que no se afecten las zonas arqueológicas, monumentales, históricas o cualquier elemento que integre el patrimonio cultural;\nV. Que se respeten las especificaciones de dimensionamiento, equipamiento y obras resultantes;\nVI. Que se respeten las densidades de población y construcción propuestas en los\nProgramas Parciales y de Desarrollo Urbano de los Centros de Población;\nVII. Que se respete el ambiente, el equilibrio y la armonía de la zona y que la de las obras necesarias para dotar de equipamiento y servicio a los predios resultantes.\nLey de Desarrollo Urbano del Estado de Baja California. Página 63\nARTICULO 162.- Para otorgar las autorizaciones de las acciones de urbanización, se evaluarán entre otros, los siguientes aspectos:\nI. La zona en que se ubicará y los usos permisibles;\nII. Las características de la acción de urbanización de acuerdo con su clasificación y tipología;\nIII. Los índices de densidad de población propuestos y los permisibles;\nIV. La integración y organización de la estructura vial y de transporte;\nV. La proporción y aplicación de las inversiones en sus diversas etapas;\nVI. Las proporciones relativas a las áreas destinadas a equipamiento urbano y su ubicación;\nVII. Las especificaciones relativas a las características y dimensiones de los predios resultantes, coeficientes de ocupación y utilización del suelo;\nVIII. Las normas y especificaciones de urbanización;\nIX. Las áreas de destinos cuya propiedad será transferida gratuitamente;\nX. La compatibilidad de los usos propuestos, los usos condicionados y los no compatibles;\nXI. Los impactos económicos y sociales de la acción de urbanización en la zona de influencia;\nXII. Los impactos físicos y ambientales de la acción de urbanización en la zona de influencia, en los términos de la Ley General del Equilibrio Ecológico y la Protección al\nAmbiente y la Ley de Protección al Ambiente para el Estado.\nArtículo Reformado\nARTICULO 163.- Para la autorización de acciones de urbanización para la expansión o renovación urbana, es indispensable que se encuentren previstas dentro del Plan o\nPrograma de Desarrollo Urbano vigente para la zona en cuestión, o en su defecto, se presente para su aprobación el correspondiente Programa Parcial de Desarrollo Urbano. En los casos de acciones de urbanización para renovación, se requerirá de la conformidad expresa de los propietarios y ocupantes de los inmuebles en la zona de influencia con el procedimiento que determine el Reglamento correspondiente.\nARTICULO 164.- No se recibirá para trámite ninguna solicitud de autorización para realizar acciones de urbanización, que no vaya acompañada de los títulos de propiedad posesión jurídica de los terrenos, que podrá ser la de apeo y deslinde judicial. Para que proceda el trámite, la solicitud correspondiente deberá ir acompañada de los nombres y firmas de los urbanizadores, promotores y peritos responsables legalmente autorizados.\nARTICULO 165.- Toda autorización para realizar las acciones de urbanización deberá ser solicitada a la autoridad competente en los términos de esta Ley, por la persona física o\nLey de Desarrollo Urbano del Estado de Baja California. Página 64 desarrollar, o en el caso de fideicomiso, por quien tenga facultades para ello, a quien en lo sucesivo se le denominará \"el urbanizador\".\nARTICULO 166.- Cuando el solicitante sea distinto al urbanizador, se le denominará\n\"promotor inmobiliario\" y además de cumplir con los requisitos estipulados para la aprobación del Programa Parcial de Desarrollo Urbano, deberán acompañar a la solicitud las copias de los contratos celebrados con los propietarios de los terrenos, para el caso de acciones de urbanización para la expansión, o de terrenos y edificios, en el caso de acciones de urbanización para la renovación, de los cuales se derive su interés en el trámite.\nEl promotor inmobiliario deberá asumir expresamente la responsabilidad de la ejecución de las obras de urbanización, en forma solidaria con los propietarios de los terrenos o de fincas y predios, según corresponda, en la solicitud de trámite correspondiente.\nARTICULO 167.- Cuando se desee realizar alguna de las acciones de urbanización a que se refiere el Artículo 147 y éstas se localicen fuera de los Centros de Población o no estén contempladas dentro de los Programas de Desarrollo Urbano de los Centros de\nPoblación, o no existan Programas de Desarrollo Urbano, la Secretaría, aprobará los estudios que demuestren su factibilidad y congruencia con los diferentes Planes y\nProgramas de Desarrollo Urbano, elaborando los solicitantes un anteproyecto que contenga los elementos de un Programa Parcial de Desarrollo Urbano, siguiendo los lineamientos que dictamine la Comisión Coordinadora de acuerdo con la fracción IV del Artículo 21 de ésta\nLey y los demás que sean requeridos por el Reglamento correspondiente, salvo las excepciones que por ubicación, tamaño o densidad en el mismo se consideren y para proceder con su aprobación en los términos de la presente Ley.\nArtículo Reformado\nLa solicitud de aprobación de Programa Parcial de Desarrollo y su propuesta de\nPrograma, deberán ser entregados a la autoridad competente según el municipio en que se pretendan realizar las acciones de urbanización.\nARTICULO 168.- Recibida la solicitud de autorización de Programa Parcial de\nDesarrollo Urbano por la autoridad competente, se dispondrá de un plazo de quince días hábiles para proceder a su revisión y para verificar que se cumplan los requisitos legales.\nCuando la documentación esté incompleta o no se acrediten los requisitos legales, se requerirá al interesado para que subsane las omisiones en un plazo de quince días, quedando suspendido el trámite de solicitud. Una vez que el interesado haya cumplido con los requerimientos de la autoridad, se continuarán los trámites previstos en la presente Ley y en el Reglamento correspondiente.\nEl no hacer las correcciones en el tiempo convenido, causará la cancelación automática del trámite.\nARTICULO 169.- Formulado el proyecto de Programa Parcial de Desarrollo Urbano e integrado su expediente, la autoridad procederá a considerar su aprobación en los términos de esta Ley. El acuerdo de la autoridad puede recurrirse solicitando su revocación.\nLey de Desarrollo Urbano del Estado de Baja California. Página 65\nARTICULO 170.- Una vez aprobado por la autoridad el Programa Parcial de\nDesarrollo Urbano, se remitirá al Ejecutivo del Estado a través de la Secretaría, para tramitar la publicación de su versión abreviada y su registro conforme lo previsto en esta Ley.\nArtículo Reformado\nARTICULO 171.- Aprobado por la Autoridad el Programa Parcial de Desarrollo\nUrbano, se procederá a integrar el proyecto ejecutivo de la acción de urbanización por los peritos debidamente inscritos en la Dirección de Profesiones del Estado y registrados por su especialidad en el Municipio correspondiente.\nARTICULO 172.- El proyecto ejecutivo de la acción de urbanización se integrará con la información requerida para el caso en el Artículo 164 de esta Ley y en el Reglamento correspondiente, debiendo contener como mínimo:\nI.- Solicitud expedida por la autoridad que corresponda debidamente llenada y firmada por los urbanizadores, promotores y peritos;\nII. Planos propios del Proyecto respetando las condiciones del Artículo 161 de esta\nLey;\nIII. Planos de redes y servicios propuestos y existentes;\nIV. Las especificaciones generales de la acción de urbanización;\nV. Documentación complementaria que incluya constancia de propiedad, libertad de gravámenes, memorias descriptivas y de cálculo de la acción de urbanización y otras.\nVI. Fianza de garantía\nArtículo Reformado\nARTICULO 173.- La autoridad procederá a la revisión del proyecto auxiliándose para ello de los organismos encargados de la dotación y operación de servicios. En caso de existir alguna observación o corrección en el mismo, se procederá a dar aviso al solicitante para que haga las modificaciones requeridas.\nARTICULO 174.- Las autorizaciones para realizar acciones de urbanización que otorguen las autoridades competentes, se harán mediante Acuerdo de autorización debidamente publicado en el Periódico Oficial e inscrito en el Registro Público de la\nPropiedad y del Comercio; en dicho acuerdo se consignarán las obligaciones a que deben sujetarse el urbanizador y el promotor inmobiliario, las especificaciones de las obras de urbanización, las áreas destinadas a equipamiento y cuya propiedad deberá ser transferida gratuitamente a la autoridad correspondiente una vez concluida la acción de urbanización, las etapas en las que se efectuará, su ejecución, plazos para su terminación y otras.\nSe considera como título de propiedad de las áreas destinadas para equipamiento, al antes expuestos. Una vez transferida la propiedad de dichas áreas, se regirán como bienes inmuebles del dominio público para todos los efectos legales.\nLey de Desarrollo Urbano del Estado de Baja California. Página 66\nLos gastos y derechos que causen la autorización, publicación y registro del acuerdo de autorización, serán a cargo del urbanizador o del Promotor Inmobiliario.\nCAPITULO CUARTO\nARTICULO 175.- El urbanizador esta obligado a costear por su cuenta todas las obras de urbanización definidas conforme al Programa Parcial de Desarrollo Urbano y al proyecto ejecutivo aprobado. Además, debe contribuir a la construcción de centros escolares conforme a las disposiciones de la Ley de Ingresos del Estado y transferir gratuitamente el derecho de propiedad de ésta área y en general de las áreas destinadas para equipamiento a las autoridades correspondientes, de acuerdo a lo especificado en el Reglamento respectivo.\nARTICULO 176.- Cuando en la zona de influencia se requieran obras de infraestructura o equipamiento que rebasen las necesidades de la acción de urbanización por desarrollar, el urbanizador estará obligado a realizarlas en su totalidad o a destinar el área requerida para su ubicación, asumiendo éste el derecho de obtener la restitución del monto adicional al costo de la obra de urbanización por él requerida. Dicha restitución podrá ser bonificada con cargo a los residentes de la zona de influencia beneficiada, o mediante la reducción de los derechos que la autorización cause.\nARTICULO 177.- Para la transmisión de la propiedad, posesión, usufructo o aprovechamiento de lotes resultantes de las acciones de urbanización realizadas, el urbanizador deberá cumplir previamente con los siguientes requisitos:\nI. Que se cuente con las actas o constancias aprobatorias de terminación de las obras de urbanización expedidas por los organismos competentes, así como la constancia de terminación de la acción de urbanización expedida por la Secretaría;\nII. Que se hayan cumplido los requisitos de incorporación o reincorporación urbana y en el caso de fraccionamientos por objetivo social progresivos, que la autoridad competente haya aprobado las obras mínimas conforme lo establece el Reglamento correspondiente; y,\nIII. Que se haya cumplido con el requisito de transferir gratuitamente la propiedad de las áreas destinadas para equipamiento a las autoridades competentes.\nArtículo Reformado\nARTICULO 178.-Cuando las obras de urbanización estén en proceso de construcción, el urbanizador podrá enajenar al público los lotes resultantes, constituyendo una garantía por con los siguientes requisitos:\nI. Que se cuente con la publicación hecha por el Ejecutivo del Estado del Acuerdo de autorización de la acción de urbanización;\nLey de Desarrollo Urbano del Estado de Baja California. Página 67\nII. Que se hayan pagado o garantizado las obligaciones que establezcan a su cargo las leyes hacendarias; y,\nIII. Que los textos de cualquier tipo de publicidad comercial para venta que promueva el urbanizador, estén autorizados por la autoridad competente donde se lleve a cabo la acción de urbanización.\nCAPITULO QUINTO\nDe la Ejecución de las Acciones de Urbanización\nARTICULO 179.- En ningún caso se podrán iniciar las acciones de urbanización antes de que se hayan tramitado los permisos o las autorizaciones correspondientes.\nARTICULO 180.- La ejecución de las acciones de urbanización autorizadas conforme al proyecto definitivo, se hará bajo la responsabilidad de los peritos debidamente registrados que se requieran, según el caso. Todas las acciones de urbanización se ajustarán a las especificaciones y normas de calidad mínima que se establezcan en los Reglamentos y\nNormas Técnicas correspondientes.\nARTICULO 181.- Tanto el Ayuntamiento como la Secretaría, según corresponda, tendrán en todo tiempo la facultad de supervisar mediante inspección técnica la ejecución de las obras, para verificar el debido cumplimiento de las normas de calidad y las especificaciones del proyecto autorizado.\nArtículo Reformado\nARTICULO 182.- Los urbanizadores, promotores inmobiliarios y sus peritos, observarán las indicaciones que hagan los inspectores técnicos de la autoridad competente, mismas que deberán de apegarse al Programa Parcial de Urbanización y al proyecto definitivo.\nARTICULO 183.- Para cualquier modificación del proyecto definitivo de las acciones de urbanización, sea propuesta por el urbanizador o por la propia autoridad, ésta dispondrá se elabore un dictamen específico para fundamentarlo. Expedido el dictamen y la resolución que dicte, se hará del conocimiento del urbanizador para su debido cumplimiento. En caso de inconformidad del urbanizador, podrá interponer los recursos que establece el presente ordenamiento y demás disposiciones legales.\nARTICULO 184.- Cuando el urbanizador al realizar las acciones de urbanización para ejecutar el programa parcial incurra en violaciones graves o sustanciales, se aplicarán las aplicables.\nARTICULO 185.- La Secretaría cuando practique una supervisión, comunicará sus observaciones al Ayuntamiento correspondiente, a fin de enterarlo de posibles anomalías en el proceso de ejecución. Esta Secretaría, conforme el convenio que celebre el Ayuntamiento con el Ejecutivo del Estado, podrá asumir las funciones y facultades que a los\nAyuntamientos le otorga esta Ley, cuando éstos no dispongan de los recursos humanos y\nLey de Desarrollo Urbano del Estado de Baja California. Página 68 técnicos necesarios. Asimismo, a solicitud expresa de la autoridad municipal, dicha que se refiere el artículo anterior.\nArtículo Reformado\nARTICULO 186.- Se declara de utilidad pública la expropiación de las áreas y predios necesarios para conectar una acción de urbanización en proyecto y otras zonas previamente urbanizadas del centro de población, siempre y cuando las obras de conexión sean congruentes con los Planes o Programas de Desarrollo Urbano aplicables.\nCuando para conectar una acción de urbanización en proyecto con otras zonas urbanizadas, sea necesario abrir accesos o conducir servicios públicos a través de predios de terceros que no formen parte del terreno por urbanizar, se requerirá el consentimiento de éstos. En caso de no otorgarse el permiso, la autoridad gestionará ante el Ejecutivo del\nEstado la expropiación por causa de utilidad pública de las superficies que se requieran, quedando obligado el urbanizador a realizar las obras a su costo en su totalidad y a pagar el importe que corresponda por indemnización.\nLas obras ejecutadas por este medio y los terrenos afectados pasarán a ser del dominio municipal y éste tendrá derecho a considerar su costo en futuras incorporaciones de los predios aledaños.\nARTICULO 187.- Cuando en un predio por urbanizar existan obras o instalaciones de servicios públicos, se deberán señalar en el proyecto definitivo las especificaciones y restricciones para que el urbanizador evite la interferencia de sus propias obras o instalaciones con las ya existentes. En el caso de que se cause daño o deterioro a esas obras o instalaciones existentes durante la ejecución de las acciones de urbanización, el urbanizador deberá reponerlas a satisfacción de la autoridad. A este efecto, dada la naturaleza del daño y la urgencia de repararlo, la autoridad fijará el plazo para que tales reparaciones queden ejecutadas y la sanción económica aplicable.\nSi transcurrido el plazo a que se refiere el párrafo anterior, el urbanizador no hubiese concluido las reparaciones, la autoridad está facultada para proceder a la ejecución de las respectiva, la relación de las erogaciones realizadas para ese fin, para los efectos de su cobro y liquidación correspondiente, en los términos de las leyes hacendarias.\nCAPITULO SEXTO\nARTICULO 188.- En tanto no se concluyan las acciones de urbanización y éstas sean recibidas por el Municipio, quedan bajo la responsabilidad del urbanizador para cumplir las obligaciones que se establecen en esta Ley y otros ordenamientos aplicables.\nLey de Desarrollo Urbano del Estado de Baja California. Página 69 de esta Ley no podrán ser recibidas por el Municipio, siempre serán responsabilidad del urbanizador, o bien, del comité de vecinos del fraccionamiento respectivo.\nPárrafo Adicionado\nArtículo Reformado\nARTICULO 189.- Terminadas las acciones de urbanización, la persona interesada solicitará a las dependencias que operarán las redes de servicios y sistemas, para que en un plazo que no exceda de 60 días naturales, realicen el levantamiento de actas de certificación aprobatorias de dichos trabajos, así como a la Secretaría una constancia de cumplimiento de acciones de urbanización.\nLa persona interesada podrá insistir ante la misma dependencia para que se resuelva sobre la autorización de su proyecto definitivo de urbanización, en un plazo perentorio de 30 días naturales; agotado el plazo adicional, se aplicará la afirmativa ficta, por lo que bastará que la persona solicitante exhiba los documentos que acrediten el paso el tiempo.\nUna vez que la acción de urbanización esté concluida y reunidos todos los requisitos y constancias aprobatorias que marca la presente Ley y su Reglamento, se procederá a la entrega de las obras a las autoridades y su correspondiente incorporación o reincorporación urbana.\nEn caso de que la autoridad competente omita realizar el cumplimiento de acciones de urbanización, una vez que la persona interesada haya ejercido el derecho de ejercer la afirmativa ficta, esta podrá recurrir a interponer recurso correspondiente ante el Tribunal\nEstatal de Justicia Administrativa de Baja California.\nCumplidas las acciones de urbanización en todos sus rubros, la o el perito, la persona propietaria o su representante según corresponda, estarán obligados a iniciar el proceso de entrega ante las dependencias correspondientes en un término no mayor a 60 días naturales. Por el incumplimiento de esta obligación se aplicarán las sanciones administrativas a que se refiere el Capítulo II del Título Octavo de esta Ley. urbanización terminadas, registrando oficialmente el inicio y conclusión de las mismas, incluida la entrega-recepción del fraccionamiento, ya sea en su totalidad o en partes, según el acuerdo de fraccionamiento en un término no mayor a 60 días naturales de haberse concluido dichas acciones.\nArtículo Reformado\nARTICULO 190.- Para que la autoridad pueda recibir la acción de urbanización terminada, se requiere:\nLey de Desarrollo Urbano del Estado de Baja California. Página 70\nI. Que se hayan ejecutado las obras y cumplido con los requisitos establecidos en el\nPrograma Parcial de Desarrollo Urbano y el Acuerdo de autorización respectivo;\nII. Que se hayan recabado todas las constancias y acuerdos marcados en la presente\nLey y su reglamento, para la terminación de las obras y acciones de urbanización; y,\nIII. Que se hayan realizado los pagos que determinan las leyes hacendarias municipales y estatales.\nEn caso que transcurran los plazos de terminación de las acciones de urbanización sin que estas hayan sido concluidas por parte del urbanizador, y previa solicitud de los vecinos o requerimiento del Ayuntamiento, éste último esta facultado para proceder a la ejecución de las obras y en su momento informar a la Secretaría de Planeación y Finanzas del Estado o a la Tesorería Municipal respectiva, la relación de las erogaciones realizadas para ese fin, para los efectos de su cobro y liquidación correspondiente, en los términos de las leyes hacendarias; o en todo caso podrá hacer valida la fianza de garantía a que se refiere el artículo 172 de esta Ley, para que en su caso se ejecuten las obras pendientes.\nArtículo Reformado\nARTICULO 191.- En los casos de acciones de urbanización para la expansión urbana recibidos por el Ayuntamiento, se procederá a acordar en sesión de cabildo su incorporación al centro de población, dejando de pertenecer el predio a la reserva urbana, y para los casos de acciones de urbanización para la renovación urbana recibidos por el Ayuntamiento, se procederá a acordar en sesión del cabildo su reincorporación al centro de población.\nDicha incorporación o reincorporación se formalizará mediante Acuerdo del cabildo correspondiente, en donde se recibirá gratuitamente por parte del urbanizador la propiedad correspondiente a las áreas de vialidad, los espacios para las instalaciones públicas que se requieran y las necesarias para equipamiento, reservando para el Estado las áreas destinadas para educación.\nARTICULO 192.- El Ayuntamiento al expedir el Acuerdo de incorporación o reincorporación de la zona urbanizada, asumirá los compromisos mencionados en el Artículo\n154 de esta Ley y establecerá o ratificará la nomenclatura del desarrollo urbano considerado, notificando lo anterior a la Administración de Correos, a la Comisión Federal de\nTITULO SEXTO\nDE LAS OBRAS DE EDIFICACION\nCAPITULO UNICO\nDe las Disposiciones Generales\nARTICULO 193.- Las acciones de urbanización de adecuación física y espacial relativas a la edificación comprenden:\nLey de Desarrollo Urbano del Estado de Baja California. Página 71\nI. Las propias de la arquitectura e ingeniería civil que transforman el espacio de una área, un predio o lote de suelo urbanizado para hacer posibles las actividades humanas, de declaratorias correspondientes;\nII. Las relativas a la ampliación, reestructuración o mejoramiento de los edificios o espacios acondicionados existentes;\nIII. Las inherentes a la preservación, restauración y conservación de las mismos, en especial las relativos al patrimonio histórico cultural; y,\nIV. Las referidas al acotamiento, aseguramiento, demolición, saneamiento y mantenimiento de predios y fincas, que garanticen tanto la seguridad y la salud pública, como su armónica integración a su contexto urbano.\nARTICULO 194.- Las obras de edificación se clasifican en:\nI. Obras de edificación nueva: las relativas a los elementos técnicos de construcción para dar a los lotes de suelo urbanizado, un aprovechamiento específico conforme a las declaratorias de usos y destinos;\nII. Obras para la remodelación o ampliación de la edificación: las relativas a los elementos técnicos de construcción existentes, para modificarlas y permitir un aprovechamiento específico similar o diferente al anterior;\nIII. Obras para la conservación de la edificación: las relativas a los elementos técnicos de construcción existentes, para su preservación o reestructuración; y\nIV. Obras para la seguridad y sanidad de lotes y edificios: las relativas a los elementos técnicos de construcción en predios y fincas existentes, necesarias a realizar cuando el estado de los mismos no pueda garantizar la seguridad y salud pública.\nARTICULO 195.- Toda obra de edificación deberá ejecutarse y utilizarse en concordancia con los Planes y Programas de Desarrollo Urbano, acatando las disposiciones legales aplicables y se regirán por la Ley de Edificaciones del Estado de Baja California y los\nReglamentos municipales vigentes.\nARTICULO 196.- Dentro del área de los centros de población solamente se podrá edificar en terrenos o lotes de suelo urbanizado. simultáneas que se ubiquen en suelo no urbanizado dentro de los Centros de Población, se deberá respetar el requisito especificado en el Artículo 201 de esta Ley.\nARTICULO 197.- Los edificios y espacios acondicionados resultantes de estas acciones, para entrar en operación requerirán de su respectiva autorización de ocupación.\nARTICULO 198.- La ocupación a que se hace mención en la presente Ley, se refiere edificación, una vez que las autoridades en la materia hayan realizado la inspección que\nLey de Desarrollo Urbano del Estado de Baja California. Página 72 menoscabo de la salud e integridad de quienes lo vayan a aprovechar.\nEn las edificaciones nuevas o en ampliaciones y reparaciones, las autoridades verificarán que las obras se hayan realizado conforme a los permisos otorgados.\nARTICULO 199.- Ninguna obra de edificación podrá realizarse sin la licencia respectiva expedida por el ayuntamiento correspondiente, con excepción de aquellos casos especiales que no requieran de licencia de construcción o responsable director de obra especificados en la Ley de Edificaciones.\nDicha licencia se otorgará de conformidad con lo dispuesto en este Capítulo, la Ley de Edificaciones del Estado de Baja California, sus Reglamentos y demás disposiciones aplicables.\nARTICULO 200.- El Ejecutivo del Estado tiene el deber de proporcionar los medios y criterios de prevención para que los habitantes de la Entidad puedan desplazarse, garantizando la seguridad de trayecto de los mismos, en el ámbito de su competencia.\nPárrafo Reformado\nLos Ayuntamientos deberán solicitar a la Secretaría, dictamen de congruencia, así como a la Secretaría de Economía Sustentable y Turismo la manifestación de impacto ambiental, previo a la expedición de la licencia de construcción en los casos previstos en el\nArtículo 60, fracciones I a VI y 61 de la Ley de Edificaciones del Estado.\nPárrafo Adicionado\nPárrafo Reformado\nArtículo Reformado\nARTICULO 201.- Los Ayuntamientos solo podrán autorizar obras de edificación en terrenos no urbanizados dentro del Centro de Población, cuando se lleven a cabo simultáneamente con la acción de urbanización respectiva.\nPara los casos de obras de edificación en terrenos fuera de los centros de población, los Ayuntamientos deberán exigir primeramente la autorización de acción de urbanización correspondiente expedida por la Secretaría.\nPara ambos casos será obligatorio el respetar los requisitos de trámite y contenido especificados en esta Ley, la Ley de Edificaciones del Estado y sus Reglamentos respectivos.\nArtículo Reformado\nARTICULO 202.- Todas aquellas personas que realicen obras de edificación deberán solicitar ante la autoridad competente, dictamen de uso del suelo o de zonificación según corresponda al predio donde se desarrollarán las obras, con excepción de aquellas que no de Edificaciones del Estado de Baja California.\nObtenida la constancia a que se refiere el párrafo anterior, los propietarios o\nLey de Desarrollo Urbano del Estado de Baja California. Página 73 aplicables.\nARTICULO 203.- Los proyectos arquitectónicos deberán ser revisados por la autoridad competente, para verificar que reúnan los requisitos mínimos de seguridad general en las instalaciones hidráulicas, sanitarias, eléctricas, especiales y estructurales, de conformidad con las Leyes y disposiciones reglamentarias correspondientes y de acuerdo a la tipología de edificación propuesta.\nARTICULO 204.- Una vez revisados los proyectos, la autoridad competente extenderá al particular, los permisos respecto a las instalaciones sanitarias, eléctricas, de gas, combustibles y explosivos, de conformidad con las Leyes y Reglamentos respectivos.\nARTICULO 205.- Una vez recabadas las autorizaciones y permisos a que se refieren los artículos anteriores, deberán ser presentados junto con el proyecto arquitectónico ante la autoridad municipal, para tramitar la licencia de construcción de conformidad con el\nReglamento respectivo.\nARTICULO 206.- Los proyectos de edificación que por sus características de densidad, coeficientes de usos y ocupación discrepen de la zona donde se proyecten, serán rechazados hasta que su reforma los haga armonizar con el contexto urbano que lo circunde.\nARTICULO 207.- Todas las edificaciones, reconstrucciones o demoliciones, deberán quedar bajo la responsabilidad de un profesionista con cédula profesional legalmente expedida, y que esté inscrito en el registro de peritos responsables que al efecto llevará el\nAyuntamiento correspondiente.\nTITULO SEPTIMO\nDE LAS MODALIDADES DE LAS ACCIONES DE URBANIZACION\nCAPITULO PRIMERO\nDe las Disposiciones Generales\nARTICULO 208.- Las obras de edificación, acciones de urbanización o acciones de urbanización y edificación simultáneas, se proyectarán y se realizarán de acuerdo con los centros de población, mediante las modalidades siguientes, que preven las formas de participación ciudadana y de los distintos sectores de la población:\nI. Acciones de urbanización privadas;\nII. Acciones de urbanización pública;\nIII. Acciones de urbanización por cooperación;\nIV. Acciones de urbanización por plusvalía;\nV. Acciones de urbanización y reparcelación por asociación de interés público;\nLey de Desarrollo Urbano del Estado de Baja California. Página 74\nVI. Acciones de urbanización por concertación; y\nVII. Acciones de urbanización por objetivo social.\nCAPITULO SEGUNDO\nDe las Acciones de Urbanización Privadas\nARTICULO 209.- Las acciones de urbanización o edificación privadas se refieren a las que se realizan para usos determinados por parte de cualquier propietario o promotor asociado con el mismo, en predios de propiedad particular que cumplan con los requisitos estipulados en esta Ley y demás disposiciones aplicables. Bajo esta modalidad se regirán las acciones de urbanización y edificación promovidas y ejecutadas por los organismos públicos descentralizados.\nCAPITULO TERCERO\nDe las Acciones de Urbanización Pública\nARTICULO 210.- Las acciones de urbanización y edificación pública para destinos se refieren a las que se realizan por parte de la Administración Pública Federal, Estatal o por los Ayuntamientos, para satisfacer las necesidades de los centros de población.\nARTICULO 211.- Las dependencias federales, estatales y municipales que proyecten y ejecuten acciones de urbanización y edificación, deberán respetar y aplicar con toda diligencia las disposiciones derivadas de los Planes y Programas de Desarrollo Urbano, destacando la importancia de sus acciones en el ordenamiento y regulación de los centros de población.\nARTICULO 212.- Cuando en un centro de población sea urgente la realización de obras públicas y no se cuente con el Programa de Desarrollo Urbano correspondiente, el\nAyuntamiento las autorizará previo dictamen de la Comisión Coordinadora de Desarrollo\nUrbano del Estado, disponiendo se realicen los estudios indispensables para garantizar su ejecución conforme a las disposiciones de este ordenamiento y las normas de los reglamentos de zonificación y uso del suelo.\nCAPÍTULO TERCERO BIS\nCONTROL DE LA CONTAMINACIÓN LUMÍNICA\nARTÍCULO 212 BIS.- Para los efectos de esta ley se entiende por contaminación lumínica, la emisión de flujo luminoso en la atmosfera de fuentes artificiales nocturnas, en intensidades, direcciones, rangos espectrales y/o horarios innecesarios para la realización de las actividades previstas en la zona en que se instala la fuente.\nArtículo Reformado\nLey de Desarrollo Urbano del Estado de Baja California. Página 75\nARTÍCULO 212 BIS 1.- En materia de prevención y control de la contaminación lumínica, los municipios tendrán las siguientes facultades:\nArtículo Reformado\nI.- Elaborar, aprobar y publicar programas referentes a los sistemas de iluminación\nII.- Aprobar y emitir lineamientos que establezcan el tipo de luminarias a utilizarse en los sistemas de iluminación de exteriores públicos y privados, permanentes o temporales, así como la zonificación para el uso de los mismos;\nIII.- Aprobar y emitir lineamientos que establezcan el tipo de fuente luminosas para usos publicitarios públicos y privados, permanentes o temporales, así como la zonificación para el uso de las mismas;\nIV.- Promover y fomentar en la ciudadanía el uso correcto y eficiente de iluminación y prevención de la contaminación lumínica;\nV.- Integrar y mantener actualizado el inventario de luminarias y coordinarse con el gobierno estatal para la integración del inventario en el Estado;\nVI.- Promover convenios de colaboración con organismos de instituciones de investigación local, nacional e internacional, interesados en la preservación de la calidad de la atmosfera; y\nVII.- Vigilar el cumplimiento de los requisitos y normas de edificación adecuadas para evitar la contaminación lumínica y para preservar la calidad astronómica del municipio.\nCAPITULO CUARTO\nDe las Acciones de Urbanización por Cooperación\nARTICULO 213.- Las acciones de urbanización por cooperación se refieren a las que se realizan en vías y espacios públicos, que benefician directamente a los propietarios de los predios adyacentes a las mismas, y sean promovidas y ejecutadas por los Consejos de\nUrbanización Municipal, con su participación.\nARTICULO 214.- Los proyectos y la ejecución de las obras cumplirán con los su ejecución, deberán cumplir con todos los procedimientos señalados en la Ley de\nUrbanización del Estado, referentes a los proyectos, presupuesto, financiamiento, derramas y contratación, así como a las juntas de los propietarios en donde se apruebe la ejecución de las obras. parcial de los Ayuntamientos.\nLey de Desarrollo Urbano del Estado de Baja California. Página 76\nCAPITULO QUINTO\nARTICULO 215.- Las acciones de urbanización y edificación por plusvalía, son que son declaradas de utilidad pública, con un beneficio general para el centro de población y que requieren, en cada caso, de las contribuciones de mejoras establecidas en la Ley de\nUrbanización del Estado.\nArtículo Reformado\nARTICULO 216.- Las acciones de urbanización o edificación por plusvalía se ejecutarán de acuerdo a los Planes y Programas de Desarrollo Urbano y demás disposiciones aplicables, y serán realizadas a través de la autoridad competente en los términos estipulados en la Ley de Urbanización del Estado, que señala las normas para la individualización de las contribuciones de mejoras para el sistema de plusvalía, así como las bases para su pago y recaudación.\nLas acciones de urbanización o edificación previstas en los Programas Parciales de\nDesarrollo Urbano de los centros de población que incluyan acciones de conservación, mejoramiento o crecimiento, podrán ser realizadas por este sistema de plusvalía, demostrando que son de utilidad pública y de beneficio social y general.\nArtículo Reformado\nCAPITULO SEXTO\nDe las Acciones de Urbanización y Reparcelación por Asociación de Interés Público\nARTICULO 217.- Las acciones de urbanización y reparcelación por asociación de interés público son aquellas promovidas por un organismo público descentralizado para el desarrollo urbano de una porción de reserva territorial para el crecimiento así designada en el Programa de Desarrollo Urbano de un centro de población, en el que el organismo promotor se asocia con los propietarios de los predios involucrados con el fin de compartir los costos y beneficios consecuentes de la urbanización y comercialización de los lotes o parcelas resultantes.\nARTICULO 218.- Para realizar acciones de urbanización y reparcelación por asociación de interés público, se requiere de un Programa Parcial de Desarrollo Urbano y de un Proyecto de Acción de Urbanización según lo previsto en esta Ley. En ellos deberán precisarse las obras y servicios a ejecutar, los usos y destinos de los predios, densidades de construcción e intensidades de uso y estudios de ingeniería vial, impacto ambiental e imagen urbana a que deberá sujetarse el desarrollo.\nARTICULO 219.- Para que el organismo promotor cubra los costos de proyecto, construcción y comercialización de la acción de urbanización propuesta, se estimará el valor probable de mercado del suelo ya urbanizado. El costo total de la acción se dividirá entre el\nLey de Desarrollo Urbano del Estado de Baja California. Página 77 porcentaje de esa superficie equivale al costo total del desarrollo. A dicho porcentaje se le denominará \"porcentaje de superficie equivalente del costo\" que sumado al porcentaje del cada miembro de la asociación aportó a la misma. Las superficies resultantes así reducidas predio original aportado. El resto de la superficie vendible la retendrá el organismo promotor para su comercialización, cubriendo los costos incurridos más una reserva para futuras promociones.\nARTICULO 220.- Para la realización de las acciones de urbanización y reparcelación por asociación de interés público, se seguirá el procedimiento siguiente:\nI. El organismo promovente con la aprobación de por lo menos el 80% de los propietarios integrará los estudios urbanísticos que acrediten el interés público del desarrollo urbano propuesto;\nII. Dicho estudio será presentado a la Comisión Coordinadora de Desarrollo Urbano, quien si lo aprueba dispondrá la elaboración del Programa Parcial de Desarrollo Urbano con la intervención del Ayuntamiento respectivo o con la de la Secretaría, según el tipo de acción de urbanización de que se trate o su ubicación geográfica; y,\nIII. Tanto la aprobación del Programa Parcial de Desarrollo Urbano como el Acuerdo de Autorización de la acción de urbanización se darán en los términos de la presente Ley.\nArtículo Reformado\nCAPITULO SEPTIMO\nDe las Acciones de Urbanización por Concertación\nARTICULO 221.- Las acciones de urbanización por concertación son aquellas obras que se realizan en vías y espacios públicos, mediante convenio celebrado con el\nAyuntamiento respectivo, con la participación de los propietarios o promotores asociados con éstos que tengan interés en realizarlas.\nARTICULO 222.- Las acciones de urbanización por concertación se realizarán siempre y cuando se presente previamente al Ayuntamiento, una solicitud acompañada del acuerdo de aceptación de realizarlas a su cargo, por parte de todos los propietarios de predios directamente beneficiados por las obras.\nUrbanización Municipal correspondiente.\nLas acciones que se proyecten realizar mediante esta modalidad, deberán cumplir con las normas definidas en esta Ley y demás disposiciones aplicables.\nCAPITULO OCTAVO\nLey de Desarrollo Urbano del Estado de Baja California. Página 78\nARTICULO 223.- Las acciones de urbanización por objetivo social se refieren al ambas autoridades, a fin de responder a la demanda de suelo urbano para la vivienda popular y evitar, con ello, el asentamiento espontáneo o irregular.\nA efecto de ampliar las posibilidades de acceso a la vivienda a las familias de bajos ingresos o sectores de la población más desprotegidos, el Gobernador del Estado, por sí o a través de sus organismos descentralizados, bajo acuerdo del Ayuntamiento respectivo, en atención a la urgencia inmediata de resolver problemas de vivienda, podrá impulsar el desarrollo de fraccionamientos de tipo Habitacional Social Progresivo, con los requisitos mínimos de urbanización previstos en la presente Ley.\nPárrafo Adicionado\nArtículo Reformado\nARTICULO 224.- La gestión de toda acción de urbanización por objetivo social, se realizará por iniciativa de las autoridades estatales y municipales, quienes tratándose de predios de propiedad privada, pueden asociarse con sus propietarios para el desarrollo de este tipo de urbanizaciones. Asimismo, las autoridades estatales y municipales podrán atender las peticiones de ciudadanos, que agrupados en cooperativas y asociaciones de colonos soliciten este tipo de acción de urbanización y aporten los terrenos para desarrollarlo.\nEn el caso de los fraccionamientos de tipo Habitacional Social Progresivo, el Ejecutivo del Estado o sus organismos descentralizados podrán convenir con el sector social o con organismos públicos federales, cuya finalidad sea la construcción, subsidio o financiamiento de vivienda de interés social, para la adquisición de terrenos o en cualquier otra operación necesaria para llevar a cabo el fraccionamiento, quedando a cargo del Ejecutivo del Estado o el organismo descentralizado correspondiente su supervisión.\nPárrafo Adicionado\nArtículo Reformado\nARTICULO 225.- En ningún caso, las acciones de urbanización por objetivo social podrán estar a cargo exclusivamente de particulares.\nLa participación del Estado y los Municipios en esta modalidad, tendrá el propósito de garantizar a los adquirentes por medio de la gestión pública, el desarrollo progresivo de las obras de urbanización, otorgar un valor social a los terrenos y, en general, cumplir con su objetivo.\nARTICULO 226.- Para promover una acción de urbanización por objetivo social, será necesario:\nI. Realizar los estudios que la fundamenten, tanto en lo económico y social, como en desarrollo, en relación a los servicios de agua potable, drenaje y electricidad, entre otros;\nLey de Desarrollo Urbano del Estado de Baja California. Página 79 corresponda, decidirán si realizan la urbanización bajo esta modalidad; corresponda, elaborarán el proyecto definitivo, en el caso del Fraccionamiento Habitacional\nSocial Progresivo, se definirán las obras mínimas que se ejecutarán y las obras complementarias que integran una urbanización popular completa;\nFracción Reformado\nIV. Las obras mínimas a que se refiere la fracción anterior, que se exigirán son las siguientes:\nFracción Reformada\na) Aprovisionamiento de agua potable mediante hidrantes localizados en una de las esquinas; y,\nb) Conformación del terreno para señalar las vías públicas;\nc) La construcción de guarniciones de banqueta, y\nInciso Adicionado\nd) La introducción de redes de infraestructura de servicios de electrificación y alumbrado público.\nInciso Adicionado\nFracción Reformada\nV. Realizadas las obras en los términos previstos en la presente Ley y los\nReglamentos correspondientes, el Ayuntamiento procederá a su recepción levantando el acta respectiva; y\nFracción Reformada\nVI. En el caso del Fraccionamiento Habitacional Social Progresivo, una vez que el\nAyuntamiento haya recibido de conformidad las obras, se procederá a ocupar los lotes.\nFracción Reformada\nArtículo Reformado\nARTICULO 227.- El complemento de las obras de urbanización en una acción de urbanización por objetivo social, deberán concluirse dentro del plazo de 5 años contados a partir de la fecha en que el Ayuntamiento haya recibido las obras mínimas respectivas, y se respectivo y los adquirientes de los lotes.\nPárrafo Reformado posibles las gestiones que se establezcan en dicho convenio.\nArtículo Reformado\nARTICULO 228.- La junta de vecinos, previa autorización del Ayuntamiento y/o del\nEjecutivo del Estado, según corresponda, podrá solicitar al Consejo de Urbanización\nLey de Desarrollo Urbano del Estado de Baja California. Página 80 faltantes en el desarrollo progresivo, cuando así lo convengan y de acuerdo a la capacidad económica de los adquirentes de los lotes.\nARTICULO 229.- Mientras las obras de urbanización no estén concluidas conforme las disposiciones reglamentarias en la materia, el Ayuntamiento no levantará el acta final de recepción de obras.\nARTICULO 230.- Los propietarios de lotes en una acción de urbanización por objetivo social o quienes adquieran sus derechos, están obligados solidariamente en las responsabilidades derivadas de la realización de las obras de urbanización progresiva. Este hecho deberá consignarse en los documentos de propiedad que se expidan y en las inscripciones que se hagan en el Registro Público de la Propiedad y del Comercio.\nArtículo Reformado\nARTICULO 231.- El Estado participará como promotor a través de la Secretaría y demás organismos descentralizados.\nArtículo Reformado\nARTICULO 232.- Los Ayuntamientos participarán como promotores a través de la\nDependencia de Obras Públicas correspondiente, o de un organismo municipal especializado en materia inmobiliaria.\nARTICULO 233.- La autorización de este tipo de acción de urbanización se otorgará cumpliendo con todas las disposiciones previstas en esta Ley y en el Reglamento respectivo para dichos casos; la autorización corresponderá a los Ayuntamientos cuando estén ubicados dentro del centro de población y si se localizan fuera de estos límites será competencia del Estado.\nARTICULO 234.- Cuando las obras de urbanización progresiva se concluyan de conformidad con las regulaciones en la materia, se procederá a levantar el acta final de recepción de obras, por parte del Ayuntamiento, quien procederá a notificarlo al Registro\nPúblico de la Propiedad y del Comercio que corresponda.\nTITULO OCTAVO\nDE LAS RESPONSABILIDADES, MEDIDAS DE SEGURIDAD, SANCIONES Y DEFENSA\nDE LOS PARTICULARES\nCAPITULO PRIMERO\nDe las Responsabilidades\nARTICULO 235.- Son infracciones cuya responsabilidad corresponde a los encargados del Registro Público de la Propiedad y del Comercio, Notarios y en general a los servidores públicos investidos de fe pública:\nLey de Desarrollo Urbano del Estado de Baja California. Página 81\nI. Autorizar documentos, contratos, convenios, escrituras o minutas que contravengan lo dispuesto en los Programas, Declaratorias, Decretos o Resoluciones Administrativas relativas al desarrollo urbano en el Estado;\nII. Proporcionar los informes o documentos a que se refiere la fracción anterior, con datos alterados o falsificados;\nIII. Cooperar con los infractores o facilitarles en cualquier forma la violación a las disposiciones de la presente Ley, y demás disposiciones reglamentarias.\nARTICULO 236.- Los servidores públicos responsables de las infracciones previstas en el artículo anterior, serán sancionados conforme a las disposiciones de la Ley de\nResponsabilidades de los Servidores Públicos del Estado de Baja California, y los Fedatarios\nPúblicos responsables de las infracciones señaladas en el artículo anterior, serán sancionados por el Ejecutivo del Estado conforme a lo estipulado en la Ley del Notariado del\nEstado de Baja California y demás disposiciones legales aplicables.\nARTICULO 237.- Son infracciones cuya responsabilidad corresponde a los servidores públicos:\nI. Autorizar o dar curso a documentos, contratos o convenios que contravengan lo dispuesto en esta Ley y reglamentos, a los Planes y Programas, Declaratorias, Decretos y\nResoluciones Administrativas relativas al Desarrollo Urbano de la Entidad;\nII. Faltar a la obligación de guardar secreto respecto de los asuntos que conozcan, revelar los datos confidenciales o aprovecharse de ellos; y,\nIII. Exigir a los particulares, bajo el título de colaboración u otra semejante, cualquier prestación pecuniaria o de otra índole no prevista en esta Ley y demás disposiciones relativas.\nARTICULO 238.- Se sancionará a los responsables señalados en el artículo anterior, de acuerdo a lo dispuesto en la Ley de Responsabilidades de los Servidores Públicos del\nEstado de Baja California.\nCAPITULO SEGUNDO\nDe las Medidas de Seguridad y Sanciones\nARTICULO 239.- El Ejecutivo del Estado, a través de la Secretaría así como las\nAutoridades Municipales correspondientes, tendrán a su cargo la vigilancia del cumplimiento de las disposiciones de esta Ley y demás disposiciones relativas; para tal efecto, podrán adoptar y ejecutar las medidas de seguridad, calificar las infracciones e imponer las sanciones administrativas que correspondan.\nArtículo Reformado\nARTICULO 240.- Para los efectos de esta Ley, se consideran medidas de seguridad, la adopción y ejecución de las disposiciones que, con apoyo en sus preceptos, dicten las\nLey de Desarrollo Urbano del Estado de Baja California. Página 82 jurisdicciones, encaminadas a evitar los daños que puedan causar las instalaciones, las construcciones y las obras tanto públicas como privadas. Las medidas de seguridad son de inmediata ejecución, tienen carácter preventivo y se aplicarán sin perjuicio de las sanciones que en su caso correspondan. protección civil cuando exista el convenio correspondiente, desempeñarán la función de inspección y verificación en lo relativo a construcciones, establecimientos, instalaciones y análogas, dedicadas al almacenamiento, distribución y venta al público de gas licuado de petróleo, a fin de que estas cumplan con lo dispuesto en la Ley de Protección Civil y Gestión de Riesgos del Estado, así como con las Normas Oficiales Mexicanas, los reglamentos municipales y disposiciones en materia de seguridad industrial, operativa y de protección ambiental.\nPárrafo Adicionado\nLas Direcciones de Administración Urbana o análogas de los municipios, realizarán las verificaciones e inspecciones correspondientes, a fin de emitir las recomendaciones técnicas necesarias, y en caso de detectar irregularidades; darán vista a la Unidad de\nProtección Civil Municipal que corresponda, y aplicarán las medidas de seguridad y sanciones respectivas.\nPárrafo Adicionado\nAdemás de lo anterior, las Direcciones de Administración Urbana o análogas de los municipios deberán atender las resoluciones de los inspectores de las autoridades competentes en materia federal, para dar el debido cumplimiento a la normatividad aplicable dentro del ámbito de su competencia.\nPárrafo Adicionado\nEn el supuesto de que los particulares impidan el desahogo de las inspecciones señaladas en el presente artículo, los inspectores podrán solicitar auxilio de la fuerza pública para que se lleve a cabo la inspección.\nPárrafo Adicionado\nArtículo Reformado\nARTICULO 241.- Se consideran como medidas de seguridad:\nI. La suspensión de trabajos y servicios;\nII. La clausura temporal o definitiva, total o parcial de las instalaciones, construcciones y obras públicas o privadas;\nIII. La desocupación o desalojo de inmuebles;\nIV. La demolición de construcciones;\nV. El retiro de las instalaciones;\nVI. La prohibición de uso del inmueble;\nVII. Cualesquiera otra que tienda a lograr los fines expresados en el artículo anterior.\nLey de Desarrollo Urbano del Estado de Baja California. Página 83\nARTICULO 242.- Las sanciones administrativas podrán consistir en:\nI. Clausura temporal o definitiva, total o parcial de las instalaciones, las construcciones y de las obras y servicios;\nII. Multa de 1 a 500 veces el salario mínimo vigente en la región respectiva, y tratándose de inmuebles, hasta el 10% de su valor;\nIII. Demolición de las construcciones efectuadas en contravención de los Planes y\nProgramas de Desarrollo Urbano, así como de las disposiciones de esta Ley y demás disposiciones relativas;\nIV. Revocación de las autorizaciones, permisos o licencias otorgadas.\nARTICULO 243.- En las disposiciones reglamentarias de esta Ley, se determinarán los casos y el procedimiento en que deberán de ser aplicadas las medidas de seguridad, así como la imposición de sanciones, tomando en cuenta la gravedad de la infracción, las circunstancias particulares del caso y la reincidencia.\nARTICULO 244.- Si las circunstancias así lo exigen, podrá imponerse simultáneamente al infractor las sanciones y las medidas de seguridad que correspondan, sin perjuicio de la responsabilidad penal, civil o administrativa en que incurra.\nCAPITULO TERCERO\nDe la Defensa de los Particulares\nARTICULO 245.- Contra las resoluciones dictadas por la aplicación de esta Ley y sus reglamentos, procederá el recurso de revocación, el cual deberá ser presentado por escrito dentro del término de 10 días hábiles siguientes a la notificación del acto impugnado, y ante la autoridad que hubiese emitido la resolución recurrida.\nARTICULO 246.- Procede el recurso de revocación:\nI. Contra los actos de las autoridades que determinen y ejecuten las medidas de seguridad previstas en esta ley y que el promovente estime improcedentes o inadecuadas;\nII. Contra los actos de las autoridades que impongan las sanciones a que ésta Ley se refiere y que el interesado estime indebidamente fundadas y motivadas; y,\nIII.- Contra los actos de las autoridades administrativas que los interesados estimen violatorios de esta Ley, sus Planes y Programas de Desarrollo Urbano, Declaratorias, Decretos o Reglamentos Vigentes.\nARTICULO 247.- Las normas para la substanciación del recurso deberán ser dictadas dentro del reglamento de la presente Ley que elaboren los Ayuntamientos, debiendo establecer no más de dos instancias, su capítulo de suspensión del acto reclamado con las reglas respectivas para su otorgamiento y los términos en que se deba resolver.\nLey de Desarrollo Urbano del Estado de Baja California. Página 84\nARTICULO PRIMERO.- Esta ley entrará en vigor a los 30 días siguientes a su\nARTICULO SEGUNDO.- Se abroga la Ley de Desarrollo Urbano del Estado de Baja reglamentos y demás disposiciones derivadas de la Ley que se abroga, continuarán surtiendo sus efectos en todo aquello que no se opongan a esta Ley y hasta que se expidan los nuevos reglamentos que emanen de la misma.\nARTICULO TERCERO.- Las autorizaciones de fraccionamientos, subdivisiones y relotificaciones expedidas por la Secretaría de Asentamientos Humanos y Obras Públicas del Estado con anterioridad a la vigencia de esta Ley, de los planes y declaratorias, podrán continuar en los términos que fueron concedidas.\nLas autorizaciones o licencias de construcción otorgadas con anterioridad a la vigencia de la presente Ley, concluirán conforme a la autorización que las ampara.\nARTICULO CUARTO.- Las solicitudes de licencias, permisos y autorizaciones para fraccionamientos, subdivisiones, relotificaciones y edificaciones que se encuentren en trámite ante la Secretaría de Asentamientos Humanos y Obras Públicas del Estado, serán cumplimentadas por ésta última, aplicándole la presente Ley en todo lo que le beneficie al promovente.\nARTICULO QUINTO.- Los fraccionadores que hubieran iniciado o realizado una acción sin la autorización correspondiente, tendrán un plazo de 90 días a partir de la entrada en vigor de esta Ley, para que soliciten su regularización a la autoridad que corresponda; transcurrido este tiempo se harán acreedores a las sanciones que para el caso señala esta\nLey y las demás disposiciones reglamentarias.\nARTICULO SEXTO.- Se disuelve la Comisión Coordinadora de los Planes de\nDesarrollo Urbano constituida durante la vigencia de la ley que se abroga, y en su caso los\nDesarrollo Urbano del Estado.\nARTICULO SEPTIMO.- La Comisión Coordinadora de Desarrollo Urbano a que se refiere esta Ley, expedirá su Reglamento en un plazo no mayor de 45 días contados a partir de su primera sesión.\nMexicali, Baja California, a los dieciséis días del mes de junio de mil novecientos noventa y cuatro.\nFRANCISCO JAVIER REYNOSO NUÑO\nLey de Desarrollo Urbano del Estado de Baja California. Página 85\nDIPUTADO PRESIDENTE\n(RÚBRICA).\nLUIS MERCADO SOLIS\nDIPUTADO SECRETARIO\n(RÚBRICA).\nDE CONFORMIDAD CON LO DISPUESTO POR LA FRACCION I DEL ARTICULO\n49 DE LA CONSTITUCION POLITICA DEL ESTADO, MANDO SE IMPRIMA, PUBLIQUE,\nOBSERVE Y SE LE DE EL DEBIDO CUMPLIMIENTO.\nMEXICALI, BAJA CALIFORNIA, A LOS VEINTIDOS DIAS DEL MES DE JUNIO DE\nMIL NOVECIENTOS NOVENTA Y CUATRO.\nEL GOBERNADOR CONSTITUCIONAL DEL ESTADO\nLIC. ERNESTO RUFFO APPEL\n(RÚBRICA).\nEL SECRETARIO GENERAL DE GOBIERNO\nC.P. FORTUNATO ALVAREZ ENRIQUEZ\n(RÚBRICA).\nLey de Desarrollo Urbano del Estado de Baja California. Página 86\nARTÍCULO 3.- Fue reformado por Decreto No. 31, publicado en el Periódico Oficial No. 45, siendo Gobernador Constitucional el C. Lic. Héctor Terán Terán, 1995-1998; fue reformado\nÍndice, Tomo CXXXI, expedido por la H. XXIV Legislatura, siendo Gobernadora\nConstitucional la C. Marina del Pilar Ávila Olmeda 2021-2027;\nARTÍCULO 4.- Fue reformado por Decreto No. 211, Publicado en el Periódico Oficial\nNo. 24, de fecha 25 de mayo de 2012, Sección II, Tomo CXIX, expedido por la H. XX\nLegislatura, siendo Gobernador Constitucional el C. José Guadalupe Osuna Millán 20072013; fue reformado por Decreto No. 313, publicado en el Periódico Oficial No. 39, Sección\nII, Tomo CXXII, de fecha 21 de agosto de 2015, expedido por la H. XXI Legislatura, siendo\nGobernador Constitucional el C. Francisco Arturo Vega de Lamadrid 2013-2019; fue reformado por Decreto No. 347, publicado en el Periódico Oficial No. 30, Sección III, Tomo\nCXXVI, de fecha 12 de julio de 2019, expedido por la H. XXII Legislatura, siendo Gobernador\nConstitucional el C. Francisco Arturo Vega de Lamadrid 2013-2019; fue reformado por\nDecreto No. 36, publicado en el Periódico Oficial No. 67, Sección VIII, Tomo CXXVI, de fecha 31 de diciembre de 2019, expedido por la H. XXIII Legislatura, siendo Gobernador\nConstitucional el C. Jaime Bonilla Valdez 2019-2021; fue reformado por Decreto No. 279, publicado en el Periódico Oficial No. 51, Sección IV, Tomo CXXVIII, de fecha 23 de julio de\n2021, expedido por la H. XXIII Legislatura, siendo Gobernador Constitucional el C. Jaime\nBonilla Valdez 2019-2021; fue reformado por Decreto No. 197, publicado en el Periódico\nOficial No. 76, Sección III, Tomo CXXIX, de fecha 30 de diciembre de 2022, expedido por la\nH. XXIV Legislatura, siendo Gobernadora Constitucional la C. Marina del Pilar Ávila Olmeda\n2021-2027;\nARTÍCULO 6.- Fue reformado por Decreto No. 325, Publicado en el Periódico Oficial\nNo. 58, de fecha 28 de diciembre de 2009, Sección II, Tomo CXVI, expedido por la H. XIX\nLegislatura, siendo Gobernador Constitucional el C. José Guadalupe Osuna Millán 20072013; fue reformado por Decreto No. 33, Publicado en el Periódico Oficial No. 11, de fecha\n18 de febrero de 2011, Sección I, Tomo CXVIII, expedido por la H. XX Legislatura, siendo\nGobernador Constitucional el C. José Guadalupe Osuna Millán 2007-2013; fue reformado por Decreto No. 431, Publicado en el Periódico Oficial No. 15, de fecha 22 de marzo de\n2013, Sección I, Tomo CXX, expedido por la H. XX Legislatura, siendo Gobernador\nConstitucional el C. José Guadalupe Osuna Millán 2007-2013; fue reformado mediante\nSección I, Tomo CXX, expedido por la H. XX Legislatura, siendo Gobernador Constitucional el C. José Guadalupe Osuna Millán 2007-2013; fue reformado mediante Decreto No. 248, publicado en Periódico Oficial No. 33, de fecha 13 de julio 2018, Sección III, Tomo CXXV, expedido por la H. XXII Legislatura, siendo Gobernador Constitucional el C. Francisco Arturo\nVega de Lamadrid 2013-2019; fue reformado por Decreto No. 279, publicado en el Periódico\nXXIII Legislatura, siendo Gobernador Constitucional el C. Jaime Bonilla Valdez 2019-2021;\nLey de Desarrollo Urbano del Estado de Baja California. Página 87 fue reformado por Decreto No. 129, publicado en el Periódico Oficial No. 56, Sección III, siendo Gobernadora Constitucional la C. Marina del Pilar Ávila Olmeda 2021-2027; fue reformado por Decreto No. 452, publicado en el Periódico Oficial No.40, Índice, de fecha 16\nConstitucional la C. Marina del Pilar Ávila Olmeda 2021-2027;\nARTÍCULO 7.- Fue reformado por Decreto No. 325, Publicado en el Periódico Oficial\nNo. 58, de fecha 28 de diciembre de 2009, Sección II, Tomo CXVI, expedido por la H. XIX\nLegislatura, siendo Gobernador Constitucional el C. José Guadalupe Osuna Millán 20072013; fue reformado por Decreto No. 279, publicado en el Periódico Oficial No. 51, Sección\nIV, Tomo CXXVIII, de fecha 23 de julio de 2021, expedido por la H. XXIII Legislatura, siendo\nGobernador Constitucional el C. Jaime Bonilla Valdez 2019-2021;\nARTÍCULO 9.- Fue reformado por Decreto No. 325, Publicado en el Periódico Oficial\nNo. 58, de fecha 28 de diciembre de 2009, Sección II, Tomo CXVI, expedido por la H. XIX\nLegislatura, siendo Gobernador Constitucional el C. José Guadalupe Osuna Millán 20072013;\nARTÍCULO 10.- Fue reformado por Decreto No. 325, Publicado en el Periódico Oficial\nNo. 58, de fecha 28 de diciembre de 2009, Sección II, Tomo CXVI, expedido por la H. XIX\nLegislatura, siendo Gobernador Constitucional el C. José Guadalupe Osuna Millán 20072013; fue reformado mediante Decreto No. 248, publicado en Periódico Oficial No. 33, de fecha 13 de julio 2018, Sección III, Tomo CXXV, expedido por la H. XXII Legislatura, siendo\nGobernador Constitucional el C. Francisco Arturo Vega de Lamadrid 2013-2019; fue reformado por Decreto No. 279, publicado en el Periódico Oficial No. 51, Sección IV, Tomo\nCXXVIII, de fecha 23 de julio de 2021, expedido por la H. XXIII Legislatura, siendo\nGobernador Constitucional el C. Jaime Bonilla Valdez 2019-2021;\nARTÍCULO 11.- Fue reformado por Decreto No. 325, Publicado en el Periódico Oficial\nNo. 58, de fecha 28 de diciembre de 2009, Sección II, Tomo CXVI, expedido por la H. XIX\nLegislatura, siendo Gobernador Constitucional el C. José Guadalupe Osuna Millán 20072013; fue reformado por Decreto No. 218, Publicado en el Periódico Oficial No. 14, de fecha\n20 de marzo de 2015, Tomo CXXII, expedido por la H. XXI Legislatura, siendo Gobernador\nConstitucional el C. Francisco Arturo Vega de Lamadrid 2013-2019; fue reformado por\nDecreto No. 279, publicado en el Periódico Oficial No. 51, Sección IV, Tomo CXXVIII, de\nConstitucional el C. Jaime Bonilla Valdez 2019-2021;\nARTÍCULO 12.- Fue reformado por Decreto No. 325, Publicado en el Periódico Oficial\nLegislatura, siendo Gobernador Constitucional el C. José Guadalupe Osuna Millán 20072013; fue reformado mediante Decreto No. 248, publicado en Periódico Oficial No. 33, de fecha 13 de julio 2018, Sección III, Tomo CXXV, expedido por la H. XXII Legislatura, siendo\nLey de Desarrollo Urbano del Estado de Baja California. Página 88\nGobernador Constitucional el C. Francisco Arturo Vega de Lamadrid 2013-2019; fue reformado por Decreto No. 279, publicado en el Periódico Oficial No. 51, Sección IV, Tomo\nGobernador Constitucional el C. Jaime Bonilla Valdez 2019-2021;\nARTÍCULO 13.- Fue reformado por Decreto No. 325, Publicado en el Periódico Oficial\nNo. 58, de fecha 28 de diciembre de 2009, Sección II, Tomo CXVI, expedido por la H. XIX\nLegislatura, siendo Gobernador Constitucional el C. José Guadalupe Osuna Millán 20072013;\nARTÍCULO 14.- Fue reformado por Decreto No. 325, Publicado en el Periódico Oficial\nNo. 58, de fecha 28 de diciembre de 2009, Sección II, Tomo CXVI, expedido por la H. XIX\nLegislatura, siendo Gobernador Constitucional el C. José Guadalupe Osuna Millán 20072013;\nARTÍCULO 15.- Fue reformado por Decreto No. 325, Publicado en el Periódico Oficial\nNo. 58, de fecha 28 de diciembre de 2009, Sección II, Tomo CXVI, expedido por la H. XIX\nLegislatura, siendo Gobernador Constitucional el C. José Guadalupe Osuna Millán 20072013;\nARTÍCULO 17.- Fue reformado por Decreto No. 325, Publicado en el Periódico Oficial\nNo. 58, de fecha 28 de diciembre de 2009, Sección II, Tomo CXVI, expedido por la H. XIX\nLegislatura, siendo Gobernador Constitucional el C. José Guadalupe Osuna Millán 20072013;\nARTÍCULO 18.- Fue reformado por Decreto No. 325, Publicado en el Periódico Oficial\nNo. 58, de fecha 28 de diciembre de 2009, Sección II, Tomo CXVI, expedido por la H. XIX\nLegislatura, siendo Gobernador Constitucional el C. José Guadalupe Osuna Millán 20072013;\nARTÍCULO 19.- Fue reformado por Decreto No. 325, Publicado en el Periódico Oficial\nNo. 58, de fecha 28 de diciembre de 2009, Sección II, Tomo CXVI, expedido por la H. XIX\nLegislatura, siendo Gobernador Constitucional el C. José Guadalupe Osuna Millán 20072013;\nARTÍCULO 21.- Fue reformado por Decreto No. 325, Publicado en el Periódico Oficial\nLegislatura, siendo Gobernador Constitucional el C. José Guadalupe Osuna Millán 20072013;\nARTÍCULO 22.- Fue reformado por Decreto No. 325, Publicado en el Periódico Oficial\nLegislatura, siendo Gobernador Constitucional el C. José Guadalupe Osuna Millán 20072013; fue reformado por Decreto No. 219, publicado en el Periódico Oficial No. 15, Sección\nGobernador Constitucional el C. Francisco Arturo Vega de Lamadrid 2013-2019;\nLey de Desarrollo Urbano del Estado de Baja California. Página 89\nARTÍCULO 22 BIS.- Fue reformado por Decreto No. 279, publicado en el Periódico\nXXIII Legislatura, siendo Gobernador Constitucional el C. Jaime Bonilla Valdez 2019-2021;\nARTÍCULO 22 TER.- Fue reformado por Decreto No. 279, publicado en el Periódico\nXXIII Legislatura, siendo Gobernador Constitucional el C. Jaime Bonilla Valdez 2019-2021;\nARTÍCULO 22 QUATER.- Fue reformado por Decreto No. 279, publicado en el\nPeriódico Oficial No. 51, Sección IV, Tomo CXXVIII, de fecha 23 de julio de 2021, expedido por la H. XXIII Legislatura, siendo Gobernador Constitucional el C. Jaime Bonilla Valdez\n2019-2021;\nARTÍCULO 22 QUINQUIES.- Fue reformado por Decreto No. 279, publicado en el\nPeriódico Oficial No. 51, Sección IV, Tomo CXXVIII, de fecha 23 de julio de 2021, expedido por la H. XXIII Legislatura, siendo Gobernador Constitucional el C. Jaime Bonilla Valdez\n2019-2021;\nARTÍCULO 22 SEXIES.- Fue reformado por Decreto No. 279, publicado en el\nPeriódico Oficial No. 51, Sección IV, Tomo CXXVIII, de fecha 23 de julio de 2021, expedido por la H. XXIII Legislatura, siendo Gobernador Constitucional el C. Jaime Bonilla Valdez\n2019-2021;\nARTÍCULO 22 SEPTIES.- Fue reformado por Decreto No. 279, publicado en el\nPeriódico Oficial No. 51, Sección IV, Tomo CXXVIII, de fecha 23 de julio de 2021, expedido por la H. XXIII Legislatura, siendo Gobernador Constitucional el C. Jaime Bonilla Valdez\n2019-2021;\nARTÍCULO 23.- Fue reformado por Decreto No. 325, Publicado en el Periódico Oficial\nNo. 58, de fecha 28 de diciembre de 2009 Sección II, Tomo CXVI, expedido por la H. XIX\nLegislatura, siendo Gobernador Constitucional el C. José Guadalupe Osuna Millán 20072013;\nARTÍCULO 24.- Fue reformado por Decreto No. 325, Publicado en el Periódico Oficial\nLegislatura, siendo Gobernador Constitucional el C. José Guadalupe Osuna Millán 20072013; fue reformado por Decreto No. 279, publicado en el Periódico Oficial No. 51, Sección\nGobernador Constitucional el C. Jaime Bonilla Valdez 2019-2021;\nARTÍCULO 26.- Fue reformado por Decreto No. 260, publicado en el Periódico Oficial\nLegislatura, siendo Gobernador Constitucional el C. Jaime Bonilla Valdez 2019-2021;\nLey de Desarrollo Urbano del Estado de Baja California. Página 90\nARTÍCULO 28.- Fue reformado por Decreto No. 325, Publicado en el Periódico Oficial\nLegislatura, siendo Gobernador Constitucional el C. José Guadalupe Osuna Millán 20072013;\nARTÍCULO 35.- Fue reformado por Decreto No. 325, Publicado en el Periódico Oficial\nNo. 58, de fecha 28 de diciembre de 2009, Sección II, Tomo CXVI, expedido por la H. XIX\nLegislatura, siendo Gobernador Constitucional el C. José Guadalupe Osuna Millán 20072013;\nARTÍCULO 36.- Fue reformado por Decreto No. 325, Publicado en el Periódico Oficial\nNo. 58, de fecha 28 de diciembre de 2009, Sección II, Tomo CXVI, expedido por la H. XIX\nLegislatura, siendo Gobernador Constitucional el C. José Guadalupe Osuna Millán 20072013;\nARTÍCULO 39.- Fue reformado por Decreto No. 129, publicado en el Periódico Oficial\nNo. 56, Sección III, Tomo CXXIX, de fecha 19 de septiembre de 2022, expedido por la H.\nXXIV Legislatura, siendo Gobernadora Constitucional la C. Marina del Pilar Ávila Olmeda\n2021-2027;\nARTÍCULO 41.- Fue reformado por Decreto No. 325, Publicado en el Periódico Oficial\nNo. 58, de fecha 28 de diciembre de 2009, Sección II, Tomo CXVI, expedido por la H. XIX\nLegislatura, siendo Gobernador Constitucional el C. José Guadalupe Osuna Millán 20072013;\nARTÍCULO 43.- Fue reformado por Decreto No. 325, Publicado en el Periódico Oficial\nNo. 58, de fecha 28 de diciembre de 2009, Sección II, Tomo CXVI, expedido por la H. XIX\nLegislatura, siendo Gobernador Constitucional el C. José Guadalupe Osuna Millán 20072013;\nARTÍCULO 45.- Fue reformado por Decreto No. 325, Publicado en el Periódico Oficial\nNo. 58, de fecha 28 de diciembre de 2009, Sección II, Tomo CXVI, expedido por la H. XIX\nLegislatura, siendo Gobernador Constitucional el C. José Guadalupe Osuna Millán 20072013;\nARTÍCULO 46.- Fue reformado por Decreto No. 325, Publicado en el Periódico Oficial\nNo. 58, de fecha 28 de diciembre de 2009, Sección II, Tomo CXVI, expedido por la H. XIX\nLegislatura, siendo Gobernador Constitucional el C. José Guadalupe Osuna Millán 20072013;\nARTÍCULO 53.- Fue reformado por Decreto No. 129, publicado en el Periódico Oficial\nXXIV Legislatura, siendo Gobernadora Constitucional la C. Marina del Pilar Ávila Olmeda\n2021-2027;\nARTÍCULO 56.- Fue reformado por Decreto No. 129, publicado en el Periódico Oficial\nXXIV Legislatura, siendo Gobernadora Constitucional la C. Marina del Pilar Ávila Olmeda\n2021-2027;\nLey de Desarrollo Urbano del Estado de Baja California. Página 91\nARTÍCULO 72.- Fue reformado por Decreto No. 129, publicado en el Periódico Oficial\nXXIV Legislatura, siendo Gobernadora Constitucional la C. Marina del Pilar Ávila Olmeda\n2021-2027;\nARTÍCULO 73.- Fue reformado por Decreto No. 325, Publicado en el Periódico Oficial\nNo. 58, de fecha 28 de diciembre de 2009, Sección II, Tomo CXVI, expedido por la H. XIX\nLegislatura, siendo Gobernador Constitucional el C. José Guadalupe Osuna Millán 20072013;\nARTÍCULO 77.- Fue reformado por Decreto No. 325, Publicado en el Periódico Oficial\nNo. 58, de fecha 28 de diciembre de 2009, Sección II, Tomo CXVI, expedido por la H. XIX\nLegislatura, siendo Gobernador Constitucional el C. José Guadalupe Osuna Millán 20072013;\nARTÍCULO 91.- Fue reformado por Decreto No. 325, Publicado en el Periódico Oficial\nNo. 58, de fecha 28 de diciembre de 2009, Sección II, Tomo CXVI, expedido por la H. XIX\nLegislatura, siendo Gobernador Constitucional el C. José Guadalupe Osuna Millán 20072013;\nARTÍCULO 95.- Fue reformado por Decreto No. 325, Publicado en el Periódico Oficial\nNo. 58, de fecha 28 de diciembre de 2009, Sección II, Tomo CXVI, expedido por la H. XIX\nLegislatura, siendo Gobernador Constitucional el C. José Guadalupe Osuna Millán 20072013;\nARTÍCULO 98.- Fue reformado por Decreto No. 325, Publicado en el Periódico Oficial\nNo. 58, de fecha 28 de diciembre de 2009, Sección II, Tomo CXVI, expedido por la H. XIX\nLegislatura, siendo Gobernador Constitucional el C. José Guadalupe Osuna Millán 20072013;\nARTÍCULO 103.- Fue reformado mediante Decreto No. 491, publicado en el Periódico\nOficial No. 34, de fecha 02 de agosto de 2013, Sección I, Tomo CXX, expedido por la H. XX\nLegislatura, siendo Gobernador Constitucional el C. José Guadalupe Osuna Millán 20072013; fue reformado por Decreto No. 129, publicado en el Periódico Oficial No. 56, Sección\nIII, Tomo CXXIX, de fecha 19 de septiembre de 2022, expedido por la H. XXIV Legislatura, siendo Gobernadora Constitucional la C. Marina del Pilar Ávila Olmeda 2021-2027;\nARTÍCULO 104.- Fue reformado por Decreto No. 129, publicado en el Periódico\nH. XXIV Legislatura, siendo Gobernadora Constitucional la C. Marina del Pilar Ávila Olmeda\n2021-2027;\nARTÍCULO 112.- Fue reformado por Decreto No. 325, Publicado en el Periódico\nXIX Legislatura, siendo Gobernador Constitucional el C. José Guadalupe Osuna Millán 20072013;\nARTÍCULO 113.- Fue reformado por Decreto No. 325, Publicado en el Periódico\nLey de Desarrollo Urbano del Estado de Baja California. Página 92\nXIX Legislatura, siendo Gobernador Constitucional el C. José Guadalupe Osuna Millán 20072013;\nARTÍCULO 114.- Fue reformado por Decreto No. 452, publicado en el Periódico\nLegislatura, siendo Gobernador Constitucional el C. José Guadalupe Osuna Millán 20072013; fue reformado mediante Decreto No. 491, publicado en el Periódico Oficial No. 34, de fecha 02 de agosto de 2013, Sección I, Tomo CXX, expedido por la H. XX Legislatura, siendo Gobernador Constitucional el C. José Guadalupe Osuna Millán 2007-2013; fue reformado por Decreto No. 129, publicado en el Periódico Oficial No. 56, Sección III, Tomo\nCXXIX, de fecha 19 de septiembre de 2022, expedido por la H. XXIV Legislatura, siendo\nGobernadora Constitucional la C. Marina del Pilar Ávila Olmeda 2021-2027; fue reformado por Decreto No. 54, publicado en el Periódico Oficial No.15, Índice, de fecha 14 de marzo de\n2025, Tomo CXXXII, expedido por la H. XXV Legislatura, siendo Gobernadora Constitucional la C. Marina del Pilar Ávila Olmeda 2021-2027;\nARTÍCULO 114 BIS.- Fue adicionado por Decreto No. 54, publicado en el Periódico\nOficial No. 15, Índice, de fecha 14 de marzo de 2025, Tomo CXXXII, expedido por la H. XXV\nLegislatura, siendo Gobernadora Constitucional la C. Marina del Pilar Ávila Olmeda 20212027;\nARTÍCULO 115.- Fue reformado por Decreto No. 325, Publicado en el Periódico\nOficial No. 58, de fecha 28 de diciembre de 2009, Sección II, Tomo CXVI, expedido por la H.\nXIX Legislatura, siendo Gobernador Constitucional el C. José Guadalupe Osuna Millán 20072013;\nARTÍCULO 117.- Fue reformado por Decreto No. 33, Publicado en el Periódico Oficial\nNo. 11, de fecha 18 de febrero de 2011, Sección I, Tomo CXVIII, expedido por la H. XX\nLegislatura, siendo Gobernador Constitucional el C. José Guadalupe Osuna Millán 20072013; Fue reformado por Decreto No. 453, publicado en el Periódico Oficial No. 24, de fecha\n24 de mayo de 2013, Tomo CXX, expedido por la H. XX Legislatura, siendo Gobernador\nConstitucional el C. José Guadalupe Osuna Millán 2007-2013; fue reformado mediante\nDecreto No. 248, publicado en Periódico Oficial No. 33, de fecha 13 de julio 2018, Sección\nIII, Tomo CXXV, expedido por la H. XXII Legislatura, siendo Gobernador Constitucional el C.\nFrancisco Arturo Vega de Lamadrid 2013-2019;\nARTÍCULO 117 BIS.- Fue adicionado mediante Decreto No. 248, publicado en\nPeriódico Oficial No. 33, de fecha 13 de julio 2018, Sección III, Tomo CXXV, expedido por la\nH. XXII Legislatura, siendo Gobernador Constitucional el C. Francisco Arturo Vega de\nLamadrid 2013-2019;\nARTÍCULO 128.- Fue reformado por Decreto No. 325, Publicado en el Periódico\nXIX Legislatura, siendo Gobernador Constitucional el C. José Guadalupe Osuna Millán 20072013;\nLey de Desarrollo Urbano del Estado de Baja California. Página 93\nARTÍCULO 129.- Fue reformado por Decreto No. 325, Publicado en el Periódico\nXIX Legislatura, siendo Gobernador Constitucional el C. José Guadalupe Osuna Millán 20072013;\nARTÍCULO 134.- Fue reformado por Decreto No. 325, Publicado en el Periódico\nOficial No. 58, de fecha 28 de diciembre de 2009, Sección II, Tomo CXVI, expedido por la H.\nXIX Legislatura, siendo Gobernador Constitucional el C. José Guadalupe Osuna Millán 20072013;\nARTÍCULO 140.- Fue reformado mediante Decreto No. 248, publicado en Periódico\nOficial No. 33, de fecha 13 de julio 2018, Sección III, Tomo CXXV, expedido por la H. XXII\nLegislatura, siendo Gobernador Constitucional el C. Francisco Arturo Vega de Lamadrid\n2013-2019;\nARTÍCULO 145.- Fue reformado por Decreto No. 327, publicado en el Periódico\nOficial No. 35, de fecha 17 de agosto de 2001, Tomo CVIII, Sección I, expedido por la H. XVI\nLegislatura; siendo Gobernador Constitucional el C. Lic. Alejandro González Alcocer 19982001;\nARTÍCULO 146.- Fue reformado por Decreto No. 260, publicado en el Periódico\nOficial No. 57, Sección I, Tomo CXXVIII, de fecha 06 de agosto de 2021, expedido por la H.\nXXIII Legislatura, siendo Gobernador Constitucional el C. Jaime Bonilla Valdez 2019-2021;\nARTÍCULO 147.- Fue reformado por Decreto No. 31, publicado en el Periódico Oficial No.\n45, Tomo CIII, de Fecha 20 de septiembre de 1996, expedido por la Honorable XV\nLegislatura, siendo Gobernador Constitucional el C. Lic. Héctor Terán Terán, 1995-1998; fue reformado por Decreto No. 129, publicado en el Periódico Oficial No. 56, Sección III, Tomo\nCXXIX, de fecha 19 de septiembre de 2022, expedido por la H. XXIV Legislatura, siendo\nGobernadora Constitucional la C. Marina del Pilar Ávila Olmeda 2021-2027; fue reformado por Decreto No. 240, publicado en el Periódico Oficial No. 37, Índice, de fecha 23 de junio de\n2023, Tomo CXXX, expedido por la H. XXIV Legislatura, siendo Gobernadora Constitucional la C. Marina del Pilar Ávila Olmeda 2021-2027; fue reformado por Decreto No. 369, publicado en el Periódico Oficial No.5, de fecha 26 de enero de 2024, Índice, Tomo CXXXI, expedido por la H. XXIV Legislatura, siendo Gobernadora Constitucional la C. Marina del\nPilar Ávila Olmeda 2021-2027;\nARTÍCULO 150.- Fue reformado por Decreto No. 325, Publicado en el Periódico\nXIX Legislatura, siendo Gobernador Constitucional el C. José Guadalupe Osuna Millán 20072013; fue reformado mediante Decreto No. 248, publicado en Periódico Oficial No. 33, de fecha 13 de julio 2018, Sección III, Tomo CXXV, expedido por la H. XXII Legislatura, siendo\nGobernador Constitucional el C. Francisco Arturo Vega de Lamadrid 2013-2019; fue reformado por Decreto No. 279, publicado en el Periódico Oficial No. 51, Sección IV, Tomo\nGobernador Constitucional el C. Jaime Bonilla Valdez 2019-2021;\nLey de Desarrollo Urbano del Estado de Baja California. Página 94\nARTÍCULO 150 BIS.- Fue adicionado mediante Decreto No. 248, publicado en\nPeriódico Oficial No. 33, de fecha 13 de julio 2018, Sección III, Tomo CXXV, expedido por la\nH. XXII Legislatura, siendo Gobernador Constitucional el C. Francisco Arturo Vega de\nLamadrid 2013-2019;\nARTÍCULO 153.- Fue reformado por Decreto No. 228, publicado en el Periódico\nOficial No. 45, de fecha 06 de noviembre de 1998, expedido por la Honorable XV\nLegislatura, siendo Gobernador Constitucional el C. Lic. Héctor Terán Terán, 1995-1998;\nARTÍCULO 160 BIS.- Fue adicionado por Decreto No. 129, publicado en el Periódico\nOficial No. 56, Sección III, Tomo CXXIX, de fecha 19 de septiembre de 2022, expedido por la\nH. XXIV Legislatura, siendo Gobernadora Constitucional la C. Marina del Pilar Ávila Olmeda\n2021-2027;\nARTÍCULO 160 TER.- Fue adicionado por Decreto No. 129, publicado en el Periódico\nOficial No. 56, Sección III, Tomo CXXIX, de fecha 19 de septiembre de 2022, expedido por la\nH. XXIV Legislatura, siendo Gobernadora Constitucional la C. Marina del Pilar Ávila Olmeda\n2021-2027;\nARTÍCULO 160 QUATER.- Fue adicionado por Decreto No. 206, publicado en el\nPeriódico Oficial No. 9, Índice, Tomo CXXX, de fecha 17 de febrero de 2023, expedido por la\nH. XXIV Legislatura, siendo Gobernadora Constitucional la C. Marina del Pilar Ávila Olmeda\n2021-2027;\nARTÍCULO 162.- Fue reformado por Decreto No. 325, Publicado en el Periódico\nOficial No. 58, de fecha 28 de diciembre de 2009, Sección II, Tomo CXVI, expedido por la H.\nXIX Legislatura, siendo Gobernador Constitucional el C. José Guadalupe Osuna Millán 20072013;\nARTÍCULO 167.- Fue reformado por Decreto No. 325, Publicado en el Periódico\nOficial No. 58, de fecha 28 de diciembre de 2009, Sección II, Tomo CXVI, expedido por la H.\nXIX Legislatura, siendo Gobernador Constitucional el C. José Guadalupe Osuna Millán 20072013;\nARTÍCULO 170.- Fue reformado por Decreto No. 325, Publicado en el Periódico\nOficial No. 58, de fecha 28 de diciembre de 2009, Sección II, Tomo CXVI, expedido por la H.\nXIX Legislatura, siendo Gobernador Constitucional el C. José Guadalupe Osuna Millán 20072013;\nARTÍCULO 172.- Fue reformado por Decreto No. 216, Publicado en el Periódico siendo Gobernador Constitucional el C. José Guadalupe Osuna Millán 2007-2013;\nARTÍCULO 177.- Fue reformado por Decreto No. 325, Publicado en el Periódico\nXIX Legislatura, siendo Gobernador Constitucional el C. José Guadalupe Osuna Millán 20072013;\nARTÍCULO 181.- Fue reformado por Decreto No. 325, Publicado en el Periódico\nLey de Desarrollo Urbano del Estado de Baja California. Página 95\nXIX Legislatura, siendo Gobernador Constitucional el C. José Guadalupe Osuna Millán 20072013;\nARTÍCULO 185.- Fue reformado por Decreto No. 325, Publicado en el Periódico\nXIX Legislatura, siendo Gobernador Constitucional el C. José Guadalupe Osuna Millán 20072013;\nARTÍCULO 188.- Fue reformado por Decreto No. 206, publicado en el Periódico\nOficial No. 9, Índice, Tomo CXXX, de fecha 17 de febrero de 2023, expedido por la H. XXIV\nLegislatura, siendo Gobernadora Constitucional la C. Marina del Pilar Ávila Olmeda 20212027;\nARTÍCULO 189.- Fue reformado por Decreto No. 325, Publicado en el Periódico\nOficial No. 58, de fecha 28 de diciembre de 2009, Sección II, Tomo CXVI, expedido por la H.\nXIX Legislatura, siendo Gobernador Constitucional el C. José Guadalupe Osuna Millán 20072013; fue reformado por Decreto No. 216, Publicado en el Periódico Oficial No. 28, de fecha\n22 de junio de 2012, Tomo CXIX, expedido por la H. XX Legislatura, siendo Gobernador\nConstitucional el C. José Guadalupe Osuna Millán 2007-2013; fue reformado por Decreto\nNo. 205, publicado en el Periódico Oficial No. 9, Índice, Tomo CXXX, de fecha 17 de febrero de 2023, expedido por la H. XXIV Legislatura, siendo Gobernadora Constitucional la C.\nMarina del Pilar Ávila Olmeda 2021-2027;\nARTÍCULO 190.- Fue reformado por Decreto No. 216, Publicado en el Periódico\nOficial No. 28, de fecha 22 de junio de 2012, Tomo CXIX, expedido por la H. XX Legislatura, siendo Gobernador Constitucional el C. José Guadalupe Osuna Millán 2007-2013;\nARTÍCULO 200.- Fue reformado por Decreto No. 325, Publicado en el Periódico\nOficial No. 58, de fecha 28 de diciembre de 2009, Sección II, Tomo CXVI, expedido por la H.\nXIX Legislatura, siendo Gobernador Constitucional el C. José Guadalupe Osuna Millán 20072013; fue reformado mediante Decreto No. 248, publicado en Periódico Oficial No. 33, de fecha 13 de julio 2018, Sección III, Tomo CXXV, expedido por la H. XXII Legislatura, siendo\nGobernador Constitucional el C. Francisco Arturo Vega de Lamadrid 2013-2019; fue reformado por Decreto No. 279, publicado en el Periódico Oficial No. 51, Sección IV, Tomo\nGobernador Constitucional el C. Jaime Bonilla Valdez 2019-2021;\nARTÍCULO 201.- Fue reformado por Decreto No. 325, Publicado en el Periódico\nXIX Legislatura, siendo Gobernador Constitucional el C. José Guadalupe Osuna Millán 20072013;\nFue adicionado este Capítulo por Decreto No. 572, publicado en el Periódico Oficial No. 44, Ley de Desarrollo Urbano del Estado de Baja California. Página 96\nLegislatura, siendo Gobernador Constitucional el C. Francisco Arturo Vega de Lamadrid\n2013-2019;\nCAPÍTULO TERCERO BIS\nCONTROL DE LA CONTAMINACIÓN LUMÍNICA\nARTÍCULO 212 BIS.- Fue adicionado por Decreto No. 572, publicado en el Periódico\nOficial No. 44, Sección II, Tomo CXXIII, de fecha 30 de septiembre de 201, expedido por la\nH. XXI Legislatura, siendo Gobernador Constitucional el C. Francisco Arturo Vega de\nLamadrid 2013-2019;\nARTÍCULO 212 BIS 1.- Fue adicionado por Decreto No. 572, publicado en el\nPeriódico Oficial No. 44, Sección II, Tomo CXXIII, de fecha 30 de septiembre de 2018, expedido por la H. XXI Legislatura, siendo Gobernador Constitucional el C. Francisco Arturo\nVega de Lamadrid 2013-2019;\nARTÍCULO 215.- Fue reformado por Decreto No. 153, publicado en el Periódico\nOficial No. 10, de fecha 28 de febrero de 2003, Tomo CX, Sección I, expedido por la H. XVII\nLegislatura, siendo Gobernador Constitucional el C. Eugenio Elorduy Walther 2001-2007;\nARTÍCULO 216.- Fue reformado por Decreto No. 153, publicado en el Periódico\nOficial No. 10, de fecha 28 de febrero de 2003, Tomo CX, Sección I, expedido por la H. XVII\nLegislatura, siendo Gobernador Constitucional el C. Eugenio Elorduy Walther 2001-2007;\nARTÍCULO 220.- Fue reformado por Decreto No. 325, Publicado en el Periódico\nOficial No. 58, de fecha 28 de diciembre de 2009, Sección II, Tomo CXVI, expedido por la H.\nXIX Legislatura, siendo Gobernador Constitucional el C. José Guadalupe Osuna Millán 20072013;\nARTÍCULO 223.- Fue reformado por Decreto No. 180, publicado en el Periódico\nOficial No. 10, de fecha 12 de febrero de 2021, Índice, Tomo CXXVIII, expedido por la H.\nXXIII Legislatura, siendo Gobernador Constitucional el C. Jaime Bonilla Valdez 2019-2021;\nARTÍCULO 224.- Fue reformado por Decreto No. 180, publicado en el Periódico\nOficial No. 10, de fecha 12 de febrero de 2021, Índice, Tomo CXXVIII, expedido por la H.\nXXIII Legislatura, siendo Gobernador Constitucional el C. Jaime Bonilla Valdez 2019-2021;\nARTÍCULO 226.- Fue reformado por Decreto No. 180, publicado en el Periódico\nXXIII Legislatura, siendo Gobernador Constitucional el C. Jaime Bonilla Valdez 2019-2021;\nARTÍCULO 227.- Fue reformado por Decreto No. 180, publicado en el Periódico\nXXIII Legislatura, siendo Gobernador Constitucional el C. Jaime Bonilla Valdez 2019-2021;\nARTÍCULO 230.- Fue reformado por Decreto No. 180, publicado en el Periódico\nXXIII Legislatura, siendo Gobernador Constitucional el C. Jaime Bonilla Valdez 2019-2021;\nLey de Desarrollo Urbano del Estado de Baja California. Página 97\nARTÍCULO 231.- Fue reformado por Decreto No. 325, Publicado en el Periódico\nXIX Legislatura, siendo Gobernador Constitucional el C. José Guadalupe Osuna Millán 20072013;\nARTÍCULO 239.- Fue reformado por Decreto No. 325, Publicado en el Periódico\nXIX Legislatura, siendo Gobernador Constitucional el C. José Guadalupe Osuna Millán 20072013;\nARTÍCULO 240.- fue reformado mediante Decreto No. 248, publicado en Periódico\nOficial No. 33, de fecha 13 de julio 2018, Sección III, Tomo CXXV, expedido por la H. XXII\nLegislatura, siendo Gobernador Constitucional el C. Francisco Arturo Vega de Lamadrid\n2013-2019;\nLey de Desarrollo Urbano del Estado de Baja California. Página 98\nARTÍCULOS TRANSITORIOS DEL DECRETO No. 31, POR EL QUE SE\nREFORMAN LOS ARTÍCULOS 3, ADICIONANDOLE UNA FRACCIÓN XVII Y 147,\nADICIONANDOLE UNA FRACCIÓN VII, PUBLICADO EN EL PERIÓDICO OFICIAL No. 45,\nXV LEGISLATURA Y SIENDO GOBERNADOR CONSTITUCIONAL EL C. LIC. HÉCTOR\nTERÁN TERÁN, 1995-1998.\nARTICULO PRIMERO.- Este Decreto entrará en vigor a partir de los tres días siguientes de su publicación en el Periódico Oficial del Estado.\nARTICULO SEGUNDO.- El ejecutivo del Estado ordenará que la elaboración de los programas sectoriales a nivel estatal y regional, se contengan las acciones tendientes a la construcción y adecuación de la infraestructura, el equipamiento y los servicios urbanos que requiera la población discapacitada para su ejecución en todo el Estado, en los términos que establecen las presentes reformas.\nDADO en el Salón de Sesiones Lic. Benito Juárez García del H. Poder Legislativo en la Ciudad de Mexicali, Baja California, a los catorce días del mes de Agosto de mil novecientos noventa y seis.\nLIC. RAMIRO PAZ HERNANDEZ\nDIPUTADO PRESIDENTE\n(RÚBRICA)\nC.P. JUAN ALGRAVEZ URANGA\nDIPUTADO SECRETARIO\n(RÚBRICA)\nDE CONFORMIDAD CON LO DISPUESTO POR LA FRACCION I DEL ARTICULO\n49 DE LA CONSTITUCION POLITICA DEL ESTADO, MANDO SE IMPRIMA, PUBLIQUE,\nOBSERVE Y SE LE DE EL DEBIDO CUMPLIMIENTO.\nMEXICALI, BAJA CALIFORNIA, A LOS TREINTA DIAS DEL MES DE AGOSTO DE\nMIL NOVECIENTOS NOVENTA Y SEIS.\nEL GOBERNADOR CONSTITUCIONAL DEL ESTADO.\nLIC. HECTOR TERÁN TERÁN\n(RÚBRICA)\nEL SECRETARIO GENERAL DE GOBIERNO.\nLIC. RODOLFO VALDEZ GUTIÉRREZ.\n(RÚBRICA)\nLey de Desarrollo Urbano del Estado de Baja California. Página 99\nARTÍCULO ÚNICO TRANSITORIO DEL DECRETO No. 228, POR EL QUE SE\nREFORMA EL ARTÍCULO 153, PUBLICADO EN EL PERIÓDICO OFICIAL No. 45, TOMO\nLEGISLATURA Y SIENDO GOBERNADOR CONSTITUCIONAL EL C. LIC. HÉCTOR\nTERÁN TERÁN, 1995-1998.\nARTICULO UNICO.- Este Decreto entrará en vigor a partir del día siguiente al de su publicación en el Periódico Oficial, Órgano del Gobierno del Estado de Baja California.\nLegislativo, en la Ciudad de Mexicali, Baja California, a los once días del mes de septiembre de mil novecientos noventa y ocho.\nM.V.Z. JOSE MANUEL SALCEDO SAÑUDO\nDIPUTADO PRESIDENTE\n(RÚBRICA).\nC.P. JUAN PABLO VALENZUELA GARCIA\nDIPUTADO SECRETARIO\n(RÚBRICA).\nDE CONFORMIDAD CON LO DISPUESTO POR LA FRACCION I DEL ARTICULO\n49 DE LA CONSTITUCION POLITICA DEL ESTADO, MANDO SE IMPRIMA Y PUBLIQUE.\nMEXICALI, BAJA CALIFORNIA, A LOS VEINTE DIAS DEL MES DE OCTUBRE DE\nMIL NOVECIENTOS NOVENTA Y OCHO.\nEL GOBERNADOR CONSTITUCIONAL DEL ESTADO\nLIC. ALEJANDRO GONZALEZ ALCOCER.\n(RÚBRICA).\nEL OFICIAL MAYOR DE GOBIERNO ENCARGADO\nDE LA SECRETARIA GENERAL DE GOBIERNO\nPOR MINISTRERIO DE LEY.\nLIC. SALVADOR MORALES MUÑOZ\n(RÚBRICA).\nARTÍCULO ÚNICO TRANSITORIO DEL DECRETO NO. 327, POR EL QUE SE\nREFORMA EL ARTÍCULO 145, PUBLICADO EN EL PERIÓDICO OFICIAL NO. 35, DE\nLEGISLATURA, SIENDO GOBERNADOR CONSTITUCIONAL EL C. LIC. ALEJANDRO\nGONZÁLEZ ALCOCER 1998-2001.\nLey de Desarrollo Urbano del Estado de Baja California. Página 100\nPRIMERO.- La presente reforma entrará en vigor el día siguiente de su publicación en el Periódico Oficial del Estado de Baja California. decreto.\nTERCERO.- Los gobiernos Municipales del Estado, en sus respectivos ámbitos de competencias, concertaran con los fraccionadores o promotores inmobiliarios de viviendas de interés social o popular, en sus jurisdicciones territoriales, sobre la previsión de viviendas destinadas para discapacitados en los términos de este Decreto, de acuerdo a los mínimos o máximos que acuerde la autoridad municipal.\nDADO en el Salón de Sesiones \"Lic. Benito Juárez García\" del H. Poder Legislativo, en la Ciudad de Mexicali, Baja California, a los veintinueve días del mes de junio del año dos mil uno.\nDIP. GILBERTO FLORES MUÑOZ\nPRESIDENTE\n(RÚBRICA).\nDIP. OLIVIA VILLALAZ BECERRA\nSECRETARIA\n(RÚBRICA).\nDE CONFORMIDAD CON LO DISPUESTO POR LA FRACCION I DEL ARTICULO\n49 DE LA CONSTITUCION POLITICA DEL ESTADO, MANDO SE IMPRIMA Y PUBLIQUE.\nMEXICALI, BAJA CALIFORNIA, A LOS DIECISIETE DIAS DEL MES DE JULIO DEL\nAÑO DOS MIL UNO.\nEL GOBERNADOR CONSTITUCIONAL DEL ESTADO\nLIC. ALEJANDRO GONZALEZ ALCOCER\n(RÚBRICA).\nEL SECRETARIO GENERAL DE GOBIERNO\nC.P. JORGE RAMOS\n(RÚBRICA).\nARTICULO SEGUNDO TRANSITORIO DEL DECRETO NO. 153, POR EL QUE SE\nREFORMAN LOS ARTICULOS 215 Y 216, PUBLICADO EN EL PERIODICO OFICIAL NO.\nLey de Desarrollo Urbano del Estado de Baja California. Página 101\nXVII LEGISLATURA, SIENDO GOBERNADOR CONSTITUCIONAL EL C. EUGENIO\nELORDUY WALTHER 2001-2007.\nUNICO.- Las presentes reformas y adiciones entrarán en vigor al día siguiente al de su Publicación en el Periódico Oficial del Estado de Baja California.\nDADO en el Salón de Sesiones “Lic. Benito Juárez García” de este Honorable\nPoder Legislativo, en la Ciudad de Mexicali, Baja California, a los doce días del mes de febrero del año dos mil tres.\nDIP. LAURA SANCHEZ MEDRANO\nPRESIDENTA\n(RÚBRICA).\nDIP. JESUS ALEJANDRO RUIZ URIBE\nSECREATARIO\n(RÚBRICA).\nDE CONFORMIDAD CON LO DISPUESTO POR LA FRACCION I DEL ARTICULO\n49 DE LA CONSTITUCION POLITICA DEL ESTADO, IMPRIMASE Y PUBLIQUESE.\nMEXICALI, BAJA CALIFORNIA, A LOS VEINTIUN DIAS DEL MES DE FEBERO DEL\nAÑO DOS MIL TRES.\nGOBERNADOR DEL ESTADO\nEUGENIO ELORDUY WALTHER\n(RÚBRICA).\nSECRETARIO GENERAL DE GOBIERNO\nBERNARDO H. MARTINEZ AGUIRRE\n(RÚBRICA).\nARTÍCULO PRIMERO TRANSITORIO DEL DECRETO No. 325, POR EL QUE SE\nAPRUEBA LA REFORMA A LAS FRACCIONES XX, XXI, XXII, XXIII Y XXIV DEL\nARTÍCULO 6º, LAS FRACCIONES IV Y VI DEL ARTÍCULO 7, LA FRACCIÓN III DEL\nARTÍCULO 9º, LAS FRACCIONES X, XI, XV, XVI, XVII, XXVI Y XXIX DEL ARTÍCULO 10,\nLAS FRACCIONES XIII, XXXIII Y XXXIV DEL ARTÍCULO 11, EL PÁRRAFO PRIMERO Y LA\nFRACCIÓN XII DEL ARTÍCULO 12, EL ARTÍCULO 13, EL PÁRRAFO PRIMERO Y LA\nARTÍCULO 21, LA FRACCIÓN I DEL ARTÍCULO 22, EL ARTÍCULO 23, LA FRACCIÓN I\nNUMERAL 2 DEL ARTÍCULO 24, EL PÁRRAFO SEGUNDO DEL ARTÍCULO 28, LOS\nLey de Desarrollo Urbano del Estado de Baja California. Página 102\nARTÍCULOS 35, 36, EL INCISO B) DE LA FRACCIÓN VII DEL ARTÍCULO 41; EL\nPÁRRAFO PRIMERO DEL ARTÍCULO 43, LOS ARTÍCULOS 45, 46, 73, 77; QUE CAMBIA\nLA DENOMINACIÓN DEL TÍTULO TERCERO Y DEL CAPÍTULO PRIMERO DEL MISMO,\nQUE REFORMA LOS ARTÍCULOS 91, 95, 98, 112, 113, 115 Y 128 PÁRRAFO PRIMERO,\n129 Y EL PÁRRAFO PRIMERO DEL ARTÍCULO 134, 150 FRACCIONES I, II Y III, 162\nFRACCIÓN XII, 167 PÁRRAFO PRIMERO, 170, 177 FRACCIÓN I, 181, 185, 189 PÁRRAFO\nPRIMERO, 200, 201 PÁRRAFO SEGUNDO, 220 FRACCIÓN II, 231 Y 239; Y QUE\nADICIONA LA FRACCIÓN XXV Y XXVI DEL ARTÍCULO 6º Y UN PÁRRAFO SEGUNDO AL\nARTÍCULO 15, DE FECHA 28 DE DICIEMBRE DE 2009, TOMO CXVI, SECCION II,\nEXPEDIDO POR LA H. XIX LEGISLATURA, SIENDO GOBERNADOR CONSTITUCIONAL\nEL C. JOSÉ GUADALUPE OSUNA MILLÁN 2007-2013.\nARTÍCULO TRANSITORIO\nÚNICO.- Las presentes reformas entrarán en vigor al día siguiente de su publicación en el Periódico Oficial del Estado.\nDADO en el Salón de Sesiones “Lic. Benito Juárez García” del H. Poder Legislativo del Estado de Baja California, en la ciudad de Mexicali, B.C., a los nueve días del mes de diciembre de dos mil nueve.\nDIP. ANTONIO RICARDO CANO JIMÉNEZ\nPRESIDENTE\n(RÚBRICA)\nDIP. RUBÉN ERNESTO ARMENTA ZANABIA\nSECRETARIO\n(RÚBRICA)\nDE CONFORMIDAD CON LO DISPUESTO POR LA FRACCION I DEL ARTICULO\n49 DE LA CONSTITUCION POLITICA DEL ESTADO, IMPRIMASE Y PUBLIQUESE.\nMEXICALI, BAJA CALIFORNIA, A LOS VEITIDÓS DIAS DEL MES DE DICIEMBRE\nDEL AÑO DOS MIL NUEVE.\nGOBERNADOR DEL ESTADO\nJOSE GUADALUPE OSUNA MILLAN\n(RÚBRICA)\nSECRETARIO GENERAL DE GOBIERNO\nJOSE FRANCISCO BLAKE MORA\n(RÚBRICA)\nLey de Desarrollo Urbano del Estado de Baja California. Página 103\nARTÍCULO ÚNICO TRANSITORIO DEL DECRETO No. 33, POR EL QUE SE\nAPRUEBA LA REFORMA AL ARTÍCULO 6º Y 117, PUBLICADO EN EL PERIÓDICO\nEXPEDIDO POR LA H. XX LEGISLATURA, SIENDO GOBERNADOR CONSTITUCIONAL\nEL C. JOSÉ GUADALUPE OSUNA MILLN 2007-2013.\nPRIMERO.- Las presentes reformas entraran en vigor al día siguiente de su publicación en el Periódico Oficial del Estado.\nSEGUNDO.- En un plazo de 90 días a partir del día en que inicie su vigencia las presentes reformas, los Ayuntamientos deberán adecuar su marco jurídico reglamentario.\nTERCERO.- Todos los procedimientos que se hayan iniciado antes de la vigencia de las presentes reformas y que no se encuentren concluidos, se regirán conforme a las disposiciones con los que se iniciaron.\nDADO en el Salón de Sesiones “Lic. Benito Juárez García” del H. Poder Legislativo del Estado de Baja California, en la Ciudad de Mexicali, B.C., a los treinta y un días del mes de enero del año dos mil once.\nDIP. NANCY G. SÁNCHEZ ARREDONDO\nPRESIDENTE\n(RÚBRICA)\nDIP. CLAUDIA JOSEFINA AGATÓN MUÑIZ\nSECRETARIO\n(RÚBRICA)\n49 DE LA CONSTITUCION POLITICA DEL ESTADO, IMPRIMASE Y PUBLIQUESE.\nMEXICALI, BAJA CALIFORNIA, A LOS DOS DIAS DEL MES DE FEBRERO DEL\nAÑO DOS MIL ONCE.\nGOBERNADOR DEL ESTADO\nJOSE GUADALUPE OSUNA MILLAN\n(RÚBRICA)\nSECRETARIO GENERAL DE GOBIERNO\nJOSE FRANCISCO BLAKE MORA\nLey de Desarrollo Urbano del Estado de Baja California. Página 104\n(RÚBRICA)\nARTÍCULO ÚNICO TRANSITORIO DEL DECRETO No. 211, POR EL QUE SE\nAPRUEBA LA REFORMA AL ARTÍCULO 4, PUBLICADO EN EL PERIÓDICO OFICIAL No.\nXX LEGISLATURA, SIENDO GOBERNADOR CONSTITUCIONAL EL C. JOSÉ\nGUADALUPE OSUNA MILLÁN 2007-2013.\nARTÍCULOS TRANSITORIOS\nPRIMERO.- El presente Decreto entrará en vigor el día de su publicación en el\nPeriódico Oficial del Estado.\nSEGUNDO.- Se derogan todas aquellas disposiciones que se opongan a lo establecido en el presente Decreto.\nDADO en el Salón de Sesiones “Lic. Benito Juárez García” del H. Poder Legislativo del Estado de Baja California, en la Ciudad de Mexicali, B.C., a los quince días del mes de mayo del año dos mil doce.\nDIP. DAVID JORGE LOZANO PÉREZ\n(RÚBRICA)\nDIP. ALFONSO GARZÓN ZATARAIN\n(RÚBRICA)\nDE CONFORMIDAD CON LO DISPUESTO POR LA FRACCIÓN I DEL ARTÍCULO\nMEXICALI, BAJA CALIFORNIA, A LOS DOS DÍAS DEL MES DE MAYO DEL AÑO\nDOS MIL DOCE.\nJOSÉ GUADALUPE OSUNA MILLÁN\nGOBERNADOR DEL ESTADO\n(RÚBRICA)\nCUAUHTÉMOC CARDONA BENAVIDES\nSECRETARIO GENERAL DE GOBIERNO\n(RÚBRICA)\nLey de Desarrollo Urbano del Estado de Baja California. Página 105\nARTÍCULO ÚNICO TRANSITORIO DEL DECRETO No. 216, POR EL QUE SE\nREFORMAN LOS ARTÍCULOS 172, 189 Y 190, PUBLICADO EN EL PERIÓDICO OFICIAL\nLEGISLATURA, SIENDO GOBERNADOR CONSTITUCIONAL EL C. JOSÉ GUADALUPE\nOSUNA MILLÁN 2007-2013.\nTRANSITORIOS\nPRIMERO.- Las presentes reformas entrarán en vigor al día siguiente de su publicación en el Periódico Oficial del Estado.\nSEGUNDO.- En un término que no exceda de 60 días, el Poder Ejecutivo del Estado y los Ayuntamientos harán las modificaciones a sus respectivos reglamentos.\nDADO en el Salón de Sesiones “Lic. Benito Juárez García” del H. Poder Legislativo del Estado de Baja California, en la Ciudad de Mexicali, B.C., a los veintinueve días del mes de mayo del año dos mil doce.\nDIP. DAVID JORGE LOZANO PÉREZ\n(RÚBRICA)\nDIP. ALFONSO GARZÓN ZATARAIN\n(RÚBRICA)\nDE CONFORMIDAD CON LO DISPUESTO POR LA FRACCIÓN I DEL ARTÍCULO\nMEXICALI, BAJA CALIFORNIA, A LOS CINCO DÍAS DEL MES DE JUNIO DEL AÑO\nDOS MIL DOCE.\nJOSÉ GUADALUPE OSUNA MILLÁN\nGOBERNADOR DEL ESTADO\n(RÚBRICA)\nCUAUHTÉMOC CARDONA BENAVIDES\nSECRETARIO GENERAL DE GOBIERNO\n(RÚBRICA)\nARTÍCULO ÚNICO TRANSITORIO DEL DECRETO No. 431, POR EL QUE SE\nADICIONA UNA FRACCIÓN XXVIII AL ARTÍCULO 6, PUBLICADO EN EL PERIÓDICO\nLey de Desarrollo Urbano del Estado de Baja California. Página 106\nXX LEGISLATURA, SIENDO GOBERNADOR CONSTITUCIONAL EL C. JOSÉ\nGUADALUPE OSUNA MILLÁN 2007-2013.\nARTÍCULO TRANSITORIO\nÚNICO.- Las presentes reformas entrarán en vigor al día siguiente de su publicación en el Periódico Oficial del Estado de Baja California.\nDADO en el Salón de Sesiones “Lic. Benito Juárez García” del H. Poder Legislativo del Estado de Baja California, en la Ciudad de Mexicali, B.C., a los veintiséis días del mes de febrero del año dos mil trece.\nDIP. JULIO FELIPE GARCÍA MUÑOZ\nPRESIDENTE\n(RÚBRICA)\nDIP. MARCO ANTONIO VIZCARRA CALDERÓN\nSECRETARIO\n(RÚBRICA)\nDE CONFORMIDAD CON LO DISPUESTO POR LA FRACCIÓN I DEL ARTÍCULO\nMEXICALI, BAJA CALIFORNIA, A LOS CUATRO DÍAS DEL MES DE MARZO DEL\nAÑO DOS MIL TRECE.\nJOSÉ GUADALUPE OSUNA MILLÁN\nGOBERNADOR DEL ESTADO\n(RÚBRICA)\nFRANCISCO ANTONIO GARCÍA BURGOS\nSECRETARIO GENERAL DE GOBIERNO\n(RÚBRICA)\nARTÍCULO ÚNICO TRANSITORIO DEL DECRETO No. 453, POR EL QUE SE\nREFORMAN LAS FRACCIONES I, III Y VI DEL PÁRRAFO QUINTO DEL ARTÍCULO 117,\nTOMO CXX, EXPEDIDO POR LA H. XX LEGISLATURA, SIENDO GOBERNADOR\nCONSTITUCIONAL EL C. JOSÉ GUADALUPE OSUNA MILLÁN 2007-2013.\nLey de Desarrollo Urbano del Estado de Baja California. Página 107\nARTÍCULOS TRANSITORIOS\nPRIMERO.- Las presentes reformas, entrarán en vigor al día siguiente de su publicación en el Periódico Oficial del Estado. los Ayuntamientos harán las modificaciones a sus respectivos reglamentos.\nDADO en el Salón de Sesiones “Lic. Benito Juárez García” del H. Poder Legislativo del Estado de Baja California, en la Ciudad de Mexicali, B.C., a los veintitrés días del mes de abril del año dos mil trece.\nDIP. ALFONSO GARZÓN ZATARAIN\nVICEPRESIDENTE\n(RÚBRICA).\nDIP. MARCO ANTONIO VIZCARRA CALDERÓN\nSECRETARIO\n(RÚBRICA).\nDE CONFORMIDAD CON LO DISPUESTO POR LA FRACCIÓN I DEL ARTÍCULO 49\nMEXICALI, BAJA CALIFORNIA, A LOS TREINTA DÍAS DEL MES DE ABRIL DEL\nAÑO DOS MIL TRECE.\nJOSÉ GUADALUPE OSUNA MILLÁN\nGOBERNADOR DEL ESTADO\n(RÚBRICA)\nFRANCISCO ANTONIO GARCÍA BURGOS\nSECRETARIO GENERAL DE GOBIERNO\n(RÚBRICA)\nARTÍCULO ÚNICO TRANSITORIO DEL DECRETO No. 452, POR EL QUE SE\nADICIONA UN SEGUNDO PÁRRAFO AL ARTÍCULO 114, PUBLICADO EN EL PERIÓDICO\nPOR LA H. XX LEGISLATURA, SIENDO GOBERNADOR CONSTITUCIONAL EL C. JOSÉ\nGUADALUPE OSUNA MILLÁN 2007-2013.\nARTÍCULO TRANSITORIO\nLey de Desarrollo Urbano del Estado de Baja California. Página 108\nÚNICO.- La presente reforma entrará en vigor al día siguiente de su publicación en el\nPeriódico Oficial del Estado. del Estado de Baja California, en la Ciudad de Mexicali, B.C., a los veintitrés días del mes de abril del año dos mil trece.\nDIP. ALFONSO GARZÓN ZATARAIN\nVICEPRESIDENTE\n(RÚBRICA).\nDIP. MARCO ANTONIO VIZCARRA CALDERÓN\nSECRETARIO\n(RÚBRICA).\nDE CONFORMIDAD CON LO DISPUESTO POR LA FRACCIÓN I DEL ARTÍCULO 49\nMEXICALI, BAJA CALIFORNIA, A LOS TREINTA DÍAS DEL MES DE ABRIL DEL\nAÑO DOS MIL TRECE.\nJOSÉ GUADALUPE OSUNA MILLÁN\nGOBERNADOR DEL ESTADO\n(RÚBRICA)\nFRANCISCO ANTONIO GARCÍA BURGOS\nSECRETARIO GENERAL DE GOBIERNO\n(RÚBRICA)\nARTÍCULO SEGUNDO TRANSITORIO DEL DECRETO No. 491, POR EL QUE SE\nREFORMAN LOS ARTÍCULOS 6 EN SU FRACCIÓN IV, 103 Y SE ADICIONA UN\nPÁRRAFO TERCERO AL ARTÍCULO 114, PUBLICADO EN EL PERIÓDICO OFICIAL No.\nXX LEGISLATURA, SIENDO GOBERNADOR CONSTITUCIONAL EL C. JOSÉ\nGUADALUPE OSUNA MILLÁN 2007-2013.\nARTÍCULO TRANSITORIO\nÚNICO.- Las presentes reformas entrarán en vigor al día siguiente de su publicación\nLey de Desarrollo Urbano del Estado de Baja California. Página 109 del Estado de Baja California, en la Ciudad de Mexicali, B.C., a los once días del mes de julio del año dos mil trece.\nDIP. GREGORIO CARRANZA HERNÁNDEZ\nPRESIDENTE\n(RÚBRICA)\nDIP. MARCO ANTONIO VIZCARRA CALDERÓN\nSECRETARIO\n(RÚBRICA)\nDE CONFORMIDAD CON LO DISPUESTO POR LA FRACCIÓN I DEL ARTÍCULO 49\nMEXICALI, BAJA CALIFORNIA, A LOS DIECIOCHO DÍAS DEL MES DE JULIO DEL\nAÑO DOS MIL TRECE.\nJOSÉ GUADALUPE OSUNA MILLÁN\nGOBERNADOR DEL ESTADO\n(RÚBRICA)\nFRANCISCO ANTONIO GARCÍA BURGOS\nSECRETARIO GENERAL DE GOBIERNO\n(RÚBRICA)\nARTÍCULO UNICO TRANSITORIO DEL DECRETO No. 218, POR EL QUE SE\nADICIONA UN SEGUNDO PÁRRAFO A LA FRACCIÓN XIX AL ARTÍCULO 11,\nPUBLICADO EN EL PERIÓDICO OFICIAL No. 14, TOMO CXXII, DE FECHA 20 DE MARZO\nDE 2015, EXPEDIDO POR LA H. XXI LEGISLATURA, SIENDO GOBERNADOR\nCONSTITUCIONAL EL C. FRANCISCO ARTURO VEGA DE LA MADRID 2013-2019.\nARTÍCULO TRANSITORIO\nÚNICO.- El presente Decreto entrará en vigor al día siguiente de su publicación en el\nPeriódico Oficial del Estado. del Estado de Baja California, en la Ciudad de Mexicali, B.C., a los diecinueve días del mes de febrero del año dos mil quince.\nLey de Desarrollo Urbano del Estado de Baja California. Página 110\nDIP. FRANCISCO ALCIBIADES GARCÍA LIZARDI\nPRESIDENTE\n(RÚBRICA)\nDIP. ROSALBA LÓPEZ REGALADO\nSECRETARIO\n(RÚBRICA)\nDE CONFORMIDAD CON LO DISPUESTO POR LA FRACCIÓN I DEL ARTÍCULO 49\nMEXICALI, BAJA CALIFORNIA, A LOS TRES DÍAS DEL MES DE MARZO DEL AÑO\nDOS MIL QUINCE.\nFRANCISCO ARTURO VEGA DE LA MADRID\nGOBERNADOR DEL ESTADO\n(RÚBRICA)\nFRANCISCO RUEDA GÓMEZ\nSECRETARIO GENERAL DE GOBIERNO\n(RÚBRICA)\nARTÍCULO UNICO TRANSITORIO DEL DECRETO No. 219, POR EL QUE SE\nREFORMA EL ARTÍCULO 22, PUBLICADO EN EL PERIÓDICO OFICIAL No. 15, SECCIÓN\nII, TOMO CXXII, DE FECHA 27 DE MARZO DE 2015, EXPEDIDO POR LA H. XXI\nLEGISLATURA, SIENDO GOBERNADOR CONSTITUCIONAL EL C. FRANCISCO\nARTURO VEGA DE LAMADRID;\nARTÍCULO TRANSITORIO\nÚNICO.- Las presentes reformas entrarán en vigor al día siguiente de su publicación en el Periódico Oficial del Estado de Baja California. del Estado de Baja California, en la Ciudad de Mexicali, B.C., a los diecinueve días del mes de febrero del año dos mil quince.\nDIP. FCO. ALCIBIADES GARCÍA LIZARDÍ\nPRESIDENTE\n(RÚBRICA)\nDIP. ROSALBA LÓPEZ REGALADO\nSECRETARIO\nLey de Desarrollo Urbano del Estado de Baja California. Página 111\n(RÚBRICA)\nDE CONFORMIDAD CON LO DISPUESTO POR LA FRACCION I DEL ARTÍCULO 49\nMEXICALI, BAJA CALIFORNIA, A LOS TRES DÍAS DEL MES DE MARZO DEL AÑO\nDOS MIL QUINCE.\nFRANCISCO ARTURO VEGA DE LAMADRID\nGOBERNADOR DEL ESTADO\n(RÚBRICA)\nFRANCISCO RUEDA\nSECRETARIO GENERAL DE GOBIERNO\n(RÚBRICA).\nARTÍCULO UNICO TRANSITORIO DEL DECRETO No. 313, POR EL QUE SE\nREFORMA EL ARTÍCULO 4, PUBLICADO EN EL PERIÓDICO OFICIAL No. 39, SECCIÓN\nII, TOMO CXXII, DE FECHA 21 DE AGOSTO DE 2015, EXPEDIDO POR LA H. XXI\nLEGISLATURA, SIENDO GOBERNADOR CONSTITUCIONAL EL C. FRANCISCO\nARTURO VEGA DE LAMADRID;\nARTÍCULO TRANSITORIO\nÚNICO.- La presente reforma entrará en vigor al día siguiente de su publicación en el\nPeriódico Oficial del Estado.\nDADO en el Salón de Sesiones “Lic. Benito Juárez García” del H. Poder Legislativo del Estado de Baja California, en la Ciudad de Mexicali, B.C., a los seis del mes de agosto del año dos mil quince.\nDIP. FCO. JULIO CÉSAR VÁZQUEZ CASTILLO\nPRESIDENTE\n(RÚBRICA)\nDIP. RODOLFO OLIMPO HERNÁNDEZ BOJÓRQUEZ\nSECRETARIO\n(RÚBRICA)\nDE CONFORMIDAD CON LO DISPUESTO POR LA FRACCION I DEL ARTÍCULO 49\nLey de Desarrollo Urbano del Estado de Baja California. Página 112\nMEXICALI, BAJA CALIFORNIA, A LOS DIEZ DÍAS DEL MES DE AGOSTO DEL AÑO\nDOS MIL QUINCE.\nFRANCISCO ARTURO VEGA DE LAMADRID\nGOBERNADOR DEL ESTADO\n(RÚBRICA)\nFRANCISCO RUEDA\nSECRETARIO GENERAL DE GOBIERNO\n(RÚBRICA).\nARTÍCULO UNICO TRANSITORIO DEL DECRETO No. 572, POR EL QUE SE\nADICIONA EL CAPÍTULO TERCERO BIS; PUBLICADO EN EL PERIÓDICO OFICIAL No.\n44, SECCION II, TOMO CXXIII, DE FECHA 30 DE SEPTIEMBRE DE 2016, EXPEDIDO\nPOR LA H. XXI LEGISLATURA, SIENDO GOBERNADOR CONSTITUCIONAL EL C.\nFRANCISCO ARTURO VEGA DE LAMADRID 2013-2019.\nTRANSITORIO\nÚNICO: El presente Decreto entrara en vigor al día siguiente de su publicación en el\nPeriódico Oficial del Estado.\nDADO en el Salón de Sesiones “Lic. Benito Juárez García” del H. Poder Legislativo del Estado de Baja California, en la Ciudad de Mexicali, B.C., al primer día del mes de septiembre del año dos mil dieciséis.\nDIP. MÓNICA BEDOYA SERNA\nPRESIDENTE\n(RÚBRICA).\nDIP. ROSA ISELA PERALTA CASILLAS\nSECRETARIA\n(RÚBRICA).\nDE CONFORMIDAD CON LO DISPUESTO POR LA FRACCION I DEL ARTÍCULO 49\nMEXICALI, BAJA CALIFORNIA, A LOS NUEVE DÍAS DEL MES DE SEPTIEMBRE DEL\nAÑO DOS MIL DIECISÉIS.\nFRANCISCO ARTURO VEGA DE LAMADRID\nGOBERNADOR DEL ESTADO\n(RÚBRICA)\nLey de Desarrollo Urbano del Estado de Baja California. Página 113\nFRANCISCO RUEDA GOMEZ\nSECRETARIO GENERAL DE GOBIERNO\n(RÚBRICA)\nARTÍCULO PRIMERO TRANSITORIO DEL DECRETO No. 248, POR EL QUE SE\nREFORMAN LOS ARTÍCULOS 6, 10, 12, 117, 140, 150, 200, 240 Y SE ADICIONAN LOS\nARTÍCULOS 117 BIS, 150 BIS; PUBLICADO EN EL PERIÓDICO OFICIAL No. 33, TOMO\nCXXV, SECCIÓN III, DE FECHA 13 DE JULIO DE 2018, EXPEDIDO POR LA H. XXII\nLEGISLATURA, SIENDO GOBERNADOR CONSTITUCIONAL EL C. FRANCISCO\nARTURO VEGA DE LAMADRID 2013-2019.\nTRANSITORIOS\nPRIMERO. - Las presentes reformas entrarán en vigor al día siguiente de su publicación en el Periódico Oficial del Estado.\nDADO en el Salón de Sesiones “Lic. Benito Juárez García” del H. Poder Legislativo del Estado de Baja California, en la Ciudad de Mexicali, B.C., a los doce días del mes de julio del año dos mil dieciocho.\nDIP. MARCO A. CORONA BOLAÑOS CACHO\nPRESIDENTE\n(RÚBRICA)\nDIP. VICTORIA BENTLEY DUARTE\nSECRETARIA\n(RÚBRICA)\nDE CONFORMIDAD CON LO DISPUESTO POR LA FRACCIÓN I DEL ARTÍCULO 49\nCALIFORNIA, IMPRÍMASE Y PUBLÍQUESE.\nMEXICALI, BAJA CALIFORNIA, A LOS TRECE DÍAS DEL MES DE JULIO DEL AÑO\nDOS MIL DIECIOCHO.\nFRANCISCO ARTURO VEGA DE LAMADRID\nGOBERNADOR DEL ESTADO\n(RÚBRICA)\nFRANCISCO RUEDA GÓMEZ\nSECRETARIO GENERAL DE GOBIERNO\nLey de Desarrollo Urbano del Estado de Baja California. Página 114\n(RÚBRICA)\nARTÍCULO ÚNICO TRANSITORIO DEL DECRETO No. 347, POR EL QUE SE\nREFORMA EL ARTÍCULO 4; PUBLICADO EN EL PERIÓDICO OFICIAL No. 30, TOMO\nLEGISLATURA, SIENDO GOBERNADOR CONSTITUCIONAL EL C. FRANCISCO\nARTURO VEGA DE LAMADRID 2013-2019.\nTRANSITORIOS\nPRIMERO. - La presente reforma entrará en vigor al día siguiente de su publicación en el Periódico Oficial del Estado.\nDADO en el Salón de Sesiones “Lic. Benito Juárez García” del H. Poder Legislativo del Estado de Baja California, en la Ciudad de Mexicali, B.C., a los dieciséis días del mes de mayo del año dos mil diecinueve.\nDIP. EDGAR BENJAMÍN GÓMEZ MACÍAS\nPRESIDENTE\n(RÚBRICA)\nDIP. ROCÍO LÓPEZ GOROSAVE\nPROSECRETARIA\n(RÚBRICA)\nDE CONFORMIDAD CON LO DISPUESTO POR LA FRACCIÓN I DEL ARTÍCULO 49\nCALIFORNIA, IMPRÍMASE Y PUBLÍQUESE.\nMEXICALI, BAJA CALIFORNIA, A LOS CINCO DÍAS DEL MES DE JULIO DEL AÑO\nDOS MIL DIECINUEVE.\nFRANCISCO ARTURO VEGA DE LAMADRID\nGOBERNADOR DEL ESTADO\n(RÚBRICA)\nFRANCISCO RUEDA GÓMEZ\nSECRETARIO GENERAL DE GOBIERNO\n(RÚBRICA)\nLey de Desarrollo Urbano del Estado de Baja California. Página 115\nARTÍCULO ÚNICO TRANSITORIO DEL DECRETO No. 36, POR EL QUE SE\nREFORMA EL ARTÍCULO 4; PUBLICADO EN EL PERIÓDICO OFICIAL No. 67, TOMO\nXXIII LEGISLATURA, SIENDO GOBERNADOR CONSTITUCIONAL EL C. JAIME BONILLA\nVALDEZ 2019-2021.\nTRANSITORIOS\nARTICULO PRIMERO.- La presente reforma entrará en vigor el día después de su publicación en el Periódico Oficial del Estado.\nARTICULO SEGUNDO.- Los Ayuntamientos del Estado contarán con un plazo de treinta días para dejar sin efecto cualquier normatividad que se haya aprobado para reglamentar la prohibición aquí suprimida.\nDADO en el Salón de Sesiones “Lic. Benito Juárez García” del H. Poder Legislativo del Estado de Baja California, en la Ciudad de Mexicali, B.C., a los 31 días del mes de diciembre del año dos mil diecinueve.\nDIP. VÍCTOR MANUEL MORÁN HERNÁNDEZ\nPRESIDENTE\n(RÚBRICA)\nDIP. CARMEN LETICIA HERNÁNDEZ CARMONA\nSECRETARIA\n(RÚBRICA)\nDE CONFORMIDAD CON LO DISPUESTO POR LA FRACCIÓN I DEL ARTÍCULO 49\nCALIFORNIA, IMPRÍMASE Y PUBLÍQUESE.\nMEXICALI, BAJA CALIFORNIA, A LOS TREINTA Y UN DÍAS DEL MES DE\nDICIEMBRE DEL AÑO DOS MIL DIECINUEVE.\nJAIME BONILLA VALDEZ\nGOBERNADOR DEL ESTADO\n(RÚBRICA)\nAMADOR RODRÍGUEZ LOZANO\nSECRETARIO GENERAL DE GOBIERNO\nLey de Desarrollo Urbano del Estado de Baja California. Página 116\n(RÚBRICA)\nARTÍCULO ÚNICO TRANSITORIO DEL DECRETO No. 180, POR EL QUE SE\nAPRUEBA LA REFORMA A LOS ARTÍCULOS 223. 224, 226, 227 Y 230; PUBLICADO EN\nEL PERIÓDICO OFICIAL No. 10, TOMO CXXVIII, ÍNDICE, DE FECHA 12 DE FEBRERO DE\n2021, EXPEDIDO POR LA H. XXIII LEGISLATURA, SIENDO GOBERNADOR\nCONSTITUCIONAL EL C. JAIME BONILLA VALDEZ 2019-2021.\nTRANSITORIOS\nÚNICO. El presente Decreto entrará en vigor al día siguiente de su publicación en el\nPeriódico Oficial del Estado.\nDADO en Sesión Ordinaria de Clausura Virtual en la Ciudad de Mexicali, B.C., a los treinta días del mes de noviembre del año dos mil veinte.\nDIP. JULIO CÉSAR VÁZQUEZ CASTILLO\nPRESIDENTE\n(RÚBRICA)\nDIP. EVA GRICELDA RODRÍGUEZ\nSECRETARIA\n(RÚBRICA)\nDE CONFORMIDAD CON LO DISPUESTO POR LA FRACCIÓN I DEL ARTÍCULO 49\nCALIFORNIA, IMPRÍMASE Y PUBLÍQUESE.\nMEXICALI, BAJA CALIFORNIA, A LOS DOS DÍAS DEL MES DE DICIEMBRE DEL\nAÑO DOS MIL VEINTE.\nJAIME BONILLA VALDEZ\nGOBERNADOR DEL ESTADO\n(RÚBRICA)\nAMADOR RODRÍGUEZ LOZANO\nSECRETARIO GENERAL DE GOBIERNO\n(RÚBRICA)\nARTÍCULO ÚNICO TRANSITORIO DEL DECRETO No. 279, POR EL QUE SE\nAPRUEBA LA REFORMA QUE MODIFICA LOS ARTÍCULOS 4, 6, 7, 10, 11, 12, 24, 150 Y\nLey de Desarrollo Urbano del Estado de Baja California. Página 117\n200, ASÍ COMO LA ADICIÓN DE LOS ARTÍCULOS 22 BIS, 22 TER, 22 QUATER, 22\nQUINQUIES, 22 SEXIES Y 22 SEPTIES; PUBLICADO EN EL PERIÓDICO OFICIAL No. 51,\nXXIII LEGISLATURA, SIENDO GOBERNADOR CONSTITUCIONAL EL C. JAIME BONILLA\nVALDEZ 2019-2021.\nTRANSITORIOS\nARTÍCULO PRIMERO.- Las presentes reformas entrarán en vigor al día siguiente de su publicación en el Periódico Oficial del Estado de Baja California.\nARTÍCULO SEGUNDO.- Los permisos y licencias de uso de suelo y edificaciones que conforme a la presente reforma sean considerados de impacto estatal, que hayan sido iniciados con anterioridad a la entrada en vigor de la presente reforma, y que no hayan sido resueltos por la autoridad municipal, deberán contar con el dictamen técnico de congruencia.\nARTÍCULO TERCERO.- Dentro del plazo de tres meses contado a partir de la entrada en vigor de la presente reforma, la Secretaría realizará reuniones de coordinación y supervisión con las autoridades municipales en materia de desarrollo urbano para coordinar la implementación de la presente reforma realizando las gestiones necesarias para el efecto de subsanar las irregularidades que detecten en materia de autorizaciones de otorgamiento de permisos y licencias de uso de suelo y edificaciones en las zonas agrícola, pecuaria, agropecuaria, forestal y ambiental.\nDADO en el Salón de Sesiones Benito Juárez García en Sesión Ordinaria de la XXIII\nLegislatura en la Ciudad de Mexicali, B.C., a los veintiún días del mes de julio del año dos mil veintiuno.\nDIP. EVA GRICELDA RODRÍGUEZ\nPRESIDENTE\n(RÚBRICA)\nDIP. MARÍA LUISA VILLALOBOS ÁVILA\nSECRETARIA\n(RÚBRICA)\nDE CONFORMIDAD CON LO DISPUESTO POR LA FRACCIÓN I DEL ARTÍCULO 49\nCALIFORNIA, IMPRÍMASE Y PUBLÍQUESE.\nMEXICALI, BAJA CALIFORNIA, A LOS VEINTITRÉS DÍAS DEL MES DE JULIO DEL\nAÑO DOS MIL VEINTIUNO.\nLey de Desarrollo Urbano del Estado de Baja California. Página 118\nJAIME BONILLA VALDEZ\nGOBERNADOR DEL ESTADO\n(RÚBRICA)\nAMADOR RODRÍGUEZ LOZANO\nSECRETARIO GENERAL DE GOBIERNO\n(RÚBRICA)\nARTÍCULO ÚNICO TRANSITORIO DEL DECRETO No. 260, POR EL QUE SE\nAPRUEBA LA REFORMA A LOS ARTÍCULOS 26 Y 146; PUBLICADO EN EL PERIÓDICO\nOFICIAL No. 57, TOMO CXXVIII, SECCIÓN I, DE FECHA 06 DE AGOSTO DE 2021,\nEXPEDIDO POR LA H. XXIII LEGISLATURA, SIENDO GOBERNADOR CONSTITUCIONAL\nEL C. JAIME BONILLA VALDEZ 2019-2021.\nTRANSITORIOS\nPRIMERO. El presente Decreto entrará en vigor al día siguiente de su publicación en el Periódico Oficial del Estado.\nSEGUNDO. La Secretaría de Infraestructura, Desarrollo Urbano y Reordenación\nTerritorial y los Municipios deberán realizar las gestiones necesarias para la actualización de sus portales institucionales, contando con un plazo de 180 días a partir de la entrada en vigor del presente decreto.\nDADO en Sesión Ordinaria Virtual en la Ciudad de Mexicali, B.C., a los dieciséis días del mes de junio del año dos mil veintiuno.\nDIP. EVA GRICELDA RODRÍGUEZ\nPRESIDENTA\n(RÚBRICA)\nDIP. MARÍA LUISA VILLALOBOS ÁVILA\nSECRETARIA\n(RÚBRICA)\nDE CONFORMIDAD CON LO DISPUESTO POR LA FRACCIÓN I DEL ARTÍCULO 49\nCALIFORNIA, IMPRÍMASE Y PUBLÍQUESE.\nMEXICALI, BAJA CALIFORNIA, AL DÍA PRIMERO DEL MES DE JULIO DEL AÑO\nDOS MIL VEINTIUNO.\nLey de Desarrollo Urbano del Estado de Baja California. Página 119\nJAIME BONILLA VALDEZ\nGOBERNADOR DEL ESTADO\n(RÚBRICA)\nAMADOR RODRÍGUEZ LOZANO\nSECRETARIO GENERAL DE GOBIERNO\n(RÚBRICA)\nARTÍCULO SEGUNDO TRANSITORIO DEL DECRETO No. 129, POR EL QUE SE\nAPRUEBA LA REFORMA DE LOS ARTÍCULOS 6, 39, 53, 56, 72, 103, 104, 114, 147, ASÍ\nCOMO LA ADICIÓN DE LOS ARTÍCULOS 160 BIS Y 160 TER; PUBLICADO EN EL\nPERIÓDICO OFICIAL No. 56, TOMO CXXIX, SECCIÓN III, DE FECHA 19 DE\nSEPTIEMBRE DE 2022, EXPEDIDO POR LA H. XXIV LEGISLATURA, SIENDO\nGOBERNADORA CONSTITUCIONAL LA C. MARINA DEL PILAR ÁVILA OLMEDA 2021-\n2027.\nTRANSITORIOS\nPRIMERO.- La presente reforma entrará en vigor al día siguiente de su publicación en el Periódico Oficial del Estado de Baja California.\nSEGUNDO.- El Ejecutivo del Estado y los Ayuntamientos deberán ajustar su reglamentación dentro de los tres meses siguientes al inicio de su vigencia de esta Reforma.\nTERCERO.- Los procedimientos relacionados con la autorización de proyectos ejecutivos de acciones de urbanización en trámite al inicio de la vigencia de este decreto se sustanciarán conforme a las normas vigentes al momento de la presentación de la solicitud a que se refiere el artículo 172 de la Ley de Desarrollo Urbano del Estado de Baja California.\nDADO en Sesión Ordinaria de la XXIV Legislatura en la Ciudad de Mexicali, B.C., a los veinticinco días del mes de agosto del año dos mil veintidós.\nDIP. ALEJANDRA MARÍA ANG HERNÁNDEZ\nPRESIDENTA\n(RÚBRICA)\nDIP. DUNNIA MONTSERRAT MURILLO LÓPEZ\nSECRETARIA\n(RÚBRICA)\nLey de Desarrollo Urbano del Estado de Baja California. Página 120\nDE CONFORMIDAD CON LO DISPUESTO POR LA FRACCIÓN I DEL ARTÍCULO 49\nCALIFORNIA, IMPRÍMASE Y PUBLÍQUESE.\nMEXICALI, BAJA CALIFORNIA, A LOS CINCO DÍAS DEL MES DE SEPTIEMBRE DEL\nAÑO DOS MIL VEINTIDÓS.\nMARINA DEL PILAR ÁVILA OLMEDA\nGOBERNADORA DEL ESTADO\nDE BAJA CALIFORNIA\n(RÚBRICA)\nCATALINO ZAVALA MÁRQUEZ\nSECRETARIO GENERAL DE GOBIERNO\nDEL ESTADO DE BAJA CALIFORNIA\n(RÚBRICA)\nARTÍCULO ÚNICO TRANSITORIO DEL DECRETO No. 197, POR EL QUE SE\nAPRUEBA LA REFORMA AL ARTÍCULO 4; PUBLICADO EN EL PERIÓDICO OFICIAL No.\n76, DE FECHA 19 DE SEPTIEMBRE DE 2022, SECCIÓN III, TOMO CXXIX, EXPEDIDO\nPOR LA H. XXIV LEGISLATURA, SIENDO GOBERNADORA CONSTITUCIONAL LA C.\nMARINA DEL PILAR ÁVILA OLMEDA 2021-2027.\nTRANSITORIOS\nÚNICO.- La presente reforma entrará en vigor al día siguiente al de su publicación en el Periódico Oficial del Estado de Baja California.\nDADO en Sesión Ordinaria de la XXIV Legislatura en la Ciudad de Mexicali, B.C., a los veinte días del mes de diciembre del año dos mil veintidós.\nDIP. MARÍA DEL ROCÍO ADAME MUÑOZ\nPRESIDENTA\n(RÚBRICA)\nDIP. DUNNIA MONTSERRAT MURILLO LÓPEZ\nSECRETARIA\n(RÚBRICA)\nDE CONFORMIDAD CON LO DISPUESTO POR LA FRACCIÓN I DEL ARTÍCULO 49\nCALIFORNIA, IMPRÍMASE Y PUBLÍQUESE.\nLey de Desarrollo Urbano del Estado de Baja California. Página 121\nMEXICALI, BAJA CALIFORNIA, A LOS VEINTIÚN DÍAS DEL MES DE DICIEMBRE\nDEL AÑO DOS MIL VEINTIDÓS.\nMARINA DEL PILAR ÁVILA OLMEDA\nGOBERNADORA DEL ESTADO\nDE BAJA CALIFORNIA\n(RÚBRICA)\nCATALINO ZAVALA MÁRQUEZ\nSECRETARIO GENERAL DE GOBIERNO\nDEL ESTADO DE BAJA CALIFORNIA\n(RÚBRICA)\nARTÍCULO ÚNICO TRANSITORIO DEL DECRETO No. 205, POR EL QUE SE\nAPRUEBA LA REFORMA AL ARTÍCULO 189; PUBLICADO EN EL PERIÓDICO OFICIAL\nNo. 9, DE FECHA 17 DE FEBRERO DE 2023, ÍNDICE, TOMO CXXX, EXPEDIDO POR LA\nH. XXIV LEGISLATURA, SIENDO GOBERNADORA CONSTITUCIONAL LA C. MARINA\nDEL PILAR ÁVILA OLMEDA 2021-2027.\nTRANSITORIOS\nÚNICO.- El presente Decreto entrará en vigor al día siguiente de su publicación en el\nPeriódico Oficial del Estado.\nDADO en Sesión Ordinaria de la XXIV Legislatura en la Ciudad de Mexicali, B.C., a los dos días del mes de febrero del año dos mil veintitrés.\nDIP. MARÍA DEL ROCÍO ADAME MUÑOZ\nPRESIDENTA\n(RÚBRICA)\nDIP. DUNNIA MONTSERRAT MURILLO LÓPEZ\nSECRETARIA\n(RÚBRICA)\nDE CONFORMIDAD CON LO DISPUESTO POR LA FRACCIÓN I DEL ARTÍCULO 49\nCALIFORNIA, IMPRÍMASE Y PUBLÍQUESE.\nMEXICALI, BAJA CALIFORNIA, A LOS TRES DÍAS DEL MES DE FEBRERO DEL\nAÑO DOS MIL VEINTITRÉS.\nLey de Desarrollo Urbano del Estado de Baja California. Página 122\nMARINA DEL PILAR ÁVILA OLMEDA\nGOBERNADORA DEL ESTADO\nDE BAJA CALIFORNIA\n(RÚBRICA)\nCATALINO ZAVALA MÁRQUEZ\nSECRETARIO GENERAL DE GOBIERNO\nDEL ESTADO DE BAJA CALIFORNIA\n(RÚBRICA)\nARTÍCULO ÚNICO TRANSITORIO DEL DECRETO No. 206, POR EL QUE SE\nAPRUEBA LA REFORMA AL ARTÍCULO 188, ASÍ COMO LA ADICIÓN DEL ARTÍCULO\n160 QUATER; PUBLICADO EN EL PERIÓDICO OFICIAL No. 9, DE FECHA 17 DE\nFEBRERO DE 2023, ÍNDICE, TOMO CXXX, EXPEDIDO POR LA H. XXIV LEGISLATURA,\nSIENDO GOBERNADORA CONSTITUCIONAL LA C. MARINA DEL PILAR ÁVILA OLMEDA\n2021-2027.\nTRANSITORIOS\nPRIMERO. El presente decreto entrará en vigor al día siguiente de su publicación en el Periódico Oficial del Estado de Baja California.\nSEGUNDO. Una vez entrado en vigor el presente decreto los Ayuntamientos del\nEstado contarán con 45 días hábiles para modificar y adecuar la reglamentación correspondiente.\nTERCERO. Los fraccionamientos, en la modalidad de acceso controlado, que existan desde antes de la entrada en vigor del presente decreto, tendrán un plazo de 180 días anterior para cumplir con el presente Decreto.\nDADO en Sesión Ordinaria de la XXIV Legislatura en la Ciudad de Mexicali, B.C., a los dos días del mes de febrero del año dos mil veintitrés.\nDIP. MARÍA DEL ROCÍO ADAME MUÑOZ\nPRESIDENTA\n(RÚBRICA)\nDIP. DUNNIA MONTSERRAT MURILLO LÓPEZ\nSECRETARIA\nLey de Desarrollo Urbano del Estado de Baja California. Página 123\n(RÚBRICA)\nDE CONFORMIDAD CON LO DISPUESTO POR LA FRACCIÓN I DEL ARTÍCULO 49\nCALIFORNIA, IMPRÍMASE Y PUBLÍQUESE.\nMEXICALI, BAJA CALIFORNIA, A LOS TRES DÍAS DEL MES DE FEBRERO DEL\nAÑO DOS MIL VEINTITRÉS.\nMARINA DEL PILAR ÁVILA OLMEDA\nGOBERNADORA DEL ESTADO\nDE BAJA CALIFORNIA\n(RÚBRICA)\nCATALINO ZAVALA MÁRQUEZ\nSECRETARIO GENERAL DE GOBIERNO\nDEL ESTADO DE BAJA CALIFORNIA\n(RÚBRICA)\nARTÍCULO ÚNICO TRANSITORIO DEL DECRETO No. 240, POR EL QUE SE\nREFORMA LA FRACCIÓN V DEL ARTÍCULO 147; PUBLICADO EN EL PERIÓDICO\nOFICIAL No. 37, ÍNDICE, DE FECHA 23 DE JUNIO DE 2023, TOMO CXXX, EXPEDIDO\nPOR LA H. XXIV LEGISLATURA, SIENDO GOBERNADORA CONSTITUCIONAL LA C.\nMARINA DEL PILAR ÁVILA OLMEDA 2021-2027.\nARTICULO TRANSITORIO\nÚNICO.- La presente reforma entrará en vigor al día siguiente de su publicación en el\nPeriódico Oficial del Estado de Baja California.\nDADO en Sesión Ordinaria de la XXIV Legislatura en la Ciudad de Mexicali, B.C., a los ocho días del mes de junio del año dos mil veintitrés.\nDIP. MANUEL GUERRERO LUNA\nPRESIDENTE\n(RÚBRICA)\nDIP. ALEJANDRA MARÍA ANG HERNÁNDEZ\nSECRETARIA\n(RÚBRICA)\nDE CONFORMIDAD CON LO DISPUESTO POR LA FRACCIÓN I DEL ARTÍCULO 49\nBAJA CALIFORNIA, IMPRÍMASE Y PUBLÍQUESE.\nLey de Desarrollo Urbano del Estado de Baja California. Página 124\nMEXICALI, BAJA CALIFORNIA, A LOS NUEVE DÍAS DEL MES DE JUNIO DEL AÑO DOS\nMIL VEINTITRÉS.\nMARINA DEL PILAR ÁVILA OLMEDA\nGOBERNADOR DEL ESTADO\nDE BAJA CALIFORNIA\n(RÚBRICA)\nCATALINO ZAVALA MÁRQUEZ\nSECRETARIO GENERAL DE GOBIERNO\nDEL ESTADO DE BAJA CALIFORNIA\n(RÚBRICA)\nARTÍCULO ÚNICO TRANSITORIO DEL DECRETO No. 369, POR EL QUE SE\nAPRUEBA LA REFORMA A LOS ARTÍCULOS 3 Y 147; PUBLICADO EN EL PERIÓDICO\nOFICIAL No. 5, DE FECHA 26 DE ENERO DE 2024, ÍNDICE, TOMO CXXXI, EXPEDIDO\nPOR LA H. XXIV LEGISLATURA, SIENDO GOBERNADORA CONSTITUCIONAL LA C.\nMARINA DEL PILAR ÁVILA OLMEDA 2021-2027.\nTRANSITORIO\nÚNICO.- El presente Decreto entrará en vigor al día siguiente de su publicación en el\nPeriódico Oficial del Estado.\nDADO en Sesión Ordinaria de la XXIV Legislatura en la Ciudad de Mexicali, B.C., a los once días del mes de enero del año dos mil veinticuatro.\nDIP. ARACELI GERALDO NÚÑEZ\nPRESIDENTA\n(RÚBRICA)\nDIP. MANUEL GUERRERO LUNA\nSECRETARIO\n(RÚBRICA)\nDE CONFORMIDAD CON LO DISPUESTO POR LA FRACCIÓN I DEL ARTÍCULO 49\nCALIFORNIA, IMPRÍMASE Y PUBLÍQUESE.\nMEXICALI, BAJA CALIFORNIA, A LOS DOCE DÍAS DEL MES DE ENERO DEL AÑO\nDOS MIL VEINTICUATRO.\nLey de Desarrollo Urbano del Estado de Baja California. Página 125\nMARINA DEL PILAR ÁVILA OLMEDA\nGOBERNADORA DEL ESTADO\nDE BAJA CALIFORNIA\n(RÚBRICA)\nALFREDO ÁLVAREZ CÁRDENAS\nSECRETARIO GENERAL DE GOBIERNO\nDEL ESTADO DE BAJA CALIFORNIA\n(RÚBRICA)\nARTÍCULO ÚNICO TRANSITORIO DEL DECRETO No. 452, POR EL QUE SE\nAPRUEBA LA REFORMA AL ARTÍCULO 6; PUBLICADO EN EL PERIÓDICO OFICIAL No.\n40, ÍNDICE, DE FECHA 16 DE AGOSTO DE 2024, TOMO CXXXI, EXPEDIDO POR LA H.\nXXIV LEGISLATURA, SIENDO GOBERNADORA CONSTITUCIONAL LA C. MARINA DEL\nPILAR ÁVILA OLMEDA 2021-2027.\nTRANSITORIO\nÚNICO.- Las presentes reformas entrarán en vigor al día siguiente de su publicación en el\nPeriódico Oficial del Estado de Baja California.\nDADO en Sesión Ordinaria de la XXIV Legislatura en la Ciudad de Mexicali, B.C., a los veinticinco días del mes de julio del año dos mil veinticuatro.\nDIP. RAMÓN VÁZQUEZ VALADEZ\nPRESIDENTE\n(RÚBRICA)\nDIP. MANUEL GUERRERO LUNA\nSECRETARIO\n(RÚBRICA)\nDE CONFORMIDAD CON LO DISPUESTO POR LA FRACCIÓN I DEL ARTÍCULO 49\nCALIFORNIA, IMPRÍMASE Y PUBLÍQUESE.\nMEXICALI, BAJA CALIFORNIA, AL DÍA PRIMERO DEL MES DE AGOSTO DEL AÑO\nDOS MIL VEINTICUATRO.\nMARINA DEL PILAR ÁVILA OLMEDA\nGOBERNADORA DEL ESTADO\nDE BAJA CALIFORNIA\n(RÚBRICA)\nALFREDO ÁLVAREZ CÁRDENAS\nSECRETARIO GENERAL DE GOBIERNO\nLey de Desarrollo Urbano del Estado de Baja California. Página 126\nDEL ESTADO DE BAJA CALIFORNIA\n(RÚBRICA)\nARTÍCULO ÚNICO TRANSITORIO DEL DECRETO No. 54, POR EL QUE SE\nAPRUEBA LA REFORMA DEL ARTÍCULO 114, ASÍ COMO LA ADICIÓN DEL ARTÍCULO\n114 BIS; PUBLICADO EN EL PERIÓDICO OFICIAL No. 15, ÍNDICE, DE FECHA 14 DE\nMARZO DE 2025, TOMO CXXXII, EXPEDIDO POR LA H. XXV LEGISLATURA, SIENDO\nGOBERNADORA CONSTITUCIONAL LA C. MARINA DEL PILAR ÁVILA OLMEDA 2021-\n2027.\nTRANSITORIO\nÚNICO.- La presente reforma entrará en vigor al día siguiente de su publicación en el\nPeriódico Oficial del Estado.\nDADO en Sesión Ordinaria de la XXV Legislatura en la Ciudad de Mexicali, B.C., a los veintisiete días del mes de febrero del año dos mil veinticinco.\nDIP. EVELYN SÁNCHEZ SÁNCHEZ\nPRESIDENTA\n(RÚBRICA)\nDIP. MICHELLE ALEJANDRA TEJEDA MEDINA\nSECRETARIA\n(RÚBRICA)\nDE CONFORMIDAD CON LO DISPUESTO POR LA FRACCIÓN I DEL ARTÍCULO 49\nCALIFORNIA, IMPRÍMASE Y PUBLÍQUESE.\nMEXICALI, BAJA CALIFORNIA, A LOS TRES DÍAS DEL MES DE MARZO DEL AÑO\nDOS MIL VEINTICINCO.\nMARINA DEL PILAR ÁVILA OLMEDA\nGOBERNADORA DEL ESTADO\nDE BAJA CALIFORNIA\n(RÚBRICA)\nALFREDO ÁLVAREZ CÁRDENAS\nSECRETARIO GENERAL DE GOBIERNO\nDEL ESTADO DE BAJA CALIFORNIA\n(RÚBRICA)\nLey de Desarrollo Urbano del Estado de Baja California. Página 127",
  "ordenamiento": "REGLAMENTO",
  "jurisdiccion": "BAJA CALIFORNIA",
  "fuente_oficial": "Periódico Oficial",
  "FECHA PER OFIC": "2025/03/14",
  "ESTATUS": "VIGENTE",
  "TOMO": "TOMO_VII",
  "URL": "https://www.congresobc.gob.mx/Documentos/ProcesoParlamentario/Leyes/TOMO_VII/20250314_LEYDESUR.PDF",
  "es_escaneado": false,
  "tiene_tablas": true,
  "materia": [
    "ambiental",
    "urbanismo",
    "infraestructura"
  ]
}