{
  "titulo": "Ley DE INGRESOS DEL MUNICIPIO DE SAN FELIPE, BAJA CALIFORNIA PARA EL EJERCICIO FISCAL DEL 2025",
  "Contenido": "BAJA CALIFORNIA, EN USO DE LAS FACULTADES QUE LE CONFIERE EL ARTÍCULO\nSOBERANO DE BAJA CALIFORNIA, TIENE A BIEN APROBAR LA SIGUIENTE:\nLEY DE INGRESOS DEL MUNICIPIO\nDE SAN FELIPE, BAJA CALIFORNIA\nPARA EL EJERCICIO FISCAL DEL 2025\nTÍTULO PRIMERO\nDISPOSICIONES PRELIMINARES\nCAPÍTULO ÚNICO\nDE LOS INGRESOS\nARTÍCULO 1.- La presente Ley es de orden público y de interés social, y tiene por objeto establecer los ingresos que percibirá la Hacienda\nPública del Municipio de San Felipe, Estado de Baja California durante el ejercicio fiscal del 1o. de Enero al 31 de Diciembre del 2025, y serán los que se obtengan por los siguientes conceptos en cantidades estimadas que a continuación se enumeran:\n1 IMPUESTOS $ 53,542,500\n1 IMPUESTOS SOBRE LOS INGRESOS\n2 IMPUESTOS SOBRE EL PATRIMONIO $ 43,219,500\n01 Impuesto Predial $25,419,500\n02 Impuesto sobre Adquisición de\nInmuebles $ 17,800,000\n3 IMPUESTOS SOBRE LA PRODUCCIÓN, 0\nEL CONSUMO Y LAS TRANSACCIONES\n4 IMPUESTOS AL COMERCIO EXTERIOR 0\n5 IMPUESTOS SOBRE NÓMINAS Y\nASIMILABLES 0\n6 IMPUESTOS ECOLÓGICOS 0\n7 ACCESORIOS DE IMPUESTOS $ 2,035,000\n01 Accesorios de Impuestos $ 2,035,000\n8 OTROS IMPUESTOS $ 288,000\n01 Impuesto sobre Asistencia a\nDiversiones y Espectáculos\nPúblicos $ 288,000\n02 Impuesto para el Mantenimiento y\nConservación de las Vías\nPúblicas Municipales $ 0\n03 Impuesto a Centros de Apuestas, Apuestas Remotas, Salas de\nSorteo, de Números y/o Casinos $ 0\n9 IMPUESTOS NO COMPRENDIDOS EN LA\nLEY DE INGRESOS VIGENTE, CAUSADOS\nEN EJERCICIOS FISCALES ANTERIORES\nPENDIENTES DE LIQUIDACIÓN O PAGO $ 8,000,000\n01 Impuestos causados en ejercicios anteriores pendientes de liquidación o pago $ 8,000,000\n2 CUOTAS Y APORTACIONES DE SEGURIDAD SOCIAL $ 0\n1 APORTACIONES PARA FONDOS DE 0\nVIVIENDA\n2 CUOTAS PARA LA SEGURIDAD SOCIAL 0\n3 CUOTAS DE AHORRO PARA EL RETIRO 0\n4 OTRAS CUOTAS Y APORTACIONES\nPARA LA SEGURIDAD SOCIAL $ 0\n01 Otras Cuotas y Aportaciones de\nRecuperación de Servicios\nMédicos $ 0\n5 ACCESORIOS DE CUOTAS Y\nAPORTACIONES DE SEGURIDAD\nSOCIAL 0\n3 CONTRIBUCIONES DE MEJORAS 0\n1 CONTRIBUCIONES DE MEJORAS POR\nOBRAS PÚBLICAS 0\n01 Aportaciones de Particulares para Obras Públicas Municipales 0\n2 CONTRIBUCIONES DE MEJORAS NO\nCOMPRENDIDAS EN LA LEY DE\nINGRESOS VIGENTE, CAUSADAS EN\nEJERCICIOS FISCALES ANTERIORES\nPENDIENTES DE LIQUIDACIÓN O PAGO 0\n01 Aportaciones de Particulares para Obras Públicas Municipales de Ejercicios Anteriores 0\n4 DERECHOS $ 26,414,050\n1 DERECHOS POR EL USO, GOCE,\nAPROVECHAMIENTO O EXPLOTACIÓN DE\nBIENES DE DOMINIO PÚBLICO 0\n2 DERECHOS POR PRESTACIÓN DE\nSERVICIOS $ 23,931,050\n01 Exención de Derechos a\nAsociaciones Civiles sin fines de lucro $ 0\n02 Derecho por Servicio de\nAlumbrado Público $ 2,100,000\n03 Servicios que presta el\nRegistro Civil $ 1,207,350\n04 Por la autorización del Uso u\nOcupación de Vías Públicas para ejercer el comercio o la prestación de servicios, por\nComerciantes Ambulantes, con\nPuestos Semifijos o Mercados\nSobre Ruedas. $ 1,130,000\n05 Por la autorización de la Venta, Almacenaje o Consumo Público de\nBebidas Alcohólicas $ 5,137,200\n06 Por la autorización del funcionamiento de Máquinas\nElectrónicas, Electromecánicas, Mecánicas, Musicales, Digitales, Videojuegos y cualquier tecnología similar $ 0\n07 Por la autorización de la\nInstalación de Máquinas\nExpendedoras de alimentos, Bebidas, productos y similares $ 0\n08 Por la autorización para la\nRealización de Eventos, Espectáculos Públicos y de\nDiversión $ 241,000\n09 Establecimientos para Eventos\nSociales y Fiestas $ 0\n10 Estacionamiento de Vehículos en la Vía Pública y\nEstacionamientos Públicos $ 2,771,800\n11 Servicios que presta Oficialía\nMayor $ 56,400\n12 Servicios que presta Servicios\nMédicos Municipales $ 908,000\n13 Servicios que presta Seguridad\nPública Municipal $ 761,500\n1- Permisos, opiniones y revalidaciones $ 641,500\na) Ingresos de DARE, UMAPEV, ESJUDE,\nK9 $ 120,000\n14 Servicios que presta Bomberos, Protección Civil y Protección al\nAmbiente $ 1,482,500\na) Heroico Cuerpo de Bomberos $ 997,000\nb) Protección Civil $ 124,500\nc) Protección al Ambiente $ 361,000\n15 Servicios que presta\nAdministración Urbana $ 6,120,800\na) Control Urbano $ 1,198,200\nb) Fraccionamientos $ 1,482,000\nc) Tránsito $ 38,600\nd) Catastro Municipal $ 3,402,000\ne) Urbanización Municipal $ 0\n16 Servicios que presta Obras y\nServicios Públicos Municipales $ 49,500\n17 Expedición de otros Certificados, Títulos o Copias de Documentos $ 907,000\n18 Servicios que Presta la\nCoordinación del Deporte y\nCultura Física Municipal y la\nCoordinación Municipal de Arte y\nCultura $ 540,000\n19 Servicios que presta Bienestar\nSocial Municipal $ 24,000\n20 Servicios que presta Turismo y\nConvenciones de San Felipe $ 24,000\n21 Servicios que presta Desarrollo\nIntegral de la Familia Municipal $ 24,000\n3 OTROS DERECHOS $ 0\n4 ACCESORIOS DE DERECHOS $ 2,483,000\n01 Accesorios de Derechos $ 2,483,000\n5 DERECHOS NO COMPRENDIDOS EN LA\nLEY DE INGRESOS VIGENTE,\nCAUSADOS EN EJERCICIOS FISCALES\nANTERIORES PENDIENTES DE\nLIQUIDACIÓN O PAGO 0\n01 Derechos causados en Ejercicios\nAnteriores pendientes de liquidación o pago 0\n5 PRODUCTOS $ 2,035,000\n1 PRODUCTOS $ 2,035,000\n01 Productos $ 2,035,000\n2 PRODUCTOS NO COMPRENDIDOS EN LA\nLEY DE INGRESOS VIGENTE,\nCAUSADOS EN EJERCICIOS FISCALES\nANTERIORES PENDIENTES DE\nLIQUIDACIÓN O PAGO 0\n01 Productos causados en Ejercicios\nAnteriores pendientes de liquidación o pago 0\n6 APROVECHAMIENTOS $ 12,563,600\n1 APROVECHAMIENTOS $ 11,842,600\n01 Multas $ 8,602,500\n02 Reintegros e Indemnizaciones $ 0\n03 Donaciones, Cesiones, Herencias y Legados a Favor del Municipio $ 495,900\n04 Otros Aprovechamientos $ 2,744,200\n2 APROVECHAMIENTOS PATRIMONIALES $ 612,000\n01 Explotación o Arrendamiento de\nBienes Muebles e Inmuebles\nPropiedad del Gobierno\nMunicipal. $ 452,000\n02 Enajenación de Bienes Muebles e\nInmuebles Propiedad del Gobierno\nMunicipal $ 160,000\n03 Otras Actividades del Gobierno\nMunicipal que no correspondan a sus Funciones Propias de\nDerecho Público $ 0\n04 Del Piso 0\n05 Bienes Mostrencos 0\n3 ACCESORIOS DE APROVECHAMIENTOS $ 0\n01 Accesorios de Aprovechamientos $ 0\n4 APROVECHAMIENTOS NO COMPRENDIDOS\nEN LA LEY DE INGRESOS VIGENTE,\nCAUSADOS EN EJERCICIOS FISCALES\nANTERIORES PENDIENTES DE\nLIQUIDACIÓN O PAGO $ 109,000\n01 Aprovechamientos causados en\nEjercicios Anteriores pendientes de liquidación o pago $ 109,000\n7 INGRESOS POR VENTA DE BIENES, PRESTACIÓN DE\nSERVICIOS Y OTROS INGRESOS. $750,000\n1 INGRESOS POR VENTA DE BIENES Y\nPRESTACIÓN DE SERVICIOS DE\nINSTITUCIONES PÚBLICAS DE\nSEGURIDAD SOCIAL. 0\n2 INGRESOS POR VENTA DE BIENES Y\nPRESTACIÓN DE SERVICIOS DE\nEMPRESAS PRODUCTIVAS DEL ESTADO. 0\n3 INGRESOS POR VENTA DE BIENES Y\nPRESTACIÓN DE SERVICIOS DE\nENTIDADES PARAESTATALES Y\nFIDEICOMISOS NO EMPRESARIALES Y\nNO FINANCIEROS. 0\n4 INGRESOS POR VENTA DE BIENES Y\nPRESTACIÓN DE SERVICIOS DE\nENTIDADES PARAESTATALES\nEMPRESARIALES NO FINANCIERAS CON\nPARTICIPACIÓN ESTATAL\nMAYORITARIA. 0\n5 INGRESOS POR VENTA DE BIENES Y\nPRESTACIÓN DE SERVICIOS DE\nENTIDADES PARAESTATALES\nEMPRESARIALES FINANCIERAS\nMONETARIAS CON PARTICIPACIÓN\nESTATAL MAYORITARIA. 0\n6 INGRESOS POR VENTA DE BIENES Y\nPRESTACIÓN DE SERVICIOS DE\nENTIDADES PARAESTATALES\nEMPRESARIALES FINANCIERAS NO\nMONETARIAS CON PARTICIPACIÓN\nESTATAL MAYORITARIA. 0\n7 INGRESOS POR VENTA DE BIENES Y\nPRESTACIÓN DE SERVICIOS DE\nFIDEICOMISOS FINANCIEROS\nPÚBLICOS CON PARTICIPACIÓN\nESTATAL MAYORITARIA. 0\n8 INGRESOS POR VENTA DE BIENES Y\nPRESTACIÓN DE SERVICIOS DE LOS\nPODERES LEGISLATIVO Y JUDICIAL,\nY DE LOS ÓRGANOS AUTÓNOMOS. 0\n9 OTROS INGRESOS\n$750,000\n8 PARTICIPACIONES, APORTACIONES, CONVENIOS,\nY FONDOS DISTINTOS DE APORTACIONES $ 107,690,331\n1 PARTICIPACIONES $ 85,268,842\n01 Participaciones de\nContribuciones Federales 83,849,995\n1 Fondo General de Participación 40,976,829\n2 Fondo de Fomento Municipal 7,033,190\n3 Impuesto sobre gasolina 19,217,951\n4 Impuesto especial sobre productos y servicios 0\n5 Participación de gasolina y diesel 20,252,395\n6 Fondo de compensación ISAN 143,206\n7 Participación ISR 11,049,282\n8 Otras aportaciones federales 4,395,053\n02 Participaciones de\nContribuciones Estatales $ 1,418,887\n1 Fondo Estatal Compensatorio 21,332\n2 Participación Estatal 1,397,555\n2 APORTACIONES $ 19,647,629\n01 Aportaciones Federales del Ramo\n33 $ 19,647,629\n1 Infraestructura Social Municipal 2,545,898\n2 Fortalecimiento Municipal 17,101,731\n02 Otras Aportaciones $ 0\n3 CONVENIOS\n4 INCENTIVOS DERIVADOS DE LA\nCOLABORACIÓN FISCAL\n$ 2,773,860\n1 Derecho Zona Federal $ 2,773,860\n5 FONDOS DISTINTOS DE APORTACIONES\n9 TRANSFERENCIAS, ASIGNACIONES, SUBSIDIOS Y\nSUBVENCIONES, Y PENSIONES Y JUBILACIONES 0\n1 TRANSFERENCIAS Y ASIGNACIONES\n2 SUBSIDIOS Y SUBVENCIONES 0\n01 Subsidios y Subvenciones 0\n3 PENSIONES Y JUBILACIONES 0\n4 TRANSFERENCIAS DEL FONDO\nMEXICANO DEL PETRÓLEO PARA LA\nESTABILIZACIÓN Y EL DESARROLLO 0\n10 INGRESOS DERIVADOS DE FINANCIAMIENTOS 0\n1 ENDEUDAMIENTO INTERNO 0\n2 ENDEUDAMIENTO EXTERNO 0\n3 FINANCIAMIENTO INTERNO 0\nTOTAL DE INGRESOS $ 202,995,481\nTÍTULO SEGUNDO\n1 IMPUESTOS\nCAPÍTULO I\n1 IMPUESTOS SOBRE LOS INGRESOS\n2 IMPUESTOS SOBRE EL PATRIMONIO\n01 IMPUESTO PREDIAL\nARTÍCULO 2.- El Impuesto Predial se causará de acuerdo a lo que se establece en la Ley de Hacienda Municipal y la Ley del Catastro\nInmobiliario, ambas del Estado de Baja California, así como en lo dispuesto por el Reglamento del Catastro Inmobiliario para el Municipio de Mexicali, Baja California o el Reglamento del Catastro Inmobiliario para el Municipio de Ensenada, Baja California, en lo que resulte aplicable atendiendo a la demarcación territorial que le hubiere correspondido, y de conformidad con la Tabla de Valores Catastrales\nUnitarios aprobada por el Consejo Municipal del Catastro Inmobiliario, y aprobada por el Congreso del Estado, para el Municipio de San Felipe, Baja California, y no podrá ser menor a 2.00 veces la Unidad de medida y actualización vigente. catastral unitario, por el número de metros cuadrados que corresponda a la superficie de cada predio, aplicándole las siguientes:\nI.- Predios Baldíos o no edificados............. 9.00 al millar\nII.- Predios que teniendo construcciones, se encuentren en estado de abandono............ 9.00 al millar\nIII.- Predios Comerciales ubicados en plazas y corredores.................................. 6.00 al millar\nIV.- Predios Industriales........................ 6.00 al millar\nV.- Predios Comerciales ubicados en zona Valle 6.00 al millar de San\nFelipe...............................\nVI.- Predios Habitacionales:\na).- En uso exclusivo en el que habite el propietario............................ 3. 0 0 al millar\nCuando el predio sea habitado exclusivamente por su propietario y/o cónyuge, y esté registrado a su nombre, siendo éste pensionado, jubilado, persona con discapacidad, viuda mayor de 50 años, presentando documentación comprobatoria o persona mayor de sesenta años que acredite esta condición con identificación oficial expedida por Institución\nPública, en la que se especifique el domicilio del predio a pagar gozará de un descuento del 50% de la tasa precisada en esta fracción.\nCuando se aplique el beneficio de este inciso, el impuesto predial resultante, no podrá ser menor a 2 veces la Unidad de medida y actualización vigente.\nb).- Predios habitacionales en uso o goce de terceras personas...................... 3. 00 al millar\nVII.- Predios de asociaciones, sociedades u 6.00 veces actividades agropecuarias y pesqueras........ y Actualización\na).- Cuando las asociaciones, sociedades u organizaciones a que se refiere esta fracción, acrediten haber aplicado políticas y prácticas en favor de la equidad de género, tendrán un 30% de descuento.\nVIII.- Predios de asociaciones y sociedades que su actividad principal sea realizar programas\nAsistenciales con fines no lucrativos, siempre y cuando se encuentren debidamente constituidas, registradas, 10.00 veces reconocidas y que los predios se encuentren Unidad de Medida a nombre de éstas....................... y Actualización\na).- Cuando las asociaciones, sociedades u organizaciones a que se refiere esta fracción, acrediten haber aplicado políticas y prácticas en favor de la equidad de género, tendrán un 30% de descuento.\nIX.- Predios sociales, religiosos, educativos y de organizaciones sindicales.................... 6.00 al millar\na).- Los predios Educativos que se encuentren debidamente adscritos ante la Secretaría de Educación Pública, podrán acceder de una disminución de un valor de 1.50 al millar.\nX.- Predios de agrupaciones debidamente constituidas y reconocidas por la autoridad correspondiente.............................. 6.00 al millar\na).- Cuando las asociaciones, sociedades u organizaciones a que se refiere esta fracción, acrediten haber aplicado políticas y prácticas en favor de la equidad de género, tendrán un 30% de descuento.\nXI.- Predios ubicados en zonas habitacionales, para uso industrial, comercial o mixto....... 6.00 al millar\nXII.- Predios ubicados en las Zonas Urbanas de los\nEjidos o Poblados Rurales en uso habitacional exclusivamente.................. 3.00 al millar\nXIII.- Predios de reserva urbana o reserva territorial.................................. 3.00 al millar\na).- Que tengan factibilidad de servicios y no cuenten con los mismos a pie de terreno................................ 6.00 al millar\nb).- Que cuenten con los servicios básicos a pie de terreno....................... 6.00 al millar\nXIV.- Predios dedicados permanentemente a fines:\na).- Agrícolas.............................. 3.00 al millar\nb).- Ganaderos.............................. 3.00 al millar\nc).- Forestal............................... 3.00 al millar\nd).- Acuícola............................... 3.00 al millar\ne).- De extracción de pétreos............... 3.00 al millar\nf).- Arenosos y cerril...................... 3.00 al millar\nXV.- Predios ubicados en zonas urbanas de los ejidos o poblados rurales que no estén destinados a la explotación agropecuaria a la tasa establecida para el uso y destino del suelo.\nXVI.- Predios de propiedad de particulares que se encuentren destinados a un servicio público a cargo del Gobierno Municipal, que se encuentren en proceso o sean destinados para ser donados a favor del Municipio, previa calificación que realice la Autoridad\nFiscal competente............................ 0.00 al millar\nLos predios de Dominio Público, propiedad de la Federación, del Estado o de los Municipios, estarán exentos de pago de conformidad con lo estipulado en el Artículo 75 BIS A Fracción IX de la Ley de Hacienda\nMunicipal del Estado de Baja California, con las excepciones que el mismo establece. o Estatal, siempre que estén destinados total y exclusivamente para organismos, pagarán de acuerdo a la tasa establecida para dicho uso. o por particulares, bajo cualquier título, o la proporción de los mismos que sean utilizados para fines administrativos y no operativos, en el Artículo 115 de la Constitución Política de los Estados Unidos\nMexicanos, pagarán el Impuesto Predial de acuerdo al valor, uso y destino del suelo que sea determinado por Catastro. artículo 2, se establece la siguiente sobre tasa del impuesto predial:\na).- Sobre tasa en apoyo al fomento deportivo y educacional, del 2.00 al millar sobre la base del citado impuesto.\nPara efectos de este artículo se entiende por:\n1).- Predio.- A la porción de terreno, con o sin construcción, limitada por un perímetro, comprendida dentro del\nMunicipio, que constituya una sola propiedad, copropiedad, posesión o usufructo.\n2).- Predio urbano.- Los existentes dentro del límite de la mancha urbana, zonas de transición y de las manchas urbanas de los poblados, que cuenten con acción o acciones de urbanización, con excepción de los predios dedicados permanentemente a fines agrícolas, o los que estén ubicados en las zonas rústicas y contengan construcciones que no se destinen a fines agrícolas, ganaderos, mineros o forestales.\n3).- Predio suburbano.- Es aquel que se encuentra dentro del acción de urbanización, pero que por su ubicación y características es factible de recibirlas. Dentro de esta categoría se consideran las reservas territoriales, que suelo para el desarrollo urbano y la vivienda.\n4).- Predio rústico.- Los predios que no estén comprendidos dentro de los números anteriores 2) y 3).\n5).- Predio no edificado o baldío.- Al que encuadre en cualquiera de los siguientes supuestos:\na).- Al predio urbano que no tenga construcciones y se encuentre improductivo.\nb).- Al predio urbano que teniendo construcciones en proceso, en receso o en estado ruinoso, presente condiciones de inseguridad y se encuentre improductivo.\nc).- Al predio urbano que teniendo construcciones no habitadas por el propietario, al hacerse el avalúo de éstas, resulten con valor inferior al cincuenta por ciento del valor del terreno, en zonas que cuenten como mínimo con servicios de agua, electricidad y drenaje.\nd).- Al predio que teniendo construcciones, éstas sean de carácter provisional, los materiales usados sean de uso transitorio o puedan removerse fácilmente y además se encuentre improductivo.\nPara efectos de lo dispuesto en los incisos anteriores, se entiende que un predio es improductivo cuando, siendo urbano, no sea utilizado con fines habitacionales, educativos, para la realización de actividades comerciales, industriales, de equipamiento o servicios y carezca de de equipamiento y mantenimiento adecuado a su uso.\nNo se consideran predios no edificados o baldíos, los que sean utilizados con fines habitacionales, educativos, comerciales, industriales, de prestación de servicios, aprovechen en la realización de actividades deportivas, siempre y cuando cuenten con la infraestructura, equipamiento e instalaciones necesarias para dicho objeto.\n6).- Predio edificado.- Todos aquellos predios urbanos que no estén especificados en el numeral anterior.\n7).- Predio habitacional.- Todos aquellos dedicados exclusivamente para habitación.\n8).- Predio industrial.- Los que se encuentren comprendidos población, así como los ocupados exclusivamente para la indicada.\n9).- Predio comercial.- Todos aquellos que se dediquen total o parcialmente a giros comercial, así como actividades u oficinas administrativas gubernamentales.\n10).- Predio público.- Aquellos propiedad o posesión de la\nFederación, Estado o Municipio que con base en la Ley aplicable, sean considerados en dominio público.\n11).- Predio educativo.- Los que estén dedicados exclusivamente a alojar instalaciones para la prestación de servicios educativos.\n12).- Predio social.- Todos aquellos de propiedad o posesión particular que se dediquen de manera exclusiva al desarrollo de actividades de beneficencia.\n13).- Predios de agrupaciones.- Los que sea propiedad o posesión de organizaciones sindicales, ejidales, sociedades o asociaciones civiles u otras similares.\n14).- Vía pública.- Todo espacio de uso común que se encuentre destinado o que de hecho se utilice, al libre tránsito de personas, bienes o servicios, a alojar redes de infraestructura urbana a dar acceso, iluminación, ventilación y asoleamiento a los predios que lo delimitan.\nEste espacio está limitado por la superficie engendrada por la generatriz vertical que sigue el alineamiento oficial o el lindero de dicha vía pública.\nApartado. Asimismo, las asociaciones, sociedades u organizaciones, Municipal correspondiente.\nARTÍCULO 3.- El Impuesto Predial se causará y deberá cubrirse anualmente durante los dos primeros meses del año, excepto cuando exceda de cuatro veces la Unidad de Medida y Actualización vigente, que podrá ser cubierto bimestralmente durante los meses de Febrero, Abril, Junio, Agosto, Octubre y Diciembre.\nARTÍCULO 4.- Los contribuyentes que acudan a efectuar el pago del importe anual del Impuesto Predial del presente ejercicio fiscal, Enero, Febrero y Marzo, del año en curso, gozarán de un descuento del\n15%, durante los meses de Enero y Febrero, y del 10% durante el mes de marzo, respectivamente, únicamente respecto del importe total a pagar por concepto del Impuesto Predial, por lo que no se incluye el descuento en la sobre tasa referida en el artículo 2 de esta Ley.\nLos contribuyentes que tengan rezago en el pago del impuesto predial de ejercicios fiscales anteriores, tendrán un descuento del 100% en el mes de enero, 80% en el mes de febrero y 70% en el mes de marzo, en multas y recargos generados, pagando la totalidad del adeudo del\nImpuesto y sobretasa en una sola exhibición durante los meses precitados.\nLos propietarios de predios urbanos baldíos o no edificados, que adquieran el Certificado de Mejoramiento de la Imagen Urbana que expide\nAdministración Urbana, gozarán de hasta un 50% de descuento en el pago del impuesto predial y su impuesto causado en ejercicios anteriores pendientes de liquidación o pago, siempre y cuando no hayan recibido el beneficio a que se refiere el párrafo anterior. El descuento que otorga el certificado podrá aplicarse en forma bimestral.\nLas bases del Certificado de Mejoramiento a la Imagen Urbana, se encuentran establecidas en el Artículo 43, apartado “B” de esta ley.\n02 IMPUESTO SOBRE ADQUISICIÓN DE INMUEBLES.\nARTÍCULO 5.- El Impuesto sobre Adquisición de Inmuebles, se calculará aplicando la tasa del 2%, sobre la base gravable que se determine conforme a la Ley de Hacienda Municipal del Estado de Baja California. encargadas de la regularización de la tenencia de la tierra, y las que desarrollos habitacionales de interés social y popular, pagarán el equivalente a dos Unidades de Medida y Actualización vigente. adquisición del o los inmuebles de que se trate, por causas imputables al solicitante y se compruebe por Recaudación de Rentas Municipal, se\nAdquisición de Inmuebles, aplicando una sanción de 5 Unidades de\nMedida y Actualización vigente. Esta sanción no será procedente cuando municipal, así como en el supuesto previsto en el párrafo anterior\n3 IMPUESTOS SOBRE LA PRODUCCIÓN, EL CONSUMO Y LAS TRANSACCIONES\n4 IMPUESTOS AL COMERCIO EXTERIOR\n5 IMPUESTOS SOBRE NÓMINAS Y ASIMILABLES\n6 IMPUESTOS ECOLÓGICOS\nCAPÍTULO II\n7 ACCESORIOS DE IMPUESTOS\n01 ACCESORIOS DE IMPUESTOS\nARTÍCULO 6.- Son los ingresos que se perciben por concepto de recargos, sanciones, gastos de ejecución, indemnizaciones, entre otros, asociados a los impuestos, cuando éstos no se cubran oportunamente, de conformidad con lo siguiente:\nI.- Recargos por mora: Cuando no se paguen las contribuciones dentro de los plazos señalados en las disposiciones fiscales o no se cubran las parcialidades en los plazos convenidos, se pagarán recargos por mora a la tasa del 2% mensual.\nII.- Recargos por financiamiento: Cuando se conceda prórroga sean cubiertos en parcialidades, se causarán recargos por financiamiento sobre el saldo insoluto a la tasa del 1.5% mensual.\nIII.- Sanciones: Las multas derivadas del incumplimiento en el pago de contribuciones en la forma, fecha y términos que respectivas.\nIV.- Gastos de Ejecución: Cuando las autoridades fiscales la recuperación de los créditos fiscales que correspondan, se estará a lo establecido en el \"Capítulo VIII. De los\nGastos de Ejecución\" de la Ley de Hacienda Municipal del\nEstado de Baja California.\nV.- Otros: Todos aquellos que se encuentren asociados o establecidos en las leyes fiscales.\nCAPÍTULO III\n8 OTROS IMPUESTOS\n01 IMPUESTO SOBRE ASISTENCIA A DIVERSIONES\nY ESPECTÁCULOS PÚBLICOS\nARTÍCULO 7.- Son sujetos de este impuesto, los asistentes a juegos permitidos, espectáculos públicos y centros nocturnos de diversión, así como a las funciones de obras de teatro y circo. No se considerarán objeto de este impuesto, espectáculos públicos presentados en restaurantes, bares, cabarets, salones de fiesta o baile y centros nocturnos, cuando se acredite previamente a la celebración del evento que los ingresos por dichos espectáculos, serán acumulados a los propios del establecimiento.\nARTÍCULO 8.- El impuesto sobre asistencia a diversiones y espectáculos públicos se calculará aplicando la tasa del 5% sobre el precio de admisión.\nCon dos días hábiles de anticipación a la iniciación de los actos generadores de esta contribución, los organizadores de los juegos permitidos y espectáculos, deberán solicitar el permiso correspondiente y garantizar, en su carácter de responsables solidarios con el causante, el crédito fiscal estimado por la Tesorería Municipal, mediante depósito en efectivo, que no será inferior al impuesto correspondiente a un día de actividades, ni superior al que pudiera corresponder también estimativamente a tres días. personal designado por la Tesorería Municipal, quien causará los honorarios que determine la Autoridad fiscal, y que oscilará de entre\n$ 400 a $ 800 pesos por interventor a cargo del promotor u organizador del evento.\nNo se pagará este impuesto, tratándose de eventos realizados por\nPartidos Políticos, siempre y cuando se acredite fehacientemente a través de contrato o declaración de impuestos, 5 días hábiles previos al evento, organizado por el “Partido Político”. que padezcan cáncer en etapa terminal, debidamente registrados ante institución oficial que para tales efectos señale la Ley de la materia, gravarán este impuesto a tasa cero previa autorización del Presidente\nMunicipal de San Felipe, en caso de no contar con ella causarán el impuesto a una tasa del 2.5%.\nTratándose de eventos organizados o que participen en su organización asociaciones civiles con fines no lucrativos, dependencias oficiales y entidades gubernamentales, organismos no gubernamentales u organizaciones que fomenten el deporte debidamente constituidas que tengan por objeto allegarse recursos para el cumplimiento de sus fines, causarán el impuesto a una tasa del 2.5%.\nLos organizadores de los eventos a que se refiere el párrafo anterior podrán exentar el pago hasta en un cien por ciento de este impuesto previa solicitud y autorización del Presidente Municipal de San Felipe.\nSerá obligatorio tratándose de Partidos Políticos, Asociaciones\nCiviles, así como de las Instituciones anteriormente mencionadas en este artículo, que deberán de contar con un representante previamente acreditado ante la Tesorería Municipal, para la verificación de la apertura de los accesos del lugar donde se llevará a cabo el evento, así como para la firma del acta de liquidación y el pago a los\nInterventores comisionados por parte de la Tesorería Municipal del espectáculo o evento realizado y para el cual se hubiere aprobado la exención del impuesto. En el caso de no encontrarse ningún representante por parte de los organizadores del evento, el Interventor\nMunicipal procederá a cancelar la exención del impuesto, cobrando lo estipulado en este artículo. a diversiones y espectáculos públicos, se destinarán a la promoción y vulnerables, a la promoción del sano desarrollo físico, mental y social de la niñez, a través de Desarrollo Integral de la Familia Municipal.\nARTÍCULO 9.- Los organizadores o empresarios de los espectáculos públicos, juegos permitidos, centros de diversión y funciones de obras de teatro o circo, serán solidariamente responsables del pago de este impuesto, debiendo retener al momento de pagar el asistente el boleto de celebrarse éste, previa liquidación o comprobación del ingreso al interventor municipal, en el caso en que sea intervenido el evento, o en su defecto, en la Recaudación Municipal el día hábil siguiente al de la celebración del evento.\n02 IMPUESTO PARA MANTENIMIENTO Y CONSERVACIÓN\nDE LAS VÍAS PÚBLICAS MUNICIPALES\nARTÍCULO 10.- Son sujetos de este impuesto, los propietarios o poseedores de vehículos de motor, que residan dentro del territorio del municipio de San Felipe, Baja California, para contribuir en el mantenimiento y conservación de las vías públicas municipales.\nARTÍCULO 11.- El pago de este impuesto se realizará anualmente y se enterará ante la Recaudación de Rentas o ante las instituciones autorizadas, previo convenio que se celebre con el Ayuntamiento, al momento en que aquellos realicen el trámite de expedición o revalidación de la tarjeta de circulación relativa, conforme a las siguientes tarifas:\nUNIDAD DE MEDIDA Y\nACTUALIZACIÓN VIGENTE\nI.- Vehículos de uso particular................. 6.96 veces\nII.- Camiones de uso particular.................. 11.60 veces\nIII.- Vehículos de transporte público de pasajeros 9.28 veces\nIV.- Camiones de transporte público de pasajeros o carga..................................... 13.92 veces\nV.- Motocicletas................................ 2.00 veces\nLos ingresos que se recauden por este concepto, se destinarán al mantenimiento y conservación de las vías públicas municipales.\n03 IMPUESTO A CENTROS DE APUESTAS, APUESTAS REMOTAS,\nSALAS DE SORTEOS, DE NÚMEROS Y/O CASINOS\nARTÍCULO 12.- Son sujetos de este impuesto los permisionarios que, proceden de los juegos con apuestas y/o habilidades o destrezas, que judicial que haya causado estado, registrados y reconocidos en la página oficial de la citada Secretaría de Gobernación, pagarán este impuesto de acuerdo a lo siguiente: y/o habilidades o destrezas, calcularán este impuesto aplicando la tasa del 3.0% al valor nominal de los billetes, boletos, apuestas y demás comprobantes que permitan la participación o la apuesta, deduciéndose a dicha base gravable el valor del premio efectivamente pagado o entregado a los participantes dentro de los primeros quince días de cada mes.\nCAPÍTULO IV\n9 IMPUESTOS NO COMPRENDIDOS EN LA LEY DE INGRESOS VIGENTE CAUSADOS EN\nEJERCICIOS FISCALES ANTERIORES PENDIENTES DE LIQUIDACIÓN O PAGO.\n01 IMPUESTOS CAUSADOS EN EJERCICIOS ANTERIORES PENDIENTES DE\nLIQUIDACIÓN O PAGO\nARTÍCULO 13.- Los Impuestos no pagados en el ejercicio fiscal en que se causaron se cobrarán como pagos extemporáneos de ejercicios fiscales anteriores, aplicando en cuanto al fondo, las leyes vigentes a la fecha en que se generaron y en cuanto a la forma mediante el procedimiento administrativo de ejecución que establece la Ley de Hacienda Municipal del Estado de Baja California o en su caso, el procedimiento judicial que corresponda.\nEn el caso del Impuesto Predial, cuando el Consejo del Catastro anterioridad, el nuevo valor se aplicará retroactivamente al Impuesto pendiente de pago.\nTÍTULO TERCERO\n2 CUOTAS Y APORTACIONES DE SEGURIDAD SOCIAL\nCAPÍTULO I\n1 APORTACIONES PARA FONDOS DE VIVIENDA\n2 CUOTAS PARA LA SEGURIDAD SOCIAL\n3 CUOTAS DE AHORRO PARA EL RETIRO\n4 OTRAS CUOTAS Y APORTACIONES PARA LA SEGURIDAD SOCIAL.\n01 OTRAS CUOTAS Y APORTACIONES DE RECUPERACIÓN DE SERVICIOS MÉDICOS\nARTÍCULO 14.- Los empleados municipales, que a través de convenio tengan servicios de seguridad social o médica por parte del Municipio, deberán aportar una cuota equivalente al 5% de su salario neto como aportación de recuperación de servicios médicos municipales.\n5 ACCESORIOS DE CUOTAS Y APORTACIONES DE SEGURIDAD SOCIAL\nTÍTULO CUARTO\n3 CONTRIBUCIONES DE MEJORAS\nCAPÍTULO I\n1 CONTRIBUCIONES DE MEJORAS POR OBRAS PÚBLICAS\n01 APORTACIONES DE PARTICULARES PARA OBRAS PÚBLICAS MUNICIPALES\nARTÍCULO 15.- El Gobierno Municipal, por conducto de Administración\nUrbana, obtendrá ingresos por contribuciones de mejoras, conforme a lo que establece la Ley de Urbanización del Estado de Baja California y su Reglamento, derramándose el costo de las obras entre los manera directa por las obras que realice, en proporción a la superficie de los mismos.\nCAPÍTULO II\n2 CONTRIBUCIONES DE MEJORAS NO COMPRENDIDAS EN LA LEY DE INGRESOS\nVIGENTE, CAUSADAS EN EJERCICIOS FISCALES ANTERIORES PENDIENTES DE\nLIQUIDACIÓN O PAGO\n01 APORTACIONES DE PARTICULARES PARA OBRAS PÚBLICAS MUNICIPALES DE\nEJERCICIOS ANTERIORES\nARTÍCULO 16.- Las Contribuciones de Mejoras no pagadas en el ejercicio ejercicios fiscales anteriores, aplicando en cuanto al fondo, las leyes\nHacienda Municipal del Estado de Baja California o en su caso, el procedimiento judicial que corresponda.\nTÍTULO QUINTO\n4 DERECHOS\nCAPÍTULO I\n1 DERECHOS POR EL USO, GOCE, APROVECHAMIENTO O EXPLOTACIÓN DE BIENES\nDEL DOMINIO PÚBLICO\nCAPÍTULO II\n2 DERECHOS POR LA PRESTACIÓN DE SERVICIOS\n01 EXENCIÓN DE DERECHOS A ASOCIACIONES CIVILES SIN FINES DE LUCRO\nARTÍCULO 17.- Se autoriza a las instituciones de asistencia social como\nAsilos, Estancias Infantiles, Casas Hogar, Centros de Atención a\nMigrantes y Centros de Rehabilitación, previo estudio socio económico, la exención en el pago de los derechos correspondientes a los trámites siguientes:\nI.- Factibilidad de Uso de Suelo;\nII.- Dictamen de Uso de Suelo;\nIII.- Acceso vial;\nIV.- Certificación de Deslinde;\nV.- Licencia de Construcción;\nVI.- Terminación de Obra;\nVII.- Inspección de Bomberos;\nVIII.- Plan de Contingencia;\nIX.- Certificación de Dispositivos de Seguridad;\nX.- Licencia Ambiental;\nXI.- Programa Interno de Protección Civil;\nXII.- Inspecciones de Protección Civil;\nXIII.- Capacitaciones de Protección Civil; y\nXIV.- Todos los demás trámites que garanticen la Seguridad de los\nCentros de Asistencia Social.\n02 DERECHO POR SERVICIO DE ALUMBRADO PÚBLICO\nARTÍCULO 18.- En materia de Derechos por Servicio de Alumbrado\nPúblico, se aplicarán las siguientes disposiciones:\nI. Es objeto de este derecho, la prestación del servicio de alumbrado público. Se entiende por servicio de alumbrado público, el servicio de iluminación que las autoridades municipales otorgan a través de la red de alumbrado público, en espacios públicos y vialidades como calles, avenidas, bulevares, caminos vecinales, plazas, parques, jardines y otros lugares de uso común del Municipio de San Felipe.\nII. Son sujetos de este derecho, los beneficiarios del servicio de alumbrado público a que se refiere la fracción anterior, propietarios o poseedores de inmuebles en el Municipio de San Felipe.\nIII. El derecho por el servicio de alumbrado público se causará mensualmente conforme a una cuota fija de $15.00 pesos 00/100 m.n.\nIV. La base de este derecho es el costo anual actualizado del servicio de alumbrado público erogado por el municipio, el cual incluye el consumo de energía eléctrica de las redes de alumbrado público del\nMunicipio de San Felipe, así como la ampliación, instalación, reparación, limpieza y mantenimiento del alumbrado público, la calidad municipio, así como gastos administrativos, sueldos y honorarios del personal directamente involucrado en la prestación del servicio. anual actualizado del ejercicio fiscal inmediato anterior, que\nMunicipio de San Felipe, erogó en la prestación de este servicio y dividido entre el número de sujetos de este derecho, el cociente fue dividido entre 12 para determinar el monto mensual del derecho a pagar.\nSe entiende por costo anual actualizado, la suma que resulte del total año inmediato anterior, por el gasto directamente involucrado con la ocupa el municipio de San Felipe, Baja California, traídos a valor previo al inmediato anterior.\nV. El pago del Derecho por Servicio de Alumbrado Público deberá realizarse dentro de los primeros 10 días siguientes al mes en que se cause, en las oficinas recaudadoras municipales y demás instancias o establecimientos autorizados para tal efecto.\nEl citado plazo y lugar de pago, podrá modificarse o ampliarse en beneficio de los contribuyentes, cuando existan acuerdos entre el\nMunicipio con otras instancias públicas o privadas, que permitan simplificar el entero de la contribución. Para tal efecto, las instancias competentes del Municipio podrán celebrar convenios a través de los cuales se logre lo indicado con anterioridad. El contribuyente aceptará tácitamente esta opción, salvo que haya solicitado expresamente por escrito realizar el pago directamente en las oficinas recaudadoras municipales y demás instancias o establecimientos autorizados para tal efecto. Para el caso de que el contribuyente decida realizar el entero de este derecho en un solo pago, podrá acceder al descuento previsto en el artículo Décimo\nSegundo Transitorio de esta Ley.\nVI. Los ingresos que se perciban por el derecho establecido en este artículo, se destinarán al pago de conceptos que se requieran para el debido servicio, operación y mantenimiento del alumbrado público que proporciona el Municipio, incluyendo su ampliación y renovación, así prestación del servicio.\n03 SERVICIOS QUE PRESTA REGISTRO CIVIL\nARTÍCULO 19.- Los derechos por servicios que preste el Registro Civil, serán pagados por los usuarios, sujetándose a la siguiente tarifa:\nUNIDAD DE MEDIDA Y\nACTUALIZACIÓN VIGENTE\nI.- NACIMIENTOS\na).- Registro en horas hábiles dentro de la oficina............................... EXENTO\nb).- Registro en Institución de Salud....... EXENTO\nc).- Registro en horas inhábiles dentro de la\nOficina previa cita.................... EXENTO\nd).- Por traslado a domicilio para registro en\ne).- Por traslado a domicilio para registro en\nf).- Registro de nacimiento dentro del\nPrograma “Jornadas del Registro\ng).- Registro a domicilio en horas inhábiles, por enfermedad, contingencia o situación extraordinaria, previo certificado médico, declaración oficial o petición oficial de autoridad pública........... EXENTO\nh).- Declaratoria de hechos para registros cuando no lo representa la Procuraduría de Protección de Niñas, Niños y\nAdolescentes............................ 1.20 veces\nLas personas de escasos recursos, sean: mujeres jefas de familia, personas con discapacidad, personas indígenas, pescadoras ribereñas, afrodescendientes y afromexicanos, previa solicitud y estudio la Familia Municipal, tendrán un descuento del 50% en lo que se refiere a los incisos d) y h).\nII.- MATRIMONIOS\na).- Solicitud, trámite y celebración en horas hábiles dentro de la oficina..... 6.61 veces\nb).- Solicitud, trámite y celebración en horas inhábiles dentro de la oficina... 10.58 veces\nc).- Solicitud, trámite y celebración en días inhábiles dentro de la oficina.... 12.60 veces\nd).- Solicitud, trámite y celebración a domicilio en horas hábiles dentro de la zona urbana...................... 26.50 veces\ne).- Solicitud, trámite y celebración a domicilio en horas inhábiles dentro de la zona urbana.................... 33.00 veces\nf).- Solicitud, trámite y celebración a domicilio en días inhábiles dentro de la zona urbana:\na) De 09:00 a 14:00 horas............. 49.00 veces\nb) De 15:00 a 20:00 horas............. 55.00 veces\ng).Solicitud, trámite y celebración a domicilio en horas hábiles fuera de la zona urbana.................. 52.92 veces\nh).- Solicitud, trámite y celebración a domicilio en horas inhábiles fuera de la zona urbana.................. 66.15 veces\ni).- Solicitud de trámite y celebración a domicilio en días inhábiles fuera de la zona urbana:\na) De 09:00 a 14:00 horas............. 79.38 veces\nb) De 15:00 a 20:00 horas............. 85.00 veces\nj).- Solicitud, trámite y celebración fuera de la oficina, pero en lugar asignado por la oficialía....................... 26.46 veces\nk).- Anotación de cambio de régimen matrimonial, registro o modificación a las capitulaciones matrimoniales....... 16.54 veces\nl).- Costo adicional por servicio de celebración urgente, dentro de la oficina...................... 3.96 veces\nm).- Costo adicional por servicio de celebración urgente, fuera de la oficina.............. 16.54 veces\nn).- Formatos oficiales para contraer matrimonio, siendo estos: Solicitud para contraer matrimonio, formato para certificado médico prenupcial y contrato de régimen matrimonial........ 3.31 veces\no).- Constancia de asistencia a pláticas prematrimoniales....................... 2.64 veces\np).- Celebración de matrimonio dentro del programa de Matrimonios Colectivos... EXENTO\nq).- Dentro del Programa Matrimonios\nColectivos los formatos oficiales para contraer matrimonio, siendo estos:\nSolicitud para contraer matrimonio, formato para certificado médico prenupcial y contrato de régimen matrimonial............................ EXENTO\nr).- Dentro del Programa Matrimonios\nColectivos la constancia de asistencia a pláticas prematrimoniales............ EXENTO\nEn caso de cancelación del servicio solicitado, en los incisos a), b),\nc), d), e), f) y g) previstos en esta fracción, se llevará a cabo la devolución del 50% del pago efectuado, siempre y cuando se solicite hasta 5 días anteriores a la fecha en que se llevaría a cabo el matrimonio. discapacidad, problemas motrices, enfermedades terminales, que se\nCivil, la celebración del matrimonio a domicilio o Instituciones de\nSalud, será exento de pago, previa constancia emitida por institución de salud pública, que señale dicha imposibilidad.\nIII.- DEFUNCIONES\na).- Servicio, registro y expedición de 5.29 veces\nOrden de Inhumación y/o cremación en horas hábiles..........................\nb).- Registro y expedición de Orden de\nInhumación y/o cremación en horas inhábiles.............................. 5.98 veces\nc).- Registro y expedición de Orden de\nInhumación y/o cremación en día inhábil................................ 5.98 veces\nd).- Por servicios que preste el Registro\nCivil a panteones particulares en horas hábiles....................... 9.26 veces\ne).- Por servicios que preste el Registro\nCivil a panteones particulares en día\nInhábil......................... 10.73 veces\nf).- Por servicios que preste el Registro\nCivil a panteones particulares en horas inhábiles..................... 11.90 veces\ng).- Servicio, registro y expedición de\nOrden de Traslado de cadáver, cenizas o restos humanos dentro de Territorio\nNacional en días hábiles............... 6.61 veces\nh).- Servicio, registro y expedición de\nOrden de Traslado de cadáver, cenizas o restos humanos dentro de Territorio\nNacional en hora o día inhábil.. 8.82 veces\ni).- Servicio, registro y expedición de\nOrden de Traslado de cadáver, cenizas o restos humanos fuera de Territorio\nNacional................. 18.52 veces\nj).- Servicio, registro y expedición de\nOrden de Traslado de cadáver, cenizas o restos humanos fuera de Territorio\nNacional en hora o día inhábil.. 23.53 veces\nk).- Orden de Exhumación.................... 7.93 veces\nl).- Servicio y registro de defunción por\nPresunción de Muerte................... 5.29 veces\nm).- Servicio, registro y expedición de Orden de inhumación, en fosa común, en hora hábil solicitada por SEMEFO de personas no identificadas o no reclamadas por familiar............................... EXENTO\nn).- Autorización de Inhumación de restos humanos cremados (cenizas) en panteón municipal............................. 2.98 veces\no).- Autorización de Inhumación de restos humanos similares a osamentas, fetos, así como personas nacidas muertas, en panteón\nAnte la declaración de una emergencia sanitaria por la Autoridad competente, los derechos que comprenden los incisos a), b), c), d),\ne), f), g), h), i) y j) de esta fracción, y los accesorios que se causen por dichos conceptos, quedarán exentos de pago en el tiempo que permanezca vigente la emergencia y en los casos en que la defunción sea asociada directamente con dicha emergencia sanitaria.\nEn cumplimiento a la Fracción VIII del Artículo 63 de la Ley sobre\nDesaparición y Búsqueda de Personas para el Estado de Baja California, quedan exentas del pago en lo que se refiere a la Fracción III incisos\na), b), k) y o) de este Artículo, los familiares que soliciten estos servicios respecto de una persona que fuere objeto de búsqueda y localización en términos de dicha Ley, previa comprobación del parentesco.\nIV.- DIVORCIOS\na).- Administrativo.......................... 39.69 veces\nb).- Inscripción de sentencia de divorcio o nulidad de matrimonio proveniente de\nJuzgado................................. 19.84 veces\nV.- ADOPCIONES\na).- Inscripción de Sentencia de Adopción proveniente de Juzgado.................. 13.23 veces\nVI.- RECONOCIMIENTO DE HIJOS\na).- Registro de reconocimiento.............. 6.61 veces\nb).- Reconocimiento dentro del programa\n“Jornadas del Registro Civil”........... EXENTO\nVII.- INSCRIPCIONES\na).- Inscripción de constancias referentes a Hechos o actos del Registro Civil ocurridos en el Extranjero, con participación de Mexicanos......... 19.84 veces\nb).- Programa de inscripción colectiva de constancias referentes a hechos o actos del Registro Civil ocurridos en el\nExtranjero, con participación de\nMexicanos............................... 9.92 veces\nPor servicio (urgente) extraordinario de los trámites de las fracciones IV, V, VI y VII, se cobrará de manera adicional, dicho trámite se realizará el mismo día si se solicita antes de las 11:00 de la mañana, y el día hábil siguiente si se solicita posteriormente... 3.96 veces\nVIII.- EXPEDICIÓN DE ACTAS Y CERTIFICADOS\na) Por expedición de acta certificada o digitalizada de los hechos y actos civiles asentados en Registro Civil del Municipio de\nb) Por trámite de solicitud de constancias referentes a hechos o actos del registro civil solicitados desde el extranjero.... 19.84 veces\nc) Por la expedición de la primera copia certificada de acta de nacimiento a la persona que acuda a registrarse por primera vez, registro normal o extemporáneo.... EXENTO\nd)\nPor el servicio de la expedición de acta digitalizada Estatales a través del sistema electrónico de la Dirección del Registro\ne) Por el servicio de la expedición de acta digitalizada Interestatales a través del sistema electrónico de la Dirección del\nRegistro Civil de Gobierno del\nEstado..................................... 2.50 veces\nf) Expedición de copia certificada o digitalizada de acta de nacimiento a menores de 12 años, asentada en el Registro\nCivil del Municipio de San Felipe, el día en el mes de abril, previamente señalado por la\nAutoridad Municipal, solicitada el mismo día de 8:00 a 13:00 horas, dentro del Programa\nNiño Sanfelipeño..... EXENTO\ng) Por expedición de acta certificada o digitalizada de los hechos o actos civiles asentados en Registro Civil del Municipio de\nSan Felipe, solicitadas en campañas o ferias de servicios............................ EXENTO\nPor la expedición de documentos subsecuentes al primer, señalados en el inciso a), se cobrará el 50% del costo normal del servicio con excepción de los incisos c), e) y f), en caso de requerir copias adicionales deberá cubrirse lo señalado en el inciso a).\na).- Copias fotostáticas no certificadas, por\nHoja de apéndices, actas, recibos de pago y/o documentación necesaria para trámites ante el registro civil..... 0.06 veces\nb).- Recepción y trámite para anotación marginal de rectificación de acta salvo a aquellos errores imputables al\nRegistro Civil......................... 5.29 veces\nc).- Recepción y trámite para anotación marginal de rectificación de acta, cuando el error es imputable al Registro Civil...... EXENTO\nd).- Corrección de acta, cuando el error haya sido detectado por el ciudadano antes del día 5 del mes siguiente en que llevo a cabo su registro...................... 1.99 veces\ne).- Campañas especiales relativas al Estado\nCivil de las personas................... EXENTO\nf).- Recepción, trámite y anotación marginal de cancelación de acta por duplicidad... 5.29 veces\ng).- Otras anotaciones marginales............ 5.29 veces\nh).- Certificados y constancias\n1).- Por Expedición de Certificación de\nApéndices de Asentamientos por\n2).- Por expedición de certificación de apéndices de Asentamientos, completo. 3.64 veces\n3).- Otros. 2.64 veces\ni).- Por solicitud y envío de actas que obran en las Oficialías del Registro Civil del territorio nacional vía servicio de mensajería, independientemente del costo por derechos estipulado en cada estado. 3.31 veces\nj).- Constancia de inexistencia.............. 2.64 veces\nk).- Costo adicional por servicio urgente incisos g), h) y j)................ 1.96 veces\nPor la expedición de documentos subsecuentes al primero, señalados en los incisos a), h) y j), se cobrará el 50% del costo normal del servicio.\nEn los trámites comprendidos en las fracciones I inciso d) y h), II inciso a), n) y o), III inciso a), c) y g), IV, V, VI inciso a), VII inciso a), VIII inciso a), IX inciso b), f) y h), se considerarán las siguientes atenuantes para otorgar descuentos:\nLos pensionados, jubilados, personas con discapacidad y las personas mayores de sesenta años, pagarán el 50% de la tarifa, únicamente tratándose de documentos que estén a su nombre, debiendo comprobar su condición con identificación oficial o documentación expedida por\nInstitución Pública, únicamente en los trámites comprendidos en las fracciones IV, V, VI inciso a), VII inciso a), VIII inciso a), IX incisos b) y f).\nTratándose de indigentes, personas de escasos recursos, mayores de 60 años, las personas con discapacidad, viudas mayores de 50 años y personas indígenas, pescadoras ribereñas, mujeres jefas de familia, afrodescendientes y afromexicanas, estarán exentos de pago, previa solicitud o en su caso, y estudio socioeconómico, realizado por Trabajo\nSocial de Desarrollo Integral de la Familia Municipal, el cual emitirá\nRegistro Civil solicitando la exención del pago de Derechos, en razón de los resultados obtenidos, en los trámites comprendidos en las fracciones IV, V, VI inciso a), VII inciso a), VIII inciso a), IX b) y f).\nEn cuanto a los descuentos señalados en este artículo, cuando se trate de personas finadas, los podrán solicitar cónyuge, padre, madre o descendientes directos, siendo los solicitantes quienes deberán acreditar su condición económica.\nPara los efectos del presente artículo, se entiende por horas hábiles, las transcurridas de 8:00 a 14:00 horas y por días hábiles de lunes a viernes, siempre y cuando no se trate de un día inhábil decretado oficialmente.\nEn caso de existir circunstancias de emergencia sanitaria en el\nMunicipio, se entenderán por horas hábiles las transcurridas de 8:00 a 17:00 horas.\n04 POR LA AUTORIZACIÓN DEL USO U OCUPACIÓN DE VÍAS PÚBLICAS PARA EJERCER\nEL COMERCIO O LA PRESTACIÓN DE SERVICIOS, POR COMERCIANTES AMBULANTES,\nCON PUESTOS SEMIFIJOS O MERCADOS SOBRE RUEDAS\nARTÍCULO 20.- Por la expedición o revalidación de permisos para el uso u ocupación de las vías públicas para ejercer el comercio o la prestación de servicios en los términos del reglamento de la materia, se pagarán conforme la siguiente:\nUNIDAD DE MEDIDA Y\nACTUALIZACIÓN VIGENTE\nI.- Permisos Ordinarios (Anuales):\na).- Aseadores de calzado ambulante.......... 5.29 veces\nb).- Aseadores de calzado semifijos.......... 10.58 veces\nc).- Fotógrafos ambulantes................... 9.26 veces\nd).- Músicos ambulantes...................... 9.26 veces\ne).- Vendedores ambulantes................... 13.23 veces\nf).- Puestos semifijos....................... 33.07 veces\ng).- Puestos semifijos periódicos y revistas. 10.58 veces\nh).- Comerciante en mercado sobre ruedas, por la superficie especificada en el\nReglamento que le resulte aplicable a la materia, de 1 a 3 días de la semana.................................. 18.52 veces\ni).- Comerciante en mercado sobre ruedas, por la superficie especificada en el\nReglamento que le resulte aplicable a la materia, de 4 a 7 días de la semana.................................. 34.39 veces\nj).- Ambulantes con vehículo................. 50.00 veces por vehículo\nk).- Dentro de Zona Federal (para cualquier tipo de comercio ambulante).... 33.07 veces\nLas tarifas anteriores se cobrarán proporcionalmente al número de meses del ejercicio fiscal del que se trate, pendientes de transcurrir a partir de la fecha en que se expida el permiso.\nII.- Permisos Extraordinarios (de 1 a 30 días naturales):\nUNIDAD DE MEDIDA Y\nACTUALIZACIÓN VIGENTE\na).- Ambulante............................... 3.96 veces\nb).- Músicos ambulantes hasta tres\nIntegrantes............................. 3.96 veces\n1.- 4 o más Integrantes................ 1.32 veces por cada uno\nc).- Semifijos............................... 6.61 veces\nd).- Mercado Sobre Ruedas.................... 1.32 veces\ne).- Ambulantes con vehículo................. 13.23 veces por vehículo\nf).- Permiso Especial para la ocupación de la vía pública para el desarrollo de actividades sociales u otro tipo de actividades............................. EXENTO\nIII.- Permiso especial (1 a 3 días naturales):\na).- Semifijo en eventos turísticos\nIV.- Otros Servicios:\na).- Constancias de permisionario............ 2.64 veces\nb).- Reposición de constancia de permisionario........................... 3.96 veces\nc).- Certificado de no adeudo................ EXENTO\nd).- Modificaciones, reposiciones o cambios a permisos ordinarios..................... 3.96 veces\nPara los residentes de la zona suburbana y zona rural se aplicará el\n75% de las tarifas del presente artículo.\nAquellas personas que acrediten con documentación oficial ser pensionados, jubilados o mayores de 60 años, así como las personas con discapacidad y que cuenten con autorización vigente a su nombre, cubrirán sólo el 50% por concepto de derechos a que hace referencia este artículo tratándose de los primeros, y estarán exentas de pago las personas con discapacidad.\nEste beneficio se aplicará a un solo permiso, por lo que en el caso de que la persona contara con más de uno, a éste(os) se aplicará la tarifa señalada en las fracciones anteriores, según corresponda.\nLas personas que no revaliden sus permisos, dentro del primer trimestre recargo económico, independientemente de las sanciones administrativas a que se tuviese lugar. impondrá una sanción, derivada del 5% adicional al valor del permiso del presente artículo.\n05 POR LA AUTORIZACIÓN DE LA VENTA, ALMACENAJE O CONSUMO PÚBLICO DE\nBEBIDAS ALCOHÓLICAS.\nARTÍCULO 21.- Por la recepción, análisis y revisión de solicitudes de permisos nuevos para la operación de establecimientos con venta, almacenaje o consumo de bebidas alcohólicas o alcohol, cambio de giro, cambio de permisionario, cambio de nombre o denominación y cambio de domicilio, así como la emisión de permisos y certificados que por dichos conceptos y similares, se expidan de conformidad con el reglamento de la materia, estarán sujetos a la siguiente tarifa:\nUNIDAD DE MEDIDA Y\nACTUALIZACIÓN VIGENTE\nI.- Certificado de distancias................... 48.95 veces\nII.- Constancia de cumplimiento de las condiciones del permiso.................... 1.65 veces\nIII.- Dictamen de factibilidad................... 25.13 veces\nIV.- Inspección de condiciones del local......... 25.13 veces\nV.- Dictamen de Procedencia para la autorización de permisos nuevos, cambio de giro y cambio de domicilio, para operar, el cual sólo se pagará en caso de que éste sea favorable al solicitante, dependiendo del giro autorizado por los derechos y obligaciones que adquiera:\nUNIDAD DE MEDIDA y\nACTUALIZACIÓN\nVIGENTE\na).- Abarrotes............................ 100.30 veces\nb).- Fonda o Lonchería................... 100.30 veces\nc).- Restaurante.......................... 150.45 veces\nd).- Mercado.............................. 132.30 veces\ne).- Supermercado......................... 793.80 veces\nf).- Billar............................... 248.72 veces\ng).- Tienda de Autoservicio............... 330.75 veces\nh).- Agencia y SubAgencia................. 330.75 veces\ni).- Expendio............................. 496.12 veces\nj).- Restaurante Bar...................... 330.15 veces\nk).- Bar Turístico........................ 300.12 veces\nl).- Licorería............................ 578.15 veces\nm).- Café Cantante........................ 500.25 veces\nn).- Hotel................................ 529.20 veces ñ).- Discoteca............................ 992.25 veces\no).- Bodega............................... 330.75 veces\np).- Bar Terraza.......................... 500.87 veces\nq).- Centro de Espectáculos............... 550.50 veces\nr).- Microcervecería...................... 132.30 veces\ns).- Sala de Degustación para la venta de cerveza artesanal.................... 132.30 veces\nt).- Boutique de cerveza artesanal........ 132.30 veces\nu).- Deposito............................. 320.75 veces\nv).- Centro de Apuestas................... 472.50 veces\nVI.- Expedición de Permiso provisional y autorización para la venta de bebidas alcohólicas, cuando el solicitante reúna las condiciones establecidas en el Reglamento que le resulte aplicable a la materia, se cobrará 504.00 veces la Unidad de Medida y Actualización Vigente.\nVII.- Expedición del permiso eventual para la venta de bebidas alcohólicas:\nUNIDAD DE MEDIDA y\nEVENTO ACTUALIZACIÓN\nVIGENTE\na).- Kermeses y posadas..................... 21.16 veces\nb).- Eventos de centros escolares........... 13.23 veces\nc).- Degustación de bebidas alcohólicas y obsequios de bebidas alcohólicas..... 40.50 veces\nd).- Contingencias de autos de carreras o exhibición de autos o tractocamiones.. 100.00 veces\ne).- Eventos de lucha libre y artes marciales mixtas..................... 60.31 veces\nf).- Charreadas, rodeo o jaripeo.......... 50.02 veces\ng).- Corrida de toros, rejoneo o novillada............................ 129.65 veces\nh).- Arrancones de autos, tractocamiones, motocicletas y cualquier otro vehículo de motor............................. 82.61 veces\ni).- Funciones de box no profesional o amateurs........................... 50.00 veces\nj).- Funciones de box profesional.......... 80.00 veces\nk).- Baile popular........................ 60.00 veces\nl).- Peleas de gallos y carreras de\nCaballos............................. 80.00 veces\nm).- Ferias o festejos populares........... 60.00 veces\nn).- Conciertos musicales masivos.......... 100.00 veces ñ).- Pasarelas, eventos de modelaje........ 30.21 veces\no).- Eventos de música locales............. 50.00 veces\np).- Muestras gastronómicas y exposiciones generales............... 50.27 veces\nq).- Cena baile........................... 50.25 veces\nr).- Torneos deportivos o trasmisión, reproducción y/o difusión digital de eventos deportivos (voleibol, basquetbol, béisbol, fútbol, etc.)................................ 50.08 veces\ns).- Obras de teatro....................... 50.27 veces\nt).- Aniversario e Inauguraciones de eventos.............................. 50.50 veces\nu).- Eventos o bailes en salones o centro nocturnos............................ 100.69 veces\nv).- Verbena popular...................... 20.00 veces\nw).- Bailes o Espectáculos Eróticos....... 250.75 veces\nx).- Contingencias, exhibición o espectáculos de motocicletas y bicicletas........................... 30.50 veces\ny).- Eventos de música de grupos locales generales........................... 50.00 veces\nz).- Carreras de vehículos de motor fuera de camino de pista.................... 200.00 veces\nLos eventos promovidos por dependencias o entidades gubernamentales, juntas de mejoramiento, organismos descentralizados de gobierno, entidades paraestatales y municipales, por las asociaciones religiosas constituidas legalmente, por asociaciones civiles con fines no lucrativos que sean organizados conjuntamente con las entidades públicas a que se refiere este párrafo y que tengan por objeto allegarse de recursos para el cumplimiento de sus fines, estarán............................. EXENTOS\nPermisos por espacio o local, autorizado por día, dentro de la zona de festejos públicos municipales, de conformidad a la clasificación hecha por el organizador y a la siguiente tabla: (cifras en Unidad de Medida y Actualización (UMA)vigente).\nCerveza y Vino 22.27 14.85 10.12\nCerveza y Licor 49.27 45.90 34.42\nSe entiende por zona \"A\" el área del Malecón, zona \"B\" corredores comerciales y zona \"C\" resto de la Zona Urbana.\nVIII.- Los derechos por expedición de permisos nuevos, una vez que se autoricen, se pagarán conforme a la siguiente tarifa, de Procedencia:\nUNIDAD DE MEDIDA y\nVIGENTE\na).- Abarrotes............................ 2,000.00 veces\nb).- Fonda o Lonchería.................... 2,000.00 veces\nc).- Restaurante.......................... 2,000.00 veces\nd).- Mercado.............................. 10,080.00 veces\ne).- Supermercado......................... 12,600.00 veces\nf).- Billar............................... 9,450.00 veces\ng).- Tienda de Autoservicio............... 13,860.00 veces\nh).- Agencia y SubAgencia................. 4,788.00 veces\ni).- Expendio............................. 7,182.00 veces\nj).- Restaurante Bar...................... 5,000.00 veces\nk).- Bar Turístico........................ 5,000.00 veces\nl).- Licorería............................ 8,946.00 veces\nm).- Café Cantante........................ 10,000.00 veces\nn).- Hotel................................ 11,000.00 veces ñ).- Discoteca............................ 15,000.00 veces\no).- Bodega............................... 4,788.00 veces\np).- Bar Terraza.......................... 18,900.00 veces\nq).- Centro de Espectáculos............... 12,600.00 veces\nr).- Microcervecería...................... 378.00 veces\ns).- Sala de Degustación para la venta de cerveza artesanal.................... 378.00 veces\nt).- Boutique de cerveza artesanal........ 378.00 veces\nu).- Deposito............................. 4,788.00 veces\nv).- Centro de Apuestas................... 31,500.00 veces\nw).- Aquellos permisos que se otorguen a entidades paramunicipales enfocadas a parques temáticos.................... EXENTOS\nLos residentes de zona sur del Municipio de San Felipe, en lo que se refiere al inciso n) tendrán un 23.05% de descuento, inciso p) tendrán un 55.21% de descuento, siempre y cuando acrediten la residencia y establecimiento comercial en esta zona. Esto debido a la falta de servicios básicos en la zona sur. De cambiar de domicilio fiscal, antes de un año de haber expedido el permiso, tendrá que pagar la diferencia que resulte, por la zona a la que corresponda el nuevo domicilio.\nAsimismo, se hará un descuento del 5% a personas físicas y morales que acrediten mediante las disposiciones que la autoridad municipal emita, haber aplicado políticas, en favor de la equidad de género, tanto para empleados, como para la comunidad en general.\nIX.- Derechos por revalidación anual de permisos\nUNIDAD DE MEDIDA y\nVIGENTE\na).- Abarrotes............................ 34.77 veces\nb).- Fonda o Lonchería.................... 87.69 veces\nc).- Restaurante.......................... 101.30 veces\nd).- Mercado.............................. 181.44 veces\ne).- Supermercado......................... 279.72 veces\nf).- Billar............................... 189.00 veces\ng).- Tienda de Autoservicio............... 189.00 veces\nh).- Agencia y SubAgencia................. 140.61 veces\ni).- Expendio............................. 170.85 veces\nj).- Restaurante Bar...................... 300.88 veces\nk).- Bar Turístico........................ 349.27 veces\nl).- Licorería............................ 181.44 veces\nm).- Café Cantante........................ 420.33 veces\nn).- Hotel/Motel.......................... 210.16 veces ñ).- Discoteca............................ 359.85 veces\no).- Bodega............................... 130.03 veces\np).- Bar Terraza.......................... 300.58 veces\nq).- Centro de Espectáculos............... 220.75 veces\nr).- Microcervecería...................... 101.30 veces\ns).- Sala de Degustación para la venta de cerveza artesanal.................... 101.30 veces\nt).- Boutique de cerveza artesanal........ 101.30 veces\nu).- Centro de Apuestas................... 472.50 veces\nv).- Deposito............................. 140.61 veces\nLos residentes de zona sur del Municipio de San Felipe, tendrán un 20% de descuento, siempre y cuando acrediten la residencia y establecimiento comercial en esta zona. Esto debido a la falta de servicios básicos en la zona sur. De cambiar de domicilio fiscal, antes de un año de haber revalidado el permiso, tendrá que pagar la diferencia que resulte, por la zona a la que corresponda el nuevo domicilio.\nAsimismo, se hará un descuento del 5% a personas físicas y morales que acrediten mediante las disposiciones que la autoridad municipal emita, haber aplicado políticas, en favor de la equidad de género, tanto para empleados, como para la comunidad en general.\nAdicional a la revalidación anual de permisos permanentes, los alcohólicas en envase abierto enumerados en los incisos c), f), i),\nj), k), m), n), ñ), p) y q), de esta fracción IX, causarán derechos por la cantidad equivalente a 12.60 veces la Unidad de medida y actualización vigente, por concepto de apoyo a las campañas y relacionados con el consumo inmoderado de bebidas alcohólicas, así control de seguridad en los establecimientos. calendario por mes y giros.\nJunio:\nBar Terraza, Bar turístico, Café cantante y Discoteca, Centro de apuestas y Depósitos\nJulio:\nBillar, Bodega, Expendio, Licorería y Motel.\nAgosto:\nAgencia y SubAgencia, Autoservicio, Mercado, Supermercado y abarrotes.\nSeptiembre:\nRestaurant, Restaurant Bar, Fonda o Lonchería, Hotel, Centro de\nEspectáculos, Microcervecería, Sala de Degustación para la Venta\nExclusiva de Cerveza Artesanal y Boutique de Cerveza Artesanal.\nDe cada año de lo contrario se procederá a lo establecido en el párrafo siguiente:\nQuienes no revaliden sus permisos en forma oportuna o quienes lo hagan fuera de los plazos establecidos conforme a esta Ley de\nIngresos causarán una sanción económica, dependiendo de los servicios adicionales con los que cuente el permiso original independientemente de las sanciones administrativas a que tuviese lugar, no procederá revalidación de permisos por parte de la Tesorería, las de 90 días naturales.\nLa sanción aplicable será de acuerdo al siguiente tabulador:\nUNIDAD DE MEDIDA y\nVIGENTE\na).- Abarrotes............................ 33.39 veces\nb).- Fonda o Lonchería.................... 66.15 veces\nc).- Restaurante.......................... 66.15 veces\nd).- Mercado.............................. 99.22 veces\ne).- Supermercado......................... 132.30 veces\nf).- Billar............................... 98.91 veces\ng).- Tienda de Autoservicio............... 98.91 veces\nh).- Agencia y Sub-Agencia................ 66.15 veces\ni).- Expendio............................. 99.22 veces\nj).- Restaurante Bar...................... 132.30 veces\nk).- Bar Turístico........................ 165.37 veces\nl).- Licorería............................ 99.22 veces\nm).- Café Cantante........................ 198.45 veces\nn).- Hotel/Motel.......................... 99.22 veces ñ).- Discoteca............................ 165.37 veces\no).- Bodega............................... 66.15 veces\np).- Bar Terraza.......................... 132.30 veces\nq).- Centro de Espectáculos............... 132.30 veces\nr).- Microcervecería...................... 66.15 veces\ns).- Sala de Degustación para la venta de cerveza artesanal.................... 66.15 veces\nt).- Boutique de cerveza artesanal........ 66.15 veces\nu).- Centro de Apuestas................... 157.50 veces\nv).- Depósito............................. 66.15 veces\nX.- La expedición de autorización de cambios o modificación al permiso pagará los siguientes derechos, disminuyéndose de éstos el pago realizado por el Dictamen de Procedencia, dependiendo del giro autorizado por los derechos y obligaciones que adquiera:\na).- Cambio de giro comercial de manera ascendente, se nuevos de los giros que se modifican.\nb).- Por cambio de giro comercial de manera descendente, se\nV de este artículo, relativa al Dictamen de\nProcedencia del giro que prevalece.\nc).- Por el cambio de nombre comercial se pagará 10% sobre el valor del permiso.\nd).- 30% Sobre el valor del permiso por cambio de domicilio.\ne).- 50% Sobre el valor del permiso por cambio de propietario.\nf).- Operadores Diversos.................. 63.00 veces\nEl cambio de propietario por muerte de su titular, se reducirá 50% del costo previsto en este inciso, siempre y cuando exista testamento que los herederos, en ambos casos, sean familiares descendientes, ascendientes, cónyuge, concubina o concubinario o que tengan cesión línea recta hasta el segundo grado.\nXI.- Derechos por otorgamiento de servicios adicionales\nUNIDAD DE MEDIDA y\nACTUALIZACIÓN\nVIGENTE\na).- Áreas adicionales de servicio, tales como albercas, jardines, patios, salones o instalaciones para eventos. 456.87 veces\nb).- Música grabada....................... 270.10 veces\nc).- Música en vivo....................... 399.09 veces\nd).- Baile................................ 380.72 veces\ne).- Espectáculo artístico................ 532.01 veces\nf).- Mesas de billar...................... 304.58 veces\ng).- Boliche.............................. 456.07 veces\nh).- Bailes Eróticos...................... 1,141.74 veces\nXII.- Derechos por revalidación anual de servicios adicionales\na).- Áreas adicionales de servicio, tales como albercas, jardines, patios, salones o instalaciones para eventos. 46.30 veces\nb).- Música grabada....................... 30.42 veces\nc).- Música en vivo....................... 41.01 veces\nd).- Espectáculo artístico................ 66.15 veces\ne).- Servibar............................. 46.30 veces\nf).- Mesas de billar...................... 34.39 veces\ng).- Servicio en su auto.................. 91.28 veces\nh).- Bailes Eróticos...................... 91.28 veces\ni).- Boliche.............................. 76.73 veces\nj).- Baile................................ 41.01 veces\nXIII.- Recepción, análisis y evaluación de la solicitud de plazo para revalidación de permiso de alcohol......................... 30.42 veces\nXIV.- Evaluación y dictamen sobre la procedencia de ampliación al plazo para inicio de operaciones................. 13.23 veces\nXV.- Autorización de suspensión del uso del permiso.................................... 39.69 veces\nXVI.- Derechos por otorgamiento de horario extraordinario, por cada hora que se otorgue.................................... 29.10 veces\nAdemás se adiciona al pago de la fracción anterior el cobro de 48.00 veces la Unidad de medida y actualización vigente para fortalecer la campaña y/o capacitación de prevención de accidentes relacionados con el consumo de bebidas alcohólicas.\nXVII.- Expedición de certificación de los permisos para exhibición en establecimientos........................... 5.04 veces\nXVIII.- Expedición de certificación de los permisos por robo, destrucción o extravío......... 63.00 veces\n06 POR LA AUTORIZACIÓN DEL FUNCIONAMIENTO DE MÁQUINAS ELECTRÓNICAS,\nELECTROMECÁNICAS, MECÁNICAS, MUSICALES, DIGITALES, VIDEOJUEGOS Y\nCUALQUIER TECNOLOGÍA SIMILAR.\nARTÍCULO 22.- Para la apertura, cambio de domicilio o de propietario, electrónicas, electromecánicas, mecánicas, musicales, digitales, videojuegos y cualquier tecnología similar, que operen mediante la inserción de billete, moneda, ficha, tarjeta, banda magnética o cualquier otro medio de cobro integrado a la máquina, así como la renta de las mismas, como rocolas y karaokes entre otros, deberá entregarse y analizarse la documentación necesaria, previo al pago de derechos que se causen conforme a la tabla siguiente:\nUNIDAD DE MEDIDA Y\nACTUALIZACIÓN VIGENTE\nI.- Apertura de establecimiento hasta diez aparatos...................................... 33.07 veces\nII.- Apertura de establecimiento mayor de diez aparatos...................................... 66.15 veces\nIII.- Expedición por primera vez de calcomanía por aparato....................................... 3.96 veces\nIV.- Cambio de domicilio........................... 39.69 veces\nV.- Cambio de propietario......................... 39.69 veces\nVI.- Cambio o incremento, por aparato.............. 6.61 veces\nVII.- Multa por no exhibir la calcomanía que expide la autoridad municipal........................ 10.50 veces\nVIII.- Por revalidación anual, por aparato........... 5.29 veces\nLa revalidación de los documentos a que se refiere la fracción VIII de este artículo, deberá realizarse a más tardar en el mes de marzo de cada año. electrónicas, electromecánicas, mecánicas, musicales, digitales, de un billete, moneda, ficha, tarjeta, banda magnética o cualquier otro medio de cobro integrado a la máquina, así como los propietarios y/o poseedores de los bienes inmuebles donde se instalen, serán solidariamente responsables del pago de los impuestos, derechos y/o instalados en esta municipalidad.\nCENTROS DE APUESTAS, APUESTAS REMOTAS, SALAS DE SORTEOS DE NÚMEROS Y/O\nCASINOS.\nIX.- Las máquinas de azar o con combinaciones de azar y destreza, autorización de la Secretaría de Gobernación, pagarán tabla:\na).- Apertura del establecimiento............ 2,646.00 veces\nb).- Expedición por primera vez de calcomanía por máquina............................. 50.40 veces\nc).- Cambio de domicilio..................... 1,890.00 veces\nd).- Cambio de propietario................... 1,890.00 veces\ne).- Cambio de nombre comercial.............. 1,890.00 veces\nf).- Revalidación trimestral por máquina..... 31.50 veces\ng).- Incremento por aparato.................. 50.40 veces\nh).- Revalidación anual de licencia de operación/ocupación por establecimiento.. 1,008.00 veces\ni).- Aportación para programas preventivos para la ludopatía, trimestral por máquina por unidad de aparato similar autorizado.............................. 1.89 veces\nLudopatía una cuota de 500.00 veces la Unidad de medida y actualización vigente\nj).- Permiso de operación por horario ampliado, anual........................ 1,984.50 veces\nRespecto al inciso f), de la fracción IX del presente artículo, los derechos se causarán y deberán cubrirse trimestralmente, siendo la fecha de vencimiento el último día de cada trimestre.\nAsí mismo, la calcomanía correspondiente al ejercicio fiscal en curso, este artículo.\n07 POR LA AUTORIZACIÓN DE LA INSTALACIÓN DE MÁQUINAS EXPENDEDORAS DE\nALIMENTOS, BEBIDAS, PRODUCTOS Y SIMILARES.\nARTÍCULO 23.- Para la apertura o inicio de actividades, cambio de domicilio o de propietario, la revalidación o el incremento de máquinas expendedoras de alimentos, bebidas, productos y similares, deberá entregarse y analizarse la documentación necesaria previo el pago de derechos que se causen, conforme a la tabla siguiente:\nUNIDAD DE MEDIDA Y\nACTUALIZACIÓN VIGENTE\nI.- Máquinas consideradas consolas expendedoras:\na).- Apertura por aparato o incremento....... 13.23 veces\nb).- Para la revalidación anual de permiso... 6.61 veces\nc).- Cambio de domicilio..................... 26.46 veces\nd).- Cambio de propietario................... 26.46 veces\ne).- Expedición por primera vez de calcomanía por aparato............................. 3.96 veces\nII.- Módulos conformados por cabezales:\na).- Apertura o incremento por aparato....... 6.61 veces\nIII.- Para la revalidación anual del permiso:\na).- Los aparatos que estén conformados por módulo de 1 hasta 4 cabezales monederos. 1.99 veces\nb).- Los aparatos que estén conformados por módulo de 5 hasta 10 cabezales monederos 3.31 veces\nA partir de la onceava pagará cada uno.. 1.32 veces\nc).- Los aparatos considerados consola expendedora............................. 6.61 veces\nd).- Multa por no exhibir la calcomanía que expida la autoridad..................... 10.50 veces\nPara cambio de domicilio o de propietario, se aplicarán los incisos\nIV.- Requisitos:\nPara la autorización de las máquinas expendedoras de alimentos, bebidas, productos y similares, el solicitante deberá cumplir con los requisitos que a continuación se señalan:\n1.- Solicitud dirigida al Titular de Recaudación de Rentas\nMunicipal.\n2.- Inscripción en el registro federal de contribuyentes.\n3.- Identificación oficial con fotografía del propietario, y en el caso de personas morales copia de acta constitutiva e identificación del representante legal.\n4.- Documento que acredite la legal propiedad o posesión de las máquinas, especificando la marca, modelo y serie.\n5.- Documento que acredite la legal estancia en el país en caso de que la máquina sea extranjera.\n6.- Fotografía de la máquina a registrar.\n7.- La anuencia del propietario del inmueble donde se instalará la máquina. realizarse a más tardar en el mes de Abril de cada año. expendedoras de alimentos, bebidas, productos y similares, así como los propietarios y/o poseedores de los bienes inmuebles donde se instalen, serán solidariamente responsables del pago de los impuestos, derechos y/o multas que se originen con motivo de dichas máquinas que tengan instaladas en esta municipalidad.\n08 POR LA AUTORIZACIÓN PARA LA REALIZACIÓN DE EVENTOS, ESPECTÁCULOS\nPÚBLICOS Y DE DIVERSIÓN\nARTÍCULO 24.- Las personas físicas o morales que soliciten permisos para la realización de eventos, espectáculos públicos y de diversión deberán entregar la documentación necesaria, previo el pago de los derechos que se causen de acuerdo a la siguiente tarifa:\nUNIDAD DE MEDIDA Y\nACTUALIZACIÓN VIGENTE\nI.- Circos:\na).- Por semana.............................. 37.80 veces\nb).- Por día................................. 5.39 veces\nII.- Juegos mecánicos, por semana:\na).- Zona urbana............................. 37.80 veces\nb).- Zona suburbana, Zona rural y otras zonas................................... 31.50 veces\nIII.- Pasarelas, eventos de modelaje:\na).- Con fines de lucro...................... 16.75 veces\nb).- Sin fines de lucro...................... 6.23 veces\nIV.- Desfiles relativos a centros educativos por exposición de presentaciones temáticas y alusivas a sus actividades académicas......... EXENTOS\nV.- Charreadas y otros............................ 13.23 veces\nVI.- Funciones:\na).- Box, lucha libre y artes marciales mixtas\n1).- Con fines de lucro................. 34.39 veces\n2).- Sin fines de lucro................. 23.81 veces\nb).- Obras de teatro\n1).- Con fines de lucro................. 21.16 veces\n2).- Sin fines de lucro................. EXENTO\nc).- Circuito cerrado......................... 23.81 veces\nd).- Otros.................................... 13.23 veces\nVII.- Espectáculos masivos:\na).- Corrida de toros........................ 33.07 veces\nb).- Presentación de artistas, cantantes y otros................................... 33.07 veces\nc).- Fiestas o bailes, sin fines de especulación............................ 13.23 veces\nd).- Fiestas o bailes en salones que se alquilen para tal fin, sin fines de especulación............................ 6.61 veces\ne).- Bailes populares........................ 33.07 veces\nf).- Arrancones de vehículos de motor....... 33.07 veces\ng).- Carreras de vehículos de motor fuera de camino en pista......................... 100.00 veces\nh).- Paseos recreativos en vehículos de motor fuera de camino sin velocidad (Poker Run) 20.00 veces\ni).- Peleas de Gallos........................ 39.69 veces\n1).- Dictamen de no inconveniente...... 26.46 veces\nj).- Exhibición de gallos (casteo) sin apuestas 33.07 veces\nk).- Carrera de Caballos..................... 39.69 veces\n1).- Dictamen de no inconveniente...... 26.46 veces\nl).- Otros................................... 15.87 veces\nm).- Multa por anunciarse o promocionarse sin 50.00 a permiso correspondiente................. 500.00 veces\nn).- Será sancionado como responsable solidario la persona física o moral que permita la promoción de eventos y venta de entradas (boletos) al espectáculo o evento, sin contar con la autorización o permiso expedido por las 50.00 a autoridades municipales................... 500.00 veces\no).- La persona física o moral propietaria de las estructuras para la colocación de\nAnuncios Espectaculares o Carteleras, tendrá la obligación de solicitar el documento de la Autorización o Permiso que expida la autoridad municipal al arrendatario, para la colocación de propaganda o publicidad, debido a que si el arrendador no cuenta con el documento de la Autorización o permiso que expidió la autoridad municipal, se hará acreedor 50.00 a a una sanción de......................... 500.00 veces\np).- Tratándose de espectáculos realizados por Organismo no lucrativos que brinden servicios y asistencia médica de manera gratuita a enfermos que padezcan cáncer en etapa terminal, debidamente registrados ante institución oficial que para tales efectos señale la Ley de la materia.............................. EXENTO\nVIII.- Los eventos promovidos por dependencias o autoridades del municipio, estarán.......... EXENTO\nEl permiso deberá solicitarse 48 horas antes del evento, en caso contrario se cobrará el doble de la tarifa correspondiente.\nPara los permisos referentes a lo estipulado en las Fracciones III, V, VI, VII, se otorgará un 50% de descuento, a promotores de la localidad, siempre y cuando acrediten ser residentes del Municipio de\nSan Felipe con documentación oficial.\n09 ESTABLECIMIENTOS PARA EVENTOS SOCIALES Y FIESTAS\nARTÍCULO 25.- Las personas físicas o morales que soliciten permiso para el funcionamiento de establecimientos para eventos sociales y fiestas, deberán entregar la documentación necesaria, para su análisis en el área municipal correspondiente, previo al pago de derechos que se causen conforme a la siguiente tarifa:\nUNIDAD DE MEDIDA Y\nACTUALIZACIÓN VIGENTE\nI.- Inspección de Factibilidad..................... 26.46 veces\nII.- Apertura\nEn zona habitacional:\na).- Establecimiento abierto con horario de\n11:00 horas a 22:00 horas................ 85.99 veces\nb).- Establecimiento mixto con horario de\n11:00 horas a 24:00 horas................ 171.99 veces\nc).- Establecimiento cerrado con horario de\n11:00 horas a 24:00 horas................ 343.98 veces\nEn zona comercial:\na).- Establecimiento abierto con horario de\n11:00 horas a 2:00 horas................. 171.99 veces\nb).- Establecimiento mixto con horario de\n11:00 horas a 2:00 horas................. 264.60 veces\nc).- Establecimiento cerrado con horario de\n11:00 horas a 2:00 horas................. 529.20 veces\nd).- Multa por operar sin el permiso 50.00 a correspondiente.......................... 250.00 veces\nUNIDAD DE MEDIDA Y\nACTUALIZACIÓN VIGENTE\nZONA ZONA\nHABITACIONAL COMERCIAL\nIII.- Cambio de propietario............. 52.92 veces 66.15 veces\nIV.- Cambio de nombre comercial........ 26.46 veces 39.69 veces\nV.- La revalidación anual del permiso, deberá realizarse a más tardar en el mes de marzo de cada año, de acuerdo con la siguiente tarifa:\nZona Habitacional:\na).- Establecimiento abierto con horario de\n11:00 horas a 22:00 horas................ 46.30 veces\nb).- Establecimiento mixto con horario de\n11:00 horas a 24:00 horas................ 85.99 veces\nc).- Establecimiento cerrado con horario de\n11:00 horas a 24:00 horas................ 171.99 veces\nEn zona comercial:\na).- Establecimiento abierto con horario de\n11:00 horas a 2:00 horas................. 85.99 veces\nb).- Establecimiento mixto con horario de\n11:00 horas a 2:00 horas................. 132.30 veces\nc).- Establecimiento cerrado con horario de\n11:00 horas a 2:00 horas................. 264.60 veces la documentación necesaria y el no adeudo municipal, además se les impondrá una sanción económica de 10 a 75 veces la Unidad de Medida y\nActualización vigente, a quienes no revaliden sus permisos en forma a esta ley.\n10 ESTACIONAMIENTO DE VEHÍCULOS EN LA VÍA PÚBLICA Y\nESTACIONAMIENTOS PÚBLICOS\nARTÍCULO 26.- Las personas físicas o morales que ocupen la vía pública con vehículos, pagarán derechos por el uso de la misma conforme a lo siguiente:\nI.- Con señalamiento de cordones de color amarillo, para sitio exclusivo de estacionamiento de vehículos, dentro de los primeros veinte días de cada mes, por cada espacio de estacionamiento mensualmente:\nUNIDAD DE MEDIDA Y\nACTUALIZACIÓN VIGENTE\nZONA ZONA\nTURÍSTICA COMERCIAL\na).- Batería(limitada a 1 cajón por cada 5m de frente de negocio)................ 8.74 Veces 3.75 veces\nb).- Cordón (máximo 12m de frente del negocio)........... 5.46 veces 3.75 veces\nc).- Zonas exclusivas de taxis, por vehículo, una cuota de\n6.61 veces la Unidad de medida y actualización vigente por mes.\nd).- Zonas exclusivas de taxis en la Zona Suburbana y Zona Rural, por vehículo, se reducirá el 50% de las tarifas previstas por este artículo..\nEl estacionamiento en cordón amarillo no podrá ser utilizado para otra actividad diferente al uso exclusivo de estacionamiento sin obtener ningún lucro de ello, lo contrario resultaría en la cancelación del permiso, independientemente de las sanciones correspondientes.\nII.- Por el derecho de estacionarse en uso exclusivo para personas con discapacidad, se pagará una cuota anual de 1.26 Unidad de medida y actualización vigente. estacionamientos, se estará al procedimiento que establece el\nReglamento que le resulte aplicable a la materia.\nIII.- Por el servicio de estacionamiento en la vía pública en los lugares, en donde se hayan instalado dispositivos para el control de estacionamiento en la vía pública, la tarifa será la siguiente:\na).- Por cada quince minutos o fracción de quince minutos la cantidad de 0.0334 veces Unidad de medida y actualización vigente.\nb).- Los domingos y días festivos de descanso obligatorio que marca la Ley Federal del Trabajo, el estacionamiento será gratuito.\nc).- Dentro del horario de 20:01 a 7:59 horas del día siguiente, el estacionamiento será gratuito. pública, dentro del perímetro controlado por parquímetros o dispositivos de control de estacionamiento en la vía pública, que la autoridad municipal autorice a utilizar a particulares de acuerdo con la normatividad vigente y aplicable:\nUNIDAD DE MEDIDA Y\nACTUALIZACIÓN VIGENTE\na).- Particulares, por cajón para un vehículo, anual...................................... 463.05 veces\nb).- Comercial para realizar maniobras de carga y descarga, por cajón para un vehículo, anual..................................... 463.05 veces\nc).- Autorización para ocupar la vía pública como terminal para el servicio de transporte público de carga o pasajeros, por cajón para un vehículo, anual......... 463.05 veces\nEstán exentos del pago de los derechos por estacionamiento en la vía pública en las zonas que se encuentren controladas por dispositivos electrónicos identificados como parquímetros, las citados dispositivos, siempre y cuando hayan cumplido con los aplicable a la materia.\nIV.- Por el estacionamiento de vehículos en zonas de tiempo estacionamiento colocados en la vía pública, comúnmente denominados parquímetros:\na).- Por el derecho de estacionarse en zonas de tiempo limitado, hasta por un máximo de dos horas consecutivas, para vehículos con placas nacionales, fronterizas y extranjeras, una cuota de 1.25 veces la Unidad de medida y actualización vigente por año.\nEl pago del derecho antes referido es obligatorio, para todo propietario por cada vehículo de su propiedad, excepto tratándose de personas con discapacidad, únicamente por un solo vehículo de su propiedad, y siempre y cuando demuestren que hayan cubierto la cuota anual para estacionamiento exclusivo para personas con discapacidad.\nUNIDAD DE MEDIDA Y\nACTUALIZACIÓN VIGENTE\n- Por infracción al excederse de dos horas consecutivas, si se liquida dentro de los 5 días siguientes........................................ 0.53 veces\n- Por infracción al excederse de dos horas consecutivas si se liquida después de los 5 días siguientes........................................ 1.05 veces\nb).- Las personas cuyos vehículos estén contemplados en el\nInciso anterior, podrán obtener calcomanías o en su caso, comprobantes de pago, por el derecho de estacionarse por más de dos horas y sin límite de tiempo, para vehículos con placas nacionales y fronterizas, con una cuota de 12.60 veces la Unidad de medida y en que se solicite el servicio.\nEl entero de los derechos a que se refiere ésta fracción, tendrá como los derechos por expedición de placas y tarjeta de circulación, conforme a las Leyes y disposiciones relativas que correspondan, en los módulos que al efecto instale la autoridad municipal.\nV.- Estacionamientos Públicos. meses del año:\nPor permiso anual:\nUNIDAD DE MEDIDA Y\nACTUALIZACIÓN VIGENTE\na).- De 1 a 40 cajones de estacionamiento... 66.15 veces\nb).- De 41 a 100 cajones de estacionamiento... 111.13 veces\nc).- De 101 a 180 cajones de estacionamiento... 158.76 veces\nd).- De 181 a 280 cajones de estacionamiento... 206.64 veces\ne).- De 281 a 400 cajones de estacionamiento... 253.26 veces\nf).- De más a 400 cajones de estacionamiento... 302.40 veces\n11 SERVICIOS QUE PRESTA OFICIALÍA MAYOR\nARTÍCULO 27.- Por los servicios que preste Oficialía Mayor en cuanto a la regularización de bienes inmuebles y/o de terrenos excedentes de la vía pública, se pagará conforme a lo siguiente:\nUNIDAD DE MEDIDA Y\nACTUALIZACIÓN VIGENTE\nI.- Por atención, análisis, integración y determinación de expediente que contiene la petición de venta de él o los excedentes y/o él o los terrenos de la vía pública a regular. 18.90 veces\nII.- Por expedición de Contrato de compraventa de\nBienes inmuebles y/o terrenos excedentes de la vía pública................................ 25.20 veces\nARTÍCULO 28.- Los derechos por el Servicio de Depósitos Vehiculares, deberán cubrirse de acuerdo con las siguientes tarifas:\nI.- MANIOBRAS DE SALVAMENTO:\nLos derechos por maniobras de salvamento, deberán cubrirse de acuerdo con la siguiente tarifa:\nUNIDAD DE MEDIDA Y\nACTUALIZACIÓN VIGENTE\na).- Automóviles, Pick Up y Camionetas......... 5.23 veces\nb).- Camiones Urbanos de Pasajeros............. 16.25 veces\nc).- Autobuses de Pasajeros.................... 18.88 veces\nd).- Camiones de Carga......................... 21.50 veces\ne).- Tractocamiones............................ 24.13 veces\nf).- Remolques................................. 24.13 veces\ng).- Tractocamiones con Remolque............... 29.38 veces\nh).- Motocicletas.............................. 1.03 veces rescate de vehículos imposibilitados para circular, hasta dejarlos en condiciones de arrastre o traslado, como es el caso de vehículos mal estacionados, volcados, accidentados fuera de la carpeta asfáltica, dentro de un canal o barranco, entre otros.\nPor lo que se cobrará una sola cuota por vehículo.\nII.- ARRASTRE DE VEHÍCULOS:\nLos derechos por el arrastre de vehículos deberán cubrirse de acuerdo con la siguiente tarifa:\nUNIDAD DE MEDIDA Y\nACTUALIZACIÓN VIGENTE\na).- Automóviles, Pick Up y Camionetas......... 10.40 veces\nb).- Camiones Urbanos de Pasajeros............. 17.80 veces\nc).- Autobuses de Pasajeros.................... 24.10 veces\nd).- Camiones de Carga:\nSin carga................................. 30.40 veces\nCon carga................................. 37.75 veces\ne).- Tractocamiones sin Remolque............... 35.65 veces\nf).- Remolques................................. 35.65 veces\ng).- Tractocamiones con Remolque............... 62.95 veces\nh).- Motocicletas.............................. 7.30 veces\ni).- Bicicletas................................ 1.55 veces población, se incrementará en 0.25 veces la Unidad de medida y actualización vigente por kilómetro recorrido.\nIII.- SERVICIOS A DOMICILIO: con la tarifa de arrastre y maniobras de salvamento.\nIV.- MANIOBRAS INCONCLUSAS DE GRÚA:\nNo se pagarán los derechos por servicios de salvamento, arrastre y almacenaje en caso de maniobras inconclusas de grúa, cualquiera que sea la causa, de los siguientes vehículos: automóviles, camionetas, pick up, camiones de pasajeros (microbús), remolques (trailers) y autobuses de pasajeros, remolque de tractocamiones de tres o más cajas.\nV.- ALMACENAJE DE VEHÍCULOS\na).- Derechos:\nLos derechos por almacenaje de vehículos causarán, después de las primeras 24 horas una cuota de:\nPor cada 24 horas o fracción:\nUNIDAD DE MEDIDA Y\nACTUALIZACIÓN VIGENTE\n1).- Automóviles, Pick Up y Camionetas......... 0.58 veces\n2).- Camiones Urbanos de Pasajeros............. 1.32 veces\n3).- Autobuses de Pasajeros.................... 1.32 veces\n4).- Camiones de Carga......................... 1.32 veces\n5).- Tractocamiones............................ 1.32 veces\n6).- Remolques (trailers)...................... 1.32 veces\n7).- Tractocamiones con Remolque............... 1.84 veces\n8).- Motocicletas.............................. 0.45 veces\n9).- B icicletas................................ 0.14 veces\n10).- Otros..................................... 0.79 veces\nb).- Exención: oficiales de Autoridad Competente, se exentará del pago de los derechos de maniobras de salvamento, arrastre y almacenaje de vehículos, siempre y cuando el robo sea reportado dentro de las primeras 72 horas subsecuentes al hecho.\nc).- Generalidades:\nPara la Zona Suburbana y Zona Rural, se reducirá el 50% de las tarifas previstas por este artículo.\nd).- Tiempo:\nTratándose de vehículos retenidos por concepto de infracción, se le su vehículo sin cobro por los servicios de traslado y resguardo, desde necesarias para cubrir la o las multas.\n12 SERVICIOS QUE PRESTA SERVICIOS MÉDICOS MUNICIPALES\nARTÍCULO 29.- Los servicios proporcionados por Servicios Médicos\nMunicipales, se pagarán de acuerdo a la siguiente tarifa:\nUNIDAD DE MEDIDA Y\nACTUALIZACIÓN VIGENTE\nI.- Expedición de certificados prenupciales........ 3.31 veces\nII.- Consultas médicas.............................. 2.64 veces\nIII.- Servicios en el Centro de Atención de Enfermedades de\nTransmisión Sexual (C.A.E.T.S).\na).- Servicios o procedimientos de consulta vigente.................................. EXENTO\nb).- Servicios o procedimientos de consulta vencida.................................. 1.32 veces un 50% a aquellas personas que acrediten su insolvencia económica en el estudio socioeconómico que se les practique.\nIV.- Expedición de tarjeta de salud:\na).- Primera vez.............................. EXENTO\nb).- Reposición por extravío, mutilación o daño a la tarjeta........................ 1.32 veces\nV.- Credencial de identificación para personas con discapacidad.............................. 1.32 veces\nVI.- Expedición de tarjetón para uso de\nEstacionamiento en personas con discapacidad\nVII.- Expedición de tarjetón para uso de estacionamiento en personas con discapacidad permanente..................................... EXENTO\nVIII.- Por reposición por extravío, mutilación o daño al tarjetón para uso de Estacionamiento en personas con discapacidad..................... 1. 99 veces\nIX.- Certificado médico legal...................... 3.31 veces\nNo se causará este derecho, cuando el certificado sea expedido en favor de alguna persona que hubiere sido detenida y puesta a disposición de la autoridad competente, en los casos en que no se hubieren cometido ningún tipo de infracción al\nReglamento de Tránsito Municipal y/o Bando de Policía y\nGobierno aplicable.\nX.- Certificado médico legal con aplicación de alcoholímetro E/E............................. 6.61 veces\nXI.- Servicio de ambulancia en zona urbana por solicitud particular.......................... 15.87 veces\nXII.- Servicio de ambulancia en eventos particulares por hora...................................... 13.23 veces\nXIII.- Certificado de salud o discapacidad........... 1.32 veces\nXIV.- Otros servicios médicos....................... 3.31 a\n13.23 veces\nXV.- Atención Médica:\na).- Atención de heridas sin sutura.......... 1.32 veces\nb).- Atención de Heridas sin sutura de hasta\n3cms................................... 3.96 veces\nc).- Herida-Sutura de 3.1 a 10 cms........... 10.58 veces\nd).- Electrofulguración de verrugas Vulgares. 7.28 veces\ne).- Electrofulguración de condilomas........ 8.60 veces\nf).- Electrofulguración de úlceras cervicales 11.25 veces\nXVI.- Multa del módulo.............................. 5.00 veces\nARTÍCULO 30.- Los servicios proporcionados por Control Animal, se pagarán de acuerdo a la siguiente tarifa:\nI.- Servicios:\nUNIDAD DE MEDIDA Y\nACTUALIZACIÓN VIGENTE\na).- Consulta................................. 1.99 veces\nb).- Esterilización quirúrgica................ 3.96 veces\nc).- Desahucio Humanitario.................... 1.32 veces\nd).- Desparasitado............................ 1.99 veces\ne).- Vacuna contra el moquillo................ 3.31 veces\nf).- Enucleación.............................. 10.58 veces\ng).- Reparación de hernias.................... 6.61 veces\nh).- Reparación de heridas.................... 4.63 veces\ni).- Prolapso Vaginal......................... 10.58 veces\nj).- Mastectomía.............................. 8.60 veces\nk).- Emisión de microprocesador de identificación de mascota................ 5.29 veces\nl).- Emisión placa de identificación.......... 3.31 veces\nm).- Servicio de cremación para perros........ 1.32 veces\nII.- Se pagarán las siguientes cuotas de acuerdo a la captura y\nPosterior devolución del animal, adicionales a las cuotas de exija el Reglamento respectivo.\nUNIDAD DE MEDIDA Y\nACTUALIZACIÓN VIGENTE\na).- Captura (Devolución)..................... 9.70 veces\nSe otorgará el 50% de descuento en el pago de este derecho:\n1.- A aquellas personas que no sean reincidentes y acrediten cuenten con las vacunas.\n2.- Cuando la devolución se realice para la adopción de la mascota.\n13 SERVICIOS QUE PRESTA SEGURIDAD PÚBLICA MUNICIPAL\nARTÍCULO 31.- Los derechos por servicios que se soliciten a Seguridad\nPública se cobrarán:\nUNIDAD DE MEDIDA Y\nACTUALIZACIÓN VIGENTE\nI.- Por servicio permanente de vigilancia\nPolicíaca, por elemento por turno de ocho horas, al solicitarse el servicio............. 17.01 veces\nSe entenderá por servicio permanente de vigilancia Policiaca cuando se contrate por un término igual o mayor a seis meses de manera continua, para lo cual se deberá celebrar un contrato entre el Municipio y el solicitante, donde se establezcan los derechos y obligaciones para ambas partes, así mismo el pago de las bonificaciones en faltas, como retardos de los elementos, tendrá que ser dentro de los primeros seis meses en que ocurrieron las faltas.\nII.- Por servicio eventual de vigilancia Policíaca, por elemento por turno de ocho horas al solicitarse el servicio por dependencias y entidades gubernamentales de cualquier orden de gobierno................................... 6.61 veces\nIII.- Por servicio eventual de vigilancia Policíaca, por elemento por turno de ocho horas al solicitarse el servicio por iniciativa privada........................................ 26.46 veces\nIV.- Por servicio eventual de vigilancia policiaca por horas..................................... 13.00 veces discontinua, con total independencia del evento que se trate.\nV.- Por servicio en apoyo en cortejos fúnebres, por elemento.................................. 7.28 veces\nVI.- Por impartición de curso de manejo por persona 13.23 veces\nVII.- Por ratificación de peritajes de accidentes de tránsito...................................... 2.64 veces\nVIII.- Las personas físicas o morales que se dediquen a la instalación de alarmas comerciales e industriales, así como a los servicios de la opinión del Área de Seguridad Pública\nMunicipal debiendo cubrir las siguientes tarifas:\na).- Por la opinión para la apertura o inicio de actividades.......................... 132.30 veces\nb).- Por revalidación anual.................. 66.15 veces\nLa expedición o revalidación del documento a que se refiere esta fracción, se establece para las empresas que inicien actividades o ya estén operando, y deberán solicitarse a más tardar en el mes de marzo de cada año.\nARTÍCULO 32.- Los derechos por alimentación de detenidos estén o no a disposición de la autoridad investigadora o judicial local o federal, que hayan ingresado a separos, por la comisión de algún ilícito o estén compurgando una sanción administrativa, impuesta por el Juez\nCalificador, se pagarán 1.89 veces la Unidad de medida y actualización vigente en la entidad por día. Siempre y cuando se proporcione la alimentación antes mencionada.\nARTÍCULO 33.- Los derechos por traslado de detenidos a disposición de otras autoridades sean federales o estatales, y lo requieran para la práctica de diligencias ordenadas conforme a las leyes, serán los siguientes:\nUNIDAD DE MEDIDA Y\nACTUALIZACIÓN VIGENTE\nI.- Cuando el traslado se realice dentro de la misma mancha urbana de la Ciudad, se pagará por detenido.................................. 5.29 veces\nII.- Cuando el traslado se realice de la Ciudad a cualquier delegación municipal se pagará por detenido.......................... 15.87 veces\nIII.- Cuando el traslado se realice a otro municipio o viceversa, se pagará por detenido....................... 35.00 veces\nARTÍCULO 34.- La entrega de citatorios y notificaciones que expida cualquier autoridad para ser entregadas a las personas dentro de la municipalidad, así como la localización, búsqueda de personas y apoyo en diligencias, que soliciten las autoridades diversas de las municipales, causarán los siguientes derechos:\nUNIDAD DE MEDIDA Y\nACTUALIZACIÓN VIGENTE\nI.- La entrega de citatorios y diversas notificaciones que se realicen dentro de la mancha urbana de la Ciudad se pagarán......... 2.64 veces\nII.- La entrega de citatorios y diversas notificaciones que se realicen fuera de la mancha urbana de la Ciudad se pagarán......... 5.29 veces\nIII.- La búsqueda o localización de personas y/o domicilios se pagará, por quien lo solicite.. 5.29 veces\nIV.- Apoyo en diligencias ordenadas por autoridad judicial, administrativa o laboral por elemento diario............................... 3.96 veces\nMUNICIPIO DE SAN FELIPE\n(DARE);\nVulnerabilidad (UMAPEV);\nEscuadrón Juvenil Deportivo (ESJUDE); y\nUnidad Canina (K9)\nARTÍCULO 35.- Los ingresos que por concepto de derechos, transferencias, asignaciones y ayudas sociales que se perciban con motivo del Programa, pasarán a formar parte del patrimonio municipal.\n14 SERVICIOS QUE PRESTA\nBOMBEROS, PROTECCIÓN CIVIL Y PROTECCIÓN AL AMBIENTE\nARTÍCULO 36.- Los servicios que presta Bomberos a giros comerciales, causarán conforme a la siguiente tarifa:\nA.- PROYECTOS DE CONSTRUCCIÓN\nI.- Revisión y autorización de sistemas contra incendios y dispositivos de seguridad en proyectos de construcción:\nUNIDAD DE MEDIDA Y\nACTUALIZACIÓN VIGENTE\nCONSTRUCCIÓN REGULARIZACIÓN\na).- Casa-habitación por m²........ 0.063 veces 0.075 veces\nb).- Comercial por m² de construcción.................. 0.10 veces 0.11 veces\nc).- Industrial, naves de inventario, almacenes, bodegas por m² de construcción........ 0.26 veces 0.40 veces\nd).- Administrativo/Oficinas por m² de construcción............... 0.13 veces 0.16 veces\ne).- Barda, fachada y remodelaciones por m²:\nCasa-Habitación............... 0.025 veces 0.037 veces\nComercial..................... 0.063 veces 0.075 veces\nIndustrial.................... 0.13 veces 0.16 veces\nf).- Por análisis y autorización de proyecto para Estaciones de\nCarburación, Estaciones de servicio, autoconsumo y/o giros similares............... 2 64.60 veces 396.90 veces\ng).- Estacionamientos por m² de terreno....................... 0.088 veces 0.10 veces\nh).- Instalaciones: Estaciones y\nSub-Estaciones eléctricas, torres y antenas de telefonía, carteleras espectaculares,\ni).- Las microempresas por m² que ingresen por trámite S.A.R.E\nSistema de Apertura Rápida de\nEmpresas) de hasta 100 m²..... 0.088 veces 0.10 veces\nII.- Por la asesoría de anteproyectos de sistemas contra incendios y dispositivos de seguridad.\na).- Proyecto Comercial........................ 13.23 veces\nb).- Proyecto Industrial....................... 13.23 veces\nB.- INSPECCIÓN Y VERIFICACIÓN DE DISPOSITIVOS DE SEGURIDAD EN\nEDIFICIOS EXISTENTES, DE OFICIO O A PETICIÓN DE PARTE:\nI.- Comercio en pequeño, hasta de 30 m² de superficie 3.96 veces\nII.- Giro de servicio como: estéticas/peluquerías, veterinarias, internet, sastrerías, costureras, planchadurías, lavanderías y giros similares..... 5.29 veces\nIII.- Giro mercantil/comercial, templos religiosos y otros............................................ 10.58 veces\nIV.- Salón y parque de fiestas........................ 19.84 veces\nV.- Abarrotes, mercado, supermercado, licorerías, autoservicios, papelerías, hospitales/clínicas, salas cinematográficas, tortillerías, teatros, plazas comerciales, oficinas administrativas, refaccionarias por m² de construcción:\na).- Hasta 50 m²................................ 5.29 veces\nb).- De 51 hasta 150 m²......................... 10.58 veces\nc).- De 151 a 500 m²............................ 39.69 veces\nd).- De 501 a 1,000 m².......................... 52.92 veces\ne).- De 1,001 a 2,000 m²........................ 66.15 veces\nf).- De 2,001 a 3,000 m²........................ 92.61 veces\ng).- De 3,001 m² en adelante.................... 105.84 veces\nVI.- Restaurante, restaurante bar, Cantinas, Bar, Video-Bar, Karaoke, Café cantante, Bar Terraza, Palenque (casteo), Discotecas y giros similares:\na).- Hasta 50 m²................................ 10.58 veces\nb).- De 51 hasta 150 m²......................... 33.07 veces\nc).- De 151 a 500 m²............................ 52.92 veces\nd).- De 501 a 1,000 m².......................... 105.84 veces\nRestaurantes con venta para consumo únicamente de vinos de mesa nacionales, sala de degustación exclusiva de cerveza artesanal, boutique de cerveza artesanal o establecimientos destiladores, fermentadores y\n/o establecimientos vinícolas tendrán un 25% de descuento al solicitar el servicio de manera oportuna.\nVII.- Tiendas departamentales, Centros de espectáculos, Centros/Parques recreativos con dos o más albercas, clubes deportivos por giro............ 105.84 veces\nVIII. Moteles:\na).- Hasta 10 habitaciones...................... 19.84 veces\nb).- De 11 a 20 habitaciones.................... 26.46 veces\nc).- De 21 habitaciones en adelante............. 33.07 veces\nIX.- Hoteles:\na).- Hasta 30 habitaciones...................... 39.69 veces\nb).- De 31 habitaciones en adelante............. 52.92 veces\nc).- De tres niveles o más...................... 105.84 veces\nX.- Edificios Educativos Públicos................... 2.64 veces\nXI.- Edificios Educativos Privados, Estancias\nInfantiles, Asilos, Casa hogar, Centros de\nRehabilitación:\na).- Hasta 10 aulas............................. 18.52 veces\nb).- De 11 aulas en adelante.................... 33.07 veces\nInstituciones educativas públicas de los tres niveles de gobierno, gratuita a enfermos que padezcan cáncer y personas en situación vulnerable, estarán exentos del pago de derechos a que se refiera el inciso B, presentando documentación comprobatoria de los servicios prestados de forma gratuita.\nXII.- En empresas dedicadas al reciclaje en general y tarimeras...................................... 66.15 veces\nXIII. Chatarreras, en empresas dedicadas a la desmantelación de vehículos (Yonkes)............ 26.46 veces\nXIV.- Otros giros no especificados.................... 13.23 veces\nEDIFICIOS INDUSTRIALES:\nXV.- Industria, almacenes, bodegas, naves de inventario, empacadoras:\na).- Hasta 2,000 m²............................. 66.15 veces\nb).- De 2,001 hasta 4,500 m².................... 132.30 veces\nc).- De 4,501 m² adelante....................... 264.60 veces\nGIROS DE ALTO RIESGO:\nXVI. Industria generadora de electricidad, distribuidoras de gases comprimidos y criogénicos, combustibles y lubricantes, oxígenos y acetilenos, polvorines, Plantas de\nAlmacenamiento de gas, Licuado de Petróleo y\nLubricantes y demás establecimientos de alto riesgo.......................................... 264.60 veces\nXVII Estación de distribución de Gas L.P. u Otros\nGases Licuados. (Almacenamiento de hasta 10,000 litros)......................................... 132.30 veces\nXVIII Planta de distribución de Gas L.P. u Otros Gases\nLicuados (Almacenamiento hasta 5,000 litros).... 66.15 veces\nXIX.- Estaciones de gasolina/estaciones de autoconsumo\n(Hasta 4 dispensarios).......................... 66.15 veces\nXX.- Estaciones de gasolina/estaciones de autoconsumo\n(Mayor de 4 dispensarios)....................... 132.30 veces\nXXI Mercados y abarrotes con venta de minas de gas LP 33.07 veces\nCENTROS DE APUESTAS, APUESTAS REMOTAS, SALAS DE SORTEOS DE NÚMEROS\nY/O CASINOS PALENQUES (APUESTAS DE GALLOS).\nXXII Inspección anual................................ 264.60 veces\nXXIII Dictamen de operación/permiso de ocupación...... 264.60 veces\nPara los casos en que los solicitantes de los servicios no cumplan con las normas o sistemas de prevención de incendios en su primera visita de inspección, podrán solicitar su posterior verificación, la cual se realizará por el 50% del costo estipulado para la inspección que corresponda, sin perjuicio de la aplicación de las sanciones que prevé dispositivos de seguridad correspondientes.\nC.- ANÁLISIS Y/O DICTAMEN DE FACTIBILIDAD PARA LA PRESTACIÓN DE\nSERVICIOS DE BOMBEROS EN PROYECTOS DE DESARROLLOS URBANOS:\nI.- Desarrollo habitacional:\na).- Hasta 5,000 m²............................. 66.15 veces\nb).- Mayor de 5,001 m².......................... 132.30 veces\nII.- Desarrollo industrial y comercial............... 132.30 veces\nIII.- Cambio de régimen de propiedad, cambio de razón social.......................................... 26.46 veces\nD.- CERTIFICACIÓN DE DAÑOS EN BIENES SINIESTRADOS:\nI.- Casa habitación................................. EXENTO\nII.- Comercio........................................ 66.15 veces\nIII.- Industria....................................... 132.30 veces\nIV.- Agrícola........................................ 66.15 veces\nV.- Vehículos particulares.......................... 6.61 veces\nVI.- Vehículos comerciales........................... 13.23 veces\nQuedan exceptuados del pago de este derecho, aquellas casashabitación que no se encuentren aseguradas al ocurrir el siniestro.\nE.- EXPEDICIÓN DE CERTIFICACIÓN DE EQUIPO Y DISPOSITIVOS DE\nSEGURIDAD:\nI.- Vivienda, comercio pequeño..................... 3.96 veces\nII.- Comercio........................................ 13.23 veces\nIII.- Industria....................................... 19.84 veces\nIV.- Certificación de sistemas hidráulicos contra incendios/Sistemas de detección de incendios\n/iluminación................................... 66.15 veces\nV.- Comercios dedicados a la venta, Renta y mantenimiento de extintores.................... 66.15 veces\nF.- REVISIÓN DE LAS CONDICIONES DE SEGURIDAD EN LAS INSTALACIONES\nTEMPORALES:\nI.- Circos y ferias................................ 26.46 veces\nII.- Juegos mecánicos por aparato mecánico revisado 1.32 veces\nIII.- Exposiciones, kermeses y otros no especificados.................................. 13.23 veces\nIV.- Bailes populares............................... 39.69 veces\nV.- Eventos masivos de más de 1,000 personas....... 52.92 veces\nVI.- Eventos deportivos y culturales................ 19.84 veces\nPara los supuestos del inciso F, fracciones I, II, III, IV y VI, los eventos promovidos por dependencias o entidades gubernamentales, juntas de mejoramiento, organismos descentralizados de gobierno, entidades paraestatales y municipales, por las asociaciones religiosas constituidas legalmente, por asociaciones civiles con fines no lucrativos que sean organizados conjuntamente con las entidades públicas a que se refiere este párrafo y que tengan por objeto allegarse de recursos para el cumplimiento de sus fines, estarán exentos de este pago.\nG.- SERVICIOS ESPECIALES:\nCURSO:\nI.- Cursos de orientación en caso de sismo, incendios, evacuación de inmuebles............. 33.07 veces\nII.- Formación de brigadas y combate a incendios.... 66.15 veces\nIII.- Primeros auxilios.............................. 66.15 veces\nIV.- Manejo de extintores........................... 39.69 veces\nV.- Prevención de incendios........................ 39.69 veces\nVI.- Uso y manejo de mangueras contra incendios..... 66.15 veces\nVII.- Bombero infantil............................... 13.23 veces\nVIII. Supervisión de simulacros...................... 13.23 veces\nIX.- Otros cursos no especificados.................. 13.23 veces sin fines de lucro.\nUSO DE EQUIPO POR EVENTO:\nX.- Máquina extintora........................... 56.70 veces\nXI.- Máquina de iluminación......................... 39.69 veces\nXII.- Máquina escala................................. 39.69 veces\nXIII. Ambulancia en caso de eventos deportivos o sociales....................................... 25.20 veces\nXIV.- Por servicios de supervisión contratados para cubrir eventos públicos o privados, por bombero 6.61 veces\nQuedan exentas del Cobro en lo que se refiere a las fracciones X, XI, XII, XIII y XIV las Instituciones de Gobierno y asociaciones sin fines de lucro.\nREVISIÓN DE EXPLOSIVOS:\nXV.- Revisión de polvorines o permisos de explosivos 1 3 2.30 veces\nXVI.- Centros de distribución al menudeo............. 132.30 veces\nXVII. Revisión de castillos pirotécnicos............. 13.23 veces\nH.- REVISIÓN DE DOCUMENTACIÓN.\nI.- Plan de contingencias contra incendios......... 33.07 veces\nII.- Análisis de riesgos............................ 26.46 veces\nIII.- Expedición de oficio de terminación de Obra.... 13.23 veces\nIV.- Expedición de carta de no inconveniente....... 13.23 veces\nPara los supuestos del inciso H, Fracción IV, los eventos realizados municipio, se les cobrara el 50% del pago por la expedición del documento.\nI.- TRAMITES INGRESADOS POR EL SISTEMA DE APERTURA RAPIDA DE\nEMPRESAS (SARE).\nI.- Por concepto de Inspección certificación....... 19.84 veces\nLos servicios a que hace referencia este artículo, cuando se trate de escuelas públicas, quedarán exentas de pago.\nARTÍCULO 37.- Los servicios que presta Protección Civil a los inmuebles e instalaciones fijas y móviles de las dependencias, entidades, instituciones, organismos, industrias o empresas, pertenecientes a los sectores público, privado y social, se pagarán conforme a la siguiente tarifa:\nI.- Por la elaboración y/o asesoría de programas específicos en materia de Protección Civil:\nUNIDAD DE MEDIDA Y\nACTUALIZACIÓN VIGENTE\na).- Asesoría para elaboración de programa interno de Protección Civil por m² de construcción:\nHasta 50 m²................................. 79.20 veces\nDe 51 a 90 m²............................... 132.30 veces\nDe 91 a 500 m².............................. 198.45 veces\nDe 501 a 1,000 m²........................... 396.90 veces\nDe 1,001 m² en adelante..................... 793.80 veces\nb).- Elaboración de análisis de vulnerabilidad y riesgo:\n1.- Revisión para la aprobación de estudios de análisis de riesgos para la licencia de construcción:\nHasta 90 m²................................. 65.52 veces\nDe 91 a 500 m².............................. 132.30 veces\nDe 501 a 1,000 m²........................... 264.60 veces\nDe 1,001 m² en adelante..................... 529.20 veces\n2.- Elaboración de Dictamen de Estabilidad\nEstructural:\nHasta 90 m²................................. 81.90 veces\nDe 91 a 500 m².............................. 138.60 veces\nDe 501 a 1,000 m²........................... 270.60 veces\nDe 1,001 m² en adelante..................... 567.00 veces\n3.- Para uso y ocupación.\nFijos por m² de construcción:\nHasta 90 m²................................. 105.84 veces\nDe 91 a 500 m².............................. 198.45 veces\nDe 501 a 1,000 m²........................... 330.75 veces\nDe 1,001 m² en adelante..................... 661.50 veces\nc).- Dictamen de factibilidad en materia de\nProtección Civil............................ 132.30 veces\nPara los servicios a que se refiere esta fracción, en población fuera de la zona urbana pagarán 10 veces la Unidad de medida y actualización vigente adicional hasta cien kilómetros, después de cien kilómetros pagara 15 veces la Unidad de medida y actualización vigente adicionales.\nII.- Por revisión y autorización de programas específicos en materia de\nProtección Civil:\nUNIDAD DE MEDIDA Y\nACTUALIZACIÓN VIGENTE\na).- Eventos temporales masivos:\nHasta 300 personas.......................... 13.86 veces\nDe 301 a 500 personas....................... 26.46 veces\nDe 501 a 1,000 personas..................... 52.92 veces\nDe 1,001 a 3,000 personas................... 79.38 veces\nDe 3,001 a 6,000 personas................... 105.84 veces\nDe 6,001 en adelante........................ 132.30 veces\nb).- Programa interno de Protección Civil:\n1.- Por primera revisión:\nHasta 50 m²................................ 10.00 veces\nDe 51 a 120 m²................................ 44.10 veces\nDe 121 a 500 m²............................. 73.08 veces\nDe 501 a 1,000 m²........................... 146.16 veces\nDe 1,001 m² en adelante..................... 291.06 veces\n2.- Revalidación anual.......................... 7.56 veces\nEdificios de Gobierno, Escuelas Públicas y casas hogar, quedan exentos del cobro de derechos por este rubro.\nIII.- Multas por incumplir o no contar con el programa interno de\nProtección Civil:\nEn base a lo establecido en la Ley de Protección Civil y Gestión Integral de Riesgos del Estado de Baja California se impondrá una sanción del 30% por el incumplimiento al Programa Interno de Protección Civil y todas aquellas faltas a la Ley General de Protección Civil y legislación en materia, en caso de reincidencia se aplicará una sanción por el 100% del aplicarse.\nIV.- Servicios de Capacitación:\nCursos que se imparten.\nUNIDAD DE MEDIDA Y\nACTUALIZACIÓN VIGENTE\na).- Nivel básico en primeros auxilios para el primer respondiente:\n1.- Hasta 25 personas...................... 26.46 veces\n2.- De 26 hasta 50 personas................ 46.30 veces\n3.- De 51 hasta 100 personas............... 66.15 veces\nb).- Búsqueda y rescate:\n1.- Hasta 25 personas...................... 26.46 veces\n2.- De 26 hasta 50 personas................ 46.30 veces\n3.- De 51 hasta 100 personas............... 66.15 veces\nc).- Rutas de evacuación y señalización:\n1.- Hasta 25 personas...................... 26.46 veces\n2.- De 26 hasta 50 personas................ 46.30 veces\n3.- De 51 hasta 100 personas............... 66.15 veces\nd).- Formación de unidades internas de Protección\nCivil....................................... 66.15 veces\ne).- Elaboración de programas internos de\nProtección Civil............................ 66.15 veces\nf).- Elaboración de análisis de riesgo........... 66.15 veces\ng).- Otros no especificados...................... 13.23 veces\nEn el caso de los tres primeros cursos que se menciona, el cupo máximo será de 100 personas.\nQuedan exentas del cobro las instituciones de Gobierno, Escuelas\nPúblicas y Casas Hogar; así mismo como los que encuadren en el supuesto del artículo 17 de la presente Ley.\nV.- Asistencia y evaluación presencial en un Simulacro: 12.60 veces\nQuedan exentas del cobro las instituciones de Gobierno, Escuelas\nPúblicas y Casas Hogar; así mismo como los que encuadren en el supuesto del artículo 17 de la presente Ley.\nVI.- Otros Servicios:\nUNIDAD DE MEDIDA Y\nACTUALIZACIÓN VIGENTE\na).- Otros servicios no especificados............ 13.23 veces\nARTÍCULO 38.- Los servicios que presta Protección al Ambiente se pagarán conforme a lo siguiente:\nI.- Por la recepción y evaluación de documentos para resolver en materia ambiental municipal:\nUNIDAD DE MEDIDA Y\nACTUALIZACIÓN VIGENTE\na).- En caso de construcción de fraccionamientos:\n1).- Industriales........................... 378.00 veces\n2).- Habitacionales......................... 252.00 veces\nb).- En caso de construcción para la distribución de gas butano, gasolineras, almacenes de hidrocarburos, almacenes de sustancias químicas......................... 189.00 veces\nc).- En caso de construcción de centro de acopio:\n1).- Residuos sólidos urbanos............... 126.00 veces\n2).- Residuos de manejo especial............ 189.00 veces\n3).- Residuos peligrosos.................... 252.00 veces\nd).- Para la operación de centro de acopio, separación o aprovechamiento de residuos sólidos urbanos.............................\n1. Primera vez........\n132.30 veces\n2. Revalidación anual\n66.00 veces\ne).- Para la construcción de comercios y/o servicios con una superficie de:\n1).- Hasta 150 m²........................... 18.90 veces\n2).- Mayor a 151 m² y hasta 500 m².......... 31.50 veces\n3).- Mayor a 501 m² y hasta 1,000 m²........ 44.10 veces\n4).- Mayor a 1,001 m² y hasta 2,000 m².... 56.70 veces\n5).- Mayor a 2,000 m²........... 81.90 veces\nf).- Para actividades comerciales y/o de servicios:\n1).- Con superficie de construcción hasta\n150 m²:\n1.1).- Primera vez........................ 12.60 veces\n1.2).- Revalidación anual................. 3.78 veces\n2).- Con superficie de construcción mayor a\n151 m² y hasta 500 m²:\n2.1).- Primera vez........................ 25.20 veces\n2.2).- Revalidación anual................. 7.56 veces\n3).- Con superficie de construcción mayor de\n501 m² y hasta 1,000 m²:\n3.1).- Primera vez........................ 37.80 veces\n3.2).- Revalidación anual................. 12.60 veces\n4).- Con superficie de construcción mayor a\n1,001 m²:\n4.1).- Primera vez........................ 50.40 veces\n4.2).- Revalidación anual................. 18.90 veces\ng).- Para comercios o servicios ingresada por el sistema de apertura rápida hasta 100 m² de superficie de construcción.................. 6.61 veces\nh).- Para la evaluación de obra civil para casa habitación, por única vez.. 2.70 veces\ni).- Para el Aprovechamiento de Materiales Pétreos\n1. Primera vez........................\n139.00 veces\n2. Revalidación anual.................\n69.50 veces\nj).- Para Comercio Ambulante Fijo y Semifijo, anual\nK).- Por verificación e inspección de solicitudes\nL).- Para comercios y/o servicios temporales (90 días)\nII.- Otros Dictámenes y Servicios en Materia Ambiental:\na).- Por la emisión de dictámenes técnicos y de factibilidad ambiental:\nEn todos los casos.......................... 39.69 veces\nb).- Por la emisión de autorizaciones para la recolección y transporte de:\n1).- Residuos sólidos urbanos, No-peligrosos: neumáticos usados, de la construcción o demolición, por cada vehículo anual.... 26.46 veces\n2).- Aguas residuales, por cada vehículo anual.................................. 13.23 veces\nc).- Por permiso para la remoción y/o trasplante de árboles y otras plantas:\nPor cada organismo vegetativo............... 6.61 veces\nSe exime el pago de solicitud o permiso por remoción de troncos de árboles secos.\nd).- Por autorización anual para la quema de fuegos artificiales o pirotécnicos.......... 630.00 veces\n1).- Por autorización eventual para la quema de fuegos artificiales o pirotécnicos 30.32 veces\nSe exenta de pago en festividades que se celebren conforme a las tradiciones de los habitantes del Municipio, previa autorización.\ne).- Copia de documentos por expediente por fojas:\nDe 1 a 25................................... 1.32 veces\nDe 26 a 50.................................. 2.64 veces\nDe 51 en adelante........................... 3.96 veces\nf).- Por la recepción y evaluación de solicitudes de prórrogas de tiempo para el cumplimiento de resoluciones administrativas emitidas por la dependencia 2.64 veces\ng).- Por la autorización ambiental para la utilización de equipos de perifoneo en unidades móviles hasta 30 días.............. 6.61 veces\nh).- Por autorización ambiental para la utilización de equipo de sonido en establecimientos comerciales y de servicios:\nPor 30 días................................. 63.00 veces\ni).- Por la autorización ambiental anual para la utilización de anuncios luminosos de fuentes fijas en establecimientos comerciales y de servicios................................... 2 2.36 veces\nj).- Por autorización ambiental para la utilización de anuncios luminosos en unidades móviles hasta por 6 meses.......... 1 3.23 veces\nk).- Por dictamen relativo a áreas verdes dentro de fraccionamientos habitacionales e industriales................................ 37.80 veces\nl).- Por dictamen relativo a la arborización de estacionamientos mayores a 9 cajones........ 37.80 veces\nm).- Por el estudio y evaluación de factibilidad para formar parte del padrón de prestadores de servicios ambientales en calidad de auditores................................... 6.30 veces\nn).- Por la inscripción al padrón de prestadores de servicios ambientales en calidad de auditores................................... 10.08 veces ñ).- Por la evaluación para permanecer inscrito en el padrón de prestadores de servicios ambientales en calidad de auditores......... 3.78 veces\no).- Por revisión física mecánica anual:\n1.- Automóviles particulares por unidad...... EXENTO\n2.- Infracción por incumplimiento a la revisión mecánica a cargo de particulares............ 4.00 veces\np).- Capacitación de operadores del transporte público y emisión de constancia respectiva............................... 3.78 veces\nq).- Por la emisión de factibilidad ambiental para eventos temporales\n2.- De 501 a 1000 personas.......... 27.00 veces\n3.- Mayor a 1000 personas.......... 40.00 veces\n4.- Evento temporal sin fines de lucro y/o promocionados por el Gobierno Municipal..\nPara los permisos referentes a lo estipulado en los numerales 1 y 2 del inciso q) de la Fracción II del presente artículo, se otorgará un\n50% de descuento, a promotores de la localidad, siempre y cuando acrediten ser residentes del Municipio de San Felipe con documentación oficial vigente.\n15 SERVICIOS QUE PRESTA ADMINISTRACIÓN URBANA\nA) CONTROL URBANO\nARTÍCULO 39.- Los servicios que presta control urbano, por Licencias de Construcción se pagarán conforme a lo siguiente:\nI.- REVISIÓN DE SOLICITUDES Y EXPEDICIÓN DE LICENCIAS DE EDIFICACIÓN,\nAMPLIACIÓN, REMODELACIÓN, DEMOLICIÓN DE INMUEBLES, INSTALACIONES,\nANUNCIOS Y OTROS permisos o licencias, deberán ser cubiertos por los solicitantes, de acuerdo con la siguiente tarifa:\nPara construcción, reconstrucción, ampliación, remodelación y otras construcciones de edificios habitacionales, comerciales e industriales, de acuerdo a la siguiente tabla:\nUNIDAD DE MEDIDA Y\nTARIFA\nACTUALIZACIÓN VIGENTE\n1.- Casa habitación y vivienda de interés social unifamiliares, tratándose de cualquier tipo de inmuebles.\na).- Para vivienda nueva y ampliaciones hasta\n40 m² propiedad de particulares, en fraccionamientos y colonias pagará.......... 6.93 veces\nb).- Para vivienda nueva y ampliaciones de 40 m² a 60 m² propiedad de particulares, en fraccionamientos y colonias pagará.......... 16.63 veces\nc).- Para vivienda nueva y ampliaciones de 60 m² a 120 m², propiedad de particulares, en fraccionamientos y colonias se pagará....... 33.26 veces\nd).- Para vivienda nueva y ampliación mayor a\n120 m², propiedad de particulares, en\nFraccionamientos y colonias pagará por el total, por metro cuadrado................... 0.35 veces\nLas viviendas particulares mayores a 60 m2 que se inicien sin licencia de construcción, pagarán 50% por regularización adicional al costo de la licencia.\nPor las viviendas menores a 60 m2 propiedad de particulares, se pagará 50% menos presentando carta de no propiedad.\n2.- Para la instalación de cada módulo prefabricado tipo casa móvil:\na).- Para uso habitacional, por unidad incluye el retiro...................................... 21.42 veces\n3.- Para comercio y servicios hasta 100 m² de móvil............................................ 72.07 veces\nPor cada 100 m² o fracción subsecuente........... 41.58 veces\n4.- Para industria hasta de 100 m² de construcción incluyendo prefabricado tipo casa móvil.......... 55.44 veces\nPor cada 100 m² o fracción subsecuente........... 55.44 veces\n5.- Estacionamiento y patios de maniobras para industria, comercio y servicios con necesidad:\na).- Hasta 40 cajones de estacionamiento......... 15.24 veces\nb).- De 41 a 100 cajones de estacionamiento...... 27.72 veces\nc).- Por cada cajón subsecuente.................. 0.27 veces\n6.- Bardas, cercos y fachadas:\nHasta 100 metros lineales........................ 9.70 veces\nPor cada 100 metros lineales subsecuentes........ 9.70 veces\n7.- Movimiento de tierras por los primeros 1,000 m² o fracción......................................... 18.01 veces\nPor cada 1,000 m² adicionales o fracción......... 2.07 veces\n8.- Prórroga de licencia de edificación:\na).- Para habitacionales, en todos los rangos de superficie por cada vivienda................ 6.93 veces\nb).- Por edificación comercial y servicio........ 13.86 veces\nc).- Por edificación industrial.................. 27.72 veces\nd).- Por barda................................... 6.93 veces\n9.- Terminación de obra y autorización de ocupación:\na).- Para viviendas con superficie de\nb).- Para habitacionales mayores de 60 m² de superficie por cada vivienda................ 8.31 veces\nc).- Comercial y de servicios.................... 20.79 veces\nd).- Industrial por cada edificación............. 48.51 veces\n10.- Para instalaciones y/o estructuras no habitables, por cada unidad que requiera de análisis en materia de construcción, se pagarán derechos de acuerdo a la siguiente tabla:\na).- Hasta 20 m² de superficie en construcción... 36.03 veces\nb).- Por cada 10 m² o fracción en construcción subsecuente................................. 4.15 veces\nc).- Por cada unidad de cisternas, fosas, tanques, silos y otros.............................. 2 7.72 veces\nd).- Por la instalación de Paneles Solares por cada módulo................................. 0.25 veces\nEn uso habitacional y generador de área sombreada para estacionamiento y andadores será EXENTO.\n11.- Para la demolición parcial o total de edificaciones se pagará de acuerdo a la siguiente tarifa:\na).- Por cada 100 m²............................. 14.49 veces\nb).- Demolición de cordón para modificación, por metro lineal................................ 0.55 veces\nc).- Demolición de banquetas para modificación, por metro cuadrado.......................... 0.41 veces\nd).- Demolición para reposición o construcción de banqueta y cordones de vía pública.......... E X ENTO\ne).- Demolición de cualquier tipo de edificación en estado de abandono para mejorar las\n12.- Por expedición de Factibilidad de Licencia de\nConstrucción para las siguientes edificaciones:\na).- Habitacionales.............................. 11.08 veces\nb).- Comerciales y de servicios.................. 2 0.79 veces\nc).- Industrial.................................. 27.72 veces\n13.- Por la autorización de licencia incluida la o aéreos sobre la vía pública:\na).- Por canalización que incluya una o más tuberías, cuya suma de diámetros sea menor a\n9 cm. por cada 10 metros lineales o fracción 1.38 veces\nb).- Por canalización que incluya una o más tuberías, cuya suma de diámetros sea mayor a\n9 cm. por cada 10 metros lineales o fracción 2.77 veces\nc).- Por reparación o sustitución de línea subterránea con circuitos de uno o mas cableados, sin modificar canalización por cada 10 metros lineales o fracción.......... 0.69 veces\nd).- Para instalaciones aéreas, con circuitos de uno o más cableados en la misma trayectoria, por cada 10 metros lineales o fracción... 2.77 veces\ne).- Para estructuras subterráneas como registros, cajas de válvulas, etc. por m².............. 4.15 veces\nf).- Para estructuras sobre y/o empotradas en la vía pública como módulos, casetas, registros, etc............................. f.1).- Hasta 2.00 m²........................ 3.46 veces f.2).- Por cada m² o fracción adicional..... 2.07 veces\ng).- Prórroga de licencia para la instalación de líneas aéreas y subterráneas sobre la vía pública..................................... 1 3.86 veces\nh).- Terminación de obra licencia instalación de\nLíneas aéreas y subterráneas sobre la vía pública..................................... 2 0.79 veces\n14.- Construcción de alberca o instalación de albercas prefabricadas por m3…...\na).- Casa habitación Unifamiliar 0.50 veces\nb).- Otros 1.75 veces\n15.- Revisión de documentación para incorporación al padrón de Perito responsable de Proyectista y/o\nDirector de obra:\na) Por revisión inicial......................... 15.00 veces\nb) Por revisión subsecuente anual.............. 10.00 veces\nEn caso de remodelación de interiores sin afectar estructura, donde se edificación, se cobrará el 50% de la tarifa anterior.\nEn caso de regularización de cualquier tipo de trámite o autorización, se incrementará en un 50% de las tarifas fijadas en la presente fracción.\nPor la evaluación de anteproyectos arquitectónicos, previa a la expedición del permiso o licencia, se cobrará 12.60 veces la Unidad de medida y actualización vigente.\nCuando el número de revisiones de dichos proyectos exceda de dos veces para un mismo trámite, siendo esto imputable al propietario, se cobrará adicionalmente el 50% de la tarifa anterior.\nLas edificaciones u obras públicas destinadas a escuelas y en general a equipamientos y servicios, incluyendo redes y urbanizaciones que se construyan en predios propiedad del Gobierno Federal, Estatal o\nMunicipal, estarán exentos del pago de los derechos a que se refiere esta fracción.\nII.- POR ANÁLISIS DE SOLICITUDES Y EMISIÓN DE DECLARATORIA PARA\nCONSTITUIR REGÍMENES DE PROPIEDAD EN CONDOMINIO DE INMUEBLES\nA).- Por análisis de anteproyectos de conjuntos habitacionales, Comerciales, industriales o mixtos, únicos, que estarán bajo el régimen de propiedad en condominio, se pagará:\nUNIDAD DE MEDIDA Y\nACTUALIZACIÓN VIGENTE\n1.- Por conjunto hasta de 10 unidades........... 34.65 veces\n2.- Por cada unidad que exceda de las diez primeras.................................... 4. 85 veces\nB).- Por análisis de anteproyectos de conjuntos habitacionales, comerciales, industriales o mixtos, que se utilizarán en forma inmobiliario, se pagará por el primero las mismas cuotas del inciso anterior, y el 10% de éstas para las subsecuentes.\nC).- Por análisis y dictamen de factibilidad de conversión al habitacionales, comerciales, industriales o mixtos ya construidos se pagará:\n1.- Por fraccionamientos habitacionales hasta de\n10 unidades................................. 34.65 veces\n2.- Por cada unidad habitacional que exceda de las diez primeras........................... 4.85 veces\n3.- Por Centros Comerciales, urbanos o sub urbanos hasta de 5 unidades................. 6 2.37 veces\n4.- Por cada unidad comercial que exceda de las cinco primeras.............................. 5. 54 veces\n5.- Por cada unidad industrial hasta 1,000 m²... 1 8.01 veces\n6.- Por cada m² o fracción subsecuente.......... 0. 063 veces\nD).- Por la emisión de la declaratoria para la constitución del régimen de propiedad en condominio de inmuebles, se pagará por cada lote, departamento, vivienda, casa o local comercial en la forma siguiente:\n1.- Por cada unidad habitacional............ 13.86 veces\n2.- Por cada unidad comercial............... 31.87 veces\n3.- Por cada unidad industrial de hasta 1,000 m² 62.37 veces\n4.- Por cada m² o fracción subsecuente.......... 0.075 veces\nE).- Por verificación y certificación de memorias descriptivas de departamentos, viviendas, casas o locales, pertenecientes a condominios, se pagará por la primera revisión en la forma siguiente:\n1.- Por cada conjunto hasta de 5 unidades....... 48.51 veces\n2.- Por cada unidad excedente................... 9.00 veces\nEn el caso de revisiones subsecuentes, se pagará el 50% de la cuota prevista para la primera revisión, siempre y cuando se trate de observaciones de la autoridad.\nF).- Por emisión de constancia de traslación de\nDominio.......................................... 55.44 veces\nG).- Por constancia para cancelación de fianza en condominios...................................... 27.72 veces\n“A” y “B”, se hará previa notificación de Control Urbano, una vez determinados los lotes o unidades resultantes.\nEn el caso de no enterar en la Recaudación de Rentas del\nMunicipio el monto total de estos derechos en un plazo de 20 días a partir de la fecha de su notificación, se suspenderá el trámite correspondiente.\nIII.- PARA CONSTRUCCIÓN, RECONSTRUCCIÓN, AMPLIACIÓN Y REMODELACIÓN DE\nMÓDULO AEROGENERADOR DE ENERGÍA EÓLICA Y PARQUE DE ENERGÍA SOLAR\nUNIDAD DE MEDIDA Y\nACTUALIZACIÓN VIGENTE\na).- Construcción de módulo aerogenerador de energía eólica.......................... 3,791.89 veces\nb).- Construcción de parque de energía solar\n1.- Hasta 500.00 m2......................... 0.10 veces por m2 de construcción\n2.- Mayor de 500.00 m2...................... 0.05 veces por m2 de construcción\nc).- Construcción y/o instalación de torre de medición de vientos.\n1.- Hasta 10.00 metros de altura.............. 50.56 veces\n2.- Mayor de 10.00 y hasta 20.00 metros de altura.................................... 200.23 veces\n3.- Mayor de 20.00 y hasta 30.00 metros de altura.................................... 505.58 veces\n4.- Mayor de 30.00 metros de altura............ 758.38 veces\nd).- Construcción de edificaciones para 4.04 veces por m² generación de energía de construcción\ne).- Por expedición de prórroga de licencia de construcción:\n1.- Instalaciones para la generación y transmisión de energía eólica.\na) Por primer aerogenerador de energía eólica.................................... 151.68 veces\nb) Por aerogenerador subsecuente de energía eólica.................................... 70.78 veces\nf).- Edificios o instalaciones para la generación y transmisión de energía eléctrica eólica.\nHasta 500.00 m²........................... 0.05 veces por m²\nMayor a 500.00 m²......................... 0.02 veces por m²\ng).- Por certificación de terminación y/o ocupación de obra, se cobrará por edificio de la siguiente manera:\n1.- Módulo aerogenerador de energía...... 151.68 veces\nTratándose de obras provenientes de inversiones del Gobierno Federal o del Estado de Baja California, no causarán el Derecho estipulado en este apartado.\nARTÍCULO 40.- Los servicios que presta control urbano, por uso del suelo se pagarán conforme a lo siguiente:\nI.- POR ANÁLISIS Y EMISIÓN DE DICTAMEN O CONSTANCIA DE USO DEL\nSUELO:\nUNIDAD DE MEDIDA Y\nACTUALIZACIÓN VIGENTE\n1.- Vivienda:\na).- Multifamiliar\nHasta 3 viviendas........................... 11.08 veces\nDe 4 a 6 viviendas.......................... 19.40 veces\nPor cada vivienda adicional................. 4.15 veces\nb).- Mixto\nVivienda con uso comercial de baja escala... 19.40 veces\n2.- En equipamiento y servicios, por superficie del predio:\na).- Comercio:\nAbasto y almacenaje; depósitos de productos básicos, de materiales de construcción, maquinaria, vehículos y otros; venta de alimentos en instalaciones móviles y comida para llevar dentro de un predio.\nHasta 5,000 m² de superficie............... 37.42 veces\nPor cada 1,000 m² subsecuentes, se pagará la cuota anterior más.......................... 4.15 veces\nArtículos, servicios comerciales, estéticas, lavanderías, planchadurías, limpiadurías, alquiler de vehículos y equipo, sastrerías y vestimenta de alquiler, boutique de cerveza artesanal, etc.\nHasta 500 m² de superficie................. 41.58 veces\nDe 501 m² a 2,500 m² de superficie.......... 55.44 veces\nDe 2,501 m² hasta 5,000 m² de superficie.... 69.30 veces\nMayor de 5,001 m² de superficie............. 97.02 veces\nTramites ingresados a través del Sistema de\nApertura Rápida de Empresas (SARE), hasta\n100 m² de superficie........................ 27.72 veces\nb).- Educación y Cultura:\nPreescolar, elemental, media básica, media superior, superior, academias y escuelas técnicas:\n(Incluye escuelas particulares)\nHasta 500 m² de superficie de terreno...... 27.72 veces\nDe 501 m² hasta 1,000 m² de superficie de terreno..................................... 55.44 veces\nPor cada 100 m² subsecuentes, o fracción pagará la cuota anterior más................ 5.54 veces\nc).- Salud y Servicios Asistenciales:\nHospitales, centros médicos y de especialidades:\nHasta 5,000 m² de superficie............... 34.65 veces\nMayor de 5,000 m² hasta 10,000 m² de superficie.................................. 48.51 veces\nPor cada 1,000 m² subsecuentes se pagará la cuota anterior más.......................... 2.77 veces\nClínicas, consultorios, servicios médicos forenses, laboratorios médicos y guarderías:\nHasta 500 m² de superficie................. 11.08 veces\nMayor de 500 m² a 1,000 m² de superficie.... 16.63 veces\nMayor de 1,000 m² hasta 5,000 m² de\nSuperficie.................................. 34.65 veces\nPor cada 1,000 m² subsecuentes, o fracción pagará la cuota anterior más................ 2.77 veces\nd).- Deportes y Recreación:\nCentros deportivos y entretenimiento: estadios, lienzos charros, campos de tiro, boliche y juegos de mesa o electrónicos:\nHasta 5,000 m².............................. 23.56 veces\nMayor de 5,000 m² hasta 10,000 m²........... 27.72 veces\nPor cada 1,000 m² subsecuentes se pagará la cuota anterior más.......................... 2.77 veces\nCanchas deportivas, albercas, salones de ejercicio y acondicionamiento físico:\nHasta 2,500 m².............................. 18.01 veces\nMayor de 2,500 m² hasta 5,000 m²............ 23.56 veces\nPor cada 1,000 m² subsecuentes se pagará la cuota anterior más.......................... 2.77 veces\ne).- Servicios Administrativos:\nHasta 2,500 m².............................. 20.79 veces\nMayor de 2,500 m² hasta 5,000 m²............ 34.65 veces\nPor cada 1,000 m² subsecuentes se pagará la cuota anterior más.......................... 2.77 veces\nf).- Seguridad y Bienestar:\nDefensa, reclusorios, unidades de rescate y basureros:\nHasta 5,000 m².............................. 27.72 veces\nMayor de 5,000 m² hasta 10,000 m²........... 34.65 veces\nPor cada 1,000 m² que exceda los 10,000 m² pagará la cuota anterior más................ 2.77 veces\ng).- Turismo:\nAlojamiento: hoteles, moteles, casas de huéspedes y estacionamiento para casas rodantes y vehículos para acampar:\nHasta 5,000 m².............................. 34.65 veces\nMayor de 5,000 m² hasta 10,000 m²........... 38.80 veces\nPor cada 1,000 m² subsecuentes se pagará la cuota anterior más.......................... 4.15 veces\nh).- Servicios Mortuorios:\nCrematorios, velatorios, agencias de inhumaciones y funerarias:\nHasta 1,000 m².............................. 18.08 veces\nMayor de 1,000 m² hasta 5,000 m²............ 34.65 veces\nPor cada 1,000 m² subsecuentes se pagará la cuota anterior más.......................... 2.77 veces\ni).- Comunicaciones y Transportes:\nTransporte: estaciones y sitios de transporte público\n(autobuses y taxis), estacionamientos públicos, estacionamientos privados, terminales de transporte foráneo, encierro de transporte de carga, de vehículos de alquiler y base para radio taxis:\nHasta 5,000 m².............................. 29.10 veces\nMayor de 5,000 m² hasta 10,000 m²........... 33.26 veces\nPor cada 1,000 m² subsecuentes se pagará la cuota anterior más.......................... 2.77 veces\nComunicaciones: estaciones de radio, televisión, telefonía y concentradoras:\nHasta 2,500 m².............................. 18.01 veces\nMayor de 2,500 m² hasta 5,000 m²............ 24.94 veces\nMayor de 5,000 m² hasta 10,000 m²........... 29.10 veces\nPor cada 1,000 m² subsecuentes se pagará la cuota anterior más.......................... 2.77 veces\nj).- Diversión y Espectáculos:\nAuditorios, teatros, cines, exposiciones, y sitios de diversiones:\nHasta 10,000 m²............................. 41.58 veces\nPor cada 1,000 m² subsecuentes se pagará la cuota anterior más.......................... 4.15 veces\nCentros de apuestas, apuestas remotas, salas de sorteos de números y/o casinos, Libro Foráneo y similares:\nHasta 3,000 m² de superficie................ 693.00 veces\nDe 3,001 m² de terreno en adelante.......... 1,039.50 veces\nCentros Sociales: jardines para fiestas, salones para banquetes, salones de baile, centros nocturnos, cantinas, café cantante, bares y billares, sala de degustación de cerveza artesanal:\nHasta 1,000 m².............................. 76.23 veces\nDe 1,001 m² hasta 2,500 m² de terreno....... 97.02 veces\nPor cada 500 m² subsecuente, o fracción se pagará la cuota anterior más................ 8.31 veces\nk).- Especial:\nEstación o distribución de gas, gasolineras, almacén de hidrocarburos y estaciones de carburación:\nHasta 5,000 m².............................. 76.23 veces\nPor cada 1,000 m² subsecuentes se pagará la cuota anterior más.......................... 4.15 veces\n3.- En industria, por superficie del predio:\na).- Extractiva: Explotación de minas o bancos de materiales de construcción:\nHasta 2 hectáreas de predio................. 69.30 veces\nPor cada hectárea subsecuente se pagará la cuota anterior más.......................... 4. 15 veces\nb).- Transformación: Fundición de minerales metálicos, fertilizantes, hules y plásticos, petróleos y derivados, papel madera, bloqueras y ladrilleras, alimenticia, bebidas y tabaco, pigmentos, pinturas colorantes y derivados, vidrios, cerámica y derivados:\nHasta 10,000 m² de predio.................. 69.30 veces\nPor cada 2,000 m² subsecuentes se pagará la cuota anterior más.......................... 4.15 veces\nc).- Manufacturera: Máquinas y herramientas, textiles e industrias de cueros, de la madera, productos de papel, ensamble de aparatos eléctricos o electrónicos, maquiladoras de otros tipos:\nHasta 10,000 m² de predio.................. 62.37 veces\nPor cada 2,000 m² subsecuentes se pagará la cuota anterior más.......................... 4.15 veces\nd).- Agroindustria: Envases y empaques, forrajes y otras.\nCualquier superficie........................ 34.65 veces\ne).- Micro Industria: Imprentas, talleres de Serigrafía, taller de torno y soldadura, taller de herrería, elaboración de frituras, taller de carrocería y pintura, elaboración de cerveza artesanal.\nHasta 500 m² de superficie.................. 23.56 veces\nMayor de 500 hasta 1,000 m²................. 36.03 veces\nMayor de 1,000 m²........................... 48.51 veces\n4.- Infraestructura, por superficie del predio:\nInstalaciones: Plantas, estaciones y subestaciones, torres y antenas, antenas de telefonía celular, carteleras espectaculares, carteleras electrónicas, depósitos, antenas de radio, telefonía, cárcamos y bombas, ramales, tuberías, generación de energía mediante paneles solares, generación eólica, generación de energía mediante turbinas y otros:\nPor elemento en cada predio...................... 145.53 veces\nTratándose de antenas, torres, antenas de como carteleras electrónicas realizarán una 207.90 veces revalidación anual si se determina uso temporal.. por unidad\n5.- En otros usos:\na).- Actividades agropecuarias, cauces y cuerpo de agua:\nPor cualquier superficie.................... 41.58 veces\nb).- Casetas fitosanitarias, centros de pesaje, viveros, pistas para fumigadores, pistas para carreras de vehículos:\nHasta 1,000 m² de superficie................ 34.65 veces\nDe 1,001 hasta 2,500 m²..................... 41.58 veces\nDe 2,501 hasta 5,000 m²..................... 48.51 veces\nMayor de 5,000 m²........................... 62.37 veces\nDesmanteladoras (yonques), recicladoras...... 83.16 veces\nEn cualquier caso anterior, por regularización de uso de suelo, se adicionará un 50% de las tarifas anteriores.\nAlbergues, centros de tratamiento psiquiátrico, centros de rehabilitación física y orfanatos o casas de cuna, quedarán exentos de pago.\nDictámenes en predios propiedad del Gobierno Federal, Estatal o\nMunicipal, estarán exentos del pago de los derechos a que se refiere esta fracción.\nII.- POR FACTIBILIDAD DE USO DEL SUELO.\n1.- Para construcciones en uso o desuso y para predios a desarrollar a solicitud del interesado:\nUNIDAD DE MEDIDA Y\nACTUALIZACIÓN VIGENTE\nVivienda:\na).- Multifamiliar\nPor cada vivienda........................... 2.07 veces\nb).- Mixto\nVivienda con uso comercial de baja escala... 9.70 veces\n2.- En equipamiento y servicios, por superficie del predio:\na).- Comercio:\nAbasto y almacenaje; depósitos de productos básicos, de materiales de construcción, maquinaria, vehículos y otros; llevar dentro de un predio.\nPor predio.................................. 18.01 veces\nArtículos, servicios comerciales, estéticas, lavanderías, planchadurías, limpiadurías, alquiler de vehículos y equipo, sastrerías y vestimenta de alquiler, etc.\nPor predio.................................. 27.72 veces\nb).- Educación y Cultura:\nPreescolar, elemental, media básica, media superior, superior, academias y escuelas técnicas:\nPor predio.................................. 13.86 veces\nc).- Salud y Servicios Asistenciales:\nHospitales, centros médicos y de especialidades:\nPor predio.................................. 21.48 veces\nClínicas, consultorios, servicios médicos forenses, laboratorios médicos y guarderías:\nPor predio.................................. 17.32 veces\nd).- Deportes y Recreación:\nCentros deportivos y entretenimiento: estadios, lienzos charros, campos de tiro, boliche y juegos de mesa o electrónicos:\nPor predio.................................. 13.86 veces\nCanchas deportivas, albercas, salones de ejercicio y acondicionamiento físico:\nPor predio.................................. 11.78 veces\ne).- Servicios Administrativos:\nPor predio.................................. 10.39 veces\nf).- Seguridad y Bienestar:\nDefensa, reclusorios, unidades de rescate y basureros:\nPor predio.................................. 13.86 veces\ng).- Turismo:\nAlojamiento: hoteles, moteles, casas de huéspedes y estacionamiento para casas rodantes y vehículos para acampar:\nPor predio.................................. 19.40 veces\nh).- Servicios Mortuorios:\nCrematorios, velatorios, agencias de inhumaciones y funerarias:\nPor predio.................................. 17.32 veces\ni).- Comunicaciones y Transportes:\nTransporte: estaciones y sitios de transporte público\n(autobuses y taxis), estacionamientos públicos, estacionamientos privados, terminales de transporte foráneo, estacionamiento y encierro de transporte de carga y de vehículos de alquiler:\nPor predio.................................. 14.55 veces\nComunicaciones: estaciones de radio, televisión, telefonía y concentradoras:\nPor predio.................................. 14.55 veces\nj).- Diversión y Espectáculos:\nAuditorios, teatros, cines, exposiciones, y sitios de diversiones:\nPor predio.................................. 20.79 veces\nCentros de apuestas, apuestas remotas, salas de sorteos de números y/o casinos, Libro Foráneo y similares:\nHasta 3,000 m² de superficie................ 346.50 veces\nDe 3,001 m² de terreno en adelante.......... 485.10 veces\nCentros Sociales: jardines para fiestas, salones para banquetes, salones de baile, centros nocturnos, cantinas, café cantante, bares y billares:\nPor predio.................................. 34.65 veces\nk).- Especial:\nEstación o distribución de gas, gasolineras, almacén de hidrocarburos y estaciones de carburación:\nPor predio.................................. 277.20 veces\n3.- En industria, por superficie del predio:\na).- Extractiva: Explotación de minas o bancos de materiales de construcción:\nPor predio.................................. 20.79 veces\nb).- Transformación: Fundición de minerales metálicos, fertilizantes, hules y plásticos, petróleos y derivados, papel madera, bloqueras y ladrilleras, alimenticia, bebidas y tabaco, pigmentos, pinturas colorantes y derivados, vidrios, cerámica y derivados:\nPor predio.................................. 20.79 veces\nc).- Manufacturera: Máquinas y herramientas, textiles e industrias de cueros, de la madera, productos de papel, ensamble de aparatos eléctricos o electrónicos, maquiladoras de otros tipos:\nPor predio.................................. 20.79 veces\nd).- Agroindustria: Envases y empaques, forrajes y otras.\nCualquier superficie........................ 13.86 veces\ne).- Micro Industria: Imprentas, Talleres de Serigrafía, Taller de Torno y Soldadura, Taller de Herrería, Elaboración de frituras, taller de carrocería y pintura.\nHasta 500 m² de superficie.................. 8.31 veces\nMayor de 500 hasta 1,000 m²................. 9.70 veces\nMayor de 1,000 m²........................... 13.86 veces\n4.- Infraestructura, por superficie del predio:\nInstalaciones: Plantas, estaciones y subestaciones, torres y antenas, antenas de telefonía, carteleras espectaculares, carteleras electrónicas, depósitos, antenas de radio, telefonía, cárcamos y bombas:\na).- Hasta 1,000 m² de superficie................ 16.63 veces\nb).- Mayor de 1,000 m² de superficie............. 20.79 veces\nEn otros usos:\na).- Actividades agropecuarias, cauces y cuerpo de agua:\nPor cualquier superficie.................... 16.63 veces\nb).- Casetas fitosanitarias, centros de pesaje, viveros, pistas para fumigadores, pistas para carreras de vehículos:\nPor predio.................................. 20.79 veces\n5.- Reconsideraciones de uso de suelo.\nPara cualquier uso de suelo................. 11.08 veces\n6.- Permisos temporales de uso de suelo.\na).- Instalaciones temporales destinadas a eventos públicos como circos, espectáculos, convenciones, exposiciones, carpas, casas muestras, árboles de navidad, juguetería, regalos y similares:\nPor predio.................................. 20.79 veces\n7.- Anuencia de Uso de Suelo:\nPor trámite................................. 13.86 veces\n8.- Congruencia de Uso por cualquier superficie...... 41.58 veces\n9.- Copia Certificada:\na).- Copia de documentos, la primera hoja........................................ 1.38 veces\nb).- Por cada hoja subsecuente................... 0.35 veces\n10.- Inspección para constancia uso de suelo.......... 20.79 veces\nIII.- INSTALACIONES DE INFRAESTRUCTURA URBANA:\nLos derechos por la ocupación de la vía pública con instalaciones de infraestructura urbana, se regirán bajo el supuesto del denominado del Piso, de esta ley.\nARTÍCULO 41.- Los servicios que presta control urbano, por concepto de\nImagen Urbana, se pagarán conforme a lo siguiente:\nI.- PARA RÓTULOS E INSTALACIÓN DE ESTRUCTURAS DE ANUNCIOS, SE\nPAGARÁN DERECHOS DE ACUERDO A LA SIGUIENTE TABLA, EN LA CUAL LAS\nSUPERFICIES SE CONSIDERAN LAS CARAS EXPUESTAS DEL ANUNCIO:\na).- Establecimientos de giro comercial y de servicios que cuenten con un sólo anuncio adosado en propiedad privada, clasificado como denominativo, en fachadas principales y muros laterales que no excedan de 3 m²... EXENTO\nb).- Establecimientos de giro comercial y de\nServicios que se ingresen a través del\nSistema de Apertura Rápida de Empresas\n(SARE), que cuenten con un solo anuncio que no exceda de 3 m².......................... EXENTO\nc).- Hasta 15 m² de superficie.............. 25.89 veces\nd).- Mayor de 15 m²........................... 50.90 veces\nII.- ESTABLECIMIENTO DE MOBILIARIO URBANO Y PUBLICITARIO HACIA LA VÍA\nPÚBLICA. urbano y publicitario en la vía pública, se determinará de acuerdo a las cuotas o tarifas siguientes:\nPor la autorización para la construcción y/o instalación de anuncios por cara expuesta, se pagarán las siguientes cuotas vigente:\n1.- Pantalla Electrónica incluyendo instalación............................... 252.00 veces\n2.- Espectacular Unipolar o en azotea incluye instalación................................ 201.60 veces\n3.- Unipolar mediano/directorio sobre poste o azotea, incluye instalación................ 107.10 veces\n4.- Unipolar pequeño........................... 44.10 veces\n5.- Electrónicos, incluye instalación.......... 50.40 veces\nIII.- POR PERMISO TEMPORAL PARA LA COLOCACIÓN DE ANUNCIO HACIA LA VÍA\nPÚBLICA, EXCEPTUANDO LA PROPAGANDA POLÍTICA, SE PAGARÁ LO\nSIGUIENTE:\nUNIDAD DE MEDIDA Y\nACTUALIZACIÓN VIGENTE\n1).- Anuncios tipo caballete, bandera, banderín o estandarte, hasta 4 m² por ambas caras, colocados en estructuras de cualquier tipo 20.79 veces de material por un período de 3 meses..... por cada uno\n2).- Por cada cartel promocional de hasta\n1.50 m²:\na).- Vigencia hasta 90 días................ 6.93 veces\n3).- Rótulo tipo manta o lona en vía pública o en propiedad privada por un período de 15 días hasta 90 días:\na).- Por cada 20 m² o fracción de superficie........................... 20.79 veces\n4).- Promoción en elementos y/o estructuras inflables luminosos o sin iluminación en propiedad privada o en vehículos:\na).- Vigencia por cada 15 días............ 13.86 veces\n5.- Licencias nuevas para rótulos en cobertizos publicitarios, mobiliario urbano, figuras cilíndricas y en vehículos móviles, con o sin iluminación con vigencia hasta un año:\na).- Rótulo por anuncio:\n1.- Ajeno a la razón social del\nEstablecimiento hasta 3 m² por anuncio.............................. 6.93 veces\n2.- Excedente de 3 m² por cada metro cuadrado............................. 1.38 veces\n3.- Igual a la razón social hasta 3 m²... EXENTO\n4.- Igual a la razón social de 3 m² en adelante por metro cuadrado.......... 4. 1 5 veces\nb).- Rótulo con iluminación..................... 4.15 veces por m²\nc).- Anuncio electrónico o electromecánico, LED por m²..................................... 11.08 veces\nd).- Instalación de cobertizo publicitario y/o mobiliario urbano (banca publicitaria, bote 16.63 veces de basura o buzón con publicidad, etc.).... por unidad\ne).- Torrete en techo de camión o taxi.......... 4.15 veces por unidad\nf).- Rótulo en vehículos o autobuses excepto 27.72 veces aquellos de distintivo oficial............. por unidad\ng).- Anuncios electrónicos y rótulos electrónicos con o sin movimiento en 27.72 veces vehículos con vigencia de tres meses....... por unidad\nIV.- LA REVALIDACIÓN DEL PERMISO PARA ANUNCIOS Y SIMILARES,\nCONSTRUIDOS EN PROPIEDAD PRIVADA, CONSIDERANDO LA SUPERFICIE DE\nCADA CARA EXPUESTA, SE PAGARÁN DERECHOS DE ACUERDO CON LA\nSIGUIENTE TARIFA:\na).- Anuncio adosado, toldo, rótulo, etc. por m² 1.38 veces por m²\nb).- Anuncio en pantalla electrónica o electromecánica con o sin movimiento....... 207.90 veces\nc).- Torrete en techo de camión o taxi por unidad..................................... 4.15 veces\nd).- Anuncio electrónico y con movimiento en vehículos por unidad....................... 27.72 veces\ne).- Espectacular............................... 75.60 veces\nEstarán exentos de revalidar los rótulos y adosados sobre pared no luminosos, en propiedad privada con superficie de hasta 3 m².\nLas instituciones educativas públicas, culturales, asociaciones civiles y religiosas dedicadas a la beneficencia pública, estarán exentas del pago de este derecho.\nV.- POR ANÁLISIS Y EMISIÓN DE FACTIBILIDAD DE OPINIONES TÉCNICAS\nCONSTRUIDA EN PROPIEDAD PRIVADA.\nPor cada anuncio o estructura.................... 15.12 veces\nLa revalidación se hará en los primeros tres meses de cada año. comercial.\nVI.- GENERALIDADES:\nA).- Copia de documento, por cada hoja....................................... 1.38 veces\nB).- Constancia de documento.................... 5.54 veces\nC).- Certificación de documento................. 4.15 veces\nD).- Inspección ocular, a solicitud del interesado................................. 5.54 veces\nARTÍCULO 42.- Las personas físicas o morales que presten los servicios de publicidad, así como los propietarios y/o poseedores de los bienes donde se instalen anuncios, serán solidariamente responsables del pago de los impuestos, derechos y/o multas que se originen con motivo de los anuncios que tengan instalados en esta municipalidad.\nARTÍCULO 43.- El Certificado de Mejoramiento de la Imagen Urbana, es el documento expedido por Control Urbano en el que se hace constar el estado físico de un predio urbano, que cuenten con tasa de baldío o no edificado, conforme el Reglamento del Catastro Inmobiliario para el Municipio de Mexicali, Baja California o el Reglamento del Catastro\nInmobiliario para el Municipio de Ensenada, Baja California, en lo que resulte aplicable atendiendo a la demarcación territorial que le hubiere correspondido y en base al Artículo 2, Fracción I de la presente Ley de Ingresos.\nLos contribuyentes que adquieran el Certificado de Mejoramiento de la\nImagen Urbana de conformidad con las bases para el otorgamiento del mismo, tendrán derecho a los siguientes descuentos en el pago anual del Impuesto Predial.\nA).- Predios con tasa de Baldíos o no Edificados:\nI.- Los predios baldíos o no edificados deberán: estar sin uso, libres de basura, maleza, escombro, cascajo o cualquier otro residuo, desecho o desperdicio............ 20 %\nII.- Contar con guarniciones y banquetas en buen estado que permitan el libre tránsito peatonal.................................. 1 0 %\nIII.- Tener en sus colindancias barda, cerco de malla ciclónica, estructura metálica o similar debidamente rigidizados, con elementos estructurales uniformes. Libre de graffiti en muros propios o ajenos.... 10 %\nIV.- Contar con áreas verdes en buenas condiciones al frente del predio sin que obstruyan el tránsito peatonal............ 5 %\nTOTAL 45 %\nB).- Bases para el otorgamiento del Certificado de Mejoramiento de la\nImagen Urbana:\nI.- Acreditar ser propietario o poseedor de un inmueble urbano que se encuentre con tasa de baldío o no edificado.\nII.- Al momento de inscribirse para adquirir el Certificado de\nMejoramiento de la Imagen Urbana, pagar la cuota correspondiente, en base a la siguiente tabla:\nCOSTO DEL CERTIFICADO\nVALOR CATASTRAL VECES LA UNIDAD DE MEDIDA\nDE A Y ACTUALIZACIÓN VIGENTE\n$ 0 $ 37,200 0.31\n37,201 93,000 0.63\n93,001 186,000 1.89\n186,001 279,000 3.15\n279,001 372,000 5.04\n372,001 558,000 7.56\n558,001 774,000 10.08\n774,001 1,116,000 15.12\n1’116,001 2’232,000 18.90\n2’232,001 5’208,000 69.30\n5’208,001 8’928,000 113.40\n8’928,001 En adelante 126.00\nB)FRACCIONAMIENTOS\nARTÍCULO 44.- Los servicios que presta fraccionamientos, se pagarán conforme a lo siguiente:\nI.- POR ANÁLISIS DE DESARROLLOS URBANOS: superficie de predio:\nA).- Por análisis de predios a urbanizar, incorporar o reincorporar al área urbana, revisión de restricciones existentes y de los del suelo:\nUNIDAD DE MEDIDA Y\nACTUALIZACIÓN VIGENTE\n1.- Por emisión de Dictamen de Uso de Suelo:\na).- Hasta 3 hectáreas................. 63.00 veces\nb).- Por cada hectárea o fracción adicional......................... 6.30 veces\nLas colonias populares y fraccionamientos con urbanización mínima promovidas por Organismos Gubernamentales pagarán un 50% de la tarifa anterior.\nPara predios con superficie menor a 1.00 hectárea, que no sean desarrollados como fraccionamientos, el monto a pagar deberá calcularse conforme al artículo 39 de esta Ley.\n2.- Por emisión de Factibilidad de Uso de Suelo:\na).- En terrenos de hasta 3 has. dentro del límite del centro de población de\nSan Felipe............................ 50.40 veces\nb).- En terrenos de hasta 3 has. fuera del límite del centro de población de\nFelipe.............................. 75.60 veces\nHectárea o fracción adicional......... 6.30 veces\n3.- Por Gestión en Autorización de Cambio de Uso de Suelo, se se deberá cubrir:\na).- Hasta 3.00 hectáreas.................. 186.00 veces\nb).- Por cada hectárea adicional o fracción adicional............................. 15.12 veces\n4.- Por realización de inspección y elaboración de dictamen técnico, se deberá cubrir previo al inicio del trámite:\na).- Encaminado a la desincorporación de los bienes del dominio público........ 9.70 veces\nb).- Encaminado a la obtención de dictamen técnico para la asignación en comodato de un bien del dominio público........ 11.08 veces\nc).- Dictamen técnico encaminado a la certificación de datos sobre la ubicación, medidas y colindancias de un bien del dominio privado........... 12.47 veces\n5.- Por emisión de dictamen de congruencia:\nEn terrenos ubicados dentro del centro de población de la cabecera municipal.......... 103.95 veces\nEn terrenos ubicados dentro de los centros de población de los poblados................ 138.60 veces\n6.- Por ratificación de dictamen de uso de suelo, que haya sido emitido en un periodo mayor de un año:\nPor cada vez................................ 13.86 veces\nB).- Por análisis de anteproyectos de lotificación para acciones de\nUrbanización en sus diversas modalidades, consistentes en el\nAnálisis de la distribución de los usos y destinos del suelo, estructuración del desarrollo, integración vial al contexto urbano, así como por la modificación o revalidación de los mismos, se cobrará por la superficie total para cualquier tipo de desarrollo y uso en la forma siguiente:\n1.- Por análisis de anteproyecto de lotificación en Acciones de Urbanización:\nUNIDAD DE MEDIDA\nACTUALIZACIÓN VIGENTE\na).- En terrenos dentro de los centros de población:\nHasta 5 hectáreas..................... 75.60 veces\nPor cada hectárea o fracción adicional 7.56 veces\nb).- En terrenos fuera de los centros de población:\nHasta 5 hectáreas..................... 107.10 veces\nPor cada hectárea o fracción adicional. 7.56 veces\nEn caso de regularización de fraccionamientos se incrementarán en un\n25% las tarifas de la presente fracción.\nLas acciones de urbanización por objetivo social, las colonias y fraccionamientos populares, con urbanización mínima promovida por\nOrganismos Gubernamentales pagarán un 50% de las tarifas anteriores.\nPor la tercera revisión se cobrara el 50% de la tarifa y por la cuarta revisión en adelante se cobrara el 25%.\nC).- Por análisis de proyectos ejecutivos nuevos o modificaciones de la geometría de ejes de vías públicas, manzanas y lotificación de Acciones de Urbanización en sus diversas modalidades, se pagará dentro o fuera de los centros de población, de la forma siguiente:\n1.- Para acciones de urbanización nuevas, modificaciones y regularización:\nHasta 5 hectáreas..................... 113.40 veces\nPor cada hectárea o fracción adicional 15.12 veces\nLas acciones de urbanización por objetivo social, las colonias y fraccionamientos populares, con urbanización mínima promovida por los\nOrganismos Gubernamentales pagarán un 50% de las tarifas anteriores.\nEn revisiones subsecuentes a la segunda se cobrará el 50% de la tarifa anterior.\nD).- Por análisis de anteproyectos de infraestructura urbana para acciones de urbanización, consistente en inspección al terreno a desarrollar, análisis de la ubicación de los servicios públicos en las vías públicas resultantes, en servidumbres de paso establecidas, integración de la infraestructura a instalar a los ya existentes y revisión de los alcances de los servicios públicos de alumbrado público, equipamiento de áreas verdes e instalación de hidrante, en cualquier modalidad de acciones de urbanización, incluyendo la incorporación o reincorporación municipal:\nHasta 5 hectáreas................................ 75.60 veces\nPor cada hectárea o fracción adicional........... 1.89 veces\nLas acciones de urbanización por objetivo social, las colonias y fraccionamientos populares, con urbanización mínima promovidas por\nOrganismos Gubernamentales pagarán un 50% de las tarifas anteriores.\nEn caso de regularización de fraccionamientos se incrementará en un\n25% de las tarifas fijadas en los incisos C) y D).\nEn revisiones subsecuentes a la segunda se cobrará el 50% de la tarifa anterior.\nE).- Modificación de predios:\n1.- Por relotificación, subdivisión o fusión de predios urbanos: solicitud:\na).- Ubicados dentro del centro de población............................. 5.54 veces\nb).- Ubicados fuera del centro de población. 8.31 veces\nPor cada lote resultante de la\nModificación.......................... 2.77 veces\n2.- Por análisis, expedición de autorización y certificación de la memoria descriptiva resultante por subdivisión, relotificación o fusión de predios urbanos:\na).- En lotes baldíos:\nHasta 5 lotes resultantes por subdivisión, relotificación o fusión por cada uno.......................... 9.45 veces\nPor cada lote resultante por subdivisión, relotificación o fusión adicional............................. 2.77 veces\nb).- En lotes construidos:\nHasta 5 lotes resultantes por subdivisión, relotificación o fusión por cada uno.......................... 12.60 veces\nPor cada lote resultante por subdivisión, relotificación o fusión adicional............................. 2.77 veces\nF).- Por subdivisión o fusión de lotes rústicos y análisis para visto bueno:\n1.- Por inspección ocular de cada solicitud:\na).- Ubicados dentro del centro de\nPoblación............................. 9.45 veces\nb).- Ubicados fuera del centro de población 11.97 veces\nPor cada lote resultante de la modificación. 2.77 veces\n2.- Por análisis, expedición de autorización y certificación de la memoria descriptiva, por cada lote resultante........................ 3 3.39 veces\nG).- Por certificación de memorias descriptivas:\n1.- Por verificación y certificación de memorias descriptivas modificaciones, se pagará por cada revisión en la forma siguiente:\na).- Hasta 50 lotes........................ 25.20 veces\nb).- Por cada lote adicional a 50.......... 0.37 veces\n2.- Por validación a la modificación de la memoria la Propiedad y del Comercio, propiedad de instituciones deslinde actualizado certificado por catastro municipal:\nPor cada lote............................... 8.82 veces\nH).- Por constancia de cumplimiento de requisitos para traslación de de dominio en desarrollos urbanos:\nDe 1 a 50 lotes solicitados................. 88.20 veces\nPor cada lote adicional..................... 1.89 veces\nI).- Emisión de respuestas y constancias en el proceso de autorización de las acciones de urbanización:\nPor cada vez................................ 20.79 veces\nJ).- Por acta de recepción de fraccionamientos para su mantenimiento por etapa o completo:\nPor cada vez................................ 69.30 veces\nK).- Por copia certificada de documento o plano:\n1.- Por documento hasta 10 hojas................ 1.89 veces\nPor cada hoja adicional..................... 0.37 veces\n2.- Por plano................................... 3.78 veces\nL).- Por revisión del presupuesto de urbanización para pago de derechos, notificación y modificación del monto de la fianza y por constancia de reducción y/o cancelación de fianza de desarrollos urbanos y/o acciones de urbanización por documento:\nHasta 5 hectáreas........................... 27.72 veces\nPor cada hectárea adicional................. 6.30 veces\nM).- Visto bueno para que el desarrollador provisionalmente municipio:\nPor cada vez................................ 6.93 veces\nN).- Por elaboración de dictamen técnico e integración de expediente al municipio mediante el pago por su valor comercial, por obras de infraestructura y/o obras de edificación se deben pagar previo a su envío al Ayuntamiento:\nPor cada vez................................ 27.72 veces\nÑ).- Por integración de expediente, formulación de dictamen y trámite para opinión de la Acción de Urbanización solicitada:\nPor cada vez................................ 75.60 veces\nO).- Por elaboración de Acuerdo de Autorización de Acciones de\nUrbanización, o modificaciones a éstas, se cobrará:\nHasta 3 hectáreas........................... 75.60 veces\nPor cada hectárea o fracción adicional...... 3.78 veces\nEl pago de los derechos que se refieren a los incisos del “A” al “O” notificación de Fraccionamientos del Municipio.\nC) TRÁNSITO\nARTÍCULO 45.- Los servicios que presta Tránsito, se causarán conforme a lo siguiente:\nI.- Por expedición de lineamientos viales para el desarrollo urbano y obras de infraestructura, se pagará por la superficie total registrada del predio:\nUNIDAD DE MEDIDA Y\nACTUALIZACIÓN VIGENTE\na).- Menor de 1 hectárea......................... 27.78 veces\nb).- Mayor de 1 ha. Hasta 3 ha................... 55.56 veces\nc).- Mayor de 3 ha. Hasta 5 ha................... 83.34 veces\nd).- Por hectárea adicional de 5 ha. además de la cuota anterior se agrega.................... 7.93 veces\ne).- Por ratificación y actualización de lineamientos viales emitidos en un período mayor de un año............................. 27.78 veces\nf).- Por emisión de constancia de no lineamientos viales...................................... 21.16 veces\ng).- Cuando la expedición de lineamientos viales\nCorresponda a un trámite de subdivisión, certificación de deslinde edificación u obras de infraestructura, se pagará el 50% de los derechos enunciados en los incisos que anteceden, según corresponda.\nII.- Por análisis de accesos vehiculares se pagará en relación a los cajones de estacionamiento requeridos por el Reglamento de\nEdificaciones aplicable a la materia para el Municipio de\nSan Felipe de la forma siguiente:\na).- Por emisión de factibilidad de acceso vehicular por predio:\n1).- Lotes habitacionales de aprovechamiento comercial.............................. 7.93 veces\n2).- Lotes comerciales y de servicio con área de estacionamiento privado........ 10.58 veces\n3).- Naves industriales, centros de abasto y almacenaje, andenes de carga y descarga, o cualquier uso similar...... 1 5.87 veces\n4).- Estaciones de servicio, de carburación o cualquier uso similar............... 2 9.10 veces\nb).- Por análisis y elaboración de dictamen de proyectos de acceso vehicular a:\n1).- Lotes habitacionales de aprovechamiento comercial.............................. 15.87 veces\n2).- Lotes comerciales y de servicio con área de estacionamiento privado, se pagará de la siguiente manera:\n2.1).- Hasta 10 cajones..................... 21.16 veces\n2.2).- De 11 a 20 cajones................... 42.33 veces\n2.3).- De 21 a 30 cajones................... 63.50 veces\n2.4).- Por cada cajón de estacionamiento adicional además de la cuota anterior 1. 9 9 v e c e s\n3).- Naves industriales, centros de abasto y almacenaje, andenes de carga y descarga, o cualquier uso similar...... 3 1.75 veces\n3.1).- Por cada cajón de estacionamiento, además de la cuota anterior.......... 1.99 veces\n4).- Estaciones de servicio, de carburación o cualquier uso similar................ 58.21 veces\n4.1).- Por cada cajón de estacionamiento además de la cuota anterior.......... 1. 99 veces\nc).- Por modificaciones a proyectos de acceso vehicular a:\n1).- Lotes habitacionales de aprovechamiento comercial.............................. 7. 93 veces\n2).- Lotes comerciales y de servicio con área de estacionamiento privado, se pagará de la siguiente manera:\n2.1).- Hasta 10 cajones..................... 10.58 veces\n2.2).- De 11 a 20 cajones................... 21.16 veces\n2.3).- De 21 a 30 cajones................... 31.75 veces\n2.4).- Por cada cajón de estacionamiento\n3).- Naves industriales, centros de abasto y almacenaje, andenes de carga y descarga, o cualquier uso similar...... 1 5.87 veces\n3.1).- Por cada cajón de estacionamiento, además de la cuota anterior.......... 0.99 veces\n4).- Estaciones de servicio, de carburación o cualquier uso similar................ 29.10 veces\n4.1).- Por cada cajón de estacionamiento además de la cuota anterior.......... 0. 99 veces\nd).- En caso de tratarse de edificaciones existentes o regularizaciones, a la cuota respectiva se le agregará el\n50%.\nIII.- Por análisis y autorización de proyectos de señalamiento vial, se pagará de la forma siguiente:\na).- A fraccionamientos de cualquier tipo se pagará de la siguiente manera:\n1).- Hasta de 5 hectáreas................... 63.50 veces\n2).- De 5 hasta 10 hectáreas................ 74.08 veces\n3).- De 10 hasta 20 hectáreas............... 83.34 veces\n4).- De 20 hasta 40 hectáreas............... 95.26 veces\n5).- Por cada 5 hectáreas o fracción excedente por hectárea adicional....... 3.96 veces\nb).- Por análisis y elaboración de dictamen de señalamiento vial extra y dispositivos reductores de velocidad (topes) a escuelas particulares de cualquier nivel educativo y/o empresas privadas............................ 7.93 veces\nc).- Por análisis y elaboración de dictamen para 15.87 veces la instalación de dispositivos reductores de velocidad (topes) a empresas y/o particulares\nIV.- Por la opinión técnica del uso de la vía pública a empresas, escuelas o particulares en las siguientes modalidades:\na).- Para el cierre parcial y temporal de vialidades y/o andador peatonal (banqueta):\n1).- Eventos públicos....................... 19.84 veces\n2).- Eventos privados sobre vialidades con pavimentación y banquetas\n....................... 9.26 veces\n3).- Eventos privados en colonia popular sin pavimentación y banqueta........ 3.50 veces\n4).- Eventos deportivos:\nCon fines de lucro................... 13.23 veces\nSin fines de lucro................... EXENTO\n5).- Eventos Religiosos, Educativos, Culturales, etc.:\nCon fines de lucro................... 9.26 veces\nSin fines de lucro................... 1.26 veces\n6).- Funerales........................... Excento\nb).- Por emisión de opinión técnica para habilitar estacionamientos exclusivos....... 9.26 veces\n1).- Por emisión de opinión técnica para habilitar estacionamiento exclusivo en azul................................... 13.23 veces\nc).- Para carga y descarga o eventos especiales\nCon horario establecido con un máximo de 5 horas por día............................... 7.93 veces\nPor cada hora adicional................ 1.83 veces\nd).- Por cierre parcial (1 carril) de vialidad con horario establecido con un máximo de 5 horas por día............................... 9.19 veces\n1).- Por cierre parcial (1 carril) de\nVialidad por hora adicional hasta 23 horas................................. 1.83 veces\n2).- Por cierre parcial (1 carril) por 24 horas................................. 44.15 veces\ne).- Por cierre total de la vialidad por 24 horas 57.15 veces\nV.- Por análisis y autorización de rutas de carga con transporte pesado dentro de la ciudad:\na).- Carga hasta 25 toneladas vigencia sesenta días sin un horario establecido:\n1).- A empresas con flota vehicular hasta de tres camiones...................... 13.23 veces\n2).- A empresas con flota vehicular hasta de diez camiones...................... 26.46 veces\n3).- A empresas con flota vehicular hasta veinte camiones....................... 52.92 veces\n4).- A empresas con flota vehicular mayor de veinte camiones, por cada vehículo adicional............................. 1. 99 veces\nb).- Carga mayor de 25 toneladas vigencia sesenta días:\n1).- A empresas con flota vehicular hasta de tres camiones...................... 26.46 veces\n2).- A empresas con flota vehicular hasta de diez camiones...................... 59.53 veces\n3).- A empresas con flota vehicular hasta veinte camiones....................... 79.38 veces\n4).- A empresas con flota vehicular mayor 9.26 veces de veinte camiones, por cada vehículo adicional.............................\nc).- Ruta de carga de camiones pesados con vigencia de un día con horario establecido.. 6.61 veces\nd).- Vehículos de carga hasta de 25 toneladas:\n1).- Carga especial o con exceso de dimensiones por única vez y vigencia de horario nocturno................... 26.46 veces\n2).- Por cada tonelada adicional........... 3.96 veces\ne).- Para el tránsito de unidades foráneas sin ruta específica determinada, se cobrará por unidad por día.............................. 39.69 veces\nVI.- Generalidades:\na).- Por definición de secciones viales para acciones de urbanización y/o instalación de infraestructura, por cada una............... 7.93 veces\nb).- Por análisis y autorización de rutas de infraestructura urbana por kilómetro o fracción, en vía pública................... 21.16 veces\nc).- Por análisis y autorización de proyectos de infraestructura urbana por kilómetro o fracción, en vía pública.................... 27.78 veces\nd).- Por análisis de proyectos de semaforización presentados por empresas o particulares..... 29.10 veces\ne).- Por análisis y factibilidad de proyectos geométricos y/o de señalamiento para integración vial............................ 21.16 veces\nf).- Por análisis y aprobación de proyectos geométricos y/o de señalamiento para integración vial............................ 42.33 veces\ng).- Por elaboración de aforos vehiculares dentro 21.16 veces de la estructura vial de la ciudad (por estación, por día)..........................\nh).- Por expedición de copias fotostáticas de aforos vehiculares (por estación, por día).. 5.29 veces\ni).- Por la emisión de factibilidad u opinión técnica a empresas y/o particulares de conceptos no previstos en esta Ley.......... 9.26 veces\nj).- Copia certificada:\n1.- Copia de documentos la primera hoja.......................... 1. 38 veces\n2.- Por cada hoja subsecuente............. 0. 35 veces\nk).- Por la elaboración de dictamen de factibilidad de reubicación de terminales y cierre de circuito.............................. 31.50 veces\nVII.- Por análisis y emisión de factibilidad de opinión técnica de congruencia para la ubicación o utilización de zonas de ascenso para el transporte público, incluye la definición de las características geométricas:\n1.- Por análisis de solicitud de ubicación dentro del primer cuadro y corredores de la zona urbana del municipio............... 25.20 veces\n2.- Por análisis de solicitud de ubicación fuera del primer cuadro y corredores de la zona urbana del municipio............... 16.38 veces\n3.- Por reubicación dentro del primer cuadro y corredores comerciales de la 20.16 veces zona urbana del municipio...............\n4.- Por reubicación fuera del primer cuadro y corredores comerciales de la zona urbana del municipio..... 12.60 veces\n5.- Por elaboración de dictamen de factibilidad de cambio de domicilio de una base de radio taxi y/o taxi ejecutivo 12.60 veces\nD) CATASTRO MUNICIPAL\nARTÍCULO 46.- Los servicios que presta catastro municipal, se pagarán conforme a la siguiente tarifa:\nUNIDAD DE MEDIDA Y\nACTUALIZACIÓN VIGENTE\nA.- POR EXPEDICIÓN DE DOCUMENTOS:\nI.- Corrección de datos catastrales:\na).- Cambio de propietario.............. 1.50 veces\nb).- Cambio de tasa y valor unitario....... EXENTO\nc).- Cambio de superficie.................. 1.99 veces\nLas entidades Federales, Estatales y Municipales, que soliciten cambios de superficie, se encontrarán exentos de pago, siempre y cuando los predios se encuentren registrados a su nombre.\nII.- Certificado catastral para constancia de libertad de gravámenes, por predio......... 4.63 veces\nIII.- Análisis de información:\na).- Para determinar la ubicación y/o superficie resultante previo a deslinde de un predio con clave de colonia urbana que no se encuentre catastrado y/o regularizado........... 8.82 veces\nb).- Para determinar la ubicación y/o 18.90 veces\nSuperficie resultante previo a deslinde de un predio con clave rústica que no se encuentre catastrado y/o regularizado por cada\n20 hectáreas..........................\nc).- Revisión de la superficie asignadas en base a Indiviso de las unidades resultantes de un condominio, por unidad................................ 1.26 veces\nIV.- Copias de documentos:\na).- Copia Simple, primera hoja............ 0.40 veces\nb).- Por hoja adicional.................... 0.075 veces\nV.- Por ampliación de vigencia de acta de deslinde o levantamiento certificado en original, hasta un año después de su vigencia, por cada uno de los predios a certificar por única ocasión............... 7.61 veces\nVI.- Certificación de documentos:\na).- Primera hoja.......................... 4.63 veces\nb).- Hoja adicional........................ 0.79 veces\nVII.- Cédula única catastral y Registral......... 4.63 veces\nVIII Constancia de registro catastral........... 6.30 veces\nIX.- Expedición de carta de no propiedad........ 1.32 veces\nX.- Certificación de copias de planos......... 7.61 veces\nXI.- Valuación:\na).- Elaboración de avalúos Catastrales.... 7.61 veces más el 3.00 al millar sobre el valor del inmueble\nb).- Certificación de avalúo elaborado por\nPerito Valuador Registrado en el\nPadrón Municipal...................... 5.29 veces\nc).- Avalúo de la comisión municipal de valuación solicitado por personas físicas o morales..................... 18.90 veces más el 1.05 al millar sobre el valor de avalúo\nd).- Inspección para análisis de valor catastral y/o tasa por predio a solicitud:\n1.- Dentro de los límites de la zona urbana........................... 3.96 veces\n2.- Fuera de la zona urbana del\nMunicipio de San Felipe. 6.30 veces\n3.- Fuera de la zona urbana por cada kilómetro recorrido fuera del límite de un centro de población. 0.37 veces\nXII.- Elaboración de memoria descriptiva, por predio..................................... 2.31 veces\nXIII. Análisis y ratificación de firmas de\n- documento privado.......................... 7.56 veces\nEn cumplimiento a lo dispuesto en el\nArtículo 2191, del capítulo VIII de la forma del contrato de Compra-Venta del\nCalifornia.\nXIV.- Constancia de no deslinde................. 6.61 veces\nEstatal o Municipal, estarán exentos del pago de los derechos a que se refiere este apartado.\nB.- ASIGNACIÓN DE CLAVE CATASTRAL:\nI.- En el registro de fraccionamientos, colonias regularizadas o modificaciones de predios, por cada clave:\nNo. de Predios UNIDAD DE MEDIDA Y\nPor cada uno ACTUALIZACIÓN VIGENTE\na).- De 1 a 100 claves catastrales.............. 3.96 veces\nb).- De 101 en adelante......................... 3.31 veces\nII.- Asignación de clave catastral individual:\na).- Por cada predio............................ 3.31 veces\nIII.- Por el registro de la posesión de un predio 7. 9 3 veces\nIV.- Análisis para la asignación de claves catastrales en el proyecto de la modificación de predios.................... 2. 3 1 veces\nV.- Análisis técnico, documental y determinación de clave catastral provisional por trámite:\na).- Por cada predio...................... 13.23 veces\nb).- Para predios con clave rústica hasta\nC.- NOMENCLATURA Y NÚMEROS OFICIALES:\nI.- Análisis y revisión de anteproyectos y\nAutorización de proyectos de nomenclatura para nuevos desarrollos de fraccionamientos o condominios, con superficie hasta 5 has.. 26.46 veces\nPor hectárea adicional o fracción.......... 3.31 veces\nII.- Individuales:\na).- Por asignación y expedición de número oficial para predios con clave rústica 4.41 veces\nb).- Por asignación y expedición de número oficial para predios con clave de colonia urbana........................ 2.31 veces\nIII.- Fraccionamientos:\na).- Por asignación y autorización de números oficiales de proyectos para nuevos desarrollos de fraccionamientos o condominios:\n1.- Por autorización y asignación de números oficiales en plano....... 18.90 veces\nb).- Por expedición de boleta de número oficial\n1.- Por cada boleta expedida de número oficial................... 2. 3 1 veces\nc).- Por expedición de certificación de alineamiento:\n1.- Por cada certificado de alineamiento..................... 3.96 veces\nD.- SERVICIOS DE CARTOGRAFÍA Y PROCESOS:\nUNIDAD DE MEDIDA Y\nACTUALIZACIÓN VIGENTE\nI.- Cartografía digital del Municipio de San Felipe escala\n1:1000, a nivel predio:\na).- Por el primer kilómetro cuadrado...... 72.76 veces\nb).- Por kilómetro cuadrado adicional...... 6.61 veces\nII.- Catálogo general de colonias formato\nDigital.................................... 12.60 veces\nE.- POR TRABAJOS TÉCNICOS:\nI.- Perito deslindador autorizado por Catastro\nMunicipal:\na).- Solicitud y aplicación de examen para ingresar al padrón de peritos deslindadores......................... 25.20 veces\nb).- Registro de perito deslindador........ 19.84 veces\nc).- Revalidación anual de peritos deslindadores......................... 19.84 veces\nII.- Referencias de ejes de fraccionamientos:\na).- Revisión en campo de ejes de fraccionamiento para proceso de entrega recepción..................... 5 2.92 veces\nb).- Por cada revisión en campo adicional.. 13.23 veces\nc).- Por análisis y colocación física de referencia de ejes dentro del límite de centro de población por intersección.......................... 18.90 veces\nIII.- Deslinde de predios:\n1.- Elaboración de deslinde y levantamientos en zonas urbanas en donde existan ejes físicos correctos y puntos de control comprobados:\nMAYOR DE: HASTA: UNIDAD DE MEDIDA Y\nACTUALIZACIÓN VIGENTE\n1.00 500.00 M² 22.50 veces\n500.01 1,000.00 M² 31.72 veces\n1,000.01 2,000.00 M² 37.96 veces\n2,000.01 4,000.00 M² 53.41 veces\n4,000.01 6,000.00 M² 71.15 veces\n6,000.01 8,000.00 M² 88.31 veces\n8,000.01 10,000.00 M² 105.48 veces\nSUPERFICIE EN HECTÁREAS\nUNIDAD DE MEDIDA Y\nMAYOR DE HASTA: ACTUALIZACIÓN VIGENTE\n140-00-00 150-00-00 1,766.83 veces\n2.- En las zonas urbanas irregulares o carentes de puntos de control y ejes físicos definidos, se les incrementará 25% a las cuotas del punto número 1.\n3.- Para predios ubicados fuera de la zona urbana pero dentro de los límites del centro de población de San Felipe se les aplicarán los mismos valores del número anterior.\n4.- Los predios cuya superficie excede de las 150-00-00 hectáreas pagarán los derechos de deslinde de acuerdo al presupuesto que al efecto realice Catastro Municipal, el que en todo caso será equivalente al costo del servicio y previa solicitud del interesado.\n5.- A los predios ubicados dentro de los límites de centros de\nPoblación que no sean cabecera municipal, además de las cuotas anteriores se les acumulará 0.40 veces la Unidad de medida y actualización vigente para cada kilómetro fuera de la ciudad.\n6.- Para terrenos semicerriles o lomeríos, los cuales para uniformes menores de 30 grados, tendrán las cuotas anteriores un incremento de 40%, los terrenos cerriles, pendientes mayores de 30 grados, tendrán un aumento del\n75% a las cuotas establecidas.\nIV.- Levantamiento de predios, se pagará el 25% más del costo de los deslindes, de acuerdo a los rangos establecidos en los incisos anteriores. al presupuesto que al efecto realice Catastro Municipal, el que en todo caso, será equivalente al costo del servicio y previa solicitud del interesado.\n2.- A los predios ubicados fuera del centro de población de\nSan Felipe, además de las cuotas anteriores se les acumulará\n0.37 veces la Unidad de medida y actualización vigente para cada kilómetro fuera de la Zona Urbana.\n3.- Para terrenos semicerriles o lomeríos, los cuales para efectos fiscales se considerarán aquellos de pendientes uniformes menores de 30 grados tendrán las cuotas anteriores un incremento de 40%, los terrenos cerriles, considerándose para efecto aquellos con cambios bruscos de pendientes mayores de 30 grados, tendrán un aumento del\n75% a las cuotas establecidas.\n4.- En zonas urbanas o suburbanas irregulares o fuera de los límites de los centros de población donde no exista la totalidad de los ejes físicos y puntos de control definidos, que requieran análisis extraordinarios se cobrará un 50% adicional a las cuotas anteriores de deslindes.\n5.- Los trabajos de levantamiento, deslinde o estudio, cálculo y verificación física de planos para efectos de certificación catastral de predios ubicados en lugares donde no exista oficina de Catastro Municipal y Control\nUrbano causarán una cuota adicional, equivalente a los gastos de transporte, alojamiento y alimentación del personal que se utilice.\nV.- Verificación física de deslinde de predio, para colocación de con vigencia menor a 3 años a solicitud del interesado, se pagará un 50% del costo de los deslindes o levantamiento, de acuerdo a los rangos establecidos en los incisos anteriores.\nVI.- Certificación de deslindes y/o levantamiento para el estudio, Autorización y certificación por parte de Catastro Municipal, se levantamiento de los predios, de conformidad con la siguiente tabla:\n1.- Hasta 10,000 m².............................. 35.00 %\n2.- Mayor de 1 hasta 20 hectáreas................ 30.00 %\n3.- Mayor de 20 hectáreas........................ 27.50 %\nHectáreas, pagarán los derechos de certificación de\nCatastro Municipal. artículo, por causas imputables al solicitante y se compruebe por parte de Catastro Municipal, se llevará a cabo la devolución del\n25% del pago efectuado.\nVII.- En la certificación de deslindes urbanos, que se requiera en carácter de urgente se cobrará tres veces el valor que se específica en el Artículo 46, inciso E de esta Ley.\nVIII.- Verificación física de deslinde de predio para certificación a partir de la segunda revisión en campo.\na). Dentro de los límites de la zona urbana...... 6.61 veces\nb). Fuera de la zona urbana del Municipio de San\nFelipe, dentro del límite de un centro de población.................................. 7.93 veces\nc). Fuera de la zona urbana de la del Municipio de\nSan Felipe, por cada kilómetro recorrido fuera del límite de un centro de población......... 0.40 veces\nE) URBANIZACIÓN MUNICIPAL\nARTÍCULO 47.- Los servicios que presta Urbanización Municipal de San\nFelipe, se cobrarán conforme a lo siguiente:\nUNIDAD DE MEDIDA Y\nACTUALIZACIÓN VIGENTE\nI.- Verificación del certificado de no adeudo por parte de Urbanización Municipal de San\nFelipe..................................... 2.50 veces\nII.- Emisión de carta de confirmación de inclusión en el Programa de Obra del Organismo de determinada obra de urbanización a efectuarse. 2.50 veces\nIII.- Carta de cancelación de Gravamen ante Registro\nPúblico de la propiedad........................ 2.50 veces\nIV.- Servicios de expedición, grabación y/o envío de documentos e información solicitada a\nUrbanización, serán pagados de acuerdo a lo siguiente:\na).- Copia Fotostática......................... 0.0166 veces\nb).- Copia certificada......................... 1.05 veces\nc).- Copia digital de expedientes por cada 20 páginas................................... 0.18 veces\nV.- Otros Servicios:\nLas obras ejecutadas en años anteriores se determinarán y cobrarán aplicando la tasa fija de la Ley de Ingresos vigente en la fecha en que se realizaron.\nSe cobrarán Derechos de conformidad al presupuesto que al efecto realice Urbanización Municipal de San Felipe, los que en todo caso serán proporcionales al costo del servicio. Los ingresos que por concepto de derechos, transferencias, asignaciones y ayudas sociales que se perciban, pasarán a formar parte del patrimonio de Urbanización\nMunicipal de San Felipe.\n16 SERVICIOS QUE PRESTA OBRAS Y SERVICIOS PÚBLICOS MUNICIPALES\nARTÍCULO 48.- Los derechos por estos servicios, se pagarán conforme a lo siguiente:\nPANTEONES MUNICIPALES\nUNIDAD DE MEDIDA Y\nACTUALIZACIÓN VIGENTE\nI.- Exhumaciones................................... 10.58 veces\nII.- Inhumaciones de restos humanos................. 2.46 veces\nIII.- Inhumaciones a perpetuidad, en hora hábil...... 39.69 veces\nIV.- Inhumaciones a perpetuidad en hora inhábil..... 52.92 veces\nV.- Apertura de fosa............................... 13.23 veces\nVI.- Instalación o remodelación de lápidas.......... 2.46 veces tendrán un descuento del 100%, las personas de escasos recursos, previa\nDesarrollo Integral de la Familia Municipal, en los servicios para padres e hijos y cónyuges.\nEn cumplimiento a la fracción VIII del Artículo 63 de la Ley sobre\nDesaparición y Búsqueda de Personas para el Estado de Baja California, quedan exentas del pago de los derechos a que se refieren las Fracciones\nI, II, III y IV de este Artículo, los familiares que soliciten estos servicios respecto de una persona que fuere objeto de búsqueda y localización en términos de dicha Ley, previa comprobación del parentesco.\nSon solidariamente responsables del pago de los derechos a que se refiere este artículo, las personas físicas, jurídicas o unidades económicas, que presten los servicios.\nRECOLECCIÓN DE BASURA\nARTÍCULO 49.- Los derechos por el servicio de recolección de basura en recipientes comunales o que tengan carácter extraordinario, que preste la Autoridad Municipal a giros comerciales, industriales o de servicio, la ubicación, superficie del terreno, periodicidad del servicio y otros elementos que impacten en el costo del mismo.\nEl servicio de recolección de basura para giros comerciales, industriales o de servicio, será de acuerdo al costo siguiente:\nTABULADOR\nUNIDAD DE MEDIDA Y\nACTUALIZACIÓN VIGENTE\n1.- Abarrotes, misceláneas, panaderías, pastelerías, paleterías, papelerías, vidrierías, comisionistas, café internet, curiosidades y artesanías, dulcerías, decoraciones, puestos de dulces, equipos de comunicación, gimnasios, imprentas, videos, zapaterías, venta de artículos de belleza, venta de artículos para el hogar, regalos y novedades, venta de artículos para fiestas, talabarterías, tapicerías, televisión por cable, estéticas, salas de belleza, barberías y peluquerías, laboratorios, farmacias, renta de tuxedos, seguridad y protección, rayos X, ultrasonidos, reparación de calzado, retacerías, rotulistas, sastrerías:\na).- Con superficie de construcción menor a 20 M² 3.00 VECES\nb).- Con superficie de construcción de 21 a 60 M² 4.00 VECES\nc).- Con superficie de construcción de 61 a 100 M² 5.00 VECES\nd).- Con superficie de construcción mayor a 100 M² 7.50 VECES\n2.- Artículos deportivos, centros de copiado, tiendas de ropa, librerías, casas de cambio, boutiques, venta de agua purificada, (llenado de garrafón), casetas telefónicas, cerrajerías, bolerías, diseño gráfico, venta de celulares, centros cambiarios, fotografías, venta de discos y casetes, casas de empeño, venta de revistas, editoriales, artesanías de vidrio, alfarerías, perfumerías, telecomunicaciones, mueblerías, joyerías, jugueterías, modistas, venta de hielo, venta de pañales, venta de productos de limpieza, venta de video juegos comerciales, fumigadoras, botánicas:\na).- Con superficie de construcción menor a 20 M² 3.00 VECES\nb).- Con superficie de construcción de 21 a 60 M² 3.00 VECES\nc).- Con superficie de construcción de 61 a 100 M² 4.00 VECES\nd).- Con superficie de construcción mayor a 100 M² 5.00 VECES\n3.- Despachos profesionales. Oficinas administrativas, agencias aduanales, agencias bienes y raíces, agencia de mudanzas, agencias de publicidad, agencia de seguros y fianzas, agencias de viajes, bufetes jurídicos, notarías y escritorios públicos, limpiadurías:\na).- Con superficie de construcción menor a 20 M² 4.00 VECES\nb).- Con superficie de construcción de 21 a 60 M² 5.00 VECES\nc).- Con superficie de construcción de 61 a 100 M² 7.50 VECES\nd).- Con superficie de construcción mayor a 100 M² 10.00 VECES\n4.- Academias particulares, escuelas, centros educativos, edificios educativos, colegios particulares, guarderías y jardines de niños particulares:\na).- Hasta 6 aulas 10.00 VECES\nb).- Mayor a 6 aulas 20.00 VECES\n5.- Estacionamientos públicos, guarderías, jardines de niños particulares:\na).- Con superficie de construcción menor a 60 M² 10.00 VECES\nb).- Con superficie de construcción de 61 a 100 M² 15.00 VECES\nc).- Con superficie de construcción mayor de 100 M² 20.00 VECES\n6.- Lavanderías, (lavamáticas), graneros, clínicas veterinarias, autolavados, avícolas, acuarios, forrajearías, tiendas de artículos de segunda y establos:\na).- Con superficie de construcción menor a 20 M² 5.00 VECES\nb).- Con superficie de construcción de 21 a 60 M² 7.50 VECES\nc).- Con superficie de construcción de 61 a 100 M² 12.50 VECES\nd).- Con superficie de construcción mayor a 100 M² 15.00 VECES\n7.- Consultorios médicos, consultorios dentales, clínicas y sanatorios, centros de reducción de peso, nutriólogos, centros de rehabilitación y ópticas:\na).- Con superficie de construcción menor a 60 M² 5.00 VECES\nb).- Con superficie de construcción de 61 a 100 M² 10.00 VECES\nc).- Con superficie de construcción mayor a 100 M² 15.00 VECES\n8.- Centros de espectáculos, centros recreativos, centros vacacionales, cinemas, discotecas y salones de baile (fiestas y\n9.- Talleres: reparación de bicicletas, reparación de tv y radio, industriales autoeléctricos, carrocería, y pinturas, equipos de oficina, de mofles, de soldadura, mecánicos, para tornear, de servicios automotriz y autoservicios, llanteras, reconstructoras automotriz, servicio de lavado y engrasado, reparación de lavadoras, secadoras, estufas, herrerías, reparación de todo en general y maquinados industriales:\na).- Con superficie de construcción menor a 20 M² 4.00 VECES\nb).- Con superficie de construcción de 21 a 60 M² 7.50 VECES\nc).- Con superficie de construcción de 61 a 100 M² 12.50 VECES\nd).- Con superficie de construcción mayor a 100 M² 16.50 VECES\n10.- Moteles con ocupación hasta de 10 habitaciones....25.00 VECES\n11.- Moteles con ocupación mayor de 10 habitaciones.... 33.00 VECES\n12.- Hoteles con ocupación hasta de 30 habitaciones...33.00 VECES\n13.- Hoteles con ocupación mayor a 30 habitaciones... 45.00 VECES\n14.- Agencias automotriz, arrendadoras de equipo de construcción, compra venta de maquinaria industrial, constructoras, renta de autos, lotes de autos usados, renta de maquinaria, renta y venta de casa móviles, venta de equipos diversos y venta de acumuladores:\na).- Con superficie de construcción menor a 20 M² 10.00 VECES\nb).- Con superficie de construcción de 21 a 60 M² 15.00 VECES\nc).- Con superficie de construcción de 61 a 100 M² 25.00 VECES\nd).- Con superficie de construcción mayor a 100 M² 33.00 VECES\n15.- Restaurantes, loncherías, torterías, taquerías, rosticerías, cafeterías, menuderías y pizzerías:\na).- Con superficie de construcción menor a 20 M² 10.00 VECES\nb).- Con superficie de construcción de 21 a 60 M² 15.00 VECES\nc).- Con superficie de construcción de 61 a 100 M² 20.00 VECES\nd).- Con superficie de construcción mayor a 100 M² 25.00 VECES\n16.- Restaurantes bar, bares, cantinas, billares, pescaderías, venta de mariscos preparados y centros de apuestas y sorteos:\na).- Con superficie de construcción menor a 60 M² 15.00 VECES\nb).- Con superficie de construcción de 61 a 100 M² 20.00 VECES\nc).- Con superficie de construcción mayor a 100 M² 25.00 VECES\n17.- Fábricas de cerveza, fábricas de dulces, mueblerías, fábricas de productos alimenticios, fábricas de productos metálicos, marmolerías, fábricas de cartón, fábrica de conservas, fábricas de concreto, fábricas de helados, carpinterías, fábricas de muebles, fábricas de productos de barro y cerámica fábricas de textiles, fábricas de ropa, fábricas de varios ´productos, fundiciones, fábrica de ladrillos, blocks y mosaicos:\na).- Con superficie de construcción menor a 20 M² 15.00 VECES\nb).- Con superficie de construcción de 21 a 60 M² 20.00 VECES\nc).- Con superficie de construcción de 61 a 100 M² 33.00 VECES\nd).- Con superficie de construcción mayor a 100 M² 45.00 VECES\n18.- Maquilas de: aparatos electrónicos y eléctricos, artículos de piel, componentes electrónicos, productos de limpieza, muebles, plásticos, productos alimenticios, productos de vidrio, productos metálicos, productos de madera, productos textiles, productos de barro\n19.- Materiales para la construcción, materiales pétreos, pinturas y barnices, plomería y electricidad, transportistas, bodegas, depósitos y almacén, ferreterías, refaccionarias, refacciones para aparatos domésticos, refacciones para maquinaria pesada, venta de aceites y lubricantes, madererías, servicios de transporte urbano, grúas\n(servicio de arrastre de vehículos y transportes foráneos:\na).- Con superficie de construcción menor a 20 M² 10.00 VECES\nb).- Con superficie de construcción de 21 a 60 M² 15.00 VECES\nc).- Con superficie de construcción de 61 a 100 M² 25.00 VECES\nd).- Con superficie de construcción mayor a 100 M² 33.00 VECES\n20.- Tiendas de autoservicio, carnicerías, centros de abasto, distribución y venta de alimentos preparados, comercializadoras, tortillerías, fruterías y verdulerías, licorerías, mercados, supermercados, productos lácteos, expendios de cervezas, funerarias, fumigadoras, gases industriales, gasolineras, recicladoras de basura, yonkes, recolectoras de basura, distribuidoras de gas doméstico, empacadoras, envasadoras y embotelladoras, florerías, mensajería y recicladoras:\na).- Con superficie de construcción menor a 20 M² 10.00 VECES\nb).- Con superficie de construcción de 21 a 60 M² 15.00 VECES\nc).- Con superficie de construcción de 61 a 100 M² 25.00 VECES\nd).- Con superficie de construcción mayor a 100 M² 33.00 VECES\n21.- Templos/Iglesias e instituciones no lucrativas:\na).- Con superficie de construcción hasta a 100 M² 5.00 VECES\nb).- Con superficie de construcción mayor a 100 M² 33.00 VECES\n22.- Instituciones bancarias, institutos de comunicación y comercio, radiodifusoras:\na).- Con superficie de construcción menor a 20 M² 8.00 VECES\nb).- Con superficie de construcción de 21 a 60 M² 10.00 VECES\nc).- Con superficie de construcción de 61 a 100 M² 15.00 VECES\nd).- Con superficie de construcción mayor a 100 M² 25.00 VECES\n23.- Servicios de instalaciones eléctricas, servicentros, servicios de limpieza, servicios de teléfonos, servicios administrativos, servicios de aire acondicionado, servicios de informática, servicios de ingeniería y arquitectura, servicios de plomería y servicios en general:\na).- Con superficie de construcción menor a 20 M² 8.00 VECES\nb).- Con superficie de construcción de 21 a 60 M² 10.00 VECES\nc).- Con superficie de construcción de 61 a 100 M² 15.00 VECES\nd).- Con superficie de construcción mayor a 100 M² 20.00 VECES\nLos pagos a que se refiere este artículo se pagarán de forma trimestral.\nLos giros descritos en los numerales del 1 al 9 gozarán de un 10% de descuento al realizar su pago anual. Quedan exentos de pago en 2025 las escuelas de educación básica, media superior y superior tanto públicas como privadas. el pago de acuerdo a la tarifa de giros similares. enajenación de bienes propios del Municipio de San Felipe, consistente en materia de Reciclaje que deberá ser separado del resto del contenido recolectado, conforme lo establezca el reglamento correspondiente aplicable a la materia.\nSERVICIOS DE LIMPIEZA, TRASLADO, TAPIADO Y DEMOLICIÓN\nARTÍCULO 50.- Los derechos por servicios de limpia, traslado, tapiado y demolición por afectación a la vía pública y/o a petición de parte en domicilios particulares, terrenos baldíos, unidades habitacionales y otros, serán fijados en cada caso por la autoridad municipal, dependiendo de la ubicación, superficie y otros elementos que impacten en el costo del mismo. Debiéndose pagar los Derechos correspondientes de acuerdo a lo siguiente:\nUNIDAD DE MEDIDA Y\nACTUALIZACIÓN VIGENTE\nA). - Limpieza y deshierbe con medios Mecánicos (M²)... 0.25 VECES\nB). - Limpieza y deshierbe con medios manuales (M²)... 0.50 VECES\nC).- LIMPIEZA POR EVENTOS Y ESPECTACULOS.................10.00 VECES\nD).- Por poda de árbol y arbusto se pagará de acuerdo a lo siguiente:\na).- Poda con herramienta manual de pieza menor de 3.00 m. de altura (copa de 3.00 a 4.00 m.), incluye: herramienta menor, realización del trabajo, limpieza, retiro y traslado del producto de la poda. 15.60 VECES\nb).- Poda con maquinaria y equipo a pieza mayor a\n3.00 m. y menor a 11.00 m. (copa de 8.00 a\n66.30 VECES\n11.00 m.) incluye: grúa, equipo especial y herramienta menor, mano de obra, limpieza, traslado y retiro del producto de la poda.\nE).- Por tala de árbol y arbusto se pagará de acuerdo a lo siguiente:\na).- Tala con herramienta manual de pieza menor de 3.00 m de altura (copa de 3.00 a 4.00 m.) incluye: herramienta menor, realización del trabajo, limpieza, retiro y traslado del producto de la tala. 23.40 VECES\nb).- Tala con maquinaria y equipo a pieza mayor a\n3.00 m. y menor a 11.00 m. (copa de 8.00 a\n11.00 m.), incluye: equipo especial y herramienta menor, mano de obra, limpieza, traslado y retiro del producto la tala. 123.50 VECES\nF).- Por tala de árbol y arbusto urgente se pagará de acuerdo a lo siguiente:\na).- Tala con herramienta manual de pieza menor de 3.00 m de altura (copa de 3.00 a 4.00 m.) incluye: herramienta menor, realización del trabajo, limpieza, retiro y traslado del\nb).- Tala con maquinaria y equipo a pieza mayor a\n3.00 m. y menor a 11.00 m. (copa de 8.00 a\n11.00 m.), incluye: grúa, equipo especial y herramienta menor, mano de obra, limpieza, traslado y retiro del producto de la tala 239.20 VECES\nG).- Por transportar los productos de tala o poda de árboles y arbustos, por Servicios Públicos Municipales.\nH). - Carga y retiro de material producto de la limpieza (basura pesada, escombro, ramas, otros) a un kilómetro (M³)........8.00 VECES\nI).- Demolición con medios mecánicos de estructuras (madera, concreto, bloque, otros) carga y acarreo a un kilómetro (M²).....13.00 VECES\nJ).- Acarreo a Km subsecuentes (M³/Km)...........0.25 VECES\nK).- Recolección de basura (ton).............. 7.6 VECES\nSÓLIDOS MUNICIPALES\nARTÍCULO 51.- Los servicios por utilización del sitio de disposición final de residuos sólidos municipales, se pagarán conforme a lo siguiente:\nI.- ESTACIÓN DE TRANSFERENCIA DE LA CIUDAD\nUNIDAD DE MEDIDA Y\nACTUALIZACIÓN VIGENTE\na).- Particulares que en forma esporádica y por sus propios medios depositan residuos de su propiedad, excepto escombro, siempre que no exceda de camión de 1½ toneladas y de tres metros de longitud.......................... EXENTO\nb).- Residuo sólido urbano por tonelada.......... 2.46 veces\nc).- Residuo sólido urbano voluminoso, o diferente al doméstico por tonelada......... 2.46 veces\nII.- ESTACIÓN DE TRANSFERENCIA Y RELLENOS SANITARIOS DEL MUNICIPIO\nDE SAN FELIPE\nUNIDAD DE MEDIDA Y\nACTUALIZACIÓN VIGENTE\na).- Pick-up (con o sin redilas) con basura doméstica por cada ocasión................. EXENTO\nb).- Pick-up (con o sin redilas) con basura\nComercial por cada ocasión................. 1.99 veces\nc).- Camión de una tonelada por cada ocasión.. 2.44 veces\nd).- Camión cerrado o de redilas hasta 6 mts. de largo por cada ocasión..................... 5.29 veces\ne).- Particulares, que en forma esporádica y por sus propios medios depositan desechos de su propiedad, excepto escombro, siempre que no exceda de camión de 1½ toneladas........... EXENTO\nIII.- RELLENO SANITARIO\na).- Particulares, que en forma esporádica y por sus propios medios depositan residuos de su propiedad, excepto escombro, siempre que no exceda de camión de 1½ toneladas y de tres metros de longitud......................... E X ENTO\nb).- Residuo sólido urbano por tonelada......... 1.99 veces\nc).- Residuo sólido urbano, voluminoso o diferente al doméstico por tonelada........ 2.46 veces\nARTÍCULO 52.- Servicios por Supervisión, Licencias de Autorización, Obras de Señalamiento Vial, Constancias de Cumplimiento y Urbanización.\nI.- SERVICIOS POR URBANIZACIÓN en campo que incluya la topografía, infraestructura e instalaciones, estructura de pavimentos, geometría y otros, en la ejecución de obras de urbanización de terrenos que serán destinados a vías públicas, se\nUrbano, el 2%.\nInfraestructura, Desarrollo Urbano y Reordenación Territorial del\nOrganismos Gubernamentales, pagarán un 50% de la tarifa anterior.\nA los urbanizadores y/o promotores inmobiliarios que promuevan donde construyan como mínimo un 25% viviendas tipo económicas del total de los lotes habitacionales que esté desarrollando en el municipio de\nSan Felipe, les será devuelta la cantidad que resulte de multiplicar el número de viviendas económicas inscritas en el Registro Público de la Propiedad y de Comercio del Estado a favor de terceros adquirientes por $1,104.00 pesos Moneda Nacional.\nEsta devolución será aplicable como máximo hasta cubrir la cantidad total de los derechos de urbanización calculados.\nSe considera como vivienda económica aquella que ajustada a la normatividad en materia de edificaciones cuente con todas las obras de urbanización propias de fraccionamientos tipo interés social cuyo valor no exceda los 55,000 UDIS.\nPrevia devolución de la cantidad antes señalada los urbanizadores y/o promotores inmobiliarios deberán someter a la consideración de\nAdministración Urbana los presupuestos de las obras de edificación la cantidad de $ 800.00 pesos Moneda Nacional. Dichos presupuestos se de Obras Públicas Municipales.\nII.- SERVICIOS POR OBRA\nUNIDAD DE MEDIDA Y\nACTUALIZACIÓN VIGENTE pública, para la ejecución de obras públicas o privadas se cobrará conforme a la siguiente tarifa:\na).- De piso, vía pública en lugar no pavimentado, por metro cuadrado o fracción. 1.32 veces\nb).- De calles revestidas de grava conformada, por metro cuadrado o fracción.............. 3.31 veces\nc).- De concreto hidráulico o asfáltico, por metro cuadrado o fracción.................. 5. 2 9 veces\nd).- De guarniciones y banquetas de concreto, por metro cuadrado o fracción.............. 3.31 veces\nCuando la ruptura de la banqueta tenga como propósito su reposición sin modificar su trazo y estructura, así como mejorar la imagen urbana, se considera: EXENTO\nEn cualquiera de los casos previstos en los incisos anteriores, cuando con la obra se mejore la imagen urbana mediante el cambio de una instalación aérea por una subterránea: EXENTO\ne).- Multa por romper pavimento, guarnición, Banqueta y terracería de la vía pública sin haber realizado el trámite ante Obras\nPúblicas Municipales y pago correspondiente para otorgar la licencia o permiso de ruptura teniendo un costo de 150% del valor de la licencia o permiso.\nf).- Multa por alterar o modificar el pavimento, guarnición o banqueta de la vía pública, en las colonias o fraccionamientos destinadas a rampas vehiculares construidas por los ciudadanos para el acceso de un segundo vehículo a la vivienda, sin haber realizado el trámite ante Obras Públicas Municipales y pago correspondiente Para otorgar la licencia o permiso de ruptura teniendo un costo de 150% del valor de la licencia o permiso.\nIII.- SERVICIOS DE MANTENIMIENTO A VIALIDADES solicitantes, así como instalación de altos de discos a giros comerciales y escuelas privadas, tarifa:\na).- Construcción de topes.\nUnidad de medida: metros lineales.......... 15.87 veces\nb).- Retiro de topes.\nUnidad de medida: metros lineales.......... 7.93 veces\nc).- Altos de disco.\nUnidad de medida: pieza.................... 30.42 veces\nIV.- CONGELADO DE CRUCES PEATONALES, ZONAS COMERCIALES Y ESCUELAS\nPRIVADAS.\nPor la aplicación de pintura reflejante a solicitud de giros comerciales y escuelas privadas, tarifa:\na).- En cruces peatonales.\nUnidad de medida: metros cuadrados......... 1.99 veces\nb).- En cordones.\nUnidad de medida: metros lineales.......... 1.32 veces\nc).- En líneas de pavimento.\nUnidad de medida: metros lineales.......... 0.20 veces\nV.- SERVICIOS POR EXPEDICIÓN DE CONSTANCIAS DE URBANIZACIÓN\nPor la expedición de “constancia de terminación de obra y liberación de garantías” se pagará de acuerdo a la siguiente tarifa:\na).- Para fraccionamientos dentro del centro de 66.15 veces población..................................\nb).- Para fraccionamientos fuera del centro de población.................................. 92.61 veces\nVI.- POR CONSTANCIA DE CUMPLIMIENTO DE REQUISITOS PARA TRASLACIÓN DE\nDOMINIO EN DESARROLLOS URBANOS\na).- De 1 a 50 lotes solicitados................ 66.15 veces\nb).- Por cada lote adicional.................... 1.38 veces\nDe ser necesario una segunda revisión, se deberá cubrir el 50% de los antes dispuesto según rango.\n17 EXPEDICIÓN DE OTROS CERTIFICADOS, TÍTULOS O COPIAS DE DOCUMENTOS\nARTÍCULO 53.- Los certificados, copias certificadas, legalización de firmas y demás servicios administrativos proporcionados por las Áreas\nMunicipales, de los cuales no exista tarifa específica en otro apartado de esta Ley, se pagarán conforme a la siguiente tarifa:\nUNIDAD DE MEDIDA Y\nACTUALIZACIÓN VIGENTE\nI.- Certificación en general por documento.......... 1.32 veces\nII.- Tratándose de certificación de expedientes, por cada hoja....................................... 0.209 veces\nIII.- Expedición de títulos de propiedad o contratos de compraventa.................................. 19.84 veces\nIV.- Certificado de residencia....................... 1.32 veces\nV.- Carta de residencia para obtener la tarjeta del\nINAPAM y/o Tarjeta Violeta...................... EXENTO\nVI.- Expedición de Certificado de Vecindad........... 6.61 veces\nVII.- Certificado de Arraigo.......................... 6.61 veces\nVIII.- Certificación de firmas de Constitución de\n13.23 veces\nSociedades Cooperativas.........................\na).- Copia adicional de la Certificación........ 3. 96 veces\nb).- Certificación de actas de asambleas........ 6.61 veces\nIX.- Constancia de Origen............................ 6.61 veces\nX.- Formato de declaración para el pago del Impuesto\nSobre Adquisición de Inmuebles de 1 a 10 formas. 0.18 vez c/u\na).- De 11 a 50 formas.......................... 0.17 vez c/u\nb).- De 51 a 100 formas......................... 0.16 vez c/u\nc).- De 101 en adelante......................... 0.15 vez c/u\nXI.- Revisión, análisis y resguardo documental para registro de peritos valuadores, pago único...... 19.84 veces\nXII.- Revalidación anual de revisión, análisis y valuadores...................................... 19.84 veces\nXIII.- Por revisión de avalúo por clave Catastral...... 5.29 veces\nXIV.- Copia:\na).- Fotostática simple por hoja............... 0.06 veces\nb).- Por copia digital por hoja............. 0.06 veces\nSe entenderá por copia digital la que conste en archivo digital o sistema de cómputo.\nc).- Por copia simple o digitalizada que requiera testarse.......................... 0. 22 veces\nd).- Cuando implique la entrega de no más de\nXV.- Emisión de estados de cuenta del Impuesto\nPredial:\na).- De 1 a 10.................................. EXENTO\nb).- De 11 en adelante.......................... 0.018 vez c/u\nXVI.- Por servicio del cobro y entrega a domicilio del recibo de pago del impuesto predial (hasta dos trámites en un mismo domicilio)................. 1.32 veces\nXVII.- Certificado de no adeudo para licitaciones y proveedores del Gobierno Municipal............... 1.99 veces\nXVIII.- Certificado de no adeudo para revalidación de permisos por establecimiento.................... 1.99 veces\nXIX.- Certificado de no adeudo para revalidación del\nPermiso de alcoholes y establecimientos para eventos sociales................................ 1.99 veces\nXX.- Certificado de no adeudo para revalidación vehicular....................................... EXENTO\nXXI.- Expedición de Constancia de Presentación de la\nDeclaración de Situación Patrimonial y de con la presentación de la Declaración Fiscal. 6.61 veces\nTratándose de la Fracción IV del presente Artículo, tendrán un 50% de urbana. Personas mayores de sesenta años de edad, personas con dependencia económica, pescadoras ribereñas y madres jefas de familia quedarán exentas del pago.\n18 SERVICIOS QUE PRESTA LA COORDINACIÓN DEL DEPORTE Y CULTURA FÍSICA\nMUNICIPAL Y LA COORDINACIÓN MUNICIPAL DE ARTE Y CULTURA.\nA) UNIDADES DEPORTIVAS, PARQUES Y ESTADIOS MUNICIPALES\nARTÍCULO 54.- Los servicios que prestan las Unidades Deportivas, Parques y Estadios Municipales por el uso de inmobiliario e instalaciones, se cobrarán conforme a lo siguiente:\nI.- Los ingresos por conceptos son:\nTARIFA\nMONEDA NACIONAL\n1). Entradas:\na).- Boleto menores de 18 años....... EXENTO\nb).- Boleto entrada, adultos........ $ 5.00 M.N.\nc).- Entrada adulto mayor presentando tarjeta INAPAM o cualquier identificación vigente que lo acredite..... EXENTO\nd).- Personas con discapacidad..... EXENTO\n2). Estacionamiento:\n-\na). Estacionamiento por vehículo.. EXENTO\nb). Estacionamiento por vehículo\n3). Renta de instalaciones y otros servicios:\n-\na). Palapa.......................... $ 440.00 M.N.\nb). Áreas verdes................... $1,500.00 a\n$5,000.00 M.N.\nc). Kiosco......................... $1,000.00 a\n$2,750.00 M.N.\nd). Valla Publicitaria $1,000.00 a\n(perimetral) $3,000.00 M.N.\ne). Estacionamiento por cajón por día para renta de espacio para exposiciones juegos o ferias..... $ 20.00 M.N.\nf). Cuota de recuperación por el uso de Energía eléctrica por evento (Rocolas, inflables, abanicos, aparatos eléctricos)................... $ 160.00 M.N.\ng).- Autorización a vendedores ambulantes por día (Puestos chicos/móviles)................. $ 150.00 M.N.\nh). Autorización a vendedores ambulantes por día (puestos semifijos)...................... $ 350.00 M.N.\ni). Autorización a vendedores ambulantes por día en eventos vespertinos.................... $ 300.00 M.N.\nj). Autorización a vendedores ambulantes por día en eventos nocturnos...................... $ 300.00 M.N.\nk). Por venta para consumo inmediato de bebidas alcohólicas en el interior de las instalaciones, se reintegrará a la Coordinación de Deporte y\nCultura Física Municipal y la\nCoordinación Municipal de Arte y\nCultura por cada unidad vendida:\nSi el precio de venta es de $25.00 $ 4.00 M.N.\nSi el precio de venta es de $30.00 $ 5.00 M.N.\nSi el precio de venta es de $35.00 $ 6.00 M.N.\nY así sucesivamente por cada aumento de 5.00 en el precio de venta se aumentará el costo en $1.00 M.N.\nl). Curso de verano inscripción...... $ 800.00 M.N.\nm). Chapoteadero:\nPersonas con discapacidad....... EXENTO\nNiños de 4 a 15 años (todo el día) $ 30.00 M.N.\nAdultos (todo el día)............ $ 40.00 M.N.\nEn las inscripciones de más de 3 hijos se otorgará un descuento del 30%.\n4). Uso de todo el parque, cualquier\n- día de lunes a viernes, por doce horas $4,400.00 M.N.\n5). Uso de todo el parque sábado o\n- domingo, por todo el día............. $5,500.00 M.N.\n6). Renta mensual de\n- Cafetería.......................... $1,650.00 M.N.\n7). Renta de palapas y mobiliario:\na). Palapas por 6 horas.............. $ 500.00 M.N.\nb). Kiosco (a un costado del área de juegos)................. $ 350.00 M.N.\nc). Cuota de recuperación por limpieza........................ $ 150.00 M.N.\nd). Sillas (c/u).................... $ 10.00 M.N.\ne). Mesas (c/u)..................... $ 30.00 M.N.\n8).- Renta de canchas:\na). Renta de cancha Basquetbol al aire libre, por hora:\nRegular........................ $ 100.00 M.N.\nGrupos con convenio............. $ 50.00 M.N.\nb). Renta de cancha de Fútbol\nAmericano por tres horas (De día):\nRegular......................... $ 400.00 M.N.\nGrupos con convenio.............. $ 300.00 M.N.\nPor cada hora adicional......... $ 130.00 M.N.\nc). Renta de cancha de Fútbol\nAmericano por tres horas (De noche):\nRegular......................... $ 600.00 M.N.\nGrupos con convenio.............. $ 400.00 M.N.\nPor cada hora adicional.......... $ 130.00 M.N.\nd). Renta de cancha de Voleibol al aire libre, por hora (De día):\nRegular......................... $ 100.00 M.N.\nGrupos con convenio.............. $ 50.00 M.N.\ne). Renta de cancha de Voleibol al aire libre, por hora (De noche):\nRegular......................... $ 250.00 M.N.\nGrupos con convenio.............. $ 100.00 M.N.\nf). Renta de cancha de Fútbol\nRápido por hora (De día):\nRegular......................... $ 250.00 M.N.\nGrupos con convenio.............. $ 150.00 M.N.\ng). Renta de cancha de Fútbol\nRápido por hora (De noche):\nRegular......................... $ 400.00 M.N.\nGrupos con convenio.............. $ 300.00 M.N.\nh). Renta de cancha de usos múltiples al aire libre, por día\n(máximo 5 horas):\nRegular......................... $ 700.00 M.N.\nGrupos con convenio............. $ 500.00 M.N.\ni). Renta de campo de Softbol por juego(De día):\nRegular......................... $ 200.00 M.N.\nGrupos con convenio............. $ 150.00 M.N.\nj). Renta de campo de Softbol por juego (De noche):\nRegular......................... $ 400.00 M.N.\nGrupos con convenio............. $ 300.00 M.N.\nPara efectos de este inciso se considera horario de noche en:\nVerano a partir de las 19:00 horas\nInvierno a partir de las 17:00 horas\nk). Renta de equipo deportivo\n(balones de voleibol, básquetbol, fútbol, redes, raquetas, etc.)................ $ 20.00 M.N.\nl). Renta de Brincolina Acuática en evento organizado en las instalaciones por 5 horas........................... $ 500.00 M.N.\n9).- Renta de espacios a vendedores ambulantes:\n1. Autorización a toma de fotografías con fines lucrativos, por día......................... $ 350.00 M.N.\n2. Renta mensual de espacio por máquina expendedora de productos...................... $ 900.00 M.N.\n3. Renta mensual de espacio por mesa\n$ 250.00 M.N. de juego........................\n10). Renta de espacios publicitarios:\n1. Renta mensual de espacio publicitario.\na) Menor o igual a 1.8 x 1.5 mts.......................... $ 500.00 M.N.\n2. Renta de espacio publicitario de\n2.0 x 1.8 mts, ubicado Av.\nChetumal, Mar Caribe Sur, Mar\nCaribe Norte y del km 0 San Felipe al km 13, km 190 al km 170 San\nFelipe carretera 5.\na) Mensual...................... $ 1,000.00 M.N.\nb) Semestral.................... $ 5,000.00 M.N.\nc) Anual........................ $ 10,000.00 M.N.\n3. Renta de espacio publicitario de\n3.0 x 1.8 mts, ubicado sobre Av.\nChetumal, Mar Caribe Sur, Mar\nCaribe Norte y del km 0 San Felipe al km 13, km 190 al km 170 San\nFelipe carretera 5.\na) Mensual...................... $ 2,000.00 M.N.\nb) Semestral.................... $10,000.00 M.N.\nc) Anual....................... $20,000.00\nM.N.\n4. Renta de espacio publicitario de\n3.0 x 2.4 mts y 3.0 x 3.0 mts, ubicado sobre Av. Chetumal, Mar\nCaribe Sur, Mar Caribe Norte y del km 0 San Felipe al km 13, km\n190 al km 170 San Felipe carretera 5.\na) Mensual...................... $ 3,000.00 M.N.\nb) Semestral.................... $15,000.00 M.N.\nc) Anual........................ $28,000.00 M.N.\n5. Renta de espacio publicitario de\n2.4 x 1.2 mts, ubicado dentro y fuera de las instalaciones de la\nUnidad Deportiva José Cabrera\nGándara, parques municipales y estadio.\na) Mensual..................... $ 1,000.00 M.N.\nb) Semestral.................... $ 3,000.00 M.N.\nc) Anual........................ $ 6,000.00 M.N.\n6. Renta de espacio por vehículo en evento \"Car Show\" por día... $ 15.00 M.N.\n11). Cursos (costo mensual):\n1. Acondicionamiento Físico....... $ 300.00 M.N.\n2. Animación deportiva............ $ 300.00 M.N.\n3. Baloncesto (Incluye revisión\n$ 300.00 M.N.\n4. Béisbol........................ $ 300.00 M.N.\n5. Box............................. $ 300.00 M.N.\n6. Campo de entrenamiento\n(Bootcamp).....................\n$ 300.00 M.N.\n7.- Esgrima......................... $ 350.00 M.N.\n8.- Fútbol.......................... $ 350.00 M.N.\n9.- Fútbol Americano................ $ 350.00 M.N.\n10. Fútbol Banderitas.............. $ 350.00 M.N.\n11. Tiro con Arco................... $ 500.00 M.N.\n12. Voleibol....................... $ 350.00 M.N.\n12).- Cursos de Albercas:\n1. Acuaeróbics................... $600.00\nM.N.\n2. Matronatación.................. $800.00 M.N.\n3. Natación........................ $800.00\n(Iniciación, intermedio y M.N. avanzado)\nPor los cursos de los incisos 11) y 12) se otorgará a Instituciones y empresas el 50% de descuento por 10 elementos inscritos.\nPor los cursos de los incisos 11) números 1, 2, 4, 5, 7, 9, 10, y\n12, así como el inciso 12) deberá cubrirse, además de la revisión física, la exploración física al momento de la inscripción.\nTodos los cursos son mensuales, la inscripción se cobra los primeros cinco días de cada mes, del día seis en adelante NO se cobrará proporcional, deberá cubrir la totalidad de la mensualidad.\n13).- Programas Vacacionales:\n1.- Programa Vacacional de Verano por participante, (horario 8:00 a.m. a\n13:00 p.m.) incluye camiseta.......... $1,200.00 M.N.\n2.- Programa Vacacional de Verano por participante, (horario 8:00 a.m. a\n15:00 p.m.) incluye camiseta.......... $1,500.00 M.N.\n3.- Programa vacacional de Semana Santa por participante, (horario 8:00 a.m. a\n15:00 p.m.) NO incluye camiseta....... $ 500.00 M.N.\n4.- Camiseta adicional para el\nParticipante inscrito en el Programa\nVacacional............................ $ 100.00 M.N.\n14).- Otros:\n1.- Arbitraje de Baloncesto por equipo por juego:\na) Abierta, Liga o Copa............... $ 300.00 M.N.\nb) Infantil........................... $ 250.00 M.N.\nc) Escolar............................ $ 200.00 M.N.\n2.- Arbitraje de Fútbol por equipo por juego:\na) Abierta, Liga o Copa............... $ 200.00 M.N.\nb) Infantil........................... $ 150.00 M.N.\nc) Escolar............................ $ 125.00 M.N.\n3.- Arbitraje de Voleibol por equipo por juego.................................\na) Abierta, Liga o Copa............... $ 200.00 M.N.\nb) Infantil........................... $ 150.00 M.N.\nc) Escolar............................ $ 125.00 M.N.\n4.- Inscripción carrera atlética\na) 2 km............................... $ 30.00 M.N.\nb) 5 km............................... $ 50.00 M.N.\n5.- Inscripción paseo ciclista............ $ 20.00 M.N.\n6.- Inscripción torneos categoría Abierta\nNovatos............................... $ 500.00 M.N.\n7.- Inscripción torneos Escolar/Infantil.. $ 400.00 M.N.\n8.- Inscripciones y arbitrajes otros...... $ 300.00 a\n$1,500.00 M.N.\n9.- Pintado de cancha de Fútbol y Softbol. $ 100.00 M.N.\n10.- Organización-Logística de eventos, festivales o torneos, por evento:\na) Regular............................ $3,000.00 a\n$8,000.00 M.N.\nb) Sector empresarial o escolar....... $5,000.00 a\n15,000.00 M.N.\n11.- Organización de Rally Deportivo:\n(Por niño o adulto)\na) Escolar:\n1) De 5 a 8 estaciones............. $ 30.00 a\n$ 50.00 M.N.\n2) De 10 a 15 estaciones........... $ 70.00 a\n$ 100.00 M.N.\nb) Sector Empresarial:\n1) De 5 a 8 estaciones............. $ 70.00 a\n$ 100.00 M.N.\n2) De 10 a 15 estaciones........... $ 100.00 a\n$ 150.00 M.N.\n12.- Reposición de credencial o tarjetón, por persona........................... $ 50.00 M.N.\n13.- Tarjetones (no incluyen la entrada del jugador).............................. $ 50.00 M.N.\nPersonas con más de un hijo, tendrán un 30% de descuento a partir del segundo hijo. Personas con hijos con discapacidad, tendrán un\n50% de descuento por éste.\nSe otorgará un descuento del 15% a mujeres jefas de familia, personas indígenas, personas afrodescendientes o afromexicanas que, mediante estudio socioeconómico emitido por Desarrollo\nIntegral de la Familia Municipal, acredite bajos recursos.\n15).- Paquete Fiestas:\n1.- Paquete Fiesta # 1, que incluye: 3 mesas, 24 sillas, Sonido y Palapa..... $ 650.00 M.N.\n2.- Paquete Fiesta # 2, que incluye: 3 mesas, 24 sillas, Sonido, Palapa y brincolina............................ $ 950.00 M.N.\n3.- Paquete Fiesta # 3, que incluye: 5 mesas, 40 sillas, Sonido y Palapa..... $ 850.00 M.N.\n4.- Paquete Fiesta # 4, que incluye: 5 mesas, 40 sillas, Sonido, Palapa y brincolina............................ $1,200.00 M.N.\n5.- Paquete Fiesta # 5, que incluye: 10 mesas, 80 sillas, Sonido, Palapa y brincolina............................ $1,500.00 M.N.\nLos ingresos que por concepto de derechos, transferencias, Deportivas, Parques y Estadios Municipales, pasarán a formar parte del patrimonio municipal.\nB) COORDINACIÓN DEL DEPORTE Y CULTURA FÍSICA MUNICIPAL\nARTÍCULO 55.- Los servicios que presta la Coordinación del Deporte, y Cultura Física Municipal, se cobrarán conforme a lo siguiente:\nA) DEPORTE:\nI.- Arrendamiento de espacios deportivos:\nTARIFA\nMONEDA NACIONAL\na). Gimnasios:\n-\n1.- Espectáculo Musical................... $ 1 0, 0 0 0.00 a\n$14,000.00 M.N\n2.- Función de Lucha Libre................ $6,800.00 M.N.\n3.- Función de Box........................ $6,800.00 a\n$8,500.00 M.N.\n4.- Función de Artes Marciales............ $6,500.00 M.N.\n5.- Evento Social......................... $6,800.00 a\n$8,850.00 M.N.\n6.- Evento organizado por Asociaciones\nReligiosas legalmente constituidas.... $6,800.00 M.N.\n7.- Expo Industria........................ $6,800.00 a\n$7,800.00 M.N.\n8.- Evento realizado por Partidos\nPolíticos............................. $6,800.00 M.N.\n9.- En programas vacacionales, clínicas deportivas y campamentos.............. $6,800.00 M.N.\n10.- Festivales Escolares.................. EXENTO\n11.- Otros................................. $6,800.00 M.N.\nb). Canchas de Fútbol Soccer:\n-\n1.- Campo de Fútbol Soccer por día (6 horas máximo por día)................. $1,200.00 M.N.\n2.- Campo de Futbol Soccer por partido.... $ 250.00 M.N.\n3.- Campo de Futbol Soccer por hora....... $ 150.00 M.N.\n4.- Otros................................. $ 150.00 a\n$1,000.00 M.N.\nc). Canchas de Béisbol/Softbol:\n-\n1.- Campo de Béisbol o Softbol por día (6 horas máximo por día)................. $1,200.00 M.N.\n2.- Campo de Béisbol o Softbol por partido $ 250.00 M.N.\n3.- Campo de Béisbol o Softbol por hora... $ 150.00 M.N.\n4.- Otros................................. $ 150.00 a\n$1,000.00 M.N.\nd). Canchas de usos múltiples (Basquetbol, Voleibol y otros\n- espacios deportivos):\n1.- Campo de usos múltiples por día....... $ 800.00 M.N.\n(6 horas máximo por día)\n2.- Campo de usos múltiples por partido... $ 250.00 M.N.\n3.- Campo de usos múltiples por hora para eventos no deportivos......... $ 250.00 M.N.\n4.- Otros................................. $ 150.00 a\n$ 400.00 M.N.\ne).- Albercas (arrendamiento únicamente de la mitad de la alberca):\n1.- Alberca por día (4 horas máximo por día).................................. $1,200.00 M.N.\n2.- Alberca por hora...................... $ 15.00 M.N.\n3.- Otros, costo diario................... $ 500.00 a\n$1,000.00 M.N.\nPara los conceptos a los que se refieren los incisos a), b), c) y d) jugadores del municipio de San Felipe para competencias foráneas. Esto con la finalidad de apoyar al deporte local.\nII.- Renta de Otros espacios distintos a los deportivos:\nTARIFA\nMONEDA NACIONAL\na). Por la renta de espacios comerciales\n- (alimentos, dulces otros, etc.):\nMensual:................................... $1,000.00 a\n$4,000.00 M.N.\nPor día:................................... $ 200.00 M.N.\nb). Por la renta de espectaculares:\nAnual:..................................... $60,000.00 a\n$84,000.00 M.N\nMensual:................................... $8,000.00 M.N.\nIII.- Programas y Cursos:\nTARIFA\nMONEDA NACIONAL\n1.- Programa Vacacional de Verano impartido en las instalaciones del área correspondiente por participante:\n1).- Primer niño...................... $ 600.00 M.N.\n2).- Segundo hermano en adelante...... $ 550.00 M.N.\n2.- Curso de natación (por Participante por mes)....................................... $ 300.00 M.N.\n3.- Cursos diversos en instalaciones del área correspondiente por persona............ $ 200.00 M.N.\nPodrán otorgarse descuentos para personas con discapacidad, personas adultas mayores, apoyo institucional, programas de tipo institucional, por intercambio de servicios, mujeres jefas de familia, afrodescendientes, afromexicanas, viudas mayores de 50 años y personas que acrediten bajos recursos mediante estudio socioeconómico emitido por Desarrollo Integral de la Familia Municipal, según lo establezca el Reglamento aplicable a la materia.\nB) COORDINACIÓN MUNICIPAL DE ARTE Y CULTURA:\nI.- Servicios:\nTARIFA\nMONEDA NACIONAL\na).- Inscripción a cursos regulares en la Casa $ 700.00 de la Cultura............................. M.N.\nb).- Inscripción a clases individuales de piano $ 1, 5 00.00 M.N.\nc).- Inscripción a cursos de verano en la Casa $ 725.00 de la Cultura............................. M.N.\nd).- Paquete de curso de verano en Casa de la\n$1,500.00 M.N.\nCultura...................................\ne).- Extensión de horario en paquete de curso de verano en Casa de la Cultura........... $ 3 5 0.00 M.N.\nf).- Inscripción a cursos regulares en Centros\n$ 325.00\nCulturales................................ M.N.\ng).- Paquete de curso de verano en Centros\n$ 630.00\nCulturales................................ M.N.\nh).- Extensión de horario en paquete de curso\n$ 200.00 de verano en Centros culturales........... M. N.\ni).- Adquisición de CD en blanco............... $ 8.00 M.N.\nj).- Copia fotostática simple.................. $ 1.00 M.N.\nk).- Impresión en blanco y negro............... $ 2.00 M.N.\nl).- Escaneo de imágenes....................... $ 7.00 M.N.\nm).- Impresión a color en tamaño carta......... $ 5.00 M.N.\nn).- Impresión a color en tamaño doble carta... $ 10.00 M.N. ñ).- Impresión en 3D (Precio por metro de filamento empleado en cada proyecto)...... $ 4.00 M.N.\no).- Inscripción a cursos en línea en la Casa $ 350.00 de la Cultura............................. M.N.\np).- Inscripción clases individuales en línea de piano y cuerdas en la Casa de la\nCultura................................... $1,500.00 M.N.\nq).- Inscripción a cursos en línea en los $ 250.00\nCentros Culturales de San Felipe........ M.N.\nr).- Asesoría escolar\n1. Semanal........................... 200.00 M.N\n2. Por hora.......................... 50.00 M.N\nPodrán otorgarse descuentos para personas con discapacidad, personas adultas mayores, apoyo institucional, programas de tipo institucional, por intercambio de servicios, mujeres jefas de familia, afrodescendientes, afromexicanas, viudas mayores de 50 años, personas indígenas, pescadoras ribereñas y personas que acrediten bajos\nIntegral de la Familia Municipal, según lo establezca el Reglamento aplicable a la materia.\nII.- Renta de espacios por evento:\nTARIFA\nMONEDA NACIONAL\na).- Salón de usos múltiples centro cultural\nSan Felipe (por 4 horas de evento).......... $1,500.00 M.N.\nb).- Renta de sala de cómputo digital (por 3 horas de evento).......................... $1,500.00 M.N.\nRenta adicional por hora de computadora, en curso de capacitación que exceda de tres horas diarias el costo será de $12.00 M.N.\nPodrán otorgarse descuentos para personas con discapacidad, personas adultas mayores, apoyo institucional, programas de tipo institucional, por intercambio de servicios, pescadoras ribereñas, mujeres jefas de familia, afrodescendientes, afromexicanas, viudas mayores de 50 años y personas que acrediten bajos recursos mediante estudio socioeconómico emitido por Desarrollo Integral de la Familia\nMunicipal, según lo establezca el Reglamento aplicable a la materia.\nEn apoyo a los artistas de la localidad se establece la modalidad de porcentaje, la cual se establecería a través de un instrumento legal en el cual se dictan las condiciones de descuento; esto con el fin de contribuir al fomento de la cultura.\nLos ingresos que por concepto de derechos, transferencias, Municipal de Arte y Cultura, pasarán a formar parte del patrimonio municipal.\n19 SERVICIOS QUE PRESTA BIENESTAR SOCIAL MUNICIPAL\nARTÍCULO 56.- Los servicios que presta el Centro de Desarrollo Humano\nIntegral, se cobrarán conforme a lo siguiente:\nI.- Los ingresos por conceptos son:\nTARIFA\nMONEDA NACIONAL\na).- Servicios Médicos:\n1.- Revisión física por día................ $ 15.00 M.N.\n2.- Revisión física mensual................ $ 50.00 M.N.\n3.- Revisión física adulto mayor\n(presentando credencial INAPAM)........ E XENTO\n4.- Ficha Exploración Física, válida por 15 días, para acceso a las albercas....... $ 50.00 M.N.\nb).- Servicios:\n1.- Atención nutricional sesión............ $ 100.00 M.N.\n2.- Evaluación psicológica individual, niños o adultos........................ $ 100.00 M.N.\n3.- Sesión atención psicológica individual. $ 100.00 M.N.\n4.- Sesión atención psicológica pareja..... $ 150.00 M.N.\n5.- Sesión atención psicológica familiar... $ 200.00 M.N.\n6.- Taller Psicológico Comunitario o\nEmpresarial, por persona............... $ 1 3 0. 0 0 M. N.\n(30 a 50 personas)\n7.- Evaluaciones en niños o adultos por cada prueba............................ $ 600.00 M.N.\na) Test Proyectivo de Personalidad (HTP)\nb) Test de Figura Humana (MACHOVER)\nc) Test de Frases Incompletas (ZACK)\n8.- Paquete de tres evaluaciones........... $1,400.00 M.N.\nToda consulta nutricional o psicológica, deberá cubrirse en su totalidad al momento de agendar la cita.\nPodrán otorgarse descuentos para personas con discapacidad, personas adultas mayores, apoyo institucional, programas de tipo institucional, por intercambio de servicios, pescadoras ribereñas, mujeres jefas de familia, afrodescendientes, afromexicanas, viudas mayores de 50 años y personas que acrediten bajos recursos mediante estudio socioeconómico emitido por\nDesarrollo Integral de la Familia Municipal, según lo establezca el Reglamento aplicable a la materia.\nTratándose de los incisos a) numeral 1, inciso b) numerales 3 y 5 canalizadas por \"instituto\" de la Mujer.\nc).- Asesoría escolar:\n1.- Asesoría individual, en todos los niveles escolares:\na) Por semana........................ $ 150.00 M.N.\nb) Por sesión........................ $ 40.00 M.N.\n2.- Escuela para adultos:\na) Por semana........................ $ 150.00 M.N.\nb) Por sesión........................ $ 40.00 M.N.\nd).- Renta de infraestructura:\n1.- Renta de concesión “A” mensual......... $3,000.00 M.N.\n2.- Renta de concesión \"B\" y \"C\" mensual... $3,000.00 M.N.\n3.- Renta de salón de usos múltiples por hora (capacidad máxima 40 personas).... $ 300.00 M.N.\n4.- Renta de sala audiovisual por hora:\n(No incluye proyector)\nRegular................................ $ 400.00 M.N.\nGrupos con convenio.................... $ 300.00 M.N.\n5.- Renta de sala audiovisual, máximo 8 horas: (No incluye proyector)\nRegular................................ $2,000.00 M.N.\nGrupos con convenio.................... $1,000.00 M.N.\n6.- Renta de Brincolina en evento organizado en las instalaciones por\n5 horas................................ $ 450.00 M.N.\n7.- Renta de Sonido (Bocina y tripie) en evento organizado dentro de las instalaciones por día..................\n$ 250.00 M.N.\n8.- La renta mensual de los bienes inmuebles propiedad del Centro de\nDesarrollo Humano Integral, será fijada de acuerdo al contrato o convenio que se celebre, dependiendo de la superficie ocupada y de su localización.\ne).- Cursos (costo mensual):\n1.- Artes Marciales Chinas (Kung Fu, Wu\nShu, Tai Chi)....................... $ 300.00 M.N.\n2.- Artes Marciales Chinas por sesión\n(Kung Fu, Wu Shu, Tai Chi).......... $ 30.00 M.N.\n3.- Artes marciales mixtas................ $ 300.00 M.N.\n4.- Artes marciales mixtas por sesión..... $ 30.00 M.N.\n5.- Baile de Salón........................ $ 350.00 M.N.\n6.- Ballet por sesión................... $ 40.00 M.N.\n7.- Ballet.............................. $ 350.00 M.N.\n8.- Belleza............................... $ 400.00 M.N.\n9.- Canto................................. $ 300.00 M.N.\n10.- Computación........................... $ 300.00 M.N.\n11.- Corte y confección.................... $ 400.00 M.N.\n12.- Danza aérea......................... $ 350.00 M.N.\n13.- Danza Folklórica................... $ 350.00 M.N.\n14.- Danzas Internacionales por sesión..... $ 40.00 M.N.\n15.- Danzas Internacionales.............. $ 350.00 M.N.\n16.- Danzas Polinesias por sesión.......... $ 40.00 M.N.\n17.- Danzas Polinesias................... $ 350.00 M.N.\n18.- Dibujo................................ $ 300.00 M.N.\n19.- Dibujo por sesión..................... $ 25.00 M.N.\n20.- Dibujo Digital........................ $ 400.00 M.N.\n21.- Diplomado............................. $3,500.00 M.N.\n22.- Guitarra.............................. $ 300.00 M.N.\n23.- Guitarra por sesión................... $ 55.00 M.N.\n24.- Hip Hop............................... $ 350.00 M.N.\n25.- Jazz.................................. $ 350.00 M.N.\n26.- Jazz por sesión....................... $ 30.00 M.N.\n27.- Karate.............................. $ 350.00 M.N.\n28.- Karate por sesión................... $ 40.00 M.N.\n29.- Kick Boxing......................... $ 300.00 M.N.\n30.- Kick Boxing por sesión................ $ 40.00 M.N.\n31.- Manualidades.......................... $ 300.00 M.N.\n32.- Manualidades por sesión:\na) Sábados............................ $ 80.00 M.N.\nb) Entre semana....................... $ 40.00 M.N.\n33.- Modelaje y Expresión Corporal......... $ 500.00 M.N.\n34.- Pintura............................... $ 300.00 M.N.\n35.- Pintura por sesión.................... $ 80.00 M.N.\n36.- Rumba (Ritmos latinos)................ $ 350.00 M.N.\n37.- Salsa................................. $ 300.00 M.N.\n38.- Taekwondo............................. $ 300.00 M.N.\n39.- Teatro................................ $ 300.00 M.N.\n40.- Uñas acrílicas........................ $ 400.00 M.N.\n41.- Yoga.................................. $ 300.00 M.N.\n42.- Zumba................................. $ 300.00 M.N.\n43.- Zumba por sesión...................... $ 40.00 M.N.\n44.- Otros cursos.......................... $ 300.00 a\n$1,500.00 M.N.\nPodrán otorgarse descuentos para personas con discapacidad, personas adultas mayores, apoyo institucional, programas de tipo institucional, por intercambio de servicios, pescadoras ribereñas, mujeres jefas de familia, afrodescendientes, afromexicanas, viudas mayores de 50 años emitido por Desarrollo Integral de la Familia Municipal, según lo establezca el Reglamento aplicable a la materia.\nf).- Programas Vacacionales:\n1.- Programa Vacacional de Verano por participante, (horario 8:00 a.m. a\n13:00 p.m.) incluye camiseta.......... $1,200.00 M.N.\n2.- Programa Vacacional de Verano por participante, (horario 8:00 a.m. a\n15:00 p.m.) incluye camiseta.......... $1,500.00 M.N.\n3.- Programa vacacional de Semana Santa por participante, (horario 8:00 a.m. a\n15:00 p.m.) NO incluye camiseta....... $ 500.00 M.N.\n4.- Camiseta adicional para el\nParticipante inscrito en el Programa\nVacacional............................ $ 100.00 M.N.\ng).- Centro de conocimiento:\n1.- Hora de Internet...................... $ 5.00 M.N.\n2.- Impresiones en blanco y negro (precio por hoja)............................. $ 1.00 M.N.\n3.- Impresiones y/o copias a color precio por hoja)............................. $ 6.00 M.N.\n4.- Copia tamaño/carta en blanco y negro\n(precio por hoja)..................... $ 1.00 M.N.\n5.- Copia tamaño/oficio en blanco y negro\n(precio por hoja)..................... $ 2.00 M.N.\nh).- Preparatoria abierta impartida en\nCentro de Desarrollo Humano Integral por alumno por día.............. $ 12.00 M.N.\ni).- Renta mensual del espacio a máquinas expendedoras:\n1.- Productos Bimbo........................ $1,900.00 M.N.\n2.- Productos Coca Cola.................... $1,200.00 M.N.\n1.- EMPLEADOS DE CONFIANZA, EVENTUALES, ASIMILADOS Y COMISIONADOS\nDEL CENTRO DE DESARROLLO HUMANO INTEGRAL\na).- Descuento del 20% en cursos permanentes, 20% en cursos temporales como: vacacional, 10% de descuento en todos los demás servicios (rentas, etc.) Para ellos y sus familias, incluye: padres, esposo (a) e hijos, y solamente para empleados solteros y sin hijos incluye a los hermanos. Excepto sesión psicológica esta aplica el pago del 100% del costo.\n2.- EMPLEADOS DE LOS TRES NIVELES DE GOBIERNO CON IDENTIFICACIÓN\nVIGENTE.\na).- Descuento del 20% en cursos para ellos y sus familias, incluye: esposo (a) e hijos y descuento del 30% a partir del segundo curso a una misma persona.\n3.- POBLACIÓN EN GENERAL.\na).- Familiar inscrito en algún curso, (esposo(a), padres, hermanos, hijos) descuento del 10% a partir del segundo usuario inscrito y descuento del 20% a partir del segundo curso a una misma persona, así como descuento del 20% al segundo o más hermanos que se inscriban en cualquier curso.\nb).- Personas con necesidades de rehabilitación, 100% de descuento en el uso de las instalaciones del gimnasio, presentando parte del paramédico del centro.\nc).- Personas adultas con enfermedades crónicas degenerativas\n(diabetes, hipertensión, sobrepeso, obesidad, etc.) 100% de descuento en curso presentando su solicitud por escrito acompañada de una copia del diagnóstico médico emitido por una institución de salud pública o privada y disposición para realizarse una revisión física por parte del paramédico del centro.\nd).- Personas con discapacidad, descuento del 100% en servicios\n(rentas, etc.).\ne).- Personas Adultos Mayores, descuento del 50% en cursos presentando su credencial de INAPAM. No transferible, SUJETO A\nSANCIÓN.\nf).- Cualquier otro descuento que no figure en los ya mencionados, deberá ser autorizado por la autoridad municipal.\n4.- POLÍTICA GENERAL DE PROMOCIONES Y DESCUENTOS.\na).- Se establece de forma permanente 2 x 1 a usuarios de nuevo\nIngreso o en cursos a un mismo usuario, en los meses de Enero, Febrero y Septiembre, por ser temporada baja, en aquellos cursos que tengan solo 5 o menos usuarios inscritos, siempre que el instructor esté de acuerdo.\nb)- Al iniciar un nuevo curso se podrá otorgar promoción del 2x1\nInstructor esté de acuerdo.\nc).- Las personas indígenas, personas afromexicanas, afrodescendientes, viudas mayor de 50 años, previa solicitud y\nIntegral de la Familia Municipal, tendrá 50% de descuento en los servicios correspondientes a la Fracción I incisos a), b), c),\ne) y h).\nd).Mujeres canalizadas por ser víctimas de violencia estarán exentas de pago en los servicios correspondientes a la Fracción I incisos\na), b), c), e) y h).\nNota: Estos descuentos no son acumulativos a otras promociones.\nLos ingresos que por concepto de derechos, transferencias, asignaciones y ayudas sociales que se perciban en favor del Centro de Desarrollo Humano Integral, pasarán a formar parte del patrimonio municipal.\nARTÍCULO 57.- Los servicios que presta la Coordinación de Deporte y\nCultura Física Municipal y la Coordinación Municipal de Arte y Cultura de San Felipe, se cobrarán conforme a lo siguiente:\nTARIFA\nMONEDA NACIONAL\nI.- Cuota diaria por cursos y talleres Impartidos... $ 12.00 M.N.\nII.- Plan Vacacional por alumno por día............... $ 20.00 M.N.\nARTÍCULO 58.- Los servicios que presta Bienestar Social Municipal, se pagarán conforme a lo siguiente:\nTARIFA\nMONEDA NACIONAL\na).- Boletos por entrada de eventos culturales, sociales, deportivos, conferencias, talleres, cursos y sorteos que por su naturaleza se tengan que cobrar....... EXENTO\nLos ingresos que por concepto de derechos, transferencias, asignaciones\nMunicipal, pasarán a formar parte del patrimonio municipal.\n20 SERVICIOS QUE PRESTA EL COMITÉ DE TURISMO\nY CONVENCIONES DE SAN FELIPE\nARTÍCULO 59.- Los servicios que presta el Comité de Turismo y\nConvenciones del Municipio de San Felipe, se cobrarán conforme a lo siguiente:\nTARIFA\nMONEDA NACIONAL\nI.- Mapa Turístico:\na). Espacio................................ $5,000.00 M.N\n.\nII.- Por la recuperación del costo que impacta en el desarrollo de eventos turísticos, por concepto de recolección de basura, seguridad pública y servicios adicionales, se pagará por el participante en los eventos, siendo responsables solidarios y retenedores los organizadores de los mismos, debiendo cubrirse los Derechos correspondientes al solicitarse el servicio, de acuerdo a la siguiente tarifa:\na). Eventos con unidades motorizadas, unidad............................... 3.38 UMA\nb). Eventos con unidades no motorizadas, participante........................... 0.40 UMA\n.\nLos ingresos que por concepto de derechos, transferencias, asignaciones\nConvenciones, pasarán a formar parte del patrimonio municipal.\n21 SERVICIOS QUE PRESTA\nDESARROLLO INTEGRAL DE LA FAMILIA MUNICIPAL\nARTÍCULO 60.- Los servicios que presta Desarrollo Integral de la Familia\nMunicipal de San Felipe, se cobrarán conforme a lo siguiente:\nTARIFA\nMONEDA NACIONAL\nI.- Oficinas Generales:\na).- Consulta Médica........................... EXENTO\nb).- Certificado Médico........................ $ 20.00 M.N.\nc).- Consulta Psicológica, por Sesión.......... $ 50.00 M.N.\nd).- Servicio Dental........................... $ 50.00 M.N.\ne).- Cuota de Inscripción por curso.......... $ 60.00 M.N.\nf).- Cuota semanal por taller por participante dependiendo del curso........ $ 30.00 hasta\n$ 60.00 M.N\nAdemás de los subsidios, aportaciones, subvenciones y bienes que los\nGobiernos Federal, Estatal y Municipal, y otras entidades otorguen.\nLas aportaciones, donaciones, legados y demás liberalidades que reciba de personas físicas y morales.\nPodrán otorgarse descuentos para personas con discapacidad, personas adultas mayores, apoyo institucional, programas de tipo institucional, por intercambio de servicios, pescadoras ribereñas, mujeres jefas de familia, afrodescendientes, afromexicanas, viudas mayores de 50 años y personas que\nDesarrollo Integral de la Familia Municipal, según lo establezca el Reglamento aplicable a la materia.\nLos ingresos que por concepto de derechos, transferencias, asignaciones\nFamilia Municipal, pasarán a formar parte del patrimonio municipal.\nLos derechos causados por la prestación de los servicios que establece el presente artículo, estarán sujetos a condonación total o parcial, siempre y cuando medie la autorización de la autoridad municipal, previo estudio socio-económico.\nCAPÍTULO III\n3 OTROS DERECHOS\nCAPÍTULO IV\n4 ACCESORIOS DE DERECHOS\n01 ACCESORIOS DE DERECHOS\nARTÍCULO 61.- Son los ingresos que se perciben por concepto de recargos, sanciones, gastos de ejecución, indemnizaciones, entre otros, asociados a los derechos, cuando éstos no se cubran oportunamente, de conformidad con lo siguiente:\nI.- Recargos por mora: Cuando no se paguen las contribuciones convenidos, se pagarán recargos por mora a la tasa del 2% mensual.\nII.- Recargos por financiamiento: Cuando se conceda prórroga sean cubiertos en parcialidades, se causarán recargos por financiamiento sobre el saldo insoluto a la tasa del 1.5% mensual.\nIII.- Sanciones: Las multas derivadas del incumplimiento en el pago de contribuciones en la forma, fecha y términos que respectivas.\nIV.- Gastos de Ejecución: Cuando las autoridades fiscales la recuperación de los créditos fiscales que correspondan, se estará a lo establecido en el \"Capítulo VIII. De los\nGastos de Ejecución\" de la Ley de Hacienda Municipal del\nEstado de Baja California.\nV.- Otros: Todos aquellos que se encuentren asociados o establecidos en las leyes fiscales.\nCAPÍTULO V\n5 DERECHOS NO COMPRENDIDOS EN LA LEY DE INGRESOS VIGENTE CAUSADOS EN\nEJERCICIOS FISCALES ANTERIORES PENDIENTES\nDE LIQUIDACIÓN O PAGO\n01 DERECHOS CAUSADOS EN EJERCICIOS ANTERIORES PENDIENTES DE\nLIQUIDACIÓN O PAGO\nARTÍCULO 62.- Los Derechos no pagados en el ejercicio fiscal en que se causaron se cobrarán como pagos extemporáneos de ejercicios fiscales anteriores, aplicando en cuanto al fondo, las leyes vigentes a la fecha en que se generaron y en cuanto a la forma mediante el procedimiento del Estado de Baja California o en su caso, el procedimiento judicial que corresponda.\nTÍTULO SEXTO\n5 PRODUCTOS\n1 PRODUCTOS\n01 PRODUCTOS\n2 PRODUCTOS NO COMPRENDIDOS EN LA LEY DE INGRESOS VIGENTE, CAUSADOS\n01 PRODUCTOS CAUSADOS EN EJERCICIOS ANTERIORES PENDIENTES DE\nLIQUIDACIÓN O PAGO\nARTÍCULO 63.- Los Productos no pagados en el ejercicio fiscal en que anteriores, aplicando en cuanto al fondo, las leyes vigentes a la fecha del Estado de Baja California o en su caso, el procedimiento judicial que corresponda.\nTÍTULO SÉPTIMO\n6 APROVECHAMIENTOS\nCAPÍTULO I\n1 APROVECHAMIENTOS\n01 MULTAS\nARTÍCULO 64.- Las que se contemplan en los reglamentos municipales que resultaren aplicables en las diferentes materias, y las que deriven por el incumplimiento de las disposiciones fiscales, así mismo la autoridad municipal al hacer efectiva la sanción impuesta por las diversas áreas municipales, por violaciones a los reglamentos aplicables, y al hacer efectivas dichas infracciones mediante el procedimiento administrativo de ejecución podrá apegarse a lo establecido por el Artículo 88 de la Ley de Hacienda Municipal del\nEstado de Baja California.\n02 REINTEGROS E INDEMNIZACIONES\n03 DONACIONES, CESIONES, HERENCIAS Y LEGADOS\nA FAVOR DEL MUNICIPIO\n04 OTROS APROVECHAMIENTOS\nCAPÍTULO II\n2 APROVECHAMIENTOS PATRIMONIALES\n01 EXPLOTACIÓN O ARRENDAMIENTO DE BIENES MUEBLES E INMUEBLES\nPROPIEDAD DEL GOBIERNO MUNICIPAL\nARTÍCULO 65.- La renta de los bienes inmuebles de dominio público y privado propiedad del Municipio de San Felipe, así como los que tiene derecho a subarrendar, serán fijados en cada caso por Oficialía Mayor, dependiendo de la superficie ocupada y de su localización, cuyo pago deberá efectuarse dentro de los primeros cinco días de cada mes.\n02 ENAJENACIÓN DE BIENES MUEBLES E INMUEBLES PROPIEDAD DEL\nGOBIERNO MUNICIPAL\nARTÍCULO 66.- El Ayuntamiento de San Felipe podrá disponer de Bienes requieran fortalecer las finanzas Municipal, para ponerlos en venta suscripción de contrato, mismo que no podrá exceder los 5 años, con el financiamiento que para tales efectos proponga al Ayuntamiento la\nOficialía Mayor Municipal.\nLos valores de los Bienes Muebles e Inmuebles patrimoniales serán aquellos que para tales efectos establezca la Comisión Estatal de\nAvalúos o en su defecto el valor fiscal, cuando el primero resulte inferior al segundo.\n03 OTRAS ACTIVIDADES DEL GOBIERNO MUNICIPAL QUE NO CORRESPONDAN A\nSUS FUNCIONES PROPIAS DE DERECHO PÚBLICO\nARTÍCULO 67.- Las personas físicas que hagan uso de los sanitarios públicos propiedad del Municipio de San Felipe, ubicados en Avenida\nMalecón de San Felipe, pagarán una tarifa de $10.00 M.N. por usuario en el uso de sanitario y de $15.00 M.N. por uso de regaderas por usuario.\n04 DEL PISO\nARTÍCULO 68.- Las personas físicas o morales que previa autorización de la autoridad municipal correspondiente hagan uso del piso, de instalaciones subterráneas o aéreas en las vías públicas, o en el de actividades comerciales.\nPor construcción de tuberías tendido de cables, fibras ópticas o similares y conducciones aéreas de uso público y privado, sean eléctricas, telefónicas, telecomunicaciones, de transportación de gas domiciliario o industrial y otros, pagarán por metro lineal:\nUNIDAD DE MEDIDA Y\nACTUALIZACIÓN VIGENTE\nI.- Casetas telefónicas, registros para distribuidores telefónicos, sobre el nivel de banqueta, diariamente, por cada una; debiendo realizar el pago anual dentro de los primeros 60 días del ejercicio fiscal.................................. 1.21 veces\nII.- Instalación de postes o similar en vía pública.... 1.21 veces\nIII.- Instalaciones de infraestructura, por metro lineal, anualmente:\na).- Líneas subterráneas de:\n1).- Telefonía............................... 0.10 veces\n2).- Transmisión de datos.................... 0.10 veces\n3).- Transmisión de señales de televisión por cable................................... 0.10 veces\n4).- Distribución de gas..................... 0.10 veces\n5).- Energía eléctrica....................... 0.10 veces\nb).- Líneas visibles o aéreas de:\n1).- Telefonía............................... 0.90 veces\n2).- Transmisión de datos.................... 0.90 veces\n3).- Transmisión de señales de televisión por cable................................... 0.90 veces\n4).- Energía eléctrica....................... 0.90 veces\nCualquier otra instalación permanente en la vía pública, pagará lo que\nMunicipal.\nPor uso de las vías públicas y/o del equipamiento urbano público y/o de las áreas verdes municipales, para la explotación de la imagen urbana, pagarán por estructura o instalación:\na).- Anuncio publicitario o propaganda; debiendo realizar el pago anual dentro de los primeros 60 días del ejercicio fiscal....... 60.00 veces\n05 BIENES MOSTRENCOS no tener dueño aparente, de acuerdo al procedimiento establecido en el cumplido el plazo fijado para su reclamo, si no aparece el dueño legítimo, el Municipio percibirá ingresos por concepto de la venta de bienes mostrencos en subasta pública tales como:\nI.- Bienes muebles\nII.- Otros\nCAPÍTULO III\n3 ACCESORIOS DE APROVECHAMIENTOS\n01 ACCESORIOS DE APROVECHAMIENTOS\nARTÍCULO 69.- Son los ingresos que se perciben por concepto de recargos, sanciones, gastos de ejecución, indemnizaciones, entre otros, asociados a los aprovechamientos, cuando éstos no se cubran oportunamente, de conformidad con lo siguiente:\nI.- Recargos por mora: Cuando no se paguen las contribuciones dentro de los plazos señalados en las disposiciones fiscales o no se cubran las parcialidades en los plazos convenidos, se pagarán recargos por mora a la tasa del 2% mensual.\nII.- Recargos por financiamiento: Cuando se conceda prórroga sean cubiertos en parcialidades, se causarán recargos por financiamiento sobre el saldo insoluto a la tasa del 1.5% mensual.\nIII.- Sanciones: Las multas derivadas del incumplimiento en el pago de contribuciones en la forma, fecha y términos que respectivas.\nIV.- Gastos de Ejecución: Cuando las autoridades fiscales la recuperación de los créditos fiscales que correspondan, se estará a lo establecido en el \"Capítulo VIII. De los\nGastos de Ejecución\" de la Ley de Hacienda Municipal del\nEstado de Baja California.\nV.- Otros: Todos aquellos que se encuentren asociados o establecidos en las leyes fiscales.\nCAPÍTULO IV\n9 APROVECHAMIENTOS NO COMPRENDIDOS EN LA LEY DE INGRESOS VIGENTE,\nCAUSADOS EN EJERCICIOS FISCALES ANTERIORES PENDIENTES DE LIQUIDACIÓN\nO PAGO\n01 APROVECHAMIENTOS CAUSADOS EN EJERCICIOS ANTERIORES\nPENDIENTES DE LIQUIDACIÓN O PAGO\nARTÍCULO 70.- Los Aprovechamientos no pagados en el ejercicio fiscal en que se causaron se cobrarán como pagos extemporáneos de ejercicios fiscales anteriores, aplicando en cuanto al fondo, las leyes vigentes a la fecha en que se generaron y en cuanto a la forma mediante el procedimiento administrativo de ejecución que establece la Ley de\nHacienda Municipal del Estado de Baja California o en su caso, el procedimiento judicial que corresponda.\nTÍTULO OCTAVO\n7 INGRESOS POR VENTA DE BIENES, PRESTACIÓN DE SERVICIOS\nY OTROS INGRESOS\nCAPÍTULO I\n1 INGRESOS POR VENTA DE BIENES Y PRESTACIÓN DE SERVICIOS\nDE INSTITUCIONES PÚBLICAS DE SEGURIDAD SOCIAL.\n2 INGRESOS POR VENTA DE BIENES Y PRESTACIÓN DE SERVICIOS\nDE EMPRESAS PRODUCTIVAS DEL ESTADO.\n3 INGRESOS POR VENTA DE BIENES Y PRESTACIÓN DE SERVICIOS\nDE ENTIDADES PARAESTATALES Y FIDEICOMISOS NO\nEMPRESARIALES Y NO FINANCIEROS.\n4 INGRESOS POR VENTA DE BIENES Y PRESTACIÓN DE SERVICIOS\nDE ENTIDADES PARAESTATALES EMPRESARIALES NO\nFINANCIERAS CON PARTICIPACIÓN ESTATAL MAYORITARIA.\n5 INGRESOS POR VENTA DE BIENES Y PRESTACIÓN DE SERVICIOS\nMONETARIAS CON PARTICIPACIÓN ESTATAL MAYORITARIA.\n6 INGRESOS POR VENTA DE BIENES Y PRESTACIÓN DE SERVICIOS\nNO MONETARIAS CON PARTICIPACIÓN ESTATAL MAYORITARIA.\n7 INGRESOS POR VENTA DE BIENES Y PRESTACIÓN DE SERVICIOS\nDE FIDEICOMISOS FINANCIEROS PÚBLICOS CON PARTICIPACIÓN\nESTATAL MAYORITARIA.\n8 INGRESOS POR VENTA DE BIENES Y PRESTACIÓN DE SERVICIOS\nDE LOS PODERES LEGISLATIVO Y JUDICIAL, Y DE LOS\nÓRGANOS AUTÓNOMOS.\n9 OTROS INGRESOS\nTÍTULO NOVENO\n8 PARTICIPACIONES, APORTACIONES, CONVENIOS, INCENTIVOS DERIVADOS DE\nCAPÍTULO I\n1 PARTICIPACIONES\n01 PARTICIPACIONES DE CONTRIBUCIONES FEDERALES\n02 PARTICIPACIONES DE CONTRIBUCIONES ESTATALES\nObras.\nII.- Por Otros Impuestos o Ingresos del Estado, que señalen las\nLeyes, Acuerdos o Convenios que las Regulen.\nCAPÍTULO II\n2 APORTACIONES\n01 APORTACIONES FEDERALES DEL RAMO 33\nI.- Fondo de Aportaciones para la Infraestructura Social Municipal.\nII.- Fondo de Aportaciones para el Fortalecimiento de los Municipios.\n02 OTRAS APORTACIONES\nI.- Fondo de Desarrollo Regional Sustentable de Estados y\nMunicipios Mineros.\nCAPÍTULO III\n3 CONVENIOS\n01 OTROS INGRESOS POR CONVENIOS FEDERALES\n02 OTROS INGRESOS POR CONVENIOS ESTATALES\nI.- Convenio de Colaboración Administrativa en Materia Fiscal\nFederal que celebran el Gobierno Federal por conducto de la Secretaría de Hacienda y Crédito Público y el Gobierno del Estado de Baja California y el Ayuntamiento de San Felipe.\nII.- Convenio de Colaboración para la Administración de Multas\nBaja California y el Ayuntamiento de San Felipe.\n4 INCENTIVOS DERIVADOS DE LA COLABORACIÓN FISCAL\n5 FONDOS DISTINTOS DE APORTACIONES\nTÍTULO DÉCIMO\n9 TRANSFERENCIAS, ASIGNACIONES, SUBSIDIOS Y SUBVENCIONES,\nY PENSIONES Y JUBILACIONES\nCAPÍTULO I\n1 TRANSFERENCIAS Y ASIGNACIONES\n2 SUBSIDIOS Y SUBVENCIONES\n01 SUBSIDIOS Y SUBVENCIONES\n3 PENSIONES Y JUBILACIONES\n4 TRANSFERENCIAS DEL FONDO MEXICANO DEL PETRÓLEO PARA LA\nESTABILIZACIÓN Y DESAROLLO\nTÍTULO DECIMOPRIMERO\n10 INGRESOS DERIVADOS DE FINANCIAMIENTOS\nCAPÍTULO I\n1 ENDEUDAMIENTO INTERNO\n1.- Créditos otorgados al municipio\nDeuda Pública.\nLa Deuda Pública Municipal, se constituye por las obligaciones derivadas de las operaciones de financiamiento.\nCAPÍTULO II\n2 ENDEUDAMIENTO EXTERNO\n1.- Otros créditos otorgados al municipio.\n3 FINANCIAMIENTO INTERNO\nTÍTULO DECIMOSEGUNDO\nDISPOSICIONES GENERALES\nARTÍCULO 71.- Ninguna contribución podrá recaudarse si no está prevista en la presente Ley de Ingresos Municipal.\nARTÍCULO 72.- Las participaciones de impuestos federales y estatales que perciba el Municipio, serán las que fijen las Leyes, Convenios\nFederales y Estatales respectivas.\nARTÍCULO 73.- La validez de las licencias así como permisos otorgados por el Municipio, está condicionada al exacto cumplimiento de los ordenamientos legales aplicables.\nARTÍCULO 74.- Las cuotas de Impuestos y Derechos, serán proporcionales en los casos de apertura, siempre que el período sea menor de seis meses, a excepción de los correspondientes a los contribuyentes eventuales.\nARTÍCULO 75.- Los gravámenes que prevé la presente Ley, no serán motivo de exención, condonación o modificación por parte de las autoridades municipales, salvo por autorización expresa del Congreso del Estado, con excepción de los Recargos, que podrán condonarse total o parcialmente, conforme al Artículo 110 de la Ley de Hacienda Municipal del Estado de Baja California.\nARTÍCULO 76.- Se entiende como fecha de iniciación de operaciones de las personas físicas y de las unidades económicas, aquella en que se efectúa la apertura del negocio o en la que se obtenga el primer ingreso. En caso de personas morales, el día de su constitución, aun cuando ésta sea anterior a la fecha de apertura del negocio o a la fecha en que se obtenga el primer ingreso.\nARTÍCULO 77.- Las personas físicas, morales o unidades económicas, que para expender sus mercancías lo hagan a través de vendedores ambulantes, agentes de venta, comisionistas, repartidores, concesionarios ambulantes o cualquier otro nombre que se le dé al expendedor, serán solidariamente responsables del pago de los\nImpuestos, Derechos y/o Multas que se originen con motivo de las actividades que ejerzan para lo cual se constituirán en retenedores de los Créditos Fiscales, debiendo enterarlos a la Tesorería Municipal, dentro de los plazos que fijen las Leyes Fiscales.\nARTÍCULO 78.- Son cuotas de cooperación los ingresos que perciba\nUrbanización Municipal, a cargo de los propietarios y/o poseedores de urbanización, de acuerdo a las bases y procedimientos previstos en la\nLey de Urbanización del Estado de Baja California.\nARTÍCULO 79.- El cheque recibido por las autoridades fiscales que sea presentado en tiempo y no sea pagado, dará lugar al cobro del monto éste, y se exigirá independientemente de los demás conceptos a que se refiere este artículo. Para tal efecto, la Tesorería Municipal requerirá al librador del cheque para que, dentro de un plazo de tres días, efectúe el pago junto con la mencionada indemnización del 20%, o bien, acredite fehacientemente, con las pruebas documentales procedentes, que se realizó el pago o que dicho pago no se realizó por causas exclusivamente imputables a la institución de crédito. cualquiera de los extremos antes señalados, la autoridad fiscal requerirá y cobrará el monto del cheque, la indemnización mencionada y los demás accesorios que correspondan, mediante el procedimiento administrativo de ejecución, sin perjuicio de la responsabilidad que en su caso procediere.\nARTÍCULO 80.- Cuando se establezca un plazo específico para el pago de un derecho o impuesto, ya sea en esta ley o en otra disposición normativa de la cual derivaren aquellos, vencido este término se causara un recargo económico independientemente de las sanciones administrativas a que hubiere lugar.\nLas dudas y/o aclaraciones que pudieran presentarse con relación a los términos, plazos, condiciones o formas, en las que deban de cumplirse las contribuciones previstas en esta ley, se resolverán, por la autoridad administrativa en lo que resultare aplicable.\nARTÍCULO PRIMERO.- La presente Ley entrará en vigor el día primero de enero del año dos mil veinticinco.\nARTÍCULO SEGUNDO.- Para las contribuciones previstas en esta Ley y en lo que resulte aplicable, se reconocerán los efectos de los reglamentos, acuerdos, circulares planes, programas y demás normatividad que rige dichas contribuciones, que hubieren sido emitidos por las autoridades del Ayuntamiento de Mexicali, Baja\nCalifornia o del Ayuntamiento de Ensenada, Baja California, en ejercicio de sus atribuciones y ajustados a la legalidad, hasta en tanto se emitan los propios por el Ayuntamiento de San Felipe y/o sus autoridades.\nARTÍCULO TERCERO.- Para las contribuciones previstas en esta Ley y en lo que resulte aplicable, se reconocerán los efectos de los convenios de colaboración y/o coordinación, actos, acuerdos y demás instrumentos que hubieren sido celebrados por el Ayuntamiento de Mexicali, Baja\nCalifornia o el Ayuntamiento de Ensenada, Baja California, con motivo de las mismas, hasta en tanto se formalice lo propio por el Ayuntamiento de San Felipe; siempre y cuando estén ajustados a la legalidad.\nARTÍCULO CUARTO.- Los actos que se hubieren suscrito entre contribuyentes y/o particulares comprendidos dentro de la demarcación territorial del Municipio de San Felipe, Baja California, y/o autoridades del Municipio de Mexicali, Baja California y/o autoridades del Municipio de Ensenada, Baja California, se reconocerán sus efectos, condiciones y alcances, en el entendido de que el cobro de por las autoridades del Municipio de San Felipe, conforme a la legislación que les resultare aplicables al momento de su generación, las que necesariamente deberán quedar a favor del mismo; siempre y cuando estén ajustados a la legalidad.\nARTÍCULO QUINTO.- La Unidad de medida y actualización aplicable en todos los conceptos que marca la presente Ley, será la última publicada en el Diario Oficial de la Federación.\nARTÍCULO SEXTO.- Para los efectos de la revalidación de permisos y licencias, así como sus prórrogas, las autoridades del Municipio de\nSan Felipe, Baja California, tomarán en consideración el registro que se hubiere obtenido anteriormente y se cobrará conforme lo establecido en esta Ley.\nARTÍCULO SÉPTIMO.- Los adeudos de ejercicios anteriores a cargo de los contribuyentes por créditos fiscales correspondientes a la demarcación territorial del Municipio de San Felipe, Baja California, generados con anterioridad a la entrada en vigor de la presente Ley, deberán ingresarse a la Tesorería del Ayuntamiento de San Felipe, Baja\nCalifornia.\nARTÍCULO OCTAVO.- Las consecuencias de los actos que sean ventilados ante autoridades judiciales o administrativas, relacionados con la aplicación de las anteriores Leyes de Ingresos del Municipio de\nMexicali, Baja California o las Leyes de Ingresos del Municipio de\nEnsenada, Baja California, que guarden relación con la demarcación territorial del Municipio de San Felipe, Baja California, deberán correr a cargo de este último.\nARTÍCULO NOVENO.- Los actos judiciales o administrativos que se autoridades del Municipio de Mexicali, Baja California o del Municipio de Ensenada, Baja California, así como los adeudos que se encontraren pendientes de pago por parte de dichas autoridades, que estén\nFelipe, Baja California, seguirán siendo responsabilidad de aquellos, según corresponda, hasta su conclusión y/o pago.\nARTÍCULO DÉCIMO.- La Tesorería Municipal proporcionará a las sociedades las Sociedades de Información Crediticia, la información de los establecen.\nARTÍCULO DÉCIMO PRIMERO.- En caso de que durante el presente ejercicio fiscal, las áreas a que se refiere esta Ley, sufrieran alguna modificación en sus funciones o cambiaran su denominación, los servicios previstos para ser prestados por las mismas, se entenderán por referidos y prestados por las que las sustituyan, dando lugar al pago de los derechos que señala ésta.\nARTÍCULO DÉCIMO SEGUNDO.- Los contribuyentes que en los meses de enero y febrero opten por pagar en una sola exhibición las cuotas fijas mensuales correspondientes al ejercicio fiscal 2025, por el Derecho del Servicio de Alumbrado Público que se contempla en el Artículo 18 de esta Ley, obtendrán un descuento equivalente al 10% sobre el monto total a pagar. Este beneficio de pronto pago solo podrá hacerse valer en las oficinas recaudadoras municipales.\nARTÍCULO DÉCIMO TERCERO.- Los pensionados, jubilados, personas mayores de sesenta años de edad, personas con discapacidad o que cuenten con familiar directo con discapacidad bajo su dependencia económica, pescadoras ribereñas y madres jefas de familia, que acrediten esta condición con identificación o documentación oficial expedida por\nInstitución Pública, obtendrán un descuento equivalente al 20% sobre el pago mensual del Derecho del Servicio de Alumbrado Público que se contempla en el Artículo 18 de esta Ley y únicamente será aplicable sobre uno de los bienes inmuebles propiedad o en posesión del contribuyente.\nEste beneficio solo podrá hacerse valer en las oficinas recaudadoras municipales, no podrá acumularse con otros beneficios como el de pronto pago. Asimismo, el contribuyente podrá optar por gozar de este servicio.\nARTÍCULO DÉCIMO CUARTO.- Se condona el 100% del cobro del derecho establecido en la fracción IV, del Artículo 41 de la presente Ley de o adosados pintados no luminosos, que cuenten con un solo anuncio de hasta 3 m², construidos en propiedad privada, comprendidos desde el ejercicio fiscal de 2021 y años anteriores, siempre y cuando cubran los derechos correspondientes a los ejercicios fiscales de 2022, 2023, 2024 y 2025.\nARTÍCULO DÉCIMO QUINTO.- Serán homogéneos en su valor catastral, los e industriales y que sirvan o se utilicen para los mismos fines, sin importar las características del mismo.\nARTÍCULO DÉCIMO SEXTO.- La presente Ley Ingresos se encontrará disponible en el Portal de Internet del Gobierno Municipal.\nARTÍCULO DÉCIMO SÉPTIMO.- Para efectos de esta Ley, se considera como:\n− ZONA URBANA: Las colonias y fraccionamientos que se encuentran dentro del límite de centro de población del municipio de San Felipe, todos los campos turísticos ubicados en la zona norte y los campos ubicados en la zona sur hasta entroncar con rancho punta estrella, desarrollos inmobiliarios, turísticos e industriales los poblados y determinadas zonas del ejido plan nacional agrario, todos siempre que cuenten con acciones de urbanización que se encuentren dentro del polígono del centro de población de San Felipe Baja California.\n− ZONA SUB URBANA: Las que se encuentren dentro y/o al límite de la zona urbana del centro de población que no han recibido acción de urbanización, pero es factible de contar con ello.\n− ZONA RURAL: Las correspondientes a los Ejidos del Municipio de San\nFelipe Baja California, incluidos el Ejido Plan Nacional Agrario, Ejido Delicias, Ejido Matomi, Ejido Hermenegildo Galeana, así como las colonias, fraccionamientos y comunidades que no han recibido acción de urbanización.\n− ZONA TURÍSTICA: Las zonas costeras del Mar de Cortés y/o Golfo de\nCalifornia de Norte a Sur, iniciando en cerro el moreno, campo turístico Villas del Cortes, malecón y bahía de San Felipe hasta entroncar al sur con los límites del Municipio de San Quintín, zonas arqueológicas, zona cerril de la Sierra San Pedro Mártir colindante con el municipio de Ensenada.\n− ZONA DE FESTEJOS PÚBLICOS MUNICIPALES: Parques públicos, vía pública, unidades deportivas, estacionamientos municipales, públicos municipales.\n− ZONA INDUSTRIAL: Las que desarrollen actividades de la industria minera, generación de energías renovables o de cualquier tipo, las zonas donde operan fábricas de cualquier tipo y giro, cuyas dimensiones para su funcionamiento operativo exceda de 1,500 m2 de constricción.\n− ZONA SUR: Se considera a partir del rancho punta estrella, hasta la colindancia y/o límite de Ejido Hermenegildo Galeana.\n− ZONA COMERCIAL: Las que desarrollen actividades comerciales, contempladas en esta ley como corredores comerciales, distintos de la zona turística.\n− COMERCIO PEQUEÑO: Curios, comercios de 4X4 mts, los Food Truck o carretas.\n− CURIOS: Coloquialmente conocidos en la comunidad a los locales que comercian con artesanías mexicanas y curiosidades alusivas al puerto.\nARTÍCULO DÉCIMO OCTAVO.- En la aplicación de la sobre tasa en apoyo al Fomento Deportivo y Educacional, establecida en el artículo 2 de esta Ley, se otorgarán los descuentos siguientes:\nI.- Descuento del 1.52 al millar de la sobretasa, respecto a las tasas establecidas en las fracciones VI, XII, XIII excepto los incisos a) y b) y la fracción XIV.\nII.- Descuento del 1.04 al millar de la sobretasa, respecto a las fracciones III, IV, V, IX, X, XI, XIII únicamente los incisos a) y\nb).\nIII.- Descuento del 0.56 al millar de la sobretasa, respecto a las fracciones I y II\nARTÍCULO DÉCIMO NOVENO.- Se exenta a las personas físicas y morales inscritas en el Programa Estatal de Vivienda 2022-2027, del pago de derechos que se causen por; factibilidades, dictámenes, certificados, autorizaciones, licencias y en general, por trámites relacionados con la construcción de vivienda social, exclusivamente para los proyectos la Secretaría de Infraestructura, Desarrollo Urbano y Reordenación\nTerritorial (SIDURT), y se lleven a cabo en términos de los\nVivienda publicado en el Periódico Oficial del Estado en fecha 21 de la Secretaría de Desarrollo Agrario, Territorial y Urbano (SEDATU), Instituto Nacional del Suelo Sustentable (INSUS), Comisión Nacional de Vivienda (CONAVI), Instituto del Fondo Nacional de la Vivienda para los Trabajadores (INFONAVIT), Instituto de Seguridad y Servicios\nSociales de los Trabajadores del Estado (ISSSTE) y el Fondo de la\nTrabajadores del Estado (FOVISSSTE), en conjunto con la Entidad\nFederativa y sus Municipios.\nLos derechos a exentar se enuncian a continuación:\nI. Factibilidad de uso de suelo\nII. Certificado de libertad de gravamen\nIII. Dictamen de uso del suelo\nIV. Manifestación de impacto ambiental\nV. Movimiento de tierras\nVI. Deslinde catastral\nVII. Licencia de construcción\nVIII. Régimen de Propiedad en Condominio\nIX. Licencia de Fraccionamiento\nX. Certificado de numero oficial\nXI. Constancia de obra terminada\nXII. Cambio de propietario\nXIII. Impuesto sobre adquisición de bienes inmuebles\nArtículo Transitorio Reformado a los veinte días del mes de diciembre del dos mil veinticuatro.\nC. EVELYN SÁNCHEZ SÁNCHEZ\nDIPUTADA PRESIDENTA\n(RÚBRICA)\nC. MICHELLE ALEJANDRA TEJEDA MEDINA\nDIPUTADA SECRETARIA\n(RÚBRICA)\nDE CONFORMIDAD CON LO DISPUESTO POR LA FRACCIÓN I DEL ARTÍCULO 49 DE LA\nIMPRÍMASE Y PUBLÍQUESE.\nMEXICALI, BAJA CALIFORNIA, A LOS VEINTISÉIS DÍAS DEL MES DE DICIEMBRE DEL AÑO\nDOS MIL VEINTICUATRO.\nMARINA DEL PILAR ÁVILA OLMEDA\nGOBERNADORA DEL ESTADO\nDE BAJA CALIFORNIA\n(RÚBRICA)\nALFREDO ÁLVAREZ CÁRDENAS\nSECRETARIO GENERAL DE GOBIERNO\nDEL ESTADO DE BAJA CALIFORNIA\n(RÚBRICA)\nFELIPE, BAJA CALIFORNIA PARA EL EJERCICIO FISCAL DEL 2025, PUBLICADA EN EL\nPERIÓDICO OFICIAL DEL ESTADO DE BAJA CALIFORNIA NÚMERO 66, SECCIÓN VIII,\nINVOLUNTARIO EN LA IMPRESIÓN DEL DOCUMENTO PUBLICADO, SE DESFASARON LOS\nMÁRGENES EN ALGUNAS CANTIDADES, SUSCITADO POR CAUSAS INHERENTES A LA\nCONVERSIÓN DEL FORMATO “DOCX” A “PDF” DE DICHO INSTRUMENTO, ASÍ COMO\nOTROS ERRORES DE IMPRESIÓN. FE DE ERRATAS PUBLICADA EN EL PERIÓDICO\nPOR LA H. XXV LEGISLATURA; SIENDO GOBERNADORA CONSTITUCIONAL LA C. MARINA\nDEL PULAR ÁVILA OLMEDA 2021-2027.\nATENTAMENTE\nMEXICALI, BAJA CALIFORNIA, A 30 DE ENERO DE 2025\nDIP. EVELYN SÁNCHEZ SÁNCHEZ\nPRESIDENTA\n(RÚBRICA)\nDIP. MICHELLE ALEJANDRA TEJEDA MEDINA\nSECRETARIA\n(RÚBRICA)\nARTÍCULO ÚNICO TRANSITORIO DEL DECRETO No. 72, POR EL QUE SE\nAPRUEBA LA REFORMA AL ARTÍCULO DÉCIMO NOVENO TRANSITORIO DE LA LEY\nDE INGRESOS DEL MUNICIPIO DE SAN FELIPE, BAJA CALIFORNIA PARA EL\nEJERCICIO FISCAL 2025; PUBLICADO EN EL PERIÓDICO OFICIAL No. 22, ÍNDICE,\nDE FECHA 11 DE ABRIL DE 2025, TOMO CXXXII; EXPEDIDO POR LA H. XXV\nLEGISLATURA; SIENDO GOBERNADORA CONSTITUCIONAL LA C. MARINA DEL\nPILAR ÁVILA OLMEDA 2021-2027.\nTRANSITORIOS\nPRIMERO.- La presente reforma entrará en vigor al día siguiente de su publicación en el\nPeriódico Oficial del Estado de Baja California.\nSEGUNDO.- Publíquese en el Periódico Oficial del Estado de Baja California y en la\nGaceta Municipal Órgano de Difusión de Ayuntamiento de San Felipe, Baja California, para el conocimiento de los habitantes del Municipio.\nDADO en Sesión Ordinaria de la XXV Legislatura en la Ciudad de Tijuana, B.C., a los veintisiete días del mes de marzo del año dos mil veinticinco.\nDIP. EVELYN SÁNCHEZ SÁNCHEZ\nPRESIDENTA\n(RÚBICA)\nDIP. MICHELLE ALEJANDRA TEJEDA MEDINA\nSECRETARIA\n(RÚBICA)\nDE BAJA CALIFORNIA, IMPRÍMASE Y PUBLÍQUESE.\nMEXICALI, BAJA CALIFORNIA, A LOS 31 DÍAS DEL MES DE MARZO DEL AÑO\nDOS MIL VEINTICINCO.\nMARINA DEL PILAR ÁVILA OLMEDA\nGOBERNADORA DEL ESTADO\nDE BAJA CALIFORNIA\n(RÚBRICA)\nALFREDO ÁLVAREZ CÁRDENAS\nSECRETARIO GENERAL DE GOBIERNO\nDEL ESTADO DE BAJA CALIFORNIA\n(RÚBRICA)",
  "ordenamiento": "REGLAMENTO",
  "jurisdiccion": "BAJA CALIFORNIA",
  "fuente_oficial": "Periódico Oficial",
  "FECHA PER OFIC": "2025/04/11",
  "ESTATUS": "VIGENTE",
  "TOMO": "TOMO_II",
  "URL": "https://www.congresobc.gob.mx/Documentos/ProcesoParlamentario/Leyes/TOMO_II/20250411_LEYINGRESOSANFELIPE2025.PDF",
  "es_escaneado": false,
  "tiene_tablas": false,
  "materia": [
    "financiero",
    "fiscal",
    "económico"
  ]
}