{
  "titulo": "Reglamento de Peritas, Peritos y Auxiliares de la Administración de Justicia del Estado de Baja Cali",
  "Contenido": "JUSTICIA DEL ESTADO DE BAJA CALIFORNIA\nTÍTULO PRIMERO\nCAPÍTULO PRIMERO\nDISPOSICIONES GENERALES\nArtículo 1. El presente reglamento es de observancia obligatoria y tiene por objeto regular la actividad que realicen peritas, peritos y auxiliares que presten servicios en la administración de justicia del Estado de Baja California.\nArtículo 2. Para los efectos del presente Reglamento se entenderá por:\nI. Auxiliar: Auxiliar de la administración de justicia del Estado de Baja California;\nII. Consejo: Consejo de Administración del Poder Judicial del Estado de Baja California;\nIII. Constancia: Constancia de pertenencia al padrón de peritas, peritos y auxiliares de la administración de justicia del Estado de Baja California;\nV. Coordinación: Coordinación de peritas y peritos del Consejo de Administración del Poder\nJudicial del Estado de Baja California;\nVII. Padrón: Lista en la que se establecen las peritas, peritos y auxiliares de la administración de justicia del Estado de Baja California en los términos previstos por el artículo 231 y 232 de la Ley\nVIII. Perita y Perito: Persona pertenecientes al padrón de peritas, peritos y auxiliares de la administración de justicia del Estado de Baja California;\nX. Reglamento: Reglamento de peritas, peritos y auxiliares de la administración de justicia del\nEstado de Baja California.\nXI. Unidad de Medida y Actualización (UMA): Es la referencia económica en pesos para determinar la cuantía del pago de las obligaciones y supuestos previstos en las leyes federales, de las entidades federativas, así como en las disposiciones jurídicas que emanen de todas las anteriores.\nCAPÍTULO SEGUNDO\nATRIBUCIONES DEL CONSEJO\nArtículo 3. La regulación y vigilancia del desempeño de servicios periciales así como del desempeño de los auxiliares en el Poder Judicial, estará a cargo de la Coordinación.\nArtículo 4. Corresponde a la Coordinación lo siguiente:\nI. Vigilar el cumplimiento exacto del presente Reglamento;\nII. Presentar al Consejo la propuesta de convocatoria para formar parte del padrón de peritas, peritos y auxiliares, para su aprobación, en su caso;\nIII. Recibir las solicitudes de las y los interesados a integrarse al Padrón;\nIV. Auxiliar al Pleno del Consejo en la elaboración y actualización del Padrón, así como la publicación anual de la lista que contenga los nombres, direcciones, especialidad, datos profesionales, y partido judicial para el cual estará autorizado, cada uno de los integrantes de ese padrón;\nV. Auxiliar al Pleno del Consejo en la emisión de la constancia de pertenencia al padrón de peritas, peritos y auxiliares de la administración de justicia del Estado de Baja California;\nVI. Recibir las quejas en contra de peritas, peritos y auxiliares, y verificar que la tramitación del\nReglamento;\nVII. Emitir la opinión correspondiente que se refiere el artículo 33 fracción VI del presente\nReglamento;\nVIII. Autorizar que una perita, perito o auxiliar se desempeñe con ese carácter en otro partido judicial diverso al que solicitó, siempre que el Juez o la Jueza lo pida por escrito fundando y motivando la petición, y en dicho partido judicial no se cuente con persona certificada para tales efectos, o bien, que habiéndolos se encuentren impedidos;\nIX. Suscribir convenios de colaboración con instituciones académicas, científicas o sociales, y\nX. Las demás que confieran otras disposiciones legales aplicables o necesarias para el mejor desempeño de su función.\nArtículo 5. Para los casos no previstos en la Ley Orgánica y este Reglamento se aplicarán los\nAcuerdos que expida el Consejo.\nTÍTULO SEGUNDO\nDEL PADRÓN\nCAPÍTULO PRIMERO\nDEL INGRESO AL PADRÓN\nArtículo 6. El Poder Judicial contará con un padrón de las personas certificadas por el Consejo como versadas en los diversos ramos del conocimiento humano, de reconocida solvencia moral, del cual deberán designar las autoridades judiciales a las peritas, peritos y auxiliares, a fin de que se desempeñen en los cargos previstos.\nSólo en el caso de que no existiera Padrón, o que las personas indicadas en él estuvieren impedidas para ejercer el cargo, las personas juzgadoras podrán nombrarlos libremente, preferentemente de entre asociaciones, colegios de profesionistas o instituciones académicas.\nArtículo 7. El Consejo a través de la Coordinación publicará en el mes de octubre de cada año convocatoria dirigida a las y los interesados en formar parte del Padrón, la cual se publicará por tres ocasiones cuando menos, en el Boletín Judicial del Estado de Baja California.\nPara ingresar al Padrón, las personas interesadas deberán presentar una solicitud ante la\nCoordinación acompañada de los documentos que acrediten el cumplimiento de los requisitos que correspondan a cada categoría, de conformidad a lo dispuesto en la Ley, este categoría, de conformidad a lo dispuesto en la Ley, este Reglamento y la convocatoria que al efecto emita la Coordinación previa aprobación del Consejo. localizados, así como las personas autorizadas para oír y recibir notificaciones en su nombre.\nArtículo 8. Son auxiliares de la administración de justicia, las personas de connotada solvencia\nDentro de las y los auxiliares se encuentran los siguientes:\na) Albacea;\nb) Arbitro;\nc) Curador;\nd) Depositario;\ne) Interventor;\nf) Orientador Familiar;\ng) Síndico;\nh) Tutor;\ni) Los demás que determine el Consejo a petición de la Coordinación.\nArtículo 9. Para efecto de este Reglamento, las peritas y peritos se clasifican en:\nI. Peritas y peritos valuadores: son profesionistas científicos, técnicos, o prácticos que en los términos y requisitos de este Reglamento, cuentan con los conocimientos necesarios para emitir dictámenes técnicos de valor en los siguientes ramos:\na) Bienes inmuebles.\n1. Urbanos.\n2. Rústicos.\nb) Bienes muebles.\n1. Bienes agropecuarios.\n2. Bienes industriales; maquinaria, y equipo.\n3. Alhajas y metales.\n4. Antigüedades y obras de arte.\n5. Vehículos automotores.\n6. Aparatos e instrumentos electrónicos.\n7. Mobiliario y enseres menores.\nc) Servicios.\nLa función de las peritas y peritos valuadores consiste en, expedir avalúos elaborados justificación técnica;\nII. Peritas y peritos dictaminadores: son profesionistas científicos, técnicos o prácticos que, en los términos y requisitos de este Reglamento, cuentan con los conocimientos necesarios en la ciencia, arte, oficio o industria sobre la que verse el asunto acerca del cual se elabore su informe de pericia.\nCon carácter enunciativo, las materias de pericia de los dictaminadores se clasifican en:\n1. Administración.\n2. Agronomía.\n3. Análisis de voz.\n4. Antropología.\n5. Antropometría.\n6. Arquitectura.\n7. Artes en general.\n8. Auditoría.\n9. Audio y video grabación forense.\n10. Balística.\n11. Carpintería.\n12. Ciencias económicas.\n13. Ciencias sociales.\n14. Comercio.\n15. Computación e informática forense.\n16. Contabilidad.\n17. Criminalística de campo.\n18. Criminología.\n19. Dactiloscopía.\n20. Derecho.\n21. Dibujo y planimetría.\n22. Documentoscopía.\n23. Filatelia.\n24. Fotografía forense.\n25. Genética.\n26. Genética forense.\n27. Grafoscopía y Documentología.\n28. Identificación fisonómica.\n29. Incendios y explosiones.\n30. Informática.\n31. Ingeniería.\n32. Ingeniería civil, topografía y arquitectura forense.\n33. Matemáticas.\n34. Mecánica en general.\n35. Medicina del trabajo.\n36. Medicina forense.\n37. Medicina general.\n38. Medicina veterinaria.\n39. Numismática.\n40. Odontología.\n41. Odontología forense.\n42. Poligrafía.\n43. Propiedad intelectual.\n44. Psicología.\n45. Psicología forense.\n46. Psiquiatría.\n47. Psiquiatría forense.\n48. Química.\n49. Química forense.\n50. Radiología.\n51. Retrato hablado.\n52. Reparación del daño (moral y material).\n53. Sociología.\n54. Tránsito terrestre, aéreo, náutico o fluvial.\n55. Las demás que sean necesarias.\nLa función de las y los peritos dictaminadores consiste en la emisión de opiniones fundadas que, expliquen, aclaren, definan o clarifiquen en forma metodológica, técnica, o científica sobre el asunto en el que se solicite su intervención, y\nIII. Peritas y peritos traductores e intérpretes: son profesionistas, técnicos o personas con conocimientos prácticos especializados que, cumpliendo los requisitos previstos en este\nReglamento, tienen la función de traducir o interpretar, de manera fiel, clara y precisa, lo expresado en una lengua, idioma o sistema de comunicación humana, a otra lengua, idioma o sistema distinto, incluyendo aquellos de carácter no verbal.\nLa función de las y los peritos traductores e intérpretes consiste en garantizar la comunicación efectiva y comprensible entre las partes, órganos jurisdiccionales y demás intervinientes en un procedimiento, mediante la conversión de mensajes orales o escritos, preservando su sentido, contenido y contexto. Para ello, deberán abstenerse de alterar, omitir, agregar o modificar la información, asegurando la neutralidad, objetividad y confiabilidad de su intervención.\nArtículo 10. Los requisitos para desempeñarse como perito, perita o auxiliar son los siguientes:\nI. Nacionalidad Mexicana;\nII. Título Profesional que acredite su pericia expedido por Institución autorizada para tales efectos;\nIII. Estar inscritos en el Registro Federal de Contribuyentes y proporcionar sus datos de identificación fiscal;\nIV. Poseer cédula profesional expedida por autoridad legalmente facultada para ello;\nV. Residencia efectiva en el Estado de Baja California por cuando menos el año inmediato anterior de manera ininterrumpida;\nVI. Acreditar contar con buena fama en el concepto público y prestigio profesional;\nVII. No tener antecedentes penales;\nVIII. Acreditar contar con conocimientos y estudios especializados impartidos por Institución oficial, en la materia o ramo que desea desempeñar.\nIX. Pertenecer preferentemente a cualquiera de los Colegios o Asociaciones de profesionistas\nDepartamento de Profesiones del Estado de Baja California.\nX. Comprobar la actualización de sus conocimientos a través, de respaldos académicos o capacitación recibida.\nXI. Pagar el importe que determine la Ley de Ingresos del Estado de Baja California, para el ejercicio fiscal que corresponda, por cada una de las disciplinas que se les autorice.\nXII. Tratándose de peritas y peritos traductores de idiomas, deberá contar con certificado expedido por una institución oficial que haga constar que el interesado cuenta con capacidad como intérprete y no sólo tener conocimiento del idioma de que se trate, salvo acuerdo especial que emita el Consejo cuando a su juicio no existan personas suficientes que reúnan este requisito.\nPara las ramas que conforme a la Ley no se requiere un Título Profesional expedido por autoridad competente, no se exigirán los requisitos indicados en las fracciones II, IV, VIII y IX de este artículo, sin embargo, deberán acreditar tener probada experiencia en el arte, ciencia o técnica de que se trate y buen desempeño en el desarrollo de las actividades inherentes al mismo.\nArtículo 11. El Consejo podrá a través de la Coordinación llevar a cabo las indagaciones que proporcionada, valorar los documentos presentados con la cooperación de instituciones exámenes para corroborar los conocimientos con que se ostentan.\nArtículo 12. La Coordinación analizará el cumplimiento de los requisitos a que se refiere este\nReglamento, y emitirá un dictamen en el que determine la inclusión de la persona aspirante al padrón, y dará cuenta al Pleno del Consejo para su aprobación.\nArtículo 13. Una vez autorizado el padrón, se publicará en el Boletín Judicial del Estado de Baja\nCalifornia. Esta publicación tendrá efectos de notificación a todas las personas que solicitaron su inscripción como peritas y peritos auxiliares.\nArtículo 14. En los casos no previstos, o cuando el Consejo lo estime pertinente, después de publicado el padrón de peritas, peritos y auxiliares, podrá publicarse por única vez en el mes de marzo una lista complementaria, la que contendrá únicamente cambios y precisiones que especialidades, e incluso cambios de domicilios y números telefónicos, no se incluirán nuevos ingresos, salvo en el caso de que no existan peritas, peritos o auxiliares en el cargo correspondiente en el partido judicial que se solicite.\nEl escrito de modificación de datos podrá presentarse desde el día siguiente de la publicación del padrón en el Boletín Judicial del Estado de Baja California hasta el último día hábil de febrero.\nCAPÍTULO SEGUNDO\nCONSTANCIA DE PERTENENCIA AL PADRÓN\nArtículo 15. La duración del cargo como perita, perito o auxiliar será de un año contado del primero de enero al treinta y uno de diciembre, pero podrá terminarse anticipadamente o suspenderse en los casos previstos por este Reglamento.\nArtículo 16. El Consejo a través de la Coordinación, entregará a las peritas, peritos y auxiliares, una constancia de pertenencia al padrón.\nArtículo 17. La constancia a que se refiere el artículo anterior deberá contener las firmas de autorización de la persona titular de la Secretaría General del Consejo y de la persona titular de la Coordinadora, así como la firma y fotografía de la o el interesado.\nAsimismo, deberá incorporar el sello oficial o el Código QR correspondiente, como elementos adicionales de autenticidad, sin los cuales el documento carecerá de validez.\nTÍTULO TERCERO\nDEL DESEMPEÑO DE PERITAS, PERITOS Y AUXILIARES\nCAPÍTULO PRIMERO\nDERECHOS, OBLIGACIONES Y PROHIBICIONES\nArtículo 18. Las peritas, peritos y auxiliares pertenecientes al padrón, tendrán las siguientes obligaciones:\nI. Conservar los requisitos exigidos para su ingreso al padrón;\nII. Realizar personalmente el dictamen, avalúo o actividad que les sea encomendada, en los términos previstos en este Reglamento;\nIII. Emitir avalúos, dictámenes, traducciones o interpretaciones, con estricto apego al conocimiento de la profesión, materia, oficio, arte o técnica en los que se fundamenten y con entera independencia o imparcialidad de la parte a cuyo favor fueren a valuar, dictaminar, traducir o interpretar o de quien en último término cubra sus honorarios;\nIV. Dar cumplimiento a los términos previstos por este Reglamento o los otorgados por las personas juzgadoras para el desarrollo de las actividades que le son encomendadas;\nV. Justificar su negativa a efectuar un dictamen o desempeñar un cargo encomendado, ante la persona juzgadora que conozca del asunto.\nEl Juez o la Jueza que conozca del asunto notificará inmediatamente a la Coordinación en caso de que la perita, perito o auxiliar no justifique a satisfacción de la persona juzgadora su negativa.\nVI. Elaborar, por lo menos, dos veces al año, el servicio social a que se refiere el presente\nReglamento;\nVII. Acudir al Juzgado cuantas veces sea requerido por la persona juzgadora;\nVIII. Guardar secrecía de los asuntos que con motivo de sus actividades tengan conocimiento;\nIX. Acreditar cursos de actualización, incluyendo aquellos con enfoque y perspectiva de género, y\nX. Las demás que dispongan las leyes o el Consejo por conducto de la Coordinación.\nArtículo 19. Las peritas, peritos y auxiliares deberán rendir trimestralmente a la Coordinación un informe detallado y completo que contenga:\nI. El número de dictámenes emitidos;\nII. Juzgado y número de expediente en los cuales rindieron sus peritajes;\nIII. El importe de los honorarios cobrados, y\nIV. Los peritajes que hayan realizado como servicio social, indicando los mismos datos señalados en la fracción II de este artículo para su verificación.\nArtículo 20. Las peritas, peritos y auxiliares tienen derecho a:\nI. Que se les reconozca como inscritos al padrón de peritas, peritos y auxiliares de la administración de justicia mediante la expedición de la constancia respectiva;\nII. Cuando medie causa justificada, solicitar una ampliación del término concedido para rendir dictámenes o efectuar las actividades que le fueron encomendadas, ante el Juez o la Jueza de la causa, quien resolverá sobre la procedencia de la petición;\nIII. Recibir una remuneración por la prestación de su servicio, en términos de lo señalado en este Reglamento y demás disposiciones aplicables, y\nIV. Las demás que les otorguen las leyes.\nArtículo 21. En el caso de que, en algún partido judicial del Estado de Baja California, no existan peritas o peritos en materia o conocimiento específico, se podrán autorizar al efecto, a petición de la persona juzgadora, a alguna o alguno que forme parte del Padrón, en otro partido judicial.\nDe no existir dicha categoría en el padrón se procederá en los términos del artículo 6 del presente Reglamento.\nArtículo 22. Las peritas y peritos practicarán todas las operaciones y experimentos que conforme a su profesión, ciencia, técnica o arte sean necesarios; emitirán por escrito su dictamen y lo ratificarán en diligencia especial cuando la autoridad lo requiera. El dictamen pericial contendrá los requisitos que exigen las normas procedimentales aplicables.\nArtículo 23. Las traducciones a idioma español deberán acompañarse de una certificación que efectúe la Secretaria o Secretario del Consejo o bien, de las personas Delegadas de la\nUnidad Administrativa del Consejo, en la que se precise que la perita o perito traductor se tiene registrada ante la Coordinación.\nCAPÍTULO SEGUNDO\nDE LOS HONORARIOS\nArtículo 24. Las peritas, peritos y auxiliares en sus diferentes especialidades que acepten prestar sus servicios como Auxiliares de la administración de justicia, se ajustarán al cobro de honorarios conforme al siguiente Arancel:\nI. Valuación de bienes muebles e inmuebles:\nUNIDAD DE MEDIDA\nDE ACTUALIZACIÓN\nRANGO DEL VALOR COMERCIAL\nDE HASTA HASTA\n$1 $100,000.00 15\n$100,001.00 $1,000,000.00 30\n$1,000,001.00 $2,000,000.00 45\n$2,000,001.00 $3,000,000.00 60\n$3,000,001.00 $4,000,000.00 75\n$4,000,001.00 $5,000,000.00 90\n$5,000,001.00 $6,000,000.00 105\n$6,000,001.00 En adelante 120\nII. Grafoscopía, documentoscopía y dactiloscopía:\nRANGO DEL VALOR UNIDAD DE MEDIDA Y\nACTUALIZACIÓN\nHasta\n80\nIII. Traducciones, por asistencia ante las autoridades judiciales para traducir declaraciones, de lenguas indígenas o idioma extranjero.\nRANGO DEL VALOR UNIDAD DE MEDIDA Y ACTUALIZACIÓN\nTraducción y asistencia en Hasta 5 por hora audiencias judiciales\nTraducción de documentos Hasta 2, por cuartilla\nIV. Dictámenes en general en cualquier área, disciplina o ciencia, con excepción de los señalados en el artículo subsecuente:\nRANGO DEL VALOR UNIDAD DE MEDIDA Y\nACTUALIZACIÓN\nHasta\nArtículo 25. Las Juezas y Jueces en materia familiar, podrán ordenar la intervención de peritas y peritos del Padrón en las áreas de psicología, trabajo social y psiquiatría, a costa y de común\nIntegral de la Familia de Baja California, quienes ajustarán al cobro de sus honorarios conforme al siguiente Arancel:\nI. Psicología\nRANGO DEL VALOR UNIDAD DE MEDIDA Y\nACTUALIZACIÓN\nHasta\nII. Trabajo Social\nRANGO DEL VALOR UNIDAD DE MEDIDA Y\nACTUALIZACIÓN\nHasta\n70\nIII. Psiquiatría\nRANGO DEL VALOR UNIDAD DE MEDIDA Y\nACTUALIZACIÓN\nHasta\n90\nArtículo 26. En los casos en los que por la naturaleza del servicio, requerimientos técnicos, materiales o complejidad del asunto, se pueda rebasar el límite máximo fijado en este\nReglamento para el monto de honorarios señalados en el artículo anterior, la perita, perito o auxiliar, deberá acreditarlo fehacientemente ante el Juzgador o Juzgadora de la causa, quien discrecionalmente y bajo las máximas de la experiencia tazará discrecionalmente los honorarios correspondientes.\nArtículo 27. Cuando la perita, perito o auxiliar acepte el cargo conferido, y proteste su fiel y legal desempeño, se le otorgará un plazo de tres días hábiles para que presente un escrito ante el órgano jurisdiccional correspondiente, en el que señale el monto de sus honorarios, de acuerdo con este Reglamento. Lo anterior, sin perjuicio de lo que establezcan las normas procesales aplicables al caso concreto.\nArtículo 28. Los honorarios de la perita, perito o auxiliar designado por cada una de las partes serán cubiertos por aquella parte que lo designe; en caso de que la perita, perito o auxiliar sea designado en rebeldía de alguna de las partes, sus honorarios serán cubiertos por la parte que debió designarlo y no lo hizo; o bien, cuando la persona juzgadora realice la designación como perito tercero, éste debe ser pagado por ambas partes. Lo anterior, siempre que no sentencia definitiva respecto a las costas.\nCAPÍTULO TERCERO\nSERVICIO SOCIAL\nArtículo 29. Las peritas, peritos y auxiliares están obligados a prestar servicio social, al menos en dos ocasiones al año y comprobar ante la Coordinación su cumplimiento.\nArtículo 30. Las personas juzgadoras podrán solicitar informes a la Coordinación con el fin de conocer si la perita, perito o auxiliar que ha de designar ya ha prestado su servicio social.\nSi la perita, perito o auxiliar designado ya ha cumplido con esta disposición, se nombrará uno diverso.\nArtículo 31. El Consejo a través de la Coordinación, tendrá facultad discrecional para brindar apoyo a grupos o personas en estado de vulnerabilidad.\nCAPÍTULO CUARTO\nRESPONSABILIDAD DE PERITAS, PERITOS Y AUXILIARES\nArtículo 32. Son faltas que pueden cometer las peritas, peritos y auxiliares, además de las previstas en la Ley, las siguientes:\nI. No manifestar negativa o aceptación del cargo conferido;\nII. Emitir con dolo o mala fe dictámenes periciales o avalúos;\nIII. Haber obtenido el registro y constancia del padrón de peritos, peritas y auxiliares, proporcionando datos o documentos falsos o alterados;\nIV. Negarse sin causa justificada prestar sus servicios o no dar cumplimiento a la obligación de realizar anualmente, al menos dos peritajes gratuitos como servicio social;\nV. Intervenir como perita, perito o auxiliar en asuntos en los que se encuentre legalmente impedido o impedida de conformidad con lo dispuesto en el presente Reglamento;\nVI. Presentar dictámenes estando inhabilitado por resolución judicial o administrativa;\nVII. Emitir dictámenes que notoriamente favorezcan a una de las partes, de manera indebida e injustificada;\nVIII. Formular dictámenes en los que resulte notoria la falta de observancia del conocimiento de la profesión, ciencia, industria, materia, oficio, arte o técnica, estando obligado a aplicarlo;\nIX. No presentar el dictamen en los plazos fijados en la ley o señalados por el órgano jurisdiccional;\nX. Presentar su informe pericial fuera de los plazos referidos;\nXI. No asistir sin causa justificada a las citaciones que les comuniquen los órganos jurisdiccionales;\nXII. No protestar el cargo en el término que les haya sido señalado;\nXIII. No informar a la Coordinación cualquier cambio que incida en su localización;\nXIV. Revelar datos de los asuntos en los que intervenga;\nXV. Presentar dictámenes no formulados personalmente o delegar la responsabilidad de su elaboración;\nXVI. Desempeñar su actividad sin lealtad y honradez;\nXVII. Ostentarse como servidor o servidora pública del Poder Judicial, y\nXVIII. Las demás que prevén las Leyes, o determine el Consejo mediante Acuerdo que se haga del conocimiento general.\nLas perita, peritos y auxiliares serán responsables por los delitos y faltas oficiales en que incurran durante el ejercicio de su cargo y responderán de los daños y perjuicios que causen.\nCAPÍTULO QUINTO\nDEL PROCEDIMIENTO DE RESPONSABILIDADES\nArtículo 33. El Procedimiento disciplinario se tramitará de la siguiente manera:\nI. Iniciará de oficio o a petición de parte;\nII. Los órganos jurisdiccionales comunicarán a la Coordinación el incumplimiento de las obligaciones en las que presuntamente incurrió la perita, perito o auxiliar;\nIII. Las partes del proceso, bajo su más estricta responsabilidad, podrán acudir ante la\nCoordinación a interponer queja por escrito, proponiendo las pruebas que sustenten su dicho o agravio. La Coordinación sin mayor trámite remitirá la denuncia o queja a la Comisión de\nResponsabilidades del Consejo;\nIV. De existir indicios, la Comisión de Responsabilidades del Consejo dictará un acuerdo de inicio y se ordenará correr traslado con la queja y pruebas a la perita, perito o auxiliar, para notificación, manifieste por escrito lo que a su derecho e interés convenga y proponga el material probatorio respectivo;\nV. Transcurrido el término, la Comisión de Responsabilidades del Consejo admitirá las pruebas escucharán los alegatos de las partes.\nVI. La Coordinación emitirá la opinión correspondiente la cual será remitida a la Comisión de\nResponsabilidades del Consejo para que forme parte de los autos;\nVII. La Comisión de Responsabilidades del Consejo, elaborará el proyecto de resolución y lo propondrá ante el Pleno del Consejo para su aprobación, contra el cual no procederá recurso alguno.\nArtículo 34. Las sanciones que pueden hacerse acreedores las peritas, peritos y auxiliares, son las siguientes:\nI. Amonestación por escrito.\nII. Multa, que pondrá oscilar de entre diez a cincuenta veces el valor diario de la Unidad de\nMedida y Actualización de acuerdo con la gravedad de la falta.\nIII. Suspensión temporal de la lista por el periodo que el Consejo estime necesario según la gravedad del caso.\nIV. Cancelación del nombramiento como perita, perito o auxiliar.\nV. Inhabilitación para ser integrante del padrón.\nTRANSITORIOS\nPRIMERO. El presente Reglamento entrará en vigor el mismo día al de su publicación en el\nBoletín Judicial del Estado.\nSEGUNDO. Publíquese el presente Reglamento en el Periódico Oficial del Estado para su mayor difusión.\nTERCERO. Se abroga el Reglamento de Peritos y Auxiliares de la Administración de Justicia del\nEstado de Baja California, publicado en el Periódico Oficial del Estado el once de octubre de dos mil dos.\nCUARTO. Se derogan las disposiciones reglamentarias, administrativas o normativas que se opongan a lo establecido en este Reglamento.\nSecretario General Oscar Julián Peralta Hoyo, que autoriza y da fe.\nCALIFORNIA, OSCAR JULIÁN PERALTA HOYO\nQUE EL PRESENTE REGLAMENTO DE PERITAS, PERITOS Y AUXILIARES DE LA ADMINISTRACIÓN DE JUSTICIA DEL\nESTADO DE BAJA CALIFORNIA, FUE APROBADO EN LA SESIÓN ORDINARIA DE FECHA VEINTITRÉS DE\nOCTUBRE DE DOS MIL VEINTICINCO, POR UNANIMIDAD DE VOTOS EN LO GENERAL, POR LAS CONSEJERAS\nY LOS CONSEJEROS PRESENTES, CON UNA RESERVA: MAGISTRADO PRESIDENTE ALEJANDRO ISAAC\nFRAGOZO LÓPEZ, MAGISTRADA COLUMBA IMELDA AMADOR GUILLEN, MAGISTRADO NELSON ALONSO\nKIM SALAS, LICENCIADA CECILIA RAZO VELASQUEZ Y LICENCIADO FRANCISCO JAVIER TENORIO\nANDÚJAR.- MEXICALI, BAJA CALIFORNIA, A VEINTICUATRO DE OCTUBRE DE DOS MIL VEINTICINCO.CONSTE.-\n(Rúbrica)\nOSCAR JULIÁN PERALTA HOYO",
  "ordenamiento": "REGLAMENTO",
  "jurisdiccion": "BAJA CALIFORNIA",
  "fuente_oficial": "Periódico Oficial",
  "Fecha de última modificación": "2025/10/24",
  "Fecha de publicación": "24/10/2025",
  "url": "https://transparencia.pjbc.gob.mx/documentos/pdfs/reglamentos/ReglamentoPeritaje.pdf",
  "es_escaneado": false,
  "tiene_tablas": true,
  "materia": [
    "procesal",
    "forense",
    "administrativo"
  ]
}