{
  "titulo": "Reglamento Que Regula la Función y Organización de la Central de Actuarios del Poder Judicial del Es",
  "Contenido": "BOLETIN JUDICIAL DEL ESTADO DE\nBAJA CALIFORNIA\nDEL ESTADO\nNO.- 14,934 MEXICALI, BAJA CALIFORNIA VOL. LX\nLunes 10 de Febrero del 2025\nACUERDO GENERAL 03/2025 DEL PLENO DEL CONSEJO DE LA JUDICATURA DEL\nCALIFORNIA, PUBLICADO EN EL BOLETÍN JUDICIAL DEL ESTADO DE BAJA\nCALIFORNIA NÚMERO 14,636 DE FECHA 10 DE OCTUBRE DE 2023 Y EN EL\nPERIÓDICO OFICIAL DEL ESTADO DE BAJA CALIFORNIA EL 20 DE OCTUBRE DE\n2023, Y A SU VEZ, APRUEBA LA EMISIÓN DEL NUEVO REGLAMENTO QUE REGULA\nLA FUNCIÓN Y ORGANIZACIÓN DE LA CENTRAL DE ACTUARIOS DEL PODER\nJUDICIAL DEL ESTADO DE BAJA CALIFORNIA, PRIMERO. La vigilancia, disciplina, supervisión y administración del Poder\nJudicial del Estado de Baja California, corresponde al Consejo de la\nJudicatura del Estado, con fundamento en el artículo 57 fracción, segundo\nCalifornia; y los artículos 2 párrafo segundo, 168 fracciones II y XXX de la Ley\nSEGUNDO. De conformidad con el artículo 155 de la Ley Orgánica del Poder\nJudicial del Estado de Baja California; el Consejo de la Judicatura es el imparcialidad;\nTERCERO. Es facultad del Consejo de la Judicatura expedir acuerdos generales para el adecuado ejercicio de sus funciones, así como establecer adecuado funcionamiento de conformidad con lo previsto en el artículo 65 del Estado de Baja California;\nCUARTO. El artículo 17 de la Constitución Política de los Estados Unidos plazos y términos que fijen las leyes;\nQUINTO. Que el presente se encuentra vinculado con la Política 1.6 Servicio de calidad y humanizado, del Plan de Desarrollo del Poder Judicial del\nEstado de Baja California 2024-2026, teniendo como objetivo Brindar los servicios de impartición de justicia con calidad, acercando la justicia a la gente de forma humanizada, aunado a la atención de las estrategias del\nPlan 1.6.1.5 Implementar mecanismos de comunicación y vinculación rápida y sencilla con instituciones u órganos de gobierno, agilizando con ello la impartición de justicia. 1.6.1.11 Continuar con la modernización tecnológica de los procesos que operan en los Juzgados del sistema escrito, con la finalidad de hacer más accesible la justicia para la ciudadanía con procesos más transparentes, eficientes y ágiles;\nSEXTO. El pleno del Consejo de la Judicatura en sesión ordinaria de fecha\nEstado de Baja California;\nSÉPTIMO. Este pleno del Consejo de la Judicatura en sesión ordinaria de número 18/2023, relativo a la Creación e inicio de funciones de la Central\nOCTAVO. El Consejo de la Judicatura del Estado, analiza permanentemente la demanda de los servicios de administración de justicia, para en su caso, NOVENO. Este Pleno considera derogar el Reglamento que Regula la\nEstado de Baja California, publicado en el Boletín Judicial del Estado de Baja emitir uno nuevo que establezca diversas figuras entre estas, una dirección encargada de coordinar, gestionar y supervisar la operación de la Central de Actuarios en cada uno de los partidos Judiciales. Dirección que deberá asegurar el correcto funcionamiento de la Central, garantizando la uniformidad y eficiencia en los procedimientos, así como la adecuada capacitación y apoyo a los actuarios en todos los partidos judiciales. Siendo responsable de implementar estrategias para optimizar los recursos y mejorar la calidad de los servicios prestados.\nDÉCIMO. Que el nuevo proyecto de Reglamento que Regula la Función y\nOrganización de la Central de Actuarios del Poder Judicial del Estado de\nBaja California, brinda la pauta para crear un nuevo modelo organizativo.\nEvitando la duplicidad de funciones, optimizando los procesos operativos, garantizando una estructura más ágil y eficiente, en la que cada personal adscrito a la central tendrá sus actividades y responsabilidades, sin necesidad de cargos adicionales que realicen funciones ya cubiertas.\nDÉCIMO PRIMERO. Conforme a lo establecido en el artículo 116 fracción II de\nActuarios, podrán ser sancionados administrativamente según las sanciones establecidas en el artículo 132 de la ley en comento, cuando incurran en responsabilidad, por los actos u omisiones que afecten la legalidad, honradez, lealtad, imparcialidad y eficiencia, que deban observar en el desempeño de su empleo, cargo o comisión.\nEn consecuencia, con fundamento en las disposiciones constitucionales y legales invocadas, este Pleno del Consejo de la Judicatura expide el siguiente:\nBAJA CALIFORNIA\nCapítulo I\nDisposiciones generales\nArticulo 1.- El presente reglamento es de orden público e interés general y\nActuarios, la cual prestará servicio a los juzgados de las diversas ramas del derecho, autorizadas previamente por el Pleno del Consejo de la Judicatura del Estado y administrativamente, quedará adscrita a la Secretaría General de Acuerdos del Consejo de la Judicatura del Estado.\nArtículo 2.- La Central de Actuarios tendrá su sede dentro de los límites correspondientes a cada partido judicial, la cual podrá extenderse por coordinaciones en los diversos partidos judiciales, cuando las circunstancias, así lo ameriten, ello previa autorización del Pleno del Consejo de la\nJudicatura.\nArtículo 3.- Para su buen funcionamiento y organización, la Central de\nActuarios contará con el personal que requiera y permita el presupuesto, según se justifique, atendiendo a las necesidades en el servicio y a la factibilidad económica.\nArtículo 4.- La Central de Actuarios a través de las personas secretarias actuarias a su cargo, será la encargada de ejecutar, sin distingos y de manera pronta y expedita, los mandamientos judiciales que deban llevarse a cabo dentro o fuera de las instalaciones de los órganos jurisdiccionales, siempre con sujeción a la normatividad aplicable, teniendo como objetivos la:\na) Estandarización de criterios y formatos de los documentos.\nb) Agilización en los procedimientos de los medios de notificación y comunicación.\nc) Especialización de la función del actuario.\nd) Distribución de los medios de notificación de manera sistematizada, aleatoria y con base referenciada por sus ubicaciones.\nCapítulo II\nArtículo 5.- Cualquier medio de comunicación o notificación que sea de la Central de Actuarios. su cargo de los oficios.\nArtículo 6.- Los juzgados, a través del sistema denominado ¨CENTRAL DE\nACTUARIOS¨ implementado por el departamento de Informática, solicitarán el inicio y la práctica de las diligencias a la Central de Actuarios, el mismo día que se lista para publicación la resolución indicada, dentro del horario de las 8:30 ocho horas con treinta minutos a las 14:00 catorce horas.\nArtículo 7.- Las diligencias solicitadas fuera del horario establecido en el artículo anterior, se registrarán en el sistema con fecha del día hábil siguiente a su petición.\nArtículo 8.- Para la debida diligencia de las notificaciones, el juzgado solicitante deberá capturar los datos requeridos por el sistema, diferenciando los mandamientos que se deberán de practicar de forma oficiosa, de los que son a instancia de parte.\nArtículo 9.- En aquellos casos en que sea necesario compartir copias de traslado, cédula u otro anexo, el juzgado solicitante a través de la persona llegar físicamente a la Central de Actuarios. Lo anterior, a más tardar a las\n20:00 horas del mismo día de su solicitud, debiendo cumplir con los requisitos establecidos por las disposiciones legales, las cuales serán observadas por la\nCoordinación de la Central de Actuarios, en el caso de no estar ajustada a lo señalado, quedará en el estatus de rechazado en el sistema y bajo responsabilidad de término de notificación del juzgado solicitante.\nArtículo 10.- Para el trámite oficioso de la Central de Actuarios se observará lo siguiente: inmueble del Juzgado; con base en lo solicitado y registrado en el expediente electrónico, realizará a través del sistema, las cédulas de diligencias ordenadas; así como la descripción detallada de cada uno de los expedientes que debe remitir a la Central de Actuarios. desarrollar las diligencias en la Central de Actuarios, y al término de la generación y reunión de los documentos necesarios, vía sistema y con base en los domicilios señalados por las partes y registrados por el personal del juzgado solicitante, la Coordinación de la Central determinará en forma aleatoria la carga de trabajo a cada uno de los actuarios.\nLa Coordinación de la Central de Actuarios generará, con base en la distribución mencionada en el párrafo anterior, el plan de trabajo y entregará a cada uno de los actuarios las copias de traslado y cédulas de notificación que contienen en su caso los anexos correspondientes a las diligencias a realizar.\nLas personas secretarias actuarias de la Central, recogerán sus diligencias asignadas en el tercer día hábil posterior a la solicitud realizada por el\nJuzgado, siendo esta la fecha en la que sale publicado el acuerdo y la solicitud planteada por el juzgado, debiendo practicarlas conforme a lo señalado por la legislación aplicable. de central de actuarios, anexar los documentos correspondientes a las sistema de Central de Actuarios, el mismo día que se le turnó, con excepción horas inhábiles para practicarlas, deberán estar disponibles en sistema a más tardar al día hábil siguiente de su notificación. persona enlace con presencia física en el inmueble del juzgado solicitante, las diligencias que se llevaron a cabo, a más tardar a las 15:00 quince horas del día siguiente de la entrega por parte del actuario, verificando que la diligencia quedó debidamente registrada en el sistema; siendo la persona a las diligencias, remitiendo al personal adscrito al Juzgado solicitante las constancias para su debida integración al expediente en cuestión, de acuerdo al modelo de gestión aplicable ya sea en físico, electrónico o ambos según corresponda.\nArtículo 11.- Para el trámite de las notificaciones a petición de parte, se observará lo siguiente:\nUna vez que sean ordenadas por el juzgado a través del sistema, la persona interesada o autorizada dentro de los autos del expediente, a partir del día hábil en que salga publicada la resolución deberá acudir a la Central de\nActuarios a fin de realizar la solicitud respectiva para que le asigne fecha para desahogar la diligencia. En caso de no presentarse en el término de tres días la persona enlace retendrá los autos a su cargo, hasta en tanto se le informe que ya se solicitó fecha.\nEn caso de que la parte interesada o autorizada comparezca a la Central de Actuarios a solicitar fecha para desahogo de notificación, la persona\nCoordinadora deberá asignar fecha e integrarla a la agenda del sistema de la central de actuarios, para que se refleje en el sistema y así, la persona enlace del Juzgado remita los documentos a la Central realizando la descripción detallada de cada uno de los documentos que integran las solicitudes de diligencia. La solicitud efectuada seguirá el mismo proceso de las solicitadas de manera oficiosa, siempre y cuando se solicite fecha en agenda y en su caso, se encuentren los documentos señalados en petición, para el caso de que éstos sean necesarios.\nEn aquellas solicitudes que requieran de la presencia física del interesado, se deberá acordar la fecha en que se practicará la diligencia. Acontecida la fecha de la diligencia programada previamente, la persona enlace tendrá la precaución de haber preparado todo lo conducente, a fin de que notificación requerida por la parte interesada. Una vez hecha la diligencia, notificación, el acta capturada y/o escaneada en el sistema de la Central, los días y las horas inhábiles para practicarlas, se capturarán de su notificación. obre en sistema la notificación a más tardar a las 15:00 quince horas del día siguiente de la entrega por parte de la persona actuaria, y corroborar que la persona enlace del juzgado solicitante los verifique y en su caso, proceda a autorizarla en el sistema para su integración al expediente electrónico. Y lleve a cabo su debida integración física al expediente en cuestión.\nArtículo 12.- Para aquellos diferentes casos de medios de comunicación como envío de citaciones, exhortos, despachos, súplicas o algún otro ordenado por la autoridad judicial, deberán ser solicitados por el juzgado de origen, en el mismo orden estipulado en los artículos anteriores, especificando el tipo de medio a comunicar, a quién se dirige, el asunto y, en su caso, si son de oficio o a petición de parte y demás elementos que sean necesarios y requeridos por el sistema de actuarios.\nLa persona enlace con presencia física en los inmuebles del juzgado de origen deberá preparar dentro del término de 24 veinticuatro horas, cada uno de los diferentes medios de comunicación mencionados en el párrafo anterior, con excepción de aquellos ordenados de extrema urgencia por la o él juez, quien solicitará el apoyo inmediato de la Central de Actuarios.\nEl mismo día de turno, la persona ¨ secretaria actuaria asignada¨ deberá\nCentral de Actuarios el acuse de recibo correspondiente, debidamente registrado e ingresado (documento digitalizado) en el sistema.\nEn caso de resultar infructuoso, la persona “secretaria actuaria asignada¨ aquélla, debidamente registrado e ingresado en el sistema. Hecho lo anterior, se dará vista vía sistema y estará disponible en el mismo para la persona enlace con presencia física en los inmuebles del juzgado solicitante, a más tardar a las 18:00 horas del día siguiente de la entrega por parte de la persona secretaria actuaria. algún anexo o documento, la persona enlace con presencia física en el petición y lo deberá hacer llegar físicamente a la Central de Actuarios. Lo anterior, a más tardar a las 18:00 horas del mismo día de su solicitud, legales, las cuales serán observadas por la persona Coordinadora de la\nCentral de Actuarios, en el caso de no estar ajustada a lo señalado, quedará en el estatus de rechazado y bajo responsabilidad de término de notificación de la persona enlace con presencia física en los inmuebles del\nJuzgado solicitante.\nCapitulo III\nIncidencias.\nArtículo 13.- Serán consideradas como incidencias las siguientes:\na) La cancelación de la notificación u otro medio de comunicación.\nPor el juzgado solicitante: Es aquella requerida de manera oficiosa por el juzgado que la solicita, la cual deberá realizar a través de la persona enlace con presencia física en el juzgado. Lo anterior a más tardar a las 18:00 horas del mismo día de su solicitud. Y respecto a las solicitudes señaladas como de instancia de parte, hasta en tanto no se haya solicitado por el interesado.\nPor la Persona Enlace: Es aquella requerida inmediatamente a la presencia física en las instalaciones del juzgado; al tener conocimiento que secretaria actuaria o secretaria de acuerdos. A fin de que mediante sistema comunicación tenga conocimiento de ello, y así se evite la duplicidad de notificaciones.\nPor la Central de Actuarios: Es aquella requerida por la persona persona actuaria y antes de su notificación por éste.\nPor la parte interesada o autorizada: Es aquella requerida en cualquier momento por la parte interesada o autorizada; misma que se podrá realizar\nCoordinadora de la Central de Actuarios, identificándose la parte interesada o autorizada como parte del juicio. Ante quien se realice la cancelación de la notificación u otro medio de comunicación, deberá asentar las razones respectivas en el sistema de la central.\nb) La solicitud de carácter urgente. Es aquella decretada por la o él juez de la materia, para mejor proveer de conformidad con las disposiciones legales, inminentes y necesarias para la celebración de la audiencia en ese día o dentro de la misma. Así como los documentos de término de 24 veinticuatro horas, remitidos por los juzgados a las autoridades federales.\nDiversos casos, que se deberán solicitar a través del sistema de la central.\nEllo, con el fin de que la Central de Actuarios, esté en la aptitud de diligenciar de manera inmediata a través de las personas actuarias adscritas a la Central. Subiendo al sistema mediante fotografía con sello de recibido el documento diligenciado o en su caso devolviéndolo al juzgado emisor, registrando y razonando en el sistema el motivo por el que no se diligenció.\nc) La falta de documentación. Son todas aquellas copias de traslado u otros anexos que se requieran acompañar a la notificación o al medio de comunicación solicitado, las que deberán estar requisitadas y descritas por conforme a las disposiciones legales, mismas que serán verificadas a su vez, por la persona secretaria actuaria asignada, y en caso de que no fuesen entregados físicamente. En consecuencia, dicha diligencia quedará rechazada en el sistema y remitida al juzgado de origen, recayendo la del juzgado de origen en lo referente al término de notificación.\nd) La falta de impulso procesal: Es aquella no solicitada por la parte materia. solicitante, de las solicitudes rechazadas por estar pendientes de allegar documentación. Y la persona enlace deberá informar la no solicitud o diligencia por parte interesada; lo anterior con el fin de que el Juzgador resuelva lo conducente sobre las mismas.\nCapítulo IV\nDe la estructura y organización de la Central de Actuarios.\nArtículo 14.- La Central de Actuarios a nivel Estado contará con una\nDirección que dependerá del Consejo de la Judicatura, siendo esta la responsable de atender las necesidades específicas de cada central, organizándose con las o los coordinadores de las centrales de actuarios en los diversos partidos judiciales, a fin de lograr los objetivos y metas deseados mediante el uso de los recursos disponibles de manera eficaz y eficiente.\nArtículo 15.- La Central de Actuarios a nivel Estado estará a cargo de una persona Director, cuyas atribuciones son las siguientes:\nI. Establecer la necesaria coordinación y comunicación con las o los coordinadores de la central de actuarios de cada partido judicial, a efecto de garantizar el cabal y puntual cumplimiento de las resoluciones judiciales;\nII. Recibir informe de incidencias diarias por las diversas coordinaciones de la central de actuarios de cada partido judicial; así como autorizar la programación de vacaciones.\nIII. Resolver situaciones de emergencia y conflicto respecto la operatividad de la central de actuarios.\nIV. Vigilar el buen funcionamiento de la Central de Actuarios en cada partido judicial;\nV. Verificar y vigilar que las personas coordinadoras de cada una de las centrales, realicen su trabajo con la responsabilidad y diligencia respectiva;\nVI. Orientar cuando se requiera a las personas coordinadoras de cada una resoluciones judiciales;\nVII. En caso de requerirse, deberá establecer la necesaria comunicación judicial;\nVIII. Levantar las actas administrativas a las faltas cometidas por la persona coordinadora de la Central del partido judicial que corresponda;\nIX. Realizar análisis y verificación de estadísticas para evaluar el\nX. Rendir la estadística e informe mensual de actividades al Pleno del\nConsejo de la Judicatura y a la Unidad de Planeación y Desarrollo del\nPoder Judicial del Estado de Baja California.\nXI. Supervisar el cumplimiento de plazos para atender las solicitudes de los juzgados, así como para llevar a cabo las diligencias, evitando rezagos.\nXII. Otorgar el visto bueno a las propuestas de personal realizadas por las personas coordinadoras de cada central de actuarios.\nXIII. Vigilar que los resultados de las diligencias que se realicen en cada central de los diversos partidos judiciales estén actualizados.\nXIV. Asegurar que todos los colaboradores conozcan sus funciones y responsabilidades.\nXV. Coordinar y verificar el seguimiento a las tareas del personal, asegurando que se cumplan con los objetivos y plazos establecidos.,\nXVI. Desarrollar las actividades conforme a los procedimientos documentados.\nXVII. Las demás que la ley, el pleno del Consejo de la Judicatura, le encomienden.\nArtículo 16.- La Central de Actuarios de cada partido judicial se integrará con:\nI. La persona Coordinadora;\nII. Las personas Secretarias Actuarias, pertenecientes a la Central;\nIII. Personal de enlace, que podrá tener presencia física en los inmuebles\nCentral y el Juzgado\nIV. Demás personal técnico y administrativo que apruebe el Pleno del\nConsejo de la Judicatura, de acuerdo con disponibilidad presupuestal.\nArtículo 17.- La Central de Actuarios estará a cargo de una persona\nCoordinadora, cuyas atribuciones son las siguientes:\nI. Establecer la necesaria coordinación y comunicación con los juzgados solicitantes, a efecto de garantizar el cabal y puntual cumplimiento de las resoluciones judiciales;\nII. Recibir diariamente las actuaciones que remitan los juzgados solicitantes para la práctica de las diligencias respectivas;\nIII. Organizar el desahogo de las diligencias y el trabajo del personal de acuerdo a las necesidades del servicio, detectando índices de desempeño, productividad y eficacia;\nIV. Establecer roles de trabajo, guardias y suplencias por impedimentos a excusas entre el personal a su cargo;\nV. Verificar que las diligencias solicitadas por los interesados, se señalen conforme a los lineamientos establecidos en este reglamento;\nVI. Vigilar que a cada persona secretaria actuaria a su cargo se le asigne la carga de diligencias ordenadas por las y los jueces solicitantes, conforme al sistema el cual distribuirá de manera equitativa y aleatoria la carga de trabajo;\nVII. Asignar en forma aleatoria, el número de personas secretarias actuarias que, conforme a la carga de trabajo realizarán las diligencias ordinarias, así como las personas secretarias actuarias que realizarán las extraordinarias;\nVIII. Designar a través del sistema las diligencias a las personas secretarias actuarias, apoyado del personal a su cargo para seguimiento y control del desahogo de estas, hasta su total ejecución. Solicitando a la persona enlace y/o a las partes interesadas, los datos que se consideren necesarios para agilizar la práctica de las diligencias;\nIX. Autorizar en sistema las cédulas de notificación que remite la diligencias;\nX. Disponer el desahogo inmediato de notificaciones y diligencias ordenadas por los jueces con carácter de urgente, asignando la persona secretaria actuaria disponible en el momento;\nXI. Verificar y vigilar que las personas enlace realicen su trabajo con la responsabilidad y diligencia respectiva.\nXII. Comunicarse cuando así lo requiera con el Titular del Juzgado que ordenó la diligencia, a fin de orientar a las personas secretarias judiciales;\nXIII. Devolver a cada juzgado a través de la persona enlace los documentos generados en sistema ya sea diligenciados, o sin diligenciar donde obren las razones que impidieron la práctica de la actuación;\nXIV. Atender los requerimientos o quejas que presenten los juzgados, litigantes y público en general respecto a las actividades de su competencia;\nXV. Atender a las observaciones y recomendaciones de las personas titulares de los juzgados, a efecto de prevenir y corregir excesos y defectos en la ejecución de las resoluciones judiciales;\nXVI. Velar por la debida custodia de los documentos entregados por los juzgados;\nXVII. Establecer las medidas de control y vigilancia que garanticen la debida transparencia, así como el sigilo en los casos que así lo requieran;\nXVIII. Llevar un control de las salidas de las personas actuarias de ruta pertenecientes a la Central de Actuarios; según corresponda, así como de la duración de esté y de la participación de los interesados, en su promoción y ejecución, de acuerdo a los requerimientos de la diligencia a practicar;\nXIX. Verificar que se haya gestionado por la parte interesada cuando la o él juez ordene el auxilio de la fuerza pública, en términos de\nLey, de acuerdo a la naturaleza y riesgos de la resolución a ejecutar;\nXX. Establecer la necesaria comunicación con las autoridades bienes relacionados con la ejecución de una resolución judicial, para garantizar su debida conservación;\nXXI. Supervisar que las diligencias se practiquen con estricto apego a derecho;\nXXII. Levantar las actas administrativas a las faltas cometidas por el personal de la Central del partido al que se encuentre adscrito;\nXXIII. Rendir la estadística e informe mensual de actividades a la\nEstado de Baja California.\nXXIV. Las demás que la ley, el pleno del Consejo de la Judicatura, le encomienden.\nArtículo 18.- Son atribuciones y obligaciones de las Personas Enlace con presencia física en los inmuebles de los Juzgados:\nI. Examinar previamente los autos para confirmar qué tipo de diligencias son ordenadas y el término en el que se deben de realizar;\nII. Autorizar con su firma los documentos que justifiquen la recepción de los expedientes por parte del Juzgado en el que se encuentran asignados por la coordinación de la Central;\nIII. Preparar debidamente las diligencias ordenadas por el Juzgado en el que se encuentran asignados por la coordinación de la Central;\nIV. Operar el programa computarizado para la elaboración de las cédulas de notificación y la obtención de los demás documentos necesarios para la debida diligencia y conocimiento de los demás medios de comunicación;\nV. Verificar a través del sistema que las diligencias solicitadas por el juzgado, se realizaron cabalmente por las personas actuarias de la central; para en su caso, autorizar en el expediente electrónico o devolver a la central para su debida diligencia;\nVI. Turnar a través del sistema y en físico al secretario de acuerdos del\nJuzgado correspondiente las actuaciones autorizadas, mismas que fueron realizadas por los actuarios de la Central, para la elaboración del acuerdo correspondiente.\nVII. Velar por la debida custodia de los documentos entregados por el\nCoordinación de la Central;\nVIII. Informar incidencias a la persona Coordinadora para un mejor central, aclarándole dudas, comunicándose para tal efecto en caso de considerarlo necesario.\nIX. Mantener actualizado con la información requerida el módulo del que integran el expediente electrónico.\nX. Las demás que les fijen las leyes, reglamentos o acuerdos emitidos por el Consejo de la Judicatura.\nArtículo 19.- Son obligaciones de las personas secretarias actuarias adscritas a la Central de Actuarios las siguientes:\nI. Realizar las diligencias asignadas en el término y conforme lo disponga la ley, examinando previamente los autos para verificar qué tipo de diligencias son y si están debidamente preparadas; practicar conforme a las fechas prefijadas las diligencias ordenadas por las y los jueces, dentro de las horas y día hábiles o habilitados;\nII. Autorizar con su nombre y firma las diligencias que realice;\nIII. Priorizar y solicitar el auxilio de la fuerza pública, en términos de Ley, de acuerdo a la naturaleza y riesgos para los grupos prioritarios o en algún contexto de vulnerabilidad.\nIV. Solicitar el auxilio de la o él Juez, con el fin de que se requiera el apoyo de la fuerza pública para el desahogo de las diligencias, en caso de ser necesario;\nV. Solicitar el auxilio de la fuerza pública en caso de verse amagada su seguridad o integridad física, durante el desahogo de alguna diligencia;\nVI. A efecto de garantizar el debido cumplimiento, y de acuerdo a sus atribuciones, resolver las incidencias que se presentaren y en caso de suspensión de la diligencia por imposibilidad jurídica, material o riesgo a su integridad, asentar tales circunstancias en el acta respectiva que se captura en el sistema;\nVII. Comunicar con la debida oportunidad, a la persona coordinadora de la Central de Actuarios, el impedimento o excusa grave que tengan para practicar las diligencias asignadas. Lo anterior, a fin de que previa autorización de la persona coordinadora, se haga la substitución. La falta de cumplimiento a esta obligación, será causa de responsabilidad;\nVIII. Informar diariamente a la persona coordinadora de la Central o al personal que este designe para apoyo, el resultado de las diligencias realizadas y, en su caso, las razones por las que no fue posible llevarlas a cabo;\nIX. Capturar en sistema el Acta respectiva según la diligencia encomendada, siguiendo los lineamientos de los formatos efecto; En caso de no practicarse la diligencia deberá devolver la realizó. Actuaciones que deberán obrar en el sistema en formato electrónico el mismo día de su turno;\nX. Mantener actualizado con la información requerida el módulo del sistema Central de Actuarios mediante el cual se elaborarán las actas que integran el expediente electrónico;\nXI. Mantener y custodiar en buen estado los bienes muebles asignados, con razón de sus actividades en la Central de Actuarios;\nXII. En aquellos casos de amparo, deberá elaborar por escrito la contestación de las demandas interpuestas en contra de sus actuaciones, así como la presentación de la misma ante la autoridad correspondiente en tiempo y forma; y\nXIII. Las demás que les fijen las leyes, reglamentos o acuerdos emitidos por el Consejo de la Judicatura.\nArtículo 20.- El personal administrativo tendrá las siguientes atribuciones:\nI. Atender al público en general que acuda a la Central de\nActuarios;\nII. Operar en el sistema de la Central las solicitudes que realizan los juzgados;\nIII. Recibir y verificar que los documentos enviados por las personas correspondan con lo señalado en las cédulas de notificación.\nIV. Realizar la conciliación, verificación y la relación diaria en el sistema de las actuaciones y diligencias realizadas, así como los juzgados;\nV. Organizar y separar debidamente la documentación según su clasificación y estatus;\nVI. Monitorear diariamente y mantener actualizado en el sistema y atendidos por la Central de Actuarios.\nVII. Realizar los oficios y contestaciones a las diversas autoridades, incluyendo los informes de los juicios de amparo.\nVIII. Checar diariamente la correspondencia; y\nIX. Demás funciones que le sean encomendadas por sus superiores.\nCapítulo V\nQuejas\nArticulo 21.- Es deber de la persona coordinadora de la Central de\nActuarios, el atender los requerimientos o quejas que presenten los jueces, litigantes y público en general respecto a las actividades de su competencia;\nArtículo 22.- La denuncia y/o queja por parte interesada, podrá presentarse por escrito, ante la Central de Actuarios, la cual deberá de enviar a la brevedad posible ante la autoridad competente, para su conocimiento y trámite legal, previo su registro para su control pertinente.\nCapítulo VI\nDe las Sanciones\nArtículo 23.- Las faltas en que incurran la persona titular de la Dirección de la Central de Actuarios, la persona coordinadora y las personas secretarias actuarias de la Central, serán sancionadas por el Pleno del Consejo de la del Estado de Baja California, sin perjuicio de que expresamente prevé el responsabilidad penal que, en su caso, pudieran a incurrir.\nArtículo 24.- Las faltas en que incurra el personal administrativo adscrito a la\nCentral de Actuarios, serán sancionadas en los términos de las Leyes administrativas aplicables; con independencia de la responsabilidad penal que, en su caso, pudieran a incurrir.\nTRANSITORIOS\nPRIMERO.- El presente reglamento entrará en vigor al día siguiente de su publicación en el Boletín Judicial del Estado.\nSEGUNDO. – Se deroga el Reglamento que Regula la Función y Organización publicado en el Boletín Judicial del Estado de Baja California número 14,636 de fecha diez de octubre de dos mil veintitrés.\nTERCERO.- Publíquese el presente acuerdo en el Boletín Judicial del Estado de Baja California y en el Periódico oficial del Estado de Baja California.\nCUARTO. - El Consejo de la Judicatura del Estado, resolverá cualquier del presente.\nEL LICENCIADO CARLOS RAFAEL FLORES DOMÍNGUEZ, SECRETARIO GENERAL\nDEL CONSEJO DE LA JUDICATURA DEL ESTADO DE BAJA CALIFORNIA.\nQUE EL PRESENTE ACUERDO GENERAL NÚMERO 03/2025 DEL PLENO DEL\nCONSEJO DE LA JUDICATURA DEL ESTADO, POR EL QUE APRUEBA LA\nCALIFORNIA, PUBLICADO EN EL BOLETÍN JUDICIAL DEL ESTADO DE BAJA\nPERIÓDICO OFICIAL DEL ESTADO DE BAJA CALIFORNIA EL 20 DE OCTUBRE DE\n2023, Y A SU VEZ, APRUEBA LA EMISIÓN DEL NUEVO REGLAMENTO QUE REGULA\nLA FUNCIÓN Y ORGANIZACIÓN DE LA CENTRAL DE ACTUARIOS DEL PODER\nJUDICIAL DEL ESTADO DE BAJA CALIFORNIA, FUE APROBADO POR EL PLENO\nDEL PROPIO CONSEJO, EN SESIÓN ORDINARIA DEL DÍA 06 DE FEBRERO DE\n2025, POR UNANIMIDAD DE VOTOS DE LOS CONSEJEROS Y CONSEJERAS\nPRESENTES: MAGISTRADO PRESIDENTE ALEJANDRO ISAAC FRAGOZO LÓPEZ,\nMAGISTRADA MARÍA DOLORES MORENO ROMERO, MAGISTRADO GUSTAVO\nMEDINA CONTRERAS, JUEZ HUMBERTO TAMAYO CAMACHO, LICENCIADA\nCONSTE.DEL ESTADO DE BAJA CALIFORNIA\n(Rúbrica)\nMTRO. CARLOS RAFAEL FLORES DOMÍNGUEZ",
  "ordenamiento": "REGLAMENTO",
  "jurisdiccion": "BAJA CALIFORNIA",
  "fuente_oficial": "Periódico Oficial",
  "Fecha de última modificación": null,
  "Fecha de publicación": null,
  "url": null,
  "es_escaneado": false,
  "tiene_tablas": true,
  "materia": [
    "administrativo",
    "procesal",
    "carrera judicial"
  ]
}