{
  "titulo": "Ley DE ACCESO DE LAS MUJERES A UNA VIDA LIBRE DE VIOLENCIA DEL ESTADO DE CAMPECHE",
  "Contenido": "DE VIOLENCIA DEL ESTADO DE CAMPECHE\nTÍTULO\nPRIMERO\nCAPÍTULO\nÚNICO\nDISPOSICIONES GENERALES\nARTÍCULO 1.- La presente ley es de orden público e interés social y tiene por objeto prevenir, atender, sancionar y erradicar la violencia contra las mujeres, así como establecer los principios, instrumentos y mecanismos para garantizar su acceso a una calidad de vida que favorezca su desarrollo y bienestar.\nARTÍCULO 2.- Los principios rectores para el acceso de las mujeres a una vida libre de violencia son:\nI. La igualdad jurídica de género;\nII. El respeto a los derechos humanos de las mujeres;\nIII. La no discriminación.\nIV. La libertad y autodeterminación de las mujeres;\nV. El pluralismo social y la multiculturalidad de las mujeres;\nVI. La perspectiva de género que permite incorporar a la mujer como sujeto social; y\nVII. La integración plena y total de las mujeres a la vida democrática y productiva del Estado.\nNota: Se reformó la fracción II y se adicionaron las fracciones IV, V, VI y VII mediante decreto 254 de la LXI legislatura, publicado en el P.O. del gobierno del Estado No.5119 de fecha 14 de noviembre de 2012.\nARTÍCULO 2 bis.- Serán principios procesales en la presente Ley, en aquellos procedimientos civiles y penales, que ventilen algún tipo de violencia de género, los siguientes:\nI. La gratuidad;\nII. La celeridad; y\nIII. La confidencialidad.\nNota: Se adicionó mediante decreto 254 de la LXI legislatura, publicado en el P.O. del\nARTÍCULO 2 ter.- Los derechos de las mujeres protegidos por esta Ley son:\nI. La vida;\nII. La libertad;\nIII. La igualdad;\nIV. La intimidad;\nV. La no discriminación;\nVI. La integridad física, psicoemocional y sexual de las mujeres; y\nVII. El patrimonio\nNota:Se adicionó mediante decreto 254 de la LXI Legislatura, publicado en el P.O. del\nARTÍCULO 3.- La aplicación de la presente ley corresponde al Poder Ejecutivo del\nEstado, a través de las dependencias y entes públicos estatales que se señalan en esta ley, así como a los Ayuntamientos, en sus respectivos ámbitos de competencia.\nARTÍCULO 4.- El Estado y los Municipios preverán en sus respectivos presupuestos de egresos los recursos necesarios para implementar los programas y acciones de prevención y atención a las mujeres víctimas de violencia derivados de la presente ley.\nARTÍCULO 5.- Los tipos de violencia contra las mujeres son:\nI. Violencia psicológica.- Es cualquier acto u omisión reiterada que dañe la estabilidad psicológica, que puede consistir en negligencia, abandono, insultos, devaluación, marginación, comparaciones destructivas, restricción a la autodeterminación y amenazas, las cuales conllevan a la víctima a la depresión, al aislamiento, a la devaluación de su autoestima e incluso al suicidio;\nII. Violencia física.- Es cualquier acto que inflija daño no accidental, usando la fuerza física o algún tipo de arma u objeto que pueda provocar o no lesiones ya sean internas, externas, o ambas;\nIII. Violencia patrimonial.- Es cualquier acto u omisión que afecta la supervivencia de la víctima. Se manifiesta en la transformación, sustracción, destrucción, retención o distracción de objetos, documentos personales, bienes y valores, derechos patrimoniales o recursos económicos destinados a satisfacer sus necesidades y puede abarcar los daños a los bienes comunes o propios de la víctima;\nIV. Violencia económica.- Es toda acción u omisión del agresor que afecta la supervivencia económica de la víctima. Se manifiesta a través de limitaciones encaminadas a controlar el ingreso de sus percepciones económicas, así como la percepción de un salario menor por igual trabajo, dentro de un mismo centro laboral;\nV. Violencia sexual.- Es cualquier acto que degrada o daña el cuerpo y/o la sexualidad de la víctima y que por tanto atenta contra su libertad sexual, dignidad e integridad física. Es una expresión de abuso de poder que implica la supremacía masculina sobre la mujer, al denigrarla y concebirla como objeto; y\nVI. Violencia Política en contra de las mujeres en razón de género: es toda acción u omisión, incluida la tolerancia, basada en elementos de género y ejercida dentro de la esfera pública o privada, que tenga por objeto o resultado limitar, anular o menoscabar el ejercicio efectivo de los derechos políticos y electorales de una o varias mujeres, el acceso al pleno ejercicio de las atribuciones inherentes a su cargo, labor o actividad, el libre desarrollo de la función pública, la toma de decisiones, la libertad de organización, así como precandidatura, candidatura o a un cargo público;\nVII. Violencia Obstétrica.- Es toda acción u omisión por parte del personal médico y de salud, que dañe, lastime, denigre o cause la muerte a la mujer durante el embarazo, parto y puerperio; así como la negligencia en su atención médica que se exprese en un trato deshumanizado, en un abuso de medicalización y patologización de los procesos naturales, trayendo consigo pérdida de autonomía y capacidad de decidir libremente sobre sus cuerpos y sexualidad;\nconsiderando como tales la omisión de la atención oportuna y eficaz de las emergencias obstétricas; practicar el parto por vía de cesárea, existiendo condiciones para el parto natural; el uso de métodos anticonceptivos o esterilización sin que medie el consentimiento voluntario, expreso e informado de la mujer; así como obstaculizar sin causa médica justificada el apego precoz del niño o niña con su madre, negándole la posibilidad de cargarlo y amamantarlo inmediatamente después de nacer;\nVIII. Violencia Digital.- Son los actos de acoso, hostigamiento, amenaza, insultos, vulneración de datos e información privada, divulgación de la información apócrifa, mensajes de odio, difusión de contenido sexual sin consentimiento, textos, fotografías, vídeos y/o datos personales u otras impresiones gráficas o sonoras, verdaderas o alteradas, o cualquier otra acción que sea cometida a través de las Tecnologías de la Información y la Comunicación, plataformas de internet, redes sociales, correo electrónico, aplicaciones, o cualquier otro espacio digital que atente contra la integridad, dignidad, intimidad, libertad, vida privada o vulnere algún derecho humano de las mujeres; y\nIX. Cualesquiera otras formas análogas que lesionen o sean susceptibles de dañar la dignidad, integridad o libertad de las mujeres.\nNota: Se reformó la fracción VI y se adiciona la fracción VII mediante decreto 126 de la\nNota: Se reformó la fracción VII y se adicionó una fracción VIII mediante decreto 255\nNota: Se reformaron las fracciones VI y VIII y se adicionó una fracción IX mediante\nTÍTULO SEGUNDO\nMODALIDADES DE LA VIOLENCIA EN CONTRA DE LAS\nMUJERES\nCAPÍTULO I\nDE LA VIOLENCIA EN EL ÁMBITO FAMILIAR\nARTÍCULO 6.- La violencia familiar es el acto de poder u omisión intencional, dirigido a dominar, someter, controlar o agredir de manera física, verbal, psicoemocional, patrimonial, económica y sexual a las mujeres, dentro o fuera del domicilio familiar, afinidad, de matrimonio, concubinato o mantengan o hayan mantenido una relación de hecho.\nEn lo relativo a este tipo de violencia se estará a lo dispuesto en la Ley de Prevención y\nAtención de la Violencia Intrafamiliar para el Estado de Campeche, así como en los\nCódigos Civil y de Procedimientos Civiles, Penal y de Procedimientos Penales para el\nEstado de Campeche.\nCAPÍTULO II\nDE LA VIOLENCIA LABORAL Y DOCENTE\nARTÍCULO 7.- La violencia laboral la constituye la negativa ilegal a contratar a la víctima intimidación, las humillaciones, la explotación y todo tipo de discriminación por condición de género.\nARTÍCULO 8.- La violencia docente se materializa por aquellas conductas que dañen la autoestima de las alumnas con actos de discriminación por su sexo, edad, condición social, académica, limitaciones y/o características físicas, que les infringen los docentes y/o académicos o personal administrativo.\nARTÍCULO 9.- La violencia laboral y la docente pueden consistir en un solo evento dañino o en una serie de eventos cuya suma produce el daño y pueden en algunos casos configurar el acoso o el hostigamiento sexual, en los términos de la legislación penal del Estado.\nSe entiende por hostigamiento el ejercicio del poder, en una relación de subordinación real de la víctima frente al agresor.\nsubordinación real de la víctima frente al agresor en los ámbitos laboral y/o escolar, pero en que el agresor, con fines sexuales, usa poder que conlleva a un estado de indefensión y riesgo de la víctima.\nNota: Se adicionaron los párrafos segundo y tercero mediante decreto 133 de la LXIII\nCAPÍTULO III\nDE LA VIOLENCIA EN LA COMUNIDAD\nARTÍCULO 10.- Violencia en la Comunidad: Son los actos individuales o colectivos que transgreden derechos fundamentales de las mujeres y propician su denigración, discriminación, marginación o exclusión en el ámbito público.\nCAPÍTULO IV\nDE LA VIOLENCIA DE FUNCIONARIOS PÚBLICOS\nARTÍCULO 11.- Constituye la violencia de funcionarios públicos los actos u omisiones de obstaculizar o impedir el goce y ejercicio de los derechos humanos de las mujeres, así como su acceso al disfrute de políticas públicas destinadas a prevenir, atender, investigar, sancionar y erradicar los diferentes tipos de violencia.\nARTÍCULO 12.- El Estado y los Municipios, en el ámbito de sus respectivas competencias, fomentarán las adecuaciones que correspondan en el ámbito administrativo y procurarán la capacitación que requieran sus servidores públicos, a fin de que en el ejercicio de sus funciones éstos sean capaces de asegurar el derecho de las mujeres a una vida libre de violencia.\nARTÍCULO 13.- El Estado y los Municipios promoverán las acciones conducentes para prevenir, atender, investigar y sancionar las conductas violentas en contra de las mujeres ejercidas por servidores públicos, así como aquellas que, en su caso, sean necesarias a fin de que se repare el daño inflingido (sic) a las víctimas, de conformidad con lo dispuesto por las disposiciones jurídicas aplicables.\nCAPÍTULO V\nDE LA VIOLENCIA FEMINICIDA\nARTÍCULO 14.- La violencia feminicida es la forma extrema de violencia de género contra las mujeres, producto de la violación de sus derechos humanos, en los ámbitos público y privado, conformada por el conjunto de conductas misóginas que pueden conllevar impunidad y culminar en homicidio y formas de muerte violenta de mujeres, impida el ejercicio pleno de los derechos humanos de las mujeres.\nARTÍCULO 15.- Cuando se presenten casos de violencia feminicida, el Gobierno del la seguridad de las mujeres, el cese de la violencia en su contra y eliminar las situaciones de desigualdad en que se encuentren, sin perjuicio de que puedan de género, a fin de que se adopten las medidas y acciones preventivas de seguridad y justicia que procedan.\nseñaladas.\nCAPÍTULO V BIS\nDE LA VIOLENCIA POLÍTICA CONTRA LAS\nMUJERES EN RAZÓN DE GÉNERO\nNota: Se adicionó mediante decreto 126 de la LXI Legislatura, publicado en el P.O. del gobierno del Estado No. 5502 de fecha 11 de junio de 2014.\nNota: Se reformó la denominación mediante decreto 133 de la LXIII Legislatura, publicado en el P.O. del gobierno del Estado No. 1183 Tercera Sección de fecha 27 de mayo de 2020.\nARTÍCULO 16 BIS. La violencia política contra las mujeres en razón de género, es toda acción u omisión, incluida la tolerancia, basada en elementos de género y ejercida dentro de la esfera pública o privada, que tenga por objeto o resultado limitar, anular o menoscabar el ejercicio efectivo de los derechos políticos y electorales de una o varias mujeres, el acceso al pleno ejercicio de las atribuciones inherentes a su cargo, labor o actividad, el libre desarrollo de la función pública, la toma de decisiones, la libertad de organización, así como el acceso y ejercicio a las prerrogativas correspondientes a una precandidatura, candidatura o a un cargo público.\nSe entenderá que las acciones u omisiones se basan en elementos de género, cuando se dirijan a una mujer por su condición de mujer; le afecten desproporcionadamente o tengan un impacto diferenciado en ella.\nPuede manifestarse en cualquiera de los tipos de violencia reconocidos en esta Ley y puede ser perpetrada indistintamente por agentes estatales, por superiores jerárquicos, colegas de trabajo, personas dirigentes de partidos políticos, militantes, simpatizantes, precandidatas, precandidatos, candidatas o candidatos postulados por los partidos políticos o representantes de los mismos; medios de comunicación y sus integrantes, por un particular o por un grupo de personas particulares.\nLa violencia política contra las mujeres puede expresarse, entre otras, a través de las siguientes conductas:\nI. Incumplir las disposiciones jurídicas nacionales e internacionales que reconocen el ejercicio pleno de los derechos políticos de las mujeres;\nII. Restringir o anular el derecho al voto libre y secreto de las mujeres, u organizaciones políticas y civiles, en razón de género;\nIII. Ocultar información u omitir la convocatoria para el registro de candidaturas o desarrollo de sus funciones y actividades;\nIV. Proporcionar a las mujeres que aspiran u ocupan un cargo de elección popular información falsa o incompleta, que impida su registro como candidata o induzca al incorrecto ejercicio de sus atribuciones;\nV. Proporcionar información incompleta o datos falsos a las autoridades administrativas, electorales o jurisdiccionales, con la finalidad de menoscabar los derechos políticos de las mujeres y la garantía del debido proceso;\nVI. Proporcionar a las mujeres que ocupan un cargo de elección popular, información falsa, incompleta o imprecisa, para impedir que induzca al incorrecto ejercicio de sus atribuciones;\nVII. Obstaculizar la campaña de modo que se impida que la competencia electoral se desarrolle en condiciones de igualdad;\nVIII. Realizar o distribuir propaganda política o electoral que calumnie, degrade o descalifique a una candidata basándose en estereotipos de género que reproduzcan relaciones de dominación, desigualdad o discriminación contra las mujeres, con el objetivo de menoscabar su imagen pública o limitar sus derechos políticos y electorales;\nIX. Difamar, calumniar, injuriar o realizar cualquier expresión que denigre o descalifique a las mujeres en ejercicio de sus funciones políticas, con base en estereotipos de género, con el objetivo o el resultado de menoscabar su imagen pública o limitar o anular sus derechos;\nX. Divulgar imágenes, mensajes o información privada de una mujer candidata o en funciones, por cualquier medio físico o virtual, con el propósito de desacreditarla, difamarla, denigrarla y poner en entredicho su capacidad o habilidades para la política, con base en estereotipos de género;\nXI. Amenazar o intimidar a una o varias mujeres o a su familia o colaboradores con el objeto de inducir su renuncia a la candidatura o al cargo para el que fue electa o designada;\nXII. Impedir, por cualquier medio, que las mujeres electas o designadas a cualquier puesto o encargo público tomen protesta de su encargo, asistan a las sesiones ordinarias o extraordinarias o a cualquier otra actividad que implique la toma de decisiones y el ejercicio del cargo, impidiendo o suprimiendo su derecho a voz y voto;\nXIII. Restringir los derechos políticos de las mujeres con base a la aplicación de tradiciones, costumbres o sistemas normativos internos o propios, que sean violatorios de los derechos humanos;\nXIV. Imponer, con base en estereotipos de género, la realización de actividades distintas a las atribuciones propias de la representación política, cargo o función;\nXV. Discriminar a la mujer en el ejercicio de sus derechos políticos por encontrarse en estado de embarazo, parto, puerperio, o impedir o restringir su cualquier otra licencia contemplada en la normatividad;\nXVI. Ejercer violencia física, sexual, simbólica, psicológica, económica o patrimonial contra una mujer en ejercicio de sus derechos políticos;\nXVII. Limitar o negar arbitrariamente el uso de cualquier recurso o atribución inherente al cargo que ocupe la mujer, incluido el pago de salarios, dietas u otras prestaciones asociadas al ejercicio del cargo, en condiciones de igualdad;\nXVIII. Obligar a una mujer, mediante fuerza, presión o intimidación, a suscribir\nXIX. Obstaculizar o impedir el acceso a la justicia de las mujeres para proteger sus derechos políticos;\nXX. Limitar o negar arbitrariamente el uso de cualquier recurso o atribución inherente al cargo político que ocupa la mujer, impidiendo el ejercicio del cargo en condiciones de igualdad;\nXXI. Imponer sanciones injustificadas o abusivas, impidiendo o restringiendo el ejercicio de sus derechos políticos en condiciones de igualdad, o\nXXII. Cualesquiera otras formas análogas que lesionen o sean susceptibles de dañar la dignidad, integridad o libertad de las mujeres en el ejercicio de un cargo político, público, de poder o de decisión, que afecte sus derechos políticos electorales.\nLa violencia política contra las mujeres en razón de género se sancionará en los términos establecidos en la legislación electoral, penal y de responsabilidades administrativas.\nNota: Se adicionó mediante decreto 126 de la LXI Legislatura, publicado en el P.O. del gobierno del Estado No. 5502 de fecha 11 de junio de 2014.\nNota: Se reformó mediante decreto 133 de la LXIII Legislatura, publicado en el P.O. del gobierno del Estado No. 1183 Tercera Sección de fecha 27 de mayo de 2020.\nARTÍCULO 16 TER. El gobierno estatal y los municipales, así como los organismos autónomos, deberán garantizar e impulsar la defensa del pleno ejercicio de los derechos políticos de las mujeres. Para tal fin, los dos órdenes de gobierno y sus respectivos poderes, en el ámbito de sus competencias, deberán:\nI. Realizar las reformas necesarias a sus ordenamientos jurídicos a fin de garantizar a las mujeres una vida libre de violencia en el ámbito político, con disposiciones que garanticen la protección de las mujeres que incursionan en las actividades políticas y sancionen las acciones u omisiones que impidan o dificulten su participación.\nII. Establecer políticas públicas que garanticen a las mujeres el derecho a una vida libre de violencia en el ámbito político.\nIII. Establecer acciones a fin de que las mujeres conozcan y hagan uso de las político electorales y, si son víctimas de discriminación o violencia, denuncien, demanden, impugnen.\nIV. Documentar los casos de violencia contra las mujeres en la actividad política.\nV. Impulsar la investigación en el tema.\nVI. Procurar que en la designación de integrantes de los órganos colegiados de autoridad se encuentren representados de manera paritaria ambos géneros.\nNota: Se adicionó mediante decreto 126 de la LXI Legislatura, publicado en el P.O. del\nNota: Se reformó mediante decreto 254 de la LXII Legislatura, publicado en el P.O.\nTÍTULO TERCERO\nDEL SISTEMA ESTATAL PARA PREVENIR, ATENDER,\nMUJERES\nCAPÍTULO I\nDEL OBJETO E INTEGRACIÓN DEL SISTEMA ESTATAL\nARTÍCULO 17.- El Estado y los Municipios se coordinarán para establecer el Sistema\nEstatal para Prevenir, Atender, Sancionar y Erradicar la Violencia contra las Mujeres, el cual tiene por objeto la conjunción de esfuerzos, instrumentos, políticas, servicios y acciones interinstitucionales para la prevención, atención, sanción y erradicación de la violencia contra las mujeres.\nARTÍCULO 18.- El Sistema Estatal se conformará por los titulares, o las personas que estos designen de:\nI. La Secretaría General de Gobierno;\nII. La Secretaría de Desarrollo Social y Humano, quien lo presidirá;\nIII. La Secretaría de Seguridad Pública;\nIV. La Fiscalía General del Estado;\nV. La Secretaría de Educación;\nVI. La Secretaría de Salud;\nVII. El Instituto de la Mujer del Estado, quien ocupará la Secretaría Ejecutiva del\nSistema Estatal;\nVIII. DIF Estatal;\nIX. Los organismos y dependencias instituidos en el ámbito municipal para la las mujeres;\nX. La Delegación Estatal de la Comisión Nacional para el Desarrollo de los\nPueblos Indígenas;\nXI. El Instituto Electoral del Estado.\nNota: Se reformó mediante decreto 133 de la LXIII Legislatura, publicado en el P.O. del\nARTÍCULO 19.- La Secretaría Ejecutiva del Sistema Estatal elaborará el Reglamento para aprobación en su caso.\nCAPÍTULO II\nDEL PROGRAMA ESTATAL PARA PREVENIR, ATENDER,\nMUJERES\nARTÍCULO 20.- La formulación del Programa Estatal será coordinada por el Instituto\nEstatal de la Mujer. El Programa Estatal deberá ser congruente con el Plan Estatal de\nDesarrollo y el Plan Nacional de Desarrollo y contendrá las acciones con perspectiva de género para:\nI. Impulsar y fomentar el conocimiento y el respeto a los derechos humanos de las mujeres;\nII. Transformar los modelos socioculturales de conducta de mujeres y hombres, incluyendo la formulación de programas y acciones de educación formales y no formales, en todos los niveles educativos y de instrucción, con la finalidad de prevenir, atender y erradicar las conductas estereotipadas que permiten, fomentan y toleran la violencia contra las mujeres;\nIII. Educar y capacitar en materia de derechos humanos de las mujeres al personal encargado de la procuración de justicia, policías y demás funcionarios encargados de las políticas de prevención, atención, sanción y eliminación de la violencia contra las mujeres;\nIV. Promover la capacitación en materia de derechos humanos de las mujeres, al personal encargado de la impartición de justicia, a fin de dotarles de instrumentos que les permitan juzgar con perspectiva de género;\nV. Brindar los servicios especializados y gratuitos para la atención y protección a las víctimas, por medio de las autoridades y las instituciones públicas o privadas;\nVI. Fomentar y apoyar programas de educación pública y privada, destinados a concientizar a la sociedad sobre las causas y las consecuencias de la violencia contra las mujeres;\nVII. Diseñar programas de atención y capacitación a víctimas y victimarios que les permita participar plenamente en todos los ámbitos de la vida;\nVIII. Promover que los medios de comunicación no fomenten la violencia contra las mujeres y que favorezcan la erradicación de todos los tipos de violencia, mujeres;\nIX. Garantizar la investigación y la elaboración de diagnósticos estadísticos sobre las causas, la frecuencia y las consecuencias de la violencia contra las mujeres, con el fin de evaluar la eficacia de las medidas desarrolladas para prevenir, atender, sancionar y erradicar todo tipo de violencia;\nX. Publicar semestralmente la información general y estadística sobre los casos\nInformación sobre Casos de Violencia contra las Mujeres;\nXI. Promover la cultura de denuncia de la violencia contra las mujeres en el integridad; y\nXII. Diseñar un modelo integral de atención a los derechos humanos y ciudadanía de las mujeres que deberán instrumentar las instituciones, los centros de atención y los refugios que atiendan a víctimas.\nXIII. Vigilar que los usos y costumbres sociales no atenten contra los derechos humanos de las mujeres.\nNota: Se adicionó una fracción XIII mediante decreto 126 de la LXI Legislatura, publicado en el P.O. del gobierno del Estado No. 5502 de fecha 11 de junio de 2014.\nARTÍCULO 21.- Se procurará la participación de los sectores público, social y privado, especialmente de los organismos sociales en la formulación, ejecución y evaluación del\nPrograma Estatal.\nTÍTULO CUARTO\nDE LA COMPETENCIA EN MATERIA DE PREVENCIÓN,\nATENCIÓN Y ERRADICACIÓN DE LA VIOLENCIA EN CONTRA\nDE LAS MUJERES\nCAPÍTULO I\nDE LA COMPETENCIA ESTATAL\nARTÍCULO 22.- El Gobierno del Estado se coordinará con la Federación para integrar y consolidar el Sistema Nacional y participará en la formulación y ejecución del\nPrograma Nacional.\nAsimismo, adoptará todas las medidas y acciones previstas en la presente ley para prevenir, atender, sancionar y erradicar la violencia contra las mujeres.\nARTÍCULO 23.- Las dependencias y entes públicos estatales previstos en esta ley deberán:\nI. Tomar medidas y realizar las acciones necesarias, en coordinación con las demás autoridades del Sistema Estatal, para alcanzar los objetivos previstos en la presente ley;\nII. Ejecutar y dar seguimiento a las acciones del Programa Estatal, con la avanzar en la eliminación de la violencia contra las mujeres;\nIII. Impulsar la participación de los sectores sociales y privados y de las organizaciones sociales, en la ejecución del Programa Estatal;\nIV. Promover investigaciones sobre las causas y las consecuencias de la violencia contra las mujeres;\nV. Promover una cultura de respeto a los derechos humanos de las mujeres;\nVI. Promover ante las autoridades competentes la adopción de las medidas de la mujer que haya sido víctima de violencia;\nVII. Proporcionar a las instancias encargadas de realizar estadísticas, la información necesaria para la elaboración de éstas;\nVIII. Promover programas de información a la población en la materia;\nIX. Recibir de las organizaciones sociales propuestas y recomendaciones sobre la prevención, atención y sanción de la violencia contra mujeres, a fin de mejorar los mecanismos para su erradicación;\nX. Establecer, utilizar, supervisar y mantener todos los instrumentos y acciones encaminados al mejoramiento del Sistema y del Programa Estatales;\nXI. Impulsar la creación de refugios para la atención y protección de las víctimas, conforme al modelo de atención diseñado por el Sistema Estatal;\nXII. Difundir por todos los medios de comunicación el contenido de esta Ley;\nXIII. Celebrar convenios de cooperación, coordinación y concertación con los sectores públicos social y privado en la materia; y\nXIV. Las demás previstas en esta ley y en otras disposiciones aplicables.\nARTÍCULO 24.- La Secretaría General de Gobierno tendrá a su cargo:\nI. A propuesta del Instituto de la Mujer formular las bases de coordinación entre las autoridades estatales y municipales para la prevención, atención, sanción y erradicación de la violencia contra las mujeres;\nII. Coordinar y dar seguimiento a las acciones del Gobierno del Estado en materia de protección, atención, sanción y erradicación de la violencia contra las mujeres;\nIII. Coordinar y dar seguimiento a los trabajos de promoción y defensa de los derechos humanos de las mujeres, que lleven a cabo las dependencias y entidades de la administración pública estatal;\nIV. Realizar a través del Instituto de la Mujer, un diagnóstico estatal y otros estudios complementarios de manera periódica con perspectiva de género sobre todas las formas de violencia contra las mujeres, en todos los ámbitos, que proporcione información objetiva para la elaboración de políticas gubernamentales en materia de prevención, atención, sanción y erradicación de la violencia contra las mujeres;\nV. Derogada;\nVI. Las demás previstas en esta ley y en otras disposiciones aplicables.\nNota: Se reformó el primer párrafo y se derogó la fracción V mediante decreto 133 de la\nARTÍCULO 25.- La Secretaría de Desarrollo Social y Humano será la encargada de:\nI. Presidir el Sistema Estatal, así como fomentar el desarrollo social desde la perspectiva de género, para garantizarles una vida libre de violencia;\nII. Formular la política de desarrollo social del Estado considerando el adelanto de las mujeres y su plena participación en todos los ámbitos de la vida;\nIII. Promover políticas de igualdad de condiciones y oportunidades entre mujeres y hombres, para eliminar desventajas de género; y\nIV. Las demás previstas en esta ley y demás disposiciones aplicables.\nNota: Se reformó el primer párrafo y la fracción I mediante decreto 133 de la LXIII fecha 27 de mayo de 2020.\nARTÍCULO 26.- La Secretaría de Seguridad Pública, tendrá a su cargo:\nI. Diseñar la política integral para la prevención de delitos violentos contra las mujeres, en los ámbitos público y privado;\nII. Procurar la capacitación del personal de la policía que está bajo su mando para atender los casos de violencia contra las mujeres;\nIII. Establecer las acciones y medidas necesarias que para la reeducación de la sociedad mediante programas de prevención del delito; y\nIV. Las demás previstas en esta ley y en otras disposiciones aplicables.\nARTÍCULO 27.- Corresponderá a la Secretaría de Educación:\nI. Promover en las políticas educativas los principios de igualdad, equidad y no discriminación entre mujeres y hombres y el respeto pleno a los derechos humanos;\nII. Desarrollar programas educativos, en todos los niveles de escolaridad, que fomenten la cultura de una vida libre de violencia contra las mujeres, así como el respeto a su dignidad;\nIII. Garantizar el derecho de las mujeres a la educación, a la alfabetización y al acceso, permanencia y terminación de estudios en todos los niveles;\nIV. Fomentar el desarrollo de la investigación multidisciplinaria encaminada a crear modelos de detección de la violencia contra las mujeres en los centros educativos;\nV. Incorporar en los programas educativos, en todos los niveles de la instrucción, de competencia estatal, el respeto a los derechos humanos de las mujeres,\nVI. Diseñar y difundir materiales educativos que promuevan la prevención y atención de la violencia contra las mujeres;\nVII. Proporcionar acciones formativas a todo el personal de los centros educativos, en materia de derechos humanos de las mujeres y políticas de prevención, atención, sanción y erradicación de la violencia contra las mujeres; y\nVIII. Las demás previstas en esta ley y en otras disposiciones aplicables.\nNota: Se reformó el primer párrafo mediante decreto 133 de la LXIII Legislatura,\nARTÍCULO 28.- Corresponde a la Secretaría de Salud:\nI. Diseñar con perspectiva de género, la política de salud, considerando acciones de prevención y atención de la violencia en contra de las mujeres;\nII. Ejecutar con perspectiva de género la política de salud;\nIII. Capacitar al personal del sector salud para la detección de actos de violencia contra las mujeres, así como para la atención de las víctimas;\nIV. Difundir en las instituciones del sector salud, material referente a la prevención y atención de la violencia contra las mujeres;\nV. Canalizar a las víctimas a las instituciones que prestan atención y protección especializada a las mujeres, en su caso;\nVI. Apoyar a las autoridades encargadas de efectuar investigaciones en materia de violencia contra las mujeres, proporcionando la siguiente información:\na) El número de víctimas que se atiendan en los centros y servicios hospitalarios;\nb) Las situaciones de violencia que sufren las mujeres;\nc) El tipo de violencia por la cual se atendió a la víctima;\nd) Los efectos causados por la violencia en las mujeres; y\ne) Los recursos erogados en la atención de las víctimas.\nVII. Establecer programas y servicios profesionales y eficaces, con horario de veinticuatro horas en las dependencias públicas relacionadas con la atención de la violencia contra las mujeres;\nVIII. Brindar servicios reeducativos integrales a las víctimas y a los agresores, a fin de que logren estar en condiciones de participar plenamente en la vida pública, social y privada;\nIX. Participar activamente, en la ejecución del Programa, en el diseño de nuevos modelos de prevención, atención y erradicación de la violencia contra las mujeres, en colaboración con las demás autoridades encargadas de la aplicación de la presente ley;\nX. Asegurar que en la prestación de los servicios del sector salud sean respetados los derechos humanos de las mujeres;\nXI. Celebrar convenios de cooperación, coordinación y concertación en la materia,\nXII. Las demás previstas en esta ley y en otras disposiciones aplicables.\nNota: Se reformó la fracción VII y se adicionaron las fracciones VIII, IX, X, XI y XII mediante decreto 254 de la LXII Legislatura, publicado en el P.O. del gobierno del\nARTÍCULO 29.- Corresponde a la Fiscalía General del Estado, en materia de violencia en contra de las mujeres:\nI. Promover la formación y especialización de Agentes del Ministerio Público y derechos humanos de las mujeres;\nII. Proporcionar a las víctimas orientación y asesoría para su eficaz atención y protección;\nIII. Dictar las medidas necesarias para que la víctima reciba atención médica;\nIV. Brindar a las víctimas o al agresor, en su caso, la información integral sobre las instituciones públicas o privadas encargadas de su atención;\nV. Proporcionar a las instancias encargadas de realizar estadísticas las referencias necesarias sobre el número de víctimas atendidas;\nVI. Brindar protección para salvaguardar la integridad física de las mujeres que denuncien la violencia cometida en su contra; y\nVII. Las demás previstas en esta ley y en otras disposiciones aplicables.\nNota: Se reformó el primer párrafo mediante decreto 133 de la LXIII Legislatura, publicado en el P.O. del gobierno del Estado No. 1183 Tercera Sección de fecha 27 de mayo de 2020.\nARTÍCULO 30.- Corresponde al Instituto de la Mujer del Estado:\nI. Fungir como Secretaría Ejecutiva del Sistema Estatal, a través de su titular;\nII. Diseñar, la política integral con perspectiva de género orientada a la prevención, atención, sanción y erradicación de los delitos violentos contra las mujeres;\nIII. Coordinar la elaboración del Programa Estatal con las demás autoridades integrantes del Sistema Estatal;\nIV. Formular la propuesta para las bases de coordinación entre las autoridades estatales y municipales para la prevención, atención, sanción y erradicación de la violencia contra las mujeres;\nV. Realizar el diagnóstico estatal y otros estudios complementarios de manera contra las mujeres;\nVI. Organizar y mantener actualizado el Banco Estatal de Datos e Información sobre casos de violencia contra las mujeres en el que se integren, además de los casos señalados, las investigaciones realizadas por los sectores público, social y privado sobre las causas, características y consecuencias de la violencia en contra de las mujeres; las medidas de prevención, atención y erradicación adoptadas en esta materia y las evaluaciones de las mismas, así en el Estado los derechos humanos de las mujeres;\nVII. Proponer a las instancias encargadas de la aplicación de la presente ley, los programas, las medidas y las acciones que se requieran, a fin de erradicar la violencia contra las mujeres;\nVIII. Colaborar con las instituciones del Sistema Estatal en el diseño y evaluación del modelo de atención a víctimas en los refugios;\nIX. Canalizar a las víctimas a programas reeducativos integrales que les permitan participar activamente en la vida pública, privada y social;\nX. Promover y vigilar que la atención ofrecida en las diversas instituciones públicas o privadas, sea proporcionada por especialistas en la materia;\nXI. Difundir a través de diversos medios, los resultados del Sistema Estatal y del\nPrograma Estatal a los que se refiere esta ley; y\nXII. Las demás previstas en esta ley y en otras disposiciones aplicables.\nCAPÍTULO II\nDE LA COMPETENCIA DE LOS MUNICIPIOS\nARTÍCULO 31.- Corresponde a los Municipios, en materia de prevención, atención, sanción y erradicación de la violencia contra las mujeres:\nI. Coordinarse con el Gobierno del Estado en la adopción y consolidación del\nSistema Estatal;\nII. Instrumentar y articular, en concordancia con la política estatal, su política orientada a erradicar la violencia contra las mujeres;\nIII. Participar en la ejecución y evaluación de las acciones previstas en el\nPrograma Estatal;\nIV. Formular, ejecutar y evaluar el Programa Municipal de Prevención, Atención Sanción y Erradicación de la Violencia contra las Mujeres;\nV. Promover, en coordinación con el Gobierno del Estado, cursos de capacitación a las personas que atienden a víctimas;\nVI. Apoyar la creación de programas de reeducación integral para los agresores;\nVII. Promover programas educativos sobre la igualdad y la equidad entre los géneros para eliminar la violencia contra las mujeres;\nVIII. Apoyar la creación de refugios seguros para las víctimas;\nIX. Llevar a cabo programas de información a la población respecto de la violencia contra las mujeres;\nX. Celebrar convenios de coordinación y concertación con los sectores público, social y privado en la materia a que se refiere esta Ley; y\nXI. Las demás previstas en esta ley y en otras disposiciones aplicables.\nTÍTULO QUINTO\nDE LAS MEDIDAS DE PROTECCIÓN\nCAPÍTULO ÚNICO\nDE LAS ÓRDENES DE PROTECCIÓN\nARTÍCULO 32.- Las órdenes de protección son actos de urgente aplicación en función del interés superior de la víctima, son fundamentalmente precautorias y cautelares, Ministerio Público o por los órganos jurisdiccionales competentes, en el momento en delito o infracción, que ponga en riesgo la integridad, la libertad o la vida de las mujeres de algún tercero, tenga contacto de cualquier tipo o medio con la víctima.\nEn materia de violencia política de las mujeres en razón de género, el Instituto Electoral del Estado de Campeche y el Tribunal Electoral del Estado de Campeche, podrán solicitar a las autoridades competentes las medidas a que se refiere el presente capítulo.\nNota: Se adicionó un segundo párrafo mediante decreto 133 de la LXIII Legislatura, publicado en el P.O. del gobierno del Estado No. 1183 Tercera Sección de fecha 27 de mayo de 2020.\nNota: Se reformó el párrafo primero mediante decreto 227 de la LXIII Legislatura, publicado en el P.O. del gobierno del Estado No. 1446 Cuarta Sección de fecha 3 de junio de 2021.\nARTÍCULO 32 bis.- Quien en ejercicio de funciones públicas tenga conocimiento de la probable existencia de un hecho que la ley señale como delito en contra de una mujer o niña, está obligado a denunciarlo inmediatamente al Ministerio Público, proporcionándole todos los datos que tuviere, poniendo a su disposición a la persona imputada, si hubiere sido detenida en flagrancia.\nQuien tenga el deber jurídico de denunciar y no lo haga, será acreedor a las sanciones correspondientes.\nNota: Se adicionó mediante decreto 227 de la LXIII Legislatura, publicado en el P.O. del gobierno del Estado No. 1446 Cuarta Sección de fecha 3 de junio de 2021.\nARTÍCULO 32 ter.- Las órdenes de protección que señala la presente ley son personalísimas e intransferibles y podrán ser:\nI. Administrativas: que son emitidas por el Ministerio Público y las autoridades administrativas, y\nII. De naturaleza jurisdiccional: que son las emitidas por los órganos encargados de la administración de justicia.\nLas órdenes de protección tendrán una duración de hasta 60 días, prorrogables por 30 tardar dentro de las 4 horas siguientes al conocimiento de los hechos que las generan.\nNota: Se adicionó mediante decreto 227 de la LXIII Legislatura, publicado en el P.O.\nARTÍCULO 32 quater.- Las órdenes de protección se deberán dictar e implementar con base en los siguientes principios:\nI. Principio de protección: Considera primordial la vida, la integridad física, la libertad y la seguridad de las personas;\nII. Principio de necesidad y proporcionalidad: Las órdenes de protección deben destinataria, y deben garantizar su seguridad o reducir los riesgos existentes;\nIII. Principio de confidencialidad: Toda la información y actividad administrativa o jurisdiccional relacionada con el ámbito de protección de las personas, debe ser reservada para los fines de la investigación o del proceso respectivo;\nIV. Principio de oportunidad y eficacia: Las órdenes deben ser oportunas, específicas, adecuadas y eficientes para la protección de la víctima, y deben ser otorgadas e implementadas de manera inmediata y durante el tiempo que garanticen su objetivo;\nV. Principio de accesibilidad: Se deberá articular un procedimiento sencillo para que facilite a las víctimas obtener la protección inmediata que requiere su situación;\nVI. Principio de integralidad: El otorgamiento de la medida a favor de la víctima deberá generarse en un solo acto y de forma automática, y\nVII. Principio pro persona: Para interpretar lo referente al otorgamiento de las órdenes de protección, en caso de duda, con relación a la situación de violencia, se estará a lo más favorable para la víctima, tratándose de niñas siempre se garantizará que se cumpla en todas las decisiones que se tomen respecto de las órdenes de protección. De igual forma, cuando las determinaciones que se tomen respecto de una mujer víctima de violencia pudieran impactar en los derechos de las hijas o hijos menores de 18 años de edad.\nNota: Se adicionó mediante decreto 227 de la LXIII Legislatura, publicado en el P.O. del gobierno del Estado No. 1446 Cuarta Sección de fecha 3 de junio de 2021.\nARTÍCULO 32 quinquies.- Cuando una mujer o una niña víctima de violencia soliciten una orden de protección a la autoridad administrativa, ministerial y/o judicial, se le la propia orden.\nLa autoridad deberá informar con un lenguaje claro, sencillo y empático a la mujer víctima de violencia sobre su derecho a solicitar las órdenes de protección, y evitará cualquier información tendiente a inhibir o desincentivar la solicitud. Así también deberá realizar la medición y valoración del riesgo, la valoración médica en caso de requerirse, así como la valoración psicológica.\nNota: Se adicionó mediante decreto 227 de la LXIII Legislatura, publicado en el P.O. del\nARTÍCULO 32 sexies.- Para la emisión de las órdenes de protección las autoridades administrativas, el Ministerio Público o el órgano jurisdiccional competente tomará en consideración:\nI. Los hechos relatados por la mujer o la niña, en situación de violencia, conocimiento a la autoridad;\nII. Las peticiones explícitas de la mujer o la niña, en situación de violencia, considerando su desarrollo evolutivo y cognoscitivo o de quien informe sobre el hecho;\nIII. Las medidas que ella considere oportunas, una vez informada de cuáles pueden ser esas medidas. Tratándose de niñas, las medidas siempre serán determinadas conforme al principio del interés superior de la niñez;\nIV. Las necesidades que se deriven de su situación particular analizando su identidad de género, orientación sexual, raza, origen étnico, edad, nacionalidad, discapacidad, religión, así como cualquier otra condición relevante;\nV. La persistencia del riesgo aún después de su salida de un refugio temporal, y\nVI. La manifestación de actos o hechos previos de cualquier tipo de violencia que hubiese sufrido la víctima.\nAdemás, deberán ordenar la protección necesaria, atendiendo:\nI. Los principios establecidos en esta ley;\nII. Que sea adecuada, oportuna y proporcional;\nIII. Que los sistemas normativos propios basados en usos y costumbres no impidan la garantía de los derechos de las mujeres reconocidos en la Constitución Política de los Estados Unidos Mexicanos, así como en los tratados internacionales ratificados por el Estado Mexicano;\nIV. La discriminación y vulnerabilidad que viven las mujeres y las niñas por razón de identidad de género, orientación sexual, raza, origen étnico, edad, nacionalidad, discapacidad, religión o cualquiera otra, que las coloque en una situación de mayor riesgo, y\nV. Las necesidades expresadas por la mujer o niña solicitante.\nLas autoridades administrativas, el Ministerio Público y los órganos jurisdiccionales determinarán las órdenes de protección para denunciantes anónimas de violencia, privilegiando la integridad y la seguridad de las víctimas.\nNota: Se adicionó mediante decreto 227 de la LXIII Legislatura, publicado en el P.O.\nARTÍCULOS 32 septies.- Las órdenes de naturaleza jurisdiccional, además de las previstas en otros ordenamientos, podrán consistir en una o varias de las siguientes acciones:\nI. La reserva del domicilio, lugar de trabajo, profesión o cualquier otro dato que permita que a la persona agresora o su familia puedan ubicar a la víctima;\nII. El uso de medios o dispositivos electrónicos para impedir el contacto directo de la persona agresora con la víctima;\nIII. Entrega inmediata de objetos de uso personal y documentos de identidad de la víctima y en su caso, de sus hijas e hijos;\nIV. Medidas para evitar que se capten y/o se transmitan por cualquier medio o tecnologías de la información y la comunicación, imágenes de la mujer en situación de violencia que permitan su identificación o la de sus familiares.\nTratándose de niñas hay una prohibición absoluta de transmitir datos e imágenes que permitan su identificación;\nV. Prohibir el acceso a la persona agresora al domicilio, permanente o temporal de la mujer, o la niña, en situación de violencia, así como acercarse al lugar de trabajo, estudio o cualquier lugar que frecuente;\nVI. Embargo preventivo de bienes de la persona agresora, a efecto de garantizar las obligaciones alimentarias;\nVII. La desocupación por la persona agresora, del domicilio conyugal o de pareja, independientemente de la acreditación de propiedad o posesión del inmueble, aún en los casos de arrendamiento del mismo, y en su caso el reingreso de la mujer en situación de violencia una vez que se resguarde su seguridad;\nVIII. Obligación alimentaria provisional e inmediata;\nIX. La notificación al superior jerárquico inmediato, cuando la persona agresora sea servidora pública y en el ejercicio de su cargo, comisión o servicio, se le involucre en un hecho de violencia contra las mujeres.\nEsta orden será emitida en todos los casos donde la persona agresora pertenezca a los cuerpos policiacos o de seguridad, ya sea corporaciones públicas o privadas;\nX. La obligación de la persona agresora de presentarse periódicamente ante el órgano jurisdiccional que emitió la orden;\nXI. La prohibición a la persona agresora de salir sin autorización judicial del país o del ámbito territorial que fije el juez o la jueza, y\nXII. Las demás que se requieran para brindar una protección a la víctima.\nNota: Se adicionó mediante decreto 227 de la LXIII Legislatura, publicado en el P.O.\nARTÍCULO 32 octies.- Las autoridades competentes deberán de establecer los coordinación con las instancias responsables de atenderlas e implementarlas.\nNota: Se adicionó mediante decreto 227 de la LXIII Legislatura, publicado en el P.O.\nARTÍCULO 32 novies.- La tramitación y otorgamiento de una orden de protección podrá contener una o varias medidas, atendiendo al principio de integralidad. No se necesita una orden para cada medida, una sola orden de protección podrá concentrar en situación de violencia y en su caso de las víctimas indirectas.\nNota: Se adicionó mediante decreto 227 de la LXIII Legislatura, publicado en el P.O.\nARTÍCULO 32 decies.- Las órdenes de protección deberán ser evaluadas para modificarse o adecuarse, en caso de que al momento de evaluar la efectividad de la orden se detecten irregularidades o incumplimiento, se sustanciará la comunicación correspondiente a los órganos internos de control de las dependencias involucradas.\nPrevio a la suspensión de las órdenes de protección decretadas, las autoridades administrativas, ministeriales y órganos jurisdiccionales deberán asegurarse bajo su más estricta responsabilidad que la situación de riesgo o peligro de la víctima ha cesado, realizando una nueva evaluación de riesgo y analizando los informes de implementación por parte de las autoridades responsables de su cumplimiento.\nNota: Se adicionó mediante decreto 227 de la LXIII Legislatura, publicado en el P.O. del gobierno del Estado No. 1446 Cuarta Sección de fecha 3 de junio de 2021.\nARTÍCULO 32 undecies.- En los casos donde la persona agresora pertenezca a los cuerpos policiacos o de seguridad, ya sea de corporaciones públicas o privadas, la autoridad deberá retirar el arma de cargo o de cualquier otra que tenga registrada.\nNota: Se adicionó mediante decreto 227 de la LXIII Legislatura, publicado en el P.O. del gobierno del Estado No. 1446 Cuarta Sección de fecha 3 de junio de 2021.\nARTÍCULO 32 duodecies.- Al momento de dictarse sentencia las autoridades judiciales competentes determinarán las órdenes de protección y medidas similares que deban dictarse de manera temporal o durante el tiempo que dure la sentencia.\nLas órdenes de protección podrán ser dictadas de oficio o a solicitud de la mujer en situación de violencia, de su representante legal o del Ministerio Público, tratándose de niñas víctimas de un delito, la autoridad judicial se encuentra obligada a hacer la determinación del interés superior de la niñez, a fin de dictar órdenes de protección, aun cuando no exista una solicitud.\nNota: Se adicionó mediante decreto 227 de la LXIII Legislatura, publicado en el P.O.\nARTÍCULO 32 ter decies.- Por ninguna circunstancia las autoridades administrativas, el agresora a través de la víctima. Cualquier notificación es responsabilidad exclusiva de la autoridad.\nLas autoridades que intervengan en el cumplimiento de una orden, también serán las periódica.\nNota: Se adicionó mediante decreto 227 de la LXIII Legislatura, publicado en el P.O.\nARTÍCULO 32 quater decies.- A ninguna mujer o niña y sus hijas e hijos en situación de violencia que solicite orden de protección, se le podrá requerir que acredite su situación migratoria, ni cualquier otro elemento que impida su derecho al acceso a la justicia y la protección.\nNota: Se adicionó mediante decreto 227 de la LXIII Legislatura, publicado en el P.O.\nARTÍCULO 32 quinquies decies.- La Procuraduría de Protección de los Derechos de\nNiñas, Niños y Adolescentes del Estado de Campeche, deberán solicitar las órdenes de protección a las autoridades correspondientes de manera oficiosa de conformidad con las disposiciones normativas aplicables.\nNota: Se adicionó mediante decreto 227 de la LXIII Legislatura, publicado en el P.O. del gobierno del Estado No. 1446 Cuarta Sección de fecha 3 de junio de 2021.\nARTÍCULO 32 sexies decies.- En caso de que la persona agresora incumpla la orden de protección, se emitirán las medidas de apremio conforme a la legislación aplicable.\nAsimismo, se reforzarán las acciones que se contemplaron en un primer momento con la finalidad de salvaguardar la vida y seguridad de las mujeres y niñas.\nNota: Se adicionó mediante decreto 227 de la LXIII Legislatura, publicado en el P.O. del gobierno del Estado No. 1446 Cuarta Sección de fecha 3 de junio de 2021.\nTÍTULO SEXTO\nDE LA ATENCIÓN A VÍCTIMAS Y DE LOS REFUGIOS\nCAPÍTULO I\nDE LA ATENCIÓN A VÍCTIMAS\nARTÍCULO 33.- Las víctimas de cualquier tipo de violencia tendrán los derechos siguientes:\nI. Ser tratada con respeto a su integridad y al ejercicio pleno de sus derechos;\nII. Contar con protección inmediata y efectiva por parte de las autoridades;\nIII. Recibir información veraz y suficiente que les permita decidir sobre las opciones de atención;\nIV. Contar con asesoría jurídica gratuita y expedita;\nV. Recibir información y atención médica y psicológica;\nVI. Ser aceptada en un refugio, mientras lo necesite;\nVII. Ser valoradas y educadas libres de estereotipos de comportamiento y subordinación;\nVIII. En los casos de violencia familiar, las mujeres que tengan hijas y/o hijos podrán acudir a los refugios con éstos; y\nIX. Los demás señalados en esta ley y otras disposiciones legales.\nARTÍCULO 34.- Las autoridades estatales y municipales, en el ámbito de sus respectivas competencias, según corresponda, deberán adoptar las medidas y acciones necesarias para brindar protección, atención médica psicológica y jurídica y demás servicios que requiera la mujer víctima de violencia, incluyendo su canalización a los refugios cuando necesite de un mayor tiempo para su recuperación.\nARTÍCULO 35.- El agresor deberá participar obligatoriamente en los programas de reeducación integral, cuando se le determine por mandato de autoridad competente.\nCAPÍTULO II\nDE LOS REFUGIOS PARA LAS VÍCTIMAS\nARTÍCULO 36.- El Estado y los Municipios se coordinarán con los diversos sectores social y privado para impulsar la creación de refugios para la atención a las víctimas de violencia.\nLos refugios que se constituyan, desde la perspectiva de género tendrán a su cargo:\nI. Participar en la aplicación del Programa Estatal;\nII. Velar por la seguridad de las mujeres que se encuentren en ellos;\nIII. Proporcionar a las mujeres la atención necesaria para su recuperación física y psicológica, que les permita participar plenamente en la vida pública, social y privada;\nIV. Dar información a las víctimas sobre las instituciones encargadas de prestar asesoría jurídica gratuita;\nV. Brindar a las víctimas la información necesaria que les permita decidir sobre las opciones de atención; y\nVI. Realizar todas aquellas inherentes a la prevención, protección y atención de las personas que se encuentren en ellos.\nvíctimas.\npor ejercer algún tipo de violencia.\nviolencia.\nNota: Se adicionó un párrafo quinto mediante decreto 133 de la LXIII Legislatura,\nARTÍCULO 37.- Los refugios deberán ser lugares seguros para las víctimas, por lo que no se podrá proporcionar su ubicación a personas no autorizadas para acudir a ellos.\nARTÍCULO 38.- La permanencia de las víctimas en los refugios durará mientras persista su inestabilidad física, psicológica o su situación de riesgo.\nARTÍCULO 39.- En ningún caso se podrá mantener a las víctimas en los refugios en contra de su voluntad.\nARTÍCULO 40.- El Gobierno del Estado y los Municipios, con la participación que corresponda de los sectores social y privado, promoverán el establecimiento de mecanismos que permitan proveer de los apoyos necesarios para que los refugios cumplan con su objeto.\nLEY APROBADA POR UNANIMIDAD Y EXPEDIDA POR DECRETO NÚM. 65, P.O. 3835,\n04/JULIO/2007. LIX LEGISLATURA.\nPRIMERO.- La presente ley entrará en vigor pleno el día primero de enero del dos mil ocho, previa su publicación en el Periódico Oficial del Estado.\nSEGUNDO.- El reglamento de esta ley se expedirá dentro de los noventa días posteriores a la entrada en vigor de este decreto.\nTERCERO.- El Sistema Estatal para Prevenir, Atender, Sancionar y Erradicar la Violencia contra las Mujeres, se instalará dentro de los treinta días siguientes a la entrada en vigor de la presente ley.\nCUARTO.- El Reglamento del Sistema Estatal, se expedirá dentro de los sesenta días siguientes a la fecha de su instalación.\nQUINTO.- Para los efectos señalados en los transitorios segundo, tercero y cuarto, la del Estado.\nSEXTO.- Los recursos que se requieran para dar debido cumplimiento a las disposiciones de esta ley, se cubrirán con cargo al presupuesto autorizado a las\nMunicipios, para el presente ejercicio fiscal y los subsecuentes, asimismo no requerirán misma ley.\nSÉPTIMO.- Se derogan todas aquellas disposiciones legales y reglamentarias en todo lo que se opongan al contenido del presente decreto.\nDado en el Salón de Sesiones del Palacio Legislativo, en la ciudad de San Francisco de\nCampeche, Campeche, a los diecinueve días del mes de junio del año dos mil siete.\nC. Oscar Román Rosas González, Diputado Presidente.- C. Jorge Isaac Brown\nFiligrana, Diputado Secretario.- C. Gloria Aguilar de Ita, Diputada Secretaria.Rúbricas.\nEn cumplimiento de lo dispuesto por los artículos 48, 49 y 71 fracción XVIII de la para su debida observancia.\nDado en el Palacio de Gobierno del Estado, en San Francisco de Campeche, Campeche, a los veintidós días del mes de junio del año dos mil siete.- EL GOBERNADOR\nCONSTITUCIONAL DEL ESTADO, C.P. JORGE CARLOS HURTADO VALDEZ.- EL\nSECRETARIO DE GOBIERNO, M. en D. RICARDO MEDINA FARFAN.- RUBRICAS.\nDECRETO No. 254, QUE REFORMÓ LA FRACCIÓN II Y ADICIONÓ LAS FRACCIONES\nIV, V, VI Y VII AL ARTÍCULO 2 Y, SE ADICIONÓ LOS ARTÍCULOS 2 BIS Y 2 TER,\nEXPEDIDO POR LA LX LEGISLATURA, PUBLICADO EN P.O. DEL GOBIERNO DEL\nESTADO No. 5119 DE FECHA 14 DE NOVIEMBRE DEL 2012.\nPRIMERO.- El presente decreto entrará en vigor tres días después de su publicación en el Periódico Oficial del Estado.\nSEGUNDO.- Se derogan todas las disposiciones legales y reglamentarias en lo que se opongan al contenido del presente decreto.\nDado en el Salón de Sesiones del recinto alterno del Congreso del Estado, en la ciudad de San Francisco de Campeche, Campeche, a los veintidós días del mes de agosto del año dos mil doce.- C. Jorge Luis González Curi, Diputado Presidente.- C. Carlos Alberto\nArjona Gutiérrez, Diputado Secretario.- C. Ramón Cuauhtémoc Santini Cobos, Diputado\nEn cumplimiento de lo dispuesto por los artículos 48, 49 y 71 fracción XVIII de la su debida observancia.\na los veintisiete días del mes de agosto del año dos mil doce. EL GOBERNADOR\nCONSTITUCIONAL DEL ESTADO, LIC. LIC. FERNANDO EUTIMIO ORTEGA BERNES.LA SUBSECRETARIA “A” DE GOBIERNO ENCARGADA DEL DESPACHO DE LA\nSECRETARIA DE GOBIERNO, MTRA. PERLA KARINA CASTRO FARIAS.- RÚBRICAS.\nDECRETO 126, QUE REFORMÓ LA FRACCIÓN VI Y ADICIONÓ UNA FRACCIÓN VII DEL\nARTÍCULO 5, LA FRACCIÓN XIII AL ARTÍCULO 20 Y UN CAPÍTULO V BIS AL TITULO\nSEGUNDO, EXPEDIDO POR LA LXI LEGISLATURA, PUBLICADO EN EL P.O. DEL\nTRANSITORIOS\nPRIMERO.- El presente decreto entrará en vigor a los tres días siguientes de su publicación en el Periódico Oficial del Estado.\nSEGUNDO.- Se derogan todas las disposiciones legales y reglamentarias que se opongan al contenido del presente decreto.\nDado en el Salón de Sesiones del Palacio Legislativo, en la ciudad de San Francisco de\nCampeche, Campeche, a los tres días del mes de abril del año dos mil catorce. C.\nFrancisco Elías Romellón Herrera, Diputado Presidente.- C. Miguel Ángel García\nEscalante, Diputado Secretario.- C. Ana María López Hernández, Diputada\nSecretaria.\nDECRETO 255, QUE REFORMÓ LA FRACCIÓN VII Y ADICIONÓ UNA FRACCIÓN VIII AL\nARTÍCULO 5, EXPEDIDO POR LA LXI LEGISLATURA, PUBLICADO EN EL P.O. DEL\nGOBIERNO DEL ESTADO NO. 5778 DE FECHA 21 DE JULIO DE 2015.\nTRANSITORIOS\nPRIMERO.- El presente decreto entrará en vigor quince días después de su publicación en el Periódico Oficial del Estado.\nSEGUNDO.- Se derogan todas las disposiciones legales y reglamentarias que se opongan al contenido del presente decreto.\nDado en el Salón de Sesiones del Palacio Legislativo, en la ciudad de San\nFrancisco de Campeche, Campeche, a los veinticinco días del mes de junio del año dos mil quince.\nC. José Adalberto Canto Sosa, Diputado Presidente.-, C. José Eduardo Bravo Negrín\nDiputado Secretario.-, C. Oscar Eduardo Uc Dzul Diputado Secretario.- Rúbricas.- - - DECRETO 254, QUE REFORMÓ EL ARTÍCULO 16 TER; LA FRACCIÓN VII Y SE\nADICIONÓ LAS FRACCIONES VIII, IX, X, XI Y XII AL ARTÍCULO 28, EXPEDIDO POR LA\nLXII LEGISLATURA, PUBLICADO EN EL PERIÓDIO OFICIAL DEL ESTADO No. 0626\nTRANSITORIOS\nPRIMERO.- El presente decreto entrará en vigor a los tres días siguientes al de su publicación en el Periódico Oficial del Estado.\nSEGUNDO.- Se derogan todas las disposiciones legales que se opongan al presente decreto.\nDado en el Salón de Sesiones del Palacio Legislativo, en la ciudad de San Francisco de\nCampeche, Campeche, a los seis días del mes de febrero del año dos mil dieciocho.\nC. Carlos Ramiro Sosa Pacheco, Diputado Presidente.- C. Marina Sánchez Rodríguez\nDiputada Secretaria.- C. María del Carmen Pérez López Diputada Secretaria.DECRETO 133, QUE REFORMÓ LAS FRACCIONES VI Y VIII DEL ARTÍCULO 5; LA\nDENOMINACIÓN DEL CAPÍTULO V BIS “DE LA VIOLENCIA POLÍTICA CONTRA LAS\nMUJERES” DEL TÍTULO SEGUNDO PARA QUEDAR COMO “DE LA VIOLENCIA\nPOLÍTICA CONTRA LAS MUJERES EN RAZÓN DE GÉNERO”; LOS ARTÍCULOS 16 BIS Y\n18; EL PRIMER PÁRRAFO DEL ARTÍCULO 24; EL PRIMER PÁRRAFO Y LA FRACCIÓN I\nDEL ARTÍCULO 25; EL PRIMER PÁRRAFO DEL ARTÍCULO 27 Y EL PRIMER PÁRRAFO\nDEL ARTÍCULO 29; ASÍ COMO SE ADICIONA UNA FRACCIÓN IX AL ARTÍCULO 5; LOS\nPÁRRAFOS SEGUNDO Y TERCERO AL ARTÍCULO 9; UN SEGUNDO PÁRRAFO AL\nARTÍCULO 32 Y UN PÁRRAFO QUINTO AL ARTÍCULO 36 Y, SE DEROGA LA FRACCIÓN\nV DEL ARTÍCULO 24 TODOS DE LA LEY DE ACCESO DE LAS MUJERES A UNA VIDA\nLIBRE DE VIOLENCIA DEL ESTADO DE CAMPECHE, EXPEDIDO POR LA LXIII\nLEGISLATURA, PUBLICADO EN EL PERIÓDICO OFICIAL DEL ESTADO No. 1183\nTERCERA SECCIÓN DE FECHA 27 DE MAYO DE 2020.\nTRANSITORIOS\nPrimero.- El presente decreto entrará en vigor a los tres días después de su publicación en el Periódico Oficial del Estado.\nSegundo.- Los municipios del Estado, en la medida de sus posibilidades deberán hacer ajustes presupuestarios necesarios para la aplicación de lo dispuesto en el párrafo quinto del artículo 36 del presente decreto.\nTercero.- Se derogan todas las disposiciones legales y reglamentarias del marco jurídico estatal, en lo que se opongan al contenido del presente decreto.\nDado en el Salón de Sesiones del Palacio Legislativo, en la ciudad de San Francisco de\nCampeche, Campeche, a los veintiséis días del mes de mayo del año dos mil veinte.\nC. Celia Rodríguez Gil, Diputada Presidenta.- C. Rigoberto Figueroa Ortiz, Diputado Secretario.- C. Óscar Eduardo Uc Dzul, Diputado Secretario.- Rúbricas.- - - DECRETO 227, QUE REFORMÓ EL PÁRRAFO PRIMERO DEL ARTÍCULO 32 Y SE\nADICIONARON LOS ARTÍCULOS 32 BIS; 32 TER; 32 QUATER; 32 QUINQUIES; 32\nSEXIES; 32 SEPTIES; 32 OCTIES; 32 NOVIES; 32 DECIES; 32 UNDECIES; 32\nDUODECIES; 32 TER DECIES; 32 QUATER DECIES; 32 QUINQUIES DECIES; 32 SEXIES\nDEL ESTADO DE CAMPECHE, EXPEDIDO POR LA LXIII LEGISLATURA, PUBLICADO\nTRANSITORIOS\nPrimero. El presente decreto entrará en vigor a los quince días después de su publicación en el Periódico Oficial del Estado.\nSegundo. Se derogan todas las disposiciones legales y reglamentarias del marco jurídico estatal, en lo que se opongan al contenido del presente decreto.\nDado en el Salón de Sesiones del Palacio Legislativo, en la ciudad de San\nFrancisco de Campeche, Campeche, a los diecinueve días del mes de mayo del año dos mil veintiuno.\nC. Leonor Elena Piña Sabido, Diputada Presidenta.- C. Óscar Eduardo Uc Dzul, Diputado Secretario.- C. Alvar Eduardo Ortiz Azar, Diputado Secretario.- Rúbricas.- - -",
  "ordenamiento": "REGLAMENTO",
  "jurisdiccion": "CAMPECHE",
  "fuente_oficial": "DIARIO OFICIAL DE LA FEDERACION",
  "Fecha de Publicación": "14 de noviembre de 2012",
  "es_escaneado": false,
  "tiene_tablas": false,
  "materia": [
    "género",
    "municipal"
  ]
}