{
  "titulo": "Acuerdo por el Que Se Crea el Programa Fortalecimiento de Culturas de los Pueblos Indígenas y Afrome",
  "Contenido": "REGLAS DE OPERACIÓN PARA EL EJERCICIO FISCAL\nPROGRAMA FORTALECIMIENTO, PRESERVACIÓN Y DIFUSIÓN DE LA CULTURA DE LOS PUEBLOS\nINDÍGENAS Y AFROMEXICANO, Y SE EMITEN SUS REGLAS DE OPERACIÓN, PUBLICADO EN EL PERIÓDICO\nOFICIAL DEL GOBIERNO DEL ESTADO No. 32 ALCANCE IV, EL VIERNES 19 DE ABRIL DE 2024.\n|\nTEXTO ORIGINAL.\nAcuerdo publicado en el Periódico Oficial del Gobierno del Estado No. 33 Alcance II, el Martes 25 de Abril de 2023.\nACUERDO POR EL QUE SE CREA EL PROGRAMA FORTALECIMIENTO DE CULTURAS DE\nLOS PUEBLOS INDÍGENAS Y AFROMEXICANOS, Y SE EMITEN SUS REGLAS DE OPERACIÓN\nPARA EL EJERCICIO FISCAL 2023.\nGuerrero. - Poder Ejecutivo.\nMAESTRA EVELYN CECIA SALGADO PINEDA, GOBERNADORA CONSTITUCIONAL DEL ESTADO\nDE GUERRERO, CON FUNDAMENTO EN LO DISPUESTO POR LOS ARTÍCULOS 71, 87, 88, 90\nLOS ARTÍCULOS 2, 4, 8, 9, 14, 22 APARTADO A FRACCIONES I Y XIV, 23 FRACCIÓN III Y 35\nFRACCIONES IV Y XII DE LA LEY ORGÁNICA DE LA ADMINISTRACIÓN PÚBLICA DEL ESTADO DE\nGUERRERO 242; 1, 2 FRACCIÓN I, 18 Y 25 DE LA LEY NÚMERO 454 DE PRESUPUESTO Y\nDISCIPLINA FISCAL DEL ESTADO DE GUERRERO; 7 DE LA LEY NÚMERO 701 DE\nRECONOCIMIENTO, DERECHOS Y CULTURA DE LOS PUEBLOS Y COMUNIDADES INDÍGENAS DEL\nESTADO DE GUERRERO; EN RELACIÓN CON EL ARTÍCULO 47 Y ANEXOS 23 (E14) Y 23-A DEL\nDECRETO NÚMERO 424 DEL PRESUPUESTO DE EGRESOS DEL ESTADO DE GUERRERO PARA\nEL EJERCICIO FISCAL 2023, Y LOS LINEAMIENTOS PARA LA ELABORACIÓN DE LAS REGLAS DE\nOPERACIÓN DE LOS PROGRAMAS SOCIALES ESTATALES PARA EL PERIODO 2022-2027.\nQue el Plan Nacional de Desarrollo 2019-2024 en el apartado de Política y Gobierno incluye Recuperar el\nEstado de Derecho y Libertad e Igualdad, la Política Social en Construir con un país de bienestar, y\nEconomía con Proyectos regionales de Autosuficiencia alimentaria y rescate del campo.\nQue el Plan Estatal de Desarrollo 2022-2027 en el apartado de Pueblos Originarios y Afromexicano señala de los mismos.\nQue la política estatal con el lema “Transformando Guerrero”, tiene la firme convicción de combatir de manera frontal los rezagos históricos que ha padecido el estado de Guerrero, bajo los principios de la\nREGLAS DE OPERACIÓN PARA EL EJERCICIO FISCAL\nCuarta Transformación. Estos propósitos sólo se pueden lograr, escuchando las voces de los más necesitados del medio rural; promoviendo y fortaleciendo el desarrollo de capacidades de las y los habitantes que han sobrevivido con grandes carencias. de los pueblos indígenas y afromexicanos.\nQue el gobierno del estado de Guerrero tiene entre sus prioridades de impulsar, reconocer, valorar, promover y difundir las culturas indígenas vivas en todas sus expresiones y como parte esencial de la identidad y la cultura, así como fortalecer la difusión entre los jóvenes, de las lenguas originarias de las comunidades indígenas, con el fin de preservar nuestra identidad cultural.\nQue Guerrero es un ejemplo vivo de las desigualdades sociales y económicas prevalecientes en nuestro país, dentro de ellas, la desigualdad de género que es una de las brechas de mayor amplitud. Muestra de ello; es la ola de violencia en contra de los derechos de las mujeres. Los feminicidios, el acoso, la discriminación laboral y la exclusividad de los quehaceres del hogar, así como del cuidado familiar, son la evidencia de una sociedad que ve en las mujeres a personas de segunda clase, incapaces de ejercer libremente sus derechos. Por ende, la perspectiva de género es un factor de aplicación transversal en este proyecto de Presupuesto de Egresos. La visión de futuro para nuestro estado es de derechos e inclusión, siendo una de las prioridades contribuir a reducir las carencias sociales, entre las que destacan la educativa con 23.7 por ciento en esta condición, servicios de salud con 13.8 por ciento, carencia de acceso a la seguridad social con 75.6 por ciento y carencia alimentaria con 27.8 por ciento. Por lo que la alimentación, educación, salud, seguridad social son los principales indicadores por mejorar.\nQue como lo establece la Constitución Política de los Estados Unidos Mexicanos la mujer y el hombre son iguales ante la ley; la cual protegerá la organización y el desarrollo de la familia. En este sentido, el Proyecto de Presupuesto de Egresos 2023 tiene como objetivo contribuir a cimentar las bases para la disminución de la pobreza y traer paz a las familias guerrerenses. Pobreza y violencia son, sin duda, el resultado de gobiernos con poca sensibilidad social. Por lo que, la transparencia, la honestidad, la austeridad republicana, el combate a la corrupción y la eficiencia en el ejercicio del gasto son ejes fundamentales que le dan sustento. Por consiguiente, la visión de futuro para nuestro estado es de derechos e inclusión, por lo que una de las prioridades es contribuir a reducir las carencias sociales.\nQue mediante la Ley Orgánica de la Administración Pública del Estado de Guerrero Número 433, publicada\nIndígenas, con el propósito de proteger y preservar los derechos y cultura de las comunidades indígenas, dependencias federales, estatales y municipales, dirigidos a promover el desarrollo integral de las y los indígenas, correspondiéndole el despacho entre otros asuntos, el de promover el respeto de los derechos, lengua y cultura de las comunidades indígenas. De acuerdo a la Ley Orgánica de la Administración Pública del Estado de Guerrero Número 242, actualmente, la secretaría es llamada Secretaría para el Desarrollo de las Comunidades y Pueblos Indígenas y Afromexicanos.\nREGLAS DE OPERACIÓN PARA EL EJERCICIO FISCAL\nQue el artículo 35 de la Ley Orgánica de la Administración Pública del Estado de Guerrero Número 242, establece que la Secretaría para el Desarrollo de las Comunidades y Pueblos Indígenas y Afromexicanos, es el órgano encargado de promover, respetar, vigilar y garantizar el reconocimiento pleno y el ejercicio de los derechos de los pueblos y comunidades indígenas y afromexicanas, reconocidos en la Constitución\nFederal, los instrumentos jurídicos internacionales y las leyes locales.\nDentro de algunas de sus atribuciones que le confieren se describe que es la encargada de Instrumentar, coordinar y ejecutar programas y acciones, para el desarrollo económico, social y cultural de los pueblos y comunidades indígenas y afromexicanas.\nQue las personas titulares de las Secretarías, Dependencias y Entidades de la Administración Pública\nEstatal, así como, las servidoras y servidores públicos autorizados para ejercer recursos públicos del presupuesto de inversión de las mismas, serán responsables de los programas y proyectos de inversión que realicen, las cuales deberán sujetarse a criterios de objetividad, equidad, transparencia, publicidad, selectividad y temporalidad.\nQue el artículo 47 del Decreto Número 424 del Presupuesto de Egresos del Estado de Guerrero para el\nEjercicio Fiscal 2023, establece que con el objeto de asegurar la aplicación eficiente, eficaz, oportuna, equitativa y transparente de los recursos públicos, la Secretaría de Finanzas y Administración y la\nSecretaría de Planeación y Desarrollo Regional, emitirán las disposiciones a que deberán sujetarse los programas de inversión sujetos a Reglas de Operación.\nQue la Secretaría de Planeación y Desarrollo Regional, expidió los Lineamientos para la Elaboración de las Reglas de Operación de los Programas Sociales Estatales, para el periodo 2022-2027, publicadas en el Periódico Oficial del Gobierno del Estado número 14 de fecha 18 de febrero de 2022; los cuales, tienen la finalidad de ser un instrumento técnico que guie la elaboración de los apartados centrales de las reglas de operación, así como los elementos para integrar su contenido.\nQue el gobierno del estado de Guerrero, a través de la Secretaría para el Desarrollo de las Comunidades y Pueblos Indígenas y Afromexicanos, ejecutará para este ejercicio fiscal 2023, el Programa\nFortalecimiento de Culturas de los Pueblos Indígenas y Afromexicanos, con el objetivo de impulsar de los pueblos y comunidades indígenas y afromexicanas, para propiciar el reconocimiento de la diversidad y un diálogo intercultural entre la sociedad Guerrerense.\nPor lo anteriormente expuesto y con fundamento en las disposiciones legales antes citadas, he tenido a bien expedir el siguiente:\nPUEBLOS INDÍGENAS Y AFROMEXICANOS, Y SE EMITEN SUS REGLAS DE OPERACIÓN PARA EL\nEJERCICIO FISCAL 2023.\nREGLAS DE OPERACIÓN PARA EL EJERCICIO FISCAL\nArtículo 1. Se crea el Programa Fortalecimiento de Culturas de los Pueblos Indígenas y Afromexicanos cultural y las identidades de los pueblos indígenas y afromexicanos, para propiciar el reconocimiento de la diversidad y un diálogo intercultural entre la sociedad guerrerense.\nArtículo 2. La Secretaría para el Desarrollo de las Comunidades y Pueblos Indígenas y Afromexicanos, tendrá a su cargo la implementación, ejecución, evaluación y administración del Programa Fortalecimiento de Culturas de los Pueblos Indígenas y Afromexicanos, bajo los criterios de objetividad, equidad, transparencia, publicidad, selectividad y temporalidad, con estricto apego a la normatividad aplicable, siendo la encargada de la dispersión y asignación de los recursos del Programa, apegándose plenamente a las Reglas de Operación.\nArtículo 3. Se emiten las Reglas de Operación del Programa Fortalecimiento de Culturas de los Pueblos\nIndígenas y Afromexicanos, que se establece los principios de eficiencia, eficacia, oportunidad, equitativa y transparencia de los recursos públicos y requisitos que se deben de cumplir para poder acceder ha dicho\nPrograma, en los términos siguientes:\nREGLAS DE OPERACIÓN DEL PROGRAMA FORTALECIMIENTO DE CULTURAS DE LOS PUEBLOS\nINDÍGENAS Y AFROMEXICANOS.\n1. Introducción.\n1.1. Antecedentes.\nDesde la antigüedad Guerrero ha sido y sigue siendo una amalgama de pueblos, razas, idiomas, culturas y costumbres, en las que han residido y se han desarrollado lo mismo la cultura olmeca y la teotihuacana, que la mixteca, la náhuatl y sobre todo la Cultura Mezcala, la cual ha sido nuestro principal y singular aporte al mundo mesoamericano y a la posteridad. Antes de la conquista, ya habitaban en Guerrero los pueblos\nMixteco, Amuzgo, Náhuatl y los Tlapanecos de Tlapa y Yopitzingo; y desde los primeros tiempos de la\nColonia, los pueblos afromestizos de la Costa, los cuales constituyen nuestra tercera raíz.\nPor naturaleza, historia y destino Guerrero es un estado pluriétnico y multicultural, que se nutre y enriquece de su propia diversidad y de la asimilación crítica de la cultura universal. De ahí, que la resistencia de los pueblos y comunidades indígenas y afromestizas en defensa de sus derechos y libertades, tenga tan hondas raíces en esta suriana entidad. Durante todo el siglo XX se continuó considerando a los pueblos indígenas como objeto de políticas proteccionistas y asistencialistas. Ahora en pleno siglo XXI el Ejecutivo indolencia–se niegan a reconocer a los pueblos indígenas como sujetos de derecho público con personalidad jurídica y patrimonio propios y con pleno derecho a la autonomía y la libre determinación, como vivían hasta la reforma.\nLa Constitución Política de los Estados Unidos Mexicanos, precisa en su artículo 2o, que la Nación\nMexicana es única e indivisible; que, asimismo, tiene una composición pluricultural sustentada\nREGLAS DE OPERACIÓN PARA EL EJERCICIO FISCAL originalmente en sus pueblos indígenas; y que la conciencia de su identidad indígena deberá ser criterio fundamental para determinar a quienes se aplican las disposiciones sobre pueblos indígenas. La misma\nConstitución, en el artículo en cita, expresa que son comunidades integrantes de un pueblo indígena aquellas que formen una unidad social, económica y cultural, asentadas en un territorio y que reconocen autoridades propias de acuerdo con sus usos y costumbres, y que el derecho de los pueblos indígenas a la libre determinación se ejercerá en un marco constitucional de autonomía que asegure la unidad nacional; reconocimiento que se hará, en las constituciones y leyes de las entidades federativas, en las cuales se establecerán las características que mejor expresen las situaciones y aspiraciones de los pueblos indígenas en cada entidad, así como las normas para su reconocimiento, el establecimiento de las instituciones y las políticas necesarias para garantizar la vigencia de sus derechos y el desarrollo integral de sus pueblos y comunidades como entidades de interés público.\nCon la implementación del Programa Fortalecimiento de Culturas de los Pueblos Indígenas y\nAfromexicanos, el gobierno del estado de Guerrero concreta una política de reconocimiento a los pueblos indígenas y afromexicano, a través del cumplimiento de sus derechos, relacionados con la preservación y revitalización de sus culturas y el fortalecimiento de sus identidades, como fundamento en la construcción de una sociedad democrática y respetuosa de la diversidad y la pluriculturalidad que caracteriza al estado artículo 8, en el que se destaca que el estado sustenta su identidad en los pueblos indígenas nahua, mixteco, tlapaneco y amuzgo, así como en el pueblo afromexicano; asimismo hace posible dar cumplimiento al artículo 11, fracción V, en el que se reconoce como derecho el preservar y enriquecer sus lenguas, conocimientos y todos los elementos que constituyen su cultura e identidad. Bajo estas premisas, el Programa contempla el impulso de diversas expresiones artísticas y culturales, principalmente las relacionadas con la música y danzas tradicionales, así como el fortalecimiento de los saberes de los terapeutas tradicionales y la promoción cultural, a través de la publicación de trípticos, carteles y libros.\nDe esta manera, la Secretaría para el Desarrollo de las Comunidades y Pueblos Indígenas y Afromexicanos\n(SEDEPIA), como instancia responsable de implementar el Programa, propicia espacios y mecanismos de difusión y participación para impulsar y fortalecer las culturas, las identidades y el tejido social de los pueblos indígenas y afromexicanos conjuntamente con los grupos y promotores culturales interesados en los beneficios de las acciones.\nEs importante señalar que, si bien dentro de las acciones del Programa se propiciará el fortalecimiento cultural e identitarios de los cinco pueblos, se hará un especial énfasis en promover la revitalización cultural indígena y la reafirmación de la identidad Afromexicana. Lo anterior en razón de que el pueblo\nAfromexicano, a diferencia de los cuatro pueblos indígenas, recién en los últimos treinta años transita en un proceso de reconocimiento, reivindicación y auto adscripción, cuyos resultados positivos se han reflejado en su inclusión dentro de la Constitución local y en la Encuesta Intercensal 2015 del INEGI, que por primera vez considera en sus registros a la población afromexicana. manifestaciones culturales en simples piezas de artesanía, danza o música, sin ninguna vinculación con\nREGLAS DE OPERACIÓN PARA EL EJERCICIO FISCAL mecanismos de lucha y preservación de los pueblos indígenas y afromexicanos.\nAnte este panorama, la Secretaría para el Desarrollo de las Comunidades y Pueblos Indígenas y\nAfromexicanos (SEDEPIA) ha procurado aproximarse respetuosamente a las culturas indígenas y afromexicana, a partir del conocimiento de aquello que subyace a esta diversidad de expresiones para evitar, así, corromper, banalizar o folclorizar los atributos culturales que son los componentes esenciales de las identidades de estos pueblos.\nEn este sentido, se prestará una especial atención a los elementos culturales intangibles, como la música, la danza, las lenguas y los saberes y conocimientos tradicionales, que, por un lado, revitalizarán las culturas indígenas, y por el otro contribuirán en el fortalecimiento y reafirmación de la cultura afromexicana, que desde el año 2013 se ha venido atendiendo.\n2. Alineación Programática al PED y/o PND.\nEn cumplimiento a los objetivos de las políticas públicas del gobierno del estado y a las acciones específicas para alcanzarlos, el Programa Fortalecimiento de Culturas de los Pueblos Indígenas y Afromexicanos se encuentra alineado al Plan Estatal de Desarrollo 2022-2027 en su eje 1 Bienestar, Desarrollo Humano y\nJusticia Social; en los objetivos, estrategias y líneas de acción siguientes: Objetivo 1.6 preservar la identidad de las expresiones culturales de los pueblos guerrerenses, como clave para el desarrollo artísticos, económico y la cohesión social. Estrategia 1.6.1 difundir el desarrollo artístico e impulsar el trabajo creativo para el interés ciudadano, mediante mecanismos de segmentación social. Línea de acción\n1.6.1.4 reconocer y fortalecer las culturas indígenas y afromexicanas en sus contestos comunitarios y regionales y al Objetivo 1.10. Preservación de las danzas tradicionales del estado de Guerrero; Estrategias\n1.10.1 identificar las danzas consideradas tradicionales del estado de Guerrero que permita asegurar su preservación como patrimonio intangible. Línea de acción 1.10.1.1 impulsar el índice de participación en cada una de las actividades artísticas.\nY de acuerdo al Plan Nacional de Desarrollo 2019-2024 en el apartado de I.- Política y Gobierno incluye\nRecuperar el Estado de Derecho y Libertad e Igualdad, el cual reconocerá y respetará las atribuciones y facultades que el marco legal del país otorga a las comunidades indígenas y a sus instancias de decisión, así mismo la impulsará la igualdad como principio rector la igualdad efectiva de derechos entre mujeres y hombres, entre indígenas y mestizos, entre jóvenes y adultos, y se comprometerá en la erradicación de las prácticas discriminatorias que han perpetuado la opresión de sectores poblacionales enteros; II. Política\nSocial en Construir un país con bienestar, en México los artículos 3, 27, 123 y otros de la Constitución de 1917 sentaron las bases para un estado de bienestar con características propias en un país predominantemente agrario y de tradiciones indígenas comunitarias; III. Economía con Proyectos regionales Autosuficiencia alimentaria y rescate del campo. El sector agrario ha sido uno de los más devastados por las políticas neoliberales. A partir de 1988 se destruyeron mecanismos que resultaban fundamentales para el desarrollo agrario, se orientó el apoyo público a la manipulación electoral y se propició el vaciamiento poblacional del agro. Las comunidades indígenas, que han vivido desde hace siglos la opresión, el saqueo y la discriminación, padecieron con particular intensidad esta ofensiva.\nREGLAS DE OPERACIÓN PARA EL EJERCICIO FISCAL\n2.1. Diagnóstico. asientan en su territorio, principalmente por los pueblos indígenas Nahua, Na savi (mixteco), Me’pha\n(tlapaneco) y Nn´anncue Ñomdaa (amuzgo), y el pueblo afromexicano. Además, estos pueblos y sus comunidades son base fundamental de la identidad y la raíz histórica del estado, contribuyendo con sus saberes ancestrales, cosmovisiones, organización social y expresiones lingüísticas y artísticas a la riqueza cultural de Guerrero. Cabe señalar que estos cinco pueblos comparten algunos rasgos culturales, sin embargo, cada uno de ellos guarda su propia cultura e identidad que los define, diferencia y, paralelamente, los hace reconocerse como tales.\nLa trascendencia de los pueblos indígenas y afromexicano, no sólo se fundamenta en sus aportes culturales e históricos, sino también por su importancia numérica, tal como lo muestra Censo de Población y Vivienda 2020 1:\nPOBLACIÓN TOTAL Y POBLACIÓN INDÍGENA Y AFROMEXICANA\nGUERRERO 2020\nTotal de población de Guerrero: 3´540,685\nMujeres: 1´840,073\nHombres: 1´700,612\nTotal Población hablante de lengua indígena: 515,487\nTotal Población que se autoreconoce indígena: 1’198,362\nTotal, Población que se autoreconoce afromexicana: 303,923\nNo obstante, la significación de estos pueblos y sus comunidades, históricamente han padecido discriminación, marginación, pobreza y limitación en el ejercicio de sus derechos humanos, lo cual ha afectado su desarrollo individual y colectivo.\nComo uno de los efectos del rezago social y jurídico, las culturas indígenas y afromexicana enfrentan procesos de debilitamiento de su identidad que se traduce en desvaloración de lo propio, deterioro del patrimonio cultural y resquebrajamiento del tejido social2. A lo anterior habría que agregar la visión\n1 Censo de Población y Vivienda 2020, INEGI\n2 Programa Especial de Pueblos Indígenas 2014-2018. México, CDI, 2014, P. 36.\nREGLAS DE OPERACIÓN PARA EL EJERCICIO FISCAL distorsionada que aún mantienen diversos sectores de la sociedad, con respecto a las culturas indígenas y afromexicana, ya que con frecuencia se confunde cultura con folclor y se insiste en mostrar sólo aquellas dimensiones más exóticas y externas de la cultura. Al someter a las culturas indígenas y afromexicana a una visión folclórica, se crea un objeto exótico que alimenta las miradas románticas, paternalistas e ilusorias de la cultura, a la que se la quiere despojar de su importancia y trascendencia histórica, pues sólo la ven atada a la nostalgia del pasado.\nAsimismo, los pueblos indígenas y afromexicanos de Guerrero, demandan una mirada más sistémica sobre sus culturas, que no se las reduzca únicamente a los aspectos materiales y a las expresiones exotizantes, ya que no sólo son un cúmulo de cosas a ser observadas, o bienes y patrimonios materiales. En sus culturas se producen procesos de comunicación e interacción entre las personas, lo cual hace posible la construcción de los diversos sentidos de su vida social; en las manifestaciones folclóricas apenas se expresan formas de intercambio que quedan en el nivel más manifiesto, externo y secundario de la cultura.\nAsimismo, los pueblos indígenas y afromexicano no necesitan que se “rescaten” sus culturas, pues éstas se encuentran vivas; la noción de rescate cultural ha conducido y reducido a las culturas en expresiones folclóricas, visión que es comúnmente aceptada en el trabajo cultural, caracterizado por tratar de encontrar restos materiales de la cultura, para mostrarlos como las verdaderas y únicas expresiones de la identidad cultural.\nEl llamado rescate cultural está cargado de un profundo sentido etnocéntrico e ideológico, ya que representa un hecho externo surgido del experto o el rescatador, por lo tanto, desde fuera de las comunidades que son las que construyen la cultura. En el rescate cultural, la comunidad no tiene sino un mero rol de objeto pasivo, lo que contribuye a su alienación y dependencia, pues no se la ve como el sujeto histórico capaz de encargarse de la gestión de sus propias construcciones culturales.\nHoy las instituciones públicas de cultura deben trabajar en procesos no de rescate sino de revitalización cultural, puesto que estos procesos sólo pueden ser posibles desde la propia vida de las comunidades que la construyen. En la revitalización cultural la comunidad y los actores sociales comunitarios se construyen en sujetos sociales, políticos e históricos, lo que permite eliminar la visión de los rescatadores, a quienes sólo les interesa encontrar “piezas” para ser fosilizadas en los museos. Mientras que las personas que revitalizan la cultura lo hacen desde las dimensiones profundas de la memoria colectiva, incrementando la experiencia social de la existencia comunitaria, que le permita afirmar los propios recursos culturales que han sido capaces de construir como pueblos.\nEn congruencia con lo anterior, la SEDEPIA implementa el presente Programa con el objeto de atender las demandas indígenas y Afromexicanas en materia cultural, e iniciar un proceso que revitalice las culturas e identidades de estos pueblos.\n2.1.1. Población Potencial.\nEn Guerrero la población total es de 3´540,685 habitantes de los cuales 548,098 hablantes de la lengua indígena que representa el 15.48 % y 303,790 habitantes que se autoreconocen afromexicanos que\nREGLAS DE OPERACIÓN PARA EL EJERCICIO FISCAL equivale al 8.58 %, el cual da como resultado un total de 852,243 habitantes que constituyen nuestra población potencial que representa el 24.07% de la población total del estado de Guerrero.\n2.1.2. Población Objetivo.\nLa cultura se manifiesta a través del vestido, la gastronomía, la lengua, las formas de comunicación y relación; y reconocer que todas las personas, grupos y comunidades tienen una manera específica de ver al mundo y comprenderlo, hablando de la diversidad cultural. La población objetivo la constituyen a aquellos grupos o familias que se dediquen a la música, danza y/o artesanías que sean indígenas Nahua, Na savi\n(mixteco), Me’pha (tlapaneco) y Nn´anncue Ñomdaa (amuzgo)) o que se autoreconozcan como afromexicanos de todos los municipios del estado y cumpla con los requisitos previos para ser beneficiadas o beneficiados en el numeral 6 Criterios y Requisitos de Elegibilidad de las presentes Reglas de Operación.\n2.1.3. Población Beneficiaria.\nPersonas y grupo de personas indígenas y Afromexicanas que realicen actividades vinculadas con las diferentes expresiones artísticas y culturales, específicamente las relacionadas con la música, la danza y las lenguas indígenas.\n2.1.4. Población Indígena.\nSe tiene programado beneficiar a los cuatro pueblos indígenas (Nahua, Na savi, mixteco, Me’pha\n(tlapaneco) y Nn´anncue Ñomdaa (amuzgo), así como a los municipios afromexicanos, que realicen actividades vinculadas con las diferentes expresiones artísticas y culturales que habitan en todos los municipios del estado, dando prioridad a los municipios de Azoyú, Copala, Cuajinicuilapa, Cuautepec, Florencio Villarreal, Juchitán, Marquelia, Ometepec, San Marcos y Teconapa.\n2.2. Fundamento Legal. ejecución:\na) Constitución Política de los Estados Unidos Mexicanos.\nc) Ley General para la Igualdad entre Mujeres y Hombres.\nd) Ley Número 701 de Reconocimiento, Derechos y Cultura de los Pueblos y Comunidades Indígenas del\nEstado de Guerrero.\ne) Ley General de Acceso de las Mujeres a una Vida Libre de Violencia.\nf) Ley Orgánica de la Administración Pública del Estado de Guerrero Número 242.\nREGLAS DE OPERACIÓN PARA EL EJERCICIO FISCAL\nh) Ley Número 465 de Responsabilidades Administrativas para el Estado de Guerrero.\ni) Ley Número 466 de Protección de Datos Personales en Posesión de Sujetos Obligados del Estado de\nGuerrero.\nj) Ley Número 494 para la Igualdad entre Mujeres y Hombres del Estado de Guerrero. de Guerrero.\nm) Declaración Universal de las Naciones Unidas sobre los Derechos de los Pueblos Indígenas.\nn) Convenio 169 sobre Pueblos Indígenas y Tribales, de la Organización Internacional del Trabajo. ñ) Plan Nacional de Desarrollo 2019-2024.\no) Decreto Número 181 por medio del cual la Sexagésima Tercera Legislatura al Honorable Congreso del\np) Decreto Número 424 del Presupuesto de Egresos del Estado de Guerrero para el Ejercicio Fiscal 2023.\nq) Reglamento Interior de la Secretaría de Asuntos Indígenas.\nr) Lineamientos para la Elaboración de las Reglas de Operación de los Programas Sociales Estatales para el periodo 2022-2027.\ns) Ley Número 454 de Presupuesto y Disciplina Fiscal del Estado de Guerrero.\nt) Todos aquellos ordenamientos normativos aplicables.\n2.3. Definiciones y Siglas.\nDefiniciones:\nAgrupación musical: Conjunto, banda de música de viento o grupo musical, compuestos por dos o más personas que, a través de la voz y/o de instrumentos, interpretan obras musicales que conservan la tradición musical de las comunidades indígenas y afromexicanas. Para los fines de estas Reglas de\nOperación, los conjuntos o bandas musicales que interpretan cualquier género de música moderna no están considerados en esta categoría.\nREGLAS DE OPERACIÓN PARA EL EJERCICIO FISCAL\nAlienación: Pérdida de la personalidad o de la identidad de una persona o de un colectivo.\nApoyo en especie: Otorgamiento de bienes y servicios, diferente al apoyo monetario.\nAuto adscripción afromexicana: Autor reconocimiento como persona descendiente de población africana que llegó al territorio de México durante la conquista y colonización española, con base en su propia cultura, tradiciones e historia.\nAuto adscripción indígena: Autor reconocimiento como persona indígena con base en su propia cultura, tradiciones e historia, ya sea hablante o no de alguna lengua indígena.\nCarta Compromiso: Carta mediante la cual las personas beneficiarias se comprometen a cumplir con lo estipulado en estas Reglas de Operación, sin necesidad de un notario.\nCosmovisión: Es la manera de ver e interpretar el mundo. Conjunto de ideas que nos permite analizar y comprender la realidad, a partir de la propia existencia.\nCultura: Conjunto de conocimientos, creencias, valores, costumbres, conductas, leyes y cualquier otra capacidad y hábitos adquiridos por las personas, que hacen posible la vida, transformación y reproducción de una sociedad.\nCultura intangible: Es el conjunto de manifestaciones no materiales que genera una cultura, como son los saberes y conocimientos, las celebraciones y rituales, las manifestaciones musicales, literarias, dancísticas y plásticas, entre otros. Este patrimonio se transmite oralmente y se modifica con el transcurso del tiempo, a través de un proceso de recreación colectiva.\nDanzas tradicionales: Bailes típicos propios de las culturas indígenas y afromexicana, cuyo origen puede o no remontarse a la época colonial, bailadas por hombres y mujeres de las comunidades, principalmente durante acontecimientos sociales y fiestas patronales.\nDialogo intercultural: Intercambio de opiniones y puntos de vista entre distintas culturas, comunidades y pueblos, basado en la comprensión y el respeto mutuo.\nDiscriminación: Trato diferente y perjudicial que se da a una persona o colectividad por motivos de edad, color, capacidades, etnia, nacionalidad, género, orientación sexual, ideas políticas, religión, entre otras.\nElementos culturales: Son todas las partes que componen la cultura de un pueblo, país o etnia. Junto con los elementos naturales, les dan forma, cohesión e identidad a las sociedades y permiten su identificación y diferenciación respecto a otras.\nEtnocéntrico: Persona o colectividad que considera su propia cultura superior a las demás, y estima sólo válida sus criterios para interpretar y valorar los comportamientos, costumbres, tradiciones y valores de otras colectividades.\nREGLAS DE OPERACIÓN PARA EL EJERCICIO FISCAL\nExótico: Características o condiciones culturales que son muy distintas a las propias, por lo que se consideran “raras”, risibles o novedosas.\nExpresiones artísticas y culturales: Conjunto de manifestaciones de una etnia, pueblo o país que incluye la música, danza, arte, diseños, signos, símbolos, interpretaciones, ceremonias, rituales, mitos, saberes, narraciones, artesanías, formas arquitectónicas, entre otras.\nExpresiones lingüísticas: Manifestaciones que pertenecen o están relacionadas con el lenguaje.\nFolclore: Conjunto de expresiones culturales tradicionales de un pueblo, así como la disciplina que se encarga del estudio de estas materias.\nFolclorizar: Uso de una tradición popular fuera del contexto en que se desarrolló. Significa también distorsionar las culturas de los pueblos y reducirlas a una artesanía que se vende, a un objeto que se oferta y una realidad que no se investiga y no se piensa.\nGrupos étnicos: Grupo humano que comparte instituciones sociales y rasgos culturales como la lengua, valores, costumbres, entre otros elementos. Las mujeres y hombres del grupo están unidos por una consciencia de identidad común establecida históricamente.\nIdentidad: Es el sentido de pertenencia a una colectividad, construido a través de la adopción de elementos culturales comunes a dicha colectividad, y que nos permite diferenciarnos y reafirmarnos ante personas de otras culturas.\nIdeológico: Conjunto de ideas fundamentales que caracteriza el pensamiento de una persona, una colectividad o una época.\nMarginación: Indicador que mide la intensidad de las privaciones padecidas por la población a través de\n9 formas de exclusión agrupadas en 4 dimensiones: educación, vivienda, distribución de la población e ingresos monetarios.\nMemoria colectiva: Conjunto de representaciones del pasado que un grupo produce, conserva, elabora y transmite, a través de la relación entre sus miembros.\nOrganización social: Grupo de individuos que unen actuaciones para alcanzar determinados propósitos.\nPadrón de Personas Beneficiarias: Relación de beneficiarias y beneficiarios, de obras o de servicios del\nPrograma.\nParteras tradicionales: Son un recurso comunitario de atención a la salud, de amplio reconocimiento y prestigio en sus comunidades; son las encargadas de brindar cuidados a las mujeres durante el embarazo, parto y posparto.\nREGLAS DE OPERACIÓN PARA EL EJERCICIO FISCAL\nPatrimonio cultural: Conjunto de bienes tangibles e intangibles, que constituyen la herencia de un grupo humano, que refuerza su sentido de comunidad e identidad propia. Como producto de la creatividad humana, se hereda, se transmite, se modifica y optimiza de individuo a individuo y de generación a generación.\nPersona beneficiaria: Persona que recibe los bienes y/o servicios, por haber cumplido con los requisitos establecidos en las presentes Reglas de Operación.\nPrograma: Programa Fortalecimiento de Culturas de los Pueblos Indígenas y Afromexicanos.\nPromoción cultural: sistema de acciones que facilita una relación activa entre la población y la cultura.\nPluriculturalidad: Presencia de dos o más culturas en un mismo territorio, donde puede existir la posibilidad que surjan situaciones de interrelación.\nReglas de Operación: Reglas de Operación del Programa Fortalecimiento de Culturas de los Pueblos\nIndígenas y Afromexicanos.\nRevitalización cultural: Estrategia y acciones tendientes a la activación de las manifestaciones culturales, a partir del fortalecimiento de la vida de las comunidades, la revaloración de la memoria histórica y de las prácticas y saberes comunitarios.\nSaberes ancestrales: Conjunto de saberes y prácticas conservadas a lo largo del tiempo, a través de la tradición oral de los pueblos, y transmitida de generación a generación.\nSujeto histórico: Persona con la capacidad de transformar su realidad y con ello producir acontecimientos históricamente relevantes.\nTerapeutas tradicionales: Conjunto de especialistas de la medicina tradicional que constituye un recurso comunitario de atención a la salud. Son hombres y mujeres reconocidos por sus comunidades como poseedores de los saberes y habilidades para curar.\nTejido social: Es la configuración de vínculos sociales e institucionales que favorecen la unión y la reproducción de la vida social.\nSiglas:\nSEDEPIA: Secretaría para el Desarrollo de las Comunidades y Pueblos Indígenas y Afromexicanos.\n3. Objetivos y Alcances.\n3.1. Objetivo General.\nREGLAS DE OPERACIÓN PARA EL EJERCICIO FISCAL identidades de los pueblos indígenas y afromexicano, para propiciar el reconocimiento de la diversidad y un diálogo intercultural entre la sociedad guerrerense.\n3.2. Objetivo Específico.\na) Impulsar y difundir las diferentes expresiones artísticas y culturales de los pueblos indígenas y\nAfromexicano.\nb) Contribuir al fortalecimiento de la identidad Afromexicana, a través de estrategias y acciones que propicien la auto adscripción y la revaloración cultural.\n3.3. Cobertura.\nEl Programa tendrá una cobertura estatal y será implementado por la SEDEPIA, a través de la Dirección de Promoción y Difusión Cultural.\n3.4. Alcances.\nLa Ley Número 701 de Reconocimiento, Derechos y Cultura de los Pueblos y Comunidades Indígenas del\nEstado de Guerrero, en su artículo 26, fracción IV, mandata que el estado y las instituciones deberán preservar y enriquecer las lenguas indígenas, así como sus conocimientos y todos los elementos que constituyan sus culturas e identidades. Asimismo, bajo los mismos términos este derecho es reconocido\nGuerrero, en las que ya se incorpora al pueblo Afromexicano al goce de éste y otros derechos.\nAcorde con estos mandatos constitucionales y con las demandas indígenas y Afromexicanas recogidas en los Foros de Consulta Ciudadana, efectuados para elaborar el Plan Estatal de Desarrollo 2022-2027, se plantea la necesidad de implementar un programa que cumpla con las políticas públicas dictadas por la las cuatro lenguas indígenas e impulsar las culturas e identidades indígenas y afromexicana, atendiendo a su derecho a la seguridad social.\nLa forma más común de identificar la seguridad social es mediante las prestaciones y la asistencia médica, sin embargo, esas son solo algunas de las formas en las que se presenta en la vida cotidiana. En los hechos, la seguridad social también se encuentra en los actos solidarios e inclusivos de las personas hacia los demás, pues esos actos llevan en sí mismos la búsqueda del bienestar social.\n4. Metas Físicas.\nLos servicios y acciones estarán sujetos a la disponibilidad presupuestal del Programa, y son los siguientes:\nREGLAS DE OPERACIÓN PARA EL EJERCICIO FISCAL\na) Promoción y difusión de la música y danzas indígenas y afromexicanas y exposición de artesanías de pueblos indígenas y Afromexicanos:\n• 3 talleres de capacitación para reparación de instrumentos musicales, en los municipios de Atlixtac;\nMalinaltepec y Copalillo.\n• 3 encuentros de bandas de música de viento en Chilpancingo; Tlapa de Comonfort y Ometepec.\n• Acto de entrega de donación de instrumentos musicales y vestuario de danzas en tres municipios.\n• 28 instrumentos musicales.\n• 20 paquetes de vestuarios para grupos de danza.\nb) Exposición de artesanías de pueblos indígenas y afromexicanos:\n• 4 exposiciones de artesanías que se realizarán en: Chilpancingo de los Bravo, Acapulco de Juárez y\nOlinalá.\nc) Eventos para el impulso de las culturas e identidades:\n• 3 encuentros y festivales para el impulso cultural e identitario: en Chilpancingo de los Bravo y Santa\nCruz del Rincón.\n• 3 talleres para el fortalecimiento de la medicina indígena tradicional en los municipios de Tlapa de\nComonfort, Ayutla de los Libres y Xochistlahuaca.\nd) Taller de Lenguas:\n• 4 talleres de lingüísticas de las cuatro lenguas indígenas del estado de Guerrero.\n5. Programación Presupuestal.\nLos recursos aprobados en el Decreto Número 424 del Presupuesto de Egresos del Estado de Guerrero para el Ejercicio Fiscal 2023 para el Programa corresponden a inversión estatal directa que ascienden a\n$4, 100,000.00 (Cuatro millones cien mil pesos 00/100 m.n.). No se puede establecer monto de la población beneficiada en virtud que van desde ferias o exposiciones de artesanías, donación de instrumentos musicales, entre otros.\nCalendario de Ministración\nREGLAS DE OPERACIÓN PARA EL EJERCICIO FISCAL\nCONCEPTO TOTAL (« N E MAR ABR MAY JUN JUL AGO SEP OCT O I\n1. Promoción y difusión de la música y\n1,474,000 219,250 121.000 204.000 339,250 162,250 338,250 danzas indígenas y afro mexicanas\nII. Eventos para el impulso de\n2,362,000 182,000 834,000 743,000 603,000 las culturas e identidades\nIII. Taller de\n264,000 237,000 4000 7000 16,000\nLenguas\nTOTAL ($) 4,100,000 219,250 121,000 294,000 237,000 186,000 1,180,250 921,250 941,250\nTOTAl\n4,100,000 $219,250 652,000 2,287,500 941,250\nTRIMESTRAL\nCronograma de Actividades\nCONCEPTO ENE FEB MAR ABR MAY JUN JUL AGO SEP OCT NOV DIC\nI. Promoción y Difusión de la\nMúsica y Danzas Indígenas y\nAfromexicanas.\nII. Eventos para el impulso de las Culturas e Identidades\nIII. Taller de lenguas\n5.1. Gastos de Operación.\nEn cumplimiento al artículo 47 de la Ley de Coordinación Fiscal, podrá aplicarse hasta un 3% del presupuesto total del Programa, a gastos de operación y realización de diversas acciones, asociadas con la planeación, operación, supervisión, seguimiento, contraloría social y evaluación o asesoría externa del\nREGLAS DE OPERACIÓN PARA EL EJERCICIO FISCAL\nPrograma, por un monto de $123,000.00 (Ciento veintitrés mil pesos 00/100 m.n.). De acuerdo a la tabla siguiente:\nUNIDAD\nCOSTO\nCAPITULO CONCEPTO PARTIDA DE CANTIDAD TOTAL\nUNITARIO\nMEDIDA\n2111 Paquete 2 $5,000.00 $10,000.00\n2100\n2000 2121 Paquete 2 $5,000.00 $10,000.00\n2600 2611 Litro 1500 $24.00 $36,000.00\n3721 Caseta 10 $500.00 $5,000.00\n3000 3700\n3751 Día 62 $1,000.00 $62,000.00\n$123,000.00\n6. Criterios y Requisitos de Elegibilidad.\nLa forma de acceder a los servicios y apoyos que ofrece el Programa, responde a solicitud de las personas que demandan el beneficio, y los criterios serán trasparentes, equitativos y no discrecionales. Los requisitos, la forma de acceso y criterios de selección establecidos por el Programa son públicos, y estarán disponibles para las personas solicitantes en las Oficinas Centrales y Delegaciones de la SEDEPIA, cuya ubicación y horarios se anotan en el apartado 9.2. de este documento.\na) Promoción y difusión de la música y danzas indígenas y afromexicanas y exposición artesanal regional.\nb) Talleres de capacitación para reparación de instrumentos musicales.\n• Solicitud por escrito libre, firmada por la persona representante del grupo, dirigida a la persona titular de la SEDEPIA.\n• Identificación oficial de las personas participantes (copia INE).\n• La persona titular de la SEDEPIA dará respuesta por escrito a la solicitud, en un término de treinta días hábiles, posteriores a la recepción de la misma.\n• En caso de que la respuesta sea afirmativa, se procederá a establecer, de común acuerdo, la sede y fecha del taller.\n• El grupo beneficiario deberá contribuir con el mobiliario y el local, para la realización del taller.\nc) Donación de instrumentos musicales y vestuario para grupos de danza.\nREGLAS DE OPERACIÓN PARA EL EJERCICIO FISCAL\n• Solicitud por escrito libre, firmada por la persona representante del grupo, dirigida a la persona titular de la SEDEPIA.\n• Identificación oficial (copia del INE) de las y los integrantes de las agrupaciones musicales y grupos de danza.\n• Constancia comunitaria.\n• La SEDEPIA analizará las solicitudes y determinará, de acuerdo al presupuesto del Programa, a las agrupaciones musicales y de danza que no hayan recibido ningún apoyo de otra institución, y que reúnan los requisitos de elegibilidad para recibir el apoyo, el cual será en especie.\nLa SEDEPIA notificará a los grupos beneficiarios, por vía telefónica o correo electrónico, la aprobación de su solicitud, en un término de sesenta días hábiles, posteriores a la recepción de la misma.\nLas personas y agrupaciones interesadas en los apoyos arriba señalados, deberán dirigir su solicitud por escrito libre a la persona titular de la SEDEPIA, y entregarla en las oficinas centrales de la SEDEPIA, así como en sus delegaciones regionales, en un horario de 9:00 a 15:00 horas.\nd) Exposición Cultural Regional de Artesanías.\n• Solicitud por escrito libre, firmada por la persona interesada, dirigida a la persona titular de la SEDEPIA, en formato libre.\n• El INE del artesano.\ne) Eventos para el impulso de las culturas e identidades.\nLos encuentros y festivales para el impulso cultural e identitario de los pueblos indígenas y afromexicano, corresponde a diversas actividades que la SEDEPIA realizará en fechas conmemorativas, como Día\nInternacional de los Pueblos Indígenas, Día de la Mujer Indígena, Día Internacional de la Lengua materna, entre otros. Las sedes contempladas son los municipios de: Chilpancingo y Santa Cruz del Rincón.\nEn cuanto a los talleres de medicina tradicional, su programación responde a una demanda expresa hecha en 2020 por médicos y parteras tradicionales amuzgos y nahuas. Las y los participantes deberán cubrir los requisitos siguientes:\n• Solicitud por escrito libre, de manera individual de médicos y parteras tradicionales.\n• Identificación oficial (copia del INE).\nEn cuanto al encuentro de bandas regionales, su programación responde a las demandas de los pueblos indígenas y afromexicanas. Se emitirá una convocatoria y de acuerdo a sus bases las personas participantes se inscribirán. Y los requisitos serán los siguientes:\n• Copia del INE.\n• Relación de participantes de cada banda de música de viento.\nREGLAS DE OPERACIÓN PARA EL EJERCICIO FISCAL\nf) Talleres lingüísticos.\nEn cuando la programación de los talleres lingüísticos de las cuatro lenguas indígenas que existen y con base al decenio internacional de las lenguas indígenas, se emitirán una convocatoria y las personas participantes presentarán los requisitos siguientes:\n• Una solicitud por escrito libre.\n• Identificación oficial (copia INE).\nUna vez que las personas y agrupaciones hayan cubierto los requisitos establecidos para acceder a los apoyos del Programa, se entregará el comprobante respectivo y, en caso de ser aprobada su solicitud, recibirán el beneficio de manera gratuita, de acuerdo a la disponibilidad presupuestal del Programa.\n7. Tipo, Monto y Periodicidad del Apoyo.\nLos instrumentos musicales y vestuario para grupos de danza, se entregarán solamente en especie de la manera siguiente:\na) La entrega de instrumentos y vestuario se realizará en las comunidades beneficiarias, o en las delegaciones regionales u oficinas centrales de la SEDEPIA.\nb) A las personas participantes en los talleres de capacitación, se les proporcionará alimentación y pago de pasajes de su comunidad al lugar sede.\nc) A las personas artesanas que participen en las exposiciones culturales, se les proporcionará alimentación y pago de pasaje de su comunidad al lugar de la exposición.\nd) Las personas terapeutas tradicionales recibirán capacitación, materiales y utensilios para la preparación de medicamentos herbolarios, los cuales se distribuirán de manera equitativa. afromexicanos con pobreza extrema.\n7.1. Características de los Apoyos.\nREGLAS DE OPERACIÓN PARA EL EJERCICIO FISCAL\nTIPO DE APOYO CONCEPTO MONTO MÁXIMO DE APOYO\nAlimentación: hasta por un monto de $ 100.00\nPasaje: hasta por un monto de $600.00\n-Pago de alimentación. 28 Instrumentos musicales hasta por un monto de\n$ 60,000.00\n-Pago de pasaje.\nI.PROMOCIÓN Y DIFUSIÓN DE LA MÚSICA Y\nDANZAS INDÍGENAS Y AFROMEXICANAS.\n-Donación de instrumentos musicales.\n20 paquetes a Grupos de danza hasta por un\n-Vestuario a grupos de danzas. monto de $20,000.00.\nTaller de reparación de instrumentos musicales hasta por un monto de $60,000.00\nPasaje: hasta por un monto de $ 600.00\n-Pasajes\nEXPOSICIÓN CULTURAL REGIONAL DE\nARTESANÍAS. -Alimentación para los artesanos que asistan a exponer sus artesanías. Alimentación: hasta por un monto de $ 100.00\n-Pago de pasajes. Pasaje: hasta por un monto de $ 600.00\n-Alimentación. Alimentación: hasta por un monto de $ 100.00\n-Hospedaje. Hospedaje: hasta por un monto de $ 500.00\nII. EVENTOS PARA EL IMPULSO DE LAS\nCULTURAS E IDENTIDADES. -Paquetes de materia prima.\nPaquete de materia prima hasta un costo de\n-Encuentro de banda (concurso de\n$20,000.00 banda regional).\nREGLAS DE OPERACIÓN PARA EL EJERCICIO FISCAL\n-Pagos de cursos de lenguas\n(Tlapaneco mephaa, mixteco tu'un savi, nahuatl y amuzgo ñonda'a)\nIII.TALLER DE LENGUAS. Pago del facilitador $35,000.00 por taller.\n7.2. Recursos no Devengados.\nEl presupuesto no ejercido para los fines autorizados al 31 de diciembre de 2023, deberá ser reintegrado a la Dirección General de Tesorería de la Secretaría de Finanzas y Administración del estado de Guerrero.\n7.3. Resguardo de la Documentación.\nLa SEDEPIA a través de la Dirección de Promoción y Difusión Cultural y las delegaciones regionales serán las responsables del resguardo de la documentación generada por la implementación del Programa asimismo deberán verificar que se cumpla con los requisitos entregando acuse de recibo, una vez concluido cada uno de los apoyos cada uno de los expedientes deberán ser remitidos a la Delegación Administrativa quien se hará cargo de la recepción y resguardo de la documentación comprobatoria para la solventación de los recursos ejercidos del Programa que desarrolla en las presentes Reglas de Operación.\n7.4. Supervisión y Control.\nLa supervisión, control y evaluación del Programa, será interna y estará a cargo de la Dirección de\nPromoción y Difusión Cultural, para lo cual se utilizará la Metodología del Marco Lógico y los resultados de la evaluación serán compartidos cada trimestre con la Secretaría de Planeación y Desarrollo Regional y la\nSecretaría de Contralaría y Transparencia Gubernamental, mismos que se deberán presentar a más tardar\n15 días hábiles posteriores a la terminación de cada trimestre, así como los informes sobre el presupuesto ejercido y con base a los indicadores de resultados previstos en este precepto.\nTodos los gastos generados en cada una de las actividades y acciones estarán soportados con la comprobación respectiva.\n8. Criterios de Selección.\nPertenecer a uno de los pueblos Nahua, Na savi (mixteco), Me’pha (tlapaneco) y Nn´anncue Ñomdaa\n(amuzgo), y el pueblo afromexicano, las personas o agrupaciones que solicitan un apoyo deberán cumplir los requisitos de selección y elegibilidad, establecidos en el apartado 6 de las presentes Reglas de\nOperación.\n8.1. Casos Especiales. autoreconozca como tal quien, determine si será beneficiada o beneficiado con lo que oferta el Programa.\nREGLAS DE OPERACIÓN PARA EL EJERCICIO FISCAL\n8.2. Casos de Emergencia o Desastre.\nPara el caso de emergencia o desastres naturales, la SEDEPIA podrá dar atención de manera inmediata de acuerdo a la disponibilidad financiera y la evaluación de los daños a la población afectada, dicha evaluación deberá contar con la evidencia documental, como galería fotográfica y acta de hechos levantada por personal responsable del Programa y/o autoridad competente, la SEDEPIA facilitará los mecanismos para cumplir con los requisitos establecidos en las presentes Reglas de Operación.\n8.3. Suspensión o Cancelación del Programa Social.\nLa SEDEPIA, podrá suspender y/o cancelar la operación, del Programa, cuando no exista las condiciones sociales-económicas entre las partes, cuando una de las personas beneficiarias no acate las disposiciones de estas Reglas de Operación y otras señaladas por las o los ejecutores que afecte la norma estatal, federal, cuando lo determine la persona titular del ejecutivo estatal y por problemas de gobernabilidad.\n8.4. Integración del Padrón de Personas Beneficiarias.\nLas personas y agrupaciones beneficiarias del Programa, formarán parte de un Padrón de Personas\nBeneficiarias, el cual será de carácter público, siendo reservados sus datos personales, de acuerdo con la\nLey Número 207 de Transparencia y Acceso a la Información Pública del Estado de Guerrero y, en ningún caso, podrán emplearse para propósitos de proselitismo político, religioso o comercial, ni para ningún otro fin distinto al establecido en estas Reglas de Operación.\nAnte ningún caso o situación las y los servidores públicos que ejecuten el Programa podrán solicitar pago alguno por el servicio que prestan, ni procederán de manera diferente a lo establecido en estas Reglas de\nOperación.\n9. Mecánica Operativa del Programa Social.\nPara la ejecución del Programa, la SEDEPIA, a través de la Dirección General de Promoción y Difusión\nCultural elaborará las Reglas de Operación y la programación presupuestal.\nLa implementación del Programa estará a cargo de la Dirección General de Promoción y Difusión Cultural, la cual será responsable recibir todas las solicitudes de la población indígena y afromexicana, así como vigilar el correcto seguimiento y cumplimiento a los apoyos y servicios prestados. de Operación y, de acuerdo a las características no previsibles de la demanda ciudadana.\nLas personas e instancias interesadas deberán entregar, en las unidades administrativas receptoras, la solicitud de apoyo mediante escrito libre en original, en el que se indique, el nombre de la(s) persona(s) solicitante(s), el tipo de apoyo que requiere y sus datos personales para localización, acompañada por los requisitos establecidos.\nREGLAS DE OPERACIÓN PARA EL EJERCICIO FISCAL\nEl personal de las unidades administrativas receptoras deberá orientar a las personas solicitantes, en la elaboración y presentación de las solicitudes y la documentación establecida en el Programa.\nLas unidades administrativas receptoras, al recibir cada solicitud, deberán verificar que el expediente cumpla con los requisitos señalados en estas Reglas de Operación, y deberán entregar el acuse de recibo a quien solicita el apoyo o servicio, señalando los documentos o datos faltantes para que sean entregados en un plazo no mayor de cinco días hábiles.\nUna vez publicados los resultados, en los casos que aplique según el tipo de apoyo, las instancias ejecutoras o personas beneficiarias contarán con un plazo máximo de treinta días naturales para acudir a las unidades administrativas receptoras, con el objeto de firmar el convenio o acuerdo en el que se formalizarán los derechos y obligaciones entre las partes, para la ejecución, administración, seguimiento y evaluación.\nLos datos de las personas beneficiarias del Programa, así como la información que éste genere y administre estará regida por lo que establece la Ley Número 207 de Transparencia y Acceso a la Información Pública del Estado de Guerrero.\nTodos los formatos y papelería que se entregue a las personas solicitantes y personas beneficiarias del\nPrograma, así como los trámites a realizar serán totalmente gratuitos.\n9.1. Instancia Ejecutora y/o Responsable.\nLa SEDEPIA será la instancia ejecutora del Programa, a través de la Dirección de Promoción y Difusión\nCultural y de sus delegaciones regionales.\n9.2. Proceso de Incorporación al Programa Social.\nPara acceder a los servicios y apoyos del Programa, se deberá cumplir con los requisitos según el tipo de apoyo o servicio solicitado y de acuerdo a los procedimientos que se citan en el apartado 6 de estas Reglas de Operación; así como los requisitos generales que a continuación se describen:\n• Ser originarias y originarios de comunidades y municipios indígenas y afromexicano, o auto adscribirse como tales, independientemente de su sexo, edad y filiación política o religiosa.\n• Solicitud por escrito, dirigida a la persona titular de la SEDEPIA, especificando el tipo de apoyo que se demanda.\n• Constancia expedida por la autoridad comunitaria, en la que se establezca que el grupo musical o de danza cumple con una función cultural, de beneficio para su comunidad y sin fines de lucro.\nSe recibirán las solicitudes en la oficina central y de las delegaciones siguientes:\nREGLAS DE OPERACIÓN PARA EL EJERCICIO FISCAL\nChilpancingo: Av. De la Juventud, núm. 5, Col. el Centenario. C.P. 39090 Tel. 01(747) 137 0620.\nChilapa de Álvarez: Calle 8 norte, no 801, Barrio del Dulce nombre, Tel. 01 (756) 475 0253.\nOmetepec: Calle Juan Ruiz de Alarcón, núm. 32, Barrio la Guadalupe. Tel. 01 (741) 412 0055.\nTlapa de Comonfort: Carretera Tlapa-Puebla km 1, Colonia el Tepeyac, referencia la choza del indio. 757\n1005159.\n10. Evaluación.\nLa SEDEPIA tendrá la obligación de revisar, de manera interna, la correcta operación y aplicación de las presentes Reglas de Operación y, en caso necesario, podrá solicitar una evaluación externa por parte de una instancia con experiencia en el tema.\nAsimismo, efectuará periódicamente acciones de supervisión y evaluación para garantizar el adecuado desarrollo del Programa, con el objeto de corregir desfases o efectuar reasignaciones financieras con la autorización de la Secretaría de Planeación y Desarrollo Regional y de la Secretaría de Finanzas y\nAdministración, a fin de cubrir rubros prioritarios con recursos de este mismo programa o de otros que no hayan sido ejercidos en su momento, o bien que provengan de ahorros presupuestales.\n10.1. Indicadores (Construcción de la Matriz de Indicadores para Resultados. - Anexo 1).\nFicha Técnica\nIndicadores del Desempeño\n2022-2027\nRAMO: Recursos Estatales\nFONDO: Inversión Estatal Directa\nNOMBRE DEL PROGRAMA: Fortalecimiento de Culturas de los Pueblos Indígenas y Afromexicano.\nEJE TEMATICO: 1 Bienestar, Desarrollo Humano y Justicia Social\nOBJETIVO: 1.6 Preservar la identidad de las expresiones culturales de los pueblos guerrerenses, como clave para el desarrollo artístico, económico y la cohesión social.\nESTRATEGIA: 1.6.1 Difundir el desarrollo artístico e impulsar el trabajo creativo para el interés ciudadano, mediante mecanismos de segmentación social.\nLÍNEA DE ACCIÓN: 1.6.1.4 Reconocer y fortalecer las culturas indígenas y afromexicanas en sus contestos comunitarios y regionales.\nDatos de identificación del indicador\nClave Nombre Fuente\nMunicipios indígenas y afromexicanos con acciones de fortalecimiento cultural e identitario. Padrón de Beneficiarios SEDEPIA\n2023.\nDefinición Nivel en la MIR Dimensión\nMide el número de municipios indígenas y afromexicanos beneficiados con acciones de\nActividad Eficacia fortalecimiento cultural e identitario.\nMétodo de cálculo Unidad de medida\n(Número de municipios indígenas y afromexicanos beneficiados / Total de municipios indígenas y\nPorcentaje afromexicanos) x 100\nFrecuencia de medición Desagregación geográfica Serie de información disponible\nTrimestral Estatal 2014 -2022\nLínea base\nSentido del indicador\nAño Periodo Valor\nPermanente 2023 Anual 100% (30)\nParámetros de semaforización Metas\nVerde Amarillo Rojo Año Periodo Valor\n67-100 34-66 0-33 2023 Anual 100% (30)\nVariables que conforman el indicador\nREGLAS DE OPERACIÓN PARA EL EJERCICIO FISCAL\nMunicipio acciones de fortalecimiento cultural. SEDEPIA 2023.\nNombre Unidad de medida Fuente de información\nRegistro de solicitudes SEDEPIA\nNúmero de municipios indígenas y afromexicanos. Municipio\n2023.\nObservaciones\nResponsable del indicador\nNombre del Servidor Público Dependencia Área\nSecretaría para el Desarrollo de los Dirección de Promoción Cultural y\nMtra. Yolanda Matías García\nPueblos Indígenas y Afromexicanos Apoyo Social\nNombre del puesto, encargo o comisión Teléfono Correo electrónico\nDirectora de Promoción Cultural y Apoyo Social 747 129 7456 dir.cult.saia@gmail.com\nElaboró Revisó Autorizó\nLic. Dánae Marín Acevedo Mtra. Yolanda Matías García Lic. Reyna Mejía Morales\nDirectora de Promoción Cultural y Apoyo Secretaria de Desarrollo de los Pueblos Indígenas\nDirectora General de Planeación y Desarrollo\nSocial y Afromexicanos\nDirección General de Evaluación\nRecinto del Poder Ejecutivo, Edificio Tierra Caliente, planta baja, correo electrónico: dge.seplader@guerrero.qob.mx\nFicha Técnica\nIndicadores del Desempeño\n2022-2027\nRAMO: 26 Recursos Estatales\nFONDO: Inversión Estatal Directa\nNOMBRE DEL PROGRAMA: Fortalecimiento de Culturas de los Pueblos Indígenas y Afromexicano\nEJE TEMATICO: 1 Bienestar Desarrollo Humano y Justicia Social\nOBJETIVO: 1.6 Preservar la identidad de las expresiones culturales de los pueblos guerrerenses, como clave para el desarrollo artístico, económico y la cohesión social.\nESTRATEGIA: 1.6.1 Difundir el desarrollo artístico e impulsar el trabajo creativo para el interés ciudadano, mediante mecanismos de segmentación social.\nLÍNEA DE ACCIÓN: 1.6.1.4 Reconocer y fortalecer las culturas indígenas y afromexicanas en sus contestos comunitarios y regionales.\nDatos de identificación del indicador\nClave Nombre Fuente\nRegistro de solicitudes y padrón\n1 Grupos culturales indígenas y afromexicanos beneficiarios. de Beneficiarios SEDEPIA 2023.\nDefinición Nivel en la MIR Dimensión\nMide el número de grupos culturales indígenas y afromexicanos con apoyos en\nActividad Eficacia especie.\nMétodo de cálculo Unidad de medida\n(Número de grupos culturales beneficiarios con apoyos en especie / Total de grupos culturales que\nPorcentaje solicitaron apoyo en especie) x 100\nFrecuencia de medición Desagregación geográfica Serie de información disponible\nTrimestral Estatal 2022\nLínea base\nSentido del indicador\nAño Periodo Valor\nPermanente 2023 Anual 100% (262)\nParámetros de semaforización Metas\nVerde Amarillo Rojo Año Periodo Valor\n67-100 34-66 0-33 2023 Anual 100% (262)\nVariables que conforman el indicador\nREGLAS DE OPERACIÓN PARA EL EJERCICIO FISCAL\nGrupo especie. SEDEPIA 2023.\nNombre Unidad de medida Fuente de información\nRegistro de solicitudes SEDEPIA\nGrupos culturales que solicitaron apoyos en especie. Grupo\n2023.\nObservaciones\nResponsable del indicador\nNombre del Servidor Público Dependencia Área\nSecretaría para el Desarrollo de los Dirección de Promoción\nMtra. Yolanda Matías García\nPueblos Indígenas y Afromexicanos Cultural y Apoyo Social\nNombre del puesto, encargo o comisión Teléfono Correo electrónico\nDirectora de Promoción Cultural y Apoyo Social 747 129 7456 dir.cuIt.saia@gmail.com\nElaboró Revisó Autorizó\nLic. Dánae Marín Acevedo Mtra. Yolanda Matías García Lic. Reyna Mejía Morales\nDirectora de Promoción Cultural y Apoyo Secretaria de Desarrollo de los Pueblos Indígenas\nDirectora General de Planeación y Desarrollo\nSocial. y Afromexicanos\nDirección General de Evaluación\nRecinto del Poder Ejecutivo, Edificio Tierra Caliente, planta baja, correo electrónico: dge.seplader@guerrero.gob.mx\nFicha Técnica\nIndicadores del Desempeño\n2022-2027\nRAMO: 26 Recursos Estatales\nFONDO: Inversión Estatal Directa\nNOMBRE DEL PROGRAMA: Fortalecimiento de Culturas de los Pueblos Indígenas y Afromexicano.\nEJE TEMATICO: 1 Bienestar, Desarrollo Humano y Justicia Social\nOBJETIVO: 1.6 Preservar la identidad de las expresiones culturales de los pueblos guerrerenses, como clave para el desarrollo artístico, económico y la cohesión social.\nESTRATEGIA: 1.6.1 Difundir el desarrollo artístico e impulsar el trabajo creativo para el interés ciudadano, mediante mecanismos de segmentación social.\nLINEA DE ACCION: 1.6.1.4 Reconocer y fortalecer las culturas indígenas y afromexicanas en sus contestos comunitarios y regionales.\nDatos de identificación del indicador\nClave Nombre Fuente\nRegistro de Actividades y Padrón\n3 Fortalecimiento de Culturas de los Pueblos Indígenas y Afromexicano de Beneficiarios SEDEPIA 2023.\nDefinición Nivel en la MIR Dimensión\nMide el número de talleres realizados para el fortalecimiento de las cuatro lenguas\nComponente Eficacia indígenas.\nMétodo de cálculo Unidad de medida\n(Número de Talleres Realizados/Número de talleres programados)100 Porcentaje\nFrecuencia de medición Desagregación geográfica Serie de información disponible\nTrimestral Estatal 2022\nLínea base\nSentido del indicador\nAño Periodo Valor\nPermanente 2023 Anual 100% (287)\nParámetros de semaforización Metas\nVerde Amarillo Rojo Año Periodo Valor\n67-100 34-66 0-33 2023 Anual 100% (287)\nVariables que conforman el indicador\nRegistro de talleres SEDEPIA\nNúmero de Talleres realizados Actividad\n2023.\nREGLAS DE OPERACIÓN PARA EL EJERCICIO FISCAL\nRegistro de talleres SEDEPIA\nNúmero de Talleres programados Actividad\n2023.\nObservaciones\nResponsable del indicador\nNombre del Servidor Público Dependencia Área\nSecretaría para el Desarrollo de los Dirección de Promoción\nMtra. Yolanda Matías García\nPueblos Indígenas y Afromexicanos Cultural y Apoyo Social\nNombre del puesto, encargo o comisión Teléfono Correo electrónico\nDirectora de Promoción Cultural y Apoyo Social 747 129 7456 dir.cult.saia@gmail.com\nElaboró Revisó Autorizó\nLic. Dánae Marín Acevedo Mtra. Yolanda Matías García Lic. Reyna Mejía Morales\nDirectora de Promoción Cultural y Apoyo Secretaria de Desarrollo de los Pueblos Indígenas\nDirectora General de Planeación y Desarrollo\nSocial y Afromexicanos\nDirección General de Evaluación\nRecinto del Poder Ejecutivo, Edificio Tierra Caliente, planta baja, correo electrónico: dqe.seplader@querrero.qob.mx\n10.2. Seguimiento.\nLas delegaciones regionales y la Dirección de Promoción y Difusión Cultural de la SEDEPIA, llevarán a cabo el seguimiento relacionado con las metas comprometidas, a fin de verificar la aplicación correcta de los recursos otorgados y el cumplimiento de objetivos y metas establecidas. Este seguimiento se realizará a través de la evaluación y acompañamiento de las acciones desarrolladas en campo.\n10.3. Auditoría.\nLa SEDEPIA será la responsable de la supervisión directa de las acciones, así como de verificar que en su ejecución se cumpla con la normatividad aplicable. Los recursos asignados para la operación del Programa no pierden su carácter estatal, por lo que la Secretaría de Finanzas y Administración, la Secretaría de\nContraloría y Transparencia Gubernamental y la Auditoría Superior del Estado, en el ámbito de sus respectivas competencias, realizarán actividades de fiscalización y auditoría.\nAsimismo, otorgará todas las facilidades a las instancias fiscalizadoras para realizar en el momento que juzguen pertinente, las auditorías necesarias; asimismo, efectuará el seguimiento y la solventación de las observaciones planteadas por los órganos de control. La inobservancia de esta disposición, independientemente de las sanciones a que haya lugar, limitará la ministración de los recursos estatales en el siguiente ejercicio presupuestal.\n11. Mecanismo de Entrega del Apoyo.\nPara el otorgamiento de los apoyos del Programa será de acuerdo al numeral 9.2 de las presentes Reglas que provengan de municipios indígenas y afromexicanos con mayores niveles de pobreza, que radiquen en sus localidades de origen y que enfoquen sus acciones al beneficio comunitario, así como a la protección y difusión de los valores culturales e identitarios de sus pueblos y comunidades.\nREGLAS DE OPERACIÓN PARA EL EJERCICIO FISCAL\n12. Derechos y Obligaciones de las Personas Beneficiadas.\nDerechos:\na) Recibir un trato digno, respetuoso, oportuno, equitativo y de calidad.\nb) Acceder a los apoyos que otorga el Programa, de acuerdo con lo establecido en estas Reglas de\nOperación y con la disponibilidad presupuestal.\nc) Recibir orientación de la SEDEPIA para la presentación de solicitudes de apoyo e integración de expedientes sin costo alguno.\nd) Tener la garantía de privacidad de sus datos personales.\nObligaciones:\na) Conducirse con la verdad en toda la información solicitada.\nb) Emplear el bien o apoyo recibido para los fines por los que fue otorgado.\nc) Entregar la documentación e información requeridas, de acuerdo a las Reglas de Operación.\nd) Comprometerse a conservar los instrumentos musicales en condiciones favorables.\ne) Informar a la SEDEPIA, a través de sus oficinas centrales o delegaciones regionales, cuando se presente algún suceso que evite la correcta aplicación de los apoyos otorgados a las agrupaciones musicales y de danza.\n12.1. Causales de Suspensión o Baja de las Personas Beneficiadas.\na) Falta a la verdad en toda la información proporcionada.\nb) No emplear el bien o apoyo recibido para los fines por los que fue otorgado.\nc) No entregar la documentación e información requeridas, de acuerdo a las Reglas de Operación.\nd) No conservar los instrumentos musicales en condiciones favorables.\ne) No informar a la SEDEPIA, a través de sus oficinas centrales o delegaciones regionales, cuando se presente algún suceso que evite la correcta aplicación de los apoyos otorgados a las agrupaciones musicales y de danza.\n12.2. Proceso de Baja. información o cuando los apoyos sean utilizados con fines partidistas.\n13. Instancias Participantes.\nLa SEDEPIA será ejecutora del Programa, la Secretaría de Planeación y Desarrollo Regional la cual autoriza los recursos que fueron aprobados en el Decreto Número 424 del Presupuesto de Egresos del\nEstado de Guerrero para el Ejercicio Fiscal 2023 y la Secretaría de Finanzas y Administración la cual realiza la liberación del recurso correspondiente, de acuerdo al cronograma financiero, y la Secretaría de\nContraloría y Transparencia Gubernamental para realizar las recomendaciones y sanciones pertinentes.\nREGLAS DE OPERACIÓN PARA EL EJERCICIO FISCAL\n13.1. Instancia Normativa.\nLa instancia administrativa y/o normativa quien será responsable de la operación es la SEDEPIA, así como lo señala en el reglamento interno de la institución. Esto con el objeto de armonizar el correcto desempeño y aplicación de los recursos asignados por el estado para los fines del Programa.\n14. Transparencia.\n14.1. Promoción y Difusión del Programa Social.\nConforme a las disposiciones establecidas en el apartado de Programas Sujetos a Reglas de Operación del Decreto Número 424 del Presupuesto de Egresos del Estado de Guerrero para el Ejercicio Fiscal 2023, estas Reglas de Operación, además de ser publicadas en el Periódico Oficial del Gobierno del Estado, estarán disponibles para la población en general en las Oficinas Centrales de la SEDEPIA cuya ubicación será en Avenida de la Juventud número 5, colonia el Centenario, C.P. 39090, Chilpancingo, Gro, México y\nDelegaciones Regionales, así como en las páginas electrónicas: www.asuntosindígenas.guerrero. gob.mx, www.guerrero.gob.mx, y en la página de red social Facebook de la SEDEPIA.\nAsimismo, a través de las delegaciones regionales ubicadas en las ciudades de Tlapa de Comonfort, Chilapa y Ometepec, se difundirá la información relativa al Programa, incluyendo a las autoridades municipales y comunitarias de los municipios indígenas y afromexicanos. La papelería, documentación oficial y difusión del Programa, deberá incluir la leyenda de Blindaje Electoral descrita en el apartado 14.5 de las presentes Reglas de Operación.\n14.2. Contraloría Social.\nLa SEDEPIA, como instancia ejecutora, promoverá la contraloría social, la cual comprende un conjunto de acciones de control, vigilancia y evaluación que realizan las beneficiarias y beneficiarios, ya sea de manera organizada o independiente, bajo un esquema de derechos y compromisos de ciudadanas y ciudadanos con el propósito de contribuir a que la gestión gubernamental se realice en términos de transparencia, eficacia y honradez. Entre dichas acciones destacan las siguientes:\na) Informar a la ciudadanía acerca de los apoyos otorgados y su costo.\nb) Capacitar a las y los beneficiarios para que se constituyan en instancias de vigilancia y evaluación social.\nc) Establecer espacios de comunicación (reuniones vecinales, asambleas comunitarias, entre otros).\nd) Promover la integración de organizaciones de la sociedad civil para realizar acciones de contraloría social.\ne) Instrumentar mecanismos de recepción y atención de quejas y denuncias. El Órgano Interno de Control verificará en lo correspondiente la realización de dichas acciones.\n14.3. Protección de Datos Personales.\nREGLAS DE OPERACIÓN PARA EL EJERCICIO FISCAL\nGuerrero, los datos e información recabada quedan protegidos para los fines del Programa que estas\nReglas de Operación detallan.\nEn todo momento la persona beneficiaria podrá ejercer los derechos de alta, acceso, rectificación, cancelación y oposición de datos personales robados.\nLos datos recabados personales serán utilizados con la finalidad siguiente: validar que se cumplan los requisitos de elegibilidad para ser persona beneficiaria de este Programa; que serán integrados de acuerdo a las facultades propias, compactibles análogos para la realización de compulsas para la integración del padrón único de personas beneficiarias.\nPor lo tanto, se garantiza la protección de los datos personales que sean recabados y en cumplimiento con las disposiciones en materia de transparencia y acceso a la información pública aplicable.\n14.4. Quejas y Denuncias.\nLas quejas, denuncias, peticiones y sugerencias relativas a este Programa, se realizarán de manera escrita, por comparecencia de la persona interesada, por correo electrónico o vía telefónica, y para aquellas que sean escritas se depositarán en los buzones instalados en las oficinas centrales de la SEDEPIA, ubicadas en Avenida de la Juventud número 5, colonia el Centenario, C.P. 39090, Chilpancingo, Gro, así como en las delegaciones regionales, situadas en las ciudades de Tlapa de Comonfort, Chilapa de Álvarez y\nOmetepec.\nLa persona denunciante deberá proporcionar los siguientes datos: Nombre de la servidora o servidor público, departamento de adscripción, objeto de la denuncia, nombre y domicilio de la persona quejosa e identificación oficial.\nLas quejas, denuncias, peticiones y sugerencias relativas a este Programa, se atenderán a través de la\nUnidad de Transparencia y Acceso a la Información Pública, la cual dará seguimiento y respuesta en un término máximo de 20 días hábiles.\nEn caso de que la SEDEPIA no resuelva la queja de las personas solicitantes o beneficiarias, éstas podrán estado de Guerrero.\n14.5. Acciones de Blindaje.\nLa operación y ejecución de los recursos estatales destinados al Programa, deberán observar y atender las medidas que emita la Secretaría de Contraloría y Transparencia Gubernamental, para coadyuvar a que éstos no sean utilizados con fines políticos, por lo que la papelería y documentación oficial, así como la publicidad y promoción del Programa deberá de incluir la leyenda siguiente: “Este Programa es público,\nREGLAS DE OPERACIÓN PARA EL EJERCICIO FISCAL ajeno a cualquier partido político. Queda prohibido el uso para fines distintos a los establecidos en el Programa”.\n14.6. Acta de Donación. (Anexo-2)\nSe elaborará un acta de donación la cual constituye una prueba documental que certifica la existencia de la acción y es responsabilidad de la SEDEPIA, su resguardo. Quien detecte alguna irregularidad en la acción, podrá firmar el acta de manera condicionada y anotar en ella las razones de dicha inconformidad.\nAdemás, se indicará los plazos acordados para solventar las observaciones a que dé lugar. Se anexa formato.\n15. Perspectiva de Género.\nLa operación del Programa y su implementación se establece con perspectiva de género, respeto y garantía al ejercicio de los derechos de las mujeres indígenas y afromexicanas, busca mostrar que las diferencias entre mujeres y hombres se dan no sólo por su determinación biológica, sino también por las diferencias culturales asignadas a los seres humanos por lo que la SEDEPIA pondrá especial atención a mujeres para fortalecer sus capacidades y ampliar sus oportunidades y así potenciar la agencia económica en favor de mayores oportunidades para su bienestar y desarrollo.\n16. Enfoque de Derechos.\nLas personas que fungen como servidoras o servidores públicos y participen en la operación del Programa deberán promover, respetar, proteger y garantizar el ejercicio efectivo de los derechos humanos de las personas beneficiarias, de conformidad con los principios de universalidad, interdependencia, indivisibilidad y progresividad. En particular, se fomentará la eficacia y respeto irrestricto a los derechos colectivos de los pueblos indígenas y afromexicano, reconocidos en la Constitución Política de los Estados Unidos\nMexicanos e instrumentos internacionales. Con el objetivo de generar las condiciones necesarias para el acceso igualitario, en términos de disponibilidad, accesibilidad y calidad en las acciones que realiza este\nPrograma, se implementarán mecanismos que hagan efectivo el acceso a la información gubernamental y se asegurará que el acceso a los apoyos y servicios se dé únicamente con base en lo establecido en estas\nReglas de Operación, sin discriminación o distinción alguna.\n17. Acciones contra el SARS-COV 2. para lo peor: una pandemia causada por un patógeno respiratorio letal y que se propague rápidamente” y sostuvo, además, que “los sistemas y capacidades existentes en materia de preparación y respuesta ante de una pandemia altamente mortífera, así como a la conmoción que supondría para los sistemas sanitarios, sociales y económicos” (OMS, 2019,). Pocos meses después, esta alerta se hizo realidad: tras un nuevo brote epidémico provocado por el virus SARS-CoV-2.9, que se había iniciado en China y se había\nREGLAS DE OPERACIÓN PARA EL EJERCICIO FISCAL sistemas de salud precarios (OMS, 2020a). Debido a su rápida propagación por todo el mundo, el 11 de marzo la OMS declaró que el COVID- 19 constituía una pandemia3, por lo que exhortó a: i) “prepararse y estar a punto”; ii) “detectar, proteger y tratar”; iii) “reducir la transmisión”; y iv) “innovar y aprender”. En la medida en que el virus se ha propagado a escala mundial, América se ha transformado en el epicentro de la nueva pandemia.\nEn particular, en la actualidad algunos países latinoamericanos se sitúan entre las 20 naciones que, a nivel global, registran el mayor número de contagiados y fallecidos por el COVID-19 (Brasil, Perú, Colombia, México, Argentina y Chile); además de figurar en la lista de los 20 países con mayor número de casos por millón de habitantes (Panamá, Chile, Perú, Brasil y Colombia).\nEn este contexto, la Organización Panamericana de la Salud (OPS) estima que, para el 1 de octubre, ya se habrán registrado más de 438 000 muertes por COVID-19 en América Latina y el Caribe (DW, 2020).\nJunto con estas cifras alarmantes, la crisis socio sanitaria está exacerbando las ya de por sí amplias desigualdades sociales y económicas que caracterizan al subcontinente y, de no adoptarse medidas oportunas y adecuadas, también recrudecerá la inestabilidad política y social que ya asolaba a varios países de la región antes de la pandemia. Sin embargo, el mayor impacto lo sufrirán aquellos sectores de la sociedad que, históricamente, han quedado excluidos del poder político y económico, en particular, los pueblos indígenas, incluidos las mujeres, los jóvenes, las niñas y niños y las personas mayores indígenas.\n18. Anexos que reflejen la entrega del apoyo (Económico, Especie o Servicios).\nAnexo 1. MIR.\nAnexo 2. Acta de Donación.\nEJE: 1 Bienestar, Desarrollo Humano y Justicia Social\nOBJETIVO: 1.6 Preservar la identidad de las expresiones culturales de los pueblos guerrerenses. como clave para el desarrollo artístico, económico y la cohesión social.\nESTRATEGIA: 1.6.1 Difundir el desarrollo artístico e Impulsar el trabajo creativo para el Interés ciudadano, mediante mecanismos do segmentación social.\nLÍNEA DE ACCION: 1.6.1.4 Reconocer y fortalecer las culturas Indígenas y afromexicanas en sus contestos comunitarios y regionales.\nPrograma: Fortalecimiento de culturas de los pueblos indígenas y afromexicano\nMatriz de Indicadores para Resultados\nMedios de\nResumen Narrativo Indicadores de desempeño Supuestos\nVerificación\n1.Encuesta sobre\nContribuir a la pueblos indígenas. preservación del Porcentaje de personas\n2014 (Centro de Las instituciones de gobierno patrimonio cultural de los indígenas y afromexicanas\nEstudios Sociales y dan cumplimiento a los de Opinión Publica. derechos sobre cultura indígena p.37). y afromexicana. sus lenguas, saberes y sus culturas.\n2.Encuesta propia prácticas traiciónales.\nSAIA 2023\nREGLAS DE OPERACIÓN PARA EL EJERCICIO FISCAL\n1.Encuesta Nacional\nLa población indígena y afromexicana demanda el\nPropósito afromexicano fortalecen indígenas y afromexicanas 2015(UNAM, fortalecimiento de sus\n(resultados) sus expresiones artísticas beneficiarias que afirmar tablaB5). expresiones artísticas y y culturales haber fortalecido su cultura. 2.Encuesta propia\nGuturales.\nSAIA 2023\nLas instancias responsables de\nRegistro de la asignación presupuestaria, Grupos culturales indígenas y\nC.1. Apoyos otorgados en solicitudes y Padrón incrementan los recursos afromexicanas con apoyos en de especie financieros para programas especie. Beneficiaros SAIA\n2023 dirigidos a las culturas indígenas y afromexicana\nLas instancias responsables de\nPorcentaje de municipios\nRegistro de la asignación presupuestaria, Componentes C. 2. Acciones realizadas indígenas y afromexicanos solicitudes y Padrón incrementan los recursos\n(Servicios/ para el fortalecimiento de con acciones de de financieros para programas\nProductos) las culturas e identidades. fortalecimiento cultural e Beneficiarios SAIA\n2023 dirigidos a las culturas identitario indígenas y afromexicana.\nLas instancias responsables de la asignación presupuestaria, Cantidad de libros y incrementan los recursos\nC.3. Talleres lingüísticos. libros y talleres. talleres realizados financieros para programas\nSAIA 2023. dirigidos a las culturas indígenas y afromexicana.\n1.1. Porcentaje de\n1.1. Donación de agrupaciones musicales instrumentos musicales beneficiarias con Registro de instrumentos musicales. solicitudes y Padrón\n1.2. Dotación de insumos 1.2. Porcentaje de grupos de\nBeneficiarios SAIA para elaboración de danza tradicionales\n2023.\nLa población indígena y vestuarios de danzas beneficiarios con insumos afromexicana conoce y\nActividades tradicionales. para vestuario. solicita servicios y apoyos que\n(Procesos) 2.1. Realización de brinda la Secretaría de Asuntos eventos para la promoción 21. Numero de eventos Registro de los Indígenas y Afromexicanos. de las culturas indígenas y realizados eventos 2023 afromexicana.\n3.2. Numero de talleres Registro de los\n3.1. Talleres lingüísticos realizados. talleres 2023.\nREGLAS DE OPERACIÓN PARA EL EJERCICIO FISCAL\nAnexo 2. Acta de Donación.\nREGLAS DE OPERACIÓN PARA EL EJERCICIO FISCAL\nPrimero. El presente Acuerdo entrará en vigor al día siguiente de su publicación en el Periódico Oficial del\nSegundo. Se abroga el Acuerdo por el que se crea el Programa Transformando el Desarrollo de las\nCulturas de los Pueblos Indígenas y Afromexicanos 2022; publicado en Periódico Oficial del Gobierno del\nEstado Edición Extraordinaria de fecha 03 agosto del 2022.\nTercero. A partir de la entrada en vigor del presente Acuerdo, las Reglas de Operación del Programa\nFortalecimiento de Culturas de los Pueblos Indígenas y Afromexicanos, subsecuente o sus modificaciones serán emitidas por la persona titular de la Secretaría para el Desarrollo de las Comunidades y Pueblos\nIndígenas y Afromexicanos, responsable directa de la operación y ejecución de las mismas.\nDado en el “Recinto de las Oficinas del Poder Ejecutivo del Estado”, inmueble ubicado en el número 62, Edificio Norte Planta Baja, en Boulevard René Juárez Cisneros, Código Postal 39074, Colonia Ciudad de los Servicios, en la Ciudad de Chilpancingo de los Bravo, capital del estado de Guerrero, a los trece días del mes de marzo del año dos mil veintitrés.\nGOBERNADORA CONSTITUCIONAL DEL ESTADO DE GUERRERO.\nMTRA. EVELYN CECIA SALGADO PINEDA.\nRúbrica.\nSECRETARIO GENERAL DE GOBIERNO.\nMTRO. LUDWIG MARCIAL REYNOSO NÚÑEZ.\nRúbrica.\nAFROMEXICANOS.\nLIC. REYNA MEJÍA MORALES.\nRúbrica.",
  "ordenamiento": "PROGRAMA",
  "jurisdiccion": "GUERRERO",
  "fuente_oficial": "DIARIO OFICIAL DE LA FEDERACION",
  "Fecha de Publicación": "19 DE ABRIL DE 2024",
  "ULTIMA REFORMA PUBLICADA": "19 DE ABRIL DE 2024",
  "status": "ABROGADA",
  "es_escaneado": false,
  "tiene_tablas": true,
  "materia": [
    "cultura",
    "indígena"
  ]
}