{
  "titulo": "Acuerdo por el Que Se Crea el Programa Apoyos A la Producción Agropecuaria y Se Emiten Sus Reglas de 1",
  "Contenido": "EJERCICIO FISCAL 2019.\nTEXTO ORIGINAL\nAcuerdo publicado en el Periódico Oficial del Gobierno del Estado No. 35 alcance II, el martes 30 de abril de 2019.\nACUERDO POR EL QUE SE CREA EL PROGRAMA APOYOS A LA PRODUCCIÓN AGROPECUARIA\nY SE EMITEN SUS REGLAS DE OPERACIÓN PARA EL EJERCICIO FISCAL 2019.\nLIC. JUAN JOSÉ CASTRO JUSTO, SECRETARIO DE AGRICULTURA, GANADERÍA, PESCA\nY DESARROLLO RURAL, CON FUNDAMENTO EN LO DISPUESTO POR LOS ARTÍCULOS 87 Y 88 DE\nDE LAS FACULTADES QUE ME CONFIEREN LOS ARTÍCULOS 10, 11, 18 APARTADO A FRACCIÓN\nXII, 31 FRACCIONES I, II Y XXVI DE LA LEY ORGÁNICA DE LA ADMINISTRACIÓN PÚBLICA DEL\nESTADO DE GUERRERO NÚMERO 08; 10 FRACCIONES I, XIV Y XIX DEL REGLAMENTO INTERIOR\nDE LA SECRETARÍA DE AGRICULTURA, GANADERÍA, PESCA Y DESARROLLO RURAL; EL\nARTÍCULO 58 FRACCIONES IV Y V Y EL ANEXO 21-A DEL DECRETO NÚMERO 182 DEL\nPRESUPUESTO DE EGRESOS DEL ESTADO DE GUERRERO PARA EL EJERCICIO FISCAL 2019 Y\nLOS LINEAMIENTOS PARA LA ELABORACIÓN DE LAS REGLAS DE OPERACIÓN DE LOS\nPROGRAMAS SOCIALES ESTATALES PARA EL EJERCICIO FISCAL 2017.\nQue en el Plan Estatal de Desarrollo 2016 - 2021 en su objetivo 3.1. Denominado \"Construir un\nEstado garante pleno de los derechos sociales de las personas\" en su Estrategia 3.1.2, establece que fortalecerá el desarrollo de capacidades de los integrantes de una sociedad con carencias que permitan contribuir a incrementar su capacidad productiva y su calidad de vida por lo que se emprenden programas especiales de asistencia social a grupos vulnerables con el fin de brindar condiciones mínimas necesarias para el desarrollo humano.\nQue uno de los compromisos del Ejecutivo Estatal con la ciudadanía guerrerense, al asumir y tomar protesta como Gobernador Constitucional del Estado, es lograr un Guerrero de tranquilidad, de paz, de justicia, de crecimiento y de empleo, contribuyendo con ello a construir historias de éxitos individuales y colectivos que permitan consolidar el crecimiento económico y estabilidad social.\nEstado de Guerrero. con actividades del sector primario, del orden de 6.3 millones de hectáreas.\nEJERCICIO FISCAL 2019.\nQue en esta entidad suriana, la actividad agropecuaria y pesquera, representa una de las ramas económicas de mayor relevancia social en el aporte para la sobrevivencia de un gran número de familias.\nQue el Programa: Apoyos a la Producción Agropecuaria, tiene como objetivo general, coadyuvar zonas rurales a través del apoyo en la adquisición de maquinaria, insumos, especies animales, construcción de obras menores y mejora en las condiciones de infraestructura de caminos para el traslado de cosechas.\nPor lo que la Secretaría de Agricultura, Ganadería, Pesca y Desarrollo Rural, tendrá a cargo la implementación, operación, ejecución, evaluación y administración del Programa Apoyos a la Producción\nAgropecuaria.\nQue por lo antes expuesto he decidido crear el Programa Apoyos a la Producción Agropecuaria con el objeto de coadyuvar en la capitalización de las unidades de producción rural y mejorar el nivel de vida de los habitantes de las zonas rurales a través del apoyo en la adquisición de maquinaria, insumos, especies animales, construcción de obras menores y mejora en las condiciones de infraestructura de caminos para el traslado de cosechas.\nCUERDO POR EL QUE SE CREA EL PROGRAMA APOYOS A LA PRODUCCIÓN AGROPECUARIA Y\nSE EMITEN SUS REGLAS DE OPERACIÓN PARA EL EJERCICIO FISCAL 2019.\nArtículo 1. Se crea el Programa Apoyos a la Producción Agropecuaria para el Ejercicio Fiscal\n2019, el cual tiene por objeto coadyuvar en la capitalización de las unidades de producción rural y mejorar el nivel de vida de los habitantes de las zonas rurales a través del apoyo en la adquisición de maquinaria, insumos, especies animales, construcción de obras menores y mejora en las condiciones de infraestructura de caminos para el traslado de cosechas.\nArtículo 2. Se emiten las Reglas de Operación del Programa Apoyos a la Producción\nAgropecuaria para el Ejercicio Fiscal 2019, en las que se establecen los principios de eficiencia, eficacia, oportunidad, equitativa y transparencia de los recursos públicos y requisitos que se deben de cumplir para poder acceder ha dicho Programa.\nFiscal 2019, establece los criterios y requisitos que se deben de cumplir para poder acceder a dicho\nPrograma.\nArtículo 3. La Secretaría de Agricultura, Ganadería, Pesca y Desarrollo Rural tendrá a cargo la implementación, operación, ejecución, evaluación y administración del Programa Apoyos a la Producción\nAgropecuaria, bajo los criterios de objetividad, equidad, transparencia, publicidad, selectividad y temporalidad, con estricto apego a la normatividad aplicable, por lo tanto será la encargada de la dispersión y asignación de los recursos del Programa apegándose plenamente a las reglas de operación siguientes:\nEJERCICIO FISCAL 2019.\nEL EJERCICIO FISCAL 2019.\n1.- INTRODUCCIÓN\n1.1 Antecedentes\n1.2 Alineación Programática\n1.3 Diagnóstico\nPARA MEJOR ENTENDIMIENTO DEL PROGRAMA SE DESARROLLA.\na) Misión\nb) Visión\n2.- DEPENDENCIA O ENTIDAD RESPONSABLE DEL PROGRAMA\nFUNDAMENTO LEGAL\n3.- OBJETIVOS Y ALCANCES\n3.1 Objetivo General\n3.2 Objetivos Específicos\n3.3 Alcances\n4.- METAS FÍSICAS\n5.- PROGRAMACIÓN PRESUPUESTAL\n6.- REQUISITOS Y PROCEDIMIENTOS DE ACCESO\n6.1 Difusión\n6.2 Requisitos de Acceso\n6.3 Procedimientos de Acceso\nEJERCICIO FISCAL 2019.\n6.4 Requisitos de Permanencia, Causales de baja o Suspensión Temporal\n6.5 Modos de entrega del beneficio\n7.- PROCEDIMIENTOS DE INSTRUMENTACIÓN\n7.1 Operación\n7.2 Gastos de operación\n8.- TRANSPARENCIA\n8.1 Difusión\n8.2 Blindaje electoral\n8.3 Supervisión y Control\n8.4 Mecanismos de Evaluación e Indicadores\n8.4.1 Evaluación\n8.4.2 Indicadores\n8.5 Auditoría\n8.6 Recursos no devengados\n8.7 Contraloría social\n8.8 Formas de participación social\n8.9 Procedimiento de Queja o Inconformidad Ciudadana\n8.10 Mecanismo de Exigibilidad\n8.11 Acta de Entrega-Recepción\n9.- CRITERIOS DE SELECCIÓN Y ELEGIBILIDAD\n9.1 Método de selección de beneficiarios\n10.- MECÁNICA DE OPERACIÓN\n10.1 Instancia ejecutora\n10.2 Instancia administrativa y/o normativa\nEJERCICIO FISCAL 2019.\n10.3 Delimitación de atribuciones\n11.- DERECHOS, OBLIGACIONES Y SANCIONES DE LOS BENEFICIARIOS\n11.1 Derechos\n11.2 Obligaciones\n11.3 Sanciones\n12.- INTERPRETACIÓN\nAnexos\nI. INTRODUCCIÓN\n1.1. ANTECEDENTES\nEl Programa se origina derivado de la urgente necesidad de atender las demandas de los productores agropecuarios y pesqueros acerca de obtener subsidios para la adquisición de equipos, herramientas, servicios, especies animales y obras agropecuarias, que en programas federales no son susceptibles de apoyos, pero que los productores en realidad utilizan en las labores diarias en sus unidades de producción rural.\nLa creación del programa, se fundamenta en el Plan Estatal de Desarrollo Rural 2016-2021, específicamente en el eje II Guerrero Próspero, el cual mandata promover la diversificación de la economía y aprovechar las potencialidades que existen en nuestro estado. Para que Guerrero tenga un cambio cualitativo en su economía, se contempla impulsar cinco proyectos estratégicos entre los que se encuentra la Producción Agroindustrial, estableciendo como objetivo construir un sector agropecuario y pesquero productivo que garantice la seguridad alimentaria del Estado.\nActualmente en la Ley Orgánica de la Administración Pública del Estado de Guerrero número 08, en su\nAgricultura, Ganadería, Pesca y Desarrollo Rural, como el órgano encargado de Promover y Fomentar el\nDesarrollo Agrícola, Forestal, Ganadero, Pesquero, así como el manejo de los recursos naturales en el\nEstado, procurando la participación de las mujeres, en igualdad de condiciones.\n1.2 ALINEACIÓN PROGRAMÁTICA\nEJERCICIO FISCAL 2019.\nEl programa está alineado al Plan Estatal de Desarrollo del Estado de Guerrero 2016-2021 y al Programa\nSectorial de Desarrollo Rural y Pesca 2016-2021, en el eje programático Guerrero Próspero, al objetivo 2.2\nImpulsar la productividad del sector agropecuario y pesquero, para garantizar la seguridad alimentaria, a la estrategia 2.2.1 Fortalecer los sectores agropecuario y pesquero y crear condiciones para aumentar la competitividad y la autosuficiencia para garantizar la seguridad alimentaria en la entidad y a las líneas de acción Apoyar en coordinación con los productores, a mercados nacientes como el de la floricultura y plantas ornamentales. La diversificación de productos guerrerenses es necesaria para detonar el desarrollo del sector agrícola y Promover la producción de ganado bovino, porcino y caprino en el Estado y su presencia en los mercados nacional y extranjero.\n1.3 DIAGNÓSTICO\na) Problema social: los productores agropecuarios y pesqueros, obtienen bajos ingresos por las actividades agropecuarias y pesqueras que realizan en sus unidades de producción.\nb) Causas y Efectos observados del Problema Social: Las causas por las que los productores obtienen escasos ingresos es derivado de las escasas cosechas agrícolas, escasa producción pecuaria y escasa pesca en sus unidades de producción rural. Los efectos que se observan en la población por los escasos ingresos, se refleja en un bajo poder adquisitivo, alimentación deficiente, bajo nivel educativo, alta incidencia de enfermedades y en general una mala calidad de vida.\nc) Resolución del problema identificado: Con el apoyo a los productores agropecuarios y pesqueros, en la adquisición de equipos, materiales, especies animales, insumos, maquinaria agrícola, apertura de caminos, e infraestructura, para el fomento y acceso a financiamiento y cultura agropecuaria, plataformas de información, contratación de servicios de asistencia técnica y capacitación, que coadyuven a realizar de manera más eficiente las labores agropecuarias y pesqueras, y que agreguen valor a la producción, contribuyendo a obtener mayor volumen en sus cosechas y obteniendo mejores ingresos por las ventas de los excedentes de sus cosechas.\nd) Línea Base: En el año 2016, se programó subsidiar a 7,000 productores agropecuarios y pesqueros.\ne) Población Potencial: La población total de la entidad es de 3,388,768, de los cuales, el 42% vive en el sector rural, mismos que por su productividad, rentabilidad y competitividad, los productores rurales, se ubican en tres segmentos, Productores de Menores Ingresos, en este segmento se encuentra el 78.7% de los productores y está conformado por productores de menores ingresos, temporaleros y su producción es para autoconsumo, el segundo segmento es el de Productores en transición, a este sector, corresponde el 20.9% de los productores, y productividad y competitividad y el tercer segmento, corresponde a los productores\nEJERCICIO FISCAL 2019. empresariales en los que se encuentran el 0.4% de los productores, estos productores están integrados al mercado nacional e internacional, son altamente eficientes y rentables.\nLa población objetivo para el presente programa, son los productores de Menores ingresos, temporales y que su producción es para autoconsumo.\na. NATURALEZA DEL PROGRAMA SOCIAL\nEl programa de Apoyos a la Producción Agropecuaria, es un programa social, que otorga subsidios para fomentar las actividades agropecuarias, pesqueras, acuícolas y de servicios en el medio rural de la entidad, a través de la adquisición de equipos, herramientas, servicios, especies animales y obras agropecuarias, de las zonas rurales.\nb. EL ORIGEN Y FUNDAMENTO rurales acerca de obtener subsidios para la adquisición de equipos, herramientas, servicios, especies animales y obras agropecuarias, que en programas federales no son susceptibles de apoyos, pero que los productores en realidad utilizan en las labores diarias en sus unidades de producción rural.\nLa creación del programa, se fundamenta en el Plan Estatal de Desarrollo Rural 2016-2021, específicamente en el eje II Guerrero Próspero, el cual mandata promover la diversificación de la economía\nEJERCICIO FISCAL 2019. y aprovechar las potencialidades que existen en nuestro estado. Para que Guerrero tenga un cambio cualitativo en su economía, se contempla impulsar cinco proyectos estratégicos entre los que se encuentra la Producción Agroindustrial, estableciendo como objetivo construir un sector agropecuario y pesquero productivo que garantice la seguridad alimentaria del Estado.\nActualmente en la Ley Orgánica de la Administración Pública del Estado de Guerrero número 08, última reforma publicada el día 28 de agosto de 2018, en su artículo 31 contempla a la Secretaria de Agricultura, Ganadería, Pesca y Desarrollo Rural, como el órgano encargado de Promover y Fomentar el Desarrollo\nAgrícola, Forestal, Ganadero, Pesquero, así como el manejo de los recursos naturales en el Estado, procurando la participación de las mujeres, en igualdad de condiciones.\nc. OBJETIVOS Y METAS\nEl programa tiene como objetivo fomentar en la población rural, la producción de alimentos a través del apoyo para la adquisición de maquinaria, insumos, especies animales, construcción de obras y mejora en las condiciones de infraestructura de caminos para el traslado de cosechas.\nLa meta es apoyar a 560 productores con diversos apoyos para el mejor desarrollo de sus actividades agropecuarias, acuícolas y de servicios.\nd. UBICACIÓN GEOGRÁFICA DE LOS PROYECTOS A DESARROLLAR\nEl programa se implementará en el Estado de Guerrero, abarcando las ocho regiones económicas:\n• Tierra Caliente\n• Norte\n• Centro\n• Montaña\n• Costa Grande\n• Costa Chica\n• Acapulco\n• Sierra e. Actividades a Realizar\nOtorgar subsidio para la adquisición de equipos, materiales, especies animales, insumos, maquinaria agrícola, apertura de caminos, e infraestructura, para el fomento y acceso a financiamiento y cultura agropecuaria, plataformas de información, contratación de servicios de asistencia técnica y capacitación, que coadyuven a realizar de manera más eficiente las labores agropecuarias y pesqueras, y que agreguen valor a la producción.\nLa Secretaria de Agricultura, Ganadería, Pesca y Desarrollo Rural, elaborará un catálogo de conceptos a apoyar por el programa, mismo que se encontrará disponible en la página electrónica\nEJERCICIO FISCAL 2019.\nAsimismo, la Secretaría de Agricultura, Ganadería, Pesca y Desarrollo Rural, de conformidad con la Ley de Contraloría y Transparencia Gubernamental, para la adquisición y dotación de los diversos apoyos que comprende el Programa, en caso de ser necesario.\nLa Secretaría de Agricultura, Ganadería, Pesca y Desarrollo Rural, vigilará que los beneficiarios cumplan con los requisitos para acceder al programa y entregará los apoyos a los beneficiarios.\nLa aportación que puedan hacer los beneficiarios será para complementar el subsidio otorgado por el\nGobierno del Estado. f. Instancias participantes\nLa ejecución del programa estará a cargo de la Secretaria de Agricultura, Ganadería, Pesca y Desarrollo\nRural del Gobierno del Estado de Guerrero. g. Presupuesto de Inversión\nEn el decreto número 182 del Presupuesto de Egresos del Estado de Guerrero, para el programa de Apoyos a la Producción Agropecuaria establece la inversión de $ 25,756,841.00 (Veinticinco millones setecientos cincuenta y seis mil ochocientos cuarenta y un pesos 00/M.N), presupuestos que derivado de las modificaciones presupuestales entre los programas que opera la Secretaría de Agricultura, Ganadería, Pesca y Desarrollo Rural, descendió a la inversión de $ 16,758,365.00 (Dieciséis millones setecientos cincuenta y ocho mil trescientos sesenta y cinco pesos 00/100 M.N. h. Glosario de Términos:\nSAGADEGRO: Secretaría de Agricultura, Ganadería, Pesca y Desarrollo Rural.\nSEPLADER: Secretaría de Planeación y Desarrollo Regional.\nCURP: Clave única de Registro de Población.\nUPP: Unidad de Producción Pecuaria.\nRNPA: Registro Nacional de Pesca y Acuacultura.\nRFC: Registro Federal de Contribuyentes.\nPARA MEJOR ENTENDIMIENTO DEL PROGRAMA SE DESARROLLA.\na) MISIÓN\nImpulsar la producción de alimentos, mediante el otorgamiento de subsidios a productores rurales, para la adquisición de maquinaria, insumos, especies animales, construcción de obras y mejora en las condiciones de infraestructura de caminos para el traslado de cosechas, contribuyendo a elevar la productividad, la calidad, la inocuidad y la competitividad de los sectores agropecuarios, pesqueros y acuicolas, privilegiando la autosuficiencia agroalimentaria, así como el incremento al valor agregado y la comercialización de sus productos, a fin de mejorar la economía y las condiciones de vida de las familias del medio rural.\nEJERCICIO FISCAL 2019.\nb) VISIÓN\nSer el programa generador del desarrollo económico y sociocultural de la población rural de Guerrero, que transforme la pobreza alimentaria y económica, en soluciones y oportunidades a través de políticas públicas rentables, integrales y sustentables, mediante el impulso a la producción, la transformación y la comercialización de los productos agropecuarios, pesqueros y acuícolas, obteniendo así productos con potencial competitivo en los mercados regionales, nacional e internacional, que repercutan directamente en el bienestar social de los guerrerenses.\n2. DEPENDENCIA O ENTIDAD RESPONSABLE\n2.1 La Secretaría de Agricultura, Ganadería, Pesca y Desarrollo Rural, será la responsable directa de la ejecución del programa.\n2.2 En la operación del programa participará la Subsecretaría de Desarrollo Rural Sustentable, la\nSubsecretaría de Agricultura e Infraestructura Rural, la subsecretaría de Ganadería y Pesca, y la\nDelegación Administrativa de la SAGADEGRO.\n2.3 El programa solo lo ejercerá la SAGADEGRO.\n2.4 La Subsecretaría de Desarrollo Rural Sustentable, será la encargada de registrar las solicitudes presentadas por los productores, presentarlas ante el Secretario de la SAGADEGRO, para su autorización correspondiente, posteriormente turnará a las Subsecretarías de Agricultura e Infraestructura Rural, y de\nGanadería y Pesca, para que revisen e integren las solicitudes en coordinación con los productores, estas subsecretarías, elaborarán las notificaciones de autorización para los productores, mismos que presentarán el acta de entrega recepción y la factura del bien adquirido, en las subsecretarías de Agricultura e Infraestructura Rural y de Ganadería y Pesca, para que realicen el trámite de pago ante la Delegación\nAdministrativa, esta delegación, realizará el pago de los apoyos adquiridos al productor o al proveedor, según sea requerido por el productor.\n2.5 La SAGADEGRO será la dependencia involucrada en la operación del programa, así como las Subsecretarías de Desarrollo Rural Sustentable, la Subsecretaría de Agricultura e Infraestructura Rural, la Subsecretaría de Ganadería y Pesca y la Delegación Administrativa de la SAGADEGRO.\n2.6 La SAGADEGRO, es la entidad que será la responsable en la planeación y ejecución del programa.\nFundamento Legal\nEJERCICIO FISCAL 2019.\nLas presentes reglas de operación, tienen su fundamento en las siguientes leyes, decretos presidenciales y secretariales.\nGuerrero, Número 18, 19 y 20 del 3, 10 y 17 de noviembre de 1917 y número 1 del 5 de enero de 1918, artículos 1 58, 59 y 74 en su fracción XXXVII.\nLeyes:\n➢ Ley de Desarrollo Rural Sustentable, publicada en el Diario Oficial de la Federación de fecha 7 de diciembre del 2001, artículos 1,2,3,4,5,6,7,8,9,12,13,17,21 y 178; DOF de fecha 22712/2017\nDecreto por el que reforman y adicionan los artículos 3°., 143, 145 y 191 a esta Ley.\n➢ Ley Número 814 de Desarrollo Rural Sustentable del Estado de Guerrero, publicada en el Periódico\nOficial del Gobierno del Estado de Guerrero, de fecha 21 de octubre de 2011, artículos 1,2,3,4,6 y\n7;\nOficial del Gobierno del Estado de Guerrero, de fecha 26 de diciembre de 2008, artículos 1,2,3,4,5 y 6; última reforma publicada en el periódico oficial el 13 de septiembre de 2016.\n➢ Ley de Administración de Recursos Materiales del Estado de Guerrero, publicada en el Periódico\nOficial del Gobierno del Estado número 99, de fecha 29 de noviembre de 1988.\n➢ Ley 207 de Transparencia y Acceso a la Información Pública del Estado de Guerrero, dictaminada por el H. Congreso del Estado, el 5 de mayo de 2016 y publicada en el Periódico Oficial del Estado de Guerrero número 37 alcance I, el viernes 06 de mayo de 2016.\n➢ Ley Orgánica de la Administración Pública del Estado de Guerrero, número 08, en el Artículo 31 establece que La Secretaría de Agricultura, Ganadería, Pesca y Desarrollo Rural, es el órgano encargado de promover y fomentar el desarrollo agrícola, forestal, ganadero, pesquero, así como del manejo de los recursos naturales en el Estado, procurando la participación de las mujeres, en igualdad de condiciones en estas actividades de diseño y planeación y cumplimiento correspondiéndole el despacho de los asuntos siguientes:\n➢ El Plan Estatal de Desarrollo 2016-2021 específicamente en el eje II Guerrero Próspero, establece diversificar la economía y aprovechar las potencialidades que existen en nuestro Estado, para que\nGuerrero tenga un cambio cualitativo en su economía, teniendo como objetivo construir un sector agropecuario y pesquero productivo que garantice la seguridad alimentaria del Estado.\nI. - Elaborar los planes, programas y acciones, de corto, mediano y largo plazo, del sector agropecuario, forestal y pesquero, que respondan a un criterio de manejo sustentable de los recursos naturales, con la participación de las dependencias federales y estatales correspondientes, ayuntamientos, organizaciones de productores individuales y campesinos, en el seno de la Secretaría de Planeación y Desarrollo Regional y coordinar su implementación;\nII. - Formular y ejecutar los planes, programas y acciones para el desarrollo integral de las personas que viven y trabajan en zonas rurales del Estado, principalmente aquellos dirigidos a mejorar las condiciones de las mujeres;\nEJERCICIO FISCAL 2019.\nIII. - Fomentar, formular, supervisar y coordinar la operación de los programas de desarrollo agrícola, ganadero, pesquero con criterios de manejo sustentable de los recursos naturales.\nIV.- Apoyar la organización para la producción, coordinando con las dependencias federales afines y productores, las acciones para el financiamiento, seguros, insumos, asistencia técnica y administrativa, investigación, capacitación y transferencia de tecnología, en beneficio de mujeres, campesinos, ejidatarios, comuneros, pequeños propietarios y organizaciones de productores legalmente constituidos;\n➢ Decreto 182 del Presupuesto de Egresos del Estado de Guerrero, publicado en el\nPeriódico Oficial del Gobierno del Estado de Guerrero de fecha 09 de enero de 2019.\nSe atenderá a productores de escasos recursos económicos que se dediquen a actividades productivas en el medio rural.\n3. OBJETIVOS Y ALCANCES\n3.1 Objetivo General\nCoadyuvar en la capitalización de las unidades de producción rural y mejorar el nivel de vida de los habitantes de las zonas rurales a través del apoyo en la adquisición de maquinaria, insumos, especies animales, construcción de obras menores y mejora en las condiciones de infraestructura de caminos para el traslado de cosechas.\n3.2 Objetivo Específico\nSubsidiar la adquisición de maquinaria, insumos, especies animales, construcción de obras menores y mejora en las condiciones de infraestructura de caminos para el traslado de cosechas, para fomentar la producción de alimentos en las zonas rurales de la entidad.\n3.3 Alcances\nBuscando que los productores agropecuarios y pesqueros, sean capaces de obtener mayor volumen en sus cosechas y los excedentes sean comercializados para obtener ingresos que mejoren su nivel de vida, a través de apoyos o subsidios a este sector; garantizando el derecho al trabajo como lo especifica el\nCONEVAL (consejo Nacional de Evaluación de la Política de Desarrollo Social)\n4. METAS FÍSICAS\nLa meta del programa, es apoyar a 560 productores con diversos apoyos para el mejor desarrollo de sus actividades agropecuarias, pesqueras y acuícolas y de servicios.\n5. PROGRAMACIÓN PRESUPUESTAL\nEJERCICIO FISCAL 2019.\n5.1 El monto total del presupuesto autorizado para el ejercicio fiscal es de $ 25,756,841.00 (Veinticinco millones setecientos cincuenta y seis mil ochocientos cuarenta y un pesos 00/100 M.N.), y derivado de modificaciones presupuestales, la inversión que se ejercerá, desciende a $ 16,758,365.00 (Dieciséis millones setecientos cincuenta y ocho mil trescientos sesenta y cinco pesos 00/100 M.N.)\n5.2 El calendario de gasto es el siguiente:\n6. REQUISITOS Y PROCEDIMIENTOS DE ACCESO\nPara la obtención de los apoyos, los productores agropecuarios, pesqueros y acuícolas, deberán observar y cumplir con los requisitos:\n6.1. DIFUSIÓN\nLa Secretaría de Agricultura, Ganadería, Pesca y Desarrollo Rural, dará amplia difusión de los programas que ejecuta y opera a través de diferentes medios de comunicación impresos y electrónicos para que la población conozca los beneficios y requisitos de los programas. la Secretaría de Agricultura, Ganadería, Pesca y Desarrollo Rural.\nLos horarios de atención a los productores, será de lunes a viernes de 09:00 a 16:00 horas en las instalaciones de la SAGADEGRO, sita en Carretera Nacional México - Acapulco Km 274.5, Colonia\nBurócratas, teléfono 01 747 1 92 10.\nEl programa también será difundido en reuniones por personal de la SAGADEGRO, quienes se apoyaran interesados deben reunir.\nEJERCICIO FISCAL 2019.\nLa cobertura del programa será estatal, ateniéndose los productores agropecuarios, pesqueros y acuicolas de la entidad.\n6.2 Requisitos de Acceso\nLos productores interesados en obtener beneficios del programa, deberán presentar en la ventanilla de la\nSecretaria de Agricultura, Ganadería, Pesca y Desarrollo Rural, la siguiente documentación:\nApoyos de manera individual:\nPara la obtención del apoyo los interesados deberán presentar o Solicitud de apoyo en el formato establecido (Anexo a), proporcionado en la Secretaría de\nAgricultura, Ganadería, Pesca y Desarrollo Rural y disponibles en la página www.campoguerrero.gob.mx, ó Anexo I del programa de Concurrencia. o Comprobante de domicilio con vigencia no mayor a tres meses o Copia de identificación oficial vigente (credencial de elector, pasaporte, cartilla de servicio militar nacional o cédula profesional). o Copia de la CURP o Documento que acredite la actividad productiva o En el caso de apoyos a solicitudes provenientes del Programa de Concurrencia, deberán presentar para el caso de proyectos pecuarios la constancia UPP (unidad de producción pecuaria) y para proyectos pesqueros y/o acuícolas el RNPA (registro nacional de pesca y acuacultura) y para proyectos de apicultura clave de rastreabilidad de miel.\nApoyos a productores organizados en grupos o Presentar solicitud de apoyo en el formato establecido, (Anexo a), firmada por el representante del grupo, ó Anexo I del programa de Concurrencia. o Comprobante de domicilio con vigencia no mayor a tres meses o Copia de las identificaciones oficiales vigentes (credencial de elector, pasaporte, cartilla de servicio militar nacional o cédula profesional). o Copia de la CURP o Acta constitutiva de grupo de trabajo o Relación de integrantes del grupo o En el caso de apoyos a solicitudes provenientes del Programa de Concurrencia, deberán presentar para el caso de proyectos pecuarios la constancia UPP y para proyectos pesqueros y/o acuícolas el RNPA y para proyectos de apicultura clave de rastreabilidad de miel.\nPara la obtención de garantías líquidas, deberán presentar los siguientes requisitos: o Autorización de la línea de crédito.\nEJERCICIO FISCAL 2019. o Contrato del fideicomiso o Proyecto del crédito. o Acta constitutiva del sujeto de crédito (en caso de personas morales) o RFC\no CURP o Comprobante de domicilio\n6.3. Procedimiento de Acceso\n6.3.1 El programa surge por la demanda ciudadana específicamente de los productores agropecuarios y pesquero mismo que deberán presentar la solicitud de apoyo, conforme al anexo a) y/o el formato Anexo\n1. Adjuntando los requisitos establecidos en el numeral 6.2 de estas reglas de operación\n6.3.2 Los criterios para ser beneficiarios, son: presentar su solicitud de apoyo, acompañada de la documentación personal, posteriormente, la SAGADEGRO, analizara y viabilidad de apoyo de la solicitud, en base a la disposición presupuestal del programa.\n6.3.3 La documentación será recepcionada en las instalaciones que ocupa la SAGADEGRO, de lunes a viernes en horario de 09:00 a 16:00 horas.\n6.3.4 Se dará prioridad de atención a las solicitudes de apoyo, dirigidas a cultivos de mayor relevancia para la entidad.\n6.3.5 Las solicitudes de apoyo autorizadas, podrán ser consultadas en la página electrónica www.campoguerrero.gob.mx, de la SAGADEGRO.\n6.3.6 La SAGADEGRO, entregará un comprobante al productor de haber completado su registro en el programa.\n6.3.7 Los productores que sean autorizados con apoyos del programa, serán incorporados al Padrón Único de Beneficiarios de la SAGADEGRO, siendo reservados sus datos personales en base a la Ley 207 de para propósitos de proselitismo político, religioso o comercial, ni para ningún otro distinto al establecido en las presentes reglas de operación.\n6.3.8 En ningún caso las y los servidores públicos podrán solicitar o proceder de manera diferente a lo establecido en las reglas de operación.\nSe atenderán las solicitudes de apoyo hasta en tanto exista disponibilidad presupuestal por el programa.\nEJERCICIO FISCAL 2019.\n30 días hábiles)\n6.4 Requisitos de Permanencia, Causales de Baja o Suspensión Temporal\n6.4.1 El beneficiario está obligado a:\n• Dar buen uso, conservación y/o mantenimiento de los bienes recibidos Otorgar las facilidades y proporcionar la información necesaria a las instancias de coordinación, supervisión y control de los niveles de gobierno facultados para realizar visitas de inspección y monitoreo de los apoyos otorgados.\n• Seguir las recomendaciones técnico-productivas emitidas por las instancias de gobierno.\n• Mantener los apoyos por un plazo mínimo de tres años con el fin de que estén disponibles para las supervisiones físicas y documentales de las instancias de control y fiscalización\nSanciones\n• Los beneficiarios del programa que incumplan con las obligaciones, y/o presenten documentos falsos, la instancia normativa, definirá la sanción a la que se hará acreedor; el incentivo y requerida la devolución del mismo, más los productos financieros generados y será registrado por parte de la instancia Ejecutora o la Unidad Responsable en el directorio de personas físicas y/o morales que pierden su derecho de recibir incentivos, hasta en tanto no se subsane el incumplimiento detectado.\n6.5 Modos de entrega del beneficio documentación en los formatos establecidos, se les comunicará los lugares para la entrega de los apoyos,\n7. PROCEDIMIENTOS DE INSTRUMENTACIÓN\n7.1 Operación\n7.1.1 Para acceder a los beneficios del programa, los productores presentarán en la SAGADEGRO, la solicitud en el formato establecido, misma que será registrada, analizada y dependiendo de la suficiencia presupuestal, se le notificará al productor que haya sido beneficiado, para que continúe con la adquisición, comprobación y se le tramite el pago del beneficio.\nEJERCICIO FISCAL 2019.\n7.1.2 En las subsecretarías de Agricultura e Infraestructura Rural, Ganadería Pesca y de Desarrollo Rural\nSustentable y la Delegación Administrativa de la SAGADEGRO, serán las responsables de coordinar esfuerzos para la operación del programa.\n7.1.3. Los datos personales de las personas beneficiarias del programa, y la información adicional generada y administrada, se regirá por lo establecido en la Ley No. 207 de Transparencia y Acceso a la Información\nPública del Estado de Guerrero.\n7.1.4. Los formatos y los trámites a realizar para la obtención del beneficio del programa, son gratuitos.\n7.2. Gastos de Operación.\nPara cubrir los gastos ocasionados por la operación, seguimiento, supervisión y verificación de las acciones del programa, se dispondrá hasta el 3% de la inversión total del programa. Estos recursos corresponden al capítulo 4000 de la apertura programática.\nEn la erogación de los gastos de operación se deberán observar los criterios de racionalidad, austeridad presupuestal, propiciando la eficiencia, eficacia y transparencia.\n8 TRANSPARENCIA\n8.1 Difusión\nLa SAGADEGRO, dará amplia difusión al programa Apoyos a la Producción Agropecuaria, a nivel estatal a través de la página electrónica campoguerrero.gob.mx, folletos y en reuniones que se organicen por región y/o municipio, así como con organizaciones de productores, y para mayor información acudir a las instalaciones que ocupa la SAGADEGRO, sita en Carretera Nacional México-Acapulco km 274.5 Colonia\nBurócratas, Chilpancingo de los Bravo, de lunes a viernes en horario de 09:00 a 16:00 horas, o llamar al teléfono 017474719210.\nLa papelería, publicidad y promoción del programa incluirá la leyenda descrita en el apartado \"Blindaje\nElectoral\".\nLa información de montos y beneficiarios se publicará en los términos de la ley No. 207 de Transparencia y Acceso a la Información Pública del Estado de Guerrero.\n8.2 Blindaje electoral\nPara blindar al programa del clientelismo y que no sea utilizado para usos partidistas, en la documentación siempre deberán incluir la leyenda siguiente:\n\"Este programa es público ajeno a cualquier partido político. Queda prohibido el uso para fines distintos a los establecidos en el programa\".\nEJERCICIO FISCAL 2019.\n8.3. Supervisión y Control\na) Como procedimiento interno de supervisión y control del programa, se utilizarán informes mensuales, trimestrales, semestrales y anuales.\nb) Las Subsecretarías de Agricultura e Infraestructura Rural, Ganadería y Pesca y de Desarrollo Rural\nSustentable y la Delegación Administrativa de la SAGADEGRO, serán las responsables de coordinar esfuerzos para la operación del programa.\nc) Se enviarán trimestralmente a la Secretaría de Finanzas, a la Secretaría de Planeación y a la Secretaría de Contraloría, informes sobre el Presupuesto ejercido establecidos por el Consejo Nacional de\nArmonización Contable (CONAC) y con base en los indicadores de resultados previstos en las Reglas de\nOperación.\nd) Se adicionaran a los informes, la evaluación de los indicadores determinados en el programa.\ne) La SAGADEGRO, remitirá a la SEPLADER, el calendario de entrega de los apoyos.\nf) La SAGADEGRO integrará un Padrón Único de Beneficiarios del programa.\n8.4 Mecanismo de Evaluación e Indicadores.\n8.4.1 Evaluación.\nCon el propósito de conocer los resultados de los programas y proyectos sociales, se solicitará sea evaluado por alguna institución académica y de investigación u organismo especializado de carácter nacional, que cuenten con reconocimiento y experiencia en la materia; y en los términos de las disposiciones establecidas por las instancias normativas correspondientes.\n8.4.2 Indicadores\nNivel de objetivo Objetivo Indicador Fó n Res able\nSupuestos\nContribuir a Incremento en el mejorar el ingreso ingreso de los de los productores productores\nIngreso en el año\nEvaluación de\nLas condiciones\nFin anterior / Ingreso Eficacia Porcentaje Subsecretarías macroeconómicas se agropecuarios, agropecuarios, los programas del año actual mantienen estables. pesqueros y pesqueros y acuícolas acuícolas\nEJERCICIO FISCAL 2019. productores Unidades de\nUnidades de agropecuarios, producción pesqueros y agropecuarias, producción\nAvances físicos\nLas condiciones\nPropósito apoyadas / Eficiencia Porcentaje Subsecretarías macroeconómicas se acuícolas, tienen pesqueras y y financieros\nUnidades de mantienen estables. sus unidades de acuícolas producción total producción apoyadas equipadas\nOtorgar subsidio\nNúmero de para la adquisición Beneficiarios\nComponentes\n, s, o s, /\nSubsecretarías\n. obras programados acuícolas agropecuarias, pesqueras y acuícolas\nPresupuesto Las condiciones\nPago de apoyos a Avance financiero\n/ o Eficiencia Porcentaje ro s Subsecretarías\n. ejercido los productores del programa\nActividades\nEventos\nDifusión del\nEventos de realizados /\nLas condiciones difusión Eficiencia Eventos Reuniones Subsecretarías macroeconómicas se\nPrograma Eventos realizados mantienen estables. programados\n8.5 Auditoria\nLos recursos ejercidos en el programa, podrán ser fiscalizados por el Órgano Estatal de Control y demás instancias que el ámbito de sus respectivas atribuciones resulten competentes.\nComo resultado de las acciones de auditoria que se lleven a cabo, el Órgano Estatal de Control mantendrá un seguimiento interno que permita emitir los informes de las revisiones practicadas, dando principal importancia a la atención en tiempo y forma, de las irregularidades detectadas, hasta su total solventación.\n8.6 Recursos no devengados\nEl presupuesto autorizado que no se aplique a los fines autorizados, y los recursos que por cualquier motivo no estén devengados al 31 de diciembre, serán reintegrados a la Tesorería de la Secretaría de Finanzas y\n8.7 Contraloría social\nSe establecerán acciones de control, vigilancia y evaluación, bajo un esquema de derechos y compromisos ciudadanos, con el propósito de contribuir a que la gestión gubernamental se realice en términos de transparencia, eficacia y honradez.\nEstas actividades estarán a cargo de los miembros de la comunidad, incluidos los integrantes del comité o instancia asociativa de los beneficiarios del programa.\nEJERCICIO FISCAL 2019. efecto, fomentando acciones que transparenten la operación del programa en cuestión.\nLas acciones a fomentar serán las siguientes:\na) Informar a la ciudadanía acerca de los apoyos otorgados y su costo a nivel de obra, acción, nombre de los beneficiarios, derechos y obligaciones de los mismos.\nb) Capacitar a los beneficiarios para que se constituyan en instancias de vigilancia y evaluación social.\nc) Establecer espacios de comunicación (reuniones vecinales, atención directa a beneficiarios, etc).\nd) Promover la integración de organizaciones de la sociedad civil en acciones de contraloría social.\ne) Instrumentar mecanismos de recepción y atención de quejas y denuncias. El Órgano Estatal de Control verificará, en lo correspondiente, la realización de dichas acciones.\n8.8 Formas de Participación Social\nDe acuerdo con las leyes de Desarrollo Social y de Participación Ciudadana del Estado de Guerrero, la sociedad podrá participar activamente en la planeación, programación, implementación y evaluación de los programas y acciones de desarrollo social, por lo que para el programa, será en el seno del Consejo\nGuerrerense para el Desarrollo Rural Sustentable, donde se informará del seguimiento del mismo, este consejo, está conformado por organizaciones productivas, sistemas productos, Organismos Públicos\nDescentralizados, gremios y colegios de profesionistas, así como por dependencias federales y estatales.\n8.8.1 En el año, el Consejo Guerrerense para el Desarrollo Rural Sustentable, sesiona cuatro ocasiones, para planear, programar, informar de la implementación así como de las evaluaciones de los programas en el sector agropecuario y pesquero.\n8.8.2 La modalidad de participación del Consejo Guerrerense para el Desarrollo Rural Sustentable, es de información, consulta, decisión y deliberación de las acciones al sector agropecuario y pesquero, como se describe en el siguiente cuadro.\nParticipante Modalidad\nEtapa en la que Forma de participa Participación\nConsejo Planeación, Planeación, Información, Guerrerense para Programación. Programación y Consulta y el Desarrollo evaluación deliberación\nRural\nSustentable\nEJERCICIO FISCAL 2019.\n8.9 Procedimiento de Queja o Inconformidad Ciudadana recursos por parte de servidores públicos, se captarán por la Contraloría y la Auditoría General del Estado, a través de denuncias por escrito, vía internet, vía telefónica y por comparecencia del interesado. El sitio es www.contraloria.guerrero.gob.mx, y al teléfono 01 800 000 7422.\nEl denunciante o quejoso deberá proporcionar los siguientes datos:\na) Nombre del Servidor (s) Público (s)\nb) Dependencia de adscripción\nc) Objeto de la denuncia\nd) Nombre y domicilio del quejoso\ne) Identificación Oficial\n8.10 Mecanismos de Exigibilidad\nLos productores podrán verificar el estatus de su solicitud en la página electrónica campoguerrero.gob.mx.\n8.11. Acta de Entrega Recepción\nPara cada una de las obras terminadas o acciones entregadas, se elaborará un acta de entrega-recepción, en la que participará un representante de la Secretaría de Agricultura, Ganadería, Pesca y Desarrollo Rural y un representante de la comunidad beneficiada y/o un beneficiario. conformidad con el acta de entrega-recepción, la comunidad o el orden de gobierno que recibe las obras o acciones, deberá hacer explícito en el acta el compromiso de vigilar su adecuada operación y darle el mantenimiento correspondiente.\nEl acta de entrega-recepción forma parte del expediente de la obra y/o acción y que constituye la prueba documental que certifica la existencia de la misma.\nEs responsabilidad de la Secretaría de Agricultura, Ganadería, Pesca y Desarrollo Rural, resguardar las actas de entrega recepción, así como el expediente de la obra o acción.\nEJERCICIO FISCAL 2019.\n9. Criterios de selección y elegibilidad\n9.1 Método de selección de beneficios\nSerán susceptibles de apoyos todos los productores y/o productoras, de bajos ingresos del medio rural que se dediquen o quieran dedicarse a realizar actividades agrícolas, pecuarias, pesqueras y forestales.\nPara ser beneficiarios, deberán cumplir con presentar la documentación requerida en el numeral 8.2 de las presentes reglas de operación, según sea el caso de solicitar apoyo de manera individual o por grupo u organización.\n10 Mecánica de Operación\nLa Secretaría de Agricultura Ganadería, Pesca y Desarrollo, designará un responsable del Programa y un auxiliar administrativo quienes llevarán un puntual seguimiento a las solicitudes recibidas para ser apoyadas por el programa y presentarán las solicitudes recibidas ante la Secretaria de Agricultura, Ganadería, Pesca y Desarrollo Rural, para que a través de su titular emita la autorización correspondiente, la cual se notificará de manera escrita a los beneficiarios del programa, especificándole el concepto y monto de apoyo a recibir, así como los plazos de tiempo para hacer efectivo el apoyo, esta notificación se realizará a más tardar en 5 días hábiles de haber presentado la solicitud de apoyo.\nLa Secretaría de Agricultura, Ganadería, Pesca y Desarrollo Rural, entregará el bien, el subsidio o el apoyo que corresponda y el beneficiario firmará el acta de entrega recepción.\nEl responsable del programa integrará los expedientes de los beneficiarios, incluyendo el acta de entrega recepción y la factura correspondiente, para las revisiones a que haya lugar por parte de la Secretaría de\nContraloría y Transparencia Gubernamental.\n10.1. Instancia ejecutora\nLa Secretaría de Agricultura, Ganadería, Pesca y Desarrollo Rural, será la dependencia que ejercerá los recursos del programa, también, tendrá la responsabilidad de verificar que la formulación de los expedientes técnicos de los proyectos, reúnan los requisitos exigidos por la instancia normativa, tales como apego a la planeación estratégica, programación, presupuestación, calendario de ejecución, ejercicio y control del gasto público.\n10.2 Instancia administrativa y/o normativa\nLa Auditoría y la Contraloría, vigilarán que la ejecución del programa sea con apego a la normatividad para asegurar el cumplimiento de los objetivos y metas trazados.\nEJERCICIO FISCAL 2019.\n10.3. Delimitación de atribuciones\nLa Ley Orgánica de la Administración Pública del Estado de Guerrero, número 08, en el Artículo 31 establece que La Secretaría de Agricultura, Ganadería, Pesca y Desarrollo Rural, es el órgano encargado de promover y fomentar el desarrollo agrícola, forestal, ganadero, pesquero, así como del manejo de los recursos naturales en el Estado, procurando la participación de las mujeres, en igualdad de condiciones en estas actividades de diseño y planeación y cumplimiento correspondiéndole el despacho de los asuntos siguientes:\nI.- Elaborar los planes, programas y acciones, de corto, mediano y largo plazo, del sector agropecuario, forestal y pesquero, que respondan a un criterio de manejo sustentable de los recursos naturales, con la participación de las dependencias federales y estatales correspondientes, ayuntamientos, organizaciones de productores individuales y campesinos, en el seno de la Secretaria de Planeación y Desarrollo Regional del Estado de Guerrero, y coordinar su implementación;\nII. - Formular y ejecutar los planes, programas y acciones para el desarrollo integral de las personas que viven y trabajan en zonas rurales del Estado, principalmente aquellos dirigidos a mejorar las condiciones de las mujeres;\nIII. - Fomentar, formular, supervisar y coordinar la operación de los programas de desarrollo agrícola, ganadero, pesquero con criterios de manejo sustentable de los recursos naturales.\nIV. - Apoyar la organización para la producción, coordinando con las dependencias federales afines y productores, las acciones para el financiamiento, seguros, insumos, asistencia técnica y administrativa, investigación, capacitación y transferencia de tecnología, en beneficio de mujeres, campesinos, ejidatarios, comuneros, pequeños propietarios y organizaciones de productores legalmente constituidos.\n11. Derechos, obligaciones y sanciones de los beneficiarios de programas sociales\n11.1 Derechos rectores de desarrollo social, así como a recibir un trato digno y respetuoso en los términos establecidos en la constitución política de los Estados Unidos Mexicanos.\n11.2 Obligaciones\n• Dar buen uso, conservación y/o mantenimiento de los bienes recibidos\n• Otorgar las facilidades y proporcionar la información necesaria a las instancias de coordinación, supervisión y control de los niveles de gobierno facultados para realizar visitas de inspección y monitoreo de los apoyos otorgados.\nEJERCICIO FISCAL 2019.\n• Seguir las recomendaciones técnico-productivas emitidas por las instancias de gobierno.\n• Mantener los apoyos por un plazo mínimo de tres años con el fin de que estén disponibles para las supervisiones físicas y documentales de las instancias de control y fiscalización.\n11.3 Sanciones\nLos beneficiarios del programa que incumplan con las obligaciones, y/o presenten documentos falsos, la instancia normativa, definirá la sanción a la que se hará acreedor; le incentivo y requerida la devolución del mismo, más los productos financieros generados y será registrado por parte de la instancia Ejecutora o la\nUnidad Responsable en el directorio de personas físicas y/o morales que pierden su derecho de recibir incentivos, hasta en tanto no se subsane el incumplimiento detectado.\n12 Interpretación\nLa interpretación de las reglas de operación, para efectos administrativos, estará a cargo de la Secretaría de Agricultura, Ganadería, Pesca y Desarrollo Rural como dependencia responsable del programa, así como de la Secretaría de Contraloría y Transparencia Gubernamental.\nEJERCICIO FISCAL 2019.\n1. Resumen Ejecutivo, Técnico y Financiero\n2. Nombre del proyecto.\n3. Programa, componente(s), concepto(s) de apoyo, inversión total, desglose de apoyo solicitado y de aportación del solicitante, de créditos, de otros programas e instituciones, entre otros.\n4. Objetivo(s) general(es) y específico(s)\n5. Justificación a. Antecedentes. b. Descripción de la situación actual de la empresa, en su caso características y experiencias del grupo o participantes. c. Descripción de la problemática u oportunidad identificada. d. Forma en la que el proyecto, de concretarse, abordará la problemática u oportunidad identificada. e. Metas, de concretarse el proyecto, que corresponden con la problemática identificada e indicadores que permitirán verificar el cumplimiento del(los) objetivo(s) general(es) y específico(s). f. Análisis y diagnóstico de la situación actual y previsiones sin el proyecto. g. En su caso, misión y visión del grupo y proyecto.\n6. Datos generales y aspectos técnicos del proyecto a. Localización geográfica del proyecto (Entidad Federativa, Municipio y localidad, ejido o predio y referencias para localización en su caso, núcleo agrario, coordenadas georreferenciadas, así como la localización específica del proyecto o microlocalización de acuerdo a la norma técnica del INEGI).\nAdemás: clima, suelo, condiciones climáticas, vegetación, fuentes de aprovisionamiento de agua, condiciones socio ambiental, asociaciones vegetales, agrodiversidad productiva, según aplique. b. Actividad productiva, eslabón de la cadena de valor, y en su caso, ciclo agrícola y productivos, producto(s) o especie(s) involucrada(s). de acuerdo al tipo d3e proyecto. c. Descripción técnica del proyecto, la cual deberá partir del concepto de apoyo y describir de forma detallada el mismo (plano, croquis de ubicación y distribución de la unidad de producción y así mismo del arreglo interno de los equipos y esquemas del proceso, tipo de maquinaria, infraestructura, en su caso terrenos de uso agrícola y/o pecuario, ganado, material vegetativo (de ser el caso), equipo, procesos, tecnologías a emplear, monto de cada concepto a solicitar, capacidad de procesos, programas de producción y mantenimiento, asistencia técnica, consultoria y/o capacitación, escenarios con diferentes volúmenes de proceso, entre otros). d. Proceso de reconversión (en su caso).\nEJERCICIO FISCAL 2019. e. Cotizaciones de proveedores, que sustenten los costos reales y actuales al momento de la presentación del proyecto, presupuestos de las inversiones a realizar (por lo menos dos cotizaciones de distintos proveedores). f. Datos generales del solicitante (persona física, moral, grupo, comité, Asociación Civil, Institución, en su caso), aspectos organizativos, antecedentes, tipo de organización y relación de socios, miembros, integrantes y/o de representantes del comité; estructura, Consejo directivo, de ser procedente.\nPara los Comités Sistema Producto, además deberá incluir un listado de representantes gubernamentales, no gubernamentales y eslabones. Para Comités Sistema Producto, convenios vigentes con otras instituciones y fecha de constitución legal. g. Consejo directivo, perfil requerido y capacidades de los directivos y de los operadores (en su caso). h. Infraestructura y equipo actual (disponibles para el proyecto), de ser el caso, así como condiciones de uso y valoración de activos que aporta la sociedad. i. Permisos y cumplimiento de normas sanitarias, ambientales y otras. j. Para infraestructura (obra civil): catálogo de conceptos, especificaciones, presupuesto, planos según aplique, de cimentación, estructural, arquitectónico, instalaciones sanitarias, eléctricas e hidráulicas, y de detalle, cálculos de diseño, volumen de construcción, suscritos por un técnico responsable del proyecto con Cédula Profesional, componentes del proyecto, volúmenes de construcción y permisos aplicables. k. Documentos con los que se acredite la propiedad o legal posesión. l. Programas de ejecución, de administración de recursos humanos, en su caso, calendario, administrativos, de capacitación y asistencia técnica o consultoría. m. En su caso, validación del paquete tecnológico por la autoridad competente n. Desarrollo de estrategia; descripción detallada de las actividades que se implementarán para el cumplimiento de objetivos y metas, así como localización y descripción específica de donde se llevará a cabo el proyecto p. En su caso, entregables que permitan comprobar la realización de las actividades. p. Reglamento de uso presente y futuro de los apoyos otorgados. q. Proyección de riesgos.\n7. Análisis y aspectos de Mercados a. Descripción, propiedades, características y análisis de materias primas, productos y subproductos (presentación, empaque, embalaje; naturaleza, calidad, valor, evolución, cantidad, atributos, consumo, precios, balanza comercial, entre otros que apliquen), volumen de la b. Disponibilidad, accesibilidad y condiciones y mecanismos de abasto de insumos, materias primas y servicios. c. Canales de distribución y venta. d. Plan y estrategia de comercialización. e. En su caso, cartas de intención de compra o contrato(s) de compra-venta recientes y referidas al producto ofrecido, o de abasto de materias primas y cotizaciones para el aseguramiento de las inversiones, que contengan nombre y domicilio de los clientes, volumen estimado de producto,\nEJERCICIO FISCAL 2019. precio estimado, lugares y periodos de entrega recepción, forma y plazo de pago para los productos a generar con el proyecto. f. Estudios de mercado realizados (en su caso). g. Estimación de beneficios económico del proyecto. h. Análisis de fortalezas, oportunidades, debilidades y amenazas (FODA). i. Mercado objetivo.\n8. Análisis Financiero a. Evaluación financiera del proyecto, la cual debe contener flujo de efectivo, el cálculo de la Tasa\nInterna de Rendimiento (TIR), Punto de equilibrio (PE) y el Valor Actual Neto (VAN) desglosando todos sus componentes y anexando documentación que soporte dicho cálculo (incluir el archivo\nExcel considerado para los cálculos efectuados). Así mismo deberá incluir el análisis de sensibilidad, relación utilidad o beneficio costo. Nota: La hoja de cálculo no debe de estar protegida. Debe permitir verificar los cálculos y fórmulas que se presentan dentro del horizonte del análisis financiero. b. Presupuestos, composición y programa de inversiones y financiamiento complementario de algún intermediario financiero o de otro tipo. c. Proyección financiera actual y proyectada a 5 años (ingresos/egresos). d. Descripción de costos (fijos y variables). e. Necesidades de inversión. f. Financieros Proforma para los primeros tres años del proyecto. g. Cartas de autorización o compromiso de las instituciones financieras participantes en el financiamiento del proyecto.\n9. Activos a. Inventario de Activos Fijos (construcciones, terrenos agrícolas y ganaderos, inventarios de equipos, semovientes y otros, de ser el caso).\n10. Descripción y análisis de Impactos esperados a. Incremento en los niveles de capitalización (descriptivo). b. Incremento porcentual esperado en el volumen de producción, especificando kilogramos o toneladas producidas actualmente y por producir. c. Número esperado de empleos a generar con el proyecto (directos e indirectos permanentes y temporales por género) o en el caso de Promoción Comercial los que ya se generan, así como el número y tipo de empleos generados. d. Incremento en los rendimientos. e. Reducción estimada de los costos. f. Comparativo con y sin el proyecto. g. Nivel de Prioridad.\nEJERCICIO FISCAL 2019.\n11. Análisis de la situación ambiental, en su caso. a. Descripción y análisis de la situación actual del uso de los recursos, disposición de los desechos e impacto ambiental de la empresa. b. Condiciones y mecanismos de utilización de equipos de energías alternativas. c. Plan y estrategias de sustentabilidad ambiental de la empresa, en su caso. d. Estudio del impacto ambiental, en su caso. e. En su caso, permisos y autorizaciones de las Entidades Normativas sobre la preservación del medio ambiente (en el caso de proyectos de bioenergía y fuentes alternativas sólo aplica este punto de los aspectos ambientales). f. Descripción de los componentes de conservación del medio ambiente, utilización de las energías alternativas y mejoras de eficiencia energética. g. En su caso, flora y fauna (nociva).\n12. Conclusiones y recomendaciones\n13. Anexos del Proyecto, en su caso.\nPrimero. El presente Acuerdo entrará en vigor al día siguiente de su publicación en el Periódico\nSegundo. Se abrogan todas las disposiciones que contravengan las presentes Reglas de\nOperación del Programa Apoyos a la Producción Agropecuaria para el Ejercicio Fiscal 2019.\nDado en la Oficina del Titular de la Secretaría de Agricultura, Ganadería, Pesca y Desarrollo Rural, ubicada en el Edificio Carretera Nacional México- Acapulco Km 274.5 Col. Burócratas, C.P. 39090.\nChilpancingo de los Bravo, Gro, a los 28 días del mes de Enero de dos mil diecinueve.\nEL SECRETARIO DE AGRICULTURA, GANADERÍA, PESCA Y DESARROLLO RURAL.\nLIC. JUAN JOSÉ CASTRO JUSTO.\nRúbrica.",
  "ordenamiento": "PROGRAMA",
  "jurisdiccion": "GUERRERO",
  "fuente_oficial": "DIARIO OFICIAL DE LA FEDERACION",
  "Fecha de Publicación": "28 de agosto de 2018",
  "ULTIMA REFORMA PUBLICADA": "28 de agosto de 2018",
  "status": "VIGENTE",
  "es_escaneado": false,
  "tiene_tablas": true,
  "materia": [
    "agrario"
  ]
}