{
  "titulo": "Acuerdo por el Que Se Emiten las Reglas de Operación del Programa de Alimentación Escolar Modalidad",
  "Contenido": "EJERCICIO FISCAL 2023\nTEXTO ORIGINAL.\nAcuerdo publicado en el Periódico Oficial del Gobierno del Estado No. 25 Alcance II, el Martes 28 de Marzo de 2023.\nACUERDO POR EL QUE SE EMITEN LAS REGLAS DE OPERACIÓN DEL PROGRAMA DE\nALIMENTACIÓN ESCOLAR MODALIDAD CALIENTE, PARA EL EJERCICIO FISCAL 2023.\nGuerrero. - Poder Ejecutivo.\nMAESTRA EVELYN CECIA SALGADO PINEDA, GOBERNADORA CONSTITUCIONAL DEL ESTADO\nDE GUERRERO, CON FUNDAMENTO EN LO DISPUESTO POR LOS ARTÍCULOS 4o PÁRRAFOS\nTERCERO Y NOVENO DE LA CONSTITUCIÓN POLÍTICA DE LOS ESTADOS UNIDOS MEXICANOS;\n167 DE LA LEY GENERAL DE SALUD; 3 DE LA LEY DE ASISTENCIA SOCIAL; 3 FRACCIÓN XVIII\nDEL PRESUPUESTO DE EGRESOS DE LA FEDERACIÓN PARA EL EJERCICIO FISCAL 2023; 40 DE\nLA LEY DE COORDINACIÓN FISCAL; 71, 87, 88, 90 NUMERAL 2 Y 91 FRACCIONES I, IX Y XLVI DE\nEJERCICIO DE LAS FACULTADES QUE ME CONFIEREN LOS ARTÍCULOS 1 PÁRRAFO TERCERO,\n4, 9 Y 46 FRACCIÓN I DE LA LEY ORGÁNICA DE LA ADMINISTRACIÓN PÚBLICA DEL ESTADO DE\nGUERRERO NÚMERO 242; 15 DE LA LEY SOBRE EL SISTEMA ESTATAL DE ASISTENCIA SOCIAL\nNÚMERO 332; EN RELACIÓN CON EL ARTÍCULO 47 Y ANEXOS 23 (P46) Y 23-A DEL DECRETO\nNÚMERO 424 DEL PRESUPUESTO DE EGRESOS DEL ESTADO DE GUERRERO PARA EL\nEJERCICIO FISCAL 2023; ESTRATEGIA INTEGRAL DE ASISTENCIA SOCIAL ALIMENTACIÓN Y\nDESARROLLO COMUNITARIO 2023 Y LOS LINEAMIENTOS PARA LA ELABORACIÓN DE LAS\nREGLAS DE OPERACIÓN DE LOS PROGRAMAS SOCIALES ESTATALES PARA EL PERIODO 2022-\n2027.\nQue el Plan Nacional de Desarrollo 2019-2024 en su Eje Rector POR EL BIEN DE TODOS, PRIMERO\nLOS POBRES establece: “Así como Benito Juárez consumó la separación entre la Iglesia y el Estado, la\nCuarta Transformación se ha propuesto separar el poder político del poder económico. La connivencia y la corporativos en detrimento de la población. Pero una sociedad que se desentiende de sus miembros más débiles y desvalidos rompe el principio de empatía que es factor indispensable de cohesión, instaura la ley del más fuerte y acaba en un total envilecimiento”\nQue el Plan Estatal de Desarrollo 2022-2027, se encuentra alineado y armonizado a los instrumentos jurídicos nacionales y locales, así como a los lineamientos creados por los organismos internacionales que nos permiten contar con un enfoque global, con el objetivo de que lo plasmado en nuestro documento rector sea integral, incluyente, sostenible y con estricto apego a los derechos humanos, encaminado de manera\nEJERCICIO FISCAL 2023 administración pública estatal, sea eficiente en sus procesos y eficaz en sus resultados.\nEjes transversales:\n• Integridad, Transparencia, Rendición de Cuentas y Combate a la Corrupción: Porque existe el compromiso de arrancar de raíz la corrupción, el tráfico de influencias y las malas prácticas en todas las esferas de la administración, sin tolerancia, empezando de arriba hacia abajo.\n• Igualdad de Género e Inclusión Social: Porque todos los programas, estrategias, objetivos y esfuerzos del gobierno del estado, tendrán una perspectiva de género y la sensibilidad social para garantizar una administración incluyente.\n• Austeridad y Administración Pública Responsable: Porque el gobierno del estado realizará un ejercicio austero pero eficiente, que atienda las necesidades de la población para garantizar que los recursos públicos lleguen a quienes más lo necesitan.\nQue el Presupuesto de Egresos de la Federación para el Ejercicio Fiscal 2023, contempla erogaciones para el Ramo General 33 Aportaciones Federales para Entidades Federativas y Municipios precisando erogaciones para asistencia social.\nQue el uso de recursos federales del FAM implica responsabilidades para las entidades federativas, de acuerdo con la Ley de Coordinación Fiscal. Asimismo, los SEDIF como entidad ejecutora, deben publicar las Reglas de Operación a las que se sujetarán los programas en cada ejercicio fiscal, de acuerdo con el principio de fortalecimiento del pacto federal y del municipio libre establecido en los artículos 2o, fracción\nV de la Ley de Planeación, 134 Constitucional, 1, 2, 4, 5, 75 y 77 de la Ley Federal de Presupuesto y\nResponsabilidad Hacendaria; así como en el PEF de cada ejercicio fiscal.\nQue el artículo 47 del Decreto Número 424 del Presupuesto de Egresos del Estado de Guerrero para el\nEjercicio Fiscal 2023, establece que, con el objeto de asegurar la aplicación eficiente, eficaz, oportuna, equitativa y transparente de los recursos públicos, la Secretaría de Finanzas y la Secretaría de Planeación emitirán las disposiciones a que deberán sujetarse los programas de inversión sujetos a Reglas de\nOperación.\nQue, con sustento en lo anterior, la Secretaría de Planeación y Desarrollo Regional, expidió los centrales de las ROP, así como los elementos para integrar su contenido.\nQue las personas titulares de las secretarías, dependencias y entidades de la administración pública estatal, así como, las servidoras y servidores públicos autorizados para ejercer recursos públicos del presupuesto de inversión de estas, serán responsables de los programas y proyectos de inversión que\nEJERCICIO FISCAL 2023 realicen de los apoyos otorgados deberán sujetarse a criterios de objetividad, equidad, transparencia, publicidad, selectividad y temporalidad.\nQue la Ley Número 479 del Sistema para el Desarrollo Integral de la Familia del Estado de Guerrero el Sistema Estatal para el Desarrollo Integral de la Familia, como un organismo público descentralizado, el cual tiene entre otros objetivos i) Promover el bienestar social y prestar al efecto servicios de asistencia social con apoyo en las normas que dicte la Secretaría de Salubridad y Asistencia y el Sistema Nacional para el Desarrollo Integral de la Familia, así como el propio Estado; ii) Apoyar el desarrollo de la familia y de la comunidad; iii) Fomentar la educación, para la integración social; e iv) Impulsar el sano crecimiento físico y mental de la niñez.\nQue derivado del párrafo anterior, se aplica la Estrategia Integral de Asistencia Social, Alimentación y\nDesarrollo Comunitario 2023 misma que tiene como objetivo impulsar la protección integral de los grupos de atención prioritaria con perspectiva de Derechos Humanos y Cultura de Paz, mediante el desarrollo de las comunidades autogestivas, organizadas y con participación activa, así como el consumo y promoción de una alimentación nutritiva, suficiente y de calidad, dentro de la estructura de esta estrategia contempla el eje Atención Alimentaria, lo que permite que a nivel estatal se desarrolle el Programa de Alimentación\nEscolar Modalidad Caliente con el propósito, de favorecer el acceso a un desayuno adecuado y digna a las y los alumnos de los diferentes centros educativos del estado.\nPor lo anteriormente expuesto y con fundamento en las disposiciones legales antes citadas, he tenido a bien expedir el siguiente:\nACUERDO POR EL QUE SE EMITEN LAS REGLAS DE OPERACIÓN DEL PROGRAMA DE\nALIMENTACIÓN ESCOLAR MODALIDAD CALIENTE, PARA EL EJERCICIO FISCAL 2023.\nArtículo 1. Se emiten las Reglas de Operación del Programa de Alimentación Escolar Modalidad Caliente, en las que se establecen los principios de eficiencia, eficacia, oportunidad, equitativa y transparencia de los recursos públicos y requisitos que se deben de cumplir para poder acceder a dicho Programa en el estado de Guerrero.\nArtículo 2. El Sistema para el Desarrollo Integral de la Familia del Estado de Guerrero tendrá a cargo la implementación, ejecución, evaluación y administración del Programa, bajo los criterios de equidad, transparencia, publicidad, selectividad y temporalidad, con estricto apego a la normatividad aplicable, por lo tanto, será el encargado de la dispersión y asignación de los recursos del Programa en términos de las siguientes:\nREGLAS DE OPERACIÓN DEL PROGRAMA DE ALIMENTACIÓN ESCOLAR MODALIDAD CALIENTE,\nPARA EL EJERCICIO FISCAL 2023.\n1. Introducción.\nEJERCICIO FISCAL 2023\nLas presentes Reglas de Operación estarán vigentes durante el ejercicio fiscal 2023, con el fin de cumplir con el principio de anualidad presupuestaria establecido en el artículo 6 del Presupuesto de Egresos de la\nFederación 2023.\nEl indicador de rezago educativo en Guerrero entre 2008 y 2018, tuvo una disminución de 4.8 puntos porcentuales, o sea una disminución de aproximadamente 106,600 personas en esta situación al pasar de casi 966,300 en 2008 a alrededor de 859,600 en 2018. Sin embargo, el rezago educativo en Guerrero fue de 6.8 puntos porcentuales mayor que el porcentaje nacional, ocupando el estado el lugar 5 entre las 32 entidades federativas por sus niveles de carencia. (El primer lugar corresponde a la entidad federativa con mayor rezago educativo).\nEl informe de Evaluación de la Política de Desarrollo Social 2018, subraya las diversas razones por las que el derecho a la educación puede no ser efectivo. Hay diferentes condiciones económicas y no económicas que dificultan el acceso a la educación, además de que los medios, los procesos y los contenidos del sistema educativo pueden no ser los más adecuados. (FUENTE: Informe de pobreza y evolución en el estado de guerrero 2020 CONEVAL).\nPor eso será necesario:\n• Contar con una oferta educativa suficiente que abarque todos los niveles de educación obligatoria.\n• Que los servicios educativos sean accesibles para personas con condiciones particulares (condición socioeconómica, pertenencia étnica, discapacidad, entre otras).\n• Que los medios, los procesos de aprendizaje y los contenidos sean de calidad.\n• La implementación de este Programa que permitirá asegurar la inclusión alimentaria dentro del periodo en que permanece el menor de edad en los planteles educativos, focalizando la población vulnerable.\n(EN ATENCIÓN AL NUMERAL 1 CORRESPONDIENTE AL ANEXO T2.A “MODELO DE LAS REGLAS\nDE OPERACIÓN” DE LA EIASADC 2023).\n1.1. Antecedentes.\nLa historia de este tipo de apoyo se remonta a 1929 con el “Programa Gota de Leche” que a fines de los años setenta el DIF retoma con los Programas de Raciones Alimentarias (PRA) y Asistencia Social\nAlimentaria (PASAF), Hasta 1997 operaron de manera centralizada desde el SNDIF.\nEntre 1935 y 1945 los desayunos escolares que se entregaban a las niñas y niños consistían en un cubo de 250 mililitros de leche entera, sándwich, huevo cocido y un postre. Cabe destacar, que la composición del desayuno escolar atendía en esa época, a la declaratoria sobre la desnutrición como un problema grave de salud en México, ante lo cual, médicos e intelectuales incentivaron la adopción de una dieta basada en cereales, alimentos de origen animal, leche y productos lácteos (Aguilar Rodríguez, 2008).\nEJERCICIO FISCAL 2023\nAños después, el SNDIF retoma esta acción a través de dos Programas, Raciones Alimentarias y\nAsistencia Social Alimentaria a Familias (PASAF), operando bajo un esquema centralizado, ya que en sus instalaciones se encontraba la planta de desayunos escolares, en 1989 los desayunos escolares\nHidalgo, Estado de México y Tlaxcala, en 1990 se agregó a la lista Aguascalientes.\nAsimismo, en el año de 1989 se crea el Programa de Cocinas Populares y Unidades de Servicios Integrales\n(COPUSI), el cual, además de apoyar la alimentación de las familias, tenía el propósito de ofrecer un espacio para el encuentro y reflexión comunitaria, orientada a promover acciones de atención integral en cuatro ámbitos, alimentación, salud, educación, capacitación y recreación, fortaleciendo la participación y organización comunitaria a través del desarrollo de capacidades. A su vez, el Programa COPUSI fue complementado con el Programa de Fomento a la Producción de Alimentos para Autoconsumo.\nPara 1991, la cobertura de desayunos escolares llegó al estado de Guanajuato y en 1993 se expandió a\nGuerrero, Jalisco, Michoacán, Morelos, Oaxaca, Puebla y Veracruz. En 1994 los desayunos se empezaron a distribuir en Chihuahua, Chiapas, Coahuila, Durango, San Luis Potosí, Tabasco, Zacatecas, Querétaro, Sinaloa. Es en 1995, el Programa abarcó las 32 entidades del país.\nEn 1997 el propio SNDIF determinó que el modelo de operación para la entrega de desayunos escolares, no permitía la flexibilidad suficiente para considerar las diferencias en torno al consumo, así como los hábitos y cultura alimentaria de cada entidad. Además, los costos de operación se elevaban, resultando ser un modelo de operación poco eficiente, por lo que se decidió compartir la responsabilidad con las diferentes entidades.\nA partir de la descentralización de los Programas Alimentarios, en 2001 el SNDIF convocó a los SEDIF para desarrollar un proyecto de coordinación de los programas alimentarios, a través de comisiones de trabajo. El resultado fue el desarrollo de la Estrategia Integral de Asistencia Social Alimentaria y Desarrollo\nComunitario (EIASADC) que reúne una nueva estructura de cuatro programas con actividades de focalización, orientación alimentaria y aseguramiento de la calidad.\nEl principal objetivo de la estrategia fue, hasta 2007 el de contribuir a mejorar el estado de nutrición de los sujetos de asistencial social el cual ha evolucionado de acuerdo con el contexto actual de salud y nutrición. población de zonas marginadas.\nLa última modificación realizada a este Programa fue en relación al nombre, llamado anteriormente\nPrograma Cocinas Escolares Modalidad Caliente, y ahora denominándose Programa de Alimentación\nEscolar Modalidad Caliente, señalándose en la Estrategia Integral de Asistencia Social, Alimentación y\nDesarrollo Comunitario 2023.\n(EN ATENCIÓN AL NUMERAL 2 CORRESPONDIENTE AL ANEXO T2.A “MODELO DE LAS REGLAS\nDE OPERACIÓN” DE LA EIASADC 2023).\nEJERCICIO FISCAL 2023\n2. Alineación Programática al PED y/o PND. de Desarrollo 2019-2024 los cuales son los siguientes: I. Política y Gobierno, II. Política Social y III.\nEconomía; para lograr su cumplimiento, el propio Plan prevé como principios rectores: “Honradez y honestidad”; “No al gobierno rico con pueblo pobre”; “Al margen de la ley, nada; por encima de la ley, nadie”; “Economía para el bienestar”; “El mercado no sustituye al Estado”; “Por el bien de todos, primero los pobres”; “No dejar a nadie atrás, no dejar a nadie fuera”; “No puede haber paz sin justicia”; “El respeto al derecho ajeno es la paz”; “No más migración por hambre o por violencia”; “Democracia significa el poder del pueblo”, y “Ética, libertad, confianza”; Que el Plan Nacional de Desarrollo 2019-2024, en su Eje Central\nII. Política Social, en el apartado “Construir un país con Bienestar”, establece que el objetivo más importante del gobierno de la Cuarta Transformación es que en 2024 la población de México esté viviendo en un entorno de bienestar; para lo cual, se diseñó el Programa Sectorial de Bienestar 2020-2024, como un instrumento que concentra las estrategias, objetivos, prioridades y acciones puntuales necesarias para alcanzar tal objetivo; mismas que deberán regir el desempeño de las funciones de la Administración Pública\nFederal en dicho sector.\nEn relación al Plan Estatal de Desarrollo 2022-2027 en su Eje I Bienestar, Desarrollo Humano y Justicia\nSocial; Objetivo 1.2 Mejorar la calidad de vida de la población; Estrategia 1.2.2 Combate al Hambre y aumentar el acceso a una alimentación sana, nutritiva y suficiente, con particular atención a la población más pobre y en situación de vulnerabilidad incluidas niñas y niños; Línea de Acción 1.2.2.1 Incentivar la producción de alimentos sanos y nutritivos para el autoconsumo en escuelas de nivel básico de niñas, niños y adolescentes.\n2.1. Diagnóstico.\nEn Guerrero viven 841,943 niñas y niños de 0 a 12 años; de los cuales la población objetivo representa un\n33.11% de la población potencial que corresponde a 208,627 niñas y niños que asisten a planteles educativos preescolares y escolares oficiales del Sistema Educativo Estatal. (FUENTE: INEGI 2020).\nEn el estado de Guerrero se tienen contabilizados 895,157 hogares, de los cuales tienen una prevalencia de 85.1%, lo que representa 679,100 hogares, que se percibieron con inseguridad alimentaria. La cual tiene una mayor proporción en las áreas rurales en contraste con las áreas urbanas.\nEn lo que se refiere a indicadores educativos, la información recolectada para cada integrante del hogar permitió proporcionar detalles sobre asistencia la escuela y nivel máximo de estudios alcanzado. Para\nGuerrero, la ENSANUT 2012 identificó que 90.6% de las niñas y niños de 6 a 14 años asistía a la escuela, en tanto que entre los individuos de 15 a 24 años este porcentaje bajaba a 40.8%. En ambos casos, estos valores fueron inferiores al promedio nacional en aproximadamente 4.8% y 0.3 puntos porcentuales respectivamente. El promedio de años completos de escolaridad en los individuos de 15 años o más en\nGuerrero fue de 7.3 años, 13.1% inferior a los 8.4 años del promedio nacional. En este sentido, mientras la población analfabeta de 15 años o más tenía una proporción de 7.0% en el país, en Guerrero ese porcentaje fue de 2.1 veces mayor, pues llegó a 14.4 por ciento.\nEJERCICIO FISCAL 2023\nA partir de la descentralización de los programas alimentarios, en 2001 el Sistema Nacional DIF (SNDIF) convocó a los Sistemas Estatales DIF (SEDIF) para desarrollar un proyecto de coordinación de los programas alimentarios, a través de Comisiones de Trabajo. El resultado fue el desarrollo de la Estrategia\nIntegral de Asistencia Social Alimentaria (EIASA) que reúne una nueva estructura de cuatro programas con actividades de focalización, orientación alimentaria y aseguramiento de la calidad. El principal objetivo de la Estrategia fue, hasta 2007, el de contribuir a mejorar el estado de nutrición de los sujetos de asistencia social el cual ha evolucionado de acuerdo al contexto actual de salud y nutrición.\nEn el estado de Guerrero, la dieta diaria de la población beneficiaria de los programas alimentarios está basada y fundamentada en los alimentos disponibles: maíz, frijol, arroz, quelites de acuerdo a la región, chile, jitomate, cebolla, ejotes, calabazas los cuales son la base de la mayoría de su consumo.\nGran parte de ellos la siembran, otro tanto los consigue adquiriéndolos en los mercados de sus municipios y otros más como nuestras beneficiarias y beneficiarios la reciben como parte de los programas sociales alimentarios de ayuda. Normalmente es la jefa de familia quien prepara los alimentos, pocas veces los varones se involucran en estos quehaceres del hogar.\nLa forma de preparación en su mayoría es hervida, la producción agrícola de la entidad se basa en:\n• Frutícola a corto plazo: El melón, la papaya y la sandía.\n• Frutícola a largo plazo: La copra, mango, plátano, tamarindo y cítricos.\n• Productos básicos: Arroz, frijol y maíz.\n• Cultivos: Jitomate, tomate de cascara, chile verde, garbanzo blanco, cebolla, calabaza, camote, chile seco y quelites.\n• Oleaginosas: Ajonjolí y cacahuate\n• Productos industriales: Café, estropajo, jamaica y caña de azúcar.\nLa mayor parte de la producción se canaliza para autoconsumo y una cantidad mínima se comercializa en la región. (1) FUENTE: Informe de pobreza y evolución en el estado de guerrero 2012 CONEVAL.\n2.1.1. Población Potencial.\nLa población potencial es de 27,138,947 niñas, niños y adolescentes (3 a 17 años) que asisten a planteles públicos del Sistema Educativo Nacional en el estado de Guerrero.\n(EN ATENCIÓN AL NUMERAL 6.1 CORRESPONDIENTE AL ANEXO T2.A “MODELO DE LAS REGLAS\nDE OPERACIÓN” DE LA EIASADC 2023).\n2.1.2. Población Objetivo.\nLa población objetivo para el año 2023, será 630,020 entre niñas, niños y adolescentes que se encuentran en edades de 3 a 12 años.\nEJERCICIO FISCAL 2023\nNiñas, niños y adolescentes que asisten a planteles públicos del Sistema Educativo Nacional, ubicados en municipios, localidades o AGEB rurales, urbanas o indígenas de alto y muy alto grado de marginación o de rezago social en el estado de Guerrero. (CONAPO 2020 Y CONEVAL 2020).\nNiñas, niños y adolescentes que asisten a planteles públicos del Sistema Educativo Nacional con una prevalencia mayor o igual al 15% de estudiantes con desnutrición, independientemente del grado de marginación.\n(EN ATENCIÓN AL NUMERAL 6.2 CORRESPONDIENTE AL ANEXO T2.A “MODELO DE LAS REGLAS\nDE OPERACIÓN” DE LA EIASADC 2023).\n2.1.3. Población Beneficiaria.\nLa población objetivo para el año 2023 es atender a 224,933 niñas, niños y adolescentes en condiciones de vulnerabilidad, que asisten a planteles públicos del Sistema Educativo Nacional, ubicados en municipios, localidades o AGEB rurales, urbanas o indígenas de alto y muy alto grado de marginación, priorizando aquellas con elevado porcentaje de malnutrición en el estado de Guerrero.\n2.1.4. Población Indígena.\nEl Programa tendrá cobertura en localidades marginadas de población indígena con ubicación en todos los municipios del estado, que tengan sujetos de Asistencia Social Alimentaria y que cumplan con los requisitos establecidos en las presentes Reglas de Operación.\n2.2. Fundamento Legal.\n• Constitución Política de los Estados Unidos Mexicanos: Última Reforma DOF 28-05-2021 artículos\n1o, 2o apartado B, 3o fracción II inciso e) párrafo segundo, 4o párrafos primero, tercero, cuarto, noveno y décimo primero, así como 27 fracción XX.\n• Ley General de Salud: Última reforma publicada DOF 16-05-2022 artículos 2 fracción V, 3 fracción\nXVIII, 6 fracciones X, y XI, 7 fracción XIII Bis, 27 fracciones IX y X, 111 fracción II, 112 fracción III, 114, 115 fracción V, 30, y 36 fracción VII.\n36, 37 fracción II, 39, 50 fracciones III y VIII, 53 y 116 fracción XIV. fracción XI, 37 fracción II y 38 fracción VI.\nEJERCICIO FISCAL 2023 artículos 1, 2, 4, 5, 75 y 77, 85, 110, 111.\nVIII, X y XIII, 14, 15, 17, 18, 20, 28 y 29.\n• Ley de Coordinación Fiscal. Última reforma DOF 30-01-2018: artículo 25 fracción V, 40, 41, 48 y 49.\n• Ley de Disciplina Financiera de las Entidades Federativas y los Municipios. Reformada DOF 10- 02-\n2022.\n• Ley de Planeación: Última reforma DOF 16-02-2018 artículo 2, fracción V.\n• Agenda 2030 de Naciones Unidas: objetivo 1, meta 1.1, 1.2, 1.3, 1.5, objetivo 2, meta 2.1, 2.2, 2.3, objetivo 3, metas 3.2, objetivo 4, metas 4.2, 4.7, objetivo 5, meta, 5.5, objetivo 10, meta 10.2, objetivo 12, metas 12.3, 12.8, objetivo 16, metas 16.6, 16.7 y objetivo 17, meta 17.17.\n• Plan Nacional de Desarrollo 2019-2024.\n• Programa Sectorial de Salud 2019-2024.\n• Presupuesto de Egresos de la Federación 2023: Tomo IV, Ramo General 33.\n• Estrategia Integral de Asistencia Social, Alimentación y Desarrollo Comunitario 2023\n• Lineamientos para incorporar la perspectiva de género en las Reglas de Operación de los Programas\n• Ley Número 479 del Sistema para el Desarrollo Integral de la Familia del Estado de Guerrero.\n• Ley sobre el Sistema Estatal de Asistencia Social Número 332.\n• Ley Número 812 para la Protección de los Derechos de Niñas, Niños y Adolescentes del Estado de\nGuerrero\n• Ley Número 454 de Presupuesto y Disciplina Fiscal del Estado de Guerrero.\nEJERCICIO FISCAL 2023\n• Ley Número 817 para las Personas con Discapacidad del Estado.\n• Ley Número 427 del Sistema de Coordinación Hacendaria del Estado de Guerrero.\n• Lineamientos Generales para el Expendio y Distribución de Alimentos y Bebidas. Preparados y\nProcesados en las Escuelas del Sistema Educativo Nacional. Publicado en el DOF 16-05-2014.\n• Norma Oficial Mexicana NOM-014-SSA3-2013, Para la asistencia social alimentaria a grupos de riesgo: Última reforma DOF: 11- 11-2014.\n• Norma Oficial Mexicana NOM-043-SSA2-2012, Servicios básicos de salud.\n• Promoción y educación para la salud en materia alimentaria. Criterios para brindar orientación: Última reforma DOF 22-01- 2013.\n• Norma Oficial Mexicana NOM-251-SSA1-2009, Prácticas de higiene para el proceso de alimentos, bebidas o suplementos alimenticios.\n• Norma Oficial Mexicana NOM-051-SCFI/SSA1-2010, especificaciones generales de etiquetado para alimentos y bebidas no alcohólicas pre-envasados información comercial y sanitaria: Última reforma DOF:\n27-03-2020.\n• Norma Oficial Mexicana NOM-008-SSA2-1993, Control de la nutrición, crecimiento y desarrollo del niño y del adolescente. Criterios y procedimientos para la prestación del servicio. Publicada DOF 28-11-\n1994.\n• Plan Estatal de Desarrollo 2022-2027.\n• Decreto Número 424 del Presupuesto de Egresos del Estado se Guerrero para el Ejercicio Fiscal\n2023.\n• Reglamento Interior del Sistema para el Desarrollo Integral de la Familia del Estado de Guerrero.\n• Manual de Organización del Sistema para el Desarrollo Integral de la Familia del Estado de Guerrero.\n• Y todos los ordenamientos normativos aplicables.\nDefiniciones:\nÁcidos Grasos Saturados: Los que carecen de dobles ligaduras. Se recomienda que no excedan más del 7% del valor energético total de la dieta, ya que favorecen la ateroesclerosis. Algunos productos\nEJERCICIO FISCAL 2023 contienen cantidades elevadas de ácidos grasos saturados: la mantequilla y la margarina, las mantecas, el chicharrón de cerdo, el chorizo, la crema, el aceite de coco y los chocolates(cacao).\nÁcidos Grasos Trans: Son isómeros de ácidos grasos mono insaturados. Se pueden producir en la hidrogenación de aceites y grasas vegetales. Un alto consumo en la dieta puede incrementar el riesgo de presentar enfermedades cardiovasculares.\nAditivo: Cualquier sustancia permitida que, sin tener propiedades nutritivas, se incluya en la formulación de los productos y que actúe como estabilizante, conservador o modificador de sus características organolépticas, para favorecer ya su estabilidad, conservación, apariencia o aceptabilidad.\nAdolescentes: Personas que tienen entre 12 años cumplidos y 18 años incumplidos de acuerdo con lo establecido en el Artículo 2 de la Ley para la Protección de los Derechos de Niñas, Niños y Adolescentes.\nAGEB: Es la extensión territorial que corresponde a la subdivisión de las áreas geo estadísticas municipales. Constituye la unidad básica del Marco Geo estadístico Nacional y, dependiendo de sus características, se clasifican en dos tipos: urbana y rural.\nAGEB Urbana: Área geográfica ocupada por un conjunto de manzanas que generalmente va de 1 a 50, preferentemente delimitadas por calles, avenidas, andadores o cualquier otro rasgo de fácil identificación en el terreno y cuyo uso del suelo sea principalmente habitacional, industrial, de servicios, comercial, etcétera, sólo se asignan al interior de las localidades urbanas.\nAGEB Rural: Subdivisión de las áreas geo estadísticas municipales que se ubican en la parte rural, cuya extensión territorial es variable y se caracteriza por el uso del suelo de tipo agropecuario o forestal. Contiene localidades rurales y extensiones naturales como pantanos, lagos, desiertos y otros, delimitada por lo general por rasgos naturales (ríos, arroyos, barrancas, etcétera) y culturales (vías de ferrocarril, líneas de conducción eléctrica, carreteras, brechas, veredas, ductos, límites prediales, etcétera).\nAlimentación: Conjunto de procesos biológicos, psicológicos y sociológicos, relacionados con la ingestión de alimentos mediante el cual el organismo obtiene del medio, los nutrimentos que necesita, así como las satisfacciones intelectuales, emocionales, estéticas, socioculturales, que son indispensables para la vida humana plena.\nAlimentación Complementaria: Es el proceso que se inicia con la introducción paulatina de alimentos diferentes a la leche humana, para satisfacer las necesidades nutrimentales de la niña o el niño, se recomienda después de los 6 meses de edad.\nAlimentación Correcta: Hábitos alimentarios que, de acuerdo con los conocimientos reconocidos por la materia, cumple con las necesidades específicas de las diferentes etapas de la vida, promueve en las niñas y los niños el crecimiento y desarrollo adecuado, y en los adultos permite conservar o alcanzar el peso esperado para la talla y previene el desarrollo de enfermedades.\nEJERCICIO FISCAL 2023\nAnálisis de Laboratorio de los Insumos: Procedimiento químico por el cual se analizan las características físicas, químicas, biológicas y de inocuidad de los alimentos.\nAnálisis de Peligros: Proceso de recopilación y evaluación de información sobre los peligros y las condiciones que los originan, para decidir cuáles son importantes con la inocuidad de los alimentos y, por tanto, planteados en el plan del sistema de HACCP.\nAnálisis de Peligros y Control de Puntos Críticos (DACCP): Sistema que permite identificar, evaluar y controlar peligros significativos para la inocuidad de los alimentos.\nAseguramiento de la Calidad Alimentaria: Conjunto de acciones planificadas y sistematizadas, necesarias para proporcionar la confianza de que los insumos alimentarios que se entregan a los beneficiarios no afecten su salud.\nAsistencia Social: Conjunto de Acciones Tendientes a Modificar y Mejorar las Circunstancias de Carácter\nSocial que Impiden el Desarrollo Social del Individuo, así como la Protección Física, Mental y Social de\nPersonas en Estado de Necesidad.\nAsistencia Social Alimentaria: Acción de proporcionar a grupos en riesgo y a grupos vulnerables ayuda alimentaria directa, orientación alimentaria, promoción de la salud y vigilancia de la nutrición, para contribuir a mejorar las circunstancias por las que atraviesa esta población.\nAzúcares Añadidos: Azúcares añadidos a los alimentos y bebidas durante la elaboración industrial o la preparación casera.\nBeneficiarias y Beneficiarios: Población con características específicas a la que van dirigidas los programas y apoyos de asistencia social.\nCadena Alimentaria: Secuencia de etapas y operaciones involucradas en la producción, procesamiento, distribución, almacenamiento y manipulación de un alimento y sus ingredientes, desde su producción primaria hasta su consumo.\nCalidad: Propiedades y características de un producto o servicio para satisfacer las necesidades específicas o implícitas de los consumidores.\nCapacitación: Proceso de formación destinado a promover, facilitar, fomentar y desarrollar las aptitudes, habilidades o conocimientos de las personas, con el fin de permitirles mejores oportunidades y condiciones de vida.\nCédula de Inspección de Almacenes: Herramienta de verificación que incluye los requisitos mínimos establecidos en la normatividad oficial vigente, que permite evaluar las buenas prácticas de almacenamiento que deberá cumplir un almacén.\nEJERCICIO FISCAL 2023\nCereales de Grano Entero: Cereal de granos intactos que, al someterse a un proceso de molienda, rompimiento, hojuelado, entre otros, conserva sus principales componentes anatómicos y están presentes en una proporción relativamente igual a la existente en el grano intacto original, logrando esto de manera\nCertificados de Calidad: Documento que declara la conformidad de las características de un producto con base en una determinada norma o especificaciones solicitadas.\nComplemento Alimenticio: Producto alimenticio que consiste en fuentes concentradas de nutrientes que se presentan con la finalidad de complementar la ingesta de tales nutrientes de dieta normal.\nComunidad: Personas que en conjunto habitan un espacio geográfico determinado, que generan un sentido de pertenencia e identidad social, que interaccionan entre sí, operando redes de comunicación y apoyo mutuo, para lograr determinados objetivos, intereses, satisfacer necesidades, resolver problemas y desempeñar funciones sociales relevantes para su localidad.\nContaminación: Presencia de materia extraña, sustancias tóxicas o microorganismos, en cantidades que rebasen los límites permisibles establecidos por la Secretaría de Salud o en cantidades tales que representen un riesgo a la salud.\nCriterios de Calidad Nutricia: Nos referimos a una herramienta conceptual, flexible a diferentes contextos, para orientar el diseño de dotaciones alimentarias y menús cíclicos que cumplan con las características de una dieta correcta, los cuales se encuentran definidos en la EIASADC del SNDIF.\nComité: Grupo de personas con representación de la comunidad o grupo organizado para participar en los programas de los que son beneficiarias o beneficiarios.\nCultura Alimentaria: Manifestación singular de un grupo social relativa a sus hábitos de consumo de alimentos, con base en su acervo culinario, el cual está conformado por factores geográficos, económicos, sociales, religiosos e históricos.\nDesnutrición: Al estado patológico inespecífico, sistémico y potencialmente reversible que se genera por el aporte insuficiente de nutrimentos, o por una alteración en su utilización por las células del organismo.\nSe acompaña de varias manifestaciones clínicas y reviste diversos grados de intensidad (leve, moderada y grave).\nDeterminantes Sociales de la Salud: Las condiciones culturales, económicas, políticas, educativas, psicológicas y biológicas que se presentan en las localidad donde las personas nacen, crecen, viven, trabajan y envejecen, que pueden ser modificables a través de la acción comunitaria, y que están orientadas a la organización para la autogestión, autocuidado, alimentación correcta y local, economía solidaria, espacios habitables sustentables, gestión integral de riesgos, sustentabilidad y recreación y manejo del tiempo libre.\nDieta Correcta: A la que cumple con las siguientes características de la dieta completa, equilibrada, inocua, suficiente, variada y adecuada.\nEJERCICIO FISCAL 2023\nDotación Alimentaria: Para efectos de este documento, nos referimos al paquete de insumos conformados de acuerdo con criterios de calidad nutricia, que forman parte de la cultura alimentaria de los beneficiarios, que contribuyen a promover una alimentación correcta, y se otorgan a través de los programas de asistencia social alimentaria.\nEspacio Alimentario: Para efectos de este documento, lugar designado para la preparación y consumo de alimentos mediante la organización y participación social.\nEspecificación: Características o requisitos que debe cumplir un producto o un servicio.\nEspecificaciones Técnicas de Calidad: Características o requisitos que deben cumplir los insumos alimentarios de acuerdo con la EIASADC.\nEstado de Nutrición o Estado Nutricio: Es el resultado del equilibrio entre la ingestión de alimentos\n(vehículo de nutrimentos) y las necesidades nutrimentales de los individuos; es asimismo consecuencia de diferentes conjuntos de interacciones de tipo biológico, psicológico y social.\nEstándar: Documento técnico que prevé un uso común y repetido de reglas, especificaciones, atributos o métodos de prueba aplicables a un bien, producto, proceso o servicio, así como aquellas relativas a terminología, simbología, embalaje, marcado, etiquetado o concordaciones.\nEstructura Programática: Conjunto de categorías y elementos programáticos ordenados en forma coherente que define las acciones de los ejecutores de gasto para alcanzar sus objetivos y metas. Ordena y clasifica las acciones de los ejecutores de gasto para delimitar su aplicación, y permite conocer el rendimiento esperado del uso de los recursos públicos.\nEtiqueta: Cualquier rótulo, marbete, inscripción, imagen u otra materia descriptiva o gráfica, escrita, impresa, estarcida, marcada, grabada en alto o bajo relieve, adherida, sobrepuesta o fijada al envase del producto pre envasado o, cuando no sea posible por las características del producto, al embalaje.\nEvaluación de la Conformidad: Proceso técnico que permite demostrar el cumplimiento con las Normas\nOficiales Mexicanas, Estándares y Normas Internacionales ahí referidas o de otras disposiciones legales.\nComprende, entre otros, los procedimientos de muestreo, prueba, inspección, evaluación y certificación.\nFibra Dietética: Parte comestible de las plantas o hidratos de carbono que son resistentes a la digestión y grueso; se encuentra en leguminosas, cereales integrales, verduras y frutas. La fibra dietética incluye polisacáridos, lignina y otras sustancias asociadas a las plantas y se le divide en solubles e insolubles. Su consumo insuficiente se ha asociado con la aparición de enfermedades crónicas.\nFocalización: Es asegurar que los beneficios de las acciones lleguen a las familias que más requieren las intervenciones públicas, para concentrar la atención sobre un determinado problema o necesidad.\nEJERCICIO FISCAL 2023\nFrutas y Hortalizas Deshidratadas: Productos frescos, sanos y limpios, enteros o divididos, con madurez apropiada, a los cuales se les ha eliminado parcial o totalmente el agua mediante métodos naturales o artificiales.\nGrupos de Atención Prioritaria: Son Aquellos a quienes se ha identificado que deben ser atendidos de manera preferente, a través de programas especiales y estrategias, con la finalidad de alcanzar un equilibrio social.\nHábitos Alimentarios: Conjunto de conductas adquiridas por un individuo, por la repetición de actos en cuanto a la selección, la preparación y el consumo de alimentos. Los hábitos alimentarios se relacionan principalmente con las características sociales, económicas y culturales de una población o región determinada. Los hábitos generalizados de una comunidad suelen llamarse costumbres.\nInocuo: Concepto que implica que un alimento no causará daño al consumidor cuando se prepara y/o consume de acuerdo con el uso a que se destina.\nLeche Entera: Producto obtenido de la secreción natural de las glándulas mamarias de las vacas o de cualquier otra especie animal, sin calostro, con un contenido mínimo de grasa butírica de 30 g/L.\nLeche Parcialmente Descremada, Semidescremada o Descremada: Productos obtenidos de la secreción natural de las glándulas mamarias de las vacas o de cualquier otra especie animal, sin calostro.\nEl contenido de grasa butírica de la leche parcialmente descremada es de 6-28 g/L, semidescremada es de 16-18 g/L y el de la descremada es de 5 g/L máximo.\nLocalidad: Todo lugar ocupado con una o más viviendas, las cuales pueden estar habitadas o no, este lugar es reconocido por un nombre dado por la ley o la costumbre, por la cantidad de población, se dividen en urbanas (mayores de 2,500 habitantes) y rurales (menores de 2.500 habitantes), de acuerdo con el\nInstituto Nacional de Estadística y Geografía (INEGI).\nMenú Cíclico: Serie de menús planificados para un periodo específico que evita la repetición de platillos y la monotonía.\nNiñas y Niños: Personas de hasta 12 años incompletos, tal como lo establece el artículo 2 de la Ley para la Protección de los Derechos de Niñas, Niños y Adolescentes.\nObesidad: Enfermedad caracterizada por el exceso de tejido adiposo en el organismo. Se determina la existencia de obesidad en adultos cuando existe un índice de masa corporal mayor de 30 kg/m2. Se debe a la ingestión de energía en cantidades mayores a las que se gastan, acumulándose el exceso en el organismo en forma de grasa.\nOrganismo de Evaluación de la Conformidad: Persona acreditada por una entidad de acreditación o en su caso, por la autoridad normalizadora para llevar a cabo la evaluación de la conformidad.\nOrientación y Educación Alimentaria (OEA): Conjunto de acciones enfocada en transmitir nuevos conocimientos, así como reforzar aquellas buenas prácticas que realiza la comunidad, a través de\nEJERCICIO FISCAL 2023 diferentes actividades que motiven a tener actitudes saludables, mismas que, con el tiempo, se conviertan en acciones cotidianas (hábitos).\nPadrón de Personas beneficiarias: Registro nominal de las y los beneficiarios de un programa.\nParticipación Social: Proceso que permite involucrar a la población, autoridades locales, instituciones públicas y a los sectores social y privado en la planeación, programación, ejecución y evaluación de los programas y acciones de salud, con el propósito de lograr un mayor impacto.\nPersonas de Atención Prioritaria: Son aquellos a quienes se ha identificado que deben ser atendidos de manera preferente, a través de programas especiales y estrategias, con la finalidad de alcanzar un equilibrio social.\nPerspectiva de Género: Considera el papel social y cultural de las mujeres, hombres, niñas, niños y adolescentes, a fin de promover la equidad e igualdad de oportunidades y responsabilidades en un programa determinado.\nPerspectiva de los Pueblos Indígenas: Acción de reconocer que los pueblos indígenas se caracterizan por la relación especial con sus tierras, territorios y recursos naturales, donde han desarrollado culturas, lenguas, artes, medicinas, cosmogonías y formas propias de organización política, económica y social, usos y costumbres, así como principios y valores que rigen la vida comunitaria entre los que destacan: el tequio, la solidaridad, el trabajo comunitario y la ayuda mutua, mismo que deberán tomarse en cuenta para fortalecer los procesos de autonomía y formas de organización propias.\nPerspectiva Regional: Considera la cultura y tradiciones regionales para rescatar y mejorar las prácticas alimentarias de la comunidad, la familia y el individuo, por un lado, y por el otro, incentivar la economía y producción local, así como fomentar el desarrollo regional.\nPlataforma Tecnológica Integral de Infraestructura de Calidad: Solución digital donde se administrarán y ejecutarán de manera sistematizada los datos, procesos, trámites, servicios y actividades de normalización, estandarización, evaluación de la conformidad y metrología.\nPoblación Objetivo: Población especifica que un programa tiene planeado o programado atender para cubrir la población potencial y que cumple con los criterios de elegibilidad establecidos en su normatividad.\nPoblación Potencial: Población total que presenta la necesidad o problema que justifica la existencia de un programa y que, por lo tanto, pudiera ser elegible para su atención.\nPrácticas de Higiene: Medidas necesarias que se realizan durante las diferentes etapas de la cadena alimentaria, para garantizar su inocuidad.\nPrograma: Programa de Alimentación Escolar Modalidad Caliente.\nEJERCICIO FISCAL 2023\nPrograma de Limpieza y Desinfección: Documento que contiene la planeación acerca de los métodos, áreas, implementos y frecuencia con la que se realiza la limpieza y desinfección en espacios alimentarios y almacenes.\nPromoción de la Salud: Proceso que permite fortalecer los conocimientos, aptitudes y actitudes de las personas para participar corresponsablemente en el cuidado de su salud y para optar por estilos de vida saludables, facilitando el logro y conservación de un adecuado estado de salud individual y colectivo mediante actividades de participación social, comunicación educativa y educación para la salud.\nPulpas o Colados de Frutas o Verduras: Productos que han sido deshuesados, molidos o tamizados, sometidos a tratamiento térmico hasta su concentración y adicionados, o no, de ingredientes opcionales y aditivos para alimentos.\nRación Alimentaria: Para efectos de este documento, se refiere al platillo preparado que se ofrece en los espacios alimentarios.\nReglas de Operación (ROP): Son un conjunto de disposiciones que precisan la forma de operar un programa, con el propósito de transparentar y normar la distribución y entrega de los apoyos alimentarios.\nSecretaría de Contraloría: Secretaría de Contraloría y Transparencia Gubernamental.\nSeguridad Alimentaria: Acceso físico y económico de todas las personas, en todo momento, a los alimentos inocuos y nutritivos que se requieren para satisfacer sus necesidades alimenticias y sus preferencias en cuanto a los alimentos, a fin de llevar una vida saludable y activa.\nSituación de Emergencia: Condición que puede causar un daño y propiciar un riesgo excesivo para la seguridad e integridad de la población en general, generada o asociada con la inminencia, alta probabilidad o presencia de un agente perturbador.\nSodio: Nutrimento inorgánico, que constituye el principal catión del espacio extra molecular y su contenido corporal, está regulado a través de la función renal. Regula el volumen, la presión osmótica, y la carga eléctrica del fluido extra- celular. Interviene en la contracción muscular, la conducción nerviosa, la absorción de algunos nutrimentos y, en menor grado, en la constitución de los huesos.\nSustentabilidad: Capacidad de satisfacer las necesidades y ejercer los derechos humanos presentes, sin poner en riesgo la sobrevivencia y el desarrollo de las futuras generaciones, realizando acciones familiares y colectivas orientadas al cuidado del medio ambiente para disminuir la huella ecológica. Implica comprender y sensibilizarse con el entorno global, e identificar y resolver los problemas ecológicos a nivel local.\nVigilancia del Estado Nutricional: Conjunto de procedimientos sistemáticos que permiten identificar, seguir y evaluar las condiciones de nutrición en forma individual y colectiva, indispensable para la toma de decisiones.\nEJERCICIO FISCAL 2023\nVulnerabilidad: Fenómeno social que implica la presencia de una condición de riesgo que padece un individuo o una familia, resultado de la acumulación de desventajas sociales, de manera que dicha situación oportunidades de desarrollo.\n(EN ATENCIÓN AL NUMERAL 1 CORRESPONDIENTE AL ANEXO T2.A “MODELO DE LAS REGLAS\nDE OPERACIÓN” DE LA EIASADC 2023).\nSiglas:\nCNDH: Comisión Nacional de los Derechos Humanos.\nCOFEPRIS: Comisión Federal para la Protección contra Riesgos Sanitarios.\nCONAMER: Comisión Nacional de Mejora Regulatoria.\nCONEVAL: Consejo Nacional de Evaluación de la Política de Desarrollo Social.\nDOF: Diario Oficial de la Federación.\nEIASADC: Estrategia Integral de Asistencia Social, Alimentación y Desarrollo Comunitario.\nETA: Enfermedades Transmitidas por Alimentos.\nFAM-AS: Fondo de Aportaciones Múltiples Componente Asistencia Social.\nIPPEA: Informe Parcial del Proyecto Estatal Anual.\nLAS: Ley de Asistencia Social.\nLCF: Ley de Coordinación Fiscal.\nLDFEFM: Ley de Disciplina Financiera de las Entidades Federativas y los Municipios.\nLFPRH: Ley Federal de Presupuesto y Responsabilidad Hacendaria.\nLGS: Ley General de Salud.\nMIR: Matriz de Indicadores de Resultados.\nPEA: Proyecto Estatal Anual.\nPEF: Presupuesto de Egresos de la Federación.\nPP: Programa Presupuestal.\nEJERCICIO FISCAL 2023\nPTCVC: Programa Estatal de Trabajo de Comité de Vigilancia Ciudadana.\nROP: Reglas de Operación.\nSEDIF: Sistema Estatal para el Desarrollo Integral de la Familia.\nSFP: Secretaría de la Función Pública.\nSIIPP-G: Sistema Integral de Información de Padrones de Programas Gubernamentales de la Secretaría de la Función Pública.\nSMDIF: Sistema Municipal para el Desarrollo Integral de la Familia.\nSNDIF: Sistema Nacional para el Desarrollo Integral de la Familia.\nSRFT: Sistema de Recursos Federales Transferidos de la SHCP.\nSEFINA: Secretaría de Finanzas y Administración.\nSEPLADER: Secretaría de Planeación y Desarrollo Regional.\n3. Objetivos y Alcances.\n3.1. Objetivo General.\nFavorecer el acceso y consumo de alimentos nutritivos e inocuos de la población de atención prioritaria, que asiste a planteles públicos del Sistema Educativo Nacional, mediante la entrega de desayunos escolares, diseñados con base en criterios de calidad nutricia, acompañados de acciones de orientación y educación alimentaria, así como de aseguramiento de la calidad, para favorecer un estado de nutrición adecuado.\n(EN ATENCIÓN AL NUMERAL 4 CORRESPONDIENTE AL ANEXO T2.A “MODELO DE LAS REGLAS\nDE OPERACIÓN” DE LA EIASADC 2023).\n3.2. Objetivo Específico.\na) Favorecer el acceso y consumo de alimentos nutritivos e inocuos de la población de atención prioritaria, que asiste a planteles públicos del Sistema Educativo Nacional, mediante la entrega de desayunos escolares, diseñados con base en criterios de calidad nutricia, acompañados de acciones de orientación y educación alimentaria, así como de aseguramiento de la calidad, para favorecer un estado de nutrición adecuado. nivel preescolar y escolar.\nEJERCICIO FISCAL 2023\nc) Contribuir al desarrollo de buenos hábitos de alimentación en la población sujeta de Asistencia Social\nAlimentaria cuyas condiciones de vulnerabilidad los predisponen a desarrollar desnutrición y/o deficiencias alimentarias, a través de la entrega de una ración alimenticia, la cual deberá cumplir con los Criterios de\nCalidad Nutricia de la EIASADC vigentes.\nd) Verificar que los alimentos que integran las despensas sean fuente importante de nutrimentos indispensables para el crecimiento como son: Hierro, Vitaminas A y D, entre otras.\ne) Promover acciones formativas y estilos de vida saludables basados en una alimentación correcta y en la promoción de la actividad física.\nf) Difundir los menús cíclicos al personal operativo de los Sistemas Municipales DIF, a los comités del\nPrograma y a las personas beneficiarias del Programa alimentario, para el aprovechamiento de los insumos recibidos.\ng) Entregar insumos alimentarios de calidad e inocuos, a través de acciones de Aseguramiento de la\nCalidad Alimentaria, que generen las condiciones de higiene y seguridad utilizando herramientas de control en las etapas de la cadena alimentaria, desde la selección y adquisición, hasta la entrega de los apoyos alimentarios a las personas beneficiarias.\n(EN ATENCIÓN AL NUMERAL 4.1 CORRESPONDIENTE AL ANEXO T2.A “MODELO DE LAS REGLAS\nDE OPERACIÓN” DE LA EIASADC 2023).\n3.3. Cobertura.\nEl Programa operará en escuelas de nivel preescolar y escolar en las localidades marginadas con ubicación en todos los municipios del estado de Guerrero, que tengan sujetos de Asistencia Social Alimentaria.\nDichas localidades serán seleccionadas por los SMDIF en consenso con el SEDIF, en las localidades prioritarias tomando como base en el índice de marginación por municipio.\n(EN ATENCIÓN AL NUMERAL 5 CORRESPONDIENTE AL ANEXO T2.A “MODELO DE LAS REGLAS\nDE OPERACIÓN” DE LA EIASADC 2023).\n3.4. Alcances.\nA través del Programa se busca disminuir la desnutrición, de niños y niñas del nivel preescolar y primaria inscritos en planteles oficiales a través de desayunos calientes con calidad nutricia, contribuyendo en su desempeño escolar y sano desarrollo, fomentando también el consumo de frutas y verduras; con ello se garantiza el derecho a la alimentación de las niñas, niños y adolescentes a través de despensas que se entregarán directamente al plantel educativo beneficiado.\n4. Metas Físicas.\nEJERCICIO FISCAL 2023\nSe atenderán a 224,933 niñas, niños y adolescentes de manera mensual que asisten a planteles públicos del Sistema Educativo Nacional de los municipios que integran el estado de Guerrero, dando prioridad a los municipios, localidades o AGEB rurales, urbanas o indígenas de alto y muy alto grado de marginación, y/o priorizando aquellas con elevado porcentaje de malnutrición y/o con una prevalencia mayor o igual al\n15% de estudiantes con desnutrición, independientemente del grado de marginación.\n5. Programación Presupuestal.\nDentro de la política de Desarrollo Social, el Sistema para el Desarrollo Integral de la Familia del estado de\nGuerrero, opera el Programa, el cual es subsidiado a través de recursos provenientes del Ramo 33.Aportaciones Federales para Entidades Federativas y Municipios, específicamente del Fondo de\nAportaciones Múltiples (Asistencia Social), el cual tiene una inversión $386,561,605.29 (Trescientos ochenta seis millones quinientos sesenta y un mil seiscientos cinco pesos 29/100 m.n.), de acuerdo a una adecuación presupuestaria compensada teniendo como fundamento al Decreto número 424 del\nPresupuesto de Egresos del Estado de Guerrero para el Ejercicio Fiscal 2023.\nENERO FEBRERO MARZO ABRIL MAYO JUNIO\n32,213,467.10 32,213,467.10 32,213,467.10 32,213,467.10 32,213,467.10 32,213,467.10\nJULIO AGOSTO SEPTIEMBRE OCTUBRE NOVIEMBRE DICIEMBRE\n32,213,467.10 32,213,467.10 32,213,467.10 32,213,467.10 32,213,467.10 32,213,467.10\nNOTA: PUEDE EXISTIR VARIACIÓN EN RELACIÓN A LO APROBADO POR EL DOF Y A LOS RESULTADOS DE LA LICITACIÓN PÚBLICA\nNACIONAL.\n(EN ATENCIÓN AL NUMERAL 13.1 CORRESPONDIENTE AL ANEXO T2.A “MODELO DE LAS\nREGLAS DE OPERACIÓN” DE LA EIASADC 2023).\n5.1. Gastos de Operación.\nDe acuerdo con el artículo 40 de la Ley de Coordinación Fiscal que mandata el uso del FAM-AS se establece que se podrá hacer uso por concepto de gastos de operación no más del 2% del total del recurso asignado para el ejercicio fiscal 2023.\n6. Criterios y Requisitos de Elegibilidad.\na) Criterios de Focalización. programas. Los criterios para la focalización de las y los beneficiarios serán los siguientes:\n• Identificar los municipios, localidades y AGEB rurales y urbanas consideradas de alta y muy alta marginación.\n• Identificar a las personas que cubran con las características de la población objetivo descritas en las presentes Reglas de Operación.\nEJERCICIO FISCAL 2023\n(EN ATENCIÓN AL NUMERAL 6.3 CORRESPONDIENTE AL ANEXO T2.A “MODELO DE LAS REGLAS\nDE OPERACIÓN” DE LA EIASADC 2023).\nb) Requisitos de Selección de Personas Beneficiarias.\n• Las niñas, niños en condiciones de vulnerabilidad, que asisten a planteles públicos del Sistema\nEducativo Nacional, ubicados en municipios, localidades o AGEB rurales, urbanas o indígenas de alto y muy alto grado de marginación, priorizando aquellas con elevado porcentaje de malnutrición del estado de\nGuerrero.\n• Las niñas, niños y adolescentes que asisten a planteles públicos del Sistema Educativo Nacional con una prevalencia mayor o igual al 15% de estudiantes con desnutrición, independientemente del grado de marginación.\n(EN ATENCIÓN AL NUMERAL 6.4 CORRESPONDIENTE AL ANEXO T2.A “MODELO DE LAS REGLAS\nDE OPERACIÓN” DE LA EIASADC 2023).\nc) Métodos y/o procedimientos de Selección.\n1. Aplicación de las herramientas de selección.\nCriterios geográficos: Estableciendo aquellos municipios prioritarios por sus condiciones de marginación pobreza y vulnerabilidad, nivel de marginación, nivel de pobreza, estado nutricional, zona rural-urbano y población indígena.\nPor Centros Educativos: Ubicando aquellas escuelas en cuanto a organización, indicadores escolares y nivel de demanda del apoyo: tipo de escuela, nivel escolar, grado, turno, tipo de organización, indicadores escolares (deserción, aprovechamiento, eficiencia terminal).\nPor individuo: Detectando en la escuela a los niños que requieren del apoyo, por sus condiciones de desventaja en cuanto a nutrición, pobreza, vulnerabilidad familiar y aprovechamiento escolar.\nPara la apertura de una cocina escolar caliente:\n• Se identificarán las escuelas ubicadas en localidades de muy alto y alto grado de marginación de acuerdo a la CONAPO y al porcentaje de la población según el tipo de carencia social por municipio.\n• Se llenarán las tarjetas de datos de las escuelas: municipio, comunidad, distancia de la cabecera municipal a la comunidad, tiempo de traslado de la cabecera municipal a la comunidad, nombre del comisario, teléfono de la localidad, nombre del presidente de la asociación de padres de familia, Clave del\nCentro de Trabajo, Nombre del plantel, Matrícula.\nEJERCICIO FISCAL 2023\n• El Sistema Municipal DIF aplicará el estudio socioeconómico a los padres de familia para determinar educativo.\n• Se integrará el Padrón de Personas Beneficiarias: nombre del menor, sexo, fecha de nacimiento, peso, talla, CURP, lugar de nacimiento, domicilio de la menor calle, número.\n• Una vez identificadas las comunidades y escuelas de mayor necesidad se procederán a verificar cuales de éstas tienen condiciones para instalar el comedor escolar a través de las asambleas para conformar los comités de Alimentación Escolar Modalidad Caliente, donde se dará a conocer las Reglas de Operación y el reglamento interno del Programa.\n• Si los padres de familia, las autoridades del plantel y el comisario aceptan el trabajo comunitario se procede a autorizar el insumo alimentario del comedor, mediante un recibo de asignación de módulos por plantel educativo: producto, presentación, cantidad de producto, módulos que recibirá y el costo que pagará por módulo de manera mensual.\n• Una vez que se aprueba la operación de la cocina se procede a entregar el apoyo alimentario\n(Despensa) a la cocina mediante un recibo donde describe el contenido del producto y el número de módulos que recibirá de manera mensual según especifique su Padrón de Personas Beneficiarias. Esto se logra gracias a la aplicación de las cuotas de recuperación.\n• En coordinación con el área de nutrición se capacitan a los integrantes del comité de Alimentación\nEscolar Modalidad Caliente y padres de familia sobre el contenido de los menús mensuales y las recomendaciones para la elaboración de alimentos y el cuidado de la despensa escolar.\n(EN ATENCIÓN AL NUMERAL 6.5 CORRESPONDIENTE AL ANEXO T2.A “MODELO DE LAS REGLAS\nDE OPERACIÓN” DE LA EIASADC 2023).\n7. Tipo, Monto y Periodicidad del Apoyo.\nLa dotación deberá estar conformada por al menos 15 insumos diferentes de los tres grupos del plato del buen comer (en sintonía con la Norma Oficial Mexicana NOM-043-SSA2-2012, Servicios básicos de salud, promoción y educación para la salud en materia alimentaria. Criterios para brindar orientación), incluyendo cereales, verduras y frutas, leguminosas y alimentos de origen animal, estas dotaciones se entregarán mensualmente.\n(EN ATENCIÓN AL NUMERAL 7.1 Y 7.2 CORRESPONDIENTE AL ANEXO T2.A “MODELO DE LAS\nREGLAS DE OPERACIÓN” DE LA EIASADC 2023).\n7.1. Características de los Apoyos.\na) La dotación deberá incluir:\nEJERCICIO FISCAL 2023\n• Leche entera\n• Dos a cinco cereales máximo que sean fuente de fibra dietética.\n• Un alimento que sea fuente de calcio (Anexo T3.E).\n• Un alimento que sea fuente de proteína de origen animal y/o hierro hemínico (Anexo T3.E).\n• De dos a cinco variedades de leguminosas.\n• Verduras.\n• En caso de otorgar mezclas de verduras no deberán contener papa ni elote.\n• En caso de identificar población con sobrepeso u obesidad, se podrá entregar leche descremada.\nb) Prescindir de los insumos que son fuente importante de azúcares, grasas, sodio y/o harinas refinadas.\nc) Evitar cualquier alimento que contenga más de 400mg de sodio en 100g de producto.\nd) Determinar las cantidades de los insumos a distribuir a partir de las cantidades establecidas en los menús que serán entregados a la población.\n(EN ATENCIÓN AL NUMERAL 7.3 CORRESPONDIENTE AL ANEXO T2.A “MODELO DE LAS REGLAS\nDE OPERACIÓN” DE LA EIASADC 2023).\n7.2. Recursos no Devengados.\nEl presupuesto otorgado al Programa que no haya sido aplicado a los fines autorizados, y los recursos que por cualquier motivo no se hayan devengado al 31 de diciembre del presente ejercicio fiscal, serán reintegrados inmediatamente a la SEFINA.\n7.3. Resguardo de la Documentación.\nLa Dirección de Asistencia Alimentaria y Desarrollo Comunitario del SEDIF Guerrero resguardara la documentación comprobatoria de acuerdo con las disposiciones normativas establecidas en las presentes\nReglas de Operación.\n7.4. Supervisión y Control. financieros de manera mensual a la Dirección de Planeación del DIF Guerrero, de las acciones ejercidas y de manera trimestral los informes, a más tardar 15 días hábiles, posteriores a la terminación de cada trimestre.\n8. Criterios de Selección.\n• Se seleccionarán los planteles educativos a beneficiar de acuerdo con la zona de alto y muy alto grado de marginación, zonas indígenas, rurales y urbanas marginadas preferentemente.\nEJERCICIO FISCAL 2023\n• Los Sistemas Municipales DIF aplicarán el estudio socioeconómico (Anexo 5), a la población del centro escolar de nuevo ingreso elegible a beneficiar, esto con el fin de priorizar la focalización de la población beneficiaria; previa capacitación para su aplicación por parte del SEDIF Guerrero.\n8.1. Casos Especiales.\nEn caso de ocurrir alguna situación extraordinaria que impida la operación normal del Programa (cambio en la modalidad y lugar de la entrega), el Sistema Estatal DIF Guerrero; notificará a las personas beneficiadas a fin de brindar alternativas que permitan dar continuidad al suministro de alimentos.\n(EN ATENCIÓN AL NUMERAL 12.3 CORRESPONDIENTE AL ANEXO T2.A “MODELO DE LAS\nREGLAS DE OPERACIÓN” DE LA EIASADC 2023).\n8.2. Casos de Emergencia o Desastre.\nEn caso de que exista una declaratoria de Emergencia o Desastre, el Sistema DIF Guerrero, considerará que cuando así se juzgue pertinente podrán transferir los recursos de este Programa al Programa de\nAtención Alimentaria a Personas en Situación de Emergencia o Desastre, para atender a la población que así lo requiera.\n8.3. Suspensión o Cancelación del Programa Social.\nEl Sistema DIF Guerrero podrá suspender y/o cancelar la ejecución del Programa, cuando las personas beneficiarias no acaten las disposiciones de las presentes Reglas de Operación para acceder a los beneficios que a través de estos se otorgan, perderán las prerrogativas que dichas disposiciones establecen por parte de la población beneficiada.\nAsimismo, en caso de presentar documentación alterada durante el trámite de atención de su solicitud, o cuando se detecte que la información proporcionada fue limitada, incompleta o con falta de veracidad, se dará por cancelada. extraordinario a otros municipios.\n8.4. Integración del Padrón de Personas Beneficiarias.\nEl formato de padrón físico y digital (Anexo 3) de personas beneficiarias del Programa, será proporcionado por el SEDIF Guerrero a los SMDIF, para que a su vez lo distribuyan a cada una de las directoras o directores de los planteles escolares beneficiados, los SMDIF en coordinación con las autoridades educativas recaban la información, en caso de que las autoridades educativas incumplan con lo establecido, los SMDIF tendrán la responsabilidad de llevar a cabo esta actividad a fin de entregar la información en las fechas establecidas por el SEDIF Guerrero.\nEJERCICIO FISCAL 2023\nUna vez concluido el padrón de personas beneficiarias correspondiente al primer mes del ejercicio fiscal, los SMDIF remitirán para su revisión y validación al SEDIF Guerrero, en formato físico y en digital la los municipios de la entidad, conformando así el Padrón Único del estado de Guerrero.\nEl SMDIF Resguardará los padrones de personas beneficiarias en físico y digital de todos los meses entregados durante el ejercicio presupuestal 2023.\nEl padrón único del estado de Guerrero deberá llenarse de acuerdo con las primeras 21 variables obligatorias y sus características establecidas en el modelo de datos para personas físicas en el Manual de Operación del Sistema Integral de Información de Padrones de Programas Gubernamentales (SIIPP-\nG), publicado en el Diario Oficial de la Federación el 13 de septiembre del 2018.\nLa Dirección General de Alimentación y Desarrollo Comunitario (DGADC), en coordinación con el enlace interinstitucional del SNDIF ante la SFP para el SIIPP-G, podrá determinar si los padrones de la EIASADC se integrarán al SIIPP-G; así como los mecanismos para hacerlo.\nEl SEDIF Guerrero y los SMDIF informarán a las y los beneficiarios que los datos personales recabados serán protegidos en términos de los principios de protección de datos personales contenidos en la ley de la materia y demás normativas aplicables, de acuerdo a lo establecido en los artículos 12 y 1 4 de la Ley de Protección de Datos Personales en Posesión de Sujetos Obligados (particulares) (DOF, 26 enero del\n2017).\n(EN ATENCIÓN AL NUMERAL 14.2 CORRESPONDIENTE AL ANEXO T2.A “MODELO DE LAS\nREGLAS DE OPERACIÓN” DE LA EIASADC 2023).\n9. Mecánica Operativa del Programa Social.\n9.1. Instancia Ejecutora y/o Responsable.\nLa instancia ejecutora será el SEDIF Guerrero, en coordinación con los SMDIF, quienes deberán operar con apego a la programación, presupuestación, calendario de ejecución, ejercicio y control del gasto público.\n(EN ATENCIÓN AL NUMERAL 10.1 CORRESPONDIENTE AL ANEXO T2.A “MODELO DE LAS\nREGLAS DE OPERACIÓN” DE LA EIASADC 2023).\n9.2. Proceso de Incorporación al Programa Social. y podrá ser a solicitud de los DIF Municipales, los padres de familia o de los directivos de los planteles educativos a través de oficio.\nEJERCICIO FISCAL 2023 tardar en 20 días hábiles, en la Dirección de Asistencia Alimentaria y Desarrollo Comunitario, a través de la Subdirección de Asistencia Alimentaria.\nPodrán ser beneficiados con el Programa, los planteles públicos del Sistema Educativo Nacional que cumplan, con las características siguientes:\n• Escuelas públicas del nivel preescolar y escolar.\n• Estar ubicadas en municipios o localidades de alta o AGEB rurales, urbanas o indígenas de alto muy alto grado de marginación, priorizando aquellos con elevado porcentaje de malnutrición.\n• Contar con una matrícula de un mínimo de 100 menores y máxima de 200 por plantel educativo.\n• Niñas, niños y adolescentes que asisten a planteles públicos del Sistema Educativo Nacional con una prevalencia mayor o igual al 15% de alumnos con desnutrición independientemente del grado de marginación.\n(EN ATENCIÓN AL NUMERAL 12.2 CORRESPONDIENTE AL ANEXO T2.A “MODELO DE LAS\nREGLAS DE OPERACIÓN” DE LA EIASADC 2023).\n10. Evaluación.\nEl instrumento de medición de evaluación del Programa se realizará mediante indicadores de acuerdo con la metodología del marco lógico.\nPara el seguimiento del Programa, el SEDIF registrará las acciones y las actividades que realizan los coordinadores regionales en las localidades participantes, de manera mensual, los reportes que se generen de dichas acciones comunitarias programadas, durante el ciclo escolar que opere el Programa; así mismo, se elaborará reportes de autoevaluación tomando como base los avances físicos y financieros; promoviendo acciones correctivas para el óptimo desempeño de los espacios alimentarios.\n(EN ATENCIÓN AL NUMERAL 13.2 CORRESPONDIENTE AL ANEXO T2.A “MODELO DE LAS\nREGLAS DE OPERACIÓN” DE LA EIASADC 2023)\n10.1. Indicadores (Construcción de la Matriz de Indicadores para Resultados. Anexo 1).\nPara la construcción de los indicadores se seguirá la Metodología de Marco Lógico, integrando los indicadores de cumplimiento de metas asociadas a los objetivos del Programa.\nFicha Técnica\nIndicadores del Desempeño\nPlan de Desarrollo 2022-2027\nEJERCICIO FISCAL 2023\nFONDO: Fondo de Aportaciones Múltiples (Asistencia Social)\nNOMBRE DEL PROGRAMA: Programa de Alimentación Escolar Modalidad Caliente\nEJE TEMATICO: 1. BIENESTAR, DESARROLLO HUMANO Y JUSTICIA SOCIAL\nOBJETIVO: 1.2. Mejorar la calidad de vida de la población.\nESTRATEGIA: 1.2.2. Combate al hambre y aumentar el acceso a una alimentación sana, nutritiva y suficiente, con particular atención a la población más pobre y en situación de vulnerabilidad, incluidos niñas y niños.\nLINEA DE ACCIÓN: I.2.2.1. Incentivar la producción de alimentos sanos y nutritivos para el autoconsumo en escuelas de nivel básico de niñas, niños y adolescentes.\nDatos de identificación del indicador\nClave Nombre Fuente\n1.2.2.1.\nPorcentaje de entrega de sillas de ruedas DIF Guerrero\nDefinición Nivel en la MIR Dimensión\nDeterminar el porcentaje de entrega de desayunos escolares calientes\nComponente Eficacia\nMétodo de cálculo Unidad de Medida.\nPorcentaje de entrega de = Desayunos escolares calientes entregados\nPorcentaje desayunos escolares calientes Desayunos escolares calientes programados 100 para entrega\nDesagregación\nFrecuencia de medición geográfica Serie de información disponible\nAnual Estatal al cierre del ejercicio\nLínea base\nSentido del indicador\nAño Periodo Valor\nAscendente\nParámetros de semaforización Metas\nVerde Amarillo Rojo Año Periodo Valor\n÷36% y> 2023 Anual\n<35% 50% 50%\nVariables que conforman el indicador\nObservaciones\nResponsable del indicador\nEJERCICIO FISCAL 2023\nNombre del Servidor Público Dependencia Área\nDirección de Asistencia\nLic. Margarita de Jesús Ramírez Salgado DIF Guerrero Alimentaria y Desarrollo\nComunitario\nNombre del puesto, encargo o comisión Teléfono Correo electrónico\nDirectora de Asistencia Alimentaria y Desarrollo Comunitario 01 747 47 2 13 75 alimentariadif@prodigy.net.mx\nElaboró Revisó Autorizó\nLic. Yaret Itzel Gallardo Lázaro Lic. Margarita de Jesús Ramírez Salgado Lic. Antelmo Magdaleno Solís\nSubdirectora de Asistencia Alimentaria\nComunitario Guerrero\nDirección General de Evaluación\nEJERCICIO FISCAL 2023\n(EN ATENCIÓN AL NUMERAL 13.4 CORRESPONDIENTE AL ANEXO T2.A “MODELO DE LAS\nREGLAS DE OPERACIÓN” DE LA EIASADC 2023).\n10.2. Seguimiento.\nPara el seguimiento del Programa, la Dirección de Asistencia Alimentaria y Desarrollo Comunitario registrará las acciones y las actividades que realizan las personas coordinadoras regionales en las localidades participantes, quienes revisarán y actualizarán de manera mensual los reportes que se generen de dichas acciones comunitarias programadas, durante el ejercicio fiscal que opere el Programa; así mismo, se elaborará reportes de autoevaluación tomando como base los avances físicos y financieros; promoviendo acciones correctivas para el óptimo desempeño de los espacios alimentarios.\n10.3. Auditoría.\nEl ejercicio del recurso y la operatividad del Programa, están sujetos a las disposiciones federales y estatales aplicables y podrán ser auditado por la SFP, Auditoría Superior de la Federación como órganos fiscalizadores de la Federación y Secretaría de Contraloría, así como por la Auditoría Superior del Estado, conforme a la legislación vigente y en el ámbito de sus respectivas competencias.\nEl SEDIF Guerrero dará todas las facilidades a dichas instancias para realizar, en el momento en que lo juzguen pertinentes, las auditorías que consideren necesarias; asimismo, harán el seguimiento y solventará en tiempo y forma las observaciones realizadas por los órganos de control.\n(EN ATENCIÓN AL NUMERAL 13.3 CORRESPONDIENTE AL ANEXO T2.A “MODELO DE LAS\nREGLAS DE OPERACIÓN” DE LA EIASADC 2023).\n11. Mecanismo de Entrega del Apoyo.\nEl apoyo alimentario se entregará a través de los SMDIF, quienes acuden a las bodegas regionales a recibir y trasladar hasta los lugares de origen, de la población beneficiada debiendo presentar la documentación siguiente:\n• Entregar copia de su credencial del INE.\n• Presentar la ficha de depósito de la aportación para el fortalecimiento del Programa.\n• Firmar el formato de salida de almacén.\n• En caso de no presentarse la Presidenta o Director (a) del DIF Municipal, deberán presentar oficio de comisión y autorización para poder recoger los insumos alimentarios.\nDIF, los DIF Municipales tendrán que verificar que sean las cantidades establecidas de acuerdo a la programación y revisar las fechas de caducidad del producto. El apoyo alimentario podrá ser entregado por el SEDIF Guerrero directamente a las localidades y planteles educativos correspondientes, en caso de retraso en recoger los insumos alimentarios por parte de los municipios.\nEJERCICIO FISCAL 2023 con el calendario de suministro, cada SMDIF se encargará de distribuir y entregar a los espacios alimentarios sus dotaciones correspondientes para la preparación de las raciones (calientes). laborables de acuerdo con el calendario del ciclo escolar vigente.\n(EN ATENCIÓN AL NUMERAL 12.1 CORRESPONDIENTE AL ANEXO T2.A “MODELO DE LAS\nREGLAS DE OPERACIÓN” DE LA EIASADC 2023).\na) Acciones Transversales.\nLas acciones transversales llevadas a cabo por el Programa son las siguientes:\n1) Orientación y Educación Alimentaria.\nPara incidir en hábitos alimentarios saludables que contribuyan a un estado de nutrición adecuado de la población, se requiere indispensablemente, la incorporación de acciones integrales de orientación y educación alimentaria como eje transversal y clave de cada uno de los programas descritos en la presente\nEstrategia.\nLa Orientación y Educación Alimentaria (OEA) deberá dirigirse primordialmente a las personas beneficiarias de los programas alimentarios, así como al fortalecimiento del componente de alimentación correcta y local del Programa de Salud y Bienestar Comunitario, además de estar dirigida al personal de la operación en los SEDIF, en los SMDIF y en las comunidades.\nEl objetivo de la orientación y educación alimentaria es promover la integración de una alimentación correcta conforme a lo establecido en la Estrategia, a través de acciones formativas y participativas con perspectiva familiar, comunitaria, de género y regional, a fin de empoderar a los beneficiarios de los programas para la toma de decisiones saludables. De esta manera, se resalta la importancia de mantener el desarrollo de conocimientos básicos y habilidades en alimentación correcta, incluyendo a su vez, la generación de estrategias integrales enfocadas en el cambio de comportamiento de la población a distintos niveles (NOM 043- SSA2-2012). receptoras pasivas tanto de los apoyos otorgados, como de los mensajes y acciones de OEA, a un enfoque basado en la participación comunitaria, en el cual, se asume que las comunidades son autogestivas y activas en el proceso de transformarse a sí mismas, en particular transformar sus comportamientos, actitudes y prácticas relativos a la alimentación.\nFormando parte de los procesos para otorgar atención alimentaria, desde el momento de la composición de los apoyos alimentarios con criterios de calidad nutricia, durante el diseño de los menús, hasta que los insumos son consumidos por las personas beneficiarias.\nEJERCICIO FISCAL 2023\nLa planeación de las acciones debe estar basada en la identificación de los problemas de la comunidad, relacionados con la alimentación y la nutrición, señalando los factores que los determinan, ya sean socioeconómicos, climatológicos, demográficos, culturales (entre los que se encuentran los patrones de consumo), entre otros; examinando en el corto y largo plazo las consecuencias que estos problemas pueden generar.\nEs fundamental establecer procesos de comunicación que contemplen:\n• El SEDIF deberá contar con personal certificado en los Estándares de Competencia EC0217 y\nEC0334, con la finalidad de optimizar la impartición de las acciones de orientación alimentaria y preparación de alimentos respectivamente, por lo que, de así requerirlo, se deberá contactar a la Dirección General de\nProfesionalización de la Asistencia Social.\n• Deberá existir una relación colaborativa entre el SNDIF, los SEDIF y los SMDIF con el fin de coordinarse con el personal de salud, promotores y miembros de la comunidad para promover y fortalecer las acciones de OEA, a través de una comunicación eficaz, utilizando un lenguaje común y entendible para los beneficiarios.\n• La difusión de las estrategias educativas será a través de medios de comunicación que se ajusten a las características de la población a la que se dirige el mensaje. (Salud-SNDIF, 2018).\nPOBLACIÓN A LA QUE VA DIRIGIDA CAMBIOS DESEADOS EN LA POBLACIÓN A LA\nQUE VA DIRIGIDA\nNiñas, niños y adolescentes - Aumento del consumo diario de verduras, frutas y agua natural.\n- Lavado correcto de manos\nPreparadores de alimentos y comités de - Aumento en compra y utilización de alimentación Escolar verduras y frutas para el comedor.\n- Lavado correcto de manos\n- Manejo de buenas prácticas de higiene para procesar alimentos o bebidas.\nDocentes y directivos - Sensibilización acerca de la importancia de la ingesta diaria de frutas, verduras y agua simple.\n- Fomento del consumo de verduras, frutas y agua potable natural en el espacio escolar.\nPadres de familia en general - Fortalecer el consumo diario de verduras, frutas y agua potable natural en los hogares\nEJERCICIO FISCAL 2023\n2) Aseguramiento de la Calidad Alimentaria. inocuidad de los insumos, con el fin de prevenir algún riesgo a la salud de las personas beneficiarias y asegurar la calidad nutrimental para su consumo.\nEstablecer capacitaciones que permitan asesorar y promover controles que garanticen la inocuidad de los insumos alimentarios.\nAsegurar la entrega de alimentos de calidad e inocuos, a través de herramientas de control en cada una de las etapas de la cadena de suministro, desde la selección y adquisición, hasta la entrega y consumo de los apoyos alimentarios a las personas beneficiarias, garantizando la reducción de los riesgos de contaminación o deterioro de los insumos, contribuyendo a la prevención de las Enfermedades\nTransmitidas por Alimentos.\nLos controles para garantizar la calidad e inocuidad de los insumos alimenticios deben realizarse en todas las etapas de la cadena de suministro y los SEDIF deben vigilar la aplicación de éstos.\n• Antes:\nRealizar la selección de los insumos que conformarán los apoyos alimentarios, mediante el establecimiento de Especificaciones Técnicas de Calidad, se deben elegir proveedores que en sus procesos de fabricación cumplan con la normatividad vigente aplicable.\n• Durante:\nCumplir con las Buenas Prácticas de Higiene establecidas en la NORMA Oficial Mexicana NOM-251-SSA12009, Prácticas de higiene para el proceso de alimentos, bebidas o suplementos alimenticios en cada una de las etapas de manejo de insumos:\n• Almacenes estatales, regionales y/o municipales.\n• Transporte y distribución de insumos y dotaciones.\n• Preparación y consumo de alimentos en espacios alimentarios.\n• Después:\nDar seguimiento, evaluar los controles y corregir en caso de ser necesario.\n3) Especificaciones Técnicas de Calidad (ETC).\nSon herramientas documentales que describen las características que debe cumplir un insumo alimenticio. insumos adquiridos.\nEJERCICIO FISCAL 2023\nMexicanas vigentes, asimismo, deben de cumplir con los lineamientos establecidos en la EIASADC. En caso de no existir normas nacionales de referencia para algún insumo, se deberán consultar normas internacionales aplicables o documentos científicos.\nLos insumos alimenticios en todas sus presentaciones deberán contar con su ETC, y en caso de que se realice algún cambio de producto durante el año fiscal, se deberá notificar a la DGADC y enviar la ETC correspondiente del nuevo producto.\n(EN ATENCIÓN AL NUMERAL 8 CORRESPONDIENTE AL ANEXO T2.A “MODELO DE LAS REGLAS\nDE OPERACIÓN” DE LA EIASADC 2023).\n4) Mecanismos de Corresponsabilidad.\nLas partes involucradas tendrán corresponsabilidad ya que intervienen de manera directa e indirectamente en cada una de las etapas de la cadena alimentaria, para lo cual se definirá con claridad las responsabilidades que le corresponden a cada uno de acuerdo con el ámbito de su competencia.\nEl SMDIF acuerda recoger en tiempo y forma los insumos alimentarios en las bodegas regionales que les correspondan, presentando comprobante de depósito del mecanismo de corresponsabilidad del Programa, exceptuando los municipios de muy alto grado de marginación de nuestro estado de Guerrero, y aquellos que quienes recibirán sus dotaciones alimentarias donadas, quienes recibirán sus dotaciones alimentarias donadas, entregándolas a las personas beneficiarias en las mismas condiciones de gratuidad.\nTanto el SEDIF como el SMDIF acuerdan respetar los plazos de entrega de los apoyos en sus distintas modalidades, en caso de que el SMDIF no acuda a recibir sus dotaciones en tiempo y forma del Programa, el SEDIF se reserva el derecho de resguardar los productos para otorgarlos como apoyos extraordinarios\n(eventos especiales, desastres naturales, etc.).\nEn el caso de los comedores escolares el comité de padres de familia de la cocina escolar, acordará el mecanismo de corresponsabilidad a operar en el Programa y los casos de excepción, la utilización de los que complementarán los menús, dando preferencia a frutas y verduras frescas, además de otros gastos de operación. Asimismo, de todos los acuerdos que se tomen, se sugiere llevar una bitácora donde se registre la contraprestación, quedando asentados en minuta firmada por parte de los padres de familia, a fin de trasparentar dichas aportaciones.\n(EN ATENCIÓN AL NUMERAL 14.4 CORRESPONDIENTE AL ANEXO T2.A “MODELO DE LAS\nREGLAS DE OPERACIÓN” DE LA EIASADC 2023).\n12. Derechos y Obligaciones de las Personas Beneficiadas.\nDerechos:\nEJERCICIO FISCAL 2023\n• Las personas representantes de las instituciones educativas que se beneficien con este Programa\n• Recibir la información necesaria de manera clara y oportuna para participar en el Programa.\n• Un trato digno y respetuoso oportuno con calidad y equitativo sin discriminación alguna.\n• Reserva y privacidad de su información personal.\n• Recibir orientación y asesoría.\n• Recibir los Desayunos Escolares en tiempo y forma.\n• Ser informado de la situación que guarde su solicitud.\n• Ser atendido con equidad, respeto y cordialidad.\nObligaciones:\n• Dar cumplimiento a las Reglas de Operación del Programa.\n• Proporcionar la información socioeconómica bajo protesta de decir verdad que les sea requerida por el Sistema Estatal DIF Guerrero, en los términos que establezca la normatividad correspondiente.\n• Utilizar los apoyos alimentarios de manera adecuada y para los fines a los que se les otorgan y con que fueron autorizados evitando cualquier uso distinto de la misma.\n• Permitir visita de verificación con la finalidad de validar la información proporcionada en sus expedientes correspondientes.\n• Facilitar los trabajos de supervisión, en cualquier momento después de otorgado el apoyo.\n• Proporcionar la información que el coordinador o la coordinadora del Programa Alimentación Escolar\nModalidad Caliente le solicite para la valoración de su solicitud, en forma clara, completa y verídica.\n• Acudir en los horarios establecidos.\n• Presentar la documentación requerida dentro del tiempo señalado.\n• Aclarar en forma precisa y satisfactoria cualquier duda relativa a la información que proporcionen, o situaciones observadas.\nEJERCICIO FISCAL 2023\n(EN ATENCIÓN AL NUMERAL 9 CORRESPONDIENTE AL ANEXO T2.A “MODELO DE LAS REGLAS\nDE OPERACIÓN” DE LA EIASADC 2023).\n12.1. Causales de Suspensión o Baja de las Personas Beneficiadas.\n• En caso de incumplir en las disposiciones normativas establecidas en las presentes Reglas de\nOperación para acceder a los beneficios que a través de estos se otorgan, perderán las prerrogativas que dichas disposiciones establecen por parte de la población beneficiada.\n• En caso de presentar documentación alterada durante el trámite de atención de su solicitud, se dará por cancelada.\n• En caso de que se detecte que la información proporcionada fue limitada, incompleta o con falta de veracidad, se dará por cancelada dicha solicitud.\n• En caso de utilizar la dotación alimentaria para fines proselitistas.\n12.2. Proceso de Baja.\nEn caso de que se presente la suspensión o baja definitiva de alguna institución educativa se deberá proceder de la siguiente manera:\n• El Sistema Estatal DIF notificará por escrito a los Sistemas Municipales DIF, la institución educativa que cause baja definitiva, los motivos y a partir de que fechas causaran efecto.\n• Los SMDIF notificarán por escrito a la institución educativa, mencionando las causas y fecha de baja.\n• El Sistema Estatal DIF procederá a incorporar a las personas beneficiarias que se encuentren dentro de la base de datos de beneficiarios de la población objetivo, con la finalidad de que las metas sean cumplidas y en consecuencia los recursos sean ejercidos en su totalidad.\n13. Instancias Participantes.\na) Secretaría de la Función Pública. Instancia Normativa Federal.\nb) Sistema Estatal para el Desarrollo Integral de la Familia. Instancia Ejecutora y Normativa.\nc) Secretaría de Planeación y Desarrollo Regional. Instancia responsable de autorizar los recursos y\nReglas de Operación.\nd) Secretaría de Finanzas y Administración. Instancia responsable de liberar los recursos.\n13.1. Instancia Normativa.\nEJERCICIO FISCAL 2023\na) Instancia Normativa Estatal.\nLa instancia normativa será el SEDIF Guerrero, a través de la publicación de las Reglas de Operación del la operatividad del Programa asegurando el cumplimiento de los objetivos y metas trazadas.\n(EN ATENCIÓN AL NUMERAL 10.2 CORRESPONDIENTE AL ANEXO T2.A “MODELO DE LAS\nREGLAS DE OPERACIÓN” DE LA EIASADC 2023).\nb) Instancia Normativa Federal.\nEl ejercicio del recurso y la operatividad del Programa, están sujetos a las disposiciones federales y estatales aplicables y podrán ser fiscalizados por la Auditoría Superior de la Federación conforme al artículo\n47 de la Ley de Fiscalización y Rendición de Cuentas de la Federación, la SFP, en base al artículo 37 de la Ley Orgánica de la Administración Pública Federal, el Sistema Nacional DIF a través de la DGADC, por medio de la EIASADC vigente, con fundamento en la estrategia programática del FAM-AS del Presupuesto de Egresos de la Federación para el Ejercicio Fiscal 2023.\n(EN ATENCIÓN AL NUMERAL 10.3 CORRESPONDIENTE AL ANEXO T2.A “MODELO DE LAS\nREGLAS DE OPERACIÓN” DE LA EIASADC 2023).\nc) Coordinación Institucional.\n• Prevención de Duplicidades.\nEl SEDIF Guerrero, establecerá los mecanismos de coordinación necesarios para garantizar que sus programas y acciones no se contrapongan, afecten o presenten duplicidades con otros programas o acciones del gobierno estatal; la coordinación institucional y vinculación de acciones busca potenciar el impacto de los recursos, fortalecer la cobertura de las acciones, detonar la complementariedad y reducir gastos administrativos.\n(EN ATENCIÓN AL NUMERAL 11.1 CORRESPONDIENTE AL ANEXO T2.A “MODELO DE LAS\nREGLAS DE OPERACIÓN” DE LA EIASADC 2023).\n• Convenio de Colaboración.\nSMDIF, según corresponda, por cada uno de los programas de la EIASADC 2023 que operen con recursos del FAM-AS, de acuerdo con el principio de Fortalecimiento del Pacto Federal y del Municipio Libre y la fracción II, inciso a) del artículo 77 de la Ley Federal de Presupuesto y Responsabilidad Hacendaria. en beneficio del Programa. Definiendo con claridad el programa, la modalidad y plazos de entrega de los\nEJERCICIO FISCAL 2023 apoyos, así como los compromisos de las partes que sean aplicables. El contenido deberá ser congruente con las Reglas de Operación del Programa.\nLa vigencia del convenio deberá ser al 31 diciembre del 2023 con el fin de cumplir con el principio de anualidad presupuestaria establecido en el artículo 6º del Presupuesto de Egresos de la Federación 2023.\n(EN ATENCIÓN AL NUMERAL 11.2 CORRESPONDIENTE AL ANEXO T2.A “MODELO DE LAS\nREGLAS DE OPERACIÓN” DE LA EIASADC 2023).\n• Colaboración.\nCada uno de los tres niveles de gobierno federal, estatal y municipal deben participar activamente para el desarrollo de los programas, cumpliendo con cada una de las atribuciones y deberes que son detallados en las presentes Reglas de Operación.\nUna parte importante es el mecanismo de corresponsabilidad entre las personas beneficiarias y los encargados del Programa, los SMDIF y el SEDIF ya que permiten utilizar los recursos como fortalecimiento para la adquisición de insumos.\n(EN ATENCIÓN AL NUMERAL 11.3 CORRESPONDIENTE AL ANEXO T2.A “MODELO DE LAS\nREGLAS DE OPERACIÓN” DE LA EIASADC 2023).\n• Concurrencia.\nEl SEDIF Guerrero, gestionará ante las instancias gubernamentales de la entidad, recursos estatales para la operación del Programa.\n(EN ATENCIÓN AL NUMERAL 11.4 CORRESPONDIENTE AL ANEXO T2.A “MODELO DE LAS\nREGLAS DE OPERACIÓN” DE LA EIASADC 2023).\n14. Transparencia.\n14.1. Promoción y Difusión del Programa Social.\nDe acuerdo al artículo 70, capítulo II De las Obligaciones de transparencia comunes, de la Ley General de las instancias participantes en su ejecución. conocer el Programa.\nEJERCICIO FISCAL 2023 paraestatal/sistema-para-el-desarrollo integral-de-la- familia/, así como el Periódico Oficial del Gobierno del\nEstado.\nPara información sobre el Programa también podrán acudir al SEDIF Guerrero, a las oficinas de la Dirección de Asistencia Alimentaria y Desarrollo ubicadas Av. Gabriel Leyva s/n esq. Ruffo Figueroa, Col. Burócratas, C.P. 39090, Chilpancingo, Guerrero.\n(EN ATENCIÓN AL NUMERAL 14.1 CORRESPONDIENTE AL ANEXO T2.A “MODELO DE LAS\nREGLAS DE OPERACIÓN” DE LA EIASADC 2023).\n14.2. Contraloría Social.\nEL SEDIF Guerrero promoverá la Contraloría Social en base a la normatividad establecida para tal efecto, fomentando acciones que transparenten la operación del Programa incorporando a la ciudadanía en el control, vigilancia y evaluación de los programas sociales.\nLa Secretaría de Contraloría será la autoridad competente para llevar a cabo la supervisión y verificación de las acciones a realizar por la instancia ejecutora de la promoción, difusión y realización de las acciones necesarias para la participación de las personas beneficiarias de los programas a través de la integración y operación de comités de contraloría social para dar información, seguimiento, supervisión, vigilancia y evaluación del cumplimiento de criterios de elegibilidad y derechos de las personas beneficiarias, obligaciones del Programa y el desempeño de honestidad y calidad de las y los servidores públicos.\n14.3. Protección de Datos Personales.\nLos datos personales de las personas beneficiadas serán protegidos en términos de la Ley Federal de\nTransparencia y Acceso a la Información Pública, Ley General de Protección de Datos Personales en\nPosesión de Sujetos Obligados (DOF:26/01/2017) y demás disposiciones jurídicas aplicables.\n14.4. Quejas y Denuncias.\nLa población beneficiada puede presentar quejas, denuncias y solicitudes de información ante las instancias correspondientes sobre cualquier hecho, acto u omisión que produzca o pueda producir daños disposiciones y de la demás normatividad aplicable, en:\na) El Sistema DIF Guerrero\nDomicilio: Centro de Rehabilitación Integral Guerrero.\nBoulevard Lic. René Juárez Cisneros S/N, Col. Ciudad de los Servicios. Chilpancingo, Guerrero. C.P.\n39095.\nEJERCICIO FISCAL 2023\nb) La Secretaría de Contraloría y Transparencia Gubernamental.\nTeléfonos: (747) 47 1 97 41\nCisneros 62 Col. de los Servicios C.P. 39075.\nLas quejas y denuncias de la ciudadanía derivadas de alguna irregularidad en la operación del Programa podrán presentarse por escrito, por comparecencia de la persona beneficiaria, por correo electrónico o vía telefónica y deberá proporcionar los siguientes datos: nombre del servidor público, área de adscripción, objeto de la denuncia, nombre y domicilio del quejoso e identificación oficial.\n(EN ATENCIÓN AL NUMERAL 14.3 CORRESPONDIENTE AL ANEXO T2.A “MODELO DE LAS\nREGLAS DE OPERACIÓN” DE LA EIASADC 2023).\n14.5. Acciones de Blindaje.\nEn la operación y ejecución de los recursos federales o estatales, programas y proyectos sujetos a las presentes Reglas de Operación, se deberán observar y atender las medidas de carácter permanente, contenidas en las leyes federales y/o locales aplicables, las disposiciones emitidas por las autoridades electorales, tanto de carácter federal como local, así como aquellas específicas que sean emitidas de forma previa para los procesos electorales federales, estatales y municipales, por la Unidad del Abogado General y Comisionado para la Transparencia, con la finalidad de prevenir que el uso y manejo de los recursos públicos y programas sociales se vean relacionados con fines partidistas y/o político-electorales; todo ello con la firme intención de garantizar los principios de imparcialidad y equidad durante los comicios.\n14.6. Acta de Donación. (Anexo 2).\nEn cuanto a la naturaleza del Programa, el apoyo que brinda se comprueba mediante un Padrón de\nPersonas beneficiarias (Anexo 4) y acta de donación (anexo 7).\n15. Perspectiva de Género. a los beneficios de este Programa en igualdad de condiciones; privilegiando, en su caso, la inclusión de medidas especiales de carácter temporal (acciones afirmativas), para solucionar las condiciones inmediatas en la vida de las mujeres, y medidas estratégicas que tiendan a la valorización de la posición que las mujeres tienen en la comunidad, modifique los patrones culturales y destierre los estereotipos que ocasionan discriminación y violencia, así como medidas que aceleren el logro de la igualdad sustantiva productiva, en la toma de decisiones, en los procesos de implementación del Programa y en general, en el logro de los objetivos planteados en la Agenda 2030 para el desarrollo sostenible.\nEJERCICIO FISCAL 2023\n16. Enfoque de Derechos. disponibilidad, accesibilidad y calidad en las acciones que realiza este Programa, se implementarán mecanismos que hagan efectivo el acceso a la información gubernamental, se asegurará que el acceso a los apoyos y servicios se dé únicamente con base en lo establecido en estas Reglas de Operación, sin discriminación alguna.\nBajo el mismo enfoque la Ley General de los Derechos de Niñas, Niños y Adolescentes señala que para garantizar la protección de los derechos de niñas, niños, adolescentes y jóvenes, las autoridades realizarán las acciones y tomarán medidas con un enfoque integral, transversal y con perspectiva de derechos humanos en el diseño y la instrumentación de políticas y programas de gobierno.\nTodas las personas servidoras públicas involucradas en la operación del Programa deben promover, respetar, proteger y garantizar el ejercicio efectivo de los derechos humanos de las y los beneficiarios del\nPrograma, con base en los principios de universalidad, interdependencia, indivisibilidad y progresividad, brindando en todo momento un trato digno y de respeto a la población objetivo, con apego a los criterios de igualdad y no discriminación.\nEn la aplicación del Programa, se harán valer los derechos de las personas beneficiarias tomando en consideración los factores de desigualdad que pudieran poner en riesgo de vulnerabilidad a personas que pertenecen a grupos históricamente discriminados, como lo son niñas y niños, jóvenes, personas con discapacidad, personas en situación de calle, en situación de desplazamiento interno, mujeres, personas migrantes, afrodescendientes, y a aquellas pertenecientes a pueblos y comunidades indígenas, entre otros, tomando en consideración sus circunstancias y necesidades, a fin de contribuir a generar conocimiento y acciones que potencien su desarrollo integral e inclusión plena.\n17. Acciones Contra el SARS-COV 2.\nEn atención a la pandemia por COVID–19, el SEDIF Guerrero implementará las medidas siguientes:\n• Durante la distribución de insumos se deben mantener las condiciones de inocuidad de los mismos. calidad de los alimentos.\n• Previo a la entrega de la dotación, el personal encargado de la distribución y la o el beneficiario que recibe, deberán lavarse y/o desinfectarse las manos con gel antibacterial con base de alcohol al 60%, por al 60%.\n• Los apoyos deberán estar previamente empaquetados antes de su entrega.\n18. Anexos que reflejen la entrega del apoyo (Económico, Especie o Servicios).\nEJERCICIO FISCAL 2023\nAnexo 1. MIR.\nAnexo 2. Acta de Donación.\nAnexo 3. Padrón de Beneficiarios.\nAnexo 4. Acta Constitutiva de Formación de Comité. Anexo 5. Estudio Socioeconómico.\nAnexo 6. Convenio de Colaboración.\nO.P.D. SISTEMA PARA EL DESARROLLO INTEGRAL DE LA FAMILIA\nMatriz de Indicadores de Resultados\nAsistencia Alimentaria v Desarrollo Comunitario\nDetalle de la Matriz 2023\nRamo:\n5 - Sector Paraestatal\nUnidad Responsable:\nP-46 -O.P.D. Sistema cara el Desarrollo Integral de la Familia\nClave y Modalidad del\nPn: S- Sujetos a Realas de Operación\nDenominación del Pp: 1 006 FAM Asistencia Social\nClasificación Funcional:\nFinalidad: 1. BIENESTAR, DESARROLLO HUMANO Y JUSTICIA SOCIAL\nFunción: 1.1. Reducir la pobreza de los Guerrerenses\n1.2. Mejorar la calidad de vida de la población\nSubfunción: 1.1.1. Aumento del ingreso económico de la población en situación de pobreza, impulsando su integración a mercado laboral y apoyando su desarrollo integral,\n1.2.2. Combate al hambre y aumentar el acceso a una alimentación sana, nutritiva y suficiente, con particular atención a la población más pobre y en situación de vulnerabilidad, incluidos niñas y niños.\nResumen narrativo Orden Supuestos\nContribuir al estado nutricional adecuado y al 1) La población vulnerable consume alimentos desarrollo comunitario de la población en nutritivos, suficientes y de calidad. condiciones de vulnerabilidad. 2) Las comunidades son autogestivas, organizadas y con participación activa.\nUnidad de Frecuencia de Tipo de Medios de\nIndicador Método de Cálculo Línea Base Meta 2023\nMedida Medición Indicador Verificación\nPoblación de (Número total de beneficiarios la Estrategia que reciben apoyos\nIntegral de la alimentarios en el año /\nAsistencia Número total de beneficiarios Padrón de\nPorcentaje Anual Estratégico 70% 100%\nSocial inscritos a los programas Beneficiarios\nAlimentaria alimentarios de la Estrategia con acceso a Integral de la Asistencia Social alimentos Alimentaria en el año) ‘100\nPorcentaje de (Número de localidades de alta\nLocalidades y muy alta marginación con de alta y muy Grupos de Desarrollo alta Constituidos en el año/Total de Padrón de\nPorcentaje Anual con Grupos de marginación programadas para\nDesarrollo la constitución de Grupos de\nConstituidos Desarrollo) *100\nEJERCICIO FISCAL 2023\nPropósito\nResumen narrativo Orden Supuestos nutritivos e inocuos de la población en reciben raciones/despensas con base en condiciones de vulnerabilidad. 1.1 criterios de calidad nutricia, acompañados de acciones de orientación y educación alimentaria\nUnidad de Tipo de Medios de\nIndicador Método de Cálculo Frecuencia de Línea Base Meta 2023\nMedida Indicador Verificación\nMedición\nPorcentaje de dotaciones(Número de despensas- despensas dotaciones diseñados con que cumplen criterios de calidad nutricia / con los Avances físicosNúmero total de despensas Porcentaje Semestral Gestión 90% 100% criterios de Financieros dotaciones diseñadas y calidad nutricia enviadas a validación del en la\nSistema Nacional DIF) *100 población vulnerable\nCoadyuvar a la atención de los determinantes Las localidades de alta y muy alto de grado de sociales de salud a través del fortalecimiento marginación articulen procesos tendientes al de los componentes para el bienestar 1.2 ejercicio de sus derechos para incrementar su comunitario, propiciando la organizador y calidad de vida participación comunitaria.\nPorcentaje de (Número de localidades de alta localidades de y muy alta marginación con alta y muy alta Grupos de Desarrollo marginación Constituidos que han mejorado con Grupos de alguno de los determinantes\nAvances FísicosDesarrollo que sociales de salud en el año, Porcentaje Semestral\nFinancieros han mejorado /Total de Localidades de alta y algunos de los muy alta marginación determinantes programadas para la sociales de constitución de Grupos de salud Desarrollo constituidos) *100\nComponente\nResumen narrativo Orden Supuestos\nMide la proporción de apoyos alimentarios Entregar a personas en situación de despensas-dotaciones entregados que vulnerabilidad insumos alimentarios de calidad e cumplen con los criterios de calidad nutricia inocuos, a través de acciones de Aseguramiento\n1.3 de los lineamientos de la Estrategia Integral de la Calidad Alimentaria, de Asistencia Social Alimentaria (EIASA)\nUnidad de Frecuencia de Tipo de Medios de\nIndicador Método de Cálculo Línea Base Meta 2023\nMedida Medición Indicador Verificación\nProporción de\n(Número de despensasdespensas- dotaciones distribuidas de dotaciones acuerdo a los criterios de entregadas Avance Físico calidad nutricia de los Porcentaje Anual Estratégico 0% 100% que cumplen Financiero lineamientos de la con los\nEIASA/ Número total de criterios de apoyos entregados) * 100 calidad nutricia\nEJERCICIO FISCAL 2023 otorgadas en materia de determinantes conocimientos, habilidades y competencias en sociales de la salud a Grupos de Desarrollo 1.4 las personas a fin de propiciar y fortalecer la\nMarginación. bienestar colectivo.\nUnidad de Frecuencia de Tipo de Medios de\nIndicador Método de Cálculo Línea Base Meta 2023\nMedida Medición Indicador Verificación\n(Húmero da capacitaciones otorgadas en el año en materia\nPorcentaje de de los determinantes sociales capacitaciones de la salud a Grupos ce otorgadas en Desarrollo constituidos en materia de los localidades de alta y muy alta determinantes marginación / el total de Avance Físico\nPorcentaje Anual Estratégico 0% 100% sociales de capacitaciones programadas financiero\nSalud a en el año sobre los\nGrupos de determinantes sociales de la\nDesarrollo salud a Grupos de Desarrollo\nConstituidos, constituidos en localidades de alta y muy alta marginación)\n‘100\nActividades\nResumen narrativo Orden Supuestos\nFavorecer el acceso de las personas en condición de emergencia o desastre, a\nProporcionar el primer alimento a familias alimentos inocuos y nutritivos. a través de 1.3.1 afectáis por desastre naturales, apoyos alimenticios temporales, diseñados con base en criterios da calidad nutricia\nUnidad de Frecuencia de Tipo de Medios de\nIndicador Método de Cálculo Línea Base Meta 2023\nMedida Medición Indicador Verificación\nDeterminar el nivel de atención alimentaria a (Municipios con declaración de de los emergencia atendidos/Total de\nAvance Físico\nMunicipios en Municipios con Municipios Anual Gestión 0% 100%\nFinanciero condiciones Declaratoria de emergencia en emergencia la Entidad) afectada por\nDesastres\nNaturales.\nResumen narrativo Orden Supuestos disminución de la desnutrición de las niñas y base en criterios de calidad nutricia, niños que cursan el nivel preescolar y primare 1.3.2 acompañados de acciones de orientación y\nEducativo Nacional, Indicador Método de Cálculo Unidad de Frecuencia de Tipo de Línea Base Meta 2023 Medios de\nMedida Medidor Indicador Verificación\nEJERCICIO FISCAL 2023\nPorcentaje de\nDesayunos\n(Número Total de Desayunos\nCalientes que\nCalientes distribuidos a las se distribuyen niñas y niños del sistema a niñas y educativo que son beneficiarios Avance Físico niños Inscritos Porcentaje Trimestral Gestión 0% 100% del Programa/ el total de Financiero en Planteles desayunos escolares calientes\nOficiales del programados para distribución)\nSistema\n* 100\nEducativo\nNacional, Unidad de Frecuencia de Tipo de Medios de\nIndicador Método de Cálculo Línea Base Meta 2023\nMedida Mediado Indicador Verificación\nPorcentaje de\nDesayunos\n(Número Total de Desayunos\nFríos que se\nFríos distribuidos a las niñas y distribuyen a niños del sistema educativo niñas y niños que son beneficiarios del Avance Físico inscritos en Porcentaje Trimestral Gestión 0% 100%\nPrograma/ el total de Financiero\nPlanteles desayunos escolares fríos\nOficiales del programados para distribución)\nSistema\n¨100\nEducativo\nNacional, Resumen narrativo Orden Supuestos\nEntregar dotaciones alimentarias nutritivas, Contribuir a un estado nutricional adecuado fomento de la educación nutricional, la lactancia de las niñas y niños en sus primeros 1000 1.3 materna y prácticas adecuadas da cuidado, días de vida, higiene y estimulación temprana\nUnidad de Frecuencia de Tipo de Meta Medios de\nIndicador Método de Cálculo Línea Base\nMedida Medición Indicador 2023 Verificación\nPorcentaje de (Número Total de despensas despensas distribuidos a las mujeres distribuidas a embarazas o en periodo de\nAvance Físico mujeres lactancia que son beneficiarios Porcentaje Trimestral Gestión 0% 100%\nFinanciero embarazadas del Programa/ el total de en periodo de despensas programadas para lactancia distribución) *100\nResumen narrativo Orden Supuestos\nEntregar alimentos con criterios de calidad\nFavorecer el acceso y consumo de alimentos nutriera, acompañados de acciones de nutritivos e inocuos de las personas de 1.3 orientación y educación alimentaria, atención prioritaria aseguramiento de la calidad, Unidad de Tipo de Medios de\nIndicador Método de Cálculo Frecuencia de Línea Base Neta 2023\nMedida Indicador Verificación\nMedición\nEJERCICIO FISCAL 2023\nPorcentaje de (Número Total de despensas despensas distribuidos a las personas de\nPorcentaje Trimestral Gestión 0% 100% pésenos de beneficiarios del Programa/el Financiero atención total de despensas programas prioritaria para distribución) * 100\nResumen narrativo Orden Supuestos\nContribuir a mejorar las condiciones de vida de las personas y/o familias en los municipios o\nEntregar paquetes para la implementación de localidades de alta y muy alta marginación 1.3 proyectos productivos mediante la implementación de proyectos productivos de economía y traspatio.\nUnidad de Tipo de Medios de\nIndicador Método de Cálculo Frecuencia de Línea Base Meta 2023\nMedida Indicador Verificación\nMedición\nPorcentaje de entrega de\n(Número Total de Paquetes apoyos para la entregados a personas en implementación condición de vulnerabilidad de. proyectos Avance Físico para la implementación de Porcentaje Trimestral Gestión 0% 100% productivos en Financiero proyectos productivos / Total las Localidades de paquetes programados de alta y muy para entrega) * 100 alta marginación\nEJERCICIO FISCAL 2023\nAnexo 2 Acta de Donación\nSISTEMA ESTATAL PARA EL DESARROLLO\nINTEGRAL DE LA FAMILIA\nFOLIO. ____________\nACTA DE DONACIÓN\nCONTRATO DE DONACIÓN QUE CELEBRAN POR UNA PARTE EL SISTEMA PARA EL DESARROLLO INTEGRAL DE\nLA FAMILIA DEL ESTADO DE GUERRERO, REPRESENTADO POR EL DIRECTOR GENERAL, A QUIEN EN LO\nSUCESIVO SE LE DENOMINARÁ '‘DONANTE\" Y POR OTRA PARTE: DIF MUNICIPAL ___________________________\nA QUIEN EN LO SUCESIVO SE LES DENOMINARA “DONATARIO”, AL TENOR DE LAS SIGUIENTES DE\nACLARACIONES Y CLÁUSULAS:\n1.- EL DONANTE DECLARA:\n1.1.- QUE EL SISTEMA PARA EL DESARROLLO INTEGRAL DE LA FAMILIA DEL ESTADO DE GUERRERO, AL QUE\nREPRESENTA, ES UN ORGANISMO PUBLICO DESCENTRALIZADO CON PERSONALIDAD JURÍDICA Y\nPATRIMONIO PROPIO, CREADO POR LA LEY 107 DE FECHA 9 DE MARZO DE 1977, PUBLICADA EN EL\nPERIÓDICO OFICIAL DEL ESTADO EL MISMO DIA Y REGULADO ACTUALMENTE POR LA LEY SOBRE EL\nSISTEMA ESTATAL DE ASISTENCIA SOCIAL NUMERO 332, SISTEMA ESTATAL DE ASISTENCIA SOCIAL,\nNÚMERO 332, ARTÍCULO 4, FRACCIONES I A LA XV; ARTÍCULO II BIS, FRACCIÓN I AL IV Y ARTÍCULO 11\nDE FECHA 20 DE FEBRERO DEL 2015.\n1.2- QUE ENTRE OTRO, TIENE LOS SIGUIENTES OBJETIVOS:\n- PROPORCIONAR EN TODOS SUS ASPECTOS LA PROMOCION DE ASISTENCIA SOCIAL.\n- PROMOCIONAR EL AUXILIO Y ASISTENCIA A FAMILIAS DESAMPARADAS EN LA ENTIDAD.\n2- EL “DONATARIO” DECLARA\n2.1 APOYO A PERSONAS DE BAJOS RECURSOS ECONÓMICOS, DEL MUNICIPIO DE\nENTERADAS LAS PARTES DE LAS DECLARACIONES ANTERIORES, ES SU LIBRE VOLUNTAD OBLIGARSE A LAS\nSIGUIENTES:\nEJERCICIO FISCAL 2023\nPRIMERA. -LOS DONANTES TRANSFIEREN DE MANERA PURA GRATUITAMENTE AL DONATARIO LOS\nARTÍCULOS SIGUIENTES __________, MÓDULOS/DESPENSA DEL PROGRAMA DESAYUNOS ESCOLARES\nCALIENTES DE ACUERDO CON LO ESPECIFICADO EN LA SALIDA NO. ____________, CON NO. PUNTO DE\nLICITACIÓN ___________.\nSEGUNDA. - EL DONATARIO, ACEPTA LA DONACIÓN HECHA A SU FAVOR POR LOS DONANTES, RESPECTO\nDE LOS ARTÍCULOS DESCRITOS EN LA CLÁUSULA PRIMERA.\nTERCERA. - AMBAS PARTES MANIFIESTAN SU CONFORMIDAD EN LA FIRMA DEL PRESENTE CONTRATO,\nPOR NO EXISTIR VIOLENCIA, DOLO, MALA FE, LESIÓN O CUALQUIER OTRO VICIO DE CONOCIMIENTO QUE\nPUDIERAN NOTIFICAR O INVALIDAR EL ACTO QUE AQUÍ SE CONSIGNA.\nLEÍDO QUE FUE EL PRESENTE CONTRATO Y ENTERADAS LAS PARTES DE SU VALOR Y CONSECUENCIAS\nLEGALES, SE FIRMA EN LA CIUDAD DE CHILPANCINGO, GRO., A LOS ___DÍAS DEL MES _____________ DEL\nAÑO DOS MIL VEINTITRÉS.\nLIC. ANTELMO MAGDALENO SOLÍS\n___________________________________\nDIRECTOR GENERAL DEL SEDIF GUERRERO\nLIC. ROGELIO GUTIÉRREZ VÁZQUEZ LIC. CARLOS REZA RODRÍGUEZ\n__________________________________ _____________________________________\nDESARROLLO COMUNITARIO\nRECIBIÓ\n___________________________\nDONATARIO\nPROGRAMA DE ALIMENTACIÓN ESCOLAR MODALIDAD CALIENTE,\nPARA EL EJERCICIO FISCAL 2023.\nAnexo 3 Padrón de Beneficiarios\n• Padrón Físico de Beneficiarios.\nPROGRAMA DE ALIMENTACIÓN ESCOLAR MODALIDAD CALIENTE,\nPARA EL EJERCICIO FISCAL 2023.\n• Padrón Digital de Beneficiarias y Beneficiarios.\nEJERCICIO FISCAL 2023.\nAnexo 4 Acta Constitutiva de Formación de Comité\nSUBDIRECCIÓN DE ASISTENCIA ALIMENTARIA\nACTA CONSTITUTIVA DE COMITÉ DE DESAYUNOS ESCOLARES\nNOMBRE DEL PLANTEL EDUCATIVO\nDOMICILIO\nNIVEL TURNO\nCLAVE ESCOLAR CICLO ESCOLAR\nCORREO ELECTRONICO TEL. DEL PLANTEL\nLUGAR Y FECHA DE LEVANTAMIENTO DEL ACTA\nEN LA COMUNIDAD DEL ____________________ DEL MUNICIPIO SIENDO LAS\n____________ HORAS DEL DIA _____ DEL MES DE __________ DEL AÑO ____\nREUNIDOS EN EL PLANTEL EDUCATIVO ________________________________ SE\nLLEVA ACABO LA ASAMBLEA CON EL PROPÓSITO DE CONSTITUIR EN EL\nCOMITÉ ESCOLAR DEL PROGRAMA DE ALIMENTACIÓN ESCOLAR MODALIDAD\nCALIENTE CORRESPONDIENTE AL CICLO ESCOLAR _____________________\nCON UBICACIÓN EN LA ________________ CALLE ________________________,\nNO. ________ DE LA COLONIA _____________________________, EN EL USO DE\nLA PALABRA EL C. ____________________________________ REPRESENTANTE\nDEL SISTEMA ESTATAL PARA EL DESARROLLO INTEGRAL DE LA FAMILIA (DIFGUERRERO) Y LOS (AS) C.C.C.C ________________________________________\n_____________________________________________________________________\nEN SU CARACTER DE REPRESENTANTES DEL DIF MUNICIPAL, DIRECCION DE\nLA ESCUELA, DEL CONSEJO DE PARTICIPACIÓN SOCIAL O DEL COMITÉ DE\nLOCALIDAD RESPECTIVAMENTE, QUIENES REPRESENTAN A LA COMUNIDAD,\nPARA LA OPERACIÓN DE LA COCINA, MISMO QUE SE RENOVARA CADA AÑO,\nUNA VEZ QUE ESTE TERMINE SU GESTIÓN.\nEJERCICIO FISCAL 2023.\nDE ALIMENTACIÓN ESCOLAR MODALIDAD CALIENTE Y MESAS DE TRABAJO, QUIENES SE\nCALIENTES.\nSERÁ RESPONSABILIDAD DEL COMITÉ DE ALIMENTACIÓN ESCOLAR MODALIDAD CALIENTE Y LAS\nMESAS DE TRABAJO EL BUEN FUNCIONAMIENTO DEL PROGRAMA JUNTAMENTE CON LA SUPERVISIÓN\nDE LAS AUTORIDADES MUNICIPALES Y DEL COORDINADOR DE LA REGIÓN POR PARTE DEL SISTEMA\nESTATAL DIF.\nLOS QUE ASUMEN LA RESPONSABILIDAD DE FORMAR PARTE DE LAS MESAS DE TRABAJO, SERÁN\nCITADOS EN LA FECHA SEÑALADA PARA ELABORAR LOS DESAYUNOS ESCOLARES CALIENTES, EN LAS\nSEMANAS QUE LES CORRESPONDA DENTRO DE LA COCINA; SI POR ALGUNA CIRCUNSTANCIA,\nALGUNA DE ELLAS NO SE PRESENTARÁ EN LA SEMANA QUE LE CORRESPONDE, EL COMITÉ SEÑALAR\nLA SANCIÓN A QUE SE HACE ACREEDOR.\nEL REPRESENTANTE DE LA ESCUELA (DIRECTORA O DIRECTOR), LA COMUNIDAD, CONSEJO DE\nPARTICIPACIÓN SOCIAL, EL COMITÉ DE PADRES DE FAMILIA Y AUTORIDADES MUNICIPALES\nMANIFIESTAN SU ACUERDO Y SE RESPONSABILIZAN EN EL BUEN FUNCIONAMIENTO DEL PROGRAMA\nY SI POR ALGUNA CIRCUNSTANCIA EL COMITÉ DEL DESAYUNO ESCOLAR DEJARÁ DE FUNCIONAR O\nBIEN QUE NO SE CUMPLA CON LOS FINES DEL PROGRAMA, SE LE SUSPENDERÁ LA DESPENSA\nESCOLAR Y LOS UTENSILIOS DE COCINA, SE RECOGERÁN PARA SER ENTREGADOS A OTRO PLANTEL\nEDUCATIVO QUE LO REQUIERA, BAJO RESGUARDO FIRMADO POR LOS INTERESADOS.\nEN CASO DE ENCONTRAR ALGÚN MENOR CON UN GRADO DE INSEGURIDAD ALIMENTARIA SEVERO\nEL COMITÉ DEL DESAYUNO ESCOLAR DEBERÁ ASEGURARSE QUE EL MENOR RECIBASU DESAYUNO\nCALIENTE SIN COBRO DE ALGÚN MECANISMO DE CORRESPONSABILIDAD, LAS PERSONAS\nBENEFICIARIAS QUE NO PRESENTEN ESTA CIRCUNSTANCIA DEBEN CUBRIR UNA APORTACIÓN\nMÁXIMA DE $5.00 POR RACIÓN ALIMENTARIA, CUALQUIER AUMENTO DEBERÁ SER SOLICITADO POR\nESCRITO AL SISTEMA ESTATAL DIF GUERRERO, ADJUNTANDO DOCUMENTO DE INGRESOS EGRESOS\nQUE RESPALDEN LA MODIFICACIÓN DE ESTE MECANISMO DE CORRESPONSABILIDAD.\nUNA VEZ DEMOSTRADO QUE EL COMITE DEL DESAYUNO CALIENTE Y LAS PERSONAS BENEFICIARIAS\nACEPTARON EL PROGRAMA, SE PROCEDERÁ A VALORAR LA ENTREGA DE LOS MÓDULOS DE\nACUERDO CON LA MATRICULA ESCOLAR.\nEL DIF ESTATAL APOYARÁ CON LA CAPACITACIÓN PARA LA ELABORACIÓN DE LOS 20 MENÚS\nCÍCLICOS CON PRODUCTOS QUE INTEGRAN EL MODULO/DESPENSA DE DESAYUNO ESCOLAR\nCALIENTE, ASÍ COMO SUPERVISIÓN Y ASESORAMIENTO PARA LA INCORPORACIÓN DEL PROYECTO\nDE HUERTOS ESCOLARES PEDAGÓGICOS, QUE PERMITAN DOTAR DE LOS INSUMOS PERECEDEROS\nAL COMEDOR ESCOLAR, SIEMPRE Y CUANDO SE CUENTE CON LA PARTICIPACIÓN ACTIVA DE LAS\nMADRES Y PADRES DE FAMILIA, CON LA FINALIDAD DE MEJORAR EL FUNCIONAMIENTO EN BENEFICIO\nDE LA CALIDAD DE ALIMENTOS PROPORCIONADOS A LAS NIÑAS Y NIÑOS.\nCOMEDOR ESCOLAR:\nEJERCICIO FISCAL 2023.\nCARGO NOMBRE FIRMA\nPRESIDENTE (A).\nTESORERO (A).\nRESPONSABLE DE\nNUTRICIÓN Y EDUCACIÓN\nALIMENTARIA.\nRESPONSABLE DE LA\nCALIDAD ALIMENTARIA.\nRESPONSABLE DE\nVIGILANCIA NUTRICIONAL.\nRESPONSABLE DEL\nHUERTO ESCOLAR (EN\nLOS CASOS QUE\nAPLIQUE).\nRESPONSABLE DE LA\nVIGILANCIA CIUDADANA.\nUNA VEZ CONFORMADO EL COMITE, LAS RESPONSABILIDADES DE CADA INTEGRANTE SERÁN LAS\nSIGUIENTES:\na) PRESIDENTE (A)\n• PROMOVER LA INTEGRACIÓN DEL COMITÉ, DEBIENDO RENOVARSE O RATIFICARSE CADA CICLO\nESCOLAR. AL MOMENTO DE REALIZAR CAMBIOS DE PERSONAL EN EL COMITÉ, SE SOLICITASE\nREALICE LA ENTREGA DE EQUIPO Y MOBILIARIO, ASÍ COMO EL ESPACIO FÍSICO AL COMITÉ\nENTRANTE.\n• LLENAR EN COORDINACIÓN CON EL DIRECTOR DEL PLANTEL, EL PADRÓN DE BENEFICIARIOS, ASÍ\nCOMO CUALQUIER OTRA DOCUMENTACIÓN REQUERIDA POR EL SEDIF Y/O SMDIF Y ENTREGARLA EN\nTIEMPO Y FORMA A LA AUTORIDAD CORRESPONDIENTE.\n• PROPORCIONAR INFORMACIÓN VERÍDICA DE ACUERDO CON LO QUE SE LE SOLICITE EN EL\nPADRÓN DE BENEFICIARIOS.\n• COORDINAR LA RECEPCIÓN, REVISAR LA CALIDAD Y LA CANTIDAD DE LOS INSUMOS\nALIMENTICIOS ENTREGADOS POR EL SEDIF Y/O SMDIF, ASÍ COMO FIRMAR Y SELLAR LOS\nDOCUMENTOS COMPROBATORIOS DE CADA ENTREGA.\n• RESGUARDAR Y MANTENER EN ÓPTIMAS CONDICIONES EL EQUIPO, MOBILIARIO, UTENSILIOS Y\nESPACIO FÍSICO.\n• ASISTIR Y PARTICIPAR EN LOS CURSOS DE CAPACITACIÓN CONVOCADOS POR EL SEDIF Y/O\nSMDIF, CON EL PROPÓSITO DE OPERAR CORRECTAMENTE EL PROGRAMA.\n• SER EL ENLACE DIRECTO ENTRE LA ESCUELA Y EL SMDIF Y/O H. AYUNTAMIENTO EN\nCOORDINACIÓN CON LAS AUTORIDADES LOCALES.\nEJERCICIO FISCAL 2023.\nb) TESORERO (A)\n• PROMOVER ENTRE LOS PADRES DE FAMILIA DE LOS MENORES BENEFICIARIOS, QUE CUMPLAN\nCON SU OBLIGACIÓN DE APORTAR EL MECANISMO DE RESPONSABILIDAD.\n• UTILIZAR LOS RECURSOS PARA EL FORTALECIMIENTO DEL PROGRAMA Y LA ADQUISICIÓN DE\nLOS PRODUCTOS PERECEDEROS QUE COMPLEMENTARÁN LOS MENÚS, DE PREFERENCIA FRUTAS\nY VERDURAS FRESCAS, ADEMÁS DE OTROS GASTOS DE OPERACIÓN.\n• SE SUGIERE LLEVAR UNA BITÁCORA DONDE SE REGISTRE LA CONTRAPRESTACIÓN DE LOS\nPADRES DE FAMILIA Y EL MANEJO DE LA MISMA.\n• TODOS LOS ACUERDOS QUE SE TOMEN RESPECTO A LA CONTRAPRESTACIÓN, DEBEN QUEDAR\nASENTADOS EN MINUTA FIRMADA POR PARTE DE LOS PADRES DE FAMILIA.\n• ASISTIR Y PARTICIPAR EN LOS CURSOS DE CAPACITACIÓN CONVOCADOS POR EL SEDIF Y/O\nSMDIF, CON EL PROPÓSITO DE OPERAR CORRECTAMENTE EL PROGRAMA.\nc) RESPONSABLE DE NUTRICIÓN Y EDUCACIÓN ALIMENTARIA.\n• VIGILAR QUE LOS INSUMOS ALIMENTICIOS SEAN DE USO EXCLUSIVO PARA EL CONSUMO DE LOS\nESCOLARES Y LA PREPARACIÓN DE LOS ALIMENTOS EN MODALIDAD CALIENTE.\n• EN EL CASO DE LA ALIMENTACIÓN ESCOLAR EN MODALIDAD CALIENTE, COORDINAR LA\nPREPARACIÓN Y ENTREGA A LAS Y LOS BENEFICIARIOS DE LOS ALIMENTOS DE LUNES A VIERNES AL\nINICIO DE LA JORNADA ESCOLAR, O BIEN, EL HORARIO MÁS CONVENIENTE ESTABLECIDO EN\nASAMBLEA DE PADRES DE FAMILIA, Y CONTRIBUYENDO AL ADECUADO ESTADO DE NUTRICIÓN Y\nRENDIMIENTO DE LA POBLACIÓN ESCOLAR.\n• VERIFICAR Y PROMOVER QUE LAS PREPARACIONES DE ALIMENTOS SEAN DE ACUERDO CON LOS\nMENÚS CÍCLICOS ENTREGADOS POR ELSEDIF Y/O ELSMDIF.\n• ASISTIR Y PARTICIPAR EN LOS CURSOS DE CAPACITACIÓN CONVOCADOS POR EL SEDIF Y/O\nSMDIF, CON EL PROPÓSITO DE OPERAR CORRECTAMENTE EL PROGRAMA. ESTRATEGIA INTEGRAL\nDE ASISTENCIA SOCIAL, ALIMENTACIÓN Y DESARROLLO COMUNITARIO 2023 UNIDAD DE ATENCIÓN A\nPOBLACIÓN VULNERABLE DIRECCIÓN GENERAL DE ALIMENTACIÓN Y DESARROLLO COMUNITARIO 10\n• VERIFICAR QUE LOS ALIMENTOS ADQUIRIDOS CON RECURSOS EXTERNOS AL PROGRAMA, SEAN\nLOS PERMITIDOS EN LA EIASADC, FAVORECIENDO LA BUENA NUTRICIÓN DE LAS Y LOS\nBENEFICIARIOS.\n• PROMOVER ENTRE EL COMITÉ, MADRES Y PADRES DE FAMILIA Y ALUMNADO, LA CONTINUIDAD\nPOR PARTE DEL SEDIF O SMDIF.\nD) RESPONSABLE DE LA CALIDAD ALIMENTARIA\n• REVISAR QUE LA CADUCIDAD Y LOS ENVASES DE LOS INSUMOS ALIMENTICIOS SE ENCUENTREN\nVIGENTES Y EN BUEN ESTADO AL MOMENTO DE LA RECEPCIÓN YANTES DE SER UTILIZADOS.\n• ALMACENAR LOS INSUMOS ALIMENTICIOS EN UN ÁREA EXCLUSIVA, ASÍ COMO REGISTRAR\nPRIMERAS ENTRADAS-PRIMERAS SALIDAS (PEPS), ATENDIENDO A LAS RECOMENDACIONES\nCONTENIDAS EN LA GUÍA DE INOCUIDAD (ANEXO T3.A).\n• VERIFICAR QUE LAS PERSONAS QUE PREPAREN LOS ALIMENTOS CUMPLAN CON UTILIZAR\nEJERCICIO FISCAL 2023.\nDELANTAL, CABELLO RECOGIDO, COFIA, UÑAS RECORTADAS, LIMPIAS Y SIN ESMALTE, ACUDIR\nASEADAS, SIN JOYERÍA, LAVARSE LAS MANOS ANTES, DURANTE Y DESPUÉS DE LA PREPARACIÓN DE\nLOS ALIMENTOS, ENTRE OTROS.\n•ASEGURAR QUE LA LIMPIEZA Y DESINFECCIÓN DE LOS UTENSILIOS Y EQUIPOS DE COCINA Y\nSUPERFICIES, SE REALICE ANTES, DURANTE Y AL FINALIZAR LA PREPARACIÓN DE LOS ALIMENTOS.\n• VIGILAR Y PROMOVER QUE LAS PERSONAS BENEFICIARIAS SE LAVEN LAS MANOS ANTES Y\nDESPUÉS DE CONSUMIR LOS ALIMENTOS.\n• ASISTIR Y PARTICIPAR EN LOS CURSOS DE CAPACITACIÓN CONVOCADOS POR EL SEDIF Y/O\nSMDIF, CON EL PROPÓSITO DE OPERAR CORRECTAMENTE EL PROGRAMA.\nE) RESPONSABLE DE VIGILANCIA NUTRICIONAL.\n• SER ENLACE ENTRE LA ESCUELA Y EL SMDIF O SEDIF PARA FACILITAR LA EVALUACIÓN DEL\nESTADO NUTRICIONAL DE LAS NIÑAS Y NIÑOS DEL PLANTEL EDUCATIVO.\n• APOYAR AL PERSONAL DEL SEDIF, SMDIF, SECRETARÍA DE SALUD O PROFESORES, EN LA\nEVALUACIÓN DEL ESTADO NUTRICIONAL, ASÍ COMO APLICACIÓN DE ENCUESTAS A LAS NIÑAS Y\nNIÑOS DEL CENTRO ESCOLAR, O PADRES DE FAMILIA EN LOS CASOS QUE APLIQUE.\n• RESGUARDAR LAS CÉDULAS UTILIZADAS PARALA EVALUACIÓN DEL ESTADO NUTRICIONAL\nOBTENIDAS EN LA ESCUELA.\n• ENTREGAR EL CONCENTRADO DE LA EVALUACIÓN DEL ESTADO NUTRICIONAL AL SEDIF Y/O SMDIF\nSEGÚN CORRESPONDA.\n• ASISTIR Y PARTICIPAR EN LOS CURSOS DE CAPACITACIÓN CONVOCADOS POR EL SEDIF Y/O\nSMDIF, CON EL PROPÓSITO DE OPERAR CORRECTAMENTE EL PROGRAMA.\nF) RESPONSABLE DEL HUERTO ESCOLAR PEDAGÓGICO.\n• ASISTIR Y PARTICIPAR EN LAS CAPACITACIONES Y ASESORÍAS PROPORCIONADAS POR EL SEDIF,\nSMDIF O INSTITUCIONES INVOLUCRADAS, EN EL MANEJO Y MANTENIMIENTO DEL HUERTO ESCOLAR\nPEDAGÓGICO.\n• COORDINAR LAS LABORES PARA DAR MANTENIMIENTO AL HUERTO ESCOLAR PEDAGÓGICO\nDURANTE EL PERIODO ESCOLAR Y VACACIONAL CON EL APOYO DE PADRES DE FAMILIA,\nPROFESORES INVOLUCRADOS, ASÍ COMO ALUMNAS Y ALUMNOS.\n• ALENTAR A LAS Y LOS PROFESORES SOBRE EL USO DEL HUERTO COMO RECURSO DE\nAPRENDIZAJE PARA LOS ALUMNOS.\n• ELABORAR UNA BITÁCORA DE SEGUIMIENTO AL HUERTO ESCOLAR DESCRIBIENDO LOS\nPERIODOS DE SIEMBRA Y COSECHA, VARIEDADES SEMBRADAS, ACCIONES DE MANTENIMIENTO,\nCAPACITACIONES RECIBIDAS, ACTIVIDADES SOBRE EL USO DEL HUERTO EN MATERIAS ESCOLARES,\nENTRE OTRAS, PARA DAR CONTINUIDAD A LAS ACCIONES REALIZADAS EN CADA CICLO ESCOLAR.\n• ASISTIR Y PARTICIPAR EN LOS CURSOS DE CAPACITACIÓN CONVOCADOS POR EL SEDIF Y/O\nSMDIF, CON EL PROPÓSITO DE OPERAR CORRECTAMENTE EL PROGRAMA.\nG) RESPONSABLE DE VIGILANCIA CIUDADANA\nEJERCICIO FISCAL 2023.\n• REGISTRAR EN UNA BITÁCORA LA CALIDAD, CANTIDAD Y NOMBRE DE LOS INSUMOS RECIBIDOS\nEN LAS DOTACIONES ALIMENTARIAS.\n• REPORTARA LA CONTRALORÍA DEL ESTADO EL DESVÍO, VENTA AL PÚBLICO O CUALQUIER MAL\nUSO DE LOS INSUMOS ALIMENTICIOS, POR EJEMPLO, LECHE O PIEZAS SUELTAS.\n• INFORMAR DE CUALQUIER IRREGULARIDAD O MANEJO INCORRECTO DE LOS RECURSOS.\n• DIFUNDIR MATERIALES CON INFORMACIÓN SOBRE LOS PROGRAMAS, ASÍ COMO DE LA\nVIGILANCIA CIUDADANA. RECOMENDACIONES PARA LA PROMOCIÓN DE LA PARTICIPACIÓN DE LAS\nY LOS DIRECTORES Y DOCENTE.\nASIMISMO, LA ASAMBLEA DETERMINA LAS MESAS DE TRABAJO QUE SON CONFORMADAS POR MADRES Y\nPADRES DE FAMILIA DE LOS MENORES BENEFICIADOS Y QUE SERVIRÁN COMO APOYO AL COMITÉ.\nFIRMANDO AL MARGEN Y EN SUS NOMBRES PARA LOS EFECTOS A QUE HAYA LUGAR LAS PERSONAS QUE\nEN ELLA INTERVINIERON.\nESPACIOS DE PARTICIPACIÓN SOCIAL\nLISTA DE ASISTENCIA\nREGIÓN: ______________________________________ FECHA:\nMUNICIPIO: ______________________________________\nLOCALIDAD: _____________________________________\nESCUELA: _______________________________________\nFIRMA O\nNo. PROG. NOMBRE HUELLA\nEJERCICIO FISCAL 2023.\n{\"tabla_1\":{\"columnas\":[\"C._______________________________________________\\n_\\nREPRESENTANTE DEL DIF MUNICIPAL\",\"C._____________________________________________\\n_\\nREPRESENTANTE DEL DIF GUERRERO\"],\"filas\":[{\"columna_1\":\"________________________________________________\\nDIRECTORA O DIRECTOR DE LA ESCUELA\",\"columna_2\":\"______________________________________________\\nRESPONSABLE DE LA VIGILANCIA CIUDADANA\"},{\"columna_1\":\"C. ____________________________________________\\nCONSEJO DE PARTICIPACIÓN SOCIAL Y/O COMITÉ\\nDE PADRES DE FAMILIA\",\"columna_2\":\"(sin dato)\"},{\"columna_1\":\"TESTIGOS\",\"columna_2\":\"(sin dato)\"},{\"columna_1\":\"C._________________________________\",\"columna_2\":\"C.____________________________________\"}]}}\nEJERCICIO FISCAL 2023.\nAnexo 5. Estudio Socioeconómico\nEJERCICIO FISCAL 2023.\nAnexo 6. Convenio de Colaboración\nCONVENIO DE COLABORACIÓN DEL PROGRAMA\nALIMENTACIÓN ESCOLAR MODALIDAD CALIENTE\nCONVENIO DE COLABORACIÓN PARA LA OPERACIÓN DEL PROGRAMA ALIMENTACIÓN ESCOLAR MODALIDAD CALIENTE,\nPARA EL EJERCICIO 2023, OUE CELEBRAN POR UNA PARTE EL SISTEMA PARA EL DESARROLLO INTEGRAL DE LA FAMILIA\nDEL ESTADO DE GUERRERO, EN LO SUCESIVO “EL SEDIF”, REPRESENTADO POR SU DIRECTOR GENERAL, EL C.\nANTELMO MAGDALENO SOLÍS, ASISTIDO POR LA DIRECTORA DE ASISTENCIA ALIMENTARIA Y DESARROLLO\nCOMUNITARIO C. MARGARITA DE JESÚS RAMÍREZ SALGADO Y POR LA OTRA, EL H. AYUNTAMIENTO DEL MUNICIPIO DE\nXOCHIHUEHUETLAN, GUERRERO, REPRESENTADO POR SU PRESIDENTE(A) MUNICIPAL CONSTITUCIONAL, C.\nROSEMBERT PONCIANO VENEGAS Y ASISTIDO(A) POR EL DIRECTOR(A) DEL DIF MUNICIPAL C. GUADALUPE RIVERA\nPÉREZ, EN LO SUCESIVO “EL SMDIF”, A QUIENES CUANDO ACTÚEN DE MANERA CONJUNTA SE LES DENOMINARÁ “LAS\nPARTES”, DE CONFORMIDAD CON LAS SIGUIENTES DECLARACIONES Y CLÁUSULAS:\nQUE LA CONSTITUCIÓN POLÍTICA DE LOS ESTADOS UNIDOS MEXICANOS, EN SU ARTÍCULO CUARTO, ESTABLECE QUE\nTODA PERSONA TIENE DERECHO A LA ALIMENTACIÓN NUTRITIVA, SUFICIENTE Y DE CALIDAD\nQUE EL FONDO DE APORTACIONES MÚLTIPLES COMPONENTE ASISTENCIA SOCIAL (FAM-AS), FORMA PARTE DE LAS\nAPORTACIONES FEDERALES PARA ENTIDADES FEDERATIVAS Y MUNICIPIOS DEL RAMO GENERAL 33, QUE ES EL\nMECANISMO PRESUPUESTARIO DISEÑADO PARA TRANSFERIR A LOS ESTADOS Y MUNICIPIOS RECURSOS QUE LES\nPERMITAN FORTALECER SU CAPACIDAD DE RESPUESTA Y ATENDER DEMANDAS DE GOBIERNO EN LOS RUBROS DE\nPROGRAMAS ALIMENTARIOS, DE ASISTENCIA SOCIAL E INFRAESTRUCTURA EDUCATIVA; Y QUE DICHO FONDO ESTÁ\nREGULADO POR LA LEY DE COORDINACIÓN FISCAL, POR LA LEY FEDERAL DEL PRESUPUESTO Y RESPONSABILIDAD\nHACENDARIA Y EL PRESUPUESTO DE EGRESOS DE LA FEDERACIÓN 2023.\nQUE EL FORTALECIMIENTO DEL PRINCIPIO DE PACTO FEDERAL Y MUNICIPIO LIBRE ESTABLECIDO EN EL ARTÍCULO 2\nFRACCIÓN V DE LA LEY DE PLANEACIÓN, BUSCA LOGRAR UN DESARROLLO EQUILIBRADO DEL PAÍS, PROMOVIENDO LA\nDESCENTRALIZACIÓN DE LA VIDA NACIONAL\nQUE LA ESTRATEGIA INTEGRAL DE ASISTENCIA SOCIAL ALIMENTARIA Y DESARROLLO COMUNITARIO (EIASADC) 2023,\nTOMO 2 CRITERIOS NORMATIVOS; ESTABLECE EN EL APARTADO 3. CONVENIOS DE COLABORACIÓN, QUE LOS SEDIF\nDEBEN CELEBRAR CONVENIOS DE COLABORACIÓN CON LOS AYUNTAMIENTOS MUNICIPALES Y LOS SMDIF, EN EL MARCO\nDE LA OPERACIÓN DE LOS PROGRAMAS ALIMENTARIOS DERIVADOS DEL FAM-AS.\n\"ESTE PROGRAMA ES PÚBLICO, AJENO A CUALQUIER PARTIDO POLÍTICO. QUEDA PROHIBIDO EL USO PARA FINES DISTINTOS A LOS ESTABLECIDOS EN EL\nPROGRAMA.\" ARTICULO 28 NUMERAL II, FRACCIÓN A) DEL PEF 2023\nEJERCICIO FISCAL 2023.\n1. \"EL SEDIF\", DECLARA QUE:\n1.1. QUE ES UN ORGANISMO PÚBLICO DESCENTRALIZADO DE LA ADMINISTRACIÓN PÚBLICA ESTATAL CON\nPERSONALIDAD JURIDICA Y PATRIMONIO PROPIO, CON AUTONOMÍA ADMINISTRATIVA, PUBLICADA EN EL DIARIO\nOFICIAL DEL GOBIERNO DEL ESTADO, EL DÍA 9 DE MARZO DE MIL NOVECIENTOS NOVENTA Y SIETE, Y REGIDO\nACTUALMENTE POR LA LEY SOBRE EL SISTEMA ESTATAL DE ASISTENCIA SOCIAL NÚMERO 332, DE FECHA QUINCE\nDE JULIO DE MIL NOVECIENTOS OCHENTA Y SEIS.\n1.2. QUE TIENE ENTRE SUS OBJETIVOS:\n✓ PROMOVER Y PRESTAR SERVICIOS DE ASISTENCIA SOCIAL.\n✓ APOYAR EL DESARROLLO DE LA FAMILIA Y DE LA COMUNIDAD.\n✓ REALIZAR ACCIONES DE APOYO EDUCATIVO PARA LA INTEGRACIÓN SOCIAL Y DE CAPACITACIÓN PARA EL\nTRABAJO A LOS SUJETOS DE ASISTENCIA SOCIAL.\n✓ PROMOVER E IMPULSAR EL SANO CRECIMIENTO, FISICO, MENTAL Y SOCIAL DE LA NIÑEZ.\n✓ FOMENTAR, APOYAR, COORDINAR Y EVALUAR LAS ACTIVIDADES QUE LLEVEN A CABO LAS INSTITUCIONES DE\nASISTENCIA SOCIAL O ASOCIACIONES CIVILES Y TODO TIPO DE ENTIDADES PRIVADAS CUYO OBJETO SEA LA\nPRESTACIÓN DE SERVICIOS DE ASISTENCIA SOCIAL, SIN PERJUICIO DE LAS ATRIBUCIONES QUE AL EFECTO\nCORRESPONDAN A OTRAS DEPENDENCIAS.\n1.3. QUE ESTA LEGALMENTE REPRESENTADO POR EL C. ANTELMO MAGDALENO SOLÍS, QUIEN OSTENTA EL CARGO DE\nDIRECTOR GENERAL DEL SISTEMA PARA EL DESARROLLO INTEGRAL DE LA FAMILIA DEL ESTADO DE GUERRERO,\nPERSONALIDAD QUE ACREDITA CON EL NOMBRAMIENTO DE FECHA QUINCE DE FEBRERO DEL DOS MIL VEINTIDÓS,\nEXPEDIDO POR LA C. GOBERNADORA DEL ESTADO DE GUERRERO, LA MTRA. EVELYN CECIA SALGADO PINEDA Y\nSIGNADO POR EL MTRO. LUDWIG MARCIAL REYNOSO NÚÑEZ, SECRETARIO GENERAL DE GOBIERNO.\n1.4. QUE, EN EL EJERCICIO DE SUS FUNCIONES Y ATRIBUCIONES, CUENTA CON LAS FACULTADES NECESARIAS PARA\nSUSCRIBIR EL PRESENTE CONVENIO, DE CONFORMIDAD CON LO ESTABLECIDO EN EL ARTICULO 30 FRACCIÓN Vil, DE\nLA LEY SOBRE EL SISTEMA ESTATAL DE ASISTENCIA SOCIAL No. 332, POR LO QUE PUEDE CELEBRAR LOS CONVENIOS,\nCONTRATOS Y ACTOS JURÍDICOS QUE SEAN INDISPENSABLES PARA EL CUMPLIMIENTO DE LOS OBJETIVOS DEL\nSISTEMA PARA EL DESARROLLO INTEGRAL DE LA FAMILIA DEL ESTADO DE GUERRERO.\n1.5. QUE DE CONFORMIDAD CON LA FRACCIÓN I DEL ARTICULO 31 DEL REGLAMENTO INTERIOR DEL SISTEMA PARA EL\nDESARROLLO INTEGRAL DE LA FAMILIA DEL ESTADO DE GUERRERO, CORRESPONDE A LA DIRECCIÓN DE ASISTENCIA\nPROGRAMAS DE ASISTENCIA ALIMENTARIA, REPRESENTADA EN ESTE ACTO POR LA C. MARGARITA DE JESÚS\nRAMÍREZ SALGADO, DIRECTORA DE ASISTENCIA ALIMENTARIA Y DESARROLLO COMUNITARIO DE “EL SEDIF”, Y\nLIC. ANTELMO MAGDALENO SOLÍS, DIRECTOR GENERAL DEL SISTEMA PARA EL DESARROLLO INTEGRAL DE LA\nFAMILIA DEL ESTADO DE GUERRERO.\n\"ESTE PROGRAMA ES PÚBLICO, AJENO A CUALQUIER PARTIDO POLÍTICO. QUEDA PROHIBIDO EL USO PARA FINES DISTINTOS A LOS ESTABLECIDOS EN EL\nPROGRAMA.\" ARTICULO 28 NUMERAL II, FRACCIÓN A) DEL PEF 2023\nEJERCICIO FISCAL 2023.\n1.6. QUE SEÑALA COMO SU DOMICILIO EL UBICADO EN GABRIEL LEYVA ESQ CON RUFFO FIGUEROA, SIN NÚMERO,\nCOLONIA BURÓCRATAS, EN CHILPANCINGO DE LOS BRAVO, GUERRERO. C.P. 39090.\n2. \"EL SMDIF”, DECLARA QUE:\n2.1 ES LA INSTANCIA QUE ATIENDE LA ASISTENCIA SOCIAL EN EL MUNICIPIO DE XOCHIHUEHUETLAN, GRO., CON APOYO\nDEL H. AYUNTAMIENTO MUNICIPAL CONSTITUCIONAL.\n2.2 TIENE ENTRE SUS OBJETIVOS: PROMOVER EL BIENESTAR SOCIAL Y PRESTAR SERVICIOS DE ASISTENCIA SOCIAL,\nCON APOYO EN LAS NORMAS LEGALES QUE DICTEN LAS SECRETARÍAS DE SALUD, DESARROLLO SOCIAL,\nEDUCACIÓN, DIF NACIONAL, “EL SEDIF” Y LAS QUE EL PROPIO MUNICIPIO TENGA ESTABLECIDAS; PROMOVER EL\nDESARROLLO DE LA FAMILIA EN COMUNIDADES CON MAYOR ÍNDICE DE MARGINACIÓN Y VULNERABILIDAD, IMPULSAR\nEL SANO CRECIMIENTO FÍSICO Y MENTAL DE LA NIÑEZ, DAR CUMPLIMIENTO A LOS DECRETOS, ACUERDOS,\nCONVENIOS O CUALQUIER OTRA FIGURA JURÍDICA, ENCAMINADA A LA OBTENCIÓN DE BIENESTAR SOCIAL Y DEMÁS\nLEYES APLICABLES, INCLUYENDO LAS ATRIBUCIONES DEL PRESIDENTE MUNICIPAL.\n2.3 QUE EL (LA) C. ROSEMBERT PONCIANO VENEGAS, ACREDITA SU PERSONALIDAD CON LA CONSTANCIA DE MAYORÍA\nY VALIDEZ EXPEDIDA POR EL INSTITUTO ELECTORAL Y DE PARTICIPACIÓN CIUDADANA DEL ESTADO DE GUERRERO\nCON FECHA 10 DE JUNIO DEL 2021, LA CUAL DECLARA COMO PRESIDENTE(A) MUNICIPAL CONSTITUCIONAL ELECTO(A)\nDEL MUNICIPIO DE XOCHIHUEHUETLAN, GUERRERO.\n2.4 QUE EL(LA) C. GUADALUPE RIVERA PÉREZ, QUIÉN OSTENTA EL CARGO DE DIRECTOR(A) DEL SISTEMA MUNICIPAL\nPARA EL DESARROLLO INTEGRAL DE LA FAMILIA DEL MUNICIPIO DE XOCHIHUEHUETLAN GUERRERO, ACREDITA SU\nPERSONALIDAD CON EL NOMBRAMIENTO DE FECHA 04 DE OCTUBRE DEL 2021, EXPEDIDO POR EL(LA) C. ROSEMBERT\nPONCIANO VENEGAS, PRESIDENTE(A) MUNICIPAL CONSTITUCIONAL, QUIEN SE ENCUENTRA FACULTADO(A) PARA\nCELEBRAR EL PRESENTE CONVENIO DE COLABORACIÓN.\n2.5 QUE SEÑALA COMO DOMICILIO EL UBICADO EN CALLE DEL PARQUE CENTRAL S/N COL. CENTRO. H. AYUNTAMIENTO\nDEL MUNICIPIO DE XOCHIHUEHUETLAN GUERRERO.\n3. “LAS PARTES” DECLARAN QUE:\n3.1 QUE MANIFIESTAN BAJO PROTESTA DE DECIR VERDAD QUE, EN LA ELABORACIÓN DEL PRESENTE CONVENIO DE\nCOLABORACIÓN, NO EXISTE DOLO, ERROR, VIOLENCIA FÍSICA O MORAL, MALA FE, NI NINGÚN OTRO VICIO DEL\nCONSENTIMIENTO Y QUE ES SU LIBRE VOLUNTAD FORMALIZARLO.\n3.2 QUE SE RECONOCEN MUTUAMENTE LA CAPACIDAD LEGAL Y PERSONALIDAD JURÍDICA PARA CELEBRAR EL\nPRESENTE CONVENIO DE COLABORACIÓN Y MANIFIESTAN SU VOLUNTAD DE OTORGAR Y SOMETERSE AL MISMO.\nEXPUESTO LO ANTERIOR, “LAS PARTES” SE OBLIGAN DE CONFORMIDAD CON LAS SIGUIENTES:\n\"ESTE PROGRAMA ES PÚBLICO, AJENO A CUALQUIER PARTIDO POLÍTICO. QUEDA PROHIBIDO EL USO PARA FINES DISTINTOS A LOS ESTABLECIDOS EN EL\nPROGRAMA.\" ARTICULO 28 NUMERAL II, FRACCIÓN A) DEL PEF 2023\nEJERCICIO FISCAL 2023.\nPRIMERA. - OBJETO.\nEL PRESENTE CONVENIO TIENE POR OBJETO ESTABLECER LAS BASES DE COLABORACIÓN ENTRE “EL SEDIF” Y “EL SMDIF”,\nPARA COORDINAR LA OPERACIÓN DEL PROGRAMA ALIMENTACIÓN ESCOLAR MODALIDAD CALIENTE, EN ADELANTE\nDENOMINADO “EL PROGRAMA”, CON BASE EN EL RECURSO ASIGNADO A LA ENTIDAD FEDERATIVA DEL RAMO GENERAL 33,\nFONDO DE APORTACIONES MÚLTIPLES COMPONENTE ASISTENCIA SOCIAL PARA EL EJERCICIO FISCAL 2023.\nSEGUNDA. - OBJETIVO Y POBLACIÓN OBJETIVO DEL PROGRAMA.\nEL OBJETIVO DE “EL PROGRAMA”, ES FAVORECER EL ACCESO Y CONSUMO DE ALIMENTOS NUTRITIVOS E INOCUOS DE LA\nPOBLACIÓN DE ATENCIÓN PRIORITARIA, QUE ASISTEN A PLANTELES PÚBLICOS DEL SISTEMA EDUCATIVO NACIONAL,\nMEDIANTE LA ENTREGA DE DESAYUNOS ESCOLARES, DISEÑADOS CON BASE EN CRITERIOS DE CALIDAD NUTRICIA,\nACOMPAÑADOS DE ACCIONES DE ORIENTACIÓN Y EDUCACIÓN ALIMENTARIA, ASÍ COMO DE ASEGURAMIENTO DE LA\nCALIDAD, PARA FAVORECER UN ESTADO DE NUTRICIÓN ADECUADO.\nLA POBLACIÓN OBJETIVO A LA CUAL SE DIRIGEN LAS ACCIONES DE “EL PROGRAMA” SERÁ LA QUE ESTABLECE LA\nESTRATEGIA INTEGRAL DE ASISTENCIA SOCIAL ALIMENTARIA Y DESARROLLO COMUNITARIO 2023, ASÍ COMO LAS REGLAS\nDE OPERACIÓN, Y CORRESPONDE A LA SIGUIENTE:\nA) NIÑAS, NIÑOS Y ADOLESCENTES QUE ASISTEN A PLANTELES PÚBLICOS DEL SISTEMA EDUCATIVO NACIONAL,\nUBICADOS EN MUNICIPIOS, LOCALIDADES O AGEB RURALES, URBANAS O INDÍGENAS DE ALTO Y MUY ALTO GRADO DE\nMARGINACIÓN (CENTRO NACIONAL DE POBLACIÓN (CONAPO) 2020). O DE REZAGO SOCIAL (CONEVAL 2020).\nB) NIÑAS, NIÑOS Y ADOLESCENTES QUE ASISTEN A PLANTELES PÚBLICOS DEL SISTEMA EDUCATIVO NACIONAL CON\nUNA PREVALENCIA MAYOR O IGUAL AL 15% DE ESTUDIANTES CON DESNUTRICIÓN, INDEPENDIENTE DEL GRADO DE\nMARGINACIÓN.\nEL APOYO DE “EL PROGRAMA” SE OTORGARÁ EN EL MUNICIPIO DE XOCHIHUEHUETLAN, GUERRERO., DE ACUERDO CON EL\nRECURSO ANUAL PROGRAMADO Y CON LOS RESULTADOS DE LOS CRITERIOS Y LAS ACTIVIDADES DE FOCALIZACIÓN, QUE\nALTA Y MUY ALTA MARGINACIÓN.\n\"ESTE PROGRAMA ES PÚBLICO, AJENO A CUALQUIER PARTIDO POLÍTICO. QUEDA PROHIBIDO EL USO PARA FINES DISTINTOS A LOS ESTABLECIDOS EN EL PROGRAMA.\"\nARTICULO 28 NUMERAL II, FRACCIÓN A) DEL PEF 2023\nEJERCICIO FISCAL 2023.\nTERCERA. - CONFORMACIÓN DE LOS APOYOS.\nALIMENTACION ESCOLAR MODALIDAD CALIENTE\nALIMENTACION ESCOLAR MODALIDAD CALIENTE (MONTAÑA)\nNÚM PRODUCTO UNIDAD PRESENTACIÓN CANT\nLECHE DESCREMADA EN POLVO (DESHIDRATADA)\nSABOR NATURAL ADICIONADA CON VITAMINA A Y D\n2 LENTEJA G BOLSA DE 500 G 1\n3 GARBANZO GRANDE ENTERO KG BOLSA DE 1 KG 1\n4 AVENA EN HOJUELAS KG BOLSA DE 1 KG 2\n5 FRIJOL NEGRO KG BOLSA DE 1 KG 6\nHARINA DE MAÍZ NIXTAMALIZADO ADICIONADA CON\n6 ACIDO FÓLICO, HIERRO Y ZINC, Y RESTITUIDA CON KG BOLSA DE 1 KG 5\nVITAMINAS B1, VITAMINA B2, VITAMINA B3\n7 ACEITE DE CAÑOLA LT BOTELLA DE 1 LT 1\n8 ARROZ SÚPER EXTRA KG BOLSA DE 500 G 3\nENSALADA DE VEGETALES (ZANAHORIA, EJOTE Y\nCHÍCHARO)\n10 CARNE DE RES NATURAL DESHEBRADA G BOLSA DE 200 G 3\n11 AMARANTO REVENTADO G BOLSA DE 100 G 4\n12 CARNE DE POLLO MAGRA NATURAL DESHEBRADA G BOLSA DE 200 G 5\nPASTA PARA SOPA DE HARINA DE TRIGO INTEGRAL\n(VARIEDAD DE FIGURAS)\nPASTA PARA SOPA DE HARINA DE TRIGO INTEGRAL\n(ESPAGUETTI)\nGELATINA EN POLVO DIFERENTES SABORES SIN\n15 G SOBRE 25G 16\nAZÚCAR AÑADIDA\nALIMENTACIÓN ESCOLAR MODALIDAD CALIENTE\n(ZONA COSTA CHICA Y TIERRA CALIENTE)\nNÚM PRODUCTO UNIDAD PRESENTACIÓN CANT\nLECHE DESCREMADA EN POLVO (DESHIDRATADA)\n2 LENTEJA G BOLSA DE 500 G 1\n3 GARBANZO GRANDE ENTERO KG BOLSA DE 1 KG 1\n4 AVENA EN HOJUELAS KG BOLSA DE 1 KG 2\n\"ESTE PROGRAMA ES PÚBLICO, AJENO A CUALQUIER PARTIDO POLÍTICO. QUEDA PROHIBIDO EL USO PARA FINES DISTINTOS A LOS ESTABLECIDOS EN EL PROGRAMA.\"\nARTICULO 28 NUMERAL II, FRACCIÓN A) DEL PEF 2023\nEJERCICIO FISCAL 2023.\n5 FRIJOL NEGRO KG BOLSA DE 1 KG 4\n6 FRIJOL PINTO G BOLSA 900 G 1\nHARINA DE MAIZ NIXTAMAL IZADO ADICIONADA\n7 CON ACIDO FÓLICO, HIERRO Y ZINC, Y KG BOLSA DE 1 KG 5\nRESTITUIDA CON VITAMINAS B1, VITAMINA B2,\nVITAMINA B3\n8 ACEITE DE CAÑOLA LT BOTELLA DE 1 LT 1\n9 ARROZ SÚPER EXTRA KG BOLSA DE 1 KG 1\nENSALADA DE VEGETALES (ZANAHORIA, EJOTE\nY CHÍCHARO)\n11 ATÚN EN HOJUELAS EN AGUA G LATA DE 135 G 9\n12 AMARANTO REVENTADO G BOLSA DE 100G 4\nCARNE DE POLLO MAGRA NATURAL EN TROZO\nEN AGUA\nPASTA PARA SOPA DE HARINA DE TRIGO\nINTEGRAL (VARIEDAD DE FIGURAS)\nPASTA PARA SOPA DE HARINA DE TRIGO\nINTEGRAL (ESPAGUETTI)\nGELATINA EN POLVO DIFERENTES SABORES\nSIN AZÚCAR AÑADIDA\n• CUARTA. - NATURALEZA DE LOS RECURSOS.\nEL RECURSO CON QUE OPERAN “EL PROGRAMA” CORRESPONDEN A APORTACIONES FEDERALES ESTABLECIDAS EN EL\nPRESUPUESTO DE EGRESOS DE LA FEDERACIÓN 2023, PROVENIENTE DEL RAMO GENERAL 33 FONDO DE APORTACIONES\nMÚLTIPLES, COMPONENTE ASISTENCIA SOCIAL (FAM-AS); POR LO QUE SU FISCALIZACIÓN Y CONTROL SERÁ REALIZADA POR\nLA AUDITORÍA SUPERIOR DE LA FEDERACIÓN, LA SECRETARÍA DE LA FUNCIÓN PÚBLICA Y POR LA AUDITORÍA GENERAL DEL\nESTADO DE GUERRERO, EN ESTE SENTIDO, “LAS PARTES” SE OBLIGAN A:\nA) “EL SMDIF” DESARROLLARÁ LOS SISTEMAS DE CONTROL INTERNO QUE SEAN NECESARIOS A EFECTOS DE\nASEGURAR QUE LOS PROGRAMAS SEAN EJECUTADOS CON OPORTUNIDAD, ECONOMÍA, PRODUCTIVIDAD, LEGALIDAD,\nHONESTIDAD Y TRANSPARENCIA.\nB) “EL SEDIF”, POR CONDUCTO DE SU PERSONAL OPERATIVO, REALIZARÁ LAS VISITAS DE SEGUIMIENTO,\nEVALUACIONES Y SI ASÍ LO REQUIERE LA ENTREGA DIRECTA DE LOS INSUMOS, CON LA FINALIDAD DE TRANSPARENTAR\nLOS RECURSOS.\nQUINTA. - COMPROMISOS DE “EL SEDIF”.\nPARA LA APLICACIÓN DEL PRESENTE DOCUMENTO, “EL SEDIF”, DE ACUERDO CON EL APARTADO 8.2 COORDINACIÓN\nINSTITUCIONAL DE LOS SISTEMAS ESTATALES DIF, TOMO 2 EIASADC 2023 CRITERIOS NORMATIVOS, TENDRÁN LAS\nSIGUIENTES RESPONSABILIDADES:\n\"ESTE PROGRAMA ES PÚBLICO, AJENO A CUALQUIER PARTIDO POLÍTICO. QUEDA PROHIBIDO EL USO PARA FINES DISTINTOS A LOS ESTABLECIDOS EN EL PROGRAMA.\"\nARTICULO 28 NUMERAL II, FRACCIÓN A) DEL PEF 2023\nEJERCICIO FISCAL 2023.\nI. ELABORAR, CONSIDERANDO LO ESTABLECIDO EN LA PRESENTE ESTRATEGIA Y LA DEMÁS NORMATIVIDAD\nAPLICABLE, LOS INSTRUMENTOS PARA LA PLANEACIÓN, OPERACIÓN, SEGUIMIENTO Y EVALUACIÓN DE LOS\nPROGRAMAS DE LA EIASADC A NIVEL ESTATAL Y MUNICIPAL.\nII. ELABORAR LAS REGLAS DE OPERACIÓN PARA CADA UNO DE LOS PROGRAMAS DE LA EIASADC, CON EL\nPROPÓSITO DE TRANSPARENTAR Y NORMAR LA DISTRIBUCIÓN Y ENTREGA DE LOS APOYOS, CON BASE EN EL\n(ANEXO T2.A), DE LA EIASADC.\nIII. CELEBRAR CONVENIOS DE COLABORACIÓN CON LOS SMDIF PARA LA OPERACIÓN DE CADA UNO DE LOS\nPROGRAMAS DE LA EIASADC, BASÁNDOSE EN EL (ANEXO T2.B) DE LA EIASADC.\nIV. COORDINAR LA OPERACIÓN DE LOS PROGRAMAS DE LA EIASADC EN LA ENTIDAD FEDERATIVA CON LAS\nINSTANCIAS PARTICIPANTES.\nV. ADMINISTRAR Y EJERCER LOS RECURSOS PROVENIENTES DEL RAMO 33, FONDO VI, DE ACUERDO CON LA\nNORMATIVIDAD VIGENTE.\nVI. FOCALIZAR LA POBLACIÓN OBJETIVO DE CADA PROGRAMA, EN COORDINACIÓN CON LOS SMDIF, PRIORIZANDO\nLA POBLACIÓN EN MUNICIPIOS, LOCALIDADES O ÁREA GEOESTADlSTICA BÁSICA (GEB) RURALES, URBANAS O\nINDÍGENAS DE ALTO Y MUY ALTO GRADO DE MARGINACIÓN, DE ACUERDO CON LOS CRITERIOS ESTABLECIDOS\nEN LA PRESENTE ESTRATEGIA.\nVII. INICIAR OPORTUNAMENTE LA OPERACIÓN DE LOS PROGRAMAS DE LA EIASADC, Y ENTREGAR DE FORMA\nCONTINUA Y SIN INTERRUPCIONES LOS APOYOS, SERVICIOS Y CAPACITACIONES.\nVIII. FOMENTAR LA ORGANIZACIÓN, MOTIVACIÓN Y CONTINUIDAD DE LAS ACTIVIDADES REALIZADAS EN EL MARCO DE\nLOS DIFERENTES PROGRAMAS\nIX. CAPACITAR, ASESORAR Y DAR SEGUIMIENTO A LOS SMDIF EN LA OPERACIÓN DE LOS PROGRAMAS DE LA\nEIASADC.\nX. LLEVAR A CABO LOS PROCESOS DE LICITACIÓN PARA ADQUISICIÓN DE LOS INSUMOS DURANTE EL PRIMER\nTRIMESTRE DEL AÑO.\nXI. BUSCAR E IMPULSAR LA COORDINACIÓN INTERINSTITUCIONAL PARA FORTALECER LA OPERACIÓN DE LOS\nPROGRAMAS DE LA EIASADC.\nXII. DAR SEGUIMIENTO Y EVALUAR LA OPERACIÓN DE LOS PROGRAMAS DE LA EIASADC.\nXIII. PROMOVER LA FORMACIÓN Y OPERACIÓN DE LOS COMITÉS DE VIGILANCIA CIUDADANA PARA EL SEGUIMIENTO\nDE LOS PROGRAMAS.\nXIV. DE ACUERDO CON LA CIRCULAR UNO DEL 14 DE FEBRERO DE 2019, EMITIDA POR EL C. PRESIDENTE\nCONSTITUCIONAL DE LOS ESTADOS UNIDOS MEXICANOS, NO PODRÁN TRANSFERIRSE RECURSOS FEDERALES\nDEL FAM-AS A NINGUNA ORGANIZACIÓN SOCIAL, SINDICAL O CIVIL EN LA QUE ALGUNA DE ÉSTAS FUERA\nINTERMEDIARIO PARA LA ENTREGA DE LOS APOYOS A LOS BENEFICIARIOS.\nRECURSO Y OPERACIÓN DE LOS PROGRAMAS DE LA EIASADC.\nXVI. PROPORCIONAR A LA DGADC LA INFORMACIÓN ESPECÍFICA QUE ÉSTA SOLICITE, QUE PUEDE SER REQUERIDA\nEN DIFERENTES SITUACIONES Y TIEMPOS, ASÍ COMO LA ESTABLECIDA EN EL CALENDARIO 2023.\nXVII. ENTREGAR A LA DGADC LA INFORMACIÓN REQUERIDA PARA LA EVALUACIÓN DEL ÍNDICE DE DESEMPEÑO, DE\nACUERDO CON LAS INDICACIONES, FORMATOS Y CALENDARIO DE ENTREGA QUE EN ÉSTE SE SEÑALAN.\n\"ESTE PROGRAMA ES PÚBLICO, AJENO A CUALQUIER PARTIDO POLÍTICO. QUEDA PROHIBIDO EL USO PARA FINES DISTINTOS A LOS ESTABLECIDOS EN EL PROGRAMA.\"\nARTICULO 28 NUMERAL II, FRACCIÓN A) DEL PEF 2023\nEJERCICIO FISCAL 2023.\nXVIII. DETERMINAR LA VIABILIDAD DE ATENCIÓN A LAS SOLICITUDES DE APOYOS Y SERVICIOS DE LOS PROGRAMAS DE\nLA EIASADC POR PARTE DE LA CIUDADANÍA, TURNADAS POR LA DGADC, ASÍ COMO NOTIFICAR SOBRE LA\nRESPUESTA CORRESPONDIENTE.\nXIX EJERCER EL RECURSO PROVENIENTE DEL FAM-AS. DENTRO DEL EJERCICIO FISCAL PARA EL CUAL FUE\nTRANSFERIDO, EVITANDO SU APLICACIÓN EN EJERCICIOS FISCALES POSTERIORES.\nXX. CONCENTRAR, INTEGRAR, VALIDAR Y AUTORIZAR LOS PADRONES DE BENEFICIARIOS PARA CADA PROGRAMA\nOPERADO CON RECURSO DEL RAMO GENERAL 33 FAM-AS.\nXXI. PROMOVER QUE LA SELECCIÓN DE BENEFICIARIOS DE LOS PROGRAMAS OPERADOS CON RAMO 33 FAM-AS, SE\nREALICE TOMANDO EN CUENTA QUE NO HAYA DUPLICIDAD CON OTROS PROGRAMAS DE ASISTENCIA SOCIAL.\nXXII. APLICAR Y HACER UN USO ADECUADO DE LO DISPUESTO EN LA GUÍA DE IMAGEN GRÁFICA PARA LOS\nPROGRAMAS DE LA EIASADC 2022-2024.\nXXIII. DETERMINAR LA COMPOSICIÓN DE SUS APOYOS ALIMENTARIOS Y MENÚS PARA LOS PROGRAMAS QUE OPERE,\nDE ACUERDO CON LOS CRITERIOS DE CALIDAD NUTRICIA ESTABLECIDOS EN ESTA ESTRATEGIA.\nXXIV. ADQUIRIR LOS INSUMOS ALIMENTARIOS QUE CUMPLAN CON LAS ESPECIFICACIONES TÉCNICAS DE CALIDAD\n(ETC), ESTABLECIDAS EN CONGRUENCIA CON LOS CRITERIOS DE LA PRESENTE ESTRATEGIA.\nXXV. ASEGURAR EL CORRECTO ALMACENAMIENTO Y DISTRIBUCIÓN DE LOS INSUMOS, QUE PERMITA CONSERVAR SUS\nCARACTERISTICAS NUTRICIONALES, DE CALIDAD E INOCUIDAD, DESDE LA SELECCIÓN HASTA SU ENTREGA AL\nBENEFICIARIO.\nXXVI. DISEÑAR Y COORDINAR LA IMPLEMENTACIÓN DE LAS ACCIONES DE ORIENTACIÓN ALIMENTARIA Y\nASEGURAMIENTO DE LA CALIDAD, A FIN DE PROMOVER UNA ALIMENTACIÓN CORRECTA.\nXXVII PROMOVER LA INCLUSIÓN Y CONSUMO DE VERDURA Y FRUTA FRESCA COMO PARTE DE LOS APOYOS\nALIMENTARIOS.\nXXVIII IMPULSAR LA INSTALACIÓN Y USO DE HUERTOS ESCOLARES PEDAGÓGICOS PARA PROMOVER HÁBITOS\nALIMENTARIOS SALUDABLES.\nXXIX. PROMOVER LA ADAPTACIÓN, INSTALACIÓN, REMODELACIÓN Y EQUIPAMIENTO DE ESPACIOS ALIMENTARIOS.\nXXX. COORDINAR CON LAS INSTANCIAS CORRESPONDIENTES DEL SECTOR PÚBLICO, SOCIAL O PRIVADO, LA\nREALIZACIÓN DE ACCIONES DE VIGILANCIA NUTRICIONAL QUE COADYUVEN A LA ATENCIÓN INTEGRAL DE LA\nPOBLACIÓN BENEFICIARIA.\nXXXI. REALIZAR EN LABORATORIOS CERTIFICADOS POR ESPECIFICACIONES MEXICANA DE ACREDITACIÓN (EMA) O\nCOMISIÓN FEDERAL PARA LA PROTECCIÓN CONTRA RIESGOS SANITARIOS (COFEPRIS), LOS ANÁLISIS DE\nLABORATORIO POST-LICITACIÓN, DE SEGUIMIENTO Y/O AQUELLOS SOLICITADOS POR LA DGADC.\nXXXII. ENVIAR A LA DGADC LOS RESULTADOS DE LOS ANÁLISIS POST-LICITACIÓN, DE SEGUIMIENTO Y/O AQUELLOS\nSOLICITADOS POR LA MISMA, PARA VERIFICAR EL CUMPLIMIENTO DE LOS PARAMETROS DE CALIDAD E\nINOCUIDAD.\nXXXIII. CAPACITAR, ASESORAR Y DAR SEGUIMIENTO A \"EL SMDIF\" EN LA OPERACIÓN DE \"EL PROGRAMA\".\nXXXIV. INFORMAR A \"EL SMDIF\" OPORTUNAMENTE LA OPERACIÓN DE “EL PROGRAMA”, LA CALENDARIZACIÓN DE\nINSUMOS, RELACIÓN DE LOCALIDADES A BENEFICIAR, PERIODOS DE DISTRIBUCIÓN EN ALMACENES REGIONALES\nA FIN ENTREGAR DE FORMA CONTINUA Y SIN INTERRUPCIONES LAS DOTACIONES ALIMENTARIAS.\n\"ESTE PROGRAMA ES PÚBLICO, AJENO A CUALQUIER PARTIDO POLÍTICO. QUEDA PROHIBIDO EL USO PARA FINES DISTINTOS A LOS ESTABLECIDOS EN EL PROGRAMA.\"\nARTICULO 28 NUMERAL II, FRACCIÓN A) DEL PEF 2023\nEJERCICIO FISCAL 2023.\nXXXV. LLEVAR A CABO SESIONES PERIÓDICAS DE COORDINACIÓN CON \"EL SMDIF\" A FIN DE VALORAR LOS AVANCES EN\nTODOS LOS NIVELES OPERATIVOS DE \"EL PROGRAMA\", PARA LA TOMA DE DECISIONES QUE PERMITAN EL\nLOGRO DE LOS MISMOS\nXXXVI. REALIZAR VISITAS DE SEGUIMIENTO A \"EL SMDIF\" A FIN DE APOYAR Y BRINDAR ASESORIAS EN LA OPERACIÓN\nDE \"EL PROGRAMA\" Y VERIFICAR EL DESARROLLO DE LAS ESTRATEGIAS DE ACUERDO CON LOS\nPROCEDIMIENTOS ESTABLECIDOS.\nXXXVII. CONCENTRAR, AUTORIZAR E INTEGRAR LOS PADRONES DE BENEFICIARIOS DE “EL PROGRAMA”, ELABORADOS\nPOR “EL SMDIF\", CON BASE EN EL DECRETO POR EL QUE SE CREA EL SISTEMA INTEGRAL DE INFORMACIÓN DE\nPADRONES DE PROGRAMAS GUBERNAMENTALES (SIIPP-G), PUBLICADO EN EL DIARIO OFICIAL DE LA\nFEDERACIÓN (DOF) EL 12 DE ENERO DE 2006 Y A LAS VARIABLES MÍNIMAS CONSIDERADAS EN EL MANUAL DE\nOPERACIÓN DEL SISTEMA INTEGRAL DE INFORMACIÓN DE PADRONES DE PROGRAMAS GUBERNAMENTALES,\nPUBLICADO EN EL DOF EL 13 DE SEPTIEMBRE 2018.\nXXXVIII. AL INICIO DEL EJERCICIO FISCAL, \"EL SEDIF\" RECEPCIONARÁ LOS PADRONES Y EXPEDIENTES DE LOS\nBENEFICIARIOS, REMITIDOS POR \"EL SMDIF\", CON EL OBJETIVO DE VALIDAR Y/O AUTORIZAR LA FOCALIZACIÓN\nDE LOS BENEFICIARIOS, TOMANDO COMO BASE LAS REGLAS DE OPERACIÓN.\nXXXIX. ELABORAR AL INICIO DE CADA EJERCICIO FISCAL, EL PROYECTO DE LOS PROGRAMAS QUE CUENTAN CON\nMECANISMOS DE CORRESPONSABILIDAD PARA EL FORTALECIMIENTO DE LOS PROGRAMAS ALIMENTARIOS, CON\nLA APROBACIÓN DE LA H. JUNTA DE GOBIERNO, EN EL PRESENTE EJERCICIO, PARA “EL PROGRAMA” SERÁ DE\n$150.00 (CIENTO CINCUENTA PESOS 00/100 M.N) POR MÓDULO/DESPENSA, EXCEPTUANDO LOS MUNICIPIOS DE\nMUY ALTO GRADO DE MARGINACIÓN DE NUESTRO ESTADO DE GUERRERO Y AQUELLOS QUE PERTENEZCAN A\nLA ZONA MONTAÑA, QUIENES RECIBIRÁN SUS DOTACIONES ALIMENTARIAS DONADAS, ENTREGÁNDOLAS A LOS\nBENEFICIARIOS EN LA MISMA CONDICIÓN DE GRATUIDAD\nSEXTA. - COMPROMISOS DE “EL SMDIF”.\nDADO QUE LOS SMDIF SON UN ELEMENTO FUNDAMENTAL EN EL PROCESO DE OPERACIÓN DE LOS PROGRAMAS DE LA\nEIASADC, SE DEFINEN PARA ESTOS LAS SIGUIENTES RESPONSABILIDADES, DE ACUERDO CON EL APARTADO 8.3\nCOORDINACIÓN INSTITUCIONAL DE LOS SISTEMAS MUNICIPALES DIF, TOMO 2 EIASADC 2023 CRITERIOS NORMATIVOS.\nI. CELEBRAR EL CONVENIO DE COLABORACIÓN CON “EL SEDIF”, CON EL FIN DE OPERAR LOS PROGRAMAS DE LA\nEIASADC.\nII. PARTICIPAR DE FORMA CONJUNTA CON “EL SEDIF” EN EL ESTABLECIMIENTO DE MECANISMOS Y ESTRATEGIAS\nA SEGUIR PARA LA DETECCIÓN, SELECCIÓN, FOCALIZACIÓN Y ATENCIÓN DE BENEFICIARIOS.\nIII PROMOVER Y COORDINAR LA PARTICIPACIÓN COMUNITARIA EN LA OPERACIÓN DE LOS PROGRAMAS, A TRAVÉS\nDE LA FORMACIÓN DE COMITÉS Y/O GRUPOS DE DESARROLLO SEGÚN CORRESPONDA. PARA LOS PROGRAMAS\nDE ASISTENCIA ALIMENTARIA, LA FORMACIÓN DE COMITÉS SERÁ PARA LA RECEPCIÓN, PREPARACIÓN, ENTREGA\nY/O VIGILANCIA DEL CONSUMO DE LOS APOYOS ALIMENTARIOS.\nIV. IMPLEMENTAR ACCIONES DE ORIENTACIÓN Y EDUCACIÓN ALIMENTARIA, ASEGURAMIENTO DE LA CALIDAD, ASÍ\nCOMO DE ORGANIZACIÓN Y PARTICIPACIÓN COMUNITARIA.\n\"ESTE PROGRAMA ES PÚBLICO, AJENO A CUALQUIER PARTIDO POLÍTICO. QUEDA PROHIBIDO EL USO PARA FINES DISTINTOS A LOS ESTABLECIDOS EN EL PROGRAMA.\"\nARTICULO 28 NUMERAL II, FRACCIÓN A) DEL PEF 2023\nEJERCICIO FISCAL 2023.\nV. PARTICIPAR, EN COORDINACIÓN CON “EL SEDIF”, EN LA ADQUISICIÓN DE ALIMENTOS FRESCOS PARA\nCOMPLEMENTAR LOS MENÚS Y DOTACIONES.\nVI. OPERAR LOS PROGRAMAS DESCRITOS EN LA PRESENTE ESTRATEGIA, CON OBSERVANCIA Y APEGO A LAS\nREGLAS DE OPERACIÓN EMITIDAS POR “EL SEDIF” Y LO ESTABLECIDO EN EL PRESENTE CONVENIO DE\nCOLABORACIÓN FIRMADO ENTRE AMBOS\nVII. IMPULSAR LA COORDINACIÓN CON LAS INSTANCIAS CORRESPONDIENTES DEL SECTOR PÚBLICO, SOCIAL O\nPRIVADO PARA FORTALECER LA OPERACIÓN DE LOS PROGRAMAS DE LA EIASADC.\nVIII. GENERAR LOS INFORMES CORRESPONDIENTES SOBRE LA OPERACIÓN DE “EL PROGRAMA\".\nIX. INTEGRAR, ACTUALIZAR Y ENTREGAR LOS PADRONES DE BENEFICIARIOS DE “EL PROGRAMA” EN LAS FECHAS\nESTABLECIDAS POR “EL SEDIF” PARA ESTAR EN CONDICIONES DE DAR CUMPLIMIENTO A LOS TIEMPOS DEL\nCALENDARIO ENTREGA DE INFORMACIÓN ESTABLECIDOS POR EL “SNDIF”.\nX. DIFUNDIR LA EXISTENCIA DE “EL PROGRAMA”, PREFERENTEMENTE EN LAS LOCALIDADES DE ALTO Y MUY ALTO\nGRADO DE MARGINACIÓN.\nXI. EN CASO DE CONTAR CON UN ALMACÉN, ASEGURARSE QUE ESTE SEA ADECUADO Y ESTÉ DESTINADO\nEXCLUSIVAMENTE AL ALMACENAMIENTO DE INSUMOS ALIMENTARIOS.\nXII. VERIFICAR, AL MOMENTO DE LA RECEPCIÓN DE INSUMOS ALIMENTICIOS, LA FECHA DE CADUCIDAD,\nPRESENTACIÓN Y CANTIDADES DE LOS INSUMOS, DE MODO QUE CUMPLAN CON LO PROGRAMADO POR “EL\nSEDIF” Y, EN CASO DE EXISTIR ANOMALÍAS, NO RECIBIR LOS PRODUCTOS Y NOTIFICAR DE FORMA INMEDIATA A\n“EL SEDIF”.\nXIII. UNA VEZ INICIADA LA ENTREGA DE DOTACIONES ALIMENTARIAS RECOGERÁ LOS INSUMOS DE “EL PROGRAMA”,\nEN EL ALMACÉN REGIONAL QUE LE CORRESPONDA, HACIENDO ENTREGA DEL MECANISMO DE\nCORRESPONSABILIDAD Y COMPROMETIÉNDOSE A RECIBIRLOS, LOS PRIMEROS 5 DÍAS DEL MES POSTERIOR A LA\nRECEPCIÓN DE INSUMOS, “EL SMDIF” CONTARÁ CON UN PERIODO DE 10 DÍAS NATURALES PARA CUMPLIR CON\nSU CALENDARIO DE ENTREGAS A LA POBLACIÓN BENEFICIARIA, EN EL ENTENDIDO QUE DE INCUMPLIR CON ESTA\nOBLIGACIÓN SE LE CANCELARÁ EL SUMINISTRO DEL PROGRAMA A FIN DE DETERMINAR ACCIONES PARA\nREDIRIGIR ESTOS APOYOS.\nXIV. ELABORAR EL INVENTARIO DE ALMACÉN MUNICIPAL POSTERIOR A CADA ENTREGA DE INSUMOS, Y MANEJAR EN\nTODO MOMENTO EL SISTEMA DE PRIMERAS ENTRADAS, PRIMERAS SALIDAS.\nXV. PROMOVER Y VIGILAR EL CUMPLIMIENTO DE LAS REGLAS DE OPERACIÓN DE “EL PROGRAMA”, ASÍ COMO DE LOS\nLINEAMIENTOS DE LA EIASADC 2023, ENTRE LA POBLACIÓN BENEFICIARIA.\nXVI. ASISTIR A LAS CAPACITACIONES Y REUNIONES QUE CONVOQUE “EL SEDIF” CON EL OBJETO DE ANALIZAR Y\nRESOLVER PROBLEMÁTICAS QUE SE LLEGUEN A PRESENTAR EN LA EJECUCIÓN DE “EL PROGRAMA”.\nXVII. INFORMAR A “EL SEDIF” EL NÚMERO DE RACIONES Y/O APOYOS DISTRIBUIDOS POR TIPO, LOCALIDAD Y\nBENEFICIARIOS ATENDIDOS DE MANERA MENSUAL\nXVIII. DETERMINAR LA POBLACIÓN POTENCIAL EN SU MUNICIPIO DEL PROGRAMA ALIMENTARIO EN BASE A LAS\nCARACTERÍSTICAS DE LA POBLACIÓN OBJETIVO DETERMINADA POR LA EIASADC 2023.\nXIX. CONTRIBUIR AL LEVANTAMIENTO DE LOS PADRONES Y EXPEDIENTES DE BENEFICIARIOS DEL PROGRAMA\nALIMENTARIO, REENVIARLOS AL \"SEDIF” AL INICIO DEL EJERCICIO FISCAL, PARA VALIDACIÓN Y/O AUTORIZACIÓN\nDE LOS BENEFICIARIOS.\nXX. “EL SMDIF” SE COMPROMETE A INTEGRAR, RESGUARDAR LOS PADRONES Y EXPEDIENTES DE BENEFICIARIOS\nDEL PROGRAMA ALIMENTARIO, DE TODOS LOS MESES ENTREGADOS DURANTE EL PRESENTE AÑO 2023.\n\"ESTE PROGRAMA ES PÚBLICO, AJENO A CUALQUIER PARTIDO POLÍTICO. QUEDA PROHIBIDO EL USO PARA FINES DISTINTOS A LOS ESTABLECIDOS EN EL PROGRAMA.\"\nARTICULO 28 NUMERAL II, FRACCIÓN A) DEL PEF 2023\nEJERCICIO FISCAL 2023.\nSEPTIMA. - DIFUSIÓN Y DIVULGACIÓN.\n“LAS PARTES” SE COMPROMETEN A QUE LA DIFUSIÓN Y DIVULGACIÓN QUE SE REALICE POR MEDIOS IMPRESOS,\nELECTRÓNICOS, ESCRITOS, GRÁFICOS Y DE CUALQUIER OTRA ÍNDOLE INHERENTE A “EL PROGRAMA”, ASÍ COMO EL\nETIQUETADO DE LOS INSUMOS, DEBERÁ ANUNCIAR LA SIGUIENTE LEYENDA:\n\"ESTE PROGRAMA ES PÚBLICO, AJENO A CUALQUIER PARTIDO POLÍTICO. QUEDA PROHIBIDO EL USO PARA FINES\nDISTINTOS A LOS ESTABLECIDOS EN EL PROGRAMA\",\nARTICULO 28 NUMERAL II, FRACCIÓN A) DEL PRESUPUESTO DE EGRESOS DE LA FEDERACIÓN PARA EL EJERCICIO FISCAL\n2023.\nASIMISMO, CUMPLIRÁN CON LO ESTABLECIDO EN EL TOMO 2 CRITERIOS NORMATIVOS, APARTADO 7. IMAGEN GRÁFICA\nY DIFUSIÓN DE LA EIASADC 2023 Y SEÑALARÁN EXPRESAMENTE Y EN FORMA IDÉNTICA LA PARTICIPACIÓN DEL “EL SEDIF”\nY EL APOYO DEL GOBIERNO FEDERAL, A TRAVÉS DEL SISTEMA NACIONAL PARA EL DESARROLLO INTEGRAL DE LA\nFAMILIA.\nOCTAVA. - REPRESENTANTES DE LAS PARTES.\nPARA LA ADECUADA OPERACIÓN DE LAS ACTIVIDADES A QUE SE REFIERE EL PRESENTE INSTRUMENTO JURÍDICO, “LAS\nPARTES” DESIGNAN COMO SUS RESPECTIVOS REPRESENTANTES A LOS SIGUIENTES FUNCIONARIOS:\nA) POR “EL SEDIF” DIRECTORA DE ASISTENCIA ALIMENTARIA Y DESARROLLO COMUNITARIO.\nB) POR “EL SMDIF” DIRECTOR(A) DE SISTEMA MUNICIPAL DE XOCHIHUEHUETLAN, GUERRERO.\nLOS REPRESENTANTES TITULARES PODRÁN DESIGNAR SUPLENTES, QUIENES DEBERÁN CONTAR CON FACULTADES\nPARA TOMAR DECISIONES, LOS CUALES DEBERÁN TENER CUANDO MENOS, EL NIVEL JERÁRQUICO INFERIOR SIGUIENTE\nAL DEL REPRESENTANTE TITULAR, CUIDÁNDOSE QUE SEA HOMOGÉNEO Y ADECUADO PARA GARANTIZAR LA EJECUCIÓN\nDE LAS DECISIONES ADOPTADAS.\nEL CAMBIO DE RESPONSABLE SERÁ COMUNICADO A LA OTRA PARTE POR ESCRITO, PREVIO A LA FECHA QUE SE\nPRETENDA DAR EFECTO A DICHA NOTIFICACIÓN.\nNOVENA. - CONTROL Y VIGILANCIA.\nEL CONTROL Y VIGILANCIA DE LOS RECURSOS FEDERALES A QUE SE REFIERE EL PRESENTE CONVENIO,\nCORRESPONDERÁ A LOS ÓRGANOS FISCALIZADORES FEDERALES Y ESTATALES COMPETENTES, ASÍ COMO LA\nFISCALIZADORES.\nDÉCIMA. - TRANSPARENCIA\n\"ESTE PROGRAMA ES PÚBLICO, AJENO A CUALQUIER PARTIDO POLÍTICO. QUEDA PROHIBIDO EL USO PARA FINES DISTINTOS A LOS ESTABLECIDOS EN EL PROGRAMA.\"\nARTICULO 28 NUMERAL II, FRACCIÓN A) DEL PEF 2023\nEJERCICIO FISCAL 2023.\n“LAS PARTES” CONVIENEN EN PROMOVER Y FOMENTAR LA TRANSPARENCIA DE LA ASIGNACIÓN Y EJERCICIO DE LOS\nRECURSOS A QUE SE REFIERE EL PRESENTE CONVENIO. CONSECUENTEMENTE, DEBERÁN LLEVAR A CABO LA\nINTEGRACIÓN DEL PADRÓN DE PERSONAS BENEFICIARIAS, ASI COMO DAR A CONOCER SUS AVANCES FÍSICOFINANCIEROS EN LAS PÁGINAS WEB OFICIALES QUE TENGAN DISPONIBLES.\nLOS DATOS PERSONALES DE LOS BENEFICIARIOS SERÁN PROTEGIDOS EN TÉRMINOS DE LA LEY FEDERAL DE\nTRANSPARENCIA Y ACCESO A LA INFORMACIÓN PÚBLICA, LEY GENERAL DE PROTECCIÓN DE DATOS PERSONALES EN\nPOSESIÓN DE SUJETOS OBLIGADOS Y DEMÁS DISPOSICIONES JURÍDICAS APLICABLES.\nASIMISMO, “LAS PARTES” DARÁN CUMPLIMIENTO A LO ESTABLECIDO EN EL ARTÍCULO 40 DE LA LEY DE COORDINACIÓN\nFISCAL, QUE A LA LETRA DICE:\n\"LAS ENTIDADES TENDRÁN LA OBLIGACIÓN DE HACER DEL CONOCIMIENTO DE SUS HABITANTES, LOS MONTOS QUE\nRECIBAN, LAS OBRAS Y ACCIONES REALIZADAS, EL COSTO DE CADA UNA, SU UBICACIÓN Y BENEFICIARIOS. ASIMISMO,\nDEBERÁN INFORMAR A SUS HABITANTES, AL TÉRMINO DE CADA EJERCICIO, SOBRE LOS RESULTADOS ALCANZADOS\".\nDÉCIMO PRIMERA. - RELACIÓN LABORAL.\nEL PERSONAL DE CADA UNA DE “LAS PARTES” QUE SEA DESIGNADO PARA LA REALIZACIÓN DE CUALQUIER ACTIVIDAD\nRELACIONADA CON ESTE CONVENIO, PERMANECERÁ EN FORMA ABSOLUTA BAJO LA DIRECCIÓN Y DEPENDENCIA DE LA\nPARTE CON LA CUAL TIENE ESTABLECIDA SU RELACIÓN LABORAL, MERCANTIL, CIVIL, ADMINISTRATIVA O CUALQUIER\nOTRA, POR LO QUE NO SE CREARÁ UNA SUBORDINACIÓN DE NINGUNA ESPECIE CON LA PARTE OPUESTA, NI OPERARÁ\nLA FIGURA JURÍDICA DE PATRÓN SUSTITUTO O SOLIDARIO; LO ANTERIOR, CON INDEPENDENCIA DE ESTAR PRESTANDO\nSUS SERVICIOS FUERA DE LAS INSTALACIONES DE LA ENTIDAD POR LA QUE FUE CONTRATADA O REALIZAR LABORES\nDE SUPERVISIÓN DE LOS TRABAJOS QUE SE REALICEN.\nDÉCIMO SEGUNDA. - MODIFICACIONES.\nEL PRESENTE CONVENIO PODRÁ SER MODIFICADO DURANTE SU VIGENCIA, PREVIO ACUERDO DE “LAS PARTES”. LAS\nMODIFICACIONES O ADICIONES SE HARÁN CONSTAR POR ESCRITO, SURTIENDO SUS EFECTOS A PARTIR DEL MOMENTO\nDE SU SUSCRIPCIÓN\nDÉCIMO TERCERA. - VIGENCIA.\nCON BASE AL PRINCIPIO DE ANUALIDAD PRESUPUESTARIA.\nEL INSTRUMENTO PODRÁ DARSE POR TERMINADO CUANDO ASÍ LO DETERMINEN “LAS PARTES” POR MUTUO ACUERDO\nO CUANDO UNA DE ELLAS SE LO COMUNIQUE A LA OTRA MEDIANTE ESCRITO, CON TREINTA DÍAS NATURALES DE\nANTICIPACIÓN, EN EL ENTENDIDO DE QUE LAS ACTIVIDADES QUE SE ENCUENTREN EN EJECUCIÓN DEBERÁN SER\nCONCLUIDAS, SALVO ACUERDO CONTRARIO.\nDÉCIMO CUARTA. - DE LA ADQUISICIÓN Y DISTRIBUCIÓN DE LOS INSUMOS.\n\"ESTE PROGRAMA ES PÚBLICO, AJENO A CUALQUIER PARTIDO POLÍTICO. QUEDA PROHIBIDO EL USO PARA FINES DISTINTOS A LOS ESTABLECIDOS EN EL PROGRAMA.\"\nARTICULO 28 NUMERAL II, FRACCIÓN A) DEL PEF 2023\nEJERCICIO FISCAL 2023.\n“EL SEDIF” DEBERÁ CONSIDERAR LOS CRITERIOS DE CALIDAD NUTRICIA, REGULANDO LA CONFORMACIÓN DE MENÚS Y\nDOTACIONES, DE MANERA QUE SIRVAN PARA UNA ALIMENTACIÓN CORRECTA. LOS CUALES ESTÁN BASADOS EN LAS\nCARACTERISTICAS DE UNA DIETA CORRECTA, DE ACUERDO A LA NORMA OFICIAL MEXICANA NOM-043-SSA2-2012,\nSERVICIOS BÁSICOS DE SALUD, PROMOCIÓN Y EDUCACIÓN PARA LA SALUD EN MATERIA ALIMENTARIA, CRITERIOS PARA\nBRINDAR ORIENTACIÓN Y EN LAS DISPOSICIONES ESTABLECIDAS EN LOS \"LINEAMIENTOS GENERALES PARA EL\nEXPENDIO O DISTRIBUCIÓN DE ALIMENTOS Y BEBIDAS EN LOS ESTABLECIMIENTOS DE CONSUMO ESCOLAR DE LOS\nPLANTELES DE EDUCACIÓN BÁSICA\" EMITIDAS POR LA SECRETARIA DE EDUCACIÓN PÚBLICA Y LA SECRETARÍA DE\nSALUD.\n“EL SEDIF”, DEBERÁ CALCULAR LA CANTIDAD TOTAL DE LOS INSUMOS QUE SE VAN A ENTREGAR A CADA BENEFICIARIO\nPOR CADA PROGRAMA ALIMENTARIO DE ACUERDO CON EL NÚMERO DE DÍAS QUE SE BRINDARÁ EL APOYO, Y EL TIPO\nDE POBLACIÓN A QUIENES VAN DIRIGIDOS, DE ACUERDO CON LOS CÁLCULOS Y LAS RACIONES SUGERIDAS EN EL ANEXO\nT3 B DE LA EIASADC 2023.\nASÍ MISMO “EL SEDIF” PODRÁ HACER ENTREGA DE INSUMOS ALIMENTARIOS TEMPORALES, DISEÑADOS CON BASE EN\nCRITERIOS DE ORIENTACIÓN ALIMENTARIA Y ASEGURAMIENTO DE LA CALIDAD, EN SUS DISTINTAS MODALIDADES, A LAS\nPERSONAS QUE POR SUS CONDICIONES DE VULNERABILIDAD, REQUIEREN APOYO INSTITUCIONAL PARA\nENFRENTARLOS, “EL SEDIF” SE RESERVARA EL DERECHO DE OTORGAR LOS INSUMOS EN EL TIEMPO Y FORMA QUE\nCONSIDERE NECESARIOS PARA ELLO, SIN AFECTAR EL SUMINISTRO DE INSUMOS ALIMENTARIOS DE LOS MUNICIPIOS\nQUE SE ENCUENTRAN INSCRITOS EN LOS PROGRAMAS DE ESTRATEGIA INTEGRAL DE ASISTENCIA SOCIAL ALIMENTARIA\nY DESARROLLO COMUNITARIO (EIASADC) 2023.\nDÉCIMO QUINTA. - DE LOS MECANISMOS DE ENTREGA DE APOYOS\n“EL SMDIF” DEBERÁ ASIGNAR UN LUGAR QUE ESTÉ LIMPIO, EVITAR COLOCAR LAS DOTACIONES EN EL SUELO Y\nMANTENER EL ORDEN EN TODO MOMENTO; ASIMISMO DEBERÁ ESTIBARSE DE MANERA TAL, QUE NO SE MALTRATEN O\nPROVOQUEN UN ACCIDENTE.\n“LAS PARTES” FOMENTARAN ACCIONES QUE CONTRIBUYAN A CREAR HÁBITOS DE HIGIENE ENTRE EL PERSONAL\nOPERATIVO DEL PROGRAMA, TALES COMO, EL CORRECTO MANEJO DE INSUMOS, LA LIMPIEZA DE LAS UNIDADES\nVEHICULARES QUE TRANSPORTAN EL INSUMO.\nEN CUANTO A LAS DOTACIONES O RACIONES CONSUMIDAS POR LOS BENEFICIARIOS, “LAS PARTES” DEBERÁN TENER\nCORRESPONSABILIDAD EN LOS INVOLUCRADOS EN ESTA ETAPA, PARA FOMENTAR ACCIONES QUE CONTRIBUYAN A\nCREAR HÁBITOS DE HIGIENE EN LA COMUNIDAD, TALES COMO LAVADO DE MANOS, ANTES DE CONSUMIRLOS Y DESPUÉS\nDE IR AL BAÑO, ADEMÁS DEL CORRECTO MANEJO DE LOS INSUMOS. SE IMPULSARÁ A TRAVÉS DE PLÁTICAS,\nCAPACITACIONES O MATERIAL IMPRESO, PRÁCTICAS DE HIGIENE EN LA PREPARACIÓN Y CONSUMO DE ALIMENTOS, ASÍ\nCOMO INFORMAR SOBRE EL RIESGO QUE IMPLICA PARA SU SALUD, NO LLEVARLAS A CABO\nLOS SEDIF AL LLEVAR A CABO LA ENTREGA DE APOYOS ALIMENTARIOS, A TRAVÉS DE LA OPERACIÓN DE LOS\nPROGRAMAS DE LA EIASADC, BAJO LA PREMISA DE COADYUVAR A LA SEGURIDAD ALIMENTARIA, DEBEN APLICAR\nACCIONES DE ASEGURAMIENTO DE LA CALIDAD, QUE PRIVILEGIEN LA PREVENCIÓN Y ASEGUREN LA CALIDAD,\nAPOYOS ALIMENTARIOS.\n\"ESTE PROGRAMA ES PÚBLICO, AJENO A CUALQUIER PARTIDO POLÍTICO. QUEDA PROHIBIDO EL USO PARA FINES DISTINTOS A LOS ESTABLECIDOS EN EL PROGRAMA.\"\nARTICULO 28 NUMERAL II, FRACCIÓN A) DEL PEF 2023\nEJERCICIO FISCAL 2023.\nESTO REQUIERE TAMBIÉN DE LA CORRESPONSABILIDAD DE TODOS AQUELLOS AGENTES QUE, ADEMÁS DEL SEDIF,\nINTERVIENEN DE MANERA DIRECTA E INDIRECTA EN CADA UNA DE LAS ETAPAS DE LA CADENA ALIMENTARIA (SMDIF,\nPRODUCTORES LOCALES, PROVEEDORES, BENEFICIARIOS), PARA LO CUAL ES NECESARIO DEFINIR CON CLARIDAD LAS\nRESPONSABILIDADES QUE CORRESPONDEN A CADA UNO, DE ACUERDO CON EL ÁMBITO DE SU COMPETENCIA.\nDÉCIMO SEXTA. - DE LOS MECANISMOS DE CORRESPONSABILIDAD\n“LAS PARTES”, TENDRÁN CORRESPONSABILIDAD YA QUE INTERVIENEN DE MANERA DIRECTA E INDIRECTAMENTE EN\nCADA UNA DE LAS ETAPAS DE LA CADENA ALIMENTARIA, PARA LO CUAL SE DEFINIRÁ CON CLARIDAD LAS\nRESPONSABILIDADES QUE LE CORRESPONDEN A CADA UNO DE ACUERDO CON EL ÁMBITO DE SU COMPETENCIA.\n“EL SMDIF” ACUERDA RECOGER EN TIEMPO Y FORMA LOS INSUMOS ALIMENTARIOS EN LAS BODEGAS REGIONALES QUE\nLES CORRESPONDAN, PRESENTANDO IDENTIFICACION OFICIAL DEL REPRESENTANTE DEL SMDIF Y COMPROBANTE DE\nDEPOSITO DEL MECANISMO DE CORRESPONSABILIDAD DE “EL PROGRAMA” EL CUAL SERÁ DE S150.0P0 (CIENTO\nCINCUENTA PESOS 00/100 M.N.) POR MÓDULO/DESPENSA. EXCEPTUANDO LOS MUNICIPIOS DE MUY ALTO GRADO DE\nMARGINACIÓN DE NUESTRO ESTADO DE GUERRERO, Y AQUELLOS QUE QUIENES RECIBIRÁN SUS DOTACIONES\nALIMENTARIAS DONADAS, OBLIGANDOSE PERTENEZCAN A LA ZONA MONTAÑA, QUIENES RECIBIRAN SU DOTACIONES\nALIMENTARIAS DONADAS, ENTREGANDOLAS A LOS BENEFICIARIOS EN LAS MISMAS CONDICIONES DE GRATUIDAD\n“LAS PARTES” ACUERDAN RESPETAR LOS PLAZOS DE ENTREGA DE LOS APOYOS EN SUS DISTINTAS MODALIDADES.\nQUE EN CASO DE QUE “EL SMDIF\" NO ACUDA A RECIBIR SUS DOTACIONES EN TIEMPO Y FORMA DE “EL PROGRAMA”,\n“EL SEDIF\" SE RESERVA EL DERECHO DE RESGUARDAR LOS PRODUCTOS PARA OTORGARLOS COMO APOYOS\nEXTRAORDINARIOS (EVENTOS ESPECIALES, DESASTRES NATURALES, ETC).\nEN EL CASO DE LOS COMEDORES ESCOLARES EL COMITÉ DE PADRES DE FAMILIA DE LA COCINA ESCOLAR, ACORDARÁ\nEL MECANISMO DE CORRESPONSABILIDAD A OPERAR EN “EL PROGRAMA” Y LOS CASOS DE EXCEPCIÓN. LA UTILIZACIÓN\nDE LOS RECURSOS OBTENIDOS SERÁ PARA EL FORTALECIMIENTO DE “EL PROGRAMA” Y LA ADQUISICIÓN DE LOS\nPRODUCTOS PERECEDEROS QUE COMPLEMENTARÁN LOS MENÚS, DANDO PREFERENCIA A FRUTAS Y VERDURAS\nFRESCAS, ADEMÁS DE OTROS GASTOS DE OPERACIÓN. ASIMISMO, DE TODOS LOS ACUERDOS QUE SE TOMEN, SE\nSUGIERE LLEVAR UNA BITÁCORA DONDE SE REGISTRE LA CONTRAPRESTACIÓN, QUEDANDO ASENTADOS EN MINUTA\nFIRMADA POR PARTE DE LOS PADRES DE FAMILIA, A FIN DE TRASPARENTAR DICHAS APORTACIONES.\nDÉCIMO SÉPTIMA. - DE LAS SANCIONES.\n“LAS PARTES” ACUERDAN QUE EN CASO DE SUSCITARSE ALGÚN CONFLICTO O CONTROVERSIA LO RESOLVERÁN DE\nACUERDO CON LA CLÁUSULA VIGÉSIMA DEL PRESENTE CONVENIO.\nADEMÁS DE LO ESTABLECIDO EN EL PÁRRAFO ANTERIOR, “LAS PARTES” TENDRÁN RESPONSABILIDAD DE HACER DEL\nCONOCIMIENTO DE LAS AUTORIDADES COMPETENTES, CUALQUIER FALTA ADMINISTRATIVA, ACTO DE CORRUPCIÓN O\nCOMISIÓN DE DELITO ALGUNO, POR PARTE DE CUALQUIER DE LOS SERVIDORES PÚBLICOS RELACIONADOS CON LA\nOPERACIÓN DE “EL PROGRAMA”.\n\"ESTE PROGRAMA ES PÚBLICO, AJENO A CUALQUIER PARTIDO POLÍTICO. QUEDA PROHIBIDO EL USO PARA FINES DISTINTOS A LOS ESTABLECIDOS EN EL PROGRAMA.\"\nARTICULO 28 NUMERAL II, FRACCIÓN A) DEL PEF 2023\nEJERCICIO FISCAL 2023.\nDÉCIMO OCTAVA. - CONFIDENCIALIDAD\n“LAS PARTES” GUARDARÁN CONFIDENCIALIDAD ESTRICTA RESPECTO DE LA INFORMACIÓN CLASIFICADA COMO\nPÚBLICA, LA LEY GENERAL DE PROTECCIÓN DE DATOS PERSONALES EN POSESIÓN DE SUJETOS OBLIGADOS Y DEMÁS\nDISPOSICIONES APLICABLES A LA MATERIA, SALVO QUE SE CUENTE CON LA PREVIA AUTORIZACIÓN ESCRITA DE QUIEN\nSEA RESPONSABLE DE DICHA INFORMACIÓN, DEBIENDO ASEGURARSE QUE LA QUE SE PROPORCIONE POR EL\nPERSONAL QUE CADA UNA DESIGNE SEA MANEJADA BAJO ESTRICTA CONFIDENCIALIDAD.\nLAS OBLIGACIONES CONTEMPLADAS EN EL PÁRRAFO ANTERIOR, PERMANECERÁN VIGENTES Y SERÁN EXIGIBLES EN EL\nSUPUESTO DE QUE “LAS PARTES” DIERAN POR TERMINADO EL PRESENTE INSTRUMENTO JURÍDICO.\nDÉCIMO NOVENA. - PUBLICIDAD DE LOS RESULTADOS\n“LAS PARTES” POR LOS MEDIOS DE DIFUSIÓN MÁS CONVENIENTES, PROMOVERÁN Y DIVULGARÁN ENTRE LAS\nPERSONAS PROMOTORAS, EJECUTORAS E INTERESADAS EN GENERAL, LAS CARACTERÍSTICAS, ALCANCES Y\nRESULTADOS DE LA COLABORACIÓN PREVISTA EN EL PRESENTE CONVENIO, DE ACUERDO CON LA CLÁUSULA DÉCIMA \"TRANSPARENCIA\" DE ESTE INSTRUMENTO.\nVIGÉSIMA. - COMPETENCIA.\nDEL PRESENTE CONVENIO, “LAS PARTES” LO RESOLVERÁN DE COMÚN ACUERDO, DE NO LOGRARLO, ACUERDAN\nGUERRERO, CON CEDE EN ESTA CIUDAD DE CHILPANCINGO DE LOS BRAVO, RENUNCIANDO DESDE ESTE MOMENTO AL\nFUERO QUE LES PUDIERA CORRESPONDER EN RAZÓN DE SU DOMICILIO PRESENTE O FUTURO, O POR CUALQUIER\nCAUSA.\n\"ESTE PROGRAMA ES PÚBLICO, AJENO A CUALQUIER PARTIDO POLÍTICO. QUEDA PROHIBIDO EL USO PARA FINES DISTINTOS A LOS ESTABLECIDOS EN EL PROGRAMA.\"\nARTICULO 28 NUMERAL II, FRACCIÓN A) DEL PEF 2023\nEJERCICIO FISCAL 2023.\nENTERADAS “LAS PARTES” DEL CONTENIDO Y ALCANCE LEGAL DEL CONVENIO, LO FIRMAN EN CHILPANCINGO DE LOS\nBRAVO, CAPITAL DEL ESTADO DE GUERRERO, A LOS__________________________DÍAS DEL MES DE___________DEL DOS\nMIL VEINTITRES.\n{\"tabla_2\":{\"columnas\":[\"POR EL SISTEMA PARA EL DESARROLLO INTEGRAL DE\\nLA FAMILIA DEL ESTADO DE GUERRERO\",\"POR EL AYUNTAMIENTO\"],\"filas\":[{\"columna_1\":\"__________________________________________________\\nC. ANTELMO MAGDALENO SOLIS\\nDIRECTOR GENERAL DIF GUERRERO\",\"columna_2\":\"__________________________________________________\\nC. ROSEMBERT PONCIANO VENEGAS\\nPRESIDENTE(A) MUNICIPAL\\nCONSTITUCIONAL\"},{\"columna_1\":\"__________________________________________________\\nC. MARGARITA DE JESÚS RAMÍREZ SALGADO\\nDIRECTORA DE ASISTENCIA ALIMENTARIA Y\\nDESARROLLO\\nCOMUNITARIO\",\"columna_2\":\"__________________________________________________\\nC. GUADALUPE RIVERA PÉREZ\\nDIRECTOR(A) DEL SISTEMA MUNICIPAL DIF\"},{\"columna_1\":\"TESTIGOS DE HONOR\",\"columna_2\":\"(sin dato)\"},{\"columna_1\":\"___________________________________________________\\nC. LIZ ADRIANA SALGADO PINEDA\\nPRESIDENTA DEL PATRONATO DIF\\nGUERRERO\",\"columna_2\":\"________________________________________________\\nC. TERESA RIVERA PÉREZ\\nPRESIDENTE(A) DEL SISTEMA MUNICIPAL\\nDIF\"}]}}\n\"ESTE PROGRAMA ES PÚBLICO, AJENO A CUALQUIER PARTIDO POLÍTICO. QUEDA PROHIBIDO EL USO PARA FINES DISTINTOS A LOS ESTABLECIDOS EN EL PROGRAMA.\"\nARTICULO 28 NUMERAL II, FRACCIÓN A) DEL PEF 2023\nEJERCICIO FISCAL 2023.\nPrimero. El presente Acuerdo entrará en vigor al día siguiente de su publicación en el Periódico\nSegundo. Se abroga el Acuerdo por el que se emiten las Reglas de Operación del Programa\nDesayunos Escolares Calientes para el Ejercicio Fiscal 2022, publicado en el Periódico Oficial del Gobierno del Estado de Guerrero, No. 42 alcance II de fecha\n27 de mayo de 2022.\nDado en el “Recinto de las Oficinas del Poder Ejecutivo del Estado” el inmueble ubicado en el número 62 Edificio Norte Planta Baja, en el Boulevard René Juárez Cisneros, Código Postal 39074, Colonia\nCiudad de los Servicios, en Chilpancingo de los Bravo, Capital del estado de Guerrero, a los nueve días del mes de marzo de dos mil veintitrés.\nLA GOBERNADORA CONSTITUCIONAL DEL ESTADO DE GUERRERO.\nMTRA. EVELYN CECIA SALGADO PINEDA.\nRúbrica.\nEL SECRETARIO GENERAL DE GOBIERNO.\nMTRO. LUDWIG MARCIAL REYNOSO NUÑEZ.\nRúbrica.\nLA FAMILIA DEL ESTADO DE GUERRERO.\nLIC. ANTELMO MAGDALENO SOLÍS.\nRúbrica.",
  "ordenamiento": "PROGRAMA",
  "jurisdiccion": "GUERRERO",
  "fuente_oficial": "DIARIO OFICIAL DE LA FEDERACION",
  "Fecha de Publicación": "26 DE MARZO DE 2024",
  "ULTIMA REFORMA PUBLICADA": null,
  "status": "VIGENTE",
  "es_escaneado": false,
  "tiene_tablas": true,
  "materia": [
    "educación",
    "alimentación"
  ]
}