{
  "titulo": "Acuerdo por el Que Se Crea el Programa Becas Deportivas, y Se Emiten Sus Reglas de Operación",
  "Contenido": "TEXTO ORIGINAL.\nPoder Ejecutivo.\nMAESTRA EVELYN CECIA SALGADO PINEDA, GOBERNADORA CONSTITUCIONAL DEL ESTADO\nDE GUERRERO, CON FUNDAMENTO EN LO DISPUESTO POR LOS ARTÍCULOS 4o PÁRRAFO\nDÉCIMO TERCERO DE LA CONSTITUCIÓN POLÍTICA DE LOS ESTADOS UNIDOS MEXICANOS; 1 Y\n6 DE LA LEY GENERAL DE CULTURA FÍSICA Y DEPORTE; 71, 87, 88, 90 NUMERAL 2 Y 91\nGUERRERO, Y EN EL EJERCICIO DE LAS FACULTADES QUE ME CONFIEREN LOS ARTÍCULOS 1,\n2, 4, 8, 9, 16, 22 APARTADO A FRACCIÓN I, 23 FRACCIÓN III Y 46 DE LA LEY ORGÁNICA DE LA\nADMINISTRACIÓN PÚBLICA DEL ESTADO DE GUERRERO NÚMERO 242; 1, 2 FRACCIÓN I, 18 Y 25\nDE LA LEY NÚMERO 454 DE PRESUPUESTO Y DISCIPLINA FISCAL DEL ESTADO DE GUERRERO;\nEN RELACIÓN CON LOS ARTÍCULOS 1o, 2o, 3o, 4o INCISO a), 27, 28 Y 29 DE LA LEY NÚMERO 697\nDE CULTURA FÍSICA Y DEPORTE PARA EL ESTADO Y LOS MUNICIPIOS DE GUERRERO; 1o, 2o Y\n7o DEL DECRETO NÚM. 437, POR EL QUE SE CREA EL ORGANISMO PÚBLICO\nDESCENTRALIZADO “INSTITUTO DEL DEPORTE DE GUERRERO”; 47 Y ANEXOS 23 (P34) Y 23-A\nDEL DECRETO NÚMERO 424 DEL PRESUPUESTO DE EGRESOS DEL ESTADO DE GUERRERO\nPARA EL EJERCICIO FISCAL 2023 Y LOS LINEAMIENTOS PARA LA ELABORACIÓN DE LAS\nREGLAS DE OPERACIÓN DE LOS PROGRAMAS SOCIALES ESTATALES PARA EL PERIODO 2022-\n2027.\nQue el artículo 4o de la Constitución Política de los Estados Unidos Mexicanos, establece que toda persona tiene derecho a la cultura física y a la práctica del deporte. Corresponde al Estado su promoción, fomento y estímulo conforme a las leyes en la materia.\nQue el Plan Estatal de Desarrollo 2022-2027 Eje: Bienestar, Desarrollo Humano y Justicia Social. Objetivo\n1.15. Fomentar en la población de la entidad la práctica regular del deporte, la activación física y recreativa de manera sistemática e incluyente para el logro de un estilo, Estrategia 1.15.3. Fomentar el deporte de alto rendimiento para apoyar a los talentos deportivos. Línea de Acción 1.15.3.3. Ampliar el número de becas para atletas de alto rendimiento y talentos deportivos.\nQue uno de los compromisos de la titular del ejecutivo estatal con la ciudadanía guerrerense, al asumir y tomar protesta como Gobernadora Constitucional del Estado elevar, por medio de la activación física, la cultura física y el deporte, el nivel de vida social y cultural de los habitantes de Guerrero. canalizar su energía, por lo que debe ser accesible para toda la población del estado, de tal manera que beneficie, mediante la promoción y el fomento de la cultura física y el deporte, una amplia y activa condiciones de salud y bienestar físico.\nQue en la Ley Número 697 de Cultura Física y Deporte para el Estado y los Municipios de Guerrero, reglamenta el derecho a la cultura física y el deporte reconocido en la Constitución Política de los Estados\nUnidos Mexicanos y en los instrumentos internacionales de los que el Estado Mexicano es parte, correspondiendo su aplicación en forma concurrente al Ejecutivo Estatal, por conducto del Instituto del\nDeporte de Guerrero (INDEG) y las autoridades municipales, así como los sectores social y privado, en los términos que se prevén.\nQue por Decreto Núm. 437, se creó el Organismo Público Descentralizado “Instituto del Deporte de\nGuerrero”, con personalidad jurídica y patrimonio propios, con el objeto de promocionar y fomentar el deporte y la cultura física en congruencia con el Sistema Nacional del Deporte y los planes y programas establecidos por el Gobierno Federal.\nQue derivado del Decreto Número 424 del Presupuesto de Egresos del Estado de Guerrero para el Ejercicio\nFiscal 2023, publicado en el Periódico Oficial del Gobierno del Estado de Guerrero No. 103 de fecha 27 de diciembre, se establece el Programa Becas Deportivas 2023, mismas que se encuentran presupuestadas en el anexo 23-A, a efecto de crear las condiciones que permitan la participación de la juventud en el desarrollo integral del estado, como factores de modernización y mejoramiento de las condiciones de vida de los guerrerenses, programa que será ejecutado por el organismo público descentralizado “Instituto del\nDeporte de Guerrero”.\nQue el mencionado Decreto Número 424, señala que se ejercitarán los recursos bajo una política de gasto público, que permita dar cumplimiento a lo que globalmente prevén las dimensiones, ejes temáticos, objetivos, estrategias y líneas de acción del Plan Estatal de Desarrollo 2022-2027 orientados a los sectores, municipios y comunidades del estado.\nQue el artículo 47 del multicitado Decreto Número 424, establece que con el objeto de asegurar la aplicación eficiente, eficaz, oportuna, equitativa y transparente de los recursos públicos la Secretaría de\nFinanzas y Administración, y la Secretaría de Planeación y Desarrollo Regional, emitirán las disposiciones a que deberán sujetarse los Programas de Inversión sujetos a Reglas de Operación.\nQue la Secretaría de Planeación y Desarrollo Regional, expidió los Lineamientos para la elaboración de las\nReglas de Operación de los Programas Sociales Estatales para el periodo 2022-2027, publicados en el instrumento técnico que guie la elaboración de los apartados centrales de las reglas de operación, así como los elementos para integrar su contenido.\nQue el Instituto del Deporte de Guerrero entre otras atribuciones tiene diseñar y aplicar las políticas, instrumentos y programas para la cultura física y el deporte en la entidad, en concordancia con la Política\nNacional y Estatal de Cultura Física y Deporte, vinculándolos con los programas sectorial e institucional nacionales en la materia, así como con los Planes Nacional y Estatal de Desarrollo.\nQue el Programa Becas Deportivas, y la emisión de sus reglas de operación es con el objeto de otorgar transparencia y asegurar la aplicación eficiente, eficaz, oportuna y equitativa de los recursos públicos asignados al mismo.\nPor lo anteriormente expuesto y con fundamento en las disposiciones legales antes citadas, he tenido a bien expedir el siguiente:\nACUERDO POR EL QUE SE CREA EL PROGRAMA BECAS DEPORTIVAS, Y SE EMITEN SUS\nREGLAS DE OPERACIÓN.\nArtículo 1. Se crea el Programa Becas Deportivas, el cual tiene por objeto establecer las condiciones que permitan la participación de la juventud en el desarrollo integral del estado, como factores de modernización y mejoramiento de las condiciones de vida de los guerrerenses.\nArtículo 2. El Instituto del Deporte de Guerrero, tendrá a cargo la implementación, operación, ejecución, evaluación y administración del Programa, bajo los criterios de objetividad, equidad, transparencia, publicidad, selectividad y temporalidad, con estricto apego a la normatividad aplicable, por lo tanto, será el encargado de la asignación de los recursos del Programa apegándose plenamente a las Reglas de\nOperación.\nArtículo 3. Se emiten las Reglas de Operación del Programa Becas Deportivas, en las cuales se establece el procedimiento de ejecución del Programa, los principios y requisitos que se deben observar para acceder al mismo en los términos siguientes:\nREGLAS DE OPERACIÓN DEL PROGRAMA BECAS DEPORTIVAS.\n1. Introducción.\n1.1. Antecedentes.\nFiscal 1999, referente a los Programas en Materia de Educación Física y Deporte de la Secretaría de\nDeporte de Guerrero, busca fortalecer el nivel competitivo del deporte de excelencia en el estado, preparación y competencia de las selecciones nacionales juvenil, mayor y de deporte adaptado y otorgando resultados deportivos.\n2. Alineación Programática al PED y/o PND.\nEl Programa de Becas Deportivas, constituye una parte fundamental para dar cumplimiento con los objetivos en el Plan Nacional y Plan Estatal de Desarrollo vigentes, por lo tanto, se define en este apartado dicha alineación para su análisis del Programa Social: Eje: Bienestar, Desarrollo Humano y Justicia Social.\nObjetivo 1.15. Fomentar en la población de la entidad la práctica regular del deporte, la activación física y recreativa de manera sistemática e incluyente para el logro de un estilo. Estrategia 1.15.3. Fomentar el deporte de alto rendimiento para apoyar a los talentos deportivos. Línea de Acción 1.15.3.3. Ampliar el número de becas para atletas de alto rendimiento y talentos deportivos.\n2.1. Diagnóstico.\nEl estado de Guerrero presenta un considerable atraso en distintos rubros que afectan a los jóvenes deportistas y entrenadores deportivos, donde se han manifestado los problemas más frecuentes en décadas pasadas como falta de apoyo gubernamental, los pocos espacios adecuados para entrenar, falta de entrenadores certificados. En la actualidad los deportistas no cuentan con un apoyo como son becas deportivas, lo que representa poco interés en los adolescentes que representan al estado.\nPor otra parte, la CONADE otorgaba 5 becas para atletas de Alto Rendimiento, mientras que otros estados ofertaban mejores condiciones y apoyos para dichos deportistas, lo cual tiene como efecto, la fuga de deportistas prospecto y de Alto Rendimiento.\n2.1.1. Población Potencial.\nSon las niñas, niños y jóvenes entre 10 a 23 años, así como entrenadores deportivos (sin importar edad para éstos últimos).\n2.1.2. Población Objetivo.\nNiñas, niños y jóvenes entre 10 a 23 años que participen en los programas: juegos Nacionales CONADE, Juegos Nacionales Populares, eventos deportivos para deportistas con discapacidad o paranacionales, Competencias Internacionales que obtengan medallas, ya sean de Oro, Bronce o Plata, que sean Atletas destacados, Talentos, de Alto Rendimiento y Entrenadores, estos últimos sin rango de edad), con base a los requisitos establecidos, en el presente documento o en las convocatorias emitidas y publicadas en las\n2.1.3. Población Beneficiaria.\nLa población beneficiaria para el año 2023, es el otorgamiento de 100 a 112 becas para este ciclo comprendido por pago mensual a las beneficiarias y beneficiarios, niñas y niños, adolescentes, entrenadores deportivos, ubicados en los diferentes municipios del estado, incluyendo localidades o AGEB\n(Área Geoestadística Básica) rurales, urbanas o indígenas de alto y muy alto grado de marginación.\n2.1.4. Población Indígena.\nPara este rubro, es necesario dejar claro que los requisitos para las y los deportistas participantes en cuestión de becas deportivas por cualquier tipo de beca, existe libertad alguna para solicitarla, siempre y cuando se cumplan con los requisitos establecidos dentro de las convocatorias, al mismo tiempo, existe inclusión de género en relación a dicho apartado.\n2.2. Fundamento Legal.\na) Constitución Política de los Estados Unidos Mexicanos;\nb) Ley General de Cultura Física y Deporte;\nd) Ley Orgánica de la Administración Pública del Estado de Guerrero Número 242;\ne) Ley Número 697 de Cultura Física para el Estado y los Municipios de Guerrero;\nf) Decreto Número 437 por el que se crea el Organismo Público Descentralizado “Instituto del Deporte de\nGuerrero”;\ng) Decreto Número 424 del Presupuesto de Egresos del Estado de Guerrero para el Ejercicio Fiscal 2023;\nh) Ley Número 207 de Transparencia y Acceso a la Información Pública del Estado de Guerrero;\ni) Decreto Número 181 por medio del cual la Sexagésima Tercera Legislatura al Honorable Congreso del\nj) Ley Número 454 de Presupuesto y Disciplina Fiscal del Estado de Guerrero;\nk) Lineamientos para la Elaboración de las Reglas de Operación de los Programas Sociales Estatales 20222027, y\nl) Todos aquellos ordenamientos normativos que sean aplicables.\n2.3. Definiciones de Siglas.\nDefiniciones:\nInstituto: El Organismo Público Descentralizado “Instituto del Deporte de Guerrero”.\nPrograma: El Programa Becas Deportivas.\nReglas de Operación: Conjunto de disposiciones que precisan la forma de operar un programa, con el propósito de transparentar y normar la distribución y entrega de los apoyos.\nSiglas:\nCONADE: Comisión Nacional de Cultura Física y Deporte.\nINDEG: Instituto del Deporte de Guerrero.\nI.E.D: Inversión Estatal Directa.\nJNP: Juegos Nacionales Populares.\nMIR: Matriz de Indicadores para Resultados.\nMML: Metodología de Marco Lógico.\nSCyTG: Secretaría de Contraloría y Transparencia Gubernamental.\nSEFINA: Secretaría de Finanzas y Administración.\nSEPLADER: Secretaría de Planeación y Desarrollo Regional.\n3. Objetivos y Alcances.\nEl Instituto ha implementado un programa de apoyo económico que busca beneficiar a todas aquellas personas atletas que cuenten con un alto rendimiento, además de resultados sobresalientes tanto a nivel estatal, nacional e internacional.\n3.1. Objetivo General.\nEste Programa tiene como principal objetivo proporcionar apoyos económicos a las personas atletas con mayor desempeño de las disciplinas integradas en los Juegos Nacionales CONADE, Juegos Nacionales\nPopulares y Atletas destacados o de Alto Rendimiento, de acuerdo a los resultados deportivos alcanzados.\nEn relación a la valoración realizada por el Área Técnica de este Instituto, a través de la Dirección de\nDesarrollo del Deporte, este resultado es comprendido de 11 a 12 meses. Dicho apoyo tendrá cobertura en las 8 regiones del estado, dependiendo del total de becas a otorgar, tomando como referencia el año inmediato anterior.\n3.2. Objetivo Específico.\nOtorgar Becas Deportivas a través del presente Programa para deportistas de Alto Rendimiento, así como para deportistas en proceso de desarrollo y entrenadoras o entrenadores, con la finalidad de incrementar el nivel competitivo en las justas deportivas.\n3.3. Cobertura.\nLa convocatoria será abierta a toda la población deportiva, siempre y cuando cumplan con los requisitos solicitados en los tiempos establecidos.\nTendrá cobertura en las 8 regiones del estado, donde podrán participar en el proceso de selección las siguientes categorías: deportistas mujeres y hombres, entrenadoras y entrenadores, así como personas con capacidades diferentes que cumplan con todos los requisitos.\n3.4. Alcances.\nEl alcance de dicho Programa será de transferencias monetarias ya que se les dará apoyo económico a las personas atletas como incentivo de seguir practicando el deporte. Este será un apoyo de tipo económico otorgado de forma periódica a deportistas de Alto Rendimiento, en Desarrollo y en Formación, que hayan obtenido resultados vigentes destacados en eventos nacionales e internacionales. Así como a entrenadoras o entrenadores, que coadyuvan en la preparación de los deportistas, tomando en cuenta el año inmediato anterior.\n4. Metas Físicas.\nPara cumplir con las metas físicas, será necesario tomar en cuenta el año inmediato anterior y por tratarse de un programa social de nueva creación, la base anterior es de cero, lo que permitirá medir de manera cuantitativa el objetivo establecido por la cantidad de apoyos en bacas para 112 beneficiarias y beneficiarios aproximadamente, en pro del crecimiento deportivo en Guerrero.\n5. Programación Presupuestal.\nDentro de la política del Eje: Bienestar, Desarrollo Humano y Justicia Social, el INDEG, operará el\nPrograma, el cual es subsidiado a través de recursos provenientes de I.E.D., el cual tiene una inversión de\n$3’000,000.00 (Tres millones de pesos 00/100 m.n.), con un costo promedio de $250,000.00 (Doscientos cincuenta mil pesos 00/100 m.n.) mensuales, atendiendo 100 candidatas o candidatos de la población beneficiada.\nENERO FEBRERO MARZO ABRIL MAYO JUNIO\n250,000.00 250,000.00 250,000.00 250,000.00 250,000.00 250,000.00\n250,000.00 250,000.00 250,000.00 250,000.00 250,000.00 250,000.00\nNOTA: PUEDE EXISTIR VARIACIÓN EN RELACIÓN CON LA CAPACIDAD DE CONVOCATORIA DE LOS JÓVENES DE LAS 8 REGIONES DEL\nESTADO.\nNOTA: Las cantidades que presenta este numeral, podrá ser motivo de modificación, ya que es un programa nuevo, por lo que se ajustarán a las necesidades y resultados de los participantes.\n5.1. Gastos de Operación.\nPara realizar las visorias, supervisiones y demás temas de seguimiento, se realizará el trabajo de campo, lo que permitirá, poder realizar dichas actividades tomando en cuenta que dichos gastos se erogarán del\nGasto Corriente para no tomar un solo peso del Programa, recibiendo íntegro el recurso para las necesidades de las beneficiarias y beneficiarios.\n6. Criterios y Requisitos de Elegibilidad.\nEste rubro comprende la forma de difusión, que para este caso será por medio de convocatoria oficial, la cual se dará a conocer en la página oficial del Instituto.\n7. Tipo, y Monto de Periodicidad del Apoyo.\nPara el presente ejercicio fiscal, el monto mensual del Programa, contemplará a deportistas y/o entrenadoras o entrenadores, que representen o trabajen para el desarrollo del deporte en el estado de\nGuerrero, como el caso de metodólogos y que hayan sido aceptados de acuerdo a los requisitos señalados en las presentes Reglas de Operación y/o en la convocatoria emitida por el Instituto, de acuerdo a lo siguiente:\nDescripción de la Modalidad o Apoyo Número de Monto\nPeriodicidad Total\nTipo de Beca Deportiva Mensual Becas mensual\nDe 2,000.00\nMedallistas de los juegos\n3,000.00 y 20 70,000.00 12 meses 840,000.0\nNacionales CONADE.\n4,000.00 0\nDeportistas de Alto\nRendimiento/Destacadas 2,500.00 15 37,500.00 12 meses 450,000.0 o Destacados. 0\nDeportistas con discapacidad o 1,600.00 10 16,000.00 12 meses 192,000.0\nParanacionales 0\nTalentos Deportivos. 1,508.00 25 37,700.00 12 meses 452,400.0\nJuegos\n1,400.00 12 16,800.00 12 meses 201,600.0\nNacionales\nPopulares.\nEntrenadoras\n2,400.00 30 72,000.00 12 meses 864,000.0 entrenadores. 0\nTotal 112 250,000.00 12 3,000,000.\nNota: Del primer rubro, dependiendo de las medallas de Oro, Plata o Bronce, es el monto de beca que recibirá dicha beneficiaria o beneficiario. Asimismo, en caso de que no se complete con el número proyectado en medallistas, el INDEG, tendrá la facultad de reasignar dicho recurso a deportistas o entrenadoras o entrenadores según sean sus logros.\n7.1. Características de los Apoyos.\nLos apoyos que serán entregados a deportistas y entrenadoras o entrenadores como se refleja en el punto del cuadro; 7. Tipo, Monto y Periodicidad del Apoyo, se caracterizan de manera especial ya que, el tipo de población específica a beneficiar son personas vinculadas al ámbito deportivo guerrerenses de nacimiento y que no representen a otros estados en eventos deportivos.\n7.2. Recursos no Devengados.\nAquellas eventualidades que por contingencia o por una situación extrema, que no estén previstas dentro de la ministración de recursos, se suspenderán parcial o totalmente dichos apoyos. En el entendido también, que el recurso que por alguna razón los deportistas no hayan cobrado o no hayan cumplido con sus reportes mensuales; se reintegrará a la instancia normativa del ejercicio y control del gasto público, es decir a la SEFINA.\n7.3. Resguardo de la Documentación.\nLa información de los avances físico-financieros y comprobaciones del Programa, estarán bajo resguardo de la Dirección Administrativa del Instituto, asimismo, tendrá respaldo de la información comprobatoria del proceso de desarrollo de cada una de las beneficiadas o beneficiados, así como evidencia fotográfica y audiovisual que se irán publicando en el portal oficial del INDEG.\n7.4. Supervisión y Control.\nPara la supervisión y control del seguimiento de la evaluación de cada deportista y/o entrenadora o entrenador, se llevarán a cabo de manera presencial, así como la generación de reportes mensuales de las beneficiadas o beneficiados, realizando periódicamente evaluaciones por parte de la Dirección de\nDesarrollo del Deporte dependiente del Instituto.\n8. Criterios de Selección.\nPara la selección de beneficiarias y beneficiarios todos los participantes, deberán representar a Guerrero y no a otro estado o entidad deportiva:\na) Deberán ser medallistas de los Juegos Nacionales CONADE.\nb) Deportistas destacados o de Alto Rendimiento, por sus logros a nivel Nacional e Internacional.\nc) Deberán estar afiliados a una liga o club de las asociaciones deportivas en el estado.\nd) Deportistas con discapacidad, ser los más destacados en el estado de acuerdo a su Curriculum Vitae.\ne) Para deportes en conjunto, deberá seleccionarse el mejor de cada grupo de acuerdo a su trayectoria.\nf) De los deportistas que obtengan dos medallas o más en alguna disciplina deportiva, se tomará la más alta para su selección.\ng) De los Juegos Nacionales Populares, podrán participar los medallistas de dicho evento en específico.\nh) Para las y los entrenadores deportivos, se seleccionarán a los más sobresalientes del año inmediato anterior, sean medallistas de los Juegos Nacionales CONADE, JNP, o de Alto Rendimiento y/o eventos\nInternacionales.\ni) En caso de no estar algún criterio para la selección de deportistas o entrenadoras o entrenadores, quedará sujeto para su requerimiento en las convocatorias que se emitirán después de la emisión de las\nReglas de Operación.\nNota importante: De todas las solicitudes recepcionadas, se seleccionarán de acuerdo a la capacidad de becas ofertadas, quedando aprobados los que estén mejor posicionados, los cuales se someterán a su análisis y valoración, por parte del Instituto y su publicación se dará a conocer de manera oficial a través de las plataformas oficiales del INDEG, y gobierno de estado, según sea el caso.\n8.1. Casos Especiales.\nEn caso de ocurrir una situación extraordinaria que impida la operación normal del Programa, se resolverán por la persona titular del Instituto y los directivos involucrados, en caso de que algún requisito, como ficha de inscripción, papeleta o documentación citada en los puntos de estas Reglas de Operación, quedando sujetas a la publicación de la convocatoria oficial.\n8.2. Casos de Emergencia o Desastre. entrenadores, se podrá adelantar la entrega de becas, “siempre y cuando sea autorizado por el gobierno en turno”, en caso de que no se cuente con suficiencia presupuestal quedará sujeto a su análisis y valoración.\n8.3. Suspensión o Cancelación del Programa Social.\nPodrán cancelarse o suspenderse las operaciones del Programa, por incumplimiento por parte de las participantes, es decir, cuando no existan las condiciones sociales- económicas entre las partes, cuando las disposiciones y que afecte el seguimiento de los trabajos de las personas deportistas o entrenadoras.\n8.4. Integración del Padrón de Personas Beneficiarias.\nLas beneficiarias y los beneficiarios deberán cumplir con los requisitos sin distinción alguna, se realizará una convocatoria abierta para todas las personas interesadas que integrarán posteriormente un Padrón\nÚnico de Personas Beneficiarias, el cual será de carácter público, siendo reservados sus datos personales, de acuerdo con la normatividad vigente; los cuales no podrán utilizarse para proselitismo político o religioso, podrán participar en eventos públicos deportivos o cívicos, como desfiles, abanderamientos, participación de demostraciones deportivas, conferencias o talleres vinculados al deporte, entre otros.\n9. Mecánica Operativa del Programa Social.\n9.1. Instancia Ejecutora y/o Responsable.\nEl Instituto, a través de la Dirección Administrativa será la responsable del gasto, mientras que la Operación del Programa estará a cargo de la Dirección de Desarrollo del Deporte.\n9.2. Proceso de Incorporación al Programa Social.\nComo parte fundamental para las personas interesadas, deberán basarse en la convocatoria oficial emitida por el órgano rector INDEG firmada por la persona titular en turno.\nLas personas deportistas y entrenadoras serán seleccionadas en función de los criterios siguientes:\n● Cuando se realice el cotejo de los documentos establecidos en la convocatoria, y éstos cumplan con lo solicitado, el personal de la Dirección de Desarrollo del Deporte en conjunto con la Dirección Administrativa y demás personal que se considere para una mejor transparencia de los apoyos a otorgar, se tendrá que presentar en original toda la documentación solicitada.\n● Se Trabajará en coordinación con los municipios, directores del deporte municipal, presidentes de asociaciones deportivas, entrenadoras o entrenadores o metodolos.\n● Las becas deportivas que hayan sido otorgadas para el presente ciclo se renovarán para el siguiente, participando y podrá ser dado de baja por incumplimiento o reportes negativos de sus entrenadores.\nEnvío o entrega de documentación: entreguen y/o envíen en tiempo y forma la información solicitada bajo las siguientes características:\n* Todos los documentos deberán estar incluidos en una carpeta y por nombre, deberá contener el nombre de la beneficiaria o beneficiario, iniciando con sus apellidos, todo escrito con mayúsculas: ejemplo Álvarez\nMartínez Daniel.\n* Dentro de la carpeta deberán incluirse cada uno de los documentos solicitados (habrá un momento que se les pida cotejar contra originales).\n* Para el caso de deportistas, cada uno de los documentos llevará por nombre los apellidos de la beneficiaria o beneficiario, seguido del documento del que se trate.\nEjemplo:\n- Álvarez Martínez (Solicitud de propuesta)\n- Álvarez Martínez (Ficha de control técnica deportiva)\n- Álvarez Martínez (Plan de entrenamiento)\n- Álvarez Martínez (Currículum)\n- Álvarez Martínez (Identificación)\n- Álvarez Martínez (Curp)\n- Álvarez Martínez (Domicilio)\n- Álvarez Martínez (Fotografía)\nDocumentos obligatorios para deportistas:\n* Carta solicitud.\n* Sustento técnica propuesta.\n* Ficha de control técnica deportiva.\n* Plan de entrenamiento (gráfico y escrito).\n* Curriculum deportivo actualizado.\n* Identificación oficial.\n* Curp.\n* Comprobante de domicilio reciente (no mayor a 3 meses).\n* Fotografía digital reciente (de frente tamaño infantil, sin anteojos, frente descubierta).\nNota: En caso de que, al momento de la publicación de la convocatoria para el Programa, se requiera algún otro requisito el cual no se encuentre dentro de estas Reglas de Operación, las personas aspirantes deberán cumplir con ello, en el tiempo establecido antes del cierre de recepción de la documentación de la fecha establecida en la convocatoria.\nDependiendo de la zona geográfica en que se encuentren las personas aspirantes, la documentación deberá entregarse de manera física o ser enviados en tiempo y forma al siguiente correo, dependiendo de la zona geográfica en que se encuentren: institutodeporteguerrero@gmail.com\nDocumentos obligatorios para entrenadoras o entrenadores:\n* Carta de solicitud.\n* Formato D-002 (Se proporcionará el link para su descarga en la Convocatoria).\n* Plan de entrenamiento o programa de enseñanza.\n* Titulo o constancia de estudios profesionales del último grado de estudios.\n* Constancia de estudios afines de la función qué realiza (cursos, clínicas, certificaciones o actualizaciones, entrenamientos de alto rendimiento).\n* Curriculum deportivo actualizado.\n* Curp.\n* Comprobante de domicilio reciente (no a mayor a 3 meses).\n* Fotografía digital reciente (de frente, tamaño infantil, sin anteojos, frente descubierta.\nLos documentos deberán entregarse de manera física o ser enviados en tiempo y forma al siguiente correo dependiendo de la zona geográfica en que se encuentren: institutodeporteguerrero@gmail.com\nCaracterísticas que deberá contener el plan de entrenamiento gráfico y escrito:\n* Plan de entrenamiento escrito.\n* Análisis del macrociclo anterior.\n* Aspecto general de su equipo o atleta.\n* Actividades fundamentales.\n* Cronograma de competencias y objetivos.\n* Necesidades materiales y requerimientos indispensables.\n* Plan de entrenamiento gráfico.\nPlan de entrenamiento a nivel de microciclo o semana de entrenamiento.\nFecha límite de entrega de documentación de deportistas y entrenadores de manera digital:\nEl tiempo de apertura, queda sujeta a la publicación de las Reglas de Operación en el Periódico Oficial del\n10. Evaluación. beneficiarias o beneficiarios, la valoración de los resultados quedará a cargo directamente de la Dirección de Desarrollo del Deporte, siendo los encargados de informar de los aciertos y fortalezas, así como identificar sus problemas y áreas de mejora, con la finalidad de formular las observaciones y recomendaciones para su reorientación a favor del crecimiento deportivo.\n10.1. Indicadores. (Construcción de la Matriz de Indicadores para Resultados. - Anexo 1)\nPara la elaboración del Proyecto de Presupuesto se contempló la Metodología de Marco Lógico (MML); por ello, se contemplan indicadores cuantificables como son el número de becas otorgadas, a personas deportistas y entrenadoras en las diferentes modalidades.\n10.2. Seguimiento.\nPara el rubro de seguimiento es necesario obtener resultados eficientes de las beneficiarias y beneficiarios, siguiendo un grado de imparcialidad en todo el proceso, de inscripción durante el desarrollo y al final, es decir, para la rendición de cuentas.\n10.3. Auditoría.\nCon la finalidad de tener un rendimiento de cuentas clara y transparente, la Dirección Administrativa tendrá en digital y en físico la documentación probatoria para que esté disponible en caso de ser requeridas por las instancias fiscalizadoras de gasto. Asimismo, el órgano interno de control del Instituto mantendrá un seguimiento que permitirá emitir los informes de las revisiones practicadas, dando principal importancia a la atención en tiempo y forma de las irregularidades detectadas, hasta su total solventación.\n11. Mecanismo de Entrega del Apoyo.\nLas beneficiarias y los beneficiarios deberán en caso de requerírseles su presencia de manera física al\nINDEG o a algún lugar donde se vaya a realizar la entrega de las becas deportivas, deberán acudir con algún uniforme, o prenda de vestir que sea acordado a través del Instituto. En caso de que alguna persona deportista o entrenadora deportiva haya sido beneficiada se encuentre con alguna imposibilidad física o médica, deberá presentar una carta poder firmada por la persona que le asistirá para realizar los trámites pertinentes. El apoyo del recurso para la beneficiaria o beneficiario se realizará por transferencia a la persona deportista o entrenadora, no será entregado en cheque ni en efectivo.\n12. Derechos y Obligaciones de las Personas Beneficiadas.\na) Derechos de las Personas Participantes Beneficiadas.\nLas personas deportistas y/o entrenadoras beneficiarias tendrán los derechos siguientes:\n* Recibir el recurso en su totalidad en tiempo y forma.\n* No realizar pagos por trámites administrativos.\n* Recibir el comunicado por parte del personal del Instituto, sobre la asignación de la beca.\n* A través de su madre, padre, tutora, tutor y/o representante legal, suscribirá con firma autógrafa la documentación que formalice el otorgamiento de la beca, (en caso de ser menor de edad).\nb) Obligaciones de las personas Participantes Beneficiadas.\nLas personas deportistas y/o entrenadoras beneficiarias tendrán las siguientes obligaciones:\n* Proporcionar, bajo protesta de decir la verdad, la información que se les requiera de acuerdo a lo establecido en las presentes Reglas de Operación.\n* Asistir a eventos deportivos representando propios del INDEG.\n* Rendir informes de manera mensual o según se les requiera.\n* Representar al estado sin recibir beca de otra entidad federativa.\n* Ser guerrerense con documentos oficiales.\n* Estar afiliada o afiliado a una Asociación Deportiva.\n* Los casos no previstos serán sometidos a la consideración del Instituto.\n12.1. Causales de Suspensión o Baja de las Personas Beneficiadas.\na) Podrá causar suspensión o baja por incumplimiento de entregar algún requisito como reportes mensuales o como se les requiera, asistir a competencias representando a otro estado que no sea\nGuerrero, por falta de resultados o que los deportistas que no están inscritos mejoren su nivel competitivo y puedan ingresar al padrón, es por ello que, dependiendo de los resultados en un tiempo establecido se podrá continuar o dar de baja dentro del padrón.\nb) Cuando renuncien expresamente por escrito a los beneficios de la beca.\nc) Cuando contravengan con lo establecido en las presentes Reglas de Operación.\nd) Cuando se haya agotado el tiempo de duración de la beca y no se efectúe la renovación.\ne) Cuando las personas beneficiarias fallezcan.\nf) Cuando concluyan con la edad establecida.\n12.2. Proceso de Baja.\nEl proceso de baja lo remitirá a la Dirección Administrativa la Dirección de Desarrollo del Deporte de acuerdo con sus evaluaciones en el proceso de seguimiento, deberán portar uniforme oficial de la\nSi causan algún desperfecto, problemas o por ingerir algunas bebidas alcohólicas o drogas, que ponga en cualquier otra que no sea la apropiada como deportista.\n13. Instancias Participantes.\nDurante el inicio y todo el proceso, existirá estrecha vinculación entre las siguientes instancias:\nINDEG: Instituto del Deporte de Guerrero.\nSEFINA: Secretaría de Finanzas y Administración.\nSEPLADER: Secretaría de Planeación y Desarrollo Regional.\nSCyTG: Secretaría de Contraloría y Transparencia Gubernamental.\n13.1. Instancia Normativa.\nComo órgano rector del deporte en el estado, corresponde al Instituto regular la ejecución del Programa, asimismo a la SEPLADER revisar y autorizar dichas Reglas de Operación.\n14. Transparencia.\n14.1. Promoción y Difusión del Programa Social.\nPara realizar la difusión del Programa, se cuenta con un área especializada de comunicación dentro el\nINDEG, la cual será la responsable de publicar a nivel estatal la convocatoria, el proceso de alcance de las metas, todo lo concerniente en las páginas oficiales del INDEG, así como en la página oficial del gobierno del estado.\n- Facebook: Instituto del Deporte de Guerrero.\n- Correo electrónico: institutodeporteguerrero@gmail.com\n14.2. Contraloría Social.\nUna de las principales acciones para combatir la corrupción a nivel mundial es la transparencia, es por ello que el INDEG, realizará de manera transparente la operación del Programa, invitando a las asociaciones deportivas a que sean partícipes en la rendición de cuentas, así como en los informes que se presenten al órgano interno de control del INDEG.\n14.3. Protección de Datos Personales.\nPara tal efecto, los datos de las beneficiarias y beneficiarios consisten en mantener la integridad a salvo, y únicamente podrán ser utilizados con la autorización de las madres, padres, tutoras o tutores a cargo.\n14.4. Quejas y Denuncias.\nPodrán dar a conocer sus inconformidades en relación a quejas o denuncias de las formas siguientes:\n* Por correo electrónico a través del correo institucional.\n* Buzón de quejas y denuncias instalado en las oficinas centrales del Instituto.\n* Por escrito.\n* Vía Telefónica.\n14.5. Acciones de Blindaje. o en los años subsecuentes, en un segundo momento, se deberán atender las observaciones que emitan y las demás autoridades competentes.\nAsimismo, con la finalidad de impedir que los apoyos sean utilizados con fines políticos electorales, se informa que toda la papelería, documentación oficial, así como, la publicidad y promoción de este Programa deberán incluir la siguiente leyenda:\n“Este Programa es de carácter público, no es patrocinado ni promovido por partido político alguno y sus recursos provienen de los impuestos que pagan todos los contribuyentes. Está prohibido el uso de este Programa con fines políticos, electorales, de lucro y otros distintos a los establecidos.\nQuién haga uso indebido de los recursos de este Programa deberá ser denunciada o denunciado y sancionada o sancionado de acuerdo con la ley aplicable y ante la autoridad competente”.\nEn cuanto a la publicidad en medios electrónicos, así como los videos o capsulas audiovisuales, e impresos, complementarios o de cualquier otra índole, vinculados con los programas de comunicación social, se deberá incluir la leyenda siguiente:\n“Este Programa es público y ajeno a cualquier partido político. Queda prohibido su uso para fines distintos a los establecidos en el Programa”.\n14.6. Acta de Donación. (Anexo 2)\nCon la finalidad de tener certeza de vigilar el adecuado manejo y transparencia de los recursos que se ejercerán para el Programa, que se brindarán a cada uno de los deportistas, será necesario contar con evidencias documentales que certifiquen que los apoyos brindados se llevaron a cabo.\nPara ello, el Instituto del Deporte de Guerrero, por medio de la Dirección de Desarrollo del Deporte en coordinación con las asociaciones deportivas y los ayuntamientos municipales, darán fe y legalidad del beneficio de la beca a cada una de las personas beneficiadas, a través del Acta de Donación, quedará bajo el resguardo de la Dirección de Desarrollo del Deporte, así como de la Dirección Administrativa.\n15. Perspectiva de Género.\nEl Programa, engloba de manera general en su convocatoria el papel que asume el sexo femenino sin importar las clases sociales o tipo de religión, con el solo hecho de ser mujer y ser guerrerense, puede ser candidata a obtener el beneficio siempre y cuando cumpla con los requisitos.\n16. Enfoque de Derechos.\nEste Programa maneja un enfoque integral, es decir, niñas, niños, jóvenes, personas adultas y personas con capacidades diferentes, sin discriminación alguna.\n17. Acciones Contra el SARS-COV 2.\nAnte la realidad que vivimos por el desarrollo de la pandemia sanitaria originada por el SARS-Cov2 (COVID-\n19), resulta de vital importancia el escenario de salud sobre el cual se tendrá que actuar, por lo que el de cada municipio, tendrán como reto de instrumentar las sinergias pertinentes para crear las condiciones que equilibren la estrategia para el deporte de Alto Rendimiento, esto implementará una política de trabajo para la atención de los deportistas, con base en los objetivos de sus programas de preparación y competición en eventos fundamentales, como lo son los juegos nacionales CONADE, juegos nacionales populares, así como los atletas de alto rendimiento y destacados, considerando las normas sanitarias que se establezcan por los organismos de salud tanto nacionales, como internacionales. Ya que el desempeño competitivo del deporte convencional y adaptado es una prioridad para garantizar la continuidad al logro de resultados en el ámbito internacional, por ello, la estrategia de deporte de Alto\nRendimiento tiene como objetivo principal proporcionar los apoyos necesarios para la preparación y participación de los atletas que representarán al estado, ponderando en todo momento el ejercicio de los recursos disponibles, con el fin de garantizar los niveles de resultados que se pueden alcanzar en el corto y medio plazo; estos apoyos serán coordinados con las asociaciones deportivas estatales y aplicados con base en criterios técnicos que garanticen los resultados con mayor trascendencia para nuestro estado y optimizando la eficiencia del recurso humano y económico.\n18. Anexos que reflejen la entrega del apoyo (Económico, Especie o Servicios).\nAnexo 1.- Ficha Técnica.\nAnexo 1-A.- MIR (Metodología de Marco Lógico).\nAnexo 2.- Formato de Entrega-Recepción.\nAnexo 3.- Sustento Técnico de Propuesta de Beca Económica 2023 Dirección de desarrollo del deporte\nINDEG. Integrado con sus anexos 3.1, 3.2.\nAnexo 4.- Ficha de Control Técnico de Deportista 2023. Integrado con sus anexos 4.1, 4.2.\nAnexo 5.- Propuesta de Beca Deportiva Económica estatal. Integrado con su anexo 5.1.\nAnexo 1\nAnexo 1-A\nAnexo 5\nPrimero. El presente Acuerdo, entrará en vigor al siguiente día de su publicación en el Periódico Oficial del\nSegundo. A partir de la entrada en vigor del presente Acuerdo, las Reglas de Operación del Programa, subsecuentes o sus modificaciones, serán emitidas por la persona titular del Instituto del Deporte de\nGuerrero, responsable directa de la operación y ejecución de las mismas.\nDado en el “Recinto de las oficinas del Poder Ejecutivo del Estado”, el inmueble ubicado en el Edificio\nCentro, Boulevard René Juárez Cisneros No. 62 de la Ciudad de los Servicios en Chilpancingo de los\nBravo, capital del estado de Guerrero, a los veintiocho días del mes de febrero del año dos mil veintitrés.\nGOBERNADORA CONSTITUCIONAL DEL ESTADO DE GUERRERO.\nMTRA. EVELYN CECIA SALGADO PINEDA.\nRúbrica.\nSECRETARIO GENERAL DE GOBIERNO.\nMTRO. LUDWIG MARCIAL REYNOSO NÚÑEZ.\nRúbrica.\nDIRECTORA GENERAL DEL INSTITUTO DEL DEPORTE DE GUERRERO.\nDRA. ALMA ROCÍO LÓPEZ BELLO.",
  "ordenamiento": "PROGRAMA",
  "jurisdiccion": "GUERRERO",
  "fuente_oficial": "DIARIO OFICIAL DE LA FEDERACION",
  "Fecha de Publicación": "18 \nde abril de 2023",
  "ULTIMA REFORMA PUBLICADA": null,
  "status": "VIGENTE",
  "es_escaneado": false,
  "tiene_tablas": true,
  "materia": [
    "educación",
    "deporte"
  ]
}