{
  "titulo": "Acuerdo por el Que Se Crea el Programa Tarjeta Violeta y Se Emiten Sus Reglas de Operación",
  "Contenido": "TEXTO ORIGINAL.\nACUERDO POR EL QUE SE CREA EL PROGRAMA TARJETA VIOLETA Y SE EMITEN SUS REGLAS\nDE OPERACIÓN.\nGuerrero. - Poder Ejecutivo.\nMAESTRA EVELYN CECIA SALGADO PINEDA, GOBERNADORA CONSTITUCIONAL DEL\nESTADO DE GUERRERO, CON FUNDAMENTO EN LO DISPUESTO POR LOS ARTÍCULOS 71, 87, 88,\nEJERCICIO DE LAS FACULTADES QUE ME CONFIEREN LOS ARTÍCULOS 1, 2, 4, 8, 9, 14, 16, 22\nAPARTADO A FRACCIONES I Y IV, 23 FRACCIÓN III Y 26 DE LA LEY ORGÁNICA DE LA\nADMINISTRACIÓN PÚBLICA DEL ESTADO DE GUERRERO NÚMERO 242; 1, 2 FRACCIÓN I, 18 Y 25\nDE LA LEY NÚMERO 454 DE PRESUPUESTO Y DISCIPLINA FISCAL DEL ESTADO DE GUERRERO;\n1, 2, 3, 6 Y 8 DE LA LEY NÚM. 102, PARA EL DESARROLLO SOCIAL DEL ESTADO DE GUERRERO;\nEN RELACIÓN CON EL ARTÍCULO 42 DEL DECRETO NÚMERO 680 RELATIVO AL PRESUPUESTO\nDE EGRESOS DEL ESTADO DE GUERRERO PARA EL EJERCICIO FISCAL 2024 Y LOS\nLINEAMIENTOS PARA LA ELABORACIÓN DE LAS REGLAS DE OPERACIÓN DE LOS PROGRAMAS\nSOCIALES ESTATALES PARA EL PERIODO 2022-2027.\nQue la Agenda 2030 para el Desarrollo Sostenible es un documento que establece en su Objetivo\n1: Poner fin a la pobreza en todas sus formas en todo el mundo, y en su meta 1.3 señala que se deben implementar a nivel nacional sistemas y medidas apropiados de protección social para todos, incluidos niveles mínimos, y de aquí al 2030, lograr una amplia cobertura en las personas pobres y vulnerables.\nAdemás, el Objetivo 5: Lograr la igualdad entre los géneros y empoderar a todas las mujeres y las niñas, específicamente en la meta 5.c que consiste en aprobar y fortalecer políticas acertadas y leyes aplicables niveles. Finalmente el Objetivo 8: Promover el crecimiento económico sostenido, inclusivo y sostenible, el empleo pleno y productivo y el trabajo decente para todos, y en la meta 8.3 precisa que es necesario promover políticas orientadas al desarrollo que apoyen las actividades productivas, la creación de puestos de trabajo decentes, el emprendimiento, la creatividad y la innovación, y fomentar la formalización y el crecimiento de las microempresas y las pequeñas y medianas empresas, incluso mediante el acceso a servicios financieros.\nQue el Plan Estatal de Desarrollo 2022-2027 guía las acciones y políticas públicas en el estado.\nDentro de este plan y como eje rector del Programa Tarjeta Violeta, el eje 1 se enfoca en aspectos fundamentales para el bienestar y el progreso social, tales como el desarrollo humano y la justicia social.\nEl objetivo específico 1.1 de este eje se concentra en abordar la problemática de la pobreza en la población de Guerrero, un desafío importante que afecta el bienestar y la calidad de vida de las y los guerrerenses.\nPor su parte, la estrategia 1.1.1. busca apoyar el desarrollo integral de la población en situación de pobreza.\nEsto implica no sólo abordar las necesidades económicas inmediatas, sino también promover su acceso a servicios básicos de calidad, como educación, salud y vivienda, y también empoderar a las personas para que puedan salir de la pobreza de manera sostenible y mejorar su calidad de vida a largo plazo.\nDe la misma manera, la Ley Núm. 102, para el Desarrollo Social del Estado de Guerrero, establece que el objetivo de la Política Social de la entidad para el desarrollo social y superación de la pobreza, es el de fomentar las condiciones para que las personas y la sociedad en su conjunto puedan satisfacer sus necesidades humanas y sociales, para fortalecer el pleno goce de sus derechos y garantías políticas, económicas, sociales y culturales, que les permita optar por un plan de vida.\nQue la Ley Orgánica de la Administración Pública del Estado de Guerrero Número 242, en el artículo 26, establece que la Secretaría de Bienestar es el órgano encargado de la política general de desarrollo y bienestar social. Asimismo, en su fracción II, señala que tiene que coordinar las acciones que incidan en el abatimiento de los niveles de pobreza que considere la desigualdad existente entre mujeres y hombres, y fomenten un mejor nivel de vida de la población; y en la fracción III, indica que le corresponde concertar, coordinar y ejecutar programas y proyectos especiales para el desarrollo social y productivo de la entidad, que garanticen una mejoría en los niveles de vida de los grupos de población más desprotegidos, con la participación que corresponda a las secretarías, dependencias y entidades paraestatales de la administración pública federal, estatal y municipal, así como la de los sectores social y privado.\nQue el Decreto Número 680 Relativo al Presupuesto de Egresos del Estado de Guerrero para el\nEjercicio Fiscal 2024, en su artículo 47 establece que con el objeto de asegurar la aplicación eficiente, oportuna, equitativa y transparente de los recursos públicos, la Secretaría de Finanzas y Administración y la Secretaría de Planeación y Desarrollo Regional emitirán las disposiciones a que deberán apegarse los programas de inversión sujetos a Reglas de Operación, así mismo, las dependencias y entidades serán responsables de emitir las Reglas de Operación o, en su caso, las modificaciones a aquéllas que continúen vigentes.\nQue en el Reglamento Interior de la Secretaría de Desarrollo y Bienestar Social, estipula en el artículo 3, que la SBGro a través de las unidades administrativas centrales y regionales y demás órganos administrativos desconcentrados, conducirá sus actividades en forma programada y con base en las políticas, prioridades y restricciones establecidas, para el logro de los objetivos y metas del Plan Estatal de\nDesarrollo, Programa Sectorial de Desarrollo Social y demás específicos que la Secretaría de Desarrollo y nivel federal.\nQue la Secretaría de Planeación y Desarrollo Regional, expidió los Lineamientos para la elaboración de las Reglas de Operación de los Programas Sociales Estatales para el periodo 2022-2027, del 2022. Los cuales tienen la finalidad de ofrecer a las secretarías, dependencias y entidades centrales de las Reglas de Operación, así como los elementos para integrar su contenido. intervención pública, en el que se establecen los objetivos del beneficio o apoyo que entrega, los requisitos para obtenerlo, los alcances que tiene y la forma de gestionarlo. Las Reglas de Operación también son importantes porque hace explícita la lógica de intervención, los resultados que se pretenden alcanzar y el procedimiento para entregar los beneficios. Y aunque contienen una parte del diseño, no la agotan en su totalidad.\nQue el Programa de Tarjeta Violeta, es una iniciativa que pretende ayudar a aumentar los ingresos de mujeres jefas de familia y víctimas de violencia en todas sus manifestaciones, a través de la provisión de asistencia financiera y servicios complementarios (evaluación médica, ayuda psicológica y apoyo jurídico, según sea el caso de la beneficiaria que se encuentren en los Centros de Apoyo Interdisciplinario a Víctimas de Violencia), está sujeto a las Reglas de Operación estableciendo las disposiciones que brindarán transparencia y una aplicación eficiente, eficaz, oportuna y equitativa de los recursos públicos asignados, y que deberán publicarse en el Periódico Oficial del Gobierno del Estado de Guerrero.\nPor lo anteriormente expuesto y con fundamento en las disposiciones legales antes citadas, he tenido a bien expedir el siguiente:\nACUERDO POR EL QUE SE CREA EL PROGRAMA TARJETA VIOLETA Y SE EMITEN SUS REGLAS\nDE OPERACIÓN.\nArtículo 1. Se crea el Programa Tarjeta Violeta, el cual tiene como objetivo promover el empoderamiento económico de las mujeres jefas de familia en situación de vulnerabilidad o que se encuentren en los Centros de Apoyo Interdisciplinario a Víctimas de Violencia (CAIV).\nArtículo 2. La Secretaría de Bienestar, tendrá a cargo la implementación, ejecución, evaluación y administración del Programa, bajo los criterios de equidad, transparencia, publicidad, selectividad y temporalidad, con estricto apego a la normatividad aplicable, por lo tanto, será la encargada de la dispersión y asignación de los recursos apegándose plenamente a las Reglas de Operación.\nArtículo 3. Se emiten las Reglas de Operación del Programa Tarjeta Violeta, en las que se establece el procedimiento de ejecución del Programa, los principios, requisitos y condiciones que deben observarse para acceder al mismo, en los términos siguientes:\nREGLAS DE OPERACIÓN DEL PROGRAMA TARJETA VIOLETA.\n1. Introducción.\n1.1. Antecedentes. y tomar protesta como Gobernadora Constitucional del Estado, es lograr un Guerrero de paz, de justicia social, de desarrollo económico y de empleo, contribuyendo en consecuencia al desarrollo económico y estabilidad social de las familias guerrerenses. con las jefas de familia en el estado de Guerrero, y es necesario e imperante que, dentro de las políticas públicas de desarrollo, este sector sea contemplado como una prioridad para la protección integral de las familias guerrerenses. En consecuencia, se busca que los programas sociales contengan acciones encaminadas a fortalecer la participación social, la organización comunitaria que facilite los procesos productivos de los grupos vulnerables sobre todo al cuidado, promoción y dignificación de las jefas de familias Guerrerenses, por lo que ha decidido crear un programa que evite la dependencia económica y la marginalización de las mujeres y que impulse su autonomía y capacidad de sostén económico.\nLa Secretaría de Bienestar del Estado de Guerrero tendrá a cargo la implementación, operación, ejecución, evaluación y administración del Programa, bajo los criterios de objetividad, equidad, transparencia, publicidad, selectividad y temporalidad, con estricto apego a la normatividad aplicable y vigente, por lo que será la encargada de la asignación, dispersión, evaluación y seguimiento de los recursos del Programa apegándose plenamente a las Reglas de Operación y a la convocatoria que será emitida la última semana del mes de enero del año en curso. (ADICIONADO, P.O. 05 ALCANCE IV, 17 DE ENERO DE 2025).\nDe la misma manera, la Ley Núm. 102, para el Desarrollo Social del Estado de Guerrero, establece que el objetivo de la Política Social de la entidad para el Desarrollo Social y Superación de la Pobreza, es el de fomentar las condiciones para que las personas y la sociedad en su conjunto puedan satisfacer sus necesidades humanas y sociales, para fortalecer el pleno goce de sus derechos y garantías políticas, económicas, sociales y culturales, que les permita optar por un plan de vida. (ADICIONADO, P.O. 05 ALCANCE\nIV, 17 DE ENERO DE 2025). establecen entre otras cosas, que son deberes fundamentales del Estado promover el progreso social y económico, individual o colectivo, el desarrollo sustentable, la seguridad y la paz social, y el acceso de todos los guerrerenses en los asuntos políticos y en la cultura, atendiendo en todo momento al principio de equidad; que en el Estado de Guerrero toda persona gozará de los derechos humanos y las garantías reconocidos por la Constitución Política de los Estados Unidos Mexicanos, esta Constitución y los instrumentos internacionales incorporados al orden jurídico mexicano; que todas las autoridades del\nEstado, en el ámbito de su competencia tienen la obligación de promover, respetar, proteger, garantizar y defender los derechos humanos, atendiendo a los principios de universalidad, interdependencia, individual y colectiva.\nLa Convención Interamericana para Prevenir, Sancionar y Erradicar la Violencia Contra la Mujer\n(Convención Belém do Pará o Convención BDP), en el artículo 7, y la Ley Número 553 de Acceso de las que es responsabilidad del Estado, de los poderes legalmente constituidos y de los municipios, en los ámbitos de sus respectivas competencias, adoptar, por todos los medios apropiados y sin dilaciones, políticas orientadas a prevenir, sancionar y erradicar todas las formas de violencia contra la mujer. implementar políticas públicas orientadas al bienestar, ya que estas medidas tienen un impacto directo en el bienestar social al reducir los niveles de pobreza y la vulnerabilidad económica. Esto se traduce en un aumento de las oportunidades para el desarrollo humano, mejorando así la calidad de vida y elevando el estándar de bienestar de las y los guerrerenses.\nEl Instituto Nacional de Estadística y Geografía (INEGI), señala en 2020, que en el estado de\nGuerrero existen 334,190 madres jefas de familia y que el 45.1% de ellas, se encuentran solteras, separadas, divorciadas y/o en situación no vulnerable por ingresos.\nAdicionalmente, de acuerdo con datos del INEGI, obtenidos mediante la Encuesta Nacional sobre la Dinámica de las Relaciones en los Hogares (ENDIREH) 2021, en el estado de Guerrero el 68.8% de las mujeres de 15 años o más, experimentaron algún tipo de violencia: psicológica 53.3%; sexual 40.9%; física\n35.6%; económica o patrimonial 30.3% a lo largo de la vida y el 44.1% en los últimos 12 meses, destacando que el mayor porcentaje de prevalencia de violencia fue en el ámbito de pareja con un 47.6%, ocupando el primer lugar a nivel nacional, ubicándose un 7.7% por encima de la media nacional. Es importante resaltar que de acuerdo con datos comparativos con el año 2016, dicho porcentaje se ha ido incrementando en todos los casos de tipo y de ámbito de violencia.\nEl estado de Guerrero es uno de los estados con cifras más altas en cuanto a violencia de género, por lo cual es necesario que el gobierno estatal y municipal, atiendan y erradiquen las diferentes modalidades de violencia contra las mujeres y las de discriminación que resultan de estas formas dar cabal cumplimiento a las convenciones y tratados internacionales en materia de derechos, discriminación y violencia contra la mujer, en los términos establecidos por el artículo 1o de la Constitución Política de los\nEstados Unidos Mexicanos. (REFORMADO, P.O. 54 ALCANCE III, 05 DE JULIO DE 2024).\nQue la gobernadora constitucional del estado de Guerrero, instruyo a la persona titular de la\nSecretaría de Bienestar, ampliar el techo presupuestal para que las mujeres jefas de familia en situación de vulnerabilidad sean beneficiadas en el Programa Tarjeta Violeta. (REFORMADO, P.O. 54 ALCANCE III, 05 DE\nJULIO DE 2024).\n2. Alineación Programática al PED y/o PND.\nEl Programa responde al Plan Estatal de Desarrollo 2022-2027, en el eje temático 1. Bienestar, Desarrollo Humano y Justicia Social: Para garantizar los derechos de todas y todos desde una perspectiva integral, con el bienestar y la justicia social como ejes articuladores de una política pública, humana y sensible. Corresponde al objetivo 1.1. Reducir la pobreza de los guerrerenses, la estrategia 1.1.1. Aumento del ingreso económico de la población en situación de pobreza, impulsando su integración al mercado laboral y apoyando su desarrollo integral y la Línea de acción 1.1.1.1. Impulsar apoyos para la mujeres madres de familia en situación de vulnerabilidad.\nAdemás, responde al Plan Nacional de Desarrollo 2019-2024 con su Capítulo 1. Política y\nGobierno, segundo párrafo del subtema Libertad e Igualdad menciona: “En el presente sexenio el quehacer gubernamental impulsará la igualdad como principio rector: la igualdad efectiva de derechos entre mujeres y hombres, entre indígenas y mestizos, entre jóvenes y adultos, y se comprometerá en la erradicación de las prácticas discriminatorias que han perpetuado la opresión de sectores poblacionales enteros.\nEn suma, el Capítulo 2. Política Social, que establece como subtema Construir un país con\nBienestar refiere que el gobierno federal impulsará una nueva vía hacia el desarrollo para el bienestar, una vía en la que la participación de la sociedad resulte indispensable, cuyo propósito es construir la modernidad desde abajo, entre todas y todos, sin excluir a nadie. El gobierno será un garante de derechos y además, hará realidad el lema “Primero los Pobres”, que significa empezar el combate a la pobreza y la marginación por los sectores más indefensos de la población.\n2.1. Diagnóstico.\nLa intersección entre la igualdad de género y la pobreza en Guerrero plantea desafíos adicionales para las mujeres en la región. Las mujeres, especialmente aquellas en situación de pobreza, enfrentan obstáculos adicionales para acceder a recursos y oportunidades que les permitan salir de la pobreza y empoderarse económicamente.\nLas brechas de género en el acceso a la educación, la salud y el empleo digno perpetúan un ciclo de desigualdad que afecta desproporcionadamente a las mujeres. La violencia de género también actúa como un factor que perpetúa la pobreza, al limitar las opciones y oportunidades de las mujeres, así como su capacidad para desarrollarse plenamente en todos los aspectos de la vida.\nAbordar la intersección de género y pobreza en Guerrero requiere enfoques integrados que reconozcan y aborden las múltiples dimensiones de la desigualdad, promoviendo políticas y programas que empoderen a las mujeres, promuevan la equidad de género y faciliten el acceso igualitario a recursos y oportunidades para todas las personas, independientemente de su género o situación socioeconómica.\nSegún datos del Consejo Nacional de Evaluación de la Política de Desarrollo Social (CONEVAL) en su Informe de pobreza y evaluación 2022 en Guerrero, el 60.4% de la población de la entidad vivía en situación de pobreza, es decir, 2,173,300 personas, aproximadamente. De este universo, el 38.1% (cerca de 1,372,800 personas) estaba en situación de pobreza moderada, mientras que el 22.2% de la población se encontraba en situación de pobreza extrema (alrededor de 800,500 personas). (REFORMADO, P.O. 05 mayores, las madres solteras, jefas de familia y la población discapacitada; en 2020, según el Sistema de\nIndicadores sobre Pobreza y Género, 2016-2020 de CONEVAL, el 44.4% de las mujeres en México estaban en situación de pobreza en el 2020. Igualmente, el porcentaje de mujeres en pobreza de la entidad está\n24.1 puntos porcentuales por arriba del porcentaje nacional, ocupando el tercer lugar respecto a las demás entidades federativas por su porcentaje de mujeres en pobreza, que equivale aproximadamente a\n1,259,700 mujeres.\nHecho grave, que se complica aún más al analizar las particularidades culturales y educativas de las madres solteras como la situación de analfabetismo, la educación primaria sin concluir, el aspecto del monolingüismo, la marginación, el desempleo y la pobreza extrema, entre otros factores externos que abaten a este sector de la población guerrerense. madres jefas de familia en situación de vulnerabilidad que atiendan en parte, las carencias o insuficiencias de ingresos económicos sin practicar acciones de asistencialismo y que por el contrario cuenten con capacitaciones en desarrollo humano para su empoderamiento dentro de la sociedad civil.\nSegún datos oficiales del Consejo Nacional de Población (CONAPO) y con base en el Informe\nAnual de la Situación de Pobreza y Rezago Social 2023 de la Secretaría de Bienestar del Gobierno de\nMéxico, la población total de Guerrero es de 3,679,821 habitantes, siendo 51.6% mujeres y 48,4% hombres.\n{\"tabla_1\":{\"columnas\":[\"(sin encabezado)\",\"(sin encabezado)\",\"PEA\",\"PEA\"],\"filas\":[{\"columna_1\":\"(sin dato)\",\"columna_2\":\"(sin dato)\",\"columna_3\":\"FEMENINA\",\"columna_4\":\"MASCULINA\"},{\"columna_1\":\"Población Económicamente Activa\",\"columna_2\":\"1,666,265\",\"columna_3\":\"711,619\",\"columna_4\":\"954,646\"},{\"columna_1\":\"(sin dato)\",\"columna_2\":\"(sin dato)\",\"columna_3\":\"42.8%\",\"columna_4\":\"57.2%\"},{\"columna_1\":\"Población Económicamente No\",\"columna_2\":\"976,202\",\"columna_3\":\"717,960\",\"columna_4\":\"258,242\"},{\"columna_1\":\"Activa\",\"columna_2\":\"(sin dato)\",\"columna_3\":\"73.5%\",\"columna_4\":\"26.5%\"}]}}\nFUENTE: Elaboración propia con información de CONAPO 2023.\nLa participación de las mujeres en el mercado laboral, supone la aparición de nuevas formas de organización familiar, en las que mujeres y hombres, contribuyen en la obtención de los recursos para el hogar. Sin embargo, el trabajo reproductivo sigue siendo una responsabilidad eminentemente femenina, a pesar del aumento de la participación de los hombres en las primeras etapas de vida de los recién nacidos.\nLos cambios legales, sociales y culturales de los últimos años no han conseguido eliminar el modelo tradicional del trabajo reproductivo.\nCon la implementación del Programa, se establece un marco legal que propicia los principios para impulsar y promover la igualdad de género, sea donde sea que las mujeres se desenvuelvan, ya sea en el lugar de trabajo, el mercado y la comunidad. Estas bases sirven como hoja de ruta para fomentar prácticas y que éstas se vuelvan recurrentes para que contribuyan al empoderamiento de las mujeres, incluidas:\na) Construir economías fuertes.\nb) Establecer sociedades más justas y estables.\nc) Mejorar la calidad de vida de las mujeres, hombres, familias y comunidades.\n2.1.1. Población Potencial.\nMujeres mayores de 18 años y hasta 59 años 11 meses en situación de vulnerabilidad o víctimas\n2.1.2. Población Objetivo.\nMujeres residentes en el estado de Guerrero, que sean madres jefas de familia con hijas e hijos en edad escolar básica. Deben habitar en zonas de alta marginación y/o alto rezago social.\nMujeres víctimas de violencia que se encuentren en algún Centro de Apoyo Interdisciplinario a\nVíctimas de Violencia (CAIV) en el estado.\n2.1.3. Población Beneficiaria.\nEl Programa beneficiará a mujeres mayores de 18 años hasta 59 años 11 meses, que habiten en el estado de Guerrero, que sean madres solteras, jefas de familia, embarazada, lactantes (0 - 2 años\n11 meses) hija o hijo en edad escolar básica y/o media superior, que se encuentren en situación de vulnerabilidad. Además, mujeres víctimas de violencia que se encuentren en algún Centro de Apoyo\nInterdisciplinario a Víctimas de Violencia (CAIV) en el estado de Guerrero. (REFORMADO, P.O. 05 ALCANCE\nIV, 17 DE ENERO DE 2025).\nPara efectos de este Programa, se consideran mujeres en situación de vulnerabilidad a las mujeres que:\na) Sean jefas de familia mayores de 18 años hasta 59 años 11 meses en situación de pobreza.\nb) Por su ubicación geográfica, habiten en localidades catalogadas como:\n● Zonas de Atención Prioritaria 2024 (de acuerdo al Informe Anual sobre la Situación de Pobreza y Rezago Social 2024 de la Secretaría de Bienestar federal).\n● Municipios y localidades con alerta de género.\n● Municipios y localidades de alta y muy alta marginación.\n● Municipio y localidades de alto y muy alto rezago social.\nc) Mujeres víctimas de violencia.\nd) Mujeres con vulnerabilidad extrema que hayan sido canalizadas por el Protocolo Violeta en el estado de Guerrero.\n2.1.4. Población Indígena. vulnerabilidad social.\n2.2. Fundamento Legal.\na) Constitución Política de los Estados Unidos Mexicanos.\nc) Ley de Coordinación Fiscal.\nd) Plan Nacional de Desarrollo 2019-2024.\ne) Ley Orgánica de la Administración Pública del Estado de Guerrero Número 242.\nf) Ley de Fomento Económico, Inversión y Desarrollo del Estado de Guerrero Número 487.\ng) Ley Número 454 de Presupuesto y Disciplina Fiscal del Estado de Guerrero.\ni) Ley Número 466 de Protección de Datos Personales en Posesión de Sujetos Obligados del\nEstado de Guerrero.\nk) Ley Núm. 102, para el Desarrollo Social del Estado de Guerrero.\nl) Ley Número 465 de Responsabilidades Administrativas para el Estado de Guerrero.\nm) Ley Número 468 de Fiscalización Superior y Rendición de Cuentas del Estado de Guerrero.\nn) Ley Número 427 del Sistema de Coordinación Hacendaria del Estado de Guerrero.\no) Plan Estatal de Desarrollo 2022-2027.\np) Decreto Número 203 del Presupuesto de Egresos del Estado de Guerrero para el Ejercicio\nr) Acuerdo que establece los Compromisos para la Estabilidad y Desarrollo del Estado de\nGuerrero.\ns) Lineamientos para la Elaboración de las Reglas de Operación de los Programas Sociales\nEstatales para el Periodo 2022-2027.\nt) Ley Número 553 de Acceso de las Mujeres a una Vida Libre de Violencia del Estado Libre y\nSoberano de Guerrero.\nu) Todas aquellas disposiciones normativas aplicables.\n2.3. Definiciones y Siglas.\nDefiniciones:\nActa de donación: Documento público que acredita la entrega de un bien. (ADICIONADO, P.O. 05\nALCANCE IV, 17 DE ENERO DE 2025).\nBeneficiaria: Mujer que recibirá apoyo del Programa.\nCapacitación: Proceso de adquirir conocimientos, habilidades y competencias específicas a través de la enseñanza formal o informal, con el objetivo de mejorar el desempeño laboral, profesional o personal de una o un individuo.\nCarencia Social: Falta o insuficiencia de acceso a determinados bienes, servicios o condiciones básicas que son considerados fundamentales para el bienestar y el desarrollo humano.\nCentros de Apoyo Interdisciplinario a Víctimas de Violencia: Institución especializada que ofrece una variedad de servicios y recursos destinados a brindar apoyo integral a las mujeres que han sido víctimas de violencia.\nComité Dictaminador: Grupo conformado por expertos, profesionales o autoridades\nPrograma Tarjeta Violeta.\nDepositar: Poner o colocar (algo) en un lugar determinado. (ADICIONADO, P.O. 05 ALCANCE IV, 17 DE\nEdad Escolar Básica: Rango de edades durante el cual los niñas y niños suelen cursar la educación primaria y secundaria.\nElegible: Se puede elegir, o tiene capacidad legal para ser elegido. (ADICIONADO, P.O. 05 ALCANCE\nEl Secretario: Persona Titular de la Secretaría de Bienestar en el Estado de Guerrero.\nEmpoderamiento de las Mujeres: Proceso por medio del cual las mujeres transitan de cualquier situación de opresión, desigualdad, discriminación, explotación o exclusión a un estado de conciencia, autodeterminación y autonomía, el cual se manifiesta en el ejercicio pleno de sus derechos y libertades humanas.\nFormato Único: Documento requisitado por la Secretaría de Bienestar para acceder a un\nPrograma y quedar registrado en el Padrón de Mujeres Beneficiarias en términos de las presentes Reglas de Operación.\nMadre Jefa de Familia: Mujer que tiene la responsabilidad principal de proveer y cuidar de su familia, ya sea como única progenitora o como la principal figura a cargo del hogar.\nMunicipios con Alerta de Género: Aquellas localidades que han sido declaradas como áreas de alto riesgo o emergencia debido a la presencia de violencia de género sistemática y grave contra las mujeres.\nMujer Afromexicana: Persona con nacionalidad mexicana que desciende de mujeres y hombres que llegaron del continente africano. (ADICIONADO, P.O. 05 ALCANCE IV, 17 DE ENERO DE 2025).\nMujer Indígena: Persona que pertenece al pueblo que se asentó originalmente en un país o territorio y que conserva su cultura e identidad tradicional. (ADICIONADO, P.O. 05 ALCANCE IV, 17 DE ENERO DE\n2025).\nMunicipios con Alta Marginación: Localidad o población que presenta un conjunto de condiciones socioeconómicas y de desarrollo que indican un nivel significativo de desventaja y exclusión social para su población.\nPadrón de Mujeres Beneficiarias: Listado oficial de las mujeres beneficiadas por el presente\nPrograma.\nPobreza: situación en la cual una persona, familia o comunidad carece de los recursos materiales, sociales y/o económicos necesarios para satisfacer sus necesidades básicas y llevar un nivel de vida digno y adecuado.\nPrograma: Es el Programa de apoyo económico denominado “TARJETA VIOLETA” que ofrece el de familia en condición de vulnerabilidad.\nPrepa Violeta: Nombre que recibe el servicio que prestará el IMPE para conclusión de bachillerato\nRezago Social: Condición en la que ciertos grupos de la población, comunidades o regiones no tienen acceso equitativo a los recursos, servicios y oportunidades necesarios para alcanzar un nivel aceptable de bienestar y calidad de vida en comparación con el resto de la sociedad.\nSituación de Vulnerabilidad: Condición en la que se encuentra un individuo, grupo o comunidad que está expuesto a un riesgo elevado de sufrir daños, perjuicios o dificultades ante eventos adversos, crisis o situaciones desfavorables.\nRequisito: Circunstancia o condición necesaria para algo. (ADICIONADO, P.O. 05 ALCANCE IV, 17 DE\nENERO DE 2025).\nTarjeta Violeta: Es una tarjeta bancaria mediante la cual se brindará apoyo económico a las mujeres que cumplan con los criterios de selección de las presentes Reglas de Operación.\nSalud Mental: Condiciones físicas o psíquicas en que se encuentra un organismo en un momento determinado. (ADICIONADO, P.O. 05 ALCANCE IV, 17 DE ENERO DE 2025).\nTrámite: Documentación y procedimiento que se realiza y ampara la entrega de apoyo económico a las beneficiarias.\nTarjeta Bancaria: Medio de pago emitido por una entidad financiera a favor de un consumidor, a través de una cuenta asociada, que es aceptada en infinidad de comercios y establecimientos. (ADICIONADO,\nP.O. 05 ALCANCE IV, 17 DE ENERO DE 2025).\nVíctima de Violencia: Persona que ha experimentado algún tipo de daño, perjuicio, sufrimiento o trauma físico, psicológico o emocional como resultado de acciones violentas perpetradas por otra persona o grupo de personas.\nTutor: Tiene la custodia legal y física plena del menor y puede tomar todas las decisiones sobre\nVulnerable: Alguien puede ser herido o recibir una lesión física o moralmente. (ADICIONADO, P.O.\nSiglas:\nCAIV: Centro de Apoyo Interdisciplinario a Víctimas de Violencia.\nCECOSAMA: Centro Comunitario de Salud Mental y Adicciones. (ADICIONADO, P.O. 05 ALCANCE IV, CONEVAL: Consejo Nacional de Evaluación de la Política de Desarrollo Social.\nCUIS: Cuestionario Único de Información Socioeconómica.\nCURP: Clave Única de Registro de Población.\nCMIC: Cámara Mexicana de la Industria de la Construcción. (ADICIONADO, P.O. 05 ALCANCE IV, 17 DE\nDGPySPyAS: Dirección General de Planeación y Seguimiento de las Políticas y Acciones\nSociales.\nICATEGRO: Instituto de Capacitación para el Trabajo del Estado de Guerrero.\nIEEJAG: Instituto Estatal para la Educación de Jóvenes y Adultos de Guerrero. (ADICIONADO, P.O.\n05 ALCANCE IV, 17 DE ENERO DE 2025).\nINE: Instituto Nacional Electoral.\nINEGI: Instituto Nacional de Estadística y Geografía. (REFORMADO, P.O. 54 ALCANCE III, 05 DE JULIO\nDE 2024).\nIED: Inversión Estatal Directa.\nIMPE: Instituto Mexicano de Profesionalización Educativa. (ADICIONADO, P.O. 05 ALCANCE IV, 17 DE\nENERO DE 2025).\nITAIGRO: Instituto de Transparencia, Acceso a la Información y Protección de Datos Personales del Estado de Guerrero. (REFORMADO, P.O. 54 ALCANCE III, 05 DE JULIO DE 2024).\nMIR: Matriz de Indicadores de Resultados.\nSBGro: Secretaría de Bienestar.\nSCyTG: Secretaría de la Contraloría y Transparencia Gubernamental.\nSEFINA: Secretaría de Finanzas y Administración.\nSGG: Secretaría General de Gobierno.\nSTPS: Secretaría del Trabajo y Previsión Social. (ADICIONADO, P.O. 05 ALCANCE IV, 17 DE ENERO DE\n2025).\nUNEME: Unidades de Especialidades Médicas. (ADICIONADO, P.O. 05 ALCANCE IV, 17 DE ENERO DE\n2025).\nSEPLADER: Secretaría de Planeación y Desarrollo Regional.\n3. Objetivos y Alcances.\n3.1. Objetivo General.\nPromover el empoderamiento económico de las mujeres jefas de familia en situación de vulnerabilidad o mujeres que se encuentren en los CAIVS. La estrategia de atención será mediante un apoyo económico por transferencia monetaria bimestralmente.\n3.2. Objetivo Específico.\na) Mediante la implementación de este Programa, la SBGro busca generar oportunidades de desarrollo de las mujeres beneficiarias que viven en alguna situación de vulnerabilidad.\nb) Motivar e incentivar las capacidades de las mujeres mediante capacitaciones en desarrollo humano que puedan empoderarlas y ayudarlas en la generación de sus propios ingresos.\nc) Impulsar, a través del Programa, la mejora de las condiciones de equidad e igualdad de las mujeres para que, mediante el empoderamiento económico, puedan gozar de sus libertades económicas.\nd) Garantizar, mediante capacitaciones efectivas, el derecho de las mujeres a tener un trabajo digno.\ne) Impulsar y promover la igualdad de oportunidades laborales entre mujeres y hombres en localidades con mayor vulnerabilidad y rezago social.\nf) Generar las condiciones para que las beneficiarias puedan capacitarse en sus áreas de interés y conseguir certificarse para aumentar sus posibilidades de ingreso al mercado laboral.\ng) Atender eficientemente a las mujeres en situación de vulnerabilidad mediante el seguimiento a sus compromisos para acceder al apoyo económico bimestral.\nh) Atender la salud mental, la formación, la conducta de búsqueda de ayuda y prácticas de\ni) Facilitar la educación académica, para las beneficiarias con el objetivo que puedan concluir sus\n3.3. Cobertura.\nEl Programa tendrá una cobertura en 23 municipios del estado de Guerrero, siendo prioridad las mujeres mayores de 18 años hasta 59 años 11 meses que viven en alguna situación de vulnerabilidad, que sean mujeres jefas de familia o aquellas que se encuentren en los CAIVS. (REFORMADO, P.O. 05 ALCANCE IV,\n3.4. Alcances.\nEl El Programa al tener como objetivo beneficiar de manera directa mediante un apoyo económico a madres jefas de familia mayores de 18 años hasta 59 años 11 meses, y que viven en alguna situación de vulnerabilidad; busca que, mediante la entrega de una transferencia monetaria bimestral (máximo 4 depósitos por beneficiaria) se impulsen las libertades económicas como un derecho de la mujer guerrerense, en la mejora de sus condiciones y calidad de vida. Esto es, brindar a las beneficiarias oportunidades para capacitarse y así acceder a un empleo que les permita ir creando las condiciones necesarias para su empoderamiento, sobre todo, en las comunidades rurales, indígenas y afromexicanas en donde se profundiza y se desestima el trabajo y los roles que la mujer juega dentro de la sociedad.\n(REFORMADO, P.O. 05 ALCANCE IV, 17 DE ENERO DE 2025).\nPor tanto, se busca que mediante la entrega de dicho apoyo, se pueda impulsar el empoderamiento financiero para así generar libertades económicas; derecho que la mujer, principalmente en situación de vulnerabilidad, requiere para mejorar sus condiciones y calidad de vida, logrando así el derecho al trabajo y la seguridad social, entendida como los actos solidarios e inclusivos de las personas hacia los demás, pues estos llevan en si mismos a la búsqueda del bienestar social.\n4. Metas Físicas.\nCon la implementación del Programa se entregarán apoyos económicos a 20,000 madres jefas de familia de 18 años a 59 años 11 meses que viven en alguna situación de vulnerabilidad en el estado de\n5. Programación Presupuestal.\nDirecta (IED), para el ejercicio fiscal 2025, por un monto de $172.000.000.00 (Ciento Setenta y Dos\nMillones de Pesos 00/100 M.N.), mismo que se pretende aplicar de la siguiente manera:\nAPOYO ECONÓMICO PARA $160.000.000.00\nCiento Sesenta Millones de Pesos 00/100 m.n.\nBENEFICIARIAS\n$7.763.925.00\nCON DEPENDENCIAS Novecientos Veinticinco Pesos 00/100 m.n.\nGASTOS DE OPERACIÓN (3%) $5.188.575.00\nCinco Millones Ciento Ochenta y Ocho Mil\nQuinientos Setenta y Cinco Pesos 00/100 M.N.\n$172.952.500.00 Ciento Setenta y Dos Millones Novecientos\nCincuenta y Dos Mil Quinientos Pesos 00/100\nM.N.\nDe esta manera, se plantea ejercer la totalidad de los recursos de acuerdo a la programación, sin embargo, los recursos de IED están sujetos a la disponibilidad de los ingresos recaudados por la SEFINA, por lo que la calendarización y metas pueden variar:\nCalendarización presupuestal.\n(REFORMADO, P.O. 05 ALCANCE IV, 17 DE ENERO DE 2025).\nDEPEN PRESUPUESTO\nPROGRAMA / ACCION /\nFUENTE ENE FEB MAR ABR MAY JUN JUL AGO SEPT OCT NOV DIC\nDENCIA PROYECTO AUTORIZADO\nAPOYO ECONÓMICO PARA\nIED/25 SB $160,000,000.00 $\nBENEFICIARIAS\n$40,000,000.00 $ 40,000,000.00 40,000,000.00 $ 40,000,000.00\nCONVENIO DE\nIED/25 SB COLABORACIÓN CON $7,763,925.00 $7,763,925.00\nDEPENDENCIAS\nIED/25 SB GASTOS OPERATIVOS $5,188,575.00 $5,188,575.00\nTOTAL DEL PROGRAMA $172,952,500.00 $5,188,575.00 $47,763,925.00 $40,000,000.00 $40,000,000.00 $ 40,000,000.00\n5.1. Gastos de Operación.\nSe destinará el 3% de recurso del monto total del Programa, mismos que habrán de asignarse a las diversas acciones asociadas con la planeación, operación, supervisión, verificación, seguimiento y evaluación, dichas erogaciones serán congruentes con las partidas presupuestales dispuestas en el\nClasificador por Objeto del Gasto para la Administración Pública Estatal en vigor, principalmente para materiales, suministros y servicios, estudios e investigación, contratación de instructores (Secretaría de\nTrabajo, ICATEGRO, UNEME – CECOSAMA, IMPE, Y UAGro), promotores entre otros servicios y acciones que coadyuven a la operación y cumplimiento de las metas del Programa, observando en todo momento los criterios de racionalidad y austeridad presupuestal, propiciando la eficiencia, eficacia y\n6. Criterios y Requisitos de Elegibilidad.\nLas beneficiarias serán todas aquellas mujeres madres jefas de familia de 18 años a 59 años y\n11 meses que se encuentren en situación de vulnerabilidad por pobreza o violencia, de acuerdo a los datos arrojados por dependencias oficiales en la materia y que se definen en la sección 2.1.3 de las presentes\na) Criterios de Elegibilidad.\nPara beneficiarias:\n●Que sean mujeres mayores de 18 años hasta 59 años 11 meses al momento de publicarse la convocatoria; (REFORMADO, P.O. 05 ALCANCE IV, 17 DE ENERO DE 2025).\n● Ser mujer residente en el estado de Guerrero;\n● Ser mujer jefa de familia;\n● No haber recibido apoyos de algún programa de la SBGro en el último ejercicio fiscal (2023).\n● Si es el caso, que la beneficiaria se encuentre en un CAIV.\n● No contar con un ingreso mensual mayor a $10,000.00 pesos (Diez Mil Pesos 00/100 M.N.).\n●Aquellas mujeres interesadas en ingresar al programa no deben ser servidoras públicas a nivel municipal, estatal o federal o reciban algún tipo de prestación proveniente de recursos públicos.\n(ADICIONADO, P.O. 05 ALCANCE IV, 17 DE ENERO DE 2025).\n●No podrán participar beneficiarias con hijos en escuelas privadas. (ADICIONADO, P.O. 05 ALCANCE\nIV, 17 DE ENERO DE 2025).\n●Tutora legal de un menor. (ADICIONADO, P.O. 05 ALCANCE IV, 17 DE ENERO DE 2025).\n●Mujeres con alguna discapacidad, así como mujeres jefas de familia con algún hijo con\nPara Dependencias: municipal, así como con instituciones públicas o privadas que estén dispuestas a apoyar el Programa, deberán cumplir con los criterios de elegibilidad siguientes:\n● Que las dependencias, programas o entidades manifiesten que, dentro de su ámbito de influencia, cumplen con alguno de los criterios para la identificación de mujeres en situación de vulnerabilidad establecidos en el apartado 2.1.3 de las presentes Reglas de Operación\n● Deberá participar en todas las etapas del proceso en los que sea necesario involucrarse además de participar en la atención de la población beneficiaria bajo los criterios del presente ordenamiento.\n● Presentar toda la documentación y apoyo logístico o económico que pudiera ser requerido por la SBGro.\nPara esto, la SBGro dará prioridad a los ayuntamientos del estado de Guerrero, que muestren interés en participar y colaborar con el Programa con el objetivo de ampliar la cobertura y alcance del mismo por lo que se les convocará a las personas titulares de los ayuntamientos para que establezcan los términos bajo los cuales, pueden colaborar con la dependencia, siempre y cuando, se respeten los términos de operación y ejecución del Programa, por ello, participarán aquellos municipios, que logren cumplir con los preceptos establecidos, dando especial prioridad a los 9 municipios con Alerta de Violencia de Género contra las Mujeres por violencia feminicida.\nLos requisitos para participar en el Programa se establecerán según lo especificado en la sección\n2.1.3 de estas Reglas de Operación, sobre la Población Beneficiaria.\nb) Requisitos de Elegibilidad.\nPara la obtención de apoyos previstos en el presente ordenamiento, es necesario que las mujeres jefas de familia cumplan con los requisitos siguientes:\n1.- Mujeres en situación de vulnerabilidad por pobreza:\n● Participar en la convocatoria dentro de los tiempos y requisitos establecidos.\n● Prellenado de formato único y estudio socioeconómico (proporcionado por la SBGro) por parte de la beneficiaria. Si la solicitante no puede escribir, el personal de la SBGro se encargará de completarlo y la persona solicitante colocará su huella digital como firma.\n● Copia de la identificación oficial de la solicitante (INE, pasaporte, cédula profesional, licencia de manejo) actualizada. En caso de no contar con INE, presentar comprobante de trámite, teniendo 90 días naturales para entregar copia de ese documento de identificación actualizado.\n● Comprobante de domicilio o constancia de radicación de la solicitante, no mayor a 3 meses.\n● Copia de su Clave Única de Registro de Población (CURP).\n●Copia del Acta de Nacimiento de al menos una de sus hijas o hijos en nivel escolar básico y/o\n●Tener al menos una hija o hijo menor de edad, o tener guarda y custodio de un menor de edad\n(tutora), en nivel escolar básico y/o medio superior (hasta tercero de preparatoria) y presentar acta de\n●Presentar constancia de estudios o recibo de inscripción que acredite que la o el menor(es) se encuentra estudiando en el sistema educativo nacional. (REFORMADO, P.O. 05 ALCANCE IV, 17 DE ENERO DE\n2025).\n●Si la interesada o alguno de sus hijos presenta alguna discapacidad, presentar certificado médico\n●Estado civil: soltera. (ADICIONADO, P.O. 05 ALCANCE IV, 17 DE ENERO DE 2025).\nMedios de acreditación: (ADICIONADO, P.O. 05 ALCANCE IV, 17 DE ENERO DE 2025).\n1. Cruce con la Base de Datos del Registro Civil del estado de Guerrero.\n2. Presentar Constancia de soltería expedida en el H. Ayuntamiento de su adscripción residencial;\n3. Copia del acta de disolución del vínculo matrimonial o demanda de divorcio expedidos por la autoridad competente;\n4. Acta de defunción de la persona con la que haya contraído nupcias.\n2.- Mujeres en situación de vulnerabilidad por violencia (resguardada en los CAIVs):\n● Participar en la convocatoria dentro de los tiempos y requisitos establecidos.\n● Prellenado de formato único y estudio socioeconómico (proporcionado por la SBGro) por parte de la beneficiaria. Si la solicitante no puede escribir, el personal de la Secretaría se encargará de completarlo y la solicitante colocará su huella digital como firma.\n● Copia de la identificación oficial de la solicitante (INE, pasaporte, cédula profesional, licencia de manejo) actualizada. En caso de no contar con INE, presentar comprobante de trámite, teniendo 90 días naturales para entregar copia de ese documento de identificación actualizado.\n● Copia de su Clave Única de Registro de Población (CURP).\n● Tener al menos un hija o hijo menor de edad, o ser guarda y custodio de un menor de edad\n(tutora), en nivel escolar básico y presentar acta de nacimiento original.\n●Presentar constancia de estudios o recibo de inscripción que acredite que la o el menor(es) se encuentra estudiando en el sistema educativo nacional. (REFORMADO, P.O. 05 ALCANCE IV, 17 DE ENERO DE\n2025).\n●Si la interesada o alguno de sus hijos presenta alguna discapacidad, presentar certificado médico\n●Constancia de soltería expedida en el H. Ayuntamiento de su adscripción residencial; copia del acta de disolución del vínculo matrimonial o demanda de divorcio expedidos por la autoridad competente, Nota: En caso que la mujer jefa de familia, sea víctima de violencia en cualesquiera de sus formas, debe ser referida por alguna dependencia gubernamental y/o algún CAIV en el estado de Guerrero:\na) Deberá presentar carta del Centro de Albergue, Refugio o Centro de Adicciones, que contenga firma de la persona encargada y sello de la institución correspondiente y en la que se constate su situación de vulnerabilidad.\nb) Denuncia ante la autoridad competente, que avale la situación de violencia de la beneficiaria.\nPara fines de cumplimiento del presente Programa no se otorgará el apoyo a aquellas personas solicitantes que no cuenten con los documentos requeridos de selección.\n7. Tipo, Monto y Periodicidad del Apoyo.\nTipo Monto Periodicidad\nEconómico $ 2,000.00 Bimestral\nLos apoyos de este Programa serán otorgados únicamente por transferencia de fondos a la Tarjeta\nVioleta de cada beneficiaria. El apoyo es único e intransferible durante el presente ejercicio fiscal.\nLas mujeres que cumplan con los Criterios y Requisitos de Elegibilidad y selección serán apoyadas con máximo 4 depósitos de $2.000.00 (Dos Mil Pesos 00/100 M.N.) bimestrales cada una, para un total de\n$8.000.00 (Ocho Mil Pesos 00/100 M.N.) por beneficiaria. (ADICIONADO, P.O. 05 ALCANCE IV, 17 DE ENERO DE\n2025).\nEl apoyo es único e intransferible durante el presente ejercicio fiscal. (ADICIONADO, P.O. 05 ALCANCE\n7.1. Características de los Apoyos.\nEl apoyo se otorgará hasta en 4 pagos bimestrales por un monto de $2.000.00 (Dos Mil Pesos\n00/100 M.N.) a través de tarjeta bancaria y/o cualquier otro medio de pago electrónico, según sea el caso de obligaciones que tenga con el mismo o de operaciones bancarias automáticas, debiendo la beneficiaria realizar las conducentes directamente con la institución bancaria.\n7.2. Recursos no Devengados.\nEl presupuesto autorizado al Programa que no se haya aplicado a los fines autorizados, y los recursos que por cualquier motivo no se hayan devengado al término del ejercicio fiscal 2025, serán reembolsados a la Dirección General de Tesorería perteneciente a la SEFINA a más tardar el 31 de\n7.3. Resguardo de la Documentación.\nLa SBGro, a través de la DGPySPyAS, será la responsable de resguardar la información comprobatoria de los recursos ejercidos del Programa, así como de llevar a cabo el cierre del ejercicio fiscal.\n7.4. Supervisión y Control.\nLa supervisión y control se realizará de conformidad con lo establecido en el Decreto Número 203 del Presupuesto de Egresos del Estado de Guerrero para el Ejercicio Fiscal 2025. (REFORMADO, P.O. 05\nALCANCE IV, 17 DE ENERO DE 2025).\nLa SBGro en operación del Programa y para la mejora de éste, integrará de manera trimestral, los informes necesarios que a través de la DGPySPyAS deberá entregar a la SEFINA, SEPLADER, y a la\nSCyTG, informes sobre el presupuesto ejercido establecidos por el CONAC y con base en los indicadores de resultados previstos en estas Reglas de Operación. Dichos informes se deberán presentar a más tardar a los quince días hábiles posteriores a la terminación de cada trimestre.\nLa SBGro, será responsable de la supervisión directa de las acciones, así como de verificar que en su ejecución se cumpla con la normatividad aplicable.\n8. Criterios de Selección.\na) Para la determinación y dictamen del Padrón de Mujeres Beneficiarias final deberán considerarse los aspectos mencionados en el apartado 6 sobre los Criterios y Requisitos de Elegibilidad, sin embargo, para determinar la factibilidad y viabilidad de los apoyos y que éstos garanticen los objetivos establecidos deberán considerarse los aspectos siguientes:\n●El aspecto más relevante por el cual se tendrá que considerar la pertinencia o no de apoyar a alguna mujer solicitante deberá ser en todo momento sus condiciones socioeconómicas, y psicológicas.\n● Tener mínimo una hija o hijo menor de edad, o ser guarda y custodio de un menor de edad\n(tutora) en nivel escolar básico.\n● Estar resguardada en algún CAIV.\n● Por otro lado, se ponderará la ubicación de su domicilio y se determinará la focalización de la misma por el grado de marginación y vulnerabilidad, dando prioridad, preferentemente, a aquellas que habiten en localidades con mayor rezago social o índice de marginación y pobreza en el estado. También se deberá considerar si la solicitante tiene o no otra fuente de ingreso, además de contar o no con hijas y/o hijos y el número de ellos. Dándole prioridad a las madres solteras y con hijos que no cuenten con otra fuente de ingreso.\n● Serán consideradas como prioritarias las mujeres de extrema vulnerabilidad que tengan el status de víctimas, derivadas de la activación del Protocolo Violeta en el estado.\n● Serán consideradas como prioritarias las mujeres vulnerables en situación de desplazamiento forzado en el estado, de acuerdo a los términos establecidos por la SGG.\n● Si la beneficiaria cumple con todos los requisitos de elegibilidad pasará a ser parte del Padrón de Mujeres Beneficiarias. Para recibir las dispersiones del dinero deberá presentar y acreditar que está cumpliendo con las obligaciones dispuestas por las dependencias ejecutoras del Programa, mediante una certificación que valide la continuidad en el programa (ICATEGRO, IEEJAG y UNEME-CAPA).\n● La SBGro entregará a la postulante un carnet que la identificará como beneficiaria del Programa, mismo que se entregará cuando el Comité Dictaminador determine que cumple con todos los requisitos para ser beneficiaria del mismo.\nb) Finalmente, cualquier solicitud con especial atención que se considere necesario y porque, por causa de fuerza mayor, deba resolverse a favor de las mujeres solicitantes.\n8.1. Casos Especiales.\nEn los casos especiales por emergencia, casos fortuitos y/o de fuerza mayor o aquellos que por cuestiones de seguridad sanitaria o social se requiera efectuar pagos anticipados de los apoyos económicos o su reprogramación, ya sea en una zona en geográfica específica o en todo el estado, o aquellos que estén fuera de los lineamientos establecidos en las presentes Reglas de Operación, será la\nDGPySPyAS quien determinará su procedencia. (ADICIONADO, P.O. 05 ALCANCE IV, 17 DE ENERO DE 2025).\nLa SBGro establecerá un protocolo de comunicación claro para informar a las beneficiarias sobre cualquier interrupción en la entrega de tarjetas o depósitos retrasados. Se utilizarán diferentes canales de comunicación, como correo electrónico, mensajes de texto, redes sociales y anuncios en la página web\nDE 2025).\n8.2. Casos de Emergencia o Desastre.\nDeclaratoria de Emergencia o de Desastre, la SBGro podrá priorizar la asistencia a la población beneficiaria afectada por el desastre, anticipando la entrega de apoyos financieros y proporcionando ayuda humanitaria para abordar sus necesidades más urgentes causadas por la emergencia social o desastre natural.\nEn los casos especiales por emergencia, casos fortuitos y/o de fuerza mayor o aquellos que por económicos o su reprogramación, ya sea en una zona geográfica específica o en todo el estado, o aquellos que estén fuera de los lineamientos establecidos en las presentes Reglas de Operación, será la\nDGPySPyAS quien determinará su procedencia.\n8.3. Suspensión o Cancelación del Programa Social.\nLa SBGro podrá suspender o cancelar el Programa por las siguientes razones:\n● Si el Programa no cuenta con los recursos financieros necesarios para continuar operando, podría ser cancelado o suspendido temporalmente hasta que se obtengan los fondos necesarios.\n● Si se descubren irregularidades significativas o casos de fraude en la administración del\nPrograma, la autoridad competente puede optar por cancelarlo o suspenderlo mientras se investigan las denuncias.\n● Si las necesidades de la población objetivo cambian o disminuyen, podría justificar la cancelación o suspensión del Programa para asignar recursos a áreas de mayor prioridad.\n● En situaciones de desastres naturales o emergencias, los recursos pueden reasignarse temporalmente para hacer frente a la crisis, lo que podría resultar en la suspensión temporal del Programa.\n● Cambios en la legislación que rige el Programa pueden requerir ajustes o modificaciones que resulten en su cancelación o suspensión.\n8.4. Integración del Padrón de Personas Beneficiarias.\nLa SBGro podrá emitir uno o varios padrones de mujeres beneficiarias según sea el caso de la convocatoria. Se hará necesario integrar lo que se denominará como Comité Dictaminador, el cual, deberá integrarse por:\n● La persona titular de la SBGro, ● La persona titular de la Subsecretaría de Política Social de la SBGro, ● La persona responsable de la DGPySPyAS de la SBGro, ● Una representación o la persona titular de la Dirección General de Administración y Finanzas de la SBGro, así como;\n● La persona titular de la Unidad de Transparencia de la SBGro.\nUna vez que las personas solicitantes sean incorporadas al Padrón de Mujeres Beneficiarias, se dará a conocer de manera pública, siendo reservados sus datos personales, de acuerdo con la normatividad vigente; los cuales en ningún caso podrán emplearse para propósitos de proselitismo político, religioso o comercial, ni para ningún otro fin distinto al establecido en las Reglas de Operación del\nPrograma. electrónicos de los que dispone la SBGro, en las siguientes páginas web siguientes:\nInstitucional: https://www.guerrero.gob.mx/dependencia/sector-central/secretaria-del- bienestar/.\nFacebook: https://www.facebook.com/BienestarGro.\nInstagram: https://www.instagram.com/bienestar_gro/.\nX (antes Twitter): https://twitter.com/SBienestarGro.\n9. Mecánica Operativa del Programa Social.\n9.1. Instancia Ejecutora y/o Responsable.\nLas Instancias Ejecutoras serán: la SBGro, a través de la DGPySPyAS, quién será la responsable de la operación y ejecución del Programa. La ejecución del Programa será a través de la Convocatoria.\n(REFORMADO, P.O. 54 ALCANCE III, 05 DE JULIO DE 2024).\n9.2. Proceso de Incorporación al Programa Social.\nPara llevar a cabo un ejercicio y aprovechamiento eficaz y eficiente de los recursos, la SBGro, mediante la calendarización presupuestal señalado en el apartado 5 del presente Acuerdo de Modificación al Acuerdo por el que se crea el Programa Tarjeta Violeta y se Emiten sus Reglas de Operación, preverá que las aportaciones se realicen y ejerzan de manera oportuna, en apego a la normatividad aplicable.\n(REFORMADO, P.O. 54 ALCANCE III, 05 DE JULIO DE 2024).\nDeberá integrarse el equipo técnico de la DGPySPyAS que, en su momento, llevarán el control y registro de las solicitudes que fueron aceptadas por cumplir con los criterios de selección ya establecidos.\nUna vez cerrado el periodo de ingreso de solicitudes y analizadas las mismas, bajos los Criterios y Requisitos de Elegibilidad establecidos en las presentes Reglas de Operación, será responsabilidad de la DGPySPyAS presentar, en sesión plenaria, al Comité Dictaminador la propuesta. Una vez hechas las observaciones por parte del Comité Dictaminador a la propuesta de Padrón de Mujeres Beneficiarias, se estimará y aprobará, según sea el caso, el número de solicitudes que serán acreedores al apoyo, además, aprobarán, tantas veces sea necesario, los listados que abarquen el techo presupuestal del Programa hasta las fechas establecidas dentro de la convocatoria.\nPrograma así lo requiera, con el fin de alimentar adecuadamente el Padrón de Mujeres Beneficiarias. En las convocatorias se dará a conocer el objetivo del Programa, los requisitos que deberán cumplir las personas aspirantes, los criterios de selección, la dirección de los módulos o espacios donde se puede obtener mayor información, así como el listado de capacitaciones impartidas por ICATEGRO, también incluirá la dirección de internet donde se podrá ingresar la solicitud además de los datos de contacto como: número telefónico para pedir informes, fecha de apertura y cierre de ventanilla, por último, definirá la forma de entrega de resultados por conducto de los principales medios de difusión.\nLa información referente al Programa se podrá consultar de manera permanente en el Portal\nOficial del Gobierno del Estado.\nLa información y difusión se realiza a través de la publicación de la convocatoria en los diversos medios de comunicación que, para tal caso, tiene disponible la SBGro, principalmente:\nInstitucional: https://www.guerrero.gob.mx/dependencia/sector-central/secretaria-del- bienestar/.\nFacebook: https://www.facebook.com/BienestarGro.\nInstagram: https://www.instagram.com/bienestar_gro/.\nX (antes Twitter): https://twitter.com/SBienestarGro.\nPortal de Transparencia. (REFORMADO, P.O. 54 ALCANCE III, 05 DE JULIO DE 2024).\nDe igual manera, se puede solicitar información directamente en las oficinas de la SBGro, ubicada en el Recinto de las Oficinas del Poder Ejecutivo del Estado, Edificio Norte, Planta Baja, Boulevard René\nJuárez Cisneros No. 62, colonia Ciudad de los Servicios, C.P. 39074, Chilpancingo de los Bravo, Guerrero. establecidos en las presentes Reglas de Operación, estarán condicionadas a la disponibilidad presupuestal los requisitos señalados.\nFinalmente, las propuestas serán valoradas por el Comité Dictaminador, quien resolverá la pertinencia de autorizar los apoyos solicitados, siempre y cuando no contravengan los Criterios y Requisitos de Elegibilidad de las presentes Reglas de Operación.\nCuando las mujeres sean acreedoras del apoyo económico bimestral, se les hará entrega de un\nCarnet personalizado que las identificará como beneficiarias del Programa.\n10. Evaluación.\nLa SBGro, realizará una evaluación de resultados del Programa sujeto al Acuerdo de Modificación al Acuerdo por el que se crea el Programa Tarjeta Violeta y se Emiten sus Reglas de Operación, para lo cual tendrá la facultad de designar a la instancia que realizará dicho análisis. Si se realizan evaluaciones externas al Programa, serán coordinadas por la SCyTG. (REFORMADO, P.O. 54 ALCANCE III, 05 DE JULIO DE\n2024).\n10.1. Indicadores (Construcción de la Matriz de Indicadores para Resultados.\nAnexo 1).\nPrograma, se utilizarán los indicadores que se especifican en la MIR para el ejercicio fiscal 2025, publicada\n10.2. Seguimiento.\nEl seguimiento al desarrollo de las diferentes fases del Programa, lo realizará la SBGro, a través de la DGPySPyAS, para lo cual implementará una estrategia de seguimiento con base en la observancia del cumplimiento de los indicadores establecidos en la MIR.\n10.3. Auditoría.\nLa SBGro y la DGPySPyAS serán los responsables de la supervisión directa de las acciones, así como de verificar que en su ejecución se cumpla con la normatividad aplicable.\nLos recursos asignados para la operación del Programa podrán ser verificados por la SEFINA, la\nSCyTG, el órgano de fiscalización de las entidades paraestatales y la Auditoría Superior del Estado, y en el ámbito de sus respectivas competencias, realizarán actividades de fiscalización y auditoría.\nLa SBGro y la DGPySPyAS, darán todas las facilidades a las instancias fiscalizadoras para realizar en el momento que juzguen pertinente, las auditorías necesarias; asimismo, efectuará el seguimiento y la solventación de las observaciones planteadas por los órganos de control.\nLa inobservancia de esta disposición, independientemente de las sanciones a que haya lugar, limitará la ministración de los recursos estatales en el siguiente ejercicio presupuestal.\n11. Mecanismo de Entrega del Apoyo.\nLas mujeres beneficiarias, cuyos datos e información solicitada fueron verificados, validados y revisados por el Comité Dictaminador de la SBGro, que cumplan con los Criterios y Requisitos de Elegibilidad, establecidos en las presentes Reglas de Operación y convocatoria, recibirán el apoyo económico en hasta cuatro exhibiciones por medio de transferencia bancaria proporcionado por el Programa, condicionando dicho apoyo económico a la asistencia de las beneficiarias a las capacitaciones, talleres, atención en el área de salud, cursos y/o clases brindados por las dependencias participantes en el Programa.\n(REFORMADO, P.O. 05 ALCANCE IV, 17 DE ENERO DE 2025).\nPrioridad de selección: A fin de atender a las beneficiarias con mayor vulnerabilidad en el estado, se establece la siguiente prioridad de selección para acceder al Programa:\n● Mujeres jefas de familia con menores a cargo, que son víctimas de violencia en cualquiera de sus formas.\n● Mujeres jefas de familia que pertenezcan a pueblos originarios o personas de auto adscripción indígena en zonas rurales y urbanas del estado de Guerrero.\n● Mujeres jefas de familia con dependientes económicos en edad escolar básica que cuenten con discapacidad permanente o enfermedad crónica.\n● Mujeres jefas de familia con dos o más menores de edad bajo su custodia y resguardo.\n● Mujeres jefas de familia con más de tres carencias sociales.\n● Mujeres jefas de familia que se encuentren en Centro de Albergue, Refugio o Centros de\nAdicciones.\n● Mujeres en situación de vulnerabilidad.\n12. Derechos y Obligaciones de las Personas Beneficiadas.\nDerechos:\na) Recibir por parte de la SBGro, la información necesaria, de manera clara y oportuna, para participar en el Programa;\nb) Recibir un trato digno, respetuoso, oportuno y equitativo.\nc) Recibir atención sin costo alguno.\nd) A la reserva y privacidad de su información personal, de acuerdo a la Ley Número 207 de\nTransparencia y Acceso a la Información Pública del Estado de Guerrero y Ley Número 466 de Protección de Datos Personales en Posesión de Sujetos Obligados del Estado de Guerrero.\nObligaciones:\na) Una vez que la SBGro hace entrega de la tarjeta, la beneficiaria debe activarla ante la entidad bancaria correspondiente.\nb) Acudir puntualmente a las capacitaciones, talleres, atención en el área de salud, cursos y/o clases, en caso de no acudir, podrá ser motivo de cancelación del apoyo. (REFORMADO, P.O. 05 ALCANCE IV,\n17 DE ENERO DE 2025).\nc) Informar los cambios de domicilio y actualizar sus datos y documentación cuando proceda para los efectos a que dé lugar.\nd) Proveer, bajo protesta de decir verdad, la información necesaria para su incorporación al Padrón de Mujeres Beneficiarias y facultar a la SBGro para verificarla.\ne) Acudir a las oficinas de la SBGro a firmar el documento que se requiere para comprobar que la beneficiaria recibe el apoyo bimestralmente.\nf) Participar en las acciones de Contraloría Social para la vigilancia del buen funcionamiento del\nPrograma.\ng) Informar ante la SBGro, las fallas o irregularidades que se presenten en la entrega de los apoyos.\nh) Proveer, bajo protesta de decir verdad, la información necesaria para su incorporación al Padrón de Mujeres Beneficiarias y facultar a la SBGro para verificarla.\ni) Acudir a firmar el documento que se requiere para comprobar que la beneficiaria recibe el apoyo bimestralmente.\nj) Cumplir con el compromiso de corresponsabilidad.\nUna vez que se hace entrega de la Tarjeta Violeta a la beneficiaria, esta tiene la obligación de realizar la activación en el banco.\n12.1. Causales de Suspensión o Baja de las Personas Beneficiadas.\nEl incumplimiento de las obligaciones y compromisos establecidos en las presentes Reglas de\nOperación ameritarán la baja del Programa. Así mismo se consideran causales de baja las siguientes:\na) Cuando la persona solicitante haya mentido acerca de sus condiciones socioeconómicas o de cualquier otra índole con el objetivo de salir beneficiada.\nb) Cuando las beneficiarias no acaten las disposiciones de las presentes Reglas de Operación.\nc) Cuando se verifique que es receptora de otros programas de índole similar, ya sean federales o municipales.\nd) Cuando así lo determine la DGPySPyAS por no cumplir con la documentación mínima necesaria para hacer el trámite de apoyo.\ne) Cuando la beneficiaria no pueda ser contactada en los números telefónicos o referencias que proporcionó para notificarle sobre las capacitaciones y/o talleres que debe asistir.\nf) Cuando se constate que la beneficiaria trabaja o tiene un cargo en el Gobierno Federal, Estatal, Descentralizadas, Municipales, o en entidades donde estos tengan algún tipo de interés personal, familiar o empresarial.\ng) Aquella persona que, sin motivo justificado, no reciba el apoyo dentro de los treinta días naturales posteriores a su emisión, a pesar de haber sido informada sobre su disponibilidad, a menos que haya expresado por escrito antes de la fecha límite la imposibilidad de recoger su tarjeta bancaria.\nh) No presentarse a recibir la capacitación o taller autorizado en la fecha y hora señaladas.\ni) Por fallecimiento.\nj) Cuando se constate que la beneficiaria se encuentra casada, mediante una constancia de\nk) Y por cualquier otra causal que determine el Comité Dictaminador de la SBGro. (ADICIONADO, En caso que incurra en alguna de las siguientes causales, se podrá proceder con la cancelación y baja del Programa de las beneficiarias.\n1. Cuenta cancelada: la cuenta es cancelada por la beneficiaria en línea o por vía telefónica.\n2. Exceder el límite mensual máximo de $19,000.00 pesos (Diecinueve mil pesos 00/100 M.N.) autorizados como manejo de la cuenta por el banco, lo cual ocasiona que la cuenta bancaria bloquee el depósito del apoyo bimestral.\n12.2. Proceso de Baja.\nLa DGPySPyAS revisará las políticas y requisitos del Programa, recopilará la documentación necesaria, se comunicará con la beneficiaria sobre el motivo de la baja, completará y presentará la solicitud de baja siguiendo los procedimientos establecidos, dará seguimiento hasta obtener la confirmación oficial de la baja, actualizará los registros del Programa y notificará a otras partes involucradas según sea necesario.\n13. Instancias Participantes.\nLas instancias participantes del Programa serán:\n● SBGro, ejecutora del Programa\n● SEPLADER, dictaminadora de las presentes Reglas de Operación y autoriza los recursos del\nPrograma\n● SEFINA, liberará los recursos del Programa de acuerdo a la calendarización\n● Secretaría de Salud del Estado de Guerrero, ejecutora de las preconsultas psicológicas obligatorias para las beneficiarias\n●SCyTG, coadyuvante en las tareas de organización, control y evaluación del Programa\n● ICATEGRO, ejecutora del proceso de capacitación para las beneficiarias seleccionadas\n● CMIC, ejecutora del proceso de capacitación para las beneficiarias seleccionadas. (ADICIONADO, ● IEEJAG, ejecutor del proceso de educación básica para las beneficiarias seleccionadas.\n● IMPE, ejecutor del proceso de educación media superior para las beneficiarias seleccionadas.\n● UAGro, ejecutora del proceso de educación media superior y superior para las beneficiarias\n● UNEME - CECOSAMA, ejecutoras del proceso de salud emocional para las beneficiarias seleccionadas. (ADICIONADO, P.O. 05 ALCANCE IV, 17 DE ENERO DE 2025).\n● STyPS, ejecutora del proceso de vinculación laboral para las beneficiarias seleccionadas.\n(ADICIONADO, P.O. 05 ALCANCE IV, 17 DE ENERO DE 2025).\n● Unidad de Transparencia de la SBGro, garante y promotora del acceso del Programa a la información pública\n● Dirección de Administración y Finanzas de la SBGro, gestora financiera del Programa\n● DGPySPyAS de la SBGro, responsable del Programa y su ejecución\nLas entidades participantes incentivarán a las personas funcionarias públicas que participen en la ejecución del Programa a promover, respetar, proteger y asegurar el pleno ejercicio de los derechos humanos de las personas beneficiarias. Esto se realizará conforme a los principios de universalidad, interdependencia, indivisibilidad y progresividad, asegurando en todo momento un trato digno y respetuoso hacia las beneficiarias. Esto se llevará a cabo siguiendo criterios de igualdad y no discriminación.\n13.1. Instancia Normativa.\nLa SBGro, fungirá como la instancia administrativa y normativa del Programa, a través de la\nDGPySPyAS, en caso de requerirlo podrá contar con el apoyo de los organismos e instituciones de acuerdo a sus facultades, como pueden ser:\n● SCyTG.\n● Ayuntamientos municipales.\n● Fundaciones o sector privado.\n● Otras instancias del gobierno estatal o federal.\n14. Transparencia.\n14.1. Promoción y Difusión del Programa Social.\nInformación Pública del Estado de Guerrero, la SBGro, promoverá el Programa a través de los diferentes medios informativos:\nInstitucional:\nFacebook:\nInstagram: https://www.instagram.com/bienestar_gro/.\nX (antes Twitter): https://twitter.com/SBienestarGro.\nAdemás, en eventos, campañas y atención directa en la oficina central y las delegaciones, se proporcionará la información necesaria para que las personas interesadas conozcan los detalles de los apoyos, los requisitos requeridos y dónde presentarlos. Esto deberá ser comunicado en todos los casos, sin excepción, conforme a lo establecido en las Reglas de Operación actuales.\nTambién se contará con formatos y folletos en la DGPySPyAS y que se pueden acceder directamente en las oficinas de la SBGro que se ubican al interior del Recinto de las oficinas del Poder\nEjecutivo del Estado, Edificios Norte y Tierra Caliente Planta Baja, en el Boulevard René Juárez Cisneros, número 62, Colonia Ciudad de los Servicios en Chilpancingo de los Bravo, Guerrero.\n14.2. Contraloría Social.\n14.2. Contraloría Social.\nCon la finalidad de incrementar la participación ciudadana en cada una de las localidades donde habiten las beneficiarias del Programa, la DGPySPyAS podrá instalar de manera alterna un Comité de\nContraloría Social, que fungirá como un órgano ciudadano de control, vigilancia y evaluación de las actividades del Programa, conformado por personas habitantes de las localidades donde se hayan seleccionado beneficiarias, mismas que serán escogidas de entre la totalidad de las personas habitantes, con transparencia, eficiencia, eficacia, oportunidad, equidad, legalidad y honradez.\nLos objetivos específicos de este órgano de Contraloría Social son:\na) Hacer más transparentes las decisiones y la ejecución de los recursos;\nb) Incrementar la participación ciudadana;\nc) Fomentar la organización social;\nd) Inhibir los actos de corrupción y de cooptación social, política y electoral;\ne) Incrementar la eficiencia de los recursos públicos;\nf) Fortalecer la cultura de la legalidad, y\ng) Mejorar la rendición de cuentas.\nEl Comité de Contraloría Social, deberá vigilar y dar seguimiento a las acciones a través de los formatos que componen el expediente del Comité, el cual quedará integrado por:\na) Acta de conformación del Comité.\nb) Reunión con las personas beneficiarias.\nc) Ficha informativa del Programa.\nd) Cédula de vigilancia del Programa.\ne) Queja, denuncia, reclamo o reconocimiento.\nEl Comité debe estar constituido mínimamente por una presidencia, una secretaría y una vocalía, electos dentro de la localidad. El Comité deberá revisar los avances y resultados del Programa, así como la detección de cualquier presunta irregularidad.\nLa vocalía será el responsable de hacer llegar las quejas o denuncias recibidas a la SBGro, quien dará respuesta en un plazo no mayor de 15 días hábiles a partir de la fecha de recepción de la misma.\nPara impulsar la realización de las actividades de la Contraloría Social, la SBGro brindará capacitación y asesoría a las y los servidores públicos o personal que contrate y que intervengan en la operación del Programa, así como, a las personas integrantes de los Comités de Contraloría Social, para que éstos realicen adecuadamente sus actividades de seguimiento y vigilancia. De igual manera, se deberá integrar un programa de trabajo para la aplicación de las cédulas mencionadas.\n14.3. Protección de Datos Personales.\nLa información personal recolectada será utilizada para verificar el cumplimiento de los requisitos de elegibilidad para ser beneficiaria de este Programa. Además, esta información se incorporará en los de los tres niveles de gobierno en el ejercicio de sus facultades, compatibles o similares, para llevar a cabo verificaciones y mantener el Registro de Mujeres Beneficiarias. Por consiguiente, se asegura la protección información pública que sean aplicables. del Estado de Guerrero y Ley Número 466 de Protección de Datos Personales en Posesión de Sujetos\nObligados del Estado de Guerrero.\n14.4. Quejas y Denuncias.\nLa ciudadanía tiene el derecho de presentar quejas o denuncias sobre cualquier acción, acto u omisión que pueda afectar el ejercicio de sus derechos, así como también de presentar sugerencias,\na) En caso que se presente alguna queja o denuncia, la SBGro deberá recibirla para turnarla, en su caso y de acuerdo a la gravedad, a la Contraloría Social.\nb) La persona servidora pública que reciba una queja o denuncia deberá indicar a la ciudadana su nombre completo, cargo y área de adscripción, además de asentar por escrito la fecha y hora de recepción, con la finalidad de brindarle elementos de referencia para posibles aclaraciones. De igual manera para fines de dar inicio al trámite de la queja o inconformidad, la o el servidor público deberá pedir a la ciudadana quejosa: Identificación oficial y domicilio actual.\nc) El funcionariado público que reciba la queja o denuncia deberá realizar el seguimiento para asegurarse, en el ámbito de su competencia, que ésta haya tomado el cauce correspondiente.\nd) Si la queja proviene del trabajo de los comités de Contraloría Social, estos deberán cumplir los pasos siguientes:\n● Solicitar a la persona que le entregó la queja o denuncia, que le describa detalladamente el asunto que presenta.\n● Preguntar a la persona si tiene pruebas, y en caso afirmativo, deberá solicitarlas para entregarlas junto con la queja o denuncia.\n● Recibir la queja o denuncia y dar un acuse a la interesada o interesado.\n● Leer la queja y la información que se incluya en la misma.\n● Solicitar información a la autoridad competente, en caso de que así lo requiera, para que cuente con elementos de ambas partes que le permitan analizar el caso.\n● Verificar que realmente la queja sea procedente, es decir, confirmar si tiene sentido o fundamentos para que el Comité Dictaminador pueda brindar una respuesta a la persona interesada. financiamiento de responsabilidades administrativas, civiles o penales relacionadas con los programas sociales, deberá:\na) Presentarla, con la información previamente recopilada, al órgano de control estatal.\nb) Solicitar un número de registro con el que le reciben la queja o denuncia, así como preguntar y escribir el nombre de la persona a quien se la entregaron.\nc) Acudir, en el plazo establecido por la autoridad competente, para dar seguimiento a la respuesta que emita.\nd) Informar a la interesada o interesado sobre la respuesta que le brinde la autoridad.\nLas quejas o inconformidades de la ciudadanía derivadas de alguna irregularidad en la operación del Programa deberán realizarse por escrito y por comparecencia de la persona quejosa y/o interesada, misma que deberá presentarse en las oficinas de la SBGro sito en el Recinto de las Oficinas del Poder\nEjecutivo del Estado, Edificio Norte, Planta Baja, Boulevard René Juárez Cisneros No. 62, Ciudad de los\nServicios, C.P 39074, Chilpancingo de los Bravo, Guerrero.\n14.5. Acciones de Blindaje.\nLa SBGro, para la elaboración y ejecución de los recursos estatales que opera el Programa deberá observar y atender las medidas que emitan la Contraloría Social, el Instituto de Transparencia Acceso a la\nInformación y Protección de Datos Personales del Estado de Guerrero, el Instituto Electoral y de\nParticipación Ciudadana del Estado de Guerrero y las demás autoridades competentes, con la finalidad de prevenir que el uso y manejo de los recursos públicos y programas sociales se vean relacionados con fines partidistas y/o político-electorales; todo ello con la firme intención de garantizar los principios de imparcialidad y equidad durante los comicios; por lo que la papelería y documentación oficial del Programa deberá incluir la leyenda siguiente:\n“Este programa es público y ajeno a cualquier partido político. Queda prohibido el uso para fines distintos a los establecidos en el programa”.\n14.6. Acta de Donación. (Anexo 2)\nPara cada uno de las entregas del recurso a las beneficiarias, se suscribirá un Acta de Donación, en la que participará la SBGro, a través de la persona titular, y la persona beneficiaria. (REFORMADO, P.O.\n15. Perspectiva de Género. que sean reconocidas como actores económicos importantes, lo cual es crucial para el crecimiento y desarrollo de la sociedad. El desafío más importante que enfrentamos como administración es garantizar orientadas al desarrollo y bienestar social.\nEn este contexto, el Programa representa una medida afirmativa destinada a promover el empoderamiento económico de las mujeres que son jefas de familia. Esto contribuye directamente a la igualdad de género, la reducción de la pobreza y el crecimiento económico inclusivo, al tiempo que ayuda a combatir la violencia contra las mujeres.\n16. Enfoque de Derechos.\nLos derechos humanos de las mujeres abarcan todos los aspectos de la vida: la salud, la educación, la participación política, el bienestar económico, no ser objeto de violencia, por mencionar algunos de los más fundamentales. Las mujeres y las niñas tienen derecho al disfrute pleno y en condiciones de igualdad de todos sus derechos humanos y a vivir libres de todas las formas de discriminación, el empoderamiento económico de las mujeres contribuye a la reducción de los niveles de desigualdad y de pobreza, sobre todo de las mujeres en mayor situación de vulnerabilidad, como son las mujeres rurales e indígenas.\nEn este sentido, con el presente Programa contribuimos a garantizar el acceso de las mujeres a una vida libre de violencia ya que a través del empoderamiento se reduce la violencia económica.\nEn la aplicación del Programa, se harán valer los derechos de las personas beneficiarias tomando en consideración los factores de desigualdad que pudieran poner en riesgo de vulnerabilidad a personas que pertenecen a grupos históricamente discriminados, excluidos, invisibilizados como sujetos con derechos y libertades como lo son las mujeres, para que a través de la implementación de la presente política pública se reduzcan brechas de desigualdad y se promueva desde la SBGro un desarrollo incluyente, que siente las bases de un cambio verdadero desde una perspectiva del reconocimiento y ejercicio de los derechos y libertades.\n17. Acciones Contra el SARS-COV-2. ayuda, realizará campañas de concientización y prevención adaptadas a la pandemia, fomentará la coordinación interinstitucional para una respuesta integral y efectiva. Estas medidas buscan asegurar que las mujeres en situación de violencia puedan recibir apoyo y protección durante la crisis sanitaria, adaptando los servicios a las necesidades y desafíos específicos presentados por la pandemia.\n18. Anexos que reflejen la entrega del apoyo (Económico, Especie o Servicios).\nAnexo 1. MIR.\nAnexo 2. Acta de Donación.\nAnexo 1. MIR.\nFormato 4. MIR\nEje:\n1.Bienestar, Desarrollo Humano y Justicia Social.\nObjetivo:\n1.1. Reducir la Pobreza de los Guerrerenses.\nEstrategia: Línea de\n1.1.1. Aumento del Ingreso Económico de la Población en Situación de Pobreza, impulsando su integración al mercado 1.1.1.Impulsar apoyos para la\nAcción: implementación de proyectos productivos que fomenten el desarrollo de las\nMatriz de indicadores para Resultados\nResumen Narrativo Indicadores de desempeño Medios de Verificación Supuestos\nContribuir a mejorar el nivel de Mujeres de 18 a 59 años 11 INEGI (Encuesta Nacional sobre la Dinámica de las Riesgo de estigma y discriminación, bienestar de las mujeres de 18 a meses en situación de Relaciones en los Hogares ENDIREH 2021) falta de conciencia sobre los\n59 años 11 meses en situación de vulnerabilidad por pobreza y https://www.inegi.org.mx/cont programas disponibles. resistencia vulnerabilidad en el estado de violencia en el estado de enidos/programas/endireh/2021/doc/12 guerrero.pdf al cambio. desconfianza\nGuerrero, mediante apoyo Guerrero. institucional, limitaciones de acceso económico bimestral para recibir a recursos, falta de apoyo social, capacitación y lograr una mejor inadecuación cultural y limitaciones vida laboral. de infraestructura.\nLas mujeres de 18a 59 años 11 Mujeres de 18 a 59 años 11 INEGI (Encuesta Nacional sobre la Dinámica de las Riesgo de estigma y discriminación, meses en situación de meses en situación de Relaciones en los Hogares ENDIREH 2021) https: // falta de conciencia sobre los vulnerabilidad en el estado de vulnerabilidad por pobreza y www.Inegi.org. programas disponibles. resistencia\nGuerrero, mejoran su condición violencia en el estado de mx/contenidos/programas/endireh/2021/doc/12 al cambio, desconfianza\nPropósito (resultados) económica. terminan su Guerrero. guerrero.pdf institucional, limitaciones de acceso educación básica y se capacitan a recursos, falta de apoyo social, para el trabajo. inadecuación cultural y limitaciones de infraestructura.\nComponentes (Servidos C.1. Tarjeta violeta para apoyar a Porcentaje de mujeres de 18 a 59 Registro BDSBGRO. Informe de Pobreza y Evaluación Riesgos de fraude y corrupción, y Productos) mujeres jefas de familia en años 11 meses en situación de 2022 Guerrero CONEVAL desigualdades en el acceso al condición de vulnerabilidad por vulnerabilidad por pobreza o por https://www. coneval.org.mx/coordinación/enti programa. problemas de pobreza o por violencia. violencia en el estado de dades/Documents/lnforrnes_pobreza_evaluacion_2022/ identificación, inseguridad durante la\nGuerrero, apoyadas con la distribución, escasez de recursos, Tarjeta Violeta. Guerrero.pdf conflictos de interés local, INEGI (Encuesta Nacional sobre la Dinámica de las limitaciones tecnológicas y falta de\nRelaciones en los Hogares ENDIREH 2021) seguimiento y evaluación https://www.inegi.org.mx/contenidos/programas/ endireh/202\nA.1 Integración del Padrón de Porcentaje de expedientes Registros de la SBGro. Carencia de datos precisos\nBeneficiarías elegibles del Programa https://transparencia.guerrero.gob.mx y actualizados, la inoperabilidad de sistemas de recolección de datos, falla en los sistemas de seguridad para garantizar una integración efectiva de los datos.\nA.2 Entrega de Tarjetas Porcentaje de tarjetas entregadas Registros de la SBGro. Posibilidad de pérdida o robo de la a las beneficiarias https://transparencia.guerrero. gob.mx tarjeta, errores en la funcionalidad de la tarjeta, retrasos logísticos o administrativos, problemas de\nActividad es (Procesos) autenticación y verificación de datos que podrían afectar la distribución eficiente del apoyo.\nA.3 Supervisión y verificación de Porcentaje de capacitaciones real Registros de la SBGro. Posibilidad defraudes o falsificación recursos para realizar una supervisión exhaustiva, desafíos en la obtención de datos precisos sobre las actividades realizadas.\nAnexo 2. Acta de Donación\nPrimero. El presente Acuerdo entrará en vigor al día siguiente de su publicación en el Periódico\nSegundo. A partir de la entrada en vigor del presente Acuerdo, las Reglas de Operación del\nPrograma Tarjeta Violeta, subsecuentes o sus modificaciones serán emitidas por la persona titular de la\nSecretaría de Bienestar del estado de Guerrero, responsable directa de la operación y ejecución de estas.\nDado en el “Recinto de las oficinas del Poder Ejecutivo del estado”, el inmueble ubicado en el\nEdificio Centro, Boulevard René Juárez Cisneros No. 62, Código Postal 39074, Colonia Ciudad de los\nServicios, en Chilpancingo de los Bravo, capital del estado de Guerrero, a los veinte días del mes de mayo del año dos mil veinticuatro.\nLA GOBERNADORA CONSTITUCIONAL DEL ESTADO DE GUERRERO\nMTRA. EVELYN CECIA SALGADO PINEDA.\nRúbrica.\nLA SUBSECRETARIA DE GOBIERNO, ASUNTOS JURÍDICOS Y DERECHOS HUMANOS\nENCARGADA DE DESPACHO DE LA SECRETARÍA GENERAL DE GOBIERNO.\nDRA. ANACLETA LÓPEZ VEGA.\nRúbrica.\nEL SECRETARIO DE BIENESTAR DEL ESTADO DE GUERRERO.\nMTRO. PABLO ANDRE GORDILLO OLIVEROS.\nRúbrica.\nN. DE E. A CONTINUACIÓN, SE TRANSCRIBEN LOS ARTÍCULOS TRANSITORIOS DE LOS ACUERDO\nDE MODIFICACIÓN A LAS PRESENTES REGLAS DE OPERACIÓN.\nVIOLETA Y SE EMITEN SUS REGLAS DE OPERACIÓN.\nPrimero. El presente Acuerdo de Modificación entrará en vigor al día siguiente de su publicación\nSegundo. Se derogan todas las disposiciones que se opongan al presente Acuerdo de\nPrimero. El presente Acuerdo de Modificación entrará en vigor al día siguiente de su publicación\nSegundo. Se derogan todas las disposiciones que se opongan al presente Acuerdo de",
  "ordenamiento": "PROGRAMA",
  "jurisdiccion": "GUERRERO",
  "fuente_oficial": "DIARIO OFICIAL DE LA FEDERACION",
  "Fecha de Publicación": "17 DE ENERO DE 2025",
  "ULTIMA REFORMA PUBLICADA": null,
  "status": "VIGENTE",
  "es_escaneado": false,
  "tiene_tablas": true,
  "materia": [
    "general"
  ]
}