{
  "titulo": "Acuerdo por el Que Se Crea el Programa Salud y Bienestar Comunitario, y Se Emiten Sus Reglas de Oper",
  "Contenido": "FISCAL 2021\nOPERACIÓN DEL PROGRAMA DE SALUD Y BIENESTAR COMUNITARIO PARA EL PERIODO 2022, PUBLICADO EN EL\nTEXTO ORIGINAL.\nAcuerdo publicado en el Periódico Oficial del Gobierno del Estado, Edición Extraordinaria I, el\nJueves 03 de Junio de 2021.\nACUERDO POR EL QUE SE CREA EL PROGRAMA SALUD Y BIENESTAR COMUNITARIO, Y\nSE EMITEN SUS REGLAS DE OPERACIÓN PARA EL EJERCICIO FISCAL 2021.\nGuerrero.- Poder Ejecutivo.\nLICENCIADO HÉCTOR ANTONIO ASTUDILLO FLORES, GOBERNADOR CONSTITUCIONAL DEL\nESTADO DE GUERRERO, CON FUNDAMENTO EN LO DISPUESTO POR LOS ARTÍCULOS 4o DE LA\nSALUD; 3 DE LA LEY DE ASISTENCIA SOCIAL; 4 FRACCIÓN XVIII DEL PRESUPUESTO DE\nEGRESOS DE LA FEDERACIÓN PARA EL EJERCICIO FISCAL 2020; 40 DE LA LEY DE\nCOORDINACIÓN FISCAL; 71, 87, 88, 90 NUMERAL 2 Y 91 FRACCIONES I, IX Y XLVI DE LA\nLAS FACULTADES QUE ME CONFIEREN LOS ARTÍCULOS 2, 3, 6, 7, 10, 18 APARTADO A FRACCIÓN\nI, 20 FRACCIÓN III Y 45 DE LA LEY ORGÁNICA DE LA ADMINISTRACIÓN PÚBLICA DEL ESTADO\nDE GUERRERO NÚMERO 08; 15 DE LA LEY SOBRE EL SISTEMA ESTATAL DE ASISTENCIA SOCIAL\nNÚMERO 332; EN RELACIÓN CON EL ARTÍCULO 55 Y ANEXOS 21 Y 21-A DEL DECRETO NÚMERO\n644 DEL PRESUPUESTO DE EGRESOS DEL ESTADO DE GUERRERO PARA EL EJERCICIO FISCAL\n2021 Y LOS LINEAMIENTOS PARA LA ELABORACIÓN DE LAS REGLAS DE OPERACIÓN DE LOS\nPROGRAMAS SOCIALES ESTATALES PARA EL EJERCICIO FISCAL 2017ESTATALES PARA EL\nEJERCICIO FISCAL 2017.\nEn el Plan Estatal de Desarrollo 2016-2021 impulsa, un Guerrero que garantice el ejercicio efectivo de los derechos sociales de todos los guerrerenses, que vaya más allá del asistencialismo y que conecte al capital humano con las oportunidades que genera la economía, en el marco de una nueva productividad políticas públicas.\nLa Constitución Política de los Estado Unidos Mexicanos establece en su artículo 4o que la mujer y el hombre son iguales ante la ley. Esta protegerá la organización y el desarrollo de la familia. menos asistencialistas y más estructurales para garantizar el desarrollo de quienes menos tienen, a través profundos en este sector. Uno de los ejes que respaldan esta visión y se encuentra en el Plan Estatal de\nFISCAL 2021\nDesarrollo 2016-2021 es, el eje III.- Guerrero Socialmente Comprometido. Objetivo 3.7. Fortalecer la asistencia social a grupos vulnerables; implementando la Estrategia 3.7.1. Atender integralmente a los calidad de vida.\nLa Ley Número 479 del Sistema para el Desarrollo Integral de la Familia del Estado de Guerrero publicada en el Periódico Oficial del Gobierno del Estado número 61 del 02 de agosto de 1983, creó el\nSistema Estatal para el Desarrollo Integral de la Familia, como un organismo público descentralizado, el cual tiene por objeto I.- Promover el bienestar social y prestar al efecto servicios de asistencia social con apoyo en las normas que dicte la Secretaría de Salubridad y Asistencia y el Sistema Nacional para el\nDesarrollo Integral de la Familia, así como el propio Estado; II.- Apoyar el desarrollo de la familia y de la comunidad; III.- Fomentar la educación, para la integración social; IV.- Impulsar el sano crecimiento físico y mental de la niñez; 2 V.- Atender las funciones de auxilio a las instituciones de asistencia privada que le confíe la dependencia competente, con sujeción a lo que disponga la Ley relativa; VI.- Operar establecimientos de asistencia social en beneficio de menores en estado de abandono, de ancianos y de los minusválidos; VII.- Realizar estudios e investigaciones sobre los problemas de la familia, de los menores, de los ancianos y de los minusválidos; VIII.- Prestar servicios de asistencia jurídica y de orientación social de los menores, ancianos y minusválidos sin recursos; IX.- Intervenir en el ejercicio de la tutela de los menores, que corresponda al Estado, en los términos de la Ley respectiva; X.- Auxiliar al\nMinisterio Público en la protección de incapaces y de los procedimientos civiles y familiares que les afecten, de acuerdo con la Ley; XI.- Procurar permanentemente la adecuación de los objetivos y programas del sistema estatal, a los que lleve a cabo el sistema nacional, a través de decretos, acuerdos, convenios o cualquier figura jurídica encaminada a la obtención de bienestar social, y, XII.- Los demás que les encomienden las Leyes.\nLas personas titulares de las secretarías, dependencias y entidades de la administración pública estatal, así como, las servidoras y servidores públicos autorizados para ejercer recursos públicos del presupuesto de inversión de estas, serán responsables de los programas y proyectos de inversión que realicen. Que los apoyos otorgados deberán sujetarse a criterios de objetividad, equidad, transparencia, publicidad, selectividad y temporalidad.\nEl Presupuesto de Egresos de la Federación para el Ejercicio Fiscal 2021, contempla en un apartado que las erogaciones para el Ramo General 33 Aportaciones Federales para Entidades\nFederativas y Municipios, serán distribuidos conforme a lo previsto en el Anexo 28 de este Decreto, el cual se precisa en el Fondo de Aportaciones Múltiples erogaciones para asistencia social.\nEl artículo 55 del Decreto Número 644 de Presupuesto de Egresos del Estado de Guerrero, para el Ejercicio Fiscal 2021, establece y con el objeto de asegurar la aplicación eficiente, eficaz, oportuna inversión sujetos a reglas de operación.\nCon sustento en lo anterior, la Secretaría de Planeación y Desarrollo Regional, expidió los\nFISCAL 2021\nEn los que se establecen que los objetivos del Programa Salud y Bienestar Comunitario, deberá desarrollarse con independencia y plenitud, es por ello que surge este programa con el propósito de mitigar los impactos económicos sociales por las que atraviesan las personas que habiten en zonas rurales, mediante la entrega de proyectos productivos y de servicios.\nEn el Decreto Número 644 del Presupuesto de Egresos del Estado de Guerrero para el Ejercicio\nFiscal 2021 señala que se ejercerán los recursos bajo una política de gasto público, que permita dar cumplimiento a lo que globalmente prevén los ejes rectores del Plan estatal de Desarrollo 2016-2021.\nEn cumplimiento de lo anterior, se ha tenido a bien expedir el siguiente:\nACUERDO POR EL QUE SE CREA EL PROGRAMA SALUD Y BIENESTAR COMUNITARIO, Y\nSE EMITEN SUS REGLAS DE OPERACIÓN PARA EL EJERCICIO FISCAL 2021.\nArtículo 1. Se crea el Programa Salud y Bienestar Comunitario, el cual tiene por objeto contribuir a disminuir la desigualdad social entré los guerrerenses, respondiendo de manera cabal a sus expectativas de cambio; articuladora de esfuerzos, incluyente, con rostro humano.\nArtículo 2. Se emiten las Reglas de Operación del Programa Salud y Bienestar Comunitario, en los que se establecen los principios de eficiencia, eficacia, oportunidad, equitativa y transparencia de los recursos públicos y requisitos que se deben de cumplir para poder acceder ha dicho Programa.\nEn las Reglas de Operación se establecen disposiciones que instituyen la ejecución del Programa\nSalud y Bienestar Comunitario, con el objeto de otorgar transparencia y asegurar la aplicación, eficiente, eficaz, oportuno y equitativo de los recursos públicos asignados al mismo, los cuales deberán publicarse en el Periódico Oficial del Gobierno del Estado de Guerrero.\nArtículo 3. El Sistema para el Desarrollo Integral de la Familia del Estado de Guerrero tendrá a cargo la implementación, ejecución, evaluación y administración del Programa Salud y Bienestar\nComunitario, bajo los criterios de objetividad, equidad, transparencia, publicidad, selectividad y temporalidad, con estricto apego a la normatividad aplicable, por lo tanto, será el encargado de la dispersión y asignación de los recursos del Programa apegándose plenamente a las siguientes:\nEJERCICIO FISCAL 2021.\n1. Introducción.\n1.1. Antecedentes.\nFISCAL 2021\nLa carencia de oportunidades, la ausencia de capacidades y la marginación son escenarios desventajosos, que dan como resultado, entre otras problemáticas, una deficiente salud comunitaria, principalmente en las localidades de alta y muy alta marginación, y específicamente en poblaciones vulnerables. La salud comunitaria entendida como la combinación de habilidades, creencias y ciencias, dirigidas hacia el mantenimiento y la mejora de la salud de todas las personas de la comunidad, a través de la acción colectiva o social, para lograr un estado de completo de bienestar físico, mental y social (OMS,\n2004), considera un concepto amplio e integrador de la vida humana donde se defiende la vida, la naturaleza y el bien común. Por su parte, los determinantes sociales entendidos como las circunstancias en que las personas nacen crecen, viven, trabajan y envejecen, se consideran a su vez, como condicionantes de la salud comunitaria. Es así, que el problema central del Programa de Salud y Bienestar\nComunitario se enfoca en la existencia de determinantes sociales afectados, que limitan la salud comunitaria en localidades de alta y muy alta marginación. Para fines de este programa, los determinantes sociales serán abordados a través de los componentes de autocuidado, recreación y manejo de tiempo libre, gestión integral de riesgos, espacios habitables sustentables, alimentación correcta y local, economía solidaria, así como sustentabilidad.\nEl DIF Guerrero, a través de la Dirección de Asistencia Alimentaría y Desarrollo Comunitario, fomenta y promueve acciones que mitiguen la vulnerabilidad de las personas que son sujeto de asistencia social, y tiene como Intención apoyar y coordinar las acciones de desarrollo comunitario en las que participan los tres niveles de gobierno (Federal, Estatal y Municipal) dentro del ámbito de su competencia.\nEn este documento se sustenta la intervención institucional que desde el ejercicio 2020 ha venido atendiendo a la población en situaciones de vulnerabilidad, así mismo, se especifica la participación básica de llevar a cabo entre los Sistemas Municipales DIF, con el objetivo de realizar programas en coordinación, como el de Salud y Bienestar Comunitario, teniendo como prioridad la atención a aquellas familias en estado de vulnerabilidad social que habiten en localidades de alto y muy alto grado de marginación el cual tiene el propósito de fomentar el autoempleo y consumo como un elemento clave para que las familias que viven en condiciones de desventaja socioeconómica mejoren sus niveles de vida.\nEn consecuencia, la formulación de un programa de desarrollo social exige conjugar armónicamente todos los elementos que lleven a la materialización de sus objetivos, estrategias, metas y evaluación de resultados. Por ello, el programa de Salud y Bienestar Comunitario, es un programa social que permitirá disminuir el impacto del desempleo temporal, como una de las alternativas para enfrentar dicho fenómeno y brindará a los hogares mitigar los impactos económicos sociales, mismo que tiene su marginación, por lo que se atenderán aproximadamente a 12 grupos de desarrollo comunitario constituidos con un total de 300 personas, y crear fuentes de empleo y autoempleo que coadyuven en su ingreso familiar, como precedente de sustentabilidad labora atendiéndose a los 81 municipios que integran el\nEstado, dando prioridad a los municipios de alta y muy alta marginación. financieros, para llevar a cabo la adquisición de los materiales, insumos y productos necesarios en la\nFISCAL 2021 operatividad del Programa; así mismo se dará a conocer al Sistema Municipal DIF, las Reglas de Operación vigentes proporcionándose de forma calendarizada los suministros de los apoyos, para la operación y ejecución del mismo, la instancia ejecutora es el Sistema para el Desarrollo Integral de la Familia del Estado de Guerrero, a través de la Dirección de Asistencia Alimentaria y Desarrollo Comunitario, quien se coordinará con los Sistemas Municipales DIF para llevar a cabo la ejecución y seguimiento del Programa\nSalud y Bienestar Comunitario. El cual tiene contemplado una inversión de $2,400,000.00 (Dos millones cuatrocientos mil pesos 00/100 M.N.), recursos presupuestales que provienen del Ramo 33.-Aportaciones\nFederales para Entidades Federativas y Municipios, específicamente del Fondo de Aportaciones Múltiples\n(Asistencia Social).\nPara los efectos del Programa de Salud y Bienestar Comunitario, en las presentes Reglas de\nOperación se entenderá por:\nActa Constitutiva. Documento generado en Asamblea Comunitaria con vigencia de dos años, en el cual queda establecido el nombre, la edad, el domicilio y firma de quienes integran el Grupo de\nDesarrollo, sus funciones y la forma en que éste operará. Así como nombre, fecha y lugar de nacimiento, sexo, domicilio y firma de la persona representante del Grupo de Desarrollo.\nAsamblea Comunitaria. Reunión general de miembros de una localidad para decidir sobre asuntos relativos a la salud y el bienestar comunitario, tiene entre sus finalidades conformar un Grupo de\nDesarrollo, informar y tomar decisiones, así como darle seguimiento a las mismas.\nAutogestión Comunitaria. Proceso formativo que implica acciones participativas para la toma de decisiones individuales, familiares y colectivas en torno la salud comunitaria, y para disminuir la dependencia de las ayudas gubernamentales dirigidas a sobrevivir. Lo cual requiere la creación de alianzas y redes con otras organizaciones y participación en las estructuras de poder.\nAsistencia Social: Conjunto de acciones tendientes a modificar y mejorar las circunstancias de carácter social que impiden el desarrollo social del individuo, así como la protección física, mental y social de personas en estado de necesidad.\nCapacitación. Es el conjunto de actividades didácticas, orientadas a ampliar los conocimientos, habilidades y aptitudes, ya sea individuales o colectivas, de las y los participantes en el Programa de Salud y Bienestar Comunitario y que responde a las necesidades detectadas por las mismas Comunidades, se entiende como un proceso continuo y sistemático, con objetivos, fechas y horarios determinados. La planeación de una Capacitación se encuentra en una carta descriptiva.\nComité de Contraloría Social (CCS). Se constituye por la Población Atendida del Programa\nSalud y Bienestar Comunitario electa democráticamente e integrada de manera organizada, independiente, voluntaria y honorífica, su propósito es verificar la adecuada ejecución del Programa, la correcta aplicación de los recursos públicos asignados y el cumplimiento de las metas.\nComunidad. Personas que en conjunto habitan un espacio geográfico determinado, que generan un sentido de pertenencia e identidad social, que interaccionan entre sí, operando redes de comunicación\nFISCAL 2021 y apoyo mutuo, para lograr determinados objetivos, intereses, satisfacer necesidades, resolver problemas y desempeñar funciones sociales relevantes para su localidad.\nCONAPO. Consejo Nacional de Población.\nConvenio de Coordinación. Es el instrumento jurídico que suscriben el Sistema Nacional para el\nDesarrollo Integral de la Familia y los Sistemas Estatales para el Desarrollo Integral de la Familia para la asignación de recursos, con el objetivo de ejecutar un proyecto alineado al Programa de Salud y Bienestar\nComunitario.\nCuestionario de satisfacción de los apoyos recibidos. Es el instrumento a través del cual los\nGrupos de Desarrollo pueden manifestar su conformidad o inconformidad con los apoyos recibidos\n(capacitaciones e insumos para proyectos comunitarios).\nDesarrollo Comunitario. Proceso destinado a crear condiciones de progreso social y económico para toda la comunidad, con su participación y autoconfianza, siempre enfocado a la salud comunitaria y al bienestar DIF Guerrero: Sistema para el Desarrollo Integral de la Familia.\nDiagnóstico Participativo (DP): Es el ejercicio de reflexión de la realidad que llevan a cabo, en conjunto, el Grupo de Desarrollo y la Promotoría, basado en la metodología de planeación participativa, que permite identificar y priorizar sus problemáticas, y establecer alternativas de solución, todo ello como punto de partida para tomar decisiones encaminadas a mejorar la salud comunitaria.\nEconomía solidaria. Plantea la generación de ahorro o disminución de gastos a nivel familiar y comunitario, a través de iniciativas económicas en colectivo. Generalmente se expresa en acciones y proyectos que privilegian la colaboración y la contribución al bienestar común. Considera la gestión de financiamiento, insumos, capacitación y asistencia técnica, así como el rescate e inventiva de nuevas formas de intercambio basadas en el trueque.\nEstrategia Anual de Inversión Comunitaria (EAIC): Iniciativa en la que se detallan los proyectos sociales o productivos, las acciones de capacitación y asesoría técnica y sus respectivos requerimientos de financiamiento, que corresponden a las alternativas de acción colectiva que el GD ha identificado como prioritarios en su Programa de Trabajo Comunitario, pueden abarcar uno o más aspectos encaminados a modificar los determinantes sociales de la salud, de tal manera que incida significativamente en la creación de condiciones para la salud y el bienestar comunitarios.\nFocalización: Es asegurar que los beneficios de las acciones lleguen a las familias que más requieren las intervenciones públicas, para concentrar la atención sobre un determinado problema o necesidad.\nGrupos Vulnerables: Persona o grupo que por sus características de desventaja por edad, sexo, estado civil; nivel educativo, origen étnico, situación o condición física y/o mental; requieren de un esfuerzo\nFISCAL 2021\nGrupo de Desarrollo (GD): Es el conjunto de personas que se congregan y constituyen mediante asamblea como organización comunitaria, con el propósito de impulsar los trabajos para la salud y el bienestar de su localidad. Es conformado por personas que han decidido trabajar libre, gratuita y voluntariamente, sin discriminación por sexo, género, rango social, orientación sexual o cualquier otro motivo o circunstancia.\nPrograma: Programa Salud y Bienestar Comunitario.\nPrograma de Trabajo Comunitario (PTC). Es el documento que contiene la propuesta de trabajo del GD para el manejo y/o solución de las problemáticas identificadas en el Diagnóstico Participativo, en función de una visión integral que incluye las responsabilidades y tareas de los y las integrantes del GD.\nParticipación Social: Proceso que permite involucrar a la población, autoridades locales, instituciones públicas y a los sectores social y privado en la planeación, programación, ejecución y evaluación de los programas y acciones de salud, con el propósito de lograr un mayor impacto.\nPerspectiva de género: Considera el papel social y cultural de las mujeres, hombres, niñas, niños y adolescentes, a fin de promover la equidad e igualdad de oportunidades y responsabilidades en un programa determinado.\nPoblación objetivo: Población que un programa tiene planeado o programado atender para cubrir la población potencial y que cumple con los criterios de elegibilidad establecidos en su normatividad.\nPoblación potencial: Población total que presenta la necesidad o problema que justifica la existencia de un programa y que, por lo tanto, pudiera ser elegible para su atención.\nProyecto Comunitario: Es un plan de acción que considera actividades concretas, interrelacionadas y coordinadas entre sí, que se realizan con el fin de generar determinados bienes y servicios, orientados a satisfacer necesidades y/o resolver problemas colectivos. Los Proyectos\nComunitarios atienden temas relativos al logro de estilos de vida saludable por lo que pueden estar direccionados al auto-cuidado, a la recreación y manejo del tiempo libre, a la gestión integral de riesgos, a los espacios habitables sustentables, a la alimentación correcta y local, a la sustentabilidad y a la economía solidaria. Se dividen en proyectos sociales y proyectos productivos.\nReglas de Operación: Reglas de Operación del Programa Salud y Bienestar Comunitario.\nSalud Comunitaria: Se refiere a la combinación de habilidades, creencias y ciencias, dirigidas colectiva o social, para lograr un estado de completo bienestar físico, mental y social.\nSalud y Bienestar Comunitario: Para efectos de este programa, la salud y bienestar comunitario, es el estado de satisfacción de las necesidades de los integrantes de una comunidad, a través de la intervención en siete componentes: autocuidado de la salud, recreación y manejo del tiempo libre, gestión integral de riesgos, espacios habitables saludables, alimentación correcta y local, economía solidaria, así como sustentabilidad.\nFISCAL 2021\nSEDIF: Sistema para el Desarrollo Integral de la Familia.\nSEFINA: Secretaría de Finanzas y Administración.\nSEPLADER: Secretaría de Planeación y Desarrollo Regional.\n1.2. Alineación programática.\nEn cumplimiento a lo que globalmente prevén los ejes rectores del Plan Estatal de Desarrollo 20162021, este programa se alinea en el eje III.- Guerrero Socialmente Comprometido; Objetivos: 3.2. Edificar la Ruta hacia una Sociedad Equitativa e Incluyente y 3.7. Fortalecer la Asistencia Social a Grupos\nVulnerables; Estrategia: 3.2.1. Generar Programas de Desarrollo Comunitario por Medio de Procesos de\nParticipación Social y 3.7.1. Atender Integralmente a los Grupos Vulnerables y Fomentar el Acceso a los\nServicios de Protección Social que les permita Mejorar su Calidad de Vida, a través de fortalecer a los actores que promuevan el desarrollo social de los grupos en situación de vulnerabilidad y rezago y fomentar programas de generación de empleo de calidad dirigidos a los grupos poblacionales más vulnerables.\nLas presentes Reglas se alinean a lo estipulado en el Programa Estatal Sectorial “Desarrollo y\nAsistencia Social” 2016-2021, cuyo objetivo es atender a personas vulnerables, a través de desarrollar capacidades y habilidades de las familias con carencias alimentarias al proporcionar los apoyos necesarios que mejoren su calidad de vida y sus núcleos familiares, logrando fortalecer el tejido social en localidades vulnerables.\n1.3. Diagnostico.\nEl alto nivel de informalidad de la economía nacional y la marginación de numerosos municipios y localidades a lo largo de todo el país, provoca que la inestabilidad del empleo sea considerada como uno de los principales motivos de preocupación dentro de los hogares mexicanos; que la pérdida del empleo y la consecuente disminución de los ingresos aún de manera temporal tienen graves consecuencias sobre la pobreza, fundamentalmente porque la falta de empleo conduce a una importante disminución del capital económico familiar, mayor presión sobre los recursos naturales, así como el abandono de la educación y el fomento al endeudamiento, estas afectaciones frecuentemente persisten aun cuando sus miembros se reintegran a las actividades productivas y remuneradas. emergencias o por efecto de los ciclos productivos, afectando principalmente a la población de escasos recursos que enfrenta periódicamente etapas con una grave disminución en sus ingresos y patrimonio.\nEl DIF, Guerrero en concordancia con la Ley de Asistencia Social, concibe como servicio básico de salud la promoción de la participación consciente y organizada de la población, es decir, se privilegia una visión colectiva por lo que el concepto más acorde es la promoción de la salud comunitaria, entendida ésta como un derecho que trasciende el concepto de cuidado personal del equilibrio biológico, para abarcar\nFISCAL 2021 la relación entre los individuos y de éstos con el Estado, como integrantes de una comunidad, que son capaces de ejercer el derecho a participar, de conducirse con autonomía, de tomar decisiones y de demandar el acceso a servicios de salud de calidad. Por lo que se perfila como una estrategia institucionalizada para reducir la desigualdad, aumentar la prevención y fortalecer la capacidad de las personas para hacer frente a sus problemas y tomar decisiones que redunden en el control de sus procesos vitales.\nPor ello las políticas de empleo estatal deben considerar además del fomento a la creación de empleos formales e informales, la ejecución de acciones que permitan disminuir el impacto del desempleo temporal; una de las alternativas para enfrentar dicho fenómeno es la implementación del Programas y /o\nProyectos que brinden a los hogares el auto emplearse y/o generar empleo que mitiguen los impactos económicos sociales que viven; el diseño del Programa de Salud y Bienestar Comunitario implica que la población beneficiada debe participar en proyectos de beneficio familiar o comunitario como corresponsabilidad obligatoria para recibir los apoyos que se les otorgue; dicho requisito no solamente promueve la participación activa de los ciudadanos en el desarrollo de sus hogares y comunidades, sino que además genera beneficios adicionales al resto de la sociedad.\nDentro de los objetivos y estrategias que plantea el Ejecutivo Estatal, es el abatir la marginación y el rezago social que enfrentan los grupos sociales vulnerables para proveerles de igualdad en las oportunidades que les permitan desarrollarse con independencia y plenitud; asimismo, plantea elevar la productividad de las personas para que cuenten con mejores opciones de empleo e ingreso, que les permitan reducir sus niveles de pobreza.\nEl trabajo informal en países de economía subdesarrollada como México, está altamente asociada con el autoempleo, La carencia de plazas laborales que brinden una mayor seguridad salarial y mejores condiciones de trabajo orilla a casi el 60% de los buscadores de empleo a resolver por sí mismos su condición de desempleados y generalmente lo logran mediante pequeñas inversiones en el sector comercio y de servicios.\nEn el estado existen 895, 157 hogares de los cuales 293 086 están conformadas por Jefas de\nFamilias que es el 33% y 602 071, se conforman por Jefes de Familia que en términos porcentuales le corresponde el 67% razón por la cual el Sistema para el Desarrollo Integral de la Familia beneficiará a 300 personas integradas en 12 grupos de desarrollo comunitario en estado de vulnerabilidad que habiten en\nMunicipios o Localidades con alto o muy alto grado de marginación, considerando la suficiencia presupuestal para el ejercicio vigente y los criterios de focalización y priorización del programa, el cual propone, dar utilidad a estos recursos para mejorar la situación en la que se encuentran las familias guerrerenses introduciendo una alternativa más, tanto de ocupación como de alimentación, como generador de empleo y/o autoempleo.\nNuestra población potencial son todas las localidades de alta y muy alta marginación, de acuerdo con la publicación oficial “Índice de Marginación por Localidad 2010” del Consejo Nacional de Población\n(CONAPO). Ya que en nuestro Estado existen 35 municipios con alta marginación y 37 municipios con muy alta marginación. Los criterios de focalización serán los siguientes;\nFISCAL 2021\n1. Por lo que nuestra población beneficiada serán las Localidades de alta y muy alta marginación y que cuenten con un Programa de Trabajo Comunitario para recibir capacitaciones y/o proyectos comunitarios que fomenten su salud y el bienestar comunitario, Identificar las localidades de alta y muy alta marginación de acuerdo con CONAPO 2010.\n2. Contar con un diagnóstico exploratorio de las localidades seleccionadas para identificar el contexto y problemáticas generales en relación con los determinantes de la salud.\n3. Convocar una asamblea comunitaria para exponer el Programa de Salud y Bienestar.\nComunitario, en caso de que la comunidad acepte el Programa se constituye un grupo de desarrollo por medio de un acta constitutiva con al menos 15 integrantes y con una vigencia de no más de 2 años, en caso de que sea de continuidad o consolidación actualizar el acta cada 2 años.\n4. Contar con un Diagnóstico Participativo (DP) y un Programa de Trabajo Comunitario (PTC) con relación a los componentes de la salud y el bienestar comunitario con una vigencia no mayor a 2 años.\n2. Dependencia o entidad responsable del programa.\nLa instancia ejecutora será el sistema para el Desarrollo Integral de la Familia, a través de la\nDirección de Asistencia y Desarrollo Comunitario quien se coordinará con los Sistemas Municipales DIF para llevar a cabo la ejecución y seguimiento el cual tiene como fundamento legal para su implementación a los ordenamientos jurídicos siguientes:\n• Constitución Política de los Estados Unidos Mexicanos.\n• Ley General de Salud.\n• Ley de Asistencia Social.\n• Ley General para la Inclusión de las Personas con discapacidad.\n• Ley Número 817 para las Personas con Discapacidad del Estado.\n• Ley Número 479 del Sistema para el Desarrollo Integral de la Familia del Estado de Guerrero.\n• Ley Número 454 de Presupuesto y Disciplina Fiscal del Estado de Guerrero.\n• Ley Orgánica de la Administración Pública del Estado de Guerrero 08.\n• Ley Número 207 de Transparencia y Acceso a la Información Pública del Estado.\n• Ley 494 para la Igualdad entre Mujeres y Hombres del Estado de Guerrero.\n• Ley sobre el Sistema Estatal de Asistencia Social Número 332.\n• Decreto Número 196 por medio del cual la Sexagésima Primera Legislatura al Honorable\n2016-2021.\n• Programa Sectorial Desarrollo y Asistencia Social 2016-2021.\n• Decreto de Presupuesto de Egresos de la Federación para el ejercicio fiscal 2021.\n• Decreto Número 644 del Presupuesto de Egresos del Estado de Guerrero para el Ejercicio\nFiscal 2021.\nFISCAL 2021\n• Estrategia Local “Guerrero Contigo”.\n• Reglamento Interior del Sistema para el Desarrollo Integral de la Familia del Estado de\nGuerrero.\n• Manual de Organización del DIF Guerrero.\n• Y todos aquellos ordenamientos normativos aplicables.\n3. Objetivos y alcances.\n3.1. General.\nFortalecer los determinantes sociales de la salud y el bienestar comunitario en localidades de alta y muy alta marginación, mediante la implementación de proyectos comunitarios y el desarrollo de capacidades individuales y colectivas que permitan mejorar los estilos de vida saludable.\n3.2. Específicos.\n• Desarrollar conocimientos, habilidades y competencias en localidades de alta y muy alta marginación con Grupos de Desarrollo constituidos en materia de desarrollo social, humano y comunitario para fomentar la salud y bienestar comunitario, a través de capacitaciones.\n• Implementar proyectos comunitarios en localidades de alta y muy alta marginación con Grupos de Desarrollo constituidos para fomentar la salud y el bienestar comunitario.\n3.3. Alcances.\nLa implementación del programa de Salud y Bienestar Comunitario surge para mitigar y garantizar el empleo y/o autoempleo de las comunidades que atraviesan por esta situación atendiendo a su derecho al trabajo y a la alimentación a través de capacitaciones que ayuden a la implementación de proyectos productivos que logren mejor su economía familiar y comunitaria.\nLa cobertura de este programa serán Localidades de alta y muy alta marginación, de acuerdo con la publicación oficial “Índice de Marginación por Localidad 2010” del Consejo Nacional de Población\n(CONAPO), con Grupos de Desarrollo constituidos.\n4. Metas físicas.\nSe tiene programado realizar 24 capacitaciones a 12 grupos de desarrollo comunitario constituidos e implementando 7 proyectos productivos a igual número de grupos, que habiten en municipios y / o\nLocalidades de alta y muy alta marginación con vulnerabilidad social, y se encuentren en la publicación oficial “Índice de Marginación por Localidad 2010” del Consejo Nacional de Población (CONAPO).\n5. Programación presupuestal\nFISCAL 2021\nEn el Decreto número 644 del Presupuesto de Egresos del Estado de Guerrero para el Ejercicio\nFiscal 2021, señala que se ejercerán los recursos bajo una política de gasto público, que permita dar cumplimiento a lo que globalmente prevén los ejes rectores del Plan Estatal de Desarrollo 2016-2021. presupuestales provenientes del Ramo 33.- Aportaciones Federales para Entidades Federativas y\nMunicipios, específicamente del Fondo de Aportaciones Múltiples (Asistencia Social), el cual tiene una inversión de $ 2´400,000.00 (Dos millones cuatrocientos mil pesos 00/100 M.N.), para capacitaciones e implementación de proyectos productivos.\nENERO FEBRERO MARZO ABRIL MAYO\n2, 400,000.00 0.00 0.00 0.00 0.00\n6. Requisitos y procedimientos de acceso.\n6.1. Difusión.\nEl sistema para el Desarrollo Integral de la Familia a través de los diferentes medios de comunicación y de las redes sociales da conocer los diferentes programas y proyectos de asistencia social que ejecuta y opera en coordinación con las Direcciones que integran el Sistema; cuyos requisitos se encuentran en las oficinas ubicadas en Av. Rene Juárez Cisneros, Colonia Ciudad de los Servicios y en\nAv. Gabriel Leyva s/n esq. Ruffo Figueroa, Col. Burócratas, C.P. 39090, Chilpancingo, Guerrero, con un horario de atención de 8:00 am a 3:00 pm y/o los teléfonos 01(747) 4725595, 01(747)47256 00, 01(747)47\n25672 ext 1151 Y 1159. Así mismo al correo electrónico: alimentariadif@prodigy.net.mx, subdireccionalimentaria@prodigy.net.mx\nLas reglas de operación de los programas y/o proyectos son difundidas por personal capacitado de las Direcciones y en la página web del Portal del Gobierno del Estado, https://www.guerrero.gob.mx Se brinda atención a los 81 municipios del Estado, teniendo una capacidad de atención de niñas, niños y adolescentes, mujeres embarazadas, mujeres en periodo de lactancia, personas con discapacidad, adultos mayores y personas vulnerables por ingresos.\nLa papelería y documentación oficial para los programas deberán incluir la siguiente leyenda: “Este programa es público, ajeno a cualquier partido político. Queda prohibido el uso para fines distintos a los establecidos en el programa”. Todo el gasto en comunicación social relacionado con la publicidad que se adquiera para estos programas, por parte de las Dependencias y Entidades, así como aquél relacionado con los recursos presupuestarios federales que se transfieran a las entidades federativas, municipios y las electrónicos.\n6.2. Requisitos de acceso.\n1. Los interesados deberán presentar oficio de solicitud en las instalaciones del DIF Guerrero en escrito libre al Centro de Rehabilitación Integral Guerrero, con domicilio en Boulevard Lic. René Juárez\nFISCAL 2021\nCisneros S/N, Col. Ciudad de los Servicios, Chilpancingo, dirigido a la presidenta o Director General del\nDIF para ser considerado dentro del Programa, anexando copia fotostática de la siguiente documentación:\n1. Credencial de elector.\n2. CURP.\n3. Comprobante de Domicilio.\n2. La solicitud es turnada a la Dirección de Asistencia Alimentaria y Desarrollo Comunitario para su atención, quien en un plazo no mayor a 60 días hábiles dará respuesta a la misma.\n3. La Dirección de Asistencia Alimentaria y Desarrollo Comunitario aplica estudio socioeconómico.\n4. Contar con el Acta Constitutiva de la conformación del Grupo de Desarrollo.\n5. Disponer de un Diagnóstico Participativo y de un Programa de Trabajo Comunitario, que determine las necesidades de la población, así como las acciones y proyectos para fomentar la salud y bienestar comunitario, elaborados y suscritos por las personas que lo integran.\n6. El grupo de Desarrollo Comunitario deberá presentar programa de trabajo.\n7. Los proyectos comunitarios que contemplen animales de crianza deberán contar con un espacio adecuado y mantenimiento de éste.\n8. Se realiza la capacitación y la entrega del apoyo a los grupos de manera personal en el municipio, solicitando al mismo firme acta de donación que acredite el servicio y entrega.\nEn el programa Salud y Bienestar Comunitario, se debe considerar que el tipo de apoyo se otorgará mediante las siguientes dos modalidades, mismas que se otorgaran en una sola ocasión:\n• Integración de un Programa de Trabajo Comunitario: Que implique la aplicación de capacidades para tomar control sobre los determinantes sociales que afectan su salud y bienestar comunitario.\n• Detonar proyectos comunitarios, definiendo una Estrategia Anual de Inversión Comunitaria\n(EIAC).\n6.3. Procedimiento de acceso.\nLa operación de este, se realiza a través de la demanda ciudadana y / o peticiones que se reciben\nSistema Estatal, surge por la necesidad de atender el problema del desempleo y atendiendo la carencia alimentaria, el cual busca garantizar el derecho a la alimentación atendiéndose a los 81 municipios que conforman nuestro Estado, dando prioridad a los municipios de alta o muy alta marginación.\nEl DIF Guerrero, podrá presentar una serie de cursos, actividades, talleres y/o asesorías técnicas\n(con pertinencia cultural y adaptadas a las necesidades específicas de las personas considerando\nFISCAL 2021 condiciones de discapacidad), que le permitan a la población adquirir conocimientos, habilidades o destrezas en alimentación correcta y local, economía solidaria y sustentabilidad; así como darles seguimiento a los conocimientos adquiridos.\nSerán beneficiados, los solicitantes que cumplan con las siguientes características:\n1. Habitar en Municipios o Localidades de alto o muy alto grado de marginación\n2. Estar debidamente constituidos en grupos de desarrollo comunitario\nToda persona podrá conocer el estado de su trámite, y su aceptación o no de acuerdo con las reglas de operación vigentes. La población beneficiada será tratada con respeto, dignidad, además:\n• Recibir la información necesaria de manera clara y oportuna para participar en el programa.\n• Un trato digno y respetuoso oportuno con calidad y equitativo sin discriminación alguna.\n• Reserva y privacidad de su información personal.\nUna vez que las personas solicitantes son incorporadas al programa formaran parte del Padrón de beneficiarios, el cual será de carácter público, siendo reservados sus datos personales, de acuerdo con la Ley Número 207 de Transparencia y Acceso a la Información Pública del Estado de Guerrero; el acceso al Programa podrá ser a solicitud de la persona interesada, asimismo toda persona podrá conocer el estado de su trámite, y su aceptación o no.\nEl programa de salud y bienestar en concordancia con la Ley de Asistencia Social, concibe como servicio básico de salud la promoción de la participación consciente y organizada de la población, es decir, se privilegia una visión colectiva por lo que el concepto más acorde es la promoción de la salud comunitaria, entendida ésta como un derecho que trasciende el concepto de cuidado personal del equilibrio biológico, para abarcar la relación entre los individuos y de éstos con el Estado, como integrantes de una comunidad, que son capaces de ejercer el derecho a participar, de conducirse con autonomía, de tomar decisiones y de demandar el acceso a servicios de salud de calidad. Por lo que se perfila como una estrategia institucionalizada para reducir la desigualdad, aumentar la prevención y fortalecer la capacidad de las personas para hacer frente a sus problemas y tomar decisiones que redunden en el control de sus procesos vitales, por lo que el DIF Guerrero presentará talleres y/o asesorías técnicas (con pertinencia cultural y adaptadas a las necesidades específicas de las personas considerando condiciones de discapacidad), que le permitan a la población adquirir conocimientos, habilidades o destrezas en cada uno de los siguientes componentes: recreación y manejo del tiempo libre, economía solidaria y sustentabilidad; así como darle seguimiento a los conocimientos adquiridos.\n6.4. Requisitos de permanencia, causales de baja o suspensión temporal.\nPermanencia: Visita de seguimiento a los beneficiarios, con la finalidad de constatar la situación socioeconómica y seguimiento a las necesidades prioritarias, la población sujeta de atención deberá cumplir con:\n• Dar cumplimiento a las Reglas de Operación del Programa.\nFISCAL 2021\n• Utilizar los apoyos otorgados de manera adecuada y para los fines a los que se les otorgan y con que fueron autorizados evitando cualquier uso distinto de la misma, los cuales en ningún caso podrán emplearse para propósitos de proselitismo político, religioso o comercial, ni para ningún otro fin distinto al establecido en las Reglas de operación del programa social.\n• Permitir visita de verificación con la finalidad de validar la información proporcionada en sus expedientes correspondientes.\n• Facilitar los trabajos de supervisión, en cualquier momento después de haber recibido el apoyo.\nBaja: Falta de participación del grupo e inseguridad del municipio o localidad de origen del grupo\nLa población beneficiada del programa salud y bienestar comunitario, que incumplan en la Disposiciones\nNormativas de estas Reglas de Operación, perderán las prerrogativas establecidas en los numerales 6.2.y\n6.3.\n6.5. Modos de entrega del beneficio.\nLas capacitaciones serán impartidas en los lugares de origen y los apoyos de los proyectos productivos serán distribuidos directamente a los grupos beneficiados de las comunidades que se encuentran ubicadas en la publicación de oficial del “Índice de Marginación por Localidad 2010” de la\nCONAPO, en puntos sedes o en su caso, podrán acudir a las oficinas de la Dirección de Asistencia\nAlimentaria y Desarrollo Comunitario.\n7. Procedimientos de instrumentación.\n7.1. Operación.\n1. Los interesados deberán presentar oficio de solicitud en las instalaciones del DIF Guerrero en escrito libre al Centro de Rehabilitación Integral Guerrero, con domicilio en Boulevard Lic. René Juárez\nCisneros S/N, Col. Ciudad de los Servicios, Chilpancingo, dirigido a la presidenta o Director General del\nDIF para ser considerado dentro del Programa, anexando copia fotostática de la siguiente documentación:\n4. Credencial de elector.\n5. CURP.\n6. Comprobante de Domicilio.\n2. La solicitud es turnada a la Dirección de Asistencia Alimentaria y Desarrollo Comunitario para su atención, quien en un plazo no mayor a 60 días hábiles dará respuesta a la misma.\n3. La Dirección de Asistencia Alimentaria y Desarrollo Comunitario aplica estudio socioeconómico.\n4. Contar con el Acta Constitutiva de la conformación del Grupo de Desarrollo.\n5. Disponer de un Diagnóstico Participativo y de un Programa de Trabajo Comunitario, que determine las necesidades de la población, así como las acciones y proyectos para fomentar la salud y bienestar comunitario, elaborados y suscritos por las personas que lo integran.\nFISCAL 2021\n6. El grupo de Desarrollo Comunitario deberá presentar programa de trabajo.\n7. Los proyectos comunitarios que contemplen animales de crianza deberán contar con un espacio adecuado y mantenimiento de éste.\n8. Se realiza la capacitación y la entrega del apoyo a los grupos de manera personal en el municipio, solicitando al mismo firme acta de donación que acredite el servicio y entrega.\nEl Sistema Estatal DIF tendrá las siguientes responsabilidades:\na) Gestionar ante las instancias de Gobierno Federales y Estatales, los recursos financieros, para llevar a cabo la adquisición de los materiales, insumos y productos necesarios en la operatividad de los programas y / o proyectos.\nb) Dar a conocer al Sistema Municipal DIF, Reglas de Operación del programa de Salud y\nBienestar Comunitario.\nc) Proporcionar al Sistema Municipal DIF, de forma calendarizada las capacitaciones y los suministros de productos de los proyectos productivos.\nd) Vigilar y verificar que los proyectos sean otorgados directamente a las y los beneficiarios.\ne) Proporcionará almacenes regionales, para guarda, custodia de los productos que integran los proyectos; que contaran con personal capacitado para su manejo y distribución.\nf) Actualizar y profesionalizar los conocimientos del personal operativo del Sistema Estatal DIF y del Sistema Municipal DIF, a través de capacitaciones a fin de contar con las herramientas básicas para la operatividad de los programas y / o proyectos.\ng) Recepcionar de los Sistema Municipal DIF la información requerida para comprobación de los programas y / o proyectos con base a las Reglas de Operación vigentes.\nh) Procesará la información a que se refiere el punto anterior y remitirla de acuerdo con el calendario de entregas, a fin de comprobar los recursos canalizados al municipio.\ni) Elaborar a inicio de cada ejercicio fiscal, el Proyecto de los Programas y documentos que contemplarán la aplicación y operatividad con los importes correspondientes.\nSerán obligaciones del Sistema Municipal DIF las siguientes: a. El Sistema Municipal DIF se obliga a cumplir con la implementación de los Proyectos productivos que se tienen establecidos en la Subdirección de Desarrollo Comunitario y en las reglas de operación que regula el programa; salvo la pena de incurrir en responsabilidades administrativas. b. Determinará de manera conjunta la población potencial de su municipio tomando en consideración el tipo de beneficiario de todos los programas a solicitar, con esta información y en coordinación con el Sistema Estatal DIF, atenderá a la población que se encuentre en situación de vulnerabilidad de localidades de alta y muy alta marginación. c. Integrará y enviará los expedientes, así como los padrones físicos de las y los beneficiarios de los Programas y / o Proyectos solicitados a la Subdirección de Desarrollo Comunitario, de igual forma aplicables.\nFISCAL 2021 d. Integrará los padrones de los beneficiarios y / o beneficiarias con sus respectivos expedientes de los programas y / o proyectos objeto de estas Reglas. Remitiendo al Sistema Estatal DIF el padrón físico y en digital, así como los expedientes correspondientes y comprobación de estos. e. Designar personal (promotor) del Sistema Municipal DIF que realice las funciones de seguimiento y supervisión de los Programas y / o Proyecto. f. Participar en acciones de apoyo logístico para la distribución de los programas y / o Proyecto. g. Es competencia del Sistema Municipal DIF, trasladar los materiales que corresponden a los programas, a las comunidades beneficiadas, en una unidad vehicular. Será responsabilidad del municipio el resguardo y el buen uso de los materiales que se recepcionen, en el entendido que, de existir algún desvío de estos, el Sistema Estatal DIF cancelará inmediatamente el suministro del programa y / o Proyecto e iniciará un procedimiento ante la contraloría interna del sistema estatal, para determinar las sanciones a que sean acreedores.\nPara garantizar la atención completa del beneficiario, se realizan las acciones:\n• Determinar el tipo de proyectos a implementar\n• Adquisición de los materiales y que cumplan con las Especificaciones Técnicas de Calidad.\n• Asegurar el correcto almacenamiento y distribución de los materiales, hasta su entrega al beneficiario.\n• Focalizar los beneficiarios de los Programas con base a los indicadores socioeconómicos.\n• Coordinar la entrega de apoyos a la población beneficiada con los Sistemas Municipales DIF, a través de convenios de colaboración y conforme a lo establecido en las Reglas de Operación.\n• Promover la participación social a través de los Sistema Municipal DIF en la formación de comités entre la población beneficiaria, para la recepción, entrega y vigilancia de los apoyos.\n• Promover la formación y operación de grupos de contraloría social para el seguimiento del proyecto.\n• Fortalecer la operación de los programas y / o proyectos promoviendo la inclusión general de la sociedad.\nLos datos de la población beneficiada, así como la información generada y administrada se regirán por la Ley Número 207 de Transparencia y Acceso a la Información Pública del Estado de Guerrero.\nComo objetivo a corto plazo, se dará continuidad a la entrega de cada apoyo solicitado, cubriendo cada uno los requisitos solicitados en las presentes reglas de operación, mismo que será otorgado en su municipio de residencia o en su caso en el almacén general del Sistema Estatal, por otra parte, cabe mencionar que los tramites y formatos a realizar son gratuitos. resueltos en coordinación con las dependencias involucradas como son SEFINA, por la transferencia de por el SARS COV 2.\n7.2. Gastos de operación.\nFISCAL 2021\nMúltiples, no contempla Gastos de Operación.\n8. Transparencia.\n8.1. Difusión.\nLa Dirección de Asistencia Alimentaria y Desarrollo Comunitario, quien es la responsable de la operación del Proyecto Salud y Bienestar Comunitario difundirá a través de los diferentes medios de comunicación; trípticos, periódico, redes sociales la información relacionada con las características de este.\nAsí mismo se dará amplia difusión a nivel Estatal promoviéndose similares acciones por parte de las autoridades locales; y dándose a conocer en la página de internet del Gobierno del Estado, https://www.guerrero.gob.mx la información desagregada por municipio, barrio o zona urbano-marginada, proyecto y nombre de la población beneficiada; las copias de los expedientes estarán disponibles oportunamente para su consulta en las oficinas ubicadas en Av. Rene Juárez Cisneros, Colonia Ciudad de los Servicios y Av. Gabriel Leyva s/n esq. Ruffo Figueroa, Col. Burócratas, C.P. 39090, Chilpancingo, Guerrero; por otra parte la papelería, documentación oficial, así como la publicidad y promoción del\nProyecto, deberán incluir la leyenda descrita en el apartado de \"Blindaje Electoral\".\nUna vez autorizadas estas Reglas de Operación, por las instancias correspondientes, estarán disponibles para su consulta en las Oficinas de la Dirección de Asistencia Alimentaria y Desarrollo\nComunitario, quien es la responsable directo de la ejecución, a través de la Subdirección de Desarrollo\nComunitario, ubicada Av. Gabriel Leyva s/n esq. Ruffo Figueroa, Col. Burócratas, C.P. 39090, Chilpancingo, Guerrero., a los teléfonos (01747) 47 2 55 95, (01747) 47 2 56 00, (01747) 47 2 56 72 ext. 1155. Así mismo al correo electrónico: subdescomdif@prodigy.net.mx y http://www.dif.guerrero.gob.mx\nLa información generada y ministrada como montos y población beneficiada deberá ser publicada en los términos de la Ley No. 207 de Transparencia y Acceso a la Información Pública del Estado de\nGuerrero. Así mismo estas reglas cumplen con Ley General de Transparencia y Acceso a la Información\nPública y el artículo 27 del PEF 2021.\n8.2. Blindaje electoral.\nLa operación y ejecución de los recursos destinados al Proyecto deberán observar y atender las medidas que emita la Secretaría de Contraloría y Transparencia Gubernamental e Instituto Nacional\nElectoral, para coadyuvar a que éstos, no sean utilizados con fines políticos; por lo que la papelería, documentación oficial, así como la publicidad y promoción del Programa deberán incluir la siguiente leyenda: \"Este Proyecto es público, ajeno a cualquier partido político. Queda prohibido el uso para fines distintos a los establecidos en el mismo”\n8.3. Supervisión y control. la Dirección de Planeación del DIF Guerrero, las acciones ejercidas y los resultados obtenidos, del proyecto\nSecretaria de Finanzas y Administración, Secretaria de Planeación y Desarrollo Regional y la Secretaria\nFISCAL 2021 de Contraloría y Transparencia Gubernamental, informes sobre los avances físicos financieros sobre el presupuesto ejercido establecidos por el Consejo Nacional de Armonización Contable (CONAC) dichos trimestre. Y por último se deberá integrar el cierre de ejercicio sobre los recursos ejercidos durante el ejercicio fiscal 2021, especificando si las metas fueron concluidas al 100%\nLos padrones de los beneficiarios serán requisitados por los Sistemas Municipales DIF, remitiendo para su revisión a este Sistema Estatal DIF el padrón de forma física y digital de la dotación entregada para la integración de los Padrones de Beneficiarios de los 81 municipios de la Entidad mismo que serán remitidos a las instancias o dependencias operadoras.\n8.4. Mecanismos de evaluación e indicadores.\n8.4.1. Evaluación. correspondientes. Así mismo dará seguimientos de los resultados esperados del programa.\n8.4.2. Indicadores.\nMatriz de Indicadores para Resultados\nFISCAL 2021\nFISCAL 2021\nFISCAL 2021\n8.5 auditoria aplicables como son la Auditoria Superior de la Federación y la Secretaría de la Función Pública, la legislación vigente y en el ámbito de sus respectivas competencias.\nEl Sistema DIF Guerrero dará todas las facilidades a dichas instancias como órganos fiscalizadores para realizar, en el momento en que lo juzguen pertinente, las auditorías que consideren necesarias; así como el seguimiento y la solventación a las observaciones planteadas por los órganos de control.\n8.6. Recursos no devengados. y aquellos que por cualquier motivo no estuviesen devengados al 31 de diciembre del presente ejercicio fiscal.\n8.7. Contraloría social\nCon la finalidad de incrementar la participación ciudadana, se crearán Comités de Contraloría Social, como un órgano ciudadano de control, vigilancia y evaluación de las actividades del programa de salud y\nFISCAL 2021 bienestar comunitario, conformados por las y los beneficiarios, los sectores sociales, y los representantes de la localidad, quienes de manera específica supervisarán la gestión gubernamental, y que los manejos de los recursos públicos se realicen en términos de transparencia, eficacia, legalidad y honradez. Los objetivos específicos de este Órgano de Contraloría Social son:\n• Hacer más transparentes las decisiones y la ejecución de los recursos.\n• Incrementar la participación ciudadana.\n• Fomentar la organización social.\n• Inhibir los actos de corrupción y de cooptación social, política y electoral.\n• Incrementar la eficiencia de los recursos públicos.\n• Fortalecer la cultura de la legalidad.\n• Mejorar la rendición de cuentas.\n• Perfeccionar la democracia e incorporar la evaluación ciudadana.\nLas funciones de los Comités de Contraloría Social son:\na) Integración: Se conforman con la representación de la comunidad beneficiada por el Programa, y fungirán como interlocutores con el DIF Guerrero, en el ejercicio de la contraloría social. El vocal será, el responsable de hacer llegar las quejas o denuncias recibidas al DIF Guerrero, quien dará respuesta en un plazo no mayor de 15 días a partir de la fecha de recepción de la queja o denuncia.\nb) Capacitación y asesoría: Para impulsar la realización de las actividades de Contraloría Social se brindará capacitación y asesoría, a los servidores y servidoras públicas que intervienen en la operación del Programa, así como a los integrantes de los Comités Locales, para que estos realicen adecuadamente sus actividades de seguimiento y vigilancia.\nc) Seguimiento: Se deberá integrar un Programa de Trabajo a través del cual se debe incluir la descripción de las actividades, responsables, metas y calendarización de las actividades para su cumplimiento.\nEl Director General o el personal que designe el DIF Guerrero, serán los encargados de conformar los Comités de Contraloría Social, asimismo darán acompañamiento durante las actividades de control, seguimiento y vigilancia del programa.\nEl Comité de Contraloría Social debe estar constituido por un presidente, un secretario y un vocal mínimamente, electos de entre la población beneficiada tendrá que ser vigilado por un solo Comité, el cual deberá controlar, vigilar y dar seguimiento a través de los formatos que integran el expediente comunitario, los cuales son:\n1. Acta de Conformación del Comité de Contraloría Social.\n2. Reunión con beneficiarios y beneficiaras.\n3. Ficha Informativa del Programa.\n4. Cédula de Vigilancia del Programa.\n5. Actividades de Difusión y Capacitación.\nFISCAL 2021\n6. Quejas, Denuncias o Reconocimientos.\n7. Informe Anual.\n8.8. Formas de participación social. de Guerrero, se establece que la sociedad podrá participar activamente en la Planeación, Programación, Implementación y Evaluación del programa de salud y bienestar comunitario, por lo que la población beneficiada participara en la etapa de la implementación y podrán supervisar la gestión gubernamental, y que el manejo de los recursos públicos se realicen en términos de transparencia, eficacia, legalidad y honradez de acuerdo en lo estipulado en estas Reglas de Operación.\nParticipantes Etapa en la que Forma de Modalidad participa Participación\nPoblación Beneficiada Implementación Comités de Contraloría Seguimiento\n8.9. Procedimiento de queja o inconformidad ciudadana.\nLa población beneficiada podrá presentar quejas y denuncias ante las instancias correspondientes sobre cualquier hecho, acto u omisión que produzca o pueda producir daños al ejercicio de sus derechos establecidos en las presentes reglas o contravengan sus disposiciones y de la demás normatividad aplicable.\n• En el Sistema DIF Guerrero\nCorreo electrónico: buzon.dif@guerrero.gob.mx\nDomicilio: Centro de Rehabilitación Integral Guerrero.\nBoulevard Lic. René Juárez\nCisneros S/N, Col. Ciudad de los Servicios. Chilpancingo, Guerrero. C.P. 39095.\n• En la Secretaría de Contraloría y Transparencia\nGubernamental.\nTeléfonos: (474) 47 1 97 41\nPrimer Piso Edificio Norte, Blvd. René Juárez Cisneros 62 Col. Ciudad de los Servicios. Chilpancingo, Guerrero. C.P. 39075. proyecto podrán presentarse por escrito, por comparecencia de la población beneficiada beneficiario y / o beneficiaria, por correo electrónico o vía telefónica y deberá proporcionar los siguientes datos:\n• Nombre del servidor público.\nFISCAL 2021\n• Área de adscripción.\n• Objeto de la denuncia.\n• Nombre y domicilio del quejoso.\n• Identificación oficial.\n8.10. Mecanismos de exigibilidad.\nLos casos en los que se podrán exigir los derechos por incumplimiento o por violación de estos pueden ocurrir en al menos los siguientes casos:\n1) Cuando una persona solicitante cumpla con los requisitos y criterios de inclusión para acceder a determinado derecho.\n2) Cuando la persona solicitante exija que se cumpla con dicho derecho de manera integral en tiempo y forma.\n3) Cuando no se pueda satisfacer toda la demanda de incorporación al programa por restricción presupuestal.\nSerá la Secretaría de Contraloría y Transparencia Gubernamental del Gobierno del Estado quién atenderá las denuncias de violación e incumplimiento de derechos en materia de Desarrollo Social.\n8.11. Acta de entrega – recepción.\nLa Dirección de Asistencia Alimentaria y Desarrollo Comunitario y resguardará el expediente de la población beneficiada, incluyendo su acta de donación correspondiente, dada la naturaleza del apoyo otorgado, este se realiza en apego al control del gasto público.\n9. Criterios de selección y elegibilidad.\n9.1. Método de selección de beneficiarios (as).\nSerán beneficiados con el apoyo del programa salud y bienestar comunitario, las comunidades que cuenten con grupos de desarrollo comunitario constituidos, los cuales deberán presentar lo siguiente:\n1. Contar con el Acta Constitutiva de la conformación del GD, y\n2. Disponer de un Diagnóstico Participativo y de un Programa de Trabajo Comunitario, que determine las necesidades de la población, así como las acciones y proyectos para fomentar la salud y bienestar comunitario, elaborados y suscritos por las personas que integran el Grupo de Desarrollo.\n10. Mecánica de operación.\n10.1. Instancia ejecutora.\nDirección de Asistencia Alimentaria y Desarrollo Comunitario, en coordinación con los SMDIF, quien deberá\nFISCAL 2021 operar con apego a la programación, presupuestación, calendario de ejecución, ejercicio y control del gasto público.\n10.2. Instancia administrativa y/o normativas.\nLa Instancia Administrativa y Normativa Estatal es el DIF Guerrero, a través de la emisión de estas reglas de operación asimismo la Dirección de Asistencia Alimentaria y Desarrollo Comunitario, la Secretaría\nContraloría y Transparencia Gubernamental y la Auditoría Superior del Estado en el ámbito de sus respectivas competencias, quienes darán seguimiento a los objetivos y metas del Programa.\nPor otra parte, la instancia normativa federal es la que el SNDIF, a través de la DCADC es la instancia normativa federal, a través de la emisión de la Estrategia Integral Asistencia Social Alimentaria y\nDesarrollo Comunitario (EIASADC 2021).\n10.3. Delimitación de atribuciones.\nEl DIF Guerrero establecerá los mecanismos de coordinación necesarios para garantizar que sus programas y acciones no se contrapongan, afecten o presenten duplicidades con otros programas o acciones del gobierno estatal; la coordinación institucional y vinculación de acciones busca potenciar el impacto de los recursos, fortalecer la cobertura de las acciones, detonar la complementariedad y reducir gastos administrativos.\n11. Derechos, obligaciones y sanciones de los beneficiarios de programas sociales.\n11.1. Derechos.\n• Recibir trato digno, respetuoso y equitativo sin discriminación alguna, por el personal de las distintas áreas que participen dentro del programa.\n• Reserva y privacidad de la información personal.\n• Acceder a la información necesaria del programa, sus Reglas de Operación, recursos y cobertura.\n• Solicitar y recibir información sobre el estado que guarda su trámite.\n• Recibir los servicios y prestación del programa conforme a las Reglas de Operación, salvo que le sea suspendido el apoyo por alguna razón justificable.\n11.2. Obligaciones.\n• Proporcionar la información socioeconómica bajo protesta de decir verdad que les sea requerida por el DIF Guerrero, en los términos que establezca la normatividad correspondiente.\n• Utilizar los apoyos para los fines con que fueron autorizados evitando cualquier uso distinto de la misma.\n• Facilitar los trabajos de verificación, en cualquier momento después de otorgado el apoyo.\n11.3. Sanciones.\nFISCAL 2021 numerales 6.2 y 6.3 para acceder a los beneficios que a través de estos se otorgan, perderán las prerrogativas que dichas disposiciones establecen.\n12. Interpretación.\nLa interpretación de las presentes Reglas de Operación para efectos administrativos, estarán a cargo del DIF Guerrero, así como de la Secretaría de Contraloría y Transparencia Gubernamental, en el ámbito de sus respectivas competencias.\nANEXOS\nPROYECTO ANUAL DE SALUD Y BIENESTAR COMUNITARIO (PASBIC) 2021\nCONVENIO DE COLABORACIÓN PARA LA OPERACIÓN DEL PROGRAMA DE SALUD Y BIENESTAR\nCOMUNITARIO PARA EL EJERCICIO 2021 QUE CELEBRAN POR UNA PARTE, EL SISTEMA PARA EL\nDESARROLLO INTEGRAL DE LA FAMILIA DEL ESTADO DE GUERRERO, EN LO SUCESIVO “EL\nSEDIF”, REPRESENTADO POR SU DIRECTOR GENERAL EL LIC. JOSÉ FRANCISCO SOLÍS SOLÍS, Y\nPOR LA OTRA, EL SISTEMA PARA EL DESARROLLO INTEGRAL DE LA FAMILIA) DEL MUNICIPIO\nDE_____________________, EN LO SUCESIVO “EL H. AYUNTAMIENTO MUNICIPAL”,\nREPRESENTADO POR C. ______________________, A QUIENES CUANDO ACTÚEN DE MANERA\nCONJUNTA SE LES DENOMINARÁ “LAS PARTES”, DE CONFORMIDAD CON LAS SIGUIENTES\nDECLARACIONES Y CLÁUSULAS:\nQUE LA CONSTITUCIÓN POLÍTICA DE LOS ESTADOS UNIDOS MEXICANOS, EN SU ARTÍCULO\nCUARTO, ESTABLECE QUE TODA PERSONA TIENE DERECHO A LA ALIMENTACIÓN NUTRITIVA,\nSUFICIENTE Y DE CALIDAD.\nQUE EL FONDO DE APORTACIONES MÚLTIPLES COMPONENTE ASISTENCIA SOCIAL (FAM-AS)\nFORMA PARTE DE LAS APORTACIONES FEDERALES PARA ENTIDADES FEDERATIVAS Y\nMUNICIPIOS DEL RAMO GENERAL 33, QUE ES EL MECANISMO PRESUPUESTARIO DISEÑADO\nPARA TRANSFERIR A LOS ESTADOS Y MUNICIPIOS RECURSOS QUE LES PERMITAN\nRUBROS DE PROGRAMAS ALIMENTARIOS, DE ASISTENCIA SOCIAL E INFRAESTRUCTURA\nEDUCATIVA; Y QUE DICHO FONDO ESTÁ REGULADO POR LA LEY DE COORDINACIÓN FISCAL,\nPRESUPUESTO DE EGRESOS DE LA FEDERACIÓN 2021.\nESTABLECIDO EN EL ARTÍCULO 2 FRACCIÓN V DE LA LEY DE PLANEACIÓN, BUSCA LOGRAR UN\nDESARROLLO EQUILIBRADO DEL PAÍS, PROMOVIENDO LA DESCENTRALIZACIÓN DE LA VIDA\nNACIONAL.\nFISCAL 2021\nCOMUNITARIO (EIASADC) 2021 ESTABLECE EN SU APARTADO 5.1 QUE\nLOS SEDIF DEBEN CELEBRAR CONVENIOS DE COLABORACIÓN CON LOS SMDIF, EN EL MARCO\nDE LA OPERACIÓN DE LOS PROGRAMAS ALIMENTARIOS DERIVADOS DEL FAM-AS.\n1. “EL SEDIF” declara que:\n1.1 ES UN ORGANISMO PÚBLICO DESCENTRALIZADO DEL GOBIERNO DEL ESTADO DE\nGUERRERO, CON PERSONALIDAD JURÍDICA Y PATRIMONIO PROPIOS, CREADO POR LA LEY QUE\nCREA EL SISTEMA PARA EL DESARROLLO INTEGRAL DE LA FAMILIA NÚMERO 107, PUBLICADO\nEN EL PERIÓDICO OFICIAL DEL GOBIERNO DEL ESTADO DE GUERRERO, EL DÍA 9 DE MARZO DE\n1977, Y REGIDO POR LA LEY SOBRE EL SISTEMA ESTATAL DE ASISTENCIA SOCIAL NÚMERO 332,\nPUBLICADA EN EL PERIÓDICO OFICIAL DEL ESTADO DE GUERRERO, EL DÍA 15 DE JULIO DE 1986.\nI.2.- QUE DE ACUERDO A LO DISPUESTO EN LA FRACCIÓN VII, DEL ARTICULO 30 LA LEY SOBRE\nEL SISTEMA ESTATAL DE ASISTENCIA SOCIAL NÚMERO 332, EL DIRECTOR GENERAL DEL\nSISTEMA PARA EL DESARROLLO INTEGRAL DE LA FAMILIA DEL ESTADO DE GUERRERO, POSEE\nAMPLIAS FACULTADES PARA CELEBRAR CONVENIOS, CONTRATOS Y ACTOS JURÍDICOS QUE\nSEAN INDISPENSABLES PARA EL CUMPLIMIENTO DE LOS OBJETIVOS DEL ORGANISMO.\nI.3.- QUE ESTA LEGALMENTE REPRESENTADO POR EL C. LIC. JOSÉ FRANCISCO SOLÍS SOLÍS,\nQUIEN OSTENTA EL CARGO DE DIRECTOR GENERAL DEL SISTEMA PARA EL DESARROLLO\nINTEGRAL DE LA FAMILIA DEL ESTADO DE GUERRERO, PERSONALIDAD QUE ACREDITA CON EL\nNOMBRAMIENTO Y ACTA DE PROTESTA DE FECHA VEINTISIETE DE OCTUBRE DEL AÑO DOS MIL\nQUINCE, EXPEDIDO POR EL C. LIC. HÉCTOR ANTONIO ASTUDILLO FLORES, GOBERNADOR\nCONSTITUCIONAL DEL ESTADO DE GUERRERO.\nI.4.- QUE EL ORGANISMO QUE REPRESENTA TIENE COMO OBJETIVOS ENTRE OTROS, LOS\nSIGUIENTES:\nA). - PROMOVER Y PRESTAR SERVICIOS DE ASISTENCIA SOCIAL.\nB). - APOYAR EL DESARROLLO DE LA FAMILIA Y LA COMUNIDAD.\nC). -REALIZAR ACCIONES DE APOYO EDUCATIVO, PARA LA INTEGRACIÓN SOCIAL Y DE\nCAPACITACIÓN PARA EL TRABAJO A LOS SUJETOS DE LA ASISTENCIA SOCIAL.\nD). -PROMOVER E IMPULSAR EL SANO CRECIMIENTO FÍSICO, MENTAL Y SOCIAL DE LA\nNIÑEZ.\nFISCAL 2021\nE). -FOMENTAR, APOYAR, COORDINAR Y EVALUAR LAS ACTIVIDADES QUE LLEVEN A\nSOCIAL, SIN PERJUICIO DE LAS ATRIBUCIONES QUE AL EFECTO CORRESPONDAN A OTRAS\nDEPENDENCIAS.\n1.5.- QUE EN EL EJERCICIO DE SUS FUNCIONES Y ATRIBUCIONES CUENTA CON LAS\nFACULTADES NECESARIAS PARA SUSCRIBIR EL PRESENTE CONVENIO DE CONFORMIDAD CON\nLO ESTABLECIDO EN EL ARTICULO 30 FRACCIÓN VII, DE LA LEY SOBRE EL SISTEMA ESTATAL DE\nASISTENCIA SOCIAL. NUMERO 332, POR LO QUE PUEDE CELEBRAR LOS CONVENIOS,\nCONTRATOS Y ACTOS JURÍDICOS QUE SEAN INDISPENSABLES PARA EL CUMPLIMIENTO DE LOS\nOBJETIVOS DEL ORGANISMO.\n1.6- QUE SU DOMICILIO LEGAL PARA LOS EFECTOS DEL PRESENTE CONVENIO ES EL UBICADO\nEN LA CALLE DE GABRIEL LEYVA ESQUINA CON RUFFO FIGUEROA SIN NÚMERO, COLONIA\nBURÓCRATAS, CÓDIGO POSTAL 39090, EN ESTA CIUDAD DE CHILPANCINGO DE LOS BRAVO,\nGUERRERO.\nII.- DECLARA “EL H. AYUNTAMIENTO”:\nII.1.- QUE ES UN ÓRGANO DE GOBIERNO MUNICIPAL, EN EL CUAL SE REALIZAN ACCIONES DE\nGOBIERNO Y ADMINISTRACIÓN EN LOS LIMITES DEL MISMO; DE CONFORMIDAD CON LAS\nCOMPETENCIAS LEGALES, TENIENDO COMO PRINCIPAL RESPONSABILIDAD, PLANTEAR,\nCONDUCIR, COORDINAR, ORIENTAR ACCIONES, INVERSIONES, REGULAR Y FOMENTAR LAS\nACTIVIDADES QUE DEMANDA EL INTERÉS PUBLICO, CON EL FIN DE OBTENER UNA MEJORÍA\nPERMANENTE, EN LA CALIDAD DE VIDA DE LA POBLACIÓN QUE SE GOBIERNA Y UN DESARROLLO\nINTEGRAL Y EQUILIBRADO EN EL MUNICIPIO.\nII.2.- QUE DE CONFORMIDAD CON LOS ARTÍCULOS 115 DE LA CONSTITUCIÓN POLÍTICA DE LOS\nESTADOS UNIDOS MEXICANOS; 27, 170, 171, 172, 178 Y 179 DE LA CONSTITUCIÓN POLÍTICA DEL\nDEMÁS ARTÍCULOS APLICABLES DE LA LEY ORGÁNICA DEL MUNICIPIO LIBRE DEL ESTADO DE\nGUERRERO; ES DE SU INTERÉS CELEBRAR EL PRESENTE CONVENIO CON EL SISTEMA PARA EL\nDESARROLLO INTEGRAL DE LA FAMILIA DEL ESTADO DE GUERRERO.\nII.3.- EL C.____________________ EN SU CALIDAD DE PRESIDENTE MUNICIPAL CONSTITUCIONAL\nDEL MUNICIPIO DE _______________ GUERRERO, PERSONALIDAD QUE ACREDITAN CON LA\nCONSTANCIA DE MAYORÍA Y VALIDEZ, EXPEDIDO POR EL INSTITUTO ELECTORAL Y DE ESTADO\nDE GUERRERO, POR EL ____ CONSEJO DISTRITAL ELECTORAL, CON CABECERA EN __________,\nGUERRERO. EN CUMPLIMIENTO A LA RESOLUCIÓN TOMADA EN SESIÓN, DE FECHA 05 DE JUNIO\nDE _____.\nII.4.-QUE PARA LOS EFECTOS LEGALES DEL PRESENTE CONVENIO, SE SEÑALA COMO DOMICILIO\nLEGAL EN CALLE ___________________, C.P. ______, ____________, GUERRERO.\nFISCAL 2021\nIII.- DECLARAN “LAS PARTES”:\nIII.1.- QUE TIENEN EL ESPECIAL INTERÉS, EN LA FORMALIZACIÓN DEL PRESENTE CONVENIO DE\nCOLABORACIÓN, CON EL PROPÓSITO DE CONJUNTAR ACCIONES, PARA LA EJECUCION DEL\nPROGRAMA DE SALUD Y BIENESTAR COMUNITARIO 2021, EN APOYO A LA POBLACION\nCATALOGADA EN EL RANGO DE POBREZA EXTREMA.\nIII.2.- EL OBJETIVO GENERAL DEL PASBIC-2021 ES: PROMOVER LA ORGANIZACIÓN COMUNITARIA\nDESARROLLANDO CONOCIMIENTOS Y HABILIDADES TANTO DE LIDERAZGO COMO GESTORIA\nSOCIAL QUE COADYUVEN EN LA SOLUCION DEL REZAGO Y LA PROBLEMÁTICA LOCAL,\nMEDIANTE EL IMPULSO DE PROYECTOS COMUNITARIOS DE ACUERDO A LOS 7 COMPONENTES\nDE ATENCION COMO SON:\n➢ AUTOCUIDADO. ACCIONES ENCAMINADAS A PROPICIAR QUE LAS FAMILIAS DE LAS\nCOMUNIDADES ADQUIERAN CONOCIMIENTOS DE MEDICINA ALTERNATIVA Y\nACCESO DE ALIMENTOS SALUDABLES, Y PARA MEJORAR LA SALUD Y BIENESTAR\nCOMUNITARIO.\n➢ RECREACION Y MANEJO DEL TIEMPO LIBRE.ACCIONES ENFOCADAS A LA\nCONVIVENCIA COMUNITARIA PARA CONTRIBUIR AL BIENESTAR INDIVIDUAL,\nFAMILIAR Y COMUNITARIO, ENCAMINADAS A LAS ACTIVIDADES FISICAS,\nRECREATIVA, ASI COMO LA REHABILITACION DE ESPACIOS DEPORTIVOS, TEATRO,\nPARQUES RÚSTICOS.\n➢ GESTION INTEGRAL DE RIESGO. ACCIONES QUE PROMUEVAN PROYECTOS\nSOCIALES DONDE INCLUYAN CAPACITACIONES ENFOCADAS A PREVENIR Y COMO\nACTUAR DURANTE Y DESPUÉS DE LA CONTINGENCIA.\n➢ ESPACIOS HABITABLES SUSTENTABLES. ACCIONES QUE PROMUEVAN LA\nINFRAESTRUCTURA PARA LA CONSTRUCCION DE VIVIENDAS QUE AYUDEN AL\nCUIDADO DEL MEDIO AMBIENTE.\n➢ ALIMENTACION CORRECTA Y LOCAL. ACCIONES DIRIGIDAS A LA IMPLEMENTACION\nALIMENTICIOS.\n➢ ECONOMIA SOLIDARIA. FORTALECER ACCIONES QUE PROMUEVAN PROYECTOS\nPRODUCTIVOS PARA LA CONSTRUCCION DE HUERTOS INTEGRALES, GRANJA DE\nTRASPATIO, GRUPALES O COMUNITARIOS.\n➢ SUSTENTABILIDAD. ACCIONES QUE PROMUEVAN PROYECTOS SOCIALES\nSUSTENTABILIDAD, CREANDO CONCIENCIA EN UNA CONDUCTA: NO TIRAR\nBASURA, CUIDAR EL AGUA, CUIDAR EL AIRE, LOS ANIMALES, LAS PLANTAS.\nFISCAL 2021\nIII.3.- QUE SE RECONOCEN MUTUAMENTE, LA PERSONALIDAD Y CAPACIDAD CON QUE SE\nOSTENTAN, ASÍ COMO LA ESTRUCTURA Y OBJETIVOS DE LA PARTE CON LA QUE CONVIENEN.\nCONFORME A LO EXPUESTO EN LAS ANTERIORES DECLARACIONES, ACUERDAN EN CELEBRAR\nESTE CONVENIO AL TENOR DE LAS SIGUIENTES:\nPRIMERA.- OBJETO\nPRIMERA:\nEL PRESENTE CONVENIO TIENE POR OBJETO ESTABLECER LAS BASES DE COLABORACIÓN\nENTRE “EL SEDIF” Y “EL SMDIF” PARA COORDINAR LA OPERACIÓN DEL PROGRAMA DE SALUD Y\nBIENESTAR COMUNITARIO, EN ADELANTE DENOMINADO “EL PROGRAMA”, CON BASE EN EL\nRECURSO ASIGNADO A LA ENTIDAD FEDERATIVA DEL RAMO GENERAL 33, FONDO DE\nAPORTACIONES MÚLTIPLES COMPONENTE ASISTENCIA SOCIAL PARA EL EJERCICIO FISCAL\n2021.\nSEGUNDA.OBJETIVO Y POBLACIÓN OBJETIVO DEL PROGRAMA\nFORTALECER LOS DETERMINANTES SOCIALES DE LA SALUD Y EL BIENESTAR COMUNITARIO EN\nLOCALIDADES DE ALTA Y MUY ALTA MARGINACIÓN, MEDIANTE LA IMPLEMENTACIÓN DE\nPROYECTOS COMUNITARIOS Y EL DESARROLLO DE CAPACIDADES INDIVIDUALES Y\nCOLECTIVAS QUE PERMITAN MEJORAR LOS ESTILOS DE VIDA SALUDABLE.\nOBJETIVOS ESPECÍFICOS\nIMPLEMENTAR PROYECTOS COMUNITARIOS EN LOCALIDADES DE ALTA Y MUY ALTA\nMARGINACIÓN CON GRUPOS DE DESARROLLO CONSTITUIDOS PARA FOMENTAR LA SALUD Y EL\nBIENESTAR COMUNITARIO.\nDESARROLLAR CONOCIMIENTOS, HABILIDADES Y COMPETENCIAS EN LAS PERSONAS QUE\nCONSTITUIDOS, EN MATERIA DE LOS DETERMINANTES SOCIALES DE LA SALUD, A TRAVÉS DE\nCAPACITACIONES.\nPOBLACIÓN OBJETIVO\nLOCALIDADES DE ALTA Y MUY ALTA MARGINACIÓN, DE ACUERDO CON LA PUBLICACIÓN OFICIAL\n“ÍNDICE DE MARGINACIÓN POR LOCALIDAD 2010” DEL CONSEJO NACIONAL DE POBLACIÓN\n(CONAPO), CON GD CONSTITUIDOS.\nFISCAL 2021\nTERCERA.- CONFORMACIÓN DE LOS APOYOS.\nLOS APOYOS OTORGADOS POR “EL PROGRAMA DE SALUD Y BIENESTAR COMUNITARIO”\nCONSISTEN EN CAPACITACIONES E INSUMOS PARA PROYECTOS COMUNITARIOS,\nENMARCADOS EN LOS COMPONENTES DE LOS DETERMINANTES DE LA SALUD, DE ACUERDO\nCON EL RECURSO ANUAL DEL PROGRAMA Y CON LOS RESULTADOS DE LOS CRITERIOS Y LAS\nACTIVIDADES DE FOCALIZACIÓN, QUE CONTEMPLAN LA ATENCIÓN A LA POBLACIÓN QUE HABITE\nEN LOCALIDADES Y AGEB RURALES Y URBANAS CONSIDERADAS DE ALTA Y MUY ALTA\nMARGINACIÓN, DE ACUERDO CON LOS ÍNDICES DEL CONSEJO NACIONAL DE POBLACIÓN.\nCUARTA.- NATURALEZA DE LOS RECURSOS.\nLOS RECURSOS CON LOS QUE OPERA “EL PROGRAMA” CORRESPONDEN A APORTACIONES\nFEDERALES ESTABLECIDAS EN EL PRESUPUESTO DE EGRESOS DE LA FEDERACIÓN, POR LO\nQUE SU FISCALIZACIÓN Y CONTROL SERÁ REALIZADA POR LA AUDITORÍA SUPERIOR DE LA\nFEDERACIÓN Y POR LA 42 PERIÓDICO OFICIAL DEL ESTADO DE GUERRERO SECRETARÍA DE LA\nFUNCIÓN PÚBLICA. EN ESE SENTIDO, “LAS PARTES” SE OBLIGAN A:\nA) “EL AYUNTAMIENTO” DESARROLLARÁ LOS SISTEMAS DE CONTROL INTERNO QUE SEAN\nNECESARIOS A EFECTOS DE ASEGURAR QUE LOS PROGRAMAS SEAN EJECUTADOS CON\nOPORTUNIDAD, ECONOMÍA, PRODUCTIVIDAD, LEGALIDAD, HONESTIDAD Y TRANSPARENCIA.\nB) “EL SEDIF”, POR CONDUCTO SU PERSONAL OPERATIVO, PRACTICARÁ LAS VISITAS DE\nSUPERVISIÓN Y EVALUACIONES QUE ESTIME PERTINENTES.\nQUINTA.- COMPROMISOS DE “EL SEDIF”\n“EL SEDIF”, DE ACUERDO CON EL APARTADO 2.2 RESPONSABILIDADES DE LOS SISTEMAS\nESTATALES DIF DE LA EIASADC 2021, SE COMPROMETE DE MANERA ENUNCIATIVA Y NO\nLIMITATIVA A LO SIGUIENTE PARA LA APLICACIÓN DEL PRESENTE INSTRUMENTO.\nI. SUPERVISAR CONSTANTEMENTE LAS LOCALIDADES QUE HAYAN SIDO BENEFICIADAS CON EL\nPSBC, LLEVANDO UN REPORTE DE LA VISITA CON EVIDENCIA FOTOGRÁFICA;\nII. PARTICIPAR EN LAS CAPACITACIONES QUE EL SNDIF OTORGUE PARA LA MEJORA DE LA\nIMPLEMENTACIÓN DEL PSBC;\nIII. DETERMINAR LA COBERTURA DE ATENCIÓN PARA EL 2021, SIEMPRE QUE EL TERRITORIO DE\n\"ÍNDICE DE MARGINACIÓN A NIVEL LOCALIDAD 2010\" DEL CONAPO;\nIV. DAR A CONOCER EL PROGRAMA DE SALUD Y BIENESTAR COMUNITARIO Y OTORGAR\nCAPACITACIÓN SOBRE EL PSBC A LOS SMDIF;\nFISCAL 2021\nINTERESADA EN LAS TEMÁTICAS PROPUESTAS POR EL PSBC;\nVI. OTORGAR LA ORIENTACIÓN ALIMENTARIA QUE REQUIEREN LOS GD POR PARTE DEL ÁREA\nALIMENTARIA DEL SEDIF;\nVII. GARANTIZAR LA EXISTENCIA DE PROMOTORÍA (ESTATAL Y/O MUNICIPAL) PARA EL\nACOMPAÑAMIENTO Y SEGUIMIENTO DE LOS GD;\nVIII. DAR SEGUIMIENTO Y ACOMPAÑAMIENTO EN LOS PROCESOS DE CAPACITACIÓN E\nIMPLEMENTACIÓN DE LA EAIC PROGRAMADOS EN SU PASBIC;\nIX. GARANTIZAR QUE LAS PERSONAS CAPACITADORAS CUENTEN CON EL PERFIL Y\nEXPERIENCIA REQUERIDA PARA EL CASO, RECONOCIDA Y AVALADA POR LAS INSTITUCIONES\nCOMPETENTES.\nX. LOS PROYECTOS COMUNITARIOS PARA LA REHABILITACIÓN Y/O REQUIPAMIENTO DE\nESPACIOS ALIMENTARIOS, PODRÁN IMPLEMENTARSE EN LAS LOCALIDADES DE ALTO Y MUY\nALTO GRADO DE MARGINACIÓN, BUSCANDO EL DESARROLLO DE MANERA COORDINADA CON\nEL ÁREA ALIMENTARIA A FIN DE FORTALECER UNA ALIMENTACIÓN CORRECTA Y LOCAL.\nXI. APLICAR EL \"CUESTIONARIO DE SATISFACCIÓN DE LOS APOYOS OTORGADOS\" DE MANERA\nCOLECTIVA AL GD DURANTE EL SEGUNDO SEMESTRE DEL AÑO Y ENVIAR UN REPORTE\nSISTEMATIZADO DE LOS RESULTADOS AL SNDIF ANTES DEL TÉRMINO DEL AÑO;\nSEXTA.- COMPROMISOS DE “EL AYUNTAMIENTO/SMDIF”\n“EL AYUNTAMIENTO / SMDIF”, DE ACUERDO CON EL APARTADO 2.3 RESPONSABILIDADES DE\nLOS SISTEMAS MUNICIPALES DIF DE LA EIASADC 2021, SE COMPROMETE A LO SIGUIENTE PARA\nLA APLICACIÓN DEL PRESENTE INSTRUMENTO:\nI. PARTICIPAR DE FORMA CONJUNTA CON “EL SEDIF” EN EL ESTABLECIMIENTO DE\nMECANISMOS Y ESTRATEGIAS A SEGUIR PARA LA DETECCIÓN, SELECCIÓN, FOCALIZACIÓN Y\nATENCIÓN DE BENEFICIARIOS.\nII. PROMOVER Y COORDINAR LA PARTICIPACIÓN COMUNITARIA EN LA OPERACIÓN DE “EL\nPROGRAMA”, A TRAVÉS DE LA FORMACIÓN DE COMITÉS Y/O GRUPOS DE DESARROLLO SEGÚN\nCORRESPONDA.\nII. IMPLEMENTAR ACCIONES DE ORIENTACIÓN Y EDUCACIÓN ALIMENTARIA, ASEGURAMIENTO\nDE LA CALIDAD, ASÍ COMO DE ORGANIZACIÓN Y PARTICIPACIÓN COMUNITARIA.\nIV. PARTICIPAR, EN COORDINACIÓN CON “EL SEDIF”, EN LA ADQUISICIÓN DE ALIMENTOS\nFRESCOS PARA COMPLEMENTAR LOS MENÚS Y DOTACIONES.\nFISCAL 2021\nV. OPERAR “EL PROGRAMA”, CON OBSERVANCIA Y APEGO A LAS REGLAS DE OPERACIÓN\nEMITIDAS POR “EL SEDIF” Y LO ESTABLECIDO EN EL PRESENTE CONVENIO DE COLABORACIÓN.\nVI. GENERAR LOS INFORMES CORRESPONDIENTES SOBRE LA OPERACIÓN DE “EL PROGRAMA”.\nVIII. DIFUNDIR LA EXISTENCIA DE “EL PROGRAMA”, PREFERENTEMENTE EN LAS LOCALIDADES\nDE ALTO Y MUY ALTO GRADO DE MARGINACIÓN.\nSÉPTIMA.- DIFUSIÓN Y DIVULGACIÓN\n\"LAS PARTES\" SE COMPROMETEN A QUE LA DIFUSIÓN Y DIVULGACIÓN QUE SE REALICE POR\nMEDIOS IMPRESOS ELECTRÓNICOS, ESCRITOS, GRÁFICOS Y DE CUALQUIER OTRA ÍNDOLE\nINHERENTE A “EL PROGRAMA”, ASÍ COMO EN EL ETIQUETADO DE LOS INSUMOS, DEBERÁ\nENUNCIAR LA SIGUIENTE LEYENDA:\n\"ESTE PROGRAMA ES PÚBLICO, AJENO A CUALQUIER PARTIDO POLÍTICO. QUEDA PROHIBIDO EL\nUSO PARA FINES DISTINTOS A LOS ESTABLECIDOS EN EL PROGRAMA.\"\nASIMISMO, CUMPLIRÁN CON LO ESTABLECIDO EN EL APARTADO 3.1 IMAGEN GRÁFICA Y\nDIFUSIÓN DE LA EIASADC 2021 Y SEÑALARÁN EXPRESAMENTE Y EN FORMA IDÉNTICA LA\nPARTICIPACIÓN DEL \"EL SEDIF\" Y EL APOYO DEL GOBIERNO FEDERAL, A TRAVÉS DEL SISTEMA\nNACIONAL PARA EL DESARROLLO INTEGRAL DE LA FAMILIA.\nOCTAVA.- REPRESENTANTES DE LAS PARTES\nPARA LA ADECUADA OPERACIÓN DE LAS ACTIVIDADES A QUE SE REFIERE EL PRESENTE\nINSTRUMENTO JURÍDICO, \"LAS PARTES\" DESIGNAN COMO SUS RESPECTIVOS\nREPRESENTANTES A LOS SIGUIENTES FUNCIONARIOS/AS:\nA) POR \"EL SEDIF\" (EL JEFE DEL DEPARTAMENTO DE FORMACION Y PROMOCION\nCOMUNITARIA),\nB) POR \"EL AYUNTAMIENTO / SMDIF\" (DIRECTORA DEL SMDIF),\nNOVENA. CONTROL Y VIGILANCIA\nCONVENIO CORRESPONDERÁ A LOS ÓRGANOS FISCALIZADORES ESTATALES COMPETENTES,\nPÚBLICA.\nDÉCIMA. TRANSPARENCIA\n\"LAS PARTES\" CONVIENEN EN PROMOVER Y FOMENTAR LA TRANSPARENCIA DE LA\nASIGNACIÓN Y EJERCICIO DE LOS RECURSOS A QUE SE REFIERE EL PRESENTE CONVENIO.\nFISCAL 2021\nCONSECUENTEMENTE, DEBERÁN LLEVAR A CABO LA INTEGRACIÓN DEL PADRÓN DE\nPERSONAS BENEFICIARIAS, ASIMISMO, “LAS PARTES” DARÁN CUMPLIMIENTO A LO\nESTABLECIDO EN EL ARTÍCULO 40 DE LA LEY DE COORDINACIÓN FISCAL, QUE A LA LETRA DICE:\nLAS ENTIDADES TENDRÁN LA OBLIGACIÓN DE HACER DEL CONOCIMIENTO DE SUS HABITANTES,\nLOS MONTOS QUE RECIBAN, LAS OBRAS Y ACCIONES REALIZADAS, EL COSTO DE CADA UNA,\nSU UBICACIÓN Y BENEFICIARIOS. ASIMISMO, DEBERÁN INFORMAR A SUS HABITANTES, AL\nTÉRMINO DE CADA EJERCICIO, SOBRE LOS RESULTADOS ALCANZADOS.\nDÉCIMO PRIMERA.- RELACIÓN LABORAL\nEL PERSONAL DE CADA UNA DE \"LAS PARTES\" QUE SEA DESIGNADO PARA LA REALIZACIÓN DE\nCUALQUIER ACTIVIDAD RELACIONADA CON ESTE CONVENIO, PERMANECERÁ EN FORMA\nABSOLUTA BAJO LA DIRECCIÓN Y DEPENDENCIA DE LA PARTE CON LA CUAL TIENE\nESTABLECIDA SU RELACIÓN LABORAL, MERCANTIL, CIVIL, ADMINISTRATIVA O CUALQUIER\nOTRA, POR LO QUE NO SE CREARÁ UNA SUBORDINACIÓN DE NINGUNA ESPECIE CON LA PARTE\nOPUESTA, NI OPERARÁ LA FIGURA JURÍDICA DE PATRÓN SUSTITUTO O SOLIDARIO; LO\nANTERIOR, CON INDEPENDENCIA DE ESTAR PRESTANDO SUS SERVICIOS FUERA DE LAS\nINSTALACIONES DE LA ENTIDAD POR LA QUE FUE CONTRATADA O REALIZAR LABORES DE\nSUPERVISIÓN DE LOS TRABAJOS QUE SE REALICEN.\nDÉCIMO SEGUNDA.- MODIFICACIONES\nEL PRESENTE CONVENIO PODRÁ SER MODIFICADO DURANTE SU VIGENCIA, PREVIO ACUERDO\nDE “LAS PARTES”. LAS MODIFICACIONES O ADICIONES SE HARÁN CONSTAR POR ESCRITO,\nSURTIENDO SUS EFECTOS A PARTIR DEL MOMENTO DE SU SUSCRIPCIÓN.\nDÉCIMO TERCERA.- VIGENCIA\nEL PRESENTE CONVENIO TENDRÁ VIGENCIA A PARTIR DE LA FECHA DE SU FIRMA Y HASTA EL\n31 DE DICIEMBRE DE 2021.\nEL INSTRUMENTO PODRÁ DARSE POR TERMINADO CUANDO ASÍ LO DETERMINEN “LAS PARTES”\nESCRITO, CON TREINTA DÍAS NATURALES DE ANTICIPACIÓN, EN EL ENTENDIDO DE QUE LAS 46\nEJECUCIÓN DEBERÁN SER CONCLUIDAS, SALVO ACUERDO EN CONTRARIO.\nDÉCIMO CUARTO.- DE LA ADQUISICIÓN Y DISTRIBUCIÓN DE LOS APOYOS\nFONDO DE APORTACIONES MÚLTIPLES, LA DISTRIBUCIÓN DEL RECURSO DEL RAMO 33, EN SU\nVERTIENTE DE ASISTENCIA SOCIAL (FONDO V.i.).\nDECIMO QUINTO.- DE LOS MECANISMOS DE ENTREGA DE LOS APOYOS\nFISCAL 2021\nCOMUNIDADES QUE SE ENCUENTRAN EN LA COBERTURA 2021, CON UN GRADO DE\nMARGINACIÓN ALTO Y MUY ALTO DE ACUERDO A LA INFORMACIÓN DE CONAPO 2010.\nDÉCIMO SEXTO.- DE LAS SANCIONES\n“LAS PARTES” ACUERDAN QUE EN CASO DE SUSCITARSE ALGÚN CONFLICTO O\nCONTROVERSIA LO RESOLVERÁN DE ACUERDO CON LA CLÁUSULA VIGÉSIMA DEL PRESENTE\nCONVENIO.\nADEMÁS DE LO ESTABLECIDO EN EL PÁRRAFO ANTERIOR, “LAS PARTES” TENDRÁN LA\nRESPONSABILIDAD DE HACER DEL CONOCIMIENTO DE LAS AUTORIDADES COMPETENTES,\nCUALQUIER FALTA ADMINISTRATIVA, ACTO DE CORRUPCIÓN O COMISIÓN DE DELITO ALGUNO,\nPOR PARTE DE CUALQUIERA DE LOS SERVIDORES PÚBLICOS RELACIONADOS CON LA\nOPERACIÓN DEL PROGRAMA.\nDÉCIMO SÉPTIMO.- CONFIDENCIALIDAD\n\"LAS PARTES\" GUARDARÁN CONFIDENCIALIDAD ESTRICTA RESPECTO DE LA INFORMACIÓN\nCLASIFICADA COMO CONFIDENCIAL O RESERVADA, EN TÉRMINOS DE LA LEY GENERAL DE\nTRANSPARENCIA Y ACCESO A LA INFORMACIÓN PÚBLICA, LA LEY FEDERAL DE TRASPARENCIA\nY ACCESO A LA INFORMACIÓN PÚBLICA, LA LEY GENERAL DE PROTECCIÓN DE DATOS\nPERSONALES EN POSESIÓN DE SUJETOS OBLIGADOS Y DEMÁS DISPOSICIONES APLICABLES A\nLA MATERIA, SALVO QUE SE CUENTE CON LA PREVIA AUTORIZACIÓN ESCRITA DE QUIEN SEA\nRESPONSABLE DE DICHA INFORMACIÓN, DEBIENDO ASEGURARSE QUE LA QUE SE\nPROPORCIONE POR EL PERSONAL QUE CADA UNA DESIGNE SEA MANEJADA BAJO ESTRICTA\nCONFIDENCIALIDAD.\nLAS OBLIGACIONES CONTEMPLADAS EN EL PÁRRAFO ANTERIOR, PERMANECERÁN VIGENTES Y\nSERÁN EXIGIBLES EN EL SUPUESTO DE QUE \"LAS PARTES\" DIERAN POR TERMINADO EL\nPRESENTE INSTRUMENTO JURÍDICO.\nDÉCIMO OCTAVO.- PUBLICIDAD DE LOS RESULTADOS\n\"LAS PARTES\", POR LOS MEDIOS DE DIFUSIÓN MÁS CONVENIENTES, PROMOVERÁN Y\nDIVULGARÁN ENTRE LAS PERSONAS PROMOTORAS, EJECUTORAS E INTERESADAS EN\nGENERAL, LAS CARACTERÍSTICAS, ALCANCES Y RESULTADOS DE LA COLABORACIÓN PREVISTA\nEN EL PRESENTE CONVENIO, DE ACUERDO CON LA CLÁUSULA DÉCIMA “TRANSPARENCIA” DE\nESTE INSTRUMENTO.\nDÉCIMO NOVENO.- COMPETENCIA\nINTERPRETACIÓN O CUMPLIMIENTO DEL PRESENTE CONVENIO, \"LAS PARTES\" LO RESOLVERÁN\nDE COMÚN ACUERDO, DE NO LOGRARLO, ACUERDAN SOMETERSE EXPRESAMENTE A LA\nFISCAL 2021\nCOMPETENCIA DE LOS TRIBUNALES RADICADOS EN GUERRERO, RENUNCIANDO DESDE ESTE\nPRESENTE O FUTURO, O POR CUALQUIER OTRA CAUSA.\nENTERADAS “LAS PARTES” DEL CONTENIDO Y ALCANCE LEGAL DEL CONVENIO, LO FIRMAN EN\nEL ESTADO DE GUERRERO, A LOS 25 DÍAS DEL MES DE _________________ DE DOS MIL\nVEINTIUNO.\nPOR EL SISTEMA ESTATAL PARA EL AYUNTAMIENTO/SISTEMA\nDESARROLLO INTEGRAL DE LA FAMILIA.\nLIC. JOSE FRANCISCO SOLIS SOLIS.\nDIRECTOR GENERAL.\nDIRECTOR GENERAL. PRESIDENTE MUNICIPAL.\nLC. LUCIO ENRIQUE COTERO GARCIA.\nDIRECTOR DE ALIMENTACIÓN Y DIRECTOR DEL SISTEMA MUNICIPAL DIF.\nDESARROLLO COMUNITARIO.\nPrimero: El presente acuerdo entrará en vigor al día siguiente de su publicación en el Periódico\nOficial del Gobierno del Estado de Guerrero.\nSegundo: A partir de la entrada en vigor del presente acuerdo las Reglas de Operación del\nPrograma Salud y Bienestar Comunitario, subsecuentes o sus modificaciones serán emitidas por el titular del Sistema para el Desarrollo Integral de la Familia, responsable directo de la operación y ejecución de estas.\nDado en la Oficina del Titular del Sistema para el Desarrollo Integral de la Familia, ubicada en las\nInstalaciones del Centro de Rehabilitación Guerrero, Boulevard René Juárez Cisneros S/N, Ciudad de los\nServicios, en la Ciudad de Chilpancingo de los Bravo, Capital del Estado de Guerrero, a los 18 días del mes de enero de dos mil veintiuno.\nEL GOBERNADOR CONSTITUCIONAL DEL ESTADO DE GUERRERO.\nLIC. HÉCTOR ANTONIO ASTUDILLO FLORES.\nEL SECRETARIO GENERAL DE GOBIERNO.\nLIC. FLORENCIO SALAZAR ADAME.\nFISCAL 2021\nESTADO\nLIC. JOSÉ FRANCISCO SOLIS SOLIS.",
  "ordenamiento": "PROGRAMA",
  "jurisdiccion": "GUERRERO",
  "fuente_oficial": "DIARIO OFICIAL DE LA FEDERACION",
  "Fecha de Publicación": "12 DE JULIO DE 2022",
  "ULTIMA REFORMA PUBLICADA": null,
  "status": "VIGENTE",
  "es_escaneado": false,
  "tiene_tablas": true,
  "materia": [
    "salud",
    "desarrollo social"
  ]
}